{
  "type": "Feature",
  "properties": {
    "addr:full":"Estda. Pazos-reboreda, 3 Santo Paio De Abaixo Pontevedra 36818",
    "addr:housenumber":"3",
    "addr:postcode":"36818",
    "addr:street":"Pazos-Reboreda",
    "iso:country":"ES",
    "sg:address":"Estda. Pazos-reboreda, 3",
    "sg:city":"Santo Paio De Abaixo",
    "sg:orig_category":"Quincaller\u00cda (al Por Menor)",
    "sg:phone":"+34 986 40 00 18",
    "sg:postcode":"36818",
    "sg:province":"Pontevedra",
    "wof:name":"Barciela Testa Antonio",
    "wof:placetype":"venue"
},
  "geometry": {"coordinates":[-8.609254837,42.3069534302],"type":"Point"}
}