{
  "type": "Feature",
  "properties": {
    "addr:full":"Calle de Extramuros, 74 Piedrahita \u00c1vila 05500",
    "addr:housenumber":"74",
    "addr:postcode":"05500",
    "addr:street":"Calle De Extramuros",
    "iso:country":"ES",
    "sg:address":"Calle de Extramuros, 74",
    "sg:city":"Piedrahita",
    "sg:orig_category":"Venta, Instalaci\u00d3n De Cocinas",
    "sg:phone":"+34 920 36 03 65",
    "sg:postcode":"05500",
    "sg:province":"\u00c1vila",
    "wof:name":"Martin Rodriguez Santos",
    "wof:placetype":"venue"
},
  "geometry": {"coordinates":[-5.3286790848,40.4635505676],"type":"Point"}
}