{
  "type": "Feature",
  "properties": {
    "addr:full":"Rbla Marina, 301 Hospitalet Llobregat Barcelona 08907",
    "addr:housenumber":"301",
    "addr:postcode":"08907",
    "addr:street":"Rbla Marina",
    "iso:country":"ES",
    "sg:address":"Rbla Marina, 301",
    "sg:city":"Hospitalet Llobregat",
    "sg:orig_category":"Peluquer\u00cdas, Peluquer\u00cda Mixta",
    "sg:phone":"+34 932 63 00 76",
    "sg:postcode":"08907",
    "sg:province":"Barcelona",
    "wof:name":"Aranda Tejera Dolores",
    "wof:placetype":"venue"
},
  "geometry": {"coordinates":[2.1081280708,41.3520126343],"type":"Point"}
}