{
  "type": "Feature",
  "properties": {
    "addr:full":"Calle de Lucas Cortes, 2 Sevilla Sevilla 41010",
    "addr:housenumber":"2",
    "addr:postcode":"41010",
    "addr:street":"Calle De Lucas Cortes",
    "iso:country":"ES",
    "sg:address":"Calle de Lucas Cortes, 2",
    "sg:city":"Sevilla",
    "sg:orig_category":"Estancos",
    "sg:phone":"+34 954 34 41 58",
    "sg:postcode":"41010",
    "sg:province":"Sevilla",
    "wof:name":"Gonzalez-valdes Burgos Pedro Jesus",
    "wof:placetype":"venue"
},
  "geometry": {"coordinates":[-6.0087189674,37.3793563843],"type":"Point"}
}