{
  "type": "Feature",
  "properties": {
    "iso:country":"ES",
    "sg:address":"Calle de Malaga, 1",
    "sg:city":"Cordoba",
    "sg:orig_category":"Centros De Coordinaci\u00d3n",
    "sg:phone":"+34 957 47 01 49",
    "sg:postcode":"14003",
    "sg:province":"C\u00f3rdoba",
    "wof:name":"Asesoria Guillon S.l.",
    "wof:placetype":"venue"
},
  "geometry": {"coordinates":[-4.7801418304,37.8841781616],"type":"Point"}
}