{
  "type": "Feature",
  "properties": {
    "addr:full":"Calle de Santa Maria, 29 Gijon Asturias 33208",
    "addr:housenumber":"29",
    "addr:postcode":"33208",
    "addr:street":"Calle De Santa Maria",
    "iso:country":"ES",
    "sg:address":"Calle de Santa Maria, 29",
    "sg:city":"Gijon",
    "sg:orig_category":"Promotores Constructores",
    "sg:phone":"+34 985 38 20 82",
    "sg:postcode":"33208",
    "sg:province":"Asturias",
    "wof:name":"Iglesias Lopez Marcial",
    "wof:placetype":"venue"
},
  "geometry": {"coordinates":[-5.665143013,43.5322608948],"type":"Point"}
}