{
  "type": "Feature",
  "properties": {
    "addr:full":"Carr Santa Catalina Thomas, 24 Lloseta Islas Baleares 07360",
    "addr:housenumber":"24",
    "addr:postcode":"07360",
    "addr:street":"Carr Santa Catalina Thomas",
    "iso:country":"ES",
    "sg:address":"Carr Santa Catalina Thomas, 24",
    "sg:city":"Lloseta",
    "sg:orig_category":"Mec\u00c1nico Del Autom\u00d3vil",
    "sg:phone":"+34 971 51 91 65",
    "sg:postcode":"07360",
    "sg:province":"Islas Baleares",
    "wof:name":"Darder Martorell Francisco",
    "wof:placetype":"venue"
},
  "geometry": {"coordinates":[2.8661010265,39.7154998779],"type":"Point"}
}