{
  "type": "Feature",
  "properties": {
    "iso:country":"ES",
    "sg:address":"Calle de Ermitapea, 3",
    "sg:city":"Ansoain",
    "sg:orig_category":"Ebanister\u00cda",
    "sg:phone":"+34 948 12 85 23",
    "sg:postcode":"31013",
    "sg:province":"Navarra",
    "wof:name":"Carpinteria Ebanisteria Mendoza San Martin",
    "wof:placetype":"venue"
},
  "geometry": {"coordinates":[-1.6463570595,42.8325805664],"type":"Point"}
}