{
  "type": "Feature",
  "properties": {
    "iso:country":"ES",
    "sg:address":"Rua Poligono, 1",
    "sg:city":"Temple",
    "sg:orig_category":"Muebles Y Accesorios Para Cocinas Y Cuartos De Ba\u00d1o (al Por Menor)",
    "sg:phone":"+34 981 65 30 99",
    "sg:postcode":"15679",
    "sg:province":"La Coru\u00f1a",
    "wof:name":"Delba\u00f1o S.l.",
    "wof:placetype":"venue"
},
  "geometry": {"coordinates":[-8.3559913635,43.3156738281],"type":"Point"}
}