{
  "type": "Feature",
  "properties": {
    "addr:full":"Calle de Felipe Ii, 2 Valladolid Valladolid 47003",
    "addr:housenumber":"2",
    "addr:postcode":"47003",
    "addr:street":"Calle De Felipe Ii",
    "iso:country":"ES",
    "sg:address":"Calle de Felipe Ii, 2",
    "sg:city":"Valladolid",
    "sg:orig_category":"M\u00c9dicos: Estomatolog\u00cda",
    "sg:phone":"+34 983 30 42 42",
    "sg:postcode":"47003",
    "sg:province":"Valladolid",
    "wof:name":"Castrillo Martin Pedro Jesus",
    "wof:placetype":"venue"
},
  "geometry": {"coordinates":[-4.7258481979,41.6542663574],"type":"Point"}
}