{
  "type": "Feature",
  "properties": {
    "addr:full":"Rua San Lazaro (de), 20 Santiago De Compostela La Coru\u00f1a 15703",
    "addr:housenumber":"20",
    "addr:postcode":"15703",
    "addr:street":"Rua San Lazaro De;Corun\u0303A",
    "iso:country":"ES",
    "sg:address":"Rua San Lazaro (de), 20",
    "sg:city":"Santiago De Compostela",
    "sg:orig_category":"Confiter\u00cdas, Chocolater\u00cdas (al Por Menor)",
    "sg:phone":"+34 981 57 36 73",
    "sg:postcode":"15703",
    "sg:province":"La Coru\u00f1a",
    "wof:name":"Garcia Temprano Valeriano",
    "wof:placetype":"venue"
},
  "geometry": {"coordinates":[-8.5205783844,42.8867225647],"type":"Point"}
}