{
  "type": "Feature",
  "properties": {
    "addr:full":"Calle de Rascafria, 67 Villaviciosa Odon Madrid 28670",
    "addr:housenumber":"67",
    "addr:postcode":"28670",
    "addr:street":"Calle De Rascafria;Odon",
    "iso:country":"ES",
    "sg:address":"Calle de Rascafria, 67",
    "sg:city":"Villaviciosa Odon",
    "sg:orig_category":"Centros Empresariales",
    "sg:phone":"+34 916 65 93 68",
    "sg:postcode":"28670",
    "sg:province":"Madrid",
    "wof:name":"Proyecto Sotelo S.l.",
    "wof:placetype":"venue"
},
  "geometry": {"coordinates":[-3.9101340771,40.3522644043],"type":"Point"}
}