{
  "type": "Feature",
  "properties": {
    "addr:full":"Calle de Egia, 10 Donostia-san Sebastian Guip\u00f9zcoa 20012",
    "addr:housenumber":"10",
    "addr:postcode":"20012",
    "addr:street":"Calle De Egia",
    "iso:country":"ES",
    "sg:address":"Calle de Egia, 10",
    "sg:city":"Donostia-san Sebastian",
    "sg:orig_category":"Peluquer\u00cdas, Peluquer\u00cda Mixta",
    "sg:phone":"+34 943 28 12 69",
    "sg:postcode":"20012",
    "sg:province":"Guip\u00f9zcoa",
    "wof:name":"Ledesma Diez Maria Teresa",
    "wof:placetype":"venue"
},
  "geometry": {"coordinates":[-1.9736249447,43.3163337708],"type":"Point"}
}