{
  "type": "Feature",
  "properties": {
    "addr:full":"Calle de Castielfabib, 7 Valencia Valencia 46015",
    "addr:housenumber":"7",
    "addr:postcode":"46015",
    "addr:street":"Calle De Castielfabib",
    "iso:country":"ES",
    "sg:address":"Calle de Castielfabib, 7",
    "sg:city":"Valencia",
    "sg:orig_category":"Copas, Insignias, Trofeos",
    "sg:phone":"+34 963 48 36 13",
    "sg:postcode":"46015",
    "sg:province":"Valencia",
    "wof:name":"Martinez Garin Mercedes",
    "wof:placetype":"venue"
},
  "geometry": {"coordinates":[-0.3958449066,39.4784927368],"type":"Point"}
}