{
  "type": "Feature",
  "properties": {
    "iso:country":"ES",
    "sg:address":"Pg Lletres, 7",
    "sg:city":"Terrassa",
    "sg:orig_category":"Guarder\u00cdas",
    "sg:phone":"+34 935 37 64 95",
    "sg:postcode":"08221",
    "sg:province":"Barcelona",
    "wof:name":"Cooperatica Centre Educatio Lluis S.c.l.",
    "wof:placetype":"venue"
},
  "geometry": {"coordinates":[2.0104598999,41.5687408447],"type":"Point"}
}