{
  "type": "Feature",
  "properties": {
    "addr:full":"Avda Lugo De, 88 Aviles Asturias 33401",
    "addr:housenumber":"88",
    "addr:postcode":"33401",
    "addr:street":"Avda Lugo De",
    "iso:country":"ES",
    "sg:address":"Avda Lugo De, 88",
    "sg:city":"Aviles",
    "sg:orig_category":"Almacenes Frigor\u00cdficos",
    "sg:phone":"+34 985 56 65 53",
    "sg:postcode":"33401",
    "sg:province":"Asturias",
    "wof:name":"Congelados Mar De Cudillero S.l.",
    "wof:placetype":"venue"
},
  "geometry": {"coordinates":[-5.9285078049,43.5721588135],"type":"Point"}
}