{
  "type": "Feature",
  "properties": {
    "iso:country":"ES",
    "sg:address":"Carretera Aranda-torresandino, S/n",
    "sg:city":"Gumiel Mercado",
    "sg:orig_category":"Empresas De Carpinter\u00cda De Madera",
    "sg:phone":"+34 947 54 54 44",
    "sg:postcode":"09440",
    "sg:province":"Burgos",
    "sg:website":"www.lagorgola.com",
    "wof:name":"Carpinteria Hercasa S.l.",
    "wof:placetype":"venue"
},
  "geometry": {"coordinates":[-3.835973978,41.8227157593],"type":"Point"}
}