{
  "type": "Feature",
  "properties": {
    "iso:country":"ES",
    "sg:address":"Pl Porxos, 1",
    "sg:city":"Barcelona",
    "sg:orig_category":"Pescader\u00cdas (al Por Menor)",
    "sg:phone":"+34 933 03 28 39",
    "sg:postcode":"08020",
    "sg:province":"Barcelona",
    "wof:name":"Marbona Peix I Marisc S.l.",
    "wof:placetype":"venue"
},
  "geometry": {"coordinates":[2.1998660564,41.414516449],"type":"Point"}
}