{
  "type": "Feature",
  "properties": {
    "iso:country":"ES",
    "sg:address":"Calle de Cervantes, 53",
    "sg:city":"Brenes",
    "sg:orig_category":"Mec\u00c1nico Del Autom\u00d3vil",
    "sg:phone":"+34 955 65 37 95",
    "sg:postcode":"41310",
    "sg:province":"Sevilla",
    "wof:name":"Segovia Garcia Jorge",
    "wof:placetype":"venue"
},
  "geometry": {"coordinates":[-5.8665771484,37.5509567261],"type":"Point"}
}