{
  "type": "Feature",
  "properties": {
    "iso:country":"ES",
    "sg:address":"Calle de Lanzarote, 1",
    "sg:city":"San Sebastian De Los Reyes",
    "sg:orig_category":"Art\u00cdculos De Decoraci\u00d3n",
    "sg:phone":"+34 916 58 63 20",
    "sg:postcode":"28700",
    "sg:province":"Madrid",
    "wof:name":"Quaint & Quality",
    "wof:placetype":"venue"
},
  "geometry": {"coordinates":[-3.6235721111,40.5564804077],"type":"Point"}
}