{
  "type": "Feature",
  "properties": {
    "addr:full":"Calle de Comandante Caballero, 3 Oviedo Asturias 33005",
    "addr:housenumber":"3",
    "addr:postcode":"33005",
    "addr:street":"Calle De Comandante Caballero",
    "iso:country":"ES",
    "sg:address":"Calle de Comandante Caballero, 3",
    "sg:city":"Oviedo",
    "sg:orig_category":"Centros P\u00dablicos De Formaci\u00d3n Profesional Y T\u00c9cnica",
    "sg:phone":"+34 985 27 36 76",
    "sg:postcode":"33005",
    "sg:province":"Asturias",
    "wof:name":"Colegio De Abogados",
    "wof:placetype":"venue"
},
  "geometry": {"coordinates":[-5.8561916351,43.3601493835],"type":"Point"}
}