{
  "type": "Feature",
  "properties": {
    "iso:country":"ES",
    "sg:address":"Calle de Marques De La Vega, 1",
    "sg:city":"Puebla Calzada",
    "sg:orig_category":"Agencias De Viajes",
    "sg:phone":"+34 924 45 21 34",
    "sg:postcode":"06490",
    "sg:province":"Badajoz",
    "wof:name":"Reyes Miguel Emilia",
    "wof:placetype":"venue"
},
  "geometry": {"coordinates":[-6.6242790222,38.8952713013],"type":"Point"}
}