{
  "type": "Feature",
  "properties": {
    "iso:country":"ES",
    "sg:address":"Parada De Amoeiro, 152",
    "sg:city":"Parada",
    "sg:orig_category":"Caf\u00c9s, Bares, Cervecer\u00cdas",
    "sg:phone":"+34 988 27 99 00",
    "sg:postcode":"32170",
    "sg:province":"Ourense",
    "wof:name":"Novoa Vazquez Jose",
    "wof:placetype":"venue"
},
  "geometry": {"coordinates":[-7.9451670647,42.4144706726],"type":"Point"}
}