{
  "type": "Feature",
  "properties": {
    "addr:full":"Plaz Modesto Lafuente, S/n Cervera Pisuerga Palencia 34840",
    "addr:housenumber":"s / n",
    "addr:postcode":"34840",
    "iso:country":"ES",
    "sg:address":"Plaz Modesto Lafuente, S/n",
    "sg:city":"Cervera Pisuerga",
    "sg:orig_category":"Administraciones Regionales, Departamentales Y Locales",
    "sg:phone":"+34 979 87 00 02",
    "sg:postcode":"34840",
    "sg:province":"Palencia",
    "wof:name":"Ayuntamiento De Cervera De Pisuerga",
    "wof:placetype":"venue"
},
  "geometry": {"coordinates":[-4.498606205,42.8619651794],"type":"Point"}
}