{
  "type": "Feature",
  "properties": {
    "addr:full":"Calle de Julio Colomer, 17 Alfafar Valencia 46910",
    "addr:housenumber":"17",
    "addr:postcode":"46910",
    "addr:street":"Calle De Julio Colomer",
    "iso:country":"ES",
    "sg:address":"Calle de Julio Colomer, 17",
    "sg:city":"Alfafar",
    "sg:orig_category":"Art\u00cdculos De Madera (fabricaci\u00d3n Y Al Por Mayor)",
    "sg:phone":"+34 963 76 50 60",
    "sg:postcode":"46910",
    "sg:province":"Valencia",
    "wof:name":"Puga Martin Miguel",
    "wof:placetype":"venue"
},
  "geometry": {"coordinates":[-0.3885749876,39.4222564697],"type":"Point"}
}