{
  "type": "Feature",
  "properties": {
    "addr:full":"Calle de Se\u00d1orio De Albarracin, 34 Azagra Navarra 31560",
    "addr:housenumber":"34",
    "addr:postcode":"31560",
    "addr:street":"Calle De Sen\u0303Orio;Albarracin",
    "iso:country":"ES",
    "sg:address":"Calle de Se\u00d1orio De Albarracin, 34",
    "sg:city":"Azagra",
    "sg:orig_category":"Promotores Constructores",
    "sg:phone":"+34 948 69 20 86",
    "sg:postcode":"31560",
    "sg:province":"Navarra",
    "wof:name":"Construcciones Virgen Del Olmo",
    "wof:placetype":"venue"
},
  "geometry": {"coordinates":[-1.8963990211,42.3064613342],"type":"Point"}
}