{
  "type": "Feature",
  "properties": {
    "addr:full":"Calle de Ramon Y Cajal (de), 4 Pinto Madrid 28320",
    "addr:housenumber":"4",
    "addr:postcode":"28320",
    "addr:street":"Calle De Ramon Y Cajal De;Pinto",
    "iso:country":"ES",
    "sg:address":"Calle de Ramon Y Cajal (de), 4",
    "sg:city":"Pinto",
    "sg:orig_category":"Inform\u00c1tica: Soportes De Informaci\u00d3n, Suministros & Accesorios",
    "sg:phone":"+34 916 92 05 47",
    "sg:postcode":"28320",
    "sg:province":"Madrid",
    "wof:name":"Diaz Yanez Jose Manuel",
    "wof:placetype":"venue"
},
  "geometry": {"coordinates":[-3.7001709938,40.2418899536],"type":"Point"}
}