{
  "type": "Feature",
  "properties": {
    "addr:full":"Afores, S/n Anglesola Lleida 25320",
    "addr:housenumber":"s / n",
    "addr:postcode":"25320",
    "addr:street":"Afores",
    "iso:country":"ES",
    "sg:address":"Afores, S/n",
    "sg:city":"Anglesola",
    "sg:orig_category":"Hormigonados",
    "sg:phone":"+34 973 30 84 61",
    "sg:postcode":"25320",
    "sg:province":"Lleida",
    "wof:name":"Garrofe S. A.",
    "wof:placetype":"venue"
},
  "geometry": {"coordinates":[1.0846190453,41.6594657898],"type":"Point"}
}