{
  "type": "Feature",
  "properties": {
    "addr:full":"Calle de Reina Sofia, S/n Antilla Huelva 21449",
    "addr:housenumber":"s / n",
    "addr:postcode":"21449",
    "addr:street":"Calle De Reina Sofia",
    "iso:country":"ES",
    "sg:address":"Calle de Reina Sofia, S/n",
    "sg:city":"Antilla",
    "sg:orig_category":"Agencias Y Agentes Comerciales, Representantes",
    "sg:phone":"+34 959 48 14 00",
    "sg:postcode":"21449",
    "sg:province":"Huelva",
    "wof:name":"Lara Gonzalez Ignacio",
    "wof:placetype":"venue"
},
  "geometry": {"coordinates":[-7.2081589699,37.2067108154],"type":"Point"}
}