{
  "type": "Feature",
  "properties": {
    "iso:country":"ES",
    "sg:address":"Calle de Pinos Alta, 91",
    "sg:city":"Madrid",
    "sg:orig_category":"Estancos",
    "sg:phone":"+34 913 15 30 33",
    "sg:postcode":"28029",
    "sg:province":"Madrid",
    "wof:name":"Castro Garcia Francisco",
    "wof:placetype":"venue"
},
  "geometry": {"coordinates":[-3.6994130611,40.4693412781],"type":"Point"}
}