{
  "type": "Feature",
  "properties": {
    "iso:country":"ES",
    "sg:address":"Pase Castellana, 141",
    "sg:city":"Madrid",
    "sg:orig_category":"Agentes, Concesionarios Y Sucursales De Veh\u00cdculos",
    "sg:phone":"+34 915 72 06 20",
    "sg:postcode":"28046",
    "sg:province":"Madrid",
    "sg:website":"www.bmw.es/cuzco",
    "wof:name":"Cuzco Motor S.a.",
    "wof:placetype":"venue"
},
  "geometry": {"coordinates":[-3.6904060841,40.4595222473],"type":"Point"}
}