{
  "type": "Feature",
  "properties": {
    "iso:country":"ES",
    "sg:address":"Grup Arriberri, 14",
    "sg:city":"Donostia-san Sebastian",
    "sg:orig_category":"Supermercados Y Hipermercados",
    "sg:phone":"+34 943 35 12 11",
    "sg:postcode":"20017",
    "sg:province":"Guip\u00f9zcoa",
    "wof:name":"Mari Carmen Cerrato Perez",
    "wof:placetype":"venue"
},
  "geometry": {"coordinates":[-1.928614974,43.3169631958],"type":"Point"}
}