{
  "type": "Feature",
  "properties": {
    "addr:full":"Plaz Eras, 1 Baza Granada 18800",
    "addr:housenumber":"1",
    "addr:postcode":"18800",
    "addr:street":"Plaz Eras",
    "iso:country":"ES",
    "sg:address":"Plaz Eras, 1",
    "sg:city":"Baza",
    "sg:orig_category":"Electrodom\u00c9sticos (al Por Menor)",
    "sg:phone":"+34 958 70 33 53",
    "sg:postcode":"18800",
    "sg:province":"Granada",
    "wof:name":"Serrano Avila Francisco",
    "wof:placetype":"venue"
},
  "geometry": {"coordinates":[-2.7704091072,37.4930038452],"type":"Point"}
}