{
  "type": "Feature",
  "properties": {
    "iso:country":"ES",
    "sg:address":"Calle de Cervantes, 1",
    "sg:city":"Sotillo Adrada",
    "sg:orig_category":"Ropa Para Se\u00d1oras Y Caballeros (al Por Menor)",
    "sg:phone":"+34 918 66 02 77",
    "sg:postcode":"05420",
    "sg:province":"\u00c1vila",
    "wof:name":"Garcia Gonzalez Jesus",
    "wof:placetype":"venue"
},
  "geometry": {"coordinates":[-4.6326990128,40.3035736084],"type":"Point"}
}