{
  "type": "Feature",
  "properties": {
    "iso:country":"ES",
    "sg:address":"Ctra Adanero-gijon, Km. 0195,0",
    "sg:city":"Zaratan",
    "sg:orig_category":"Transportes Por V\u00cdas Navegables",
    "sg:phone":"+34 983 35 37 38",
    "sg:postcode":"47610",
    "sg:province":"Valladolid",
    "wof:name":"Lopez Pinto Aquilino",
    "wof:placetype":"venue"
},
  "geometry": {"coordinates":[-4.7845540047,41.6637001038],"type":"Point"}
}