{
  "type": "Feature",
  "properties": {
    "iso:country":"ES",
    "sg:address":"Avda Libertad (la), 21",
    "sg:city":"Navatejera",
    "sg:orig_category":"Ropa Para Ni\u00d1os (al Por Menor)",
    "sg:phone":"+34 987 28 54 67",
    "sg:postcode":"24008",
    "sg:province":"Le\u00f3n",
    "wof:name":"Vega Martinez Noel",
    "wof:placetype":"venue"
},
  "geometry": {"coordinates":[-5.5648818016,42.6201095581],"type":"Point"}
}