{
  "type": "Feature",
  "properties": {
    "addr:full":"Calle de Juan De Mena, 23 Madrid Madrid 28014",
    "addr:housenumber":"23",
    "addr:postcode":"madrid;28014",
    "addr:street":"Calle De Juan;Mena",
    "iso:country":"ES",
    "sg:address":"Calle de Juan De Mena, 23",
    "sg:city":"Madrid",
    "sg:orig_category":"Comunidades Religiosas",
    "sg:phone":"+34 915 21 70 83",
    "sg:postcode":"28014",
    "sg:province":"Madrid",
    "sg:website":"www.cruzadasdesantamaria.org",
    "wof:name":"Cruzadas De Santa Maria",
    "wof:placetype":"venue"
},
  "geometry": {"coordinates":[-3.6897668839,40.41746521],"type":"Point"}
}