{
  "type": "Feature",
  "properties": {
    "iso:country":"ES",
    "sg:address":"Calle de Joaquin Velasco Martin, 110",
    "sg:city":"Valladolid",
    "sg:orig_category":"Carnicer\u00cdas, Carnicer\u00cdas",
    "sg:phone":"+34 983 34 26 39",
    "sg:postcode":"47014",
    "sg:province":"Valladolid",
    "wof:name":"Garcia Pro Francisco",
    "wof:placetype":"venue"
},
  "geometry": {"coordinates":[-4.7407979965,41.6450691223],"type":"Point"}
}