{
  "type": "Feature",
  "properties": {
    "iso:country":"ES",
    "sg:address":"Praz Ultramar, 1",
    "sg:city":"Ferrol",
    "sg:orig_category":"Ropa Para Se\u00d1oras (al Por Menor)",
    "sg:phone":"+34 981 37 08 90",
    "sg:postcode":"15404",
    "sg:province":"A Coru\u00f1a",
    "wof:name":"Zwirner Aleman Ernesto Federico",
    "wof:placetype":"venue"
},
  "geometry": {"coordinates":[-8.2144622803,43.4897613525],"type":"Point"}
}