{
  "type": "Feature",
  "properties": {
    "addr:full":"Robledal, 48 Rivas Vaciamadrid Madrid 28529",
    "addr:housenumber":"48",
    "addr:postcode":"28529",
    "addr:street":"Robledal",
    "iso:country":"ES",
    "sg:address":"Robledal, 48",
    "sg:city":"Rivas Vaciamadrid",
    "sg:orig_category":"Guarder\u00cdas",
    "sg:phone":"+34 914 99 18 71",
    "sg:postcode":"28529",
    "sg:province":"Madrid",
    "wof:name":"Actividades Infantiles S.l.",
    "wof:placetype":"venue"
},
  "geometry": {"coordinates":[-3.5209834576,40.3563346863],"type":"Point"}
}