{
  "type": "Feature",
  "properties": {
    "addr:full":"Carrer de Enric Prat De La Riba, 195 Hospitalet Llobregat Barcelona 08901",
    "addr:housenumber":"195",
    "addr:postcode":"08901",
    "addr:street":"Carrer De Enric Prat De La Riba",
    "iso:country":"ES",
    "sg:address":"Carrer de Enric Prat De La Riba, 195",
    "sg:city":"Hospitalet Llobregat",
    "sg:orig_category":"Supermercados Y Hipermercados",
    "sg:phone":"+34 932 61 25 27",
    "sg:postcode":"08901",
    "sg:province":"Barcelona",
    "wof:name":"Consum Sociedad Cooperativa Limitada",
    "wof:placetype":"venue"
},
  "geometry": {"coordinates":[2.1075260639,41.3616333008],"type":"Point"}
}