{
  "type": "Feature",
  "properties": {
    "iso:country":"ES",
    "sg:address":"Av Llibertat, 54",
    "sg:city":"Elche",
    "sg:orig_category":"Farmacias",
    "sg:phone":"+34 965 46 57 27",
    "sg:postcode":"03206",
    "sg:province":"Alicante",
    "wof:name":"Farmacia Ruiz De Lope Y Vives Cb",
    "wof:placetype":"venue"
},
  "geometry": {"coordinates":[-0.7057170272,38.2698707581],"type":"Point"}
}