{
  "type": "Feature",
  "properties": {
    "addr:full":"Calle de Rufino Blanco, 3 Guadalajara Guadalajara 19003",
    "addr:housenumber":"3",
    "addr:postcode":"19003",
    "addr:street":"Calle De Rufino Blanco",
    "iso:country":"ES",
    "sg:address":"Calle de Rufino Blanco, 3",
    "sg:city":"Guadalajara",
    "sg:orig_category":"Abogados",
    "sg:phone":"+34 949 25 46 80",
    "sg:postcode":"19003",
    "sg:province":"Guadalajara",
    "wof:name":"Sanchez Diaz Angel Mario",
    "wof:placetype":"venue"
},
  "geometry": {"coordinates":[-3.166508913,40.6273612976],"type":"Point"}
}