{
  "type": "Feature",
  "properties": {
    "iso:country":"ES",
    "sg:address":"Calle de San Quilez, 2",
    "sg:city":"Campillo Altobuey",
    "sg:orig_category":"Quincaller\u00cda (al Por Menor)",
    "sg:phone":"+34 969 33 70 68",
    "sg:postcode":"16210",
    "sg:province":"Cuenca",
    "wof:name":"Sauquillo Marin Cristino",
    "wof:placetype":"venue"
},
  "geometry": {"coordinates":[-1.7919280529,39.6096801758],"type":"Point"}
}