{
  "type": "Feature",
  "properties": {
    "addr:full":"Calle de Manantial, 1 Valladolid Valladolid 47009",
    "addr:housenumber":"1",
    "addr:postcode":"47009",
    "addr:street":"Calle De Manantial",
    "iso:country":"ES",
    "sg:address":"Calle de Manantial, 1",
    "sg:city":"Valladolid",
    "sg:orig_category":"Cr\u00cda De Animales",
    "sg:phone":"+34 983 33 92 80",
    "sg:postcode":"47009",
    "sg:province":"Valladolid",
    "wof:name":"Torres Bazaco Isabel",
    "wof:placetype":"venue"
},
  "geometry": {"coordinates":[-4.7309689522,41.6632881165],"type":"Point"}
}