{
  "type": "Feature",
  "properties": {
    "addr:full":"Calle de Gracia, 8 Granada Granada 18002",
    "addr:housenumber":"8",
    "addr:postcode":"18002",
    "addr:street":"Calle De Gracia",
    "iso:country":"ES",
    "sg:address":"Calle de Gracia, 8",
    "sg:city":"Granada",
    "sg:orig_category":"Fabricaci\u00d3n De Su\u00c9ters Y Chalecos De Punto",
    "sg:phone":"+34 958 25 12 43",
    "sg:postcode":"18002",
    "sg:province":"Granada",
    "wof:name":"Bolivar Gazquez Emilio",
    "wof:placetype":"venue"
},
  "geometry": {"coordinates":[-3.6019170284,37.1746330261],"type":"Point"}
}