{
  "type": "Feature",
  "properties": {
    "addr:full":"Calle de Copernico, S/n Madrid Madrid 28032",
    "addr:housenumber":"/ n",
    "addr:postcode":"28032",
    "addr:street":"Calle De Copernico S",
    "iso:country":"ES",
    "sg:address":"Calle de Copernico, S/n",
    "sg:city":"Madrid",
    "sg:orig_category":"Centros De Educaci\u00d3n Especial",
    "sg:phone":"+34 917 51 09 82",
    "sg:postcode":"28032",
    "sg:province":"Madrid",
    "wof:name":"Comunidad Autonoma De Madrid-centros De Educacion",
    "wof:placetype":"venue"
},
  "geometry": {"coordinates":[-3.6235444546,40.395324707],"type":"Point"}
}