{
  "type": "Feature",
  "properties": {
    "addr:full":"Calle de Magnolias, 10 Tafira Alta Las Palmas 35017",
    "addr:housenumber":"10",
    "addr:postcode":"35017",
    "addr:street":"Calle De Magnolias;Alta",
    "iso:country":"ES",
    "sg:address":"Calle de Magnolias, 10",
    "sg:city":"Tafira Alta",
    "sg:orig_category":"Centros De Educaci\u00d3n Especial",
    "sg:phone":"+34 928 35 46 71",
    "sg:postcode":"35017",
    "sg:province":"Las Palmas",
    "wof:name":"Gobierno De Canarias",
    "wof:placetype":"venue"
},
  "geometry": {"coordinates":[-15.4612922668,28.0561084747],"type":"Point"}
}