{
  "type": "Feature",
  "properties": {
    "iso:country":"ES",
    "sg:address":"Pol Industrial Heras, S/n",
    "sg:city":"Heras",
    "sg:orig_category":"Trabajos De Perforaciones, Sondeos, Construcci\u00d3n De Pozos",
    "sg:phone":"+34 942 54 33 41",
    "sg:postcode":"39792",
    "sg:province":"Cantabria",
    "wof:name":"Laboragua S.a.",
    "wof:placetype":"venue"
},
  "geometry": {"coordinates":[-3.7650806904,43.3963508606],"type":"Point"}
}