{
  "type": "Feature",
  "properties": {
    "addr:full":"Plaz Constitucion (de La), 8 Socuellamos Ciudad Real 13630",
    "addr:housenumber":"8",
    "addr:postcode":"13630",
    "iso:country":"ES",
    "sg:address":"Plaz Constitucion (de La), 8",
    "sg:city":"Socuellamos",
    "sg:orig_category":"Loter\u00cda Y T\u00d3mbola",
    "sg:phone":"+34 926 50 08 02",
    "sg:postcode":"13630",
    "sg:province":"Ciudad Real",
    "wof:name":"Frias Delgado Pilar",
    "wof:placetype":"venue"
},
  "geometry": {"coordinates":[-2.7948589325,39.2849845886],"type":"Point"}
}