{
  "type": "Feature",
  "properties": {
    "addr:full":"Calle de Sargento Perona, 14 Pedernoso Cuenca 16638",
    "addr:housenumber":"14",
    "addr:postcode":"16638",
    "addr:street":"Calle De Sargento Perona",
    "iso:country":"ES",
    "sg:address":"Calle de Sargento Perona, 14",
    "sg:city":"Pedernoso",
    "sg:orig_category":"Asesor\u00cda Sobre Comunicaci\u00d3n De Empresas",
    "sg:phone":"+34 967 16 44 37",
    "sg:postcode":"16638",
    "sg:province":"Cuenca",
    "wof:name":"Asesoria Consulting Mancha Baja S.l.",
    "wof:placetype":"venue"
},
  "geometry": {"coordinates":[-2.743953228,39.4845962524],"type":"Point"}
}