{
  "type": "Feature",
  "properties": {
    "iso:country":"ES",
    "sg:address":"Ancora, 158",
    "sg:city":"Arguineguin-mogan",
    "sg:orig_category":"Inform\u00c1tica (estudios, Servicios, Asesor\u00cda, Formaci\u00d3n)",
    "sg:phone":"+34 928 15 08 45",
    "sg:postcode":"35120",
    "sg:province":"Las Palmas",
    "wof:name":"Computer Service S.c.p.",
    "wof:placetype":"venue"
},
  "geometry": {"coordinates":[-15.6830463409,27.7618026733],"type":"Point"}
}