{
  "type": "Feature",
  "properties": {
    "iso:country":"ES",
    "sg:address":"Carrer de Freser, 90",
    "sg:city":"Barcelona",
    "sg:orig_category":"Reposter\u00cdas",
    "sg:phone":"+34 934 55 61 76",
    "sg:postcode":"08026",
    "sg:province":"Barcelona",
    "wof:name":"Forn Elias S.l.",
    "wof:placetype":"venue"
},
  "geometry": {"coordinates":[2.1807370186,41.4121246338],"type":"Point"}
}