{
  "type": "Feature",
  "properties": {
    "addr:full":"Calle de Carretera, Km. 0348,0 Manzanal Del Puerto Le\u00f3n 24369",
    "addr:postcode":"24369",
    "addr:street":"Calle De Carretera Km. 0348,0;Leo\u0301N",
    "iso:country":"ES",
    "sg:address":"Calle de Carretera, Km. 0348,0",
    "sg:city":"Manzanal Del Puerto",
    "sg:orig_category":"Hoteles",
    "sg:phone":"+34 987 60 73 62",
    "sg:postcode":"24369",
    "sg:province":"Le\u00f3n",
    "wof:name":"Santos Rosel Mari Nieves",
    "wof:placetype":"venue"
},
  "geometry": {"coordinates":[-6.2216691971,42.5882911682],"type":"Point"}
}