{
  "type": "Feature",
  "properties": {
    "iso:country":"ES",
    "sg:address":"Calle de Pedro Iv De Aragon, 1",
    "sg:city":"Tauste",
    "sg:classifiers":[
        {
            "category":"Autos & Motor Vehicles",
            "subcategory":"Automobile Sales",
            "type":"Retail Goods"
        }
    ],
    "sg:phone":"+34 976 85 90 53",
    "sg:postcode":"50660",
    "sg:province":"Zaragoza",
    "wof:name":"Calvera Martin Jose Angel",
    "wof:placetype":"venue"
},
  "geometry": {"coordinates":[-1.2557810545,41.9218101501],"type":"Point"}
}