{
  "type": "Feature",
  "properties": {
    "addr:full":"Calle de La Rua, 30 Villalon Campos Valladolid 47600",
    "addr:postcode":"47600",
    "addr:street":"Calle De La Rua 30 Villalon Campos",
    "iso:country":"ES",
    "sg:address":"Calle de La Rua, 30",
    "sg:city":"Villalon Campos",
    "sg:orig_category":"Tiendas De Grano, Frutas Y Legumbres Secas (al Por Menor)",
    "sg:phone":"+34 983 76 10 82",
    "sg:postcode":"47600",
    "sg:province":"Valladolid",
    "wof:name":"Martinez Lopez Justina Marina",
    "wof:placetype":"venue"
},
  "geometry": {"coordinates":[-5.0348992348,42.0987815857],"type":"Point"}
}