{
  "type": "Feature",
  "properties": {
    "iso:country":"ES",
    "sg:address":"Jose Baixauli Crehua, 3",
    "sg:city":"Massanassa",
    "sg:orig_category":"Guarder\u00cdas",
    "sg:phone":"+34 961 25 10 87",
    "sg:postcode":"46470",
    "sg:province":"Valencia",
    "wof:name":"Morales Pe\u00f1arrubia Elena",
    "wof:placetype":"venue"
},
  "geometry": {"coordinates":[-0.3995760083,39.4096603394],"type":"Point"}
}