{
  "type": "Feature",
  "properties": {
    "addr:full":"Avda Gasteiz, 52 Vitoria-gasteiz \u00c1lava 01012",
    "addr:housenumber":"52",
    "addr:postcode":"01012",
    "addr:street":"Avda Gasteiz",
    "iso:country":"ES",
    "sg:address":"Avda Gasteiz, 52",
    "sg:city":"Vitoria-gasteiz",
    "sg:orig_category":"Agencias De Viajes",
    "sg:phone":"+34 945 21 36 48",
    "sg:postcode":"01012",
    "sg:province":"\u00c1lava",
    "wof:name":"Rodri\u00f1o Mendez Jose",
    "wof:placetype":"venue"
},
  "geometry": {"coordinates":[-2.6804668903,42.8501930237],"type":"Point"}
}