{
  "type": "Feature",
  "properties": {
    "iso:country":"ES",
    "sg:address":"Calle de Maestro Chanza, 7",
    "sg:city":"Villena",
    "sg:orig_category":"Comerciantes Al Por Mayor De Vinos, Licores Y Alcoholes",
    "sg:phone":"+34 965 80 25 68",
    "sg:postcode":"03400",
    "sg:province":"Alicante",
    "wof:name":"Valdes Martinez Bernardo",
    "wof:placetype":"venue"
},
  "geometry": {"coordinates":[-0.8652709723,38.632019043],"type":"Point"}
}