{
  "type": "Feature",
  "properties": {
    "iso:country":"ES",
    "sg:address":"Avda Club Deportivo, 54",
    "sg:city":"Logro\u00f1o",
    "sg:orig_category":"Guarder\u00cdas",
    "sg:phone":"+34 941 20 58 99",
    "sg:postcode":"26007",
    "sg:province":"La Rioja",
    "wof:name":"Diez Miguel Raquel",
    "wof:placetype":"venue"
},
  "geometry": {"coordinates":[-2.4580550194,42.4576416016],"type":"Point"}
}