{
  "type": "Feature",
  "properties": {
    "addr:full":"Calle de Atutxa Sailburua, 6 Intzuntza Vizcaya 48330",
    "addr:housenumber":"6",
    "addr:postcode":"48330",
    "addr:street":"Calle De Atutxa Sailburua",
    "iso:country":"ES",
    "sg:address":"Calle de Atutxa Sailburua, 6",
    "sg:city":"Intzuntza",
    "sg:orig_category":"Cajas De Ahorro",
    "sg:phone":"+34 946 31 30 46",
    "sg:postcode":"48330",
    "sg:province":"Vizcaya",
    "sg:website":"www.bbk.es",
    "wof:name":"Bilbao Bizkaia Kutxa",
    "wof:placetype":"venue"
},
  "geometry": {"coordinates":[-2.7691090107,43.2078361511],"type":"Point"}
}