{
  "type": "Feature",
  "properties": {
    "addr:full":"C/ Balmes, 8 Calonge Girona 17251",
    "addr:housenumber":"8",
    "addr:postcode":"17251",
    "addr:street":"C / Balmes",
    "iso:country":"ES",
    "sg:address":"C/ Balmes, 8",
    "sg:city":"Calonge",
    "sg:orig_category":"Reciclaje Y Tratamiento De Desechos Varios",
    "sg:phone":"+34 972 65 08 81",
    "sg:postcode":"17251",
    "sg:province":"Girona",
    "sg:website":"www.gesteiverd.com",
    "wof:name":"Gestiverd Baix Emporda S.l.",
    "wof:placetype":"venue"
},
  "geometry": {"coordinates":[3.0776660442,41.8595924377],"type":"Point"}
}