{
  "type": "Feature",
  "properties": {
    "iso:country":"ES",
    "sg:address":"Carr Sant Antoni, 8",
    "sg:city":"Palafrugell",
    "sg:orig_category":"Molduras, Junquillos, Listones Y Molduras Perforadas",
    "sg:phone":"+34 972 30 09 80",
    "sg:postcode":"17200",
    "sg:province":"Girona",
    "wof:name":"Salcedo Perello Maria Carmen",
    "wof:placetype":"venue"
},
  "geometry": {"coordinates":[3.1630020142,41.9180641174],"type":"Point"}
}