{
  "type": "Feature",
  "properties": {
    "iso:country":"ES",
    "sg:address":"Avda Manolete, 12",
    "sg:city":"Cordoba",
    "sg:orig_category":"Psic\u00d3logos",
    "sg:phone":"+34 957 45 26 29",
    "sg:postcode":"14005",
    "sg:province":"C\u00f3rdoba",
    "wof:name":"Lara Diaz Alberto",
    "wof:placetype":"venue"
},
  "geometry": {"coordinates":[-4.7964320183,37.879989624],"type":"Point"}
}