{
  "type": "Feature",
  "properties": {
    "iso:country":"ES",
    "sg:address":"Calle de San Antonio, 32",
    "sg:city":"Vitoria-gasteiz",
    "sg:orig_category":"Arquitectos",
    "sg:phone":"+34 945 13 89 59",
    "sg:postcode":"01005",
    "sg:province":"\u00c1lava",
    "wof:name":"De Lorenzo De Urien Agustin Ignacio",
    "wof:placetype":"venue"
},
  "geometry": {"coordinates":[-2.6746799946,42.8417053223],"type":"Point"}
}