{
  "type": "Feature",
  "properties": {
    "addr:full":"Calle de Peso, 20 Madridejos Toledo 45710",
    "addr:housenumber":"20",
    "addr:postcode":"45710",
    "addr:street":"Calle De Peso",
    "iso:country":"ES",
    "sg:address":"Calle de Peso, 20",
    "sg:city":"Madridejos",
    "sg:orig_category":"Confecci\u00d3n (fabricaci\u00d3n, Al Por Mayor)",
    "sg:phone":"+34 925 46 05 37",
    "sg:postcode":"45710",
    "sg:province":"Toledo",
    "wof:name":"Tipical Punto S.l.",
    "wof:placetype":"venue"
},
  "geometry": {"coordinates":[-3.5391018391,39.4685096741],"type":"Point"}
}