{
  "type": "Feature",
  "properties": {
    "iso:country":"ES",
    "sg:address":"Avda Navarra, 31",
    "sg:city":"Oyon-oion",
    "sg:orig_category":"Asociaciones Humanitarias, De Cooperaci\u00d3n, De Acci\u00d3n Social",
    "sg:phone":"+34 945 62 20 25",
    "sg:postcode":"01320",
    "sg:province":"\u00c1lava",
    "wof:name":"Asociacion Prodeficientes Mentales De Alava",
    "wof:placetype":"venue"
},
  "geometry": {"coordinates":[-2.4356276989,42.5047225952],"type":"Point"}
}