{
  "type": "Feature",
  "properties": {
    "iso:country":"ES",
    "sg:address":"Calle de Ilucia, 10",
    "sg:city":"Santisteban Puerto",
    "sg:orig_category":"Doctores En Medicina",
    "sg:phone":"+34 953 40 15 96",
    "sg:postcode":"23250",
    "sg:province":"Ja\u00e9n",
    "wof:name":"Gallardo Perez Emilio",
    "wof:placetype":"venue"
},
  "geometry": {"coordinates":[-3.2013289928,38.250743866],"type":"Point"}
}