{
  "type": "Feature",
  "properties": {
    "addr:full":"Pase Santa Maria De La Cabeza, 41 Madrid Madrid 28045",
    "addr:housenumber":"41",
    "addr:postcode":"madrid;28045",
    "addr:street":"Cabeza",
    "iso:country":"ES",
    "sg:address":"Pase Santa Maria De La Cabeza, 41",
    "sg:city":"Madrid",
    "sg:orig_category":"Alimentaci\u00d3n General (al Por Menor)",
    "sg:phone":"+34 915 30 22 19",
    "sg:postcode":"28045",
    "sg:province":"Madrid",
    "wof:name":"Lorden Velasco Lisardo",
    "wof:placetype":"venue"
},
  "geometry": {"coordinates":[-3.6974589825,40.4027442932],"type":"Point"}
}