{
  "type": "Feature",
  "properties": {
    "addr:full":"Ctra Autovia Castelldefels, Km. 0012,2 Viladecans Barcelona 08840",
    "addr:postcode":"08840",
    "addr:street":"Ctra Autovia Castelldefels Km. 0012,2",
    "iso:country":"ES",
    "sg:address":"Ctra Autovia Castelldefels, Km. 0012,2",
    "sg:city":"Viladecans",
    "sg:orig_category":"Venta De Caravanas, Casas M\u00d3viles, Camping",
    "sg:phone":"+34 936 58 12 40",
    "sg:postcode":"08840",
    "sg:province":"Barcelona",
    "wof:name":"Caravaning Penedes S.a.",
    "wof:placetype":"venue"
},
  "geometry": {"coordinates":[2.0458250046,41.3019294739],"type":"Point"}
}