{
  "type": "Feature",
  "properties": {
    "addr:full":"Calle de Nicolas Soria, 12 Oviedo Asturias 33012",
    "addr:housenumber":"12",
    "addr:postcode":"33012",
    "addr:street":"Calle De Nicolas Soria",
    "iso:country":"ES",
    "sg:address":"Calle de Nicolas Soria, 12",
    "sg:city":"Oviedo",
    "sg:orig_category":"Peluqueros: De Se\u00d1oras",
    "sg:phone":"+34 985 11 26 71",
    "sg:postcode":"33012",
    "sg:province":"Asturias",
    "wof:name":"Blanco Valle Susana",
    "wof:placetype":"venue"
},
  "geometry": {"coordinates":[-5.8535442352,43.3690643311],"type":"Point"}
}