{
  "type": "Feature",
  "properties": {
    "addr:full":"Bidekurutzeta Kalea, 27 Bergara Guip\u00f9zcoa 20570",
    "addr:housenumber":"27",
    "addr:postcode":"20570",
    "addr:street":"Bidekurutzeta Kalea;Guipu\u0300Zcoa",
    "iso:country":"ES",
    "sg:address":"Bidekurutzeta Kalea, 27",
    "sg:city":"Bergara",
    "sg:orig_category":"Abogados",
    "sg:phone":"+34 943 76 03 02",
    "sg:postcode":"20570",
    "sg:province":"Guip\u00f9zcoa",
    "wof:name":"Ugalde Asociados, C.b.",
    "wof:placetype":"venue"
},
  "geometry": {"coordinates":[-2.4233329296,43.1255264282],"type":"Point"}
}