{
  "type": "Feature",
  "properties": {
    "iso:country":"ES",
    "sg:address":"Carrer de Sant Pere, 47",
    "sg:city":"Lloret Mar",
    "sg:orig_category":"Bisuteros (fabricaci\u00d3n, Al Por Mayor)",
    "sg:phone":"+34 972 37 23 52",
    "sg:postcode":"17310",
    "sg:province":"Girona",
    "wof:name":"Pi\u00f1eiro Solsona Andres Manuel",
    "wof:placetype":"venue"
},
  "geometry": {"coordinates":[2.8457560539,41.700920105],"type":"Point"}
}