{
  "type": "Feature",
  "properties": {
    "addr:full":"Avda Compostilla, 12 Ponferrada Le\u00f3n 24400",
    "addr:housenumber":"12",
    "addr:postcode":"24400",
    "addr:street":"Avda Compostilla",
    "iso:country":"ES",
    "sg:address":"Avda Compostilla, 12",
    "sg:city":"Ponferrada",
    "sg:orig_category":"Supermercados Y Hipermercados",
    "sg:phone":"+34 987 42 32 78",
    "sg:postcode":"24400",
    "sg:province":"Le\u00f3n",
    "wof:name":"Almacenes El Anzuelo S.l.",
    "wof:placetype":"venue"
},
  "geometry": {"coordinates":[-6.5979065895,42.5500869751],"type":"Point"}
}