{
  "type": "Feature",
  "properties": {
    "iso:country":"ES",
    "sg:address":"El Ventorrillo, 9",
    "sg:city":"Piedras Blancas-laspra",
    "sg:orig_category":"Metalurgia",
    "sg:phone":"+34 985 53 02 52",
    "sg:postcode":"33450",
    "sg:province":"Asturias",
    "wof:name":"Canalones Castrillon S.l",
    "wof:placetype":"venue"
},
  "geometry": {"coordinates":[-5.974489212,43.5595817566],"type":"Point"}
}