{
  "type": "Feature",
  "properties": {
    "addr:full":"Calle de Rio Guadarranque, 7 Poligono Industrial Guadalete C\u00e1diz 11500",
    "addr:housenumber":"7 poligono",
    "addr:postcode":"11500",
    "addr:street":"Calle De Rio Guadarranque;Industrial Guadalete Ca\u0301Diz",
    "iso:country":"ES",
    "sg:address":"Calle de Rio Guadarranque, 7",
    "sg:city":"Poligono Industrial Guadalete",
    "sg:orig_category":"Listas De Boda, Menaje De Mesa Y Cocina",
    "sg:phone":"+34 956 56 02 43",
    "sg:postcode":"11500",
    "sg:province":"C\u00e1diz",
    "wof:name":"Ad Decomuebles S.l.",
    "wof:placetype":"venue"
},
  "geometry": {"coordinates":[-6.2214260101,36.5951690674],"type":"Point"}
}