{
  "type": "Feature",
  "properties": {
    "addr:full":"Vide, S/n Vide Ourense 32230",
    "addr:housenumber":"s / n",
    "addr:postcode":"32230",
    "addr:street":"Vide",
    "iso:country":"ES",
    "sg:address":"Vide, S/n",
    "sg:city":"Vide",
    "sg:orig_category":"Fabricaci\u00d3n De Su\u00c9ters Y Chalecos De Punto",
    "sg:phone":"+34 988 48 90 10",
    "sg:postcode":"32230",
    "sg:province":"Ourense",
    "wof:name":"Generos De Punto Marvy S.l.",
    "wof:placetype":"venue"
},
  "geometry": {"coordinates":[-8.0492553711,42.3203544617],"type":"Point"}
}