{
  "type": "Feature",
  "properties": {
    "iso:country":"ES",
    "sg:address":"Mercurin, S/n",
    "sg:city":"Ordes",
    "sg:orig_category":"Maquinaria Para Industrias Diversas",
    "sg:phone":"+34 981 68 27 63",
    "sg:postcode":"15680",
    "sg:province":"La Coru\u00f1a",
    "wof:name":"San Clemente De Mercurin Sl",
    "wof:placetype":"venue"
},
  "geometry": {"coordinates":[-8.4072790146,43.0771408081],"type":"Point"}
}