{
  "type": "Feature",
  "properties": {
    "addr:full":"Calle de Opera (la), 5 Elda Alicante 03600",
    "addr:housenumber":"5",
    "addr:postcode":"03600",
    "addr:street":"Calle De Opera La",
    "iso:country":"ES",
    "sg:address":"Calle de Opera (la), 5",
    "sg:city":"Elda",
    "sg:orig_category":"Promotores Constructores",
    "sg:phone":"+34 966 98 18 44",
    "sg:postcode":"03600",
    "sg:province":"Alicante",
    "wof:name":"Construcciones Jogasmi S.l.",
    "wof:placetype":"venue"
},
  "geometry": {"coordinates":[-0.7983549833,38.4811592102],"type":"Point"}
}