{
  "type": "Feature",
  "properties": {
    "addr:full":"Sabadell(bda H America), 19 Los Dolores Murcia 30310",
    "addr:housenumber":"19",
    "addr:postcode":"30310",
    "addr:street":"Bda;America",
    "iso:country":"ES",
    "sg:address":"Sabadell(bda H America), 19",
    "sg:city":"Los Dolores",
    "sg:orig_category":"Alimentaci\u00d3n General (al Por Mayor)",
    "sg:phone":"+34 968 53 45 05",
    "sg:postcode":"30310",
    "sg:province":"Murcia",
    "wof:name":"J.goyza C.b.",
    "wof:placetype":"venue"
},
  "geometry": {"coordinates":[-1.0122350454,37.634147644],"type":"Point"}
}