{
  "type": "Feature",
  "properties": {
    "iso:country":"ES",
    "sg:address":"Carrer de Arago, 517",
    "sg:city":"Barcelona",
    "sg:orig_category":"Prot\u00c9sicos Dentales",
    "sg:phone":"+34 932 45 42 87",
    "sg:postcode":"08013",
    "sg:province":"Barcelona",
    "wof:name":"Arias Sanchez Francisco Javier",
    "wof:placetype":"venue"
},
  "geometry": {"coordinates":[2.1824996471,41.4054260254],"type":"Point"}
}