{
  "type": "Feature",
  "properties": {
    "addr:full":"Carrer de Llibertat, 26 Barcelona Barcelona 08012",
    "addr:housenumber":"26",
    "addr:postcode":"08012",
    "addr:street":"Carrer De Llibertat",
    "iso:country":"ES",
    "sg:address":"Carrer de Llibertat, 26",
    "sg:city":"Barcelona",
    "sg:orig_category":"Fabricaci\u00d3n De Etiquetas",
    "sg:phone":"+34 934 57 19 14",
    "sg:postcode":"08012",
    "sg:province":"Barcelona",
    "wof:name":"Casals Canal Juan",
    "wof:placetype":"venue"
},
  "geometry": {"coordinates":[2.1615209579,41.3998565674],"type":"Point"}
}