{
  "type": "Feature",
  "properties": {
    "addr:full":"Calle de Nieves (las), 19 Segovia Segovia 40003",
    "addr:housenumber":"19",
    "addr:postcode":"40003",
    "addr:street":"Calle De Nieves Las",
    "iso:country":"ES",
    "sg:address":"Calle de Nieves (las), 19",
    "sg:city":"Segovia",
    "sg:orig_category":"Carnicer\u00cdas, Carnicer\u00cdas",
    "sg:phone":"+34 921 43 10 80",
    "sg:postcode":"40003",
    "sg:province":"Segovia",
    "wof:name":"Yuste Duran Jose Ramon",
    "wof:placetype":"venue"
},
  "geometry": {"coordinates":[-4.1111941338,40.9551391602],"type":"Point"}
}