{
  "type": "Feature",
  "properties": {
    "iso:country":"ES",
    "sg:address":"Juan Bautista Erro Kalea, 8",
    "sg:city":"Andoain",
    "sg:orig_category":"M\u00c9dicos: Estomatolog\u00cda",
    "sg:phone":"+34 943 57 96 57",
    "sg:postcode":"20140",
    "sg:province":"Guip\u00f9zcoa",
    "wof:name":"Jose Luis Oyarzabal Yurramendi",
    "wof:placetype":"venue"
},
  "geometry": {"coordinates":[-2.0207939148,43.2171897888],"type":"Point"}
}