{
  "type": "Feature",
  "properties": {
    "addr:full":"Calle de Carretas, 7 Alberca De Las Torres Murcia 30150",
    "addr:housenumber":"7",
    "addr:postcode":"30150",
    "addr:street":"Calle De Carretas",
    "iso:country":"ES",
    "sg:address":"Calle de Carretas, 7",
    "sg:city":"Alberca De Las Torres",
    "sg:orig_category":"Empresas De Carpinter\u00cda",
    "sg:phone":"+34 968 37 97 49",
    "sg:postcode":"30150",
    "sg:province":"Murcia",
    "wof:name":"Alugema S.l.",
    "wof:placetype":"venue"
},
  "geometry": {"coordinates":[-1.1439838409,37.9372787476],"type":"Point"}
}