{
  "type": "Feature",
  "properties": {
    "addr:full":"Pg Misericordia, 7 Reus Tarragona 43205",
    "addr:housenumber":"7",
    "addr:postcode":"43205",
    "addr:street":"Pg Misericordia",
    "iso:country":"ES",
    "sg:address":"Pg Misericordia, 7",
    "sg:city":"Reus",
    "sg:orig_category":"Peluquer\u00cdas, Peluquer\u00cda Mixta",
    "sg:phone":"+34 977 32 02 03",
    "sg:postcode":"43205",
    "sg:province":"Tarragona",
    "wof:name":"Perruquers Rasgos Reus S.l.",
    "wof:placetype":"venue"
},
  "geometry": {"coordinates":[1.1050109863,41.1490440369],"type":"Point"}
}