{
  "type": "Feature",
  "properties": {
    "iso:country":"ES",
    "sg:address":"Moli De La Sal, 20",
    "sg:city":"Canovelles",
    "sg:orig_category":"Ense\u00d1anza: Profesiones Art\u00cdsticas",
    "sg:phone":"+34 938 49 19 91",
    "sg:postcode":"08420",
    "sg:province":"Barcelona",
    "wof:name":"Mercafoto Canovelles S.l.",
    "wof:placetype":"venue"
},
  "geometry": {"coordinates":[2.2798349857,41.615688324],"type":"Point"}
}