{
  "type": "Feature",
  "properties": {
    "addr:full":"Calle de Juan Carlos I, 1 Sanlucar Mayor Sevilla 41800",
    "addr:housenumber":"1",
    "addr:postcode":"41800",
    "addr:street":"Calle De Juan Carlos I",
    "iso:country":"ES",
    "sg:address":"Calle de Juan Carlos I, 1",
    "sg:city":"Sanlucar Mayor",
    "sg:orig_category":"Pescader\u00cdas (al Por Menor)",
    "sg:phone":"+34 955 70 37 55",
    "sg:postcode":"41800",
    "sg:province":"Sevilla",
    "wof:name":"Estudillo Alvarez Marcos Antonio",
    "wof:placetype":"venue"
},
  "geometry": {"coordinates":[-6.2017931938,37.3858032227],"type":"Point"}
}