{
  "type": "Feature",
  "properties": {
    "iso:country":"ES",
    "sg:address":"Martires Nacionales, 5",
    "sg:city":"Burguillos Cerro",
    "sg:orig_category":"Alimentaci\u00d3n General (al Por Menor)",
    "sg:phone":"+34 924 54 11 04",
    "sg:postcode":"06370",
    "sg:province":"Badajoz",
    "wof:name":"Melo Gonzalez Cecilia",
    "wof:placetype":"venue"
},
  "geometry": {"coordinates":[-6.5910739899,38.3806800842],"type":"Point"}
}