{
  "type": "Feature",
  "properties": {
    "addr:full":"Calle de Calderon De La Barca, 4 Oliva Frontera Badajoz 06120",
    "addr:housenumber":"4",
    "addr:postcode":"06120",
    "addr:street":"Calle De Calderon De La Barca",
    "iso:country":"ES",
    "sg:address":"Calle de Calderon De La Barca, 4",
    "sg:city":"Oliva Frontera",
    "sg:orig_category":"Electrodom\u00c9sticos (al Por Menor)",
    "sg:phone":"+34 924 74 08 92",
    "sg:postcode":"06120",
    "sg:province":"Badajoz",
    "wof:name":"Sanchez Delgado Antonio",
    "wof:placetype":"venue"
},
  "geometry": {"coordinates":[-6.9184288979,38.2772521973],"type":"Point"}
}