{
  "type": "Feature",
  "properties": {
    "iso:country":"ES",
    "sg:address":"Carrer de Granollers, 5",
    "sg:city":"Barcelona",
    "sg:classifiers":[
        {
            "category":"Casinos & Gambling",
            "type":"Entertainment"
        }
    ],
    "sg:phone":"+34 934 20 87 54",
    "sg:postcode":"08032",
    "sg:province":"Barcelona",
    "sg:tags":[
        "locale",
        "de",
        "juego"
    ],
    "wof:name":"Xuli Park S.l.",
    "wof:placetype":"venue"
},
  "geometry": {"coordinates":[2.1629219055,41.4282302856],"type":"Point"}
}