{
  "type": "Feature",
  "properties": {
    "iso:country":"ES",
    "sg:address":"Carr Cavallers, 2",
    "sg:city":"Algaida",
    "sg:orig_category":"Acondicionamiento De Terrenos Para Deporte Y Juegos",
    "sg:phone":"+34 971 12 56 78",
    "sg:postcode":"07210",
    "sg:province":"Islas Baleares",
    "wof:name":"Ajuntament D'algaida",
    "wof:placetype":"venue"
},
  "geometry": {"coordinates":[2.8988728523,39.5580940247],"type":"Point"}
}