{
  "type": "Feature",
  "properties": {
    "iso:country":"ES",
    "sg:address":"Calle de Fontanilla, 46",
    "sg:city":"Beas",
    "sg:orig_category":"Venta, Montaje De Neum\u00c1ticos",
    "sg:phone":"+34 959 30 84 04",
    "sg:postcode":"21630",
    "sg:province":"Huelva",
    "wof:name":"Lobo Cruz Santiago",
    "wof:placetype":"venue"
},
  "geometry": {"coordinates":[-6.7933101654,37.4354248047],"type":"Point"}
}