{
  "type": "Feature",
  "properties": {
    "iso:country":"ES",
    "sg:address":"Rua San Pedro De Mezonzo (de), 43",
    "sg:city":"Santiago De Compostela",
    "sg:orig_category":"Abogados",
    "sg:phone":"+34 981 59 69 39",
    "sg:postcode":"15701",
    "sg:province":"La Coru\u00f1a",
    "wof:name":"Sanchez-agustino Mari\u00f1o Javier",
    "wof:placetype":"venue"
},
  "geometry": {"coordinates":[-8.5465297699,42.8706588745],"type":"Point"}
}