{
  "type": "Feature",
  "properties": {
    "addr:full":"Carrer de Francesc Macia, 160 Granollers Barcelona 08401",
    "addr:housenumber":"160",
    "addr:postcode":"08401",
    "addr:street":"Carrer De Francesc Macia",
    "iso:country":"ES",
    "sg:address":"Carrer de Francesc Macia, 160",
    "sg:city":"Granollers",
    "sg:orig_category":"Molduras, Junquillos, Listones Y Molduras Perforadas",
    "sg:phone":"+34 938 60 07 98",
    "sg:postcode":"08401",
    "sg:province":"Barcelona",
    "wof:name":"Carvajal Garcia Jose",
    "wof:placetype":"venue"
},
  "geometry": {"coordinates":[2.2866220474,41.5983886719],"type":"Point"}
}