{
  "type": "Feature",
  "properties": {
    "iso:country":"ES",
    "sg:address":"Calle de Federico Rubio, 4",
    "sg:city":"Sevilla",
    "sg:orig_category":"Asociaciones, Organismos Culturales Y Socioeducativos",
    "sg:phone":"+34 954 22 68 69",
    "sg:postcode":"41004",
    "sg:province":"Sevilla",
    "wof:name":"Hermandad Maria Santisima De La Candelaria",
    "wof:placetype":"venue"
},
  "geometry": {"coordinates":[-5.9893889427,37.3880805969],"type":"Point"}
}