{
  "type": "Feature",
  "properties": {
    "iso:country":"ES",
    "sg:address":"Camino Los Eriales, S/n",
    "sg:city":"Maracena",
    "sg:orig_category":"Aparatos, Sistemas De Tele",
    "sg:phone":"+34 958 40 46 63",
    "sg:postcode":"18200",
    "sg:province":"Granada",
    "wof:name":"Instalaciones De Seguridad Del Sur S.l.l",
    "wof:placetype":"venue"
},
  "geometry": {"coordinates":[-3.6494691372,37.2105865479],"type":"Point"}
}