{
  "type": "Feature",
  "properties": {
    "addr:full":"Calle de San Andres, 5 Almargen M\u00e1laga 29330",
    "addr:postcode":"29330",
    "addr:street":"Calle De San Andres 5 Almargen Ma\u0301Laga",
    "iso:country":"ES",
    "sg:address":"Calle de San Andres, 5",
    "sg:city":"Almargen",
    "sg:orig_category":"Electromec\u00c1nica",
    "sg:phone":"+34 952 18 22 39",
    "sg:postcode":"29330",
    "sg:province":"M\u00e1laga",
    "wof:name":"Ramirez Guerrero Jesus",
    "wof:placetype":"venue"
},
  "geometry": {"coordinates":[-5.0204467773,37.0040054321],"type":"Point"}
}