{
  "type": "Feature",
  "properties": {
    "addr:full":"Calle de Placido Pe\u00d1a, 63 Vilalba Lugo 27800",
    "addr:housenumber":"63",
    "addr:postcode":"27800",
    "addr:street":"Calle De Placido Pen\u0303A",
    "iso:country":"ES",
    "sg:address":"Calle de Placido Pe\u00d1a, 63",
    "sg:city":"Vilalba",
    "sg:orig_category":"Peluquer\u00cdas, Peluquer\u00cda Mixta",
    "sg:phone":"+34 982 51 13 38",
    "sg:postcode":"27800",
    "sg:province":"Lugo",
    "wof:name":"Lopez Carballeira Antonio",
    "wof:placetype":"venue"
},
  "geometry": {"coordinates":[-7.6791801453,43.3012008667],"type":"Point"}
}