{
  "type": "Feature",
  "properties": {
    "iso:country":"ES",
    "sg:address":"Carr Subida Al Convento, S/n",
    "sg:city":"Beniganim",
    "sg:orig_category":"Organizaci\u00d3n De Actos, Seminarios Y Congresos",
    "sg:phone":"+34 962 21 61 92",
    "sg:postcode":"46830",
    "sg:province":"Valencia",
    "wof:name":"Salones Garden J.j. S.l.",
    "wof:placetype":"venue"
},
  "geometry": {"coordinates":[-0.444671005,38.9410247803],"type":"Point"}
}