{
  "type": "Feature",
  "properties": {
    "addr:full":"Carr Sant Francesc, 51 Olleria Valencia 46850",
    "addr:housenumber":"51",
    "addr:postcode":"46850",
    "addr:street":"Carr Sant Francesc",
    "iso:country":"ES",
    "sg:address":"Carr Sant Francesc, 51",
    "sg:city":"Olleria",
    "sg:orig_category":"Florister\u00cdas",
    "sg:phone":"+34 962 20 01 13",
    "sg:postcode":"46850",
    "sg:province":"Valencia",
    "wof:name":"Juan Garcia Maria Loreto",
    "wof:placetype":"venue"
},
  "geometry": {"coordinates":[-0.5478360057,38.9096603394],"type":"Point"}
}