{
  "type": "Feature",
  "properties": {
    "iso:country":"ES",
    "sg:address":"Diego Cambreleng Mesa, 12",
    "sg:city":"Telde",
    "sg:orig_category":"Puertas Autom\u00c1ticas, Puertas De Garaje",
    "sg:phone":"+34 928 69 94 00",
    "sg:postcode":"35200",
    "sg:province":"Las Palmas",
    "wof:name":"Lopez Mayor S.l.",
    "wof:placetype":"venue"
},
  "geometry": {"coordinates":[-15.418759346,28.0002098083],"type":"Point"}
}