{
  "type": "Feature",
  "properties": {
    "addr:full":"Plaz Juez Borrull, 1 Castellon Castell\u00f3n 12003",
    "addr:housenumber":"1",
    "addr:postcode":"12003",
    "addr:street":"Plaz;Borrull;Castello\u0301N",
    "iso:country":"ES",
    "sg:address":"Plaz Juez Borrull, 1",
    "sg:city":"Castellon",
    "sg:orig_category":"Universidades",
    "sg:phone":"+34 964 26 02 40",
    "sg:postcode":"12003",
    "sg:province":"Castell\u00f3n",
    "wof:name":"Centro Universitario Deymos S.l.l.",
    "wof:placetype":"venue"
},
  "geometry": {"coordinates":[-0.0351019986,39.9842643738],"type":"Point"}
}