{
  "type": "Feature",
  "properties": {
    "addr:full":"Carrer de Lope De Vega, 111 Barcelona Barcelona 08005",
    "addr:housenumber":"111",
    "addr:postcode":"08005",
    "addr:street":"Carrer De Lope De Vega",
    "iso:country":"ES",
    "sg:address":"Carrer de Lope De Vega, 111",
    "sg:city":"Barcelona",
    "sg:orig_category":"Comercio De Piezas De Recambio Y De Accesorios De Veh\u00cdculos, Veh\u00cdculos Industriales",
    "sg:phone":"+34 933 07 09 81",
    "sg:postcode":"08005",
    "sg:province":"Barcelona",
    "wof:name":"Tura Soler Antonio",
    "wof:placetype":"venue"
},
  "geometry": {"coordinates":[2.2024838924,41.405090332],"type":"Point"}
}