{
  "type": "Feature",
  "properties": {
    "iso:country":"ES",
    "sg:address":"Calle de Ribera Del Genil, 6",
    "sg:city":"Granada",
    "sg:orig_category":"Ense\u00d1anza: Idiomas",
    "sg:phone":"+34 958 01 01 73",
    "sg:postcode":"18005",
    "sg:province":"Granada",
    "sg:website":"www.shm.edu",
    "wof:name":"Sociedad Hispano Mundial De Idiomas S.l",
    "wof:placetype":"venue"
},
  "geometry": {"coordinates":[-3.5980489254,37.1713294983],"type":"Point"}
}