{
  "type": "Feature",
  "properties": {
    "addr:full":"Crrd Capuchinos, 6 Andujar Ja\u00e9n 23740",
    "addr:postcode":"23740",
    "addr:street":"Jae\u0301N",
    "iso:country":"ES",
    "sg:address":"Crrd Capuchinos, 6",
    "sg:city":"Andujar",
    "sg:orig_category":"Ropa Para Se\u00d1oras (al Por Menor)",
    "sg:phone":"+34 953 50 29 27",
    "sg:postcode":"23740",
    "sg:province":"Ja\u00e9n",
    "wof:name":"Casas Arellano Valentina",
    "wof:placetype":"venue"
},
  "geometry": {"coordinates":[-4.0515098572,38.0363922119],"type":"Point"}
}