{
  "type": "Feature",
  "properties": {
    "addr:full":"Carr Valencia, 18 Eliana Valencia 46183",
    "addr:housenumber":"18",
    "addr:postcode":"46183",
    "addr:street":"Carr Valencia",
    "iso:country":"ES",
    "sg:address":"Carr Valencia, 18",
    "sg:city":"Eliana",
    "sg:orig_category":"Peluqueros: De Se\u00d1oras",
    "sg:phone":"+34 961 65 50 37",
    "sg:postcode":"46183",
    "sg:province":"Valencia",
    "wof:name":"Mary Estilistas S.a.",
    "wof:placetype":"venue"
},
  "geometry": {"coordinates":[-0.528208971,39.5667457581],"type":"Point"}
}