{
  "type": "Feature",
  "properties": {
    "addr:full":"Avda General Peron, 25 Madrid Madrid 28020",
    "addr:housenumber":"25",
    "addr:postcode":"madrid;28020",
    "addr:street":"Avda General Peron",
    "iso:country":"ES",
    "sg:address":"Avda General Peron, 25",
    "sg:city":"Madrid",
    "sg:orig_category":"Institutos De Belleza",
    "sg:phone":"+34 915 56 04 16",
    "sg:postcode":"28020",
    "sg:province":"Madrid",
    "wof:name":"Parrondo Panpin Marcial",
    "wof:placetype":"venue"
},
  "geometry": {"coordinates":[-3.6935670376,40.4524307251],"type":"Point"}
}