{
  "type": "Feature",
  "properties": {
    "iso:country":"ES",
    "sg:address":"Calle de Narciso Yepes, 7",
    "sg:city":"San Mateo",
    "sg:classifiers":[
        {
            "category":"Casinos & Gambling",
            "type":"Entertainment"
        }
    ],
    "sg:phone":"+34 968 47 70 44",
    "sg:postcode":"30800",
    "sg:province":"Murcia",
    "sg:tags":[
        "locale",
        "de",
        "juego"
    ],
    "wof:name":"Asociacion Eduteca",
    "wof:placetype":"venue"
},
  "geometry": {"coordinates":[-1.1298867464,37.9834747314],"type":"Point"}
}