{
  "type": "Feature",
  "properties": {
    "iso:country":"ES",
    "sg:address":"Cami Raimat, S/n",
    "sg:city":"Alpicat",
    "sg:orig_category":"Almacenes Frigor\u00cdficos",
    "sg:phone":"+34 973 73 66 53",
    "sg:postcode":"25110",
    "sg:province":"Lleida",
    "wof:name":"Agrufruto S. A.",
    "wof:placetype":"venue"
},
  "geometry": {"coordinates":[0.5412369967,41.663520813],"type":"Point"}
}