{
  "type": "Feature",
  "properties": {
    "addr:full":"Calle de Roqueta, 6 Albelda Huesca 22558",
    "addr:housenumber":"6",
    "addr:postcode":"22558",
    "addr:street":"Calle De Roqueta",
    "iso:country":"ES",
    "sg:address":"Calle de Roqueta, 6",
    "sg:city":"Albelda",
    "sg:orig_category":"Maquinaria Para Industrias Diversas",
    "sg:phone":"+34 974 42 00 95",
    "sg:postcode":"22558",
    "sg:province":"Huesca",
    "wof:name":"Muro Monesma Jose",
    "wof:placetype":"venue"
},
  "geometry": {"coordinates":[0.4628329873,41.8645324707],"type":"Point"}
}