{
  "type": "Feature",
  "properties": {
    "addr:full":"Av Can Roses, S/n Rubi Barcelona 08191",
    "addr:housenumber":"/ n",
    "addr:postcode":"08191",
    "addr:street":"Av",
    "iso:country":"ES",
    "sg:address":"Av Can Roses, S/n",
    "sg:city":"Rubi",
    "sg:orig_category":"Materias Pl\u00c1sticas: Art\u00cdculos Para La Industria",
    "sg:phone":"+34 935 86 20 10",
    "sg:postcode":"08191",
    "sg:province":"Barcelona",
    "sg:website":"www.arpol.com",
    "wof:name":"Uniones Arpol S. A.",
    "wof:placetype":"venue"
},
  "geometry": {"coordinates":[2.0436809063,41.5048446655],"type":"Point"}
}