{
  "type": "Feature",
  "properties": {
    "addr:full":"Calle de Paloma, 15 Burgos Burgos 09003",
    "addr:housenumber":"15",
    "addr:postcode":"09003",
    "addr:street":"Calle De Paloma",
    "iso:country":"ES",
    "sg:address":"Calle de Paloma, 15",
    "sg:city":"Burgos",
    "sg:orig_category":"Bisuter\u00cda, Joyer\u00cda, Relojer\u00cda (al Por Menor)",
    "sg:phone":"+34 947 20 63 38",
    "sg:postcode":"09003",
    "sg:province":"Burgos",
    "wof:name":"De La Villa Saiz Maria Ines",
    "wof:placetype":"venue"
},
  "geometry": {"coordinates":[-3.7028040886,42.34116745],"type":"Point"}
}