{
  "type": "Feature",
  "properties": {
    "addr:full":"Calle de Viriato, 15 Linares Ja\u00e9n 23700",
    "addr:housenumber":"15",
    "addr:postcode":"23700",
    "addr:street":"Calle De Viriato;Jae\u0301N",
    "iso:country":"ES",
    "sg:address":"Calle de Viriato, 15",
    "sg:city":"Linares",
    "sg:orig_category":"Telas Y Sedas (al Por Menor)",
    "sg:phone":"+34 953 69 10 59",
    "sg:postcode":"23700",
    "sg:province":"Ja\u00e9n",
    "wof:name":"Quesada Molina Agustin",
    "wof:placetype":"venue"
},
  "geometry": {"coordinates":[-3.6310269833,38.0949440002],"type":"Point"}
}