{
  "type": "Feature",
  "properties": {
    "iso:country":"ES",
    "sg:address":"Rua Romil, 12",
    "sg:city":"Vigo",
    "sg:orig_category":"Pescader\u00cdas (al Por Mayor)",
    "sg:phone":"+34 986 24 77 04",
    "sg:postcode":"36202",
    "sg:province":"Pontevedra",
    "wof:name":"Redmond Shipping Limited",
    "wof:placetype":"venue"
},
  "geometry": {"coordinates":[-8.72960186,42.2333602905],"type":"Point"}
}