{
  "type": "Feature",
  "properties": {
    "iso:country":"ES",
    "sg:address":"Calle de Gran Via, 69",
    "sg:city":"Madrid",
    "sg:orig_category":"Traductores",
    "sg:phone":"+34 915 59 62 91",
    "sg:postcode":"28013",
    "sg:province":"Madrid",
    "wof:name":"Sirk Idiomas S.l.",
    "wof:placetype":"venue"
},
  "geometry": {"coordinates":[-3.7103259563,40.4229354858],"type":"Point"}
}