{
  "type": "Feature",
  "properties": {
    "addr:full":"Calle de Mombeltran, 15 Lanzahita \u00c1vila 05490",
    "addr:housenumber":"15",
    "addr:postcode":"05490",
    "addr:street":"Calle De Mombeltran;A\u0301Vila",
    "iso:country":"ES",
    "sg:address":"Calle de Mombeltran, 15",
    "sg:city":"Lanzahita",
    "sg:orig_category":"Contenedores (mercanc\u00cdas)",
    "sg:phone":"+34 920 37 86 21",
    "sg:postcode":"05490",
    "sg:province":"\u00c1vila",
    "wof:name":"Transportes Y Maderas Mane S.l.",
    "wof:placetype":"venue"
},
  "geometry": {"coordinates":[-4.9352030754,40.2055053711],"type":"Point"}
}