{
  "type": "Feature",
  "properties": {
    "addr:full":"Calle de Gregorio Maria Ferro, 13 Moron Frontera Sevilla 41530",
    "addr:housenumber":"13",
    "addr:postcode":"41530",
    "addr:street":"Calle De Gregorio Maria Ferro",
    "iso:country":"ES",
    "sg:address":"Calle de Gregorio Maria Ferro, 13",
    "sg:city":"Moron Frontera",
    "sg:orig_category":"Empresas De Carpinter\u00cda Met\u00c1lica",
    "sg:phone":"+34 955 85 24 85",
    "sg:postcode":"41530",
    "sg:province":"Sevilla",
    "wof:name":"Carpinteria Metalica La Verdad S.l.",
    "wof:placetype":"venue"
},
  "geometry": {"coordinates":[-5.4575209618,37.1199607849],"type":"Point"}
}