{
  "type": "Feature",
  "properties": {
    "addr:full":"Calle de Imeldo Seris, 51 Santa Cruz De Tenerife Santa Cruz De Tenerife 38003",
    "addr:housenumber":"51",
    "addr:postcode":"38003",
    "addr:street":"Calle De Imeldo Seris",
    "iso:country":"ES",
    "sg:address":"Calle de Imeldo Seris, 51",
    "sg:city":"Santa Cruz De Tenerife",
    "sg:orig_category":"Confiter\u00cdas, Chocolater\u00cdas (al Por Menor)",
    "sg:phone":"+34 922 28 09 03",
    "sg:postcode":"38003",
    "sg:province":"Santa Cruz De Tenerife",
    "wof:name":"Chialc S.l.l",
    "wof:placetype":"venue"
},
  "geometry": {"coordinates":[-16.2535533905,28.4671936035],"type":"Point"}
}