{
  "type": "Feature",
  "properties": {
    "addr:full":"Carrer de Catalunya, 48 Terrassa Barcelona 08225",
    "addr:housenumber":"48",
    "addr:postcode":"08225",
    "addr:street":"Carrer De Catalunya",
    "iso:country":"ES",
    "sg:address":"Carrer de Catalunya, 48",
    "sg:city":"Terrassa",
    "sg:orig_category":"Electricidad: Equipos Industriales, Componentes (fabricaci\u00d3n)",
    "sg:phone":"+34 937 35 20 18",
    "sg:postcode":"08225",
    "sg:province":"Barcelona",
    "wof:name":"Euroelectric Egara S.l.",
    "wof:placetype":"venue"
},
  "geometry": {"coordinates":[2.0136198997,41.5717201233],"type":"Point"}
}