{
  "type": "Feature",
  "properties": {
    "addr:full":"Calle de Preceptores, 14 Loja Granada 18300",
    "addr:housenumber":"14 loja",
    "addr:postcode":"18300",
    "addr:street":"Calle De Preceptores",
    "iso:country":"ES",
    "sg:address":"Calle de Preceptores, 14",
    "sg:city":"Loja",
    "sg:orig_category":"Librer\u00cdas",
    "sg:phone":"+34 958 32 51 08",
    "sg:postcode":"18300",
    "sg:province":"Granada",
    "wof:name":"Bautista Mata Ascension",
    "wof:placetype":"venue"
},
  "geometry": {"coordinates":[-4.1500692368,37.1644210815],"type":"Point"}
}