{
  "type": "Feature",
  "properties": {
    "iso:country":"ES",
    "sg:address":"Calle de Cura Sama, 2",
    "sg:city":"Gijon",
    "sg:orig_category":"Agentes Generales De Seguros",
    "sg:phone":"+34 985 35 85 90",
    "sg:postcode":"33202",
    "sg:province":"Asturias",
    "sg:website":"www.cafseguros.com",
    "wof:name":"Escuela Enriquez Sebastian",
    "wof:placetype":"venue"
},
  "geometry": {"coordinates":[-5.6571583748,43.5402412415],"type":"Point"}
}