{
  "type": "Feature",
  "properties": {
    "addr:full":"Rond Cerdanya, 15 Mataro Barcelona 08303",
    "addr:housenumber":"15",
    "addr:postcode":"08303",
    "addr:street":"Mataro Barcelona",
    "iso:country":"ES",
    "sg:address":"Rond Cerdanya, 15",
    "sg:city":"Mataro",
    "sg:orig_category":"Platos Preparados Refrigerados (fabricaci\u00d3n, Al Por Mayor)",
    "sg:phone":"+34 937 98 24 41",
    "sg:postcode":"08303",
    "sg:province":"Barcelona",
    "wof:name":"Iglesias Conde Vanesa",
    "wof:placetype":"venue"
},
  "geometry": {"coordinates":[2.4229540825,41.541595459],"type":"Point"}
}