{
  "type": "Feature",
  "properties": {
    "addr:full":"Calle de Tejeras, 4 Logro\u00f1o La Rioja 26007",
    "addr:housenumber":"4",
    "addr:postcode":"26007",
    "addr:street":"Calle De Tejeras;Rioja",
    "iso:country":"ES",
    "sg:address":"Calle de Tejeras, 4",
    "sg:city":"Logro\u00f1o",
    "sg:orig_category":"Agencias De Viajes",
    "sg:phone":"+34 941 20 30 78",
    "sg:postcode":"26007",
    "sg:province":"La Rioja",
    "sg:website":"www.halconviajes.com",
    "wof:name":"Viajes Halcon S.a.",
    "wof:placetype":"venue"
},
  "geometry": {"coordinates":[-2.5187389851,42.4914894104],"type":"Point"}
}