{
  "type": "Feature",
  "properties": {
    "addr:full":"Carretera De Zarza De Granadilla, S/n Casas Monte C\u00e1ceres 10730",
    "addr:housenumber":"s / n",
    "addr:postcode":"10730",
    "addr:street":"Carretera De Zarza;Granadilla;Ca\u0301Ceres",
    "iso:country":"ES",
    "sg:address":"Carretera De Zarza De Granadilla, S/n",
    "sg:city":"Casas Monte",
    "sg:orig_category":"Producci\u00d3n, Venta De Productos De Agricultura Biol\u00d3gica",
    "sg:phone":"+34 927 17 90 35",
    "sg:postcode":"10730",
    "sg:province":"C\u00e1ceres",
    "wof:name":"Cooperativa San Marcos",
    "wof:placetype":"venue"
},
  "geometry": {"coordinates":[-5.9633669853,40.2041282654],"type":"Point"}
}