{
  "type": "Feature",
  "properties": {
    "iso:country":"ES",
    "sg:address":"Carr Sant Grau, 19",
    "sg:city":"Caldes Malavella",
    "sg:orig_category":"Pe\u00d1as Y Asociaciones Varias",
    "sg:phone":"+34 972 47 04 05",
    "sg:postcode":"17455",
    "sg:province":"Girona",
    "wof:name":"Associacio De Gent De La Tercera Edat De Caldes De Malavella",
    "wof:placetype":"venue"
},
  "geometry": {"coordinates":[2.8084759712,41.8385391235],"type":"Point"}
}