{
  "type": "Feature",
  "properties": {
    "iso:country":"ES",
    "sg:address":"Carrer de Pablo Neruda, S/n",
    "sg:city":"Guardamar Segura",
    "sg:orig_category":"Empresas De Limpieza",
    "sg:phone":"+34 965 72 92 91",
    "sg:postcode":"03140",
    "sg:province":"Alicante",
    "wof:name":"Conservacion Y Mantenimiento De Viviendas",
    "wof:placetype":"venue"
},
  "geometry": {"coordinates":[-0.6515489817,38.0824394226],"type":"Point"}
}