{
  "type": "Feature",
  "properties": {
    "addr:full":"Calle de Garcia Neira, S/n Crecente Pontevedra 36420",
    "addr:housenumber":"s / n",
    "addr:postcode":"36420",
    "addr:street":"Calle De Garcia Neira",
    "iso:country":"ES",
    "sg:address":"Calle de Garcia Neira, S/n",
    "sg:city":"Crecente",
    "sg:orig_category":"Asilos De Ancianos. Centros Privados",
    "sg:phone":"+34 986 66 63 54",
    "sg:postcode":"36420",
    "sg:province":"Pontevedra",
    "wof:name":"Gestion Y Control Residencial De Galicia S.l.",
    "wof:placetype":"venue"
},
  "geometry": {"coordinates":[-8.225317955,42.1508789062],"type":"Point"}
}