{
  "type": "Feature",
  "properties": {
    "addr:full":"Avda Bravo Murillo, 5 Santa Cruz De Tenerife Santa Cruz De Tenerife 38003",
    "addr:housenumber":"5",
    "addr:postcode":"38003",
    "addr:street":"Avda Bravo Murillo",
    "iso:country":"ES",
    "sg:address":"Avda Bravo Murillo, 5",
    "sg:city":"Santa Cruz De Tenerife",
    "sg:orig_category":"Supermercados Y Hipermercados",
    "sg:phone":"+34 922 27 12 94",
    "sg:postcode":"38003",
    "sg:province":"Santa Cruz De Tenerife",
    "wof:name":"Caramelinda S.l.",
    "wof:placetype":"venue"
},
  "geometry": {"coordinates":[-16.3326644897,28.4846744537],"type":"Point"}
}