{
  "type": "Feature",
  "properties": {
    "iso:country":"ES",
    "sg:address":"Ctra Masnou, S/n",
    "sg:city":"Granollers",
    "sg:orig_category":"Chapister\u00cda",
    "sg:phone":"+34 938 70 33 72",
    "sg:postcode":"08402",
    "sg:province":"Barcelona",
    "wof:name":"Lopez Medina Manuel",
    "wof:placetype":"venue"
},
  "geometry": {"coordinates":[2.2855899334,41.592628479],"type":"Point"}
}