{
  "type": "Feature",
  "properties": {
    "addr:full":"C\u00aa Tierz, S/n Pol Ind Tierz-loporzano Huesca 22192",
    "addr:housenumber":"s / n",
    "addr:postcode":"22192",
    "addr:street":"Tierz;Pol Ind Tierz-Loporzano",
    "iso:country":"ES",
    "sg:address":"C\u00aa Tierz, S/n",
    "sg:city":"Pol Ind Tierz-loporzano",
    "sg:orig_category":"Hormigonados",
    "sg:phone":"+34 974 25 20 54",
    "sg:postcode":"22192",
    "sg:province":"Huesca",
    "wof:name":"Hormicemex S A",
    "wof:placetype":"venue"
},
  "geometry": {"coordinates":[-0.3250589967,42.1608390808],"type":"Point"}
}