{
  "type": "Feature",
  "properties": {
    "iso:country":"ES",
    "sg:address":"Calle de Esperantista Hdez. Lahuerta, 2",
    "sg:city":"Valencia",
    "sg:orig_category":"Almazaras",
    "sg:phone":"+34 963 46 70 23",
    "sg:postcode":"46015",
    "sg:province":"Valencia",
    "wof:name":"Giardina Iberica S.l.",
    "wof:placetype":"venue"
},
  "geometry": {"coordinates":[-0.3925459981,39.486995697],"type":"Point"}
}