{
  "type": "Feature",
  "properties": {
    "iso:country":"ES",
    "sg:address":"Calle de Doctor Fleming, 163",
    "sg:city":"Espinos",
    "sg:orig_category":"Venta, Montaje De Neum\u00c1ticos",
    "sg:phone":"+34 928 89 22 45",
    "sg:postcode":"35470",
    "sg:province":"Las Palmas",
    "wof:name":"Navarro Ribero Jose Manuel",
    "wof:placetype":"venue"
},
  "geometry": {"coordinates":[-15.7955989838,27.9892024994],"type":"Point"}
}