{
  "type": "Feature",
  "properties": {
    "iso:country":"ES",
    "sg:address":"Calle de Esca\u00d1uela, S/n",
    "sg:city":"Jaen",
    "sg:orig_category":"Delegados, Agentes De Tr\u00c1nsito, Auxiliares De Transporte Internacional",
    "sg:phone":"+34 953 28 12 07",
    "sg:postcode":"23009",
    "sg:province":"Ja\u00e9n",
    "sg:website":"www.ochoa.es",
    "wof:name":"Transportes Ochoa S.a.",
    "wof:placetype":"venue"
},
  "geometry": {"coordinates":[-3.7871990204,37.7989196777],"type":"Point"}
}