{
  "type": "Feature",
  "properties": {
    "addr:full":"Ctra. Castalla, Km. 0021,0 Tibi Alicante 03109",
    "addr:postcode":"03109",
    "addr:street":"Ctra. Castalla Km. 0021,0",
    "iso:country":"ES",
    "sg:address":"Ctra. Castalla, Km. 0021,0",
    "sg:city":"Tibi",
    "sg:orig_category":"Distribuci\u00d3n De Petr\u00d3leo Y Derivados",
    "sg:phone":"+34 965 61 73 74",
    "sg:postcode":"03109",
    "sg:province":"Alicante",
    "wof:name":"Bevia Santos S.l.",
    "wof:placetype":"venue"
},
  "geometry": {"coordinates":[-0.5752289891,38.5324134827],"type":"Point"}
}