{
  "type": "Feature",
  "properties": {
    "addr:full":"Avda Espa\u00d1a (de), 17 Alcobendas Madrid 28100",
    "addr:housenumber":"17",
    "addr:postcode":"28100",
    "addr:street":"Avda Espan\u0303A De",
    "iso:country":"ES",
    "sg:address":"Avda Espa\u00d1a (de), 17",
    "sg:city":"Alcobendas",
    "sg:orig_category":"Bancos",
    "sg:phone":"+34 916 59 16 92",
    "sg:postcode":"28100",
    "sg:province":"Madrid",
    "wof:name":"R Cable Y Telecomunicaciones Galicia S.a.",
    "wof:placetype":"venue"
},
  "geometry": {"coordinates":[-3.6411879063,40.5473175049],"type":"Point"}
}