{
  "type": "Feature",
  "properties": {
    "addr:full":"Cami Viladegats, 2 Arrabassada I Savinosa Tarragona 43007",
    "addr:housenumber":"2",
    "addr:postcode":"43007",
    "addr:street":"Viladegats",
    "iso:country":"ES",
    "sg:address":"Cami Viladegats, 2",
    "sg:city":"Arrabassada I Savinosa",
    "sg:orig_category":"Cer\u00c1micas: Material Y Suministros",
    "sg:phone":"+34 977 22 19 01",
    "sg:postcode":"43007",
    "sg:province":"Tarragona",
    "wof:name":"Culubret S.l.",
    "wof:placetype":"venue"
},
  "geometry": {"coordinates":[1.2601410151,41.1357688904],"type":"Point"}
}