{
  "type": "Feature",
  "properties": {
    "addr:full":"Calle de Almirante Benitez Inglott, 23 Palmas De Gran Canaria Las Palmas 35011",
    "addr:housenumber":"23",
    "addr:postcode":"35011",
    "addr:street":"Calle De Almirante Benitez Inglott",
    "iso:country":"ES",
    "sg:address":"Calle de Almirante Benitez Inglott, 23",
    "sg:city":"Palmas De Gran Canaria",
    "sg:orig_category":"Molduras, Junquillos, Listones Y Molduras Perforadas",
    "sg:phone":"+34 928 20 79 94",
    "sg:postcode":"35011",
    "sg:province":"Las Palmas",
    "wof:name":"Sistelcom-telemensaje S.a.",
    "wof:placetype":"venue"
},
  "geometry": {"coordinates":[-15.4370517731,28.1129798889],"type":"Point"}
}