{
  "type": "Feature",
  "properties": {
    "addr:full":"Lloc Volta 2, 131 Son Mesquida Islas Baleares 07209",
    "addr:housenumber":"2",
    "addr:postcode":"131;07209",
    "addr:street":"Volta",
    "iso:country":"ES",
    "sg:address":"Lloc Volta 2, 131",
    "sg:city":"Son Mesquida",
    "sg:orig_category":"Oficinas De Turismo, Asociaciones De Iniciativa",
    "sg:phone":"+34 971 18 35 82",
    "sg:postcode":"07209",
    "sg:province":"Islas Baleares",
    "wof:name":"Sureda Vaquer Margalida",
    "wof:placetype":"venue"
},
  "geometry": {"coordinates":[3.1743099689,39.4930686951],"type":"Point"}
}