{
  "type": "Feature",
  "properties": {
    "addr:full":"Calle de Meson (del), 16 Paracuellos De Jarama Madrid 28860",
    "addr:housenumber":"16",
    "addr:postcode":"28860",
    "addr:street":"Calle De Meson Del",
    "iso:country":"ES",
    "sg:address":"Calle de Meson (del), 16",
    "sg:city":"Paracuellos De Jarama",
    "sg:orig_category":"Albergues",
    "sg:phone":"+34 916 58 28 20",
    "sg:postcode":"28860",
    "sg:province":"Madrid",
    "wof:name":"Sanchez Hernandez Nuria",
    "wof:placetype":"venue"
},
  "geometry": {"coordinates":[-3.5325610638,40.5050201416],"type":"Point"}
}