{
  "type": "Feature",
  "properties": {
    "iso:country":"ES",
    "sg:address":"Calle de Calzada, 17",
    "sg:city":"Puertollano",
    "sg:orig_category":"Formaci\u00d3n A Distancia, Por Correspondencia",
    "sg:phone":"+34 926 44 15 54",
    "sg:postcode":"13500",
    "sg:province":"Ciudad Real",
    "sg:website":"www.uned.es",
    "wof:name":"Universidad Nacional De Educacion A Distancia",
    "wof:placetype":"venue"
},
  "geometry": {"coordinates":[-4.1099290848,38.6869659424],"type":"Point"}
}