{
  "type": "Feature",
  "properties": {
    "iso:country":"ES",
    "sg:address":"Prje Casas Del Puerto, S/n",
    "sg:city":"Jumilla",
    "sg:orig_category":"Comerciantes Al Por Mayor De Vinos, Licores Y Alcoholes",
    "sg:phone":"+34 968 75 71 85",
    "sg:postcode":"30520",
    "sg:province":"Murcia",
    "wof:name":"Vicente Poveda Perez De Los Cobos C.b.",
    "wof:placetype":"venue"
},
  "geometry": {"coordinates":[-1.4830360413,38.5444526672],"type":"Point"}
}