{
  "type": "Feature",
  "properties": {
    "iso:country":"ES",
    "sg:address":"Cra. Ribes (sector Can Baldic), 4",
    "sg:city":"Llerona",
    "sg:orig_category":"Importaci\u00d3n",
    "sg:phone":"+34 938 40 43 63",
    "sg:postcode":"08520",
    "sg:province":"Barcelona",
    "wof:name":"Bosch Clavell S.l.",
    "wof:placetype":"venue"
},
  "geometry": {"coordinates":[2.2992899418,41.6361808777],"type":"Point"}
}