{
  "type": "Feature",
  "properties": {
    "addr:full":"Calle de Ayerbe, 3 San Sebastian De Los Reyes Madrid 28700",
    "addr:housenumber":"3",
    "addr:postcode":"28700",
    "addr:street":"Calle De Ayerbe",
    "iso:country":"ES",
    "sg:address":"Calle de Ayerbe, 3",
    "sg:city":"San Sebastian De Los Reyes",
    "sg:orig_category":"Tapiceros Y Tapiceros",
    "sg:phone":"+34 916 53 95 95",
    "sg:postcode":"28700",
    "sg:province":"Madrid",
    "wof:name":"Honrubia Ceibane Inocencio",
    "wof:placetype":"venue"
},
  "geometry": {"coordinates":[-3.6362822056,40.550491333],"type":"Point"}
}