{
  "type": "Feature",
  "properties": {
    "addr:full":"Avda Coru\u00d1a, 87 Betanzos La Coru\u00f1a 15300",
    "addr:housenumber":"87",
    "addr:postcode":"15300",
    "addr:street":"Avda Corun\u0303A;La",
    "iso:country":"ES",
    "sg:address":"Avda Coru\u00d1a, 87",
    "sg:city":"Betanzos",
    "sg:orig_category":"Equipo De Refrigeraci\u00d3n Industrial",
    "sg:phone":"+34 981 77 01 63",
    "sg:postcode":"15300",
    "sg:province":"La Coru\u00f1a",
    "wof:name":"Frigarlo S.l.",
    "wof:placetype":"venue"
},
  "geometry": {"coordinates":[-8.2136793137,43.2823867798],"type":"Point"}
}