{
  "type": "Feature",
  "properties": {
    "iso:country":"ES",
    "sg:address":"Rua Mercado, 33",
    "sg:city":"Ourense",
    "sg:orig_category":"Peluqueros: De Se\u00d1oras",
    "sg:phone":"+34 988 21 95 37",
    "sg:postcode":"32001",
    "sg:province":"Ourense",
    "wof:name":"Lozano Iglesias Rosa",
    "wof:placetype":"venue"
},
  "geometry": {"coordinates":[-7.865032196,42.3484191895],"type":"Point"}
}