{
  "type": "Feature",
  "properties": {
    "iso:country":"ES",
    "sg:address":"Calle de Virgen De Guadalupe, 8",
    "sg:city":"Palmas De Gran Canaria",
    "sg:orig_category":"Alimentaci\u00d3n General (al Por Menor)",
    "sg:phone":"+34 928 25 29 83",
    "sg:postcode":"35013",
    "sg:province":"Las Palmas",
    "wof:name":"Lujan Ojeda Manuel",
    "wof:placetype":"venue"
},
  "geometry": {"coordinates":[-15.4347696304,28.1068286896],"type":"Point"}
}