{
  "type": "Feature",
  "properties": {
    "addr:full":"Pl Dr Ortiz De Landazuri, 4 Iru\u00f1a Navarra 31012",
    "addr:housenumber":"4",
    "addr:postcode":"31012",
    "addr:street":"Pl Dr Ortiz De Landazuri",
    "iso:country":"ES",
    "sg:address":"Pl Dr Ortiz De Landazuri, 4",
    "sg:city":"Iru\u00f1a",
    "sg:orig_category":"Promotores Constructores",
    "sg:phone":"+34 948 26 72 12",
    "sg:postcode":"31012",
    "sg:province":"Navarra",
    "wof:name":"Cid Fernandez Francisco",
    "wof:placetype":"venue"
},
  "geometry": {"coordinates":[-1.6726690531,42.8213882446],"type":"Point"}
}