{
  "type": "Feature",
  "properties": {
    "addr:full":"Calle de Puentecella, 1 Zamora Zamora 49027",
    "addr:housenumber":"1",
    "addr:postcode":"49027",
    "addr:street":"Calle De Puentecella",
    "iso:country":"ES",
    "sg:address":"Calle de Puentecella, 1",
    "sg:city":"Zamora",
    "sg:orig_category":"Distribuci\u00d3n De Petr\u00d3leo Y Derivados",
    "sg:phone":"+34 980 67 03 08",
    "sg:postcode":"49027",
    "sg:province":"Zamora",
    "wof:name":"Pescados Martin Blanco S.l.",
    "wof:placetype":"venue"
},
  "geometry": {"coordinates":[-5.7610769272,41.5046424866],"type":"Point"}
}