{
  "type": "Feature",
  "properties": {
    "addr:full":"C/ Curtidores, 40 Elche Alicante 03203",
    "addr:housenumber":"40",
    "addr:postcode":"03203",
    "addr:street":"C / Curtidores",
    "iso:country":"ES",
    "sg:address":"C/ Curtidores, 40",
    "sg:city":"Elche",
    "sg:orig_category":"Asesor\u00cda Sobre Comunicaci\u00d3n De Empresas",
    "sg:phone":"+34 965 42 52 99",
    "sg:postcode":"03203",
    "sg:province":"Alicante",
    "wof:name":"Vindex Soporte Legal S.l.",
    "wof:placetype":"venue"
},
  "geometry": {"coordinates":[-0.6941490173,38.2619132996],"type":"Point"}
}