{
  "type": "Feature",
  "properties": {
    "iso:country":"ES",
    "sg:address":"Carrer de Josep Darder,metge, 22",
    "sg:city":"Palma",
    "sg:orig_category":"Estancos",
    "sg:phone":"+34 971 27 59 42",
    "sg:postcode":"07008",
    "sg:province":"Islas Baleares",
    "wof:name":"Fuster Rigo Gabriel",
    "wof:placetype":"venue"
},
  "geometry": {"coordinates":[2.6657989025,39.5775756836],"type":"Point"}
}