{
  "type": "Feature",
  "properties": {
    "addr:full":"Carrer de Rossello, 171 Barcelona Barcelona 08036",
    "addr:housenumber":"171",
    "addr:postcode":"08036",
    "addr:street":"Carrer De Rossello",
    "iso:country":"ES",
    "sg:address":"Carrer de Rossello, 171",
    "sg:city":"Barcelona",
    "sg:orig_category":"Contables",
    "sg:phone":"+34 933 21 58 49",
    "sg:postcode":"08036",
    "sg:province":"Barcelona",
    "wof:name":"Sanchez Fuster Amalia",
    "wof:placetype":"venue"
},
  "geometry": {"coordinates":[2.1535539627,41.3906517029],"type":"Point"}
}