{
  "type": "Feature",
  "properties": {
    "iso:country":"ES",
    "sg:address":"Avda Chaparral, 23",
    "sg:city":"San Sebastian De Los Reyes",
    "sg:orig_category":"Ense\u00d1anza Variada",
    "sg:phone":"+34 916 51 47 70",
    "sg:postcode":"28700",
    "sg:province":"Madrid",
    "wof:name":"Academia Olimpia S.l.",
    "wof:placetype":"venue"
},
  "geometry": {"coordinates":[-3.6305806637,40.5510902405],"type":"Point"}
}