{
  "type": "Feature",
  "properties": {
    "iso:country":"ES",
    "sg:address":"Carrer de Muses, 18",
    "sg:city":"Hospitalet Llobregat",
    "sg:orig_category":"Fabricaci\u00d3n De Juegos Y Juguetes",
    "sg:phone":"+34 934 40 95 05",
    "sg:postcode":"08905",
    "sg:province":"Barcelona",
    "wof:name":"Domingo Barona Maribel",
    "wof:placetype":"venue"
},
  "geometry": {"coordinates":[2.1136140823,41.3702163696],"type":"Point"}
}