{
  "type": "Feature",
  "properties": {
    "iso:country":"ES",
    "sg:address":"Calle de Lagasca, S/n",
    "sg:city":"San Pedro Alcantara",
    "sg:orig_category":"Art\u00cdculos De Decoraci\u00d3n",
    "sg:phone":"+34 952 78 15 34",
    "sg:postcode":"29670",
    "sg:province":"M\u00e1laga",
    "wof:name":"Sprawson  Sandra",
    "wof:placetype":"venue"
},
  "geometry": {"coordinates":[-4.9899687767,36.4859237671],"type":"Point"}
}