{
  "type": "Feature",
  "properties": {
    "addr:full":"Avda Madrid, 37 Palencia Palencia 34004",
    "addr:housenumber":"37",
    "addr:postcode":"34004",
    "addr:street":"Avda Madrid",
    "iso:country":"ES",
    "sg:address":"Avda Madrid, 37",
    "sg:city":"Palencia",
    "sg:orig_category":"Tiendas De Grano, Frutas Y Legumbres Secas (al Por Menor)",
    "sg:phone":"+34 979 71 04 00",
    "sg:postcode":"34004",
    "sg:province":"Palencia",
    "wof:name":"Productos Alimenticios Belros S.a.",
    "wof:placetype":"venue"
},
  "geometry": {"coordinates":[-4.5202989578,41.9938316345],"type":"Point"}
}