{
  "type": "Feature",
  "properties": {
    "iso:country":"ES",
    "sg:address":"Cta. Palencia, 7",
    "sg:city":"Astudillo",
    "sg:orig_category":"Empresas De Carpinter\u00cda Met\u00c1lica",
    "sg:phone":"+34 979 82 22 83",
    "sg:postcode":"34450",
    "sg:province":"Palencia",
    "wof:name":"Carton Diez Julian",
    "wof:placetype":"venue"
},
  "geometry": {"coordinates":[-4.2987589836,42.1923675537],"type":"Point"}
}