{
  "type": "Feature",
  "properties": {
    "iso:country":"ES",
    "sg:address":"Calle de Rafael Perez De Guzman, 1",
    "sg:city":"Cordoba",
    "sg:orig_category":"Reposter\u00cdas",
    "sg:phone":"+34 957 45 12 32",
    "sg:postcode":"14005",
    "sg:province":"C\u00f3rdoba",
    "wof:name":"Hidalgo Cambas Jorge",
    "wof:placetype":"venue"
},
  "geometry": {"coordinates":[-4.7965908051,37.8810005188],"type":"Point"}
}