{
  "type": "Feature",
  "properties": {
    "iso:country":"ES",
    "sg:address":"Barr Goitondo, 5",
    "sg:city":"Berano Nagusi",
    "sg:orig_category":"Agencias Y Asesores De Publicidad",
    "sg:phone":"+34 943 17 39 11",
    "sg:postcode":"48269",
    "sg:province":"Vizcaya",
    "wof:name":"Montajes Oizubi S.l.",
    "wof:placetype":"venue"
},
  "geometry": {"coordinates":[-2.5300109386,43.1897888184],"type":"Point"}
}