{
  "type": "Feature",
  "properties": {
    "addr:full":"Carrer de Muntaner, 305 Barcelona Barcelona 08021",
    "addr:housenumber":"305",
    "addr:postcode":"08021",
    "addr:street":"Carrer De Muntaner",
    "iso:country":"ES",
    "sg:address":"Carrer de Muntaner, 305",
    "sg:city":"Barcelona",
    "sg:orig_category":"Cl\u00cdnicas M\u00c9dicas",
    "sg:phone":"+34 934 88 12 00",
    "sg:postcode":"08021",
    "sg:province":"Barcelona",
    "wof:name":"Fernandez Martinez Alfonso",
    "wof:placetype":"venue"
},
  "geometry": {"coordinates":[2.145761013,41.3968467712],"type":"Point"}
}