{
  "type": "Feature",
  "properties": {
    "addr:full":"Pla\u00c7 Joan Carreras Dagas, 1 Bisbal D'emporda Girona 17100",
    "addr:housenumber":"1",
    "addr:postcode":"17100",
    "addr:street":"Joan;Dagas",
    "iso:country":"ES",
    "sg:address":"Pla\u00c7 Joan Carreras Dagas, 1",
    "sg:city":"Bisbal D'emporda",
    "sg:orig_category":"Agencias De Viajes",
    "sg:phone":"+34 972 64 26 91",
    "sg:postcode":"17100",
    "sg:province":"Girona",
    "wof:name":"Viatges Bisbal Tours S.l.",
    "wof:placetype":"venue"
},
  "geometry": {"coordinates":[2.813131094,41.9749221802],"type":"Point"}
}