{
  "type": "Feature",
  "properties": {
    "addr:full":"Calle de Mallorca, 7 Palmas De Gran Canaria Las Palmas 35013",
    "addr:housenumber":"7",
    "addr:postcode":"35013",
    "addr:street":"Calle De Mallorca",
    "iso:country":"ES",
    "sg:address":"Calle de Mallorca, 7",
    "sg:city":"Palmas De Gran Canaria",
    "sg:orig_category":"Molduras, Junquillos, Listones Y Molduras Perforadas",
    "sg:phone":"+34 928 41 00 16",
    "sg:postcode":"35013",
    "sg:province":"Las Palmas",
    "wof:name":"Garcia Garcia Felix",
    "wof:placetype":"venue"
},
  "geometry": {"coordinates":[-15.4505491257,28.0952014923],"type":"Point"}
}