{
  "type": "Feature",
  "properties": {
    "addr:full":"Carr Conquista, La, 3 Eliana Valencia 46183",
    "addr:housenumber":"3",
    "addr:postcode":"46183",
    "addr:street":"Carr Conquista La",
    "iso:country":"ES",
    "sg:address":"Carr Conquista, La, 3",
    "sg:city":"Eliana",
    "sg:orig_category":"Ingenier\u00cda, Centros De Estudios (diversos)",
    "sg:phone":"+34 962 75 04 41",
    "sg:postcode":"46183",
    "sg:province":"Valencia",
    "wof:name":"Lloder Group S.l.",
    "wof:placetype":"venue"
},
  "geometry": {"coordinates":[-0.528208971,39.5667457581],"type":"Point"}
}