{
  "type": "Feature",
  "properties": {
    "addr:full":"Calle de Jose Ojeda, 42 Roquetas Mar Almer\u00eda 04740",
    "addr:housenumber":"42",
    "addr:postcode":"04740",
    "addr:street":"Calle De Jose Ojeda;Mar Almeri\u0301A",
    "iso:country":"ES",
    "sg:address":"Calle de Jose Ojeda, 42",
    "sg:city":"Roquetas Mar",
    "sg:orig_category":"Electricidad: Instaladores",
    "sg:phone":"+34 950 32 91 83",
    "sg:postcode":"04740",
    "sg:province":"Almer\u00eda",
    "wof:name":"Pinart Fernandez Cristobal",
    "wof:placetype":"venue"
},
  "geometry": {"coordinates":[-2.6065790653,36.7597007751],"type":"Point"}
}