{
  "type": "Feature",
  "properties": {
    "addr:full":"Calle de Doctor Jesus Galan, 50 Avila \u00c1vila 05003",
    "addr:housenumber":"50",
    "addr:postcode":"05003",
    "addr:street":"Calle De Doctor Jesus Galan;A\u0301Vila",
    "iso:country":"ES",
    "sg:address":"Calle de Doctor Jesus Galan, 50",
    "sg:city":"Avila",
    "sg:orig_category":"Telas Y Sedas (al Por Menor)",
    "sg:phone":"+34 920 22 96 61",
    "sg:postcode":"05003",
    "sg:province":"\u00c1vila",
    "wof:name":"Nu\u00f1ez Diaz Santiago",
    "wof:placetype":"venue"
},
  "geometry": {"coordinates":[-4.6971635818,40.6506004333],"type":"Point"}
}