{
  "type": "Feature",
  "properties": {
    "iso:country":"ES",
    "sg:address":"Carrer de L'harmonia, 33",
    "sg:city":"Barcelona",
    "sg:orig_category":"Edici\u00d3n De Diarios, Revistas, Boletines",
    "sg:phone":"+34 934 28 66 14",
    "sg:postcode":"08035",
    "sg:province":"Barcelona",
    "wof:name":"Abarca Nidegger Leandro",
    "wof:placetype":"venue"
},
  "geometry": {"coordinates":[2.141482,41.434216],"type":"Point"}
}