{
  "type": "Feature",
  "properties": {
    "addr:full":"T. P. Carranza, 26 Lumbrales Salamanca 37240",
    "addr:housenumber":"26",
    "addr:postcode":"37240",
    "addr:street":"T. P. Carranza",
    "iso:country":"ES",
    "sg:address":"T. P. Carranza, 26",
    "sg:city":"Lumbrales",
    "sg:orig_category":"Muebles, Minoristas",
    "sg:phone":"+34 923 51 20 47",
    "sg:postcode":"37240",
    "sg:province":"Salamanca",
    "wof:name":"Olivera Robledo Manuel",
    "wof:placetype":"venue"
},
  "geometry": {"coordinates":[-6.7207489014,40.9344139099],"type":"Point"}
}