{
  "type": "Feature",
  "properties": {
    "addr:full":"Calle de Alvaro Florez Estrada, 19 Oviedo Asturias 33006",
    "addr:housenumber":"19",
    "addr:postcode":"33006",
    "addr:street":"Calle De Alvaro Florez Estrada",
    "iso:country":"ES",
    "sg:address":"Calle de Alvaro Florez Estrada, 19",
    "sg:city":"Oviedo",
    "sg:orig_category":"M\u00c9dicos: Ginecolog\u00cda Y Obstetricia",
    "sg:phone":"+34 985 25 55 73",
    "sg:postcode":"33006",
    "sg:province":"Asturias",
    "wof:name":"Rodriguez Alvarez Jose Maria Alberto",
    "wof:placetype":"venue"
},
  "geometry": {"coordinates":[-5.8614435196,43.356426239],"type":"Point"}
}