{
  "type": "Feature",
  "properties": {
    "addr:full":"Calle de Infantes, 20 Villarrobledo Albacete 02600",
    "addr:housenumber":"20",
    "addr:postcode":"02600",
    "addr:street":"Calle De Infantes",
    "iso:country":"ES",
    "sg:address":"Calle de Infantes, 20",
    "sg:city":"Villarrobledo",
    "sg:orig_category":"Plomeros",
    "sg:phone":"+34 967 14 09 31",
    "sg:postcode":"02600",
    "sg:province":"Albacete",
    "wof:name":"Melero Calero Sebastian",
    "wof:placetype":"venue"
},
  "geometry": {"coordinates":[-2.598531723,39.2700119019],"type":"Point"}
}