{
  "type": "Feature",
  "properties": {
    "iso:country":"ES",
    "sg:address":"Avda Visley (de), 3",
    "sg:city":"Jerez De La Frontera",
    "sg:orig_category":"Asesor\u00cda Sobre Comunicaci\u00d3n De Empresas",
    "sg:phone":"+34 956 30 86 03",
    "sg:postcode":"11407",
    "sg:province":"C\u00e1diz",
    "wof:name":"Fernandez De Bobadilla Ivison Enrique",
    "wof:placetype":"venue"
},
  "geometry": {"coordinates":[-6.1306738853,36.6956710815],"type":"Point"}
}