{
  "type": "Feature",
  "properties": {
    "iso:country":"ES",
    "sg:address":"Calle de Mar, 14",
    "sg:city":"Valencia",
    "sg:orig_category":"Muebles, Minoristas",
    "sg:phone":"+34 963 91 98 09",
    "sg:postcode":"46003",
    "sg:province":"Valencia",
    "sg:website":"www.grassoler.com",
    "wof:name":"Proyectos Mercantiles Isater S.l.",
    "wof:placetype":"venue"
},
  "geometry": {"coordinates":[-0.3740530014,39.4737739563],"type":"Point"}
}