{
  "type": "Feature",
  "properties": {
    "addr:full":"Calle de Dobla, 2 Sevilla Sevilla 41006",
    "addr:housenumber":"2",
    "addr:postcode":"41006",
    "addr:street":"Calle De Dobla",
    "iso:country":"ES",
    "sg:address":"Calle de Dobla, 2",
    "sg:city":"Sevilla",
    "sg:orig_category":"Armas Y Municiones (fabricaci\u00d3n, Al Por Mayor)",
    "sg:phone":"+34 954 67 64 50",
    "sg:postcode":"41006",
    "sg:province":"Sevilla",
    "wof:name":"Mark 2 S. A.",
    "wof:placetype":"venue"
},
  "geometry": {"coordinates":[-5.9474902153,37.3860015869],"type":"Point"}
}