{
  "type": "Feature",
  "properties": {
    "iso:country":"ES",
    "sg:address":"Calle de Van Dyck, 8",
    "sg:city":"Alacant",
    "sg:orig_category":"Empresas De Carpinter\u00cda Met\u00c1lica",
    "sg:phone":"+34 965 17 08 81",
    "sg:postcode":"03009",
    "sg:province":"Alicante",
    "wof:name":"Arroyo Barba Antonio",
    "wof:placetype":"venue"
},
  "geometry": {"coordinates":[-0.4998809099,38.3737030029],"type":"Point"}
}