{
  "type": "Feature",
  "properties": {
    "addr:full":"Carrer de Sant Sebastia, 3 Reus Tarragona 43204",
    "addr:housenumber":"3",
    "addr:postcode":"43204",
    "addr:street":"Carrer De Sant Sebastia",
    "iso:country":"ES",
    "sg:address":"Carrer de Sant Sebastia, 3",
    "sg:city":"Reus",
    "sg:orig_category":"Cr\u00cda De Animales",
    "sg:phone":"+34 977 34 41 85",
    "sg:postcode":"43204",
    "sg:province":"Tarragona",
    "wof:name":"Comercial Ramadera Baix Camp S.l.",
    "wof:placetype":"venue"
},
  "geometry": {"coordinates":[1.1135309935,41.1577110291],"type":"Point"}
}