{
  "type": "Feature",
  "properties": {
    "iso:country":"ES",
    "sg:address":"Carr Verge Del Toro, De La, 47",
    "sg:city":"Mercadal",
    "sg:orig_category":"Alimentaci\u00d3n General (al Por Menor)",
    "sg:phone":"+34 971 15 41 57",
    "sg:postcode":"07740",
    "sg:province":"Islas Baleares",
    "wof:name":"Super Mercadal S.l.",
    "wof:placetype":"venue"
},
  "geometry": {"coordinates":[4.1529397964,40.00730896],"type":"Point"}
}