{
  "type": "Feature",
  "properties": {
    "iso:country":"ES",
    "sg:address":"Calle de Goya, 43",
    "sg:city":"Madrid",
    "sg:orig_category":"Estancos",
    "sg:phone":"+34 915 76 01 32",
    "sg:postcode":"28001",
    "sg:province":"Madrid",
    "wof:name":"Fernandez Golfin Martinez Ba\u00f1os Alicia",
    "wof:placetype":"venue"
},
  "geometry": {"coordinates":[-3.6829237938,40.4251441956],"type":"Point"}
}