{
  "type": "Feature",
  "properties": {
    "iso:country":"ES",
    "sg:address":"Avgd Corts Valencianes, 13",
    "sg:city":"Canals",
    "sg:orig_category":"Mec\u00c1nico Del Autom\u00d3vil",
    "sg:phone":"+34 962 24 22 52",
    "sg:postcode":"46650",
    "sg:province":"Valencia",
    "wof:name":"Talleres Canals S. A.",
    "wof:placetype":"venue"
},
  "geometry": {"coordinates":[-0.5884860158,38.9552497864],"type":"Point"}
}