{
  "type": "Feature",
  "properties": {
    "iso:country":"ES",
    "sg:address":"Calle de La Plaza, 41",
    "sg:city":"Paterna Campo",
    "sg:orig_category":"Comercio De Piezas De Recambio Y De Accesorios De Veh\u00cdculos, Veh\u00cdculos Industriales",
    "sg:phone":"+34 959 42 81 81",
    "sg:postcode":"21880",
    "sg:province":"Huelva",
    "wof:name":"Sauro Vazquez Jose",
    "wof:placetype":"venue"
},
  "geometry": {"coordinates":[-6.3992109299,37.4198722839],"type":"Point"}
}