{
  "type": "Feature",
  "properties": {
    "iso:country":"ES",
    "sg:address":"Calle de Mu\u00d1oz Leon, 13",
    "sg:city":"Sevilla",
    "sg:orig_category":"Molduras, Junquillos, Listones Y Molduras Perforadas",
    "sg:phone":"+34 954 37 34 54",
    "sg:postcode":"41009",
    "sg:province":"Sevilla",
    "wof:name":"Jose Gomez Perez E Hijos S.l.",
    "wof:placetype":"venue"
},
  "geometry": {"coordinates":[-5.9855899811,37.4017982483],"type":"Point"}
}