{
  "type": "Feature",
  "properties": {
    "addr:full":"Calle de Amor Hermoso, 49 Madrid Madrid 28026",
    "addr:housenumber":"49",
    "addr:postcode":"madrid;28026",
    "addr:street":"Calle De Amor Hermoso",
    "iso:country":"ES",
    "sg:address":"Calle de Amor Hermoso, 49",
    "sg:city":"Madrid",
    "sg:orig_category":"Grabados",
    "sg:phone":"+34 917 92 36 44",
    "sg:postcode":"28026",
    "sg:province":"Madrid",
    "wof:name":"Revenga Grabados Artisticos S.l.",
    "wof:placetype":"venue"
},
  "geometry": {"coordinates":[-3.7037189007,40.3844833374],"type":"Point"}
}