{
  "type": "Feature",
  "properties": {
    "iso:country":"ES",
    "sg:address":"Calle de Juan Carlos I, S/n",
    "sg:city":"Catral",
    "sg:orig_category":"Animales (al Por Menor)",
    "sg:phone":"+34 966 78 76 41",
    "sg:postcode":"03158",
    "sg:province":"Alicante",
    "wof:name":"Paraiso Liba S.l.",
    "wof:placetype":"venue"
},
  "geometry": {"coordinates":[-0.8007752895,38.1624946594],"type":"Point"}
}