{
  "type": "Feature",
  "properties": {
    "addr:full":"Calle de Francia, 82 Monta\u00e7a Roja Las Palmas 35580",
    "addr:housenumber":"82",
    "addr:postcode":"35580",
    "addr:street":"Calle De Francia",
    "iso:country":"ES",
    "sg:address":"Calle de Francia, 82",
    "sg:city":"Monta\u00e7a Roja",
    "sg:orig_category":"Promotores Constructores",
    "sg:phone":"+34 928 34 92 93",
    "sg:postcode":"35580",
    "sg:province":"Las Palmas",
    "wof:name":"Piscinas De Lujo Sol-rac S.l.u",
    "wof:placetype":"venue"
},
  "geometry": {"coordinates":[-13.8307790756,28.8657550812],"type":"Point"}
}