{
  "type": "Feature",
  "properties": {
    "iso:country":"ES",
    "sg:address":"Carrer de Gremi De Tintorers, 14",
    "sg:city":"Poligon Industrial De Son Castello",
    "sg:orig_category":"Empresas De Carpinter\u00cda De Madera",
    "sg:phone":"+34 971 20 79 16",
    "sg:postcode":"07009",
    "sg:province":"Islas Baleares",
    "wof:name":"Moreno Diaz Jose",
    "wof:placetype":"venue"
},
  "geometry": {"coordinates":[2.6741399765,39.6011390686],"type":"Point"}
}