{
  "type": "Feature",
  "properties": {
    "addr:full":"Calle de Purissima, 16 Nules Castell\u00f3n 12520",
    "addr:housenumber":"16",
    "addr:postcode":"12520",
    "addr:street":"Calle De Purissima",
    "iso:country":"ES",
    "sg:address":"Calle de Purissima, 16",
    "sg:city":"Nules",
    "sg:orig_category":"Peluquer\u00cdas, Peluquer\u00cda Mixta",
    "sg:phone":"+34 964 67 09 73",
    "sg:postcode":"12520",
    "sg:province":"Castell\u00f3n",
    "wof:name":"Albalat Esteban Adelaida",
    "wof:placetype":"venue"
},
  "geometry": {"coordinates":[-0.1541152,39.8568229675],"type":"Point"}
}