{
  "type": "Feature",
  "properties": {
    "addr:full":"Calle de Santa Teresa, 13 San Nicolas Murcia 30005",
    "addr:housenumber":"13",
    "addr:postcode":"30005",
    "addr:street":"Calle De Santa Teresa",
    "iso:country":"ES",
    "sg:address":"Calle de Santa Teresa, 13",
    "sg:city":"San Nicolas",
    "sg:orig_category":"Cl\u00cdnicas Dentales",
    "sg:phone":"+34 968 21 21 74",
    "sg:postcode":"30005",
    "sg:province":"Murcia",
    "wof:name":"Garcia Cruz Emilio Jose",
    "wof:placetype":"venue"
},
  "geometry": {"coordinates":[-1.1381909847,37.9864425659],"type":"Point"}
}