{
  "type": "Feature",
  "properties": {
    "iso:country":"ES",
    "sg:address":"Calle de Peris Brell, 6",
    "sg:city":"Valencia",
    "sg:orig_category":"Formaci\u00d3n Continuada (variada)",
    "sg:phone":"+34 963 30 27 95",
    "sg:postcode":"46022",
    "sg:province":"Valencia",
    "wof:name":"Zamora Pons Maria Desamparados",
    "wof:placetype":"venue"
},
  "geometry": {"coordinates":[-0.3475610018,39.4647598267],"type":"Point"}
}