{
  "type": "Feature",
  "properties": {
    "addr:full":"Plaz Berria / Plaza Nueva, 10 Ansoain Navarra 31013",
    "addr:housenumber":"10",
    "addr:postcode":"31013",
    "addr:street":"Plaz Berria / Plaza Nueva",
    "iso:country":"ES",
    "sg:address":"Plaz Berria / Plaza Nueva, 10",
    "sg:city":"Ansoain",
    "sg:orig_category":"Tapiceros Y Tapiceros",
    "sg:phone":"+34 948 12 44 43",
    "sg:postcode":"31013",
    "sg:province":"Navarra",
    "wof:name":"Alberca Algaba Antonio",
    "wof:placetype":"venue"
},
  "geometry": {"coordinates":[-1.6384311914,42.8338890076],"type":"Point"}
}