{
  "type": "Feature",
  "properties": {
    "iso:country":"ES",
    "sg:address":"Calle de Predicadores, 24",
    "sg:city":"Zaragoza",
    "sg:orig_category":"Jardiner\u00cdas, Vegetales, Art\u00cdculos De Jardiner\u00cda (al Por Menor)",
    "sg:phone":"+34 976 28 56 05",
    "sg:postcode":"50003",
    "sg:province":"Zaragoza",
    "wof:name":"Culmarza S.l.",
    "wof:placetype":"venue"
},
  "geometry": {"coordinates":[-0.8839780092,41.6571502686],"type":"Point"}
}