{
  "type": "Feature",
  "properties": {
    "addr:full":"Avda Ribera Alta De La, 67 Alberic Valencia 46260",
    "addr:housenumber":"67",
    "addr:postcode":"46260",
    "addr:street":"Avda Ribera Alta De La",
    "iso:country":"ES",
    "sg:address":"Avda Ribera Alta De La, 67",
    "sg:city":"Alberic",
    "sg:orig_category":"Tapicer\u00cdas",
    "sg:phone":"+34 962 44 32 34",
    "sg:postcode":"46260",
    "sg:province":"Valencia",
    "wof:name":"Vip-mur S.l.",
    "wof:placetype":"venue"
},
  "geometry": {"coordinates":[-0.527658999,39.1119308472],"type":"Point"}
}