{
  "type": "Feature",
  "properties": {
    "iso:country":"ES",
    "sg:address":"Ctra Mengibar, S/n",
    "sg:city":"Cazalilla",
    "sg:orig_category":"Frutas Y Legumbres Frescas (al Por Mayor)",
    "sg:phone":"+34 953 53 73 04",
    "sg:postcode":"23628",
    "sg:province":"Ja\u00e9n",
    "wof:name":"Sociedad Cooperativa San Blas",
    "wof:placetype":"venue"
},
  "geometry": {"coordinates":[-3.8633890152,38.0313720703],"type":"Point"}
}