{
  "type": "Feature",
  "properties": {
    "iso:country":"ES",
    "sg:address":"Calle de Julian De Apraiz, 2",
    "sg:city":"Vitoria-gasteiz",
    "sg:orig_category":"Molduras, Junquillos, Listones Y Molduras Perforadas",
    "sg:phone":"+34 945 22 77 24",
    "sg:postcode":"01012",
    "sg:province":"\u00c1lava",
    "wof:name":"Sampedro Martinez Jesus",
    "wof:placetype":"venue"
},
  "geometry": {"coordinates":[-2.673789978,42.8531913757],"type":"Point"}
}