{
  "type": "Feature",
  "properties": {
    "iso:country":"ES",
    "sg:address":"Calle de Peregrinos (los), 4",
    "sg:city":"Palencia",
    "sg:orig_category":"Iglesia Cat\u00d3lica",
    "sg:phone":"+34 979 71 16 40",
    "sg:postcode":"34004",
    "sg:province":"Palencia",
    "wof:name":"Parroquia De San Jose",
    "wof:placetype":"venue"
},
  "geometry": {"coordinates":[-4.5221261978,41.9987068176],"type":"Point"}
}