{
  "type": "Feature",
  "properties": {
    "addr:full":"La Vanera, S/n Puigcerda Girona 17520",
    "addr:housenumber":"s",
    "addr:postcode":"17520",
    "addr:street":"/ N Puigcerda",
    "iso:country":"ES",
    "sg:address":"La Vanera, S/n",
    "sg:city":"Puigcerda",
    "sg:orig_category":"Cr\u00cda De Cerdos",
    "sg:phone":"+34 972 19 70 06",
    "sg:postcode":"17520",
    "sg:province":"Girona",
    "wof:name":"La Vanera S.l.",
    "wof:placetype":"venue"
},
  "geometry": {"coordinates":[1.9278999567,42.4336547852],"type":"Point"}
}