{
  "type": "Feature",
  "properties": {
    "addr:full":"Pla\u00c7 Mercat (del), 16 Algemesi Valencia 46680",
    "addr:postcode":"46680",
    "iso:country":"ES",
    "sg:address":"Pla\u00c7 Mercat (del), 16",
    "sg:city":"Algemesi",
    "sg:orig_category":"Bisuter\u00cda, Joyer\u00cda, Relojer\u00cda (al Por Menor)",
    "sg:phone":"+34 962 42 07 01",
    "sg:postcode":"46680",
    "sg:province":"Valencia",
    "wof:name":"Dominguez Ferragut Salvador",
    "wof:placetype":"venue"
},
  "geometry": {"coordinates":[-0.4383490086,39.1962852478],"type":"Point"}
}