{
  "type": "Feature",
  "properties": {
    "iso:country":"ES",
    "sg:address":"Rabuceiras, S/n",
    "sg:city":"Rabuceiras",
    "sg:orig_category":"Pintura Y Barniz (al Por Menor)",
    "sg:phone":"+34 981 71 13 27",
    "sg:postcode":"15111",
    "sg:province":"A Coru\u00f1a",
    "wof:name":"Torrado Anido S.l.",
    "wof:placetype":"venue"
},
  "geometry": {"coordinates":[-8.7833986282,43.2669487],"type":"Point"}
}