{
  "type": "Feature",
  "properties": {
    "addr:full":"Av Castiero, 7 Vielha Lleida 25530",
    "addr:housenumber":"7",
    "addr:postcode":"25530",
    "addr:street":"Av Castiero",
    "iso:country":"ES",
    "sg:address":"Av Castiero, 7",
    "sg:city":"Vielha",
    "sg:orig_category":"Cajas De Ahorro",
    "sg:phone":"+34 973 64 15 59",
    "sg:postcode":"25530",
    "sg:province":"Lleida",
    "wof:name":"Caixa D'estalvis De Catalunya",
    "wof:placetype":"venue"
},
  "geometry": {"coordinates":[0.7947720289,42.7023925781],"type":"Point"}
}