{
  "type": "Feature",
  "properties": {
    "addr:full":"Calle de Bidasoa, S/n Bosque Madrid 28670",
    "addr:housenumber":"s / n",
    "addr:postcode":"28670",
    "addr:street":"Calle De Bidasoa",
    "iso:country":"ES",
    "sg:address":"Calle de Bidasoa, S/n",
    "sg:city":"Bosque",
    "sg:orig_category":"Peluquer\u00cdas, Peluquer\u00cda Mixta",
    "sg:phone":"+34 916 16 70 54",
    "sg:postcode":"28670",
    "sg:province":"Madrid",
    "wof:name":"Sanchez Sanchez Concepcion",
    "wof:placetype":"venue"
},
  "geometry": {"coordinates":[-3.9334971905,40.3872032166],"type":"Point"}
}