{
  "type": "Feature",
  "properties": {
    "addr:full":"Calle de San Vicente, 76 Sevilla Sevilla 41002",
    "addr:housenumber":"76",
    "addr:postcode":"41002",
    "addr:street":"Calle De San Vicente",
    "iso:country":"ES",
    "sg:address":"Calle de San Vicente, 76",
    "sg:city":"Sevilla",
    "sg:orig_category":"Molduras, Junquillos, Listones Y Molduras Perforadas",
    "sg:phone":"+34 954 38 73 54",
    "sg:postcode":"41002",
    "sg:province":"Sevilla",
    "wof:name":"Marques Palomo Antonia",
    "wof:placetype":"venue"
},
  "geometry": {"coordinates":[-5.9990468025,37.397567749],"type":"Point"}
}