{
  "type": "Feature",
  "properties": {
    "addr:full":"Lermandabidea, S/n Jundiz \u00c1lava 01015",
    "addr:postcode":"01015",
    "addr:street":"Lermandabidea S / N Jundiz A\u0301Lava",
    "iso:country":"ES",
    "sg:address":"Lermandabidea, S/n",
    "sg:city":"Jundiz",
    "sg:orig_category":"Transporte En General",
    "sg:phone":"+34 945 29 06 33",
    "sg:postcode":"01015",
    "sg:province":"\u00c1lava",
    "wof:name":"Distribuidora General Alavesa S. A.",
    "wof:placetype":"venue"
},
  "geometry": {"coordinates":[-6.1999697685,43.3617782593],"type":"Point"}
}