{
  "type": "Feature",
  "properties": {
    "iso:country":"ES",
    "sg:address":"San Roque, 14",
    "sg:city":"Combarro",
    "sg:orig_category":"Artesan\u00cda",
    "sg:phone":"+34 986 77 21 89",
    "sg:postcode":"36993",
    "sg:province":"Pontevedra",
    "wof:name":"Agulla Insuela Manuel",
    "wof:placetype":"venue"
},
  "geometry": {"coordinates":[-8.7050056458,42.431930542],"type":"Point"}
}