{
  "type": "Feature",
  "properties": {
    "iso:country":"ES",
    "sg:address":"Calle de Miguel Angel, 6",
    "sg:city":"Madrid",
    "sg:orig_category":"Asociaciones, Organismos Culturales Y Socioeducativos",
    "sg:phone":"+34 913 19 01 85",
    "sg:postcode":"28010",
    "sg:province":"Madrid",
    "wof:name":"Ballester Fernandez Jose Maria",
    "wof:placetype":"venue"
},
  "geometry": {"coordinates":[-3.6911389828,40.4339179993],"type":"Point"}
}