{
  "type": "Feature",
  "properties": {
    "iso:country":"ES",
    "sg:address":"Ctra N-152, Km. 0023,6",
    "sg:city":"Can Gosc",
    "sg:orig_category":"Piscinas, Accesorios, Suministros (fabricaci\u00d3n, Al Por Mayor)",
    "sg:phone":"+34 935 73 01 07",
    "sg:postcode":"08150",
    "sg:province":"Barcelona",
    "sg:website":"www.europa-piscinas.com",
    "wof:name":"Europa Produccions Piscines Poliester S.a.",
    "wof:placetype":"venue"
},
  "geometry": {"coordinates":[2.2319469452,41.5694198608],"type":"Point"}
}