{
  "type": "Feature",
  "properties": {
    "iso:country":"ES",
    "sg:address":"Calle de Donoso Cortes, 18",
    "sg:city":"Madrid",
    "sg:orig_category":"Agencias De Viajes",
    "sg:phone":"+34 914 47 24 49",
    "sg:postcode":"28015",
    "sg:province":"Madrid",
    "sg:website":"www.imaginatravel.com",
    "wof:name":"Imagina Travel S.l.",
    "wof:placetype":"venue"
},
  "geometry": {"coordinates":[-3.7073893547,40.4361495972],"type":"Point"}
}