{
  "type": "Feature",
  "properties": {
    "iso:country":"ES",
    "sg:address":"Calle de Real, S/n",
    "sg:city":"Campamento",
    "sg:orig_category":"Molduras, Junquillos, Listones Y Molduras Perforadas",
    "sg:phone":"+34 956 69 84 09",
    "sg:postcode":"11314",
    "sg:province":"C\u00e1diz",
    "wof:name":"Bernal Hidalgo Maria",
    "wof:placetype":"venue"
},
  "geometry": {"coordinates":[-5.3745741844,36.1756744385],"type":"Point"}
}