{
  "type": "Feature",
  "properties": {
    "iso:country":"ES",
    "sg:address":"Calle de Doctor Gomez Del Rio, 1",
    "sg:city":"Malaga",
    "sg:orig_category":"Venta, Instalaci\u00d3n, Mantenimiento De Chimeneas De Interior Y Accesorios",
    "sg:phone":"+34 952 02 32 18",
    "sg:postcode":"29006",
    "sg:province":"M\u00e1laga",
    "wof:name":"Dise\u00f1o Y Fuego S.l.",
    "wof:placetype":"venue"
},
  "geometry": {"coordinates":[-4.4797000885,36.7077064514],"type":"Point"}
}