{
  "type": "Feature",
  "properties": {
    "iso:country":"ES",
    "sg:address":"Avda Juan Carlos I, 4",
    "sg:city":"Barbate",
    "sg:orig_category":"Chapister\u00cda",
    "sg:phone":"+34 956 43 30 53",
    "sg:postcode":"11160",
    "sg:province":"C\u00e1diz",
    "wof:name":"Pareja Revuelta Antonio",
    "wof:placetype":"venue"
},
  "geometry": {"coordinates":[-5.9182758331,36.1951217651],"type":"Point"}
}