{
  "type": "Feature",
  "properties": {
    "addr:full":"Calle de Matilla, 10 Baeza Ja\u00e9n 23440",
    "addr:housenumber":"10",
    "addr:postcode":"23440",
    "addr:street":"Calle De Matilla",
    "iso:country":"ES",
    "sg:address":"Calle de Matilla, 10",
    "sg:city":"Baeza",
    "sg:orig_category":"Imprenta",
    "sg:phone":"+34 953 74 05 05",
    "sg:postcode":"23440",
    "sg:province":"Ja\u00e9n",
    "wof:name":"Torres Orzaez Francisco",
    "wof:placetype":"venue"
},
  "geometry": {"coordinates":[-3.4700210094,37.9947166443],"type":"Point"}
}