{
  "type": "Feature",
  "properties": {
    "iso:country":"ES",
    "sg:address":"Calle de Santa Eulalia, 12",
    "sg:city":"Santurtzi",
    "sg:orig_category":"Mercer\u00cda, Lencer\u00cda (al Por Menor)",
    "sg:phone":"+34 944 00 24 29",
    "sg:postcode":"48980",
    "sg:province":"Vizcaya",
    "wof:name":"Tintoreria Serantes",
    "wof:placetype":"venue"
},
  "geometry": {"coordinates":[-3.0318260193,43.3266220093],"type":"Point"}
}