{
  "type": "Feature",
  "properties": {
    "iso:country":"ES",
    "sg:address":"Ctra. Do\u00f1a Mencia, 1",
    "sg:city":"Baena",
    "sg:orig_category":"Productos Qu\u00cdmicos (fabricaci\u00d3n, Al Por Mayor)",
    "sg:phone":"+34 957 67 11 80",
    "sg:postcode":"14850",
    "sg:province":"C\u00f3rdoba",
    "wof:name":"Ortega Navarro Antonio Jesus",
    "wof:placetype":"venue"
},
  "geometry": {"coordinates":[-4.323964119,37.6170043945],"type":"Point"}
}