{
  "type": "Feature",
  "properties": {
    "iso:country":"ES",
    "sg:address":"Calle de Gabriel Y Galan, 15",
    "sg:city":"Almendralejo",
    "sg:orig_category":"Arquitectos",
    "sg:phone":"+34 924 66 55 27",
    "sg:postcode":"06200",
    "sg:province":"Badajoz",
    "wof:name":"Molino Barrero Antonio",
    "wof:placetype":"venue"
},
  "geometry": {"coordinates":[-6.4092588425,38.6828994751],"type":"Point"}
}