{
  "type": "Feature",
  "properties": {
    "addr:full":"Calle de Escultor Marinas (del), 4 Segovia Segovia 40001",
    "addr:housenumber":"4",
    "addr:postcode":"40001",
    "addr:street":"Calle De Escultor Marinas Del",
    "iso:country":"ES",
    "sg:address":"Calle de Escultor Marinas (del), 4",
    "sg:city":"Segovia",
    "sg:orig_category":"Tapicer\u00cdas",
    "sg:phone":"+34 921 42 64 02",
    "sg:postcode":"40001",
    "sg:province":"Segovia",
    "wof:name":"Lopez Sanz Mariano",
    "wof:placetype":"venue"
},
  "geometry": {"coordinates":[-4.1199679375,40.9448547363],"type":"Point"}
}