{
  "type": "Feature",
  "properties": {
    "iso:country":"ES",
    "sg:address":"Pi\u00f1eiral, 14",
    "sg:city":"Ourense",
    "sg:orig_category":"Expertos Contables, Revisores De Cuentas",
    "sg:phone":"+34 988 22 74 47",
    "sg:postcode":"32005",
    "sg:province":"Ourense",
    "wof:name":"Goc S.a.",
    "wof:placetype":"venue"
},
  "geometry": {"coordinates":[-7.8519001007,42.3053703308],"type":"Point"}
}