{
  "type": "Feature",
  "properties": {
    "addr:full":"Calle de Carrera, 82 Azuaga Badajoz 06920",
    "addr:housenumber":"82",
    "addr:postcode":"06920",
    "addr:street":"Calle De Carrera",
    "iso:country":"ES",
    "sg:address":"Calle de Carrera, 82",
    "sg:city":"Azuaga",
    "sg:orig_category":"Empresas De Carpinter\u00cda De Madera",
    "sg:phone":"+34 924 89 03 85",
    "sg:postcode":"06920",
    "sg:province":"Badajoz",
    "wof:name":"Centeno Sanchez Antonio Alfonso",
    "wof:placetype":"venue"
},
  "geometry": {"coordinates":[-5.6811714172,38.2571563721],"type":"Point"}
}