{
  "type": "Feature",
  "properties": {
    "addr:full":"Calle de Sagunt, 8 Alzira Valencia 46600",
    "addr:housenumber":"8",
    "addr:postcode":"46600",
    "addr:street":"Calle De Sagunt",
    "iso:country":"ES",
    "sg:address":"Calle de Sagunt, 8",
    "sg:city":"Alzira",
    "sg:orig_category":"Peluquer\u00cdas, Peluquer\u00cda Mixta",
    "sg:phone":"+34 962 41 28 62",
    "sg:postcode":"46600",
    "sg:province":"Valencia",
    "wof:name":"Olmos Laporta Ramon",
    "wof:placetype":"venue"
},
  "geometry": {"coordinates":[-0.4352779984,39.149017334],"type":"Point"}
}