{
  "type": "Feature",
  "properties": {
    "addr:full":"Calle de Santander, 9 Arganda Madrid 28500",
    "addr:housenumber":"9",
    "addr:postcode":"28500",
    "addr:street":"Calle De Santander",
    "iso:country":"ES",
    "sg:address":"Calle de Santander, 9",
    "sg:city":"Arganda",
    "sg:orig_category":"Fabricaci\u00d3n, Distribuci\u00d3n De Material Para La Climatizaci\u00d3n, Aireaci\u00d3n Y Ventilaci\u00d3n",
    "sg:phone":"+34 918 71 44 44",
    "sg:postcode":"28500",
    "sg:province":"Madrid",
    "sg:website":"www.sistemasgaitan.es",
    "wof:name":"Sistemas Gaitan S. A.",
    "wof:placetype":"venue"
},
  "geometry": {"coordinates":[-3.4406979084,40.2999954224],"type":"Point"}
}