{
  "type": "Feature",
  "properties": {
    "addr:full":"Urb Poligono Juncaril, S/n Albolote Granada 18220",
    "addr:housenumber":"s / n",
    "addr:postcode":"18220",
    "addr:street":"Urb Poligono Juncaril",
    "iso:country":"ES",
    "sg:address":"Urb Poligono Juncaril, S/n",
    "sg:city":"Albolote",
    "sg:orig_category":"Venta, Montaje De Neum\u00c1ticos",
    "sg:phone":"+34 958 46 84 26",
    "sg:postcode":"18220",
    "sg:province":"Granada",
    "wof:name":"Recacor S.a.",
    "wof:placetype":"venue"
},
  "geometry": {"coordinates":[-3.6585440636,37.2332839966],"type":"Point"}
}