{
  "type": "Feature",
  "properties": {
    "iso:country":"ES",
    "sg:address":"Carrer de Doctor Robert, 31",
    "sg:city":"Reus",
    "sg:orig_category":"Tapicer\u00cdas",
    "sg:phone":"+34 977 34 31 31",
    "sg:postcode":"43201",
    "sg:province":"Tarragona",
    "wof:name":"Granados Trabalon Jose Luis",
    "wof:placetype":"venue"
},
  "geometry": {"coordinates":[1.1093000174,41.1578712463],"type":"Point"}
}