{
  "type": "Feature",
  "properties": {
    "iso:country":"ES",
    "sg:address":"Carrer de Conveni, 12",
    "sg:city":"Barcelona",
    "sg:orig_category":"Empresas De Carpinter\u00cda De Madera",
    "sg:phone":"+34 933 50 18 95",
    "sg:postcode":"08016",
    "sg:province":"Barcelona",
    "wof:name":"Vargas Rius Jose",
    "wof:placetype":"venue"
},
  "geometry": {"coordinates":[2.185092926,41.443321228],"type":"Point"}
}