{
  "type": "Feature",
  "properties": {
    "addr:full":"Calle de Ponzano, 83 Madrid Madrid 28003",
    "addr:housenumber":"83",
    "addr:postcode":"madrid;28003",
    "addr:street":"Calle De Ponzano",
    "iso:country":"ES",
    "sg:address":"Calle de Ponzano, 83",
    "sg:city":"Madrid",
    "sg:orig_category":"Plomeros",
    "sg:phone":"+34 915 33 77 17",
    "sg:postcode":"28003",
    "sg:province":"Madrid",
    "wof:name":"Sanchez Cabanas Luis",
    "wof:placetype":"venue"
},
  "geometry": {"coordinates":[-3.6990299225,40.444316864],"type":"Point"}
}