{
  "type": "Feature",
  "properties": {
    "iso:country":"ES",
    "sg:address":"Carr Riu Freser, 80",
    "sg:city":"Girona",
    "sg:orig_category":"Suministros Para Hoteles",
    "sg:phone":"+34 972 20 29 84",
    "sg:postcode":"17003",
    "sg:province":"Girona",
    "wof:name":"Azkoyen Hosteleria S.a.",
    "wof:placetype":"venue"
},
  "geometry": {"coordinates":[2.8130517006,41.9634475708],"type":"Point"}
}