{
  "type": "Feature",
  "properties": {
    "iso:country":"ES",
    "sg:address":"Ctra Pe\u00d1aflor, S/n",
    "sg:city":"Lora Rio",
    "sg:orig_category":"Electrodom\u00c9sticos (al Por Menor)",
    "sg:phone":"+34 955 80 43 22",
    "sg:postcode":"41440",
    "sg:province":"Sevilla",
    "wof:name":"Garcia Martin Angel",
    "wof:placetype":"venue"
},
  "geometry": {"coordinates":[-5.5333189964,37.661491394],"type":"Point"}
}