{
  "type": "Feature",
  "properties": {
    "iso:country":"ES",
    "sg:address":"Carrer de Balears, 16",
    "sg:city":"Cambrils",
    "sg:orig_category":"Radiocomunicaciones, Telefon\u00cda M\u00d3vil, Radiomensajer\u00cda: Servicios, Comercializaci\u00d3n",
    "sg:phone":"+34 977 36 64 62",
    "sg:postcode":"43850",
    "sg:province":"Tarragona",
    "wof:name":"Agehtor Associats S.l.",
    "wof:placetype":"venue"
},
  "geometry": {"coordinates":[1.0580267906,41.0682945251],"type":"Point"}
}