{
  "type": "Feature",
  "properties": {
    "addr:full":"Rbla Modolell, 52 Viladecans Barcelona 08840",
    "addr:housenumber":"52",
    "addr:postcode":"08840",
    "addr:street":"Rbla Modolell",
    "iso:country":"ES",
    "sg:address":"Rbla Modolell, 52",
    "sg:city":"Viladecans",
    "sg:orig_category":"Bancos",
    "sg:phone":"+34 936 37 65 37",
    "sg:postcode":"08840",
    "sg:province":"Barcelona",
    "wof:name":"Banco Espa\u00f1ol De Credito S.a.",
    "wof:placetype":"venue"
},
  "geometry": {"coordinates":[2.0194070339,41.3186683655],"type":"Point"}
}