{
  "type": "Feature",
  "properties": {
    "addr:full":"Ptda Cotes Baixes, 11 Alcoi Alicante 03804",
    "addr:housenumber":"11",
    "addr:postcode":"03804",
    "addr:street":"Ptda Cotes Baixes",
    "iso:country":"ES",
    "sg:address":"Ptda Cotes Baixes, 11",
    "sg:city":"Alcoi",
    "sg:orig_category":"Reciclaje, Tratamiento De Tejidos",
    "sg:phone":"+34 965 52 57 70",
    "sg:postcode":"03804",
    "sg:province":"Alicante",
    "wof:name":"Miguel Carcelen Y Cia. S. L.",
    "wof:placetype":"venue"
},
  "geometry": {"coordinates":[-0.4650489986,38.712688446],"type":"Point"}
}