{
  "type": "Feature",
  "properties": {
    "iso:country":"ES",
    "sg:address":"Calle de Heliotropo, 1",
    "sg:city":"Madrid",
    "sg:orig_category":"Tapicer\u00cdas",
    "sg:phone":"+34 913 15 57 33",
    "sg:postcode":"28029",
    "sg:province":"Madrid",
    "wof:name":"Jimenez Martinez Maxima",
    "wof:placetype":"venue"
},
  "geometry": {"coordinates":[-3.6911332607,40.4726600647],"type":"Point"}
}