{
  "type": "Feature",
  "properties": {
    "iso:country":"ES",
    "sg:address":"Calle de Camino De Valladolid, 33",
    "sg:city":"Torrelodones",
    "sg:orig_category":"Animales (al Por Menor)",
    "sg:phone":"+34 918 59 35 85",
    "sg:postcode":"28250",
    "sg:province":"Madrid",
    "wof:name":"Baena Palacios Gonzalo",
    "wof:placetype":"venue"
},
  "geometry": {"coordinates":[-3.9329698086,40.5763092041],"type":"Point"}
}