{
  "type": "Feature",
  "properties": {
    "iso:country":"ES",
    "sg:address":"Calle de Isla Cabrera, 36",
    "sg:city":"Valencia",
    "sg:orig_category":"Inform\u00c1tica (estudios, Servicios, Asesor\u00cda, Formaci\u00d3n)",
    "sg:phone":"+34 963 16 24 45",
    "sg:postcode":"46026",
    "sg:province":"Valencia",
    "wof:name":"Algisa Informatica S.l.",
    "wof:placetype":"venue"
},
  "geometry": {"coordinates":[-0.3793255091,39.449054718],"type":"Point"}
}