{
  "type": "Feature",
  "properties": {
    "addr:full":"Calle de Rocio, 14 Sevilla Sevilla 41010",
    "addr:housenumber":"14",
    "addr:postcode":"41010",
    "addr:street":"Calle De Rocio",
    "iso:country":"ES",
    "sg:address":"Calle de Rocio, 14",
    "sg:city":"Sevilla",
    "sg:orig_category":"Asesor\u00cda De Comercio Exterior",
    "sg:phone":"+34 954 34 07 20",
    "sg:postcode":"41010",
    "sg:province":"Sevilla",
    "wof:name":"Zambrano Antequera S.l.",
    "wof:placetype":"venue"
},
  "geometry": {"coordinates":[-6.0018491745,37.3841743469],"type":"Point"}
}