{
  "type": "Feature",
  "properties": {
    "addr:full":"Calle de Princesa, 31 Madrid Madrid 28008",
    "addr:housenumber":"31",
    "addr:postcode":"madrid;28008",
    "addr:street":"Calle De Princesa",
    "iso:country":"ES",
    "sg:address":"Calle de Princesa, 31",
    "sg:city":"Madrid",
    "sg:orig_category":"Aeropuertos Y Servicios Aeroportuarios",
    "sg:phone":"+34 915 48 90 32",
    "sg:postcode":"28008",
    "sg:province":"Madrid",
    "wof:name":"Air China Limited Sucursal En Espa\u00f1a",
    "wof:placetype":"venue"
},
  "geometry": {"coordinates":[-3.71443367,40.4280128479],"type":"Point"}
}