{
  "type": "Feature",
  "properties": {
    "addr:full":"V San Felix(peral), 30 Cartagena Murcia 30300",
    "addr:housenumber":"30",
    "addr:postcode":"30300",
    "addr:street":"V San Felix Peral",
    "iso:country":"ES",
    "sg:address":"V San Felix(peral), 30",
    "sg:city":"Cartagena",
    "sg:orig_category":"T\u00c9cnicos Veterinarios",
    "sg:phone":"+34 968 51 33 41",
    "sg:postcode":"30300",
    "sg:province":"Murcia",
    "wof:name":"Ortega Madrid Juan",
    "wof:placetype":"venue"
},
  "geometry": {"coordinates":[-0.9920899868,37.6299133301],"type":"Point"}
}