{
  "type": "Feature",
  "properties": {
    "addr:full":"Carrer de L'hostal D'en Sol, 12 Barcelona Barcelona 08002",
    "addr:housenumber":"12",
    "addr:postcode":"08002",
    "addr:street":"Carrer De L'Hostal D'En Sol",
    "iso:country":"ES",
    "sg:address":"Carrer de L'hostal D'en Sol, 12",
    "sg:city":"Barcelona",
    "sg:orig_category":"Caf\u00c9s, Bares, Cervecer\u00cdas",
    "sg:phone":"+34 933 15 29 59",
    "sg:postcode":"08002",
    "sg:province":"Barcelona",
    "wof:name":"Casa Xuanin S.l.",
    "wof:placetype":"venue"
},
  "geometry": {"coordinates":[2.1804857254,41.3815574646],"type":"Point"}
}