{
  "type": "Feature",
  "properties": {
    "iso:country":"ES",
    "sg:address":"Pg Isabel Ii, 6",
    "sg:city":"Barcelona",
    "sg:orig_category":"Pesca Y Caza: Art\u00cdculos (al Por Menor)",
    "sg:phone":"+34 933 10 76 18",
    "sg:postcode":"08003",
    "sg:province":"Barcelona",
    "wof:name":"Moreno Moreno Juan",
    "wof:placetype":"venue"
},
  "geometry": {"coordinates":[2.1827580929,41.3815727234],"type":"Point"}
}