{
  "type": "Feature",
  "properties": {
    "addr:full":"Calle de Ramon Y Cajal, 10 Teruel Teruel 44001",
    "addr:housenumber":"10",
    "addr:postcode":"44001",
    "addr:street":"Calle De Ramon Y Cajal",
    "iso:country":"ES",
    "sg:address":"Calle de Ramon Y Cajal, 10",
    "sg:city":"Teruel",
    "sg:orig_category":"Grafistas",
    "sg:phone":"+34 978 61 23 63",
    "sg:postcode":"44001",
    "sg:province":"Teruel",
    "sg:website":"www.ekix.net",
    "wof:name":"Ekix. Soluciones Graficas S.l.",
    "wof:placetype":"venue"
},
  "geometry": {"coordinates":[-1.1072239876,40.3420181274],"type":"Point"}
}