{
  "type": "Feature",
  "properties": {
    "addr:full":"Carrer de Sardenya, 302 Barcelona Barcelona 08013",
    "addr:housenumber":"302",
    "addr:postcode":"08013",
    "addr:street":"Carrer De Sardenya",
    "iso:country":"ES",
    "sg:address":"Carrer de Sardenya, 302",
    "sg:city":"Barcelona",
    "sg:orig_category":"Herboristas (al Por Menor)",
    "sg:phone":"+34 932 32 15 66",
    "sg:postcode":"08013",
    "sg:province":"Barcelona",
    "wof:name":"Agell Ferran Mercedes",
    "wof:placetype":"venue"
},
  "geometry": {"coordinates":[2.1749424934,41.4021987915],"type":"Point"}
}