{
  "type": "Feature",
  "properties": {
    "addr:full":"Calle de Via Del Canal, 1 Benavente Zamora 49600",
    "addr:housenumber":"1",
    "addr:postcode":"49600",
    "addr:street":"Calle De Via Del Canal",
    "iso:country":"ES",
    "sg:address":"Calle de Via Del Canal, 1",
    "sg:city":"Benavente",
    "sg:orig_category":"Chapister\u00cda",
    "sg:phone":"+34 980 63 02 98",
    "sg:postcode":"49600",
    "sg:province":"Zamora",
    "wof:name":"Ma\u00f1anes Del Castillo Angel",
    "wof:placetype":"venue"
},
  "geometry": {"coordinates":[-5.6729650497,42.0029945374],"type":"Point"}
}