{
  "type": "Feature",
  "properties": {
    "iso:country":"ES",
    "sg:address":"Calle de Italia, 12",
    "sg:city":"Palmas De Gran Canaria",
    "sg:orig_category":"Audiovisuales: Material Y Accesorios (al Por Menor)",
    "sg:phone":"+34 928 24 42 84",
    "sg:postcode":"35006",
    "sg:province":"Las Palmas",
    "wof:name":"Telese\u00f1al Canarias S.a.",
    "wof:placetype":"venue"
},
  "geometry": {"coordinates":[-15.4308137894,28.1310100555],"type":"Point"}
}