{
  "type": "Feature",
  "properties": {
    "addr:full":"Calle de Encarnacion Oviol, 42 Madrid Madrid 28021",
    "addr:housenumber":"42",
    "addr:postcode":"madrid;28021",
    "addr:street":"Calle De;Oviol",
    "iso:country":"ES",
    "sg:address":"Calle de Encarnacion Oviol, 42",
    "sg:city":"Madrid",
    "sg:orig_category":"Frutas, Legumbres Frescas Y Tempranas (al Por Menor)",
    "sg:phone":"+34 917 95 39 63",
    "sg:postcode":"28021",
    "sg:province":"Madrid",
    "wof:name":"Frutas Rosi S.l.",
    "wof:placetype":"venue"
},
  "geometry": {"coordinates":[-3.6878340244,40.3505249023],"type":"Point"}
}