{
  "type": "Feature",
  "properties": {
    "iso:country":"ES",
    "sg:address":"Plaz Padre Jeronimo De Cordoba, S/n",
    "sg:city":"Sevilla",
    "sg:orig_category":"Supermercados Y Hipermercados",
    "sg:phone":"+34 954 21 20 04",
    "sg:postcode":"41003",
    "sg:province":"Sevilla",
    "wof:name":"Supermercado Altozano S.l.",
    "wof:placetype":"venue"
},
  "geometry": {"coordinates":[-5.986497879,37.3930778503],"type":"Point"}
}