{
  "type": "Feature",
  "properties": {
    "iso:country":"ES",
    "sg:address":"Calle de Mayor, 42",
    "sg:city":"Santa Cruz De La Zarza",
    "sg:orig_category":"Cajas De Ahorro",
    "sg:phone":"+34 925 14 32 90",
    "sg:postcode":"45370",
    "sg:province":"Toledo",
    "sg:website":"www.ccm.es",
    "wof:name":"Caja De Ahorros De Castilla La Mancha",
    "wof:placetype":"venue"
},
  "geometry": {"coordinates":[-3.187746048,39.9838294983],"type":"Point"}
}