{
  "type": "Feature",
  "properties": {
    "iso:country":"ES",
    "sg:address":"Poli Ciudad Del Transporte, S/n",
    "sg:city":"San Juan De Mozarrifar",
    "sg:orig_category":"Promotores Constructores",
    "sg:phone":"+34 976 58 76 66",
    "sg:postcode":"50820",
    "sg:province":"Zaragoza",
    "sg:website":"www.aexar.com",
    "wof:name":"Asociacion De Excavadores De Aragon",
    "wof:placetype":"venue"
},
  "geometry": {"coordinates":[-0.8407598138,41.7179450989],"type":"Point"}
}