{
  "type": "Feature",
  "properties": {
    "addr:full":"Parque Tomas Caballero, 2 Iru\u00f1a Navarra 31005",
    "addr:housenumber":"2",
    "addr:postcode":"31005",
    "addr:street":"Caballero",
    "iso:country":"ES",
    "sg:address":"Parque Tomas Caballero, 2",
    "sg:city":"Iru\u00f1a",
    "sg:orig_category":"Arquitectos",
    "sg:phone":"+34 948 15 41 24",
    "sg:postcode":"31005",
    "sg:province":"Navarra",
    "wof:name":"Iriondo Apaolaza Carlos",
    "wof:placetype":"venue"
},
  "geometry": {"coordinates":[-1.6365259886,42.8060684204],"type":"Point"}
}