{
  "type": "Feature",
  "properties": {
    "addr:full":"Calle de Enmedio, 53 Castellon Castell\u00f3n 12001",
    "addr:housenumber":"53",
    "addr:postcode":"12001",
    "addr:street":"Calle De Enmedio",
    "iso:country":"ES",
    "sg:address":"Calle de Enmedio, 53",
    "sg:city":"Castellon",
    "sg:orig_category":"Ropa Para Ni\u00d1os (al Por Menor)",
    "sg:phone":"+34 964 24 64 74",
    "sg:postcode":"12001",
    "sg:province":"Castell\u00f3n",
    "sg:website":"www.bershka.com",
    "wof:name":"Bershka Bsr Espa\u00f1a S.a.",
    "wof:placetype":"venue"
},
  "geometry": {"coordinates":[-0.0382350013,39.9865531921],"type":"Point"}
}