{
  "type": "Feature",
  "properties": {
    "iso:country":"ES",
    "sg:address":"Avda Gernikako Arbola, 14",
    "sg:city":"Barakaldo",
    "sg:orig_category":"Art\u00cdculos De Decoraci\u00d3n (fabricaci\u00d3n Y Al Por Mayor)",
    "sg:phone":"+34 944 00 01 87",
    "sg:postcode":"48902",
    "sg:province":"Vizcaya",
    "sg:website":"www.bilbaoguia.com/casanier.htm",
    "wof:name":"Distribuciones De Decoracion Casanier S.l.",
    "wof:placetype":"venue"
},
  "geometry": {"coordinates":[-2.9918439388,43.2944526672],"type":"Point"}
}