{
  "type": "Feature",
  "properties": {
    "addr:full":"Calle de Hospital, 8 Ciruelos Toledo 45314",
    "addr:housenumber":"8",
    "addr:postcode":"45314",
    "addr:street":"Calle De Hospital",
    "iso:country":"ES",
    "sg:address":"Calle de Hospital, 8",
    "sg:city":"Ciruelos",
    "sg:orig_category":"Agentes, Concesionarios Y Sucursales De Camiones Y Veh\u00cdculos Industriales",
    "sg:phone":"+34 925 15 40 70",
    "sg:postcode":"45314",
    "sg:province":"Toledo",
    "wof:name":"Motor Greja S.l.",
    "wof:placetype":"venue"
},
  "geometry": {"coordinates":[-3.6160480976,39.9363098145],"type":"Point"}
}