{
  "type": "Feature",
  "properties": {
    "addr:full":"Calle de Lope De Larrea, 2 Vitoria-gasteiz \u00c1lava 01005",
    "addr:housenumber":"2",
    "addr:postcode":"01005",
    "addr:street":"Calle De Lope De Larrea",
    "iso:country":"ES",
    "sg:address":"Calle de Lope De Larrea, 2",
    "sg:city":"Vitoria-gasteiz",
    "sg:orig_category":"Agencias De Trabajo Temporal",
    "sg:phone":"+34 945 12 40 60",
    "sg:postcode":"01005",
    "sg:province":"\u00c1lava",
    "wof:name":"Iman Temporing Ett S.l.",
    "wof:placetype":"venue"
},
  "geometry": {"coordinates":[-2.6688230038,42.8423461914],"type":"Point"}
}