{
  "type": "Feature",
  "properties": {
    "addr:full":"Plaz San Juan Bautista La Salle, 1 Santa Cruz De Tenerife Santa Cruz De Tenerife 38005",
    "addr:postcode":"38005",
    "addr:street":"Plaz",
    "iso:country":"ES",
    "sg:address":"Plaz San Juan Bautista La Salle, 1",
    "sg:city":"Santa Cruz De Tenerife",
    "sg:orig_category":"Asociaciones Y Clubs Deportivos",
    "sg:phone":"+34 922 29 42 00",
    "sg:postcode":"38005",
    "sg:province":"Santa Cruz De Tenerife",
    "wof:name":"Prom Patin Shop S.l.",
    "wof:placetype":"venue"
},
  "geometry": {"coordinates":[-16.2568359375,28.4639358521],"type":"Point"}
}