{
  "type": "Feature",
  "properties": {
    "addr:full":"Calle de Marques De Torrelaguna, 6 Madrid Madrid 28046",
    "addr:housenumber":"6",
    "addr:postcode":"28046",
    "addr:street":"Calle De Marques De Torrelaguna",
    "iso:country":"ES",
    "sg:address":"Calle de Marques De Torrelaguna, 6",
    "sg:city":"Madrid",
    "sg:orig_category":"Inform\u00c1tica Equipo Y Programas (al Por Mayor)",
    "sg:phone":"+34 913 14 81 20",
    "sg:postcode":"28046",
    "sg:province":"Madrid",
    "wof:name":"Feral Smart Cards S.l.",
    "wof:placetype":"venue"
},
  "geometry": {"coordinates":[-3.6862790585,40.4732971191],"type":"Point"}
}