{
  "type": "Feature",
  "properties": {
    "addr:full":"Calle de Mataro, 25 Madrid Madrid 28034",
    "addr:housenumber":"25",
    "addr:postcode":"madrid;28034",
    "addr:street":"Calle De Mataro",
    "iso:country":"ES",
    "sg:address":"Calle de Mataro, 25",
    "sg:city":"Madrid",
    "sg:orig_category":"Limpieza Industrial",
    "sg:phone":"+34 917 34 97 72",
    "sg:postcode":"28034",
    "sg:province":"Madrid",
    "wof:name":"Lavanderia Y Limpieza Valverde S.l.",
    "wof:placetype":"venue"
},
  "geometry": {"coordinates":[-3.6932890415,40.4933509827],"type":"Point"}
}