{
  "type": "Feature",
  "properties": {
    "addr:full":"Carrer de Mascaro, 54 Barcelona Barcelona 08032",
    "addr:housenumber":"54",
    "addr:postcode":"08032",
    "addr:street":"Carrer De Mascaro",
    "iso:country":"ES",
    "sg:address":"Carrer de Mascaro, 54",
    "sg:city":"Barcelona",
    "sg:orig_category":"Engranajes Y Elementos De Transmisi\u00d3n",
    "sg:phone":"+34 934 46 02 19",
    "sg:postcode":"08032",
    "sg:province":"Barcelona",
    "wof:name":"Transmisiones F.u. Iberica S. L.",
    "wof:placetype":"venue"
},
  "geometry": {"coordinates":[2.1734750271,41.422744751],"type":"Point"}
}