{
  "type": "Feature",
  "properties": {
    "iso:country":"ES",
    "sg:address":"Rua Rubalcava, 30",
    "sg:city":"Ferrol",
    "sg:orig_category":"Sociedades, Compa\u00d1\u00cdas Aseguradoras",
    "sg:phone":"+34 981 35 34 65",
    "sg:postcode":"15402",
    "sg:province":"La Coru\u00f1a",
    "wof:name":"Antonio Y Manuel J.sanchez Ramos Seguros C.b.",
    "wof:placetype":"venue"
},
  "geometry": {"coordinates":[-8.232919693,43.4850463867],"type":"Point"}
}