{
  "type": "Feature",
  "properties": {
    "addr:full":"Calle de Ramon Y Cajal, S/n Castejon Navarra 31590",
    "addr:housenumber":"s / n",
    "addr:postcode":"31590",
    "addr:street":"Calle De Ramon Y Cajal",
    "iso:country":"ES",
    "sg:address":"Calle de Ramon Y Cajal, S/n",
    "sg:city":"Castejon",
    "sg:orig_category":"Sindicatos De Trabajadores",
    "sg:phone":"+34 948 77 07 17",
    "sg:postcode":"31590",
    "sg:province":"Navarra",
    "wof:name":"Sindicato Espa\u00f1ol Maquinistas Y Ayudantes Ferroviarios",
    "wof:placetype":"venue"
},
  "geometry": {"coordinates":[-1.6869440079,42.1698646545],"type":"Point"}
}