{
  "type": "Feature",
  "properties": {
    "addr:full":"Calle de Mar Adriatico, 32 Varadero Granada 18600",
    "addr:housenumber":"32",
    "addr:postcode":"18600",
    "addr:street":"Calle De Mar Adriatico",
    "iso:country":"ES",
    "sg:address":"Calle de Mar Adriatico, 32",
    "sg:city":"Varadero",
    "sg:orig_category":"Maquinaria Para Industrias Diversas",
    "sg:phone":"+34 958 82 24 36",
    "sg:postcode":"18600",
    "sg:province":"Granada",
    "wof:name":"Comercial Mazve Motril S.l.",
    "wof:placetype":"venue"
},
  "geometry": {"coordinates":[-3.5152790546,36.7456130981],"type":"Point"}
}