{
  "type": "Feature",
  "properties": {
    "iso:country":"ES",
    "sg:address":"Calle de Cumbres, S/n",
    "sg:city":"Antilla",
    "sg:orig_category":"Tapiceros Y Tapiceros",
    "sg:phone":"+34 959 48 65 34",
    "sg:postcode":"21449",
    "sg:province":"Huelva",
    "sg:website":"www.arquideco.com",
    "wof:name":"Arquydeco 2000 S.l.",
    "wof:placetype":"venue"
},
  "geometry": {"coordinates":[-7.2276821136,37.2055282593],"type":"Point"}
}