{
  "type": "Feature",
  "properties": {
    "iso:country":"ES",
    "sg:address":"Calle de Riscos Candilitos, 1",
    "sg:city":"Salvaleon",
    "sg:orig_category":"Cooperativas Agr\u00cdcolas",
    "sg:phone":"+34 924 75 27 85",
    "sg:postcode":"06174",
    "sg:province":"Badajoz",
    "wof:name":"Cooperativa Ganadera De Salvaleon S. C. L.",
    "wof:placetype":"venue"
},
  "geometry": {"coordinates":[-6.7867622375,38.5120735168],"type":"Point"}
}