{
  "type": "Feature",
  "properties": {
    "iso:country":"ES",
    "sg:address":"Calle de Pablo Ruiz Picasso, 15",
    "sg:city":"Alameda",
    "sg:orig_category":"Empresas De Carpinter\u00cda De Madera",
    "sg:phone":"+34 952 71 03 30",
    "sg:postcode":"29530",
    "sg:province":"M\u00e1laga",
    "wof:name":"Torres Narbona Francisco",
    "wof:placetype":"venue"
},
  "geometry": {"coordinates":[-4.6571559906,37.2051467896],"type":"Point"}
}