{
  "type": "Feature",
  "properties": {
    "iso:country":"ES",
    "sg:address":"Rosario, 33",
    "sg:city":"Albox",
    "sg:orig_category":"Abogados",
    "sg:phone":"+34 950 43 16 21",
    "sg:postcode":"04800",
    "sg:province":"Almer\u00eda",
    "wof:name":"Navarro De Calin Juan Carlos",
    "wof:placetype":"venue"
},
  "geometry": {"coordinates":[-2.1482689381,37.3886909485],"type":"Point"}
}