{
  "type": "Feature",
  "properties": {
    "addr:full":"Calle de Serapio Mugica, 5 Irun Guip\u00f9zcoa 20302",
    "addr:housenumber":"5",
    "addr:postcode":"20302",
    "addr:street":"Calle De Serapio Mugica;Guipu\u0300Zcoa",
    "iso:country":"ES",
    "sg:address":"Calle de Serapio Mugica, 5",
    "sg:city":"Irun",
    "sg:orig_category":"Zapatos (al Por Menor)",
    "sg:phone":"+34 943 61 80 10",
    "sg:postcode":"20302",
    "sg:province":"Guip\u00f9zcoa",
    "wof:name":"Vaquero Martin Antonio",
    "wof:placetype":"venue"
},
  "geometry": {"coordinates":[-1.7955329418,43.3393096924],"type":"Point"}
}