{
  "type": "Feature",
  "properties": {
    "iso:country":"ES",
    "sg:address":"Carr Juan March, 5",
    "sg:city":"Cala Ratjada",
    "sg:orig_category":"Empresarios",
    "sg:phone":"+34 971 56 34 75",
    "sg:postcode":"07590",
    "sg:province":"Islas Baleares",
    "wof:name":"Fundacion Bartolome March Servera",
    "wof:placetype":"venue"
},
  "geometry": {"coordinates":[3.4606449604,39.7145996094],"type":"Point"}
}