{
  "type": "Feature",
  "properties": {
    "addr:full":"Carr Alfons Xii, 9 Badalona Barcelona 08912",
    "addr:housenumber":"9",
    "addr:postcode":"08912",
    "addr:street":"Carr Alfons Xii",
    "iso:country":"ES",
    "sg:address":"Carr Alfons Xii, 9",
    "sg:city":"Badalona",
    "sg:orig_category":"Electricidad: Instaladores",
    "sg:phone":"+34 934 64 40 82",
    "sg:postcode":"08912",
    "sg:province":"Barcelona",
    "wof:name":"Instalacions Ferrando S.l.",
    "wof:placetype":"venue"
},
  "geometry": {"coordinates":[2.2436230183,41.4472351074],"type":"Point"}
}