{
  "type": "Feature",
  "properties": {
    "iso:country":"ES",
    "sg:address":"Calle de Animas, 19",
    "sg:city":"Bola\u00e7os De Calatrava",
    "sg:orig_category":"Conservas De Legumbres (fabricaci\u00d3n, Al Por Mayor)",
    "sg:phone":"+34 926 87 09 90",
    "sg:postcode":"13260",
    "sg:province":"Ciudad Real",
    "wof:name":"Conservas Manchegas Antonio S.l.",
    "wof:placetype":"venue"
},
  "geometry": {"coordinates":[-3.9272627831,38.9860954285],"type":"Point"}
}