{
  "type": "Feature",
  "properties": {
    "iso:country":"ES",
    "sg:address":"Trav Tte Gral Fdco Michavila, 12",
    "sg:city":"Alcora",
    "sg:classifiers":[
        {
            "category":"Casinos & Gambling",
            "type":"Entertainment"
        }
    ],
    "sg:phone":"+34 964 36 31 12",
    "sg:postcode":"12110",
    "sg:province":"Castell\u00f3n",
    "sg:tags":[
        "locale",
        "de",
        "juego"
    ],
    "wof:name":"Franch Simo Maria Dolores",
    "wof:placetype":"venue"
},
  "geometry": {"coordinates":[-0.2178789973,40.0734786987],"type":"Point"}
}