{
  "type": "Feature",
  "properties": {
    "addr:full":"Calle de Mariano Riquer Wallis, 2 Santa Eulalia Islas Baleares 07840",
    "addr:housenumber":"2",
    "addr:postcode":"07840",
    "addr:street":"Calle De Mariano Riquer Wallis",
    "iso:country":"ES",
    "sg:address":"Calle de Mariano Riquer Wallis, 2",
    "sg:city":"Santa Eulalia",
    "sg:orig_category":"Sociedades, Compa\u00d1\u00cdas Aseguradoras",
    "sg:phone":"+34 971 33 63 68",
    "sg:postcode":"07840",
    "sg:province":"Islas Baleares",
    "wof:name":"Ferrer Guasch Jose",
    "wof:placetype":"venue"
},
  "geometry": {"coordinates":[2.9117100239,39.6136398315],"type":"Point"}
}