{
  "type": "Feature",
  "properties": {
    "iso:country":"ES",
    "sg:address":"Calle de Egido Del Puente, S/n",
    "sg:city":"Andujar",
    "sg:orig_category":"Transporte En General",
    "sg:phone":"+34 953 51 33 62",
    "sg:postcode":"23740",
    "sg:province":"Ja\u00e9n",
    "wof:name":"Industrias Metropolitanas Del Pan S.a",
    "wof:placetype":"venue"
},
  "geometry": {"coordinates":[-4.0612487793,38.0351676941],"type":"Point"}
}