{
  "type": "Feature",
  "properties": {
    "iso:country":"ES",
    "sg:address":"Avgd Soller, De, S/n",
    "sg:city":"Palmanyola",
    "sg:orig_category":"Empresas De Vigilancia, Guardia Y Protecci\u00d3n",
    "sg:phone":"+34 971 61 78 09",
    "sg:postcode":"07193",
    "sg:province":"Islas Baleares",
    "wof:name":"Escoltes De Mallorca",
    "wof:placetype":"venue"
},
  "geometry": {"coordinates":[2.6747450829,39.6631546021],"type":"Point"}
}