{
  "type": "Feature",
  "properties": {
    "iso:country":"ES",
    "sg:address":"Calle de Eduardo Marquina, 33",
    "sg:city":"Madrid",
    "sg:orig_category":"Sanatorios M\u00c9dico",
    "sg:phone":"+34 914 60 51 00",
    "sg:postcode":"28019",
    "sg:province":"Madrid",
    "wof:name":"Organismo Autonomo De Informatica Y Comunicaciones De La Comunidad De Madrid",
    "wof:placetype":"venue"
},
  "geometry": {"coordinates":[-3.7101609707,40.3923721313],"type":"Point"}
}