{
  "type": "Feature",
  "properties": {
    "addr:full":"Calle de Mercedes De Velilla, 18 Camas Sevilla 41900",
    "addr:housenumber":"18",
    "addr:postcode":"41900",
    "addr:street":"Calle De Mercedes De Velilla",
    "iso:country":"ES",
    "sg:address":"Calle de Mercedes De Velilla, 18",
    "sg:city":"Camas",
    "sg:orig_category":"Producci\u00d3n, Comercio De Cereales",
    "sg:phone":"+34 954 39 08 97",
    "sg:postcode":"41900",
    "sg:province":"Sevilla",
    "wof:name":"Montalvo Romero Antonio",
    "wof:placetype":"venue"
},
  "geometry": {"coordinates":[-6.0356378555,37.4069442749],"type":"Point"}
}