{
  "type": "Feature",
  "properties": {
    "addr:full":"Cosmo, S/n Morro Jable Las Palmas 35625",
    "addr:housenumber":"s / n",
    "addr:postcode":"35625",
    "iso:country":"ES",
    "sg:address":"Cosmo, S/n",
    "sg:city":"Morro Jable",
    "sg:orig_category":"Oficinas De Turismo, Asociaciones De Iniciativa",
    "sg:phone":"+34 928 54 50 44",
    "sg:postcode":"35625",
    "sg:province":"Las Palmas",
    "wof:name":"Ayuntamiento De Pajara",
    "wof:placetype":"venue"
},
  "geometry": {"coordinates":[-14.3477210999,28.0498352051],"type":"Point"}
}