{
  "type": "Feature",
  "properties": {
    "addr:full":"Avda Oporto, 23 Madrid Madrid 28019",
    "addr:housenumber":"23",
    "addr:postcode":"madrid;28019",
    "addr:street":"Avda Oporto",
    "iso:country":"ES",
    "sg:address":"Avda Oporto, 23",
    "sg:city":"Madrid",
    "sg:orig_category":"Laboratorios Y Trabajos De Fotograf\u00cda, V\u00cddeo Y Cine",
    "sg:phone":"+34 914 60 11 75",
    "sg:postcode":"28019",
    "sg:province":"Madrid",
    "wof:name":"Photo Oporto S.l.",
    "wof:placetype":"venue"
},
  "geometry": {"coordinates":[-3.723156929,40.3852157593],"type":"Point"}
}