{
  "type": "Feature",
  "properties": {
    "addr:full":"Ctra San Vicente, 43 Valle Trapaga Vizcaya 48510",
    "addr:housenumber":"43",
    "addr:postcode":"48510",
    "addr:street":"Ctra San Vicente;Trapaga",
    "iso:country":"ES",
    "sg:address":"Ctra San Vicente, 43",
    "sg:city":"Valle Trapaga",
    "sg:orig_category":"Delegados, Agentes De Tr\u00c1nsito, Auxiliares De Transporte Internacional",
    "sg:phone":"+34 944 95 32 88",
    "sg:postcode":"48510",
    "sg:province":"Vizcaya",
    "wof:name":"Logistica Internacional, S.l.",
    "wof:placetype":"venue"
},
  "geometry": {"coordinates":[-3.0191290379,43.2994880676],"type":"Point"}
}