{
  "type": "Feature",
  "properties": {
    "addr:full":"Ctra Ba\u00d1os De Arteijo, 83 Grela La Coru\u00f1a 15008",
    "addr:housenumber":"83",
    "addr:postcode":"15008",
    "addr:street":"Ctra Ban\u0303Os De Arteijo;La Corun\u0303A",
    "iso:country":"ES",
    "sg:address":"Ctra Ba\u00d1os De Arteijo, 83",
    "sg:city":"Grela",
    "sg:orig_category":"Electricidad: Equipos Industriales, Componentes (fabricaci\u00d3n)",
    "sg:phone":"+34 981 17 33 00",
    "sg:postcode":"15008",
    "sg:province":"La Coru\u00f1a",
    "sg:website":"www.kilovatiogalicia.es",
    "wof:name":"Kilovatio Galicia S. A.",
    "wof:placetype":"venue"
},
  "geometry": {"coordinates":[-8.4471950531,43.0565299988],"type":"Point"}
}