{
  "type": "Feature",
  "properties": {
    "addr:full":"Calle de Cristo Del Calvario, 4 Sevilla Sevilla 41001",
    "addr:housenumber":"4",
    "addr:postcode":"41001",
    "addr:street":"Calle De Cristo Del Calvario",
    "iso:country":"ES",
    "sg:address":"Calle de Cristo Del Calvario, 4",
    "sg:city":"Sevilla",
    "sg:orig_category":"Agencias Y Agentes Comerciales, Representantes",
    "sg:phone":"+34 954 22 14 01",
    "sg:postcode":"41001",
    "sg:province":"Sevilla",
    "wof:name":"Vaquero Mu\u00f1oz Ramon",
    "wof:placetype":"venue"
},
  "geometry": {"coordinates":[-5.9990091324,37.3905105591],"type":"Point"}
}