{
  "type": "Feature",
  "properties": {
    "addr:full":"Carrer de Casta\u00d1os, 30 Mataro Barcelona 08302",
    "addr:housenumber":"30",
    "addr:postcode":"08302",
    "addr:street":"Carrer De Castan\u0303Os",
    "iso:country":"ES",
    "sg:address":"Carrer de Casta\u00d1os, 30",
    "sg:city":"Mataro",
    "sg:orig_category":"Fabricaci\u00d3n De Su\u00c9ters Y Chalecos De Punto",
    "sg:phone":"+34 937 98 10 89",
    "sg:postcode":"08302",
    "sg:province":"Barcelona",
    "wof:name":"Albert Corp Antonio",
    "wof:placetype":"venue"
},
  "geometry": {"coordinates":[2.4401473999,41.5356788635],"type":"Point"}
}