{
  "type": "Feature",
  "properties": {
    "iso:country":"ES",
    "sg:address":"Calle de Juan Jose Lorente, 49",
    "sg:city":"Zaragoza",
    "sg:orig_category":"Molduras, Junquillos, Listones Y Molduras Perforadas",
    "sg:phone":"+34 976 56 79 84",
    "sg:postcode":"50005",
    "sg:province":"Zaragoza",
    "wof:name":"La Buhardilla S.cv.",
    "wof:placetype":"venue"
},
  "geometry": {"coordinates":[-0.8972529769,41.6445045471],"type":"Point"}
}