{
  "type": "Feature",
  "properties": {
    "iso:country":"ES",
    "sg:address":"Ctra Moraira A Teulada, 11",
    "sg:city":"Paitxi",
    "sg:orig_category":"Inmobiliaria (agencias)",
    "sg:phone":"+34 966 49 02 62",
    "sg:postcode":"03725",
    "sg:province":"Alicante",
    "wof:name":"J.b.e.s.a.",
    "wof:placetype":"venue"
},
  "geometry": {"coordinates":[0.1417161971,38.7222976685],"type":"Point"}
}