{
  "type": "Feature",
  "properties": {
    "addr:full":"Pol Ind Saprelorca, S/n Lorca Murcia 30800",
    "addr:housenumber":"s / n",
    "addr:postcode":"30800",
    "iso:country":"ES",
    "sg:address":"Pol Ind Saprelorca, S/n",
    "sg:city":"Lorca",
    "sg:orig_category":"Empresas De Vigilancia, Guardia Y Protecci\u00d3n",
    "sg:phone":"+34 968 47 63 13",
    "sg:postcode":"30800",
    "sg:province":"Murcia",
    "wof:name":"Gestion De Seguridad Y Control S.a.",
    "wof:placetype":"venue"
},
  "geometry": {"coordinates":[-1.6905640364,37.680557251],"type":"Point"}
}