{
  "type": "Feature",
  "properties": {
    "addr:full":"Calle de Pico Del Aguila (del), 15 Humanes De Madrid Madrid 28970",
    "addr:postcode":"28970",
    "addr:street":"Calle De Pico Del;Del",
    "iso:country":"ES",
    "sg:address":"Calle de Pico Del Aguila (del), 15",
    "sg:city":"Humanes De Madrid",
    "sg:orig_category":"Aluminio Y Aleaciones (producci\u00d3n, Transformaci\u00d3n, Negocio)",
    "sg:phone":"+34 916 04 92 84",
    "sg:postcode":"28970",
    "sg:province":"Madrid",
    "wof:name":"Pulidos Del Pliego S.l.",
    "wof:placetype":"venue"
},
  "geometry": {"coordinates":[-3.8130643368,40.2616386414],"type":"Point"}
}