{
  "type": "Feature",
  "properties": {
    "addr:full":"Calle de Perpetua Diaz, 13 Madrid Madrid 28026",
    "addr:housenumber":"13",
    "addr:postcode":"madrid;28026",
    "addr:street":"Calle De Perpetua Diaz",
    "iso:country":"ES",
    "sg:address":"Calle de Perpetua Diaz, 13",
    "sg:city":"Madrid",
    "sg:orig_category":"Ropa Para Caballeros Y Se\u00d1oras (al Por Mayor)",
    "sg:phone":"+34 915 00 08 93",
    "sg:postcode":"28026",
    "sg:province":"Madrid",
    "wof:name":"Picueta S.l.",
    "wof:placetype":"venue"
},
  "geometry": {"coordinates":[-3.709031105,40.3844604492],"type":"Point"}
}