{
  "type": "Feature",
  "properties": {
    "addr:full":"Carrer de Napols, 326 Barcelona Barcelona 08025",
    "addr:housenumber":"326",
    "addr:postcode":"08025",
    "addr:street":"Carrer De Napols",
    "iso:country":"ES",
    "sg:address":"Carrer de Napols, 326",
    "sg:city":"Barcelona",
    "sg:orig_category":"Asesor\u00cda Fiscal Y Jur\u00cddica",
    "sg:phone":"+34 934 57 84 01",
    "sg:postcode":"08025",
    "sg:province":"Barcelona",
    "wof:name":"Serra Casanovas Maria Isabel",
    "wof:placetype":"venue"
},
  "geometry": {"coordinates":[2.167329073,41.4046974182],"type":"Point"}
}