{
  "type": "Feature",
  "properties": {
    "iso:country":"ES",
    "sg:address":"Rond Sant Oleguer, 118",
    "sg:city":"Mataro",
    "sg:orig_category":"Fabricaci\u00d3n De Su\u00c9ters Y Chalecos De Punto",
    "sg:phone":"+34 937 90 63 05",
    "sg:postcode":"08304",
    "sg:province":"Barcelona",
    "wof:name":"Vinuesa Arias Vicente",
    "wof:placetype":"venue"
},
  "geometry": {"coordinates":[2.4475960732,41.5517044067],"type":"Point"}
}