{
  "type": "Feature",
  "properties": {
    "iso:country":"ES",
    "sg:address":"Pl Esglesia, 7",
    "sg:city":"Riudoms",
    "sg:orig_category":"Art\u00cdculos Funerarios (al Por Menor)",
    "sg:phone":"+34 977 85 11 61",
    "sg:postcode":"43330",
    "sg:province":"Tarragona",
    "wof:name":"Mena Margalef Francisco",
    "wof:placetype":"venue"
},
  "geometry": {"coordinates":[1.0517450571,41.1388397217],"type":"Point"}
}