{
  "type": "Feature",
  "properties": {
    "iso:country":"ES",
    "sg:address":"Calle de Patricio Ferrandiz, 66",
    "sg:city":"Denia",
    "sg:orig_category":"Electrodom\u00c9sticos (al Por Menor)",
    "sg:phone":"+34 965 78 67 50",
    "sg:postcode":"03700",
    "sg:province":"Alicante",
    "wof:name":"Lon Jaen Joaquin Andres",
    "wof:placetype":"venue"
},
  "geometry": {"coordinates":[0.1092739999,38.8388710022],"type":"Point"}
}