{
  "type": "Feature",
  "properties": {
    "addr:full":"Carr Doctor Manel Vidal, 1 Vielha Lleida 25530",
    "addr:housenumber":"1",
    "addr:postcode":"25530",
    "addr:street":"Carr Doctor Manel Vidal",
    "iso:country":"ES",
    "sg:address":"Carr Doctor Manel Vidal, 1",
    "sg:city":"Vielha",
    "sg:orig_category":"Mec\u00c1nico Del Autom\u00d3vil",
    "sg:phone":"+34 973 64 29 46",
    "sg:postcode":"25530",
    "sg:province":"Lleida",
    "wof:name":"Benet Moli Antonio",
    "wof:placetype":"venue"
},
  "geometry": {"coordinates":[0.7978249788,42.7017402649],"type":"Point"}
}