{
  "type": "Feature",
  "properties": {
    "addr:full":"Espa\u00f1a, 78 Villamuriel Palencia 34190",
    "addr:housenumber":"78",
    "addr:postcode":"34190",
    "addr:street":"Espan\u0303A;Palencia",
    "iso:country":"ES",
    "sg:address":"Espa\u00f1a, 78",
    "sg:city":"Villamuriel",
    "sg:orig_category":"Contenedores (mercanc\u00cdas)",
    "sg:phone":"+34 979 77 11 35",
    "sg:postcode":"34190",
    "sg:province":"Palencia",
    "wof:name":"Abymatrans S.l",
    "wof:placetype":"venue"
},
  "geometry": {"coordinates":[-4.49899,41.939117],"type":"Point"}
}