{
  "type": "Feature",
  "properties": {
    "addr:full":"Calle de Luis De Morales, S/n Sevilla Sevilla 41018",
    "addr:housenumber":"s / n",
    "addr:postcode":"41018",
    "addr:street":"Calle De Luis De Morales",
    "iso:country":"ES",
    "sg:address":"Calle de Luis De Morales, S/n",
    "sg:city":"Sevilla",
    "sg:orig_category":"Bancos",
    "sg:phone":"+34 954 57 72 66",
    "sg:postcode":"41018",
    "sg:province":"Sevilla",
    "wof:name":"Bankinter S.a.",
    "wof:placetype":"venue"
},
  "geometry": {"coordinates":[-5.9723768234,37.3867759705],"type":"Point"}
}