{
  "type": "Feature",
  "properties": {
    "addr:full":"Calle de Madrid, 137 San Jose Rinconada Sevilla 41300",
    "addr:housenumber":"137",
    "addr:postcode":"41300",
    "addr:street":"Calle De Madrid",
    "iso:country":"ES",
    "sg:address":"Calle de Madrid, 137",
    "sg:city":"San Jose Rinconada",
    "sg:orig_category":"Cl\u00cdnicas Dentales",
    "sg:phone":"+34 954 79 22 81",
    "sg:postcode":"41300",
    "sg:province":"Sevilla",
    "wof:name":"Aprodent S.l.",
    "wof:placetype":"venue"
},
  "geometry": {"coordinates":[-5.9393639565,37.4856071472],"type":"Point"}
}