{
  "type": "Feature",
  "properties": {
    "addr:full":"Av Castelldefels, Km. 0017,3 Castelldefels Barcelona 08860",
    "addr:postcode":"08860",
    "addr:street":"Av Castelldefels Km. 0017,3",
    "iso:country":"ES",
    "sg:address":"Av Castelldefels, Km. 0017,3",
    "sg:city":"Castelldefels",
    "sg:orig_category":"Asociaciones Y Clubs Deportivos",
    "sg:phone":"+34 936 45 22 38",
    "sg:postcode":"08860",
    "sg:province":"Barcelona",
    "wof:name":"Seae S.l.",
    "wof:placetype":"venue"
},
  "geometry": {"coordinates":[1.9870599508,41.2696418762],"type":"Point"}
}