{
  "type": "Feature",
  "properties": {
    "addr:full":"Cno Rio Muerto, S/n Archena Murcia 30600",
    "addr:housenumber":"s / n",
    "addr:postcode":"30600",
    "addr:street":"Cno Rio Muerto",
    "iso:country":"ES",
    "sg:address":"Cno Rio Muerto, S/n",
    "sg:city":"Archena",
    "sg:orig_category":"Aguas (distribuci\u00d3n, Servicios)",
    "sg:phone":"+34 968 43 02 95",
    "sg:postcode":"30600",
    "sg:province":"Murcia",
    "sg:website":"www.ondagua.es",
    "wof:name":"Pridesa Proyectos Y Servicios S.a.",
    "wof:placetype":"venue"
},
  "geometry": {"coordinates":[-1.2949659824,38.1053543091],"type":"Point"}
}