{
  "type": "Feature",
  "properties": {
    "iso:country":"ES",
    "sg:address":"Calle de Nervion, 8",
    "sg:city":"San Vicente De Barakaldo",
    "sg:orig_category":"Art\u00cdculos De Decoraci\u00d3n (fabricaci\u00d3n Y Al Por Mayor)",
    "sg:phone":"+34 944 38 43 49",
    "sg:postcode":"48901",
    "sg:province":"Vizcaya",
    "wof:name":"Pelarda Alonso Miguel Angel",
    "wof:placetype":"venue"
},
  "geometry": {"coordinates":[-2.982200861,43.3005256653],"type":"Point"}
}