{
  "type": "Feature",
  "properties": {
    "iso:country":"ES",
    "sg:address":"Av Ondara, S/n",
    "sg:city":"Tarrega",
    "sg:orig_category":"Art\u00cdculos Funerarios (al Por Menor)",
    "sg:phone":"+34 973 31 19 94",
    "sg:postcode":"25300",
    "sg:province":"Lleida",
    "wof:name":"Tanatori L'urgell S.l.",
    "wof:placetype":"venue"
},
  "geometry": {"coordinates":[1.1345150471,41.6462059021],"type":"Point"}
}