{
  "type": "Feature",
  "properties": {
    "iso:country":"ES",
    "sg:address":"Calle de Ansite, 115",
    "sg:city":"Cruce De Arinaga",
    "sg:orig_category":"Inform\u00c1tica: Material Y Suministros",
    "sg:phone":"+34 928 18 87 65",
    "sg:postcode":"35118",
    "sg:province":"Las Palmas",
    "wof:name":"Martin Moreno Ricardo Manuel",
    "wof:placetype":"venue"
},
  "geometry": {"coordinates":[-15.425532341,27.876241684],"type":"Point"}
}