{
  "type": "Feature",
  "properties": {
    "addr:full":"Calle de Alcala, 179 Madrid Madrid 28009",
    "addr:housenumber":"179",
    "addr:postcode":"28009",
    "addr:street":"Calle De Alcala",
    "iso:country":"ES",
    "sg:address":"Calle de Alcala, 179",
    "sg:city":"Madrid",
    "sg:orig_category":"Papeler\u00cdas, Librer\u00cdas",
    "sg:phone":"+34 914 01 37 85",
    "sg:postcode":"28009",
    "sg:province":"Madrid",
    "wof:name":"Arranz Tarrero Juan Angel",
    "wof:placetype":"venue"
},
  "geometry": {"coordinates":[-3.6713886261,40.4268455505],"type":"Point"}
}