{
  "type": "Feature",
  "properties": {
    "addr:full":"Calle de Lorca, 23 Palmar  O Lugar De Don Juan Murcia 30120",
    "addr:housenumber":"23",
    "addr:postcode":"30120",
    "addr:street":"Calle De Lorca;Lugar",
    "iso:country":"ES",
    "sg:address":"Calle de Lorca, 23",
    "sg:city":"Palmar  O Lugar De Don Juan",
    "sg:orig_category":"Trajes Y Adornos De Boda (confecci\u00d3n, Al Por Menor)",
    "sg:phone":"+34 968 88 15 91",
    "sg:postcode":"30120",
    "sg:province":"Murcia",
    "wof:name":"Noguera Martinez Sacramento",
    "wof:placetype":"venue"
},
  "geometry": {"coordinates":[-1.1302490234,37.9829597473],"type":"Point"}
}