{
  "type": "Feature",
  "properties": {
    "addr:full":"Calle de San Martin, 16 Valladolid Valladolid 47003",
    "addr:housenumber":"16",
    "addr:postcode":"47003",
    "addr:street":"Calle De San Martin",
    "iso:country":"ES",
    "sg:address":"Calle de San Martin, 16",
    "sg:city":"Valladolid",
    "sg:orig_category":"Psic\u00d3logos",
    "sg:phone":"+34 983 26 42 14",
    "sg:postcode":"47003",
    "sg:province":"Valladolid",
    "wof:name":"Ramirez Villafa\u00f1ez Amado",
    "wof:placetype":"venue"
},
  "geometry": {"coordinates":[-4.7215638161,41.6561813354],"type":"Point"}
}