{
  "type": "Feature",
  "properties": {
    "iso:country":"ES",
    "sg:address":"Avda Alberto Alcocer, 26",
    "sg:city":"Madrid",
    "sg:orig_category":"M\u00c9dicos: Cirug\u00cda Urol\u00d3gica",
    "sg:phone":"+34 914 58 89 14",
    "sg:postcode":"28036",
    "sg:province":"Madrid",
    "wof:name":"Martin Laborda Fernando",
    "wof:placetype":"venue"
},
  "geometry": {"coordinates":[-3.6842367649,40.4586296082],"type":"Point"}
}