{
  "type": "Feature",
  "properties": {
    "iso:country":"ES",
    "sg:address":"Avda Navarra, 69",
    "sg:city":"Errenteria",
    "sg:orig_category":"Bisuter\u00cda, Joyer\u00cda, Relojer\u00cda (al Por Menor)",
    "sg:phone":"+34 943 52 07 96",
    "sg:postcode":"20100",
    "sg:province":"Guip\u00f9zcoa",
    "wof:name":"Vivar Ruiz Carlos",
    "wof:placetype":"venue"
},
  "geometry": {"coordinates":[-1.9020303488,43.3147888184],"type":"Point"}
}