{
  "type": "Feature",
  "properties": {
    "iso:country":"ES",
    "sg:address":"Calle de Bejar, 5",
    "sg:city":"Madrid",
    "sg:orig_category":"Florister\u00cdas",
    "sg:phone":"+34 917 25 20 10",
    "sg:postcode":"28028",
    "sg:province":"Madrid",
    "wof:name":"Agudo Almendros Pedro",
    "wof:placetype":"venue"
},
  "geometry": {"coordinates":[-3.6743741035,40.4352111816],"type":"Point"}
}