{
  "type": "Feature",
  "properties": {
    "addr:full":"Carrer de Mao, 10 Barcelona Barcelona 08022",
    "addr:housenumber":"10",
    "addr:postcode":"08022",
    "addr:street":"Carrer De Mao",
    "iso:country":"ES",
    "sg:address":"Carrer de Mao, 10",
    "sg:city":"Barcelona",
    "sg:orig_category":"Inmobiliaria (agencias)",
    "sg:phone":"+34 932 11 67 33",
    "sg:postcode":"08022",
    "sg:province":"Barcelona",
    "wof:name":"Online Network S.l.",
    "wof:placetype":"venue"
},
  "geometry": {"coordinates":[2.1321079731,41.4037055969],"type":"Point"}
}