{
  "type": "Feature",
  "properties": {
    "addr:full":"Mercat Tres Torres, S/n Barcelona Barcelona 08017",
    "addr:postcode":"08017",
    "addr:street":"Torres S / N",
    "iso:country":"ES",
    "sg:address":"Mercat Tres Torres, S/n",
    "sg:city":"Barcelona",
    "sg:orig_category":"Carnicer\u00cdas, Carnicer\u00cdas",
    "sg:phone":"+34 934 18 14 95",
    "sg:postcode":"08017",
    "sg:province":"Barcelona",
    "wof:name":"Pedrol Reverter Francisco",
    "wof:placetype":"venue"
},
  "geometry": {"coordinates":[2.1353878975,41.396774292],"type":"Point"}
}