{
  "type": "Feature",
  "properties": {
    "iso:country":"ES",
    "sg:address":"Crtra. General, S/n",
    "sg:city":"S. Tirso Abres",
    "sg:orig_category":"Negocio De Madera",
    "sg:phone":"+34 985 63 44 94",
    "sg:postcode":"33774",
    "sg:province":"Asturias",
    "wof:name":"Martinez Lopez Benigno",
    "wof:placetype":"venue"
},
  "geometry": {"coordinates":[-7.1420388222,43.4099617004],"type":"Point"}
}