{
  "type": "Feature",
  "properties": {
    "addr:full":"Calle de General Riera, 16 Palma Islas Baleares 07003",
    "addr:housenumber":"16",
    "addr:postcode":"07003",
    "addr:street":"Calle De General Riera",
    "iso:country":"ES",
    "sg:address":"Calle de General Riera, 16",
    "sg:city":"Palma",
    "sg:orig_category":"Abogados",
    "sg:phone":"+34 971 76 00 20",
    "sg:postcode":"07003",
    "sg:province":"Islas Baleares",
    "wof:name":"Vidal Gil Maria Del Pilar",
    "wof:placetype":"venue"
},
  "geometry": {"coordinates":[2.648086071,39.5797233582],"type":"Point"}
}