{
  "type": "Feature",
  "properties": {
    "iso:country":"ES",
    "sg:address":"Calle de Sancho Panza, 1",
    "sg:city":"Granada",
    "sg:orig_category":"M\u00c9dicos: Medicina General Orientada A La Acupuntura",
    "sg:phone":"+34 958 12 84 80",
    "sg:postcode":"18008",
    "sg:province":"Granada",
    "wof:name":"Acu\u00f1a Garcia Francisco",
    "wof:placetype":"venue"
},
  "geometry": {"coordinates":[-3.5878059864,37.1630706787],"type":"Point"}
}