{
  "type": "Feature",
  "properties": {
    "addr:full":"Calle de Sirio, 6 Madrid Madrid 28007",
    "addr:housenumber":"6",
    "addr:postcode":"28007",
    "addr:street":"Calle De Sirio",
    "iso:country":"ES",
    "sg:address":"Calle de Sirio, 6",
    "sg:city":"Madrid",
    "sg:orig_category":"Tiendas De Grano, Frutas Y Legumbres Secas (al Por Menor)",
    "sg:phone":"+34 915 73 11 35",
    "sg:postcode":"28007",
    "sg:province":"Madrid",
    "wof:name":"Vinuesa I\u00f1iguez Eduardo",
    "wof:placetype":"venue"
},
  "geometry": {"coordinates":[-3.6670870781,40.4070892334],"type":"Point"}
}