{
  "type": "Feature",
  "properties": {
    "iso:country":"ES",
    "sg:address":"Carrer de Sant Lluis, 29",
    "sg:city":"Gava",
    "sg:orig_category":"Fabricaci\u00d3n De Cortinas Y Visillos",
    "sg:phone":"+34 936 62 93 55",
    "sg:postcode":"08850",
    "sg:province":"Barcelona",
    "wof:name":"Cruz Moreno Maria Pilar",
    "wof:placetype":"venue"
},
  "geometry": {"coordinates":[2.0035469532,41.3058776855],"type":"Point"}
}