{
  "type": "Feature",
  "properties": {
    "addr:full":"Calle de Bielsa, 12 Barbastro Huesca 22300",
    "addr:housenumber":"12",
    "addr:postcode":"22300",
    "addr:street":"Calle De Bielsa",
    "iso:country":"ES",
    "sg:address":"Calle de Bielsa, 12",
    "sg:city":"Barbastro",
    "sg:orig_category":"Empresas De Pintura Y Revestimientos",
    "sg:phone":"+34 974 31 02 92",
    "sg:postcode":"22300",
    "sg:province":"Huesca",
    "wof:name":"Puy Cazcarra Conrado",
    "wof:placetype":"venue"
},
  "geometry": {"coordinates":[0.1248755008,42.033367157],"type":"Point"}
}