{
  "type": "Feature",
  "properties": {
    "iso:country":"ES",
    "sg:address":"Calle de Ronda Exterior, 11",
    "sg:city":"Gijon",
    "sg:orig_category":"Molduras, Junquillos, Listones Y Molduras Perforadas",
    "sg:phone":"+34 985 39 58 13",
    "sg:postcode":"33210",
    "sg:province":"Asturias",
    "wof:name":"Sistelcom-telemensaje S.a.",
    "wof:placetype":"venue"
},
  "geometry": {"coordinates":[-5.6680288315,43.5232582092],"type":"Point"}
}