{
  "type": "Feature",
  "properties": {
    "addr:full":"Carrer de Josep Anselm Clave, 21 Santa Coloma De Gramenet Barcelona 08921",
    "addr:housenumber":"21",
    "addr:postcode":"08921",
    "addr:street":"Carrer De Josep Anselm Clave",
    "iso:country":"ES",
    "sg:address":"Carrer de Josep Anselm Clave, 21",
    "sg:city":"Santa Coloma De Gramenet",
    "sg:orig_category":"Agencias De Viajes",
    "sg:phone":"+34 934 66 22 98",
    "sg:postcode":"08921",
    "sg:province":"Barcelona",
    "sg:website":"www.barceloviajes.com",
    "wof:name":"Viajes Barcelo S.l.",
    "wof:placetype":"venue"
},
  "geometry": {"coordinates":[2.208739996,41.4530181885],"type":"Point"}
}