{
  "type": "Feature",
  "properties": {
    "iso:country":"ES",
    "sg:address":"Calle de Beato Tomas De Zumarraga, 31",
    "sg:city":"Vitoria-gasteiz",
    "sg:orig_category":"Fabricaci\u00d3n, Importaci\u00d3n, Venta De Material De Telefon\u00cda, Peritelefon\u00cda",
    "sg:phone":"+34 945 22 72 00",
    "sg:postcode":"01008",
    "sg:province":"\u00c1lava",
    "sg:website":"www.naturalvox.com",
    "wof:name":"Natural Vox S.a.",
    "wof:placetype":"venue"
},
  "geometry": {"coordinates":[-2.6866858006,42.8509063721],"type":"Point"}
}