{
  "type": "Feature",
  "properties": {
    "addr:full":"Calle de Atarizar, 22 Donostia-san Sebastian Guip\u00f9zcoa 20013",
    "addr:housenumber":"22",
    "addr:postcode":"20013",
    "addr:street":"Calle De Atarizar",
    "iso:country":"ES",
    "sg:address":"Calle de Atarizar, 22",
    "sg:city":"Donostia-san Sebastian",
    "sg:orig_category":"Centros De Educaci\u00d3n Especial",
    "sg:phone":"+34 943 32 04 28",
    "sg:postcode":"20013",
    "sg:province":"Guip\u00f9zcoa",
    "wof:name":"Gobierno Vasco-eusko Jaurlaritza",
    "wof:placetype":"venue"
},
  "geometry": {"coordinates":[-1.9616783857,43.3213386536],"type":"Point"}
}