{
  "type": "Feature",
  "properties": {
    "iso:country":"ES",
    "sg:address":"Carrer de Ferrers (dels), 1",
    "sg:city":"Tarragona",
    "sg:orig_category":"Material Y Suministros Para Imprenta E Industrias Gr\u00c1ficas",
    "sg:phone":"+34 977 23 32 51",
    "sg:postcode":"43003",
    "sg:province":"Tarragona",
    "wof:name":"Impremta Virgili C.b.",
    "wof:placetype":"venue"
},
  "geometry": {"coordinates":[1.2546260357,41.118019104],"type":"Point"}
}