{
  "type": "Feature",
  "properties": {
    "iso:country":"ES",
    "sg:address":"Carrer de Sofre (del), S/n",
    "sg:city":"Floresta",
    "sg:orig_category":"V\u00c1lvulas",
    "sg:phone":"+34 977 20 67 00",
    "sg:postcode":"43006",
    "sg:province":"Tarragona",
    "sg:website":"www.mecesa.com",
    "wof:name":"Mecanica Egarense S.a.",
    "wof:placetype":"venue"
},
  "geometry": {"coordinates":[1.2209249735,41.1154441833],"type":"Point"}
}