{
  "type": "Feature",
  "properties": {
    "iso:country":"ES",
    "sg:address":"Calle de Lienzos (los), 10",
    "sg:city":"Fuentes De Ropel",
    "sg:orig_category":"Iglesia Cat\u00d3lica",
    "sg:phone":"+34 980 66 30 15",
    "sg:postcode":"49670",
    "sg:province":"Zamora",
    "wof:name":"Obispado De Zamora",
    "wof:placetype":"venue"
},
  "geometry": {"coordinates":[-5.5425729752,42.0024223328],"type":"Point"}
}