{
  "type": "Feature",
  "properties": {
    "iso:country":"ES",
    "sg:address":"Psaj Sancho Alvarez, 10",
    "sg:city":"Madridejos",
    "sg:orig_category":"Transportes Por V\u00cdas Navegables",
    "sg:phone":"+34 925 46 03 46",
    "sg:postcode":"45710",
    "sg:province":"Toledo",
    "wof:name":"Gonzalez Martin Pedro",
    "wof:placetype":"venue"
},
  "geometry": {"coordinates":[-3.5349140167,39.4685554504],"type":"Point"}
}