{
  "type": "Feature",
  "properties": {
    "iso:country":"ES",
    "sg:address":"Av Diagonal, 478",
    "sg:city":"Barcelona",
    "sg:orig_category":"Farmacias",
    "sg:phone":"+34 934 16 12 70",
    "sg:postcode":"08006",
    "sg:province":"Barcelona",
    "wof:name":"Serra Mandri Juan Maria",
    "wof:placetype":"venue"
},
  "geometry": {"coordinates":[2.1558530331,41.3959388733],"type":"Point"}
}