{
  "type": "Feature",
  "properties": {
    "addr:full":"Avda Galicia De, 14 Salas Asturias 33860",
    "addr:housenumber":"14",
    "addr:postcode":"33860",
    "addr:street":"Avda Galicia De",
    "iso:country":"ES",
    "sg:address":"Avda Galicia De, 14",
    "sg:city":"Salas",
    "sg:orig_category":"Bancos",
    "sg:phone":"+34 985 83 00 03",
    "sg:postcode":"33860",
    "sg:province":"Asturias",
    "sg:website":"www.banesto.es",
    "wof:name":"Banco Espa\u00f1ol De Credito S.a.",
    "wof:placetype":"venue"
},
  "geometry": {"coordinates":[-6.2590689659,43.4085884094],"type":"Point"}
}