{
  "type": "Feature",
  "properties": {
    "iso:country":"ES",
    "sg:address":"Ctra Carretera Carrion (poligono Industrial), 78",
    "sg:city":"Ciudad Real",
    "sg:orig_category":"Agentes, Concesionarios Y Sucursales De Veh\u00cdculos",
    "sg:phone":"+34 926 22 20 99",
    "sg:postcode":"13005",
    "sg:province":"Ciudad Real",
    "wof:name":"Euro Turismo S.a.l.",
    "wof:placetype":"venue"
},
  "geometry": {"coordinates":[-3.9525969028,38.9611473083],"type":"Point"}
}