{
  "type": "Feature",
  "properties": {
    "addr:full":"Cmno Llano Del Espartal, S/n Alacant Alicante 03006",
    "addr:housenumber":"s / n",
    "addr:postcode":"03006",
    "addr:street":"Cmno Llano Del Espartal",
    "iso:country":"ES",
    "sg:address":"Cmno Llano Del Espartal, S/n",
    "sg:city":"Alacant",
    "sg:orig_category":"Postigos, Persianas Y Celos\u00cdas",
    "sg:phone":"+34 965 11 30 34",
    "sg:postcode":"03006",
    "sg:province":"Alicante",
    "wof:name":"Romalux S.l.",
    "wof:placetype":"venue"
},
  "geometry": {"coordinates":[-0.5278589725,38.348526001],"type":"Point"}
}