{
  "type": "Feature",
  "properties": {
    "addr:full":"Carrer de Previssio, 11 S. Joan Despi Barcelona 08970",
    "addr:housenumber":"11",
    "addr:postcode":"08970",
    "addr:street":"Carrer De Previssio;S. Joan Despi",
    "iso:country":"ES",
    "sg:address":"Carrer de Previssio, 11",
    "sg:city":"S. Joan Despi",
    "sg:orig_category":"Fabricaci\u00d3n De Jabones, Detergentes Y Lej\u00cdas",
    "sg:phone":"+34 933 73 66 96",
    "sg:postcode":"08970",
    "sg:province":"Barcelona",
    "wof:name":"Dosyquim S.l.",
    "wof:placetype":"venue"
},
  "geometry": {"coordinates":[2.0581920147,41.3663330078],"type":"Point"}
}