{
  "type": "Feature",
  "properties": {
    "iso:country":"ES",
    "sg:address":"Ctra. Pamplona, S/n",
    "sg:city":"Campanas",
    "sg:orig_category":"Acero: Productos Sider\u00dargicos Y Transformados (fabricaci\u00d3n, Negocio)",
    "sg:phone":"+34 948 36 01 03",
    "sg:postcode":"31397",
    "sg:province":"Navarra",
    "wof:name":"Talleres Feudo S.l.",
    "wof:placetype":"venue"
},
  "geometry": {"coordinates":[-1.6374239922,42.6963653564],"type":"Point"}
}