{
  "type": "Feature",
  "properties": {
    "addr:full":"Av. San Ignacio, 6 Iru\u00f1a Navarra 31002",
    "addr:housenumber":"6",
    "addr:postcode":"31002",
    "addr:street":"Av. San Ignacio",
    "iso:country":"ES",
    "sg:address":"Av. San Ignacio, 6",
    "sg:city":"Iru\u00f1a",
    "sg:orig_category":"Sociedades, Compa\u00d1\u00cdas Aseguradoras",
    "sg:phone":"+34 948 22 04 01",
    "sg:postcode":"31002",
    "sg:province":"Navarra",
    "wof:name":"Mutua General Seguros",
    "wof:placetype":"venue"
},
  "geometry": {"coordinates":[-1.6433149576,42.8151855469],"type":"Point"}
}