{
  "type": "Feature",
  "properties": {
    "addr:full":"Calle de Sol, 10 Mora Toledo 45400",
    "addr:housenumber":"10",
    "addr:postcode":"45400",
    "addr:street":"Calle De Sol",
    "iso:country":"ES",
    "sg:address":"Calle de Sol, 10",
    "sg:city":"Mora",
    "sg:orig_category":"Empresas De Demolici\u00d3n",
    "sg:phone":"+34 925 30 14 08",
    "sg:postcode":"45400",
    "sg:province":"Toledo",
    "wof:name":"Palmero Gomez Domingo",
    "wof:placetype":"venue"
},
  "geometry": {"coordinates":[-3.7734720707,39.6789245605],"type":"Point"}
}