{
  "type": "Feature",
  "properties": {
    "addr:full":"Calle de Martin De Vargas, 3 Madrid Madrid 28005",
    "addr:housenumber":"3",
    "addr:postcode":"28005",
    "addr:street":"Calle De Martin De Vargas",
    "iso:country":"ES",
    "sg:address":"Calle de Martin De Vargas, 3",
    "sg:city":"Madrid",
    "sg:orig_category":"Fabricaci\u00d3n De Juguetes Autom\u00c1ticos",
    "sg:phone":"+34 915 17 57 35",
    "sg:postcode":"28005",
    "sg:province":"Madrid",
    "wof:name":"Tetra Comercial Del Ocio S.l.",
    "wof:placetype":"venue"
},
  "geometry": {"coordinates":[-3.7031340599,40.4046401978],"type":"Point"}
}