{
  "type": "Feature",
  "properties": {
    "addr:full":"Avda Manuel Navarro, 31 Puebla Vicar Almer\u00eda 04738",
    "addr:housenumber":"31",
    "addr:postcode":"04738",
    "addr:street":"Avda Manuel Navarro",
    "iso:country":"ES",
    "sg:address":"Avda Manuel Navarro, 31",
    "sg:city":"Puebla Vicar",
    "sg:orig_category":"Zapatos (al Por Menor)",
    "sg:phone":"+34 950 55 31 69",
    "sg:postcode":"04738",
    "sg:province":"Almer\u00eda",
    "wof:name":"Poyato Gomez Dolores",
    "wof:placetype":"venue"
},
  "geometry": {"coordinates":[-2.6420009136,36.8316612244],"type":"Point"}
}