{
  "type": "Feature",
  "properties": {
    "iso:country":"ES",
    "sg:address":"Urb La Campana, 7",
    "sg:city":"Punta Prima",
    "sg:orig_category":"Bisuter\u00cda, Joyer\u00cda, Relojer\u00cda (al Por Menor)",
    "sg:phone":"+34 965 32 89 94",
    "sg:postcode":"03189",
    "sg:province":"Alicante",
    "wof:name":"Ba\u00f1os Martinez Adela",
    "wof:placetype":"venue"
},
  "geometry": {"coordinates":[-0.7374460101,37.948802948],"type":"Point"}
}