{
  "type": "Feature",
  "properties": {
    "addr:full":"Calle de Espiritu Santo, 38 Madrid Madrid 28004",
    "addr:housenumber":"38",
    "addr:postcode":"madrid;28004",
    "addr:street":"Calle De Espiritu Santo",
    "iso:country":"ES",
    "sg:address":"Calle de Espiritu Santo, 38",
    "sg:city":"Madrid",
    "sg:orig_category":"Molduras, Junquillos, Listones Y Molduras Perforadas",
    "sg:phone":"+34 915 21 73 46",
    "sg:postcode":"28004",
    "sg:province":"Madrid",
    "wof:name":"Jurado Rodriguez Angel Luis",
    "wof:placetype":"venue"
},
  "geometry": {"coordinates":[-3.704934597,40.4255599976],"type":"Point"}
}