{
  "type": "Feature",
  "properties": {
    "addr:full":"Pase San Anton, 79 Llerena Badajoz 06900",
    "addr:housenumber":"79",
    "addr:postcode":"06900",
    "addr:street":"San Anton",
    "iso:country":"ES",
    "sg:address":"Pase San Anton, 79",
    "sg:city":"Llerena",
    "sg:orig_category":"Promotores Constructores",
    "sg:phone":"+34 924 87 21 66",
    "sg:postcode":"06900",
    "sg:province":"Badajoz",
    "wof:name":"U.t.e.campi\u00f1a Sur",
    "wof:placetype":"venue"
},
  "geometry": {"coordinates":[-6.016368866,38.2411804199],"type":"Point"}
}