{
  "type": "Feature",
  "properties": {
    "iso:country":"ES",
    "sg:address":"Calle de Rumania, 5",
    "sg:city":"Alcala Henares",
    "sg:orig_category":"Ense\u00d1anza: Comercio, Gesti\u00d3n, Inform\u00c1tica",
    "sg:phone":"+34 918 78 90 33",
    "sg:postcode":"28802",
    "sg:province":"Madrid",
    "sg:website":"www.binary.es",
    "wof:name":"Binary Soluciones Informaticas S.l.",
    "wof:placetype":"venue"
},
  "geometry": {"coordinates":[-3.4041180611,40.4754447937],"type":"Point"}
}