{
  "type": "Feature",
  "properties": {
    "iso:country":"ES",
    "sg:address":"Calle de Alonso Cano, 50",
    "sg:city":"Madrid",
    "sg:orig_category":"Costureras",
    "sg:phone":"+34 915 53 05 14",
    "sg:postcode":"28003",
    "sg:province":"Madrid",
    "wof:name":"Garcia Lopez Saturnino",
    "wof:placetype":"venue"
},
  "geometry": {"coordinates":[-3.6974835396,40.4419288635],"type":"Point"}
}