{
  "type": "Feature",
  "properties": {
    "iso:country":"ES",
    "sg:address":"Calle de Fundadora De Las Siervas De Jesus, 3",
    "sg:city":"Vitoria-gasteiz",
    "sg:orig_category":"Empresarios",
    "sg:phone":"+34 945 25 26 33",
    "sg:postcode":"01001",
    "sg:province":"\u00c1lava",
    "wof:name":"Sociedad De Gestion De Los Centros Historicos De Alava Arabarri S.a.",
    "wof:placetype":"venue"
},
  "geometry": {"coordinates":[-2.6751339436,42.847858429],"type":"Point"}
}