{
  "type": "Feature",
  "properties": {
    "addr:full":"Carr Porreres, 2 Felanitx Islas Baleares 07200",
    "addr:housenumber":"2",
    "addr:postcode":"07200",
    "addr:street":"Carr Porreres",
    "iso:country":"ES",
    "sg:address":"Carr Porreres, 2",
    "sg:city":"Felanitx",
    "sg:orig_category":"Importaci\u00d3n",
    "sg:phone":"+34 971 58 03 80",
    "sg:postcode":"07200",
    "sg:province":"Islas Baleares",
    "wof:name":"Vidal Barcelo Sebastian",
    "wof:placetype":"venue"
},
  "geometry": {"coordinates":[3.1440649033,39.4740219116],"type":"Point"}
}