{
  "type": "Feature",
  "properties": {
    "addr:full":"Crta Breda, S/n Viabrea Girona 17404",
    "addr:housenumber":"/ n",
    "addr:postcode":"17404",
    "addr:street":"Crta Breda S",
    "iso:country":"ES",
    "sg:address":"Crta Breda, S/n",
    "sg:city":"Viabrea",
    "sg:orig_category":"Materias Pl\u00c1sticas: Productos De Consumo Masivo (fabricaci\u00d3n, Al Por Mayor)",
    "sg:phone":"+34 938 47 23 29",
    "sg:postcode":"17404",
    "sg:province":"Girona",
    "wof:name":"Decotec S.l.",
    "wof:placetype":"venue"
},
  "geometry": {"coordinates":[2.548609972,41.7198448181],"type":"Point"}
}