{
  "type": "Feature",
  "properties": {
    "addr:full":"Calle de Almeria, 12 Catarroja Valencia 46470",
    "addr:housenumber":"12",
    "addr:postcode":"46470",
    "addr:street":"Calle De Almeria",
    "iso:country":"ES",
    "sg:address":"Calle de Almeria, 12",
    "sg:city":"Catarroja",
    "sg:orig_category":"Ropa Y Accesorios",
    "sg:phone":"+34 961 27 25 36",
    "sg:postcode":"46470",
    "sg:province":"Valencia",
    "wof:name":"Almenar Serra Filomena",
    "wof:placetype":"venue"
},
  "geometry": {"coordinates":[-0.4052577913,39.4062423706],"type":"Point"}
}