{
  "type": "Feature",
  "properties": {
    "addr:full":"C/ Mare De Deu De La Neu, 11 Manacor Islas Baleares 07500",
    "addr:housenumber":"11",
    "addr:postcode":"07500",
    "addr:street":"C / Mare De Deu De La Neu",
    "iso:country":"ES",
    "sg:address":"C/ Mare De Deu De La Neu, 11",
    "sg:city":"Manacor",
    "sg:orig_category":"Sociedades, Compa\u00d1\u00cdas Aseguradoras",
    "sg:phone":"+34 971 55 24 50",
    "sg:postcode":"07500",
    "sg:province":"Islas Baleares",
    "wof:name":"Llull Segur Correduria De Seguros",
    "wof:placetype":"venue"
},
  "geometry": {"coordinates":[3.2123410702,39.5674057007],"type":"Point"}
}