{
  "type": "Feature",
  "properties": {
    "iso:country":"ES",
    "sg:address":"Cargadero Del Mineral, S/n",
    "sg:city":"Melilla",
    "sg:orig_category":"Centros P\u00dablicos De Formaci\u00d3n Profesional Y T\u00c9cnica",
    "sg:phone":"+34 952 69 67 59",
    "sg:postcode":"52004",
    "sg:province":"Melilla",
    "wof:name":"Colegio De Ingenieros De Caminos, Puertos Y Canales.",
    "wof:placetype":"venue"
},
  "geometry": {"coordinates":[-2.9414598942,35.2887496948],"type":"Point"}
}