{
  "type": "Feature",
  "properties": {
    "addr:full":"Calle de Las Marismas, 23 Madrid Madrid 28038",
    "addr:housenumber":"23",
    "addr:postcode":"madrid;28038",
    "addr:street":"Calle De Las Marismas",
    "iso:country":"ES",
    "sg:address":"Calle de Las Marismas, 23",
    "sg:city":"Madrid",
    "sg:orig_category":"Marroquiner\u00cda (confecci\u00d3n)",
    "sg:phone":"+34 915 01 61 08",
    "sg:postcode":"28038",
    "sg:province":"Madrid",
    "wof:name":"Piel Urbana S.l.",
    "wof:placetype":"venue"
},
  "geometry": {"coordinates":[-3.6545920372,40.4028015137],"type":"Point"}
}