{
  "type": "Feature",
  "properties": {
    "addr:full":"Ctra Navarrete (de), 20 Fuenmayor La Rioja 26360",
    "addr:housenumber":"20",
    "addr:postcode":"26360",
    "addr:street":"Ctra Navarrete De;Rioja",
    "iso:country":"ES",
    "sg:address":"Ctra Navarrete (de), 20",
    "sg:city":"Fuenmayor",
    "sg:orig_category":"Paneles De Madera: Contrachapados, Fibras, Particulados, Estratificados (fabricaci\u00d3n, Venta)",
    "sg:phone":"+34 941 45 05 00",
    "sg:postcode":"26360",
    "sg:province":"La Rioja",
    "wof:name":"Garnica Plywood Fuenmayor S.l.u.",
    "wof:placetype":"venue"
},
  "geometry": {"coordinates":[-2.5643351078,42.4638252258],"type":"Point"}
}