{
  "type": "Feature",
  "properties": {
    "iso:country":"ES",
    "sg:address":"Calle de Asilo, 11",
    "sg:city":"Puertollano",
    "sg:orig_category":"Reposter\u00cdas",
    "sg:phone":"+34 926 42 52 10",
    "sg:postcode":"13500",
    "sg:province":"Ciudad Real",
    "wof:name":"Carrion Caminero Jesus",
    "wof:placetype":"venue"
},
  "geometry": {"coordinates":[-4.0992078781,38.6846847534],"type":"Point"}
}