{
  "type": "Feature",
  "properties": {
    "addr:full":"Cami Geganta (de La), 1 Mataro Barcelona 08302",
    "addr:housenumber":"1",
    "addr:postcode":"08302",
    "addr:street":"Mataro Barcelona",
    "iso:country":"ES",
    "sg:address":"Cami Geganta (de La), 1",
    "sg:city":"Mataro",
    "sg:orig_category":"Platos Preparados Refrigerados (fabricaci\u00d3n, Al Por Mayor)",
    "sg:phone":"+34 937 98 06 68",
    "sg:postcode":"08302",
    "sg:province":"Barcelona",
    "wof:name":"Gabinet Admin Ramon Gomez S.l.",
    "wof:placetype":"venue"
},
  "geometry": {"coordinates":[2.4408268929,41.5442123413],"type":"Point"}
}