{
  "type": "Feature",
  "properties": {
    "addr:full":"Martin Azpilcueta, 10 Iru\u00f1a Navarra 31011",
    "addr:housenumber":"10",
    "addr:postcode":"31011",
    "addr:street":"Azpilcueta",
    "iso:country":"ES",
    "sg:address":"Martin Azpilcueta, 10",
    "sg:city":"Iru\u00f1a",
    "sg:orig_category":"Carnicer\u00cdas, Carnicer\u00cdas",
    "sg:phone":"+34 948 19 65 82",
    "sg:postcode":"31011",
    "sg:province":"Navarra",
    "wof:name":"Carnicerias Juan Carlos S.l.",
    "wof:placetype":"venue"
},
  "geometry": {"coordinates":[-1.6631629467,42.8142547607],"type":"Point"}
}