{
  "type": "Feature",
  "properties": {
    "iso:country":"ES",
    "sg:address":"Plaz Ayuntamiento (el), 1",
    "sg:city":"Ponferrada",
    "sg:orig_category":"Administraciones Regionales, Departamentales Y Locales",
    "sg:phone":"+34 987 44 66 00",
    "sg:postcode":"24400",
    "sg:province":"Le\u00f3n",
    "wof:name":"Ayuntamiento De Ponferrada",
    "wof:placetype":"venue"
},
  "geometry": {"coordinates":[-6.5996961594,42.4982566833],"type":"Point"}
}