{
  "type": "Feature",
  "properties": {
    "addr:full":"Calle de Virgen De La Cabeza, 59 Valencia Valencia 46014",
    "addr:housenumber":"59",
    "addr:postcode":"46014",
    "addr:street":"Calle De Virgen De La Cabeza",
    "iso:country":"ES",
    "sg:address":"Calle de Virgen De La Cabeza, 59",
    "sg:city":"Valencia",
    "sg:orig_category":"Arquitectos",
    "sg:phone":"+34 963 57 31 84",
    "sg:postcode":"46014",
    "sg:province":"Valencia",
    "wof:name":"Garcia Candel Ricardo",
    "wof:placetype":"venue"
},
  "geometry": {"coordinates":[-0.3993990123,39.4620132446],"type":"Point"}
}