{
  "type": "Feature",
  "properties": {
    "iso:country":"ES",
    "sg:address":"Carrer de Tres Creus, 138",
    "sg:city":"Sabadell",
    "sg:orig_category":"Agencias De Viajes",
    "sg:phone":"+34 937 15 60 10",
    "sg:postcode":"08202",
    "sg:province":"Barcelona",
    "wof:name":"Viatges Mirpe8 Catalunya S.l.l.",
    "wof:placetype":"venue"
},
  "geometry": {"coordinates":[2.1135759354,41.5460281372],"type":"Point"}
}