{
  "type": "Feature",
  "properties": {
    "iso:country":"ES",
    "sg:address":"Doctor Gortari, 3",
    "sg:city":"Iru\u00f1a",
    "sg:orig_category":"Transportes Por V\u00cdas Navegables",
    "sg:phone":"+34 948 14 18 40",
    "sg:postcode":"31012",
    "sg:province":"Navarra",
    "wof:name":"Leon Serrano Pedro",
    "wof:placetype":"venue"
},
  "geometry": {"coordinates":[-1.6683080196,42.8213348389],"type":"Point"}
}