{
  "type": "Feature",
  "properties": {
    "iso:country":"ES",
    "sg:address":"Plaz Monse\u00d1or Bocanegra, 20",
    "sg:city":"Malaga",
    "sg:orig_category":"Reposter\u00cdas",
    "sg:phone":"+34 952 28 98 89",
    "sg:postcode":"29011",
    "sg:province":"M\u00e1laga",
    "wof:name":"Alorpan S.l.",
    "wof:placetype":"venue"
},
  "geometry": {"coordinates":[-4.4336438179,36.7910690308],"type":"Point"}
}