{
  "type": "Feature",
  "properties": {
    "addr:full":"Calle de Juan Espa\u00d1ol, 42 Madrid Madrid 28026",
    "addr:housenumber":"42",
    "addr:postcode":"madrid;28026",
    "addr:street":"Calle De Juan Espan\u0303Ol",
    "iso:country":"ES",
    "sg:address":"Calle de Juan Espa\u00d1ol, 42",
    "sg:city":"Madrid",
    "sg:orig_category":"Congelados: Productos Alimentarios (al Por Menor)",
    "sg:phone":"+34 914 60 29 02",
    "sg:postcode":"28026",
    "sg:province":"Madrid",
    "wof:name":"Nu\u00f1ez Calzado Jose Antonio",
    "wof:placetype":"venue"
},
  "geometry": {"coordinates":[-3.7132520676,40.3865127563],"type":"Point"}
}