{
  "type": "Feature",
  "properties": {
    "addr:full":"Avda Alt Rei En Jaume I (l'), 12 Altea Alicante 03590",
    "addr:housenumber":"12",
    "addr:postcode":"03590",
    "addr:street":"Avda Alt Rei En Jaume I L '",
    "iso:country":"ES",
    "sg:address":"Avda Alt Rei En Jaume I (l'), 12",
    "sg:city":"Altea",
    "sg:orig_category":"Administradores De Bienes Y Delegados De Comunidades De Propietarios",
    "sg:phone":"+34 965 84 12 96",
    "sg:postcode":"03590",
    "sg:province":"Alicante",
    "wof:name":"Flores Feo Vicente",
    "wof:placetype":"venue"
},
  "geometry": {"coordinates":[-0.0464509986,38.6026573181],"type":"Point"}
}