{
  "type": "Feature",
  "properties": {
    "iso:country":"ES",
    "sg:address":"Calle de Granados, 15",
    "sg:city":"Daimiel",
    "sg:orig_category":"Alimentaci\u00d3n General (al Por Menor)",
    "sg:phone":"+34 926 85 02 54",
    "sg:postcode":"13250",
    "sg:province":"Ciudad Real",
    "wof:name":"Arroyo Garcia-consuegra Felipe",
    "wof:placetype":"venue"
},
  "geometry": {"coordinates":[-3.6136782169,39.0721321106],"type":"Point"}
}