{
  "type": "Feature",
  "properties": {
    "addr:full":"Calle de Agustin De Foxa, 31 Madrid Madrid 28036",
    "addr:housenumber":"31",
    "addr:postcode":"madrid;28036",
    "addr:street":"Calle De Agustin De Foxa",
    "iso:country":"ES",
    "sg:address":"Calle de Agustin De Foxa, 31",
    "sg:city":"Madrid",
    "sg:orig_category":"Agricultores, Agricultores",
    "sg:phone":"+34 913 14 02 69",
    "sg:postcode":"28036",
    "sg:province":"Madrid",
    "wof:name":"Caballero Chamorro Jose Francisco",
    "wof:placetype":"venue"
},
  "geometry": {"coordinates":[-3.6843500137,40.4716491699],"type":"Point"}
}