{
  "type": "Feature",
  "properties": {
    "addr:full":"Avda Sierra (la), 13 Najera La Rioja 26300",
    "addr:housenumber":"13",
    "addr:postcode":"26300",
    "addr:street":"Avda Sierra La;Rioja",
    "iso:country":"ES",
    "sg:address":"Avda Sierra (la), 13",
    "sg:city":"Najera",
    "sg:orig_category":"Carnicer\u00cdas, Carnicer\u00cdas",
    "sg:phone":"+34 941 36 22 52",
    "sg:postcode":"26300",
    "sg:province":"La Rioja",
    "wof:name":"Busto Oporto Julia",
    "wof:placetype":"venue"
},
  "geometry": {"coordinates":[-2.7296791077,42.4170265198],"type":"Point"}
}