{
  "type": "Feature",
  "properties": {
    "addr:full":"Carrer de Lepant, 246 Barcelona Barcelona 08013",
    "addr:housenumber":"246",
    "addr:postcode":"08013",
    "addr:street":"Carrer De Lepant",
    "iso:country":"ES",
    "sg:address":"Carrer de Lepant, 246",
    "sg:city":"Barcelona",
    "sg:orig_category":"Radiocomunicaciones, Telefon\u00cda M\u00d3vil, Radiomensajer\u00cda: Servicios, Comercializaci\u00d3n",
    "sg:phone":"+34 932 65 40 52",
    "sg:postcode":"08013",
    "sg:province":"Barcelona",
    "wof:name":"Vazquez Llerena Ivan Enrique",
    "wof:placetype":"venue"
},
  "geometry": {"coordinates":[2.1788730621,41.4030036926],"type":"Point"}
}