{
  "type": "Feature",
  "properties": {
    "addr:full":"Carrer de Conca De Barbera, 4 Valls Tarragona 43800",
    "addr:housenumber":"4",
    "addr:postcode":"43800",
    "addr:street":"Carrer De Conca De Barbera",
    "iso:country":"ES",
    "sg:address":"Carrer de Conca De Barbera, 4",
    "sg:city":"Valls",
    "sg:orig_category":"Tapicer\u00cdas",
    "sg:phone":"+34 977 61 49 04",
    "sg:postcode":"43800",
    "sg:province":"Tarragona",
    "wof:name":"Pujol Escarre Pere",
    "wof:placetype":"venue"
},
  "geometry": {"coordinates":[1.24219203,41.2858581543],"type":"Point"}
}