{
  "type": "Feature",
  "properties": {
    "iso:country":"ES",
    "sg:address":"Carrer de Canyelles (de), 12",
    "sg:city":"Tarragona",
    "sg:orig_category":"Ropa Para Se\u00d1oras (al Por Menor)",
    "sg:phone":"+34 977 23 36 33",
    "sg:postcode":"43001",
    "sg:province":"Tarragona",
    "wof:name":"Mestre Calvet Jose",
    "wof:placetype":"venue"
},
  "geometry": {"coordinates":[1.2499370575,41.1159095764],"type":"Point"}
}