{
  "type": "Feature",
  "properties": {
    "iso:country":"ES",
    "sg:address":"Cami Bruixes (les), 5",
    "sg:city":"Alpicat",
    "sg:orig_category":"Material Y Suministros Para Horticultura, Arboricultura",
    "sg:phone":"+34 973 73 63 23",
    "sg:postcode":"25110",
    "sg:province":"Lleida",
    "wof:name":"Domingo Batlle Antonio",
    "wof:placetype":"venue"
},
  "geometry": {"coordinates":[0.5455330014,41.6560020447],"type":"Point"}
}