{
  "type": "Feature",
  "properties": {
    "iso:country":"ES",
    "sg:address":"Mercamadrid, Km. 0003,8",
    "sg:city":"Madrid",
    "sg:orig_category":"Almacenes Frigor\u00cdficos",
    "sg:phone":"+34 917 86 20 03",
    "sg:postcode":"28053",
    "sg:province":"Madrid",
    "wof:name":"Atolon 98 S.a.",
    "wof:placetype":"venue"
},
  "geometry": {"coordinates":[-3.6673941612,40.3681945801],"type":"Point"}
}