{
  "type": "Feature",
  "properties": {
    "addr:full":"Cami Ral, 121 Mataro Barcelona 08301",
    "addr:housenumber":"121",
    "addr:postcode":"08301",
    "addr:street":"Ral",
    "iso:country":"ES",
    "sg:address":"Cami Ral, 121",
    "sg:city":"Mataro",
    "sg:orig_category":"Fabricaci\u00d3n, Instalaci\u00d3n Y Reparaci\u00d3n De Bombas",
    "sg:phone":"+34 937 96 48 56",
    "sg:postcode":"08301",
    "sg:province":"Barcelona",
    "wof:name":"Servicios Y Mercancias Exclusivas S.l.",
    "wof:placetype":"venue"
},
  "geometry": {"coordinates":[2.4524049759,41.5405426025],"type":"Point"}
}