{
  "type": "Feature",
  "properties": {
    "addr:full":"Ptda Salinetas, 56 Petrer Alicante 03610",
    "addr:housenumber":"56",
    "addr:postcode":"03610",
    "addr:street":"Ptda Salinetas",
    "iso:country":"ES",
    "sg:address":"Ptda Salinetas, 56",
    "sg:city":"Petrer",
    "sg:orig_category":"Zapater\u00cdas",
    "sg:phone":"+34 965 37 15 09",
    "sg:postcode":"03610",
    "sg:province":"Alicante",
    "wof:name":"Tacones Gamar S. L.",
    "wof:placetype":"venue"
},
  "geometry": {"coordinates":[-0.7711269855,38.4766960144],"type":"Point"}
}