{
  "type": "Feature",
  "properties": {
    "iso:country":"ES",
    "sg:address":"Calle de General Martinez Anido, 3",
    "sg:city":"Palmas De Gran Canaria",
    "sg:orig_category":"Arquitectos",
    "sg:phone":"+34 928 36 41 36",
    "sg:postcode":"35003",
    "sg:province":"Las Palmas",
    "wof:name":"Blanco Bautista Manuel",
    "wof:placetype":"venue"
},
  "geometry": {"coordinates":[-15.4219093323,28.1124305725],"type":"Point"}
}