{
  "type": "Feature",
  "properties": {
    "iso:country":"ES",
    "sg:address":"As Gandaras, S/n",
    "sg:city":"Porri\u00f1o",
    "sg:orig_category":"Hormig\u00d3n (m\u00c1quinas E Instalaci\u00d3n)",
    "sg:phone":"+34 986 33 19 00",
    "sg:postcode":"36475",
    "sg:province":"Pontevedra",
    "wof:name":"Ingenieria De Prefabricados S.l",
    "wof:placetype":"venue"
},
  "geometry": {"coordinates":[-8.606926918,42.1053466797],"type":"Point"}
}