{
  "type": "Feature",
  "properties": {
    "addr:full":"Calle de Marques De Pickman, 9 Sevilla Sevilla 41005",
    "addr:housenumber":"9",
    "addr:postcode":"41005",
    "addr:street":"Calle De Marques De Pickman",
    "iso:country":"ES",
    "sg:address":"Calle de Marques De Pickman, 9",
    "sg:city":"Sevilla",
    "sg:orig_category":"Perfumer\u00cda (al Por Menor)",
    "sg:phone":"+34 954 98 11 10",
    "sg:postcode":"41005",
    "sg:province":"Sevilla",
    "wof:name":"Drogueria Y Perfumerias Ana S.l.",
    "wof:placetype":"venue"
},
  "geometry": {"coordinates":[-5.9641442299,37.381439209],"type":"Point"}
}