{
  "type": "Feature",
  "properties": {
    "iso:country":"ES",
    "sg:address":"Calle de Rios Rosas, 18",
    "sg:city":"Ronda",
    "sg:orig_category":"Bancos",
    "sg:phone":"+34 952 87 28 42",
    "sg:postcode":"29400",
    "sg:province":"M\u00e1laga",
    "wof:name":"Banco De Andalucia",
    "wof:placetype":"venue"
},
  "geometry": {"coordinates":[-5.1641778946,36.7427253723],"type":"Point"}
}