{
  "type": "Feature",
  "properties": {
    "iso:country":"ES",
    "sg:address":"Calle de Sdo Soberats Antol, 28",
    "sg:city":"Palma",
    "sg:orig_category":"Cajas De Ahorro",
    "sg:phone":"+34 971 75 98 69",
    "sg:postcode":"07010",
    "sg:province":"Islas Baleares",
    "sg:website":"www.coloya.es",
    "wof:name":"Caja De Ahorros De Pollenca Colonya",
    "wof:placetype":"venue"
},
  "geometry": {"coordinates":[2.6483650208,39.5871315002],"type":"Point"}
}