{
  "type": "Feature",
  "properties": {
    "addr:full":"Calle de Polca, S/n Argana Alta Las Palmas 35500",
    "addr:housenumber":"s / n",
    "addr:postcode":"35500",
    "addr:street":"Calle De Polca",
    "iso:country":"ES",
    "sg:address":"Calle de Polca, S/n",
    "sg:city":"Argana Alta",
    "sg:orig_category":"Empresas De Carpinter\u00cda De Madera",
    "sg:phone":"+34 928 80 09 61",
    "sg:postcode":"35500",
    "sg:province":"Las Palmas",
    "wof:name":"Hernandez Rojas Isidro",
    "wof:placetype":"venue"
},
  "geometry": {"coordinates":[-13.5695285797,28.9773693085],"type":"Point"}
}