{
  "type": "Feature",
  "properties": {
    "addr:full":"Calle de Manuel Murguia, 12 Coru\u00d1a La Coru\u00f1a 15011",
    "addr:housenumber":"12",
    "addr:postcode":"15011",
    "addr:street":"Calle De Manuel Murguia;La Corun\u0303A",
    "iso:country":"ES",
    "sg:address":"Calle de Manuel Murguia, 12",
    "sg:city":"Coru\u00d1a",
    "sg:orig_category":"Caf\u00c9s, Bares, Cervecer\u00cdas",
    "sg:phone":"+34 981 26 70 07",
    "sg:postcode":"15011",
    "sg:province":"La Coru\u00f1a",
    "wof:name":"Lema Ameijenda Eugenio",
    "wof:placetype":"venue"
},
  "geometry": {"coordinates":[-8.4168729782,43.3696365356],"type":"Point"}
}