{
  "type": "Feature",
  "properties": {
    "addr:full":"Calle de Angeles (los), 2 Torrelodones Madrid 28250",
    "addr:housenumber":"2",
    "addr:postcode":"28250",
    "addr:street":"Calle De Angeles Los",
    "iso:country":"ES",
    "sg:address":"Calle de Angeles (los), 2",
    "sg:city":"Torrelodones",
    "sg:orig_category":"Asociaciones Y Clubs Deportivos",
    "sg:phone":"+34 918 59 39 69",
    "sg:postcode":"28250",
    "sg:province":"Madrid",
    "wof:name":"Raki S.l.",
    "wof:placetype":"venue"
},
  "geometry": {"coordinates":[-3.9295623302,40.5768928528],"type":"Point"}
}