{
  "type": "Feature",
  "properties": {
    "addr:full":"Rua San Roque, 66 Lugo Lugo 27002",
    "addr:housenumber":"66",
    "addr:postcode":"27002",
    "addr:street":"Rua San Roque",
    "iso:country":"ES",
    "sg:address":"Rua San Roque, 66",
    "sg:city":"Lugo",
    "sg:orig_category":"Asesor\u00cda Fiscal Y Jur\u00cddica",
    "sg:phone":"+34 982 25 50 26",
    "sg:postcode":"27002",
    "sg:province":"Lugo",
    "wof:name":"Reigosa Varela S.l.",
    "wof:placetype":"venue"
},
  "geometry": {"coordinates":[-7.5514650345,43.0072135925],"type":"Point"}
}