{
  "type": "Feature",
  "properties": {
    "addr:full":"Rua Domingo Fontan, 3 Ourense Ourense 32004",
    "addr:housenumber":"3",
    "addr:postcode":"32004",
    "addr:street":"Rua Domingo Fontan",
    "iso:country":"ES",
    "sg:address":"Rua Domingo Fontan, 3",
    "sg:city":"Ourense",
    "sg:orig_category":"Parques De Atracciones Y Centros De Esparcimiento",
    "sg:phone":"+34 988 24 04 21",
    "sg:postcode":"32004",
    "sg:province":"Ourense",
    "wof:name":"Iglesias Morrazo S.a.",
    "wof:placetype":"venue"
},
  "geometry": {"coordinates":[-7.8654818535,42.3306007385],"type":"Point"}
}