{
  "type": "Feature",
  "properties": {
    "iso:country":"ES",
    "sg:address":"Carr Colon, 15",
    "sg:city":"Moncada",
    "sg:orig_category":"Entrega Y Recogida (servicios)",
    "sg:phone":"+34 961 39 25 73",
    "sg:postcode":"46113",
    "sg:province":"Valencia",
    "wof:name":"Vicent Marques C.b.",
    "wof:placetype":"venue"
},
  "geometry": {"coordinates":[-0.3918159902,39.5475387573],"type":"Point"}
}