{
  "type": "Feature",
  "properties": {
    "addr:full":"Calle de Antonio Veredas, 13 Avila \u00c1vila 05004",
    "addr:housenumber":"13",
    "addr:postcode":"05004",
    "addr:street":"Calle De Antonio Veredas;A\u0301Vila",
    "iso:country":"ES",
    "sg:address":"Calle de Antonio Veredas, 13",
    "sg:city":"Avila",
    "sg:orig_category":"Ingeniero",
    "sg:phone":"+34 920 22 93 09",
    "sg:postcode":"05004",
    "sg:province":"\u00c1vila",
    "wof:name":"Domench Ingenieria Y Proyectos",
    "wof:placetype":"venue"
},
  "geometry": {"coordinates":[-4.6656961441,40.6610679626],"type":"Point"}
}