{
  "type": "Feature",
  "properties": {
    "iso:country":"ES",
    "sg:address":"Calle de Hernan Cortes, 8",
    "sg:city":"Jaen",
    "sg:orig_category":"Imprenta",
    "sg:phone":"+34 953 25 24 61",
    "sg:postcode":"23006",
    "sg:province":"Ja\u00e9n",
    "wof:name":"Catena 3 S.l.",
    "wof:placetype":"venue"
},
  "geometry": {"coordinates":[-3.800178051,37.7800292969],"type":"Point"}
}