{
  "type": "Feature",
  "properties": {
    "addr:full":"Calle de Secundino Alonso, 20 Pto. Rosario Las Palmas 35600",
    "addr:housenumber":"20",
    "addr:postcode":"35600",
    "addr:street":"Calle De Secundino Alonso;Pto. Rosario Las",
    "iso:country":"ES",
    "sg:address":"Calle de Secundino Alonso, 20",
    "sg:city":"Pto. Rosario",
    "sg:orig_category":"Centros P\u00dablicos De Formaci\u00d3n Profesional Y T\u00c9cnica",
    "sg:phone":"+34 928 85 17 92",
    "sg:postcode":"35600",
    "sg:province":"Las Palmas",
    "wof:name":"Colegio Procuradores De Las Palmas",
    "wof:placetype":"venue"
},
  "geometry": {"coordinates":[-13.8617038727,28.4988212585],"type":"Point"}
}