{
  "type": "Feature",
  "properties": {
    "iso:country":"ES",
    "sg:address":"Calle de Carpio, 6",
    "sg:city":"Malaga",
    "sg:orig_category":"Bisuter\u00cda, Joyer\u00cda, Relojer\u00cda (al Por Menor)",
    "sg:phone":"+34 952 32 43 80",
    "sg:postcode":"29002",
    "sg:province":"M\u00e1laga",
    "wof:name":"Soto Loma Fernando",
    "wof:placetype":"venue"
},
  "geometry": {"coordinates":[-4.4387731552,36.7029762268],"type":"Point"}
}