{
  "type": "Feature",
  "properties": {
    "addr:full":"Carrer de Sant Jaume, 10 S. Quirze Valles Barcelona 08192",
    "addr:housenumber":"10",
    "addr:postcode":"08192",
    "addr:street":"Carrer De Sant Jaume",
    "iso:country":"ES",
    "sg:address":"Carrer de Sant Jaume, 10",
    "sg:city":"S. Quirze Valles",
    "sg:orig_category":"M\u00c9dicos: Estomatolog\u00cda",
    "sg:phone":"+34 937 21 14 56",
    "sg:postcode":"08192",
    "sg:province":"Barcelona",
    "wof:name":"Soto Ballesteros Maria Dolores",
    "wof:placetype":"venue"
},
  "geometry": {"coordinates":[2.0842111111,41.5321311951],"type":"Point"}
}