{
  "type": "Feature",
  "properties": {
    "iso:country":"ES",
    "sg:address":"Avda Orense, 28",
    "sg:city":"Puente De Domingo Florez",
    "sg:orig_category":"Iglesia Cat\u00d3lica",
    "sg:phone":"+34 987 46 00 03",
    "sg:postcode":"24380",
    "sg:province":"Le\u00f3n",
    "wof:name":"Diocesis Astorga Administracion",
    "wof:placetype":"venue"
},
  "geometry": {"coordinates":[-6.822095871,42.4136657715],"type":"Point"}
}