{
  "type": "Feature",
  "properties": {
    "iso:country":"ES",
    "sg:address":"Cmno Bobalar, S/n",
    "sg:city":"Alaquas",
    "sg:orig_category":"Transportes Por Carretera: Lotes Completos, Mercanc\u00cdas Diversas",
    "sg:phone":"+34 961 51 23 06",
    "sg:postcode":"46970",
    "sg:province":"Valencia",
    "wof:name":"Represent. Y Distrib. Car-bel S.l.",
    "wof:placetype":"venue"
},
  "geometry": {"coordinates":[-0.4578439891,39.4546356201],"type":"Point"}
}