{
  "type": "Feature",
  "properties": {
    "addr:full":"Avda Faro Pechiguera, 5 Monta\u00e7a Roja Las Palmas 35580",
    "addr:housenumber":"5",
    "addr:postcode":"35580",
    "addr:street":"Avda Faro Pechiguera",
    "iso:country":"ES",
    "sg:address":"Avda Faro Pechiguera, 5",
    "sg:city":"Monta\u00e7a Roja",
    "sg:orig_category":"Inmobiliaria (agencias)",
    "sg:phone":"+34 928 34 94 35",
    "sg:postcode":"35580",
    "sg:province":"Las Palmas",
    "wof:name":"Lanz Suxury Villa Management Services S.l",
    "wof:placetype":"venue"
},
  "geometry": {"coordinates":[-13.8307790756,28.8657550812],"type":"Point"}
}