{
  "type": "Feature",
  "properties": {
    "iso:country":"ES",
    "sg:address":"Carrer de Sant Salvador, 47",
    "sg:city":"S. Cugat Valles",
    "sg:orig_category":"Asilos De Ancianos. Centros Privados",
    "sg:phone":"+34 935 89 68 35",
    "sg:postcode":"08172",
    "sg:province":"Barcelona",
    "sg:website":"www.inforesidencias.com/webs/sant-salvador/",
    "wof:name":"Crisemi S.l.",
    "wof:placetype":"venue"
},
  "geometry": {"coordinates":[2.0880360603,41.4680862427],"type":"Point"}
}