{
  "type": "Feature",
  "properties": {
    "iso:country":"ES",
    "sg:address":"Avda Cantabria, S/n",
    "sg:city":"Corrales",
    "sg:orig_category":"Aguas (distribuci\u00d3n, Servicios)",
    "sg:phone":"+34 942 84 22 25",
    "sg:postcode":"39400",
    "sg:province":"Cantabria",
    "wof:name":"Aguas Torrelavega S.a.",
    "wof:placetype":"venue"
},
  "geometry": {"coordinates":[-4.0705041885,43.2623558044],"type":"Point"}
}