{
  "type": "Feature",
  "properties": {
    "addr:full":"Ctra Tora, 54 Solsona Lleida 25280",
    "addr:housenumber":"54",
    "addr:postcode":"25280",
    "addr:street":"Ctra Tora",
    "iso:country":"ES",
    "sg:address":"Ctra Tora, 54",
    "sg:city":"Solsona",
    "sg:orig_category":"Asociaciones Humanitarias, De Cooperaci\u00d3n, De Acci\u00d3n Social",
    "sg:phone":"+34 973 48 21 08",
    "sg:postcode":"25280",
    "sg:province":"Lleida",
    "wof:name":"Associacio Pro-minusvalids De Solsona I Comarca",
    "wof:placetype":"venue"
},
  "geometry": {"coordinates":[1.5117036104,41.9907302856],"type":"Point"}
}