{
  "type": "Feature",
  "properties": {
    "iso:country":"ES",
    "sg:address":"Carrer de Llibertat, 32",
    "sg:city":"Manresa",
    "sg:orig_category":"Venta, Alquiler De Grupos Electr\u00d3genos",
    "sg:phone":"+34 938 74 19 16",
    "sg:postcode":"08243",
    "sg:province":"Barcelona",
    "wof:name":"Ewor S.l.",
    "wof:placetype":"venue"
},
  "geometry": {"coordinates":[1.8335820436,41.734375],"type":"Point"}
}