{
  "type": "Feature",
  "properties": {
    "addr:full":"Ctra. Mova, 26 Alaior Islas Baleares 07730",
    "addr:housenumber":"26",
    "addr:postcode":"07730",
    "addr:street":"Ctra. Mova",
    "iso:country":"ES",
    "sg:address":"Ctra. Mova, 26",
    "sg:city":"Alaior",
    "sg:orig_category":"Molduras, Junquillos, Listones Y Molduras Perforadas",
    "sg:phone":"+34 971 37 10 48",
    "sg:postcode":"07730",
    "sg:province":"Islas Baleares",
    "wof:name":"Andreu Llambias Francisca",
    "wof:placetype":"venue"
},
  "geometry": {"coordinates":[4.1374535561,39.9310073853],"type":"Point"}
}