{
  "type": "Feature",
  "properties": {
    "addr:full":"Avda Constitucion, S/n Narejos Murcia 30710",
    "addr:postcode":"30710",
    "addr:street":"Avda Constitucion S / N",
    "iso:country":"ES",
    "sg:address":"Avda Constitucion, S/n",
    "sg:city":"Narejos",
    "sg:orig_category":"Restaurantes",
    "sg:phone":"+34 968 57 56 34",
    "sg:postcode":"30710",
    "sg:province":"Murcia",
    "wof:name":"Hotel Los Narejos S.l.",
    "wof:placetype":"venue"
},
  "geometry": {"coordinates":[-0.8390290141,37.7581748962],"type":"Point"}
}