{
  "type": "Feature",
  "properties": {
    "iso:country":"ES",
    "sg:address":"Avgd De Daniel Gil, 53",
    "sg:city":"Ontinyent",
    "sg:orig_category":"Estancos",
    "sg:phone":"+34 962 38 13 43",
    "sg:postcode":"46870",
    "sg:province":"Valencia",
    "wof:name":"Pla Alcaraz Carmen",
    "wof:placetype":"venue"
},
  "geometry": {"coordinates":[-0.6006270051,38.8209190369],"type":"Point"}
}