{
  "type": "Feature",
  "properties": {
    "addr:full":"Calle de Mayor, 4 Membrilla Ciudad Real 13230",
    "addr:housenumber":"4",
    "addr:postcode":"13230",
    "addr:street":"Calle De Mayor",
    "iso:country":"ES",
    "sg:address":"Calle de Mayor, 4",
    "sg:city":"Membrilla",
    "sg:orig_category":"Empresas De Carpinter\u00cda De Madera",
    "sg:phone":"+34 926 63 64 56",
    "sg:postcode":"13230",
    "sg:province":"Ciudad Real",
    "wof:name":"Cano Garcia Emilio",
    "wof:placetype":"venue"
},
  "geometry": {"coordinates":[-3.3407199383,38.9680671692],"type":"Point"}
}