{
  "type": "Feature",
  "properties": {
    "addr:full":"Calle de Pidal, 20 Llanes Asturias 33500",
    "addr:housenumber":"20",
    "addr:postcode":"33500",
    "addr:street":"Calle De Pidal",
    "iso:country":"ES",
    "sg:address":"Calle de Pidal, 20",
    "sg:city":"Llanes",
    "sg:orig_category":"Ingeniero",
    "sg:phone":"+34 985 40 12 47",
    "sg:postcode":"33500",
    "sg:province":"Asturias",
    "wof:name":"Ruisanchez Garcia Alvaro",
    "wof:placetype":"venue"
},
  "geometry": {"coordinates":[-4.7549939156,43.4207191467],"type":"Point"}
}