{
  "type": "Feature",
  "properties": {
    "addr:full":"Av De La Sal, 2 Torrevieja Alicante 03180",
    "addr:housenumber":"2",
    "addr:postcode":"03180",
    "addr:street":"Av De La Sal",
    "iso:country":"ES",
    "sg:address":"Av De La Sal, 2",
    "sg:city":"Torrevieja",
    "sg:orig_category":"Sales (al Por Mayor)",
    "sg:phone":"+34 966 70 54 72",
    "sg:postcode":"03180",
    "sg:province":"Alicante",
    "wof:name":"Nueva Compa\u00f1ia Arrendataria De Las Salinas De Torrevieja S.a.",
    "wof:placetype":"venue"
},
  "geometry": {"coordinates":[-0.6536790133,38.0173606873],"type":"Point"}
}