{
  "type": "Feature",
  "properties": {
    "iso:country":"ES",
    "sg:address":"Carrer de Ca L'alegre De Dalt, 55",
    "sg:city":"Barcelona",
    "sg:orig_category":"Cine: Pel\u00cdculas Educativas, Industriales Y Publicitarias (producci\u00d3n)",
    "sg:phone":"+34 932 85 02 29",
    "sg:postcode":"08024",
    "sg:province":"Barcelona",
    "sg:website":"www.voodooproductions.net",
    "wof:name":"Voodoo Productions S.l.",
    "wof:placetype":"venue"
},
  "geometry": {"coordinates":[2.1611461639,41.4091186523],"type":"Point"}
}