{
  "type": "Feature",
  "properties": {
    "iso:country":"ES",
    "sg:address":"Calle de Pablo Morillo, 2",
    "sg:city":"Zamora",
    "sg:orig_category":"Institutos De Belleza",
    "sg:phone":"+34 980 51 19 50",
    "sg:postcode":"49013",
    "sg:province":"Zamora",
    "wof:name":"Sanchez Martin Micaela",
    "wof:placetype":"venue"
},
  "geometry": {"coordinates":[-5.7417449951,41.50756073],"type":"Point"}
}