{
  "type": "Feature",
  "properties": {
    "addr:full":"Barr Barca (la), S/n Viveda Cantabria 39314",
    "addr:postcode":"39314",
    "addr:street":"La S / N",
    "iso:country":"ES",
    "sg:address":"Barr Barca (la), S/n",
    "sg:city":"Viveda",
    "sg:orig_category":"Poli\u00c9ster",
    "sg:phone":"+34 942 88 24 30",
    "sg:postcode":"39314",
    "sg:province":"Cantabria",
    "wof:name":"Poliester Siete Sdad. Coop.",
    "wof:placetype":"venue"
},
  "geometry": {"coordinates":[-4.0504131317,43.3769798279],"type":"Point"}
}