{
  "type": "Feature",
  "properties": {
    "addr:full":"Calle de Ternate, 7 Malaga M\u00e1laga 29190",
    "addr:housenumber":"7",
    "addr:postcode":"29190",
    "addr:street":"Calle De Ternate;Ma\u0301Laga",
    "iso:country":"ES",
    "sg:address":"Calle de Ternate, 7",
    "sg:city":"Malaga",
    "sg:orig_category":"Inmobiliaria (agencias)",
    "sg:phone":"+34 952 43 16 21",
    "sg:postcode":"29190",
    "sg:province":"M\u00e1laga",
    "wof:name":"Inversiones Galan Tellez Sl",
    "wof:placetype":"venue"
},
  "geometry": {"coordinates":[-4.4699349403,36.7376899719],"type":"Point"}
}