{
  "type": "Feature",
  "properties": {
    "addr:full":"Calle de Flor (la), 10 Vi\u00d1uelas Guadalajara 19183",
    "addr:housenumber":"10",
    "addr:postcode":"19183",
    "addr:street":"Calle De Flor La",
    "iso:country":"ES",
    "sg:address":"Calle de Flor (la), 10",
    "sg:city":"Vi\u00d1uelas",
    "sg:orig_category":"Cajas Para Embalar",
    "sg:phone":"+34 949 85 45 08",
    "sg:postcode":"19183",
    "sg:province":"Guadalajara",
    "wof:name":"Caja Rural Provincial De Toledo",
    "wof:placetype":"venue"
},
  "geometry": {"coordinates":[-3.3430540562,40.794467926],"type":"Point"}
}