{
  "type": "Feature",
  "properties": {
    "iso:country":"ES",
    "sg:address":"Carrer de Francesc Moragas, 50",
    "sg:city":"Hospitalet Llobregat",
    "sg:orig_category":"Molduras, Junquillos, Listones Y Molduras Perforadas",
    "sg:phone":"+34 933 37 79 96",
    "sg:postcode":"08901",
    "sg:province":"Barcelona",
    "wof:name":"Bar Restaurante Pato I S.c.p.",
    "wof:placetype":"venue"
},
  "geometry": {"coordinates":[2.0978178978,41.35704422],"type":"Point"}
}