{
  "type": "Feature",
  "properties": {
    "iso:country":"ES",
    "sg:address":"Calle de Cilla (la), 66",
    "sg:city":"Osuna",
    "sg:orig_category":"Panader\u00cdas, Panader\u00cdas",
    "sg:phone":"+34 954 81 03 96",
    "sg:postcode":"41640",
    "sg:province":"Sevilla",
    "wof:name":"Crujera Gonzalez Francisco",
    "wof:placetype":"venue"
},
  "geometry": {"coordinates":[-5.108479023,37.2391548157],"type":"Point"}
}