{
  "type": "Feature",
  "properties": {
    "iso:country":"ES",
    "sg:address":"Avda Canillejas A Vicalvaro, 51",
    "sg:city":"Madrid",
    "sg:orig_category":"Aluminio Y Aleaciones (producci\u00d3n, Transformaci\u00d3n, Negocio)",
    "sg:phone":"+34 913 20 98 39",
    "sg:postcode":"28022",
    "sg:province":"Madrid",
    "wof:name":"Alucean S.l.",
    "wof:placetype":"venue"
},
  "geometry": {"coordinates":[-3.6131827831,40.4372177124],"type":"Point"}
}