{
  "type": "Feature",
  "properties": {
    "iso:country":"ES",
    "sg:address":"Avda General Fanjul, 67",
    "sg:city":"Madrid",
    "sg:orig_category":"Centros Empresariales",
    "sg:phone":"+34 917 10 78 08",
    "sg:postcode":"28044",
    "sg:province":"Madrid",
    "wof:name":"Garcia Garcia Daniel",
    "wof:placetype":"venue"
},
  "geometry": {"coordinates":[-3.773154974,40.382434845],"type":"Point"}
}