{
  "type": "Feature",
  "properties": {
    "addr:full":"Calle de Hacienda De Pavones, 118 Madrid Madrid 28030",
    "addr:housenumber":"118",
    "addr:postcode":"28030",
    "addr:street":"Calle De Hacienda De Pavones",
    "iso:country":"ES",
    "sg:address":"Calle de Hacienda De Pavones, 118",
    "sg:city":"Madrid",
    "sg:orig_category":"Peluqueros: De Se\u00d1oras",
    "sg:phone":"+34 917 73 55 99",
    "sg:postcode":"28030",
    "sg:province":"Madrid",
    "wof:name":"Gazquez Sede\u00f1o Francisco Antonio",
    "wof:placetype":"venue"
},
  "geometry": {"coordinates":[-3.6445960999,40.4028320312],"type":"Point"}
}