{
  "type": "Feature",
  "properties": {
    "iso:country":"ES",
    "sg:address":"Avda Linares Rivas, 30",
    "sg:city":"Coru\u00d1a",
    "sg:orig_category":"Sociedades, Compa\u00d1\u00cdas Aseguradoras",
    "sg:phone":"+34 981 12 07 58",
    "sg:postcode":"15005",
    "sg:province":"La Coru\u00f1a",
    "wof:name":"Correduria De Seguros De Lico Corporacion S.a.",
    "wof:placetype":"venue"
},
  "geometry": {"coordinates":[-8.4054012299,43.3628692627],"type":"Point"}
}