{
  "type": "Feature",
  "properties": {
    "iso:country":"ES",
    "sg:address":"Calle de Aguas Vivas, S/n",
    "sg:city":"Caceres",
    "sg:orig_category":"Asilos De Ancianos. Centros Privados",
    "sg:phone":"+34 927 24 44 21",
    "sg:postcode":"10004",
    "sg:province":"C\u00e1ceres",
    "wof:name":"Ciudad Jardin Parque Del Principe S.l.",
    "wof:placetype":"venue"
},
  "geometry": {"coordinates":[-6.3767147064,39.4796066284],"type":"Point"}
}