{
  "type": "Feature",
  "properties": {
    "iso:country":"ES",
    "sg:address":"Plaz San Juan, 7",
    "sg:city":"Xirivella",
    "sg:orig_category":"Quincaller\u00cda (al Por Menor)",
    "sg:phone":"+34 963 50 06 06",
    "sg:postcode":"46950",
    "sg:province":"Valencia",
    "wof:name":"Ferreteria Mercado 2 S.l.",
    "wof:placetype":"venue"
},
  "geometry": {"coordinates":[-0.4283800125,39.4641113281],"type":"Point"}
}