{
  "type": "Feature",
  "properties": {
    "addr:full":"Calle de Mercado El, 1 Cangas Onis Asturias 33550",
    "addr:postcode":"33550",
    "addr:street":"Calle De;El;Asturias",
    "iso:country":"ES",
    "sg:address":"Calle de Mercado El, 1",
    "sg:city":"Cangas Onis",
    "sg:orig_category":"Molduras, Junquillos, Listones Y Molduras Perforadas",
    "sg:phone":"+34 985 84 81 37",
    "sg:postcode":"33550",
    "sg:province":"Asturias",
    "wof:name":"Suero Suero Hermenegildo",
    "wof:placetype":"venue"
},
  "geometry": {"coordinates":[-5.1271700859,43.3505706787],"type":"Point"}
}