{
  "type": "Feature",
  "properties": {
    "addr:full":"Calle de Conde Cifuentes, 33 Granada Granada 18005",
    "addr:housenumber":"33",
    "addr:postcode":"18005",
    "addr:street":"Calle De Conde Cifuentes",
    "iso:country":"ES",
    "sg:address":"Calle de Conde Cifuentes, 33",
    "sg:city":"Granada",
    "sg:orig_category":"Agencias Y Agentes Comerciales, Representantes",
    "sg:phone":"+34 958 25 18 44",
    "sg:postcode":"18005",
    "sg:province":"Granada",
    "wof:name":"Martin Vargas Manuel",
    "wof:placetype":"venue"
},
  "geometry": {"coordinates":[-3.6027333736,37.1696472168],"type":"Point"}
}