{
  "type": "Feature",
  "properties": {
    "iso:country":"ES",
    "sg:address":"Calle de Mayor, 27",
    "sg:city":"Cartagena",
    "sg:orig_category":"Abogados",
    "sg:phone":"+34 968 52 16 05",
    "sg:postcode":"30201",
    "sg:province":"Murcia",
    "wof:name":"Ayala Sanchez Andres",
    "wof:placetype":"venue"
},
  "geometry": {"coordinates":[-0.9866273999,37.6008071899],"type":"Point"}
}