{
  "type": "Feature",
  "properties": {
    "addr:full":"Ctra San Vicente, 9 Valle Trapaga Vizcaya 48510",
    "addr:housenumber":"9",
    "addr:postcode":"48510",
    "addr:street":"Ctra San Vicente;Trapaga",
    "iso:country":"ES",
    "sg:address":"Ctra San Vicente, 9",
    "sg:city":"Valle Trapaga",
    "sg:orig_category":"Tratamiento De Metales",
    "sg:phone":"+34 944 72 12 89",
    "sg:postcode":"48510",
    "sg:province":"Vizcaya",
    "wof:name":"Afinamiento Y Recuperacion De Metales S.l.",
    "wof:placetype":"venue"
},
  "geometry": {"coordinates":[-3.0238177776,43.2997398376],"type":"Point"}
}