{
  "type": "Feature",
  "properties": {
    "iso:country":"ES",
    "sg:address":"Luga Poligono 12, 522",
    "sg:city":"Llucmajor",
    "sg:orig_category":"Producci\u00d3n De Abonos Y De Fertilizantes",
    "sg:phone":"+34 971 66 24 42",
    "sg:postcode":"07620",
    "sg:province":"Islas Baleares",
    "wof:name":"Excavacionesbarcelo",
    "wof:placetype":"venue"
},
  "geometry": {"coordinates":[2.8689489365,39.4487228394],"type":"Point"}
}