{
  "type": "Feature",
  "properties": {
    "addr:full":"Calle de Santa Maria De Gracia, 23 Camas Sevilla 41900",
    "addr:housenumber":"23",
    "addr:postcode":"41900",
    "addr:street":"Calle De Santa",
    "iso:country":"ES",
    "sg:address":"Calle de Santa Maria De Gracia, 23",
    "sg:city":"Camas",
    "sg:orig_category":"Abogados",
    "sg:phone":"+34 955 98 27 07",
    "sg:postcode":"41900",
    "sg:province":"Sevilla",
    "wof:name":"Marin Ramos Manuel",
    "wof:placetype":"venue"
},
  "geometry": {"coordinates":[-6.0351371765,37.4027137756],"type":"Point"}
}