{
  "type": "Feature",
  "properties": {
    "addr:full":"Calle de Eduardo Barreiros, 13 Madrid Madrid 28041",
    "addr:housenumber":"13",
    "addr:postcode":"madrid;28041",
    "addr:street":"Calle De Eduardo Barreiros",
    "iso:country":"ES",
    "sg:address":"Calle de Eduardo Barreiros, 13",
    "sg:city":"Madrid",
    "sg:orig_category":"Reciclaje, Tratamiento De Papel Y Cart\u00d3n",
    "sg:phone":"+34 913 69 85 07",
    "sg:postcode":"28041",
    "sg:province":"Madrid",
    "sg:website":"www.filcarton.es",
    "wof:name":"Servicios Papeleros Celiber S.l.",
    "wof:placetype":"venue"
},
  "geometry": {"coordinates":[-3.6972670555,40.3668823242],"type":"Point"}
}