{
  "type": "Feature",
  "properties": {
    "iso:country":"ES",
    "sg:address":"Calle de Doctor Gomez Ulla, 18",
    "sg:city":"Madrid",
    "sg:orig_category":"Abogados",
    "sg:phone":"+34 913 56 77 60",
    "sg:postcode":"28028",
    "sg:province":"Madrid",
    "wof:name":"Diego Ochoa Jose Antonio",
    "wof:placetype":"venue"
},
  "geometry": {"coordinates":[-3.6674370766,40.4301757812],"type":"Point"}
}