{
  "type": "Feature",
  "properties": {
    "addr:full":"Calle de San Wenceslao, 2 Madrid Madrid 28025",
    "addr:housenumber":"2",
    "addr:postcode":"28025",
    "addr:street":"Calle De San Wenceslao",
    "iso:country":"ES",
    "sg:address":"Calle de San Wenceslao, 2",
    "sg:city":"Madrid",
    "sg:orig_category":"Loter\u00cda Y T\u00d3mbola",
    "sg:phone":"+34 915 25 77 55",
    "sg:postcode":"28025",
    "sg:province":"Madrid",
    "wof:name":"Alonso Garcia Fernando",
    "wof:placetype":"venue"
},
  "geometry": {"coordinates":[-3.7321760654,40.3801002502],"type":"Point"}
}