{
  "type": "Feature",
  "properties": {
    "addr:full":"Calle de Mayor, 76 Canteras Murcia 30394",
    "addr:housenumber":"76",
    "addr:postcode":"30394",
    "addr:street":"Calle De Mayor",
    "iso:country":"ES",
    "sg:address":"Calle de Mayor, 76",
    "sg:city":"Canteras",
    "sg:orig_category":"Cajas De Ahorro",
    "sg:phone":"+34 968 55 34 85",
    "sg:postcode":"30394",
    "sg:province":"Murcia",
    "sg:website":"www.cajamurcia.es",
    "wof:name":"Caja De Ahorros De Murcia",
    "wof:placetype":"venue"
},
  "geometry": {"coordinates":[-1.0443190336,37.6118888855],"type":"Point"}
}