{
  "type": "Feature",
  "properties": {
    "addr:full":"Calle de Huesca, 27 Madrid Madrid 28020",
    "addr:housenumber":"27",
    "addr:postcode":"madrid;28020",
    "addr:street":"Calle De Huesca",
    "iso:country":"ES",
    "sg:address":"Calle de Huesca, 27",
    "sg:city":"Madrid",
    "sg:orig_category":"Fabricaci\u00d3n, Importaci\u00d3n De Material Y Sistemas De Telecomunicaciones",
    "sg:phone":"+34 915 71 14 36",
    "sg:postcode":"28020",
    "sg:province":"Madrid",
    "wof:name":"Saad  Khaled",
    "wof:placetype":"venue"
},
  "geometry": {"coordinates":[-3.697717905,40.4581222534],"type":"Point"}
}