{
  "type": "Feature",
  "properties": {
    "addr:full":"Sanguesa, 38 Iru\u00f1a Navarra 31005",
    "addr:housenumber":"38",
    "addr:postcode":"31005",
    "addr:street":"Sanguesa",
    "iso:country":"ES",
    "sg:address":"Sanguesa, 38",
    "sg:city":"Iru\u00f1a",
    "sg:orig_category":"Televisi\u00d3n, V\u00cddeo: Aparatos Y Accesorios (venta)",
    "sg:phone":"+34 948 24 34 42",
    "sg:postcode":"31005",
    "sg:province":"Navarra",
    "wof:name":"Tele-navarra S. L.",
    "wof:placetype":"venue"
},
  "geometry": {"coordinates":[-1.6424590349,42.8065986633],"type":"Point"}
}