{
  "type": "Feature",
  "properties": {
    "addr:full":"Carrer de Alcala Galiano, 40 Almeda Mercader Barcelona 08940",
    "addr:housenumber":"40",
    "addr:postcode":"08940",
    "addr:street":"Carrer De Alcala Galiano;Mercader Barcelona",
    "iso:country":"ES",
    "sg:address":"Carrer de Alcala Galiano, 40",
    "sg:city":"Almeda Mercader",
    "sg:classifiers":[
        {
            "category":"Manufacturing",
            "subcategory":"Metals",
            "type":"Manufacturing & Wholesale Goods"
        }
    ],
    "sg:phone":"+34 933 77 15 84",
    "sg:postcode":"08940",
    "sg:province":"Barcelona",
    "sg:tags":[
        "en",
        "fundiciones"
    ],
    "sg:website":"www.fumegar.com",
    "wof:name":"Fumegar S. A.",
    "wof:placetype":"venue"
},
  "geometry": {"coordinates":[2.0708940029,41.3559417725],"type":"Point"}
}