{
  "type": "Feature",
  "properties": {
    "addr:full":"Calle de Concha Espina, 2 Arrigorriaga Vizcaya 48480",
    "addr:housenumber":"2",
    "addr:postcode":"48480",
    "addr:street":"Calle De Concha Espina",
    "iso:country":"ES",
    "sg:address":"Calle de Concha Espina, 2",
    "sg:city":"Arrigorriaga",
    "sg:orig_category":"Asociaciones Y Clubs Deportivos",
    "sg:phone":"+34 946 71 30 15",
    "sg:postcode":"48480",
    "sg:province":"Vizcaya",
    "wof:name":"Andres Suarez Jose Benito",
    "wof:placetype":"venue"
},
  "geometry": {"coordinates":[-2.8868000507,43.2083053589],"type":"Point"}
}