{
  "type": "Feature",
  "properties": {
    "iso:country":"ES",
    "sg:address":"Calle de Don Bernardo Guillamon, 2",
    "sg:city":"Abaran",
    "sg:orig_category":"Pescader\u00cdas (al Por Menor)",
    "sg:phone":"+34 968 77 10 17",
    "sg:postcode":"30550",
    "sg:province":"Murcia",
    "wof:name":"Cutillas Mora Jesus",
    "wof:placetype":"venue"
},
  "geometry": {"coordinates":[-1.2794743776,38.2779998779],"type":"Point"}
}