{
  "type": "Feature",
  "properties": {
    "addr:full":"Carrer de Sant Joan, 3 Monovar Alicante 03640",
    "addr:housenumber":"3",
    "addr:postcode":"03640",
    "addr:street":"Carrer De Sant Joan;Alicante",
    "iso:country":"ES",
    "sg:address":"Carrer de Sant Joan, 3",
    "sg:city":"Monovar",
    "sg:orig_category":"Asociaciones Humanitarias, De Cooperaci\u00d3n, De Acci\u00d3n Social",
    "sg:phone":"+34 965 47 27 22",
    "sg:postcode":"03640",
    "sg:province":"Alicante",
    "wof:name":"Asociacion Espa\u00f1ola Contra El Cancer",
    "wof:placetype":"venue"
},
  "geometry": {"coordinates":[-0.8395822048,38.4368591309],"type":"Point"}
}