{
  "type": "Feature",
  "properties": {
    "iso:country":"ES",
    "sg:address":"Rua Rosalia De Castro, 20",
    "sg:city":"Muros",
    "sg:orig_category":"Molduras, Junquillos, Listones Y Molduras Perforadas",
    "sg:phone":"+34 981 82 78 02",
    "sg:postcode":"15250",
    "sg:province":"La Coru\u00f1a",
    "wof:name":"Aerot S.l.",
    "wof:placetype":"venue"
},
  "geometry": {"coordinates":[-9.0564680099,42.774105072],"type":"Point"}
}