{
  "type": "Feature",
  "properties": {
    "iso:country":"ES",
    "sg:address":"Avda Constitucion, 60",
    "sg:city":"Villena",
    "sg:orig_category":"Cl\u00cdnicas Dentales",
    "sg:phone":"+34 965 81 38 60",
    "sg:postcode":"03400",
    "sg:province":"Alicante",
    "wof:name":"Manglano Borso De Carminati Cayetana",
    "wof:placetype":"venue"
},
  "geometry": {"coordinates":[-0.865095973,38.6345748901],"type":"Point"}
}