{
  "type": "Feature",
  "properties": {
    "iso:country":"ES",
    "sg:address":"Carrer de Canonge Joncar, 56",
    "sg:city":"Sabadell",
    "sg:orig_category":"Internados & Ense\u00d1anza Privada",
    "sg:phone":"+34 937 16 54 94",
    "sg:postcode":"08208",
    "sg:province":"Barcelona",
    "wof:name":"Ribatallada S. C. L.",
    "wof:placetype":"venue"
},
  "geometry": {"coordinates":[2.1067171097,41.5564079285],"type":"Point"}
}