{
  "type": "Feature",
  "properties": {
    "addr:full":"Calle de Garcia Lorca, 9 Rozas De Madrid Madrid 28230",
    "addr:housenumber":"9",
    "addr:postcode":"28230",
    "addr:street":"Calle De Garcia Lorca",
    "iso:country":"ES",
    "sg:address":"Calle de Garcia Lorca, 9",
    "sg:city":"Rozas De Madrid",
    "sg:orig_category":"Inform\u00c1tica: Consultores",
    "sg:phone":"+34 916 37 39 96",
    "sg:postcode":"28230",
    "sg:province":"Madrid",
    "wof:name":"Gintel",
    "wof:placetype":"venue"
},
  "geometry": {"coordinates":[-4.4682002068,40.2627868652],"type":"Point"}
}