{
  "type": "Feature",
  "properties": {
    "addr:full":"Pl Vila, 17 S. Celoni Barcelona 08470",
    "addr:housenumber":"17",
    "addr:postcode":"08470",
    "addr:street":"Pl Vila;S. Celoni Barcelona",
    "iso:country":"ES",
    "sg:address":"Pl Vila, 17",
    "sg:city":"S. Celoni",
    "sg:orig_category":"Controles De Edificaci\u00d3n (construcci\u00d3n, Seguridad)",
    "sg:phone":"+34 938 67 22 22",
    "sg:postcode":"08470",
    "sg:province":"Barcelona",
    "wof:name":"Sic Bosch S.l.",
    "wof:placetype":"venue"
},
  "geometry": {"coordinates":[2.4916338921,41.6897125244],"type":"Point"}
}