{
  "type": "Feature",
  "properties": {
    "iso:country":"ES",
    "sg:address":"Calle de Alcalde Mateos Mancilla, 2",
    "sg:city":"Jerez De La Frontera",
    "sg:orig_category":"Electricidad Veh\u00cdculo",
    "sg:phone":"+34 956 33 61 98",
    "sg:postcode":"11408",
    "sg:province":"C\u00e1diz",
    "wof:name":"Rueda Rubiales Federico",
    "wof:placetype":"venue"
},
  "geometry": {"coordinates":[-6.1385970116,36.6740646362],"type":"Point"}
}