{
  "type": "Feature",
  "properties": {
    "iso:country":"ES",
    "sg:address":"Ctra Candeleda, 2",
    "sg:city":"Arenas San Pedro",
    "sg:orig_category":"Perfumer\u00cda (al Por Menor)",
    "sg:phone":"+34 920 37 01 59",
    "sg:postcode":"05400",
    "sg:province":"\u00c1vila",
    "wof:name":"Blazquez Jara Maria Luz",
    "wof:placetype":"venue"
},
  "geometry": {"coordinates":[-5.0918459892,40.2101745605],"type":"Point"}
}