{
  "type": "Feature",
  "properties": {
    "addr:full":"Calle de Churruca, 3 Madrid Madrid 28004",
    "addr:housenumber":"3",
    "addr:postcode":"28004",
    "addr:street":"Calle De Churruca",
    "iso:country":"ES",
    "sg:address":"Calle de Churruca, 3",
    "sg:city":"Madrid",
    "sg:orig_category":"Molduras, Junquillos, Listones Y Molduras Perforadas",
    "sg:phone":"+34 915 24 17 91",
    "sg:postcode":"28004",
    "sg:province":"Madrid",
    "wof:name":"Kildon 9 S.l.",
    "wof:placetype":"venue"
},
  "geometry": {"coordinates":[-3.7006747723,40.4268074036],"type":"Point"}
}