{
  "type": "Feature",
  "properties": {
    "addr:full":"Carrer de Doctor Fleming, S/n Caldes Montbui Barcelona 08140",
    "addr:housenumber":"s / n",
    "addr:postcode":"08140",
    "addr:street":"Carrer De Doctor Fleming;Montbui Barcelona",
    "iso:country":"ES",
    "sg:address":"Carrer de Doctor Fleming, S/n",
    "sg:city":"Caldes Montbui",
    "sg:orig_category":"Fabricaci\u00d3n De Telas Y Sedas",
    "sg:phone":"+34 938 65 39 93",
    "sg:postcode":"08140",
    "sg:province":"Barcelona",
    "wof:name":"Textil J Balaguer S.a.",
    "wof:placetype":"venue"
},
  "geometry": {"coordinates":[2.1668040752,41.6362228394],"type":"Point"}
}