{
  "type": "Feature",
  "properties": {
    "addr:full":"Avda Kansas City, 9 Sevilla Sevilla 41007",
    "addr:housenumber":"9",
    "addr:postcode":"41007",
    "addr:street":"Avda Kansas City",
    "iso:country":"ES",
    "sg:address":"Avda Kansas City, 9",
    "sg:city":"Sevilla",
    "sg:orig_category":"Electricidad: Instaladores",
    "sg:phone":"+34 954 42 49 01",
    "sg:postcode":"41007",
    "sg:province":"Sevilla",
    "wof:name":"Especialidades Electricas S.a.",
    "wof:placetype":"venue"
},
  "geometry": {"coordinates":[-5.9727392197,37.3882408142],"type":"Point"}
}