{
  "type": "Feature",
  "properties": {
    "iso:country":"ES",
    "sg:address":"Co Campo Abajo, 22",
    "sg:city":"Navarrete",
    "sg:orig_category":"Empresas De Carpinter\u00cda De Madera",
    "sg:phone":"+34 941 44 07 41",
    "sg:postcode":"26370",
    "sg:province":"La Rioja",
    "wof:name":"Marin Hurtado Ricardo",
    "wof:placetype":"venue"
},
  "geometry": {"coordinates":[-2.5627059937,42.4329109192],"type":"Point"}
}