{
  "type": "Feature",
  "properties": {
    "iso:country":"ES",
    "sg:address":"Calle de Masnou, 34",
    "sg:city":"Adra",
    "sg:orig_category":"Promotores Constructores",
    "sg:phone":"+34 950 40 00 76",
    "sg:postcode":"04770",
    "sg:province":"Almer\u00eda",
    "wof:name":"Grupo Kiroba S.l.l.",
    "wof:placetype":"venue"
},
  "geometry": {"coordinates":[-3.0199990273,36.7488937378],"type":"Point"}
}