{
  "type": "Feature",
  "properties": {
    "addr:full":"Avda Jable (el), S/n Callao Salvaje Santa Cruz De Tenerife 38678",
    "addr:housenumber":"/ n",
    "addr:postcode":"38678",
    "addr:street":"Avda Jable El S",
    "iso:country":"ES",
    "sg:address":"Avda Jable (el), S/n",
    "sg:city":"Callao Salvaje",
    "sg:orig_category":"Perfumer\u00cda (al Por Menor)",
    "sg:phone":"+34 922 74 05 35",
    "sg:postcode":"38678",
    "sg:province":"Santa Cruz De Tenerife",
    "wof:name":"Perfumeria Elisabeth S.l.",
    "wof:placetype":"venue"
},
  "geometry": {"coordinates":[-16.7826786041,28.1290245056],"type":"Point"}
}