{
  "type": "Feature",
  "properties": {
    "iso:country":"ES",
    "sg:address":"Avda Eduardo Dato, 24",
    "sg:city":"Sevilla",
    "sg:orig_category":"Farmacias",
    "sg:phone":"+34 954 63 25 91",
    "sg:postcode":"41005",
    "sg:province":"Sevilla",
    "wof:name":"Galdo Seco Maria Del Carmen",
    "wof:placetype":"venue"
},
  "geometry": {"coordinates":[-5.9728736877,37.3827629089],"type":"Point"}
}