{
  "type": "Feature",
  "properties": {
    "addr:full":"Poli Poligono Industrial Amargacena, 7 Cordoba C\u00f3rdoba 14013",
    "addr:housenumber":"7",
    "addr:postcode":"14013",
    "addr:street":"Poligono Industrial Amargacena;Co\u0301Rdoba",
    "iso:country":"ES",
    "sg:address":"Poli Poligono Industrial Amargacena, 7",
    "sg:city":"Cordoba",
    "sg:orig_category":"Art\u00cdculos De Aluminio",
    "sg:phone":"+34 957 29 57 88",
    "sg:postcode":"14013",
    "sg:province":"C\u00f3rdoba",
    "wof:name":"Talleres Huerta De La Cruz S.l.",
    "wof:placetype":"venue"
},
  "geometry": {"coordinates":[-4.7784028053,37.8779411316],"type":"Point"}
}