{
  "type": "Feature",
  "properties": {
    "iso:country":"ES",
    "sg:address":"Ctra Cogullada, 244",
    "sg:city":"San Juan De Mozarrifar",
    "sg:orig_category":"Lecher\u00cdas",
    "sg:phone":"+34 976 58 70 23",
    "sg:postcode":"50820",
    "sg:province":"Zaragoza",
    "wof:name":"Gomez Gutierrez Vidal",
    "wof:placetype":"venue"
},
  "geometry": {"coordinates":[-0.8416489959,41.7171096802],"type":"Point"}
}