{
  "type": "Feature",
  "properties": {
    "iso:country":"ES",
    "sg:address":"Calle de Antonia Merce, 8",
    "sg:city":"Madrid",
    "sg:orig_category":"Ense\u00d1anza: Idiomas",
    "sg:phone":"+34 914 31 14 66",
    "sg:postcode":"28009",
    "sg:province":"Madrid",
    "wof:name":"Spanish Heritage S.a.",
    "wof:placetype":"venue"
},
  "geometry": {"coordinates":[-3.6730265617,40.42445755],"type":"Point"}
}