{
  "type": "Feature",
  "properties": {
    "iso:country":"ES",
    "sg:address":"Calle de Juan Thalamas Labandibar, 69",
    "sg:city":"Irun",
    "sg:orig_category":"Comerciantes Al Por Mayor De Vinos, Licores Y Alcoholes",
    "sg:phone":"+34 943 63 41 10",
    "sg:postcode":"20305",
    "sg:province":"Guip\u00f9zcoa",
    "wof:name":"Saura Salazar Jose Antonio",
    "wof:placetype":"venue"
},
  "geometry": {"coordinates":[-1.7629760504,43.3427085876],"type":"Point"}
}