{
  "type": "Feature",
  "properties": {
    "iso:country":"ES",
    "sg:address":"Rua Lavandeiras, 5",
    "sg:city":"Batan",
    "sg:orig_category":"Arquitectos",
    "sg:phone":"+34 981 63 12 67",
    "sg:postcode":"15176",
    "sg:province":"La Coru\u00f1a",
    "wof:name":"Reboredo Santos Andres",
    "wof:placetype":"venue"
},
  "geometry": {"coordinates":[-8.3265943527,43.3246536255],"type":"Point"}
}