{
  "type": "Feature",
  "properties": {
    "iso:country":"ES",
    "sg:address":"Plaz Capitan Boixareu Rivera, 47",
    "sg:city":"Guadalajara",
    "sg:classifiers":[
        {
            "category":"Shopping",
            "subcategory":"Clothing, Apparel, & Fashions",
            "type":"Retail Goods"
        }
    ],
    "sg:phone":"+34 949 23 02 94",
    "sg:postcode":"19001",
    "sg:province":"Guadalajara",
    "sg:tags":[
        "boutique"
    ],
    "wof:name":"Rojo Rojo Maria Isabel",
    "wof:placetype":"venue"
},
  "geometry": {"coordinates":[-3.1608259678,40.6319465637],"type":"Point"}
}