{
  "type": "Feature",
  "properties": {
    "iso:country":"ES",
    "sg:address":"Calle de Rocinante, 42",
    "sg:city":"Malaga",
    "sg:orig_category":"Postigos, Persianas Y Celos\u00cdas",
    "sg:phone":"+34 952 43 81 51",
    "sg:postcode":"29190",
    "sg:province":"M\u00e1laga",
    "wof:name":"Ruiz Perez Juan Antonio",
    "wof:placetype":"venue"
},
  "geometry": {"coordinates":[-4.4774689674,36.7454376221],"type":"Point"}
}