{
  "type": "Feature",
  "properties": {
    "iso:country":"ES",
    "sg:address":"Avda Jesus Santos Rein, 6",
    "sg:city":"Fuengirola",
    "sg:orig_category":"Ortopedia General",
    "sg:phone":"+34 952 66 52 46",
    "sg:postcode":"29640",
    "sg:province":"M\u00e1laga",
    "wof:name":"Moreno Blanca Inmaculada",
    "wof:placetype":"venue"
},
  "geometry": {"coordinates":[-4.618519783,36.5497817993],"type":"Point"}
}