{
  "type": "Feature",
  "properties": {
    "addr:full":"Ctra Medellin, Km. 0001,8 Caceres C\u00e1ceres 10005",
    "addr:postcode":"10005",
    "addr:street":"Ctra Medellin Km. 0001,8;Ca\u0301Ceres",
    "iso:country":"ES",
    "sg:address":"Ctra Medellin, Km. 0001,8",
    "sg:city":"Caceres",
    "sg:orig_category":"Juegos Y Juguetes (al Por Menor)",
    "sg:phone":"+34 927 24 91 22",
    "sg:postcode":"10005",
    "sg:province":"C\u00e1ceres",
    "wof:name":"Juguetes Avila S.l.",
    "wof:placetype":"venue"
},
  "geometry": {"coordinates":[-6.3712091446,39.4599304199],"type":"Point"}
}