{
  "type": "Feature",
  "properties": {
    "iso:country":"ES",
    "sg:address":"Calle de Rio Tajo, S/n",
    "sg:city":"San Vicente Del Raspeig-sant Vicent Del Raspeig",
    "sg:orig_category":"Parafarmacias",
    "sg:phone":"+34 965 67 61 48",
    "sg:postcode":"03690",
    "sg:province":"Alicante",
    "wof:name":"Borja Jimenez S.l.",
    "wof:placetype":"venue"
},
  "geometry": {"coordinates":[-0.5049390197,38.3922157288],"type":"Point"}
}