{
  "type": "Feature",
  "properties": {
    "addr:full":"Carrer de Virgili, 74 Barcelona Barcelona 08030",
    "addr:housenumber":"74",
    "addr:postcode":"08030",
    "addr:street":"Carrer De Virgili",
    "iso:country":"ES",
    "sg:address":"Carrer de Virgili, 74",
    "sg:city":"Barcelona",
    "sg:orig_category":"Reposter\u00cdas",
    "sg:phone":"+34 933 46 75 51",
    "sg:postcode":"08030",
    "sg:province":"Barcelona",
    "wof:name":"Tur Padro Jordi",
    "wof:placetype":"venue"
},
  "geometry": {"coordinates":[2.193365097,41.4319992065],"type":"Point"}
}