{
  "type": "Feature",
  "properties": {
    "addr:full":"Avda Orbigo (el), S/n Benavides De Orbigo Le\u00f3n 24280",
    "addr:housenumber":"s / n",
    "addr:postcode":"24280",
    "addr:street":"Avda Orbigo El;Leo\u0301N",
    "iso:country":"ES",
    "sg:address":"Avda Orbigo (el), S/n",
    "sg:city":"Benavides De Orbigo",
    "sg:orig_category":"Bebidas",
    "sg:phone":"+34 987 37 01 76",
    "sg:postcode":"24280",
    "sg:province":"Le\u00f3n",
    "wof:name":"Distribuciones Y Almacenes Guerra S.l.",
    "wof:placetype":"venue"
},
  "geometry": {"coordinates":[-5.8961648941,42.5003242493],"type":"Point"}
}