{
  "type": "Feature",
  "properties": {
    "addr:full":"Carr Mare De Deu De Loreto (de La), 69 Atzeneta Maestrat Castell\u00f3n 12132",
    "addr:housenumber":"69",
    "addr:postcode":"12132",
    "addr:street":"Carr Mare De Deu De Loreto De La;Maestrat Castello\u0301N",
    "iso:country":"ES",
    "sg:address":"Carr Mare De Deu De Loreto (de La), 69",
    "sg:city":"Atzeneta Maestrat",
    "sg:orig_category":"Bebidas",
    "sg:phone":"+34 964 37 00 57",
    "sg:postcode":"12132",
    "sg:province":"Castell\u00f3n",
    "wof:name":"Bertran Juan Patricia",
    "wof:placetype":"venue"
},
  "geometry": {"coordinates":[-0.1721789986,40.215839386],"type":"Point"}
}