{
  "type": "Feature",
  "properties": {
    "addr:full":"Carr Gracia, 4 Escala Girona 17130",
    "addr:housenumber":"4",
    "addr:postcode":"17130",
    "addr:street":"Carr Gracia",
    "iso:country":"ES",
    "sg:address":"Carr Gracia, 4",
    "sg:city":"Escala",
    "sg:orig_category":"Ropa Para Se\u00d1oras Y Caballeros (al Por Menor)",
    "sg:phone":"+34 972 77 07 47",
    "sg:postcode":"17130",
    "sg:province":"Girona",
    "wof:name":"Sabadi Puignau Emilia",
    "wof:placetype":"venue"
},
  "geometry": {"coordinates":[3.1321649551,42.1229934692],"type":"Point"}
}