{
  "type": "Feature",
  "properties": {
    "iso:country":"ES",
    "sg:address":"Rio Manzanares, 6",
    "sg:city":"Pqe. Boadilla",
    "sg:orig_category":"M\u00c9dicos: Medicina General",
    "sg:phone":"+34 916 33 38 88",
    "sg:postcode":"28669",
    "sg:province":"Madrid",
    "wof:name":"Fomento Salud S.l.",
    "wof:placetype":"venue"
},
  "geometry": {"coordinates":[-3.9164450169,40.4304504395],"type":"Point"}
}