{
  "type": "Feature",
  "properties": {
    "addr:full":"Avda Puente (del), 10 Titulcia Madrid 28359",
    "addr:housenumber":"10",
    "addr:postcode":"28359",
    "addr:street":"Avda Puente Del",
    "iso:country":"ES",
    "sg:address":"Avda Puente (del), 10",
    "sg:city":"Titulcia",
    "sg:orig_category":"Empresarios",
    "sg:phone":"+34 918 01 00 79",
    "sg:postcode":"28359",
    "sg:province":"Madrid",
    "wof:name":"Construcciones Y Reformas Bayona S.l.",
    "wof:placetype":"venue"
},
  "geometry": {"coordinates":[-3.5726571083,40.1369819641],"type":"Point"}
}