{
  "type": "Feature",
  "properties": {
    "iso:country":"ES",
    "sg:address":"Calle de Retogenes, S/n",
    "sg:city":"Soria",
    "sg:orig_category":"Centros De Educaci\u00d3n Especial",
    "sg:phone":"+34 975 22 21 57",
    "sg:postcode":"42001",
    "sg:province":"Soria",
    "wof:name":"Colegio Publico Las Pedrizas",
    "wof:placetype":"venue"
},
  "geometry": {"coordinates":[-2.4710741043,41.7671165466],"type":"Point"}
}