{
  "type": "Feature",
  "properties": {
    "iso:country":"ES",
    "sg:address":"Zona Muelle Pesquero, S/n",
    "sg:city":"Algeciras",
    "sg:classifiers":[
        {
            "category":"Recreation",
            "type":"Entertainment"
        }
    ],
    "sg:phone":"+34 956 63 16 28",
    "sg:postcode":"11201",
    "sg:province":"C\u00e1diz",
    "sg:tags":[
        "caza",
        "pr\u00c1ctica",
        "la",
        "de",
        "pesca",
        "y"
    ],
    "wof:name":"Lonja Pesquera De Algeciras",
    "wof:placetype":"venue"
},
  "geometry": {"coordinates":[-5.4397826195,36.135761261],"type":"Point"}
}