{
  "type": "Feature",
  "properties": {
    "addr:full":"Calle de Manuel Llaneza, 13 Langreo Asturias 33900",
    "addr:housenumber":"13",
    "addr:postcode":"33900",
    "addr:street":"Calle De Manuel Llaneza",
    "iso:country":"ES",
    "sg:address":"Calle de Manuel Llaneza, 13",
    "sg:city":"Langreo",
    "sg:orig_category":"Asociaciones Y Clubs Deportivos",
    "sg:phone":"+34 984 18 28 76",
    "sg:postcode":"33900",
    "sg:province":"Asturias",
    "wof:name":"Simon Gonzalez Gonzalez",
    "wof:placetype":"venue"
},
  "geometry": {"coordinates":[-5.6794061661,43.2928009033],"type":"Point"}
}