{
  "type": "Feature",
  "properties": {
    "iso:country":"ES",
    "sg:address":"Calle de Cordoba, S/n",
    "sg:city":"Ecija",
    "sg:orig_category":"Carnicer\u00cdas, Carnicer\u00cdas",
    "sg:phone":"+34 954 83 04 77",
    "sg:postcode":"41400",
    "sg:province":"Sevilla",
    "wof:name":"Camuez Palacios Angel",
    "wof:placetype":"venue"
},
  "geometry": {"coordinates":[-5.0893359184,37.546546936],"type":"Point"}
}