{
  "type": "Feature",
  "properties": {
    "iso:country":"ES",
    "sg:address":"Carrer de Sants, 109",
    "sg:city":"Barcelona",
    "sg:orig_category":"Instalaci\u00d3n De Sanitarios",
    "sg:phone":"+34 933 30 49 25",
    "sg:postcode":"08028",
    "sg:province":"Barcelona",
    "wof:name":"Colom Gabarro Maria Teresa",
    "wof:placetype":"venue"
},
  "geometry": {"coordinates":[2.1348159313,41.3752861023],"type":"Point"}
}