{
  "type": "Feature",
  "properties": {
    "addr:full":"Rond O'donnell, 25 Mataro Barcelona 08303",
    "addr:housenumber":"25",
    "addr:postcode":"08303",
    "addr:street":"O'Donnell",
    "iso:country":"ES",
    "sg:address":"Rond O'donnell, 25",
    "sg:city":"Mataro",
    "sg:orig_category":"Bisuter\u00cda, Joyer\u00cda, Relojer\u00cda (al Por Menor)",
    "sg:phone":"+34 937 98 67 72",
    "sg:postcode":"08303",
    "sg:province":"Barcelona",
    "wof:name":"Diaz Espinosa Enrique",
    "wof:placetype":"venue"
},
  "geometry": {"coordinates":[2.432060957,41.537979126],"type":"Point"}
}