{
  "type": "Feature",
  "properties": {
    "addr:full":"Calle de Lavador, 54 Calasparra Murcia 30420",
    "addr:housenumber":"54",
    "addr:postcode":"30420",
    "addr:street":"Calle De Lavador",
    "iso:country":"ES",
    "sg:address":"Calle de Lavador, 54",
    "sg:city":"Calasparra",
    "sg:orig_category":"Pintura, Barniz, Productos Asimilables (fabricaci\u00d3n, Al Por Mayor)",
    "sg:phone":"+34 968 72 05 04",
    "sg:postcode":"30420",
    "sg:province":"Murcia",
    "wof:name":"Pinturas Ure\u00f1a S.l.",
    "wof:placetype":"venue"
},
  "geometry": {"coordinates":[-1.6993069649,38.2312889099],"type":"Point"}
}