{
  "type": "Feature",
  "properties": {
    "addr:full":"Ctra Sevilla, Km. 0003,0 Badajoz Badajoz 06009",
    "addr:postcode":"06009",
    "addr:street":"Ctra Sevilla Km. 0003,0",
    "iso:country":"ES",
    "sg:address":"Ctra Sevilla, Km. 0003,0",
    "sg:city":"Badajoz",
    "sg:orig_category":"Frutas Y Legumbres Secas (al Por Mayor)",
    "sg:phone":"+34 924 24 08 51",
    "sg:postcode":"06009",
    "sg:province":"Badajoz",
    "wof:name":"Roman Duran S.l.",
    "wof:placetype":"venue"
},
  "geometry": {"coordinates":[-6.9603190422,38.8727493286],"type":"Point"}
}