{
  "type": "Feature",
  "properties": {
    "addr:full":"Pl Sant Ramon, 7 Cerdanyola Valles Barcelona 08290",
    "addr:housenumber":"7",
    "addr:postcode":"08290",
    "addr:street":"Pl Sant Ramon;Valles Barcelona",
    "iso:country":"ES",
    "sg:address":"Pl Sant Ramon, 7",
    "sg:city":"Cerdanyola Valles",
    "sg:orig_category":"Abogados",
    "sg:phone":"+34 936 91 89 97",
    "sg:postcode":"08290",
    "sg:province":"Barcelona",
    "wof:name":"Fernandez Martinez Maria Luz",
    "wof:placetype":"venue"
},
  "geometry": {"coordinates":[2.1360499859,41.4894714355],"type":"Point"}
}