{
  "type": "Feature",
  "properties": {
    "addr:full":"Ctra Nacional Ii, Km. 0402,0 Pe\u00f1alba Huesca 22592",
    "addr:postcode":"22592",
    "addr:street":"Ctra Nacional Ii Km. 0402,0",
    "iso:country":"ES",
    "sg:address":"Ctra Nacional Ii, Km. 0402,0",
    "sg:city":"Pe\u00f1alba",
    "sg:orig_category":"Forjas Y Altos Hornos",
    "sg:phone":"+34 974 46 32 76",
    "sg:postcode":"22592",
    "sg:province":"Huesca",
    "wof:name":"Palomera Dejuan Jose Maria",
    "wof:placetype":"venue"
},
  "geometry": {"coordinates":[-0.0414940007,41.4992332458],"type":"Point"}
}