{
  "type": "Feature",
  "properties": {
    "iso:country":"ES",
    "sg:address":"Carrer de Bisbe Morgades, 13",
    "sg:city":"Vilafranca Penedes",
    "sg:orig_category":"Heladeros",
    "sg:phone":"+34 938 17 12 19",
    "sg:postcode":"08720",
    "sg:province":"Barcelona",
    "wof:name":"Tot Gelat S.l.",
    "wof:placetype":"venue"
},
  "geometry": {"coordinates":[1.6978759766,41.3430671692],"type":"Point"}
}