{
  "type": "Feature",
  "properties": {
    "iso:country":"ES",
    "sg:address":"N. Carriquiri, 11",
    "sg:city":"Iru\u00f1a",
    "sg:orig_category":"Agencias Y Agentes Comerciales, Representantes",
    "sg:phone":"+34 948 12 82 90",
    "sg:postcode":"31014",
    "sg:province":"Navarra",
    "wof:name":"Heliz Herramientas S.l.",
    "wof:placetype":"venue"
},
  "geometry": {"coordinates":[-1.6437540054,42.81275177],"type":"Point"}
}