{
  "type": "Feature",
  "properties": {
    "addr:full":"Carrer de Viladordis, 106 Manresa Barcelona 08241",
    "addr:housenumber":"106",
    "addr:postcode":"08241",
    "addr:street":"Carrer De Viladordis",
    "iso:country":"ES",
    "sg:address":"Carrer de Viladordis, 106",
    "sg:city":"Manresa",
    "sg:orig_category":"Fisioterapia",
    "sg:phone":"+34 938 77 39 81",
    "sg:postcode":"08241",
    "sg:province":"Barcelona",
    "wof:name":"Fernandez Martinez Amaya",
    "wof:placetype":"venue"
},
  "geometry": {"coordinates":[1.8369309902,41.7256965637],"type":"Point"}
}