{
  "type": "Feature",
  "properties": {
    "addr:full":"Llano De Mora, S/n Valle S. Lorenzo Santa Cruz De Tenerife 38626",
    "addr:housenumber":"s",
    "addr:postcode":"38626",
    "addr:street":"/ N Valle S. Lorenzo",
    "iso:country":"ES",
    "sg:address":"Llano De Mora, S/n",
    "sg:city":"Valle S. Lorenzo",
    "sg:orig_category":"Supermercados Y Hipermercados",
    "sg:phone":"+34 922 76 62 04",
    "sg:postcode":"38626",
    "sg:province":"Santa Cruz De Tenerife",
    "wof:name":"Sierra Rodriguez Juan",
    "wof:placetype":"venue"
},
  "geometry": {"coordinates":[-16.6702098846,28.0729980469],"type":"Point"}
}