{
  "type": "Feature",
  "properties": {
    "iso:country":"ES",
    "sg:address":"Calle de Vitoria, 247",
    "sg:city":"Burgos",
    "sg:orig_category":"Fabricaci\u00d3n De Art\u00cdculos Para Papeler\u00cdas",
    "sg:phone":"+34 947 48 34 78",
    "sg:postcode":"09007",
    "sg:province":"Burgos",
    "sg:website":"www.sagredo.com",
    "wof:name":"Comercial Sagredo S. A.",
    "wof:placetype":"venue"
},
  "geometry": {"coordinates":[-3.6639690399,42.3549766541],"type":"Point"}
}