{
  "type": "Feature",
  "properties": {
    "addr:full":"Plaz Constitucion (de La), 6 Almu\u00f1ecar Granada 18690",
    "addr:housenumber":"6",
    "addr:postcode":"18690",
    "iso:country":"ES",
    "sg:address":"Plaz Constitucion (de La), 6",
    "sg:city":"Almu\u00f1ecar",
    "sg:orig_category":"Bisuter\u00cda, Joyer\u00cda, Relojer\u00cda (al Por Menor)",
    "sg:phone":"+34 958 88 13 97",
    "sg:postcode":"18690",
    "sg:province":"Granada",
    "wof:name":"Torres Barbero Diego Manuel",
    "wof:placetype":"venue"
},
  "geometry": {"coordinates":[-3.6911330223,36.7337188721],"type":"Point"}
}