{
  "type": "Feature",
  "properties": {
    "addr:full":"Carrer de Reding (de), 38 Tarragona Tarragona 43001",
    "addr:housenumber":"38",
    "addr:postcode":"43001",
    "addr:street":"Carrer De Reding De",
    "iso:country":"ES",
    "sg:address":"Carrer de Reding (de), 38",
    "sg:city":"Tarragona",
    "sg:orig_category":"Juegos Y Juguetes (al Por Menor)",
    "sg:phone":"+34 977 21 37 63",
    "sg:postcode":"43001",
    "sg:province":"Tarragona",
    "wof:name":"Ferre Saperas Maria Asuncion",
    "wof:placetype":"venue"
},
  "geometry": {"coordinates":[1.248232007,41.1160202026],"type":"Point"}
}