{
  "type": "Feature",
  "properties": {
    "iso:country":"ES",
    "sg:address":"Ctra. Laguna-punta Hidalgo, Km. 0007,0",
    "sg:city":"Tegueste",
    "sg:orig_category":"Quincaller\u00cda (al Por Menor)",
    "sg:phone":"+34 922 54 10 34",
    "sg:postcode":"38280",
    "sg:province":"Santa Cruz De Tenerife",
    "wof:name":"Gonzalez Alfaro Roberto",
    "wof:placetype":"venue"
},
  "geometry": {"coordinates":[-16.3384094238,28.5215549469],"type":"Point"}
}