{
  "type": "Feature",
  "properties": {
    "addr:full":"Calle de San Jose, 4 Santa Eulalia Islas Baleares 07840",
    "addr:housenumber":"4",
    "addr:postcode":"07840",
    "addr:street":"Calle De San Jose",
    "iso:country":"ES",
    "sg:address":"Calle de San Jose, 4",
    "sg:city":"Santa Eulalia",
    "sg:orig_category":"Peluquer\u00cdas, Peluquer\u00cda Mixta",
    "sg:phone":"+34 971 33 26 17",
    "sg:postcode":"07840",
    "sg:province":"Islas Baleares",
    "wof:name":"Clenxes S.l.",
    "wof:placetype":"venue"
},
  "geometry": {"coordinates":[1.5332330465,38.9855041504],"type":"Point"}
}