{
  "type": "Feature",
  "properties": {
    "iso:country":"ES",
    "sg:address":"Pg Sant Gervasi, 22",
    "sg:city":"Barcelona",
    "sg:orig_category":"Fabricaci\u00d3n De Etiquetas",
    "sg:phone":"+34 934 17 94 05",
    "sg:postcode":"08022",
    "sg:province":"Barcelona",
    "sg:website":"www.dennybros.com",
    "wof:name":"Denny Bros Ltd",
    "wof:placetype":"venue"
},
  "geometry": {"coordinates":[2.1346509457,41.4088020325],"type":"Point"}
}