{
  "type": "Feature",
  "properties": {
    "addr:full":"Avda Najera, S/n Santo Domingo De La Calzada La Rioja 26250",
    "addr:housenumber":"/ n",
    "addr:postcode":"26250",
    "addr:street":"Avda Najera S;Calzada;Rioja",
    "iso:country":"ES",
    "sg:address":"Avda Najera, S/n",
    "sg:city":"Santo Domingo De La Calzada",
    "sg:orig_category":"Empresas De Carpinter\u00cda",
    "sg:phone":"+34 941 34 30 85",
    "sg:postcode":"26250",
    "sg:province":"La Rioja",
    "wof:name":"Aluminios Jose Ignacio S.l.u.",
    "wof:placetype":"venue"
},
  "geometry": {"coordinates":[-2.9477918148,42.436088562],"type":"Point"}
}