{
  "type": "Feature",
  "properties": {
    "addr:full":"Calle de Rio Segre, 2 Alcorcon Madrid 28923",
    "addr:housenumber":"2",
    "addr:postcode":"28923",
    "addr:street":"Calle De Rio Segre",
    "iso:country":"ES",
    "sg:address":"Calle de Rio Segre, 2",
    "sg:city":"Alcorcon",
    "sg:orig_category":"Farmacias",
    "sg:phone":"+34 916 19 97 53",
    "sg:postcode":"28923",
    "sg:province":"Madrid",
    "wof:name":"Seriola Garcia-morales Manuel",
    "wof:placetype":"venue"
},
  "geometry": {"coordinates":[-3.8149430752,40.3450584412],"type":"Point"}
}