{
  "type": "Feature",
  "properties": {
    "iso:country":"ES",
    "sg:address":"Avda Kiriki\u00d1o, 42",
    "sg:city":"Bilbao",
    "sg:orig_category":"Supermercados Y Hipermercados",
    "sg:phone":"+34 944 44 60 71",
    "sg:postcode":"48012",
    "sg:province":"Vizcaya",
    "wof:name":"Autoservicios Antei S.l.l.",
    "wof:placetype":"venue"
},
  "geometry": {"coordinates":[-2.9368770123,43.2535018921],"type":"Point"}
}