{
  "type": "Feature",
  "properties": {
    "iso:country":"ES",
    "sg:address":"Calle de Alfonso Vi, 1",
    "sg:city":"Sepulveda",
    "sg:orig_category":"Ropa Para Se\u00d1oras Y Caballeros (al Por Menor)",
    "sg:phone":"+34 921 54 00 97",
    "sg:postcode":"40300",
    "sg:province":"Segovia",
    "wof:name":"Ponce Anton David",
    "wof:placetype":"venue"
},
  "geometry": {"coordinates":[-3.7485799789,41.2977790833],"type":"Point"}
}