{
  "type": "Feature",
  "properties": {
    "iso:country":"ES",
    "sg:address":"Pl. Mercat, 15",
    "sg:city":"Olot",
    "sg:orig_category":"Carnicer\u00cdas, Carnicer\u00cdas",
    "sg:phone":"+34 972 26 69 20",
    "sg:postcode":"17800",
    "sg:province":"Girona",
    "wof:name":"Garrido Carrillo Robustiano",
    "wof:placetype":"venue"
},
  "geometry": {"coordinates":[2.4703056812,42.1801338196],"type":"Point"}
}