{
  "type": "Feature",
  "properties": {
    "iso:country":"ES",
    "sg:address":"Carr Progres, S/n",
    "sg:city":"Santa Margalida",
    "sg:orig_category":"Ense\u00d1anza Secundaria: Colegios Y Escuelas Privadas",
    "sg:phone":"+34 971 85 60 00",
    "sg:postcode":"07450",
    "sg:province":"Islas Baleares",
    "wof:name":"Institut D'ensenyament Secundari De Santa Margalida",
    "wof:placetype":"venue"
},
  "geometry": {"coordinates":[3.1024870872,39.7049102783],"type":"Point"}
}