{
  "type": "Feature",
  "properties": {
    "iso:country":"ES",
    "sg:address":"Palencia, 11",
    "sg:city":"Candeleda",
    "sg:orig_category":"Inmobiliaria (agencias)",
    "sg:phone":"+34 920 38 06 20",
    "sg:postcode":"05480",
    "sg:province":"\u00c1vila",
    "wof:name":"Gescam Inversiones S.l.",
    "wof:placetype":"venue"
},
  "geometry": {"coordinates":[-5.240790844,40.1553764343],"type":"Point"}
}