{
  "type": "Feature",
  "properties": {
    "iso:country":"ES",
    "sg:address":"Avda Manolete De, 1",
    "sg:city":"Nueva Andalucia",
    "sg:orig_category":"Cl\u00cdnicas M\u00c9dicas",
    "sg:phone":"+34 952 81 42 29",
    "sg:postcode":"29660",
    "sg:province":"M\u00e1laga",
    "wof:name":"Centro Medico Alboran S.c",
    "wof:placetype":"venue"
},
  "geometry": {"coordinates":[-4.9597129822,36.4921302795],"type":"Point"}
}