{
  "type": "Feature",
  "properties": {
    "iso:country":"ES",
    "sg:address":"Avda Hernan Cortes, 20",
    "sg:city":"Caceres",
    "sg:orig_category":"M\u00c9dicos: Oftalmolog\u00cda",
    "sg:phone":"+34 927 24 01 25",
    "sg:postcode":"10004",
    "sg:province":"C\u00e1ceres",
    "wof:name":"Jimenez Rosaleny Juan Maria",
    "wof:placetype":"venue"
},
  "geometry": {"coordinates":[-6.378991127,39.4752235413],"type":"Point"}
}