{
  "type": "Feature",
  "properties": {
    "addr:full":"Calle de Pelayo, 3 Oviedo Asturias 33003",
    "addr:housenumber":"3",
    "addr:postcode":"33003",
    "addr:street":"Calle De Pelayo",
    "iso:country":"ES",
    "sg:address":"Calle de Pelayo, 3",
    "sg:city":"Oviedo",
    "sg:orig_category":"Fotograf\u00cda Y Cine: Aparatos, Pel\u00cdculas Y Accesorios (fabricaci\u00d3n, Al Por Mayor)",
    "sg:phone":"+34 985 21 01 04",
    "sg:postcode":"33003",
    "sg:province":"Asturias",
    "wof:name":"Rapidfot S.a.",
    "wof:placetype":"venue"
},
  "geometry": {"coordinates":[-5.8481497765,43.362575531],"type":"Point"}
}