{
  "type": "Feature",
  "properties": {
    "iso:country":"ES",
    "sg:address":"Avda Deportes (de Los), 7",
    "sg:city":"Arevalo",
    "sg:orig_category":"Psic\u00d3logos",
    "sg:phone":"+34 920 30 19 50",
    "sg:postcode":"05200",
    "sg:province":"\u00c1vila",
    "wof:name":"Garcia Pulido Jose Antonio",
    "wof:placetype":"venue"
},
  "geometry": {"coordinates":[-4.7180738449,41.0576553345],"type":"Point"}
}