{
  "type": "Feature",
  "properties": {
    "addr:full":"Partida Torreta Izquierda, 34 Elda Alicante 03600",
    "addr:housenumber":"34",
    "addr:postcode":"03600",
    "addr:street":"Partida Torreta Izquierda",
    "iso:country":"ES",
    "sg:address":"Partida Torreta Izquierda, 34",
    "sg:city":"Elda",
    "sg:orig_category":"Suministros Y Materiales Industriales",
    "sg:phone":"+34 965 39 23 62",
    "sg:postcode":"03600",
    "sg:province":"Alicante",
    "wof:name":"Suintra S.l.",
    "wof:placetype":"venue"
},
  "geometry": {"coordinates":[-0.7966089845,38.4770317078],"type":"Point"}
}