{
  "type": "Feature",
  "properties": {
    "iso:country":"ES",
    "sg:address":"Calle de Parque San Julian, 14",
    "sg:city":"Cuenca",
    "sg:orig_category":"Art\u00cdculos De Decoraci\u00d3n",
    "sg:phone":"+34 969 22 75 16",
    "sg:postcode":"16002",
    "sg:province":"Cuenca",
    "wof:name":"Angulo Huelamo Alejandro",
    "wof:placetype":"venue"
},
  "geometry": {"coordinates":[-2.1350729465,40.0736618042],"type":"Point"}
}