{
  "type": "Feature",
  "properties": {
    "iso:country":"ES",
    "sg:address":"Calle de Virgen De La Victoria, 12",
    "sg:city":"Sevilla",
    "sg:orig_category":"Ropa Para Se\u00d1oras (al Por Menor)",
    "sg:phone":"+34 954 45 15 05",
    "sg:postcode":"41011",
    "sg:province":"Sevilla",
    "wof:name":"Leon Tamayo Monserrat",
    "wof:placetype":"venue"
},
  "geometry": {"coordinates":[-6.0017676353,37.3721160889],"type":"Point"}
}