{
  "type": "Feature",
  "properties": {
    "iso:country":"ES",
    "sg:address":"Calle de Medinaceli, 3",
    "sg:city":"Torrejon Ardoz",
    "sg:orig_category":"Colchones (fabricaci\u00d3n, Al Por Mayor, Al Por Menor)",
    "sg:phone":"+34 916 77 02 67",
    "sg:postcode":"28850",
    "sg:province":"Madrid",
    "wof:name":"Lopez Jaen David",
    "wof:placetype":"venue"
},
  "geometry": {"coordinates":[-3.4779241085,40.4599990845],"type":"Point"}
}