{
  "type": "Feature",
  "properties": {
    "addr:full":"Carrer de Gabriel Ferrater, 16 Barcelona Barcelona 08017",
    "addr:housenumber":"16",
    "addr:postcode":"08017",
    "addr:street":"Carrer De Gabriel Ferrater",
    "iso:country":"ES",
    "sg:address":"Carrer de Gabriel Ferrater, 16",
    "sg:city":"Barcelona",
    "sg:orig_category":"Inmobiliaria (agencias)",
    "sg:phone":"+34 934 06 98 82",
    "sg:postcode":"08017",
    "sg:province":"Barcelona",
    "wof:name":"Vitae Soluciones Inmobiliarias S.l.",
    "wof:placetype":"venue"
},
  "geometry": {"coordinates":[2.109919548,41.4170379639],"type":"Point"}
}