{
  "type": "Feature",
  "properties": {
    "addr:full":"Martin Azpilcueta, 22 Iru\u00f1a Navarra 31011",
    "addr:housenumber":"22",
    "addr:postcode":"31011",
    "addr:street":"Azpilcueta",
    "iso:country":"ES",
    "sg:address":"Martin Azpilcueta, 22",
    "sg:city":"Iru\u00f1a",
    "sg:orig_category":"Cl\u00cdnicas Dentales",
    "sg:phone":"+34 948 17 13 32",
    "sg:postcode":"31011",
    "sg:province":"Navarra",
    "wof:name":"Landa Aizcorbe Juan Miguel",
    "wof:placetype":"venue"
},
  "geometry": {"coordinates":[-1.6619839668,42.8133735657],"type":"Point"}
}