{
  "type": "Feature",
  "properties": {
    "addr:full":"Av Metro, 1 Hospitalet Llobregat Barcelona 08902",
    "addr:housenumber":"1",
    "addr:postcode":"08902",
    "addr:street":"Av Metro",
    "iso:country":"ES",
    "sg:address":"Av Metro, 1",
    "sg:city":"Hospitalet Llobregat",
    "sg:orig_category":"Loter\u00cda Y T\u00d3mbola",
    "sg:phone":"+34 932 96 53 74",
    "sg:postcode":"08902",
    "sg:province":"Barcelona",
    "wof:name":"Trias Cambra Jaime",
    "wof:placetype":"venue"
},
  "geometry": {"coordinates":[2.1269340515,41.3671722412],"type":"Point"}
}