{
  "type": "Feature",
  "properties": {
    "iso:country":"ES",
    "sg:address":"Calle de Gonzalez Davila, 22",
    "sg:city":"Madrid",
    "sg:orig_category":"Estilistas Y Estudios De Estilo De Corte Y Confecci\u00d3n",
    "sg:phone":"+34 917 78 38 56",
    "sg:postcode":"28031",
    "sg:province":"Madrid",
    "wof:name":"Marin Y Mier S.l.",
    "wof:placetype":"venue"
},
  "geometry": {"coordinates":[-3.6384589672,40.3746910095],"type":"Point"}
}