{
  "type": "Feature",
  "properties": {
    "iso:country":"ES",
    "sg:address":"Carr Doctor Lleonart, 11",
    "sg:city":"Burjassot",
    "sg:orig_category":"Promotores Constructores",
    "sg:phone":"+34 963 63 05 30",
    "sg:postcode":"46100",
    "sg:province":"Valencia",
    "wof:name":"Pascual Llorens S.l.",
    "wof:placetype":"venue"
},
  "geometry": {"coordinates":[-0.4144679904,39.5071792603],"type":"Point"}
}