{
  "type": "Feature",
  "properties": {
    "iso:country":"ES",
    "sg:address":"Avda Manuel Aza\u00d1a (de), 12",
    "sg:city":"Coslada",
    "sg:orig_category":"Lavado, Limpieza De Veh\u00cdculos",
    "sg:phone":"+34 916 71 68 47",
    "sg:postcode":"28820",
    "sg:province":"Madrid",
    "wof:name":"Gomez Lopez Manuel",
    "wof:placetype":"venue"
},
  "geometry": {"coordinates":[-3.5538809299,40.4187660217],"type":"Point"}
}