{
  "type": "Feature",
  "properties": {
    "addr:full":"Calle de Llanos (los), S/n Carboneras Almer\u00eda 04140",
    "addr:postcode":"04140",
    "addr:street":"Calle De Llanos Los S / N;Almeri\u0301A",
    "iso:country":"ES",
    "sg:address":"Calle de Llanos (los), S/n",
    "sg:city":"Carboneras",
    "sg:orig_category":"Albergues",
    "sg:phone":"+34 950 45 42 54",
    "sg:postcode":"04140",
    "sg:province":"Almer\u00eda",
    "wof:name":"Alarcon Diaz Ana",
    "wof:placetype":"venue"
},
  "geometry": {"coordinates":[-1.8921784163,37.0014076233],"type":"Point"}
}