{
  "type": "Feature",
  "properties": {
    "addr:full":"Avda Valladolid, 28 Valencia Valencia 46020",
    "addr:housenumber":"28",
    "addr:postcode":"46020",
    "addr:street":"Avda Valladolid",
    "iso:country":"ES",
    "sg:address":"Avda Valladolid, 28",
    "sg:city":"Valencia",
    "sg:orig_category":"Estancos",
    "sg:phone":"+34 963 93 13 24",
    "sg:postcode":"46020",
    "sg:province":"Valencia",
    "wof:name":"Gimeno Beltran Luis",
    "wof:placetype":"venue"
},
  "geometry": {"coordinates":[-0.3596299887,39.4887237549],"type":"Point"}
}