{
  "type": "Feature",
  "properties": {
    "iso:country":"ES",
    "sg:address":"Av Carles Buigas (de), 5",
    "sg:city":"Salou",
    "sg:orig_category":"Art\u00cdculos De Regalo (al Por Menor)",
    "sg:phone":"+34 977 38 59 02",
    "sg:postcode":"43840",
    "sg:province":"Tarragona",
    "wof:name":"La Cuca Igualames S.l.",
    "wof:placetype":"venue"
},
  "geometry": {"coordinates":[1.1449459791,41.0728797913],"type":"Point"}
}