{
  "type": "Feature",
  "properties": {
    "addr:full":"Calle de Trinidad, 10 Guardia Toledo 45760",
    "addr:housenumber":"10",
    "addr:postcode":"45760",
    "addr:street":"Calle De Trinidad",
    "iso:country":"ES",
    "sg:address":"Calle de Trinidad, 10",
    "sg:city":"Guardia",
    "sg:orig_category":"Peluquer\u00cdas, Peluquer\u00cda Mixta",
    "sg:phone":"+34 925 13 85 20",
    "sg:postcode":"45760",
    "sg:province":"Toledo",
    "wof:name":"Dominguez Garcia Laura",
    "wof:placetype":"venue"
},
  "geometry": {"coordinates":[-3.4735291004,39.787689209],"type":"Point"}
}