{
  "type": "Feature",
  "properties": {
    "iso:country":"ES",
    "sg:address":"Juan De Borbon, 16",
    "sg:city":"Torres Cotillas",
    "sg:orig_category":"Estudios Y Construcci\u00d3n De Acuarios Y Viveros",
    "sg:phone":"+34 968 62 42 86",
    "sg:postcode":"30565",
    "sg:province":"Murcia",
    "sg:website":"www.marine-pond-garde.com",
    "wof:name":"Zapata Garcia Remedios",
    "wof:placetype":"venue"
},
  "geometry": {"coordinates":[-1.2380244732,38.020980835],"type":"Point"}
}