{
  "type": "Feature",
  "properties": {
    "addr:full":"Ctra Sant Climent, 12 Viladecans Barcelona 08840",
    "addr:housenumber":"12",
    "addr:postcode":"08840",
    "addr:street":"Ctra Sant Climent",
    "iso:country":"ES",
    "sg:address":"Ctra Sant Climent, 12",
    "sg:city":"Viladecans",
    "sg:orig_category":"Florister\u00cdas",
    "sg:phone":"+34 936 37 45 10",
    "sg:postcode":"08840",
    "sg:province":"Barcelona",
    "wof:name":"Mata Arroyo Maria Teresa",
    "wof:placetype":"venue"
},
  "geometry": {"coordinates":[2.0183849335,41.3197250366],"type":"Point"}
}