{
  "type": "Feature",
  "properties": {
    "iso:country":"ES",
    "sg:address":"Carrer de Puigmarti, 19",
    "sg:city":"Barcelona",
    "sg:orig_category":"Fabricaci\u00d3n De Ropa De Deportes",
    "sg:phone":"+34 932 13 04 27",
    "sg:postcode":"08012",
    "sg:province":"Barcelona",
    "sg:website":"www.sportdisseny.com",
    "wof:name":"Martin Rosell Josep Maria",
    "wof:placetype":"venue"
},
  "geometry": {"coordinates":[2.1602098942,41.4022865295],"type":"Point"}
}