{
  "type": "Feature",
  "properties": {
    "iso:country":"ES",
    "sg:address":"Avda Comercio (del), 11",
    "sg:city":"Chiclana De La Frontera",
    "sg:orig_category":"Veh\u00cdculos De Ocasi\u00d3n",
    "sg:phone":"+34 956 40 73 48",
    "sg:postcode":"11130",
    "sg:province":"C\u00e1diz",
    "wof:name":"Autorevent S.l.",
    "wof:placetype":"venue"
},
  "geometry": {"coordinates":[-6.1471271515,36.4265289307],"type":"Point"}
}