{
  "type": "Feature",
  "properties": {
    "addr:full":"Avda Valencia, 70 Castellon Castell\u00f3n 12006",
    "addr:housenumber":"70",
    "addr:postcode":"12006",
    "addr:street":"Avda Valencia",
    "iso:country":"ES",
    "sg:address":"Avda Valencia, 70",
    "sg:city":"Castellon",
    "sg:orig_category":"Pintura Y Barniz (al Por Menor)",
    "sg:phone":"+34 964 24 73 73",
    "sg:postcode":"12006",
    "sg:province":"Castell\u00f3n",
    "wof:name":"Pinturas Martin Gil S.a.",
    "wof:placetype":"venue"
},
  "geometry": {"coordinates":[-0.1292939931,40.0168533325],"type":"Point"}
}