{
  "type": "Feature",
  "properties": {
    "addr:full":"Rincon Gallego, 15 Torreaguera Murcia 30579",
    "addr:housenumber":"15",
    "addr:postcode":"30579",
    "addr:street":"Gallego",
    "iso:country":"ES",
    "sg:address":"Rincon Gallego, 15",
    "sg:city":"Torreaguera",
    "sg:orig_category":"M\u00c1rmoles, Granitos Y Piedras Naturales",
    "sg:phone":"+34 968 82 44 03",
    "sg:postcode":"30579",
    "sg:province":"Murcia",
    "wof:name":"Montoya Vicente Antonio Tomas",
    "wof:placetype":"venue"
},
  "geometry": {"coordinates":[-1.054823041,37.9840812683],"type":"Point"}
}