{
  "type": "Feature",
  "properties": {
    "addr:full":"Carrer de Calaf, 25 Barcelona Barcelona 08021",
    "addr:housenumber":"25",
    "addr:postcode":"08021",
    "addr:street":"Carrer De Calaf",
    "iso:country":"ES",
    "sg:address":"Carrer de Calaf, 25",
    "sg:city":"Barcelona",
    "sg:orig_category":"Supermercados Y Hipermercados",
    "sg:phone":"+34 932 00 51 46",
    "sg:postcode":"08021",
    "sg:province":"Barcelona",
    "sg:website":"www.capraboacasa.com",
    "wof:name":"Caprabo S.a.",
    "wof:placetype":"venue"
},
  "geometry": {"coordinates":[2.1428689957,41.3963623047],"type":"Point"}
}