{
  "type": "Feature",
  "properties": {
    "addr:full":"Calle de Primo De Rivera, 21 Pe\u00f1iscola Castell\u00f3n 12598",
    "addr:housenumber":"21",
    "addr:postcode":"12598",
    "addr:street":"Calle De Primo De Rivera;Castello\u0301N",
    "iso:country":"ES",
    "sg:address":"Calle de Primo De Rivera, 21",
    "sg:city":"Pe\u00f1iscola",
    "sg:orig_category":"Asociaciones Y Clubs Deportivos",
    "sg:phone":"+34 964 48 01 32",
    "sg:postcode":"12598",
    "sg:province":"Castell\u00f3n",
    "wof:name":"Deportes Clavilla C.b.",
    "wof:placetype":"venue"
},
  "geometry": {"coordinates":[0.4034300148,40.3598175049],"type":"Point"}
}