{
  "type": "Feature",
  "properties": {
    "addr:full":"Pl. Galcer\u00e1n De Pinos, 1 Baga Barcelona 08695",
    "addr:housenumber":"1",
    "addr:postcode":"08695",
    "addr:street":"Pl. Galcera\u0301N De Pinos",
    "iso:country":"ES",
    "sg:address":"Pl. Galcer\u00e1n De Pinos, 1",
    "sg:city":"Baga",
    "sg:orig_category":"Inform\u00c1tica, Ofim\u00c1tica (estudios, Asesor\u00cda, Ingenier\u00cda, Formaci\u00d3n)",
    "sg:phone":"+34 938 24 48 74",
    "sg:postcode":"08695",
    "sg:province":"Barcelona",
    "sg:website":"www.setze.net",
    "wof:name":"Setze.net S.c.p.",
    "wof:placetype":"venue"
},
  "geometry": {"coordinates":[1.8605049849,42.2527961731],"type":"Point"}
}