{
  "type": "Feature",
  "properties": {
    "addr:full":"Camino Del Molino, S/n Bornos C\u00e1diz 11640",
    "addr:housenumber":"s / n",
    "addr:postcode":"11640",
    "addr:street":"Camino Del Molino;Bornos Ca\u0301Diz",
    "iso:country":"ES",
    "sg:address":"Camino Del Molino, S/n",
    "sg:city":"Bornos",
    "sg:orig_category":"Bebidas",
    "sg:phone":"+34 956 71 23 96",
    "sg:postcode":"11640",
    "sg:province":"C\u00e1diz",
    "wof:name":"Distribuidora Bornense S.l.",
    "wof:placetype":"venue"
},
  "geometry": {"coordinates":[-5.7435588837,36.8215560913],"type":"Point"}
}