{
  "type": "Feature",
  "properties": {
    "iso:country":"ES",
    "sg:address":"Calle de Maria De Molina, 56",
    "sg:city":"Madrid",
    "sg:orig_category":"Organismos De Reclutamiento",
    "sg:phone":"+34 915 62 38 82",
    "sg:postcode":"28006",
    "sg:province":"Madrid",
    "wof:name":"Osbo Consultores S.l.",
    "wof:placetype":"venue"
},
  "geometry": {"coordinates":[-3.6797196865,40.4374084473],"type":"Point"}
}