{
  "type": "Feature",
  "properties": {
    "iso:country":"ES",
    "sg:address":"Av. Constitucion, 51",
    "sg:city":"Torrent",
    "sg:orig_category":"Arquitectos",
    "sg:phone":"+34 961 56 66 73",
    "sg:postcode":"46900",
    "sg:province":"Valencia",
    "wof:name":"Lluna Reig Carlos",
    "wof:placetype":"venue"
},
  "geometry": {"coordinates":[-0.4793789983,39.4306869507],"type":"Point"}
}