{
  "type": "Feature",
  "properties": {
    "addr:full":"Ciudad Real-madrid, Km. 0332,6 Daimiel Ciudad Real 13250",
    "addr:postcode":"13250",
    "addr:street":"Real-Madrid Km. 0332,6",
    "iso:country":"ES",
    "sg:address":"Ciudad Real-madrid, Km. 0332,6",
    "sg:city":"Daimiel",
    "sg:orig_category":"Art\u00cdculos De Regalo (al Por Menor)",
    "sg:phone":"+34 926 69 30 00",
    "sg:postcode":"13250",
    "sg:province":"Ciudad Real",
    "sg:website":"www.daimiel.com",
    "wof:name":"Comercial Daimiele\u00f1a Melero S.l.",
    "wof:placetype":"venue"
},
  "geometry": {"coordinates":[-3.5926830769,39.0789985657],"type":"Point"}
}