{
  "type": "Feature",
  "properties": {
    "iso:country":"ES",
    "sg:address":"Calle de Navarra, 3",
    "sg:city":"Valencia",
    "sg:orig_category":"Inform\u00c1tica (estudios, Servicios, Asesor\u00cda, Formaci\u00d3n)",
    "sg:phone":"+34 963 84 84 90",
    "sg:postcode":"46008",
    "sg:province":"Valencia",
    "wof:name":"Posada De Almanzor S.l.",
    "wof:placetype":"venue"
},
  "geometry": {"coordinates":[-0.3859019876,39.4674110413],"type":"Point"}
}