{
  "type": "Feature",
  "properties": {
    "addr:full":"Calle de Ceferino Rodriguez, 4 Madrid Madrid 28029",
    "addr:housenumber":"4",
    "addr:postcode":"28029",
    "addr:street":"Calle De Ceferino Rodriguez",
    "iso:country":"ES",
    "sg:address":"Calle de Ceferino Rodriguez, 4",
    "sg:city":"Madrid",
    "sg:orig_category":"Asilos De Ancianos. Centros Privados",
    "sg:phone":"+34 913 23 09 12",
    "sg:postcode":"28029",
    "sg:province":"Madrid",
    "wof:name":"Seijas Calvo Maria Del Carmen",
    "wof:placetype":"venue"
},
  "geometry": {"coordinates":[-3.697302103,40.4664726257],"type":"Point"}
}