{
  "type": "Feature",
  "properties": {
    "addr:full":"Calle de Langreo, 11 Gijon Asturias 33206",
    "addr:housenumber":"11",
    "addr:postcode":"33206",
    "addr:street":"Calle De Langreo",
    "iso:country":"ES",
    "sg:address":"Calle de Langreo, 11",
    "sg:city":"Gijon",
    "sg:orig_category":"Caf\u00c9s, Bares, Cervecer\u00cdas",
    "sg:phone":"+34 985 35 88 49",
    "sg:postcode":"33206",
    "sg:province":"Asturias",
    "wof:name":"Suarez Cuervo S.l.",
    "wof:placetype":"venue"
},
  "geometry": {"coordinates":[-5.6654543877,43.5405540466],"type":"Point"}
}