{
  "type": "Feature",
  "properties": {
    "addr:full":"Calle de Miguel De Cervantes, 3 Santurtzi Vizcaya 48980",
    "addr:housenumber":"3",
    "addr:postcode":"48980",
    "addr:street":"Calle De Miguel De Cervantes",
    "iso:country":"ES",
    "sg:address":"Calle de Miguel De Cervantes, 3",
    "sg:city":"Santurtzi",
    "sg:orig_category":"Fabricaci\u00d3n, Venta De Cuadros, Accesorios Para Enmarcar",
    "sg:phone":"+34 944 62 57 99",
    "sg:postcode":"48980",
    "sg:province":"Vizcaya",
    "wof:name":"Alfredo Jimenez Roldan Y Otro C.b.",
    "wof:placetype":"venue"
},
  "geometry": {"coordinates":[-3.0321059227,43.3265228271],"type":"Point"}
}