{
  "type": "Feature",
  "properties": {
    "iso:country":"ES",
    "sg:address":"Pje Carmen D. Miral, 3",
    "sg:city":"Jaca",
    "sg:orig_category":"Institutos De Belleza",
    "sg:phone":"+34 974 36 45 00",
    "sg:postcode":"22700",
    "sg:province":"Huesca",
    "wof:name":"Vila Lera Julia",
    "wof:placetype":"venue"
},
  "geometry": {"coordinates":[-0.5519520044,42.5658493042],"type":"Point"}
}