{
  "type": "Feature",
  "properties": {
    "addr:full":"Calle de Rosalia De Castro, 1 Majadahonda Madrid 28220",
    "addr:housenumber":"1",
    "addr:postcode":"28220",
    "addr:street":"Calle De Rosalia De Castro",
    "iso:country":"ES",
    "sg:address":"Calle de Rosalia De Castro, 1",
    "sg:city":"Majadahonda",
    "sg:orig_category":"Inmobiliaria (agencias)",
    "sg:phone":"+34 916 34 77 90",
    "sg:postcode":"28220",
    "sg:province":"Madrid",
    "sg:website":"www.remax.es",
    "wof:name":"Privilege Home, Sl",
    "wof:placetype":"venue"
},
  "geometry": {"coordinates":[-3.8711268902,40.4674873352],"type":"Point"}
}