{
  "type": "Feature",
  "properties": {
    "iso:country":"ES",
    "sg:address":"Ctra. Beniali, Km. 0002,7",
    "sg:city":"Enguera",
    "sg:orig_category":"Explotaci\u00d3n De Canteras",
    "sg:phone":"+34 962 13 20 38",
    "sg:postcode":"46810",
    "sg:province":"Valencia",
    "sg:website":"www.calcinor.com",
    "wof:name":"Triturados Arisan S.l.",
    "wof:placetype":"venue"
},
  "geometry": {"coordinates":[-0.6887639761,38.9810943604],"type":"Point"}
}