{
  "type": "Feature",
  "properties": {
    "addr:full":"Calle de Antonio Espinosa, 12 Salamanca Salamanca 37007",
    "addr:housenumber":"12",
    "addr:postcode":"37007",
    "addr:street":"Calle De Antonio Espinosa",
    "iso:country":"ES",
    "sg:address":"Calle de Antonio Espinosa, 12",
    "sg:city":"Salamanca",
    "sg:orig_category":"Peluquer\u00cdas, Peluquer\u00cda Mixta",
    "sg:phone":"+34 923 24 70 28",
    "sg:postcode":"37007",
    "sg:province":"Salamanca",
    "wof:name":"Puente Arribas Jose Carlos",
    "wof:placetype":"venue"
},
  "geometry": {"coordinates":[-5.6655006409,40.9702415466],"type":"Point"}
}