{
  "type": "Feature",
  "properties": {
    "iso:country":"ES",
    "sg:address":"Calle de San Vicente Ferrer, 19",
    "sg:city":"Zaragoza",
    "sg:orig_category":"Pintura: M\u00c1quinas (instalaci\u00d3n)",
    "sg:phone":"+34 976 34 59 99",
    "sg:postcode":"50011",
    "sg:province":"Zaragoza",
    "wof:name":"Lazaro Galindo Jose",
    "wof:placetype":"venue"
},
  "geometry": {"coordinates":[-0.926874876,41.6508255005],"type":"Point"}
}