{
  "type": "Feature",
  "properties": {
    "addr:full":"Plaz Santo Domingo, 2 Alca\u00f1iz Teruel 44600",
    "addr:housenumber":"2",
    "addr:postcode":"44600",
    "addr:street":"Santo Domingo",
    "iso:country":"ES",
    "sg:address":"Plaz Santo Domingo, 2",
    "sg:city":"Alca\u00f1iz",
    "sg:orig_category":"Transportes De Material De Construcci\u00d3n",
    "sg:phone":"+34 978 83 00 49",
    "sg:postcode":"44600",
    "sg:province":"Teruel",
    "wof:name":"Lopez Lopez Francisco",
    "wof:placetype":"venue"
},
  "geometry": {"coordinates":[-0.1347319931,41.0515289307],"type":"Point"}
}