{
  "type": "Feature",
  "properties": {
    "addr:full":"Calle de Mendizabal, 4 Oviedo Asturias 33003",
    "addr:housenumber":"4",
    "addr:postcode":"33003",
    "addr:street":"Calle De Mendizabal",
    "iso:country":"ES",
    "sg:address":"Calle de Mendizabal, 4",
    "sg:city":"Oviedo",
    "sg:orig_category":"Fotograf\u00cda Art\u00cdstica Y Retratos",
    "sg:phone":"+34 985 21 81 30",
    "sg:postcode":"33003",
    "sg:province":"Asturias",
    "wof:name":"Jose Antonio Carretero Sevilla Y Otros Cdad.",
    "wof:placetype":"venue"
},
  "geometry": {"coordinates":[-5.8463659286,43.3627471924],"type":"Point"}
}