{
  "type": "Feature",
  "properties": {
    "addr:full":"Avda Constitucion, 27 Artajona Navarra 31140",
    "addr:housenumber":"27",
    "addr:postcode":"31140",
    "addr:street":"Avda Constitucion",
    "iso:country":"ES",
    "sg:address":"Avda Constitucion, 27",
    "sg:city":"Artajona",
    "sg:orig_category":"Material Y Herramientas Agr\u00cdcolas",
    "sg:phone":"+34 948 36 41 18",
    "sg:postcode":"31140",
    "sg:province":"Navarra",
    "wof:name":"Divasson Izuriaga Alberto Y Divasson Valencia Gregorio S.cv.",
    "wof:placetype":"venue"
},
  "geometry": {"coordinates":[-1.7589039803,42.5915145874],"type":"Point"}
}