{
  "type": "Feature",
  "properties": {
    "addr:full":"Avda Antonio Chacon, 5 Zafra Badajoz 06300",
    "addr:housenumber":"5",
    "addr:postcode":"06300",
    "addr:street":"Avda Antonio Chacon",
    "iso:country":"ES",
    "sg:address":"Avda Antonio Chacon, 5",
    "sg:city":"Zafra",
    "sg:orig_category":"Alquiler De V\u00cddeo",
    "sg:phone":"+34 924 55 52 22",
    "sg:postcode":"06300",
    "sg:province":"Badajoz",
    "wof:name":"Garcia Rodriguez Fernando",
    "wof:placetype":"venue"
},
  "geometry": {"coordinates":[-6.4121069908,38.4245681763],"type":"Point"}
}