{
  "type": "Feature",
  "properties": {
    "addr:full":"Pl Creu, 4 Benidorm Alicante 03500",
    "addr:housenumber":"4",
    "addr:postcode":"03500",
    "addr:street":"Pl Creu",
    "iso:country":"ES",
    "sg:address":"Pl Creu, 4",
    "sg:city":"Benidorm",
    "sg:orig_category":"Asociaciones Y Clubs Deportivos",
    "sg:phone":"+34 965 85 05 65",
    "sg:postcode":"03500",
    "sg:province":"Alicante",
    "wof:name":"Loix Sport S.l.",
    "wof:placetype":"venue"
},
  "geometry": {"coordinates":[-0.129124999,38.5368347168],"type":"Point"}
}