{
  "type": "Feature",
  "properties": {
    "iso:country":"ES",
    "sg:address":"Alam Marques De Casa Domecq, 7",
    "sg:city":"Jerez De La Frontera",
    "sg:orig_category":"Molduras, Junquillos, Listones Y Molduras Perforadas",
    "sg:phone":"+34 956 34 49 00",
    "sg:postcode":"11403",
    "sg:province":"C\u00e1diz",
    "wof:name":"Vivero Roldan Andres",
    "wof:placetype":"venue"
},
  "geometry": {"coordinates":[-6.1407694817,36.6844329834],"type":"Point"}
}