{
  "type": "Feature",
  "properties": {
    "iso:country":"ES",
    "sg:address":"Calle de Garcia Lorca, 1",
    "sg:city":"Pulianas",
    "sg:orig_category":"Cajas De Ahorro",
    "sg:phone":"+34 958 40 62 26",
    "sg:postcode":"18197",
    "sg:province":"Granada",
    "sg:website":"www.lacaixa.es",
    "wof:name":"Caixa D'estalvis I Pensions De Barcelona",
    "wof:placetype":"venue"
},
  "geometry": {"coordinates":[-3.6071050167,37.2225990295],"type":"Point"}
}