{
  "type": "Feature",
  "properties": {
    "iso:country":"ES",
    "sg:address":"Calle de Carrera, S/n",
    "sg:city":"Noves",
    "sg:orig_category":"Asociaciones, Organismos Culturales Y Socioeducativos",
    "sg:phone":"+34 925 77 84 97",
    "sg:postcode":"45519",
    "sg:province":"Toledo",
    "wof:name":"Asociacion Cultural Pe\u00f1a El Porron",
    "wof:placetype":"venue"
},
  "geometry": {"coordinates":[-4.2772226334,40.0494499207],"type":"Point"}
}