{
  "type": "Feature",
  "properties": {
    "iso:country":"ES",
    "sg:address":"Calle de Sevilla, 3",
    "sg:city":"Aduanas",
    "sg:orig_category":"Ropa Para Se\u00d1oras Y Caballeros (al Por Menor)",
    "sg:phone":"+34 965 79 22 37",
    "sg:postcode":"03730",
    "sg:province":"Alicante",
    "wof:name":"Mari Cervera Francisca",
    "wof:placetype":"venue"
},
  "geometry": {"coordinates":[0.1808049977,38.7946548462],"type":"Point"}
}