{
  "type": "Feature",
  "properties": {
    "addr:full":"Carr Sant Cristofol, 9 Castell Islas Baleares 07720",
    "addr:housenumber":"9",
    "addr:postcode":"07720",
    "addr:street":"Carr Sant Cristofol",
    "iso:country":"ES",
    "sg:address":"Carr Sant Cristofol, 9",
    "sg:city":"Castell",
    "sg:orig_category":"Importaci\u00d3n",
    "sg:phone":"+34 971 35 26 84",
    "sg:postcode":"07720",
    "sg:province":"Islas Baleares",
    "wof:name":"Mar Azul C.b.",
    "wof:placetype":"venue"
},
  "geometry": {"coordinates":[4.2850251198,39.8720703125],"type":"Point"}
}