{
  "type": "Feature",
  "properties": {
    "iso:country":"ES",
    "sg:address":"Calle de Marques De Cadiz, 23",
    "sg:city":"Malaga",
    "sg:orig_category":"Tapiceros Y Tapiceros",
    "sg:phone":"+34 952 65 77 00",
    "sg:postcode":"29013",
    "sg:province":"M\u00e1laga",
    "wof:name":"Lago Decoracion Y Reforma S.l.",
    "wof:placetype":"venue"
},
  "geometry": {"coordinates":[-4.4242291451,36.7297401428],"type":"Point"}
}