{
  "type": "Feature",
  "properties": {
    "addr:full":"Calle de Alique, 52 Villarrobledo Albacete 02600",
    "addr:housenumber":"52",
    "addr:postcode":"02600",
    "addr:street":"Calle De Alique",
    "iso:country":"ES",
    "sg:address":"Calle de Alique, 52",
    "sg:city":"Villarrobledo",
    "sg:orig_category":"Ingenier\u00cda, Centros De Estudios (diversos)",
    "sg:phone":"+34 967 14 64 68",
    "sg:postcode":"02600",
    "sg:province":"Albacete",
    "wof:name":"Navarro Clemente Ingenieria S.l.u.",
    "wof:placetype":"venue"
},
  "geometry": {"coordinates":[-2.6061007977,39.2627067566],"type":"Point"}
}