{
  "type": "Feature",
  "properties": {
    "addr:full":"Carrer de Jaume Balmes, 15 Palma Islas Baleares 07005",
    "addr:housenumber":"15",
    "addr:postcode":"07005",
    "addr:street":"Carrer De Jaume Balmes",
    "iso:country":"ES",
    "sg:address":"Carrer de Jaume Balmes, 15",
    "sg:city":"Palma",
    "sg:orig_category":"Caf\u00c9s, Bares, Cervecer\u00cdas",
    "sg:phone":"+34 971 24 18 18",
    "sg:postcode":"07005",
    "sg:province":"Islas Baleares",
    "wof:name":"Bisquerra Pujol Coloma Josefa",
    "wof:placetype":"venue"
},
  "geometry": {"coordinates":[2.6612460613,39.5791511536],"type":"Point"}
}