{
  "type": "Feature",
  "properties": {
    "addr:full":"Avda Los Huetos, 18 Vitoria-gasteiz \u00c1lava 01010",
    "addr:housenumber":"18",
    "addr:postcode":"01010",
    "addr:street":"Avda Los Huetos",
    "iso:country":"ES",
    "sg:address":"Avda Los Huetos, 18",
    "sg:city":"Vitoria-gasteiz",
    "sg:orig_category":"Transportes Por V\u00cdas Navegables",
    "sg:phone":"+34 945 22 29 71",
    "sg:postcode":"01010",
    "sg:province":"\u00c1lava",
    "wof:name":"Morena Zurdo Manuel",
    "wof:placetype":"venue"
},
  "geometry": {"coordinates":[-2.6999499798,42.8539543152],"type":"Point"}
}