{
  "type": "Feature",
  "properties": {
    "iso:country":"ES",
    "sg:address":"Calle de Portal De Legutiano, 4",
    "sg:city":"Vitoria-gasteiz",
    "sg:orig_category":"Alimentaci\u00d3n General (al Por Menor)",
    "sg:phone":"+34 945 28 53 94",
    "sg:postcode":"01002",
    "sg:province":"\u00c1lava",
    "wof:name":"Garcia De Orozco Miriam",
    "wof:placetype":"venue"
},
  "geometry": {"coordinates":[-2.6525239944,42.8486938477],"type":"Point"}
}