{
  "type": "Feature",
  "properties": {
    "addr:full":"Carrer de Miquel Romeu, 84 Hospitalet Llobregat Barcelona 08907",
    "addr:housenumber":"84",
    "addr:postcode":"08907",
    "addr:street":"Carrer De Miquel Romeu",
    "iso:country":"ES",
    "sg:address":"Carrer de Miquel Romeu, 84",
    "sg:city":"Hospitalet Llobregat",
    "sg:orig_category":"Metalurgia",
    "sg:phone":"+34 933 37 18 48",
    "sg:postcode":"08907",
    "sg:province":"Barcelona",
    "wof:name":"Marce Ferre Jaime",
    "wof:placetype":"venue"
},
  "geometry": {"coordinates":[2.1118099689,41.3599395752],"type":"Point"}
}