{
  "type": "Feature",
  "properties": {
    "iso:country":"ES",
    "sg:address":"Carrer de Autovia De Castelldefels, Km. 0016,0",
    "sg:city":"Gava",
    "sg:orig_category":"Tejidos (al Por Menor)",
    "sg:phone":"+34 936 33 18 16",
    "sg:postcode":"08850",
    "sg:province":"Barcelona",
    "wof:name":"Kuppers  Hans",
    "wof:placetype":"venue"
},
  "geometry": {"coordinates":[2.0012850761,41.3040237427],"type":"Point"}
}