{
  "type": "Feature",
  "properties": {
    "iso:country":"ES",
    "sg:address":"Calle de Pilares, 22",
    "sg:city":"Almeria",
    "sg:orig_category":"Venta, Alquiler De Toldos",
    "sg:phone":"+34 950 22 96 97",
    "sg:postcode":"04006",
    "sg:province":"Almer\u00eda",
    "wof:name":"Servicio Integral De Cubiertas S.l.",
    "wof:placetype":"venue"
},
  "geometry": {"coordinates":[-2.443999052,36.8449783325],"type":"Point"}
}