{
  "type": "Feature",
  "properties": {
    "addr:full":"Carrer de Comer\u00c7, 42 Barcelona Barcelona 08003",
    "addr:housenumber":"42",
    "addr:postcode":"08003",
    "addr:street":"Carrer De Comerc\u0327",
    "iso:country":"ES",
    "sg:address":"Carrer de Comer\u00c7, 42",
    "sg:city":"Barcelona",
    "sg:orig_category":"Agencias Y Agentes Comerciales, Representantes",
    "sg:phone":"+34 933 10 32 39",
    "sg:postcode":"08003",
    "sg:province":"Barcelona",
    "wof:name":"Lopez Garcia Fulgencio",
    "wof:placetype":"venue"
},
  "geometry": {"coordinates":[2.1821784973,41.3866233826],"type":"Point"}
}