{
  "type": "Feature",
  "properties": {
    "iso:country":"ES",
    "sg:address":"Calle de Denia, 41",
    "sg:city":"Valencia",
    "sg:orig_category":"Mec\u00c1nico Del Autom\u00d3vil",
    "sg:phone":"+34 963 41 45 33",
    "sg:postcode":"46006",
    "sg:province":"Valencia",
    "wof:name":"Monta\u00f1ana Sales Antonio",
    "wof:placetype":"venue"
},
  "geometry": {"coordinates":[-0.3754634857,39.462852478],"type":"Point"}
}