{
  "type": "Feature",
  "properties": {
    "iso:country":"ES",
    "sg:address":"Fnc. La Toledana, S/n",
    "sg:city":"Pueblo Nuevo Bullaque",
    "sg:orig_category":"Cr\u00cda De Animales",
    "sg:phone":"+34 926 69 71 52",
    "sg:postcode":"13194",
    "sg:province":"Ciudad Real",
    "wof:name":"Dehesa De Las Cabrerizas S.l.",
    "wof:placetype":"venue"
},
  "geometry": {"coordinates":[-4.2586288452,39.2843360901],"type":"Point"}
}