{
  "type": "Feature",
  "properties": {
    "addr:full":"Carr Casa Del Poble, 9 Cabaneta Islas Baleares 07141",
    "addr:housenumber":"9",
    "addr:postcode":"07141",
    "addr:street":"Carr Casa Del Poble;Islas",
    "iso:country":"ES",
    "sg:address":"Carr Casa Del Poble, 9",
    "sg:city":"Cabaneta",
    "sg:orig_category":"Notarios",
    "sg:phone":"+34 971 60 22 85",
    "sg:postcode":"07141",
    "sg:province":"Islas Baleares",
    "wof:name":"Gutierrez Moreno Pedro Luis",
    "wof:placetype":"venue"
},
  "geometry": {"coordinates":[2.741590023,39.6156005859],"type":"Point"}
}