{
  "type": "Feature",
  "properties": {
    "iso:country":"ES",
    "sg:address":"Carr Felix Pizcueta, 2",
    "sg:city":"Quart Poblet",
    "sg:orig_category":"Carnicer\u00cdas, Carnicer\u00cdas",
    "sg:phone":"+34 961 53 31 58",
    "sg:postcode":"46930",
    "sg:province":"Valencia",
    "wof:name":"Ruiz Ros Jose",
    "wof:placetype":"venue"
},
  "geometry": {"coordinates":[-0.4478310049,39.4832687378],"type":"Point"}
}