{
  "type": "Feature",
  "properties": {
    "iso:country":"ES",
    "sg:address":"Carrer de Salut, 42",
    "sg:city":"Sabadell",
    "sg:orig_category":"Obras Y Organismos Sociales",
    "sg:phone":"+34 937 26 46 30",
    "sg:postcode":"08202",
    "sg:province":"Barcelona",
    "wof:name":"Associacio D'atencio Dels Pobres I Marginats Eulalia Garriga",
    "wof:placetype":"venue"
},
  "geometry": {"coordinates":[2.1096947193,41.5504226685],"type":"Point"}
}