{
  "type": "Feature",
  "properties": {
    "addr:full":"Plaz Marques Casa Quijano, 2 Moreda Asturias 33670",
    "addr:housenumber":"2",
    "addr:postcode":"33670",
    "iso:country":"ES",
    "sg:address":"Plaz Marques Casa Quijano, 2",
    "sg:city":"Moreda",
    "sg:orig_category":"M\u00c9dicos: Estomatolog\u00cda",
    "sg:phone":"+34 985 48 04 09",
    "sg:postcode":"33670",
    "sg:province":"Asturias",
    "wof:name":"Fernandez-vigil Garcia Ignacio",
    "wof:placetype":"venue"
},
  "geometry": {"coordinates":[-5.7376289368,43.1678504944],"type":"Point"}
}