{
  "type": "Feature",
  "properties": {
    "iso:country":"ES",
    "sg:address":"Carrer de Doctor Balari, 21",
    "sg:city":"Sabadell",
    "sg:orig_category":"Trabajos De Fotocomposici\u00d3n",
    "sg:phone":"+34 937 11 74 78",
    "sg:postcode":"08203",
    "sg:province":"Barcelona",
    "sg:website":"www.computergraf.net",
    "wof:name":"Sallent Puig Joan",
    "wof:placetype":"venue"
},
  "geometry": {"coordinates":[2.1057600975,41.5295829773],"type":"Point"}
}