{
  "type": "Feature",
  "properties": {
    "addr:full":"Calle de Animas, 2 Valverde Camino Huelva 21600",
    "addr:housenumber":"2",
    "addr:postcode":"21600",
    "addr:street":"Calle De Animas;Camino Huelva",
    "iso:country":"ES",
    "sg:address":"Calle de Animas, 2",
    "sg:city":"Valverde Camino",
    "sg:orig_category":"Cristaler\u00cdas",
    "sg:phone":"+34 959 55 01 69",
    "sg:postcode":"21600",
    "sg:province":"Huelva",
    "wof:name":"Grisval Sdad Civil",
    "wof:placetype":"venue"
},
  "geometry": {"coordinates":[-6.7485847473,37.5753517151],"type":"Point"}
}