{
  "type": "Feature",
  "properties": {
    "iso:country":"ES",
    "sg:address":"Cabrera, 38",
    "sg:city":"Madrid",
    "sg:orig_category":"Universidades",
    "sg:phone":"+34 913 98 74 01",
    "sg:postcode":"28...",
    "sg:province":"Madrid",
    "wof:name":"Universidad Nacional De Educacion A Distancia",
    "wof:placetype":"venue"
},
  "geometry": {"coordinates":[-3.6751608849,40.4422874451],"type":"Point"}
}