{
  "type": "Feature",
  "properties": {
    "addr:full":"Avda Portugal, 77 Talavera Reina Toledo 45600",
    "addr:housenumber":"77",
    "addr:postcode":"45600",
    "addr:street":"Avda Portugal",
    "iso:country":"ES",
    "sg:address":"Avda Portugal, 77",
    "sg:city":"Talavera Reina",
    "sg:orig_category":"Puertas Y Portales",
    "sg:phone":"+34 925 80 20 00",
    "sg:postcode":"45600",
    "sg:province":"Toledo",
    "wof:name":"Hipermadera Talavera S.l.",
    "wof:placetype":"venue"
},
  "geometry": {"coordinates":[-4.848154068,39.9577674866],"type":"Point"}
}