{
  "type": "Feature",
  "properties": {
    "iso:country":"ES",
    "sg:address":"Puerto Rey, S/n",
    "sg:city":"Garrucha",
    "sg:orig_category":"Asociaciones Y Clubs Deportivos",
    "sg:phone":"+34 950 13 34 56",
    "sg:postcode":"04630",
    "sg:province":"Almer\u00eda",
    "wof:name":"Charbonnel  Patrick",
    "wof:placetype":"venue"
},
  "geometry": {"coordinates":[-1.8204389811,37.188293457],"type":"Point"}
}