{
  "type": "Feature",
  "properties": {
    "iso:country":"ES",
    "sg:address":"Carrer de Londres, 63",
    "sg:city":"Barcelona",
    "sg:orig_category":"Carnicer\u00cdas, Carnicer\u00cdas",
    "sg:phone":"+34 934 19 40 03",
    "sg:postcode":"08036",
    "sg:province":"Barcelona",
    "wof:name":"Gracia Monzon Felipe",
    "wof:placetype":"venue"
},
  "geometry": {"coordinates":[2.1484720707,41.3919487],"type":"Point"}
}