{
  "type": "Feature",
  "properties": {
    "addr:full":"Calle de Sierra Toledana, 47 Madrid Madrid 28038",
    "addr:housenumber":"47",
    "addr:postcode":"madrid;28038",
    "addr:street":"Calle De Sierra Toledana",
    "iso:country":"ES",
    "sg:address":"Calle de Sierra Toledana, 47",
    "sg:city":"Madrid",
    "sg:orig_category":"Artes Gr\u00c1ficas, Artes Pl\u00c1sticas: Material Y Suministros (al Por Menor)",
    "sg:phone":"+34 914 34 90 38",
    "sg:postcode":"28038",
    "sg:province":"Madrid",
    "sg:website":"www.boicok.com",
    "wof:name":"Lorenzo Ares Manuel",
    "wof:placetype":"venue"
},
  "geometry": {"coordinates":[-3.659717083,40.4039039612],"type":"Point"}
}