{
  "type": "Feature",
  "properties": {
    "iso:country":"ES",
    "sg:address":"Calle de Torres Quevedo, 59",
    "sg:city":"Sevilla",
    "sg:orig_category":"Supermercados Y Hipermercados",
    "sg:phone":"+34 954 40 31 39",
    "sg:postcode":"41016",
    "sg:province":"Sevilla",
    "wof:name":"Robles Lopez Adolfo",
    "wof:placetype":"venue"
},
  "geometry": {"coordinates":[-5.9068632126,37.3845672607],"type":"Point"}
}