{
  "type": "Feature",
  "properties": {
    "iso:country":"ES",
    "sg:address":"Poligono Industrial, S/n",
    "sg:city":"Pol. Ind. Onzonilla",
    "sg:orig_category":"Delegados, Agentes De Tr\u00c1nsito, Auxiliares De Transporte Internacional",
    "sg:phone":"+34 987 21 48 09",
    "sg:postcode":"24231",
    "sg:province":"Le\u00f3n",
    "wof:name":"Transleica S.l.",
    "wof:placetype":"venue"
},
  "geometry": {"coordinates":[-5.5844950676,42.5004310608],"type":"Point"}
}