{
  "type": "Feature",
  "properties": {
    "addr:full":"Av. Bayona, 24 Iru\u00f1a Navarra 31011",
    "addr:housenumber":"24",
    "addr:postcode":"31011",
    "addr:street":"Av. Bayona",
    "iso:country":"ES",
    "sg:address":"Av. Bayona, 24",
    "sg:city":"Iru\u00f1a",
    "sg:orig_category":"Farmacias",
    "sg:phone":"+34 948 19 72 06",
    "sg:postcode":"31011",
    "sg:province":"Navarra",
    "wof:name":"Farmacia Cristina Cabiro-maria Pilar Echeverria C.b.",
    "wof:placetype":"venue"
},
  "geometry": {"coordinates":[-1.6580300331,42.8148956299],"type":"Point"}
}