{
  "type": "Feature",
  "properties": {
    "iso:country":"ES",
    "sg:address":"Calle de San Gerardo, 16",
    "sg:city":"Salamanca",
    "sg:orig_category":"Ingenier\u00cda, Centros De Estudios (diversos)",
    "sg:phone":"+34 923 26 69 80",
    "sg:postcode":"37007",
    "sg:province":"Salamanca",
    "wof:name":"Sanchez Hernandez Sara",
    "wof:placetype":"venue"
},
  "geometry": {"coordinates":[-5.6713271141,40.9628829956],"type":"Point"}
}