{
  "type": "Feature",
  "properties": {
    "addr:full":"Calle de Florida (la), 2 Labastida \u00c1lava 01330",
    "addr:housenumber":"2",
    "addr:postcode":"01330",
    "addr:street":"Calle De Florida La;A\u0301Lava",
    "iso:country":"ES",
    "sg:address":"Calle de Florida (la), 2",
    "sg:city":"Labastida",
    "sg:orig_category":"Electrodom\u00c9sticos (al Por Menor)",
    "sg:phone":"+34 945 33 13 53",
    "sg:postcode":"01330",
    "sg:province":"\u00c1lava",
    "wof:name":"Petralanda Echevarria Jose Luis",
    "wof:placetype":"venue"
},
  "geometry": {"coordinates":[-2.7941908836,42.5895309448],"type":"Point"}
}