{
  "type": "Feature",
  "properties": {
    "addr:full":"Calle de Puentelarra, 5 Madrid Madrid 28031",
    "addr:housenumber":"5",
    "addr:postcode":"28031",
    "addr:street":"Calle De Puentelarra",
    "iso:country":"ES",
    "sg:address":"Calle de Puentelarra, 5",
    "sg:city":"Madrid",
    "sg:orig_category":"Doctores En Medicina",
    "sg:phone":"+34 913 31 32 52",
    "sg:postcode":"28031",
    "sg:province":"Madrid",
    "wof:name":"Serrano Diez Jose Luis",
    "wof:placetype":"venue"
},
  "geometry": {"coordinates":[-3.6086730957,40.3826522827],"type":"Point"}
}