{
  "type": "Feature",
  "properties": {
    "addr:full":"Calle de Anabel Segura (de), 1 Alcobendas Madrid 28100",
    "addr:postcode":"28100",
    "addr:street":"Calle De Anabel",
    "iso:country":"ES",
    "sg:address":"Calle de Anabel Segura (de), 1",
    "sg:city":"Alcobendas",
    "sg:orig_category":"Electromec\u00c1nica",
    "sg:phone":"+34 914 84 01 59",
    "sg:postcode":"28100",
    "sg:province":"Madrid",
    "wof:name":"Alcatel Espa\u00f1a S.a.",
    "wof:placetype":"venue"
},
  "geometry": {"coordinates":[-3.6266634464,40.5340919495],"type":"Point"}
}