{
  "type": "Feature",
  "properties": {
    "iso:country":"ES",
    "sg:address":"Pl Brisa (de La), 11",
    "sg:city":"Mataro",
    "sg:orig_category":"Asociaciones, Organismos Culturales Y Socioeducativos",
    "sg:phone":"+34 937 90 32 28",
    "sg:postcode":"08301",
    "sg:province":"Barcelona",
    "wof:name":"Penya Esplanada",
    "wof:placetype":"venue"
},
  "geometry": {"coordinates":[2.4457581043,41.5448188782],"type":"Point"}
}