{
  "type": "Feature",
  "properties": {
    "addr:full":"Pl Eloi Mestre, 1 Ampolla Tarragona 43895",
    "addr:housenumber":"1",
    "addr:postcode":"43895",
    "addr:street":"Pl Eloi Mestre",
    "iso:country":"ES",
    "sg:address":"Pl Eloi Mestre, 1",
    "sg:city":"Ampolla",
    "sg:orig_category":"Molduras, Junquillos, Listones Y Molduras Perforadas",
    "sg:phone":"+34 977 46 00 07",
    "sg:postcode":"43895",
    "sg:province":"Tarragona",
    "wof:name":"Mestre Usach Maria Cristina",
    "wof:placetype":"venue"
},
  "geometry": {"coordinates":[0.7071049809,40.8109703064],"type":"Point"}
}