{
  "type": "Feature",
  "properties": {
    "iso:country":"ES",
    "sg:address":"Calle de Condes De Aragon, 7",
    "sg:city":"Zaragoza",
    "sg:orig_category":"Arquitectos",
    "sg:phone":"+34 976 55 07 35",
    "sg:postcode":"50009",
    "sg:province":"Zaragoza",
    "sg:website":"www.inasic.es",
    "wof:name":"Inasic S.l.",
    "wof:placetype":"venue"
},
  "geometry": {"coordinates":[-0.9051849842,41.6393547058],"type":"Point"}
}