{
  "type": "Feature",
  "properties": {
    "addr:full":"Calle de Ciguela, 35 Palma Rio C\u00f3rdoba 14700",
    "addr:housenumber":"35",
    "addr:postcode":"14700",
    "addr:street":"Calle De Ciguela;Rio Co\u0301Rdoba",
    "iso:country":"ES",
    "sg:address":"Calle de Ciguela, 35",
    "sg:city":"Palma Rio",
    "sg:orig_category":"Art\u00cdculos Funerarios (al Por Menor)",
    "sg:phone":"+34 957 64 46 68",
    "sg:postcode":"14700",
    "sg:province":"C\u00f3rdoba",
    "wof:name":"Montero Guzman Maria De Los Reyes",
    "wof:placetype":"venue"
},
  "geometry": {"coordinates":[-5.2818613052,37.7005386353],"type":"Point"}
}