{
  "type": "Feature",
  "properties": {
    "addr:full":"Carr Santa Eugenia, 96 Girona Girona 17005",
    "addr:housenumber":"96",
    "addr:postcode":"17005",
    "addr:street":"Carr Santa Eugenia",
    "iso:country":"ES",
    "sg:address":"Carr Santa Eugenia, 96",
    "sg:city":"Girona",
    "sg:orig_category":"Asesor\u00cda Sobre Comunicaci\u00d3n De Empresas",
    "sg:phone":"+34 972 40 24 62",
    "sg:postcode":"17005",
    "sg:province":"Girona",
    "wof:name":"Servicios Profesionales Integrados Serproint S.a.",
    "wof:placetype":"venue"
},
  "geometry": {"coordinates":[2.8116669655,41.9794921875],"type":"Point"}
}