{
  "type": "Feature",
  "properties": {
    "addr:full":"Calle de Hermanos Jimenez, 15 Porzuna Ciudad Real 13120",
    "addr:housenumber":"15",
    "addr:postcode":"13120",
    "addr:street":"Calle De Hermanos Jimenez",
    "iso:country":"ES",
    "sg:address":"Calle de Hermanos Jimenez, 15",
    "sg:city":"Porzuna",
    "sg:orig_category":"Autob\u00das (explotaci\u00d3n Y Servicios De)",
    "sg:phone":"+34 926 78 00 48",
    "sg:postcode":"13120",
    "sg:province":"Ciudad Real",
    "wof:name":"Sanchez Illan Hilario",
    "wof:placetype":"venue"
},
  "geometry": {"coordinates":[-4.1556887627,39.1494216919],"type":"Point"}
}