{
  "type": "Feature",
  "properties": {
    "iso:country":"ES",
    "sg:address":"Plaz Alta, 14",
    "sg:city":"Mollina",
    "sg:orig_category":"Comercio Y Bancos",
    "sg:phone":"+34 952 74 12 70",
    "sg:postcode":"29532",
    "sg:province":"M\u00e1laga",
    "wof:name":"Molina Garcia Clemente",
    "wof:placetype":"venue"
},
  "geometry": {"coordinates":[-4.6613688469,37.1246490479],"type":"Point"}
}