{
  "type": "Feature",
  "properties": {
    "addr:full":"Calle de Ramon Celma Bernal, 2 Zaragoza Zaragoza 50003",
    "addr:housenumber":"2",
    "addr:postcode":"50003",
    "addr:street":"Calle De Ramon Celma Bernal",
    "iso:country":"ES",
    "sg:address":"Calle de Ramon Celma Bernal, 2",
    "sg:city":"Zaragoza",
    "sg:orig_category":"Peluquer\u00cdas, Peluquer\u00cda Mixta",
    "sg:phone":"+34 976 44 60 36",
    "sg:postcode":"50003",
    "sg:province":"Zaragoza",
    "wof:name":"Salondi S.l.",
    "wof:placetype":"venue"
},
  "geometry": {"coordinates":[-0.8893690109,41.6583633423],"type":"Point"}
}