{
  "type": "Feature",
  "properties": {
    "iso:country":"ES",
    "sg:address":"C/ Maria Benlliure, 6",
    "sg:city":"Elche",
    "sg:orig_category":"Arquitectos",
    "sg:phone":"+34 965 44 87 94",
    "sg:postcode":"03201",
    "sg:province":"Alicante",
    "wof:name":"Guillen Domarco Jose",
    "wof:placetype":"venue"
},
  "geometry": {"coordinates":[-0.7036030293,38.2630653381],"type":"Point"}
}