{
  "type": "Feature",
  "properties": {
    "addr:full":"Calle de Ribera (la), 33 S. Adrian Navarra 31570",
    "addr:housenumber":"33",
    "addr:postcode":"31570",
    "addr:street":"Calle De Ribera La;S. Adrian Navarra",
    "iso:country":"ES",
    "sg:address":"Calle de Ribera (la), 33",
    "sg:city":"S. Adrian",
    "sg:orig_category":"Conservas De Legumbres (fabricaci\u00d3n, Al Por Mayor)",
    "sg:phone":"+34 948 67 20 21",
    "sg:postcode":"31570",
    "sg:province":"Navarra",
    "sg:website":"www.conservasjae.com",
    "wof:name":"Juan Ayensa E Hijos S.l.",
    "wof:placetype":"venue"
},
  "geometry": {"coordinates":[-1.9319535494,42.3357391357],"type":"Point"}
}