{
  "type": "Feature",
  "properties": {
    "addr:full":"Calle de Torriano, 17 Le\u00f3n Le\u00f3n 24004",
    "addr:housenumber":"17",
    "addr:postcode":"24004",
    "addr:street":"Calle De Torriano;Leo\u0301N",
    "iso:country":"ES",
    "sg:address":"Calle de Torriano, 17",
    "sg:city":"Le\u00f3n",
    "sg:orig_category":"Peluqueros: De Se\u00d1oras",
    "sg:phone":"+34 987 20 32 63",
    "sg:postcode":"24004",
    "sg:province":"Le\u00f3n",
    "wof:name":"Llamazares Llamazares Rosa",
    "wof:placetype":"venue"
},
  "geometry": {"coordinates":[-5.5741939545,42.5924873352],"type":"Point"}
}