{
  "type": "Feature",
  "properties": {
    "addr:full":"San Francisco, 16 Alhaurin Torre M\u00e1laga 29130",
    "addr:housenumber":"16",
    "addr:postcode":"29130",
    "addr:street":"San Francisco",
    "iso:country":"ES",
    "sg:address":"San Francisco, 16",
    "sg:city":"Alhaurin Torre",
    "sg:orig_category":"Supermercados Y Hipermercados",
    "sg:phone":"+34 952 96 37 32",
    "sg:postcode":"29130",
    "sg:province":"M\u00e1laga",
    "sg:website":"www.aldi.es",
    "wof:name":"Aldi Dos Hermanas Supermercados S.l.",
    "wof:placetype":"venue"
},
  "geometry": {"coordinates":[-4.5482783318,36.6583518982],"type":"Point"}
}