{
  "type": "Feature",
  "properties": {
    "addr:full":"Carrer de Aribau, 12 Barcelona Barcelona 08011",
    "addr:housenumber":"12",
    "addr:postcode":"08011",
    "addr:street":"Carrer De Aribau",
    "iso:country":"ES",
    "sg:address":"Carrer de Aribau, 12",
    "sg:city":"Barcelona",
    "sg:orig_category":"Laboratorios Y Trabajos De Fotograf\u00cda, V\u00cddeo Y Cine",
    "sg:phone":"+34 933 01 05 34",
    "sg:postcode":"08011",
    "sg:province":"Barcelona",
    "wof:name":"Valles Diaz Mario",
    "wof:placetype":"venue"
},
  "geometry": {"coordinates":[2.1624588966,41.386264801],"type":"Point"}
}