{
  "type": "Feature",
  "properties": {
    "iso:country":"ES",
    "sg:address":"Avda Ramon Y Cajal, 7",
    "sg:city":"Olivenza",
    "sg:orig_category":"Caf\u00c9s, Bares, Cervecer\u00cdas",
    "sg:phone":"+34 924 49 16 98",
    "sg:postcode":"06100",
    "sg:province":"Badajoz",
    "wof:name":"Tecnol C.b.",
    "wof:placetype":"venue"
},
  "geometry": {"coordinates":[-7.0980839729,38.6843605042],"type":"Point"}
}