{
  "type": "Feature",
  "properties": {
    "addr:full":"Carr Convent, 7 Gandia Valencia 46700",
    "addr:housenumber":"7",
    "addr:postcode":"46700",
    "addr:street":"Carr Convent;Valencia",
    "iso:country":"ES",
    "sg:address":"Carr Convent, 7",
    "sg:city":"Gandia",
    "sg:orig_category":"Alquiler De V\u00cddeo",
    "sg:phone":"+34 962 86 52 24",
    "sg:postcode":"46700",
    "sg:province":"Valencia",
    "wof:name":"24 Horas Pops S.l",
    "wof:placetype":"venue"
},
  "geometry": {"coordinates":[-0.190854,38.960064],"type":"Point"}
}