{
  "type": "Feature",
  "properties": {
    "addr:full":"Calle de Coronel Bens, 1 Arrecife Las Palmas 35500",
    "addr:housenumber":"1",
    "addr:postcode":"35500",
    "addr:street":"Calle De Coronel Bens",
    "iso:country":"ES",
    "sg:address":"Calle de Coronel Bens, 1",
    "sg:city":"Arrecife",
    "sg:orig_category":"Arquitectos",
    "sg:phone":"+34 928 81 66 59",
    "sg:postcode":"35500",
    "sg:province":"Las Palmas",
    "wof:name":"Sanchez Martin Victor Alberto",
    "wof:placetype":"venue"
},
  "geometry": {"coordinates":[-13.5522193909,28.9580135345],"type":"Point"}
}