{
  "type": "Feature",
  "properties": {
    "addr:full":"Calle de Real (del), 19 Pinto Madrid 28320",
    "addr:housenumber":"19",
    "addr:postcode":"28320",
    "addr:street":"Calle De Real Del",
    "iso:country":"ES",
    "sg:address":"Calle de Real (del), 19",
    "sg:city":"Pinto",
    "sg:orig_category":"Caf\u00c9s, Bares, Cervecer\u00cdas",
    "sg:phone":"+34 916 92 59 76",
    "sg:postcode":"28320",
    "sg:province":"Madrid",
    "wof:name":"El Mar De Arena Cafe Dakar S.l.",
    "wof:placetype":"venue"
},
  "geometry": {"coordinates":[-3.700740099,40.2420578003],"type":"Point"}
}