{
  "type": "Feature",
  "properties": {
    "iso:country":"ES",
    "sg:address":"Carrer de Llevant, 9",
    "sg:city":"Corro D'avall",
    "sg:orig_category":"Reparaciones Y Remolcado De Veh\u00cdculos",
    "sg:phone":"+34 938 40 49 41",
    "sg:postcode":"08520",
    "sg:province":"Barcelona",
    "wof:name":"Gruas Saul Torres S.l.",
    "wof:placetype":"venue"
},
  "geometry": {"coordinates":[2.2963292599,41.6282539368],"type":"Point"}
}