{
  "type": "Feature",
  "properties": {
    "iso:country":"ES",
    "sg:address":"Calle de Poeta Antonino Chocomeli, 6",
    "sg:city":"Valencia",
    "sg:orig_category":"M\u00c9dicos: Estomatolog\u00cda",
    "sg:phone":"+34 963 48 78 71",
    "sg:postcode":"46015",
    "sg:province":"Valencia",
    "wof:name":"Millet Lopez Juan",
    "wof:placetype":"venue"
},
  "geometry": {"coordinates":[-0.3975969851,39.478767395],"type":"Point"}
}