{
  "type": "Feature",
  "properties": {
    "iso:country":"ES",
    "sg:address":"Calle de Fuente Del Tiro, 3",
    "sg:city":"Madrid",
    "sg:orig_category":"Inmobiliaria (agencias)",
    "sg:phone":"+34 917 10 78 16",
    "sg:postcode":"28024",
    "sg:province":"Madrid",
    "wof:name":"Patrimonios Inmuebles Gespain S.l.",
    "wof:placetype":"venue"
},
  "geometry": {"coordinates":[-3.7806224823,40.3834724426],"type":"Point"}
}