{
  "type": "Feature",
  "properties": {
    "iso:country":"ES",
    "sg:address":"Calle de Santa Maria, 11",
    "sg:city":"Jerez De La Frontera",
    "sg:orig_category":"Fabricaci\u00d3n De Productos Textiles Sin Tejer",
    "sg:phone":"+34 956 33 04 47",
    "sg:postcode":"11402",
    "sg:province":"C\u00e1diz",
    "wof:name":"Rosado Pichaco Manuel",
    "wof:placetype":"venue"
},
  "geometry": {"coordinates":[-6.1360440254,36.6831817627],"type":"Point"}
}