{
  "type": "Feature",
  "properties": {
    "addr:full":"Calle de Fresadora (de La), 14 Partija-santa Monica Madrid 28529",
    "addr:housenumber":"14",
    "addr:postcode":"28529",
    "addr:street":"Calle De Fresadora De La",
    "iso:country":"ES",
    "sg:address":"Calle de Fresadora (de La), 14",
    "sg:city":"Partija-santa Monica",
    "sg:orig_category":"Empresas De Carpinter\u00cda De Madera",
    "sg:phone":"+34 916 66 54 77",
    "sg:postcode":"28529",
    "sg:province":"Madrid",
    "sg:website":"www.cayba.es",
    "wof:name":"Manuel Carrillo Sanchez Y Otro Cdad.",
    "wof:placetype":"venue"
},
  "geometry": {"coordinates":[-3.5102670193,40.314289093],"type":"Point"}
}