{
  "type": "Feature",
  "properties": {
    "addr:full":"Calle de Allende Manuel, 11 Bilbao Vizcaya 48010",
    "addr:housenumber":"11",
    "addr:postcode":"48010",
    "addr:street":"Calle De Allende Manuel",
    "iso:country":"ES",
    "sg:address":"Calle de Allende Manuel, 11",
    "sg:city":"Bilbao",
    "sg:orig_category":"Mercer\u00cda, Lencer\u00cda (al Por Menor)",
    "sg:phone":"+34 944 44 18 45",
    "sg:postcode":"48010",
    "sg:province":"Vizcaya",
    "wof:name":"Fernandez Vizkarguenaga Argi\u00f1e",
    "wof:placetype":"venue"
},
  "geometry": {"coordinates":[-2.9419369698,43.2599143982],"type":"Point"}
}