{
  "type": "Feature",
  "properties": {
    "addr:full":"Calle de Garcia Morato, 13 Cox Alicante 03350",
    "addr:housenumber":"13",
    "addr:postcode":"03350",
    "addr:street":"Calle De Garcia Morato",
    "iso:country":"ES",
    "sg:address":"Calle de Garcia Morato, 13",
    "sg:city":"Cox",
    "sg:orig_category":"Electricidad: Instaladores",
    "sg:phone":"+34 965 36 07 27",
    "sg:postcode":"03350",
    "sg:province":"Alicante",
    "wof:name":"Manresa Quirante Miguel",
    "wof:placetype":"venue"
},
  "geometry": {"coordinates":[-0.8881210089,38.1402778625],"type":"Point"}
}