{
  "type": "Feature",
  "properties": {
    "addr:full":"Carrer de Francesc Macia, 27 Cunit Tarragona 43881",
    "addr:housenumber":"27",
    "addr:postcode":"43881",
    "addr:street":"Carrer De Francesc Macia",
    "iso:country":"ES",
    "sg:address":"Carrer de Francesc Macia, 27",
    "sg:city":"Cunit",
    "sg:orig_category":"Flores Y Plantas Naturales (al Por Mayor)",
    "sg:phone":"+34 977 67 50 80",
    "sg:postcode":"43881",
    "sg:province":"Tarragona",
    "wof:name":"Martinez Garcia Antonia",
    "wof:placetype":"venue"
},
  "geometry": {"coordinates":[1.6351900101,41.1969146729],"type":"Point"}
}