{
  "type": "Feature",
  "properties": {
    "addr:full":"Ptge Pau (la), 1 S. Joan Despi Barcelona 08970",
    "addr:postcode":"08970",
    "addr:street":"Ptge Pau La 1 S. Joan Despi",
    "iso:country":"ES",
    "sg:address":"Ptge Pau (la), 1",
    "sg:city":"S. Joan Despi",
    "sg:orig_category":"Empresas De Limpieza",
    "sg:phone":"+34 934 77 03 59",
    "sg:postcode":"08970",
    "sg:province":"Barcelona",
    "wof:name":"Senesant 2000 S.l.",
    "wof:placetype":"venue"
},
  "geometry": {"coordinates":[2.057090044,41.3629188538],"type":"Point"}
}