{
  "type": "Feature",
  "properties": {
    "iso:country":"ES",
    "sg:address":"Carr Batlloria, 17",
    "sg:city":"Badalona",
    "sg:orig_category":"Estilistas Y Estudios De Estilo De Corte Y Confecci\u00d3n",
    "sg:phone":"+34 934 60 70 44",
    "sg:postcode":"08912",
    "sg:province":"Barcelona",
    "wof:name":"Well Good S. L.",
    "wof:placetype":"venue"
},
  "geometry": {"coordinates":[2.2383139133,41.4526786804],"type":"Point"}
}