{
  "type": "Feature",
  "properties": {
    "iso:country":"ES",
    "sg:address":"Ctra Alicante-valencia, Km. 0204,0",
    "sg:city":"Verger",
    "sg:orig_category":"Aparcamientos (infraestructuras, Accesorios)",
    "sg:phone":"+34 965 75 03 01",
    "sg:postcode":"03770",
    "sg:province":"Alicante",
    "sg:website":"www.parkingsantaana.com",
    "wof:name":"Parking Santa Ana S.l.",
    "wof:placetype":"venue"
},
  "geometry": {"coordinates":[0.0022150001,38.8531761169],"type":"Point"}
}