{
  "type": "Feature",
  "properties": {
    "iso:country":"ES",
    "sg:address":"Calle de Ramon Y Cajal, 8",
    "sg:city":"Agost",
    "sg:orig_category":"Delegados, Agentes De Tr\u00c1nsito, Auxiliares De Transporte Internacional",
    "sg:phone":"+34 965 69 21 78",
    "sg:postcode":"03698",
    "sg:province":"Alicante",
    "wof:name":"Arroyo Campa\u00f1a Juan",
    "wof:placetype":"venue"
},
  "geometry": {"coordinates":[-0.6373727918,38.4373893738],"type":"Point"}
}