{
  "type": "Feature",
  "properties": {
    "addr:full":"Carrer de Francesc Moragas, 74 Hospitalet Llobregat Barcelona 08907",
    "addr:housenumber":"74",
    "addr:postcode":"08907",
    "addr:street":"Carrer De Francesc Moragas",
    "iso:country":"ES",
    "sg:address":"Carrer de Francesc Moragas, 74",
    "sg:city":"Hospitalet Llobregat",
    "sg:classifiers":[
        {
            "category":"Communications",
            "subcategory":"Radio Station",
            "type":"Services"
        }
    ],
    "sg:phone":"+34 933 38 83 09",
    "sg:postcode":"08907",
    "sg:province":"Barcelona",
    "sg:tags":[
        "de",
        "electr\u00d3nica",
        "material",
        "fabricaci\u00d3n",
        "y",
        "profesional"
    ],
    "wof:name":"Blausonic S.l.",
    "wof:placetype":"venue"
},
  "geometry": {"coordinates":[2.0990331173,41.3552207947],"type":"Point"}
}