{
  "type": "Feature",
  "properties": {
    "addr:full":"Calle de Sor Maria Fe, S/n Santa Olalla Del Cala Huelva 21260",
    "addr:housenumber":"s / n",
    "addr:postcode":"21260",
    "addr:street":"Calle De Sor Maria Fe",
    "iso:country":"ES",
    "sg:address":"Calle de Sor Maria Fe, S/n",
    "sg:city":"Santa Olalla Del Cala",
    "sg:orig_category":"Reposter\u00cdas",
    "sg:phone":"+34 959 19 00 78",
    "sg:postcode":"21260",
    "sg:province":"Huelva",
    "wof:name":"Torrado Fernandez Eugenia",
    "wof:placetype":"venue"
},
  "geometry": {"coordinates":[-6.2242541313,37.9065437317],"type":"Point"}
}