{
  "type": "Feature",
  "properties": {
    "iso:country":"ES",
    "sg:address":"Avda Coronel Baeza, 23",
    "sg:city":"Toledo",
    "sg:orig_category":"Fotocopias, Reprograf\u00cda",
    "sg:phone":"+34 925 25 31 52",
    "sg:postcode":"45004",
    "sg:province":"Toledo",
    "sg:website":"www.copaer.com",
    "wof:name":"Copaer S.l.",
    "wof:placetype":"venue"
},
  "geometry": {"coordinates":[-4.0316610336,39.8686599731],"type":"Point"}
}