{
  "type": "Feature",
  "properties": {
    "addr:full":"Rua Basqui\u00d1os (dos), 7 Santiago De Compostela La Coru\u00f1a 15704",
    "addr:housenumber":"7",
    "addr:postcode":"15704",
    "addr:street":"Rua Basquin\u0303Os Dos;Corun\u0303A",
    "iso:country":"ES",
    "sg:address":"Rua Basqui\u00d1os (dos), 7",
    "sg:city":"Santiago De Compostela",
    "sg:orig_category":"Molduras, Junquillos, Listones Y Molduras Perforadas",
    "sg:phone":"+34 981 58 48 38",
    "sg:postcode":"15704",
    "sg:province":"La Coru\u00f1a",
    "wof:name":"Guerra Parente Agustin",
    "wof:placetype":"venue"
},
  "geometry": {"coordinates":[-8.5403118134,42.8864593506],"type":"Point"}
}