{
  "type": "Feature",
  "properties": {
    "addr:full":"Avda Miguel De Cervantes, 1 Ecija Sevilla 41400",
    "addr:housenumber":"1",
    "addr:postcode":"41400",
    "addr:street":"Avda Miguel De Cervantes",
    "iso:country":"ES",
    "sg:address":"Avda Miguel De Cervantes, 1",
    "sg:city":"Ecija",
    "sg:orig_category":"Cajas De Ahorro",
    "sg:phone":"+34 954 83 22 09",
    "sg:postcode":"41400",
    "sg:province":"Sevilla",
    "sg:website":"www.unicaja.es",
    "wof:name":"Unicaja",
    "wof:placetype":"venue"
},
  "geometry": {"coordinates":[-5.07918787,37.5408058167],"type":"Point"}
}