{
  "type": "Feature",
  "properties": {
    "addr:full":"Africa(la Serreta), 7 Molina Segura Murcia 30500",
    "addr:housenumber":"7",
    "addr:postcode":"30500",
    "addr:street":"Serreta",
    "iso:country":"ES",
    "sg:address":"Africa(la Serreta), 7",
    "sg:city":"Molina Segura",
    "sg:orig_category":"Centros Empresariales",
    "sg:phone":"+34 902 11 30 50",
    "sg:postcode":"30500",
    "sg:province":"Murcia",
    "wof:name":"Grupo Inter-gesaco S.a.",
    "wof:placetype":"venue"
},
  "geometry": {"coordinates":[-1.2308759689,38.0779724121],"type":"Point"}
}