{
  "type": "Feature",
  "properties": {
    "iso:country":"ES",
    "sg:address":"Avda Catorce, 18",
    "sg:city":"Bolbaite",
    "sg:orig_category":"Bazares, Art\u00cdculos De Limpieza Y De Cocina (al Por Menor)",
    "sg:phone":"+34 962 22 33 74",
    "sg:postcode":"46822",
    "sg:province":"Valencia",
    "wof:name":"Gonzalez Garcia Placido",
    "wof:placetype":"venue"
},
  "geometry": {"coordinates":[-0.6749860048,39.0570144653],"type":"Point"}
}