{
  "type": "Feature",
  "properties": {
    "iso:country":"ES",
    "sg:address":"Calle de Frailes, 13",
    "sg:city":"Granada",
    "sg:orig_category":"Tapicer\u00cdas",
    "sg:phone":"+34 958 26 21 11",
    "sg:postcode":"18005",
    "sg:province":"Granada",
    "wof:name":"Vilchez Palma Francisco",
    "wof:placetype":"venue"
},
  "geometry": {"coordinates":[-3.6010770798,37.1721687317],"type":"Point"}
}