{
  "type": "Feature",
  "properties": {
    "addr:full":"N Poligono, S/n Soria Soria 42005",
    "addr:postcode":"42005",
    "addr:street":"Poligono S / N",
    "iso:country":"ES",
    "sg:address":"N Poligono, S/n",
    "sg:city":"Soria",
    "sg:orig_category":"Muebles, Minoristas",
    "sg:phone":"+34 975 22 26 41",
    "sg:postcode":"42005",
    "sg:province":"Soria",
    "wof:name":"Garcia Perez Teodoro",
    "wof:placetype":"venue"
},
  "geometry": {"coordinates":[-2.4798560143,41.9514465332],"type":"Point"}
}