{
  "type": "Feature",
  "properties": {
    "iso:country":"ES",
    "sg:address":"Cra. Roda, 30",
    "sg:city":"Manlleu",
    "sg:orig_category":"Quincaller\u00cda (al Por Menor)",
    "sg:phone":"+34 938 51 20 71",
    "sg:postcode":"08560",
    "sg:province":"Barcelona",
    "wof:name":"Lafaktoria.net S.c.p.",
    "wof:placetype":"venue"
},
  "geometry": {"coordinates":[2.2829101086,42.0033149719],"type":"Point"}
}