{
  "type": "Feature",
  "properties": {
    "addr:full":"Calle de Pablo Picasso, 3 Purchena Almer\u00eda 04870",
    "addr:housenumber":"3",
    "addr:postcode":"04870",
    "addr:street":"Calle De Pablo Picasso;Almeri\u0301A",
    "iso:country":"ES",
    "sg:address":"Calle de Pablo Picasso, 3",
    "sg:city":"Purchena",
    "sg:orig_category":"Pr\u00c9stamos Personales E Hipotecarios",
    "sg:phone":"+34 950 42 30 35",
    "sg:postcode":"04870",
    "sg:province":"Almer\u00eda",
    "wof:name":"Registro De La Propiedad",
    "wof:placetype":"venue"
},
  "geometry": {"coordinates":[-2.3591089249,37.3469581604],"type":"Point"}
}