{
  "type": "Feature",
  "properties": {
    "addr:full":"Calle de Portugal, 7 Albacete Albacete 02002",
    "addr:housenumber":"7",
    "addr:postcode":"02002",
    "addr:street":"Calle De Portugal",
    "iso:country":"ES",
    "sg:address":"Calle de Portugal, 7",
    "sg:city":"Albacete",
    "sg:orig_category":"Mec\u00c1nico Del Autom\u00d3vil",
    "sg:phone":"+34 967 50 98 48",
    "sg:postcode":"02002",
    "sg:province":"Albacete",
    "wof:name":"Martinez Sotos Juan Angel",
    "wof:placetype":"venue"
},
  "geometry": {"coordinates":[-1.8565629721,38.9833106995],"type":"Point"}
}