{
  "type": "Feature",
  "properties": {
    "addr:full":"Calle de Pintor Zurbaran, 12 Pechina Almer\u00eda 04250",
    "addr:housenumber":"12",
    "addr:postcode":"04250",
    "addr:street":"Calle De Pintor Zurbaran;Almeri\u0301A",
    "iso:country":"ES",
    "sg:address":"Calle de Pintor Zurbaran, 12",
    "sg:city":"Pechina",
    "sg:orig_category":"Peluquer\u00cdas, Peluquer\u00cda Mixta",
    "sg:phone":"+34 950 31 71 23",
    "sg:postcode":"04250",
    "sg:province":"Almer\u00eda",
    "wof:name":"Hernandez Rodriguez Manuela",
    "wof:placetype":"venue"
},
  "geometry": {"coordinates":[-2.4380021095,36.9183769226],"type":"Point"}
}