{
  "type": "Feature",
  "properties": {
    "addr:full":"Psaj Jacaranda, 52 Jerez De La Frontera C\u00e1diz 11405",
    "addr:postcode":"11405",
    "addr:street":"Jacaranda 52",
    "iso:country":"ES",
    "sg:address":"Psaj Jacaranda, 52",
    "sg:city":"Jerez De La Frontera",
    "sg:orig_category":"Laboratorios Farmac\u00c9uticos",
    "sg:phone":"+34 956 18 46 93",
    "sg:postcode":"11405",
    "sg:province":"C\u00e1diz",
    "sg:website":"www.msd.es",
    "wof:name":"Merck Sharp & Dohme Espa\u00d1ola S.a.",
    "wof:placetype":"venue"
},
  "geometry": {"coordinates":[-6.1191329956,36.6985435486],"type":"Point"}
}