{
  "type": "Feature",
  "properties": {
    "iso:country":"ES",
    "sg:address":"Avda Julian Claveria, 11",
    "sg:city":"Oviedo",
    "sg:orig_category":"Clubes Y Asociaciones Deportivas Y De Actividades Invernales Y De Monta\u00d1a",
    "sg:phone":"+34 985 27 63 50",
    "sg:postcode":"33006",
    "sg:province":"Asturias",
    "sg:website":"www.fcpa@telefonica.net",
    "wof:name":"Federacion De Caza Principado De Asturias",
    "wof:placetype":"venue"
},
  "geometry": {"coordinates":[-5.8704957962,43.3573455811],"type":"Point"}
}