{
  "type": "Feature",
  "properties": {
    "iso:country":"ES",
    "sg:address":"Calle de El Torno, 6",
    "sg:city":"Vitoria-gasteiz",
    "sg:orig_category":"Ense\u00d1anza: Idiomas",
    "sg:phone":"+34 945 26 38 06",
    "sg:postcode":"01001",
    "sg:province":"\u00c1lava",
    "wof:name":"Academia De Ingles Brandon S.c.",
    "wof:placetype":"venue"
},
  "geometry": {"coordinates":[-2.669211,42.848755],"type":"Point"}
}