{
  "type": "Feature",
  "properties": {
    "addr:full":"Calle de San Miguel, 1 Fortuna Murcia 30620",
    "addr:housenumber":"1",
    "addr:postcode":"30620",
    "addr:street":"Calle De San Miguel",
    "iso:country":"ES",
    "sg:address":"Calle de San Miguel, 1",
    "sg:city":"Fortuna",
    "sg:orig_category":"Invernaderos Y Semilleros",
    "sg:phone":"+34 968 68 52 36",
    "sg:postcode":"30620",
    "sg:province":"Murcia",
    "wof:name":"Santos Pina Claudio",
    "wof:placetype":"venue"
},
  "geometry": {"coordinates":[-1.1243460178,38.1790275574],"type":"Point"}
}