{
  "type": "Feature",
  "properties": {
    "addr:full":"Calle de Diego Betancor Suarez, 39 Palmas De Gran Canaria Las Palmas 35012",
    "addr:housenumber":"39",
    "addr:postcode":"35012",
    "addr:street":"Calle De Diego Betancor Suarez",
    "iso:country":"ES",
    "sg:address":"Calle de Diego Betancor Suarez, 39",
    "sg:city":"Palmas De Gran Canaria",
    "sg:orig_category":"Alimentaci\u00d3n General (al Por Menor)",
    "sg:phone":"+34 928 41 24 34",
    "sg:postcode":"35012",
    "sg:province":"Las Palmas",
    "wof:name":"Almeida Perez Maria De La Cruz",
    "wof:placetype":"venue"
},
  "geometry": {"coordinates":[-15.4458322525,28.1073112488],"type":"Point"}
}