{
  "type": "Feature",
  "properties": {
    "addr:full":"Calle de Embajadores, 20 Madrid Madrid 28012",
    "addr:housenumber":"20",
    "addr:postcode":"madrid;28012",
    "addr:street":"Calle De Embajadores",
    "iso:country":"ES",
    "sg:address":"Calle de Embajadores, 20",
    "sg:city":"Madrid",
    "sg:orig_category":"Porcelanas, Azulejos (fabricaci\u00d3n, Al Por Mayor)",
    "sg:phone":"+34 915 27 07 13",
    "sg:postcode":"28012",
    "sg:province":"Madrid",
    "wof:name":"Exclusivas Almenara S.l.",
    "wof:placetype":"venue"
},
  "geometry": {"coordinates":[-3.7060329914,40.4095573425],"type":"Point"}
}