{
  "type": "Feature",
  "properties": {
    "iso:country":"ES",
    "sg:address":"Pl. Regne De Valencia, S/n",
    "sg:city":"Massanassa",
    "sg:orig_category":"Molduras, Junquillos, Listones Y Molduras Perforadas",
    "sg:phone":"+34 961 25 10 07",
    "sg:postcode":"46470",
    "sg:province":"Valencia",
    "wof:name":"Hogar Parroquial Sociedad",
    "wof:placetype":"venue"
},
  "geometry": {"coordinates":[-0.3962790072,39.4093399048],"type":"Point"}
}