{
  "type": "Feature",
  "properties": {
    "iso:country":"ES",
    "sg:address":"Avda Constitucion, 13",
    "sg:city":"Callosa Segura",
    "sg:orig_category":"Cl\u00cdnicas Dentales",
    "sg:phone":"+34 965 31 13 71",
    "sg:postcode":"03360",
    "sg:province":"Alicante",
    "wof:name":"Pelegrin Garcia Mari Carmen",
    "wof:placetype":"venue"
},
  "geometry": {"coordinates":[-0.8778399825,38.1265563965],"type":"Point"}
}