{
  "type": "Feature",
  "properties": {
    "iso:country":"ES",
    "sg:address":"Alba Rosa, 6",
    "sg:city":"Olot",
    "sg:orig_category":"Ense\u00d1anza: Profesiones Art\u00cdsticas",
    "sg:phone":"+34 972 26 00 63",
    "sg:postcode":"17800",
    "sg:province":"Girona",
    "wof:name":"Pons Semelis Anna Maria",
    "wof:placetype":"venue"
},
  "geometry": {"coordinates":[2.5007240772,42.1927986145],"type":"Point"}
}