{
  "type": "Feature",
  "properties": {
    "addr:full":"Calle de Virgen, 14 Tarazona Mancha Albacete 02100",
    "addr:housenumber":"14",
    "addr:postcode":"02100",
    "addr:street":"Calle De Virgen",
    "iso:country":"ES",
    "sg:address":"Calle de Virgen, 14",
    "sg:city":"Tarazona Mancha",
    "sg:orig_category":"Asesor\u00cda Fiscal Y Jur\u00cddica",
    "sg:phone":"+34 967 49 72 80",
    "sg:postcode":"02100",
    "sg:province":"Albacete",
    "wof:name":"Ruiz Lopez Maria Albina",
    "wof:placetype":"venue"
},
  "geometry": {"coordinates":[-1.9120399952,39.2639160156],"type":"Point"}
}