{
  "type": "Feature",
  "properties": {
    "addr:full":"Carrer de Vistalegre, 44 Cornella Llobregat Barcelona 08940",
    "addr:housenumber":"44",
    "addr:postcode":"08940",
    "addr:street":"Carrer De Vistalegre",
    "iso:country":"ES",
    "sg:address":"Carrer de Vistalegre, 44",
    "sg:city":"Cornella Llobregat",
    "sg:orig_category":"Transportes Por Carretera: Lotes Completos, Mercanc\u00cdas Diversas",
    "sg:phone":"+34 934 71 01 46",
    "sg:postcode":"08940",
    "sg:province":"Barcelona",
    "wof:name":"Figueroa De Figueroa Luz Janeth",
    "wof:placetype":"venue"
},
  "geometry": {"coordinates":[2.075676918,41.3623962402],"type":"Point"}
}