{
  "type": "Feature",
  "properties": {
    "iso:country":"ES",
    "sg:address":"Av Masnou, 82",
    "sg:city":"Hospitalet Llobregat",
    "sg:orig_category":"\u00d3ptica: Instrumentos (fabricaci\u00d3n)",
    "sg:phone":"+34 933 34 31 99",
    "sg:postcode":"08905",
    "sg:province":"Barcelona",
    "wof:name":"Gibert Rovira Juan Alberto",
    "wof:placetype":"venue"
},
  "geometry": {"coordinates":[2.1106379032,41.3690948486],"type":"Point"}
}