{
  "type": "Feature",
  "properties": {
    "iso:country":"ES",
    "sg:address":"Calle de Manuel Alvarez, 1",
    "sg:city":"Madrid",
    "sg:orig_category":"Chapister\u00cda",
    "sg:phone":"+34 914 66 15 95",
    "sg:postcode":"28025",
    "sg:province":"Madrid",
    "wof:name":"Talleres Gomez Ayuso S.l.l.",
    "wof:placetype":"venue"
},
  "geometry": {"coordinates":[-3.7439239025,40.38829422],"type":"Point"}
}