{
  "type": "Feature",
  "properties": {
    "iso:country":"ES",
    "sg:address":"Avda Alemania (de), 15",
    "sg:city":"Caceres",
    "sg:orig_category":"Ingeniero",
    "sg:phone":"+34 927 23 18 74",
    "sg:postcode":"10001",
    "sg:province":"C\u00e1ceres",
    "wof:name":"Andrada Daza Pedro Pablo",
    "wof:placetype":"venue"
},
  "geometry": {"coordinates":[-6.3802571297,39.4669075012],"type":"Point"}
}