{
  "type": "Feature",
  "properties": {
    "addr:full":"Rua Soportais (dos), 5 Pontevedra Pontevedra 36002",
    "addr:housenumber":"5",
    "addr:postcode":"36002",
    "addr:street":"Rua Soportais Dos",
    "iso:country":"ES",
    "sg:address":"Rua Soportais (dos), 5",
    "sg:city":"Pontevedra",
    "sg:orig_category":"Confecci\u00d3n (fabricaci\u00d3n, Al Por Mayor)",
    "sg:phone":"+34 986 85 61 78",
    "sg:postcode":"36002",
    "sg:province":"Pontevedra",
    "wof:name":"Diaz Gonzalez Carlos Antonio",
    "wof:placetype":"venue"
},
  "geometry": {"coordinates":[-8.6233987808,42.4448699951],"type":"Point"}
}