{
  "type": "Feature",
  "properties": {
    "iso:country":"ES",
    "sg:address":"Av Pais Valencia (del), 150",
    "sg:city":"Cocentaina",
    "sg:orig_category":"Fabricaci\u00d3n, Importaci\u00d3n De L\u00c1mparas Y Bombillas",
    "sg:phone":"+34 965 59 34 42",
    "sg:postcode":"03820",
    "sg:province":"Alicante",
    "sg:website":"www.alalamp.com",
    "wof:name":"Alalamp S.l.",
    "wof:placetype":"venue"
},
  "geometry": {"coordinates":[-0.4411376119,38.7358131409],"type":"Point"}
}