{
  "type": "Feature",
  "properties": {
    "iso:country":"ES",
    "sg:address":"Calle de Dolores De La Rocha, 38",
    "sg:city":"Palmas De Gran Canaria",
    "sg:orig_category":"Ingeniero",
    "sg:phone":"+34 928 31 07 41",
    "sg:postcode":"35001",
    "sg:province":"Las Palmas",
    "wof:name":"Suarez Moreno Jose Antonio",
    "wof:placetype":"venue"
},
  "geometry": {"coordinates":[-15.4134378433,28.0977592468],"type":"Point"}
}