{
  "type": "Feature",
  "properties": {
    "iso:country":"ES",
    "sg:address":"Carr Mendez Nu\u00d1ez, 2",
    "sg:city":"Figueres",
    "sg:orig_category":"Pensiones Familiares",
    "sg:phone":"+34 972 50 14 73",
    "sg:postcode":"17600",
    "sg:province":"Girona",
    "wof:name":"Vila Bartis Concepcio",
    "wof:placetype":"venue"
},
  "geometry": {"coordinates":[2.9659199715,42.2661209106],"type":"Point"}
}