{
  "type": "Feature",
  "properties": {
    "iso:country":"ES",
    "sg:address":"Calle de Maestranza, 8",
    "sg:city":"Malaga",
    "sg:orig_category":"Ingeniero",
    "sg:phone":"+34 952 60 77 23",
    "sg:postcode":"29016",
    "sg:province":"M\u00e1laga",
    "wof:name":"Silva Moreira Esteban",
    "wof:placetype":"venue"
},
  "geometry": {"coordinates":[-4.41040802,36.7196807861],"type":"Point"}
}