{
  "type": "Feature",
  "properties": {
    "iso:country":"ES",
    "sg:address":"Carrer de Sant Leopold, 25",
    "sg:city":"Terrassa",
    "sg:orig_category":"Arquitectos",
    "sg:phone":"+34 937 88 96 89",
    "sg:postcode":"08221",
    "sg:province":"Barcelona",
    "wof:name":"Broto Comerma Eduard",
    "wof:placetype":"venue"
},
  "geometry": {"coordinates":[2.0129499435,41.5667457581],"type":"Point"}
}