{
  "type": "Feature",
  "properties": {
    "iso:country":"ES",
    "sg:address":"Calle de Cabezas Rubias, 16",
    "sg:city":"Huelva",
    "sg:orig_category":"Farmacias",
    "sg:phone":"+34 959 22 39 46",
    "sg:postcode":"21007",
    "sg:province":"Huelva",
    "wof:name":"Farmacia Raquel Velasco Reinold",
    "wof:placetype":"venue"
},
  "geometry": {"coordinates":[-6.9269599915,37.2646408081],"type":"Point"}
}