{
  "type": "Feature",
  "properties": {
    "addr:full":"Rua San Lourenzo (de), 29 Santiago De Compostela La Coru\u00f1a 15705",
    "addr:housenumber":"29",
    "addr:postcode":"15705",
    "addr:street":"Rua San Lourenzo De;Corun\u0303A",
    "iso:country":"ES",
    "sg:address":"Rua San Lourenzo (de), 29",
    "sg:city":"Santiago De Compostela",
    "sg:orig_category":"Alimentaci\u00d3n General (al Por Menor)",
    "sg:phone":"+34 981 58 52 95",
    "sg:postcode":"15705",
    "sg:province":"La Coru\u00f1a",
    "wof:name":"Lopez Rey Regina",
    "wof:placetype":"venue"
},
  "geometry": {"coordinates":[-8.5534296036,42.8789215088],"type":"Point"}
}