{
  "type": "Feature",
  "properties": {
    "addr:full":"Avda Trebujena (de), S/n Sanlucar De Barrameda C\u00e1diz 11540",
    "addr:housenumber":"/ n",
    "addr:postcode":"11540",
    "addr:street":"Avda Trebujena De S;Ca\u0301Diz",
    "iso:country":"ES",
    "sg:address":"Avda Trebujena (de), S/n",
    "sg:city":"Sanlucar De Barrameda",
    "sg:orig_category":"Productores Recolectores, Venta Directa De Vinos",
    "sg:phone":"+34 956 36 01 24",
    "sg:postcode":"11540",
    "sg:province":"C\u00e1diz",
    "sg:website":"www.manzanillasanlucar.com",
    "wof:name":"Florido Cano Gaspar",
    "wof:placetype":"venue"
},
  "geometry": {"coordinates":[-6.3444738388,36.769908905],"type":"Point"}
}