{
  "type": "Feature",
  "properties": {
    "addr:full":"C/ Fray Luis De Leon, 13 Elche Alicante 03203",
    "addr:housenumber":"13",
    "addr:postcode":"03203",
    "addr:street":"C / Fray Luis De Leon",
    "iso:country":"ES",
    "sg:address":"C/ Fray Luis De Leon, 13",
    "sg:city":"Elche",
    "sg:orig_category":"Ebanister\u00cda",
    "sg:phone":"+34 965 45 43 31",
    "sg:postcode":"03203",
    "sg:province":"Alicante",
    "wof:name":"Mora Bernad Antonio",
    "wof:placetype":"venue"
},
  "geometry": {"coordinates":[-0.6968259811,38.2573432922],"type":"Point"}
}