{
  "type": "Feature",
  "properties": {
    "addr:full":"Calle de Regimiento De Toledo, 33 Zamora Zamora 49011",
    "addr:housenumber":"33",
    "addr:postcode":"49011",
    "addr:street":"Calle De Regimiento De Toledo",
    "iso:country":"ES",
    "sg:address":"Calle de Regimiento De Toledo, 33",
    "sg:city":"Zamora",
    "sg:orig_category":"Periodistas Profesionales",
    "sg:phone":"+34 980 52 34 50",
    "sg:postcode":"49011",
    "sg:province":"Zamora",
    "wof:name":"Pablos Florez Luis",
    "wof:placetype":"venue"
},
  "geometry": {"coordinates":[-5.7379589081,41.5108146667],"type":"Point"}
}