{
  "type": "Feature",
  "properties": {
    "iso:country":"ES",
    "sg:address":"Urbz La Ermita, 5",
    "sg:city":"Ota\u00f1es",
    "sg:orig_category":"Fabricaci\u00d3n, Distribuci\u00d3n De Discos, V\u00cddeodiscos Y Musicassettes",
    "sg:phone":"+34 942 87 90 15",
    "sg:postcode":"39707",
    "sg:province":"Cantabria",
    "wof:name":"Saez Amador Javier",
    "wof:placetype":"venue"
},
  "geometry": {"coordinates":[-3.1923139095,43.3296279907],"type":"Point"}
}