{
  "type": "Feature",
  "properties": {
    "iso:country":"ES",
    "sg:address":"Vena Sant Jaume, 1",
    "sg:city":"Sant Jaume De Treia",
    "sg:orig_category":"Cerrajer\u00cda, Ferrallista",
    "sg:phone":"+34 937 57 22 93",
    "sg:postcode":"08310",
    "sg:province":"Barcelona",
    "sg:website":"www.candadosgile.com",
    "wof:name":"Gile S.c.p.",
    "wof:placetype":"venue"
},
  "geometry": {"coordinates":[2.4036650658,41.5564155579],"type":"Point"}
}