{
  "type": "Feature",
  "properties": {
    "iso:country":"ES",
    "sg:address":"Calle de Llano Ponte, 52",
    "sg:city":"Aviles",
    "sg:orig_category":"Agentes, Concesionarios Y Sucursales De Veh\u00cdculos",
    "sg:phone":"+34 985 54 01 48",
    "sg:postcode":"33402",
    "sg:province":"Asturias",
    "wof:name":"Autos Maga S.l.",
    "wof:placetype":"venue"
},
  "geometry": {"coordinates":[-5.9179592133,43.5517578125],"type":"Point"}
}