{
  "type": "Feature",
  "properties": {
    "addr:full":"Rua Urzaiz, 180 Vigo Pontevedra 36205",
    "addr:housenumber":"180",
    "addr:postcode":"36205",
    "addr:street":"Rua Urzaiz",
    "iso:country":"ES",
    "sg:address":"Rua Urzaiz, 180",
    "sg:city":"Vigo",
    "sg:orig_category":"Cajas De Ahorro",
    "sg:phone":"+34 986 37 83 77",
    "sg:postcode":"36205",
    "sg:province":"Pontevedra",
    "wof:name":"Caixa D'estalvis I Pensions De Barcelona",
    "wof:placetype":"venue"
},
  "geometry": {"coordinates":[-8.7025613785,42.2308807373],"type":"Point"}
}