{
  "type": "Feature",
  "properties": {
    "iso:country":"ES",
    "sg:address":"Calle de Pintor Juan Camprobin Passano, 5",
    "sg:city":"Almagro",
    "sg:orig_category":"Hielo Artificial (fabricaci\u00d3n, Distribuci\u00d3n)",
    "sg:phone":"+34 926 86 10 03",
    "sg:postcode":"13270",
    "sg:province":"Ciudad Real",
    "wof:name":"Serrano Cobo Vicente",
    "wof:placetype":"venue"
},
  "geometry": {"coordinates":[-3.6998538971,38.891784668],"type":"Point"}
}