{
  "type": "Feature",
  "properties": {
    "iso:country":"ES",
    "sg:address":"Avda Constitucion De La, S/n",
    "sg:city":"Caceres",
    "sg:orig_category":"Veh\u00cdculos De Ocasi\u00d3n",
    "sg:phone":"+34 927 62 92 96",
    "sg:postcode":"10195",
    "sg:province":"C\u00e1ceres",
    "wof:name":"Vivas Frejo Felipe",
    "wof:placetype":"venue"
},
  "geometry": {"coordinates":[-6.3922438622,39.4486846924],"type":"Point"}
}