{
  "type": "Feature",
  "properties": {
    "addr:full":"Carrer de Brutau, 180 Sabadell Barcelona 08203",
    "addr:housenumber":"180",
    "addr:postcode":"08203",
    "addr:street":"Carrer De Brutau",
    "iso:country":"ES",
    "sg:address":"Carrer de Brutau, 180",
    "sg:city":"Sabadell",
    "sg:orig_category":"Reposter\u00cdas",
    "sg:phone":"+34 937 12 24 93",
    "sg:postcode":"08203",
    "sg:province":"Barcelona",
    "wof:name":"Susapan.s.l.",
    "wof:placetype":"venue"
},
  "geometry": {"coordinates":[2.1165668964,41.5377998352],"type":"Point"}
}