{
  "type": "Feature",
  "properties": {
    "iso:country":"ES",
    "sg:address":"Carr S Magi, 6",
    "sg:city":"Igualada",
    "sg:orig_category":"Frutas, Legumbres Frescas Y Tempranas (al Por Menor)",
    "sg:phone":"+34 938 03 55 13",
    "sg:postcode":"08700",
    "sg:province":"Barcelona",
    "wof:name":"Cubi Collado Norberto",
    "wof:placetype":"venue"
},
  "geometry": {"coordinates":[1.6165430546,41.5802536011],"type":"Point"}
}