{
  "type": "Feature",
  "properties": {
    "addr:full":"Pase Malkaitz, 1 Mutiloagoiti Navarra 31192",
    "addr:housenumber":"1",
    "addr:postcode":"31192",
    "addr:street":"Malkaitz",
    "iso:country":"ES",
    "sg:address":"Pase Malkaitz, 1",
    "sg:city":"Mutiloagoiti",
    "sg:orig_category":"Abogados",
    "sg:phone":"+34 948 23 66 67",
    "sg:postcode":"31192",
    "sg:province":"Navarra",
    "wof:name":"Valls Esparza Martin",
    "wof:placetype":"venue"
},
  "geometry": {"coordinates":[-1.617759943,42.8010864258],"type":"Point"}
}