{
  "type": "Feature",
  "properties": {
    "iso:country":"ES",
    "sg:address":"Carrer de Valencia, 601",
    "sg:city":"Barcelona",
    "sg:orig_category":"Contenedores (mercanc\u00cdas)",
    "sg:phone":"+34 932 32 29 82",
    "sg:postcode":"08026",
    "sg:province":"Barcelona",
    "wof:name":"Hormigon Garcia Jose",
    "wof:placetype":"venue"
},
  "geometry": {"coordinates":[2.1854529381,41.409488678],"type":"Point"}
}