{
  "type": "Feature",
  "properties": {
    "iso:country":"ES",
    "sg:address":"Carrer de Sant Joan, 54",
    "sg:city":"Pobla Mafumet",
    "sg:orig_category":"Trabajos De Perforaciones, Sondeos, Construcci\u00d3n De Pozos",
    "sg:phone":"+34 977 84 03 03",
    "sg:postcode":"43140",
    "sg:province":"Tarragona",
    "wof:name":"Sarda Montserrat Jose Maria",
    "wof:placetype":"venue"
},
  "geometry": {"coordinates":[1.21025002,41.185749054],"type":"Point"}
}