{
  "type": "Feature",
  "properties": {
    "addr:full":"Ctra Ciutadella, 3 Cales Piques Islas Baleares 07760",
    "addr:housenumber":"3",
    "addr:postcode":"07760",
    "addr:street":"Ctra Ciutadella;Islas",
    "iso:country":"ES",
    "sg:address":"Ctra Ciutadella, 3",
    "sg:city":"Cales Piques",
    "sg:orig_category":"Cervecer\u00cdas",
    "sg:phone":"+34 971 38 86 05",
    "sg:postcode":"07760",
    "sg:province":"Islas Baleares",
    "wof:name":"Ametler Gomila Sebastian",
    "wof:placetype":"venue"
},
  "geometry": {"coordinates":[2.8577105999,39.5341796875],"type":"Point"}
}