{
  "type": "Feature",
  "properties": {
    "iso:country":"ES",
    "sg:address":"Calle de Jesus Gil Gonzalez, 47",
    "sg:city":"Pozuelo De Alarcon",
    "sg:orig_category":"Procuradores",
    "sg:phone":"+34 913 52 94 02",
    "sg:postcode":"28223",
    "sg:province":"Madrid",
    "wof:name":"Pelaez Pancheri Elena",
    "wof:placetype":"venue"
},
  "geometry": {"coordinates":[-3.8136439323,40.4400901794],"type":"Point"}
}