{
  "type": "Feature",
  "properties": {
    "addr:full":"Calle de Medico Antonio Pavia, 25 Aspe Alicante 03680",
    "addr:housenumber":"25",
    "addr:postcode":"03680",
    "addr:street":"Calle De Medico Antonio Pavia",
    "iso:country":"ES",
    "sg:address":"Calle de Medico Antonio Pavia, 25",
    "sg:city":"Aspe",
    "sg:orig_category":"Abogados",
    "sg:phone":"+34 965 49 42 39",
    "sg:postcode":"03680",
    "sg:province":"Alicante",
    "wof:name":"Martinez Garcia Juan Carlos",
    "wof:placetype":"venue"
},
  "geometry": {"coordinates":[-0.7658960223,38.3473167419],"type":"Point"}
}