{
  "type": "Feature",
  "properties": {
    "addr:full":"Carrer de Pujades, 210 Barcelona Barcelona 08005",
    "addr:housenumber":"210",
    "addr:postcode":"08005",
    "addr:street":"Carrer De Pujades",
    "iso:country":"ES",
    "sg:address":"Carrer de Pujades, 210",
    "sg:city":"Barcelona",
    "sg:orig_category":"Iglesia Cat\u00d3lica",
    "sg:phone":"+34 933 09 63 65",
    "sg:postcode":"08005",
    "sg:province":"Barcelona",
    "wof:name":"Parroquia De Santa Maria De Taulat",
    "wof:placetype":"venue"
},
  "geometry": {"coordinates":[2.202256918,41.4027481079],"type":"Point"}
}