{
  "type": "Feature",
  "properties": {
    "addr:full":"Calle de General Riera, 32 Palma Islas Baleares 07003",
    "addr:housenumber":"32",
    "addr:postcode":"07003",
    "addr:street":"Calle De General Riera",
    "iso:country":"ES",
    "sg:address":"Calle de General Riera, 32",
    "sg:city":"Palma",
    "sg:orig_category":"Asistencia Social",
    "sg:phone":"+34 971 20 01 80",
    "sg:postcode":"07003",
    "sg:province":"Islas Baleares",
    "sg:website":"www.remar.org",
    "wof:name":"Remar Espa\u00f1a",
    "wof:placetype":"venue"
},
  "geometry": {"coordinates":[2.6474509239,39.5811042786],"type":"Point"}
}