{
  "type": "Feature",
  "properties": {
    "iso:country":"ES",
    "sg:address":"Calle de Pablo Iglesias, 85",
    "sg:city":"Cabezas S. Juan",
    "sg:orig_category":"Mec\u00c1nico Del Autom\u00d3vil",
    "sg:phone":"+34 955 87 39 96",
    "sg:postcode":"41730",
    "sg:province":"Sevilla",
    "wof:name":"Moron Becerra Juan",
    "wof:placetype":"venue"
},
  "geometry": {"coordinates":[-5.9434728622,36.9773788452],"type":"Point"}
}