{
  "type": "Feature",
  "properties": {
    "addr:full":"Carrer de Balandra, 8 Torroja Del Priorat Tarragona 43737",
    "addr:housenumber":"8",
    "addr:postcode":"43737",
    "addr:street":"Carrer De Balandra",
    "iso:country":"ES",
    "sg:address":"Carrer de Balandra, 8",
    "sg:city":"Torroja Del Priorat",
    "sg:orig_category":"Productores Recolectores, Venta Directa De Vinos",
    "sg:phone":"+34 977 83 92 85",
    "sg:postcode":"43737",
    "sg:province":"Tarragona",
    "sg:website":"www.rotllantorra.com",
    "wof:name":"Vins D'alta Qualitat S.l.",
    "wof:placetype":"venue"
},
  "geometry": {"coordinates":[0.8096870184,41.213558197],"type":"Point"}
}