{
  "type": "Feature",
  "properties": {
    "addr:full":"Calle de Bomba, 14 Badajoz Badajoz 06004",
    "addr:housenumber":"14",
    "addr:postcode":"06004",
    "addr:street":"Calle De Bomba",
    "iso:country":"ES",
    "sg:address":"Calle de Bomba, 14",
    "sg:city":"Badajoz",
    "sg:orig_category":"Periodistas Profesionales",
    "sg:phone":"+34 924 25 97 24",
    "sg:postcode":"06004",
    "sg:province":"Badajoz",
    "wof:name":"Vela Jaramillo Jose Luis",
    "wof:placetype":"venue"
},
  "geometry": {"coordinates":[-6.9720058441,38.8744544983],"type":"Point"}
}