{
  "type": "Feature",
  "properties": {
    "addr:full":"Rua Fonti\u00d1a, Km. 0249,0 San Paio Ourense 32414",
    "addr:postcode":"32414",
    "addr:street":"Rua Fontin\u0303A Km. 0249,0 San",
    "iso:country":"ES",
    "sg:address":"Rua Fonti\u00d1a, Km. 0249,0",
    "sg:city":"San Paio",
    "sg:orig_category":"Distribuci\u00d3n De Petr\u00d3leo Y Derivados",
    "sg:phone":"+34 988 47 71 22",
    "sg:postcode":"32414",
    "sg:province":"Ourense",
    "wof:name":"Suministros Y Areas De Servicios Ploc S.a.",
    "wof:placetype":"venue"
},
  "geometry": {"coordinates":[-7.7956900597,41.9095687866],"type":"Point"}
}