{
  "type": "Feature",
  "properties": {
    "addr:full":"Carrer de Embut (l'), 4 Parcent Alicante 03792",
    "addr:housenumber":"4",
    "addr:postcode":"03792",
    "addr:street":"Carrer De Embut L '",
    "iso:country":"ES",
    "sg:address":"Carrer de Embut (l'), 4",
    "sg:city":"Parcent",
    "sg:orig_category":"Comerciantes Al Por Mayor De Vinos, Licores Y Alcoholes",
    "sg:phone":"+34 966 40 52 66",
    "sg:postcode":"03792",
    "sg:province":"Alicante",
    "sg:website":"www.arrakis.es/gutivega",
    "wof:name":"Gutierrez De Vega Lopez Felipe",
    "wof:placetype":"venue"
},
  "geometry": {"coordinates":[-0.0647870004,38.7451286316],"type":"Point"}
}