{
  "type": "Feature",
  "properties": {
    "addr:full":"Plaz Inmaculada (la), 2 Huesca Huesca 22003",
    "addr:housenumber":"2",
    "addr:postcode":"22003",
    "addr:street":"La",
    "iso:country":"ES",
    "sg:address":"Plaz Inmaculada (la), 2",
    "sg:city":"Huesca",
    "sg:orig_category":"Sindicatos Y Colegios Profesionales",
    "sg:phone":"+34 974 23 04 24",
    "sg:postcode":"22003",
    "sg:province":"Huesca",
    "wof:name":"Asociacion Provincial De Tecnicos Y Auxiliares De Farmacia",
    "wof:placetype":"venue"
},
  "geometry": {"coordinates":[-0.4104340076,42.1386566162],"type":"Point"}
}