{
  "type": "Feature",
  "properties": {
    "iso:country":"ES",
    "sg:address":"Calle de Madrid, 12",
    "sg:city":"Burgos",
    "sg:orig_category":"Peluquer\u00cdas",
    "sg:phone":"+34 947 27 32 55",
    "sg:postcode":"09002",
    "sg:province":"Burgos",
    "wof:name":"Castrillo Santamaria Laura",
    "wof:placetype":"venue"
},
  "geometry": {"coordinates":[-3.7012579441,42.337184906],"type":"Point"}
}