{
  "type": "Feature",
  "properties": {
    "iso:country":"ES",
    "sg:address":"Calle de Vicente Espinel, 32",
    "sg:city":"Madrid",
    "sg:orig_category":"Abogados",
    "sg:phone":"+34 914 07 81 87",
    "sg:postcode":"28017",
    "sg:province":"Madrid",
    "wof:name":"Sanchez Fernandez Maria Angeles",
    "wof:placetype":"venue"
},
  "geometry": {"coordinates":[-3.6412899494,40.4333305359],"type":"Point"}
}