{
  "type": "Feature",
  "properties": {
    "iso:country":"ES",
    "sg:address":"Avda Andalucia, 53",
    "sg:city":"Villacarrillo",
    "sg:orig_category":"Supermercados Y Hipermercados",
    "sg:phone":"+34 953 45 44 85",
    "sg:postcode":"23300",
    "sg:province":"Ja\u00e9n",
    "wof:name":"Santiago Collado Josefa",
    "wof:placetype":"venue"
},
  "geometry": {"coordinates":[-3.0915970802,38.1141090393],"type":"Point"}
}