{
  "type": "Feature",
  "properties": {
    "addr:full":"Calle de Paloma, 14 Ciudad Real Ciudad Real 13004",
    "addr:housenumber":"14",
    "addr:postcode":"13004",
    "addr:street":"Calle De Paloma",
    "iso:country":"ES",
    "sg:address":"Calle de Paloma, 14",
    "sg:city":"Ciudad Real",
    "sg:orig_category":"Ropa Para Se\u00d1oras (al Por Menor)",
    "sg:phone":"+34 926 25 16 48",
    "sg:postcode":"13004",
    "sg:province":"Ciudad Real",
    "wof:name":"Factory Mix Sl",
    "wof:placetype":"venue"
},
  "geometry": {"coordinates":[-3.9270310402,38.9865112305],"type":"Point"}
}