{
  "type": "Feature",
  "properties": {
    "addr:full":"Romero Puebla, 12 La Puebla Rio Sevilla 41130",
    "addr:housenumber":"12",
    "addr:postcode":"41130",
    "addr:street":"Puebla",
    "iso:country":"ES",
    "sg:address":"Romero Puebla, 12",
    "sg:city":"La Puebla Rio",
    "sg:orig_category":"Electrodom\u00c9sticos (al Por Menor)",
    "sg:phone":"+34 955 77 21 01",
    "sg:postcode":"41130",
    "sg:province":"Sevilla",
    "wof:name":"Lopez Carrasco E Hijos S.l.",
    "wof:placetype":"venue"
},
  "geometry": {"coordinates":[-6.0651087761,37.2680435181],"type":"Point"}
}