{
  "type": "Feature",
  "properties": {
    "addr:full":"Carr Palma, De, 45 Consell Islas Baleares 07330",
    "addr:housenumber":"45",
    "addr:postcode":"07330",
    "addr:street":"Carr Palma De",
    "iso:country":"ES",
    "sg:address":"Carr Palma, De, 45",
    "sg:city":"Consell",
    "sg:orig_category":"Promotores Constructores",
    "sg:phone":"+34 971 14 20 50",
    "sg:postcode":"07330",
    "sg:province":"Islas Baleares",
    "wof:name":"Construcciones Mateo Roig Fiol S.l.",
    "wof:placetype":"venue"
},
  "geometry": {"coordinates":[2.8202500343,39.6667709351],"type":"Point"}
}