{
  "type": "Feature",
  "properties": {
    "addr:full":"Extrarradio, S/n Lagunilla Vega Palencia 34134",
    "addr:housenumber":"s / n",
    "addr:postcode":"34134",
    "addr:street":"Extrarradio",
    "iso:country":"ES",
    "sg:address":"Extrarradio, S/n",
    "sg:city":"Lagunilla Vega",
    "sg:orig_category":"Distribuci\u00d3n De Petr\u00d3leo Y Derivados",
    "sg:phone":"+34 979 88 40 96",
    "sg:postcode":"34134",
    "sg:province":"Palencia",
    "wof:name":"Tarilonte Sastre S.l.",
    "wof:placetype":"venue"
},
  "geometry": {"coordinates":[-4.7547049522,42.4381332397],"type":"Point"}
}