{
  "type": "Feature",
  "properties": {
    "addr:full":"Calle de Lepanto, 2 Castellon Castell\u00f3n 12006",
    "addr:housenumber":"2",
    "addr:postcode":"12006",
    "addr:street":"Calle De Lepanto;Castello\u0301N",
    "iso:country":"ES",
    "sg:address":"Calle de Lepanto, 2",
    "sg:city":"Castellon",
    "sg:orig_category":"Impermeabilizantes",
    "sg:phone":"+34 964 20 52 48",
    "sg:postcode":"12006",
    "sg:province":"Castell\u00f3n",
    "wof:name":"Garcia Ruiz Joaquin",
    "wof:placetype":"venue"
},
  "geometry": {"coordinates":[-0.1292939931,40.0168533325],"type":"Point"}
}