{
  "type": "Feature",
  "properties": {
    "addr:full":"C/ Montsec, 4 Tarrega Lleida 25300",
    "addr:housenumber":"4",
    "addr:postcode":"25300",
    "addr:street":"C / Montsec",
    "iso:country":"ES",
    "sg:address":"C/ Montsec, 4",
    "sg:city":"Tarrega",
    "sg:orig_category":"Agencias Y Agentes Comerciales, Representantes",
    "sg:phone":"+34 973 31 21 40",
    "sg:postcode":"25300",
    "sg:province":"Lleida",
    "wof:name":"Torres Sole Josep",
    "wof:placetype":"venue"
},
  "geometry": {"coordinates":[1.1334949732,41.6479415894],"type":"Point"}
}