{
  "type": "Feature",
  "properties": {
    "iso:country":"ES",
    "sg:address":"Carrer de Josep Pla, 9",
    "sg:city":"Hospitalet Llobregat",
    "sg:orig_category":"Mec\u00c1nico Del Autom\u00d3vil",
    "sg:phone":"+34 933 37 56 11",
    "sg:postcode":"08901",
    "sg:province":"Barcelona",
    "wof:name":"Orea Martinez Antonio",
    "wof:placetype":"venue"
},
  "geometry": {"coordinates":[2.1044108868,41.3601913452],"type":"Point"}
}