{
  "type": "Feature",
  "properties": {
    "addr:full":"Calle de Portugalejo, 7 Madrigalejo C\u00e1ceres 10110",
    "addr:housenumber":"7",
    "addr:postcode":"10110",
    "addr:street":"Calle De Portugalejo;Ca\u0301Ceres",
    "iso:country":"ES",
    "sg:address":"Calle de Portugalejo, 7",
    "sg:city":"Madrigalejo",
    "sg:orig_category":"Bazares, Art\u00cdculos De Limpieza Y De Cocina (al Por Menor)",
    "sg:phone":"+34 927 35 40 92",
    "sg:postcode":"10110",
    "sg:province":"C\u00e1ceres",
    "wof:name":"Hermanos Martinez Mauricio S.l.",
    "wof:placetype":"venue"
},
  "geometry": {"coordinates":[-5.6288580894,39.138885498],"type":"Point"}
}