{
  "type": "Feature",
  "properties": {
    "addr:full":"C/ Major De La Vila, 10 Elche Alicante 03202",
    "addr:housenumber":"10",
    "addr:postcode":"03202",
    "addr:street":"C / Major De La Vila",
    "iso:country":"ES",
    "sg:address":"C/ Major De La Vila, 10",
    "sg:city":"Elche",
    "sg:orig_category":"Fotocopias, Reprograf\u00cda",
    "sg:phone":"+34 965 45 94 21",
    "sg:postcode":"03202",
    "sg:province":"Alicante",
    "wof:name":"Plot-copy Elche S.l.",
    "wof:placetype":"venue"
},
  "geometry": {"coordinates":[-0.698126018,38.266658783],"type":"Point"}
}