{
  "type": "Feature",
  "properties": {
    "addr:full":"Calle de Fernando Cintas Rosas, 1 Salvatierra De Los Barros Badajoz 06175",
    "addr:housenumber":"1",
    "addr:postcode":"06175",
    "addr:street":"Calle De Fernando Cintas Rosas;Barros",
    "iso:country":"ES",
    "sg:address":"Calle de Fernando Cintas Rosas, 1",
    "sg:city":"Salvatierra De Los Barros",
    "sg:orig_category":"Porcelanas, Azulejos (fabricaci\u00d3n, Al Por Mayor)",
    "sg:phone":"+34 924 69 84 02",
    "sg:postcode":"06175",
    "sg:province":"Badajoz",
    "wof:name":"Moriano Nisa Fernando",
    "wof:placetype":"venue"
},
  "geometry": {"coordinates":[-6.6841039658,38.4925003052],"type":"Point"}
}