{
  "type": "Feature",
  "properties": {
    "iso:country":"ES",
    "sg:address":"Av Catalunya, 73",
    "sg:city":"Vila-sana",
    "sg:orig_category":"Cr\u00cda De Bovinos",
    "sg:phone":"+34 973 60 19 36",
    "sg:postcode":"25245",
    "sg:province":"Lleida",
    "wof:name":"Querol Felip Santiago",
    "wof:placetype":"venue"
},
  "geometry": {"coordinates":[0.9284080267,41.6621322632],"type":"Point"}
}