{
  "type": "Feature",
  "properties": {
    "addr:full":"Rua Santiago De Chile (de), 12 Santiago De Compostela A Coru\u00f1a 15706",
    "addr:housenumber":"12",
    "addr:postcode":"15706",
    "addr:street":"Rua Santiago De Chile De;Corun\u0303A",
    "iso:country":"ES",
    "sg:address":"Rua Santiago De Chile (de), 12",
    "sg:city":"Santiago De Compostela",
    "sg:orig_category":"M\u00c9dicos: Estomatolog\u00cda",
    "sg:phone":"+34 981 59 97 56",
    "sg:postcode":"15706",
    "sg:province":"A Coru\u00f1a",
    "wof:name":"San Martin Lens Juan Carlos",
    "wof:placetype":"venue"
},
  "geometry": {"coordinates":[-8.550909996,42.8723602295],"type":"Point"}
}