{
  "type": "Feature",
  "properties": {
    "addr:full":"Calle de Angel Ganivet, 3 Granada Granada 18009",
    "addr:housenumber":"3",
    "addr:postcode":"18009",
    "addr:street":"Calle De Angel Ganivet",
    "iso:country":"ES",
    "sg:address":"Calle de Angel Ganivet, 3",
    "sg:city":"Granada",
    "sg:orig_category":"Procuradores",
    "sg:phone":"+34 958 22 61 95",
    "sg:postcode":"18009",
    "sg:province":"Granada",
    "wof:name":"Espigares Huete Ana",
    "wof:placetype":"venue"
},
  "geometry": {"coordinates":[-3.5990264416,37.1733398438],"type":"Point"}
}