{
  "type": "Feature",
  "properties": {
    "iso:country":"ES",
    "sg:address":"Avda Tejeda (de), 9",
    "sg:city":"San Fernando",
    "sg:orig_category":"Guarder\u00cdas",
    "sg:phone":"+34 928 76 25 41",
    "sg:postcode":"35100",
    "sg:province":"Las Palmas",
    "wof:name":"Jardin Los Dados",
    "wof:placetype":"venue"
},
  "geometry": {"coordinates":[-15.5842504501,28.0904903412],"type":"Point"}
}