{
  "type": "Feature",
  "properties": {
    "iso:country":"ES",
    "sg:address":"Xar, 31",
    "sg:city":"Barcia",
    "sg:orig_category":"Centros Empresariales",
    "sg:phone":"+34 986 68 24 42",
    "sg:postcode":"36519",
    "sg:province":"Pontevedra",
    "wof:name":"Gallega De Construcciones Y Viales S.l",
    "wof:placetype":"venue"
},
  "geometry": {"coordinates":[-8.1928815842,42.6296806335],"type":"Point"}
}