{
  "type": "Feature",
  "properties": {
    "iso:country":"ES",
    "sg:address":"Pol Imepiel, 18",
    "sg:city":"Vall Uixo",
    "sg:orig_category":"Art\u00cdculos De Limpieza Y De Cocina (fabricaci\u00d3n, Al Por Mayor)",
    "sg:phone":"+34 964 66 72 50",
    "sg:postcode":"12600",
    "sg:province":"Castell\u00f3n",
    "wof:name":"Rosario Ruiz S.l.",
    "wof:placetype":"venue"
},
  "geometry": {"coordinates":[-0.2315589935,39.8232955933],"type":"Point"}
}