{
  "type": "Feature",
  "properties": {
    "addr:full":"Carrer de Miquel Angel, 40 Sabadell Barcelona 08206",
    "addr:housenumber":"40",
    "addr:postcode":"08206",
    "addr:street":"Carrer De Miquel Angel",
    "iso:country":"ES",
    "sg:address":"Carrer de Miquel Angel, 40",
    "sg:city":"Sabadell",
    "sg:orig_category":"Empresarios",
    "sg:phone":"+34 937 45 95 35",
    "sg:postcode":"08206",
    "sg:province":"Barcelona",
    "wof:name":"Ebanisteria Y Decoracion Unitsa S.l.",
    "wof:placetype":"venue"
},
  "geometry": {"coordinates":[2.0885379314,41.5483932495],"type":"Point"}
}