{
  "type": "Feature",
  "properties": {
    "iso:country":"ES",
    "sg:address":"Ctra Jaen (de), S/n",
    "sg:city":"Granada",
    "sg:orig_category":"Comercio De Piezas De Recambio Y De Accesorios De Veh\u00cdculos, Veh\u00cdculos Industriales",
    "sg:phone":"+34 958 15 68 00",
    "sg:postcode":"18018",
    "sg:province":"Granada",
    "sg:website":"www.norauto.es",
    "wof:name":"Norauto S.a.",
    "wof:placetype":"venue"
},
  "geometry": {"coordinates":[-3.6119110584,37.1988677979],"type":"Point"}
}