{
  "type": "Feature",
  "properties": {
    "iso:country":"ES",
    "sg:address":"Calle de Emilio Castelar, 22",
    "sg:city":"Alcazar S. Juan",
    "sg:orig_category":"Radiocomunicaciones, Telefon\u00cda M\u00d3vil, Radiomensajer\u00cda: Servicios, Comercializaci\u00d3n",
    "sg:phone":"+34 926 54 23 14",
    "sg:postcode":"13600",
    "sg:province":"Ciudad Real",
    "wof:name":"Moises Mata S.l.",
    "wof:placetype":"venue"
},
  "geometry": {"coordinates":[-3.208812952,39.3908653259],"type":"Point"}
}