{
  "type": "Feature",
  "properties": {
    "iso:country":"ES",
    "sg:address":"Calle de Chorron, 38",
    "sg:city":"Guadalajara",
    "sg:orig_category":"Electrodom\u00c9sticos (al Por Menor)",
    "sg:phone":"+34 949 23 15 35",
    "sg:postcode":"19005",
    "sg:province":"Guadalajara",
    "wof:name":"Lacofriser S.l.",
    "wof:placetype":"venue"
},
  "geometry": {"coordinates":[-3.1591506004,40.6306991577],"type":"Point"}
}