{
  "type": "Feature",
  "properties": {
    "addr:full":"Rond Pais Valencia, 32 Sueca Valencia 46410",
    "addr:housenumber":"32",
    "addr:postcode":"46410",
    "addr:street":"Rond Pais Valencia",
    "iso:country":"ES",
    "sg:address":"Rond Pais Valencia, 32",
    "sg:city":"Sueca",
    "sg:orig_category":"Pintura Y Barniz (al Por Menor)",
    "sg:phone":"+34 961 70 29 64",
    "sg:postcode":"46410",
    "sg:province":"Valencia",
    "wof:name":"Valenciana De Temples S.l.",
    "wof:placetype":"venue"
},
  "geometry": {"coordinates":[-0.308205992,39.2008781433],"type":"Point"}
}