{
  "type": "Feature",
  "properties": {
    "iso:country":"ES",
    "sg:address":"Carr Temple, 26",
    "sg:city":"Badalona",
    "sg:orig_category":"Agencias Y Agentes Comerciales, Representantes",
    "sg:phone":"+34 934 64 09 96",
    "sg:postcode":"08911",
    "sg:province":"Barcelona",
    "wof:name":"Ballester Gimenez Marta",
    "wof:placetype":"venue"
},
  "geometry": {"coordinates":[2.2472798824,41.4519844055],"type":"Point"}
}