{
  "type": "Feature",
  "properties": {
    "iso:country":"ES",
    "sg:address":"Avda Pablo Iglesias, 64",
    "sg:city":"Gijon",
    "sg:orig_category":"Caf\u00c9s, Bares, Cervecer\u00cdas",
    "sg:phone":"+34 985 36 04 65",
    "sg:postcode":"33204",
    "sg:province":"Asturias",
    "wof:name":"Anton Sanchez Teodoro",
    "wof:placetype":"venue"
},
  "geometry": {"coordinates":[-5.6516361237,43.53540802],"type":"Point"}
}