{
  "type": "Feature",
  "properties": {
    "iso:country":"ES",
    "sg:address":"Carrer de Diputacio, 342",
    "sg:city":"Barcelona",
    "sg:orig_category":"Cine (producci\u00d3n, Realizaci\u00d3n)",
    "sg:phone":"+34 932 31 59 69",
    "sg:postcode":"08009",
    "sg:province":"Barcelona",
    "wof:name":"Little Films S.l.",
    "wof:placetype":"venue"
},
  "geometry": {"coordinates":[2.1750650406,41.3962287903],"type":"Point"}
}