{
  "type": "Feature",
  "properties": {
    "iso:country":"ES",
    "sg:address":"Avda Peris Y Valero, 14",
    "sg:city":"Valencia",
    "sg:orig_category":"Molduras, Junquillos, Listones Y Molduras Perforadas",
    "sg:phone":"+34 963 33 79 34",
    "sg:postcode":"46006",
    "sg:province":"Valencia",
    "wof:name":"Troiti\u00f1o Portela Maria Flor",
    "wof:placetype":"venue"
},
  "geometry": {"coordinates":[-0.3787640035,39.4553718567],"type":"Point"}
}