{
  "type": "Feature",
  "properties": {
    "iso:country":"ES",
    "sg:address":"Calle de Pozanos, S/n",
    "sg:city":"Burgos",
    "sg:orig_category":"Aislamiento El\u00c9ctrico",
    "sg:phone":"+34 947 22 05 16",
    "sg:postcode":"09006",
    "sg:province":"Burgos",
    "wof:name":"Espray Burgos S.l.",
    "wof:placetype":"venue"
},
  "geometry": {"coordinates":[-3.6882920265,42.3571472168],"type":"Point"}
}