{
  "type": "Feature",
  "properties": {
    "iso:country":"ES",
    "sg:address":"Luga Cortijo Turon, S/n",
    "sg:city":"Ardales",
    "sg:orig_category":"Aceites Y Grasas Alimentarias (fabricaci\u00d3n, Al Por Mayor)",
    "sg:phone":"+34 952 45 82 79",
    "sg:postcode":"29550",
    "sg:province":"M\u00e1laga",
    "wof:name":"Bravoliva S.l.",
    "wof:placetype":"venue"
},
  "geometry": {"coordinates":[-4.8453269005,36.88098526],"type":"Point"}
}