{
  "type": "Feature",
  "properties": {
    "addr:full":"Carrer de Muralla Del Carme, 6 Manresa Barcelona 08241",
    "addr:housenumber":"6",
    "addr:postcode":"08241",
    "addr:street":"Carrer De Muralla Del Carme",
    "iso:country":"ES",
    "sg:address":"Carrer de Muralla Del Carme, 6",
    "sg:city":"Manresa",
    "sg:orig_category":"Parques De Atracciones Y Centros De Esparcimiento",
    "sg:phone":"+34 938 72 83 16",
    "sg:postcode":"08241",
    "sg:province":"Barcelona",
    "wof:name":"Comallonga Muncunill Enric",
    "wof:placetype":"venue"
},
  "geometry": {"coordinates":[1.8256449699,41.7253684998],"type":"Point"}
}