{
  "type": "Feature",
  "properties": {
    "addr:full":"Carrer de Puig Del Ravell, 6 Martorell Barcelona 08760",
    "addr:housenumber":"6",
    "addr:postcode":"08760",
    "addr:street":"Carrer De Puig Del Ravell",
    "iso:country":"ES",
    "sg:address":"Carrer de Puig Del Ravell, 6",
    "sg:city":"Martorell",
    "sg:orig_category":"Ropa Para Se\u00d1oras (al Por Menor)",
    "sg:phone":"+34 937 74 32 95",
    "sg:postcode":"08760",
    "sg:province":"Barcelona",
    "wof:name":"Catizope S.l.",
    "wof:placetype":"venue"
},
  "geometry": {"coordinates":[1.9156329632,41.4783172607],"type":"Point"}
}