{
  "type": "Feature",
  "properties": {
    "addr:full":"Avda Cantabria, 32 Corrales Cantabria 39400",
    "addr:housenumber":"32",
    "addr:postcode":"39400",
    "addr:street":"Avda Cantabria",
    "iso:country":"ES",
    "sg:address":"Avda Cantabria, 32",
    "sg:city":"Corrales",
    "sg:orig_category":"Librer\u00cdas",
    "sg:phone":"+34 942 83 27 70",
    "sg:postcode":"39400",
    "sg:province":"Cantabria",
    "wof:name":"Fernandez Fernandez Maria Cruz",
    "wof:placetype":"venue"
},
  "geometry": {"coordinates":[-4.0689969063,43.2609825134],"type":"Point"}
}