{
  "type": "Feature",
  "properties": {
    "iso:country":"ES",
    "sg:address":"Santalla, 2",
    "sg:city":"Santalla",
    "sg:orig_category":"Producci\u00d3n, Venta De Productos De Agricultura Biol\u00d3gica",
    "sg:phone":"+34 982 15 61 49",
    "sg:postcode":"27712",
    "sg:province":"Lugo",
    "wof:name":"Fari\u00d1eiro Sat N 1049",
    "wof:placetype":"venue"
},
  "geometry": {"coordinates":[-7.0873880386,43.512096405],"type":"Point"}
}