{
  "type": "Feature",
  "properties": {
    "addr:full":"Calle de Dulcinea Del Toboso, 15 Miguelturra Ciudad Real 13170",
    "addr:housenumber":"15",
    "addr:postcode":"13170",
    "addr:street":"Calle De Dulcinea Del Toboso",
    "iso:country":"ES",
    "sg:address":"Calle de Dulcinea Del Toboso, 15",
    "sg:city":"Miguelturra",
    "sg:orig_category":"Escayola Y Productos De Escayola (fabricaci\u00d3n, Al Por Mayor)",
    "sg:phone":"+34 926 24 31 33",
    "sg:postcode":"13170",
    "sg:province":"Ciudad Real",
    "wof:name":"Chentouf  Hicham",
    "wof:placetype":"venue"
},
  "geometry": {"coordinates":[-3.8881764412,38.9607887268],"type":"Point"}
}