{
  "type": "Feature",
  "properties": {
    "addr:full":"Ctra Ecija-herrera, Km. 0059,2 Ecija Sevilla 41400",
    "addr:postcode":"41400",
    "addr:street":"Ctra Ecija-Herrera Km. 0059,2",
    "iso:country":"ES",
    "sg:address":"Ctra Ecija-herrera, Km. 0059,2",
    "sg:city":"Ecija",
    "sg:orig_category":"Fabricaci\u00d3n De Muebles",
    "sg:phone":"+34 955 90 38 02",
    "sg:postcode":"41400",
    "sg:province":"Sevilla",
    "wof:name":"Xilo Decoracion Y Mobiliario S.l.",
    "wof:placetype":"venue"
},
  "geometry": {"coordinates":[-5.103656292,37.7027549744],"type":"Point"}
}