{
  "type": "Feature",
  "properties": {
    "addr:full":"Avda Salinas, S/n Laguna Duero Valladolid 47140",
    "addr:housenumber":"s / n",
    "addr:postcode":"47140",
    "addr:street":"Avda Salinas",
    "iso:country":"ES",
    "sg:address":"Avda Salinas, S/n",
    "sg:city":"Laguna Duero",
    "sg:orig_category":"Asociaciones Y Clubs Deportivos",
    "sg:phone":"+34 983 54 52 56",
    "sg:postcode":"47140",
    "sg:province":"Valladolid",
    "sg:website":"www.clubtorrelago.com",
    "wof:name":"Promotora Club Social Torrelago S.a.",
    "wof:placetype":"venue"
},
  "geometry": {"coordinates":[-4.7216892242,41.5881195068],"type":"Point"}
}