{
  "type": "Feature",
  "properties": {
    "addr:full":"Calle de Damas, 2 Riaza Segovia 40500",
    "addr:housenumber":"2",
    "addr:postcode":"40500",
    "addr:street":"Calle De Damas",
    "iso:country":"ES",
    "sg:address":"Calle de Damas, 2",
    "sg:city":"Riaza",
    "sg:orig_category":"Cervecer\u00cdas",
    "sg:phone":"+34 921 55 11 96",
    "sg:postcode":"40500",
    "sg:province":"Segovia",
    "wof:name":"Martin Garcia Maria Oliva",
    "wof:placetype":"venue"
},
  "geometry": {"coordinates":[-3.4785454273,41.2770233154],"type":"Point"}
}