{
  "type": "Feature",
  "properties": {
    "iso:country":"ES",
    "sg:address":"Avda Reconquista, 12",
    "sg:city":"Toledo",
    "sg:orig_category":"Panader\u00cdas, Panader\u00cdas",
    "sg:phone":"+34 925 22 02 27",
    "sg:postcode":"45004",
    "sg:province":"Toledo",
    "wof:name":"Ramos Velasco Arsenio",
    "wof:placetype":"venue"
},
  "geometry": {"coordinates":[-4.0281457901,39.8652458191],"type":"Point"}
}