{
  "type": "Feature",
  "properties": {
    "addr:full":"Avda Infantes (los), 85 Santander Cantabria 39005",
    "addr:housenumber":"85",
    "addr:postcode":"39005",
    "addr:street":"Avda Infantes Los",
    "iso:country":"ES",
    "sg:address":"Avda Infantes (los), 85",
    "sg:city":"Santander",
    "sg:orig_category":"M\u00c9dicos: Cirug\u00cda Pl\u00c1stica, Reconstructiva Y Est\u00c9tica",
    "sg:phone":"+34 942 37 08 19",
    "sg:postcode":"39005",
    "sg:province":"Cantabria",
    "wof:name":"Iglesias Marques Manuel",
    "wof:placetype":"venue"
},
  "geometry": {"coordinates":[-3.7877988815,43.472328186],"type":"Point"}
}