{
  "type": "Feature",
  "properties": {
    "addr:full":"Carrer de Llacuna, 1 Barcelona Barcelona 08005",
    "addr:housenumber":"1",
    "addr:postcode":"08005",
    "addr:street":"Carrer De Llacuna",
    "iso:country":"ES",
    "sg:address":"Carrer de Llacuna, 1",
    "sg:city":"Barcelona",
    "sg:orig_category":"Suministros Para Hoteles",
    "sg:phone":"+34 932 25 43 66",
    "sg:postcode":"08005",
    "sg:province":"Barcelona",
    "wof:name":"Bacupal Institucional S.l.",
    "wof:placetype":"venue"
},
  "geometry": {"coordinates":[2.203275919,41.3976783752],"type":"Point"}
}