{
  "type": "Feature",
  "properties": {
    "iso:country":"ES",
    "sg:address":"Calle de Ruiz Romero, 11",
    "sg:city":"Jaen",
    "sg:orig_category":"Tapicer\u00cdas",
    "sg:phone":"+34 953 24 21 01",
    "sg:postcode":"23003",
    "sg:province":"Ja\u00e9n",
    "wof:name":"Martinez Navarro Maria Teresa",
    "wof:placetype":"venue"
},
  "geometry": {"coordinates":[-3.7899889946,37.7687759399],"type":"Point"}
}