{
  "type": "Feature",
  "properties": {
    "iso:country":"ES",
    "sg:address":"Luga Pi\u00d1eira Seca, 22",
    "sg:city":"Pi\u00e7eira Seca",
    "sg:orig_category":"Mayoristas E Intermediarios En Alcoholes",
    "sg:phone":"+34 988 45 44 03",
    "sg:postcode":"32631",
    "sg:province":"Ourense",
    "wof:name":"Rodriguez Diaz Jose Antonio",
    "wof:placetype":"venue"
},
  "geometry": {"coordinates":[-7.60415411,42.0871887207],"type":"Point"}
}