{
  "type": "Feature",
  "properties": {
    "addr:full":"Calle de Margaritas, 29 Madrid Madrid 28039",
    "addr:housenumber":"29",
    "addr:postcode":"madrid;28039",
    "addr:street":"Calle De Margaritas",
    "iso:country":"ES",
    "sg:address":"Calle de Margaritas, 29",
    "sg:city":"Madrid",
    "sg:orig_category":"Teatros Y Salas De Espect\u00c1culos",
    "sg:phone":"+34 914 50 54 46",
    "sg:postcode":"28039",
    "sg:province":"Madrid",
    "wof:name":"La Barraca Teatro Popular S.coop.ltda.",
    "wof:placetype":"venue"
},
  "geometry": {"coordinates":[-3.7076480389,40.4582595825],"type":"Point"}
}