{
  "type": "Feature",
  "properties": {
    "addr:full":"Ctra. Villanueva, Km. 0100,7 Don Benito Badajoz 06400",
    "addr:postcode":"06400",
    "addr:street":"Ctra. Villanueva Km. 0100,7",
    "iso:country":"ES",
    "sg:address":"Ctra. Villanueva, Km. 0100,7",
    "sg:city":"Don Benito",
    "sg:orig_category":"Venta, Montaje De Neum\u00c1ticos",
    "sg:phone":"+34 924 81 13 82",
    "sg:postcode":"06400",
    "sg:province":"Badajoz",
    "wof:name":"Autodisco S. A.",
    "wof:placetype":"venue"
},
  "geometry": {"coordinates":[-5.8413972855,38.9631881714],"type":"Point"}
}