{
  "type": "Feature",
  "properties": {
    "iso:country":"ES",
    "sg:address":"Alam Recalde, 7",
    "sg:city":"Bilbao",
    "sg:orig_category":"Inform\u00c1tica (estudios, Servicios, Asesor\u00cda, Formaci\u00d3n)",
    "sg:phone":"+34 902 19 63 29",
    "sg:postcode":"48009",
    "sg:province":"Vizcaya",
    "wof:name":"Tecnologia Contable Aplicada S.l.",
    "wof:placetype":"venue"
},
  "geometry": {"coordinates":[-2.9330921173,43.2670898438],"type":"Point"}
}