{
  "type": "Feature",
  "properties": {
    "iso:country":"ES",
    "sg:address":"Calle de Cura, 2",
    "sg:city":"Nombela",
    "sg:orig_category":"Iglesia Cat\u00d3lica",
    "sg:phone":"+34 925 79 20 17",
    "sg:postcode":"45917",
    "sg:province":"Toledo",
    "wof:name":"Parroquia De Nuestra Se\u00f1ora De La Asuncion",
    "wof:placetype":"venue"
},
  "geometry": {"coordinates":[-4.5024256706,40.1561393738],"type":"Point"}
}