{
  "type": "Feature",
  "properties": {
    "addr:full":"A Moura, 38 Moura A Coru\u00f1a 15010",
    "addr:housenumber":"38",
    "addr:postcode":"15010",
    "addr:street":"Moura;Corun\u0303A",
    "iso:country":"ES",
    "sg:address":"A Moura, 38",
    "sg:city":"Moura",
    "sg:orig_category":"Maquinaria Para Industrias Diversas",
    "sg:phone":"+34 981 27 74 00",
    "sg:postcode":"15010",
    "sg:province":"A Coru\u00f1a",
    "wof:name":"Talleres De Maquinaria Industrial S. A.",
    "wof:placetype":"venue"
},
  "geometry": {"coordinates":[-8.3964595795,43.3701095581],"type":"Point"}
}