{
  "type": "Feature",
  "properties": {
    "addr:full":"Calle de Pintor Velazquez (del), 6 Mostoles Madrid 28932",
    "addr:housenumber":"6",
    "addr:postcode":"28932",
    "addr:street":"Calle De Pintor Velazquez Del",
    "iso:country":"ES",
    "sg:address":"Calle de Pintor Velazquez (del), 6",
    "sg:city":"Mostoles",
    "sg:orig_category":"Molduras, Junquillos, Listones Y Molduras Perforadas",
    "sg:phone":"+34 916 13 74 51",
    "sg:postcode":"28932",
    "sg:province":"Madrid",
    "wof:name":"Abad Gonzalo Julian",
    "wof:placetype":"venue"
},
  "geometry": {"coordinates":[-3.863204,40.333012],"type":"Point"}
}