{
  "type": "Feature",
  "properties": {
    "iso:country":"ES",
    "sg:address":"Calle de Real De Burgos, 20",
    "sg:city":"Valladolid",
    "sg:orig_category":"Caf\u00c9s, Bares, Cervecer\u00cdas",
    "sg:phone":"+34 983 25 54 33",
    "sg:postcode":"47011",
    "sg:province":"Valladolid",
    "wof:name":"Broco Guerrero Antonio",
    "wof:placetype":"venue"
},
  "geometry": {"coordinates":[-4.7188901901,41.6587677002],"type":"Point"}
}