{
  "type": "Feature",
  "properties": {
    "iso:country":"ES",
    "sg:address":"Rua Pino, 58",
    "sg:city":"Vigo",
    "sg:orig_category":"Peluqueros: De Se\u00d1oras",
    "sg:phone":"+34 986 37 06 72",
    "sg:postcode":"36206",
    "sg:province":"Pontevedra",
    "wof:name":"Rodriguez Prado Carmen",
    "wof:placetype":"venue"
},
  "geometry": {"coordinates":[-8.7071352005,42.2341537476],"type":"Point"}
}