{
  "type": "Feature",
  "properties": {
    "addr:full":"Calle de Marques De Comillas, 14 Almeria Almer\u00eda 04004",
    "addr:housenumber":"14",
    "addr:postcode":"04004",
    "addr:street":"Calle De Marques De Comillas",
    "iso:country":"ES",
    "sg:address":"Calle de Marques De Comillas, 14",
    "sg:city":"Almeria",
    "sg:orig_category":"Abogados",
    "sg:phone":"+34 950 23 12 23",
    "sg:postcode":"04004",
    "sg:province":"Almer\u00eda",
    "wof:name":"Lozano De Cruz Miguel Angel",
    "wof:placetype":"venue"
},
  "geometry": {"coordinates":[-2.4622581005,36.8368492126],"type":"Point"}
}