{
  "type": "Feature",
  "properties": {
    "addr:full":"Calle de Jose Antonio (de), 45 Boadilla Del Monte Madrid 28660",
    "addr:housenumber":"45",
    "addr:postcode":"28660",
    "addr:street":"Calle De Jose Antonio De",
    "iso:country":"ES",
    "sg:address":"Calle de Jose Antonio (de), 45",
    "sg:city":"Boadilla Del Monte",
    "sg:orig_category":"Estancos",
    "sg:phone":"+34 916 32 06 07",
    "sg:postcode":"28660",
    "sg:province":"Madrid",
    "wof:name":"Sevilla Nicolas Angeles",
    "wof:placetype":"venue"
},
  "geometry": {"coordinates":[-3.8784489632,40.406791687],"type":"Point"}
}