{
  "type": "Feature",
  "properties": {
    "addr:full":"Calle de Magdalena, 36 Madrid Madrid 28012",
    "addr:housenumber":"36",
    "addr:postcode":"madrid;28012",
    "addr:street":"Calle De Magdalena",
    "iso:country":"ES",
    "sg:address":"Calle de Magdalena, 36",
    "sg:city":"Madrid",
    "sg:orig_category":"Arquitectos",
    "sg:phone":"+34 913 69 16 73",
    "sg:postcode":"28012",
    "sg:province":"Madrid",
    "wof:name":"Diaz Turleque Juan",
    "wof:placetype":"venue"
},
  "geometry": {"coordinates":[-3.7000179291,40.4122314453],"type":"Point"}
}