{
  "type": "Feature",
  "properties": {
    "iso:country":"ES",
    "sg:address":"Calle de Jose Pellicer, 12",
    "sg:city":"Zaragoza",
    "sg:orig_category":"Reposter\u00cdas",
    "sg:phone":"+34 976 25 95 01",
    "sg:postcode":"50007",
    "sg:province":"Zaragoza",
    "wof:name":"Horno Jucar S.l.",
    "wof:placetype":"venue"
},
  "geometry": {"coordinates":[-0.879019022,41.6380157471],"type":"Point"}
}