{
  "type": "Feature",
  "properties": {
    "addr:full":"Avda Malaga (de), 9 Yunquera Henares Guadalajara 19210",
    "addr:housenumber":"9",
    "addr:postcode":"19210",
    "addr:street":"Avda Malaga De",
    "iso:country":"ES",
    "sg:address":"Avda Malaga (de), 9",
    "sg:city":"Yunquera Henares",
    "sg:orig_category":"Seguridad En El Trabajo Y Prevenci\u00d3n De Riesgos Laborales",
    "sg:phone":"+34 949 33 10 61",
    "sg:postcode":"19210",
    "sg:province":"Guadalajara",
    "wof:name":"Sanchez Perez Reyes",
    "wof:placetype":"venue"
},
  "geometry": {"coordinates":[-3.1683399677,40.7556266785],"type":"Point"}
}