{
  "type": "Feature",
  "properties": {
    "addr:full":"Avda Andalucia, 84 Cadiz C\u00e1diz 11008",
    "addr:housenumber":"84",
    "addr:postcode":"11008",
    "addr:street":"Avda Andalucia",
    "iso:country":"ES",
    "sg:address":"Avda Andalucia, 84",
    "sg:city":"Cadiz",
    "sg:orig_category":"Sociedades, Compa\u00d1\u00cdas Aseguradoras",
    "sg:phone":"+34 956 26 00 05",
    "sg:postcode":"11008",
    "sg:province":"C\u00e1diz",
    "wof:name":"Mutua General Seguros",
    "wof:placetype":"venue"
},
  "geometry": {"coordinates":[-6.2818231583,36.5145835876],"type":"Point"}
}