{
  "type": "Feature",
  "properties": {
    "addr:full":"Calle de General Riera, 64 Palma Islas Baleares 07010",
    "addr:housenumber":"64",
    "addr:postcode":"07010",
    "addr:street":"Calle De General Riera",
    "iso:country":"ES",
    "sg:address":"Calle de General Riera, 64",
    "sg:city":"Palma",
    "sg:orig_category":"Textil",
    "sg:phone":"+34 971 20 19 72",
    "sg:postcode":"07010",
    "sg:province":"Islas Baleares",
    "wof:name":"Poniente C.b.",
    "wof:placetype":"venue"
},
  "geometry": {"coordinates":[2.6465139389,39.5843811035],"type":"Point"}
}