{
  "type": "Feature",
  "properties": {
    "addr:full":"Ctra Cambrils, Km. 0004,5 Reus Tarragona 43206",
    "addr:postcode":"43206",
    "addr:street":"Ctra Cambrils Km. 0004,5",
    "iso:country":"ES",
    "sg:address":"Ctra Cambrils, Km. 0004,5",
    "sg:city":"Reus",
    "sg:orig_category":"M\u00c1quinas De Jardiner\u00cda",
    "sg:phone":"+34 977 12 07 59",
    "sg:postcode":"43206",
    "sg:province":"Tarragona",
    "wof:name":"Plantarium Center S.l.",
    "wof:placetype":"venue"
},
  "geometry": {"coordinates":[1.1039400101,41.1745300293],"type":"Point"}
}