{
  "type": "Feature",
  "properties": {
    "iso:country":"ES",
    "sg:address":"Rua Valdecorbos, 28",
    "sg:city":"Pontevedra",
    "sg:orig_category":"Empresarios",
    "sg:phone":"+34 986 85 61 73",
    "sg:postcode":"36161",
    "sg:province":"Pontevedra",
    "wof:name":"Prado Cortizo Jose",
    "wof:placetype":"venue"
},
  "geometry": {"coordinates":[-8.5811071396,42.4439888],"type":"Point"}
}