{
  "type": "Feature",
  "properties": {
    "iso:country":"ES",
    "sg:address":"Avda Galicia, 5",
    "sg:city":"Cambados",
    "sg:orig_category":"Ambulancias",
    "sg:phone":"+34 986 54 34 34",
    "sg:postcode":"36630",
    "sg:province":"Pontevedra",
    "wof:name":"Ambulancias Do Salnes S.l.",
    "wof:placetype":"venue"
},
  "geometry": {"coordinates":[-8.8150186539,42.5152320862],"type":"Point"}
}