{
  "type": "Feature",
  "properties": {
    "iso:country":"ES",
    "sg:address":"Calle de Encarnacion, 18",
    "sg:city":"Trujillo",
    "sg:orig_category":"Abogados",
    "sg:phone":"+34 927 32 15 68",
    "sg:postcode":"10200",
    "sg:province":"C\u00e1ceres",
    "wof:name":"Martin Murillo Maria Dolores",
    "wof:placetype":"venue"
},
  "geometry": {"coordinates":[-5.8808188438,39.4573440552],"type":"Point"}
}