{
  "type": "Feature",
  "properties": {
    "iso:country":"ES",
    "sg:address":"Calle de Algemesi, 47",
    "sg:city":"Madrid",
    "sg:orig_category":"Peluqueros: De Se\u00d1oras",
    "sg:phone":"+34 913 29 12 56",
    "sg:postcode":"28042",
    "sg:province":"Madrid",
    "wof:name":"Garri Pel S.l",
    "wof:placetype":"venue"
},
  "geometry": {"coordinates":[-3.5822954178,40.4724998474],"type":"Point"}
}