{
  "type": "Feature",
  "properties": {
    "iso:country":"ES",
    "sg:address":"Calle de Alicante, 9",
    "sg:city":"Segorbe",
    "sg:orig_category":"Arquitectos",
    "sg:phone":"+34 964 71 11 78",
    "sg:postcode":"12400",
    "sg:province":"Castell\u00f3n",
    "wof:name":"Gpt Oficina Tecnica S.l Unip.",
    "wof:placetype":"venue"
},
  "geometry": {"coordinates":[-0.4876640141,39.8496818542],"type":"Point"}
}