{
  "type": "Feature",
  "properties": {
    "iso:country":"ES",
    "sg:address":"Avda Juan Carlos I, S/n",
    "sg:city":"Cristianos",
    "sg:orig_category":"Agentes Generales De Seguros",
    "sg:phone":"+34 922 79 34 53",
    "sg:postcode":"38650",
    "sg:province":"Santa Cruz De Tenerife",
    "wof:name":"Seguros Israel Cabrera S.l.",
    "wof:placetype":"venue"
},
  "geometry": {"coordinates":[-16.7118148804,28.0564250946],"type":"Point"}
}