{
  "type": "Feature",
  "properties": {
    "iso:country":"ES",
    "sg:address":"Calle de Don Daniel, 10",
    "sg:city":"Santander",
    "sg:orig_category":"Asesor\u00cdas Y Estudios Financieros",
    "sg:phone":"+34 942 27 26 71",
    "sg:postcode":"39004",
    "sg:province":"Cantabria",
    "wof:name":"Van Den Eynde Ballesteros Victor Carlos",
    "wof:placetype":"venue"
},
  "geometry": {"coordinates":[-3.7863531113,43.4648551941],"type":"Point"}
}