{
  "type": "Feature",
  "properties": {
    "addr:full":"Calle de Portugal, 33 Fuenlabrada Madrid 28943",
    "addr:housenumber":"33",
    "addr:postcode":"28943",
    "addr:street":"Calle De Portugal",
    "iso:country":"ES",
    "sg:address":"Calle de Portugal, 33",
    "sg:city":"Fuenlabrada",
    "sg:orig_category":"Ropa Y Art\u00cdculos Pre",
    "sg:phone":"+34 916 07 01 24",
    "sg:postcode":"28943",
    "sg:province":"Madrid",
    "wof:name":"Mendieta Turcios Elena",
    "wof:placetype":"venue"
},
  "geometry": {"coordinates":[-3.8092150688,40.2818031311],"type":"Point"}
}