{
  "type": "Feature",
  "properties": {
    "addr:full":"Avda Emilio Lemos, 7 Sevilla Sevilla 41020",
    "addr:housenumber":"7",
    "addr:postcode":"41020",
    "addr:street":"Avda Emilio Lemos",
    "iso:country":"ES",
    "sg:address":"Avda Emilio Lemos, 7",
    "sg:city":"Sevilla",
    "sg:orig_category":"Arquitectos",
    "sg:phone":"+34 954 40 49 09",
    "sg:postcode":"41020",
    "sg:province":"Sevilla",
    "wof:name":"Medina De La Vega Alfonso",
    "wof:placetype":"venue"
},
  "geometry": {"coordinates":[-5.9125590324,37.4064598083],"type":"Point"}
}