{
  "type": "Feature",
  "properties": {
    "addr:full":"Plaz Poniente, 5 Valladolid Valladolid 47003",
    "addr:housenumber":"5",
    "addr:postcode":"47003",
    "addr:street":"Plaz Poniente",
    "iso:country":"ES",
    "sg:address":"Plaz Poniente, 5",
    "sg:city":"Valladolid",
    "sg:orig_category":"Florister\u00cdas",
    "sg:phone":"+34 983 37 06 62",
    "sg:postcode":"47003",
    "sg:province":"Valladolid",
    "wof:name":"Gimenez Alonso Cristina",
    "wof:placetype":"venue"
},
  "geometry": {"coordinates":[-4.7314209938,41.6527099609],"type":"Point"}
}