{
  "type": "Feature",
  "properties": {
    "addr:full":"Trss Vall (la), 5 Aitona Lleida 25182",
    "addr:housenumber":"5",
    "addr:postcode":"25182",
    "iso:country":"ES",
    "sg:address":"Trss Vall (la), 5",
    "sg:city":"Aitona",
    "sg:orig_category":"Pescader\u00cdas (al Por Menor)",
    "sg:phone":"+34 973 79 45 04",
    "sg:postcode":"25182",
    "sg:province":"Lleida",
    "wof:name":"Lozano Chica Antoni",
    "wof:placetype":"venue"
},
  "geometry": {"coordinates":[0.5191699862,41.4816703796],"type":"Point"}
}