{
  "type": "Feature",
  "properties": {
    "addr:full":"Calle de Profesor Tierno Galvan, 45 Camas Sevilla 41900",
    "addr:housenumber":"45",
    "addr:postcode":"41900",
    "addr:street":"Calle De Profesor Tierno Galvan",
    "iso:country":"ES",
    "sg:address":"Calle de Profesor Tierno Galvan, 45",
    "sg:city":"Camas",
    "sg:orig_category":"Arquitectos",
    "sg:phone":"+34 954 39 60 71",
    "sg:postcode":"41900",
    "sg:province":"Sevilla",
    "wof:name":"Zapata Pedre\u00f1o Daniel",
    "wof:placetype":"venue"
},
  "geometry": {"coordinates":[-6.0403141975,37.3816299438],"type":"Point"}
}