{
  "type": "Feature",
  "properties": {
    "addr:full":"Ctra San Gregorio, Km. 0001,0 Tiemblo \u00c1vila 05270",
    "addr:postcode":"05270",
    "addr:street":"Ctra San Gregorio Km. 0001,0 Tiemblo A\u0301Vila",
    "iso:country":"ES",
    "sg:address":"Ctra San Gregorio, Km. 0001,0",
    "sg:city":"Tiemblo",
    "sg:orig_category":"Cerrajer\u00cda, Ferrallista",
    "sg:phone":"+34 918 62 70 33",
    "sg:postcode":"05270",
    "sg:province":"\u00c1vila",
    "wof:name":"Enamorado Navas Isidoro",
    "wof:placetype":"venue"
},
  "geometry": {"coordinates":[-4.5002861023,40.4145774841],"type":"Point"}
}