{
  "type": "Feature",
  "properties": {
    "addr:full":"Calle de Boticas, 4 Mula Murcia 30170",
    "addr:housenumber":"4",
    "addr:postcode":"30170",
    "addr:street":"Calle De Boticas",
    "iso:country":"ES",
    "sg:address":"Calle de Boticas, 4",
    "sg:city":"Mula",
    "sg:orig_category":"Electrodom\u00c9sticos (al Por Menor)",
    "sg:phone":"+34 968 66 01 11",
    "sg:postcode":"30170",
    "sg:province":"Murcia",
    "wof:name":"Lopez Herrera Fausto",
    "wof:placetype":"venue"
},
  "geometry": {"coordinates":[-1.4911984205,38.0414428711],"type":"Point"}
}