{
  "type": "Feature",
  "properties": {
    "addr:full":"Ptge Penedes, S/n Sant Feliu Llobregat Barcelona 08980",
    "addr:housenumber":"s / n",
    "addr:postcode":"08980",
    "addr:street":"Ptge Penedes",
    "iso:country":"ES",
    "sg:address":"Ptge Penedes, S/n",
    "sg:city":"Sant Feliu Llobregat",
    "sg:orig_category":"Ense\u00d1anza Agr\u00cdcola",
    "sg:phone":"+34 936 85 24 98",
    "sg:postcode":"08980",
    "sg:province":"Barcelona",
    "wof:name":"Minyons Escoltes-guies Sant Jordi De Cat",
    "wof:placetype":"venue"
},
  "geometry": {"coordinates":[2.0460629463,41.3805427551],"type":"Point"}
}