{
  "type": "Feature",
  "properties": {
    "iso:country":"ES",
    "sg:address":"Avda Lepant De, 11",
    "sg:city":"Benitachell",
    "sg:orig_category":"Librer\u00cdas",
    "sg:phone":"+34 966 49 33 48",
    "sg:postcode":"03726",
    "sg:province":"Alicante",
    "wof:name":"Comella Rovira Miguel Antonio",
    "wof:placetype":"venue"
},
  "geometry": {"coordinates":[0.1413500011,38.7316513062],"type":"Point"}
}