{
  "type": "Feature",
  "properties": {
    "iso:country":"ES",
    "sg:address":"Barr Goitondo, S/n",
    "sg:city":"Berano Nagusi",
    "sg:orig_category":"Trabajos De Soldaduras",
    "sg:phone":"+34 943 17 15 69",
    "sg:postcode":"48269",
    "sg:province":"Vizcaya",
    "wof:name":"Cid Perez Jose",
    "wof:placetype":"venue"
},
  "geometry": {"coordinates":[-2.5300109386,43.1897888184],"type":"Point"}
}