{
  "type": "Feature",
  "properties": {
    "addr:full":"Pol Ind Quiebracostilla, S/n Baena C\u00f3rdoba 14850",
    "addr:housenumber":"s",
    "addr:postcode":"14850",
    "addr:street":"/ N;Co\u0301Rdoba",
    "iso:country":"ES",
    "sg:address":"Pol Ind Quiebracostilla, S/n",
    "sg:city":"Baena",
    "sg:orig_category":"Empresarios",
    "sg:phone":"+34 957 67 00 22",
    "sg:postcode":"14850",
    "sg:province":"C\u00f3rdoba",
    "wof:name":"Fundacion Patrimonio Comunal Olivarero",
    "wof:placetype":"venue"
},
  "geometry": {"coordinates":[-4.323964119,37.6170043945],"type":"Point"}
}