{
  "type": "Feature",
  "properties": {
    "iso:country":"ES",
    "sg:address":"Calle de Valdivieso, 2",
    "sg:city":"Madrid",
    "sg:orig_category":"Peluquer\u00cdas, Peluquer\u00cda Mixta",
    "sg:phone":"+34 913 57 53 59",
    "sg:postcode":"28023",
    "sg:province":"Madrid",
    "sg:website":"www.rizos.es",
    "wof:name":"Damas De Azul Peluqueros S.l.",
    "wof:placetype":"venue"
},
  "geometry": {"coordinates":[-3.7804260254,40.4587364197],"type":"Point"}
}