{
  "type": "Feature",
  "properties": {
    "addr:full":"Rua Galicia (de), 41 Vilalba Lugo 27800",
    "addr:housenumber":"41",
    "addr:postcode":"27800",
    "addr:street":"Rua Galicia De",
    "iso:country":"ES",
    "sg:address":"Rua Galicia (de), 41",
    "sg:city":"Vilalba",
    "sg:orig_category":"Fabricaci\u00d3n De Productos Textiles Sin Tejer",
    "sg:phone":"+34 982 51 02 17",
    "sg:postcode":"27800",
    "sg:province":"Lugo",
    "wof:name":"Ramudo Tenreiro Maria Julia",
    "wof:placetype":"venue"
},
  "geometry": {"coordinates":[-7.68120718,43.295879364],"type":"Point"}
}