{
  "type": "Feature",
  "properties": {
    "iso:country":"ES",
    "sg:address":"Grup San Diego, 4",
    "sg:city":"Sevilla",
    "sg:orig_category":"Mercer\u00cda, Lencer\u00cda (al Por Menor)",
    "sg:phone":"+34 954 95 36 16",
    "sg:postcode":"41008",
    "sg:province":"Sevilla",
    "wof:name":"Navarro Palacios Manuela",
    "wof:placetype":"venue"
},
  "geometry": {"coordinates":[-5.9673390388,37.4151115417],"type":"Point"}
}