{
  "type": "Feature",
  "properties": {
    "addr:full":"Calle de Fray Luis De Leon, 8 Novelda Alicante 03660",
    "addr:housenumber":"8",
    "addr:postcode":"03660",
    "addr:street":"Calle De Fray Luis De Leon",
    "iso:country":"ES",
    "sg:address":"Calle de Fray Luis De Leon, 8",
    "sg:city":"Novelda",
    "sg:orig_category":"Importaci\u00d3n",
    "sg:phone":"+34 965 60 75 22",
    "sg:postcode":"03660",
    "sg:province":"Alicante",
    "wof:name":"Marmoles Sotomar S.l",
    "wof:placetype":"venue"
},
  "geometry": {"coordinates":[-0.7663279176,38.386554718],"type":"Point"}
}