{
  "type": "Feature",
  "properties": {
    "iso:country":"ES",
    "sg:address":"Calle de Bodas Reales, 7",
    "sg:city":"Soria",
    "sg:orig_category":"Asociaciones Y Clubs Deportivos",
    "sg:phone":"+34 975 22 50 80",
    "sg:postcode":"42003",
    "sg:province":"Soria",
    "wof:name":"Galvez Lopez Angel",
    "wof:placetype":"venue"
},
  "geometry": {"coordinates":[-2.4686305523,41.762096405],"type":"Point"}
}