{
  "type": "Feature",
  "properties": {
    "addr:full":"Vte Mtnez Colomer, 8 Benissa Alicante 03720",
    "addr:housenumber":"8",
    "addr:postcode":"03720",
    "addr:street":"Colomer",
    "iso:country":"ES",
    "sg:address":"Vte Mtnez Colomer, 8",
    "sg:city":"Benissa",
    "sg:orig_category":"Mec\u00c1nico Del Autom\u00d3vil",
    "sg:phone":"+34 965 73 02 39",
    "sg:postcode":"03720",
    "sg:province":"Alicante",
    "wof:name":"Taller Sendra Cuello S.l.",
    "wof:placetype":"venue"
},
  "geometry": {"coordinates":[0.050774999,38.7144584656],"type":"Point"}
}