{
  "type": "Feature",
  "properties": {
    "addr:full":"Carr Conde Berbedel, 12 Betera Valencia 46117",
    "addr:housenumber":"12",
    "addr:postcode":"46117",
    "addr:street":"Carr Conde Berbedel",
    "iso:country":"ES",
    "sg:address":"Carr Conde Berbedel, 12",
    "sg:city":"Betera",
    "sg:orig_category":"Confecci\u00d3n (fabricaci\u00d3n, Al Por Mayor)",
    "sg:phone":"+34 961 60 05 29",
    "sg:postcode":"46117",
    "sg:province":"Valencia",
    "wof:name":"Aloy Martinez Jose Manuel",
    "wof:placetype":"venue"
},
  "geometry": {"coordinates":[-0.4639647901,39.5915031433],"type":"Point"}
}