{
  "type": "Feature",
  "properties": {
    "addr:full":"Calle de Puerto Del Suebe, 8 Madrid Madrid 28038",
    "addr:housenumber":"8",
    "addr:postcode":"madrid;28038",
    "addr:street":"Calle De Puerto Del Suebe",
    "iso:country":"ES",
    "sg:address":"Calle de Puerto Del Suebe, 8",
    "sg:city":"Madrid",
    "sg:orig_category":"Tapicer\u00cdas",
    "sg:phone":"+34 914 78 59 91",
    "sg:postcode":"28038",
    "sg:province":"Madrid",
    "wof:name":"Toro Martin Antonio",
    "wof:placetype":"venue"
},
  "geometry": {"coordinates":[-3.6643941402,40.39635849],"type":"Point"}
}