{
  "type": "Feature",
  "properties": {
    "iso:country":"ES",
    "sg:address":"Prje Canalon, S/n",
    "sg:city":"Camporrobles",
    "sg:orig_category":"Poller\u00cda Y Caza (al Por Menor)",
    "sg:phone":"+34 962 13 91 52",
    "sg:postcode":"46330",
    "sg:province":"Valencia",
    "wof:name":"Mata Pardo Francisco Javier",
    "wof:placetype":"venue"
},
  "geometry": {"coordinates":[-1.4011189938,39.6466217041],"type":"Point"}
}