{
  "type": "Feature",
  "properties": {
    "addr:full":"Carrer de Muntaner, 89 Barcelona Barcelona 08036",
    "addr:housenumber":"89",
    "addr:postcode":"08036",
    "addr:street":"Carrer De Muntaner",
    "iso:country":"ES",
    "sg:address":"Carrer de Muntaner, 89",
    "sg:city":"Barcelona",
    "sg:orig_category":"Institutos De Belleza",
    "sg:phone":"+34 934 54 69 16",
    "sg:postcode":"08036",
    "sg:province":"Barcelona",
    "sg:website":"www.fhysiomins.net",
    "wof:name":"Slim Balance Center 2 Sl",
    "wof:placetype":"venue"
},
  "geometry": {"coordinates":[2.1568620205,41.3883590698],"type":"Point"}
}