{
  "type": "Feature",
  "properties": {
    "addr:full":"Avda Hermanos Bou, 18 Castellon Castell\u00f3n 12003",
    "addr:housenumber":"18",
    "addr:postcode":"12003",
    "addr:street":"Avda Hermanos Bou",
    "iso:country":"ES",
    "sg:address":"Avda Hermanos Bou, 18",
    "sg:city":"Castellon",
    "sg:orig_category":"Agentes, Concesionarios Y Sucursales De Veh\u00cdculos",
    "sg:phone":"+34 964 22 32 12",
    "sg:postcode":"12003",
    "sg:province":"Castell\u00f3n",
    "sg:website":"www.cobelsa.com",
    "wof:name":"Cobelsa S. A.",
    "wof:placetype":"venue"
},
  "geometry": {"coordinates":[-0.0324250013,39.9832687378],"type":"Point"}
}