{
  "type": "Feature",
  "properties": {
    "iso:country":"ES",
    "sg:address":"Carrer de Joan Tuto, 3",
    "sg:city":"Mataro",
    "sg:orig_category":"Hilaturas (fibras Naturales Diversas)",
    "sg:phone":"+34 937 96 04 22",
    "sg:postcode":"08304",
    "sg:province":"Barcelona",
    "wof:name":"Pe\u00f1a Morales Diego",
    "wof:placetype":"venue"
},
  "geometry": {"coordinates":[2.4474699497,41.550907135],"type":"Point"}
}