{
  "type": "Feature",
  "properties": {
    "iso:country":"ES",
    "sg:address":"Cra. Martorell Terrassa, Km. 0005,0",
    "sg:city":"Castellbisbal",
    "sg:orig_category":"Distribuci\u00d3n De Petr\u00d3leo Y Derivados",
    "sg:phone":"+34 937 74 05 35",
    "sg:postcode":"08755",
    "sg:province":"Barcelona",
    "wof:name":"Adestased S.l.",
    "wof:placetype":"venue"
},
  "geometry": {"coordinates":[1.968560338,41.5049514771],"type":"Point"}
}