{
  "type": "Feature",
  "properties": {
    "iso:country":"ES",
    "sg:address":"Rua Doutor Teixeiro (do), 10",
    "sg:city":"Santiago De Compostela",
    "sg:orig_category":"Abogados",
    "sg:phone":"+34 981 56 69 32",
    "sg:postcode":"15701",
    "sg:province":"A Coru\u00f1a",
    "wof:name":"Vazquez Tu\u00f1as Eva Maria",
    "wof:placetype":"venue"
},
  "geometry": {"coordinates":[-8.5452480316,42.8753585815],"type":"Point"}
}