{
  "type": "Feature",
  "properties": {
    "iso:country":"ES",
    "sg:address":"Ctra Nal 340, Km. 0175,0",
    "sg:city":"Bellus",
    "sg:orig_category":"Explotaci\u00d3n De Canteras",
    "sg:phone":"+34 962 13 20 05",
    "sg:postcode":"46839",
    "sg:province":"Valencia",
    "sg:website":"www.aridossierragordasl.com",
    "wof:name":"Aridos Sierra Gorda S.l.",
    "wof:placetype":"venue"
},
  "geometry": {"coordinates":[-0.4873113036,38.9452896118],"type":"Point"}
}