{
  "type": "Feature",
  "properties": {
    "iso:country":"ES",
    "sg:address":"Calle de Americas (de Las), 14",
    "sg:city":"Coslada",
    "sg:orig_category":"Droguer\u00cdas (al Por Menor)",
    "sg:phone":"+34 916 69 75 71",
    "sg:postcode":"28820",
    "sg:province":"Madrid",
    "sg:website":"www.alborant.com",
    "wof:name":"Alborant Suministros S.l.",
    "wof:placetype":"venue"
},
  "geometry": {"coordinates":[-3.5302858353,40.4339561462],"type":"Point"}
}