{
  "type": "Feature",
  "properties": {
    "addr:full":"Carrer de Sant Jordi, 7 Manlleu Barcelona 08560",
    "addr:housenumber":"7",
    "addr:postcode":"08560",
    "addr:street":"Carrer De Sant Jordi",
    "iso:country":"ES",
    "sg:address":"Carrer de Sant Jordi, 7",
    "sg:city":"Manlleu",
    "sg:orig_category":"\u00d3ptica: Instrumentos (fabricaci\u00d3n)",
    "sg:phone":"+34 938 51 25 50",
    "sg:postcode":"08560",
    "sg:province":"Barcelona",
    "wof:name":"Pujol Basaga\u00f1a Luis",
    "wof:placetype":"venue"
},
  "geometry": {"coordinates":[2.2857379913,42.0000419617],"type":"Point"}
}