{
  "type": "Feature",
  "properties": {
    "iso:country":"ES",
    "sg:address":"Avda Huesca De, 37",
    "sg:city":"Sari\u00f1ena",
    "sg:orig_category":"Empresas De Carpinter\u00cda De Madera",
    "sg:phone":"+34 974 57 24 85",
    "sg:postcode":"22200",
    "sg:province":"Huesca",
    "wof:name":"Carpinterias Y Muebles Hermanos Llamas S.l.",
    "wof:placetype":"venue"
},
  "geometry": {"coordinates":[-0.1568229944,41.798614502],"type":"Point"}
}