{
  "type": "Feature",
  "properties": {
    "iso:country":"ES",
    "sg:address":"C/ Na Saurina D'enten\u00c7a, 69",
    "sg:city":"Alcoi",
    "sg:orig_category":"Ropa Para Caballeros (al Por Menor)",
    "sg:phone":"+34 966 52 12 54",
    "sg:postcode":"03803",
    "sg:province":"Alicante",
    "wof:name":"Sancho Rodriguez Jesus",
    "wof:placetype":"venue"
},
  "geometry": {"coordinates":[-0.4781669974,38.7031822205],"type":"Point"}
}