{
  "type": "Feature",
  "properties": {
    "addr:full":"Calle de Castilla La Mancha, S/n Manzaneque Toledo 45460",
    "addr:housenumber":"s / n",
    "addr:postcode":"45460",
    "addr:street":"Calle De Castilla La Mancha",
    "iso:country":"ES",
    "sg:address":"Calle de Castilla La Mancha, S/n",
    "sg:city":"Manzaneque",
    "sg:orig_category":"Cajas Para Embalar",
    "sg:phone":"+34 925 34 48 14",
    "sg:postcode":"45460",
    "sg:province":"Toledo",
    "sg:website":"www.cajarural.es",
    "wof:name":"Caja Rural Provincial De Toledo",
    "wof:placetype":"venue"
},
  "geometry": {"coordinates":[-3.7941839695,39.6354789734],"type":"Point"}
}