{
  "type": "Feature",
  "properties": {
    "addr:full":"Av Diagonal, 608 Barcelona Barcelona 08021",
    "addr:housenumber":"608",
    "addr:postcode":"08021",
    "addr:street":"Av Diagonal",
    "iso:country":"ES",
    "sg:address":"Av Diagonal, 608",
    "sg:city":"Barcelona",
    "sg:orig_category":"Asesores De Gesti\u00d3n Del Patrimonio",
    "sg:phone":"+34 932 00 73 61",
    "sg:postcode":"08021",
    "sg:province":"Barcelona",
    "wof:name":"Fernandez Fernandez Antonio Y Cia C.b",
    "wof:placetype":"venue"
},
  "geometry": {"coordinates":[2.1427640915,41.3927536011],"type":"Point"}
}