{
  "type": "Feature",
  "properties": {
    "addr:full":"Avda Burjasot, 26 Valencia Valencia 46009",
    "addr:housenumber":"26",
    "addr:postcode":"46009",
    "addr:street":"Avda Burjasot",
    "iso:country":"ES",
    "sg:address":"Avda Burjasot, 26",
    "sg:city":"Valencia",
    "sg:orig_category":"Restaurantes",
    "sg:phone":"+34 963 40 50 58",
    "sg:postcode":"46009",
    "sg:province":"Valencia",
    "wof:name":"Wu  Jianhua",
    "wof:placetype":"venue"
},
  "geometry": {"coordinates":[-0.4309031963,39.4721488953],"type":"Point"}
}