{
  "type": "Feature",
  "properties": {
    "iso:country":"ES",
    "sg:address":"Carrer de Carme, S/n",
    "sg:city":"Cambrils",
    "sg:orig_category":"\u00d3pticos Optometristas (al Por Menor)",
    "sg:phone":"+34 977 79 20 20",
    "sg:postcode":"43850",
    "sg:province":"Tarragona",
    "wof:name":"Optica Gemma Salas S.c.p.",
    "wof:placetype":"venue"
},
  "geometry": {"coordinates":[1.0618540049,41.0661087036],"type":"Point"}
}