{
  "type": "Feature",
  "properties": {
    "iso:country":"ES",
    "sg:address":"Carrer de Huguet Des Far, 3",
    "sg:city":"Santa Pon\u00c7a",
    "sg:orig_category":"Fotograf\u00cda Art\u00cdstica Y Retratos",
    "sg:phone":"+34 971 69 13 08",
    "sg:postcode":"07180",
    "sg:province":"Islas Baleares",
    "wof:name":"Williamson  Rogney Geoffrey",
    "wof:placetype":"venue"
},
  "geometry": {"coordinates":[2.4721899033,39.5201721191],"type":"Point"}
}