{
  "type": "Feature",
  "properties": {
    "addr:full":"Avenida Zorita, S/n Melgar Fernamental Burgos 09100",
    "addr:housenumber":"s / n",
    "addr:postcode":"09100",
    "addr:street":"Avenida Zorita;Fernamental",
    "iso:country":"ES",
    "sg:address":"Avenida Zorita, S/n",
    "sg:city":"Melgar Fernamental",
    "sg:orig_category":"Promotores Constructores",
    "sg:phone":"+34 947 37 24 88",
    "sg:postcode":"09100",
    "sg:province":"Burgos",
    "wof:name":"Construcciones Failde Arroyo S.l.",
    "wof:placetype":"venue"
},
  "geometry": {"coordinates":[-4.2453022003,42.4037704468],"type":"Point"}
}