{
  "type": "Feature",
  "properties": {
    "addr:full":"Luga Ca\u00d1on Del Ambar, S/n Clavellinas Las Palmas 35214",
    "addr:postcode":"35214",
    "addr:street":"Ambar S / N Clavellinas Las Palmas",
    "iso:country":"ES",
    "sg:address":"Luga Ca\u00d1on Del Ambar, S/n",
    "sg:city":"Clavellinas",
    "sg:orig_category":"Electrodom\u00c9sticos (fabricaci\u00d3n, Al Por Mayor)",
    "sg:phone":"+34 928 13 35 22",
    "sg:postcode":"35214",
    "sg:province":"Las Palmas",
    "wof:name":"Electrodomesticos Bd S.l.",
    "wof:placetype":"venue"
},
  "geometry": {"coordinates":[-15.3887634277,27.9937648773],"type":"Point"}
}