{
  "type": "Feature",
  "properties": {
    "iso:country":"ES",
    "sg:address":"Calle de Agua Del Albayzin, 19",
    "sg:city":"Granada",
    "sg:orig_category":"Asesor\u00cda Sobre Comunicaci\u00d3n De Empresas",
    "sg:phone":"+34 958 80 09 19",
    "sg:postcode":"18010",
    "sg:province":"Granada",
    "wof:name":"Sanchez Iba\u00f1ez Maria Carmen",
    "wof:placetype":"venue"
},
  "geometry": {"coordinates":[-3.5933260918,37.1833114624],"type":"Point"}
}