{
  "type": "Feature",
  "properties": {
    "addr:full":"Carrer de Castillejos, 330 Barcelona Barcelona 08025",
    "addr:housenumber":"330",
    "addr:postcode":"08025",
    "addr:street":"Carrer De Castillejos",
    "iso:country":"ES",
    "sg:address":"Carrer de Castillejos, 330",
    "sg:city":"Barcelona",
    "sg:orig_category":"Zapatos (al Por Menor)",
    "sg:phone":"+34 934 55 99 74",
    "sg:postcode":"08025",
    "sg:province":"Barcelona",
    "wof:name":"Bertran Geli Juan",
    "wof:placetype":"venue"
},
  "geometry": {"coordinates":[2.1742360592,41.409828186],"type":"Point"}
}