{
  "type": "Feature",
  "properties": {
    "iso:country":"ES",
    "sg:address":"Calle de Guayadeque, 3",
    "sg:city":"Puerto Del Carmen",
    "sg:orig_category":"Molduras, Junquillos, Listones Y Molduras Perforadas",
    "sg:phone":"+34 928 51 35 59",
    "sg:postcode":"35510",
    "sg:province":"Las Palmas",
    "wof:name":"Iamond Comercial S.l.",
    "wof:placetype":"venue"
},
  "geometry": {"coordinates":[-13.6662149429,28.9237804413],"type":"Point"}
}