{
  "type": "Feature",
  "properties": {
    "iso:country":"ES",
    "sg:address":"Calle de Santo Domingo, 9",
    "sg:city":"Santa Cruz De Tenerife",
    "sg:orig_category":"Transporte En General",
    "sg:phone":"+34 922 24 81 29",
    "sg:postcode":"38003",
    "sg:province":"Santa Cruz De Tenerife",
    "wof:name":"Comunidad De Bienes L.t.chetwani E Hijos",
    "wof:placetype":"venue"
},
  "geometry": {"coordinates":[-16.2492446899,28.4652347565],"type":"Point"}
}