{
  "type": "Feature",
  "properties": {
    "addr:full":"Calle de Gamazo, 24 Valladolid Valladolid 47004",
    "addr:housenumber":"24",
    "addr:postcode":"47004",
    "addr:street":"Calle De Gamazo",
    "iso:country":"ES",
    "sg:address":"Calle de Gamazo, 24",
    "sg:city":"Valladolid",
    "sg:orig_category":"Ense\u00d1anza: Peluquer\u00cda Est\u00c9tica",
    "sg:phone":"+34 983 30 60 39",
    "sg:postcode":"47004",
    "sg:province":"Valladolid",
    "wof:name":"Colomer Beauty And Profesional Products S.l.",
    "wof:placetype":"venue"
},
  "geometry": {"coordinates":[-4.7265539169,41.6454391479],"type":"Point"}
}