{
  "type": "Feature",
  "properties": {
    "addr:full":"Calle de Julian Toron, 8 S.juan Las Palmas 35200",
    "addr:housenumber":"8",
    "addr:postcode":"35200",
    "addr:street":"Calle De Julian Toron;Las Palmas",
    "iso:country":"ES",
    "sg:address":"Calle de Julian Toron, 8",
    "sg:city":"S.juan",
    "sg:orig_category":"Abogados",
    "sg:phone":"+34 928 68 30 83",
    "sg:postcode":"35200",
    "sg:province":"Las Palmas",
    "wof:name":"Sarmiento Rodriguez Maria Del Carmen",
    "wof:placetype":"venue"
},
  "geometry": {"coordinates":[-15.4144220352,28.0029888153],"type":"Point"}
}