{
  "type": "Feature",
  "properties": {
    "iso:country":"ES",
    "sg:address":"Plaz Palacio, 2",
    "sg:city":"Hecho",
    "sg:orig_category":"Molduras, Junquillos, Listones Y Molduras Perforadas",
    "sg:phone":"+34 974 37 50 65",
    "sg:postcode":"22720",
    "sg:province":"Huesca",
    "wof:name":"Perez Larripa Vicente",
    "wof:placetype":"venue"
},
  "geometry": {"coordinates":[-0.7509850264,42.7383384705],"type":"Point"}
}