{
  "type": "Feature",
  "properties": {
    "iso:country":"ES",
    "sg:address":"Calle de Juan Xxiii, 23",
    "sg:city":"Castalla",
    "sg:orig_category":"Delegados, Agentes De Tr\u00c1nsito, Auxiliares De Transporte Internacional",
    "sg:phone":"+34 965 56 01 42",
    "sg:postcode":"03420",
    "sg:province":"Alicante",
    "wof:name":"Dura Canalas Pedro",
    "wof:placetype":"venue"
},
  "geometry": {"coordinates":[-0.6732469797,38.592956543],"type":"Point"}
}