{
  "type": "Feature",
  "properties": {
    "addr:full":"Vedrin, S/n Taramundi Asturias 33775",
    "addr:housenumber":"s / n",
    "addr:postcode":"33775",
    "addr:street":"Vedrin",
    "iso:country":"ES",
    "sg:address":"Vedrin, S/n",
    "sg:city":"Taramundi",
    "sg:orig_category":"Cajas Para Embalar",
    "sg:phone":"+34 985 64 67 93",
    "sg:postcode":"33775",
    "sg:province":"Asturias",
    "sg:website":"www.ruralvia.com",
    "wof:name":"Caja Rural De Asturias",
    "wof:placetype":"venue"
},
  "geometry": {"coordinates":[-7.1083769798,43.3608856201],"type":"Point"}
}