{
  "type": "Feature",
  "properties": {
    "addr:full":"Calle de Vital Aza, 15 Madrid Madrid 28017",
    "addr:housenumber":"15",
    "addr:postcode":"madrid;28017",
    "addr:street":"Calle De Vital Aza",
    "iso:country":"ES",
    "sg:address":"Calle de Vital Aza, 15",
    "sg:city":"Madrid",
    "sg:orig_category":"Peluqueros: De Se\u00d1oras",
    "sg:phone":"+34 913 67 39 64",
    "sg:postcode":"28017",
    "sg:province":"Madrid",
    "wof:name":"Gallardo Carmona Juana",
    "wof:placetype":"venue"
},
  "geometry": {"coordinates":[-3.6444220543,40.4311332703],"type":"Point"}
}