{
  "type": "Feature",
  "properties": {
    "addr:full":"Calle de General Casta\u00d1os, 28 Portugalete Vizcaya 48920",
    "addr:housenumber":"28",
    "addr:postcode":"48920",
    "addr:street":"Calle De General Castan\u0303Os",
    "iso:country":"ES",
    "sg:address":"Calle de General Casta\u00d1os, 28",
    "sg:city":"Portugalete",
    "sg:orig_category":"Bisuter\u00cda, Joyer\u00cda, Relojer\u00cda (al Por Menor)",
    "sg:phone":"+34 944 00 35 56",
    "sg:postcode":"48920",
    "sg:province":"Vizcaya",
    "wof:name":"Maria Elena Antolin Mariscal",
    "wof:placetype":"venue"
},
  "geometry": {"coordinates":[-3.0209410191,43.3210716248],"type":"Point"}
}