{
  "type": "Feature",
  "properties": {
    "iso:country":"ES",
    "sg:address":"Rbla Rambla Vella, 21",
    "sg:city":"Tarragona",
    "sg:orig_category":"Sindicatos De Trabajadores",
    "sg:phone":"+34 977 22 64 08",
    "sg:postcode":"43003",
    "sg:province":"Tarragona",
    "wof:name":"Sindicato De Iniciativa Y Turismo De Tarragona",
    "wof:placetype":"venue"
},
  "geometry": {"coordinates":[1.2541049719,41.1169281006],"type":"Point"}
}