{
  "type": "Feature",
  "properties": {
    "addr:full":"Calle de Alfonso Xiii, 3 Parla Madrid 28980",
    "addr:housenumber":"3",
    "addr:postcode":"28980",
    "addr:street":"Calle De Alfonso Xiii",
    "iso:country":"ES",
    "sg:address":"Calle de Alfonso Xiii, 3",
    "sg:city":"Parla",
    "sg:orig_category":"\u00d3ptica: Instrumentos (fabricaci\u00d3n)",
    "sg:phone":"+34 916 05 46 31",
    "sg:postcode":"28980",
    "sg:province":"Madrid",
    "wof:name":"Cdc Optical S.l.",
    "wof:placetype":"venue"
},
  "geometry": {"coordinates":[-3.767365694,40.2336044312],"type":"Point"}
}