{
  "type": "Feature",
  "properties": {
    "addr:full":"Carrer de Vicen\u00c7 Bou, 11 Esplugues Llobregat Barcelona 08950",
    "addr:housenumber":"11",
    "addr:postcode":"08950",
    "addr:street":"Carrer De Vicenc\u0327 Bou",
    "iso:country":"ES",
    "sg:address":"Carrer de Vicen\u00c7 Bou, 11",
    "sg:city":"Esplugues Llobregat",
    "sg:orig_category":"Electricidad: Instaladores",
    "sg:phone":"+34 933 72 60 71",
    "sg:postcode":"08950",
    "sg:province":"Barcelona",
    "wof:name":"Instalaciones Gaspar S.l.",
    "wof:placetype":"venue"
},
  "geometry": {"coordinates":[2.0841510296,41.3746299744],"type":"Point"}
}