{
  "type": "Feature",
  "properties": {
    "addr:full":"Calle de Jacobo Camarero, 11 Albolote Granada 18220",
    "addr:housenumber":"11",
    "addr:postcode":"18220",
    "addr:street":"Calle De Jacobo Camarero",
    "iso:country":"ES",
    "sg:address":"Calle de Jacobo Camarero, 11",
    "sg:city":"Albolote",
    "sg:orig_category":"Producci\u00d3n De Abonos Y De Fertilizantes",
    "sg:phone":"+34 958 43 09 25",
    "sg:postcode":"18220",
    "sg:province":"Granada",
    "wof:name":"Turbas Y Abonos Biologicos El Rocio S.c.a.",
    "wof:placetype":"venue"
},
  "geometry": {"coordinates":[-3.6524400711,37.2277107239],"type":"Point"}
}