{
  "type": "Feature",
  "properties": {
    "iso:country":"ES",
    "sg:address":"Pg Prim, 14",
    "sg:city":"Reus",
    "sg:orig_category":"M\u00c9dicos: Ginecolog\u00cda Y Obstetricia",
    "sg:phone":"+34 977 33 08 22",
    "sg:postcode":"43202",
    "sg:province":"Tarragona",
    "wof:name":"Boj Borbones Joaquin",
    "wof:placetype":"venue"
},
  "geometry": {"coordinates":[1.101575017,41.1557884216],"type":"Point"}
}