{
  "type": "Feature",
  "properties": {
    "addr:full":"C/ Major, 13 Salt Girona 17190",
    "addr:housenumber":"13",
    "addr:postcode":"17190",
    "addr:street":"C / Major",
    "iso:country":"ES",
    "sg:address":"C/ Major, 13",
    "sg:city":"Salt",
    "sg:orig_category":"Caf\u00c9s, Bares, Cervecer\u00cdas",
    "sg:phone":"+34 972 40 26 84",
    "sg:postcode":"17190",
    "sg:province":"Girona",
    "wof:name":"Garcia Garcia Ramon",
    "wof:placetype":"venue"
},
  "geometry": {"coordinates":[2.7996394634,41.9762878418],"type":"Point"}
}