{
  "type": "Feature",
  "properties": {
    "addr:full":"Calle de Fuente De Arriba, 43 Quintanar Sierra Burgos 09670",
    "addr:housenumber":"43",
    "addr:postcode":"09670",
    "addr:street":"Calle De Fuente De Arriba",
    "iso:country":"ES",
    "sg:address":"Calle de Fuente De Arriba, 43",
    "sg:city":"Quintanar Sierra",
    "sg:orig_category":"Promotores Constructores",
    "sg:phone":"+34 947 39 52 24",
    "sg:postcode":"09670",
    "sg:province":"Burgos",
    "wof:name":"Construcciones Alta Sierra S.l.",
    "wof:placetype":"venue"
},
  "geometry": {"coordinates":[-3.0393490791,41.9821586609],"type":"Point"}
}