{
  "type": "Feature",
  "properties": {
    "iso:country":"ES",
    "sg:address":"Plaz Luis Chamizo, 8",
    "sg:city":"Valverde Leganes",
    "sg:orig_category":"Reposter\u00cdas",
    "sg:phone":"+34 924 49 61 27",
    "sg:postcode":"06130",
    "sg:province":"Badajoz",
    "wof:name":"Conde Femenia Jose",
    "wof:placetype":"venue"
},
  "geometry": {"coordinates":[-6.9829440117,38.670425415],"type":"Point"}
}