{
  "type": "Feature",
  "properties": {
    "addr:full":"Calle de Jacinto Benavente, 18 Fuengirola M\u00e1laga 29640",
    "addr:housenumber":"18",
    "addr:postcode":"29640",
    "addr:street":"Calle De Jacinto Benavente;Ma\u0301Laga",
    "iso:country":"ES",
    "sg:address":"Calle de Jacinto Benavente, 18",
    "sg:city":"Fuengirola",
    "sg:orig_category":"Perfumer\u00cda (al Por Menor)",
    "sg:phone":"+34 952 58 13 84",
    "sg:postcode":"29640",
    "sg:province":"M\u00e1laga",
    "sg:website":"www.espejo-perfumerias.com",
    "wof:name":"Espejo Hermanos S. A.",
    "wof:placetype":"venue"
},
  "geometry": {"coordinates":[-4.6220197678,36.5410614014],"type":"Point"}
}