{
  "type": "Feature",
  "properties": {
    "iso:country":"ES",
    "sg:address":"Carr Jorge Juan, 74",
    "sg:city":"Burjassot",
    "sg:orig_category":"Alquiler De Casas Y Habitaciones Amuebladas",
    "sg:phone":"+34 963 64 37 16",
    "sg:postcode":"46100",
    "sg:province":"Valencia",
    "wof:name":"Reuniver Burjassot S.l.",
    "wof:placetype":"venue"
},
  "geometry": {"coordinates":[-0.4089510143,39.5076065063],"type":"Point"}
}