{
  "type": "Feature",
  "properties": {
    "iso:country":"ES",
    "sg:address":"Calle de Bohemios, 12",
    "sg:city":"Madrid",
    "sg:orig_category":"Estancos",
    "sg:phone":"+34 913 17 89 39",
    "sg:postcode":"28041",
    "sg:province":"Madrid",
    "wof:name":"Diaz Santiago Antonio",
    "wof:placetype":"venue"
},
  "geometry": {"coordinates":[-3.6964011192,40.3564338684],"type":"Point"}
}