{
  "type": "Feature",
  "properties": {
    "addr:full":"Barr Usabal Auzoa, 4 Usabal Guip\u00f9zcoa 20400",
    "addr:housenumber":"4",
    "addr:postcode":"20400",
    "addr:street":"Usabal Auzoa;Guipu\u0300Zcoa",
    "iso:country":"ES",
    "sg:address":"Barr Usabal Auzoa, 4",
    "sg:city":"Usabal",
    "sg:orig_category":"Calderer\u00cda",
    "sg:phone":"+34 943 67 41 22",
    "sg:postcode":"20400",
    "sg:province":"Guip\u00f9zcoa",
    "sg:website":"www.calguinox.com",
    "wof:name":"Caldereria Guipuzcoana De Inoxidable S.l.",
    "wof:placetype":"venue"
},
  "geometry": {"coordinates":[-2.0789339542,43.1339912415],"type":"Point"}
}