{
  "type": "Feature",
  "properties": {
    "iso:country":"ES",
    "sg:address":"Carr Ramon Y Cajal, 12",
    "sg:city":"Vila Joiosa",
    "sg:orig_category":"Negocio De Enlosados, Soler\u00cdas",
    "sg:phone":"+34 966 85 30 85",
    "sg:postcode":"03570",
    "sg:province":"Alicante",
    "wof:name":"Fernandez Alcala Eugenio",
    "wof:placetype":"venue"
},
  "geometry": {"coordinates":[-0.2310770005,38.5087165833],"type":"Point"}
}