{
  "type": "Feature",
  "properties": {
    "iso:country":"ES",
    "sg:address":"Pase Mercadal (del), 19",
    "sg:city":"Calahorra",
    "sg:orig_category":"Agencias De Trabajo Temporal",
    "sg:phone":"+34 941 13 52 52",
    "sg:postcode":"26500",
    "sg:province":"La Rioja",
    "wof:name":"Manpower Team Empresas De Trabajo Temporal",
    "wof:placetype":"venue"
},
  "geometry": {"coordinates":[-1.9637440443,42.3042907715],"type":"Point"}
}