{
  "type": "Feature",
  "properties": {
    "addr:full":"Carr Pujades, 2 Figueres Girona 17600",
    "addr:housenumber":"2",
    "addr:postcode":"17600",
    "addr:street":"Carr Pujades",
    "iso:country":"ES",
    "sg:address":"Carr Pujades, 2",
    "sg:city":"Figueres",
    "sg:orig_category":"M\u00c9dicos: Cardiolog\u00cda Y Afecciones Cardiovasculares",
    "sg:phone":"+34 972 50 31 86",
    "sg:postcode":"17600",
    "sg:province":"Girona",
    "wof:name":"Vila Forment Ernesto",
    "wof:placetype":"venue"
},
  "geometry": {"coordinates":[2.9656751156,42.2613677979],"type":"Point"}
}