{
  "type": "Feature",
  "properties": {
    "iso:country":"ES",
    "sg:address":"Calle de Real, 26",
    "sg:city":"Ca\u00f1averal",
    "sg:orig_category":"Bancos",
    "sg:phone":"+34 927 30 06 02",
    "sg:postcode":"10820",
    "sg:province":"C\u00e1ceres",
    "wof:name":"Banco Popular Espa\u00f1ol S.a.",
    "wof:placetype":"venue"
},
  "geometry": {"coordinates":[-6.3931407928,39.7906532288],"type":"Point"}
}