{
  "type": "Feature",
  "properties": {
    "iso:country":"ES",
    "sg:address":"Calle de Cerrillo San Roque C, 1",
    "sg:city":"Cuenca",
    "sg:orig_category":"Restaurantes",
    "sg:phone":"+34 969 21 40 29",
    "sg:postcode":"16004",
    "sg:province":"Cuenca",
    "wof:name":"Chucla S.l.",
    "wof:placetype":"venue"
},
  "geometry": {"coordinates":[-2.1357879639,40.0708236694],"type":"Point"}
}