{
  "type": "Feature",
  "properties": {
    "iso:country":"ES",
    "sg:address":"Avgd Pais Valencia, 32",
    "sg:city":"Muro Alcoy",
    "sg:orig_category":"Fabricaci\u00d3n De Telas Y Sedas",
    "sg:phone":"+34 966 51 62 69",
    "sg:postcode":"03830",
    "sg:province":"Alicante",
    "wof:name":"Garcia Martinez Maria Jose",
    "wof:placetype":"venue"
},
  "geometry": {"coordinates":[-0.4414289892,38.7812538147],"type":"Point"}
}