{
  "type": "Feature",
  "properties": {
    "iso:country":"ES",
    "sg:address":"Calle de Milano Plomizo, 1",
    "sg:city":"Sevilla",
    "sg:orig_category":"Sociedades, Compa\u00d1\u00cdas Aseguradoras",
    "sg:phone":"+34 954 57 75 75",
    "sg:postcode":"41020",
    "sg:province":"Sevilla",
    "wof:name":"Gesmalec S.l.",
    "wof:placetype":"venue"
},
  "geometry": {"coordinates":[-5.9424490929,37.4035835266],"type":"Point"}
}