{
  "type": "Feature",
  "properties": {
    "addr:full":"Calle de Villanueva, 30 Madrid Madrid 28001",
    "addr:housenumber":"30",
    "addr:postcode":"madrid;28001",
    "addr:street":"Calle De Villanueva",
    "iso:country":"ES",
    "sg:address":"Calle de Villanueva, 30",
    "sg:city":"Madrid",
    "sg:orig_category":"Fabricaci\u00d3n, Importaci\u00d3n De L\u00c1mparas Y Bombillas",
    "sg:phone":"+34 915 76 91 01",
    "sg:postcode":"28001",
    "sg:province":"Madrid",
    "wof:name":"Tridex S. A.",
    "wof:placetype":"venue"
},
  "geometry": {"coordinates":[-3.6850409508,40.422252655],"type":"Point"}
}