{
  "type": "Feature",
  "properties": {
    "addr:full":"Carrer de Nord, 9 Vendrell Tarragona 43700",
    "addr:housenumber":"9",
    "addr:postcode":"43700",
    "addr:street":"Carrer De Nord",
    "iso:country":"ES",
    "sg:address":"Carrer de Nord, 9",
    "sg:city":"Vendrell",
    "sg:orig_category":"Droguer\u00cdas (al Por Menor)",
    "sg:phone":"+34 977 66 12 35",
    "sg:postcode":"43700",
    "sg:province":"Tarragona",
    "wof:name":"Cal Vicento S.l.",
    "wof:placetype":"venue"
},
  "geometry": {"coordinates":[1.5360720158,41.2214164734],"type":"Point"}
}