{
  "type": "Feature",
  "properties": {
    "addr:full":"Calle de Bailen, 42 Sevilla Sevilla 41001",
    "addr:housenumber":"42",
    "addr:postcode":"41001",
    "addr:street":"Calle De Bailen",
    "iso:country":"ES",
    "sg:address":"Calle de Bailen, 42",
    "sg:city":"Sevilla",
    "sg:orig_category":"Fabricaci\u00d3n De Enlosados, Soler\u00cdas",
    "sg:phone":"+34 954 21 09 87",
    "sg:postcode":"41001",
    "sg:province":"Sevilla",
    "wof:name":"Delage Jimenez Ana",
    "wof:placetype":"venue"
},
  "geometry": {"coordinates":[-5.9997577667,37.3917732239],"type":"Point"}
}