{
  "type": "Feature",
  "properties": {
    "iso:country":"ES",
    "sg:address":"Calle de Menorca, S/n",
    "sg:city":"Calypo Fado",
    "sg:orig_category":"Asociaciones Y Clubs Deportivos",
    "sg:phone":"+34 918 13 21 37",
    "sg:postcode":"45950",
    "sg:province":"Toledo",
    "wof:name":"Robleespor S.l.",
    "wof:placetype":"venue"
},
  "geometry": {"coordinates":[-4.064458847,40.2556190491],"type":"Point"}
}