{
  "type": "Feature",
  "properties": {
    "addr:full":"Calle de Raimundo Fernandez Villaverde, 16 Madrid Madrid 28003",
    "addr:housenumber":"16",
    "addr:postcode":"madrid;28003",
    "addr:street":"Calle De Raimundo Fernandez Villaverde",
    "iso:country":"ES",
    "sg:address":"Calle de Raimundo Fernandez Villaverde, 16",
    "sg:city":"Madrid",
    "sg:orig_category":"Arquitectos",
    "sg:phone":"+34 915 34 65 10",
    "sg:postcode":"28003",
    "sg:province":"Madrid",
    "wof:name":"Promociones Y Proyectos El Sotillo S.l.",
    "wof:placetype":"venue"
},
  "geometry": {"coordinates":[-3.7019150257,40.4465522766],"type":"Point"}
}