{
  "type": "Feature",
  "properties": {
    "iso:country":"ES",
    "sg:address":"Carrer de Bisbe Verger, Del, 39",
    "sg:city":"Santanyi",
    "sg:orig_category":"Electrodom\u00c9sticos (al Por Menor)",
    "sg:phone":"+34 971 65 33 87",
    "sg:postcode":"07650",
    "sg:province":"Islas Baleares",
    "wof:name":"Electriques S'aljub S.l.",
    "wof:placetype":"venue"
},
  "geometry": {"coordinates":[3.1267030239,39.3532066345],"type":"Point"}
}