{
  "type": "Feature",
  "properties": {
    "addr:full":"Carrer de Conca, 24 Barcelona Barcelona 08026",
    "addr:housenumber":"24",
    "addr:postcode":"08026",
    "addr:street":"Carrer De Conca",
    "iso:country":"ES",
    "sg:address":"Carrer de Conca, 24",
    "sg:city":"Barcelona",
    "sg:orig_category":"Empresas De Demolici\u00d3n",
    "sg:phone":"+34 934 56 78 52",
    "sg:postcode":"08026",
    "sg:province":"Barcelona",
    "wof:name":"Ruescas Sanchez Juan Jose",
    "wof:placetype":"venue"
},
  "geometry": {"coordinates":[2.1802709103,41.4137077332],"type":"Point"}
}