{
  "type": "Feature",
  "properties": {
    "addr:full":"Carr Nou, 2 Hostalric Girona 17450",
    "addr:housenumber":"2",
    "addr:postcode":"17450",
    "addr:street":"Carr Nou",
    "iso:country":"ES",
    "sg:address":"Carr Nou, 2",
    "sg:city":"Hostalric",
    "sg:orig_category":"Electrodom\u00c9sticos (al Por Menor)",
    "sg:phone":"+34 972 86 42 36",
    "sg:postcode":"17450",
    "sg:province":"Girona",
    "wof:name":"Ribas Puig Jose",
    "wof:placetype":"venue"
},
  "geometry": {"coordinates":[2.6305301189,41.7464103699],"type":"Point"}
}