{
  "type": "Feature",
  "properties": {
    "addr:full":"Carrer de Periodista Grane, 11 Terrassa Barcelona 08226",
    "addr:housenumber":"11",
    "addr:postcode":"08226",
    "addr:street":"Carrer De Periodista Grane",
    "iso:country":"ES",
    "sg:address":"Carrer de Periodista Grane, 11",
    "sg:city":"Terrassa",
    "sg:orig_category":"Molduras, Junquillos, Listones Y Molduras Perforadas",
    "sg:phone":"+34 937 31 18 02",
    "sg:postcode":"08226",
    "sg:province":"Barcelona",
    "wof:name":"Rabasa Cruells Pedro",
    "wof:placetype":"venue"
},
  "geometry": {"coordinates":[2.0233840942,41.5694694519],"type":"Point"}
}