{
  "type": "Feature",
  "properties": {
    "iso:country":"ES",
    "sg:address":"Calle de Isaac Peral, 5",
    "sg:city":"Linares",
    "sg:orig_category":"Pod\u00d3logos: Pedicuros",
    "sg:phone":"+34 953 69 17 06",
    "sg:postcode":"23700",
    "sg:province":"Ja\u00e9n",
    "wof:name":"Garcia Garcia Miguel",
    "wof:placetype":"venue"
},
  "geometry": {"coordinates":[-3.6338961124,38.0966186523],"type":"Point"}
}