{
  "type": "Feature",
  "properties": {
    "addr:full":"Afueras, S/n Pasaron Vera C\u00e1ceres 10411",
    "addr:postcode":"10411",
    "addr:street":"Afueras S / N Pasaron Vera Ca\u0301Ceres",
    "iso:country":"ES",
    "sg:address":"Afueras, S/n",
    "sg:city":"Pasaron Vera",
    "sg:orig_category":"Cerrajer\u00cda, Ferrallista",
    "sg:phone":"+34 927 19 42 26",
    "sg:postcode":"10411",
    "sg:province":"C\u00e1ceres",
    "wof:name":"Cefoca S.l.",
    "wof:placetype":"venue"
},
  "geometry": {"coordinates":[-5.8198461533,40.0514221191],"type":"Point"}
}