{
  "type": "Feature",
  "properties": {
    "addr:full":"Polig. Ind. A Granxa, 85 Porri\u00f1o Pontevedra 36475",
    "addr:housenumber":"85",
    "addr:postcode":"36475",
    "addr:street":"Polig. Ind. A Granxa",
    "iso:country":"ES",
    "sg:address":"Polig. Ind. A Granxa, 85",
    "sg:city":"Porri\u00f1o",
    "sg:orig_category":"Rectificaci\u00d3n, Mecanizado, Fresado",
    "sg:phone":"+34 986 34 26 99",
    "sg:postcode":"36475",
    "sg:province":"Pontevedra",
    "wof:name":"Mecanizados Ogal S.l.",
    "wof:placetype":"venue"
},
  "geometry": {"coordinates":[-8.606926918,42.1053466797],"type":"Point"}
}