{
  "type": "Feature",
  "properties": {
    "iso:country":"ES",
    "sg:address":"San Cristobal, 2",
    "sg:city":"Iru\u00f1a",
    "sg:orig_category":"M\u00c9dicos: Estomatolog\u00cda",
    "sg:phone":"+34 948 38 29 25",
    "sg:postcode":"31015",
    "sg:province":"Navarra",
    "wof:name":"Paez Diez Alvaro",
    "wof:placetype":"venue"
},
  "geometry": {"coordinates":[-1.6313430071,42.8245658875],"type":"Point"}
}