{
  "type": "Feature",
  "properties": {
    "addr:full":"Ctra Terrassa, 100 Rubi Barcelona 08191",
    "addr:housenumber":"100",
    "addr:postcode":"08191",
    "addr:street":"Ctra Terrassa",
    "iso:country":"ES",
    "sg:address":"Ctra Terrassa, 100",
    "sg:city":"Rubi",
    "sg:orig_category":"Fabricaci\u00d3n, Instalaci\u00d3n Y Reparaci\u00d3n De Bombas",
    "sg:phone":"+34 935 88 29 48",
    "sg:postcode":"08191",
    "sg:province":"Barcelona",
    "wof:name":"M.j. Reparacion De Bombas S.l.",
    "wof:placetype":"venue"
},
  "geometry": {"coordinates":[2.0330600739,41.5011138916],"type":"Point"}
}