{
  "type": "Feature",
  "properties": {
    "iso:country":"ES",
    "sg:address":"Avda Mediterraneo, 2",
    "sg:city":"Benidorm",
    "sg:orig_category":"Ropa Para Se\u00d1oras Y Caballeros (al Por Menor)",
    "sg:phone":"+34 965 85 36 98",
    "sg:postcode":"03500",
    "sg:province":"Alicante",
    "wof:name":"Perez Martorell Miguel",
    "wof:placetype":"venue"
},
  "geometry": {"coordinates":[-0.1261339933,38.5372276306],"type":"Point"}
}