{
  "type": "Feature",
  "properties": {
    "iso:country":"ES",
    "sg:address":"Ronda, S/n",
    "sg:city":"Ceclavin",
    "sg:orig_category":"Transportes Por V\u00cdas Navegables",
    "sg:phone":"+34 927 39 32 50",
    "sg:postcode":"10870",
    "sg:province":"C\u00e1ceres",
    "wof:name":"Ibarra Lucero Miguel",
    "wof:placetype":"venue"
},
  "geometry": {"coordinates":[-6.7764601707,39.8228607178],"type":"Point"}
}