{
  "type": "Feature",
  "properties": {
    "addr:full":"Avda. Castellnou, 147 Urb. Castellnou-can Mir Barcelona 08191",
    "addr:housenumber":"147",
    "addr:postcode":"08191",
    "addr:street":"Avda. Castellnou;Urb. Castellnou-Can Mir Barcelona",
    "iso:country":"ES",
    "sg:address":"Avda. Castellnou, 147",
    "sg:city":"Urb. Castellnou-can Mir",
    "sg:orig_category":"Supermercados Y Hipermercados",
    "sg:phone":"+34 935 86 00 27",
    "sg:postcode":"08191",
    "sg:province":"Barcelona",
    "wof:name":"Castellgiro S.l.",
    "wof:placetype":"venue"
},
  "geometry": {"coordinates":[2.0316240788,41.4919128418],"type":"Point"}
}