{
  "type": "Feature",
  "properties": {
    "iso:country":"ES",
    "sg:address":"Plaz Espa\u00d1a, 5",
    "sg:city":"Vitigudino",
    "sg:orig_category":"Formaci\u00d3n Continuada (variada)",
    "sg:phone":"+34 923 52 81 33",
    "sg:postcode":"37210",
    "sg:province":"Salamanca",
    "wof:name":"Navarro Lara Jose",
    "wof:placetype":"venue"
},
  "geometry": {"coordinates":[-6.4347958565,41.0086898804],"type":"Point"}
}