{
  "type": "Feature",
  "properties": {
    "iso:country":"ES",
    "sg:address":"Calle de Mayor, 16",
    "sg:city":"Sonseca",
    "sg:classifiers":[
        {
            "category":"Casinos & Gambling",
            "type":"Entertainment"
        }
    ],
    "sg:phone":"+34 925 38 15 01",
    "sg:postcode":"45100",
    "sg:province":"Toledo",
    "sg:tags":[
        "locale",
        "de",
        "juego"
    ],
    "wof:name":"Casino De Amistad",
    "wof:placetype":"venue"
},
  "geometry": {"coordinates":[-3.9759569168,39.6741981506],"type":"Point"}
}