{
  "type": "Feature",
  "properties": {
    "addr:full":"Zezenbide Kalea, 8 Eibar Guip\u00f9zcoa 20600",
    "addr:housenumber":"8",
    "addr:postcode":"20600",
    "addr:street":"Zezenbide Kalea;Guipu\u0300Zcoa",
    "iso:country":"ES",
    "sg:address":"Zezenbide Kalea, 8",
    "sg:city":"Eibar",
    "sg:orig_category":"Electricidad, Electr\u00d3nica: Suministros (al Por Menor)",
    "sg:phone":"+34 943 82 04 82",
    "sg:postcode":"20600",
    "sg:province":"Guip\u00f9zcoa",
    "wof:name":"Aplicaciones Practicas Electronicas S. A.",
    "wof:placetype":"venue"
},
  "geometry": {"coordinates":[-2.4738233089,43.1836280823],"type":"Point"}
}