{
  "type": "Feature",
  "properties": {
    "addr:full":"Carr Verge De Montserrat, 14 Ponts Lleida 25740",
    "addr:housenumber":"14",
    "addr:postcode":"25740",
    "addr:street":"Carr Verge De Montserrat",
    "iso:country":"ES",
    "sg:address":"Carr Verge De Montserrat, 14",
    "sg:city":"Ponts",
    "sg:orig_category":"Contenedores (mercanc\u00cdas)",
    "sg:phone":"+34 973 46 00 18",
    "sg:postcode":"25740",
    "sg:province":"Lleida",
    "wof:name":"Excavaciones Goncar S.l.",
    "wof:placetype":"venue"
},
  "geometry": {"coordinates":[1.1852109432,41.9165611267],"type":"Point"}
}