{
  "type": "Feature",
  "properties": {
    "iso:country":"ES",
    "sg:address":"Urb Araucarias (las), 1",
    "sg:city":"Orotava",
    "sg:orig_category":"Ense\u00d1anza, Formaci\u00d3n Profesional: Aprendizaje",
    "sg:phone":"+34 922 32 80 17",
    "sg:postcode":"38300",
    "sg:province":"Santa Cruz De Tenerife",
    "wof:name":"Excelentisimo Ayuntamiento De La Orotava",
    "wof:placetype":"venue"
},
  "geometry": {"coordinates":[-16.5193557739,28.3954544067],"type":"Point"}
}