{
  "type": "Feature",
  "properties": {
    "addr:full":"Calle de Don Sancho, 3 Valladolid Valladolid 47002",
    "addr:housenumber":"3",
    "addr:postcode":"47002",
    "addr:street":"Calle De Don Sancho",
    "iso:country":"ES",
    "sg:address":"Calle de Don Sancho, 3",
    "sg:city":"Valladolid",
    "sg:orig_category":"M\u00c9dicos: Reumatolog\u00cda",
    "sg:phone":"+34 983 29 51 17",
    "sg:postcode":"47002",
    "sg:province":"Valladolid",
    "wof:name":"Altuzarra Y Corral Luis Maria",
    "wof:placetype":"venue"
},
  "geometry": {"coordinates":[-4.7194747925,41.6483764648],"type":"Point"}
}