{
  "type": "Feature",
  "properties": {
    "iso:country":"ES",
    "sg:address":"Diseminados, S/n",
    "sg:city":"Benabarre",
    "sg:orig_category":"Alquiler De Casas Y Habitaciones Amuebladas",
    "sg:phone":"+34 974 54 31 50",
    "sg:postcode":"22580",
    "sg:province":"Huesca",
    "wof:name":"Arcas Calvo Maria Luisa",
    "wof:placetype":"venue"
},
  "geometry": {"coordinates":[0.469109714,42.0970077515],"type":"Point"}
}