{
  "type": "Feature",
  "properties": {
    "iso:country":"ES",
    "sg:address":"Calle de Duranes, 9",
    "sg:city":"Antequera",
    "sg:orig_category":"Ropa Para Se\u00d1oras (al Por Menor)",
    "sg:phone":"+34 952 84 05 10",
    "sg:postcode":"29200",
    "sg:province":"M\u00e1laga",
    "wof:name":"Kira Moda S.l.",
    "wof:placetype":"venue"
},
  "geometry": {"coordinates":[-4.5593295097,37.0197563171],"type":"Point"}
}