{
  "type": "Feature",
  "properties": {
    "iso:country":"ES",
    "sg:address":"Pase Colon, 35",
    "sg:city":"Irun",
    "sg:orig_category":"Inmobiliaria (agencias)",
    "sg:phone":"+34 943 61 00 84",
    "sg:postcode":"20301",
    "sg:province":"Guip\u00f9zcoa",
    "wof:name":"Abad Alba I\u00f1aki",
    "wof:placetype":"venue"
},
  "geometry": {"coordinates":[-1.790234,43.339523],"type":"Point"}
}