{
  "type": "Feature",
  "properties": {
    "iso:country":"ES",
    "sg:address":"Calle de Guadiato, 1",
    "sg:city":"Sevilla",
    "sg:classifiers":[
        {
            "category":"Professional",
            "subcategory":"Management & Consulting",
            "type":"Services"
        }
    ],
    "sg:phone":"+34 954 63 59 36",
    "sg:postcode":"41005",
    "sg:province":"Sevilla",
    "sg:tags":[
        "asesor\u00cda",
        "en",
        "marketing"
    ],
    "wof:name":"Dibegil Hermanos S.l.l.",
    "wof:placetype":"venue"
},
  "geometry": {"coordinates":[-5.9661631584,37.3736686707],"type":"Point"}
}