{
  "type": "Feature",
  "properties": {
    "iso:country":"ES",
    "sg:address":"Plaz San Francisco, 13",
    "sg:city":"Cartagena",
    "sg:orig_category":"Imprenta",
    "sg:phone":"+34 968 50 14 83",
    "sg:postcode":"30202",
    "sg:province":"Murcia",
    "wof:name":"Molero Garceran Juan Antonio",
    "wof:placetype":"venue"
},
  "geometry": {"coordinates":[-0.9829890132,37.6014556885],"type":"Point"}
}