{
  "type": "Feature",
  "properties": {
    "iso:country":"ES",
    "sg:address":"Calle de Montera, 21",
    "sg:city":"Madrid",
    "sg:orig_category":"Fabricaci\u00d3n De Jabones, Detergentes Y Lej\u00cdas",
    "sg:phone":"+34 915 21 26 86",
    "sg:postcode":"28013",
    "sg:province":"Madrid",
    "wof:name":"Nikolaev Koulev Jan",
    "wof:placetype":"venue"
},
  "geometry": {"coordinates":[-3.7028551102,40.4179344177],"type":"Point"}
}