{
  "type": "Feature",
  "properties": {
    "iso:country":"ES",
    "sg:address":"Carrer de Font D'en Canyelles, 90",
    "sg:city":"Barcelona",
    "sg:orig_category":"Barbacoas Y Accesorios",
    "sg:phone":"+34 933 53 32 70",
    "sg:postcode":"08042",
    "sg:province":"Barcelona",
    "wof:name":"Rodriguez Brando Alvaro Diego",
    "wof:placetype":"venue"
},
  "geometry": {"coordinates":[2.1746315956,41.4410095215],"type":"Point"}
}