{
  "type": "Feature",
  "properties": {
    "addr:full":"Calle de Abastos, 12 Roda Andalucia Sevilla 41590",
    "addr:housenumber":"12",
    "addr:postcode":"41590",
    "addr:street":"Calle De Abastos",
    "iso:country":"ES",
    "sg:address":"Calle de Abastos, 12",
    "sg:city":"Roda Andalucia",
    "sg:orig_category":"Ense\u00d1anza, Formaci\u00d3n Profesional: Aprendizaje",
    "sg:phone":"+34 954 01 63 95",
    "sg:postcode":"41590",
    "sg:province":"Sevilla",
    "wof:name":"Ayuntamiento De La Roda De Andalucia",
    "wof:placetype":"venue"
},
  "geometry": {"coordinates":[-4.7806196213,37.2007331848],"type":"Point"}
}