{
  "type": "Feature",
  "properties": {
    "iso:country":"ES",
    "sg:address":"Carr Pintor Sorolla, 21",
    "sg:city":"Aldaia",
    "sg:orig_category":"Farmacias",
    "sg:phone":"+34 961 50 19 74",
    "sg:postcode":"46960",
    "sg:province":"Valencia",
    "wof:name":"Rodriguez Lozano Manuel Alberto",
    "wof:placetype":"venue"
},
  "geometry": {"coordinates":[-0.4649460018,39.4581832886],"type":"Point"}
}