{
  "type": "Feature",
  "properties": {
    "iso:country":"ES",
    "sg:address":"Calle de Padre Manuel Fernandez, 10",
    "sg:city":"Jerez De La Frontera",
    "sg:orig_category":"Promotores Constructores",
    "sg:phone":"+34 956 32 22 47",
    "sg:postcode":"11408",
    "sg:province":"C\u00e1diz",
    "wof:name":"Limsar S.l.",
    "wof:placetype":"venue"
},
  "geometry": {"coordinates":[-6.1482830048,36.685005188],"type":"Point"}
}