{
  "type": "Feature",
  "properties": {
    "addr:full":"Av Estanislau Figueres (d'), 22 Tarragona Tarragona 43002",
    "addr:housenumber":"22",
    "addr:postcode":"43002",
    "addr:street":"Av Estanislau Figueres D '",
    "iso:country":"ES",
    "sg:address":"Av Estanislau Figueres (d'), 22",
    "sg:city":"Tarragona",
    "sg:orig_category":"Asesor\u00cda De Formaci\u00d3n Y Gesti\u00d3n De Personal",
    "sg:phone":"+34 977 23 81 12",
    "sg:postcode":"43002",
    "sg:province":"Tarragona",
    "wof:name":"Dades I Serveis S.a.",
    "wof:placetype":"venue"
},
  "geometry": {"coordinates":[1.2508579493,41.1177978516],"type":"Point"}
}