{
  "type": "Feature",
  "properties": {
    "iso:country":"ES",
    "sg:address":"B. Real, S/n",
    "sg:city":"Melilla",
    "sg:orig_category":"Confiter\u00cdas, Chocolater\u00cdas (al Por Menor)",
    "sg:phone":"+34 952 69 11 57",
    "sg:postcode":"52006",
    "sg:province":"Melilla",
    "wof:name":"Allal Moh Abdelkader",
    "wof:placetype":"venue"
},
  "geometry": {"coordinates":[-2.9345984459,35.2940292358],"type":"Point"}
}