{
  "type": "Feature",
  "properties": {
    "addr:full":"Calle de Anatolio De Fuentes Garcia, 4 Santa Cruz De Tenerife Santa Cruz De Tenerife 38009",
    "addr:housenumber":"4",
    "addr:postcode":"38009",
    "addr:street":"Calle De Anatolio;Garcia",
    "iso:country":"ES",
    "sg:address":"Calle de Anatolio De Fuentes Garcia, 4",
    "sg:city":"Santa Cruz De Tenerife",
    "sg:orig_category":"Bazares, Art\u00cdculos De Limpieza Y De Cocina (al Por Menor)",
    "sg:phone":"+34 922 23 04 62",
    "sg:postcode":"38009",
    "sg:province":"Santa Cruz De Tenerife",
    "wof:name":"Exclusivas Rodier S.l.",
    "wof:placetype":"venue"
},
  "geometry": {"coordinates":[-16.2699012756,28.4510936737],"type":"Point"}
}