{
  "type": "Feature",
  "properties": {
    "addr:full":"Calle de General Sanjurjo, 68 Santa Cruz De Tenerife Santa Cruz De Tenerife 38006",
    "addr:housenumber":"68",
    "addr:postcode":"38006",
    "addr:street":"Calle De General Sanjurjo",
    "iso:country":"ES",
    "sg:address":"Calle de General Sanjurjo, 68",
    "sg:city":"Santa Cruz De Tenerife",
    "sg:orig_category":"Industria Qu\u00cdmica",
    "sg:phone":"+34 922 24 98 07",
    "sg:postcode":"38006",
    "sg:province":"Santa Cruz De Tenerife",
    "wof:name":"Concepcion Diaz Jose Carlos",
    "wof:placetype":"venue"
},
  "geometry": {"coordinates":[-16.2642803192,28.4706878662],"type":"Point"}
}