{
  "type": "Feature",
  "properties": {
    "iso:country":"ES",
    "sg:address":"Calle de Travieso, 22",
    "sg:city":"Palmas De Gran Canaria",
    "sg:orig_category":"Ropa Para Se\u00d1oras (al Por Menor)",
    "sg:phone":"+34 928 36 98 03",
    "sg:postcode":"35002",
    "sg:province":"Las Palmas",
    "wof:name":"Knowing Canarias S.l.",
    "wof:placetype":"venue"
},
  "geometry": {"coordinates":[-15.4175167084,28.1044330597],"type":"Point"}
}