{
  "type": "Feature",
  "properties": {
    "addr:full":"Carrer de Indians (dels), 1 Torredembarra Tarragona 43830",
    "addr:housenumber":"1",
    "addr:postcode":"43830",
    "addr:street":"Carrer De Indians Dels",
    "iso:country":"ES",
    "sg:address":"Carrer de Indians (dels), 1",
    "sg:city":"Torredembarra",
    "sg:orig_category":"Grafistas",
    "sg:phone":"+34 977 13 05 30",
    "sg:postcode":"43830",
    "sg:province":"Tarragona",
    "wof:name":"Ayuso Virgili Hector",
    "wof:placetype":"venue"
},
  "geometry": {"coordinates":[1.399001956,41.1452674866],"type":"Point"}
}