{
  "type": "Feature",
  "properties": {
    "addr:full":"Calle de Portugal, 7 Don Benito Badajoz 06400",
    "addr:housenumber":"7",
    "addr:postcode":"06400",
    "addr:street":"Calle De Portugal",
    "iso:country":"ES",
    "sg:address":"Calle de Portugal, 7",
    "sg:city":"Don Benito",
    "sg:orig_category":"Confecci\u00d3n (fabricaci\u00d3n, Al Por Mayor)",
    "sg:phone":"+34 924 81 20 70",
    "sg:postcode":"06400",
    "sg:province":"Badajoz",
    "wof:name":"Gil Jeans S.l.",
    "wof:placetype":"venue"
},
  "geometry": {"coordinates":[-5.8639287949,38.9570846558],"type":"Point"}
}