{
  "type": "Feature",
  "properties": {
    "iso:country":"ES",
    "sg:address":"Rcial Parque De Las Delicias, 16",
    "sg:city":"Rota",
    "sg:orig_category":"Agencias Y Agentes Comerciales, Representantes",
    "sg:phone":"+34 956 84 10 48",
    "sg:postcode":"11520",
    "sg:province":"C\u00e1diz",
    "wof:name":"Reyes Garci Sandra",
    "wof:placetype":"venue"
},
  "geometry": {"coordinates":[-6.3688821793,36.6247940063],"type":"Point"}
}