{
  "type": "Feature",
  "properties": {
    "addr:full":"Calle de Gardenias (las), 21 Alcorcon Madrid 28925",
    "addr:housenumber":"21",
    "addr:postcode":"28925",
    "addr:street":"Calle De Gardenias Las",
    "iso:country":"ES",
    "sg:address":"Calle de Gardenias (las), 21",
    "sg:city":"Alcorcon",
    "sg:orig_category":"Agencias Y Asesores De Publicidad",
    "sg:phone":"+34 916 10 69 48",
    "sg:postcode":"28925",
    "sg:province":"Madrid",
    "sg:website":"www.manone.es",
    "wof:name":"Man One Ideas Energeticas S.l.",
    "wof:placetype":"venue"
},
  "geometry": {"coordinates":[-3.8008599281,40.3541526794],"type":"Point"}
}