{
  "type": "Feature",
  "properties": {
    "iso:country":"ES",
    "sg:address":"Calle de General Vives, 51",
    "sg:city":"Palmas De Gran Canaria",
    "sg:orig_category":"Bisuter\u00cda, Joyer\u00cda, Relojer\u00cda (al Por Menor)",
    "sg:phone":"+34 928 22 51 28",
    "sg:postcode":"35007",
    "sg:province":"Las Palmas",
    "wof:name":"Bola\u00f1os Guerra Violeta",
    "wof:placetype":"venue"
},
  "geometry": {"coordinates":[-15.4312133789,28.1390666962],"type":"Point"}
}