{
  "type": "Feature",
  "properties": {
    "iso:country":"ES",
    "sg:address":"Calle de Santa Felicidad, 28",
    "sg:city":"Madrid",
    "sg:orig_category":"Molduras, Junquillos, Listones Y Molduras Perforadas",
    "sg:phone":"+34 914 05 01 25",
    "sg:postcode":"28017",
    "sg:province":"Madrid",
    "wof:name":"Gil Rodriguez Juan",
    "wof:placetype":"venue"
},
  "geometry": {"coordinates":[-3.650703907,40.4245452881],"type":"Point"}
}