{
  "type": "Feature",
  "properties": {
    "addr:full":"Carrer de Montblanc, 20 Vilafranca Penedes Barcelona 08720",
    "addr:housenumber":"20",
    "addr:postcode":"08720",
    "addr:street":"Carrer De Montblanc;Penedes Barcelona",
    "iso:country":"ES",
    "sg:address":"Carrer de Montblanc, 20",
    "sg:city":"Vilafranca Penedes",
    "sg:orig_category":"Asociaciones, Organismos Culturales Y Socioeducativos",
    "sg:phone":"+34 938 90 13 63",
    "sg:postcode":"08720",
    "sg:province":"Barcelona",
    "wof:name":"Associacio Moviment Infantil De Vilafranca",
    "wof:placetype":"venue"
},
  "geometry": {"coordinates":[1.6954996586,41.3403358459],"type":"Point"}
}