{
  "type": "Feature",
  "properties": {
    "iso:country":"ES",
    "sg:address":"Calle de Hoya, 2",
    "sg:city":"Arcos Frontera",
    "sg:orig_category":"Molduras, Junquillos, Listones Y Molduras Perforadas",
    "sg:phone":"+34 956 70 01 87",
    "sg:postcode":"11630",
    "sg:province":"C\u00e1diz",
    "wof:name":"Carrera Navarro Jose",
    "wof:placetype":"venue"
},
  "geometry": {"coordinates":[9.0760097504,52.7750091553],"type":"Point"}
}