{
  "type": "Feature",
  "properties": {
    "iso:country":"ES",
    "sg:address":"Calle de Camino De San Antonio, 12",
    "sg:city":"Motril",
    "sg:orig_category":"Asesor\u00cda Fiscal Y Jur\u00cddica",
    "sg:phone":"+34 958 60 70 80",
    "sg:postcode":"18600",
    "sg:province":"Granada",
    "wof:name":"Cara Lopez Juan Carlos De",
    "wof:placetype":"venue"
},
  "geometry": {"coordinates":[-3.5190234184,36.7465934753],"type":"Point"}
}