{
  "type": "Feature",
  "properties": {
    "iso:country":"ES",
    "sg:address":"Calle de Virgen Del Rosario, 9",
    "sg:city":"Almoradi",
    "sg:orig_category":"Zapatos (al Por Menor)",
    "sg:phone":"+34 966 78 15 29",
    "sg:postcode":"03160",
    "sg:province":"Alicante",
    "wof:name":"Promociones Euro-house 2000 S.l.",
    "wof:placetype":"venue"
},
  "geometry": {"coordinates":[-0.790225029,38.1084938049],"type":"Point"}
}