{
  "type": "Feature",
  "properties": {
    "addr:full":"Avda Mijas, S/n Fuengirola M\u00e1laga 29640",
    "addr:housenumber":"s / n",
    "addr:postcode":"29640",
    "addr:street":"Avda Mijas;Ma\u0301Laga",
    "iso:country":"ES",
    "sg:address":"Avda Mijas, S/n",
    "sg:city":"Fuengirola",
    "sg:orig_category":"Delegados, Agentes De Tr\u00c1nsito, Auxiliares De Transporte Internacional",
    "sg:phone":"+34 952 46 25 81",
    "sg:postcode":"29640",
    "sg:province":"M\u00e1laga",
    "wof:name":"Sanchez Qui\u00f1ones Jose Antonio",
    "wof:placetype":"venue"
},
  "geometry": {"coordinates":[-4.630959034,36.5442657471],"type":"Point"}
}