{
  "type": "Feature",
  "properties": {
    "addr:full":"Carrer de Calderon, 68 Sabadell Barcelona 08201",
    "addr:housenumber":"68",
    "addr:postcode":"08201",
    "addr:street":"Carrer De Calderon",
    "iso:country":"ES",
    "sg:address":"Carrer de Calderon, 68",
    "sg:city":"Sabadell",
    "sg:orig_category":"Colchones (fabricaci\u00d3n, Al Por Mayor, Al Por Menor)",
    "sg:phone":"+34 937 25 27 37",
    "sg:postcode":"08201",
    "sg:province":"Barcelona",
    "wof:name":"Matalaseria Garriga S.l.",
    "wof:placetype":"venue"
},
  "geometry": {"coordinates":[2.1037659645,41.5475578308],"type":"Point"}
}