{
  "type": "Feature",
  "properties": {
    "addr:full":"Calle de San Marcos, 4 Errenteria Guip\u00f9zcoa 20100",
    "addr:housenumber":"4",
    "addr:postcode":"20100",
    "addr:street":"Calle De San Marcos;Guipu\u0300Zcoa",
    "iso:country":"ES",
    "sg:address":"Calle de San Marcos, 4",
    "sg:city":"Errenteria",
    "sg:orig_category":"Molduras, Junquillos, Listones Y Molduras Perforadas",
    "sg:phone":"+34 943 51 81 30",
    "sg:postcode":"20100",
    "sg:province":"Guip\u00f9zcoa",
    "wof:name":"Alvarez Dominguez Deborah",
    "wof:placetype":"venue"
},
  "geometry": {"coordinates":[-1.9141180515,43.3112220764],"type":"Point"}
}