{
  "type": "Feature",
  "properties": {
    "addr:full":"Carrer de Rec, 40 Barcelona Barcelona 08003",
    "addr:housenumber":"40",
    "addr:postcode":"08003",
    "addr:street":"Carrer De Rec",
    "iso:country":"ES",
    "sg:address":"Carrer de Rec, 40",
    "sg:city":"Barcelona",
    "sg:orig_category":"Ropa Para Se\u00d1oras (al Por Menor)",
    "sg:phone":"+34 933 10 67 43",
    "sg:postcode":"08003",
    "sg:province":"Barcelona",
    "sg:website":"www.gimenezzuaao.com",
    "wof:name":"Gimenez & Zuazo S.l.",
    "wof:placetype":"venue"
},
  "geometry": {"coordinates":[2.1829829216,41.384765625],"type":"Point"}
}