{
  "type": "Feature",
  "properties": {
    "iso:country":"ES",
    "sg:address":"Calle de Bachiller, 4",
    "sg:city":"Pto. Rosario",
    "sg:orig_category":"Ropa Para Se\u00d1oras Y Caballeros (al Por Menor)",
    "sg:phone":"+34 928 53 20 38",
    "sg:postcode":"35600",
    "sg:province":"Las Palmas",
    "wof:name":"Chacon Armas Juan Ildefonso",
    "wof:placetype":"venue"
},
  "geometry": {"coordinates":[-13.8638353348,28.4989891052],"type":"Point"}
}