{
  "type": "Feature",
  "properties": {
    "addr:full":"Grajilla, S/n G\u00fcejar-sierra Granada 18160",
    "addr:postcode":"18160",
    "addr:street":"Grajilla S / N Gueejar-Sierra",
    "iso:country":"ES",
    "sg:address":"Grajilla, S/n",
    "sg:city":"G\u00fcejar-sierra",
    "sg:orig_category":"Agricultura: Abastecimiento Y Cosechado (negocio)",
    "sg:phone":"+34 958 48 46 86",
    "sg:postcode":"18160",
    "sg:province":"Granada",
    "wof:name":"Cooperativa Maitena Del Genil",
    "wof:placetype":"venue"
},
  "geometry": {"coordinates":[-3.4379739761,37.1602554321],"type":"Point"}
}