{
  "type": "Feature",
  "properties": {
    "addr:full":"Avda Pais Valencia (del), 57 Onda Castell\u00f3n 12200",
    "addr:postcode":"12200",
    "addr:street":"Avda Pais;Del;Castello\u0301N",
    "iso:country":"ES",
    "sg:address":"Avda Pais Valencia (del), 57",
    "sg:city":"Onda",
    "sg:orig_category":"\u00d3ptica: Instrumentos (fabricaci\u00d3n)",
    "sg:phone":"+34 964 77 21 38",
    "sg:postcode":"12200",
    "sg:province":"Castell\u00f3n",
    "wof:name":"Lenticornea S.l.",
    "wof:placetype":"venue"
},
  "geometry": {"coordinates":[-0.2635320127,39.9649505615],"type":"Point"}
}