{
  "type": "Feature",
  "properties": {
    "iso:country":"ES",
    "sg:address":"Avda Cantabrico, 12",
    "sg:city":"Vitoria-gasteiz",
    "sg:orig_category":"Congelados: Productos Alimentarios (al Por Menor)",
    "sg:phone":"+34 945 12 86 87",
    "sg:postcode":"01013",
    "sg:province":"\u00c1lava",
    "wof:name":"Rodriguez Y Renes S.l.",
    "wof:placetype":"venue"
},
  "geometry": {"coordinates":[-2.6595649719,42.8647041321],"type":"Point"}
}