{
  "type": "Feature",
  "properties": {
    "addr:full":"Calle de Mayor, 5 Molinos Teruel 44556",
    "addr:housenumber":"5",
    "addr:postcode":"44556",
    "addr:street":"Calle De Mayor",
    "iso:country":"ES",
    "sg:address":"Calle de Mayor, 5",
    "sg:city":"Molinos",
    "sg:orig_category":"Albergues",
    "sg:phone":"+34 978 84 92 34",
    "sg:postcode":"44556",
    "sg:province":"Teruel",
    "wof:name":"Ferrer Royo David",
    "wof:placetype":"venue"
},
  "geometry": {"coordinates":[-0.4503329992,40.8194694519],"type":"Point"}
}