{
  "type": "Feature",
  "properties": {
    "iso:country":"ES",
    "sg:address":"Calle de Santo Tomas, 25",
    "sg:city":"Jaen",
    "sg:orig_category":"Mec\u00c1nico Del Autom\u00d3vil",
    "sg:phone":"+34 953 27 60 21",
    "sg:postcode":"23009",
    "sg:province":"Ja\u00e9n",
    "wof:name":"Valdivia Robles Miguel",
    "wof:placetype":"venue"
},
  "geometry": {"coordinates":[-3.7824149132,37.7758140564],"type":"Point"}
}