{
  "type": "Feature",
  "properties": {
    "iso:country":"ES",
    "sg:address":"Calle de Emilio Tuya, 9",
    "sg:city":"Gijon",
    "sg:orig_category":"Venta, Instalaci\u00d3n De Calefacci\u00d3n",
    "sg:phone":"+34 902 15 87 71",
    "sg:postcode":"33202",
    "sg:province":"Asturias",
    "sg:website":"www.grupo-aci.com",
    "wof:name":"Asturiana De Calefaccion Electrica",
    "wof:placetype":"venue"
},
  "geometry": {"coordinates":[-5.6505489349,43.5394897461],"type":"Point"}
}