{
  "type": "Feature",
  "properties": {
    "addr:full":"Calle de Costa Rica, 6 Caceres C\u00e1ceres 10005",
    "addr:housenumber":"6",
    "addr:postcode":"10005",
    "addr:street":"Calle De Costa Rica;Ca\u0301Ceres",
    "iso:country":"ES",
    "sg:address":"Calle de Costa Rica, 6",
    "sg:city":"Caceres",
    "sg:orig_category":"Fabricaci\u00d3n, Distribuci\u00d3n De Material Para La Climatizaci\u00d3n, Aireaci\u00d3n Y Ventilaci\u00d3n",
    "sg:phone":"+34 927 22 43 14",
    "sg:postcode":"10005",
    "sg:province":"C\u00e1ceres",
    "wof:name":"Galan Pedrosa Leonardo",
    "wof:placetype":"venue"
},
  "geometry": {"coordinates":[-6.3725361824,39.4589080811],"type":"Point"}
}