{
  "type": "Feature",
  "properties": {
    "addr:full":"San Inazio Kalea, 19 Beasain Guip\u00f9zcoa 20200",
    "addr:housenumber":"19",
    "addr:postcode":"20200",
    "addr:street":"San Inazio Kalea;Guipu\u0300Zcoa",
    "iso:country":"ES",
    "sg:address":"San Inazio Kalea, 19",
    "sg:city":"Beasain",
    "sg:orig_category":"Bancos",
    "sg:phone":"+34 943 16 21 19",
    "sg:postcode":"20200",
    "sg:province":"Guip\u00f9zcoa",
    "wof:name":"Euskaltel S.a.",
    "wof:placetype":"venue"
},
  "geometry": {"coordinates":[-2.1969549656,43.0475845337],"type":"Point"}
}