{
  "type": "Feature",
  "properties": {
    "iso:country":"ES",
    "sg:address":"Calle de San Bernardo, 15",
    "sg:city":"Aviles",
    "sg:orig_category":"Pod\u00d3logos: Pedicuros",
    "sg:phone":"+34 985 56 23 10",
    "sg:postcode":"33402",
    "sg:province":"Asturias",
    "wof:name":"Alvarez Campa Alberto",
    "wof:placetype":"venue"
},
  "geometry": {"coordinates":[-5.9231181145,43.5569763184],"type":"Point"}
}