{
  "type": "Feature",
  "properties": {
    "iso:country":"ES",
    "sg:address":"Carrer de Volta, 231",
    "sg:city":"Terrassa",
    "sg:orig_category":"Molduras, Junquillos, Listones Y Molduras Perforadas",
    "sg:phone":"+34 937 89 22 89",
    "sg:postcode":"08224",
    "sg:province":"Barcelona",
    "wof:name":"Negra Gallart Enrique",
    "wof:placetype":"venue"
},
  "geometry": {"coordinates":[1.9997830391,41.5615844727],"type":"Point"}
}