{
  "type": "Feature",
  "properties": {
    "iso:country":"ES",
    "sg:address":"Plaz Sitios (los), 1",
    "sg:city":"Zaragoza",
    "sg:orig_category":"Florister\u00cdas",
    "sg:phone":"+34 976 22 18 06",
    "sg:postcode":"50001",
    "sg:province":"Zaragoza",
    "wof:name":"Ortiz Hernandez Azucena",
    "wof:placetype":"venue"
},
  "geometry": {"coordinates":[-0.8790900111,41.6496772766],"type":"Point"}
}