{
  "type": "Feature",
  "properties": {
    "iso:country":"ES",
    "sg:address":"Calle de Periodista Nicolas Ortega Pagan, 2",
    "sg:city":"Santa Eulalia",
    "sg:orig_category":"Asociaciones, Organismos Culturales Y Socioeducativos",
    "sg:phone":"+34 968 22 14 25",
    "sg:postcode":"30003",
    "sg:province":"Murcia",
    "wof:name":"Liberacion Asociacion Cultural",
    "wof:placetype":"venue"
},
  "geometry": {"coordinates":[-1.124374032,37.9848823547],"type":"Point"}
}