{
  "type": "Feature",
  "properties": {
    "addr:full":"Carr Jose Gascon, 31 Betera Valencia 46117",
    "addr:housenumber":"31",
    "addr:postcode":"46117",
    "addr:street":"Carr Jose Gascon",
    "iso:country":"ES",
    "sg:address":"Carr Jose Gascon, 31",
    "sg:city":"Betera",
    "sg:orig_category":"Reposter\u00cdas",
    "sg:phone":"+34 961 60 12 65",
    "sg:postcode":"46117",
    "sg:province":"Valencia",
    "wof:name":"Forn I Pastisseria Aloy Sl",
    "wof:placetype":"venue"
},
  "geometry": {"coordinates":[-0.4612289965,39.5911750793],"type":"Point"}
}