{
  "type": "Feature",
  "properties": {
    "addr:full":"Selva (parc Negocis Mas Blau I), 12 Prat Llobregat Barcelona 08820",
    "addr:housenumber":"12",
    "addr:postcode":"08820",
    "addr:street":"Llobregat",
    "iso:country":"ES",
    "sg:address":"Selva (parc Negocis Mas Blau I), 12",
    "sg:city":"Prat Llobregat",
    "sg:orig_category":"Carb\u00d3n, Carb\u00d3n De Madera (al Por Mayor)",
    "sg:phone":"+34 932 31 41 11",
    "sg:postcode":"08820",
    "sg:province":"Barcelona",
    "wof:name":"Garcia-munte Energia S.l.",
    "wof:placetype":"venue"
},
  "geometry": {"coordinates":[2.0716540813,41.315826416],"type":"Point"}
}