{
  "type": "Feature",
  "properties": {
    "addr:full":"Av Lloren\u00c7 Puig Tomas, 56 Viladecans Barcelona 08840",
    "addr:housenumber":"56",
    "addr:postcode":"08840",
    "addr:street":"Av Llorenc\u0327 Puig Tomas",
    "iso:country":"ES",
    "sg:address":"Av Lloren\u00c7 Puig Tomas, 56",
    "sg:city":"Viladecans",
    "sg:orig_category":"Institutos De Belleza",
    "sg:phone":"+34 936 58 93 58",
    "sg:postcode":"08840",
    "sg:province":"Barcelona",
    "wof:name":"Parpal Mendieta Maria Del Carmen",
    "wof:placetype":"venue"
},
  "geometry": {"coordinates":[2.0148069859,41.3248214722],"type":"Point"}
}