{
  "type": "Feature",
  "properties": {
    "iso:country":"ES",
    "sg:address":"Avgd Republica Argentina, 51",
    "sg:city":"Gandia",
    "sg:orig_category":"Iglesia Cat\u00d3lica",
    "sg:phone":"+34 962 86 41 27",
    "sg:postcode":"46700",
    "sg:province":"Valencia",
    "wof:name":"Parroquia De Cristo Rey",
    "wof:placetype":"venue"
},
  "geometry": {"coordinates":[-0.1913339943,38.960735321],"type":"Point"}
}