{
  "type": "Feature",
  "properties": {
    "addr:full":"Av Lluis Companys, 18 S. Cugat Valles Barcelona 08172",
    "addr:housenumber":"18",
    "addr:postcode":"08172",
    "addr:street":"Av Lluis Companys;S. Cugat Valles Barcelona",
    "iso:country":"ES",
    "sg:address":"Av Lluis Companys, 18",
    "sg:city":"S. Cugat Valles",
    "sg:orig_category":"Peluqueros: De Se\u00d1oras",
    "sg:phone":"+34 936 74 47 63",
    "sg:postcode":"08172",
    "sg:province":"Barcelona",
    "wof:name":"J.m.s.c.s.l.",
    "wof:placetype":"venue"
},
  "geometry": {"coordinates":[2.0784800053,41.4699325562],"type":"Point"}
}