{
  "type": "Feature",
  "properties": {
    "addr:full":"Avda Paz (de La), 8 Huesca Huesca 22003",
    "addr:housenumber":"8",
    "addr:postcode":"22003",
    "addr:street":"Avda Paz De La",
    "iso:country":"ES",
    "sg:address":"Avda Paz (de La), 8",
    "sg:city":"Huesca",
    "sg:orig_category":"Asociaciones, Organismos Culturales Y Socioeducativos",
    "sg:phone":"+34 974 22 90 08",
    "sg:postcode":"22003",
    "sg:province":"Huesca",
    "wof:name":"Huesca Club De Vehiculos Historicos",
    "wof:placetype":"venue"
},
  "geometry": {"coordinates":[-0.4157089889,42.1393432617],"type":"Point"}
}