{
  "type": "Feature",
  "properties": {
    "iso:country":"ES",
    "sg:address":"Rua Perfectino Vieitez, 16",
    "sg:city":"Carballi\u00f1o",
    "sg:orig_category":"Ropa Para Se\u00d1oras (al Por Menor)",
    "sg:phone":"+34 988 27 42 80",
    "sg:postcode":"32500",
    "sg:province":"Ourense",
    "wof:name":"Alvarez Gonzalez Edelmiro",
    "wof:placetype":"venue"
},
  "geometry": {"coordinates":[-8.0773992538,42.430519104],"type":"Point"}
}