{
  "type": "Feature",
  "properties": {
    "iso:country":"ES",
    "sg:address":"Calle de Casimiro Sainz, 4",
    "sg:city":"Torrelavega",
    "sg:orig_category":"Fabricaci\u00d3n De Material Y Sistemas De Se\u00d1alizaci\u00d3n De Carreteras, Urbanos Y De Obras",
    "sg:phone":"+34 942 89 31 50",
    "sg:postcode":"39300",
    "sg:province":"Cantabria",
    "wof:name":"Distribuciones Exclusivas De Vinos Hercomur S.l.",
    "wof:placetype":"venue"
},
  "geometry": {"coordinates":[-4.0450601578,43.3529243469],"type":"Point"}
}