{
  "type": "Feature",
  "properties": {
    "iso:country":"ES",
    "sg:address":"Calle de Maldonado, 54",
    "sg:city":"Madrid",
    "sg:orig_category":"M\u00c9dicos: Alergolog\u00cda",
    "sg:phone":"+34 913 09 03 07",
    "sg:postcode":"28006",
    "sg:province":"Madrid",
    "wof:name":"De Buen Sanchez Clementina",
    "wof:placetype":"venue"
},
  "geometry": {"coordinates":[-3.6753120422,40.4333496094],"type":"Point"}
}