{
  "type": "Feature",
  "properties": {
    "iso:country":"ES",
    "sg:address":"Carrer de Sant Antoni, 11",
    "sg:city":"Castellbisbal",
    "sg:orig_category":"Empresas De Desmonte",
    "sg:phone":"+34 937 72 12 55",
    "sg:postcode":"08755",
    "sg:province":"Barcelona",
    "wof:name":"Muset Padros Isidro",
    "wof:placetype":"venue"
},
  "geometry": {"coordinates":[1.9818810225,41.4750709534],"type":"Point"}
}