{
  "type": "Feature",
  "properties": {
    "iso:country":"ES",
    "sg:address":"Calle de Medina Y Galnares, 117",
    "sg:city":"Sevilla",
    "sg:orig_category":"Hielo Artificial (fabricaci\u00d3n, Distribuci\u00d3n)",
    "sg:phone":"+34 954 38 11 79",
    "sg:postcode":"41015",
    "sg:province":"Sevilla",
    "wof:name":"Hielo Car Castellano S.l.",
    "wof:placetype":"venue"
},
  "geometry": {"coordinates":[-5.9811220169,37.429107666],"type":"Point"}
}