{
  "type": "Feature",
  "properties": {
    "addr:full":"Rua Illas Baleares, 22 Vigo Pontevedra 36203",
    "addr:housenumber":"22",
    "addr:postcode":"36203",
    "addr:street":"Rua Illas Baleares",
    "iso:country":"ES",
    "sg:address":"Rua Illas Baleares, 22",
    "sg:city":"Vigo",
    "sg:orig_category":"Farmacias",
    "sg:phone":"+34 986 41 97 10",
    "sg:postcode":"36203",
    "sg:province":"Pontevedra",
    "wof:name":"Lopez Barrero Maria Del Carmen",
    "wof:placetype":"venue"
},
  "geometry": {"coordinates":[-8.723151207,42.226650238],"type":"Point"}
}