{
  "type": "Feature",
  "properties": {
    "addr:full":"Calle de Vera Cruz, 47 S. Adrian Navarra 31570",
    "addr:housenumber":"47",
    "addr:postcode":"31570",
    "addr:street":"Calle De Vera Cruz;S. Adrian Navarra",
    "iso:country":"ES",
    "sg:address":"Calle de Vera Cruz, 47",
    "sg:city":"S. Adrian",
    "sg:orig_category":"Plomeros",
    "sg:phone":"+34 948 67 07 78",
    "sg:postcode":"31570",
    "sg:province":"Navarra",
    "wof:name":"Casado Fernandez Jose Antonio",
    "wof:placetype":"venue"
},
  "geometry": {"coordinates":[-1.9396560192,42.3350601196],"type":"Point"}
}