{
  "type": "Feature",
  "properties": {
    "iso:country":"ES",
    "sg:address":"Calle de Forata, 4",
    "sg:city":"Valencia",
    "sg:orig_category":"Promotores Constructores",
    "sg:phone":"+34 963 57 71 51",
    "sg:postcode":"46017",
    "sg:province":"Valencia",
    "wof:name":"Coopropietarios Forata",
    "wof:placetype":"venue"
},
  "geometry": {"coordinates":[-0.3936879933,39.4507446289],"type":"Point"}
}