{
  "type": "Feature",
  "properties": {
    "iso:country":"ES",
    "sg:address":"Carr Lleida, Km. 0471,0",
    "sg:city":"Alamus",
    "sg:orig_category":"Hoteles",
    "sg:phone":"+34 973 19 91 88",
    "sg:postcode":"25221",
    "sg:province":"Lleida",
    "wof:name":"Pecrime S.a.",
    "wof:placetype":"venue"
},
  "geometry": {"coordinates":[0.7368059754,41.6161804199],"type":"Point"}
}