{
  "type": "Feature",
  "properties": {
    "addr:full":"Calle de Chiquinquira, 6 Madrid Madrid 28033",
    "addr:housenumber":"6",
    "addr:postcode":"28033",
    "addr:street":"Calle De Chiquinquira",
    "iso:country":"ES",
    "sg:address":"Calle de Chiquinquira, 6",
    "sg:city":"Madrid",
    "sg:orig_category":"Asociaciones Y Clubs Deportivos",
    "sg:phone":"+34 917 63 91 14",
    "sg:postcode":"28033",
    "sg:province":"Madrid",
    "wof:name":"Gonzalez Deus Antonio Anibal",
    "wof:placetype":"venue"
},
  "geometry": {"coordinates":[-3.6385846138,40.4718856812],"type":"Point"}
}