{
  "type": "Feature",
  "properties": {
    "addr:full":"Quimica, S/n Alcazar S. Juan Ciudad Real 13600",
    "addr:housenumber":"s / n",
    "addr:postcode":"13600",
    "addr:street":"Quimica;Alcazar S. Juan Ciudad Real",
    "iso:country":"ES",
    "sg:address":"Quimica, S/n",
    "sg:city":"Alcazar S. Juan",
    "sg:orig_category":"Serigraf\u00cda",
    "sg:phone":"+34 926 54 13 07",
    "sg:postcode":"13600",
    "sg:province":"Ciudad Real",
    "wof:name":"Grafimancha 2002 S.l.",
    "wof:placetype":"venue"
},
  "geometry": {"coordinates":[-3.2269239426,39.3956413269],"type":"Point"}
}