{
  "type": "Feature",
  "properties": {
    "addr:full":"Calle de Rio Chico, 11 Guardo Palencia 34880",
    "addr:housenumber":"11",
    "addr:postcode":"34880",
    "addr:street":"Calle De Rio Chico",
    "iso:country":"ES",
    "sg:address":"Calle de Rio Chico, 11",
    "sg:city":"Guardo",
    "sg:orig_category":"Empresas De Pintura Y Revestimientos",
    "sg:phone":"+34 979 85 22 79",
    "sg:postcode":"34880",
    "sg:province":"Palencia",
    "wof:name":"Decoracion Y Pinturas Carmelo S.l.",
    "wof:placetype":"venue"
},
  "geometry": {"coordinates":[-4.8461289406,42.7899703979],"type":"Point"}
}