{
  "type": "Feature",
  "properties": {
    "iso:country":"ES",
    "sg:address":"Calle de Heroes Del Alcazar, 10",
    "sg:city":"Torrijos",
    "sg:orig_category":"Transportes Por Carretera: Lotes Completos, Mercanc\u00cdas Diversas",
    "sg:phone":"+34 925 77 03 98",
    "sg:postcode":"45500",
    "sg:province":"Toledo",
    "wof:name":"Alonso Gonzalez Felipe",
    "wof:placetype":"venue"
},
  "geometry": {"coordinates":[-4.2860512733,39.9786148071],"type":"Point"}
}