{
  "type": "Feature",
  "properties": {
    "addr:full":"Calle de Orense, 29 Madrid Madrid 28020",
    "addr:housenumber":"29",
    "addr:postcode":"madrid;28020",
    "addr:street":"Calle De Orense",
    "iso:country":"ES",
    "sg:address":"Calle de Orense, 29",
    "sg:city":"Madrid",
    "sg:orig_category":"Asesor\u00cda Sobre Comunicaci\u00d3n De Empresas",
    "sg:phone":"+34 915 97 44 90",
    "sg:postcode":"28020",
    "sg:province":"Madrid",
    "wof:name":"Garcia Diaz Leonor",
    "wof:placetype":"venue"
},
  "geometry": {"coordinates":[-3.6952440739,40.4519233704],"type":"Point"}
}