{
  "type": "Feature",
  "properties": {
    "addr:full":"Calle de Hermanos Velasco Lopez, 11 Torrelodones Madrid 28250",
    "addr:housenumber":"11",
    "addr:postcode":"28250",
    "addr:street":"Calle De Hermanos Velasco Lopez",
    "iso:country":"ES",
    "sg:address":"Calle de Hermanos Velasco Lopez, 11",
    "sg:city":"Torrelodones",
    "sg:orig_category":"Laboratorios Y Cl\u00cdnicas Veterinarias",
    "sg:phone":"+34 918 59 47 75",
    "sg:postcode":"28250",
    "sg:province":"Madrid",
    "wof:name":"Morgade Salgado Inmaculada Concepcion",
    "wof:placetype":"venue"
},
  "geometry": {"coordinates":[-3.9277207851,40.5767936707],"type":"Point"}
}