{
  "type": "Feature",
  "properties": {
    "iso:country":"ES",
    "sg:address":"Ctra. Valdepe\u00f1as, S/n",
    "sg:city":"Cozar",
    "sg:orig_category":"Fabricaci\u00d3n De Enlosados, Soler\u00cdas",
    "sg:phone":"+34 926 69 41 00",
    "sg:postcode":"13345",
    "sg:province":"Ciudad Real",
    "wof:name":"Alcalaten S.l.",
    "wof:placetype":"venue"
},
  "geometry": {"coordinates":[-3.0760536194,38.6584854126],"type":"Point"}
}