{
  "type": "Feature",
  "properties": {
    "iso:country":"ES",
    "sg:address":"Calle de Purissima, 28",
    "sg:city":"Nules",
    "sg:orig_category":"Electrodom\u00c9sticos (al Por Menor)",
    "sg:phone":"+34 964 67 47 80",
    "sg:postcode":"12520",
    "sg:province":"Castell\u00f3n",
    "wof:name":"Ripolles Portales Vicente",
    "wof:placetype":"venue"
},
  "geometry": {"coordinates":[-0.153222993,39.8570175171],"type":"Point"}
}