{
  "type": "Feature",
  "properties": {
    "addr:full":"Real, 28 Cadiar Granada 18440",
    "addr:housenumber":"28",
    "addr:postcode":"18440",
    "addr:street":"Real",
    "iso:country":"ES",
    "sg:address":"Real, 28",
    "sg:city":"Cadiar",
    "sg:orig_category":"Bisuter\u00cda, Joyer\u00cda, Relojer\u00cda (al Por Menor)",
    "sg:phone":"+34 958 76 80 25",
    "sg:postcode":"18440",
    "sg:province":"Granada",
    "wof:name":"Martin Montoliva Francisca",
    "wof:placetype":"venue"
},
  "geometry": {"coordinates":[-3.1801640987,36.9440383911],"type":"Point"}
}