{
  "type": "Feature",
  "properties": {
    "addr:full":"Calle de Sevilla, 6 Jerez De La Frontera C\u00e1diz 11402",
    "addr:housenumber":"6",
    "addr:postcode":"11402",
    "addr:street":"Calle De Sevilla",
    "iso:country":"ES",
    "sg:address":"Calle de Sevilla, 6",
    "sg:city":"Jerez De La Frontera",
    "sg:orig_category":"Cajas De Ahorro",
    "sg:phone":"+34 956 32 64 37",
    "sg:postcode":"11402",
    "sg:province":"C\u00e1diz",
    "wof:name":"Caixa D'estalvis I Pensions De Barcelona",
    "wof:placetype":"venue"
},
  "geometry": {"coordinates":[-6.1360192299,36.690071106],"type":"Point"}
}