{
  "type": "Feature",
  "properties": {
    "addr:full":"Calle de Gonzalo Bilbao, 23 Sevilla Sevilla 41003",
    "addr:housenumber":"23",
    "addr:postcode":"41003",
    "addr:street":"Calle De Gonzalo Bilbao",
    "iso:country":"ES",
    "sg:address":"Calle de Gonzalo Bilbao, 23",
    "sg:city":"Sevilla",
    "sg:orig_category":"Promotores Constructores",
    "sg:phone":"+34 954 54 03 82",
    "sg:postcode":"41003",
    "sg:province":"Sevilla",
    "wof:name":"Construcciones Direcop S.l.",
    "wof:placetype":"venue"
},
  "geometry": {"coordinates":[-5.9814171791,37.3925514221],"type":"Point"}
}