{
  "type": "Feature",
  "properties": {
    "addr:full":"Ander Deuna, 15 Bermeo Vizcaya 48370",
    "addr:housenumber":"15",
    "addr:postcode":"48370",
    "addr:street":"Ander Deuna",
    "iso:country":"ES",
    "sg:address":"Ander Deuna, 15",
    "sg:city":"Bermeo",
    "sg:orig_category":"Mec\u00c1nico Del Autom\u00d3vil",
    "sg:phone":"+34 946 18 67 89",
    "sg:postcode":"48370",
    "sg:province":"Vizcaya",
    "wof:name":"Juan Pedro Garay Landa (talleres Garay)",
    "wof:placetype":"venue"
},
  "geometry": {"coordinates":[-2.7294991016,43.416633606],"type":"Point"}
}