{
  "type": "Feature",
  "properties": {
    "iso:country":"ES",
    "sg:address":"Avda Juan Sebastian Elcano, 3",
    "sg:city":"Malaga",
    "sg:orig_category":"Ingenier\u00cda, Centros De Estudios (diversos)",
    "sg:phone":"+34 952 29 27 27",
    "sg:postcode":"29017",
    "sg:province":"M\u00e1laga",
    "wof:name":"Vasserot Fuentes Matias Adolfo",
    "wof:placetype":"venue"
},
  "geometry": {"coordinates":[-4.3796601295,36.7220039368],"type":"Point"}
}