{
  "type": "Feature",
  "properties": {
    "iso:country":"ES",
    "sg:address":"Avda Fuente De Las Piedras, S/n",
    "sg:city":"Cabra",
    "sg:orig_category":"Art\u00cdculos De Decoraci\u00d3n",
    "sg:phone":"+34 957 52 02 75",
    "sg:postcode":"14940",
    "sg:province":"C\u00f3rdoba",
    "sg:website":"www.promi.es",
    "wof:name":"Muebles Promi S.l.",
    "wof:placetype":"venue"
},
  "geometry": {"coordinates":[-4.4420938492,37.4775657654],"type":"Point"}
}