{
  "type": "Feature",
  "properties": {
    "addr:full":"Calle de Humilladero, 21 Sig\u00fcenza Guadalajara 19250",
    "addr:housenumber":"21",
    "addr:postcode":"19250",
    "addr:street":"Calle De Humilladero",
    "iso:country":"ES",
    "sg:address":"Calle de Humilladero, 21",
    "sg:city":"Sig\u00fcenza",
    "sg:orig_category":"Carnicer\u00cdas, Carnicer\u00cdas",
    "sg:phone":"+34 949 39 14 12",
    "sg:postcode":"19250",
    "sg:province":"Guadalajara",
    "wof:name":"Carniceria Garcia S.l",
    "wof:placetype":"venue"
},
  "geometry": {"coordinates":[-2.64407897,41.0689697266],"type":"Point"}
}