{
  "type": "Feature",
  "properties": {
    "iso:country":"ES",
    "sg:address":"Avda Portugal, 1",
    "sg:city":"Logro\u00f1o",
    "sg:orig_category":"Tintorer\u00cdas, Limpieza En Seco",
    "sg:phone":"+34 941 22 21 62",
    "sg:postcode":"26001",
    "sg:province":"La Rioja",
    "wof:name":"Blazquez Madariaga Jose Ramon",
    "wof:placetype":"venue"
},
  "geometry": {"coordinates":[-2.4480800629,42.4641685486],"type":"Point"}
}