{
  "type": "Feature",
  "properties": {
    "iso:country":"ES",
    "sg:address":"Calle de Sevilla, 32",
    "sg:city":"Armilla",
    "sg:orig_category":"Farmacias",
    "sg:phone":"+34 958 55 37 77",
    "sg:postcode":"18100",
    "sg:province":"Granada",
    "wof:name":"Sanchez Alonso Francisco",
    "wof:placetype":"venue"
},
  "geometry": {"coordinates":[-3.6237928867,37.1415901184],"type":"Point"}
}