{
  "type": "Feature",
  "properties": {
    "addr:full":"Calle de Centelles, Los, 28 Valencia Valencia 46006",
    "addr:housenumber":"28",
    "addr:postcode":"46006",
    "addr:street":"Calle De Centelles Los",
    "iso:country":"ES",
    "sg:address":"Calle de Centelles, Los, 28",
    "sg:city":"Valencia",
    "sg:orig_category":"Reposter\u00cdas",
    "sg:phone":"+34 963 34 84 52",
    "sg:postcode":"46006",
    "sg:province":"Valencia",
    "wof:name":"A\u00f1o Casanova Antonia",
    "wof:placetype":"venue"
},
  "geometry": {"coordinates":[-0.3724228144,39.4594955444],"type":"Point"}
}