{
  "type": "Feature",
  "properties": {
    "addr:full":"Avda Ciudad De Mataro, S/n Cehegin Murcia 30430",
    "addr:housenumber":"s / n",
    "addr:postcode":"30430",
    "addr:street":"Avda Ciudad De Mataro",
    "iso:country":"ES",
    "sg:address":"Avda Ciudad De Mataro, S/n",
    "sg:city":"Cehegin",
    "sg:orig_category":"Carnicer\u00cdas, Carnicer\u00cdas",
    "sg:phone":"+34 968 74 03 30",
    "sg:postcode":"30430",
    "sg:province":"Murcia",
    "wof:name":"Fernandez Martinez Jose Luis",
    "wof:placetype":"venue"
},
  "geometry": {"coordinates":[-1.7968540192,38.0949249268],"type":"Point"}
}