{
  "type": "Feature",
  "properties": {
    "iso:country":"ES",
    "sg:address":"Calle de Ubeda, 17",
    "sg:city":"Linares",
    "sg:orig_category":"T\u00c9cnicos Veterinarios",
    "sg:phone":"+34 953 69 70 55",
    "sg:postcode":"23700",
    "sg:province":"Ja\u00e9n",
    "wof:name":"Martin Cruz Antonio",
    "wof:placetype":"venue"
},
  "geometry": {"coordinates":[-3.6174190044,38.0962905884],"type":"Point"}
}