{
  "type": "Feature",
  "properties": {
    "iso:country":"ES",
    "sg:address":"Ctr. Jorquera, Km. 0000,8",
    "sg:city":"Casas Juan Nu\u00f1ez",
    "sg:orig_category":"Producci\u00d3n, Comercio De Cereales",
    "sg:phone":"+34 967 57 20 49",
    "sg:postcode":"02151",
    "sg:province":"Albacete",
    "wof:name":"Vega Del Jucar S.l.",
    "wof:placetype":"venue"
},
  "geometry": {"coordinates":[-1.5579140186,39.1002540588],"type":"Point"}
}