{
  "type": "Feature",
  "properties": {
    "addr:full":"Calle de Hernan Cortes, 82 Villanueva Serena Badajoz 06700",
    "addr:housenumber":"82",
    "addr:postcode":"06700",
    "addr:street":"Calle De Hernan Cortes",
    "iso:country":"ES",
    "sg:address":"Calle de Hernan Cortes, 82",
    "sg:city":"Villanueva Serena",
    "sg:orig_category":"Ropa Para Se\u00d1oras Y Caballeros (al Por Menor)",
    "sg:phone":"+34 924 84 52 34",
    "sg:postcode":"06700",
    "sg:province":"Badajoz",
    "wof:name":"Corraliza Escobar Juana",
    "wof:placetype":"venue"
},
  "geometry": {"coordinates":[-5.7927851677,38.9742088318],"type":"Point"}
}