{
  "type": "Feature",
  "properties": {
    "addr:full":"Doctor Gortari, 1 Iru\u00f1a Navarra 31012",
    "addr:housenumber":"1",
    "addr:postcode":"31012",
    "addr:street":"Doctor Gortari",
    "iso:country":"ES",
    "sg:address":"Doctor Gortari, 1",
    "sg:city":"Iru\u00f1a",
    "sg:orig_category":"Farmacias",
    "sg:phone":"+34 948 14 17 51",
    "sg:postcode":"31012",
    "sg:province":"Navarra",
    "wof:name":"Liberal Romero Alicia",
    "wof:placetype":"venue"
},
  "geometry": {"coordinates":[-1.6682219505,42.8211631775],"type":"Point"}
}