{
  "type": "Feature",
  "properties": {
    "addr:full":"Calle de Estadio, 5 Valladolid Valladolid 47006",
    "addr:housenumber":"5",
    "addr:postcode":"47006",
    "addr:street":"Calle De Estadio",
    "iso:country":"ES",
    "sg:address":"Calle de Estadio, 5",
    "sg:city":"Valladolid",
    "sg:orig_category":"Caf\u00c9s, Bares, Cervecer\u00cdas",
    "sg:phone":"+34 983 27 87 09",
    "sg:postcode":"47006",
    "sg:province":"Valladolid",
    "wof:name":"Arnaez Rodriguez Francisco",
    "wof:placetype":"venue"
},
  "geometry": {"coordinates":[-4.7392268181,41.6393737793],"type":"Point"}
}