{
  "type": "Feature",
  "properties": {
    "iso:country":"ES",
    "sg:address":"Calle de Barranco Del Molino, 2",
    "sg:city":"Autol",
    "sg:orig_category":"Panader\u00cdas, Panader\u00cdas",
    "sg:phone":"+34 941 39 04 49",
    "sg:postcode":"26560",
    "sg:province":"La Rioja",
    "wof:name":"Miranda Mazo Maria Del Carmen",
    "wof:placetype":"venue"
},
  "geometry": {"coordinates":[-2.0068666935,42.2198143005],"type":"Point"}
}