{
  "type": "Feature",
  "properties": {
    "addr:full":"Almazara, 9 Benirrama Alicante 03787",
    "addr:housenumber":"9",
    "addr:postcode":"03787",
    "addr:street":"Almazara;Alicante",
    "iso:country":"ES",
    "sg:address":"Almazara, 9",
    "sg:city":"Benirrama",
    "sg:orig_category":"Arboricultura Y Producci\u00d3n De Frutas",
    "sg:phone":"+34 965 57 28 85",
    "sg:postcode":"03787",
    "sg:province":"Alicante",
    "wof:name":"Cerezas Monta\u00d1a-alicante Cooperativa Sda",
    "wof:placetype":"venue"
},
  "geometry": {"coordinates":[-0.194562003,38.8311080933],"type":"Point"}
}