{
  "type": "Feature",
  "properties": {
    "addr:full":"Progreso, 3 Ciudad Rodrigo Salamanca 37500",
    "addr:housenumber":"3",
    "addr:postcode":"37500",
    "addr:street":"Progreso",
    "iso:country":"ES",
    "sg:address":"Progreso, 3",
    "sg:city":"Ciudad Rodrigo",
    "sg:orig_category":"Escayola Y Productos De Escayola (fabricaci\u00d3n, Al Por Mayor)",
    "sg:phone":"+34 923 46 16 45",
    "sg:postcode":"37500",
    "sg:province":"Salamanca",
    "wof:name":"Escayolas Gaspar Cb",
    "wof:placetype":"venue"
},
  "geometry": {"coordinates":[-6.5599341393,40.575088501],"type":"Point"}
}