{
  "type": "Feature",
  "properties": {
    "addr:full":"Calle de Rey, 31 Plasencia C\u00e1ceres 10600",
    "addr:housenumber":"31",
    "addr:postcode":"10600",
    "addr:street":"Calle De Rey;Ca\u0301Ceres",
    "iso:country":"ES",
    "sg:address":"Calle de Rey, 31",
    "sg:city":"Plasencia",
    "sg:orig_category":"Inform\u00c1tica, Ofim\u00c1tica (estudios, Asesor\u00cda, Ingenier\u00cda, Formaci\u00d3n)",
    "sg:phone":"+34 927 42 19 36",
    "sg:postcode":"10600",
    "sg:province":"C\u00e1ceres",
    "wof:name":"Amor Mu\u00f1oz Carmelo",
    "wof:placetype":"venue"
},
  "geometry": {"coordinates":[-6.088927269,40.0308074951],"type":"Point"}
}