{
  "type": "Feature",
  "properties": {
    "iso:country":"ES",
    "sg:address":"Calle de Traseras, 26",
    "sg:city":"Bularros",
    "sg:orig_category":"Contenedores (mercanc\u00cdas)",
    "sg:phone":"+34 920 20 80 93",
    "sg:postcode":"05140",
    "sg:province":"\u00c1vila",
    "wof:name":"Mate Sanchez Ramon",
    "wof:placetype":"venue"
},
  "geometry": {"coordinates":[-97.78224945069999,45.7040786743],"type":"Point"}
}