{
  "type": "Feature",
  "properties": {
    "addr:full":"Calle de Joaquin Gonzalo, S/n Carbajosa Sagrada Salamanca 37188",
    "addr:housenumber":"s / n",
    "addr:postcode":"37188",
    "addr:street":"Calle De Joaquin Gonzalo",
    "iso:country":"ES",
    "sg:address":"Calle de Joaquin Gonzalo, S/n",
    "sg:city":"Carbajosa Sagrada",
    "sg:orig_category":"Empresas De Demolici\u00d3n",
    "sg:phone":"+34 923 20 82 49",
    "sg:postcode":"37188",
    "sg:province":"Salamanca",
    "wof:name":"Transportes Y Excavaciones Felix Lopez S.l.",
    "wof:placetype":"venue"
},
  "geometry": {"coordinates":[-5.6512241364,40.9352874756],"type":"Point"}
}