{
  "type": "Feature",
  "properties": {
    "addr:full":"Calle de Canalejas, 4 Zaragoza Zaragoza 50001",
    "addr:housenumber":"4",
    "addr:postcode":"50001",
    "addr:street":"Calle De Canalejas",
    "iso:country":"ES",
    "sg:address":"Calle de Canalejas, 4",
    "sg:city":"Zaragoza",
    "sg:orig_category":"Promotores Constructores",
    "sg:phone":"+34 976 21 19 02",
    "sg:postcode":"50001",
    "sg:province":"Zaragoza",
    "wof:name":"Promociones Penaerata S.l.",
    "wof:placetype":"venue"
},
  "geometry": {"coordinates":[-0.8786634803,41.647857666],"type":"Point"}
}