{
  "type": "Feature",
  "properties": {
    "iso:country":"ES",
    "sg:address":"Calle de Rosales, 22",
    "sg:city":"Aranda Duero",
    "sg:orig_category":"Fabricaci\u00d3n, Venta, Instalaci\u00d3n De R\u00d3tulos, De R\u00d3tulos Luminosos",
    "sg:phone":"+34 947 50 57 85",
    "sg:postcode":"09400",
    "sg:province":"Burgos",
    "wof:name":"Bravo Pe\u00f1a Isidro",
    "wof:placetype":"venue"
},
  "geometry": {"coordinates":[-3.693723917,41.6662368774],"type":"Point"}
}