{
  "type": "Feature",
  "properties": {
    "iso:country":"ES",
    "sg:address":"Avgd Alcalde Pujol, 11",
    "sg:city":"Lleida",
    "sg:orig_category":"Arquitectos",
    "sg:phone":"+34 973 27 14 10",
    "sg:postcode":"25006",
    "sg:province":"Lleida",
    "wof:name":"A3 Arola Arquitecto Y Asociados S.l.",
    "wof:placetype":"venue"
},
  "geometry": {"coordinates":[0.611866,41.620346],"type":"Point"}
}