{
  "type": "Feature",
  "properties": {
    "addr:full":"Ctra Navalpino, 13 Toledo Toledo 45004",
    "addr:housenumber":"13",
    "addr:postcode":"45004",
    "addr:street":"Ctra Navalpino",
    "iso:country":"ES",
    "sg:address":"Ctra Navalpino, 13",
    "sg:city":"Toledo",
    "sg:orig_category":"Venta, Montaje De Neum\u00c1ticos",
    "sg:phone":"+34 925 25 71 31",
    "sg:postcode":"45004",
    "sg:province":"Toledo",
    "wof:name":"Espinosa Gomez Jose Angel",
    "wof:placetype":"venue"
},
  "geometry": {"coordinates":[-4.0373430252,39.8586883545],"type":"Point"}
}