{
  "type": "Feature",
  "properties": {
    "iso:country":"ES",
    "sg:address":"Carrer de Balmes, 63",
    "sg:city":"Castellar Valles",
    "sg:orig_category":"Caf\u00c9s, Bares, Cervecer\u00cdas",
    "sg:phone":"+34 937 14 83 73",
    "sg:postcode":"08211",
    "sg:province":"Barcelona",
    "wof:name":"Romero Duran Juan",
    "wof:placetype":"venue"
},
  "geometry": {"coordinates":[2.0896000862,41.6121101379],"type":"Point"}
}