{
  "type": "Feature",
  "properties": {
    "iso:country":"ES",
    "sg:address":"Carrer de Marina, 12",
    "sg:city":"Almeda Mercader",
    "sg:orig_category":"Metalurgia: Maquinaria Y Equipos",
    "sg:phone":"+34 934 74 02 28",
    "sg:postcode":"08940",
    "sg:province":"Barcelona",
    "sg:website":"www.amada-iberica.es",
    "wof:name":"Amada Maquinaria S.l.",
    "wof:placetype":"venue"
},
  "geometry": {"coordinates":[2.1122398376,41.3495368958],"type":"Point"}
}