{
  "type": "Feature",
  "properties": {
    "iso:country":"ES",
    "sg:address":"Carrer de Major, 19",
    "sg:city":"Deltebre",
    "sg:orig_category":"Perfumer\u00cda, Art\u00cdculos De Ba\u00d1o (fabricaci\u00d3n, Al Por Mayor)",
    "sg:phone":"+34 977 48 14 56",
    "sg:postcode":"43580",
    "sg:province":"Tarragona",
    "wof:name":"Ramirez Fresquet Carolina",
    "wof:placetype":"venue"
},
  "geometry": {"coordinates":[0.73486799,40.7180290222],"type":"Point"}
}