{
  "type": "Feature",
  "properties": {
    "addr:full":"Ctra Santa Creu De Calafell, 108 S. Boi Llobregat Barcelona 08830",
    "addr:housenumber":"108",
    "addr:postcode":"08830",
    "addr:street":"Ctra Santa Creu De Calafell;S.",
    "iso:country":"ES",
    "sg:address":"Ctra Santa Creu De Calafell, 108",
    "sg:city":"S. Boi Llobregat",
    "sg:orig_category":"Papel (al Por Mayor)",
    "sg:phone":"+34 936 30 77 33",
    "sg:postcode":"08830",
    "sg:province":"Barcelona",
    "wof:name":"Papeles Para La Alimentacion S.a.",
    "wof:placetype":"venue"
},
  "geometry": {"coordinates":[2.0334870815,41.3261299133],"type":"Point"}
}