{
  "type": "Feature",
  "properties": {
    "addr:full":"Carrer de Major, 1 Asco Tarragona 43791",
    "addr:housenumber":"1",
    "addr:postcode":"43791",
    "addr:street":"Carrer De Major",
    "iso:country":"ES",
    "sg:address":"Carrer de Major, 1",
    "sg:city":"Asco",
    "sg:orig_category":"Conservatorios",
    "sg:phone":"+34 977 40 40 22",
    "sg:postcode":"43791",
    "sg:province":"Tarragona",
    "wof:name":"Ajuntament D'asco",
    "wof:placetype":"venue"
},
  "geometry": {"coordinates":[0.5681725144,41.1797904968],"type":"Point"}
}