{
  "type": "Feature",
  "properties": {
    "iso:country":"ES",
    "sg:address":"Calle de Ruperto Escobar, 66",
    "sg:city":"Umbrete",
    "sg:orig_category":"Bebidas",
    "sg:phone":"+34 955 71 60 64",
    "sg:postcode":"41806",
    "sg:province":"Sevilla",
    "wof:name":"Distribuciones Ito S.c.",
    "wof:placetype":"venue"
},
  "geometry": {"coordinates":[-6.1527481079,37.3689079285],"type":"Point"}
}