{
  "type": "Feature",
  "properties": {
    "addr:full":"Av America, 51 Mataro Barcelona 08304",
    "addr:housenumber":"51",
    "addr:postcode":"08304",
    "addr:street":"Av America",
    "iso:country":"ES",
    "sg:address":"Av America, 51",
    "sg:city":"Mataro",
    "sg:orig_category":"Estancos",
    "sg:phone":"+34 937 96 04 59",
    "sg:postcode":"08304",
    "sg:province":"Barcelona",
    "wof:name":"Sanchez Martinez Manuel",
    "wof:placetype":"venue"
},
  "geometry": {"coordinates":[2.4501669407,41.5473632812],"type":"Point"}
}