{
  "type": "Feature",
  "properties": {
    "iso:country":"ES",
    "sg:address":"Calle de Jesus Fernandez Duro, 6",
    "sg:city":"Langreo",
    "sg:orig_category":"Cerrajer\u00cda, Ferrallista",
    "sg:phone":"+34 985 67 86 96",
    "sg:postcode":"33930",
    "sg:province":"Asturias",
    "wof:name":"Tania Y Elena  Hosteleros Asociados S.l",
    "wof:placetype":"venue"
},
  "geometry": {"coordinates":[-5.6889190674,43.3080101013],"type":"Point"}
}