{
  "type": "Feature",
  "properties": {
    "iso:country":"ES",
    "sg:address":"Carrer de Ramon Berenguer Iv (de), S/n",
    "sg:city":"Salou",
    "sg:orig_category":"Peluqueros: De Se\u00d1oras",
    "sg:phone":"+34 977 35 24 09",
    "sg:postcode":"43840",
    "sg:province":"Tarragona",
    "wof:name":"Torres Cabello Ana",
    "wof:placetype":"venue"
},
  "geometry": {"coordinates":[1.1401950121,41.0768356323],"type":"Point"}
}