{
  "type": "Feature",
  "properties": {
    "addr:full":"Calle de San Juan, 8 Alsasua Navarra 31800",
    "addr:housenumber":"8",
    "addr:postcode":"31800",
    "addr:street":"Calle De San Juan",
    "iso:country":"ES",
    "sg:address":"Calle de San Juan, 8",
    "sg:city":"Alsasua",
    "sg:orig_category":"Panader\u00cdas, Panader\u00cdas",
    "sg:phone":"+34 948 56 31 92",
    "sg:postcode":"31800",
    "sg:province":"Navarra",
    "wof:name":"Lecea Zufiaurre Miguel Angel",
    "wof:placetype":"venue"
},
  "geometry": {"coordinates":[-2.17157197,42.8955879211],"type":"Point"}
}