{
  "type": "Feature",
  "properties": {
    "iso:country":"ES",
    "sg:address":"Carr Mestre Serrano, 9",
    "sg:city":"Villarreal",
    "sg:orig_category":"Molduras, Junquillos, Listones Y Molduras Perforadas",
    "sg:phone":"+34 964 52 47 68",
    "sg:postcode":"12540",
    "sg:province":"Castell\u00f3n",
    "wof:name":"Garcia Palomares Jose",
    "wof:placetype":"venue"
},
  "geometry": {"coordinates":[-0.1123040989,39.9373855591],"type":"Point"}
}