{
  "type": "Feature",
  "properties": {
    "iso:country":"ES",
    "sg:address":"Av Alexandre Rossello, 15",
    "sg:city":"Palma",
    "sg:orig_category":"Inform\u00c1tica: Consultores",
    "sg:phone":"+34 971 71 60 70",
    "sg:postcode":"07002",
    "sg:province":"Islas Baleares",
    "sg:website":"www.grupovjofre.com",
    "wof:name":"Auditoria Y Consulting Balear S.l.",
    "wof:placetype":"venue"
},
  "geometry": {"coordinates":[2.6557519436,39.5734939575],"type":"Point"}
}