{
  "type": "Feature",
  "properties": {
    "addr:full":"Calle de Arcos, 11 Jerez De La Frontera C\u00e1diz 11402",
    "addr:housenumber":"11",
    "addr:postcode":"11402",
    "addr:street":"Calle De Arcos",
    "iso:country":"ES",
    "sg:address":"Calle de Arcos, 11",
    "sg:city":"Jerez De La Frontera",
    "sg:orig_category":"Tatuajes",
    "sg:phone":"+34 956 34 89 11",
    "sg:postcode":"11402",
    "sg:province":"C\u00e1diz",
    "sg:website":"www.jereztatu.esp.st",
    "wof:name":"Vallano Jimenez Arturo",
    "wof:placetype":"venue"
},
  "geometry": {"coordinates":[-6.1346378326,36.6835975647],"type":"Point"}
}