{
  "type": "Feature",
  "properties": {
    "addr:full":"Calle de Francisco De Nebreda, 6 Avila \u00c1vila 05005",
    "addr:housenumber":"6",
    "addr:postcode":"05005",
    "addr:street":"Calle De Francisco De Nebreda;A\u0301Vila",
    "iso:country":"ES",
    "sg:address":"Calle de Francisco De Nebreda, 6",
    "sg:city":"Avila",
    "sg:orig_category":"Lavado, Limpieza De Veh\u00cdculos",
    "sg:phone":"+34 920 22 62 32",
    "sg:postcode":"05005",
    "sg:province":"\u00c1vila",
    "wof:name":"Ayuso Montalvo Andres",
    "wof:placetype":"venue"
},
  "geometry": {"coordinates":[-4.6929540634,40.6590194702],"type":"Point"}
}