{
  "type": "Feature",
  "properties": {
    "addr:full":"Calle de Aldapa, 9 Leioa Vizcaya 48940",
    "addr:housenumber":"9",
    "addr:postcode":"48940",
    "addr:street":"Calle De Aldapa",
    "iso:country":"ES",
    "sg:address":"Calle de Aldapa, 9",
    "sg:city":"Leioa",
    "sg:orig_category":"Molduras, Junquillos, Listones Y Molduras Perforadas",
    "sg:phone":"+34 944 64 57 96",
    "sg:postcode":"48940",
    "sg:province":"Vizcaya",
    "wof:name":"David Gil Fernandez",
    "wof:placetype":"venue"
},
  "geometry": {"coordinates":[-2.9884905815,43.322101593],"type":"Point"}
}