{
  "type": "Feature",
  "properties": {
    "addr:full":"Calle de Doctor Cerrada, 12 Zaragoza Zaragoza 50005",
    "addr:housenumber":"12",
    "addr:postcode":"50005",
    "addr:street":"Calle De Doctor Cerrada",
    "iso:country":"ES",
    "sg:address":"Calle de Doctor Cerrada, 12",
    "sg:city":"Zaragoza",
    "sg:orig_category":"Centros De Coordinaci\u00d3n",
    "sg:phone":"+34 976 23 72 31",
    "sg:postcode":"50005",
    "sg:province":"Zaragoza",
    "wof:name":"Zagin S.l.",
    "wof:placetype":"venue"
},
  "geometry": {"coordinates":[-0.8879324794,41.647693634],"type":"Point"}
}