{
  "type": "Feature",
  "properties": {
    "iso:country":"ES",
    "sg:address":"Calle de Concejo, 9",
    "sg:city":"Vitoria-gasteiz",
    "sg:orig_category":"Empresas De Carpinter\u00cda De Madera",
    "sg:phone":"+34 945 28 35 91",
    "sg:postcode":"01013",
    "sg:province":"\u00c1lava",
    "wof:name":"Carpinteria Ebanisteria 5r",
    "wof:placetype":"venue"
},
  "geometry": {"coordinates":[-2.6398479939,42.867931366],"type":"Point"}
}