{
  "type": "Feature",
  "properties": {
    "addr:full":"Carr Sant Ramon, 8 Gandia Valencia 46700",
    "addr:housenumber":"8",
    "addr:postcode":"46700",
    "addr:street":"Carr Sant Ramon;Valencia",
    "iso:country":"ES",
    "sg:address":"Carr Sant Ramon, 8",
    "sg:city":"Gandia",
    "sg:orig_category":"Teatros Y Salas De Espect\u00c1culos",
    "sg:phone":"+34 962 86 65 32",
    "sg:postcode":"46700",
    "sg:province":"Valencia",
    "wof:name":"Grup De Teatre Pluja Cooperativa Valenciana",
    "wof:placetype":"venue"
},
  "geometry": {"coordinates":[-0.1913339943,38.960735321],"type":"Point"}
}