{
  "type": "Feature",
  "properties": {
    "addr:full":"Cno La Calle, S/n Rafelbunyol Valencia 46138",
    "addr:housenumber":"s / n",
    "addr:postcode":"46138",
    "addr:street":"Cno La Calle",
    "iso:country":"ES",
    "sg:address":"Cno La Calle, S/n",
    "sg:city":"Rafelbunyol",
    "sg:orig_category":"Arboricultura Y Producci\u00d3n De Frutas",
    "sg:phone":"+34 961 41 12 64",
    "sg:postcode":"46138",
    "sg:province":"Valencia",
    "wof:name":"Balco De Llevant S.l.",
    "wof:placetype":"venue"
},
  "geometry": {"coordinates":[-0.3630670011,39.6022033691],"type":"Point"}
}