{
  "type": "Feature",
  "properties": {
    "addr:full":"Calle de Castillo, 77 Santa Cruz De Tenerife Santa Cruz De Tenerife 38003",
    "addr:housenumber":"77",
    "addr:postcode":"38003",
    "addr:street":"Calle De Castillo",
    "iso:country":"ES",
    "sg:address":"Calle de Castillo, 77",
    "sg:city":"Santa Cruz De Tenerife",
    "sg:orig_category":"Talleres: Ropa A Medida",
    "sg:phone":"+34 922 28 28 34",
    "sg:postcode":"38003",
    "sg:province":"Santa Cruz De Tenerife",
    "wof:name":"Iglesias Fernandez Isaura",
    "wof:placetype":"venue"
},
  "geometry": {"coordinates":[-16.2549552917,28.467628479],"type":"Point"}
}