{
  "type": "Feature",
  "properties": {
    "addr:full":"Calle de Toledo, 74 Fuensalida Toledo 45510",
    "addr:housenumber":"74",
    "addr:postcode":"45510",
    "addr:street":"Calle De Toledo",
    "iso:country":"ES",
    "sg:address":"Calle de Toledo, 74",
    "sg:city":"Fuensalida",
    "sg:orig_category":"Promotores Constructores",
    "sg:phone":"+34 925 78 42 08",
    "sg:postcode":"45510",
    "sg:province":"Toledo",
    "wof:name":"Conejo Alvarez Mariano",
    "wof:placetype":"venue"
},
  "geometry": {"coordinates":[-4.2089190483,40.0553016663],"type":"Point"}
}