{
  "type": "Feature",
  "properties": {
    "addr:full":"Afueras, S/n Garciaz C\u00e1ceres 10250",
    "addr:postcode":"10250",
    "addr:street":"Afueras S / N Garciaz Ca\u0301Ceres",
    "iso:country":"ES",
    "sg:address":"Afueras, S/n",
    "sg:city":"Garciaz",
    "sg:orig_category":"Cr\u00cda De Animales",
    "sg:phone":"+34 927 49 00 54",
    "sg:postcode":"10250",
    "sg:province":"C\u00e1ceres",
    "wof:name":"Holgado Sanchez Juan",
    "wof:placetype":"venue"
},
  "geometry": {"coordinates":[-5.6247668266,39.4127960205],"type":"Point"}
}