{
  "type": "Feature",
  "properties": {
    "addr:full":"Calle de Bego\u00d1a, 16 Coslada Madrid 28820",
    "addr:housenumber":"16",
    "addr:postcode":"28820",
    "addr:street":"Calle De Begon\u0303A",
    "iso:country":"ES",
    "sg:address":"Calle de Bego\u00d1a, 16",
    "sg:city":"Coslada",
    "sg:orig_category":"Bancos",
    "sg:phone":"+34 916 73 77 11",
    "sg:postcode":"28820",
    "sg:province":"Madrid",
    "wof:name":"Barclays Bank S.a.e.",
    "wof:placetype":"venue"
},
  "geometry": {"coordinates":[-3.5680561066,40.425693512],"type":"Point"}
}