{
  "type": "Feature",
  "properties": {
    "addr:full":"Ctra Abanilla (de), S/n Santomera Murcia 30140",
    "addr:housenumber":"/ n",
    "addr:postcode":"30140",
    "addr:street":"Ctra Abanilla De S",
    "iso:country":"ES",
    "sg:address":"Ctra Abanilla (de), S/n",
    "sg:city":"Santomera",
    "sg:orig_category":"Poller\u00cda Y Caza (al Por Menor)",
    "sg:phone":"+34 968 60 81 22",
    "sg:postcode":"30140",
    "sg:province":"Murcia",
    "wof:name":"Fuster Garcia Francisco",
    "wof:placetype":"venue"
},
  "geometry": {"coordinates":[-1.0554889441,38.0687713623],"type":"Point"}
}