{
  "type": "Feature",
  "properties": {
    "addr:full":"Calle de Juan De La Cruz, 8 Canjayar Almer\u00eda 04450",
    "addr:housenumber":"8",
    "addr:postcode":"04450",
    "addr:street":"Calle De Juan De La Cruz;Almeri\u0301A",
    "iso:country":"ES",
    "sg:address":"Calle de Juan De La Cruz, 8",
    "sg:city":"Canjayar",
    "sg:orig_category":"Iglesia Cat\u00d3lica",
    "sg:phone":"+34 950 51 01 09",
    "sg:postcode":"04450",
    "sg:province":"Almer\u00eda",
    "wof:name":"Parroquia Arciprestal De La Santa Cruz",
    "wof:placetype":"venue"
},
  "geometry": {"coordinates":[-2.7390499115,37.0099182129],"type":"Point"}
}