{
  "type": "Feature",
  "properties": {
    "addr:full":"Albatros (u. Sevilla Golf), 33 Alcala Guadaira Sevilla 41500",
    "addr:housenumber":"33",
    "addr:postcode":"41500",
    "addr:street":"Golf",
    "iso:country":"ES",
    "sg:address":"Albatros (u. Sevilla Golf), 33",
    "sg:city":"Alcala Guadaira",
    "sg:orig_category":"Inversiones",
    "sg:phone":"+34 954 12 26 99",
    "sg:postcode":"41500",
    "sg:province":"Sevilla",
    "wof:name":"Inversiones Remagan S.l.",
    "wof:placetype":"venue"
},
  "geometry": {"coordinates":[-5.8398590088,37.3383140564],"type":"Point"}
}