{
  "type": "Feature",
  "properties": {
    "iso:country":"ES",
    "sg:address":"Muel Olabeaga, 21",
    "sg:city":"Bilbao",
    "sg:orig_category":"Comercio De Piezas De Recambio Y De Accesorios De Veh\u00cdculos, Veh\u00cdculos Industriales",
    "sg:phone":"+34 944 41 98 98",
    "sg:postcode":"48013",
    "sg:province":"Vizcaya",
    "wof:name":"Taller Ruiz Losa",
    "wof:placetype":"venue"
},
  "geometry": {"coordinates":[-2.9588489532,43.2649612427],"type":"Point"}
}