{
  "type": "Feature",
  "properties": {
    "addr:full":"Ctra Nacional Ii, 5 Jonquera Girona 17700",
    "addr:housenumber":"5",
    "addr:postcode":"17700",
    "addr:street":"Ctra Nacional Ii",
    "iso:country":"ES",
    "sg:address":"Ctra Nacional Ii, 5",
    "sg:city":"Jonquera",
    "sg:orig_category":"Delegados, Agentes De Tr\u00c1nsito, Auxiliares De Transporte Internacional",
    "sg:phone":"+34 972 55 42 53",
    "sg:postcode":"17700",
    "sg:province":"Girona",
    "wof:name":"Megitrans S.l.",
    "wof:placetype":"venue"
},
  "geometry": {"coordinates":[2.8718750477,42.4159698486],"type":"Point"}
}