{
  "type": "Feature",
  "properties": {
    "iso:country":"ES",
    "sg:address":"Pase Chopera (de La), 313",
    "sg:city":"Alcobendas",
    "sg:orig_category":"Ense\u00d1anza: Idiomas",
    "sg:phone":"+34 916 61 10 82",
    "sg:postcode":"28100",
    "sg:province":"Madrid",
    "wof:name":"Huertas Fernandez Manuel",
    "wof:placetype":"venue"
},
  "geometry": {"coordinates":[-3.659252882,40.5450630188],"type":"Point"}
}