{
  "type": "Feature",
  "properties": {
    "addr:full":"Plaz Constitucion, 5 Noblejas Toledo 45350",
    "addr:housenumber":"5",
    "addr:postcode":"45350",
    "addr:street":"Constitucion",
    "iso:country":"ES",
    "sg:address":"Plaz Constitucion, 5",
    "sg:city":"Noblejas",
    "sg:orig_category":"\u00d3ptica: Instrumentos (fabricaci\u00d3n)",
    "sg:phone":"+34 925 14 14 44",
    "sg:postcode":"45350",
    "sg:province":"Toledo",
    "wof:name":"Visual Optico Ecjm S.l.",
    "wof:placetype":"venue"
},
  "geometry": {"coordinates":[-3.4416017532,39.9802055359],"type":"Point"}
}