{
  "type": "Feature",
  "properties": {
    "addr:full":"Calle de Bravo Murillo, 41 Madrid Madrid 28015",
    "addr:housenumber":"41",
    "addr:postcode":"madrid;28015",
    "addr:street":"Calle De Bravo Murillo",
    "iso:country":"ES",
    "sg:address":"Calle de Bravo Murillo, 41",
    "sg:city":"Madrid",
    "sg:orig_category":"Tiendas De Grano, Frutas Y Legumbres Secas (al Por Menor)",
    "sg:phone":"+34 915 94 41 83",
    "sg:postcode":"28015",
    "sg:province":"Madrid",
    "wof:name":"Alvarez Pellitero Maria Luisa",
    "wof:placetype":"venue"
},
  "geometry": {"coordinates":[-3.7043194771,40.4375343323],"type":"Point"}
}