{
  "type": "Feature",
  "properties": {
    "iso:country":"ES",
    "sg:address":"Calle de Prim, 14",
    "sg:city":"Donostia-san Sebastian",
    "sg:orig_category":"Int\u00c9rpretes",
    "sg:phone":"+34 943 45 23 22",
    "sg:postcode":"20006",
    "sg:province":"Guip\u00f9zcoa",
    "wof:name":"Almandoz Rios Matilde",
    "wof:placetype":"venue"
},
  "geometry": {"coordinates":[-1.979942441,43.3168487549],"type":"Point"}
}