{
  "type": "Feature",
  "properties": {
    "iso:country":"ES",
    "sg:address":"Ctra. Aldaya, Km. 0002,0",
    "sg:city":"Xirivella",
    "sg:orig_category":"Fabricaci\u00d3n De Enlosados, Soler\u00cdas",
    "sg:phone":"+34 963 83 41 63",
    "sg:postcode":"46950",
    "sg:province":"Valencia",
    "wof:name":"Azulejos Chaparro Imperial S.l.",
    "wof:placetype":"venue"
},
  "geometry": {"coordinates":[-0.4393742979,39.4623908997],"type":"Point"}
}