{
  "type": "Feature",
  "properties": {
    "iso:country":"ES",
    "sg:address":"Avda Iparragirre, 16",
    "sg:city":"Elexalde",
    "sg:orig_category":"Asociaciones Y Clubs Deportivos",
    "sg:phone":"+34 944 63 52 85",
    "sg:postcode":"48940",
    "sg:province":"Vizcaya",
    "wof:name":"Garran Nu\u00f1ez Ana Maria",
    "wof:placetype":"venue"
},
  "geometry": {"coordinates":[-2.6767952442,43.3140869141],"type":"Point"}
}