{
  "type": "Feature",
  "properties": {
    "iso:country":"ES",
    "sg:address":"Calle de Marcelino Suarez, 10",
    "sg:city":"Oviedo",
    "sg:orig_category":"Parafarmacias",
    "sg:phone":"+34 985 24 30 25",
    "sg:postcode":"33012",
    "sg:province":"Asturias",
    "wof:name":"Fernandez Montalvo Maria De Los Angeles",
    "wof:placetype":"venue"
},
  "geometry": {"coordinates":[-5.8623790741,43.3643302917],"type":"Point"}
}