{
  "type": "Feature",
  "properties": {
    "addr:full":"Calle de Manteria, 18 Valladolid Valladolid 47004",
    "addr:housenumber":"18",
    "addr:postcode":"47004",
    "addr:street":"Calle De Manteria",
    "iso:country":"ES",
    "sg:address":"Calle de Manteria, 18",
    "sg:city":"Valladolid",
    "sg:orig_category":"Tatuajes",
    "sg:phone":"+34 983 29 89 55",
    "sg:postcode":"47004",
    "sg:province":"Valladolid",
    "wof:name":"Tito Carballo Manuel",
    "wof:placetype":"venue"
},
  "geometry": {"coordinates":[-4.7231378555,41.6486434937],"type":"Point"}
}