{
  "type": "Feature",
  "properties": {
    "addr:full":"Calle de Atocha, 14 Madrid Madrid 28012",
    "addr:housenumber":"14",
    "addr:postcode":"madrid;28012",
    "addr:street":"Calle De Atocha",
    "iso:country":"ES",
    "sg:address":"Calle de Atocha, 14",
    "sg:city":"Madrid",
    "sg:orig_category":"Promotores Constructores",
    "sg:phone":"+34 914 29 59 64",
    "sg:postcode":"28012",
    "sg:province":"Madrid",
    "wof:name":"Promotora Gavir S.a.",
    "wof:placetype":"venue"
},
  "geometry": {"coordinates":[-3.7040657997,40.4143257141],"type":"Point"}
}