{
  "type": "Feature",
  "properties": {
    "iso:country":"ES",
    "sg:address":"C/ Camilo Flammarion, 35",
    "sg:city":"Elche",
    "sg:orig_category":"Electrodom\u00c9sticos (al Por Menor)",
    "sg:phone":"+34 965 46 94 64",
    "sg:postcode":"03201",
    "sg:province":"Alicante",
    "wof:name":"Electrodomesticos Antonio S. L.",
    "wof:placetype":"venue"
},
  "geometry": {"coordinates":[-0.7006080151,38.263584137],"type":"Point"}
}