{
  "type": "Feature",
  "properties": {
    "addr:full":"Carrer de Nou, 32 Roda De Bara Tarragona 43883",
    "addr:housenumber":"32",
    "addr:postcode":"43883",
    "addr:street":"Carrer De Nou",
    "iso:country":"ES",
    "sg:address":"Carrer de Nou, 32",
    "sg:city":"Roda De Bara",
    "sg:orig_category":"Reposter\u00cdas",
    "sg:phone":"+34 977 65 71 42",
    "sg:postcode":"43883",
    "sg:province":"Tarragona",
    "wof:name":"Queralt Ventosa Montserrat",
    "wof:placetype":"venue"
},
  "geometry": {"coordinates":[1.4552249908,41.1841773987],"type":"Point"}
}