{
  "type": "Feature",
  "properties": {
    "addr:full":"Avda Club Deportivo, 5 Logro\u00f1o La Rioja 26006",
    "addr:postcode":"26006",
    "addr:street":"Avda Club Deportivo 5 Logron\u0303O;Rioja",
    "iso:country":"ES",
    "sg:address":"Avda Club Deportivo, 5",
    "sg:city":"Logro\u00f1o",
    "sg:orig_category":"M\u00c9dicos: Radioterapia (radioterapia Como Opci\u00d3n Oncol\u00d3gica)",
    "sg:phone":"+34 941 20 81 91",
    "sg:postcode":"26006",
    "sg:province":"La Rioja",
    "wof:name":"Resonancia Magnetica S.a.",
    "wof:placetype":"venue"
},
  "geometry": {"coordinates":[-2.4487280846,42.4558525085],"type":"Point"}
}