{
  "type": "Feature",
  "properties": {
    "iso:country":"ES",
    "sg:address":"Calle de Jose Maria Pereda, 45",
    "sg:city":"Madrid",
    "sg:orig_category":"Comercio De Piezas De Recambio Y De Accesorios De Veh\u00cdculos, Veh\u00cdculos Industriales",
    "sg:phone":"+34 913 77 42 41",
    "sg:postcode":"28017",
    "sg:province":"Madrid",
    "wof:name":"Real Castellano Jose",
    "wof:placetype":"venue"
},
  "geometry": {"coordinates":[-3.6477630138,40.4303665161],"type":"Point"}
}