{
  "type": "Feature",
  "properties": {
    "addr:full":"Rua Daniel De La Sota Valdecilla, 2 Pontevedra Pontevedra 36001",
    "addr:housenumber":"2",
    "addr:postcode":"36001",
    "addr:street":"Rua Daniel De La Sota",
    "iso:country":"ES",
    "sg:address":"Rua Daniel De La Sota Valdecilla, 2",
    "sg:city":"Pontevedra",
    "sg:orig_category":"Deportes N\u00c1uticos, Acu\u00c1ticos Y Subacu\u00c1ticos: Art\u00cdculos Y Equipo (al Por Menor)",
    "sg:phone":"+34 986 85 24 62",
    "sg:postcode":"36001",
    "sg:province":"Pontevedra",
    "wof:name":"Losada Baquero Luis Maria",
    "wof:placetype":"venue"
},
  "geometry": {"coordinates":[-8.6427936554,42.4306716919],"type":"Point"}
}