{
  "type": "Feature",
  "properties": {
    "addr:full":"Rond Zamenhof, 108 Sabadell Barcelona 08208",
    "addr:housenumber":"108",
    "addr:postcode":"08208",
    "addr:street":"Zamenhof",
    "iso:country":"ES",
    "sg:address":"Rond Zamenhof, 108",
    "sg:city":"Sabadell",
    "sg:orig_category":"Contables",
    "sg:phone":"+34 937 17 69 42",
    "sg:postcode":"08208",
    "sg:province":"Barcelona",
    "wof:name":"Camarassa Ronco David",
    "wof:placetype":"venue"
},
  "geometry": {"coordinates":[2.0991659164,41.550491333],"type":"Point"}
}