{
  "type": "Feature",
  "properties": {
    "iso:country":"ES",
    "sg:address":"Carr Pare Espuig, 51",
    "sg:city":"Villarreal",
    "sg:orig_category":"Alimentaci\u00d3n General (al Por Menor)",
    "sg:phone":"+34 964 52 02 41",
    "sg:postcode":"12540",
    "sg:province":"Castell\u00f3n",
    "wof:name":"Ayet Lopez Matilde",
    "wof:placetype":"venue"
},
  "geometry": {"coordinates":[-0.0952939987,39.9453048706],"type":"Point"}
}