{
  "type": "Feature",
  "properties": {
    "addr:full":"Calle de Comendador Chacon, 2 Ubeda Ja\u00e9n 23400",
    "addr:housenumber":"2",
    "addr:postcode":"23400",
    "addr:street":"Calle De Comendador Chacon;Jae\u0301N",
    "iso:country":"ES",
    "sg:address":"Calle de Comendador Chacon, 2",
    "sg:city":"Ubeda",
    "sg:orig_category":"Ense\u00d1anza: Idiomas",
    "sg:phone":"+34 953 75 46 18",
    "sg:postcode":"23400",
    "sg:province":"Ja\u00e9n",
    "wof:name":"Cano Medel Alonso",
    "wof:placetype":"venue"
},
  "geometry": {"coordinates":[-3.3797109127,38.0164756775],"type":"Point"}
}