{
  "type": "Feature",
  "properties": {
    "iso:country":"ES",
    "sg:address":"Calle de Campillo (del), 10",
    "sg:city":"Baltanas",
    "sg:classifiers":[
        {
            "category":"Taxi",
            "type":"Transportation"
        }
    ],
    "sg:phone":"+34 979 79 02 11",
    "sg:postcode":"34240",
    "sg:province":"Palencia",
    "wof:name":"Garcia Ines Matias",
    "wof:placetype":"venue"
},
  "geometry": {"coordinates":[-4.2472043037,41.9385643005],"type":"Point"}
}