{
  "type": "Feature",
  "properties": {
    "iso:country":"ES",
    "sg:address":"Avda Alcalde De Mostoles (del), 9",
    "sg:city":"Mostoles",
    "sg:orig_category":"Fisioterapia",
    "sg:phone":"+34 912 26 51 01",
    "sg:postcode":"28932",
    "sg:province":"Madrid",
    "sg:website":"www.clinica-fisis.com",
    "wof:name":"Yubero Jimenez Sandra",
    "wof:placetype":"venue"
},
  "geometry": {"coordinates":[-3.8598792553,40.3336524963],"type":"Point"}
}