{
  "type": "Feature",
  "properties": {
    "addr:full":"Calle de Francos Rodriguez, 14 Madrid Madrid 28039",
    "addr:housenumber":"14",
    "addr:postcode":"madrid;28039",
    "addr:street":"Calle De Francos Rodriguez",
    "iso:country":"ES",
    "sg:address":"Calle de Francos Rodriguez, 14",
    "sg:city":"Madrid",
    "sg:orig_category":"Herboristas (al Por Menor)",
    "sg:phone":"+34 914 59 81 41",
    "sg:postcode":"28039",
    "sg:province":"Madrid",
    "wof:name":"Gonzalez Del Val Pedro Antonio",
    "wof:placetype":"venue"
},
  "geometry": {"coordinates":[-3.7037189007,40.455039978],"type":"Point"}
}