{
  "type": "Feature",
  "properties": {
    "addr:full":"Calle de Canals, 14 Valencia Valencia 46005",
    "addr:housenumber":"14",
    "addr:postcode":"46005",
    "addr:street":"Calle De Canals",
    "iso:country":"ES",
    "sg:address":"Calle de Canals, 14",
    "sg:city":"Valencia",
    "sg:orig_category":"Fabricaci\u00d3n De Moldes Y Modelos",
    "sg:phone":"+34 963 74 51 65",
    "sg:postcode":"46005",
    "sg:province":"Valencia",
    "wof:name":"Matrilev S.l.",
    "wof:placetype":"venue"
},
  "geometry": {"coordinates":[-0.3672665954,39.4618682861],"type":"Point"}
}