{
  "type": "Feature",
  "properties": {
    "addr:full":"Mariana Pineda, 81 Miranda Ebro Burgos 09200",
    "addr:housenumber":"81",
    "addr:postcode":"09200",
    "addr:street":"Mariana Pineda",
    "iso:country":"ES",
    "sg:address":"Mariana Pineda, 81",
    "sg:city":"Miranda Ebro",
    "sg:orig_category":"Alquiler De V\u00cddeo",
    "sg:phone":"+34 947 34 19 20",
    "sg:postcode":"09200",
    "sg:province":"Burgos",
    "wof:name":"Video Club Acevedo Hermanos S.l",
    "wof:placetype":"venue"
},
  "geometry": {"coordinates":[-2.9704549313,42.6823730469],"type":"Point"}
}