{
  "type": "Feature",
  "properties": {
    "iso:country":"ES",
    "sg:address":"Plaz Gesta De La, 3",
    "sg:city":"Oviedo",
    "sg:orig_category":"Fotograf\u00cda Art\u00cdstica Y Retratos",
    "sg:phone":"+34 985 25 15 74",
    "sg:postcode":"33007",
    "sg:province":"Asturias",
    "wof:name":"Oliveira Mateo Jose Antonio",
    "wof:placetype":"venue"
},
  "geometry": {"coordinates":[-5.8522028923,43.3575897217],"type":"Point"}
}