{
  "type": "Feature",
  "properties": {
    "addr:full":"Plaz Toro (del), S/n Tres Cantos Madrid 28760",
    "addr:housenumber":"s / n",
    "addr:postcode":"28760",
    "iso:country":"ES",
    "sg:address":"Plaz Toro (del), S/n",
    "sg:city":"Tres Cantos",
    "sg:orig_category":"Camiser\u00cda Y Ropa Interior Masculina (al Por Menor)",
    "sg:phone":"+34 918 03 27 53",
    "sg:postcode":"28760",
    "sg:province":"Madrid",
    "wof:name":"Almazan La Cave Purificacion",
    "wof:placetype":"venue"
},
  "geometry": {"coordinates":[-3.7168662548,40.6059989929],"type":"Point"}
}