{
  "type": "Feature",
  "properties": {
    "addr:full":"Avda Compostela, 33 Boiro A Coru\u00f1a 15930",
    "addr:housenumber":"33",
    "addr:postcode":"15930",
    "addr:street":"Avda Compostela;Corun\u0303A",
    "iso:country":"ES",
    "sg:address":"Avda Compostela, 33",
    "sg:city":"Boiro",
    "sg:orig_category":"Molduras, Junquillos, Listones Y Molduras Perforadas",
    "sg:phone":"+34 981 84 59 37",
    "sg:postcode":"15930",
    "sg:province":"A Coru\u00f1a",
    "wof:name":"Vazquez Lai\u00f1o Ramona",
    "wof:placetype":"venue"
},
  "geometry": {"coordinates":[-8.8905200958,42.6451950073],"type":"Point"}
}