{
  "type": "Feature",
  "properties": {
    "iso:country":"ES",
    "sg:address":"Pase San Frantzisko Ibiltokia, 7",
    "sg:city":"Tolosa",
    "sg:orig_category":"Sociedades, Compa\u00d1\u00cdas Aseguradoras",
    "sg:phone":"+34 943 65 50 26",
    "sg:postcode":"20400",
    "sg:province":"Guip\u00f9zcoa",
    "wof:name":"Carasa Cilveti Lacort Y Cia S.a.",
    "wof:placetype":"venue"
},
  "geometry": {"coordinates":[-2.0746560097,43.1361885071],"type":"Point"}
}