{
  "type": "Feature",
  "properties": {
    "addr:full":"Carr Castello De La Plana, 2 Algemesi Valencia 46680",
    "addr:housenumber":"2",
    "addr:postcode":"46680",
    "addr:street":"Carr Castello De La Plana",
    "iso:country":"ES",
    "sg:address":"Carr Castello De La Plana, 2",
    "sg:city":"Algemesi",
    "sg:orig_category":"Asesor\u00cda Sobre Comunicaci\u00d3n De Empresas",
    "sg:phone":"+34 962 48 45 60",
    "sg:postcode":"46680",
    "sg:province":"Valencia",
    "wof:name":"Castell Llacer Rafael",
    "wof:placetype":"venue"
},
  "geometry": {"coordinates":[-0.438966006,39.1884002686],"type":"Point"}
}