{
  "type": "Feature",
  "properties": {
    "addr:full":"Calle de Princesa Guajara, S/n San Isidro Santa Cruz De Tenerife 38611",
    "addr:housenumber":"s / n",
    "addr:postcode":"38611",
    "addr:street":"Calle De Princesa Guajara",
    "iso:country":"ES",
    "sg:address":"Calle de Princesa Guajara, S/n",
    "sg:city":"San Isidro",
    "sg:orig_category":"Inmobiliaria (agencias)",
    "sg:phone":"+34 922 39 19 10",
    "sg:postcode":"38611",
    "sg:province":"Santa Cruz De Tenerife",
    "wof:name":"Inmobiliaria Ardid S.l.",
    "wof:placetype":"venue"
},
  "geometry": {"coordinates":[-16.5568809509,28.0760936737],"type":"Point"}
}