{
  "type": "Feature",
  "properties": {
    "addr:full":"Ctra. De Madrid Barcelona, 2 Almunia D. Godina Zaragoza 50100",
    "addr:housenumber":"2",
    "addr:postcode":"50100",
    "addr:street":"Ctra. De Madrid Barcelona;D. Godina",
    "iso:country":"ES",
    "sg:address":"Ctra. De Madrid Barcelona, 2",
    "sg:city":"Almunia D. Godina",
    "sg:orig_category":"Productos Fitosanitarios (negocio, Aplicaci\u00d3n)",
    "sg:phone":"+34 976 60 01 93",
    "sg:postcode":"50100",
    "sg:province":"Zaragoza",
    "wof:name":"Comercial Agricola Sencos S.l.",
    "wof:placetype":"venue"
},
  "geometry": {"coordinates":[-1.3779189587,41.4772033691],"type":"Point"}
}