{
  "type": "Feature",
  "properties": {
    "iso:country":"ES",
    "sg:address":"Carr Sant Vicent Ferrer, 18",
    "sg:city":"Gandia",
    "sg:orig_category":"Postigos, Persianas Y Celos\u00cdas",
    "sg:phone":"+34 962 86 21 31",
    "sg:postcode":"46700",
    "sg:province":"Valencia",
    "sg:website":"www.persianasvidal.com",
    "wof:name":"Persianas Vidal S. A.",
    "wof:placetype":"venue"
},
  "geometry": {"coordinates":[-0.1913339943,38.960735321],"type":"Point"}
}