{
  "type": "Feature",
  "properties": {
    "iso:country":"ES",
    "sg:address":"Plaz Unidad Nacional, 8",
    "sg:city":"Huesca",
    "sg:orig_category":"Importaci\u00d3n",
    "sg:phone":"+34 974 24 03 05",
    "sg:postcode":"22001",
    "sg:province":"Huesca",
    "wof:name":"Centro De Estudios Scio S. A.",
    "wof:placetype":"venue"
},
  "geometry": {"coordinates":[-0.4048619866,42.1397781372],"type":"Point"}
}