{
  "type": "Feature",
  "properties": {
    "addr:full":"Avda Trinidad (la), 68 San Cristobal De La Laguna Santa Cruz De Tenerife 38204",
    "addr:housenumber":"68",
    "addr:postcode":"38204",
    "addr:street":"Avda Trinidad La",
    "iso:country":"ES",
    "sg:address":"Avda Trinidad (la), 68",
    "sg:city":"San Cristobal De La Laguna",
    "sg:orig_category":"Centros M\u00c9dicos Y Sociales, Dispensarios",
    "sg:phone":"+34 922 63 17 32",
    "sg:postcode":"38204",
    "sg:province":"Santa Cruz De Tenerife",
    "wof:name":"Centro Asistencial La Trinidad S.l",
    "wof:placetype":"venue"
},
  "geometry": {"coordinates":[-16.3174686432,28.4832000732],"type":"Point"}
}