{
  "type": "Feature",
  "properties": {
    "addr:full":"Carrer de Amposta, 97 Terrassa Barcelona 08227",
    "addr:housenumber":"97",
    "addr:postcode":"08227",
    "addr:street":"Carrer De Amposta",
    "iso:country":"ES",
    "sg:address":"Carrer de Amposta, 97",
    "sg:city":"Terrassa",
    "sg:classifiers":[
        {
            "category":"Professional",
            "subcategory":"Management & Consulting",
            "type":"Services"
        }
    ],
    "sg:phone":"+34 937 85 85 16",
    "sg:postcode":"08227",
    "sg:province":"Barcelona",
    "sg:tags":[
        "asesor\u00cda",
        "en",
        "marketing"
    ],
    "wof:name":"Portero Salmeron Juan Sebastian",
    "wof:placetype":"venue"
},
  "geometry": {"coordinates":[2.0418119431,41.5709991455],"type":"Point"}
}