{
  "type": "Feature",
  "properties": {
    "iso:country":"ES",
    "sg:address":"Calle de Angel Embil, 6",
    "sg:city":"Pola De Siero",
    "sg:orig_category":"Locales Y Clases De Danza",
    "sg:phone":"+34 985 72 46 03",
    "sg:postcode":"33510",
    "sg:province":"Asturias",
    "wof:name":"Laruelo Sanchez Patricia",
    "wof:placetype":"venue"
},
  "geometry": {"coordinates":[-5.6569766998,43.3936157227],"type":"Point"}
}