{
  "type": "Feature",
  "properties": {
    "iso:country":"ES",
    "sg:address":"Calle de Luis Montoto, 16",
    "sg:city":"Sevilla",
    "sg:orig_category":"Cl\u00cdnicas Dentales",
    "sg:phone":"+34 954 41 72 06",
    "sg:postcode":"41003",
    "sg:province":"Sevilla",
    "wof:name":"Ponce Ruiz Jose Gabriel",
    "wof:placetype":"venue"
},
  "geometry": {"coordinates":[-5.9833989143,37.3888397217],"type":"Point"}
}