{
  "type": "Feature",
  "properties": {
    "iso:country":"ES",
    "sg:address":"Avda Gran Via Rey Juan Carlos I, 6",
    "sg:city":"Logro\u00f1o",
    "sg:orig_category":"M\u00c9dicos: Dermatolog\u00cda Y Venereolog\u00cda",
    "sg:phone":"+34 941 22 60 51",
    "sg:postcode":"26002",
    "sg:province":"La Rioja",
    "wof:name":"Aizpun Ponzan Miguel",
    "wof:placetype":"venue"
},
  "geometry": {"coordinates":[-2.4463627338,42.4633369446],"type":"Point"}
}