{
  "type": "Feature",
  "properties": {
    "addr:full":"C/ Velazquez, 8 Elche Alicante 03203",
    "addr:housenumber":"8",
    "addr:postcode":"03203",
    "addr:street":"C / Velazquez",
    "iso:country":"ES",
    "sg:address":"C/ Velazquez, 8",
    "sg:city":"Elche",
    "sg:orig_category":"Carnicer\u00cdas, Carnicer\u00cdas",
    "sg:phone":"+34 966 61 46 28",
    "sg:postcode":"03203",
    "sg:province":"Alicante",
    "wof:name":"Quiles Gillermo Diego",
    "wof:placetype":"venue"
},
  "geometry": {"coordinates":[-0.6935459971,38.2652168274],"type":"Point"}
}