{
  "type": "Feature",
  "properties": {
    "iso:country":"ES",
    "sg:address":"Plaz Ovando, 3",
    "sg:city":"Brozas",
    "sg:orig_category":"Contenedores (mercanc\u00cdas)",
    "sg:phone":"+34 927 39 53 14",
    "sg:postcode":"10950",
    "sg:province":"C\u00e1ceres",
    "wof:name":"Aldeano Duque Jose Maria",
    "wof:placetype":"venue"
},
  "geometry": {"coordinates":[-6.770813942,39.5579299927],"type":"Point"}
}