{
  "type": "Feature",
  "properties": {
    "iso:country":"ES",
    "sg:address":"Miguel Servet(p I Las Teresas), 2",
    "sg:city":"Yecla",
    "sg:orig_category":"Fabricaci\u00d3n De Taburetes, Sillas Y Sillones",
    "sg:phone":"+34 968 75 24 56",
    "sg:postcode":"30510",
    "sg:province":"Murcia",
    "wof:name":"Losbu S.l.",
    "wof:placetype":"venue"
},
  "geometry": {"coordinates":[-1.0751490593,38.6194381714],"type":"Point"}
}