{
  "type": "Feature",
  "properties": {
    "addr:full":"Calle de Rio Taju\u00d1a, 2 Alcala Henares Madrid 28803",
    "addr:housenumber":"2",
    "addr:postcode":"28803",
    "addr:street":"Calle De Rio Tajun\u0303A",
    "iso:country":"ES",
    "sg:address":"Calle de Rio Taju\u00d1a, 2",
    "sg:city":"Alcala Henares",
    "sg:orig_category":"Asociaciones, Organismos Culturales Y Socioeducativos",
    "sg:phone":"+34 918 82 26 44",
    "sg:postcode":"28803",
    "sg:province":"Madrid",
    "wof:name":"Asociacion Juvenil Nueva Alcala",
    "wof:placetype":"venue"
},
  "geometry": {"coordinates":[-3.3649668694,40.4689254761],"type":"Point"}
}