{
  "type": "Feature",
  "properties": {
    "iso:country":"ES",
    "sg:address":"Calle de Ingeniero Leon Y Castillo, 20",
    "sg:city":"S.gregorio",
    "sg:orig_category":"Cristaler\u00cdas",
    "sg:phone":"+34 928 69 59 87",
    "sg:postcode":"35200",
    "sg:province":"Las Palmas",
    "wof:name":"Quintana Santiago Miguel",
    "wof:placetype":"venue"
},
  "geometry": {"coordinates":[-15.4144220352,28.0029888153],"type":"Point"}
}