{
  "type": "Feature",
  "properties": {
    "iso:country":"ES",
    "sg:address":"Ctra Valencia (de), S/n",
    "sg:city":"Campillo Altobuey",
    "sg:orig_category":"Cooperativas Agr\u00cdcolas",
    "sg:phone":"+34 969 33 70 37",
    "sg:postcode":"16210",
    "sg:province":"Cuenca",
    "wof:name":"Cooperativa Del Campo San Andres Apostol",
    "wof:placetype":"venue"
},
  "geometry": {"coordinates":[-1.7931189537,39.6124000549],"type":"Point"}
}