{
  "type": "Feature",
  "properties": {
    "iso:country":"ES",
    "sg:address":"Avda Francisco La Roche, 11",
    "sg:city":"Santa Cruz De Tenerife",
    "sg:orig_category":"Centros Comerciales Y Grandes Tiendas",
    "sg:phone":"+34 922 28 24 96",
    "sg:postcode":"38001",
    "sg:province":"Santa Cruz De Tenerife",
    "wof:name":"Top Anaga 24 Horas",
    "wof:placetype":"venue"
},
  "geometry": {"coordinates":[-16.2449493408,28.4773406982],"type":"Point"}
}