{
  "type": "Feature",
  "properties": {
    "addr:full":"A Estacion, 9 Estacion Pontevedra 36430",
    "addr:postcode":"36430",
    "addr:street":"Estacion;Estacion Pontevedra",
    "iso:country":"ES",
    "sg:address":"A Estacion, 9",
    "sg:city":"Estacion",
    "sg:orig_category":"Comercio De Minerales, F\u00d3siles Y Conchas",
    "sg:phone":"+34 986 66 51 86",
    "sg:postcode":"36430",
    "sg:province":"Pontevedra",
    "wof:name":"Casa Mezquita S.l.",
    "wof:placetype":"venue"
},
  "geometry": {"coordinates":[-8.2902040482,42.1192703247],"type":"Point"}
}