{
  "type": "Feature",
  "properties": {
    "addr:full":"Calle de Doctor Manuel Villegas, 11 Cordoba C\u00f3rdoba 14007",
    "addr:housenumber":"11",
    "addr:postcode":"14007",
    "addr:street":"Calle De Doctor Manuel Villegas;Co\u0301Rdoba",
    "iso:country":"ES",
    "sg:address":"Calle de Doctor Manuel Villegas, 11",
    "sg:city":"Cordoba",
    "sg:orig_category":"Electrodom\u00c9sticos (al Por Menor)",
    "sg:phone":"+34 957 43 78 83",
    "sg:postcode":"14007",
    "sg:province":"C\u00f3rdoba",
    "wof:name":"Millan Sicilia Jose",
    "wof:placetype":"venue"
},
  "geometry": {"coordinates":[-4.7657327652,37.8946037292],"type":"Point"}
}