{
  "type": "Feature",
  "properties": {
    "iso:country":"ES",
    "sg:address":"Avda Tres Cruces, 30",
    "sg:city":"Zamora",
    "sg:orig_category":"Institutos De Belleza",
    "sg:phone":"+34 980 52 59 42",
    "sg:postcode":"49008",
    "sg:province":"Zamora",
    "wof:name":"Ankara S.l.",
    "wof:placetype":"venue"
},
  "geometry": {"coordinates":[-5.7409644127,41.5114250183],"type":"Point"}
}