{
  "type": "Feature",
  "properties": {
    "addr:full":"Calle de Real, 67 Torredonjimeno Ja\u00e9n 23650",
    "addr:housenumber":"67",
    "addr:postcode":"23650",
    "addr:street":"Calle De Real",
    "iso:country":"ES",
    "sg:address":"Calle de Real, 67",
    "sg:city":"Torredonjimeno",
    "sg:classifiers":[
        {
            "category":"Communications",
            "type":"Services"
        }
    ],
    "sg:phone":"+34 953 57 23 55",
    "sg:postcode":"23650",
    "sg:province":"Ja\u00e9n",
    "sg:tags":[
        "televisiones",
        "y",
        "radio"
    ],
    "wof:name":"Canal Tvt De Torredonjimeno",
    "wof:placetype":"venue"
},
  "geometry": {"coordinates":[-3.953346014,37.7639961243],"type":"Point"}
}