{
  "type": "Feature",
  "properties": {
    "addr:full":"Avda Genil (del), S/n Ecija Sevilla 41400",
    "addr:postcode":"41400",
    "addr:street":"Avda Genil Del S / N",
    "iso:country":"ES",
    "sg:address":"Avda Genil (del), S/n",
    "sg:city":"Ecija",
    "sg:orig_category":"Zapatos (al Por Menor)",
    "sg:phone":"+34 954 83 34 47",
    "sg:postcode":"41400",
    "sg:province":"Sevilla",
    "wof:name":"Pereira Berrocal Jesus",
    "wof:placetype":"venue"
},
  "geometry": {"coordinates":[-5.0761189461,37.5353431702],"type":"Point"}
}