{
  "type": "Feature",
  "properties": {
    "addr:full":"Plaz Mayor, S/n Lupiana Guadalajara 19142",
    "addr:housenumber":"s",
    "addr:postcode":"19142",
    "addr:street":"Plaz Mayor;/ N Lupiana",
    "iso:country":"ES",
    "sg:address":"Plaz Mayor, S/n",
    "sg:city":"Lupiana",
    "sg:orig_category":"Ense\u00d1anza, Formaci\u00d3n Profesional: Aprendizaje",
    "sg:phone":"+34 949 29 02 01",
    "sg:postcode":"19142",
    "sg:province":"Guadalajara",
    "wof:name":"Ayuntamiento",
    "wof:placetype":"venue"
},
  "geometry": {"coordinates":[-3.0533108711,40.6103248596],"type":"Point"}
}