{
  "type": "Feature",
  "properties": {
    "addr:full":"Ctra Arahal-coronil, 2 Arahal Sevilla 41600",
    "addr:housenumber":"2",
    "addr:postcode":"41600",
    "addr:street":"Ctra Arahal-Coronil",
    "iso:country":"ES",
    "sg:address":"Ctra Arahal-coronil, 2",
    "sg:city":"Arahal",
    "sg:orig_category":"Frutas Y Legumbres Frescas (al Por Mayor)",
    "sg:phone":"+34 954 84 06 55",
    "sg:postcode":"41600",
    "sg:province":"Sevilla",
    "wof:name":"Aceitunas Sanchez Quero S.l.",
    "wof:placetype":"venue"
},
  "geometry": {"coordinates":[-5.5428285599,37.2640991211],"type":"Point"}
}