{
  "type": "Feature",
  "properties": {
    "addr:full":"Carrer de Mecanica, 12 Barcelona Barcelona 08038",
    "addr:housenumber":"12",
    "addr:postcode":"08038",
    "addr:street":"Carrer De Mecanica",
    "iso:country":"ES",
    "sg:address":"Carrer de Mecanica, 12",
    "sg:city":"Barcelona",
    "sg:orig_category":"Estancos",
    "sg:phone":"+34 934 32 19 09",
    "sg:postcode":"08038",
    "sg:province":"Barcelona",
    "wof:name":"Ayo Pi\u00f1ero Juan Antonio",
    "wof:placetype":"venue"
},
  "geometry": {"coordinates":[2.1370990276,41.3586540222],"type":"Point"}
}