{
  "type": "Feature",
  "properties": {
    "iso:country":"ES",
    "sg:address":"Barandiaran Kalea, 3",
    "sg:city":"Zarautz",
    "sg:orig_category":"Asociaciones, Organismos Culturales Y Socioeducativos",
    "sg:phone":"+34 943 83 26 50",
    "sg:postcode":"20800",
    "sg:province":"Guip\u00f9zcoa",
    "wof:name":"Sociedad Recreativa Gastronomica Kurpil",
    "wof:placetype":"venue"
},
  "geometry": {"coordinates":[-2.1787259579,43.2835388184],"type":"Point"}
}