{
  "type": "Feature",
  "properties": {
    "addr:full":"Carrer de Joan Baptista Gali, 1 Terrassa Barcelona 08221",
    "addr:housenumber":"1",
    "addr:postcode":"08221",
    "addr:street":"Carrer De Joan Baptista Gali",
    "iso:country":"ES",
    "sg:address":"Carrer de Joan Baptista Gali, 1",
    "sg:city":"Terrassa",
    "sg:orig_category":"Ense\u00d1anza Secundaria: Colegios Y Escuelas Privadas",
    "sg:phone":"+34 937 89 92 32",
    "sg:postcode":"08221",
    "sg:province":"Barcelona",
    "sg:website":"www.caper.es",
    "wof:name":"Caper Ensenyament S.l",
    "wof:placetype":"venue"
},
  "geometry": {"coordinates":[2.0112099648,41.5657348633],"type":"Point"}
}