{
  "type": "Feature",
  "properties": {
    "iso:country":"ES",
    "sg:address":"Calle de Cura Bartolome Mu\u00d1oz, 10",
    "sg:city":"Petrer",
    "sg:orig_category":"Peluquer\u00cdas, Peluquer\u00cda Mixta",
    "sg:phone":"+34 965 37 52 14",
    "sg:postcode":"03610",
    "sg:province":"Alicante",
    "wof:name":"Varea Ruiz Dolores",
    "wof:placetype":"venue"
},
  "geometry": {"coordinates":[-0.7699859738,38.4843444824],"type":"Point"}
}