{
  "type": "Feature",
  "properties": {
    "addr:full":"Calle de Santisimo, 65 Motril Granada 18600",
    "addr:housenumber":"65",
    "addr:postcode":"18600",
    "addr:street":"Calle De Santisimo",
    "iso:country":"ES",
    "sg:address":"Calle de Santisimo, 65",
    "sg:city":"Motril",
    "sg:orig_category":"Centros De Educaci\u00d3n Especial",
    "sg:phone":"+34 958 60 33 33",
    "sg:postcode":"18600",
    "sg:province":"Granada",
    "wof:name":"Asociacion Promotora De Minusvalidos Psiquicos De Motril",
    "wof:placetype":"venue"
},
  "geometry": {"coordinates":[-3.5132915974,36.7492179871],"type":"Point"}
}