{
  "type": "Feature",
  "properties": {
    "addr:full":"Ctra Obejo, Km. 0028,0 Adamuz C\u00f3rdoba 14430",
    "addr:postcode":"14430",
    "addr:street":"Ctra Obejo Km. 0028,0;Co\u0301Rdoba",
    "iso:country":"ES",
    "sg:address":"Ctra Obejo, Km. 0028,0",
    "sg:city":"Adamuz",
    "sg:orig_category":"Cr\u00cda De Animales",
    "sg:phone":"+34 957 33 60 12",
    "sg:postcode":"14430",
    "sg:province":"C\u00f3rdoba",
    "wof:name":"R.v.agro S.l.",
    "wof:placetype":"venue"
},
  "geometry": {"coordinates":[-4.5246610641,38.0278129578],"type":"Point"}
}