{
  "type": "Feature",
  "properties": {
    "addr:full":"Calle de Mesones, 23 Aracena Huelva 21200",
    "addr:housenumber":"23",
    "addr:postcode":"21200",
    "addr:street":"Calle De Mesones",
    "iso:country":"ES",
    "sg:address":"Calle de Mesones, 23",
    "sg:city":"Aracena",
    "sg:orig_category":"Marmolistas Funerarios",
    "sg:phone":"+34 959 12 83 39",
    "sg:postcode":"21200",
    "sg:province":"Huelva",
    "wof:name":"Vazquez Dominguez Gregoria",
    "wof:placetype":"venue"
},
  "geometry": {"coordinates":[-6.5601348877,37.8951225281],"type":"Point"}
}