{
  "type": "Feature",
  "properties": {
    "iso:country":"ES",
    "sg:address":"Carrer de Antoni Gaudi, 21",
    "sg:city":"Castelldefels",
    "sg:orig_category":"Inmobiliaria (agencias)",
    "sg:phone":"+34 936 36 21 25",
    "sg:postcode":"08860",
    "sg:province":"Barcelona",
    "wof:name":"Fadas 2010 S.l.",
    "wof:placetype":"venue"
},
  "geometry": {"coordinates":[1.9416960478,41.2732276917],"type":"Point"}
}