{
  "type": "Feature",
  "properties": {
    "iso:country":"ES",
    "sg:address":"Avda Sierra Espu\u00d1a, S/n",
    "sg:city":"Alhama Murcia",
    "sg:orig_category":"Reposter\u00cdas",
    "sg:phone":"+34 968 63 90 39",
    "sg:postcode":"30840",
    "sg:province":"Murcia",
    "wof:name":"Lopez Carre\u00f1o Antonio",
    "wof:placetype":"venue"
},
  "geometry": {"coordinates":[-1.433784008,37.8516654968],"type":"Point"}
}