{
  "type": "Feature",
  "properties": {
    "addr:full":"Carrer de Josep Estivill, 60 Barcelona Barcelona 08027",
    "addr:housenumber":"60",
    "addr:postcode":"08027",
    "addr:street":"Carrer De Josep Estivill",
    "iso:country":"ES",
    "sg:address":"Carrer de Josep Estivill, 60",
    "sg:city":"Barcelona",
    "sg:orig_category":"Ropa Para Ni\u00d1os (al Por Menor)",
    "sg:phone":"+34 933 52 09 02",
    "sg:postcode":"08027",
    "sg:province":"Barcelona",
    "wof:name":"Garcia Gallego Ana Fernanda",
    "wof:placetype":"venue"
},
  "geometry": {"coordinates":[2.1898040771,41.4192314148],"type":"Point"}
}