{
  "type": "Feature",
  "properties": {
    "addr:full":"Plaz Virgen Blanca, S/n Vitoria-gasteiz \u00c1lava 01001",
    "addr:housenumber":"s / n",
    "addr:postcode":"01001",
    "addr:street":"Plaz;Blanca",
    "iso:country":"ES",
    "sg:address":"Plaz Virgen Blanca, S/n",
    "sg:city":"Vitoria-gasteiz",
    "sg:orig_category":"Iglesia Cat\u00d3lica",
    "sg:phone":"+34 945 23 12 90",
    "sg:postcode":"01001",
    "sg:province":"\u00c1lava",
    "wof:name":"Parroquia San Miguel",
    "wof:placetype":"venue"
},
  "geometry": {"coordinates":[-2.6734941006,42.8466186523],"type":"Point"}
}