{
  "type": "Feature",
  "properties": {
    "addr:full":"Av. Constitucio, 75 Calig Castell\u00f3n 12589",
    "addr:housenumber":"75",
    "addr:postcode":"12589",
    "addr:street":"Av. Constitucio;Castello\u0301N",
    "iso:country":"ES",
    "sg:address":"Av. Constitucio, 75",
    "sg:city":"Calig",
    "sg:orig_category":"Mec\u00c1nico Del Autom\u00d3vil",
    "sg:phone":"+34 964 49 20 70",
    "sg:postcode":"12589",
    "sg:province":"Castell\u00f3n",
    "wof:name":"Sanz Alberich Crisanto",
    "wof:placetype":"venue"
},
  "geometry": {"coordinates":[0.358099997,40.4621200562],"type":"Point"}
}