{
  "type": "Feature",
  "properties": {
    "addr:full":"Cuarzo, S/n Arganda Madrid 28500",
    "addr:housenumber":"s / n",
    "addr:postcode":"28500",
    "addr:street":"Cuarzo",
    "iso:country":"ES",
    "sg:address":"Cuarzo, S/n",
    "sg:city":"Arganda",
    "sg:orig_category":"Artes Gr\u00c1ficas, Artes Pl\u00c1sticas (curso)",
    "sg:phone":"+34 918 72 00 31",
    "sg:postcode":"28500",
    "sg:province":"Madrid",
    "wof:name":"Industria Grafica Chavigraf S.l.",
    "wof:placetype":"venue"
},
  "geometry": {"coordinates":[-3.467015028,40.3043518066],"type":"Point"}
}