{
  "type": "Feature",
  "properties": {
    "addr:full":"Av Cristofol Colom (de), 48 Tortosa Tarragona 43500",
    "addr:postcode":"43500",
    "addr:street":"Av Cristofol",
    "iso:country":"ES",
    "sg:address":"Av Cristofol Colom (de), 48",
    "sg:city":"Tortosa",
    "sg:orig_category":"Iglesia Cat\u00d3lica",
    "sg:phone":"+34 977 50 01 67",
    "sg:postcode":"43500",
    "sg:province":"Tarragona",
    "wof:name":"Bisbat De Tortosa",
    "wof:placetype":"venue"
},
  "geometry": {"coordinates":[0.5155900121,40.8145904541],"type":"Point"}
}