{
  "type": "Feature",
  "properties": {
    "iso:country":"ES",
    "sg:address":"Calle de Naciente, S/n",
    "sg:city":"Pozuelo De Vidriales",
    "sg:orig_category":"Autob\u00das (explotaci\u00d3n Y Servicios De)",
    "sg:phone":"+34 980 65 99 25",
    "sg:postcode":"49621",
    "sg:province":"Zamora",
    "wof:name":"Casta\u00f1o E Hijos S.l.",
    "wof:placetype":"venue"
},
  "geometry": {"coordinates":[-5.961774826,42.0407028198],"type":"Point"}
}