{
  "type": "Feature",
  "properties": {
    "addr:full":"Calle de Soledad, 1 Madridejos Toledo 45710",
    "addr:housenumber":"1",
    "addr:postcode":"45710",
    "addr:street":"Calle De Soledad",
    "iso:country":"ES",
    "sg:address":"Calle de Soledad, 1",
    "sg:city":"Madridejos",
    "sg:classifiers":[
        {
            "category":"Autos & Motor Vehicles",
            "subcategory":"Automobile Sales",
            "type":"Retail Goods"
        }
    ],
    "sg:phone":"+34 925 46 39 49",
    "sg:postcode":"45710",
    "sg:province":"Toledo",
    "wof:name":"Hernandez Resa Eloy S.l.n.e.",
    "wof:placetype":"venue"
},
  "geometry": {"coordinates":[-3.527328968,39.4668388367],"type":"Point"}
}