{
  "type": "Feature",
  "properties": {
    "iso:country":"ES",
    "sg:address":"B, 4",
    "sg:city":"Alcoi",
    "sg:orig_category":"Fabricaci\u00d3n De Productos Textiles Sin Tejer",
    "sg:phone":"+34 965 52 39 13",
    "sg:postcode":"03800",
    "sg:province":"Alicante",
    "wof:name":"Gamma Tensor S.l.",
    "wof:placetype":"venue"
},
  "geometry": {"coordinates":[-0.4732739925,38.6984100342],"type":"Point"}
}