{
  "type": "Feature",
  "properties": {
    "addr:full":"Calle de Onesimo Redondo, S/n Ampuero Cantabria 39840",
    "addr:housenumber":"s / n",
    "addr:postcode":"39840",
    "addr:street":"Calle De Onesimo Redondo",
    "iso:country":"ES",
    "sg:address":"Calle de Onesimo Redondo, S/n",
    "sg:city":"Ampuero",
    "sg:orig_category":"Reposter\u00cdas",
    "sg:phone":"+34 942 63 41 42",
    "sg:postcode":"39840",
    "sg:province":"Cantabria",
    "wof:name":"Colina Torre Teresa",
    "wof:placetype":"venue"
},
  "geometry": {"coordinates":[-3.4166390896,43.3434791565],"type":"Point"}
}