{
  "type": "Feature",
  "properties": {
    "iso:country":"ES",
    "sg:address":"Ctra Madrid, S/n",
    "sg:city":"Molina Segura",
    "sg:orig_category":"Alimentaci\u00d3n: Aditivos, Esencias Alimentarias, Levaduras (fabricaci\u00d3n, Al Por Mayor)",
    "sg:phone":"+34 902 10 22 52",
    "sg:postcode":"30500",
    "sg:province":"Murcia",
    "wof:name":"Arconsa S.a.",
    "wof:placetype":"venue"
},
  "geometry": {"coordinates":[-1.2257548571,38.0739707947],"type":"Point"}
}