{
  "type": "Feature",
  "properties": {
    "addr:full":"Plaz Maria De Molina, 1 Palencia Palencia 34002",
    "addr:postcode":"34002",
    "iso:country":"ES",
    "sg:address":"Plaz Maria De Molina, 1",
    "sg:city":"Palencia",
    "sg:orig_category":"Autob\u00das (explotaci\u00d3n Y Servicios De)",
    "sg:phone":"+34 979 72 12 53",
    "sg:postcode":"34002",
    "sg:province":"Palencia",
    "wof:name":"Mier Alvarez Jose De",
    "wof:placetype":"venue"
},
  "geometry": {"coordinates":[-4.52703619,42.0040588379],"type":"Point"}
}