{
  "type": "Feature",
  "properties": {
    "addr:full":"Calle de Buen Pastor, 244 S. Fernando C\u00e1diz 11100",
    "addr:housenumber":"244",
    "addr:postcode":"11100",
    "addr:street":"Calle De Buen Pastor;S. Fernando Ca\u0301Diz",
    "iso:country":"ES",
    "sg:address":"Calle de Buen Pastor, 244",
    "sg:city":"S. Fernando",
    "sg:orig_category":"Ense\u00d1anza Variada",
    "sg:phone":"+34 956 48 75 98",
    "sg:postcode":"11100",
    "sg:province":"C\u00e1diz",
    "wof:name":"Garcia Gutierrez Juan Asensio",
    "wof:placetype":"venue"
},
  "geometry": {"coordinates":[-6.2078652382,36.4447669983],"type":"Point"}
}