{
  "type": "Feature",
  "properties": {
    "addr:full":"Nou, 9 Bossost Lleida 25550",
    "addr:housenumber":"9",
    "addr:postcode":"25550",
    "addr:street":"Nou",
    "iso:country":"ES",
    "sg:address":"Nou, 9",
    "sg:city":"Bossost",
    "sg:classifiers":[
        {
            "category":"Taxi",
            "type":"Transportation"
        }
    ],
    "sg:phone":"+34 973 64 70 27",
    "sg:postcode":"25550",
    "sg:province":"Lleida",
    "wof:name":"Moles Gonzalez Benjamin",
    "wof:placetype":"venue"
},
  "geometry": {"coordinates":[0.6910129786,42.7821159363],"type":"Point"}
}