{
  "type": "Feature",
  "properties": {
    "iso:country":"ES",
    "sg:address":"Carr Gas, 14",
    "sg:city":"Palafrugell",
    "sg:orig_category":"Tapones Y Art\u00cdculos De Corcho",
    "sg:phone":"+34 972 30 25 26",
    "sg:postcode":"17200",
    "sg:province":"Girona",
    "sg:website":"www.articor.com",
    "wof:name":"Articor S.l.",
    "wof:placetype":"venue"
},
  "geometry": {"coordinates":[3.1592626572,41.9261894226],"type":"Point"}
}