{
  "type": "Feature",
  "properties": {
    "addr:full":"Valle Cares, S/n Lomas Madrid 28669",
    "addr:housenumber":"s / n",
    "addr:postcode":"28669",
    "addr:street":"Cares",
    "iso:country":"ES",
    "sg:address":"Valle Cares, S/n",
    "sg:city":"Lomas",
    "sg:orig_category":"Ingeniero",
    "sg:phone":"+34 916 33 13 40",
    "sg:postcode":"28669",
    "sg:province":"Madrid",
    "sg:website":"www.agrenvec.com",
    "wof:name":"Agrenvec S.l.",
    "wof:placetype":"venue"
},
  "geometry": {"coordinates":[-3.9016671181,40.4386520386],"type":"Point"}
}