{
  "type": "Feature",
  "properties": {
    "addr:full":"S Jose(la Cueva), 21 Monteagudo Murcia 30160",
    "addr:housenumber":"21",
    "addr:postcode":"30160",
    "addr:street":"S;La Cueva",
    "iso:country":"ES",
    "sg:address":"S Jose(la Cueva), 21",
    "sg:city":"Monteagudo",
    "sg:orig_category":"Empresas De Escayolas",
    "sg:phone":"+34 968 85 13 41",
    "sg:postcode":"30160",
    "sg:province":"Murcia",
    "wof:name":"Perez Fernandez Francisco",
    "wof:placetype":"venue"
},
  "geometry": {"coordinates":[-1.0960119963,38.0188484192],"type":"Point"}
}