{
  "type": "Feature",
  "properties": {
    "iso:country":"ES",
    "sg:address":"Calle de Gaudi (de), 5",
    "sg:city":"Boadilla Del Monte",
    "sg:orig_category":"Asesor\u00cda Sobre Comunicaci\u00d3n De Empresas",
    "sg:phone":"+34 916 33 69 99",
    "sg:postcode":"28660",
    "sg:province":"Madrid",
    "wof:name":"Recoletos Servicios De Asesoria S.l.",
    "wof:placetype":"venue"
},
  "geometry": {"coordinates":[-3.8951246738,40.4040641785],"type":"Point"}
}