{
  "type": "Feature",
  "properties": {
    "iso:country":"ES",
    "sg:address":"Pase Pintor Martinez Vazquez, 12",
    "sg:city":"Arenas San Pedro",
    "sg:orig_category":"Supermercados Y Hipermercados",
    "sg:phone":"+34 920 37 26 88",
    "sg:postcode":"05400",
    "sg:province":"\u00c1vila",
    "wof:name":"Cermol 79 S.a.",
    "wof:placetype":"venue"
},
  "geometry": {"coordinates":[-5.0852108002,40.2112960815],"type":"Point"}
}