{
  "type": "Feature",
  "properties": {
    "addr:full":"Calle de Villavieja, 15 Castellon Castell\u00f3n 12003",
    "addr:housenumber":"15",
    "addr:postcode":"12003",
    "addr:street":"Calle De Villavieja",
    "iso:country":"ES",
    "sg:address":"Calle de Villavieja, 15",
    "sg:city":"Castellon",
    "sg:orig_category":"Electricidad: Instaladores",
    "sg:phone":"+34 964 22 11 33",
    "sg:postcode":"12003",
    "sg:province":"Castell\u00f3n",
    "wof:name":"Instalaciones Gamarvic S.l",
    "wof:placetype":"venue"
},
  "geometry": {"coordinates":[-0.0292990003,39.9902572632],"type":"Point"}
}