{
  "type": "Feature",
  "properties": {
    "iso:country":"ES",
    "sg:address":"Pase Pereda, 32",
    "sg:city":"Santander",
    "sg:orig_category":"M\u00c9dicos: Cirug\u00cda Cardiovascular Y Tor\u00c1cica",
    "sg:phone":"+34 942 31 44 44",
    "sg:postcode":"39004",
    "sg:province":"Cantabria",
    "wof:name":"Gomez Fleitas Manuel",
    "wof:placetype":"venue"
},
  "geometry": {"coordinates":[-3.7988109589,43.4623680115],"type":"Point"}
}