{
  "type": "Feature",
  "properties": {
    "addr:full":"Calle de Marin Moll Duniach, 20 Palma Islas Baleares 07014",
    "addr:housenumber":"20",
    "addr:postcode":"07014",
    "addr:street":"Calle De Marin Moll Duniach",
    "iso:country":"ES",
    "sg:address":"Calle de Marin Moll Duniach, 20",
    "sg:city":"Palma",
    "sg:orig_category":"Plomeros",
    "sg:phone":"+34 971 28 13 76",
    "sg:postcode":"07014",
    "sg:province":"Islas Baleares",
    "wof:name":"Balboa Membrive Maximiano",
    "wof:placetype":"venue"
},
  "geometry": {"coordinates":[2.629185915,39.5714416504],"type":"Point"}
}