{
  "type": "Feature",
  "properties": {
    "addr:full":"Calle de Madridejos, 15 Madrid Madrid 28026",
    "addr:housenumber":"15",
    "addr:postcode":"madrid;28026",
    "addr:street":"Calle De Madridejos",
    "iso:country":"ES",
    "sg:address":"Calle de Madridejos, 15",
    "sg:city":"Madrid",
    "sg:orig_category":"Alimentaci\u00d3n General (al Por Menor)",
    "sg:phone":"+34 915 69 32 14",
    "sg:postcode":"28026",
    "sg:province":"Madrid",
    "wof:name":"Pollo Rico S.l.",
    "wof:placetype":"venue"
},
  "geometry": {"coordinates":[-3.7102708817,40.3855743408],"type":"Point"}
}