{
  "type": "Feature",
  "properties": {
    "addr:full":"Carrer de Palangres, 2 Can Pastilla Islas Baleares 07610",
    "addr:housenumber":"2",
    "addr:postcode":"07610",
    "addr:street":"Carrer De Palangres",
    "iso:country":"ES",
    "sg:address":"Carrer de Palangres, 2",
    "sg:city":"Can Pastilla",
    "sg:orig_category":"Ense\u00d1ante, Direcci\u00d3n",
    "sg:phone":"+34 971 49 00 25",
    "sg:postcode":"07610",
    "sg:province":"Islas Baleares",
    "wof:name":"Llambias Piza Francisca",
    "wof:placetype":"venue"
},
  "geometry": {"coordinates":[2.7154500484,39.5350074768],"type":"Point"}
}