{
  "type": "Feature",
  "properties": {
    "iso:country":"ES",
    "sg:address":"Calle de Valmojado, 131",
    "sg:city":"Madrid",
    "sg:orig_category":"Bazares, Art\u00cdculos De Limpieza Y De Cocina (al Por Menor)",
    "sg:phone":"+34 915 09 96 57",
    "sg:postcode":"28047",
    "sg:province":"Madrid",
    "wof:name":"Lin  Kang Yun",
    "wof:placetype":"venue"
},
  "geometry": {"coordinates":[-3.7570691109,40.3910598755],"type":"Point"}
}