{
  "type": "Feature",
  "properties": {
    "addr:full":"Calle de Charles Darwin, S/n Sevilla Sevilla 41092",
    "addr:housenumber":"s / n",
    "addr:postcode":"41092",
    "addr:street":"Calle De Charles Darwin",
    "iso:country":"ES",
    "sg:address":"Calle de Charles Darwin, S/n",
    "sg:city":"Sevilla",
    "sg:orig_category":"Cajas De Ahorro",
    "sg:phone":"+34 954 46 76 75",
    "sg:postcode":"41092",
    "sg:province":"Sevilla",
    "wof:name":"Unicaja",
    "wof:placetype":"venue"
},
  "geometry": {"coordinates":[-6.0050139427,37.4021492004],"type":"Point"}
}