{
  "type": "Feature",
  "properties": {
    "addr:full":"Calle de Bentades, 2 Mungia Vizcaya 48100",
    "addr:housenumber":"2",
    "addr:postcode":"48100",
    "addr:street":"Calle De Bentades",
    "iso:country":"ES",
    "sg:address":"Calle de Bentades, 2",
    "sg:city":"Mungia",
    "sg:orig_category":"Centros M\u00c9dicos Y Sociales, Dispensarios",
    "sg:phone":"+34 946 74 36 07",
    "sg:postcode":"48100",
    "sg:province":"Vizcaya",
    "wof:name":"Varona Leguinazabal Juan",
    "wof:placetype":"venue"
},
  "geometry": {"coordinates":[-2.8507039547,43.3569412231],"type":"Point"}
}