{
  "type": "Feature",
  "properties": {
    "addr:full":"Cmno Fontanillas (las), Km. 0042,3 Lucena C\u00f3rdoba 14900",
    "addr:postcode":"14900",
    "addr:street":"Cmno Fontanillas Las Km. 0042,3",
    "iso:country":"ES",
    "sg:address":"Cmno Fontanillas (las), Km. 0042,3",
    "sg:city":"Lucena",
    "sg:orig_category":"Reciclaje, Desguace De Veh\u00cdculos",
    "sg:phone":"+34 957 33 48 34",
    "sg:postcode":"14900",
    "sg:province":"C\u00f3rdoba",
    "wof:name":"Autodesguace Y Reciclajes Lucena S.l.",
    "wof:placetype":"venue"
},
  "geometry": {"coordinates":[-4.4847187996,37.4150352478],"type":"Point"}
}