{
  "type": "Feature",
  "properties": {
    "iso:country":"ES",
    "sg:address":"Calle de Alcalde Isaac Dominguez, 14",
    "sg:city":"Teror",
    "sg:orig_category":"Mercer\u00cda, Lencer\u00cda (al Por Menor)",
    "sg:phone":"+34 928 63 06 65",
    "sg:postcode":"35330",
    "sg:province":"Las Palmas",
    "wof:name":"Suarez Perez Antonio Vicente",
    "wof:placetype":"venue"
},
  "geometry": {"coordinates":[-15.5474185944,28.061290741],"type":"Point"}
}