{
  "type": "Feature",
  "properties": {
    "addr:full":"Calle de Martinez, 2 Malaga M\u00e1laga 29005",
    "addr:housenumber":"2",
    "addr:postcode":"29005",
    "addr:street":"Calle De Martinez;Ma\u0301Laga",
    "iso:country":"ES",
    "sg:address":"Calle de Martinez, 2",
    "sg:city":"Malaga",
    "sg:orig_category":"Aguas (distribuci\u00d3n, Servicios)",
    "sg:phone":"+34 952 12 02 40",
    "sg:postcode":"29005",
    "sg:province":"M\u00e1laga",
    "wof:name":"Empresa Municipal De Aguas De Malaga S.a.",
    "wof:placetype":"venue"
},
  "geometry": {"coordinates":[-4.4226517677,36.7184257507],"type":"Point"}
}