{
  "type": "Feature",
  "properties": {
    "iso:country":"ES",
    "sg:address":"Carrer de Llibertat, S/n",
    "sg:city":"Ametlla Mar",
    "sg:orig_category":"Empresas De Electricidad En General",
    "sg:phone":"+34 977 49 31 08",
    "sg:postcode":"43860",
    "sg:province":"Tarragona",
    "wof:name":"Electrica Del Ebro S. A.",
    "wof:placetype":"venue"
},
  "geometry": {"coordinates":[0.800424993,40.8844299316],"type":"Point"}
}