{
  "type": "Feature",
  "properties": {
    "iso:country":"ES",
    "sg:address":"Calle de Ramon Y Cajal, 5",
    "sg:city":"Pe\u00f1alba",
    "sg:orig_category":"Alimentaci\u00d3n General (al Por Menor)",
    "sg:phone":"+34 974 46 31 97",
    "sg:postcode":"22592",
    "sg:province":"Huesca",
    "wof:name":"Pomar Clavel Elena",
    "wof:placetype":"venue"
},
  "geometry": {"coordinates":[-0.0389200002,41.5002555847],"type":"Point"}
}