{
  "type": "Feature",
  "properties": {
    "addr:full":"Calle de Polo Y Peyrolon, 5 Valencia Valencia 46021",
    "addr:housenumber":"5",
    "addr:postcode":"46021",
    "addr:street":"Calle De Polo Y Peyrolon",
    "iso:country":"ES",
    "sg:address":"Calle de Polo Y Peyrolon, 5",
    "sg:city":"Valencia",
    "sg:orig_category":"Arquitectos",
    "sg:phone":"+34 963 69 54 36",
    "sg:postcode":"46021",
    "sg:province":"Valencia",
    "wof:name":"Giner Giner Miguel",
    "wof:placetype":"venue"
},
  "geometry": {"coordinates":[-0.3560740054,39.4714851379],"type":"Point"}
}