{
  "type": "Feature",
  "properties": {
    "iso:country":"ES",
    "sg:address":"Calle de Navacerrada, Km. 0001,5",
    "sg:city":"Brunete",
    "sg:orig_category":"Dise\u00d1o Industrial",
    "sg:phone":"+34 918 15 90 20",
    "sg:postcode":"28690",
    "sg:province":"Madrid",
    "wof:name":"Benito Moran Gregorio",
    "wof:placetype":"venue"
},
  "geometry": {"coordinates":[-3.9946110249,40.400680542],"type":"Point"}
}