{
  "type": "Feature",
  "properties": {
    "iso:country":"ES",
    "sg:address":"Calle de Albareda, 7",
    "sg:city":"Zaragoza",
    "sg:orig_category":"Bisuter\u00cda, Joyer\u00cda, Relojer\u00cda (al Por Menor)",
    "sg:phone":"+34 976 21 12 34",
    "sg:postcode":"50004",
    "sg:province":"Zaragoza",
    "wof:name":"Sierra Ezquerro Carlos",
    "wof:placetype":"venue"
},
  "geometry": {"coordinates":[-0.8852720261,41.649356842],"type":"Point"}
}