{
  "type": "Feature",
  "properties": {
    "iso:country":"ES",
    "sg:address":"Avda Palma De Mallorca, 35",
    "sg:city":"Torremolinos",
    "sg:orig_category":"Agencias De Viajes",
    "sg:phone":"+34 952 38 90 11",
    "sg:postcode":"29620",
    "sg:province":"M\u00e1laga",
    "sg:website":"www.veuromar.com",
    "wof:name":"Viajes Euromar S.a.",
    "wof:placetype":"venue"
},
  "geometry": {"coordinates":[-4.4995861053,36.6201553345],"type":"Point"}
}