{
  "type": "Feature",
  "properties": {
    "addr:full":"Calle de Santa Engracia, 83 Madrid Madrid 28010",
    "addr:housenumber":"83",
    "addr:postcode":"madrid;28010",
    "addr:street":"Calle De Santa Engracia",
    "iso:country":"ES",
    "sg:address":"Calle de Santa Engracia, 83",
    "sg:city":"Madrid",
    "sg:orig_category":"Quincaller\u00cda (al Por Menor)",
    "sg:phone":"+34 914 48 38 93",
    "sg:postcode":"28010",
    "sg:province":"Madrid",
    "wof:name":"Martinez Naranjo Abel",
    "wof:placetype":"venue"
},
  "geometry": {"coordinates":[-3.699146986,40.4356536865],"type":"Point"}
}