{
  "type": "Feature",
  "properties": {
    "addr:full":"Carr Sebastian Hernandez, De, S/n Carcaixent Valencia 46740",
    "addr:postcode":"46740",
    "addr:street":"Carr Sebastian Hernandez De S / N",
    "iso:country":"ES",
    "sg:address":"Carr Sebastian Hernandez, De, S/n",
    "sg:city":"Carcaixent",
    "sg:orig_category":"Materias Pl\u00c1sticas: Productos De Consumo Masivo (fabricaci\u00d3n, Al Por Mayor)",
    "sg:phone":"+34 962 43 49 55",
    "sg:postcode":"46740",
    "sg:province":"Valencia",
    "wof:name":"Biosca Boluda Balbino",
    "wof:placetype":"venue"
},
  "geometry": {"coordinates":[-0.4447340071,39.1192092896],"type":"Point"}
}