{
  "type": "Feature",
  "properties": {
    "addr:full":"Calle de Nueva, S/n Robledo Albacete 02340",
    "addr:housenumber":"s / n",
    "addr:postcode":"02340",
    "addr:street":"Calle De Nueva;Robledo Albacete",
    "iso:country":"ES",
    "sg:address":"Calle de Nueva, S/n",
    "sg:city":"Robledo",
    "sg:orig_category":"Centros De Educaci\u00d3n Especial",
    "sg:phone":"+34 967 38 82 32",
    "sg:postcode":"02340",
    "sg:province":"Albacete",
    "wof:name":"Colegio Publico",
    "wof:placetype":"venue"
},
  "geometry": {"coordinates":[-2.4518339634,38.7574501038],"type":"Point"}
}