{
  "type": "Feature",
  "properties": {
    "iso:country":"ES",
    "sg:address":"Psaj Ripalda, 12",
    "sg:city":"Valencia",
    "sg:orig_category":"Cueros Y Pieles (al Por Mayor)",
    "sg:phone":"+34 963 52 78 66",
    "sg:postcode":"46002",
    "sg:province":"Valencia",
    "wof:name":"Andres Molina Y Asociados S. L.",
    "wof:placetype":"venue"
},
  "geometry": {"coordinates":[-0.3764049113,39.4721908569],"type":"Point"}
}