{
  "type": "Feature",
  "properties": {
    "addr:full":"Calle de San Lorenzo, 27 Zaragoza Zaragoza 50001",
    "addr:housenumber":"27",
    "addr:postcode":"50001",
    "addr:street":"Calle De San Lorenzo",
    "iso:country":"ES",
    "sg:address":"Calle de San Lorenzo, 27",
    "sg:city":"Zaragoza",
    "sg:orig_category":"Molduras, Junquillos, Listones Y Molduras Perforadas",
    "sg:phone":"+34 976 29 72 25",
    "sg:postcode":"50001",
    "sg:province":"Zaragoza",
    "wof:name":"Miguel Campoverde Enrique",
    "wof:placetype":"venue"
},
  "geometry": {"coordinates":[-0.8746960163,41.6523475647],"type":"Point"}
}