{
  "type": "Feature",
  "properties": {
    "addr:full":"Calle de Conde Duque, 22 Madrid Madrid 28015",
    "addr:housenumber":"22",
    "addr:postcode":"madrid;28015",
    "addr:street":"Calle De Conde Duque",
    "iso:country":"ES",
    "sg:address":"Calle de Conde Duque, 22",
    "sg:city":"Madrid",
    "sg:orig_category":"Peluquer\u00cdas, Peluquer\u00cda Mixta",
    "sg:phone":"+34 915 47 76 65",
    "sg:postcode":"28015",
    "sg:province":"Madrid",
    "wof:name":"Calonge Flores Marta",
    "wof:placetype":"venue"
},
  "geometry": {"coordinates":[-3.7105019093,40.4273605347],"type":"Point"}
}