{
  "type": "Feature",
  "properties": {
    "iso:country":"ES",
    "sg:address":"Calle de Periferica, 7",
    "sg:city":"Navas Del Marques",
    "sg:orig_category":"Empresas De Carpinter\u00cda De Madera",
    "sg:phone":"+34 918 97 21 37",
    "sg:postcode":"05230",
    "sg:province":"\u00c1vila",
    "wof:name":"Salvador Sanz S.a.",
    "wof:placetype":"venue"
},
  "geometry": {"coordinates":[-4.332198143,40.594959259],"type":"Point"}
}