{
  "type": "Feature",
  "properties": {
    "iso:country":"ES",
    "sg:address":"Plaz Jardines De Don Diego, 2",
    "sg:city":"Aranda Duero",
    "sg:orig_category":"Cajas De Ahorro",
    "sg:phone":"+34 947 51 41 32",
    "sg:postcode":"09400",
    "sg:province":"Burgos",
    "sg:website":"www.bancaja.es",
    "wof:name":"Caja De Ahorros De Valencia Castellon Y Alicante",
    "wof:placetype":"venue"
},
  "geometry": {"coordinates":[-3.6889948845,41.6699256897],"type":"Point"}
}