{
  "type": "Feature",
  "properties": {
    "addr:full":"Catamaran, S/n Los Narejos Murcia 30710",
    "addr:housenumber":"s / n",
    "addr:postcode":"30710",
    "addr:street":"Catamaran;Los Narejos",
    "iso:country":"ES",
    "sg:address":"Catamaran, S/n",
    "sg:city":"Los Narejos",
    "sg:orig_category":"Ropa Para Se\u00d1oras (al Por Menor)",
    "sg:phone":"+34 968 17 02 25",
    "sg:postcode":"30710",
    "sg:province":"Murcia",
    "wof:name":"New Orkan S.l.",
    "wof:placetype":"venue"
},
  "geometry": {"coordinates":[-0.8345069885,37.763507843],"type":"Point"}
}