{
  "type": "Feature",
  "properties": {
    "addr:full":"Carr Sant Tomas, 139 Benicasim Castell\u00f3n 12560",
    "addr:housenumber":"139",
    "addr:postcode":"12560",
    "addr:street":"Carr Sant Tomas",
    "iso:country":"ES",
    "sg:address":"Carr Sant Tomas, 139",
    "sg:city":"Benicasim",
    "sg:orig_category":"Mec\u00c1nico Del Autom\u00d3vil",
    "sg:phone":"+34 964 30 00 03",
    "sg:postcode":"12560",
    "sg:province":"Castell\u00f3n",
    "wof:name":"Soliva Salvador Francisco",
    "wof:placetype":"venue"
},
  "geometry": {"coordinates":[0.0457400009,40.0510292053],"type":"Point"}
}