{
  "type": "Feature",
  "properties": {
    "addr:full":"Calle de Salamanca, 21 Barrax Albacete 02639",
    "addr:housenumber":"21",
    "addr:postcode":"02639",
    "addr:street":"Calle De Salamanca",
    "iso:country":"ES",
    "sg:address":"Calle de Salamanca, 21",
    "sg:city":"Barrax",
    "sg:orig_category":"Farmacias",
    "sg:phone":"+34 967 36 45 76",
    "sg:postcode":"02639",
    "sg:province":"Albacete",
    "wof:name":"Mero\u00f1o Bautista Ana Isabel",
    "wof:placetype":"venue"
},
  "geometry": {"coordinates":[-2.2013189793,39.0461196899],"type":"Point"}
}