{
  "type": "Feature",
  "properties": {
    "iso:country":"ES",
    "sg:address":"Calle de Carmen, 1",
    "sg:city":"Nerja",
    "sg:orig_category":"Organismos De Turismo",
    "sg:phone":"+34 952 52 61 79",
    "sg:postcode":"29780",
    "sg:province":"M\u00e1laga",
    "wof:name":"Patronato De La Cueva De Nerja",
    "wof:placetype":"venue"
},
  "geometry": {"coordinates":[-3.876619339,36.7450485229],"type":"Point"}
}