{
  "type": "Feature",
  "properties": {
    "iso:country":"ES",
    "sg:address":"Praj Benzal (el), S/n",
    "sg:city":"Benzal",
    "sg:orig_category":"Importaci\u00d3n",
    "sg:phone":"+34 950 52 96 02",
    "sg:postcode":"04640",
    "sg:province":"Almer\u00eda",
    "wof:name":"Francisco Oliva S.l.",
    "wof:placetype":"venue"
},
  "geometry": {"coordinates":[-1.7254290581,37.3880081177],"type":"Point"}
}