{
  "type": "Feature",
  "properties": {
    "iso:country":"ES",
    "sg:address":"Carrer de Soledat, 9",
    "sg:city":"Vic",
    "sg:orig_category":"Lavado, Limpieza De Veh\u00cdculos",
    "sg:phone":"+34 938 83 35 72",
    "sg:postcode":"08500",
    "sg:province":"Barcelona",
    "wof:name":"Autonec-vic S.c.p.",
    "wof:placetype":"venue"
},
  "geometry": {"coordinates":[2.2557470798,41.927066803],"type":"Point"}
}