{
  "type": "Feature",
  "properties": {
    "addr:full":"Plaz San Juan, 2 Jerez De La Frontera C\u00e1diz 11403",
    "addr:housenumber":"2",
    "addr:postcode":"11403",
    "addr:street":"Plaz San Juan",
    "iso:country":"ES",
    "sg:address":"Plaz San Juan, 2",
    "sg:city":"Jerez De La Frontera",
    "sg:orig_category":"Persianas Interiores, Exteriores",
    "sg:phone":"+34 956 34 50 52",
    "sg:postcode":"11403",
    "sg:province":"C\u00e1diz",
    "wof:name":"Prote-sol S.l.",
    "wof:placetype":"venue"
},
  "geometry": {"coordinates":[-6.1422657967,36.6865386963],"type":"Point"}
}