{
  "type": "Feature",
  "properties": {
    "addr:full":"Calle de Perez Galdos, 3 Le\u00f3n Le\u00f3n 24009",
    "addr:housenumber":"3",
    "addr:postcode":"24009",
    "addr:street":"Calle De Perez Galdos;Leo\u0301N",
    "iso:country":"ES",
    "sg:address":"Calle de Perez Galdos, 3",
    "sg:city":"Le\u00f3n",
    "sg:orig_category":"Congelados: Productos Alimentarios (al Por Menor)",
    "sg:phone":"+34 987 22 43 09",
    "sg:postcode":"24009",
    "sg:province":"Le\u00f3n",
    "wof:name":"Congelados Casta\u00f1on S.l",
    "wof:placetype":"venue"
},
  "geometry": {"coordinates":[-5.5877351761,42.5997123718],"type":"Point"}
}