{
  "type": "Feature",
  "properties": {
    "addr:full":"Calle de Padre Martinez Garcia, 41 Molina Segura Murcia 30500",
    "addr:housenumber":"41",
    "addr:postcode":"30500",
    "addr:street":"Calle De Padre Martinez Garcia",
    "iso:country":"ES",
    "sg:address":"Calle de Padre Martinez Garcia, 41",
    "sg:city":"Molina Segura",
    "sg:orig_category":"Agentes Generales De Seguros",
    "sg:phone":"+34 968 64 22 09",
    "sg:postcode":"30500",
    "sg:province":"Murcia",
    "wof:name":"Angel Canovas Garcia S.l.",
    "wof:placetype":"venue"
},
  "geometry": {"coordinates":[-1.2083063126,38.0545578003],"type":"Point"}
}