{
  "type": "Feature",
  "properties": {
    "iso:country":"ES",
    "sg:address":"Rua De Arriba, 28",
    "sg:city":"Cee",
    "sg:orig_category":"Mercer\u00cda, Lencer\u00cda (al Por Menor)",
    "sg:phone":"+34 981 74 59 80",
    "sg:postcode":"15270",
    "sg:province":"La Coru\u00f1a",
    "wof:name":"Mejuto Leis Aurea",
    "wof:placetype":"venue"
},
  "geometry": {"coordinates":[-9.1879320145,42.9548606873],"type":"Point"}
}