{
  "type": "Feature",
  "properties": {
    "iso:country":"ES",
    "sg:address":"Calle de Perez Galdos, 52",
    "sg:city":"Bilbao",
    "sg:orig_category":"Papeler\u00cdas: Art\u00cdculos (al Por Mayor)",
    "sg:phone":"+34 944 27 28 09",
    "sg:postcode":"48013",
    "sg:province":"Vizcaya",
    "wof:name":"Dimpel S.l.",
    "wof:placetype":"venue"
},
  "geometry": {"coordinates":[-2.9482591152,43.2603416443],"type":"Point"}
}