{
  "type": "Feature",
  "properties": {
    "iso:country":"ES",
    "sg:address":"Avda Baron De Carcer, 25",
    "sg:city":"Valencia",
    "sg:orig_category":"Loter\u00cda Y T\u00d3mbola",
    "sg:phone":"+34 963 51 81 64",
    "sg:postcode":"46001",
    "sg:province":"Valencia",
    "wof:name":"Lopez Sanchez Arturo Alberto",
    "wof:placetype":"venue"
},
  "geometry": {"coordinates":[-0.379599005,39.4720916748],"type":"Point"}
}