{
  "type": "Feature",
  "properties": {
    "iso:country":"ES",
    "sg:address":"Carrer de Rei En Jaume, 7",
    "sg:city":"Hostalets Pierola",
    "sg:orig_category":"Periodistas Profesionales",
    "sg:phone":"+34 937 71 25 53",
    "sg:postcode":"08781",
    "sg:province":"Barcelona",
    "wof:name":"Heda Comunicacion S.l.",
    "wof:placetype":"venue"
},
  "geometry": {"coordinates":[1.769389987,41.535446167],"type":"Point"}
}