{
  "type": "Feature",
  "properties": {
    "addr:full":"Pl Sant Jaume, 41 Sabadell Barcelona 08201",
    "addr:housenumber":"41",
    "addr:postcode":"08201",
    "addr:street":"Pl Sant Jaume",
    "iso:country":"ES",
    "sg:address":"Pl Sant Jaume, 41",
    "sg:city":"Sabadell",
    "sg:orig_category":"Caf\u00c9s, Bares, Cervecer\u00cdas",
    "sg:phone":"+34 937 25 21 39",
    "sg:postcode":"08201",
    "sg:province":"Barcelona",
    "wof:name":"Sentis Paris Josep Miquel",
    "wof:placetype":"venue"
},
  "geometry": {"coordinates":[2.10414505,41.5462493896],"type":"Point"}
}