{
  "type": "Feature",
  "properties": {
    "iso:country":"ES",
    "sg:address":"Calle de Alferez Rubianes, 1",
    "sg:city":"Cuenca",
    "sg:orig_category":"\u00d3ptica: Instrumentos (fabricaci\u00d3n)",
    "sg:phone":"+34 969 23 39 32",
    "sg:postcode":"16004",
    "sg:province":"Cuenca",
    "wof:name":"Reinoso Bonilla Maria Dolores",
    "wof:placetype":"venue"
},
  "geometry": {"coordinates":[-2.1361033916,40.0704689026],"type":"Point"}
}