{
  "type": "Feature",
  "properties": {
    "iso:country":"ES",
    "sg:address":"Barr Basan Peque\u00d1o, S/n",
    "sg:city":"Chantada",
    "sg:orig_category":"M\u00c1rmoles, Granitos Y Piedras Naturales",
    "sg:phone":"+34 982 44 17 51",
    "sg:postcode":"27500",
    "sg:province":"Lugo",
    "wof:name":"Regueira Vazquez Jose",
    "wof:placetype":"venue"
},
  "geometry": {"coordinates":[-7.7645859718,42.6176071167],"type":"Point"}
}