{
  "type": "Feature",
  "properties": {
    "addr:full":"Carrer de Bisbe Vilanova, 2 Olot Girona 17800",
    "addr:housenumber":"2",
    "addr:postcode":"17800",
    "addr:street":"Carrer De Bisbe Vilanova",
    "iso:country":"ES",
    "sg:address":"Carrer de Bisbe Vilanova, 2",
    "sg:city":"Olot",
    "sg:orig_category":"Servicios De Telecomunicaciones",
    "sg:phone":"+34 972 26 05 53",
    "sg:postcode":"17800",
    "sg:province":"Girona",
    "wof:name":"Camos Comunicacio S.l.",
    "wof:placetype":"venue"
},
  "geometry": {"coordinates":[2.4851970673,42.1796035767],"type":"Point"}
}