{
  "type": "Feature",
  "properties": {
    "iso:country":"ES",
    "sg:address":"Calle de Esteban Mora, 45",
    "sg:city":"Madrid",
    "sg:classifiers":[
        {
            "category":"Personal",
            "subcategory":"Barber",
            "type":"Services"
        }
    ],
    "sg:phone":"+34 914 05 36 40",
    "sg:postcode":"28027",
    "sg:province":"Madrid",
    "sg:tags":[
        "caballeros",
        "de",
        "peluqueros"
    ],
    "wof:name":"Martin Plaza Esteban",
    "wof:placetype":"venue"
},
  "geometry": {"coordinates":[-3.6537630558,40.4391098022],"type":"Point"}
}