{
  "type": "Feature",
  "properties": {
    "addr:full":"Calle de Sorolla, 7 Linea De La Concepcion C\u00e1diz 11300",
    "addr:housenumber":"7",
    "addr:postcode":"11300",
    "addr:street":"Calle De Sorolla;Ca\u0301Diz",
    "iso:country":"ES",
    "sg:address":"Calle de Sorolla, 7",
    "sg:city":"Linea De La Concepcion",
    "sg:orig_category":"Chapister\u00cda",
    "sg:phone":"+34 956 17 63 16",
    "sg:postcode":"11300",
    "sg:province":"C\u00e1diz",
    "wof:name":"Servan Puya Martin",
    "wof:placetype":"venue"
},
  "geometry": {"coordinates":[-5.3548297882,36.1698608398],"type":"Point"}
}