{
  "type": "Feature",
  "properties": {
    "addr:full":"Avda Baron De Warsage, 2 Calatayud Zaragoza 50300",
    "addr:housenumber":"2",
    "addr:postcode":"50300",
    "addr:street":"Avda Baron De Warsage",
    "iso:country":"ES",
    "sg:address":"Avda Baron De Warsage, 2",
    "sg:city":"Calatayud",
    "sg:orig_category":"Restaurantes",
    "sg:phone":"+34 976 88 38 12",
    "sg:postcode":"50300",
    "sg:province":"Zaragoza",
    "wof:name":"Bar Churreria Mi\u00f1ana S.l.",
    "wof:placetype":"venue"
},
  "geometry": {"coordinates":[-1.6347409487,41.3542747498],"type":"Point"}
}