{
  "type": "Feature",
  "properties": {
    "iso:country":"ES",
    "sg:address":"Calle de Juan Florez, 24",
    "sg:city":"Coru\u00d1a",
    "sg:orig_category":"M\u00c9dicos: Psiquiatr\u00cda",
    "sg:phone":"+34 981 14 20 70",
    "sg:postcode":"15004",
    "sg:province":"La Coru\u00f1a",
    "wof:name":"Rodriguez Lapuerta Pedro",
    "wof:placetype":"venue"
},
  "geometry": {"coordinates":[-8.4085531235,43.3655395508],"type":"Point"}
}