{
  "type": "Feature",
  "properties": {
    "addr:full":"Calle de Villanueva Del Rio Segura, 2 Molina Segura Murcia 30500",
    "addr:housenumber":"2",
    "addr:postcode":"30500",
    "addr:street":"Calle De Villanueva Del Rio Segura",
    "iso:country":"ES",
    "sg:address":"Calle de Villanueva Del Rio Segura, 2",
    "sg:city":"Molina Segura",
    "sg:orig_category":"Artes Gr\u00c1ficas, Artes Pl\u00c1sticas (curso)",
    "sg:phone":"+34 968 64 56 99",
    "sg:postcode":"30500",
    "sg:province":"Murcia",
    "wof:name":"La Imprenta De Murcia S.l.l.",
    "wof:placetype":"venue"
},
  "geometry": {"coordinates":[-1.2119740248,38.0535736084],"type":"Point"}
}