{
  "type": "Feature",
  "properties": {
    "addr:full":"Carr Vallcalent, 28 Lleida Lleida 25006",
    "addr:housenumber":"28",
    "addr:postcode":"25006",
    "addr:street":"Carr Vallcalent",
    "iso:country":"ES",
    "sg:address":"Carr Vallcalent, 28",
    "sg:city":"Lleida",
    "sg:orig_category":"Asociaciones, Organismos Culturales Y Socioeducativos",
    "sg:phone":"+34 973 26 63 03",
    "sg:postcode":"25006",
    "sg:province":"Lleida",
    "wof:name":"Club Raier",
    "wof:placetype":"venue"
},
  "geometry": {"coordinates":[0.6080690026,41.6190834045],"type":"Point"}
}