{
  "type": "Feature",
  "properties": {
    "iso:country":"ES",
    "sg:address":"Avda Ebro, 76",
    "sg:city":"Agoncillo",
    "sg:orig_category":"Mec\u00c1nico Del Autom\u00d3vil",
    "sg:phone":"+34 941 43 14 08",
    "sg:postcode":"26509",
    "sg:province":"La Rioja",
    "wof:name":"Martinez Gumiel Manuel",
    "wof:placetype":"venue"
},
  "geometry": {"coordinates":[-2.1222639084,42.4031410217],"type":"Point"}
}