{
  "type": "Feature",
  "properties": {
    "iso:country":"ES",
    "sg:address":"Av. Ciencias Edif Azalea, S/n",
    "sg:city":"Sevilla",
    "sg:orig_category":"Cer\u00c1micas: Material Y Suministros",
    "sg:phone":"+34 954 44 23 68",
    "sg:postcode":"41020",
    "sg:province":"Sevilla",
    "wof:name":"Sondeos Y Excavaciones Del Sur S.a.",
    "wof:placetype":"venue"
},
  "geometry": {"coordinates":[-5.9219141006,37.3954162598],"type":"Point"}
}