{
  "type": "Feature",
  "properties": {
    "addr:full":"Calle de Nu\u00d1ez De Balboa, 99 Madrid Madrid 28006",
    "addr:housenumber":"99",
    "addr:postcode":"madrid;28006",
    "addr:street":"Calle De Nun\u0303Ez De Balboa",
    "iso:country":"ES",
    "sg:address":"Calle de Nu\u00d1ez De Balboa, 99",
    "sg:city":"Madrid",
    "sg:orig_category":"Cl\u00cdnicas M\u00c9dicas",
    "sg:phone":"+34 915 62 63 80",
    "sg:postcode":"28006",
    "sg:province":"Madrid",
    "wof:name":"Hurtado De Mendoza Lopez Bernabe",
    "wof:placetype":"venue"
},
  "geometry": {"coordinates":[-3.6821269989,40.4351043701],"type":"Point"}
}