{
  "type": "Feature",
  "properties": {
    "iso:country":"ES",
    "sg:address":"Calle de Malaga, 51",
    "sg:city":"Almachar",
    "sg:orig_category":"Tiendas De Grano, Frutas Y Legumbres Secas (al Por Menor)",
    "sg:phone":"+34 952 51 20 49",
    "sg:postcode":"29718",
    "sg:province":"M\u00e1laga",
    "wof:name":"Gutierrez Gomez Jose Rafael",
    "wof:placetype":"venue"
},
  "geometry": {"coordinates":[-4.2146091461,36.8095016479],"type":"Point"}
}