{
  "type": "Feature",
  "properties": {
    "addr:full":"Torreon, 8 Pontedeume La Coru\u00f1a 15600",
    "addr:postcode":"15600",
    "addr:street":"Torreon;Pontedeume;Corun\u0303A",
    "iso:country":"ES",
    "sg:address":"Torreon, 8",
    "sg:city":"Pontedeume",
    "sg:orig_category":"Electrodom\u00c9sticos (al Por Menor)",
    "sg:phone":"+34 981 43 13 99",
    "sg:postcode":"15600",
    "sg:province":"La Coru\u00f1a",
    "wof:name":"Brage Anca Manuel",
    "wof:placetype":"venue"
},
  "geometry": {"coordinates":[-8.17137146,43.4076156616],"type":"Point"}
}