{
  "type": "Feature",
  "properties": {
    "addr:full":"Calle de Leon Felipe, 4 Salamanca Salamanca 37007",
    "addr:housenumber":"4",
    "addr:postcode":"37007",
    "addr:street":"Calle De Leon Felipe",
    "iso:country":"ES",
    "sg:address":"Calle de Leon Felipe, 4",
    "sg:city":"Salamanca",
    "sg:orig_category":"Venta, Instalaci\u00d3n De Calefacci\u00d3n",
    "sg:phone":"+34 923 23 90 25",
    "sg:postcode":"37007",
    "sg:province":"Salamanca",
    "wof:name":"Sucesores De Hijos De A.diaz S.l.",
    "wof:placetype":"venue"
},
  "geometry": {"coordinates":[-5.6676235199,40.9710693359],"type":"Point"}
}