{
  "type": "Feature",
  "properties": {
    "iso:country":"ES",
    "sg:address":"Calle de Real De Guadalix, 7",
    "sg:city":"Guadalix De La Sierra",
    "sg:orig_category":"Puertas Autom\u00c1ticas, Puertas De Garaje",
    "sg:phone":"+34 918 47 10 77",
    "sg:postcode":"28794",
    "sg:province":"Madrid",
    "wof:name":"Portticae S.l.",
    "wof:placetype":"venue"
},
  "geometry": {"coordinates":[-3.6934831142,40.7816619873],"type":"Point"}
}