{
  "type": "Feature",
  "properties": {
    "iso:country":"ES",
    "sg:address":"Kale Nagusia, 18",
    "sg:city":"Astigarraga",
    "sg:orig_category":"Molduras, Junquillos, Listones Y Molduras Perforadas",
    "sg:phone":"+34 943 55 10 07",
    "sg:postcode":"20115",
    "sg:province":"Guip\u00f9zcoa",
    "wof:name":"Aduriz Isasa Mikaela",
    "wof:placetype":"venue"
},
  "geometry": {"coordinates":[-1.9497320652,43.2803611755],"type":"Point"}
}