{
  "type": "Feature",
  "properties": {
    "addr:full":"Calle de Heracles, 1 Valdemoro Madrid 28340",
    "addr:housenumber":"1",
    "addr:postcode":"28340",
    "addr:street":"Calle De Heracles",
    "iso:country":"ES",
    "sg:address":"Calle de Heracles, 1",
    "sg:city":"Valdemoro",
    "sg:orig_category":"Construcciones Met\u00c1licas",
    "sg:phone":"+34 918 08 49 49",
    "sg:postcode":"28340",
    "sg:province":"Madrid",
    "wof:name":"Cubox Metal Y Dise\u00f1o S.l.",
    "wof:placetype":"venue"
},
  "geometry": {"coordinates":[-3.6870820522,40.1807518005],"type":"Point"}
}