{
  "type": "Feature",
  "properties": {
    "iso:country":"ES",
    "sg:address":"Calle de Batalla De Lepanto, 7",
    "sg:city":"Ba\u00d1eza",
    "sg:orig_category":"Peluqueros: De Se\u00d1oras",
    "sg:phone":"+34 987 64 43 61",
    "sg:postcode":"24750",
    "sg:province":"Le\u00f3n",
    "wof:name":"Mazon Morales Maria Soledad",
    "wof:placetype":"venue"
},
  "geometry": {"coordinates":[-5.8970160484,42.3021316528],"type":"Point"}
}