{
  "type": "Feature",
  "properties": {
    "addr:full":"Calle de Ines Rosales, 20 Castilleja Cuesta Sevilla 41950",
    "addr:housenumber":"20",
    "addr:postcode":"41950",
    "addr:street":"Calle De Ines Rosales;Cuesta Sevilla",
    "iso:country":"ES",
    "sg:address":"Calle de Ines Rosales, 20",
    "sg:city":"Castilleja Cuesta",
    "sg:orig_category":"Ropa Para Ni\u00d1os (al Por Menor)",
    "sg:phone":"+34 954 16 09 95",
    "sg:postcode":"41950",
    "sg:province":"Sevilla",
    "wof:name":"Jurado Cejas Maria De Los Milagros",
    "wof:placetype":"venue"
},
  "geometry": {"coordinates":[-6.0547242165,37.3845252991],"type":"Point"}
}