{
  "type": "Feature",
  "properties": {
    "iso:country":"ES",
    "sg:address":"Carr Valencia, 19",
    "sg:city":"Algemesi",
    "sg:orig_category":"Ense\u00d1anza: Profesiones Art\u00cdsticas",
    "sg:phone":"+34 962 42 17 99",
    "sg:postcode":"46680",
    "sg:province":"Valencia",
    "wof:name":"Roig Aliaga Vicente Jose",
    "wof:placetype":"venue"
},
  "geometry": {"coordinates":[-0.4369679987,39.1943473816],"type":"Point"}
}