{
  "type": "Feature",
  "properties": {
    "addr:full":"Calle de Zamora, 14 Medina Campo Valladolid 47400",
    "addr:housenumber":"14",
    "addr:postcode":"47400",
    "addr:street":"Calle De Zamora",
    "iso:country":"ES",
    "sg:address":"Calle de Zamora, 14",
    "sg:city":"Medina Campo",
    "sg:orig_category":"Supermercados Y Hipermercados",
    "sg:phone":"+34 983 80 05 84",
    "sg:postcode":"47400",
    "sg:province":"Valladolid",
    "wof:name":"Santos Boya Luis",
    "wof:placetype":"venue"
},
  "geometry": {"coordinates":[-4.9194288254,41.3067207336],"type":"Point"}
}