{
  "type": "Feature",
  "properties": {
    "addr:full":"Av 8 D'agost, 3 Eivissa Islas Baleares 07800",
    "addr:housenumber":"3",
    "addr:postcode":"07800",
    "addr:street":"Av 8 D'Agost",
    "iso:country":"ES",
    "sg:address":"Av 8 D'agost, 3",
    "sg:city":"Eivissa",
    "sg:orig_category":"Inmobiliaria (agencias)",
    "sg:phone":"+34 971 19 94 79",
    "sg:postcode":"07800",
    "sg:province":"Islas Baleares",
    "wof:name":"Hb Service Ibiza 04, S.l.",
    "wof:placetype":"venue"
},
  "geometry": {"coordinates":[1.4456750154,38.9176979065],"type":"Point"}
}