{
  "type": "Feature",
  "properties": {
    "iso:country":"ES",
    "sg:address":"Calle de Recondo, 19",
    "sg:city":"Valladolid",
    "sg:orig_category":"Herboristas (al Por Menor)",
    "sg:phone":"+34 983 22 69 63",
    "sg:postcode":"47007",
    "sg:province":"Valladolid",
    "wof:name":"Lozano Herrero Montserrat",
    "wof:placetype":"venue"
},
  "geometry": {"coordinates":[-4.730928421,41.6412353516],"type":"Point"}
}