{
  "type": "Feature",
  "properties": {
    "iso:country":"ES",
    "sg:address":"Calle de Francisco Bernal, 7",
    "sg:city":"Aljorra",
    "sg:orig_category":"Molduras, Junquillos, Listones Y Molduras Perforadas",
    "sg:phone":"+34 968 55 83 15",
    "sg:postcode":"30390",
    "sg:province":"Murcia",
    "wof:name":"Saura Soto Antonio",
    "wof:placetype":"venue"
},
  "geometry": {"coordinates":[-1.070538044,37.6914710999],"type":"Point"}
}