{
  "type": "Feature",
  "properties": {
    "iso:country":"ES",
    "sg:address":"Carr Sant Agusti, 32",
    "sg:city":"Girona",
    "sg:orig_category":"Formaci\u00d3n Continuada (variada)",
    "sg:phone":"+34 972 48 56 37",
    "sg:postcode":"17003",
    "sg:province":"Girona",
    "wof:name":"Institut Per Al Desenvolupament De La Formacio I L'ocupacio",
    "wof:placetype":"venue"
},
  "geometry": {"coordinates":[2.8209240437,41.9701271057],"type":"Point"}
}