{
  "type": "Feature",
  "properties": {
    "iso:country":"ES",
    "sg:address":"Calle de Cuba, 65",
    "sg:city":"Valencia",
    "sg:orig_category":"Confecci\u00d3n (fabricaci\u00d3n, Al Por Mayor)",
    "sg:phone":"+34 963 80 64 84",
    "sg:postcode":"46006",
    "sg:province":"Valencia",
    "wof:name":"Chen  Ehengyi",
    "wof:placetype":"venue"
},
  "geometry": {"coordinates":[-0.3750321865,39.4591560364],"type":"Point"}
}