{
  "type": "Feature",
  "properties": {
    "addr:full":"Ctra. De Alhama, S/n Churriana Vega Granada 18194",
    "addr:housenumber":"s / n",
    "addr:postcode":"18194",
    "addr:street":"Ctra. De Alhama",
    "iso:country":"ES",
    "sg:address":"Ctra. De Alhama, S/n",
    "sg:city":"Churriana Vega",
    "sg:orig_category":"Polideportivos",
    "sg:phone":"+34 958 57 05 51",
    "sg:postcode":"18194",
    "sg:province":"Granada",
    "wof:name":"Ayuntamiento De Churriana De La Vega",
    "wof:placetype":"venue"
},
  "geometry": {"coordinates":[-3.6383988857,37.1415786743],"type":"Point"}
}