{
  "type": "Feature",
  "properties": {
    "iso:country":"ES",
    "sg:address":"Calle de Adriano, 21",
    "sg:city":"Sevilla",
    "sg:orig_category":"Art\u00cdculos De Regalo (al Por Menor)",
    "sg:phone":"+34 954 22 75 74",
    "sg:postcode":"41001",
    "sg:province":"Sevilla",
    "wof:name":"Vazquez Garcia Juan Manuel",
    "wof:placetype":"venue"
},
  "geometry": {"coordinates":[-5.9979600906,37.3864898682],"type":"Point"}
}