{
  "type": "Feature",
  "properties": {
    "addr:full":"F. Hoya Sta. Ana, S/n Tobarra Albacete 02500",
    "addr:housenumber":"s / n",
    "addr:postcode":"02500",
    "addr:street":"F.;Sta. Ana",
    "iso:country":"ES",
    "sg:address":"F. Hoya Sta. Ana, S/n",
    "sg:city":"Tobarra",
    "sg:orig_category":"Producci\u00d3n, Venta De Productos De Agricultura Biol\u00d3gica",
    "sg:phone":"+34 967 58 80 54",
    "sg:postcode":"02500",
    "sg:province":"Albacete",
    "wof:name":"Roser Hoya S.a.",
    "wof:placetype":"venue"
},
  "geometry": {"coordinates":[-1.689489007,38.5949516296],"type":"Point"}
}