{
  "type": "Feature",
  "properties": {
    "iso:country":"ES",
    "sg:address":"Rua Antonio Palacios, 123",
    "sg:city":"Porri\u00f1o",
    "sg:orig_category":"Imprenta",
    "sg:phone":"+34 986 33 39 89",
    "sg:postcode":"36400",
    "sg:province":"Pontevedra",
    "wof:name":"A G Palacios S.l.",
    "wof:placetype":"venue"
},
  "geometry": {"coordinates":[-8.6137428284,42.1600494385],"type":"Point"}
}