{
  "type": "Feature",
  "properties": {
    "iso:country":"ES",
    "sg:address":"Calle de Burriana, 44",
    "sg:city":"Valencia",
    "sg:orig_category":"Plomeros",
    "sg:phone":"+34 963 74 16 38",
    "sg:postcode":"46005",
    "sg:province":"Valencia",
    "wof:name":"Navarro Linares Avelino",
    "wof:placetype":"venue"
},
  "geometry": {"coordinates":[-0.3640997112,39.4662017822],"type":"Point"}
}