{
  "type": "Feature",
  "properties": {
    "iso:country":"ES",
    "sg:address":"Calle de Moises De Leon, S/n",
    "sg:city":"Le\u00f3n",
    "sg:orig_category":"Ingeniero",
    "sg:phone":"+34 987 21 54 52",
    "sg:postcode":"24006",
    "sg:province":"Le\u00f3n",
    "wof:name":"Estudios Y Proyectos Desarrollo Y Gestion S.a.",
    "wof:placetype":"venue"
},
  "geometry": {"coordinates":[-5.5604667664,42.5924835205],"type":"Point"}
}