{
  "type": "Feature",
  "properties": {
    "addr:full":"Calle de Belmez (de), 8 Fuenlabrada Madrid 28946",
    "addr:housenumber":"8",
    "addr:postcode":"28946",
    "addr:street":"Calle De Belmez De",
    "iso:country":"ES",
    "sg:address":"Calle de Belmez (de), 8",
    "sg:city":"Fuenlabrada",
    "sg:orig_category":"Hornos Industriales",
    "sg:phone":"+34 916 15 48 02",
    "sg:postcode":"28946",
    "sg:province":"Madrid",
    "wof:name":"Ingenieria 2000 S. A.",
    "wof:placetype":"venue"
},
  "geometry": {"coordinates":[-3.7625422478,40.2804946899],"type":"Point"}
}