{
  "type": "Feature",
  "properties": {
    "addr:full":"Calle de San Pedro, 10 Olivenza Badajoz 06100",
    "addr:housenumber":"10",
    "addr:postcode":"06100",
    "addr:street":"Calle De San Pedro",
    "iso:country":"ES",
    "sg:address":"Calle de San Pedro, 10",
    "sg:city":"Olivenza",
    "sg:orig_category":"Traductores",
    "sg:phone":"+34 924 49 28 51",
    "sg:postcode":"06100",
    "sg:province":"Badajoz",
    "wof:name":"Ortiz Gomez Maria Concepcion",
    "wof:placetype":"venue"
},
  "geometry": {"coordinates":[-7.1024041176,38.6847190857],"type":"Point"}
}