{
  "type": "Feature",
  "properties": {
    "iso:country":"ES",
    "sg:address":"Camino Viejo De Rute, S/n",
    "sg:city":"Encinas Reales",
    "sg:orig_category":"Fabricaci\u00d3n De Peines Y De Accesorios De Peluquer\u00cda",
    "sg:phone":"+34 957 59 84 05",
    "sg:postcode":"14913",
    "sg:province":"C\u00f3rdoba",
    "wof:name":"A.r.cosmetic S.l.l.",
    "wof:placetype":"venue"
},
  "geometry": {"coordinates":[-4.4748258591,37.2823562622],"type":"Point"}
}