{
  "type": "Feature",
  "properties": {
    "iso:country":"ES",
    "sg:address":"Carr Progres, 34",
    "sg:city":"Badalona",
    "sg:orig_category":"Maquinaria Para Industrias Diversas",
    "sg:phone":"+34 933 84 12 14",
    "sg:postcode":"08912",
    "sg:province":"Barcelona",
    "wof:name":"19 Izquierda S.l.",
    "wof:placetype":"venue"
},
  "geometry": {"coordinates":[2.243864,41.444393],"type":"Point"}
}