{
  "type": "Feature",
  "properties": {
    "iso:country":"ES",
    "sg:address":"Carretera De Jerez-cartagena, Km. 0475,5",
    "sg:city":"Huetor-tajar",
    "sg:orig_category":"Material Y Herramientas Agr\u00cdcolas",
    "sg:phone":"+34 958 33 37 84",
    "sg:postcode":"18360",
    "sg:province":"Granada",
    "sg:website":"www.asigran.com",
    "wof:name":"Asigran S.l.",
    "wof:placetype":"venue"
},
  "geometry": {"coordinates":[-4.0388917923,37.1964759827],"type":"Point"}
}