{
  "type": "Feature",
  "properties": {
    "iso:country":"ES",
    "sg:address":"Ctra Carretera Nacional V, Km. 0253,0",
    "sg:city":"Trujillo",
    "sg:orig_category":"Comit\u00c9s De Organizaci\u00d3n De Exposiciones, Ferias, Salones",
    "sg:phone":"+34 927 32 14 54",
    "sg:postcode":"10200",
    "sg:province":"C\u00e1ceres",
    "wof:name":"Institucion Ferial Del Mercado De Ganados De Extremadura Feria De Muestras Agroganadera",
    "wof:placetype":"venue"
},
  "geometry": {"coordinates":[-5.9621105194,39.561050415],"type":"Point"}
}