{
  "type": "Feature",
  "properties": {
    "addr:full":"Avda Ruzafa, 4 Benidorm Alicante 03500",
    "addr:housenumber":"4",
    "addr:postcode":"03500",
    "addr:street":"Avda Ruzafa",
    "iso:country":"ES",
    "sg:address":"Avda Ruzafa, 4",
    "sg:city":"Benidorm",
    "sg:orig_category":"Cajas De Ahorro",
    "sg:phone":"+34 965 85 80 11",
    "sg:postcode":"03500",
    "sg:province":"Alicante",
    "wof:name":"Caja De Ahorros De Valencia Castellon Y Alicante",
    "wof:placetype":"venue"
},
  "geometry": {"coordinates":[-0.1743289977,38.5408058167],"type":"Point"}
}