{
  "type": "Feature",
  "properties": {
    "iso:country":"ES",
    "sg:address":"Calle de Marco Aurelio, S/n",
    "sg:city":"Torreciega",
    "sg:orig_category":"Producci\u00d3n, Comercio De Cereales",
    "sg:phone":"+34 968 12 16 17",
    "sg:postcode":"30392",
    "sg:province":"Murcia",
    "wof:name":"Viuda E Hijos De Francisco Vera S.l.",
    "wof:placetype":"venue"
},
  "geometry": {"coordinates":[-0.9686157107,37.614616394],"type":"Point"}
}