{
  "type": "Feature",
  "properties": {
    "addr:full":"Calle de Cabecillo De Martin Sanchez, 2 Valverde Camino Huelva 21600",
    "addr:housenumber":"2",
    "addr:postcode":"21600",
    "addr:street":"Calle De Cabecillo De Martin Sanchez;Camino Huelva",
    "iso:country":"ES",
    "sg:address":"Calle de Cabecillo De Martin Sanchez, 2",
    "sg:city":"Valverde Camino",
    "sg:orig_category":"Asociaciones Y Clubs Deportivos",
    "sg:phone":"+34 959 55 39 42",
    "sg:postcode":"21600",
    "sg:province":"Huelva",
    "wof:name":"Sociedad Olimpica Valverde\u00f1a",
    "wof:placetype":"venue"
},
  "geometry": {"coordinates":[-6.7531261444,37.572227478],"type":"Point"}
}