{
  "type": "Feature",
  "properties": {
    "iso:country":"ES",
    "sg:address":"Carrer de Jaume Cuyas, 23",
    "sg:city":"Santa Agnes De Malanyanes",
    "sg:orig_category":"Reposter\u00cdas",
    "sg:phone":"+34 938 42 00 24",
    "sg:postcode":"08430",
    "sg:province":"Barcelona",
    "wof:name":"Fleca Rovira S.l.",
    "wof:placetype":"venue"
},
  "geometry": {"coordinates":[2.3505220413,41.6032485962],"type":"Point"}
}