{
  "type": "Feature",
  "properties": {
    "addr:full":"Calle de Alfonso V, 4 Le\u00f3n Le\u00f3n 24001",
    "addr:housenumber":"4",
    "addr:postcode":"24001",
    "addr:street":"Calle De Alfonso V;Leo\u0301N",
    "iso:country":"ES",
    "sg:address":"Calle de Alfonso V, 4",
    "sg:city":"Le\u00f3n",
    "sg:orig_category":"M\u00c9dicos: Estomatolog\u00cda",
    "sg:phone":"+34 987 22 17 59",
    "sg:postcode":"24001",
    "sg:province":"Le\u00f3n",
    "wof:name":"Gonzalez Maudes Maria Victoria",
    "wof:placetype":"venue"
},
  "geometry": {"coordinates":[-5.5741009712,42.5980224609],"type":"Point"}
}