{
  "type": "Feature",
  "properties": {
    "addr:full":"Campo De Pazos, 9 Rianxo La Coru\u00f1a 15920",
    "addr:housenumber":"9",
    "addr:postcode":"15920",
    "addr:street":"De Pazos;La Corun\u0303A",
    "iso:country":"ES",
    "sg:address":"Campo De Pazos, 9",
    "sg:city":"Rianxo",
    "sg:orig_category":"Estancos",
    "sg:phone":"+34 981 86 12 06",
    "sg:postcode":"15920",
    "sg:province":"La Coru\u00f1a",
    "wof:name":"Ces Pi\u00f1eiro Angel",
    "wof:placetype":"venue"
},
  "geometry": {"coordinates":[-8.8172187805,42.6528091431],"type":"Point"}
}