{
  "type": "Feature",
  "properties": {
    "iso:country":"ES",
    "sg:address":"Calle de Benavites, 3",
    "sg:city":"Sagunt",
    "sg:orig_category":"Ense\u00d1anza: Idiomas",
    "sg:phone":"+34 962 65 11 08",
    "sg:postcode":"46500",
    "sg:province":"Valencia",
    "wof:name":"Carde\u00f1osa Fernandez Sara",
    "wof:placetype":"venue"
},
  "geometry": {"coordinates":[-0.2799282968,39.6824073792],"type":"Point"}
}