{
  "type": "Feature",
  "properties": {
    "iso:country":"ES",
    "sg:address":"Carrer de Viladordis, 33",
    "sg:city":"Manresa",
    "sg:orig_category":"Herboristas (al Por Menor)",
    "sg:phone":"+34 938 74 33 24",
    "sg:postcode":"08241",
    "sg:province":"Barcelona",
    "wof:name":"Subirats Fernandez Joaquina",
    "wof:placetype":"venue"
},
  "geometry": {"coordinates":[1.8359450102,41.7256317139],"type":"Point"}
}