{
  "type": "Feature",
  "properties": {
    "addr:full":"Partida Serres, S/n Serres Tarragona 43392",
    "addr:housenumber":"s / n",
    "addr:postcode":"43392",
    "addr:street":"Partida Serres",
    "iso:country":"ES",
    "sg:address":"Partida Serres, S/n",
    "sg:city":"Serres",
    "sg:orig_category":"Arquitectos",
    "sg:phone":"+34 977 85 53 21",
    "sg:postcode":"43392",
    "sg:province":"Tarragona",
    "wof:name":"Vilafranca Pijoan Joaquim",
    "wof:placetype":"venue"
},
  "geometry": {"coordinates":[1.0993720293,41.1803131104],"type":"Point"}
}