{
  "type": "Feature",
  "properties": {
    "iso:country":"ES",
    "sg:address":"Urb Universitaria, S/n",
    "sg:city":"Badajoz",
    "sg:orig_category":"Doctores En Medicina",
    "sg:phone":"+34 924 27 24 57",
    "sg:postcode":"06007",
    "sg:province":"Badajoz",
    "wof:name":"Ravelo Chavez Leocadio",
    "wof:placetype":"venue"
},
  "geometry": {"coordinates":[-6.8165788651,38.9051589966],"type":"Point"}
}