{
  "type": "Feature",
  "properties": {
    "iso:country":"ES",
    "sg:address":"Disseminats, S/n",
    "sg:city":"Begues",
    "sg:orig_category":"Empresas De Electricidad En General",
    "sg:phone":"+34 936 39 08 21",
    "sg:postcode":"08859",
    "sg:province":"Barcelona",
    "wof:name":"Red Electrica De Espa\u00f1a S.a.",
    "wof:placetype":"venue"
},
  "geometry": {"coordinates":[1.924265027,41.3304252625],"type":"Point"}
}