{
  "type": "Feature",
  "properties": {
    "addr:full":"Carr Carles Sarthou Carreres, 10 Las Villas Castell\u00f3n 12560",
    "addr:housenumber":"10",
    "addr:postcode":"12560",
    "addr:street":"Carr Carles Sarthou Carreres;Castello\u0301N",
    "iso:country":"ES",
    "sg:address":"Carr Carles Sarthou Carreres, 10",
    "sg:city":"Las Villas",
    "sg:orig_category":"Contenedores (mercanc\u00cdas)",
    "sg:phone":"+34 964 30 23 72",
    "sg:postcode":"12560",
    "sg:province":"Castell\u00f3n",
    "wof:name":"Camy Logistic S.l.",
    "wof:placetype":"venue"
},
  "geometry": {"coordinates":[0.0590550005,40.0523414612],"type":"Point"}
}