{
  "type": "Feature",
  "properties": {
    "addr:full":"Calle de Mediterraneo, 3 S. Pedro Pinatar Murcia 30740",
    "addr:housenumber":"3",
    "addr:postcode":"30740",
    "addr:street":"Calle De Mediterraneo",
    "iso:country":"ES",
    "sg:address":"Calle de Mediterraneo, 3",
    "sg:city":"S. Pedro Pinatar",
    "sg:orig_category":"Asesor\u00cda Sobre Comunicaci\u00d3n De Empresas",
    "sg:phone":"+34 968 18 32 26",
    "sg:postcode":"30740",
    "sg:province":"Murcia",
    "wof:name":"Javier Valerdi Y Asociados S.l.",
    "wof:placetype":"venue"
},
  "geometry": {"coordinates":[-0.7905970216,37.8359527588],"type":"Point"}
}