{
  "type": "Feature",
  "properties": {
    "addr:full":"Calle de Collado Mediano, 26 Rozas De Madrid Madrid 28230",
    "addr:housenumber":"26",
    "addr:postcode":"28230",
    "addr:street":"Calle De Collado Mediano",
    "iso:country":"ES",
    "sg:address":"Calle de Collado Mediano, 26",
    "sg:city":"Rozas De Madrid",
    "sg:orig_category":"Inform\u00c1tica Equipo Y Programas (al Por Mayor)",
    "sg:phone":"+34 916 36 30 13",
    "sg:postcode":"28230",
    "sg:province":"Madrid",
    "sg:website":"www.atril.com",
    "wof:name":"Atril Adevelopement S.l.",
    "wof:placetype":"venue"
},
  "geometry": {"coordinates":[-3.8740949631,40.4983100891],"type":"Point"}
}