{
  "type": "Feature",
  "properties": {
    "iso:country":"ES",
    "sg:address":"Calle de Nuestra S\u00d1ra La Asuncion, 27",
    "sg:city":"Vall D'uixo",
    "sg:orig_category":"Peluquer\u00cdas, Peluquer\u00cda Mixta",
    "sg:phone":"+34 964 66 22 27",
    "sg:postcode":"12600",
    "sg:province":"Castell\u00f3n",
    "wof:name":"Sanchez Amador Maria Jose",
    "wof:placetype":"venue"
},
  "geometry": {"coordinates":[-0.0432699993,39.9984931946],"type":"Point"}
}