{
  "type": "Feature",
  "properties": {
    "iso:country":"ES",
    "sg:address":"Carrer de Rossello, 85",
    "sg:city":"Barcelona",
    "sg:orig_category":"Peluquer\u00cdas, Peluquer\u00cda Mixta",
    "sg:phone":"+34 934 10 97 34",
    "sg:postcode":"08029",
    "sg:province":"Barcelona",
    "wof:name":"Limon Mogena Isabel",
    "wof:placetype":"venue"
},
  "geometry": {"coordinates":[2.1473710537,41.3859901428],"type":"Point"}
}