{
  "type": "Feature",
  "properties": {
    "iso:country":"ES",
    "sg:address":"Carrer de Mirador Del Romani (del), 23",
    "sg:city":"Bonanova",
    "sg:orig_category":"Inmobiliaria (agencias)",
    "sg:phone":"+34 977 69 03 72",
    "sg:postcode":"43820",
    "sg:province":"Tarragona",
    "wof:name":"Patrimonios Del Vendrell 2000 S.l.",
    "wof:placetype":"venue"
},
  "geometry": {"coordinates":[1.5684100389,41.1977844238],"type":"Point"}
}