{
  "type": "Feature",
  "properties": {
    "addr:full":"Avda 2 De Mayo, 7 Mocejon Toledo 45270",
    "addr:housenumber":"7",
    "addr:postcode":"45270",
    "addr:street":"Avda 2 De Mayo",
    "iso:country":"ES",
    "sg:address":"Avda 2 De Mayo, 7",
    "sg:city":"Mocejon",
    "sg:orig_category":"Panader\u00cdas, Panader\u00cdas",
    "sg:phone":"+34 925 36 00 36",
    "sg:postcode":"45270",
    "sg:province":"Toledo",
    "wof:name":"Calvo Redondo Juan Antonio",
    "wof:placetype":"venue"
},
  "geometry": {"coordinates":[-3.9195990562,39.937046051],"type":"Point"}
}