{
  "type": "Feature",
  "properties": {
    "iso:country":"ES",
    "sg:address":"Rua Antonio Puga, 60",
    "sg:city":"Ourense",
    "sg:orig_category":"Alimentaci\u00d3n General (al Por Menor)",
    "sg:phone":"+34 988 24 03 37",
    "sg:postcode":"32002",
    "sg:province":"Ourense",
    "wof:name":"Gali\u00f1a Ferreiro Benito",
    "wof:placetype":"venue"
},
  "geometry": {"coordinates":[-7.8700051308,42.3424491882],"type":"Point"}
}