{
  "type": "Feature",
  "properties": {
    "iso:country":"ES",
    "sg:address":"Avgd Palmar, 9",
    "sg:city":"Silla",
    "sg:orig_category":"Gr\u00daas, Montacargas Y Elevadores Para Astilleros",
    "sg:phone":"+34 963 55 95 10",
    "sg:postcode":"46460",
    "sg:province":"Valencia",
    "wof:name":"Sistemas De Elevacion S.l.",
    "wof:placetype":"venue"
},
  "geometry": {"coordinates":[-0.4077430069,39.3706893921],"type":"Point"}
}