{
  "type": "Feature",
  "properties": {
    "addr:full":"Calle de Gabriel Ciscar, 24 Albacete Albacete 02005",
    "addr:housenumber":"24",
    "addr:postcode":"02005",
    "addr:street":"Calle De Gabriel Ciscar",
    "iso:country":"ES",
    "sg:address":"Calle de Gabriel Ciscar, 24",
    "sg:city":"Albacete",
    "sg:orig_category":"Bricolaje, Herramientas (al Por Menor)",
    "sg:phone":"+34 967 21 13 75",
    "sg:postcode":"02005",
    "sg:province":"Albacete",
    "wof:name":"Gama Decoracion Y Pinturas S. L.",
    "wof:placetype":"venue"
},
  "geometry": {"coordinates":[-1.8617538214,39.0020904541],"type":"Point"}
}