{
  "type": "Feature",
  "properties": {
    "iso:country":"ES",
    "sg:address":"Castillo, S/n",
    "sg:city":"Yecla",
    "sg:orig_category":"Museos",
    "sg:phone":"+34 968 43 51 66",
    "sg:postcode":"30510",
    "sg:province":"Murcia",
    "wof:name":"Ayuntamiento De Yecla",
    "wof:placetype":"venue"
},
  "geometry": {"coordinates":[-1.1188089848,38.6124267578],"type":"Point"}
}