{
  "type": "Feature",
  "properties": {
    "iso:country":"ES",
    "sg:address":"Calle de Juan Xxiii, 14",
    "sg:city":"Cristianos",
    "sg:orig_category":"\u00d3ptica: Instrumentos (fabricaci\u00d3n)",
    "sg:phone":"+34 922 79 06 68",
    "sg:postcode":"38650",
    "sg:province":"Santa Cruz De Tenerife",
    "wof:name":"Optica San Isidro S. L.",
    "wof:placetype":"venue"
},
  "geometry": {"coordinates":[-16.7182636261,28.051815033],"type":"Point"}
}