{
  "type": "Feature",
  "properties": {
    "iso:country":"ES",
    "sg:address":"Lonja De Pescado, S/n",
    "sg:city":"Benicarlo",
    "sg:orig_category":"Restaurantes",
    "sg:phone":"+34 964 46 10 99",
    "sg:postcode":"12580",
    "sg:province":"Castell\u00f3n",
    "wof:name":"Catamaran Port Blo Sl",
    "wof:placetype":"venue"
},
  "geometry": {"coordinates":[0.4042100012,40.4457893372],"type":"Point"}
}