{
  "type": "Feature",
  "properties": {
    "iso:country":"ES",
    "sg:address":"Calle de Plaza (la), 3",
    "sg:city":"Villamalea",
    "sg:orig_category":"\u00d3ptica: Instrumentos (fabricaci\u00d3n)",
    "sg:phone":"+34 967 48 39 79",
    "sg:postcode":"02270",
    "sg:province":"Albacete",
    "wof:name":"Monsalvez Ruiz Alicia",
    "wof:placetype":"venue"
},
  "geometry": {"coordinates":[-1.5969090462,39.364200592],"type":"Point"}
}