{
  "type": "Feature",
  "properties": {
    "iso:country":"ES",
    "sg:address":"Carrer de Sant Domingo, 4",
    "sg:city":"Palma",
    "sg:orig_category":"Marroquiner\u00cda (confecci\u00d3n)",
    "sg:phone":"+34 971 72 42 62",
    "sg:postcode":"07001",
    "sg:province":"Islas Baleares",
    "wof:name":"Fuster Palmer Pedro",
    "wof:placetype":"venue"
},
  "geometry": {"coordinates":[2.6494309902,39.5698318481],"type":"Point"}
}