{
  "type": "Feature",
  "properties": {
    "iso:country":"ES",
    "sg:address":"Carrer de Mare De Deu Del Pilar, 111",
    "sg:city":"Mutxamel",
    "sg:orig_category":"Zapater\u00cdas",
    "sg:phone":"+34 965 95 11 46",
    "sg:postcode":"03110",
    "sg:province":"Alicante",
    "wof:name":"Herraez Cosculluela Porfiria Teresa",
    "wof:placetype":"venue"
},
  "geometry": {"coordinates":[-0.4423890114,38.4128608704],"type":"Point"}
}