{
  "type": "Feature",
  "properties": {
    "iso:country":"ES",
    "sg:address":"Calle de Mostoles (de), 16",
    "sg:city":"Fuenlabrada",
    "sg:orig_category":"Agencias Y Agentes Comerciales, Representantes",
    "sg:phone":"+34 916 09 91 96",
    "sg:postcode":"28945",
    "sg:province":"Madrid",
    "wof:name":"Hernandez Diaz Baltasar",
    "wof:placetype":"venue"
},
  "geometry": {"coordinates":[-3.7970030308,40.2844581604],"type":"Point"}
}