{
  "type": "Feature",
  "properties": {
    "addr:full":"Plaz Poeta Llorente, 1 Pobla Vallbona Valencia 46185",
    "addr:housenumber":"1",
    "addr:postcode":"46185",
    "addr:street":"Plaz;Llorente",
    "iso:country":"ES",
    "sg:address":"Plaz Poeta Llorente, 1",
    "sg:city":"Pobla Vallbona",
    "sg:orig_category":"Promotores Constructores",
    "sg:phone":"+34 961 66 16 97",
    "sg:postcode":"46185",
    "sg:province":"Valencia",
    "wof:name":"Bastiment Y Arquitectura S.l.",
    "wof:placetype":"venue"
},
  "geometry": {"coordinates":[-0.5541440248,39.5929985046],"type":"Point"}
}