{
  "type": "Feature",
  "properties": {
    "iso:country":"ES",
    "sg:address":"Calle de Aladino, 9",
    "sg:city":"Torremolinos",
    "sg:orig_category":"Centros Comerciales Y Grandes Tiendas",
    "sg:phone":"+34 952 38 60 71",
    "sg:postcode":"29620",
    "sg:province":"M\u00e1laga",
    "wof:name":"Baena Romero Maria Teresa",
    "wof:placetype":"venue"
},
  "geometry": {"coordinates":[-4.504283905,36.6097183228],"type":"Point"}
}