{
  "type": "Feature",
  "properties": {
    "addr:full":"Calle de Tudela, 6 Alfaro La Rioja 26540",
    "addr:housenumber":"6",
    "addr:postcode":"26540",
    "addr:street":"Calle De Tudela;Rioja",
    "iso:country":"ES",
    "sg:address":"Calle de Tudela, 6",
    "sg:city":"Alfaro",
    "sg:orig_category":"Pintura Y Barniz (al Por Menor)",
    "sg:phone":"+34 941 18 08 03",
    "sg:postcode":"26540",
    "sg:province":"La Rioja",
    "wof:name":"Martinez Sainz Presentacion",
    "wof:placetype":"venue"
},
  "geometry": {"coordinates":[-1.7500859499,42.1747589111],"type":"Point"}
}