{
  "type": "Feature",
  "properties": {
    "addr:full":"Avda Alcoy, 3 Agost Alicante 03698",
    "addr:housenumber":"3",
    "addr:postcode":"03698",
    "addr:street":"Avda Alcoy",
    "iso:country":"ES",
    "sg:address":"Avda Alcoy, 3",
    "sg:city":"Agost",
    "sg:orig_category":"Delegados, Agentes De Tr\u00c1nsito, Auxiliares De Transporte Internacional",
    "sg:phone":"+34 965 69 13 11",
    "sg:postcode":"03698",
    "sg:province":"Alicante",
    "wof:name":"Garcia Martinez Fernando",
    "wof:placetype":"venue"
},
  "geometry": {"coordinates":[-0.6362069845,38.4391212463],"type":"Point"}
}