{
  "type": "Feature",
  "properties": {
    "iso:country":"ES",
    "sg:address":"Calle de Cardenal Mendoza, 51",
    "sg:city":"Madrid",
    "sg:orig_category":"Tintorer\u00cdas, Limpieza En Seco",
    "sg:phone":"+34 914 64 46 60",
    "sg:postcode":"28011",
    "sg:province":"Madrid",
    "wof:name":"Fernandez Villar Teresa",
    "wof:placetype":"venue"
},
  "geometry": {"coordinates":[-3.729735136,40.4115753174],"type":"Point"}
}