{
  "type": "Feature",
  "properties": {
    "iso:country":"ES",
    "sg:address":"Extramuros, S/n",
    "sg:city":"Siruela",
    "sg:orig_category":"Sanatorios M\u00c9dico",
    "sg:phone":"+34 924 62 66 07",
    "sg:postcode":"06650",
    "sg:province":"Badajoz",
    "wof:name":"Servicio Extreme\u00d1o De Salud",
    "wof:placetype":"venue"
},
  "geometry": {"coordinates":[-5.0529341698,38.979724884],"type":"Point"}
}