{
  "type": "Feature",
  "properties": {
    "addr:full":"Calle de Blas Cabrera, 9 Alcala Henares Madrid 28806",
    "addr:housenumber":"9",
    "addr:postcode":"28806",
    "addr:street":"Calle De Blas Cabrera",
    "iso:country":"ES",
    "sg:address":"Calle de Blas Cabrera, 9",
    "sg:city":"Alcala Henares",
    "sg:orig_category":"Centros Empresariales",
    "sg:phone":"+34 918 77 19 60",
    "sg:postcode":"28806",
    "sg:province":"Madrid",
    "wof:name":"Flection Spain S. L.",
    "wof:placetype":"venue"
},
  "geometry": {"coordinates":[-3.4046757221,40.4934806824],"type":"Point"}
}