{
  "type": "Feature",
  "properties": {
    "iso:country":"ES",
    "sg:address":"Calle de Conde, 83",
    "sg:city":"Baiona",
    "sg:orig_category":"Peluquer\u00cdas, Peluquer\u00cda Mixta",
    "sg:phone":"+34 986 35 82 19",
    "sg:postcode":"36300",
    "sg:province":"Pontevedra",
    "wof:name":"Estevez Alvarez Maria Jose",
    "wof:placetype":"venue"
},
  "geometry": {"coordinates":[-8.8485651016,42.1186981201],"type":"Point"}
}