{
  "type": "Feature",
  "properties": {
    "addr:full":"Calle de Jesus Del Valle, 31 Madrid Madrid 28004",
    "addr:housenumber":"31",
    "addr:postcode":"madrid;28004",
    "addr:street":"Calle De Jesus Del Valle",
    "iso:country":"ES",
    "sg:address":"Calle de Jesus Del Valle, 31",
    "sg:city":"Madrid",
    "sg:orig_category":"Periodistas Profesionales",
    "sg:phone":"+34 915 24 07 68",
    "sg:postcode":"28004",
    "sg:province":"Madrid",
    "wof:name":"Saez Garcia Sara",
    "wof:placetype":"venue"
},
  "geometry": {"coordinates":[-3.7034060955,40.4252052307],"type":"Point"}
}