{
  "type": "Feature",
  "properties": {
    "iso:country":"ES",
    "sg:address":"Calle de Alcala, 187",
    "sg:city":"Madrid",
    "sg:orig_category":"M\u00c9dicos: An\u00c1lisis Cl\u00cdnicos",
    "sg:phone":"+34 914 01 15 84",
    "sg:postcode":"28009",
    "sg:province":"Madrid",
    "wof:name":"Martin Tranque Juan Antonio",
    "wof:placetype":"venue"
},
  "geometry": {"coordinates":[-3.67029953,40.4273681641],"type":"Point"}
}