{
  "type": "Feature",
  "properties": {
    "addr:full":"Real, 63 Mestanza Ciudad Real 13592",
    "addr:housenumber":"63",
    "addr:postcode":"13592",
    "addr:street":"Real",
    "iso:country":"ES",
    "sg:address":"Real, 63",
    "sg:city":"Mestanza",
    "sg:orig_category":"Agricultura: Abastecimiento Y Cosechado (negocio)",
    "sg:phone":"+34 926 48 55 09",
    "sg:postcode":"13592",
    "sg:province":"Ciudad Real",
    "wof:name":"Ca\u00f1icor S.l.",
    "wof:placetype":"venue"
},
  "geometry": {"coordinates":[-4.0687661171,38.5763511658],"type":"Point"}
}