{
  "type": "Feature",
  "properties": {
    "iso:country":"ES",
    "sg:address":"Calle de Albareda, 84",
    "sg:city":"Palmas De Gran Canaria",
    "sg:orig_category":"Ropa Para Se\u00d1oras Y Caballeros (al Por Menor)",
    "sg:phone":"+34 928 46 65 22",
    "sg:postcode":"35008",
    "sg:province":"Las Palmas",
    "wof:name":"Padron Gonzalez Antonio",
    "wof:placetype":"venue"
},
  "geometry": {"coordinates":[-15.4291000366,28.1484680176],"type":"Point"}
}