{
  "type": "Feature",
  "properties": {
    "iso:country":"ES",
    "sg:address":"Avda Balsicas (de), 16",
    "sg:city":"San Javier",
    "sg:orig_category":"Imprenta",
    "sg:phone":"+34 968 19 12 45",
    "sg:postcode":"30730",
    "sg:province":"Murcia",
    "wof:name":"Gomez Gomez Jose",
    "wof:placetype":"venue"
},
  "geometry": {"coordinates":[-0.8377289772,37.8054389954],"type":"Point"}
}