{
  "type": "Feature",
  "properties": {
    "iso:country":"ES",
    "sg:address":"Calle de Ca\u00d1o De Las Pimientas, 24",
    "sg:city":"Poligono Industrial Los Villares",
    "sg:orig_category":"Construcciones Met\u00c1licas",
    "sg:phone":"+34 923 20 40 55",
    "sg:postcode":"37184",
    "sg:province":"Salamanca",
    "wof:name":"Industrias Mingo S.l.",
    "wof:placetype":"venue"
},
  "geometry": {"coordinates":[-5.6476120949,41.0065116882],"type":"Point"}
}