{
  "type": "Feature",
  "properties": {
    "addr:full":"Calle de Santa Eulalia, 17 Santa Olalla Del Cala Huelva 21260",
    "addr:housenumber":"17",
    "addr:postcode":"21260",
    "addr:street":"Calle De Santa Eulalia",
    "iso:country":"ES",
    "sg:address":"Calle de Santa Eulalia, 17",
    "sg:city":"Santa Olalla Del Cala",
    "sg:orig_category":"Promotores Constructores",
    "sg:phone":"+34 959 19 06 09",
    "sg:postcode":"21260",
    "sg:province":"Huelva",
    "wof:name":"Fuentes Pelayo Manuel",
    "wof:placetype":"venue"
},
  "geometry": {"coordinates":[-6.2234377861,37.9061431885],"type":"Point"}
}