{
  "type": "Feature",
  "properties": {
    "addr:full":"Ctra. Almeria, S/n Ugijar Granada 18480",
    "addr:housenumber":"s",
    "addr:postcode":"18480",
    "addr:street":"Ctra. Almeria;/ N Ugijar",
    "iso:country":"ES",
    "sg:address":"Ctra. Almeria, S/n",
    "sg:city":"Ugijar",
    "sg:orig_category":"Agentes, Concesionarios Y Sucursales De Camiones Y Veh\u00cdculos Industriales",
    "sg:phone":"+34 958 76 71 08",
    "sg:postcode":"18480",
    "sg:province":"Granada",
    "wof:name":"La Alpujarra Craburantes Y Lubricantes S.l.",
    "wof:placetype":"venue"
},
  "geometry": {"coordinates":[-3.0517139435,36.9622535706],"type":"Point"}
}