{
  "type": "Feature",
  "properties": {
    "addr:full":"Calle de Camarena, 108 Madrid Madrid 28047",
    "addr:housenumber":"108",
    "addr:postcode":"28047",
    "addr:street":"Calle De Camarena",
    "iso:country":"ES",
    "sg:address":"Calle de Camarena, 108",
    "sg:city":"Madrid",
    "sg:orig_category":"Bisuter\u00cda, Joyer\u00cda, Relojer\u00cda (al Por Menor)",
    "sg:phone":"+34 917 17 58 56",
    "sg:postcode":"28047",
    "sg:province":"Madrid",
    "wof:name":"Jardin Diaz Jose",
    "wof:placetype":"venue"
},
  "geometry": {"coordinates":[-3.7572746277,40.3924102783],"type":"Point"}
}