{
  "type": "Feature",
  "properties": {
    "iso:country":"ES",
    "sg:address":"Calle de Aurrekoetxea, 22",
    "sg:city":"Bermeo",
    "sg:orig_category":"Institutos De Belleza",
    "sg:phone":"+34 946 18 78 68",
    "sg:postcode":"48370",
    "sg:province":"Vizcaya",
    "sg:website":"www.euskalnet.net-xiratx",
    "wof:name":"Iratxe Bilbao Telletxea",
    "wof:placetype":"venue"
},
  "geometry": {"coordinates":[-2.7217042446,43.4209480286],"type":"Point"}
}