{
  "type": "Feature",
  "properties": {
    "iso:country":"ES",
    "sg:address":"Carr Puigmal, 4",
    "sg:city":"Hostalric",
    "sg:orig_category":"Reposter\u00cdas",
    "sg:phone":"+34 972 86 50 30",
    "sg:postcode":"17450",
    "sg:province":"Girona",
    "wof:name":"Pa Artesanal Josep I Merce S.l.",
    "wof:placetype":"venue"
},
  "geometry": {"coordinates":[2.6256630421,41.743396759],"type":"Point"}
}