{
  "type": "Feature",
  "properties": {
    "iso:country":"ES",
    "sg:address":"Cno. Pescadores, S/n",
    "sg:city":"El Bosque",
    "sg:orig_category":"Estudios Y Construcci\u00d3n De Acuarios Y Viveros",
    "sg:phone":"+34 956 72 70 51",
    "sg:postcode":"11670",
    "sg:province":"C\u00e1diz",
    "wof:name":"Piscifactoria Y Coto Truchero El Bosque",
    "wof:placetype":"venue"
},
  "geometry": {"coordinates":[-5.5029292107,36.7614250183],"type":"Point"}
}