{
  "type": "Feature",
  "properties": {
    "iso:country":"ES",
    "sg:address":"Calle de Hernando De Perona, 13",
    "sg:city":"Roda",
    "sg:orig_category":"Trabajos De Aislamiento T\u00c9rmico Y Ac\u00dastico",
    "sg:phone":"+34 967 44 00 81",
    "sg:postcode":"02630",
    "sg:province":"Albacete",
    "wof:name":"Minaya Lopez Pedro Antonio",
    "wof:placetype":"venue"
},
  "geometry": {"coordinates":[-2.1572859287,39.2046203613],"type":"Point"}
}