{
  "type": "Feature",
  "properties": {
    "iso:country":"ES",
    "sg:address":"Calle de Real, 11",
    "sg:city":"Almeria",
    "sg:orig_category":"Papel Pintado (al Por Menor)",
    "sg:phone":"+34 950 23 12 72",
    "sg:postcode":"04003",
    "sg:province":"Almer\u00eda",
    "wof:name":"Contreras Barranco Teresa",
    "wof:placetype":"venue"
},
  "geometry": {"coordinates":[-2.4658880234,36.8401565552],"type":"Point"}
}