{
  "type": "Feature",
  "properties": {
    "iso:country":"ES",
    "sg:address":"Alam San Mames, 28",
    "sg:city":"Bilbao",
    "sg:orig_category":"Comercio De Mobiliario De Oficina",
    "sg:phone":"+34 944 21 02 57",
    "sg:postcode":"48010",
    "sg:province":"Vizcaya",
    "wof:name":"Epo S. A.",
    "wof:placetype":"venue"
},
  "geometry": {"coordinates":[-2.937128067,43.2590332031],"type":"Point"}
}