{
  "type": "Feature",
  "properties": {
    "addr:full":"Carrer de Castellsapera, 81 Terrassa Barcelona 08227",
    "addr:housenumber":"81",
    "addr:postcode":"08227",
    "addr:street":"Carrer De Castellsapera",
    "iso:country":"ES",
    "sg:address":"Carrer de Castellsapera, 81",
    "sg:city":"Terrassa",
    "sg:orig_category":"Molduras, Junquillos, Listones Y Molduras Perforadas",
    "sg:phone":"+34 937 85 21 65",
    "sg:postcode":"08227",
    "sg:province":"Barcelona",
    "wof:name":"Castillo Galindo Antonio",
    "wof:placetype":"venue"
},
  "geometry": {"coordinates":[2.0317080021,41.5768470764],"type":"Point"}
}