{
  "type": "Feature",
  "properties": {
    "addr:full":"Avda Comuneros, 17 Salamanca Salamanca 37003",
    "addr:housenumber":"17",
    "addr:postcode":"37003",
    "addr:street":"Avda Comuneros",
    "iso:country":"ES",
    "sg:address":"Avda Comuneros, 17",
    "sg:city":"Salamanca",
    "sg:orig_category":"Producci\u00d3n, Venta De Productos De Agricultura Biol\u00d3gica",
    "sg:phone":"+34 923 24 20 23",
    "sg:postcode":"37003",
    "sg:province":"Salamanca",
    "wof:name":"Sat Cava",
    "wof:placetype":"venue"
},
  "geometry": {"coordinates":[-5.655974865,40.9687652588],"type":"Point"}
}