{
  "type": "Feature",
  "properties": {
    "iso:country":"ES",
    "sg:address":"Rua Quintana, S/n",
    "sg:city":"Quintans",
    "sg:orig_category":"Centros De Educaci\u00d3n Especial",
    "sg:phone":"+34 986 50 27 82",
    "sg:postcode":"36619",
    "sg:province":"Pontevedra",
    "wof:name":"Colexio Publico Casanova",
    "wof:placetype":"venue"
},
  "geometry": {"coordinates":[-8.7645044327,42.5797958374],"type":"Point"}
}