{
  "type": "Feature",
  "properties": {
    "addr:full":"Urb San Francisco, 3 Caceres C\u00e1ceres 10003",
    "addr:housenumber":"3",
    "addr:postcode":"10003",
    "addr:street":"San Francisco;Ca\u0301Ceres",
    "iso:country":"ES",
    "sg:address":"Urb San Francisco, 3",
    "sg:city":"Caceres",
    "sg:orig_category":"Veh\u00cdculos De Ocasi\u00d3n",
    "sg:phone":"+34 927 21 10 18",
    "sg:postcode":"10003",
    "sg:province":"C\u00e1ceres",
    "wof:name":"Juan Ojalvo E Hijos",
    "wof:placetype":"venue"
},
  "geometry": {"coordinates":[-6.3706297874,39.4702606201],"type":"Point"}
}