{
  "type": "Feature",
  "properties": {
    "addr:full":"Calle de San Agustin, 6 Antequera M\u00e1laga 29200",
    "addr:housenumber":"6",
    "addr:postcode":"29200",
    "addr:street":"Calle De San Agustin",
    "iso:country":"ES",
    "sg:address":"Calle de San Agustin, 6",
    "sg:city":"Antequera",
    "sg:classifiers":[
        {
            "category":"Communications",
            "type":"Services"
        }
    ],
    "sg:phone":"+34 952 70 26 26",
    "sg:postcode":"29200",
    "sg:province":"M\u00e1laga",
    "sg:tags":[
        "televisiones",
        "y",
        "radio"
    ],
    "wof:name":"Uniprex-onda Cero",
    "wof:placetype":"venue"
},
  "geometry": {"coordinates":[-4.5609321594,37.0169754028],"type":"Point"}
}