{
  "type": "Feature",
  "properties": {
    "addr:full":"Iglesias, S/n Jumilla Murcia 30520",
    "addr:housenumber":"/ n",
    "addr:postcode":"30520",
    "addr:street":"Iglesias S",
    "iso:country":"ES",
    "sg:address":"Iglesias, S/n",
    "sg:city":"Jumilla",
    "sg:orig_category":"Productores Recolectores, Venta Directa De Vinos",
    "sg:phone":"+34 968 78 01 00",
    "sg:postcode":"30520",
    "sg:province":"Murcia",
    "wof:name":"Bodegas Martinez Herrero S.a.",
    "wof:placetype":"venue"
},
  "geometry": {"coordinates":[-1.32249403,38.4786148071],"type":"Point"}
}