{
  "type": "Feature",
  "properties": {
    "iso:country":"ES",
    "sg:address":"Carr Llitera, 10",
    "sg:city":"Lleida",
    "sg:orig_category":"Molduras, Junquillos, Listones Y Molduras Perforadas",
    "sg:phone":"+34 973 22 31 56",
    "sg:postcode":"25004",
    "sg:province":"Lleida",
    "wof:name":"Sociart Grup, S.l.",
    "wof:placetype":"venue"
},
  "geometry": {"coordinates":[0.6201819777,41.6187553406],"type":"Point"}
}