{
  "type": "Feature",
  "properties": {
    "addr:full":"Cami Barranc De La Llet (del), 153 Tortosa Tarragona 43500",
    "addr:postcode":"43500",
    "addr:street":"Barranc;La;Del",
    "iso:country":"ES",
    "sg:address":"Cami Barranc De La Llet (del), 153",
    "sg:city":"Tortosa",
    "sg:orig_category":"Muebles, Minoristas",
    "sg:phone":"+34 977 44 19 64",
    "sg:postcode":"43500",
    "sg:province":"Tarragona",
    "wof:name":"Escudero Subirats Julia",
    "wof:placetype":"venue"
},
  "geometry": {"coordinates":[0.5276899934,40.7954902649],"type":"Point"}
}