{
  "type": "Feature",
  "properties": {
    "iso:country":"ES",
    "sg:address":"Calle de San Miguel, 16",
    "sg:city":"Amorebieta",
    "sg:orig_category":"Agencias De Trabajo Temporal",
    "sg:phone":"+34 946 73 03 88",
    "sg:postcode":"48340",
    "sg:province":"Vizcaya",
    "sg:website":"www.flexiplan.es",
    "wof:name":"Flexiplan S.a.",
    "wof:placetype":"venue"
},
  "geometry": {"coordinates":[-2.7319540977,43.2192001343],"type":"Point"}
}