{
  "type": "Feature",
  "properties": {
    "iso:country":"ES",
    "sg:address":"Calle de Cami Reial, 102",
    "sg:city":"Torrent",
    "sg:orig_category":"Comercio, Reparaci\u00d3n De Motocicletas, Bicicletas Y Piezas Sueltas",
    "sg:phone":"+34 961 56 30 49",
    "sg:postcode":"46900",
    "sg:province":"Valencia",
    "wof:name":"Motos Torrent S.l.",
    "wof:placetype":"venue"
},
  "geometry": {"coordinates":[-0.5352355838,39.4127235413],"type":"Point"}
}