{
  "type": "Feature",
  "properties": {
    "iso:country":"ES",
    "sg:address":"Calle de Lealtad, 12",
    "sg:city":"Santander",
    "sg:orig_category":"Abogados",
    "sg:phone":"+34 942 22 58 61",
    "sg:postcode":"39002",
    "sg:province":"Cantabria",
    "wof:name":"Mier Del Hoyo Gregorio",
    "wof:placetype":"venue"
},
  "geometry": {"coordinates":[-3.808494091,43.4611473083],"type":"Point"}
}