{
  "type": "Feature",
  "properties": {
    "addr:full":"Calle de Fuenterrabia, 21 Irun Guip\u00f9zcoa 20301",
    "addr:housenumber":"21",
    "addr:postcode":"20301",
    "addr:street":"Calle De Fuenterrabia;Guipu\u0300Zcoa",
    "iso:country":"ES",
    "sg:address":"Calle de Fuenterrabia, 21",
    "sg:city":"Irun",
    "sg:orig_category":"Muebles, Minoristas",
    "sg:phone":"+34 943 61 89 33",
    "sg:postcode":"20301",
    "sg:province":"Guip\u00f9zcoa",
    "wof:name":"Ignacio Gonzalez Irazusta",
    "wof:placetype":"venue"
},
  "geometry": {"coordinates":[-1.7902339697,43.3395233154],"type":"Point"}
}