{
  "type": "Feature",
  "properties": {
    "iso:country":"ES",
    "sg:address":"Calle de Padre Rubio, 24",
    "sg:city":"Madrid",
    "sg:orig_category":"Plomeros",
    "sg:phone":"+34 913 15 88 27",
    "sg:postcode":"28029",
    "sg:province":"Madrid",
    "sg:website":"www.geberit.es",
    "wof:name":"Geberit S.a.",
    "wof:placetype":"venue"
},
  "geometry": {"coordinates":[-3.6926059723,40.4707069397],"type":"Point"}
}