{
  "type": "Feature",
  "properties": {
    "iso:country":"ES",
    "sg:address":"Cmno. Campo, S/n",
    "sg:city":"Chatun",
    "sg:orig_category":"Cr\u00cda De Animales",
    "sg:phone":"+34 921 12 30 46",
    "sg:postcode":"40241",
    "sg:province":"Segovia",
    "wof:name":"Ganadera El Cigue\u00f1al S.l.",
    "wof:placetype":"venue"
},
  "geometry": {"coordinates":[-4.3280878067,41.2902336121],"type":"Point"}
}