{
  "type": "Feature",
  "properties": {
    "iso:country":"ES",
    "sg:address":"Calle de Boticas, S/n",
    "sg:city":"Mula",
    "sg:orig_category":"Librer\u00cdas",
    "sg:phone":"+34 968 63 75 74",
    "sg:postcode":"30170",
    "sg:province":"Murcia",
    "wof:name":"Diaz Torrones Maria Mercedes",
    "wof:placetype":"venue"
},
  "geometry": {"coordinates":[-1.4916732311,38.0411148071],"type":"Point"}
}