{
  "type": "Feature",
  "properties": {
    "iso:country":"ES",
    "sg:address":"Pje. San Antonio, 7",
    "sg:city":"Marmolejo",
    "sg:orig_category":"Alquiler De V\u00cddeo",
    "sg:phone":"+34 953 54 05 50",
    "sg:postcode":"23770",
    "sg:province":"Ja\u00e9n",
    "wof:name":"Mudarra Garcia Jose Luis",
    "wof:placetype":"venue"
},
  "geometry": {"coordinates":[-4.1715269089,38.0454750061],"type":"Point"}
}