{
  "type": "Feature",
  "properties": {
    "addr:full":"Calle de Marques De Albaida, 7 Palencia Palencia 34005",
    "addr:housenumber":"7",
    "addr:postcode":"34005",
    "addr:street":"Calle De Marques De Albaida",
    "iso:country":"ES",
    "sg:address":"Calle de Marques De Albaida, 7",
    "sg:city":"Palencia",
    "sg:orig_category":"Librer\u00cdas",
    "sg:phone":"+34 979 74 51 43",
    "sg:postcode":"34005",
    "sg:province":"Palencia",
    "wof:name":"Rodriguez Del Burgo Francisco Javier",
    "wof:placetype":"venue"
},
  "geometry": {"coordinates":[-4.5329871178,42.0073356628],"type":"Point"}
}