{
  "type": "Feature",
  "properties": {
    "addr:full":"Calle de Campillo (del), 1 Baltanas Palencia 34240",
    "addr:housenumber":"1",
    "addr:postcode":"34240",
    "addr:street":"Calle De Campillo Del",
    "iso:country":"ES",
    "sg:address":"Calle de Campillo (del), 1",
    "sg:city":"Baltanas",
    "sg:orig_category":"Cajas Para Embalar",
    "sg:phone":"+34 979 79 06 46",
    "sg:postcode":"34240",
    "sg:province":"Palencia",
    "wof:name":"Caja Rural Del Duero",
    "wof:placetype":"venue"
},
  "geometry": {"coordinates":[-4.247546196,41.9389572144],"type":"Point"}
}