{
  "type": "Feature",
  "properties": {
    "iso:country":"ES",
    "sg:address":"Carrer de L'argenter, 1",
    "sg:city":"Barcelona",
    "sg:orig_category":"Colchones (fabricaci\u00d3n, Al Por Mayor, Al Por Menor)",
    "sg:phone":"+34 933 19 19 37",
    "sg:postcode":"08003",
    "sg:province":"Barcelona",
    "wof:name":"Sese Villanova Jose Maria",
    "wof:placetype":"venue"
},
  "geometry": {"coordinates":[2.1773860455,41.3879013062],"type":"Point"}
}