{
  "type": "Feature",
  "properties": {
    "addr:full":"Urb Ciudad Verde, 227 Sevilla Sevilla 41020",
    "addr:housenumber":"227",
    "addr:postcode":"41020",
    "addr:street":"Urb Ciudad Verde",
    "iso:country":"ES",
    "sg:address":"Urb Ciudad Verde, 227",
    "sg:city":"Sevilla",
    "sg:orig_category":"Empresarios Y Productoras De Espect\u00c1culos",
    "sg:phone":"+34 954 40 50 94",
    "sg:postcode":"41020",
    "sg:province":"Sevilla",
    "sg:website":"www.latranfulla.com",
    "wof:name":"Jimenez Berros Maria Del Carmen",
    "wof:placetype":"venue"
},
  "geometry": {"coordinates":[-5.9294447899,37.3990135193],"type":"Point"}
}