{
  "type": "Feature",
  "properties": {
    "iso:country":"ES",
    "sg:address":"Calle de Benidorm, 5",
    "sg:city":"Sevilla",
    "sg:orig_category":"Aparcamientos (infraestructuras, Accesorios)",
    "sg:phone":"+34 954 22 94 19",
    "sg:postcode":"41001",
    "sg:province":"Sevilla",
    "wof:name":"Garaje Benidorm S.l.",
    "wof:placetype":"venue"
},
  "geometry": {"coordinates":[-6.0033178329,37.3893432617],"type":"Point"}
}