{
  "type": "Feature",
  "properties": {
    "addr:full":"Avda Olivar (del), 25 Valdemoro Madrid 28340",
    "addr:housenumber":"25",
    "addr:postcode":"28340",
    "addr:street":"Avda Olivar Del",
    "iso:country":"ES",
    "sg:address":"Avda Olivar (del), 25",
    "sg:city":"Valdemoro",
    "sg:orig_category":"Fabricaci\u00d3n De Cajas De Cart\u00d3n",
    "sg:phone":"+34 918 01 93 82",
    "sg:postcode":"28340",
    "sg:province":"Madrid",
    "wof:name":"Top-carton S.l.",
    "wof:placetype":"venue"
},
  "geometry": {"coordinates":[-3.6742529869,40.2052345276],"type":"Point"}
}