{
  "type": "Feature",
  "properties": {
    "addr:full":"Rua Subida A Estacion, 5 Redondela Pontevedra 36800",
    "addr:housenumber":"5",
    "addr:postcode":"36800",
    "addr:street":"Rua Subida A Estacion",
    "iso:country":"ES",
    "sg:address":"Rua Subida A Estacion, 5",
    "sg:city":"Redondela",
    "sg:orig_category":"Fisioterapia",
    "sg:phone":"+34 986 40 51 11",
    "sg:postcode":"36800",
    "sg:province":"Pontevedra",
    "wof:name":"Fimar C.b. Pontevedra",
    "wof:placetype":"venue"
},
  "geometry": {"coordinates":[-8.6130027771,42.2835464478],"type":"Point"}
}