{
  "type": "Feature",
  "properties": {
    "addr:full":"Calle de Mi\u00d1o (del), 3 Alcobendas Madrid 28100",
    "addr:postcode":"28100",
    "addr:street":"Calle De Min\u0303O Del;Alcobendas",
    "iso:country":"ES",
    "sg:address":"Calle de Mi\u00d1o (del), 3",
    "sg:city":"Alcobendas",
    "sg:orig_category":"Zapatos (al Por Menor)",
    "sg:phone":"+34 916 52 70 78",
    "sg:postcode":"28100",
    "sg:province":"Madrid",
    "wof:name":"Brice\u00f1o Ramos Antonio",
    "wof:placetype":"venue"
},
  "geometry": {"coordinates":[-3.6392319202,40.544052124],"type":"Point"}
}