{
  "type": "Feature",
  "properties": {
    "addr:full":"Av Conqueridor, 116 Ciutadella Menorca Islas Baleares 07760",
    "addr:housenumber":"116",
    "addr:postcode":"07760",
    "addr:street":"Av Conqueridor",
    "iso:country":"ES",
    "sg:address":"Av Conqueridor, 116",
    "sg:city":"Ciutadella Menorca",
    "sg:orig_category":"Agencias De Viajes",
    "sg:phone":"+34 971 38 41 41",
    "sg:postcode":"07760",
    "sg:province":"Islas Baleares",
    "sg:website":"www.halconviajes.es",
    "wof:name":"Viajes Halcon S.a.",
    "wof:placetype":"venue"
},
  "geometry": {"coordinates":[3.8392601013,39.9993057251],"type":"Point"}
}