{
  "type": "Feature",
  "properties": {
    "addr:full":"Avda Juan Xxiii, 19 Pozuelo De Alarcon Madrid 28224",
    "addr:housenumber":"19",
    "addr:postcode":"28224",
    "addr:street":"Avda Juan Xxiii",
    "iso:country":"ES",
    "sg:address":"Avda Juan Xxiii, 19",
    "sg:city":"Pozuelo De Alarcon",
    "sg:orig_category":"Fisioterapia",
    "sg:phone":"+34 913 52 54 21",
    "sg:postcode":"28224",
    "sg:province":"Madrid",
    "wof:name":"Imagine Pilates S.l",
    "wof:placetype":"venue"
},
  "geometry": {"coordinates":[-3.8078160286,40.4430656433],"type":"Point"}
}