{
  "type": "Feature",
  "properties": {
    "iso:country":"ES",
    "sg:address":"Calle de Tordo, S/n",
    "sg:city":"Valladolid",
    "sg:orig_category":"Tintes (fabricaci\u00d3n, Al Por Mayor)",
    "sg:phone":"+34 983 30 85 48",
    "sg:postcode":"47012",
    "sg:province":"Valladolid",
    "wof:name":"Cuesta Fernandez Maria Del Carmen",
    "wof:placetype":"venue"
},
  "geometry": {"coordinates":[-4.7069787979,41.6490249634],"type":"Point"}
}