{
  "type": "Feature",
  "properties": {
    "iso:country":"ES",
    "sg:address":"Calle de Alamos, 42",
    "sg:city":"Malaga",
    "sg:orig_category":"Centros De Coordinaci\u00d3n",
    "sg:phone":"+34 952 21 12 73",
    "sg:postcode":"29012",
    "sg:province":"M\u00e1laga",
    "wof:name":"Gestoria Espa\u00f1a S.l.",
    "wof:placetype":"venue"
},
  "geometry": {"coordinates":[-4.4182839394,36.7231521606],"type":"Point"}
}