{
  "type": "Feature",
  "properties": {
    "addr:full":"Avda Pedro Mateo Sagasta, 34 Caldas De Reis Pontevedra 36650",
    "addr:housenumber":"34",
    "addr:postcode":"36650",
    "addr:street":"Avda Pedro Mateo Sagasta",
    "iso:country":"ES",
    "sg:address":"Avda Pedro Mateo Sagasta, 34",
    "sg:city":"Caldas De Reis",
    "sg:orig_category":"Art\u00cdculos De Regalo (al Por Menor)",
    "sg:phone":"+34 986 54 14 57",
    "sg:postcode":"36650",
    "sg:province":"Pontevedra",
    "wof:name":"Manuel Maran S.l",
    "wof:placetype":"venue"
},
  "geometry": {"coordinates":[-8.6427087784,42.6046562195],"type":"Point"}
}