{
  "type": "Feature",
  "properties": {
    "iso:country":"ES",
    "sg:address":"Calle de Antonio Monedero, 37",
    "sg:city":"Due\u00f1as",
    "sg:orig_category":"Molduras, Junquillos, Listones Y Molduras Perforadas",
    "sg:phone":"+34 979 78 08 80",
    "sg:postcode":"34210",
    "sg:province":"Palencia",
    "wof:name":"Caballero De La Hoz Maria Luisa",
    "wof:placetype":"venue"
},
  "geometry": {"coordinates":[-4.5450201035,41.8756599426],"type":"Point"}
}