{
  "type": "Feature",
  "properties": {
    "iso:country":"ES",
    "sg:address":"Plaz Pontevedra, 6",
    "sg:city":"Coru\u00d1a",
    "sg:orig_category":"Fabricaci\u00d3n De Sobres, Bolsas Y Fundas",
    "sg:phone":"+34 981 21 25 12",
    "sg:postcode":"15003",
    "sg:province":"A Coru\u00f1a",
    "wof:name":"Tiendas M & B S.l.",
    "wof:placetype":"venue"
},
  "geometry": {"coordinates":[-8.4063863754,43.3679389954],"type":"Point"}
}