{
  "type": "Feature",
  "properties": {
    "addr:full":"Plaz Jose Canalejas, 1 Algezares Murcia 30157",
    "addr:housenumber":"1",
    "addr:postcode":"30157",
    "addr:street":"Jose Canalejas",
    "iso:country":"ES",
    "sg:address":"Plaz Jose Canalejas, 1",
    "sg:city":"Algezares",
    "sg:orig_category":"Mercer\u00cda, Lencer\u00cda (al Por Menor)",
    "sg:phone":"+34 968 84 77 14",
    "sg:postcode":"30157",
    "sg:province":"Murcia",
    "wof:name":"Ruiz Almansa Josefa",
    "wof:placetype":"venue"
},
  "geometry": {"coordinates":[-1.111479044,37.9454307556],"type":"Point"}
}