{
  "type": "Feature",
  "properties": {
    "addr:full":"Calle de Santa Ana, 16 Castuera Badajoz 06420",
    "addr:housenumber":"16",
    "addr:postcode":"06420",
    "addr:street":"Calle De Santa Ana",
    "iso:country":"ES",
    "sg:address":"Calle de Santa Ana, 16",
    "sg:city":"Castuera",
    "sg:classifiers":[
        {
            "category":"Autos & Motor Vehicles",
            "subcategory":"Automobile Sales",
            "type":"Retail Goods"
        }
    ],
    "sg:phone":"+34 924 76 06 18",
    "sg:postcode":"06420",
    "sg:province":"Badajoz",
    "wof:name":"Romero Galan Manuel",
    "wof:placetype":"venue"
},
  "geometry": {"coordinates":[-5.5447831154,38.7227554321],"type":"Point"}
}