{
  "type": "Feature",
  "properties": {
    "addr:full":"Pueblo Marinero, S/n Ceuta Ceuta 51001",
    "addr:housenumber":"s",
    "addr:postcode":"51001",
    "addr:street":"Marinero;/ N",
    "iso:country":"ES",
    "sg:address":"Pueblo Marinero, S/n",
    "sg:city":"Ceuta",
    "sg:orig_category":"Pesca Y Caza: Art\u00cdculos (al Por Menor)",
    "sg:phone":"+34 956 52 47 24",
    "sg:postcode":"51001",
    "sg:province":"Ceuta",
    "wof:name":"Deportes Mendoza S.l.",
    "wof:placetype":"venue"
},
  "geometry": {"coordinates":[-5.3302302361,35.8947601318],"type":"Point"}
}