{
  "type": "Feature",
  "properties": {
    "iso:country":"ES",
    "sg:address":"Carrer de Puigcerda, 118",
    "sg:city":"Barcelona",
    "sg:orig_category":"Cueros Y Pieles (al Por Mayor)",
    "sg:phone":"+34 933 07 54 22",
    "sg:postcode":"08019",
    "sg:province":"Barcelona",
    "wof:name":"Inter Leather S.l.",
    "wof:placetype":"venue"
},
  "geometry": {"coordinates":[2.2101240158,41.4150505066],"type":"Point"}
}