{
  "type": "Feature",
  "properties": {
    "iso:country":"ES",
    "sg:address":"Plaz Mancomunidad Cabo Pe\u00d1as, 2",
    "sg:city":"Candas",
    "sg:classifiers":[
        {
            "category":"Banks & Credit Unions",
            "subcategory":"Bureau De Change",
            "type":"Services"
        }
    ],
    "sg:phone":"+34 985 87 29 59",
    "sg:postcode":"33430",
    "sg:province":"Asturias",
    "sg:tags":[
        "organismos",
        "control"
    ],
    "wof:name":"Ruoleima S.l.",
    "wof:placetype":"venue"
},
  "geometry": {"coordinates":[-5.767619133,43.5897827148],"type":"Point"}
}