{
  "type": "Feature",
  "properties": {
    "addr:full":"Calle de Estacion (la), 7 Robla Le\u00f3n 24640",
    "addr:housenumber":"7",
    "addr:postcode":"24640",
    "addr:street":"Calle De Estacion La;Leo\u0301N",
    "iso:country":"ES",
    "sg:address":"Calle de Estacion (la), 7",
    "sg:city":"Robla",
    "sg:orig_category":"Reposter\u00cdas",
    "sg:phone":"+34 987 57 01 45",
    "sg:postcode":"24640",
    "sg:province":"Le\u00f3n",
    "wof:name":"Ramos Blanco Angel",
    "wof:placetype":"venue"
},
  "geometry": {"coordinates":[-5.6277589798,42.8041648865],"type":"Point"}
}