{
  "type": "Feature",
  "properties": {
    "addr:full":"Avda Menendez Pelayo, S/n Santa Cruz De Bezana Cantabria 39100",
    "addr:housenumber":"s / n",
    "addr:postcode":"39100",
    "addr:street":"Avda Menendez Pelayo",
    "iso:country":"ES",
    "sg:address":"Avda Menendez Pelayo, S/n",
    "sg:city":"Santa Cruz De Bezana",
    "sg:orig_category":"Iglesia Cat\u00d3lica",
    "sg:phone":"+34 942 58 04 81",
    "sg:postcode":"39100",
    "sg:province":"Cantabria",
    "wof:name":"Parroquia Santa Cruz Bezana",
    "wof:placetype":"venue"
},
  "geometry": {"coordinates":[-3.9063470364,43.4495429993],"type":"Point"}
}