{
  "type": "Feature",
  "properties": {
    "iso:country":"ES",
    "sg:address":"Calle de San Cayetano, 11",
    "sg:city":"Armilla",
    "sg:orig_category":"Electricidad: Instaladores",
    "sg:phone":"+34 958 55 26 27",
    "sg:postcode":"18100",
    "sg:province":"Granada",
    "wof:name":"Inca Electricidad S.l.",
    "wof:placetype":"venue"
},
  "geometry": {"coordinates":[-3.6291780472,37.1439628601],"type":"Point"}
}