{
  "type": "Feature",
  "properties": {
    "iso:country":"ES",
    "sg:address":"Calle de San Nemesio, 4",
    "sg:city":"Madrid",
    "sg:orig_category":"Centros Empresariales",
    "sg:phone":"+34 914 13 32 92",
    "sg:postcode":"28043",
    "sg:province":"Madrid",
    "wof:name":"Arje S. L.",
    "wof:placetype":"venue"
},
  "geometry": {"coordinates":[-3.6581847668,40.4523200989],"type":"Point"}
}