{
  "type": "Feature",
  "properties": {
    "addr:full":"Pla\u00c7 Espanya, 1 Gimenells Lleida 25112",
    "addr:postcode":"1 gimenells;25112",
    "iso:country":"ES",
    "sg:address":"Pla\u00c7 Espanya, 1",
    "sg:city":"Gimenells",
    "sg:orig_category":"Iglesia Cat\u00d3lica",
    "sg:phone":"+34 973 74 81 25",
    "sg:postcode":"25112",
    "sg:province":"Lleida",
    "wof:name":"Parroquia Nuestra Se\u00f1ora Del Rosario",
    "wof:placetype":"venue"
},
  "geometry": {"coordinates":[0.3899149895,41.6523666382],"type":"Point"}
}