{
  "type": "Feature",
  "properties": {
    "addr:full":"Calle de Ribera De Curtidores, 37 Madrid Madrid 28005",
    "addr:housenumber":"37",
    "addr:postcode":"madrid;28005",
    "addr:street":"Calle De Ribera De Curtidores",
    "iso:country":"ES",
    "sg:address":"Calle de Ribera De Curtidores, 37",
    "sg:city":"Madrid",
    "sg:orig_category":"Venta, Instalaci\u00d3n, Mantenimiento De Chimeneas De Interior Y Accesorios",
    "sg:phone":"+34 915 27 44 21",
    "sg:postcode":"28005",
    "sg:province":"Madrid",
    "wof:name":"Marmoles Y Chimeneas S.l.",
    "wof:placetype":"venue"
},
  "geometry": {"coordinates":[-3.7070729733,40.4068527222],"type":"Point"}
}