{
  "type": "Feature",
  "properties": {
    "addr:full":"Carrer de Girona, 148 Barcelona Barcelona 08037",
    "addr:housenumber":"148",
    "addr:postcode":"08037",
    "addr:street":"Carrer De Girona",
    "iso:country":"ES",
    "sg:address":"Carrer de Girona, 148",
    "sg:city":"Barcelona",
    "sg:orig_category":"Propiedad Industrial: Patentes De Inventos, Marcas, Modelos, Dise\u00d1os",
    "sg:phone":"+34 934 59 13 68",
    "sg:postcode":"08037",
    "sg:province":"Barcelona",
    "wof:name":"Canela Patentes Y Marcas S.l.",
    "wof:placetype":"venue"
},
  "geometry": {"coordinates":[2.1661469936,41.3987846375],"type":"Point"}
}