{
  "type": "Feature",
  "properties": {
    "addr:full":"San Roman-toreno, Km. 0001,0 San Roman De Bembibre Le\u00f3n 24318",
    "addr:postcode":"24318",
    "addr:street":"Km. 0001,0 San Roman De Bembibre Leo\u0301N",
    "iso:country":"ES",
    "sg:address":"San Roman-toreno, Km. 0001,0",
    "sg:city":"San Roman De Bembibre",
    "sg:orig_category":"Hormigonados",
    "sg:phone":"+34 987 69 31 27",
    "sg:postcode":"24318",
    "sg:province":"Le\u00f3n",
    "wof:name":"Canteras Industriales Del Bierzo S.a.",
    "wof:placetype":"venue"
},
  "geometry": {"coordinates":[-6.4443688393,42.6436843872],"type":"Point"}
}