{
  "type": "Feature",
  "properties": {
    "addr:full":"Plaz Jimenez Diaz, 5 Getafe Madrid 28903",
    "addr:housenumber":"5",
    "addr:postcode":"28903",
    "addr:street":"Diaz",
    "iso:country":"ES",
    "sg:address":"Plaz Jimenez Diaz, 5",
    "sg:city":"Getafe",
    "sg:orig_category":"Asociaciones Humanitarias, De Cooperaci\u00d3n, De Acci\u00d3n Social",
    "sg:phone":"+34 916 95 28 03",
    "sg:postcode":"28903",
    "sg:province":"Madrid",
    "wof:name":"Asociacion De Padres De Ni\u00d1os Diferentes",
    "wof:placetype":"venue"
},
  "geometry": {"coordinates":[-3.7215080261,40.3152084351],"type":"Point"}
}