{
  "type": "Feature",
  "properties": {
    "iso:country":"ES",
    "sg:address":"Avda Compostela, 51",
    "sg:city":"Padron",
    "sg:orig_category":"Abogados",
    "sg:phone":"+34 981 81 23 07",
    "sg:postcode":"15900",
    "sg:province":"La Coru\u00f1a",
    "wof:name":"Blanco Mari\u00f1o Francisco Serafin",
    "wof:placetype":"venue"
},
  "geometry": {"coordinates":[-8.6600198746,42.7365951538],"type":"Point"}
}