{
  "type": "Feature",
  "properties": {
    "addr:full":"Carrer de Vista Alegre (de La), 34 S. Carles Rapita Tarragona 43540",
    "addr:housenumber":"34",
    "addr:postcode":"43540",
    "addr:street":"Carrer De Vista Alegre De La;S. Carles Rapita",
    "iso:country":"ES",
    "sg:address":"Carrer de Vista Alegre (de La), 34",
    "sg:city":"S. Carles Rapita",
    "sg:orig_category":"Agencias De Aduana",
    "sg:phone":"+34 977 74 00 11",
    "sg:postcode":"43540",
    "sg:province":"Tarragona",
    "sg:website":"www.tcvirsa.com",
    "wof:name":"Vir S. A.",
    "wof:placetype":"venue"
},
  "geometry": {"coordinates":[0.5940099955,40.6177406311],"type":"Point"}
}