{
  "type": "Feature",
  "properties": {
    "iso:country":"ES",
    "sg:address":"Calle de Cardenal Cisneros, 19",
    "sg:city":"Lomo De La Herradura",
    "sg:orig_category":"Promotores Constructores",
    "sg:phone":"+34 928 69 55 57",
    "sg:postcode":"35200",
    "sg:province":"Las Palmas",
    "wof:name":"Ferreteria Y Construcciones Ojeda S.l.",
    "wof:placetype":"venue"
},
  "geometry": {"coordinates":[-15.4297227859,27.9957065582],"type":"Point"}
}