{
  "type": "Feature",
  "properties": {
    "addr:full":"Av Moli De Vent, 2 Pu\u00e7ol Valencia 46530",
    "addr:housenumber":"2",
    "addr:postcode":"46530",
    "addr:street":"Av Moli De Vent",
    "iso:country":"ES",
    "sg:address":"Av Moli De Vent, 2",
    "sg:city":"Pu\u00e7ol",
    "sg:orig_category":"Centros M\u00c9dicos Y Sociales, Dispensarios",
    "sg:phone":"+34 961 46 43 43",
    "sg:postcode":"46530",
    "sg:province":"Valencia",
    "wof:name":"Maria Amparo Zuriaga Senent,manuel Julio Ma\u00f1es Gomez Y Susana Zaragoza Blasco Cdad.",
    "wof:placetype":"venue"
},
  "geometry": {"coordinates":[-0.3093020022,39.6181221008],"type":"Point"}
}