{
  "type": "Feature",
  "properties": {
    "addr:full":"Cami Antic Sta. Coloma-lloret, S/n Lloret Mar Girona 17310",
    "addr:postcode":"17310",
    "addr:street":"Antic;Coloma-Lloret S / N Lloret",
    "iso:country":"ES",
    "sg:address":"Cami Antic Sta. Coloma-lloret, S/n",
    "sg:city":"Lloret Mar",
    "sg:orig_category":"Promotores Constructores",
    "sg:phone":"+34 972 36 39 90",
    "sg:postcode":"17310",
    "sg:province":"Girona",
    "wof:name":"Tierras Del Sur S.l.",
    "wof:placetype":"venue"
},
  "geometry": {"coordinates":[2.846834898,41.6981697083],"type":"Point"}
}