{
  "type": "Feature",
  "properties": {
    "iso:country":"ES",
    "sg:address":"Calle de Alicante, 51",
    "sg:city":"San Vicente Del Raspeig-sant Vicent Del Raspeig",
    "sg:orig_category":"Inmobiliaria (agencias)",
    "sg:phone":"+34 965 67 57 79",
    "sg:postcode":"03690",
    "sg:province":"Alicante",
    "wof:name":"Gestion Inmobiliaria Ana S.l.",
    "wof:placetype":"venue"
},
  "geometry": {"coordinates":[-0.511117816,38.3874702454],"type":"Point"}
}