{
  "type": "Feature",
  "properties": {
    "iso:country":"ES",
    "sg:address":"Rua Travesia De Vigo, 204",
    "sg:city":"Roris",
    "sg:orig_category":"Farmacias",
    "sg:phone":"+34 986 25 12 20",
    "sg:postcode":"36207",
    "sg:province":"Pontevedra",
    "wof:name":"Garcia Pe\u00f1a Maria Teresa",
    "wof:placetype":"venue"
},
  "geometry": {"coordinates":[-7.1463718414,42.3855743408],"type":"Point"}
}