{
  "type": "Feature",
  "properties": {
    "addr:full":"Calle de Larga, 13 Navalmorales Toledo 45140",
    "addr:housenumber":"13",
    "addr:postcode":"45140",
    "addr:street":"Calle De Larga",
    "iso:country":"ES",
    "sg:address":"Calle de Larga, 13",
    "sg:city":"Navalmorales",
    "sg:orig_category":"Reposter\u00cdas",
    "sg:phone":"+34 925 40 46 53",
    "sg:postcode":"45140",
    "sg:province":"Toledo",
    "wof:name":"Recuero Martin Eloy",
    "wof:placetype":"venue"
},
  "geometry": {"coordinates":[-4.6422758102,39.7283096313],"type":"Point"}
}