{
  "type": "Feature",
  "properties": {
    "iso:country":"ES",
    "sg:address":"Avda Francisco Fernandez Ordo\u00d1ez, 29",
    "sg:city":"Getafe",
    "sg:orig_category":"Sociedades, Compa\u00d1\u00cdas Aseguradoras",
    "sg:phone":"+34 916 82 31 56",
    "sg:postcode":"28903",
    "sg:province":"Madrid",
    "wof:name":"Yuste Ortega Segur S.l.",
    "wof:placetype":"venue"
},
  "geometry": {"coordinates":[-3.7151391506,40.3153266907],"type":"Point"}
}