{
  "type": "Feature",
  "properties": {
    "addr:full":"Calle de Huesca De, 65 Fraga Huesca 22520",
    "addr:housenumber":"65",
    "addr:postcode":"22520",
    "addr:street":"Calle De Huesca De",
    "iso:country":"ES",
    "sg:address":"Calle de Huesca De, 65",
    "sg:city":"Fraga",
    "sg:orig_category":"Plomeros",
    "sg:phone":"+34 974 47 17 92",
    "sg:postcode":"22520",
    "sg:province":"Huesca",
    "wof:name":"Fonsa Instalaciones Y Energias Renovables S.l.",
    "wof:placetype":"venue"
},
  "geometry": {"coordinates":[0.3325499892,41.5208816528],"type":"Point"}
}