{
  "type": "Feature",
  "properties": {
    "iso:country":"ES",
    "sg:address":"Calle de Breton De Los Herreros, 40",
    "sg:city":"Logro\u00f1o",
    "sg:orig_category":"Agencias De Viajes",
    "sg:phone":"+34 941 20 55 11",
    "sg:postcode":"26001",
    "sg:province":"La Rioja",
    "sg:website":"www.incavisa.com",
    "wof:name":"Herrera Martinez Jesus Angel",
    "wof:placetype":"venue"
},
  "geometry": {"coordinates":[-2.4488210678,42.4652099609],"type":"Point"}
}