{
  "type": "Feature",
  "properties": {
    "addr:full":"Rua Eduardo Blanco Amor, 2 Porto De Santa Cruz La Coru\u00f1a 15179",
    "addr:housenumber":"2",
    "addr:postcode":"15179",
    "addr:street":"Rua Eduardo Blanco Amor;Corun\u0303A",
    "iso:country":"ES",
    "sg:address":"Rua Eduardo Blanco Amor, 2",
    "sg:city":"Porto De Santa Cruz",
    "sg:classifiers":[
        {
            "category":"Taxi",
            "type":"Transportation"
        }
    ],
    "sg:phone":"+34 981 61 44 66",
    "sg:postcode":"15179",
    "sg:province":"La Coru\u00f1a",
    "wof:name":"Asociacion Local De Auto Turismos Clase B De Oleiros",
    "wof:placetype":"venue"
},
  "geometry": {"coordinates":[-8.2059621811,43.2575149536],"type":"Point"}
}