{
  "type": "Feature",
  "properties": {
    "iso:country":"ES",
    "sg:address":"Calle de Cristobal Colon, 1",
    "sg:city":"Utrera",
    "sg:orig_category":"Molduras, Junquillos, Listones Y Molduras Perforadas",
    "sg:phone":"+34 954 86 07 14",
    "sg:postcode":"41710",
    "sg:province":"Sevilla",
    "wof:name":"Cid Romero Javier",
    "wof:placetype":"venue"
},
  "geometry": {"coordinates":[-5.7781891823,37.1829109192],"type":"Point"}
}