{
  "type": "Feature",
  "properties": {
    "addr:full":"Avda Palo Dulce, 52 Gibraleon Huelva 21500",
    "addr:housenumber":"52",
    "addr:postcode":"21500",
    "addr:street":"Avda Palo Dulce",
    "iso:country":"ES",
    "sg:address":"Avda Palo Dulce, 52",
    "sg:city":"Gibraleon",
    "sg:orig_category":"Empresas De Carpinter\u00cda Met\u00c1lica",
    "sg:phone":"+34 959 30 00 03",
    "sg:postcode":"21500",
    "sg:province":"Huelva",
    "wof:name":"Jara De La Rosa Manuel",
    "wof:placetype":"venue"
},
  "geometry": {"coordinates":[-6.9664788246,37.3744239807],"type":"Point"}
}