{
  "type": "Feature",
  "properties": {
    "addr:full":"Ctra Convent Del, 3 Oliva Valencia 46780",
    "addr:housenumber":"3",
    "addr:postcode":"46780",
    "addr:street":"Ctra Convent Del",
    "iso:country":"ES",
    "sg:address":"Ctra Convent Del, 3",
    "sg:city":"Oliva",
    "sg:orig_category":"Abogados",
    "sg:phone":"+34 962 85 09 44",
    "sg:postcode":"46780",
    "sg:province":"Valencia",
    "wof:name":"Soler Mi\u00f1ana Jose Salvador",
    "wof:placetype":"venue"
},
  "geometry": {"coordinates":[-0.1183699965,38.9206428528],"type":"Point"}
}