{
  "type": "Feature",
  "properties": {
    "addr:full":"Plaz Espa\u00d1a De, 1 Trigueros Huelva 21620",
    "addr:postcode":"21620",
    "addr:street":"Plaz",
    "iso:country":"ES",
    "sg:address":"Plaz Espa\u00d1a De, 1",
    "sg:city":"Trigueros",
    "sg:orig_category":"Farmacias",
    "sg:phone":"+34 959 30 58 42",
    "sg:postcode":"21620",
    "sg:province":"Huelva",
    "wof:name":"Palacios Clemente Ignacio",
    "wof:placetype":"venue"
},
  "geometry": {"coordinates":[-6.8301939964,37.3829040527],"type":"Point"}
}