{
  "type": "Feature",
  "properties": {
    "iso:country":"ES",
    "sg:address":"Calle de Alcalde Fraga Bello, 13",
    "sg:city":"Vilalba",
    "sg:orig_category":"Comercio, Reparaci\u00d3n De Motocicletas, Bicicletas Y Piezas Sueltas",
    "sg:phone":"+34 982 51 05 08",
    "sg:postcode":"27800",
    "sg:province":"Lugo",
    "wof:name":"Portela Rouco Dario",
    "wof:placetype":"venue"
},
  "geometry": {"coordinates":[-7.6785240173,43.2974700928],"type":"Point"}
}