{
  "type": "Feature",
  "properties": {
    "addr:full":"Calle de Rafael Alberti, 2 Estacion Madrid 28400",
    "addr:housenumber":"2 estacion",
    "addr:postcode":"28400",
    "addr:street":"Calle De Rafael Alberti",
    "iso:country":"ES",
    "sg:address":"Calle de Rafael Alberti, 2",
    "sg:city":"Estacion",
    "sg:orig_category":"Institutos De Belleza",
    "sg:phone":"+34 918 50 97 14",
    "sg:postcode":"28400",
    "sg:province":"Madrid",
    "wof:name":"Almagro Jimenez Yolanda",
    "wof:placetype":"venue"
},
  "geometry": {"coordinates":[-3.758859396,40.1025886536],"type":"Point"}
}