{
  "type": "Feature",
  "properties": {
    "iso:country":"ES",
    "sg:address":"Carr Rectoria, De Sa, 1",
    "sg:city":"Binissalem",
    "sg:orig_category":"Iglesia Cat\u00d3lica",
    "sg:phone":"+34 971 51 10 18",
    "sg:postcode":"07350",
    "sg:province":"Islas Baleares",
    "wof:name":"Obispado De Mallorca",
    "wof:placetype":"venue"
},
  "geometry": {"coordinates":[2.8423779011,39.6892166138],"type":"Point"}
}