{
  "type": "Feature",
  "properties": {
    "iso:country":"ES",
    "sg:address":"Calle de Antonio Lopez, 9",
    "sg:city":"Madrid",
    "sg:orig_category":"Molduras, Junquillos, Listones Y Molduras Perforadas",
    "sg:phone":"+34 915 69 76 25",
    "sg:postcode":"28019",
    "sg:province":"Madrid",
    "wof:name":"Gonzalez Pedraza Manuel German",
    "wof:placetype":"venue"
},
  "geometry": {"coordinates":[-3.7141377926,40.3970375061],"type":"Point"}
}