{
  "type": "Feature",
  "properties": {
    "iso:country":"ES",
    "sg:address":"Calle de Juana De Vega, 35",
    "sg:city":"Coru\u00d1a",
    "sg:orig_category":"Asesor\u00cda De Comercio Exterior",
    "sg:phone":"+34 981 22 68 12",
    "sg:postcode":"15004",
    "sg:province":"La Coru\u00f1a",
    "sg:website":"www.safei.com",
    "wof:name":"Eurosafei S.v.b.",
    "wof:placetype":"venue"
},
  "geometry": {"coordinates":[-8.4064950943,43.3677330017],"type":"Point"}
}