{
  "type": "Feature",
  "properties": {
    "addr:full":"Calle de Huesca, 21 Logro\u00f1o La Rioja 26002",
    "addr:housenumber":"21",
    "addr:postcode":"26002",
    "addr:street":"Calle De Huesca;Rioja",
    "iso:country":"ES",
    "sg:address":"Calle de Huesca, 21",
    "sg:city":"Logro\u00f1o",
    "sg:orig_category":"Institutos De Belleza",
    "sg:phone":"+34 941 23 88 70",
    "sg:postcode":"26002",
    "sg:province":"La Rioja",
    "wof:name":"Mu\u00f1oz Ramirez Oscar",
    "wof:placetype":"venue"
},
  "geometry": {"coordinates":[-2.4490189552,42.4589309692],"type":"Point"}
}