{
  "type": "Feature",
  "properties": {
    "addr:full":"Avda Campanar, 108 Valencia Valencia 46015",
    "addr:housenumber":"108",
    "addr:postcode":"46015",
    "addr:street":"Avda Campanar",
    "iso:country":"ES",
    "sg:address":"Avda Campanar, 108",
    "sg:city":"Valencia",
    "sg:orig_category":"Psic\u00d3logos",
    "sg:phone":"+34 963 49 17 12",
    "sg:postcode":"46015",
    "sg:province":"Valencia",
    "sg:website":"www.cidai.com",
    "wof:name":"Cidai Psicologia Clinica S.l.",
    "wof:placetype":"venue"
},
  "geometry": {"coordinates":[-0.394073993,39.4794540405],"type":"Point"}
}