{
  "type": "Feature",
  "properties": {
    "addr:full":"Avda Daroca, 45 Madrid Madrid 28017",
    "addr:housenumber":"45",
    "addr:postcode":"madrid;28017",
    "addr:street":"Avda Daroca",
    "iso:country":"ES",
    "sg:address":"Avda Daroca, 45",
    "sg:city":"Madrid",
    "sg:orig_category":"Promotores Constructores",
    "sg:phone":"+34 914 06 10 17",
    "sg:postcode":"28017",
    "sg:province":"Madrid",
    "wof:name":"Losetas Y Adoquines Construcciones S.l.",
    "wof:placetype":"venue"
},
  "geometry": {"coordinates":[-3.6523389816,40.4294052124],"type":"Point"}
}