{
  "type": "Feature",
  "properties": {
    "addr:full":"Carrer de Salauris (de), 1 Salou Tarragona 43840",
    "addr:housenumber":"1",
    "addr:postcode":"43840",
    "addr:street":"Carrer De Salauris De",
    "iso:country":"ES",
    "sg:address":"Carrer de Salauris (de), 1",
    "sg:city":"Salou",
    "sg:orig_category":"Inform\u00c1tica (estudios, Servicios, Asesor\u00cda, Formaci\u00d3n)",
    "sg:phone":"+34 977 38 85 40",
    "sg:postcode":"43840",
    "sg:province":"Tarragona",
    "wof:name":"Blueprint S.l.",
    "wof:placetype":"venue"
},
  "geometry": {"coordinates":[1.136204958,41.079624176],"type":"Point"}
}