{
  "type": "Feature",
  "properties": {
    "addr:full":"Calle de Severiano Goig, 7 Valencia Valencia 46013",
    "addr:housenumber":"7",
    "addr:postcode":"46013",
    "addr:street":"Calle De Severiano Goig",
    "iso:country":"ES",
    "sg:address":"Calle de Severiano Goig, 7",
    "sg:city":"Valencia",
    "sg:orig_category":"Fabricaci\u00d3n, Importaci\u00d3n, Venta De Material De Telefon\u00cda, Peritelefon\u00cda",
    "sg:phone":"+34 963 95 93 31",
    "sg:postcode":"46013",
    "sg:province":"Valencia",
    "wof:name":"Beteta Pinel Carmen",
    "wof:placetype":"venue"
},
  "geometry": {"coordinates":[-0.3627260029,39.4539604187],"type":"Point"}
}