{
  "type": "Feature",
  "properties": {
    "addr:full":"Ctra Alicun (de), S/n Roquetas Mar Almer\u00eda 04...",
    "addr:housenumber":"04 ...",
    "addr:street":"Ctra Alicun De S / N Roquetas Mar Almeri\u0301A",
    "iso:country":"ES",
    "sg:address":"Ctra Alicun (de), S/n",
    "sg:city":"Roquetas Mar",
    "sg:orig_category":"Bricolaje, Herramientas (al Por Menor)",
    "sg:phone":"+34 950 33 98 00",
    "sg:postcode":"04...",
    "sg:province":"Almer\u00eda",
    "sg:website":"www.leroymerlin.es",
    "wof:name":"Leroy Merlin S.a.",
    "wof:placetype":"venue"
},
  "geometry": {"coordinates":[-2.6124989986,36.7638435364],"type":"Point"}
}