{
  "type": "Feature",
  "properties": {
    "addr:full":"Calle de Yecla, 1 Madrid Madrid 28037",
    "addr:housenumber":"1",
    "addr:postcode":"28037",
    "addr:street":"Calle De Yecla",
    "iso:country":"ES",
    "sg:address":"Calle de Yecla, 1",
    "sg:city":"Madrid",
    "sg:orig_category":"Peluqueros: De Se\u00d1oras",
    "sg:phone":"+34 913 04 46 17",
    "sg:postcode":"28037",
    "sg:province":"Madrid",
    "wof:name":"Lucena Caro Teodora",
    "wof:placetype":"venue"
},
  "geometry": {"coordinates":[-3.624147892,40.4295387268],"type":"Point"}
}