{
  "type": "Feature",
  "properties": {
    "addr:full":"Calle de San Vicente De Paul, 2 Cordoba C\u00f3rdoba 14004",
    "addr:housenumber":"2",
    "addr:postcode":"14004",
    "addr:street":"Calle De San Vicente De Paul;Co\u0301Rdoba",
    "iso:country":"ES",
    "sg:address":"Calle de San Vicente De Paul, 2",
    "sg:city":"Cordoba",
    "sg:orig_category":"Peluqueros: De Se\u00d1oras",
    "sg:phone":"+34 957 29 74 36",
    "sg:postcode":"14004",
    "sg:province":"C\u00f3rdoba",
    "wof:name":"Peluqueria Hermanas Del Pino C.b",
    "wof:placetype":"venue"
},
  "geometry": {"coordinates":[-4.7848677635,37.8796806335],"type":"Point"}
}