{
  "type": "Feature",
  "properties": {
    "addr:full":"Trva Santo Domingo, 20 Guadalajara Guadalajara 19001",
    "addr:housenumber":"20",
    "addr:postcode":"19001",
    "addr:street":"Trva Santo Domingo",
    "iso:country":"ES",
    "sg:address":"Trva Santo Domingo, 20",
    "sg:city":"Guadalajara",
    "sg:orig_category":"Cl\u00cdnicas Dentales",
    "sg:phone":"+34 949 21 75 72",
    "sg:postcode":"19001",
    "sg:province":"Guadalajara",
    "wof:name":"Alcadent S.l",
    "wof:placetype":"venue"
},
  "geometry": {"coordinates":[-3.1666707993,40.6332778931],"type":"Point"}
}