{
  "type": "Feature",
  "properties": {
    "addr:full":"G.v. Lopez De Haro D. Diego, 17 Bilbao Vizcaya 48001",
    "addr:housenumber":"17",
    "addr:postcode":"48001",
    "addr:street":"Lopez De Haro D. Diego",
    "iso:country":"ES",
    "sg:address":"G.v. Lopez De Haro D. Diego, 17",
    "sg:city":"Bilbao",
    "sg:orig_category":"Psic\u00d3logos",
    "sg:phone":"+34 944 16 09 39",
    "sg:postcode":"48001",
    "sg:province":"Vizcaya",
    "wof:name":"Pe\u00f1a Valbuena Sonia De La",
    "wof:placetype":"venue"
},
  "geometry": {"coordinates":[-2.9289669991,43.2615470886],"type":"Point"}
}