{
  "type": "Feature",
  "properties": {
    "iso:country":"ES",
    "sg:address":"Calle de Venecia, 6",
    "sg:city":"Quinto",
    "sg:orig_category":"Molduras, Junquillos, Listones Y Molduras Perforadas",
    "sg:phone":"+34 954 12 43 09",
    "sg:postcode":"41089",
    "sg:province":"Sevilla",
    "wof:name":"Infotelcom Telefonia Publica S.c.",
    "wof:placetype":"venue"
},
  "geometry": {"coordinates":[-5.9332537651,37.3442153931],"type":"Point"}
}