{
  "type": "Feature",
  "properties": {
    "addr:full":"Carrer de Lluis Martinell, 2 Valls Tarragona 43800",
    "addr:housenumber":"2",
    "addr:postcode":"43800",
    "addr:street":"Carrer De Lluis Martinell",
    "iso:country":"ES",
    "sg:address":"Carrer de Lluis Martinell, 2",
    "sg:city":"Valls",
    "sg:orig_category":"Asilos De Ancianos. Centros Privados",
    "sg:phone":"+34 977 60 63 23",
    "sg:postcode":"43800",
    "sg:province":"Tarragona",
    "wof:name":"Residencia Ballus S.l.",
    "wof:placetype":"venue"
},
  "geometry": {"coordinates":[1.2544349432,41.2912750244],"type":"Point"}
}