{
  "type": "Feature",
  "properties": {
    "addr:full":"Ctra Prat, 34 Barcelona Barcelona 08038",
    "addr:housenumber":"34",
    "addr:postcode":"08038",
    "addr:street":"Ctra Prat",
    "iso:country":"ES",
    "sg:address":"Ctra Prat, 34",
    "sg:city":"Barcelona",
    "sg:orig_category":"Internados & Ense\u00d1anza Privada",
    "sg:phone":"+34 934 21 61 99",
    "sg:postcode":"08038",
    "sg:province":"Barcelona",
    "wof:name":"Compa\u00f1ia Santa Teresa De Jesus",
    "wof:placetype":"venue"
},
  "geometry": {"coordinates":[2.1356201172,41.3624687195],"type":"Point"}
}