{
  "type": "Feature",
  "properties": {
    "addr:full":"Po Ganadero, S/n Alpera Albacete 02690",
    "addr:housenumber":"s / n",
    "addr:postcode":"02690",
    "iso:country":"ES",
    "sg:address":"Po Ganadero, S/n",
    "sg:city":"Alpera",
    "sg:orig_category":"Cooperativas Agr\u00cdcolas",
    "sg:phone":"+34 967 58 21 24",
    "sg:postcode":"02690",
    "sg:province":"Albacete",
    "wof:name":"Cooperativa Cinegetica De Alpera",
    "wof:placetype":"venue"
},
  "geometry": {"coordinates":[-1.2285660505,38.9572486877],"type":"Point"}
}