{
  "type": "Feature",
  "properties": {
    "addr:full":"Calle de Conde De Guadalhorce, S/n Malaga M\u00e1laga 29006",
    "addr:housenumber":"s / n",
    "addr:postcode":"29006",
    "addr:street":"Calle De Conde De Guadalhorce;Ma\u0301Laga",
    "iso:country":"ES",
    "sg:address":"Calle de Conde De Guadalhorce, S/n",
    "sg:city":"Malaga",
    "sg:orig_category":"Ense\u00d1anza, Formaci\u00d3n Profesional: Aprendizaje",
    "sg:phone":"+34 952 04 02 76",
    "sg:postcode":"29006",
    "sg:province":"M\u00e1laga",
    "wof:name":"Ayuntamiento De Malaga",
    "wof:placetype":"venue"
},
  "geometry": {"coordinates":[-4.441868782,36.714050293],"type":"Point"}
}