{
  "type": "Feature",
  "properties": {
    "iso:country":"ES",
    "sg:address":"Pol Ind La Azucarera, S/n",
    "sg:city":"Antequera",
    "sg:orig_category":"Venta, Instalaci\u00d3n De Cocinas",
    "sg:phone":"+34 952 84 59 56",
    "sg:postcode":"29200",
    "sg:province":"M\u00e1laga",
    "wof:name":"Pascual Ruiz Juan Rogelio",
    "wof:placetype":"venue"
},
  "geometry": {"coordinates":[-4.5636138916,37.0203018188],"type":"Point"}
}