{
  "type": "Feature",
  "properties": {
    "iso:country":"ES",
    "sg:address":"Calle de Julia Garcia Boutan, 29",
    "sg:city":"Madrid",
    "sg:orig_category":"Electricidad, Electr\u00d3nica: Suministros (al Por Menor)",
    "sg:phone":"+34 913 13 50 99",
    "sg:postcode":"28022",
    "sg:province":"Madrid",
    "wof:name":"Connecta Elementos Y Sistemas S.l.",
    "wof:placetype":"venue"
},
  "geometry": {"coordinates":[-3.6067221165,40.4302368164],"type":"Point"}
}