{
  "type": "Feature",
  "properties": {
    "iso:country":"ES",
    "sg:address":"Calle de Siguenza, 18",
    "sg:city":"Guadalajara",
    "sg:orig_category":"Cerrajer\u00cda, Ferrallista",
    "sg:phone":"+34 949 24 77 06",
    "sg:postcode":"19003",
    "sg:province":"Guadalajara",
    "wof:name":"Goncalves Farinha Enrique",
    "wof:placetype":"venue"
},
  "geometry": {"coordinates":[-3.1685540676,40.6269950867],"type":"Point"}
}