{
  "type": "Feature",
  "properties": {
    "iso:country":"ES",
    "sg:address":"Carrer de Manso, 49",
    "sg:city":"Barcelona",
    "sg:orig_category":"Marroquiner\u00cda (confecci\u00d3n)",
    "sg:phone":"+34 934 23 43 27",
    "sg:postcode":"08015",
    "sg:province":"Barcelona",
    "wof:name":"Temprado Artola Margarita",
    "wof:placetype":"venue"
},
  "geometry": {"coordinates":[2.1615719795,41.3776168823],"type":"Point"}
}