{
  "type": "Feature",
  "properties": {
    "iso:country":"ES",
    "sg:address":"Calle de Gran Via De Colon, 27",
    "sg:city":"Granada",
    "sg:orig_category":"Gafas (fabricaci\u00d3n)",
    "sg:phone":"+34 958 27 82 42",
    "sg:postcode":"18001",
    "sg:province":"Granada",
    "wof:name":"Acosta Medina Pablo",
    "wof:placetype":"venue"
},
  "geometry": {"coordinates":[-3.5992703438,37.1789093018],"type":"Point"}
}