{
  "type": "Feature",
  "properties": {
    "addr:full":"Ctra. Arcos-guadalcacin, S/n Arcos Frontera C\u00e1diz 11630",
    "addr:housenumber":"s",
    "addr:postcode":"11630",
    "addr:street":"Ctra. Arcos-Guadalcacin;/ N Arcos;Ca\u0301Diz",
    "iso:country":"ES",
    "sg:address":"Ctra. Arcos-guadalcacin, S/n",
    "sg:city":"Arcos Frontera",
    "sg:orig_category":"Producci\u00d3n, Venta De Productos De Agricultura Biol\u00d3gica",
    "sg:phone":"+34 956 70 22 55",
    "sg:postcode":"11630",
    "sg:province":"C\u00e1diz",
    "wof:name":"Agroconcejo S.l.",
    "wof:placetype":"venue"
},
  "geometry": {"coordinates":[-6.29240942,36.5299415588],"type":"Point"}
}