{
  "type": "Feature",
  "properties": {
    "addr:full":"Calle de Ejido (el), 21 Dos Hermanas Sevilla 41700",
    "addr:housenumber":"21",
    "addr:postcode":"41700",
    "addr:street":"Calle De Ejido El",
    "iso:country":"ES",
    "sg:address":"Calle de Ejido (el), 21",
    "sg:city":"Dos Hermanas",
    "sg:orig_category":"Promotores Constructores",
    "sg:phone":"+34 954 72 17 51",
    "sg:postcode":"41700",
    "sg:province":"Sevilla",
    "wof:name":"Clipeus S.a.",
    "wof:placetype":"venue"
},
  "geometry": {"coordinates":[-5.9281339645,37.2829055786],"type":"Point"}
}