{
  "type": "Feature",
  "properties": {
    "addr:full":"Calle de Izer, 2 Amorebieta Vizcaya 48340",
    "addr:housenumber":"2",
    "addr:postcode":"48340",
    "addr:street":"Calle De Izer",
    "iso:country":"ES",
    "sg:address":"Calle de Izer, 2",
    "sg:city":"Amorebieta",
    "sg:orig_category":"Servicio De Salud",
    "sg:phone":"+34 946 73 10 16",
    "sg:postcode":"48340",
    "sg:province":"Vizcaya",
    "wof:name":"Leonardo Azpiri S.a.",
    "wof:placetype":"venue"
},
  "geometry": {"coordinates":[-2.7369449139,43.2218475342],"type":"Point"}
}