{
  "type": "Feature",
  "properties": {
    "iso:country":"ES",
    "sg:address":"Calle de Espoz Y Mina, 1",
    "sg:city":"Madrid",
    "sg:orig_category":"Ropa Para Ni\u00d1os (al Por Menor)",
    "sg:phone":"+34 915 31 82 17",
    "sg:postcode":"28012",
    "sg:province":"Madrid",
    "wof:name":"Vazquez Simon Antonio",
    "wof:placetype":"venue"
},
  "geometry": {"coordinates":[-3.7021079063,40.4165458679],"type":"Point"}
}