{
  "type": "Feature",
  "properties": {
    "iso:country":"ES",
    "sg:address":"Calle de Barrio Verde, 1",
    "sg:city":"Tudela",
    "sg:orig_category":"Ropa Para Se\u00d1oras Y Caballeros (al Por Menor)",
    "sg:phone":"+34 948 82 21 62",
    "sg:postcode":"31500",
    "sg:province":"Navarra",
    "wof:name":"Cunchillos Perez Emilio",
    "wof:placetype":"venue"
},
  "geometry": {"coordinates":[-1.6021885872,42.0615768433],"type":"Point"}
}