{
  "type": "Feature",
  "properties": {
    "iso:country":"ES",
    "sg:address":"Av. Marie Curie, 15",
    "sg:city":"Granollers",
    "sg:orig_category":"Partidos Pol\u00cdticos",
    "sg:phone":"+34 938 40 03 81",
    "sg:postcode":"08400",
    "sg:province":"Barcelona",
    "wof:name":"Partit Dels Socialistes De Catalunya",
    "wof:placetype":"venue"
},
  "geometry": {"coordinates":[2.2889099121,41.6079521179],"type":"Point"}
}