{
  "type": "Feature",
  "properties": {
    "iso:country":"ES",
    "sg:address":"Horta, 21",
    "sg:city":"Selva Del Camp",
    "sg:orig_category":"Material Y Herramientas Agr\u00cdcolas",
    "sg:phone":"+34 977 84 43 62",
    "sg:postcode":"43470",
    "sg:province":"Tarragona",
    "wof:name":"Industries Garriga S.l.",
    "wof:placetype":"venue"
},
  "geometry": {"coordinates":[1.1412400007,41.2136268616],"type":"Point"}
}