{
  "type": "Feature",
  "properties": {
    "iso:country":"ES",
    "sg:address":"Calle de Farmaceutico Enrique Murillo Herrera, 5",
    "sg:city":"Sevilla",
    "sg:orig_category":"Pescader\u00cdas (al Por Menor)",
    "sg:phone":"+34 954 45 40 74",
    "sg:postcode":"41010",
    "sg:province":"Sevilla",
    "wof:name":"Leal Lagares Rosario",
    "wof:placetype":"venue"
},
  "geometry": {"coordinates":[-6.00167799,37.3807067871],"type":"Point"}
}