{
  "type": "Feature",
  "properties": {
    "addr:full":"Rond General Mitre, 206 Barcelona Barcelona 08006",
    "addr:housenumber":"206",
    "addr:postcode":"08006",
    "addr:street":"Mitre",
    "iso:country":"ES",
    "sg:address":"Rond General Mitre, 206",
    "sg:city":"Barcelona",
    "sg:orig_category":"Arquitectos",
    "sg:phone":"+34 932 18 09 99",
    "sg:postcode":"08006",
    "sg:province":"Barcelona",
    "sg:website":"www.coblonal.com",
    "wof:name":"Coblonal S.l.",
    "wof:placetype":"venue"
},
  "geometry": {"coordinates":[2.1458818913,41.405582428],"type":"Point"}
}