{
  "type": "Feature",
  "properties": {
    "addr:full":"Praz San Antonio (de), 4 Ourense Ourense 32004",
    "addr:postcode":"32004",
    "addr:street":"Praz San Antonio De",
    "iso:country":"ES",
    "sg:address":"Praz San Antonio (de), 4",
    "sg:city":"Ourense",
    "sg:orig_category":"Instalaci\u00d3n De Sanitarios",
    "sg:phone":"+34 988 39 23 17",
    "sg:postcode":"32004",
    "sg:province":"Ourense",
    "wof:name":"Lomba Borrajo Jose Maria",
    "wof:placetype":"venue"
},
  "geometry": {"coordinates":[-7.8511948586,42.3493232727],"type":"Point"}
}