{
  "type": "Feature",
  "properties": {
    "addr:full":"Calle de Obispo Rocamora, 28 Orihuela Alicante 03300",
    "addr:housenumber":"28",
    "addr:postcode":"03300",
    "addr:street":"Calle De Obispo Rocamora",
    "iso:country":"ES",
    "sg:address":"Calle de Obispo Rocamora, 28",
    "sg:city":"Orihuela",
    "sg:orig_category":"Quincaller\u00cda (al Por Menor)",
    "sg:phone":"+34 965 30 34 91",
    "sg:postcode":"03300",
    "sg:province":"Alicante",
    "wof:name":"Ferreteria Vega S.l.",
    "wof:placetype":"venue"
},
  "geometry": {"coordinates":[-0.9428120255,38.0833702087],"type":"Point"}
}