{
  "type": "Feature",
  "properties": {
    "iso:country":"ES",
    "sg:address":"Calle de Santa Teresa, 6",
    "sg:city":"Malaga",
    "sg:orig_category":"Plomeros",
    "sg:phone":"+34 952 33 01 63",
    "sg:postcode":"29006",
    "sg:province":"M\u00e1laga",
    "wof:name":"Martin Jurado Juan",
    "wof:placetype":"venue"
},
  "geometry": {"coordinates":[-4.4384131432,36.7143707275],"type":"Point"}
}