{
  "type": "Feature",
  "properties": {
    "iso:country":"ES",
    "sg:address":"Calle de Fundaciones (de Las), 33",
    "sg:city":"Colmenar Viejo",
    "sg:orig_category":"Agencias Y Agentes Comerciales, Representantes",
    "sg:phone":"+34 918 48 40 45",
    "sg:postcode":"28770",
    "sg:province":"Madrid",
    "wof:name":"Tercero Diaz Maria Del Carmen",
    "wof:placetype":"venue"
},
  "geometry": {"coordinates":[-3.7816879749,40.6658554077],"type":"Point"}
}