{
  "type": "Feature",
  "properties": {
    "iso:country":"ES",
    "sg:address":"Calle de Holanda, 8",
    "sg:city":"Gran Alacant",
    "sg:orig_category":"Agencias Y Agentes Comerciales, Representantes",
    "sg:phone":"+34 966 69 83 13",
    "sg:postcode":"03130",
    "sg:province":"Alicante",
    "wof:name":"Higgins  Thomas",
    "wof:placetype":"venue"
},
  "geometry": {"coordinates":[-0.5578309894,38.2048950195],"type":"Point"}
}