{
  "type": "Feature",
  "properties": {
    "iso:country":"ES",
    "sg:address":"Carr Escoles, S/n",
    "sg:city":"Artesa Segre",
    "sg:orig_category":"Negocio De Materiales De Construcci\u00d3n",
    "sg:phone":"+34 973 40 08 98",
    "sg:postcode":"25730",
    "sg:province":"Lleida",
    "wof:name":"Suministros Jovell S.l.",
    "wof:placetype":"venue"
},
  "geometry": {"coordinates":[1.0498579741,41.8959960938],"type":"Point"}
}