{
  "type": "Feature",
  "properties": {
    "iso:country":"ES",
    "sg:address":"Psaj Vicente Moliner, 5",
    "sg:city":"Puerto",
    "sg:orig_category":"Caf\u00c9s, Bares, Cervecer\u00cdas",
    "sg:phone":"+34 962 68 19 04",
    "sg:postcode":"46520",
    "sg:province":"Valencia",
    "wof:name":"Masni S.l.",
    "wof:placetype":"venue"
},
  "geometry": {"coordinates":[-0.2278539985,39.6646537781],"type":"Point"}
}