{
  "type": "Feature",
  "properties": {
    "addr:full":"Trva Concha De Armas, 1 Garachico Santa Cruz De Tenerife 38450",
    "addr:housenumber":"1",
    "addr:postcode":"38450",
    "addr:street":"Trva Concha De Armas",
    "iso:country":"ES",
    "sg:address":"Trva Concha De Armas, 1",
    "sg:city":"Garachico",
    "sg:orig_category":"Centros De Coordinaci\u00d3n",
    "sg:phone":"+34 922 13 30 10",
    "sg:postcode":"38450",
    "sg:province":"Santa Cruz De Tenerife",
    "wof:name":"Rodriguez Maradei Claudia",
    "wof:placetype":"venue"
},
  "geometry": {"coordinates":[-16.7653083801,28.3736457825],"type":"Point"}
}