{
  "type": "Feature",
  "properties": {
    "addr:full":"Pase Hortaz (del), 44 Tamarite Litera Huesca 22550",
    "addr:postcode":"22550",
    "iso:country":"ES",
    "sg:address":"Pase Hortaz (del), 44",
    "sg:city":"Tamarite Litera",
    "sg:orig_category":"Cajas Para Embalar",
    "sg:phone":"+34 974 42 01 25",
    "sg:postcode":"22550",
    "sg:province":"Huesca",
    "wof:name":"Caja Rural Aragonesa Y De Los Pirineos",
    "wof:placetype":"venue"
},
  "geometry": {"coordinates":[0.4240469933,41.8659324646],"type":"Point"}
}