{
  "type": "Feature",
  "properties": {
    "addr:full":"Calle de Eduardo Saavedra, 46 Soria Soria 42004",
    "addr:housenumber":"46",
    "addr:postcode":"42004",
    "addr:street":"Calle De Eduardo Saavedra",
    "iso:country":"ES",
    "sg:address":"Calle de Eduardo Saavedra, 46",
    "sg:city":"Soria",
    "sg:orig_category":"Seguros",
    "sg:phone":"+34 975 22 52 00",
    "sg:postcode":"42004",
    "sg:province":"Soria",
    "wof:name":"Madurga S.a.",
    "wof:placetype":"venue"
},
  "geometry": {"coordinates":[-2.4749250412,41.7588539124],"type":"Point"}
}