{
  "type": "Feature",
  "properties": {
    "iso:country":"ES",
    "sg:address":"Calle de Escuelas, S/n",
    "sg:city":"Rueda",
    "sg:orig_category":"Productores Recolectores, Venta Directa De Vinos",
    "sg:phone":"+34 983 86 82 92",
    "sg:postcode":"47490",
    "sg:province":"Valladolid",
    "sg:website":"www.grupoillguera.com",
    "wof:name":"Sat 2566 Grupo Yllera",
    "wof:placetype":"venue"
},
  "geometry": {"coordinates":[-4.9608469009,41.4137992859],"type":"Point"}
}