{
  "type": "Feature",
  "properties": {
    "iso:country":"ES",
    "sg:address":"Calle de Fuentenueva, 14",
    "sg:city":"Archidona",
    "sg:orig_category":"Molduras, Junquillos, Listones Y Molduras Perforadas",
    "sg:phone":"+34 952 71 70 39",
    "sg:postcode":"29300",
    "sg:province":"M\u00e1laga",
    "wof:name":"Fernandez Alvarez Mari Cruz",
    "wof:placetype":"venue"
},
  "geometry": {"coordinates":[-4.3907856941,37.0951728821],"type":"Point"}
}