{
  "type": "Feature",
  "properties": {
    "iso:country":"ES",
    "sg:address":"Calle de Menendez Pidal, 3",
    "sg:city":"Villa Don Fadrique",
    "sg:orig_category":"Plomeros",
    "sg:phone":"+34 925 19 55 87",
    "sg:postcode":"45850",
    "sg:province":"Toledo",
    "wof:name":"Aparicio Zaballas Jose Antonio",
    "wof:placetype":"venue"
},
  "geometry": {"coordinates":[-3.2200229168,39.6116790771],"type":"Point"}
}