{
  "type": "Feature",
  "properties": {
    "iso:country":"ES",
    "sg:address":"Calle de Maria Josefa Melgarejo, 2",
    "sg:city":"S. Clemente",
    "sg:orig_category":"Fabrica De Cer\u00c1micas",
    "sg:phone":"+34 969 30 09 48",
    "sg:postcode":"16600",
    "sg:province":"Cuenca",
    "wof:name":"Establecimientos Notario S.l.",
    "wof:placetype":"venue"
},
  "geometry": {"coordinates":[-2.4259209633,39.3982925415],"type":"Point"}
}