{
  "type": "Feature",
  "properties": {
    "addr:full":"Carr Sant Pere, 36 Gandia Valencia 46700",
    "addr:housenumber":"36",
    "addr:postcode":"46700",
    "addr:street":"Carr Sant Pere;Valencia",
    "iso:country":"ES",
    "sg:address":"Carr Sant Pere, 36",
    "sg:city":"Gandia",
    "sg:orig_category":"Ortopedia General",
    "sg:phone":"+34 962 86 25 20",
    "sg:postcode":"46700",
    "sg:province":"Valencia",
    "wof:name":"Ortopedia Paris S.l.",
    "wof:placetype":"venue"
},
  "geometry": {"coordinates":[-0.1913339943,38.960735321],"type":"Point"}
}