{
  "type": "Feature",
  "properties": {
    "addr:full":"Avda Santa Marina, 23 Badajoz Badajoz 06005",
    "addr:housenumber":"23",
    "addr:postcode":"06005",
    "addr:street":"Avda Santa Marina",
    "iso:country":"ES",
    "sg:address":"Avda Santa Marina, 23",
    "sg:city":"Badajoz",
    "sg:orig_category":"Transportes Por Carretera: Lotes Completos, Mercanc\u00cdas Diversas",
    "sg:phone":"+34 924 24 12 71",
    "sg:postcode":"06005",
    "sg:province":"Badajoz",
    "wof:name":"Grupo El Arbol Distribucion Y Supermercados S.a. Unipersonal",
    "wof:placetype":"venue"
},
  "geometry": {"coordinates":[-6.9784188271,38.8748397827],"type":"Point"}
}