{
  "type": "Feature",
  "properties": {
    "iso:country":"ES",
    "sg:address":"Av Europa, 110",
    "sg:city":"Hospitalet Llobregat",
    "sg:orig_category":"Tapiceros Y Tapiceros",
    "sg:phone":"+34 932 63 51 22",
    "sg:postcode":"08907",
    "sg:province":"Barcelona",
    "sg:website":"www.interiorismodelatorre.com",
    "wof:name":"Torre Cano Alfonso De La",
    "wof:placetype":"venue"
},
  "geometry": {"coordinates":[2.1144230366,41.3552818298],"type":"Point"}
}