{
  "type": "Feature",
  "properties": {
    "addr:full":"Calle de Real, 9 Pozo-lorente Albacete 02154",
    "addr:housenumber":"9",
    "addr:postcode":"02154",
    "addr:street":"Calle De Real",
    "iso:country":"ES",
    "sg:address":"Calle de Real, 9",
    "sg:city":"Pozo-lorente",
    "sg:orig_category":"Centros De Salud",
    "sg:phone":"+34 967 40 65 00",
    "sg:postcode":"02154",
    "sg:province":"Albacete",
    "wof:name":"Ayuntamiento De Pozo Lorente",
    "wof:placetype":"venue"
},
  "geometry": {"coordinates":[-1.5060664415,39.078327179],"type":"Point"}
}