{
  "type": "Feature",
  "properties": {
    "addr:full":"Ctra La Magdalena, S/n Guardo Palencia 34880",
    "addr:housenumber":"s / n",
    "addr:postcode":"34880",
    "addr:street":"Ctra La Magdalena",
    "iso:country":"ES",
    "sg:address":"Ctra La Magdalena, S/n",
    "sg:city":"Guardo",
    "sg:orig_category":"Empresas De Carpinter\u00cda De Madera",
    "sg:phone":"+34 979 85 04 29",
    "sg:postcode":"34880",
    "sg:province":"Palencia",
    "wof:name":"Rueda Nicolas Fernando",
    "wof:placetype":"venue"
},
  "geometry": {"coordinates":[-4.866874218,42.7786102295],"type":"Point"}
}