{
  "type": "Feature",
  "properties": {
    "addr:full":"Ctra. Villalonquejar, 58 Burgos Burgos 09001",
    "addr:housenumber":"58",
    "addr:postcode":"09001",
    "addr:street":"Ctra. Villalonquejar",
    "iso:country":"ES",
    "sg:address":"Ctra. Villalonquejar, 58",
    "sg:city":"Burgos",
    "sg:orig_category":"Peluquer\u00cdas, Peluquer\u00cda Mixta",
    "sg:phone":"+34 947 46 25 54",
    "sg:postcode":"09001",
    "sg:province":"Burgos",
    "wof:name":"Alia Mata Maria Del Puerto",
    "wof:placetype":"venue"
},
  "geometry": {"coordinates":[-3.7333819866,42.3491821289],"type":"Point"}
}