{
  "type": "Feature",
  "properties": {
    "iso:country":"ES",
    "sg:address":"El Pino-arca, 24",
    "sg:city":"Pino-pedrouzo",
    "sg:orig_category":"Estudios, Instalaci\u00d3n De Climatizaci\u00d3n",
    "sg:phone":"+34 981 81 43 07",
    "sg:postcode":"15821",
    "sg:province":"La Coru\u00f1a",
    "wof:name":"Compostela Boaire S.l.",
    "wof:placetype":"venue"
},
  "geometry": {"coordinates":[-8.3636646271,42.9042625427],"type":"Point"}
}