{
  "type": "Feature",
  "properties": {
    "addr:full":"Muelle Calvo S. Norte, S/n A Coru\u00f1a A Coru\u00f1a 15004",
    "addr:housenumber":"s / n",
    "addr:postcode":"15004",
    "addr:street":"Calvo;Norte;A Corun\u0303A A Corun\u0303A",
    "iso:country":"ES",
    "sg:address":"Muelle Calvo S. Norte, S/n",
    "sg:city":"A Coru\u00f1a",
    "sg:orig_category":"Barcos",
    "sg:phone":"+34 981 12 61 69",
    "sg:postcode":"15004",
    "sg:province":"A Coru\u00f1a",
    "wof:name":"Terminales Maritimos De Galicia S.l.",
    "wof:placetype":"venue"
},
  "geometry": {"coordinates":[-8.3967437744,43.3701553345],"type":"Point"}
}