{
  "type": "Feature",
  "properties": {
    "addr:full":"Carrer de Proven\u00c7a, 111 Barcelona Barcelona 08029",
    "addr:housenumber":"111",
    "addr:postcode":"08029",
    "addr:street":"Carrer De Provenc\u0327A",
    "iso:country":"ES",
    "sg:address":"Carrer de Proven\u00c7a, 111",
    "sg:city":"Barcelona",
    "sg:orig_category":"Carnicer\u00cdas, Carnicer\u00cdas",
    "sg:phone":"+34 934 54 95 71",
    "sg:postcode":"08029",
    "sg:province":"Barcelona",
    "wof:name":"Andres Vilaseca Maria Antonia",
    "wof:placetype":"venue"
},
  "geometry": {"coordinates":[2.1510794163,41.3869171143],"type":"Point"}
}