{
  "type": "Feature",
  "properties": {
    "addr:full":"Calle de Antonio Herrera, 16 Villanueva Ariscal Sevilla 41808",
    "addr:housenumber":"16",
    "addr:postcode":"41808",
    "addr:street":"Calle De Antonio Herrera",
    "iso:country":"ES",
    "sg:address":"Calle de Antonio Herrera, 16",
    "sg:city":"Villanueva Ariscal",
    "sg:orig_category":"Centros Empresariales",
    "sg:phone":"+34 954 11 36 72",
    "sg:postcode":"41808",
    "sg:province":"Sevilla",
    "wof:name":"Criollo Dorado Rosa Fabiola",
    "wof:placetype":"venue"
},
  "geometry": {"coordinates":[-6.142013073,37.3937301636],"type":"Point"}
}