{
  "type": "Feature",
  "properties": {
    "addr:full":"Ctra. Nazaret-oliva, S/n Daimus Valencia 46710",
    "addr:housenumber":"s",
    "addr:postcode":"46710",
    "addr:street":"Ctra. Nazaret-Oliva;/ N",
    "iso:country":"ES",
    "sg:address":"Ctra. Nazaret-oliva, S/n",
    "sg:city":"Daimus",
    "sg:orig_category":"Cooperativas Agr\u00cdcolas",
    "sg:phone":"+34 962 81 92 61",
    "sg:postcode":"46710",
    "sg:province":"Valencia",
    "wof:name":"Cooperativa Agricola De Gandia Coop. V.",
    "wof:placetype":"venue"
},
  "geometry": {"coordinates":[-0.1560789943,38.9696846008],"type":"Point"}
}