{
  "type": "Feature",
  "properties": {
    "addr:full":"Calle de Ense\u00d1anza, 6 Castellon Castell\u00f3n 12001",
    "addr:housenumber":"6",
    "addr:postcode":"12001",
    "addr:street":"Calle De Ensen\u0303Anza;Castello\u0301N",
    "iso:country":"ES",
    "sg:address":"Calle de Ense\u00d1anza, 6",
    "sg:city":"Castellon",
    "sg:orig_category":"Centros P\u00dablicos De Formaci\u00d3n Profesional Y T\u00c9cnica",
    "sg:phone":"+34 964 22 35 43",
    "sg:postcode":"12001",
    "sg:province":"Castell\u00f3n",
    "wof:name":"Hermandad Nacional De Arquitectos",
    "wof:placetype":"venue"
},
  "geometry": {"coordinates":[-0.0356649011,39.9876213074],"type":"Point"}
}