{
  "type": "Feature",
  "properties": {
    "addr:full":"Avda Arcadio Pardi\u00d1as, 141 Burela Lugo 27880",
    "addr:housenumber":"141",
    "addr:postcode":"27880",
    "addr:street":"Avda Arcadio Pardin\u0303As",
    "iso:country":"ES",
    "sg:address":"Avda Arcadio Pardi\u00d1as, 141",
    "sg:city":"Burela",
    "sg:orig_category":"Pescader\u00cdas (al Por Menor)",
    "sg:phone":"+34 982 58 55 82",
    "sg:postcode":"27880",
    "sg:province":"Lugo",
    "wof:name":"Fanego Prieto Maria Ramona",
    "wof:placetype":"venue"
},
  "geometry": {"coordinates":[-7.3576412201,43.6556816101],"type":"Point"}
}