{
  "type": "Feature",
  "properties": {
    "iso:country":"ES",
    "sg:address":"Carrer de Joncar, 47",
    "sg:city":"Barcelona",
    "sg:orig_category":"Arquitectos",
    "sg:phone":"+34 934 85 42 47",
    "sg:postcode":"08005",
    "sg:province":"Barcelona",
    "wof:name":"Segui Arquitectura, Sl",
    "wof:placetype":"venue"
},
  "geometry": {"coordinates":[2.2050569057,41.4018592834],"type":"Point"}
}