{
  "type": "Feature",
  "properties": {
    "addr:full":"Avda Ronda, 1 Macael Almer\u00eda 04867",
    "addr:housenumber":"1",
    "addr:postcode":"04867",
    "addr:street":"Avda Ronda",
    "iso:country":"ES",
    "sg:address":"Avda Ronda, 1",
    "sg:city":"Macael",
    "sg:orig_category":"Inmobiliaria (agencias)",
    "sg:phone":"+34 950 12 61 00",
    "sg:postcode":"04867",
    "sg:province":"Almer\u00eda",
    "wof:name":"Maf & Mand S.a.",
    "wof:placetype":"venue"
},
  "geometry": {"coordinates":[-2.3021855354,37.3355331421],"type":"Point"}
}