{
  "type": "Feature",
  "properties": {
    "addr:full":"Calle de Alberto Duce, 14 Zaragoza Zaragoza 50015",
    "addr:housenumber":"14",
    "addr:postcode":"50015",
    "addr:street":"Calle De Alberto Duce",
    "iso:country":"ES",
    "sg:address":"Calle de Alberto Duce, 14",
    "sg:city":"Zaragoza",
    "sg:orig_category":"Inform\u00c1tica: Material Y Suministros",
    "sg:phone":"+34 976 52 36 33",
    "sg:postcode":"50015",
    "sg:province":"Zaragoza",
    "sg:website":"www.memorycache.es",
    "wof:name":"Memory Cache S.l.",
    "wof:placetype":"venue"
},
  "geometry": {"coordinates":[-0.8866009712,41.6720809937],"type":"Point"}
}