{
  "type": "Feature",
  "properties": {
    "addr:full":"Calle de Bataneros, 11 A\u00d1ora C\u00f3rdoba 14450",
    "addr:housenumber":"11",
    "addr:postcode":"14450",
    "addr:street":"Calle De Bataneros;Co\u0301Rdoba",
    "iso:country":"ES",
    "sg:address":"Calle de Bataneros, 11",
    "sg:city":"A\u00d1ora",
    "sg:orig_category":"Trabajos De Perforaciones, Sondeos, Construcci\u00d3n De Pozos",
    "sg:phone":"+34 957 15 13 94",
    "sg:postcode":"14450",
    "sg:province":"C\u00f3rdoba",
    "wof:name":"Rubio Sanchez Placido",
    "wof:placetype":"venue"
},
  "geometry": {"coordinates":[-4.8982405663,38.4131774902],"type":"Point"}
}