{
  "type": "Feature",
  "properties": {
    "iso:country":"ES",
    "sg:address":"Carrer de Peru, 279",
    "sg:city":"Barcelona",
    "sg:orig_category":"Peluqueros: De Se\u00d1oras",
    "sg:phone":"+34 933 03 08 38",
    "sg:postcode":"08020",
    "sg:province":"Barcelona",
    "wof:name":"Garcia Atero Encarna",
    "wof:placetype":"venue"
},
  "geometry": {"coordinates":[2.2047290802,41.4150543213],"type":"Point"}
}