{
  "type": "Feature",
  "properties": {
    "iso:country":"ES",
    "sg:address":"Carrer de Coroleu, 78",
    "sg:city":"Barcelona",
    "sg:orig_category":"Centros De Coordinaci\u00d3n",
    "sg:phone":"+34 932 74 01 17",
    "sg:postcode":"08030",
    "sg:province":"Barcelona",
    "wof:name":"Gestoria Pascual Y Andres Asesores Asociados S.c.p.",
    "wof:placetype":"venue"
},
  "geometry": {"coordinates":[2.1847689152,41.4332427979],"type":"Point"}
}