{
  "type": "Feature",
  "properties": {
    "addr:full":"Calle de Ingeniero Juan De La Cierva, S/n Cordoba C\u00f3rdoba 14013",
    "addr:housenumber":"s / n",
    "addr:postcode":"14013",
    "addr:street":"Calle De Ingeniero Juan De La Cierva;Co\u0301Rdoba",
    "iso:country":"ES",
    "sg:address":"Calle de Ingeniero Juan De La Cierva, S/n",
    "sg:city":"Cordoba",
    "sg:orig_category":"Bancos",
    "sg:phone":"+34 957 29 64 11",
    "sg:postcode":"14013",
    "sg:province":"C\u00f3rdoba",
    "sg:website":"www.bancopopular.es",
    "wof:name":"Banco Popular Espa\u00f1ol",
    "wof:placetype":"venue"
},
  "geometry": {"coordinates":[-4.7913241386,37.8515510559],"type":"Point"}
}