{
  "type": "Feature",
  "properties": {
    "addr:full":"Plaz Bolamar, 10 Teruel Teruel 44001",
    "addr:housenumber":"10",
    "addr:postcode":"44001",
    "addr:street":"Plaz Bolamar",
    "iso:country":"ES",
    "sg:address":"Plaz Bolamar, 10",
    "sg:city":"Teruel",
    "sg:orig_category":"Ingeniero",
    "sg:phone":"+34 978 60 94 81",
    "sg:postcode":"44001",
    "sg:province":"Teruel",
    "wof:name":"Lozano Carreras Alberto",
    "wof:placetype":"venue"
},
  "geometry": {"coordinates":[-1.1049189568,40.3418388367],"type":"Point"}
}