{
  "type": "Feature",
  "properties": {
    "iso:country":"ES",
    "sg:address":"Avda Divina Pastora, 9",
    "sg:city":"Granada",
    "sg:orig_category":"M\u00c9dicos: Oftalmolog\u00cda",
    "sg:phone":"+34 958 29 11 41",
    "sg:postcode":"18012",
    "sg:province":"Granada",
    "wof:name":"Auriguiberri Gonzalez Javier",
    "wof:placetype":"venue"
},
  "geometry": {"coordinates":[-3.6025390625,37.1843833923],"type":"Point"}
}