{
  "type": "Feature",
  "properties": {
    "iso:country":"ES",
    "sg:address":"Avda Condes Santa Maria De Abona, 4",
    "sg:city":"Candelaria",
    "sg:orig_category":"Herboristas (al Por Menor)",
    "sg:phone":"+34 922 50 28 68",
    "sg:postcode":"38530",
    "sg:province":"Santa Cruz De Tenerife",
    "wof:name":"Lopez Herrera Maria Candelaria",
    "wof:placetype":"venue"
},
  "geometry": {"coordinates":[-16.3703460693,28.3546104431],"type":"Point"}
}