{
  "type": "Feature",
  "properties": {
    "addr:full":"Carrer de Moles, 31 Barcelona Barcelona 08002",
    "addr:housenumber":"31",
    "addr:postcode":"08002",
    "addr:street":"Carrer De Moles",
    "iso:country":"ES",
    "sg:address":"Carrer de Moles, 31",
    "sg:city":"Barcelona",
    "sg:orig_category":"Artes Gr\u00c1ficas, Artes Pl\u00c1sticas (curso)",
    "sg:phone":"+34 933 01 08 35",
    "sg:postcode":"08002",
    "sg:province":"Barcelona",
    "wof:name":"Masanas Forte Juan",
    "wof:placetype":"venue"
},
  "geometry": {"coordinates":[2.1723949909,41.3875579834],"type":"Point"}
}