{
  "type": "Feature",
  "properties": {
    "addr:full":"Calle de Dean Llopez, 71 Santa Pola Alicante 03130",
    "addr:housenumber":"71",
    "addr:postcode":"03130",
    "addr:street":"Calle De Dean Llopez",
    "iso:country":"ES",
    "sg:address":"Calle de Dean Llopez, 71",
    "sg:city":"Santa Pola",
    "sg:orig_category":"Electricidad: Instaladores",
    "sg:phone":"+34 965 41 25 79",
    "sg:postcode":"03130",
    "sg:province":"Alicante",
    "wof:name":"Cerda Montiel Lorenzo",
    "wof:placetype":"venue"
},
  "geometry": {"coordinates":[-0.5523002148,38.1919975281],"type":"Point"}
}