{
  "type": "Feature",
  "properties": {
    "addr:full":"Calle de Fatima, 11 Almachar M\u00e1laga 29718",
    "addr:housenumber":"11",
    "addr:postcode":"29718",
    "addr:street":"Calle De Fatima;Ma\u0301Laga",
    "iso:country":"ES",
    "sg:address":"Calle de Fatima, 11",
    "sg:city":"Almachar",
    "sg:orig_category":"Cajas Para Embalar",
    "sg:phone":"+34 952 51 21 92",
    "sg:postcode":"29718",
    "sg:province":"M\u00e1laga",
    "sg:website":"www.cajamar.es",
    "wof:name":"Cajamar",
    "wof:placetype":"venue"
},
  "geometry": {"coordinates":[-4.2171292305,36.8088111877],"type":"Point"}
}