{
  "type": "Feature",
  "properties": {
    "iso:country":"ES",
    "sg:address":"Carrer de Mossen Cinto Verdaguer, 6",
    "sg:city":"S. Antoni Vilamajor",
    "sg:orig_category":"Vinos Y Licores (venta Al Por Menor)",
    "sg:phone":"+34 938 45 10 01",
    "sg:postcode":"08459",
    "sg:province":"Barcelona",
    "wof:name":"Nicolau Pascual Juan",
    "wof:placetype":"venue"
},
  "geometry": {"coordinates":[2.3997049332,41.6725349426],"type":"Point"}
}