{
  "type": "Feature",
  "properties": {
    "iso:country":"ES",
    "sg:address":"Calle de Exarchs, 19",
    "sg:city":"Valencia",
    "sg:orig_category":"Confecci\u00d3n De Zapatos",
    "sg:phone":"+34 963 91 69 90",
    "sg:postcode":"46001",
    "sg:province":"Valencia",
    "wof:name":"Molina Domingo Vicente",
    "wof:placetype":"venue"
},
  "geometry": {"coordinates":[-0.3809680045,39.4743041992],"type":"Point"}
}