{
  "type": "Feature",
  "properties": {
    "iso:country":"ES",
    "sg:address":"Poli Talluntxe / Talluntze Industrialdea, 30",
    "sg:city":"Noain",
    "sg:orig_category":"Venta, Alquiler, Mantenimiento De Calderas",
    "sg:phone":"+34 948 31 86 04",
    "sg:postcode":"31110",
    "sg:province":"Navarra",
    "wof:name":"Servisol S.l.l.",
    "wof:placetype":"venue"
},
  "geometry": {"coordinates":[-1.6338239908,42.7598800659],"type":"Point"}
}