{
  "type": "Feature",
  "properties": {
    "addr:full":"Pla\u00c7 Hostals, 4 Santa Maria Del Cami Islas Baleares 07320",
    "addr:housenumber":"4",
    "addr:postcode":"07320",
    "addr:street":"Plac\u0327 Hostals;Islas",
    "iso:country":"ES",
    "sg:address":"Pla\u00c7 Hostals, 4",
    "sg:city":"Santa Maria Del Cami",
    "sg:orig_category":"Refiner\u00cdas De Petr\u00d3leo",
    "sg:phone":"+34 971 62 03 62",
    "sg:postcode":"07320",
    "sg:province":"Islas Baleares",
    "sg:website":"www.cepsa.es",
    "wof:name":"Ramis Ca\u00f1ellas Ramon",
    "wof:placetype":"venue"
},
  "geometry": {"coordinates":[2.7729899883,39.6510467529],"type":"Point"}
}