{
  "type": "Feature",
  "properties": {
    "addr:full":"Avda Indianos (los), 22 Santa Cruz Palma Santa Cruz De Tenerife 38700",
    "addr:housenumber":"22",
    "addr:postcode":"38700",
    "addr:street":"Avda Indianos Los",
    "iso:country":"ES",
    "sg:address":"Avda Indianos (los), 22",
    "sg:city":"Santa Cruz Palma",
    "sg:orig_category":"Teatro, Ballet, Danza (agrupaciones, Compa\u00d1\u00cdas)",
    "sg:phone":"+34 922 41 65 02",
    "sg:postcode":"38700",
    "sg:province":"Santa Cruz De Tenerife",
    "wof:name":"Coros Y Danzas De Santa Cruz De La Palma",
    "wof:placetype":"venue"
},
  "geometry": {"coordinates":[-17.7704353333,28.6771087646],"type":"Point"}
}