{
  "type": "Feature",
  "properties": {
    "iso:country":"ES",
    "sg:address":"Carrer de Catalunya, 103",
    "sg:city":"Castellar Valles",
    "sg:orig_category":"Empresas De Pintura Y Revestimientos",
    "sg:phone":"+34 937 14 61 30",
    "sg:postcode":"08211",
    "sg:province":"Barcelona",
    "wof:name":"Totespint S.l.",
    "wof:placetype":"venue"
},
  "geometry": {"coordinates":[2.0914959908,41.6147575378],"type":"Point"}
}