{
  "type": "Feature",
  "properties": {
    "iso:country":"ES",
    "sg:address":"Av Bases Manresa, 51",
    "sg:city":"Manresa",
    "sg:orig_category":"Asociaciones, Organismos Culturales Y Socioeducativos",
    "sg:phone":"+34 938 77 13 60",
    "sg:postcode":"08242",
    "sg:province":"Barcelona",
    "wof:name":"Ajuntament De Manresa",
    "wof:placetype":"venue"
},
  "geometry": {"coordinates":[1.8274054527,41.7365264893],"type":"Point"}
}