{
  "type": "Feature",
  "properties": {
    "iso:country":"ES",
    "sg:address":"Disseminat, S/n",
    "sg:city":"Sant Pere De Torello",
    "sg:orig_category":"Agricultores, Agricultores",
    "sg:phone":"+34 937 44 70 13",
    "sg:postcode":"08572",
    "sg:province":"Barcelona",
    "wof:name":"Granja Casabella Escarra S.c.p.",
    "wof:placetype":"venue"
},
  "geometry": {"coordinates":[2.2939250469,42.0749282837],"type":"Point"}
}