{
  "type": "Feature",
  "properties": {
    "addr:full":"Calle de Solanilla, S/n Loarre Huesca 22809",
    "addr:housenumber":"s / n",
    "addr:postcode":"22809",
    "addr:street":"Calle De Solanilla",
    "iso:country":"ES",
    "sg:address":"Calle de Solanilla, S/n",
    "sg:city":"Loarre",
    "sg:orig_category":"Cajas Para Embalar",
    "sg:phone":"+34 974 38 27 04",
    "sg:postcode":"22809",
    "sg:province":"Huesca",
    "wof:name":"Caja Rural Aragonesa Y De Los Pirineos",
    "wof:placetype":"venue"
},
  "geometry": {"coordinates":[-0.6252179742,42.3142662048],"type":"Point"}
}