{
  "type": "Feature",
  "properties": {
    "addr:full":"Pla\u00c7 Baltasar Mallent, S/n Burjassot Valencia 46100",
    "addr:postcode":"46100",
    "addr:street":"Mallent S / N",
    "iso:country":"ES",
    "sg:address":"Pla\u00c7 Baltasar Mallent, S/n",
    "sg:city":"Burjassot",
    "sg:orig_category":"Centros Empresariales",
    "sg:phone":"+34 963 64 54 21",
    "sg:postcode":"46100",
    "sg:province":"Valencia",
    "wof:name":"Asociacion Comerciantes Y Detallistas Mercado Municipal De Burjassot",
    "wof:placetype":"venue"
},
  "geometry": {"coordinates":[-0.4101619124,39.5090026855],"type":"Point"}
}