{
  "type": "Feature",
  "properties": {
    "addr:full":"Calle de Alfareria, S/n Coria Rio Sevilla 41100",
    "addr:housenumber":"s / n",
    "addr:postcode":"41100",
    "addr:street":"Calle De Alfareria;Rio Sevilla",
    "iso:country":"ES",
    "sg:address":"Calle de Alfareria, S/n",
    "sg:city":"Coria Rio",
    "sg:orig_category":"Chapister\u00cda",
    "sg:phone":"+34 954 77 23 43",
    "sg:postcode":"41100",
    "sg:province":"Sevilla",
    "wof:name":"Talleres Asian Lora S.l.",
    "wof:placetype":"venue"
},
  "geometry": {"coordinates":[-6.0588088036,37.2936782837],"type":"Point"}
}