{
  "type": "Feature",
  "properties": {
    "addr:full":"Major, 55 Almacelles Lleida 25100",
    "addr:housenumber":"55",
    "addr:postcode":"25100",
    "addr:street":"Major",
    "iso:country":"ES",
    "sg:address":"Major, 55",
    "sg:city":"Almacelles",
    "sg:orig_category":"Molduras, Junquillos, Listones Y Molduras Perforadas",
    "sg:phone":"+34 973 74 12 81",
    "sg:postcode":"25100",
    "sg:province":"Lleida",
    "wof:name":"Masgoret Escola Eloy",
    "wof:placetype":"venue"
},
  "geometry": {"coordinates":[0.4392879903,41.7298965454],"type":"Point"}
}