{
  "type": "Feature",
  "properties": {
    "iso:country":"ES",
    "sg:address":"Calle de Santa Rosa De Lima, 19",
    "sg:city":"Santa Cruz De Tenerife",
    "sg:classifiers":[
        {
            "category":"Professional",
            "subcategory":"Business Services",
            "type":"Services"
        }
    ],
    "sg:phone":"+34 922 29 14 44",
    "sg:postcode":"38002",
    "sg:province":"Santa Cruz De Tenerife",
    "sg:tags":[
        "control",
        "asesor\u00cda",
        "organizaci\u00d3n",
        "la",
        "de",
        "gesti\u00d3n",
        "y"
    ],
    "wof:name":"Cano Borges Rafael",
    "wof:placetype":"venue"
},
  "geometry": {"coordinates":[-16.2495174408,28.470533371],"type":"Point"}
}