{
  "type": "Feature",
  "properties": {
    "iso:country":"ES",
    "sg:address":"Avda Covadonga, 9",
    "sg:city":"Cangas Onis",
    "sg:orig_category":"Cl\u00cdnicas M\u00c9dicas",
    "sg:phone":"+34 985 84 90 36",
    "sg:postcode":"33550",
    "sg:province":"Asturias",
    "wof:name":"Clinica Cangas C.b.",
    "wof:placetype":"venue"
},
  "geometry": {"coordinates":[-5.1302847862,43.350894928],"type":"Point"}
}