{
  "type": "Feature",
  "properties": {
    "iso:country":"ES",
    "sg:address":"Av Generalitat De Catalunya, 17",
    "sg:city":"S. Just Desvern",
    "sg:orig_category":"Ingeniero",
    "sg:phone":"+34 934 80 26 70",
    "sg:postcode":"08960",
    "sg:province":"Barcelona",
    "wof:name":"Rodriguez Vives Remigio",
    "wof:placetype":"venue"
},
  "geometry": {"coordinates":[2.0733160973,41.3786277771],"type":"Point"}
}