{
  "type": "Feature",
  "properties": {
    "iso:country":"ES",
    "sg:address":"Ptda Zafarich, 36",
    "sg:city":"Monovar",
    "sg:orig_category":"Zapatos: Material, Suministros, Accesorios (fabricaci\u00d3n, Al Por Mayor)",
    "sg:phone":"+34 965 47 10 07",
    "sg:postcode":"03640",
    "sg:province":"Alicante",
    "wof:name":"Palazon Alonso Jose",
    "wof:placetype":"venue"
},
  "geometry": {"coordinates":[-0.8396289945,38.434135437],"type":"Point"}
}