{
  "type": "Feature",
  "properties": {
    "iso:country":"ES",
    "sg:address":"Avda Burgos, 20",
    "sg:city":"Aranda Duero",
    "sg:orig_category":"Extinci\u00d3n De Incendios: Material Y Suministros (fabricaci\u00d3n, Al Por Mayor)",
    "sg:phone":"+34 947 50 67 29",
    "sg:postcode":"09400",
    "sg:province":"Burgos",
    "wof:name":"Extintores Castellanoleoneses Sl",
    "wof:placetype":"venue"
},
  "geometry": {"coordinates":[-3.6791660786,41.66954422],"type":"Point"}
}