{
  "type": "Feature",
  "properties": {
    "addr:full":"Plaz San Lucas, 7 Jerez De La Frontera C\u00e1diz 11403",
    "addr:postcode":"11403",
    "addr:street":"Plaz",
    "iso:country":"ES",
    "sg:address":"Plaz San Lucas, 7",
    "sg:city":"Jerez De La Frontera",
    "sg:orig_category":"Asociaciones, Organismos Culturales Y Socioeducativos",
    "sg:phone":"+34 956 33 84 04",
    "sg:postcode":"11403",
    "sg:province":"C\u00e1diz",
    "wof:name":"Pe\u00f1a Flamenca Buena Gente",
    "wof:placetype":"venue"
},
  "geometry": {"coordinates":[-6.143029213,36.6850471497],"type":"Point"}
}