{
  "type": "Feature",
  "properties": {
    "addr:full":"Calle de Romeral, 6 Rozas De Madrid Madrid 28230",
    "addr:housenumber":"6",
    "addr:postcode":"28230",
    "addr:street":"Calle De Romeral",
    "iso:country":"ES",
    "sg:address":"Calle de Romeral, 6",
    "sg:city":"Rozas De Madrid",
    "sg:orig_category":"Centros De Reservas Hoteleras",
    "sg:phone":"+34 916 37 62 12",
    "sg:postcode":"28230",
    "sg:province":"Madrid",
    "wof:name":"Kukla Nunez Hugo",
    "wof:placetype":"venue"
},
  "geometry": {"coordinates":[-3.8735091686,40.4928245544],"type":"Point"}
}