{
  "type": "Feature",
  "properties": {
    "addr:full":"Calle de Conde Torreanaz, 6 Torrelavega Cantabria 39300",
    "addr:housenumber":"6",
    "addr:postcode":"39300",
    "addr:street":"Calle De Conde Torreanaz",
    "iso:country":"ES",
    "sg:address":"Calle de Conde Torreanaz, 6",
    "sg:city":"Torrelavega",
    "sg:orig_category":"Tintes (fabricaci\u00d3n, Al Por Mayor)",
    "sg:phone":"+34 942 81 31 84",
    "sg:postcode":"39300",
    "sg:province":"Cantabria",
    "wof:name":"Garcia Pecharroman Miguel",
    "wof:placetype":"venue"
},
  "geometry": {"coordinates":[-4.0476102829,43.3514938354],"type":"Point"}
}