{
  "type": "Feature",
  "properties": {
    "iso:country":"ES",
    "sg:address":"Calle de Portuetxe, 83",
    "sg:city":"Donostia-san Sebastian",
    "sg:orig_category":"Inform\u00c1tica, Ofim\u00c1tica (estudios, Asesor\u00cda, Ingenier\u00cda, Formaci\u00d3n)",
    "sg:phone":"+34 943 21 39 11",
    "sg:postcode":"20018",
    "sg:province":"Guip\u00f9zcoa",
    "sg:website":"www.aranbide.com",
    "wof:name":"Aranbide Material De Oficina E Informatica S. L.",
    "wof:placetype":"venue"
},
  "geometry": {"coordinates":[-2.018679142,43.3009719849],"type":"Point"}
}