{
  "type": "Feature",
  "properties": {
    "iso:country":"ES",
    "sg:address":"Av Mare De Deu De Montserrat, 38",
    "sg:city":"Poligon Industrial De Sant Pere Molanta",
    "sg:orig_category":"Suministros Para Carrocer\u00cdas",
    "sg:phone":"+34 938 92 46 30",
    "sg:postcode":"08799",
    "sg:province":"Barcelona",
    "wof:name":"Carroceries Serca S.l.",
    "wof:placetype":"venue"
},
  "geometry": {"coordinates":[1.7381500006,41.3486938477],"type":"Point"}
}