{
  "type": "Feature",
  "properties": {
    "addr:full":"Calle de Luis Rosales, S/n Ogijares Granada 18151",
    "addr:postcode":"18151",
    "addr:street":"Calle De Luis Rosales S / N Ogijares",
    "iso:country":"ES",
    "sg:address":"Calle de Luis Rosales, S/n",
    "sg:city":"Ogijares",
    "sg:orig_category":"Peluqueros: De Se\u00d1oras",
    "sg:phone":"+34 958 50 64 17",
    "sg:postcode":"18151",
    "sg:province":"Granada",
    "wof:name":"Garrido Garcia Francisco",
    "wof:placetype":"venue"
},
  "geometry": {"coordinates":[-3.6074519157,37.1203689575],"type":"Point"}
}