{
  "type": "Feature",
  "properties": {
    "addr:full":"Lo Rat Penat, 32 Puig Valencia 46540",
    "addr:housenumber":"32",
    "addr:postcode":"46540",
    "addr:street":"Penat",
    "iso:country":"ES",
    "sg:address":"Lo Rat Penat, 32",
    "sg:city":"Puig",
    "sg:classifiers":[
        {
            "category":"Professional",
            "subcategory":"Business Services",
            "type":"Services"
        }
    ],
    "sg:phone":"+34 961 47 29 23",
    "sg:postcode":"46540",
    "sg:province":"Valencia",
    "sg:tags":[
        "control",
        "asesor\u00cda",
        "organizaci\u00d3n",
        "la",
        "de",
        "gesti\u00d3n",
        "y"
    ],
    "wof:name":"Implantaciones De Sistemas De Gestion S.l.",
    "wof:placetype":"venue"
},
  "geometry": {"coordinates":[-0.3048729897,39.5888710022],"type":"Point"}
}