{
  "type": "Feature",
  "properties": {
    "addr:full":"Calle de Monasterio De Montes, 6 Ponferrada Le\u00f3n 24400",
    "addr:housenumber":"6",
    "addr:postcode":"24400",
    "addr:street":"Calle De Monasterio De Montes",
    "iso:country":"ES",
    "sg:address":"Calle de Monasterio De Montes, 6",
    "sg:city":"Ponferrada",
    "sg:orig_category":"M\u00c9dicos: Estomatolog\u00cda",
    "sg:phone":"+34 987 42 66 61",
    "sg:postcode":"24400",
    "sg:province":"Le\u00f3n",
    "wof:name":"Blanco Silvan Maria Del Carmen",
    "wof:placetype":"venue"
},
  "geometry": {"coordinates":[-6.5872859955,42.5471076965],"type":"Point"}
}