{
  "type": "Feature",
  "properties": {
    "addr:full":"Calle de Carmen, 26 Pe\u00e7aranda De Bracamonte Salamanca 37300",
    "addr:housenumber":"26",
    "addr:postcode":"37300",
    "addr:street":"Calle De Carmen",
    "iso:country":"ES",
    "sg:address":"Calle de Carmen, 26",
    "sg:city":"Pe\u00e7aranda De Bracamonte",
    "sg:orig_category":"Ropa Para Se\u00d1oras Y Caballeros (al Por Menor)",
    "sg:phone":"+34 923 54 14 95",
    "sg:postcode":"37300",
    "sg:province":"Salamanca",
    "wof:name":"Sanchez Sanchez Rufino",
    "wof:placetype":"venue"
},
  "geometry": {"coordinates":[-5.6630473137,40.9649734497],"type":"Point"}
}