{
  "type": "Feature",
  "properties": {
    "addr:full":"Calle de Miramar, 4 Taliarte Las Palmas 35214",
    "addr:housenumber":"4",
    "addr:postcode":"35214",
    "addr:street":"Calle De Miramar;Las Palmas",
    "iso:country":"ES",
    "sg:address":"Calle de Miramar, 4",
    "sg:city":"Taliarte",
    "sg:orig_category":"Zapatos (al Por Menor)",
    "sg:phone":"+34 928 70 62 04",
    "sg:postcode":"35214",
    "sg:province":"Las Palmas",
    "wof:name":"Magacon S.l.",
    "wof:placetype":"venue"
},
  "geometry": {"coordinates":[-15.3887634277,27.9937648773],"type":"Point"}
}