{
  "type": "Feature",
  "properties": {
    "addr:full":"Avda Antonio Hurtado, 20 Caceres C\u00e1ceres 10002",
    "addr:housenumber":"20",
    "addr:postcode":"10002",
    "addr:street":"Avda Antonio Hurtado;Ca\u0301Ceres",
    "iso:country":"ES",
    "sg:address":"Avda Antonio Hurtado, 20",
    "sg:city":"Caceres",
    "sg:orig_category":"Peluquer\u00cdas",
    "sg:phone":"+34 927 26 04 98",
    "sg:postcode":"10002",
    "sg:province":"C\u00e1ceres",
    "wof:name":"Nu\u00f1ez Molano Noelia",
    "wof:placetype":"venue"
},
  "geometry": {"coordinates":[-6.3768348694,39.4658546448],"type":"Point"}
}