{
  "type": "Feature",
  "properties": {
    "iso:country":"ES",
    "sg:address":"Avda Moris Marrodan, S/n",
    "sg:city":"Martos",
    "sg:orig_category":"Autob\u00das (explotaci\u00d3n Y Servicios De)",
    "sg:phone":"+34 953 55 00 67",
    "sg:postcode":"23600",
    "sg:province":"Ja\u00e9n",
    "wof:name":"Transportes Ure\u00f1a S. A.",
    "wof:placetype":"venue"
},
  "geometry": {"coordinates":[-3.9721429348,37.7167625427],"type":"Point"}
}