{
  "type": "Feature",
  "properties": {
    "iso:country":"ES",
    "sg:address":"Calle de Imagen, 27",
    "sg:city":"Madrid",
    "sg:orig_category":"Agentes, Concesionarios Y Sucursales De Camiones Y Veh\u00cdculos Industriales",
    "sg:phone":"+34 915 07 36 87",
    "sg:postcode":"28018",
    "sg:province":"Madrid",
    "wof:name":"Yocrisa Motor S.l.",
    "wof:placetype":"venue"
},
  "geometry": {"coordinates":[-3.7720558643,40.548412323],"type":"Point"}
}