{
  "type": "Feature",
  "properties": {
    "iso:country":"ES",
    "sg:address":"Calle de San Juan Bosco, 43",
    "sg:city":"Valencia",
    "sg:orig_category":"Aparcamientos (infraestructuras, Accesorios)",
    "sg:phone":"+34 963 66 08 58",
    "sg:postcode":"46019",
    "sg:province":"Valencia",
    "wof:name":"Alfonso Llorens Fernando",
    "wof:placetype":"venue"
},
  "geometry": {"coordinates":[-0.3721478879,39.4928283691],"type":"Point"}
}