{
  "type": "Feature",
  "properties": {
    "iso:country":"ES",
    "sg:address":"Avda Habana (la), 14",
    "sg:city":"Cristianos",
    "sg:orig_category":"Asesor\u00cda Fiscal Y Jur\u00cddica",
    "sg:phone":"+34 922 79 26 82",
    "sg:postcode":"38650",
    "sg:province":"Santa Cruz De Tenerife",
    "wof:name":"C&r Advising Services S.l.",
    "wof:placetype":"venue"
},
  "geometry": {"coordinates":[-16.7244701385,28.0545520782],"type":"Point"}
}