{
  "type": "Feature",
  "properties": {
    "addr:full":"Avda Champagnat, 79 Salamanca Salamanca 37007",
    "addr:housenumber":"79",
    "addr:postcode":"37007",
    "addr:street":"Avda Champagnat",
    "iso:country":"ES",
    "sg:address":"Avda Champagnat, 79",
    "sg:city":"Salamanca",
    "sg:orig_category":"Comunidades Religiosas",
    "sg:phone":"+34 923 23 11 73",
    "sg:postcode":"37007",
    "sg:province":"Salamanca",
    "wof:name":"Religiosas De Cristo Sacerdote",
    "wof:placetype":"venue"
},
  "geometry": {"coordinates":[-5.6752700806,40.9688186646],"type":"Point"}
}