{
  "type": "Feature",
  "properties": {
    "addr:full":"Calle de Andalucia, 4 Alaquas Valencia 46970",
    "addr:housenumber":"4",
    "addr:postcode":"46970",
    "addr:street":"Calle De Andalucia",
    "iso:country":"ES",
    "sg:address":"Calle de Andalucia, 4",
    "sg:city":"Alaquas",
    "sg:orig_category":"Abogados",
    "sg:phone":"+34 961 51 52 03",
    "sg:postcode":"46970",
    "sg:province":"Valencia",
    "wof:name":"Aparici Y Moya Via Ejecutiva Legal C.b.",
    "wof:placetype":"venue"
},
  "geometry": {"coordinates":[-0.4194417894,39.4776649475],"type":"Point"}
}