{
  "type": "Feature",
  "properties": {
    "iso:country":"ES",
    "sg:address":"Malaga, S/n",
    "sg:city":"Valdemoro",
    "sg:orig_category":"Puertas Y Portales",
    "sg:phone":"+34 918 95 62 79",
    "sg:postcode":"28340",
    "sg:province":"Madrid",
    "wof:name":"Cerrainver Sl",
    "wof:placetype":"venue"
},
  "geometry": {"coordinates":[-3.6738090515,40.1909751892],"type":"Point"}
}