{
  "type": "Feature",
  "properties": {
    "addr:full":"Calle de Fortuny, 3 Mostoles Madrid 28933",
    "addr:housenumber":"3",
    "addr:postcode":"28933",
    "addr:street":"Calle De Fortuny",
    "iso:country":"ES",
    "sg:address":"Calle de Fortuny, 3",
    "sg:city":"Mostoles",
    "sg:orig_category":"Caf\u00c9s, Bares, Cervecer\u00cdas",
    "sg:phone":"+34 916 14 52 04",
    "sg:postcode":"28933",
    "sg:province":"Madrid",
    "wof:name":"Izco S.l.",
    "wof:placetype":"venue"
},
  "geometry": {"coordinates":[-3.8637440205,40.3276596069],"type":"Point"}
}