{
  "type": "Feature",
  "properties": {
    "iso:country":"ES",
    "sg:address":"Pl Eguilaz, 9",
    "sg:city":"Barcelona",
    "sg:orig_category":"Pod\u00d3logos: Pedicuros",
    "sg:phone":"+34 932 05 17 77",
    "sg:postcode":"08017",
    "sg:province":"Barcelona",
    "wof:name":"Cbp Flaire S.l.",
    "wof:placetype":"venue"
},
  "geometry": {"coordinates":[2.1320910454,41.3939437866],"type":"Point"}
}