{
  "type": "Feature",
  "properties": {
    "iso:country":"ES",
    "sg:address":"Calle de Carrascos, 2",
    "sg:city":"Sangonera La Verde O Ermita Nueva",
    "sg:orig_category":"Electrodom\u00c9sticos (fabricaci\u00d3n, Al Por Mayor)",
    "sg:phone":"+34 968 86 80 00",
    "sg:postcode":"30833",
    "sg:province":"Murcia",
    "wof:name":"Electrodomesticos Sanmur S.l.",
    "wof:placetype":"venue"
},
  "geometry": {"coordinates":[-1.2131119967,37.9312362671],"type":"Point"}
}