{
  "type": "Feature",
  "properties": {
    "addr:full":"Avda San Martin De Valdeiglesias, Km. 0001,8 Quijorna Madrid 28693",
    "addr:postcode":"28693",
    "addr:street":"Avda San Martin De Valdeiglesias Km. 0001,8",
    "iso:country":"ES",
    "sg:address":"Avda San Martin De Valdeiglesias, Km. 0001,8",
    "sg:city":"Quijorna",
    "sg:orig_category":"Alquiler De Gr\u00daas",
    "sg:phone":"+34 918 16 83 03",
    "sg:postcode":"28693",
    "sg:province":"Madrid",
    "wof:name":"Marino Ruiz Oliva Y Otros C.b.",
    "wof:placetype":"venue"
},
  "geometry": {"coordinates":[-4.0565438271,40.4243659973],"type":"Point"}
}