{
  "type": "Feature",
  "properties": {
    "iso:country":"ES",
    "sg:address":"Plaz Andramariko, 8",
    "sg:city":"Amorebieta",
    "sg:orig_category":"Agencias De Trabajo Temporal",
    "sg:phone":"+34 946 30 93 84",
    "sg:postcode":"48340",
    "sg:province":"Vizcaya",
    "sg:website":"www.adecco.es",
    "wof:name":"Adecco E.t.t. S.a.",
    "wof:placetype":"venue"
},
  "geometry": {"coordinates":[-2.7324244976,43.2180366516],"type":"Point"}
}