{
  "type": "Feature",
  "properties": {
    "addr:full":"Avda Martinez De Velasco, 40 Huesca Huesca 22004",
    "addr:housenumber":"40",
    "addr:postcode":"22004",
    "addr:street":"Avda Martinez De Velasco",
    "iso:country":"ES",
    "sg:address":"Avda Martinez De Velasco, 40",
    "sg:city":"Huesca",
    "sg:orig_category":"Florister\u00cdas",
    "sg:phone":"+34 974 21 43 70",
    "sg:postcode":"22004",
    "sg:province":"Huesca",
    "wof:name":"Calero Garcia Juana Mercedes",
    "wof:placetype":"venue"
},
  "geometry": {"coordinates":[-0.4185419977,42.1321029663],"type":"Point"}
}