{
  "type": "Feature",
  "properties": {
    "addr:full":"Riera Del Pare Fita, 20 Arenys Mar Barcelona 08350",
    "addr:housenumber":"20",
    "addr:postcode":"08350",
    "addr:street":"Riera Del Pare Fita",
    "iso:country":"ES",
    "sg:address":"Riera Del Pare Fita, 20",
    "sg:city":"Arenys Mar",
    "sg:orig_category":"Cajas De Ahorro",
    "sg:phone":"+34 937 92 33 20",
    "sg:postcode":"08350",
    "sg:province":"Barcelona",
    "wof:name":"Caixa De Girona",
    "wof:placetype":"venue"
},
  "geometry": {"coordinates":[2.5484321117,41.583026886],"type":"Point"}
}