{
  "type": "Feature",
  "properties": {
    "addr:full":"Calle de Asturias, 2 Gijon Asturias 33206",
    "addr:housenumber":"2",
    "addr:postcode":"33206",
    "addr:street":"Calle De Asturias",
    "iso:country":"ES",
    "sg:address":"Calle de Asturias, 2",
    "sg:city":"Gijon",
    "sg:orig_category":"Abogados",
    "sg:phone":"+34 985 35 07 54",
    "sg:postcode":"33206",
    "sg:province":"Asturias",
    "wof:name":"De La Fuente Fernandez Andres Emilio",
    "wof:placetype":"venue"
},
  "geometry": {"coordinates":[-5.6638560295,43.5402259827],"type":"Point"}
}