{
  "type": "Feature",
  "properties": {
    "addr:full":"Calle de Zubileta, 27 San Vicente De Barakaldo Vizcaya 48903",
    "addr:housenumber":"27",
    "addr:postcode":"48903",
    "addr:street":"Calle De Zubileta",
    "iso:country":"ES",
    "sg:address":"Calle de Zubileta, 27",
    "sg:city":"San Vicente De Barakaldo",
    "sg:orig_category":"Fabricaci\u00d3n De Muebles Y De Accesorios De Cuartos De Ba\u00d1o",
    "sg:phone":"+34 944 99 01 72",
    "sg:postcode":"48903",
    "sg:province":"Vizcaya",
    "wof:name":"Mobiliario Bilko S.l.",
    "wof:placetype":"venue"
},
  "geometry": {"coordinates":[-2.9777140617,43.2733192444],"type":"Point"}
}