{
  "type": "Feature",
  "properties": {
    "addr:full":"Avda Baviera, 7 Madrid Madrid 28028",
    "addr:housenumber":"7",
    "addr:postcode":"madrid;28028",
    "addr:street":"Avda Baviera",
    "iso:country":"ES",
    "sg:address":"Avda Baviera, 7",
    "sg:city":"Madrid",
    "sg:orig_category":"Peluqueros: De Se\u00d1oras",
    "sg:phone":"+34 917 26 62 91",
    "sg:postcode":"28028",
    "sg:province":"Madrid",
    "wof:name":"Alonso Rodriguez Maria Dolores",
    "wof:placetype":"venue"
},
  "geometry": {"coordinates":[-3.6636753082,40.4421272278],"type":"Point"}
}