{
  "type": "Feature",
  "properties": {
    "addr:full":"Calle de Artesa De Segre, 5 Madrid Madrid 28035",
    "addr:housenumber":"5",
    "addr:postcode":"28035",
    "addr:street":"Calle De Artesa De Segre",
    "iso:country":"ES",
    "sg:address":"Calle de Artesa De Segre, 5",
    "sg:city":"Madrid",
    "sg:orig_category":"Frutas, Legumbres Frescas Y Tempranas (al Por Menor)",
    "sg:phone":"+34 913 16 93 56",
    "sg:postcode":"28035",
    "sg:province":"Madrid",
    "wof:name":"Vela Gil Angeles",
    "wof:placetype":"venue"
},
  "geometry": {"coordinates":[-3.7275109291,40.4696578979],"type":"Point"}
}