{
  "type": "Feature",
  "properties": {
    "addr:full":"Rond Buenavista, 23 Toledo Toledo 45005",
    "addr:housenumber":"23",
    "addr:postcode":"45005",
    "addr:street":"Buenavista",
    "iso:country":"ES",
    "sg:address":"Rond Buenavista, 23",
    "sg:city":"Toledo",
    "sg:orig_category":"Construcci\u00d3n De Edificios Residenciales Y No Residenciales",
    "sg:phone":"+34 925 25 47 41",
    "sg:postcode":"45005",
    "sg:province":"Toledo",
    "sg:website":"www.tecmave.com",
    "wof:name":"Construcciones Tecmave S.l.",
    "wof:placetype":"venue"
},
  "geometry": {"coordinates":[-4.0404000282,39.8759918213],"type":"Point"}
}