{
  "type": "Feature",
  "properties": {
    "addr:full":"Plaza Alta Y Baja, 7 Lucena C\u00f3rdoba 14900",
    "addr:housenumber":"7",
    "addr:postcode":"14900",
    "addr:street":"Baja",
    "iso:country":"ES",
    "sg:address":"Plaza Alta Y Baja, 7",
    "sg:city":"Lucena",
    "sg:orig_category":"Fabricaci\u00d3n De Productos Textiles Sin Tejer",
    "sg:phone":"+34 957 50 02 77",
    "sg:postcode":"14900",
    "sg:province":"C\u00f3rdoba",
    "wof:name":"Osuna Jimenez Jose",
    "wof:placetype":"venue"
},
  "geometry": {"coordinates":[-4.4836421013,37.4092559814],"type":"Point"}
}