{
  "type": "Feature",
  "properties": {
    "iso:country":"ES",
    "sg:address":"Rua Alfonso Xii, 6",
    "sg:city":"Redondela",
    "sg:orig_category":"M\u00c9dicos: Estomatolog\u00cda",
    "sg:phone":"+34 986 40 05 59",
    "sg:postcode":"36800",
    "sg:province":"Pontevedra",
    "wof:name":"Alfaya Ocampo Teresa De Lourdes",
    "wof:placetype":"venue"
},
  "geometry": {"coordinates":[-8.6088972092,42.2833595276],"type":"Point"}
}