{
  "type": "Feature",
  "properties": {
    "addr:full":"Plaz Constitucion, 5 Biar Alicante 03410",
    "addr:housenumber":"5",
    "addr:postcode":"03410",
    "addr:street":"Constitucion",
    "iso:country":"ES",
    "sg:address":"Plaz Constitucion, 5",
    "sg:city":"Biar",
    "sg:orig_category":"Iglesia Cat\u00d3lica",
    "sg:phone":"+34 965 81 06 74",
    "sg:postcode":"03410",
    "sg:province":"Alicante",
    "wof:name":"Parroquia De Ntra Sra De La Asuncion De Bihar",
    "wof:placetype":"venue"
},
  "geometry": {"coordinates":[-0.7657520175,38.6301879883],"type":"Point"}
}