{
  "type": "Feature",
  "properties": {
    "iso:country":"ES",
    "sg:address":"Calle de Cobre (pol. Ind.), 15",
    "sg:city":"Marbella",
    "sg:orig_category":"Chapister\u00cda",
    "sg:phone":"+34 952 89 89 73",
    "sg:postcode":"29600",
    "sg:province":"M\u00e1laga",
    "wof:name":"Taller Chapa Y Pintura Sando S.ll.",
    "wof:placetype":"venue"
},
  "geometry": {"coordinates":[-4.8676810265,36.5114898682],"type":"Point"}
}