{
  "type": "Feature",
  "properties": {
    "iso:country":"ES",
    "sg:address":"Calle de Acevi\u00d1o Guajara, S/n",
    "sg:city":"Guajara",
    "sg:orig_category":"Centros Comerciales Y Grandes Tiendas",
    "sg:phone":"+34 922 82 40 82",
    "sg:postcode":"38296",
    "sg:province":"Santa Cruz De Tenerife",
    "wof:name":"Restotel S.l.",
    "wof:placetype":"venue"
},
  "geometry": {"coordinates":[-16.2548561096,28.4698104858],"type":"Point"}
}