{
  "type": "Feature",
  "properties": {
    "iso:country":"ES",
    "sg:address":"Pol Ind El Calvario, S/n",
    "sg:city":"Villanueva Reina",
    "sg:orig_category":"Producci\u00d3n De Abonos Y De Fertilizantes",
    "sg:phone":"+34 953 53 70 53",
    "sg:postcode":"23730",
    "sg:province":"Ja\u00e9n",
    "wof:name":"Productos Auxiliares Medioambientales S.l.",
    "wof:placetype":"venue"
},
  "geometry": {"coordinates":[-3.9147191048,38.0040740967],"type":"Point"}
}