{
  "type": "Feature",
  "properties": {
    "addr:full":"Calle de Doctor Vila, 9 Rua De Valdeorras Ourense 32350",
    "addr:housenumber":"9",
    "addr:postcode":"32350",
    "addr:street":"Calle De Doctor Vila;Rua De",
    "iso:country":"ES",
    "sg:address":"Calle de Doctor Vila, 9",
    "sg:city":"Rua De Valdeorras",
    "sg:orig_category":"Abogados",
    "sg:phone":"+34 988 31 24 86",
    "sg:postcode":"32350",
    "sg:province":"Ourense",
    "wof:name":"Sotelo Casado Jose Manuel",
    "wof:placetype":"venue"
},
  "geometry": {"coordinates":[-7.114481926,42.3937339783],"type":"Point"}
}