{
  "type": "Feature",
  "properties": {
    "addr:full":"Carrer de Llobregat, 9 Sant Vicen\u00c7 Dels Horts Barcelona 08620",
    "addr:housenumber":"9",
    "addr:postcode":"08620",
    "addr:street":"Carrer De Llobregat;Sant Vicenc\u0327 Dels Horts Barcelona",
    "iso:country":"ES",
    "sg:address":"Carrer de Llobregat, 9",
    "sg:city":"Sant Vicen\u00c7 Dels Horts",
    "sg:orig_category":"Carnicer\u00cdas, Carnicer\u00cdas",
    "sg:phone":"+34 936 56 67 03",
    "sg:postcode":"08620",
    "sg:province":"Barcelona",
    "wof:name":"Esteve Duran Maria Dolors",
    "wof:placetype":"venue"
},
  "geometry": {"coordinates":[2.0070300102,41.4003601074],"type":"Point"}
}