{
  "type": "Feature",
  "properties": {
    "addr:full":"Homs, 9 Vulpellac Girona 17111",
    "addr:housenumber":"9",
    "addr:postcode":"17111",
    "addr:street":"Homs",
    "iso:country":"ES",
    "sg:address":"Homs, 9",
    "sg:city":"Vulpellac",
    "sg:orig_category":"Construcci\u00d3n Mec\u00c1nica",
    "sg:phone":"+34 972 64 48 47",
    "sg:postcode":"17111",
    "sg:province":"Girona",
    "wof:name":"Taller Mecanic Nou Metal S.l.l.",
    "wof:placetype":"venue"
},
  "geometry": {"coordinates":[3.054970026,41.9602890015],"type":"Point"}
}