{
  "type": "Feature",
  "properties": {
    "addr:full":"Calle de Sotillo, 35 Madrid Madrid 28043",
    "addr:housenumber":"35",
    "addr:postcode":"madrid;28043",
    "addr:street":"Calle De Sotillo",
    "iso:country":"ES",
    "sg:address":"Calle de Sotillo, 35",
    "sg:city":"Madrid",
    "sg:orig_category":"Centros Empresariales",
    "sg:phone":"+34 917 59 82 42",
    "sg:postcode":"28043",
    "sg:province":"Madrid",
    "wof:name":"Dipresa",
    "wof:placetype":"venue"
},
  "geometry": {"coordinates":[-3.6373200417,40.4574584961],"type":"Point"}
}