{
  "type": "Feature",
  "properties": {
    "iso:country":"ES",
    "sg:address":"Calle de Rio Duero, 3",
    "sg:city":"Mostoles",
    "sg:orig_category":"Muebles, Minoristas",
    "sg:phone":"+34 916 47 28 13",
    "sg:postcode":"28935",
    "sg:province":"Madrid",
    "wof:name":"Todo Joven S.l.",
    "wof:placetype":"venue"
},
  "geometry": {"coordinates":[-3.8783710003,40.3173294067],"type":"Point"}
}