{
  "type": "Feature",
  "properties": {
    "addr:full":"Carrer de Narcis Monturiol, 10 Vendrell Tarragona 43700",
    "addr:housenumber":"10",
    "addr:postcode":"43700",
    "addr:street":"Carrer De Narcis Monturiol",
    "iso:country":"ES",
    "sg:address":"Carrer de Narcis Monturiol, 10",
    "sg:city":"Vendrell",
    "sg:orig_category":"Reposter\u00cdas",
    "sg:phone":"+34 977 66 21 44",
    "sg:postcode":"43700",
    "sg:province":"Tarragona",
    "wof:name":"Del Pozo Gil Maria Dolores",
    "wof:placetype":"venue"
},
  "geometry": {"coordinates":[1.5392129421,41.2208976746],"type":"Point"}
}