{
  "type": "Feature",
  "properties": {
    "addr:full":"Calle de Armengual De La Mota, 12 Malaga M\u00e1laga 29007",
    "addr:housenumber":"12",
    "addr:postcode":"29007",
    "addr:street":"Calle De Armengual De La Mota;Ma\u0301Laga",
    "iso:country":"ES",
    "sg:address":"Calle de Armengual De La Mota, 12",
    "sg:city":"Malaga",
    "sg:orig_category":"Agencias De Viajes",
    "sg:phone":"+34 952 61 42 32",
    "sg:postcode":"29007",
    "sg:province":"M\u00e1laga",
    "sg:website":"www.barceloviajes.com",
    "wof:name":"Viajes Barcelo S.l.",
    "wof:placetype":"venue"
},
  "geometry": {"coordinates":[-4.4292469025,36.7185783386],"type":"Point"}
}