{
  "type": "Feature",
  "properties": {
    "addr:full":"Calle de Parroco Francisco Rguez Rguez, 106 Palmas De Gran Canaria Las Palmas 35010",
    "addr:housenumber":"106",
    "addr:postcode":"35010",
    "addr:street":"Calle De Parroco Francisco Rguez Rguez",
    "iso:country":"ES",
    "sg:address":"Calle de Parroco Francisco Rguez Rguez, 106",
    "sg:city":"Palmas De Gran Canaria",
    "sg:orig_category":"Venta, Colocaci\u00d3n, Reparaci\u00d3n De Radiadores Para Veh\u00cdculos",
    "sg:phone":"+34 928 22 73 08",
    "sg:postcode":"35010",
    "sg:province":"Las Palmas",
    "wof:name":"Hernandez Rodriguez Santiago",
    "wof:placetype":"venue"
},
  "geometry": {"coordinates":[-15.4432554245,28.1272182465],"type":"Point"}
}