{
  "type": "Feature",
  "properties": {
    "iso:country":"ES",
    "sg:address":"Calle de Ramon Y Cajal, 3",
    "sg:city":"Vitoria-gasteiz",
    "sg:orig_category":"Material Y Herramientas Agr\u00cdcolas",
    "sg:phone":"+34 945 13 06 05",
    "sg:postcode":"01007",
    "sg:province":"\u00c1lava",
    "wof:name":"Armentia Salazar Luis Angel",
    "wof:placetype":"venue"
},
  "geometry": {"coordinates":[-2.6769015789,42.8435058594],"type":"Point"}
}