{
  "type": "Feature",
  "properties": {
    "iso:country":"ES",
    "sg:address":"Carrer de Regoyos, 18",
    "sg:city":"Pinemar",
    "sg:orig_category":"Textiles: Suministros Y Accesorios Para Industrias (fabricaci\u00d3n, Negocio)",
    "sg:phone":"+34 937 62 56 84",
    "sg:postcode":"08397",
    "sg:province":"Barcelona",
    "wof:name":"Gomez Boadas S.a.",
    "wof:placetype":"venue"
},
  "geometry": {"coordinates":[2.6895120144,41.6376991272],"type":"Point"}
}