{
  "type": "Feature",
  "properties": {
    "addr:full":"Rbla Joaquim Ruyra, 78 Blanes Girona 17300",
    "addr:housenumber":"78",
    "addr:postcode":"17300",
    "addr:street":"Rbla Joaquim Ruyra",
    "iso:country":"ES",
    "sg:address":"Rbla Joaquim Ruyra, 78",
    "sg:city":"Blanes",
    "sg:classifiers":[
        {
            "category":"Autos & Motor Vehicles",
            "subcategory":"Automobile Sales",
            "type":"Retail Goods"
        }
    ],
    "sg:phone":"+34 972 33 02 02",
    "sg:postcode":"17300",
    "sg:province":"Girona",
    "wof:name":"Escoles De Conduccio Sole S.l.",
    "wof:placetype":"venue"
},
  "geometry": {"coordinates":[2.7900309563,41.6748161316],"type":"Point"}
}