{
  "type": "Feature",
  "properties": {
    "iso:country":"ES",
    "sg:address":"Cust Loreto, 1",
    "sg:city":"Tudela",
    "sg:orig_category":"Radiocomunicaciones, Telefon\u00cda M\u00d3vil, Radiomensajer\u00cda: Servicios, Comercializaci\u00d3n",
    "sg:phone":"+34 948 41 21 52",
    "sg:postcode":"31500",
    "sg:province":"Navarra",
    "wof:name":"Montelectu S.l.",
    "wof:placetype":"venue"
},
  "geometry": {"coordinates":[-1.6075199842,42.0593795776],"type":"Point"}
}