{
  "type": "Feature",
  "properties": {
    "addr:full":"Carrer de Bertran, 103 Barcelona Barcelona 08023",
    "addr:housenumber":"103",
    "addr:postcode":"08023",
    "addr:street":"Carrer De Bertran",
    "iso:country":"ES",
    "sg:address":"Carrer de Bertran, 103",
    "sg:city":"Barcelona",
    "sg:orig_category":"Materias Pl\u00c1sticas: Art\u00cdculos Para La Industria",
    "sg:phone":"+34 934 18 14 47",
    "sg:postcode":"08023",
    "sg:province":"Barcelona",
    "wof:name":"Plaintex S. A.",
    "wof:placetype":"venue"
},
  "geometry": {"coordinates":[2.1395449638,41.4088859558],"type":"Point"}
}