{
  "type": "Feature",
  "properties": {
    "addr:full":"Carrofeito, 2 Boiro La Coru\u00f1a 15930",
    "addr:housenumber":"2",
    "addr:postcode":"15930",
    "addr:street":"Carrofeito;La Corun\u0303A",
    "iso:country":"ES",
    "sg:address":"Carrofeito, 2",
    "sg:city":"Boiro",
    "sg:orig_category":"Agentes Generales De Seguros",
    "sg:phone":"+34 981 84 81 94",
    "sg:postcode":"15930",
    "sg:province":"La Coru\u00f1a",
    "wof:name":"Pompas Funebres Europeas S.l.",
    "wof:placetype":"venue"
},
  "geometry": {"coordinates":[-8.8847093582,42.6471214294],"type":"Point"}
}