{
  "type": "Feature",
  "properties": {
    "addr:full":"Carrer de Mallorca, 593 Barcelona Barcelona 08026",
    "addr:housenumber":"593",
    "addr:postcode":"08026",
    "addr:street":"Carrer De Mallorca",
    "iso:country":"ES",
    "sg:address":"Carrer de Mallorca, 593",
    "sg:city":"Barcelona",
    "sg:orig_category":"Centros De Educaci\u00d3n Especial",
    "sg:phone":"+34 934 56 90 20",
    "sg:postcode":"08026",
    "sg:province":"Barcelona",
    "wof:name":"Ajuntament De Barcelona",
    "wof:placetype":"venue"
},
  "geometry": {"coordinates":[2.1857311726,41.4112358093],"type":"Point"}
}