{
  "type": "Feature",
  "properties": {
    "addr:full":"Rua Jose Angel Valente Docasar, 4 Ourense Ourense 32003",
    "addr:housenumber":"4",
    "addr:postcode":"32003",
    "addr:street":"Rua Jose Angel Valente Docasar",
    "iso:country":"ES",
    "sg:address":"Rua Jose Angel Valente Docasar, 4",
    "sg:city":"Ourense",
    "sg:orig_category":"Arquitectos",
    "sg:phone":"+34 988 37 01 02",
    "sg:postcode":"32003",
    "sg:province":"Ourense",
    "wof:name":"Cinnania S.l.",
    "wof:placetype":"venue"
},
  "geometry": {"coordinates":[-7.8661170006,42.3389396667],"type":"Point"}
}