{
  "type": "Feature",
  "properties": {
    "addr:full":"Olite-erriberri Kalea, 46 Iru\u00f1a Navarra 31004",
    "addr:housenumber":"46",
    "addr:postcode":"31004",
    "addr:street":"Olite-Erriberri Kalea",
    "iso:country":"ES",
    "sg:address":"Olite-erriberri Kalea, 46",
    "sg:city":"Iru\u00f1a",
    "sg:orig_category":"Confiter\u00cdas, Chocolater\u00cdas (al Por Menor)",
    "sg:phone":"+34 948 24 54 52",
    "sg:postcode":"31004",
    "sg:province":"Navarra",
    "wof:name":"Ezquerro Marin Jose Ramon",
    "wof:placetype":"venue"
},
  "geometry": {"coordinates":[-1.6331789494,42.8100547791],"type":"Point"}
}