{
  "type": "Feature",
  "properties": {
    "iso:country":"ES",
    "sg:address":"Calle de Encarnacion, 8",
    "sg:city":"Antequera",
    "sg:orig_category":"Telas Y Sedas (al Por Menor)",
    "sg:phone":"+34 952 70 42 64",
    "sg:postcode":"29200",
    "sg:province":"M\u00e1laga",
    "wof:name":"Rosillo Nuevo S.l.l.",
    "wof:placetype":"venue"
},
  "geometry": {"coordinates":[-4.558590889,37.0163383484],"type":"Point"}
}