{
  "type": "Feature",
  "properties": {
    "iso:country":"ES",
    "sg:address":"Calle de Gudari Kalea, 18",
    "sg:city":"Tolosa",
    "sg:orig_category":"Cl\u00cdnicas Dentales",
    "sg:phone":"+34 943 65 13 02",
    "sg:postcode":"20400",
    "sg:province":"Guip\u00f9zcoa",
    "wof:name":"Ansorena Ormazabal Ignacio",
    "wof:placetype":"venue"
},
  "geometry": {"coordinates":[-2.0756599903,43.1335792542],"type":"Point"}
}