{
  "type": "Feature",
  "properties": {
    "addr:full":"Calle de Al Andalus, 2 Salobre\u00f1a Granada 18680",
    "addr:housenumber":"2",
    "addr:postcode":"18680",
    "addr:street":"Calle De Al Andalus",
    "iso:country":"ES",
    "sg:address":"Calle de Al Andalus, 2",
    "sg:city":"Salobre\u00f1a",
    "sg:orig_category":"Fisioterapia",
    "sg:phone":"+34 958 61 11 14",
    "sg:postcode":"18680",
    "sg:province":"Granada",
    "wof:name":"Garcia Hortal Antonia",
    "wof:placetype":"venue"
},
  "geometry": {"coordinates":[-3.5825903416,36.7446022034],"type":"Point"}
}