{
  "type": "Feature",
  "properties": {
    "addr:full":"Trva Marina (da), 43 Viveiro Lugo 27850",
    "addr:postcode":"27850",
    "addr:street":"Trva Marina Da",
    "iso:country":"ES",
    "sg:address":"Trva Marina (da), 43",
    "sg:city":"Viveiro",
    "sg:orig_category":"Cajas De Ahorro",
    "sg:phone":"+34 982 56 04 00",
    "sg:postcode":"27850",
    "sg:province":"Lugo",
    "sg:website":"www.cajaespana.es",
    "wof:name":"Caja Espa\u00f1a De Inversiones Caja De Ahorros Y Monte De Piedad",
    "wof:placetype":"venue"
},
  "geometry": {"coordinates":[-7.5967211723,43.6605224609],"type":"Point"}
}