{
  "type": "Feature",
  "properties": {
    "iso:country":"ES",
    "sg:address":"Mayor, 12",
    "sg:city":"Juslibol",
    "sg:orig_category":"Herramientas Y Suministros Para Plomeros",
    "sg:phone":"+34 976 51 05 37",
    "sg:postcode":"50191",
    "sg:province":"Zaragoza",
    "wof:name":"Gobepal S.l.",
    "wof:placetype":"venue"
},
  "geometry": {"coordinates":[-0.8995090127,41.6933364868],"type":"Point"}
}