{
  "type": "Feature",
  "properties": {
    "addr:full":"Calle de Nueva, 30 Torreperogil Ja\u00e9n 23320",
    "addr:housenumber":"30",
    "addr:postcode":"23320",
    "addr:street":"Calle De Nueva",
    "iso:country":"ES",
    "sg:address":"Calle de Nueva, 30",
    "sg:city":"Torreperogil",
    "sg:orig_category":"Agentes Generales De Seguros",
    "sg:phone":"+34 953 77 63 13",
    "sg:postcode":"23320",
    "sg:province":"Ja\u00e9n",
    "wof:name":"Vazquez Ruiz Maria Del Pilar",
    "wof:placetype":"venue"
},
  "geometry": {"coordinates":[-3.2903399467,38.0340995789],"type":"Point"}
}