{
  "type": "Feature",
  "properties": {
    "iso:country":"ES",
    "sg:address":"Calle de Jorge Manrique, 4",
    "sg:city":"Zaragoza",
    "sg:orig_category":"Administradores De Bienes Y Delegados De Comunidades De Propietarios",
    "sg:phone":"+34 976 46 60 54",
    "sg:postcode":"50015",
    "sg:province":"Zaragoza",
    "wof:name":"Hierro & Granados Y Asociados S.l.",
    "wof:placetype":"venue"
},
  "geometry": {"coordinates":[-0.8867880106,41.6694259644],"type":"Point"}
}