{
  "type": "Feature",
  "properties": {
    "iso:country":"ES",
    "sg:address":"Avda Alcalde Jose Fernandin, 25",
    "sg:city":"Piedras Blancas",
    "sg:orig_category":"Farmacias",
    "sg:phone":"+34 985 53 00 57",
    "sg:postcode":"33450",
    "sg:province":"Asturias",
    "wof:name":"Garcia De La Mata Fernandez Sandra",
    "wof:placetype":"venue"
},
  "geometry": {"coordinates":[-5.9748687744,43.5615768433],"type":"Point"}
}