{
  "type": "Feature",
  "properties": {
    "addr:full":"Calle de Maestro Falla, 26 Ronquillo Sevilla 41880",
    "addr:housenumber":"26",
    "addr:postcode":"41880",
    "addr:street":"Calle De Maestro Falla",
    "iso:country":"ES",
    "sg:address":"Calle de Maestro Falla, 26",
    "sg:city":"Ronquillo",
    "sg:orig_category":"Alimentaci\u00d3n General (al Por Menor)",
    "sg:phone":"+34 954 13 14 32",
    "sg:postcode":"41880",
    "sg:province":"Sevilla",
    "wof:name":"El Ronco Hispalense S.l.",
    "wof:placetype":"venue"
},
  "geometry": {"coordinates":[-6.1775331497,37.7252349854],"type":"Point"}
}