{
  "type": "Feature",
  "properties": {
    "addr:full":"Carr Pals, 7 Palafrugell Girona 17200",
    "addr:housenumber":"7",
    "addr:postcode":"17200",
    "addr:street":"Carr Pals",
    "iso:country":"ES",
    "sg:address":"Carr Pals, 7",
    "sg:city":"Palafrugell",
    "sg:orig_category":"Carnicer\u00cdas, Carnicer\u00cdas",
    "sg:phone":"+34 972 30 01 40",
    "sg:postcode":"17200",
    "sg:province":"Girona",
    "wof:name":"Llimona Broto Xavier",
    "wof:placetype":"venue"
},
  "geometry": {"coordinates":[3.1597599983,41.9181594849],"type":"Point"}
}