{
  "type": "Feature",
  "properties": {
    "addr:full":"Ctra Hinojos, Km. 0001,4 Chucena Huelva 21891",
    "addr:postcode":"21891",
    "addr:street":"Ctra Hinojos Km. 0001,4",
    "iso:country":"ES",
    "sg:address":"Ctra Hinojos, Km. 0001,4",
    "sg:city":"Chucena",
    "sg:orig_category":"Distribuci\u00d3n De Petr\u00d3leo Y Derivados",
    "sg:phone":"+34 959 50 61 56",
    "sg:postcode":"21891",
    "sg:province":"Huelva",
    "wof:name":"Quiles Y Delgado Sociedad Civil",
    "wof:placetype":"venue"
},
  "geometry": {"coordinates":[-6.3909797668,37.3635215759],"type":"Point"}
}