{
  "type": "Feature",
  "properties": {
    "addr:full":"Carrer de Rebolledo (dels), 9 Tarragona Tarragona 43004",
    "addr:housenumber":"9",
    "addr:postcode":"43004",
    "addr:street":"Carrer De Rebolledo Dels",
    "iso:country":"ES",
    "sg:address":"Carrer de Rebolledo (dels), 9",
    "sg:city":"Tarragona",
    "sg:orig_category":"Edici\u00d3n De Diarios, Revistas, Boletines",
    "sg:phone":"+34 977 22 13 96",
    "sg:postcode":"43004",
    "sg:province":"Tarragona",
    "wof:name":"Ediciones El Medol S.l.",
    "wof:placetype":"venue"
},
  "geometry": {"coordinates":[1.2497210503,41.1122589111],"type":"Point"}
}