{
  "type": "Feature",
  "properties": {
    "addr:full":"Calle de San Fernando, 1 Sevilla Sevilla 41004",
    "addr:housenumber":"1",
    "addr:postcode":"41004",
    "addr:street":"Calle De San Fernando",
    "iso:country":"ES",
    "sg:address":"Calle de San Fernando, 1",
    "sg:city":"Sevilla",
    "sg:orig_category":"Fotocopias, Reprograf\u00cda",
    "sg:phone":"+34 954 21 20 74",
    "sg:postcode":"41004",
    "sg:province":"Sevilla",
    "sg:website":"www.workcenter.es",
    "wof:name":"Workcenter Andalucia S.l.",
    "wof:placetype":"venue"
},
  "geometry": {"coordinates":[-5.9926900864,37.382434845],"type":"Point"}
}