{
  "type": "Feature",
  "properties": {
    "addr:full":"Avda Real De Pinto, 21 Madrid Madrid 28021",
    "addr:housenumber":"21",
    "addr:postcode":"madrid;28021",
    "addr:street":"Avda Real De Pinto",
    "iso:country":"ES",
    "sg:address":"Avda Real De Pinto, 21",
    "sg:city":"Madrid",
    "sg:orig_category":"Ense\u00d1anza Variada",
    "sg:phone":"+34 917 96 14 28",
    "sg:postcode":"28021",
    "sg:province":"Madrid",
    "sg:website":"www.wsi.es",
    "wof:name":"W.s.i. Villa S.l.",
    "wof:placetype":"venue"
},
  "geometry": {"coordinates":[-3.7063643932,40.3472900391],"type":"Point"}
}