{
  "type": "Feature",
  "properties": {
    "iso:country":"ES",
    "sg:address":"Calle de Ganado, 67",
    "sg:city":"Puerto De Santa Maria",
    "sg:orig_category":"Reposter\u00cdas",
    "sg:phone":"+34 956 85 34 53",
    "sg:postcode":"11500",
    "sg:province":"C\u00e1diz",
    "wof:name":"Braza Lobo Ismael",
    "wof:placetype":"venue"
},
  "geometry": {"coordinates":[-6.2281551361,36.602142334],"type":"Point"}
}