{
  "type": "Feature",
  "properties": {
    "iso:country":"ES",
    "sg:address":"Rua Irixo (do), 13",
    "sg:city":"Carballi\u00f1o",
    "sg:orig_category":"Promotores Constructores",
    "sg:phone":"+34 988 27 01 77",
    "sg:postcode":"32500",
    "sg:province":"Ourense",
    "wof:name":"Fernandez Pereira Balbino",
    "wof:placetype":"venue"
},
  "geometry": {"coordinates":[-8.07862854,42.4361114502],"type":"Point"}
}