{
  "type": "Feature",
  "properties": {
    "iso:country":"ES",
    "sg:address":"Calle de Josue Lillo, 43",
    "sg:city":"Madrid",
    "sg:orig_category":"Empresarios Y Productoras De Espect\u00c1culos",
    "sg:phone":"+34 914 78 06 61",
    "sg:postcode":"28053",
    "sg:province":"Madrid",
    "wof:name":"Exposiciones Tesoros Del Ayer C.b.",
    "wof:placetype":"venue"
},
  "geometry": {"coordinates":[-3.6694450378,40.3848152161],"type":"Point"}
}