{
  "type": "Feature",
  "properties": {
    "addr:full":"Calle de Toledo, 85 Merida Badajoz 06800",
    "addr:housenumber":"85",
    "addr:postcode":"06800",
    "addr:street":"Calle De Toledo",
    "iso:country":"ES",
    "sg:address":"Calle de Toledo, 85",
    "sg:city":"Merida",
    "sg:orig_category":"Fabricaci\u00d3n, Importaci\u00d3n, Venta De Material De Telefon\u00cda, Peritelefon\u00cda",
    "sg:phone":"+34 924 33 02 50",
    "sg:postcode":"06800",
    "sg:province":"Badajoz",
    "wof:name":"Perez Garcia Francisco",
    "wof:placetype":"venue"
},
  "geometry": {"coordinates":[-6.3528838158,38.9213752747],"type":"Point"}
}