{
  "type": "Feature",
  "properties": {
    "addr:full":"Calle de General Casta\u00d1eda, 8 Torrelavega Cantabria 39300",
    "addr:housenumber":"8",
    "addr:postcode":"39300",
    "addr:street":"Calle De General Castan\u0303Eda",
    "iso:country":"ES",
    "sg:address":"Calle de General Casta\u00d1eda, 8",
    "sg:city":"Torrelavega",
    "sg:orig_category":"Asistencia Social",
    "sg:phone":"+34 942 89 12 42",
    "sg:postcode":"39300",
    "sg:province":"Cantabria",
    "wof:name":"Asociacion Monta\u00f1esa De Ayuda Al Toxicomano",
    "wof:placetype":"venue"
},
  "geometry": {"coordinates":[-4.0499615669,43.347202301],"type":"Point"}
}