{
  "type": "Feature",
  "properties": {
    "addr:full":"Calle de Batan De San Sebastian, 1 Palencia Palencia 34002",
    "addr:housenumber":"1",
    "addr:postcode":"34002",
    "addr:street":"Calle De Batan De San Sebastian",
    "iso:country":"ES",
    "sg:address":"Calle de Batan De San Sebastian, 1",
    "sg:city":"Palencia",
    "sg:orig_category":"Abogados",
    "sg:phone":"+34 979 71 39 27",
    "sg:postcode":"34002",
    "sg:province":"Palencia",
    "wof:name":"Fuente Diez Mercedes De La",
    "wof:placetype":"venue"
},
  "geometry": {"coordinates":[-4.5296325684,42.0043487549],"type":"Point"}
}