{
  "type": "Feature",
  "properties": {
    "iso:country":"ES",
    "sg:address":"Calle de Cervantes, 25",
    "sg:city":"Pozoblanco",
    "sg:orig_category":"Fabricaci\u00d3n, Distribuci\u00d3n De Material Para La Climatizaci\u00d3n, Aireaci\u00d3n Y Ventilaci\u00d3n",
    "sg:phone":"+34 957 77 21 52",
    "sg:postcode":"14400",
    "sg:province":"C\u00f3rdoba",
    "wof:name":"Frivall S.c.a.",
    "wof:placetype":"venue"
},
  "geometry": {"coordinates":[-4.8528242111,38.3790588379],"type":"Point"}
}