{
  "type": "Feature",
  "properties": {
    "iso:country":"ES",
    "sg:address":"Calle de Coches (los), 7",
    "sg:city":"Segovia",
    "sg:orig_category":"M\u00c9dicos: Estomatolog\u00cda",
    "sg:phone":"+34 921 44 29 35",
    "sg:postcode":"40002",
    "sg:province":"Segovia",
    "sg:website":"www.paginasamarillas.es",
    "wof:name":"Grado Viejo Maria Del Mar De",
    "wof:placetype":"venue"
},
  "geometry": {"coordinates":[-4.119035244,40.9449386597],"type":"Point"}
}