{
  "type": "Feature",
  "properties": {
    "iso:country":"ES",
    "sg:address":"Av Roma, 125",
    "sg:city":"Barcelona",
    "sg:orig_category":"Albergues",
    "sg:phone":"+34 934 54 49 06",
    "sg:postcode":"08011",
    "sg:province":"Barcelona",
    "sg:website":"www.milos-online.de",
    "wof:name":"Comercial Milos S.l.",
    "wof:placetype":"venue"
},
  "geometry": {"coordinates":[2.1550340652,41.3859138489],"type":"Point"}
}