{
  "type": "Feature",
  "properties": {
    "addr:full":"Calle de Pousafoles, S/n Pousafoles Ourense 32229",
    "addr:housenumber":"s",
    "addr:postcode":"32229",
    "addr:street":"Calle De Pousafoles;/ N",
    "iso:country":"ES",
    "sg:address":"Calle de Pousafoles, S/n",
    "sg:city":"Pousafoles",
    "sg:orig_category":"Ense\u00d1anza, Formaci\u00d3n Profesional: Aprendizaje",
    "sg:phone":"+34 988 49 44 22",
    "sg:postcode":"32229",
    "sg:province":"Ourense",
    "wof:name":"Ayuntamiento De Padrenda",
    "wof:placetype":"venue"
},
  "geometry": {"coordinates":[-7.8646407127,42.340007782],"type":"Point"}
}