{
  "type": "Feature",
  "properties": {
    "addr:full":"Av Cales Piques, S/n Cales Piques Islas Baleares 07760",
    "addr:housenumber":"s",
    "addr:postcode":"07760",
    "addr:street":"Av Cales Piques;/ N Cales Piques",
    "iso:country":"ES",
    "sg:address":"Av Cales Piques, S/n",
    "sg:city":"Cales Piques",
    "sg:orig_category":"Alquiler De Veh\u00cdculos: Turismos Y Utilitarios",
    "sg:phone":"+34 971 38 88 43",
    "sg:postcode":"07760",
    "sg:province":"Islas Baleares",
    "wof:name":"Hiper Rent A Car S.a.",
    "wof:placetype":"venue"
},
  "geometry": {"coordinates":[3.7996919155,40.0072402954],"type":"Point"}
}