{
  "type": "Feature",
  "properties": {
    "iso:country":"ES",
    "sg:address":"Plaz Carmelitas, 5",
    "sg:city":"Salamanca",
    "sg:orig_category":"Institutos De Belleza",
    "sg:phone":"+34 923 26 21 53",
    "sg:postcode":"37007",
    "sg:province":"Salamanca",
    "wof:name":"Gonzalez Benayas Maria Soledad",
    "wof:placetype":"venue"
},
  "geometry": {"coordinates":[-5.6679291725,40.9684944153],"type":"Point"}
}