{
  "type": "Feature",
  "properties": {
    "addr:full":"Calle de Borrero, 9 Pedro\u00d1eras Cuenca 16660",
    "addr:housenumber":"9",
    "addr:postcode":"16660",
    "addr:street":"Calle De Borrero",
    "iso:country":"ES",
    "sg:address":"Calle de Borrero, 9",
    "sg:city":"Pedro\u00d1eras",
    "sg:orig_category":"Farmacias",
    "sg:phone":"+34 967 16 00 34",
    "sg:postcode":"16660",
    "sg:province":"Cuenca",
    "wof:name":"Martinez Chicano Lucia",
    "wof:placetype":"venue"
},
  "geometry": {"coordinates":[-2.6721591949,39.4477767944],"type":"Point"}
}