{
  "type": "Feature",
  "properties": {
    "iso:country":"ES",
    "sg:address":"Carretera De Castejon, Km. 0004,0",
    "sg:city":"Alfaro",
    "sg:orig_category":"Animales (al Por Menor)",
    "sg:phone":"+34 941 18 34 96",
    "sg:postcode":"26540",
    "sg:province":"La Rioja",
    "wof:name":"Explotaciones Chavarri Martinez S.l.",
    "wof:placetype":"venue"
},
  "geometry": {"coordinates":[-1.7497990131,42.1742782593],"type":"Point"}
}