{
  "type": "Feature",
  "properties": {
    "iso:country":"ES",
    "sg:address":"Calle de Domingo Martinez, 31",
    "sg:city":"Valladolid",
    "sg:orig_category":"Laboratorios Y Cl\u00cdnicas Veterinarias",
    "sg:phone":"+34 983 22 29 47",
    "sg:postcode":"47007",
    "sg:province":"Valladolid",
    "wof:name":"Moran Corces Pedro",
    "wof:placetype":"venue"
},
  "geometry": {"coordinates":[-4.7345128059,41.638343811],"type":"Point"}
}