{
  "type": "Feature",
  "properties": {
    "addr:full":"Calle de Marques De Casa Valdes, 6 Gijon Asturias 33202",
    "addr:housenumber":"6",
    "addr:postcode":"33202",
    "addr:street":"Calle De Marques De Casa Valdes",
    "iso:country":"ES",
    "sg:address":"Calle de Marques De Casa Valdes, 6",
    "sg:city":"Gijon",
    "sg:orig_category":"Cueros Y Pieles (al Por Mayor)",
    "sg:phone":"+34 985 34 44 04",
    "sg:postcode":"33202",
    "sg:province":"Asturias",
    "sg:website":"www.curtidoscarrasco.com",
    "wof:name":"Curtidos Carrasco C.b.",
    "wof:placetype":"venue"
},
  "geometry": {"coordinates":[-5.6574478149,43.5403327942],"type":"Point"}
}