{
  "type": "Feature",
  "properties": {
    "addr:full":"Calle de Alfonso X El Sabio, 33 Argana Baja Las Palmas 35500",
    "addr:housenumber":"33",
    "addr:postcode":"35500",
    "addr:street":"Calle De Alfonso X El Sabio",
    "iso:country":"ES",
    "sg:address":"Calle de Alfonso X El Sabio, 33",
    "sg:city":"Argana Baja",
    "sg:orig_category":"Supermercados Y Hipermercados",
    "sg:phone":"+34 928 80 53 49",
    "sg:postcode":"35500",
    "sg:province":"Las Palmas",
    "wof:name":"Carrasco Cortes Jose Antonio",
    "wof:placetype":"venue"
},
  "geometry": {"coordinates":[-15.4300060272,28.1248226166],"type":"Point"}
}