{
  "type": "Feature",
  "properties": {
    "iso:country":"ES",
    "sg:address":"Luga Sabariz, 21",
    "sg:city":"Sabariz",
    "sg:orig_category":"Poller\u00cda Y Caza (al Por Menor)",
    "sg:phone":"+34 988 43 44 05",
    "sg:postcode":"32857",
    "sg:province":"Ourense",
    "wof:name":"Alvarez Gra\u00f1a Gumersindo",
    "wof:placetype":"venue"
},
  "geometry": {"coordinates":[-7.8415679932,42.1081619263],"type":"Point"}
}