{
  "type": "Feature",
  "properties": {
    "iso:country":"ES",
    "sg:address":"Avda J. Solis Ruiz, 47",
    "sg:city":"Cabra",
    "sg:orig_category":"Inform\u00c1tica, Ofim\u00c1tica (estudios, Asesor\u00cda, Ingenier\u00cda, Formaci\u00d3n)",
    "sg:phone":"+34 957 52 52 37",
    "sg:postcode":"14940",
    "sg:province":"C\u00f3rdoba",
    "wof:name":"Informatica Jose Julio S.l",
    "wof:placetype":"venue"
},
  "geometry": {"coordinates":[-4.4435248375,37.4730606079],"type":"Point"}
}