{
  "type": "Feature",
  "properties": {
    "iso:country":"ES",
    "sg:address":"Via Alexandra, 93",
    "sg:city":"Sabadell",
    "sg:orig_category":"Molduras, Junquillos, Listones Y Molduras Perforadas",
    "sg:phone":"+34 937 17 00 52",
    "sg:postcode":"08206",
    "sg:province":"Barcelona",
    "wof:name":"Arenas Ropero Pedro",
    "wof:placetype":"venue"
},
  "geometry": {"coordinates":[2.0862329006,41.5577201843],"type":"Point"}
}