{
  "type": "Feature",
  "properties": {
    "addr:full":"Vidreiro, 1 Vidreiro La Coru\u00f1a 15600",
    "addr:housenumber":"1",
    "addr:postcode":"15600",
    "addr:street":"Vidreiro;La Corun\u0303A",
    "iso:country":"ES",
    "sg:address":"Vidreiro, 1",
    "sg:city":"Vidreiro",
    "sg:orig_category":"Ense\u00d1anza, Formaci\u00d3n Profesional: Aprendizaje",
    "sg:phone":"+34 981 43 05 91",
    "sg:postcode":"15600",
    "sg:province":"La Coru\u00f1a",
    "wof:name":"Concello De Pontedeume",
    "wof:placetype":"venue"
},
  "geometry": {"coordinates":[-8.1694135666,43.4068565369],"type":"Point"}
}