{
  "type": "Feature",
  "properties": {
    "addr:full":"Carrer de Foc, S/n Barcelona Barcelona 08038",
    "addr:housenumber":"s / n",
    "addr:postcode":"08038",
    "addr:street":"Carrer De Foc",
    "iso:country":"ES",
    "sg:address":"Carrer de Foc, S/n",
    "sg:city":"Barcelona",
    "sg:orig_category":"Sanatorios M\u00c9dico",
    "sg:phone":"+34 932 23 28 88",
    "sg:postcode":"08038",
    "sg:province":"Barcelona",
    "wof:name":"Centre De Telecomunicaciones De Catalunya",
    "wof:placetype":"venue"
},
  "geometry": {"coordinates":[2.1395099163,41.3553924561],"type":"Point"}
}