{
  "type": "Feature",
  "properties": {
    "iso:country":"ES",
    "sg:address":"Calle de Don Jaime I, 24",
    "sg:city":"Zaragoza",
    "sg:orig_category":"Procuradores",
    "sg:phone":"+34 976 39 79 81",
    "sg:postcode":"50001",
    "sg:province":"Zaragoza",
    "wof:name":"Gimenez Navarro Isaac",
    "wof:placetype":"venue"
},
  "geometry": {"coordinates":[-0.8784943223,41.6531219482],"type":"Point"}
}