{
  "type": "Feature",
  "properties": {
    "addr:full":"Avda Enrique Ruiz Gomez, 13 Bomberos Madrid 28250",
    "addr:postcode":"28250",
    "addr:street":"Avda Enrique Ruiz Gomez 13",
    "iso:country":"ES",
    "sg:address":"Avda Enrique Ruiz Gomez, 13",
    "sg:city":"Bomberos",
    "sg:orig_category":"Publicidad (soportes Y Gesti\u00d3n)",
    "sg:phone":"+34 918 59 65 47",
    "sg:postcode":"28250",
    "sg:province":"Madrid",
    "sg:website":"www.reclamistas.com",
    "wof:name":"Oportunidades Promocionales S.l.",
    "wof:placetype":"venue"
},
  "geometry": {"coordinates":[-3.9306790829,40.57654953],"type":"Point"}
}