{
  "type": "Feature",
  "properties": {
    "addr:full":"Plaz Rey, 2 Santillana Cantabria 39330",
    "addr:housenumber":"2",
    "addr:postcode":"39330",
    "addr:street":"Plaz Rey",
    "iso:country":"ES",
    "sg:address":"Plaz Rey, 2",
    "sg:city":"Santillana",
    "sg:orig_category":"Carnicer\u00cdas, Carnicer\u00cdas",
    "sg:phone":"+34 942 81 83 62",
    "sg:postcode":"39330",
    "sg:province":"Cantabria",
    "wof:name":"Alvaro Ruiz Leandro",
    "wof:placetype":"venue"
},
  "geometry": {"coordinates":[-4.1089258194,43.3875694275],"type":"Point"}
}