{
  "type": "Feature",
  "properties": {
    "iso:country":"ES",
    "sg:address":"Moraleja-guijo C. Ctra., S/n",
    "sg:city":"Santiba\u00f1ez Alto",
    "sg:orig_category":"Cr\u00cda De Animales",
    "sg:phone":"+34 927 19 70 17",
    "sg:postcode":"10859",
    "sg:province":"C\u00e1ceres",
    "wof:name":"La Parra Del Soberal S. A.",
    "wof:placetype":"venue"
},
  "geometry": {"coordinates":[-6.5466189384,40.1860351562],"type":"Point"}
}