{
  "type": "Feature",
  "properties": {
    "iso:country":"ES",
    "sg:address":"Trva Valle Inclan, S/n",
    "sg:city":"Monforte De Lemos",
    "sg:orig_category":"Mec\u00c1nico Del Autom\u00d3vil",
    "sg:phone":"+34 982 40 26 76",
    "sg:postcode":"27400",
    "sg:province":"Lugo",
    "wof:name":"Autovalosa S.a.l.",
    "wof:placetype":"venue"
},
  "geometry": {"coordinates":[-7.5043492317,42.5225143433],"type":"Point"}
}