{
  "type": "Feature",
  "properties": {
    "iso:country":"ES",
    "sg:address":"Calle de Benigafull, 50",
    "sg:city":"Vall D'uixo",
    "sg:orig_category":"Diet\u00c9tica: Productos Biol\u00d3gicos, Naturales Y Diet\u00c9ticos (fabricaci\u00d3n, Al Por Mayor)",
    "sg:phone":"+34 964 66 54 27",
    "sg:postcode":"12600",
    "sg:province":"Castell\u00f3n",
    "wof:name":"Sanchez-pascuala Navarro Gregorio",
    "wof:placetype":"venue"
},
  "geometry": {"coordinates":[-0.2357338965,39.8226089478],"type":"Point"}
}