{
  "type": "Feature",
  "properties": {
    "addr:full":"Calle de Dionisio Aldama Kalea, 5 Amurrio \u00c1lava 01470",
    "addr:housenumber":"5",
    "addr:postcode":"01470",
    "addr:street":"Calle De Dionisio Aldama Kalea",
    "iso:country":"ES",
    "sg:address":"Calle de Dionisio Aldama Kalea, 5",
    "sg:city":"Amurrio",
    "sg:orig_category":"Sociedades, Compa\u00d1\u00cdas Aseguradoras",
    "sg:phone":"+34 945 39 31 31",
    "sg:postcode":"01470",
    "sg:province":"\u00c1lava",
    "sg:website":"www.mapfre.com",
    "wof:name":"Mapfre Servicios De Informatica",
    "wof:placetype":"venue"
},
  "geometry": {"coordinates":[-3.0006012917,43.0513420105],"type":"Point"}
}