{
  "type": "Feature",
  "properties": {
    "addr:full":"Calle de Sanchez Preciados, 26 Madrid Madrid 28039",
    "addr:housenumber":"26",
    "addr:postcode":"madrid;28039",
    "addr:street":"Calle De Sanchez Preciados",
    "iso:country":"ES",
    "sg:address":"Calle de Sanchez Preciados, 26",
    "sg:city":"Madrid",
    "sg:orig_category":"Molduras, Junquillos, Listones Y Molduras Perforadas",
    "sg:phone":"+34 913 11 14 46",
    "sg:postcode":"28039",
    "sg:province":"Madrid",
    "wof:name":"Jimenez Velayos Arturo",
    "wof:placetype":"venue"
},
  "geometry": {"coordinates":[-3.7109370232,40.4596366882],"type":"Point"}
}