{
  "type": "Feature",
  "properties": {
    "iso:country":"ES",
    "sg:address":"Calle de Argantonio, 10",
    "sg:city":"Cadiz",
    "sg:orig_category":"Empresas De Portes Y Mensajer\u00cda",
    "sg:phone":"+34 956 22 74 49",
    "sg:postcode":"11004",
    "sg:province":"C\u00e1diz",
    "wof:name":"Unipost S.a.",
    "wof:placetype":"venue"
},
  "geometry": {"coordinates":[-6.2939391136,36.5331344604],"type":"Point"}
}