{
  "type": "Feature",
  "properties": {
    "iso:country":"ES",
    "sg:address":"G.v. Corts Catalanes, 616",
    "sg:city":"Barcelona",
    "sg:orig_category":"Agencias De Viajes",
    "sg:phone":"+34 933 42 66 26",
    "sg:postcode":"08007",
    "sg:province":"Barcelona",
    "wof:name":"Orixa Agencia Viatges S.a.",
    "wof:placetype":"venue"
},
  "geometry": {"coordinates":[2.1665139198,41.3876800537],"type":"Point"}
}