{
  "type": "Feature",
  "properties": {
    "addr:full":"Recheo, S/n Cee La Coru\u00f1a 15270",
    "addr:postcode":"15270",
    "addr:street":"Recheo S / N;La",
    "iso:country":"ES",
    "sg:address":"Recheo, S/n",
    "sg:city":"Cee",
    "sg:orig_category":"Ropa Para Ni\u00d1os (al Por Menor)",
    "sg:phone":"+34 981 70 62 88",
    "sg:postcode":"15270",
    "sg:province":"La Coru\u00f1a",
    "wof:name":"Kiddys's Class S.a.",
    "wof:placetype":"venue"
},
  "geometry": {"coordinates":[-9.187494278,42.9554710388],"type":"Point"}
}