{
  "type": "Feature",
  "properties": {
    "addr:full":"Calle de Paseo Del Agua, 5 Brenes Sevilla 41310",
    "addr:housenumber":"5",
    "addr:postcode":"41310",
    "addr:street":"Calle De Paseo Del Agua",
    "iso:country":"ES",
    "sg:address":"Calle de Paseo Del Agua, 5",
    "sg:city":"Brenes",
    "sg:orig_category":"Mayoristas E Intermediarios En Alcoholes",
    "sg:phone":"+34 954 79 68 28",
    "sg:postcode":"41310",
    "sg:province":"Sevilla",
    "wof:name":"Osuna Mantecon S.l.",
    "wof:placetype":"venue"
},
  "geometry": {"coordinates":[-5.8697390556,37.5507011414],"type":"Point"}
}