{
  "type": "Feature",
  "properties": {
    "addr:full":"Avda Jaen, 13 Torredonjimeno Ja\u00e9n 23650",
    "addr:housenumber":"13",
    "addr:postcode":"23650",
    "addr:street":"Avda Jaen",
    "iso:country":"ES",
    "sg:address":"Avda Jaen, 13",
    "sg:city":"Torredonjimeno",
    "sg:orig_category":"Pintura Y Barniz (al Por Menor)",
    "sg:phone":"+34 953 57 28 40",
    "sg:postcode":"23650",
    "sg:province":"Ja\u00e9n",
    "sg:website":"www.jrodan.hypermart.net",
    "wof:name":"J. Roldan S.l.",
    "wof:placetype":"venue"
},
  "geometry": {"coordinates":[-3.9456119537,37.7635421753],"type":"Point"}
}