{
  "type": "Feature",
  "properties": {
    "addr:full":"Crri Mercado (do), 2 Lugo Lugo 27001",
    "addr:housenumber":"2",
    "addr:postcode":"27001",
    "iso:country":"ES",
    "sg:address":"Crri Mercado (do), 2",
    "sg:city":"Lugo",
    "sg:orig_category":"Reposter\u00cdas",
    "sg:phone":"+34 982 22 32 97",
    "sg:postcode":"27001",
    "sg:province":"Lugo",
    "wof:name":"Lopez Hernandez Francisco Jose",
    "wof:placetype":"venue"
},
  "geometry": {"coordinates":[-7.5579538345,43.0121231079],"type":"Point"}
}