{
  "type": "Feature",
  "properties": {
    "iso:country":"ES",
    "sg:address":"Calle de Doce De Octubre, 3",
    "sg:city":"Cordoba",
    "sg:orig_category":"Cervecer\u00cdas",
    "sg:phone":"+34 957 47 30 23",
    "sg:postcode":"14001",
    "sg:province":"C\u00f3rdoba",
    "wof:name":"Arranz Feria Ramon Manuel",
    "wof:placetype":"venue"
},
  "geometry": {"coordinates":[-4.7811050415,37.8890647888],"type":"Point"}
}