{
  "type": "Feature",
  "properties": {
    "addr:full":"Avda Sor Soledad Cobian, 48 Orotava Santa Cruz De Tenerife 38300",
    "addr:housenumber":"48",
    "addr:postcode":"38300",
    "addr:street":"Avda Sor Soledad Cobian",
    "iso:country":"ES",
    "sg:address":"Avda Sor Soledad Cobian, 48",
    "sg:city":"Orotava",
    "sg:orig_category":"Importaci\u00d3n",
    "sg:phone":"+34 922 33 09 71",
    "sg:postcode":"38300",
    "sg:province":"Santa Cruz De Tenerife",
    "wof:name":"Comercial Ricosta S.l.",
    "wof:placetype":"venue"
},
  "geometry": {"coordinates":[-16.5182285309,28.3915195465],"type":"Point"}
}