{
  "type": "Feature",
  "properties": {
    "addr:full":"Carrer de Navas De Tolosa, 344 Barcelona Barcelona 08027",
    "addr:housenumber":"344",
    "addr:postcode":"08027",
    "addr:street":"Carrer De Navas De Tolosa",
    "iso:country":"ES",
    "sg:address":"Carrer de Navas De Tolosa, 344",
    "sg:city":"Barcelona",
    "sg:orig_category":"Peluquer\u00cdas, Peluquer\u00cda Mixta",
    "sg:phone":"+34 933 49 74 76",
    "sg:postcode":"08027",
    "sg:province":"Barcelona",
    "wof:name":"Torralbo Fuentes Rafael",
    "wof:placetype":"venue"
},
  "geometry": {"coordinates":[2.1822009087,41.4190254211],"type":"Point"}
}