{
  "type": "Feature",
  "properties": {
    "addr:full":"Carr De Sant Roc, 1 S. Rafael Rio Castell\u00f3n 12510",
    "addr:housenumber":"1",
    "addr:postcode":"12510",
    "addr:street":"Carr De Sant Roc;Rafael Rio Castello\u0301N",
    "iso:country":"ES",
    "sg:address":"Carr De Sant Roc, 1",
    "sg:city":"S. Rafael Rio",
    "sg:orig_category":"Cooperativas Agr\u00cdcolas",
    "sg:phone":"+34 977 57 05 36",
    "sg:postcode":"12510",
    "sg:province":"Castell\u00f3n",
    "wof:name":"Cooperativa Agricola San Rafael Del Rio Verde",
    "wof:placetype":"venue"
},
  "geometry": {"coordinates":[0.3464699984,40.6063156128],"type":"Point"}
}