{
  "type": "Feature",
  "properties": {
    "addr:full":"Carrer de Duran I Bas, 11 Barcelona Barcelona 08002",
    "addr:housenumber":"11",
    "addr:postcode":"08002",
    "addr:street":"Carrer De Duran I Bas",
    "iso:country":"ES",
    "sg:address":"Carrer de Duran I Bas, 11",
    "sg:city":"Barcelona",
    "sg:orig_category":"Librer\u00cdas",
    "sg:phone":"+34 933 17 94 43",
    "sg:postcode":"08002",
    "sg:province":"Barcelona",
    "wof:name":"Distribuidora Balmes S.l.",
    "wof:placetype":"venue"
},
  "geometry": {"coordinates":[2.1746749878,41.3857002258],"type":"Point"}
}