{
  "type": "Feature",
  "properties": {
    "iso:country":"ES",
    "sg:address":"Calle de Real, 19",
    "sg:city":"Fabero",
    "sg:orig_category":"Telas Y Sedas (al Por Menor)",
    "sg:phone":"+34 987 55 00 13",
    "sg:postcode":"24420",
    "sg:province":"Le\u00f3n",
    "wof:name":"Alvarez Ramon Manuel",
    "wof:placetype":"venue"
},
  "geometry": {"coordinates":[-6.6265306473,42.767162323],"type":"Point"}
}