{
  "type": "Feature",
  "properties": {
    "iso:country":"ES",
    "sg:address":"Av Mediterrani, 62",
    "sg:city":"Cunit",
    "sg:classifiers":[
        {
            "category":"Professional",
            "subcategory":"Management & Consulting",
            "type":"Services"
        }
    ],
    "sg:phone":"+34 977 67 20 93",
    "sg:postcode":"43881",
    "sg:province":"Tarragona",
    "sg:tags":[
        "asesor\u00cda",
        "en",
        "marketing"
    ],
    "wof:name":"Transoluciones",
    "wof:placetype":"venue"
},
  "geometry": {"coordinates":[1.6134059429,41.1950378418],"type":"Point"}
}