{
  "type": "Feature",
  "properties": {
    "iso:country":"ES",
    "sg:address":"C/ Mestre Padilla, 12",
    "sg:city":"Bellreguard",
    "sg:orig_category":"Aguas (distribuci\u00d3n, Servicios)",
    "sg:phone":"+34 962 81 53 50",
    "sg:postcode":"46713",
    "sg:province":"Valencia",
    "wof:name":"Empresa General Valenciana Del Agua S.a.",
    "wof:placetype":"venue"
},
  "geometry": {"coordinates":[-0.1613579988,38.9476661682],"type":"Point"}
}