{
  "type": "Feature",
  "properties": {
    "iso:country":"ES",
    "sg:address":"Calle de Real, 1",
    "sg:city":"Mojados",
    "sg:orig_category":"Carnicer\u00cdas, Carnicer\u00cdas",
    "sg:phone":"+34 983 60 70 56",
    "sg:postcode":"47250",
    "sg:province":"Valladolid",
    "wof:name":"Mendez Vaca Miguel Angel",
    "wof:placetype":"venue"
},
  "geometry": {"coordinates":[-4.6632890701,41.4321708679],"type":"Point"}
}