{
  "type": "Feature",
  "properties": {
    "iso:country":"ES",
    "sg:address":"Calle de Bernart Etxepare, 17",
    "sg:city":"Kurtzea",
    "sg:orig_category":"Diarios, Revistas Y Boletines (suscripciones)",
    "sg:phone":"+34 944 57 26 61",
    "sg:postcode":"48960",
    "sg:province":"Vizcaya",
    "wof:name":"Rodriguez Puente Federico",
    "wof:placetype":"venue"
},
  "geometry": {"coordinates":[-2.8438484669,43.2339553833],"type":"Point"}
}