{
  "type": "Feature",
  "properties": {
    "addr:full":"Calle de Barroso, 12 Cordoba C\u00f3rdoba 14003",
    "addr:housenumber":"12",
    "addr:postcode":"14003",
    "addr:street":"Calle De Barroso;Co\u0301Rdoba",
    "iso:country":"ES",
    "sg:address":"Calle de Barroso, 12",
    "sg:city":"Cordoba",
    "sg:orig_category":"Agencias Y Asesores De Publicidad",
    "sg:phone":"+34 957 47 12 19",
    "sg:postcode":"14003",
    "sg:province":"C\u00f3rdoba",
    "wof:name":"Publicidad Faro S. A.",
    "wof:placetype":"venue"
},
  "geometry": {"coordinates":[-4.7812657356,37.8827133179],"type":"Point"}
}