{
  "type": "Feature",
  "properties": {
    "addr:full":"Rua Rosalia De Castro, 6 Ourense Ourense 32001",
    "addr:housenumber":"6",
    "addr:postcode":"32001",
    "addr:street":"Rua Rosalia De Castro",
    "iso:country":"ES",
    "sg:address":"Rua Rosalia De Castro, 6",
    "sg:city":"Ourense",
    "sg:orig_category":"Asesor\u00cda Fiscal Y Jur\u00cddica",
    "sg:phone":"+34 988 37 39 74",
    "sg:postcode":"32001",
    "sg:province":"Ourense",
    "wof:name":"Pi\u00f1ero Mi\u00f1o Antonio Jose",
    "wof:placetype":"venue"
},
  "geometry": {"coordinates":[-7.8668260574,42.3479652405],"type":"Point"}
}