{
  "type": "Feature",
  "properties": {
    "iso:country":"ES",
    "sg:address":"Calle de Maestro Perez Cervera, 80",
    "sg:city":"Cieza",
    "sg:orig_category":"Centros De Educaci\u00d3n Especial",
    "sg:phone":"+34 968 76 07 23",
    "sg:postcode":"30530",
    "sg:province":"Murcia",
    "wof:name":"C.e.i.p.cristo Del Consuelo",
    "wof:placetype":"venue"
},
  "geometry": {"coordinates":[-1.4217389822,38.2416000366],"type":"Point"}
}