{
  "type": "Feature",
  "properties": {
    "addr:full":"Part. Burgaret, 155 Reus Tarragona 43206",
    "addr:housenumber":"155",
    "addr:postcode":"43206",
    "iso:country":"ES",
    "sg:address":"Part. Burgaret, 155",
    "sg:city":"Reus",
    "sg:orig_category":"Negocio De Materiales De Construcci\u00d3n",
    "sg:phone":"+34 977 75 47 08",
    "sg:postcode":"43206",
    "sg:province":"Tarragona",
    "wof:name":"Jordi Rull S.a.",
    "wof:placetype":"venue"
},
  "geometry": {"coordinates":[1.1039400101,41.1745300293],"type":"Point"}
}