{
  "type": "Feature",
  "properties": {
    "iso:country":"ES",
    "sg:address":"Pase General Davila, 121",
    "sg:city":"Santander",
    "sg:orig_category":"Mec\u00c1nico Del Autom\u00d3vil",
    "sg:phone":"+34 942 34 69 60",
    "sg:postcode":"39007",
    "sg:province":"Cantabria",
    "wof:name":"Frechoso Ambrosio Jose Manuel",
    "wof:placetype":"venue"
},
  "geometry": {"coordinates":[-3.8258430958,43.4624443054],"type":"Point"}
}