{
  "type": "Feature",
  "properties": {
    "addr:full":"Ctra Hoyos A Los, Km. 0004,2 Hoyos Las Palmas 35017",
    "addr:postcode":"35017",
    "addr:street":"Ctra Hoyos;Los Km. 0004,2 Hoyos",
    "iso:country":"ES",
    "sg:address":"Ctra Hoyos A Los, Km. 0004,2",
    "sg:city":"Hoyos",
    "sg:orig_category":"Ense\u00d1anza: Idiomas",
    "sg:phone":"+34 928 43 00 23",
    "sg:postcode":"35017",
    "sg:province":"Las Palmas",
    "wof:name":"Centro De Ense\u00f1anza Norteamericana De Las Palmas De Gran Canaria",
    "wof:placetype":"venue"
},
  "geometry": {"coordinates":[-15.4646606445,28.054693222],"type":"Point"}
}