{
  "type": "Feature",
  "properties": {
    "addr:full":"Carrer de Mare De Deu De La Salut, 83 Barcelona Barcelona 08024",
    "addr:housenumber":"83",
    "addr:postcode":"08024",
    "addr:street":"Carrer De Mare De Deu De La Salut",
    "iso:country":"ES",
    "sg:address":"Carrer de Mare De Deu De La Salut, 83",
    "sg:city":"Barcelona",
    "sg:orig_category":"Aparcamientos (infraestructuras, Accesorios)",
    "sg:phone":"+34 932 84 67 34",
    "sg:postcode":"08024",
    "sg:province":"Barcelona",
    "wof:name":"Parking Salud, S. A.",
    "wof:placetype":"venue"
},
  "geometry": {"coordinates":[2.1595458984,41.4132423401],"type":"Point"}
}