{
  "type": "Feature",
  "properties": {
    "addr:full":"Carrer de Francesc Codina, 29 Vilassar Dalt Barcelona 08339",
    "addr:housenumber":"29",
    "addr:postcode":"08339",
    "addr:street":"Carrer De Francesc Codina;Dalt Barcelona",
    "iso:country":"ES",
    "sg:address":"Carrer de Francesc Codina, 29",
    "sg:city":"Vilassar Dalt",
    "sg:orig_category":"Material Y Suministros Para Horticultura, Arboricultura",
    "sg:phone":"+34 937 50 90 70",
    "sg:postcode":"08339",
    "sg:province":"Barcelona",
    "wof:name":"Francisco Xiberta S.l.",
    "wof:placetype":"venue"
},
  "geometry": {"coordinates":[2.3616290092,41.5183601379],"type":"Point"}
}