{
  "type": "Feature",
  "properties": {
    "iso:country":"ES",
    "sg:address":"Plg. Norte, S/n",
    "sg:city":"Mieres",
    "sg:orig_category":"Bebidas",
    "sg:phone":"+34 985 45 14 83",
    "sg:postcode":"33600",
    "sg:province":"Asturias",
    "wof:name":"Mediavilla Gonzalez Diana",
    "wof:placetype":"venue"
},
  "geometry": {"coordinates":[-5.7719388008,43.2503890991],"type":"Point"}
}