{
  "type": "Feature",
  "properties": {
    "addr:full":"Acacias (colonia), 2 Argamasilla Alba Ciudad Real 13710",
    "addr:postcode":"13710",
    "addr:street":"Colonia;Argamasilla",
    "iso:country":"ES",
    "sg:address":"Acacias (colonia), 2",
    "sg:city":"Argamasilla Alba",
    "sg:orig_category":"Centros De Coordinaci\u00d3n",
    "sg:phone":"+34 926 53 70 79",
    "sg:postcode":"13710",
    "sg:province":"Ciudad Real",
    "wof:name":"Madrid Lucendo Maria Angeles",
    "wof:placetype":"venue"
},
  "geometry": {"coordinates":[-3.0829439163,39.1299705505],"type":"Point"}
}