{
  "type": "Feature",
  "properties": {
    "iso:country":"ES",
    "sg:address":"Port Empuries-b, 66",
    "sg:city":"Empuriabrava",
    "sg:orig_category":"Inmobiliaria (agencias)",
    "sg:phone":"+34 972 45 17 80",
    "sg:postcode":"17487",
    "sg:province":"Girona",
    "wof:name":"Ampurdan Natura S.l.",
    "wof:placetype":"venue"
},
  "geometry": {"coordinates":[3.1221101284,42.2478599548],"type":"Point"}
}