{
  "type": "Feature",
  "properties": {
    "iso:country":"ES",
    "sg:address":"Carrer de Ferrer De Blanes, 8",
    "sg:city":"Barcelona",
    "sg:orig_category":"Promotores Constructores",
    "sg:phone":"+34 932 38 68 56",
    "sg:postcode":"08012",
    "sg:province":"Barcelona",
    "wof:name":"Construccions Domenech Aguila S.l.",
    "wof:placetype":"venue"
},
  "geometry": {"coordinates":[2.1592469215,41.3985824585],"type":"Point"}
}