{
  "type": "Feature",
  "properties": {
    "addr:full":"Avda Ramon Y Cajal, 56 Roda Albacete 02630",
    "addr:housenumber":"56",
    "addr:postcode":"02630",
    "addr:street":"Avda Ramon Y Cajal",
    "iso:country":"ES",
    "sg:address":"Avda Ramon Y Cajal, 56",
    "sg:city":"Roda",
    "sg:orig_category":"Arquitectos",
    "sg:phone":"+34 967 44 38 79",
    "sg:postcode":"02630",
    "sg:province":"Albacete",
    "sg:website":"www.cipingenieros.com",
    "wof:name":"Alarcon Celaya Aurelio",
    "wof:placetype":"venue"
},
  "geometry": {"coordinates":[-2.1579763889,39.2047386169],"type":"Point"}
}