{
  "type": "Feature",
  "properties": {
    "iso:country":"ES",
    "sg:address":"Av Barcelona, 111",
    "sg:city":"Miami Playa",
    "sg:orig_category":"Cajas De Ahorro",
    "sg:phone":"+34 977 81 02 15",
    "sg:postcode":"43892",
    "sg:province":"Tarragona",
    "sg:website":"www.caixatarragona.es",
    "wof:name":"Caixa D'estalvis De Tarragona",
    "wof:placetype":"venue"
},
  "geometry": {"coordinates":[0.9573349953,41.0249786377],"type":"Point"}
}