{
  "type": "Feature",
  "properties": {
    "iso:country":"ES",
    "sg:address":"Calle de Secoya, 18",
    "sg:city":"Madrid",
    "sg:orig_category":"Autob\u00das (explotaci\u00d3n Y Servicios De)",
    "sg:phone":"+34 915 08 41 00",
    "sg:postcode":"28044",
    "sg:province":"Madrid",
    "wof:name":"Autobuses Prisei S.l.",
    "wof:placetype":"venue"
},
  "geometry": {"coordinates":[-3.7451150417,40.3694190979],"type":"Point"}
}