{
  "type": "Feature",
  "properties": {
    "addr:full":"Calle de Corregidor Jose De Pasamonte, 29 Madrid Madrid 28030",
    "addr:housenumber":"29",
    "addr:postcode":"madrid;28030",
    "addr:street":"Calle De Corregidor Jose De Pasamonte",
    "iso:country":"ES",
    "sg:address":"Calle de Corregidor Jose De Pasamonte, 29",
    "sg:city":"Madrid",
    "sg:orig_category":"Frutas, Legumbres Frescas Y Tempranas (al Por Menor)",
    "sg:phone":"+34 914 30 39 82",
    "sg:postcode":"28030",
    "sg:province":"Madrid",
    "wof:name":"Dudzik  Zriqniew",
    "wof:placetype":"venue"
},
  "geometry": {"coordinates":[-3.6473500729,40.4110298157],"type":"Point"}
}