{
  "type": "Feature",
  "properties": {
    "addr:full":"Carrer de Gracia, 148 Sabadell Barcelona 08201",
    "addr:housenumber":"148",
    "addr:postcode":"08201",
    "addr:street":"Carrer De Gracia",
    "iso:country":"ES",
    "sg:address":"Carrer de Gracia, 148",
    "sg:city":"Sabadell",
    "sg:classifiers":[
        {
            "category":"Arts & Performance",
            "subcategory":"Art Gallery",
            "type":"Entertainment"
        }
    ],
    "sg:phone":"+34 937 27 50 96",
    "sg:postcode":"08201",
    "sg:province":"Barcelona",
    "sg:tags":[
        "obras",
        "de",
        "coleccionismo",
        "compraventa",
        "arte",
        "y"
    ],
    "wof:name":"Boladeras Tordera Mercedes",
    "wof:placetype":"venue"
},
  "geometry": {"coordinates":[2.1047461033,41.550617218],"type":"Point"}
}