{
  "type": "Feature",
  "properties": {
    "addr:full":"Ctra. Nacional Ii, Km. 0040,0 Azuqueca Henares Guadalajara 19200",
    "addr:postcode":"19200",
    "addr:street":"Ctra. Nacional Ii Km. 0040,0",
    "iso:country":"ES",
    "sg:address":"Ctra. Nacional Ii, Km. 0040,0",
    "sg:city":"Azuqueca Henares",
    "sg:orig_category":"V\u00c1lvulas",
    "sg:phone":"+34 949 26 09 50",
    "sg:postcode":"19200",
    "sg:province":"Guadalajara",
    "wof:name":"Valois Espa\u00f1a S.a.",
    "wof:placetype":"venue"
},
  "geometry": {"coordinates":[-3.2677440643,40.5646400452],"type":"Point"}
}