{
  "type": "Feature",
  "properties": {
    "addr:full":"Plaz Cetina, 3 Catedral Murcia 30001",
    "addr:housenumber":"3",
    "addr:postcode":"30001",
    "addr:street":"Plaz Cetina",
    "iso:country":"ES",
    "sg:address":"Plaz Cetina, 3",
    "sg:city":"Catedral",
    "sg:orig_category":"Tatuajes",
    "sg:phone":"+34 968 22 02 38",
    "sg:postcode":"30001",
    "sg:province":"Murcia",
    "wof:name":"True Love Studio, S. L.",
    "wof:placetype":"venue"
},
  "geometry": {"coordinates":[-1.1302490234,37.9829597473],"type":"Point"}
}