{
  "type": "Feature",
  "properties": {
    "iso:country":"ES",
    "sg:address":"Carrer de Nou, 16",
    "sg:city":"Florida",
    "sg:orig_category":"Estancos",
    "sg:phone":"+34 935 60 18 63",
    "sg:postcode":"08130",
    "sg:province":"Barcelona",
    "wof:name":"Corral Romero Jose",
    "wof:placetype":"venue"
},
  "geometry": {"coordinates":[2.195043087,41.521686554],"type":"Point"}
}