{
  "type": "Feature",
  "properties": {
    "iso:country":"ES",
    "sg:address":"Calle de Rave, 9",
    "sg:city":"Medina Campo",
    "sg:orig_category":"Molduras, Junquillos, Listones Y Molduras Perforadas",
    "sg:phone":"+34 983 81 06 13",
    "sg:postcode":"47400",
    "sg:province":"Valladolid",
    "wof:name":"Bar Lipri C.b.",
    "wof:placetype":"venue"
},
  "geometry": {"coordinates":[-4.9114742279,41.3034210205],"type":"Point"}
}