{
  "type": "Feature",
  "properties": {
    "iso:country":"ES",
    "sg:address":"Carrer de Foneria, 46",
    "sg:city":"Barcelona",
    "sg:orig_category":"Doctores En Medicina",
    "sg:phone":"+34 933 32 69 91",
    "sg:postcode":"08038",
    "sg:province":"Barcelona",
    "wof:name":"Mas Sivera Jose",
    "wof:placetype":"venue"
},
  "geometry": {"coordinates":[2.1404600143,41.3610839844],"type":"Point"}
}