{
  "type": "Feature",
  "properties": {
    "iso:country":"ES",
    "sg:address":"Carrer de Isaac Albeniz, 2",
    "sg:city":"Palma",
    "sg:orig_category":"Arquitectos",
    "sg:phone":"+34 971 75 17 15",
    "sg:postcode":"07009",
    "sg:province":"Islas Baleares",
    "wof:name":"Ecp-97 S.l.",
    "wof:placetype":"venue"
},
  "geometry": {"coordinates":[2.6624720097,39.5861091614],"type":"Point"}
}