{
  "type": "Feature",
  "properties": {
    "addr:full":"Calle de Lara\u00d1a, 12 Sevilla Sevilla 41003",
    "addr:housenumber":"12",
    "addr:postcode":"41003",
    "addr:street":"Calle De Laran\u0303A",
    "iso:country":"ES",
    "sg:address":"Calle de Lara\u00d1a, 12",
    "sg:city":"Sevilla",
    "sg:orig_category":"Agentes Generales De Seguros",
    "sg:phone":"+34 954 50 04 20",
    "sg:postcode":"41003",
    "sg:province":"Sevilla",
    "sg:website":"www.segurmonte.com",
    "wof:name":"Segurmonte S.l.",
    "wof:placetype":"venue"
},
  "geometry": {"coordinates":[-5.9933218956,37.3929443359],"type":"Point"}
}