{
  "type": "Feature",
  "properties": {
    "iso:country":"ES",
    "sg:address":"Pase Portales Tundidores, 2",
    "sg:city":"Baeza",
    "sg:orig_category":"Bisuteros (fabricaci\u00d3n, Al Por Mayor)",
    "sg:phone":"+34 953 74 01 30",
    "sg:postcode":"23440",
    "sg:province":"Ja\u00e9n",
    "wof:name":"Guerrero Carmona Cristobal",
    "wof:placetype":"venue"
},
  "geometry": {"coordinates":[-3.480134964,37.9483451843],"type":"Point"}
}