{
  "type": "Feature",
  "properties": {
    "addr:full":"Calle de Don Juan De Austria, 36 Valencia Valencia 46002",
    "addr:housenumber":"36",
    "addr:postcode":"46002",
    "addr:street":"Calle De Don Juan De Austria",
    "iso:country":"ES",
    "sg:address":"Calle de Don Juan De Austria, 36",
    "sg:city":"Valencia",
    "sg:orig_category":"Mutuas De Seguros",
    "sg:phone":"+34 963 51 09 17",
    "sg:postcode":"46002",
    "sg:province":"Valencia",
    "wof:name":"Mutualidad Arrocera De Seguros",
    "wof:placetype":"venue"
},
  "geometry": {"coordinates":[-0.3714405,39.4702949524],"type":"Point"}
}