{
  "type": "Feature",
  "properties": {
    "iso:country":"ES",
    "sg:address":"Calle de Augusto Figueroa, 18",
    "sg:city":"Madrid",
    "sg:orig_category":"Torrefactado De Caf\u00c9",
    "sg:phone":"+34 915 32 05 79",
    "sg:postcode":"28004",
    "sg:province":"Madrid",
    "wof:name":"Porras Del Poo Raul",
    "wof:placetype":"venue"
},
  "geometry": {"coordinates":[-3.6984927654,40.4223976135],"type":"Point"}
}