{
  "type": "Feature",
  "properties": {
    "addr:full":"C/ Maulets (els), 30 Alcoi Alicante 03801",
    "addr:postcode":"03801",
    "addr:street":"C /;Els",
    "iso:country":"ES",
    "sg:address":"C/ Maulets (els), 30",
    "sg:city":"Alcoi",
    "sg:orig_category":"Reposter\u00cdas",
    "sg:phone":"+34 965 54 31 16",
    "sg:postcode":"03801",
    "sg:province":"Alicante",
    "wof:name":"Garcia Jorda Luis",
    "wof:placetype":"venue"
},
  "geometry": {"coordinates":[-0.4778749943,38.6913337708],"type":"Point"}
}