{
  "type": "Feature",
  "properties": {
    "addr:full":"Avda Huesca, 21 Alca\u00f1iz Teruel 44600",
    "addr:housenumber":"21",
    "addr:postcode":"44600",
    "addr:street":"Avda Huesca",
    "iso:country":"ES",
    "sg:address":"Avda Huesca, 21",
    "sg:city":"Alca\u00f1iz",
    "sg:orig_category":"Partidos Pol\u00cdticos",
    "sg:phone":"+34 978 87 06 00",
    "sg:postcode":"44600",
    "sg:province":"Teruel",
    "wof:name":"Partido Popular",
    "wof:placetype":"venue"
},
  "geometry": {"coordinates":[-0.1277990043,41.0481491089],"type":"Point"}
}