{
  "type": "Feature",
  "properties": {
    "addr:full":"Calle de Hernan Cortes, 40 Yecla Murcia 30510",
    "addr:housenumber":"40",
    "addr:postcode":"30510",
    "addr:street":"Calle De Hernan Cortes",
    "iso:country":"ES",
    "sg:address":"Calle de Hernan Cortes, 40",
    "sg:city":"Yecla",
    "sg:orig_category":"Reposter\u00cdas",
    "sg:phone":"+34 968 79 13 37",
    "sg:postcode":"30510",
    "sg:province":"Murcia",
    "wof:name":"Ortu\u00f1o Espert Juan Jose",
    "wof:placetype":"venue"
},
  "geometry": {"coordinates":[-1.1234899759,38.6145858765],"type":"Point"}
}