{
  "type": "Feature",
  "properties": {
    "addr:full":"Desvio Distante, S/n Hospitalet Llobregat Barcelona 08904",
    "addr:housenumber":"s",
    "addr:postcode":"08904",
    "addr:street":"/ N",
    "iso:country":"ES",
    "sg:address":"Desvio Distante, S/n",
    "sg:city":"Hospitalet Llobregat",
    "sg:orig_category":"Centros Empresariales",
    "sg:phone":"+34 934 48 16 66",
    "sg:postcode":"08904",
    "sg:province":"Barcelona",
    "sg:website":"www.teleurge.es",
    "wof:name":"Catalana Teleurge S.l.",
    "wof:placetype":"venue"
},
  "geometry": {"coordinates":[2.1700499058,41.3857192993],"type":"Point"}
}