{
  "type": "Feature",
  "properties": {
    "addr:full":"Calle de Carabela La Pinta, 19 Baiona Pontevedra 36300",
    "addr:housenumber":"19",
    "addr:postcode":"36300",
    "addr:street":"Calle De Carabela La Pinta",
    "iso:country":"ES",
    "sg:address":"Calle de Carabela La Pinta, 19",
    "sg:city":"Baiona",
    "sg:orig_category":"Inmobiliaria (agencias)",
    "sg:phone":"+34 986 35 63 14",
    "sg:postcode":"36300",
    "sg:province":"Pontevedra",
    "wof:name":"Santandres Pedregosa Bego\u00f1a",
    "wof:placetype":"venue"
},
  "geometry": {"coordinates":[-97.78224945069999,45.7040786743],"type":"Point"}
}