{
  "type": "Feature",
  "properties": {
    "iso:country":"ES",
    "sg:address":"Calle de Gran Via De San Marcos, 1",
    "sg:city":"Le\u00f3n",
    "sg:orig_category":"Relojer\u00cda (al Por Menor, Reparaci\u00d3n)",
    "sg:phone":"+34 987 22 67 67",
    "sg:postcode":"24001",
    "sg:province":"Le\u00f3n",
    "wof:name":"Sarabia Garcia Carlos",
    "wof:placetype":"venue"
},
  "geometry": {"coordinates":[-5.5765228271,42.5995750427],"type":"Point"}
}