{
  "type": "Feature",
  "properties": {
    "addr:full":"Calle de Nuestra Se\u00d1ora De Monserrate, S/n Torrevieja Alicante 03180",
    "addr:housenumber":"s / n",
    "addr:postcode":"03180",
    "addr:street":"Calle De Nuestra Sen\u0303Ora De Monserrate",
    "iso:country":"ES",
    "sg:address":"Calle de Nuestra Se\u00d1ora De Monserrate, S/n",
    "sg:city":"Torrevieja",
    "sg:orig_category":"Clases De M\u00dasica Y Canto",
    "sg:phone":"+34 965 71 16 82",
    "sg:postcode":"03180",
    "sg:province":"Alicante",
    "wof:name":"Orenes Lorenzo Maria Paz",
    "wof:placetype":"venue"
},
  "geometry": {"coordinates":[-0.6685839891,37.9776992798],"type":"Point"}
}