{
  "type": "Feature",
  "properties": {
    "addr:full":"Pol De As Gandaras, S/n Poligono De Gandaras Pontevedra 36475",
    "addr:housenumber":"s / n",
    "addr:postcode":"36475",
    "iso:country":"ES",
    "sg:address":"Pol De As Gandaras, S/n",
    "sg:city":"Poligono De Gandaras",
    "sg:orig_category":"Adaptaciones, Acondicionamientos Especiales Para Veh\u00cdculos, Veh\u00cdculos Industriales",
    "sg:phone":"+34 986 34 27 12",
    "sg:postcode":"36475",
    "sg:province":"Pontevedra",
    "wof:name":"Fredi Fandi\u00f1o S.l.n.e.",
    "wof:placetype":"venue"
},
  "geometry": {"coordinates":[-8.606926918,42.1053466797],"type":"Point"}
}