{
  "type": "Feature",
  "properties": {
    "addr:full":"Calle de Maiquez, 21 Madrid Madrid 28009",
    "addr:housenumber":"21",
    "addr:postcode":"madrid;28009",
    "addr:street":"Calle De Maiquez",
    "iso:country":"ES",
    "sg:address":"Calle de Maiquez, 21",
    "sg:city":"Madrid",
    "sg:orig_category":"Aparcamientos (infraestructuras, Accesorios)",
    "sg:phone":"+34 915 73 51 68",
    "sg:postcode":"28009",
    "sg:province":"Madrid",
    "wof:name":"Aparcamientos Maiquez S. A.",
    "wof:placetype":"venue"
},
  "geometry": {"coordinates":[-3.6731872559,40.4173316956],"type":"Point"}
}