{
  "type": "Feature",
  "properties": {
    "iso:country":"ES",
    "sg:address":"Calle de Andres Ochando, 17",
    "sg:city":"Casas De Juan Nu\u00e7ez",
    "sg:orig_category":"Carnicer\u00cdas, Carnicer\u00cdas",
    "sg:phone":"+34 967 40 53 31",
    "sg:postcode":"02151",
    "sg:province":"Albacete",
    "wof:name":"Gomez Soler Fernando",
    "wof:placetype":"venue"
},
  "geometry": {"coordinates":[-1.559731245,39.1015930176],"type":"Point"}
}