{
  "type": "Feature",
  "properties": {
    "addr:full":"Carrer de Alacant, 48 Senia Tarragona 43560",
    "addr:housenumber":"48",
    "addr:postcode":"43560",
    "addr:street":"Carrer De Alacant",
    "iso:country":"ES",
    "sg:address":"Carrer de Alacant, 48",
    "sg:city":"Senia",
    "sg:orig_category":"Metalurgia: Maquinaria Y Equipos",
    "sg:phone":"+34 977 57 64 71",
    "sg:postcode":"43560",
    "sg:province":"Tarragona",
    "wof:name":"Senia Equips S.l",
    "wof:placetype":"venue"
},
  "geometry": {"coordinates":[0.2854830027,40.6319351196],"type":"Point"}
}