{
  "type": "Feature",
  "properties": {
    "iso:country":"ES",
    "sg:address":"C/ Mestre Llobet, 17",
    "sg:city":"Tarrega",
    "sg:orig_category":"Contenedores (mercanc\u00cdas)",
    "sg:phone":"+34 973 31 19 32",
    "sg:postcode":"25300",
    "sg:province":"Lleida",
    "wof:name":"Bernaus Grant Daniel",
    "wof:placetype":"venue"
},
  "geometry": {"coordinates":[1.1435220242,41.6497840881],"type":"Point"}
}