{
  "type": "Feature",
  "properties": {
    "iso:country":"ES",
    "sg:address":"Pase Estacion, 17",
    "sg:city":"Torredonjimeno",
    "sg:orig_category":"Quincaller\u00cda (al Por Menor)",
    "sg:phone":"+34 953 57 21 05",
    "sg:postcode":"23650",
    "sg:province":"Ja\u00e9n",
    "wof:name":"Lopez Villegas Antonio",
    "wof:placetype":"venue"
},
  "geometry": {"coordinates":[-4.0899910927,37.8016700745],"type":"Point"}
}