{
  "type": "Feature",
  "properties": {
    "addr:full":"Rua Maria Berdiales, 4 Vigo Pontevedra 36203",
    "addr:housenumber":"4",
    "addr:postcode":"36203",
    "addr:street":"Rua Maria Berdiales",
    "iso:country":"ES",
    "sg:address":"Rua Maria Berdiales, 4",
    "sg:city":"Vigo",
    "sg:orig_category":"Estancos",
    "sg:phone":"+34 986 22 21 76",
    "sg:postcode":"36203",
    "sg:province":"Pontevedra",
    "wof:name":"Fernandez Martinez Celsa",
    "wof:placetype":"venue"
},
  "geometry": {"coordinates":[-8.7207202911,42.2351150513],"type":"Point"}
}