{
  "type": "Feature",
  "properties": {
    "iso:country":"ES",
    "sg:address":"Calle de Idiakez, 6",
    "sg:city":"Donostia-san Sebastian",
    "sg:orig_category":"Asociaciones, Organismos Culturales Y Socioeducativos",
    "sg:phone":"+34 943 42 98 27",
    "sg:postcode":"20004",
    "sg:province":"Guip\u00f9zcoa",
    "wof:name":"Hezkide Eskola",
    "wof:placetype":"venue"
},
  "geometry": {"coordinates":[-1.9814349413,43.3204193115],"type":"Point"}
}