{
  "type": "Feature",
  "properties": {
    "iso:country":"ES",
    "sg:address":"Pase Victoria (de La), 39",
    "sg:city":"Cordoba",
    "sg:orig_category":"Ingenier\u00cda, Centros De Estudios (diversos)",
    "sg:phone":"+34 957 42 21 00",
    "sg:postcode":"14004",
    "sg:province":"C\u00f3rdoba",
    "wof:name":"Lopez Laguna Jose Luis",
    "wof:placetype":"venue"
},
  "geometry": {"coordinates":[-4.7844700813,37.8831138611],"type":"Point"}
}