{
  "type": "Feature",
  "properties": {
    "addr:full":"Calle de Magistral Marrero, 4 Villa De Moya Las Palmas 35420",
    "addr:housenumber":"4",
    "addr:postcode":"35420",
    "addr:street":"Calle De Magistral Marrero",
    "iso:country":"ES",
    "sg:address":"Calle de Magistral Marrero, 4",
    "sg:city":"Villa De Moya",
    "sg:orig_category":"Cajas Para Embalar",
    "sg:phone":"+34 928 61 20 71",
    "sg:postcode":"35420",
    "sg:province":"Las Palmas",
    "sg:website":"www.ruralcanarias.com",
    "wof:name":"Caja Rural De Canarias",
    "wof:placetype":"venue"
},
  "geometry": {"coordinates":[-15.5828590393,28.1099147797],"type":"Point"}
}