{
  "type": "Feature",
  "properties": {
    "addr:full":"Ctra Benetuser, 72 Paiporta Valencia 46200",
    "addr:housenumber":"72",
    "addr:postcode":"46200",
    "addr:street":"Ctra Benetuser",
    "iso:country":"ES",
    "sg:address":"Ctra Benetuser, 72",
    "sg:city":"Paiporta",
    "sg:orig_category":"Materias Pl\u00c1sticas: Art\u00cdculos Para La Industria",
    "sg:phone":"+34 963 97 30 27",
    "sg:postcode":"46200",
    "sg:province":"Valencia",
    "wof:name":"Plasticos Energia S.l.",
    "wof:placetype":"venue"
},
  "geometry": {"coordinates":[-0.4019550085,39.4257507324],"type":"Point"}
}