{
  "type": "Feature",
  "properties": {
    "addr:full":"Puerto De San Isidro, S/n Puebla Lillo Le\u00f3n 24855",
    "addr:housenumber":"s",
    "addr:postcode":"24855",
    "addr:street":"Puerto;San Isidro;/ N",
    "iso:country":"ES",
    "sg:address":"Puerto De San Isidro, S/n",
    "sg:city":"Puebla Lillo",
    "sg:orig_category":"Estudios Y Construcci\u00d3n De Acuarios Y Viveros",
    "sg:phone":"+34 987 73 12 54",
    "sg:postcode":"24855",
    "sg:province":"Le\u00f3n",
    "wof:name":"Lillogem S.l.",
    "wof:placetype":"venue"
},
  "geometry": {"coordinates":[-5.3612446785,43.065826416],"type":"Point"}
}