{
  "type": "Feature",
  "properties": {
    "addr:full":"Prol Ronda De Santo Domingo, 1 Orihuela Alicante 03300",
    "addr:housenumber":"1",
    "addr:postcode":"03300",
    "addr:street":"Prol Ronda De Santo Domingo",
    "iso:country":"ES",
    "sg:address":"Prol Ronda De Santo Domingo, 1",
    "sg:city":"Orihuela",
    "sg:orig_category":"Fisioterapia",
    "sg:phone":"+34 966 73 90 79",
    "sg:postcode":"03300",
    "sg:province":"Alicante",
    "wof:name":"Berenguer Ubeda Jose Miguel",
    "wof:placetype":"venue"
},
  "geometry": {"coordinates":[-0.9402120113,38.0862464905],"type":"Point"}
}