{
  "type": "Feature",
  "properties": {
    "iso:country":"ES",
    "sg:address":"Calle de Cavas, 42",
    "sg:city":"Calahorra",
    "sg:orig_category":"Lencer\u00cda Femenina, Corseter\u00cda, Trajes De Ba\u00d1o (al Por Menor)",
    "sg:phone":"+34 941 13 33 05",
    "sg:postcode":"26500",
    "sg:province":"La Rioja",
    "wof:name":"Urrutia Garrido Magdalena",
    "wof:placetype":"venue"
},
  "geometry": {"coordinates":[-1.9615030289,42.3029747009],"type":"Point"}
}