{
  "type": "Feature",
  "properties": {
    "iso:country":"ES",
    "sg:address":"Urb Pantaleon, S/n",
    "sg:city":"Alhaurin Grande",
    "sg:orig_category":"Dise\u00d1o Industrial",
    "sg:phone":"+34 952 49 00 51",
    "sg:postcode":"29120",
    "sg:province":"M\u00e1laga",
    "wof:name":"Cortes Rueda Alfonso",
    "wof:placetype":"venue"
},
  "geometry": {"coordinates":[-4.6911292076,36.6420783997],"type":"Point"}
}