{
  "type": "Feature",
  "properties": {
    "addr:full":"Calle de Poeta Llorente, 61 Pobla Vallbona Valencia 46185",
    "addr:housenumber":"61",
    "addr:postcode":"46185",
    "addr:street":"Calle De Poeta Llorente",
    "iso:country":"ES",
    "sg:address":"Calle de Poeta Llorente, 61",
    "sg:city":"Pobla Vallbona",
    "sg:orig_category":"Asesor\u00cda Fiscal Y Jur\u00cddica",
    "sg:phone":"+34 962 76 31 91",
    "sg:postcode":"46185",
    "sg:province":"Valencia",
    "wof:name":"Romero March Maria Reyes",
    "wof:placetype":"venue"
},
  "geometry": {"coordinates":[-0.5515220165,39.5916442871],"type":"Point"}
}