{
  "type": "Feature",
  "properties": {
    "iso:country":"ES",
    "sg:address":"Carrer de Francesc Macia, 64",
    "sg:city":"Castellbisbal",
    "sg:orig_category":"Centros Empresariales",
    "sg:phone":"+34 937 72 26 39",
    "sg:postcode":"08755",
    "sg:province":"Barcelona",
    "wof:name":"Gonzalez Pacheco Irene",
    "wof:placetype":"venue"
},
  "geometry": {"coordinates":[1.9835699797,41.4762916565],"type":"Point"}
}