{
  "type": "Feature",
  "properties": {
    "iso:country":"ES",
    "sg:address":"Calle de Monterrey, 17",
    "sg:city":"Arroyo De La Miel-benalmadena Costa",
    "sg:orig_category":"Inform\u00c1tica (estudios, Servicios, Asesor\u00cda, Formaci\u00d3n)",
    "sg:phone":"+34 952 56 43 10",
    "sg:postcode":"29631",
    "sg:province":"M\u00e1laga",
    "wof:name":"Bayview S.l.",
    "wof:placetype":"venue"
},
  "geometry": {"coordinates":[-4.5542998314,36.6025314331],"type":"Point"}
}