{
  "type": "Feature",
  "properties": {
    "iso:country":"ES",
    "sg:address":"Avda Federico Garcia Lorca, 22",
    "sg:city":"Almeria",
    "sg:orig_category":"Internados & Ense\u00d1anza Privada",
    "sg:phone":"+34 950 25 03 88",
    "sg:postcode":"04004",
    "sg:province":"Almer\u00eda",
    "wof:name":"Colegio Stella Maris Hijas De Jesus",
    "wof:placetype":"venue"
},
  "geometry": {"coordinates":[-2.4609539509,36.8367614746],"type":"Point"}
}