{
  "type": "Feature",
  "properties": {
    "addr:full":"Calle de Santa Fe, 16 Toledo Toledo 45001",
    "addr:housenumber":"16",
    "addr:postcode":"45001",
    "addr:street":"Calle De Santa Fe",
    "iso:country":"ES",
    "sg:address":"Calle de Santa Fe, 16",
    "sg:city":"Toledo",
    "sg:orig_category":"Asesor\u00cda Fiscal Y Jur\u00cddica",
    "sg:phone":"+34 925 28 05 47",
    "sg:postcode":"45001",
    "sg:province":"Toledo",
    "wof:name":"Duran Ortega Jorge",
    "wof:placetype":"venue"
},
  "geometry": {"coordinates":[-4.0206561089,39.8598480225],"type":"Point"}
}