{
  "type": "Feature",
  "properties": {
    "addr:full":"Rafel De Casanova, 4 Llardecans Lleida 25186",
    "addr:housenumber":"4",
    "addr:postcode":"25186",
    "iso:country":"ES",
    "sg:address":"Rafel De Casanova, 4",
    "sg:city":"Llardecans",
    "sg:orig_category":"Estudios, Instalaci\u00d3n De Climatizaci\u00d3n",
    "sg:phone":"+34 973 13 02 86",
    "sg:postcode":"25186",
    "sg:province":"Lleida",
    "wof:name":"Garcia Gimenez Miguel",
    "wof:placetype":"venue"
},
  "geometry": {"coordinates":[0.5487729907,41.3746910095],"type":"Point"}
}