{
  "type": "Feature",
  "properties": {
    "iso:country":"ES",
    "sg:address":"Calle de Nuestro Padre Jesus Nazareno, 68",
    "sg:city":"Moguer",
    "sg:orig_category":"Promotores Constructores",
    "sg:phone":"+34 959 37 04 12",
    "sg:postcode":"21800",
    "sg:province":"Huelva",
    "wof:name":"Construcciones Azualba S.l.l",
    "wof:placetype":"venue"
},
  "geometry": {"coordinates":[-6.8326392174,37.280670166],"type":"Point"}
}