{
  "type": "Feature",
  "properties": {
    "iso:country":"ES",
    "sg:address":"Avda Cameranos, 10",
    "sg:city":"Zafra",
    "sg:orig_category":"Puertas Y Portales",
    "sg:phone":"+34 924 55 43 44",
    "sg:postcode":"06300",
    "sg:province":"Badajoz",
    "wof:name":"Jose Esteban Martin Gutierrez Y Otro Cdad",
    "wof:placetype":"venue"
},
  "geometry": {"coordinates":[-6.4112248421,38.419834137],"type":"Point"}
}