{
  "type": "Feature",
  "properties": {
    "iso:country":"ES",
    "sg:address":"Can Barbut, 10",
    "sg:city":"Alaro",
    "sg:orig_category":"Alimentaci\u00d3n General (al Por Menor)",
    "sg:phone":"+34 971 51 03 21",
    "sg:postcode":"07340",
    "sg:province":"Islas Baleares",
    "wof:name":"Crespi Ordinas Margarita",
    "wof:placetype":"venue"
},
  "geometry": {"coordinates":[2.7900950909,39.7046737671],"type":"Point"}
}