{
  "type": "Feature",
  "properties": {
    "addr:full":"Calle de Batalla Del Salado, 36 Madrid Madrid 28045",
    "addr:housenumber":"36",
    "addr:postcode":"madrid;28045",
    "addr:street":"Calle De Batalla Del Salado",
    "iso:country":"ES",
    "sg:address":"Calle de Batalla Del Salado, 36",
    "sg:city":"Madrid",
    "sg:orig_category":"Fabricaci\u00d3n, Venta De Cuadros, Accesorios Para Enmarcar",
    "sg:phone":"+34 915 30 99 22",
    "sg:postcode":"28045",
    "sg:province":"Madrid",
    "wof:name":"Moran Vazquez Leopoldo",
    "wof:placetype":"venue"
},
  "geometry": {"coordinates":[-3.6964008808,40.3988265991],"type":"Point"}
}