{
  "type": "Feature",
  "properties": {
    "iso:country":"ES",
    "sg:address":"Calle de Libreros, 3",
    "sg:city":"Valencia",
    "sg:orig_category":"Cl\u00cdnicas Dentales",
    "sg:phone":"+34 963 52 96 74",
    "sg:postcode":"46002",
    "sg:province":"Valencia",
    "wof:name":"Reig Martinez Pedro",
    "wof:placetype":"venue"
},
  "geometry": {"coordinates":[-0.3738740087,39.4727935791],"type":"Point"}
}