{
  "type": "Feature",
  "properties": {
    "iso:country":"ES",
    "sg:address":"Errotazar, 36",
    "sg:city":"Iru\u00f1a",
    "sg:orig_category":"Reparaci\u00d3n Y Restauraci\u00d3n De Objetos Diversos",
    "sg:phone":"+34 948 12 75 01",
    "sg:postcode":"31014",
    "sg:province":"Navarra",
    "wof:name":"Aurelio Martinez Y Alejandro Zaratiegui S.l.",
    "wof:placetype":"venue"
},
  "geometry": {"coordinates":[-1.6454960108,42.8243141174],"type":"Point"}
}