{
  "type": "Feature",
  "properties": {
    "addr:full":"Avda Juan De La Cierva, 27 Getafe Madrid 28902",
    "addr:housenumber":"27",
    "addr:postcode":"28902",
    "addr:street":"Avda Juan De La Cierva",
    "iso:country":"ES",
    "sg:address":"Avda Juan De La Cierva, 27",
    "sg:city":"Getafe",
    "sg:orig_category":"Cl\u00cdnicas M\u00c9dicas",
    "sg:phone":"+34 916 81 74 99",
    "sg:postcode":"28902",
    "sg:province":"Madrid",
    "wof:name":"Mengual Diez Juan Jose",
    "wof:placetype":"venue"
},
  "geometry": {"coordinates":[-3.725219965,40.3082962036],"type":"Point"}
}