{
  "type": "Feature",
  "properties": {
    "addr:full":"Carr Ciutat De Castello, 31 Vila Joiosa Alicante 03570",
    "addr:housenumber":"31",
    "addr:postcode":"03570",
    "addr:street":"Carr Ciutat De Castello",
    "iso:country":"ES",
    "sg:address":"Carr Ciutat De Castello, 31",
    "sg:city":"Vila Joiosa",
    "sg:orig_category":"Plomeros",
    "sg:phone":"+34 966 81 00 87",
    "sg:postcode":"03570",
    "sg:province":"Alicante",
    "wof:name":"Fontaneria T Y D S.a.l.",
    "wof:placetype":"venue"
},
  "geometry": {"coordinates":[-0.2348919958,38.5089263916],"type":"Point"}
}