{
  "type": "Feature",
  "properties": {
    "iso:country":"ES",
    "sg:address":"Rua Emilia Pardo Bazan, 17",
    "sg:city":"Celanova",
    "sg:orig_category":"Partidos Pol\u00cdticos",
    "sg:phone":"+34 988 43 10 03",
    "sg:postcode":"32800",
    "sg:province":"Ourense",
    "wof:name":"Partido Socialista Obrero Espa\u00d1ol",
    "wof:placetype":"venue"
},
  "geometry": {"coordinates":[-7.9575572014,42.1531715393],"type":"Point"}
}