{
  "type": "Feature",
  "properties": {
    "iso:country":"ES",
    "sg:address":"Barr Estacio, S/n",
    "sg:city":"Planes D'hostoles",
    "sg:orig_category":"Herramientas Manuales (fabricaci\u00d3n, Al Por Mayor)",
    "sg:phone":"+34 972 44 80 79",
    "sg:postcode":"17172",
    "sg:province":"Girona",
    "wof:name":"Isidro Arnau S. A.",
    "wof:placetype":"venue"
},
  "geometry": {"coordinates":[2.8086740971,41.9922447205],"type":"Point"}
}