{
  "type": "Feature",
  "properties": {
    "iso:country":"ES",
    "sg:address":"Calle de Uruguay, 1",
    "sg:city":"Toledo",
    "sg:orig_category":"Ropa Para Caballeros (al Por Menor)",
    "sg:phone":"+34 925 21 49 04",
    "sg:postcode":"45004",
    "sg:province":"Toledo",
    "sg:website":"www.felixramiro.com",
    "wof:name":"Ramirez Rodriguez Felix",
    "wof:placetype":"venue"
},
  "geometry": {"coordinates":[-4.0323009491,39.8673095703],"type":"Point"}
}