{
  "type": "Feature",
  "properties": {
    "addr:full":"Calle de San Pablo, 16 Linea De La Concepcion C\u00e1diz 11300",
    "addr:housenumber":"16",
    "addr:postcode":"11300",
    "addr:street":"Calle De San Pablo;Ca\u0301Diz",
    "iso:country":"ES",
    "sg:address":"Calle de San Pablo, 16",
    "sg:city":"Linea De La Concepcion",
    "sg:orig_category":"Herboristas (al Por Menor)",
    "sg:phone":"+34 956 76 08 83",
    "sg:postcode":"11300",
    "sg:province":"C\u00e1diz",
    "wof:name":"Cadenas Cuadrado Agustin",
    "wof:placetype":"venue"
},
  "geometry": {"coordinates":[-5.3492479324,36.1619873047],"type":"Point"}
}