{
  "type": "Feature",
  "properties": {
    "iso:country":"ES",
    "sg:address":"Calle de Victoriano Revelo, 19",
    "sg:city":"Moraleja",
    "sg:orig_category":"Bisuter\u00cda, Joyer\u00cda, Relojer\u00cda (al Por Menor)",
    "sg:phone":"+34 927 14 73 14",
    "sg:postcode":"10840",
    "sg:province":"C\u00e1ceres",
    "wof:name":"Maillo Hidalgo Amando Jose",
    "wof:placetype":"venue"
},
  "geometry": {"coordinates":[-6.6594109535,40.0696678162],"type":"Point"}
}