{
  "type": "Feature",
  "properties": {
    "iso:country":"ES",
    "sg:address":"Carrer de Escoles Pies, 16",
    "sg:city":"Barcelona",
    "sg:orig_category":"Agencias Y Agentes Comerciales, Representantes",
    "sg:phone":"+34 932 01 72 89",
    "sg:postcode":"08017",
    "sg:province":"Barcelona",
    "wof:name":"Import-export Beaumont S. A.",
    "wof:placetype":"venue"
},
  "geometry": {"coordinates":[2.13529706,41.3962478638],"type":"Point"}
}