{
  "type": "Feature",
  "properties": {
    "addr:full":"Avda Roquetas, 73 Roquetas Mar Almer\u00eda 04740",
    "addr:housenumber":"73",
    "addr:postcode":"04740",
    "addr:street":"Avda Roquetas;Mar Almeri\u0301A",
    "iso:country":"ES",
    "sg:address":"Avda Roquetas, 73",
    "sg:city":"Roquetas Mar",
    "sg:orig_category":"Bisuter\u00cda, Joyer\u00cda, Relojer\u00cda (al Por Menor)",
    "sg:phone":"+34 950 32 72 74",
    "sg:postcode":"04740",
    "sg:province":"Almer\u00eda",
    "wof:name":"Fernandez Antequera Soledad",
    "wof:placetype":"venue"
},
  "geometry": {"coordinates":[-2.6124989986,36.7638435364],"type":"Point"}
}