{
  "type": "Feature",
  "properties": {
    "addr:full":"Calle de Marques De Villores, 23 Albacete Albacete 02003",
    "addr:housenumber":"23",
    "addr:postcode":"02003",
    "addr:street":"Calle De Marques De Villores",
    "iso:country":"ES",
    "sg:address":"Calle de Marques De Villores, 23",
    "sg:city":"Albacete",
    "sg:orig_category":"Talleres De Corte Y Confecci\u00d3n",
    "sg:phone":"+34 967 50 54 25",
    "sg:postcode":"02003",
    "sg:province":"Albacete",
    "wof:name":"Molina Cullell Isabel",
    "wof:placetype":"venue"
},
  "geometry": {"coordinates":[-1.8573329449,38.9912261963],"type":"Point"}
}