{
  "type": "Feature",
  "properties": {
    "iso:country":"ES",
    "sg:address":"G.v. Lopez De Haro D. Diego, 8",
    "sg:city":"Bilbao",
    "sg:orig_category":"Expertos Contables, Revisores De Cuentas",
    "sg:phone":"+34 944 23 34 25",
    "sg:postcode":"48001",
    "sg:province":"Vizcaya",
    "wof:name":"Gesnor S. L.",
    "wof:placetype":"venue"
},
  "geometry": {"coordinates":[-2.9288609028,43.2618026733],"type":"Point"}
}