{
  "type": "Feature",
  "properties": {
    "iso:country":"ES",
    "sg:address":"Calle de Romea, 2",
    "sg:city":"Linares",
    "sg:orig_category":"Empresas De Impermeabilizaci\u00d3n",
    "sg:phone":"+34 953 69 22 14",
    "sg:postcode":"23700",
    "sg:province":"Ja\u00e9n",
    "wof:name":"Nu\u00f1ez Cerquera Salustiano",
    "wof:placetype":"venue"
},
  "geometry": {"coordinates":[-3.6306049824,38.0989532471],"type":"Point"}
}