{
  "type": "Feature",
  "properties": {
    "iso:country":"ES",
    "sg:address":"Calle de Europa, 21",
    "sg:city":"Irun",
    "sg:orig_category":"Transportes Frigor\u00cdficos",
    "sg:phone":"+34 943 63 20 00",
    "sg:postcode":"20305",
    "sg:province":"Guip\u00f9zcoa",
    "wof:name":"Sdf Pais Vasco S.a.",
    "wof:placetype":"venue"
},
  "geometry": {"coordinates":[-1.7557909489,43.3409881592],"type":"Point"}
}