{
  "type": "Feature",
  "properties": {
    "iso:country":"ES",
    "sg:address":"Avda Pablo Picasso, 6",
    "sg:city":"Granada",
    "sg:orig_category":"Inform\u00c1tica Equipo Y Programas (al Por Mayor)",
    "sg:phone":"+34 958 13 26 10",
    "sg:postcode":"18006",
    "sg:province":"Granada",
    "sg:website":"www.emg-biometricos.com",
    "wof:name":"Emilio Garcia Paniagua S.l.",
    "wof:placetype":"venue"
},
  "geometry": {"coordinates":[-3.5977749825,37.1632156372],"type":"Point"}
}