{
  "type": "Feature",
  "properties": {
    "addr:full":"Calle de Doctor Diaz Caneja, 9 Palencia Palencia 34002",
    "addr:housenumber":"9",
    "addr:postcode":"34002",
    "addr:street":"Calle De Doctor Diaz Caneja",
    "iso:country":"ES",
    "sg:address":"Calle de Doctor Diaz Caneja, 9",
    "sg:city":"Palencia",
    "sg:orig_category":"Molduras, Junquillos, Listones Y Molduras Perforadas",
    "sg:phone":"+34 979 71 17 00",
    "sg:postcode":"34002",
    "sg:province":"Palencia",
    "wof:name":"Alvarez Garcia Cesar Javier",
    "wof:placetype":"venue"
},
  "geometry": {"coordinates":[-4.5283226967,42.0018005371],"type":"Point"}
}