{
  "type": "Feature",
  "properties": {
    "iso:country":"ES",
    "sg:address":"C/ Ciutat D'onda, S/n",
    "sg:city":"Paterna",
    "sg:orig_category":"Muebles",
    "sg:phone":"+34 961 32 50 46",
    "sg:postcode":"46988",
    "sg:province":"Valencia",
    "wof:name":"Serunion S.a.",
    "wof:placetype":"venue"
},
  "geometry": {"coordinates":[-0.4395399988,39.500629425],"type":"Point"}
}