{
  "type": "Feature",
  "properties": {
    "addr:full":"Calle de Antonio Cumella, 7 Madrid Madrid 28030",
    "addr:housenumber":"7",
    "addr:postcode":"madrid;28030",
    "addr:street":"Calle De Antonio Cumella",
    "iso:country":"ES",
    "sg:address":"Calle de Antonio Cumella, 7",
    "sg:city":"Madrid",
    "sg:orig_category":"Guarder\u00cdas",
    "sg:phone":"+34 913 71 12 35",
    "sg:postcode":"28030",
    "sg:province":"Madrid",
    "wof:name":"Porta Villanueva Mercedes",
    "wof:placetype":"venue"
},
  "geometry": {"coordinates":[-3.6365551949,40.4094848633],"type":"Point"}
}