{
  "type": "Feature",
  "properties": {
    "iso:country":"ES",
    "sg:address":"Caserios De San Pedro, 10",
    "sg:city":"Caserios S. Pedro",
    "sg:orig_category":"Cr\u00cda De Animales",
    "sg:phone":"+34 945 46 42 48",
    "sg:postcode":"01138",
    "sg:province":"\u00c1lava",
    "wof:name":"Landetxe S.c.",
    "wof:placetype":"venue"
},
  "geometry": {"coordinates":[-2.6983869076,42.9099998474],"type":"Point"}
}