{
  "type": "Feature",
  "properties": {
    "iso:country":"ES",
    "sg:address":"Benisa, 6",
    "sg:city":"Teulada",
    "sg:orig_category":"Promotores Constructores",
    "sg:phone":"+34 965 74 01 34",
    "sg:postcode":"03725",
    "sg:province":"Alicante",
    "wof:name":"Ferrer Bertomeu Antonio",
    "wof:placetype":"venue"
},
  "geometry": {"coordinates":[0.1051350012,38.7279167175],"type":"Point"}
}