{
  "type": "Feature",
  "properties": {
    "addr:full":"Carrer de Proven\u00c7a, 477 Barcelona Barcelona 08025",
    "addr:housenumber":"477",
    "addr:postcode":"08025",
    "addr:street":"Carrer De Provenc\u0327A",
    "iso:country":"ES",
    "sg:address":"Carrer de Proven\u00c7a, 477",
    "sg:city":"Barcelona",
    "sg:orig_category":"Bisuter\u00cda, Joyer\u00cda, Relojer\u00cda (al Por Menor)",
    "sg:phone":"+34 934 56 53 53",
    "sg:postcode":"08025",
    "sg:province":"Barcelona",
    "wof:name":"Fina Garcia S.a.",
    "wof:placetype":"venue"
},
  "geometry": {"coordinates":[2.1762859821,41.4060287476],"type":"Point"}
}