{
  "type": "Feature",
  "properties": {
    "addr:full":"Calle de Victoria, 34 Ubeda Ja\u00e9n 23400",
    "addr:housenumber":"34",
    "addr:postcode":"23400",
    "addr:street":"Calle De Victoria;Jae\u0301N",
    "iso:country":"ES",
    "sg:address":"Calle de Victoria, 34",
    "sg:city":"Ubeda",
    "sg:orig_category":"Confecci\u00d3n (fabricaci\u00d3n, Al Por Mayor)",
    "sg:phone":"+34 953 75 79 91",
    "sg:postcode":"23400",
    "sg:province":"Ja\u00e9n",
    "wof:name":"Fernandez Garcia Alfonso",
    "wof:placetype":"venue"
},
  "geometry": {"coordinates":[-3.3753449917,38.0119552612],"type":"Point"}
}