{
  "type": "Feature",
  "properties": {
    "addr:full":"Avda Angel, 20 Getxo Vizcaya 48990",
    "addr:housenumber":"20",
    "addr:postcode":"48990",
    "addr:street":"Avda Angel",
    "iso:country":"ES",
    "sg:address":"Avda Angel, 20",
    "sg:city":"Getxo",
    "sg:orig_category":"Congelados: Productos Alimentarios (fabricaci\u00d3n, Al Por Mayor)",
    "sg:phone":"+34 944 60 10 11",
    "sg:postcode":"48990",
    "sg:province":"Vizcaya",
    "wof:name":"Distribuciones Diez Goitia S.l.",
    "wof:placetype":"venue"
},
  "geometry": {"coordinates":[-3.0163650513,43.3589363098],"type":"Point"}
}