{
  "type": "Feature",
  "properties": {
    "iso:country":"ES",
    "sg:address":"Calle de Jose Maria Lillo, 35",
    "sg:city":"Mengibar",
    "sg:orig_category":"Cl\u00cdnicas M\u00c9dicas",
    "sg:phone":"+34 953 37 05 00",
    "sg:postcode":"23620",
    "sg:province":"Ja\u00e9n",
    "wof:name":"Clinica Magdalena S.l.",
    "wof:placetype":"venue"
},
  "geometry": {"coordinates":[-3.8059389591,37.9688873291],"type":"Point"}
}