{
  "type": "Feature",
  "properties": {
    "iso:country":"ES",
    "sg:address":"Rond Paisos Catalans (dels), 27",
    "sg:city":"Mataro",
    "sg:orig_category":"Ropa Para Se\u00d1oras (al Por Menor)",
    "sg:phone":"+34 937 58 63 03",
    "sg:postcode":"08304",
    "sg:province":"Barcelona",
    "wof:name":"Raco De L'infant S.l.",
    "wof:placetype":"venue"
},
  "geometry": {"coordinates":[2.4389870167,41.5539283752],"type":"Point"}
}