{
  "type": "Feature",
  "properties": {
    "addr:full":"Calle de San Millan, 5 Malaga M\u00e1laga 29013",
    "addr:housenumber":"5",
    "addr:postcode":"29013",
    "addr:street":"Calle De San Millan;Ma\u0301Laga",
    "iso:country":"ES",
    "sg:address":"Calle de San Millan, 5",
    "sg:city":"Malaga",
    "sg:orig_category":"Administradores De Bienes Y Delegados De Comunidades De Propietarios",
    "sg:phone":"+34 952 25 03 05",
    "sg:postcode":"29013",
    "sg:province":"M\u00e1laga",
    "wof:name":"Gallego Monserrate Gustavo",
    "wof:placetype":"venue"
},
  "geometry": {"coordinates":[-4.4202947617,36.7271652222],"type":"Point"}
}