{
  "type": "Feature",
  "properties": {
    "iso:country":"ES",
    "sg:address":"Calle de Alcalde Francisco Arnau, 15",
    "sg:city":"Segorbe",
    "sg:orig_category":"Peluqueros: De Se\u00d1oras",
    "sg:phone":"+34 964 71 35 36",
    "sg:postcode":"12400",
    "sg:province":"Castell\u00f3n",
    "wof:name":"Minguez Sanz Juan Manuel",
    "wof:placetype":"venue"
},
  "geometry": {"coordinates":[-0.4928149879,39.8503112793],"type":"Point"}
}