{
  "type": "Feature",
  "properties": {
    "iso:country":"ES",
    "sg:address":"Calle de Calvario, 11",
    "sg:city":"Marbella",
    "sg:orig_category":"Centros De Educaci\u00d3n Especial",
    "sg:phone":"+34 952 86 54 42",
    "sg:postcode":"29600",
    "sg:province":"M\u00e1laga",
    "wof:name":"Gongora Zanettini Catia Regina",
    "wof:placetype":"venue"
},
  "geometry": {"coordinates":[-4.8911457062,36.5145988464],"type":"Point"}
}