{
  "type": "Feature",
  "properties": {
    "iso:country":"ES",
    "sg:address":"Calle de Colon, S/n",
    "sg:city":"Puebla De Los Infantes",
    "sg:orig_category":"Producci\u00d3n De Abonos Y De Fertilizantes",
    "sg:phone":"+34 954 80 82 63",
    "sg:postcode":"41479",
    "sg:province":"Sevilla",
    "wof:name":"Fertilizantes Y Agroquimicos Roman S.l.",
    "wof:placetype":"venue"
},
  "geometry": {"coordinates":[-5.3910474777,37.781993866],"type":"Point"}
}