{
  "type": "Feature",
  "properties": {
    "addr:full":"Calle de Fraga, 48 Torrente Cinca Huesca 22590",
    "addr:housenumber":"48",
    "addr:postcode":"22590",
    "addr:street":"Calle De Fraga",
    "iso:country":"ES",
    "sg:address":"Calle de Fraga, 48",
    "sg:city":"Torrente Cinca",
    "sg:orig_category":"Construcci\u00d3n Mec\u00c1nica",
    "sg:phone":"+34 974 46 71 47",
    "sg:postcode":"22590",
    "sg:province":"Huesca",
    "wof:name":"Nevado Perez Antonio",
    "wof:placetype":"venue"
},
  "geometry": {"coordinates":[0.3349699974,41.4747695923],"type":"Point"}
}