{
  "type": "Feature",
  "properties": {
    "addr:full":"Calle de San Isidro, 13 Lugo De Llanera Asturias 33690",
    "addr:housenumber":"13",
    "addr:postcode":"33690",
    "addr:street":"Calle De San Isidro",
    "iso:country":"ES",
    "sg:address":"Calle de San Isidro, 13",
    "sg:city":"Lugo De Llanera",
    "sg:orig_category":"Suministros Y Materiales Industriales",
    "sg:phone":"+34 985 77 17 58",
    "sg:postcode":"33690",
    "sg:province":"Asturias",
    "wof:name":"Herma Del Principado S.l.",
    "wof:placetype":"venue"
},
  "geometry": {"coordinates":[-5.8168787956,43.441280365],"type":"Point"}
}