{
  "type": "Feature",
  "properties": {
    "addr:full":"Cno Mar, S/n Sagunt Valencia 46500",
    "addr:housenumber":"/ n",
    "addr:postcode":"46500",
    "addr:street":"Cno Mar S",
    "iso:country":"ES",
    "sg:address":"Cno Mar, S/n",
    "sg:city":"Sagunt",
    "sg:orig_category":"Frutas Y Legumbres Frescas (al Por Mayor)",
    "sg:phone":"+34 962 66 13 63",
    "sg:postcode":"46500",
    "sg:province":"Valencia",
    "wof:name":"Vilfruit S.l.",
    "wof:placetype":"venue"
},
  "geometry": {"coordinates":[-0.2783089876,39.6799659729],"type":"Point"}
}