{
  "type": "Feature",
  "properties": {
    "iso:country":"ES",
    "sg:address":"Avda Marques De La Vega De Armijo, 64",
    "sg:city":"Montilla",
    "sg:orig_category":"Construcci\u00d3n Mec\u00c1nica",
    "sg:phone":"+34 957 65 04 94",
    "sg:postcode":"14550",
    "sg:province":"C\u00f3rdoba",
    "wof:name":"Talleres Garcia Construcciones Mecanicas S.l.",
    "wof:placetype":"venue"
},
  "geometry": {"coordinates":[-4.6322212219,37.587020874],"type":"Point"}
}