{
  "type": "Feature",
  "properties": {
    "addr:full":"Carrer de Emporda, 8 Cornella Llobregat Barcelona 08940",
    "addr:housenumber":"8",
    "addr:postcode":"08940",
    "addr:street":"Carrer De Emporda",
    "iso:country":"ES",
    "sg:address":"Carrer de Emporda, 8",
    "sg:city":"Cornella Llobregat",
    "sg:orig_category":"Muebles Y Accesorios Para Cocinas Y Cuartos De Ba\u00d1o (al Por Menor)",
    "sg:phone":"+34 933 76 50 01",
    "sg:postcode":"08940",
    "sg:province":"Barcelona",
    "wof:name":"Tena Moriana Joaquin",
    "wof:placetype":"venue"
},
  "geometry": {"coordinates":[2.0796608925,41.358581543],"type":"Point"}
}