{
  "type": "Feature",
  "properties": {
    "addr:full":"Avda Eusebio Gomez, 12 Saron Cantabria 39620",
    "addr:housenumber":"12",
    "addr:postcode":"39620",
    "addr:street":"Avda Eusebio Gomez",
    "iso:country":"ES",
    "sg:address":"Avda Eusebio Gomez, 12",
    "sg:city":"Saron",
    "sg:orig_category":"Pescader\u00cdas (al Por Menor)",
    "sg:phone":"+34 942 56 35 98",
    "sg:postcode":"39620",
    "sg:province":"Cantabria",
    "wof:name":"Valle Gomez Avelino",
    "wof:placetype":"venue"
},
  "geometry": {"coordinates":[-3.8524999619,43.3253364563],"type":"Point"}
}