{
  "type": "Feature",
  "properties": {
    "iso:country":"ES",
    "sg:address":"Calle de Merced (la), 4",
    "sg:city":"Utiel",
    "sg:orig_category":"Agencias Y Agentes Comerciales, Representantes",
    "sg:phone":"+34 962 17 01 87",
    "sg:postcode":"46300",
    "sg:province":"Valencia",
    "wof:name":"Ortola Y Garzaran Sociedad Limitada Agencia De Seguros",
    "wof:placetype":"venue"
},
  "geometry": {"coordinates":[-1.2017029524,39.5658798218],"type":"Point"}
}