{
  "type": "Feature",
  "properties": {
    "addr:full":"Calle de Navarra, 118 Castellon Castell\u00f3n 12002",
    "addr:housenumber":"118",
    "addr:postcode":"12002",
    "addr:street":"Calle De Navarra;Castello\u0301N",
    "iso:country":"ES",
    "sg:address":"Calle de Navarra, 118",
    "sg:city":"Castellon",
    "sg:orig_category":"Arquitectos",
    "sg:phone":"+34 964 21 21 99",
    "sg:postcode":"12002",
    "sg:province":"Castell\u00f3n",
    "wof:name":"Font Suay Guillermo",
    "wof:placetype":"venue"
},
  "geometry": {"coordinates":[-0.0432629995,39.9847412109],"type":"Point"}
}