{
  "type": "Feature",
  "properties": {
    "iso:country":"ES",
    "sg:address":"Calle de Gonzalez Besada, 21",
    "sg:city":"Oviedo",
    "sg:orig_category":"Asesor\u00cdas Y Estudios Financieros",
    "sg:phone":"+34 985 23 60 89",
    "sg:postcode":"33007",
    "sg:province":"Asturias",
    "wof:name":"Gonzalez Fernandez Pelayo",
    "wof:placetype":"venue"
},
  "geometry": {"coordinates":[-5.8498048782,43.3565940857],"type":"Point"}
}