{
  "type": "Feature",
  "properties": {
    "addr:full":"Calle de General Lopez Brea, 2 Quintanar Orden Toledo 45800",
    "addr:housenumber":"2",
    "addr:postcode":"45800",
    "addr:street":"Calle De General Lopez Brea",
    "iso:country":"ES",
    "sg:address":"Calle de General Lopez Brea, 2",
    "sg:city":"Quintanar Orden",
    "sg:orig_category":"Cl\u00cdnicas M\u00c9dicas",
    "sg:phone":"+34 925 56 40 01",
    "sg:postcode":"45800",
    "sg:province":"Toledo",
    "wof:name":"C.m.q. Servicios Medicos S.l.",
    "wof:placetype":"venue"
},
  "geometry": {"coordinates":[-3.0416009426,39.5888252258],"type":"Point"}
}