{
  "type": "Feature",
  "properties": {
    "addr:full":"Calle de Sevilla, 25 Zafra Badajoz 06300",
    "addr:housenumber":"25",
    "addr:postcode":"06300",
    "addr:street":"Calle De Sevilla",
    "iso:country":"ES",
    "sg:address":"Calle de Sevilla, 25",
    "sg:city":"Zafra",
    "sg:orig_category":"Confecci\u00d3n (fabricaci\u00d3n, Al Por Mayor)",
    "sg:phone":"+34 924 55 34 77",
    "sg:postcode":"06300",
    "sg:province":"Badajoz",
    "wof:name":"Llera Rocha Maria Fernanda",
    "wof:placetype":"venue"
},
  "geometry": {"coordinates":[-6.418489933,38.4240379333],"type":"Point"}
}