{
  "type": "Feature",
  "properties": {
    "addr:full":"Calle de Mayor, 15 Vinaros Castell\u00f3n 12500",
    "addr:housenumber":"15",
    "addr:postcode":"12500",
    "addr:street":"Calle De Mayor",
    "iso:country":"ES",
    "sg:address":"Calle de Mayor, 15",
    "sg:city":"Vinaros",
    "sg:orig_category":"Bazares, Art\u00cdculos De Limpieza Y De Cocina (al Por Menor)",
    "sg:phone":"+34 964 45 10 79",
    "sg:postcode":"12500",
    "sg:province":"Castell\u00f3n",
    "wof:name":"Bazar Abella S.l.",
    "wof:placetype":"venue"
},
  "geometry": {"coordinates":[0.4749450088,40.4711990356],"type":"Point"}
}