{
  "type": "Feature",
  "properties": {
    "iso:country":"ES",
    "sg:address":"Calle de San Isidoro, 1",
    "sg:city":"Granada",
    "sg:orig_category":"Electricidad Veh\u00cdculo",
    "sg:phone":"+34 958 20 11 21",
    "sg:postcode":"18003",
    "sg:province":"Granada",
    "wof:name":"Palomo Castillo Manuel",
    "wof:placetype":"venue"
},
  "geometry": {"coordinates":[-3.6102240086,37.1762619019],"type":"Point"}
}