{
  "type": "Feature",
  "properties": {
    "iso:country":"ES",
    "sg:address":"Avda Zarandona, 41",
    "sg:city":"Zarandona",
    "sg:orig_category":"Piscinas, Accesorios, Suministros (fabricaci\u00d3n, Al Por Mayor)",
    "sg:phone":"+34 968 23 39 44",
    "sg:postcode":"30007",
    "sg:province":"Murcia",
    "wof:name":"Bazar Fermin S.l.",
    "wof:placetype":"venue"
},
  "geometry": {"coordinates":[-1.1158089638,38.007232666],"type":"Point"}
}