{
  "type": "Feature",
  "properties": {
    "addr:full":"Calle de Arcos, 9 Jerez De La Frontera C\u00e1diz 11402",
    "addr:housenumber":"9",
    "addr:postcode":"11402",
    "addr:street":"Calle De Arcos",
    "iso:country":"ES",
    "sg:address":"Calle de Arcos, 9",
    "sg:city":"Jerez De La Frontera",
    "sg:orig_category":"Mercer\u00cda, Lencer\u00cda (al Por Menor)",
    "sg:phone":"+34 956 33 82 63",
    "sg:postcode":"11402",
    "sg:province":"C\u00e1diz",
    "wof:name":"Benitez Gonzalez Maria Dolores",
    "wof:placetype":"venue"
},
  "geometry": {"coordinates":[-6.1347332001,36.6835746765],"type":"Point"}
}