{
  "type": "Feature",
  "properties": {
    "iso:country":"ES",
    "sg:address":"Carrer de Misericordia, 4",
    "sg:city":"Reus",
    "sg:orig_category":"Dietistas",
    "sg:phone":"+34 977 77 53 04",
    "sg:postcode":"43205",
    "sg:province":"Tarragona",
    "wof:name":"Arroyo Borroy Maria Luisa",
    "wof:placetype":"venue"
},
  "geometry": {"coordinates":[1.1085963249,41.1525306702],"type":"Point"}
}