{
  "type": "Feature",
  "properties": {
    "iso:country":"ES",
    "sg:address":"Avda Segovia, 63",
    "sg:city":"Valladolid",
    "sg:orig_category":"Fabricaci\u00d3n, Venta De Cuadros, Accesorios Para Enmarcar",
    "sg:phone":"+34 983 23 82 44",
    "sg:postcode":"47013",
    "sg:province":"Valladolid",
    "wof:name":"Garcia Sanz Marina",
    "wof:placetype":"venue"
},
  "geometry": {"coordinates":[-4.7202320099,41.6409721375],"type":"Point"}
}