{
  "type": "Feature",
  "properties": {
    "iso:country":"ES",
    "sg:address":"Carrer de Jacint Verdaguer (de), 3",
    "sg:city":"Montornes Centre",
    "sg:orig_category":"Panader\u00cdas, Panader\u00cdas",
    "sg:phone":"+34 935 68 06 61",
    "sg:postcode":"08170",
    "sg:province":"Barcelona",
    "wof:name":"Pastisseria Vi\u00f1allonga S.l.",
    "wof:placetype":"venue"
},
  "geometry": {"coordinates":[2.2649900913,41.5424995422],"type":"Point"}
}