{
  "type": "Feature",
  "properties": {
    "iso:country":"ES",
    "sg:address":"Rond Segovia, 2",
    "sg:city":"Madrid",
    "sg:orig_category":"M\u00c9dicos: Geriatr\u00cda, Gerontolog\u00cda (enfermedades De La Tercera Edad)",
    "sg:phone":"+34 913 54 13 13",
    "sg:postcode":"28005",
    "sg:province":"Madrid",
    "wof:name":"Agrupacion De Centros Geriatricos",
    "wof:placetype":"venue"
},
  "geometry": {"coordinates":[-3.7177975178,40.4102973938],"type":"Point"}
}