{
  "type": "Feature",
  "properties": {
    "addr:full":"Avda Monforte De Lemos, 101 Madrid Madrid 28029",
    "addr:housenumber":"101",
    "addr:postcode":"28029",
    "addr:street":"Avda Monforte De Lemos",
    "iso:country":"ES",
    "sg:address":"Avda Monforte De Lemos, 101",
    "sg:city":"Madrid",
    "sg:orig_category":"Cristaler\u00cdas",
    "sg:phone":"+34 917 30 21 42",
    "sg:postcode":"28029",
    "sg:province":"Madrid",
    "wof:name":"Garcia Gomez Jose",
    "wof:placetype":"venue"
},
  "geometry": {"coordinates":[-3.7053320408,40.4789886475],"type":"Point"}
}