{
  "type": "Feature",
  "properties": {
    "iso:country":"ES",
    "sg:address":"Carr Juan Xxiii, 22",
    "sg:city":"Canals",
    "sg:orig_category":"Tintes (fabricaci\u00d3n, Al Por Mayor)",
    "sg:phone":"+34 962 24 05 53",
    "sg:postcode":"46650",
    "sg:province":"Valencia",
    "wof:name":"Garrigos Navalon Manuel",
    "wof:placetype":"venue"
},
  "geometry": {"coordinates":[-0.5813919902,38.961479187],"type":"Point"}
}