{
  "type": "Feature",
  "properties": {
    "iso:country":"ES",
    "sg:address":"Carrer de Torras I Pujalt, 12",
    "sg:city":"Barcelona",
    "sg:orig_category":"Ingenier\u00cda, Centros De Estudios (diversos)",
    "sg:phone":"+34 934 18 15 18",
    "sg:postcode":"08022",
    "sg:province":"Barcelona",
    "wof:name":"Abadia Pocino Leopoldo",
    "wof:placetype":"venue"
},
  "geometry": {"coordinates":[2.134593,41.401039],"type":"Point"}
}