{
  "type": "Feature",
  "properties": {
    "addr:full":"C/ Vicente Fuentes Sansano, 35 Elche Alicante 03205",
    "addr:housenumber":"35",
    "addr:postcode":"03205",
    "addr:street":"C / Vicente Fuentes Sansano",
    "iso:country":"ES",
    "sg:address":"C/ Vicente Fuentes Sansano, 35",
    "sg:city":"Elche",
    "sg:orig_category":"Promotores Constructores",
    "sg:phone":"+34 965 43 57 00",
    "sg:postcode":"03205",
    "sg:province":"Alicante",
    "wof:name":"Construcciones Tecar 2004 S.l.",
    "wof:placetype":"venue"
},
  "geometry": {"coordinates":[-0.7156919837,38.2690658569],"type":"Point"}
}