{
  "type": "Feature",
  "properties": {
    "addr:full":"Avd. Industriales, S/n La Solana Ciudad Real 13240",
    "addr:housenumber":"s / n",
    "addr:postcode":"13240",
    "addr:street":"Industriales;La Solana;Real",
    "iso:country":"ES",
    "sg:address":"Avd. Industriales, S/n",
    "sg:city":"La Solana",
    "sg:orig_category":"Muebles Y Accesorios Para Cocinas Y Cuartos De Ba\u00d1o (al Por Menor)",
    "sg:phone":"+34 926 64 85 28",
    "sg:postcode":"13240",
    "sg:province":"Ciudad Real",
    "wof:name":"Muebles De Cocina Y Ba\u00f1o Mansol S.l.l.",
    "wof:placetype":"venue"
},
  "geometry": {"coordinates":[-3.2599489689,38.9395713806],"type":"Point"}
}