{
  "type": "Feature",
  "properties": {
    "addr:full":"Calle de Iparbide, 15 Getxo Vizcaya 48990",
    "addr:housenumber":"15",
    "addr:postcode":"48990",
    "addr:street":"Calle De Iparbide",
    "iso:country":"ES",
    "sg:address":"Calle de Iparbide, 15",
    "sg:city":"Getxo",
    "sg:orig_category":"Peluquer\u00cdas, Peluquer\u00cda Mixta",
    "sg:phone":"+34 944 06 94 13",
    "sg:postcode":"48990",
    "sg:province":"Vizcaya",
    "wof:name":"Maria Polo Azkorra",
    "wof:placetype":"venue"
},
  "geometry": {"coordinates":[-3.0049099922,43.3484611511],"type":"Point"}
}