{
  "type": "Feature",
  "properties": {
    "iso:country":"ES",
    "sg:address":"Rua Galicia (de), 45",
    "sg:city":"Vilalba",
    "sg:orig_category":"Aparcamientos (infraestructuras, Accesorios)",
    "sg:phone":"+34 982 51 07 06",
    "sg:postcode":"27800",
    "sg:province":"Lugo",
    "wof:name":"Garaje Roma De Villalba S.l.",
    "wof:placetype":"venue"
},
  "geometry": {"coordinates":[-7.6838989258,43.297580719],"type":"Point"}
}