{
  "type": "Feature",
  "properties": {
    "addr:full":"Avda Albufera, 78 Madrid Madrid 28038",
    "addr:housenumber":"78",
    "addr:postcode":"madrid;28038",
    "addr:street":"Avda Albufera",
    "iso:country":"ES",
    "sg:address":"Avda Albufera, 78",
    "sg:city":"Madrid",
    "sg:orig_category":"Ense\u00d1anza Secundaria: Colegios Y Escuelas Privadas",
    "sg:phone":"+34 914 77 38 09",
    "sg:postcode":"28038",
    "sg:province":"Madrid",
    "wof:name":"I.e.s. Vallecas I",
    "wof:placetype":"venue"
},
  "geometry": {"coordinates":[-3.663189888,40.3949737549],"type":"Point"}
}