{
  "type": "Feature",
  "properties": {
    "addr:full":"Carrer de Montornes, 37 Barcelona Barcelona 08023",
    "addr:housenumber":"37",
    "addr:postcode":"08023",
    "addr:street":"Carrer De Montornes",
    "iso:country":"ES",
    "sg:address":"Carrer de Montornes, 37",
    "sg:city":"Barcelona",
    "sg:orig_category":"Ense\u00d1anza: Profesiones Art\u00cdsticas",
    "sg:phone":"+34 932 11 10 62",
    "sg:postcode":"08023",
    "sg:province":"Barcelona",
    "wof:name":"Fundacio Conservatori Del Liceu",
    "wof:placetype":"venue"
},
  "geometry": {"coordinates":[2.1427869797,41.4186248779],"type":"Point"}
}