{
  "type": "Feature",
  "properties": {
    "iso:country":"ES",
    "sg:address":"Calle de Puerta De Granada, 15",
    "sg:city":"Roda",
    "sg:orig_category":"Asesor\u00cda Sobre Comunicaci\u00d3n De Empresas",
    "sg:phone":"+34 967 44 34 96",
    "sg:postcode":"02630",
    "sg:province":"Albacete",
    "wof:name":"Tep Asesores S.l.",
    "wof:placetype":"venue"
},
  "geometry": {"coordinates":[-2.1609370708,39.2042655945],"type":"Point"}
}