{
  "type": "Feature",
  "properties": {
    "addr:full":"Calle de Martinez Maldonado, 38 Malaga M\u00e1laga 29007",
    "addr:housenumber":"38",
    "addr:postcode":"29007",
    "addr:street":"Calle De Martinez Maldonado;Ma\u0301Laga",
    "iso:country":"ES",
    "sg:address":"Calle de Martinez Maldonado, 38",
    "sg:city":"Malaga",
    "sg:orig_category":"Inmobiliaria (agencias)",
    "sg:phone":"+34 952 30 59 56",
    "sg:postcode":"29007",
    "sg:province":"M\u00e1laga",
    "wof:name":"Gatto  Diego",
    "wof:placetype":"venue"
},
  "geometry": {"coordinates":[-4.4351038933,36.7215881348],"type":"Point"}
}