{
  "type": "Feature",
  "properties": {
    "addr:full":"Carrer de Canigo, 83 Barcelona Barcelona 08031",
    "addr:housenumber":"83",
    "addr:postcode":"08031",
    "addr:street":"Carrer De Canigo",
    "iso:country":"ES",
    "sg:address":"Carrer de Canigo, 83",
    "sg:city":"Barcelona",
    "sg:orig_category":"Enfermeras: Consultas, Atenci\u00d3n A Domicilio",
    "sg:phone":"+34 934 27 02 03",
    "sg:postcode":"08031",
    "sg:province":"Barcelona",
    "wof:name":"Portell Mu\u00f1oz Jose",
    "wof:placetype":"venue"
},
  "geometry": {"coordinates":[2.1588430405,41.4362335205],"type":"Point"}
}