{
  "type": "Feature",
  "properties": {
    "addr:full":"Carr Juli Garreta, 10 Girona Girona 17002",
    "addr:housenumber":"10",
    "addr:postcode":"17002",
    "addr:street":"Carr Juli Garreta",
    "iso:country":"ES",
    "sg:address":"Carr Juli Garreta, 10",
    "sg:city":"Girona",
    "sg:orig_category":"Institutos De Belleza (productos Y Aparatos)",
    "sg:phone":"+34 972 21 28 85",
    "sg:postcode":"17002",
    "sg:province":"Girona",
    "wof:name":"J. Touron S. A.",
    "wof:placetype":"venue"
},
  "geometry": {"coordinates":[2.8194551468,41.9795570374],"type":"Point"}
}