{
  "type": "Feature",
  "properties": {
    "addr:full":"Avda Valencia, 26 Nules Castell\u00f3n 12520",
    "addr:housenumber":"26",
    "addr:postcode":"12520",
    "addr:street":"Avda Valencia",
    "iso:country":"ES",
    "sg:address":"Avda Valencia, 26",
    "sg:city":"Nules",
    "sg:orig_category":"Centros Comerciales Y Grandes Tiendas",
    "sg:phone":"+34 964 65 90 56",
    "sg:postcode":"12520",
    "sg:province":"Castell\u00f3n",
    "wof:name":"Julio Palau Arturo",
    "wof:placetype":"venue"
},
  "geometry": {"coordinates":[-0.1560139954,39.8508491516],"type":"Point"}
}