{
  "type": "Feature",
  "properties": {
    "iso:country":"ES",
    "sg:address":"Carr Marina, 60",
    "sg:city":"Badalona",
    "sg:orig_category":"Venta, Instalaci\u00d3n De Calefacci\u00d3n",
    "sg:phone":"+34 933 89 21 57",
    "sg:postcode":"08912",
    "sg:province":"Barcelona",
    "wof:name":"Guirao Garrido Carmelo",
    "wof:placetype":"venue"
},
  "geometry": {"coordinates":[2.2464530468,41.4474983215],"type":"Point"}
}