{
  "type": "Feature",
  "properties": {
    "iso:country":"ES",
    "sg:address":"Calle de Cruz, 13",
    "sg:city":"Sevilla",
    "sg:orig_category":"Alimentaci\u00d3n General (al Por Menor)",
    "sg:phone":"+34 954 23 11 08",
    "sg:postcode":"41013",
    "sg:province":"Sevilla",
    "wof:name":"Martin Martin Benjamin",
    "wof:placetype":"venue"
},
  "geometry": {"coordinates":[-5.9817934036,37.3750457764],"type":"Point"}
}