{
  "type": "Feature",
  "properties": {
    "addr:full":"Carrer de Josep Estivill, 67 Barcelona Barcelona 08027",
    "addr:housenumber":"67",
    "addr:postcode":"08027",
    "addr:street":"Carrer De Josep Estivill",
    "iso:country":"ES",
    "sg:address":"Carrer de Josep Estivill, 67",
    "sg:city":"Barcelona",
    "sg:orig_category":"Instalaci\u00d3n, Mantenimiento De Porteros Electr\u00d3nicos Y Controles De Acceso",
    "sg:phone":"+34 932 43 03 76",
    "sg:postcode":"08027",
    "sg:province":"Barcelona",
    "sg:website":"www.comedit.es",
    "wof:name":"Comedit Espa\u00f1a S.l.",
    "wof:placetype":"venue"
},
  "geometry": {"coordinates":[2.1900279522,41.4194030762],"type":"Point"}
}