{
  "type": "Feature",
  "properties": {
    "addr:full":"Calle de Granada, 32 Malaga M\u00e1laga 29015",
    "addr:housenumber":"32",
    "addr:postcode":"29015",
    "addr:street":"Calle De Granada;Ma\u0301Laga",
    "iso:country":"ES",
    "sg:address":"Calle de Granada, 32",
    "sg:city":"Malaga",
    "sg:orig_category":"M\u00c9dicos: Cardiolog\u00cda Y Afecciones Cardiovasculares",
    "sg:phone":"+34 952 22 74 76",
    "sg:postcode":"29015",
    "sg:province":"M\u00e1laga",
    "wof:name":"Salto Mendez-trelles Jose Maria",
    "wof:placetype":"venue"
},
  "geometry": {"coordinates":[-4.4200139046,36.7216148376],"type":"Point"}
}