{
  "type": "Feature",
  "properties": {
    "addr:full":"Pont Vell D'oliva, 35 Gandia Valencia 46700",
    "addr:housenumber":"35",
    "addr:postcode":"46700",
    "addr:street":"D'Oliva;Valencia",
    "iso:country":"ES",
    "sg:address":"Pont Vell D'oliva, 35",
    "sg:city":"Gandia",
    "sg:orig_category":"Cristaler\u00cdas",
    "sg:phone":"+34 962 86 16 99",
    "sg:postcode":"46700",
    "sg:province":"Valencia",
    "wof:name":"Alborch Maronda Jose Francisco",
    "wof:placetype":"venue"
},
  "geometry": {"coordinates":[-0.147300899,38.9352912903],"type":"Point"}
}