{
  "type": "Feature",
  "properties": {
    "addr:full":"Calle de Postas, 9 Vitoria-gasteiz \u00c1lava 01001",
    "addr:housenumber":"9",
    "addr:postcode":"01001",
    "addr:street":"Calle De Postas",
    "iso:country":"ES",
    "sg:address":"Calle de Postas, 9",
    "sg:city":"Vitoria-gasteiz",
    "sg:orig_category":"Sindicatos De Trabajadores",
    "sg:phone":"+34 945 14 78 44",
    "sg:postcode":"01001",
    "sg:province":"\u00c1lava",
    "wof:name":"Comisiones Obreras De Euskadi",
    "wof:placetype":"venue"
},
  "geometry": {"coordinates":[-2.6713829041,42.8460540771],"type":"Point"}
}