{
  "type": "Feature",
  "properties": {
    "addr:full":"Cant Grande, 16 Coru\u00d1a A Coru\u00f1a 15003",
    "addr:housenumber":"16",
    "addr:postcode":"15003",
    "addr:street":"Cant Grande;Corun\u0303A",
    "iso:country":"ES",
    "sg:address":"Cant Grande, 16",
    "sg:city":"Coru\u00d1a",
    "sg:orig_category":"Sociedades, Compa\u00d1\u00cdas Aseguradoras",
    "sg:phone":"+34 981 21 43 44",
    "sg:postcode":"15003",
    "sg:province":"A Coru\u00f1a",
    "wof:name":"Seguros Catalana Occidente S.a. De Seguros Y Reaseguros",
    "wof:placetype":"venue"
},
  "geometry": {"coordinates":[-8.4038801193,43.369720459],"type":"Point"}
}