{
  "type": "Feature",
  "properties": {
    "addr:full":"Callejon De Las Tinajas, 65 El Viso Alcor Sevilla 41520",
    "addr:housenumber":"65",
    "addr:postcode":"41520",
    "addr:street":"Callejon De Las Tinajas",
    "iso:country":"ES",
    "sg:address":"Callejon De Las Tinajas, 65",
    "sg:city":"El Viso Alcor",
    "sg:orig_category":"Cristaler\u00cdas",
    "sg:phone":"+34 955 94 63 75",
    "sg:postcode":"41520",
    "sg:province":"Sevilla",
    "wof:name":"Roldan Cadenas Manuel",
    "wof:placetype":"venue"
},
  "geometry": {"coordinates":[-5.7176990509,37.3943862915],"type":"Point"}
}