{
  "type": "Feature",
  "properties": {
    "addr:full":"Calle de Arabial, S/n Granada Granada 18003",
    "addr:housenumber":"s / n",
    "addr:postcode":"18003",
    "addr:street":"Calle De Arabial",
    "iso:country":"ES",
    "sg:address":"Calle de Arabial, S/n",
    "sg:city":"Granada",
    "sg:orig_category":"Inmobiliaria (agencias)",
    "sg:phone":"+34 958 53 51 89",
    "sg:postcode":"18003",
    "sg:province":"Granada",
    "wof:name":"Jardin De Fiesta S.l.",
    "wof:placetype":"venue"
},
  "geometry": {"coordinates":[-3.6118454933,37.177406311],"type":"Point"}
}