{
  "type": "Feature",
  "properties": {
    "addr:full":"Calle de Alboraya, 67 Valencia Valencia 46010",
    "addr:housenumber":"67",
    "addr:postcode":"46010",
    "addr:street":"Calle De Alboraya",
    "iso:country":"ES",
    "sg:address":"Calle de Alboraya, 67",
    "sg:city":"Valencia",
    "sg:orig_category":"Farmacias",
    "sg:phone":"+34 963 60 55 25",
    "sg:postcode":"46010",
    "sg:province":"Valencia",
    "wof:name":"Calvo Senent Josefa Maria",
    "wof:placetype":"venue"
},
  "geometry": {"coordinates":[-0.3681532145,39.4866981506],"type":"Point"}
}