{
  "type": "Feature",
  "properties": {
    "addr:full":"Praz Eugenio Fadrique, 3 Vigo Pontevedra 36208",
    "addr:housenumber":"3",
    "addr:postcode":"36208",
    "addr:street":"Praz Eugenio Fadrique",
    "iso:country":"ES",
    "sg:address":"Praz Eugenio Fadrique, 3",
    "sg:city":"Vigo",
    "sg:orig_category":"Electrodom\u00c9sticos (al Por Menor)",
    "sg:phone":"+34 986 23 20 36",
    "sg:postcode":"36208",
    "sg:province":"Pontevedra",
    "wof:name":"Sienes Barreiro Manuel Antonio Bernardo",
    "wof:placetype":"venue"
},
  "geometry": {"coordinates":[-8.7359991074,42.2242584229],"type":"Point"}
}