{
  "type": "Feature",
  "properties": {
    "iso:country":"ES",
    "sg:address":"Cno. Ayelo, S/n",
    "sg:city":"Olleria",
    "sg:orig_category":"Negocio De Madera",
    "sg:phone":"+34 962 20 22 10",
    "sg:postcode":"46850",
    "sg:province":"Valencia",
    "wof:name":"A.c. Valenciana Maderas S.l.",
    "wof:placetype":"venue"
},
  "geometry": {"coordinates":[-0.554148972,38.9132995605],"type":"Point"}
}