{
  "type": "Feature",
  "properties": {
    "iso:country":"ES",
    "sg:address":"Carr Casablanca (de), 67",
    "sg:city":"Almenara",
    "sg:orig_category":"Bazares, Art\u00cdculos De Limpieza Y De Cocina (al Por Menor)",
    "sg:phone":"+34 962 62 31 51",
    "sg:postcode":"12590",
    "sg:province":"Castell\u00f3n",
    "wof:name":"Mari Carmen Granell Calatallud Y Marina Granell Calatallud C.b.",
    "wof:placetype":"venue"
},
  "geometry": {"coordinates":[-0.2249779999,39.7515258789],"type":"Point"}
}