{
  "type": "Feature",
  "properties": {
    "iso:country":"ES",
    "sg:address":"Calle de Sancho Iv El Bravo, 21",
    "sg:city":"Tarifa",
    "sg:orig_category":"Cine (producci\u00d3n, Realizaci\u00d3n)",
    "sg:phone":"+34 956 62 72 90",
    "sg:postcode":"11380",
    "sg:province":"C\u00e1diz",
    "wof:name":"P.smith Location Services S.l.",
    "wof:placetype":"venue"
},
  "geometry": {"coordinates":[-5.6030640602,36.0127944946],"type":"Point"}
}