{
  "type": "Feature",
  "properties": {
    "addr:full":"Av Verge Montserrat, 112 Prat Llobregat Barcelona 08820",
    "addr:housenumber":"112",
    "addr:postcode":"08820",
    "addr:street":"Av Verge Montserrat;Llobregat",
    "iso:country":"ES",
    "sg:address":"Av Verge Montserrat, 112",
    "sg:city":"Prat Llobregat",
    "sg:orig_category":"Bancos",
    "sg:phone":"+34 933 79 55 00",
    "sg:postcode":"08820",
    "sg:province":"Barcelona",
    "wof:name":"Banco Popular Espa\u00f1ol",
    "wof:placetype":"venue"
},
  "geometry": {"coordinates":[2.094755888,41.325958252],"type":"Point"}
}