{
  "type": "Feature",
  "properties": {
    "iso:country":"ES",
    "sg:address":"Calle de Santa Eugenia, 25",
    "sg:city":"Getxo",
    "sg:orig_category":"Peluquer\u00cdas, Peluquer\u00cda Mixta",
    "sg:phone":"+34 944 63 39 91",
    "sg:postcode":"48930",
    "sg:province":"Vizcaya",
    "wof:name":"Maria Pilar Galletero Arenas",
    "wof:placetype":"venue"
},
  "geometry": {"coordinates":[-3.0076229572,43.3255882263],"type":"Point"}
}