{
  "type": "Feature",
  "properties": {
    "iso:country":"ES",
    "sg:address":"Calle de Cruz Del Molinillo, 33",
    "sg:city":"Malaga",
    "sg:orig_category":"Electrodom\u00c9sticos (al Por Menor)",
    "sg:phone":"+34 952 26 41 90",
    "sg:postcode":"29013",
    "sg:province":"M\u00e1laga",
    "wof:name":"Santiago Garcia Margarita",
    "wof:placetype":"venue"
},
  "geometry": {"coordinates":[-4.422770977,36.7272224426],"type":"Point"}
}