{
  "type": "Feature",
  "properties": {
    "addr:full":"Calle de Joaquin Turina, 15 Madrid Madrid 28044",
    "addr:housenumber":"15",
    "addr:postcode":"madrid;28044",
    "addr:street":"Calle De Joaquin Turina",
    "iso:country":"ES",
    "sg:address":"Calle de Joaquin Turina, 15",
    "sg:city":"Madrid",
    "sg:orig_category":"Florister\u00cdas",
    "sg:phone":"+34 915 08 11 13",
    "sg:postcode":"28044",
    "sg:province":"Madrid",
    "wof:name":"Prado Pascual Maria Soledad",
    "wof:placetype":"venue"
},
  "geometry": {"coordinates":[-3.7519600391,40.3729820251],"type":"Point"}
}