{
  "type": "Feature",
  "properties": {
    "addr:full":"Calle de Alcalde Manuel Oramas, 6 Pto. Rosario Las Palmas 35600",
    "addr:housenumber":"6",
    "addr:postcode":"35600",
    "addr:street":"Calle De Alcalde Manuel Oramas;Pto. Rosario Las",
    "iso:country":"ES",
    "sg:address":"Calle de Alcalde Manuel Oramas, 6",
    "sg:city":"Pto. Rosario",
    "sg:orig_category":"Delegados, Agentes De Tr\u00c1nsito, Auxiliares De Transporte Internacional",
    "sg:phone":"+34 928 85 25 08",
    "sg:postcode":"35600",
    "sg:province":"Las Palmas",
    "wof:name":"Consorcio Insular Mizar S.l.",
    "wof:placetype":"venue"
},
  "geometry": {"coordinates":[-13.8660554886,28.5050697327],"type":"Point"}
}