{
  "type": "Feature",
  "properties": {
    "addr:full":"G.v. Corts Catalanes, 1012 Barcelona Barcelona 08020",
    "addr:postcode":"1012;08020",
    "addr:street":"Catalanes",
    "iso:country":"ES",
    "sg:address":"G.v. Corts Catalanes, 1012",
    "sg:city":"Barcelona",
    "sg:orig_category":"Empresas De Limpieza",
    "sg:phone":"+34 932 66 46 22",
    "sg:postcode":"08020",
    "sg:province":"Barcelona",
    "wof:name":"Aldazabal De Mantenimientos Y Servicios S.l.",
    "wof:placetype":"venue"
},
  "geometry": {"coordinates":[2.1991081238,41.4119949341],"type":"Point"}
}