{
  "type": "Feature",
  "properties": {
    "iso:country":"ES",
    "sg:address":"Calle de Lersundi, 1",
    "sg:city":"Bilbao",
    "sg:orig_category":"Sociedades, Compa\u00d1\u00cdas Aseguradoras",
    "sg:phone":"+34 944 23 32 49",
    "sg:postcode":"48009",
    "sg:province":"Vizcaya",
    "wof:name":"Ordo\u00f1ez Peritaciones S.l.",
    "wof:placetype":"venue"
},
  "geometry": {"coordinates":[-2.9308729172,43.2662887573],"type":"Point"}
}