{
  "type": "Feature",
  "properties": {
    "iso:country":"ES",
    "sg:address":"Calle de Impresores, 23",
    "sg:city":"Getafe",
    "sg:orig_category":"Fabricaci\u00d3n Y Comercio De M\u00c1quinas",
    "sg:phone":"+34 916 65 15 28",
    "sg:postcode":"28906",
    "sg:province":"Madrid",
    "wof:name":"Quimilock S.a.",
    "wof:placetype":"venue"
},
  "geometry": {"coordinates":[-3.6988830566,40.3106155396],"type":"Point"}
}