{
  "type": "Feature",
  "properties": {
    "iso:country":"ES",
    "sg:address":"Calle de Vicente Beltran Grimal (escultor), 26",
    "sg:city":"Valencia",
    "sg:orig_category":"Asesor\u00cda Fiscal Y Jur\u00cddica",
    "sg:phone":"+34 963 30 15 93",
    "sg:postcode":"46023",
    "sg:province":"Valencia",
    "wof:name":"Orti Soler Salvador",
    "wof:placetype":"venue"
},
  "geometry": {"coordinates":[-0.347871989,39.4636497498],"type":"Point"}
}