{
  "type": "Feature",
  "properties": {
    "iso:country":"ES",
    "sg:address":"Carrer de Saturn, 2",
    "sg:city":"S. Adria Besos",
    "sg:orig_category":"Guarder\u00cdas",
    "sg:phone":"+34 933 81 68 50",
    "sg:postcode":"08930",
    "sg:province":"Barcelona",
    "wof:name":"Hijas De La Caridad De San Vicente De Paul",
    "wof:placetype":"venue"
},
  "geometry": {"coordinates":[2.2181699276,41.4181404114],"type":"Point"}
}