{
  "type": "Feature",
  "properties": {
    "addr:full":"Calle de Nueve De Mayo, S/n Oviedo Asturias 33002",
    "addr:housenumber":"s / n",
    "addr:postcode":"33002",
    "addr:street":"Calle De Nueve De Mayo",
    "iso:country":"ES",
    "sg:address":"Calle de Nueve De Mayo, S/n",
    "sg:city":"Oviedo",
    "sg:orig_category":"Estancos",
    "sg:phone":"+34 985 22 68 06",
    "sg:postcode":"33002",
    "sg:province":"Asturias",
    "wof:name":"Fernandez-ladreda Garcia-san Miguel Jose Maria",
    "wof:placetype":"venue"
},
  "geometry": {"coordinates":[-5.8498091698,43.3654441833],"type":"Point"}
}