{
  "type": "Feature",
  "properties": {
    "iso:country":"ES",
    "sg:address":"Calle de Nueva, 38",
    "sg:city":"Granja Torrehermosa",
    "sg:orig_category":"Tapicer\u00cdas",
    "sg:phone":"+34 924 89 60 27",
    "sg:postcode":"06910",
    "sg:province":"Badajoz",
    "wof:name":"Boza Pulgarin Adolfo",
    "wof:placetype":"venue"
},
  "geometry": {"coordinates":[-5.6022458076,38.3100814819],"type":"Point"}
}