{
  "type": "Feature",
  "properties": {
    "iso:country":"ES",
    "sg:address":"Carrer de Germans Sant Gabriel, 2",
    "sg:city":"Valls",
    "sg:orig_category":"Cl\u00cdnicas Dentales",
    "sg:phone":"+34 977 60 38 38",
    "sg:postcode":"43800",
    "sg:province":"Tarragona",
    "wof:name":"Valls Serveis Dentals S.l.",
    "wof:placetype":"venue"
},
  "geometry": {"coordinates":[1.2525299788,41.2871513367],"type":"Point"}
}