{
  "type": "Feature",
  "properties": {
    "addr:full":"Av Marignane, 16 Figueres Girona 17600",
    "addr:housenumber":"16",
    "addr:postcode":"17600",
    "addr:street":"Av Marignane",
    "iso:country":"ES",
    "sg:address":"Av Marignane, 16",
    "sg:city":"Figueres",
    "sg:orig_category":"Contables",
    "sg:phone":"+34 972 50 88 16",
    "sg:postcode":"17600",
    "sg:province":"Girona",
    "wof:name":"Gestinvertiam",
    "wof:placetype":"venue"
},
  "geometry": {"coordinates":[2.9555590153,42.2728919983],"type":"Point"}
}