{
  "type": "Feature",
  "properties": {
    "iso:country":"ES",
    "sg:address":"Rua Celso Emilio Ferreiro, 2",
    "sg:city":"Celanova",
    "sg:orig_category":"Alimentaci\u00d3n General (al Por Menor)",
    "sg:phone":"+34 988 43 19 56",
    "sg:postcode":"32800",
    "sg:province":"Ourense",
    "wof:name":"Cereijo Diaz Emilia",
    "wof:placetype":"venue"
},
  "geometry": {"coordinates":[-7.9568929672,42.1533508301],"type":"Point"}
}