{
  "type": "Feature",
  "properties": {
    "addr:full":"Ctra Eraul, 1 Abarzuza Navarra 31178",
    "addr:housenumber":"1",
    "addr:postcode":"31178",
    "addr:street":"Ctra Eraul",
    "iso:country":"ES",
    "sg:address":"Ctra Eraul, 1",
    "sg:city":"Abarzuza",
    "sg:orig_category":"Cr\u00cda De Animales",
    "sg:phone":"+34 948 52 00 07",
    "sg:postcode":"31178",
    "sg:province":"Navarra",
    "wof:name":"Fernandez Perez Bego\u00f1a Y Sainz Munarriz Javier Cb",
    "wof:placetype":"venue"
},
  "geometry": {"coordinates":[-2.0202140808,42.727684021],"type":"Point"}
}