{
  "type": "Feature",
  "properties": {
    "addr:full":"Rua Pai Crespo, 20 Redondela Pontevedra 36800",
    "addr:housenumber":"20",
    "addr:postcode":"36800",
    "addr:street":"Rua Pai Crespo",
    "iso:country":"ES",
    "sg:address":"Rua Pai Crespo, 20",
    "sg:city":"Redondela",
    "sg:orig_category":"Art\u00cdculos De Decoraci\u00d3n",
    "sg:phone":"+34 986 40 23 63",
    "sg:postcode":"36800",
    "sg:province":"Pontevedra",
    "wof:name":"Garcia Alvarez Maria Pilar",
    "wof:placetype":"venue"
},
  "geometry": {"coordinates":[-8.6092348099,42.2810783386],"type":"Point"}
}