{
  "type": "Feature",
  "properties": {
    "addr:full":"Carrer de Major, 54 Castellbisbal Barcelona 08755",
    "addr:housenumber":"54",
    "addr:postcode":"08755",
    "addr:street":"Carrer De Major",
    "iso:country":"ES",
    "sg:address":"Carrer de Major, 54",
    "sg:city":"Castellbisbal",
    "sg:orig_category":"Carnicer\u00cdas, Carnicer\u00cdas",
    "sg:phone":"+34 937 72 00 56",
    "sg:postcode":"08755",
    "sg:province":"Barcelona",
    "wof:name":"Rovira Salvador Joan",
    "wof:placetype":"venue"
},
  "geometry": {"coordinates":[1.980036974,41.4767227173],"type":"Point"}
}