{
  "type": "Feature",
  "properties": {
    "iso:country":"ES",
    "sg:address":"Carr Sant Antoni, 38",
    "sg:city":"Lleida",
    "sg:orig_category":"Restaurantes: Restauraci\u00d3n R\u00c1pida Y Autoservicio",
    "sg:phone":"+34 973 28 01 74",
    "sg:postcode":"25002",
    "sg:province":"Lleida",
    "wof:name":"P.i Co.lleida S.l.",
    "wof:placetype":"venue"
},
  "geometry": {"coordinates":[0.6217600107,41.6121177673],"type":"Point"}
}