{
  "type": "Feature",
  "properties": {
    "iso:country":"ES",
    "sg:address":"Cust Del Hospital, 1",
    "sg:city":"Benavente",
    "sg:orig_category":"Abogados",
    "sg:phone":"+34 980 63 01 87",
    "sg:postcode":"49600",
    "sg:province":"Zamora",
    "wof:name":"Casado Sardino Marta",
    "wof:placetype":"venue"
},
  "geometry": {"coordinates":[-5.6764287949,42.0042800903],"type":"Point"}
}