{
  "type": "Feature",
  "properties": {
    "iso:country":"ES",
    "sg:address":"Barr San Esteban, 6",
    "sg:city":"San Esteban",
    "sg:orig_category":"Agentes, Concesionarios Y Sucursales De Veh\u00cdculos",
    "sg:phone":"+34 943 65 48 75",
    "sg:postcode":"20400",
    "sg:province":"Guip\u00f9zcoa",
    "wof:name":"Kaixo Motor S.l.",
    "wof:placetype":"venue"
},
  "geometry": {"coordinates":[-2.0820989609,43.1345481873],"type":"Point"}
}