{
  "type": "Feature",
  "properties": {
    "iso:country":"ES",
    "sg:address":"Calle de Mayor Principal, 140",
    "sg:city":"Palencia",
    "sg:orig_category":"Ropa Para Ni\u00d1os (al Por Menor)",
    "sg:phone":"+34 979 74 07 57",
    "sg:postcode":"34001",
    "sg:province":"Palencia",
    "wof:name":"Maria Del Mar Gutierrez Hernando Y Elsa Raquel Gutierrez Hernando Cb",
    "wof:placetype":"venue"
},
  "geometry": {"coordinates":[-4.5327916145,42.0124015808],"type":"Point"}
}