{
  "type": "Feature",
  "properties": {
    "addr:full":"Carr Valls D'andorra, 36 Lleida Lleida 25005",
    "addr:housenumber":"36",
    "addr:postcode":"25005",
    "addr:street":"Carr Valls D'Andorra",
    "iso:country":"ES",
    "sg:address":"Carr Valls D'andorra, 36",
    "sg:city":"Lleida",
    "sg:orig_category":"Agencias Y Agentes Comerciales, Representantes",
    "sg:phone":"+34 973 72 53 01",
    "sg:postcode":"25005",
    "sg:province":"Lleida",
    "wof:name":"Sky Walker S.l.",
    "wof:placetype":"venue"
},
  "geometry": {"coordinates":[0.6210510135,41.6300125122],"type":"Point"}
}