{
  "type": "Feature",
  "properties": {
    "iso:country":"ES",
    "sg:address":"Praj Barranco Molax, S/n",
    "sg:city":"Barranco Molax",
    "sg:orig_category":"Frutas Y Legumbres Secas (al Por Mayor)",
    "sg:phone":"+34 968 77 08 86",
    "sg:postcode":"30550",
    "sg:province":"Murcia",
    "wof:name":"Sociedad Cooperativa Agricola Del Surest",
    "wof:placetype":"venue"
},
  "geometry": {"coordinates":[-1.3944859505,38.2074737549],"type":"Point"}
}