{
  "type": "Feature",
  "properties": {
    "iso:country":"ES",
    "sg:address":"Calle de Bustamante, 21",
    "sg:city":"Madrid",
    "sg:orig_category":"Agencias Y Agentes Comerciales, Representantes",
    "sg:phone":"+34 915 39 48 83",
    "sg:postcode":"28045",
    "sg:province":"Madrid",
    "wof:name":"Lopez De Andujar Navarro Luis Isidoro",
    "wof:placetype":"venue"
},
  "geometry": {"coordinates":[-3.6904273033,40.4006843567],"type":"Point"}
}