{
  "type": "Feature",
  "properties": {
    "addr:full":"Calle de Carteros, 16 Valencia Valencia 46017",
    "addr:housenumber":"16",
    "addr:postcode":"46017",
    "addr:street":"Calle De Carteros",
    "iso:country":"ES",
    "sg:address":"Calle de Carteros, 16",
    "sg:city":"Valencia",
    "sg:orig_category":"M\u00c9dicos: An\u00c1lisis Cl\u00cdnicos",
    "sg:phone":"+34 963 57 03 13",
    "sg:postcode":"46017",
    "sg:province":"Valencia",
    "wof:name":"Laboratorios Martinez Reig S.l.",
    "wof:placetype":"venue"
},
  "geometry": {"coordinates":[-0.3888998926,39.4514389038],"type":"Point"}
}