{
  "type": "Feature",
  "properties": {
    "addr:full":"Calle de Mauricio Legendre, 36 Madrid Madrid 28046",
    "addr:housenumber":"36",
    "addr:postcode":"madrid;28046",
    "addr:street":"Calle De Mauricio Legendre",
    "iso:country":"ES",
    "sg:address":"Calle de Mauricio Legendre, 36",
    "sg:city":"Madrid",
    "sg:orig_category":"Urbanistas",
    "sg:phone":"+34 913 14 97 28",
    "sg:postcode":"28046",
    "sg:province":"Madrid",
    "wof:name":"Inmuebles Y Proyectos S.a.",
    "wof:placetype":"venue"
},
  "geometry": {"coordinates":[-3.6850299835,40.4742431641],"type":"Point"}
}