{
  "type": "Feature",
  "properties": {
    "iso:country":"ES",
    "sg:address":"Cno. Gerardo, 8",
    "sg:city":"Ca\u00f1ada San Urbano",
    "sg:orig_category":"Gr\u00daas, Montacargas Y Elevadores Para Astilleros",
    "sg:phone":"+34 950 29 19 22",
    "sg:postcode":"04120",
    "sg:province":"Almer\u00eda",
    "wof:name":"Gruas Y Desguaces Fuentes S.l.",
    "wof:placetype":"venue"
},
  "geometry": {"coordinates":[-2.4679217339,36.8401641846],"type":"Point"}
}