{
  "type": "Feature",
  "properties": {
    "iso:country":"ES",
    "sg:address":"Calle de Navegantes, 10",
    "sg:city":"Irun",
    "sg:classifiers":[
        {
            "category":"Tea Room",
            "subcategory":"None",
            "type":"Food & Drink"
        }
    ],
    "sg:phone":"+34 943 62 82 59",
    "sg:postcode":"20303",
    "sg:province":"Guip\u00f9zcoa",
    "sg:tags":[
        "snack"
    ],
    "wof:name":"Gonzalez Vigil Maria Paz",
    "wof:placetype":"venue"
},
  "geometry": {"coordinates":[-1.7902339697,43.3395233154],"type":"Point"}
}