{
  "type": "Feature",
  "properties": {
    "addr:full":"Carrer de Escultor Juli Antoni, 6 Reus Tarragona 43205",
    "addr:housenumber":"6",
    "addr:postcode":"43205",
    "addr:street":"Carrer De Escultor Juli Antoni",
    "iso:country":"ES",
    "sg:address":"Carrer de Escultor Juli Antoni, 6",
    "sg:city":"Reus",
    "sg:orig_category":"Empresas De Carpinter\u00cda De Madera",
    "sg:phone":"+34 977 75 44 97",
    "sg:postcode":"43205",
    "sg:province":"Tarragona",
    "wof:name":"Vernet Cendros Emilio",
    "wof:placetype":"venue"
},
  "geometry": {"coordinates":[1.117612958,41.1424827576],"type":"Point"}
}