{
  "type": "Feature",
  "properties": {
    "iso:country":"ES",
    "sg:address":"Carrer de Andalusia, 11",
    "sg:city":"Cambrils",
    "sg:orig_category":"Molduras, Junquillos, Listones Y Molduras Perforadas",
    "sg:phone":"+34 977 79 53 70",
    "sg:postcode":"43850",
    "sg:province":"Tarragona",
    "wof:name":"Maldonado Casta\u00f1o Rafaela",
    "wof:placetype":"venue"
},
  "geometry": {"coordinates":[1.057090044,41.0693092346],"type":"Point"}
}