{
  "type": "Feature",
  "properties": {
    "iso:country":"ES",
    "sg:address":"Avda Ca\u00d1a (la), 20",
    "sg:city":"Algeciras",
    "sg:orig_category":"Farmacias",
    "sg:phone":"+34 956 65 62 14",
    "sg:postcode":"11203",
    "sg:province":"C\u00e1diz",
    "wof:name":"Farmacia Pine Y Vazquez S.c.",
    "wof:placetype":"venue"
},
  "geometry": {"coordinates":[-5.4555268288,36.1337013245],"type":"Point"}
}