{
  "type": "Feature",
  "properties": {
    "iso:country":"ES",
    "sg:address":"Calle de Ciudad De Martos, 6",
    "sg:city":"Mora",
    "sg:orig_category":"Sociedades, Compa\u00d1\u00cdas Aseguradoras",
    "sg:phone":"+34 925 30 04 23",
    "sg:postcode":"45400",
    "sg:province":"Toledo",
    "wof:name":"Soliss Agencia De Seguros S.l.",
    "wof:placetype":"venue"
},
  "geometry": {"coordinates":[-3.7727198601,39.6853065491],"type":"Point"}
}