{
  "type": "Feature",
  "properties": {
    "iso:country":"ES",
    "sg:address":"Calle de Roger De Flor, 23",
    "sg:city":"Zaragoza",
    "sg:orig_category":"Masajistas Kinesiterapeutas",
    "sg:phone":"+34 976 32 78 65",
    "sg:postcode":"50017",
    "sg:province":"Zaragoza",
    "wof:name":"Binaburo Utrillas Francisco",
    "wof:placetype":"venue"
},
  "geometry": {"coordinates":[-0.9161159992,41.6476364136],"type":"Point"}
}