{
  "type": "Feature",
  "properties": {
    "addr:full":"Carrer de Montflorit, 143 Gava Barcelona 08850",
    "addr:housenumber":"143",
    "addr:postcode":"08850",
    "addr:street":"Carrer De Montflorit",
    "iso:country":"ES",
    "sg:address":"Carrer de Montflorit, 143",
    "sg:city":"Gava",
    "sg:orig_category":"Alquiler De V\u00cddeo",
    "sg:phone":"+34 936 62 91 18",
    "sg:postcode":"08850",
    "sg:province":"Barcelona",
    "sg:website":"www.reddragongava.com",
    "wof:name":"Rosal Sanchez Ana",
    "wof:placetype":"venue"
},
  "geometry": {"coordinates":[1.9983049631,41.30701828],"type":"Point"}
}