{
  "type": "Feature",
  "properties": {
    "addr:full":"Bruselas(p I Mas De Tous), 15 Pobla Vallbona Valencia 46185",
    "addr:housenumber":"15",
    "addr:postcode":"46185",
    "addr:street":"Bruselas",
    "iso:country":"ES",
    "sg:address":"Bruselas(p I Mas De Tous), 15",
    "sg:city":"Pobla Vallbona",
    "sg:orig_category":"Folclore",
    "sg:phone":"+34 962 76 32 01",
    "sg:postcode":"46185",
    "sg:province":"Valencia",
    "wof:name":"Desarrollo De Elementos Constructivos",
    "wof:placetype":"venue"
},
  "geometry": {"coordinates":[-0.5389279723,39.5920372009],"type":"Point"}
}