{
  "type": "Feature",
  "properties": {
    "addr:full":"Calle de Barreras (las), 12 Villaverde Abadia Le\u00f3n 24390",
    "addr:housenumber":"12",
    "addr:postcode":"24390",
    "addr:street":"Calle De;Las",
    "iso:country":"ES",
    "sg:address":"Calle de Barreras (las), 12",
    "sg:city":"Villaverde Abadia",
    "sg:orig_category":"Escayola Y Productos De Escayola (fabricaci\u00d3n, Al Por Mayor)",
    "sg:phone":"+34 987 54 44 55",
    "sg:postcode":"24390",
    "sg:province":"Le\u00f3n",
    "wof:name":"Pacios Vidal Luis",
    "wof:placetype":"venue"
},
  "geometry": {"coordinates":[-6.7091612816,42.5240592957],"type":"Point"}
}