{
  "type": "Feature",
  "properties": {
    "addr:full":"Calle de Urbano Gonzalez Serrano, 16 Navalmoral Mata C\u00e1ceres 10300",
    "addr:housenumber":"16",
    "addr:postcode":"10300",
    "addr:street":"Calle De Urbano Gonzalez Serrano;Ca\u0301Ceres",
    "iso:country":"ES",
    "sg:address":"Calle de Urbano Gonzalez Serrano, 16",
    "sg:city":"Navalmoral Mata",
    "sg:orig_category":"Asesor\u00cda Fiscal Y Jur\u00cddica",
    "sg:phone":"+34 927 53 15 16",
    "sg:postcode":"10300",
    "sg:province":"C\u00e1ceres",
    "wof:name":"Yuste Garcia Maria Dolores",
    "wof:placetype":"venue"
},
  "geometry": {"coordinates":[-5.5415773392,39.8912315369],"type":"Point"}
}