{
  "type": "Feature",
  "properties": {
    "addr:full":"Calle de Montesinos, 16 Alcazar S. Juan Ciudad Real 13600",
    "addr:housenumber":"16",
    "addr:postcode":"13600",
    "addr:street":"Calle De Montesinos;Alcazar S. Juan Ciudad Real",
    "iso:country":"ES",
    "sg:address":"Calle de Montesinos, 16",
    "sg:city":"Alcazar S. Juan",
    "sg:orig_category":"Ingeniero",
    "sg:phone":"+34 926 54 58 32",
    "sg:postcode":"13600",
    "sg:province":"Ciudad Real",
    "wof:name":"Carrero Logro\u00f1o Jaime",
    "wof:placetype":"venue"
},
  "geometry": {"coordinates":[-3.2016789913,39.3932762146],"type":"Point"}
}