{
  "type": "Feature",
  "properties": {
    "iso:country":"ES",
    "sg:address":"Urtaki, 40",
    "sg:city":"Aduna",
    "sg:orig_category":"Delegados, Agentes De Tr\u00c1nsito, Auxiliares De Transporte Internacional",
    "sg:phone":"+34 943 69 60 61",
    "sg:postcode":"20150",
    "sg:province":"Guip\u00f9zcoa",
    "wof:name":"Trans-ernio Gipuzkoa S.coop.ltda.",
    "wof:placetype":"venue"
},
  "geometry": {"coordinates":[-2.0411190987,43.2013473511],"type":"Point"}
}