{
  "type": "Feature",
  "properties": {
    "addr:full":"Carrer de Paris, 187 Barcelona Barcelona 08036",
    "addr:housenumber":"187",
    "addr:postcode":"08036",
    "addr:street":"Carrer De Paris",
    "iso:country":"ES",
    "sg:address":"Carrer de Paris, 187",
    "sg:city":"Barcelona",
    "sg:orig_category":"Molduras, Junquillos, Listones Y Molduras Perforadas",
    "sg:phone":"+34 932 09 85 30",
    "sg:postcode":"08036",
    "sg:province":"Barcelona",
    "wof:name":"Hugas Casals Montserrat",
    "wof:placetype":"venue"
},
  "geometry": {"coordinates":[2.1528520584,41.393535614],"type":"Point"}
}