{
  "type": "Feature",
  "properties": {
    "addr:full":"Avda Valdes, 27 Ponferrada Le\u00f3n 24400",
    "addr:housenumber":"27",
    "addr:postcode":"24400",
    "addr:street":"Avda Valdes",
    "iso:country":"ES",
    "sg:address":"Avda Valdes, 27",
    "sg:city":"Ponferrada",
    "sg:orig_category":"Cr\u00cda De Animales",
    "sg:phone":"+34 987 41 07 95",
    "sg:postcode":"24400",
    "sg:province":"Le\u00f3n",
    "wof:name":"Marques Marques Daniel",
    "wof:placetype":"venue"
},
  "geometry": {"coordinates":[-6.6002960205,42.5499153137],"type":"Point"}
}