{
  "type": "Feature",
  "properties": {
    "iso:country":"ES",
    "sg:address":"Calle de Orense, 8",
    "sg:city":"Madrid",
    "sg:orig_category":"Alimentaci\u00d3n General (al Por Menor)",
    "sg:phone":"+34 915 97 28 30",
    "sg:postcode":"28020",
    "sg:province":"Madrid",
    "wof:name":"Aguila-gutierrez Aguirre Alicia",
    "wof:placetype":"venue"
},
  "geometry": {"coordinates":[-3.6953771114,40.4484138489],"type":"Point"}
}