{
  "type": "Feature",
  "properties": {
    "iso:country":"ES",
    "sg:address":"Zalatambor, 12",
    "sg:city":"Estella",
    "sg:orig_category":"Material Y Suministros Para Perforaciones, Sondeos",
    "sg:phone":"+34 948 54 64 11",
    "sg:postcode":"31200",
    "sg:province":"Navarra",
    "wof:name":"Obras Y Servicios Tex S.l.",
    "wof:placetype":"venue"
},
  "geometry": {"coordinates":[-2.0309491158,42.6669998169],"type":"Point"}
}