{
  "type": "Feature",
  "properties": {
    "iso:country":"ES",
    "sg:address":"Ctra Castellnovo, S/n",
    "sg:city":"Segorbe",
    "sg:orig_category":"Puertas Y Portales",
    "sg:phone":"+34 964 71 10 67",
    "sg:postcode":"12400",
    "sg:province":"Castell\u00f3n",
    "sg:website":"www.puertas-piquer.com",
    "wof:name":"Puertas Metalicas Piquer S.l.",
    "wof:placetype":"venue"
},
  "geometry": {"coordinates":[-0.4852710068,39.8516426086],"type":"Point"}
}