{
  "type": "Feature",
  "properties": {
    "addr:full":"Calle de Enrique Fuentes, 18 Madrid Madrid 28026",
    "addr:housenumber":"18",
    "addr:postcode":"madrid;28026",
    "addr:street":"Calle De Enrique Fuentes",
    "iso:country":"ES",
    "sg:address":"Calle de Enrique Fuentes, 18",
    "sg:city":"Madrid",
    "sg:orig_category":"Librer\u00cdas",
    "sg:phone":"+34 915 69 03 06",
    "sg:postcode":"28026",
    "sg:province":"Madrid",
    "sg:website":"www.mtgmetropolis.com",
    "wof:name":"Metropolis Usera S.l.",
    "wof:placetype":"venue"
},
  "geometry": {"coordinates":[-3.7119340897,40.3863067627],"type":"Point"}
}