{
  "type": "Feature",
  "properties": {
    "addr:full":"Rond Mates, 30 Olot Girona 17800",
    "addr:housenumber":"30",
    "addr:postcode":"17800",
    "addr:street":"Mates",
    "iso:country":"ES",
    "sg:address":"Rond Mates, 30",
    "sg:city":"Olot",
    "sg:orig_category":"Empresas De Carpinter\u00cda Met\u00c1lica",
    "sg:phone":"+34 972 27 03 17",
    "sg:postcode":"17800",
    "sg:province":"Girona",
    "wof:name":"Serralleria Andreu S.l.",
    "wof:placetype":"venue"
},
  "geometry": {"coordinates":[2.5084340572,42.1933631897],"type":"Point"}
}