{
  "type": "Feature",
  "properties": {
    "iso:country":"ES",
    "sg:address":"Carrer de Rosa Marine, 40",
    "sg:city":"Floresta",
    "sg:orig_category":"Plumas Y Pelusas (al Por Mayor)",
    "sg:phone":"+34 936 74 32 66",
    "sg:postcode":"08198",
    "sg:province":"Barcelona",
    "wof:name":"Boix Benedi Nuria",
    "wof:placetype":"venue"
},
  "geometry": {"coordinates":[2.0732800961,41.4501914978],"type":"Point"}
}