{
  "type": "Feature",
  "properties": {
    "iso:country":"ES",
    "sg:address":"Poligono Industrial, S/n",
    "sg:city":"Azagra",
    "sg:orig_category":"Sales (al Por Mayor)",
    "sg:phone":"+34 948 69 27 28",
    "sg:postcode":"31560",
    "sg:province":"Navarra",
    "sg:website":"www.fiab.es-virto",
    "wof:name":"Ultracongelados Virto S.a.",
    "wof:placetype":"venue"
},
  "geometry": {"coordinates":[-1.902402997,42.3164176941],"type":"Point"}
}