{
  "type": "Feature",
  "properties": {
    "iso:country":"ES",
    "sg:address":"Av Estadi, 21",
    "sg:city":"Vic",
    "sg:orig_category":"Panader\u00cdas, Panader\u00cdas",
    "sg:phone":"+34 938 85 01 82",
    "sg:postcode":"08500",
    "sg:province":"Barcelona",
    "wof:name":"Pastisseria Llado S.l.",
    "wof:placetype":"venue"
},
  "geometry": {"coordinates":[2.2544240952,41.9217185974],"type":"Point"}
}