{
  "type": "Feature",
  "properties": {
    "addr:full":"Av Mare De Deu De Montserrat, 35 S. Joan Despi Barcelona 08970",
    "addr:housenumber":"35",
    "addr:postcode":"08970",
    "addr:street":"Av Mare De Deu De Montserrat;S. Joan Despi",
    "iso:country":"ES",
    "sg:address":"Av Mare De Deu De Montserrat, 35",
    "sg:city":"S. Joan Despi",
    "sg:orig_category":"Materiales De Aislamiento T\u00c9rmico Y Ac\u00dastico",
    "sg:phone":"+34 934 77 64 20",
    "sg:postcode":"08970",
    "sg:province":"Barcelona",
    "wof:name":"Ingapa S.l.",
    "wof:placetype":"venue"
},
  "geometry": {"coordinates":[2.0652320385,41.369846344],"type":"Point"}
}