{
  "type": "Feature",
  "properties": {
    "addr:full":"Calle de Pizarro, 10 Poligono Industrial Los Villares Salamanca 37184",
    "addr:housenumber":"10",
    "addr:postcode":"37184",
    "addr:street":"Calle De Pizarro;Poligono Industrial",
    "iso:country":"ES",
    "sg:address":"Calle de Pizarro, 10",
    "sg:city":"Poligono Industrial Los Villares",
    "sg:orig_category":"Transportes Por Carretera: Lotes Completos, Mercanc\u00cdas Diversas",
    "sg:phone":"+34 923 24 98 34",
    "sg:postcode":"37184",
    "sg:province":"Salamanca",
    "wof:name":"Mendez Garcia Jose Antonio",
    "wof:placetype":"venue"
},
  "geometry": {"coordinates":[-5.6476120949,41.0065116882],"type":"Point"}
}