{
  "type": "Feature",
  "properties": {
    "addr:full":"Avgd Valencia, 12 Massamagrell Valencia 46130",
    "addr:housenumber":"12",
    "addr:postcode":"46130",
    "addr:street":"Valencia",
    "iso:country":"ES",
    "sg:address":"Avgd Valencia, 12",
    "sg:city":"Massamagrell",
    "sg:orig_category":"Ropa Para Ni\u00d1os (al Por Menor)",
    "sg:phone":"+34 961 44 07 13",
    "sg:postcode":"46130",
    "sg:province":"Valencia",
    "wof:name":"Verdu Nu\u00f1ez Juana Maria",
    "wof:placetype":"venue"
},
  "geometry": {"coordinates":[-0.3348749876,39.5718269348],"type":"Point"}
}