{
  "type": "Feature",
  "properties": {
    "addr:full":"Calle de Vereda De Los Barros, 9 Ventorro Del Cano Madrid 28925",
    "addr:housenumber":"9",
    "addr:postcode":"28925",
    "addr:street":"Calle De Vereda De Los Barros",
    "iso:country":"ES",
    "sg:address":"Calle de Vereda De Los Barros, 9",
    "sg:city":"Ventorro Del Cano",
    "sg:orig_category":"Transportes Por Carretera: Lotes Completos, Mercanc\u00cdas Diversas",
    "sg:phone":"+34 916 32 22 70",
    "sg:postcode":"28925",
    "sg:province":"Madrid",
    "wof:name":"Santos Y Gesteira S.l.",
    "wof:placetype":"venue"
},
  "geometry": {"coordinates":[-3.8307540417,40.390789032],"type":"Point"}
}