{
  "type": "Feature",
  "properties": {
    "iso:country":"ES",
    "sg:address":"Calle de Capitan Aranda Alta, 24",
    "sg:city":"Jaen",
    "sg:orig_category":"Alimentaci\u00d3n General (al Por Menor)",
    "sg:phone":"+34 953 24 16 22",
    "sg:postcode":"23002",
    "sg:province":"Ja\u00e9n",
    "wof:name":"Ordo\u00f1ez Gamez Gregorio",
    "wof:placetype":"venue"
},
  "geometry": {"coordinates":[-3.793694973,37.7663421631],"type":"Point"}
}