{
  "type": "Feature",
  "properties": {
    "addr:full":"Carr Bajoli, 19 Poima Islas Baleares 07714",
    "addr:housenumber":"19",
    "addr:postcode":"07714",
    "addr:street":"Carr Bajoli;Islas",
    "iso:country":"ES",
    "sg:address":"Carr Bajoli, 19",
    "sg:city":"Poima",
    "sg:orig_category":"Mec\u00c1nico Del Autom\u00d3vil",
    "sg:phone":"+34 971 35 38 96",
    "sg:postcode":"07714",
    "sg:province":"Islas Baleares",
    "wof:name":"Autoreparaciones Bajoli S.l.",
    "wof:placetype":"venue"
},
  "geometry": {"coordinates":[4.2455391884,39.8860473633],"type":"Point"}
}