{
  "type": "Feature",
  "properties": {
    "addr:full":"Avda Camilo Jose Cela, S/n Ciudad Real Ciudad Real 13005",
    "addr:housenumber":"s / n",
    "addr:postcode":"13005",
    "addr:street":"Avda Camilo Jose Cela",
    "iso:country":"ES",
    "sg:address":"Avda Camilo Jose Cela, S/n",
    "sg:city":"Ciudad Real",
    "sg:orig_category":"Ense\u00d1anza, Formaci\u00d3n Profesional: Aprendizaje",
    "sg:phone":"+34 926 25 05 59",
    "sg:postcode":"13005",
    "sg:province":"Ciudad Real",
    "wof:name":"Junta De Comunidades Castilla-la Mancha",
    "wof:placetype":"venue"
},
  "geometry": {"coordinates":[-3.9219288826,38.9965057373],"type":"Point"}
}