{
  "type": "Feature",
  "properties": {
    "iso:country":"ES",
    "sg:address":"Cirro, S/n",
    "sg:city":"Cirro",
    "sg:orig_category":"Flores Y Plantas Naturales (al Por Mayor)",
    "sg:phone":"+34 981 88 87 06",
    "sg:postcode":"15280",
    "sg:province":"La Coru\u00f1a",
    "wof:name":"Lucio Raris Garcia Y Otro S.c.",
    "wof:placetype":"venue"
},
  "geometry": {"coordinates":[-8.6716041565,42.8535842896],"type":"Point"}
}