{
  "type": "Feature",
  "properties": {
    "addr:full":"Pase Portales Mercaderes, 8 Baeza Ja\u00e9n 23440",
    "addr:housenumber":"8",
    "addr:postcode":"23440",
    "addr:street":"Mercaderes",
    "iso:country":"ES",
    "sg:address":"Pase Portales Mercaderes, 8",
    "sg:city":"Baeza",
    "sg:orig_category":"Aparatos Digitales",
    "sg:phone":"+34 953 74 05 27",
    "sg:postcode":"23440",
    "sg:province":"Ja\u00e9n",
    "wof:name":"Quesada Sanchez Jose",
    "wof:placetype":"venue"
},
  "geometry": {"coordinates":[-3.4683389664,37.9931411743],"type":"Point"}
}