{
  "type": "Feature",
  "properties": {
    "iso:country":"ES",
    "sg:address":"Avda Paz (de La) (completa), 8",
    "sg:city":"Moraira",
    "sg:orig_category":"Pr\u00c1ctica De Vela, Navegaci\u00d3n Y Deportes N\u00c1uticos Y Acu\u00c1ticos",
    "sg:phone":"+34 966 49 21 21",
    "sg:postcode":"03724",
    "sg:province":"Alicante",
    "wof:name":"Segel Schule Magellan S.l.",
    "wof:placetype":"venue"
},
  "geometry": {"coordinates":[0.1319250017,38.6884841919],"type":"Point"}
}