{
  "type": "Feature",
  "properties": {
    "addr:full":"Calle de Parra (la), 4 Casetas Zaragoza 50620",
    "addr:postcode":"50620",
    "addr:street":"Calle De Parra La 4 Casetas",
    "iso:country":"ES",
    "sg:address":"Calle de Parra (la), 4",
    "sg:city":"Casetas",
    "sg:orig_category":"Alimentaci\u00d3n General (al Por Menor)",
    "sg:phone":"+34 976 77 18 88",
    "sg:postcode":"50620",
    "sg:province":"Zaragoza",
    "wof:name":"Gregorio Andres Barbara",
    "wof:placetype":"venue"
},
  "geometry": {"coordinates":[-1.0279150009,41.7192802429],"type":"Point"}
}