{
  "type": "Feature",
  "properties": {
    "iso:country":"ES",
    "sg:address":"Ctra Valencia-ademuz, Km. 0028,0",
    "sg:city":"Lliria",
    "sg:orig_category":"Materias Pl\u00c1sticas: Art\u00cdculos Para La Industria",
    "sg:phone":"+34 962 79 91 00",
    "sg:postcode":"46160",
    "sg:province":"Valencia",
    "wof:name":"Lab.radio S.a.",
    "wof:placetype":"venue"
},
  "geometry": {"coordinates":[-0.6247159839,39.6471366882],"type":"Point"}
}