{
  "type": "Feature",
  "properties": {
    "iso:country":"ES",
    "sg:address":"La Loma, 6",
    "sg:city":"Samano",
    "sg:orig_category":"Material Hidr\u00c1ulico",
    "sg:phone":"+34 942 86 90 14",
    "sg:postcode":"39709",
    "sg:province":"Cantabria",
    "wof:name":"Voss S.a.",
    "wof:placetype":"venue"
},
  "geometry": {"coordinates":[-3.231490612,43.3568458557],"type":"Point"}
}