{
  "type": "Feature",
  "properties": {
    "iso:country":"ES",
    "sg:address":"Calle de Carlos Senti, 13",
    "sg:city":"Denia",
    "sg:orig_category":"Ropa Para Se\u00d1oras (al Por Menor)",
    "sg:phone":"+34 965 78 02 57",
    "sg:postcode":"03700",
    "sg:province":"Alicante",
    "wof:name":"Peiro C.b.",
    "wof:placetype":"venue"
},
  "geometry": {"coordinates":[0.1085444987,38.8405189514],"type":"Point"}
}