{
  "type": "Feature",
  "properties": {
    "addr:full":"Avda Madrid, 200 Zaragoza Zaragoza 50017",
    "addr:housenumber":"200",
    "addr:postcode":"50017",
    "addr:street":"Avda Madrid",
    "iso:country":"ES",
    "sg:address":"Avda Madrid, 200",
    "sg:city":"Zaragoza",
    "sg:orig_category":"Alimentaci\u00d3n General (al Por Menor)",
    "sg:phone":"+34 976 33 05 11",
    "sg:postcode":"50017",
    "sg:province":"Zaragoza",
    "wof:name":"Velasco Andres Miguel Angel",
    "wof:placetype":"venue"
},
  "geometry": {"coordinates":[-0.9152600169,41.6510925293],"type":"Point"}
}