{
  "type": "Feature",
  "properties": {
    "addr:full":"Calle de Alamos (de Los), 4 Arevalo \u00c1vila 05200",
    "addr:housenumber":"4",
    "addr:postcode":"05200",
    "addr:street":"Calle De Alamos De Los",
    "iso:country":"ES",
    "sg:address":"Calle de Alamos (de Los), 4",
    "sg:city":"Arevalo",
    "sg:orig_category":"Organizaciones Internacionales",
    "sg:phone":"+34 920 30 33 44",
    "sg:postcode":"05200",
    "sg:province":"\u00c1vila",
    "wof:name":"Asociacion Escuelas Campesinas De Avila",
    "wof:placetype":"venue"
},
  "geometry": {"coordinates":[-4.7215127945,41.0566482544],"type":"Point"}
}