{
  "type": "Feature",
  "properties": {
    "iso:country":"ES",
    "sg:address":"Av Onze De Setembre, 63",
    "sg:city":"Llagosta",
    "sg:orig_category":"Animales (al Por Menor)",
    "sg:phone":"+34 935 74 20 84",
    "sg:postcode":"08120",
    "sg:province":"Barcelona",
    "wof:name":"Requena Miro Ramon",
    "wof:placetype":"venue"
},
  "geometry": {"coordinates":[2.1922769547,41.5127296448],"type":"Point"}
}