{
  "type": "Feature",
  "properties": {
    "iso:country":"ES",
    "sg:address":"Calle de Rico, 33",
    "sg:city":"Huelva",
    "sg:orig_category":"Pr\u00c1ctica De Vela, Navegaci\u00d3n Y Deportes N\u00c1uticos Y Acu\u00c1ticos",
    "sg:phone":"+34 959 25 13 15",
    "sg:postcode":"21001",
    "sg:province":"Huelva",
    "sg:website":"www.sudoeste.info",
    "wof:name":"Gestion Maritima Suroeste S.l.",
    "wof:placetype":"venue"
},
  "geometry": {"coordinates":[-6.9525232315,37.2552566528],"type":"Point"}
}