{
  "type": "Feature",
  "properties": {
    "iso:country":"ES",
    "sg:address":"Calle de Ramiro El Monje (san Lorenzo), 4",
    "sg:city":"San Lorenzo Del Flumen",
    "sg:orig_category":"M\u00c9dicos: Foniatr\u00cda Y Logopedia",
    "sg:phone":"+34 974 39 53 93",
    "sg:postcode":"22212",
    "sg:province":"Huesca",
    "wof:name":"Latre Puyuelo Vicente",
    "wof:placetype":"venue"
},
  "geometry": {"coordinates":[-0.2135930061,41.9075622559],"type":"Point"}
}