{
  "type": "Feature",
  "properties": {
    "addr:full":"Calle de Pedro Caravaca, 1 Sevilla Sevilla 41004",
    "addr:housenumber":"1",
    "addr:postcode":"41004",
    "addr:street":"Calle De Pedro Caravaca",
    "iso:country":"ES",
    "sg:address":"Calle de Pedro Caravaca, 1",
    "sg:city":"Sevilla",
    "sg:orig_category":"Asociaciones, Organismos Culturales Y Socioeducativos",
    "sg:phone":"+34 954 22 66 25",
    "sg:postcode":"41004",
    "sg:province":"Sevilla",
    "wof:name":"Real Circulo De Labradores Y Propietarios De Sevilla",
    "wof:placetype":"venue"
},
  "geometry": {"coordinates":[-5.9950151443,37.3917503357],"type":"Point"}
}