{
  "type": "Feature",
  "properties": {
    "addr:full":"Pase Olivos, 24 Madrid Madrid 28011",
    "addr:housenumber":"24",
    "addr:postcode":"madrid;28011",
    "addr:street":"Olivos",
    "iso:country":"ES",
    "sg:address":"Pase Olivos, 24",
    "sg:city":"Madrid",
    "sg:classifiers":[
        {
            "category":"Autos & Motor Vehicles",
            "subcategory":"Automobile Sales",
            "type":"Retail Goods"
        }
    ],
    "sg:phone":"+34 914 79 79 52",
    "sg:postcode":"28011",
    "sg:province":"Madrid",
    "wof:name":"Fernandez Riveras Jose Amaro",
    "wof:placetype":"venue"
},
  "geometry": {"coordinates":[-3.7335860729,40.4059181213],"type":"Point"}
}