{
  "type": "Feature",
  "properties": {
    "addr:full":"Calle de Fuente Nueva, S/n Pedro Bernardo \u00c1vila 05470",
    "addr:housenumber":"s / n",
    "addr:postcode":"05470",
    "addr:street":"Calle De Fuente Nueva",
    "iso:country":"ES",
    "sg:address":"Calle de Fuente Nueva, S/n",
    "sg:city":"Pedro Bernardo",
    "sg:orig_category":"Electrolisis, Depurado Del Aluminio Y De Aleaciones",
    "sg:phone":"+34 920 38 90 87",
    "sg:postcode":"05470",
    "sg:province":"\u00c1vila",
    "wof:name":"Pujales Crespo Jose Antonio",
    "wof:placetype":"venue"
},
  "geometry": {"coordinates":[-4.9137592316,40.2430648804],"type":"Point"}
}