{
  "type": "Feature",
  "properties": {
    "addr:full":"Calle de Arenal, 48 Chinchilla Monte-aragon Albacete 02520",
    "addr:housenumber":"48",
    "addr:postcode":"02520",
    "addr:street":"Calle De Arenal;Monte-Aragon",
    "iso:country":"ES",
    "sg:address":"Calle de Arenal, 48",
    "sg:city":"Chinchilla Monte-aragon",
    "sg:orig_category":"Reposter\u00cdas",
    "sg:phone":"+34 967 26 03 68",
    "sg:postcode":"02520",
    "sg:province":"Albacete",
    "wof:name":"Jimenez Gomez Mariano",
    "wof:placetype":"venue"
},
  "geometry": {"coordinates":[-1.7220554352,38.9161567688],"type":"Point"}
}