{
  "type": "Feature",
  "properties": {
    "addr:full":"Ctra. C. Pelea, Km. 0015,8 Alvarado Badajoz 06170",
    "addr:postcode":"06170",
    "addr:street":"Ctra. C. Pelea Km. 0015,8 Alvarado",
    "iso:country":"ES",
    "sg:address":"Ctra. C. Pelea, Km. 0015,8",
    "sg:city":"Alvarado",
    "sg:orig_category":"Agricultores, Agricultores",
    "sg:phone":"+34 924 14 03 52",
    "sg:postcode":"06170",
    "sg:province":"Badajoz",
    "wof:name":"Ramos Fernandez De Soria Eduardo Maria",
    "wof:placetype":"venue"
},
  "geometry": {"coordinates":[-6.825674057,38.7182540894],"type":"Point"}
}