{
  "type": "Feature",
  "properties": {
    "addr:full":"Av Universitat Autonoma, S/n Cerdanyola Valles Barcelona 08290",
    "addr:housenumber":"s / n",
    "addr:postcode":"08290",
    "addr:street":"Av Universitat Autonoma;Valles Barcelona",
    "iso:country":"ES",
    "sg:address":"Av Universitat Autonoma, S/n",
    "sg:city":"Cerdanyola Valles",
    "sg:orig_category":"Molduras, Junquillos, Listones Y Molduras Perforadas",
    "sg:phone":"+34 936 91 01 12",
    "sg:postcode":"08290",
    "sg:province":"Barcelona",
    "wof:name":"Restauracion Universitaria S.l.",
    "wof:placetype":"venue"
},
  "geometry": {"coordinates":[2.1282300949,41.4847145081],"type":"Point"}
}