{
  "type": "Feature",
  "properties": {
    "iso:country":"ES",
    "sg:address":"Calle de Donoso Cortes, 20",
    "sg:city":"Madrid",
    "sg:orig_category":"Papeler\u00cdas, Librer\u00cdas",
    "sg:phone":"+34 915 93 15 41",
    "sg:postcode":"28015",
    "sg:province":"Madrid",
    "wof:name":"Sanz Naranjo Roberto",
    "wof:placetype":"venue"
},
  "geometry": {"coordinates":[-3.7077360153,40.4362831116],"type":"Point"}
}