{
  "type": "Feature",
  "properties": {
    "addr:full":"Calle de Ciruelo (el), 6 Aguadulce Almer\u00eda 04720",
    "addr:housenumber":"6",
    "addr:postcode":"04720",
    "addr:street":"Calle De Ciruelo El;Almeri\u0301A",
    "iso:country":"ES",
    "sg:address":"Calle de Ciruelo (el), 6",
    "sg:city":"Aguadulce",
    "sg:orig_category":"Inmobiliaria (agencias)",
    "sg:phone":"+34 950 55 07 09",
    "sg:postcode":"04720",
    "sg:province":"Almer\u00eda",
    "wof:name":"Moreno Carretero Alfredo Eugenio",
    "wof:placetype":"venue"
},
  "geometry": {"coordinates":[-2.5777614117,36.808139801],"type":"Point"}
}