{
  "type": "Feature",
  "properties": {
    "addr:full":"Calle de Zubileta, 8 Barakaldo Vizcaya 48903",
    "addr:housenumber":"8",
    "addr:postcode":"48903",
    "addr:street":"Calle De Zubileta",
    "iso:country":"ES",
    "sg:address":"Calle de Zubileta, 8",
    "sg:city":"Barakaldo",
    "sg:orig_category":"Molduras, Junquillos, Listones Y Molduras Perforadas",
    "sg:phone":"+34 944 82 10 67",
    "sg:postcode":"48903",
    "sg:province":"Vizcaya",
    "wof:name":"Antonio San Roman Lavin",
    "wof:placetype":"venue"
},
  "geometry": {"coordinates":[-2.9789745808,43.2786369324],"type":"Point"}
}