{
  "type": "Feature",
  "properties": {
    "addr:full":"Calle de Doctor Lozano, 17 Madrid Madrid 28038",
    "addr:housenumber":"17",
    "addr:postcode":"madrid;28038",
    "addr:street":"Calle De Doctor Lozano",
    "iso:country":"ES",
    "sg:address":"Calle de Doctor Lozano, 17",
    "sg:city":"Madrid",
    "sg:orig_category":"Inmobiliaria (agencias)",
    "sg:phone":"+34 914 33 82 77",
    "sg:postcode":"28038",
    "sg:province":"Madrid",
    "wof:name":"Torrecentre S.l.",
    "wof:placetype":"venue"
},
  "geometry": {"coordinates":[-3.6615123749,40.4033508301],"type":"Point"}
}