{
  "type": "Feature",
  "properties": {
    "iso:country":"ES",
    "sg:address":"Roxos, 171",
    "sg:city":"Roxos",
    "sg:orig_category":"Hoteles",
    "sg:phone":"+34 981 53 71 00",
    "sg:postcode":"15896",
    "sg:province":"La Coru\u00f1a",
    "wof:name":"Esparis Sampedro Manuel",
    "wof:placetype":"venue"
},
  "geometry": {"coordinates":[-8.6018266678,42.8758583069],"type":"Point"}
}