{
  "type": "Feature",
  "properties": {
    "iso:country":"ES",
    "sg:address":"Carrer de Migdia, 8",
    "sg:city":"Vilafranca Penedes",
    "sg:orig_category":"Agencias Y Agentes Comerciales, Representantes",
    "sg:phone":"+34 938 17 51 95",
    "sg:postcode":"08720",
    "sg:province":"Barcelona",
    "wof:name":"Castells Marti Maria Antonia",
    "wof:placetype":"venue"
},
  "geometry": {"coordinates":[1.7012250423,41.3450660706],"type":"Point"}
}