{
  "type": "Feature",
  "properties": {
    "addr:full":"Calle de Rio Segura, S/n Beniel Murcia 30130",
    "addr:housenumber":"s / n",
    "addr:postcode":"30130",
    "addr:street":"Calle De Rio Segura",
    "iso:country":"ES",
    "sg:address":"Calle de Rio Segura, S/n",
    "sg:city":"Beniel",
    "sg:orig_category":"Promotores Constructores",
    "sg:phone":"+34 968 60 05 70",
    "sg:postcode":"30130",
    "sg:province":"Murcia",
    "wof:name":"Constructora Del Segura S.c.l.",
    "wof:placetype":"venue"
},
  "geometry": {"coordinates":[-1.0025089979,38.0451164246],"type":"Point"}
}