{
  "type": "Feature",
  "properties": {
    "addr:full":"Carrer de Reina Elionor, 80 Sabadell Barcelona 08205",
    "addr:housenumber":"80",
    "addr:postcode":"08205",
    "addr:street":"Carrer De Reina Elionor",
    "iso:country":"ES",
    "sg:address":"Carrer de Reina Elionor, 80",
    "sg:city":"Sabadell",
    "sg:orig_category":"Restaurantes",
    "sg:phone":"+34 937 10 00 58",
    "sg:postcode":"08205",
    "sg:province":"Barcelona",
    "wof:name":"Gonzalez Deu Monica",
    "wof:placetype":"venue"
},
  "geometry": {"coordinates":[2.103053093,41.5386390686],"type":"Point"}
}