{
  "type": "Feature",
  "properties": {
    "addr:full":"Carrer de Jacint Verdaguer, 20 Vic Barcelona 08500",
    "addr:housenumber":"20",
    "addr:postcode":"08500",
    "addr:street":"Carrer De Jacint Verdaguer",
    "iso:country":"ES",
    "sg:address":"Carrer de Jacint Verdaguer, 20",
    "sg:city":"Vic",
    "sg:orig_category":"Agencias De Viajes",
    "sg:phone":"+34 938 81 49 10",
    "sg:postcode":"08500",
    "sg:province":"Barcelona",
    "wof:name":"Itinerari 2002 S.l.",
    "wof:placetype":"venue"
},
  "geometry": {"coordinates":[2.2516160011,41.9307785034],"type":"Point"}
}