{
  "type": "Feature",
  "properties": {
    "iso:country":"ES",
    "sg:address":"Carr Creu, S/n",
    "sg:city":"Puiggros",
    "sg:orig_category":"Centros De Educaci\u00d3n Especial",
    "sg:phone":"+34 973 14 30 16",
    "sg:postcode":"25420",
    "sg:province":"Lleida",
    "wof:name":"Co%egi Public De Puiggros",
    "wof:placetype":"venue"
},
  "geometry": {"coordinates":[0.8878149986,41.5514297485],"type":"Point"}
}