{
  "type": "Feature",
  "properties": {
    "addr:full":"Calle de Morerillas (las), S/n Dos Hermanas Sevilla 41700",
    "addr:postcode":"41700",
    "addr:street":"Calle De Morerillas Las S / N Dos",
    "iso:country":"ES",
    "sg:address":"Calle de Morerillas (las), S/n",
    "sg:city":"Dos Hermanas",
    "sg:orig_category":"Peluquer\u00cdas, Peluquer\u00cda Mixta",
    "sg:phone":"+34 955 66 06 08",
    "sg:postcode":"41700",
    "sg:province":"Sevilla",
    "wof:name":"Ortega Romero Virtudes",
    "wof:placetype":"venue"
},
  "geometry": {"coordinates":[-5.9214038849,37.2839241028],"type":"Point"}
}