{
  "type": "Feature",
  "properties": {
    "iso:country":"ES",
    "sg:address":"Calle de San Marcos, 7",
    "sg:city":"Madrid",
    "sg:orig_category":"Peluquer\u00cdas, Peluquer\u00cda Mixta",
    "sg:phone":"+34 915 21 66 52",
    "sg:postcode":"28004",
    "sg:province":"Madrid",
    "wof:name":"Canorea Salazar Eugenio",
    "wof:placetype":"venue"
},
  "geometry": {"coordinates":[-3.6995959282,40.4219322205],"type":"Point"}
}