{
  "type": "Feature",
  "properties": {
    "addr:full":"Calle de Asin Palacios, 41 Cordoba C\u00f3rdoba 14011",
    "addr:housenumber":"41",
    "addr:postcode":"14011",
    "addr:street":"Calle De Asin Palacios;Co\u0301Rdoba",
    "iso:country":"ES",
    "sg:address":"Calle de Asin Palacios, 41",
    "sg:city":"Cordoba",
    "sg:orig_category":"Peluqueros: De Se\u00d1oras",
    "sg:phone":"+34 957 46 35 65",
    "sg:postcode":"14011",
    "sg:province":"C\u00f3rdoba",
    "wof:name":"Delgado Chacon Josefina",
    "wof:placetype":"venue"
},
  "geometry": {"coordinates":[-4.7940974236,37.8901786804],"type":"Point"}
}