{
  "type": "Feature",
  "properties": {
    "iso:country":"ES",
    "sg:address":"Ebre, 5",
    "sg:city":"Miami Platja",
    "sg:orig_category":"Asesor\u00cda Sobre Comunicaci\u00d3n De Empresas",
    "sg:phone":"+34 977 81 17 24",
    "sg:postcode":"43892",
    "sg:province":"Tarragona",
    "wof:name":"Lange  Kiaus",
    "wof:placetype":"venue"
},
  "geometry": {"coordinates":[0.9338750243,41.0097999573],"type":"Point"}
}