{
  "type": "Feature",
  "properties": {
    "iso:country":"ES",
    "sg:address":"Nou, 11",
    "sg:city":"Ferreries",
    "sg:orig_category":"Electricidad: Instaladores",
    "sg:phone":"+34 971 37 31 34",
    "sg:postcode":"07750",
    "sg:province":"Islas Baleares",
    "wof:name":"Capo Gual Juan",
    "wof:placetype":"venue"
},
  "geometry": {"coordinates":[4.0117897987,39.9854049683],"type":"Point"}
}