{
  "type": "Feature",
  "properties": {
    "iso:country":"ES",
    "sg:address":"Carrer de Formentera, S/n",
    "sg:city":"Barcelona",
    "sg:orig_category":"Fabricaci\u00d3n De Juguetes Autom\u00c1ticos",
    "sg:phone":"+34 933 54 59 03",
    "sg:postcode":"08016",
    "sg:province":"Barcelona",
    "wof:name":"J. J. Salas S.a.",
    "wof:placetype":"venue"
},
  "geometry": {"coordinates":[2.1847500801,41.4439735413],"type":"Point"}
}