{
  "type": "Feature",
  "properties": {
    "addr:full":"Av Llibertat, 20 Mollet Valles Barcelona 08100",
    "addr:housenumber":"20",
    "addr:postcode":"08100",
    "addr:street":"Av Llibertat",
    "iso:country":"ES",
    "sg:address":"Av Llibertat, 20",
    "sg:city":"Mollet Valles",
    "sg:orig_category":"Librer\u00cdas",
    "sg:phone":"+34 935 70 38 78",
    "sg:postcode":"08100",
    "sg:province":"Barcelona",
    "wof:name":"Pe\u00f1a Pe\u00f1a Carlos",
    "wof:placetype":"venue"
},
  "geometry": {"coordinates":[2.2117760181,41.535823822],"type":"Point"}
}