{
  "type": "Feature",
  "properties": {
    "iso:country":"ES",
    "sg:address":"Calle de Corredera, S/n",
    "sg:city":"Iruela",
    "sg:orig_category":"Aguas (distribuci\u00d3n, Servicios)",
    "sg:phone":"+34 953 72 05 94",
    "sg:postcode":"23476",
    "sg:province":"Ja\u00e9n",
    "wof:name":"Aguas Jaen S.a.",
    "wof:placetype":"venue"
},
  "geometry": {"coordinates":[-2.9940156937,37.9204788208],"type":"Point"}
}