{
  "type": "Feature",
  "properties": {
    "iso:country":"ES",
    "sg:address":"Pl Vall Del Castell, 11",
    "sg:city":"Vilafranca Penedes",
    "sg:orig_category":"Peluqueros: De Se\u00d1oras",
    "sg:phone":"+34 938 17 37 49",
    "sg:postcode":"08720",
    "sg:province":"Barcelona",
    "wof:name":"Keko 99 S.l.",
    "wof:placetype":"venue"
},
  "geometry": {"coordinates":[1.6967220306,41.3480415344],"type":"Point"}
}