{
  "type": "Feature",
  "properties": {
    "addr:full":"Avda Brasil, 4 Madrid Madrid 28020",
    "addr:housenumber":"4",
    "addr:postcode":"28020",
    "addr:street":"Avda Brasil",
    "iso:country":"ES",
    "sg:address":"Avda Brasil, 4",
    "sg:city":"Madrid",
    "sg:orig_category":"Inmobiliaria (agencias)",
    "sg:phone":"+34 915 97 10 41",
    "sg:postcode":"28020",
    "sg:province":"Madrid",
    "wof:name":"Fomento Meridional S.l.",
    "wof:placetype":"venue"
},
  "geometry": {"coordinates":[-3.6933660507,40.4537734985],"type":"Point"}
}