{
  "type": "Feature",
  "properties": {
    "addr:full":"Calle de Castilla La Vieja (de), 10 Fuenlabrada Madrid 28941",
    "addr:postcode":"28941",
    "addr:street":"Calle De Castilla La",
    "iso:country":"ES",
    "sg:address":"Calle de Castilla La Vieja (de), 10",
    "sg:city":"Fuenlabrada",
    "sg:orig_category":"Sociedades, Compa\u00d1\u00cdas Aseguradoras",
    "sg:phone":"+34 916 15 74 34",
    "sg:postcode":"28941",
    "sg:province":"Madrid",
    "wof:name":"Seguros Catalana Occidente S.a. De Seguros Y Reaseguros",
    "wof:placetype":"venue"
},
  "geometry": {"coordinates":[-3.8017129898,40.2920837402],"type":"Point"}
}