{
  "type": "Feature",
  "properties": {
    "addr:full":"Calle de Gamonal, 5 Madrid Madrid 28031",
    "addr:housenumber":"5",
    "addr:postcode":"28031",
    "addr:street":"Calle De Gamonal",
    "iso:country":"ES",
    "sg:address":"Calle de Gamonal, 5",
    "sg:city":"Madrid",
    "sg:orig_category":"Bisuter\u00cda, Joyer\u00cda, Relojer\u00cda (al Por Menor)",
    "sg:phone":"+34 913 03 57 04",
    "sg:postcode":"28031",
    "sg:province":"Madrid",
    "wof:name":"Tempus Rapid S.l.",
    "wof:placetype":"venue"
},
  "geometry": {"coordinates":[-3.6461918354,40.371711731],"type":"Point"}
}