{
  "type": "Feature",
  "properties": {
    "addr:full":"Carrer de Bruch, 15 Ametlla Mar Tarragona 43860",
    "addr:housenumber":"15",
    "addr:postcode":"43860",
    "addr:street":"Carrer De Bruch",
    "iso:country":"ES",
    "sg:address":"Carrer de Bruch, 15",
    "sg:city":"Ametlla Mar",
    "sg:orig_category":"Peluqueros: De Se\u00d1oras",
    "sg:phone":"+34 977 45 69 89",
    "sg:postcode":"43860",
    "sg:province":"Tarragona",
    "wof:name":"Ferre Nomen Josefa",
    "wof:placetype":"venue"
},
  "geometry": {"coordinates":[0.8035839796,40.8834686279],"type":"Point"}
}