{
  "type": "Feature",
  "properties": {
    "iso:country":"ES",
    "sg:address":"Carrer de Escodines, 1",
    "sg:city":"Manresa",
    "sg:orig_category":"Estancos",
    "sg:phone":"+34 938 72 29 95",
    "sg:postcode":"08241",
    "sg:province":"Barcelona",
    "wof:name":"Carrio Salabarnada Maria Carmen",
    "wof:placetype":"venue"
},
  "geometry": {"coordinates":[1.8294810057,41.7239685059],"type":"Point"}
}