{
  "type": "Feature",
  "properties": {
    "iso:country":"ES",
    "sg:address":"Avda Doctor Artero, 19",
    "sg:city":"Huesca",
    "sg:orig_category":"Promotores Constructores",
    "sg:phone":"+34 974 24 17 04",
    "sg:postcode":"22004",
    "sg:province":"Huesca",
    "wof:name":"Construcciones Rialar",
    "wof:placetype":"venue"
},
  "geometry": {"coordinates":[-0.4152109921,42.1439437866],"type":"Point"}
}