{
  "type": "Feature",
  "properties": {
    "iso:country":"ES",
    "sg:address":"C/ Tamarit, 114",
    "sg:city":"Ripollet",
    "sg:orig_category":"Paletas",
    "sg:phone":"+34 935 94 63 02",
    "sg:postcode":"08291",
    "sg:province":"Barcelona",
    "wof:name":"Recupalets De Montcada S.l.",
    "wof:placetype":"venue"
},
  "geometry": {"coordinates":[2.1665201187,41.4953613281],"type":"Point"}
}