{
  "type": "Feature",
  "properties": {
    "addr:full":"Ctra Sant Joan Despi, 86 Fatjo Barcelona 08940",
    "addr:housenumber":"86",
    "addr:postcode":"08940",
    "addr:street":"Ctra Sant Joan Despi;Barcelona",
    "iso:country":"ES",
    "sg:address":"Ctra Sant Joan Despi, 86",
    "sg:city":"Fatjo",
    "sg:orig_category":"Peluqueros: De Se\u00d1oras",
    "sg:phone":"+34 934 74 54 79",
    "sg:postcode":"08940",
    "sg:province":"Barcelona",
    "wof:name":"Fuentes Narbona Maria Dolores",
    "wof:placetype":"venue"
},
  "geometry": {"coordinates":[2.0708940029,41.3559417725],"type":"Point"}
}