{
  "type": "Feature",
  "properties": {
    "iso:country":"ES",
    "sg:address":"Veinticinco De Abril, 15",
    "sg:city":"Moncada",
    "sg:orig_category":"Tintorer\u00cdas, Limpieza En Seco",
    "sg:phone":"+34 961 30 31 05",
    "sg:postcode":"46113",
    "sg:province":"Valencia",
    "wof:name":"Martinez Villadas Julia",
    "wof:placetype":"venue"
},
  "geometry": {"coordinates":[-0.3962120116,39.5446510315],"type":"Point"}
}