{
  "type": "Feature",
  "properties": {
    "addr:full":"Calle de Morella, 1 Alcora Castell\u00f3n 12110",
    "addr:housenumber":"1",
    "addr:postcode":"12110",
    "addr:street":"Calle De Morella;Castello\u0301N",
    "iso:country":"ES",
    "sg:address":"Calle de Morella, 1",
    "sg:city":"Alcora",
    "sg:orig_category":"Empresas De Pintura Y Revestimientos",
    "sg:phone":"+34 964 36 09 80",
    "sg:postcode":"12110",
    "sg:province":"Castell\u00f3n",
    "wof:name":"Casas Poveda Juan",
    "wof:placetype":"venue"
},
  "geometry": {"coordinates":[-0.2109279931,40.0792655945],"type":"Point"}
}