{
  "type": "Feature",
  "properties": {
    "addr:full":"Calle de Calvo Sotelo, S/n Gomezserracin Segovia 40240",
    "addr:housenumber":"s / n",
    "addr:postcode":"40240",
    "addr:street":"Calle De Calvo Sotelo",
    "iso:country":"ES",
    "sg:address":"Calle de Calvo Sotelo, S/n",
    "sg:city":"Gomezserracin",
    "sg:orig_category":"Mec\u00c1nico Del Autom\u00d3vil",
    "sg:phone":"+34 921 16 82 60",
    "sg:postcode":"40240",
    "sg:province":"Segovia",
    "wof:name":"Pinilla Ruano Jose Vicente",
    "wof:placetype":"venue"
},
  "geometry": {"coordinates":[-4.3230948448,41.2881774902],"type":"Point"}
}