{
  "type": "Feature",
  "properties": {
    "addr:full":"Calle de Navero, S/n Tramacastilla Tena Huesca 22663",
    "addr:housenumber":"s",
    "addr:postcode":"22663",
    "addr:street":"Calle De Navero;/ N Tramacastilla",
    "iso:country":"ES",
    "sg:address":"Calle de Navero, S/n",
    "sg:city":"Tramacastilla Tena",
    "sg:orig_category":"Deportes Y Programas De Aventura",
    "sg:phone":"+34 974 48 76 26",
    "sg:postcode":"22663",
    "sg:province":"Huesca",
    "sg:website":"www.grogol.com",
    "wof:name":"Gorgol Guias De Monta\u00f1a S.l.",
    "wof:placetype":"venue"
},
  "geometry": {"coordinates":[-0.3154760003,42.7132759094],"type":"Point"}
}