{
  "type": "Feature",
  "properties": {
    "iso:country":"ES",
    "sg:address":"Calle de Rosario, 7",
    "sg:city":"Santo Angel",
    "sg:orig_category":"Asesor\u00cda Sobre Comunicaci\u00d3n De Empresas",
    "sg:phone":"+34 968 84 72 77",
    "sg:postcode":"30151",
    "sg:province":"Murcia",
    "wof:name":"Marketing Pga 2000 S.l.",
    "wof:placetype":"venue"
},
  "geometry": {"coordinates":[-1.1290069818,37.9400291443],"type":"Point"}
}