{
  "type": "Feature",
  "properties": {
    "addr:full":"Carr Torrent Vallmajor, 64 Badalona Barcelona 08911",
    "addr:housenumber":"64",
    "addr:postcode":"08911",
    "addr:street":"Carr Torrent Vallmajor",
    "iso:country":"ES",
    "sg:address":"Carr Torrent Vallmajor, 64",
    "sg:city":"Badalona",
    "sg:orig_category":"Agentes, Concesionarios Y Sucursales De Veh\u00cdculos",
    "sg:phone":"+34 933 88 21 72",
    "sg:postcode":"08911",
    "sg:province":"Barcelona",
    "sg:website":"www.matumocion.com",
    "wof:name":"Mastertrac De Automacion S. A.",
    "wof:placetype":"venue"
},
  "geometry": {"coordinates":[2.2594993114,41.4619522095],"type":"Point"}
}