{
  "type": "Feature",
  "properties": {
    "addr:full":"Calle de Ciudad Real, 15 Alacant Alicante 03005",
    "addr:housenumber":"15",
    "addr:postcode":"03005",
    "addr:street":"Calle De Ciudad Real",
    "iso:country":"ES",
    "sg:address":"Calle de Ciudad Real, 15",
    "sg:city":"Alacant",
    "sg:orig_category":"Centros De Educaci\u00d3n Especial",
    "sg:phone":"+34 965 22 98 79",
    "sg:postcode":"03005",
    "sg:province":"Alicante",
    "wof:name":"Generalitat Valenciana",
    "wof:placetype":"venue"
},
  "geometry": {"coordinates":[-0.5006564856,38.3513259888],"type":"Point"}
}