{
  "type": "Feature",
  "properties": {
    "iso:country":"ES",
    "sg:address":"Carrer de Vila I Vila, 55",
    "sg:city":"Barcelona",
    "sg:orig_category":"Papeler\u00cdas, Librer\u00cdas",
    "sg:phone":"+34 934 42 58 62",
    "sg:postcode":"08004",
    "sg:province":"Barcelona",
    "wof:name":"Bueno Perez Antonio",
    "wof:placetype":"venue"
},
  "geometry": {"coordinates":[2.1704490185,41.373626709],"type":"Point"}
}