{
  "type": "Feature",
  "properties": {
    "addr:full":"Calle de Aguilar, 85 Puente-genil C\u00f3rdoba 14500",
    "addr:housenumber":"85",
    "addr:postcode":"14500",
    "addr:street":"Calle De Aguilar;Co\u0301Rdoba",
    "iso:country":"ES",
    "sg:address":"Calle de Aguilar, 85",
    "sg:city":"Puente-genil",
    "sg:orig_category":"Ense\u00d1anza: Profesiones Art\u00cdsticas",
    "sg:phone":"+34 957 60 44 80",
    "sg:postcode":"14500",
    "sg:province":"C\u00f3rdoba",
    "wof:name":"Ortiz Carpio Jorge",
    "wof:placetype":"venue"
},
  "geometry": {"coordinates":[-4.7622609138,37.3911056519],"type":"Point"}
}