{
  "type": "Feature",
  "properties": {
    "iso:country":"ES",
    "sg:address":"Calle de Cordoba, 18",
    "sg:city":"Ojos De Garza",
    "sg:orig_category":"Promotores Constructores",
    "sg:phone":"+34 928 57 40 17",
    "sg:postcode":"35219",
    "sg:province":"Las Palmas",
    "wof:name":"Herbolan S.l.",
    "wof:placetype":"venue"
},
  "geometry": {"coordinates":[-15.3946533203,27.9462718964],"type":"Point"}
}