{
  "type": "Feature",
  "properties": {
    "addr:full":"Avda Italia, 4 Pozuelo De Alarcon Madrid 28224",
    "addr:housenumber":"4",
    "addr:postcode":"28224",
    "addr:street":"Avda Italia",
    "iso:country":"ES",
    "sg:address":"Avda Italia, 4",
    "sg:city":"Pozuelo De Alarcon",
    "sg:orig_category":"Asesor\u00cda Sobre Comunicaci\u00d3n De Empresas",
    "sg:phone":"+34 917 99 01 85",
    "sg:postcode":"28224",
    "sg:province":"Madrid",
    "wof:name":"Proyectos Asesoria Y Servicios S.a.",
    "wof:placetype":"venue"
},
  "geometry": {"coordinates":[-3.7971100807,40.4497413635],"type":"Point"}
}