{
  "type": "Feature",
  "properties": {
    "addr:full":"Av Lluis Pericot, 35 Girona Girona 17003",
    "addr:housenumber":"35",
    "addr:postcode":"17003",
    "addr:street":"Av Lluis Pericot",
    "iso:country":"ES",
    "sg:address":"Av Lluis Pericot, 35",
    "sg:city":"Girona",
    "sg:orig_category":"Farmacias",
    "sg:phone":"+34 972 22 48 38",
    "sg:postcode":"17003",
    "sg:province":"Girona",
    "wof:name":"Pita Gonzalez Maria Fernanda",
    "wof:placetype":"venue"
},
  "geometry": {"coordinates":[2.8241260052,41.9687080383],"type":"Point"}
}