{
  "type": "Feature",
  "properties": {
    "iso:country":"ES",
    "sg:address":"Calle de Santiago, 5",
    "sg:city":"Sevilla",
    "sg:orig_category":"M\u00c9dicos: Neuropsiquiatr\u00cda",
    "sg:phone":"+34 954 22 43 43",
    "sg:postcode":"41003",
    "sg:province":"Sevilla",
    "wof:name":"Garcia Jaramillo Manuel",
    "wof:placetype":"venue"
},
  "geometry": {"coordinates":[-5.987528801,37.3927650452],"type":"Point"}
}