{
  "type": "Feature",
  "properties": {
    "addr:full":"Carrer de Ramelleres, 22 Barcelona Barcelona 08001",
    "addr:housenumber":"22",
    "addr:postcode":"08001",
    "addr:street":"Carrer De Ramelleres",
    "iso:country":"ES",
    "sg:address":"Carrer de Ramelleres, 22",
    "sg:city":"Barcelona",
    "sg:orig_category":"Peluqueros: De Se\u00d1oras",
    "sg:phone":"+34 933 02 15 31",
    "sg:postcode":"08001",
    "sg:province":"Barcelona",
    "wof:name":"Jorda Tomas Rosa",
    "wof:placetype":"venue"
},
  "geometry": {"coordinates":[2.1684930325,41.3846435547],"type":"Point"}
}