{
  "type": "Feature",
  "properties": {
    "iso:country":"ES",
    "sg:address":"Calle de Perez Galdos, 93",
    "sg:city":"San Vicente Del Raspeig-sant Vicent Del Raspeig",
    "sg:orig_category":"Imprenta",
    "sg:phone":"+34 965 66 47 96",
    "sg:postcode":"03690",
    "sg:province":"Alicante",
    "wof:name":"Graficas San Vicente S.l.",
    "wof:placetype":"venue"
},
  "geometry": {"coordinates":[-0.5293880105,38.3990859985],"type":"Point"}
}