{
  "type": "Feature",
  "properties": {
    "addr:full":"Esquiroz-ezkirotz Kalea, 26 Iru\u00f1a Navarra 31007",
    "addr:housenumber":"26",
    "addr:postcode":"31007",
    "addr:street":"Esquiroz-Ezkirotz Kalea",
    "iso:country":"ES",
    "sg:address":"Esquiroz-ezkirotz Kalea, 26",
    "sg:city":"Iru\u00f1a",
    "sg:orig_category":"Bronceado Por Rayos Uva",
    "sg:phone":"+34 948 17 75 21",
    "sg:postcode":"31007",
    "sg:province":"Navarra",
    "wof:name":"Liciaga Goena Izaskum",
    "wof:placetype":"venue"
},
  "geometry": {"coordinates":[-1.651556015,42.8040962219],"type":"Point"}
}