{
  "type": "Feature",
  "properties": {
    "addr:full":"Poli Industrial La Corona, 38 Fuentes Ebro Zaragoza 50740",
    "addr:housenumber":"38",
    "addr:postcode":"50740",
    "addr:street":"Corona",
    "iso:country":"ES",
    "sg:address":"Poli Industrial La Corona, 38",
    "sg:city":"Fuentes Ebro",
    "sg:orig_category":"Cerrajer\u00cda, Ferrallista",
    "sg:phone":"+34 976 16 91 91",
    "sg:postcode":"50740",
    "sg:province":"Zaragoza",
    "wof:name":"Marcametal S.c",
    "wof:placetype":"venue"
},
  "geometry": {"coordinates":[-0.6268740296,41.5112380981],"type":"Point"}
}