{
  "type": "Feature",
  "properties": {
    "addr:full":"Avda Pio Xii, 4 Valencia Valencia 46009",
    "addr:housenumber":"4",
    "addr:postcode":"46009",
    "addr:street":"Avda Pio Xii",
    "iso:country":"ES",
    "sg:address":"Avda Pio Xii, 4",
    "sg:city":"Valencia",
    "sg:orig_category":"Farmacias",
    "sg:phone":"+34 963 47 86 75",
    "sg:postcode":"46009",
    "sg:province":"Valencia",
    "wof:name":"Carmen Trullenque Dicenta Y Otros Cdad",
    "wof:placetype":"venue"
},
  "geometry": {"coordinates":[-0.3911730051,39.4797325134],"type":"Point"}
}