{
  "type": "Feature",
  "properties": {
    "addr:full":"Calle de Marques De Cabri\u00d1ana, 11 Cordoba C\u00f3rdoba 14011",
    "addr:housenumber":"11",
    "addr:postcode":"14011",
    "addr:street":"Calle De Marques De Cabrin\u0303Ana;Co\u0301Rdoba",
    "iso:country":"ES",
    "sg:address":"Calle de Marques De Cabri\u00d1ana, 11",
    "sg:city":"Cordoba",
    "sg:orig_category":"Lencer\u00cda Femenina, Corseter\u00cda, Trajes De Ba\u00d1o (al Por Menor)",
    "sg:phone":"+34 957 46 05 52",
    "sg:postcode":"14011",
    "sg:province":"C\u00f3rdoba",
    "wof:name":"Merina Lopez Teresa",
    "wof:placetype":"venue"
},
  "geometry": {"coordinates":[-4.7925901413,37.8887138367],"type":"Point"}
}