{
  "type": "Feature",
  "properties": {
    "iso:country":"ES",
    "sg:address":"Carrer de Pujada Del Castell, 52",
    "sg:city":"Manresa",
    "sg:orig_category":"Ropa De Trabajo Y Profesionales (fabricaci\u00d3n, Al Por Mayor)",
    "sg:phone":"+34 938 77 48 26",
    "sg:postcode":"08241",
    "sg:province":"Barcelona",
    "wof:name":"Rodriguez Morales Juan Diego",
    "wof:placetype":"venue"
},
  "geometry": {"coordinates":[1.8280220032,41.7289772034],"type":"Point"}
}