{
  "type": "Feature",
  "properties": {
    "addr:full":"Calle de Principe De Vergara, 74 Madrid Madrid 28006",
    "addr:housenumber":"74",
    "addr:postcode":"madrid;28006",
    "addr:street":"Calle De Principe De Vergara",
    "iso:country":"ES",
    "sg:address":"Calle de Principe De Vergara, 74",
    "sg:city":"Madrid",
    "sg:orig_category":"Sindicatos Y Colegios Profesionales",
    "sg:phone":"+34 914 11 59 71",
    "sg:postcode":"28006",
    "sg:province":"Madrid",
    "wof:name":"Asociacion Espa\u00f1ola De Anodizadores",
    "wof:placetype":"venue"
},
  "geometry": {"coordinates":[-3.6792743206,40.4348297119],"type":"Point"}
}