{
  "type": "Feature",
  "properties": {
    "addr:full":"Calle de Corregidor Jose De Pasamonte, 21 Madrid Madrid 28030",
    "addr:housenumber":"21",
    "addr:postcode":"madrid;28030",
    "addr:street":"Calle De Corregidor Jose De Pasamonte",
    "iso:country":"ES",
    "sg:address":"Calle de Corregidor Jose De Pasamonte, 21",
    "sg:city":"Madrid",
    "sg:orig_category":"Frutas, Legumbres Frescas Y Tempranas (al Por Menor)",
    "sg:phone":"+34 914 37 53 06",
    "sg:postcode":"28030",
    "sg:province":"Madrid",
    "wof:name":"Bermejo Ruiz Juan Jose",
    "wof:placetype":"venue"
},
  "geometry": {"coordinates":[-3.6479759216,40.4103126526],"type":"Point"}
}