{
  "type": "Feature",
  "properties": {
    "addr:full":"Avda Sevilla (de), 11 Rota C\u00e1diz 11520",
    "addr:housenumber":"11",
    "addr:postcode":"11520",
    "addr:street":"Avda Sevilla De;Ca\u0301Diz",
    "iso:country":"ES",
    "sg:address":"Avda Sevilla (de), 11",
    "sg:city":"Rota",
    "sg:orig_category":"Molduras, Junquillos, Listones Y Molduras Perforadas",
    "sg:phone":"+34 956 84 08 89",
    "sg:postcode":"11520",
    "sg:province":"C\u00e1diz",
    "wof:name":"Mcmahon  Victoria Caroline",
    "wof:placetype":"venue"
},
  "geometry": {"coordinates":[-6.3634018898,36.6202011108],"type":"Point"}
}