{
  "type": "Feature",
  "properties": {
    "addr:full":"Calle de San Martin, 10 Salvatierra O Agurain \u00c1lava 01200",
    "addr:housenumber":"10",
    "addr:postcode":"01200",
    "addr:street":"Calle De San Martin;A\u0301Lava",
    "iso:country":"ES",
    "sg:address":"Calle de San Martin, 10",
    "sg:city":"Salvatierra O Agurain",
    "sg:orig_category":"Quincaller\u00cda (al Por Menor)",
    "sg:phone":"+34 945 30 02 92",
    "sg:postcode":"01200",
    "sg:province":"\u00c1lava",
    "wof:name":"Leza Iba\u00f1ez De Gauna Alfredo",
    "wof:placetype":"venue"
},
  "geometry": {"coordinates":[-2.3933091164,42.8452339172],"type":"Point"}
}