{
  "type": "Feature",
  "properties": {
    "iso:country":"ES",
    "sg:address":"Calle de Maestro Martinez, 19",
    "sg:city":"Ceuti",
    "sg:orig_category":"Empresas De Carpinter\u00cda De Madera",
    "sg:phone":"+34 968 69 03 52",
    "sg:postcode":"30562",
    "sg:province":"Murcia",
    "wof:name":"Ruiz Caballero Angel",
    "wof:placetype":"venue"
},
  "geometry": {"coordinates":[-1.2729799747,38.0782012939],"type":"Point"}
}