{
  "type": "Feature",
  "properties": {
    "addr:full":"Avda Fragoso, 32 Vigo Pontevedra 36210",
    "addr:housenumber":"32",
    "addr:postcode":"36210",
    "addr:street":"Avda Fragoso",
    "iso:country":"ES",
    "sg:address":"Avda Fragoso, 32",
    "sg:city":"Vigo",
    "sg:orig_category":"Art\u00cdculos De Decoraci\u00d3n",
    "sg:phone":"+34 986 29 65 01",
    "sg:postcode":"36210",
    "sg:province":"Pontevedra",
    "sg:website":"www.lareira.com",
    "wof:name":"Lareira Eurococinas S.a.",
    "wof:placetype":"venue"
},
  "geometry": {"coordinates":[-8.7343559265,42.2178077698],"type":"Point"}
}