{
  "type": "Feature",
  "properties": {
    "iso:country":"ES",
    "sg:address":"Av Catalunya, 1",
    "sg:city":"Pobla Segur",
    "sg:orig_category":"Loter\u00cda Y T\u00d3mbola",
    "sg:phone":"+34 973 68 10 65",
    "sg:postcode":"25500",
    "sg:province":"Lleida",
    "wof:name":"Agullo Ribal Maria Teresa",
    "wof:placetype":"venue"
},
  "geometry": {"coordinates":[0.9662823081,42.2488250732],"type":"Point"}
}