{
  "type": "Feature",
  "properties": {
    "iso:country":"ES",
    "sg:address":"Casta\u00f1ar, 67",
    "sg:city":"Bejar",
    "sg:orig_category":"Promotores Constructores",
    "sg:phone":"+34 923 40 41 17",
    "sg:postcode":"37700",
    "sg:province":"Salamanca",
    "wof:name":"Lopez Martin Ciriaco",
    "wof:placetype":"venue"
},
  "geometry": {"coordinates":[-5.7658338547,40.3824653625],"type":"Point"}
}