{
  "type": "Feature",
  "properties": {
    "addr:full":"Calle de Buenos Aires, 115 Muela Zaragoza 50196",
    "addr:housenumber":"115",
    "addr:postcode":"50196",
    "addr:street":"Calle De Buenos Aires",
    "iso:country":"ES",
    "sg:address":"Calle de Buenos Aires, 115",
    "sg:city":"Muela",
    "sg:orig_category":"Embalajes",
    "sg:phone":"+34 976 14 47 84",
    "sg:postcode":"50196",
    "sg:province":"Zaragoza",
    "sg:website":"comercial@pivalco.com",
    "wof:name":"Pivalco S.l.",
    "wof:placetype":"venue"
},
  "geometry": {"coordinates":[-1.0742878914,41.6119194031],"type":"Point"}
}