{
  "type": "Feature",
  "properties": {
    "iso:country":"ES",
    "sg:address":"Poste, 19",
    "sg:city":"Rianxo",
    "sg:orig_category":"Alimentaci\u00d3n General (al Por Menor)",
    "sg:phone":"+34 981 86 23 06",
    "sg:postcode":"15920",
    "sg:province":"La Coru\u00f1a",
    "wof:name":"Filgueira Abuin Dolores",
    "wof:placetype":"venue"
},
  "geometry": {"coordinates":[-8.8172187805,42.6528091431],"type":"Point"}
}