{
  "type": "Feature",
  "properties": {
    "iso:country":"ES",
    "sg:address":"Calle de Barrio Y Mier, 6",
    "sg:city":"Palencia",
    "sg:orig_category":"Bazares, Art\u00cdculos De Limpieza Y De Cocina (al Por Menor)",
    "sg:phone":"+34 979 74 37 26",
    "sg:postcode":"34001",
    "sg:province":"Palencia",
    "wof:name":"Diego Gonzalez Sebastian",
    "wof:placetype":"venue"
},
  "geometry": {"coordinates":[-4.5340466499,42.01171875],"type":"Point"}
}