{
  "type": "Feature",
  "properties": {
    "iso:country":"ES",
    "sg:address":"Calle de Caramuel, 16",
    "sg:city":"Madrid",
    "sg:orig_category":"Molduras, Junquillos, Listones Y Molduras Perforadas",
    "sg:phone":"+34 914 70 04 59",
    "sg:postcode":"28011",
    "sg:province":"Madrid",
    "wof:name":"Xabier Pimenton Eusebio",
    "wof:placetype":"venue"
},
  "geometry": {"coordinates":[-3.7269759178,40.412273407],"type":"Point"}
}