{
  "type": "Feature",
  "properties": {
    "iso:country":"ES",
    "sg:address":"Calle de Maestro Maceda, 3",
    "sg:city":"Navia",
    "sg:orig_category":"Mensajer\u00cda Express, Portes Internacionales",
    "sg:phone":"+34 985 47 39 50",
    "sg:postcode":"33710",
    "sg:province":"Asturias",
    "wof:name":"Trancepal S.u.l",
    "wof:placetype":"venue"
},
  "geometry": {"coordinates":[-6.6691579819,43.5343322754],"type":"Point"}
}