{
  "type": "Feature",
  "properties": {
    "iso:country":"ES",
    "sg:address":"Avda Galicia (de), 5",
    "sg:city":"Ribadeo",
    "sg:orig_category":"Peluqueros: De Se\u00d1oras",
    "sg:phone":"+34 982 12 82 55",
    "sg:postcode":"27700",
    "sg:province":"Lugo",
    "wof:name":"Peluqueria Reflejos",
    "wof:placetype":"venue"
},
  "geometry": {"coordinates":[-7.0477337837,43.5367736816],"type":"Point"}
}