{
  "type": "Feature",
  "properties": {
    "addr:full":"Calle de Alejandro Moran, 23 Madrid Madrid 28025",
    "addr:housenumber":"23",
    "addr:postcode":"madrid;28025",
    "addr:street":"Calle De Alejandro Moran",
    "iso:country":"ES",
    "sg:address":"Calle de Alejandro Moran, 23",
    "sg:city":"Madrid",
    "sg:orig_category":"Comercio De Piezas De Recambio Y De Accesorios De Veh\u00cdculos, Veh\u00cdculos Industriales",
    "sg:phone":"+34 915 25 33 27",
    "sg:postcode":"28025",
    "sg:province":"Madrid",
    "wof:name":"Galiauto S.a.",
    "wof:placetype":"venue"
},
  "geometry": {"coordinates":[-3.7320857048,40.385887146],"type":"Point"}
}