{
  "type": "Feature",
  "properties": {
    "iso:country":"ES",
    "sg:address":"Avda Valencia, 41",
    "sg:city":"Villanueva Arzobispo",
    "sg:orig_category":"Zapatos (al Por Menor)",
    "sg:phone":"+34 953 45 12 68",
    "sg:postcode":"23330",
    "sg:province":"Ja\u00e9n",
    "wof:name":"Maza Herrera Alejandro",
    "wof:placetype":"venue"
},
  "geometry": {"coordinates":[-3.0064814091,38.1697273254],"type":"Point"}
}