{
  "type": "Feature",
  "properties": {
    "iso:country":"ES",
    "sg:address":"Calle de San Benito, S/n",
    "sg:city":"Orgaz",
    "sg:orig_category":"Asilos De Ancianos. Centros Privados",
    "sg:phone":"+34 925 31 73 21",
    "sg:postcode":"45450",
    "sg:province":"Toledo",
    "wof:name":"Edad Dorada Castilla-la Mancha",
    "wof:placetype":"venue"
},
  "geometry": {"coordinates":[-3.8746190071,39.6463432312],"type":"Point"}
}