{
  "type": "Feature",
  "properties": {
    "addr:full":"Av Concordia, 32 Sabadell Barcelona 08206",
    "addr:housenumber":"32",
    "addr:postcode":"08206",
    "addr:street":"Av Concordia",
    "iso:country":"ES",
    "sg:address":"Av Concordia, 32",
    "sg:city":"Sabadell",
    "sg:orig_category":"Guarder\u00cdas",
    "sg:phone":"+34 937 17 21 03",
    "sg:postcode":"08206",
    "sg:province":"Barcelona",
    "wof:name":"Boixaderas Masso Teresa",
    "wof:placetype":"venue"
},
  "geometry": {"coordinates":[2.0956840515,41.5597801208],"type":"Point"}
}