{
  "type": "Feature",
  "properties": {
    "addr:full":"Plaz Orense, 7 Coru\u00d1a La Coru\u00f1a 15...",
    "addr:housenumber":"7;15 ...",
    "addr:street":"Plaz Orense;La Corun\u0303A",
    "iso:country":"ES",
    "sg:address":"Plaz Orense, 7",
    "sg:city":"Coru\u00d1a",
    "sg:orig_category":"Sociedades, Compa\u00d1\u00cdas Aseguradoras",
    "sg:phone":"+34 981 12 27 43",
    "sg:postcode":"15...",
    "sg:province":"La Coru\u00f1a",
    "wof:name":"Sanitas S.a.",
    "wof:placetype":"venue"
},
  "geometry": {"coordinates":[-8.6255121231,43.0141448975],"type":"Point"}
}