{
  "type": "Feature",
  "properties": {
    "addr:full":"Calle de Real, 107 Almeria Almer\u00eda 04002",
    "addr:housenumber":"107",
    "addr:postcode":"04002",
    "addr:street":"Calle De Real",
    "iso:country":"ES",
    "sg:address":"Calle de Real, 107",
    "sg:city":"Almeria",
    "sg:orig_category":"Abogados",
    "sg:phone":"+34 950 23 50 51",
    "sg:postcode":"04002",
    "sg:province":"Almer\u00eda",
    "wof:name":"Gonzalez Vazquez Francisco Javier",
    "wof:placetype":"venue"
},
  "geometry": {"coordinates":[-2.4667489529,36.835975647],"type":"Point"}
}