{
  "type": "Feature",
  "properties": {
    "iso:country":"ES",
    "sg:address":"Pase Alberto Palacios, 18",
    "sg:city":"Madrid",
    "sg:orig_category":"Panader\u00cdas, Panader\u00cdas",
    "sg:phone":"+34 917 97 23 99",
    "sg:postcode":"28021",
    "sg:province":"Madrid",
    "wof:name":"Algarra Climent Josefina",
    "wof:placetype":"venue"
},
  "geometry": {"coordinates":[-3.7109069824,40.346206665],"type":"Point"}
}