{
  "type": "Feature",
  "properties": {
    "iso:country":"ES",
    "sg:address":"Carrer de Borguny, 7",
    "sg:city":"Palma",
    "sg:orig_category":"Tapicer\u00cdas",
    "sg:phone":"+34 971 73 19 62",
    "sg:postcode":"07013",
    "sg:province":"Islas Baleares",
    "wof:name":"Guarinos Deco-hogar S.l.",
    "wof:placetype":"venue"
},
  "geometry": {"coordinates":[2.638258934,39.5740394592],"type":"Point"}
}