{
  "type": "Feature",
  "properties": {
    "addr:full":"Rbra Zorrotzaurre, 15 Bilbao Vizcaya 48014",
    "addr:housenumber":"15",
    "addr:postcode":"48014",
    "addr:street":"Zorrotzaurre",
    "iso:country":"ES",
    "sg:address":"Rbra Zorrotzaurre, 15",
    "sg:city":"Bilbao",
    "sg:orig_category":"Textil",
    "sg:phone":"+34 944 15 00 80",
    "sg:postcode":"48014",
    "sg:province":"Vizcaya",
    "wof:name":"Alquileres Y Cremalleras S.a.",
    "wof:placetype":"venue"
},
  "geometry": {"coordinates":[-2.9681274891,43.2766799927],"type":"Point"}
}