{
  "type": "Feature",
  "properties": {
    "iso:country":"ES",
    "sg:address":"Carrer de Sant Jordi, 3",
    "sg:city":"Manlleu",
    "sg:orig_category":"Agencias De Viajes",
    "sg:phone":"+34 938 50 70 17",
    "sg:postcode":"08560",
    "sg:province":"Barcelona",
    "wof:name":"Viatges Osona S. L.",
    "wof:placetype":"venue"
},
  "geometry": {"coordinates":[2.2853059769,41.9999732971],"type":"Point"}
}