{
  "type": "Feature",
  "properties": {
    "iso:country":"ES",
    "sg:address":"Calle de Nueva, 35",
    "sg:city":"Motril",
    "sg:orig_category":"Centros Comerciales Y Grandes Tiendas",
    "sg:phone":"+34 958 60 22 36",
    "sg:postcode":"18600",
    "sg:province":"Granada",
    "wof:name":"Correa La Hoz Victoria",
    "wof:placetype":"venue"
},
  "geometry": {"coordinates":[-3.5181660652,36.7475662231],"type":"Point"}
}