{
  "type": "Feature",
  "properties": {
    "iso:country":"ES",
    "sg:address":"Calle de Santa Engracia, 151",
    "sg:city":"Madrid",
    "sg:orig_category":"Periodistas Profesionales",
    "sg:phone":"+34 915 33 73 74",
    "sg:postcode":"28003",
    "sg:province":"Madrid",
    "wof:name":"Maestro Martinez Angel",
    "wof:placetype":"venue"
},
  "geometry": {"coordinates":[-3.7028269768,40.4439620972],"type":"Point"}
}