{
  "type": "Feature",
  "properties": {
    "iso:country":"ES",
    "sg:address":"R. Laporta, 30",
    "sg:city":"Cantalapiedra",
    "sg:orig_category":"Iglesia Cat\u00d3lica",
    "sg:phone":"+34 923 53 00 70",
    "sg:postcode":"37400",
    "sg:province":"Salamanca",
    "wof:name":"Obispado De Salamanca",
    "wof:placetype":"venue"
},
  "geometry": {"coordinates":[-5.1828389168,41.125289917],"type":"Point"}
}