{
  "type": "Feature",
  "properties": {
    "iso:country":"ES",
    "sg:address":"Carrer de Ample, 45",
    "sg:city":"Barcelona",
    "sg:orig_category":"Empresarios",
    "sg:phone":"+34 932 68 79 53",
    "sg:postcode":"08002",
    "sg:province":"Barcelona",
    "wof:name":"Iqbal  Yasar",
    "wof:placetype":"venue"
},
  "geometry": {"coordinates":[2.1803689003,41.3812332153],"type":"Point"}
}