{
  "type": "Feature",
  "properties": {
    "addr:full":"Calle de San Fortunato, 32 Madrid Madrid 28041",
    "addr:housenumber":"32",
    "addr:postcode":"madrid;28041",
    "addr:street":"Calle De San Fortunato",
    "iso:country":"ES",
    "sg:address":"Calle de San Fortunato, 32",
    "sg:city":"Madrid",
    "sg:orig_category":"Cer\u00c1micas: Material Y Suministros",
    "sg:phone":"+34 917 92 14 39",
    "sg:postcode":"28041",
    "sg:province":"Madrid",
    "wof:name":"Suministros Y Saneamientos San Fermin S.l",
    "wof:placetype":"venue"
},
  "geometry": {"coordinates":[-3.6892917156,40.3734207153],"type":"Point"}
}