{
  "type": "Feature",
  "properties": {
    "iso:country":"ES",
    "sg:address":"Pol Ind La Rambla, S/n",
    "sg:city":"Almassora",
    "sg:orig_category":"Maquinaria Para Industrias Diversas",
    "sg:phone":"+34 964 50 61 49",
    "sg:postcode":"12550",
    "sg:province":"Castell\u00f3n",
    "wof:name":"Consulting Elec-eurotec S.l.u.",
    "wof:placetype":"venue"
},
  "geometry": {"coordinates":[-0.0631700009,39.9439582825],"type":"Point"}
}