{
  "type": "Feature",
  "properties": {
    "iso:country":"ES",
    "sg:address":"Avda Sevilla, 54",
    "sg:city":"Palacios Y Villafranca",
    "sg:orig_category":"Servicio De Salud",
    "sg:phone":"+34 955 81 49 31",
    "sg:postcode":"41720",
    "sg:province":"Sevilla",
    "wof:name":"Fontaneria Y Azulejos Rodriguez S.l.",
    "wof:placetype":"venue"
},
  "geometry": {"coordinates":[-5.924246788,37.1639900208],"type":"Point"}
}