{
  "type": "Feature",
  "properties": {
    "iso:country":"ES",
    "sg:address":"Calle de Torres Quevedo, S/n",
    "sg:city":"Pe\u00e7arroya-pueblonuevo",
    "sg:orig_category":"Mec\u00c1nico Del Autom\u00d3vil",
    "sg:phone":"+34 957 56 25 42",
    "sg:postcode":"14200",
    "sg:province":"C\u00f3rdoba",
    "wof:name":"Duran Alvarez Rafael",
    "wof:placetype":"venue"
},
  "geometry": {"coordinates":[-5.2566537857,38.2997550964],"type":"Point"}
}