{
  "type": "Feature",
  "properties": {
    "addr:full":"Carrer de Roger De Flor, 242 Barcelona Barcelona 08025",
    "addr:housenumber":"242",
    "addr:postcode":"08025",
    "addr:street":"Carrer De Roger De Flor",
    "iso:country":"ES",
    "sg:address":"Carrer de Roger De Flor, 242",
    "sg:city":"Barcelona",
    "sg:orig_category":"Imprenta",
    "sg:phone":"+34 934 57 32 31",
    "sg:postcode":"08025",
    "sg:province":"Barcelona",
    "wof:name":"Vilanova Sans Joan",
    "wof:placetype":"venue"
},
  "geometry": {"coordinates":[2.1690011024,41.4017906189],"type":"Point"}
}