{
  "type": "Feature",
  "properties": {
    "addr:full":"Carr Sor Rita Mercader, 22 Igualada Barcelona 08700",
    "addr:housenumber":"22",
    "addr:postcode":"08700",
    "addr:street":"Carr Sor Rita Mercader",
    "iso:country":"ES",
    "sg:address":"Carr Sor Rita Mercader, 22",
    "sg:city":"Igualada",
    "sg:orig_category":"Fabricaci\u00d3n De Su\u00c9ters Y Chalecos De Punto",
    "sg:phone":"+34 938 03 74 11",
    "sg:postcode":"08700",
    "sg:province":"Barcelona",
    "wof:name":"Esteve Aguilera S.a.",
    "wof:placetype":"venue"
},
  "geometry": {"coordinates":[1.6099100113,41.5821418762],"type":"Point"}
}