{
  "type": "Feature",
  "properties": {
    "addr:full":"Calle de Cuesta Del Monjon (de La), 16 Colmenar Viejo Madrid 28770",
    "addr:postcode":"28770",
    "addr:street":"Calle De Cuesta Del Monjon De La",
    "iso:country":"ES",
    "sg:address":"Calle de Cuesta Del Monjon (de La), 16",
    "sg:city":"Colmenar Viejo",
    "sg:orig_category":"Cerrajer\u00cda, Ferrallista",
    "sg:phone":"+34 918 45 76 52",
    "sg:postcode":"28770",
    "sg:province":"Madrid",
    "wof:name":"Herrero Diaz Luis",
    "wof:placetype":"venue"
},
  "geometry": {"coordinates":[-3.7662372589,40.6530189514],"type":"Point"}
}