{
  "type": "Feature",
  "properties": {
    "iso:country":"ES",
    "sg:address":"Calle de Alberto Aguilera, 4",
    "sg:city":"Madrid",
    "sg:orig_category":"Abogados",
    "sg:phone":"+34 915 93 13 35",
    "sg:postcode":"28015",
    "sg:province":"Madrid",
    "wof:name":"Nieto Huete Luis Miguel",
    "wof:placetype":"venue"
},
  "geometry": {"coordinates":[-3.7065644264,40.4297332764],"type":"Point"}
}