{
  "type": "Feature",
  "properties": {
    "addr:full":"Carr Progres, 316 Badalona Barcelona 08918",
    "addr:housenumber":"316",
    "addr:postcode":"08918",
    "addr:street":"Carr Progres",
    "iso:country":"ES",
    "sg:address":"Carr Progres, 316",
    "sg:city":"Badalona",
    "sg:orig_category":"Art\u00cdculos De Decoraci\u00d3n",
    "sg:phone":"+34 934 60 33 80",
    "sg:postcode":"08918",
    "sg:province":"Barcelona",
    "wof:name":"Gualart S. L.",
    "wof:placetype":"venue"
},
  "geometry": {"coordinates":[2.2329289913,41.4345817566],"type":"Point"}
}