{
  "type": "Feature",
  "properties": {
    "addr:full":"Calle de Claudio Coello, 99 Madrid Madrid 28006",
    "addr:housenumber":"99",
    "addr:postcode":"madrid;28006",
    "addr:street":"Calle De Claudio Coello",
    "iso:country":"ES",
    "sg:address":"Calle de Claudio Coello, 99",
    "sg:city":"Madrid",
    "sg:orig_category":"Edici\u00d3n De Diarios, Revistas, Boletines",
    "sg:phone":"+34 915 93 15 48",
    "sg:postcode":"28006",
    "sg:province":"Madrid",
    "wof:name":"Fernando Villaverde Ediciones S.l.",
    "wof:placetype":"venue"
},
  "geometry": {"coordinates":[-3.6857609749,40.4313354492],"type":"Point"}
}