{
  "type": "Feature",
  "properties": {
    "iso:country":"ES",
    "sg:address":"Avda Virgen De La Monta\u00d1a, 6",
    "sg:city":"Caceres",
    "sg:orig_category":"Centros P\u00dablicos De Formaci\u00d3n Profesional Y T\u00c9cnica",
    "sg:phone":"+34 927 21 46 04",
    "sg:postcode":"10004",
    "sg:province":"C\u00e1ceres",
    "wof:name":"Colegio De Abogados De Caceres",
    "wof:placetype":"venue"
},
  "geometry": {"coordinates":[-6.3765239716,39.4711494446],"type":"Point"}
}