{
  "type": "Feature",
  "properties": {
    "iso:country":"ES",
    "sg:address":"Calle de San Juan, 17",
    "sg:city":"Meliana",
    "sg:orig_category":"M\u00c9dicos: Estomatolog\u00cda",
    "sg:phone":"+34 961 49 15 96",
    "sg:postcode":"46133",
    "sg:province":"Valencia",
    "wof:name":"Peris Riera Jose",
    "wof:placetype":"venue"
},
  "geometry": {"coordinates":[-0.3480559886,39.5281257629],"type":"Point"}
}