{
  "type": "Feature",
  "properties": {
    "iso:country":"ES",
    "sg:address":"Afores, S/n",
    "sg:city":"S. Jaume Enveja",
    "sg:orig_category":"Fabricaci\u00d3n De Pastas Alimentarias",
    "sg:phone":"+34 977 46 81 14",
    "sg:postcode":"43877",
    "sg:province":"Tarragona",
    "wof:name":"Sat El Pantar R.l.",
    "wof:placetype":"venue"
},
  "geometry": {"coordinates":[0.7171549797,40.7040596008],"type":"Point"}
}