{
  "type": "Feature",
  "properties": {
    "addr:full":"Carr Costa Brava, S/n Blanes Girona 17300",
    "addr:housenumber":"s / n",
    "addr:postcode":"17300",
    "addr:street":"Carr Costa Brava",
    "iso:country":"ES",
    "sg:address":"Carr Costa Brava, S/n",
    "sg:city":"Blanes",
    "sg:orig_category":"Calderer\u00cda",
    "sg:phone":"+34 972 33 35 49",
    "sg:postcode":"17300",
    "sg:province":"Girona",
    "wof:name":"Inoxcer S.l.",
    "wof:placetype":"venue"
},
  "geometry": {"coordinates":[2.7862250805,41.66746521],"type":"Point"}
}