{
  "type": "Feature",
  "properties": {
    "addr:full":"Calle de Salamanca, 16 Alcala Henares Madrid 28804",
    "addr:housenumber":"16",
    "addr:postcode":"28804",
    "addr:street":"Calle De Salamanca",
    "iso:country":"ES",
    "sg:address":"Calle de Salamanca, 16",
    "sg:city":"Alcala Henares",
    "sg:orig_category":"Peluquer\u00cdas, Peluquer\u00cda Mixta",
    "sg:phone":"+34 918 82 58 93",
    "sg:postcode":"28804",
    "sg:province":"Madrid",
    "wof:name":"Feeling Peluqueros S.l.",
    "wof:placetype":"venue"
},
  "geometry": {"coordinates":[-3.3508880138,40.4855957031],"type":"Point"}
}