{
  "type": "Feature",
  "properties": {
    "addr:full":"Calle de Alberto Aguilera, 64 Madrid Madrid 28015",
    "addr:housenumber":"64",
    "addr:postcode":"madrid;28015",
    "addr:street":"Calle De Alberto Aguilera",
    "iso:country":"ES",
    "sg:address":"Calle de Alberto Aguilera, 64",
    "sg:city":"Madrid",
    "sg:orig_category":"Ropa Para Se\u00d1oras Y Caballeros (al Por Menor)",
    "sg:phone":"+34 915 44 05 79",
    "sg:postcode":"28015",
    "sg:province":"Madrid",
    "sg:website":"www.coroneltapioca.com",
    "wof:name":"Coronel Tapioca S.a.",
    "wof:placetype":"venue"
},
  "geometry": {"coordinates":[-3.7147858143,40.4305458069],"type":"Point"}
}