{
  "type": "Feature",
  "properties": {
    "iso:country":"ES",
    "sg:address":"Ctra. Linares, 12",
    "sg:city":"Ubeda",
    "sg:orig_category":"Caf\u00c9s, Bares, Cervecer\u00cdas",
    "sg:phone":"+34 953 75 72 98",
    "sg:postcode":"23400",
    "sg:province":"Ja\u00e9n",
    "wof:name":"Josema Y Anabel S.l.",
    "wof:placetype":"venue"
},
  "geometry": {"coordinates":[-3.3713839054,38.0111618042],"type":"Point"}
}