{
  "type": "Feature",
  "properties": {
    "iso:country":"ES",
    "sg:address":"Carrer de Sant Josep De Calassan\u00c7, 13",
    "sg:city":"Granollers",
    "sg:orig_category":"Agentes Generales De Seguros",
    "sg:phone":"+34 938 70 20 80",
    "sg:postcode":"08402",
    "sg:province":"Barcelona",
    "wof:name":"Morera Vilardell Margarita",
    "wof:placetype":"venue"
},
  "geometry": {"coordinates":[2.2898139954,41.6043701172],"type":"Point"}
}