{
  "type": "Feature",
  "properties": {
    "iso:country":"ES",
    "sg:address":"Calle de Parra (la), 15",
    "sg:city":"Cella",
    "sg:orig_category":"Promotores Constructores",
    "sg:phone":"+34 978 65 33 10",
    "sg:postcode":"44370",
    "sg:province":"Teruel",
    "wof:name":"Roberto Rodriguez E Hijos S.l.",
    "wof:placetype":"venue"
},
  "geometry": {"coordinates":[-1.2818330526,40.4533309937],"type":"Point"}
}