{
  "type": "Feature",
  "properties": {
    "addr:full":"Avda Doctor Jimenez Diaz, 22 Alacant Alicante 03005",
    "addr:housenumber":"22",
    "addr:postcode":"03005",
    "addr:street":"Avda Doctor Jimenez Diaz",
    "iso:country":"ES",
    "sg:address":"Avda Doctor Jimenez Diaz, 22",
    "sg:city":"Alacant",
    "sg:orig_category":"Venta, Montaje De Neum\u00c1ticos",
    "sg:phone":"+34 965 12 48 92",
    "sg:postcode":"03005",
    "sg:province":"Alicante",
    "wof:name":"Neumaticos Soledad S.l.",
    "wof:placetype":"venue"
},
  "geometry": {"coordinates":[-0.5014500022,38.3545303345],"type":"Point"}
}