{
  "type": "Feature",
  "properties": {
    "addr:full":"Carrer de Santa Anna, 10 Barcelona Barcelona 08002",
    "addr:housenumber":"10",
    "addr:postcode":"08002",
    "addr:street":"Carrer De Santa Anna",
    "iso:country":"ES",
    "sg:address":"Carrer de Santa Anna, 10",
    "sg:city":"Barcelona",
    "sg:orig_category":"Alimentaci\u00d3n General (al Por Menor)",
    "sg:phone":"+34 933 17 27 88",
    "sg:postcode":"08002",
    "sg:province":"Barcelona",
    "wof:name":"Gil Burillo Gerardo",
    "wof:placetype":"venue"
},
  "geometry": {"coordinates":[2.1712970734,41.3849220276],"type":"Point"}
}