{
  "type": "Feature",
  "properties": {
    "iso:country":"ES",
    "sg:address":"Las Escuelas, 17",
    "sg:city":"Montorio",
    "sg:orig_category":"Producci\u00d3n, Venta De Productos De Agricultura Biol\u00d3gica",
    "sg:phone":"+34 947 15 40 64",
    "sg:postcode":"09125",
    "sg:province":"Burgos",
    "wof:name":"Sociedad Cooperativa Rio Mon",
    "wof:placetype":"venue"
},
  "geometry": {"coordinates":[-3.859525919,42.617389679],"type":"Point"}
}