{
  "type": "Feature",
  "properties": {
    "iso:country":"ES",
    "sg:address":"Calle de Eugenio Hermoso, 2",
    "sg:city":"Oliva Frontera",
    "sg:orig_category":"Polideportivos",
    "sg:phone":"+34 924 74 07 28",
    "sg:postcode":"06120",
    "sg:province":"Badajoz",
    "wof:name":"Ayuntamiento",
    "wof:placetype":"venue"
},
  "geometry": {"coordinates":[-6.9174423218,38.2705001831],"type":"Point"}
}