{
  "type": "Feature",
  "properties": {
    "iso:country":"ES",
    "sg:address":"Calle de Virgen De Los Peligros, 11",
    "sg:city":"Madrid",
    "sg:orig_category":"Bisuter\u00cda, Joyer\u00cda, Relojer\u00cda (al Por Menor)",
    "sg:phone":"+34 915 22 44 23",
    "sg:postcode":"28013",
    "sg:province":"Madrid",
    "wof:name":"Ramirez Poblacion Buenaventura",
    "wof:placetype":"venue"
},
  "geometry": {"coordinates":[-3.6998031139,40.4190139771],"type":"Point"}
}