{
  "type": "Feature",
  "properties": {
    "iso:country":"ES",
    "sg:address":"Avda Madrid (de), 35",
    "sg:city":"Arganda",
    "sg:orig_category":"Artes Gr\u00c1ficas, Artes Pl\u00c1sticas (curso)",
    "sg:phone":"+34 918 75 01 00",
    "sg:postcode":"28500",
    "sg:province":"Madrid",
    "wof:name":"Gaez S.a.",
    "wof:placetype":"venue"
},
  "geometry": {"coordinates":[-3.4612679482,40.3055038452],"type":"Point"}
}