{
  "type": "Feature",
  "properties": {
    "addr:full":"Rond Sant Pere, 21 Barcelona Barcelona 08010",
    "addr:housenumber":"21",
    "addr:postcode":"08010",
    "addr:street":"Sant Pere",
    "iso:country":"ES",
    "sg:address":"Rond Sant Pere, 21",
    "sg:city":"Barcelona",
    "sg:orig_category":"Librer\u00cdas",
    "sg:phone":"+34 933 01 14 88",
    "sg:postcode":"08010",
    "sg:province":"Barcelona",
    "wof:name":"Pia Sociedad Hijas De San Pablo",
    "wof:placetype":"venue"
},
  "geometry": {"coordinates":[2.1740159988,41.3895797729],"type":"Point"}
}