{
  "type": "Feature",
  "properties": {
    "iso:country":"ES",
    "sg:address":"Carr Calvario, 63",
    "sg:city":"Betera",
    "sg:orig_category":"Fisioterapia",
    "sg:phone":"+34 961 69 18 87",
    "sg:postcode":"46117",
    "sg:province":"Valencia",
    "wof:name":"Morello Izquierdo Juan Jose",
    "wof:placetype":"venue"
},
  "geometry": {"coordinates":[-0.458968997,39.5898666382],"type":"Point"}
}