{
  "type": "Feature",
  "properties": {
    "addr:full":"Calle de Padre R. De Los Rios, 37 Alacant Alicante 03005",
    "addr:housenumber":"37",
    "addr:postcode":"03005",
    "addr:street":"Calle De Padre R. De Los Rios",
    "iso:country":"ES",
    "sg:address":"Calle de Padre R. De Los Rios, 37",
    "sg:city":"Alacant",
    "sg:orig_category":"Loter\u00cda Y T\u00d3mbola",
    "sg:phone":"+34 965 92 55 62",
    "sg:postcode":"03005",
    "sg:province":"Alicante",
    "wof:name":"Hernandez Ferri Eva Maria",
    "wof:placetype":"venue"
},
  "geometry": {"coordinates":[-0.5013030171,38.3495063782],"type":"Point"}
}