{
  "type": "Feature",
  "properties": {
    "addr:full":"Calle de Constitucion, 7 Chiclana De La Frontera C\u00e1diz 11130",
    "addr:housenumber":"7",
    "addr:postcode":"11130",
    "addr:street":"Calle De Constitucion",
    "iso:country":"ES",
    "sg:address":"Calle de Constitucion, 7",
    "sg:city":"Chiclana De La Frontera",
    "sg:orig_category":"Psic\u00d3logos",
    "sg:phone":"+34 956 53 31 97",
    "sg:postcode":"11130",
    "sg:province":"C\u00e1diz",
    "wof:name":"Rodriguez Vazquez Carmen",
    "wof:placetype":"venue"
},
  "geometry": {"coordinates":[-6.1496562958,36.4191741943],"type":"Point"}
}