{
  "type": "Feature",
  "properties": {
    "addr:full":"A Torre(sarces), 13 Laxe La Coru\u00f1a 15117",
    "addr:housenumber":"13",
    "addr:postcode":"15117",
    "addr:street":"Laxe La Corun\u0303A",
    "iso:country":"ES",
    "sg:address":"A Torre(sarces), 13",
    "sg:city":"Laxe",
    "sg:orig_category":"Electrodom\u00c9sticos (al Por Menor)",
    "sg:phone":"+34 981 72 83 57",
    "sg:postcode":"15117",
    "sg:province":"La Coru\u00f1a",
    "wof:name":"Comercial Santelibar S.l.",
    "wof:placetype":"venue"
},
  "geometry": {"coordinates":[-9.0046443939,43.2222595215],"type":"Point"}
}