{
  "type": "Feature",
  "properties": {
    "addr:full":"Carr Alfons Xii, 169 Badalona Barcelona 08912",
    "addr:housenumber":"169",
    "addr:postcode":"08912",
    "addr:street":"Carr Alfons Xii",
    "iso:country":"ES",
    "sg:address":"Carr Alfons Xii, 169",
    "sg:city":"Badalona",
    "sg:orig_category":"Asesor\u00cda Fiscal Y Jur\u00cddica",
    "sg:phone":"+34 933 99 08 50",
    "sg:postcode":"08912",
    "sg:province":"Barcelona",
    "wof:name":"Servicios Empresariales Lloreda S.l.",
    "wof:placetype":"venue"
},
  "geometry": {"coordinates":[2.2376880646,41.4422302246],"type":"Point"}
}