{
  "type": "Feature",
  "properties": {
    "addr:full":"Pla\u00c7 Fabrica Nova, 17 Vilanova I La Geltru Barcelona 08800",
    "addr:housenumber":"17",
    "addr:postcode":"08800",
    "iso:country":"ES",
    "sg:address":"Pla\u00c7 Fabrica Nova, 17",
    "sg:city":"Vilanova I La Geltru",
    "sg:orig_category":"Inmobiliaria (agencias)",
    "sg:phone":"+34 938 16 59 43",
    "sg:postcode":"08800",
    "sg:province":"Barcelona",
    "wof:name":"Ferrer Vilela Jorge",
    "wof:placetype":"venue"
},
  "geometry": {"coordinates":[1.7167259455,41.2257270813],"type":"Point"}
}