{
  "type": "Feature",
  "properties": {
    "iso:country":"ES",
    "sg:address":"Calle de Comercio, 78",
    "sg:city":"Puebla Del Rio",
    "sg:orig_category":"Electricidad: Equipos Industriales, Componentes (fabricaci\u00d3n)",
    "sg:phone":"+34 955 77 19 19",
    "sg:postcode":"41130",
    "sg:province":"Sevilla",
    "wof:name":"Rafael Viejo S.cv.",
    "wof:placetype":"venue"
},
  "geometry": {"coordinates":[-6.0622520447,37.2682037354],"type":"Point"}
}