{
  "type": "Feature",
  "properties": {
    "iso:country":"ES",
    "sg:address":"Calle de Puerto Real, S/n",
    "sg:city":"Jerez De La Frontera",
    "sg:orig_category":"Producci\u00d3n De Abonos Y De Fertilizantes",
    "sg:phone":"+34 956 23 72 47",
    "sg:postcode":"11408",
    "sg:province":"C\u00e1diz",
    "wof:name":"Sufi S.a.",
    "wof:placetype":"venue"
},
  "geometry": {"coordinates":[-6.1366939545,36.6730575562],"type":"Point"}
}