{
  "type": "Feature",
  "properties": {
    "addr:full":"Calle de Riego (santa Isabel), 1 Zaragoza Zaragoza 50016",
    "addr:housenumber":"1",
    "addr:postcode":"50016",
    "addr:street":"Calle De Riego Santa Isabel",
    "iso:country":"ES",
    "sg:address":"Calle de Riego (santa Isabel), 1",
    "sg:city":"Zaragoza",
    "sg:orig_category":"Cervecer\u00cdas",
    "sg:phone":"+34 976 57 34 17",
    "sg:postcode":"50016",
    "sg:province":"Zaragoza",
    "wof:name":"Telefonia Aragonesa Escucha Rapida S.l.",
    "wof:placetype":"venue"
},
  "geometry": {"coordinates":[-0.8330268264,41.6673126221],"type":"Point"}
}