{
  "type": "Feature",
  "properties": {
    "iso:country":"ES",
    "sg:address":"Calle de Comercio, 18",
    "sg:city":"Ribadesella",
    "sg:orig_category":"Abogados",
    "sg:phone":"+34 985 85 80 28",
    "sg:postcode":"33560",
    "sg:province":"Asturias",
    "wof:name":"Arg\u00fcero Martinez Jose Luis",
    "wof:placetype":"venue"
},
  "geometry": {"coordinates":[-5.0586156845,43.4627037048],"type":"Point"}
}