{
  "type": "Feature",
  "properties": {
    "addr:full":"Plaz Alloz, S/n Madrid Madrid 28025",
    "addr:housenumber":"s / n",
    "addr:postcode":"28025",
    "addr:street":"Plaz Alloz",
    "iso:country":"ES",
    "sg:address":"Plaz Alloz, S/n",
    "sg:city":"Madrid",
    "sg:orig_category":"Centros De Educaci\u00d3n Especial",
    "sg:phone":"+34 914 28 41 64",
    "sg:postcode":"28025",
    "sg:province":"Madrid",
    "wof:name":"Ministerio De Educacion Y Cienca",
    "wof:placetype":"venue"
},
  "geometry": {"coordinates":[-3.7368888855,40.3761444092],"type":"Point"}
}