{
  "type": "Feature",
  "properties": {
    "iso:country":"ES",
    "sg:address":"Pol Ind Marismas, 27",
    "sg:city":"Lebrija",
    "sg:orig_category":"Material Y Herramientas Agr\u00cdcolas",
    "sg:phone":"+34 955 97 00 38",
    "sg:postcode":"41740",
    "sg:province":"Sevilla",
    "wof:name":"Sicilia Castro S.l.",
    "wof:placetype":"venue"
},
  "geometry": {"coordinates":[-6.0658698082,36.9205932617],"type":"Point"}
}