{
  "type": "Feature",
  "properties": {
    "iso:country":"ES",
    "sg:address":"Calle de Sol (del), 10",
    "sg:city":"Linea De La Concepcion",
    "sg:orig_category":"Agencias De Viajes",
    "sg:phone":"+34 956 69 00 72",
    "sg:postcode":"11300",
    "sg:province":"C\u00e1diz",
    "wof:name":"Viajes Porto Albo S.l.",
    "wof:placetype":"venue"
},
  "geometry": {"coordinates":[-5.3366889954,36.175403595],"type":"Point"}
}