{
  "type": "Feature",
  "properties": {
    "iso:country":"ES",
    "sg:address":"Calle de Huerta Del Convento, 10",
    "sg:city":"Loja",
    "sg:orig_category":"Asociaciones Y Clubs Deportivos",
    "sg:phone":"+34 958 32 36 99",
    "sg:postcode":"18300",
    "sg:province":"Granada",
    "wof:name":"Recrea Servicios Deportivos, S.l.",
    "wof:placetype":"venue"
},
  "geometry": {"coordinates":[-4.1452770233,37.1625022888],"type":"Point"}
}