{
  "type": "Feature",
  "properties": {
    "iso:country":"ES",
    "sg:address":"Ctra. Pulpi, S/n",
    "sg:city":"Huercal-overa",
    "sg:orig_category":"Aparatos E Instalaci\u00d3n De Regad\u00cdos",
    "sg:phone":"+34 950 47 11 86",
    "sg:postcode":"04600",
    "sg:province":"Almer\u00eda",
    "wof:name":"Parra Sanchez Diego",
    "wof:placetype":"venue"
},
  "geometry": {"coordinates":[-1.9068739414,37.4010925293],"type":"Point"}
}