{
  "type": "Feature",
  "properties": {
    "iso:country":"ES",
    "sg:address":"Carr Pollentia, 21",
    "sg:city":"Alcudia",
    "sg:orig_category":"Inmobiliaria (agencias)",
    "sg:phone":"+34 971 54 75 77",
    "sg:postcode":"07400",
    "sg:province":"Islas Baleares",
    "wof:name":"Rebasa Cerda Jose Miguel",
    "wof:placetype":"venue"
},
  "geometry": {"coordinates":[3.1250770092,39.8522491455],"type":"Point"}
}