{
  "type": "Feature",
  "properties": {
    "iso:country":"ES",
    "sg:address":"Av Catalunya, 18",
    "sg:city":"Puigdalber",
    "sg:orig_category":"Ca\u00d1a, Mimbre Y Bamb\u00da",
    "sg:phone":"+34 938 98 82 44",
    "sg:postcode":"08797",
    "sg:province":"Barcelona",
    "wof:name":"Canyissos Valles S.l.",
    "wof:placetype":"venue"
},
  "geometry": {"coordinates":[1.7017869949,41.403968811],"type":"Point"}
}