{
  "type": "Feature",
  "properties": {
    "addr:full":"El Carmen, S/n Tegueste Santa Cruz De Tenerife 38280",
    "addr:housenumber":"s / n",
    "addr:postcode":"38280",
    "addr:street":"El Carmen",
    "iso:country":"ES",
    "sg:address":"El Carmen, S/n",
    "sg:city":"Tegueste",
    "sg:orig_category":"Bazares, Art\u00cdculos De Limpieza Y De Cocina (al Por Menor)",
    "sg:phone":"+34 922 15 09 81",
    "sg:postcode":"38280",
    "sg:province":"Santa Cruz De Tenerife",
    "wof:name":"Rodriguez Rodriguez Carlos Manuel",
    "wof:placetype":"venue"
},
  "geometry": {"coordinates":[-16.3379745483,28.5221805573],"type":"Point"}
}