{
  "type": "Feature",
  "properties": {
    "iso:country":"ES",
    "sg:address":"Avda Gregorio Diego, 11",
    "sg:city":"Malaga",
    "sg:orig_category":"Adaptaciones, Acondicionamientos Especiales Para Veh\u00cdculos, Veh\u00cdculos Industriales",
    "sg:phone":"+34 952 23 24 39",
    "sg:postcode":"29004",
    "sg:province":"M\u00e1laga",
    "wof:name":"Gonzalez Martinez Diego",
    "wof:placetype":"venue"
},
  "geometry": {"coordinates":[-4.4532032013,36.691028595],"type":"Point"}
}