{
  "type": "Feature",
  "properties": {
    "iso:country":"ES",
    "sg:address":"Calle de Cercados (los), 7",
    "sg:city":"Fuentemilanos",
    "sg:orig_category":"Quincaller\u00cda (al Por Menor)",
    "sg:phone":"+34 921 48 51 47",
    "sg:postcode":"40153",
    "sg:province":"Segovia",
    "wof:name":"Femaser S.l",
    "wof:placetype":"venue"
},
  "geometry": {"coordinates":[-4.2291622162,40.8747291565],"type":"Point"}
}