{
  "type": "Feature",
  "properties": {
    "iso:country":"ES",
    "sg:address":"Calle de Noya, 36",
    "sg:city":"Coru\u00d1a",
    "sg:orig_category":"Caf\u00c9s, Bares, Cervecer\u00cdas",
    "sg:phone":"+34 981 23 00 79",
    "sg:postcode":"15007",
    "sg:province":"La Coru\u00f1a",
    "wof:name":"Maria Josefa Pereira Torron Y Otra Sc",
    "wof:placetype":"venue"
},
  "geometry": {"coordinates":[-8.4108324051,43.3569641113],"type":"Point"}
}