{
  "type": "Feature",
  "properties": {
    "iso:country":"ES",
    "sg:address":"Calle de Portales, 16",
    "sg:city":"Rincon Soto",
    "sg:orig_category":"Quincaller\u00cda (al Por Menor)",
    "sg:phone":"+34 941 16 06 98",
    "sg:postcode":"26550",
    "sg:province":"La Rioja",
    "wof:name":"Mendizabal Mendizabal Pilar",
    "wof:placetype":"venue"
},
  "geometry": {"coordinates":[-1.8525849581,42.2351913452],"type":"Point"}
}