{
  "type": "Feature",
  "properties": {
    "addr:full":"Pol Ind Los Vasalos, 107 Onil Alicante 03430",
    "addr:housenumber":"107",
    "addr:postcode":"03430",
    "addr:street":"Vasalos",
    "iso:country":"ES",
    "sg:address":"Pol Ind Los Vasalos, 107",
    "sg:city":"Onil",
    "sg:orig_category":"Juegos Y Juguetes (al Por Menor)",
    "sg:phone":"+34 966 55 75 45",
    "sg:postcode":"03430",
    "sg:province":"Alicante",
    "wof:name":"Industrias Buzma S.l",
    "wof:placetype":"venue"
},
  "geometry": {"coordinates":[-0.6756309867,38.623840332],"type":"Point"}
}