{
  "type": "Feature",
  "properties": {
    "addr:full":"San Roque, 42 Melide La Coru\u00f1a 15800",
    "addr:housenumber":"42",
    "addr:postcode":"15800",
    "addr:street":"San Roque;La Corun\u0303A",
    "iso:country":"ES",
    "sg:address":"San Roque, 42",
    "sg:city":"Melide",
    "sg:orig_category":"Quincaller\u00cda (al Por Menor)",
    "sg:phone":"+34 981 50 59 09",
    "sg:postcode":"15800",
    "sg:province":"La Coru\u00f1a",
    "wof:name":"Industrias Sanchez Couceiro S.l.",
    "wof:placetype":"venue"
},
  "geometry": {"coordinates":[-8.0126686096,42.9136886597],"type":"Point"}
}