{
  "type": "Feature",
  "properties": {
    "addr:full":"Calle de Prado Del Rey, 59 Humera-somosaguas-prado Del Rey Madrid 28223",
    "addr:housenumber":"59",
    "addr:postcode":"28223",
    "addr:street":"Calle De Prado Del Rey",
    "iso:country":"ES",
    "sg:address":"Calle de Prado Del Rey, 59",
    "sg:city":"Humera-somosaguas-prado Del Rey",
    "sg:orig_category":"Masajistas Kinesiterapeutas",
    "sg:phone":"+34 917 11 99 18",
    "sg:postcode":"28223",
    "sg:province":"Madrid",
    "wof:name":"Puerta Vazquez Maria Esther",
    "wof:placetype":"venue"
},
  "geometry": {"coordinates":[-3.7948269844,40.4133529663],"type":"Point"}
}