{
  "type": "Feature",
  "properties": {
    "iso:country":"ES",
    "sg:address":"Ctra San Juan, 14",
    "sg:city":"Moratalla",
    "sg:orig_category":"Electrodom\u00c9sticos (al Por Menor)",
    "sg:phone":"+34 968 73 03 75",
    "sg:postcode":"30440",
    "sg:province":"Murcia",
    "wof:name":"Electronica Sanchez Y Moya S.l.",
    "wof:placetype":"venue"
},
  "geometry": {"coordinates":[-1.8907990456,38.187286377],"type":"Point"}
}