{
  "type": "Feature",
  "properties": {
    "addr:full":"Carr Botera, 11 Alguaire Lleida 25125",
    "addr:housenumber":"11",
    "addr:postcode":"25125",
    "addr:street":"Carr Botera",
    "iso:country":"ES",
    "sg:address":"Carr Botera, 11",
    "sg:city":"Alguaire",
    "sg:orig_category":"Fabrica De Cer\u00c1micas",
    "sg:phone":"+34 973 75 61 99",
    "sg:postcode":"25125",
    "sg:province":"Lleida",
    "wof:name":"Seve Jove Juan",
    "wof:placetype":"venue"
},
  "geometry": {"coordinates":[0.5832750201,41.7359428406],"type":"Point"}
}