{
  "type": "Feature",
  "properties": {
    "addr:full":"Cust Atalaya, 36 Santander Cantabria 39001",
    "addr:housenumber":"36",
    "addr:postcode":"39001",
    "iso:country":"ES",
    "sg:address":"Cust Atalaya, 36",
    "sg:city":"Santander",
    "sg:orig_category":"Reposter\u00cdas",
    "sg:phone":"+34 942 22 94 80",
    "sg:postcode":"39001",
    "sg:province":"Cantabria",
    "wof:name":"Franco Gonzalez Angeles",
    "wof:placetype":"venue"
},
  "geometry": {"coordinates":[-3.8078091145,43.4655570984],"type":"Point"}
}