{
  "type": "Feature",
  "properties": {
    "addr:full":"Carr Sort, 4 Seu D'urgell Lleida 25700",
    "addr:housenumber":"4",
    "addr:postcode":"25700",
    "addr:street":"Carr Sort",
    "iso:country":"ES",
    "sg:address":"Carr Sort, 4",
    "sg:city":"Seu D'urgell",
    "sg:orig_category":"Artesan\u00cda",
    "sg:phone":"+34 973 36 00 49",
    "sg:postcode":"25700",
    "sg:province":"Lleida",
    "wof:name":"Soler Pallas Montserrat",
    "wof:placetype":"venue"
},
  "geometry": {"coordinates":[0.6281549931,41.6376152039],"type":"Point"}
}