{
  "type": "Feature",
  "properties": {
    "addr:full":"Calle de Santo Domingo, 104 Sanlucar De Barrameda C\u00e1diz 11540",
    "addr:housenumber":"104",
    "addr:postcode":"11540",
    "addr:street":"Calle De Santo Domingo;Ca\u0301Diz",
    "iso:country":"ES",
    "sg:address":"Calle de Santo Domingo, 104",
    "sg:city":"Sanlucar De Barrameda",
    "sg:orig_category":"Bisuter\u00cda, Joyer\u00cda, Relojer\u00cda (al Por Menor)",
    "sg:phone":"+34 956 36 67 73",
    "sg:postcode":"11540",
    "sg:province":"C\u00e1diz",
    "wof:name":"Perez Morales Juan",
    "wof:placetype":"venue"
},
  "geometry": {"coordinates":[-6.3489108086,36.7813034058],"type":"Point"}
}