{
  "type": "Feature",
  "properties": {
    "iso:country":"ES",
    "sg:address":"Carrer de Sant Francesc De Paula, 25",
    "sg:city":"Mataro",
    "sg:orig_category":"Arquitectos",
    "sg:phone":"+34 937 90 63 79",
    "sg:postcode":"08301",
    "sg:province":"Barcelona",
    "wof:name":"Estudi Tecnic Montero S.l.",
    "wof:placetype":"venue"
},
  "geometry": {"coordinates":[2.4475929737,41.5376625061],"type":"Point"}
}