{
  "type": "Feature",
  "properties": {
    "addr:full":"Calle de Carmen Conde, 2 Fortuna Murcia 30620",
    "addr:housenumber":"2",
    "addr:postcode":"30620",
    "addr:street":"Calle De Carmen Conde",
    "iso:country":"ES",
    "sg:address":"Calle de Carmen Conde, 2",
    "sg:city":"Fortuna",
    "sg:orig_category":"Electrodom\u00c9sticos (al Por Menor)",
    "sg:phone":"+34 968 68 53 60",
    "sg:postcode":"30620",
    "sg:province":"Murcia",
    "wof:name":"Electro Mobe S.l.",
    "wof:placetype":"venue"
},
  "geometry": {"coordinates":[-1.1252481937,38.1790237427],"type":"Point"}
}