{
  "type": "Feature",
  "properties": {
    "addr:full":"Carrer de Mallorca, 555 Barcelona Barcelona 08026",
    "addr:housenumber":"555",
    "addr:postcode":"08026",
    "addr:street":"Carrer De Mallorca",
    "iso:country":"ES",
    "sg:address":"Carrer de Mallorca, 555",
    "sg:city":"Barcelona",
    "sg:orig_category":"Aparcamientos (infraestructuras, Accesorios)",
    "sg:phone":"+34 934 55 89 82",
    "sg:postcode":"08026",
    "sg:province":"Barcelona",
    "wof:name":"Grat S.a.",
    "wof:placetype":"venue"
},
  "geometry": {"coordinates":[2.183932066,41.4100799561],"type":"Point"}
}