{
  "type": "Feature",
  "properties": {
    "addr:full":"Valtocado, 61 Mijas M\u00e1laga 29650",
    "addr:housenumber":"61",
    "addr:postcode":"29650",
    "addr:street":"Valtocado",
    "iso:country":"ES",
    "sg:address":"Valtocado, 61",
    "sg:city":"Mijas",
    "sg:orig_category":"Promotores Constructores",
    "sg:phone":"+34 952 48 56 38",
    "sg:postcode":"29650",
    "sg:province":"M\u00e1laga",
    "wof:name":"Bauert  Isabele",
    "wof:placetype":"venue"
},
  "geometry": {"coordinates":[-4.6364178658,36.5977363586],"type":"Point"}
}