{
  "type": "Feature",
  "properties": {
    "addr:full":"Ctra Huercal Overa, 1 Pulpi Almer\u00eda 04640",
    "addr:housenumber":"1",
    "addr:postcode":"04640",
    "addr:street":"Ctra Huercal Overa;Almeri\u0301A",
    "iso:country":"ES",
    "sg:address":"Ctra Huercal Overa, 1",
    "sg:city":"Pulpi",
    "sg:orig_category":"Sociedades, Compa\u00d1\u00cdas Aseguradoras",
    "sg:phone":"+34 950 46 46 98",
    "sg:postcode":"04640",
    "sg:province":"Almer\u00eda",
    "wof:name":"Andamur S.l.u.",
    "wof:placetype":"venue"
},
  "geometry": {"coordinates":[-1.7453733683,37.4054756165],"type":"Point"}
}