{
  "type": "Feature",
  "properties": {
    "iso:country":"ES",
    "sg:address":"Calle de Sanclemente, 13",
    "sg:city":"Zaragoza",
    "sg:orig_category":"Marroquiner\u00cda (confecci\u00d3n)",
    "sg:phone":"+34 976 23 44 85",
    "sg:postcode":"50001",
    "sg:province":"Zaragoza",
    "sg:website":"www.acosta.es",
    "wof:name":"Acosta Zaragoza S.l.",
    "wof:placetype":"venue"
},
  "geometry": {"coordinates":[-0.8815680742,41.6496582031],"type":"Point"}
}