{
  "type": "Feature",
  "properties": {
    "addr:full":"Avgd Diputacio Provincial (de La), 5 Olleria Valencia 46850",
    "addr:housenumber":"5",
    "addr:postcode":"46850",
    "addr:street":"Olleria",
    "iso:country":"ES",
    "sg:address":"Avgd Diputacio Provincial (de La), 5",
    "sg:city":"Olleria",
    "sg:orig_category":"Asesor\u00cda De Formaci\u00d3n Y Gesti\u00d3n De Personal",
    "sg:phone":"+34 962 20 25 47",
    "sg:postcode":"46850",
    "sg:province":"Valencia",
    "wof:name":"Vidal Mediadores De Seguros S.l.",
    "wof:placetype":"venue"
},
  "geometry": {"coordinates":[-0.5478360057,38.9096603394],"type":"Point"}
}