{
  "type": "Feature",
  "properties": {
    "iso:country":"ES",
    "sg:address":"Bo. S. Jose, 186",
    "sg:city":"Callosa Segura",
    "sg:orig_category":"Contenedores Para Dep\u00d3sito De Sustancias Peligrosas (fabricaci\u00d3n, Al Por Mayor)",
    "sg:phone":"+34 965 31 18 12",
    "sg:postcode":"03360",
    "sg:province":"Alicante",
    "wof:name":"Cerrajeria Rimar S.l.",
    "wof:placetype":"venue"
},
  "geometry": {"coordinates":[-0.8776689768,38.1256752014],"type":"Point"}
}