{
  "type": "Feature",
  "properties": {
    "iso:country":"ES",
    "sg:address":"Avda Zaragoza, 3",
    "sg:city":"Tudela",
    "sg:orig_category":"Ropa Para Ni\u00d1os (al Por Menor)",
    "sg:phone":"+34 948 82 61 50",
    "sg:postcode":"31500",
    "sg:province":"Navarra",
    "wof:name":"Orradre Belloso Yolanda",
    "wof:placetype":"venue"
},
  "geometry": {"coordinates":[-1.6028950214,42.0620727539],"type":"Point"}
}