{
  "type": "Feature",
  "properties": {
    "iso:country":"ES",
    "sg:address":"Calle de Fernandez Navarro, 21",
    "sg:city":"Santa Cruz De Tenerife",
    "sg:orig_category":"Peluquer\u00cdas, Peluquer\u00cda Mixta",
    "sg:phone":"+34 922 22 90 17",
    "sg:postcode":"38003",
    "sg:province":"Santa Cruz De Tenerife",
    "wof:name":"Anceladejo S.l.",
    "wof:placetype":"venue"
},
  "geometry": {"coordinates":[-16.2538661957,28.4615745544],"type":"Point"}
}