{
  "type": "Feature",
  "properties": {
    "addr:full":"Miguel Servet (p I Ca\u00f1amo), 19 San Jose Rinconada Sevilla 41300",
    "addr:housenumber":"19",
    "addr:postcode":"41300",
    "addr:street":"Miguel Servet P;Can\u0303Amo",
    "iso:country":"ES",
    "sg:address":"Miguel Servet (p I Ca\u00f1amo), 19",
    "sg:city":"San Jose Rinconada",
    "sg:orig_category":"Empresas De Carpinter\u00cda De Madera",
    "sg:phone":"+34 954 79 03 01",
    "sg:postcode":"41300",
    "sg:province":"Sevilla",
    "wof:name":"Carpinteria Y Ebanisteria Dicarpe S.l.l.",
    "wof:placetype":"venue"
},
  "geometry": {"coordinates":[-5.9317932129,37.4900436401],"type":"Point"}
}