{
  "type": "Feature",
  "properties": {
    "iso:country":"ES",
    "sg:address":"Benasau, 6",
    "sg:city":"Elche",
    "sg:orig_category":"Entrega Y Recogida (servicios)",
    "sg:phone":"+34 965 44 27 42",
    "sg:postcode":"03005",
    "sg:province":"Alicante",
    "wof:name":"Almira Romero Jose Maria",
    "wof:placetype":"venue"
},
  "geometry": {"coordinates":[-0.721487999,38.279838562],"type":"Point"}
}