{
  "type": "Feature",
  "properties": {
    "addr:full":"Carr Eivissa, D', 15 Campos Islas Baleares 07630",
    "addr:housenumber":"15",
    "addr:postcode":"07630",
    "addr:street":"Carr Eivissa D '",
    "iso:country":"ES",
    "sg:address":"Carr Eivissa, D', 15",
    "sg:city":"Campos",
    "sg:orig_category":"Molduras, Junquillos, Listones Y Molduras Perforadas",
    "sg:phone":"+34 971 65 29 63",
    "sg:postcode":"07630",
    "sg:province":"Islas Baleares",
    "wof:name":"Ga%erins Construccions S.l.",
    "wof:placetype":"venue"
},
  "geometry": {"coordinates":[3.0146679878,39.4296722412],"type":"Point"}
}