{
  "type": "Feature",
  "properties": {
    "iso:country":"ES",
    "sg:address":"Calle de San Jose, 8",
    "sg:city":"Cadiz",
    "sg:orig_category":"Doctores En Medicina",
    "sg:phone":"+34 956 22 25 80",
    "sg:postcode":"11001",
    "sg:province":"C\u00e1diz",
    "wof:name":"Ureba Ramirez Antonio",
    "wof:placetype":"venue"
},
  "geometry": {"coordinates":[-6.2980132103,36.5344429016],"type":"Point"}
}