{
  "type": "Feature",
  "properties": {
    "addr:full":"Avda Constitucion, 200 Torrejon Ardoz Madrid 28850",
    "addr:housenumber":"200",
    "addr:postcode":"28850",
    "addr:street":"Avda Constitucion",
    "iso:country":"ES",
    "sg:address":"Avda Constitucion, 200",
    "sg:city":"Torrejon Ardoz",
    "sg:orig_category":"Agentes, Concesionarios Y Sucursales De Veh\u00cdculos",
    "sg:phone":"+34 916 77 49 54",
    "sg:postcode":"28850",
    "sg:province":"Madrid",
    "wof:name":"Quiles Servicios Empresariales",
    "wof:placetype":"venue"
},
  "geometry": {"coordinates":[-3.4479598999,40.4627838135],"type":"Point"}
}