{
  "type": "Feature",
  "properties": {
    "addr:full":"Avda Antonio Hurtado, 9 Caceres C\u00e1ceres 10002",
    "addr:housenumber":"9",
    "addr:postcode":"10002",
    "addr:street":"Avda Antonio Hurtado;Ca\u0301Ceres",
    "iso:country":"ES",
    "sg:address":"Avda Antonio Hurtado, 9",
    "sg:city":"Caceres",
    "sg:orig_category":"Asesor\u00cdas Y Estudios Financieros",
    "sg:phone":"+34 927 22 40 38",
    "sg:postcode":"10002",
    "sg:province":"C\u00e1ceres",
    "wof:name":"Viniegra Fernandez Jose Fernando",
    "wof:placetype":"venue"
},
  "geometry": {"coordinates":[-6.3777618408,39.4673500061],"type":"Point"}
}