{
  "type": "Feature",
  "properties": {
    "addr:full":"Avda Mar, Del, 35 Castellon Castell\u00f3n 12003",
    "addr:housenumber":"35",
    "addr:postcode":"12003",
    "addr:street":"Avda Mar Del",
    "iso:country":"ES",
    "sg:address":"Avda Mar, Del, 35",
    "sg:city":"Castellon",
    "sg:orig_category":"Arboricultura Y Producci\u00d3n De Frutas",
    "sg:phone":"+34 964 22 05 18",
    "sg:postcode":"12003",
    "sg:province":"Castell\u00f3n",
    "wof:name":"Serra Nadal Francisco",
    "wof:placetype":"venue"
},
  "geometry": {"coordinates":[-0.0077,39.9838409424],"type":"Point"}
}