{
  "type": "Feature",
  "properties": {
    "iso:country":"ES",
    "sg:address":"Calle de Antonio Lopez, 191",
    "sg:city":"Madrid",
    "sg:orig_category":"Inmobiliaria (agencias)",
    "sg:phone":"+34 914 76 35 01",
    "sg:postcode":"28026",
    "sg:province":"Madrid",
    "wof:name":"Agofer S.l.",
    "wof:placetype":"venue"
},
  "geometry": {"coordinates":[-3.6995229721,40.3880805969],"type":"Point"}
}