{
  "type": "Feature",
  "properties": {
    "iso:country":"ES",
    "sg:address":"Avda San Miguel, Km. 0021,3",
    "sg:city":"Iscar",
    "sg:orig_category":"Ebanister\u00cda",
    "sg:phone":"+34 983 61 22 37",
    "sg:postcode":"47420",
    "sg:province":"Valladolid",
    "wof:name":"Ebanisteria Y Decoracion Miguel S.l.",
    "wof:placetype":"venue"
},
  "geometry": {"coordinates":[-4.5376338959,41.3601837158],"type":"Point"}
}