{
  "type": "Feature",
  "properties": {
    "addr:full":"Praz Espa\u00d1a, 9 Vilagarcia Pontevedra 36600",
    "addr:housenumber":"9",
    "addr:postcode":"36600",
    "addr:street":"Praz Espan\u0303A",
    "iso:country":"ES",
    "sg:address":"Praz Espa\u00d1a, 9",
    "sg:city":"Vilagarcia",
    "sg:orig_category":"Agencias De Viajes",
    "sg:phone":"+34 986 50 26 94",
    "sg:postcode":"36600",
    "sg:province":"Pontevedra",
    "sg:website":"www.viajeseroski.es",
    "wof:name":"Viajes Eroski S.a.",
    "wof:placetype":"venue"
},
  "geometry": {"coordinates":[-8.7652978897,42.5917396545],"type":"Point"}
}