{
  "type": "Feature",
  "properties": {
    "addr:full":"Av. Zaragoza, 21 Iru\u00f1a Navarra 31003",
    "addr:housenumber":"21",
    "addr:postcode":"31003",
    "addr:street":"Av. Zaragoza",
    "iso:country":"ES",
    "sg:address":"Av. Zaragoza, 21",
    "sg:city":"Iru\u00f1a",
    "sg:orig_category":"Cooperativas Agr\u00cdcolas",
    "sg:phone":"+34 948 24 39 12",
    "sg:postcode":"31003",
    "sg:province":"Navarra",
    "wof:name":"Servicios Empresariales Agro Industruales S. A.",
    "wof:placetype":"venue"
},
  "geometry": {"coordinates":[-1.6435910463,42.8098373413],"type":"Point"}
}