{
  "type": "Feature",
  "properties": {
    "iso:country":"ES",
    "sg:address":"Calle de Manila, 30",
    "sg:city":"Castellon",
    "sg:orig_category":"Cr\u00cda De Animales",
    "sg:phone":"+34 964 21 12 96",
    "sg:postcode":"12004",
    "sg:province":"Castell\u00f3n",
    "wof:name":"Royo Iba\u00f1ez Ramon",
    "wof:placetype":"venue"
},
  "geometry": {"coordinates":[-0.041979,39.9984207153],"type":"Point"}
}