{
  "type": "Feature",
  "properties": {
    "iso:country":"ES",
    "sg:address":"Carrer de Ferreries, 11",
    "sg:city":"Urbanitzacio Can Valls-torre Negrell",
    "sg:orig_category":"Contenedores (mercanc\u00cdas)",
    "sg:phone":"+34 938 65 50 98",
    "sg:postcode":"08140",
    "sg:province":"Barcelona",
    "sg:website":"www.cytrab.com",
    "wof:name":"Gruas Y Transportes Rab S.l.",
    "wof:placetype":"venue"
},
  "geometry": {"coordinates":[2.1856610775,41.6169052124],"type":"Point"}
}