{
  "type": "Feature",
  "properties": {
    "addr:full":"Villacondide, S/n Villacondide Asturias 33796",
    "addr:postcode":"33796",
    "addr:street":"Villacondide S / N Villacondide Asturias",
    "iso:country":"ES",
    "sg:address":"Villacondide, S/n",
    "sg:city":"Villacondide",
    "sg:orig_category":"Iglesia Cat\u00d3lica",
    "sg:phone":"+34 985 47 32 38",
    "sg:postcode":"33796",
    "sg:province":"Asturias",
    "wof:name":"Diocesis De Oviedo",
    "wof:placetype":"venue"
},
  "geometry": {"coordinates":[-6.734664917,43.5106811523],"type":"Point"}
}