{
  "type": "Feature",
  "properties": {
    "iso:country":"ES",
    "sg:address":"Pol Industrial, 1",
    "sg:city":"Aguilas",
    "sg:orig_category":"Pescader\u00cdas (al Por Menor)",
    "sg:phone":"+34 968 41 38 58",
    "sg:postcode":"30880",
    "sg:province":"Murcia",
    "wof:name":"Pescados El Chitin S.l.",
    "wof:placetype":"venue"
},
  "geometry": {"coordinates":[-1.5839740038,37.4077987671],"type":"Point"}
}