{
  "type": "Feature",
  "properties": {
    "addr:full":"San Isidro, 1 El Espinar Segovia 40400",
    "addr:postcode":"40400",
    "addr:street":"San Isidro",
    "iso:country":"ES",
    "sg:address":"San Isidro, 1",
    "sg:city":"El Espinar",
    "sg:orig_category":"Pescader\u00cdas (al Por Menor)",
    "sg:phone":"+34 921 18 10 21",
    "sg:postcode":"40400",
    "sg:province":"Segovia",
    "wof:name":"Del Monte Martin Jose Manuel",
    "wof:placetype":"venue"
},
  "geometry": {"coordinates":[-4.2465538979,40.7174797058],"type":"Point"}
}