{
  "type": "Feature",
  "properties": {
    "addr:full":"Avda Padre Isla, 55 Le\u00f3n Le\u00f3n 24002",
    "addr:housenumber":"55",
    "addr:postcode":"24002",
    "addr:street":"Avda Padre Isla;Leo\u0301N",
    "iso:country":"ES",
    "sg:address":"Avda Padre Isla, 55",
    "sg:city":"Le\u00f3n",
    "sg:orig_category":"Molduras, Junquillos, Listones Y Molduras Perforadas",
    "sg:phone":"+34 987 23 55 43",
    "sg:postcode":"24002",
    "sg:province":"Le\u00f3n",
    "wof:name":"Moro Armenteros Teodoro",
    "wof:placetype":"venue"
},
  "geometry": {"coordinates":[-5.5764708519,42.6031799316],"type":"Point"}
}