{
  "type": "Feature",
  "properties": {
    "iso:country":"ES",
    "sg:address":"Calle de Real De Santa Fe, 26",
    "sg:city":"Santa Fe",
    "sg:orig_category":"Electrodom\u00c9sticos (al Por Menor)",
    "sg:phone":"+34 958 44 26 15",
    "sg:postcode":"18320",
    "sg:province":"Granada",
    "wof:name":"Murcia Morales Maria Isabel",
    "wof:placetype":"venue"
},
  "geometry": {"coordinates":[-3.714564085,37.1907157898],"type":"Point"}
}