{
  "type": "Feature",
  "properties": {
    "iso:country":"ES",
    "sg:address":"Avda Tomas Garcia Figueras, 15",
    "sg:city":"Jerez De La Frontera",
    "sg:orig_category":"Quiropr\u00c1cticos",
    "sg:phone":"+34 956 30 99 86",
    "sg:postcode":"11407",
    "sg:province":"C\u00e1diz",
    "wof:name":"Lorente Herrera Mercedes",
    "wof:placetype":"venue"
},
  "geometry": {"coordinates":[-6.1394948959,36.6987228394],"type":"Point"}
}