{
  "type": "Feature",
  "properties": {
    "addr:full":"Avda Iparragirre, 50 Elexalde Vizcaya 48940",
    "addr:housenumber":"50",
    "addr:postcode":"48940",
    "addr:street":"Avda Iparragirre",
    "iso:country":"ES",
    "sg:address":"Avda Iparragirre, 50",
    "sg:city":"Elexalde",
    "sg:orig_category":"Institutos De Belleza",
    "sg:phone":"+34 944 05 33 37",
    "sg:postcode":"48940",
    "sg:province":"Vizcaya",
    "wof:name":"Martin Martin Maria Rosario",
    "wof:placetype":"venue"
},
  "geometry": {"coordinates":[-2.989372015,43.3259162903],"type":"Point"}
}