{
  "type": "Feature",
  "properties": {
    "addr:full":"Urb Jardin Del Mar Xiii, 118 El Chaparral Alicante 03180",
    "addr:housenumber":"118",
    "addr:postcode":"03180",
    "addr:street":"Urb Jardin Del Mar Xiii;El Chaparral",
    "iso:country":"ES",
    "sg:address":"Urb Jardin Del Mar Xiii, 118",
    "sg:city":"El Chaparral",
    "sg:orig_category":"Agencias Y Agentes Comerciales, Representantes",
    "sg:phone":"+34 966 78 45 32",
    "sg:postcode":"03180",
    "sg:province":"Alicante",
    "wof:name":"Iaksess S.l.",
    "wof:placetype":"venue"
},
  "geometry": {"coordinates":[-0.6536790133,38.0173606873],"type":"Point"}
}