{
  "type": "Feature",
  "properties": {
    "iso:country":"ES",
    "sg:address":"Calle de Suelta El Prado, S/n",
    "sg:city":"San Rafael",
    "sg:orig_category":"Transporte En General",
    "sg:phone":"+34 921 17 10 99",
    "sg:postcode":"40410",
    "sg:province":"Segovia",
    "wof:name":"Garcia Rubio Jesus",
    "wof:placetype":"venue"
},
  "geometry": {"coordinates":[-4.1855669022,40.7127342224],"type":"Point"}
}