{
  "type": "Feature",
  "properties": {
    "addr:full":"Rbla Egara, 203 Terrassa Barcelona 08224",
    "addr:housenumber":"203",
    "addr:postcode":"08224",
    "addr:street":"Rbla Egara",
    "iso:country":"ES",
    "sg:address":"Rbla Egara, 203",
    "sg:city":"Terrassa",
    "sg:orig_category":"Muebles, Minoristas",
    "sg:phone":"+34 937 88 03 87",
    "sg:postcode":"08224",
    "sg:province":"Barcelona",
    "wof:name":"Model Cuina S.l.",
    "wof:placetype":"venue"
},
  "geometry": {"coordinates":[2.0076019764,41.5628967285],"type":"Point"}
}