{
  "type": "Feature",
  "properties": {
    "addr:full":"Plaz San Pedro, 5 Larva Ja\u00e9n 23591",
    "addr:housenumber":"5",
    "addr:postcode":"23591",
    "addr:street":"Plaz San Pedro",
    "iso:country":"ES",
    "sg:address":"Plaz San Pedro, 5",
    "sg:city":"Larva",
    "sg:orig_category":"Iglesia Cat\u00d3lica",
    "sg:phone":"+34 953 78 15 04",
    "sg:postcode":"23591",
    "sg:province":"Ja\u00e9n",
    "wof:name":"Parroquia De San Pedro",
    "wof:placetype":"venue"
},
  "geometry": {"coordinates":[-3.2016758919,37.7589454651],"type":"Point"}
}