{
  "type": "Feature",
  "properties": {
    "iso:country":"ES",
    "sg:address":"Prolongacion De Millan Astrain, 2",
    "sg:city":"Santisteban Puerto",
    "sg:orig_category":"Ense\u00d1anza Secundaria: Colegios Y Escuelas Privadas",
    "sg:phone":"+34 953 40 20 64",
    "sg:postcode":"23250",
    "sg:province":"Ja\u00e9n",
    "wof:name":"Junta De Andalucia",
    "wof:placetype":"venue"
},
  "geometry": {"coordinates":[-3.2013289928,38.250743866],"type":"Point"}
}