{
  "type": "Feature",
  "properties": {
    "iso:country":"ES",
    "sg:address":"Calle de General Tamayo, 11",
    "sg:city":"Almeria",
    "sg:orig_category":"Sociedades, Compa\u00d1\u00cdas Aseguradoras",
    "sg:phone":"+34 950 62 07 00",
    "sg:postcode":"04004",
    "sg:province":"Almer\u00eda",
    "wof:name":"Cesce Compa\u00f1ia Espa\u00f1ola De Seguros De Credito A La Exportacion S.a.",
    "wof:placetype":"venue"
},
  "geometry": {"coordinates":[-2.4628140926,36.8368263245],"type":"Point"}
}