{
  "type": "Feature",
  "properties": {
    "iso:country":"ES",
    "sg:address":"Calle de Arroyo De La Media Legua, 1",
    "sg:city":"Madrid",
    "sg:orig_category":"Molduras, Junquillos, Listones Y Molduras Perforadas",
    "sg:phone":"+34 914 39 96 60",
    "sg:postcode":"28030",
    "sg:province":"Madrid",
    "wof:name":"Li  Longlong",
    "wof:placetype":"venue"
},
  "geometry": {"coordinates":[-3.6579887867,40.4077072144],"type":"Point"}
}