{
  "type": "Feature",
  "properties": {
    "iso:country":"ES",
    "sg:address":"Carrer de Iba\u00d1ez De Aldecoa, 50",
    "sg:city":"Terrassa",
    "sg:orig_category":"Tapicer\u00cdas",
    "sg:phone":"+34 937 84 26 20",
    "sg:postcode":"08227",
    "sg:province":"Barcelona",
    "wof:name":"Martinez Ramirez Adulia",
    "wof:placetype":"venue"
},
  "geometry": {"coordinates":[2.036315918,41.5773200989],"type":"Point"}
}