{
  "type": "Feature",
  "properties": {
    "addr:full":"Avda Hispanidade, 61 Vigo Pontevedra 36203",
    "addr:housenumber":"61",
    "addr:postcode":"36203",
    "addr:street":"Avda Hispanidade",
    "iso:country":"ES",
    "sg:address":"Avda Hispanidade, 61",
    "sg:city":"Vigo",
    "sg:orig_category":"Arquitectos",
    "sg:phone":"+34 986 42 14 36",
    "sg:postcode":"36203",
    "sg:province":"Pontevedra",
    "wof:name":"Prado Costas Jose Ramon",
    "wof:placetype":"venue"
},
  "geometry": {"coordinates":[-8.7290563583,42.2282676697],"type":"Point"}
}