{
  "type": "Feature",
  "properties": {
    "iso:country":"ES",
    "sg:address":"Plaz Alonso De Mendoza, 13",
    "sg:city":"Garrovilla",
    "sg:orig_category":"Bancos",
    "sg:phone":"+34 924 33 51 36",
    "sg:postcode":"06870",
    "sg:province":"Badajoz",
    "wof:name":"Banco Caixa Geral S.a.",
    "wof:placetype":"venue"
},
  "geometry": {"coordinates":[-6.4824938774,38.9198150635],"type":"Point"}
}