{
  "type": "Feature",
  "properties": {
    "iso:country":"ES",
    "sg:address":"Pol. Industrial, S/n",
    "sg:city":"Yuncos",
    "sg:orig_category":"Fabricaci\u00d3n De Taburetes, Sillas Y Sillones",
    "sg:phone":"+34 925 55 39 70",
    "sg:postcode":"45210",
    "sg:province":"Toledo",
    "wof:name":"Gosantos C.b.",
    "wof:placetype":"venue"
},
  "geometry": {"coordinates":[-3.8721139431,40.0867118835],"type":"Point"}
}