{
  "type": "Feature",
  "properties": {
    "addr:full":"Calle de Andres Segovia, 8 Aguilas Murcia 30880",
    "addr:housenumber":"8",
    "addr:postcode":"30880",
    "addr:street":"Calle De Andres Segovia",
    "iso:country":"ES",
    "sg:address":"Calle de Andres Segovia, 8",
    "sg:city":"Aguilas",
    "sg:orig_category":"Electricidad: Instaladores",
    "sg:phone":"+34 968 41 25 67",
    "sg:postcode":"30880",
    "sg:province":"Murcia",
    "wof:name":"Lopez Morata Antonio",
    "wof:placetype":"venue"
},
  "geometry": {"coordinates":[-1.5647823811,37.4096717834],"type":"Point"}
}