{
  "type": "Feature",
  "properties": {
    "iso:country":"ES",
    "sg:address":"Carr Calderon De La Barca, 53",
    "sg:city":"Gandia",
    "sg:orig_category":"Sociedades, Compa\u00d1\u00cdas Aseguradoras",
    "sg:phone":"+34 962 86 27 62",
    "sg:postcode":"46700",
    "sg:province":"Valencia",
    "wof:name":"Correduria De Seguros Maxim Gandia S.l.",
    "wof:placetype":"venue"
},
  "geometry": {"coordinates":[-0.1913339943,38.960735321],"type":"Point"}
}