{
  "type": "Feature",
  "properties": {
    "addr:full":"Rbla Anselm Clave, 38 Cornella Llobregat Barcelona 08940",
    "addr:housenumber":"38",
    "addr:postcode":"08940",
    "addr:street":"Rbla Anselm Clave",
    "iso:country":"ES",
    "sg:address":"Rbla Anselm Clave, 38",
    "sg:city":"Cornella Llobregat",
    "sg:orig_category":"Cajas De Ahorro",
    "sg:phone":"+34 933 77 10 12",
    "sg:postcode":"08940",
    "sg:province":"Barcelona",
    "sg:website":"www.caixamanresa.es",
    "wof:name":"Caixa D'estalvis De Manresa",
    "wof:placetype":"venue"
},
  "geometry": {"coordinates":[2.073071003,41.3537750244],"type":"Point"}
}