{
  "type": "Feature",
  "properties": {
    "iso:country":"ES",
    "sg:address":"Calle de Buen Pastor, 44",
    "sg:city":"Casa Pastores",
    "sg:orig_category":"Inmobiliaria (agencias)",
    "sg:phone":"+34 928 75 37 14",
    "sg:postcode":"35110",
    "sg:province":"Las Palmas",
    "wof:name":"Gestiones Inmobiliarias Nicolletta S.l",
    "wof:placetype":"venue"
},
  "geometry": {"coordinates":[-15.4300060272,28.1248226166],"type":"Point"}
}