{
  "type": "Feature",
  "properties": {
    "addr:full":"Grupo Larraina, 2 Iru\u00f1a Navarra 31011",
    "addr:housenumber":"2",
    "addr:postcode":"31011",
    "addr:street":"Irun\u0303A Navarra",
    "iso:country":"ES",
    "sg:address":"Grupo Larraina, 2",
    "sg:city":"Iru\u00f1a",
    "sg:orig_category":"Asociaciones Y Clubs Deportivos",
    "sg:phone":"+34 948 26 08 09",
    "sg:postcode":"31011",
    "sg:province":"Navarra",
    "wof:name":"Campo Deportes Larraina",
    "wof:placetype":"venue"
},
  "geometry": {"coordinates":[-1.6565289497,42.8185005188],"type":"Point"}
}