{
  "type": "Feature",
  "properties": {
    "addr:full":"Trva Desvio, 26 A\u00e7over De Tajo Toledo 45250",
    "addr:housenumber":"26",
    "addr:postcode":"45250",
    "addr:street":"Trva Desvio",
    "iso:country":"ES",
    "sg:address":"Trva Desvio, 26",
    "sg:city":"A\u00e7over De Tajo",
    "sg:orig_category":"Chapister\u00cda",
    "sg:phone":"+34 925 55 51 90",
    "sg:postcode":"45250",
    "sg:province":"Toledo",
    "wof:name":"Pariente Gonzalez Cipriano",
    "wof:placetype":"venue"
},
  "geometry": {"coordinates":[-3.7649140358,39.9933586121],"type":"Point"}
}