{
  "type": "Feature",
  "properties": {
    "iso:country":"ES",
    "sg:address":"Calle de Vitoria, 165",
    "sg:city":"Burgos",
    "sg:orig_category":"Empresas De Pintura Y Revestimientos",
    "sg:phone":"+34 947 23 78 25",
    "sg:postcode":"09007",
    "sg:province":"Burgos",
    "wof:name":"Puente Pe\u00f1a Jose Antonio",
    "wof:placetype":"venue"
},
  "geometry": {"coordinates":[-3.6712830067,42.3522224426],"type":"Point"}
}