{
  "type": "Feature",
  "properties": {
    "iso:country":"ES",
    "sg:address":"Carr Mendez Nu\u00d1ez, 37",
    "sg:city":"Figueres",
    "sg:orig_category":"Carnicer\u00cdas, Carnicer\u00cdas",
    "sg:phone":"+34 972 50 57 87",
    "sg:postcode":"17600",
    "sg:province":"Girona",
    "wof:name":"Hurtos Planells Juan",
    "wof:placetype":"venue"
},
  "geometry": {"coordinates":[2.9661290646,42.2638587952],"type":"Point"}
}