{
  "type": "Feature",
  "properties": {
    "addr:full":"Calle de Abastos (de), 18 Aranjuez Madrid 28300",
    "addr:postcode":"28300",
    "addr:street":"Calle De",
    "iso:country":"ES",
    "sg:address":"Calle de Abastos (de), 18",
    "sg:city":"Aranjuez",
    "sg:orig_category":"Juegos Y Juguetes (al Por Menor)",
    "sg:phone":"+34 918 91 89 78",
    "sg:postcode":"28300",
    "sg:province":"Madrid",
    "wof:name":"Barba Dorado Rosa Maria",
    "wof:placetype":"venue"
},
  "geometry": {"coordinates":[-3.6061832905,40.0319900513],"type":"Point"}
}