{
  "type": "Feature",
  "properties": {
    "addr:full":"Carrer de Calabria, 17 Barcelona Barcelona 08015",
    "addr:housenumber":"17",
    "addr:postcode":"08015",
    "addr:street":"Carrer De Calabria",
    "iso:country":"ES",
    "sg:address":"Carrer de Calabria, 17",
    "sg:city":"Barcelona",
    "sg:orig_category":"Cajas De Ahorro",
    "sg:phone":"+34 934 25 47 33",
    "sg:postcode":"08015",
    "sg:province":"Barcelona",
    "wof:name":"Caixa D'estalvis I Pensions De Barcelona",
    "wof:placetype":"venue"
},
  "geometry": {"coordinates":[2.1598238945,41.3758926392],"type":"Point"}
}