{
  "type": "Feature",
  "properties": {
    "iso:country":"ES",
    "sg:address":"Calle de San Pedro Y San Felices, 34",
    "sg:city":"Burgos",
    "sg:orig_category":"Ense\u00d1anza Secundaria: Colegios Y Escuelas Privadas",
    "sg:phone":"+34 947 27 86 28",
    "sg:postcode":"09001",
    "sg:province":"Burgos",
    "wof:name":"Ies Diego De Siloe",
    "wof:placetype":"venue"
},
  "geometry": {"coordinates":[-3.7066690922,42.3319091797],"type":"Point"}
}