{
  "type": "Feature",
  "properties": {
    "addr:full":"Av Venecia(resid Sta Ana), 18 Los Dolores Murcia 30310",
    "addr:housenumber":"18",
    "addr:postcode":"30310",
    "addr:street":"Av Venecia;Ana",
    "iso:country":"ES",
    "sg:address":"Av Venecia(resid Sta Ana), 18",
    "sg:city":"Los Dolores",
    "sg:orig_category":"Cajas Para Embalar",
    "sg:phone":"+34 968 33 01 25",
    "sg:postcode":"30310",
    "sg:province":"Murcia",
    "wof:name":"Cajamar",
    "wof:placetype":"venue"
},
  "geometry": {"coordinates":[-1.0082689524,37.6360816956],"type":"Point"}
}