{
  "type": "Feature",
  "properties": {
    "addr:full":"Avda Calvo Sotelo, 23 Beniel Murcia 30130",
    "addr:housenumber":"23",
    "addr:postcode":"30130",
    "addr:street":"Avda Calvo Sotelo",
    "iso:country":"ES",
    "sg:address":"Avda Calvo Sotelo, 23",
    "sg:city":"Beniel",
    "sg:orig_category":"Mec\u00c1nico Del Autom\u00d3vil",
    "sg:phone":"+34 968 60 01 96",
    "sg:postcode":"30130",
    "sg:province":"Murcia",
    "wof:name":"Automocion Hermanos Lidon S.l.",
    "wof:placetype":"venue"
},
  "geometry": {"coordinates":[-1.0058139563,38.0426712036],"type":"Point"}
}