{
  "type": "Feature",
  "properties": {
    "iso:country":"ES",
    "sg:address":"Avda Alfares (de Los), 50",
    "sg:city":"Cuenca",
    "sg:orig_category":"Fotocopias, Reprograf\u00cda",
    "sg:phone":"+34 969 23 56 69",
    "sg:postcode":"16002",
    "sg:province":"Cuenca",
    "wof:name":"Carretero Lozano Agustin Luis",
    "wof:placetype":"venue"
},
  "geometry": {"coordinates":[-2.1469569206,40.0768127441],"type":"Point"}
}