{
  "type": "Feature",
  "properties": {
    "addr:full":"Carrer de Gran De Sant Andreu, 356 Barcelona Barcelona 08030",
    "addr:housenumber":"356",
    "addr:postcode":"08030",
    "addr:street":"Carrer De Gran De Sant Andreu",
    "iso:country":"ES",
    "sg:address":"Carrer de Gran De Sant Andreu, 356",
    "sg:city":"Barcelona",
    "sg:orig_category":"Agentes, Concesionarios Y Sucursales De Veh\u00cdculos",
    "sg:phone":"+34 933 45 65 00",
    "sg:postcode":"08030",
    "sg:province":"Barcelona",
    "wof:name":"Zics S.a.",
    "wof:placetype":"venue"
},
  "geometry": {"coordinates":[2.1889259815,41.4382400513],"type":"Point"}
}