{
  "type": "Feature",
  "properties": {
    "iso:country":"ES",
    "sg:address":"Avda Alfonso X El Sabio, 4",
    "sg:city":"Alguazas",
    "sg:orig_category":"Maquinaria Para Industrias Diversas",
    "sg:phone":"+34 968 62 25 14",
    "sg:postcode":"30560",
    "sg:province":"Murcia",
    "wof:name":"Jose Guillen E Hijos S.l.",
    "wof:placetype":"venue"
},
  "geometry": {"coordinates":[-1.2457380295,38.0554237366],"type":"Point"}
}