{
  "type": "Feature",
  "properties": {
    "addr:full":"Alam Mazarredo, 8 Bilbao Vizcaya 48001",
    "addr:housenumber":"8",
    "addr:postcode":"48001",
    "addr:street":"Mazarredo",
    "iso:country":"ES",
    "sg:address":"Alam Mazarredo, 8",
    "sg:city":"Bilbao",
    "sg:orig_category":"Caf\u00c9s, Bares, Cervecer\u00cdas",
    "sg:phone":"+34 944 24 56 53",
    "sg:postcode":"48001",
    "sg:province":"Vizcaya",
    "wof:name":"Fernandez Pereda Jose Fernando",
    "wof:placetype":"venue"
},
  "geometry": {"coordinates":[-2.9287540913,43.2638626099],"type":"Point"}
}