{
  "type": "Feature",
  "properties": {
    "addr:full":"Enchidero, 5 Motril Granada 18600",
    "addr:housenumber":"5",
    "addr:postcode":"18600",
    "addr:street":"Enchidero",
    "iso:country":"ES",
    "sg:address":"Enchidero, 5",
    "sg:city":"Motril",
    "sg:orig_category":"Sociedades, Compa\u00d1\u00cdas Aseguradoras",
    "sg:phone":"+34 958 60 75 21",
    "sg:postcode":"18600",
    "sg:province":"Granada",
    "wof:name":"Nortehispana De Seguros Y Reaseguros S.a.",
    "wof:placetype":"venue"
},
  "geometry": {"coordinates":[-3.5166819096,36.7446365356],"type":"Point"}
}