{
  "type": "Feature",
  "properties": {
    "addr:full":"Calle de Ramon Y Cajal, 40 Santander Cantabria 39005",
    "addr:housenumber":"40",
    "addr:postcode":"39005",
    "addr:street":"Calle De Ramon Y Cajal",
    "iso:country":"ES",
    "sg:address":"Calle de Ramon Y Cajal, 40",
    "sg:city":"Santander",
    "sg:orig_category":"Doctores En Medicina",
    "sg:phone":"+34 942 27 47 00",
    "sg:postcode":"39005",
    "sg:province":"Cantabria",
    "wof:name":"Rodriguez Gallo Jesus Pablo",
    "wof:placetype":"venue"
},
  "geometry": {"coordinates":[-3.7846140862,43.468296051],"type":"Point"}
}