{
  "type": "Feature",
  "properties": {
    "addr:full":"Calle de Carteros (los), 9 San Jose Rinconada Sevilla 41300",
    "addr:housenumber":"9",
    "addr:postcode":"41300",
    "addr:street":"Calle De Carteros Los",
    "iso:country":"ES",
    "sg:address":"Calle de Carteros (los), 9",
    "sg:city":"San Jose Rinconada",
    "sg:orig_category":"Alimentaci\u00d3n General (al Por Menor)",
    "sg:phone":"+34 954 79 00 46",
    "sg:postcode":"41300",
    "sg:province":"Sevilla",
    "wof:name":"Pepe Del Aceite E Hijos S.l.",
    "wof:placetype":"venue"
},
  "geometry": {"coordinates":[-5.9471783638,37.479888916],"type":"Point"}
}