{
  "type": "Feature",
  "properties": {
    "addr:full":"Avda Andes (de Los), 4 Fuenlabrada Madrid 28945",
    "addr:housenumber":"4",
    "addr:postcode":"28945",
    "addr:street":"Avda Andes De Los",
    "iso:country":"ES",
    "sg:address":"Avda Andes (de Los), 4",
    "sg:city":"Fuenlabrada",
    "sg:orig_category":"Empresas De Carpinter\u00cda De Madera",
    "sg:phone":"+34 914 92 00 12",
    "sg:postcode":"28945",
    "sg:province":"Madrid",
    "wof:name":"Baudil Archilla Rafael",
    "wof:placetype":"venue"
},
  "geometry": {"coordinates":[-3.7890770435,40.2952766418],"type":"Point"}
}