{
  "type": "Feature",
  "properties": {
    "iso:country":"ES",
    "sg:address":"Calle de Juan Perez Arriete, 13",
    "sg:city":"Algeciras",
    "sg:orig_category":"M\u00c1rmoles, Granitos Y Piedras Naturales",
    "sg:phone":"+34 956 66 45 02",
    "sg:postcode":"11204",
    "sg:province":"C\u00e1diz",
    "wof:name":"Machin Almagro Sebastian",
    "wof:placetype":"venue"
},
  "geometry": {"coordinates":[-5.4471287727,36.1409416199],"type":"Point"}
}