{
  "type": "Feature",
  "properties": {
    "iso:country":"ES",
    "sg:address":"Avda Constitucion, 24",
    "sg:city":"Torrejon Ardoz",
    "sg:classifiers":[
        {
            "category":"Autos & Motor Vehicles",
            "subcategory":"Automobile Sales",
            "type":"Retail Goods"
        }
    ],
    "sg:phone":"+34 916 75 08 49",
    "sg:postcode":"28850",
    "sg:province":"Madrid",
    "wof:name":"Auto-escuela Torrelaguna S.l.",
    "wof:placetype":"venue"
},
  "geometry": {"coordinates":[-3.4829056263,40.4552955627],"type":"Point"}
}