{
  "type": "Feature",
  "properties": {
    "iso:country":"ES",
    "sg:address":"Calle de Compostela, 4",
    "sg:city":"Tui",
    "sg:orig_category":"Caf\u00c9s, Bares, Cervecer\u00cdas",
    "sg:phone":"+34 986 60 19 92",
    "sg:postcode":"36700",
    "sg:province":"Pontevedra",
    "wof:name":"Dieguez Estevez Balbina",
    "wof:placetype":"venue"
},
  "geometry": {"coordinates":[-8.6463527679,42.0505180359],"type":"Point"}
}