{
  "type": "Feature",
  "properties": {
    "addr:full":"Calle de Santo Domingo, 15 Marchena Sevilla 41620",
    "addr:housenumber":"15",
    "addr:postcode":"41620",
    "addr:street":"Calle De Santo Domingo",
    "iso:country":"ES",
    "sg:address":"Calle de Santo Domingo, 15",
    "sg:city":"Marchena",
    "sg:orig_category":"Electrodom\u00c9sticos (al Por Menor)",
    "sg:phone":"+34 954 84 38 59",
    "sg:postcode":"41620",
    "sg:province":"Sevilla",
    "wof:name":"Henares Bautista Manuel",
    "wof:placetype":"venue"
},
  "geometry": {"coordinates":[-5.4165201187,37.3284873962],"type":"Point"}
}