{
  "type": "Feature",
  "properties": {
    "addr:full":"Carrer de Josep Anselm Clave, 5 Esplugues Llobregat Barcelona 08950",
    "addr:housenumber":"5",
    "addr:postcode":"08950",
    "addr:street":"Carrer De Josep Anselm Clave",
    "iso:country":"ES",
    "sg:address":"Carrer de Josep Anselm Clave, 5",
    "sg:city":"Esplugues Llobregat",
    "sg:orig_category":"Fabricaci\u00d3n, Instalaci\u00d3n De Escaleras",
    "sg:phone":"+34 933 71 94 58",
    "sg:postcode":"08950",
    "sg:province":"Barcelona",
    "wof:name":"Ideal Kit S.l.",
    "wof:placetype":"venue"
},
  "geometry": {"coordinates":[2.0911879539,41.3767051697],"type":"Point"}
}