{
  "type": "Feature",
  "properties": {
    "addr:full":"Rond Ibon De Plan, 16 Zaragoza Zaragoza 50011",
    "addr:housenumber":"16",
    "addr:postcode":"50011",
    "addr:street":"Plan",
    "iso:country":"ES",
    "sg:address":"Rond Ibon De Plan, 16",
    "sg:city":"Zaragoza",
    "sg:orig_category":"Cooperativas Agr\u00cdcolas",
    "sg:phone":"+34 876 26 35 16",
    "sg:postcode":"50011",
    "sg:province":"Zaragoza",
    "wof:name":"Cooperativa Los Monegros De Sari\u00f1ena Soc",
    "wof:placetype":"venue"
},
  "geometry": {"coordinates":[-0.9913589954,41.662853241],"type":"Point"}
}