{
  "type": "Feature",
  "properties": {
    "addr:full":"Av Bocana, 9 Santa Margarida-salatar Girona 17480",
    "addr:housenumber":"9",
    "addr:postcode":"17480",
    "addr:street":"Av Bocana",
    "iso:country":"ES",
    "sg:address":"Av Bocana, 9",
    "sg:city":"Santa Margarida-salatar",
    "sg:orig_category":"Agencias Y Agentes Comerciales, Representantes",
    "sg:phone":"+34 972 25 74 48",
    "sg:postcode":"17480",
    "sg:province":"Girona",
    "wof:name":"Ellerbrock  Barbara",
    "wof:placetype":"venue"
},
  "geometry": {"coordinates":[3.1493599415,42.2607917786],"type":"Point"}
}