{
  "type": "Feature",
  "properties": {
    "iso:country":"ES",
    "sg:address":"Plaz Jose Antonio, 7",
    "sg:city":"Ramales Victoria",
    "sg:orig_category":"Panader\u00cdas, Panader\u00cdas",
    "sg:phone":"+34 942 64 61 89",
    "sg:postcode":"39800",
    "sg:province":"Cantabria",
    "wof:name":"Moral Campa Domingo Del",
    "wof:placetype":"venue"
},
  "geometry": {"coordinates":[-3.442991972,43.2613754272],"type":"Point"}
}