{
  "type": "Feature",
  "properties": {
    "iso:country":"ES",
    "sg:address":"Ctra. Villamanta, S/n",
    "sg:city":"Mentrida",
    "sg:orig_category":"Cerrajer\u00cda, Ferrallista",
    "sg:phone":"+34 918 17 76 78",
    "sg:postcode":"45930",
    "sg:province":"Toledo",
    "wof:name":"Cerrajeria Garcia Uceta S.l.",
    "wof:placetype":"venue"
},
  "geometry": {"coordinates":[-4.1898789406,40.2442398071],"type":"Point"}
}