{
  "type": "Feature",
  "properties": {
    "addr:full":"Ptda Benimarco, 100 Teulada Alicante 03725",
    "addr:housenumber":"100",
    "addr:postcode":"03725",
    "addr:street":"Ptda Benimarco",
    "iso:country":"ES",
    "sg:address":"Ptda Benimarco, 100",
    "sg:city":"Teulada",
    "sg:orig_category":"Frutas Y Legumbres Frescas (al Por Mayor)",
    "sg:phone":"+34 966 49 87 06",
    "sg:postcode":"03725",
    "sg:province":"Alicante",
    "wof:name":"Julia Crespo Bartolome",
    "wof:placetype":"venue"
},
  "geometry": {"coordinates":[0.1042950004,38.7289505005],"type":"Point"}
}