{
  "type": "Feature",
  "properties": {
    "addr:full":"Carrer de Sant Francesc D'assis, 16 Mataro Barcelona 08301",
    "addr:housenumber":"16",
    "addr:postcode":"08301",
    "addr:street":"Carrer De Sant Francesc D'Assis",
    "iso:country":"ES",
    "sg:address":"Carrer de Sant Francesc D'assis, 16",
    "sg:city":"Mataro",
    "sg:orig_category":"Ense\u00d1anza Variada",
    "sg:phone":"+34 937 90 67 50",
    "sg:postcode":"08301",
    "sg:province":"Barcelona",
    "wof:name":"Llavina Gemisans Maria Del Carmen",
    "wof:placetype":"venue"
},
  "geometry": {"coordinates":[2.4479339123,41.5373954773],"type":"Point"}
}