{
  "type": "Feature",
  "properties": {
    "iso:country":"ES",
    "sg:address":"Calle de San Luis, 27",
    "sg:city":"Torrevieja",
    "sg:orig_category":"Institutos De Belleza",
    "sg:phone":"+34 965 71 84 63",
    "sg:postcode":"03180",
    "sg:province":"Alicante",
    "wof:name":"Conesa Bleda Maria Jose",
    "wof:placetype":"venue"
},
  "geometry": {"coordinates":[-0.6875950098,37.9806442261],"type":"Point"}
}