{
  "type": "Feature",
  "properties": {
    "iso:country":"ES",
    "sg:address":"Rua Policarpo Sanz, 29",
    "sg:city":"Vigo",
    "sg:orig_category":"M\u00c9dicos: Ginecolog\u00cda Y Obstetricia",
    "sg:phone":"+34 986 43 67 60",
    "sg:postcode":"36202",
    "sg:province":"Pontevedra",
    "wof:name":"Pardi\u00f1as Costas Isabel",
    "wof:placetype":"venue"
},
  "geometry": {"coordinates":[-8.7231664658,42.2376823425],"type":"Point"}
}