{
  "type": "Feature",
  "properties": {
    "addr:full":"Carrer de Vilardell, 50 Barcelona Barcelona 08014",
    "addr:housenumber":"50",
    "addr:postcode":"08014",
    "addr:street":"Carrer De Vilardell",
    "iso:country":"ES",
    "sg:address":"Carrer de Vilardell, 50",
    "sg:city":"Barcelona",
    "sg:orig_category":"Iglesia Cat\u00d3lica",
    "sg:phone":"+34 934 23 32 89",
    "sg:postcode":"08014",
    "sg:province":"Barcelona",
    "wof:name":"Parroquia Del Sant Angel Custodi",
    "wof:placetype":"venue"
},
  "geometry": {"coordinates":[2.1448440552,41.374458313],"type":"Point"}
}