{
  "type": "Feature",
  "properties": {
    "iso:country":"ES",
    "sg:address":"Calle de Mesones, 45",
    "sg:city":"Villanueva De Los Castillejos",
    "sg:orig_category":"Carnicer\u00cdas, Carnicer\u00cdas",
    "sg:phone":"+34 959 38 59 85",
    "sg:postcode":"21540",
    "sg:province":"Huelva",
    "sg:website":"www.jabugobio.com",
    "wof:name":"Jabugo Export S.l.",
    "wof:placetype":"venue"
},
  "geometry": {"coordinates":[-7.2719459534,37.5029449463],"type":"Point"}
}