{
  "type": "Feature",
  "properties": {
    "iso:country":"ES",
    "sg:address":"Carrer de Calvari, 3",
    "sg:city":"Genova",
    "sg:orig_category":"Fabricaci\u00d3n, Reparaci\u00d3n Y Mantenimiento De Construcciones Navales Y Fluviales",
    "sg:phone":"+34 971 70 72 74",
    "sg:postcode":"07015",
    "sg:province":"Islas Baleares",
    "wof:name":"Muller  Jorn",
    "wof:placetype":"venue"
},
  "geometry": {"coordinates":[2.5952939987,39.5620536804],"type":"Point"}
}