{
  "type": "Feature",
  "properties": {
    "iso:country":"ES",
    "sg:address":"Calle de Juan De Garay, 2",
    "sg:city":"Villarcayo",
    "sg:orig_category":"Inmobiliaria (agencias)",
    "sg:phone":"+34 947 13 12 64",
    "sg:postcode":"09550",
    "sg:province":"Burgos",
    "wof:name":"Inmobiliaria Y Servicios Mapi",
    "wof:placetype":"venue"
},
  "geometry": {"coordinates":[-3.5718090534,42.9365501404],"type":"Point"}
}