{
  "type": "Feature",
  "properties": {
    "iso:country":"ES",
    "sg:address":"Pase Constitucion De (la), 61",
    "sg:city":"Arnedo",
    "sg:orig_category":"Ense\u00d1anza Variada",
    "sg:phone":"+34 941 38 47 74",
    "sg:postcode":"26580",
    "sg:province":"La Rioja",
    "wof:name":"Abad Martinez-losa Eva",
    "wof:placetype":"venue"
},
  "geometry": {"coordinates":[-2.102323,42.226288],"type":"Point"}
}