{
  "type": "Feature",
  "properties": {
    "iso:country":"ES",
    "sg:address":"Calle de Juan Carlos I Rey De Espa\u00d1a, 21",
    "sg:city":"Rute",
    "sg:orig_category":"Cristaler\u00cdas",
    "sg:phone":"+34 957 53 30 58",
    "sg:postcode":"14960",
    "sg:province":"C\u00f3rdoba",
    "wof:name":"Tintoreria Rute\u00f1a S.l.",
    "wof:placetype":"venue"
},
  "geometry": {"coordinates":[-4.3717398643,37.3274002075],"type":"Point"}
}