{
  "type": "Feature",
  "properties": {
    "addr:full":"Calle de San Gabriel, 12 Tamaraceite Las Palmas 35018",
    "addr:housenumber":"12",
    "addr:postcode":"35018",
    "addr:street":"Calle De San Gabriel;Las Palmas",
    "iso:country":"ES",
    "sg:address":"Calle de San Gabriel, 12",
    "sg:city":"Tamaraceite",
    "sg:orig_category":"Ense\u00d1anza Secundaria: Colegios Y Escuelas Privadas",
    "sg:phone":"+34 928 67 02 00",
    "sg:postcode":"35018",
    "sg:province":"Las Palmas",
    "wof:name":"Gobierno De Canarias",
    "wof:placetype":"venue"
},
  "geometry": {"coordinates":[-15.4772787094,28.1020317078],"type":"Point"}
}