{
  "type": "Feature",
  "properties": {
    "addr:full":"Calle de Obieta Kalea, 23 Erandio Vizcaya 48950",
    "addr:housenumber":"23",
    "addr:postcode":"48950",
    "addr:street":"Calle De Obieta Kalea",
    "iso:country":"ES",
    "sg:address":"Calle de Obieta Kalea, 23",
    "sg:city":"Erandio",
    "sg:orig_category":"Alimentaci\u00d3n General (al Por Menor)",
    "sg:phone":"+34 944 67 02 57",
    "sg:postcode":"48950",
    "sg:province":"Vizcaya",
    "wof:name":"Eduardo Uriarte Azkorra",
    "wof:placetype":"venue"
},
  "geometry": {"coordinates":[-2.9737379551,43.3037643433],"type":"Point"}
}