{
  "type": "Feature",
  "properties": {
    "addr:full":"Pase Habana, 68 Madrid Madrid 28036",
    "addr:housenumber":"68",
    "addr:postcode":"madrid;28036",
    "iso:country":"ES",
    "sg:address":"Pase Habana, 68",
    "sg:city":"Madrid",
    "sg:classifiers":[
        {
            "category":"Personal",
            "subcategory":"Barber",
            "type":"Services"
        }
    ],
    "sg:phone":"+34 915 64 91 64",
    "sg:postcode":"28036",
    "sg:province":"Madrid",
    "sg:tags":[
        "caballeros",
        "de",
        "peluqueros"
    ],
    "wof:name":"Ortiz Vazquez Jose Antonio",
    "wof:placetype":"venue"
},
  "geometry": {"coordinates":[-3.6849439144,40.4527359009],"type":"Point"}
}