{
  "type": "Feature",
  "properties": {
    "iso:country":"ES",
    "sg:address":"Avgd Pius Xii, 7",
    "sg:city":"Badalona",
    "sg:orig_category":"Televisi\u00d3n, V\u00cddeo: Aparatos Y Accesorios (venta)",
    "sg:phone":"+34 933 97 12 21",
    "sg:postcode":"08913",
    "sg:province":"Barcelona",
    "wof:name":"Martos Rojas Jose",
    "wof:placetype":"venue"
},
  "geometry": {"coordinates":[2.217236042,41.4368667603],"type":"Point"}
}