{
  "type": "Feature",
  "properties": {
    "iso:country":"ES",
    "sg:address":"Av Llibertat (la), 10",
    "sg:city":"Novelda",
    "sg:orig_category":"Locales Y Clases De Danza",
    "sg:phone":"+34 965 60 72 32",
    "sg:postcode":"03660",
    "sg:province":"Alicante",
    "wof:name":"Marcos Guarinos Maria Del Mar",
    "wof:placetype":"venue"
},
  "geometry": {"coordinates":[-0.7718489766,38.389251709],"type":"Point"}
}