{
  "type": "Feature",
  "properties": {
    "addr:full":"Av Francesc Macia, 43 Sabadell Barcelona 08206",
    "addr:housenumber":"43",
    "addr:postcode":"08206",
    "addr:street":"Av Francesc Macia",
    "iso:country":"ES",
    "sg:address":"Av Francesc Macia, 43",
    "sg:city":"Sabadell",
    "sg:orig_category":"Artes Gr\u00c1ficas, Artes Pl\u00c1sticas: Material Y Suministros (al Por Menor)",
    "sg:phone":"+34 937 16 58 41",
    "sg:postcode":"08206",
    "sg:province":"Barcelona",
    "wof:name":"Telemensaje S.a.",
    "wof:placetype":"venue"
},
  "geometry": {"coordinates":[2.0972299576,41.5571098328],"type":"Point"}
}