{
  "type": "Feature",
  "properties": {
    "iso:country":"ES",
    "sg:address":"Viella(bda H America), 13",
    "sg:city":"Los Dolores",
    "sg:orig_category":"Contenedores (mercanc\u00cdas)",
    "sg:phone":"+34 968 51 12 96",
    "sg:postcode":"30310",
    "sg:province":"Murcia",
    "wof:name":"Molina Moya Manuel",
    "wof:placetype":"venue"
},
  "geometry": {"coordinates":[-1.0116859674,37.6330795288],"type":"Point"}
}