{
  "type": "Feature",
  "properties": {
    "iso:country":"ES",
    "sg:address":"A Cumieira De Arriba, S/n",
    "sg:city":"Cumieira De Riba",
    "sg:orig_category":"Ense\u00d1anza, Formaci\u00d3n Profesional: Aprendizaje",
    "sg:phone":"+34 986 62 56 44",
    "sg:postcode":"36770",
    "sg:province":"Pontevedra",
    "wof:name":"Xunta De Galicia Red Privada",
    "wof:placetype":"venue"
},
  "geometry": {"coordinates":[-8.6480531693,42.4336204529],"type":"Point"}
}