{
  "type": "Feature",
  "properties": {
    "addr:full":"Calle de Guiomar Fernandez, 24 Burgos Burgos 09006",
    "addr:housenumber":"24",
    "addr:postcode":"09006",
    "addr:street":"Calle De Guiomar Fernandez",
    "iso:country":"ES",
    "sg:address":"Calle de Guiomar Fernandez, 24",
    "sg:city":"Burgos",
    "sg:orig_category":"Alquiler De V\u00cddeo",
    "sg:phone":"+34 947 24 23 95",
    "sg:postcode":"09006",
    "sg:province":"Burgos",
    "wof:name":"Scyo S.l.",
    "wof:placetype":"venue"
},
  "geometry": {"coordinates":[-3.6789019108,42.3604774475],"type":"Point"}
}