{
  "type": "Feature",
  "properties": {
    "addr:full":"Parque Comercial Mojacar, S/n Mojacar Almer\u00eda 04638",
    "addr:housenumber":"s",
    "addr:postcode":"04638",
    "addr:street":"/ N;Almeri\u0301A",
    "iso:country":"ES",
    "sg:address":"Parque Comercial Mojacar, S/n",
    "sg:city":"Mojacar",
    "sg:orig_category":"Centros Empresariales",
    "sg:phone":"+34 950 47 27 03",
    "sg:postcode":"04638",
    "sg:province":"Almer\u00eda",
    "wof:name":"Spanish Conveyancing Services Sl",
    "wof:placetype":"venue"
},
  "geometry": {"coordinates":[-1.8467450142,37.1402359009],"type":"Point"}
}