{
  "type": "Feature",
  "properties": {
    "addr:full":"Carrer de Felipe De Paz, 6 Barcelona Barcelona 08028",
    "addr:housenumber":"6",
    "addr:postcode":"08028",
    "addr:street":"Carrer De Felipe De Paz",
    "iso:country":"ES",
    "sg:address":"Carrer de Felipe De Paz, 6",
    "sg:city":"Barcelona",
    "sg:orig_category":"Reposter\u00cdas",
    "sg:phone":"+34 933 39 56 60",
    "sg:postcode":"08028",
    "sg:province":"Barcelona",
    "wof:name":"Llaras Muzas Montserrat",
    "wof:placetype":"venue"
},
  "geometry": {"coordinates":[2.1260368824,41.3797149658],"type":"Point"}
}