{
  "type": "Feature",
  "properties": {
    "addr:full":"Calle de Estrella Polar, 16 Madrid Madrid 28007",
    "addr:housenumber":"16",
    "addr:postcode":"madrid;28007",
    "addr:street":"Calle De Estrella Polar",
    "iso:country":"ES",
    "sg:address":"Calle de Estrella Polar, 16",
    "sg:city":"Madrid",
    "sg:orig_category":"Sociedades, Compa\u00d1\u00cdas Aseguradoras",
    "sg:phone":"+34 914 09 25 02",
    "sg:postcode":"28007",
    "sg:province":"Madrid",
    "wof:name":"Casas Gallo Juan Francisco De La",
    "wof:placetype":"venue"
},
  "geometry": {"coordinates":[-3.6668100357,40.4101638794],"type":"Point"}
}