{
  "type": "Feature",
  "properties": {
    "addr:full":"Pol La Rosaleda, S/n Vila-real Castell\u00f3n 12540",
    "addr:housenumber":"s / n;castello\u0301n",
    "addr:postcode":"12540",
    "addr:street":"Pol La Rosaleda",
    "iso:country":"ES",
    "sg:address":"Pol La Rosaleda, S/n",
    "sg:city":"Vila-real",
    "sg:orig_category":"Acero: Productos Sider\u00dargicos Y Transformados (fabricaci\u00d3n, Negocio)",
    "sg:phone":"+34 964 52 58 25",
    "sg:postcode":"12540",
    "sg:province":"Castell\u00f3n",
    "wof:name":"Talleres Calmont S.l.",
    "wof:placetype":"venue"
},
  "geometry": {"coordinates":[-0.0952899978,39.9453010559],"type":"Point"}
}