{
  "type": "Feature",
  "properties": {
    "iso:country":"ES",
    "sg:address":"Paraje Pinares, S/n",
    "sg:city":"Quinto",
    "sg:orig_category":"Veh\u00cdculos De Ocasi\u00d3n",
    "sg:phone":"+34 976 17 70 65",
    "sg:postcode":"50770",
    "sg:province":"Zaragoza",
    "wof:name":"Comercial Gasco Agustin S.l.",
    "wof:placetype":"venue"
},
  "geometry": {"coordinates":[-0.5005689859,41.429561615],"type":"Point"}
}