{
  "type": "Feature",
  "properties": {
    "addr:full":"Ctra. Mocejon, S/n Toledo Toledo 45008",
    "addr:housenumber":"s / n",
    "addr:postcode":"45008",
    "addr:street":"Ctra. Mocejon",
    "iso:country":"ES",
    "sg:address":"Ctra. Mocejon, S/n",
    "sg:city":"Toledo",
    "sg:orig_category":"Polideportivos",
    "sg:phone":"+34 925 21 26 46",
    "sg:postcode":"45008",
    "sg:province":"Toledo",
    "wof:name":"Patronato Deportivo Municipal De Toledo",
    "wof:placetype":"venue"
},
  "geometry": {"coordinates":[-3.9743340015,39.8845291138],"type":"Point"}
}