{
  "type": "Feature",
  "properties": {
    "addr:full":"Carrer de Vazquez De Mella, 7 Terrassa Barcelona 08224",
    "addr:housenumber":"7",
    "addr:postcode":"08224",
    "addr:street":"Carrer De Vazquez De Mella",
    "iso:country":"ES",
    "sg:address":"Carrer de Vazquez De Mella, 7",
    "sg:city":"Terrassa",
    "sg:orig_category":"Caf\u00c9s, Bares, Cervecer\u00cdas",
    "sg:phone":"+34 937 80 55 24",
    "sg:postcode":"08224",
    "sg:province":"Barcelona",
    "wof:name":"Sarrion Honrrubia Juan Emilio",
    "wof:placetype":"venue"
},
  "geometry": {"coordinates":[2.0058300495,41.5659713745],"type":"Point"}
}