{
  "type": "Feature",
  "properties": {
    "addr:full":"Calle de Miguel Loredo Rola, 6 Portugalete Vizcaya 48920",
    "addr:housenumber":"6",
    "addr:postcode":"48920",
    "addr:street":"Calle De Miguel Loredo Rola",
    "iso:country":"ES",
    "sg:address":"Calle de Miguel Loredo Rola, 6",
    "sg:city":"Portugalete",
    "sg:orig_category":"Carnicer\u00cdas, Carnicer\u00cdas",
    "sg:phone":"+34 944 95 24 43",
    "sg:postcode":"48920",
    "sg:province":"Vizcaya",
    "wof:name":"Francisco Javier Bilbao Gomez",
    "wof:placetype":"venue"
},
  "geometry": {"coordinates":[-3.0173339844,43.3175849915],"type":"Point"}
}