{
  "type": "Feature",
  "properties": {
    "iso:country":"ES",
    "sg:address":"Ezponda, 4",
    "sg:city":"Huarte",
    "sg:orig_category":"Pescader\u00cdas (al Por Menor)",
    "sg:phone":"+34 948 33 09 12",
    "sg:postcode":"31620",
    "sg:province":"Navarra",
    "wof:name":"Bacalao Samper S.a.",
    "wof:placetype":"venue"
},
  "geometry": {"coordinates":[-1.6032381058,42.8261375427],"type":"Point"}
}