{
  "type": "Feature",
  "properties": {
    "addr:full":"Ctra Caceres-lisboa, Km. 0093,1 Valencia Alcantara C\u00e1ceres 10500",
    "addr:postcode":"10500",
    "addr:street":"Ctra Caceres-Lisboa Km. 0093,1;Alcantara Ca\u0301Ceres",
    "iso:country":"ES",
    "sg:address":"Ctra Caceres-lisboa, Km. 0093,1",
    "sg:city":"Valencia Alcantara",
    "sg:orig_category":"Mec\u00c1nico Del Autom\u00d3vil",
    "sg:phone":"+34 927 58 01 95",
    "sg:postcode":"10500",
    "sg:province":"C\u00e1ceres",
    "wof:name":"Talleres Montero Amuedo S.l.",
    "wof:placetype":"venue"
},
  "geometry": {"coordinates":[-7.2451472282,39.4101142883],"type":"Point"}
}