{
  "type": "Feature",
  "properties": {
    "addr:full":"Carr Laietania, 17 Badalona Barcelona 08911",
    "addr:housenumber":"17",
    "addr:postcode":"08911",
    "addr:street":"Carr Laietania",
    "iso:country":"ES",
    "sg:address":"Carr Laietania, 17",
    "sg:city":"Badalona",
    "sg:orig_category":"Administradores De Bienes Y Delegados De Comunidades De Propietarios",
    "sg:phone":"+34 933 84 00 00",
    "sg:postcode":"08911",
    "sg:province":"Barcelona",
    "wof:name":"Assesoria Finques Badalona S.l.",
    "wof:placetype":"venue"
},
  "geometry": {"coordinates":[2.2481191158,41.4532699585],"type":"Point"}
}