{
  "type": "Feature",
  "properties": {
    "iso:country":"ES",
    "sg:address":"Calle de Orixe, 54",
    "sg:city":"Bilbao",
    "sg:orig_category":"Venta, Instalaci\u00d3n De Calefacci\u00d3n",
    "sg:phone":"+34 944 76 00 42",
    "sg:postcode":"48015",
    "sg:province":"Vizcaya",
    "wof:name":"Cantera Perex Gotzon",
    "wof:placetype":"venue"
},
  "geometry": {"coordinates":[-2.9641840458,43.2845993042],"type":"Point"}
}