{
  "type": "Feature",
  "properties": {
    "iso:country":"ES",
    "sg:address":"Urb. La Paz, 5",
    "sg:city":"Llanes",
    "sg:orig_category":"Ingenier\u00cda, Centros De Estudios (diversos)",
    "sg:phone":"+34 985 40 26 94",
    "sg:postcode":"33500",
    "sg:province":"Asturias",
    "wof:name":"Asturagua S.a.",
    "wof:placetype":"venue"
},
  "geometry": {"coordinates":[-4.8416934013,43.4103507996],"type":"Point"}
}