{
  "type": "Feature",
  "properties": {
    "addr:full":"Calle de Major, 8 Sant Pere De Torello Barcelona 08572",
    "addr:housenumber":"8",
    "addr:postcode":"08572",
    "addr:street":"Calle De Major",
    "iso:country":"ES",
    "sg:address":"Calle de Major, 8",
    "sg:city":"Sant Pere De Torello",
    "sg:orig_category":"Cajas Y Embalajes De Cart\u00d3n Y Papel",
    "sg:phone":"+34 938 58 40 11",
    "sg:postcode":"08572",
    "sg:province":"Barcelona",
    "wof:name":"Cartonatge Font S.l.",
    "wof:placetype":"venue"
},
  "geometry": {"coordinates":[2.2966399193,42.0746955872],"type":"Point"}
}