{
  "type": "Feature",
  "properties": {
    "addr:full":"Carrer de Llatzeret, 25 Barcelona Barcelona 08005",
    "addr:housenumber":"25",
    "addr:postcode":"08005",
    "addr:street":"Carrer De Llatzeret",
    "iso:country":"ES",
    "sg:address":"Carrer de Llatzeret, 25",
    "sg:city":"Barcelona",
    "sg:orig_category":"Guarder\u00cdas",
    "sg:phone":"+34 933 07 77 36",
    "sg:postcode":"08005",
    "sg:province":"Barcelona",
    "wof:name":"Gonzalez Guillen Maria Del Carmen",
    "wof:placetype":"venue"
},
  "geometry": {"coordinates":[2.2018270493,41.4034805298],"type":"Point"}
}