{
  "type": "Feature",
  "properties": {
    "iso:country":"ES",
    "sg:address":"Pol Ind La Atalaya, S/n",
    "sg:city":"Cabra",
    "sg:orig_category":"Electricidad, Electr\u00d3nica: Material Y Suministros (al Por Mayor)",
    "sg:phone":"+34 957 52 38 54",
    "sg:postcode":"14940",
    "sg:province":"C\u00f3rdoba",
    "wof:name":"Sumelca Trading Iii Sll",
    "wof:placetype":"venue"
},
  "geometry": {"coordinates":[-4.4485092163,37.4801063538],"type":"Point"}
}