{
  "type": "Feature",
  "properties": {
    "addr:full":"Avda Juan Carlos I, 53 Estepona M\u00e1laga 29680",
    "addr:housenumber":"53",
    "addr:postcode":"29680",
    "addr:street":"Avda Juan Carlos I",
    "iso:country":"ES",
    "sg:address":"Avda Juan Carlos I, 53",
    "sg:city":"Estepona",
    "sg:orig_category":"Centros De Educaci\u00d3n Especial",
    "sg:phone":"+34 952 80 12 67",
    "sg:postcode":"29680",
    "sg:province":"M\u00e1laga",
    "wof:name":"Junta De Andalucia",
    "wof:placetype":"venue"
},
  "geometry": {"coordinates":[-5.1528987885,36.4255218506],"type":"Point"}
}