{
  "type": "Feature",
  "properties": {
    "iso:country":"ES",
    "sg:address":"Calle de Arroyo De Las Pilillas, 52",
    "sg:city":"Madrid",
    "sg:orig_category":"Molduras, Junquillos, Listones Y Molduras Perforadas",
    "sg:phone":"+34 914 39 50 33",
    "sg:postcode":"28030",
    "sg:province":"Madrid",
    "wof:name":"Diego Ponce Jesus De",
    "wof:placetype":"venue"
},
  "geometry": {"coordinates":[-3.6514360905,40.4077987671],"type":"Point"}
}