{
  "type": "Feature",
  "properties": {
    "iso:country":"ES",
    "sg:address":"Carrer de Esglesia, 106",
    "sg:city":"Castelldefels",
    "sg:orig_category":"Electricidad: Equipos Industriales, Componentes (fabricaci\u00d3n)",
    "sg:phone":"+34 936 36 17 93",
    "sg:postcode":"08860",
    "sg:province":"Barcelona",
    "wof:name":"Pemosa S.cp",
    "wof:placetype":"venue"
},
  "geometry": {"coordinates":[1.983651042,41.2855834961],"type":"Point"}
}