{
  "type": "Feature",
  "properties": {
    "iso:country":"ES",
    "sg:address":"Urb Oasis Residencial, S/n",
    "sg:city":"Manga Mar Menor",
    "sg:orig_category":"Inmobiliaria (agencias)",
    "sg:phone":"+34 968 14 23 01",
    "sg:postcode":"30380",
    "sg:province":"Murcia",
    "wof:name":"Abity Inmuebles S.a.",
    "wof:placetype":"venue"
},
  "geometry": {"coordinates":[-1.129887,37.983475],"type":"Point"}
}