{
  "type": "Feature",
  "properties": {
    "addr:full":"Av. C. Sotelo, S/n Padron La Coru\u00f1a 15900",
    "addr:housenumber":"s / n",
    "addr:postcode":"15900",
    "addr:street":"Av. C. Sotelo;Padron La Corun\u0303A",
    "iso:country":"ES",
    "sg:address":"Av. C. Sotelo, S/n",
    "sg:city":"Padron",
    "sg:orig_category":"Electrodom\u00c9sticos (al Por Menor)",
    "sg:phone":"+34 981 81 00 08",
    "sg:postcode":"15900",
    "sg:province":"La Coru\u00f1a",
    "wof:name":"Castro Cajaraville Jose",
    "wof:placetype":"venue"
},
  "geometry": {"coordinates":[-8.6598138809,42.7375144958],"type":"Point"}
}