{
  "type": "Feature",
  "properties": {
    "addr:full":"Rua Curros Enriquez (poeta), 10 Lugo Lugo 27004",
    "addr:housenumber":"10",
    "addr:postcode":"27004",
    "addr:street":"Rua Curros Enriquez Poeta",
    "iso:country":"ES",
    "sg:address":"Rua Curros Enriquez (poeta), 10",
    "sg:city":"Lugo",
    "sg:orig_category":"Cer\u00c1micas: Material Y Suministros",
    "sg:phone":"+34 982 21 91 50",
    "sg:postcode":"27004",
    "sg:province":"Lugo",
    "wof:name":"Alaplana Coru\u00f1a S.l.",
    "wof:placetype":"venue"
},
  "geometry": {"coordinates":[-7.5659332275,43.0194129944],"type":"Point"}
}