{
  "type": "Feature",
  "properties": {
    "addr:full":"Cmno. Villas, 7 Castello Plana Castell\u00f3n 12004",
    "addr:postcode":"12004",
    "addr:street":"Cmno. Villas 7",
    "iso:country":"ES",
    "sg:address":"Cmno. Villas, 7",
    "sg:city":"Castello Plana",
    "sg:orig_category":"Asociaciones Humanitarias, De Cooperaci\u00d3n, De Acci\u00d3n Social",
    "sg:phone":"+34 964 76 09 55",
    "sg:postcode":"12004",
    "sg:province":"Castell\u00f3n",
    "wof:name":"Reto A La Esperanza Asociacion",
    "wof:placetype":"venue"
},
  "geometry": {"coordinates":[-0.0441690013,40.0043563843],"type":"Point"}
}