{
  "type": "Feature",
  "properties": {
    "addr:full":"Calle de Pedro Cabanes, 10 Valencia Valencia 46019",
    "addr:housenumber":"10",
    "addr:postcode":"46019",
    "addr:street":"Calle De Pedro Cabanes",
    "iso:country":"ES",
    "sg:address":"Calle de Pedro Cabanes, 10",
    "sg:city":"Valencia",
    "sg:classifiers":[
        {
            "category":"Autos & Motor Vehicles",
            "subcategory":"Automobile Sales",
            "type":"Retail Goods"
        }
    ],
    "sg:phone":"+34 963 68 08 08",
    "sg:postcode":"46019",
    "sg:province":"Valencia",
    "wof:name":"Ademuz Formacion Y Tecnologia",
    "wof:placetype":"venue"
},
  "geometry": {"coordinates":[-0.3727521002,39.4953536987],"type":"Point"}
}