{
  "type": "Feature",
  "properties": {
    "addr:full":"Calle de Mariana Pineda, 24 Albacete Albacete 02005",
    "addr:housenumber":"24",
    "addr:postcode":"02005",
    "addr:street":"Calle De Mariana Pineda",
    "iso:country":"ES",
    "sg:address":"Calle de Mariana Pineda, 24",
    "sg:city":"Albacete",
    "sg:orig_category":"Mec\u00c1nico Del Autom\u00d3vil",
    "sg:phone":"+34 967 52 42 81",
    "sg:postcode":"02005",
    "sg:province":"Albacete",
    "wof:name":"Automediterraneo S.a.",
    "wof:placetype":"venue"
},
  "geometry": {"coordinates":[-1.8556710482,38.9988098145],"type":"Point"}
}