{
  "type": "Feature",
  "properties": {
    "addr:full":"Calle de Cervantes, 1 Villanueva De Los Infantes Ciudad Real 13320",
    "addr:housenumber":"1",
    "addr:postcode":"13320",
    "addr:street":"Calle De Cervantes;Infantes",
    "iso:country":"ES",
    "sg:address":"Calle de Cervantes, 1",
    "sg:city":"Villanueva De Los Infantes",
    "sg:orig_category":"Farmacias",
    "sg:phone":"+34 926 36 15 19",
    "sg:postcode":"13320",
    "sg:province":"Ciudad Real",
    "wof:name":"Coca Menchero Vicente",
    "wof:placetype":"venue"
},
  "geometry": {"coordinates":[-3.0127203465,38.7352104187],"type":"Point"}
}