{
  "type": "Feature",
  "properties": {
    "addr:full":"Calle de Gomez Ferrer, 1 Mislata Valencia 46920",
    "addr:housenumber":"1",
    "addr:postcode":"46920",
    "addr:street":"Calle De Gomez Ferrer",
    "iso:country":"ES",
    "sg:address":"Calle de Gomez Ferrer, 1",
    "sg:city":"Mislata",
    "sg:orig_category":"Empresas De Limpieza",
    "sg:phone":"+34 963 83 44 48",
    "sg:postcode":"46920",
    "sg:province":"Valencia",
    "wof:name":"Limpiezas El Turia S. L.",
    "wof:placetype":"venue"
},
  "geometry": {"coordinates":[-0.4135960042,39.4738998413],"type":"Point"}
}