{
  "type": "Feature",
  "properties": {
    "addr:full":"Ctra. Montehermoso, 105 Carcaboso C\u00e1ceres 10670",
    "addr:housenumber":"105",
    "addr:postcode":"10670",
    "addr:street":"Ctra. Montehermoso;Ca\u0301Ceres",
    "iso:country":"ES",
    "sg:address":"Ctra. Montehermoso, 105",
    "sg:city":"Carcaboso",
    "sg:orig_category":"Almacenes Para Venta: Muebles Y Varios",
    "sg:phone":"+34 927 40 22 65",
    "sg:postcode":"10670",
    "sg:province":"C\u00e1ceres",
    "wof:name":"Pulido Dominguez Fermin",
    "wof:placetype":"venue"
},
  "geometry": {"coordinates":[-6.2117791176,40.0478935242],"type":"Point"}
}