{
  "type": "Feature",
  "properties": {
    "addr:full":"Carrer de Sant Antoni (de), 27 Vila-seca Tarragona 43480",
    "addr:housenumber":"27",
    "addr:postcode":"43480",
    "addr:street":"Carrer De Sant Antoni De",
    "iso:country":"ES",
    "sg:address":"Carrer de Sant Antoni (de), 27",
    "sg:city":"Vila-seca",
    "sg:orig_category":"Contables",
    "sg:phone":"+34 977 39 20 69",
    "sg:postcode":"43480",
    "sg:province":"Tarragona",
    "wof:name":"Rafols Assessors S.l.",
    "wof:placetype":"venue"
},
  "geometry": {"coordinates":[1.1446130276,41.110370636],"type":"Point"}
}