{
  "type": "Feature",
  "properties": {
    "addr:full":"Calle de Isaac Albeniz, S/n Padul Granada 18640",
    "addr:housenumber":"s / n",
    "addr:postcode":"18640",
    "addr:street":"Calle De Isaac Albeniz",
    "iso:country":"ES",
    "sg:address":"Calle de Isaac Albeniz, S/n",
    "sg:city":"Padul",
    "sg:orig_category":"Molduras, Junquillos, Listones Y Molduras Perforadas",
    "sg:phone":"+34 958 77 35 20",
    "sg:postcode":"18640",
    "sg:province":"Granada",
    "wof:name":"Robles Marchan Carmen",
    "wof:placetype":"venue"
},
  "geometry": {"coordinates":[-3.6250090599,37.0216445923],"type":"Point"}
}