{
  "type": "Feature",
  "properties": {
    "addr:full":"Calle de Guzman El Bueno, 52 Madrid Madrid 28015",
    "addr:housenumber":"52",
    "addr:postcode":"madrid;28015",
    "addr:street":"Calle De Guzman El Bueno",
    "iso:country":"ES",
    "sg:address":"Calle de Guzman El Bueno, 52",
    "sg:city":"Madrid",
    "sg:orig_category":"Panader\u00cdas, Panader\u00cdas",
    "sg:phone":"+34 915 43 10 94",
    "sg:postcode":"28015",
    "sg:province":"Madrid",
    "wof:name":"Animari Pastelerias S.l.",
    "wof:placetype":"venue"
},
  "geometry": {"coordinates":[-3.7131021023,40.4359512329],"type":"Point"}
}