{
  "type": "Feature",
  "properties": {
    "iso:country":"ES",
    "sg:address":"Carrer de Mayor, 21",
    "sg:city":"Guardamar Segura",
    "sg:orig_category":"Peluquer\u00cdas, Peluquer\u00cda Mixta",
    "sg:phone":"+34 966 72 76 16",
    "sg:postcode":"03140",
    "sg:province":"Alicante",
    "wof:name":"Marhuenda Gimenez Virtudes",
    "wof:placetype":"venue"
},
  "geometry": {"coordinates":[-0.6540290117,38.086681366],"type":"Point"}
}