{
  "type": "Feature",
  "properties": {
    "iso:country":"ES",
    "sg:address":"Avda Costa Blanca, 128",
    "sg:city":"Alacant",
    "sg:orig_category":"Negocio De Materiales De Construcci\u00d3n",
    "sg:phone":"+34 965 26 09 07",
    "sg:postcode":"03540",
    "sg:province":"Alicante",
    "wof:name":"Esparavel Aplicacion S.l.",
    "wof:placetype":"venue"
},
  "geometry": {"coordinates":[-0.4116620123,38.3665008545],"type":"Point"}
}