{
  "type": "Feature",
  "properties": {
    "addr:full":"Prol Ronda De Santo Domingo, 4 Orihuela Alicante 03300",
    "addr:housenumber":"4",
    "addr:postcode":"03300",
    "addr:street":"Prol Ronda De Santo Domingo",
    "iso:country":"ES",
    "sg:address":"Prol Ronda De Santo Domingo, 4",
    "sg:city":"Orihuela",
    "sg:orig_category":"Electricidad: Instaladores",
    "sg:phone":"+34 966 73 91 59",
    "sg:postcode":"03300",
    "sg:province":"Alicante",
    "sg:website":"www.draintel.com",
    "wof:name":"Ruiz Aparicio Damian",
    "wof:placetype":"venue"
},
  "geometry": {"coordinates":[-0.940474987,38.0861206055],"type":"Point"}
}