{
  "type": "Feature",
  "properties": {
    "iso:country":"ES",
    "sg:address":"Plaz Republica Argentina, 8",
    "sg:city":"Madrid",
    "sg:orig_category":"Distribuci\u00d3n De Petr\u00d3leo Y Derivados",
    "sg:phone":"+34 915 62 03 64",
    "sg:postcode":"28002",
    "sg:province":"Madrid",
    "wof:name":"Manzano Dalmases Maria Dolores",
    "wof:placetype":"venue"
},
  "geometry": {"coordinates":[-3.6849679947,40.445110321],"type":"Point"}
}