{
  "type": "Feature",
  "properties": {
    "addr:full":"Martires Auzoa, 41 Arrieta-mendi Guip\u00f9zcoa 20720",
    "addr:housenumber":"41",
    "addr:postcode":"20720",
    "addr:street":"Martires Auzoa;Guipu\u0300Zcoa",
    "iso:country":"ES",
    "sg:address":"Martires Auzoa, 41",
    "sg:city":"Arrieta-mendi",
    "sg:classifiers":[
        {
            "category":"Manufacturing",
            "subcategory":"Metals",
            "type":"Manufacturing & Wholesale Goods"
        }
    ],
    "sg:phone":"+34 943 85 76 57",
    "sg:postcode":"20720",
    "sg:province":"Guip\u00f9zcoa",
    "sg:tags":[
        "en",
        "fundiciones"
    ],
    "wof:name":"Beitia Iriarte Luis Maria",
    "wof:placetype":"venue"
},
  "geometry": {"coordinates":[-2.3134639263,43.1762886047],"type":"Point"}
}