{
  "type": "Feature",
  "properties": {
    "iso:country":"ES",
    "sg:address":"Pase Mediterraneo (del), 259",
    "sg:city":"Ventanicas-el Cantal",
    "sg:orig_category":"Papeler\u00cdas, Librer\u00cdas",
    "sg:phone":"+34 950 47 53 01",
    "sg:postcode":"04638",
    "sg:province":"Almer\u00eda",
    "wof:name":"Rubio Lopez Jose",
    "wof:placetype":"venue"
},
  "geometry": {"coordinates":[-1.8406590223,37.122089386],"type":"Point"}
}