{
  "type": "Feature",
  "properties": {
    "iso:country":"ES",
    "sg:address":"Avda Maria Auxiliadora, 23",
    "sg:city":"Ecija",
    "sg:orig_category":"Caf\u00c9s, Bares, Cervecer\u00cdas",
    "sg:phone":"+34 955 90 47 48",
    "sg:postcode":"41400",
    "sg:province":"Sevilla",
    "wof:name":"Caro Muriana Francisco",
    "wof:placetype":"venue"
},
  "geometry": {"coordinates":[-5.0865340233,37.5425758362],"type":"Point"}
}