{
  "type": "Feature",
  "properties": {
    "addr:full":"Calle de Olleria Kalea, 5 Durango Vizcaya 48200",
    "addr:housenumber":"5",
    "addr:postcode":"48200",
    "addr:street":"Calle De Olleria Kalea",
    "iso:country":"ES",
    "sg:address":"Calle de Olleria Kalea, 5",
    "sg:city":"Durango",
    "sg:orig_category":"Cajas De Ahorro",
    "sg:phone":"+34 946 81 97 52",
    "sg:postcode":"48200",
    "sg:province":"Vizcaya",
    "wof:name":"Caixa D'estalvis I Pensions De Barcelona",
    "wof:placetype":"venue"
},
  "geometry": {"coordinates":[-2.6271140575,43.1707801819],"type":"Point"}
}