{
  "type": "Feature",
  "properties": {
    "iso:country":"ES",
    "sg:address":"Calle de Flor De Albahaca, 7",
    "sg:city":"Sevilla",
    "sg:orig_category":"Inform\u00c1tica, Ofim\u00c1tica (estudios, Asesor\u00cda, Ingenier\u00cda, Formaci\u00d3n)",
    "sg:phone":"+34 954 44 41 02",
    "sg:postcode":"41020",
    "sg:province":"Sevilla",
    "wof:name":"Lab Computer S.l.",
    "wof:placetype":"venue"
},
  "geometry": {"coordinates":[-5.9217119217,37.3967094421],"type":"Point"}
}