{
  "type": "Feature",
  "properties": {
    "addr:full":"Plaz Cuartel Viejo, 7 Zamora Zamora 49006",
    "addr:housenumber":"7",
    "addr:postcode":"49006",
    "addr:street":"Plaz;Viejo",
    "iso:country":"ES",
    "sg:address":"Plaz Cuartel Viejo, 7",
    "sg:city":"Zamora",
    "sg:orig_category":"Electrodom\u00c9sticos (al Por Menor)",
    "sg:phone":"+34 980 53 09 41",
    "sg:postcode":"49006",
    "sg:province":"Zamora",
    "wof:name":"Hernandez De Las Heras Laudelina",
    "wof:placetype":"venue"
},
  "geometry": {"coordinates":[-5.7447071075,41.5068702698],"type":"Point"}
}