{
  "type": "Feature",
  "properties": {
    "addr:full":"Calle de Luna, 56 Motilla Palancar Cuenca 16200",
    "addr:housenumber":"56",
    "addr:postcode":"16200",
    "addr:street":"Calle De Luna",
    "iso:country":"ES",
    "sg:address":"Calle de Luna, 56",
    "sg:city":"Motilla Palancar",
    "sg:orig_category":"Inform\u00c1tica, Ofim\u00c1tica (estudios, Asesor\u00cda, Ingenier\u00cda, Formaci\u00d3n)",
    "sg:phone":"+34 969 33 10 77",
    "sg:postcode":"16200",
    "sg:province":"Cuenca",
    "wof:name":"Cejalvo Valera Juan Carlos",
    "wof:placetype":"venue"
},
  "geometry": {"coordinates":[-1.9089189768,39.5623512268],"type":"Point"}
}