{
  "type": "Feature",
  "properties": {
    "iso:country":"ES",
    "sg:address":"Carrer de Moia, S/n",
    "sg:city":"Mas Fabrera",
    "sg:orig_category":"Cintas, Balduques Y Cierres De Tela (fabricaci\u00d3n, Al Por Mayor)",
    "sg:phone":"+34 938 46 56 71",
    "sg:postcode":"08480",
    "sg:province":"Barcelona",
    "wof:name":"Vilalta Casas Jordi",
    "wof:placetype":"venue"
},
  "geometry": {"coordinates":[2.2588799,41.6636009216],"type":"Point"}
}