{
  "type": "Feature",
  "properties": {
    "addr:full":"Sbid Cuartel, 7 Caspe Zaragoza 50700",
    "addr:housenumber":"7",
    "addr:postcode":"50700",
    "addr:street":"Sbid",
    "iso:country":"ES",
    "sg:address":"Sbid Cuartel, 7",
    "sg:city":"Caspe",
    "sg:orig_category":"Bordado, Marcado A Medida",
    "sg:phone":"+34 976 63 18 46",
    "sg:postcode":"50700",
    "sg:province":"Zaragoza",
    "wof:name":"Peiro Franco Maria Carmen",
    "wof:placetype":"venue"
},
  "geometry": {"coordinates":[-0.0405590013,41.2350769043],"type":"Point"}
}