{
  "type": "Feature",
  "properties": {
    "iso:country":"ES",
    "sg:address":"Calle de Cerro De Valdemartin, 25",
    "sg:city":"Madrid",
    "sg:orig_category":"Servidores Y Editores De Bases De Datos",
    "sg:phone":"+34 917 34 64 17",
    "sg:postcode":"28034",
    "sg:province":"Madrid",
    "sg:website":"www.websjob.com",
    "wof:name":"Flexitime E.t.t.s.l.",
    "wof:placetype":"venue"
},
  "geometry": {"coordinates":[-3.7074706554,40.4896354675],"type":"Point"}
}