{
  "type": "Feature",
  "properties": {
    "iso:country":"ES",
    "sg:address":"Calle de Colon, 35",
    "sg:city":"S. Fernando",
    "sg:orig_category":"Complementos De Vestir (al Por Menor)",
    "sg:phone":"+34 956 59 25 19",
    "sg:postcode":"11100",
    "sg:province":"C\u00e1diz",
    "wof:name":"Quijada Fernandez Jose Ismael",
    "wof:placetype":"venue"
},
  "geometry": {"coordinates":[-6.1969966888,36.4687690735],"type":"Point"}
}