{
  "type": "Feature",
  "properties": {
    "iso:country":"ES",
    "sg:address":"Rua Penedo (do), 13",
    "sg:city":"Santiago De Compostela",
    "sg:orig_category":"Muebles, Minoristas",
    "sg:phone":"+34 981 52 19 50",
    "sg:postcode":"15706",
    "sg:province":"A Coru\u00f1a",
    "wof:name":"Sucesores De Jose Fernandez Quintas Cdad",
    "wof:placetype":"venue"
},
  "geometry": {"coordinates":[-8.5526208878,42.8648757935],"type":"Point"}
}