{
  "type": "Feature",
  "properties": {
    "addr:full":"Calle de Real Baja, 10 Majadahonda Madrid 28220",
    "addr:housenumber":"10",
    "addr:postcode":"28220",
    "addr:street":"Calle De Real Baja",
    "iso:country":"ES",
    "sg:address":"Calle de Real Baja, 10",
    "sg:city":"Majadahonda",
    "sg:orig_category":"Artesan\u00cda",
    "sg:phone":"+34 916 38 01 18",
    "sg:postcode":"28220",
    "sg:province":"Madrid",
    "wof:name":"Diaz Sanchez Jose Maria",
    "wof:placetype":"venue"
},
  "geometry": {"coordinates":[-3.8727509975,40.4720306396],"type":"Point"}
}