{
  "type": "Feature",
  "properties": {
    "iso:country":"ES",
    "sg:address":"Carr Camp De La Vila (del), 3",
    "sg:city":"Pont Suert",
    "sg:orig_category":"Juegos Y Juguetes (al Por Menor)",
    "sg:phone":"+34 973 69 02 72",
    "sg:postcode":"25520",
    "sg:province":"Lleida",
    "wof:name":"Troquet Castan Antonio",
    "wof:placetype":"venue"
},
  "geometry": {"coordinates":[0.7406290174,42.4080657959],"type":"Point"}
}