{
  "type": "Feature",
  "properties": {
    "addr:full":"Plaz Sitios (los), 11 Zaragoza Zaragoza 50001",
    "addr:housenumber":"11",
    "addr:postcode":"50001",
    "addr:street":"Plaz;Los",
    "iso:country":"ES",
    "sg:address":"Plaz Sitios (los), 11",
    "sg:city":"Zaragoza",
    "sg:orig_category":"Art\u00cdculos De Decoraci\u00d3n",
    "sg:phone":"+34 976 46 85 58",
    "sg:postcode":"50001",
    "sg:province":"Zaragoza",
    "wof:name":"Creating The Look S.l.",
    "wof:placetype":"venue"
},
  "geometry": {"coordinates":[-0.8797360063,41.6495437622],"type":"Point"}
}