{
  "type": "Feature",
  "properties": {
    "addr:full":"Calle de Enrique Marco Dorta, 4 Sevilla Sevilla 41018",
    "addr:housenumber":"4",
    "addr:postcode":"41018",
    "addr:street":"Calle De Enrique Marco Dorta",
    "iso:country":"ES",
    "sg:address":"Calle de Enrique Marco Dorta, 4",
    "sg:city":"Sevilla",
    "sg:orig_category":"Asociaciones Humanitarias, De Cooperaci\u00d3n, De Acci\u00d3n Social",
    "sg:phone":"+34 954 41 80 30",
    "sg:postcode":"41018",
    "sg:province":"Sevilla",
    "wof:name":"Asociacion De Padres Para La Nornalizacion Rehabilitacion E Integracion Del Disminuido",
    "wof:placetype":"venue"
},
  "geometry": {"coordinates":[-5.979470253,37.3901138306],"type":"Point"}
}