{
  "type": "Feature",
  "properties": {
    "addr:full":"Cami Assagador, 1 Marxuquera Alta Valencia 46728",
    "addr:housenumber":"1",
    "addr:postcode":"46728",
    "addr:street":"Assagador",
    "iso:country":"ES",
    "sg:address":"Cami Assagador, 1",
    "sg:city":"Marxuquera Alta",
    "sg:orig_category":"Molduras, Junquillos, Listones Y Molduras Perforadas",
    "sg:phone":"+34 962 86 44 58",
    "sg:postcode":"46728",
    "sg:province":"Valencia",
    "wof:name":"Sotos Villena Pascual",
    "wof:placetype":"venue"
},
  "geometry": {"coordinates":[-0.2635430098,38.9826202393],"type":"Point"}
}