{
  "type": "Feature",
  "properties": {
    "iso:country":"ES",
    "sg:address":"Carreras, 132",
    "sg:city":"Chauchina",
    "sg:orig_category":"Asesor\u00cda Fiscal Y Jur\u00cddica",
    "sg:phone":"+34 958 44 74 20",
    "sg:postcode":"18330",
    "sg:province":"Granada",
    "wof:name":"Sanchez Garcia Rosa Carmen",
    "wof:placetype":"venue"
},
  "geometry": {"coordinates":[-3.7737350464,37.1960220337],"type":"Point"}
}