{
  "type": "Feature",
  "properties": {
    "iso:country":"ES",
    "sg:address":"Calle de Virgen De Los Reyes, 16",
    "sg:city":"Madrid",
    "sg:orig_category":"Servicios De Higiene Y Peluquer\u00cda Para Perros Y Gatos",
    "sg:phone":"+34 914 05 17 51",
    "sg:postcode":"28027",
    "sg:province":"Madrid",
    "wof:name":"Carpio Plaza Santiago",
    "wof:placetype":"venue"
},
  "geometry": {"coordinates":[-3.6512811184,40.4385452271],"type":"Point"}
}