{
  "type": "Feature",
  "properties": {
    "iso:country":"ES",
    "sg:address":"Calle de Rio Guare\u00d1a, 3",
    "sg:city":"Malaga",
    "sg:orig_category":"Ingeniero",
    "sg:phone":"+34 952 35 37 37",
    "sg:postcode":"29006",
    "sg:province":"M\u00e1laga",
    "wof:name":"Sistemas Electronicos Y Telecomunicacion S. A.",
    "wof:placetype":"venue"
},
  "geometry": {"coordinates":[-4.4469079971,36.7105522156],"type":"Point"}
}