{
  "type": "Feature",
  "properties": {
    "addr:full":"Urb Tancat De L'alter, 5 Picassent Valencia 46220",
    "addr:housenumber":"5",
    "addr:postcode":"46220",
    "addr:street":"Urb",
    "iso:country":"ES",
    "sg:address":"Urb Tancat De L'alter, 5",
    "sg:city":"Picassent",
    "sg:orig_category":"Pintores",
    "sg:phone":"+34 961 22 10 29",
    "sg:postcode":"46220",
    "sg:province":"Valencia",
    "wof:name":"Segrelles Del Pilar Eustaquio",
    "wof:placetype":"venue"
},
  "geometry": {"coordinates":[-0.4868200123,39.3502502441],"type":"Point"}
}