{
  "type": "Feature",
  "properties": {
    "addr:full":"Calle de Germanies, 58 Torrent Valencia 46900",
    "addr:housenumber":"58",
    "addr:postcode":"46900",
    "addr:street":"Calle De Germanies;Valencia",
    "iso:country":"ES",
    "sg:address":"Calle de Germanies, 58",
    "sg:city":"Torrent",
    "sg:orig_category":"Reposter\u00cdas",
    "sg:phone":"+34 961 55 47 56",
    "sg:postcode":"46900",
    "sg:province":"Valencia",
    "wof:name":"Cu\u00f1at Marquez Antonio Salvador",
    "wof:placetype":"venue"
},
  "geometry": {"coordinates":[-0.4720009863,39.4335670471],"type":"Point"}
}