{
  "type": "Feature",
  "properties": {
    "addr:full":"Orbazai, S/n Orbazai Lugo 27297",
    "addr:postcode":"27297",
    "addr:street":"Orbazai S / N",
    "iso:country":"ES",
    "sg:address":"Orbazai, S/n",
    "sg:city":"Orbazai",
    "sg:orig_category":"Charcuter\u00cdas (al Por Mayor)",
    "sg:phone":"+34 982 24 23 83",
    "sg:postcode":"27297",
    "sg:province":"Lugo",
    "wof:name":"Pardo Vila Jaime",
    "wof:placetype":"venue"
},
  "geometry": {"coordinates":[-7.6009187698,43.0232086182],"type":"Point"}
}