{
  "type": "Feature",
  "properties": {
    "iso:country":"ES",
    "sg:address":"Ptge Virreina, 8",
    "sg:city":"Barcelona",
    "sg:orig_category":"Animales (al Por Menor)",
    "sg:phone":"+34 933 17 12 06",
    "sg:postcode":"08001",
    "sg:province":"Barcelona",
    "wof:name":"Aus Ous I Ca\u00d1a S.l.",
    "wof:placetype":"venue"
},
  "geometry": {"coordinates":[2.1708064079,41.3820800781],"type":"Point"}
}