{
  "type": "Feature",
  "properties": {
    "addr:full":"Avda Tenor Fleta, 8 Zaragoza Zaragoza 50007",
    "addr:housenumber":"8",
    "addr:postcode":"50007",
    "addr:street":"Avda Tenor Fleta",
    "iso:country":"ES",
    "sg:address":"Avda Tenor Fleta, 8",
    "sg:city":"Zaragoza",
    "sg:orig_category":"M\u00c9dicos: Estomatolog\u00cda",
    "sg:phone":"+34 976 37 92 54",
    "sg:postcode":"50007",
    "sg:province":"Zaragoza",
    "wof:name":"Gonzalez Izquierdo Jesus",
    "wof:placetype":"venue"
},
  "geometry": {"coordinates":[-0.8853420019,41.6416473389],"type":"Point"}
}