{
  "type": "Feature",
  "properties": {
    "iso:country":"ES",
    "sg:address":"Avda Rey Juan Carlos I, 35",
    "sg:city":"Tarancon",
    "sg:orig_category":"Florister\u00cdas",
    "sg:phone":"+34 969 32 15 99",
    "sg:postcode":"16400",
    "sg:province":"Cuenca",
    "wof:name":"Algarra Melero Felipe",
    "wof:placetype":"venue"
},
  "geometry": {"coordinates":[-3.0036399364,40.0046005249],"type":"Point"}
}