{
  "type": "Feature",
  "properties": {
    "iso:country":"ES",
    "sg:address":"Calle de Manuel Gonzalez, 18",
    "sg:city":"Almoradi",
    "sg:orig_category":"Tapiceros Y Tapiceros",
    "sg:phone":"+34 966 78 04 93",
    "sg:postcode":"03160",
    "sg:province":"Alicante",
    "wof:name":"Reina Ruiz Jose",
    "wof:placetype":"venue"
},
  "geometry": {"coordinates":[-0.7938150167,38.1107559204],"type":"Point"}
}