{
  "type": "Feature",
  "properties": {
    "addr:full":"Calle de Fernando El Catolico, 57 Pina De Ebro Zaragoza 50750",
    "addr:housenumber":"57",
    "addr:postcode":"50750",
    "addr:street":"Calle De Fernando El Catolico",
    "iso:country":"ES",
    "sg:address":"Calle de Fernando El Catolico, 57",
    "sg:city":"Pina De Ebro",
    "sg:orig_category":"Negocio De Materiales De Construcci\u00d3n",
    "sg:phone":"+34 976 16 64 33",
    "sg:postcode":"50750",
    "sg:province":"Zaragoza",
    "wof:name":"Bello Miguel Jose Victor",
    "wof:placetype":"venue"
},
  "geometry": {"coordinates":[-0.5256469846,41.4885559082],"type":"Point"}
}