{
  "type": "Feature",
  "properties": {
    "iso:country":"ES",
    "sg:address":"Calle de Marques De Montortal, 2",
    "sg:city":"Valencia",
    "sg:orig_category":"Caf\u00c9s, Bares, Cervecer\u00cdas",
    "sg:phone":"+34 963 65 08 06",
    "sg:postcode":"46019",
    "sg:province":"Valencia",
    "wof:name":"Capilla Capilla Luis Gonzalo",
    "wof:placetype":"venue"
},
  "geometry": {"coordinates":[-0.3745279908,39.492313385],"type":"Point"}
}