{
  "type": "Feature",
  "properties": {
    "addr:full":"Carrer de Creu (de La), 17 Gata Gorgos Alicante 03740",
    "addr:housenumber":"17",
    "addr:postcode":"03740",
    "addr:street":"Carrer De Creu De La",
    "iso:country":"ES",
    "sg:address":"Carrer de Creu (de La), 17",
    "sg:city":"Gata Gorgos",
    "sg:orig_category":"Promotores Constructores",
    "sg:phone":"+34 965 75 70 26",
    "sg:postcode":"03740",
    "sg:province":"Alicante",
    "wof:name":"Monfort Rosa Jose Luis",
    "wof:placetype":"venue"
},
  "geometry": {"coordinates":[0.0839079991,38.7759056091],"type":"Point"}
}