{
  "type": "Feature",
  "properties": {
    "iso:country":"ES",
    "sg:address":"Calle de San Miguel, 17",
    "sg:city":"Zaragoza",
    "sg:orig_category":"Arquitectos",
    "sg:phone":"+34 976 22 49 93",
    "sg:postcode":"50001",
    "sg:province":"Zaragoza",
    "wof:name":"Navarro Trallero Miguel Angel",
    "wof:placetype":"venue"
},
  "geometry": {"coordinates":[-0.8793609738,41.650680542],"type":"Point"}
}