{
  "type": "Feature",
  "properties": {
    "addr:full":"Carrer de Gran De Gracia, 76 Barcelona Barcelona 08012",
    "addr:housenumber":"76",
    "addr:postcode":"08012",
    "addr:street":"Carrer De Gran De Gracia",
    "iso:country":"ES",
    "sg:address":"Carrer de Gran De Gracia, 76",
    "sg:city":"Barcelona",
    "sg:orig_category":"Zapatos (al Por Menor)",
    "sg:phone":"+34 932 38 76 56",
    "sg:postcode":"08012",
    "sg:province":"Barcelona",
    "wof:name":"Alfonso Sigalat Norberto",
    "wof:placetype":"venue"
},
  "geometry": {"coordinates":[2.1553897858,41.3999519348],"type":"Point"}
}