{
  "type": "Feature",
  "properties": {
    "iso:country":"ES",
    "sg:address":"Calle de Blas De Lezo, 22",
    "sg:city":"Irun",
    "sg:orig_category":"Supermercados Y Hipermercados",
    "sg:phone":"+34 943 61 42 10",
    "sg:postcode":"20301",
    "sg:province":"Guip\u00f9zcoa",
    "wof:name":"Distribucion De Supermercados S. L.",
    "wof:placetype":"venue"
},
  "geometry": {"coordinates":[-1.801946044,43.34116745],"type":"Point"}
}