{
  "type": "Feature",
  "properties": {
    "addr:full":"Calle de Jose Antonio, 12 Arafo Santa Cruz De Tenerife 38550",
    "addr:housenumber":"12",
    "addr:postcode":"38550",
    "addr:street":"Calle De Jose Antonio",
    "iso:country":"ES",
    "sg:address":"Calle de Jose Antonio, 12",
    "sg:city":"Arafo",
    "sg:orig_category":"Ingeniero",
    "sg:phone":"+34 922 51 36 43",
    "sg:postcode":"38550",
    "sg:province":"Santa Cruz De Tenerife",
    "wof:name":"Pinzon Azul S L",
    "wof:placetype":"venue"
},
  "geometry": {"coordinates":[-16.4184131622,28.3391532898],"type":"Point"}
}