{
  "type": "Feature",
  "properties": {
    "iso:country":"ES",
    "sg:address":"Calle de General Mur, 2",
    "sg:city":"Graus",
    "sg:orig_category":"Iglesia Cat\u00d3lica",
    "sg:phone":"+34 974 54 00 93",
    "sg:postcode":"22430",
    "sg:province":"Huesca",
    "wof:name":"Congregacion Carmelitas Misioneras Teresianas",
    "wof:placetype":"venue"
},
  "geometry": {"coordinates":[0.3397000134,42.192024231],"type":"Point"}
}