{
  "type": "Feature",
  "properties": {
    "iso:country":"ES",
    "sg:address":"C.v. Godella, 55",
    "sg:city":"Valencia",
    "sg:orig_category":"Organizaci\u00d3n De Actos, Seminarios Y Congresos",
    "sg:phone":"+34 963 65 17 70",
    "sg:postcode":"46025",
    "sg:province":"Valencia",
    "sg:website":"www.alqueriadelpi.com",
    "wof:name":"Alqueria Del Pi",
    "wof:placetype":"venue"
},
  "geometry": {"coordinates":[-0.3868851066,39.5020751953],"type":"Point"}
}