{
  "type": "Feature",
  "properties": {
    "iso:country":"ES",
    "sg:address":"O Casal, S/n",
    "sg:city":"Casal",
    "sg:orig_category":"Serrer\u00cdas De Madera",
    "sg:phone":"+34 986 55 31 59",
    "sg:postcode":"36668",
    "sg:province":"Pontevedra",
    "wof:name":"Novo Barros Jose Angel",
    "wof:placetype":"venue"
},
  "geometry": {"coordinates":[-8.5659818649,42.5975761414],"type":"Point"}
}