{
  "type": "Feature",
  "properties": {
    "iso:country":"ES",
    "sg:address":"Riera (la), 92",
    "sg:city":"Mataro",
    "sg:orig_category":"Notarios",
    "sg:phone":"+34 937 55 52 80",
    "sg:postcode":"08301",
    "sg:province":"Barcelona",
    "wof:name":"Clavel Jorda Guzman",
    "wof:placetype":"venue"
},
  "geometry": {"coordinates":[2.4439051151,41.5415153503],"type":"Point"}
}