{
  "type": "Feature",
  "properties": {
    "addr:full":"Calle de San Pedro, 16 Zumaia Guip\u00f9zcoa 20750",
    "addr:housenumber":"16",
    "addr:postcode":"20750",
    "addr:street":"Calle De San Pedro;Guipu\u0300Zcoa",
    "iso:country":"ES",
    "sg:address":"Calle de San Pedro, 16",
    "sg:city":"Zumaia",
    "sg:orig_category":"Formaci\u00d3n Continuada (variada)",
    "sg:phone":"+34 943 86 16 36",
    "sg:postcode":"20750",
    "sg:province":"Guip\u00f9zcoa",
    "wof:name":"Alberdi Ibarra Ramon",
    "wof:placetype":"venue"
},
  "geometry": {"coordinates":[-2.2562673092,43.2972602844],"type":"Point"}
}