{
  "type": "Feature",
  "properties": {
    "iso:country":"ES",
    "sg:address":"Calle de Joaquin Benlloch, 2",
    "sg:city":"Valencia",
    "sg:orig_category":"Farmacias",
    "sg:phone":"+34 963 34 27 76",
    "sg:postcode":"46006",
    "sg:province":"Valencia",
    "wof:name":"Ballester Chirivella Rosa",
    "wof:placetype":"venue"
},
  "geometry": {"coordinates":[-0.3780849874,39.4556999207],"type":"Point"}
}