{
  "type": "Feature",
  "properties": {
    "iso:country":"ES",
    "sg:address":"Las Vi\u00f1as, 4",
    "sg:city":"Iru\u00f1a",
    "sg:orig_category":"Plomeros",
    "sg:phone":"+34 948 14 21 62",
    "sg:postcode":"31014",
    "sg:province":"Navarra",
    "wof:name":"Go\u00f1i Zoco Miguel Y Alegria Lacarra Luis S. Cv.",
    "wof:placetype":"venue"
},
  "geometry": {"coordinates":[-1.6583939791,42.826713562],"type":"Point"}
}