{
  "type": "Feature",
  "properties": {
    "iso:country":"ES",
    "sg:address":"Calle de Palomeras, 41",
    "sg:city":"Madrid",
    "sg:orig_category":"Inmobiliaria (agencias)",
    "sg:phone":"+34 917 57 01 51",
    "sg:postcode":"28053",
    "sg:province":"Madrid",
    "sg:website":"www.tecnocasa.es/madrid",
    "wof:name":"Area Sandiego S.l.",
    "wof:placetype":"venue"
},
  "geometry": {"coordinates":[-3.6666133404,40.3891944885],"type":"Point"}
}