{
  "type": "Feature",
  "properties": {
    "addr:full":"Avda Andalucia (de), 11 Frigiliana M\u00e1laga 29788",
    "addr:housenumber":"11",
    "addr:postcode":"29788",
    "addr:street":"Avda Andalucia De",
    "iso:country":"ES",
    "sg:address":"Avda Andalucia (de), 11",
    "sg:city":"Frigiliana",
    "sg:orig_category":"Laboratorios Y Trabajos De Fotograf\u00cda, V\u00cddeo Y Cine",
    "sg:phone":"+34 952 53 40 15",
    "sg:postcode":"29788",
    "sg:province":"M\u00e1laga",
    "wof:name":"Orihuela Martin Antonio",
    "wof:placetype":"venue"
},
  "geometry": {"coordinates":[-3.8941318989,36.7859916687],"type":"Point"}
}