{
  "type": "Feature",
  "properties": {
    "addr:full":"Cno. Carpesa A Moncada, 207 Pueblo Nuevo Valencia 46025",
    "addr:housenumber":"207",
    "addr:postcode":"46025",
    "addr:street":"Carpesa;Moncada",
    "iso:country":"ES",
    "sg:address":"Cno. Carpesa A Moncada, 207",
    "sg:city":"Pueblo Nuevo",
    "sg:orig_category":"Artesan\u00cda",
    "sg:phone":"+34 963 66 95 26",
    "sg:postcode":"46025",
    "sg:province":"Valencia",
    "sg:website":"www.ademascorcho.com",
    "wof:name":"Ademas Corcho S.l.",
    "wof:placetype":"venue"
},
  "geometry": {"coordinates":[-0.3768048882,39.4702377319],"type":"Point"}
}