{
  "type": "Feature",
  "properties": {
    "addr:full":"Avda Gran Via Juan Carlos I, 17 Cieza Murcia 30530",
    "addr:housenumber":"17",
    "addr:postcode":"30530",
    "addr:street":"Avda Gran Via Juan Carlos I",
    "iso:country":"ES",
    "sg:address":"Avda Gran Via Juan Carlos I, 17",
    "sg:city":"Cieza",
    "sg:orig_category":"Empresas De Carpinter\u00cda De Madera",
    "sg:phone":"+34 968 76 00 65",
    "sg:postcode":"30530",
    "sg:province":"Murcia",
    "wof:name":"Lopez Yepes Manuel",
    "wof:placetype":"venue"
},
  "geometry": {"coordinates":[-1.4241739511,38.2379302979],"type":"Point"}
}