{
  "type": "Feature",
  "properties": {
    "addr:full":"Carrer de Merce Rodoreda, 64 Montmelo Barcelona 08160",
    "addr:housenumber":"64",
    "addr:postcode":"08160",
    "addr:street":"Carrer De Merce Rodoreda",
    "iso:country":"ES",
    "sg:address":"Carrer de Merce Rodoreda, 64",
    "sg:city":"Montmelo",
    "sg:orig_category":"Partidos Pol\u00cdticos",
    "sg:phone":"+34 935 72 36 98",
    "sg:postcode":"08160",
    "sg:province":"Barcelona",
    "wof:name":"Iniciativa Per Catalunya",
    "wof:placetype":"venue"
},
  "geometry": {"coordinates":[2.2420709133,41.5514335632],"type":"Point"}
}