{
  "type": "Feature",
  "properties": {
    "addr:full":"Carrer de Esqueis, 25 Rieral De Bigues Barcelona 08415",
    "addr:housenumber":"25",
    "addr:postcode":"08415",
    "addr:street":"Carrer De Esqueis",
    "iso:country":"ES",
    "sg:address":"Carrer de Esqueis, 25",
    "sg:city":"Rieral De Bigues",
    "sg:orig_category":"Empresas De Operaciones Portuarias Y Elevaci\u00d3n De Mercanc\u00cdas",
    "sg:phone":"+34 938 65 77 70",
    "sg:postcode":"08415",
    "sg:province":"Barcelona",
    "wof:name":"Semap Promocions S.l.",
    "wof:placetype":"venue"
},
  "geometry": {"coordinates":[2.2202100754,41.6673088074],"type":"Point"}
}