{
  "type": "Feature",
  "properties": {
    "iso:country":"ES",
    "sg:address":"Carretera De Berria, S/n",
    "sg:city":"Santo\u00f1a",
    "sg:orig_category":"Empresas De Hormig\u00d3n, Hormig\u00d3n Armado Y Pretensado",
    "sg:phone":"+34 942 66 00 06",
    "sg:postcode":"39740",
    "sg:province":"Cantabria",
    "wof:name":"Hermanos Ruigomez S.l.",
    "wof:placetype":"venue"
},
  "geometry": {"coordinates":[-3.4555449486,43.4479560852],"type":"Point"}
}