{
  "type": "Feature",
  "properties": {
    "iso:country":"ES",
    "sg:address":"Calle de Diputacion, 11",
    "sg:city":"Ermua",
    "sg:orig_category":"Agencias De Viajes",
    "sg:phone":"+34 943 17 19 31",
    "sg:postcode":"48260",
    "sg:province":"Vizcaya",
    "sg:website":"www.halconviajes.com",
    "wof:name":"Viajes Halcon S.a.",
    "wof:placetype":"venue"
},
  "geometry": {"coordinates":[-2.5049190521,43.1869087219],"type":"Point"}
}