{
  "type": "Feature",
  "properties": {
    "iso:country":"ES",
    "sg:address":"Praj Barranco Molax, 17",
    "sg:city":"Barranco Molax",
    "sg:orig_category":"Frutos Y Legumbres",
    "sg:phone":"+34 968 77 07 91",
    "sg:postcode":"30550",
    "sg:province":"Murcia",
    "wof:name":"Frutas Torero S.a.",
    "wof:placetype":"venue"
},
  "geometry": {"coordinates":[-1.3944859505,38.2074737549],"type":"Point"}
}