{
  "type": "Feature",
  "properties": {
    "addr:full":"Calle de Santiago, 17 Valladolid Valladolid 47001",
    "addr:housenumber":"17",
    "addr:postcode":"47001",
    "addr:street":"Calle De Santiago",
    "iso:country":"ES",
    "sg:address":"Calle de Santiago, 17",
    "sg:city":"Valladolid",
    "sg:orig_category":"Organizaci\u00d3n De Actos, Seminarios Y Congresos",
    "sg:phone":"+34 983 35 33 99",
    "sg:postcode":"47001",
    "sg:province":"Valladolid",
    "wof:name":"Publicidad Gis S. A.",
    "wof:placetype":"venue"
},
  "geometry": {"coordinates":[-4.7287240028,41.6498336792],"type":"Point"}
}