{
  "type": "Feature",
  "properties": {
    "iso:country":"ES",
    "sg:address":"Plaz Alonso De Vandelvira, 4",
    "sg:city":"Sabiote",
    "sg:orig_category":"Sanatorios M\u00c9dico",
    "sg:phone":"+34 953 77 36 03",
    "sg:postcode":"23410",
    "sg:province":"Ja\u00e9n",
    "wof:name":"Ayuntamiento De Sabiote",
    "wof:placetype":"venue"
},
  "geometry": {"coordinates":[-3.2784824371,38.0810203552],"type":"Point"}
}