{
  "type": "Feature",
  "properties": {
    "iso:country":"ES",
    "sg:address":"Carrer de Major, 5",
    "sg:city":"Sitges",
    "sg:orig_category":"Alimentaci\u00d3n General (al Por Menor)",
    "sg:phone":"+34 938 94 03 60",
    "sg:postcode":"08870",
    "sg:province":"Barcelona",
    "wof:name":"Badia Iglesias Josefa",
    "wof:placetype":"venue"
},
  "geometry": {"coordinates":[1.8112610579,41.2353515625],"type":"Point"}
}