{
  "type": "Feature",
  "properties": {
    "addr:full":"Rua San Eufrasio, 161 Lugo Lugo 27002",
    "addr:housenumber":"161",
    "addr:postcode":"27002",
    "addr:street":"Rua San Eufrasio",
    "iso:country":"ES",
    "sg:address":"Rua San Eufrasio, 161",
    "sg:city":"Lugo",
    "sg:orig_category":"Molduras, Junquillos, Listones Y Molduras Perforadas",
    "sg:phone":"+34 982 22 10 78",
    "sg:postcode":"27002",
    "sg:province":"Lugo",
    "wof:name":"Martinez Lamas Manuela",
    "wof:placetype":"venue"
},
  "geometry": {"coordinates":[-7.5474491119,43.0100402832],"type":"Point"}
}