{
  "type": "Feature",
  "properties": {
    "iso:country":"ES",
    "sg:address":"Calle de Mimosas Las, 124",
    "sg:city":"Poligono Industrial De Arinaga",
    "sg:orig_category":"Congelados: Productos Alimentarios (fabricaci\u00d3n, Al Por Mayor)",
    "sg:phone":"+34 928 18 01 29",
    "sg:postcode":"35118",
    "sg:province":"Las Palmas",
    "wof:name":"Congelados Herbania S.a.",
    "wof:placetype":"venue"
},
  "geometry": {"coordinates":[-15.4319887161,27.8808555603],"type":"Point"}
}