{
  "type": "Feature",
  "properties": {
    "addr:full":"Calle de Duquesa Villahermosa, 129 Zaragoza Zaragoza 50009",
    "addr:housenumber":"129",
    "addr:postcode":"50009",
    "addr:street":"Calle De Duquesa Villahermosa",
    "iso:country":"ES",
    "sg:address":"Calle de Duquesa Villahermosa, 129",
    "sg:city":"Zaragoza",
    "sg:orig_category":"Peluquer\u00cdas, Peluquer\u00cda Mixta",
    "sg:phone":"+34 976 55 89 19",
    "sg:postcode":"50009",
    "sg:province":"Zaragoza",
    "wof:name":"Sebastian Artal Ana Belen",
    "wof:placetype":"venue"
},
  "geometry": {"coordinates":[-0.9104599953,41.6450386047],"type":"Point"}
}