{
  "type": "Feature",
  "properties": {
    "iso:country":"ES",
    "sg:address":"Avda Infante Don Luis (del), 16",
    "sg:city":"Boadilla Del Monte",
    "sg:orig_category":"Inform\u00c1tica (estudios, Servicios, Asesor\u00cda, Formaci\u00d3n)",
    "sg:phone":"+34 916 33 77 24",
    "sg:postcode":"28660",
    "sg:province":"Madrid",
    "wof:name":"Atlas Digital Net S.l.",
    "wof:placetype":"venue"
},
  "geometry": {"coordinates":[-3.8969109058,40.402053833],"type":"Point"}
}