{
  "type": "Feature",
  "properties": {
    "iso:country":"ES",
    "sg:address":"Talaia Sa, 3",
    "sg:city":"S. Josep Talaia",
    "sg:orig_category":"Institutos De Belleza",
    "sg:phone":"+34 971 80 01 95",
    "sg:postcode":"07830",
    "sg:province":"Islas Baleares",
    "wof:name":"Tur I Prats De Pass Cb",
    "wof:placetype":"venue"
},
  "geometry": {"coordinates":[1.2928240299,38.9215202332],"type":"Point"}
}