{
  "type": "Feature",
  "properties": {
    "addr:full":"Trva Troncoso, 2 Guarda Pontevedra 36780",
    "addr:housenumber":"2",
    "addr:postcode":"36780",
    "addr:street":"Trva Troncoso",
    "iso:country":"ES",
    "sg:address":"Trva Troncoso, 2",
    "sg:city":"Guarda",
    "sg:classifiers":[
        {
            "category":"Casinos & Gambling",
            "type":"Entertainment"
        }
    ],
    "sg:phone":"+34 986 61 00 04",
    "sg:postcode":"36780",
    "sg:province":"Pontevedra",
    "sg:tags":[
        "locale",
        "de",
        "juego"
    ],
    "wof:name":"Casino De La Guardia",
    "wof:placetype":"venue"
},
  "geometry": {"coordinates":[-8.8713140488,41.9025039673],"type":"Point"}
}