{
  "type": "Feature",
  "properties": {
    "addr:full":"Pase Dr Fernandez Iparraguirre, 8 Guadalajara Guadalajara 19001",
    "addr:housenumber":"8",
    "addr:postcode":"19001",
    "addr:street":"Pase Dr Fernandez Iparraguirre",
    "iso:country":"ES",
    "sg:address":"Pase Dr Fernandez Iparraguirre, 8",
    "sg:city":"Guadalajara",
    "sg:orig_category":"Ense\u00d1anza, Formaci\u00d3n Profesional: Aprendizaje",
    "sg:phone":"+34 949 22 04 42",
    "sg:postcode":"19001",
    "sg:province":"Guadalajara",
    "wof:name":"Bt Espa\u00d1a Compa\u00d1ia De Servicios Globales De Telecomunicaciones S.a.u.",
    "wof:placetype":"venue"
},
  "geometry": {"coordinates":[-3.1662700176,40.6300086975],"type":"Point"}
}