{
  "type": "Feature",
  "properties": {
    "addr:full":"Calle de Miguel Villanueva, 10 Logro\u00f1o La Rioja 26001",
    "addr:housenumber":"10",
    "addr:postcode":"26001",
    "addr:street":"Calle De Miguel Villanueva;Rioja",
    "iso:country":"ES",
    "sg:address":"Calle de Miguel Villanueva, 10",
    "sg:city":"Logro\u00f1o",
    "sg:orig_category":"Empresas De Desmonte",
    "sg:phone":"+34 941 24 19 73",
    "sg:postcode":"26001",
    "sg:province":"La Rioja",
    "wof:name":"Excavaciones Transportes Aridos La Union S.l.",
    "wof:placetype":"venue"
},
  "geometry": {"coordinates":[-2.4449241161,42.4639778137],"type":"Point"}
}