{
  "type": "Feature",
  "properties": {
    "addr:full":"Calle de Esperanza, 22 Ciudad Real Ciudad Real 13003",
    "addr:housenumber":"22",
    "addr:postcode":"13003",
    "addr:street":"Calle De Esperanza",
    "iso:country":"ES",
    "sg:address":"Calle de Esperanza, 22",
    "sg:city":"Ciudad Real",
    "sg:orig_category":"Suministros Y Materiales Industriales",
    "sg:phone":"+34 926 22 22 54",
    "sg:postcode":"13003",
    "sg:province":"Ciudad Real",
    "wof:name":"Agustin Araque Mu\u00f1oz Y Otros C.b.",
    "wof:placetype":"venue"
},
  "geometry": {"coordinates":[-3.9313600063,38.9931335449],"type":"Point"}
}