{
  "type": "Feature",
  "properties": {
    "addr:full":"Calle de Pablo Neruda, 30 Zaragoza Zaragoza 50015",
    "addr:housenumber":"30",
    "addr:postcode":"50015",
    "addr:street":"Calle De Pablo Neruda",
    "iso:country":"ES",
    "sg:address":"Calle de Pablo Neruda, 30",
    "sg:city":"Zaragoza",
    "sg:orig_category":"Electrodom\u00c9sticos (al Por Menor)",
    "sg:phone":"+34 976 52 15 54",
    "sg:postcode":"50015",
    "sg:province":"Zaragoza",
    "wof:name":"Valero Garcia Valentin",
    "wof:placetype":"venue"
},
  "geometry": {"coordinates":[-0.8832330108,41.670009613],"type":"Point"}
}