{
  "type": "Feature",
  "properties": {
    "addr:full":"Carrer de Tibidabo, 68 Barbera Valles Barcelona 08210",
    "addr:housenumber":"68",
    "addr:postcode":"08210",
    "addr:street":"Carrer De Tibidabo",
    "iso:country":"ES",
    "sg:address":"Carrer de Tibidabo, 68",
    "sg:city":"Barbera Valles",
    "sg:orig_category":"Farmacias",
    "sg:phone":"+34 937 19 01 01",
    "sg:postcode":"08210",
    "sg:province":"Barcelona",
    "wof:name":"Blanca Gutierrez Jose Maria",
    "wof:placetype":"venue"
},
  "geometry": {"coordinates":[2.1148869991,41.5115852356],"type":"Point"}
}