{
  "type": "Feature",
  "properties": {
    "addr:full":"Rua Couto Pi\u00d1eiro, 18 Vigo Pontevedra 36204",
    "addr:housenumber":"18",
    "addr:postcode":"36204",
    "addr:street":"Rua Couto Pin\u0303Eiro",
    "iso:country":"ES",
    "sg:address":"Rua Couto Pi\u00d1eiro, 18",
    "sg:city":"Vigo",
    "sg:orig_category":"Electromec\u00c1nica",
    "sg:phone":"+34 986 41 88 49",
    "sg:postcode":"36204",
    "sg:province":"Pontevedra",
    "wof:name":"Vieitez Alen Camilo",
    "wof:placetype":"venue"
},
  "geometry": {"coordinates":[-8.7110013962,42.2301750183],"type":"Point"}
}