{
  "type": "Feature",
  "properties": {
    "iso:country":"ES",
    "sg:address":"Carrer de Duran I Bas, 3",
    "sg:city":"Barcelona",
    "sg:orig_category":"Restaurantes",
    "sg:phone":"+34 933 02 15 87",
    "sg:postcode":"08002",
    "sg:province":"Barcelona",
    "wof:name":"Espi\u00f1a Fernandez Antonio",
    "wof:placetype":"venue"
},
  "geometry": {"coordinates":[2.1738209724,41.3854408264],"type":"Point"}
}