{
  "type": "Feature",
  "properties": {
    "iso:country":"ES",
    "sg:address":"Plaz Mercado, S/n",
    "sg:city":"Fuente S. Esteban",
    "sg:orig_category":"Ense\u00d1anza, Formaci\u00d3n Profesional: Aprendizaje",
    "sg:phone":"+34 923 44 09 57",
    "sg:postcode":"37200",
    "sg:province":"Salamanca",
    "wof:name":"Servicio Territorial De Agricultura Y Ganaderia",
    "wof:placetype":"venue"
},
  "geometry": {"coordinates":[-6.1650328636,40.826171875],"type":"Point"}
}