{
  "type": "Feature",
  "properties": {
    "iso:country":"ES",
    "sg:address":"Calle de Yecla, 14",
    "sg:city":"Valencia",
    "sg:orig_category":"Centros Empresariales",
    "sg:phone":"+34 963 62 97 66",
    "sg:postcode":"46021",
    "sg:province":"Valencia",
    "wof:name":"Ortega Aparicio Pedro Jose",
    "wof:placetype":"venue"
},
  "geometry": {"coordinates":[-0.3509860039,39.4723625183],"type":"Point"}
}