{
  "type": "Feature",
  "properties": {
    "addr:full":"Calle de Candida Carbonell, 14 Denia Alicante 03700",
    "addr:housenumber":"14",
    "addr:postcode":"03700",
    "addr:street":"Calle De Candida Carbonell",
    "iso:country":"ES",
    "sg:address":"Calle de Candida Carbonell, 14",
    "sg:city":"Denia",
    "sg:orig_category":"Instalaci\u00d3n De Aspiraci\u00d3n De Gases Y Humos",
    "sg:phone":"+34 965 78 04 93",
    "sg:postcode":"03700",
    "sg:province":"Alicante",
    "wof:name":"Gas Del Marquesat S.l.",
    "wof:placetype":"venue"
},
  "geometry": {"coordinates":[0.1102939993,38.8404541016],"type":"Point"}
}