{
  "type": "Feature",
  "properties": {
    "iso:country":"ES",
    "sg:address":"Granada, S/n",
    "sg:city":"Montilla",
    "sg:orig_category":"Loter\u00cda Y T\u00d3mbola",
    "sg:phone":"+34 957 65 30 30",
    "sg:postcode":"14550",
    "sg:province":"C\u00f3rdoba",
    "wof:name":"Gomez Luque Alfonso",
    "wof:placetype":"venue"
},
  "geometry": {"coordinates":[-4.6337790489,37.5892333984],"type":"Point"}
}