{
  "type": "Feature",
  "properties": {
    "iso:country":"ES",
    "sg:address":"Calle de Baza, S/n",
    "sg:city":"Albolote",
    "sg:orig_category":"Comercio De Hierro",
    "sg:phone":"+34 958 46 70 09",
    "sg:postcode":"18220",
    "sg:province":"Granada",
    "sg:website":"www.cdl.es",
    "wof:name":"Hierros Guadalquivir S.a.",
    "wof:placetype":"venue"
},
  "geometry": {"coordinates":[-3.6438014507,37.2280883789],"type":"Point"}
}