{
  "type": "Feature",
  "properties": {
    "addr:full":"Cmno Valeriano Perez, 21 Guamasa Santa Cruz De Tenerife 38330",
    "addr:housenumber":"21",
    "addr:postcode":"38330",
    "addr:street":"Cmno Valeriano Perez",
    "iso:country":"ES",
    "sg:address":"Cmno Valeriano Perez, 21",
    "sg:city":"Guamasa",
    "sg:orig_category":"Asesor\u00cda De Formaci\u00d3n Y Gesti\u00d3n De Personal",
    "sg:phone":"+34 922 63 79 35",
    "sg:postcode":"38330",
    "sg:province":"Santa Cruz De Tenerife",
    "wof:name":"Asesoria Baez Gonzalez S.l.",
    "wof:placetype":"venue"
},
  "geometry": {"coordinates":[-16.2548561096,28.4698104858],"type":"Point"}
}