{
  "type": "Feature",
  "properties": {
    "iso:country":"ES",
    "sg:address":"Ctra Palma Del Rio (villarrubia), 220",
    "sg:city":"Villarrubia",
    "sg:orig_category":"Empresas De Carpinter\u00cda Met\u00c1lica",
    "sg:phone":"+34 957 32 72 32",
    "sg:postcode":"14710",
    "sg:province":"C\u00f3rdoba",
    "wof:name":"Segovia Rodriguez Manuel",
    "wof:placetype":"venue"
},
  "geometry": {"coordinates":[-4.9146289825,37.8490753174],"type":"Point"}
}