{
  "type": "Feature",
  "properties": {
    "addr:full":"Calle de Don Juan De Austria, 34 Valencia Valencia 46002",
    "addr:housenumber":"34",
    "addr:postcode":"46002",
    "addr:street":"Calle De Don Juan De Austria",
    "iso:country":"ES",
    "sg:address":"Calle de Don Juan De Austria, 34",
    "sg:city":"Valencia",
    "sg:orig_category":"Financiaci\u00d3n Y Cr\u00c9ditos",
    "sg:phone":"+34 963 53 01 23",
    "sg:postcode":"46002",
    "sg:province":"Valencia",
    "wof:name":"Inmoactivos S.l.",
    "wof:placetype":"venue"
},
  "geometry": {"coordinates":[-0.3717150986,39.4703063965],"type":"Point"}
}