{
  "type": "Feature",
  "properties": {
    "addr:full":"Carrer de Osona, 6 Barcelona Barcelona 08023",
    "addr:housenumber":"6",
    "addr:postcode":"08023",
    "addr:street":"Carrer De Osona",
    "iso:country":"ES",
    "sg:address":"Carrer de Osona, 6",
    "sg:city":"Barcelona",
    "sg:orig_category":"Suministros Para Hoteles",
    "sg:phone":"+34 932 11 47 90",
    "sg:postcode":"08023",
    "sg:province":"Barcelona",
    "wof:name":"Silesia Espa\u00f1a S.a.",
    "wof:placetype":"venue"
},
  "geometry": {"coordinates":[2.1448869705,41.4078330994],"type":"Point"}
}