{
  "type": "Feature",
  "properties": {
    "addr:full":"Carrer de Andreu Llambrich, 51 Ametlla Mar Tarragona 43860",
    "addr:housenumber":"51",
    "addr:postcode":"43860",
    "addr:street":"Carrer De Andreu Llambrich",
    "iso:country":"ES",
    "sg:address":"Carrer de Andreu Llambrich, 51",
    "sg:city":"Ametlla Mar",
    "sg:orig_category":"Alimentaci\u00d3n General (al Por Menor)",
    "sg:phone":"+34 977 45 60 88",
    "sg:postcode":"43860",
    "sg:province":"Tarragona",
    "wof:name":"Marsal Callau Tomas Manuel",
    "wof:placetype":"venue"
},
  "geometry": {"coordinates":[0.7992730141,40.8853607178],"type":"Point"}
}