{
  "type": "Feature",
  "properties": {
    "addr:full":"Calle de Abu Zeyan, S/n Denia Alicante 03700",
    "addr:housenumber":"s",
    "addr:postcode":"03700",
    "addr:street":"Calle De Abu Zeyan;/ N",
    "iso:country":"ES",
    "sg:address":"Calle de Abu Zeyan, S/n",
    "sg:city":"Denia",
    "sg:orig_category":"Reposter\u00cdas",
    "sg:phone":"+34 966 42 36 04",
    "sg:postcode":"03700",
    "sg:province":"Alicante",
    "wof:name":"Gonzalez Sapena Jose",
    "wof:placetype":"venue"
},
  "geometry": {"coordinates":[0.0840215012,38.8309745789],"type":"Point"}
}