{
  "type": "Feature",
  "properties": {
    "addr:full":"Av Abat Marcet, 75 Terrassa Barcelona 08225",
    "addr:housenumber":"75",
    "addr:postcode":"08225",
    "addr:street":"Av Abat Marcet",
    "iso:country":"ES",
    "sg:address":"Av Abat Marcet, 75",
    "sg:city":"Terrassa",
    "sg:classifiers":[
        {
            "category":"Autos & Motor Vehicles",
            "subcategory":"Automobile Sales",
            "type":"Retail Goods"
        }
    ],
    "sg:phone":"+34 937 35 85 85",
    "sg:postcode":"08225",
    "sg:province":"Barcelona",
    "wof:name":"Lucia Lucia Julio",
    "wof:placetype":"venue"
},
  "geometry": {"coordinates":[2.0106720924,41.5747070312],"type":"Point"}
}