{
  "type": "Feature",
  "properties": {
    "addr:full":"Calle de Telletxe, 34 Algorta Vizcaya 48993",
    "addr:housenumber":"34",
    "addr:postcode":"48993",
    "addr:street":"Calle De Telletxe",
    "iso:country":"ES",
    "sg:address":"Calle de Telletxe, 34",
    "sg:city":"Algorta",
    "sg:orig_category":"Compraventa De Antig\u00dcedades",
    "sg:phone":"+34 944 60 84 90",
    "sg:postcode":"48993",
    "sg:province":"Vizcaya",
    "wof:name":"Busturia Echeandia Inmaculada De",
    "wof:placetype":"venue"
},
  "geometry": {"coordinates":[-3.011220932,43.3555335999],"type":"Point"}
}