{
  "type": "Feature",
  "properties": {
    "iso:country":"ES",
    "sg:address":"Calle de Meteorologo Fco. Garcia, 42",
    "sg:city":"Villafranqueza - Palamo",
    "sg:orig_category":"Alquiler De Muebles",
    "sg:phone":"+34 965 18 50 74",
    "sg:postcode":"03112",
    "sg:province":"Alicante",
    "wof:name":"Sillas Jose S.l.",
    "wof:placetype":"venue"
},
  "geometry": {"coordinates":[-0.4690259993,38.4094772339],"type":"Point"}
}