{
  "type": "Feature",
  "properties": {
    "iso:country":"ES",
    "sg:address":"Av Generalitat, 41",
    "sg:city":"Santa Coloma De Gramenet",
    "sg:orig_category":"Ropa Para Ni\u00d1os (al Por Menor)",
    "sg:phone":"+34 934 66 20 44",
    "sg:postcode":"08922",
    "sg:province":"Barcelona",
    "wof:name":"Confecciones Fema S.a.",
    "wof:placetype":"venue"
},
  "geometry": {"coordinates":[2.2107889652,41.4476547241],"type":"Point"}
}