{
  "type": "Feature",
  "properties": {
    "addr:full":"Plaz San Sebastian, 11 Orihuela Alicante 03300",
    "addr:housenumber":"11",
    "addr:postcode":"03300",
    "addr:street":"Plaz San Sebastian",
    "iso:country":"ES",
    "sg:address":"Plaz San Sebastian, 11",
    "sg:city":"Orihuela",
    "sg:orig_category":"Internados & Ense\u00d1anza Privada",
    "sg:phone":"+34 965 30 29 48",
    "sg:postcode":"03300",
    "sg:province":"Alicante",
    "wof:name":"Religiosas De Jesus Maria",
    "wof:placetype":"venue"
},
  "geometry": {"coordinates":[-0.9469810128,38.0824127197],"type":"Point"}
}