{
  "type": "Feature",
  "properties": {
    "addr:full":"Pase Extremadura, 21 Casar Caceres C\u00e1ceres 10190",
    "addr:housenumber":"21",
    "addr:postcode":"10190",
    "addr:street":"Extremadura;Ca\u0301Ceres",
    "iso:country":"ES",
    "sg:address":"Pase Extremadura, 21",
    "sg:city":"Casar Caceres",
    "sg:orig_category":"Organizaci\u00d3n De Actos, Seminarios Y Congresos",
    "sg:phone":"+34 927 29 02 46",
    "sg:postcode":"10190",
    "sg:province":"C\u00e1ceres",
    "wof:name":"Casa Claudio S.l.",
    "wof:placetype":"venue"
},
  "geometry": {"coordinates":[-6.4156990051,39.5572166443],"type":"Point"}
}