{
  "type": "Feature",
  "properties": {
    "addr:full":"Carretera De Burgos-valladolid, Km. 0030,0 Villaquiran Infantes Burgos 09226",
    "addr:postcode":"09226",
    "addr:street":"Carretera De Burgos-Valladolid Km. 0030,0 Villaquiran Infantes",
    "iso:country":"ES",
    "sg:address":"Carretera De Burgos-valladolid, Km. 0030,0",
    "sg:city":"Villaquiran Infantes",
    "sg:orig_category":"Cajas Para Embalar",
    "sg:phone":"+34 947 16 11 80",
    "sg:postcode":"09226",
    "sg:province":"Burgos",
    "sg:website":"www.cajaruraldeburgos.es",
    "wof:name":"Caja Rural De Burgos",
    "wof:placetype":"venue"
},
  "geometry": {"coordinates":[-4.00730896,42.1751365662],"type":"Point"}
}