{
  "type": "Feature",
  "properties": {
    "addr:full":"Carrer de Josep Anselm Clave (de), S/n Vila-seca Tarragona 43480",
    "addr:postcode":"43480",
    "addr:street":"Carrer De Josep Anselm Clave De S / N",
    "iso:country":"ES",
    "sg:address":"Carrer de Josep Anselm Clave (de), S/n",
    "sg:city":"Vila-seca",
    "sg:orig_category":"Inmobiliaria (agencias)",
    "sg:phone":"+34 977 39 36 17",
    "sg:postcode":"43480",
    "sg:province":"Tarragona",
    "wof:name":"Finques Bon Habitatge S.l.",
    "wof:placetype":"venue"
},
  "geometry": {"coordinates":[1.1487400532,41.1118850708],"type":"Point"}
}