{
  "type": "Feature",
  "properties": {
    "iso:country":"ES",
    "sg:address":"Carrer de Ronda Del Pedregar, S/n",
    "sg:city":"Montmelo",
    "sg:orig_category":"Maquinaria Para Industrias Diversas",
    "sg:phone":"+34 935 68 36 33",
    "sg:postcode":"08160",
    "sg:province":"Barcelona",
    "wof:name":"Autoequip Iberica S.a.",
    "wof:placetype":"venue"
},
  "geometry": {"coordinates":[2.2513799667,41.5548171997],"type":"Point"}
}