{
  "type": "Feature",
  "properties": {
    "addr:full":"Cno Los Merinales (p I Fuente Del Rey), 2 Dos Hermanas Sevilla 41700",
    "addr:housenumber":"2",
    "addr:postcode":"41700",
    "addr:street":"Cno Los Merinales P;Del Rey;Sevilla",
    "iso:country":"ES",
    "sg:address":"Cno Los Merinales (p I Fuente Del Rey), 2",
    "sg:city":"Dos Hermanas",
    "sg:orig_category":"Suministros Y Materiales Industriales",
    "sg:phone":"+34 954 68 99 20",
    "sg:postcode":"41700",
    "sg:province":"Sevilla",
    "wof:name":"Blumaq S.a.",
    "wof:placetype":"venue"
},
  "geometry": {"coordinates":[-5.9281339645,37.2829055786],"type":"Point"}
}