{
  "type": "Feature",
  "properties": {
    "addr:full":"Carr Doctor Robert, 148 Badalona Barcelona 08915",
    "addr:housenumber":"148",
    "addr:postcode":"08915",
    "addr:street":"Carr Doctor Robert",
    "iso:country":"ES",
    "sg:address":"Carr Doctor Robert, 148",
    "sg:city":"Badalona",
    "sg:orig_category":"Mec\u00c1nico Del Autom\u00d3vil",
    "sg:phone":"+34 933 99 69 24",
    "sg:postcode":"08915",
    "sg:province":"Barcelona",
    "wof:name":"Dominguez Gomez Jesus",
    "wof:placetype":"venue"
},
  "geometry": {"coordinates":[2.2428939342,41.4600105286],"type":"Point"}
}