{
  "type": "Feature",
  "properties": {
    "iso:country":"ES",
    "sg:address":"Calle de Botavara, 29",
    "sg:city":"Algeciras",
    "sg:orig_category":"Inmobiliaria (agencias)",
    "sg:phone":"+34 956 57 36 56",
    "sg:postcode":"11207",
    "sg:province":"C\u00e1diz",
    "wof:name":"Magapla S.l.",
    "wof:placetype":"venue"
},
  "geometry": {"coordinates":[-5.439312458,36.114276886],"type":"Point"}
}