{
  "type": "Feature",
  "properties": {
    "iso:country":"ES",
    "sg:address":"Carrer de Pi I Gibert, 22",
    "sg:city":"S. Adria Besos",
    "sg:orig_category":"Caf\u00c9s, Bares, Cervecer\u00cdas",
    "sg:phone":"+34 933 81 63 71",
    "sg:postcode":"08930",
    "sg:province":"Barcelona",
    "wof:name":"Tejeda Castillo Jordi",
    "wof:placetype":"venue"
},
  "geometry": {"coordinates":[2.2153689861,41.4305000305],"type":"Point"}
}