{
  "type": "Feature",
  "properties": {
    "iso:country":"ES",
    "sg:address":"Calle de Castilla, 31",
    "sg:city":"Ciudad Real",
    "sg:orig_category":"Mec\u00c1nico Del Autom\u00d3vil",
    "sg:phone":"+34 926 25 46 06",
    "sg:postcode":"13004",
    "sg:province":"Ciudad Real",
    "wof:name":"Paton Pinilla Miguel",
    "wof:placetype":"venue"
},
  "geometry": {"coordinates":[-3.9182093143,38.979839325],"type":"Point"}
}