{
  "type": "Feature",
  "properties": {
    "iso:country":"ES",
    "sg:address":"Calle de Donantes De Sangre, 38",
    "sg:city":"Menasalbas",
    "sg:orig_category":"Estudios, Instalaci\u00d3n De Climatizaci\u00d3n",
    "sg:phone":"+34 925 40 70 14",
    "sg:postcode":"45128",
    "sg:province":"Toledo",
    "wof:name":"Rodriguez Garcia Fidela",
    "wof:placetype":"venue"
},
  "geometry": {"coordinates":[-4.2910637856,39.6383705139],"type":"Point"}
}