{
  "type": "Feature",
  "properties": {
    "addr:full":"Barr Arenas (las), S/n Arenas Cantabria 39593",
    "addr:postcode":"39593",
    "addr:street":"Las S / N",
    "iso:country":"ES",
    "sg:address":"Barr Arenas (las), S/n",
    "sg:city":"Arenas",
    "sg:orig_category":"Fabricaci\u00d3n De Juegos Y Juguetes",
    "sg:phone":"+34 942 70 96 65",
    "sg:postcode":"39593",
    "sg:province":"Cantabria",
    "wof:name":"Artesania Latina S.a.",
    "wof:placetype":"venue"
},
  "geometry": {"coordinates":[-4.0500340462,43.1861534119],"type":"Point"}
}