{
  "type": "Feature",
  "properties": {
    "addr:full":"Avda Valladolid, 26 Valencia Valencia 46020",
    "addr:housenumber":"26",
    "addr:postcode":"46020",
    "addr:street":"Avda Valladolid",
    "iso:country":"ES",
    "sg:address":"Avda Valladolid, 26",
    "sg:city":"Valencia",
    "sg:orig_category":"Plomeros",
    "sg:phone":"+34 963 61 58 97",
    "sg:postcode":"46020",
    "sg:province":"Valencia",
    "wof:name":"Martinez Aguilar Joaquin",
    "wof:placetype":"venue"
},
  "geometry": {"coordinates":[-0.3597790003,39.4887390137],"type":"Point"}
}