{
  "type": "Feature",
  "properties": {
    "iso:country":"ES",
    "sg:address":"Calle de Argensola, 21",
    "sg:city":"Madrid",
    "sg:orig_category":"M\u00c9dicos: Cirug\u00cda Pl\u00c1stica, Reconstructiva Y Est\u00c9tica",
    "sg:phone":"+34 917 02 07 22",
    "sg:postcode":"28004",
    "sg:province":"Madrid",
    "wof:name":"Centro Del Tratamiento Estetico Corporal S.l.",
    "wof:placetype":"venue"
},
  "geometry": {"coordinates":[-3.6943628788,40.4260482788],"type":"Point"}
}