{
  "type": "Feature",
  "properties": {
    "addr:full":"Calle de Alfonso De Castro, 23 Salamanca Salamanca 37005",
    "addr:housenumber":"23",
    "addr:postcode":"37005",
    "addr:street":"Calle De Alfonso De Castro",
    "iso:country":"ES",
    "sg:address":"Calle de Alfonso De Castro, 23",
    "sg:city":"Salamanca",
    "sg:orig_category":"Cajas Para Embalar",
    "sg:phone":"+34 923 23 55 50",
    "sg:postcode":"37005",
    "sg:province":"Salamanca",
    "wof:name":"Caja Rural Provincial De Salamanca",
    "wof:placetype":"venue"
},
  "geometry": {"coordinates":[-5.659705162,40.9734916687],"type":"Point"}
}