{
  "type": "Feature",
  "properties": {
    "addr:full":"C/ Alginet, 1 Elche Alicante 03202",
    "addr:housenumber":"1",
    "addr:postcode":"03202",
    "addr:street":"C / Alginet",
    "iso:country":"ES",
    "sg:address":"C/ Alginet, 1",
    "sg:city":"Elche",
    "sg:orig_category":"Centros De Coordinaci\u00d3n",
    "sg:phone":"+34 965 45 50 43",
    "sg:postcode":"03202",
    "sg:province":"Alicante",
    "sg:website":"www.ibercal.com",
    "wof:name":"Iberica De Control Tecnico Y Gestion De Calidad S.l.",
    "wof:placetype":"venue"
},
  "geometry": {"coordinates":[-0.6804890037,38.2738494873],"type":"Point"}
}