{
  "type": "Feature",
  "properties": {
    "addr:full":"Carr Algemesi, 3 Santa Eulalia Islas Baleares 07840",
    "addr:housenumber":"3",
    "addr:postcode":"07840",
    "addr:street":"Carr Algemesi",
    "iso:country":"ES",
    "sg:address":"Carr Algemesi, 3",
    "sg:city":"Santa Eulalia",
    "sg:orig_category":"Juegos Y Juguetes (al Por Menor)",
    "sg:phone":"+34 971 33 27 60",
    "sg:postcode":"07840",
    "sg:province":"Islas Baleares",
    "wof:name":"Di-ver Shop 2005 S.l.",
    "wof:placetype":"venue"
},
  "geometry": {"coordinates":[2.9117100239,39.6136398315],"type":"Point"}
}