{
  "type": "Feature",
  "properties": {
    "iso:country":"ES",
    "sg:address":"Plaz Dr Latino Salgueiro, 8",
    "sg:city":"Gondomar",
    "sg:orig_category":"Bancos",
    "sg:phone":"+34 986 36 01 37",
    "sg:postcode":"36380",
    "sg:province":"Pontevedra",
    "wof:name":"Banco Espa\u00f1ol De Credito S.a.",
    "wof:placetype":"venue"
},
  "geometry": {"coordinates":[-8.7611093521,42.1116867065],"type":"Point"}
}