{
  "type": "Feature",
  "properties": {
    "addr:full":"Calle de Lope De Vega, 54 Manzanares Ciudad Real 13200",
    "addr:housenumber":"54",
    "addr:postcode":"13200",
    "addr:street":"Calle De Lope De Vega",
    "iso:country":"ES",
    "sg:address":"Calle de Lope De Vega, 54",
    "sg:city":"Manzanares",
    "sg:orig_category":"Iglesia Cat\u00d3lica",
    "sg:phone":"+34 926 61 00 98",
    "sg:postcode":"13200",
    "sg:province":"Ciudad Real",
    "wof:name":"Parroquia Nuestra Se\u00f1ora De Altagracia",
    "wof:placetype":"venue"
},
  "geometry": {"coordinates":[-3.3701190948,38.9996681213],"type":"Point"}
}