{
  "type": "Feature",
  "properties": {
    "iso:country":"ES",
    "sg:address":"Carrer de Prim, 3",
    "sg:city":"S. Celoni",
    "sg:orig_category":"Peluqueros: De Se\u00d1oras",
    "sg:phone":"+34 938 67 27 62",
    "sg:postcode":"08470",
    "sg:province":"Barcelona",
    "wof:name":"Morella Travesa Montserrat",
    "wof:placetype":"venue"
},
  "geometry": {"coordinates":[2.463572979,41.7227363586],"type":"Point"}
}