{
  "type": "Feature",
  "properties": {
    "addr:full":"Urb Eden Platja, S/n S. Antoni Calonge Girona 17252",
    "addr:postcode":"17252",
    "addr:street":"Urb;Platja S / N S. Antoni",
    "iso:country":"ES",
    "sg:address":"Urb Eden Platja, S/n",
    "sg:city":"S. Antoni Calonge",
    "sg:orig_category":"Inmobiliaria (agencias)",
    "sg:phone":"+34 972 65 21 35",
    "sg:postcode":"17252",
    "sg:province":"Girona",
    "wof:name":"Raset Siete Inmobiliaria S.l.",
    "wof:placetype":"venue"
},
  "geometry": {"coordinates":[3.1094601154,41.8569297791],"type":"Point"}
}