{
  "type": "Feature",
  "properties": {
    "iso:country":"ES",
    "sg:address":"Carrer de Arada, 6",
    "sg:city":"Molins Rei",
    "sg:orig_category":"Agencias Y Agentes Comerciales, Representantes",
    "sg:phone":"+34 936 73 04 69",
    "sg:postcode":"08750",
    "sg:province":"Barcelona",
    "wof:name":"Rubio Espinosa Jose",
    "wof:placetype":"venue"
},
  "geometry": {"coordinates":[2.0125501156,41.4174118042],"type":"Point"}
}