{
  "type": "Feature",
  "properties": {
    "iso:country":"ES",
    "sg:address":"Rond Industria (de La), 2",
    "sg:city":"Huesca",
    "sg:orig_category":"Edici\u00d3n De Diarios, Revistas, Boletines",
    "sg:phone":"+34 974 24 59 31",
    "sg:postcode":"22006",
    "sg:province":"Huesca",
    "wof:name":"Publicaciones Y Edicciones Del Alto Aragon S.a.",
    "wof:placetype":"venue"
},
  "geometry": {"coordinates":[-0.3940289915,42.1475105286],"type":"Point"}
}