{
  "type": "Feature",
  "properties": {
    "iso:country":"ES",
    "sg:address":"Calle de Argentina, 5",
    "sg:city":"Coslada",
    "sg:orig_category":"Electrodom\u00c9sticos (al Por Menor)",
    "sg:phone":"+34 916 73 37 83",
    "sg:postcode":"28820",
    "sg:province":"Madrid",
    "wof:name":"Gallego Sanchez Felisa",
    "wof:placetype":"venue"
},
  "geometry": {"coordinates":[-3.5437345505,40.4264335632],"type":"Point"}
}