{
  "type": "Feature",
  "properties": {
    "iso:country":"ES",
    "sg:address":"Rua Faustino Santalices, 7",
    "sg:city":"Bande",
    "sg:orig_category":"Cajas De Ahorro",
    "sg:phone":"+34 988 44 30 13",
    "sg:postcode":"32840",
    "sg:province":"Ourense",
    "sg:website":"www.caixagalicia.es",
    "wof:name":"Bt Espa\u00d1a Compa\u00d1ia De Servicios Globales De Telecomunicaciones S.a.u.",
    "wof:placetype":"venue"
},
  "geometry": {"coordinates":[-7.9771399498,42.0333366394],"type":"Point"}
}