{
  "type": "Feature",
  "properties": {
    "iso:country":"ES",
    "sg:address":"Calle de Ramon Areces, S/n",
    "sg:city":"Nueva Andalucia",
    "sg:orig_category":"Perfumer\u00cda (al Por Menor)",
    "sg:phone":"+34 952 90 60 17",
    "sg:postcode":"29660",
    "sg:province":"M\u00e1laga",
    "sg:website":"www.gala.ad",
    "wof:name":"Gala Perfums S.l.",
    "wof:placetype":"venue"
},
  "geometry": {"coordinates":[-4.9540901184,36.4891586304],"type":"Point"}
}