{
  "type": "Feature",
  "properties": {
    "iso:country":"ES",
    "sg:address":"Carrer de Sant Isidre, 1",
    "sg:city":"Terrassa",
    "sg:orig_category":"Ense\u00d1anza Secundaria: Colegios Y Escuelas Privadas",
    "sg:phone":"+34 937 88 18 86",
    "sg:postcode":"08221",
    "sg:province":"Barcelona",
    "wof:name":"Patronat Municipal D'educacio De Terrassa",
    "wof:placetype":"venue"
},
  "geometry": {"coordinates":[2.0129029751,41.5665359497],"type":"Point"}
}