{
  "type": "Feature",
  "properties": {
    "addr:full":"Calle de Ancha, 27 Castro Rio C\u00f3rdoba 14840",
    "addr:housenumber":"27",
    "addr:postcode":"14840",
    "addr:street":"Calle De Ancha;Rio Co\u0301Rdoba",
    "iso:country":"ES",
    "sg:address":"Calle de Ancha, 27",
    "sg:city":"Castro Rio",
    "sg:orig_category":"Farmacias",
    "sg:phone":"+34 957 37 22 37",
    "sg:postcode":"14840",
    "sg:province":"C\u00f3rdoba",
    "wof:name":"Martinez Doncel Jose",
    "wof:placetype":"venue"
},
  "geometry": {"coordinates":[-4.4807796478,37.6915588379],"type":"Point"}
}