{
  "type": "Feature",
  "properties": {
    "addr:full":"Rond Monestir, S/n Banyoles Girona 17820",
    "addr:housenumber":"s / n",
    "addr:postcode":"17820",
    "addr:street":"Monestir",
    "iso:country":"ES",
    "sg:address":"Rond Monestir, S/n",
    "sg:city":"Banyoles",
    "sg:orig_category":"Molduras, Junquillos, Listones Y Molduras Perforadas",
    "sg:phone":"+34 972 57 40 56",
    "sg:postcode":"17820",
    "sg:province":"Girona",
    "wof:name":"Martin Sole Marta",
    "wof:placetype":"venue"
},
  "geometry": {"coordinates":[2.7686750889,42.1206207275],"type":"Point"}
}