{
  "type": "Feature",
  "properties": {
    "iso:country":"ES",
    "sg:address":"Carrer de Moreres (les), 19",
    "sg:city":"Prat Llobregat",
    "sg:orig_category":"Diet\u00c9tica: Productos Biol\u00d3gicos, Naturales Y Diet\u00c9ticos (fabricaci\u00d3n, Al Por Mayor)",
    "sg:phone":"+34 933 70 40 67",
    "sg:postcode":"08820",
    "sg:province":"Barcelona",
    "sg:website":"www.bestprotein.com",
    "wof:name":"Best Protein S.l.",
    "wof:placetype":"venue"
},
  "geometry": {"coordinates":[2.1010899544,41.3324317932],"type":"Point"}
}