{
  "type": "Feature",
  "properties": {
    "iso:country":"ES",
    "sg:address":"Ctra Villamarchante, 77",
    "sg:city":"Riba-roja Turia",
    "sg:orig_category":"Chapister\u00cda",
    "sg:phone":"+34 962 77 01 56",
    "sg:postcode":"46190",
    "sg:province":"Valencia",
    "wof:name":"Morena-llacer Xx1 S.l.l.",
    "wof:placetype":"venue"
},
  "geometry": {"coordinates":[-0.5716459751,39.5446052551],"type":"Point"}
}