{
  "type": "Feature",
  "properties": {
    "iso:country":"ES",
    "sg:address":"Calle de Don Pelayo, 24",
    "sg:city":"Ejido",
    "sg:orig_category":"Insecticidas, Fumigaci\u00d3n",
    "sg:phone":"+34 950 48 08 06",
    "sg:postcode":"04700",
    "sg:province":"Almer\u00eda",
    "wof:name":"Mu\u00f1oz Flores Francisco",
    "wof:placetype":"venue"
},
  "geometry": {"coordinates":[-2.8175218105,36.7803192139],"type":"Point"}
}