{
  "type": "Feature",
  "properties": {
    "iso:country":"ES",
    "sg:address":"Calle de Cervantes, 31",
    "sg:city":"Bembibre",
    "sg:orig_category":"Arquitectos",
    "sg:phone":"+34 987 51 08 14",
    "sg:postcode":"24300",
    "sg:province":"Le\u00f3n",
    "wof:name":"Asensio Velasco Roberto",
    "wof:placetype":"venue"
},
  "geometry": {"coordinates":[-6.4171676636,42.6168136597],"type":"Point"}
}