{
  "type": "Feature",
  "properties": {
    "iso:country":"ES",
    "sg:address":"Calle de Pedro Guerrero, 26",
    "sg:city":"Fuente Alamo",
    "sg:orig_category":"Bibliotecas, Mediatecas",
    "sg:phone":"+34 968 59 87 17",
    "sg:postcode":"30320",
    "sg:province":"Murcia",
    "wof:name":"Jaime Garcia Guerrero S.l.",
    "wof:placetype":"venue"
},
  "geometry": {"coordinates":[-1.1712100506,37.7236022949],"type":"Point"}
}