{
  "type": "Feature",
  "properties": {
    "addr:full":"Av Piera, 45 Martorelles Barcelona 08107",
    "addr:housenumber":"45",
    "addr:postcode":"08107",
    "addr:street":"Av Piera",
    "iso:country":"ES",
    "sg:address":"Av Piera, 45",
    "sg:city":"Martorelles",
    "sg:orig_category":"Cajas De Ahorro",
    "sg:phone":"+34 935 70 60 22",
    "sg:postcode":"08107",
    "sg:province":"Barcelona",
    "sg:website":"www.caixasabadell.es",
    "wof:name":"Caixa D'estalvis Sabadell",
    "wof:placetype":"venue"
},
  "geometry": {"coordinates":[2.2339890003,41.5274429321],"type":"Point"}
}