{
  "type": "Feature",
  "properties": {
    "addr:full":"Calle de Alcala, 420 Madrid Madrid 28027",
    "addr:housenumber":"420",
    "addr:postcode":"28027",
    "addr:street":"Calle De Alcala",
    "iso:country":"ES",
    "sg:address":"Calle de Alcala, 420",
    "sg:city":"Madrid",
    "sg:orig_category":"Asesor\u00cda Fiscal Y Jur\u00cddica",
    "sg:phone":"+34 913 93 25 24",
    "sg:postcode":"28027",
    "sg:province":"Madrid",
    "wof:name":"Vega Rodriguez Lourdes De",
    "wof:placetype":"venue"
},
  "geometry": {"coordinates":[-3.6373999119,40.4379310608],"type":"Point"}
}