{
  "type": "Feature",
  "properties": {
    "addr:full":"J M Guelbenzu, 26 Iru\u00f1a Navarra 31005",
    "addr:housenumber":"26",
    "addr:postcode":"31005",
    "addr:street":"Guelbenzu",
    "iso:country":"ES",
    "sg:address":"J M Guelbenzu, 26",
    "sg:city":"Iru\u00f1a",
    "sg:orig_category":"Panader\u00cdas, Panader\u00cdas",
    "sg:phone":"+34 948 23 10 73",
    "sg:postcode":"31005",
    "sg:province":"Navarra",
    "wof:name":"Panaderias Navarras S.a.",
    "wof:placetype":"venue"
},
  "geometry": {"coordinates":[-1.6404650211,42.8058738708],"type":"Point"}
}