{
  "type": "Feature",
  "properties": {
    "addr:full":"Calle de Marques De Hinojares (del), 9 Mejorada Campo Madrid 28840",
    "addr:housenumber":"9",
    "addr:postcode":"28840",
    "addr:street":"Calle De Marques De Hinojares Del",
    "iso:country":"ES",
    "sg:address":"Calle de Marques De Hinojares (del), 9",
    "sg:city":"Mejorada Campo",
    "sg:orig_category":"M\u00c9dicos: Estomatolog\u00cda",
    "sg:phone":"+34 916 68 07 43",
    "sg:postcode":"28840",
    "sg:province":"Madrid",
    "wof:name":"Escobal Ramos Ulises",
    "wof:placetype":"venue"
},
  "geometry": {"coordinates":[-3.4859011173,40.3985977173],"type":"Point"}
}