{
  "type": "Feature",
  "properties": {
    "addr:full":"Calle de Antequera Y Bobadilla, 73 Cuesta Santa Cruz De Tenerife 38320",
    "addr:housenumber":"73",
    "addr:postcode":"38320",
    "addr:street":"Calle De Antequera Y Bobadilla;Cuesta Santa Cruz De",
    "iso:country":"ES",
    "sg:address":"Calle de Antequera Y Bobadilla, 73",
    "sg:city":"Cuesta",
    "sg:orig_category":"Mec\u00c1nico Del Autom\u00d3vil",
    "sg:phone":"+34 922 22 01 03",
    "sg:postcode":"38320",
    "sg:province":"Santa Cruz De Tenerife",
    "wof:name":"Hernandez Mendez Jose Carmelo",
    "wof:placetype":"venue"
},
  "geometry": {"coordinates":[-16.2793331146,28.4715938568],"type":"Point"}
}