{
  "type": "Feature",
  "properties": {
    "addr:full":"Carrer de Bruniquer, 32 Barcelona Barcelona 08024",
    "addr:housenumber":"32",
    "addr:postcode":"08024",
    "addr:street":"Carrer De Bruniquer",
    "iso:country":"ES",
    "sg:address":"Carrer de Bruniquer, 32",
    "sg:city":"Barcelona",
    "sg:orig_category":"Reposter\u00cdas",
    "sg:phone":"+34 932 84 07 50",
    "sg:postcode":"08024",
    "sg:province":"Barcelona",
    "wof:name":"Lucas Ramirez Ramon",
    "wof:placetype":"venue"
},
  "geometry": {"coordinates":[2.1610300541,41.4047813416],"type":"Point"}
}