{
  "type": "Feature",
  "properties": {
    "iso:country":"ES",
    "sg:address":"Estd Xunqueira (de), S/n",
    "sg:city":"Allariz",
    "sg:orig_category":"Centros De Educaci\u00d3n Especial",
    "sg:phone":"+34 988 44 08 25",
    "sg:postcode":"32660",
    "sg:province":"Ourense",
    "wof:name":"Colexio De Educacion Infantil E Primaria Padre Feijo",
    "wof:placetype":"venue"
},
  "geometry": {"coordinates":[-7.798304081,42.1901702881],"type":"Point"}
}