{
  "type": "Feature",
  "properties": {
    "iso:country":"ES",
    "sg:address":"Calle de Esparteros, 6",
    "sg:city":"Ubeda",
    "sg:orig_category":"Peluqueros: De Se\u00d1oras",
    "sg:phone":"+34 953 79 36 61",
    "sg:postcode":"23400",
    "sg:province":"Ja\u00e9n",
    "wof:name":"Hernanadez Leon Maria Dolores",
    "wof:placetype":"venue"
},
  "geometry": {"coordinates":[-3.3634939194,38.0166893005],"type":"Point"}
}