{
  "type": "Feature",
  "properties": {
    "iso:country":"ES",
    "sg:address":"Avda Alcalde Lorenzo Carbonell, 27",
    "sg:city":"Alacant",
    "sg:orig_category":"Cajas De Ahorro",
    "sg:phone":"+34 965 28 54 00",
    "sg:postcode":"03008",
    "sg:province":"Alicante",
    "sg:website":"www.cam.es",
    "wof:name":"Caja De Ahorros Del Mediterraneo",
    "wof:placetype":"venue"
},
  "geometry": {"coordinates":[-0.5066769719,38.3390159607],"type":"Point"}
}