{
  "type": "Feature",
  "properties": {
    "addr:full":"Calle de Cementerio, 33 Pedraja Portillo Valladolid 47196",
    "addr:housenumber":"33",
    "addr:postcode":"47196",
    "addr:street":"Calle De Cementerio",
    "iso:country":"ES",
    "sg:address":"Calle de Cementerio, 33",
    "sg:city":"Pedraja Portillo",
    "sg:orig_category":"Agencias Y Agentes Comerciales, Representantes",
    "sg:phone":"+34 983 55 31 52",
    "sg:postcode":"47196",
    "sg:province":"Valladolid",
    "wof:name":"Gonzalez Pelaez Antonio",
    "wof:placetype":"venue"
},
  "geometry": {"coordinates":[-4.6437573433,41.4736213684],"type":"Point"}
}