{
  "type": "Feature",
  "properties": {
    "iso:country":"ES",
    "sg:address":"Calle de Vicente Y Tutor, 7",
    "sg:city":"Agreda",
    "sg:orig_category":"Plomeros",
    "sg:phone":"+34 976 64 72 24",
    "sg:postcode":"42100",
    "sg:province":"Soria",
    "wof:name":"Mo\u00f1ux Ejido Julio",
    "wof:placetype":"venue"
},
  "geometry": {"coordinates":[-1.9184809923,41.8540649414],"type":"Point"}
}