{
  "type": "Feature",
  "properties": {
    "addr:full":"Calle de Principe De Vergara, 82 Madrid Madrid 28006",
    "addr:housenumber":"82",
    "addr:postcode":"madrid;28006",
    "addr:street":"Calle De Principe De Vergara",
    "iso:country":"ES",
    "sg:address":"Calle de Principe De Vergara, 82",
    "sg:city":"Madrid",
    "sg:orig_category":"Asesor\u00cda Fiscal Y Jur\u00cddica",
    "sg:phone":"+34 915 63 83 40",
    "sg:postcode":"28006",
    "sg:province":"Madrid",
    "wof:name":"Legaltax S.l.",
    "wof:placetype":"venue"
},
  "geometry": {"coordinates":[-3.6791009903,40.4354782104],"type":"Point"}
}