{
  "type": "Feature",
  "properties": {
    "iso:country":"ES",
    "sg:address":"Avda Pio Xii, S/n",
    "sg:city":"Salteras",
    "sg:orig_category":"Flores Y Plantas Naturales (al Por Mayor)",
    "sg:phone":"+34 955 70 82 35",
    "sg:postcode":"41909",
    "sg:province":"Sevilla",
    "wof:name":"Marin Rodriguez Dolores",
    "wof:placetype":"venue"
},
  "geometry": {"coordinates":[-6.1125559807,37.4220504761],"type":"Point"}
}