{
  "type": "Feature",
  "properties": {
    "addr:full":"Carrer de Aigua Nova (cami De L'), 14 Reus Tarragona 43204",
    "addr:housenumber":"14",
    "addr:postcode":"43204",
    "addr:street":"Carrer De Aigua;De L '",
    "iso:country":"ES",
    "sg:address":"Carrer de Aigua Nova (cami De L'), 14",
    "sg:city":"Reus",
    "sg:orig_category":"Confecci\u00d3n De Trajes Para Se\u00d1oras",
    "sg:phone":"+34 977 30 00 97",
    "sg:postcode":"43204",
    "sg:province":"Tarragona",
    "wof:name":"Cinderella 2.5, Sll.",
    "wof:placetype":"venue"
},
  "geometry": {"coordinates":[1.1133769751,41.1543197632],"type":"Point"}
}