{
  "type": "Feature",
  "properties": {
    "addr:full":"Calle de Estacion, 24 Miranda Ebro Burgos 09200",
    "addr:housenumber":"24",
    "addr:postcode":"09200",
    "addr:street":"Calle De Estacion",
    "iso:country":"ES",
    "sg:address":"Calle de Estacion, 24",
    "sg:city":"Miranda Ebro",
    "sg:orig_category":"Arquitectos",
    "sg:phone":"+34 947 33 57 93",
    "sg:postcode":"09200",
    "sg:province":"Burgos",
    "wof:name":"Sanjurjo Perez Enrique",
    "wof:placetype":"venue"
},
  "geometry": {"coordinates":[-2.945581913,42.6866073608],"type":"Point"}
}