{
  "type": "Feature",
  "properties": {
    "iso:country":"ES",
    "sg:address":"Mayor, 5",
    "sg:city":"Benitachell",
    "sg:orig_category":"Ense\u00d1anza, Formaci\u00d3n Profesional: Aprendizaje",
    "sg:phone":"+34 966 49 35 21",
    "sg:postcode":"03726",
    "sg:province":"Alicante",
    "wof:name":"Suma Gestion Tributaria Diputacion Alicante",
    "wof:placetype":"venue"
},
  "geometry": {"coordinates":[0.1435489953,38.7315673828],"type":"Point"}
}