{
  "type": "Feature",
  "properties": {
    "addr:full":"Calle de Cerrajeria, 5 Talavera Reina Toledo 45600",
    "addr:housenumber":"5",
    "addr:postcode":"45600",
    "addr:street":"Calle De Cerrajeria",
    "iso:country":"ES",
    "sg:address":"Calle de Cerrajeria, 5",
    "sg:city":"Talavera Reina",
    "sg:orig_category":"Molduras, Junquillos, Listones Y Molduras Perforadas",
    "sg:phone":"+34 925 81 59 91",
    "sg:postcode":"45600",
    "sg:province":"Toledo",
    "wof:name":"Montes Iba\u00f1ez Olga Natalia",
    "wof:placetype":"venue"
},
  "geometry": {"coordinates":[-4.8453555107,39.9556007385],"type":"Point"}
}