{
  "type": "Feature",
  "properties": {
    "addr:full":"Av Lluis Companys, 7 S. Cugat Valles Barcelona 08172",
    "addr:housenumber":"7",
    "addr:postcode":"08172",
    "addr:street":"Av Lluis Companys;Barcelona",
    "iso:country":"ES",
    "sg:address":"Av Lluis Companys, 7",
    "sg:city":"S. Cugat Valles",
    "sg:orig_category":"Frutas, Legumbres Frescas Y Tempranas (al Por Menor)",
    "sg:phone":"+34 935 89 75 14",
    "sg:postcode":"08172",
    "sg:province":"Barcelona",
    "wof:name":"Murcia Tolosa Belen",
    "wof:placetype":"venue"
},
  "geometry": {"coordinates":[2.0783629417,41.4702568054],"type":"Point"}
}