{
  "type": "Feature",
  "properties": {
    "addr:full":"Av Catalunya, 144 Cervera Lleida 25200",
    "addr:housenumber":"144",
    "addr:postcode":"25200",
    "addr:street":"Av Catalunya",
    "iso:country":"ES",
    "sg:address":"Av Catalunya, 144",
    "sg:city":"Cervera",
    "sg:orig_category":"Electricidad: Instaladores",
    "sg:phone":"+34 973 53 03 60",
    "sg:postcode":"25200",
    "sg:province":"Lleida",
    "wof:name":"Jesus Espada S.l.",
    "wof:placetype":"venue"
},
  "geometry": {"coordinates":[1.2686790228,41.6709861755],"type":"Point"}
}