{
  "type": "Feature",
  "properties": {
    "iso:country":"ES",
    "sg:address":"Calle de San Virgilio, 2",
    "sg:city":"Madrid",
    "sg:orig_category":"Ingeniero",
    "sg:phone":"+34 913 28 31 08",
    "sg:postcode":"28038",
    "sg:province":"Madrid",
    "wof:name":"Briega Ortega Justo",
    "wof:placetype":"venue"
},
  "geometry": {"coordinates":[-3.6625480652,40.3956069946],"type":"Point"}
}