{
  "type": "Feature",
  "properties": {
    "addr:full":"Calle de Doctor Fourquet, 17 Madrid Madrid 28012",
    "addr:housenumber":"17",
    "addr:postcode":"madrid;28012",
    "addr:street":"Calle De Doctor Fourquet",
    "iso:country":"ES",
    "sg:address":"Calle de Doctor Fourquet, 17",
    "sg:city":"Madrid",
    "sg:orig_category":"Ense\u00d1ante, Direcci\u00d3n",
    "sg:phone":"+34 915 39 38 64",
    "sg:postcode":"28012",
    "sg:province":"Madrid",
    "wof:name":"Fermin Ruiz Eugenio",
    "wof:placetype":"venue"
},
  "geometry": {"coordinates":[-3.6970589161,40.4075546265],"type":"Point"}
}