{
  "type": "Feature",
  "properties": {
    "iso:country":"ES",
    "sg:address":"Bebares, S/n",
    "sg:city":"La Barca",
    "sg:orig_category":"Alimentaci\u00d3n General (al Por Mayor)",
    "sg:phone":"+34 985 80 37 31",
    "sg:postcode":"33876",
    "sg:province":"Asturias",
    "wof:name":"Rozos Amores Isidro",
    "wof:placetype":"venue"
},
  "geometry": {"coordinates":[-6.4057312012,43.3230934143],"type":"Point"}
}