{
  "type": "Feature",
  "properties": {
    "iso:country":"ES",
    "sg:address":"Plaz Mister Park, S/n",
    "sg:city":"Palmas De Gran Canaria",
    "sg:orig_category":"Asesor\u00cda Para La Organizaci\u00d3n Y Gesti\u00d3n Del Transporte",
    "sg:phone":"+34 928 46 02 07",
    "sg:postcode":"35008",
    "sg:province":"Las Palmas",
    "wof:name":"Manipulaciones Portuarias Grupajes Y Transitos S.a.",
    "wof:placetype":"venue"
},
  "geometry": {"coordinates":[-15.419380188,28.1532001495],"type":"Point"}
}