{
  "type": "Feature",
  "properties": {
    "addr:full":"San Javier, 28 Mijas Costa M\u00e1laga 29649",
    "addr:housenumber":"28",
    "addr:postcode":"29649",
    "addr:street":"San Javier",
    "iso:country":"ES",
    "sg:address":"San Javier, 28",
    "sg:city":"Mijas Costa",
    "sg:orig_category":"Aguas (distribuci\u00d3n, Servicios)",
    "sg:phone":"+34 952 46 77 26",
    "sg:postcode":"29649",
    "sg:province":"M\u00e1laga",
    "sg:website":"www.mijagua.es",
    "wof:name":"Mijagua",
    "wof:placetype":"venue"
},
  "geometry": {"coordinates":[-4.7157039642,36.4931945801],"type":"Point"}
}