{
  "type": "Feature",
  "properties": {
    "iso:country":"ES",
    "sg:address":"Ramon Llull, S/n",
    "sg:city":"Montu\u00efri",
    "sg:orig_category":"Forjas Y Altos Hornos",
    "sg:phone":"+34 971 64 41 31",
    "sg:postcode":"07230",
    "sg:province":"Islas Baleares",
    "wof:name":"Salhi  Mustafa",
    "wof:placetype":"venue"
},
  "geometry": {"coordinates":[2.9860699177,39.5694694519],"type":"Point"}
}