{
  "type": "Feature",
  "properties": {
    "iso:country":"ES",
    "sg:address":"Calle de Azkue Resurreccion Maria De, 6",
    "sg:city":"Bilbao",
    "sg:orig_category":"Plomeros",
    "sg:phone":"+34 944 33 64 42",
    "sg:postcode":"48004",
    "sg:province":"Vizcaya",
    "wof:name":"Fontaneria El Carmen, S.l.",
    "wof:placetype":"venue"
},
  "geometry": {"coordinates":[-2.9168257713,43.2528686523],"type":"Point"}
}