{
  "type": "Feature",
  "properties": {
    "addr:full":"Calle de Monzon, 18 Sevilla Sevilla 41012",
    "addr:housenumber":"18",
    "addr:postcode":"41012",
    "addr:street":"Calle De Monzon",
    "iso:country":"ES",
    "sg:address":"Calle de Monzon, 18",
    "sg:city":"Sevilla",
    "sg:orig_category":"Aparatos, Material Y Suministros Para Laboratorios",
    "sg:phone":"+34 954 61 05 03",
    "sg:postcode":"41012",
    "sg:province":"Sevilla",
    "wof:name":"Afora S.a.",
    "wof:placetype":"venue"
},
  "geometry": {"coordinates":[-5.9857563972,37.3595466614],"type":"Point"}
}