{
  "type": "Feature",
  "properties": {
    "addr:full":"Plaz Moreno, 9 Guadalajara Guadalajara 19001",
    "addr:housenumber":"9",
    "addr:postcode":"19001",
    "addr:street":"Moreno",
    "iso:country":"ES",
    "sg:address":"Plaz Moreno, 9",
    "sg:city":"Guadalajara",
    "sg:orig_category":"Asesor\u00cda Fiscal Y Jur\u00cddica",
    "sg:phone":"+34 949 22 90 61",
    "sg:postcode":"19001",
    "sg:province":"Guadalajara",
    "wof:name":"Javier Garcia Y Asociado S.l.",
    "wof:placetype":"venue"
},
  "geometry": {"coordinates":[-3.1641490459,40.6297950745],"type":"Point"}
}