{
  "type": "Feature",
  "properties": {
    "iso:country":"ES",
    "sg:address":"Calle de Pablo Picasso, S/n",
    "sg:city":"Pinto",
    "sg:orig_category":"Museos",
    "sg:phone":"+34 916 92 62 05",
    "sg:postcode":"28320",
    "sg:province":"Madrid",
    "sg:website":"www.arqueopinto.com",
    "wof:name":"Paleorama S.l.",
    "wof:placetype":"venue"
},
  "geometry": {"coordinates":[-3.6949789524,40.2378349304],"type":"Point"}
}