{
  "type": "Feature",
  "properties": {
    "addr:full":"Calle de Romancero, S/n Carranque Toledo 45216",
    "addr:housenumber":"s / n",
    "addr:postcode":"45216",
    "addr:street":"Calle De Romancero",
    "iso:country":"ES",
    "sg:address":"Calle de Romancero, S/n",
    "sg:city":"Carranque",
    "sg:orig_category":"Inmobiliaria (agencias)",
    "sg:phone":"+34 925 54 44 72",
    "sg:postcode":"45216",
    "sg:province":"Toledo",
    "wof:name":"Orozco Garcia Jesus",
    "wof:placetype":"venue"
},
  "geometry": {"coordinates":[-3.9126141071,40.1664581299],"type":"Point"}
}