{
  "type": "Feature",
  "properties": {
    "addr:full":"Calle de Nuestra Se\u00d1ora De Monserrate, 6 Torrevieja Alicante 03180",
    "addr:housenumber":"6",
    "addr:postcode":"03180",
    "addr:street":"Calle De Nuestra Sen\u0303Ora De Monserrate",
    "iso:country":"ES",
    "sg:address":"Calle de Nuestra Se\u00d1ora De Monserrate, 6",
    "sg:city":"Torrevieja",
    "sg:orig_category":"Reposter\u00cdas",
    "sg:phone":"+34 965 70 65 23",
    "sg:postcode":"03180",
    "sg:province":"Alicante",
    "wof:name":"Panaderia Torregrosa S.l.",
    "wof:placetype":"venue"
},
  "geometry": {"coordinates":[-0.6536790133,38.0173606873],"type":"Point"}
}