{
  "type": "Feature",
  "properties": {
    "iso:country":"ES",
    "sg:address":"Calle de Santa Juliana, 18",
    "sg:city":"Madrid",
    "sg:orig_category":"Chapister\u00cda",
    "sg:phone":"+34 914 50 03 17",
    "sg:postcode":"28039",
    "sg:province":"Madrid",
    "wof:name":"Exposito Bonafonte Luis",
    "wof:placetype":"venue"
},
  "geometry": {"coordinates":[-3.7047040462,40.4525413513],"type":"Point"}
}