{
  "type": "Feature",
  "properties": {
    "iso:country":"ES",
    "sg:address":"Cullerers, 21",
    "sg:city":"Alaquas",
    "sg:orig_category":"Cajas Y Embalajes De Pl\u00c1stico",
    "sg:phone":"+34 961 50 73 15",
    "sg:postcode":"46970",
    "sg:province":"Valencia",
    "sg:website":"www.artplastsl.com",
    "wof:name":"Manufacturas Arplast S.l.",
    "wof:placetype":"venue"
},
  "geometry": {"coordinates":[-0.4785439968,39.4476203918],"type":"Point"}
}