{
  "type": "Feature",
  "properties": {
    "iso:country":"ES",
    "sg:address":"Carrer de Mar, 48",
    "sg:city":"Calafell",
    "sg:orig_category":"Institutos De Belleza",
    "sg:phone":"+34 977 69 57 07",
    "sg:postcode":"43820",
    "sg:province":"Tarragona",
    "wof:name":"Conejo Bernal Yolanda",
    "wof:placetype":"venue"
},
  "geometry": {"coordinates":[1.5690129995,41.1974906921],"type":"Point"}
}