{
  "type": "Feature",
  "properties": {
    "iso:country":"ES",
    "sg:address":"Calle de Blas Perez Gonzalez, 12",
    "sg:city":"Llanos De Aridane",
    "sg:orig_category":"Metalurgia",
    "sg:phone":"+34 922 46 24 52",
    "sg:postcode":"38760",
    "sg:province":"Santa Cruz De Tenerife",
    "wof:name":"Agroisle\u00f1a Suministros S.l.",
    "wof:placetype":"venue"
},
  "geometry": {"coordinates":[-17.9125728607,28.6559772491],"type":"Point"}
}