{
  "type": "Feature",
  "properties": {
    "iso:country":"ES",
    "sg:address":"Calle de Mayor, 34",
    "sg:city":"Alcantarilla",
    "sg:orig_category":"Bancos",
    "sg:phone":"+34 968 80 48 61",
    "sg:postcode":"30820",
    "sg:province":"Murcia",
    "wof:name":"Banco Popular Espa\u00f1ol",
    "wof:placetype":"venue"
},
  "geometry": {"coordinates":[-1.2093379498,37.9722595215],"type":"Point"}
}