{
  "type": "Feature",
  "properties": {
    "iso:country":"ES",
    "sg:address":"Avda Ingeniero Jose Alegria, 60",
    "sg:city":"Zarandona",
    "sg:orig_category":"Lencer\u00cda Femenina, Corseter\u00cda, Trajes De Ba\u00d1o (al Por Menor)",
    "sg:phone":"+34 968 23 91 60",
    "sg:postcode":"30007",
    "sg:province":"Murcia",
    "wof:name":"Carmona Noguera Antonio",
    "wof:placetype":"venue"
},
  "geometry": {"coordinates":[-1.1142389774,37.9970092773],"type":"Point"}
}