{
  "type": "Feature",
  "properties": {
    "addr:full":"Avda Garcia Barbon, 122 Vigo Pontevedra 36201",
    "addr:housenumber":"122",
    "addr:postcode":"36201",
    "addr:street":"Avda Garcia Barbon",
    "iso:country":"ES",
    "sg:address":"Avda Garcia Barbon, 122",
    "sg:city":"Vigo",
    "sg:orig_category":"Prot\u00c9sicos Dentales",
    "sg:phone":"+34 986 22 52 56",
    "sg:postcode":"36201",
    "sg:province":"Pontevedra",
    "wof:name":"Rodriguez Garcia Ramon",
    "wof:placetype":"venue"
},
  "geometry": {"coordinates":[-8.7089090347,42.2389717102],"type":"Point"}
}