{
  "type": "Feature",
  "properties": {
    "iso:country":"ES",
    "sg:address":"Calle de Atanasio Barron, 2",
    "sg:city":"Sevilla",
    "sg:orig_category":"Abogados",
    "sg:phone":"+34 954 53 80 55",
    "sg:postcode":"41003",
    "sg:province":"Sevilla",
    "wof:name":"Marin Villalobos Carmelo",
    "wof:placetype":"venue"
},
  "geometry": {"coordinates":[-5.9848389626,37.3878326416],"type":"Point"}
}