{
  "type": "Feature",
  "properties": {
    "addr:full":"Av Alicante, 49 Cocentaina Alicante 03820",
    "addr:housenumber":"49",
    "addr:postcode":"03820",
    "addr:street":"Av Alicante",
    "iso:country":"ES",
    "sg:address":"Av Alicante, 49",
    "sg:city":"Cocentaina",
    "sg:orig_category":"Distribuci\u00d3n De Petr\u00d3leo Y Derivados",
    "sg:phone":"+34 966 50 04 42",
    "sg:postcode":"03820",
    "sg:province":"Alicante",
    "wof:name":"Easter Petroleum Company S.l.",
    "wof:placetype":"venue"
},
  "geometry": {"coordinates":[-0.4539430141,38.7218933105],"type":"Point"}
}