{
  "type": "Feature",
  "properties": {
    "iso:country":"ES",
    "sg:address":"Calle de Embarcadero, 2",
    "sg:city":"Zaragoza",
    "sg:orig_category":"Fabricaci\u00d3n De Juguetes Autom\u00c1ticos",
    "sg:phone":"+34 976 35 38 04",
    "sg:postcode":"50009",
    "sg:province":"Zaragoza",
    "wof:name":"Oper Delicias S.a.",
    "wof:placetype":"venue"
},
  "geometry": {"coordinates":[-0.9073070288,41.629650116],"type":"Point"}
}