{
  "type": "Feature",
  "properties": {
    "addr:full":"Avda San Amador, 39 Martos Ja\u00e9n 23600",
    "addr:housenumber":"39",
    "addr:postcode":"23600",
    "addr:street":"Avda San Amador;Jae\u0301N",
    "iso:country":"ES",
    "sg:address":"Avda San Amador, 39",
    "sg:city":"Martos",
    "sg:orig_category":"Distribuci\u00d3n De Petr\u00d3leo Y Derivados",
    "sg:phone":"+34 953 55 44 61",
    "sg:postcode":"23600",
    "sg:province":"Ja\u00e9n",
    "wof:name":"Rando Perez Juan",
    "wof:placetype":"venue"
},
  "geometry": {"coordinates":[-3.9725680351,37.7201080322],"type":"Point"}
}