{
  "type": "Feature",
  "properties": {
    "addr:full":"Carrer de Miguel Machado, 3 Palmanova Islas Baleares 07181",
    "addr:housenumber":"3",
    "addr:postcode":"07181",
    "addr:street":"Carrer De Miguel Machado",
    "iso:country":"ES",
    "sg:address":"Carrer de Miguel Machado, 3",
    "sg:city":"Palmanova",
    "sg:orig_category":"Art\u00cdculos De Decoraci\u00d3n",
    "sg:phone":"+34 971 68 17 40",
    "sg:postcode":"07181",
    "sg:province":"Islas Baleares",
    "wof:name":"I Love Fabrics S.l",
    "wof:placetype":"venue"
},
  "geometry": {"coordinates":[2.5457770824,39.5281600952],"type":"Point"}
}