{
  "type": "Feature",
  "properties": {
    "addr:full":"Calle de Garcilaso De La Vega, 24 Palacios Y Villafranca Sevilla 41720",
    "addr:housenumber":"24",
    "addr:postcode":"41720",
    "addr:street":"Calle De Garcilaso De La Vega",
    "iso:country":"ES",
    "sg:address":"Calle de Garcilaso De La Vega, 24",
    "sg:city":"Palacios Y Villafranca",
    "sg:orig_category":"Material Y Herramientas Agr\u00cdcolas",
    "sg:phone":"+34 955 81 62 90",
    "sg:postcode":"41720",
    "sg:province":"Sevilla",
    "wof:name":"Moguer Amuedo Rosario",
    "wof:placetype":"venue"
},
  "geometry": {"coordinates":[-5.9241790771,37.1630935669],"type":"Point"}
}