{
  "type": "Feature",
  "properties": {
    "addr:full":"Calle de Mayor, 110 Alcantarilla Murcia 30820",
    "addr:housenumber":"110",
    "addr:postcode":"30820",
    "addr:street":"Calle De Mayor",
    "iso:country":"ES",
    "sg:address":"Calle de Mayor, 110",
    "sg:city":"Alcantarilla",
    "sg:orig_category":"Abogados",
    "sg:phone":"+34 968 89 03 00",
    "sg:postcode":"30820",
    "sg:province":"Murcia",
    "wof:name":"Martinez Lison Antonio",
    "wof:placetype":"venue"
},
  "geometry": {"coordinates":[-1.2127389908,37.9702606201],"type":"Point"}
}