{
  "type": "Feature",
  "properties": {
    "addr:full":"Quejana, 12 Kexaa \u00c1lava 01478",
    "addr:housenumber":"12",
    "addr:postcode":"01478",
    "addr:street":"Quejana;A\u0301Lava",
    "iso:country":"ES",
    "sg:address":"Quejana, 12",
    "sg:city":"Kexaa",
    "sg:orig_category":"Cr\u00cda De Animales",
    "sg:phone":"+34 945 39 92 97",
    "sg:postcode":"01478",
    "sg:province":"\u00c1lava",
    "wof:name":"Berganza S.c.",
    "wof:placetype":"venue"
},
  "geometry": {"coordinates":[-3.0612668991,43.0823707581],"type":"Point"}
}