{
  "type": "Feature",
  "properties": {
    "addr:full":"Carrer de Barbera, Km7 Roquetes Tarragona 43520",
    "addr:postcode":"43520",
    "addr:street":"Carrer De Barbera",
    "iso:country":"ES",
    "sg:address":"Carrer de Barbera, Km7",
    "sg:city":"Roquetes",
    "sg:orig_category":"Detectives, Agentes Investigadores Privados",
    "sg:phone":"+34 977 50 35 82",
    "sg:postcode":"43520",
    "sg:province":"Tarragona",
    "wof:name":"Jose Martinez Cazorla",
    "wof:placetype":"venue"
},
  "geometry": {"coordinates":[0.5002449751,40.8249855042],"type":"Point"}
}