{
  "type": "Feature",
  "properties": {
    "addr:full":"C/ Verge De Montserrat, 59 Ripollet Barcelona 08291",
    "addr:housenumber":"59",
    "addr:postcode":"08291",
    "addr:street":"C / Verge De Montserrat",
    "iso:country":"ES",
    "sg:address":"C/ Verge De Montserrat, 59",
    "sg:city":"Ripollet",
    "sg:orig_category":"Muebles Y Accesorios Para Cocinas Y Cuartos De Ba\u00d1o (al Por Menor)",
    "sg:phone":"+34 935 80 48 27",
    "sg:postcode":"08291",
    "sg:province":"Barcelona",
    "wof:name":"Novoestil S. A.",
    "wof:placetype":"venue"
},
  "geometry": {"coordinates":[2.1413369179,41.5016021729],"type":"Point"}
}