{
  "type": "Feature",
  "properties": {
    "addr:full":"Calle de Nieremberg, 23 Madrid Madrid 28002",
    "addr:housenumber":"23",
    "addr:postcode":"madrid;28002",
    "addr:street":"Calle De Nieremberg",
    "iso:country":"ES",
    "sg:address":"Calle de Nieremberg, 23",
    "sg:city":"Madrid",
    "sg:orig_category":"Agencias Y Agentes Comerciales, Representantes",
    "sg:phone":"+34 914 15 94 46",
    "sg:postcode":"28002",
    "sg:province":"Madrid",
    "wof:name":"Mcm-representaciones S.l.",
    "wof:placetype":"venue"
},
  "geometry": {"coordinates":[-3.672492981,40.4479827881],"type":"Point"}
}