{
  "type": "Feature",
  "properties": {
    "addr:full":"Calle de Diego Hidalgo Solis, 26 Villafranca De Los Barros Badajoz 06220",
    "addr:housenumber":"26",
    "addr:postcode":"06220",
    "addr:street":"Calle De Diego Hidalgo Solis",
    "iso:country":"ES",
    "sg:address":"Calle de Diego Hidalgo Solis, 26",
    "sg:city":"Villafranca De Los Barros",
    "sg:orig_category":"Agencias Y Agentes Comerciales, Representantes",
    "sg:phone":"+34 924 52 02 07",
    "sg:postcode":"06220",
    "sg:province":"Badajoz",
    "wof:name":"Lopez Gonzalez Juan",
    "wof:placetype":"venue"
},
  "geometry": {"coordinates":[-6.336833477,38.5573120117],"type":"Point"}
}