{
  "type": "Feature",
  "properties": {
    "addr:full":"Calle de Isabel Colbrand, 16 Madrid Madrid 28050",
    "addr:housenumber":"16",
    "addr:postcode":"madrid;28050",
    "addr:street":"Calle De Isabel Colbrand",
    "iso:country":"ES",
    "sg:address":"Calle de Isabel Colbrand, 16",
    "sg:city":"Madrid",
    "sg:orig_category":"Fabricaci\u00d3n De Juguetes Autom\u00c1ticos",
    "sg:phone":"+34 913 58 86 00",
    "sg:postcode":"28050",
    "sg:province":"Madrid",
    "wof:name":"Alejandre Narro Alberto",
    "wof:placetype":"venue"
},
  "geometry": {"coordinates":[-3.6764850616,40.5110015869],"type":"Point"}
}