{
  "type": "Feature",
  "properties": {
    "addr:full":"San Vicente Do Mar, 2 San Vicente Pontevedra 36988",
    "addr:housenumber":"2",
    "addr:postcode":"36988",
    "addr:street":"Mar",
    "iso:country":"ES",
    "sg:address":"San Vicente Do Mar, 2",
    "sg:city":"San Vicente",
    "sg:orig_category":"Inmobiliaria (agencias)",
    "sg:phone":"+34 986 73 81 22",
    "sg:postcode":"36988",
    "sg:province":"Pontevedra",
    "wof:name":"Sieiro S. A.",
    "wof:placetype":"venue"
},
  "geometry": {"coordinates":[-8.921954155,42.458114624],"type":"Point"}
}