{
  "type": "Feature",
  "properties": {
    "iso:country":"ES",
    "sg:address":"Calle de Iglesia, 2",
    "sg:city":"Espinar",
    "sg:orig_category":"Cristaler\u00cdas",
    "sg:phone":"+34 921 18 10 62",
    "sg:postcode":"40400",
    "sg:province":"Segovia",
    "wof:name":"Cristaleria Y Aluminio Doyca S.l.",
    "wof:placetype":"venue"
},
  "geometry": {"coordinates":[-4.2474751472,40.7179298401],"type":"Point"}
}