{
  "type": "Feature",
  "properties": {
    "iso:country":"ES",
    "sg:address":"San Agustin, 18",
    "sg:city":"Iru\u00f1a",
    "sg:orig_category":"Alimentaci\u00d3n General (al Por Menor)",
    "sg:phone":"+34 948 22 03 32",
    "sg:postcode":"31001",
    "sg:province":"Navarra",
    "wof:name":"Rivas Salvatierra Rosario",
    "wof:placetype":"venue"
},
  "geometry": {"coordinates":[-1.6410720348,42.8173103333],"type":"Point"}
}