{
  "type": "Feature",
  "properties": {
    "addr:full":"Calle de Empedrada, 30 Vegadeo Asturias 33770",
    "addr:housenumber":"30",
    "addr:postcode":"33770",
    "addr:street":"Calle De Empedrada",
    "iso:country":"ES",
    "sg:address":"Calle de Empedrada, 30",
    "sg:city":"Vegadeo",
    "sg:orig_category":"Peluquer\u00cdas, Peluquer\u00cda Mixta",
    "sg:phone":"+34 985 47 62 97",
    "sg:postcode":"33770",
    "sg:province":"Asturias",
    "wof:name":"Perez Garcia Elena",
    "wof:placetype":"venue"
},
  "geometry": {"coordinates":[-7.0480651855,43.4648551941],"type":"Point"}
}