{
  "type": "Feature",
  "properties": {
    "addr:full":"Calle de Narciso Serra, 4 Madrid Madrid 28007",
    "addr:housenumber":"4",
    "addr:postcode":"28007",
    "addr:street":"Calle De Narciso Serra",
    "iso:country":"ES",
    "sg:address":"Calle de Narciso Serra, 4",
    "sg:city":"Madrid",
    "sg:orig_category":"Mercer\u00cda, Lencer\u00cda (al Por Menor)",
    "sg:phone":"+34 915 52 96 38",
    "sg:postcode":"28007",
    "sg:province":"Madrid",
    "wof:name":"Siguenza Milan Maria Luisa",
    "wof:placetype":"venue"
},
  "geometry": {"coordinates":[-3.6793129444,40.4041099548],"type":"Point"}
}