{
  "type": "Feature",
  "properties": {
    "addr:full":"Calle de Arevalo, 11 Lucena C\u00f3rdoba 14900",
    "addr:housenumber":"11",
    "addr:postcode":"14900",
    "addr:street":"Calle De Arevalo",
    "iso:country":"ES",
    "sg:address":"Calle de Arevalo, 11",
    "sg:city":"Lucena",
    "sg:orig_category":"Promotores Constructores",
    "sg:phone":"+34 957 51 55 44",
    "sg:postcode":"14900",
    "sg:province":"C\u00f3rdoba",
    "wof:name":"F.pe\u00f1alver Cordoba S.l.",
    "wof:placetype":"venue"
},
  "geometry": {"coordinates":[-4.4859166145,37.4121665955],"type":"Point"}
}