{
  "type": "Feature",
  "properties": {
    "iso:country":"ES",
    "sg:address":"Avda General Aviles, 58",
    "sg:city":"Valencia",
    "sg:orig_category":"Florister\u00cdas",
    "sg:phone":"+34 963 49 17 87",
    "sg:postcode":"46015",
    "sg:province":"Valencia",
    "wof:name":"Fombuena Pe\u00f1arrocha Maria Amparo",
    "wof:placetype":"venue"
},
  "geometry": {"coordinates":[-0.3998099864,39.4844589233],"type":"Point"}
}