{
  "type": "Feature",
  "properties": {
    "iso:country":"ES",
    "sg:address":"Rua Serafin Pazo, 26",
    "sg:city":"Estrada",
    "sg:orig_category":"Tintes (fabricaci\u00d3n, Al Por Mayor)",
    "sg:phone":"+34 986 57 10 48",
    "sg:postcode":"36680",
    "sg:province":"Pontevedra",
    "wof:name":"Tintoreria Punto Elegante",
    "wof:placetype":"venue"
},
  "geometry": {"coordinates":[-8.4884557724,42.6875457764],"type":"Point"}
}