{
  "type": "Feature",
  "properties": {
    "addr:full":"Avda Somosierra (de), 12 San Sebastian De Los Reyes Madrid 28700",
    "addr:housenumber":"12",
    "addr:postcode":"28700",
    "addr:street":"Avda Somosierra De",
    "iso:country":"ES",
    "sg:address":"Avda Somosierra (de), 12",
    "sg:city":"San Sebastian De Los Reyes",
    "sg:orig_category":"Seguridad En El Trabajo Y Prevenci\u00d3n De Riesgos Laborales",
    "sg:phone":"+34 916 59 22 84",
    "sg:postcode":"28700",
    "sg:province":"Madrid",
    "wof:name":"Grupo 17 S.l.",
    "wof:placetype":"venue"
},
  "geometry": {"coordinates":[-3.6174271107,40.5525093079],"type":"Point"}
}