{
  "type": "Feature",
  "properties": {
    "addr:full":"Calle de Pe\u00d1a Pajar, S/n Ledesma Salamanca 37100",
    "addr:housenumber":"s / n",
    "addr:postcode":"37100",
    "addr:street":"Calle De Pen\u0303A Pajar",
    "iso:country":"ES",
    "sg:address":"Calle de Pe\u00d1a Pajar, S/n",
    "sg:city":"Ledesma",
    "sg:orig_category":"Cerrajer\u00cda, Ferrallista",
    "sg:phone":"+34 923 57 04 24",
    "sg:postcode":"37100",
    "sg:province":"Salamanca",
    "wof:name":"Cerrajeria Gomez De La Nava S.l.",
    "wof:placetype":"venue"
},
  "geometry": {"coordinates":[-6.0004591942,41.0852890015],"type":"Point"}
}