{
  "type": "Feature",
  "properties": {
    "iso:country":"ES",
    "sg:address":"Carrer de Transversal, 239",
    "sg:city":"Terrassa",
    "sg:orig_category":"Imprenta",
    "sg:phone":"+34 937 35 63 47",
    "sg:postcode":"08225",
    "sg:province":"Barcelona",
    "wof:name":"Monerris Caballero Javier",
    "wof:placetype":"venue"
},
  "geometry": {"coordinates":[2.0117220879,41.5729446411],"type":"Point"}
}