{
  "type": "Feature",
  "properties": {
    "iso:country":"ES",
    "sg:address":"Calle de Bernabe Soriano, 12",
    "sg:city":"Jaen",
    "sg:orig_category":"Relojer\u00cda (al Por Menor, Reparaci\u00d3n)",
    "sg:phone":"+34 953 23 40 24",
    "sg:postcode":"23001",
    "sg:province":"Ja\u00e9n",
    "wof:name":"Puche Morales Pedro Jose",
    "wof:placetype":"venue"
},
  "geometry": {"coordinates":[-3.7888936996,37.7660713196],"type":"Point"}
}