{
  "type": "Feature",
  "properties": {
    "addr:full":"Carr Vicente Cuervo, 13 Eivissa Islas Baleares 07800",
    "addr:housenumber":"13",
    "addr:postcode":"07800",
    "addr:street":"Carr Vicente Cuervo",
    "iso:country":"ES",
    "sg:address":"Carr Vicente Cuervo, 13",
    "sg:city":"Eivissa",
    "sg:orig_category":"Confiter\u00cdas, Chocolater\u00cdas (al Por Menor)",
    "sg:phone":"+34 971 31 33 61",
    "sg:postcode":"07800",
    "sg:province":"Islas Baleares",
    "wof:name":"Prabel S. A.",
    "wof:placetype":"venue"
},
  "geometry": {"coordinates":[1.4337790012,38.9085884094],"type":"Point"}
}