{
  "type": "Feature",
  "properties": {
    "iso:country":"ES",
    "sg:address":"Avda Antibioticos, 260",
    "sg:city":"Trobajo Del Cerecedo",
    "sg:orig_category":"Madera Para Construcci\u00d3n E Industria",
    "sg:phone":"+34 987 26 37 56",
    "sg:postcode":"24192",
    "sg:province":"Le\u00f3n",
    "wof:name":"Estructuras Y Casas En Madera S.l.",
    "wof:placetype":"venue"
},
  "geometry": {"coordinates":[-5.5670289993,42.5441398621],"type":"Point"}
}