{
  "type": "Feature",
  "properties": {
    "iso:country":"ES",
    "sg:address":"Carr Santanyi, De, 15",
    "sg:city":"Campos",
    "sg:orig_category":"Sociedades, Compa\u00d1\u00cdas Aseguradoras",
    "sg:phone":"+34 971 65 04 01",
    "sg:postcode":"07630",
    "sg:province":"Islas Baleares",
    "wof:name":"Maria Miquel Seguros C.b.",
    "wof:placetype":"venue"
},
  "geometry": {"coordinates":[3.0205309391,39.4292945862],"type":"Point"}
}