{
  "type": "Feature",
  "properties": {
    "addr:full":"Calle de Consolacion, 81 Torredonjimeno Ja\u00e9n 23650",
    "addr:housenumber":"81",
    "addr:postcode":"23650",
    "addr:street":"Calle De Consolacion",
    "iso:country":"ES",
    "sg:address":"Calle de Consolacion, 81",
    "sg:city":"Torredonjimeno",
    "sg:orig_category":"Material Y Herramientas Agr\u00cdcolas",
    "sg:phone":"+34 953 34 41 97",
    "sg:postcode":"23650",
    "sg:province":"Ja\u00e9n",
    "wof:name":"Agrobensa Sur S.l.",
    "wof:placetype":"venue"
},
  "geometry": {"coordinates":[-3.9643785954,37.7689552307],"type":"Point"}
}