{
  "type": "Feature",
  "properties": {
    "iso:country":"ES",
    "sg:address":"Avda Valladolid, 44",
    "sg:city":"Soria",
    "sg:orig_category":"Empresarios",
    "sg:phone":"+34 975 22 04 88",
    "sg:postcode":"42004",
    "sg:province":"Soria",
    "wof:name":"Diaz Diez Placido",
    "wof:placetype":"venue"
},
  "geometry": {"coordinates":[-2.4806718826,41.7672462463],"type":"Point"}
}