{
  "type": "Feature",
  "properties": {
    "iso:country":"ES",
    "sg:address":"Pol. Ind. Serrallo, S/n",
    "sg:city":"Castello Plana",
    "sg:orig_category":"Producci\u00d3n De Abonos Y De Fertilizantes",
    "sg:phone":"+34 964 28 46 80",
    "sg:postcode":"12100",
    "sg:province":"Castell\u00f3n",
    "wof:name":"Fertilizantes Del Turia S. A.",
    "wof:placetype":"venue"
},
  "geometry": {"coordinates":[0.0176999997,39.9888801575],"type":"Point"}
}