{
  "type": "Feature",
  "properties": {
    "addr:full":"Calle de Luis Montoto, 139 Sevilla Sevilla 41007",
    "addr:housenumber":"139",
    "addr:postcode":"41007",
    "addr:street":"Calle De Luis Montoto",
    "iso:country":"ES",
    "sg:address":"Calle de Luis Montoto, 139",
    "sg:city":"Sevilla",
    "sg:orig_category":"Fabricaci\u00d3n De Mobiliario De Oficina",
    "sg:phone":"+34 954 98 12 43",
    "sg:postcode":"41007",
    "sg:province":"Sevilla",
    "sg:website":"www.ofiprix.com",
    "wof:name":"System Ofiprix S.l.",
    "wof:placetype":"venue"
},
  "geometry": {"coordinates":[-5.9671301842,37.387588501],"type":"Point"}
}