{
  "type": "Feature",
  "properties": {
    "iso:country":"ES",
    "sg:address":"Calle de Pintor Pablo Uranga, 10",
    "sg:city":"Vitoria-gasteiz",
    "sg:orig_category":"Alimentaci\u00d3n General (al Por Menor)",
    "sg:phone":"+34 945 01 04 01",
    "sg:postcode":"01008",
    "sg:province":"\u00c1lava",
    "wof:name":"Urcelay Bolinaga Hermanos, C.b.",
    "wof:placetype":"venue"
},
  "geometry": {"coordinates":[-2.6851680279,42.8460693359],"type":"Point"}
}