{
  "type": "Feature",
  "properties": {
    "iso:country":"ES",
    "sg:address":"Avda Mar Mediterraneo (del), 3",
    "sg:city":"Valdemoro",
    "sg:orig_category":"Inmobiliaria (agencias)",
    "sg:phone":"+34 918 01 85 38",
    "sg:postcode":"28340",
    "sg:province":"Madrid",
    "sg:website":"www.inmobiliariatuhogar.com",
    "wof:name":"Asesores Inmobiliarios Tu Hogar S. L.",
    "wof:placetype":"venue"
},
  "geometry": {"coordinates":[-3.6848363876,40.1801719666],"type":"Point"}
}