{
  "type": "Feature",
  "properties": {
    "iso:country":"ES",
    "sg:address":"Rond San Bartolome, 10",
    "sg:city":"Cuellar",
    "sg:orig_category":"Muebles, Minoristas",
    "sg:phone":"+34 921 14 32 22",
    "sg:postcode":"40200",
    "sg:province":"Segovia",
    "wof:name":"Muebles Hermanos Marcos S.a.",
    "wof:placetype":"venue"
},
  "geometry": {"coordinates":[-4.3175759315,41.398223877],"type":"Point"}
}