{
  "type": "Feature",
  "properties": {
    "iso:country":"ES",
    "sg:address":"Calle de Panaderos, 8",
    "sg:city":"Le\u00f3n",
    "sg:orig_category":"Fabricaci\u00d3n, Instalaci\u00d3n De Armarios",
    "sg:phone":"+34 987 21 36 04",
    "sg:postcode":"24006",
    "sg:province":"Le\u00f3n",
    "wof:name":"Cristalera Salvador Del Nido S.l.",
    "wof:placetype":"venue"
},
  "geometry": {"coordinates":[-5.5651578903,42.5982398987],"type":"Point"}
}