{
  "type": "Feature",
  "properties": {
    "iso:country":"ES",
    "sg:address":"Calle de Navarredonda, 1",
    "sg:city":"Rozas De Madrid",
    "sg:orig_category":"Trabajos De Topograf\u00cda",
    "sg:phone":"+34 916 39 80 56",
    "sg:postcode":"28230",
    "sg:province":"Madrid",
    "sg:website":"www.topocad.es",
    "wof:name":"Topocad S.l.",
    "wof:placetype":"venue"
},
  "geometry": {"coordinates":[-3.8592214584,40.4826774597],"type":"Point"}
}