{
  "type": "Feature",
  "properties": {
    "addr:full":"Carrer de Ventura Rodriguez, 2 Barcelona Barcelona 08035",
    "addr:housenumber":"2",
    "addr:postcode":"08035",
    "addr:street":"Carrer De Ventura Rodriguez",
    "iso:country":"ES",
    "sg:address":"Carrer de Ventura Rodriguez, 2",
    "sg:city":"Barcelona",
    "sg:orig_category":"Panader\u00cdas, Panader\u00cdas",
    "sg:phone":"+34 934 28 37 03",
    "sg:postcode":"08035",
    "sg:province":"Barcelona",
    "wof:name":"Arregui Sancho Manuel",
    "wof:placetype":"venue"
},
  "geometry": {"coordinates":[2.1490578651,41.4317207336],"type":"Point"}
}