{
  "type": "Feature",
  "properties": {
    "iso:country":"ES",
    "sg:address":"Avda Castilla Y Leon, 8",
    "sg:city":"Guardo",
    "sg:orig_category":"Molduras, Junquillos, Listones Y Molduras Perforadas",
    "sg:phone":"+34 979 85 12 60",
    "sg:postcode":"34880",
    "sg:province":"Palencia",
    "wof:name":"Santos Huertes Ventura",
    "wof:placetype":"venue"
},
  "geometry": {"coordinates":[-4.8459038734,42.7888374329],"type":"Point"}
}