{
  "type": "Feature",
  "properties": {
    "addr:full":"Calle de Palacios, 2 Puerto De Santa Maria C\u00e1diz 11500",
    "addr:housenumber":"2",
    "addr:postcode":"11500",
    "addr:street":"Calle De Palacios;Ca\u0301Diz",
    "iso:country":"ES",
    "sg:address":"Calle de Palacios, 2",
    "sg:city":"Puerto De Santa Maria",
    "sg:orig_category":"M\u00c9dicos: Otorrinolaringolog\u00cda",
    "sg:phone":"+34 956 85 19 09",
    "sg:postcode":"11500",
    "sg:province":"C\u00e1diz",
    "wof:name":"Clinica Doctor Casimiro S.l.",
    "wof:placetype":"venue"
},
  "geometry": {"coordinates":[-6.224878788,36.5971107483],"type":"Point"}
}