{
  "type": "Feature",
  "properties": {
    "addr:full":"Calle de Santa Engracia, 101 Madrid Madrid 28010",
    "addr:housenumber":"101",
    "addr:postcode":"28010",
    "addr:street":"Calle De Santa Engracia",
    "iso:country":"ES",
    "sg:address":"Calle de Santa Engracia, 101",
    "sg:city":"Madrid",
    "sg:orig_category":"Bisuter\u00cda, Joyer\u00cda, Relojer\u00cda (al Por Menor)",
    "sg:phone":"+34 914 48 66 84",
    "sg:postcode":"28010",
    "sg:province":"Madrid",
    "wof:name":"Santiago Lopez Ramiro",
    "wof:placetype":"venue"
},
  "geometry": {"coordinates":[-3.699575901,40.4368057251],"type":"Point"}
}