{
  "type": "Feature",
  "properties": {
    "iso:country":"ES",
    "sg:address":"Avda Industria (de La), 6",
    "sg:city":"Coslada",
    "sg:orig_category":"Aluminio Y Aleaciones (producci\u00d3n, Transformaci\u00d3n, Negocio)",
    "sg:phone":"+34 914 85 27 50",
    "sg:postcode":"28820",
    "sg:province":"Madrid",
    "sg:website":"www.grupoayuso.org",
    "wof:name":"Aluminios Ayuso S. L.",
    "wof:placetype":"venue"
},
  "geometry": {"coordinates":[-3.5569529533,40.4294624329],"type":"Point"}
}