{
  "type": "Feature",
  "properties": {
    "addr:full":"Carrer de Solsones, S/n Poligon Industrial Barcelona 08759",
    "addr:housenumber":"s / n",
    "addr:postcode":"08759",
    "addr:street":"Carrer De Solsones;Industrial Barcelona",
    "iso:country":"ES",
    "sg:address":"Carrer de Solsones, S/n",
    "sg:city":"Poligon Industrial",
    "sg:orig_category":"Fabricaci\u00d3n, Importaci\u00d3n De L\u00c1mparas Y Bombillas",
    "sg:phone":"+34 933 37 64 31",
    "sg:postcode":"08759",
    "sg:province":"Barcelona",
    "sg:website":"www.diart.es/www.diart.anthill.es",
    "wof:name":"Diart Iluminacion S. L.",
    "wof:placetype":"venue"
},
  "geometry": {"coordinates":[1.9203499556,41.380191803],"type":"Point"}
}