{
  "type": "Feature",
  "properties": {
    "addr:full":"San Antolin, 17 Legutiano \u00c1lava 01170",
    "addr:housenumber":"17",
    "addr:postcode":"01170",
    "addr:street":"San Antolin",
    "iso:country":"ES",
    "sg:address":"San Antolin, 17",
    "sg:city":"Legutiano",
    "sg:orig_category":"Postigos, Persianas Y Celos\u00cdas",
    "sg:phone":"+34 945 46 50 54",
    "sg:postcode":"01170",
    "sg:province":"\u00c1lava",
    "wof:name":"Area 2 S.l.",
    "wof:placetype":"venue"
},
  "geometry": {"coordinates":[-2.6500940323,42.9477996826],"type":"Point"}
}