{
  "type": "Feature",
  "properties": {
    "addr:full":"Avda Malvarrosa, 10 Valencia Valencia 46011",
    "addr:housenumber":"10",
    "addr:postcode":"46011",
    "addr:street":"Avda Malvarrosa",
    "iso:country":"ES",
    "sg:address":"Avda Malvarrosa, 10",
    "sg:city":"Valencia",
    "sg:orig_category":"Asociaciones, Organismos Culturales Y Socioeducativos",
    "sg:phone":"+34 963 71 15 29",
    "sg:postcode":"46011",
    "sg:province":"Valencia",
    "wof:name":"Diaz Boils Berta",
    "wof:placetype":"venue"
},
  "geometry": {"coordinates":[-0.3274770081,39.4760818481],"type":"Point"}
}