{
  "type": "Feature",
  "properties": {
    "addr:full":"Ctra Alcabon, S/n Santa Olalla Toledo 45530",
    "addr:housenumber":"s / n",
    "addr:postcode":"45530",
    "addr:street":"Ctra Alcabon",
    "iso:country":"ES",
    "sg:address":"Ctra Alcabon, S/n",
    "sg:city":"Santa Olalla",
    "sg:orig_category":"Sales (al Por Mayor)",
    "sg:phone":"+34 925 79 71 84",
    "sg:postcode":"45530",
    "sg:province":"Toledo",
    "wof:name":"Mazapanes Y Dulces De Toledo S. A.",
    "wof:placetype":"venue"
},
  "geometry": {"coordinates":[-4.3834729195,40.0066719055],"type":"Point"}
}