{
  "type": "Feature",
  "properties": {
    "iso:country":"ES",
    "sg:address":"Grup Andalucia Residencial Fase I, 1",
    "sg:city":"Sevilla",
    "sg:orig_category":"Abogados",
    "sg:phone":"+34 954 40 83 91",
    "sg:postcode":"41020",
    "sg:province":"Sevilla",
    "wof:name":"Moreno Vioque Maria Luisa",
    "wof:placetype":"venue"
},
  "geometry": {"coordinates":[-5.9333291054,37.4165763855],"type":"Point"}
}