{
  "type": "Feature",
  "properties": {
    "addr:full":"Calle de Arrandi, 34 San Vicente De Barakaldo Vizcaya 48901",
    "addr:housenumber":"34",
    "addr:postcode":"48901",
    "addr:street":"Calle De Arrandi",
    "iso:country":"ES",
    "sg:address":"Calle de Arrandi, 34",
    "sg:city":"San Vicente De Barakaldo",
    "sg:orig_category":"Hilaturas, Hilos Y Actividades Relacionadas",
    "sg:phone":"+34 944 78 20 88",
    "sg:postcode":"48901",
    "sg:province":"Vizcaya",
    "wof:name":"Lobo Caballero Antonio",
    "wof:placetype":"venue"
},
  "geometry": {"coordinates":[-2.9864518642,43.2950363159],"type":"Point"}
}