{
  "type": "Feature",
  "properties": {
    "addr:full":"Calle de Rio Pisuerga, 2 Moron Frontera Sevilla 41530",
    "addr:housenumber":"2",
    "addr:postcode":"41530",
    "addr:street":"Calle De Rio Pisuerga",
    "iso:country":"ES",
    "sg:address":"Calle de Rio Pisuerga, 2",
    "sg:city":"Moron Frontera",
    "sg:orig_category":"Electrodom\u00c9sticos (al Por Menor)",
    "sg:phone":"+34 955 85 33 32",
    "sg:postcode":"41530",
    "sg:province":"Sevilla",
    "wof:name":"Moron Cocinas S.l.",
    "wof:placetype":"venue"
},
  "geometry": {"coordinates":[-5.4540319443,37.1232948303],"type":"Point"}
}