{
  "type": "Feature",
  "properties": {
    "addr:full":"Carrer de Laurea Miro, 207 Esplugues Llobregat Barcelona 08950",
    "addr:housenumber":"207",
    "addr:postcode":"08950",
    "addr:street":"Carrer De Laurea Miro",
    "iso:country":"ES",
    "sg:address":"Carrer de Laurea Miro, 207",
    "sg:city":"Esplugues Llobregat",
    "sg:orig_category":"Fabricaci\u00d3n De Juguetes Autom\u00c1ticos",
    "sg:phone":"+34 933 72 91 97",
    "sg:postcode":"08950",
    "sg:province":"Barcelona",
    "wof:name":"Mayo Chavero Manuel",
    "wof:placetype":"venue"
},
  "geometry": {"coordinates":[2.0878810883,41.3773002625],"type":"Point"}
}