{
  "type": "Feature",
  "properties": {
    "addr:full":"Avda Perez Galdos, 91 Valencia Valencia 46018",
    "addr:housenumber":"91",
    "addr:postcode":"46018",
    "addr:street":"Avda Perez Galdos",
    "iso:country":"ES",
    "sg:address":"Avda Perez Galdos, 91",
    "sg:city":"Valencia",
    "sg:orig_category":"Droguer\u00cdas (al Por Menor)",
    "sg:phone":"+34 963 85 85 43",
    "sg:postcode":"46018",
    "sg:province":"Valencia",
    "wof:name":"Chamorro Vera Bernardo",
    "wof:placetype":"venue"
},
  "geometry": {"coordinates":[-0.3922489882,39.4698791504],"type":"Point"}
}