{
  "type": "Feature",
  "properties": {
    "addr:full":"Calle de Estacion, 3 Irun Guip\u00f9zcoa 20301",
    "addr:housenumber":"3",
    "addr:postcode":"20301",
    "addr:street":"Calle De Estacion;Guipu\u0300Zcoa",
    "iso:country":"ES",
    "sg:address":"Calle de Estacion, 3",
    "sg:city":"Irun",
    "sg:orig_category":"Librer\u00cdas",
    "sg:phone":"+34 943 61 82 21",
    "sg:postcode":"20301",
    "sg:province":"Guip\u00f9zcoa",
    "wof:name":"Cansado Becerra Francisco",
    "wof:placetype":"venue"
},
  "geometry": {"coordinates":[-1.7981649637,43.3410835266],"type":"Point"}
}