{
  "type": "Feature",
  "properties": {
    "addr:full":"Carrer de Sant Gervasi De Cassoles, 94 Barcelona Barcelona 08022",
    "addr:housenumber":"94",
    "addr:postcode":"08022",
    "addr:street":"Carrer De Sant Gervasi De Cassoles",
    "iso:country":"ES",
    "sg:address":"Carrer de Sant Gervasi De Cassoles, 94",
    "sg:city":"Barcelona",
    "sg:orig_category":"Cueros Y Pieles (al Por Mayor)",
    "sg:phone":"+34 932 11 14 01",
    "sg:postcode":"08022",
    "sg:province":"Barcelona",
    "wof:name":"Gil Villar Pedro Jose",
    "wof:placetype":"venue"
},
  "geometry": {"coordinates":[2.1351530552,41.4063835144],"type":"Point"}
}