{
  "type": "Feature",
  "properties": {
    "iso:country":"ES",
    "sg:address":"Calle de Isaac Peral, 42",
    "sg:city":"Rota",
    "sg:orig_category":"Costureras",
    "sg:phone":"+34 956 81 06 52",
    "sg:postcode":"11520",
    "sg:province":"C\u00e1diz",
    "wof:name":"Rizo Lopez Rosario",
    "wof:placetype":"venue"
},
  "geometry": {"coordinates":[-6.3575549126,36.6204986572],"type":"Point"}
}