{
  "type": "Feature",
  "properties": {
    "addr:full":"Calle de Emilio Mari, 8 Valencia Valencia 46025",
    "addr:housenumber":"8",
    "addr:postcode":"46025",
    "addr:street":"Calle De Emilio Mari",
    "iso:country":"ES",
    "sg:address":"Calle de Emilio Mari, 8",
    "sg:city":"Valencia",
    "sg:orig_category":"Mec\u00c1nico Del Autom\u00d3vil",
    "sg:phone":"+34 963 40 41 35",
    "sg:postcode":"46025",
    "sg:province":"Valencia",
    "wof:name":"Valls Moreno S. L.",
    "wof:placetype":"venue"
},
  "geometry": {"coordinates":[-0.3940959871,39.4938201904],"type":"Point"}
}