{
  "type": "Feature",
  "properties": {
    "iso:country":"ES",
    "sg:address":"Calle de Fueros (los), 9",
    "sg:city":"Getxo",
    "sg:orig_category":"Edici\u00d3n De Diarios, Revistas, Boletines",
    "sg:phone":"+34 944 60 46 86",
    "sg:postcode":"48990",
    "sg:province":"Vizcaya",
    "wof:name":"Miguel Castellanos Jimenez",
    "wof:placetype":"venue"
},
  "geometry": {"coordinates":[-3.0061919689,43.3446044922],"type":"Point"}
}