{
  "type": "Feature",
  "properties": {
    "iso:country":"ES",
    "sg:address":"Mcdo Feria, S/n",
    "sg:city":"Sevilla",
    "sg:orig_category":"Pescader\u00cdas (al Por Menor)",
    "sg:phone":"+34 954 37 20 60",
    "sg:postcode":"41003",
    "sg:province":"Sevilla",
    "wof:name":"Cabrera Garcia Jose Miguel",
    "wof:placetype":"venue"
},
  "geometry": {"coordinates":[-5.9917340279,37.3999595642],"type":"Point"}
}