{
  "type": "Feature",
  "properties": {
    "addr:full":"Carr Pablo Iglesias, 11 Badalona Barcelona 08914",
    "addr:housenumber":"11",
    "addr:postcode":"08914",
    "addr:street":"Carr Pablo Iglesias",
    "iso:country":"ES",
    "sg:address":"Carr Pablo Iglesias, 11",
    "sg:city":"Badalona",
    "sg:orig_category":"Compresores",
    "sg:phone":"+34 932 25 50 45",
    "sg:postcode":"08914",
    "sg:province":"Barcelona",
    "wof:name":"Instalacions De Dire Industrials Pheneum",
    "wof:placetype":"venue"
},
  "geometry": {"coordinates":[2.223608017,41.445148468],"type":"Point"}
}