{
  "type": "Feature",
  "properties": {
    "iso:country":"ES",
    "sg:address":"Calle de Aragon, 84",
    "sg:city":"Sevilla",
    "sg:orig_category":"Mec\u00c1nico Del Autom\u00d3vil",
    "sg:phone":"+34 954 92 48 57",
    "sg:postcode":"41006",
    "sg:province":"Sevilla",
    "wof:name":"Lopez Vicente Enrique",
    "wof:placetype":"venue"
},
  "geometry": {"coordinates":[-5.9611988068,37.374912262],"type":"Point"}
}