{
  "type": "Feature",
  "properties": {
    "iso:country":"ES",
    "sg:address":"Pl Espanya, 3",
    "sg:city":"Palma",
    "sg:orig_category":"Restaurantes: Restauraci\u00d3n R\u00c1pida Y Autoservicio",
    "sg:phone":"+34 971 72 10 75",
    "sg:postcode":"07002",
    "sg:province":"Islas Baleares",
    "wof:name":"Trili S.l.",
    "wof:placetype":"venue"
},
  "geometry": {"coordinates":[2.653331995,39.5760383606],"type":"Point"}
}