{
  "type": "Feature",
  "properties": {
    "iso:country":"ES",
    "sg:address":"Calle de Hospital De Mujeres, 72",
    "sg:city":"Cadiz",
    "sg:orig_category":"Alimentaci\u00d3n General (al Por Menor)",
    "sg:phone":"+34 956 22 71 64",
    "sg:postcode":"11002",
    "sg:province":"C\u00e1diz",
    "wof:name":"Senra Freire Manuel",
    "wof:placetype":"venue"
},
  "geometry": {"coordinates":[-6.3026471138,36.5325927734],"type":"Point"}
}