{
  "type": "Feature",
  "properties": {
    "addr:full":"Carrer de Paris, 64 Barcelona Barcelona 08029",
    "addr:housenumber":"64",
    "addr:postcode":"08029",
    "addr:street":"Carrer De Paris",
    "iso:country":"ES",
    "sg:address":"Carrer de Paris, 64",
    "sg:city":"Barcelona",
    "sg:orig_category":"M\u00c9dicos: Dermatolog\u00cda Y Venereolog\u00cda",
    "sg:phone":"+34 934 19 30 80",
    "sg:postcode":"08029",
    "sg:province":"Barcelona",
    "wof:name":"Bassas Miquel Ignacio",
    "wof:placetype":"venue"
},
  "geometry": {"coordinates":[2.1446568966,41.3869895935],"type":"Point"}
}