{
  "type": "Feature",
  "properties": {
    "addr:full":"Polg I Ntra Sra Estrella, S/n Coria Rio Sevilla 41100",
    "addr:housenumber":"s",
    "addr:postcode":"41100",
    "addr:street":"/ N",
    "iso:country":"ES",
    "sg:address":"Polg I Ntra Sra Estrella, S/n",
    "sg:city":"Coria Rio",
    "sg:orig_category":"Poller\u00cda Y Caza (al Por Menor)",
    "sg:phone":"+34 954 77 56 42",
    "sg:postcode":"41100",
    "sg:province":"Sevilla",
    "wof:name":"La Saga Avicola S.l.",
    "wof:placetype":"venue"
},
  "geometry": {"coordinates":[-6.0509738922,37.2873153687],"type":"Point"}
}