{
  "type": "Feature",
  "properties": {
    "addr:full":"Calle de Valle Ballina Y Fernandez, 7 Villaviciosa Asturias 33300",
    "addr:housenumber":"7",
    "addr:postcode":"33300",
    "addr:street":"Calle De Valle;Y Fernandez",
    "iso:country":"ES",
    "sg:address":"Calle de Valle Ballina Y Fernandez, 7",
    "sg:city":"Villaviciosa",
    "sg:orig_category":"Peluqueros: De Se\u00d1oras",
    "sg:phone":"+34 985 89 27 71",
    "sg:postcode":"33300",
    "sg:province":"Asturias",
    "wof:name":"Suarez Vega Imelda",
    "wof:placetype":"venue"
},
  "geometry": {"coordinates":[-5.4347896576,43.4810943604],"type":"Point"}
}