{
  "type": "Feature",
  "properties": {
    "iso:country":"ES",
    "sg:address":"Calle de Lopez Sancho, S/n",
    "sg:city":"Granada",
    "sg:orig_category":"Chapister\u00cda",
    "sg:phone":"+34 958 29 16 70",
    "sg:postcode":"18015",
    "sg:province":"Granada",
    "wof:name":"Rodriguez Lopez Mario",
    "wof:placetype":"venue"
},
  "geometry": {"coordinates":[-3.6260240078,37.1917610168],"type":"Point"}
}