{
  "type": "Feature",
  "properties": {
    "addr:full":"Pl Gal.la Placidia, 24 Barcelona Barcelona 08006",
    "addr:housenumber":"24",
    "addr:postcode":"08006",
    "addr:street":"Pl Gal.La Placidia",
    "iso:country":"ES",
    "sg:address":"Pl Gal.la Placidia, 24",
    "sg:city":"Barcelona",
    "sg:orig_category":"Loter\u00cda Y T\u00d3mbola",
    "sg:phone":"+34 934 15 37 34",
    "sg:postcode":"08006",
    "sg:province":"Barcelona",
    "wof:name":"Ferrer Oliveras Maria Gloria",
    "wof:placetype":"venue"
},
  "geometry": {"coordinates":[2.1528069973,41.3997001648],"type":"Point"}
}