{
  "type": "Feature",
  "properties": {
    "iso:country":"ES",
    "sg:address":"Ctra. Puebla Sanabria, S/n",
    "sg:city":"El Puente",
    "sg:orig_category":"Hoteles",
    "sg:phone":"+34 980 62 02 17",
    "sg:postcode":"49350",
    "sg:province":"Zamora",
    "wof:name":"Hernando Panchito Manuel",
    "wof:placetype":"venue"
},
  "geometry": {"coordinates":[-6.6421990395,42.0836639404],"type":"Point"}
}