{
  "type": "Feature",
  "properties": {
    "iso:country":"ES",
    "sg:address":"Rond Sant Pere, 16",
    "sg:city":"Barcelona",
    "sg:orig_category":"\u00d3ptica: Instrumentos (fabricaci\u00d3n)",
    "sg:phone":"+34 933 01 82 49",
    "sg:postcode":"08010",
    "sg:province":"Barcelona",
    "wof:name":"Jurasil S.l.",
    "wof:placetype":"venue"
},
  "geometry": {"coordinates":[2.1715600491,41.3883552551],"type":"Point"}
}