{
  "type": "Feature",
  "properties": {
    "addr:full":"Muel Nardiz Tar Benanzio, 14 Bermeo Vizcaya 48370",
    "addr:housenumber":"14",
    "addr:postcode":"48370",
    "addr:street":"Benanzio",
    "iso:country":"ES",
    "sg:address":"Muel Nardiz Tar Benanzio, 14",
    "sg:city":"Bermeo",
    "sg:orig_category":"Asociaciones, Organismos Culturales Y Socioeducativos",
    "sg:phone":"+34 946 88 31 03",
    "sg:postcode":"48370",
    "sg:province":"Vizcaya",
    "wof:name":"Asociacion Recreativa Y Gastronomica Kai-gane De Bermeo",
    "wof:placetype":"venue"
},
  "geometry": {"coordinates":[-2.7481176853,43.4026641846],"type":"Point"}
}