{
  "type": "Feature",
  "properties": {
    "iso:country":"ES",
    "sg:address":"Avda Encarnacion, S/n",
    "sg:city":"Fuengirola",
    "sg:orig_category":"Bisuter\u00cda, Joyer\u00cda, Relojer\u00cda (al Por Menor)",
    "sg:phone":"+34 952 19 87 01",
    "sg:postcode":"29640",
    "sg:province":"M\u00e1laga",
    "wof:name":"Aranda Gimeno Cristina",
    "wof:placetype":"venue"
},
  "geometry": {"coordinates":[-4.6322612762,36.5266304016],"type":"Point"}
}