{
  "type": "Feature",
  "properties": {
    "iso:country":"ES",
    "sg:address":"Calle de San Andres, 14",
    "sg:city":"Jaen",
    "sg:orig_category":"Material Y Suministros Para Perforaciones, Sondeos",
    "sg:phone":"+34 953 24 37 59",
    "sg:postcode":"23003",
    "sg:province":"Ja\u00e9n",
    "wof:name":"Carrasco Garcia Jose",
    "wof:placetype":"venue"
},
  "geometry": {"coordinates":[-3.7923231125,37.7714271545],"type":"Point"}
}