{
  "type": "Feature",
  "properties": {
    "iso:country":"ES",
    "sg:address":"Avda Ronda (de), 97",
    "sg:city":"Elda",
    "sg:orig_category":"Afilado",
    "sg:phone":"+34 965 38 43 97",
    "sg:postcode":"03600",
    "sg:province":"Alicante",
    "wof:name":"Rueda Romero Joaquin",
    "wof:placetype":"venue"
},
  "geometry": {"coordinates":[-0.8011289835,38.477809906],"type":"Point"}
}