{
  "type": "Feature",
  "properties": {
    "iso:country":"ES",
    "sg:address":"Carrer de Pasqual Ribot, 7",
    "sg:city":"Palma",
    "sg:orig_category":"Confecci\u00d3n De Ropa Interior",
    "sg:phone":"+34 971 28 13 14",
    "sg:postcode":"07011",
    "sg:province":"Islas Baleares",
    "wof:name":"Mesquida Blanco Eva Maria",
    "wof:placetype":"venue"
},
  "geometry": {"coordinates":[2.638864994,39.5783042908],"type":"Point"}
}