{
  "type": "Feature",
  "properties": {
    "addr:full":"Calle de Arroyo, 3 Toledo Toledo 45006",
    "addr:housenumber":"3",
    "addr:postcode":"45006",
    "addr:street":"Calle De Arroyo",
    "iso:country":"ES",
    "sg:address":"Calle de Arroyo, 3",
    "sg:city":"Toledo",
    "sg:orig_category":"Pescader\u00cdas (al Por Menor)",
    "sg:phone":"+34 925 25 00 53",
    "sg:postcode":"45006",
    "sg:province":"Toledo",
    "wof:name":"Villar Moreno Yolanda Del",
    "wof:placetype":"venue"
},
  "geometry": {"coordinates":[-4.0053591728,39.8586082458],"type":"Point"}
}