{
  "type": "Feature",
  "properties": {
    "iso:country":"ES",
    "sg:address":"Calle de Nuria, 59",
    "sg:city":"Madrid",
    "sg:orig_category":"Gastronom\u00cda: Especialidades Regionales (al Por Menor)",
    "sg:phone":"+34 917 35 00 82",
    "sg:postcode":"28034",
    "sg:province":"Madrid",
    "wof:name":"Pasamar Gonzalo Arturo",
    "wof:placetype":"venue"
},
  "geometry": {"coordinates":[-3.7069985867,40.4926643372],"type":"Point"}
}