{
  "type": "Feature",
  "properties": {
    "iso:country":"ES",
    "sg:address":"Calle de Azagra, 2",
    "sg:city":"Albarracin",
    "sg:orig_category":"Restaurantes",
    "sg:phone":"+34 978 70 03 55",
    "sg:postcode":"44100",
    "sg:province":"Teruel",
    "wof:name":"Lopez Benitez Jorge Luis",
    "wof:placetype":"venue"
},
  "geometry": {"coordinates":[-1.4424058199,40.4080963135],"type":"Point"}
}