{
  "type": "Feature",
  "properties": {
    "addr:full":"Calle de Betis, 9 Sevilla Sevilla 41010",
    "addr:housenumber":"9",
    "addr:postcode":"41010",
    "addr:street":"Calle De Betis",
    "iso:country":"ES",
    "sg:address":"Calle de Betis, 9",
    "sg:city":"Sevilla",
    "sg:orig_category":"Sociedades, Compa\u00d1\u00cdas Aseguradoras",
    "sg:phone":"+34 954 33 90 81",
    "sg:postcode":"41010",
    "sg:province":"Sevilla",
    "wof:name":"Seguros Agencia Triana S.c.",
    "wof:placetype":"venue"
},
  "geometry": {"coordinates":[-6.0019841194,37.3849639893],"type":"Point"}
}