{
  "type": "Feature",
  "properties": {
    "iso:country":"ES",
    "sg:address":"Calle de Santa Ana, 9",
    "sg:city":"Plasencia",
    "sg:orig_category":"Arquitectos",
    "sg:phone":"+34 927 42 34 50",
    "sg:postcode":"10600",
    "sg:province":"C\u00e1ceres",
    "wof:name":"Perez Nieto Manuel",
    "wof:placetype":"venue"
},
  "geometry": {"coordinates":[-6.0888929367,40.0317459106],"type":"Point"}
}