{
  "type": "Feature",
  "properties": {
    "addr:full":"Urb. Saporo, S/n Vielha Lleida 25530",
    "addr:housenumber":"s / n",
    "addr:postcode":"25530",
    "iso:country":"ES",
    "sg:address":"Urb. Saporo, S/n",
    "sg:city":"Vielha",
    "sg:orig_category":"Inmobiliaria (agencias)",
    "sg:phone":"+34 973 64 20 72",
    "sg:postcode":"25530",
    "sg:province":"Lleida",
    "wof:name":"Inversiones Vallesanas S.l.",
    "wof:placetype":"venue"
},
  "geometry": {"coordinates":[0.793775022,42.70287323],"type":"Point"}
}