{
  "type": "Feature",
  "properties": {
    "iso:country":"ES",
    "sg:address":"Calle de Rodriguez De Cepeda, 55",
    "sg:city":"Valencia",
    "sg:orig_category":"Cajas De Ahorro",
    "sg:phone":"+34 963 69 34 96",
    "sg:postcode":"46021",
    "sg:province":"Valencia",
    "sg:website":"www.bancaja.es",
    "wof:name":"Caja De Ahorros De Valencia Castellon Y Alicante",
    "wof:placetype":"venue"
},
  "geometry": {"coordinates":[-0.3508200049,39.4681053162],"type":"Point"}
}