{
  "type": "Feature",
  "properties": {
    "addr:full":"Calle de Iscar Peyra, 29 Salamanca Salamanca 37002",
    "addr:housenumber":"29",
    "addr:postcode":"37002",
    "addr:street":"Calle De Iscar Peyra",
    "iso:country":"ES",
    "sg:address":"Calle de Iscar Peyra, 29",
    "sg:city":"Salamanca",
    "sg:classifiers":[
        {
            "category":"Autos & Motor Vehicles",
            "subcategory":"Automobile Sales",
            "type":"Retail Goods"
        }
    ],
    "sg:phone":"+34 923 27 15 85",
    "sg:postcode":"37002",
    "sg:province":"Salamanca",
    "wof:name":"Ruano Bernal Claudio",
    "wof:placetype":"venue"
},
  "geometry": {"coordinates":[-5.6658377647,40.9661865234],"type":"Point"}
}