{
  "type": "Feature",
  "properties": {
    "addr:full":"Calle de San Pedro De Carde\u00d1a, 30 Burgos Burgos 09002",
    "addr:housenumber":"30",
    "addr:postcode":"09002",
    "addr:street":"Calle De;Carden\u0303A",
    "iso:country":"ES",
    "sg:address":"Calle de San Pedro De Carde\u00d1a, 30",
    "sg:city":"Burgos",
    "sg:orig_category":"Artes Gr\u00c1ficas, Artes Pl\u00c1sticas (curso)",
    "sg:phone":"+34 947 26 41 77",
    "sg:postcode":"09002",
    "sg:province":"Burgos",
    "wof:name":"Martinez Del Rio Joaquin Maria",
    "wof:placetype":"venue"
},
  "geometry": {"coordinates":[-3.6903250217,42.3384590149],"type":"Point"}
}