{
  "type": "Feature",
  "properties": {
    "addr:full":"Avda Doctor Meca, 28 Puerto Mazarron Murcia 30860",
    "addr:housenumber":"28",
    "addr:postcode":"30860",
    "addr:street":"Avda Doctor Meca",
    "iso:country":"ES",
    "sg:address":"Avda Doctor Meca, 28",
    "sg:city":"Puerto Mazarron",
    "sg:orig_category":"Agencias De Viajes",
    "sg:phone":"+34 968 59 55 84",
    "sg:postcode":"30860",
    "sg:province":"Murcia",
    "sg:website":"www.drantours.net",
    "wof:name":"Dragon Tours S.l.",
    "wof:placetype":"venue"
},
  "geometry": {"coordinates":[-1.2608629465,37.5671958923],"type":"Point"}
}