{
  "type": "Feature",
  "properties": {
    "iso:country":"ES",
    "sg:address":"Calle de Padre Marin, 14",
    "sg:city":"Logro\u00f1o",
    "sg:orig_category":"Alimentaci\u00d3n General (al Por Menor)",
    "sg:phone":"+34 941 24 86 50",
    "sg:postcode":"26004",
    "sg:province":"La Rioja",
    "wof:name":"Martinez Ochoa Alberto",
    "wof:placetype":"venue"
},
  "geometry": {"coordinates":[-2.4303929806,42.4648971558],"type":"Point"}
}