{
  "type": "Feature",
  "properties": {
    "iso:country":"ES",
    "sg:address":"Rua Gomez Ulla (de), 8",
    "sg:city":"Santiago De Compostela",
    "sg:orig_category":"Alquiler De Veh\u00cdculos: Turismos Y Utilitarios",
    "sg:phone":"+34 981 56 55 24",
    "sg:postcode":"15702",
    "sg:province":"La Coru\u00f1a",
    "sg:website":"www.autosbrea.com",
    "wof:name":"Autos Brea S. L.",
    "wof:placetype":"venue"
},
  "geometry": {"coordinates":[-8.543548584,42.8752822876],"type":"Point"}
}