{
  "type": "Feature",
  "properties": {
    "iso:country":"ES",
    "sg:address":"Calle de Iliada, 15",
    "sg:city":"Madrid",
    "sg:orig_category":"Caf\u00c9s, Bares, Cervecer\u00cdas",
    "sg:phone":"+34 917 42 28 66",
    "sg:postcode":"28022",
    "sg:province":"Madrid",
    "wof:name":"Cafe Coke S.l.",
    "wof:placetype":"venue"
},
  "geometry": {"coordinates":[-3.6102991104,40.4352378845],"type":"Point"}
}