{
  "type": "Feature",
  "properties": {
    "addr:full":"Rua Publicista Saralegui Y Medina, 12 Ferrol La Coru\u00f1a 15403",
    "addr:housenumber":"12",
    "addr:postcode":"15403",
    "addr:street":"Rua Publicista Saralegui Y Medina;La Corun\u0303A",
    "iso:country":"ES",
    "sg:address":"Rua Publicista Saralegui Y Medina, 12",
    "sg:city":"Ferrol",
    "sg:orig_category":"Fabricaci\u00d3n De Juguetes Autom\u00c1ticos",
    "sg:phone":"+34 981 33 00 54",
    "sg:postcode":"15403",
    "sg:province":"La Coru\u00f1a",
    "wof:name":"Comar Rias Altas",
    "wof:placetype":"venue"
},
  "geometry": {"coordinates":[-8.224568367,43.4887695312],"type":"Point"}
}