{
  "type": "Feature",
  "properties": {
    "iso:country":"ES",
    "sg:address":"Ctra Sax, 34",
    "sg:city":"Elda",
    "sg:orig_category":"Ambulancias",
    "sg:phone":"+34 965 39 85 08",
    "sg:postcode":"03600",
    "sg:province":"Alicante",
    "wof:name":"S.o.s. Benidorm Ambulancias S.l.",
    "wof:placetype":"venue"
},
  "geometry": {"coordinates":[-0.8026729822,38.490737915],"type":"Point"}
}