{
  "type": "Feature",
  "properties": {
    "addr:full":"Aire, 5 Campamento C\u00e1diz 11314",
    "addr:housenumber":"5",
    "addr:postcode":"11314",
    "addr:street":"Aire;Ca\u0301Diz",
    "iso:country":"ES",
    "sg:address":"Aire, 5",
    "sg:city":"Campamento",
    "sg:orig_category":"Enfermeras: Consultas, Atenci\u00d3n A Domicilio",
    "sg:phone":"+34 956 69 88 94",
    "sg:postcode":"11314",
    "sg:province":"C\u00e1diz",
    "wof:name":"Luna Portillo Manuel",
    "wof:placetype":"venue"
},
  "geometry": {"coordinates":[-5.3743262291,36.1766204834],"type":"Point"}
}