{
  "type": "Feature",
  "properties": {
    "iso:country":"ES",
    "sg:address":"Carrer de Regal, 47",
    "sg:city":"Palma",
    "sg:orig_category":"Electrodom\u00c9sticos (al Por Menor)",
    "sg:phone":"+34 971 24 79 85",
    "sg:postcode":"07008",
    "sg:province":"Islas Baleares",
    "wof:name":"Planas Mas Nadal",
    "wof:placetype":"venue"
},
  "geometry": {"coordinates":[2.6723380089,39.5746955872],"type":"Point"}
}