{
  "type": "Feature",
  "properties": {
    "iso:country":"ES",
    "sg:address":"Calle de Jose Echegaray (de), 4",
    "sg:city":"Alcobendas",
    "sg:orig_category":"Molduras, Junquillos, Listones Y Molduras Perforadas",
    "sg:phone":"+34 916 61 04 27",
    "sg:postcode":"28100",
    "sg:province":"Madrid",
    "wof:name":"Proinal S.l.",
    "wof:placetype":"venue"
},
  "geometry": {"coordinates":[-3.6545488834,40.5417098999],"type":"Point"}
}