{
  "type": "Feature",
  "properties": {
    "addr:full":"Ctra Nacional Iii, Km. 0323,0 Chiva Valencia 46370",
    "addr:postcode":"46370",
    "addr:street":"Ctra Nacional Iii Km. 0323,0",
    "iso:country":"ES",
    "sg:address":"Ctra Nacional Iii, Km. 0323,0",
    "sg:city":"Chiva",
    "sg:orig_category":"Carros Elevadores, Carros De Operaciones Portuarias",
    "sg:phone":"+34 962 52 45 00",
    "sg:postcode":"46370",
    "sg:province":"Valencia",
    "sg:website":"www.clem.es",
    "wof:name":"Serviclems.l.",
    "wof:placetype":"venue"
},
  "geometry": {"coordinates":[-0.7179690003,39.4728012085],"type":"Point"}
}