{
  "type": "Feature",
  "properties": {
    "iso:country":"ES",
    "sg:address":"Psaj Archanda, 7",
    "sg:city":"Malaga",
    "sg:orig_category":"Animales (al Por Menor)",
    "sg:phone":"+34 952 61 18 79",
    "sg:postcode":"29010",
    "sg:province":"M\u00e1laga",
    "wof:name":"Amador Guerrero Maria Jose",
    "wof:placetype":"venue"
},
  "geometry": {"coordinates":[-4.5108861923,36.7505378723],"type":"Point"}
}