{
  "type": "Feature",
  "properties": {
    "addr:full":"Carrer de Sant Roc, 19 Barcelona Barcelona 08014",
    "addr:housenumber":"19",
    "addr:postcode":"08014",
    "addr:street":"Carrer De Sant Roc",
    "iso:country":"ES",
    "sg:address":"Carrer de Sant Roc, 19",
    "sg:city":"Barcelona",
    "sg:orig_category":"Molduras, Junquillos, Listones Y Molduras Perforadas",
    "sg:phone":"+34 934 23 67 16",
    "sg:postcode":"08014",
    "sg:province":"Barcelona",
    "wof:name":"Crespo Gomez Maria Carmen",
    "wof:placetype":"venue"
},
  "geometry": {"coordinates":[2.1455891132,41.3737487793],"type":"Point"}
}