{
  "type": "Feature",
  "properties": {
    "addr:full":"Ctra. Marcilla, Km. 0002,0 Peralta Navarra 31350",
    "addr:postcode":"31350",
    "addr:street":"Ctra. Marcilla Km. 0002,0",
    "iso:country":"ES",
    "sg:address":"Ctra. Marcilla, Km. 0002,0",
    "sg:city":"Peralta",
    "sg:orig_category":"Fabricaci\u00d3n De Distribuidores Autom\u00c1ticos",
    "sg:phone":"+34 948 75 17 92",
    "sg:postcode":"31350",
    "sg:province":"Navarra",
    "wof:name":"Jofemar S. A.",
    "wof:placetype":"venue"
},
  "geometry": {"coordinates":[-1.8050489426,42.3389167786],"type":"Point"}
}