{
  "type": "Feature",
  "properties": {
    "iso:country":"ES",
    "sg:address":"Ptge Sisternes, 4",
    "sg:city":"Mataro",
    "sg:orig_category":"Electricidad, Electr\u00d3nica: Material Y Suministros (al Por Mayor)",
    "sg:phone":"+34 937 57 18 17",
    "sg:postcode":"08302",
    "sg:province":"Barcelona",
    "wof:name":"Farres Font Joaquin",
    "wof:placetype":"venue"
},
  "geometry": {"coordinates":[2.4403269291,41.5432701111],"type":"Point"}
}