{
  "type": "Feature",
  "properties": {
    "iso:country":"ES",
    "sg:address":"Calle de Sancho Panza, 4",
    "sg:city":"Membrilla",
    "sg:orig_category":"Venta, Instalaci\u00d3n De Calefacci\u00d3n",
    "sg:phone":"+34 926 63 63 25",
    "sg:postcode":"13230",
    "sg:province":"Ciudad Real",
    "wof:name":"Nu\u00f1ez Lara Manuel",
    "wof:placetype":"venue"
},
  "geometry": {"coordinates":[-3.3428246975,38.9713935852],"type":"Point"}
}