{
  "type": "Feature",
  "properties": {
    "iso:country":"ES",
    "sg:address":"Plaz Nueva, 6",
    "sg:city":"Ceuti",
    "sg:orig_category":"Farmacias",
    "sg:phone":"+34 968 69 01 88",
    "sg:postcode":"30562",
    "sg:province":"Murcia",
    "wof:name":"Jara Perez Ezequiel",
    "wof:placetype":"venue"
},
  "geometry": {"coordinates":[-1.2735799551,38.0787734985],"type":"Point"}
}