{
  "type": "Feature",
  "properties": {
    "addr:full":"Carrer de Alella, 13 Barcelona Barcelona 08016",
    "addr:housenumber":"13",
    "addr:postcode":"08016",
    "addr:street":"Carrer De Alella",
    "iso:country":"ES",
    "sg:address":"Carrer de Alella, 13",
    "sg:city":"Barcelona",
    "sg:orig_category":"Cl\u00cdnicas Dentales",
    "sg:phone":"+34 934 08 51 97",
    "sg:postcode":"08016",
    "sg:province":"Barcelona",
    "wof:name":"Torres Segura Juan Carlos",
    "wof:placetype":"venue"
},
  "geometry": {"coordinates":[2.180380106,41.4313240051],"type":"Point"}
}