{
  "type": "Feature",
  "properties": {
    "iso:country":"ES",
    "sg:address":"Calle de Cadiz, 11",
    "sg:city":"Flores Del Sil",
    "sg:orig_category":"Electrodom\u00c9sticos (al Por Menor)",
    "sg:phone":"+34 987 41 03 23",
    "sg:postcode":"24400",
    "sg:province":"Le\u00f3n",
    "wof:name":"Fernandez Dominguez Elvira",
    "wof:placetype":"venue"
},
  "geometry": {"coordinates":[-6.615737915,42.5480995178],"type":"Point"}
}