{
  "type": "Feature",
  "properties": {
    "addr:full":"Pla\u00c7 Mercat Vell, 5 Silla Valencia 46460",
    "addr:housenumber":"5",
    "addr:postcode":"46460",
    "addr:street":"Silla",
    "iso:country":"ES",
    "sg:address":"Pla\u00c7 Mercat Vell, 5",
    "sg:city":"Silla",
    "sg:orig_category":"Ropa Para Ni\u00d1os (al Por Menor)",
    "sg:phone":"+34 961 21 64 12",
    "sg:postcode":"46460",
    "sg:province":"Valencia",
    "wof:name":"Marti Cantos Javier",
    "wof:placetype":"venue"
},
  "geometry": {"coordinates":[-0.4130060077,39.3623008728],"type":"Point"}
}