{
  "type": "Feature",
  "properties": {
    "iso:country":"ES",
    "sg:address":"C/ Sant Joan, 37",
    "sg:city":"Manacor",
    "sg:orig_category":"Ingenier\u00cda, Centros De Estudios (industria)",
    "sg:phone":"+34 971 84 41 92",
    "sg:postcode":"07500",
    "sg:province":"Islas Baleares",
    "wof:name":"Sanso Perello Pedro",
    "wof:placetype":"venue"
},
  "geometry": {"coordinates":[3.2118821144,39.5698013306],"type":"Point"}
}