{
  "type": "Feature",
  "properties": {
    "iso:country":"ES",
    "sg:address":"C/ Doctor Josep Maria Vilaseca, 38",
    "sg:city":"Calonge",
    "sg:orig_category":"Fabricaci\u00d3n, Importaci\u00d3n De L\u00c1mparas Y Bombillas",
    "sg:phone":"+34 972 65 03 52",
    "sg:postcode":"17251",
    "sg:province":"Girona",
    "wof:name":"Grau Puig Jacinto",
    "wof:placetype":"venue"
},
  "geometry": {"coordinates":[3.0752260685,41.8592185974],"type":"Point"}
}