{
  "type": "Feature",
  "properties": {
    "addr:full":"Av Magaluf, 13 Magaluf Islas Baleares 07181",
    "addr:housenumber":"13",
    "addr:postcode":"07181",
    "addr:street":"Av Magaluf",
    "iso:country":"ES",
    "sg:address":"Av Magaluf, 13",
    "sg:city":"Magaluf",
    "sg:orig_category":"Concepci\u00d3n Y Realizaci\u00d3n De Maquetas Profesionales Y Prototipos",
    "sg:phone":"+34 971 13 11 16",
    "sg:postcode":"07181",
    "sg:province":"Islas Baleares",
    "wof:name":"Bobby Inversiones S.l.",
    "wof:placetype":"venue"
},
  "geometry": {"coordinates":[2.5347409248,39.509021759],"type":"Point"}
}