{
  "type": "Feature",
  "properties": {
    "addr:full":"Trav. De Manzarra, 25 Bienvenida Badajoz 06250",
    "addr:housenumber":"25",
    "addr:postcode":"06250",
    "addr:street":"Trav. De Manzarra",
    "iso:country":"ES",
    "sg:address":"Trav. De Manzarra, 25",
    "sg:city":"Bienvenida",
    "sg:orig_category":"Forjas Y Altos Hornos",
    "sg:phone":"+34 924 50 60 04",
    "sg:postcode":"06250",
    "sg:province":"Badajoz",
    "wof:name":"Valle Calurano Jose",
    "wof:placetype":"venue"
},
  "geometry": {"coordinates":[-6.2099862099,38.2964286804],"type":"Point"}
}