{
  "type": "Feature",
  "properties": {
    "iso:country":"ES",
    "sg:address":"Pase Extremadura, 60",
    "sg:city":"Madrid",
    "sg:orig_category":"Zapatos (al Por Menor)",
    "sg:phone":"+34 914 63 61 93",
    "sg:postcode":"28011",
    "sg:province":"Madrid",
    "wof:name":"Calzados Bustamante S.l.",
    "wof:placetype":"venue"
},
  "geometry": {"coordinates":[-3.7302229404,40.4131584167],"type":"Point"}
}