{
  "type": "Feature",
  "properties": {
    "addr:full":"Calle de Francisco Aritio, 96 Guadalajara Guadalajara 19004",
    "addr:housenumber":"96",
    "addr:postcode":"19004",
    "addr:street":"Calle De Francisco Aritio",
    "iso:country":"ES",
    "sg:address":"Calle de Francisco Aritio, 96",
    "sg:city":"Guadalajara",
    "sg:orig_category":"Mec\u00c1nico Del Autom\u00d3vil",
    "sg:phone":"+34 949 20 30 47",
    "sg:postcode":"19004",
    "sg:province":"Guadalajara",
    "wof:name":"Autorreparaciones Pala S.a.l.",
    "wof:placetype":"venue"
},
  "geometry": {"coordinates":[-3.1912710667,40.6342926025],"type":"Point"}
}