{
  "type": "Feature",
  "properties": {
    "addr:full":"Calle de San Francisco, 5 Vitoria-gasteiz \u00c1lava 01001",
    "addr:housenumber":"5",
    "addr:postcode":"01001",
    "addr:street":"Calle De San Francisco",
    "iso:country":"ES",
    "sg:address":"Calle de San Francisco, 5",
    "sg:city":"Vitoria-gasteiz",
    "sg:orig_category":"Bazares, Art\u00cdculos De Limpieza Y De Cocina (al Por Menor)",
    "sg:phone":"+34 945 26 34 40",
    "sg:postcode":"01001",
    "sg:province":"\u00c1lava",
    "wof:name":"Fernandez De Jauregui Lopez De Abechuco Felix",
    "wof:placetype":"venue"
},
  "geometry": {"coordinates":[-2.6715888977,42.8467597961],"type":"Point"}
}