{
  "type": "Feature",
  "properties": {
    "addr:full":"Av Oscar Espla, 5 Pla Parcial Platja Alicante 03580",
    "addr:housenumber":"5",
    "addr:postcode":"03580",
    "addr:street":"Av Oscar Espla",
    "iso:country":"ES",
    "sg:address":"Av Oscar Espla, 5",
    "sg:city":"Pla Parcial Platja",
    "sg:orig_category":"Inmobiliaria (agencias)",
    "sg:phone":"+34 966 86 81 60",
    "sg:postcode":"03580",
    "sg:province":"Alicante",
    "sg:website":"www.norskboogreiseservice.com",
    "wof:name":"Norsk Bo Go Reiseservice S.l.",
    "wof:placetype":"venue"
},
  "geometry": {"coordinates":[-0.1033039987,38.5793037415],"type":"Point"}
}