{
  "type": "Feature",
  "properties": {
    "addr:full":"Calle de Suecia, 44 Madrid Madrid 28022",
    "addr:housenumber":"44",
    "addr:postcode":"madrid;28022",
    "addr:street":"Calle De Suecia",
    "iso:country":"ES",
    "sg:address":"Calle de Suecia, 44",
    "sg:city":"Madrid",
    "sg:orig_category":"Iglesia Cat\u00d3lica",
    "sg:phone":"+34 917 60 08 47",
    "sg:postcode":"28022",
    "sg:province":"Madrid",
    "wof:name":"Parroquia Nuestra Se?ora De Las Rosas",
    "wof:placetype":"venue"
},
  "geometry": {"coordinates":[-3.6038808823,40.4249687195],"type":"Point"}
}