{
  "type": "Feature",
  "properties": {
    "iso:country":"ES",
    "sg:address":"Av Real Monast Sta Maria Poblet, 22",
    "sg:city":"Quart Poblet",
    "sg:orig_category":"Agentes, Concesionarios Y Sucursales De Veh\u00cdculos",
    "sg:phone":"+34 961 53 40 98",
    "sg:postcode":"46930",
    "sg:province":"Valencia",
    "sg:website":"www.grupo-iberica.com",
    "wof:name":"Iberlogistic Spares Company S.l.",
    "wof:placetype":"venue"
},
  "geometry": {"coordinates":[-0.3768048882,39.4702377319],"type":"Point"}
}