{
  "type": "Feature",
  "properties": {
    "iso:country":"ES",
    "sg:address":"Calle de Federico Garcia Lorca, 2",
    "sg:city":"Burgos",
    "sg:orig_category":"Supermercados Y Hipermercados",
    "sg:phone":"+34 947 48 98 70",
    "sg:postcode":"09007",
    "sg:province":"Burgos",
    "wof:name":"Alimentacion Casa Miguel Angel S.l.",
    "wof:placetype":"venue"
},
  "geometry": {"coordinates":[-3.6665349007,42.3498191833],"type":"Point"}
}