{
  "type": "Feature",
  "properties": {
    "iso:country":"ES",
    "sg:address":"Masia Torrents, S/n",
    "sg:city":"Vilanova I La Geltru",
    "sg:orig_category":"Estudios, Instalaci\u00d3n De Climatizaci\u00d3n",
    "sg:phone":"+34 938 93 96 15",
    "sg:postcode":"08800",
    "sg:province":"Barcelona",
    "sg:website":"www.hitecsa.com",
    "wof:name":"Hitecsa Aire Acondicionado S.l.",
    "wof:placetype":"venue"
},
  "geometry": {"coordinates":[1.7397450209,41.2257499695],"type":"Point"}
}