{
  "type": "Feature",
  "properties": {
    "addr:full":"Calle de Mercado, 14 Olvera C\u00e1diz 11690",
    "addr:housenumber":"14",
    "addr:postcode":"11690",
    "addr:street":"Calle De Mercado;Ca\u0301Diz",
    "iso:country":"ES",
    "sg:address":"Calle de Mercado, 14",
    "sg:city":"Olvera",
    "sg:orig_category":"Supermercados Y Hipermercados",
    "sg:phone":"+34 956 12 04 61",
    "sg:postcode":"11690",
    "sg:province":"C\u00e1diz",
    "wof:name":"Mi Super Albeyco S.a.",
    "wof:placetype":"venue"
},
  "geometry": {"coordinates":[-5.2655448914,36.9356040955],"type":"Point"}
}