{
  "type": "Feature",
  "properties": {
    "iso:country":"ES",
    "sg:address":"Calle de Ramon Gallud, 40",
    "sg:city":"Torrevieja",
    "sg:orig_category":"Florister\u00cdas",
    "sg:phone":"+34 965 71 72 54",
    "sg:postcode":"03180",
    "sg:province":"Alicante",
    "wof:name":"Carmona Melgarejo Josefa",
    "wof:placetype":"venue"
},
  "geometry": {"coordinates":[-0.6823539734,37.9771499634],"type":"Point"}
}