{
  "type": "Feature",
  "properties": {
    "iso:country":"ES",
    "sg:address":"Calle de Isabel Colbrand, 10",
    "sg:city":"Madrid",
    "sg:orig_category":"Marketing Telef\u00d3nico",
    "sg:phone":"+34 913 58 93 14",
    "sg:postcode":"28050",
    "sg:province":"Madrid",
    "wof:name":"Sierra & Leth S.l",
    "wof:placetype":"venue"
},
  "geometry": {"coordinates":[-3.6728239059,40.5124511719],"type":"Point"}
}