{
  "type": "Feature",
  "properties": {
    "addr:full":"Calle de Becquer, 3 Guardo Palencia 34880",
    "addr:housenumber":"3",
    "addr:postcode":"34880",
    "addr:street":"Calle De Becquer",
    "iso:country":"ES",
    "sg:address":"Calle de Becquer, 3",
    "sg:city":"Guardo",
    "sg:orig_category":"Venta, Instalaci\u00d3n De Calefacci\u00d3n",
    "sg:phone":"+34 979 85 28 20",
    "sg:postcode":"34880",
    "sg:province":"Palencia",
    "sg:website":"www.paginasamarillas.es",
    "wof:name":"Martinez Lopez Miguel Angel",
    "wof:placetype":"venue"
},
  "geometry": {"coordinates":[-4.8452758789,42.7883834839],"type":"Point"}
}