{
  "type": "Feature",
  "properties": {
    "iso:country":"ES",
    "sg:address":"Outeiro, S/n",
    "sg:city":"Vila Mouros",
    "sg:classifiers":[
        {
            "category":"Taxi",
            "type":"Transportation"
        }
    ],
    "sg:phone":"+34 982 42 40 50",
    "sg:postcode":"27341",
    "sg:province":"Lugo",
    "wof:name":"Armesto Castro Jose Luis",
    "wof:placetype":"venue"
},
  "geometry": {"coordinates":[-7.5558514595,43.0120849609],"type":"Point"}
}