{
  "type": "Feature",
  "properties": {
    "addr:full":"Calle de Camilo Jose Cela, 18 Marbella M\u00e1laga 29600",
    "addr:housenumber":"18",
    "addr:postcode":"29600",
    "addr:street":"Calle De Camilo Jose Cela;Ma\u0301Laga",
    "iso:country":"ES",
    "sg:address":"Calle de Camilo Jose Cela, 18",
    "sg:city":"Marbella",
    "sg:orig_category":"Inmobiliaria (agencias)",
    "sg:phone":"+34 952 82 55 17",
    "sg:postcode":"29600",
    "sg:province":"M\u00e1laga",
    "sg:website":"www.nevadomarbella.com",
    "wof:name":"Nevado Realty S.l.",
    "wof:placetype":"venue"
},
  "geometry": {"coordinates":[-4.896364212,36.5082168579],"type":"Point"}
}