{
  "type": "Feature",
  "properties": {
    "addr:full":"Avda Castros (los), 137 Santander Cantabria 39005",
    "addr:housenumber":"137",
    "addr:postcode":"39005",
    "addr:street":"Avda Castros Los",
    "iso:country":"ES",
    "sg:address":"Avda Castros (los), 137",
    "sg:city":"Santander",
    "sg:orig_category":"Maquinaria Neum\u00c1tica",
    "sg:phone":"+34 942 33 86 42",
    "sg:postcode":"39005",
    "sg:province":"Cantabria",
    "wof:name":"Hidraulica Neumatica Y Valvulas S.l.",
    "wof:placetype":"venue"
},
  "geometry": {"coordinates":[-3.8187839985,43.467628479],"type":"Point"}
}