{
  "type": "Feature",
  "properties": {
    "addr:full":"Calle de Conde De Altea, 41 Altea Alicante 03590",
    "addr:housenumber":"41",
    "addr:postcode":"03590",
    "addr:street":"Calle De Conde De Altea",
    "iso:country":"ES",
    "sg:address":"Calle de Conde De Altea, 41",
    "sg:city":"Altea",
    "sg:orig_category":"Ropa Para Se\u00d1oras (al Por Menor)",
    "sg:phone":"+34 965 84 16 69",
    "sg:postcode":"03590",
    "sg:province":"Alicante",
    "wof:name":"Menendez Bulla Ana Maria",
    "wof:placetype":"venue"
},
  "geometry": {"coordinates":[-0.0459594987,38.6020851135],"type":"Point"}
}