{
  "type": "Feature",
  "properties": {
    "addr:full":"Avda Ramon Y Cajal, 65 Candeleda \u00c1vila 05480",
    "addr:housenumber":"65",
    "addr:postcode":"05480",
    "addr:street":"Avda Ramon Y Cajal",
    "iso:country":"ES",
    "sg:address":"Avda Ramon Y Cajal, 65",
    "sg:city":"Candeleda",
    "sg:orig_category":"Barbacoas Y Accesorios",
    "sg:phone":"+34 920 38 02 14",
    "sg:postcode":"05480",
    "sg:province":"\u00c1vila",
    "wof:name":"Karisan Candeleda S.l.",
    "wof:placetype":"venue"
},
  "geometry": {"coordinates":[-5.2413048744,40.1552314758],"type":"Point"}
}