{
  "type": "Feature",
  "properties": {
    "addr:full":"Plaz Constitucion De (la), S/n Ausejo La Rioja 26513",
    "addr:housenumber":"s",
    "addr:postcode":"26513",
    "addr:street":"/ N Ausejo;Rioja",
    "iso:country":"ES",
    "sg:address":"Plaz Constitucion De (la), S/n",
    "sg:city":"Ausejo",
    "sg:orig_category":"Cajas De Ahorro",
    "sg:phone":"+34 941 43 00 02",
    "sg:postcode":"26513",
    "sg:province":"La Rioja",
    "wof:name":"Caja De Ahorros Y Monte De Piedad De Zaragoza Aragon Y Rioja",
    "wof:placetype":"venue"
},
  "geometry": {"coordinates":[-2.1675701141,42.3410720825],"type":"Point"}
}