{
  "type": "Feature",
  "properties": {
    "iso:country":"ES",
    "sg:address":"Carrer de Sant Ramon De Penyafort, 58",
    "sg:city":"Sabadell",
    "sg:orig_category":"Limpieza Industrial",
    "sg:phone":"+34 937 12 08 25",
    "sg:postcode":"08203",
    "sg:province":"Barcelona",
    "wof:name":"Serco Limpiezas Industriales S.a.",
    "wof:placetype":"venue"
},
  "geometry": {"coordinates":[2.1071228981,41.5351600647],"type":"Point"}
}