{
  "type": "Feature",
  "properties": {
    "addr:full":"Rua Orense (de), 18 Carballi\u00f1o Ourense 32500",
    "addr:housenumber":"18",
    "addr:postcode":"32500",
    "addr:street":"Rua Orense De",
    "iso:country":"ES",
    "sg:address":"Rua Orense (de), 18",
    "sg:city":"Carballi\u00f1o",
    "sg:orig_category":"Distribuci\u00d3n De Petr\u00d3leo Y Derivados",
    "sg:phone":"+34 988 27 06 35",
    "sg:postcode":"32500",
    "sg:province":"Ourense",
    "sg:website":"www.cepsa.es",
    "wof:name":"Piteira Cibeira S.a.",
    "wof:placetype":"venue"
},
  "geometry": {"coordinates":[-8.0665817261,42.4291114807],"type":"Point"}
}