{
  "type": "Feature",
  "properties": {
    "addr:full":"Calle de Puerto Rico, 32 Madrid Madrid 28016",
    "addr:housenumber":"32",
    "addr:postcode":"madrid;28016",
    "addr:street":"Calle De Puerto Rico",
    "iso:country":"ES",
    "sg:address":"Calle de Puerto Rico, 32",
    "sg:city":"Madrid",
    "sg:orig_category":"Arquitectos",
    "sg:phone":"+34 914 15 19 91",
    "sg:postcode":"28016",
    "sg:province":"Madrid",
    "wof:name":"Rodriguez Alvarez Eladio",
    "wof:placetype":"venue"
},
  "geometry": {"coordinates":[-3.6735670567,40.455532074],"type":"Point"}
}