{
  "type": "Feature",
  "properties": {
    "addr:full":"San Cristobal, S/n Mijas Costa M\u00e1laga 29649",
    "addr:postcode":"29649",
    "addr:street":"San Cristobal S / N",
    "iso:country":"ES",
    "sg:address":"San Cristobal, S/n",
    "sg:city":"Mijas Costa",
    "sg:orig_category":"Maquinaria Para Industrias Diversas",
    "sg:phone":"+34 952 47 25 05",
    "sg:postcode":"29649",
    "sg:province":"M\u00e1laga",
    "wof:name":"Almuco S.l.",
    "wof:placetype":"venue"
},
  "geometry": {"coordinates":[-4.6411604881,36.5099143982],"type":"Point"}
}