{
  "type": "Feature",
  "properties": {
    "addr:full":"Ctra. Nava De Santiago, S/n Montijo Badajoz 06480",
    "addr:housenumber":"/ n",
    "addr:postcode":"06480",
    "addr:street":"Ctra. Nava;Santiago S",
    "iso:country":"ES",
    "sg:address":"Ctra. Nava De Santiago, S/n",
    "sg:city":"Montijo",
    "sg:orig_category":"Mataderos De Poller\u00cda",
    "sg:phone":"+34 924 45 34 00",
    "sg:postcode":"06480",
    "sg:province":"Badajoz",
    "wof:name":"Sada P.a. Andalucia S.a.",
    "wof:placetype":"venue"
},
  "geometry": {"coordinates":[-6.5984392166,38.9197158813],"type":"Point"}
}