{
  "type": "Feature",
  "properties": {
    "addr:full":"Calle de General Casta\u00d1os, 52 Portugalete Vizcaya 48920",
    "addr:housenumber":"52",
    "addr:postcode":"48920",
    "addr:street":"Calle De General Castan\u0303Os",
    "iso:country":"ES",
    "sg:address":"Calle de General Casta\u00d1os, 52",
    "sg:city":"Portugalete",
    "sg:orig_category":"Moquetas, Alfombras (al Por Menor)",
    "sg:phone":"+34 944 62 72 31",
    "sg:postcode":"48920",
    "sg:province":"Vizcaya",
    "wof:name":"Pablo Martinez Rodriguez",
    "wof:placetype":"venue"
},
  "geometry": {"coordinates":[-3.0239899158,43.3223724365],"type":"Point"}
}