{
  "type": "Feature",
  "properties": {
    "addr:full":"Calle de Perez Galdos, S/n Fuentes Ebro Zaragoza 50740",
    "addr:housenumber":"s / n",
    "addr:postcode":"50740",
    "addr:street":"Calle De Perez Galdos",
    "iso:country":"ES",
    "sg:address":"Calle de Perez Galdos, S/n",
    "sg:city":"Fuentes Ebro",
    "sg:orig_category":"Electricidad: Instaladores",
    "sg:phone":"+34 976 16 06 23",
    "sg:postcode":"50740",
    "sg:province":"Zaragoza",
    "wof:name":"Montalban Miranda Adolfo Jesus",
    "wof:placetype":"venue"
},
  "geometry": {"coordinates":[-0.6276900172,41.5127487183],"type":"Point"}
}