{
  "type": "Feature",
  "properties": {
    "addr:full":"Gaintxurizketa Bidea, S/n Lezo Guip\u00f9zcoa 20100",
    "addr:housenumber":"s / n",
    "addr:postcode":"20100",
    "addr:street":"Gaintxurizketa Bidea;Guipu\u0300Zcoa",
    "iso:country":"ES",
    "sg:address":"Gaintxurizketa Bidea, S/n",
    "sg:city":"Lezo",
    "sg:orig_category":"Pintura, Barniz, Productos Asimilables (fabricaci\u00d3n, Al Por Mayor)",
    "sg:phone":"+34 943 52 47 00",
    "sg:postcode":"20100",
    "sg:province":"Guip\u00f9zcoa",
    "sg:website":"www.iztieta.com",
    "wof:name":"Almacenes Iztieta S. A.",
    "wof:placetype":"venue"
},
  "geometry": {"coordinates":[-1.8911390305,43.3213005066],"type":"Point"}
}