{
  "type": "Feature",
  "properties": {
    "iso:country":"ES",
    "sg:address":"Avda Antonio Mairena, 18",
    "sg:city":"Alcala Guadaira",
    "sg:orig_category":"Producci\u00d3n, Distribuci\u00d3n De Gas Butano Y Propano",
    "sg:phone":"+34 955 68 37 52",
    "sg:postcode":"41500",
    "sg:province":"Sevilla",
    "wof:name":"Butano Distribuidor Comercial S.a.",
    "wof:placetype":"venue"
},
  "geometry": {"coordinates":[-5.8403759003,37.3378562927],"type":"Point"}
}