{
  "type": "Feature",
  "properties": {
    "addr:full":"Calle de Francisco Ferrer, 1 Zaragoza Zaragoza 50015",
    "addr:housenumber":"1",
    "addr:postcode":"50015",
    "addr:street":"Calle De Francisco Ferrer",
    "iso:country":"ES",
    "sg:address":"Calle de Francisco Ferrer, 1",
    "sg:city":"Zaragoza",
    "sg:orig_category":"Mec\u00c1nico Del Autom\u00d3vil",
    "sg:phone":"+34 976 52 46 34",
    "sg:postcode":"50015",
    "sg:province":"Zaragoza",
    "wof:name":"Trapero Gonzalez Jose Alipio",
    "wof:placetype":"venue"
},
  "geometry": {"coordinates":[-0.8930715919,41.6788444519],"type":"Point"}
}