{
  "type": "Feature",
  "properties": {
    "iso:country":"ES",
    "sg:address":"Calle de Cristobal Colon, 32",
    "sg:city":"Algeciras",
    "sg:orig_category":"Loter\u00cda Y T\u00d3mbola",
    "sg:phone":"+34 956 66 63 03",
    "sg:postcode":"11201",
    "sg:province":"C\u00e1diz",
    "wof:name":"Fernandez Del Villar De La Fuente Gloria",
    "wof:placetype":"venue"
},
  "geometry": {"coordinates":[-5.4467759132,36.1290206909],"type":"Point"}
}