{
  "type": "Feature",
  "properties": {
    "addr:full":"Carrer de Calaf, 12 Barcelona Barcelona 08021",
    "addr:housenumber":"12",
    "addr:postcode":"08021",
    "addr:street":"Carrer De Calaf",
    "iso:country":"ES",
    "sg:address":"Carrer de Calaf, 12",
    "sg:city":"Barcelona",
    "sg:orig_category":"Ropa Para Ni\u00d1os (al Por Menor)",
    "sg:phone":"+34 932 09 21 19",
    "sg:postcode":"08021",
    "sg:province":"Barcelona",
    "wof:name":"Alcaser Company Regina",
    "wof:placetype":"venue"
},
  "geometry": {"coordinates":[2.1444907188,41.3977127075],"type":"Point"}
}