{
  "type": "Feature",
  "properties": {
    "addr:full":"Plaz Gaiteira, S/n Coru\u00d1a La Coru\u00f1a 15006",
    "addr:housenumber":"s / n",
    "addr:postcode":"15006",
    "addr:street":"Plaz Gaiteira;La Corun\u0303A",
    "iso:country":"ES",
    "sg:address":"Plaz Gaiteira, S/n",
    "sg:city":"Coru\u00d1a",
    "sg:orig_category":"Arquitectos",
    "sg:phone":"+34 981 13 74 54",
    "sg:postcode":"15006",
    "sg:province":"La Coru\u00f1a",
    "wof:name":"Besiga Diaz Blanco Julio",
    "wof:placetype":"venue"
},
  "geometry": {"coordinates":[-8.3975877762,43.3542709351],"type":"Point"}
}