{
  "type": "Feature",
  "properties": {
    "iso:country":"ES",
    "sg:address":"Carrer de Llibertat, 4",
    "sg:city":"Castelldefels",
    "sg:orig_category":"Bisuter\u00cda, Joyer\u00cda, Relojer\u00cda (al Por Menor)",
    "sg:phone":"+34 936 65 40 96",
    "sg:postcode":"08860",
    "sg:province":"Barcelona",
    "wof:name":"J.j.joyeros Catalu\u00f1a S.c.p.",
    "wof:placetype":"venue"
},
  "geometry": {"coordinates":[1.976976037,41.2791366577],"type":"Point"}
}