{
  "type": "Feature",
  "properties": {
    "addr:full":"Calle de Palma, 18 Madrid Madrid 28004",
    "addr:housenumber":"18",
    "addr:postcode":"madrid;28004",
    "addr:street":"Calle De Palma",
    "iso:country":"ES",
    "sg:address":"Calle de Palma, 18",
    "sg:city":"Madrid",
    "sg:orig_category":"Fabricaci\u00d3n, Venta, Instalaci\u00d3n De R\u00d3tulos, De R\u00d3tulos Luminosos",
    "sg:phone":"+34 913 60 44 96",
    "sg:postcode":"28004",
    "sg:province":"Madrid",
    "wof:name":"Kromatek Soluciones Graficas,sl",
    "wof:placetype":"venue"
},
  "geometry": {"coordinates":[-3.7029759884,40.4263687134],"type":"Point"}
}