{
  "type": "Feature",
  "properties": {
    "addr:full":"Avda Monforte De Lemos, 63 Madrid Madrid 28029",
    "addr:housenumber":"63",
    "addr:postcode":"madrid;28029",
    "addr:street":"Avda Monforte De Lemos",
    "iso:country":"ES",
    "sg:address":"Avda Monforte De Lemos, 63",
    "sg:city":"Madrid",
    "sg:orig_category":"Empresarios",
    "sg:phone":"+34 913 14 33 23",
    "sg:postcode":"28029",
    "sg:province":"Madrid",
    "wof:name":"Nogueira Carballedo Manuel",
    "wof:placetype":"venue"
},
  "geometry": {"coordinates":[-3.6990699768,40.4797134399],"type":"Point"}
}