{
  "type": "Feature",
  "properties": {
    "addr:full":"Avda Pasqualeta, S/n Paiporta Valencia 46200",
    "addr:housenumber":"s / n",
    "addr:postcode":"46200",
    "addr:street":"Avda Pasqualeta",
    "iso:country":"ES",
    "sg:address":"Avda Pasqualeta, S/n",
    "sg:city":"Paiporta",
    "sg:orig_category":"Art\u00cdculos De Madera (fabricaci\u00d3n Y Al Por Mayor)",
    "sg:phone":"+34 963 97 28 16",
    "sg:postcode":"46200",
    "sg:province":"Valencia",
    "sg:website":"www.danieldelafuene.com",
    "wof:name":"Muebles Daniel De La Fuente S. L.",
    "wof:placetype":"venue"
},
  "geometry": {"coordinates":[-0.4061940014,39.4328346252],"type":"Point"}
}