{
  "type": "Feature",
  "properties": {
    "iso:country":"ES",
    "sg:address":"Calle de Rio Alberche, S/n",
    "sg:city":"Poligono Sta M. De Benquerencia",
    "sg:orig_category":"Comercio, Reparaci\u00d3n De Bicicletas, De Motocicletas, De Accesorios",
    "sg:phone":"+34 925 24 14 58",
    "sg:postcode":"45007",
    "sg:province":"Toledo",
    "wof:name":"Motos Polma S.l.",
    "wof:placetype":"venue"
},
  "geometry": {"coordinates":[-3.9484488964,39.8663139343],"type":"Point"}
}