{
  "type": "Feature",
  "properties": {
    "iso:country":"ES",
    "sg:address":"Calle de Santa Eugenia, 9",
    "sg:city":"Arenas -areeta",
    "sg:orig_category":"Venta, Instalaci\u00d3n De Cocinas",
    "sg:phone":"+34 944 63 00 73",
    "sg:postcode":"48930",
    "sg:province":"Vizcaya",
    "wof:name":"Juan Cardoso Sierray Otra C.b.",
    "wof:placetype":"venue"
},
  "geometry": {"coordinates":[-3.0093200207,43.3268661499],"type":"Point"}
}