{
  "type": "Feature",
  "properties": {
    "iso:country":"ES",
    "sg:address":"Calle de Guetaria, 72",
    "sg:city":"Madrid",
    "sg:orig_category":"Molduras, Junquillos, Listones Y Molduras Perforadas",
    "sg:phone":"+34 913 41 81 34",
    "sg:postcode":"28041",
    "sg:province":"Madrid",
    "wof:name":"Sanchez Tinoco Pedro",
    "wof:placetype":"venue"
},
  "geometry": {"coordinates":[-3.7156419754,40.370464325],"type":"Point"}
}