{
  "type": "Feature",
  "properties": {
    "addr:full":"Carrer de Alts Forns, 72 Barcelona Barcelona 08038",
    "addr:housenumber":"72",
    "addr:postcode":"08038",
    "addr:street":"Carrer De Alts Forns",
    "iso:country":"ES",
    "sg:address":"Carrer de Alts Forns, 72",
    "sg:city":"Barcelona",
    "sg:orig_category":"Quincaller\u00cda (al Por Menor)",
    "sg:phone":"+34 933 32 44 16",
    "sg:postcode":"08038",
    "sg:province":"Barcelona",
    "wof:name":"Puchades Monzo Concepcion",
    "wof:placetype":"venue"
},
  "geometry": {"coordinates":[2.1415688992,41.3590583801],"type":"Point"}
}