{
  "type": "Feature",
  "properties": {
    "iso:country":"ES",
    "sg:address":"La Concha-i, 17",
    "sg:city":"Marbella",
    "sg:orig_category":"Plomeros",
    "sg:phone":"+34 952 77 89 07",
    "sg:postcode":"29600",
    "sg:province":"M\u00e1laga",
    "wof:name":"Troyano Andrade Jose Maria",
    "wof:placetype":"venue"
},
  "geometry": {"coordinates":[-4.8833007812,36.5079956055],"type":"Point"}
}