{
  "type": "Feature",
  "properties": {
    "addr:full":"Aiguadors, 8 Gandia Valencia 46700",
    "addr:housenumber":"8",
    "addr:postcode":"46700",
    "addr:street":"Aiguadors;Valencia",
    "iso:country":"ES",
    "sg:address":"Aiguadors, 8",
    "sg:city":"Gandia",
    "sg:orig_category":"Persianas Interiores, Exteriores",
    "sg:phone":"+34 962 86 44 06",
    "sg:postcode":"46700",
    "sg:province":"Valencia",
    "wof:name":"Toldos Cato S.l.",
    "wof:placetype":"venue"
},
  "geometry": {"coordinates":[-0.1835760027,38.9819526672],"type":"Point"}
}