{
  "type": "Feature",
  "properties": {
    "addr:full":"Avda Reyes Catolicos, 42 Alhaurin Torre M\u00e1laga 29130",
    "addr:housenumber":"42",
    "addr:postcode":"29130",
    "addr:street":"Avda Reyes Catolicos",
    "iso:country":"ES",
    "sg:address":"Avda Reyes Catolicos, 42",
    "sg:city":"Alhaurin Torre",
    "sg:orig_category":"Reposter\u00cdas",
    "sg:phone":"+34 952 41 08 60",
    "sg:postcode":"29130",
    "sg:province":"M\u00e1laga",
    "wof:name":"Garcia Gonzalez Nicolas",
    "wof:placetype":"venue"
},
  "geometry": {"coordinates":[-4.5672998428,36.6599388123],"type":"Point"}
}