{
  "type": "Feature",
  "properties": {
    "iso:country":"ES",
    "sg:address":"Calle de Mauricio Legendre, 41",
    "sg:city":"Madrid",
    "sg:orig_category":"Quincaller\u00cda (al Por Menor)",
    "sg:phone":"+34 913 15 68 00",
    "sg:postcode":"28046",
    "sg:province":"Madrid",
    "wof:name":"Hernan De Frutos Andres",
    "wof:placetype":"venue"
},
  "geometry": {"coordinates":[-3.6847920418,40.4740066528],"type":"Point"}
}