{
  "type": "Feature",
  "properties": {
    "addr:full":"Calle de Palafox, 8 Biota Zaragoza 50695",
    "addr:housenumber":"8",
    "addr:postcode":"50695",
    "addr:street":"Calle De Palafox",
    "iso:country":"ES",
    "sg:address":"Calle de Palafox, 8",
    "sg:city":"Biota",
    "sg:orig_category":"Producci\u00d3n, Venta De Productos De Agricultura Biol\u00d3gica",
    "sg:phone":"+34 976 67 00 03",
    "sg:postcode":"50695",
    "sg:province":"Zaragoza",
    "wof:name":"Martinez Abad Jose Antonio",
    "wof:placetype":"venue"
},
  "geometry": {"coordinates":[-1.1857130527,42.2621536255],"type":"Point"}
}