{
  "type": "Feature",
  "properties": {
    "iso:country":"ES",
    "sg:address":"Calle de Ramon Y Cajal, 8",
    "sg:city":"Mocejon",
    "sg:orig_category":"Molduras, Junquillos, Listones Y Molduras Perforadas",
    "sg:phone":"+34 925 36 03 17",
    "sg:postcode":"45270",
    "sg:province":"Toledo",
    "wof:name":"Aranda Castilla Roberto",
    "wof:placetype":"venue"
},
  "geometry": {"coordinates":[-3.9175717831,39.9386940002],"type":"Point"}
}