{
  "type": "Feature",
  "properties": {
    "addr:full":"Calle de Juan Padilla, S/n Santa Marta De Tormes Salamanca 37900",
    "addr:housenumber":"s / n",
    "addr:postcode":"37900",
    "addr:street":"Calle De Juan Padilla",
    "iso:country":"ES",
    "sg:address":"Calle de Juan Padilla, S/n",
    "sg:city":"Santa Marta De Tormes",
    "sg:orig_category":"Asociaciones Y Clubs Deportivos",
    "sg:phone":"+34 923 13 13 42",
    "sg:postcode":"37900",
    "sg:province":"Salamanca",
    "wof:name":"Luengo Fontanillo Aurora",
    "wof:placetype":"venue"
},
  "geometry": {"coordinates":[-5.62586689,40.9490509033],"type":"Point"}
}