{
  "type": "Feature",
  "properties": {
    "addr:full":"Calle de Jose Monge Gomez, 7 Pastrana C\u00e1diz 11540",
    "addr:housenumber":"7",
    "addr:postcode":"11540",
    "addr:street":"Calle De Jose Monge Gomez",
    "iso:country":"ES",
    "sg:address":"Calle de Jose Monge Gomez, 7",
    "sg:city":"Pastrana",
    "sg:orig_category":"Cerrajer\u00cda, Ferrallista",
    "sg:phone":"+34 956 36 98 60",
    "sg:postcode":"11540",
    "sg:province":"C\u00e1diz",
    "wof:name":"Garcia Ortega Diego",
    "wof:placetype":"venue"
},
  "geometry": {"coordinates":[-6.3575987816,36.777721405],"type":"Point"}
}