{
  "type": "Feature",
  "properties": {
    "addr:full":"Poli Industrial C/b, 26 Rozas De Madrid Madrid 28230",
    "addr:housenumber":"b 26",
    "addr:postcode":"28230",
    "iso:country":"ES",
    "sg:address":"Poli Industrial C/b, 26",
    "sg:city":"Rozas De Madrid",
    "sg:orig_category":"Muebles",
    "sg:phone":"+34 916 37 28 81",
    "sg:postcode":"28230",
    "sg:province":"Madrid",
    "sg:website":"www.multisilla.com",
    "wof:name":"Multisilla S. L.",
    "wof:placetype":"venue"
},
  "geometry": {"coordinates":[-3.8913800716,40.5247497559],"type":"Point"}
}