{
  "type": "Feature",
  "properties": {
    "iso:country":"ES",
    "sg:address":"Avda Galicia De, 23",
    "sg:city":"Luarca",
    "sg:orig_category":"Sociedades, Compa\u00d1\u00cdas Aseguradoras",
    "sg:phone":"+34 985 47 01 43",
    "sg:postcode":"33700",
    "sg:province":"Asturias",
    "wof:name":"Segurastur S.l.",
    "wof:placetype":"venue"
},
  "geometry": {"coordinates":[-6.5396680832,43.5403404236],"type":"Point"}
}