{
  "type": "Feature",
  "properties": {
    "addr:full":"Carr Cavallers, S/n Algaida Islas Baleares 07210",
    "addr:housenumber":"s / n",
    "addr:postcode":"07210",
    "addr:street":"Carr Cavallers",
    "iso:country":"ES",
    "sg:address":"Carr Cavallers, S/n",
    "sg:city":"Algaida",
    "sg:orig_category":"Cooperativas Agr\u00cdcolas",
    "sg:phone":"+34 971 66 55 38",
    "sg:postcode":"07210",
    "sg:province":"Islas Baleares",
    "wof:name":"Sociedad Cooperativa Limitada Agraria",
    "wof:placetype":"venue"
},
  "geometry": {"coordinates":[2.8965749741,39.5586433411],"type":"Point"}
}