{
  "type": "Feature",
  "properties": {
    "iso:country":"ES",
    "sg:address":"Calle de Pico De Aneto (del), 4",
    "sg:city":"San Sebastian De Los Reyes",
    "sg:orig_category":"Cl\u00cdnicas Dentales",
    "sg:phone":"+34 916 54 50 51",
    "sg:postcode":"28700",
    "sg:province":"Madrid",
    "wof:name":"Sansedent S.l.",
    "wof:placetype":"venue"
},
  "geometry": {"coordinates":[-3.6368820667,40.550403595],"type":"Point"}
}