{
  "type": "Feature",
  "properties": {
    "addr:full":"Calle de Santa Lucia, 3 Madrid Madrid 28004",
    "addr:housenumber":"3",
    "addr:postcode":"28004",
    "addr:street":"Calle De Santa Lucia",
    "iso:country":"ES",
    "sg:address":"Calle de Santa Lucia, 3",
    "sg:city":"Madrid",
    "sg:orig_category":"El Hogar: Amueblado, Acondicionamiento, Decoraci\u00d3n Y Mantenimiento",
    "sg:phone":"+34 915 21 19 26",
    "sg:postcode":"28004",
    "sg:province":"Madrid",
    "wof:name":"Estuco Decoracion En Color Rehabilitacion Y Dise\u00f1o S.l.",
    "wof:placetype":"venue"
},
  "geometry": {"coordinates":[-3.7054140568,40.4253082275],"type":"Point"}
}