{
  "type": "Feature",
  "properties": {
    "iso:country":"ES",
    "sg:address":"Calle de Moraleja, 8",
    "sg:city":"Jarandilla Vera",
    "sg:classifiers":[
        {
            "category":"Taxi",
            "type":"Transportation"
        }
    ],
    "sg:phone":"+34 927 56 04 97",
    "sg:postcode":"10450",
    "sg:province":"C\u00e1ceres",
    "wof:name":"Mu\u00f1oz Martin Antonio",
    "wof:placetype":"venue"
},
  "geometry": {"coordinates":[-5.6612057686,40.1243476868],"type":"Point"}
}