{
  "type": "Feature",
  "properties": {
    "iso:country":"ES",
    "sg:address":"Calle de Cantarranas, 33",
    "sg:city":"Huelma",
    "sg:orig_category":"Semiller\u00cdas",
    "sg:phone":"+34 953 39 01 02",
    "sg:postcode":"23560",
    "sg:province":"Ja\u00e9n",
    "wof:name":"Mu\u00f1oz Cabrera Enrique",
    "wof:placetype":"venue"
},
  "geometry": {"coordinates":[-3.4584925175,37.6464767456],"type":"Point"}
}