{
  "type": "Feature",
  "properties": {
    "addr:full":"Ctra Santa Oliva, 16 Vendrell Tarragona 43700",
    "addr:housenumber":"16",
    "addr:postcode":"43700",
    "addr:street":"Ctra Santa Oliva",
    "iso:country":"ES",
    "sg:address":"Ctra Santa Oliva, 16",
    "sg:city":"Vendrell",
    "sg:orig_category":"Mec\u00c1nico Del Autom\u00d3vil",
    "sg:phone":"+34 977 66 70 51",
    "sg:postcode":"43700",
    "sg:province":"Tarragona",
    "wof:name":"Marti Bargallo Salvador",
    "wof:placetype":"venue"
},
  "geometry": {"coordinates":[1.537340045,41.2243881226],"type":"Point"}
}