{
  "type": "Feature",
  "properties": {
    "addr:full":"Calle de Santa Maria, 15 Jerez De La Frontera C\u00e1diz 11402",
    "addr:housenumber":"15",
    "addr:postcode":"11402",
    "addr:street":"Calle De Santa Maria",
    "iso:country":"ES",
    "sg:address":"Calle de Santa Maria, 15",
    "sg:city":"Jerez De La Frontera",
    "sg:orig_category":"Bisuter\u00cda, Joyer\u00cda, Relojer\u00cda (al Por Menor)",
    "sg:phone":"+34 956 33 22 86",
    "sg:postcode":"11402",
    "sg:province":"C\u00e1diz",
    "wof:name":"Salazar Martell Diego",
    "wof:placetype":"venue"
},
  "geometry": {"coordinates":[-6.1359081268,36.6834259033],"type":"Point"}
}