{
  "type": "Feature",
  "properties": {
    "iso:country":"ES",
    "sg:address":"Calle de Braulio Navas, 23",
    "sg:city":"Hervas",
    "sg:orig_category":"Farmacias",
    "sg:phone":"+34 927 48 10 27",
    "sg:postcode":"10700",
    "sg:province":"C\u00e1ceres",
    "wof:name":"Garcia Pe\u00f1a Isabel",
    "wof:placetype":"venue"
},
  "geometry": {"coordinates":[-5.8601284027,40.2728271484],"type":"Point"}
}