{
  "type": "Feature",
  "properties": {
    "addr:full":"Calle de San Juan, 38 Logro\u00f1o La Rioja 26001",
    "addr:housenumber":"38",
    "addr:postcode":"26001",
    "addr:street":"Calle De San Juan;Rioja",
    "iso:country":"ES",
    "sg:address":"Calle de San Juan, 38",
    "sg:city":"Logro\u00f1o",
    "sg:orig_category":"Artes Gr\u00c1ficas, Artes Pl\u00c1sticas (curso)",
    "sg:phone":"+34 941 26 37 30",
    "sg:postcode":"26001",
    "sg:province":"La Rioja",
    "sg:website":"www.pilaralonso.com",
    "wof:name":"Pilar Alonso Y Otros S.l.",
    "wof:placetype":"venue"
},
  "geometry": {"coordinates":[-2.4441640377,42.465637207],"type":"Point"}
}