{
  "type": "Feature",
  "properties": {
    "iso:country":"ES",
    "sg:address":"Calle de Antonio Mairena, 8",
    "sg:city":"Madrid",
    "sg:orig_category":"Alquiler De V\u00cddeo",
    "sg:phone":"+34 917 78 38 41",
    "sg:postcode":"28038",
    "sg:province":"Madrid",
    "wof:name":"Martinez De Castro Pilar",
    "wof:placetype":"venue"
},
  "geometry": {"coordinates":[-3.6412045956,40.39112854],"type":"Point"}
}