{
  "type": "Feature",
  "properties": {
    "addr:full":"Calle de Cresta Del Gallo, 4 Santo Angel Murcia 30151",
    "addr:housenumber":"4",
    "addr:postcode":"30151",
    "addr:street":"Calle De Cresta Del Gallo",
    "iso:country":"ES",
    "sg:address":"Calle de Cresta Del Gallo, 4",
    "sg:city":"Santo Angel",
    "sg:orig_category":"Alquiler De Gr\u00daas",
    "sg:phone":"+34 968 84 30 03",
    "sg:postcode":"30151",
    "sg:province":"Murcia",
    "wof:name":"Montajes Miralles S.l.",
    "wof:placetype":"venue"
},
  "geometry": {"coordinates":[-1.1272416115,37.9437026978],"type":"Point"}
}