{
  "type": "Feature",
  "properties": {
    "iso:country":"ES",
    "sg:address":"Plaz Cruz De Humilladero, S/n",
    "sg:city":"Malaga",
    "sg:orig_category":"Distribuci\u00d3n De Petr\u00d3leo Y Derivados",
    "sg:phone":"+34 952 31 48 47",
    "sg:postcode":"29006",
    "sg:province":"M\u00e1laga",
    "wof:name":"Anher S. L.",
    "wof:placetype":"venue"
},
  "geometry": {"coordinates":[-4.4980049133,36.7106819153],"type":"Point"}
}