{
  "type": "Feature",
  "properties": {
    "iso:country":"ES",
    "sg:address":"Calle de Puentezuelas, 3",
    "sg:city":"Granada",
    "sg:orig_category":"Asesor\u00cda Sobre Comunicaci\u00d3n De Empresas",
    "sg:phone":"+34 958 25 88 79",
    "sg:postcode":"18002",
    "sg:province":"Granada",
    "wof:name":"Bellver Candela S.a.",
    "wof:placetype":"venue"
},
  "geometry": {"coordinates":[-3.6008450985,37.1730041504],"type":"Point"}
}