{
  "type": "Feature",
  "properties": {
    "addr:full":"Trva Sousas (de), 35 Verin Ourense 32600",
    "addr:housenumber":"35",
    "addr:postcode":"32600",
    "addr:street":"Trva Sousas De",
    "iso:country":"ES",
    "sg:address":"Trva Sousas (de), 35",
    "sg:city":"Verin",
    "sg:orig_category":"Panader\u00cdas, Panader\u00cdas",
    "sg:phone":"+34 988 41 41 45",
    "sg:postcode":"32600",
    "sg:province":"Ourense",
    "wof:name":"Panaderia Alvaro S.l.",
    "wof:placetype":"venue"
},
  "geometry": {"coordinates":[-7.4346041679,41.9415092468],"type":"Point"}
}