{
  "type": "Feature",
  "properties": {
    "addr:full":"Calle de Zarco Del Valle, 21 Bailen Ja\u00e9n 23710",
    "addr:housenumber":"21",
    "addr:postcode":"23710",
    "addr:street":"Calle De Zarco Del Valle;Jae\u0301N",
    "iso:country":"ES",
    "sg:address":"Calle de Zarco Del Valle, 21",
    "sg:city":"Bailen",
    "sg:orig_category":"Hielo Artificial (fabricaci\u00d3n, Distribuci\u00d3n)",
    "sg:phone":"+34 953 67 09 06",
    "sg:postcode":"23710",
    "sg:province":"Ja\u00e9n",
    "wof:name":"Caballero Garcia Dolores",
    "wof:placetype":"venue"
},
  "geometry": {"coordinates":[-3.7777030468,38.0954589844],"type":"Point"}
}