{
  "type": "Feature",
  "properties": {
    "addr:full":"Calle de Ceuta (de), 12 Alcobendas Madrid 28100",
    "addr:housenumber":"12",
    "addr:postcode":"28100",
    "addr:street":"Calle De Ceuta De",
    "iso:country":"ES",
    "sg:address":"Calle de Ceuta (de), 12",
    "sg:city":"Alcobendas",
    "sg:orig_category":"Guarder\u00cdas",
    "sg:phone":"+34 916 61 35 90",
    "sg:postcode":"28100",
    "sg:province":"Madrid",
    "wof:name":"Rivas Chamorro Josefa",
    "wof:placetype":"venue"
},
  "geometry": {"coordinates":[-3.6370296478,40.5395469666],"type":"Point"}
}