{
  "type": "Feature",
  "properties": {
    "iso:country":"ES",
    "sg:address":"Calle de Santa Lucrecia, 8",
    "sg:city":"Madrid",
    "sg:orig_category":"El Hogar: Amueblado, Acondicionamiento, Decoraci\u00d3n Y Mantenimiento",
    "sg:phone":"+34 915 69 28 44",
    "sg:postcode":"28019",
    "sg:province":"Madrid",
    "wof:name":"Pinturas Tormes Galan S.l.",
    "wof:placetype":"venue"
},
  "geometry": {"coordinates":[-3.7186799049,40.3868026733],"type":"Point"}
}