{
  "type": "Feature",
  "properties": {
    "addr:full":"Calle de San Bernardo (de), 14 Alcobendas Madrid 28108",
    "addr:postcode":"28108",
    "addr:street":"Calle De San;De;Alcobendas",
    "iso:country":"ES",
    "sg:address":"Calle de San Bernardo (de), 14",
    "sg:city":"Alcobendas",
    "sg:orig_category":"Chapister\u00cda",
    "sg:phone":"+34 916 61 14 05",
    "sg:postcode":"28108",
    "sg:province":"Madrid",
    "wof:name":"Talleres Miguel Fornell S.l.",
    "wof:placetype":"venue"
},
  "geometry": {"coordinates":[-3.6460626125,40.5359535217],"type":"Point"}
}