{
  "type": "Feature",
  "properties": {
    "iso:country":"ES",
    "sg:address":"Carrer de Gorria (d'en), 3",
    "sg:city":"S. Carles Rapita",
    "sg:orig_category":"Zapatos (al Por Menor)",
    "sg:phone":"+34 977 74 21 02",
    "sg:postcode":"43540",
    "sg:province":"Tarragona",
    "wof:name":"Roca Pons Benjamin",
    "wof:placetype":"venue"
},
  "geometry": {"coordinates":[0.592204988,40.6186599731],"type":"Point"}
}