{
  "type": "Feature",
  "properties": {
    "iso:country":"ES",
    "sg:address":"Avda Lope De Vega, S/n",
    "sg:city":"Logro\u00f1o",
    "sg:orig_category":"Promotores Constructores",
    "sg:phone":"+34 941 74 01 54",
    "sg:postcode":"26006",
    "sg:province":"La Rioja",
    "wof:name":"Riojano Europea De Construccion S.l.",
    "wof:placetype":"venue"
},
  "geometry": {"coordinates":[-2.4469640255,42.4532089233],"type":"Point"}
}