{
  "type": "Feature",
  "properties": {
    "addr:full":"Carrer de Antoni Maura, 6 Terrassa Barcelona 08225",
    "addr:housenumber":"6",
    "addr:postcode":"08225",
    "addr:street":"Carrer De Antoni Maura",
    "iso:country":"ES",
    "sg:address":"Carrer de Antoni Maura, 6",
    "sg:city":"Terrassa",
    "sg:orig_category":"Agencias Y Agentes Comerciales, Representantes",
    "sg:phone":"+34 937 88 49 20",
    "sg:postcode":"08225",
    "sg:province":"Barcelona",
    "wof:name":"Cortes Barea Rafael",
    "wof:placetype":"venue"
},
  "geometry": {"coordinates":[2.0024330616,41.5720710754],"type":"Point"}
}