{
  "type": "Feature",
  "properties": {
    "addr:full":"Ptge Xerrico, 19 Hospitalet Llobregat Barcelona 08901",
    "addr:housenumber":"19",
    "addr:postcode":"08901",
    "addr:street":"Ptge Xerrico",
    "iso:country":"ES",
    "sg:address":"Ptge Xerrico, 19",
    "sg:city":"Hospitalet Llobregat",
    "sg:orig_category":"Grafistas",
    "sg:phone":"+34 933 37 10 10",
    "sg:postcode":"08901",
    "sg:province":"Barcelona",
    "wof:name":"Gonzalez Ariza Francisco Jose",
    "wof:placetype":"venue"
},
  "geometry": {"coordinates":[2.1006290913,41.359954834],"type":"Point"}
}