{
  "type": "Feature",
  "properties": {
    "iso:country":"ES",
    "sg:address":"Carrer de Lleida, 48",
    "sg:city":"Prat Llobregat",
    "sg:orig_category":"Caf\u00c9s, Bares, Cervecer\u00cdas",
    "sg:phone":"+34 934 78 00 29",
    "sg:postcode":"08820",
    "sg:province":"Barcelona",
    "wof:name":"Cerezo Zamorano Roberto",
    "wof:placetype":"venue"
},
  "geometry": {"coordinates":[2.0925500393,41.3212585449],"type":"Point"}
}