{
  "type": "Feature",
  "properties": {
    "iso:country":"ES",
    "sg:address":"Avda Almendros (de Los), S/n",
    "sg:city":"Cabanillas Campo",
    "sg:orig_category":"Agencias De Viajes",
    "sg:phone":"+34 949 33 75 39",
    "sg:postcode":"19171",
    "sg:province":"Guadalajara",
    "wof:name":"Vaquero Martinez Pilar",
    "wof:placetype":"venue"
},
  "geometry": {"coordinates":[-3.2335939407,40.6413955688],"type":"Point"}
}