{
  "type": "Feature",
  "properties": {
    "addr:full":"Barr Musel, S/n Gijon Asturias 33290",
    "addr:housenumber":"s",
    "addr:postcode":"33290",
    "addr:street":"Musel;/ N",
    "iso:country":"ES",
    "sg:address":"Barr Musel, S/n",
    "sg:city":"Gijon",
    "sg:classifiers":[
        {
            "category":"Manufacturing",
            "subcategory":"Building Materials",
            "type":"Manufacturing & Wholesale Goods"
        }
    ],
    "sg:phone":"+34 985 31 00 19",
    "sg:postcode":"33290",
    "sg:province":"Asturias",
    "sg:tags":[
        "cemento",
        "y",
        "de",
        "fabricaci\u00d3n",
        "cal"
    ],
    "wof:name":"Intermonte Asturias S.a.",
    "wof:placetype":"venue"
},
  "geometry": {"coordinates":[-5.7190551758,43.5478096008],"type":"Point"}
}