{
  "type": "Feature",
  "properties": {
    "addr:full":"Av Argentina, 69 Palma Islas Baleares 07011",
    "addr:housenumber":"69",
    "addr:postcode":"07011",
    "addr:street":"Av Argentina",
    "iso:country":"ES",
    "sg:address":"Av Argentina, 69",
    "sg:city":"Palma",
    "sg:orig_category":"Ropa De Hogar (al Por Menor)",
    "sg:phone":"+34 971 28 00 89",
    "sg:postcode":"07011",
    "sg:province":"Islas Baleares",
    "wof:name":"Hogar Mj S.l",
    "wof:placetype":"venue"
},
  "geometry": {"coordinates":[2.6406109333,39.5748176575],"type":"Point"}
}