{
  "type": "Feature",
  "properties": {
    "iso:country":"ES",
    "sg:address":"Calle de Ganeta, 3",
    "sg:city":"Getxo",
    "sg:orig_category":"Bricolaje, Herramientas (al Por Menor)",
    "sg:phone":"+34 944 64 56 54",
    "sg:postcode":"48930",
    "sg:province":"Vizcaya",
    "wof:name":"Maria Mercedes Valverde Pe\u00f1a",
    "wof:placetype":"venue"
},
  "geometry": {"coordinates":[-3.0086240768,43.3289070129],"type":"Point"}
}