{
  "type": "Feature",
  "properties": {
    "iso:country":"ES",
    "sg:address":"Calle de Juan De La Cierva, 9",
    "sg:city":"Leganes",
    "sg:orig_category":"Mec\u00c1nico Del Autom\u00d3vil",
    "sg:phone":"+34 916 80 74 39",
    "sg:postcode":"28914",
    "sg:province":"Madrid",
    "wof:name":"Servicios Perez S.l.",
    "wof:placetype":"venue"
},
  "geometry": {"coordinates":[-3.7394690514,40.3265113831],"type":"Point"}
}