{
  "type": "Feature",
  "properties": {
    "addr:full":"Calle de Francisco Iglesias, 40 Madrid Madrid 28038",
    "addr:housenumber":"40",
    "addr:postcode":"madrid;28038",
    "addr:street":"Calle De Francisco Iglesias",
    "iso:country":"ES",
    "sg:address":"Calle de Francisco Iglesias, 40",
    "sg:city":"Madrid",
    "sg:orig_category":"Arreglo, Reparaci\u00d3n, Piezas Sueltas De Televisi\u00d3n, V\u00cddeo, Hi",
    "sg:phone":"+34 914 30 65 76",
    "sg:postcode":"28038",
    "sg:province":"Madrid",
    "wof:name":"Sampedro Ayaso Manuel",
    "wof:placetype":"venue"
},
  "geometry": {"coordinates":[-3.6639969349,40.3984336853],"type":"Point"}
}