{
  "type": "Feature",
  "properties": {
    "iso:country":"ES",
    "sg:address":"Rua Progreso, 44",
    "sg:city":"Sanxenxo",
    "sg:orig_category":"Sociedades, Compa\u00d1\u00cdas Aseguradoras",
    "sg:phone":"+34 986 72 10 43",
    "sg:postcode":"36960",
    "sg:province":"Pontevedra",
    "wof:name":"Sernieto S.l.",
    "wof:placetype":"venue"
},
  "geometry": {"coordinates":[-8.799908638,42.4011306763],"type":"Point"}
}