{
  "type": "Feature",
  "properties": {
    "addr:full":"Carrer de Bernat Metge, 42 Mollet Valles Barcelona 08100",
    "addr:housenumber":"42",
    "addr:postcode":"08100",
    "addr:street":"Carrer De Bernat Metge",
    "iso:country":"ES",
    "sg:address":"Carrer de Bernat Metge, 42",
    "sg:city":"Mollet Valles",
    "sg:orig_category":"Electricidad (montaje, Ensamblaje De Componentes)",
    "sg:phone":"+34 935 93 17 98",
    "sg:postcode":"08100",
    "sg:province":"Barcelona",
    "wof:name":"Moreno Vaquer Alberto",
    "wof:placetype":"venue"
},
  "geometry": {"coordinates":[2.2084550858,41.5381126404],"type":"Point"}
}