{
  "type": "Feature",
  "properties": {
    "addr:full":"Calle de Diego De Los Reyes, 56 Castilleja Cuesta Sevilla 41950",
    "addr:housenumber":"56",
    "addr:postcode":"41950",
    "addr:street":"Calle De Diego De Los Reyes",
    "iso:country":"ES",
    "sg:address":"Calle de Diego De Los Reyes, 56",
    "sg:city":"Castilleja Cuesta",
    "sg:orig_category":"Contenedores (mercanc\u00cdas)",
    "sg:phone":"+34 954 16 24 45",
    "sg:postcode":"41950",
    "sg:province":"Sevilla",
    "wof:name":"Transmer Plan S.l.",
    "wof:placetype":"venue"
},
  "geometry": {"coordinates":[-6.0548400879,37.384853363],"type":"Point"}
}