{
  "type": "Feature",
  "properties": {
    "iso:country":"ES",
    "sg:address":"Calle de San Vicente Martir, 59",
    "sg:city":"Valencia",
    "sg:orig_category":"Bisuter\u00cda, Joyer\u00cda, Relojer\u00cda (al Por Menor)",
    "sg:phone":"+34 963 51 05 39",
    "sg:postcode":"46002",
    "sg:province":"Valencia",
    "wof:name":"Regalo Y Complementos S.a.",
    "wof:placetype":"venue"
},
  "geometry": {"coordinates":[-0.3784190118,39.4698638916],"type":"Point"}
}