{
  "type": "Feature",
  "properties": {
    "iso:country":"ES",
    "sg:address":"Avda Doctor Mara\u00d1on, 49",
    "sg:city":"Malaga",
    "sg:orig_category":"Estancos",
    "sg:phone":"+34 952 39 92 41",
    "sg:postcode":"29009",
    "sg:province":"M\u00e1laga",
    "wof:name":"Alonso Bueno Maria",
    "wof:placetype":"venue"
},
  "geometry": {"coordinates":[-4.4283423424,36.7321472168],"type":"Point"}
}