{
  "type": "Feature",
  "properties": {
    "addr:full":"Galicia, 14 Miranda Asturias 33410",
    "addr:housenumber":"14",
    "addr:postcode":"33410",
    "addr:street":"Galicia",
    "iso:country":"ES",
    "sg:address":"Galicia, 14",
    "sg:city":"Miranda",
    "sg:orig_category":"Empresas De Limpieza",
    "sg:phone":"+34 985 55 12 38",
    "sg:postcode":"33410",
    "sg:province":"Asturias",
    "wof:name":"Asturlimp Sl",
    "wof:placetype":"venue"
},
  "geometry": {"coordinates":[-5.9802451134,43.5585594177],"type":"Point"}
}