{
  "type": "Feature",
  "properties": {
    "addr:full":"Calle de Torre Arias, 23 Madrid Madrid 28022",
    "addr:housenumber":"23",
    "addr:postcode":"madrid;28022",
    "addr:street":"Calle De Torre Arias",
    "iso:country":"ES",
    "sg:address":"Calle de Torre Arias, 23",
    "sg:city":"Madrid",
    "sg:orig_category":"Peluqueros: De Se\u00d1oras",
    "sg:phone":"+34 913 20 12 18",
    "sg:postcode":"28022",
    "sg:province":"Madrid",
    "wof:name":"Ropero Del Amo Elisa",
    "wof:placetype":"venue"
},
  "geometry": {"coordinates":[-3.7057740688,40.42029953],"type":"Point"}
}