{
  "type": "Feature",
  "properties": {
    "iso:country":"ES",
    "sg:address":"Ronda Sur Almansa, S/n",
    "sg:city":"Almansa",
    "sg:orig_category":"M\u00c1rmoles, Granitos Y Piedras Naturales",
    "sg:phone":"+34 967 31 21 93",
    "sg:postcode":"02640",
    "sg:province":"Albacete",
    "wof:name":"Marmoles Y Granitos Aremar S.l.",
    "wof:placetype":"venue"
},
  "geometry": {"coordinates":[-1.1196290255,38.8718490601],"type":"Point"}
}