{
  "type": "Feature",
  "properties": {
    "iso:country":"ES",
    "sg:address":"Calle de Zugastinobia, 5",
    "sg:city":"Bilbao",
    "sg:orig_category":"Deportes Diversos",
    "sg:phone":"+34 944 21 26 49",
    "sg:postcode":"48012",
    "sg:province":"Vizcaya",
    "wof:name":"Sociedad De Caza Y Pesca Los Cazallos",
    "wof:placetype":"venue"
},
  "geometry": {"coordinates":[-2.942802906,43.2572059631],"type":"Point"}
}