{
  "type": "Feature",
  "properties": {
    "addr:full":"Calle de Concepcion Arenal, S/n Almonte Huelva 21730",
    "addr:housenumber":"s / n",
    "addr:postcode":"21730",
    "addr:street":"Calle De Concepcion Arenal",
    "iso:country":"ES",
    "sg:address":"Calle de Concepcion Arenal, S/n",
    "sg:city":"Almonte",
    "sg:orig_category":"Electromec\u00c1nica",
    "sg:phone":"+34 959 40 63 77",
    "sg:postcode":"21730",
    "sg:province":"Huelva",
    "wof:name":"Espina Espina Francisco",
    "wof:placetype":"venue"
},
  "geometry": {"coordinates":[-6.5356450081,37.0745658875],"type":"Point"}
}