{
  "type": "Feature",
  "properties": {
    "iso:country":"ES",
    "sg:address":"Avda Jose Ortega Y Gasset, 87",
    "sg:city":"Malaga",
    "sg:orig_category":"Fabricaci\u00d3n De Enlosados, Soler\u00cdas",
    "sg:phone":"+34 952 32 97 78",
    "sg:postcode":"29006",
    "sg:province":"M\u00e1laga",
    "wof:name":"Azulejos Antonio Infantes S.l.",
    "wof:placetype":"venue"
},
  "geometry": {"coordinates":[-4.4499402046,36.7104797363],"type":"Point"}
}