{
  "type": "Feature",
  "properties": {
    "iso:country":"ES",
    "sg:address":"Calle de San Martin, 35",
    "sg:city":"Valladolid",
    "sg:orig_category":"Comercio, Reparaci\u00d3n De Bicicletas, De Motocicletas, De Accesorios",
    "sg:phone":"+34 983 31 00 40",
    "sg:postcode":"47003",
    "sg:province":"Valladolid",
    "wof:name":"Garcia Iglesias Julio Gonzalo",
    "wof:placetype":"venue"
},
  "geometry": {"coordinates":[-4.7210168839,41.6565856934],"type":"Point"}
}