{
  "type": "Feature",
  "properties": {
    "iso:country":"ES",
    "sg:address":"Calle de Eduardo Mazon, 3",
    "sg:city":"Madrid",
    "sg:orig_category":"M\u00c9dicos: Estomatolog\u00cda",
    "sg:phone":"+34 913 20 75 29",
    "sg:postcode":"28042",
    "sg:province":"Madrid",
    "wof:name":"Ortega Ruano Juan Jose",
    "wof:placetype":"venue"
},
  "geometry": {"coordinates":[-3.6145420074,40.4523773193],"type":"Point"}
}