{
  "type": "Feature",
  "properties": {
    "addr:full":"Calle de Rio Narcea, 21 Gijon Asturias 33210",
    "addr:housenumber":"21",
    "addr:postcode":"33210",
    "addr:street":"Calle De Rio Narcea",
    "iso:country":"ES",
    "sg:address":"Calle de Rio Narcea, 21",
    "sg:city":"Gijon",
    "sg:orig_category":"Molduras, Junquillos, Listones Y Molduras Perforadas",
    "sg:phone":"+34 985 14 33 66",
    "sg:postcode":"33210",
    "sg:province":"Asturias",
    "wof:name":"Iglesias Rodriguez Luis",
    "wof:placetype":"venue"
},
  "geometry": {"coordinates":[-5.6653380394,43.5195007324],"type":"Point"}
}