{
  "type": "Feature",
  "properties": {
    "addr:full":"Ctra Tries, Les, 60 Olot Girona 17800",
    "addr:housenumber":"60",
    "addr:postcode":"17800",
    "addr:street":"Ctra Tries Les",
    "iso:country":"ES",
    "sg:address":"Ctra Tries, Les, 60",
    "sg:city":"Olot",
    "sg:orig_category":"Empresas De Pintura Y Revestimientos",
    "sg:phone":"+34 972 26 49 99",
    "sg:postcode":"17800",
    "sg:province":"Girona",
    "wof:name":"Plana Batalle Alfonso",
    "wof:placetype":"venue"
},
  "geometry": {"coordinates":[2.4893848896,42.1809463501],"type":"Point"}
}