{
  "type": "Feature",
  "properties": {
    "iso:country":"ES",
    "sg:address":"Calle de Calvo Sotelo, 30",
    "sg:city":"Chantada",
    "sg:orig_category":"Telas Y Sedas (al Por Menor)",
    "sg:phone":"+34 982 44 00 41",
    "sg:postcode":"27500",
    "sg:province":"Lugo",
    "wof:name":"Mazaira Perez Jose",
    "wof:placetype":"venue"
},
  "geometry": {"coordinates":[-7.7709708214,42.6089286804],"type":"Point"}
}