{
  "type": "Feature",
  "properties": {
    "addr:full":"Calle de Real, 32 Huetor-vega Granada 18198",
    "addr:housenumber":"32",
    "addr:postcode":"18198",
    "addr:street":"Calle De Real",
    "iso:country":"ES",
    "sg:address":"Calle de Real, 32",
    "sg:city":"Huetor-vega",
    "sg:orig_category":"Peluquer\u00cdas, Peluquer\u00cda Mixta",
    "sg:phone":"+34 958 30 39 28",
    "sg:postcode":"18198",
    "sg:province":"Granada",
    "wof:name":"Diaz Lozano Maria Teresa",
    "wof:placetype":"venue"
},
  "geometry": {"coordinates":[-3.5714380741,37.1445655823],"type":"Point"}
}