{
  "type": "Feature",
  "properties": {
    "iso:country":"ES",
    "sg:address":"Calle de Ofelia Nieto, 40",
    "sg:city":"Madrid",
    "sg:orig_category":"Mec\u00c1nico Del Autom\u00d3vil",
    "sg:phone":"+34 914 59 27 71",
    "sg:postcode":"28039",
    "sg:province":"Madrid",
    "wof:name":"Prado Garcia Manuel",
    "wof:placetype":"venue"
},
  "geometry": {"coordinates":[-3.7092878819,40.4603042603],"type":"Point"}
}