{
  "type": "Feature",
  "properties": {
    "iso:country":"ES",
    "sg:address":"Carrer de Montserrat, 154",
    "sg:city":"Martorell",
    "sg:orig_category":"Cables Y Hilos El\u00c9ctricos (fabricaci\u00d3n, Al Por Mayor)",
    "sg:phone":"+34 937 73 50 55",
    "sg:postcode":"08760",
    "sg:province":"Barcelona",
    "wof:name":"Tainco Gestio S.a.",
    "wof:placetype":"venue"
},
  "geometry": {"coordinates":[1.9204599857,41.4835700989],"type":"Point"}
}