{
  "type": "Feature",
  "properties": {
    "iso:country":"ES",
    "sg:address":"Calle de Santo\u00d1a, 13",
    "sg:city":"Madrid",
    "sg:orig_category":"Lencer\u00cda Femenina, Corseter\u00cda, Trajes De Ba\u00d1o (al Por Menor)",
    "sg:phone":"+34 914 60 06 57",
    "sg:postcode":"28026",
    "sg:province":"Madrid",
    "wof:name":"Villar Gonzalez Visitacion",
    "wof:placetype":"venue"
},
  "geometry": {"coordinates":[-3.7145619392,40.3819084167],"type":"Point"}
}