{
  "type": "Feature",
  "properties": {
    "iso:country":"ES",
    "sg:address":"Calle de Huertas (de Las), S/n",
    "sg:city":"Fuenmayor",
    "sg:orig_category":"Productores Recolectores, Venta Directa De Vinos",
    "sg:phone":"+34 941 45 10 83",
    "sg:postcode":"26360",
    "sg:province":"La Rioja",
    "wof:name":"Bodegas Cardema S.l.",
    "wof:placetype":"venue"
},
  "geometry": {"coordinates":[-2.5634939671,42.4646186829],"type":"Point"}
}