{
  "type": "Feature",
  "properties": {
    "iso:country":"ES",
    "sg:address":"Calle de Clavel, 6",
    "sg:city":"Palmas De Gran Canaria",
    "sg:orig_category":"Herboristas (al Por Menor)",
    "sg:phone":"+34 928 36 59 25",
    "sg:postcode":"35002",
    "sg:province":"Las Palmas",
    "wof:name":"Quevedo Marrero Jose",
    "wof:placetype":"venue"
},
  "geometry": {"coordinates":[-15.4154129028,28.1049461365],"type":"Point"}
}