{
  "type": "Feature",
  "properties": {
    "iso:country":"ES",
    "sg:address":"Plaz Universidad, 5",
    "sg:city":"Yunquera",
    "sg:orig_category":"Delegados, Agentes De Tr\u00c1nsito, Auxiliares De Transporte Internacional",
    "sg:phone":"+34 952 48 28 28",
    "sg:postcode":"29410",
    "sg:province":"M\u00e1laga",
    "wof:name":"Merino Asensio Jose",
    "wof:placetype":"venue"
},
  "geometry": {"coordinates":[-4.9454803467,36.7333068848],"type":"Point"}
}