{
  "type": "Feature",
  "properties": {
    "addr:full":"Avda Ferrandis Salvador, 8 Mas Dels Frares Castell\u00f3n 12560",
    "addr:housenumber":"8",
    "addr:postcode":"12560",
    "addr:street":"Avda Ferrandis Salvador;Castello\u0301N",
    "iso:country":"ES",
    "sg:address":"Avda Ferrandis Salvador, 8",
    "sg:city":"Mas Dels Frares",
    "sg:orig_category":"Delegados, Agentes De Tr\u00c1nsito, Auxiliares De Transporte Internacional",
    "sg:phone":"+34 964 30 46 07",
    "sg:postcode":"12560",
    "sg:province":"Castell\u00f3n",
    "wof:name":"Iba\u00f1ez Cabedo Rafael",
    "wof:placetype":"venue"
},
  "geometry": {"coordinates":[0.0687929988,40.047203064],"type":"Point"}
}