{
  "type": "Feature",
  "properties": {
    "addr:full":"Calle de Flores Las, 7 Arroyo De La Miel-benalmadena Costa M\u00e1laga 29631",
    "addr:housenumber":"7",
    "addr:postcode":"29631",
    "addr:street":"Calle De Flores Las;Arroyo De La Miel-Benalmadena Costa Ma\u0301Laga",
    "iso:country":"ES",
    "sg:address":"Calle de Flores Las, 7",
    "sg:city":"Arroyo De La Miel-benalmadena Costa",
    "sg:orig_category":"Pescader\u00cdas (al Por Menor)",
    "sg:phone":"+34 952 56 04 68",
    "sg:postcode":"29631",
    "sg:province":"M\u00e1laga",
    "wof:name":"Giraldez Chacon Dolores",
    "wof:placetype":"venue"
},
  "geometry": {"coordinates":[-4.5332360268,36.6002502441],"type":"Point"}
}