{
  "type": "Feature",
  "properties": {
    "addr:full":"Avda Corres, S/n Maestu \u00c1lava 01120",
    "addr:housenumber":"s",
    "addr:postcode":"01120",
    "addr:street":"Avda Corres;/ N Maestu A\u0301Lava",
    "iso:country":"ES",
    "sg:address":"Avda Corres, S/n",
    "sg:city":"Maestu",
    "sg:orig_category":"Paneles De Madera: Contrachapados, Fibras, Particulados, Estratificados (fabricaci\u00d3n, Venta)",
    "sg:phone":"+34 945 41 00 01",
    "sg:postcode":"01120",
    "sg:province":"\u00c1lava",
    "wof:name":"International Elaborados De Maestu S.l.",
    "wof:placetype":"venue"
},
  "geometry": {"coordinates":[-2.4472329617,42.7371940613],"type":"Point"}
}