{
  "type": "Feature",
  "properties": {
    "iso:country":"ES",
    "sg:address":"Crta. De Morella, S/n",
    "sg:city":"Herbes",
    "sg:orig_category":"Laboratorios Y Cl\u00cdnicas Veterinarias",
    "sg:phone":"+34 978 76 90 80",
    "sg:postcode":"12317",
    "sg:province":"Castell\u00f3n",
    "wof:name":"Centro De Inseminacion Artificial Porcina",
    "wof:placetype":"venue"
},
  "geometry": {"coordinates":[-0.004094,40.7209358215],"type":"Point"}
}