{
  "type": "Feature",
  "properties": {
    "iso:country":"ES",
    "sg:address":"Calle de Hilario Marco, 14",
    "sg:city":"Cazorla",
    "sg:orig_category":"Doctores En Medicina",
    "sg:phone":"+34 953 72 01 52",
    "sg:postcode":"23470",
    "sg:province":"Ja\u00e9n",
    "wof:name":"Ruiz Hueso Manuel",
    "wof:placetype":"venue"
},
  "geometry": {"coordinates":[-3.0041689873,37.9144172668],"type":"Point"}
}