{
  "type": "Feature",
  "properties": {
    "addr:full":"Avda Doctor Gadea, 24 Alacant Alicante 03001",
    "addr:housenumber":"24",
    "addr:postcode":"03001",
    "addr:street":"Avda Doctor Gadea",
    "iso:country":"ES",
    "sg:address":"Avda Doctor Gadea, 24",
    "sg:city":"Alacant",
    "sg:orig_category":"M\u00c9dicos: Estomatolog\u00cda",
    "sg:phone":"+34 965 21 98 69",
    "sg:postcode":"03001",
    "sg:province":"Alicante",
    "wof:name":"A\u00f1o Martinez Maria Consuelo",
    "wof:placetype":"venue"
},
  "geometry": {"coordinates":[-0.4883613884,38.3430671692],"type":"Point"}
}