{
  "type": "Feature",
  "properties": {
    "iso:country":"ES",
    "sg:address":"Quintana, S/n",
    "sg:city":"Posada",
    "sg:orig_category":"Empresas De Carpinter\u00cda De Madera",
    "sg:phone":"+34 985 40 73 46",
    "sg:postcode":"33594",
    "sg:province":"Asturias",
    "wof:name":"Carpinteria El Bosque S.c.",
    "wof:placetype":"venue"
},
  "geometry": {"coordinates":[-4.8510131836,43.4222412109],"type":"Point"}
}