{
  "type": "Feature",
  "properties": {
    "addr:full":"Calle de General Moscardo, 20 Madrid Madrid 28020",
    "addr:housenumber":"20",
    "addr:postcode":"madrid;28020",
    "addr:street":"Calle De General Moscardo",
    "iso:country":"ES",
    "sg:address":"Calle de General Moscardo, 20",
    "sg:city":"Madrid",
    "sg:orig_category":"Muebles Y Accesorios Para Cocinas Y Cuartos De Ba\u00d1o (al Por Menor)",
    "sg:phone":"+34 915 55 98 93",
    "sg:postcode":"28020",
    "sg:province":"Madrid",
    "sg:website":"www.gunni.es",
    "wof:name":"Gunni S. A.",
    "wof:placetype":"venue"
},
  "geometry": {"coordinates":[-3.6968486309,40.449054718],"type":"Point"}
}