{
  "type": "Feature",
  "properties": {
    "addr:full":"Cmi Moli, S/n Vallmoll Tarragona 43144",
    "addr:housenumber":"s",
    "addr:postcode":"43144",
    "addr:street":"/ N",
    "iso:country":"ES",
    "sg:address":"Cmi Moli, S/n",
    "sg:city":"Vallmoll",
    "sg:orig_category":"M\u00c1rmoles, Granitos Y Piedras Naturales",
    "sg:phone":"+34 977 63 74 48",
    "sg:postcode":"43144",
    "sg:province":"Tarragona",
    "wof:name":"Marbres Alt Camp S.l.",
    "wof:placetype":"venue"
},
  "geometry": {"coordinates":[1.249235034,41.2438163757],"type":"Point"}
}