{
  "type": "Feature",
  "properties": {
    "iso:country":"ES",
    "sg:address":"Leyre-leire Kalea, 2",
    "sg:city":"Iru\u00f1a",
    "sg:orig_category":"Agencias Y Agentes Comerciales, Representantes",
    "sg:phone":"+34 948 22 88 49",
    "sg:postcode":"31002",
    "sg:province":"Navarra",
    "wof:name":"Promociones Urbanisticas Bidea S.l.",
    "wof:placetype":"venue"
},
  "geometry": {"coordinates":[-1.6366300583,42.815788269],"type":"Point"}
}