{
  "type": "Feature",
  "properties": {
    "addr:full":"Calle de Segovia, 2 San Juan De Aznalfarache Sevilla 41920",
    "addr:housenumber":"2",
    "addr:postcode":"41920",
    "addr:street":"Calle De Segovia",
    "iso:country":"ES",
    "sg:address":"Calle de Segovia, 2",
    "sg:city":"San Juan De Aznalfarache",
    "sg:orig_category":"Carnicer\u00cdas, Carnicer\u00cdas",
    "sg:phone":"+34 954 76 73 61",
    "sg:postcode":"41920",
    "sg:province":"Sevilla",
    "wof:name":"Gamero Cubero Juan Antonio",
    "wof:placetype":"venue"
},
  "geometry": {"coordinates":[-6.0364851952,37.3570899963],"type":"Point"}
}