{
  "type": "Feature",
  "properties": {
    "addr:full":"J. Ramon Jimenez, 3 Parque Empresarial Madrid 28232",
    "addr:postcode":"28232",
    "addr:street":"Jimenez;Parque",
    "iso:country":"ES",
    "sg:address":"J. Ramon Jimenez, 3",
    "sg:city":"Parque Empresarial",
    "sg:orig_category":"Confecci\u00d3n De Ropa Interior",
    "sg:phone":"+34 916 40 01 46",
    "sg:postcode":"28232",
    "sg:province":"Madrid",
    "wof:name":"Warnaco Intimo S.a.",
    "wof:placetype":"venue"
},
  "geometry": {"coordinates":[-3.7003455162,40.4166908264],"type":"Point"}
}