{
  "type": "Feature",
  "properties": {
    "iso:country":"ES",
    "sg:address":"Calle de Moreta (de Los), 3",
    "sg:city":"Barco De Avila",
    "sg:orig_category":"Carnicer\u00cdas, Carnicer\u00cdas",
    "sg:phone":"+34 920 34 04 69",
    "sg:postcode":"05600",
    "sg:province":"\u00c1vila",
    "wof:name":"Venero Moreno Joaquin",
    "wof:placetype":"venue"
},
  "geometry": {"coordinates":[-5.5234298706,40.356262207],"type":"Point"}
}