{
  "type": "Feature",
  "properties": {
    "addr:full":"Carr Miraculosa, 7 Picassent Valencia 46220",
    "addr:housenumber":"7",
    "addr:postcode":"46220",
    "addr:street":"Carr Miraculosa",
    "iso:country":"ES",
    "sg:address":"Carr Miraculosa, 7",
    "sg:city":"Picassent",
    "sg:orig_category":"Farmacias",
    "sg:phone":"+34 961 23 02 39",
    "sg:postcode":"46220",
    "sg:province":"Valencia",
    "wof:name":"Poyatos Perez Beatriz",
    "wof:placetype":"venue"
},
  "geometry": {"coordinates":[-0.4595290124,39.3631401062],"type":"Point"}
}