{
  "type": "Feature",
  "properties": {
    "addr:full":"Carr Major, 17 Lliria Valencia 46160",
    "addr:housenumber":"17",
    "addr:postcode":"46160",
    "addr:street":"Carr Major",
    "iso:country":"ES",
    "sg:address":"Carr Major, 17",
    "sg:city":"Lliria",
    "sg:orig_category":"Reposter\u00cdas",
    "sg:phone":"+34 962 78 04 29",
    "sg:postcode":"46160",
    "sg:province":"Valencia",
    "wof:name":"Bodi Coi Roberto",
    "wof:placetype":"venue"
},
  "geometry": {"coordinates":[-0.5963310003,39.6259841919],"type":"Point"}
}