{
  "type": "Feature",
  "properties": {
    "addr:full":"Calle de Carreteros, 5 Casarrubios Monte Toledo 45950",
    "addr:housenumber":"5",
    "addr:postcode":"45950",
    "addr:street":"Calle De Carreteros",
    "iso:country":"ES",
    "sg:address":"Calle de Carreteros, 5",
    "sg:city":"Casarrubios Monte",
    "sg:orig_category":"Inmobiliaria (agencias)",
    "sg:phone":"+34 918 18 25 05",
    "sg:postcode":"45950",
    "sg:province":"Toledo",
    "wof:name":"Edarje S.l.",
    "wof:placetype":"venue"
},
  "geometry": {"coordinates":[-4.0385861397,40.1849784851],"type":"Point"}
}