{
  "type": "Feature",
  "properties": {
    "addr:full":"Calle de Villa (la), 65 Santa Cruz De Campezo \u00c1lava 01110",
    "addr:housenumber":"65",
    "addr:postcode":"01110",
    "addr:street":"Calle De Villa La;A\u0301Lava",
    "iso:country":"ES",
    "sg:address":"Calle de Villa (la), 65",
    "sg:city":"Santa Cruz De Campezo",
    "sg:orig_category":"Electricidad (montaje, Ensamblaje De Componentes)",
    "sg:phone":"+34 945 41 51 50",
    "sg:postcode":"01110",
    "sg:province":"\u00c1lava",
    "wof:name":"Azilu Chasco Miguel",
    "wof:placetype":"venue"
},
  "geometry": {"coordinates":[-2.354695797,42.6698989868],"type":"Point"}
}