{
  "type": "Feature",
  "properties": {
    "addr:full":"Calle de Eduardo Martinez Del Campo, 5 Burgos Burgos 09003",
    "addr:housenumber":"5",
    "addr:postcode":"09003",
    "addr:street":"Calle De Eduardo Martinez Del Campo",
    "iso:country":"ES",
    "sg:address":"Calle de Eduardo Martinez Del Campo, 5",
    "sg:city":"Burgos",
    "sg:orig_category":"Abogados",
    "sg:phone":"+34 947 20 62 37",
    "sg:postcode":"09003",
    "sg:province":"Burgos",
    "wof:name":"Diez-pardo Hernandez Isabel Maria",
    "wof:placetype":"venue"
},
  "geometry": {"coordinates":[-3.7059669495,42.3390541077],"type":"Point"}
}