{
  "type": "Feature",
  "properties": {
    "addr:full":"Calle de Juan De La Encina, 8 Almeria Almer\u00eda 04006",
    "addr:housenumber":"8",
    "addr:postcode":"04006",
    "addr:street":"Calle De Juan De La Encina",
    "iso:country":"ES",
    "sg:address":"Calle de Juan De La Encina, 8",
    "sg:city":"Almeria",
    "sg:orig_category":"Tintes (fabricaci\u00d3n, Al Por Mayor)",
    "sg:phone":"+34 950 23 27 89",
    "sg:postcode":"04006",
    "sg:province":"Almer\u00eda",
    "wof:name":"Martinez Imbarato Esteban",
    "wof:placetype":"venue"
},
  "geometry": {"coordinates":[-2.4482769966,36.8391838074],"type":"Point"}
}