{
  "type": "Feature",
  "properties": {
    "iso:country":"ES",
    "sg:address":"Calle de Albacete, 6",
    "sg:city":"Arganda",
    "sg:orig_category":"Higiene, Belleza: Art\u00cdculos (al Por Menor)",
    "sg:phone":"+34 918 72 91 66",
    "sg:postcode":"28500",
    "sg:province":"Madrid",
    "wof:name":"Eurosanic Maresme S.l.",
    "wof:placetype":"venue"
},
  "geometry": {"coordinates":[-3.4601624012,40.3075370789],"type":"Point"}
}