{
  "type": "Feature",
  "properties": {
    "iso:country":"ES",
    "sg:address":"Plaz Conde De Ferreria, 22",
    "sg:city":"Malaga",
    "sg:orig_category":"Carnicer\u00cdas, Carnicer\u00cdas",
    "sg:phone":"+34 952 30 85 32",
    "sg:postcode":"29009",
    "sg:province":"M\u00e1laga",
    "wof:name":"Tindor S.l.",
    "wof:placetype":"venue"
},
  "geometry": {"coordinates":[-4.428686142,36.7305450439],"type":"Point"}
}