{
  "type": "Feature",
  "properties": {
    "iso:country":"ES",
    "sg:address":"Calle de Corregidor Rodrigo Rodriguez, 1",
    "sg:city":"Madrid",
    "sg:orig_category":"Peluqueros: De Se\u00d1oras",
    "sg:phone":"+34 914 39 19 98",
    "sg:postcode":"28030",
    "sg:province":"Madrid",
    "wof:name":"Josefa Ginez Lorenzo",
    "wof:placetype":"venue"
},
  "geometry": {"coordinates":[-3.6607172489,40.40782547],"type":"Point"}
}