{
  "type": "Feature",
  "properties": {
    "iso:country":"ES",
    "sg:address":"C/ Mossen Jacint Verdaguer, 7",
    "sg:city":"Banyoles",
    "sg:orig_category":"Lencer\u00cda Femenina, Corseter\u00cda, Trajes De Ba\u00d1o (al Por Menor)",
    "sg:phone":"+34 972 57 58 09",
    "sg:postcode":"17820",
    "sg:province":"Girona",
    "sg:website":"www.noemilluna.com",
    "wof:name":"Lourdes Ubeda S.l.",
    "wof:placetype":"venue"
},
  "geometry": {"coordinates":[2.7626791,42.1179046631],"type":"Point"}
}