{
  "type": "Feature",
  "properties": {
    "iso:country":"ES",
    "sg:address":"Calle de Gordillo, 96",
    "sg:city":"Palmas De Gran Canaria",
    "sg:orig_category":"Asociaciones Y Clubs Deportivos",
    "sg:phone":"+34 928 46 23 37",
    "sg:postcode":"35009",
    "sg:province":"Las Palmas",
    "wof:name":"Vallecal S.l.",
    "wof:placetype":"venue"
},
  "geometry": {"coordinates":[-15.426987648,28.1527404785],"type":"Point"}
}