{
  "type": "Feature",
  "properties": {
    "addr:full":"Calle de Ferroviarios, 91 Madrid Madrid 28026",
    "addr:housenumber":"91",
    "addr:postcode":"madrid;28026",
    "addr:street":"Calle De Ferroviarios",
    "iso:country":"ES",
    "sg:address":"Calle de Ferroviarios, 91",
    "sg:city":"Madrid",
    "sg:orig_category":"Transporte En General",
    "sg:phone":"+34 914 75 11 56",
    "sg:postcode":"28026",
    "sg:province":"Madrid",
    "wof:name":"Alvarez Izquierdo Dionisio",
    "wof:placetype":"venue"
},
  "geometry": {"coordinates":[-3.7044432163,40.3820838928],"type":"Point"}
}