{
  "type": "Feature",
  "properties": {
    "iso:country":"ES",
    "sg:address":"Calle de Arrufat Alonso, 18",
    "sg:city":"Castellon",
    "sg:orig_category":"Cl\u00cdnicas Dentales",
    "sg:phone":"+34 964 25 16 33",
    "sg:postcode":"12001",
    "sg:province":"Castell\u00f3n",
    "wof:name":"Dental Corbi S.l.",
    "wof:placetype":"venue"
},
  "geometry": {"coordinates":[-0.0398918018,39.98960495],"type":"Point"}
}