{
  "type": "Feature",
  "properties": {
    "addr:full":"Calle de Rivero, 5 Sevilla Sevilla 41004",
    "addr:housenumber":"5",
    "addr:postcode":"41004",
    "addr:street":"Calle De Rivero",
    "iso:country":"ES",
    "sg:address":"Calle de Rivero, 5",
    "sg:city":"Sevilla",
    "sg:orig_category":"Peluquer\u00cdas, Peluquer\u00cda Mixta",
    "sg:phone":"+34 954 21 45 94",
    "sg:postcode":"41004",
    "sg:province":"Sevilla",
    "wof:name":"Estilistas Tendencias 4 S.l.",
    "wof:placetype":"venue"
},
  "geometry": {"coordinates":[-5.9938812256,37.3913383484],"type":"Point"}
}