{
  "type": "Feature",
  "properties": {
    "iso:country":"ES",
    "sg:address":"Carrer de Monturiol, S/n",
    "sg:city":"Rubi",
    "sg:orig_category":"Cristaler\u00cdas",
    "sg:phone":"+34 936 97 34 06",
    "sg:postcode":"08191",
    "sg:province":"Barcelona",
    "wof:name":"Gracia Garcia Carlos",
    "wof:placetype":"venue"
},
  "geometry": {"coordinates":[2.0332798958,41.4827308655],"type":"Point"}
}