{
  "type": "Feature",
  "properties": {
    "iso:country":"ES",
    "sg:address":"Av Castiero, 10",
    "sg:city":"Vielha",
    "sg:orig_category":"Juegos Y Juguetes (al Por Menor)",
    "sg:phone":"+34 973 64 09 90",
    "sg:postcode":"25530",
    "sg:province":"Lleida",
    "wof:name":"Establiments Cortina S.l",
    "wof:placetype":"venue"
},
  "geometry": {"coordinates":[0.7944080234,42.7027778625],"type":"Point"}
}