{
  "type": "Feature",
  "properties": {
    "iso:country":"ES",
    "sg:address":"Avda Almogavares (de), S/n",
    "sg:city":"Cordoba",
    "sg:orig_category":"Promotores Constructores",
    "sg:phone":"+34 957 43 37 39",
    "sg:postcode":"14006",
    "sg:province":"C\u00f3rdoba",
    "wof:name":"Construcciones Alben Martin S.l.",
    "wof:placetype":"venue"
},
  "geometry": {"coordinates":[-4.7760539055,37.8967132568],"type":"Point"}
}