{
  "type": "Feature",
  "properties": {
    "iso:country":"ES",
    "sg:address":"Calle de Cristobal Perez Pastor, 77",
    "sg:city":"Albacete",
    "sg:orig_category":"Fabricaci\u00d3n De Enlosados, Soler\u00cdas",
    "sg:phone":"+34 967 23 75 09",
    "sg:postcode":"02004",
    "sg:province":"Albacete",
    "wof:name":"Jose Naharro Sarrion Y Otro C.b.",
    "wof:placetype":"venue"
},
  "geometry": {"coordinates":[-1.8668726683,38.9941368103],"type":"Point"}
}