{
  "type": "Feature",
  "properties": {
    "addr:full":"Calle de Hospital (del), 4 Caracenilla Cuenca 16540",
    "addr:postcode":"16540",
    "addr:street":"Calle De",
    "iso:country":"ES",
    "sg:address":"Calle de Hospital (del), 4",
    "sg:city":"Caracenilla",
    "sg:orig_category":"Granos Y Semillas (producci\u00d3n, Al Por Mayor)",
    "sg:phone":"+34 969 27 26 60",
    "sg:postcode":"16540",
    "sg:province":"Cuenca",
    "wof:name":"Ajuyo Caracenilla S.l.l.",
    "wof:placetype":"venue"
},
  "geometry": {"coordinates":[-2.5689697266,40.1397438049],"type":"Point"}
}