{
  "type": "Feature",
  "properties": {
    "iso:country":"ES",
    "sg:address":"Calle de Escritor Busto Previ, 15",
    "sg:city":"Malaga",
    "sg:orig_category":"Textil",
    "sg:phone":"+34 952 43 19 57",
    "sg:postcode":"29190",
    "sg:province":"M\u00e1laga",
    "wof:name":"Mayorga Torreblanca Eduardo",
    "wof:placetype":"venue"
},
  "geometry": {"coordinates":[-4.4796910286,36.7379875183],"type":"Point"}
}