{
  "type": "Feature",
  "properties": {
    "addr:full":"Avda Arias De Velasco, 25 Marbella M\u00e1laga 29600",
    "addr:housenumber":"25",
    "addr:postcode":"29600",
    "addr:street":"Avda Arias De Velasco;Ma\u0301Laga",
    "iso:country":"ES",
    "sg:address":"Avda Arias De Velasco, 25",
    "sg:city":"Marbella",
    "sg:orig_category":"Ense\u00d1anza, Formaci\u00d3n Profesional: Aprendizaje",
    "sg:phone":"+34 952 76 26 00",
    "sg:postcode":"29600",
    "sg:province":"M\u00e1laga",
    "wof:name":"Direccion General De La Policia",
    "wof:placetype":"venue"
},
  "geometry": {"coordinates":[-4.8809938431,36.5162277222],"type":"Point"}
}