{
  "type": "Feature",
  "properties": {
    "addr:full":"Cal Marques, S/n Vall Bianya Girona 17813",
    "addr:housenumber":"s / n",
    "addr:postcode":"17813",
    "addr:street":"Cal Marques",
    "iso:country":"ES",
    "sg:address":"Cal Marques, S/n",
    "sg:city":"Vall Bianya",
    "sg:orig_category":"Laboratorios Y Cl\u00cdnicas Veterinarias",
    "sg:phone":"+34 972 29 03 33",
    "sg:postcode":"17813",
    "sg:province":"Girona",
    "wof:name":"Fort Dodge Veterinaria S.a.",
    "wof:placetype":"venue"
},
  "geometry": {"coordinates":[2.4543850422,42.2110366821],"type":"Point"}
}