{
  "type": "Feature",
  "properties": {
    "iso:country":"ES",
    "sg:address":"Avda Tirajana (de), 3",
    "sg:city":"Playa Del Ingles",
    "sg:orig_category":"Discotecas Y Salas De Baile",
    "sg:phone":"+34 928 76 06 77",
    "sg:postcode":"35100",
    "sg:province":"Las Palmas",
    "wof:name":"Mcfall  Kent",
    "wof:placetype":"venue"
},
  "geometry": {"coordinates":[-15.5772924423,27.7519817352],"type":"Point"}
}