{
  "type": "Feature",
  "properties": {
    "addr:full":"Ctra Canillas, 144 Madrid Madrid 28043",
    "addr:housenumber":"144",
    "addr:postcode":"28043",
    "addr:street":"Ctra Canillas",
    "iso:country":"ES",
    "sg:address":"Ctra Canillas, 144",
    "sg:city":"Madrid",
    "sg:orig_category":"Venta, Montaje De Neum\u00c1ticos",
    "sg:phone":"+34 913 81 35 02",
    "sg:postcode":"28043",
    "sg:province":"Madrid",
    "wof:name":"Mayor Moral Agustin",
    "wof:placetype":"venue"
},
  "geometry": {"coordinates":[-3.6387419701,40.465133667],"type":"Point"}
}