{
  "type": "Feature",
  "properties": {
    "iso:country":"ES",
    "sg:address":"Cra. Aigues, S/n",
    "sg:city":"Cardedeu",
    "sg:orig_category":"Imprenta",
    "sg:phone":"+34 938 45 40 18",
    "sg:postcode":"08440",
    "sg:province":"Barcelona",
    "wof:name":"Smart Impression S.l.",
    "wof:placetype":"venue"
},
  "geometry": {"coordinates":[2.3615949154,41.6211891174],"type":"Point"}
}