{
  "type": "Feature",
  "properties": {
    "iso:country":"ES",
    "sg:address":"Pica-soques El, 25",
    "sg:city":"S. Jordi Salines",
    "sg:orig_category":"Molduras, Junquillos, Listones Y Molduras Perforadas",
    "sg:phone":"+34 971 30 42 24",
    "sg:postcode":"07817",
    "sg:province":"Islas Baleares",
    "wof:name":"Baena Arredondo Pedro",
    "wof:placetype":"venue"
},
  "geometry": {"coordinates":[1.3922774792,38.9040298462],"type":"Point"}
}