{
  "type": "Feature",
  "properties": {
    "addr:full":"Calle de Pizarro, S/n Aranda Duero Burgos 09400",
    "addr:housenumber":"s / n",
    "addr:postcode":"09400",
    "addr:street":"Calle De Pizarro",
    "iso:country":"ES",
    "sg:address":"Calle de Pizarro, S/n",
    "sg:city":"Aranda Duero",
    "sg:orig_category":"Polideportivos",
    "sg:phone":"+34 947 51 03 30",
    "sg:postcode":"09400",
    "sg:province":"Burgos",
    "wof:name":"Ayuntamiento De Aranda De Duero",
    "wof:placetype":"venue"
},
  "geometry": {"coordinates":[-3.6763689518,41.6702957153],"type":"Point"}
}