{
  "type": "Feature",
  "properties": {
    "addr:full":"Calle de Molino (el), 7 Villagonzalo-pedernales Burgos 09195",
    "addr:housenumber":"7",
    "addr:postcode":"09195",
    "addr:street":"Calle De Molino El",
    "iso:country":"ES",
    "sg:address":"Calle de Molino (el), 7",
    "sg:city":"Villagonzalo-pedernales",
    "sg:orig_category":"Plomeros",
    "sg:phone":"+34 947 29 43 36",
    "sg:postcode":"09195",
    "sg:province":"Burgos",
    "wof:name":"Manso Civera Luis Alberto",
    "wof:placetype":"venue"
},
  "geometry": {"coordinates":[-3.7345690727,42.3016433716],"type":"Point"}
}