{
  "type": "Feature",
  "properties": {
    "addr:full":"Calle de Cirilo Santos, 29 Santa Maria Del Paramo Le\u00f3n 24240",
    "addr:housenumber":"29",
    "addr:postcode":"24240",
    "addr:street":"Calle De Cirilo Santos",
    "iso:country":"ES",
    "sg:address":"Calle de Cirilo Santos, 29",
    "sg:city":"Santa Maria Del Paramo",
    "sg:orig_category":"Servicios Gsm",
    "sg:phone":"+34 987 35 05 69",
    "sg:postcode":"24240",
    "sg:province":"Le\u00f3n",
    "wof:name":"Fonocinco S.l.",
    "wof:placetype":"venue"
},
  "geometry": {"coordinates":[-5.7498998642,42.3542861938],"type":"Point"}
}