{
  "type": "Feature",
  "properties": {
    "addr:full":"Calle de Puerta De La Villa, 2 Roa Burgos 09300",
    "addr:housenumber":"2",
    "addr:postcode":"09300",
    "addr:street":"Calle De Puerta De La Villa",
    "iso:country":"ES",
    "sg:address":"Calle de Puerta De La Villa, 2",
    "sg:city":"Roa",
    "sg:orig_category":"Empresas De Carpinter\u00cda Met\u00c1lica",
    "sg:phone":"+34 947 54 02 70",
    "sg:postcode":"09300",
    "sg:province":"Burgos",
    "wof:name":"Carpinteria Metalica Arauzo S.l.",
    "wof:placetype":"venue"
},
  "geometry": {"coordinates":[-3.9305949211,41.6977806091],"type":"Point"}
}