{
  "type": "Feature",
  "properties": {
    "addr:full":"Carr Llarguer, 4 Gandia Valencia 46700",
    "addr:housenumber":"4",
    "addr:postcode":"46700",
    "addr:street":"Carr Llarguer;Valencia",
    "iso:country":"ES",
    "sg:address":"Carr Llarguer, 4",
    "sg:city":"Gandia",
    "sg:orig_category":"Venta Al Preg\u00d3n",
    "sg:phone":"+34 962 86 06 06",
    "sg:postcode":"46700",
    "sg:province":"Valencia",
    "wof:name":"Creix Nieto Eduardo",
    "wof:placetype":"venue"
},
  "geometry": {"coordinates":[-0.1913339943,38.960735321],"type":"Point"}
}