{
  "type": "Feature",
  "properties": {
    "iso:country":"ES",
    "sg:address":"Carrer de Salvador Espriu, 58",
    "sg:city":"Mollet Valles",
    "sg:orig_category":"Panader\u00cdas, Panader\u00cdas",
    "sg:phone":"+34 935 93 42 90",
    "sg:postcode":"08100",
    "sg:province":"Barcelona",
    "wof:name":"Reposteria Artesana S.c.p.",
    "wof:placetype":"venue"
},
  "geometry": {"coordinates":[2.202630043,41.5467033386],"type":"Point"}
}