{
  "type": "Feature",
  "properties": {
    "addr:full":"Av Catalunya, 12 Cervera Lleida 25200",
    "addr:housenumber":"12",
    "addr:postcode":"25200",
    "addr:street":"Av Catalunya",
    "iso:country":"ES",
    "sg:address":"Av Catalunya, 12",
    "sg:city":"Cervera",
    "sg:orig_category":"Cajas De Ahorro",
    "sg:phone":"+34 973 53 00 97",
    "sg:postcode":"25200",
    "sg:province":"Lleida",
    "wof:name":"Caja De Ahorros Y Monte De Piedad De Zaragoza Aragon Y Rioja",
    "wof:placetype":"venue"
},
  "geometry": {"coordinates":[1.2717599869,41.6649856567],"type":"Point"}
}