{
  "type": "Feature",
  "properties": {
    "addr:full":"Rbla Independencia, 2 Silla Valencia 46460",
    "addr:housenumber":"2",
    "addr:postcode":"46460",
    "addr:street":"Rbla Independencia",
    "iso:country":"ES",
    "sg:address":"Rbla Independencia, 2",
    "sg:city":"Silla",
    "sg:orig_category":"Poller\u00cda Y Caza (al Por Menor)",
    "sg:phone":"+34 961 21 30 42",
    "sg:postcode":"46460",
    "sg:province":"Valencia",
    "wof:name":"Pollos Planes S.l.",
    "wof:placetype":"venue"
},
  "geometry": {"coordinates":[-0.4125829935,39.3615036011],"type":"Point"}
}