{
  "type": "Feature",
  "properties": {
    "iso:country":"ES",
    "sg:address":"Calle de Sanchez Pacheco, 93",
    "sg:city":"Madrid",
    "sg:orig_category":"Electricidad, Electr\u00d3nica: Suministros (al Por Menor)",
    "sg:phone":"+34 915 10 05 93",
    "sg:postcode":"28002",
    "sg:province":"Madrid",
    "wof:name":"Microelectronica Espa\u00d1ola S.a.",
    "wof:placetype":"venue"
},
  "geometry": {"coordinates":[-3.6677820683,40.4494018555],"type":"Point"}
}