{
  "type": "Feature",
  "properties": {
    "iso:country":"ES",
    "sg:address":"Calle de Batalla Del Salado, 51",
    "sg:city":"Madrid",
    "sg:orig_category":"Aparcamientos (infraestructuras, Accesorios)",
    "sg:phone":"+34 914 68 45 17",
    "sg:postcode":"28045",
    "sg:province":"Madrid",
    "wof:name":"Sayalero Lopez Victoriano",
    "wof:placetype":"venue"
},
  "geometry": {"coordinates":[-3.6963000298,40.3978385925],"type":"Point"}
}