{
  "type": "Feature",
  "properties": {
    "iso:country":"ES",
    "sg:address":"Carrer de Pau Claris, 18",
    "sg:city":"Santa Perpetua De Mogoda",
    "sg:orig_category":"Inform\u00c1tica (estudios, Servicios, Asesor\u00cda, Formaci\u00d3n)",
    "sg:phone":"+34 935 74 19 33",
    "sg:postcode":"08130",
    "sg:province":"Barcelona",
    "wof:name":"Informatica Sanitaria S.c.p.",
    "wof:placetype":"venue"
},
  "geometry": {"coordinates":[2.1837260723,41.5336112976],"type":"Point"}
}