{
  "type": "Feature",
  "properties": {
    "addr:full":"Calle de Merced, 17 Burgos Burgos 09002",
    "addr:housenumber":"17",
    "addr:postcode":"09002",
    "addr:street":"Calle De Merced",
    "iso:country":"ES",
    "sg:address":"Calle de Merced, 17",
    "sg:city":"Burgos",
    "sg:orig_category":"Caf\u00c9s, Bares, Cervecer\u00cdas",
    "sg:phone":"+34 947 20 49 50",
    "sg:postcode":"09002",
    "sg:province":"Burgos",
    "wof:name":"Mate Mate Gumersindo S.c.",
    "wof:placetype":"venue"
},
  "geometry": {"coordinates":[-3.7042710781,42.3381004333],"type":"Point"}
}