{
  "type": "Feature",
  "properties": {
    "addr:full":"Calle de Parroco Fernandez Pedrera, 25 Pola De Siero Asturias 33510",
    "addr:housenumber":"25",
    "addr:postcode":"33510",
    "addr:street":"Calle De Parroco Fernandez Pedrera",
    "iso:country":"ES",
    "sg:address":"Calle de Parroco Fernandez Pedrera, 25",
    "sg:city":"Pola De Siero",
    "sg:orig_category":"Escayola Y Productos De Escayola (fabricaci\u00d3n, Al Por Mayor)",
    "sg:phone":"+34 985 72 19 79",
    "sg:postcode":"33510",
    "sg:province":"Asturias",
    "wof:name":"Hevia Perez Florentino",
    "wof:placetype":"venue"
},
  "geometry": {"coordinates":[-5.6571159363,43.3875541687],"type":"Point"}
}