{
  "type": "Feature",
  "properties": {
    "iso:country":"ES",
    "sg:address":"Mercat Sant Marti, S/n",
    "sg:city":"Barcelona",
    "sg:orig_category":"Carnicer\u00cdas, Carnicer\u00cdas",
    "sg:phone":"+34 933 13 47 94",
    "sg:postcode":"08020",
    "sg:province":"Barcelona",
    "wof:name":"Montserrat Marti Grau",
    "wof:placetype":"venue"
},
  "geometry": {"coordinates":[2.1956210136,41.4245605469],"type":"Point"}
}