{
  "type": "Feature",
  "properties": {
    "addr:full":"Calle de Bolivia, 19 Zaragoza Zaragoza 50010",
    "addr:housenumber":"19",
    "addr:postcode":"50010",
    "addr:street":"Calle De Bolivia",
    "iso:country":"ES",
    "sg:address":"Calle de Bolivia, 19",
    "sg:city":"Zaragoza",
    "sg:orig_category":"Peleter\u00cdas",
    "sg:phone":"+34 976 53 26 67",
    "sg:postcode":"50010",
    "sg:province":"Zaragoza",
    "wof:name":"Las Benedi Jesus",
    "wof:placetype":"venue"
},
  "geometry": {"coordinates":[-0.8986213803,41.6521949768],"type":"Point"}
}