{
  "type": "Feature",
  "properties": {
    "iso:country":"ES",
    "sg:address":"Carrer de Voluntaris, 85",
    "sg:city":"Terrassa",
    "sg:orig_category":"Molduras, Junquillos, Listones Y Molduras Perforadas",
    "sg:phone":"+34 937 35 67 30",
    "sg:postcode":"08225",
    "sg:province":"Barcelona",
    "wof:name":"Romero Amaro Jose Luis",
    "wof:placetype":"venue"
},
  "geometry": {"coordinates":[2.013256073,41.5775871277],"type":"Point"}
}