{
  "type": "Feature",
  "properties": {
    "iso:country":"ES",
    "sg:address":"Avda Juan Carlos I, 6",
    "sg:city":"Talavera Reina",
    "sg:orig_category":"Droguer\u00cdas (al Por Mayor)",
    "sg:phone":"+34 925 82 18 45",
    "sg:postcode":"45600",
    "sg:province":"Toledo",
    "wof:name":"Almacenes Felipe Godoy E Hijos S.l.",
    "wof:placetype":"venue"
},
  "geometry": {"coordinates":[-4.8181834221,39.9636917114],"type":"Point"}
}