{
  "type": "Feature",
  "properties": {
    "addr:full":"Casilla, S/n Otones De Benjumea Segovia 40394",
    "addr:postcode":"40394",
    "addr:street":"S / N",
    "iso:country":"ES",
    "sg:address":"Casilla, S/n",
    "sg:city":"Otones De Benjumea",
    "sg:orig_category":"Agricultores, Agricultores",
    "sg:phone":"+34 921 12 70 89",
    "sg:postcode":"40394",
    "sg:province":"Segovia",
    "wof:name":"Paraje Los Calderones S.l.",
    "wof:placetype":"venue"
},
  "geometry": {"coordinates":[-4.0558609962,41.1351356506],"type":"Point"}
}