{
  "type": "Feature",
  "properties": {
    "addr:full":"Ibarra Kalea, 14 Bergara Guip\u00f9zcoa 20570",
    "addr:housenumber":"14",
    "addr:postcode":"20570",
    "addr:street":"Ibarra Kalea;Guipu\u0300Zcoa",
    "iso:country":"ES",
    "sg:address":"Ibarra Kalea, 14",
    "sg:city":"Bergara",
    "sg:orig_category":"Restaurantes",
    "sg:phone":"+34 943 76 42 57",
    "sg:postcode":"20570",
    "sg:province":"Guip\u00f9zcoa",
    "wof:name":"Suinaga Azcarate-ascasua Antonia",
    "wof:placetype":"venue"
},
  "geometry": {"coordinates":[-2.4255619049,43.1030921936],"type":"Point"}
}