{
  "type": "Feature",
  "properties": {
    "iso:country":"ES",
    "sg:address":"Trva Gran Via, 57",
    "sg:city":"Fuente Alamo",
    "sg:orig_category":"Asociaciones Y Clubs Deportivos",
    "sg:phone":"+34 968 59 89 01",
    "sg:postcode":"30320",
    "sg:province":"Murcia",
    "wof:name":"Rosique Martinez Jose",
    "wof:placetype":"venue"
},
  "geometry": {"coordinates":[-1.1687190533,37.7235946655],"type":"Point"}
}