{
  "type": "Feature",
  "properties": {
    "addr:full":"Carrer de Cova D'es Drac, De Sa, 15 Cala Santanyi Islas Baleares 07659",
    "addr:housenumber":"15",
    "addr:postcode":"07659",
    "addr:street":"Carrer De Cova D'Es Drac De Sa;Santanyi",
    "iso:country":"ES",
    "sg:address":"Carrer de Cova D'es Drac, De Sa, 15",
    "sg:city":"Cala Santanyi",
    "sg:orig_category":"Inmobiliaria (agencias)",
    "sg:phone":"+34 971 16 55 69",
    "sg:postcode":"07659",
    "sg:province":"Islas Baleares",
    "wof:name":"Burguera Pons Damian",
    "wof:placetype":"venue"
},
  "geometry": {"coordinates":[3.1466081142,39.3319740295],"type":"Point"}
}