{
  "type": "Feature",
  "properties": {
    "iso:country":"ES",
    "sg:address":"Calle de Visconti, 14",
    "sg:city":"Tarazona",
    "sg:orig_category":"Ropa Para Se\u00d1oras (al Por Menor)",
    "sg:phone":"+34 976 64 07 00",
    "sg:postcode":"50500",
    "sg:province":"Zaragoza",
    "wof:name":"Gomez Ullate Maria Del Carmen",
    "wof:placetype":"venue"
},
  "geometry": {"coordinates":[-1.7256920338,41.9051589966],"type":"Point"}
}