{
  "type": "Feature",
  "properties": {
    "addr:full":"Calle de Virgen De Guia, 41 Castilleja Cuesta Sevilla 41950",
    "addr:housenumber":"41",
    "addr:postcode":"41950",
    "addr:street":"Calle De Virgen De Guia",
    "iso:country":"ES",
    "sg:address":"Calle de Virgen De Guia, 41",
    "sg:city":"Castilleja Cuesta",
    "sg:orig_category":"Agencias Y Agentes Comerciales, Representantes",
    "sg:phone":"+34 954 16 14 56",
    "sg:postcode":"41950",
    "sg:province":"Sevilla",
    "wof:name":"Chacon Lopez Jose Maria",
    "wof:placetype":"venue"
},
  "geometry": {"coordinates":[-6.0632090569,37.3866577148],"type":"Point"}
}