{
  "type": "Feature",
  "properties": {
    "addr:full":"Ctra Barcelona, 661 Sabadell Barcelona 08204",
    "addr:housenumber":"661",
    "addr:postcode":"08204",
    "addr:street":"Ctra Barcelona",
    "iso:country":"ES",
    "sg:address":"Ctra Barcelona, 661",
    "sg:city":"Sabadell",
    "sg:orig_category":"Cajas De Ahorro",
    "sg:phone":"+34 937 10 32 37",
    "sg:postcode":"08204",
    "sg:province":"Barcelona",
    "sg:website":"www.caixacatalunya.es",
    "wof:name":"Caixa D'estalvis De Catalunya",
    "wof:placetype":"venue"
},
  "geometry": {"coordinates":[2.1201300621,41.5259208679],"type":"Point"}
}