{
  "type": "Feature",
  "properties": {
    "iso:country":"ES",
    "sg:address":"Rua Tomas A Alonso, 251",
    "sg:city":"Vigo",
    "sg:orig_category":"Farmacias",
    "sg:phone":"+34 986 23 38 42",
    "sg:postcode":"36208",
    "sg:province":"Pontevedra",
    "wof:name":"Vieitez Rodriguez Maria Teresa",
    "wof:placetype":"venue"
},
  "geometry": {"coordinates":[-8.7486534119,42.2234115601],"type":"Point"}
}