{
  "type": "Feature",
  "properties": {
    "iso:country":"ES",
    "sg:address":"Bodegas Del Ca\u00f1o, S/n",
    "sg:city":"Fuensalda\u00d1a",
    "sg:orig_category":"Bebidas",
    "sg:phone":"+34 983 58 33 87",
    "sg:postcode":"47194",
    "sg:province":"Valladolid",
    "wof:name":"Fraile Valles Miguel",
    "wof:placetype":"venue"
},
  "geometry": {"coordinates":[-4.7626929283,41.7072410583],"type":"Point"}
}