{
  "type": "Feature",
  "properties": {
    "iso:country":"ES",
    "sg:address":"Calle de Reyes Catolicos, 31",
    "sg:city":"Avila",
    "sg:orig_category":"Abogados",
    "sg:phone":"+34 920 25 34 15",
    "sg:postcode":"05001",
    "sg:province":"\u00c1vila",
    "wof:name":"Lopez Picon Ignacio",
    "wof:placetype":"venue"
},
  "geometry": {"coordinates":[-4.6983098984,40.6557197571],"type":"Point"}
}