{
  "type": "Feature",
  "properties": {
    "addr:full":"Calle de Manuel Gomez Casta\u00d1o, 38 Olivenza Badajoz 06100",
    "addr:housenumber":"38",
    "addr:postcode":"06100",
    "addr:street":"Calle De Manuel Gomez Castan\u0303O",
    "iso:country":"ES",
    "sg:address":"Calle de Manuel Gomez Casta\u00d1o, 38",
    "sg:city":"Olivenza",
    "sg:orig_category":"Asesor\u00cda Fiscal Y Jur\u00cddica",
    "sg:phone":"+34 924 49 17 30",
    "sg:postcode":"06100",
    "sg:province":"Badajoz",
    "wof:name":"Asesoria Iemex S.l.",
    "wof:placetype":"venue"
},
  "geometry": {"coordinates":[-7.1030583382,38.682849884],"type":"Point"}
}