{
  "type": "Feature",
  "properties": {
    "iso:country":"ES",
    "sg:address":"Calle de Cruz De La Langosta, 8",
    "sg:city":"Hellin",
    "sg:orig_category":"Animales (al Por Menor)",
    "sg:phone":"+34 967 30 32 15",
    "sg:postcode":"02400",
    "sg:province":"Albacete",
    "wof:name":"Distribuciones Santos S.l.",
    "wof:placetype":"venue"
},
  "geometry": {"coordinates":[-1.7034054995,38.5164718628],"type":"Point"}
}