{
  "type": "Feature",
  "properties": {
    "iso:country":"ES",
    "sg:address":"Calle de Galicia, 3",
    "sg:city":"Estacion",
    "sg:orig_category":"Rectificaci\u00d3n, Mecanizado, Fresado",
    "sg:phone":"+34 925 54 58 66",
    "sg:postcode":"45220",
    "sg:province":"Toledo",
    "wof:name":"Mecanizados San Jose Parejo S.l.",
    "wof:placetype":"venue"
},
  "geometry": {"coordinates":[-3.8059339523,40.1223945618],"type":"Point"}
}