{
  "type": "Feature",
  "properties": {
    "addr:full":"Las Dalias, 10 S. Agustin-playa Ingles Las Palmas 35100",
    "addr:housenumber":"10",
    "addr:postcode":"35100",
    "addr:street":"Las Dalias",
    "iso:country":"ES",
    "sg:address":"Las Dalias, 10",
    "sg:city":"S. Agustin-playa Ingles",
    "sg:orig_category":"Edici\u00d3n De Diarios, Revistas, Boletines",
    "sg:phone":"+34 928 76 84 20",
    "sg:postcode":"35100",
    "sg:province":"Las Palmas",
    "wof:name":"Dn Publications & Investment S.l.",
    "wof:placetype":"venue"
},
  "geometry": {"coordinates":[-15.4397096634,28.1302204132],"type":"Point"}
}