{
  "type": "Feature",
  "properties": {
    "addr:full":"Avda Navarra, S/n Rada Navarra 31383",
    "addr:housenumber":"/ n",
    "addr:postcode":"31383",
    "addr:street":"Avda Navarra S",
    "iso:country":"ES",
    "sg:address":"Avda Navarra, S/n",
    "sg:city":"Rada",
    "sg:orig_category":"Electromec\u00c1nica",
    "sg:phone":"+34 948 73 11 42",
    "sg:postcode":"31383",
    "sg:province":"Navarra",
    "sg:website":"www.elementosmagneticos.com",
    "wof:name":"Elementos Magneticos Navarra S.l.",
    "wof:placetype":"venue"
},
  "geometry": {"coordinates":[-1.5746389627,42.3198661804],"type":"Point"}
}