{
  "type": "Feature",
  "properties": {
    "addr:full":"Calle de Eloy Gonzalo, 8 Madrid Madrid 28010",
    "addr:housenumber":"8",
    "addr:postcode":"madrid;28010",
    "addr:street":"Calle De Eloy Gonzalo",
    "iso:country":"ES",
    "sg:address":"Calle de Eloy Gonzalo, 8",
    "sg:city":"Madrid",
    "sg:orig_category":"Molduras, Junquillos, Listones Y Molduras Perforadas",
    "sg:phone":"+34 914 48 51 18",
    "sg:postcode":"28010",
    "sg:province":"Madrid",
    "wof:name":"Abellan Martinez Jose Luis",
    "wof:placetype":"venue"
},
  "geometry": {"coordinates":[-3.703116,40.433857],"type":"Point"}
}