{
  "type": "Feature",
  "properties": {
    "addr:full":"Calle de Corredera Del Cristo, 2 Talavera Reina Toledo 45600",
    "addr:housenumber":"2",
    "addr:postcode":"45600",
    "addr:street":"Calle De Corredera Del Cristo",
    "iso:country":"ES",
    "sg:address":"Calle de Corredera Del Cristo, 2",
    "sg:city":"Talavera Reina",
    "sg:orig_category":"Mutuas De Seguros",
    "sg:phone":"+34 925 80 92 60",
    "sg:postcode":"45600",
    "sg:province":"Toledo",
    "sg:website":"www.midat-mutua.es",
    "wof:name":"Mutual Midat Cyclops Mutua De Accidentes De Trabajo Y Enfermedades Profesionales De La Seguridad Soc",
    "wof:placetype":"venue"
},
  "geometry": {"coordinates":[-4.8325314522,39.9601860046],"type":"Point"}
}