{
  "type": "Feature",
  "properties": {
    "iso:country":"ES",
    "sg:address":"Calle de San Juan De Dios, 30",
    "sg:city":"Granada",
    "sg:orig_category":"Centros Empresariales",
    "sg:phone":"+34 958 29 05 80",
    "sg:postcode":"18001",
    "sg:province":"Granada",
    "wof:name":"Sociedad Europea De Consultores Juridicos Y De Empresas S.l.",
    "wof:placetype":"venue"
},
  "geometry": {"coordinates":[-3.6025490761,37.1811676025],"type":"Point"}
}