{
  "type": "Feature",
  "properties": {
    "iso:country":"ES",
    "sg:address":"Avda Galicia De, 58",
    "sg:city":"Oviedo",
    "sg:orig_category":"M\u00c9dicos: Medicina General",
    "sg:phone":"+34 985 23 90 87",
    "sg:postcode":"33005",
    "sg:province":"Asturias",
    "wof:name":"Dentap Poo C.b.",
    "wof:placetype":"venue"
},
  "geometry": {"coordinates":[-5.8567590714,43.3610992432],"type":"Point"}
}