{
  "type": "Feature",
  "properties": {
    "iso:country":"ES",
    "sg:address":"Carrer de Gran De Gracia, 91",
    "sg:city":"Barcelona",
    "sg:orig_category":"Productos Alimentarios",
    "sg:phone":"+34 932 17 49 21",
    "sg:postcode":"08012",
    "sg:province":"Barcelona",
    "sg:website":"www.e-teashop.com",
    "wof:name":"East West Company Spain S.l.",
    "wof:placetype":"venue"
},
  "geometry": {"coordinates":[2.1543259621,41.400718689],"type":"Point"}
}