{
  "type": "Feature",
  "properties": {
    "addr:full":"Avda Andres De Cerezo, 55 Cerezo De Rio Tiron Burgos 09270",
    "addr:housenumber":"55",
    "addr:postcode":"09270",
    "addr:street":"Avda Andres De Cerezo",
    "iso:country":"ES",
    "sg:address":"Avda Andres De Cerezo, 55",
    "sg:city":"Cerezo De Rio Tiron",
    "sg:orig_category":"Negocio De Materiales De Construcci\u00d3n",
    "sg:phone":"+34 947 58 30 97",
    "sg:postcode":"09270",
    "sg:province":"Burgos",
    "wof:name":"Manero Aguero Francisca",
    "wof:placetype":"venue"
},
  "geometry": {"coordinates":[-3.1371591091,42.4920005798],"type":"Point"}
}