{
  "type": "Feature",
  "properties": {
    "iso:country":"ES",
    "sg:address":"Calle de Larga, 56",
    "sg:city":"Olivares",
    "sg:classifiers":[
        {
            "category":"Autos & Motor Vehicles",
            "subcategory":"Automobile Sales",
            "type":"Retail Goods"
        }
    ],
    "sg:phone":"+34 955 71 89 44",
    "sg:postcode":"41804",
    "sg:province":"Sevilla",
    "wof:name":"Cotan Cotan Manuel",
    "wof:placetype":"venue"
},
  "geometry": {"coordinates":[-6.1557221413,37.4195632935],"type":"Point"}
}