{
  "type": "Feature",
  "properties": {
    "addr:full":"Calle de Padre Manjon, 10 Elda Alicante 03600",
    "addr:housenumber":"10",
    "addr:postcode":"03600",
    "addr:street":"Calle De Padre Manjon",
    "iso:country":"ES",
    "sg:address":"Calle de Padre Manjon, 10",
    "sg:city":"Elda",
    "sg:orig_category":"Cl\u00cdnicas M\u00c9dicas",
    "sg:phone":"+34 966 98 20 50",
    "sg:postcode":"03600",
    "sg:province":"Alicante",
    "wof:name":"Clinica Medicoginecologica S.l.",
    "wof:placetype":"venue"
},
  "geometry": {"coordinates":[-0.7928990126,38.4757347107],"type":"Point"}
}