{
  "type": "Feature",
  "properties": {
    "addr:full":"Ctra Camas-santiponce, Km. 0005,0 Camas Sevilla 41900",
    "addr:postcode":"41900",
    "addr:street":"Ctra Camas-Santiponce Km. 0005,0",
    "iso:country":"ES",
    "sg:address":"Ctra Camas-santiponce, Km. 0005,0",
    "sg:city":"Camas",
    "sg:orig_category":"Promotores Constructores",
    "sg:phone":"+34 955 98 28 46",
    "sg:postcode":"41900",
    "sg:province":"Sevilla",
    "wof:name":"Rues Automocion S.l.",
    "wof:placetype":"venue"
},
  "geometry": {"coordinates":[-6.0344491005,37.4007263184],"type":"Point"}
}