{
  "type": "Feature",
  "properties": {
    "iso:country":"ES",
    "sg:address":"Palmitos, S/n",
    "sg:city":"Maspalomas",
    "sg:orig_category":"Molduras, Junquillos, Listones Y Molduras Perforadas",
    "sg:phone":"+34 928 14 27 12",
    "sg:postcode":"35100",
    "sg:province":"Las Palmas",
    "wof:name":"Afonso Rodriguez Emilio",
    "wof:placetype":"venue"
},
  "geometry": {"coordinates":[-15.5323486328,28.1479816437],"type":"Point"}
}