{
  "type": "Feature",
  "properties": {
    "addr:full":"Calle de Fronton (del), 2 Fuentemilanos Segovia 40153",
    "addr:housenumber":"2",
    "addr:postcode":"40153",
    "addr:street":"Calle De Fronton Del;Segovia",
    "iso:country":"ES",
    "sg:address":"Calle de Fronton (del), 2",
    "sg:city":"Fuentemilanos",
    "sg:orig_category":"Empresas De Carpinter\u00cda De Madera",
    "sg:phone":"+34 921 48 51 13",
    "sg:postcode":"40153",
    "sg:province":"Segovia",
    "wof:name":"Subtil Sociedad Cooperativa",
    "wof:placetype":"venue"
},
  "geometry": {"coordinates":[-4.2286119461,40.8743896484],"type":"Point"}
}