{
  "type": "Feature",
  "properties": {
    "iso:country":"ES",
    "sg:address":"Calle de Presidente Alvear, 50",
    "sg:city":"Palmas De Gran Canaria",
    "sg:orig_category":"Estancos",
    "sg:phone":"+34 928 27 08 06",
    "sg:postcode":"35007",
    "sg:province":"Las Palmas",
    "wof:name":"Bouzon Crespo Jesus",
    "wof:placetype":"venue"
},
  "geometry": {"coordinates":[-15.4303922653,28.137216568],"type":"Point"}
}