{
  "type": "Feature",
  "properties": {
    "addr:full":"Psaj Moixo, 11 Badalona Barcelona 08918",
    "addr:housenumber":"11",
    "addr:postcode":"08918",
    "addr:street":"Moixo",
    "iso:country":"ES",
    "sg:address":"Psaj Moixo, 11",
    "sg:city":"Badalona",
    "sg:orig_category":"Pintura Y Barniz (al Por Menor)",
    "sg:phone":"+34 933 99 08 00",
    "sg:postcode":"08918",
    "sg:province":"Barcelona",
    "sg:website":"www.pinturaspalacios.com",
    "wof:name":"Palacios Bcn Color S.l.",
    "wof:placetype":"venue"
},
  "geometry": {"coordinates":[2.2314929962,41.4341087341],"type":"Point"}
}