{
  "type": "Feature",
  "properties": {
    "addr:full":"Maria Flores (la Gallega), S/n Sta Cruz Tenerife Santa Cruz De Tenerife 38108",
    "addr:postcode":"38108",
    "addr:street":"Gallega S / N Sta Cruz Tenerife",
    "iso:country":"ES",
    "sg:address":"Maria Flores (la Gallega), S/n",
    "sg:city":"Sta Cruz Tenerife",
    "sg:orig_category":"Peluquer\u00cdas, Peluquer\u00cda Mixta",
    "sg:phone":"+34 922 62 43 27",
    "sg:postcode":"38108",
    "sg:province":"Santa Cruz De Tenerife",
    "wof:name":"Bao Ledesma Juan Jose",
    "wof:placetype":"venue"
},
  "geometry": {"coordinates":[-16.2957706451,28.4491081238],"type":"Point"}
}