{
  "type": "Feature",
  "properties": {
    "addr:full":"Trva Loureiro, 58 Trabanca Sardi\u00e7eira Pontevedra 36618",
    "addr:housenumber":"58",
    "addr:postcode":"36618",
    "addr:street":"Trva Loureiro",
    "iso:country":"ES",
    "sg:address":"Trva Loureiro, 58",
    "sg:city":"Trabanca Sardi\u00e7eira",
    "sg:orig_category":"Productores Recolectores, Venta Directa De Vinos",
    "sg:phone":"+34 986 50 88 96",
    "sg:postcode":"36618",
    "sg:province":"Pontevedra",
    "wof:name":"Coto De Xiabre S.l.",
    "wof:placetype":"venue"
},
  "geometry": {"coordinates":[-8.7647190094,42.5881881714],"type":"Point"}
}