{
  "type": "Feature",
  "properties": {
    "addr:full":"Pl Vila, 3 Santa Coloma De Gramenet Barcelona 08921",
    "addr:housenumber":"3",
    "addr:postcode":"08921",
    "addr:street":"Pl Vila",
    "iso:country":"ES",
    "sg:address":"Pl Vila, 3",
    "sg:city":"Santa Coloma De Gramenet",
    "sg:orig_category":"Farmacias",
    "sg:phone":"+34 933 86 01 55",
    "sg:postcode":"08921",
    "sg:province":"Barcelona",
    "wof:name":"Taillefer De Prado Maria Jesus",
    "wof:placetype":"venue"
},
  "geometry": {"coordinates":[2.2082800865,41.4519996643],"type":"Point"}
}