{
  "type": "Feature",
  "properties": {
    "iso:country":"ES",
    "sg:address":"Avda Cantabria, 43",
    "sg:city":"Reinosa",
    "sg:classifiers":[
        {
            "category":"Personal",
            "subcategory":"Barber",
            "type":"Services"
        }
    ],
    "sg:phone":"+34 942 75 13 19",
    "sg:postcode":"39200",
    "sg:province":"Cantabria",
    "sg:tags":[
        "caballeros",
        "de",
        "peluqueros"
    ],
    "wof:name":"Gonzalez Fernandez Ana Maria",
    "wof:placetype":"venue"
},
  "geometry": {"coordinates":[-4.130710125,43.0060157776],"type":"Point"}
}