{
  "type": "Feature",
  "properties": {
    "iso:country":"ES",
    "sg:address":"Calle de Fierro, 9",
    "sg:city":"Oviedo",
    "sg:orig_category":"Restaurantes",
    "sg:phone":"+34 985 22 71 55",
    "sg:postcode":"33009",
    "sg:province":"Asturias",
    "wof:name":"Martinez Gonzalez Victor Manuel",
    "wof:placetype":"venue"
},
  "geometry": {"coordinates":[-5.8451042175,43.3600387573],"type":"Point"}
}