{
  "type": "Feature",
  "properties": {
    "addr:full":"Calle de San Agustin, S/n Burgos Burgos 09001",
    "addr:housenumber":"/ n",
    "addr:postcode":"09001",
    "addr:street":"Calle De San Agustin S",
    "iso:country":"ES",
    "sg:address":"Calle de San Agustin, S/n",
    "sg:city":"Burgos",
    "sg:orig_category":"Asilos De Ancianos. Centros Privados",
    "sg:phone":"+34 947 27 95 17",
    "sg:postcode":"09001",
    "sg:province":"Burgos",
    "wof:name":"Hijas De La Caridad De San Vicente De Paul",
    "wof:placetype":"venue"
},
  "geometry": {"coordinates":[-3.7006130219,42.3331336975],"type":"Point"}
}