{
  "type": "Feature",
  "properties": {
    "iso:country":"ES",
    "sg:address":"Av Fran\u00c7a (de), 43",
    "sg:city":"S. Julia Ramis",
    "sg:orig_category":"Piscinas, Accesorios, Suministros (fabricaci\u00d3n, Al Por Mayor)",
    "sg:phone":"+34 972 17 01 41",
    "sg:postcode":"17481",
    "sg:province":"Girona",
    "sg:website":"www.laguiadeguias.com",
    "wof:name":"Corominas Ribas Sebastian",
    "wof:placetype":"venue"
},
  "geometry": {"coordinates":[2.8267281055,42.0239982605],"type":"Point"}
}