{
  "type": "Feature",
  "properties": {
    "addr:full":"Calle de Isla, 9 Zafarraya Granada 18128",
    "addr:housenumber":"9",
    "addr:postcode":"18128",
    "addr:street":"Calle De Isla",
    "iso:country":"ES",
    "sg:address":"Calle de Isla, 9",
    "sg:city":"Zafarraya",
    "sg:orig_category":"Asesor\u00cda De Formaci\u00d3n Y Gesti\u00d3n De Personal",
    "sg:phone":"+34 958 36 80 34",
    "sg:postcode":"18128",
    "sg:province":"Granada",
    "wof:name":"Zamora Garcia Jose Luis",
    "wof:placetype":"venue"
},
  "geometry": {"coordinates":[-4.141933918,36.9743881226],"type":"Point"}
}