{
  "type": "Feature",
  "properties": {
    "iso:country":"ES",
    "sg:address":"Carr Enriqueta Paler, 6",
    "sg:city":"Figueres",
    "sg:orig_category":"Maquinaria Para Industrias Diversas",
    "sg:phone":"+34 972 67 46 19",
    "sg:postcode":"17600",
    "sg:province":"Girona",
    "wof:name":"Regiscopi S.c.",
    "wof:placetype":"venue"
},
  "geometry": {"coordinates":[2.9581100941,42.2656898499],"type":"Point"}
}