{
  "type": "Feature",
  "properties": {
    "addr:full":"Ctra Hortsavinya, Km. 0001,6 Calella Barcelona 08370",
    "addr:postcode":"08370",
    "addr:street":"Ctra Hortsavinya Km. 0001,6",
    "iso:country":"ES",
    "sg:address":"Ctra Hortsavinya, Km. 0001,6",
    "sg:city":"Calella",
    "sg:orig_category":"Material Y Suministros Para Horticultura, Arboricultura",
    "sg:phone":"+34 937 66 04 16",
    "sg:postcode":"08370",
    "sg:province":"Barcelona",
    "wof:name":"S Espelt S.l.",
    "wof:placetype":"venue"
},
  "geometry": {"coordinates":[2.6559550762,41.614276886],"type":"Point"}
}