{
  "type": "Feature",
  "properties": {
    "iso:country":"ES",
    "sg:address":"Calle de Prado De Las Banderillas (del), 25",
    "sg:city":"Colmenar Viejo",
    "sg:orig_category":"Serigraf\u00cda (material Y Suministros)",
    "sg:phone":"+34 918 46 31 68",
    "sg:postcode":"28770",
    "sg:province":"Madrid",
    "sg:website":"www.cao-ingtec.com",
    "wof:name":"Cao Ingtec S.l.",
    "wof:placetype":"venue"
},
  "geometry": {"coordinates":[-3.7578730583,40.653049469],"type":"Point"}
}