{
  "type": "Feature",
  "properties": {
    "iso:country":"ES",
    "sg:address":"Calle de Ecce Homo, 5",
    "sg:city":"Onda",
    "sg:orig_category":"Pod\u00d3logos: Pedicuros",
    "sg:phone":"+34 964 60 03 85",
    "sg:postcode":"12200",
    "sg:province":"Castell\u00f3n",
    "wof:name":"Marti Colera Juan Bautista",
    "wof:placetype":"venue"
},
  "geometry": {"coordinates":[-0.2648951113,39.9625053406],"type":"Point"}
}