{
  "type": "Feature",
  "properties": {
    "iso:country":"ES",
    "sg:address":"Calle de Antonio Palau, 1",
    "sg:city":"Ba\u00d1eza",
    "sg:orig_category":"Librer\u00cdas",
    "sg:phone":"+34 987 64 04 83",
    "sg:postcode":"24750",
    "sg:province":"Le\u00f3n",
    "wof:name":"Acedo Martinez Maria Luisa",
    "wof:placetype":"venue"
},
  "geometry": {"coordinates":[-5.9022803307,42.3000335693],"type":"Point"}
}