{
  "type": "Feature",
  "properties": {
    "iso:country":"ES",
    "sg:address":"Calle de Leopoldo Alas Clarin, S/n",
    "sg:city":"Madrid",
    "sg:orig_category":"Estancos",
    "sg:phone":"+34 913 16 94 61",
    "sg:postcode":"28035",
    "sg:province":"Madrid",
    "wof:name":"Bueno Somoza Emilio",
    "wof:placetype":"venue"
},
  "geometry": {"coordinates":[-3.7364010811,40.4802703857],"type":"Point"}
}