{
  "type": "Feature",
  "properties": {
    "iso:country":"ES",
    "sg:address":"Calle de Juan Jose Lorente, 50",
    "sg:city":"Zaragoza",
    "sg:orig_category":"Artesan\u00cda",
    "sg:phone":"+34 976 56 11 38",
    "sg:postcode":"50005",
    "sg:province":"Zaragoza",
    "wof:name":"Serrano Peguero Carlota",
    "wof:placetype":"venue"
},
  "geometry": {"coordinates":[-0.8975089788,41.644695282],"type":"Point"}
}