{
  "type": "Feature",
  "properties": {
    "addr:full":"Rua Montero Rios (de), 52 Santiago De Compostela La Coru\u00f1a 15706",
    "addr:housenumber":"52",
    "addr:postcode":"15706",
    "addr:street":"Rua Montero Rios De;Corun\u0303A",
    "iso:country":"ES",
    "sg:address":"Rua Montero Rios (de), 52",
    "sg:city":"Santiago De Compostela",
    "sg:orig_category":"Promotores Constructores",
    "sg:phone":"+34 981 80 66 34",
    "sg:postcode":"15706",
    "sg:province":"La Coru\u00f1a",
    "wof:name":"Montesiago S.l.",
    "wof:placetype":"venue"
},
  "geometry": {"coordinates":[-8.5497608185,42.8756370544],"type":"Point"}
}