{
  "type": "Feature",
  "properties": {
    "addr:full":"Carrer de Colon, 2 S. Feliu Guixols Girona 17220",
    "addr:housenumber":"2",
    "addr:postcode":"17220",
    "addr:street":"Carrer De Colon;Feliu",
    "iso:country":"ES",
    "sg:address":"Carrer de Colon, 2",
    "sg:city":"S. Feliu Guixols",
    "sg:orig_category":"Pesca Y Caza: Art\u00cdculos (al Por Menor)",
    "sg:phone":"+34 972 32 23 11",
    "sg:postcode":"17220",
    "sg:province":"Girona",
    "wof:name":"Folgado Tena Jose",
    "wof:placetype":"venue"
},
  "geometry": {"coordinates":[3.0378599167,41.7843742371],"type":"Point"}
}