{
  "type": "Feature",
  "properties": {
    "iso:country":"ES",
    "sg:address":"Calle de Madrid, 1",
    "sg:city":"Puertollano",
    "sg:orig_category":"Asesor\u00cda Fiscal Y Jur\u00cddica",
    "sg:phone":"+34 926 41 19 60",
    "sg:postcode":"13500",
    "sg:province":"Ciudad Real",
    "wof:name":"Esymar 2001 S.l.l.",
    "wof:placetype":"venue"
},
  "geometry": {"coordinates":[-4.1063761711,38.6891441345],"type":"Point"}
}