{
  "type": "Feature",
  "properties": {
    "iso:country":"ES",
    "sg:address":"Calle de Arco, 22",
    "sg:city":"S. Clemente",
    "sg:orig_category":"T\u00c9cnicos Veterinarios",
    "sg:phone":"+34 969 30 04 43",
    "sg:postcode":"16600",
    "sg:province":"Cuenca",
    "wof:name":"Garcia Garcia Vicente",
    "wof:placetype":"venue"
},
  "geometry": {"coordinates":[-2.4296765327,39.4044952393],"type":"Point"}
}