{
  "type": "Feature",
  "properties": {
    "iso:country":"ES",
    "sg:address":"Calle de Camino Real, 46",
    "sg:city":"Cartes",
    "sg:orig_category":"Muebles, Minoristas",
    "sg:phone":"+34 942 81 93 64",
    "sg:postcode":"39311",
    "sg:province":"Cantabria",
    "wof:name":"Apezteguia Gonzalez Mercedes",
    "wof:placetype":"venue"
},
  "geometry": {"coordinates":[-4.0685510635,43.327381134],"type":"Point"}
}