{
  "type": "Feature",
  "properties": {
    "iso:country":"ES",
    "sg:address":"Carr Padua, 31",
    "sg:city":"Vilanova I La Geltru",
    "sg:orig_category":"Centros Empresariales",
    "sg:phone":"+34 938 93 66 05",
    "sg:postcode":"08800",
    "sg:province":"Barcelona",
    "wof:name":"Gutierrez Recuero Isabel",
    "wof:placetype":"venue"
},
  "geometry": {"coordinates":[1.7269519567,41.2258911133],"type":"Point"}
}