{
  "type": "Feature",
  "properties": {
    "addr:full":"Praz Campo Da Feira, 4 Estrada Pontevedra 36680",
    "addr:housenumber":"4",
    "addr:postcode":"36680",
    "addr:street":"Praz Campo Da Feira;Estrada Pontevedra",
    "iso:country":"ES",
    "sg:address":"Praz Campo Da Feira, 4",
    "sg:city":"Estrada",
    "sg:orig_category":"Molduras, Junquillos, Listones Y Molduras Perforadas",
    "sg:phone":"+34 986 57 01 40",
    "sg:postcode":"36680",
    "sg:province":"Pontevedra",
    "wof:name":"Bahamonde Valladares Maria Luz",
    "wof:placetype":"venue"
},
  "geometry": {"coordinates":[-8.4293889999,42.6800613403],"type":"Point"}
}