{
  "type": "Feature",
  "properties": {
    "addr:full":"Las Cuevas, 3 Comares M\u00e1laga 29195",
    "addr:housenumber":"3",
    "addr:postcode":"29195",
    "addr:street":"Cuevas",
    "iso:country":"ES",
    "sg:address":"Las Cuevas, 3",
    "sg:city":"Comares",
    "sg:orig_category":"Producci\u00d3n, Venta De Productos De Agricultura Biol\u00d3gica",
    "sg:phone":"+34 952 03 35 21",
    "sg:postcode":"29195",
    "sg:province":"M\u00e1laga",
    "wof:name":"Bonilla Fernandez Vicente",
    "wof:placetype":"venue"
},
  "geometry": {"coordinates":[-4.2473611832,36.8484954834],"type":"Point"}
}