{
  "type": "Feature",
  "properties": {
    "iso:country":"ES",
    "sg:address":"Calle de Marques De La Valdavia (del), 102",
    "sg:city":"Alcobendas",
    "sg:orig_category":"Ropa Para Se\u00d1oras (al Por Menor)",
    "sg:phone":"+34 916 63 83 44",
    "sg:postcode":"28100",
    "sg:province":"Madrid",
    "wof:name":"Martin Diaz Carmen",
    "wof:placetype":"venue"
},
  "geometry": {"coordinates":[-3.6481101513,40.5463676453],"type":"Point"}
}