{
  "type": "Feature",
  "properties": {
    "iso:country":"ES",
    "sg:address":"Pl Mayor, 5",
    "sg:city":"Palleja",
    "sg:orig_category":"Ropa Para Se\u00d1oras Y Caballeros (al Por Menor)",
    "sg:phone":"+34 936 63 11 48",
    "sg:postcode":"08780",
    "sg:province":"Barcelona",
    "wof:name":"Galcez Nevado Joaquin",
    "wof:placetype":"venue"
},
  "geometry": {"coordinates":[1.9965490103,41.4211845398],"type":"Point"}
}