{
  "type": "Feature",
  "properties": {
    "addr:full":"Ctra Brieva A Vicolozano (de), S/n Brieva \u00c1vila 05194",
    "addr:housenumber":"/ n",
    "addr:postcode":"05194",
    "addr:street":"Ctra Brieva A Vicolozano De S;A\u0301Vila",
    "iso:country":"ES",
    "sg:address":"Ctra Brieva A Vicolozano (de), S/n",
    "sg:city":"Brieva",
    "sg:orig_category":"M\u00c9dicos: Medicina Penitenciaria",
    "sg:phone":"+34 920 25 90 22",
    "sg:postcode":"05194",
    "sg:province":"\u00c1vila",
    "wof:name":"Direccion General De Instituciones Penitenciarias",
    "wof:placetype":"venue"
},
  "geometry": {"coordinates":[-4.598359108,40.6895103455],"type":"Point"}
}