{
  "type": "Feature",
  "properties": {
    "addr:full":"Calle de Nuestra Se\u00d1ora De Regla, 9 Pajara Las Palmas 35628",
    "addr:housenumber":"9",
    "addr:postcode":"35628",
    "addr:street":"Calle De Nuestra Sen\u0303Ora De Regla;Las Palmas",
    "iso:country":"ES",
    "sg:address":"Calle de Nuestra Se\u00d1ora De Regla, 9",
    "sg:city":"Pajara",
    "sg:orig_category":"Partidos Pol\u00cdticos",
    "sg:phone":"+34 928 16 16 97",
    "sg:postcode":"35628",
    "sg:province":"Las Palmas",
    "wof:name":"Asamblea Majorera",
    "wof:placetype":"venue"
},
  "geometry": {"coordinates":[-14.1064014435,28.3509807587],"type":"Point"}
}