{
  "type": "Feature",
  "properties": {
    "iso:country":"ES",
    "sg:address":"Canalejas, 27",
    "sg:city":"Negreira",
    "sg:orig_category":"Ropa Para Ni\u00d1os (al Por Menor)",
    "sg:phone":"+34 981 88 52 41",
    "sg:postcode":"15830",
    "sg:province":"La Coru\u00f1a",
    "wof:name":"Alvite Lema Jose",
    "wof:placetype":"venue"
},
  "geometry": {"coordinates":[-8.8252506256,42.9020614624],"type":"Point"}
}