{
  "type": "Feature",
  "properties": {
    "addr:full":"La Solanilla, 6 Menasalbas Toledo 45128",
    "addr:housenumber":"6",
    "addr:postcode":"45128",
    "addr:street":"Solanilla",
    "iso:country":"ES",
    "sg:address":"La Solanilla, 6",
    "sg:city":"Menasalbas",
    "sg:orig_category":"Mataderos Y Talleres De Despiezado",
    "sg:phone":"+34 925 41 32 09",
    "sg:postcode":"45128",
    "sg:province":"Toledo",
    "wof:name":"Ganados Ruigan S.l.",
    "wof:placetype":"venue"
},
  "geometry": {"coordinates":[-4.2860794067,39.6352348328],"type":"Point"}
}