{
  "type": "Feature",
  "properties": {
    "iso:country":"ES",
    "sg:address":"Calle de Ramon Y Cajal, 4",
    "sg:city":"Donostia-san Sebastian",
    "sg:orig_category":"Bebidas",
    "sg:phone":"+34 943 32 68 76",
    "sg:postcode":"20002",
    "sg:province":"Guip\u00f9zcoa",
    "wof:name":"Comercial Pulet S.l.",
    "wof:placetype":"venue"
},
  "geometry": {"coordinates":[-1.9760340452,43.3245239258],"type":"Point"}
}