{
  "type": "Feature",
  "properties": {
    "addr:full":"Calle de Okendo, 5 Donostia-san Sebastian Guip\u00f9zcoa 20004",
    "addr:housenumber":"5",
    "addr:postcode":"20004",
    "addr:street":"Calle De Okendo",
    "iso:country":"ES",
    "sg:address":"Calle de Okendo, 5",
    "sg:city":"Donostia-san Sebastian",
    "sg:orig_category":"Abogados",
    "sg:phone":"+34 943 42 19 73",
    "sg:postcode":"20004",
    "sg:province":"Guip\u00f9zcoa",
    "wof:name":"Garmendia Novo Joaquin",
    "wof:placetype":"venue"
},
  "geometry": {"coordinates":[-1.9803830385,43.3209571838],"type":"Point"}
}