{
  "type": "Feature",
  "properties": {
    "addr:full":"Calle de Madrid, 105 Barrio De La Vega Granada 18193",
    "addr:housenumber":"105",
    "addr:postcode":"18193",
    "addr:street":"Calle De Madrid",
    "iso:country":"ES",
    "sg:address":"Calle de Madrid, 105",
    "sg:city":"Barrio De La Vega",
    "sg:orig_category":"Empresas De Carpinter\u00cda Met\u00c1lica",
    "sg:phone":"+34 958 30 06 92",
    "sg:postcode":"18193",
    "sg:province":"Granada",
    "wof:name":"Aguilar Albea Emilio",
    "wof:placetype":"venue"
},
  "geometry": {"coordinates":[-3.5606360435,37.1331520081],"type":"Point"}
}