{
  "type": "Feature",
  "properties": {
    "addr:full":"Coto (rua Nova), 48 Viveiro Lugo 27850",
    "addr:housenumber":"48",
    "addr:postcode":"27850",
    "addr:street":"Rua Nova",
    "iso:country":"ES",
    "sg:address":"Coto (rua Nova), 48",
    "sg:city":"Viveiro",
    "sg:orig_category":"Empresarios",
    "sg:phone":"+34 982 56 08 19",
    "sg:postcode":"27850",
    "sg:province":"Lugo",
    "wof:name":"Seara Vidal Jose",
    "wof:placetype":"venue"
},
  "geometry": {"coordinates":[-7.5959348679,43.6629714966],"type":"Point"}
}