{
  "type": "Feature",
  "properties": {
    "addr:full":"Calle de Camino Real, 23 Yecla Murcia 30510",
    "addr:housenumber":"23",
    "addr:postcode":"30510",
    "addr:street":"Calle De Camino Real",
    "iso:country":"ES",
    "sg:address":"Calle de Camino Real, 23",
    "sg:city":"Yecla",
    "sg:orig_category":"Laboratorios Y Cl\u00cdnicas Veterinarias",
    "sg:phone":"+34 968 75 17 00",
    "sg:postcode":"30510",
    "sg:province":"Murcia",
    "wof:name":"J.ignacio Erroz Y M.piedad Ferrer C.b.",
    "wof:placetype":"venue"
},
  "geometry": {"coordinates":[-1.1124857664,38.6148681641],"type":"Point"}
}