{
  "type": "Feature",
  "properties": {
    "iso:country":"ES",
    "sg:address":"Calle de General Benavides, 11",
    "sg:city":"Ba\u00d1eza",
    "sg:orig_category":"Transportes Internacionales",
    "sg:phone":"+34 987 64 17 85",
    "sg:postcode":"24750",
    "sg:province":"Le\u00f3n",
    "wof:name":"Transportes Badetrans S.a.",
    "wof:placetype":"venue"
},
  "geometry": {"coordinates":[-5.9242091179,42.3069114685],"type":"Point"}
}