{
  "type": "Feature",
  "properties": {
    "iso:country":"ES",
    "sg:address":"Avda Andalucia, 56",
    "sg:city":"Jaen",
    "sg:orig_category":"Electricidad: Instaladores",
    "sg:phone":"+34 953 22 65 72",
    "sg:postcode":"23006",
    "sg:province":"Ja\u00e9n",
    "wof:name":"Mata Jimenez Antonio",
    "wof:placetype":"venue"
},
  "geometry": {"coordinates":[-3.8005950451,37.7781639099],"type":"Point"}
}