{
  "type": "Feature",
  "properties": {
    "addr:full":"Pg Ferrocarril, 48 Castelldefels Barcelona 08860",
    "addr:housenumber":"48",
    "addr:postcode":"08860",
    "addr:street":"Pg Ferrocarril",
    "iso:country":"ES",
    "sg:address":"Pg Ferrocarril, 48",
    "sg:city":"Castelldefels",
    "sg:orig_category":"Reposter\u00cdas",
    "sg:phone":"+34 936 65 44 37",
    "sg:postcode":"08860",
    "sg:province":"Barcelona",
    "wof:name":"Forn De La Platja",
    "wof:placetype":"venue"
},
  "geometry": {"coordinates":[1.9571700096,41.2668800354],"type":"Point"}
}