{
  "type": "Feature",
  "properties": {
    "addr:full":"Calle de Portugal, 70 Palmas De Gran Canaria Las Palmas 35010",
    "addr:housenumber":"70",
    "addr:postcode":"35010",
    "addr:street":"Calle De Portugal",
    "iso:country":"ES",
    "sg:address":"Calle de Portugal, 70",
    "sg:city":"Palmas De Gran Canaria",
    "sg:orig_category":"Supermercados Y Hipermercados",
    "sg:phone":"+34 928 26 67 63",
    "sg:postcode":"35010",
    "sg:province":"Las Palmas",
    "wof:name":"Dinosol Supermercados S.l.",
    "wof:placetype":"venue"
},
  "geometry": {"coordinates":[-15.4389743805,28.1356105804],"type":"Point"}
}