{
  "type": "Feature",
  "properties": {
    "iso:country":"ES",
    "sg:address":"Calle de Magallanes, 2",
    "sg:city":"Zamora",
    "sg:orig_category":"Mutuas De Seguros",
    "sg:phone":"+34 980 52 50 44",
    "sg:postcode":"49020",
    "sg:province":"Zamora",
    "wof:name":"Fraternidad-muprexpa Mutua De Accidentes De Trabajo Y Enfermedades Profesionales",
    "wof:placetype":"venue"
},
  "geometry": {"coordinates":[-5.7358908653,41.5064544678],"type":"Point"}
}