{
  "type": "Feature",
  "properties": {
    "iso:country":"ES",
    "sg:address":"Avda Alfonso X El Sabio, 3",
    "sg:city":"Ciudad Real",
    "sg:orig_category":"Florister\u00cdas",
    "sg:phone":"+34 926 21 24 98",
    "sg:postcode":"13001",
    "sg:province":"Ciudad Real",
    "wof:name":"Sanchez-herrera Ramirez Alfonsa",
    "wof:placetype":"venue"
},
  "geometry": {"coordinates":[-3.9291229248,38.9842567444],"type":"Point"}
}