{
  "type": "Feature",
  "properties": {
    "iso:country":"ES",
    "sg:address":"Avda Aguirre Lehendakari, 141",
    "sg:city":"Bilbao",
    "sg:orig_category":"Mercer\u00cda, Lencer\u00cda (al Por Menor)",
    "sg:phone":"+34 944 76 22 43",
    "sg:postcode":"48015",
    "sg:province":"Vizcaya",
    "wof:name":"Barona Castro Luis",
    "wof:placetype":"venue"
},
  "geometry": {"coordinates":[-2.9603600502,43.2767448425],"type":"Point"}
}