{
  "type": "Feature",
  "properties": {
    "iso:country":"ES",
    "sg:address":"Carrer de Alber, 5",
    "sg:city":"Cornella Llobregat",
    "sg:orig_category":"Panader\u00cdas, Panader\u00cdas",
    "sg:phone":"+34 933 75 12 87",
    "sg:postcode":"08940",
    "sg:province":"Barcelona",
    "wof:name":"Gonzalez Pacheco Carlos",
    "wof:placetype":"venue"
},
  "geometry": {"coordinates":[2.0820960999,41.3650932312],"type":"Point"}
}