{
  "type": "Feature",
  "properties": {
    "iso:country":"ES",
    "sg:address":"Calle de Ecuador, 5",
    "sg:city":"Alcorcon",
    "sg:orig_category":"Empresas De Limpieza",
    "sg:phone":"+34 916 19 02 00",
    "sg:postcode":"28922",
    "sg:province":"Madrid",
    "sg:website":"www.sherlimp.com",
    "wof:name":"Limpieza De Alfombras Sherlimp Soc.coop.",
    "wof:placetype":"venue"
},
  "geometry": {"coordinates":[-3.824996233,40.3585548401],"type":"Point"}
}