{
  "type": "Feature",
  "properties": {
    "addr:full":"Calle de Santiago, 16 Valladolid Valladolid 47001",
    "addr:housenumber":"16",
    "addr:postcode":"47001",
    "addr:street":"Calle De Santiago",
    "iso:country":"ES",
    "sg:address":"Calle de Santiago, 16",
    "sg:city":"Valladolid",
    "sg:orig_category":"Radiocomunicaciones, Telefon\u00cda M\u00d3vil, Radiomensajer\u00cda: Servicios, Comercializaci\u00d3n",
    "sg:phone":"+34 983 37 41 84",
    "sg:postcode":"47001",
    "sg:province":"Valladolid",
    "sg:website":"www.phonehouse.es",
    "wof:name":"Phone Warehouse S.a.",
    "wof:placetype":"venue"
},
  "geometry": {"coordinates":[-4.7290058136,41.6500015259],"type":"Point"}
}