{
  "type": "Feature",
  "properties": {
    "addr:full":"Carr Carbo, De, 2 Campos Islas Baleares 07630",
    "addr:postcode":"07630",
    "addr:street":"Carr Carbo De",
    "iso:country":"ES",
    "sg:address":"Carr Carbo, De, 2",
    "sg:city":"Campos",
    "sg:orig_category":"Carnicer\u00cdas, Carnicer\u00cdas",
    "sg:phone":"+34 971 65 14 42",
    "sg:postcode":"07630",
    "sg:province":"Islas Baleares",
    "wof:name":"Vidal Maimo Margalida Barbara",
    "wof:placetype":"venue"
},
  "geometry": {"coordinates":[3.0197050571,39.430480957],"type":"Point"}
}