{
  "type": "Feature",
  "properties": {
    "addr:full":"Avda Julian Sanchez, S/n Fuente El Saz De Jarama Madrid 28140",
    "addr:postcode":"28140",
    "addr:street":"Avda Julian Sanchez S / N",
    "iso:country":"ES",
    "sg:address":"Avda Julian Sanchez, S/n",
    "sg:city":"Fuente El Saz De Jarama",
    "sg:orig_category":"Polideportivos",
    "sg:phone":"+34 916 20 08 20",
    "sg:postcode":"28140",
    "sg:province":"Madrid",
    "wof:name":"Ayuntamiento De Fuente El Saz Del Jarama",
    "wof:placetype":"venue"
},
  "geometry": {"coordinates":[-3.5164630413,40.6293067932],"type":"Point"}
}