{
  "type": "Feature",
  "properties": {
    "addr:full":"Rua San Pedro De Mezonzo (de), 19 Santiago De Compostela La Coru\u00f1a 15701",
    "addr:housenumber":"19",
    "addr:postcode":"15701",
    "addr:street":"Rua San Pedro De Mezonzo De;Corun\u0303A",
    "iso:country":"ES",
    "sg:address":"Rua San Pedro De Mezonzo (de), 19",
    "sg:city":"Santiago De Compostela",
    "sg:orig_category":"Inform\u00c1tica, Ofim\u00c1tica (estudios, Asesor\u00cda, Ingenier\u00cda, Formaci\u00d3n)",
    "sg:phone":"+34 981 59 95 58",
    "sg:postcode":"15701",
    "sg:province":"La Coru\u00f1a",
    "wof:name":"Jump Ordenadores S.l.",
    "wof:placetype":"venue"
},
  "geometry": {"coordinates":[-8.5482139587,42.872959137],"type":"Point"}
}