{
  "type": "Feature",
  "properties": {
    "addr:full":"Calle de Mar (del), 8 Torre Mar M\u00e1laga 29740",
    "addr:postcode":"29740",
    "addr:street":"Calle De;Del;Torre;Ma\u0301Laga",
    "iso:country":"ES",
    "sg:address":"Calle de Mar (del), 8",
    "sg:city":"Torre Mar",
    "sg:orig_category":"\u00d3ptica: Instrumentos (fabricaci\u00d3n)",
    "sg:phone":"+34 952 54 71 04",
    "sg:postcode":"29740",
    "sg:province":"M\u00e1laga",
    "wof:name":"Rojo Diaz Fernando",
    "wof:placetype":"venue"
},
  "geometry": {"coordinates":[-4.3591871262,36.7206001282],"type":"Point"}
}