{
  "type": "Feature",
  "properties": {
    "addr:full":"Rua Manuel Lustres Rivas, 21 Santa Uxia De Ribeira La Coru\u00f1a 15960",
    "addr:housenumber":"21",
    "addr:postcode":"15960",
    "addr:street":"Rua Manuel Lustres Rivas;Corun\u0303A",
    "iso:country":"ES",
    "sg:address":"Rua Manuel Lustres Rivas, 21",
    "sg:city":"Santa Uxia De Ribeira",
    "sg:orig_category":"Sociedades, Compa\u00d1\u00cdas Aseguradoras",
    "sg:phone":"+34 981 87 52 65",
    "sg:postcode":"15960",
    "sg:province":"La Coru\u00f1a",
    "wof:name":"Lampon Agrelo Cipriano",
    "wof:placetype":"venue"
},
  "geometry": {"coordinates":[-8.9914093018,42.5556297302],"type":"Point"}
}