{
  "type": "Feature",
  "properties": {
    "iso:country":"ES",
    "sg:address":"Avda Gran Via, 57",
    "sg:city":"Vigo",
    "sg:orig_category":"Doctores En Medicina",
    "sg:phone":"+34 986 41 06 15",
    "sg:postcode":"36204",
    "sg:province":"Pontevedra",
    "wof:name":"Anibarro Cases Juan Luis",
    "wof:placetype":"venue"
},
  "geometry": {"coordinates":[-8.7187681198,42.2302894592],"type":"Point"}
}