{
  "type": "Feature",
  "properties": {
    "iso:country":"ES",
    "sg:address":"Calle de Escalerinas, S/n",
    "sg:city":"Masueco",
    "sg:orig_category":"Electricidad: Instaladores",
    "sg:phone":"+34 923 50 52 42",
    "sg:postcode":"37251",
    "sg:province":"Salamanca",
    "wof:name":"Vicente Blanco Jose",
    "wof:placetype":"venue"
},
  "geometry": {"coordinates":[-6.5897340775,41.2032546997],"type":"Point"}
}