{
  "type": "Feature",
  "properties": {
    "addr:full":"Vallehermoso, 91 Madrid Madrid 28003",
    "addr:housenumber":"91",
    "addr:postcode":"madrid;28003",
    "addr:street":"Vallehermoso",
    "iso:country":"ES",
    "sg:address":"Vallehermoso, 91",
    "sg:city":"Madrid",
    "sg:orig_category":"Muebles, Minoristas",
    "sg:phone":"+34 915 33 96 08",
    "sg:postcode":"28003",
    "sg:province":"Madrid",
    "wof:name":"Chara Arocas Ricardo",
    "wof:placetype":"venue"
},
  "geometry": {"coordinates":[-3.7083649635,40.4398231506],"type":"Point"}
}