{
  "type": "Feature",
  "properties": {
    "iso:country":"ES",
    "sg:address":"Calle de Federico Garcia Lorca, 1",
    "sg:city":"Arnedo",
    "sg:orig_category":"Carnicer\u00cdas, Carnicer\u00cdas",
    "sg:phone":"+34 941 38 42 17",
    "sg:postcode":"26580",
    "sg:province":"La Rioja",
    "wof:name":"Jimenez Gallardo Dionisio",
    "wof:placetype":"venue"
},
  "geometry": {"coordinates":[-2.1044890881,42.2243003845],"type":"Point"}
}