{
  "type": "Feature",
  "properties": {
    "addr:full":"Calle de Bordel, S/n Padron A Coru\u00f1a 15900",
    "addr:housenumber":"s",
    "addr:postcode":"15900",
    "addr:street":"Calle De Bordel;/ N Padron A Corun\u0303A",
    "iso:country":"ES",
    "sg:address":"Calle de Bordel, S/n",
    "sg:city":"Padron",
    "sg:orig_category":"C\u00c1maras De Comercio E Industria, Oficios, Agricultura",
    "sg:phone":"+34 981 81 04 04",
    "sg:postcode":"15900",
    "sg:province":"A Coru\u00f1a",
    "wof:name":"Xunta De Galicia",
    "wof:placetype":"venue"
},
  "geometry": {"coordinates":[-8.6602649689,42.7406082153],"type":"Point"}
}