{
  "type": "Feature",
  "properties": {
    "addr:full":"Avda Alfonso El Sabio, 34 Alacant Alicante 03004",
    "addr:housenumber":"34",
    "addr:postcode":"03004",
    "addr:street":"Avda Alfonso El Sabio",
    "iso:country":"ES",
    "sg:address":"Avda Alfonso El Sabio, 34",
    "sg:city":"Alacant",
    "sg:orig_category":"Abogados",
    "sg:phone":"+34 965 21 25 80",
    "sg:postcode":"03004",
    "sg:province":"Alicante",
    "wof:name":"Perez Bartolome Joaquin",
    "wof:placetype":"venue"
},
  "geometry": {"coordinates":[-0.4884929955,38.3469581604],"type":"Point"}
}