{
  "type": "Feature",
  "properties": {
    "addr:full":"Pla\u00c7 Missions, 5 Lleida Lleida 25003",
    "addr:housenumber":"5",
    "addr:postcode":"25003",
    "addr:street":"Missions",
    "iso:country":"ES",
    "sg:address":"Pla\u00c7 Missions, 5",
    "sg:city":"Lleida",
    "sg:orig_category":"Asesor\u00cda Sobre Comunicaci\u00d3n De Empresas",
    "sg:phone":"+34 973 28 13 11",
    "sg:postcode":"25003",
    "sg:province":"Lleida",
    "wof:name":"Aymerich & Associats S.c.c.l.",
    "wof:placetype":"venue"
},
  "geometry": {"coordinates":[0.6170459986,41.6164207458],"type":"Point"}
}