{
  "type": "Feature",
  "properties": {
    "iso:country":"ES",
    "sg:address":"Calle de Eras, 16",
    "sg:city":"Calahorra",
    "sg:orig_category":"Reposter\u00cdas",
    "sg:phone":"+34 941 13 07 36",
    "sg:postcode":"26500",
    "sg:province":"La Rioja",
    "wof:name":"Llorente Perez Antonio",
    "wof:placetype":"venue"
},
  "geometry": {"coordinates":[-1.9583603144,42.3039016724],"type":"Point"}
}