{
  "type": "Feature",
  "properties": {
    "addr:full":"Calle de Eucalipto (del), 4 Parque Coimbra Madrid 28935",
    "addr:postcode":"28935",
    "addr:street":"Calle De Eucalipto Del;Parque",
    "iso:country":"ES",
    "sg:address":"Calle de Eucalipto (del), 4",
    "sg:city":"Parque Coimbra",
    "sg:orig_category":"Empresarios",
    "sg:phone":"+34 916 47 82 32",
    "sg:postcode":"28935",
    "sg:province":"Madrid",
    "wof:name":"Proyectos Y Reformas J2m 2002 S.l.",
    "wof:placetype":"venue"
},
  "geometry": {"coordinates":[-3.9251389503,40.3101272583],"type":"Point"}
}