{
  "type": "Feature",
  "properties": {
    "addr:full":"Gta Fueros De Aragon (de Los), 1 Borja Zaragoza 50540",
    "addr:housenumber":"1",
    "addr:postcode":"50540",
    "addr:street":"Gta Fueros De Aragon De Los",
    "iso:country":"ES",
    "sg:address":"Gta Fueros De Aragon (de Los), 1",
    "sg:city":"Borja",
    "sg:orig_category":"Pizzer\u00cdas",
    "sg:phone":"+34 976 85 27 18",
    "sg:postcode":"50540",
    "sg:province":"Zaragoza",
    "wof:name":"Gonzalbo Urchaga S.l.",
    "wof:placetype":"venue"
},
  "geometry": {"coordinates":[-1.5315898657,41.833316803],"type":"Point"}
}