{
  "type": "Feature",
  "properties": {
    "iso:country":"ES",
    "sg:address":"Calle de Cercas, 12",
    "sg:city":"Belorado",
    "sg:orig_category":"Colchones (fabricaci\u00d3n, Al Por Mayor, Al Por Menor)",
    "sg:phone":"+34 947 58 00 77",
    "sg:postcode":"09250",
    "sg:province":"Burgos",
    "wof:name":"Perez Gonzalo Alejandro",
    "wof:placetype":"venue"
},
  "geometry": {"coordinates":[-3.191618681,42.4201049805],"type":"Point"}
}