{
  "type": "Feature",
  "properties": {
    "addr:full":"Calle de Jabata, 11 Villanueva Serena Badajoz 06700",
    "addr:housenumber":"11",
    "addr:postcode":"06700",
    "addr:street":"Calle De Jabata",
    "iso:country":"ES",
    "sg:address":"Calle de Jabata, 11",
    "sg:city":"Villanueva Serena",
    "sg:orig_category":"Farmacias",
    "sg:phone":"+34 924 84 41 12",
    "sg:postcode":"06700",
    "sg:province":"Badajoz",
    "wof:name":"Gomez Paco Julian",
    "wof:placetype":"venue"
},
  "geometry": {"coordinates":[-5.7976970673,38.9817695618],"type":"Point"}
}