{
  "type": "Feature",
  "properties": {
    "iso:country":"ES",
    "sg:address":"Calle de Benjamin Palencia, 11",
    "sg:city":"Barrax",
    "sg:orig_category":"Cajas Para Embalar",
    "sg:phone":"+34 967 36 51 03",
    "sg:postcode":"02639",
    "sg:province":"Albacete",
    "wof:name":"Caja Rural De Albacete",
    "wof:placetype":"venue"
},
  "geometry": {"coordinates":[-2.1984987259,39.0440139771],"type":"Point"}
}