{
  "type": "Feature",
  "properties": {
    "addr:full":"Calle de Doctor Castilla Del Pino, 7 Ronda M\u00e1laga 29400",
    "addr:housenumber":"7",
    "addr:postcode":"29400",
    "addr:street":"Calle De Doctor Castilla Del Pino;Ronda Ma\u0301Laga",
    "iso:country":"ES",
    "sg:address":"Calle de Doctor Castilla Del Pino, 7",
    "sg:city":"Ronda",
    "sg:orig_category":"Contables",
    "sg:phone":"+34 952 87 27 92",
    "sg:postcode":"29400",
    "sg:province":"M\u00e1laga",
    "wof:name":"Contabilidades Del Sur S.l",
    "wof:placetype":"venue"
},
  "geometry": {"coordinates":[-5.1523838043,36.7535133362],"type":"Point"}
}