{
  "type": "Feature",
  "properties": {
    "iso:country":"ES",
    "sg:address":"Plaz Trinidad (de La), S/n",
    "sg:city":"Cordoba",
    "sg:orig_category":"Comunidades Religiosas",
    "sg:phone":"+34 957 29 47 57",
    "sg:postcode":"14003",
    "sg:province":"C\u00f3rdoba",
    "wof:name":"Obra Pia Stma Trinidad",
    "wof:placetype":"venue"
},
  "geometry": {"coordinates":[-4.7831487656,37.882610321],"type":"Point"}
}