{
  "type": "Feature",
  "properties": {
    "addr:full":"Calle de Doctor Calatayud, S/n Moraira Alicante 03724",
    "addr:housenumber":"s / n",
    "addr:postcode":"03724",
    "addr:street":"Calle De Doctor Calatayud",
    "iso:country":"ES",
    "sg:address":"Calle de Doctor Calatayud, S/n",
    "sg:city":"Moraira",
    "sg:orig_category":"Distribuci\u00d3n De Petr\u00d3leo Y Derivados",
    "sg:phone":"+34 965 74 40 38",
    "sg:postcode":"03724",
    "sg:province":"Alicante",
    "wof:name":"Estaciones De Servicio Campol S.l.",
    "wof:placetype":"venue"
},
  "geometry": {"coordinates":[0.1347935945,38.6879386902],"type":"Point"}
}