{
  "type": "Feature",
  "properties": {
    "addr:full":"Calle de Ombu, 3 Madrid Madrid 28045",
    "addr:housenumber":"3",
    "addr:postcode":"28045",
    "addr:street":"Calle De Ombu",
    "iso:country":"ES",
    "sg:address":"Calle de Ombu, 3",
    "sg:city":"Madrid",
    "sg:orig_category":"Financiaci\u00d3n Y Cr\u00c9ditos",
    "sg:phone":"+34 915 28 65 07",
    "sg:postcode":"28045",
    "sg:province":"Madrid",
    "sg:website":"www.experian.es",
    "wof:name":"Experian Marketing Services S.l.",
    "wof:placetype":"venue"
},
  "geometry": {"coordinates":[-3.676484108,40.3945045471],"type":"Point"}
}