{
  "type": "Feature",
  "properties": {
    "addr:full":"Calle de Massamagrell, 25 Rafelbunyol Valencia 46138",
    "addr:housenumber":"25",
    "addr:postcode":"46138",
    "addr:street":"Calle De Massamagrell",
    "iso:country":"ES",
    "sg:address":"Calle de Massamagrell, 25",
    "sg:city":"Rafelbunyol",
    "sg:orig_category":"Artes Gr\u00c1ficas, Artes Pl\u00c1sticas (curso)",
    "sg:phone":"+34 961 41 34 21",
    "sg:postcode":"46138",
    "sg:province":"Valencia",
    "wof:name":"Troquelados Y Salma S.r.l.",
    "wof:placetype":"venue"
},
  "geometry": {"coordinates":[-0.3252640069,39.58826828],"type":"Point"}
}