{
  "type": "Feature",
  "properties": {
    "iso:country":"ES",
    "sg:address":"Carrer de Lope De Vega, 81",
    "sg:city":"Barcelona",
    "sg:orig_category":"Animales (al Por Menor)",
    "sg:phone":"+34 933 09 04 13",
    "sg:postcode":"08005",
    "sg:province":"Barcelona",
    "wof:name":"Clemente Llovera Andreu",
    "wof:placetype":"venue"
},
  "geometry": {"coordinates":[2.2039721012,41.4040756226],"type":"Point"}
}