{
  "type": "Feature",
  "properties": {
    "addr:full":"Carrer de Pla De Fornells, 27 Barcelona Barcelona 08042",
    "addr:housenumber":"27",
    "addr:postcode":"08042",
    "addr:street":"Carrer De Pla De Fornells",
    "iso:country":"ES",
    "sg:address":"Carrer de Pla De Fornells, 27",
    "sg:city":"Barcelona",
    "sg:orig_category":"Quincaller\u00cda (al Por Menor)",
    "sg:phone":"+34 933 59 84 12",
    "sg:postcode":"08042",
    "sg:province":"Barcelona",
    "wof:name":"Julia Llurba Francesc",
    "wof:placetype":"venue"
},
  "geometry": {"coordinates":[2.1760818958,41.4470901489],"type":"Point"}
}