{
  "type": "Feature",
  "properties": {
    "iso:country":"ES",
    "sg:address":"Calle de Cardenal Spinola, 33",
    "sg:city":"Sevilla",
    "sg:orig_category":"Abogados",
    "sg:phone":"+34 954 38 26 08",
    "sg:postcode":"41002",
    "sg:province":"Sevilla",
    "wof:name":"Castillo Y Mantilla De Los Rios Jose Manuel Del",
    "wof:placetype":"venue"
},
  "geometry": {"coordinates":[-5.9968652725,37.3969078064],"type":"Point"}
}