{
  "type": "Feature",
  "properties": {
    "addr:full":"Carrer de Gorgon\u00c7ana, 16 Esparreguera Barcelona 08292",
    "addr:housenumber":"16",
    "addr:postcode":"08292",
    "addr:street":"Carrer De Gorgonc\u0327Ana",
    "iso:country":"ES",
    "sg:address":"Carrer de Gorgon\u00c7ana, 16",
    "sg:city":"Esparreguera",
    "sg:orig_category":"Iglesias Cristianas Diversas",
    "sg:phone":"+34 937 77 32 05",
    "sg:postcode":"08292",
    "sg:province":"Barcelona",
    "wof:name":"Testigos Cristianos De Jehova",
    "wof:placetype":"venue"
},
  "geometry": {"coordinates":[1.8732149601,41.537399292],"type":"Point"}
}