{
  "type": "Feature",
  "properties": {
    "iso:country":"ES",
    "sg:address":"Calle de Piscis, 85",
    "sg:city":"Zaragoza",
    "sg:orig_category":"Art\u00cdculos De Madera (fabricaci\u00d3n Y Al Por Mayor)",
    "sg:phone":"+34 976 75 33 34",
    "sg:postcode":"50012",
    "sg:province":"Zaragoza",
    "wof:name":"Talleres Martin Esteban S.l.",
    "wof:placetype":"venue"
},
  "geometry": {"coordinates":[-0.9354090095,41.6375694275],"type":"Point"}
}