{
  "type": "Feature",
  "properties": {
    "iso:country":"ES",
    "sg:address":"Calle de Liebre, 44",
    "sg:city":"Valdezorras",
    "sg:orig_category":"Supermercados Y Hipermercados",
    "sg:phone":"+34 954 25 95 63",
    "sg:postcode":"41020",
    "sg:province":"Sevilla",
    "wof:name":"La Tienda Nueva Garcia Hermanos S.l.",
    "wof:placetype":"venue"
},
  "geometry": {"coordinates":[-5.9249591827,37.4294395447],"type":"Point"}
}