{
  "type": "Feature",
  "properties": {
    "iso:country":"ES",
    "sg:address":"Calle de Nueva, 1",
    "sg:city":"Bilbao",
    "sg:orig_category":"Peluquer\u00cdas, Peluquer\u00cda Mixta",
    "sg:phone":"+34 944 16 97 67",
    "sg:postcode":"48005",
    "sg:province":"Vizcaya",
    "wof:name":"Moral Sainz Maria De Los Angeles",
    "wof:placetype":"venue"
},
  "geometry": {"coordinates":[-2.9230620861,43.2592887878],"type":"Point"}
}