{
  "type": "Feature",
  "properties": {
    "iso:country":"ES",
    "sg:address":"Paseo Principe De Asturias, S/n",
    "sg:city":"Cox",
    "sg:orig_category":"Distribuci\u00d3n De Petr\u00d3leo Y Derivados",
    "sg:phone":"+34 965 36 10 62",
    "sg:postcode":"03350",
    "sg:province":"Alicante",
    "wof:name":"Carburantes Cox S.l.",
    "wof:placetype":"venue"
},
  "geometry": {"coordinates":[-0.8963639736,38.1433448792],"type":"Point"}
}