{
  "type": "Feature",
  "properties": {
    "iso:country":"ES",
    "sg:address":"Calle de Mayor, 65",
    "sg:city":"Burgo Ebro",
    "sg:orig_category":"Reposter\u00cdas",
    "sg:phone":"+34 976 10 50 81",
    "sg:postcode":"50730",
    "sg:province":"Zaragoza",
    "wof:name":"Gallego Mur Jose Maria",
    "wof:placetype":"venue"
},
  "geometry": {"coordinates":[-0.7447599769,41.5740432739],"type":"Point"}
}