{
  "type": "Feature",
  "properties": {
    "iso:country":"ES",
    "sg:address":"Carr Cami De Dos Molins, 6",
    "sg:city":"Xativa",
    "sg:orig_category":"Agentes, Concesionarios Y Sucursales De Veh\u00cdculos",
    "sg:phone":"+34 962 27 01 61",
    "sg:postcode":"46800",
    "sg:province":"Valencia",
    "wof:name":"Auto-haus Sanchez S.l.",
    "wof:placetype":"venue"
},
  "geometry": {"coordinates":[-0.5275039077,38.9894752502],"type":"Point"}
}