{
  "type": "Feature",
  "properties": {
    "iso:country":"ES",
    "sg:address":"Avda Jose De Mora, 11",
    "sg:city":"Baza",
    "sg:orig_category":"Trajes Y Adornos De Boda (confecci\u00d3n, Al Por Menor)",
    "sg:phone":"+34 958 70 37 69",
    "sg:postcode":"18800",
    "sg:province":"Granada",
    "wof:name":"Corral Miron Encarnacion",
    "wof:placetype":"venue"
},
  "geometry": {"coordinates":[-2.7718269825,37.4878349304],"type":"Point"}
}