{
  "type": "Feature",
  "properties": {
    "addr:full":"La Chica, 6 Ventas Huelma Granada 18131",
    "addr:housenumber":"6",
    "addr:postcode":"18131",
    "addr:street":"Chica",
    "iso:country":"ES",
    "sg:address":"La Chica, 6",
    "sg:city":"Ventas Huelma",
    "sg:orig_category":"Pescader\u00cdas (al Por Menor)",
    "sg:phone":"+34 958 58 33 56",
    "sg:postcode":"18131",
    "sg:province":"Granada",
    "wof:name":"Hidalgo Quintana Manuel",
    "wof:placetype":"venue"
},
  "geometry": {"coordinates":[-3.8177690506,37.0688400269],"type":"Point"}
}