{
  "type": "Feature",
  "properties": {
    "addr:full":"Ctra M-111 (paracuellos-belvis), Km. 0000,0 El Cruce Madrid 28860",
    "addr:postcode":"28860",
    "addr:street":"Ctra M-111 Paracuellos-Belvis Km. 0000,0",
    "iso:country":"ES",
    "sg:address":"Ctra M-111 (paracuellos-belvis), Km. 0000,0",
    "sg:city":"El Cruce",
    "sg:orig_category":"Caf\u00c9s (al Por Menor)",
    "sg:phone":"+34 916 58 01 87",
    "sg:postcode":"28860",
    "sg:province":"Madrid",
    "wof:name":"Cafes El Paname\u00f1o S.a.",
    "wof:placetype":"venue"
},
  "geometry": {"coordinates":[-3.5296940804,40.5049209595],"type":"Point"}
}