{
  "type": "Feature",
  "properties": {
    "addr:full":"Calle de En Bou, 2 Valencia Valencia 46001",
    "addr:housenumber":"2",
    "addr:postcode":"46001",
    "addr:street":"Calle De En Bou",
    "iso:country":"ES",
    "sg:address":"Calle de En Bou, 2",
    "sg:city":"Valencia",
    "sg:orig_category":"Albergues",
    "sg:phone":"+34 963 91 57 73",
    "sg:postcode":"46001",
    "sg:province":"Valencia",
    "wof:name":"Antigua Morellana S.l.",
    "wof:placetype":"venue"
},
  "geometry": {"coordinates":[-0.377292186,39.4746437073],"type":"Point"}
}