{
  "type": "Feature",
  "properties": {
    "iso:country":"ES",
    "sg:address":"Carrer de Felip Pedrell, 14",
    "sg:city":"Alcanar",
    "sg:orig_category":"Perfumer\u00cda (al Por Menor)",
    "sg:phone":"+34 977 73 03 57",
    "sg:postcode":"43530",
    "sg:province":"Tarragona",
    "wof:name":"Forcadell Sancho Jose",
    "wof:placetype":"venue"
},
  "geometry": {"coordinates":[0.480881989,40.5437316895],"type":"Point"}
}