{
  "type": "Feature",
  "properties": {
    "iso:country":"ES",
    "sg:address":"Avda Carlos Iii (de), 30",
    "sg:city":"Cordoba",
    "sg:orig_category":"Estancos",
    "sg:phone":"+34 957 43 43 81",
    "sg:postcode":"14014",
    "sg:province":"C\u00f3rdoba",
    "wof:name":"Garcia Arevalo Juan",
    "wof:placetype":"venue"
},
  "geometry": {"coordinates":[-4.7509069443,37.895526886],"type":"Point"}
}