{
  "type": "Feature",
  "properties": {
    "iso:country":"ES",
    "sg:address":"Calle de Clara Campoamor, 13",
    "sg:city":"Zaragoza",
    "sg:orig_category":"Servicio De Salud",
    "sg:phone":"+34 976 73 47 31",
    "sg:postcode":"50015",
    "sg:province":"Zaragoza",
    "wof:name":"Lacruz Marco Raquel",
    "wof:placetype":"venue"
},
  "geometry": {"coordinates":[-0.892331183,41.6676063538],"type":"Point"}
}