{
  "type": "Feature",
  "properties": {
    "addr:full":"Av Rapita (de La), 38 Amposta Tarragona 43870",
    "addr:housenumber":"38",
    "addr:postcode":"43870",
    "addr:street":"Av Rapita De La",
    "iso:country":"ES",
    "sg:address":"Av Rapita (de La), 38",
    "sg:city":"Amposta",
    "sg:orig_category":"Bisuter\u00cda, Joyer\u00cda, Relojer\u00cda (al Por Menor)",
    "sg:phone":"+34 977 70 57 52",
    "sg:postcode":"43870",
    "sg:province":"Tarragona",
    "wof:name":"Bernado Gisbert Jose",
    "wof:placetype":"venue"
},
  "geometry": {"coordinates":[0.5798900127,40.7106819153],"type":"Point"}
}