{
  "type": "Feature",
  "properties": {
    "addr:full":"Plaz Constitucion (de La), 1 Colmenarejo Madrid 28270",
    "addr:housenumber":"1",
    "addr:postcode":"28270",
    "iso:country":"ES",
    "sg:address":"Plaz Constitucion (de La), 1",
    "sg:city":"Colmenarejo",
    "sg:orig_category":"Administraciones Regionales, Departamentales Y Locales",
    "sg:phone":"+34 918 58 90 72",
    "sg:postcode":"28270",
    "sg:province":"Madrid",
    "wof:name":"Ayuntamiento De Colmenarejo",
    "wof:placetype":"venue"
},
  "geometry": {"coordinates":[-4.0167322159,40.5609893799],"type":"Point"}
}