{
  "type": "Feature",
  "properties": {
    "addr:full":"Agaraitz Auzoa, S/n Villabona Guip\u00f9zcoa 20150",
    "addr:housenumber":"s / n",
    "addr:postcode":"20150",
    "addr:street":"Agaraitz Auzoa;Guipu\u0300Zcoa",
    "iso:country":"ES",
    "sg:address":"Agaraitz Auzoa, S/n",
    "sg:city":"Villabona",
    "sg:orig_category":"Agentes, Concesionarios Y Sucursales De Veh\u00cdculos",
    "sg:phone":"+34 943 69 04 00",
    "sg:postcode":"20150",
    "sg:province":"Guip\u00f9zcoa",
    "wof:name":"Resa Guipuzcoana S. A.",
    "wof:placetype":"venue"
},
  "geometry": {"coordinates":[-2.049612999,43.1962165833],"type":"Point"}
}