{
  "type": "Feature",
  "properties": {
    "iso:country":"ES",
    "sg:address":"Ptda Raco Dels Pins, 2",
    "sg:city":"Burjassot",
    "sg:orig_category":"Cueros Y Pieles (al Por Mayor)",
    "sg:phone":"+34 963 63 49 66",
    "sg:postcode":"46100",
    "sg:province":"Valencia",
    "wof:name":"Curtidos Escrich S.l.",
    "wof:placetype":"venue"
},
  "geometry": {"coordinates":[-0.4105490148,39.5093688965],"type":"Point"}
}