{
  "type": "Feature",
  "properties": {
    "addr:full":"Calle de Toreno, 57 Fuenlabrada Madrid 28947",
    "addr:housenumber":"57",
    "addr:postcode":"28947",
    "addr:street":"Calle De Toreno",
    "iso:country":"ES",
    "sg:address":"Calle de Toreno, 57",
    "sg:city":"Fuenlabrada",
    "sg:orig_category":"Construcci\u00d3n Mec\u00c1nica",
    "sg:phone":"+34 916 42 24 24",
    "sg:postcode":"28947",
    "sg:province":"Madrid",
    "wof:name":"Industrias Franjo S. A.",
    "wof:placetype":"venue"
},
  "geometry": {"coordinates":[-3.7514269352,40.2634277344],"type":"Point"}
}