{
  "type": "Feature",
  "properties": {
    "addr:full":"Rond Nelle, 98 Coru\u00d1a La Coru\u00f1a 15005",
    "addr:housenumber":"98",
    "addr:postcode":"15005",
    "addr:street":"Rond Nelle;Corun\u0303A",
    "iso:country":"ES",
    "sg:address":"Rond Nelle, 98",
    "sg:city":"Coru\u00d1a",
    "sg:orig_category":"Asesor\u00cda De Formaci\u00d3n Y Gesti\u00d3n De Personal",
    "sg:phone":"+34 981 14 04 30",
    "sg:postcode":"15005",
    "sg:province":"La Coru\u00f1a",
    "wof:name":"Gestoria Geyne S.l.",
    "wof:placetype":"venue"
},
  "geometry": {"coordinates":[-8.4150562286,43.360660553],"type":"Point"}
}