{
  "type": "Feature",
  "properties": {
    "addr:full":"E. De San Blas, 6 Villanueva Arzobispo Ja\u00e9n 23330",
    "addr:housenumber":"6",
    "addr:postcode":"23330",
    "addr:street":"E.;San Blas",
    "iso:country":"ES",
    "sg:address":"E. De San Blas, 6",
    "sg:city":"Villanueva Arzobispo",
    "sg:orig_category":"Empresas De Carpinter\u00cda De Madera",
    "sg:phone":"+34 953 45 03 47",
    "sg:postcode":"23330",
    "sg:province":"Ja\u00e9n",
    "wof:name":"Sanchez Secaduras Manuel Y Otros C.b.",
    "wof:placetype":"venue"
},
  "geometry": {"coordinates":[-3.0082640648,38.1664009094],"type":"Point"}
}