{
  "type": "Feature",
  "properties": {
    "addr:full":"Rua Ribeira, 9 Redondela Pontevedra 36800",
    "addr:housenumber":"9",
    "addr:postcode":"36800",
    "addr:street":"Rua Ribeira",
    "iso:country":"ES",
    "sg:address":"Rua Ribeira, 9",
    "sg:city":"Redondela",
    "sg:classifiers":[
        {
            "category":"Personal",
            "subcategory":"Barber",
            "type":"Services"
        }
    ],
    "sg:phone":"+34 986 40 29 63",
    "sg:postcode":"36800",
    "sg:province":"Pontevedra",
    "sg:tags":[
        "caballeros",
        "de",
        "peluqueros"
    ],
    "wof:name":"Lago Otero Jose Francisco",
    "wof:placetype":"venue"
},
  "geometry": {"coordinates":[-8.6090641022,42.2820243835],"type":"Point"}
}