{
  "type": "Feature",
  "properties": {
    "iso:country":"ES",
    "sg:address":"Carrer de Ausias Marc, 46",
    "sg:city":"Barcelona",
    "sg:orig_category":"Inmobiliaria (agencias)",
    "sg:phone":"+34 932 44 00 23",
    "sg:postcode":"08010",
    "sg:province":"Barcelona",
    "wof:name":"Pirox Inmobiliaria S.l",
    "wof:placetype":"venue"
},
  "geometry": {"coordinates":[2.1766819954,41.3919563293],"type":"Point"}
}