{
  "type": "Feature",
  "properties": {
    "addr:full":"Calle de Barroeta Aldamar, 3 Bilbao Vizcaya 48001",
    "addr:housenumber":"3",
    "addr:postcode":"48001",
    "addr:street":"Calle De Barroeta Aldamar",
    "iso:country":"ES",
    "sg:address":"Calle de Barroeta Aldamar, 3",
    "sg:city":"Bilbao",
    "sg:orig_category":"Asilos De Ancianos. Centros Privados",
    "sg:phone":"+34 944 23 14 76",
    "sg:postcode":"48001",
    "sg:province":"Vizcaya",
    "wof:name":"Residencia Uribitarte S.l",
    "wof:placetype":"venue"
},
  "geometry": {"coordinates":[-2.9262061119,43.2630271912],"type":"Point"}
}