{
  "type": "Feature",
  "properties": {
    "iso:country":"ES",
    "sg:address":"Ptda Pla Senieta, 1",
    "sg:city":"Calpe",
    "sg:orig_category":"Empresas De Limpieza",
    "sg:phone":"+34 965 83 49 44",
    "sg:postcode":"03710",
    "sg:province":"Alicante",
    "wof:name":"Garcia Vengut Maria Rosario",
    "wof:placetype":"venue"
},
  "geometry": {"coordinates":[0.0535200015,38.6515808105],"type":"Point"}
}