{
  "type": "Feature",
  "properties": {
    "iso:country":"ES",
    "sg:address":"Carrer de Peru, 4",
    "sg:city":"Palma",
    "sg:orig_category":"Ense\u00d1anza Secundaria: Colegios Y Escuelas Privadas",
    "sg:phone":"+34 971 24 20 34",
    "sg:postcode":"07007",
    "sg:province":"Islas Baleares",
    "wof:name":"Institut D'ensenyament Secundari Antoni Maura",
    "wof:placetype":"venue"
},
  "geometry": {"coordinates":[2.67000103,39.5676002502],"type":"Point"}
}