{
  "type": "Feature",
  "properties": {
    "addr:full":"Calle de General Zabala, 2 Madrid Madrid 28002",
    "addr:housenumber":"2",
    "addr:postcode":"28002",
    "addr:street":"Calle De General Zabala",
    "iso:country":"ES",
    "sg:address":"Calle de General Zabala, 2",
    "sg:city":"Madrid",
    "sg:classifiers":[
        {
            "category":"Personal",
            "subcategory":"Barber",
            "type":"Services"
        }
    ],
    "sg:phone":"+34 915 61 02 44",
    "sg:postcode":"28002",
    "sg:province":"Madrid",
    "sg:tags":[
        "caballeros",
        "de",
        "peluqueros"
    ],
    "wof:name":"Del Fresno Delgado Luis",
    "wof:placetype":"venue"
},
  "geometry": {"coordinates":[-3.6743900776,40.4427566528],"type":"Point"}
}