{
  "type": "Feature",
  "properties": {
    "iso:country":"ES",
    "sg:address":"Calle de Lopez De Fenar, 14",
    "sg:city":"Le\u00f3n",
    "sg:orig_category":"Pescader\u00cdas (al Por Menor)",
    "sg:phone":"+34 987 20 95 54",
    "sg:postcode":"24003",
    "sg:province":"Le\u00f3n",
    "wof:name":"Blanco Alvarez Jose Antonio",
    "wof:placetype":"venue"
},
  "geometry": {"coordinates":[-5.5669231415,42.5937576294],"type":"Point"}
}