{
  "type": "Feature",
  "properties": {
    "addr:full":"Barr Mallabiena, 57 Mallabiena Vizcaya 48215",
    "addr:housenumber":"57",
    "addr:postcode":"48215",
    "addr:street":"Mallabiena",
    "iso:country":"ES",
    "sg:address":"Barr Mallabiena, 57",
    "sg:city":"Mallabiena",
    "sg:orig_category":"Electricidad: Instaladores",
    "sg:phone":"+34 946 81 28 62",
    "sg:postcode":"48215",
    "sg:province":"Vizcaya",
    "wof:name":"Electricidad Gure-etxea S. L.",
    "wof:placetype":"venue"
},
  "geometry": {"coordinates":[-2.631608963,43.1760597229],"type":"Point"}
}