{
  "type": "Feature",
  "properties": {
    "iso:country":"ES",
    "sg:address":"Avda Monegros, S/n",
    "sg:city":"Sari\u00f1ena",
    "sg:orig_category":"Electricidad Veh\u00cdculo",
    "sg:phone":"+34 974 57 07 80",
    "sg:postcode":"22200",
    "sg:province":"Huesca",
    "wof:name":"Lacuna Asin Alfredo",
    "wof:placetype":"venue"
},
  "geometry": {"coordinates":[-0.160879001,41.7910766602],"type":"Point"}
}