{
  "type": "Feature",
  "properties": {
    "iso:country":"ES",
    "sg:address":"Crta. Nacional 340, Km. 0061,7",
    "sg:city":"Almassora Pol. Ind.",
    "sg:orig_category":"Agentes, Concesionarios Y Sucursales De Camiones Y Veh\u00cdculos Industriales",
    "sg:phone":"+34 964 53 66 88",
    "sg:postcode":"12550",
    "sg:province":"Castell\u00f3n",
    "wof:name":"Automocion La Pista S.a.",
    "wof:placetype":"venue"
},
  "geometry": {"coordinates":[-0.0631740019,39.9439582825],"type":"Point"}
}