{
  "type": "Feature",
  "properties": {
    "iso:country":"ES",
    "sg:address":"Carrer de Jovara, 212",
    "sg:city":"Calella",
    "sg:orig_category":"Cer\u00c1mica Art\u00cdstica Y Decorativa",
    "sg:phone":"+34 937 66 16 35",
    "sg:postcode":"08370",
    "sg:province":"Barcelona",
    "wof:name":"Ceramica Artistica Socemar S.l.",
    "wof:placetype":"venue"
},
  "geometry": {"coordinates":[2.6625831127,41.6139640808],"type":"Point"}
}