{
  "type": "Feature",
  "properties": {
    "iso:country":"ES",
    "sg:address":"Calle de San Juan, 14",
    "sg:city":"Donostia-san Sebastian",
    "sg:orig_category":"M\u00c9dicos: Cirug\u00cda Maxilofacial",
    "sg:phone":"+34 943 42 16 06",
    "sg:postcode":"20003",
    "sg:province":"Guip\u00f9zcoa",
    "wof:name":"Rad Carrera Juan Antonio",
    "wof:placetype":"venue"
},
  "geometry": {"coordinates":[-1.9844330549,43.3257522583],"type":"Point"}
}