{
  "type": "Feature",
  "properties": {
    "iso:country":"ES",
    "sg:address":"Calle de Hilera, 8",
    "sg:city":"Malaga",
    "sg:orig_category":"Asesor\u00cda Sobre Comunicaci\u00d3n De Empresas",
    "sg:phone":"+34 952 30 20 62",
    "sg:postcode":"29007",
    "sg:province":"M\u00e1laga",
    "wof:name":"Laude Asesores S.l.",
    "wof:placetype":"venue"
},
  "geometry": {"coordinates":[-4.429956913,36.7181968689],"type":"Point"}
}