{
  "type": "Feature",
  "properties": {
    "iso:country":"ES",
    "sg:address":"Avda Medina Olmos, 6",
    "sg:city":"Guadix",
    "sg:orig_category":"Confecci\u00d3n (fabricaci\u00d3n, Al Por Mayor)",
    "sg:phone":"+34 958 66 01 95",
    "sg:postcode":"18500",
    "sg:province":"Granada",
    "wof:name":"Romero Vallecillos Jose",
    "wof:placetype":"venue"
},
  "geometry": {"coordinates":[-3.13230896,37.3007698059],"type":"Point"}
}