{
  "type": "Feature",
  "properties": {
    "iso:country":"ES",
    "sg:address":"Carrer de Castellnou, 41",
    "sg:city":"Barcelona",
    "sg:orig_category":"Fabricaci\u00d3n De Papel Para Embalar",
    "sg:phone":"+34 932 03 23 16",
    "sg:postcode":"08017",
    "sg:province":"Barcelona",
    "wof:name":"Andres Barella Jorge",
    "wof:placetype":"venue"
},
  "geometry": {"coordinates":[2.1294794083,41.3957901001],"type":"Point"}
}