{
  "type": "Feature",
  "properties": {
    "iso:country":"ES",
    "sg:address":"Avda Antiguako Ama, 5",
    "sg:city":"Ondarroa",
    "sg:orig_category":"Molduras, Junquillos, Listones Y Molduras Perforadas",
    "sg:phone":"+34 946 83 00 19",
    "sg:postcode":"48700",
    "sg:province":"Vizcaya",
    "wof:name":"Jose Francisco Bedialauneta Gastelum (bar Cantabrico)",
    "wof:placetype":"venue"
},
  "geometry": {"coordinates":[-2.4224059582,43.3231620789],"type":"Point"}
}