{
  "type": "Feature",
  "properties": {
    "addr:full":"Calle de Ruiz Ramos, 13 Montellano Sevilla 41770",
    "addr:housenumber":"13",
    "addr:postcode":"41770",
    "addr:street":"Calle De Ruiz Ramos",
    "iso:country":"ES",
    "sg:address":"Calle de Ruiz Ramos, 13",
    "sg:city":"Montellano",
    "sg:orig_category":"Art\u00cdculos De Regalo (al Por Menor)",
    "sg:phone":"+34 954 87 56 90",
    "sg:postcode":"41770",
    "sg:province":"Sevilla",
    "wof:name":"Luna Salguero Jose Manuel",
    "wof:placetype":"venue"
},
  "geometry": {"coordinates":[-5.5707530975,36.9911689758],"type":"Point"}
}