{
  "type": "Feature",
  "properties": {
    "addr:full":"Fueyo, 22 Fueyo Asturias 33199",
    "addr:housenumber":"22",
    "addr:postcode":"33199",
    "addr:street":"Fueyo;Asturias",
    "iso:country":"ES",
    "sg:address":"Fueyo, 22",
    "sg:city":"Fueyo",
    "sg:orig_category":"Empresas De Limpieza",
    "sg:phone":"+34 985 97 28 72",
    "sg:postcode":"33199",
    "sg:province":"Asturias",
    "wof:name":"Limpiezas Pahino S.l.",
    "wof:placetype":"venue"
},
  "geometry": {"coordinates":[-5.7451562881,43.3663215637],"type":"Point"}
}