{
  "type": "Feature",
  "properties": {
    "iso:country":"ES",
    "sg:address":"Rua De Moron, 9",
    "sg:city":"Silleda",
    "sg:orig_category":"Chapister\u00cda",
    "sg:phone":"+34 986 58 07 32",
    "sg:postcode":"36540",
    "sg:province":"Pontevedra",
    "wof:name":"Taller Lalin Taboada S.cv.",
    "wof:placetype":"venue"
},
  "geometry": {"coordinates":[-8.2474994659,42.7010612488],"type":"Point"}
}