{
  "type": "Feature",
  "properties": {
    "iso:country":"ES",
    "sg:address":"Camino Viejo Simancas, 14",
    "sg:city":"Valladolid",
    "sg:orig_category":"Animales (al Por Menor)",
    "sg:phone":"+34 983 23 94 25",
    "sg:postcode":"47008",
    "sg:province":"Valladolid",
    "wof:name":"Asturcon Agrobroker C.b.",
    "wof:placetype":"venue"
},
  "geometry": {"coordinates":[-4.7468328476,41.6267662048],"type":"Point"}
}