{
  "type": "Feature",
  "properties": {
    "iso:country":"ES",
    "sg:address":"Calle de Milanos, 6",
    "sg:city":"Pinto",
    "sg:orig_category":"Aparatos, Material Y Suministros Para Laboratorios",
    "sg:phone":"+34 916 91 65 80",
    "sg:postcode":"28320",
    "sg:province":"Madrid",
    "wof:name":"Omadisa Industrias Del Laboratorio S.a.",
    "wof:placetype":"venue"
},
  "geometry": {"coordinates":[-3.7054750919,40.248626709],"type":"Point"}
}