{
  "type": "Feature",
  "properties": {
    "iso:country":"ES",
    "sg:address":"Plaz Uncibay, S/n",
    "sg:city":"Malaga",
    "sg:orig_category":"Agencias De Viajes",
    "sg:phone":"+34 952 22 52 50",
    "sg:postcode":"29008",
    "sg:province":"M\u00e1laga",
    "wof:name":"Viajes Amor Tour S. A.",
    "wof:placetype":"venue"
},
  "geometry": {"coordinates":[-4.4202990532,36.7226638794],"type":"Point"}
}