{
  "type": "Feature",
  "properties": {
    "addr:full":"Ctra Era Cardon, 1 Vecindario Las Palmas 35110",
    "addr:housenumber":"1",
    "addr:postcode":"35110",
    "addr:street":"Ctra Era Cardon;Palmas",
    "iso:country":"ES",
    "sg:address":"Ctra Era Cardon, 1",
    "sg:city":"Vecindario",
    "sg:orig_category":"Reposter\u00cdas",
    "sg:phone":"+34 928 75 55 90",
    "sg:postcode":"35110",
    "sg:province":"Las Palmas",
    "wof:name":"Panificadora San Isidro S.a.",
    "wof:placetype":"venue"
},
  "geometry": {"coordinates":[-15.4485340118,27.8392906189],"type":"Point"}
}