{
  "type": "Feature",
  "properties": {
    "iso:country":"ES",
    "sg:address":"Carrer de Cardenal Reig, 25",
    "sg:city":"Barcelona",
    "sg:orig_category":"Doctores En Medicina",
    "sg:phone":"+34 934 48 08 71",
    "sg:postcode":"08028",
    "sg:province":"Barcelona",
    "wof:name":"Lillo Espinosa Jose Luis",
    "wof:placetype":"venue"
},
  "geometry": {"coordinates":[2.1149759293,41.3785133362],"type":"Point"}
}