{
  "type": "Feature",
  "properties": {
    "iso:country":"ES",
    "sg:address":"Calle de Real De Motril, 15",
    "sg:city":"Armilla",
    "sg:orig_category":"Montaje (empresas De)",
    "sg:phone":"+34 958 57 36 91",
    "sg:postcode":"18100",
    "sg:province":"Granada",
    "wof:name":"Electrica San Miguel Cb",
    "wof:placetype":"venue"
},
  "geometry": {"coordinates":[-3.6256380081,37.1432533264],"type":"Point"}
}