{
  "type": "Feature",
  "properties": {
    "iso:country":"ES",
    "sg:address":"Av Ignasi Wallis, 10",
    "sg:city":"Eivissa",
    "sg:orig_category":"Ropa Para Caballeros (al Por Menor)",
    "sg:phone":"+34 971 31 21 86",
    "sg:postcode":"07800",
    "sg:province":"Islas Baleares",
    "wof:name":"Teatralia C.b.",
    "wof:placetype":"venue"
},
  "geometry": {"coordinates":[1.4278570414,38.9157295227],"type":"Point"}
}