{
  "type": "Feature",
  "properties": {
    "addr:full":"Calle de Tomas Edison, 23 Zaragoza Zaragoza 50014",
    "addr:housenumber":"23",
    "addr:postcode":"50014",
    "addr:street":"Calle De Tomas Edison",
    "iso:country":"ES",
    "sg:address":"Calle de Tomas Edison, 23",
    "sg:city":"Zaragoza",
    "sg:orig_category":"Instalaci\u00d3n, Reparaci\u00d3n De Ascensores Y Montacargas",
    "sg:phone":"+34 976 47 11 90",
    "sg:postcode":"50014",
    "sg:province":"Zaragoza",
    "wof:name":"Mecanicas Reunidas Romanos S. A.",
    "wof:placetype":"venue"
},
  "geometry": {"coordinates":[-0.8662719727,41.6683387756],"type":"Point"}
}