{
  "type": "Feature",
  "properties": {
    "addr:full":"Avda Felix Arranz, 4 Mentrida Toledo 45930",
    "addr:housenumber":"4",
    "addr:postcode":"45930",
    "addr:street":"Avda Felix Arranz",
    "iso:country":"ES",
    "sg:address":"Avda Felix Arranz, 4",
    "sg:city":"Mentrida",
    "sg:orig_category":"Agencias Y Agentes Comerciales, Representantes",
    "sg:phone":"+34 918 17 87 71",
    "sg:postcode":"45930",
    "sg:province":"Toledo",
    "wof:name":"Sanchez Garcia Jose Eugenio",
    "wof:placetype":"venue"
},
  "geometry": {"coordinates":[-4.1951050758,40.2356834412],"type":"Point"}
}