{
  "type": "Feature",
  "properties": {
    "addr:full":"Av Ntra. Sra. De L'assumpcio, 190 Deltebre Tarragona 43580",
    "addr:housenumber":"190",
    "addr:postcode":"43580",
    "addr:street":"Av Ntra. Sra. De L'Assumpcio",
    "iso:country":"ES",
    "sg:address":"Av Ntra. Sra. De L'assumpcio, 190",
    "sg:city":"Deltebre",
    "sg:orig_category":"Farmacias",
    "sg:phone":"+34 977 48 91 21",
    "sg:postcode":"43580",
    "sg:province":"Tarragona",
    "wof:name":"Albiol Gisbert Francisco",
    "wof:placetype":"venue"
},
  "geometry": {"coordinates":[0.7342733741,40.7338066101],"type":"Point"}
}