{
  "type": "Feature",
  "properties": {
    "addr:full":"Calle de Suertes (las), 91 Estacion Madrid 28400",
    "addr:housenumber":"91",
    "addr:postcode":"28400",
    "addr:street":"Calle De Suertes Las",
    "iso:country":"ES",
    "sg:address":"Calle de Suertes (las), 91",
    "sg:city":"Estacion",
    "sg:orig_category":"Traductores",
    "sg:phone":"+34 918 51 16 73",
    "sg:postcode":"28400",
    "sg:province":"Madrid",
    "wof:name":"Systems Outsourcing S.l.",
    "wof:placetype":"venue"
},
  "geometry": {"coordinates":[-3.9919650555,40.6455612183],"type":"Point"}
}