{
  "type": "Feature",
  "properties": {
    "iso:country":"ES",
    "sg:address":"Avda Elduayen, 7",
    "sg:city":"Gondomar",
    "sg:orig_category":"Mercer\u00cda, Lencer\u00cda (al Por Menor)",
    "sg:phone":"+34 986 36 01 83",
    "sg:postcode":"36380",
    "sg:province":"Pontevedra",
    "wof:name":"Dominguez Penedo Juan",
    "wof:placetype":"venue"
},
  "geometry": {"coordinates":[-8.7624645233,42.1114730835],"type":"Point"}
}