{
  "type": "Feature",
  "properties": {
    "iso:country":"ES",
    "sg:address":"Calle de Cantarranas, 60",
    "sg:city":"Cabezas S. Juan",
    "sg:orig_category":"Droguer\u00cdas (al Por Menor)",
    "sg:phone":"+34 955 87 15 20",
    "sg:postcode":"41730",
    "sg:province":"Sevilla",
    "wof:name":"Fernandez Gomez Cristobal",
    "wof:placetype":"venue"
},
  "geometry": {"coordinates":[-5.9384021759,36.9839782715],"type":"Point"}
}