{
  "type": "Feature",
  "properties": {
    "iso:country":"ES",
    "sg:address":"Avda Ayuntamiento, 24",
    "sg:city":"Sanet Y Negrals",
    "sg:orig_category":"Centros De Educaci\u00d3n Especial",
    "sg:phone":"+34 966 40 81 85",
    "sg:postcode":"03769",
    "sg:province":"Alicante",
    "wof:name":"Generalitat Valenciana",
    "wof:placetype":"venue"
},
  "geometry": {"coordinates":[-0.0359750018,38.820022583],"type":"Point"}
}