{
  "type": "Feature",
  "properties": {
    "addr:full":"Avda. F. Salvador, 50 Castello Plana Castell\u00f3n 12100",
    "addr:housenumber":"50",
    "addr:postcode":"12100",
    "addr:street":"Avda. F. Salvador;Castello\u0301N",
    "iso:country":"ES",
    "sg:address":"Avda. F. Salvador, 50",
    "sg:city":"Castello Plana",
    "sg:orig_category":"Centros Empresariales",
    "sg:phone":"+34 964 73 70 69",
    "sg:postcode":"12100",
    "sg:province":"Castell\u00f3n",
    "wof:name":"Calderon Amigo Jesus",
    "wof:placetype":"venue"
},
  "geometry": {"coordinates":[0.0176999997,39.9888801575],"type":"Point"}
}