{
  "type": "Feature",
  "properties": {
    "addr:full":"Pase Extremadura, S/n Pinofranqueado C\u00e1ceres 10630",
    "addr:postcode":"10630",
    "addr:street":"Extremadura S / N;Ca\u0301Ceres",
    "iso:country":"ES",
    "sg:address":"Pase Extremadura, S/n",
    "sg:city":"Pinofranqueado",
    "sg:orig_category":"Restaurantes Para Recepciones, Banquetes, Conferencias",
    "sg:phone":"+34 927 67 40 28",
    "sg:postcode":"10630",
    "sg:province":"C\u00e1ceres",
    "wof:name":"Gomez Sanchez Rafael",
    "wof:placetype":"venue"
},
  "geometry": {"coordinates":[-6.3333010674,40.3016433716],"type":"Point"}
}