{
  "type": "Feature",
  "properties": {
    "iso:country":"ES",
    "sg:address":"Ciud R.-valdepe\u00f1as, Km. 0010,7",
    "sg:city":"Pozuelo Calatrava",
    "sg:orig_category":"Fabricaci\u00d3n De Bibliotecas Y Estanter\u00cdas",
    "sg:phone":"+34 926 84 01 79",
    "sg:postcode":"13179",
    "sg:province":"Ciudad Real",
    "wof:name":"Chacon Miguel Carmelo",
    "wof:placetype":"venue"
},
  "geometry": {"coordinates":[-3.8354260921,38.9131889343],"type":"Point"}
}