{
  "type": "Feature",
  "properties": {
    "iso:country":"ES",
    "sg:address":"Rua Perpetuo Socorro, 3",
    "sg:city":"Lugo",
    "sg:orig_category":"Comercio, Reparaci\u00d3n De Bicicletas, De Motocicletas, De Accesorios",
    "sg:phone":"+34 982 25 31 70",
    "sg:postcode":"27003",
    "sg:province":"Lugo",
    "wof:name":"Brites Medin Jose Manuel",
    "wof:placetype":"venue"
},
  "geometry": {"coordinates":[-7.5623040199,43.0195579529],"type":"Point"}
}