{
  "type": "Feature",
  "properties": {
    "iso:country":"ES",
    "sg:address":"Avda Suecia (de), 11",
    "sg:city":"Cristianos",
    "sg:orig_category":"Zapatos (al Por Menor)",
    "sg:phone":"+34 922 79 08 10",
    "sg:postcode":"38650",
    "sg:province":"Santa Cruz De Tenerife",
    "wof:name":"Comercial Atope S. A.",
    "wof:placetype":"venue"
},
  "geometry": {"coordinates":[-16.7181930542,28.0520305634],"type":"Point"}
}