{
  "type": "Feature",
  "properties": {
    "addr:full":"Calle de Callao (de), 52 Fuenlabrada Madrid 28945",
    "addr:housenumber":"52",
    "addr:postcode":"28945",
    "addr:street":"Calle De Callao De",
    "iso:country":"ES",
    "sg:address":"Calle de Callao (de), 52",
    "sg:city":"Fuenlabrada",
    "sg:orig_category":"Inmobiliaria (agencias)",
    "sg:phone":"+34 916 97 62 00",
    "sg:postcode":"28945",
    "sg:province":"Madrid",
    "wof:name":"Aracasa Asesores Inmobiliarios S.l",
    "wof:placetype":"venue"
},
  "geometry": {"coordinates":[-3.785500288,40.2938842773],"type":"Point"}
}