{
  "type": "Feature",
  "properties": {
    "iso:country":"ES",
    "sg:address":"Praz Ravella, 15",
    "sg:city":"Vilagarcia",
    "sg:orig_category":"Panader\u00cdas, Panader\u00cdas",
    "sg:phone":"+34 986 50 23 95",
    "sg:postcode":"36600",
    "sg:province":"Pontevedra",
    "wof:name":"Ankarr Villagarcia S.l.u.",
    "wof:placetype":"venue"
},
  "geometry": {"coordinates":[-8.7642822266,42.5966148376],"type":"Point"}
}