{
  "type": "Feature",
  "properties": {
    "iso:country":"ES",
    "sg:address":"Carretera De Soria-valladolid, S/n",
    "sg:city":"Villaciervos",
    "sg:orig_category":"Venta, Instalaci\u00d3n De Cocinas",
    "sg:phone":"+34 975 28 00 23",
    "sg:postcode":"42192",
    "sg:province":"Soria",
    "wof:name":"Blasco Perez Jaime",
    "wof:placetype":"venue"
},
  "geometry": {"coordinates":[-2.7410569191,41.7375297546],"type":"Point"}
}