{
  "type": "Feature",
  "properties": {
    "addr:full":"Carr Jaume I, 64 Girona Girona 17001",
    "addr:housenumber":"64",
    "addr:postcode":"17001",
    "addr:street":"Carr Jaume I",
    "iso:country":"ES",
    "sg:address":"Carr Jaume I, 64",
    "sg:city":"Girona",
    "sg:orig_category":"Ense\u00d1anza, Formaci\u00d3n Profesional: Aprendizaje",
    "sg:phone":"+34 972 21 69 21",
    "sg:postcode":"17001",
    "sg:province":"Girona",
    "wof:name":"Centre De Telecomunicaciones De Catalunya",
    "wof:placetype":"venue"
},
  "geometry": {"coordinates":[2.8199219704,41.981678009],"type":"Point"}
}