{
  "type": "Feature",
  "properties": {
    "iso:country":"ES",
    "sg:address":"Avda Andalucia (de), 148",
    "sg:city":"Valdemoro",
    "sg:orig_category":"Promotores Constructores",
    "sg:phone":"+34 918 09 53 45",
    "sg:postcode":"28340",
    "sg:province":"Madrid",
    "wof:name":"Red Espa\u00d1ola De Logistica S.l.",
    "wof:placetype":"venue"
},
  "geometry": {"coordinates":[-3.6793351173,40.2058143616],"type":"Point"}
}