{
  "type": "Feature",
  "properties": {
    "addr:full":"Cami Sant Cugat, 35 Barcelona Barcelona 08017",
    "addr:housenumber":"35",
    "addr:postcode":"08017",
    "addr:street":"Sant Cugat",
    "iso:country":"ES",
    "sg:address":"Cami Sant Cugat, 35",
    "sg:city":"Barcelona",
    "sg:orig_category":"Asociaciones, Organismos Culturales Y Socioeducativos",
    "sg:phone":"+34 932 12 06 05",
    "sg:postcode":"08017",
    "sg:province":"Barcelona",
    "wof:name":"Servei D'informacio De Sistemes Educatius",
    "wof:placetype":"venue"
},
  "geometry": {"coordinates":[2.1153099537,41.4264907837],"type":"Point"}
}