{
  "type": "Feature",
  "properties": {
    "addr:full":"Pquia. Bergondo-pol. Ind., S/n Babio A Coru\u00f1a 15166",
    "addr:housenumber":"s / n",
    "addr:postcode":"15166",
    "addr:street":"Babio A Corun\u0303A",
    "iso:country":"ES",
    "sg:address":"Pquia. Bergondo-pol. Ind., S/n",
    "sg:city":"Babio",
    "sg:classifiers":[
        {
            "category":"Banks & Credit Unions",
            "subcategory":"Bureau De Change",
            "type":"Services"
        }
    ],
    "sg:phone":"+34 981 78 47 74",
    "sg:postcode":"15166",
    "sg:province":"A Coru\u00f1a",
    "sg:tags":[
        "organismos",
        "control"
    ],
    "sg:website":"www.scia.es",
    "wof:name":"Servicios Control Inspeccion S.a.",
    "wof:placetype":"venue"
},
  "geometry": {"coordinates":[-8.2616682053,43.3274726868],"type":"Point"}
}