{
  "type": "Feature",
  "properties": {
    "addr:full":"Ctra Garrucha-villaricos, 158 Garrucha Almer\u00eda 04630",
    "addr:housenumber":"158",
    "addr:postcode":"04630",
    "addr:street":"Ctra Garrucha-Villaricos;Almeri\u0301A",
    "iso:country":"ES",
    "sg:address":"Ctra Garrucha-villaricos, 158",
    "sg:city":"Garrucha",
    "sg:orig_category":"Promotores Constructores",
    "sg:phone":"+34 950 46 00 91",
    "sg:postcode":"04630",
    "sg:province":"Almer\u00eda",
    "wof:name":"Proyectos Del Levante Almeriense S.a.",
    "wof:placetype":"venue"
},
  "geometry": {"coordinates":[-1.8196489811,37.1859741211],"type":"Point"}
}