{
  "type": "Feature",
  "properties": {
    "addr:full":"Calle de Pinar De Do\u00d1a Consuelo, 18 Majadahonda Madrid 28220",
    "addr:housenumber":"18",
    "addr:postcode":"28220",
    "addr:street":"Calle De Pinar De Don\u0303A Consuelo",
    "iso:country":"ES",
    "sg:address":"Calle de Pinar De Do\u00d1a Consuelo, 18",
    "sg:city":"Majadahonda",
    "sg:orig_category":"Artes Gr\u00c1ficas, Artes Pl\u00c1sticas (curso)",
    "sg:phone":"+34 916 34 58 25",
    "sg:postcode":"28220",
    "sg:province":"Madrid",
    "wof:name":"Igi Imagen Y Comunicacion",
    "wof:placetype":"venue"
},
  "geometry": {"coordinates":[-3.8780040741,40.4829101562],"type":"Point"}
}