{
  "type": "Feature",
  "properties": {
    "addr:full":"Alfonso El Batallador, 11 Iru\u00f1a Navarra 31007",
    "addr:housenumber":"11",
    "addr:postcode":"31007",
    "addr:street":"Batallador",
    "iso:country":"ES",
    "sg:address":"Alfonso El Batallador, 11",
    "sg:city":"Iru\u00f1a",
    "sg:orig_category":"Electromec\u00c1nica",
    "sg:phone":"+34 948 26 00 60",
    "sg:postcode":"31007",
    "sg:province":"Navarra",
    "wof:name":"Diaz Go\u00f1i Jesus",
    "wof:placetype":"venue"
},
  "geometry": {"coordinates":[-1.6526149511,42.8035469055],"type":"Point"}
}