{
  "type": "Feature",
  "properties": {
    "addr:full":"C/ Major, 8 Paterna Valencia 46980",
    "addr:housenumber":"8",
    "addr:postcode":"46980",
    "addr:street":"C / Major",
    "iso:country":"ES",
    "sg:address":"C/ Major, 8",
    "sg:city":"Paterna",
    "sg:orig_category":"Ropa Para Se\u00d1oras (al Por Menor)",
    "sg:phone":"+34 961 38 11 02",
    "sg:postcode":"46980",
    "sg:province":"Valencia",
    "wof:name":"Boutique Isa C.b",
    "wof:placetype":"venue"
},
  "geometry": {"coordinates":[-0.445201993,39.5047111511],"type":"Point"}
}