{
  "type": "Feature",
  "properties": {
    "iso:country":"ES",
    "sg:address":"Calle de Blas Infante, 36",
    "sg:city":"Castillo Locubin",
    "sg:orig_category":"Ropa Para Se\u00d1oras (al Por Menor)",
    "sg:phone":"+34 953 59 05 11",
    "sg:postcode":"23670",
    "sg:province":"Ja\u00e9n",
    "wof:name":"Collado Moyano Manuel",
    "wof:placetype":"venue"
},
  "geometry": {"coordinates":[-3.944204092,37.5285072327],"type":"Point"}
}