{
  "type": "Feature",
  "properties": {
    "iso:country":"ES",
    "sg:address":"Calle de Solos Prados (de), S/n",
    "sg:city":"Becerril Sierra",
    "sg:orig_category":"Polideportivos",
    "sg:phone":"+34 918 53 74 36",
    "sg:postcode":"28490",
    "sg:province":"Madrid",
    "wof:name":"Ayuntamiento De Becerril De La Sierra",
    "wof:placetype":"venue"
},
  "geometry": {"coordinates":[-3.9852020741,40.7109222412],"type":"Point"}
}