{
  "type": "Feature",
  "properties": {
    "addr:full":"Calle de Eskalantegi, 17 Pasai Antxo Guip\u00f9zcoa 20110",
    "addr:housenumber":"17",
    "addr:postcode":"20110",
    "addr:street":"Calle De Eskalantegi;Guipu\u0300Zcoa",
    "iso:country":"ES",
    "sg:address":"Calle de Eskalantegi, 17",
    "sg:city":"Pasai Antxo",
    "sg:orig_category":"Empresas De Carpinter\u00cda Met\u00c1lica",
    "sg:phone":"+34 943 52 07 30",
    "sg:postcode":"20110",
    "sg:province":"Guip\u00f9zcoa",
    "wof:name":"Crespo Abalia Felix Maria",
    "wof:placetype":"venue"
},
  "geometry": {"coordinates":[-1.9190490246,43.3179740906],"type":"Point"}
}