{
  "type": "Feature",
  "properties": {
    "iso:country":"ES",
    "sg:address":"Carr Sant Manuel, 137",
    "sg:city":"Mao",
    "sg:orig_category":"Empresas De Carpinter\u00cda De Madera",
    "sg:phone":"+34 971 36 14 96",
    "sg:postcode":"07702",
    "sg:province":"Islas Baleares",
    "wof:name":"Anglada Rotger Gabriel",
    "wof:placetype":"venue"
},
  "geometry": {"coordinates":[4.2659292221,39.8834609985],"type":"Point"}
}