{
  "type": "Feature",
  "properties": {
    "iso:country":"ES",
    "sg:address":"Arenal, 129",
    "sg:city":"Javea",
    "sg:orig_category":"Pintura, Barniz, Productos Asimilables (fabricaci\u00d3n, Al Por Mayor)",
    "sg:phone":"+34 965 79 49 12",
    "sg:postcode":"03730",
    "sg:province":"Alicante",
    "wof:name":"Servicio Y Color Ondara S.l.",
    "wof:placetype":"venue"
},
  "geometry": {"coordinates":[0.1570300013,38.7885093689],"type":"Point"}
}