{
  "type": "Feature",
  "properties": {
    "iso:country":"ES",
    "sg:address":"Carrer de Balmes, 180",
    "sg:city":"Barcelona",
    "sg:orig_category":"M\u00c9dicos: Psiquiatr\u00cda",
    "sg:phone":"+34 932 37 19 84",
    "sg:postcode":"08006",
    "sg:province":"Barcelona",
    "wof:name":"Gonzalez Monclus Enrique",
    "wof:placetype":"venue"
},
  "geometry": {"coordinates":[2.1537210941,41.3963127136],"type":"Point"}
}