{
  "type": "Feature",
  "properties": {
    "iso:country":"ES",
    "sg:address":"C/ Jeremias Pastor Perez, 28",
    "sg:city":"Elche",
    "sg:orig_category":"Muebles Y Accesorios Para Cocinas Y Cuartos De Ba\u00d1o (al Por Menor)",
    "sg:phone":"+34 965 46 75 68",
    "sg:postcode":"03206",
    "sg:province":"Alicante",
    "wof:name":"Muebles De Cocina Lozoya S.l.",
    "wof:placetype":"venue"
},
  "geometry": {"coordinates":[-0.7115200162,38.2769317627],"type":"Point"}
}