{
  "type": "Feature",
  "properties": {
    "iso:country":"ES",
    "sg:address":"Rua Jose Antonio, 30",
    "sg:city":"Ordes",
    "sg:orig_category":"Reposter\u00cdas",
    "sg:phone":"+34 981 68 27 43",
    "sg:postcode":"15680",
    "sg:province":"La Coru\u00f1a",
    "wof:name":"Fraga Blanco Angel Manuel",
    "wof:placetype":"venue"
},
  "geometry": {"coordinates":[-8.4081506729,43.0758972168],"type":"Point"}
}