{
  "type": "Feature",
  "properties": {
    "iso:country":"ES",
    "sg:address":"Rond Espanya (d'), 27",
    "sg:city":"Sueca",
    "sg:orig_category":"Carnicer\u00cdas, Carnicer\u00cdas",
    "sg:phone":"+34 961 70 03 53",
    "sg:postcode":"46410",
    "sg:province":"Valencia",
    "wof:name":"Osca  Cristina",
    "wof:placetype":"venue"
},
  "geometry": {"coordinates":[-0.3076440096,39.2027435303],"type":"Point"}
}