{
  "type": "Feature",
  "properties": {
    "iso:country":"ES",
    "sg:address":"La Bargana, 5",
    "sg:city":"Tolivia",
    "sg:orig_category":"Explotaci\u00d3n De Minas",
    "sg:phone":"+34 985 61 52 93",
    "sg:postcode":"33986",
    "sg:province":"Asturias",
    "wof:name":"Gonzalez Garcia Samuel",
    "wof:placetype":"venue"
},
  "geometry": {"coordinates":[-5.5768809319,43.222114563],"type":"Point"}
}