{
  "type": "Feature",
  "properties": {
    "iso:country":"ES",
    "sg:address":"Polig. Lalin Dos Mil, 1",
    "sg:city":"Donsion",
    "sg:orig_category":"Empresas De Desmonte",
    "sg:phone":"+34 986 79 42 93",
    "sg:postcode":"36519",
    "sg:province":"Pontevedra",
    "wof:name":"Excavaciones M. E. Mejuto S.l.",
    "wof:placetype":"venue"
},
  "geometry": {"coordinates":[-8.1627492905,42.5798492432],"type":"Point"}
}