{
  "type": "Feature",
  "properties": {
    "addr:full":"Calle de Diamante, 5 Madrid Madrid 28021",
    "addr:housenumber":"5",
    "addr:postcode":"28021",
    "addr:street":"Calle De Diamante",
    "iso:country":"ES",
    "sg:address":"Calle de Diamante, 5",
    "sg:city":"Madrid",
    "sg:orig_category":"Centros Comerciales Y Grandes Tiendas",
    "sg:phone":"+34 915 05 29 13",
    "sg:postcode":"28021",
    "sg:province":"Madrid",
    "wof:name":"Gonzalez Y Pulido S.l.",
    "wof:placetype":"venue"
},
  "geometry": {"coordinates":[-3.6883230209,40.3536987305],"type":"Point"}
}