{
  "type": "Feature",
  "properties": {
    "addr:full":"Calle de Natalio Rivas, S/n Gualchos Granada 18614",
    "addr:housenumber":"s / n",
    "addr:postcode":"18614",
    "addr:street":"Calle De Natalio Rivas",
    "iso:country":"ES",
    "sg:address":"Calle de Natalio Rivas, S/n",
    "sg:city":"Gualchos",
    "sg:orig_category":"Iglesia Cat\u00d3lica",
    "sg:phone":"+34 958 65 62 47",
    "sg:postcode":"18614",
    "sg:province":"Granada",
    "wof:name":"Parroquia De San Miguel Arcangel",
    "wof:placetype":"venue"
},
  "geometry": {"coordinates":[-3.3892309666,36.744178772],"type":"Point"}
}