{
  "type": "Feature",
  "properties": {
    "addr:full":"Calle de Rey (del), 3 Fuente Palmera C\u00f3rdoba 14120",
    "addr:housenumber":"3",
    "addr:postcode":"14120",
    "addr:street":"Calle De Rey Del",
    "iso:country":"ES",
    "sg:address":"Calle de Rey (del), 3",
    "sg:city":"Fuente Palmera",
    "sg:orig_category":"Urbanistas",
    "sg:phone":"+34 957 63 80 11",
    "sg:postcode":"14120",
    "sg:province":"C\u00f3rdoba",
    "wof:name":"Prorecol S.l.",
    "wof:placetype":"venue"
},
  "geometry": {"coordinates":[-5.1040039062,37.7032585144],"type":"Point"}
}