{
  "type": "Feature",
  "properties": {
    "addr:full":"Calle de Alboraya, 61 Valencia Valencia 46010",
    "addr:housenumber":"61",
    "addr:postcode":"46010",
    "addr:street":"Calle De Alboraya",
    "iso:country":"ES",
    "sg:address":"Calle de Alboraya, 61",
    "sg:city":"Valencia",
    "sg:orig_category":"Electricidad: Instaladores",
    "sg:phone":"+34 963 69 92 01",
    "sg:postcode":"46010",
    "sg:province":"Valencia",
    "wof:name":"Sancho Iba\u00f1ez Juan",
    "wof:placetype":"venue"
},
  "geometry": {"coordinates":[-0.3685480058,39.4859542847],"type":"Point"}
}