{
  "type": "Feature",
  "properties": {
    "iso:country":"ES",
    "sg:address":"Calle de Elena Tamarit, 3",
    "sg:city":"Torrent",
    "sg:orig_category":"Sindicatos De Trabajadores",
    "sg:phone":"+34 961 58 07 83",
    "sg:postcode":"46900",
    "sg:province":"Valencia",
    "wof:name":"Comissions Obreres Del Pais Valencia",
    "wof:placetype":"venue"
},
  "geometry": {"coordinates":[-0.47042799,39.4322052002],"type":"Point"}
}