{
  "type": "Feature",
  "properties": {
    "addr:full":"Calle de Avila, 35 Madrid Madrid 28020",
    "addr:housenumber":"35",
    "addr:postcode":"madrid;28020",
    "addr:street":"Calle De Avila",
    "iso:country":"ES",
    "sg:address":"Calle de Avila, 35",
    "sg:city":"Madrid",
    "sg:orig_category":"Loter\u00cda Y T\u00d3mbola",
    "sg:phone":"+34 915 70 27 62",
    "sg:postcode":"28020",
    "sg:province":"Madrid",
    "wof:name":"Garcia Montes Maria Pilar",
    "wof:placetype":"venue"
},
  "geometry": {"coordinates":[-3.699504137,40.4526062012],"type":"Point"}
}