{
  "type": "Feature",
  "properties": {
    "iso:country":"ES",
    "sg:address":"Calle de Ntra. Sra. De Rocamador, 2",
    "sg:city":"Palencia",
    "sg:orig_category":"Sociedades, Compa\u00d1\u00cdas Aseguradoras",
    "sg:phone":"+34 979 71 17 56",
    "sg:postcode":"34002",
    "sg:province":"Palencia",
    "wof:name":"Gomez Ule Enrique",
    "wof:placetype":"venue"
},
  "geometry": {"coordinates":[-4.5289888382,42.0044212341],"type":"Point"}
}