{
  "type": "Feature",
  "properties": {
    "addr:full":"Rua Xeneral Gutierrez Mellado, 11 Pontevedra Pontevedra 36001",
    "addr:housenumber":"11",
    "addr:postcode":"36001",
    "addr:street":"Rua Xeneral;Mellado",
    "iso:country":"ES",
    "sg:address":"Rua Xeneral Gutierrez Mellado, 11",
    "sg:city":"Pontevedra",
    "sg:orig_category":"Bancos",
    "sg:phone":"+34 986 86 60 15",
    "sg:postcode":"36001",
    "sg:province":"Pontevedra",
    "wof:name":"Banco Espa\u00f1ol De Credito S.a.",
    "wof:placetype":"venue"
},
  "geometry": {"coordinates":[-8.6459665298,42.4305114746],"type":"Point"}
}