{
  "type": "Feature",
  "properties": {
    "addr:full":"Calle de San Sebastian, 2 Alfacar Granada 18170",
    "addr:housenumber":"2",
    "addr:postcode":"18170",
    "addr:street":"Calle De San Sebastian",
    "iso:country":"ES",
    "sg:address":"Calle de San Sebastian, 2",
    "sg:city":"Alfacar",
    "sg:orig_category":"Asesor\u00cda Sobre Comunicaci\u00d3n De Empresas",
    "sg:phone":"+34 958 54 06 37",
    "sg:postcode":"18170",
    "sg:province":"Granada",
    "wof:name":"Asesoria Alfaguara Sl",
    "wof:placetype":"venue"
},
  "geometry": {"coordinates":[-3.5656173229,37.2388420105],"type":"Point"}
}