{
  "type": "Feature",
  "properties": {
    "addr:full":"Calle de Melilla, 11 Alcala Henares Madrid 28805",
    "addr:housenumber":"11",
    "addr:postcode":"28805",
    "addr:street":"Calle De Melilla",
    "iso:country":"ES",
    "sg:address":"Calle de Melilla, 11",
    "sg:city":"Alcala Henares",
    "sg:orig_category":"Fabricaci\u00d3n, Venta, Instalaci\u00d3n De R\u00d3tulos, De R\u00d3tulos Luminosos",
    "sg:phone":"+34 918 82 28 31",
    "sg:postcode":"28805",
    "sg:province":"Madrid",
    "wof:name":"Nadador Lopez David",
    "wof:placetype":"venue"
},
  "geometry": {"coordinates":[-3.3403890133,40.4931602478],"type":"Point"}
}