{
  "type": "Feature",
  "properties": {
    "addr:full":"Carr Peressall, 15 Tremp Lleida 25620",
    "addr:housenumber":"15",
    "addr:postcode":"25620",
    "addr:street":"Carr Peressall",
    "iso:country":"ES",
    "sg:address":"Carr Peressall, 15",
    "sg:city":"Tremp",
    "sg:orig_category":"Librer\u00cdas",
    "sg:phone":"+34 973 65 02 08",
    "sg:postcode":"25620",
    "sg:province":"Lleida",
    "wof:name":"Mirabet Canut Maria Carmen",
    "wof:placetype":"venue"
},
  "geometry": {"coordinates":[0.8959389925,42.1667175293],"type":"Point"}
}