{
  "type": "Feature",
  "properties": {
    "iso:country":"ES",
    "sg:address":"La Ribera, 4",
    "sg:city":"Burgos",
    "sg:orig_category":"Rectificaci\u00d3n, Mecanizado, Fresado",
    "sg:phone":"+34 947 48 49 24",
    "sg:postcode":"09007",
    "sg:province":"Burgos",
    "wof:name":"Talleres El Polo S. A.",
    "wof:placetype":"venue"
},
  "geometry": {"coordinates":[-3.6497778893,42.3492851257],"type":"Point"}
}