{
  "type": "Feature",
  "properties": {
    "iso:country":"ES",
    "sg:address":"Av Catalunya, 344",
    "sg:city":"Aldea",
    "sg:orig_category":"Ropa Para Se\u00d1oras Y Caballeros (al Por Menor)",
    "sg:phone":"+34 977 45 07 89",
    "sg:postcode":"43896",
    "sg:province":"Tarragona",
    "wof:name":"Seret",
    "wof:placetype":"venue"
},
  "geometry": {"coordinates":[0.6258090138,40.7493400574],"type":"Point"}
}