{
  "type": "Feature",
  "properties": {
    "addr:full":"Ctra Lleida, 14 Ponts Lleida 25740",
    "addr:housenumber":"14",
    "addr:postcode":"25740",
    "addr:street":"Ctra Lleida",
    "iso:country":"ES",
    "sg:address":"Ctra Lleida, 14",
    "sg:city":"Ponts",
    "sg:orig_category":"Florister\u00cdas",
    "sg:phone":"+34 973 46 03 37",
    "sg:postcode":"25740",
    "sg:province":"Lleida",
    "wof:name":"Sala Mallol Mariano",
    "wof:placetype":"venue"
},
  "geometry": {"coordinates":[1.1860250235,41.9162902832],"type":"Point"}
}