{
  "type": "Feature",
  "properties": {
    "iso:country":"ES",
    "sg:address":"Calle de Sargento Provisional, 16",
    "sg:city":"Coru\u00d1a",
    "sg:orig_category":"Florister\u00cdas",
    "sg:phone":"+34 981 24 16 61",
    "sg:postcode":"15007",
    "sg:province":"La Coru\u00f1a",
    "wof:name":"Lopez Calvi\u00f1o Alicia",
    "wof:placetype":"venue"
},
  "geometry": {"coordinates":[-8.4157457352,43.3571128845],"type":"Point"}
}