{
  "type": "Feature",
  "properties": {
    "iso:country":"ES",
    "sg:address":"Carr Major, 113",
    "sg:city":"Jonquera",
    "sg:orig_category":"Alimentaci\u00d3n General (al Por Menor)",
    "sg:phone":"+34 972 55 49 65",
    "sg:postcode":"17700",
    "sg:province":"Girona",
    "wof:name":"Vazquez Corento C.b.",
    "wof:placetype":"venue"
},
  "geometry": {"coordinates":[2.8718750477,42.4159698486],"type":"Point"}
}