{
  "type": "Feature",
  "properties": {
    "addr:full":"Calle de Catamaran, 2 Madrid Madrid 28042",
    "addr:housenumber":"2",
    "addr:postcode":"28042",
    "addr:street":"Calle De Catamaran",
    "iso:country":"ES",
    "sg:address":"Calle de Catamaran, 2",
    "sg:city":"Madrid",
    "sg:orig_category":"Bancos",
    "sg:phone":"+34 913 20 83 21",
    "sg:postcode":"28042",
    "sg:province":"Madrid",
    "wof:name":"Banco Popular Espa\u00f1ol S.a.",
    "wof:placetype":"venue"
},
  "geometry": {"coordinates":[-3.5944809914,40.4512481689],"type":"Point"}
}