{
  "type": "Feature",
  "properties": {
    "iso:country":"ES",
    "sg:address":"Grup Murueta Torre Auzunea, S/n",
    "sg:city":"Durango",
    "sg:orig_category":"Caf\u00c9s, Bares, Cervecer\u00cdas",
    "sg:phone":"+34 946 81 64 47",
    "sg:postcode":"48200",
    "sg:province":"Vizcaya",
    "wof:name":"Gestion Hosteleria Navarra S.l.",
    "wof:placetype":"venue"
},
  "geometry": {"coordinates":[-2.6326551437,43.1690673828],"type":"Point"}
}