{
  "type": "Feature",
  "properties": {
    "iso:country":"ES",
    "sg:address":"Calle de Isabel Larra\u00d1aga, 28",
    "sg:city":"Fuensalida",
    "sg:orig_category":"Panader\u00cdas, Panader\u00cdas",
    "sg:phone":"+34 925 78 41 16",
    "sg:postcode":"45510",
    "sg:province":"Toledo",
    "wof:name":"Lopez Montes Angel",
    "wof:placetype":"venue"
},
  "geometry": {"coordinates":[-4.2086257935,40.0503883362],"type":"Point"}
}