{
  "type": "Feature",
  "properties": {
    "iso:country":"ES",
    "sg:address":"Avda Algorta, 37",
    "sg:city":"Algorta",
    "sg:orig_category":"Plomeros",
    "sg:phone":"+34 944 60 34 55",
    "sg:postcode":"48992",
    "sg:province":"Vizcaya",
    "wof:name":"Fontaneria Getxofont S.a.l.",
    "wof:placetype":"venue"
},
  "geometry": {"coordinates":[-3.0099749565,43.346572876],"type":"Point"}
}