{
  "type": "Feature",
  "properties": {
    "iso:country":"ES",
    "sg:address":"Carrer de Cami Reial, S/n",
    "sg:city":"Vendrell",
    "sg:orig_category":"Centros M\u00c9dicos Y Sociales, Dispensarios",
    "sg:phone":"+34 977 66 33 56",
    "sg:postcode":"43700",
    "sg:province":"Tarragona",
    "wof:name":"Instituto Pedro Mata S.a.",
    "wof:placetype":"venue"
},
  "geometry": {"coordinates":[1.5310800076,41.2140846252],"type":"Point"}
}