{
  "type": "Feature",
  "properties": {
    "addr:full":"Calle de Santa Teresa, 27 Mislata Valencia 46920",
    "addr:housenumber":"27",
    "addr:postcode":"46920",
    "addr:street":"Calle De Santa Teresa",
    "iso:country":"ES",
    "sg:address":"Calle de Santa Teresa, 27",
    "sg:city":"Mislata",
    "sg:orig_category":"Agencias De Viajes",
    "sg:phone":"+34 963 13 63 30",
    "sg:postcode":"46920",
    "sg:province":"Valencia",
    "sg:website":"www.viajeselcorteingles.com",
    "wof:name":"Viajes El Corte Ingles S.a.",
    "wof:placetype":"venue"
},
  "geometry": {"coordinates":[-0.4180090129,39.4742012024],"type":"Point"}
}