{
  "type": "Feature",
  "properties": {
    "addr:full":"Czad Oleta De, 35 Donostia-san Sebastian Guip\u00f9zcoa 20017",
    "addr:housenumber":"35",
    "addr:postcode":"20017",
    "addr:street":"Czad",
    "iso:country":"ES",
    "sg:address":"Czad Oleta De, 35",
    "sg:city":"Donostia-san Sebastian",
    "sg:orig_category":"Rejas Y Cortinas Met\u00c1licas",
    "sg:phone":"+34 943 35 17 28",
    "sg:postcode":"20017",
    "sg:province":"Guip\u00f9zcoa",
    "wof:name":"Lijados Y Barnizados Jesus Suarez,sl",
    "wof:placetype":"venue"
},
  "geometry": {"coordinates":[-1.9294910431,43.3208312988],"type":"Point"}
}