{
  "type": "Feature",
  "properties": {
    "addr:full":"Calle de Prado, 7 Valladolid Valladolid 47003",
    "addr:housenumber":"7",
    "addr:postcode":"47003",
    "addr:street":"Calle De Prado",
    "iso:country":"ES",
    "sg:address":"Calle de Prado, 7",
    "sg:city":"Valladolid",
    "sg:orig_category":"Asociaciones Humanitarias, De Cooperaci\u00d3n, De Acci\u00d3n Social",
    "sg:phone":"+34 983 32 01 16",
    "sg:postcode":"47003",
    "sg:province":"Valladolid",
    "wof:name":"Feaps Castilla Y Leon",
    "wof:placetype":"venue"
},
  "geometry": {"coordinates":[-4.7210259438,41.6557540894],"type":"Point"}
}