{
  "type": "Feature",
  "properties": {
    "iso:country":"ES",
    "sg:address":"Carrer de Sant Magi, 81",
    "sg:city":"Palma",
    "sg:orig_category":"Inmobiliaria (agencias)",
    "sg:phone":"+34 971 22 07 38",
    "sg:postcode":"07013",
    "sg:province":"Islas Baleares",
    "wof:name":"La Lonja Inmuebles S.l",
    "wof:placetype":"venue"
},
  "geometry": {"coordinates":[2.6354379654,39.5703620911],"type":"Point"}
}