{
  "type": "Feature",
  "properties": {
    "addr:full":"Calle de Sierra De Agullent, 7 Valencia Valencia 46015",
    "addr:housenumber":"7",
    "addr:postcode":"46015",
    "addr:street":"Calle De Sierra De Agullent",
    "iso:country":"ES",
    "sg:address":"Calle de Sierra De Agullent, 7",
    "sg:city":"Valencia",
    "sg:orig_category":"Plomeros",
    "sg:phone":"+34 963 46 30 26",
    "sg:postcode":"46015",
    "sg:province":"Valencia",
    "wof:name":"Ernesto Y Ricardo S.l.",
    "wof:placetype":"venue"
},
  "geometry": {"coordinates":[-0.3967100084,39.4945487976],"type":"Point"}
}