{
  "type": "Feature",
  "properties": {
    "iso:country":"ES",
    "sg:address":"Pol. Ind. Sia-sta. Barbara, S/n",
    "sg:city":"Lugones",
    "sg:orig_category":"Agencias Y Asesores De Publicidad",
    "sg:phone":"+34 985 26 21 37",
    "sg:postcode":"33420",
    "sg:province":"Asturias",
    "wof:name":"Chiwake Agencia De Publicidad S.l.l.",
    "wof:placetype":"venue"
},
  "geometry": {"coordinates":[-5.8129429817,43.4078216553],"type":"Point"}
}