{
  "type": "Feature",
  "properties": {
    "addr:full":"Ctra. Extremadura, Km. 0029,0 Navalcarnero Madrid 28600",
    "addr:postcode":"28600",
    "addr:street":"Ctra. Extremadura Km. 0029,0",
    "iso:country":"ES",
    "sg:address":"Ctra. Extremadura, Km. 0029,0",
    "sg:city":"Navalcarnero",
    "sg:orig_category":"Aluminio Y Aleaciones (producci\u00d3n, Transformaci\u00d3n, Negocio)",
    "sg:phone":"+34 918 11 00 00",
    "sg:postcode":"28600",
    "sg:province":"Madrid",
    "wof:name":"Cromados Garcia S.l.",
    "wof:placetype":"venue"
},
  "geometry": {"coordinates":[-3.977684021,40.2939796448],"type":"Point"}
}