{
  "type": "Feature",
  "properties": {
    "addr:full":"Calle de Profesor Waksman, 12 Madrid Madrid 28036",
    "addr:housenumber":"12",
    "addr:postcode":"madrid;28036",
    "addr:street":"Calle De Profesor Waksman",
    "iso:country":"ES",
    "sg:address":"Calle de Profesor Waksman, 12",
    "sg:city":"Madrid",
    "sg:orig_category":"Vinos Y Licores (venta Al Por Menor)",
    "sg:phone":"+34 913 44 04 73",
    "sg:postcode":"28036",
    "sg:province":"Madrid",
    "wof:name":"Bodegas Rincon Privado S.l",
    "wof:placetype":"venue"
},
  "geometry": {"coordinates":[-3.6877450943,40.4558677673],"type":"Point"}
}