{
  "type": "Feature",
  "properties": {
    "addr:full":"Calle de Quitapenas, 31 Malaga M\u00e1laga 29017",
    "addr:housenumber":"31",
    "addr:postcode":"29017",
    "addr:street":"Calle De Quitapenas;Ma\u0301Laga",
    "iso:country":"ES",
    "sg:address":"Calle de Quitapenas, 31",
    "sg:city":"Malaga",
    "sg:orig_category":"Molduras, Junquillos, Listones Y Molduras Perforadas",
    "sg:phone":"+34 952 29 43 17",
    "sg:postcode":"29017",
    "sg:province":"M\u00e1laga",
    "wof:name":"Cantarero Moreno Carmen",
    "wof:placetype":"venue"
},
  "geometry": {"coordinates":[-4.3628191948,36.71925354],"type":"Point"}
}