{
  "type": "Feature",
  "properties": {
    "addr:full":"Av Pau Claris, 10 Seu D'urgell Lleida 25700",
    "addr:housenumber":"10",
    "addr:postcode":"25700",
    "addr:street":"Av Pau Claris",
    "iso:country":"ES",
    "sg:address":"Av Pau Claris, 10",
    "sg:city":"Seu D'urgell",
    "sg:orig_category":"Fabricaci\u00d3n, Importaci\u00d3n, Venta De Material De Telefon\u00cda, Peritelefon\u00cda",
    "sg:phone":"+34 973 35 51 91",
    "sg:postcode":"25700",
    "sg:province":"Lleida",
    "wof:name":"Bt Espa\u00d1a Compa\u00d1ia De Servicios Globales De Telecomunicaciones S.a.u.",
    "wof:placetype":"venue"
},
  "geometry": {"coordinates":[0.6219109893,41.6222572327],"type":"Point"}
}