{
  "type": "Feature",
  "properties": {
    "iso:country":"ES",
    "sg:address":"Calle de Mayor, 24",
    "sg:city":"Dos-torres",
    "sg:orig_category":"Confecci\u00d3n (fabricaci\u00d3n, Al Por Mayor)",
    "sg:phone":"+34 957 13 41 27",
    "sg:postcode":"14460",
    "sg:province":"C\u00f3rdoba",
    "wof:name":"Cooperativa De Confeccion Santa Lucia",
    "wof:placetype":"venue"
},
  "geometry": {"coordinates":[-4.8963479996,38.4440345764],"type":"Point"}
}