{
  "type": "Feature",
  "properties": {
    "addr:full":"Av Mediterrani, 42 Poblenou Barcelona 08397",
    "addr:housenumber":"42",
    "addr:postcode":"08397",
    "addr:street":"Av Mediterrani",
    "iso:country":"ES",
    "sg:address":"Av Mediterrani, 42",
    "sg:city":"Poblenou",
    "sg:orig_category":"Empresas De Carpinter\u00cda",
    "sg:phone":"+34 937 66 21 42",
    "sg:postcode":"08397",
    "sg:province":"Barcelona",
    "wof:name":"Tubert Laborel Jordi",
    "wof:placetype":"venue"
},
  "geometry": {"coordinates":[2.6730880737,41.6189117432],"type":"Point"}
}