{
  "type": "Feature",
  "properties": {
    "addr:full":"Ctra. Fuentepelayo, 13 Pinarnegrillo Segovia 40294",
    "addr:housenumber":"13",
    "addr:postcode":"40294",
    "addr:street":"Ctra. Fuentepelayo;Segovia",
    "iso:country":"ES",
    "sg:address":"Ctra. Fuentepelayo, 13",
    "sg:city":"Pinarnegrillo",
    "sg:orig_category":"Alquiler De Veh\u00cdculos: Turismos Y Utilitarios",
    "sg:phone":"+34 921 57 40 45",
    "sg:postcode":"40294",
    "sg:province":"Segovia",
    "wof:name":"Sangobus",
    "wof:placetype":"venue"
},
  "geometry": {"coordinates":[-4.2081098557,41.1919326782],"type":"Point"}
}