{
  "type": "Feature",
  "properties": {
    "addr:full":"Calle de Zankoeta, 7 Bilbao Vizcaya 48013",
    "addr:housenumber":"7",
    "addr:postcode":"48013",
    "addr:street":"Calle De Zankoeta",
    "iso:country":"ES",
    "sg:address":"Calle de Zankoeta, 7",
    "sg:city":"Bilbao",
    "sg:orig_category":"Lavado, Limpieza De Veh\u00cdculos",
    "sg:phone":"+34 944 42 47 34",
    "sg:postcode":"48013",
    "sg:province":"Vizcaya",
    "wof:name":"Garaje Centro",
    "wof:placetype":"venue"
},
  "geometry": {"coordinates":[-2.946434021,43.2583198547],"type":"Point"}
}