{
  "type": "Feature",
  "properties": {
    "addr:full":"Avda General Sanjurjo, 36 Coru\u00d1a La Coru\u00f1a 15006",
    "addr:housenumber":"36",
    "addr:postcode":"15006",
    "addr:street":"Avda General Sanjurjo;Corun\u0303A",
    "iso:country":"ES",
    "sg:address":"Avda General Sanjurjo, 36",
    "sg:city":"Coru\u00d1a",
    "sg:orig_category":"Laboratorios Farmac\u00c9uticos",
    "sg:phone":"+34 981 13 17 93",
    "sg:postcode":"15006",
    "sg:province":"La Coru\u00f1a",
    "wof:name":"Canzobre Vazquez Jose Maria",
    "wof:placetype":"venue"
},
  "geometry": {"coordinates":[-8.4017152786,43.35572052],"type":"Point"}
}