{
  "type": "Feature",
  "properties": {
    "iso:country":"ES",
    "sg:address":"Calle de Barrionuevo, 4",
    "sg:city":"Catedral",
    "sg:orig_category":"Panader\u00cdas, Panader\u00cdas",
    "sg:phone":"+34 968 21 64 30",
    "sg:postcode":"30001",
    "sg:province":"Murcia",
    "wof:name":"Maite Murcia S.l.",
    "wof:placetype":"venue"
},
  "geometry": {"coordinates":[-1.1298867464,37.9834747314],"type":"Point"}
}