{
  "type": "Feature",
  "properties": {
    "iso:country":"ES",
    "sg:address":"Bloc Filipinas, S/n",
    "sg:city":"Sant Pere I Sant Pau",
    "sg:orig_category":"Electricidad: Instaladores",
    "sg:phone":"+34 977 20 16 39",
    "sg:postcode":"43007",
    "sg:province":"Tarragona",
    "wof:name":"Electricidad Y Fontaneria A.g.c. S.l.",
    "wof:placetype":"venue"
},
  "geometry": {"coordinates":[1.2959779501,41.1377334595],"type":"Point"}
}