{
  "type": "Feature",
  "properties": {
    "iso:country":"ES",
    "sg:address":"Cno. De La Mata Grande, S/n",
    "sg:city":"Antequera",
    "sg:orig_category":"Asociaciones Y Clubs Deportivos",
    "sg:phone":"+34 952 70 36 58",
    "sg:postcode":"29200",
    "sg:province":"M\u00e1laga",
    "wof:name":"Club Matagrande S.a.",
    "wof:placetype":"venue"
},
  "geometry": {"coordinates":[-4.5636138916,37.0203018188],"type":"Point"}
}