{
  "type": "Feature",
  "properties": {
    "iso:country":"ES",
    "sg:address":"Ctra De Vistabella, 15",
    "sg:city":"Atzeneta Maestrat",
    "sg:orig_category":"Empresas De Pintura Y Revestimientos",
    "sg:phone":"+34 964 37 04 58",
    "sg:postcode":"12132",
    "sg:province":"Castell\u00f3n",
    "wof:name":"Centelles Garcia Francisco",
    "wof:placetype":"venue"
},
  "geometry": {"coordinates":[-0.1716389954,40.2210960388],"type":"Point"}
}