{
  "type": "Feature",
  "properties": {
    "addr:full":"Av Montgo, 23 Escala Girona 17130",
    "addr:housenumber":"23",
    "addr:postcode":"17130",
    "addr:street":"Av Montgo",
    "iso:country":"ES",
    "sg:address":"Av Montgo, 23",
    "sg:city":"Escala",
    "sg:orig_category":"Carnicer\u00cdas, Carnicer\u00cdas",
    "sg:phone":"+34 972 77 27 01",
    "sg:postcode":"17130",
    "sg:province":"Girona",
    "wof:name":"Franch Antoner Juan",
    "wof:placetype":"venue"
},
  "geometry": {"coordinates":[3.1384150982,42.1142158508],"type":"Point"}
}