{
  "type": "Feature",
  "properties": {
    "addr:full":"Av Pais Valencia, 15 Elche Alicante 03201",
    "addr:housenumber":"15",
    "addr:postcode":"03201",
    "addr:street":"Av Pais Valencia",
    "iso:country":"ES",
    "sg:address":"Av Pais Valencia, 15",
    "sg:city":"Elche",
    "sg:orig_category":"Pr\u00c9stamos Personales E Hipotecarios",
    "sg:phone":"+34 966 66 55 67",
    "sg:postcode":"03201",
    "sg:province":"Alicante",
    "wof:name":"Lapuente Madrid Maria Isabel",
    "wof:placetype":"venue"
},
  "geometry": {"coordinates":[-0.7006170154,38.2666664124],"type":"Point"}
}