{
  "type": "Feature",
  "properties": {
    "addr:full":"Pl. Los Fueros, 11 Estella Navarra 31200",
    "addr:housenumber":"11",
    "addr:postcode":"31200",
    "addr:street":"Los Fueros",
    "iso:country":"ES",
    "sg:address":"Pl. Los Fueros, 11",
    "sg:city":"Estella",
    "sg:orig_category":"Electrodom\u00c9sticos (al Por Menor)",
    "sg:phone":"+34 948 55 43 10",
    "sg:postcode":"31200",
    "sg:province":"Navarra",
    "wof:name":"Gil Santesteban Samuel",
    "wof:placetype":"venue"
},
  "geometry": {"coordinates":[-2.0317430496,42.6723861694],"type":"Point"}
}