{
  "type": "Feature",
  "properties": {
    "addr:full":"Calle de San Jose, 77 Yecla Murcia 30510",
    "addr:housenumber":"77",
    "addr:postcode":"30510",
    "addr:street":"Calle De San",
    "iso:country":"ES",
    "sg:address":"Calle de San Jose, 77",
    "sg:city":"Yecla",
    "sg:orig_category":"Electrodom\u00c9sticos (al Por Menor)",
    "sg:phone":"+34 968 75 23 67",
    "sg:postcode":"30510",
    "sg:province":"Murcia",
    "wof:name":"E.d.o. Electrodomesticos S.l.",
    "wof:placetype":"venue"
},
  "geometry": {"coordinates":[-1.1113239527,38.6126785278],"type":"Point"}
}