{
  "type": "Feature",
  "properties": {
    "addr:full":"Avda Argentina, 5 Maracena Granada 18200",
    "addr:housenumber":"5",
    "addr:postcode":"18200",
    "addr:street":"Avda Argentina",
    "iso:country":"ES",
    "sg:address":"Avda Argentina, 5",
    "sg:city":"Maracena",
    "sg:orig_category":"Mec\u00c1nico Del Autom\u00d3vil",
    "sg:phone":"+34 958 42 12 82",
    "sg:postcode":"18200",
    "sg:province":"Granada",
    "wof:name":"Tallon Serrano Manuel",
    "wof:placetype":"venue"
},
  "geometry": {"coordinates":[-3.6394989491,37.2092018127],"type":"Point"}
}