{
  "type": "Feature",
  "properties": {
    "iso:country":"ES",
    "sg:address":"Mcdo. Panaderos, S/n",
    "sg:city":"Valladolid",
    "sg:orig_category":"Carnicer\u00cdas, Carnicer\u00cdas",
    "sg:phone":"+34 983 20 36 32",
    "sg:postcode":"47004",
    "sg:province":"Valladolid",
    "wof:name":"Fernandez Prieto Jose Miguel",
    "wof:placetype":"venue"
},
  "geometry": {"coordinates":[-4.7222938538,41.6443405151],"type":"Point"}
}