{
  "type": "Feature",
  "properties": {
    "iso:country":"ES",
    "sg:address":"Calle de Huelva, 12",
    "sg:city":"Zubia",
    "sg:orig_category":"Plomeros",
    "sg:phone":"+34 958 59 07 29",
    "sg:postcode":"18140",
    "sg:province":"Granada",
    "wof:name":"Antequera Cuadros Manuel",
    "wof:placetype":"venue"
},
  "geometry": {"coordinates":[-3.6242845058,37.1402511597],"type":"Point"}
}