{
  "type": "Feature",
  "properties": {
    "addr:full":"Avda General Peron, 32 Madrid Madrid 28020",
    "addr:housenumber":"32",
    "addr:postcode":"madrid;28020",
    "addr:street":"Avda General Peron",
    "iso:country":"ES",
    "sg:address":"Avda General Peron, 32",
    "sg:city":"Madrid",
    "sg:orig_category":"Ingenier\u00cda, Centros De Estudios (diversos)",
    "sg:phone":"+34 914 17 48 80",
    "sg:postcode":"28020",
    "sg:province":"Madrid",
    "wof:name":"Spx Cooling Technologies Iberica S. L.",
    "wof:placetype":"venue"
},
  "geometry": {"coordinates":[-3.6931860447,40.4521408081],"type":"Point"}
}