{
  "type": "Feature",
  "properties": {
    "iso:country":"ES",
    "sg:address":"Calle de Artesanos, 17",
    "sg:city":"Ecija",
    "sg:orig_category":"Carnes De Carnicer\u00cda (al Por Mayor)",
    "sg:phone":"+34 955 90 19 53",
    "sg:postcode":"41400",
    "sg:province":"Sevilla",
    "wof:name":"Productos Derivados Del Cerdo Parra S.l.",
    "wof:placetype":"venue"
},
  "geometry": {"coordinates":[-5.1015224457,37.4861946106],"type":"Point"}
}