{
  "type": "Feature",
  "properties": {
    "iso:country":"ES",
    "sg:address":"Calle de Vitoria, 29",
    "sg:city":"Burgos",
    "sg:orig_category":"Arqueolog\u00cda Y Patrimonio Cultural",
    "sg:phone":"+34 947 04 14 99",
    "sg:postcode":"09004",
    "sg:province":"Burgos",
    "wof:name":"2b Arqueologia Y Gestion De Patrimonio Sl.",
    "wof:placetype":"venue"
},
  "geometry": {"coordinates":[-3.695788,42.341843],"type":"Point"}
}