{
  "type": "Feature",
  "properties": {
    "addr:full":"Calle de Beato Diego De Cadiz, 18 Cadiz C\u00e1diz 11004",
    "addr:housenumber":"18",
    "addr:postcode":"11004",
    "addr:street":"Calle De Beato Diego De Cadiz",
    "iso:country":"ES",
    "sg:address":"Calle de Beato Diego De Cadiz, 18",
    "sg:city":"Cadiz",
    "sg:orig_category":"Bares, Piano",
    "sg:phone":"+34 956 21 26 97",
    "sg:postcode":"11004",
    "sg:province":"C\u00e1diz",
    "wof:name":"Torres Lopez Antonio",
    "wof:placetype":"venue"
},
  "geometry": {"coordinates":[-6.2940292358,36.5341911316],"type":"Point"}
}