{
  "type": "Feature",
  "properties": {
    "iso:country":"ES",
    "sg:address":"Calle de Juan Ramon Jimenez, 14",
    "sg:city":"Sevilla",
    "sg:orig_category":"Farmacias",
    "sg:phone":"+34 954 45 19 08",
    "sg:postcode":"41011",
    "sg:province":"Sevilla",
    "wof:name":"Gonzalez Molina Mercedes",
    "wof:placetype":"venue"
},
  "geometry": {"coordinates":[-5.9987549782,37.3740272522],"type":"Point"}
}