{
  "type": "Feature",
  "properties": {
    "addr:full":"Calle de San Sebastian, 11 Campillos M\u00e1laga 29320",
    "addr:housenumber":"11",
    "addr:postcode":"29320",
    "addr:street":"Calle De San Sebastian",
    "iso:country":"ES",
    "sg:address":"Calle de San Sebastian, 11",
    "sg:city":"Campillos",
    "sg:orig_category":"Bancos",
    "sg:phone":"+34 952 72 27 00",
    "sg:postcode":"29320",
    "sg:province":"M\u00e1laga",
    "wof:name":"Banco De Andalucia",
    "wof:placetype":"venue"
},
  "geometry": {"coordinates":[-4.8587350845,37.0415611267],"type":"Point"}
}