{
  "type": "Feature",
  "properties": {
    "addr:full":"Calle de Fuenterrabia, 7 Donostia-san Sebastian Guip\u00f9zcoa 20005",
    "addr:housenumber":"7",
    "addr:postcode":"20005",
    "addr:street":"Calle De Fuenterrabia",
    "iso:country":"ES",
    "sg:address":"Calle de Fuenterrabia, 7",
    "sg:city":"Donostia-san Sebastian",
    "sg:orig_category":"Ropa Para Se\u00d1oras Y Caballeros (al Por Menor)",
    "sg:phone":"+34 943 42 15 72",
    "sg:postcode":"20005",
    "sg:province":"Guip\u00f9zcoa",
    "wof:name":"Idepar S.l.",
    "wof:placetype":"venue"
},
  "geometry": {"coordinates":[-1.9816980362,43.3184661865],"type":"Point"}
}