{
  "type": "Feature",
  "properties": {
    "iso:country":"ES",
    "sg:address":"Carrer de Vila I Vila, 21",
    "sg:city":"Barcelona",
    "sg:orig_category":"Estudios, Instalaci\u00d3n De Climatizaci\u00d3n",
    "sg:phone":"+34 934 42 45 48",
    "sg:postcode":"08004",
    "sg:province":"Barcelona",
    "sg:website":"www.filair.es",
    "wof:name":"Filair S.a.",
    "wof:placetype":"venue"
},
  "geometry": {"coordinates":[2.1728110313,41.3728752136],"type":"Point"}
}