{
  "type": "Feature",
  "properties": {
    "addr:full":"Plaz Mendez Parada, 2 Madrid Madrid 28025",
    "addr:housenumber":"2",
    "addr:postcode":"28025",
    "addr:street":"Plaz;Parada",
    "iso:country":"ES",
    "sg:address":"Plaz Mendez Parada, 2",
    "sg:city":"Madrid",
    "sg:orig_category":"Molduras, Junquillos, Listones Y Molduras Perforadas",
    "sg:phone":"+34 914 66 79 94",
    "sg:postcode":"28025",
    "sg:province":"Madrid",
    "wof:name":"Gonzalez Lopez Ramon",
    "wof:placetype":"venue"
},
  "geometry": {"coordinates":[-3.7322640419,40.3840637207],"type":"Point"}
}