{
  "type": "Feature",
  "properties": {
    "iso:country":"ES",
    "sg:address":"Calle de Barcelona, 7",
    "sg:city":"Arganda",
    "sg:orig_category":"Estudios, Instalaci\u00d3n De Climatizaci\u00d3n",
    "sg:phone":"+34 918 71 27 95",
    "sg:postcode":"28500",
    "sg:province":"Madrid",
    "sg:website":"www.industriasdiru.es",
    "wof:name":"Industrias Diru S. L.",
    "wof:placetype":"venue"
},
  "geometry": {"coordinates":[-3.454862833,40.3063011169],"type":"Point"}
}