{
  "type": "Feature",
  "properties": {
    "iso:country":"ES",
    "sg:address":"Carrer de Argentina (de L'), 20",
    "sg:city":"Tortosa",
    "sg:orig_category":"Confecci\u00d3n De Trajes Para Se\u00d1oras",
    "sg:phone":"+34 977 44 32 50",
    "sg:postcode":"43500",
    "sg:province":"Tarragona",
    "wof:name":"Guallar Navarro Maria Teresa",
    "wof:placetype":"venue"
},
  "geometry": {"coordinates":[0.5217270255,40.8097763062],"type":"Point"}
}