{
  "type": "Feature",
  "properties": {
    "addr:full":"Calle de Luna, 7 Arrabal De Portillo Valladolid 47160",
    "addr:housenumber":"7",
    "addr:postcode":"47160",
    "addr:street":"Calle De Luna",
    "iso:country":"ES",
    "sg:address":"Calle de Luna, 7",
    "sg:city":"Arrabal De Portillo",
    "sg:orig_category":"Droguer\u00cdas (al Por Menor)",
    "sg:phone":"+34 983 55 61 45",
    "sg:postcode":"47160",
    "sg:province":"Valladolid",
    "wof:name":"Velasco Garcia Carlos",
    "wof:placetype":"venue"
},
  "geometry": {"coordinates":[-4.5954551697,41.4742698669],"type":"Point"}
}