{
  "type": "Feature",
  "properties": {
    "iso:country":"ES",
    "sg:address":"Calle de Concilio, 9",
    "sg:city":"Valencia De Don Juan",
    "sg:orig_category":"Pintura, Barniz, Productos Asimilables (fabricaci\u00d3n, Al Por Mayor)",
    "sg:phone":"+34 987 75 08 60",
    "sg:postcode":"24200",
    "sg:province":"Le\u00f3n",
    "wof:name":"Pinturas Freca S.l.",
    "wof:placetype":"venue"
},
  "geometry": {"coordinates":[-5.5199551582,42.2916946411],"type":"Point"}
}