{
  "type": "Feature",
  "properties": {
    "iso:country":"ES",
    "sg:address":"Plaz San Gines, 1",
    "sg:city":"Urda",
    "sg:orig_category":"Bancos",
    "sg:phone":"+34 925 47 21 02",
    "sg:postcode":"45480",
    "sg:province":"Toledo",
    "wof:name":"Banco Popular Espa\u00f1ol",
    "wof:placetype":"venue"
},
  "geometry": {"coordinates":[-3.7219750881,39.4137535095],"type":"Point"}
}