{
  "type": "Feature",
  "properties": {
    "addr:full":"Carr Romerets (els), S/n Mas Dels Frares Castell\u00f3n 12560",
    "addr:housenumber":"s",
    "addr:postcode":"12560",
    "addr:street":"Carr Romerets Els;/ N Mas Dels Frares Castello\u0301N",
    "iso:country":"ES",
    "sg:address":"Carr Romerets (els), S/n",
    "sg:city":"Mas Dels Frares",
    "sg:orig_category":"Agencias Y Agentes Comerciales, Representantes",
    "sg:phone":"+34 964 30 18 00",
    "sg:postcode":"12560",
    "sg:province":"Castell\u00f3n",
    "wof:name":"Rodriguez Rodriguez Eulogio",
    "wof:placetype":"venue"
},
  "geometry": {"coordinates":[0.0590550005,40.0523414612],"type":"Point"}
}