{
  "type": "Feature",
  "properties": {
    "iso:country":"ES",
    "sg:address":"Rua Santiago, 36",
    "sg:city":"Amoeiro",
    "sg:orig_category":"Caf\u00c9s, Bares, Cervecer\u00cdas",
    "sg:phone":"+34 988 28 10 15",
    "sg:postcode":"32170",
    "sg:province":"Ourense",
    "wof:name":"Galtelcom",
    "wof:placetype":"venue"
},
  "geometry": {"coordinates":[-7.9534511566,42.4108428955],"type":"Point"}
}