{
  "type": "Feature",
  "properties": {
    "addr:full":"Alto De La Albillera, S/n Zamora Zamora 49025",
    "addr:housenumber":"s",
    "addr:postcode":"49025",
    "addr:street":"Alto;La Albillera;/ N",
    "iso:country":"ES",
    "sg:address":"Alto De La Albillera, S/n",
    "sg:city":"Zamora",
    "sg:orig_category":"Transporte En General",
    "sg:phone":"+34 980 52 29 00",
    "sg:postcode":"49025",
    "sg:province":"Zamora",
    "wof:name":"Corinza S.l.",
    "wof:placetype":"venue"
},
  "geometry": {"coordinates":[-5.7524838448,41.509349823],"type":"Point"}
}