{
  "type": "Feature",
  "properties": {
    "iso:country":"ES",
    "sg:address":"Carrer de Arago, 4",
    "sg:city":"Palma",
    "sg:orig_category":"Abogados",
    "sg:phone":"+34 971 71 33 80",
    "sg:postcode":"07006",
    "sg:province":"Islas Baleares",
    "wof:name":"Riera Barcelo Maria Rosa",
    "wof:placetype":"venue"
},
  "geometry": {"coordinates":[2.6573040485,39.5730133057],"type":"Point"}
}