{
  "type": "Feature",
  "properties": {
    "iso:country":"ES",
    "sg:address":"La Recta, S/n",
    "sg:city":"Grado",
    "sg:orig_category":"Bebidas",
    "sg:phone":"+34 985 75 32 46",
    "sg:postcode":"33820",
    "sg:province":"Asturias",
    "wof:name":"Gonzalez Alvarez Maria Consuelo",
    "wof:placetype":"venue"
},
  "geometry": {"coordinates":[-6.0709972382,43.3890724182],"type":"Point"}
}