{
  "type": "Feature",
  "properties": {
    "addr:full":"Castro De Unta, 25 Betanzos La Coru\u00f1a 15300",
    "addr:housenumber":"25",
    "addr:postcode":"15300",
    "addr:street":"Unta;La",
    "iso:country":"ES",
    "sg:address":"Castro De Unta, 25",
    "sg:city":"Betanzos",
    "sg:orig_category":"Calcoman\u00cda, Impresi\u00d3n, Transferencia (transfert)",
    "sg:phone":"+34 981 77 64 98",
    "sg:postcode":"15300",
    "sg:province":"La Coru\u00f1a",
    "sg:website":"www.elidealgallego.com",
    "wof:name":"Editorial La Capital S.l.",
    "wof:placetype":"venue"
},
  "geometry": {"coordinates":[-8.2090368271,43.279800415],"type":"Point"}
}