{
  "type": "Feature",
  "properties": {
    "iso:country":"ES",
    "sg:address":"Calle de Virgen De La Esperanza, 15",
    "sg:city":"Ibi",
    "sg:orig_category":"Fabricaci\u00d3n De Juegos Y Juguetes",
    "sg:phone":"+34 965 55 21 70",
    "sg:postcode":"03440",
    "sg:province":"Alicante",
    "wof:name":"Talleres La Paz S. L.",
    "wof:placetype":"venue"
},
  "geometry": {"coordinates":[-0.5797650218,38.6182594299],"type":"Point"}
}