{
  "type": "Feature",
  "properties": {
    "iso:country":"ES",
    "sg:address":"Calle de Garcia Menendez, 4",
    "sg:city":"Zaragoza",
    "sg:orig_category":"Comercio De Cuadros, L\u00c1minas Y Reproducciones De Obras De Arte",
    "sg:phone":"+34 976 27 73 56",
    "sg:postcode":"50007",
    "sg:province":"Zaragoza",
    "wof:name":"Romance Herrera Francisco",
    "wof:placetype":"venue"
},
  "geometry": {"coordinates":[-0.8810369968,41.639251709],"type":"Point"}
}