{
  "type": "Feature",
  "properties": {
    "iso:country":"ES",
    "sg:address":"Avda Concordia, S/n",
    "sg:city":"Tui",
    "sg:orig_category":"Cerrajer\u00cda, Ferrallista",
    "sg:phone":"+34 986 60 05 95",
    "sg:postcode":"36700",
    "sg:province":"Pontevedra",
    "wof:name":"Nogueira Dominguez Vicente Telmo",
    "wof:placetype":"venue"
},
  "geometry": {"coordinates":[-8.6416788101,42.0589332581],"type":"Point"}
}