{
  "type": "Feature",
  "properties": {
    "iso:country":"ES",
    "sg:address":"Calle de Adelfa, 7",
    "sg:city":"Humanes De Madrid",
    "sg:orig_category":"Puertas Y Portales",
    "sg:phone":"+34 916 09 72 00",
    "sg:postcode":"28970",
    "sg:province":"Madrid",
    "wof:name":"Representaciones El Roble S.l.",
    "wof:placetype":"venue"
},
  "geometry": {"coordinates":[-3.8378098011,40.2681274414],"type":"Point"}
}