{
  "type": "Feature",
  "properties": {
    "iso:country":"ES",
    "sg:address":"Carr Segria, 23",
    "sg:city":"Lleida",
    "sg:orig_category":"Molduras, Junquillos, Listones Y Molduras Perforadas",
    "sg:phone":"+34 973 28 31 88",
    "sg:postcode":"25006",
    "sg:province":"Lleida",
    "wof:name":"Bar Passatge Scp",
    "wof:placetype":"venue"
},
  "geometry": {"coordinates":[0.6131169796,41.6180343628],"type":"Point"}
}