{
  "type": "Feature",
  "properties": {
    "iso:country":"ES",
    "sg:address":"O Froxel, 60",
    "sg:city":"Froxel",
    "sg:orig_category":"Empresas De Carpinter\u00cda Met\u00c1lica",
    "sg:phone":"+34 981 60 11 01",
    "sg:postcode":"15141",
    "sg:province":"La Coru\u00f1a",
    "wof:name":"Metalica Varsan S.l.",
    "wof:placetype":"venue"
},
  "geometry": {"coordinates":[-8.4798288345,43.3172454834],"type":"Point"}
}