{
  "type": "Feature",
  "properties": {
    "iso:country":"ES",
    "sg:address":"Crri Zamoras, S/n",
    "sg:city":"Camino Viejo De Casillas",
    "sg:orig_category":"Empresas De Desmonte",
    "sg:phone":"+34 968 20 20 96",
    "sg:postcode":"30007",
    "sg:province":"Murcia",
    "wof:name":"Excavaciones Monteagudo S.l.",
    "wof:placetype":"venue"
},
  "geometry": {"coordinates":[-1.1035890579,38.0079536438],"type":"Point"}
}