{
  "type": "Feature",
  "properties": {
    "iso:country":"ES",
    "sg:address":"Av. Valladolid, 21",
    "sg:city":"Madrid",
    "sg:orig_category":"Centros Empresariales",
    "sg:phone":"+34 915 47 10 20",
    "sg:postcode":"28008",
    "sg:province":"Madrid",
    "wof:name":"Faceta Servicios Integrales S.l.",
    "wof:placetype":"venue"
},
  "geometry": {"coordinates":[-3.7279260159,40.4267807007],"type":"Point"}
}