{
  "type": "Feature",
  "properties": {
    "addr:full":"Avda Alcalde Clemente Diaz Ruiz, 10 Fuengirola M\u00e1laga 29640",
    "addr:housenumber":"10",
    "addr:postcode":"29640",
    "addr:street":"Avda Alcalde Clemente Diaz Ruiz;Ma\u0301Laga",
    "iso:country":"ES",
    "sg:address":"Avda Alcalde Clemente Diaz Ruiz, 10",
    "sg:city":"Fuengirola",
    "sg:orig_category":"Asesor\u00cda Fiscal Y Jur\u00cddica",
    "sg:phone":"+34 952 46 64 92",
    "sg:postcode":"29640",
    "sg:province":"M\u00e1laga",
    "wof:name":"International Advisers S.l.",
    "wof:placetype":"venue"
},
  "geometry": {"coordinates":[-4.6266860962,36.5485916138],"type":"Point"}
}