{
  "type": "Feature",
  "properties": {
    "iso:country":"ES",
    "sg:address":"Calle de Denia, 76",
    "sg:city":"Valencia",
    "sg:orig_category":"Negocio De Metales No Ferrosos",
    "sg:phone":"+34 963 42 26 23",
    "sg:postcode":"46006",
    "sg:province":"Valencia",
    "wof:name":"Medina Martinez Valentin",
    "wof:placetype":"venue"
},
  "geometry": {"coordinates":[-0.3778966069,39.4618721008],"type":"Point"}
}