{
  "type": "Feature",
  "properties": {
    "iso:country":"ES",
    "sg:address":"Avda Reyes Catolicos (de Los), 21",
    "sg:city":"San Sebastian De Los Reyes",
    "sg:orig_category":"Cristaler\u00cdas",
    "sg:phone":"+34 916 53 43 29",
    "sg:postcode":"28700",
    "sg:province":"Madrid",
    "wof:name":"Eurocristal Sanse S.l.",
    "wof:placetype":"venue"
},
  "geometry": {"coordinates":[-3.6274590492,40.5511398315],"type":"Point"}
}