{
  "type": "Feature",
  "properties": {
    "iso:country":"ES",
    "sg:address":"Ctra Doctor Robert, 37",
    "sg:city":"Vendrell",
    "sg:orig_category":"Reposter\u00cdas",
    "sg:phone":"+34 977 66 63 00",
    "sg:postcode":"43700",
    "sg:province":"Tarragona",
    "wof:name":"2-u.a.t. S.l.",
    "wof:placetype":"venue"
},
  "geometry": {"coordinates":[1.53758,41.221802],"type":"Point"}
}