{
  "type": "Feature",
  "properties": {
    "iso:country":"ES",
    "sg:address":"Rua Rafael Pico, 46",
    "sg:city":"Portonovo",
    "sg:classifiers":[
        {
            "category":"Tea Room",
            "subcategory":"None",
            "type":"Food & Drink"
        }
    ],
    "sg:phone":"+34 986 69 12 50",
    "sg:postcode":"36970",
    "sg:province":"Pontevedra",
    "sg:tags":[
        "snack"
    ],
    "wof:name":"Vi\u00f1a Pedreira S.l",
    "wof:placetype":"venue"
},
  "geometry": {"coordinates":[-8.8248443604,42.3953971863],"type":"Point"}
}