{
  "type": "Feature",
  "properties": {
    "iso:country":"ES",
    "sg:address":"Calle de General Serrano, 8",
    "sg:city":"Santa Cruz De Tenerife",
    "sg:orig_category":"M\u00c9dicos: Cirug\u00cda Urol\u00d3gica",
    "sg:phone":"+34 922 28 18 53",
    "sg:postcode":"38004",
    "sg:province":"Santa Cruz De Tenerife",
    "wof:name":"Rodriguez Hernandez Pedro",
    "wof:placetype":"venue"
},
  "geometry": {"coordinates":[-16.2566986084,28.4663219452],"type":"Point"}
}