{
  "type": "Feature",
  "properties": {
    "iso:country":"ES",
    "sg:address":"Ctra Segovia, S/n",
    "sg:city":"Sanchonu\u00d1o",
    "sg:orig_category":"Producci\u00d3n, Venta De Productos De Agricultura Biol\u00d3gica",
    "sg:phone":"+34 921 16 02 50",
    "sg:postcode":"40297",
    "sg:province":"Segovia",
    "wof:name":"La Canal De Sanchonu\u00f1o S.c",
    "wof:placetype":"venue"
},
  "geometry": {"coordinates":[-4.305398941,41.3188438416],"type":"Point"}
}