{
  "type": "Feature",
  "properties": {
    "addr:full":"Calle de Sierra De Guadarrama (de La), 90 Poligono De San Fernando De Henares Madrid 28830",
    "addr:housenumber":"90",
    "addr:postcode":"28830",
    "addr:street":"Calle De Sierra De Guadarrama De La",
    "iso:country":"ES",
    "sg:address":"Calle de Sierra De Guadarrama (de La), 90",
    "sg:city":"Poligono De San Fernando De Henares",
    "sg:orig_category":"Inform\u00c1tica Equipo Y Programas (al Por Mayor)",
    "sg:phone":"+34 916 77 06 02",
    "sg:postcode":"28830",
    "sg:province":"Madrid",
    "wof:name":"Batch Pc S.l.",
    "wof:placetype":"venue"
},
  "geometry": {"coordinates":[-3.4958229065,40.452041626],"type":"Point"}
}