{
  "type": "Feature",
  "properties": {
    "addr:full":"Concejal Jeronimo Leal, S/n Espartinas Sevilla 41807",
    "addr:housenumber":"s / n",
    "addr:postcode":"41807",
    "addr:street":"Concejal Jeronimo Leal",
    "iso:country":"ES",
    "sg:address":"Concejal Jeronimo Leal, S/n",
    "sg:city":"Espartinas",
    "sg:orig_category":"Molduras, Junquillos, Listones Y Molduras Perforadas",
    "sg:phone":"+34 954 11 31 66",
    "sg:postcode":"41807",
    "sg:province":"Sevilla",
    "wof:name":"Tilde Deportes Sl",
    "wof:placetype":"venue"
},
  "geometry": {"coordinates":[-6.1235818863,37.3828926086],"type":"Point"}
}