{
  "type": "Feature",
  "properties": {
    "addr:full":"Plaz Carmen (del), 3 Almeria Almer\u00eda 04003",
    "addr:postcode":"04003",
    "addr:street":"Almeria Almeri\u0301A",
    "iso:country":"ES",
    "sg:address":"Plaz Carmen (del), 3",
    "sg:city":"Almeria",
    "sg:orig_category":"M\u00c9dicos: Estomatolog\u00cda",
    "sg:phone":"+34 950 27 51 48",
    "sg:postcode":"04003",
    "sg:province":"Almer\u00eda",
    "wof:name":"Lopez Leon Maria Isabel",
    "wof:placetype":"venue"
},
  "geometry": {"coordinates":[-2.4649400711,36.8420562744],"type":"Point"}
}