{
  "type": "Feature",
  "properties": {
    "addr:full":"Ctra Villanueva-andujar, S/n Belalcazar C\u00f3rdoba 14280",
    "addr:housenumber":"s",
    "addr:postcode":"14280",
    "addr:street":"Ctra Villanueva-Andujar;/ N;Co\u0301Rdoba",
    "iso:country":"ES",
    "sg:address":"Ctra Villanueva-andujar, S/n",
    "sg:city":"Belalcazar",
    "sg:orig_category":"Bares, Piano",
    "sg:phone":"+34 957 14 60 71",
    "sg:postcode":"14280",
    "sg:province":"C\u00f3rdoba",
    "wof:name":"Comercial Medina Pulido S.l.",
    "wof:placetype":"venue"
},
  "geometry": {"coordinates":[-5.1626439095,38.5788993835],"type":"Point"}
}