{
  "type": "Feature",
  "properties": {
    "iso:country":"ES",
    "sg:address":"Calle de Murillo, 2",
    "sg:city":"Pto. Rosario",
    "sg:orig_category":"Ropa Para Se\u00d1oras (al Por Menor)",
    "sg:phone":"+34 928 53 06 77",
    "sg:postcode":"35600",
    "sg:province":"Las Palmas",
    "wof:name":"Reina Iglesias Carmen Maria",
    "wof:placetype":"venue"
},
  "geometry": {"coordinates":[-13.8680515289,28.5011367798],"type":"Point"}
}