{
  "type": "Feature",
  "properties": {
    "addr:full":"Carr Patacos, S/n Alfas Pi Alicante 03580",
    "addr:housenumber":"s",
    "addr:postcode":"03580",
    "addr:street":"Carr Patacos;/ N Alfas;Alicante",
    "iso:country":"ES",
    "sg:address":"Carr Patacos, S/n",
    "sg:city":"Alfas Pi",
    "sg:orig_category":"Inmobiliaria (agencias)",
    "sg:phone":"+34 965 88 83 20",
    "sg:postcode":"03580",
    "sg:province":"Alicante",
    "wof:name":"Fuente Expor Construcciones Promociones S.l",
    "wof:placetype":"venue"
},
  "geometry": {"coordinates":[-0.1106439978,38.5881652832],"type":"Point"}
}