{
  "type": "Feature",
  "properties": {
    "addr:full":"Carrer de Jacint Verdaguer, 16 Reus Tarragona 43202",
    "addr:housenumber":"16",
    "addr:postcode":"43202",
    "addr:street":"Carrer De Jacint Verdaguer",
    "iso:country":"ES",
    "sg:address":"Carrer de Jacint Verdaguer, 16",
    "sg:city":"Reus",
    "sg:orig_category":"Animales: Material Y Suministros Para (fabricaci\u00d3n, Al Por Mayor)",
    "sg:phone":"+34 977 31 55 06",
    "sg:postcode":"43202",
    "sg:province":"Tarragona",
    "wof:name":"Royo Creaciones Avicolas S.l.",
    "wof:placetype":"venue"
},
  "geometry": {"coordinates":[1.0980759859,41.1575164795],"type":"Point"}
}