{
  "type": "Feature",
  "properties": {
    "iso:country":"ES",
    "sg:address":"Pase Arriba Da Ponte, 19",
    "sg:city":"Cedeira",
    "sg:orig_category":"Albergues",
    "sg:phone":"+34 981 48 10 54",
    "sg:postcode":"15350",
    "sg:province":"La Coru\u00f1a",
    "wof:name":"Quintana Suarez Jesus",
    "wof:placetype":"venue"
},
  "geometry": {"coordinates":[-8.0549716949,43.6620788574],"type":"Point"}
}