{
  "type": "Feature",
  "properties": {
    "addr:full":"Calle de Jose Franchy Roca, 11 Palmas De Gran Canaria Las Palmas 35007",
    "addr:housenumber":"11",
    "addr:postcode":"35007",
    "addr:street":"Calle De Jose Franchy Roca",
    "iso:country":"ES",
    "sg:address":"Calle de Jose Franchy Roca, 11",
    "sg:city":"Palmas De Gran Canaria",
    "sg:orig_category":"M\u00c9dicos: Cirug\u00cda Ortop\u00c9dica Y Traumatolog\u00cda",
    "sg:phone":"+34 928 26 79 54",
    "sg:postcode":"35007",
    "sg:province":"Las Palmas",
    "wof:name":"Ortega Ojeda Jose Francisco",
    "wof:placetype":"venue"
},
  "geometry": {"coordinates":[-15.4324808121,28.1387882233],"type":"Point"}
}