{
  "type": "Feature",
  "properties": {
    "iso:country":"ES",
    "sg:address":"Carrer de Om, 28",
    "sg:city":"Vendrell",
    "sg:orig_category":"Arquitectos",
    "sg:phone":"+34 977 66 33 46",
    "sg:postcode":"43700",
    "sg:province":"Tarragona",
    "wof:name":"Societat Eynis Associats S.a.",
    "wof:placetype":"venue"
},
  "geometry": {"coordinates":[1.5340989828,41.2187652588],"type":"Point"}
}