{
  "type": "Feature",
  "properties": {
    "addr:full":"Carrer de Joan Xxiii, 11 Alcanar Tarragona 43530",
    "addr:housenumber":"11",
    "addr:postcode":"43530",
    "addr:street":"Carrer De Joan Xxiii",
    "iso:country":"ES",
    "sg:address":"Carrer de Joan Xxiii, 11",
    "sg:city":"Alcanar",
    "sg:orig_category":"Empresas De Carpinter\u00cda De Madera",
    "sg:phone":"+34 977 73 13 33",
    "sg:postcode":"43530",
    "sg:province":"Tarragona",
    "wof:name":"Fusteria Bertomeu S.l.",
    "wof:placetype":"venue"
},
  "geometry": {"coordinates":[0.4762119949,40.5447807312],"type":"Point"}
}