{
  "type": "Feature",
  "properties": {
    "addr:full":"Calle de Valencia, 12 Toledo Toledo 45005",
    "addr:housenumber":"12",
    "addr:postcode":"45005",
    "addr:street":"Calle De Valencia",
    "iso:country":"ES",
    "sg:address":"Calle de Valencia, 12",
    "sg:city":"Toledo",
    "sg:classifiers":[
        {
            "category":"Autos & Motor Vehicles",
            "subcategory":"Automobile Sales",
            "type":"Retail Goods"
        }
    ],
    "sg:phone":"+34 925 22 46 58",
    "sg:postcode":"45005",
    "sg:province":"Toledo",
    "wof:name":"Medina Lorenzo Alfredo",
    "wof:placetype":"venue"
},
  "geometry": {"coordinates":[-4.0350089073,39.874332428],"type":"Point"}
}