{
  "type": "Feature",
  "properties": {
    "addr:full":"Trav De Gracia, 18 Barcelona Barcelona 08021",
    "addr:housenumber":"18",
    "addr:postcode":"08021",
    "addr:street":"Trav De Gracia",
    "iso:country":"ES",
    "sg:address":"Trav De Gracia, 18",
    "sg:city":"Barcelona",
    "sg:orig_category":"Inform\u00c1tica (estudios, Servicios, Asesor\u00cda, Formaci\u00d3n)",
    "sg:phone":"+34 932 09 03 58",
    "sg:postcode":"08021",
    "sg:province":"Barcelona",
    "wof:name":"Cosp Martinez Guillermo",
    "wof:placetype":"venue"
},
  "geometry": {"coordinates":[2.1465919018,41.394077301],"type":"Point"}
}