{
  "type": "Feature",
  "properties": {
    "addr:full":"Av Catalunya, 10 Tarragona Tarragona 43002",
    "addr:housenumber":"10",
    "addr:postcode":"43002",
    "addr:street":"Av Catalunya",
    "iso:country":"ES",
    "sg:address":"Av Catalunya, 10",
    "sg:city":"Tarragona",
    "sg:orig_category":"Transporte En General",
    "sg:phone":"+34 977 24 37 60",
    "sg:postcode":"43002",
    "sg:province":"Tarragona",
    "wof:name":"Bon Preu S.a.",
    "wof:placetype":"venue"
},
  "geometry": {"coordinates":[1.2533990145,41.1194419861],"type":"Point"}
}