{
  "type": "Feature",
  "properties": {
    "iso:country":"ES",
    "sg:address":"Carrer de Pere Martell (de), 13",
    "sg:city":"Tarragona",
    "sg:orig_category":"Sociedades, Compa\u00d1\u00cdas Aseguradoras",
    "sg:phone":"+34 977 21 47 40",
    "sg:postcode":"43001",
    "sg:province":"Tarragona",
    "wof:name":"P.salas Correduria De Seguros S.l.",
    "wof:placetype":"venue"
},
  "geometry": {"coordinates":[1.2443749905,41.1170463562],"type":"Point"}
}