{
  "type": "Feature",
  "properties": {
    "addr:full":"Carrer de Bisbe Strauch, 16 Vic Barcelona 08500",
    "addr:housenumber":"16",
    "addr:postcode":"08500",
    "addr:street":"Carrer De Bisbe Strauch",
    "iso:country":"ES",
    "sg:address":"Carrer de Bisbe Strauch, 16",
    "sg:city":"Vic",
    "sg:orig_category":"M\u00c9dicos: Naturistas",
    "sg:phone":"+34 938 89 46 02",
    "sg:postcode":"08500",
    "sg:province":"Barcelona",
    "wof:name":"Avicena Espai Natural S.l.",
    "wof:placetype":"venue"
},
  "geometry": {"coordinates":[2.2512750626,41.9230384827],"type":"Point"}
}