{
  "type": "Feature",
  "properties": {
    "addr:full":"Calle de Labradores, 22 Medina Campo Valladolid 47400",
    "addr:housenumber":"22",
    "addr:postcode":"47400",
    "addr:street":"Calle De Labradores",
    "iso:country":"ES",
    "sg:address":"Calle de Labradores, 22",
    "sg:city":"Medina Campo",
    "sg:orig_category":"Mec\u00c1nico Del Autom\u00d3vil",
    "sg:phone":"+34 983 81 20 48",
    "sg:postcode":"47400",
    "sg:province":"Valladolid",
    "wof:name":"Talleres Floan Automedina S.l.",
    "wof:placetype":"venue"
},
  "geometry": {"coordinates":[-4.9211359024,41.3172225952],"type":"Point"}
}