{
  "type": "Feature",
  "properties": {
    "iso:country":"ES",
    "sg:address":"Torrent D'en Negre, 5",
    "sg:city":"S. Joan Despi",
    "sg:orig_category":"Notarios",
    "sg:phone":"+34 933 73 52 62",
    "sg:postcode":"08970",
    "sg:province":"Barcelona",
    "wof:name":"Alvarez Jimenez Maria Del Sagrario",
    "wof:placetype":"venue"
},
  "geometry": {"coordinates":[2.056217432,41.3669929504],"type":"Point"}
}