{
  "type": "Feature",
  "properties": {
    "iso:country":"ES",
    "sg:address":"Plaz Bizente Goikoetxea, 1",
    "sg:city":"Ibarra",
    "sg:orig_category":"Ense\u00d1anza, Formaci\u00d3n Profesional: Aprendizaje",
    "sg:phone":"+34 945 44 50 16",
    "sg:postcode":"01160",
    "sg:province":"\u00c1lava",
    "wof:name":"Ayuntamiento De Ibarra De Aramayona",
    "wof:placetype":"venue"
},
  "geometry": {"coordinates":[-2.5653066635,43.0512199402],"type":"Point"}
}