{
  "type": "Feature",
  "properties": {
    "iso:country":"ES",
    "sg:address":"Plaz Longoria Carbajal, 1",
    "sg:city":"Oviedo",
    "sg:orig_category":"Inform\u00c1tica: Consultores",
    "sg:phone":"+34 985 21 98 11",
    "sg:postcode":"33002",
    "sg:province":"Asturias",
    "sg:website":"www.netinex.es",
    "wof:name":"Netinex S.a.",
    "wof:placetype":"venue"
},
  "geometry": {"coordinates":[-5.8482837677,43.3645324707],"type":"Point"}
}