{
  "type": "Feature",
  "properties": {
    "iso:country":"ES",
    "sg:address":"Avda Fragoso, 22",
    "sg:city":"Vigo",
    "sg:orig_category":"Electrodom\u00c9sticos (fabricaci\u00d3n, Al Por Mayor)",
    "sg:phone":"+34 986 21 00 12",
    "sg:postcode":"36210",
    "sg:province":"Pontevedra",
    "wof:name":"Gelu S.l.",
    "wof:placetype":"venue"
},
  "geometry": {"coordinates":[-8.7336950302,42.2189865112],"type":"Point"}
}