{
  "type": "Feature",
  "properties": {
    "iso:country":"ES",
    "sg:address":"Calle de Emilio Gastesi Fernandez, 1",
    "sg:city":"Madrid",
    "sg:orig_category":"Radiocomunicaciones, Telefon\u00cda M\u00d3vil, Radiomensajer\u00cda: Servicios, Comercializaci\u00d3n",
    "sg:phone":"+34 913 67 24 23",
    "sg:postcode":"28027",
    "sg:province":"Madrid",
    "wof:name":"Art Visual Media S.l.",
    "wof:placetype":"venue"
},
  "geometry": {"coordinates":[-3.6474499702,40.4359741211],"type":"Point"}
}