{
  "type": "Feature",
  "properties": {
    "iso:country":"ES",
    "sg:address":"Calle de Moreno Nieto, 14",
    "sg:city":"Olivenza",
    "sg:orig_category":"Ropa Para Ni\u00d1os (al Por Menor)",
    "sg:phone":"+34 924 49 23 74",
    "sg:postcode":"06100",
    "sg:province":"Badajoz",
    "wof:name":"Rodriguez Piriz Maria Luisa",
    "wof:placetype":"venue"
},
  "geometry": {"coordinates":[-7.1015748978,38.6852836609],"type":"Point"}
}