{
  "type": "Feature",
  "properties": {
    "iso:country":"ES",
    "sg:address":"Cno Estret De Sorio, S/n",
    "sg:city":"Xativa",
    "sg:orig_category":"Juegos Y Juguetes (al Por Menor)",
    "sg:phone":"+34 962 28 41 61",
    "sg:postcode":"46800",
    "sg:province":"Valencia",
    "wof:name":"Almacenes Beltran S.l.",
    "wof:placetype":"venue"
},
  "geometry": {"coordinates":[-0.5244722962,39.0036392212],"type":"Point"}
}