{
  "type": "Feature",
  "properties": {
    "addr:full":"Av Peguera, 50 Peguera Islas Baleares 07160",
    "addr:housenumber":"50",
    "addr:postcode":"07160",
    "addr:street":"Av Peguera",
    "iso:country":"ES",
    "sg:address":"Av Peguera, 50",
    "sg:city":"Peguera",
    "sg:orig_category":"Electrodom\u00c9sticos (al Por Menor)",
    "sg:phone":"+34 971 68 71 35",
    "sg:postcode":"07160",
    "sg:province":"Islas Baleares",
    "wof:name":"Mulet Gomila Francisca",
    "wof:placetype":"venue"
},
  "geometry": {"coordinates":[2.4499740601,39.5377464294],"type":"Point"}
}