{
  "type": "Feature",
  "properties": {
    "iso:country":"ES",
    "sg:address":"Calle de Notaria (a), 89",
    "sg:city":"Notaria",
    "sg:orig_category":"Muebles, Minoristas",
    "sg:phone":"+34 988 49 41 60",
    "sg:postcode":"32236",
    "sg:province":"Ourense",
    "wof:name":"Pi\u00f1a Vas Jesus",
    "wof:placetype":"venue"
},
  "geometry": {"coordinates":[-8.1897850037,42.1536026001],"type":"Point"}
}