{
  "type": "Feature",
  "properties": {
    "iso:country":"ES",
    "sg:address":"Carrer de Girona, 132",
    "sg:city":"Barcelona",
    "sg:orig_category":"Agencias Y Agentes Comerciales, Representantes",
    "sg:phone":"+34 934 59 08 36",
    "sg:postcode":"08037",
    "sg:province":"Barcelona",
    "wof:name":"Mir Nou Juan",
    "wof:placetype":"venue"
},
  "geometry": {"coordinates":[2.16741395,41.3978157043],"type":"Point"}
}