{
  "type": "Feature",
  "properties": {
    "iso:country":"ES",
    "sg:address":"Calle de Pages Del Corro, 144",
    "sg:city":"Sevilla",
    "sg:orig_category":"M\u00c9dicos: Estomatolog\u00cda",
    "sg:phone":"+34 954 27 26 72",
    "sg:postcode":"41010",
    "sg:province":"Sevilla",
    "wof:name":"Quiros Valderas Jose",
    "wof:placetype":"venue"
},
  "geometry": {"coordinates":[-6.0014457703,37.3818244934],"type":"Point"}
}