{
  "type": "Feature",
  "properties": {
    "iso:country":"ES",
    "sg:address":"Calle de Nueva, S/n",
    "sg:city":"Sanlucar Guadiana",
    "sg:orig_category":"Alquiler De Casas Y Habitaciones Amuebladas",
    "sg:phone":"+34 959 38 85 16",
    "sg:postcode":"21595",
    "sg:province":"Huelva",
    "wof:name":"Montes Martin Maria Dolores",
    "wof:placetype":"venue"
},
  "geometry": {"coordinates":[-7.4674777985,37.4728279114],"type":"Point"}
}