{
  "type": "Feature",
  "properties": {
    "addr:full":"Calle de San Antonio (de), 82 Aranjuez Madrid 28300",
    "addr:housenumber":"82",
    "addr:postcode":"28300",
    "addr:street":"Calle De San Antonio",
    "iso:country":"ES",
    "sg:address":"Calle de San Antonio (de), 82",
    "sg:city":"Aranjuez",
    "sg:orig_category":"Quincaller\u00cda (al Por Menor)",
    "sg:phone":"+34 918 91 06 02",
    "sg:postcode":"28300",
    "sg:province":"Madrid",
    "wof:name":"Mara\u00f1on Gonzalez Maria Juana",
    "wof:placetype":"venue"
},
  "geometry": {"coordinates":[-3.6029169559,40.0333213806],"type":"Point"}
}