{
  "type": "Feature",
  "properties": {
    "iso:country":"ES",
    "sg:address":"Real, 85",
    "sg:city":"Betxi",
    "sg:orig_category":"Bisuter\u00cda, Joyer\u00cda, Relojer\u00cda (al Por Menor)",
    "sg:phone":"+34 964 62 04 68",
    "sg:postcode":"12549",
    "sg:province":"Castell\u00f3n",
    "wof:name":"Rico Gonzalez Maria",
    "wof:placetype":"venue"
},
  "geometry": {"coordinates":[-0.1982019991,39.9267311096],"type":"Point"}
}