{
  "type": "Feature",
  "properties": {
    "addr:full":"Carrer de Ali Bei, 51 Barcelona Barcelona 08013",
    "addr:housenumber":"51",
    "addr:postcode":"08013",
    "addr:street":"Carrer De Ali Bei",
    "iso:country":"ES",
    "sg:address":"Carrer de Ali Bei, 51",
    "sg:city":"Barcelona",
    "sg:orig_category":"Mensajer\u00cda Express, Portes Internacionales",
    "sg:phone":"+34 932 32 48 59",
    "sg:postcode":"08013",
    "sg:province":"Barcelona",
    "wof:name":"Central De Recaderos Fores S.c.p.",
    "wof:placetype":"venue"
},
  "geometry": {"coordinates":[2.1802220345,41.3931694031],"type":"Point"}
}