{
  "type": "Feature",
  "properties": {
    "iso:country":"ES",
    "sg:address":"Carrer de Arago, 91",
    "sg:city":"Barcelona",
    "sg:orig_category":"Artesan\u00cda",
    "sg:phone":"+34 932 26 57 44",
    "sg:postcode":"08015",
    "sg:province":"Barcelona",
    "sg:website":"www.miniescaparate.com",
    "wof:name":"Abu Simbel S.l.",
    "wof:placetype":"venue"
},
  "geometry": {"coordinates":[2.151207,41.381905],"type":"Point"}
}