{
  "type": "Feature",
  "properties": {
    "iso:country":"ES",
    "sg:address":"Calle de Pico Andolinas, 5",
    "sg:city":"Pravia",
    "sg:orig_category":"Delegados, Agentes De Tr\u00c1nsito, Auxiliares De Transporte Internacional",
    "sg:phone":"+34 985 82 01 33",
    "sg:postcode":"33120",
    "sg:province":"Asturias",
    "wof:name":"Alvarez Fernandez Jose Antonio",
    "wof:placetype":"venue"
},
  "geometry": {"coordinates":[-6.114010334,43.4885292053],"type":"Point"}
}