{
  "type": "Feature",
  "properties": {
    "addr:full":"Calle de Madrid (de), 2 Colmenar Viejo Madrid 28770",
    "addr:postcode":"28770",
    "addr:street":"Calle De Madrid De",
    "iso:country":"ES",
    "sg:address":"Calle de Madrid (de), 2",
    "sg:city":"Colmenar Viejo",
    "sg:orig_category":"Abogados",
    "sg:phone":"+34 918 46 51 63",
    "sg:postcode":"28770",
    "sg:province":"Madrid",
    "wof:name":"Gonzalo Tomey Jesus",
    "wof:placetype":"venue"
},
  "geometry": {"coordinates":[-3.7739388943,40.6710357666],"type":"Point"}
}