{
  "type": "Feature",
  "properties": {
    "addr:full":"Carrer de Motors, 1 Barcelona Barcelona 08040",
    "addr:housenumber":"1",
    "addr:postcode":"08040",
    "addr:street":"Carrer",
    "iso:country":"ES",
    "sg:address":"Carrer de Motors, 1",
    "sg:city":"Barcelona",
    "sg:orig_category":"Electricidad, Electr\u00d3nica: Suministros (al Por Menor)",
    "sg:phone":"+34 932 23 12 00",
    "sg:postcode":"08040",
    "sg:province":"Barcelona",
    "sg:website":"www.qualityespresso.net",
    "wof:name":"Quality Espresso S.a.",
    "wof:placetype":"venue"
},
  "geometry": {"coordinates":[2.138240099,41.3486595154],"type":"Point"}
}