{
  "type": "Feature",
  "properties": {
    "addr:full":"Ctra Albatera, Km. 0003,0 S. Isidro Alicante 03349",
    "addr:postcode":"03349",
    "addr:street":"Ctra Albatera Km. 0003,0 S. Isidro Alicante",
    "iso:country":"ES",
    "sg:address":"Ctra Albatera, Km. 0003,0",
    "sg:city":"S. Isidro",
    "sg:orig_category":"Transportes Internacionales",
    "sg:phone":"+34 965 48 63 09",
    "sg:postcode":"03349",
    "sg:province":"Alicante",
    "wof:name":"Traserco Cooperativa Valenciana",
    "wof:placetype":"venue"
},
  "geometry": {"coordinates":[-0.8811699748,38.232131958],"type":"Point"}
}