{
  "type": "Feature",
  "properties": {
    "addr:full":"Calle de Antonio Machado, 3 Camas Sevilla 41900",
    "addr:housenumber":"3",
    "addr:postcode":"41900",
    "addr:street":"Calle De Antonio Machado",
    "iso:country":"ES",
    "sg:address":"Calle de Antonio Machado, 3",
    "sg:city":"Camas",
    "sg:orig_category":"Agencias De Viajes",
    "sg:phone":"+34 954 39 49 07",
    "sg:postcode":"41900",
    "sg:province":"Sevilla",
    "sg:website":"www.viajestriana.com",
    "wof:name":"Viajes Triana S.a.",
    "wof:placetype":"venue"
},
  "geometry": {"coordinates":[-6.0324440002,37.4008560181],"type":"Point"}
}