{
  "type": "Feature",
  "properties": {
    "addr:full":"Carrer de Can Cuyas, 69 Can Cuias Barcelona 08110",
    "addr:housenumber":"69",
    "addr:postcode":"08110",
    "addr:street":"Carrer De Can Cuyas",
    "iso:country":"ES",
    "sg:address":"Carrer de Can Cuyas, 69",
    "sg:city":"Can Cuias",
    "sg:orig_category":"Delegados, Agentes De Tr\u00c1nsito, Auxiliares De Transporte Internacional",
    "sg:phone":"+34 935 65 15 60",
    "sg:postcode":"08110",
    "sg:province":"Barcelona",
    "wof:name":"Trafertir Cargo S.a.",
    "wof:placetype":"venue"
},
  "geometry": {"coordinates":[2.1817660332,41.4890899658],"type":"Point"}
}