{
  "type": "Feature",
  "properties": {
    "iso:country":"ES",
    "sg:address":"Carrer de Sant Benet, 40",
    "sg:city":"Mataro",
    "sg:orig_category":"Muebles, Minoristas",
    "sg:phone":"+34 937 99 75 10",
    "sg:postcode":"08302",
    "sg:province":"Barcelona",
    "sg:website":"www.treku.es",
    "wof:name":"Transit Mataro S. L.",
    "wof:placetype":"venue"
},
  "geometry": {"coordinates":[2.4401369095,41.5384559631],"type":"Point"}
}