{
  "type": "Feature",
  "properties": {
    "iso:country":"ES",
    "sg:address":"Calle de San Felipe, 44",
    "sg:city":"Icod De Los Vinos",
    "sg:orig_category":"Asociaciones Humanitarias, De Cooperaci\u00d3n, De Acci\u00d3n Social",
    "sg:phone":"+34 922 81 28 07",
    "sg:postcode":"38430",
    "sg:province":"Santa Cruz De Tenerife",
    "wof:name":"Manuel Guerra Casellano S.l.",
    "wof:placetype":"venue"
},
  "geometry": {"coordinates":[-16.7168064117,28.3693466187],"type":"Point"}
}