{
  "type": "Feature",
  "properties": {
    "iso:country":"ES",
    "sg:address":"Avda Gomez Laguna, 155",
    "sg:city":"Zaragoza",
    "sg:classifiers":[
        {
            "category":"Taxi",
            "type":"Transportation"
        }
    ],
    "sg:phone":"+34 976 75 15 14",
    "sg:postcode":"50009",
    "sg:province":"Zaragoza",
    "wof:name":"Cooperativa De Auto Taxi",
    "wof:placetype":"venue"
},
  "geometry": {"coordinates":[-0.913507998,41.6404418945],"type":"Point"}
}