{
  "type": "Feature",
  "properties": {
    "addr:full":"Calle de Maria De Molina, 6 Madrid Madrid 28...",
    "addr:housenumber":"6;28 ...",
    "addr:street":"Calle De Maria De Molina;Madrid",
    "iso:country":"ES",
    "sg:address":"Calle de Maria De Molina, 6",
    "sg:city":"Madrid",
    "sg:orig_category":"Cajas De Ahorro",
    "sg:phone":"+34 914 36 63 80",
    "sg:postcode":"28...",
    "sg:province":"Madrid",
    "wof:name":"Caixa D'estalvis I Pensions De Barcelona",
    "wof:placetype":"venue"
},
  "geometry": {"coordinates":[-3.6892058849,40.4378318787],"type":"Point"}
}