{
  "type": "Feature",
  "properties": {
    "addr:full":"Carr Lloren\u00c7 Tomas I Costa, 74 Seu D'urgell Lleida 25700",
    "addr:housenumber":"74",
    "addr:postcode":"25700",
    "addr:street":"Carr Llorenc\u0327 Tomas I Costa",
    "iso:country":"ES",
    "sg:address":"Carr Lloren\u00c7 Tomas I Costa, 74",
    "sg:city":"Seu D'urgell",
    "sg:orig_category":"Carnicer\u00cdas, Carnicer\u00cdas",
    "sg:phone":"+34 973 36 08 50",
    "sg:postcode":"25700",
    "sg:province":"Lleida",
    "wof:name":"Xarcuteria Pages S.c.p.",
    "wof:placetype":"venue"
},
  "geometry": {"coordinates":[1.4576772451,42.3563499451],"type":"Point"}
}