{
  "type": "Feature",
  "properties": {
    "iso:country":"ES",
    "sg:address":"Calle de Rosario, 10",
    "sg:city":"Sevilla",
    "sg:orig_category":"Agencias De Viajes",
    "sg:phone":"+34 902 23 90 33",
    "sg:postcode":"41001",
    "sg:province":"Sevilla",
    "sg:website":"wwww.pilman.com",
    "wof:name":"Viajes Pilman S.l.",
    "wof:placetype":"venue"
},
  "geometry": {"coordinates":[-5.9961681366,37.3902397156],"type":"Point"}
}