{
  "type": "Feature",
  "properties": {
    "addr:full":"Zubierreka Auzoa, S/n Zubierreka Guip\u00f9zcoa 20210",
    "addr:housenumber":"s / n",
    "addr:postcode":"20210",
    "addr:street":"Zubierreka Auzoa;Zubierreka Guipu\u0300Zcoa",
    "iso:country":"ES",
    "sg:address":"Zubierreka Auzoa, S/n",
    "sg:city":"Zubierreka",
    "sg:orig_category":"Maquinaria Para Industrias Diversas",
    "sg:phone":"+34 943 88 02 99",
    "sg:postcode":"20210",
    "sg:province":"Guip\u00f9zcoa",
    "wof:name":"Talleres Mecanicos Largui S.l.",
    "wof:placetype":"venue"
},
  "geometry": {"coordinates":[-2.1873590946,43.0314903259],"type":"Point"}
}