{
  "type": "Feature",
  "properties": {
    "addr:full":"Psaj Santa Ana, 4 Torremolinos M\u00e1laga 29620",
    "addr:housenumber":"4",
    "addr:postcode":"29620",
    "addr:street":"Santa Ana;Ma\u0301Laga",
    "iso:country":"ES",
    "sg:address":"Psaj Santa Ana, 4",
    "sg:city":"Torremolinos",
    "sg:orig_category":"Marroquiner\u00cda (confecci\u00d3n)",
    "sg:phone":"+34 952 37 14 54",
    "sg:postcode":"29620",
    "sg:province":"M\u00e1laga",
    "wof:name":"Minun Mohamed Mohamed",
    "wof:placetype":"venue"
},
  "geometry": {"coordinates":[-4.4998540878,36.6244087219],"type":"Point"}
}