{
  "type": "Feature",
  "properties": {
    "addr:full":"Ctra. Malaga, S/n Loja Granada 18300",
    "addr:housenumber":"loja",
    "addr:postcode":"18300",
    "addr:street":"Ctra. Malaga S / N",
    "iso:country":"ES",
    "sg:address":"Ctra. Malaga, S/n",
    "sg:city":"Loja",
    "sg:orig_category":"Hormigonados",
    "sg:phone":"+34 958 34 11 13",
    "sg:postcode":"18300",
    "sg:province":"Granada",
    "wof:name":"Antonio Matas S.l.",
    "wof:placetype":"venue"
},
  "geometry": {"coordinates":[-4.2123422623,37.1356163025],"type":"Point"}
}