{
  "type": "Feature",
  "properties": {
    "addr:full":"Cmno Goleta (de La), 57 Almeria Almer\u00eda 04006",
    "addr:housenumber":"57",
    "addr:postcode":"04006",
    "addr:street":"Cmno Goleta De La",
    "iso:country":"ES",
    "sg:address":"Cmno Goleta (de La), 57",
    "sg:city":"Almeria",
    "sg:orig_category":"Caf\u00c9s, Bares, Cervecer\u00cdas",
    "sg:phone":"+34 950 22 85 91",
    "sg:postcode":"04006",
    "sg:province":"Almer\u00eda",
    "wof:name":"Calero Garcia Antonio Miguel",
    "wof:placetype":"venue"
},
  "geometry": {"coordinates":[-2.4608390331,36.8422698975],"type":"Point"}
}