{
  "type": "Feature",
  "properties": {
    "addr:full":"Avda Parador (del), 30 Bailen Ja\u00e9n 23710",
    "addr:housenumber":"30",
    "addr:postcode":"23710",
    "addr:street":"Avda Parador Del;Jae\u0301N",
    "iso:country":"ES",
    "sg:address":"Avda Parador (del), 30",
    "sg:city":"Bailen",
    "sg:orig_category":"Electrodom\u00c9sticos (al Por Menor)",
    "sg:phone":"+34 953 67 12 10",
    "sg:postcode":"23710",
    "sg:province":"Ja\u00e9n",
    "wof:name":"Lorente Girona Jose",
    "wof:placetype":"venue"
},
  "geometry": {"coordinates":[-3.7710540295,38.0965309143],"type":"Point"}
}