{
  "type": "Feature",
  "properties": {
    "addr:full":"Calle de Haba, 33 Villanueva Serena Badajoz 06700",
    "addr:housenumber":"33",
    "addr:postcode":"06700",
    "addr:street":"Calle De Haba",
    "iso:country":"ES",
    "sg:address":"Calle de Haba, 33",
    "sg:city":"Villanueva Serena",
    "sg:orig_category":"Psic\u00d3logos",
    "sg:phone":"+34 924 84 55 99",
    "sg:postcode":"06700",
    "sg:province":"Badajoz",
    "wof:name":"Prieto Atanasio Antonio Jose",
    "wof:placetype":"venue"
},
  "geometry": {"coordinates":[-5.7992391586,38.9729881287],"type":"Point"}
}