{
  "type": "Feature",
  "properties": {
    "iso:country":"ES",
    "sg:address":"Pol Ind Magdalena, S/n",
    "sg:city":"Castello Plana",
    "sg:orig_category":"Adaptaciones, Acondicionamientos Especiales Para Veh\u00cdculos, Veh\u00cdculos Industriales",
    "sg:phone":"+34 964 21 66 79",
    "sg:postcode":"12004",
    "sg:province":"Castell\u00f3n",
    "wof:name":"Gas Navarro Francisco Jose",
    "wof:placetype":"venue"
},
  "geometry": {"coordinates":[-0.0441690013,40.0043563843],"type":"Point"}
}