{
  "type": "Feature",
  "properties": {
    "iso:country":"ES",
    "sg:address":"Prolongacion El Puente, 62",
    "sg:city":"Santa Cruz Palma",
    "sg:orig_category":"Transporte En General",
    "sg:phone":"+34 922 41 25 30",
    "sg:postcode":"38700",
    "sg:province":"Santa Cruz De Tenerife",
    "wof:name":"Aperitivos Snacks S.a.",
    "wof:placetype":"venue"
},
  "geometry": {"coordinates":[-17.7697505951,28.6869468689],"type":"Point"}
}