{
  "type": "Feature",
  "properties": {
    "addr:full":"Calle de Real, 20 Torrejon Calzada Madrid 28991",
    "addr:housenumber":"20",
    "addr:postcode":"28991",
    "addr:street":"Calle De Real;Calzada",
    "iso:country":"ES",
    "sg:address":"Calle de Real, 20",
    "sg:city":"Torrejon Calzada",
    "sg:orig_category":"Inmobiliaria (agencias)",
    "sg:phone":"+34 918 10 60 81",
    "sg:postcode":"28991",
    "sg:province":"Madrid",
    "wof:name":"Guscasa Inmobiliaria S.l.",
    "wof:placetype":"venue"
},
  "geometry": {"coordinates":[-3.8003680706,40.2005767822],"type":"Point"}
}