{
  "type": "Feature",
  "properties": {
    "addr:full":"Miudes, S/n Miudes Asturias 33758",
    "addr:postcode":"33758",
    "addr:street":"Miudes S / N Miudes Asturias",
    "iso:country":"ES",
    "sg:address":"Miudes, S/n",
    "sg:city":"Miudes",
    "sg:orig_category":"Granos Y Semillas (producci\u00d3n, Al Por Mayor)",
    "sg:phone":"+34 985 63 76 68",
    "sg:postcode":"33758",
    "sg:province":"Asturias",
    "wof:name":"Noroeste Agropecuario S. L",
    "wof:placetype":"venue"
},
  "geometry": {"coordinates":[-6.8051829338,43.5472984314],"type":"Point"}
}