{
  "type": "Feature",
  "properties": {
    "addr:full":"Avda Ancares, 71 Vega Espinareda Le\u00f3n 24430",
    "addr:housenumber":"71",
    "addr:postcode":"24430",
    "addr:street":"Avda Ancares;Espinareda Leo\u0301N",
    "iso:country":"ES",
    "sg:address":"Avda Ancares, 71",
    "sg:city":"Vega Espinareda",
    "sg:orig_category":"Mec\u00c1nico Del Autom\u00d3vil",
    "sg:phone":"+34 987 56 84 81",
    "sg:postcode":"24430",
    "sg:province":"Le\u00f3n",
    "wof:name":"Talleres Pi\u00f1era S.l.",
    "wof:placetype":"venue"
},
  "geometry": {"coordinates":[-6.6542592049,42.7258110046],"type":"Point"}
}