{
  "type": "Feature",
  "properties": {
    "iso:country":"ES",
    "sg:address":"Calle de Fuente Bodillas, 7",
    "sg:city":"Porzuna",
    "sg:orig_category":"Materiales De Aislamiento T\u00c9rmico Y Ac\u00dastico",
    "sg:phone":"+34 926 78 12 31",
    "sg:postcode":"13120",
    "sg:province":"Ciudad Real",
    "wof:name":"Orme\u00f1o Garcia Jose Antonio",
    "wof:placetype":"venue"
},
  "geometry": {"coordinates":[-4.1525301933,39.1446418762],"type":"Point"}
}