{
  "type": "Feature",
  "properties": {
    "iso:country":"ES",
    "sg:address":"Calle de Punta Umbria, 1",
    "sg:city":"Ayamonte",
    "sg:orig_category":"Asociaciones Humanitarias, De Cooperaci\u00d3n, De Acci\u00d3n Social",
    "sg:phone":"+34 959 32 02 11",
    "sg:postcode":"21400",
    "sg:province":"Huelva",
    "wof:name":"Asociacion De Minusvalidos Aprosca",
    "wof:placetype":"venue"
},
  "geometry": {"coordinates":[-7.4047093391,37.2065429688],"type":"Point"}
}