{
  "type": "Feature",
  "properties": {
    "addr:full":"Calle de Mayor Principal, 8 Palencia Palencia 34001",
    "addr:housenumber":"8",
    "addr:postcode":"34001",
    "addr:street":"Calle De Mayor Principal",
    "iso:country":"ES",
    "sg:address":"Calle de Mayor Principal, 8",
    "sg:city":"Palencia",
    "sg:orig_category":"Abogados",
    "sg:phone":"+34 979 74 92 70",
    "sg:postcode":"34001",
    "sg:province":"Palencia",
    "wof:name":"Alonso Trece\u00f1o Carlos",
    "wof:placetype":"venue"
},
  "geometry": {"coordinates":[-4.5327916145,42.0124015808],"type":"Point"}
}