{
  "type": "Feature",
  "properties": {
    "iso:country":"ES",
    "sg:address":"Calle de Canalejas, 38",
    "sg:city":"Palmas De Gran Canaria",
    "sg:orig_category":"Abogados",
    "sg:phone":"+34 928 37 40 84",
    "sg:postcode":"35003",
    "sg:province":"Las Palmas",
    "wof:name":"Palomo Montenegro Francisco",
    "wof:placetype":"venue"
},
  "geometry": {"coordinates":[-15.420217514,28.1101436615],"type":"Point"}
}