{
  "type": "Feature",
  "properties": {
    "iso:country":"ES",
    "sg:address":"Calle de San Jacinto, 85",
    "sg:city":"Sevilla",
    "sg:orig_category":"Ropa Para Ni\u00d1os (al Por Menor)",
    "sg:phone":"+34 954 33 48 11",
    "sg:postcode":"41010",
    "sg:province":"Sevilla",
    "wof:name":"Crespo Mateo Rosa Maria",
    "wof:placetype":"venue"
},
  "geometry": {"coordinates":[-6.0071191788,37.38230896],"type":"Point"}
}