{
  "type": "Feature",
  "properties": {
    "iso:country":"ES",
    "sg:address":"Calle de Enrique Sanchez, 47",
    "sg:city":"Palmas De Gran Canaria",
    "sg:orig_category":"Venta, Colocaci\u00d3n, Reparaci\u00d3n De Radiadores Para Veh\u00cdculos",
    "sg:phone":"+34 928 42 00 47",
    "sg:postcode":"35013",
    "sg:province":"Las Palmas",
    "wof:name":"Deniz Deniz Pedro Manuel",
    "wof:placetype":"venue"
},
  "geometry": {"coordinates":[-15.4398040771,28.100112915],"type":"Point"}
}