{
  "type": "Feature",
  "properties": {
    "iso:country":"ES",
    "sg:address":"Avda Madrid (de), 27",
    "sg:city":"Avila",
    "sg:orig_category":"Bisuter\u00cda, Joyer\u00cda, Relojer\u00cda (al Por Menor)",
    "sg:phone":"+34 920 25 38 00",
    "sg:postcode":"05001",
    "sg:province":"\u00c1vila",
    "wof:name":"Diaz Gonzalez Comunicaciones S.l.",
    "wof:placetype":"venue"
},
  "geometry": {"coordinates":[-4.6931648254,40.6578025818],"type":"Point"}
}