{
  "type": "Feature",
  "properties": {
    "iso:country":"ES",
    "sg:address":"R. De Cabrils (pol Ind Garrofers), Km. 0001,4",
    "sg:city":"Vilassar",
    "sg:orig_category":"Discotecas Y Salas De Baile",
    "sg:phone":"+34 937 54 00 62",
    "sg:postcode":"08340",
    "sg:province":"Barcelona",
    "wof:name":"Conservas Dani S.a.u.",
    "wof:placetype":"venue"
},
  "geometry": {"coordinates":[2.3907299042,41.5019264221],"type":"Point"}
}