{
  "type": "Feature",
  "properties": {
    "iso:country":"ES",
    "sg:address":"Calle de Luis De Medina, 4",
    "sg:city":"Alcala Henares",
    "sg:orig_category":"Cr\u00cda De Animales",
    "sg:phone":"+34 918 78 93 23",
    "sg:postcode":"28805",
    "sg:province":"Madrid",
    "wof:name":"Ambite Barco Maria Soledad",
    "wof:placetype":"venue"
},
  "geometry": {"coordinates":[-3.3561985493,40.4893722534],"type":"Point"}
}