{
  "type": "Feature",
  "properties": {
    "addr:full":"Maliciosa, 40 Tres Cantos Madrid 28760",
    "addr:housenumber":"40",
    "addr:postcode":"28760",
    "addr:street":"Maliciosa",
    "iso:country":"ES",
    "sg:address":"Maliciosa, 40",
    "sg:city":"Tres Cantos",
    "sg:orig_category":"Zapatos (al Por Menor)",
    "sg:phone":"+34 918 03 46 52",
    "sg:postcode":"28760",
    "sg:province":"Madrid",
    "wof:name":"Arias Avila Armando",
    "wof:placetype":"venue"
},
  "geometry": {"coordinates":[-3.7158522606,40.6118164062],"type":"Point"}
}