{
  "type": "Feature",
  "properties": {
    "addr:full":"Polig. Pocomaco, 5 A Coru\u00f1a A Coru\u00f1a 15190",
    "addr:housenumber":"5 a",
    "addr:postcode":"15190",
    "addr:street":"Polig. Pocomaco;Corun\u0303A A Corun\u0303A",
    "iso:country":"ES",
    "sg:address":"Polig. Pocomaco, 5",
    "sg:city":"A Coru\u00f1a",
    "sg:orig_category":"Escayola Y Productos De Escayola (fabricaci\u00d3n, Al Por Mayor)",
    "sg:phone":"+34 981 13 02 47",
    "sg:postcode":"15190",
    "sg:province":"A Coru\u00f1a",
    "wof:name":"Torrenort S.l.",
    "wof:placetype":"venue"
},
  "geometry": {"coordinates":[-8.4312744141,43.3228416443],"type":"Point"}
}