{
  "type": "Feature",
  "properties": {
    "iso:country":"ES",
    "sg:address":"Ctra Valladolid, S/n",
    "sg:city":"Lastrilla",
    "sg:orig_category":"Comercio De Piezas De Recambio Y De Accesorios De Veh\u00cdculos, Veh\u00cdculos Industriales",
    "sg:phone":"+34 921 43 10 12",
    "sg:postcode":"40196",
    "sg:province":"Segovia",
    "wof:name":"Autodisco S. A.",
    "wof:placetype":"venue"
},
  "geometry": {"coordinates":[-4.1068720818,40.9651298523],"type":"Point"}
}