{
  "type": "Feature",
  "properties": {
    "iso:country":"ES",
    "sg:address":"Calle de Uruguay, 25",
    "sg:city":"Coslada",
    "sg:orig_category":"Florister\u00cdas",
    "sg:phone":"+34 916 74 12 23",
    "sg:postcode":"28820",
    "sg:province":"Madrid",
    "wof:name":"Vicente Rincon Pilar",
    "wof:placetype":"venue"
},
  "geometry": {"coordinates":[-3.5504720211,40.425239563],"type":"Point"}
}