{
  "type": "Feature",
  "properties": {
    "iso:country":"ES",
    "sg:address":"Avda Leizaur, 2",
    "sg:city":"Peralta",
    "sg:orig_category":"Alimentaci\u00d3n General (al Por Menor)",
    "sg:phone":"+34 948 75 06 82",
    "sg:postcode":"31350",
    "sg:province":"Navarra",
    "wof:name":"Alfredo Barcos Y Julia Lezaun S.i.",
    "wof:placetype":"venue"
},
  "geometry": {"coordinates":[-1.8092217445,42.3418655396],"type":"Point"}
}