{
  "type": "Feature",
  "properties": {
    "addr:full":"Carrer de Sant Cristofol, 24 Piera Barcelona 08784",
    "addr:housenumber":"24",
    "addr:postcode":"08784",
    "addr:street":"Carrer De Sant Cristofol",
    "iso:country":"ES",
    "sg:address":"Carrer de Sant Cristofol, 24",
    "sg:city":"Piera",
    "sg:orig_category":"Relojer\u00cda (al Por Menor, Reparaci\u00d3n)",
    "sg:phone":"+34 937 76 19 19",
    "sg:postcode":"08784",
    "sg:province":"Barcelona",
    "wof:name":"Clavero Soler Mercedes",
    "wof:placetype":"venue"
},
  "geometry": {"coordinates":[1.7496210337,41.5209693909],"type":"Point"}
}