{
  "type": "Feature",
  "properties": {
    "addr:full":"Avda Tanausu, 23 Llanos De Aridane Santa Cruz De Tenerife 38760",
    "addr:housenumber":"23",
    "addr:postcode":"38760",
    "addr:street":"Avda Tanausu",
    "iso:country":"ES",
    "sg:address":"Avda Tanausu, 23",
    "sg:city":"Llanos De Aridane",
    "sg:orig_category":"Agentes, Concesionarios Y Sucursales De Veh\u00cdculos",
    "sg:phone":"+34 922 46 32 87",
    "sg:postcode":"38760",
    "sg:province":"Santa Cruz De Tenerife",
    "wof:name":"Cicilia Lorenzo Manuel Carlos",
    "wof:placetype":"venue"
},
  "geometry": {"coordinates":[-17.9166927338,28.6587238312],"type":"Point"}
}