{
  "type": "Feature",
  "properties": {
    "iso:country":"ES",
    "sg:address":"Via Laietana, 64",
    "sg:city":"Barcelona",
    "sg:orig_category":"Agencias Y Asesores De Publicidad",
    "sg:phone":"+34 932 38 83 04",
    "sg:postcode":"08003",
    "sg:province":"Barcelona",
    "wof:name":"Villar Y Rosas Agencia Publicidad S.l.",
    "wof:placetype":"venue"
},
  "geometry": {"coordinates":[2.173322916,41.388256073],"type":"Point"}
}