{
  "type": "Feature",
  "properties": {
    "addr:full":"Calle de Amposta, 14 Madrid Madrid 28037",
    "addr:housenumber":"14",
    "addr:postcode":"madrid;28037",
    "addr:street":"Calle De Amposta",
    "iso:country":"ES",
    "sg:address":"Calle de Amposta, 14",
    "sg:city":"Madrid",
    "sg:orig_category":"Ropa Para Se\u00d1oras Y Caballeros (al Por Menor)",
    "sg:phone":"+34 913 06 93 35",
    "sg:postcode":"28037",
    "sg:province":"Madrid",
    "wof:name":"Martinez Martinez Francisco",
    "wof:placetype":"venue"
},
  "geometry": {"coordinates":[-3.6218736172,40.4267654419],"type":"Point"}
}