{
  "type": "Feature",
  "properties": {
    "iso:country":"ES",
    "sg:address":"Calle de Salva, 12",
    "sg:city":"Valencia",
    "sg:orig_category":"Bisuter\u00cda, Joyer\u00cda, Relojer\u00cda (al Por Menor)",
    "sg:phone":"+34 963 52 46 37",
    "sg:postcode":"46002",
    "sg:province":"Valencia",
    "wof:name":"Guardiola Pla Maria Teresa",
    "wof:placetype":"venue"
},
  "geometry": {"coordinates":[-0.3728848994,39.4715843201],"type":"Point"}
}