{
  "type": "Feature",
  "properties": {
    "iso:country":"ES",
    "sg:address":"Errosario Kalea, 17",
    "sg:city":"Elgoibar",
    "sg:orig_category":"Asociaciones Y Clubs Deportivos",
    "sg:phone":"+34 943 74 02 97",
    "sg:postcode":"20870",
    "sg:province":"Guip\u00f9zcoa",
    "wof:name":"Morkaiko Mendi Elkartea",
    "wof:placetype":"venue"
},
  "geometry": {"coordinates":[-2.4161999226,43.214969635],"type":"Point"}
}