{
  "type": "Feature",
  "properties": {
    "iso:country":"ES",
    "sg:address":"Pla\u00c7 Calvet I Rubalcaba, S/n",
    "sg:city":"Girona",
    "sg:orig_category":"Poller\u00cda Y Caza (al Por Menor)",
    "sg:phone":"+34 972 21 88 66",
    "sg:postcode":"17002",
    "sg:province":"Girona",
    "wof:name":"Canals Planas Marta",
    "wof:placetype":"venue"
},
  "geometry": {"coordinates":[2.8222908974,41.9793663025],"type":"Point"}
}