{
  "type": "Feature",
  "properties": {
    "iso:country":"ES",
    "sg:address":"Calle de Bermudez De Castro, 96",
    "sg:city":"Oviedo",
    "sg:orig_category":"Frutas, Legumbres Frescas Y Tempranas (al Por Menor)",
    "sg:phone":"+34 985 11 30 58",
    "sg:postcode":"33011",
    "sg:province":"Asturias",
    "wof:name":"Vazquez Lopez Manuel",
    "wof:placetype":"venue"
},
  "geometry": {"coordinates":[-5.8341341019,43.3756370544],"type":"Point"}
}