{
  "type": "Feature",
  "properties": {
    "addr:full":"Calle de Zurbaran (de), 1 Parla Madrid 28980",
    "addr:postcode":"28980",
    "addr:street":"Calle De Zurbaran De 1",
    "iso:country":"ES",
    "sg:address":"Calle de Zurbaran (de), 1",
    "sg:city":"Parla",
    "sg:orig_category":"Confecci\u00d3n (fabricaci\u00d3n, Al Por Mayor)",
    "sg:phone":"+34 916 99 54 94",
    "sg:postcode":"28980",
    "sg:province":"Madrid",
    "wof:name":"Sanchez Sanchez Leoncio",
    "wof:placetype":"venue"
},
  "geometry": {"coordinates":[-3.7627670765,40.2410507202],"type":"Point"}
}