{
  "type": "Feature",
  "properties": {
    "addr:full":"Carrer de Eivissa (d'), 3 Tarragona Tarragona 43005",
    "addr:housenumber":"3",
    "addr:postcode":"43005",
    "addr:street":"Carrer De Eivissa D '",
    "iso:country":"ES",
    "sg:address":"Carrer de Eivissa (d'), 3",
    "sg:city":"Tarragona",
    "sg:orig_category":"Molduras, Junquillos, Listones Y Molduras Perforadas",
    "sg:phone":"+34 977 23 08 25",
    "sg:postcode":"43005",
    "sg:province":"Tarragona",
    "wof:name":"Romero Gonzalez Manuel",
    "wof:placetype":"venue"
},
  "geometry": {"coordinates":[1.2453030348,41.1139678955],"type":"Point"}
}