{
  "type": "Feature",
  "properties": {
    "iso:country":"ES",
    "sg:address":"Calle de Juan Pombo, 2",
    "sg:city":"Quintanilla Onesimo",
    "sg:orig_category":"Cajas Y Embalajes De Madera",
    "sg:phone":"+34 983 68 05 55",
    "sg:postcode":"47350",
    "sg:province":"Valladolid",
    "wof:name":"Fadrique Estuches S.l.",
    "wof:placetype":"venue"
},
  "geometry": {"coordinates":[-4.3622441292,41.6264533997],"type":"Point"}
}