{
  "type": "Feature",
  "properties": {
    "addr:full":"Luga Belonga, S/n Belonga Asturias 33193",
    "addr:housenumber":"s",
    "addr:postcode":"33193",
    "addr:street":"/ N Belonga Asturias",
    "iso:country":"ES",
    "sg:address":"Luga Belonga, S/n",
    "sg:city":"Belonga",
    "sg:orig_category":"Asociaciones Y Clubs Deportivos",
    "sg:phone":"+34 985 79 69 91",
    "sg:postcode":"33193",
    "sg:province":"Asturias",
    "wof:name":"Asociacion Deportiva Principado De Tiro Olimpico",
    "wof:placetype":"venue"
},
  "geometry": {"coordinates":[-5.9832577705,43.2504386902],"type":"Point"}
}