{
  "type": "Feature",
  "properties": {
    "addr:full":"Calle de Almas, 8 Vinaros Castell\u00f3n 12500",
    "addr:housenumber":"8",
    "addr:postcode":"12500",
    "addr:street":"Calle De Almas",
    "iso:country":"ES",
    "sg:address":"Calle de Almas, 8",
    "sg:city":"Vinaros",
    "sg:orig_category":"M\u00c9dicos: Ginecolog\u00cda Y Obstetricia",
    "sg:phone":"+34 964 45 32 14",
    "sg:postcode":"12500",
    "sg:province":"Castell\u00f3n",
    "wof:name":"Rey Otero Ricardo",
    "wof:placetype":"venue"
},
  "geometry": {"coordinates":[0.477779299,40.4732551575],"type":"Point"}
}