{
  "type": "Feature",
  "properties": {
    "addr:full":"Plaz Aladreros (de), 1 Cordoba C\u00f3rdoba 14008",
    "addr:postcode":"14008",
    "addr:street":"Plaz;Co\u0301Rdoba",
    "iso:country":"ES",
    "sg:address":"Plaz Aladreros (de), 1",
    "sg:city":"Cordoba",
    "sg:orig_category":"M\u00c9dicos: Pediatr\u00cda. Enfermedades De Los Ni\u00d1os",
    "sg:phone":"+34 957 47 14 22",
    "sg:postcode":"14008",
    "sg:province":"C\u00f3rdoba",
    "wof:name":"Jimenez Santos Florentin Jesus",
    "wof:placetype":"venue"
},
  "geometry": {"coordinates":[-4.7841248512,37.8855323792],"type":"Point"}
}