{
  "type": "Feature",
  "properties": {
    "addr:full":"Calle de Zurbaran, 10 Mairena Aljarafe Sevilla 41927",
    "addr:housenumber":"10",
    "addr:postcode":"41927",
    "addr:street":"Calle De Zurbaran",
    "iso:country":"ES",
    "sg:address":"Calle de Zurbaran, 10",
    "sg:city":"Mairena Aljarafe",
    "sg:orig_category":"Agencias Y Asesores De Publicidad",
    "sg:phone":"+34 955 60 92 95",
    "sg:postcode":"41927",
    "sg:province":"Sevilla",
    "wof:name":"Publicaciones E Internet S.l.",
    "wof:placetype":"venue"
},
  "geometry": {"coordinates":[-6.0696988106,37.3426551819],"type":"Point"}
}