{
  "type": "Feature",
  "properties": {
    "iso:country":"ES",
    "sg:address":"Calle de Ebanistas (los), 21",
    "sg:city":"Alcorcon",
    "sg:orig_category":"Cristaler\u00cdas",
    "sg:phone":"+34 916 41 83 83",
    "sg:postcode":"28925",
    "sg:province":"Madrid",
    "wof:name":"Jalo Glasss.l.",
    "wof:placetype":"venue"
},
  "geometry": {"coordinates":[-3.8057146072,40.3414993286],"type":"Point"}
}