{
  "type": "Feature",
  "properties": {
    "iso:country":"ES",
    "sg:address":"Carr Miquel Verdera, 59",
    "sg:city":"Pobla",
    "sg:orig_category":"Asociaciones Y Clubs Deportivos",
    "sg:phone":"+34 971 54 16 52",
    "sg:postcode":"07420",
    "sg:province":"Islas Baleares",
    "wof:name":"Planas Colom Mateo",
    "wof:placetype":"venue"
},
  "geometry": {"coordinates":[3.0173139572,39.7702255249],"type":"Point"}
}