{
  "type": "Feature",
  "properties": {
    "addr:full":"Calle de Albacete, 2 Valencia Valencia 46007",
    "addr:housenumber":"2",
    "addr:postcode":"46007",
    "addr:street":"Calle De Albacete",
    "iso:country":"ES",
    "sg:address":"Calle de Albacete, 2",
    "sg:city":"Valencia",
    "sg:orig_category":"Institutos De Belleza",
    "sg:phone":"+34 963 80 68 03",
    "sg:postcode":"46007",
    "sg:province":"Valencia",
    "wof:name":"Garcia Sanz Pilar",
    "wof:placetype":"venue"
},
  "geometry": {"coordinates":[-0.3824042082,39.4654045105],"type":"Point"}
}