{
  "type": "Feature",
  "properties": {
    "iso:country":"ES",
    "sg:address":"Carrer de Sant Xavier, 23",
    "sg:city":"Vendrell",
    "sg:orig_category":"Farmacias",
    "sg:phone":"+34 977 66 02 75",
    "sg:postcode":"43700",
    "sg:province":"Tarragona",
    "wof:name":"Parra Trillas Pedro Antonio",
    "wof:placetype":"venue"
},
  "geometry": {"coordinates":[1.5313669443,41.218536377],"type":"Point"}
}