{
  "type": "Feature",
  "properties": {
    "iso:country":"ES",
    "sg:address":"Calle de Juan Fernandez, S/n",
    "sg:city":"Paso",
    "sg:orig_category":"Arquitectos",
    "sg:phone":"+34 922 49 74 76",
    "sg:postcode":"38750",
    "sg:province":"Santa Cruz De Tenerife",
    "wof:name":"Fischer  Franka",
    "wof:placetype":"venue"
},
  "geometry": {"coordinates":[-17.8799343109,28.6529541016],"type":"Point"}
}