{
  "type": "Feature",
  "properties": {
    "iso:country":"ES",
    "sg:address":"Ola Kalea-calle De La Ferreria, 14",
    "sg:city":"Lasarte-oria",
    "sg:orig_category":"Mec\u00c1nico Del Autom\u00d3vil",
    "sg:phone":"+34 943 36 36 26",
    "sg:postcode":"20160",
    "sg:province":"Guip\u00f9zcoa",
    "wof:name":"Jose De La Calle Diez",
    "wof:placetype":"venue"
},
  "geometry": {"coordinates":[-2.020414114,43.2698173523],"type":"Point"}
}