{
  "type": "Feature",
  "properties": {
    "addr:full":"Calle de Fernando Iii El Santo, 7 Linares Ja\u00e9n 23700",
    "addr:housenumber":"7",
    "addr:postcode":"23700",
    "addr:street":"Calle De Fernando Iii El Santo;Jae\u0301N",
    "iso:country":"ES",
    "sg:address":"Calle de Fernando Iii El Santo, 7",
    "sg:city":"Linares",
    "sg:orig_category":"Sociedades, Compa\u00d1\u00cdas Aseguradoras",
    "sg:phone":"+34 953 69 06 18",
    "sg:postcode":"23700",
    "sg:province":"Ja\u00e9n",
    "wof:name":"Lopez Gomez Encarnacion Del Socorro",
    "wof:placetype":"venue"
},
  "geometry": {"coordinates":[-3.6323471069,38.0958824158],"type":"Point"}
}