{
  "type": "Feature",
  "properties": {
    "iso:country":"ES",
    "sg:address":"Calle de Manuel Mato, 3",
    "sg:city":"Vilalba",
    "sg:orig_category":"Ingenier\u00cda, Centros De Estudios (diversos)",
    "sg:phone":"+34 982 52 32 22",
    "sg:postcode":"27800",
    "sg:province":"Lugo",
    "wof:name":"Bardera Obras Civiles Y Maritimas S.l.",
    "wof:placetype":"venue"
},
  "geometry": {"coordinates":[-7.6795740128,43.2989387512],"type":"Point"}
}