{
  "type": "Feature",
  "properties": {
    "iso:country":"ES",
    "sg:address":"Calle de San Luis, 91",
    "sg:city":"Sevilla",
    "sg:orig_category":"Servidores Y Editores De Bases De Datos",
    "sg:phone":"+34 954 37 30 35",
    "sg:postcode":"41003",
    "sg:province":"Sevilla",
    "wof:name":"Rodriguez Avila Fancisco Javier",
    "wof:placetype":"venue"
},
  "geometry": {"coordinates":[-5.9888091087,37.4009094238],"type":"Point"}
}