{
  "type": "Feature",
  "properties": {
    "iso:country":"ES",
    "sg:address":"Calle de Felipe Estevez, 26",
    "sg:city":"Getafe",
    "sg:orig_category":"Ropa Y Art\u00cdculos Pre",
    "sg:phone":"+34 916 82 72 89",
    "sg:postcode":"28901",
    "sg:province":"Madrid",
    "wof:name":"Velasco Y Roncero S.l.",
    "wof:placetype":"venue"
},
  "geometry": {"coordinates":[-3.7304470539,40.3092536926],"type":"Point"}
}