{
  "type": "Feature",
  "properties": {
    "addr:full":"Plaz Mayor, 8 Porzuna Ciudad Real 13120",
    "addr:housenumber":"8",
    "addr:postcode":"13120",
    "addr:street":"Plaz Mayor",
    "iso:country":"ES",
    "sg:address":"Plaz Mayor, 8",
    "sg:city":"Porzuna",
    "sg:orig_category":"Loter\u00cda Y T\u00d3mbola",
    "sg:phone":"+34 926 78 02 54",
    "sg:postcode":"13120",
    "sg:province":"Ciudad Real",
    "wof:name":"Mora Garcia Maria Del Carmen",
    "wof:placetype":"venue"
},
  "geometry": {"coordinates":[-4.1534690857,39.1466178894],"type":"Point"}
}