{
  "type": "Feature",
  "properties": {
    "iso:country":"ES",
    "sg:address":"Cami Ca N'ubach, S/n",
    "sg:city":"Sant Vicen\u00c7 Dels Horts",
    "sg:orig_category":"Rectificaci\u00d3n, Mecanizado, Fresado",
    "sg:phone":"+34 936 72 31 75",
    "sg:postcode":"08620",
    "sg:province":"Barcelona",
    "wof:name":"Bcn Metalls S.l.",
    "wof:placetype":"venue"
},
  "geometry": {"coordinates":[1.9936269522,41.40467453],"type":"Point"}
}