{
  "type": "Feature",
  "properties": {
    "addr:full":"Calle de Bahia, S/n Valdelagrana C\u00e1diz 11500",
    "addr:housenumber":"s",
    "addr:postcode":"11500",
    "addr:street":"Calle De Bahia;/ N Valdelagrana Ca\u0301Diz",
    "iso:country":"ES",
    "sg:address":"Calle de Bahia, S/n",
    "sg:city":"Valdelagrana",
    "sg:orig_category":"Asesor\u00cda Sobre Comunicaci\u00d3n De Empresas",
    "sg:phone":"+34 956 85 18 78",
    "sg:postcode":"11500",
    "sg:province":"C\u00e1diz",
    "wof:name":"Im 11 S.l.",
    "wof:placetype":"venue"
},
  "geometry": {"coordinates":[-6.2248520851,36.5807342529],"type":"Point"}
}