{
  "type": "Feature",
  "properties": {
    "iso:country":"ES",
    "sg:address":"Calle de Emilio Baro, 82",
    "sg:city":"Valencia",
    "sg:orig_category":"M\u00c9dicos: Estomatolog\u00cda",
    "sg:phone":"+34 963 62 97 73",
    "sg:postcode":"46020",
    "sg:province":"Valencia",
    "wof:name":"Perez Poveda Antonio",
    "wof:placetype":"venue"
},
  "geometry": {"coordinates":[-0.3593809903,39.490398407],"type":"Point"}
}