{
  "type": "Feature",
  "properties": {
    "addr:full":"Carrer de Riera De Tena, 18 Barcelona Barcelona 08014",
    "addr:housenumber":"18",
    "addr:postcode":"08014",
    "addr:street":"Carrer De Riera De Tena",
    "iso:country":"ES",
    "sg:address":"Carrer de Riera De Tena, 18",
    "sg:city":"Barcelona",
    "sg:orig_category":"Organizaciones Internacionales",
    "sg:phone":"+34 932 96 89 37",
    "sg:postcode":"08014",
    "sg:province":"Barcelona",
    "wof:name":"Caritas Diocesana De Barcelona",
    "wof:placetype":"venue"
},
  "geometry": {"coordinates":[2.1339149475,41.3708076477],"type":"Point"}
}