{
  "type": "Feature",
  "properties": {
    "iso:country":"ES",
    "sg:address":"Ctra. S-lisboa, S/n",
    "sg:city":"Aroche",
    "sg:orig_category":"Negocio De Materiales De Construcci\u00d3n",
    "sg:phone":"+34 959 14 03 35",
    "sg:postcode":"21240",
    "sg:province":"Huelva",
    "wof:name":"Alvarez Mojarro Jose Manuel",
    "wof:placetype":"venue"
},
  "geometry": {"coordinates":[-6.8220787048,37.9156112671],"type":"Point"}
}