{
  "type": "Feature",
  "properties": {
    "addr:full":"Avda Fernando Blanco, 49 Cee La Coru\u00f1a 15270",
    "addr:housenumber":"49",
    "addr:postcode":"15270",
    "addr:street":"Avda Fernando Blanco;La",
    "iso:country":"ES",
    "sg:address":"Avda Fernando Blanco, 49",
    "sg:city":"Cee",
    "sg:orig_category":"Parafarmacias",
    "sg:phone":"+34 981 74 50 50",
    "sg:postcode":"15270",
    "sg:province":"La Coru\u00f1a",
    "wof:name":"Fuentes Ares Maria Amparo",
    "wof:placetype":"venue"
},
  "geometry": {"coordinates":[-9.1906223297,42.9572868347],"type":"Point"}
}