{
  "type": "Feature",
  "properties": {
    "iso:country":"ES",
    "sg:address":"Rond Guinardo, 72",
    "sg:city":"Barcelona",
    "sg:orig_category":"Peluqueros: De Se\u00d1oras",
    "sg:phone":"+34 934 35 39 88",
    "sg:postcode":"08025",
    "sg:province":"Barcelona",
    "wof:name":"Mu\u00f1oz Sevillano Josefa",
    "wof:placetype":"venue"
},
  "geometry": {"coordinates":[2.1695320606,41.4130477905],"type":"Point"}
}