{
  "type": "Feature",
  "properties": {
    "iso:country":"ES",
    "sg:address":"Calle de Ignacio Sanchez Garcia, 5",
    "sg:city":"Ca\u00f1izal",
    "sg:orig_category":"Contenedores (mercanc\u00cdas)",
    "sg:phone":"+34 980 60 40 38",
    "sg:postcode":"49440",
    "sg:province":"Zamora",
    "wof:name":"Gallego Paniagua Francisco Javier",
    "wof:placetype":"venue"
},
  "geometry": {"coordinates":[-5.3665990829,41.1671257019],"type":"Point"}
}