{
  "type": "Feature",
  "properties": {
    "iso:country":"ES",
    "sg:address":"Calle de Libreria, 9",
    "sg:city":"Valladolid",
    "sg:orig_category":"Comercio De Cuadros, L\u00c1minas Y Reproducciones De Obras De Arte",
    "sg:phone":"+34 983 21 72 61",
    "sg:postcode":"47002",
    "sg:province":"Valladolid",
    "sg:website":"samuel@infonegocio.com",
    "wof:name":"Galeria De Arte Samuel S.l.",
    "wof:placetype":"venue"
},
  "geometry": {"coordinates":[-4.720843792,41.6522102356],"type":"Point"}
}