{
  "type": "Feature",
  "properties": {
    "addr:full":"Carrer de Gon\u00c7al Pons, 14 Hospitalet Llobregat Barcelona 08902",
    "addr:housenumber":"14",
    "addr:postcode":"08902",
    "addr:street":"Carrer De Gonc\u0327Al Pons",
    "iso:country":"ES",
    "sg:address":"Carrer de Gon\u00c7al Pons, 14",
    "sg:city":"Hospitalet Llobregat",
    "sg:orig_category":"Muebles, Minoristas",
    "sg:phone":"+34 932 98 04 13",
    "sg:postcode":"08902",
    "sg:province":"Barcelona",
    "wof:name":"Kit Paris S.l.",
    "wof:placetype":"venue"
},
  "geometry": {"coordinates":[2.1202459335,41.366645813],"type":"Point"}
}