{
  "type": "Feature",
  "properties": {
    "iso:country":"ES",
    "sg:address":"Carr Burriana, 9",
    "sg:city":"Silla",
    "sg:orig_category":"Molduras, Junquillos, Listones Y Molduras Perforadas",
    "sg:phone":"+34 961 20 15 71",
    "sg:postcode":"46460",
    "sg:province":"Valencia",
    "wof:name":"Comercial Igove 94 S.l.",
    "wof:placetype":"venue"
},
  "geometry": {"coordinates":[-0.4114300013,39.3565864563],"type":"Point"}
}