{
  "type": "Feature",
  "properties": {
    "addr:full":"Calle de Pradolongo, 1 Madrid Madrid 28041",
    "addr:housenumber":"1",
    "addr:postcode":"28041",
    "addr:street":"Calle De Pradolongo",
    "iso:country":"ES",
    "sg:address":"Calle de Pradolongo, 1",
    "sg:city":"Madrid",
    "sg:orig_category":"Cl\u00cdnicas Dentales",
    "sg:phone":"+34 913 41 33 92",
    "sg:postcode":"28041",
    "sg:province":"Madrid",
    "wof:name":"Dental Orcasitas S.l.",
    "wof:placetype":"venue"
},
  "geometry": {"coordinates":[-3.7093958855,40.3691139221],"type":"Point"}
}