{
  "type": "Feature",
  "properties": {
    "addr:full":"Calle de San Antonio, 15 Vitoria-gasteiz \u00c1lava 01005",
    "addr:housenumber":"15",
    "addr:postcode":"01005",
    "addr:street":"Calle De San Antonio",
    "iso:country":"ES",
    "sg:address":"Calle de San Antonio, 15",
    "sg:city":"Vitoria-gasteiz",
    "sg:orig_category":"Psicoterapeutas",
    "sg:phone":"+34 945 23 37 37",
    "sg:postcode":"01005",
    "sg:province":"\u00c1lava",
    "wof:name":"Latatu Angulo Maria Belen",
    "wof:placetype":"venue"
},
  "geometry": {"coordinates":[-2.6740911007,42.8443756104],"type":"Point"}
}