{
  "type": "Feature",
  "properties": {
    "iso:country":"ES",
    "sg:address":"Calle de Rey Juan Carlos I, 20",
    "sg:city":"Huete",
    "sg:orig_category":"Restaurantes",
    "sg:phone":"+34 969 37 11 55",
    "sg:postcode":"16500",
    "sg:province":"Cuenca",
    "wof:name":"Serrano Serrano Juan Jose",
    "wof:placetype":"venue"
},
  "geometry": {"coordinates":[-2.690212965,40.1455078125],"type":"Point"}
}