{
  "type": "Feature",
  "properties": {
    "iso:country":"ES",
    "sg:address":"Bajada Estacion, 9",
    "sg:city":"Xativa",
    "sg:orig_category":"Importaci\u00d3n",
    "sg:phone":"+34 962 28 35 55",
    "sg:postcode":"46800",
    "sg:province":"Valencia",
    "wof:name":"Euroxativa S.l",
    "wof:placetype":"venue"
},
  "geometry": {"coordinates":[-0.5200830102,38.9934272766],"type":"Point"}
}