{
  "type": "Feature",
  "properties": {
    "iso:country":"ES",
    "sg:address":"Avgd Castello, 60",
    "sg:city":"Benicasim",
    "sg:orig_category":"Carnicer\u00cdas, Carnicer\u00cdas",
    "sg:phone":"+34 964 30 06 01",
    "sg:postcode":"12560",
    "sg:province":"Castell\u00f3n",
    "wof:name":"Villanueva Adan Antonio",
    "wof:placetype":"venue"
},
  "geometry": {"coordinates":[0.0457400009,40.0510292053],"type":"Point"}
}