{
  "type": "Feature",
  "properties": {
    "iso:country":"ES",
    "sg:address":"Carrer de Circumval.lacio, 12",
    "sg:city":"Barbera Valles",
    "sg:orig_category":"Art\u00cdculos Funerarios (al Por Menor)",
    "sg:phone":"+34 937 19 27 78",
    "sg:postcode":"08210",
    "sg:province":"Barcelona",
    "sg:website":"www.truyols.com",
    "wof:name":"Funeraria Montserrat-truyols S. A.",
    "wof:placetype":"venue"
},
  "geometry": {"coordinates":[2.131221056,41.5233688354],"type":"Point"}
}