{
  "type": "Feature",
  "properties": {
    "addr:full":"Avda Odon, 26 Villaviciosa Odon Madrid 28670",
    "addr:housenumber":"26",
    "addr:postcode":"28670",
    "addr:street":"Avda Odon;Odon",
    "iso:country":"ES",
    "sg:address":"Avda Odon, 26",
    "sg:city":"Villaviciosa Odon",
    "sg:orig_category":"Bisuter\u00cda, Joyer\u00cda, Relojer\u00cda (al Por Menor)",
    "sg:phone":"+34 916 16 40 94",
    "sg:postcode":"28670",
    "sg:province":"Madrid",
    "wof:name":"Serrano Lopez Alberto",
    "wof:placetype":"venue"
},
  "geometry": {"coordinates":[-3.906899929,40.3552055359],"type":"Point"}
}