{
  "type": "Feature",
  "properties": {
    "iso:country":"ES",
    "sg:address":"Calle de Salinas, 15",
    "sg:city":"Valencia",
    "sg:orig_category":"Arquitectos",
    "sg:phone":"+34 963 15 39 33",
    "sg:postcode":"46003",
    "sg:province":"Valencia",
    "wof:name":"Q. Arquitectes, S.c.p.",
    "wof:placetype":"venue"
},
  "geometry": {"coordinates":[-0.3791860044,39.477230072],"type":"Point"}
}