{
  "type": "Feature",
  "properties": {
    "addr:full":"Calle de Puldon-natero, 4 Cruz Santa Santa Cruz De Tenerife 38413",
    "addr:housenumber":"4",
    "addr:postcode":"38413",
    "addr:street":"Calle De Puldon-Natero;Santa",
    "iso:country":"ES",
    "sg:address":"Calle de Puldon-natero, 4",
    "sg:city":"Cruz Santa",
    "sg:orig_category":"Agentes, Concesionarios Y Sucursales De Veh\u00cdculos",
    "sg:phone":"+34 922 35 32 88",
    "sg:postcode":"38413",
    "sg:province":"Santa Cruz De Tenerife",
    "wof:name":"Morales Rodriguez Agustin",
    "wof:placetype":"venue"
},
  "geometry": {"coordinates":[-16.5606460571,28.3570613861],"type":"Point"}
}