{
  "type": "Feature",
  "properties": {
    "addr:full":"Carretera De Campillo Del Rio, S/n Torreblascopedro Ja\u00e9n 23510",
    "addr:housenumber":"/ n",
    "addr:postcode":"23510",
    "addr:street":"Carretera De Campillo Del Rio S",
    "iso:country":"ES",
    "sg:address":"Carretera De Campillo Del Rio, S/n",
    "sg:city":"Torreblascopedro",
    "sg:orig_category":"Distribuci\u00d3n De Petr\u00d3leo Y Derivados",
    "sg:phone":"+34 953 62 62 98",
    "sg:postcode":"23510",
    "sg:province":"Ja\u00e9n",
    "wof:name":"Ruiz Lorite Manuel Angel",
    "wof:placetype":"venue"
},
  "geometry": {"coordinates":[-3.6396920681,37.9961662292],"type":"Point"}
}