{
  "type": "Feature",
  "properties": {
    "addr:full":"Calle de Aljofaina, 5 Malaga M\u00e1laga 29018",
    "addr:housenumber":"5",
    "addr:postcode":"29018",
    "addr:street":"Calle De Aljofaina;Ma\u0301Laga",
    "iso:country":"ES",
    "sg:address":"Calle de Aljofaina, 5",
    "sg:city":"Malaga",
    "sg:orig_category":"Arreglo, Reparaci\u00d3n, Piezas Sueltas De Televisi\u00d3n, V\u00cddeo, Hi",
    "sg:phone":"+34 952 29 59 89",
    "sg:postcode":"29018",
    "sg:province":"M\u00e1laga",
    "wof:name":"Corral Fernandez Antonio",
    "wof:placetype":"venue"
},
  "geometry": {"coordinates":[-4.3579916954,36.7214927673],"type":"Point"}
}