{
  "type": "Feature",
  "properties": {
    "iso:country":"ES",
    "sg:address":"Avda Manuel Llaneza, 51",
    "sg:city":"Gijon",
    "sg:orig_category":"Inmobiliaria (agencias)",
    "sg:phone":"+34 985 38 94 40",
    "sg:postcode":"33208",
    "sg:province":"Asturias",
    "wof:name":"Inmobiliaria Sulcamifer S. A.",
    "wof:placetype":"venue"
},
  "geometry": {"coordinates":[-5.6650280952,43.5349578857],"type":"Point"}
}