{
  "type": "Feature",
  "properties": {
    "iso:country":"ES",
    "sg:address":"Rua Mantelas, 45",
    "sg:city":"Rioboo",
    "sg:orig_category":"Fabricaci\u00d3n De Su\u00c9ters Y Chalecos De Punto",
    "sg:phone":"+34 986 41 06 93",
    "sg:postcode":"36204",
    "sg:province":"Pontevedra",
    "wof:name":"Creaciones Joyfa S. L.",
    "wof:placetype":"venue"
},
  "geometry": {"coordinates":[-8.6428003311,42.4304618835],"type":"Point"}
}