{
  "type": "Feature",
  "properties": {
    "addr:full":"Carr Assumpcio, 9 Lleida Lleida 25005",
    "addr:housenumber":"9",
    "addr:postcode":"25005",
    "addr:street":"Carr Assumpcio",
    "iso:country":"ES",
    "sg:address":"Carr Assumpcio, 9",
    "sg:city":"Lleida",
    "sg:orig_category":"Reparaci\u00d3n, Mantenimiento De Calefacciones",
    "sg:phone":"+34 973 24 21 92",
    "sg:postcode":"25005",
    "sg:province":"Lleida",
    "wof:name":"Castillo Garcia Rafael",
    "wof:placetype":"venue"
},
  "geometry": {"coordinates":[0.6303539872,41.6349182129],"type":"Point"}
}