{
  "type": "Feature",
  "properties": {
    "iso:country":"ES",
    "sg:address":"Calle de Bengoetxea, 4",
    "sg:city":"Donostia-san Sebastian",
    "sg:orig_category":"Centros De Salud",
    "sg:phone":"+34 943 44 06 33",
    "sg:postcode":"20004",
    "sg:province":"Guip\u00f9zcoa",
    "wof:name":"Ayuntamiento De Donostia-san Sebastian-casa De Socorro",
    "wof:placetype":"venue"
},
  "geometry": {"coordinates":[-1.9817830324,43.3219261169],"type":"Point"}
}