{
  "type": "Feature",
  "properties": {
    "addr:full":"Ctra Madrid Km 233, Km. 0234,0 Villagonzalo-pedernales Burgos 09195",
    "addr:housenumber":"km",
    "addr:postcode":"09195",
    "addr:street":"Ctra Madrid;233 Km. 0234,0 Villagonzalo-Pedernales",
    "iso:country":"ES",
    "sg:address":"Ctra Madrid Km 233, Km. 0234,0",
    "sg:city":"Villagonzalo-pedernales",
    "sg:orig_category":"Aparatos E Instalaci\u00d3n De Regad\u00cdos",
    "sg:phone":"+34 947 20 41 47",
    "sg:postcode":"09195",
    "sg:province":"Burgos",
    "wof:name":"Melo Acha Victorino",
    "wof:placetype":"venue"
},
  "geometry": {"coordinates":[-3.7549920082,42.2654838562],"type":"Point"}
}