{
  "type": "Feature",
  "properties": {
    "addr:full":"Carr Fluvia, 33 Badalona Barcelona 08911",
    "addr:housenumber":"33",
    "addr:postcode":"08911",
    "addr:street":"Carr Fluvia",
    "iso:country":"ES",
    "sg:address":"Carr Fluvia, 33",
    "sg:city":"Badalona",
    "sg:orig_category":"Empresarios",
    "sg:phone":"+34 933 84 38 52",
    "sg:postcode":"08911",
    "sg:province":"Barcelona",
    "wof:name":"Fluvia Fonolla Salvador",
    "wof:placetype":"venue"
},
  "geometry": {"coordinates":[2.2470550537,41.4536437988],"type":"Point"}
}