{
  "type": "Feature",
  "properties": {
    "addr:full":"Calle de Pinto, 33 Parla Madrid 28980",
    "addr:housenumber":"33",
    "addr:postcode":"28980",
    "addr:street":"Calle De Pinto",
    "iso:country":"ES",
    "sg:address":"Calle de Pinto, 33",
    "sg:city":"Parla",
    "sg:orig_category":"\u00d3ptica: Instrumentos (fabricaci\u00d3n)",
    "sg:phone":"+34 916 99 39 54",
    "sg:postcode":"28980",
    "sg:province":"Madrid",
    "wof:name":"Martinez Oca\u00f1a Antonio",
    "wof:placetype":"venue"
},
  "geometry": {"coordinates":[-3.7675490379,40.2392692566],"type":"Point"}
}