{
  "type": "Feature",
  "properties": {
    "iso:country":"ES",
    "sg:address":"Carrer de Josep M. De Segarra, 35",
    "sg:city":"Santa Perpetua De Mogoda",
    "sg:orig_category":"Inmobiliaria (agencias)",
    "sg:phone":"+34 935 60 64 36",
    "sg:postcode":"08130",
    "sg:province":"Barcelona",
    "wof:name":"Blanes Sanchez Montserrat",
    "wof:placetype":"venue"
},
  "geometry": {"coordinates":[2.178278923,41.5338516235],"type":"Point"}
}