{
  "type": "Feature",
  "properties": {
    "addr:full":"Avda Yeseros (de Los), 32 Valmor-rompecubas Madrid 28340",
    "addr:housenumber":"32",
    "addr:postcode":"28340",
    "addr:street":"Avda Yeseros De Los",
    "iso:country":"ES",
    "sg:address":"Avda Yeseros (de Los), 32",
    "sg:city":"Valmor-rompecubas",
    "sg:orig_category":"Postigos, Persianas Y Celos\u00cdas",
    "sg:phone":"+34 918 95 64 67",
    "sg:postcode":"28340",
    "sg:province":"Madrid",
    "wof:name":"Manjavacas Escribano Carlos",
    "wof:placetype":"venue"
},
  "geometry": {"coordinates":[-3.6677899361,40.1646308899],"type":"Point"}
}