{
  "type": "Feature",
  "properties": {
    "iso:country":"ES",
    "sg:address":"Pase Carmelitas, 32",
    "sg:city":"Salamanca",
    "sg:orig_category":"Institutos De Belleza",
    "sg:phone":"+34 923 26 11 97",
    "sg:postcode":"37007",
    "sg:province":"Salamanca",
    "wof:name":"Sierra Fernandez Maria Del Carmen",
    "wof:placetype":"venue"
},
  "geometry": {"coordinates":[-5.665802002,40.9694709778],"type":"Point"}
}