{
  "type": "Feature",
  "properties": {
    "addr:full":"Carr Ponent, 13 Mollerussa Lleida 25230",
    "addr:housenumber":"13",
    "addr:postcode":"25230",
    "addr:street":"Carr Ponent",
    "iso:country":"ES",
    "sg:address":"Carr Ponent, 13",
    "sg:city":"Mollerussa",
    "sg:orig_category":"Lavado, Limpieza De Veh\u00cdculos",
    "sg:phone":"+34 973 60 02 34",
    "sg:postcode":"25230",
    "sg:province":"Lleida",
    "wof:name":"Llovera Roma Ferran",
    "wof:placetype":"venue"
},
  "geometry": {"coordinates":[0.8936949968,41.6300392151],"type":"Point"}
}