{
  "type": "Feature",
  "properties": {
    "iso:country":"ES",
    "sg:address":"Legalidad Tercero, S/n",
    "sg:city":"Legalidad Tercero",
    "sg:orig_category":"Cerrajer\u00cda, Ferrallista",
    "sg:phone":"+34 985 48 26 08",
    "sg:postcode":"33684",
    "sg:province":"Asturias",
    "wof:name":"Cerrajeria Allerastur S.l.l.",
    "wof:placetype":"venue"
},
  "geometry": {"coordinates":[-5.7493901253,43.1839447021],"type":"Point"}
}