{
  "type": "Feature",
  "properties": {
    "iso:country":"ES",
    "sg:address":"Rua Marques De Valladares, 21",
    "sg:city":"Vigo",
    "sg:orig_category":"Peluqueros: De Se\u00d1oras",
    "sg:phone":"+34 986 43 35 11",
    "sg:postcode":"36201",
    "sg:province":"Pontevedra",
    "wof:name":"Tojo Nogareda Maria Dolores",
    "wof:placetype":"venue"
},
  "geometry": {"coordinates":[-8.7227735519,42.2383918762],"type":"Point"}
}