{
  "type": "Feature",
  "properties": {
    "iso:country":"ES",
    "sg:address":"Carrer de Arago, 21",
    "sg:city":"Palma",
    "sg:orig_category":"M\u00c9dicos: Estomatolog\u00cda",
    "sg:phone":"+34 971 77 20 25",
    "sg:postcode":"07005",
    "sg:province":"Islas Baleares",
    "wof:name":"Ceos S.l.",
    "wof:placetype":"venue"
},
  "geometry": {"coordinates":[2.6581308842,39.5744247437],"type":"Point"}
}