{
  "type": "Feature",
  "properties": {
    "addr:full":"Carrer de Colom, 5 Montcada Centre Barcelona 08110",
    "addr:housenumber":"5",
    "addr:postcode":"08110",
    "addr:street":"Carrer De Colom",
    "iso:country":"ES",
    "sg:address":"Carrer de Colom, 5",
    "sg:city":"Montcada Centre",
    "sg:orig_category":"Molduras, Junquillos, Listones Y Molduras Perforadas",
    "sg:phone":"+34 935 64 69 50",
    "sg:postcode":"08110",
    "sg:province":"Barcelona",
    "wof:name":"Hernandez Perez Jordi",
    "wof:placetype":"venue"
},
  "geometry": {"coordinates":[2.1817800999,41.4892234802],"type":"Point"}
}