{
  "type": "Feature",
  "properties": {
    "iso:country":"ES",
    "sg:address":"Calle de Hernan Cortes, 13",
    "sg:city":"Alhama Murcia",
    "sg:orig_category":"Contenedores (mercanc\u00cdas)",
    "sg:phone":"+34 968 63 06 95",
    "sg:postcode":"30840",
    "sg:province":"Murcia",
    "wof:name":"Sanchez Ramirez Atanasio",
    "wof:placetype":"venue"
},
  "geometry": {"coordinates":[-1.4223099947,37.8494377136],"type":"Point"}
}