{
  "type": "Feature",
  "properties": {
    "addr:full":"Avda Papa Luna, 32 Pe\u00f1iscola Castell\u00f3n 12598",
    "addr:housenumber":"32",
    "addr:postcode":"12598",
    "addr:street":"Avda Papa Luna;Castello\u0301N",
    "iso:country":"ES",
    "sg:address":"Avda Papa Luna, 32",
    "sg:city":"Pe\u00f1iscola",
    "sg:orig_category":"Hoteles",
    "sg:phone":"+34 964 48 06 44",
    "sg:postcode":"12598",
    "sg:province":"Castell\u00f3n",
    "wof:name":"Pe\u00f1iscola Felipe Ii S.l.",
    "wof:placetype":"venue"
},
  "geometry": {"coordinates":[0.4051719904,40.3725013733],"type":"Point"}
}