{
  "type": "Feature",
  "properties": {
    "iso:country":"ES",
    "sg:address":"Pol Ind Venta Colores, S/n",
    "sg:city":"Mancha Real",
    "sg:orig_category":"Contenedores (mercanc\u00cdas)",
    "sg:phone":"+34 953 35 23 65",
    "sg:postcode":"23100",
    "sg:province":"Ja\u00e9n",
    "wof:name":"Ruiz Sanchez Francisco",
    "wof:placetype":"venue"
},
  "geometry": {"coordinates":[-3.6184639931,37.8074951172],"type":"Point"}
}