{
  "type": "Feature",
  "properties": {
    "addr:full":"Carretera De Tirgo, 4 Miranda Ebro Burgos 09200",
    "addr:housenumber":"4",
    "addr:postcode":"09200",
    "addr:street":"Carretera De Tirgo",
    "iso:country":"ES",
    "sg:address":"Carretera De Tirgo, 4",
    "sg:city":"Miranda Ebro",
    "sg:orig_category":"Charcuter\u00cdas (al Por Mayor)",
    "sg:phone":"+34 947 31 08 24",
    "sg:postcode":"09200",
    "sg:province":"Burgos",
    "wof:name":"Embutidos Oscar S L",
    "wof:placetype":"venue"
},
  "geometry": {"coordinates":[-2.9524741173,42.6833839417],"type":"Point"}
}