{
  "type": "Feature",
  "properties": {
    "addr:full":"Calle de Puente Nuevo, 16 Talavera Reina Toledo 45600",
    "addr:housenumber":"16",
    "addr:postcode":"45600",
    "addr:street":"Calle De Puente Nuevo",
    "iso:country":"ES",
    "sg:address":"Calle de Puente Nuevo, 16",
    "sg:city":"Talavera Reina",
    "sg:orig_category":"Panader\u00cdas, Panader\u00cdas",
    "sg:phone":"+34 925 80 49 69",
    "sg:postcode":"45600",
    "sg:province":"Toledo",
    "wof:name":"Pasteleria Requena S.l.",
    "wof:placetype":"venue"
},
  "geometry": {"coordinates":[-4.8338108063,39.9628295898],"type":"Point"}
}