{
  "type": "Feature",
  "properties": {
    "addr:full":"Calle de Santander, 10 Alcala Guadaira Sevilla 41500",
    "addr:housenumber":"10",
    "addr:postcode":"41500",
    "addr:street":"Calle De Santander",
    "iso:country":"ES",
    "sg:address":"Calle de Santander, 10",
    "sg:city":"Alcala Guadaira",
    "sg:orig_category":"M\u00c9dicos: An\u00c1lisis Cl\u00cdnicos",
    "sg:phone":"+34 955 68 65 68",
    "sg:postcode":"41500",
    "sg:province":"Sevilla",
    "wof:name":"Madro\u00f1al Sanchez Rosario",
    "wof:placetype":"venue"
},
  "geometry": {"coordinates":[-5.8360991478,37.3365516663],"type":"Point"}
}