{
  "type": "Feature",
  "properties": {
    "addr:full":"Carrer de Mare De Deu Del Pilar, 105 Mutxamel Alicante 03110",
    "addr:housenumber":"105",
    "addr:postcode":"03110",
    "addr:street":"Carrer De Mare De Deu Del Pilar",
    "iso:country":"ES",
    "sg:address":"Carrer de Mare De Deu Del Pilar, 105",
    "sg:city":"Mutxamel",
    "sg:orig_category":"Asesor\u00cda Fiscal Y Jur\u00cddica",
    "sg:phone":"+34 965 95 22 58",
    "sg:postcode":"03110",
    "sg:province":"Alicante",
    "wof:name":"Asesoria Fiscal Izquierdo & Asociados S.c.",
    "wof:placetype":"venue"
},
  "geometry": {"coordinates":[-0.4426522851,38.4129219055],"type":"Point"}
}