{
  "type": "Feature",
  "properties": {
    "addr:full":"Carr Minyones, 20 Colonia S. Pere Islas Baleares 07579",
    "addr:housenumber":"20",
    "addr:postcode":"07579",
    "addr:street":"Carr Minyones;Colonia S. Pere Islas",
    "iso:country":"ES",
    "sg:address":"Carr Minyones, 20",
    "sg:city":"Colonia S. Pere",
    "sg:orig_category":"Obras Y Organismos Sociales",
    "sg:phone":"+34 971 58 91 04",
    "sg:postcode":"07579",
    "sg:province":"Islas Baleares",
    "wof:name":"Mi\u00f1onas Fundacion",
    "wof:placetype":"venue"
},
  "geometry": {"coordinates":[3.3175799847,39.7534561157],"type":"Point"}
}