{
  "type": "Feature",
  "properties": {
    "iso:country":"ES",
    "sg:address":"Avda Ventisquero De La Condesa, 13",
    "sg:city":"Madrid",
    "sg:orig_category":"Centros De Coordinaci\u00d3n",
    "sg:phone":"+34 917 30 60 40",
    "sg:postcode":"28035",
    "sg:province":"Madrid",
    "wof:name":"Bordeje Peral S.l.",
    "wof:placetype":"venue"
},
  "geometry": {"coordinates":[-3.7166380882,40.4879074097],"type":"Point"}
}