{
  "type": "Feature",
  "properties": {
    "iso:country":"ES",
    "sg:address":"Arantzazuko Amaren Auzoa, 5",
    "sg:city":"Legazpi",
    "sg:orig_category":"Empresas De Limpieza",
    "sg:phone":"+34 943 73 16 31",
    "sg:postcode":"20230",
    "sg:province":"Guip\u00f9zcoa",
    "wof:name":"Gil Rubio Javier",
    "wof:placetype":"venue"
},
  "geometry": {"coordinates":[-2.3346400261,43.0559120178],"type":"Point"}
}