{
  "type": "Feature",
  "properties": {
    "addr:full":"Av Catalunya, 13 S. Adria Besos Barcelona 08930",
    "addr:housenumber":"13",
    "addr:postcode":"08930",
    "addr:street":"Av Catalunya;S. Adria Besos Barcelona",
    "iso:country":"ES",
    "sg:address":"Av Catalunya, 13",
    "sg:city":"S. Adria Besos",
    "sg:orig_category":"Marroquiner\u00cda (confecci\u00d3n)",
    "sg:phone":"+34 933 81 44 01",
    "sg:postcode":"08930",
    "sg:province":"Barcelona",
    "wof:name":"Gallifa Baldrich Xenia",
    "wof:placetype":"venue"
},
  "geometry": {"coordinates":[2.2163639069,41.4322280884],"type":"Point"}
}