{
  "type": "Feature",
  "properties": {
    "iso:country":"ES",
    "sg:address":"Calle de Publicista Jose Alegria, 21",
    "sg:city":"Nuestra Se\u00e7ora De La Fuensanta",
    "sg:orig_category":"Promotores Constructores",
    "sg:phone":"+34 968 34 00 48",
    "sg:postcode":"30011",
    "sg:province":"Murcia",
    "wof:name":"Vilaria Interiorismo Y Edificacion S.l.",
    "wof:placetype":"venue"
},
  "geometry": {"coordinates":[-1.1238540411,37.9761581421],"type":"Point"}
}