{
  "type": "Feature",
  "properties": {
    "addr:full":"Avda Generalisimo, 68 Barbate C\u00e1diz 11160",
    "addr:housenumber":"68",
    "addr:postcode":"11160",
    "addr:street":"Avda Generalisimo",
    "iso:country":"ES",
    "sg:address":"Avda Generalisimo, 68",
    "sg:city":"Barbate",
    "sg:orig_category":"Asesor\u00cda De Formaci\u00d3n Y Gesti\u00d3n De Personal",
    "sg:phone":"+34 956 43 17 88",
    "sg:postcode":"11160",
    "sg:province":"C\u00e1diz",
    "wof:name":"Gago Pi\u00f1ero Mariano",
    "wof:placetype":"venue"
},
  "geometry": {"coordinates":[-5.9209618568,36.1907424927],"type":"Point"}
}