{
  "type": "Feature",
  "properties": {
    "addr:full":"Dema Entrevies, S/n Pinedes Tarragona 43006",
    "addr:housenumber":"s",
    "addr:postcode":"43006",
    "addr:street":"/ N Pinedes",
    "iso:country":"ES",
    "sg:address":"Dema Entrevies, S/n",
    "sg:city":"Pinedes",
    "sg:orig_category":"Fabricaci\u00d3n, Reparaci\u00d3n Y Mantenimiento De Construcciones Navales Y Fluviales",
    "sg:phone":"+34 977 55 16 57",
    "sg:postcode":"43006",
    "sg:province":"Tarragona",
    "wof:name":"Dino Theo Atlantis Mc S.l.",
    "wof:placetype":"venue"
},
  "geometry": {"coordinates":[1.2209249735,41.1154441833],"type":"Point"}
}