{
  "type": "Feature",
  "properties": {
    "addr:full":"Calle de Atxeta, 4 \u00c1lava 01400",
    "addr:housenumber":"4",
    "addr:postcode":"01400",
    "addr:street":"Calle De Atxeta;A\u0301Lava",
    "iso:country":"ES",
    "sg:address":"Calle de Atxeta, 4",
    "sg:orig_category":"Peluquer\u00cdas, Peluquer\u00cda Mixta",
    "sg:phone":"+34 944 66 74 73",
    "sg:postcode":"01400",
    "sg:province":"\u00c1lava",
    "wof:name":"M\u00aa Milagros Fernandez Hernan",
    "wof:placetype":"venue"
},
  "geometry": {"coordinates":[-2.9431190491,43.147026062],"type":"Point"}
}