{
  "type": "Feature",
  "properties": {
    "iso:country":"ES",
    "sg:address":"Avda Se\u00d1ores Baselga, S/n",
    "sg:city":"Utrillas",
    "sg:orig_category":"Ense\u00d1anza Variada",
    "sg:phone":"+34 978 75 80 62",
    "sg:postcode":"44760",
    "sg:province":"Teruel",
    "wof:name":"Direccion Provincial De Educacion Y Ciencia. Centro De Profesores",
    "wof:placetype":"venue"
},
  "geometry": {"coordinates":[-0.8498690128,40.8125686646],"type":"Point"}
}