{
  "type": "Feature",
  "properties": {
    "iso:country":"ES",
    "sg:address":"Calle de Enrique Jardiel Poncela, 12",
    "sg:city":"Malaga",
    "sg:orig_category":"Negocio De Materiales De Construcci\u00d3n",
    "sg:phone":"+34 952 27 04 47",
    "sg:postcode":"29010",
    "sg:province":"M\u00e1laga",
    "wof:name":"Arrabal Lopez Juan",
    "wof:placetype":"venue"
},
  "geometry": {"coordinates":[-4.450817585,36.7288246155],"type":"Point"}
}