{
  "type": "Feature",
  "properties": {
    "addr:full":"Calle de Compa\u00d1ia, 6 Ecija Sevilla 41400",
    "addr:housenumber":"6",
    "addr:postcode":"41400",
    "addr:street":"Calle De Compan\u0303Ia",
    "iso:country":"ES",
    "sg:address":"Calle de Compa\u00d1ia, 6",
    "sg:city":"Ecija",
    "sg:orig_category":"Frutas, Legumbres Frescas Y Tempranas (al Por Menor)",
    "sg:phone":"+34 954 83 33 06",
    "sg:postcode":"41400",
    "sg:province":"Sevilla",
    "wof:name":"Pradas Tutor Marcelino",
    "wof:placetype":"venue"
},
  "geometry": {"coordinates":[-5.0806627274,37.5414466858],"type":"Point"}
}