{
  "type": "Feature",
  "properties": {
    "iso:country":"ES",
    "sg:address":"Carr Canigo, 1",
    "sg:city":"Blanes",
    "sg:orig_category":"Peluquer\u00cdas, Peluquer\u00cda Mixta",
    "sg:phone":"+34 972 33 54 91",
    "sg:postcode":"17300",
    "sg:province":"Girona",
    "wof:name":"Trujillano Cabezas Sonia",
    "wof:placetype":"venue"
},
  "geometry": {"coordinates":[2.7822430134,41.6757926941],"type":"Point"}
}