{
  "type": "Feature",
  "properties": {
    "addr:full":"Carrer de Roses, 32 Sant Feliu Llobregat Barcelona 08980",
    "addr:housenumber":"32",
    "addr:postcode":"08980",
    "addr:street":"Carrer De Roses",
    "iso:country":"ES",
    "sg:address":"Carrer de Roses, 32",
    "sg:city":"Sant Feliu Llobregat",
    "sg:orig_category":"M\u00c9dicos: Oftalmolog\u00cda",
    "sg:phone":"+34 936 85 32 22",
    "sg:postcode":"08980",
    "sg:province":"Barcelona",
    "wof:name":"Alonso Garzon Isabel",
    "wof:placetype":"venue"
},
  "geometry": {"coordinates":[2.0497283936,41.3846168518],"type":"Point"}
}