{
  "type": "Feature",
  "properties": {
    "addr:full":"Vazquez De Coronado, 1 Arroyo De La Encomienda Valladolid 47195",
    "addr:housenumber":"1",
    "addr:postcode":"47195",
    "iso:country":"ES",
    "sg:address":"Vazquez De Coronado, 1",
    "sg:city":"Arroyo De La Encomienda",
    "sg:orig_category":"Ense\u00d1ante, Direcci\u00d3n",
    "sg:phone":"+34 983 40 76 79",
    "sg:postcode":"47195",
    "sg:province":"Valladolid",
    "wof:name":"Alvarez Moratinos Tomas",
    "wof:placetype":"venue"
},
  "geometry": {"coordinates":[-4.7785801888,41.616973877],"type":"Point"}
}