{
  "type": "Feature",
  "properties": {
    "addr:full":"Calle de Solares, 26 Baza Granada 18800",
    "addr:housenumber":"26",
    "addr:postcode":"18800",
    "addr:street":"Calle De Solares",
    "iso:country":"ES",
    "sg:address":"Calle de Solares, 26",
    "sg:city":"Baza",
    "sg:orig_category":"Productos Qu\u00cdmicos (fabricaci\u00d3n, Al Por Mayor)",
    "sg:phone":"+34 958 70 27 60",
    "sg:postcode":"18800",
    "sg:province":"Granada",
    "wof:name":"Quimica Baza S.l.l.",
    "wof:placetype":"venue"
},
  "geometry": {"coordinates":[-2.7692699432,37.492225647],"type":"Point"}
}