{
  "type": "Feature",
  "properties": {
    "iso:country":"ES",
    "sg:address":"Avda America (de), 63",
    "sg:city":"Granada",
    "sg:orig_category":"Alimentaci\u00d3n General (al Por Menor)",
    "sg:phone":"+34 958 13 70 91",
    "sg:postcode":"18008",
    "sg:province":"Granada",
    "wof:name":"Sevillana De Supermercados S. A.",
    "wof:placetype":"venue"
},
  "geometry": {"coordinates":[-3.5936999321,37.1602592468],"type":"Point"}
}