{
  "type": "Feature",
  "properties": {
    "addr:full":"Avda Andalucia, 29 Atarfe Granada 18230",
    "addr:housenumber":"29",
    "addr:postcode":"18230",
    "addr:street":"Avda Andalucia",
    "iso:country":"ES",
    "sg:address":"Avda Andalucia, 29",
    "sg:city":"Atarfe",
    "sg:orig_category":"M\u00c9dicos: Estomatolog\u00cda",
    "sg:phone":"+34 958 43 65 08",
    "sg:postcode":"18230",
    "sg:province":"Granada",
    "wof:name":"Ruiz Navarro Francisco",
    "wof:placetype":"venue"
},
  "geometry": {"coordinates":[-3.6870210171,37.2229919434],"type":"Point"}
}