{
  "type": "Feature",
  "properties": {
    "iso:country":"ES",
    "sg:address":"Carrer de Tamarit, 101",
    "sg:city":"Barcelona",
    "sg:orig_category":"Reposter\u00cdas",
    "sg:phone":"+34 934 23 32 23",
    "sg:postcode":"08015",
    "sg:province":"Barcelona",
    "wof:name":"Barrero Morell Saturnina",
    "wof:placetype":"venue"
},
  "geometry": {"coordinates":[2.1570079327,41.3758544922],"type":"Point"}
}