{
  "type": "Feature",
  "properties": {
    "addr:full":"G.v. Escultor Francisco Salzillo, 4 Santa Catalina Murcia 30004",
    "addr:housenumber":"4",
    "addr:postcode":"30004",
    "addr:street":"Escultor Francisco Salzillo",
    "iso:country":"ES",
    "sg:address":"G.v. Escultor Francisco Salzillo, 4",
    "sg:city":"Santa Catalina",
    "sg:orig_category":"Abogados",
    "sg:phone":"+34 968 21 16 01",
    "sg:postcode":"30004",
    "sg:province":"Murcia",
    "wof:name":"Murcia Mazon Mercedes",
    "wof:placetype":"venue"
},
  "geometry": {"coordinates":[-1.1318620443,37.9841690063],"type":"Point"}
}