{
  "type": "Feature",
  "properties": {
    "addr:full":"Calle de Xativa, 6 Valencia Valencia 46002",
    "addr:housenumber":"6",
    "addr:postcode":"46002",
    "addr:street":"Calle De Xativa",
    "iso:country":"ES",
    "sg:address":"Calle de Xativa, 6",
    "sg:city":"Valencia",
    "sg:orig_category":"Contables",
    "sg:phone":"+34 963 94 06 54",
    "sg:postcode":"46002",
    "sg:province":"Valencia",
    "wof:name":"Sanchez Peris Valentin",
    "wof:placetype":"venue"
},
  "geometry": {"coordinates":[-0.3790979981,39.4679145813],"type":"Point"}
}