{
  "type": "Feature",
  "properties": {
    "iso:country":"ES",
    "sg:address":"Pl Abastos, S/n",
    "sg:city":"Elche",
    "sg:orig_category":"Frutas, Legumbres Frescas Y Tempranas (al Por Menor)",
    "sg:phone":"+34 965 45 18 73",
    "sg:postcode":"03202",
    "sg:province":"Alicante",
    "wof:name":"Almarcha Martinez Antonio",
    "wof:placetype":"venue"
},
  "geometry": {"coordinates":[-0.6488505006,38.3253250122],"type":"Point"}
}