{
  "type": "Feature",
  "properties": {
    "iso:country":"ES",
    "sg:address":"Polig. Lalin Dos Mil, S/n",
    "sg:city":"Donsion",
    "sg:orig_category":"Material Y Herramientas Agr\u00cdcolas",
    "sg:phone":"+34 986 78 75 44",
    "sg:postcode":"36519",
    "sg:province":"Pontevedra",
    "wof:name":"Tecnor Lalin Maquinaria S.l.",
    "wof:placetype":"venue"
},
  "geometry": {"coordinates":[-8.1627492905,42.5798492432],"type":"Point"}
}