{
  "type": "Feature",
  "properties": {
    "addr:full":"San Juan Bidea, S/n Zestoa Guip\u00f9zcoa 20740",
    "addr:housenumber":"s / n",
    "addr:postcode":"20740",
    "addr:street":"San Juan Bidea;Guipu\u0300Zcoa",
    "iso:country":"ES",
    "sg:address":"San Juan Bidea, S/n",
    "sg:city":"Zestoa",
    "sg:orig_category":"Asilos De Ancianos. Centros Privados",
    "sg:phone":"+34 943 14 70 19",
    "sg:postcode":"20740",
    "sg:province":"Guip\u00f9zcoa",
    "wof:name":"Residencia De Ancianos San Juan Zaharren Egoitza",
    "wof:placetype":"venue"
},
  "geometry": {"coordinates":[-2.2549140453,43.2378883362],"type":"Point"}
}