{
  "type": "Feature",
  "properties": {
    "iso:country":"ES",
    "sg:address":"Calle de Cartagena, S/n",
    "sg:city":"Alcazares",
    "sg:orig_category":"Heladeros",
    "sg:phone":"+34 968 57 57 86",
    "sg:postcode":"30710",
    "sg:province":"Murcia",
    "wof:name":"Mora Ramirez Jose Alfredo",
    "wof:placetype":"venue"
},
  "geometry": {"coordinates":[-0.8494818807,37.7385253906],"type":"Point"}
}