{
  "type": "Feature",
  "properties": {
    "addr:full":"Carrer de Montseny, 29 Hospitalet Llobregat Barcelona 08903",
    "addr:housenumber":"29",
    "addr:postcode":"08903",
    "addr:street":"Carrer De Montseny",
    "iso:country":"ES",
    "sg:address":"Carrer de Montseny, 29",
    "sg:city":"Hospitalet Llobregat",
    "sg:orig_category":"Empresas De Carpinter\u00cda Met\u00c1lica",
    "sg:phone":"+34 934 49 99 03",
    "sg:postcode":"08903",
    "sg:province":"Barcelona",
    "wof:name":"Juan Carbonell Giralt Y Jose M.miro Berenguer C.b.",
    "wof:placetype":"venue"
},
  "geometry": {"coordinates":[2.1236999035,41.3723716736],"type":"Point"}
}