{
  "type": "Feature",
  "properties": {
    "addr:full":"San Vicente, 1 Arneva Alicante 03312",
    "addr:housenumber":"1",
    "addr:postcode":"03312",
    "addr:street":"San Vicente;Alicante",
    "iso:country":"ES",
    "sg:address":"San Vicente, 1",
    "sg:city":"Arneva",
    "sg:orig_category":"Empresarios",
    "sg:phone":"+34 965 30 48 62",
    "sg:postcode":"03312",
    "sg:province":"Alicante",
    "wof:name":"Promociones Y Construcciones Aviles Vicente S.l.",
    "wof:placetype":"venue"
},
  "geometry": {"coordinates":[-0.9411919713,38.056388855],"type":"Point"}
}