{
  "type": "Feature",
  "properties": {
    "addr:full":"Concejo De Azpa, 3 Iru\u00f1a Navarra 31016",
    "addr:housenumber":"3",
    "addr:postcode":"31016",
    "addr:street":"Irun\u0303A Navarra",
    "iso:country":"ES",
    "sg:address":"Concejo De Azpa, 3",
    "sg:city":"Iru\u00f1a",
    "sg:orig_category":"M\u00c9dicos: Estomatolog\u00cda",
    "sg:phone":"+34 948 16 26 31",
    "sg:postcode":"31016",
    "sg:province":"Navarra",
    "wof:name":"Sanchaez Haba Maria Del Mar",
    "wof:placetype":"venue"
},
  "geometry": {"coordinates":[-1.6138650179,42.8121414185],"type":"Point"}
}