{
  "type": "Feature",
  "properties": {
    "addr:full":"Calle de Lucerna, 17 Ponferrada Le\u00f3n 24400",
    "addr:housenumber":"17",
    "addr:postcode":"24400",
    "addr:street":"Calle De Lucerna",
    "iso:country":"ES",
    "sg:address":"Calle de Lucerna, 17",
    "sg:city":"Ponferrada",
    "sg:orig_category":"Ense\u00d1ante, Direcci\u00d3n",
    "sg:phone":"+34 987 42 67 41",
    "sg:postcode":"24400",
    "sg:province":"Le\u00f3n",
    "wof:name":"Martin Cazorla Eduardo",
    "wof:placetype":"venue"
},
  "geometry": {"coordinates":[-6.5857748985,42.5418052673],"type":"Point"}
}