{
  "type": "Feature",
  "properties": {
    "addr:full":"Calle de Fernandez Ladreda, 15 Oviedo Asturias 33011",
    "addr:housenumber":"15",
    "addr:postcode":"33011",
    "addr:street":"Calle De;Ladreda",
    "iso:country":"ES",
    "sg:address":"Calle de Fernandez Ladreda, 15",
    "sg:city":"Oviedo",
    "sg:orig_category":"Alimentaci\u00d3n General (al Por Menor)",
    "sg:phone":"+34 985 28 32 40",
    "sg:postcode":"33011",
    "sg:province":"Asturias",
    "wof:name":"Blanco Gonzalez Jose Antonio",
    "wof:placetype":"venue"
},
  "geometry": {"coordinates":[-5.8356938362,43.3708229065],"type":"Point"}
}