{
  "type": "Feature",
  "properties": {
    "iso:country":"ES",
    "sg:address":"Calle de Brasil, 25",
    "sg:city":"Tablero",
    "sg:orig_category":"Mec\u00c1nico Del Autom\u00d3vil",
    "sg:phone":"+34 928 14 20 50",
    "sg:postcode":"35100",
    "sg:province":"Las Palmas",
    "wof:name":"Franco Valeron Victor",
    "wof:placetype":"venue"
},
  "geometry": {"coordinates":[-15.6055755615,27.7710952759],"type":"Point"}
}