{
  "type": "Feature",
  "properties": {
    "iso:country":"ES",
    "sg:address":"Calle de Maestro Elorza, S/n",
    "sg:city":"Llodio",
    "sg:orig_category":"Librer\u00cdas",
    "sg:phone":"+34 946 72 20 54",
    "sg:postcode":"01400",
    "sg:province":"\u00c1lava",
    "wof:name":"Larrazabal Lekanda Jon Ander",
    "wof:placetype":"venue"
},
  "geometry": {"coordinates":[-2.9618139267,43.1417884827],"type":"Point"}
}