{
  "type": "Feature",
  "properties": {
    "addr:full":"Calle de Murcia, 62 Almeria Almer\u00eda 04004",
    "addr:housenumber":"62",
    "addr:postcode":"04004",
    "addr:street":"Calle De Murcia",
    "iso:country":"ES",
    "sg:address":"Calle de Murcia, 62",
    "sg:city":"Almeria",
    "sg:orig_category":"Panader\u00cdas, Panader\u00cdas",
    "sg:phone":"+34 950 26 14 56",
    "sg:postcode":"04004",
    "sg:province":"Almer\u00eda",
    "wof:name":"Campos Alburquerque Alfonso",
    "wof:placetype":"venue"
},
  "geometry": {"coordinates":[-2.4592869282,36.8436164856],"type":"Point"}
}