{
  "type": "Feature",
  "properties": {
    "iso:country":"ES",
    "sg:address":"Ctra. Quintana Redonda, S/n",
    "sg:city":"Tardelcuende",
    "sg:orig_category":"Polideportivos",
    "sg:phone":"+34 975 30 80 48",
    "sg:postcode":"42294",
    "sg:province":"Soria",
    "wof:name":"Ayuntamiento De Tardelcuende",
    "wof:placetype":"venue"
},
  "geometry": {"coordinates":[-2.6391170025,41.6064453125],"type":"Point"}
}