{
  "type": "Feature",
  "properties": {
    "iso:country":"ES",
    "sg:address":"G.v. Corts Catalanes, 752",
    "sg:city":"Barcelona",
    "sg:orig_category":"Agentes, Concesionarios Y Sucursales De Veh\u00cdculos",
    "sg:phone":"+34 932 44 42 18",
    "sg:postcode":"08013",
    "sg:province":"Barcelona",
    "sg:website":"www.viacar2000.com",
    "wof:name":"Viacar 2000 S.a.",
    "wof:placetype":"venue"
},
  "geometry": {"coordinates":[2.1798141003,41.3976402283],"type":"Point"}
}