{
  "type": "Feature",
  "properties": {
    "iso:country":"ES",
    "sg:address":"Ctra Alcantarilla(torre Alta), S/n",
    "sg:city":"Molina Segura",
    "sg:orig_category":"Suministros Para Hoteles",
    "sg:phone":"+34 968 64 25 28",
    "sg:postcode":"30509",
    "sg:province":"Murcia",
    "wof:name":"Jesus Gomez Garcia Y Rosa Perez Garcia Cb",
    "wof:placetype":"venue"
},
  "geometry": {"coordinates":[-1.2125511169,38.0345458984],"type":"Point"}
}