{
  "type": "Feature",
  "properties": {
    "addr:full":"Calle de Maiquez, 60 Madrid Madrid 28009",
    "addr:housenumber":"60",
    "addr:postcode":"madrid;28009",
    "addr:street":"Calle De Maiquez",
    "iso:country":"ES",
    "sg:address":"Calle de Maiquez, 60",
    "sg:city":"Madrid",
    "sg:orig_category":"\u00d3ptica: Instrumentos (fabricaci\u00d3n)",
    "sg:phone":"+34 915 74 86 42",
    "sg:postcode":"28009",
    "sg:province":"Madrid",
    "wof:name":"Ortega Belmonte Maria Jose",
    "wof:placetype":"venue"
},
  "geometry": {"coordinates":[-3.6733560562,40.4170150757],"type":"Point"}
}