{
  "type": "Feature",
  "properties": {
    "iso:country":"ES",
    "sg:address":"Pozo Do Barro, 157",
    "sg:city":"Estrada",
    "sg:classifiers":[
        {
            "category":"Taxi",
            "type":"Transportation"
        }
    ],
    "sg:phone":"+34 986 57 06 83",
    "sg:postcode":"36680",
    "sg:province":"Pontevedra",
    "wof:name":"Tato Regueiro Manuel",
    "wof:placetype":"venue"
},
  "geometry": {"coordinates":[-8.4910736084,42.6887664795],"type":"Point"}
}