{
  "type": "Feature",
  "properties": {
    "iso:country":"ES",
    "sg:address":"Avda La Glorieta, 20",
    "sg:city":"Alberic",
    "sg:orig_category":"Asesor\u00cda Sobre Comunicaci\u00d3n De Empresas",
    "sg:phone":"+34 962 44 60 41",
    "sg:postcode":"46260",
    "sg:province":"Valencia",
    "sg:website":"www.ia-adarve.com",
    "wof:name":"Azahar Ribera Alta Inmobiliaria S.l.",
    "wof:placetype":"venue"
},
  "geometry": {"coordinates":[-0.5225120187,39.1173667908],"type":"Point"}
}