{
  "type": "Feature",
  "properties": {
    "iso:country":"ES",
    "sg:address":"Bo. Fingoi, S/n",
    "sg:city":"Lugo",
    "sg:classifiers":[
        {
            "category":"Communications",
            "type":"Services"
        }
    ],
    "sg:phone":"+34 982 28 30 32",
    "sg:postcode":"27002",
    "sg:province":"Lugo",
    "sg:tags":[
        "televisiones",
        "y",
        "radio"
    ],
    "wof:name":"Voz De Galicia Radio S.a.",
    "wof:placetype":"venue"
},
  "geometry": {"coordinates":[-7.5301399231,42.9997177124],"type":"Point"}
}