{
  "type": "Feature",
  "properties": {
    "iso:country":"ES",
    "sg:address":"Calle de Marmoles, 36",
    "sg:city":"Almeria",
    "sg:orig_category":"Goma: Productos De Uso Industrial (fabricaci\u00d3n, Al Por Mayor)",
    "sg:phone":"+34 950 22 26 43",
    "sg:postcode":"04006",
    "sg:province":"Almer\u00eda",
    "wof:name":"Quesada Segura Juan Jose",
    "wof:placetype":"venue"
},
  "geometry": {"coordinates":[-2.4368209839,36.8415145874],"type":"Point"}
}