{
  "type": "Feature",
  "properties": {
    "addr:full":"Calle de Bellido, 26 Jaca Huesca 22700",
    "addr:housenumber":"26",
    "addr:postcode":"22700",
    "addr:street":"Calle De Bellido",
    "iso:country":"ES",
    "sg:address":"Calle de Bellido, 26",
    "sg:city":"Jaca",
    "sg:orig_category":"Sindicatos De Trabajadores",
    "sg:phone":"+34 974 35 58 98",
    "sg:postcode":"22700",
    "sg:province":"Huesca",
    "wof:name":"Union General De Trabajadores",
    "wof:placetype":"venue"
},
  "geometry": {"coordinates":[-0.5482329726,42.5700035095],"type":"Point"}
}