{
  "type": "Feature",
  "properties": {
    "iso:country":"ES",
    "sg:address":"Avda Altillo (el), 29",
    "sg:city":"Jerez De La Frontera",
    "sg:orig_category":"Inform\u00c1tica (estudios, Servicios, Asesor\u00cda, Formaci\u00d3n)",
    "sg:phone":"+34 956 31 60 37",
    "sg:postcode":"11405",
    "sg:province":"C\u00e1diz",
    "sg:website":"www.ebmsoft.com",
    "wof:name":"Berraquero Y Mu\u00d1oz S.l.",
    "wof:placetype":"venue"
},
  "geometry": {"coordinates":[-6.1181540489,36.7007102966],"type":"Point"}
}