{
  "type": "Feature",
  "properties": {
    "addr:full":"Carrer de Sant Antoni Maria Claret, 8 Barcelona Barcelona 08037",
    "addr:housenumber":"8",
    "addr:postcode":"08037",
    "addr:street":"Carrer De Sant Antoni Maria Claret",
    "iso:country":"ES",
    "sg:address":"Carrer de Sant Antoni Maria Claret, 8",
    "sg:city":"Barcelona",
    "sg:orig_category":"Muebles, Minoristas",
    "sg:phone":"+34 934 58 44 13",
    "sg:postcode":"08037",
    "sg:province":"Barcelona",
    "wof:name":"Soriano Ros Juan",
    "wof:placetype":"venue"
},
  "geometry": {"coordinates":[2.1635479927,41.402885437],"type":"Point"}
}