{
  "type": "Feature",
  "properties": {
    "addr:full":"Carrer de Lluis Pascual Roca, 85 S. Boi Llobregat Barcelona 08830",
    "addr:housenumber":"85",
    "addr:postcode":"08830",
    "addr:street":"Carrer De Lluis Pascual Roca",
    "iso:country":"ES",
    "sg:address":"Carrer de Lluis Pascual Roca, 85",
    "sg:city":"S. Boi Llobregat",
    "sg:orig_category":"Electrodom\u00c9sticos (al Por Menor)",
    "sg:phone":"+34 936 54 41 53",
    "sg:postcode":"08830",
    "sg:province":"Barcelona",
    "wof:name":"Tejada Santamaria Luis",
    "wof:placetype":"venue"
},
  "geometry": {"coordinates":[2.0342381001,41.3462982178],"type":"Point"}
}