{
  "type": "Feature",
  "properties": {
    "iso:country":"ES",
    "sg:address":"Carrer de Girona, 11",
    "sg:city":"Tarragona",
    "sg:classifiers":[
        {
            "category":"Autos & Motor Vehicles",
            "subcategory":"Automobile Sales",
            "type":"Retail Goods"
        }
    ],
    "sg:phone":"+34 977 23 64 01",
    "sg:postcode":"43003",
    "sg:province":"Tarragona",
    "wof:name":"Carlos Y Paloma Fillo Merelo S.c:p.",
    "wof:placetype":"venue"
},
  "geometry": {"coordinates":[1.2555279732,41.1149253845],"type":"Point"}
}