{
  "type": "Feature",
  "properties": {
    "addr:full":"Carrer de Can Puiggener, 1 Sabadell Barcelona 08208",
    "addr:housenumber":"1",
    "addr:postcode":"08208",
    "addr:street":"Carrer De Can Puiggener",
    "iso:country":"ES",
    "sg:address":"Carrer de Can Puiggener, 1",
    "sg:city":"Sabadell",
    "sg:orig_category":"Abogados",
    "sg:phone":"+34 937 13 62 09",
    "sg:postcode":"08208",
    "sg:province":"Barcelona",
    "wof:name":"Marquez Perez Manuel",
    "wof:placetype":"venue"
},
  "geometry": {"coordinates":[2.1068749428,41.5523529053],"type":"Point"}
}