{
  "type": "Feature",
  "properties": {
    "addr:full":"Angel (pazos De Reyes), 1 Angel Pontevedra 36715",
    "addr:housenumber":"1",
    "addr:postcode":"36715",
    "addr:street":"Angel Pazos De Reyes",
    "iso:country":"ES",
    "sg:address":"Angel (pazos De Reyes), 1",
    "sg:city":"Angel",
    "sg:orig_category":"Alimentaci\u00d3n: Aditivos, Esencias Alimentarias, Levaduras (fabricaci\u00d3n, Al Por Mayor)",
    "sg:phone":"+34 986 62 79 35",
    "sg:postcode":"36715",
    "sg:province":"Pontevedra",
    "sg:website":"www.abiasa.es",
    "wof:name":"Avances Bioquimicos Alimentacion S.a.",
    "wof:placetype":"venue"
},
  "geometry": {"coordinates":[-8.6428003311,42.4304618835],"type":"Point"}
}