{
  "type": "Feature",
  "properties": {
    "addr:full":"Calle de Paz (la), 25 Almansa Albacete 02640",
    "addr:housenumber":"25",
    "addr:postcode":"02640",
    "addr:street":"Calle De Paz La",
    "iso:country":"ES",
    "sg:address":"Calle de Paz (la), 25",
    "sg:city":"Almansa",
    "sg:orig_category":"Agencias Y Agentes Comerciales, Representantes",
    "sg:phone":"+34 967 34 07 69",
    "sg:postcode":"02640",
    "sg:province":"Albacete",
    "wof:name":"Lopez Ruano Francisco",
    "wof:placetype":"venue"
},
  "geometry": {"coordinates":[-1.0979889631,38.8636512756],"type":"Point"}
}