{
  "type": "Feature",
  "properties": {
    "addr:full":"Ctra Almarcha, S/n S. Clemente Cuenca 16600",
    "addr:housenumber":"s",
    "addr:postcode":"16600",
    "addr:street":"Ctra Almarcha;/ N S. Clemente Cuenca",
    "iso:country":"ES",
    "sg:address":"Ctra Almarcha, S/n",
    "sg:city":"S. Clemente",
    "sg:orig_category":"Electricidad (montaje, Ensamblaje De Componentes)",
    "sg:phone":"+34 969 30 11 10",
    "sg:postcode":"16600",
    "sg:province":"Cuenca",
    "wof:name":"Jose Maria Beamud Fierre S.l.",
    "wof:placetype":"venue"
},
  "geometry": {"coordinates":[-2.4086811543,39.4386940002],"type":"Point"}
}