{
  "type": "Feature",
  "properties": {
    "addr:full":"Avda Galicia De, S/n Salas Asturias 33860",
    "addr:postcode":"33860",
    "addr:street":"Avda Galicia De S / N",
    "iso:country":"ES",
    "sg:address":"Avda Galicia De, S/n",
    "sg:city":"Salas",
    "sg:orig_category":"Alimentaci\u00d3n General (al Por Mayor)",
    "sg:phone":"+34 985 83 08 17",
    "sg:postcode":"33860",
    "sg:province":"Asturias",
    "wof:name":"Gonzalez Rodriguez Julia",
    "wof:placetype":"venue"
},
  "geometry": {"coordinates":[-6.2595391273,43.4086761475],"type":"Point"}
}