{
  "type": "Feature",
  "properties": {
    "addr:full":"O Lugar Grande, S/n Corcoesto Lugar Grande La Coru\u00f1a 15111",
    "addr:housenumber":"s / n",
    "addr:postcode":"15111",
    "addr:street":"Lugar;Lugar;La Corun\u0303A",
    "iso:country":"ES",
    "sg:address":"O Lugar Grande, S/n",
    "sg:city":"Corcoesto Lugar Grande",
    "sg:orig_category":"Material Hidr\u00c1ulico",
    "sg:phone":"+34 981 71 50 53",
    "sg:postcode":"15111",
    "sg:province":"La Coru\u00f1a",
    "wof:name":"Naturener S. A.",
    "wof:placetype":"venue"
},
  "geometry": {"coordinates":[-8.7833986282,43.2669487],"type":"Point"}
}