{
  "type": "Feature",
  "properties": {
    "iso:country":"ES",
    "sg:address":"Calle de Mayor, 22",
    "sg:city":"Puente Tocinos",
    "sg:orig_category":"Caf\u00c9s, Bares, Cervecer\u00cdas",
    "sg:phone":"+34 968 20 40 82",
    "sg:postcode":"30006",
    "sg:province":"Murcia",
    "wof:name":"Arnau Martinez Noelia",
    "wof:placetype":"venue"
},
  "geometry": {"coordinates":[-1.1066511869,37.9918022156],"type":"Point"}
}