{
  "type": "Feature",
  "properties": {
    "addr:full":"Calle de Aljirofe, 9 Galdar Las Palmas 35460",
    "addr:housenumber":"9",
    "addr:postcode":"35460",
    "addr:street":"Calle De Aljirofe",
    "iso:country":"ES",
    "sg:address":"Calle de Aljirofe, 9",
    "sg:city":"Galdar",
    "sg:orig_category":"Centros Empresariales",
    "sg:phone":"+34 928 55 22 22",
    "sg:postcode":"35460",
    "sg:province":"Las Palmas",
    "wof:name":"Asociacion De Empresarios De Eurotaxis De Galdar",
    "wof:placetype":"venue"
},
  "geometry": {"coordinates":[-15.6539754868,28.1449642181],"type":"Point"}
}