{
  "type": "Feature",
  "properties": {
    "addr:full":"Calle de Alcolea, 71 Villafranca Cordoba C\u00f3rdoba 14420",
    "addr:housenumber":"71",
    "addr:postcode":"14420",
    "addr:street":"Calle De Alcolea",
    "iso:country":"ES",
    "sg:address":"Calle de Alcolea, 71",
    "sg:city":"Villafranca Cordoba",
    "sg:orig_category":"Centros De Educaci\u00d3n Especial",
    "sg:phone":"+34 957 19 02 67",
    "sg:postcode":"14420",
    "sg:province":"C\u00f3rdoba",
    "wof:name":"Junta De Andalucia",
    "wof:placetype":"venue"
},
  "geometry": {"coordinates":[-4.54570961,37.9619560242],"type":"Point"}
}