{
  "type": "Feature",
  "properties": {
    "addr:full":"Avda Gran Capitan (del), 46 Cordoba C\u00f3rdoba 14006",
    "addr:housenumber":"46",
    "addr:postcode":"14006",
    "addr:street":"Avda Gran Capitan Del;Co\u0301Rdoba",
    "iso:country":"ES",
    "sg:address":"Avda Gran Capitan (del), 46",
    "sg:city":"Cordoba",
    "sg:orig_category":"Sindicatos Y Colegios Profesionales",
    "sg:phone":"+34 957 27 00 77",
    "sg:postcode":"14006",
    "sg:province":"C\u00f3rdoba",
    "wof:name":"Asociacion De Trabajadores Autonomos De Andalucia",
    "wof:placetype":"venue"
},
  "geometry": {"coordinates":[-4.7829303741,37.8903274536],"type":"Point"}
}