{
  "type": "Feature",
  "properties": {
    "iso:country":"ES",
    "sg:address":"Calle de Jose Cadiz Salvatierra, 4",
    "sg:city":"Jerez De La Frontera",
    "sg:orig_category":"Abogados",
    "sg:phone":"+34 956 34 84 06",
    "sg:postcode":"11405",
    "sg:province":"C\u00e1diz",
    "wof:name":"Gracia De Torres Miguel",
    "wof:placetype":"venue"
},
  "geometry": {"coordinates":[-6.1321392059,36.691608429],"type":"Point"}
}