{
  "type": "Feature",
  "properties": {
    "addr:full":"Calle de Diputacion Foral De Alava, 1 Vitoria-gasteiz \u00c1lava 01001",
    "addr:housenumber":"1",
    "addr:postcode":"01001",
    "addr:street":"Calle De Diputacion Foral De Alava",
    "iso:country":"ES",
    "sg:address":"Calle de Diputacion Foral De Alava, 1",
    "sg:city":"Vitoria-gasteiz",
    "sg:classifiers":[
        {
            "category":"Government",
            "subcategory":"City Hall",
            "type":"Public Place"
        }
    ],
    "sg:phone":"+34 945 25 04 00",
    "sg:postcode":"01001",
    "sg:province":"\u00c1lava",
    "sg:tags":[
        "el",
        "alquiler",
        "extranjero",
        "villa",
        "de",
        "en"
    ],
    "wof:name":"Fincas Anitua S.l.",
    "wof:placetype":"venue"
},
  "geometry": {"coordinates":[-2.6739265919,42.8463668823],"type":"Point"}
}