{
  "type": "Feature",
  "properties": {
    "iso:country":"ES",
    "sg:address":"Calle de Entrepe\u00d1as, 129",
    "sg:city":"Alcala Henares",
    "sg:orig_category":"Caf\u00c9s, Bares, Cervecer\u00cdas",
    "sg:phone":"+34 918 81 23 29",
    "sg:postcode":"28803",
    "sg:province":"Madrid",
    "wof:name":"Tejedor Laosa Julio",
    "wof:placetype":"venue"
},
  "geometry": {"coordinates":[-3.3630640507,40.4700698853],"type":"Point"}
}