{
  "type": "Feature",
  "properties": {
    "iso:country":"ES",
    "sg:address":"Avda Pais Valenciano, 10",
    "sg:city":"Albatera",
    "sg:orig_category":"Comercio De Piezas De Recambio Y De Accesorios De Veh\u00cdculos, Veh\u00cdculos Industriales",
    "sg:phone":"+34 965 48 74 89",
    "sg:postcode":"03340",
    "sg:province":"Alicante",
    "wof:name":"Canovas Carre\u00f1o Francisco Jose",
    "wof:placetype":"venue"
},
  "geometry": {"coordinates":[-0.8745689988,38.1775512695],"type":"Point"}
}