{
  "type": "Feature",
  "properties": {
    "addr:full":"Calle de Canalejas, 12 Don Benito Badajoz 06400",
    "addr:housenumber":"12",
    "addr:postcode":"06400",
    "addr:street":"Calle De Canalejas",
    "iso:country":"ES",
    "sg:address":"Calle de Canalejas, 12",
    "sg:city":"Don Benito",
    "sg:orig_category":"Ropa De Hogar (al Por Menor)",
    "sg:phone":"+34 924 81 32 26",
    "sg:postcode":"06400",
    "sg:province":"Badajoz",
    "wof:name":"Tiendas Pavo S.l.",
    "wof:placetype":"venue"
},
  "geometry": {"coordinates":[-5.85623312,38.9614715576],"type":"Point"}
}