{
  "type": "Feature",
  "properties": {
    "addr:full":"Avda Alicante, 15 Monforte Cid Alicante 03670",
    "addr:housenumber":"15",
    "addr:postcode":"03670",
    "addr:street":"Avda Alicante",
    "iso:country":"ES",
    "sg:address":"Avda Alicante, 15",
    "sg:city":"Monforte Cid",
    "sg:orig_category":"Estancos",
    "sg:phone":"+34 965 62 02 87",
    "sg:postcode":"03670",
    "sg:province":"Alicante",
    "wof:name":"Alberola Vicente Gloria",
    "wof:placetype":"venue"
},
  "geometry": {"coordinates":[-0.7288544774,38.3802261353],"type":"Point"}
}