{
  "type": "Feature",
  "properties": {
    "addr:full":"Carrer de Font Vella, 97 Terrassa Barcelona 08221",
    "addr:housenumber":"97",
    "addr:postcode":"08221",
    "addr:street":"Carrer De;Vella",
    "iso:country":"ES",
    "sg:address":"Carrer de Font Vella, 97",
    "sg:city":"Terrassa",
    "sg:orig_category":"Farmacias",
    "sg:phone":"+34 937 36 20 23",
    "sg:postcode":"08221",
    "sg:province":"Barcelona",
    "wof:name":"Tarin Cardona Lluis",
    "wof:placetype":"venue"
},
  "geometry": {"coordinates":[2.0146150589,41.5631141663],"type":"Point"}
}