{
  "type": "Feature",
  "properties": {
    "iso:country":"ES",
    "sg:address":"Carrer de Joan Prim, 112",
    "sg:city":"Granollers",
    "sg:orig_category":"Loter\u00cda Y T\u00d3mbola",
    "sg:phone":"+34 938 49 19 98",
    "sg:postcode":"08402",
    "sg:province":"Barcelona",
    "wof:name":"Fernandez Vicente Isabel",
    "wof:placetype":"venue"
},
  "geometry": {"coordinates":[2.2903189659,41.6126251221],"type":"Point"}
}