{
  "type": "Feature",
  "properties": {
    "iso:country":"ES",
    "sg:address":"Calle de Cobre, 3",
    "sg:city":"Torre-pacheco",
    "sg:orig_category":"Frutas Y Legumbres Frescas (al Por Mayor)",
    "sg:phone":"+34 968 57 97 45",
    "sg:postcode":"30700",
    "sg:province":"Murcia",
    "wof:name":"Vegetales De Murcia S.c.l.",
    "wof:placetype":"venue"
},
  "geometry": {"coordinates":[-0.953466475,37.7335243225],"type":"Point"}
}