{
  "type": "Feature",
  "properties": {
    "iso:country":"ES",
    "sg:address":"Carr Pablo Neruda, 10",
    "sg:city":"Blanes",
    "sg:orig_category":"Laboratorios Y Trabajos De Fotograf\u00cda, V\u00cddeo Y Cine",
    "sg:phone":"+34 972 35 14 56",
    "sg:postcode":"17300",
    "sg:province":"Girona",
    "wof:name":"Riba Mas Ramon",
    "wof:placetype":"venue"
},
  "geometry": {"coordinates":[2.7752199173,41.6674880981],"type":"Point"}
}