{
  "type": "Feature",
  "properties": {
    "addr:full":"Rua Irmans Labarta, 22 Noia La Coru\u00f1a 15200",
    "addr:housenumber":"22",
    "addr:postcode":"15200",
    "addr:street":"Rua Irmans Labarta;La Corun\u0303A",
    "iso:country":"ES",
    "sg:address":"Rua Irmans Labarta, 22",
    "sg:city":"Noia",
    "sg:orig_category":"Plomeros",
    "sg:phone":"+34 981 82 47 72",
    "sg:postcode":"15200",
    "sg:province":"La Coru\u00f1a",
    "wof:name":"Instalaciones J.ramos S.l.",
    "wof:placetype":"venue"
},
  "geometry": {"coordinates":[-8.8892793655,42.7863883972],"type":"Point"}
}