{
  "type": "Feature",
  "properties": {
    "addr:full":"Calle de Porlier, 46 Santa Cruz De Tenerife Santa Cruz De Tenerife 38004",
    "addr:housenumber":"46",
    "addr:postcode":"38004",
    "addr:street":"Calle De Porlier",
    "iso:country":"ES",
    "sg:address":"Calle de Porlier, 46",
    "sg:city":"Santa Cruz De Tenerife",
    "sg:orig_category":"Inform\u00c1tica: Material Y Suministros",
    "sg:phone":"+34 922 29 19 21",
    "sg:postcode":"38004",
    "sg:province":"Santa Cruz De Tenerife",
    "wof:name":"Inforlex Canarias S.l.",
    "wof:placetype":"venue"
},
  "geometry": {"coordinates":[-16.260055542,28.4670772552],"type":"Point"}
}