{
  "type": "Feature",
  "properties": {
    "addr:full":"Avda Ourense (de), 12 Xinzo De Limia Ourense 32630",
    "addr:housenumber":"12",
    "addr:postcode":"32630",
    "addr:street":"Avda Ourense De",
    "iso:country":"ES",
    "sg:address":"Avda Ourense (de), 12",
    "sg:city":"Xinzo De Limia",
    "sg:classifiers":[
        {
            "category":"Autos & Motor Vehicles",
            "subcategory":"Automobile Sales",
            "type":"Retail Goods"
        }
    ],
    "sg:phone":"+34 988 46 12 40",
    "sg:postcode":"32630",
    "sg:province":"Ourense",
    "wof:name":"Barrio Rodriguez Serafin",
    "wof:placetype":"venue"
},
  "geometry": {"coordinates":[-7.7259440422,42.0631408691],"type":"Point"}
}