{
  "type": "Feature",
  "properties": {
    "addr:full":"Carrer de Roger De Flor, 2 Granollers Barcelona 08401",
    "addr:housenumber":"2",
    "addr:postcode":"08401",
    "addr:street":"Carrer De Roger De Flor",
    "iso:country":"ES",
    "sg:address":"Carrer de Roger De Flor, 2",
    "sg:city":"Granollers",
    "sg:orig_category":"Agencias Y Agentes Comerciales, Representantes",
    "sg:phone":"+34 938 79 09 17",
    "sg:postcode":"08401",
    "sg:province":"Barcelona",
    "wof:name":"Ariza Casula Francisco",
    "wof:placetype":"venue"
},
  "geometry": {"coordinates":[2.2834610939,41.6105499268],"type":"Point"}
}