{
  "type": "Feature",
  "properties": {
    "iso:country":"ES",
    "sg:address":"Calle de Godella, 245",
    "sg:city":"Madrid",
    "sg:orig_category":"Distribuci\u00d3n De Petr\u00d3leo Y Derivados",
    "sg:phone":"+34 917 97 10 19",
    "sg:postcode":"28021",
    "sg:province":"Madrid",
    "wof:name":"Dominguez Joven Luis",
    "wof:placetype":"venue"
},
  "geometry": {"coordinates":[-3.6880691051,40.340171814],"type":"Point"}
}