{
  "type": "Feature",
  "properties": {
    "addr:full":"Calle de Olivo, 2 Ciudad Real Ciudad Real 13002",
    "addr:housenumber":"2",
    "addr:postcode":"13002",
    "addr:street":"Calle De Olivo",
    "iso:country":"ES",
    "sg:address":"Calle de Olivo, 2",
    "sg:city":"Ciudad Real",
    "sg:orig_category":"Veh\u00cdculos De Ocasi\u00d3n",
    "sg:phone":"+34 926 21 39 29",
    "sg:postcode":"13002",
    "sg:province":"Ciudad Real",
    "wof:name":"Oca\u00f1a Heredia Enrique",
    "wof:placetype":"venue"
},
  "geometry": {"coordinates":[-3.9319310188,38.985294342],"type":"Point"}
}