{
  "type": "Feature",
  "properties": {
    "iso:country":"ES",
    "sg:address":"C/ Sant Pelegri, 83",
    "sg:city":"Tarrega",
    "sg:orig_category":"Delegados, Agentes De Tr\u00c1nsito, Auxiliares De Transporte Internacional",
    "sg:phone":"+34 973 31 03 18",
    "sg:postcode":"25300",
    "sg:province":"Lleida",
    "wof:name":"Arrufat Manonelles Jose",
    "wof:placetype":"venue"
},
  "geometry": {"coordinates":[1.1385211945,41.6529502869],"type":"Point"}
}