{
  "type": "Feature",
  "properties": {
    "iso:country":"ES",
    "sg:address":"Carrer de Circumval.lacio, 43",
    "sg:city":"Viladecans",
    "sg:orig_category":"Centros M\u00c9dicos Y Sociales, Dispensarios",
    "sg:phone":"+34 936 37 69 34",
    "sg:postcode":"08840",
    "sg:province":"Barcelona",
    "wof:name":"Sant Joan De Deu-serveis De Salut Mental",
    "wof:placetype":"venue"
},
  "geometry": {"coordinates":[2.0066139698,41.3226356506],"type":"Point"}
}