{
  "type": "Feature",
  "properties": {
    "addr:full":"Pase Recoletos, 41 Madrid Madrid 28004",
    "addr:housenumber":"41",
    "addr:postcode":"madrid;28004",
    "addr:street":"Recoletos",
    "iso:country":"ES",
    "sg:address":"Pase Recoletos, 41",
    "sg:city":"Madrid",
    "sg:orig_category":"Museos",
    "sg:phone":"+34 913 08 08 25",
    "sg:postcode":"28004",
    "sg:province":"Madrid",
    "sg:website":"www.museoceramadrid.com",
    "wof:name":"Internacional Artis S. A.",
    "wof:placetype":"venue"
},
  "geometry": {"coordinates":[-3.6912109852,40.4248428345],"type":"Point"}
}