{
  "type": "Feature",
  "properties": {
    "addr:full":"Carrer de Jaume Balmes, 21 Granollers Barcelona 08401",
    "addr:housenumber":"21",
    "addr:postcode":"08401",
    "addr:street":"Carrer De Jaume Balmes",
    "iso:country":"ES",
    "sg:address":"Carrer de Jaume Balmes, 21",
    "sg:city":"Granollers",
    "sg:orig_category":"Hilaturas, Hilos Y Actividades Relacionadas",
    "sg:phone":"+34 938 79 54 00",
    "sg:postcode":"08401",
    "sg:province":"Barcelona",
    "wof:name":"Sunbox Distribution S.l.",
    "wof:placetype":"venue"
},
  "geometry": {"coordinates":[2.2843248844,41.6095848083],"type":"Point"}
}