{
  "type": "Feature",
  "properties": {
    "iso:country":"ES",
    "sg:address":"Calle de Burgos, 2",
    "sg:city":"Mostoles",
    "sg:orig_category":"Muebles, Minoristas",
    "sg:phone":"+34 916 13 06 71",
    "sg:postcode":"28931",
    "sg:province":"Madrid",
    "wof:name":"Muebles San Vicente Real S.l.",
    "wof:placetype":"venue"
},
  "geometry": {"coordinates":[-3.8599903584,40.3269844055],"type":"Point"}
}