{
  "type": "Feature",
  "properties": {
    "addr:full":"Calle de Puente Colgante, 2 Valladolid Valladolid 47007",
    "addr:housenumber":"2",
    "addr:postcode":"47007",
    "addr:street":"Calle De Puente Colgante",
    "iso:country":"ES",
    "sg:address":"Calle de Puente Colgante, 2",
    "sg:city":"Valladolid",
    "sg:orig_category":"Centros Empresariales",
    "sg:phone":"+34 983 22 40 92",
    "sg:postcode":"47007",
    "sg:province":"Valladolid",
    "wof:name":"Asociacion Empresarial De Transportes De Valladolid",
    "wof:placetype":"venue"
},
  "geometry": {"coordinates":[-4.7320327759,41.6411590576],"type":"Point"}
}