{
  "type": "Feature",
  "properties": {
    "iso:country":"ES",
    "sg:address":"Rua Quiroga Ballesteros, 6",
    "sg:city":"Lugo",
    "sg:orig_category":"Alimentaci\u00d3n General (al Por Menor)",
    "sg:phone":"+34 982 24 20 38",
    "sg:postcode":"27001",
    "sg:province":"Lugo",
    "wof:name":"Jato Perez Enrique",
    "wof:placetype":"venue"
},
  "geometry": {"coordinates":[-7.5579428673,43.0119438171],"type":"Point"}
}