{
  "type": "Feature",
  "properties": {
    "addr:full":"Calle de Puerto De La Cruz Verde, 26 Madrid Madrid 28045",
    "addr:housenumber":"26",
    "addr:postcode":"madrid;28045",
    "addr:street":"Calle De Puerto;Verde",
    "iso:country":"ES",
    "sg:address":"Calle de Puerto De La Cruz Verde, 26",
    "sg:city":"Madrid",
    "sg:orig_category":"Laboratorios Y Cl\u00cdnicas Veterinarias",
    "sg:phone":"+34 914 67 05 81",
    "sg:postcode":"28045",
    "sg:province":"Madrid",
    "wof:name":"Centro Medico Veterinario Parque Tierno S.l.",
    "wof:placetype":"venue"
},
  "geometry": {"coordinates":[-3.6860899925,40.3855323792],"type":"Point"}
}