{
  "type": "Feature",
  "properties": {
    "addr:full":"Cami Vell De Ciutat, 79 Campos Islas Baleares 07630",
    "addr:housenumber":"79",
    "addr:postcode":"07630",
    "addr:street":"Cami Vell De Ciutat",
    "iso:country":"ES",
    "sg:address":"Cami Vell De Ciutat, 79",
    "sg:city":"Campos",
    "sg:orig_category":"Grabados Y Decoraci\u00d3n De Metales",
    "sg:phone":"+34 971 65 11 05",
    "sg:postcode":"07630",
    "sg:province":"Islas Baleares",
    "wof:name":"Metal Guifran S.l.",
    "wof:placetype":"venue"
},
  "geometry": {"coordinates":[3.0078866482,39.4356689453],"type":"Point"}
}