{
  "type": "Feature",
  "properties": {
    "iso:country":"ES",
    "sg:address":"Carrer de Aribau, 11",
    "sg:city":"Barcelona",
    "sg:orig_category":"Administradores De Bienes Y Delegados De Comunidades De Propietarios",
    "sg:phone":"+34 934 54 42 07",
    "sg:postcode":"08011",
    "sg:province":"Barcelona",
    "wof:name":"Arnos2000 Sl",
    "wof:placetype":"venue"
},
  "geometry": {"coordinates":[2.1620886326,41.3863258362],"type":"Point"}
}