{
  "type": "Feature",
  "properties": {
    "addr:full":"Ptda Beniparrell, 58 Beniparrell Castell\u00f3n 12200",
    "addr:housenumber":"58",
    "addr:postcode":"12200",
    "addr:street":"Ptda Beniparrell",
    "iso:country":"ES",
    "sg:address":"Ptda Beniparrell, 58",
    "sg:city":"Beniparrell",
    "sg:orig_category":"T\u00c9cnicos Veterinarios",
    "sg:phone":"+34 964 60 25 25",
    "sg:postcode":"12200",
    "sg:province":"Castell\u00f3n",
    "wof:name":"Gasco Moreno Rafael",
    "wof:placetype":"venue"
},
  "geometry": {"coordinates":[-0.2620640099,39.9651794434],"type":"Point"}
}