{
  "type": "Feature",
  "properties": {
    "iso:country":"ES",
    "sg:address":"Rond Norte, S/n",
    "sg:city":"Isla Cristina",
    "sg:orig_category":"Alimentaci\u00d3n General (al Por Menor)",
    "sg:phone":"+34 959 34 34 15",
    "sg:postcode":"21410",
    "sg:province":"Huelva",
    "wof:name":"Super Isla S.l.",
    "wof:placetype":"venue"
},
  "geometry": {"coordinates":[-7.3228740692,37.2037658691],"type":"Point"}
}