{
  "type": "Feature",
  "properties": {
    "addr:full":"Calle de Torquemada, 16 Madrid Madrid 28043",
    "addr:housenumber":"16",
    "addr:postcode":"madrid;28043",
    "addr:street":"Calle De Torquemada",
    "iso:country":"ES",
    "sg:address":"Calle de Torquemada, 16",
    "sg:city":"Madrid",
    "sg:orig_category":"Asesor\u00cda Sobre Comunicaci\u00d3n De Empresas",
    "sg:phone":"+34 913 81 28 15",
    "sg:postcode":"28043",
    "sg:province":"Madrid",
    "wof:name":"Asesoria Integral De Empresas Castilla S.l.",
    "wof:placetype":"venue"
},
  "geometry": {"coordinates":[-3.6405289173,40.4666786194],"type":"Point"}
}