{
  "type": "Feature",
  "properties": {
    "addr:full":"Pg Almogavers, 12 Sabadell Barcelona 08204",
    "addr:housenumber":"12",
    "addr:postcode":"08204",
    "addr:street":"Pg Almogavers",
    "iso:country":"ES",
    "sg:address":"Pg Almogavers, 12",
    "sg:city":"Sabadell",
    "sg:orig_category":"Reposter\u00cdas",
    "sg:phone":"+34 937 10 61 82",
    "sg:postcode":"08204",
    "sg:province":"Barcelona",
    "wof:name":"Forn De Sant Quize S.l.",
    "wof:placetype":"venue"
},
  "geometry": {"coordinates":[2.1218979359,41.5306816101],"type":"Point"}
}