{
  "type": "Feature",
  "properties": {
    "iso:country":"ES",
    "sg:address":"Calle de Malaga, S/n",
    "sg:city":"Calpe",
    "sg:orig_category":"Promotores Constructores",
    "sg:phone":"+34 965 83 74 79",
    "sg:postcode":"03710",
    "sg:province":"Alicante",
    "wof:name":"Fincas Calpe S.l.",
    "wof:placetype":"venue"
},
  "geometry": {"coordinates":[0.0476250015,38.6450233459],"type":"Point"}
}