{
  "type": "Feature",
  "properties": {
    "iso:country":"ES",
    "sg:address":"Calle de Miguel Bueno, 6",
    "sg:city":"Fuengirola",
    "sg:orig_category":"Arreglo, Reparaci\u00d3n, Piezas Sueltas De Televisi\u00d3n, V\u00cddeo, Hi",
    "sg:phone":"+34 952 47 29 03",
    "sg:postcode":"29640",
    "sg:province":"M\u00e1laga",
    "sg:website":"www.electronica200sl.com",
    "wof:name":"A. Jimenez Electro 2000 S.l.",
    "wof:placetype":"venue"
},
  "geometry": {"coordinates":[-4.6282858849,36.543800354],"type":"Point"}
}