{
  "type": "Feature",
  "properties": {
    "addr:full":"Calle de Irurzun, 61 Peralta Navarra 31350",
    "addr:housenumber":"61",
    "addr:postcode":"31350",
    "addr:street":"Calle De Irurzun",
    "iso:country":"ES",
    "sg:address":"Calle de Irurzun, 61",
    "sg:city":"Peralta",
    "sg:orig_category":"Quincaller\u00cda (al Por Menor)",
    "sg:phone":"+34 948 75 01 07",
    "sg:postcode":"31350",
    "sg:province":"Navarra",
    "wof:name":"Campo Oses Blanca",
    "wof:placetype":"venue"
},
  "geometry": {"coordinates":[-1.7946790457,42.3372612],"type":"Point"}
}