{
  "type": "Feature",
  "properties": {
    "iso:country":"ES",
    "sg:address":"Carr Beat Jofre, 21",
    "sg:city":"Puig",
    "sg:orig_category":"\u00d3ptica: Instrumentos (fabricaci\u00d3n)",
    "sg:phone":"+34 961 47 25 59",
    "sg:postcode":"46540",
    "sg:province":"Valencia",
    "wof:name":"Ferrer Blasco Maria Teresa",
    "wof:placetype":"venue"
},
  "geometry": {"coordinates":[-0.3003390133,39.5875854492],"type":"Point"}
}