{
  "type": "Feature",
  "properties": {
    "addr:full":"Rond Arraona, 6 S. Quirze Valles Barcelona 08192",
    "addr:housenumber":"6",
    "addr:postcode":"08192",
    "addr:street":"Arraona;Barcelona",
    "iso:country":"ES",
    "sg:address":"Rond Arraona, 6",
    "sg:city":"S. Quirze Valles",
    "sg:classifiers":[
        {
            "category":"Autos & Motor Vehicles",
            "subcategory":"Automobile Sales",
            "type":"Retail Goods"
        }
    ],
    "sg:phone":"+34 937 21 05 01",
    "sg:postcode":"08192",
    "sg:province":"Barcelona",
    "wof:name":"Autoescuela Girbau S.l.",
    "wof:placetype":"venue"
},
  "geometry": {"coordinates":[2.0770950317,41.535243988],"type":"Point"}
}