{
  "type": "Feature",
  "properties": {
    "iso:country":"ES",
    "sg:address":"Poli Los Ca\u00d1os, S/n",
    "sg:city":"Zafra",
    "sg:orig_category":"Lencer\u00cda Femenina, Corseter\u00cda, Trajes De Ba\u00d1o (al Por Menor)",
    "sg:phone":"+34 924 55 24 65",
    "sg:postcode":"06300",
    "sg:province":"Badajoz",
    "wof:name":"Balco S.a.",
    "wof:placetype":"venue"
},
  "geometry": {"coordinates":[-6.4609999657,38.4436187744],"type":"Point"}
}