{
  "type": "Feature",
  "properties": {
    "addr:full":"Calle de Voluntarios De Santiago, 1 Huesca Huesca 22004",
    "addr:housenumber":"1",
    "addr:postcode":"22004",
    "addr:street":"Calle De Voluntarios;Santiago",
    "iso:country":"ES",
    "sg:address":"Calle de Voluntarios De Santiago, 1",
    "sg:city":"Huesca",
    "sg:orig_category":"Audiovisuales (producci\u00d3n, Edici\u00d3n, Realizaci\u00d3n)",
    "sg:phone":"+34 974 23 08 89",
    "sg:postcode":"22004",
    "sg:province":"Huesca",
    "wof:name":"Producciones Audiovisuales Iris S.l.",
    "wof:placetype":"venue"
},
  "geometry": {"coordinates":[-0.4164808989,42.1421508789],"type":"Point"}
}