{
  "type": "Feature",
  "properties": {
    "addr:full":"Carr Papa Alejandro Vi, 3 Oliva Valencia 46780",
    "addr:housenumber":"3",
    "addr:postcode":"46780",
    "addr:street":"Carr Papa Alejandro Vi",
    "iso:country":"ES",
    "sg:address":"Carr Papa Alejandro Vi, 3",
    "sg:city":"Oliva",
    "sg:orig_category":"Insecticidas, Fumigaci\u00d3n",
    "sg:phone":"+34 962 85 06 59",
    "sg:postcode":"46780",
    "sg:province":"Valencia",
    "wof:name":"Genagri S.l.",
    "wof:placetype":"venue"
},
  "geometry": {"coordinates":[-0.1153620034,38.9177398682],"type":"Point"}
}