{
  "type": "Feature",
  "properties": {
    "iso:country":"ES",
    "sg:address":"Calle de Valencia, 42",
    "sg:city":"Palmas De Gran Canaria",
    "sg:orig_category":"Empresas De Limpieza",
    "sg:phone":"+34 928 29 52 90",
    "sg:postcode":"35006",
    "sg:province":"Las Palmas",
    "wof:name":"U.t.e. Limpiezas Quesadas-canarias Sea",
    "wof:placetype":"venue"
},
  "geometry": {"coordinates":[-15.432062149,28.1334781647],"type":"Point"}
}