{
  "type": "Feature",
  "properties": {
    "addr:full":"Calle de Empedrada, S/n Bercero Valladolid 47115",
    "addr:housenumber":"s / n",
    "addr:postcode":"47115",
    "addr:street":"Calle De Empedrada",
    "iso:country":"ES",
    "sg:address":"Calle de Empedrada, S/n",
    "sg:city":"Bercero",
    "sg:orig_category":"Reposter\u00cdas",
    "sg:phone":"+34 983 77 09 58",
    "sg:postcode":"47115",
    "sg:province":"Valladolid",
    "wof:name":"Velasco Alonso Ernesto",
    "wof:placetype":"venue"
},
  "geometry": {"coordinates":[-5.0551638603,41.5650482178],"type":"Point"}
}