{
  "type": "Feature",
  "properties": {
    "addr:full":"Otalora Lizentziaduna Kalea, 29 Arrasate Guip\u00f9zcoa 20500",
    "addr:housenumber":"29",
    "addr:postcode":"20500",
    "addr:street":"Otalora Lizentziaduna Kalea;Guipu\u0300Zcoa",
    "iso:country":"ES",
    "sg:address":"Otalora Lizentziaduna Kalea, 29",
    "sg:city":"Arrasate",
    "sg:orig_category":"Fotograf\u00cda Y Cine: Aparatos, Pel\u00cdculas Y Accesorios (fabricaci\u00d3n, Al Por Mayor)",
    "sg:phone":"+34 943 77 09 01",
    "sg:postcode":"20500",
    "sg:province":"Guip\u00f9zcoa",
    "wof:name":"Sebastian San Miguel Mari Carmen",
    "wof:placetype":"venue"
},
  "geometry": {"coordinates":[-2.487128973,43.066318512],"type":"Point"}
}