{
  "type": "Feature",
  "properties": {
    "addr:full":"Av Vives Llull, 20 Mao Islas Baleares 07703",
    "addr:housenumber":"20",
    "addr:postcode":"07703",
    "addr:street":"Av Vives Llull",
    "iso:country":"ES",
    "sg:address":"Av Vives Llull, 20",
    "sg:city":"Mao",
    "sg:orig_category":"Ense\u00d1anza, Formaci\u00d3n Profesional: Aprendizaje",
    "sg:phone":"+34 971 35 31 58",
    "sg:postcode":"07703",
    "sg:province":"Islas Baleares",
    "wof:name":"Ajuntament De Mao",
    "wof:placetype":"venue"
},
  "geometry": {"coordinates":[4.2548379898,39.8880386353],"type":"Point"}
}