{
  "type": "Feature",
  "properties": {
    "addr:full":"Calle de Amposta, 3 Madrid Madrid 28037",
    "addr:housenumber":"3",
    "addr:postcode":"28037",
    "addr:street":"Calle De Amposta",
    "iso:country":"ES",
    "sg:address":"Calle de Amposta, 3",
    "sg:city":"Madrid",
    "sg:orig_category":"Tiendas De Grano, Frutas Y Legumbres Secas (al Por Menor)",
    "sg:phone":"+34 913 06 27 87",
    "sg:postcode":"28037",
    "sg:province":"Madrid",
    "wof:name":"Nu\u00f1ez Maeso Julio Simon",
    "wof:placetype":"venue"
},
  "geometry": {"coordinates":[-3.6222193241,40.4272880554],"type":"Point"}
}