{
  "type": "Feature",
  "properties": {
    "addr:full":"Avda Beiramar, 127 Vigo Pontevedra 36208",
    "addr:housenumber":"127",
    "addr:postcode":"36208",
    "addr:street":"Avda Beiramar",
    "iso:country":"ES",
    "sg:address":"Avda Beiramar, 127",
    "sg:city":"Vigo",
    "sg:orig_category":"Herradores, Herreros, Carreteros",
    "sg:phone":"+34 986 20 49 74",
    "sg:postcode":"36208",
    "sg:province":"Pontevedra",
    "wof:name":"Jarcias Y Eslingas C.b.",
    "wof:placetype":"venue"
},
  "geometry": {"coordinates":[-8.7412481308,42.2249450684],"type":"Point"}
}