{
  "type": "Feature",
  "properties": {
    "addr:full":"Avda Andalucia, 6 Dos Hermanas Sevilla 41700",
    "addr:housenumber":"6",
    "addr:postcode":"41700",
    "addr:street":"Avda Andalucia;Sevilla",
    "iso:country":"ES",
    "sg:address":"Avda Andalucia, 6",
    "sg:city":"Dos Hermanas",
    "sg:orig_category":"Promotores Constructores",
    "sg:phone":"+34 955 67 90 12",
    "sg:postcode":"41700",
    "sg:province":"Sevilla",
    "wof:name":"Globalia Intermediacion Inmobiliaria S.a.u.",
    "wof:placetype":"venue"
},
  "geometry": {"coordinates":[-5.9276800156,37.2827072144],"type":"Point"}
}