{
  "type": "Feature",
  "properties": {
    "iso:country":"ES",
    "sg:address":"F. Encinarejo Frailes, Km. 0012,0",
    "sg:city":"Encinarejo",
    "sg:orig_category":"Guarda",
    "sg:phone":"+34 957 33 01 27",
    "sg:postcode":"14710",
    "sg:province":"C\u00f3rdoba",
    "wof:name":"Romero Redondo Antonio",
    "wof:placetype":"venue"
},
  "geometry": {"coordinates":[-4.9146289825,37.8490753174],"type":"Point"}
}