{
  "type": "Feature",
  "properties": {
    "addr:full":"Calle de Carmona, 21 Campana Sevilla 41429",
    "addr:housenumber":"21",
    "addr:postcode":"41429",
    "addr:street":"Calle De Carmona",
    "iso:country":"ES",
    "sg:address":"Calle de Carmona, 21",
    "sg:city":"Campana",
    "sg:orig_category":"Empresas De Electricidad En General",
    "sg:phone":"+34 954 19 96 08",
    "sg:postcode":"41429",
    "sg:province":"Sevilla",
    "wof:name":"Central Electrica San Antonio S. A.",
    "wof:placetype":"venue"
},
  "geometry": {"coordinates":[-5.427690506,37.5693435669],"type":"Point"}
}