{
  "type": "Feature",
  "properties": {
    "addr:full":"G.v. Corts Catalanes, 264 Barcelona Barcelona 08004",
    "addr:housenumber":"264",
    "addr:postcode":"08004",
    "addr:street":"Catalanes",
    "iso:country":"ES",
    "sg:address":"G.v. Corts Catalanes, 264",
    "sg:city":"Barcelona",
    "sg:orig_category":"Fabricaci\u00d3n De Juegos Y Juguetes",
    "sg:phone":"+34 934 23 19 88",
    "sg:postcode":"08004",
    "sg:province":"Barcelona",
    "sg:website":"www.juguetestiosam.com",
    "wof:name":"Sam-distribuidora De Juguetes S.l.",
    "wof:placetype":"venue"
},
  "geometry": {"coordinates":[2.1439380646,41.3707580566],"type":"Point"}
}