{
  "type": "Feature",
  "properties": {
    "iso:country":"ES",
    "sg:address":"Rbla Catalunya, 38",
    "sg:city":"Barcelona",
    "sg:orig_category":"Agencias Y Asesores De Publicidad",
    "sg:phone":"+34 933 02 20 55",
    "sg:postcode":"08007",
    "sg:province":"Barcelona",
    "sg:website":"www.topofmind.es",
    "wof:name":"Top Of Mind S.a.",
    "wof:placetype":"venue"
},
  "geometry": {"coordinates":[2.165225029,41.3900871277],"type":"Point"}
}