{
  "type": "Feature",
  "properties": {
    "iso:country":"ES",
    "sg:address":"Centro Comercial Dendaraba, S/n",
    "sg:city":"Vitoria-gasteiz",
    "sg:orig_category":"Peluquer\u00cdas, Peluquer\u00cda Mixta",
    "sg:phone":"+34 945 14 76 53",
    "sg:postcode":"01004",
    "sg:province":"\u00c1lava",
    "wof:name":"Gestion Y Estilo S. A.",
    "wof:placetype":"venue"
},
  "geometry": {"coordinates":[-2.6670999527,42.8468704224],"type":"Point"}
}