{
  "type": "Feature",
  "properties": {
    "addr:full":"Carr Murillo, 19 Badalona Barcelona 08911",
    "addr:housenumber":"19",
    "addr:postcode":"08911",
    "addr:street":"Carr Murillo",
    "iso:country":"ES",
    "sg:address":"Carr Murillo, 19",
    "sg:city":"Badalona",
    "sg:orig_category":"Importaci\u00d3n",
    "sg:phone":"+34 933 89 92 39",
    "sg:postcode":"08911",
    "sg:province":"Barcelona",
    "wof:name":"Euroworld Trade Import S.l.",
    "wof:placetype":"venue"
},
  "geometry": {"coordinates":[2.2672441006,41.461730957],"type":"Point"}
}