{
  "type": "Feature",
  "properties": {
    "addr:full":"Calle de Huerto De Los Frailes, 1 Alcorisa Teruel 44550",
    "addr:housenumber":"1",
    "addr:postcode":"44550",
    "addr:street":"Calle De Huerto De Los Frailes",
    "iso:country":"ES",
    "sg:address":"Calle de Huerto De Los Frailes, 1",
    "sg:city":"Alcorisa",
    "sg:orig_category":"Electricidad: Instaladores",
    "sg:phone":"+34 978 88 33 80",
    "sg:postcode":"44550",
    "sg:province":"Teruel",
    "wof:name":"Hermanos Villanova Electricidad S.l.",
    "wof:placetype":"venue"
},
  "geometry": {"coordinates":[-0.3813740015,40.8936538696],"type":"Point"}
}