{
  "type": "Feature",
  "properties": {
    "iso:country":"ES",
    "sg:address":"Calle de Espronceda, 25",
    "sg:city":"Zaragoza",
    "sg:orig_category":"Estilistas Y Estudios De Estilo De Corte Y Confecci\u00d3n",
    "sg:phone":"+34 976 32 14 02",
    "sg:postcode":"50011",
    "sg:province":"Zaragoza",
    "wof:name":"Solsona Arce Emeterio",
    "wof:placetype":"venue"
},
  "geometry": {"coordinates":[-0.9232087731,41.6530952454],"type":"Point"}
}