{
  "type": "Feature",
  "properties": {
    "addr:full":"Pg Generalitat, 39 Vic Barcelona 08500",
    "addr:housenumber":"39",
    "addr:postcode":"08500",
    "addr:street":"Pg Generalitat",
    "iso:country":"ES",
    "sg:address":"Pg Generalitat, 39",
    "sg:city":"Vic",
    "sg:classifiers":[
        {
            "category":"Taxi",
            "type":"Transportation"
        }
    ],
    "sg:phone":"+34 938 85 50 00",
    "sg:postcode":"08500",
    "sg:province":"Barcelona",
    "wof:name":"Sindicato De Trabajadores Autonomos Del Taxi De Catalu\u00d1a.",
    "wof:placetype":"venue"
},
  "geometry": {"coordinates":[2.2531659603,41.9222450256],"type":"Point"}
}