{
  "type": "Feature",
  "properties": {
    "iso:country":"ES",
    "sg:address":"Calle de Utrilla, 3",
    "sg:city":"Alcala Real",
    "sg:orig_category":"Quincaller\u00cda (al Por Menor)",
    "sg:phone":"+34 953 58 00 13",
    "sg:postcode":"23680",
    "sg:province":"Ja\u00e9n",
    "wof:name":"Herrador Jimenez Jose Maria",
    "wof:placetype":"venue"
},
  "geometry": {"coordinates":[-3.9242830276,37.464641571],"type":"Point"}
}