{
  "type": "Feature",
  "properties": {
    "iso:country":"ES",
    "sg:address":"Calle de Mendarozabal, 13",
    "sg:city":"Mendaro",
    "sg:orig_category":"Supermercados Y Hipermercados",
    "sg:phone":"+34 943 75 60 65",
    "sg:postcode":"20850",
    "sg:province":"Guip\u00f9zcoa",
    "wof:name":"Leonor Barreras Portilla",
    "wof:placetype":"venue"
},
  "geometry": {"coordinates":[-2.3894090652,43.250831604],"type":"Point"}
}