{
  "type": "Feature",
  "properties": {
    "iso:country":"ES",
    "sg:address":"Calle de Belen, 40",
    "sg:city":"Aguilar De La Frontera",
    "sg:orig_category":"Producci\u00d3n, Venta De Productos De Agricultura Biol\u00d3gica",
    "sg:phone":"+34 957 66 00 85",
    "sg:postcode":"14920",
    "sg:province":"C\u00f3rdoba",
    "wof:name":"Galisteo Rios Francisco",
    "wof:placetype":"venue"
},
  "geometry": {"coordinates":[-4.6552495956,37.5213813782],"type":"Point"}
}