{
  "type": "Feature",
  "properties": {
    "addr:full":"Calle de Salobre\u00d1a, 78 Albolote Granada 18220",
    "addr:housenumber":"78",
    "addr:postcode":"18220",
    "addr:street":"Calle De Salobren\u0303A",
    "iso:country":"ES",
    "sg:address":"Calle de Salobre\u00d1a, 78",
    "sg:city":"Albolote",
    "sg:orig_category":"Maquinaria Y Herramientas Para Madera, Pvc, Aluminio Y Aperos (fabricaci\u00d3n, Comercio)",
    "sg:phone":"+34 958 46 75 74",
    "sg:postcode":"18220",
    "sg:province":"Granada",
    "sg:website":"www.ramirezcaballero.com",
    "wof:name":"Ramirez Y Caballero S.l.",
    "wof:placetype":"venue"
},
  "geometry": {"coordinates":[-3.6469590664,37.226940155],"type":"Point"}
}