{
  "type": "Feature",
  "properties": {
    "iso:country":"ES",
    "sg:address":"Calle de Padre Tena, 4",
    "sg:city":"Azuaga",
    "sg:orig_category":"Farmacias",
    "sg:phone":"+34 924 89 04 64",
    "sg:postcode":"06920",
    "sg:province":"Badajoz",
    "wof:name":"Gonzalez Palacios Manuel",
    "wof:placetype":"venue"
},
  "geometry": {"coordinates":[-5.6745109558,38.2605667114],"type":"Point"}
}