{
  "type": "Feature",
  "properties": {
    "iso:country":"ES",
    "sg:address":"Av Pau Claris, 40",
    "sg:city":"Martorell",
    "sg:orig_category":"Agentes, Concesionarios Y Sucursales De Veh\u00cdculos",
    "sg:phone":"+34 937 76 92 40",
    "sg:postcode":"08760",
    "sg:province":"Barcelona",
    "sg:website":"www.gruplesseps.com",
    "wof:name":"Martorell Motor S.a.",
    "wof:placetype":"venue"
},
  "geometry": {"coordinates":[1.920789957,41.4798774719],"type":"Point"}
}