{
  "type": "Feature",
  "properties": {
    "iso:country":"ES",
    "sg:address":"Calle de Virgen De La Fuencisla, 27",
    "sg:city":"Madrid",
    "sg:orig_category":"Tintes (fabricaci\u00d3n, Al Por Mayor)",
    "sg:phone":"+34 914 04 39 42",
    "sg:postcode":"28027",
    "sg:province":"Madrid",
    "wof:name":"Sobrino Garcia Matias",
    "wof:placetype":"venue"
},
  "geometry": {"coordinates":[-3.6493780613,40.4388313293],"type":"Point"}
}