{
  "type": "Feature",
  "properties": {
    "addr:full":"Rua Puerto Rico, 20 Vigo Pontevedra 36204",
    "addr:housenumber":"20",
    "addr:postcode":"36204",
    "addr:street":"Rua Puerto Rico",
    "iso:country":"ES",
    "sg:address":"Rua Puerto Rico, 20",
    "sg:city":"Vigo",
    "sg:orig_category":"Transportes Frigor\u00cdficos",
    "sg:phone":"+34 986 42 31 17",
    "sg:postcode":"36204",
    "sg:province":"Pontevedra",
    "wof:name":"Hilapesca S.l.",
    "wof:placetype":"venue"
},
  "geometry": {"coordinates":[-8.7168016434,42.2285385132],"type":"Point"}
}