{
  "type": "Feature",
  "properties": {
    "iso:country":"ES",
    "sg:address":"Cra. Cabrils, S/n",
    "sg:city":"Vilassar",
    "sg:orig_category":"Centros De Educaci\u00d3n Especial",
    "sg:phone":"+34 937 59 08 90",
    "sg:postcode":"08340",
    "sg:province":"Barcelona",
    "wof:name":"Escola El Mar",
    "wof:placetype":"venue"
},
  "geometry": {"coordinates":[2.3907299042,41.5019264221],"type":"Point"}
}