{
  "type": "Feature",
  "properties": {
    "addr:full":"Calle de Virgen Desamparados, 50 Mislata Valencia 46920",
    "addr:housenumber":"50",
    "addr:postcode":"46920",
    "addr:street":"Calle De Virgen Desamparados",
    "iso:country":"ES",
    "sg:address":"Calle de Virgen Desamparados, 50",
    "sg:city":"Mislata",
    "sg:orig_category":"Chapister\u00cda",
    "sg:phone":"+34 963 59 33 44",
    "sg:postcode":"46920",
    "sg:province":"Valencia",
    "wof:name":"Automoviles Hidalgo S.l.",
    "wof:placetype":"venue"
},
  "geometry": {"coordinates":[-0.4163036942,39.478477478],"type":"Point"}
}