{
  "type": "Feature",
  "properties": {
    "addr:full":"Calle de Santa Cecilia, 12 Mislata Valencia 46920",
    "addr:housenumber":"12",
    "addr:postcode":"46920",
    "addr:street":"Calle De Santa Cecilia",
    "iso:country":"ES",
    "sg:address":"Calle de Santa Cecilia, 12",
    "sg:city":"Mislata",
    "sg:orig_category":"Venta, Instalaci\u00d3n, Reparaci\u00d3n De Antenas Para Televisi\u00d3n",
    "sg:phone":"+34 963 83 24 90",
    "sg:postcode":"46920",
    "sg:province":"Valencia",
    "wof:name":"Cristobal Martinez Garcia Y Otros Cdad.",
    "wof:placetype":"venue"
},
  "geometry": {"coordinates":[-0.42098701,39.4719161987],"type":"Point"}
}