{
  "type": "Feature",
  "properties": {
    "iso:country":"ES",
    "sg:address":"Calle de San Agustin, 1",
    "sg:city":"Segovia",
    "sg:orig_category":"Abogados",
    "sg:phone":"+34 921 46 18 89",
    "sg:postcode":"40001",
    "sg:province":"Segovia",
    "wof:name":"Ruiz Charcos Agustin Eduardo",
    "wof:placetype":"venue"
},
  "geometry": {"coordinates":[-4.1192622185,40.9506835938],"type":"Point"}
}