{
  "type": "Feature",
  "properties": {
    "addr:full":"Cmno Estacion, 6 Matapozuelos Valladolid 47230",
    "addr:housenumber":"6",
    "addr:postcode":"47230",
    "addr:street":"Cmno Estacion",
    "iso:country":"ES",
    "sg:address":"Cmno Estacion, 6",
    "sg:city":"Matapozuelos",
    "sg:orig_category":"Empresas De Carpinter\u00cda",
    "sg:phone":"+34 983 83 26 45",
    "sg:postcode":"47230",
    "sg:province":"Valladolid",
    "wof:name":"Carpinteria Metalica Hnos. Martin Garnes S.l.",
    "wof:placetype":"venue"
},
  "geometry": {"coordinates":[-4.7892432213,41.4120254517],"type":"Point"}
}