{
  "type": "Feature",
  "properties": {
    "addr:full":"Pl Catalunya, 8 S. Andreu Barca Barcelona 08740",
    "addr:housenumber":"8",
    "addr:postcode":"08740",
    "addr:street":"Pl Catalunya;Andreu;Barcelona",
    "iso:country":"ES",
    "sg:address":"Pl Catalunya, 8",
    "sg:city":"S. Andreu Barca",
    "sg:orig_category":"Fisioterapia",
    "sg:phone":"+34 936 53 22 61",
    "sg:postcode":"08740",
    "sg:province":"Barcelona",
    "wof:name":"Fisiomed S.l.",
    "wof:placetype":"venue"
},
  "geometry": {"coordinates":[1.973369956,41.4486236572],"type":"Point"}
}