{
  "type": "Feature",
  "properties": {
    "iso:country":"ES",
    "sg:address":"Av Mistral, 14",
    "sg:city":"Barcelona",
    "sg:orig_category":"Pintura Y Barniz (al Por Menor)",
    "sg:phone":"+34 933 25 60 10",
    "sg:postcode":"08015",
    "sg:province":"Barcelona",
    "wof:name":"Subirats Forns Jose Enrique",
    "wof:placetype":"venue"
},
  "geometry": {"coordinates":[2.1585450172,41.3775444031],"type":"Point"}
}