{
  "type": "Feature",
  "properties": {
    "iso:country":"ES",
    "sg:address":"Calle de Petunias, 4",
    "sg:city":"Coru\u00d1a",
    "sg:orig_category":"Iglesia Cat\u00d3lica",
    "sg:phone":"+34 981 28 66 01",
    "sg:postcode":"15008",
    "sg:province":"La Coru\u00f1a",
    "wof:name":"Parroquia Resurreccion Del Se\u00f1or",
    "wof:placetype":"venue"
},
  "geometry": {"coordinates":[-8.4005594254,43.3429908752],"type":"Point"}
}