{
  "type": "Feature",
  "properties": {
    "iso:country":"ES",
    "sg:address":"Calle de Naranja, 15",
    "sg:city":"Ronda",
    "sg:orig_category":"M\u00c1quinas De Coser Y De Hacer Punto (al Por Mayor)",
    "sg:phone":"+34 952 87 14 88",
    "sg:postcode":"29400",
    "sg:province":"M\u00e1laga",
    "wof:name":"Alfa Andalucia S. A.",
    "wof:placetype":"venue"
},
  "geometry": {"coordinates":[-5.164270401,36.744102478],"type":"Point"}
}