{
  "type": "Feature",
  "properties": {
    "iso:country":"ES",
    "sg:address":"Calle de Santa Maria, 6",
    "sg:city":"Aldeanueva Vera",
    "sg:orig_category":"Empresas De Pintura Y Revestimientos",
    "sg:phone":"+34 927 57 20 35",
    "sg:postcode":"10440",
    "sg:province":"C\u00e1ceres",
    "wof:name":"Perez Torralvo Pedro",
    "wof:placetype":"venue"
},
  "geometry": {"coordinates":[-5.7013468742,40.1262168884],"type":"Point"}
}