{
  "type": "Feature",
  "properties": {
    "addr:full":"Ciudad Rodrigo-carretera De, S/n Perales Del Puerto C\u00e1ceres 10896",
    "addr:housenumber":"s",
    "addr:postcode":"10896",
    "addr:street":"/ N Perales Del Puerto Ca\u0301Ceres",
    "iso:country":"ES",
    "sg:address":"Ciudad Rodrigo-carretera De, S/n",
    "sg:city":"Perales Del Puerto",
    "sg:orig_category":"Distribuci\u00d3n De Petr\u00d3leo Y Derivados",
    "sg:phone":"+34 927 19 30 62",
    "sg:postcode":"10896",
    "sg:province":"C\u00e1ceres",
    "wof:name":"La Fatela S.l.",
    "wof:placetype":"venue"
},
  "geometry": {"coordinates":[-6.6807842255,40.1543197632],"type":"Point"}
}