{
  "type": "Feature",
  "properties": {
    "addr:full":"Pg Vilafranca, 20 Sitges Barcelona 08870",
    "addr:housenumber":"20",
    "addr:postcode":"08870",
    "addr:street":"Pg Vilafranca",
    "iso:country":"ES",
    "sg:address":"Pg Vilafranca, 20",
    "sg:city":"Sitges",
    "sg:orig_category":"Muebles, Minoristas",
    "sg:phone":"+34 938 94 38 91",
    "sg:postcode":"08870",
    "sg:province":"Barcelona",
    "wof:name":"Perez Sanz Antonio",
    "wof:placetype":"venue"
},
  "geometry": {"coordinates":[1.8050899506,41.2452964783],"type":"Point"}
}