{
  "type": "Feature",
  "properties": {
    "iso:country":"ES",
    "sg:address":"Vilouchada, S/n",
    "sg:city":"Vilouchada",
    "sg:orig_category":"Asociaciones Y Clubs Deportivos",
    "sg:phone":"+34 981 19 85 87",
    "sg:postcode":"15687",
    "sg:province":"A Coru\u00f1a",
    "wof:name":"Sociedad Deportiva Riosar S.l.",
    "wof:placetype":"venue"
},
  "geometry": {"coordinates":[-8.5195789337,43.0256118774],"type":"Point"}
}