{
  "type": "Feature",
  "properties": {
    "addr:full":"Carrer de Consell De Cent, 352 Barcelona Barcelona 08009",
    "addr:housenumber":"352",
    "addr:postcode":"08009",
    "addr:street":"Carrer De Consell De Cent",
    "iso:country":"ES",
    "sg:address":"Carrer de Consell De Cent, 352",
    "sg:city":"Barcelona",
    "sg:orig_category":"Asesor\u00cda Sobre Comunicaci\u00d3n De Empresas",
    "sg:phone":"+34 932 15 70 72",
    "sg:postcode":"08009",
    "sg:province":"Barcelona",
    "wof:name":"Gabinet D'assessorament I Gestio S.c.c.l.",
    "wof:placetype":"venue"
},
  "geometry": {"coordinates":[2.1694910526,41.3937606812],"type":"Point"}
}