{
  "type": "Feature",
  "properties": {
    "iso:country":"ES",
    "sg:address":"Jesus, S/n",
    "sg:city":"Bujalance",
    "sg:orig_category":"Aceites Y Grasas Alimentarias (fabricaci\u00d3n, Al Por Mayor)",
    "sg:phone":"+34 957 17 01 22",
    "sg:postcode":"14650",
    "sg:province":"C\u00f3rdoba",
    "wof:name":"Francisco Javier Moreda Moreno Y Otros C.b",
    "wof:placetype":"venue"
},
  "geometry": {"coordinates":[-4.3768529892,37.8964309692],"type":"Point"}
}