{
  "type": "Feature",
  "properties": {
    "addr:full":"Rbla S Ferran, 22 Igualada Barcelona 08700",
    "addr:housenumber":"22",
    "addr:postcode":"08700",
    "addr:street":"Rbla S Ferran",
    "iso:country":"ES",
    "sg:address":"Rbla S Ferran, 22",
    "sg:city":"Igualada",
    "sg:orig_category":"Peluquer\u00cdas, Peluquer\u00cda Mixta",
    "sg:phone":"+34 938 03 55 04",
    "sg:postcode":"08700",
    "sg:province":"Barcelona",
    "wof:name":"Peluqueria Carmen Mansilla S.l.",
    "wof:placetype":"venue"
},
  "geometry": {"coordinates":[1.6170699596,41.5795402527],"type":"Point"}
}