{
  "type": "Feature",
  "properties": {
    "iso:country":"ES",
    "sg:address":"Calle de Canoniga, 11",
    "sg:city":"Arrabal De Portillo",
    "sg:orig_category":"Alfarer\u00cda",
    "sg:phone":"+34 983 55 62 91",
    "sg:postcode":"47160",
    "sg:province":"Valladolid",
    "wof:name":"Laguna Plaza Juan Manuel",
    "wof:placetype":"venue"
},
  "geometry": {"coordinates":[-4.5910611153,41.4718284607],"type":"Point"}
}