{
  "type": "Feature",
  "properties": {
    "iso:country":"ES",
    "sg:address":"Calle de Kasune, 12 A",
    "sg:city":"Getxo",
    "sg:orig_category":"Peluquer\u00cdas, Peluquer\u00cda Mixta",
    "sg:phone":"+34 944 30 56 96",
    "sg:postcode":"48990",
    "sg:province":"Vizcaya",
    "wof:name":"Nuria Ibeas Diez",
    "wof:placetype":"venue"
},
  "geometry": {"coordinates":[-3.0094540119,43.3488540649],"type":"Point"}
}