{
  "type": "Feature",
  "properties": {
    "iso:country":"ES",
    "sg:address":"Calle de Illeta, 10",
    "sg:city":"Getxo",
    "sg:orig_category":"Muebles Y Accesorios Para Cocinas Y Cuartos De Ba\u00d1o (al Por Menor)",
    "sg:phone":"+34 944 30 06 77",
    "sg:postcode":"48990",
    "sg:province":"Vizcaya",
    "wof:name":"Bego\u00f1a Sanchez Alonso (cocinas Illetas)",
    "wof:placetype":"venue"
},
  "geometry": {"coordinates":[-3.0089840889,43.3535690308],"type":"Point"}
}