{
  "type": "Feature",
  "properties": {
    "iso:country":"ES",
    "sg:address":"Calle de Jose De Juan, 65",
    "sg:city":"Guadalajara",
    "sg:orig_category":"Periodistas Profesionales",
    "sg:phone":"+34 949 24 78 31",
    "sg:postcode":"19004",
    "sg:province":"Guadalajara",
    "wof:name":"Grandes Pascual Lorenzo De",
    "wof:placetype":"venue"
},
  "geometry": {"coordinates":[-3.1792180538,40.6415748596],"type":"Point"}
}