{
  "type": "Feature",
  "properties": {
    "iso:country":"ES",
    "sg:address":"Calle de Fragua, 5",
    "sg:city":"Viso S. Juan",
    "sg:orig_category":"Promotores Constructores",
    "sg:phone":"+34 925 55 97 25",
    "sg:postcode":"45215",
    "sg:province":"Toledo",
    "wof:name":"Inmocasa Calvo Y Postigo S.l.",
    "wof:placetype":"venue"
},
  "geometry": {"coordinates":[-3.919023037,40.1430664062],"type":"Point"}
}