{
  "type": "Feature",
  "properties": {
    "iso:country":"ES",
    "sg:address":"Rua Paz, S/n",
    "sg:city":"Vilar",
    "sg:orig_category":"Bibliotecas, Mediatecas",
    "sg:phone":"+34 981 66 42 57",
    "sg:postcode":"15176",
    "sg:province":"La Coru\u00f1a",
    "wof:name":"Fundacion Municipal De Cultura De Oleiros",
    "wof:placetype":"venue"
},
  "geometry": {"coordinates":[-8.3443689346,43.3194007874],"type":"Point"}
}