{
  "type": "Feature",
  "properties": {
    "iso:country":"ES",
    "sg:address":"Avda Habana, 20",
    "sg:city":"Pontes Garcia Rodriguez",
    "sg:orig_category":"Laboratorios Y Trabajos De Fotograf\u00cda, V\u00cddeo Y Cine",
    "sg:phone":"+34 981 44 01 48",
    "sg:postcode":"15320",
    "sg:province":"A Coru\u00f1a",
    "wof:name":"Vila Perez Santiago",
    "wof:placetype":"venue"
},
  "geometry": {"coordinates":[-7.8516669273,43.4477882385],"type":"Point"}
}