{
  "type": "Feature",
  "properties": {
    "iso:country":"ES",
    "sg:address":"Calle de Bernat Artola, 9",
    "sg:city":"Castellon",
    "sg:orig_category":"Carnicer\u00cdas, Carnicer\u00cdas",
    "sg:phone":"+34 964 22 99 20",
    "sg:postcode":"12004",
    "sg:province":"Castell\u00f3n",
    "wof:name":"Alejandro Pons Manuel",
    "wof:placetype":"venue"
},
  "geometry": {"coordinates":[-0.0356917009,39.9939079285],"type":"Point"}
}