{
  "type": "Feature",
  "properties": {
    "iso:country":"ES",
    "sg:address":"Carrer de Sant Pere Mes Baix, 49",
    "sg:city":"Barcelona",
    "sg:orig_category":"Ropa Para Se\u00d1oras (al Por Menor)",
    "sg:phone":"+34 933 15 12 05",
    "sg:postcode":"08003",
    "sg:province":"Barcelona",
    "wof:name":"Chen  Qiong Ruo",
    "wof:placetype":"venue"
},
  "geometry": {"coordinates":[2.178057909,41.3879890442],"type":"Point"}
}