{
  "type": "Feature",
  "properties": {
    "addr:full":"Carrer de Muntaner, 242 Barcelona Barcelona 08021",
    "addr:housenumber":"242",
    "addr:postcode":"08021",
    "addr:street":"Carrer De Muntaner",
    "iso:country":"ES",
    "sg:address":"Carrer de Muntaner, 242",
    "sg:city":"Barcelona",
    "sg:orig_category":"Centros De Reservas Hoteleras",
    "sg:phone":"+34 934 14 63 62",
    "sg:postcode":"08021",
    "sg:province":"Barcelona",
    "sg:website":"www.costa-este.com",
    "wof:name":"Ocio Management S.l.",
    "wof:placetype":"venue"
},
  "geometry": {"coordinates":[2.1488759518,41.3948020935],"type":"Point"}
}