{
  "type": "Feature",
  "properties": {
    "iso:country":"ES",
    "sg:address":"Carrer de Camil Fabra, 2",
    "sg:city":"Barcelona",
    "sg:orig_category":"Inform\u00c1tica: Consultores",
    "sg:phone":"+34 932 74 14 53",
    "sg:postcode":"08030",
    "sg:province":"Barcelona",
    "wof:name":"Eskpe Consulting S.l.",
    "wof:placetype":"venue"
},
  "geometry": {"coordinates":[2.1869289875,41.4298934937],"type":"Point"}
}