{
  "type": "Feature",
  "properties": {
    "addr:full":"Calle de Ibarra, 10 Gernika-lumo Vizcaya 48300",
    "addr:housenumber":"10",
    "addr:postcode":"48300",
    "addr:street":"Calle De Ibarra",
    "iso:country":"ES",
    "sg:address":"Calle de Ibarra, 10",
    "sg:city":"Gernika-lumo",
    "sg:orig_category":"Mec\u00c1nico Del Autom\u00d3vil",
    "sg:phone":"+34 946 25 38 01",
    "sg:postcode":"48300",
    "sg:province":"Vizcaya",
    "wof:name":"Basterrechea Martinez Jose Manuel",
    "wof:placetype":"venue"
},
  "geometry": {"coordinates":[-2.6765379906,43.3092689514],"type":"Point"}
}