{
  "type": "Feature",
  "properties": {
    "iso:country":"ES",
    "sg:address":"Calle de Cervantes, 4",
    "sg:city":"Merida",
    "sg:orig_category":"Abogados",
    "sg:phone":"+34 924 33 06 07",
    "sg:postcode":"06800",
    "sg:province":"Badajoz",
    "wof:name":"Aparicio Gonzalez Juan Jose",
    "wof:placetype":"venue"
},
  "geometry": {"coordinates":[-6.385225296,38.8869476318],"type":"Point"}
}