{
  "type": "Feature",
  "properties": {
    "iso:country":"ES",
    "sg:address":"Calle de Hortaleza, 6",
    "sg:city":"Vitoria-gasteiz",
    "sg:orig_category":"Ropa De Trabajo Y Profesionales (fabricaci\u00d3n, Al Por Mayor)",
    "sg:phone":"+34 945 12 00 05",
    "sg:postcode":"01002",
    "sg:province":"\u00c1lava",
    "wof:name":"Silabor Proteccion, S.l.",
    "wof:placetype":"venue"
},
  "geometry": {"coordinates":[-2.6647539139,42.8521614075],"type":"Point"}
}