{
  "type": "Feature",
  "properties": {
    "iso:country":"ES",
    "sg:address":"Avda Espa\u00d1a (de), 114",
    "sg:city":"Dos Hermanas",
    "sg:orig_category":"Institutos De Belleza",
    "sg:phone":"+34 955 66 88 62",
    "sg:postcode":"41700",
    "sg:province":"Sevilla",
    "wof:name":"Perez Benitez Ana Maria",
    "wof:placetype":"venue"
},
  "geometry": {"coordinates":[-5.9154877663,37.2869186401],"type":"Point"}
}