{
  "type": "Feature",
  "properties": {
    "addr:full":"Carrer de Antoni Torrella, 39 Terrassa Barcelona 08224",
    "addr:housenumber":"39",
    "addr:postcode":"08224",
    "addr:street":"Carrer De Antoni Torrella",
    "iso:country":"ES",
    "sg:address":"Carrer de Antoni Torrella, 39",
    "sg:city":"Terrassa",
    "sg:orig_category":"Asesor\u00cda Sobre Comunicaci\u00d3n De Empresas",
    "sg:phone":"+34 937 88 11 38",
    "sg:postcode":"08224",
    "sg:province":"Barcelona",
    "wof:name":"Folch Vila Jose",
    "wof:placetype":"venue"
},
  "geometry": {"coordinates":[2.005753994,41.5611763],"type":"Point"}
}