{
  "type": "Feature",
  "properties": {
    "addr:full":"Calle de Lepe, 1 Cartaya Huelva 21450",
    "addr:housenumber":"1",
    "addr:postcode":"21450",
    "addr:street":"Calle De Lepe",
    "iso:country":"ES",
    "sg:address":"Calle de Lepe, 1",
    "sg:city":"Cartaya",
    "sg:orig_category":"Molduras, Junquillos, Listones Y Molduras Perforadas",
    "sg:phone":"+34 959 39 15 67",
    "sg:postcode":"21450",
    "sg:province":"Huelva",
    "wof:name":"Escudero Maestre Maria Dolores",
    "wof:placetype":"venue"
},
  "geometry": {"coordinates":[-7.1528987885,37.2844581604],"type":"Point"}
}