{
  "type": "Feature",
  "properties": {
    "addr:full":"Calle de Cadiz, 10 Santander Cantabria 39002",
    "addr:housenumber":"10",
    "addr:postcode":"39002",
    "addr:street":"Calle De Cadiz",
    "iso:country":"ES",
    "sg:address":"Calle de Cadiz, 10",
    "sg:city":"Santander",
    "sg:orig_category":"Asesor\u00cda Sobre Comunicaci\u00d3n De Empresas",
    "sg:phone":"+34 942 36 70 70",
    "sg:postcode":"39002",
    "sg:province":"Cantabria",
    "wof:name":"E P V Norte Asesores Consultores S.a.l.",
    "wof:placetype":"venue"
},
  "geometry": {"coordinates":[-3.8082487583,43.4600486755],"type":"Point"}
}