{
  "type": "Feature",
  "properties": {
    "iso:country":"ES",
    "sg:address":"Calle de Marques Del Riscal, 9",
    "sg:city":"Madrid",
    "sg:orig_category":"Tapiceros Y Tapiceros",
    "sg:phone":"+34 913 08 25 53",
    "sg:postcode":"28010",
    "sg:province":"Madrid",
    "wof:name":"Parlade Ybarra Maria",
    "wof:placetype":"venue"
},
  "geometry": {"coordinates":[-3.6910030842,40.4307250977],"type":"Point"}
}