{
  "type": "Feature",
  "properties": {
    "addr:full":"Calle de Pilares, 4 Elda Alicante 03600",
    "addr:housenumber":"4",
    "addr:postcode":"03600",
    "addr:street":"Calle De Pilares",
    "iso:country":"ES",
    "sg:address":"Calle de Pilares, 4",
    "sg:city":"Elda",
    "sg:orig_category":"Partidos Pol\u00cdticos",
    "sg:phone":"+34 966 98 01 95",
    "sg:postcode":"03600",
    "sg:province":"Alicante",
    "wof:name":"Izquierda Unida Del Pais Valenciano",
    "wof:placetype":"venue"
},
  "geometry": {"coordinates":[-0.7960919738,38.4810028076],"type":"Point"}
}