{
  "type": "Feature",
  "properties": {
    "addr:full":"Avda Nuestra Se\u00d1ora De Montserrat, 151 Almeria Almer\u00eda 04006",
    "addr:housenumber":"151",
    "addr:postcode":"04006",
    "addr:street":"Avda Nuestra Sen\u0303Ora De Montserrat",
    "iso:country":"ES",
    "sg:address":"Avda Nuestra Se\u00d1ora De Montserrat, 151",
    "sg:city":"Almeria",
    "sg:orig_category":"Transporte En General",
    "sg:phone":"+34 950 22 55 69",
    "sg:postcode":"04006",
    "sg:province":"Almer\u00eda",
    "wof:name":"Tegarsa S.c.",
    "wof:placetype":"venue"
},
  "geometry": {"coordinates":[-2.444742918,36.8390274048],"type":"Point"}
}