{
  "type": "Feature",
  "properties": {
    "addr:full":"Calle de Seron, 29 Logro\u00f1o La Rioja 26006",
    "addr:housenumber":"29",
    "addr:postcode":"26006",
    "addr:street":"Calle De Seron;Rioja",
    "iso:country":"ES",
    "sg:address":"Calle de Seron, 29",
    "sg:city":"Logro\u00f1o",
    "sg:orig_category":"Empresas De Operaciones Portuarias Y Elevaci\u00d3n De Mercanc\u00cdas",
    "sg:phone":"+34 941 23 22 59",
    "sg:postcode":"26006",
    "sg:province":"La Rioja",
    "wof:name":"Mifir S.l.",
    "wof:placetype":"venue"
},
  "geometry": {"coordinates":[-2.4083240032,42.4569587708],"type":"Point"}
}