{
  "type": "Feature",
  "properties": {
    "addr:full":"Calle de Doce De Octubre, 1 Cordoba C\u00f3rdoba 14001",
    "addr:housenumber":"1",
    "addr:postcode":"14001",
    "addr:street":"Calle De Doce De Octubre;Co\u0301Rdoba",
    "iso:country":"ES",
    "sg:address":"Calle de Doce De Octubre, 1",
    "sg:city":"Cordoba",
    "sg:orig_category":"Abogados",
    "sg:phone":"+34 957 49 03 01",
    "sg:postcode":"14001",
    "sg:province":"C\u00f3rdoba",
    "wof:name":"Jurado Luque Bartolome",
    "wof:placetype":"venue"
},
  "geometry": {"coordinates":[-4.7808556557,37.8887214661],"type":"Point"}
}