{
  "type": "Feature",
  "properties": {
    "iso:country":"ES",
    "sg:address":"Ctra Provincial, S/n",
    "sg:city":"Raviso",
    "sg:orig_category":"Promotores Constructores",
    "sg:phone":"+34 986 47 06 25",
    "sg:postcode":"36214",
    "sg:province":"Pontevedra",
    "wof:name":"Atlantico Construcciones Y Promociones S.l.",
    "wof:placetype":"venue"
},
  "geometry": {"coordinates":[-8.6480531693,42.4336204529],"type":"Point"}
}