{
  "type": "Feature",
  "properties": {
    "iso:country":"ES",
    "sg:address":"Calle de Electrodo (del), S/n",
    "sg:city":"Partija-santa Monica",
    "sg:orig_category":"Bancos",
    "sg:phone":"+34 914 99 05 72",
    "sg:postcode":"28529",
    "sg:province":"Madrid",
    "sg:website":"www.bancodegalicia.es",
    "wof:name":"Banco De Galicia",
    "wof:placetype":"venue"
},
  "geometry": {"coordinates":[-3.5102670193,40.314289093],"type":"Point"}
}