{
  "type": "Feature",
  "properties": {
    "addr:full":"Calle de San Isidro, 48 Alcanadre La Rioja 26509",
    "addr:housenumber":"48",
    "addr:postcode":"26509",
    "addr:street":"Calle De San Isidro;Alcanadre;Rioja",
    "iso:country":"ES",
    "sg:address":"Calle de San Isidro, 48",
    "sg:city":"Alcanadre",
    "sg:orig_category":"Productores Recolectores, Venta Directa De Vinos",
    "sg:phone":"+34 941 16 52 89",
    "sg:postcode":"26509",
    "sg:province":"La Rioja",
    "wof:name":"Cooperativa Vinicola San Roque",
    "wof:placetype":"venue"
},
  "geometry": {"coordinates":[-2.1238889694,42.4030685425],"type":"Point"}
}