{
  "type": "Feature",
  "properties": {
    "iso:country":"ES",
    "sg:address":"Calle de Holguin, 2",
    "sg:city":"Merida",
    "sg:orig_category":"Arqueolog\u00cda Y Patrimonio Cultural",
    "sg:phone":"+34 924 31 55 10",
    "sg:postcode":"06800",
    "sg:province":"Badajoz",
    "wof:name":"Tera S.%",
    "wof:placetype":"venue"
},
  "geometry": {"coordinates":[-6.34897089,38.9176940918],"type":"Point"}
}