{
  "type": "Feature",
  "properties": {
    "addr:full":"Cementerio Camin., S/n Roales Zamora 49192",
    "addr:housenumber":"s",
    "addr:postcode":"49192",
    "addr:street":"/ N Roales Zamora",
    "iso:country":"ES",
    "sg:address":"Cementerio Camin., S/n",
    "sg:city":"Roales",
    "sg:orig_category":"Sales (al Por Mayor)",
    "sg:phone":"+34 980 53 87 94",
    "sg:postcode":"49192",
    "sg:province":"Zamora",
    "wof:name":"Comercial Oblanca S. A.",
    "wof:placetype":"venue"
},
  "geometry": {"coordinates":[-5.8029990196,41.550819397],"type":"Point"}
}