{
  "type": "Feature",
  "properties": {
    "iso:country":"ES",
    "sg:address":"Avda Escaleritas, 49",
    "sg:city":"Palmas De Gran Canaria",
    "sg:orig_category":"Asociaciones Y Clubs Deportivos",
    "sg:phone":"+34 928 25 59 47",
    "sg:postcode":"35011",
    "sg:province":"Las Palmas",
    "wof:name":"Sepulveda Y Barrios S.l.",
    "wof:placetype":"venue"
},
  "geometry": {"coordinates":[-15.4363908768,28.1211662292],"type":"Point"}
}