{
  "type": "Feature",
  "properties": {
    "iso:country":"ES",
    "sg:address":"Arantzazuko Amaren Auzoa, 20",
    "sg:city":"Legazpi",
    "sg:orig_category":"Sindicatos De Trabajadores",
    "sg:phone":"+34 943 73 30 30",
    "sg:postcode":"20230",
    "sg:province":"Guip\u00f9zcoa",
    "wof:name":"Union Sindical Obrera",
    "wof:placetype":"venue"
},
  "geometry": {"coordinates":[-2.334485054,43.0562782288],"type":"Point"}
}