{
  "type": "Feature",
  "properties": {
    "iso:country":"ES",
    "sg:address":"Leon-astorga, Km. 0004,0",
    "sg:city":"Trobajo Camino",
    "sg:orig_category":"Librer\u00cdas",
    "sg:phone":"+34 987 80 71 11",
    "sg:postcode":"24010",
    "sg:province":"Le\u00f3n",
    "wof:name":"Yague Vizcaino Javier",
    "wof:placetype":"venue"
},
  "geometry": {"coordinates":[-5.5818753242,42.5960502625],"type":"Point"}
}