{
  "type": "Feature",
  "properties": {
    "iso:country":"ES",
    "sg:address":"Calle de Bordadoras, 27",
    "sg:city":"Dos Hermanas",
    "sg:orig_category":"Confecci\u00d3n (fabricaci\u00d3n, Al Por Mayor)",
    "sg:phone":"+34 955 66 13 04",
    "sg:postcode":"41700",
    "sg:province":"Sevilla",
    "wof:name":"Cristobal Cristobal Julio",
    "wof:placetype":"venue"
},
  "geometry": {"coordinates":[-5.9260315895,37.2720413208],"type":"Point"}
}