{
  "type": "Feature",
  "properties": {
    "addr:full":"Calle de Conde De Altea, 52 Altea Alicante 03590",
    "addr:housenumber":"52",
    "addr:postcode":"03590",
    "addr:street":"Calle De Conde De Altea",
    "iso:country":"ES",
    "sg:address":"Calle de Conde De Altea, 52",
    "sg:city":"Altea",
    "sg:orig_category":"Asesor\u00cda Sobre Comunicaci\u00d3n De Empresas",
    "sg:phone":"+34 902 42 09 20",
    "sg:postcode":"03590",
    "sg:province":"Alicante",
    "sg:website":"www.sociedadeslimitadas.com",
    "wof:name":"Global Premium S.l.",
    "wof:placetype":"venue"
},
  "geometry": {"coordinates":[-0.0458513983,38.6021347046],"type":"Point"}
}