{
  "type": "Feature",
  "properties": {
    "addr:full":"Jdin Zabalarreta Lorategiak, 2 San Blas Guip\u00f9zcoa 20400",
    "addr:housenumber":"2",
    "addr:postcode":"20400",
    "addr:street":"Lorategiak",
    "iso:country":"ES",
    "sg:address":"Jdin Zabalarreta Lorategiak, 2",
    "sg:city":"San Blas",
    "sg:orig_category":"Bares, Piano",
    "sg:phone":"+34 943 67 13 28",
    "sg:postcode":"20400",
    "sg:province":"Guip\u00f9zcoa",
    "wof:name":"Aldalur Emanalde Maria Izaskun",
    "wof:placetype":"venue"
},
  "geometry": {"coordinates":[-2.0789339542,43.1339912415],"type":"Point"}
}