{
  "type": "Feature",
  "properties": {
    "addr:full":"Calle de Vicente Espinel, 22 Madrid Madrid 28017",
    "addr:housenumber":"22",
    "addr:postcode":"madrid;28017",
    "addr:street":"Calle De Vicente Espinel",
    "iso:country":"ES",
    "sg:address":"Calle de Vicente Espinel, 22",
    "sg:city":"Madrid",
    "sg:orig_category":"Peluqueros: De Se\u00d1oras",
    "sg:phone":"+34 914 08 11 06",
    "sg:postcode":"28017",
    "sg:province":"Madrid",
    "wof:name":"Gomez Bellido Sara",
    "wof:placetype":"venue"
},
  "geometry": {"coordinates":[-3.6412398815,40.4338760376],"type":"Point"}
}