{
  "type": "Feature",
  "properties": {
    "addr:full":"Can Cabanyes (pol Calle de Gordi), 59 Granollers Barcelona 08403",
    "addr:housenumber":"59",
    "addr:postcode":"08403",
    "addr:street":"Calle De Gordi",
    "iso:country":"ES",
    "sg:address":"Can Cabanyes (pol Calle de Gordi), 59",
    "sg:city":"Granollers",
    "sg:orig_category":"Laminadoras",
    "sg:phone":"+34 935 68 90 26",
    "sg:postcode":"08403",
    "sg:province":"Barcelona",
    "wof:name":"Abet Laminati S.a.",
    "wof:placetype":"venue"
},
  "geometry": {"coordinates":[2.266116,41.569744],"type":"Point"}
}