{
  "type": "Feature",
  "properties": {
    "iso:country":"ES",
    "sg:address":"Avda General Lopez Dominguez, 23",
    "sg:city":"Marbella",
    "sg:orig_category":"\u00d3ptica: Instrumentos (fabricaci\u00d3n)",
    "sg:phone":"+34 952 82 99 03",
    "sg:postcode":"29600",
    "sg:province":"M\u00e1laga",
    "wof:name":"Centro Optico Santamera De Los Rios S.cv.",
    "wof:placetype":"venue"
},
  "geometry": {"coordinates":[-4.8770809174,36.5142402649],"type":"Point"}
}