{
  "type": "Feature",
  "properties": {
    "iso:country":"ES",
    "sg:address":"Pazos, 7",
    "sg:city":"San Cremenzo De Pazos",
    "sg:orig_category":"Iglesia Cat\u00d3lica",
    "sg:phone":"+34 981 71 83 57",
    "sg:postcode":"15150",
    "sg:province":"La Coru\u00f1a",
    "wof:name":"Arzobispado De Santiago",
    "wof:placetype":"venue"
},
  "geometry": {"coordinates":[-8.904209137,43.1474075317],"type":"Point"}
}