{
  "type": "Feature",
  "properties": {
    "iso:country":"ES",
    "sg:address":"Calle de Concha (de La), 38",
    "sg:city":"Aranjuez",
    "sg:classifiers":[
        {
            "category":"Autos & Motor Vehicles",
            "subcategory":"Automobile Sales",
            "type":"Retail Goods"
        }
    ],
    "sg:phone":"+34 918 91 39 38",
    "sg:postcode":"28300",
    "sg:province":"Madrid",
    "wof:name":"Turbo Trafic S.l.",
    "wof:placetype":"venue"
},
  "geometry": {"coordinates":[-3.6012420654,40.0304450989],"type":"Point"}
}