{
  "type": "Feature",
  "properties": {
    "iso:country":"ES",
    "sg:address":"Carrer de Echegaray, 31",
    "sg:city":"Rubi",
    "sg:orig_category":"Ense\u00d1anza: Profesiones Art\u00cdsticas",
    "sg:phone":"+34 935 87 12 38",
    "sg:postcode":"08191",
    "sg:province":"Barcelona",
    "wof:name":"Hernandez Galindo Fernando",
    "wof:placetype":"venue"
},
  "geometry": {"coordinates":[1.9982969761,41.537311554],"type":"Point"}
}