{
  "type": "Feature",
  "properties": {
    "addr:full":"Ctra Bordeta, 39 Barcelona Barcelona 08014",
    "addr:housenumber":"39",
    "addr:postcode":"08014",
    "addr:street":"Ctra Bordeta",
    "iso:country":"ES",
    "sg:address":"Ctra Bordeta, 39",
    "sg:city":"Barcelona",
    "sg:orig_category":"Ense\u00d1anza Secundaria: Colegios Y Escuelas Privadas",
    "sg:phone":"+34 934 24 19 01",
    "sg:postcode":"08014",
    "sg:province":"Barcelona",
    "wof:name":"Institut De Batxillerat Joan Coromines",
    "wof:placetype":"venue"
},
  "geometry": {"coordinates":[2.144464016,41.3731613159],"type":"Point"}
}