{
  "type": "Feature",
  "properties": {
    "addr:full":"Carrer de Alfons Iv, 84 Granollers Barcelona 08401",
    "addr:housenumber":"84",
    "addr:postcode":"08401",
    "addr:street":"Carrer De Alfons Iv",
    "iso:country":"ES",
    "sg:address":"Carrer de Alfons Iv, 84",
    "sg:city":"Granollers",
    "sg:orig_category":"Reparaci\u00d3n, Mantenimiento De Instrumentos Y Accesorios De M\u00dasica",
    "sg:phone":"+34 938 70 86 55",
    "sg:postcode":"08401",
    "sg:province":"Barcelona",
    "wof:name":"Adagio S.a.",
    "wof:placetype":"venue"
},
  "geometry": {"coordinates":[2.2878565788,41.6034011841],"type":"Point"}
}