{
  "type": "Feature",
  "properties": {
    "addr:full":"Pl Parroquia, 2 Indioteria Islas Baleares 07009",
    "addr:housenumber":"2",
    "addr:postcode":"07009",
    "addr:street":"Parroquia;Islas",
    "iso:country":"ES",
    "sg:address":"Pl Parroquia, 2",
    "sg:city":"Indioteria",
    "sg:orig_category":"Internados & Ense\u00d1anza Privada",
    "sg:phone":"+34 971 29 47 62",
    "sg:postcode":"07009",
    "sg:province":"Islas Baleares",
    "wof:name":"Colegio Madres Agustinas",
    "wof:placetype":"venue"
},
  "geometry": {"coordinates":[2.6741399765,39.6011390686],"type":"Point"}
}