{
  "type": "Feature",
  "properties": {
    "iso:country":"ES",
    "sg:address":"Calle de Calzadas, 57",
    "sg:city":"Burgos",
    "sg:orig_category":"Transportes Por Carretera: Lotes Completos, Mercanc\u00cdas Diversas",
    "sg:phone":"+34 947 27 10 05",
    "sg:postcode":"09004",
    "sg:province":"Burgos",
    "wof:name":"Dos Hermanas S.c",
    "wof:placetype":"venue"
},
  "geometry": {"coordinates":[-3.6881256104,42.3449821472],"type":"Point"}
}