{
  "type": "Feature",
  "properties": {
    "addr:full":"Calle de Estrasburgo, 6 Sevilla Sevilla 41012",
    "addr:housenumber":"6",
    "addr:postcode":"41012",
    "addr:street":"Calle De Estrasburgo",
    "iso:country":"ES",
    "sg:address":"Calle de Estrasburgo, 6",
    "sg:city":"Sevilla",
    "sg:orig_category":"Arquitectos",
    "sg:phone":"+34 954 62 53 67",
    "sg:postcode":"41012",
    "sg:province":"Sevilla",
    "wof:name":"G.p.g.arquitectos.s.c.",
    "wof:placetype":"venue"
},
  "geometry": {"coordinates":[-5.9789156914,37.3462219238],"type":"Point"}
}