{
  "type": "Feature",
  "properties": {
    "addr:full":"Calle de Pablo Picasso (de), 1 San Fernando De Henares Madrid 28830",
    "addr:postcode":"28830",
    "addr:street":"Calle De Pablo Picasso De 1",
    "iso:country":"ES",
    "sg:address":"Calle de Pablo Picasso (de), 1",
    "sg:city":"San Fernando De Henares",
    "sg:orig_category":"Agentes Generales De Seguros",
    "sg:phone":"+34 916 69 38 72",
    "sg:postcode":"28830",
    "sg:province":"Madrid",
    "wof:name":"Morales Morales Fernando",
    "wof:placetype":"venue"
},
  "geometry": {"coordinates":[-3.5330369473,40.4261131287],"type":"Point"}
}