{
  "type": "Feature",
  "properties": {
    "iso:country":"ES",
    "sg:address":"Avda Huelva, S/n",
    "sg:city":"Espartinas",
    "sg:orig_category":"Abogados",
    "sg:phone":"+34 955 71 32 65",
    "sg:postcode":"41807",
    "sg:province":"Sevilla",
    "wof:name":"Urbanizacion Espartinilla S.a.",
    "wof:placetype":"venue"
},
  "geometry": {"coordinates":[-6.1256608963,37.3787536621],"type":"Point"}
}