{
  "type": "Feature",
  "properties": {
    "iso:country":"ES",
    "sg:address":"Emigrante, 6",
    "sg:city":"Olivenza",
    "sg:orig_category":"Art\u00cdculos De Regalo (al Por Menor)",
    "sg:phone":"+34 924 49 03 05",
    "sg:postcode":"06100",
    "sg:province":"Badajoz",
    "wof:name":"Jara Cabeza Antonia",
    "wof:placetype":"venue"
},
  "geometry": {"coordinates":[-7.0990099907,38.6805458069],"type":"Point"}
}