{
  "type": "Feature",
  "properties": {
    "addr:full":"Calle de Fray Luis De Leon, 29 Montijo Badajoz 06480",
    "addr:housenumber":"29",
    "addr:postcode":"06480",
    "addr:street":"Calle De Fray Luis De Leon",
    "iso:country":"ES",
    "sg:address":"Calle de Fray Luis De Leon, 29",
    "sg:city":"Montijo",
    "sg:orig_category":"Molduras, Junquillos, Listones Y Molduras Perforadas",
    "sg:phone":"+34 924 45 40 11",
    "sg:postcode":"06480",
    "sg:province":"Badajoz",
    "wof:name":"Tiklan S.a.l.",
    "wof:placetype":"venue"
},
  "geometry": {"coordinates":[-6.6200013161,38.9118270874],"type":"Point"}
}