{
  "type": "Feature",
  "properties": {
    "iso:country":"ES",
    "sg:address":"Carrer de Berlin, 34",
    "sg:city":"Barcelona",
    "sg:orig_category":"Cl\u00cdnicas Dentales",
    "sg:phone":"+34 934 39 35 99",
    "sg:postcode":"08014",
    "sg:province":"Barcelona",
    "wof:name":"Espa\u00f1a Tost Antonio Jesus",
    "wof:placetype":"venue"
},
  "geometry": {"coordinates":[2.1389000416,41.3830032349],"type":"Point"}
}