{
  "type": "Feature",
  "properties": {
    "addr:full":"Avda Dilar (de), 66 Granada Granada 18007",
    "addr:housenumber":"66",
    "addr:postcode":"18007",
    "addr:street":"Avda Dilar De",
    "iso:country":"ES",
    "sg:address":"Avda Dilar (de), 66",
    "sg:city":"Granada",
    "sg:orig_category":"Zapatos (al Por Menor)",
    "sg:phone":"+34 958 81 44 05",
    "sg:postcode":"18007",
    "sg:province":"Granada",
    "wof:name":"Ortega Rosillo Carmen",
    "wof:placetype":"venue"
},
  "geometry": {"coordinates":[-3.6005289555,37.1552696228],"type":"Point"}
}