{
  "type": "Feature",
  "properties": {
    "addr:full":"Carrer de Florida, 2 Abrera Barcelona 08630",
    "addr:housenumber":"2",
    "addr:postcode":"08630",
    "addr:street":"Carrer De Florida",
    "iso:country":"ES",
    "sg:address":"Carrer de Florida, 2",
    "sg:city":"Abrera",
    "sg:orig_category":"Bancos",
    "sg:phone":"+34 937 70 37 67",
    "sg:postcode":"08630",
    "sg:province":"Barcelona",
    "wof:name":"Banc Sabadell S.a.",
    "wof:placetype":"venue"
},
  "geometry": {"coordinates":[1.9028300047,41.5163497925],"type":"Point"}
}