{
  "type": "Feature",
  "properties": {
    "iso:country":"ES",
    "sg:address":"Ctra Barcelona, 100",
    "sg:city":"Centre Urba",
    "sg:orig_category":"Venta, Montaje De Neum\u00c1ticos",
    "sg:phone":"+34 972 71 57 40",
    "sg:postcode":"17500",
    "sg:province":"Girona",
    "sg:website":"www.autoequip.es",
    "wof:name":"Centres Autoequip S.a.",
    "wof:placetype":"venue"
},
  "geometry": {"coordinates":[2.1959049702,42.1965866089],"type":"Point"}
}