{
  "type": "Feature",
  "properties": {
    "iso:country":"ES",
    "sg:address":"Rua Flores (das), 9",
    "sg:city":"Burela",
    "sg:orig_category":"Coches Y Camiones (caja De Cambios, Embrague Y Frenos)",
    "sg:phone":"+34 982 58 60 50",
    "sg:postcode":"27880",
    "sg:province":"Lugo",
    "wof:name":"Frenos Carpe S.l.",
    "wof:placetype":"venue"
},
  "geometry": {"coordinates":[-7.3593831062,43.6593322754],"type":"Point"}
}