{
  "type": "Feature",
  "properties": {
    "iso:country":"ES",
    "sg:address":"Casta\u00f1ar, 5",
    "sg:city":"Bejar",
    "sg:orig_category":"Venta, Instalaci\u00d3n De Cocinas",
    "sg:phone":"+34 923 40 01 00",
    "sg:postcode":"37700",
    "sg:province":"Salamanca",
    "wof:name":"Mu\u00f1oz Rosell Fernando",
    "wof:placetype":"venue"
},
  "geometry": {"coordinates":[-5.7658338547,40.3824653625],"type":"Point"}
}