{
  "type": "Feature",
  "properties": {
    "addr:full":"Ctra N-iv Madrid-cadiz, Km. 0118,5 Madridejos Toledo 45710",
    "addr:postcode":"45710",
    "addr:street":"Ctra N-Iv Madrid-Cadiz Km. 0118,5",
    "iso:country":"ES",
    "sg:address":"Ctra N-iv Madrid-cadiz, Km. 0118,5",
    "sg:city":"Madridejos",
    "sg:orig_category":"Mec\u00c1nico Del Autom\u00d3vil",
    "sg:phone":"+34 925 46 01 93",
    "sg:postcode":"45710",
    "sg:province":"Toledo",
    "wof:name":"Talleres Jesanauto C.b.",
    "wof:placetype":"venue"
},
  "geometry": {"coordinates":[-3.5295538902,39.4659385681],"type":"Point"}
}