{
  "type": "Feature",
  "properties": {
    "iso:country":"ES",
    "sg:address":"San Antonio, 287",
    "sg:city":"Bre\u00f1a Baja",
    "sg:orig_category":"Deportes Y Ocio: Art\u00cdculos Y Ropas (al Por Menor Y Accesorios)",
    "sg:phone":"+34 922 18 13 92",
    "sg:postcode":"38712",
    "sg:province":"Santa Cruz De Tenerife",
    "wof:name":"C.b.inesa",
    "wof:placetype":"venue"
},
  "geometry": {"coordinates":[-17.7666397095,28.6466846466],"type":"Point"}
}