{
  "type": "Feature",
  "properties": {
    "iso:country":"ES",
    "sg:address":"Cmno Paredes, S/n",
    "sg:city":"Paredes",
    "sg:orig_category":"Ropa Para Se\u00d1oras (al Por Menor)",
    "sg:phone":"+34 985 26 91 13",
    "sg:postcode":"33420",
    "sg:province":"Asturias",
    "sg:website":"www.amichi.com",
    "wof:name":"Disedis S.l.",
    "wof:placetype":"venue"
},
  "geometry": {"coordinates":[-5.8106489182,43.4009132385],"type":"Point"}
}