{
  "type": "Feature",
  "properties": {
    "addr:full":"Carrer de Mare De Deu De Montserrat, S/n S. Boi Llobregat Barcelona 08830",
    "addr:housenumber":"s",
    "addr:postcode":"08830",
    "addr:street":"Carrer De Mare De Deu De Montserrat;/ N",
    "iso:country":"ES",
    "sg:address":"Carrer de Mare De Deu De Montserrat, S/n",
    "sg:city":"S. Boi Llobregat",
    "sg:orig_category":"Estancos",
    "sg:phone":"+34 936 54 15 50",
    "sg:postcode":"08830",
    "sg:province":"Barcelona",
    "wof:name":"Alamo Gimenez Antonia",
    "wof:placetype":"venue"
},
  "geometry": {"coordinates":[2.0358948708,41.3358612061],"type":"Point"}
}