{
  "type": "Feature",
  "properties": {
    "iso:country":"ES",
    "sg:address":"Carr Francesc Macia, 14",
    "sg:city":"Bellver Cerdanya",
    "sg:orig_category":"Plomeros",
    "sg:phone":"+34 973 51 00 15",
    "sg:postcode":"25720",
    "sg:province":"Lleida",
    "wof:name":"Comercial D'insta%acions Bellver Sccl",
    "wof:placetype":"venue"
},
  "geometry": {"coordinates":[1.776113987,42.3698539734],"type":"Point"}
}