{
  "type": "Feature",
  "properties": {
    "iso:country":"ES",
    "sg:address":"Avda Cristo De Las Cadenas, 14",
    "sg:city":"Oviedo",
    "sg:orig_category":"Ense\u00d1anza Secundaria: Colegios Y Escuelas Privadas",
    "sg:phone":"+34 985 27 62 35",
    "sg:postcode":"33006",
    "sg:province":"Asturias",
    "wof:name":"Carlos Alberto Sanchez Suarez Y Otros Cdad.",
    "wof:placetype":"venue"
},
  "geometry": {"coordinates":[-5.8583259583,43.3565063477],"type":"Point"}
}