{
  "type": "Feature",
  "properties": {
    "iso:country":"ES",
    "sg:address":"Pg Pere Iii, 71",
    "sg:city":"Manresa",
    "sg:orig_category":"Farmacias",
    "sg:phone":"+34 938 73 78 91",
    "sg:postcode":"08242",
    "sg:province":"Barcelona",
    "wof:name":"Ros Simats Nuria",
    "wof:placetype":"venue"
},
  "geometry": {"coordinates":[1.828668952,41.7306938171],"type":"Point"}
}