{
  "type": "Feature",
  "properties": {
    "iso:country":"ES",
    "sg:address":"Carrer de Terol, 8",
    "sg:city":"Barcelona",
    "sg:orig_category":"Arreglo, Reparaci\u00d3n, Piezas Sueltas De Televisi\u00d3n, V\u00cddeo, Hi",
    "sg:phone":"+34 932 10 47 07",
    "sg:postcode":"08012",
    "sg:province":"Barcelona",
    "wof:name":"Viudas Salomo Antonio",
    "wof:placetype":"venue"
},
  "geometry": {"coordinates":[2.157296896,41.4025115967],"type":"Point"}
}