{
  "type": "Feature",
  "properties": {
    "addr:full":"Calle de Urreta, 11 Kurtzea Vizcaya 48960",
    "addr:housenumber":"11",
    "addr:postcode":"48960",
    "addr:street":"Calle De Urreta",
    "iso:country":"ES",
    "sg:address":"Calle de Urreta, 11",
    "sg:city":"Kurtzea",
    "sg:orig_category":"Centros De Educaci\u00d3n Especial",
    "sg:phone":"+34 944 56 34 96",
    "sg:postcode":"48960",
    "sg:province":"Vizcaya",
    "wof:name":"Gobierno Vasco-eusko Jaurlaritza",
    "wof:placetype":"venue"
},
  "geometry": {"coordinates":[-2.8488259315,43.232334137],"type":"Point"}
}