{
  "type": "Feature",
  "properties": {
    "addr:full":"Carrer de Petunia, 4 Viladecans Barcelona 08840",
    "addr:housenumber":"4",
    "addr:postcode":"08840",
    "addr:street":"Carrer De Petunia",
    "iso:country":"ES",
    "sg:address":"Carrer de Petunia, 4",
    "sg:city":"Viladecans",
    "sg:orig_category":"Fabrica De Charcuter\u00cda",
    "sg:phone":"+34 936 37 25 81",
    "sg:postcode":"08840",
    "sg:province":"Barcelona",
    "wof:name":"Chaves Arnal Francisco",
    "wof:placetype":"venue"
},
  "geometry": {"coordinates":[2.007791996,41.3219947815],"type":"Point"}
}