{
  "type": "Feature",
  "properties": {
    "addr:full":"Rbla Just Oliveras, 56 Hospitalet Llobregat Barcelona 08901",
    "addr:housenumber":"56",
    "addr:postcode":"08901",
    "addr:street":"Rbla Just Oliveras",
    "iso:country":"ES",
    "sg:address":"Rbla Just Oliveras, 56",
    "sg:city":"Hospitalet Llobregat",
    "sg:orig_category":"Librer\u00cdas",
    "sg:phone":"+34 932 61 04 80",
    "sg:postcode":"08901",
    "sg:province":"Barcelona",
    "wof:name":"Lopez Soriano Jesus",
    "wof:placetype":"venue"
},
  "geometry": {"coordinates":[2.1007208824,41.3628349304],"type":"Point"}
}