{
  "type": "Feature",
  "properties": {
    "iso:country":"ES",
    "sg:address":"Rua Casimiro Gomez, 10",
    "sg:city":"Pontevedra",
    "sg:orig_category":"Material Y Herramientas Agr\u00cdcolas",
    "sg:phone":"+34 986 84 03 25",
    "sg:postcode":"36002",
    "sg:province":"Pontevedra",
    "wof:name":"Vidueira Estevez Aurelio",
    "wof:placetype":"venue"
},
  "geometry": {"coordinates":[-8.6349143982,42.4298439026],"type":"Point"}
}