{
  "type": "Feature",
  "properties": {
    "addr:full":"Av Cristofol Colom (de), 13 Tortosa Tarragona 43500",
    "addr:postcode":"43500",
    "addr:street":"Av Cristofol",
    "iso:country":"ES",
    "sg:address":"Av Cristofol Colom (de), 13",
    "sg:city":"Tortosa",
    "sg:orig_category":"Motocicletas (agentes, Concesionarios)",
    "sg:phone":"+34 977 50 31 18",
    "sg:postcode":"43500",
    "sg:province":"Tarragona",
    "wof:name":"Fabregues Motorsport S.l.",
    "wof:placetype":"venue"
},
  "geometry": {"coordinates":[0.5162199736,40.8144416809],"type":"Point"}
}