{
  "type": "Feature",
  "properties": {
    "iso:country":"ES",
    "sg:address":"C/ Bosc Tancat, 14",
    "sg:city":"Cerdanyola Valles",
    "sg:orig_category":"Artes Gr\u00c1ficas, Artes Pl\u00c1sticas (curso)",
    "sg:phone":"+34 936 92 68 73",
    "sg:postcode":"08290",
    "sg:province":"Barcelona",
    "sg:website":"www.cdde.es",
    "wof:name":"Central Del Documento S.a.",
    "wof:placetype":"venue"
},
  "geometry": {"coordinates":[2.1470150948,41.4924812317],"type":"Point"}
}