{
  "type": "Feature",
  "properties": {
    "addr:full":"Estd Castela, S/n Ponto La Coru\u00f1a 15570",
    "addr:housenumber":"s / n",
    "addr:postcode":"15570",
    "addr:street":"Ponto La Corun\u0303A",
    "iso:country":"ES",
    "sg:address":"Estd Castela, S/n",
    "sg:city":"Ponto",
    "sg:orig_category":"Centros De Educaci\u00d3n Especial",
    "sg:phone":"+34 981 38 37 44",
    "sg:postcode":"15570",
    "sg:province":"La Coru\u00f1a",
    "wof:name":"Colegio Publico De Pi\u00f1eiros",
    "wof:placetype":"venue"
},
  "geometry": {"coordinates":[-8.1647539139,43.5165405273],"type":"Point"}
}