{
  "type": "Feature",
  "properties": {
    "addr:full":"Carrer de Pi, 14 Barcelona Barcelona 08002",
    "addr:housenumber":"14",
    "addr:postcode":"08002",
    "addr:street":"Carrer De Pi",
    "iso:country":"ES",
    "sg:address":"Carrer de Pi, 14",
    "sg:city":"Barcelona",
    "sg:orig_category":"Juegos Y Juguetes (al Por Menor)",
    "sg:phone":"+34 933 18 14 87",
    "sg:postcode":"08002",
    "sg:province":"Barcelona",
    "sg:website":"www.ample24.com/drap",
    "wof:name":"Ametlla Fuset Maria Elena",
    "wof:placetype":"venue"
},
  "geometry": {"coordinates":[2.1739938259,41.3834457397],"type":"Point"}
}