{
  "type": "Feature",
  "properties": {
    "iso:country":"ES",
    "sg:address":"Calle de Castillo, S/n",
    "sg:city":"Estepona",
    "sg:orig_category":"M\u00c9dicos: Ginecolog\u00cda Y Obstetricia",
    "sg:phone":"+34 952 79 11 77",
    "sg:postcode":"29680",
    "sg:province":"M\u00e1laga",
    "wof:name":"Nicora Da Silva Oscar",
    "wof:placetype":"venue"
},
  "geometry": {"coordinates":[-5.1459794044,36.4248313904],"type":"Point"}
}