{
  "type": "Feature",
  "properties": {
    "iso:country":"ES",
    "sg:address":"Plaz Inmaculada, 4",
    "sg:city":"Algeciras",
    "sg:orig_category":"Procuradores",
    "sg:phone":"+34 956 66 76 40",
    "sg:postcode":"11202",
    "sg:province":"C\u00e1diz",
    "wof:name":"Moreno Martin Silvia",
    "wof:placetype":"venue"
},
  "geometry": {"coordinates":[-5.4511728287,36.1346321106],"type":"Point"}
}