{
  "type": "Feature",
  "properties": {
    "iso:country":"ES",
    "sg:address":"Ctra Font Roja, 5",
    "sg:city":"Alcoi",
    "sg:orig_category":"Escayola Y Productos De Escayola (fabricaci\u00d3n, Al Por Mayor)",
    "sg:phone":"+34 965 54 54 80",
    "sg:postcode":"03801",
    "sg:province":"Alicante",
    "wof:name":"Escayolas San Jorge S.a.l.",
    "wof:placetype":"venue"
},
  "geometry": {"coordinates":[-0.4762549996,38.6785926819],"type":"Point"}
}