{
  "type": "Feature",
  "properties": {
    "iso:country":"ES",
    "sg:address":"Avda Lancia, 19",
    "sg:city":"Le\u00f3n",
    "sg:orig_category":"Asistencia Social",
    "sg:phone":"+34 987 20 90 68",
    "sg:postcode":"24004",
    "sg:province":"Le\u00f3n",
    "wof:name":"Lorenzo Saez Beatriz",
    "wof:placetype":"venue"
},
  "geometry": {"coordinates":[-5.5748472214,42.5935401917],"type":"Point"}
}