{
  "type": "Feature",
  "properties": {
    "addr:full":"Carrer de Arago, 463 Barcelona Barcelona 08013",
    "addr:housenumber":"463",
    "addr:postcode":"08013",
    "addr:street":"Carrer De Arago",
    "iso:country":"ES",
    "sg:address":"Carrer de Arago, 463",
    "sg:city":"Barcelona",
    "sg:orig_category":"Ingeniero",
    "sg:phone":"+34 932 31 86 11",
    "sg:postcode":"08013",
    "sg:province":"Barcelona",
    "wof:name":"Orian Enginyers S.l.",
    "wof:placetype":"venue"
},
  "geometry": {"coordinates":[2.1791610718,41.4031066895],"type":"Point"}
}