{
  "type": "Feature",
  "properties": {
    "iso:country":"ES",
    "sg:address":"Calle de Zumarraga, 8",
    "sg:city":"Bilbao",
    "sg:orig_category":"Reposter\u00cdas",
    "sg:phone":"+34 944 15 07 63",
    "sg:postcode":"48006",
    "sg:province":"Vizcaya",
    "wof:name":"Portilla Solana Luis Enrique",
    "wof:placetype":"venue"
},
  "geometry": {"coordinates":[-2.9193849564,43.2572975159],"type":"Point"}
}