{
  "type": "Feature",
  "properties": {
    "iso:country":"ES",
    "sg:address":"Rua Oliva (la), S/n",
    "sg:city":"Pontevedra",
    "sg:orig_category":"Calzados Ortop\u00c9dicos",
    "sg:phone":"+34 986 85 27 28",
    "sg:postcode":"36001",
    "sg:province":"Pontevedra",
    "wof:name":"Pedrosa Sobral Enrique",
    "wof:placetype":"venue"
},
  "geometry": {"coordinates":[-8.6444606781,42.4303627014],"type":"Point"}
}