{
  "type": "Feature",
  "properties": {
    "iso:country":"ES",
    "sg:address":"Calle de Marcelino Rodriguez, 1",
    "sg:city":"Luanco",
    "sg:orig_category":"Librer\u00cdas",
    "sg:phone":"+34 985 88 13 99",
    "sg:postcode":"33440",
    "sg:province":"Asturias",
    "wof:name":"Garcia Garcia Martina",
    "wof:placetype":"venue"
},
  "geometry": {"coordinates":[-5.7927269936,43.6150627136],"type":"Point"}
}