{
  "type": "Feature",
  "properties": {
    "iso:country":"ES",
    "sg:address":"Ctra Trassierra (extrarradio), 26",
    "sg:city":"Cordoba",
    "sg:orig_category":"Farmacias",
    "sg:phone":"+34 957 27 41 92",
    "sg:postcode":"14011",
    "sg:province":"C\u00f3rdoba",
    "wof:name":"Farmacia Perez Oliva C.b.",
    "wof:placetype":"venue"
},
  "geometry": {"coordinates":[-4.7895960808,37.8912696838],"type":"Point"}
}