{
  "type": "Feature",
  "properties": {
    "iso:country":"ES",
    "sg:address":"Calle de Lope De Rueda, 6",
    "sg:city":"Madrid",
    "sg:orig_category":"Caf\u00c9s, Bares, Cervecer\u00cdas",
    "sg:phone":"+34 915 76 40 74",
    "sg:postcode":"28009",
    "sg:province":"Madrid",
    "wof:name":"Guzman Garcia Miguel",
    "wof:placetype":"venue"
},
  "geometry": {"coordinates":[-3.6774890423,40.4236030579],"type":"Point"}
}