{
  "type": "Feature",
  "properties": {
    "addr:full":"Carr Maragall, 44 Badalona Barcelona 08912",
    "addr:housenumber":"44",
    "addr:postcode":"08912",
    "addr:street":"Carr Maragall",
    "iso:country":"ES",
    "sg:address":"Carr Maragall, 44",
    "sg:city":"Badalona",
    "sg:orig_category":"Muebles Y Accesorios Para Cocinas Y Cuartos De Ba\u00d1o (al Por Menor)",
    "sg:phone":"+34 933 87 44 41",
    "sg:postcode":"08912",
    "sg:province":"Barcelona",
    "wof:name":"Morales Monereo Jose",
    "wof:placetype":"venue"
},
  "geometry": {"coordinates":[2.2420270443,41.4495506287],"type":"Point"}
}