{
  "type": "Feature",
  "properties": {
    "addr:full":"Calle de Emilio Niveiro Romo, 9 Talavera Reina Toledo 45600",
    "addr:housenumber":"9",
    "addr:postcode":"45600",
    "addr:street":"Calle De Emilio Niveiro Romo",
    "iso:country":"ES",
    "sg:address":"Calle de Emilio Niveiro Romo, 9",
    "sg:city":"Talavera Reina",
    "sg:orig_category":"Chapister\u00cda",
    "sg:phone":"+34 925 80 17 33",
    "sg:postcode":"45600",
    "sg:province":"Toledo",
    "wof:name":"Taller Roma Y Alpe S.l.",
    "wof:placetype":"venue"
},
  "geometry": {"coordinates":[-4.0244760513,39.8567771912],"type":"Point"}
}