{
  "type": "Feature",
  "properties": {
    "addr:full":"Avda Constitucion, 6 Rozas De Madrid Madrid 28230",
    "addr:housenumber":"6",
    "addr:postcode":"28230",
    "addr:street":"Avda Constitucion",
    "iso:country":"ES",
    "sg:address":"Avda Constitucion, 6",
    "sg:city":"Rozas De Madrid",
    "sg:orig_category":"\u00d3ptica: Instrumentos (fabricaci\u00d3n)",
    "sg:phone":"+34 916 36 32 14",
    "sg:postcode":"28230",
    "sg:province":"Madrid",
    "wof:name":"Euro-optica Maria Jose Rubido S.l.",
    "wof:placetype":"venue"
},
  "geometry": {"coordinates":[-3.8748800755,40.4925193787],"type":"Point"}
}