{
  "type": "Feature",
  "properties": {
    "iso:country":"ES",
    "sg:address":"Plaz Moreno (del), 2",
    "sg:city":"Cordoba",
    "sg:orig_category":"Agencias De Trabajo Temporal",
    "sg:phone":"+34 957 47 59 94",
    "sg:postcode":"14001",
    "sg:province":"C\u00f3rdoba",
    "wof:name":"Manpower Team Empresa Trabajo Temporal S.a.",
    "wof:placetype":"venue"
},
  "geometry": {"coordinates":[-4.7769255638,37.8897323608],"type":"Point"}
}