{
  "type": "Feature",
  "properties": {
    "addr:full":"Av Solsona, 14 Tora Lleida 25750",
    "addr:housenumber":"14",
    "addr:postcode":"25750",
    "addr:street":"Av Solsona",
    "iso:country":"ES",
    "sg:address":"Av Solsona, 14",
    "sg:city":"Tora",
    "sg:orig_category":"Material Y Herramientas Agr\u00cdcolas",
    "sg:phone":"+34 973 47 31 00",
    "sg:postcode":"25750",
    "sg:province":"Lleida",
    "wof:name":"Simo Tarres Jose",
    "wof:placetype":"venue"
},
  "geometry": {"coordinates":[1.4043149948,41.811340332],"type":"Point"}
}