{
  "type": "Feature",
  "properties": {
    "iso:country":"ES",
    "sg:address":"Calle de Alvar Fa\u00d1ez, 10",
    "sg:city":"Jerez De La Frontera",
    "sg:orig_category":"Molduras, Junquillos, Listones Y Molduras Perforadas",
    "sg:phone":"+34 956 14 11 07",
    "sg:postcode":"11401",
    "sg:province":"C\u00e1diz",
    "wof:name":"Ruiz Garcia Diego",
    "wof:placetype":"venue"
},
  "geometry": {"coordinates":[-6.1415915489,36.6767997742],"type":"Point"}
}