{
  "type": "Feature",
  "properties": {
    "addr:full":"Calle de Martinez De La Rosa, 4 Granada Granada 18002",
    "addr:housenumber":"4",
    "addr:postcode":"18002",
    "addr:street":"Calle De Martinez De La Rosa",
    "iso:country":"ES",
    "sg:address":"Calle de Martinez De La Rosa, 4",
    "sg:city":"Granada",
    "sg:classifiers":[
        {
            "category":"Personal",
            "subcategory":"Barber",
            "type":"Services"
        }
    ],
    "sg:phone":"+34 958 28 59 03",
    "sg:postcode":"18002",
    "sg:province":"Granada",
    "sg:tags":[
        "caballeros",
        "de",
        "peluqueros"
    ],
    "wof:name":"Navarro Morillo Jose Manuel",
    "wof:placetype":"venue"
},
  "geometry": {"coordinates":[-3.607047081,37.1773223877],"type":"Point"}
}