{
  "type": "Feature",
  "properties": {
    "addr:full":"C/ Sant Antoni, 6 Tossa Girona 17320",
    "addr:housenumber":"6",
    "addr:postcode":"17320",
    "addr:street":"C / Sant Antoni",
    "iso:country":"ES",
    "sg:address":"C/ Sant Antoni, 6",
    "sg:city":"Tossa",
    "sg:orig_category":"Reposter\u00cdas",
    "sg:phone":"+34 972 34 00 73",
    "sg:postcode":"17320",
    "sg:province":"Girona",
    "wof:name":"Aragay Vall-llosera Ramon",
    "wof:placetype":"venue"
},
  "geometry": {"coordinates":[2.9304220676,41.7185516357],"type":"Point"}
}