{
  "type": "Feature",
  "properties": {
    "addr:full":"Urb Aguas Nuevas, S/n Torrelamata Alicante 03188",
    "addr:housenumber":"s",
    "addr:postcode":"03188",
    "addr:street":"Urb Aguas Nuevas;/ N Torrelamata",
    "iso:country":"ES",
    "sg:address":"Urb Aguas Nuevas, S/n",
    "sg:city":"Torrelamata",
    "sg:orig_category":"Supermercados Y Hipermercados",
    "sg:phone":"+34 966 92 17 72",
    "sg:postcode":"03188",
    "sg:province":"Alicante",
    "wof:name":"Aldi Supermercados S.l.",
    "wof:placetype":"venue"
},
  "geometry": {"coordinates":[-0.4810059965,38.3452033997],"type":"Point"}
}