{
  "type": "Feature",
  "properties": {
    "addr:full":"Carrer de Sant Pere, 37 Altea Alicante 03590",
    "addr:housenumber":"37",
    "addr:postcode":"03590",
    "addr:street":"Carrer De Sant Pere",
    "iso:country":"ES",
    "sg:address":"Carrer de Sant Pere, 37",
    "sg:city":"Altea",
    "sg:orig_category":"Inmobiliaria (agencias)",
    "sg:phone":"+34 966 88 11 91",
    "sg:postcode":"03590",
    "sg:province":"Alicante",
    "sg:website":"www.livingstone/estates.com",
    "wof:name":"Livingstone Estates S.l.",
    "wof:placetype":"venue"
},
  "geometry": {"coordinates":[-0.0525889993,38.5945968628],"type":"Point"}
}