{
  "type": "Feature",
  "properties": {
    "addr:full":"Plaz Mercado, 3 Salamanca Salamanca 37001",
    "addr:housenumber":"3",
    "addr:postcode":"37001",
    "addr:street":"Mercado",
    "iso:country":"ES",
    "sg:address":"Plaz Mercado, 3",
    "sg:city":"Salamanca",
    "sg:orig_category":"Expertos Contables",
    "sg:phone":"+34 923 21 88 29",
    "sg:postcode":"37001",
    "sg:province":"Salamanca",
    "wof:name":"Gesa Dos S.l.",
    "wof:placetype":"venue"
},
  "geometry": {"coordinates":[-5.663187027,40.9650268555],"type":"Point"}
}