{
  "type": "Feature",
  "properties": {
    "addr:full":"Calle de Buenaventura Zapirain Kalea, 4 Lekeitio Vizcaya 48280",
    "addr:housenumber":"4",
    "addr:postcode":"48280",
    "addr:street":"Calle De Buenaventura Zapirain Kalea",
    "iso:country":"ES",
    "sg:address":"Calle de Buenaventura Zapirain Kalea, 4",
    "sg:city":"Lekeitio",
    "sg:orig_category":"Comercio De Piezas De Recambio Y De Accesorios De Veh\u00cdculos, Veh\u00cdculos Industriales",
    "sg:phone":"+34 946 84 23 71",
    "sg:postcode":"48280",
    "sg:province":"Vizcaya",
    "wof:name":"Autorecambios  Garai",
    "wof:placetype":"venue"
},
  "geometry": {"coordinates":[-2.5063710213,43.363483429],"type":"Point"}
}