{
  "type": "Feature",
  "properties": {
    "iso:country":"ES",
    "sg:address":"Avda Diputacion (de La), 88",
    "sg:city":"Chiclana De La Frontera",
    "sg:orig_category":"Reposter\u00cdas",
    "sg:phone":"+34 956 40 53 27",
    "sg:postcode":"11130",
    "sg:province":"C\u00e1diz",
    "wof:name":"Butron Benitez Jose",
    "wof:placetype":"venue"
},
  "geometry": {"coordinates":[-6.1731319427,36.3804702759],"type":"Point"}
}