{
  "type": "Feature",
  "properties": {
    "addr:full":"Calle de Narcis Monturiol, 30 Marbella M\u00e1laga 29600",
    "addr:housenumber":"30",
    "addr:postcode":"29600",
    "addr:street":"Calle De Narcis Monturiol;Ma\u0301Laga",
    "iso:country":"ES",
    "sg:address":"Calle de Narcis Monturiol, 30",
    "sg:city":"Marbella",
    "sg:orig_category":"Agencias Y Agentes Comerciales, Representantes",
    "sg:phone":"+34 952 82 98 39",
    "sg:postcode":"29600",
    "sg:province":"M\u00e1laga",
    "wof:name":"Warnaco Intimo S.a.",
    "wof:placetype":"venue"
},
  "geometry": {"coordinates":[-4.8721289635,36.5089302063],"type":"Point"}
}