{
  "type": "Feature",
  "properties": {
    "iso:country":"ES",
    "sg:address":"Calle de Arzobispo Barroeta, 28",
    "sg:city":"Ezcaray",
    "sg:orig_category":"Bazares, Art\u00cdculos De Limpieza Y De Cocina (al Por Menor)",
    "sg:phone":"+34 941 35 42 29",
    "sg:postcode":"26280",
    "sg:province":"La Rioja",
    "wof:name":"Soto Saenz Jose Luis",
    "wof:placetype":"venue"
},
  "geometry": {"coordinates":[-3.0156681538,42.3239707947],"type":"Point"}
}