{
  "type": "Feature",
  "properties": {
    "iso:country":"ES",
    "sg:address":"Calle de Albeniz, 29",
    "sg:city":"Oviedo",
    "sg:orig_category":"Venta, Instalaci\u00d3n, Reparaci\u00d3n De Antenas Para Televisi\u00d3n",
    "sg:phone":"+34 985 11 53 10",
    "sg:postcode":"33011",
    "sg:province":"Asturias",
    "wof:name":"Mundielectric S.l.",
    "wof:placetype":"venue"
},
  "geometry": {"coordinates":[-5.8405833244,43.370426178],"type":"Point"}
}