{
  "type": "Feature",
  "properties": {
    "iso:country":"ES",
    "sg:address":"Calle de Marte, 102",
    "sg:city":"Valdemoro",
    "sg:orig_category":"Autob\u00das (explotaci\u00d3n Y Servicios De)",
    "sg:phone":"+34 918 08 58 10",
    "sg:postcode":"28340",
    "sg:province":"Madrid",
    "wof:name":"Asociabus S.l.",
    "wof:placetype":"venue"
},
  "geometry": {"coordinates":[-3.6817643642,40.177280426],"type":"Point"}
}