{
  "type": "Feature",
  "properties": {
    "addr:full":"Calle de Arenal (el), 21 Noja Cantabria 39180",
    "addr:housenumber":"21",
    "addr:postcode":"39180",
    "addr:street":"Calle De Arenal El",
    "iso:country":"ES",
    "sg:address":"Calle de Arenal (el), 21",
    "sg:city":"Noja",
    "sg:orig_category":"Hoteles",
    "sg:phone":"+34 942 63 03 20",
    "sg:postcode":"39180",
    "sg:province":"Cantabria",
    "wof:name":"Berceda S.a.",
    "wof:placetype":"venue"
},
  "geometry": {"coordinates":[-3.5198290348,43.4893608093],"type":"Point"}
}