{
  "type": "Feature",
  "properties": {
    "iso:country":"ES",
    "sg:address":"Calle de Invierno, 1",
    "sg:city":"Torrejon Ardoz",
    "sg:orig_category":"Venta, Instalaci\u00d3n De Calefacci\u00d3n",
    "sg:phone":"+34 916 75 23 12",
    "sg:postcode":"28850",
    "sg:province":"Madrid",
    "wof:name":"Martin Agenjo Instalaciones S.l.",
    "wof:placetype":"venue"
},
  "geometry": {"coordinates":[-3.4878129959,40.4443283081],"type":"Point"}
}