{
  "type": "Feature",
  "properties": {
    "iso:country":"ES",
    "sg:address":"Calle de Carretera De Tordesillas, 19",
    "sg:city":"Morales Toro",
    "sg:orig_category":"Agencias Y Asesores De Publicidad",
    "sg:phone":"+34 980 69 82 35",
    "sg:postcode":"49810",
    "sg:province":"Zamora",
    "wof:name":"Torre Velasco Paula De La",
    "wof:placetype":"venue"
},
  "geometry": {"coordinates":[-5.3064441681,41.5372848511],"type":"Point"}
}