{
  "type": "Feature",
  "properties": {
    "iso:country":"ES",
    "sg:address":"Nueve(pol Ind Alboraya), S/n",
    "sg:city":"Alboraya",
    "sg:orig_category":"Fabricaci\u00d3n De Mobiliario Met\u00c1lico",
    "sg:phone":"+34 961 86 10 45",
    "sg:postcode":"46120",
    "sg:province":"Valencia",
    "wof:name":"Talleres Grao S. A.",
    "wof:placetype":"venue"
},
  "geometry": {"coordinates":[-0.348183006,39.5005302429],"type":"Point"}
}