{
  "type": "Feature",
  "properties": {
    "iso:country":"ES",
    "sg:address":"Av Matadepera, 3",
    "sg:city":"Sabadell",
    "sg:orig_category":"Fabricaci\u00d3n De Cortinas Y Visillos",
    "sg:phone":"+34 937 16 01 01",
    "sg:postcode":"08207",
    "sg:province":"Barcelona",
    "wof:name":"Serra Permanyer S.c.p.",
    "wof:placetype":"venue"
},
  "geometry": {"coordinates":[2.079595089,41.5739593506],"type":"Point"}
}