{
  "type": "Feature",
  "properties": {
    "iso:country":"ES",
    "sg:address":"Carrer de Major, 113",
    "sg:city":"Cervello",
    "sg:orig_category":"Supermercados Y Hipermercados",
    "sg:phone":"+34 936 84 09 48",
    "sg:postcode":"08758",
    "sg:province":"Barcelona",
    "wof:name":"Bon Preu S.a.",
    "wof:placetype":"venue"
},
  "geometry": {"coordinates":[1.9577989578,41.3962631226],"type":"Point"}
}