{
  "type": "Feature",
  "properties": {
    "iso:country":"ES",
    "sg:address":"Cra Nacional Ii, S/n",
    "sg:city":"Mataro",
    "sg:orig_category":"Iglesia Cat\u00d3lica",
    "sg:phone":"+34 937 90 70 59",
    "sg:postcode":"08301",
    "sg:province":"Barcelona",
    "wof:name":"Parroquia Sant Simo I Sant Pau",
    "wof:placetype":"venue"
},
  "geometry": {"coordinates":[2.4479300976,41.5427207947],"type":"Point"}
}