{
  "type": "Feature",
  "properties": {
    "iso:country":"ES",
    "sg:address":"Calle de Gamito, 5",
    "sg:city":"Poligono Industrial Los Villares",
    "sg:orig_category":"Comercio De Piezas De Recambio Y De Accesorios De Veh\u00cdculos, Veh\u00cdculos Industriales",
    "sg:phone":"+34 923 28 22 75",
    "sg:postcode":"37184",
    "sg:province":"Salamanca",
    "wof:name":"Iberwagem S.l.",
    "wof:placetype":"venue"
},
  "geometry": {"coordinates":[-5.6471271515,40.9923095703],"type":"Point"}
}