{
  "type": "Feature",
  "properties": {
    "iso:country":"ES",
    "sg:address":"Ctra Arbucies, 42",
    "sg:city":"Breda",
    "sg:classifiers":[
        {
            "category":"Autos & Motor Vehicles",
            "subcategory":"Automobile Sales",
            "type":"Retail Goods"
        }
    ],
    "sg:phone":"+34 972 87 09 32",
    "sg:postcode":"17400",
    "sg:province":"Girona",
    "wof:name":"Autoescola Salgado S.l.",
    "wof:placetype":"venue"
},
  "geometry": {"coordinates":[2.5599265099,41.7478866577],"type":"Point"}
}