{
  "type": "Feature",
  "properties": {
    "addr:full":"Carrer de Caputxins (dels), 27 Tarragona Tarragona 43001",
    "addr:housenumber":"27",
    "addr:postcode":"43001",
    "addr:street":"Carrer De Caputxins Dels",
    "iso:country":"ES",
    "sg:address":"Carrer de Caputxins (dels), 27",
    "sg:city":"Tarragona",
    "sg:orig_category":"Empresarios Y Productoras De Espect\u00c1culos",
    "sg:phone":"+34 977 22 55 65",
    "sg:postcode":"43001",
    "sg:province":"Tarragona",
    "wof:name":"Padrell Benet Cristina",
    "wof:placetype":"venue"
},
  "geometry": {"coordinates":[1.2472100258,41.113319397],"type":"Point"}
}