{
  "type": "Feature",
  "properties": {
    "iso:country":"ES",
    "sg:address":"Ctra Miraflores Guadalix, Km. 0006,0",
    "sg:city":"Miraflores De La Sierra",
    "sg:orig_category":"Producci\u00d3n De Abonos Y De Fertilizantes",
    "sg:phone":"+34 918 44 46 32",
    "sg:postcode":"28792",
    "sg:province":"Madrid",
    "wof:name":"Centro De Jardineria Miraflores S.c",
    "wof:placetype":"venue"
},
  "geometry": {"coordinates":[-3.7576858997,40.8003807068],"type":"Point"}
}