{
  "type": "Feature",
  "properties": {
    "iso:country":"ES",
    "sg:address":"Plaz Virgen Del Mar (de La), 4",
    "sg:city":"Almeria",
    "sg:orig_category":"Cl\u00cdnicas M\u00c9dicas",
    "sg:phone":"+34 950 24 67 24",
    "sg:postcode":"04002",
    "sg:province":"Almer\u00eda",
    "wof:name":"Terapeutica Clinica S.a.",
    "wof:placetype":"venue"
},
  "geometry": {"coordinates":[-2.4648079872,36.837223053],"type":"Point"}
}