{
  "type": "Feature",
  "properties": {
    "iso:country":"ES",
    "sg:address":"Avgd Baixada L'estacio, 7",
    "sg:city":"Xativa",
    "sg:orig_category":"Contenedores (mercanc\u00cdas)",
    "sg:phone":"+34 962 27 11 61",
    "sg:postcode":"46800",
    "sg:province":"Valencia",
    "wof:name":"Salvador Pont Vidal Sl",
    "wof:placetype":"venue"
},
  "geometry": {"coordinates":[-0.5238400102,38.9906539917],"type":"Point"}
}