{
  "type": "Feature",
  "properties": {
    "iso:country":"ES",
    "sg:address":"Calle de San Diego, 1",
    "sg:city":"Coru\u00d1a",
    "sg:orig_category":"Agencias Y Agentes Comerciales, Representantes",
    "sg:phone":"+34 981 13 53 83",
    "sg:postcode":"15009",
    "sg:province":"A Coru\u00f1a",
    "wof:name":"Sobrado Carreras Gerardo Jesus",
    "wof:placetype":"venue"
},
  "geometry": {"coordinates":[-8.399435997,43.3534851074],"type":"Point"}
}