{
  "type": "Feature",
  "properties": {
    "iso:country":"ES",
    "sg:address":"Carrer de Francisco Giner, 40",
    "sg:city":"Barcelona",
    "sg:orig_category":"Fisioterapia",
    "sg:phone":"+34 932 37 72 46",
    "sg:postcode":"08012",
    "sg:province":"Barcelona",
    "wof:name":"Pomarol Clotet Gemma",
    "wof:placetype":"venue"
},
  "geometry": {"coordinates":[2.1587710381,41.3996696472],"type":"Point"}
}