{
  "type": "Feature",
  "properties": {
    "iso:country":"ES",
    "sg:address":"Calle de Ancha, 1",
    "sg:city":"Sese\u00f1a",
    "sg:orig_category":"Centros De Coordinaci\u00d3n",
    "sg:phone":"+34 918 09 84 88",
    "sg:postcode":"45223",
    "sg:province":"Toledo",
    "wof:name":"Oficinas San Juan S.l.",
    "wof:placetype":"venue"
},
  "geometry": {"coordinates":[-3.6971814632,40.1043624878],"type":"Point"}
}