{
  "type": "Feature",
  "properties": {
    "addr:full":"Pg Generalitat, 18 Vic Barcelona 08500",
    "addr:housenumber":"18",
    "addr:postcode":"08500",
    "addr:street":"Pg Generalitat",
    "iso:country":"ES",
    "sg:address":"Pg Generalitat, 18",
    "sg:city":"Vic",
    "sg:orig_category":"Peluquer\u00cdas, Peluquer\u00cda Mixta",
    "sg:phone":"+34 938 85 55 68",
    "sg:postcode":"08500",
    "sg:province":"Barcelona",
    "wof:name":"Catalan Ruiz Inmaculada",
    "wof:placetype":"venue"
},
  "geometry": {"coordinates":[2.2532300949,41.9236907959],"type":"Point"}
}