{
  "type": "Feature",
  "properties": {
    "iso:country":"ES",
    "sg:address":"Avda Perez Galdos, 93",
    "sg:city":"Valencia",
    "sg:orig_category":"Peluqueros: De Se\u00d1oras",
    "sg:phone":"+34 963 84 61 58",
    "sg:postcode":"46018",
    "sg:province":"Valencia",
    "wof:name":"Perez Sabio Consuelo",
    "wof:placetype":"venue"
},
  "geometry": {"coordinates":[-0.3925589919,39.470035553],"type":"Point"}
}