{
  "type": "Feature",
  "properties": {
    "iso:country":"ES",
    "sg:address":"Salins Cuarta Linea, S/n",
    "sg:city":"Empuriabrava",
    "sg:orig_category":"Inmobiliaria (agencias)",
    "sg:phone":"+34 972 45 12 09",
    "sg:postcode":"17487",
    "sg:province":"Girona",
    "wof:name":"Anauxita S.l.",
    "wof:placetype":"venue"
},
  "geometry": {"coordinates":[3.1227703094,42.2480926514],"type":"Point"}
}