{
  "type": "Feature",
  "properties": {
    "addr:full":"Carr Rocaberti, 31 Figueres Girona 17600",
    "addr:housenumber":"31",
    "addr:postcode":"17600",
    "addr:street":"Carr Rocaberti",
    "iso:country":"ES",
    "sg:address":"Carr Rocaberti, 31",
    "sg:city":"Figueres",
    "sg:orig_category":"Centros Empresariales",
    "sg:phone":"+34 972 50 17 95",
    "sg:postcode":"17600",
    "sg:province":"Girona",
    "wof:name":"Casademont Duran Antonio",
    "wof:placetype":"venue"
},
  "geometry": {"coordinates":[2.9680540562,42.2606735229],"type":"Point"}
}