{
  "type": "Feature",
  "properties": {
    "iso:country":"ES",
    "sg:address":"Calle de Conde Aranda, 7",
    "sg:city":"Zaragoza",
    "sg:classifiers":[
        {
            "category":"Casinos & Gambling",
            "type":"Entertainment"
        }
    ],
    "sg:phone":"+34 976 28 27 14",
    "sg:postcode":"50004",
    "sg:province":"Zaragoza",
    "sg:tags":[
        "locale",
        "de",
        "juego"
    ],
    "wof:name":"Bingos Unidos S.a.",
    "wof:placetype":"venue"
},
  "geometry": {"coordinates":[-0.8849869967,41.6541671753],"type":"Point"}
}