{
  "type": "Feature",
  "properties": {
    "addr:full":"Calle de Atilano Del Bosque, S/n Monfarracinos Zamora 49121",
    "addr:housenumber":"s",
    "addr:postcode":"49121",
    "addr:street":"Calle De Atilano Del Bosque;/ N Monfarracinos Zamora",
    "iso:country":"ES",
    "sg:address":"Calle de Atilano Del Bosque, S/n",
    "sg:city":"Monfarracinos",
    "sg:orig_category":"Carnicer\u00cdas, Carnicer\u00cdas",
    "sg:phone":"+34 980 50 20 31",
    "sg:postcode":"49121",
    "sg:province":"Zamora",
    "wof:name":"Ballesteros Lopez Manuel",
    "wof:placetype":"venue"
},
  "geometry": {"coordinates":[-5.7064328194,41.5542602539],"type":"Point"}
}