{
  "type": "Feature",
  "properties": {
    "iso:country":"ES",
    "sg:address":"Calle de Aguilar, S/n",
    "sg:city":"Monturque",
    "sg:orig_category":"Negocio De Materiales De Construcci\u00d3n",
    "sg:phone":"+34 957 53 55 41",
    "sg:postcode":"14930",
    "sg:province":"C\u00f3rdoba",
    "wof:name":"Aguilera Porras Jose",
    "wof:placetype":"venue"
},
  "geometry": {"coordinates":[-4.5838494301,37.4734077454],"type":"Point"}
}