{
  "type": "Feature",
  "properties": {
    "iso:country":"ES",
    "sg:address":"Calle de Gobela, 32",
    "sg:city":"Arenas -areeta",
    "sg:orig_category":"Electricidad: Instaladores",
    "sg:phone":"+34 944 63 49 05",
    "sg:postcode":"48930",
    "sg:province":"Vizcaya",
    "wof:name":"Electricidad Gobela S.l.",
    "wof:placetype":"venue"
},
  "geometry": {"coordinates":[-3.0109639168,43.32629776],"type":"Point"}
}