{
  "type": "Feature",
  "properties": {
    "iso:country":"ES",
    "sg:address":"Ctra Recajo, S/n",
    "sg:city":"Viana",
    "sg:orig_category":"Mec\u00c1nico Del Autom\u00d3vil",
    "sg:phone":"+34 948 64 58 55",
    "sg:postcode":"31230",
    "sg:province":"Navarra",
    "wof:name":"Hurtado Fernandez Emilio",
    "wof:placetype":"venue"
},
  "geometry": {"coordinates":[-2.3656148911,42.5124168396],"type":"Point"}
}