{
  "type": "Feature",
  "properties": {
    "iso:country":"ES",
    "sg:address":"Cmno Vera, 27",
    "sg:city":"Campohermoso",
    "sg:orig_category":"Molduras, Junquillos, Listones Y Molduras Perforadas",
    "sg:phone":"+34 950 38 50 72",
    "sg:postcode":"04110",
    "sg:province":"Almer\u00eda",
    "wof:name":"Tristan Garcia Manuel",
    "wof:placetype":"venue"
},
  "geometry": {"coordinates":[-2.1324241161,36.9409065247],"type":"Point"}
}