{
  "type": "Feature",
  "properties": {
    "addr:full":"Calle de Maria Puga Cerdido, 6 Coru\u00d1a A Coru\u00f1a 15009",
    "addr:housenumber":"6",
    "addr:postcode":"15009",
    "addr:street":"Calle De Maria Puga Cerdido;Corun\u0303A",
    "iso:country":"ES",
    "sg:address":"Calle de Maria Puga Cerdido, 6",
    "sg:city":"Coru\u00d1a",
    "sg:orig_category":"Supermercados Y Hipermercados",
    "sg:phone":"+34 981 17 03 57",
    "sg:postcode":"15009",
    "sg:province":"A Coru\u00f1a",
    "wof:name":"Vego Supermercados S.a.",
    "wof:placetype":"venue"
},
  "geometry": {"coordinates":[-8.4034070969,43.3415412903],"type":"Point"}
}