{
  "type": "Feature",
  "properties": {
    "addr:full":"Calle de Castellon, 24 Segorbe Castell\u00f3n 12400",
    "addr:housenumber":"24",
    "addr:postcode":"12400",
    "addr:street":"Calle De Castellon",
    "iso:country":"ES",
    "sg:address":"Calle de Castellon, 24",
    "sg:city":"Segorbe",
    "sg:classifiers":[
        {
            "category":"Communications",
            "type":"Services"
        }
    ],
    "sg:phone":"+34 964 71 26 45",
    "sg:postcode":"12400",
    "sg:province":"Castell\u00f3n",
    "sg:tags":[
        "televisiones",
        "y",
        "radio"
    ],
    "wof:name":"Radiodifusion Alto Palancia S. L.",
    "wof:placetype":"venue"
},
  "geometry": {"coordinates":[-0.4888834953,39.8500404358],"type":"Point"}
}