{
  "type": "Feature",
  "properties": {
    "addr:full":"La Iglesia, 2 Parada Sil Ourense 32740",
    "addr:housenumber":"2",
    "addr:postcode":"32740",
    "addr:street":"Iglesia",
    "iso:country":"ES",
    "sg:address":"La Iglesia, 2",
    "sg:city":"Parada Sil",
    "sg:orig_category":"Farmacias",
    "sg:phone":"+34 988 20 80 91",
    "sg:postcode":"32740",
    "sg:province":"Ourense",
    "wof:name":"Gonzalez-roson Fernandez Justiniano",
    "wof:placetype":"venue"
},
  "geometry": {"coordinates":[-7.6178269386,42.2906265259],"type":"Point"}
}