{
  "type": "Feature",
  "properties": {
    "addr:full":"Calle de Cardenal Reig, S/n Oca\u00f1a Toledo 45300",
    "addr:housenumber":"s",
    "addr:postcode":"45300",
    "addr:street":"Calle De Cardenal Reig;/ N Ocan\u0303A",
    "iso:country":"ES",
    "sg:address":"Calle de Cardenal Reig, S/n",
    "sg:city":"Oca\u00f1a",
    "sg:orig_category":"Transporte En General",
    "sg:phone":"+34 925 12 11 47",
    "sg:postcode":"45300",
    "sg:province":"Toledo",
    "wof:name":"Vijumar S.l.",
    "wof:placetype":"venue"
},
  "geometry": {"coordinates":[-3.4925739765,39.9612464905],"type":"Point"}
}