{
  "type": "Feature",
  "properties": {
    "iso:country":"ES",
    "sg:address":"Avda Martires (de Los), 11",
    "sg:city":"Montiel",
    "sg:orig_category":"Albergues",
    "sg:phone":"+34 926 35 33 09",
    "sg:postcode":"13326",
    "sg:province":"Ciudad Real",
    "wof:name":"Valle Flores Antonio",
    "wof:placetype":"venue"
},
  "geometry": {"coordinates":[-2.8636689186,38.6973190308],"type":"Point"}
}