{
  "type": "Feature",
  "properties": {
    "addr:full":"Carrer de Industria, 18 Palma Islas Baleares 07013",
    "addr:housenumber":"18",
    "addr:postcode":"07013",
    "addr:street":"Carrer De Industria",
    "iso:country":"ES",
    "sg:address":"Carrer de Industria, 18",
    "sg:city":"Palma",
    "sg:orig_category":"Agencias De Trabajo Temporal",
    "sg:phone":"+34 971 78 06 76",
    "sg:postcode":"07013",
    "sg:province":"Islas Baleares",
    "sg:website":"www.adecco.es",
    "wof:name":"Adecco E.t.t. S.a.",
    "wof:placetype":"venue"
},
  "geometry": {"coordinates":[2.6388363838,39.574382782],"type":"Point"}
}