{
  "type": "Feature",
  "properties": {
    "iso:country":"ES",
    "sg:address":"Calle de Eladio Laredo, 7",
    "sg:city":"Castro Urdiales",
    "sg:orig_category":"Inform\u00c1tica, Ofim\u00c1tica (estudios, Asesor\u00cda, Ingenier\u00cda, Formaci\u00d3n)",
    "sg:phone":"+34 942 86 27 01",
    "sg:postcode":"39700",
    "sg:province":"Cantabria",
    "wof:name":"Beep Castro S.l.",
    "wof:placetype":"venue"
},
  "geometry": {"coordinates":[-3.2211840153,43.382938385],"type":"Point"}
}