{
  "type": "Feature",
  "properties": {
    "iso:country":"ES",
    "sg:address":"Calle de Ruzafa, 54",
    "sg:city":"Valencia",
    "sg:orig_category":"Bisuter\u00cda, Joyer\u00cda, Relojer\u00cda (al Por Menor)",
    "sg:phone":"+34 963 73 31 67",
    "sg:postcode":"46006",
    "sg:province":"Valencia",
    "wof:name":"Roc Villanueva Maria Pilar",
    "wof:placetype":"venue"
},
  "geometry": {"coordinates":[-0.3728249967,39.4636878967],"type":"Point"}
}