{
  "type": "Feature",
  "properties": {
    "addr:full":"Plaz Reina Do\u00d1a Juana (la), 6 Segovia Segovia 40001",
    "addr:housenumber":"6",
    "addr:postcode":"40001",
    "addr:street":"Juana La",
    "iso:country":"ES",
    "sg:address":"Plaz Reina Do\u00d1a Juana (la), 6",
    "sg:city":"Segovia",
    "sg:orig_category":"Cajas De Ahorro",
    "sg:phone":"+34 921 46 28 93",
    "sg:postcode":"40001",
    "sg:province":"Segovia",
    "sg:website":"www.cajasegovia.es",
    "wof:name":"Caja De Ahorros Y Monte De Piedad De Segovia",
    "wof:placetype":"venue"
},
  "geometry": {"coordinates":[-4.120267868,40.9496917725],"type":"Point"}
}