{
  "type": "Feature",
  "properties": {
    "addr:full":"Calle de Samuel Ros, 8 Valencia Valencia 46023",
    "addr:housenumber":"8",
    "addr:postcode":"46023",
    "addr:street":"Calle De Samuel Ros",
    "iso:country":"ES",
    "sg:address":"Calle de Samuel Ros, 8",
    "sg:city":"Valencia",
    "sg:orig_category":"Quincaller\u00cda (al Por Menor)",
    "sg:phone":"+34 963 31 04 44",
    "sg:postcode":"46023",
    "sg:province":"Valencia",
    "wof:name":"Ferreteria El Pilar S.l.",
    "wof:placetype":"venue"
},
  "geometry": {"coordinates":[-0.3459349871,39.4627723694],"type":"Point"}
}