{
  "type": "Feature",
  "properties": {
    "iso:country":"ES",
    "sg:address":"Calle de Serafin Escalante, 8",
    "sg:city":"Torrelavega",
    "sg:orig_category":"Cueros Y Pieles (al Por Mayor)",
    "sg:phone":"+34 942 88 12 50",
    "sg:postcode":"39300",
    "sg:province":"Cantabria",
    "wof:name":"Curtidos Gatoo C.b.",
    "wof:placetype":"venue"
},
  "geometry": {"coordinates":[-4.0489029884,43.3490982056],"type":"Point"}
}