{
  "type": "Feature",
  "properties": {
    "iso:country":"ES",
    "sg:address":"Plaz Clemente Zurita, S/n",
    "sg:city":"Tudela Duero",
    "sg:orig_category":"Carnicer\u00cdas, Carnicer\u00cdas",
    "sg:phone":"+34 983 52 00 46",
    "sg:postcode":"47320",
    "sg:province":"Valladolid",
    "wof:name":"Vela Recio Ricardo",
    "wof:placetype":"venue"
},
  "geometry": {"coordinates":[-4.5745568275,41.5786056519],"type":"Point"}
}