{
  "type": "Feature",
  "properties": {
    "addr:full":"Carrer de Navas De Tolosa, 260 Barcelona Barcelona 08027",
    "addr:housenumber":"260",
    "addr:postcode":"08027",
    "addr:street":"Carrer De Navas De Tolosa",
    "iso:country":"ES",
    "sg:address":"Carrer de Navas De Tolosa, 260",
    "sg:city":"Barcelona",
    "sg:orig_category":"Fabricaci\u00d3n De Moldes Y Modelos",
    "sg:phone":"+34 933 51 59 12",
    "sg:postcode":"08027",
    "sg:province":"Barcelona",
    "wof:name":"Budima S.l.",
    "wof:placetype":"venue"
},
  "geometry": {"coordinates":[2.1884720325,41.4143257141],"type":"Point"}
}