{
  "type": "Feature",
  "properties": {
    "iso:country":"ES",
    "sg:address":"Calle de Argumosa, 14",
    "sg:city":"Madrid",
    "sg:orig_category":"Ropa Para Se\u00d1oras (al Por Menor)",
    "sg:phone":"+34 915 39 58 98",
    "sg:postcode":"28012",
    "sg:province":"Madrid",
    "wof:name":"Romero Fernandez Luisa",
    "wof:placetype":"venue"
},
  "geometry": {"coordinates":[-3.6986160278,40.4080848694],"type":"Point"}
}