{
  "type": "Feature",
  "properties": {
    "iso:country":"ES",
    "sg:address":"Calle de Fueros, 8",
    "sg:city":"Jumilla",
    "sg:orig_category":"Sociedades, Compa\u00d1\u00cdas Aseguradoras",
    "sg:phone":"+34 968 78 03 61",
    "sg:postcode":"30520",
    "sg:province":"Murcia",
    "wof:name":"Gembrok Correduria De Seguros S.l.",
    "wof:placetype":"venue"
},
  "geometry": {"coordinates":[-1.3271466494,38.4731063843],"type":"Point"}
}