{
  "type": "Feature",
  "properties": {
    "addr:full":"Pla\u00c7 Neus, 13 Vilanova I La Geltru Barcelona 08800",
    "addr:housenumber":"13",
    "addr:postcode":"08800",
    "addr:street":"Neus",
    "iso:country":"ES",
    "sg:address":"Pla\u00c7 Neus, 13",
    "sg:city":"Vilanova I La Geltru",
    "sg:orig_category":"Sociedades, Compa\u00d1\u00cdas Aseguradoras",
    "sg:phone":"+34 938 93 32 00",
    "sg:postcode":"08800",
    "sg:province":"Barcelona",
    "wof:name":"Asistencia Sanitaria Colegial S.a.",
    "wof:placetype":"venue"
},
  "geometry": {"coordinates":[1.705232501,41.2381515503],"type":"Point"}
}