{
  "type": "Feature",
  "properties": {
    "iso:country":"ES",
    "sg:address":"Calle de Segovia, 31",
    "sg:city":"Cantalejo",
    "sg:orig_category":"Art\u00cdculos Funerarios (al Por Menor)",
    "sg:phone":"+34 921 52 02 33",
    "sg:postcode":"40320",
    "sg:province":"Segovia",
    "wof:name":"Diego Parra Fernando De",
    "wof:placetype":"venue"
},
  "geometry": {"coordinates":[-3.9294829369,41.2541275024],"type":"Point"}
}