{
  "type": "Feature",
  "properties": {
    "addr:full":"Carr Almogavers, 9 Badalona Barcelona 08915",
    "addr:housenumber":"9",
    "addr:postcode":"08915",
    "addr:street":"Carr Almogavers",
    "iso:country":"ES",
    "sg:address":"Carr Almogavers, 9",
    "sg:city":"Badalona",
    "sg:orig_category":"Fabricaci\u00d3n De Cervezas",
    "sg:phone":"+34 934 65 47 36",
    "sg:postcode":"08915",
    "sg:province":"Barcelona",
    "wof:name":"Font Vella S.a.",
    "wof:placetype":"venue"
},
  "geometry": {"coordinates":[2.2495241165,41.4579925537],"type":"Point"}
}