{
  "type": "Feature",
  "properties": {
    "addr:full":"Calle de La Florida, 46 Vitoria-gasteiz \u00c1lava 01005",
    "addr:housenumber":"46",
    "addr:postcode":"01005",
    "addr:street":"Calle De La Florida",
    "iso:country":"ES",
    "sg:address":"Calle de La Florida, 46",
    "sg:city":"Vitoria-gasteiz",
    "sg:orig_category":"Ropa Para Caballeros (al Por Menor)",
    "sg:phone":"+34 945 23 31 49",
    "sg:postcode":"01005",
    "sg:province":"\u00c1lava",
    "wof:name":"Fernandez Jimenez Jose Antonio",
    "wof:placetype":"venue"
},
  "geometry": {"coordinates":[-2.67030406,42.8427352905],"type":"Point"}
}