{
  "type": "Feature",
  "properties": {
    "iso:country":"ES",
    "sg:address":"Pg Catalunya, 11",
    "sg:city":"Torroella Montgri",
    "sg:orig_category":"Inmobiliaria (agencias)",
    "sg:phone":"+34 972 76 01 34",
    "sg:postcode":"17257",
    "sg:province":"Girona",
    "wof:name":"Dewe Gatford Roberto Miguel",
    "wof:placetype":"venue"
},
  "geometry": {"coordinates":[3.127671957,42.0390739441],"type":"Point"}
}