{
  "type": "Feature",
  "properties": {
    "addr:full":"Calle de General Vara De Rey, 42 Logro\u00f1o La Rioja 26002",
    "addr:housenumber":"42",
    "addr:postcode":"26002",
    "addr:street":"Calle De General Vara De Rey;Rioja",
    "iso:country":"ES",
    "sg:address":"Calle de General Vara De Rey, 42",
    "sg:city":"Logro\u00f1o",
    "sg:orig_category":"Reposter\u00cdas",
    "sg:phone":"+34 941 23 71 05",
    "sg:postcode":"26002",
    "sg:province":"La Rioja",
    "wof:name":"Javier Pastor Balmaseda Y Tres Mas S.cv.",
    "wof:placetype":"venue"
},
  "geometry": {"coordinates":[-2.446023941,42.4603233337],"type":"Point"}
}