{
  "type": "Feature",
  "properties": {
    "iso:country":"ES",
    "sg:address":"Calle de Fajardo El Bravo, S/n",
    "sg:city":"Santiago",
    "sg:orig_category":"M\u00c9dicos: Otorrinolaringolog\u00cda",
    "sg:phone":"+34 968 46 00 55",
    "sg:postcode":"30800",
    "sg:province":"Murcia",
    "wof:name":"Martinez Pelegrin Fulgencio",
    "wof:placetype":"venue"
},
  "geometry": {"coordinates":[-1.6905640364,37.680557251],"type":"Point"}
}