{
  "type": "Feature",
  "properties": {
    "addr:full":"Calle de Zurbaran, 5 Madrid Madrid 28010",
    "addr:housenumber":"5",
    "addr:postcode":"28010",
    "addr:street":"Calle De Zurbaran",
    "iso:country":"ES",
    "sg:address":"Calle de Zurbaran, 5",
    "sg:city":"Madrid",
    "sg:orig_category":"Importaci\u00d3n",
    "sg:phone":"+34 913 10 70 96",
    "sg:postcode":"28010",
    "sg:province":"Madrid",
    "wof:name":"Premium Tobacco Spain Sl",
    "wof:placetype":"venue"
},
  "geometry": {"coordinates":[-3.6950621605,40.4296875],"type":"Point"}
}