{
  "type": "Feature",
  "properties": {
    "addr:full":"Calle de Artesanos, 8 Huelva Huelva 21005",
    "addr:housenumber":"8",
    "addr:postcode":"21005",
    "addr:street":"Calle De Artesanos",
    "iso:country":"ES",
    "sg:address":"Calle de Artesanos, 8",
    "sg:city":"Huelva",
    "sg:orig_category":"Sociedades, Compa\u00d1\u00cdas Aseguradoras",
    "sg:phone":"+34 959 15 54 29",
    "sg:postcode":"21005",
    "sg:province":"Huelva",
    "wof:name":"Motero Y Medel S.l.",
    "wof:placetype":"venue"
},
  "geometry": {"coordinates":[-6.9388589859,37.2775192261],"type":"Point"}
}