{
  "type": "Feature",
  "properties": {
    "addr:full":"Calle de Pilar De Zaragoza, 106 Madrid Madrid 28028",
    "addr:housenumber":"106",
    "addr:postcode":"28028",
    "addr:street":"Calle De Pilar De Zaragoza",
    "iso:country":"ES",
    "sg:address":"Calle de Pilar De Zaragoza, 106",
    "sg:city":"Madrid",
    "sg:orig_category":"Doctores En Medicina",
    "sg:phone":"+34 913 55 06 94",
    "sg:postcode":"28028",
    "sg:province":"Madrid",
    "wof:name":"Pelaez Llovio Angel Rafael",
    "wof:placetype":"venue"
},
  "geometry": {"coordinates":[-3.6745390892,40.4384307861],"type":"Point"}
}