{
  "type": "Feature",
  "properties": {
    "addr:full":"Av. Verge De La Roca, S/n Mont-roig Camp Tarragona 43300",
    "addr:housenumber":"s / n",
    "addr:postcode":"43300",
    "addr:street":"Av. Verge De La Roca;Mont-Roig",
    "iso:country":"ES",
    "sg:address":"Av. Verge De La Roca, S/n",
    "sg:city":"Mont-roig Camp",
    "sg:orig_category":"Promotores Constructores",
    "sg:phone":"+34 977 83 82 62",
    "sg:postcode":"43300",
    "sg:province":"Tarragona",
    "wof:name":"Casas Julve Jose Maria",
    "wof:placetype":"venue"
},
  "geometry": {"coordinates":[0.9596899748,41.0852737427],"type":"Point"}
}