{
  "type": "Feature",
  "properties": {
    "addr:full":"Calle de Alberto Aguilera, 35 Madrid Madrid 28015",
    "addr:housenumber":"35",
    "addr:postcode":"madrid;28015",
    "addr:street":"Calle De Alberto Aguilera",
    "iso:country":"ES",
    "sg:address":"Calle de Alberto Aguilera, 35",
    "sg:city":"Madrid",
    "sg:orig_category":"Camiser\u00cda Y Ropa Interior Masculina (al Por Menor)",
    "sg:phone":"+34 915 48 31 46",
    "sg:postcode":"28015",
    "sg:province":"Madrid",
    "wof:name":"Duiker S.l.",
    "wof:placetype":"venue"
},
  "geometry": {"coordinates":[-3.7136809826,40.4303016663],"type":"Point"}
}