{
  "type": "Feature",
  "properties": {
    "addr:full":"Rua San Antoni\u00d1o, 83 Pontevedra Pontevedra 36002",
    "addr:housenumber":"83",
    "addr:postcode":"36002",
    "addr:street":"Rua San Antonin\u0303O",
    "iso:country":"ES",
    "sg:address":"Rua San Antoni\u00d1o, 83",
    "sg:city":"Pontevedra",
    "sg:orig_category":"Panader\u00cdas, Panader\u00cdas",
    "sg:phone":"+34 986 84 03 14",
    "sg:postcode":"36002",
    "sg:province":"Pontevedra",
    "wof:name":"Crespo Figueroa Ramon",
    "wof:placetype":"venue"
},
  "geometry": {"coordinates":[-8.646569252,42.4342193604],"type":"Point"}
}