{
  "type": "Feature",
  "properties": {
    "addr:full":"C/ Josep Ponsati, 5 Banyoles Girona 17820",
    "addr:housenumber":"5",
    "addr:postcode":"17820",
    "addr:street":"C / Josep Ponsati",
    "iso:country":"ES",
    "sg:address":"C/ Josep Ponsati, 5",
    "sg:city":"Banyoles",
    "sg:orig_category":"Empresas De Carpinter\u00cda De Madera",
    "sg:phone":"+34 972 57 54 73",
    "sg:postcode":"17820",
    "sg:province":"Girona",
    "wof:name":"Fusteria J Pla 2006 S.l.",
    "wof:placetype":"venue"
},
  "geometry": {"coordinates":[2.7730026245,42.1189346313],"type":"Point"}
}