{
  "type": "Feature",
  "properties": {
    "addr:full":"Sol (la Sagrera), 8 Corro D'avall Barcelona 08520",
    "addr:housenumber":"8",
    "addr:postcode":"08520",
    "addr:street":"Sol La Sagrera;D'Avall Barcelona",
    "iso:country":"ES",
    "sg:address":"Sol (la Sagrera), 8",
    "sg:city":"Corro D'avall",
    "sg:orig_category":"Cerrajer\u00cda, Ferrallista",
    "sg:phone":"+34 938 40 14 49",
    "sg:postcode":"08520",
    "sg:province":"Barcelona",
    "wof:name":"Losilla Garcia Agustin",
    "wof:placetype":"venue"
},
  "geometry": {"coordinates":[2.1326889992,41.3870124817],"type":"Point"}
}