{
  "type": "Feature",
  "properties": {
    "iso:country":"ES",
    "sg:address":"Calle de Azabache, 3",
    "sg:city":"Madrid",
    "sg:orig_category":"Ense\u00d1anza: Peluquer\u00cda Est\u00c9tica",
    "sg:phone":"+34 914 71 46 17",
    "sg:postcode":"28019",
    "sg:province":"Madrid",
    "wof:name":"Jimenez Castillo Paulo",
    "wof:placetype":"venue"
},
  "geometry": {"coordinates":[-3.7247138023,40.3920097351],"type":"Point"}
}