{
  "type": "Feature",
  "properties": {
    "addr:full":"Av Sant Iscle, 11 Cerdanyola Valles Barcelona 08290",
    "addr:housenumber":"11",
    "addr:postcode":"08290",
    "addr:street":"Av Sant Iscle;Valles Barcelona",
    "iso:country":"ES",
    "sg:address":"Av Sant Iscle, 11",
    "sg:city":"Cerdanyola Valles",
    "sg:orig_category":"Sociedades, Compa\u00d1\u00cdas Aseguradoras",
    "sg:phone":"+34 935 86 32 36",
    "sg:postcode":"08290",
    "sg:province":"Barcelona",
    "wof:name":"El Hatimi  Abdeslam",
    "wof:placetype":"venue"
},
  "geometry": {"coordinates":[2.1439669132,41.4901428223],"type":"Point"}
}