{
  "type": "Feature",
  "properties": {
    "iso:country":"ES",
    "sg:address":"Calle de Santiago, 70",
    "sg:city":"Almeria",
    "sg:orig_category":"Ense\u00d1anza: Profesiones Art\u00cdsticas",
    "sg:phone":"+34 950 22 60 54",
    "sg:postcode":"04006",
    "sg:province":"Almer\u00eda",
    "wof:name":"Egea Rumi Juan Antonio",
    "wof:placetype":"venue"
},
  "geometry": {"coordinates":[-2.449821949,36.8426055908],"type":"Point"}
}