{
  "type": "Feature",
  "properties": {
    "iso:country":"ES",
    "sg:address":"Carr Isabel Garau, 34",
    "sg:city":"Ca'n Picafort",
    "sg:orig_category":"Ropa Para Ni\u00d1os (al Por Menor)",
    "sg:phone":"+34 971 85 07 70",
    "sg:postcode":"07458",
    "sg:province":"Islas Baleares",
    "wof:name":"Bergas Cladera Maria",
    "wof:placetype":"venue"
},
  "geometry": {"coordinates":[2.9117100239,39.6136398315],"type":"Point"}
}