{
  "type": "Feature",
  "properties": {
    "iso:country":"ES",
    "sg:address":"Calle de Santa Maria, 11",
    "sg:city":"Parra",
    "sg:orig_category":"Iglesia Cat\u00d3lica",
    "sg:phone":"+34 924 68 24 51",
    "sg:postcode":"06176",
    "sg:province":"Badajoz",
    "wof:name":"Parroquia Nuestra Se\u00f1ora De La Asuncion",
    "wof:placetype":"venue"
},
  "geometry": {"coordinates":[-6.6250448227,38.5214233398],"type":"Point"}
}