{
  "type": "Feature",
  "properties": {
    "iso:country":"ES",
    "sg:address":"Ctra Vic, 84",
    "sg:city":"Manresa",
    "sg:orig_category":"Cristaler\u00cdas",
    "sg:phone":"+34 938 74 84 88",
    "sg:postcode":"08241",
    "sg:province":"Barcelona",
    "wof:name":"Roca Bisbal Sebastian",
    "wof:placetype":"venue"
},
  "geometry": {"coordinates":[1.8301379681,41.7287483215],"type":"Point"}
}