{
  "type": "Feature",
  "properties": {
    "addr:full":"Calle de Portman, 12 Union Murcia 30360",
    "addr:housenumber":"12",
    "addr:postcode":"30360",
    "addr:street":"Calle De Portman",
    "iso:country":"ES",
    "sg:address":"Calle de Portman, 12",
    "sg:city":"Union",
    "sg:orig_category":"Sociedades, Compa\u00d1\u00cdas Aseguradoras",
    "sg:phone":"+34 968 54 15 52",
    "sg:postcode":"30360",
    "sg:province":"Murcia",
    "wof:name":"Ros Sanchez Josefa",
    "wof:placetype":"venue"
},
  "geometry": {"coordinates":[-0.8840990067,37.6215133667],"type":"Point"}
}