{
  "type": "Feature",
  "properties": {
    "addr:full":"Del Euro-pque Empresarial, 3 Jerez C\u00e1diz 11407",
    "addr:postcode":"11407",
    "addr:street":"Empresarial",
    "iso:country":"ES",
    "sg:address":"Del Euro-pque Empresarial, 3",
    "sg:city":"Jerez",
    "sg:orig_category":"Centros Empresariales",
    "sg:phone":"+34 956 31 04 25",
    "sg:postcode":"11407",
    "sg:province":"C\u00e1diz",
    "wof:name":"Servicios Tarela S.l.",
    "wof:placetype":"venue"
},
  "geometry": {"coordinates":[-6.0982751846,36.7228431702],"type":"Point"}
}