{
  "type": "Feature",
  "properties": {
    "addr:full":"Calle de Cruz Roja, S/n Linares Ja\u00e9n 23700",
    "addr:housenumber":"s / n",
    "addr:postcode":"23700",
    "addr:street":"Calle De Cruz Roja;Jae\u0301N",
    "iso:country":"ES",
    "sg:address":"Calle de Cruz Roja, S/n",
    "sg:city":"Linares",
    "sg:orig_category":"Centros De Reservas Hoteleras",
    "sg:phone":"+34 953 65 77 08",
    "sg:postcode":"23700",
    "sg:province":"Ja\u00e9n",
    "wof:name":"Pizza Linares S.l.",
    "wof:placetype":"venue"
},
  "geometry": {"coordinates":[-3.6420478821,38.1125907898],"type":"Point"}
}