{
  "type": "Feature",
  "properties": {
    "iso:country":"ES",
    "sg:address":"Avda Andalucia, 24",
    "sg:city":"Ecija",
    "sg:orig_category":"Doctores En Medicina",
    "sg:phone":"+34 954 83 45 17",
    "sg:postcode":"41400",
    "sg:province":"Sevilla",
    "wof:name":"Velasco Cano Juan",
    "wof:placetype":"venue"
},
  "geometry": {"coordinates":[-5.0764460564,37.5379066467],"type":"Point"}
}