{
  "type": "Feature",
  "properties": {
    "addr:full":"Calle de Fundacion Jado, 5 Altzaga Vizcaya 48950",
    "addr:housenumber":"5",
    "addr:postcode":"48950",
    "addr:street":"Calle De Fundacion Jado",
    "iso:country":"ES",
    "sg:address":"Calle de Fundacion Jado, 5",
    "sg:city":"Altzaga",
    "sg:orig_category":"Sindicatos De Trabajadores",
    "sg:phone":"+34 944 67 69 88",
    "sg:postcode":"48950",
    "sg:province":"Vizcaya",
    "wof:name":"Union General De Los Trabajadores De Euskadi",
    "wof:placetype":"venue"
},
  "geometry": {"coordinates":[-2.9766139984,43.3036308289],"type":"Point"}
}