{
  "type": "Feature",
  "properties": {
    "iso:country":"ES",
    "sg:address":"Calle de Rosalia De Castro, 4",
    "sg:city":"Coru\u00d1a",
    "sg:orig_category":"Abogados",
    "sg:phone":"+34 981 22 54 72",
    "sg:postcode":"15004",
    "sg:province":"La Coru\u00f1a",
    "wof:name":"Bello Vazquez Manuel Jose",
    "wof:placetype":"venue"
},
  "geometry": {"coordinates":[-8.4070472717,43.3654937744],"type":"Point"}
}