{
  "type": "Feature",
  "properties": {
    "addr:full":"Rua Elle, 51 Verin Ourense 32600",
    "addr:housenumber":"51",
    "addr:postcode":"32600",
    "addr:street":"Rua Elle",
    "iso:country":"ES",
    "sg:address":"Rua Elle, 51",
    "sg:city":"Verin",
    "sg:orig_category":"Supermercados Y Hipermercados",
    "sg:phone":"+34 988 41 12 14",
    "sg:postcode":"32600",
    "sg:province":"Ourense",
    "wof:name":"Vego Supermercados S.a.",
    "wof:placetype":"venue"
},
  "geometry": {"coordinates":[-7.4403190613,41.9391403198],"type":"Point"}
}