{
  "type": "Feature",
  "properties": {
    "addr:full":"Rua Da Cachurra, 21 Negreira La Coru\u00f1a 15830",
    "addr:housenumber":"21",
    "addr:postcode":"15830",
    "addr:street":"Rua Da Cachurra;La Corun\u0303A",
    "iso:country":"ES",
    "sg:address":"Rua Da Cachurra, 21",
    "sg:city":"Negreira",
    "sg:orig_category":"M\u00c9dicos: Estomatolog\u00cda",
    "sg:phone":"+34 981 88 54 57",
    "sg:postcode":"15830",
    "sg:province":"La Coru\u00f1a",
    "wof:name":"Prieto Barros Carlos Antonio",
    "wof:placetype":"venue"
},
  "geometry": {"coordinates":[-8.7371406555,42.9103927612],"type":"Point"}
}