{
  "type": "Feature",
  "properties": {
    "addr:full":"Calle de Ramon Gallud, 87 Torrevieja Alicante 03180",
    "addr:housenumber":"87",
    "addr:postcode":"03180",
    "addr:street":"Calle De Ramon Gallud",
    "iso:country":"ES",
    "sg:address":"Calle de Ramon Gallud, 87",
    "sg:city":"Torrevieja",
    "sg:orig_category":"Asesor\u00cda Fiscal Y Jur\u00cddica",
    "sg:phone":"+34 965 70 76 12",
    "sg:postcode":"03180",
    "sg:province":"Alicante",
    "wof:name":"Ba\u00f1on Hernandez Jesus Vicente",
    "wof:placetype":"venue"
},
  "geometry": {"coordinates":[-0.678565979,37.9775390625],"type":"Point"}
}