{
  "type": "Feature",
  "properties": {
    "iso:country":"ES",
    "sg:address":"Calle de Autonomia, 2",
    "sg:city":"Bilbao",
    "sg:orig_category":"\u00d3ptica: Instrumentos (fabricaci\u00d3n)",
    "sg:phone":"+34 944 22 25 31",
    "sg:postcode":"48012",
    "sg:province":"Vizcaya",
    "wof:name":"Millan Abad Francisco Javier",
    "wof:placetype":"venue"
},
  "geometry": {"coordinates":[-2.9347221851,43.2573471069],"type":"Point"}
}