{
  "type": "Feature",
  "properties": {
    "iso:country":"ES",
    "sg:address":"Rua Tino Grandio (pintor), 31",
    "sg:city":"Lugo",
    "sg:orig_category":"Confecci\u00d3n (fabricaci\u00d3n, Al Por Mayor)",
    "sg:phone":"+34 982 24 05 76",
    "sg:postcode":"27004",
    "sg:province":"Lugo",
    "wof:name":"Mourenza Neira Maria Pilar",
    "wof:placetype":"venue"
},
  "geometry": {"coordinates":[-7.5622320175,43.0164108276],"type":"Point"}
}