{
  "type": "Feature",
  "properties": {
    "iso:country":"ES",
    "sg:address":"Carrer de Pelai, 10",
    "sg:city":"Barcelona",
    "sg:orig_category":"Administradores De Bienes Y Delegados De Comunidades De Propietarios",
    "sg:phone":"+34 933 02 53 97",
    "sg:postcode":"08001",
    "sg:province":"Barcelona",
    "wof:name":"Sancho Reverter Ramon",
    "wof:placetype":"venue"
},
  "geometry": {"coordinates":[2.1654360294,41.385723114],"type":"Point"}
}