{
  "type": "Feature",
  "properties": {
    "addr:full":"Calle de Salobral B (cha), 24 Madrid Madrid 28041",
    "addr:housenumber":"24",
    "addr:postcode":"madrid;28041",
    "addr:street":"Calle De Salobral B Cha",
    "iso:country":"ES",
    "sg:address":"Calle de Salobral B (cha), 24",
    "sg:city":"Madrid",
    "sg:orig_category":"Venta Al Preg\u00d3n",
    "sg:phone":"+34 913 41 77 82",
    "sg:postcode":"28041",
    "sg:province":"Madrid",
    "wof:name":"Jimenez Amador Juan Antonio",
    "wof:placetype":"venue"
},
  "geometry": {"coordinates":[-3.6990230083,40.3656692505],"type":"Point"}
}