{
  "type": "Feature",
  "properties": {
    "addr:full":"Calle de Antonio Machado, 1 Alcala Henares Madrid 28805",
    "addr:housenumber":"1",
    "addr:postcode":"28805",
    "addr:street":"Calle De Antonio Machado",
    "iso:country":"ES",
    "sg:address":"Calle de Antonio Machado, 1",
    "sg:city":"Alcala Henares",
    "sg:orig_category":"Centros Empresariales",
    "sg:phone":"+34 918 89 31 87",
    "sg:postcode":"28805",
    "sg:province":"Madrid",
    "wof:name":"Residencial Bardaji S.l.",
    "wof:placetype":"venue"
},
  "geometry": {"coordinates":[-3.3618094921,40.4857635498],"type":"Point"}
}