{
  "type": "Feature",
  "properties": {
    "iso:country":"ES",
    "sg:address":"Calle de Quinto De Ebro, 2",
    "sg:city":"Zaragoza",
    "sg:orig_category":"Peluquer\u00cdas, Peluquer\u00cda Mixta",
    "sg:phone":"+34 976 32 67 92",
    "sg:postcode":"50017",
    "sg:province":"Zaragoza",
    "wof:name":"Remiro Ayuda Alicia",
    "wof:placetype":"venue"
},
  "geometry": {"coordinates":[-0.9039298296,41.6481971741],"type":"Point"}
}