{
  "type": "Feature",
  "properties": {
    "addr:full":"Calle de Camilo Jose Cela, S/n Sevilla Sevilla 41018",
    "addr:housenumber":"s / n",
    "addr:postcode":"41018",
    "addr:street":"Calle De Camilo Jose Cela",
    "iso:country":"ES",
    "sg:address":"Calle de Camilo Jose Cela, S/n",
    "sg:city":"Sevilla",
    "sg:orig_category":"Ropa Para Ni\u00d1os (al Por Menor)",
    "sg:phone":"+34 954 64 15 67",
    "sg:postcode":"41018",
    "sg:province":"Sevilla",
    "wof:name":"Sonajero S.l.l",
    "wof:placetype":"venue"
},
  "geometry": {"coordinates":[-5.9774031639,37.380355835],"type":"Point"}
}