{
  "type": "Feature",
  "properties": {
    "addr:full":"Av. Vega, S/n Tres Cantos Madrid 28760",
    "addr:housenumber":"s / n",
    "addr:postcode":"28760",
    "addr:street":"Av. Vega",
    "iso:country":"ES",
    "sg:address":"Av. Vega, S/n",
    "sg:city":"Tres Cantos",
    "sg:orig_category":"Asociaciones Y Clubs Deportivos",
    "sg:phone":"+34 918 03 17 17",
    "sg:postcode":"28760",
    "sg:province":"Madrid",
    "wof:name":"Grupo Cantoblanco Distribucion S.l.",
    "wof:placetype":"venue"
},
  "geometry": {"coordinates":[-3.7139999866,40.6033210754],"type":"Point"}
}