{
  "type": "Feature",
  "properties": {
    "iso:country":"ES",
    "sg:address":"Manuel W Guimbarda, 10",
    "sg:city":"Cartagena",
    "sg:orig_category":"Inform\u00c1tica: Material Y Suministros",
    "sg:phone":"+34 968 50 27 53",
    "sg:postcode":"30204",
    "sg:province":"Murcia",
    "sg:website":"www.jump.es",
    "wof:name":"Jump Ordenadores S.l.",
    "wof:placetype":"venue"
},
  "geometry": {"coordinates":[-0.9862099886,37.6105041504],"type":"Point"}
}