{
  "type": "Feature",
  "properties": {
    "addr:full":"Plaz Ramon Y Cajal, 1 Aguadulce Sevilla 41550",
    "addr:housenumber":"1",
    "addr:postcode":"41550",
    "addr:street":"Ramon Y Cajal",
    "iso:country":"ES",
    "sg:address":"Plaz Ramon Y Cajal, 1",
    "sg:city":"Aguadulce",
    "sg:orig_category":"Administraciones Regionales, Departamentales Y Locales",
    "sg:phone":"+34 954 81 60 21",
    "sg:postcode":"41550",
    "sg:province":"Sevilla",
    "wof:name":"Ayuntamiento De Aguadulce",
    "wof:placetype":"venue"
},
  "geometry": {"coordinates":[-4.9150986671,37.2535400391],"type":"Point"}
}