{
  "type": "Feature",
  "properties": {
    "addr:full":"Calle de Hernan Cortes, 4 Quesa Valencia 46824",
    "addr:housenumber":"4",
    "addr:postcode":"46824",
    "addr:street":"Calle De Hernan Cortes",
    "iso:country":"ES",
    "sg:address":"Calle de Hernan Cortes, 4",
    "sg:city":"Quesa",
    "sg:orig_category":"Abogados",
    "sg:phone":"+34 962 25 63 12",
    "sg:postcode":"46824",
    "sg:province":"Valencia",
    "wof:name":"Ayuntamiento De Quesa",
    "wof:placetype":"venue"
},
  "geometry": {"coordinates":[-0.7404603958,39.1189308167],"type":"Point"}
}