{
  "type": "Feature",
  "properties": {
    "iso:country":"ES",
    "sg:address":"Calle de Maximo Martinez Haro, 15",
    "sg:city":"Bugarra",
    "sg:orig_category":"\u00c1reas De Especies Protegidas, Parques Zool\u00d3gicos",
    "sg:phone":"+34 961 66 03 15",
    "sg:postcode":"46165",
    "sg:province":"Valencia",
    "wof:name":"Antonio Martinez Alimentacion Y Sanidad Animal S.l.",
    "wof:placetype":"venue"
},
  "geometry": {"coordinates":[-0.7627879977,39.618347168],"type":"Point"}
}