{
  "type": "Feature",
  "properties": {
    "iso:country":"ES",
    "sg:address":"Calle de Progreso, 11",
    "sg:city":"Ciudad Real",
    "sg:orig_category":"Molduras, Junquillos, Listones Y Molduras Perforadas",
    "sg:phone":"+34 926 22 50 58",
    "sg:postcode":"13004",
    "sg:province":"Ciudad Real",
    "wof:name":"Puentes Fernandez Francisco",
    "wof:placetype":"venue"
},
  "geometry": {"coordinates":[-3.9243211746,38.9885559082],"type":"Point"}
}