{
  "type": "Feature",
  "properties": {
    "iso:country":"ES",
    "sg:address":"Vilar-vilalonga, 30",
    "sg:city":"Vilar",
    "sg:orig_category":"Bazares, Art\u00cdculos De Limpieza Y De Cocina (al Por Menor)",
    "sg:phone":"+34 986 74 20 05",
    "sg:postcode":"36990",
    "sg:province":"Pontevedra",
    "wof:name":"Agraso Alvarez Ana Belen",
    "wof:placetype":"venue"
},
  "geometry": {"coordinates":[-8.4517526627,42.7405128479],"type":"Point"}
}