{
  "type": "Feature",
  "properties": {
    "addr:full":"Calle de Larga, 22 Vecinos Salamanca 37452",
    "addr:housenumber":"22",
    "addr:postcode":"37452",
    "addr:street":"Calle De Larga",
    "iso:country":"ES",
    "sg:address":"Calle de Larga, 22",
    "sg:city":"Vecinos",
    "sg:orig_category":"Cerrajer\u00cda, Ferrallista",
    "sg:phone":"+34 923 38 22 88",
    "sg:postcode":"37452",
    "sg:province":"Salamanca",
    "wof:name":"Lopez Garcia Jose Maria",
    "wof:placetype":"venue"
},
  "geometry": {"coordinates":[-5.8759679794,40.7792320251],"type":"Point"}
}