{
  "type": "Feature",
  "properties": {
    "iso:country":"ES",
    "sg:address":"Calle de Alonso Quijano, 6",
    "sg:city":"Madrid",
    "sg:orig_category":"Asesor\u00cda Fiscal Y Jur\u00cddica",
    "sg:phone":"+34 913 00 55 03",
    "sg:postcode":"28034",
    "sg:province":"Madrid",
    "wof:name":"Estudio Tributario Garcia S.l.",
    "wof:placetype":"venue"
},
  "geometry": {"coordinates":[-3.6896448135,40.502243042],"type":"Point"}
}