{
  "type": "Feature",
  "properties": {
    "addr:full":"Avda. Carlos Iii, 80 Parador Hortichuelas Almer\u00eda 04720",
    "addr:housenumber":"80",
    "addr:postcode":"04720",
    "addr:street":"Avda. Carlos Iii;Almeri\u0301A",
    "iso:country":"ES",
    "sg:address":"Avda. Carlos Iii, 80",
    "sg:city":"Parador Hortichuelas",
    "sg:orig_category":"Productos Fitosanitarios (negocio, Aplicaci\u00d3n)",
    "sg:phone":"+34 950 34 75 69",
    "sg:postcode":"04720",
    "sg:province":"Almer\u00eda",
    "wof:name":"Agrinova Science S.a.",
    "wof:placetype":"venue"
},
  "geometry": {"coordinates":[-2.5984466076,36.8086280823],"type":"Point"}
}