{
  "type": "Feature",
  "properties": {
    "iso:country":"ES",
    "sg:address":"Calle de Luisos (los), 26",
    "sg:city":"Alcazares",
    "sg:orig_category":"Cajas Para Embalar",
    "sg:phone":"+34 968 58 28 03",
    "sg:postcode":"30710",
    "sg:province":"Murcia",
    "wof:name":"Cajamar",
    "wof:placetype":"venue"
},
  "geometry": {"coordinates":[-0.8497369885,37.7389717102],"type":"Point"}
}