{
  "type": "Feature",
  "properties": {
    "iso:country":"ES",
    "sg:address":"Plaz Pio Xii, 3",
    "sg:city":"Palencia",
    "sg:orig_category":"M\u00c9dicos: Estomatolog\u00cda",
    "sg:phone":"+34 979 72 98 20",
    "sg:postcode":"34002",
    "sg:province":"Palencia",
    "wof:name":"Junco Almodovar Manuel",
    "wof:placetype":"venue"
},
  "geometry": {"coordinates":[-4.531047821,42.0051116943],"type":"Point"}
}