{
  "type": "Feature",
  "properties": {
    "iso:country":"ES",
    "sg:address":"Calle de Secoya, 16",
    "sg:city":"Sevilla",
    "sg:orig_category":"Chapister\u00cda",
    "sg:phone":"+34 954 51 63 53",
    "sg:postcode":"41020",
    "sg:province":"Sevilla",
    "wof:name":"Talleres Autopista Pina S.l.u",
    "wof:placetype":"venue"
},
  "geometry": {"coordinates":[-5.9333248138,37.4099082947],"type":"Point"}
}