{
  "type": "Feature",
  "properties": {
    "addr:full":"Ctra Artica, 46 Artica Navarra 31013",
    "addr:housenumber":"46",
    "addr:postcode":"31013",
    "addr:street":"Ctra Artica",
    "iso:country":"ES",
    "sg:address":"Ctra Artica, 46",
    "sg:city":"Artica",
    "sg:orig_category":"Colchones (fabricaci\u00d3n, Al Por Mayor, Al Por Menor)",
    "sg:phone":"+34 948 14 29 04",
    "sg:postcode":"31013",
    "sg:province":"Navarra",
    "wof:name":"Adan Mediavilla Ruben",
    "wof:placetype":"venue"
},
  "geometry": {"coordinates":[-1.6537520885,42.8358840942],"type":"Point"}
}