{
  "type": "Feature",
  "properties": {
    "addr:full":"Ctra Santa Catalina, 2 Huerta De La Alberca Murcia 30150",
    "addr:housenumber":"2",
    "addr:postcode":"30150",
    "addr:street":"Ctra Santa Catalina",
    "iso:country":"ES",
    "sg:address":"Ctra Santa Catalina, 2",
    "sg:city":"Huerta De La Alberca",
    "sg:orig_category":"Distribuci\u00d3n De Petr\u00d3leo Y Derivados",
    "sg:phone":"+34 968 84 02 61",
    "sg:postcode":"30150",
    "sg:province":"Murcia",
    "wof:name":"Repsol Ypf S.a.",
    "wof:placetype":"venue"
},
  "geometry": {"coordinates":[-1.1325449944,37.942855835],"type":"Point"}
}