{
  "type": "Feature",
  "properties": {
    "addr:full":"Avda Concha Espina, 14 Madrid Madrid 28036",
    "addr:housenumber":"14",
    "addr:postcode":"madrid;28036",
    "addr:street":"Avda Concha Espina",
    "iso:country":"ES",
    "sg:address":"Avda Concha Espina, 14",
    "sg:city":"Madrid",
    "sg:orig_category":"Procuradores",
    "sg:phone":"+34 915 61 01 08",
    "sg:postcode":"28036",
    "sg:province":"Madrid",
    "wof:name":"Calatrava Gil Esther Lucia",
    "wof:placetype":"venue"
},
  "geometry": {"coordinates":[-3.6867830753,40.4517326355],"type":"Point"}
}