{
  "type": "Feature",
  "properties": {
    "addr:full":"Rua Velazquez Moreno, 3 Vigo Pontevedra 36201",
    "addr:housenumber":"3",
    "addr:postcode":"36201",
    "addr:street":"Rua Velazquez Moreno",
    "iso:country":"ES",
    "sg:address":"Rua Velazquez Moreno, 3",
    "sg:city":"Vigo",
    "sg:orig_category":"Asesor\u00cdas Y Estudios Financieros",
    "sg:phone":"+34 986 43 66 61",
    "sg:postcode":"36201",
    "sg:province":"Pontevedra",
    "wof:name":"Barreras Vazquez Salvador",
    "wof:placetype":"venue"
},
  "geometry": {"coordinates":[-8.7215709686,42.2387771606],"type":"Point"}
}