{
  "type": "Feature",
  "properties": {
    "iso:country":"ES",
    "sg:address":"Calle de Cesio, 1",
    "sg:city":"Fuenlabrada",
    "sg:orig_category":"Transporte En General",
    "sg:phone":"+34 916 42 00 27",
    "sg:postcode":"28946",
    "sg:province":"Madrid",
    "wof:name":"Tosca P.m. S.l.",
    "wof:placetype":"venue"
},
  "geometry": {"coordinates":[-3.7632818222,40.2693748474],"type":"Point"}
}