{
  "type": "Feature",
  "properties": {
    "addr:full":"Ctra Ojen, 6 Marbella M\u00e1laga 29600",
    "addr:housenumber":"6",
    "addr:postcode":"29600",
    "addr:street":"Ctra Ojen;Ma\u0301Laga",
    "iso:country":"ES",
    "sg:address":"Ctra Ojen, 6",
    "sg:city":"Marbella",
    "sg:orig_category":"Mec\u00c1nico Del Autom\u00d3vil",
    "sg:phone":"+34 952 77 40 82",
    "sg:postcode":"29600",
    "sg:province":"M\u00e1laga",
    "wof:name":"Perez Luque Manuel",
    "wof:placetype":"venue"
},
  "geometry": {"coordinates":[-4.8788700104,36.5128593445],"type":"Point"}
}