{
  "type": "Feature",
  "properties": {
    "iso:country":"ES",
    "sg:address":"S. Pere Roda, S/n",
    "sg:city":"Porqueres",
    "sg:orig_category":"Electricidad: Instaladores",
    "sg:phone":"+34 972 57 12 27",
    "sg:postcode":"17834",
    "sg:province":"Girona",
    "wof:name":"Insipa S.l.",
    "wof:placetype":"venue"
},
  "geometry": {"coordinates":[2.764480114,42.0982017517],"type":"Point"}
}