{
  "type": "Feature",
  "properties": {
    "iso:country":"ES",
    "sg:address":"Calle de Privilegio De La Union, 46",
    "sg:city":"Zaragoza",
    "sg:orig_category":"Molduras, Junquillos, Listones Y Molduras Perforadas",
    "sg:phone":"+34 976 41 10 00",
    "sg:postcode":"50013",
    "sg:province":"Zaragoza",
    "wof:name":"Lucea Felix Vanessa",
    "wof:placetype":"venue"
},
  "geometry": {"coordinates":[-0.8700640202,41.6414031982],"type":"Point"}
}