{
  "type": "Feature",
  "properties": {
    "iso:country":"ES",
    "sg:address":"Tamallancos, S/n",
    "sg:city":"Tamallancos",
    "sg:orig_category":"Negocio De Madera",
    "sg:phone":"+34 988 27 96 90",
    "sg:postcode":"32102",
    "sg:province":"Ourense",
    "wof:name":"Molduras Orense S.a.",
    "wof:placetype":"venue"
},
  "geometry": {"coordinates":[-7.9020338058,42.426574707],"type":"Point"}
}