{
  "type": "Feature",
  "properties": {
    "iso:country":"ES",
    "sg:address":"Calle de Reina Sofia, 1",
    "sg:city":"Mojados",
    "sg:orig_category":"Empresas De Pintura Y Revestimientos",
    "sg:phone":"+34 983 60 73 62",
    "sg:postcode":"47250",
    "sg:province":"Valladolid",
    "wof:name":"Apival S.l.",
    "wof:placetype":"venue"
},
  "geometry": {"coordinates":[-4.6618843079,41.4276657104],"type":"Point"}
}