{
  "type": "Feature",
  "properties": {
    "iso:country":"ES",
    "sg:address":"Avda Covelo (do), 3",
    "sg:city":"Covelo",
    "sg:orig_category":"Fabricaci\u00d3n, Venta De Cuadros, Accesorios Para Enmarcar",
    "sg:phone":"+34 986 74 15 11",
    "sg:postcode":"36992",
    "sg:province":"Pontevedra",
    "wof:name":"Balboa Balboa Concepcion",
    "wof:placetype":"venue"
},
  "geometry": {"coordinates":[-8.3665847778,42.216594696],"type":"Point"}
}