{
  "type": "Feature",
  "properties": {
    "addr:full":"Calle de Cuenca, 117 Valencia Valencia 46007",
    "addr:housenumber":"117",
    "addr:postcode":"46007",
    "addr:street":"Calle De Cuenca",
    "iso:country":"ES",
    "sg:address":"Calle de Cuenca, 117",
    "sg:city":"Valencia",
    "sg:orig_category":"Florister\u00cdas",
    "sg:phone":"+34 963 80 12 20",
    "sg:postcode":"46007",
    "sg:province":"Valencia",
    "wof:name":"Marti Sanz Cristina",
    "wof:placetype":"venue"
},
  "geometry": {"coordinates":[-0.3913027048,39.4607391357],"type":"Point"}
}