{
  "type": "Feature",
  "properties": {
    "iso:country":"ES",
    "sg:address":"Calle de Manuel Hernandez Mu\u00d1oz, 21",
    "sg:city":"Santa Brigida",
    "sg:orig_category":"Agencias De Viajes",
    "sg:phone":"+34 928 64 19 00",
    "sg:postcode":"35300",
    "sg:province":"Las Palmas",
    "wof:name":"Aldatours Viajes S.l.",
    "wof:placetype":"venue"
},
  "geometry": {"coordinates":[-15.4982690811,28.0355415344],"type":"Point"}
}