{
  "type": "Feature",
  "properties": {
    "addr:full":"Calle de Colombia, 4 Cordoba C\u00f3rdoba 14006",
    "addr:housenumber":"4",
    "addr:postcode":"14006",
    "addr:street":"Calle De Colombia;Co\u0301Rdoba",
    "iso:country":"ES",
    "sg:address":"Calle de Colombia, 4",
    "sg:city":"Cordoba",
    "sg:orig_category":"Peluqueros: De Se\u00d1oras",
    "sg:phone":"+34 957 28 15 76",
    "sg:postcode":"14006",
    "sg:province":"C\u00f3rdoba",
    "wof:name":"Pastorini Peluquero S.l.",
    "wof:placetype":"venue"
},
  "geometry": {"coordinates":[-4.7851586342,37.8953361511],"type":"Point"}
}