{
  "type": "Feature",
  "properties": {
    "addr:full":"Plaz Andalucia, 2 Ubeda Ja\u00e9n 23400",
    "addr:housenumber":"2",
    "addr:postcode":"23400",
    "addr:street":"Plaz Andalucia;Jae\u0301N",
    "iso:country":"ES",
    "sg:address":"Plaz Andalucia, 2",
    "sg:city":"Ubeda",
    "sg:orig_category":"Mercer\u00cda, Lencer\u00cda (al Por Menor)",
    "sg:phone":"+34 953 75 47 48",
    "sg:postcode":"23400",
    "sg:province":"Ja\u00e9n",
    "wof:name":"Godoy Moreno Mariana",
    "wof:placetype":"venue"
},
  "geometry": {"coordinates":[-3.376830101,38.0137939453],"type":"Point"}
}