{
  "type": "Feature",
  "properties": {
    "iso:country":"ES",
    "sg:address":"Av Francesc Macia, S/n",
    "sg:city":"Sabadell",
    "sg:orig_category":"Librer\u00cdas",
    "sg:phone":"+34 937 23 43 59",
    "sg:postcode":"08206",
    "sg:province":"Barcelona",
    "wof:name":"Freak S.l.",
    "wof:placetype":"venue"
},
  "geometry": {"coordinates":[2.0978689194,41.5524024963],"type":"Point"}
}