{
  "type": "Feature",
  "properties": {
    "addr:full":"Pl. Esglesia, 25 Binissalem Islas Baleares 07350",
    "addr:housenumber":"25",
    "addr:postcode":"07350",
    "addr:street":"Pl. Esglesia",
    "iso:country":"ES",
    "sg:address":"Pl. Esglesia, 25",
    "sg:city":"Binissalem",
    "sg:orig_category":"Molduras, Junquillos, Listones Y Molduras Perforadas",
    "sg:phone":"+34 971 51 11 36",
    "sg:postcode":"07350",
    "sg:province":"Islas Baleares",
    "wof:name":"Alomar Carbonell Antonia",
    "wof:placetype":"venue"
},
  "geometry": {"coordinates":[2.8426105976,39.6888465881],"type":"Point"}
}