{
  "type": "Feature",
  "properties": {
    "addr:full":"Calle de Almendros, Los, 4 Calpe Alicante 03710",
    "addr:housenumber":"4",
    "addr:postcode":"03710",
    "addr:street":"Calle De Almendros Los",
    "iso:country":"ES",
    "sg:address":"Calle de Almendros, Los, 4",
    "sg:city":"Calpe",
    "sg:orig_category":"Alquiler De V\u00cddeo",
    "sg:phone":"+34 965 83 03 34",
    "sg:postcode":"03710",
    "sg:province":"Alicante",
    "wof:name":"Dream Films S.l.",
    "wof:placetype":"venue"
},
  "geometry": {"coordinates":[0.0463918,38.644405365],"type":"Point"}
}