{
  "type": "Feature",
  "properties": {
    "iso:country":"ES",
    "sg:address":"Carrer de Carrer de Pto Rico, S/n",
    "sg:city":"Puerto Rico",
    "sg:orig_category":"Bares, Piano",
    "sg:phone":"+34 928 56 21 61",
    "sg:postcode":"35130",
    "sg:province":"Las Palmas",
    "wof:name":"Cozza  Vito",
    "wof:placetype":"venue"
},
  "geometry": {"coordinates":[-15.7087993622,27.7916240692],"type":"Point"}
}