{
  "type": "Feature",
  "properties": {
    "addr:full":"Calle de Real, 3 Roda Andalucia Sevilla 41590",
    "addr:housenumber":"3",
    "addr:postcode":"41590",
    "addr:street":"Calle De Real",
    "iso:country":"ES",
    "sg:address":"Calle de Real, 3",
    "sg:city":"Roda Andalucia",
    "sg:orig_category":"Molduras, Junquillos, Listones Y Molduras Perforadas",
    "sg:phone":"+34 954 01 67 81",
    "sg:postcode":"41590",
    "sg:province":"Sevilla",
    "wof:name":"Bar El Segundo S.l",
    "wof:placetype":"venue"
},
  "geometry": {"coordinates":[-4.7802009583,37.2004814148],"type":"Point"}
}