{
  "type": "Feature",
  "properties": {
    "iso:country":"ES",
    "sg:address":"Conqueridor, S/n",
    "sg:city":"Banyeres Mariola",
    "sg:orig_category":"Hilaturas, Hilos Y Actividades Relacionadas",
    "sg:phone":"+34 965 56 75 73",
    "sg:postcode":"03450",
    "sg:province":"Alicante",
    "wof:name":"Doblados Llopis Cb",
    "wof:placetype":"venue"
},
  "geometry": {"coordinates":[-0.6574190259,38.7117500305],"type":"Point"}
}