{
  "type": "Feature",
  "properties": {
    "iso:country":"ES",
    "sg:address":"Calle de Ciudad Jardin, 9",
    "sg:city":"San Vicente Del Raspeig-sant Vicent Del Raspeig",
    "sg:orig_category":"Adaptaciones, Acondicionamientos Especiales Para Veh\u00cdculos, Veh\u00cdculos Industriales",
    "sg:phone":"+34 965 66 73 35",
    "sg:postcode":"03690",
    "sg:province":"Alicante",
    "wof:name":"Bernabeu Alcaraz Vicente",
    "wof:placetype":"venue"
},
  "geometry": {"coordinates":[-0.516692996,38.3929405212],"type":"Point"}
}