{
  "type": "Feature",
  "properties": {
    "iso:country":"ES",
    "sg:address":"Calle de Calvo Sotelo, 6",
    "sg:city":"Tineo",
    "sg:orig_category":"Relojer\u00cda (al Por Menor, Reparaci\u00d3n)",
    "sg:phone":"+34 985 80 01 07",
    "sg:postcode":"33870",
    "sg:province":"Asturias",
    "wof:name":"Feito Boto Faustino",
    "wof:placetype":"venue"
},
  "geometry": {"coordinates":[-6.416703701,43.334186554],"type":"Point"}
}