{
  "type": "Feature",
  "properties": {
    "iso:country":"ES",
    "sg:address":"Avda Veinticinco De Julio, 61",
    "sg:city":"Santa Cruz De Tenerife",
    "sg:orig_category":"Agencias Y Agentes Comerciales, Representantes",
    "sg:phone":"+34 922 24 05 29",
    "sg:postcode":"38004",
    "sg:province":"Santa Cruz De Tenerife",
    "wof:name":"Dominguez Ramirez Manuel",
    "wof:placetype":"venue"
},
  "geometry": {"coordinates":[-16.2564601898,28.4795894623],"type":"Point"}
}