{
  "type": "Feature",
  "properties": {
    "addr:full":"Avda Menendez Pelayo, 19 Sevilla Sevilla 41003",
    "addr:housenumber":"19",
    "addr:postcode":"41003",
    "addr:street":"Avda Menendez Pelayo",
    "iso:country":"ES",
    "sg:address":"Avda Menendez Pelayo, 19",
    "sg:city":"Sevilla",
    "sg:orig_category":"Doctores En Medicina",
    "sg:phone":"+34 954 41 62 92",
    "sg:postcode":"41003",
    "sg:province":"Sevilla",
    "wof:name":"Pizarro Castro Jose Luis",
    "wof:placetype":"venue"
},
  "geometry": {"coordinates":[-5.9856948853,37.3865585327],"type":"Point"}
}