{
  "type": "Feature",
  "properties": {
    "addr:full":"Pl. Moss\u00e8n Lloansi, S/n Platja Aro Girona 17250",
    "addr:housenumber":"s / n",
    "addr:postcode":"17250",
    "addr:street":"Pl. Mosse\u0300N Lloansi",
    "iso:country":"ES",
    "sg:address":"Pl. Moss\u00e8n Lloansi, S/n",
    "sg:city":"Platja Aro",
    "sg:orig_category":"Iglesia Cat\u00d3lica",
    "sg:phone":"+34 972 81 86 47",
    "sg:postcode":"17250",
    "sg:province":"Girona",
    "wof:name":"Bisbat De Girona",
    "wof:placetype":"venue"
},
  "geometry": {"coordinates":[3.0639550686,41.8142547607],"type":"Point"}
}