{
  "type": "Feature",
  "properties": {
    "addr:full":"Moral, S/n Santiago Asturias 33518",
    "addr:housenumber":"s / n",
    "addr:postcode":"33518",
    "addr:street":"Moral",
    "iso:country":"ES",
    "sg:address":"Moral, S/n",
    "sg:city":"Santiago",
    "sg:orig_category":"Mec\u00c1nico Del Autom\u00d3vil",
    "sg:phone":"+34 985 74 83 99",
    "sg:postcode":"33518",
    "sg:province":"Asturias",
    "wof:name":"Foncueva Solares Luis Alberto",
    "wof:placetype":"venue"
},
  "geometry": {"coordinates":[-5.5597882271,43.4101409912],"type":"Point"}
}