{
  "type": "Feature",
  "properties": {
    "addr:full":"Calle de Pilar De Zaragoza, 75 Madrid Madrid 28028",
    "addr:housenumber":"75",
    "addr:postcode":"madrid;28028",
    "addr:street":"Calle De Pilar De Zaragoza",
    "iso:country":"ES",
    "sg:address":"Calle de Pilar De Zaragoza, 75",
    "sg:city":"Madrid",
    "sg:orig_category":"Electricidad: Equipos Industriales, Componentes (fabricaci\u00d3n)",
    "sg:phone":"+34 917 26 81 99",
    "sg:postcode":"28028",
    "sg:province":"Madrid",
    "wof:name":"Mizher Trade S.l.",
    "wof:placetype":"venue"
},
  "geometry": {"coordinates":[-3.6729130745,40.4367027283],"type":"Point"}
}