{
  "type": "Feature",
  "properties": {
    "iso:country":"ES",
    "sg:address":"Avda Fuensanta (la), 38",
    "sg:city":"Pizarra",
    "sg:orig_category":"Reposter\u00cdas",
    "sg:phone":"+34 952 48 31 92",
    "sg:postcode":"29560",
    "sg:province":"M\u00e1laga",
    "wof:name":"El Molinero De Pizarra S.l.",
    "wof:placetype":"venue"
},
  "geometry": {"coordinates":[-4.707608223,36.7684898376],"type":"Point"}
}