{
  "type": "Feature",
  "properties": {
    "addr:full":"Avda Libia (de), 27 Cordoba C\u00f3rdoba 14010",
    "addr:housenumber":"27",
    "addr:postcode":"14010",
    "addr:street":"Avda Libia De;Co\u0301Rdoba",
    "iso:country":"ES",
    "sg:address":"Avda Libia (de), 27",
    "sg:city":"Cordoba",
    "sg:orig_category":"Albergues",
    "sg:phone":"+34 957 25 10 48",
    "sg:postcode":"14010",
    "sg:province":"C\u00f3rdoba",
    "wof:name":"Suarez Varela Rafael",
    "wof:placetype":"venue"
},
  "geometry": {"coordinates":[-4.7607350349,37.8898468018],"type":"Point"}
}