{
  "type": "Feature",
  "properties": {
    "iso:country":"ES",
    "sg:address":"Carr Caama\u00d1o, 3",
    "sg:city":"Figueres",
    "sg:orig_category":"Mercer\u00cda, Lencer\u00cda (al Por Menor)",
    "sg:phone":"+34 972 50 10 62",
    "sg:postcode":"17600",
    "sg:province":"Girona",
    "wof:name":"Garriga Cros Maria Del Carmen",
    "wof:placetype":"venue"
},
  "geometry": {"coordinates":[2.9632599354,42.2667655945],"type":"Point"}
}