{
  "type": "Feature",
  "properties": {
    "iso:country":"ES",
    "sg:address":"Rua Santa Cristina, 34",
    "sg:city":"Pardavila",
    "sg:orig_category":"Empresas De Carpinter\u00cda",
    "sg:phone":"+34 986 27 96 80",
    "sg:postcode":"36214",
    "sg:province":"Pontevedra",
    "wof:name":"Silva Bande Obdulio",
    "wof:placetype":"venue"
},
  "geometry": {"coordinates":[-8.7059106827,42.2124443054],"type":"Point"}
}