{
  "type": "Feature",
  "properties": {
    "addr:full":"Ctra Alcoy, 56 Banyeres Mariola Alicante 03450",
    "addr:housenumber":"56",
    "addr:postcode":"03450",
    "addr:street":"Ctra Alcoy",
    "iso:country":"ES",
    "sg:address":"Ctra Alcoy, 56",
    "sg:city":"Banyeres Mariola",
    "sg:orig_category":"Moquetas, Alfombras (al Por Menor)",
    "sg:phone":"+34 965 56 63 49",
    "sg:postcode":"03450",
    "sg:province":"Alicante",
    "wof:name":"Latorre Perez Rafael",
    "wof:placetype":"venue"
},
  "geometry": {"coordinates":[-0.6580740213,38.7120857239],"type":"Point"}
}