{
  "type": "Feature",
  "properties": {
    "addr:full":"Carrer de Cardenal Reig, 23 Barcelona Barcelona 08028",
    "addr:housenumber":"23",
    "addr:postcode":"08028",
    "addr:street":"Carrer De Cardenal Reig",
    "iso:country":"ES",
    "sg:address":"Carrer de Cardenal Reig, 23",
    "sg:city":"Barcelona",
    "sg:orig_category":"Empresas De Limpieza",
    "sg:phone":"+34 934 40 14 21",
    "sg:postcode":"08028",
    "sg:province":"Barcelona",
    "wof:name":"Iss Facility Services S.a.",
    "wof:placetype":"venue"
},
  "geometry": {"coordinates":[2.1148209572,41.3779678345],"type":"Point"}
}