{
  "type": "Feature",
  "properties": {
    "addr:full":"Calle de Canalejas, 10 Agost Alicante 03698",
    "addr:housenumber":"10",
    "addr:postcode":"03698",
    "addr:street":"Calle De Canalejas",
    "iso:country":"ES",
    "sg:address":"Calle de Canalejas, 10",
    "sg:city":"Agost",
    "sg:orig_category":"Alimentaci\u00d3n General (al Por Menor)",
    "sg:phone":"+34 965 69 13 57",
    "sg:postcode":"03698",
    "sg:province":"Alicante",
    "wof:name":"Gomis Vicedo Dolores",
    "wof:placetype":"venue"
},
  "geometry": {"coordinates":[-0.6389560103,38.4391822815],"type":"Point"}
}