{
  "type": "Feature",
  "properties": {
    "iso:country":"ES",
    "sg:address":"Calle de Pintor Vergara, 4",
    "sg:city":"Castellon",
    "sg:orig_category":"Consultas M\u00c9dicas",
    "sg:phone":"+34 964 25 61 21",
    "sg:postcode":"12004",
    "sg:province":"Castell\u00f3n",
    "wof:name":"Raro Rueda Pilar",
    "wof:placetype":"venue"
},
  "geometry": {"coordinates":[-0.0435400009,39.9899101257],"type":"Point"}
}