{
  "type": "Feature",
  "properties": {
    "iso:country":"ES",
    "sg:address":"Calle de Gravina, 10",
    "sg:city":"Madrid",
    "sg:orig_category":"Caf\u00c9s, Bares, Cervecer\u00cdas",
    "sg:phone":"+34 915 22 21 43",
    "sg:postcode":"28004",
    "sg:province":"Madrid",
    "wof:name":"Pereira Da Silva Manuel Aparecido",
    "wof:placetype":"venue"
},
  "geometry": {"coordinates":[-3.6976792812,40.4230194092],"type":"Point"}
}