{
  "type": "Feature",
  "properties": {
    "iso:country":"ES",
    "sg:address":"Carrer de Sabino Arana, 50",
    "sg:city":"Barcelona",
    "sg:classifiers":[
        {
            "category":"Personal",
            "subcategory":"Barber",
            "type":"Services"
        }
    ],
    "sg:phone":"+34 933 39 51 57",
    "sg:postcode":"08028",
    "sg:province":"Barcelona",
    "sg:tags":[
        "caballeros",
        "de",
        "peluqueros"
    ],
    "wof:name":"Argiles Sola Antonio",
    "wof:placetype":"venue"
},
  "geometry": {"coordinates":[2.1240942478,41.3861999512],"type":"Point"}
}