{
  "type": "Feature",
  "properties": {
    "addr:full":"Carrer de Diputacio, 238 Barcelona Barcelona 08007",
    "addr:housenumber":"238",
    "addr:postcode":"08007",
    "addr:street":"Carrer De Diputacio",
    "iso:country":"ES",
    "sg:address":"Carrer de Diputacio, 238",
    "sg:city":"Barcelona",
    "sg:orig_category":"Inform\u00c1tica: Consultores",
    "sg:phone":"+34 934 12 40 67",
    "sg:postcode":"08007",
    "sg:province":"Barcelona",
    "wof:name":"Biometric Technologies S.l.",
    "wof:placetype":"venue"
},
  "geometry": {"coordinates":[2.1647830009,41.388507843],"type":"Point"}
}