{
  "type": "Feature",
  "properties": {
    "iso:country":"ES",
    "sg:address":"Calle de Duques De Najera, 25",
    "sg:city":"Logro\u00f1o",
    "sg:orig_category":"Ense\u00d1anza: Comercio, Gesti\u00d3n, Inform\u00c1tica",
    "sg:phone":"+34 941 20 56 92",
    "sg:postcode":"26002",
    "sg:province":"La Rioja",
    "wof:name":"H.d.c. Informatica S.l.",
    "wof:placetype":"venue"
},
  "geometry": {"coordinates":[-2.4539117813,42.4591331482],"type":"Point"}
}