{
  "type": "Feature",
  "properties": {
    "addr:full":"Pol Ind La Estrella, S/n Coria Rio Sevilla 41100",
    "addr:housenumber":"s",
    "addr:postcode":"41100",
    "addr:street":"/ N",
    "iso:country":"ES",
    "sg:address":"Pol Ind La Estrella, S/n",
    "sg:city":"Coria Rio",
    "sg:orig_category":"Empresas De Carpinter\u00cda De Madera",
    "sg:phone":"+34 954 77 36 51",
    "sg:postcode":"41100",
    "sg:province":"Sevilla",
    "wof:name":"Romero Maldonado Campos Sca En Constitucion",
    "wof:placetype":"venue"
},
  "geometry": {"coordinates":[-6.0509738922,37.2873153687],"type":"Point"}
}