{
  "type": "Feature",
  "properties": {
    "iso:country":"ES",
    "sg:address":"Calle de Ponce De Minerva, 9",
    "sg:city":"Le\u00f3n",
    "sg:orig_category":"Tapicer\u00cdas",
    "sg:phone":"+34 987 20 67 06",
    "sg:postcode":"24003",
    "sg:province":"Le\u00f3n",
    "wof:name":"Garcia Lopez Jaime",
    "wof:placetype":"venue"
},
  "geometry": {"coordinates":[-5.5660591125,42.59349823],"type":"Point"}
}