{
  "type": "Feature",
  "properties": {
    "addr:full":"Calle de San Antonio, 11 Yecla Murcia 30510",
    "addr:housenumber":"11",
    "addr:postcode":"30510",
    "addr:street":"Calle De San Antonio",
    "iso:country":"ES",
    "sg:address":"Calle de San Antonio, 11",
    "sg:city":"Yecla",
    "sg:classifiers":[
        {
            "category":"Autos & Motor Vehicles",
            "subcategory":"Automobile Sales",
            "type":"Retail Goods"
        }
    ],
    "sg:phone":"+34 968 79 09 84",
    "sg:postcode":"30510",
    "sg:province":"Murcia",
    "wof:name":"Autoescuela Yecla S.l.",
    "wof:placetype":"venue"
},
  "geometry": {"coordinates":[-1.1145700216,38.6132965088],"type":"Point"}
}