{
  "type": "Feature",
  "properties": {
    "iso:country":"ES",
    "sg:address":"Primero De Mayo, 7",
    "sg:city":"Las Pinedas",
    "sg:orig_category":"Venta Al Preg\u00d3n",
    "sg:phone":"+34 957 30 14 03",
    "sg:postcode":"14111",
    "sg:province":"C\u00f3rdoba",
    "wof:name":"Carmona Costa Manuel",
    "wof:placetype":"venue"
},
  "geometry": {"coordinates":[-4.948143959,37.7091178894],"type":"Point"}
}