{
  "type": "Feature",
  "properties": {
    "iso:country":"ES",
    "sg:address":"Calle de General Alava, 16",
    "sg:city":"Vitoria-gasteiz",
    "sg:orig_category":"Bancos",
    "sg:phone":"+34 945 13 22 62",
    "sg:postcode":"01005",
    "sg:province":"\u00c1lava",
    "wof:name":"Deutsche Bank S.a.e.",
    "wof:placetype":"venue"
},
  "geometry": {"coordinates":[-2.6716320515,42.8447761536],"type":"Point"}
}