{
  "type": "Feature",
  "properties": {
    "iso:country":"ES",
    "sg:address":"Calle de Elizkale, 19",
    "sg:city":"Zumarraga",
    "sg:orig_category":"Abogados",
    "sg:phone":"+34 943 72 31 01",
    "sg:postcode":"20700",
    "sg:province":"Guip\u00f9zcoa",
    "wof:name":"Mateo Criado Luis Miguel",
    "wof:placetype":"venue"
},
  "geometry": {"coordinates":[-2.3129029274,43.0882453918],"type":"Point"}
}