{
  "type": "Feature",
  "properties": {
    "iso:country":"ES",
    "sg:address":"Avda Martinez De Velasco, 35",
    "sg:city":"Huesca",
    "sg:orig_category":"Reposter\u00cdas",
    "sg:phone":"+34 974 21 11 54",
    "sg:postcode":"22004",
    "sg:province":"Huesca",
    "wof:name":"Olivan Bistuer Luis Fernando",
    "wof:placetype":"venue"
},
  "geometry": {"coordinates":[-0.4144900143,42.1328392029],"type":"Point"}
}