{
  "type": "Feature",
  "properties": {
    "iso:country":"ES",
    "sg:address":"Calle de Benito Gutierrez, S/n",
    "sg:city":"Papatrigo",
    "sg:orig_category":"Frutas Y Legumbres Secas (al Por Mayor)",
    "sg:phone":"+34 920 24 13 63",
    "sg:postcode":"05359",
    "sg:province":"\u00c1vila",
    "wof:name":"Ferradal Cdad",
    "wof:placetype":"venue"
},
  "geometry": {"coordinates":[-4.8323259354,40.8659057617],"type":"Point"}
}