{
  "type": "Feature",
  "properties": {
    "addr:full":"Rua Coru\u00d1a, 44 Vigo Pontevedra 36208",
    "addr:housenumber":"44",
    "addr:postcode":"36208",
    "addr:street":"Rua Corun\u0303A",
    "iso:country":"ES",
    "sg:address":"Rua Coru\u00d1a, 44",
    "sg:city":"Vigo",
    "sg:orig_category":"Caf\u00c9s, Bares, Cervecer\u00cdas",
    "sg:phone":"+34 986 20 96 53",
    "sg:postcode":"36208",
    "sg:province":"Pontevedra",
    "wof:name":"Perez Ramirez Antonio",
    "wof:placetype":"venue"
},
  "geometry": {"coordinates":[-8.7347898483,42.2232170105],"type":"Point"}
}