{
  "type": "Feature",
  "properties": {
    "addr:full":"Plaz San Sebastian, 5 Almeria Almer\u00eda 04003",
    "addr:housenumber":"5",
    "addr:postcode":"04003",
    "addr:street":"Plaz San Sebastian",
    "iso:country":"ES",
    "sg:address":"Plaz San Sebastian, 5",
    "sg:city":"Almeria",
    "sg:orig_category":"Laboratorios Y Cl\u00cdnicas Veterinarias",
    "sg:phone":"+34 950 23 18 18",
    "sg:postcode":"04003",
    "sg:province":"Almer\u00eda",
    "wof:name":"Ruiz Valverde Juan",
    "wof:placetype":"venue"
},
  "geometry": {"coordinates":[-2.4608390331,36.8422698975],"type":"Point"}
}