{
  "type": "Feature",
  "properties": {
    "addr:full":"Calle de Portuetxe, 47 Donostia-san Sebastian Guip\u00f9zcoa 20018",
    "addr:housenumber":"47",
    "addr:postcode":"20018",
    "addr:street":"Calle De Portuetxe",
    "iso:country":"ES",
    "sg:address":"Calle de Portuetxe, 47",
    "sg:city":"Donostia-san Sebastian",
    "sg:orig_category":"Asesor\u00cda Sobre Comunicaci\u00d3n De Empresas",
    "sg:phone":"+34 943 31 51 41",
    "sg:postcode":"20018",
    "sg:province":"Guip\u00f9zcoa",
    "wof:name":"Asistencia Tecnica Industrial S.a.e.",
    "wof:placetype":"venue"
},
  "geometry": {"coordinates":[-2.0141232014,43.3013000488],"type":"Point"}
}