{
  "type": "Feature",
  "properties": {
    "addr:full":"Carrer de Paris, 123 Barcelona Barcelona 08036",
    "addr:housenumber":"123",
    "addr:postcode":"08036",
    "addr:street":"Carrer De Paris",
    "iso:country":"ES",
    "sg:address":"Carrer de Paris, 123",
    "sg:city":"Barcelona",
    "sg:orig_category":"Agentes, Concesionarios Y Sucursales De Veh\u00cdculos",
    "sg:phone":"+34 934 10 38 38",
    "sg:postcode":"08036",
    "sg:province":"Barcelona",
    "sg:website":"www.toyota.es",
    "wof:name":"Team's Motor S.a.",
    "wof:placetype":"venue"
},
  "geometry": {"coordinates":[2.1485710144,41.3903045654],"type":"Point"}
}