{
  "type": "Feature",
  "properties": {
    "iso:country":"ES",
    "sg:address":"Ptda Matola, 244",
    "sg:city":"Matola",
    "sg:orig_category":"Confecci\u00d3n De Zapatos",
    "sg:phone":"+34 966 63 38 61",
    "sg:postcode":"03296",
    "sg:province":"Alicante",
    "wof:name":"Calzados Drima S.l",
    "wof:placetype":"venue"
},
  "geometry": {"coordinates":[-0.7447530031,38.227268219],"type":"Point"}
}