{
  "type": "Feature",
  "properties": {
    "addr:full":"Pg Carretera, 39 Benidorm Alicante 03500",
    "addr:housenumber":"39",
    "addr:postcode":"03500",
    "addr:street":"Carretera",
    "iso:country":"ES",
    "sg:address":"Pg Carretera, 39",
    "sg:city":"Benidorm",
    "sg:orig_category":"Inform\u00c1tica (estudios, Servicios, Asesor\u00cda, Formaci\u00d3n)",
    "sg:phone":"+34 966 83 01 27",
    "sg:postcode":"03500",
    "sg:province":"Alicante",
    "sg:website":"www.lcsistemas.com",
    "wof:name":"Lc Sistemas S.l.",
    "wof:placetype":"venue"
},
  "geometry": {"coordinates":[-0.1321029961,38.5365562439],"type":"Point"}
}