{
  "type": "Feature",
  "properties": {
    "iso:country":"ES",
    "sg:address":"Calle de Carcel Vieja, 11",
    "sg:city":"Valdepe\u00f1as",
    "sg:orig_category":"M\u00c9dicos: Estomatolog\u00cda",
    "sg:phone":"+34 926 32 19 50",
    "sg:postcode":"13300",
    "sg:province":"Ciudad Real",
    "wof:name":"Ortiz Viso Amtonio",
    "wof:placetype":"venue"
},
  "geometry": {"coordinates":[-3.3858015537,38.7593421936],"type":"Point"}
}