{
  "type": "Feature",
  "properties": {
    "addr:full":"Calle de Malaga, S/n Rute C\u00f3rdoba 14960",
    "addr:postcode":"14960",
    "addr:street":"Calle De Malaga S / N;Co\u0301Rdoba",
    "iso:country":"ES",
    "sg:address":"Calle de Malaga, S/n",
    "sg:city":"Rute",
    "sg:orig_category":"Bares, Piano",
    "sg:phone":"+34 957 53 22 35",
    "sg:postcode":"14960",
    "sg:province":"C\u00f3rdoba",
    "wof:name":"Gamez Diaz Carmen Maria",
    "wof:placetype":"venue"
},
  "geometry": {"coordinates":[-4.3678388596,37.318523407],"type":"Point"}
}