{
  "type": "Feature",
  "properties": {
    "iso:country":"ES",
    "sg:address":"Calle de Tigaday, 24",
    "sg:city":"Granadilla Abona",
    "sg:orig_category":"Supermercados Y Hipermercados",
    "sg:phone":"+34 922 77 24 43",
    "sg:postcode":"38600",
    "sg:province":"Santa Cruz De Tenerife",
    "wof:name":"Guillen Salas Rigoberto",
    "wof:placetype":"venue"
},
  "geometry": {"coordinates":[-16.579706192,28.1183338165],"type":"Point"}
}