{
  "type": "Feature",
  "properties": {
    "iso:country":"ES",
    "sg:address":"Calle de Tejeria, S/n",
    "sg:city":"Bidankoze",
    "sg:orig_category":"Fabricaci\u00d3n De Quesos",
    "sg:phone":"+34 948 47 70 96",
    "sg:postcode":"31413",
    "sg:province":"Navarra",
    "wof:name":"Roncalact S.a",
    "wof:placetype":"venue"
},
  "geometry": {"coordinates":[-1.0148420334,42.8015518188],"type":"Point"}
}