{
  "type": "Feature",
  "properties": {
    "addr:full":"Calle de Reina Mercedes, 18 Madrid Madrid 28020",
    "addr:housenumber":"18",
    "addr:postcode":"madrid;28020",
    "addr:street":"Calle De Reina Mercedes",
    "iso:country":"ES",
    "sg:address":"Calle de Reina Mercedes, 18",
    "sg:city":"Madrid",
    "sg:orig_category":"Arquitectos",
    "sg:phone":"+34 915 53 16 31",
    "sg:postcode":"28020",
    "sg:province":"Madrid",
    "wof:name":"Somoza Rodriguez-escudero Maria Dolores",
    "wof:placetype":"venue"
},
  "geometry": {"coordinates":[-3.697655201,40.4509544373],"type":"Point"}
}