{
  "type": "Feature",
  "properties": {
    "iso:country":"ES",
    "sg:address":"Avda Agustin Gonzalez, 8",
    "sg:city":"Posada",
    "sg:orig_category":"Material Y Herramientas Agr\u00cdcolas",
    "sg:phone":"+34 985 77 27 14",
    "sg:postcode":"33424",
    "sg:province":"Asturias",
    "wof:name":"Suarez Nu\u00f1ez Eduardo Jose",
    "wof:placetype":"venue"
},
  "geometry": {"coordinates":[-5.8518400192,43.440284729],"type":"Point"}
}