{
  "type": "Feature",
  "properties": {
    "addr:full":"Calle de Real, 50 Arguedas Navarra 31513",
    "addr:housenumber":"50",
    "addr:postcode":"31513",
    "addr:street":"Calle De Real",
    "iso:country":"ES",
    "sg:address":"Calle de Real, 50",
    "sg:city":"Arguedas",
    "sg:orig_category":"Panader\u00cdas, Panader\u00cdas",
    "sg:phone":"+34 948 83 00 62",
    "sg:postcode":"31513",
    "sg:province":"Navarra",
    "wof:name":"Panificadora La Virgen Del Yugo S.l.",
    "wof:placetype":"venue"
},
  "geometry": {"coordinates":[-1.5975329876,42.176235199],"type":"Point"}
}