{
  "type": "Feature",
  "properties": {
    "iso:country":"ES",
    "sg:address":"Ctra Marines A Denia (les), S/n",
    "sg:city":"Marines",
    "sg:orig_category":"Supermercados Y Hipermercados",
    "sg:phone":"+34 965 78 87 54",
    "sg:postcode":"03700",
    "sg:province":"Alicante",
    "wof:name":"Super G S.a.",
    "wof:placetype":"venue"
},
  "geometry": {"coordinates":[0.0785949975,38.8549537659],"type":"Point"}
}