{
  "type": "Feature",
  "properties": {
    "iso:country":"ES",
    "sg:address":"Calle de Magnus Blikstad, 38",
    "sg:city":"Gijon",
    "sg:orig_category":"Reposter\u00cdas",
    "sg:phone":"+34 985 17 10 66",
    "sg:postcode":"33207",
    "sg:province":"Asturias",
    "wof:name":"La Baguete S.l.",
    "wof:placetype":"venue"
},
  "geometry": {"coordinates":[-5.6688652039,43.5362815857],"type":"Point"}
}