{
  "type": "Feature",
  "properties": {
    "addr:full":"Calle de Sanchez Llevot, 10 Salamanca Salamanca 37005",
    "addr:housenumber":"10",
    "addr:postcode":"37005",
    "addr:street":"Calle De Sanchez Llevot",
    "iso:country":"ES",
    "sg:address":"Calle de Sanchez Llevot, 10",
    "sg:city":"Salamanca",
    "sg:orig_category":"Alimentaci\u00d3n General (al Por Menor)",
    "sg:phone":"+34 923 24 29 63",
    "sg:postcode":"37005",
    "sg:province":"Salamanca",
    "wof:name":"Garcia Anton Jose Luis",
    "wof:placetype":"venue"
},
  "geometry": {"coordinates":[-5.662088871,40.9704399109],"type":"Point"}
}