{
  "type": "Feature",
  "properties": {
    "addr:full":"Calle de Virgen De La Luz, 38 Ceuta Ceuta 51002",
    "addr:housenumber":"38",
    "addr:postcode":"51002",
    "addr:street":"Calle De Virgen De La Luz",
    "iso:country":"ES",
    "sg:address":"Calle de Virgen De La Luz, 38",
    "sg:city":"Ceuta",
    "sg:orig_category":"Asociaciones, Organismos Culturales Y Socioeducativos",
    "sg:phone":"+34 956 50 99 50",
    "sg:postcode":"51002",
    "sg:province":"Ceuta",
    "wof:name":"Asociacion Cultural Al Kadi Ayyad",
    "wof:placetype":"venue"
},
  "geometry": {"coordinates":[-5.3342199326,35.8829307556],"type":"Point"}
}