{
  "type": "Feature",
  "properties": {
    "addr:full":"Calle de Natalia De Silva, 7 Madrid Madrid 28027",
    "addr:housenumber":"7",
    "addr:postcode":"madrid;28027",
    "addr:street":"Calle De Natalia De Silva",
    "iso:country":"ES",
    "sg:address":"Calle de Natalia De Silva, 7",
    "sg:city":"Madrid",
    "sg:orig_category":"Limpieza Y Vaciado De Fosas",
    "sg:phone":"+34 917 42 20 38",
    "sg:postcode":"28027",
    "sg:province":"Madrid",
    "wof:name":"Poceria Y Construcciones Martin Arroyo S.l.",
    "wof:placetype":"venue"
},
  "geometry": {"coordinates":[-3.6441750526,40.4453315735],"type":"Point"}
}