{
  "type": "Feature",
  "properties": {
    "addr:full":"Calle de Gabriel Perez, 2 Albatera Alicante 03340",
    "addr:housenumber":"2",
    "addr:postcode":"03340",
    "addr:street":"Calle De Gabriel Perez",
    "iso:country":"ES",
    "sg:address":"Calle de Gabriel Perez, 2",
    "sg:city":"Albatera",
    "sg:orig_category":"Producci\u00d3n, Venta De Productos De Agricultura Biol\u00d3gica",
    "sg:phone":"+34 965 48 52 70",
    "sg:postcode":"03340",
    "sg:province":"Alicante",
    "wof:name":"Garcia Riquelme Gratiniano",
    "wof:placetype":"venue"
},
  "geometry": {"coordinates":[-0.8741238117,38.1795730591],"type":"Point"}
}