{
  "type": "Feature",
  "properties": {
    "iso:country":"ES",
    "sg:address":"Calle de Andres Lopez Palmeiro, 15",
    "sg:city":"Ferreira",
    "sg:orig_category":"Telas Y Sedas (al Por Menor)",
    "sg:phone":"+34 982 57 44 31",
    "sg:postcode":"27770",
    "sg:province":"Lugo",
    "wof:name":"Vila Trigo Maria Julia",
    "wof:placetype":"venue"
},
  "geometry": {"coordinates":[-7.4409809113,43.5495033264],"type":"Point"}
}