{
  "type": "Feature",
  "properties": {
    "addr:full":"Calle de Murillo (urb Casablanca), 12 Marbella M\u00e1laga 29600",
    "addr:housenumber":"12",
    "addr:postcode":"29600",
    "addr:street":"Calle De Murillo Urb Casablanca;Ma\u0301Laga",
    "iso:country":"ES",
    "sg:address":"Calle de Murillo (urb Casablanca), 12",
    "sg:city":"Marbella",
    "sg:orig_category":"Ingeniero",
    "sg:phone":"+34 952 77 06 40",
    "sg:postcode":"29600",
    "sg:province":"M\u00e1laga",
    "wof:name":"Martin Chaves Francisco",
    "wof:placetype":"venue"
},
  "geometry": {"coordinates":[-4.9101438522,36.5084762573],"type":"Point"}
}