{
  "type": "Feature",
  "properties": {
    "iso:country":"ES",
    "sg:address":"Urb. Mora, S/n",
    "sg:city":"Port Selva",
    "sg:orig_category":"Distribuci\u00d3n De Petr\u00d3leo Y Derivados",
    "sg:phone":"+34 972 38 74 22",
    "sg:postcode":"17489",
    "sg:province":"Girona",
    "wof:name":"Mension Gironella Eduardo",
    "wof:placetype":"venue"
},
  "geometry": {"coordinates":[3.1865150928,42.3239517212],"type":"Point"}
}