{
  "type": "Feature",
  "properties": {
    "iso:country":"ES",
    "sg:address":"Calle de Reina, 14",
    "sg:city":"San Ildefonso O La Granja",
    "sg:orig_category":"Venta, Instalaci\u00d3n De Cocinas",
    "sg:phone":"+34 921 47 05 48",
    "sg:postcode":"40100",
    "sg:province":"Segovia",
    "wof:name":"Restaurante Reina 14 S.l.",
    "wof:placetype":"venue"
},
  "geometry": {"coordinates":[-4.0071439743,40.9018363953],"type":"Point"}
}