{
  "type": "Feature",
  "properties": {
    "addr:full":"Calle de Fabiola, 25 Sevilla Sevilla 41004",
    "addr:housenumber":"25",
    "addr:postcode":"41004",
    "addr:street":"Calle De Fabiola",
    "iso:country":"ES",
    "sg:address":"Calle de Fabiola, 25",
    "sg:city":"Sevilla",
    "sg:orig_category":"Empresarios",
    "sg:phone":"+34 954 50 11 40",
    "sg:postcode":"41004",
    "sg:province":"Sevilla",
    "sg:website":"www.fundacionjmlara.es",
    "wof:name":"Fundacion Jose Manuel Lara",
    "wof:placetype":"venue"
},
  "geometry": {"coordinates":[-5.9889879227,37.3869285583],"type":"Point"}
}