{
  "type": "Feature",
  "properties": {
    "addr:full":"Ctra. Zolina, 10 Tajonar Navarra 31192",
    "addr:housenumber":"10",
    "addr:postcode":"31192",
    "addr:street":"Ctra. Zolina",
    "iso:country":"ES",
    "sg:address":"Ctra. Zolina, 10",
    "sg:city":"Tajonar",
    "sg:orig_category":"Cristaler\u00cdas",
    "sg:phone":"+34 948 31 70 96",
    "sg:postcode":"31192",
    "sg:province":"Navarra",
    "wof:name":"Cristaleria Belagua S.l.",
    "wof:placetype":"venue"
},
  "geometry": {"coordinates":[-1.6151809692,42.7892303467],"type":"Point"}
}