{
  "type": "Feature",
  "properties": {
    "iso:country":"ES",
    "sg:address":"Calle de Norte, S/n",
    "sg:city":"Villarrubio",
    "sg:orig_category":"Forjas Y Altos Hornos",
    "sg:phone":"+34 969 13 50 00",
    "sg:postcode":"16420",
    "sg:province":"Cuenca",
    "wof:name":"Ramirez Colino Jesus",
    "wof:placetype":"venue"
},
  "geometry": {"coordinates":[-2.8925740719,39.945640564],"type":"Point"}
}