{
  "type": "Feature",
  "properties": {
    "addr:full":"Carrer de Arago, 77 Palma Islas Baleares 07005",
    "addr:housenumber":"77",
    "addr:postcode":"07005",
    "addr:street":"Carrer De Arago",
    "iso:country":"ES",
    "sg:address":"Carrer de Arago, 77",
    "sg:city":"Palma",
    "sg:orig_category":"Asociaciones Y Clubs Deportivos",
    "sg:phone":"+34 971 24 95 52",
    "sg:postcode":"07005",
    "sg:province":"Islas Baleares",
    "wof:name":"Arago Esports",
    "wof:placetype":"venue"
},
  "geometry": {"coordinates":[2.663192749,39.5788879395],"type":"Point"}
}