{
  "type": "Feature",
  "properties": {
    "addr:full":"Calle de Tortola, 5 Fuenlabrada Madrid 28946",
    "addr:housenumber":"5",
    "addr:postcode":"28946",
    "addr:street":"Calle De Tortola",
    "iso:country":"ES",
    "sg:address":"Calle de Tortola, 5",
    "sg:city":"Fuenlabrada",
    "sg:orig_category":"Chapister\u00cda",
    "sg:phone":"+34 916 42 23 71",
    "sg:postcode":"28946",
    "sg:province":"Madrid",
    "wof:name":"Tuneart S.l.",
    "wof:placetype":"venue"
},
  "geometry": {"coordinates":[-3.7626359463,40.2643966675],"type":"Point"}
}