{
  "type": "Feature",
  "properties": {
    "iso:country":"ES",
    "sg:address":"Calle de Puerto De San Vicente, 52",
    "sg:city":"Talavera Reina",
    "sg:orig_category":"Herboristas (al Por Menor)",
    "sg:phone":"+34 925 80 10 58",
    "sg:postcode":"45600",
    "sg:province":"Toledo",
    "wof:name":"Oliva Aceituno Juan Antonio",
    "wof:placetype":"venue"
},
  "geometry": {"coordinates":[-4.8326292038,39.9584884644],"type":"Point"}
}