{
  "type": "Feature",
  "properties": {
    "iso:country":"ES",
    "sg:address":"Rua Virgen De Fatima, 3",
    "sg:city":"Ourense",
    "sg:orig_category":"Mercer\u00cda, Lencer\u00cda (al Por Menor)",
    "sg:phone":"+34 988 22 72 67",
    "sg:postcode":"32002",
    "sg:province":"Ourense",
    "wof:name":"Lamelas Grande Maria Teresa",
    "wof:placetype":"venue"
},
  "geometry": {"coordinates":[-7.8766951561,42.3420944214],"type":"Point"}
}