{
  "type": "Feature",
  "properties": {
    "iso:country":"ES",
    "sg:address":"Calle de Mayor, 130",
    "sg:city":"Murchante",
    "sg:orig_category":"Material Y Herramientas Agr\u00cdcolas",
    "sg:phone":"+34 948 83 81 31",
    "sg:postcode":"31521",
    "sg:province":"Navarra",
    "wof:name":"Jose Moreno E Hijos S.l.",
    "wof:placetype":"venue"
},
  "geometry": {"coordinates":[-1.6524239779,42.0318603516],"type":"Point"}
}