{
  "type": "Feature",
  "properties": {
    "addr:full":"Avda Perez Galdos, 57 Logro\u00f1o La Rioja 26005",
    "addr:housenumber":"57",
    "addr:postcode":"26005",
    "addr:street":"Avda Perez Galdos;Rioja",
    "iso:country":"ES",
    "sg:address":"Avda Perez Galdos, 57",
    "sg:city":"Logro\u00f1o",
    "sg:orig_category":"Centros Empresariales",
    "sg:phone":"+34 941 20 30 90",
    "sg:postcode":"26005",
    "sg:province":"La Rioja",
    "wof:name":"Grupo De Controladuria Del Norte S.l.",
    "wof:placetype":"venue"
},
  "geometry": {"coordinates":[-2.4541194439,42.46276474],"type":"Point"}
}