{
  "type": "Feature",
  "properties": {
    "iso:country":"ES",
    "sg:address":"Pase Maria Agustin, 35",
    "sg:city":"Zaragoza",
    "sg:orig_category":"Agencias De Trabajo Temporal",
    "sg:phone":"+34 976 79 45 45",
    "sg:postcode":"50004",
    "sg:province":"Zaragoza",
    "wof:name":"Oper Tem S.l.",
    "wof:placetype":"venue"
},
  "geometry": {"coordinates":[-0.8905190229,41.6511077881],"type":"Point"}
}