{
  "type": "Feature",
  "properties": {
    "addr:full":"Avda Torrelavega, 5 Saron Cantabria 39620",
    "addr:housenumber":"5",
    "addr:postcode":"39620",
    "addr:street":"Avda Torrelavega",
    "iso:country":"ES",
    "sg:address":"Avda Torrelavega, 5",
    "sg:city":"Saron",
    "sg:orig_category":"Peluquer\u00cdas, Peluquer\u00cda Mixta",
    "sg:phone":"+34 942 56 37 43",
    "sg:postcode":"39620",
    "sg:province":"Cantabria",
    "wof:name":"Calderon Lamo Luis",
    "wof:placetype":"venue"
},
  "geometry": {"coordinates":[-3.8539710045,43.3251304626],"type":"Point"}
}