{
  "type": "Feature",
  "properties": {
    "addr:full":"Luga Casas Blancas, 23 Casas Blancas Las Palmas 35290",
    "addr:housenumber":"23",
    "addr:postcode":"35290",
    "addr:street":"Blancas;Blancas",
    "iso:country":"ES",
    "sg:address":"Luga Casas Blancas, 23",
    "sg:city":"Casas Blancas",
    "sg:orig_category":"Inmobiliaria (agencias)",
    "sg:phone":"+34 928 79 86 51",
    "sg:postcode":"35290",
    "sg:province":"Las Palmas",
    "wof:name":"Hermanos Santana Cazorla S.l.",
    "wof:placetype":"venue"
},
  "geometry": {"coordinates":[-15.5732269287,27.9242973328],"type":"Point"}
}