{
  "type": "Feature",
  "properties": {
    "iso:country":"ES",
    "sg:address":"Carrer de Gran De Sant Andreu, 127",
    "sg:city":"Barcelona",
    "sg:orig_category":"Peluqueros: De Se\u00d1oras",
    "sg:phone":"+34 933 11 30 51",
    "sg:postcode":"08030",
    "sg:province":"Barcelona",
    "wof:name":"Calvo Diaz Concepcion",
    "wof:placetype":"venue"
},
  "geometry": {"coordinates":[2.1893100739,41.4314842224],"type":"Point"}
}