{
  "type": "Feature",
  "properties": {
    "iso:country":"ES",
    "sg:address":"Calle de Carretera De Fuenterrabia, Km. 0003,0",
    "sg:city":"Poblado Naval",
    "sg:orig_category":"Comidas Por Encargo, Organizaci\u00d3n De Recepciones",
    "sg:phone":"+34 956 86 00 69",
    "sg:postcode":"11500",
    "sg:province":"C\u00e1diz",
    "wof:name":"Restauradores Costa Oeste S.l.",
    "wof:placetype":"venue"
},
  "geometry": {"coordinates":[-6.2916250229,36.6222610474],"type":"Point"}
}