{
  "type": "Feature",
  "properties": {
    "addr:full":"Av Mare Deu De Montserrat, 156 Barcelona Barcelona 08041",
    "addr:housenumber":"156",
    "addr:postcode":"08041",
    "addr:street":"Av Mare;De Montserrat",
    "iso:country":"ES",
    "sg:address":"Av Mare Deu De Montserrat, 156",
    "sg:city":"Barcelona",
    "sg:orig_category":"Empresas De Limpieza",
    "sg:phone":"+34 934 50 33 99",
    "sg:postcode":"08041",
    "sg:province":"Barcelona",
    "wof:name":"Netissim 68 S.l.",
    "wof:placetype":"venue"
},
  "geometry": {"coordinates":[2.1722049713,41.4185638428],"type":"Point"}
}