{
  "type": "Feature",
  "properties": {
    "iso:country":"ES",
    "sg:address":"Carrer de Balanguera, 19",
    "sg:city":"Palma",
    "sg:orig_category":"Pintura, Barniz, Productos Asimilables (fabricaci\u00d3n, Al Por Mayor)",
    "sg:phone":"+34 971 28 90 10",
    "sg:postcode":"07011",
    "sg:province":"Islas Baleares",
    "wof:name":"Mediterraneo Decopint S.l.",
    "wof:placetype":"venue"
},
  "geometry": {"coordinates":[2.6414000988,39.5788154602],"type":"Point"}
}