{
  "type": "Feature",
  "properties": {
    "addr:full":"Avda Sancho El Sabio, 31 Donostia-san Sebastian Guip\u00f9zcoa 20010",
    "addr:housenumber":"31",
    "addr:postcode":"20010",
    "addr:street":"Avda Sancho El Sabio",
    "iso:country":"ES",
    "sg:address":"Avda Sancho El Sabio, 31",
    "sg:city":"Donostia-san Sebastian",
    "sg:orig_category":"Marroquiner\u00cda (confecci\u00d3n)",
    "sg:phone":"+34 943 46 76 80",
    "sg:postcode":"20010",
    "sg:province":"Guip\u00f9zcoa",
    "wof:name":"Ajiba Ajiba Khalid",
    "wof:placetype":"venue"
},
  "geometry": {"coordinates":[-1.9797266722,43.308719635],"type":"Point"}
}