{
  "type": "Feature",
  "properties": {
    "addr:full":"Carr Vicente Medina, 6 Benifaio Valencia 46450",
    "addr:housenumber":"6",
    "addr:postcode":"46450",
    "addr:street":"Carr Vicente Medina",
    "iso:country":"ES",
    "sg:address":"Carr Vicente Medina, 6",
    "sg:city":"Benifaio",
    "sg:orig_category":"Tintes (fabricaci\u00d3n, Al Por Mayor)",
    "sg:phone":"+34 961 78 12 51",
    "sg:postcode":"46450",
    "sg:province":"Valencia",
    "wof:name":"Tintoreria Toledo S.l.",
    "wof:placetype":"venue"
},
  "geometry": {"coordinates":[-0.424044013,39.2865943909],"type":"Point"}
}