{
  "type": "Feature",
  "properties": {
    "addr:full":"Calle de Fernando El Catolico, 13 Alcala Real Ja\u00e9n 23680",
    "addr:housenumber":"13",
    "addr:postcode":"23680",
    "addr:street":"Calle De Fernando El Catolico;Jae\u0301N",
    "iso:country":"ES",
    "sg:address":"Calle de Fernando El Catolico, 13",
    "sg:city":"Alcala Real",
    "sg:orig_category":"Pod\u00d3logos: Pedicuros",
    "sg:phone":"+34 953 58 71 93",
    "sg:postcode":"23680",
    "sg:province":"Ja\u00e9n",
    "wof:name":"Bermudez Osuna Beatriz",
    "wof:placetype":"venue"
},
  "geometry": {"coordinates":[-3.9212610722,37.4600257874],"type":"Point"}
}