{
  "type": "Feature",
  "properties": {
    "iso:country":"ES",
    "sg:address":"Calle de Cervantes, S/n",
    "sg:city":"Montoro",
    "sg:orig_category":"Librer\u00cdas",
    "sg:phone":"+34 957 16 01 69",
    "sg:postcode":"14600",
    "sg:province":"C\u00f3rdoba",
    "wof:name":"Hurtado Vera Jose",
    "wof:placetype":"venue"
},
  "geometry": {"coordinates":[-4.3830933571,38.0187187195],"type":"Point"}
}