{
  "type": "Feature",
  "properties": {
    "addr:full":"Industria (pol Ind La Borda), 4 Caldes Montbui Barcelona 08140",
    "addr:housenumber":"4",
    "addr:postcode":"08140",
    "addr:street":"Borda;Montbui Barcelona",
    "iso:country":"ES",
    "sg:address":"Industria (pol Ind La Borda), 4",
    "sg:city":"Caldes Montbui",
    "sg:orig_category":"Bares, Piano",
    "sg:phone":"+34 938 64 91 02",
    "sg:postcode":"08140",
    "sg:province":"Barcelona",
    "wof:name":"Distribucions Asociades Del Valles S.l.",
    "wof:placetype":"venue"
},
  "geometry": {"coordinates":[2.1757800579,41.6282310486],"type":"Point"}
}