{
  "type": "Feature",
  "properties": {
    "addr:full":"Calle de Cantabrica (la), 9 Astillero Cantabria 39610",
    "addr:housenumber":"9",
    "addr:postcode":"39610",
    "addr:street":"Calle De Cantabrica La",
    "iso:country":"ES",
    "sg:address":"Calle de Cantabrica (la), 9",
    "sg:city":"Astillero",
    "sg:orig_category":"Ense\u00d1anza Variada",
    "sg:phone":"+34 942 54 34 83",
    "sg:postcode":"39610",
    "sg:province":"Cantabria",
    "sg:website":"www.englishon.info",
    "wof:name":"Casta\u00f1eda Agullo Fernando",
    "wof:placetype":"venue"
},
  "geometry": {"coordinates":[-3.8167808056,43.3964805603],"type":"Point"}
}