{
  "type": "Feature",
  "properties": {
    "addr:full":"Calle de Ciscar, 43 Valencia Valencia 46005",
    "addr:housenumber":"43",
    "addr:postcode":"46005",
    "addr:street":"Calle De Ciscar",
    "iso:country":"ES",
    "sg:address":"Calle de Ciscar, 43",
    "sg:city":"Valencia",
    "sg:orig_category":"Centros De Coordinaci\u00d3n",
    "sg:phone":"+34 963 74 48 38",
    "sg:postcode":"46005",
    "sg:province":"Valencia",
    "wof:name":"Pons Aguilar Rafael",
    "wof:placetype":"venue"
},
  "geometry": {"coordinates":[-0.364570111,39.4645004272],"type":"Point"}
}