{
  "type": "Feature",
  "properties": {
    "addr:full":"Carr Nou, 32 Alfarras Lleida 25120",
    "addr:housenumber":"32",
    "addr:postcode":"25120",
    "addr:street":"Carr Nou",
    "iso:country":"ES",
    "sg:address":"Carr Nou, 32",
    "sg:city":"Alfarras",
    "sg:orig_category":"Reposter\u00cdas",
    "sg:phone":"+34 973 76 00 36",
    "sg:postcode":"25120",
    "sg:province":"Lleida",
    "wof:name":"Guitart Merce Merce",
    "wof:placetype":"venue"
},
  "geometry": {"coordinates":[0.5686320066,41.8303451538],"type":"Point"}
}