{
  "type": "Feature",
  "properties": {
    "iso:country":"ES",
    "sg:address":"Rua San Rosendo, 10",
    "sg:city":"Ourense",
    "sg:orig_category":"Panader\u00cdas, Panader\u00cdas",
    "sg:phone":"+34 988 37 29 52",
    "sg:postcode":"32001",
    "sg:province":"Ourense",
    "wof:name":"Emdulga S.l.",
    "wof:placetype":"venue"
},
  "geometry": {"coordinates":[-7.8740558624,42.3496551514],"type":"Point"}
}