{
  "type": "Feature",
  "properties": {
    "iso:country":"ES",
    "sg:address":"Calle de Arenal, 1",
    "sg:city":"Bilbao",
    "sg:orig_category":"Ense\u00d1anza: Profesiones Art\u00cdsticas",
    "sg:phone":"+34 944 15 71 47",
    "sg:postcode":"48005",
    "sg:province":"Vizcaya",
    "wof:name":"Alonso Vega Natividad",
    "wof:placetype":"venue"
},
  "geometry": {"coordinates":[-2.9245171547,43.2592697144],"type":"Point"}
}