{
  "type": "Feature",
  "properties": {
    "addr:full":"Calle de Benedicto Xv, 23 Quintanar Orden Toledo 45800",
    "addr:housenumber":"23",
    "addr:postcode":"45800",
    "addr:street":"Calle De Benedicto Xv",
    "iso:country":"ES",
    "sg:address":"Calle de Benedicto Xv, 23",
    "sg:city":"Quintanar Orden",
    "sg:orig_category":"Promotores Constructores",
    "sg:phone":"+34 925 18 18 87",
    "sg:postcode":"45800",
    "sg:province":"Toledo",
    "wof:name":"Tarce  Mircea Cristian",
    "wof:placetype":"venue"
},
  "geometry": {"coordinates":[-3.0319929123,39.588848114],"type":"Point"}
}