{
  "type": "Feature",
  "properties": {
    "addr:full":"Rua Dr. Dario Duran Gomez, 16 Vigo Pontevedra 36210",
    "addr:housenumber":"16",
    "addr:postcode":"36210",
    "addr:street":"Rua Dr. Dario Duran Gomez",
    "iso:country":"ES",
    "sg:address":"Rua Dr. Dario Duran Gomez, 16",
    "sg:city":"Vigo",
    "sg:orig_category":"M\u00c9dicos: Estomatolog\u00cda",
    "sg:phone":"+34 986 21 02 85",
    "sg:postcode":"36210",
    "sg:province":"Pontevedra",
    "wof:name":"Paez Egido Ernesto",
    "wof:placetype":"venue"
},
  "geometry": {"coordinates":[-8.7385587692,42.2175292969],"type":"Point"}
}