{
  "type": "Feature",
  "properties": {
    "addr:full":"Calle de Cesar Escudero, 1 Mombuey Zamora 49310",
    "addr:housenumber":"1",
    "addr:postcode":"49310",
    "addr:street":"Calle De Cesar Escudero",
    "iso:country":"ES",
    "sg:address":"Calle de Cesar Escudero, 1",
    "sg:city":"Mombuey",
    "sg:orig_category":"Promotores Constructores",
    "sg:phone":"+34 980 64 27 65",
    "sg:postcode":"49310",
    "sg:province":"Zamora",
    "wof:name":"Alvarez Madrigal Maria Agustina",
    "wof:placetype":"venue"
},
  "geometry": {"coordinates":[-6.329934597,42.0217170715],"type":"Point"}
}