{
  "type": "Feature",
  "properties": {
    "addr:full":"Avda Jose Antonio, 41 Plasencia C\u00e1ceres 10600",
    "addr:housenumber":"41",
    "addr:postcode":"10600",
    "addr:street":"Avda Jose Antonio;Ca\u0301Ceres",
    "iso:country":"ES",
    "sg:address":"Avda Jose Antonio, 41",
    "sg:city":"Plasencia",
    "sg:orig_category":"Carnicer\u00cdas, Carnicer\u00cdas",
    "sg:phone":"+34 927 42 33 91",
    "sg:postcode":"10600",
    "sg:province":"C\u00e1ceres",
    "wof:name":"Carnicas Pozas S.l.",
    "wof:placetype":"venue"
},
  "geometry": {"coordinates":[-6.0847759247,40.0330505371],"type":"Point"}
}