{
  "type": "Feature",
  "properties": {
    "iso:country":"ES",
    "sg:address":"Calle de Virgen Del Rosario, 6",
    "sg:city":"Agost",
    "sg:orig_category":"Fabrica De Cer\u00c1micas",
    "sg:phone":"+34 965 62 66 81",
    "sg:postcode":"03698",
    "sg:province":"Alicante",
    "wof:name":"Morant Conde E Hijos S.l.",
    "wof:placetype":"venue"
},
  "geometry": {"coordinates":[-0.6349989772,38.4366798401],"type":"Point"}
}