{
  "type": "Feature",
  "properties": {
    "addr:full":"Plaz Chueca, 8 Madrid Madrid 28004",
    "addr:housenumber":"8",
    "addr:postcode":"madrid;28004",
    "addr:street":"Plaz Chueca",
    "iso:country":"ES",
    "sg:address":"Plaz Chueca, 8",
    "sg:city":"Madrid",
    "sg:orig_category":"Formaci\u00d3n A Distancia, Por Correspondencia",
    "sg:phone":"+34 915 21 70 09",
    "sg:postcode":"28004",
    "sg:province":"Madrid",
    "sg:website":"www.bircham.edu",
    "wof:name":"Bircham International University S.l.",
    "wof:placetype":"venue"
},
  "geometry": {"coordinates":[-3.6973810196,40.422580719],"type":"Point"}
}