{
  "type": "Feature",
  "properties": {
    "iso:country":"ES",
    "sg:address":"Calle de Baja De San Pedro, 18",
    "sg:city":"Binefar",
    "sg:orig_category":"Asociaciones Y Clubs Deportivos",
    "sg:phone":"+34 974 42 86 74",
    "sg:postcode":"22500",
    "sg:province":"Huesca",
    "wof:name":"Toni Charles S.l.",
    "wof:placetype":"venue"
},
  "geometry": {"coordinates":[0.2918049991,41.8513565063],"type":"Point"}
}