{
  "type": "Feature",
  "properties": {
    "addr:full":"Calle de Antonio Silva Nu\u00d1ez, 20 Olivenza Badajoz 06100",
    "addr:housenumber":"20",
    "addr:postcode":"06100",
    "addr:street":"Calle De Antonio;Nun\u0303Ez",
    "iso:country":"ES",
    "sg:address":"Calle de Antonio Silva Nu\u00d1ez, 20",
    "sg:city":"Olivenza",
    "sg:orig_category":"Agencias Y Agentes Comerciales, Representantes",
    "sg:phone":"+34 924 49 05 96",
    "sg:postcode":"06100",
    "sg:province":"Badajoz",
    "wof:name":"Minino Garcia Vicente",
    "wof:placetype":"venue"
},
  "geometry": {"coordinates":[-7.1144037247,38.6670570374],"type":"Point"}
}