{
  "type": "Feature",
  "properties": {
    "iso:country":"ES",
    "sg:address":"Plaz Doctor Macho, 1",
    "sg:city":"Salda\u00f1a",
    "sg:orig_category":"Electrodom\u00c9sticos (al Por Menor)",
    "sg:phone":"+34 979 89 03 42",
    "sg:postcode":"34100",
    "sg:province":"Palencia",
    "wof:name":"Martinez Salvador Mateo",
    "wof:placetype":"venue"
},
  "geometry": {"coordinates":[-4.7365789413,42.5221595764],"type":"Point"}
}