{
  "type": "Feature",
  "properties": {
    "addr:full":"Kale Nagusia, 4 Asteasu Guip\u00f9zcoa 20159",
    "addr:housenumber":"4",
    "addr:postcode":"20159",
    "addr:street":"Kale Nagusia;Guipu\u0300Zcoa",
    "iso:country":"ES",
    "sg:address":"Kale Nagusia, 4",
    "sg:city":"Asteasu",
    "sg:orig_category":"Contenedores (mercanc\u00cdas)",
    "sg:phone":"+34 943 69 30 92",
    "sg:postcode":"20159",
    "sg:province":"Guip\u00f9zcoa",
    "wof:name":"Urbieta Aguinalde Jose Antonio",
    "wof:placetype":"venue"
},
  "geometry": {"coordinates":[-2.0742990971,43.1991958618],"type":"Point"}
}