{
  "type": "Feature",
  "properties": {
    "addr:full":"Plaz Sol (del), 4 Alcorcon Madrid 28922",
    "addr:postcode":"28922",
    "iso:country":"ES",
    "sg:address":"Plaz Sol (del), 4",
    "sg:city":"Alcorcon",
    "sg:orig_category":"Internados & Ense\u00d1anza Privada",
    "sg:phone":"+34 916 41 58 54",
    "sg:postcode":"28922",
    "sg:province":"Madrid",
    "wof:name":"Centro De Formacion De Protesis Dental Nuestra Se\u00d1ora Del Consuelo",
    "wof:placetype":"venue"
},
  "geometry": {"coordinates":[-3.8242239952,40.3513946533],"type":"Point"}
}