{
  "type": "Feature",
  "properties": {
    "iso:country":"ES",
    "sg:address":"Carrer de Lluis Castells, 61",
    "sg:city":"S. Boi Llobregat",
    "sg:orig_category":"Dietistas",
    "sg:phone":"+34 936 54 34 73",
    "sg:postcode":"08830",
    "sg:province":"Barcelona",
    "wof:name":"Arnau Bosch Maria Gloria",
    "wof:placetype":"venue"
},
  "geometry": {"coordinates":[2.0362138748,41.3462181091],"type":"Point"}
}