{
  "type": "Feature",
  "properties": {
    "iso:country":"ES",
    "sg:address":"Calle de Pintor Pepe Damaso, 16",
    "sg:city":"Tamaraceite",
    "sg:orig_category":"Librer\u00cdas",
    "sg:phone":"+34 928 67 75 78",
    "sg:postcode":"35018",
    "sg:province":"Las Palmas",
    "wof:name":"Navarro Rodriguez Braulio",
    "wof:placetype":"venue"
},
  "geometry": {"coordinates":[-15.4725971222,28.0987663269],"type":"Point"}
}