{
  "type": "Feature",
  "properties": {
    "iso:country":"ES",
    "sg:address":"Calle de General Segura, 13",
    "sg:city":"Almeria",
    "sg:orig_category":"Ense\u00d1anza Variada",
    "sg:phone":"+34 950 23 88 75",
    "sg:postcode":"04004",
    "sg:province":"Almer\u00eda",
    "wof:name":"Santolaria Gazquez Nuria",
    "wof:placetype":"venue"
},
  "geometry": {"coordinates":[-2.4627380371,36.8363609314],"type":"Point"}
}