{
  "type": "Feature",
  "properties": {
    "addr:full":"G.v. Corts Catalanes, 407 Barcelona Barcelona 08015",
    "addr:housenumber":"407",
    "addr:postcode":"08015",
    "addr:street":"Catalanes",
    "iso:country":"ES",
    "sg:address":"G.v. Corts Catalanes, 407",
    "sg:city":"Barcelona",
    "sg:orig_category":"Asesor\u00cda Fiscal Y Jur\u00cddica",
    "sg:phone":"+34 934 25 28 42",
    "sg:postcode":"08015",
    "sg:province":"Barcelona",
    "wof:name":"Laber Consulting S.l.",
    "wof:placetype":"venue"
},
  "geometry": {"coordinates":[2.1516621113,41.3773727417],"type":"Point"}
}