{
  "type": "Feature",
  "properties": {
    "addr:full":"Calle de Ciudad De Lugo, 9 Vilalba Lugo 27800",
    "addr:housenumber":"9",
    "addr:postcode":"27800",
    "addr:street":"Calle De Ciudad De Lugo",
    "iso:country":"ES",
    "sg:address":"Calle de Ciudad De Lugo, 9",
    "sg:city":"Vilalba",
    "sg:orig_category":"Contenedores (mercanc\u00cdas)",
    "sg:phone":"+34 982 51 07 09",
    "sg:postcode":"27800",
    "sg:province":"Lugo",
    "wof:name":"Lozano Prieto Jorge",
    "wof:placetype":"venue"
},
  "geometry": {"coordinates":[-7.6802043915,43.2932167053],"type":"Point"}
}