{
  "type": "Feature",
  "properties": {
    "iso:country":"ES",
    "sg:address":"Carrer de Montserrat, 13",
    "sg:city":"Vic",
    "sg:orig_category":"Alquiler De Veh\u00cdculos: Turismos Y Utilitarios",
    "sg:phone":"+34 938 86 25 42",
    "sg:postcode":"08500",
    "sg:province":"Barcelona",
    "wof:name":"Autos Vila Lloguer S.l.",
    "wof:placetype":"venue"
},
  "geometry": {"coordinates":[2.2626268864,41.9285583496],"type":"Point"}
}