{
  "type": "Feature",
  "properties": {
    "iso:country":"ES",
    "sg:address":"Calle de Pe\u00d1as Arriba, 6",
    "sg:city":"Reinosa",
    "sg:classifiers":[
        {
            "category":"Autos & Motor Vehicles",
            "subcategory":"Automobile Sales",
            "type":"Retail Goods"
        }
    ],
    "sg:phone":"+34 942 75 16 96",
    "sg:postcode":"39200",
    "sg:province":"Cantabria",
    "wof:name":"Santiago Ruiz Luis",
    "wof:placetype":"venue"
},
  "geometry": {"coordinates":[-4.1391940117,43.0004043579],"type":"Point"}
}