{
  "type": "Feature",
  "properties": {
    "iso:country":"ES",
    "sg:address":"Jose De Arroyo, 18",
    "sg:city":"Puerto Cruz",
    "sg:orig_category":"Ropa Para Ni\u00d1os (al Por Menor)",
    "sg:phone":"+34 922 37 26 24",
    "sg:postcode":"38400",
    "sg:province":"Santa Cruz De Tenerife",
    "wof:name":"Depositos Y Almacenes Numero-1 S.a.",
    "wof:placetype":"venue"
},
  "geometry": {"coordinates":[-16.5517692566,28.4158000946],"type":"Point"}
}