{
  "type": "Feature",
  "properties": {
    "iso:country":"ES",
    "sg:address":"Carr Coret Y Peris, 11",
    "sg:city":"Alboraya",
    "sg:orig_category":"Ense\u00d1anza Variada",
    "sg:phone":"+34 961 85 97 58",
    "sg:postcode":"46120",
    "sg:province":"Valencia",
    "wof:name":"Redon Ros Beatriz",
    "wof:placetype":"venue"
},
  "geometry": {"coordinates":[-0.3541390002,39.4995422363],"type":"Point"}
}