{
  "type": "Feature",
  "properties": {
    "iso:country":"ES",
    "sg:address":"Ctra Ojos, 42",
    "sg:city":"Alto Palomo",
    "sg:orig_category":"Arboricultura Y Producci\u00d3n De Frutas",
    "sg:phone":"+34 968 77 83 70",
    "sg:postcode":"30540",
    "sg:province":"Murcia",
    "wof:name":"Molina Ruiz Angel",
    "wof:placetype":"venue"
},
  "geometry": {"coordinates":[-1.369478941,38.1796684265],"type":"Point"}
}