{
  "type": "Feature",
  "properties": {
    "iso:country":"ES",
    "sg:address":"Avda Olimpica, 4",
    "sg:city":"Mostoles",
    "sg:orig_category":"Electrodom\u00c9sticos (al Por Menor)",
    "sg:phone":"+34 916 14 61 80",
    "sg:postcode":"28935",
    "sg:province":"Madrid",
    "wof:name":"Matute Gallego Cecilio",
    "wof:placetype":"venue"
},
  "geometry": {"coordinates":[-3.8838489056,40.3264045715],"type":"Point"}
}