{
  "type": "Feature",
  "properties": {
    "addr:full":"Barr Elejalde, 43 Elejalde Forua Vizcaya 48393",
    "addr:housenumber":"43",
    "addr:postcode":"48393",
    "addr:street":"Elejalde",
    "iso:country":"ES",
    "sg:address":"Barr Elejalde, 43",
    "sg:city":"Elejalde Forua",
    "sg:orig_category":"Ense\u00d1anza: Idiomas",
    "sg:phone":"+34 946 25 82 92",
    "sg:postcode":"48393",
    "sg:province":"Vizcaya",
    "wof:name":"Euskaraz Koop. E.",
    "wof:placetype":"venue"
},
  "geometry": {"coordinates":[-2.6769039631,43.3311882019],"type":"Point"}
}