{
  "type": "Feature",
  "properties": {
    "addr:full":"Carrer de Londres, 15 Barcelona Barcelona 08029",
    "addr:housenumber":"15",
    "addr:postcode":"08029",
    "addr:street":"Carrer De Londres",
    "iso:country":"ES",
    "sg:address":"Carrer de Londres, 15",
    "sg:city":"Barcelona",
    "sg:orig_category":"Carnicer\u00cdas, Carnicer\u00cdas",
    "sg:phone":"+34 934 30 12 45",
    "sg:postcode":"08029",
    "sg:province":"Barcelona",
    "wof:name":"Armengol Gabalda Maria Dolors",
    "wof:placetype":"venue"
},
  "geometry": {"coordinates":[2.1443138123,41.3886299133],"type":"Point"}
}