{
  "type": "Feature",
  "properties": {
    "iso:country":"ES",
    "sg:address":"Calle de Archiduque Carlos, 58",
    "sg:city":"Valencia",
    "sg:orig_category":"\u00d3ptica: Instrumentos (fabricaci\u00d3n)",
    "sg:phone":"+34 963 77 51 34",
    "sg:postcode":"46014",
    "sg:province":"Valencia",
    "wof:name":"Optica Bravo",
    "wof:placetype":"venue"
},
  "geometry": {"coordinates":[-0.3987990022,39.4614982605],"type":"Point"}
}