{
  "type": "Feature",
  "properties": {
    "addr:full":"Calle de Jaboneria, 39 Daimiel Ciudad Real 13250",
    "addr:housenumber":"39",
    "addr:postcode":"13250",
    "addr:street":"Calle De Jaboneria",
    "iso:country":"ES",
    "sg:address":"Calle de Jaboneria, 39",
    "sg:city":"Daimiel",
    "sg:orig_category":"Confecci\u00d3n (fabricaci\u00d3n, Al Por Mayor)",
    "sg:phone":"+34 926 85 29 00",
    "sg:postcode":"13250",
    "sg:province":"Ciudad Real",
    "wof:name":"Saez Merino S.a.",
    "wof:placetype":"venue"
},
  "geometry": {"coordinates":[-3.6090300083,39.0688514709],"type":"Point"}
}