{
  "type": "Feature",
  "properties": {
    "addr:full":"Plaz Constitucion, 3 Mislata Valencia 46920",
    "addr:housenumber":"3",
    "addr:postcode":"46920",
    "addr:street":"Constitucion",
    "iso:country":"ES",
    "sg:address":"Plaz Constitucion, 3",
    "sg:city":"Mislata",
    "sg:orig_category":"Bancos",
    "sg:phone":"+34 963 79 42 00",
    "sg:postcode":"46920",
    "sg:province":"Valencia",
    "sg:website":"www.bancopopular.es",
    "wof:name":"Banco Popular Espa\u00f1ol",
    "wof:placetype":"venue"
},
  "geometry": {"coordinates":[-0.417365998,39.474899292],"type":"Point"}
}