{
  "type": "Feature",
  "properties": {
    "iso:country":"ES",
    "sg:address":"C/ Simo Tort, 54",
    "sg:city":"Manacor",
    "sg:orig_category":"Empresas De Carpinter\u00cda De Madera",
    "sg:phone":"+34 971 55 18 11",
    "sg:postcode":"07500",
    "sg:province":"Islas Baleares",
    "wof:name":"Fusteria Caldentey Martinez C B",
    "wof:placetype":"venue"
},
  "geometry": {"coordinates":[3.200165987,39.5670051575],"type":"Point"}
}