{
  "type": "Feature",
  "properties": {
    "addr:full":"Carrer de Valles, 18 Terra Nostra Barcelona 08110",
    "addr:housenumber":"18",
    "addr:postcode":"08110",
    "addr:street":"Carrer De Valles",
    "iso:country":"ES",
    "sg:address":"Carrer de Valles, 18",
    "sg:city":"Terra Nostra",
    "sg:orig_category":"Limpieza Con Chorro De Arena Y Con Granalla, Pulido",
    "sg:phone":"+34 935 64 55 62",
    "sg:postcode":"08110",
    "sg:province":"Barcelona",
    "wof:name":"Garcia Matheo Daniel",
    "wof:placetype":"venue"
},
  "geometry": {"coordinates":[2.1672790051,41.4841766357],"type":"Point"}
}