{
  "type": "Feature",
  "properties": {
    "addr:full":"Calle de Pablo Mayayo, 55 Algeciras C\u00e1diz 11201",
    "addr:housenumber":"55;ca\u0301diz",
    "addr:postcode":"11201",
    "addr:street":"Calle De Pablo Mayayo",
    "iso:country":"ES",
    "sg:address":"Calle de Pablo Mayayo, 55",
    "sg:city":"Algeciras",
    "sg:orig_category":"Sociedades, Compa\u00d1\u00cdas Aseguradoras",
    "sg:phone":"+34 956 63 21 73",
    "sg:postcode":"11201",
    "sg:province":"C\u00e1diz",
    "wof:name":"Santa Lucia S.a.",
    "wof:placetype":"venue"
},
  "geometry": {"coordinates":[-5.4465007782,36.1318473816],"type":"Point"}
}