{
  "type": "Feature",
  "properties": {
    "addr:full":"Av Verge Del Claustre, S/n Solsona Lleida 25280",
    "addr:housenumber":"s / n",
    "addr:postcode":"25280",
    "addr:street":"Av Verge Del Claustre",
    "iso:country":"ES",
    "sg:address":"Av Verge Del Claustre, S/n",
    "sg:city":"Solsona",
    "sg:orig_category":"Asociaciones, Organismos Culturales Y Socioeducativos",
    "sg:phone":"+34 973 48 25 25",
    "sg:postcode":"25280",
    "sg:province":"Lleida",
    "wof:name":"Fundacio Viure I Conviure",
    "wof:placetype":"venue"
},
  "geometry": {"coordinates":[1.5164999962,41.9934463501],"type":"Point"}
}