{
  "type": "Feature",
  "properties": {
    "iso:country":"ES",
    "sg:address":"Calle de Antonia Ruiz Soro, 16",
    "sg:city":"Madrid",
    "sg:orig_category":"Chapister\u00cda",
    "sg:phone":"+34 917 26 47 28",
    "sg:postcode":"28028",
    "sg:province":"Madrid",
    "wof:name":"Hernandez Viudez Juan Jose",
    "wof:placetype":"venue"
},
  "geometry": {"coordinates":[-3.6659855843,40.4380760193],"type":"Point"}
}