{
  "type": "Feature",
  "properties": {
    "addr:full":"Plaz Colon (de), 23 Cordoba C\u00f3rdoba 14001",
    "addr:postcode":"14001",
    "addr:street":"Co\u0301Rdoba",
    "iso:country":"ES",
    "sg:address":"Plaz Colon (de), 23",
    "sg:city":"Cordoba",
    "sg:orig_category":"Funcionario De Justicia",
    "sg:phone":"+34 957 48 20 68",
    "sg:postcode":"14001",
    "sg:province":"C\u00f3rdoba",
    "wof:name":"Academia Ariete S.l.",
    "wof:placetype":"venue"
},
  "geometry": {"coordinates":[-4.776926,37.889732],"type":"Point"}
}