{
  "type": "Feature",
  "properties": {
    "addr:full":"Calle de Castilla, 150 Sevilla Sevilla 41010",
    "addr:housenumber":"150",
    "addr:postcode":"41010",
    "addr:street":"Calle De Castilla",
    "iso:country":"ES",
    "sg:address":"Calle de Castilla, 150",
    "sg:city":"Sevilla",
    "sg:orig_category":"Agencias Y Asesores De Publicidad",
    "sg:phone":"+34 954 91 54 30",
    "sg:postcode":"41010",
    "sg:province":"Sevilla",
    "sg:website":"www-comcreta.com",
    "wof:name":"Comcreta S.cooperativa Andaluza",
    "wof:placetype":"venue"
},
  "geometry": {"coordinates":[-6.0093021393,37.3890304565],"type":"Point"}
}