{
  "type": "Feature",
  "properties": {
    "addr:full":"Calle de Jorge Juan, 8 Valencia Valencia 46004",
    "addr:housenumber":"8",
    "addr:postcode":"46004",
    "addr:street":"Calle De Jorge Juan",
    "iso:country":"ES",
    "sg:address":"Calle de Jorge Juan, 8",
    "sg:city":"Valencia",
    "sg:orig_category":"M\u00c9dicos: Cirug\u00cda Pl\u00c1stica, Reconstructiva Y Est\u00c9tica",
    "sg:phone":"+34 963 94 45 35",
    "sg:postcode":"46004",
    "sg:province":"Valencia",
    "sg:website":"www.doctormira.com",
    "wof:name":"Mira Gonzalez Juan Antonio",
    "wof:placetype":"venue"
},
  "geometry": {"coordinates":[-0.3698689938,39.469707489],"type":"Point"}
}