{
  "type": "Feature",
  "properties": {
    "iso:country":"ES",
    "sg:address":"Carrer de Claret, 10",
    "sg:city":"Hospitalet Llobregat",
    "sg:orig_category":"Electricidad: Instaladores",
    "sg:phone":"+34 933 33 98 98",
    "sg:postcode":"08903",
    "sg:province":"Barcelona",
    "wof:name":"Alonso Gargallo Julian",
    "wof:placetype":"venue"
},
  "geometry": {"coordinates":[2.1216151714,41.3720626831],"type":"Point"}
}