{
  "type": "Feature",
  "properties": {
    "iso:country":"ES",
    "sg:address":"Carrer de Sant Feliu, 1",
    "sg:city":"Sabadell",
    "sg:orig_category":"Cristaler\u00cda Art\u00cdstica, Vidrio Soplado (fabricaci\u00d3n, Al Por Mayor)",
    "sg:phone":"+34 937 25 61 50",
    "sg:postcode":"08201",
    "sg:province":"Barcelona",
    "wof:name":"Serra Renom Joan",
    "wof:placetype":"venue"
},
  "geometry": {"coordinates":[2.1058599949,41.546131134],"type":"Point"}
}