{
  "type": "Feature",
  "properties": {
    "addr:full":"Carr Font (vilarnadal), 2 Vilarnadal Girona 17762",
    "addr:housenumber":"2",
    "addr:postcode":"17762",
    "addr:street":"Carr Font Vilarnadal",
    "iso:country":"ES",
    "sg:address":"Carr Font (vilarnadal), 2",
    "sg:city":"Vilarnadal",
    "sg:orig_category":"Producci\u00d3n, Venta De Productos De Agricultura Biol\u00d3gica",
    "sg:phone":"+34 972 56 34 49",
    "sg:postcode":"17762",
    "sg:province":"Girona",
    "wof:name":"Pages Serra Josep",
    "wof:placetype":"venue"
},
  "geometry": {"coordinates":[2.95333004,42.34009552],"type":"Point"}
}