{
  "type": "Feature",
  "properties": {
    "addr:full":"Calle de Ronda Fiscal, 44 Alcala Henares Madrid 28803",
    "addr:housenumber":"44",
    "addr:postcode":"28803",
    "addr:street":"Calle De Ronda Fiscal",
    "iso:country":"ES",
    "sg:address":"Calle de Ronda Fiscal, 44",
    "sg:city":"Alcala Henares",
    "sg:orig_category":"Centros De Educaci\u00d3n Especial",
    "sg:phone":"+34 918 80 75 42",
    "sg:postcode":"28803",
    "sg:province":"Madrid",
    "wof:name":"Comunidad Autonoma De Madrid-centros De Educacion",
    "wof:placetype":"venue"
},
  "geometry": {"coordinates":[-3.3728840351,40.4716644287],"type":"Point"}
}