{
  "type": "Feature",
  "properties": {
    "addr:full":"Calle de Enrique Amat, 89 Montefrio Granada 18270",
    "addr:housenumber":"89",
    "addr:postcode":"18270",
    "addr:street":"Calle De Enrique Amat",
    "iso:country":"ES",
    "sg:address":"Calle de Enrique Amat, 89",
    "sg:city":"Montefrio",
    "sg:orig_category":"Farmacias",
    "sg:phone":"+34 958 33 63 06",
    "sg:postcode":"18270",
    "sg:province":"Granada",
    "wof:name":"Garcia Baena Antonio Francisco",
    "wof:placetype":"venue"
},
  "geometry": {"coordinates":[-4.0058646202,37.3219604492],"type":"Point"}
}