{
  "type": "Feature",
  "properties": {
    "iso:country":"ES",
    "sg:address":"Calle de Celso Emilio Ferreiro, 15",
    "sg:city":"Zaragoza",
    "sg:orig_category":"Conservas De Platos Cocinados (fabricaci\u00d3n, Al Por Mayor)",
    "sg:phone":"+34 976 34 51 39",
    "sg:postcode":"50017",
    "sg:province":"Zaragoza",
    "wof:name":"Gracia Tejedor Rosa Maria",
    "wof:placetype":"venue"
},
  "geometry": {"coordinates":[-0.9154300094,41.6534385681],"type":"Point"}
}