{
  "type": "Feature",
  "properties": {
    "iso:country":"ES",
    "sg:address":"Calle de San Miguel, 18",
    "sg:city":"Zaragoza",
    "sg:orig_category":"Ense\u00d1anza: Comercio, Gesti\u00d3n, Inform\u00c1tica",
    "sg:phone":"+34 976 21 34 89",
    "sg:postcode":"50001",
    "sg:province":"Zaragoza",
    "sg:website":"www.ce-sanmiguel.com",
    "wof:name":"Centro De Estudios San Miguel De Zaragoza S.l.",
    "wof:placetype":"venue"
},
  "geometry": {"coordinates":[-0.8795089722,41.6505012512],"type":"Point"}
}