{
  "type": "Feature",
  "properties": {
    "addr:full":"Calle de Isabel La Catolica, 8 Santander Cantabria 39007",
    "addr:housenumber":"8",
    "addr:postcode":"39007",
    "addr:street":"Calle De Isabel La Catolica",
    "iso:country":"ES",
    "sg:address":"Calle de Isabel La Catolica, 8",
    "sg:city":"Santander",
    "sg:orig_category":"Establecimientos De Cura, Prevenci\u00d3n Y Readaptaci\u00d3n",
    "sg:phone":"+34 942 23 61 06",
    "sg:postcode":"39007",
    "sg:province":"Cantabria",
    "wof:name":"Fundacion Centro De Solidaridad De Canta",
    "wof:placetype":"venue"
},
  "geometry": {"coordinates":[-3.8143479824,43.4626502991],"type":"Point"}
}