{
  "type": "Feature",
  "properties": {
    "iso:country":"ES",
    "sg:address":"Calle de Feria Jerez, 5",
    "sg:city":"Fuengirola",
    "sg:orig_category":"Inmobiliaria (agencias)",
    "sg:phone":"+34 952 66 75 06",
    "sg:postcode":"29640",
    "sg:province":"M\u00e1laga",
    "wof:name":"Atanai Gestion Inmobiliaria S.l.",
    "wof:placetype":"venue"
},
  "geometry": {"coordinates":[-4.6238160133,36.5489044189],"type":"Point"}
}