{
  "type": "Feature",
  "properties": {
    "addr:full":"Calle de Santa Lucia, 4 Aranda Duero Burgos 09400",
    "addr:housenumber":"4",
    "addr:postcode":"09400",
    "addr:street":"Calle De Santa Lucia",
    "iso:country":"ES",
    "sg:address":"Calle de Santa Lucia, 4",
    "sg:city":"Aranda Duero",
    "sg:orig_category":"M\u00c1quinas De Coser Y De Hacer Punto (al Por Mayor)",
    "sg:phone":"+34 947 50 03 84",
    "sg:postcode":"09400",
    "sg:province":"Burgos",
    "wof:name":"Fernando Benito Medrano Y Concepcion Crucis Delgado Cb",
    "wof:placetype":"venue"
},
  "geometry": {"coordinates":[-3.6876029968,41.67004776],"type":"Point"}
}