{
  "type": "Feature",
  "properties": {
    "iso:country":"ES",
    "sg:address":"Carrer de L'hospital, 124",
    "sg:city":"Barcelona",
    "sg:orig_category":"Camiser\u00cda Y Ropa Interior Masculina (al Por Menor)",
    "sg:phone":"+34 934 42 37 39",
    "sg:postcode":"08001",
    "sg:province":"Barcelona",
    "wof:name":"Pamies De Riu Ferran",
    "wof:placetype":"venue"
},
  "geometry": {"coordinates":[2.1671845913,41.3795509338],"type":"Point"}
}