{
  "type": "Feature",
  "properties": {
    "iso:country":"ES",
    "sg:address":"Avda Heroes De Baler, S/n",
    "sg:city":"Caceres",
    "sg:orig_category":"Organizaci\u00d3n De Seminarios, Congresos",
    "sg:phone":"+34 927 24 54 00",
    "sg:postcode":"10004",
    "sg:province":"C\u00e1ceres",
    "wof:name":"Seminario Diocesano Coria-caceres",
    "wof:placetype":"venue"
},
  "geometry": {"coordinates":[-6.3645839691,39.4840545654],"type":"Point"}
}