{
  "type": "Feature",
  "properties": {
    "addr:full":"Carrer de Ca N'alzina, 102 Torre-romeu Barcelona 08202",
    "addr:housenumber":"102",
    "addr:postcode":"08202",
    "addr:street":"Carrer De Ca N'Alzina;Barcelona",
    "iso:country":"ES",
    "sg:address":"Carrer de Ca N'alzina, 102",
    "sg:city":"Torre-romeu",
    "sg:orig_category":"Fabrica De Charcuter\u00cda",
    "sg:phone":"+34 937 26 53 54",
    "sg:postcode":"08202",
    "sg:province":"Barcelona",
    "wof:name":"Desarrollos Carnicos S.l.",
    "wof:placetype":"venue"
},
  "geometry": {"coordinates":[2.1323900223,41.5427436829],"type":"Point"}
}