{
  "type": "Feature",
  "properties": {
    "addr:full":"Rua Progreso (do), 13 Lugo Lugo 27001",
    "addr:housenumber":"13",
    "addr:postcode":"27001",
    "addr:street":"Rua Progreso Do",
    "iso:country":"ES",
    "sg:address":"Rua Progreso (do), 13",
    "sg:city":"Lugo",
    "sg:orig_category":"Ropa Para Caballeros (al Por Menor)",
    "sg:phone":"+34 982 25 39 49",
    "sg:postcode":"27001",
    "sg:province":"Lugo",
    "wof:name":"Ropas Y Vestidos S.l.",
    "wof:placetype":"venue"
},
  "geometry": {"coordinates":[-7.5546960831,43.0110168457],"type":"Point"}
}