{
  "type": "Feature",
  "properties": {
    "iso:country":"ES",
    "sg:address":"Avda Fernando Diaz Herrero, 5",
    "sg:city":"Casarabonela",
    "sg:orig_category":"Discotecas Y Salas De Baile",
    "sg:phone":"+34 952 45 68 17",
    "sg:postcode":"29566",
    "sg:province":"M\u00e1laga",
    "wof:name":"Santiago Trujillo Miguel",
    "wof:placetype":"venue"
},
  "geometry": {"coordinates":[-4.8419981003,36.7878837585],"type":"Point"}
}