{
  "type": "Feature",
  "properties": {
    "addr:full":"Calle de Madrid, 42 Almansa Albacete 02640",
    "addr:housenumber":"42",
    "addr:postcode":"02640",
    "addr:street":"Calle De Madrid",
    "iso:country":"ES",
    "sg:address":"Calle de Madrid, 42",
    "sg:city":"Almansa",
    "sg:orig_category":"Confecci\u00d3n De Zapatos",
    "sg:phone":"+34 967 31 11 48",
    "sg:postcode":"02640",
    "sg:province":"Albacete",
    "wof:name":"Divoni S.l.",
    "wof:placetype":"venue"
},
  "geometry": {"coordinates":[-1.1087310314,38.871673584],"type":"Point"}
}