{
  "type": "Feature",
  "properties": {
    "iso:country":"ES",
    "sg:address":"Calle de Sonseca, S/n",
    "sg:city":"Yepes",
    "sg:orig_category":"Mec\u00c1nico Del Autom\u00d3vil",
    "sg:phone":"+34 925 15 50 67",
    "sg:postcode":"45313",
    "sg:province":"Toledo",
    "wof:name":"Talleres Mecanicos Yepes S.l",
    "wof:placetype":"venue"
},
  "geometry": {"coordinates":[-3.6927530766,39.9123535156],"type":"Point"}
}