{
  "type": "Feature",
  "properties": {
    "addr:full":"Calle de Segovia, 2 Alcorcon Madrid 28922",
    "addr:housenumber":"2",
    "addr:postcode":"28922",
    "addr:street":"Calle De Segovia",
    "iso:country":"ES",
    "sg:address":"Calle de Segovia, 2",
    "sg:city":"Alcorcon",
    "sg:orig_category":"Molduras, Junquillos, Listones Y Molduras Perforadas",
    "sg:phone":"+34 916 43 16 51",
    "sg:postcode":"28922",
    "sg:province":"Madrid",
    "wof:name":"Palomino Lopez Eva",
    "wof:placetype":"venue"
},
  "geometry": {"coordinates":[-3.8503348827,40.3610992432],"type":"Point"}
}