{
  "type": "Feature",
  "properties": {
    "addr:full":"Calle de Tomillo (del), 26 Torrevieja Alicante 03180",
    "addr:postcode":"03180",
    "addr:street":"Calle De Tomillo Del",
    "iso:country":"ES",
    "sg:address":"Calle de Tomillo (del), 26",
    "sg:city":"Torrevieja",
    "sg:orig_category":"Empresas De Carpinter\u00cda",
    "sg:phone":"+34 965 71 78 16",
    "sg:postcode":"03180",
    "sg:province":"Alicante",
    "wof:name":"Perello Quesada Jose Vicente",
    "wof:placetype":"venue"
},
  "geometry": {"coordinates":[-0.6818429828,37.9834251404],"type":"Point"}
}