{
  "type": "Feature",
  "properties": {
    "iso:country":"ES",
    "sg:address":"Calle de Marques De Paradas, 38",
    "sg:city":"Sevilla",
    "sg:orig_category":"Quincaller\u00cda (al Por Menor)",
    "sg:phone":"+34 954 21 72 63",
    "sg:postcode":"41001",
    "sg:province":"Sevilla",
    "wof:name":"Nu\u00f1ez Lerida Juan Manuel",
    "wof:placetype":"venue"
},
  "geometry": {"coordinates":[-6.0013861656,37.3912277222],"type":"Point"}
}