{
  "type": "Feature",
  "properties": {
    "addr:full":"Calle de Canovas Del Castillo, 11 Valladolid Valladolid 47002",
    "addr:housenumber":"11",
    "addr:postcode":"47002",
    "addr:street":"Calle De Canovas Del Castillo",
    "iso:country":"ES",
    "sg:address":"Calle de Canovas Del Castillo, 11",
    "sg:city":"Valladolid",
    "sg:orig_category":"Agencias De Viajes",
    "sg:phone":"+34 983 39 86 44",
    "sg:postcode":"47002",
    "sg:province":"Valladolid",
    "sg:website":"www.barceloviajes.com",
    "wof:name":"Viajes Barcelo S.l.",
    "wof:placetype":"venue"
},
  "geometry": {"coordinates":[-4.7252225876,41.6520996094],"type":"Point"}
}