{
  "type": "Feature",
  "properties": {
    "iso:country":"ES",
    "sg:address":"Avda Pirineos (de Los), 7",
    "sg:city":"Huesca",
    "sg:orig_category":"Material Y Suministros Para Fotocopiadoras, Reprograf\u00cda",
    "sg:phone":"+34 974 24 10 61",
    "sg:postcode":"22004",
    "sg:province":"Huesca",
    "wof:name":"Microinformatica Huesca S.l.",
    "wof:placetype":"venue"
},
  "geometry": {"coordinates":[-0.4164899886,42.1418190002],"type":"Point"}
}