{
  "type": "Feature",
  "properties": {
    "addr:full":"C/ Pitagoras, 14 Torrellano Alicante 03320",
    "addr:housenumber":"14",
    "addr:postcode":"03320",
    "addr:street":"C / Pitagoras",
    "iso:country":"ES",
    "sg:address":"C/ Pitagoras, 14",
    "sg:city":"Torrellano",
    "sg:orig_category":"Reciclaje, Tratamiento De Tejidos",
    "sg:phone":"+34 965 68 25 86",
    "sg:postcode":"03320",
    "sg:province":"Alicante",
    "wof:name":"Acabados Agullo S.l.",
    "wof:placetype":"venue"
},
  "geometry": {"coordinates":[-0.60935,38.296181],"type":"Point"}
}