{
  "type": "Feature",
  "properties": {
    "iso:country":"ES",
    "sg:address":"Calle de Limon Verde, 36",
    "sg:city":"Algete",
    "sg:orig_category":"Librer\u00cdas",
    "sg:phone":"+34 916 29 15 92",
    "sg:postcode":"28110",
    "sg:province":"Madrid",
    "wof:name":"Libreria El Arbol De Las Letras S.l.",
    "wof:placetype":"venue"
},
  "geometry": {"coordinates":[-3.4986162186,40.5985488892],"type":"Point"}
}