{
  "type": "Feature",
  "properties": {
    "addr:full":"Condes Del Prado, 26 Arjona Ja\u00e9n 23760",
    "addr:housenumber":"26",
    "addr:postcode":"23760",
    "addr:street":"Del Prado;Jae\u0301N",
    "iso:country":"ES",
    "sg:address":"Condes Del Prado, 26",
    "sg:city":"Arjona",
    "sg:orig_category":"Electrodom\u00c9sticos (fabricaci\u00d3n, Al Por Mayor)",
    "sg:phone":"+34 953 51 81 54",
    "sg:postcode":"23760",
    "sg:province":"Ja\u00e9n",
    "wof:name":"Espinosa Jimenez Pedro Mateo",
    "wof:placetype":"venue"
},
  "geometry": {"coordinates":[-4.0609068871,37.9375991821],"type":"Point"}
}