{
  "type": "Feature",
  "properties": {
    "iso:country":"ES",
    "sg:address":"Calle de Panaderos, 59",
    "sg:city":"Valladolid",
    "sg:orig_category":"Alquiler De V\u00cddeo",
    "sg:phone":"+34 983 30 17 14",
    "sg:postcode":"47004",
    "sg:province":"Valladolid",
    "wof:name":"Pais Mongil Maria De Los Angeles",
    "wof:placetype":"venue"
},
  "geometry": {"coordinates":[-4.7224302292,41.645488739],"type":"Point"}
}