{
  "type": "Feature",
  "properties": {
    "addr:full":"Calle de Langaran, 24 Bilbao Vizcaya 48004",
    "addr:housenumber":"24",
    "addr:postcode":"48004",
    "addr:street":"Calle De Langaran",
    "iso:country":"ES",
    "sg:address":"Calle de Langaran, 24",
    "sg:city":"Bilbao",
    "sg:orig_category":"Carnicer\u00cdas, Carnicer\u00cdas",
    "sg:phone":"+34 944 12 26 28",
    "sg:postcode":"48004",
    "sg:province":"Vizcaya",
    "wof:name":"Pallares Marquez Maria Pilar",
    "wof:placetype":"venue"
},
  "geometry": {"coordinates":[-2.8980989456,43.2608413696],"type":"Point"}
}