{
  "type": "Feature",
  "properties": {
    "addr:full":"Las Jacarandas, 7 Benahavis M\u00e1laga 29679",
    "addr:housenumber":"7",
    "addr:postcode":"29679",
    "addr:street":"Benahavis Ma\u0301Laga",
    "iso:country":"ES",
    "sg:address":"Las Jacarandas, 7",
    "sg:city":"Benahavis",
    "sg:orig_category":"Administradores De Bienes Y Delegados De Comunidades De Propietarios",
    "sg:phone":"+34 952 76 21 90",
    "sg:postcode":"29679",
    "sg:province":"M\u00e1laga",
    "wof:name":"La Quinta Administracion S.a.",
    "wof:placetype":"venue"
},
  "geometry": {"coordinates":[-5.0462741852,36.5238952637],"type":"Point"}
}