{
  "type": "Feature",
  "properties": {
    "iso:country":"ES",
    "sg:address":"Calle de Alberto Aguilera, 5",
    "sg:city":"Madrid",
    "sg:orig_category":"Cervecer\u00cdas",
    "sg:phone":"+34 914 48 31 46",
    "sg:postcode":"28015",
    "sg:province":"Madrid",
    "wof:name":"Roldan Rico Francisco",
    "wof:placetype":"venue"
},
  "geometry": {"coordinates":[-3.7079269886,40.4297409058],"type":"Point"}
}