{
  "type": "Feature",
  "properties": {
    "addr:full":"Calle de Infanta Maria Teresa, 14 Madrid Madrid 28016",
    "addr:housenumber":"14",
    "addr:postcode":"madrid;28016",
    "addr:street":"Calle De Infanta Maria Teresa",
    "iso:country":"ES",
    "sg:address":"Calle de Infanta Maria Teresa, 14",
    "sg:city":"Madrid",
    "sg:orig_category":"Psic\u00d3logos",
    "sg:phone":"+34 914 57 22 07",
    "sg:postcode":"28016",
    "sg:province":"Madrid",
    "wof:name":"Sanz Sanchez Soledad",
    "wof:placetype":"venue"
},
  "geometry": {"coordinates":[-3.6805460453,40.4539718628],"type":"Point"}
}