{
  "type": "Feature",
  "properties": {
    "iso:country":"ES",
    "sg:address":"Avda Malaga, 131",
    "sg:city":"Cala Moral",
    "sg:orig_category":"Zapatos (al Por Menor)",
    "sg:phone":"+34 952 97 14 36",
    "sg:postcode":"29720",
    "sg:province":"M\u00e1laga",
    "wof:name":"Trujillo Cortes Maria Del Rosario",
    "wof:placetype":"venue"
},
  "geometry": {"coordinates":[-4.3123288155,36.7152481079],"type":"Point"}
}