{
  "type": "Feature",
  "properties": {
    "iso:country":"ES",
    "sg:address":"Luga Quintas (as), 21",
    "sg:city":"Quintas",
    "sg:orig_category":"Promotores Constructores",
    "sg:phone":"+34 988 38 20 73",
    "sg:postcode":"32930",
    "sg:province":"Ourense",
    "wof:name":"Construcciones Santa Tecla San Lorenzo De Pi\u00f1or Orense S.l.",
    "wof:placetype":"venue"
},
  "geometry": {"coordinates":[-7.903219223,42.3327789307],"type":"Point"}
}