{
  "type": "Feature",
  "properties": {
    "addr:full":"Coop. J. Obrero, S/n Cabra C\u00f3rdoba 14940",
    "addr:postcode":"14940",
    "addr:street":"S / N",
    "iso:country":"ES",
    "sg:address":"Coop. J. Obrero, S/n",
    "sg:city":"Cabra",
    "sg:classifiers":[
        {
            "category":"Taxi",
            "type":"Transportation"
        }
    ],
    "sg:phone":"+34 957 52 36 11",
    "sg:postcode":"14940",
    "sg:province":"C\u00f3rdoba",
    "wof:name":"Guarde\u00f1o Urbano Fernando",
    "wof:placetype":"venue"
},
  "geometry": {"coordinates":[-4.4261989594,37.4731788635],"type":"Point"}
}