{
  "type": "Feature",
  "properties": {
    "addr:full":"Calle de Sancho El Sabio, 15 Vitoria-gasteiz \u00c1lava 01008",
    "addr:housenumber":"15",
    "addr:postcode":"01008",
    "addr:street":"Calle De Sancho El Sabio",
    "iso:country":"ES",
    "sg:address":"Calle de Sancho El Sabio, 15",
    "sg:city":"Vitoria-gasteiz",
    "sg:orig_category":"Molduras, Junquillos, Listones Y Molduras Perforadas",
    "sg:phone":"+34 945 13 07 32",
    "sg:postcode":"01008",
    "sg:province":"\u00c1lava",
    "wof:name":"C.t.a. Comunicaciones Telefonicas Alavesas",
    "wof:placetype":"venue"
},
  "geometry": {"coordinates":[-2.6800830364,42.8478126526],"type":"Point"}
}