{
  "type": "Feature",
  "properties": {
    "iso:country":"ES",
    "sg:address":"Calle de Azkue Resurreccion Maria De, 1",
    "sg:city":"Bilbao",
    "sg:orig_category":"Lanas (al Por Mayor)",
    "sg:phone":"+34 944 05 38 51",
    "sg:postcode":"48004",
    "sg:province":"Vizcaya",
    "wof:name":"Adelaida Pintado Guerra",
    "wof:placetype":"venue"
},
  "geometry": {"coordinates":[-2.9160861969,43.2531700134],"type":"Point"}
}