{
  "type": "Feature",
  "properties": {
    "addr:full":"Carrer de Batllevell, 199 Sabadell Barcelona 08208",
    "addr:housenumber":"199",
    "addr:postcode":"08208",
    "addr:street":"Carrer De Batllevell",
    "iso:country":"ES",
    "sg:address":"Carrer de Batllevell, 199",
    "sg:city":"Sabadell",
    "sg:orig_category":"Molduras, Junquillos, Listones Y Molduras Perforadas",
    "sg:phone":"+34 937 17 63 03",
    "sg:postcode":"08208",
    "sg:province":"Barcelona",
    "wof:name":"Telefonia De Pago D.p.s. S.l.",
    "wof:placetype":"venue"
},
  "geometry": {"coordinates":[2.1035039425,41.5601425171],"type":"Point"}
}