{
  "type": "Feature",
  "properties": {
    "iso:country":"ES",
    "sg:address":"Calle de Jose Gallardo, 13",
    "sg:city":"Villanueva Serena",
    "sg:orig_category":"Inform\u00c1tica: Soportes De Informaci\u00d3n, Suministros & Accesorios",
    "sg:phone":"+34 924 84 01 61",
    "sg:postcode":"06700",
    "sg:province":"Badajoz",
    "sg:website":"www.sumipal.org",
    "wof:name":"Corraliza Simon Maria Jose",
    "wof:placetype":"venue"
},
  "geometry": {"coordinates":[-5.7964038849,38.9689483643],"type":"Point"}
}