{
  "type": "Feature",
  "properties": {
    "iso:country":"ES",
    "sg:address":"Carrer de Pi I Margall, 3",
    "sg:city":"Hostalets Pierola",
    "sg:orig_category":"Hilaturas, Hilos Y Actividades Relacionadas",
    "sg:phone":"+34 937 71 27 23",
    "sg:postcode":"08781",
    "sg:province":"Barcelona",
    "wof:name":"Robles Moreno Encarnita",
    "wof:placetype":"venue"
},
  "geometry": {"coordinates":[1.7722959518,41.5334510803],"type":"Point"}
}