{
  "type": "Feature",
  "properties": {
    "iso:country":"ES",
    "sg:address":"Calle de Norte Del, 3",
    "sg:city":"Langreo",
    "sg:orig_category":"Agencias De Viajes",
    "sg:phone":"+34 985 68 18 07",
    "sg:postcode":"33930",
    "sg:province":"Asturias",
    "sg:website":"www.viajeselcorteingles.es",
    "wof:name":"Viajes El Corte Ingles S.a.",
    "wof:placetype":"venue"
},
  "geometry": {"coordinates":[-5.7070870399,43.3195877075],"type":"Point"}
}