{
  "type": "Feature",
  "properties": {
    "addr:full":"Avda Valencia, 32 Denia Alicante 03700",
    "addr:housenumber":"32",
    "addr:postcode":"03700",
    "addr:street":"Avda Valencia",
    "iso:country":"ES",
    "sg:address":"Avda Valencia, 32",
    "sg:city":"Denia",
    "sg:orig_category":"Electrodom\u00c9sticos (al Por Menor)",
    "sg:phone":"+34 965 78 08 94",
    "sg:postcode":"03700",
    "sg:province":"Alicante",
    "wof:name":"Electrodomesticos Y Electricidad Costa S.l.",
    "wof:placetype":"venue"
},
  "geometry": {"coordinates":[0.1003020033,38.839756012],"type":"Point"}
}