{
  "type": "Feature",
  "properties": {
    "iso:country":"ES",
    "sg:address":"Carrer de Tarragona, 30",
    "sg:city":"Gava",
    "sg:orig_category":"Electricidad, Electr\u00d3nica: Material Y Suministros (al Por Mayor)",
    "sg:phone":"+34 936 33 38 50",
    "sg:postcode":"08850",
    "sg:province":"Barcelona",
    "sg:website":"www.kopa.biz",
    "wof:name":"Kopa Electronica S.l.",
    "wof:placetype":"venue"
},
  "geometry": {"coordinates":[2.0125100613,41.2997894287],"type":"Point"}
}