{
  "type": "Feature",
  "properties": {
    "iso:country":"ES",
    "sg:address":"Calle de Marques De Bonanza, 3",
    "sg:city":"Jerez De La Frontera",
    "sg:orig_category":"Internados & Ense\u00d1anza Privada",
    "sg:phone":"+34 956 18 30 57",
    "sg:postcode":"11407",
    "sg:province":"C\u00e1diz",
    "wof:name":"Colegio El Cuco Jesus Maria Prov Castilla",
    "wof:placetype":"venue"
},
  "geometry": {"coordinates":[-6.1320900917,36.6957931519],"type":"Point"}
}