{
  "type": "Feature",
  "properties": {
    "iso:country":"ES",
    "sg:address":"Carretera Santander, 23",
    "sg:city":"Robledo De Torio",
    "sg:orig_category":"Aparatos E Instalaci\u00d3n De Regad\u00cdos",
    "sg:phone":"+34 987 28 17 60",
    "sg:postcode":"24197",
    "sg:province":"Le\u00f3n",
    "wof:name":"Tecnica Verde S.l.",
    "wof:placetype":"venue"
},
  "geometry": {"coordinates":[-5.5188531876,42.66147995],"type":"Point"}
}