{
  "type": "Feature",
  "properties": {
    "iso:country":"ES",
    "sg:address":"Rua Diputacion, 23",
    "sg:city":"Verin",
    "sg:orig_category":"Florister\u00cdas",
    "sg:phone":"+34 988 41 37 34",
    "sg:postcode":"32600",
    "sg:province":"Ourense",
    "wof:name":"Rodriguez Rodriguez Josefa",
    "wof:placetype":"venue"
},
  "geometry": {"coordinates":[-7.4355239868,41.9382019043],"type":"Point"}
}