{
  "type": "Feature",
  "properties": {
    "addr:full":"Calle de Fernandez Del Campo, 2 Bilbao Vizcaya 48010",
    "addr:housenumber":"2",
    "addr:postcode":"48010",
    "addr:street":"Calle De Fernandez Del Campo",
    "iso:country":"ES",
    "sg:address":"Calle de Fernandez Del Campo, 2",
    "sg:city":"Bilbao",
    "sg:classifiers":[
        {
            "category":"Personal",
            "subcategory":"Barber",
            "type":"Services"
        }
    ],
    "sg:phone":"+34 944 22 08 87",
    "sg:postcode":"48010",
    "sg:province":"Vizcaya",
    "sg:tags":[
        "caballeros",
        "de",
        "peluqueros"
    ],
    "wof:name":"Aguilera Aranda Antonio",
    "wof:placetype":"venue"
},
  "geometry": {"coordinates":[-2.9325590134,43.258266449],"type":"Point"}
}