{
  "type": "Feature",
  "properties": {
    "iso:country":"ES",
    "sg:address":"Calle de Ildefonso Rodriguez, 3",
    "sg:city":"Segovia",
    "sg:orig_category":"Delineantes",
    "sg:phone":"+34 921 46 06 09",
    "sg:postcode":"40001",
    "sg:province":"Segovia",
    "wof:name":"Artec Impresiones C.b.",
    "wof:placetype":"venue"
},
  "geometry": {"coordinates":[-4.1207551956,40.9496612549],"type":"Point"}
}