{
  "type": "Feature",
  "properties": {
    "iso:country":"ES",
    "sg:address":"Calle de Aguilas, 8",
    "sg:city":"Sevilla",
    "sg:orig_category":"Laboratorios Y Trabajos De Fotograf\u00cda, V\u00cddeo Y Cine",
    "sg:phone":"+34 954 21 27 74",
    "sg:postcode":"41004",
    "sg:province":"Sevilla",
    "wof:name":"Martin Iglesias S.l.",
    "wof:placetype":"venue"
},
  "geometry": {"coordinates":[-5.9892721176,37.389881134],"type":"Point"}
}