{
  "type": "Feature",
  "properties": {
    "addr:full":"Cmno Olivar (del), S/n Alguazas Murcia 30560",
    "addr:housenumber":"/ n",
    "addr:postcode":"30560",
    "addr:street":"Cmno Olivar Del S",
    "iso:country":"ES",
    "sg:address":"Cmno Olivar (del), S/n",
    "sg:city":"Alguazas",
    "sg:orig_category":"Congelados: Productos Alimentarios (fabricaci\u00d3n, Al Por Mayor)",
    "sg:phone":"+34 968 62 01 00",
    "sg:postcode":"30560",
    "sg:province":"Murcia",
    "wof:name":"Congelados Elite S.l.",
    "wof:placetype":"venue"
},
  "geometry": {"coordinates":[-1.242833972,38.0575370789],"type":"Point"}
}