{
  "type": "Feature",
  "properties": {
    "iso:country":"ES",
    "sg:address":"Calle de Balsa, 20",
    "sg:city":"Bullas",
    "sg:orig_category":"Electricidad: Instaladores",
    "sg:phone":"+34 968 65 46 00",
    "sg:postcode":"30180",
    "sg:province":"Murcia",
    "wof:name":"Abril Escamez Manuel",
    "wof:placetype":"venue"
},
  "geometry": {"coordinates":[-1.669931,38.050541],"type":"Point"}
}