{
  "type": "Feature",
  "properties": {
    "iso:country":"ES",
    "sg:address":"Plaz Encarnacion, 3",
    "sg:city":"Madrid",
    "sg:orig_category":"Obras Y Organismos Sociales",
    "sg:phone":"+34 915 47 03 10",
    "sg:postcode":"28013",
    "sg:province":"Madrid",
    "wof:name":"Aparicio Fernandez Raquel",
    "wof:placetype":"venue"
},
  "geometry": {"coordinates":[-3.7109668255,40.4196128845],"type":"Point"}
}