{
  "type": "Feature",
  "properties": {
    "iso:country":"ES",
    "sg:address":"Carrer de Gran De Gracia, 123",
    "sg:city":"Barcelona",
    "sg:orig_category":"Florister\u00cdas",
    "sg:phone":"+34 932 18 34 80",
    "sg:postcode":"08012",
    "sg:province":"Barcelona",
    "sg:website":"www.annabelfloristeria.com",
    "wof:name":"Gonzalez Cuevas Anabella",
    "wof:placetype":"venue"
},
  "geometry": {"coordinates":[2.1530659199,41.4017295837],"type":"Point"}
}