{
  "type": "Feature",
  "properties": {
    "iso:country":"ES",
    "sg:address":"Calle de Julian Camarillo, 33",
    "sg:city":"Madrid",
    "sg:orig_category":"Quincaller\u00cda (fabricaci\u00d3n)",
    "sg:phone":"+34 917 54 13 12",
    "sg:postcode":"28037",
    "sg:province":"Madrid",
    "wof:name":"Codiven S.l.",
    "wof:placetype":"venue"
},
  "geometry": {"coordinates":[-3.6261689663,40.4354858398],"type":"Point"}
}