{
  "type": "Feature",
  "properties": {
    "iso:country":"ES",
    "sg:address":"Avda Fernanda Y Bernarda, 13",
    "sg:city":"Utrera",
    "sg:orig_category":"Zapatos (al Por Mayor)",
    "sg:phone":"+34 955 86 57 38",
    "sg:postcode":"41710",
    "sg:province":"Sevilla",
    "wof:name":"Calzados Carretero S.l.",
    "wof:placetype":"venue"
},
  "geometry": {"coordinates":[-5.7847809792,37.1809196472],"type":"Point"}
}