{
  "type": "Feature",
  "properties": {
    "addr:full":"Calle de Pico De Las Palomas, 16 Malaga M\u00e1laga 29004",
    "addr:housenumber":"16",
    "addr:postcode":"29004",
    "addr:street":"Calle De Pico De Las Palomas;Ma\u0301Laga",
    "iso:country":"ES",
    "sg:address":"Calle de Pico De Las Palomas, 16",
    "sg:city":"Malaga",
    "sg:orig_category":"Farmacias",
    "sg:phone":"+34 952 32 66 69",
    "sg:postcode":"29004",
    "sg:province":"M\u00e1laga",
    "wof:name":"Paredes Felipe Maria Del Carmen",
    "wof:placetype":"venue"
},
  "geometry": {"coordinates":[-4.4432549477,36.6956634521],"type":"Point"}
}