{
  "type": "Feature",
  "properties": {
    "iso:country":"ES",
    "sg:address":"Carr Pau (la), 6",
    "sg:city":"Benicasim",
    "sg:orig_category":"Organizaci\u00d3n De Actos, Seminarios Y Congresos",
    "sg:phone":"+34 964 30 20 44",
    "sg:postcode":"12560",
    "sg:province":"Castell\u00f3n",
    "wof:name":"Garcia Zampella Elvetia",
    "wof:placetype":"venue"
},
  "geometry": {"coordinates":[0.0457400009,40.0510292053],"type":"Point"}
}