{
  "type": "Feature",
  "properties": {
    "iso:country":"ES",
    "sg:address":"Major, S/n",
    "sg:city":"S. Jaume Enveja",
    "sg:orig_category":"Bancos",
    "sg:phone":"+34 977 46 80 40",
    "sg:postcode":"43877",
    "sg:province":"Tarragona",
    "wof:name":"Banco Popular Espa\u00f1ol",
    "wof:placetype":"venue"
},
  "geometry": {"coordinates":[0.7172250152,40.7053337097],"type":"Point"}
}