{
  "type": "Feature",
  "properties": {
    "addr:full":"Cmno Caritat, 1 Tudela Navarra 31500",
    "addr:housenumber":"1",
    "addr:postcode":"31500",
    "addr:street":"Cmno Caritat",
    "iso:country":"ES",
    "sg:address":"Cmno Caritat, 1",
    "sg:city":"Tudela",
    "sg:orig_category":"Alquiler De V\u00cddeo",
    "sg:phone":"+34 948 82 76 07",
    "sg:postcode":"31500",
    "sg:province":"Navarra",
    "wof:name":"Star Tudela S.l.",
    "wof:placetype":"venue"
},
  "geometry": {"coordinates":[-1.5992779732,42.0583229065],"type":"Point"}
}