{
  "type": "Feature",
  "properties": {
    "iso:country":"ES",
    "sg:address":"Pla\u00c7 Sant Roc, 19",
    "sg:city":"Bellver Cerdanya",
    "sg:orig_category":"Inmobiliaria (agencias)",
    "sg:phone":"+34 973 51 04 14",
    "sg:postcode":"25720",
    "sg:province":"Lleida",
    "wof:name":"Universal De Servicios Inmobiliarios S.l.",
    "wof:placetype":"venue"
},
  "geometry": {"coordinates":[1.7763129473,42.371257782],"type":"Point"}
}