{
  "type": "Feature",
  "properties": {
    "addr:full":"Calle de Arquimedes, 3 Getafe Madrid 28906",
    "addr:housenumber":"3",
    "addr:postcode":"28906",
    "addr:street":"Calle De Arquimedes",
    "iso:country":"ES",
    "sg:address":"Calle de Arquimedes, 3",
    "sg:city":"Getafe",
    "sg:orig_category":"Frutas Y Legumbres Frescas (al Por Mayor)",
    "sg:phone":"+34 916 01 04 56",
    "sg:postcode":"28906",
    "sg:province":"Madrid",
    "wof:name":"Frusana S.l.",
    "wof:placetype":"venue"
},
  "geometry": {"coordinates":[-3.7793185711,40.2832756042],"type":"Point"}
}