{
  "type": "Feature",
  "properties": {
    "addr:full":"Pl Espanya, 18 Sabadell Barcelona 08208",
    "addr:housenumber":"18",
    "addr:postcode":"08208",
    "addr:street":"Pl Espanya",
    "iso:country":"ES",
    "sg:address":"Pl Espanya, 18",
    "sg:city":"Sabadell",
    "sg:orig_category":"Florister\u00cdas",
    "sg:phone":"+34 937 23 42 10",
    "sg:postcode":"08208",
    "sg:province":"Barcelona",
    "wof:name":"Torras Montsech Montserrat",
    "wof:placetype":"venue"
},
  "geometry": {"coordinates":[2.0967800617,41.5612182617],"type":"Point"}
}