{
  "type": "Feature",
  "properties": {
    "iso:country":"ES",
    "sg:address":"Rua San Pedro, 10",
    "sg:city":"Lugo",
    "sg:orig_category":"Librer\u00cdas",
    "sg:phone":"+34 982 22 74 58",
    "sg:postcode":"27001",
    "sg:province":"Lugo",
    "wof:name":"Lugolibro S.l.",
    "wof:placetype":"venue"
},
  "geometry": {"coordinates":[-7.5553340912,43.0102539062],"type":"Point"}
}