{
  "type": "Feature",
  "properties": {
    "addr:full":"Calle de Campi\u00d1a, 10 Madrid Madrid 28053",
    "addr:housenumber":"10",
    "addr:postcode":"madrid;28053",
    "addr:street":"Calle De Campin\u0303A",
    "iso:country":"ES",
    "sg:address":"Calle de Campi\u00d1a, 10",
    "sg:city":"Madrid",
    "sg:orig_category":"Quincaller\u00cda (al Por Mayor)",
    "sg:phone":"+34 915 07 35 28",
    "sg:postcode":"28053",
    "sg:province":"Madrid",
    "wof:name":"Garcia Alirangues Ana Maria",
    "wof:placetype":"venue"
},
  "geometry": {"coordinates":[-3.6701385975,40.3788452148],"type":"Point"}
}