{
  "type": "Feature",
  "properties": {
    "addr:full":"Carr Fornas, Des, 43 Eivissa Islas Baleares 07800",
    "addr:postcode":"07800",
    "addr:street":"Carr Fornas Des 43",
    "iso:country":"ES",
    "sg:address":"Carr Fornas, Des, 43",
    "sg:city":"Eivissa",
    "sg:orig_category":"Flores Y Plantas Naturales (al Por Mayor)",
    "sg:phone":"+34 971 30 27 40",
    "sg:postcode":"07800",
    "sg:province":"Islas Baleares",
    "wof:name":"Guasch Torres Maria Nieves",
    "wof:placetype":"venue"
},
  "geometry": {"coordinates":[1.4136278629,38.9080505371],"type":"Point"}
}