{
  "type": "Feature",
  "properties": {
    "iso:country":"ES",
    "sg:address":"I\u00f1igo Arista, 24",
    "sg:city":"Iru\u00f1a",
    "sg:orig_category":"Molduras, Junquillos, Listones Y Molduras Perforadas",
    "sg:phone":"+34 948 27 38 16",
    "sg:postcode":"31007",
    "sg:province":"Navarra",
    "wof:name":"Garcia Monarriz Yon",
    "wof:placetype":"venue"
},
  "geometry": {"coordinates":[-1.6547169685,42.8060073853],"type":"Point"}
}