{
  "type": "Feature",
  "properties": {
    "addr:full":"Calle de San Isidro, 17 Vinaros Castell\u00f3n 12500",
    "addr:housenumber":"17",
    "addr:postcode":"12500",
    "addr:street":"Calle De San Isidro",
    "iso:country":"ES",
    "sg:address":"Calle de San Isidro, 17",
    "sg:city":"Vinaros",
    "sg:orig_category":"Arquitectos",
    "sg:phone":"+34 964 45 67 31",
    "sg:postcode":"12500",
    "sg:province":"Castell\u00f3n",
    "wof:name":"Andreu Criado.arquitecte S.l.u.",
    "wof:placetype":"venue"
},
  "geometry": {"coordinates":[0.4749746919,40.4699783325],"type":"Point"}
}