{
  "type": "Feature",
  "properties": {
    "addr:full":"Carr Francesc Moragas, 1 Vilanova I La Geltru Barcelona 08800",
    "addr:housenumber":"1",
    "addr:postcode":"08800",
    "addr:street":"Carr Francesc Moragas",
    "iso:country":"ES",
    "sg:address":"Carr Francesc Moragas, 1",
    "sg:city":"Vilanova I La Geltru",
    "sg:orig_category":"Carnicer\u00cdas, Carnicer\u00cdas",
    "sg:phone":"+34 938 15 29 52",
    "sg:postcode":"08800",
    "sg:province":"Barcelona",
    "wof:name":"Monfort Balague Jaime",
    "wof:placetype":"venue"
},
  "geometry": {"coordinates":[1.7146259546,41.2212753296],"type":"Point"}
}