{
  "type": "Feature",
  "properties": {
    "iso:country":"ES",
    "sg:address":"Avda Espa\u00d1a, 11",
    "sg:city":"Caceres",
    "sg:orig_category":"Procuradores",
    "sg:phone":"+34 927 22 01 72",
    "sg:postcode":"10004",
    "sg:province":"C\u00e1ceres",
    "wof:name":"Mu\u00f1oz Garcia Antonia",
    "wof:placetype":"venue"
},
  "geometry": {"coordinates":[-6.3763971329,39.4717788696],"type":"Point"}
}