{
  "type": "Feature",
  "properties": {
    "iso:country":"ES",
    "sg:address":"Calle de Belen, 7",
    "sg:city":"Huetor-tajar",
    "sg:orig_category":"Farmacias",
    "sg:phone":"+34 958 33 20 67",
    "sg:postcode":"18360",
    "sg:province":"Granada",
    "wof:name":"Valseco Montano Francisco Javier",
    "wof:placetype":"venue"
},
  "geometry": {"coordinates":[-4.0457491875,37.1968231201],"type":"Point"}
}