{
  "type": "Feature",
  "properties": {
    "iso:country":"ES",
    "sg:address":"Avda Jorge Vigon, 22",
    "sg:city":"Logro\u00f1o",
    "sg:orig_category":"M\u00c9dicos: Estomatolog\u00cda",
    "sg:phone":"+34 941 26 24 26",
    "sg:postcode":"26003",
    "sg:province":"La Rioja",
    "wof:name":"Sufrate Simon Javier",
    "wof:placetype":"venue"
},
  "geometry": {"coordinates":[-2.4423820972,42.4620475769],"type":"Point"}
}