{
  "type": "Feature",
  "properties": {
    "addr:full":"Av Illice, 57 Torrellano Alicante 03320",
    "addr:housenumber":"57",
    "addr:postcode":"03320",
    "addr:street":"Av Illice",
    "iso:country":"ES",
    "sg:address":"Av Illice, 57",
    "sg:city":"Torrellano",
    "sg:orig_category":"\u00d3ptica: Instrumentos (fabricaci\u00d3n)",
    "sg:phone":"+34 965 68 22 09",
    "sg:postcode":"03320",
    "sg:province":"Alicante",
    "wof:name":"Jacobo Bonete Violeta Mercedes",
    "wof:placetype":"venue"
},
  "geometry": {"coordinates":[-0.585909009,38.2940063477],"type":"Point"}
}