{
  "type": "Feature",
  "properties": {
    "addr:full":"Carrer de Lepant, 285 Barcelona Barcelona 08025",
    "addr:housenumber":"285",
    "addr:postcode":"08025",
    "addr:street":"Carrer De Lepant",
    "iso:country":"ES",
    "sg:address":"Carrer de Lepant, 285",
    "sg:city":"Barcelona",
    "sg:orig_category":"Pod\u00d3logos: Pedicuros",
    "sg:phone":"+34 934 36 48 80",
    "sg:postcode":"08025",
    "sg:province":"Barcelona",
    "wof:name":"Cruset Benavent Teresa",
    "wof:placetype":"venue"
},
  "geometry": {"coordinates":[2.1755700111,41.4053001404],"type":"Point"}
}