{
  "type": "Feature",
  "properties": {
    "addr:full":"Calle de Sor Maria De Leiva, 12 Santo Domingo De La Calzada La Rioja 26250",
    "addr:housenumber":"12",
    "addr:postcode":"26250",
    "addr:street":"Calle De Sor Maria De Leiva;Rioja",
    "iso:country":"ES",
    "sg:address":"Calle de Sor Maria De Leiva, 12",
    "sg:city":"Santo Domingo De La Calzada",
    "sg:orig_category":"Comercio, Reparaci\u00d3n De Motocicletas, Bicicletas Y Piezas Sueltas",
    "sg:phone":"+34 941 34 22 07",
    "sg:postcode":"26250",
    "sg:province":"La Rioja",
    "wof:name":"Estenaga Glera Javier",
    "wof:placetype":"venue"
},
  "geometry": {"coordinates":[-2.9496939182,42.4400901794],"type":"Point"}
}