{
  "type": "Feature",
  "properties": {
    "addr:full":"Calle de Maria De Molina, 16 Valladolid Valladolid 47001",
    "addr:housenumber":"16",
    "addr:postcode":"47001",
    "addr:street":"Calle De Maria De Molina",
    "iso:country":"ES",
    "sg:address":"Calle de Maria De Molina, 16",
    "sg:city":"Valladolid",
    "sg:orig_category":"Arquitectos",
    "sg:phone":"+34 983 33 47 44",
    "sg:postcode":"47001",
    "sg:province":"Valladolid",
    "wof:name":"Burgue\u00f1o Barange Alvaro",
    "wof:placetype":"venue"
},
  "geometry": {"coordinates":[-4.7305822372,41.6496658325],"type":"Point"}
}