{
  "type": "Feature",
  "properties": {
    "iso:country":"ES",
    "sg:address":"Fd. Garcia Lorca, 1",
    "sg:city":"Villanueva Infantes",
    "sg:orig_category":"Empresas De Carpinter\u00cda Met\u00c1lica",
    "sg:phone":"+34 926 36 13 76",
    "sg:postcode":"13320",
    "sg:province":"Ciudad Real",
    "wof:name":"Sanchez Romero Francisco",
    "wof:placetype":"venue"
},
  "geometry": {"coordinates":[-3.0111939907,38.7334785461],"type":"Point"}
}