{
  "type": "Feature",
  "properties": {
    "addr:full":"Calle de Maestro Palau, 18 Paiporta Valencia 46200",
    "addr:housenumber":"18",
    "addr:postcode":"46200",
    "addr:street":"Calle De Maestro Palau",
    "iso:country":"ES",
    "sg:address":"Calle de Maestro Palau, 18",
    "sg:city":"Paiporta",
    "sg:orig_category":"Sociedades, Compa\u00d1\u00cdas Aseguradoras",
    "sg:phone":"+34 963 97 15 73",
    "sg:postcode":"46200",
    "sg:province":"Valencia",
    "sg:website":"www.mapfre.com",
    "wof:name":"Mapfre Servicios De Informatica",
    "wof:placetype":"venue"
},
  "geometry": {"coordinates":[-0.4139899909,39.4292945862],"type":"Point"}
}