{
  "type": "Feature",
  "properties": {
    "addr:full":"Calle de Hernan Cortes, 130 Villanueva Serena Badajoz 06700",
    "addr:housenumber":"130",
    "addr:postcode":"06700",
    "addr:street":"Calle De Hernan Cortes",
    "iso:country":"ES",
    "sg:address":"Calle de Hernan Cortes, 130",
    "sg:city":"Villanueva Serena",
    "sg:orig_category":"Forjas Y Altos Hornos",
    "sg:phone":"+34 924 84 17 86",
    "sg:postcode":"06700",
    "sg:province":"Badajoz",
    "wof:name":"Parejo Corraliza Diego",
    "wof:placetype":"venue"
},
  "geometry": {"coordinates":[-5.7931489944,38.975151062],"type":"Point"}
}