{
  "type": "Feature",
  "properties": {
    "iso:country":"ES",
    "sg:address":"Ctra Huerta Cabo, 14",
    "sg:city":"Melilla",
    "sg:orig_category":"Fabricaci\u00d3n De Juegos Y Juguetes",
    "sg:phone":"+34 952 67 39 40",
    "sg:postcode":"52006",
    "sg:province":"Melilla",
    "wof:name":"Heredia Martin Antonio Tomas",
    "wof:placetype":"venue"
},
  "geometry": {"coordinates":[-2.9398200512,35.2739982605],"type":"Point"}
}