{
  "type": "Feature",
  "properties": {
    "iso:country":"ES",
    "sg:address":"Calle de Porlier, 30",
    "sg:city":"Santa Cruz De Tenerife",
    "sg:orig_category":"Fabricaci\u00d3n De Telas Y Sedas",
    "sg:phone":"+34 922 29 22 84",
    "sg:postcode":"38004",
    "sg:province":"Santa Cruz De Tenerife",
    "wof:name":"Dialani Dialani Dharmu",
    "wof:placetype":"venue"
},
  "geometry": {"coordinates":[-16.2590141296,28.4669857025],"type":"Point"}
}