{
  "type": "Feature",
  "properties": {
    "addr:full":"Calle de Embajadores, 186 Madrid Madrid 28045",
    "addr:housenumber":"186",
    "addr:postcode":"28045",
    "addr:street":"Calle De Embajadores",
    "iso:country":"ES",
    "sg:address":"Calle de Embajadores, 186",
    "sg:city":"Madrid",
    "sg:orig_category":"Fabricaci\u00d3n, Importaci\u00d3n De Material Y Sistemas De Telecomunicaciones",
    "sg:phone":"+34 915 28 52 53",
    "sg:postcode":"28045",
    "sg:province":"Madrid",
    "wof:name":"Villalba Mayordomo Jose Maria",
    "wof:placetype":"venue"
},
  "geometry": {"coordinates":[-3.6937010288,40.3922271729],"type":"Point"}
}