{
  "type": "Feature",
  "properties": {
    "iso:country":"ES",
    "sg:address":"Ctra Rambla (la), 1",
    "sg:city":"Fernan Nu\u00e7ez",
    "sg:orig_category":"Granos Y Semillas (producci\u00d3n, Al Por Mayor)",
    "sg:phone":"+34 957 38 09 22",
    "sg:postcode":"14520",
    "sg:province":"C\u00f3rdoba",
    "wof:name":"Sociedad Cooperativa Andaluza De Cereales Y Otros De Fernan Nu\u00f1ez",
    "wof:placetype":"venue"
},
  "geometry": {"coordinates":[-4.7239189148,37.6722068787],"type":"Point"}
}