{
  "type": "Feature",
  "properties": {
    "iso:country":"ES",
    "sg:address":"Calle de Jesus Otero, 9",
    "sg:city":"Santillana",
    "sg:orig_category":"Molduras, Junquillos, Listones Y Molduras Perforadas",
    "sg:phone":"+34 942 84 03 30",
    "sg:postcode":"39330",
    "sg:province":"Cantabria",
    "wof:name":"Corral Lopez Luis Manuel",
    "wof:placetype":"venue"
},
  "geometry": {"coordinates":[-4.1085891724,43.3888092041],"type":"Point"}
}