{
  "type": "Feature",
  "properties": {
    "iso:country":"ES",
    "sg:address":"Calle de Virgen Milagrosa, 20",
    "sg:city":"Irun",
    "sg:orig_category":"Contenedores (mercanc\u00cdas)",
    "sg:phone":"+34 943 63 57 83",
    "sg:postcode":"20304",
    "sg:province":"Guip\u00f9zcoa",
    "wof:name":"Waldotrans Irun S.l.",
    "wof:placetype":"venue"
},
  "geometry": {"coordinates":[-1.7878049612,43.3338470459],"type":"Point"}
}