{
  "type": "Feature",
  "properties": {
    "iso:country":"ES",
    "sg:address":"Calle de Rosario, 15",
    "sg:city":"Torrecampo",
    "sg:orig_category":"Trabajos De Perforaciones, Sondeos, Construcci\u00d3n De Pozos",
    "sg:phone":"+34 957 15 50 19",
    "sg:postcode":"14410",
    "sg:province":"C\u00f3rdoba",
    "wof:name":"Garcia Higueras Antonio",
    "wof:placetype":"venue"
},
  "geometry": {"coordinates":[-4.6806120872,38.4724769592],"type":"Point"}
}