{
  "type": "Feature",
  "properties": {
    "addr:full":"Rbla Sant Jordi (de), 158 Ripollet Barcelona 08291",
    "addr:housenumber":"158",
    "addr:postcode":"08291",
    "addr:street":"Rbla Sant Jordi De",
    "iso:country":"ES",
    "sg:address":"Rbla Sant Jordi (de), 158",
    "sg:city":"Ripollet",
    "sg:orig_category":"Maquinaria Para Industrias Diversas",
    "sg:phone":"+34 935 86 53 17",
    "sg:postcode":"08291",
    "sg:province":"Barcelona",
    "wof:name":"Precedo Montes Mari Carmen",
    "wof:placetype":"venue"
},
  "geometry": {"coordinates":[2.1695098877,41.4945716858],"type":"Point"}
}