{
  "type": "Feature",
  "properties": {
    "iso:country":"ES",
    "sg:address":"Carrer de Masseva, 59",
    "sg:city":"Mataro",
    "sg:orig_category":"Centros Empresariales",
    "sg:phone":"+34 937 99 92 09",
    "sg:postcode":"08302",
    "sg:province":"Barcelona",
    "wof:name":"La Cinquena Gamma Sl",
    "wof:placetype":"venue"
},
  "geometry": {"coordinates":[2.4410700798,41.541759491],"type":"Point"}
}