{
  "type": "Feature",
  "properties": {
    "iso:country":"ES",
    "sg:address":"Calle de Villablanca, S/n",
    "sg:city":"Ayamonte",
    "sg:orig_category":"Centros De Educaci\u00d3n Especial",
    "sg:phone":"+34 959 32 04 38",
    "sg:postcode":"21400",
    "sg:province":"Huelva",
    "wof:name":"Junta De Andalucia",
    "wof:placetype":"venue"
},
  "geometry": {"coordinates":[-7.4015841484,37.2067489624],"type":"Point"}
}