{
  "type": "Feature",
  "properties": {
    "addr:full":"Ptda Llano San Jose, 58 Elche Alicante 03293",
    "addr:housenumber":"58",
    "addr:postcode":"03293",
    "addr:street":"Ptda Llano San Jose",
    "iso:country":"ES",
    "sg:address":"Ptda Llano San Jose, 58",
    "sg:city":"Elche",
    "sg:orig_category":"Confecci\u00d3n De Zapatos",
    "sg:phone":"+34 965 43 79 54",
    "sg:postcode":"03293",
    "sg:province":"Alicante",
    "wof:name":"Comodos Especiales S.l.u.",
    "wof:placetype":"venue"
},
  "geometry": {"coordinates":[-0.6995239854,38.2634811401],"type":"Point"}
}