{
  "type": "Feature",
  "properties": {
    "addr:full":"Las Eras, 36 Cistierna Le\u00f3n 24800",
    "addr:housenumber":"36",
    "addr:postcode":"24800",
    "addr:street":"Las Eras;Leo\u0301N",
    "iso:country":"ES",
    "sg:address":"Las Eras, 36",
    "sg:city":"Cistierna",
    "sg:orig_category":"Venta, Instalaci\u00d3n De Calefacci\u00d3n",
    "sg:phone":"+34 987 70 07 16",
    "sg:postcode":"24800",
    "sg:province":"Le\u00f3n",
    "wof:name":"Gonzalez Rodriguez Alfredo",
    "wof:placetype":"venue"
},
  "geometry": {"coordinates":[-5.12855196,42.8002662659],"type":"Point"}
}