{
  "type": "Feature",
  "properties": {
    "addr:full":"Partida L'olla, S/n Olla Alicante 03590",
    "addr:housenumber":"s / n",
    "addr:postcode":"03590",
    "addr:street":"Partida L'Olla",
    "iso:country":"ES",
    "sg:address":"Partida L'olla, S/n",
    "sg:city":"Olla",
    "sg:orig_category":"Inmobiliaria (agencias)",
    "sg:phone":"+34 966 88 03 83",
    "sg:postcode":"03590",
    "sg:province":"Alicante",
    "wof:name":"Elijaa S.l.",
    "wof:placetype":"venue"
},
  "geometry": {"coordinates":[-0.0314770006,38.6189727783],"type":"Point"}
}