{
  "type": "Feature",
  "properties": {
    "addr:full":"Cllj Ramos, 7 Santos De Maimona Badajoz 06230",
    "addr:housenumber":"7",
    "addr:postcode":"06230",
    "addr:street":"Ramos",
    "iso:country":"ES",
    "sg:address":"Cllj Ramos, 7",
    "sg:city":"Santos De Maimona",
    "sg:orig_category":"Zapatos (al Por Menor)",
    "sg:phone":"+34 924 57 11 97",
    "sg:postcode":"06230",
    "sg:province":"Badajoz",
    "wof:name":"Carraco Hernandez Antonio",
    "wof:placetype":"venue"
},
  "geometry": {"coordinates":[-6.3725099564,38.4434814453],"type":"Point"}
}