{
  "type": "Feature",
  "properties": {
    "iso:country":"ES",
    "sg:address":"Calle de Santa Eugenia, 7",
    "sg:city":"Arenas -areeta",
    "sg:orig_category":"Institutos De Belleza",
    "sg:phone":"+34 944 63 02 43",
    "sg:postcode":"48930",
    "sg:province":"Vizcaya",
    "wof:name":"Aguirregoicoa Elorriaga Natividad",
    "wof:placetype":"venue"
},
  "geometry": {"coordinates":[-3.0082809925,43.3258743286],"type":"Point"}
}