{
  "type": "Feature",
  "properties": {
    "iso:country":"ES",
    "sg:address":"Ctra N-401 (madrid-toledo), Km. 0018,0",
    "sg:city":"Fuenlabrada",
    "sg:orig_category":"Colchones (fabricaci\u00d3n, Al Por Mayor, Al Por Menor)",
    "sg:phone":"+34 916 42 04 29",
    "sg:postcode":"28946",
    "sg:province":"Madrid",
    "sg:website":"www.moblerone.com",
    "wof:name":"Mobles-22 S.l.",
    "wof:placetype":"venue"
},
  "geometry": {"coordinates":[-3.7928040028,40.2826004028],"type":"Point"}
}