{
  "type": "Feature",
  "properties": {
    "iso:country":"ES",
    "sg:address":"G.v. Marques Del Turia, 62",
    "sg:city":"Valencia",
    "sg:orig_category":"M\u00c9dicos: Pediatr\u00cda. Enfermedades De Los Ni\u00d1os",
    "sg:phone":"+34 963 95 58 73",
    "sg:postcode":"46005",
    "sg:province":"Valencia",
    "wof:name":"Gracia Antequera Miguel",
    "wof:placetype":"venue"
},
  "geometry": {"coordinates":[-0.3671480119,39.4674072266],"type":"Point"}
}