{
  "type": "Feature",
  "properties": {
    "addr:full":"Avda Corts Valencianes, 68 Tavernes Blanques Valencia 46016",
    "addr:housenumber":"68",
    "addr:postcode":"46016",
    "addr:street":"Avda Corts Valencianes",
    "iso:country":"ES",
    "sg:address":"Avda Corts Valencianes, 68",
    "sg:city":"Tavernes Blanques",
    "sg:orig_category":"Fabricaci\u00d3n De Muebles",
    "sg:phone":"+34 961 85 19 11",
    "sg:postcode":"46016",
    "sg:province":"Valencia",
    "wof:name":"Muebles Morte S.l.",
    "wof:placetype":"venue"
},
  "geometry": {"coordinates":[-0.3657000065,39.5065994263],"type":"Point"}
}