{
  "type": "Feature",
  "properties": {
    "iso:country":"ES",
    "sg:address":"Carr Portal De Mar, 4",
    "sg:city":"Mao",
    "sg:orig_category":"Ropa Para Se\u00d1oras Y Caballeros (al Por Menor)",
    "sg:phone":"+34 971 36 55 63",
    "sg:postcode":"07701",
    "sg:province":"Islas Baleares",
    "wof:name":"Suarez Suao Pedro Andres",
    "wof:placetype":"venue"
},
  "geometry": {"coordinates":[4.2646298409,39.8890304565],"type":"Point"}
}