{
  "type": "Feature",
  "properties": {
    "iso:country":"ES",
    "sg:address":"Av Reina Fabiola, S/n",
    "sg:city":"Platja D'aro",
    "sg:orig_category":"Asociaciones Y Clubs Deportivos",
    "sg:phone":"+34 972 82 58 20",
    "sg:postcode":"17250",
    "sg:province":"Girona",
    "wof:name":"Bosch Comerc S.l.",
    "wof:placetype":"venue"
},
  "geometry": {"coordinates":[2.8187398911,41.9808616638],"type":"Point"}
}