{
  "type": "Feature",
  "properties": {
    "iso:country":"ES",
    "sg:address":"Calle de Parral, 25",
    "sg:city":"Ayllon",
    "sg:orig_category":"Notarios",
    "sg:phone":"+34 921 55 30 09",
    "sg:postcode":"40520",
    "sg:province":"Segovia",
    "wof:name":"Arranz Arguello Enrique",
    "wof:placetype":"venue"
},
  "geometry": {"coordinates":[-3.3755507469,41.4187393188],"type":"Point"}
}