{
  "type": "Feature",
  "properties": {
    "addr:full":"Ptda Devadillo, 2 Picassent Valencia 46220",
    "addr:housenumber":"2",
    "addr:postcode":"46220",
    "addr:street":"Ptda Devadillo",
    "iso:country":"ES",
    "sg:address":"Ptda Devadillo, 2",
    "sg:city":"Picassent",
    "sg:orig_category":"Importaci\u00d3n",
    "sg:phone":"+34 961 24 27 85",
    "sg:postcode":"46220",
    "sg:province":"Valencia",
    "wof:name":"Garcia Sogo Magdalena",
    "wof:placetype":"venue"
},
  "geometry": {"coordinates":[-0.4595290124,39.3631401062],"type":"Point"}
}