{
  "type": "Feature",
  "properties": {
    "iso:country":"ES",
    "sg:address":"Calle de Juan Lirola, 5",
    "sg:city":"Almeria",
    "sg:orig_category":"Cajas De Ahorro",
    "sg:phone":"+34 950 26 79 66",
    "sg:postcode":"04001",
    "sg:province":"Almer\u00eda",
    "wof:name":"Caixa D'estalvis I Pensions De Barcelona",
    "wof:placetype":"venue"
},
  "geometry": {"coordinates":[-2.461879015,36.8409080505],"type":"Point"}
}