{
  "type": "Feature",
  "properties": {
    "iso:country":"ES",
    "sg:address":"Calle de Dragonera, 18",
    "sg:city":"Palma",
    "sg:orig_category":"Restaurantes",
    "sg:phone":"+34 971 28 30 90",
    "sg:postcode":"07014",
    "sg:province":"Islas Baleares",
    "wof:name":"Ying Yang  Long",
    "wof:placetype":"venue"
},
  "geometry": {"coordinates":[2.6287651062,39.5787658691],"type":"Point"}
}