{
  "type": "Feature",
  "properties": {
    "addr:full":"Calle de Puerto De Herrera, 2 Vitoria-gasteiz \u00c1lava 01013",
    "addr:housenumber":"2",
    "addr:postcode":"01013",
    "addr:street":"Calle De Puerto De Herrera",
    "iso:country":"ES",
    "sg:address":"Calle de Puerto De Herrera, 2",
    "sg:city":"Vitoria-gasteiz",
    "sg:orig_category":"Inform\u00c1tica (estudios, Servicios, Asesor\u00cda, Formaci\u00d3n)",
    "sg:phone":"+34 945 06 00 07",
    "sg:postcode":"01013",
    "sg:province":"\u00c1lava",
    "sg:website":"www.laboranet.net",
    "wof:name":"Laboranet-servicios Telematicos, S.l",
    "wof:placetype":"venue"
},
  "geometry": {"coordinates":[-2.6701610088,42.8602333069],"type":"Point"}
}