{
  "type": "Feature",
  "properties": {
    "addr:full":"Calle de Camino De Las Nieves, 20 Arcos Frontera C\u00e1diz 11630",
    "addr:housenumber":"20",
    "addr:postcode":"11630",
    "addr:street":"Calle De Camino De Las Nieves",
    "iso:country":"ES",
    "sg:address":"Calle de Camino De Las Nieves, 20",
    "sg:city":"Arcos Frontera",
    "sg:orig_category":"M\u00c9dicos: Ginecolog\u00cda Y Obstetricia",
    "sg:phone":"+34 956 70 01 17",
    "sg:postcode":"11630",
    "sg:province":"C\u00e1diz",
    "wof:name":"Serrano Vilar Sebastian",
    "wof:placetype":"venue"
},
  "geometry": {"coordinates":[-5.8095297813,36.7509498596],"type":"Point"}
}