{
  "type": "Feature",
  "properties": {
    "addr:full":"Rua Ecuador, 20 Vigo Pontevedra 36203",
    "addr:housenumber":"20",
    "addr:postcode":"36203",
    "addr:street":"Rua Ecuador",
    "iso:country":"ES",
    "sg:address":"Rua Ecuador, 20",
    "sg:city":"Vigo",
    "sg:orig_category":"Psicoterapeutas",
    "sg:phone":"+34 986 43 08 30",
    "sg:postcode":"36203",
    "sg:province":"Pontevedra",
    "wof:name":"Espacio Sofros S.l.",
    "wof:placetype":"venue"
},
  "geometry": {"coordinates":[-8.7220144272,42.2341804504],"type":"Point"}
}