{
  "type": "Feature",
  "properties": {
    "addr:full":"Cmno Hormigueras, 170 Madrid Madrid 28031",
    "addr:housenumber":"170",
    "addr:postcode":"28031",
    "addr:street":"Cmno Hormigueras",
    "iso:country":"ES",
    "sg:address":"Cmno Hormigueras, 170",
    "sg:city":"Madrid",
    "sg:orig_category":"Caf\u00c9s, Bares, Cervecer\u00cdas",
    "sg:phone":"+34 917 78 78 16",
    "sg:postcode":"28031",
    "sg:province":"Madrid",
    "wof:name":"Visu Hosteleria S.l.",
    "wof:placetype":"venue"
},
  "geometry": {"coordinates":[-3.634360075,40.3769683838],"type":"Point"}
}