{
  "type": "Feature",
  "properties": {
    "iso:country":"ES",
    "sg:address":"Av. B. Navarra, 44",
    "sg:city":"Iru\u00f1a",
    "sg:orig_category":"Promotores Constructores",
    "sg:phone":"+34 948 29 22 13",
    "sg:postcode":"31004",
    "sg:province":"Navarra",
    "wof:name":"A I J Asociados S.l.",
    "wof:placetype":"venue"
},
  "geometry": {"coordinates":[-1.6340028048,42.813621521],"type":"Point"}
}