{
  "type": "Feature",
  "properties": {
    "addr:full":"Carrer de Vinyes, 3 Can Sant Joan Barcelona 08110",
    "addr:housenumber":"3",
    "addr:postcode":"08110",
    "addr:street":"Carrer De Vinyes",
    "iso:country":"ES",
    "sg:address":"Carrer de Vinyes, 3",
    "sg:city":"Can Sant Joan",
    "sg:orig_category":"Telas Y Sedas (al Por Menor)",
    "sg:phone":"+34 935 75 22 69",
    "sg:postcode":"08110",
    "sg:province":"Barcelona",
    "wof:name":"Miranda Granados Fermina",
    "wof:placetype":"venue"
},
  "geometry": {"coordinates":[2.1817800999,41.4892234802],"type":"Point"}
}