{
  "type": "Feature",
  "properties": {
    "addr:full":"Pl Mercat, 3 Canals Valencia 46650",
    "addr:housenumber":"3",
    "addr:postcode":"46650",
    "addr:street":"Pl Mercat",
    "iso:country":"ES",
    "sg:address":"Pl Mercat, 3",
    "sg:city":"Canals",
    "sg:orig_category":"Farmacias",
    "sg:phone":"+34 962 24 10 57",
    "sg:postcode":"46650",
    "sg:province":"Valencia",
    "wof:name":"Farmacia Llaudes C.b.",
    "wof:placetype":"venue"
},
  "geometry": {"coordinates":[-0.588168025,38.9644203186],"type":"Point"}
}