{
  "type": "Feature",
  "properties": {
    "addr:full":"Calle de Alvarez Abellan, 30 Madrid Madrid 28025",
    "addr:housenumber":"30",
    "addr:postcode":"madrid;28025",
    "addr:street":"Calle De Alvarez Abellan",
    "iso:country":"ES",
    "sg:address":"Calle de Alvarez Abellan, 30",
    "sg:city":"Madrid",
    "sg:orig_category":"Autob\u00das (explotaci\u00d3n Y Servicios De)",
    "sg:phone":"+34 915 25 28 20",
    "sg:postcode":"28025",
    "sg:province":"Madrid",
    "wof:name":"Nogueira Prieto Eduardo",
    "wof:placetype":"venue"
},
  "geometry": {"coordinates":[-3.7304284573,40.3834152222],"type":"Point"}
}