{
  "type": "Feature",
  "properties": {
    "iso:country":"ES",
    "sg:address":"Calle de Ramon Y Cajal, 5",
    "sg:city":"Leganes",
    "sg:orig_category":"Cervezas, Bebidas (al Por Mayor)",
    "sg:phone":"+34 916 88 68 19",
    "sg:postcode":"28914",
    "sg:province":"Madrid",
    "wof:name":"Talsavero Empresarial S.l.",
    "wof:placetype":"venue"
},
  "geometry": {"coordinates":[-3.7417004108,40.3275642395],"type":"Point"}
}