{
  "type": "Feature",
  "properties": {
    "iso:country":"ES",
    "sg:address":"Avda Madrid, 14",
    "sg:city":"Laguna Duero",
    "sg:orig_category":"Promotores Constructores",
    "sg:phone":"+34 983 54 01 04",
    "sg:postcode":"47140",
    "sg:province":"Valladolid",
    "wof:name":"Driguez Sanz S.l.",
    "wof:placetype":"venue"
},
  "geometry": {"coordinates":[-4.7195987701,41.5803489685],"type":"Point"}
}