{
  "type": "Feature",
  "properties": {
    "addr:full":"Avda Ordo\u00d1o Ii, 2 Le\u00f3n Le\u00f3n 24001",
    "addr:housenumber":"2",
    "addr:postcode":"24001",
    "addr:street":"Avda Ordon\u0303O Ii;Leo\u0301N",
    "iso:country":"ES",
    "sg:address":"Avda Ordo\u00d1o Ii, 2",
    "sg:city":"Le\u00f3n",
    "sg:orig_category":"Complementos De Vestir (al Por Menor)",
    "sg:phone":"+34 987 27 08 82",
    "sg:postcode":"24001",
    "sg:province":"Le\u00f3n",
    "wof:name":"Macias Gandarillas Aurora",
    "wof:placetype":"venue"
},
  "geometry": {"coordinates":[-5.5722370148,42.5978775024],"type":"Point"}
}