{
  "type": "Feature",
  "properties": {
    "addr:full":"Calle de Miguel Hernandez (de), S/n Mejorada Campo Madrid 28840",
    "addr:postcode":"28840",
    "addr:street":"Calle De Miguel Hernandez De S / N Mejorada Campo",
    "iso:country":"ES",
    "sg:address":"Calle de Miguel Hernandez (de), S/n",
    "sg:city":"Mejorada Campo",
    "sg:orig_category":"Art\u00cdculos Funerarios (al Por Menor)",
    "sg:phone":"+34 916 79 38 67",
    "sg:postcode":"28840",
    "sg:province":"Madrid",
    "wof:name":"Servicios Funerarios Alcala-torrejon S.a.",
    "wof:placetype":"venue"
},
  "geometry": {"coordinates":[-3.4839839935,40.39585495],"type":"Point"}
}