{
  "type": "Feature",
  "properties": {
    "addr:full":"Cno. Azagador, 6 Vilamarxant Valencia 46191",
    "addr:housenumber":"6",
    "addr:postcode":"46191",
    "addr:street":"Azagador",
    "iso:country":"ES",
    "sg:address":"Cno. Azagador, 6",
    "sg:city":"Vilamarxant",
    "sg:orig_category":"Empresas De Carpinter\u00cda Met\u00c1lica",
    "sg:phone":"+34 962 71 03 27",
    "sg:postcode":"46191",
    "sg:province":"Valencia",
    "wof:name":"Sanchis Zarzo Enrique",
    "wof:placetype":"venue"
},
  "geometry": {"coordinates":[-0.616361022,39.5655136108],"type":"Point"}
}