{
  "type": "Feature",
  "properties": {
    "addr:full":"Calle de Baron De La Torre, 30 Cintruenigo Navarra 31592",
    "addr:housenumber":"30",
    "addr:postcode":"31592",
    "addr:street":"Calle De Baron De La Torre",
    "iso:country":"ES",
    "sg:address":"Calle de Baron De La Torre, 30",
    "sg:city":"Cintruenigo",
    "sg:orig_category":"Art\u00cdculos De Regalo (al Por Menor)",
    "sg:phone":"+34 948 81 10 55",
    "sg:postcode":"31592",
    "sg:province":"Navarra",
    "wof:name":"Bermejo Rincon Jose Maria",
    "wof:placetype":"venue"
},
  "geometry": {"coordinates":[-1.8085589409,42.0796546936],"type":"Point"}
}