{
  "type": "Feature",
  "properties": {
    "addr:full":"Calle de Carcaba, 13 Zalamea Serena Badajoz 06430",
    "addr:housenumber":"13",
    "addr:postcode":"06430",
    "addr:street":"Calle De Carcaba",
    "iso:country":"ES",
    "sg:address":"Calle de Carcaba, 13",
    "sg:city":"Zalamea Serena",
    "sg:orig_category":"Asesor\u00cda Fiscal Y Jur\u00cddica",
    "sg:phone":"+34 924 77 53 16",
    "sg:postcode":"06430",
    "sg:province":"Badajoz",
    "wof:name":"Carmona Moti\u00f1o Manuel",
    "wof:placetype":"venue"
},
  "geometry": {"coordinates":[-5.6606502533,38.6494979858],"type":"Point"}
}