{
  "type": "Feature",
  "properties": {
    "addr:full":"Calle de Redonda, 14 Rambla C\u00f3rdoba 14540",
    "addr:housenumber":"14",
    "addr:postcode":"14540",
    "addr:street":"Calle De Redonda;Rambla Co\u0301Rdoba",
    "iso:country":"ES",
    "sg:address":"Calle de Redonda, 14",
    "sg:city":"Rambla",
    "sg:orig_category":"Remolques, Carretillas De Mano Para Operaciones Portuarias",
    "sg:phone":"+34 957 68 22 14",
    "sg:postcode":"14540",
    "sg:province":"C\u00f3rdoba",
    "wof:name":"Remolques Osuna S.l",
    "wof:placetype":"venue"
},
  "geometry": {"coordinates":[-4.7444868088,37.6043624878],"type":"Point"}
}