{
  "type": "Feature",
  "properties": {
    "addr:full":"Luga Majadilla (la), S/n Morti Bajo Murcia 30850",
    "addr:housenumber":"/ n",
    "addr:postcode":"30850",
    "addr:street":"La S",
    "iso:country":"ES",
    "sg:address":"Luga Majadilla (la), S/n",
    "sg:city":"Morti Bajo",
    "sg:orig_category":"Alfarer\u00cda",
    "sg:phone":"+34 968 42 07 96",
    "sg:postcode":"30850",
    "sg:province":"Murcia",
    "wof:name":"Tudela Palacios Rufino",
    "wof:placetype":"venue"
},
  "geometry": {"coordinates":[-1.5030390024,37.7726860046],"type":"Point"}
}