{
  "type": "Feature",
  "properties": {
    "addr:full":"Calle de Julio, 1 Gijon Asturias 33209",
    "addr:housenumber":"1",
    "addr:postcode":"33209",
    "addr:street":"Calle De Julio",
    "iso:country":"ES",
    "sg:address":"Calle de Julio, 1",
    "sg:city":"Gijon",
    "sg:orig_category":"Bancos",
    "sg:phone":"+34 985 16 49 73",
    "sg:postcode":"33209",
    "sg:province":"Asturias",
    "wof:name":"Banco Espa\u00f1ol De Credito S.a.",
    "wof:placetype":"venue"
},
  "geometry": {"coordinates":[-5.666200161,43.5295372009],"type":"Point"}
}