{
  "type": "Feature",
  "properties": {
    "iso:country":"ES",
    "sg:address":"Barr Concepcion, S/n",
    "sg:city":"Cangas Onis",
    "sg:orig_category":"Importaci\u00d3n",
    "sg:phone":"+34 985 84 86 41",
    "sg:postcode":"33550",
    "sg:province":"Asturias",
    "sg:website":"www.lleu.es",
    "wof:name":"Lleu Comercio Y Productos S.l.",
    "wof:placetype":"venue"
},
  "geometry": {"coordinates":[-5.1302790642,43.3507957458],"type":"Point"}
}