{
  "type": "Feature",
  "properties": {
    "iso:country":"ES",
    "sg:address":"Avda Mediterraneo, 7",
    "sg:city":"Salobre\u00f1a",
    "sg:orig_category":"Construcciones Met\u00c1licas",
    "sg:phone":"+34 958 61 71 92",
    "sg:postcode":"18680",
    "sg:province":"Granada",
    "wof:name":"Estructuras Gsr S.l.",
    "wof:placetype":"venue"
},
  "geometry": {"coordinates":[-3.5827469826,36.7439804077],"type":"Point"}
}