{
  "type": "Feature",
  "properties": {
    "addr:full":"Carr Orxelles, 61 Benissa Alicante 03720",
    "addr:housenumber":"61",
    "addr:postcode":"03720",
    "addr:street":"Carr Orxelles",
    "iso:country":"ES",
    "sg:address":"Carr Orxelles, 61",
    "sg:city":"Benissa",
    "sg:orig_category":"Peluquer\u00cdas, Peluquer\u00cda Mixta",
    "sg:phone":"+34 965 73 20 72",
    "sg:postcode":"03720",
    "sg:province":"Alicante",
    "wof:name":"Ivars Cardona Jose",
    "wof:placetype":"venue"
},
  "geometry": {"coordinates":[0.045899,38.7134132385],"type":"Point"}
}