{
  "type": "Feature",
  "properties": {
    "iso:country":"ES",
    "sg:address":"Calle de Juan Florez, 15",
    "sg:city":"Coru\u00d1a",
    "sg:orig_category":"Agencias De Viajes",
    "sg:phone":"+34 981 20 44 94",
    "sg:postcode":"15004",
    "sg:province":"La Coru\u00f1a",
    "wof:name":"Reial Automobil Club De Catalunya",
    "wof:placetype":"venue"
},
  "geometry": {"coordinates":[-8.4081678391,43.3654975891],"type":"Point"}
}