{
  "type": "Feature",
  "properties": {
    "addr:full":"Calle de Catalu\u00d1a, 35 Malaga M\u00e1laga 29009",
    "addr:housenumber":"35",
    "addr:postcode":"29009",
    "addr:street":"Calle De Catalun\u0303A;Ma\u0301Laga",
    "iso:country":"ES",
    "sg:address":"Calle de Catalu\u00d1a, 35",
    "sg:city":"Malaga",
    "sg:orig_category":"Peluqueros: De Se\u00d1oras",
    "sg:phone":"+34 952 10 21 92",
    "sg:postcode":"29009",
    "sg:province":"M\u00e1laga",
    "wof:name":"Sanchez Garcia Benjamin",
    "wof:placetype":"venue"
},
  "geometry": {"coordinates":[-4.4345784187,36.7231864929],"type":"Point"}
}