{
  "type": "Feature",
  "properties": {
    "addr:full":"Calle de Duque De Lerma, 19 Toledo Toledo 45004",
    "addr:housenumber":"19",
    "addr:postcode":"45004",
    "addr:street":"Calle De Duque De Lerma",
    "iso:country":"ES",
    "sg:address":"Calle de Duque De Lerma, 19",
    "sg:city":"Toledo",
    "sg:orig_category":"Promotores Constructores",
    "sg:phone":"+34 925 22 79 50",
    "sg:postcode":"45004",
    "sg:province":"Toledo",
    "wof:name":"Dragados S.a.",
    "wof:placetype":"venue"
},
  "geometry": {"coordinates":[-4.026535511,39.8667793274],"type":"Point"}
}