{
  "type": "Feature",
  "properties": {
    "addr:full":"Rua Lavandeira, 17 Lugo Lugo 27003",
    "addr:housenumber":"17",
    "addr:postcode":"27003",
    "addr:street":"Rua Lavandeira",
    "iso:country":"ES",
    "sg:address":"Rua Lavandeira, 17",
    "sg:city":"Lugo",
    "sg:orig_category":"Cojinetes De Bolas, Agujas Y Rodillos (fabricaci\u00d3n, Al Por Mayor)",
    "sg:phone":"+34 982 21 91 41",
    "sg:postcode":"27003",
    "sg:province":"Lugo",
    "wof:name":"Rodamientos Josmar S.l.",
    "wof:placetype":"venue"
},
  "geometry": {"coordinates":[-7.5684380531,43.0263137817],"type":"Point"}
}