{
  "type": "Feature",
  "properties": {
    "iso:country":"ES",
    "sg:address":"Carr Cases Noves, 80",
    "sg:city":"Palafrugell",
    "sg:orig_category":"Pintura Industrial (trabajos De)",
    "sg:phone":"+34 972 30 21 63",
    "sg:postcode":"17200",
    "sg:province":"Girona",
    "wof:name":"Aillaments Generals Gironins S.a.",
    "wof:placetype":"venue"
},
  "geometry": {"coordinates":[3.1587853432,41.9195137024],"type":"Point"}
}