{
  "type": "Feature",
  "properties": {
    "addr:full":"Carrer de Transversal, 143 Terrassa Barcelona 08225",
    "addr:housenumber":"143",
    "addr:postcode":"08225",
    "addr:street":"Carrer De Transversal",
    "iso:country":"ES",
    "sg:address":"Carrer de Transversal, 143",
    "sg:city":"Terrassa",
    "sg:orig_category":"Inmobiliaria (agencias)",
    "sg:phone":"+34 937 89 13 24",
    "sg:postcode":"08225",
    "sg:province":"Barcelona",
    "wof:name":"Inmoclavall S.l.",
    "wof:placetype":"venue"
},
  "geometry": {"coordinates":[2.0086669922,41.5724830627],"type":"Point"}
}