{
  "type": "Feature",
  "properties": {
    "iso:country":"ES",
    "sg:address":"Mcdos C. Abastecimientos, 12",
    "sg:city":"Sevilla",
    "sg:orig_category":"Lavado, Limpieza De Veh\u00cdculos",
    "sg:phone":"+34 954 51 30 23",
    "sg:postcode":"41007",
    "sg:province":"Sevilla",
    "wof:name":"Altaller Sevilla Servicio De Lavado Y Engrase S.l.",
    "wof:placetype":"venue"
},
  "geometry": {"coordinates":[-5.9541826248,37.401134491],"type":"Point"}
}