{
  "type": "Feature",
  "properties": {
    "iso:country":"ES",
    "sg:address":"Calle de Cap Ramonell Boix, 168",
    "sg:city":"Palma",
    "sg:orig_category":"Aparatos De Medida, Control, Regulaci\u00d3n Y Detecci\u00d3n",
    "sg:phone":"+34 971 24 54 52",
    "sg:postcode":"07007",
    "sg:province":"Islas Baleares",
    "sg:website":"www.robotmallorca.com",
    "wof:name":"Robot S. A.",
    "wof:placetype":"venue"
},
  "geometry": {"coordinates":[2.6798961163,39.5590057373],"type":"Point"}
}