{
  "type": "Feature",
  "properties": {
    "iso:country":"ES",
    "sg:address":"C/ Bona-sort, 35",
    "sg:city":"Cerdanyola Valles",
    "sg:orig_category":"M\u00c1quinas De Coser Y De Hacer Punto (al Por Mayor)",
    "sg:phone":"+34 935 80 84 32",
    "sg:postcode":"08290",
    "sg:province":"Barcelona",
    "wof:name":"Lopez Martin Maria Dolores",
    "wof:placetype":"venue"
},
  "geometry": {"coordinates":[2.1470150948,41.4924812317],"type":"Point"}
}