{
  "type": "Feature",
  "properties": {
    "addr:full":"Pl Major, 17 Manresa Barcelona 08241",
    "addr:housenumber":"17",
    "addr:postcode":"08241",
    "addr:street":"Pl Major",
    "iso:country":"ES",
    "sg:address":"Pl Major, 17",
    "sg:city":"Manresa",
    "sg:orig_category":"Partidos Pol\u00cdticos",
    "sg:phone":"+34 938 72 63 52",
    "sg:postcode":"08241",
    "sg:province":"Barcelona",
    "wof:name":"Esquerra Republicana De Catalunya",
    "wof:placetype":"venue"
},
  "geometry": {"coordinates":[1.826753974,41.7233848572],"type":"Point"}
}