{
  "type": "Feature",
  "properties": {
    "addr:full":"Iglesias, 1 La Coronada Badajoz 06469",
    "addr:housenumber":"1",
    "addr:postcode":"06469",
    "addr:street":"Iglesias;La Coronada",
    "iso:country":"ES",
    "sg:address":"Iglesias, 1",
    "sg:city":"La Coronada",
    "sg:orig_category":"Aguas (distribuci\u00d3n, Servicios)",
    "sg:phone":"+34 924 82 61 61",
    "sg:postcode":"06469",
    "sg:province":"Badajoz",
    "wof:name":"Mancomunidad De Aguas La Coronada La Haba Y Magacela",
    "wof:placetype":"venue"
},
  "geometry": {"coordinates":[-5.6710691452,38.9195289612],"type":"Point"}
}