{
  "type": "Feature",
  "properties": {
    "addr:full":"Avda Cami D'artana, 2 Burriana Castell\u00f3n 12530",
    "addr:housenumber":"2",
    "addr:postcode":"12530",
    "addr:street":"Avda Cami D'Artana",
    "iso:country":"ES",
    "sg:address":"Avda Cami D'artana, 2",
    "sg:city":"Burriana",
    "sg:orig_category":"Peluquer\u00cdas, Peluquer\u00cda Mixta",
    "sg:phone":"+34 964 51 31 65",
    "sg:postcode":"12530",
    "sg:province":"Castell\u00f3n",
    "wof:name":"Mayka's Peluqueria S.l.",
    "wof:placetype":"venue"
},
  "geometry": {"coordinates":[-0.0905900002,39.8900680542],"type":"Point"}
}