{
  "type": "Feature",
  "properties": {
    "iso:country":"ES",
    "sg:address":"Calle de Pedro Pidal Arroyo, 11",
    "sg:city":"Villaviciosa",
    "sg:orig_category":"Empresas De Carpinter\u00cda Met\u00c1lica",
    "sg:phone":"+34 985 89 12 59",
    "sg:postcode":"33300",
    "sg:province":"Asturias",
    "wof:name":"Diaz Alvarez Juan Luis",
    "wof:placetype":"venue"
},
  "geometry": {"coordinates":[-5.4400758743,43.4777030945],"type":"Point"}
}