{
  "type": "Feature",
  "properties": {
    "iso:country":"ES",
    "sg:address":"Calle de Infanta Mercedes, 31",
    "sg:city":"Madrid",
    "sg:orig_category":"Ingenier\u00cda, Centros De Estudios (diversos)",
    "sg:phone":"+34 915 79 56 94",
    "sg:postcode":"28020",
    "sg:province":"Madrid",
    "wof:name":"Geasyt S.a.",
    "wof:placetype":"venue"
},
  "geometry": {"coordinates":[-3.6989729404,40.4548225403],"type":"Point"}
}