{
  "type": "Feature",
  "properties": {
    "iso:country":"ES",
    "sg:address":"Carrer de Sant Ferran, 5",
    "sg:city":"Argentona",
    "sg:orig_category":"Electricidad: Instaladores",
    "sg:phone":"+34 937 97 07 20",
    "sg:postcode":"08310",
    "sg:province":"Barcelona",
    "wof:name":"Muntatges Instal-llums S.l.",
    "wof:placetype":"venue"
},
  "geometry": {"coordinates":[2.399627924,41.5546569824],"type":"Point"}
}