{
  "type": "Feature",
  "properties": {
    "iso:country":"ES",
    "sg:address":"Plaz Nou D'octubre, 3",
    "sg:city":"Burriana",
    "sg:orig_category":"Ense\u00d1anza: Profesiones Art\u00cdsticas",
    "sg:phone":"+34 964 51 31 00",
    "sg:postcode":"12530",
    "sg:province":"Castell\u00f3n",
    "wof:name":"Garcia's C.b.",
    "wof:placetype":"venue"
},
  "geometry": {"coordinates":[-0.0840215012,39.8887367249],"type":"Point"}
}