{
  "type": "Feature",
  "properties": {
    "iso:country":"ES",
    "sg:address":"Pl Divina Pastora, 5",
    "sg:city":"Vic",
    "sg:orig_category":"Farmacias",
    "sg:phone":"+34 938 86 27 06",
    "sg:postcode":"08500",
    "sg:province":"Barcelona",
    "wof:name":"Arumi Fluvia Jaime",
    "wof:placetype":"venue"
},
  "geometry": {"coordinates":[2.2603535652,41.9311904907],"type":"Point"}
}