{
  "type": "Feature",
  "properties": {
    "addr:full":"Calle de Tomas Meabe, 30 Madrid Madrid 28019",
    "addr:housenumber":"30",
    "addr:postcode":"madrid;28019",
    "addr:street":"Calle De Tomas Meabe",
    "iso:country":"ES",
    "sg:address":"Calle de Tomas Meabe, 30",
    "sg:city":"Madrid",
    "sg:orig_category":"Aceites Y Grasas Alimentarias (fabricaci\u00d3n, Al Por Mayor)",
    "sg:phone":"+34 915 60 00 63",
    "sg:postcode":"28019",
    "sg:province":"Madrid",
    "wof:name":"Montes Montes Maria Del Rosario",
    "wof:placetype":"venue"
},
  "geometry": {"coordinates":[-3.713876009,40.3945922852],"type":"Point"}
}