{
  "type": "Feature",
  "properties": {
    "iso:country":"ES",
    "sg:address":"Calle de Real, 25",
    "sg:city":"S. Juan Puerto",
    "sg:orig_category":"Bazares, Art\u00cdculos De Limpieza Y De Cocina (al Por Menor)",
    "sg:phone":"+34 959 36 71 32",
    "sg:postcode":"21610",
    "sg:province":"Huelva",
    "wof:name":"Fernandez Garcia Encarnacion",
    "wof:placetype":"venue"
},
  "geometry": {"coordinates":[-6.8393421173,37.3152236938],"type":"Point"}
}