{
  "type": "Feature",
  "properties": {
    "iso:country":"ES",
    "sg:address":"Calle de Ca\u00d1os Del Peral, 7",
    "sg:city":"Madrid",
    "sg:orig_category":"Teatros Y Salas De Espect\u00c1culos",
    "sg:phone":"+34 915 59 90 04",
    "sg:postcode":"28013",
    "sg:province":"Madrid",
    "wof:name":"Ferreira Pregigueiro Maria Ester",
    "wof:placetype":"venue"
},
  "geometry": {"coordinates":[-3.708717823,40.4187927246],"type":"Point"}
}