{
  "type": "Feature",
  "properties": {
    "iso:country":"ES",
    "sg:address":"Avda General Sanjurjo, 132",
    "sg:city":"Coru\u00d1a",
    "sg:orig_category":"Ense\u00d1anza Variada",
    "sg:phone":"+34 981 13 30 50",
    "sg:postcode":"15006",
    "sg:province":"La Coru\u00f1a",
    "wof:name":"Centro De Estudios Abaco S.l.",
    "wof:placetype":"venue"
},
  "geometry": {"coordinates":[-8.3946580887,43.3537330627],"type":"Point"}
}