{
  "type": "Feature",
  "properties": {
    "iso:country":"ES",
    "sg:address":"Rua Lorient, 12",
    "sg:city":"Vigo",
    "sg:orig_category":"Librer\u00cdas",
    "sg:phone":"+34 986 20 22 34",
    "sg:postcode":"36210",
    "sg:province":"Pontevedra",
    "wof:name":"Miguelez Rio Antonio",
    "wof:placetype":"venue"
},
  "geometry": {"coordinates":[-8.7450895309,42.2110824585],"type":"Point"}
}