{
  "type": "Feature",
  "properties": {
    "iso:country":"ES",
    "sg:address":"Calle de Duquesa Villahermosa, 16",
    "sg:city":"Zaragoza",
    "sg:orig_category":"Internados & Ense\u00d1anza Privada",
    "sg:phone":"+34 976 33 35 24",
    "sg:postcode":"50010",
    "sg:province":"Zaragoza",
    "wof:name":"Cooperativa De Ense\u00f1anza Hijas De San Jose",
    "wof:placetype":"venue"
},
  "geometry": {"coordinates":[-0.900557518,41.648891449],"type":"Point"}
}