{
  "type": "Feature",
  "properties": {
    "addr:full":"Calle de Reina, 67 Valencia Valencia 46011",
    "addr:housenumber":"67",
    "addr:postcode":"46011",
    "addr:street":"Calle De Reina",
    "iso:country":"ES",
    "sg:address":"Calle de Reina, 67",
    "sg:city":"Valencia",
    "sg:orig_category":"Estancos",
    "sg:phone":"+34 963 71 56 84",
    "sg:postcode":"46011",
    "sg:province":"Valencia",
    "wof:name":"Carrasco Salvador Antonio Vicente",
    "wof:placetype":"venue"
},
  "geometry": {"coordinates":[-0.329151988,39.4666786194],"type":"Point"}
}