{
  "type": "Feature",
  "properties": {
    "addr:full":"Bjad Don Alonso, 5 Avila \u00c1vila 05003",
    "addr:housenumber":"5",
    "addr:postcode":"05003",
    "addr:street":"Don Alonso;A\u0301Vila",
    "iso:country":"ES",
    "sg:address":"Bjad Don Alonso, 5",
    "sg:city":"Avila",
    "sg:orig_category":"Venta, Instalaci\u00d3n De Calefacci\u00d3n",
    "sg:phone":"+34 920 22 22 20",
    "sg:postcode":"05003",
    "sg:province":"\u00c1vila",
    "wof:name":"Poveda Martin Juan",
    "wof:placetype":"venue"
},
  "geometry": {"coordinates":[-4.6898140907,40.6527786255],"type":"Point"}
}