{
  "type": "Feature",
  "properties": {
    "addr:full":"Estda. Freixo, 45 Vigo Pontevedra 36214",
    "addr:housenumber":"45",
    "addr:postcode":"36214",
    "addr:street":"Freixo",
    "iso:country":"ES",
    "sg:address":"Estda. Freixo, 45",
    "sg:city":"Vigo",
    "sg:orig_category":"Elementos Para Suelos Prefabricados",
    "sg:phone":"+34 986 46 97 36",
    "sg:postcode":"36214",
    "sg:province":"Pontevedra",
    "wof:name":"Tarimgal .s.l.",
    "wof:placetype":"venue"
},
  "geometry": {"coordinates":[-8.7059106827,42.2124443054],"type":"Point"}
}