{
  "type": "Feature",
  "properties": {
    "addr:full":"Carrer de Muntaner, 6 Can Cornet Barcelona 08397",
    "addr:housenumber":"6",
    "addr:postcode":"08397",
    "addr:street":"Carrer De Muntaner",
    "iso:country":"ES",
    "sg:address":"Carrer de Muntaner, 6",
    "sg:city":"Can Cornet",
    "sg:orig_category":"Iglesia Cat\u00d3lica",
    "sg:phone":"+34 937 62 37 90",
    "sg:postcode":"08397",
    "sg:province":"Barcelona",
    "wof:name":"Bisbat De Girona",
    "wof:placetype":"venue"
},
  "geometry": {"coordinates":[2.6893939972,41.6295928955],"type":"Point"}
}