{
  "type": "Feature",
  "properties": {
    "addr:full":"Calle de Carretera, 15 Pancrudo Teruel 44720",
    "addr:housenumber":"15",
    "addr:postcode":"44720",
    "addr:street":"Calle De Carretera",
    "iso:country":"ES",
    "sg:address":"Calle de Carretera, 15",
    "sg:city":"Pancrudo",
    "sg:orig_category":"Sanatorios M\u00c9dico",
    "sg:phone":"+34 978 77 53 06",
    "sg:postcode":"44720",
    "sg:province":"Teruel",
    "wof:name":"Ayuntamiento De Pancrudo",
    "wof:placetype":"venue"
},
  "geometry": {"coordinates":[-1.0284787416,40.7622566223],"type":"Point"}
}