{
  "type": "Feature",
  "properties": {
    "iso:country":"ES",
    "sg:address":"Avda Santa Clara, 15",
    "sg:city":"Santiago",
    "sg:orig_category":"Productos Qu\u00cdmicos (fabricaci\u00d3n, Al Por Mayor)",
    "sg:phone":"+34 968 44 19 29",
    "sg:postcode":"30800",
    "sg:province":"Murcia",
    "sg:website":"www.clariant.es",
    "wof:name":"Clariant Iberica Servicios S.l.",
    "wof:placetype":"venue"
},
  "geometry": {"coordinates":[-1.6905640364,37.680557251],"type":"Point"}
}