{
  "type": "Feature",
  "properties": {
    "iso:country":"ES",
    "sg:address":"Trva Carlos Mackintosh, 3",
    "sg:city":"Marbella",
    "sg:orig_category":"Arquitectos",
    "sg:phone":"+34 952 86 30 03",
    "sg:postcode":"29600",
    "sg:province":"M\u00e1laga",
    "wof:name":"Osborne Maestre Roberto",
    "wof:placetype":"venue"
},
  "geometry": {"coordinates":[-4.8855791092,36.5083618164],"type":"Point"}
}