{
  "type": "Feature",
  "properties": {
    "iso:country":"ES",
    "sg:address":"C/ Badalona, 2",
    "sg:city":"Banyoles",
    "sg:orig_category":"Mec\u00c1nico Del Autom\u00d3vil",
    "sg:phone":"+34 972 58 29 65",
    "sg:postcode":"17820",
    "sg:province":"Girona",
    "wof:name":"Autotaller Estandard S.l.",
    "wof:placetype":"venue"
},
  "geometry": {"coordinates":[2.7711799145,42.1152381897],"type":"Point"}
}