{
  "type": "Feature",
  "properties": {
    "addr:full":"Muelles De Portugal, 47 Ayamonte Huelva 21400",
    "addr:housenumber":"47",
    "addr:postcode":"21400",
    "iso:country":"ES",
    "sg:address":"Muelles De Portugal, 47",
    "sg:city":"Ayamonte",
    "sg:orig_category":"Inmobiliaria (agencias)",
    "sg:phone":"+34 959 32 24 74",
    "sg:postcode":"21400",
    "sg:province":"Huelva",
    "wof:name":"Peters  Karl",
    "wof:placetype":"venue"
},
  "geometry": {"coordinates":[-7.4089279175,37.2172279358],"type":"Point"}
}