{
  "type": "Feature",
  "properties": {
    "addr:full":"Av. Jerez, 8 Lebrija Sevilla 41740",
    "addr:housenumber":"8",
    "addr:postcode":"41740",
    "addr:street":"Av. Jerez",
    "iso:country":"ES",
    "sg:address":"Av. Jerez, 8",
    "sg:city":"Lebrija",
    "sg:orig_category":"Persianas Interiores, Exteriores",
    "sg:phone":"+34 955 97 42 50",
    "sg:postcode":"41740",
    "sg:province":"Sevilla",
    "wof:name":"Falcon Moreno Juan",
    "wof:placetype":"venue"
},
  "geometry": {"coordinates":[-6.0768499374,36.9164009094],"type":"Point"}
}