{
  "type": "Feature",
  "properties": {
    "iso:country":"ES",
    "sg:address":"Av Prat De La Riba, 34",
    "sg:city":"Tarragona",
    "sg:orig_category":"Ortopedia General",
    "sg:phone":"+34 977 23 11 06",
    "sg:postcode":"43001",
    "sg:province":"Tarragona",
    "wof:name":"Caravaca Ortopedics S.l.",
    "wof:placetype":"venue"
},
  "geometry": {"coordinates":[1.2456829548,41.1180343628],"type":"Point"}
}