{
  "type": "Feature",
  "properties": {
    "addr:full":"Calle de Generalisimo, S/n Socuellamos Ciudad Real 13630",
    "addr:housenumber":"s",
    "addr:postcode":"13630",
    "addr:street":"Calle De Generalisimo;/ N",
    "iso:country":"ES",
    "sg:address":"Calle de Generalisimo, S/n",
    "sg:city":"Socuellamos",
    "sg:orig_category":"Centros De Educaci\u00d3n Especial",
    "sg:phone":"+34 926 53 02 49",
    "sg:postcode":"13630",
    "sg:province":"Ciudad Real",
    "wof:name":"Ayuntamiento De Socuellamos",
    "wof:placetype":"venue"
},
  "geometry": {"coordinates":[-2.7933855057,39.2820281982],"type":"Point"}
}