{
  "type": "Feature",
  "properties": {
    "addr:full":"Calle de Alferez Provisional, 15 Talavera Reina Toledo 45600",
    "addr:housenumber":"15",
    "addr:postcode":"45600",
    "addr:street":"Calle De Alferez Provisional",
    "iso:country":"ES",
    "sg:address":"Calle de Alferez Provisional, 15",
    "sg:city":"Talavera Reina",
    "sg:orig_category":"Venta, Instalaci\u00d3n De Calefacci\u00d3n",
    "sg:phone":"+34 925 82 27 54",
    "sg:postcode":"45600",
    "sg:province":"Toledo",
    "wof:name":"Instalaciones Carrion S.l.",
    "wof:placetype":"venue"
},
  "geometry": {"coordinates":[-4.8296685219,39.9656524658],"type":"Point"}
}