{
  "type": "Feature",
  "properties": {
    "addr:full":"Edif Nevado, S/n Astun Huesca 22889",
    "addr:postcode":"22889",
    "addr:street":"S / N Astun",
    "iso:country":"ES",
    "sg:address":"Edif Nevado, S/n",
    "sg:city":"Astun",
    "sg:orig_category":"Deportes Diversos",
    "sg:phone":"+34 974 37 20 00",
    "sg:postcode":"22889",
    "sg:province":"Huesca",
    "sg:website":"www.astum.com",
    "wof:name":"Escuela De Esqui Y Snowboard De Astun S.l.",
    "wof:placetype":"venue"
},
  "geometry": {"coordinates":[-0.5231779814,42.7850799561],"type":"Point"}
}