{
  "type": "Feature",
  "properties": {
    "addr:full":"Rua Rio Mao, 23 Ourense Ourense 32001",
    "addr:housenumber":"23",
    "addr:postcode":"32001",
    "addr:street":"Rua;Mao",
    "iso:country":"ES",
    "sg:address":"Rua Rio Mao, 23",
    "sg:city":"Ourense",
    "sg:orig_category":"Peluquer\u00cdas, Peluquer\u00cda Mixta",
    "sg:phone":"+34 988 37 18 31",
    "sg:postcode":"32001",
    "sg:province":"Ourense",
    "wof:name":"Vazquez Bouza Rafael",
    "wof:placetype":"venue"
},
  "geometry": {"coordinates":[-7.8643898964,42.3525657654],"type":"Point"}
}