{
  "type": "Feature",
  "properties": {
    "addr:full":"Avda Zaragoza, 56 Utebo Zaragoza 50180",
    "addr:housenumber":"56",
    "addr:postcode":"50180",
    "addr:street":"Avda Zaragoza",
    "iso:country":"ES",
    "sg:address":"Avda Zaragoza, 56",
    "sg:city":"Utebo",
    "sg:orig_category":"Cervecer\u00cdas",
    "sg:phone":"+34 976 78 45 36",
    "sg:postcode":"50180",
    "sg:province":"Zaragoza",
    "wof:name":"Telefonia Aragonesa Escucha Rapida S.l.",
    "wof:placetype":"venue"
},
  "geometry": {"coordinates":[-0.9985030293,41.7069282532],"type":"Point"}
}