{
  "type": "Feature",
  "properties": {
    "addr:full":"Av Paisos Catalans, 43 Reus Tarragona 43202",
    "addr:housenumber":"43",
    "addr:postcode":"43202",
    "addr:street":"Av Paisos Catalans",
    "iso:country":"ES",
    "sg:address":"Av Paisos Catalans, 43",
    "sg:city":"Reus",
    "sg:orig_category":"Inmobiliaria (agencias)",
    "sg:phone":"+34 977 32 70 61",
    "sg:postcode":"43202",
    "sg:province":"Tarragona",
    "wof:name":"Comunidad De Propietarios Avinguda Paisos Catalans 43",
    "wof:placetype":"venue"
},
  "geometry": {"coordinates":[1.0972280502,41.1549758911],"type":"Point"}
}