{
  "type": "Feature",
  "properties": {
    "addr:full":"Calle de Ripoche, 1 Palmas De Gran Canaria Las Palmas 35007",
    "addr:housenumber":"1",
    "addr:postcode":"35007",
    "addr:street":"Calle De Ripoche",
    "iso:country":"ES",
    "sg:address":"Calle de Ripoche, 1",
    "sg:city":"Palmas De Gran Canaria",
    "sg:orig_category":"Estancos",
    "sg:phone":"+34 928 26 56 35",
    "sg:postcode":"35007",
    "sg:province":"Las Palmas",
    "wof:name":"Marquez Goncalvez Juan",
    "wof:placetype":"venue"
},
  "geometry": {"coordinates":[-15.4310655594,28.1403865814],"type":"Point"}
}