{
  "type": "Feature",
  "properties": {
    "addr:full":"Malaga, S/n Albox Almer\u00eda 04800",
    "addr:postcode":"04800",
    "addr:street":"Malaga S / N Albox Almeri\u0301A",
    "iso:country":"ES",
    "sg:address":"Malaga, S/n",
    "sg:city":"Albox",
    "sg:orig_category":"Artes Gr\u00c1ficas, Artes Pl\u00c1sticas (curso)",
    "sg:phone":"+34 950 12 05 70",
    "sg:postcode":"04800",
    "sg:province":"Almer\u00eda",
    "wof:name":"Saez Pareja Angel Roberto",
    "wof:placetype":"venue"
},
  "geometry": {"coordinates":[-2.1382288933,37.3827438354],"type":"Point"}
}