{
  "type": "Feature",
  "properties": {
    "addr:full":"Calle de Ramon Perez De Ayala, 96 Madrid Madrid 28038",
    "addr:housenumber":"96",
    "addr:postcode":"madrid;28038",
    "addr:street":"Calle De Ramon Perez De Ayala",
    "iso:country":"ES",
    "sg:address":"Calle de Ramon Perez De Ayala, 96",
    "sg:city":"Madrid",
    "sg:orig_category":"Droguer\u00cdas (al Por Menor)",
    "sg:phone":"+34 914 39 93 40",
    "sg:postcode":"28038",
    "sg:province":"Madrid",
    "wof:name":"Segovia Moreno Maria Jesus",
    "wof:placetype":"venue"
},
  "geometry": {"coordinates":[-3.6507389545,40.4002342224],"type":"Point"}
}