{
  "type": "Feature",
  "properties": {
    "iso:country":"ES",
    "sg:address":"Carr Corders, 20",
    "sg:city":"Badalona",
    "sg:orig_category":"Albergues",
    "sg:phone":"+34 934 64 17 41",
    "sg:postcode":"08911",
    "sg:province":"Barcelona",
    "wof:name":"Catalunya Lots S.l.",
    "wof:placetype":"venue"
},
  "geometry": {"coordinates":[2.2554209232,41.4583129883],"type":"Point"}
}