{
  "type": "Feature",
  "properties": {
    "addr:full":"Vilar De Donas, S/n Vilar Donas Lugo 27216",
    "addr:housenumber":"s",
    "addr:postcode":"27216",
    "addr:street":"/ N Vilar",
    "iso:country":"ES",
    "sg:address":"Vilar De Donas, S/n",
    "sg:city":"Vilar Donas",
    "sg:orig_category":"Cr\u00cda De Bovinos",
    "sg:phone":"+34 982 38 00 55",
    "sg:postcode":"27216",
    "sg:province":"Lugo",
    "wof:name":"S.a.t. San Antonio",
    "wof:placetype":"venue"
},
  "geometry": {"coordinates":[-7.8158640862,42.8485794067],"type":"Point"}
}