{
  "type": "Feature",
  "properties": {
    "iso:country":"ES",
    "sg:address":"Plaz Carril, 5",
    "sg:city":"Esquivias",
    "sg:orig_category":"Aceites Y Grasas Alimentarias (fabricaci\u00d3n, Al Por Mayor)",
    "sg:phone":"+34 925 52 00 32",
    "sg:postcode":"45221",
    "sg:province":"Toledo",
    "wof:name":"Aceites Hermida S.l.",
    "wof:placetype":"venue"
},
  "geometry": {"coordinates":[-3.7643930912,40.1024627686],"type":"Point"}
}