{
  "type": "Feature",
  "properties": {
    "addr:full":"Carr Raval, S/n Montclar Lleida 25317",
    "addr:housenumber":"s / n",
    "addr:postcode":"25317",
    "addr:street":"Carr Raval",
    "iso:country":"ES",
    "sg:address":"Carr Raval, S/n",
    "sg:city":"Montclar",
    "sg:orig_category":"Agricultores, Agricultores",
    "sg:phone":"+34 973 40 04 27",
    "sg:postcode":"25317",
    "sg:province":"Lleida",
    "wof:name":"Vall Majoral Juan",
    "wof:placetype":"venue"
},
  "geometry": {"coordinates":[1.0452649593,41.8479499817],"type":"Point"}
}