{
  "type": "Feature",
  "properties": {
    "addr:full":"Calle de Arizpetxu, 1 Mungia Vizcaya 48100",
    "addr:housenumber":"1",
    "addr:postcode":"48100",
    "addr:street":"Calle De Arizpetxu",
    "iso:country":"ES",
    "sg:address":"Calle de Arizpetxu, 1",
    "sg:city":"Mungia",
    "sg:orig_category":"Panader\u00cdas, Panader\u00cdas",
    "sg:phone":"+34 946 15 63 32",
    "sg:postcode":"48100",
    "sg:province":"Vizcaya",
    "wof:name":"Lekuonak S.l",
    "wof:placetype":"venue"
},
  "geometry": {"coordinates":[-2.8485524654,43.3556289673],"type":"Point"}
}