{
  "type": "Feature",
  "properties": {
    "addr:full":"Avda Coru\u00d1a (la), 8 Cangas Pontevedra 36940",
    "addr:housenumber":"8",
    "addr:postcode":"36940",
    "addr:street":"Avda Corun\u0303A La",
    "iso:country":"ES",
    "sg:address":"Avda Coru\u00d1a (la), 8",
    "sg:city":"Cangas",
    "sg:orig_category":"Caf\u00c9s, Bares, Cervecer\u00cdas",
    "sg:phone":"+34 986 30 32 71",
    "sg:postcode":"36940",
    "sg:province":"Pontevedra",
    "wof:name":"Galtelcom",
    "wof:placetype":"venue"
},
  "geometry": {"coordinates":[-8.7857990265,42.267414093],"type":"Point"}
}