{
  "type": "Feature",
  "properties": {
    "iso:country":"ES",
    "sg:address":"Avda Brillante (del), 179",
    "sg:city":"Cordoba",
    "sg:orig_category":"Asesor\u00cdas Y Estudios Financieros",
    "sg:phone":"+34 957 27 10 59",
    "sg:postcode":"14012",
    "sg:province":"C\u00f3rdoba",
    "wof:name":"Fernandez De Molina Latorre Ricardo",
    "wof:placetype":"venue"
},
  "geometry": {"coordinates":[-4.8016991615,37.9163818359],"type":"Point"}
}