{
  "type": "Feature",
  "properties": {
    "iso:country":"ES",
    "sg:address":"Calle de Prado Viejo, 29",
    "sg:city":"Logro\u00f1o",
    "sg:orig_category":"Tractores Agr\u00cdcolas Y Remolques",
    "sg:phone":"+34 941 20 66 24",
    "sg:postcode":"26007",
    "sg:province":"La Rioja",
    "wof:name":"Tracto-rioja S.a.",
    "wof:placetype":"venue"
},
  "geometry": {"coordinates":[-2.4729280472,42.4579772949],"type":"Point"}
}