{
  "type": "Feature",
  "properties": {
    "addr:full":"Calle de Carmen (del), 28 Cartagena Murcia 30201",
    "addr:postcode":"30201",
    "addr:street":"Calle De Carmen Del",
    "iso:country":"ES",
    "sg:address":"Calle de Carmen (del), 28",
    "sg:city":"Cartagena",
    "sg:orig_category":"Deportes Y Programas De Aventura",
    "sg:phone":"+34 968 12 14 54",
    "sg:postcode":"30201",
    "sg:province":"Murcia",
    "wof:name":"Pa\u00d1os Intersport S.l.",
    "wof:placetype":"venue"
},
  "geometry": {"coordinates":[-0.9881818295,37.6030502319],"type":"Point"}
}