{
  "type": "Feature",
  "properties": {
    "addr:full":"C/ Mallorca, 19 Elche Alicante 03203",
    "addr:housenumber":"19",
    "addr:postcode":"03203",
    "addr:street":"C / Mallorca",
    "iso:country":"ES",
    "sg:address":"C/ Mallorca, 19",
    "sg:city":"Elche",
    "sg:orig_category":"Agencias Y Asesores De Publicidad",
    "sg:phone":"+34 965 45 93 48",
    "sg:postcode":"03203",
    "sg:province":"Alicante",
    "wof:name":"Publicidad Anton S.l.",
    "wof:placetype":"venue"
},
  "geometry": {"coordinates":[-0.6733670235,38.2697906494],"type":"Point"}
}