{
  "type": "Feature",
  "properties": {
    "iso:country":"ES",
    "sg:address":"Calle de Losada Pintor, 31",
    "sg:city":"Bilbao",
    "sg:orig_category":"Farmacias",
    "sg:phone":"+34 944 11 10 30",
    "sg:postcode":"48004",
    "sg:province":"Vizcaya",
    "wof:name":"Francisco Javier Ojanguren, (farmacia Ojanguren)",
    "wof:placetype":"venue"
},
  "geometry": {"coordinates":[-2.9118471146,43.2504997253],"type":"Point"}
}