{
  "type": "Feature",
  "properties": {
    "iso:country":"ES",
    "sg:address":"Calle de Mar, 3",
    "sg:city":"Valencia",
    "sg:orig_category":"Promotores Constructores",
    "sg:phone":"+34 963 91 73 46",
    "sg:postcode":"46003",
    "sg:province":"Valencia",
    "wof:name":"Bm3 Obras Y Servicios S.a.",
    "wof:placetype":"venue"
},
  "geometry": {"coordinates":[-0.3749220073,39.4741096497],"type":"Point"}
}