{
  "type": "Feature",
  "properties": {
    "addr:full":"Calle de Eufemiano Fuentes Cabrera, 22 Palmas De Gran Canaria Las Palmas 35014",
    "addr:postcode":"35014",
    "addr:street":"Calle De Eufemiano Fuentes Cabrera 22",
    "iso:country":"ES",
    "sg:address":"Calle de Eufemiano Fuentes Cabrera, 22",
    "sg:city":"Palmas De Gran Canaria",
    "sg:orig_category":"Comercio De Piezas De Recambio Y De Accesorios De Veh\u00cdculos, Veh\u00cdculos Industriales",
    "sg:phone":"+34 928 42 01 79",
    "sg:postcode":"35014",
    "sg:province":"Las Palmas",
    "wof:name":"Santiago Castellano Juan",
    "wof:placetype":"venue"
},
  "geometry": {"coordinates":[-15.4374980927,28.0994148254],"type":"Point"}
}