{
  "type": "Feature",
  "properties": {
    "addr:full":"Bloc Tarragones, S/n Sant Pere I Sant Pau Tarragona 43007",
    "addr:housenumber":"s",
    "addr:postcode":"43007",
    "addr:street":"/ N",
    "iso:country":"ES",
    "sg:address":"Bloc Tarragones, S/n",
    "sg:city":"Sant Pere I Sant Pau",
    "sg:orig_category":"Zapatos (al Por Menor)",
    "sg:phone":"+34 977 21 65 50",
    "sg:postcode":"43007",
    "sg:province":"Tarragona",
    "wof:name":"Luce\u00f1o Clavijo Cristobal",
    "wof:placetype":"venue"
},
  "geometry": {"coordinates":[1.2959779501,41.1377334595],"type":"Point"}
}