{
  "type": "Feature",
  "properties": {
    "addr:full":"Calle de Luis De Uranzu, 11 Irun Guip\u00f9zcoa 20301",
    "addr:housenumber":"11",
    "addr:postcode":"20301",
    "addr:street":"Calle De Luis De Uranzu;Guipu\u0300Zcoa",
    "iso:country":"ES",
    "sg:address":"Calle de Luis De Uranzu, 11",
    "sg:city":"Irun",
    "sg:orig_category":"Papeler\u00cdas, Librer\u00cdas",
    "sg:phone":"+34 943 61 50 40",
    "sg:postcode":"20301",
    "sg:province":"Guip\u00f9zcoa",
    "wof:name":"Nieto Curto Maria De La Encarnacion",
    "wof:placetype":"venue"
},
  "geometry": {"coordinates":[-1.8010189533,43.3418540955],"type":"Point"}
}