{
  "type": "Feature",
  "properties": {
    "iso:country":"ES",
    "sg:address":"Calle de Serna (la), S/n",
    "sg:city":"Fresno Vega",
    "sg:orig_category":"Conservas De Legumbres (fabricaci\u00d3n, Al Por Mayor)",
    "sg:phone":"+34 987 77 02 55",
    "sg:postcode":"24223",
    "sg:province":"Le\u00f3n",
    "sg:website":"www.vegaesla.com",
    "wof:name":"Hortoesla C.b.",
    "wof:placetype":"venue"
},
  "geometry": {"coordinates":[-5.5342860222,42.3461227417],"type":"Point"}
}