{
  "type": "Feature",
  "properties": {
    "iso:country":"ES",
    "sg:address":"Avda Paz (de La), 2",
    "sg:city":"Burgos",
    "sg:orig_category":"Farmacias",
    "sg:phone":"+34 947 27 01 55",
    "sg:postcode":"09004",
    "sg:province":"Burgos",
    "wof:name":"Medrano Ruiz Margarita Maria",
    "wof:placetype":"venue"
},
  "geometry": {"coordinates":[-3.6955590248,42.3437423706],"type":"Point"}
}