{
  "type": "Feature",
  "properties": {
    "addr:full":"Carrer de Cap Norfeu, S/n Roses Girona 17480",
    "addr:housenumber":"s",
    "addr:postcode":"17480",
    "addr:street":"Carrer De Cap Norfeu;/ N Roses",
    "iso:country":"ES",
    "sg:address":"Carrer de Cap Norfeu, S/n",
    "sg:city":"Roses",
    "sg:orig_category":"Transporte En General",
    "sg:phone":"+34 972 15 04 78",
    "sg:postcode":"17480",
    "sg:province":"Girona",
    "wof:name":"Bon-preu S.a.",
    "wof:placetype":"venue"
},
  "geometry": {"coordinates":[3.1805500984,42.2604255676],"type":"Point"}
}