{
  "type": "Feature",
  "properties": {
    "addr:full":"Calle de Severo Ochoa, 22 Sese\u00e7a Nuevo Toledo 45224",
    "addr:housenumber":"22",
    "addr:postcode":"45224",
    "addr:street":"Calle De Severo Ochoa",
    "iso:country":"ES",
    "sg:address":"Calle de Severo Ochoa, 22",
    "sg:city":"Sese\u00e7a Nuevo",
    "sg:orig_category":"Transporte En General",
    "sg:phone":"+34 918 93 64 32",
    "sg:postcode":"45224",
    "sg:province":"Toledo",
    "sg:website":"www.sumapel.net",
    "wof:name":"Suministros Y Manipulados De Papel S.l.",
    "wof:placetype":"venue"
},
  "geometry": {"coordinates":[-3.6612639427,40.1067314148],"type":"Point"}
}