{
  "type": "Feature",
  "properties": {
    "addr:full":"Calle de Sombrereria, 27 Burgos Burgos 09003",
    "addr:housenumber":"27",
    "addr:postcode":"09003",
    "addr:street":"Calle De Sombrereria",
    "iso:country":"ES",
    "sg:address":"Calle de Sombrereria, 27",
    "sg:city":"Burgos",
    "sg:orig_category":"Lencer\u00cda Femenina, Corseter\u00cda, Trajes De Ba\u00d1o (al Por Menor)",
    "sg:phone":"+34 947 25 05 98",
    "sg:postcode":"09003",
    "sg:province":"Burgos",
    "wof:name":"Cartajena Paris Yotra S.c.",
    "wof:placetype":"venue"
},
  "geometry": {"coordinates":[-3.7029120922,42.3406295776],"type":"Point"}
}