{
  "type": "Feature",
  "properties": {
    "addr:full":"Carrer de Travau, 44 Barcelona Barcelona 08031",
    "addr:housenumber":"44",
    "addr:postcode":"08031",
    "addr:street":"Carrer De Travau",
    "iso:country":"ES",
    "sg:address":"Carrer de Travau, 44",
    "sg:city":"Barcelona",
    "sg:orig_category":"Lecher\u00cdas",
    "sg:phone":"+34 934 29 64 40",
    "sg:postcode":"08031",
    "sg:province":"Barcelona",
    "wof:name":"Ous I Llet Junoy S.l.",
    "wof:placetype":"venue"
},
  "geometry": {"coordinates":[2.1683449745,41.4321365356],"type":"Point"}
}