{
  "type": "Feature",
  "properties": {
    "iso:country":"ES",
    "sg:address":"Carr Santa Ana, 8",
    "sg:city":"Xativa",
    "sg:orig_category":"Asociaciones, Instituciones De Consumidores Y Usuarios",
    "sg:phone":"+34 962 27 69 93",
    "sg:postcode":"46800",
    "sg:province":"Valencia",
    "wof:name":"Asociacion Provincial De Amas De Casa Y Consumidores Tiryus",
    "wof:placetype":"venue"
},
  "geometry": {"coordinates":[-0.517629087,38.9896736145],"type":"Point"}
}