{
  "type": "Feature",
  "properties": {
    "addr:full":"Avda Portugal De, 18 Aviles Asturias 33402",
    "addr:housenumber":"18",
    "addr:postcode":"33402",
    "addr:street":"Avda Portugal De",
    "iso:country":"ES",
    "sg:address":"Avda Portugal De, 18",
    "sg:city":"Aviles",
    "sg:orig_category":"Farmacias",
    "sg:phone":"+34 985 51 15 70",
    "sg:postcode":"33402",
    "sg:province":"Asturias",
    "wof:name":"Ramos Vallina Silvia Josefa",
    "wof:placetype":"venue"
},
  "geometry": {"coordinates":[-5.9279527664,43.5518760681],"type":"Point"}
}