{
  "type": "Feature",
  "properties": {
    "iso:country":"ES",
    "sg:address":"Cmno Pe\u00d1ascal, 142",
    "sg:city":"Bilbao",
    "sg:orig_category":"Empresarios",
    "sg:phone":"+34 944 21 78 73",
    "sg:postcode":"48002",
    "sg:province":"Vizcaya",
    "wof:name":"Fundacion Pe\u00f1ascal",
    "wof:placetype":"venue"
},
  "geometry": {"coordinates":[-2.9434030056,43.2355995178],"type":"Point"}
}