{
  "type": "Feature",
  "properties": {
    "addr:full":"Calle de Muleros, 4 Lucena C\u00f3rdoba 14900",
    "addr:housenumber":"4",
    "addr:postcode":"14900",
    "addr:street":"Calle De Muleros",
    "iso:country":"ES",
    "sg:address":"Calle de Muleros, 4",
    "sg:city":"Lucena",
    "sg:orig_category":"Calderer\u00cda",
    "sg:phone":"+34 957 50 13 25",
    "sg:postcode":"14900",
    "sg:province":"C\u00f3rdoba",
    "wof:name":"Mu\u00f1oz Cardenas Pedro",
    "wof:placetype":"venue"
},
  "geometry": {"coordinates":[-4.4874658585,37.4096488953],"type":"Point"}
}