{
  "type": "Feature",
  "properties": {
    "iso:country":"ES",
    "sg:address":"Biduido De Abaixo, S/n",
    "sg:city":"Biduido De Abaixo",
    "sg:orig_category":"Aparatos, Material Y Suministros Para Laboratorios",
    "sg:phone":"+34 981 53 07 69",
    "sg:postcode":"15895",
    "sg:province":"A Coru\u00f1a",
    "wof:name":"Tecnociencia S.l.",
    "wof:placetype":"venue"
},
  "geometry": {"coordinates":[-8.5794343948,42.8416137695],"type":"Point"}
}