{
  "type": "Feature",
  "properties": {
    "iso:country":"ES",
    "sg:address":"Calle de Rondilla Cruz Verde, 86",
    "sg:city":"Alcazar S. Juan",
    "sg:orig_category":"Armas Y Municiones (fabricaci\u00d3n, Al Por Mayor)",
    "sg:phone":"+34 926 54 11 67",
    "sg:postcode":"13600",
    "sg:province":"Ciudad Real",
    "wof:name":"Cruz Bueno Marcelino",
    "wof:placetype":"venue"
},
  "geometry": {"coordinates":[-3.210203886,39.3900718689],"type":"Point"}
}