{
  "type": "Feature",
  "properties": {
    "addr:full":"Calle de Plaza De Toros Vieja, 7 Malaga M\u00e1laga 29002",
    "addr:housenumber":"7",
    "addr:postcode":"29002",
    "addr:street":"Calle De;Vieja;Ma\u0301Laga",
    "iso:country":"ES",
    "sg:address":"Calle de Plaza De Toros Vieja, 7",
    "sg:city":"Malaga",
    "sg:orig_category":"Abogados",
    "sg:phone":"+34 952 33 01 78",
    "sg:postcode":"29002",
    "sg:province":"M\u00e1laga",
    "wof:name":"Rodriguez Candela Jose Luis",
    "wof:placetype":"venue"
},
  "geometry": {"coordinates":[-4.4273262024,36.7121887207],"type":"Point"}
}