{
  "type": "Feature",
  "properties": {
    "addr:full":"Plaz Landabaso, 10 Bilbao Vizcaya 48015",
    "addr:housenumber":"10",
    "addr:postcode":"48015",
    "addr:street":"Plaz Landabaso",
    "iso:country":"ES",
    "sg:address":"Plaz Landabaso, 10",
    "sg:city":"Bilbao",
    "sg:orig_category":"Art\u00cdculos De Decoraci\u00d3n (fabricaci\u00d3n Y Al Por Mayor)",
    "sg:phone":"+34 944 47 39 60",
    "sg:postcode":"48015",
    "sg:province":"Vizcaya",
    "wof:name":"Zabala Aznar Carmen",
    "wof:placetype":"venue"
},
  "geometry": {"coordinates":[-2.9600863457,43.274230957],"type":"Point"}
}