{
  "type": "Feature",
  "properties": {
    "addr:full":"Ptge Marques De Santa Isabe, 40 Barcelona Barcelona 08018",
    "addr:housenumber":"40",
    "addr:postcode":"08018",
    "addr:street":"Ptge Marques De Santa Isabe",
    "iso:country":"ES",
    "sg:address":"Ptge Marques De Santa Isabe, 40",
    "sg:city":"Barcelona",
    "sg:orig_category":"Pintores",
    "sg:phone":"+34 933 08 40 41",
    "sg:postcode":"08018",
    "sg:province":"Barcelona",
    "sg:website":"www.hangar.org",
    "wof:name":"Fundacio Privada Aavc",
    "wof:placetype":"venue"
},
  "geometry": {"coordinates":[2.1687450409,41.3855895996],"type":"Point"}
}