{
  "type": "Feature",
  "properties": {
    "addr:full":"Carr Puig Campana (el), 11 Almafra Alicante 03610",
    "addr:housenumber":"11",
    "addr:postcode":"03610",
    "addr:street":"Carr Puig Campana El;Alicante",
    "iso:country":"ES",
    "sg:address":"Carr Puig Campana (el), 11",
    "sg:city":"Almafra",
    "sg:orig_category":"Grafistas",
    "sg:phone":"+34 965 37 75 73",
    "sg:postcode":"03610",
    "sg:province":"Alicante",
    "wof:name":"Barrera Manzano Antonio Juan De La",
    "wof:placetype":"venue"
},
  "geometry": {"coordinates":[-0.7731289864,38.4793281555],"type":"Point"}
}