{
  "type": "Feature",
  "properties": {
    "iso:country":"ES",
    "sg:address":"Calle de Agricultura (de La), S/n",
    "sg:city":"Huesca",
    "sg:orig_category":"Contenedores (mercanc\u00cdas)",
    "sg:phone":"+34 974 24 64 74",
    "sg:postcode":"22006",
    "sg:province":"Huesca",
    "sg:website":"www.oscaw.com",
    "wof:name":"Oscaweb S.l.",
    "wof:placetype":"venue"
},
  "geometry": {"coordinates":[-0.4081014097,42.145942688],"type":"Point"}
}