{
  "type": "Feature",
  "properties": {
    "iso:country":"ES",
    "sg:address":"Ctra San Julian, 55",
    "sg:city":"Teruel",
    "sg:orig_category":"Electricidad: Instalaciones Industriales",
    "sg:phone":"+34 978 60 60 14",
    "sg:postcode":"44003",
    "sg:province":"Teruel",
    "wof:name":"Martinez Mansilla Antonio",
    "wof:placetype":"venue"
},
  "geometry": {"coordinates":[-1.1036369801,40.3391151428],"type":"Point"}
}