{
  "type": "Feature",
  "properties": {
    "iso:country":"ES",
    "sg:address":"Calle de Amberes, 6",
    "sg:city":"Caceres",
    "sg:orig_category":"Farmacias",
    "sg:phone":"+34 927 23 62 79",
    "sg:postcode":"10005",
    "sg:province":"C\u00e1ceres",
    "wof:name":"Becerra Mu\u00f1oz Maria Josefa",
    "wof:placetype":"venue"
},
  "geometry": {"coordinates":[-6.3886590004,39.4698791504],"type":"Point"}
}