{
  "type": "Feature",
  "properties": {
    "iso:country":"ES",
    "sg:address":"Anton Miro, S/n",
    "sg:city":"Pla Santa Maria",
    "sg:classifiers":[
        {
            "category":"Taxi",
            "type":"Transportation"
        }
    ],
    "sg:phone":"+34 977 63 05 18",
    "sg:postcode":"43810",
    "sg:province":"Tarragona",
    "wof:name":"Valls Roig Joan",
    "wof:placetype":"venue"
},
  "geometry": {"coordinates":[1.2865149975,41.366645813],"type":"Point"}
}