{
  "type": "Feature",
  "properties": {
    "iso:country":"ES",
    "sg:address":"Calle de Rosal, S/n",
    "sg:city":"Aracena",
    "sg:orig_category":"Centros Empresariales",
    "sg:phone":"+34 959 12 86 55",
    "sg:postcode":"21200",
    "sg:province":"Huelva",
    "wof:name":"Arunda S.l",
    "wof:placetype":"venue"
},
  "geometry": {"coordinates":[-6.5628623962,37.89320755],"type":"Point"}
}