{
  "type": "Feature",
  "properties": {
    "addr:full":"Calle de Madrid, S/n Marina-oasis Alicante 03177",
    "addr:housenumber":"s",
    "addr:postcode":"03177",
    "addr:street":"Calle De Madrid;/ N Marina-Oasis",
    "iso:country":"ES",
    "sg:address":"Calle de Madrid, S/n",
    "sg:city":"Marina-oasis",
    "sg:orig_category":"Carnicer\u00cdas, Carnicer\u00cdas",
    "sg:phone":"+34 966 79 71 24",
    "sg:postcode":"03177",
    "sg:province":"Alicante",
    "wof:name":"Red De Carnicerias S.l.",
    "wof:placetype":"venue"
},
  "geometry": {"coordinates":[-0.4810059965,38.3452033997],"type":"Point"}
}