{
  "type": "Feature",
  "properties": {
    "iso:country":"ES",
    "sg:address":"Av Generalitat, 24",
    "sg:city":"Deltebre",
    "sg:orig_category":"Electromec\u00c1nica",
    "sg:phone":"+34 977 48 92 65",
    "sg:postcode":"43580",
    "sg:province":"Tarragona",
    "wof:name":"Auto Electric Almar Cdad.",
    "wof:placetype":"venue"
},
  "geometry": {"coordinates":[0.7253460288,40.7199745178],"type":"Point"}
}