{
  "type": "Feature",
  "properties": {
    "iso:country":"ES",
    "sg:address":"Pase Colon, 56",
    "sg:city":"Irun",
    "sg:orig_category":"Perfumer\u00cda Y Cosm\u00c9tica (fabricaci\u00d3n, Al Por Mayor)",
    "sg:phone":"+34 943 61 91 37",
    "sg:postcode":"20301",
    "sg:province":"Guip\u00f9zcoa",
    "wof:name":"Exclusivas Negredo S.l.",
    "wof:placetype":"venue"
},
  "geometry": {"coordinates":[-1.7971489429,43.3411064148],"type":"Point"}
}