{
  "type": "Feature",
  "properties": {
    "iso:country":"ES",
    "sg:address":"Avda Aragon, 18",
    "sg:city":"Valencia",
    "sg:orig_category":"Psic\u00d3logos",
    "sg:phone":"+34 963 69 61 98",
    "sg:postcode":"46021",
    "sg:province":"Valencia",
    "wof:name":"Penades Chust Alicia",
    "wof:placetype":"venue"
},
  "geometry": {"coordinates":[-0.3584629893,39.4697990417],"type":"Point"}
}