{
  "type": "Feature",
  "properties": {
    "addr:full":"Calle de Severo Ochoa, 12 Parla Madrid 28980",
    "addr:housenumber":"12",
    "addr:postcode":"28980",
    "addr:street":"Calle De Severo Ochoa",
    "iso:country":"ES",
    "sg:address":"Calle de Severo Ochoa, 12",
    "sg:city":"Parla",
    "sg:orig_category":"Agencias De Viajes",
    "sg:phone":"+34 916 05 63 91",
    "sg:postcode":"28980",
    "sg:province":"Madrid",
    "sg:website":"www.marsans.es",
    "wof:name":"Viajes Marsans S.a.",
    "wof:placetype":"venue"
},
  "geometry": {"coordinates":[-3.772124052,40.235824585],"type":"Point"}
}