{
  "type": "Feature",
  "properties": {
    "addr:full":"Calle de Lavapies, 16 Madrid Madrid 28012",
    "addr:housenumber":"16",
    "addr:postcode":"madrid;28012",
    "addr:street":"Calle De Lavapies",
    "iso:country":"ES",
    "sg:address":"Calle de Lavapies, 16",
    "sg:city":"Madrid",
    "sg:orig_category":"Venta, Instalaci\u00d3n De Cocinas",
    "sg:phone":"+34 914 68 70 42",
    "sg:postcode":"28012",
    "sg:province":"Madrid",
    "wof:name":"Petiscos S.l.l.",
    "wof:placetype":"venue"
},
  "geometry": {"coordinates":[-3.7030279636,40.4111633301],"type":"Point"}
}