{
  "type": "Feature",
  "properties": {
    "iso:country":"ES",
    "sg:address":"Calle de Jose Del Hierro, 67",
    "sg:city":"Madrid",
    "sg:orig_category":"Comercio De Mobiliario De Oficina",
    "sg:phone":"+34 914 07 31 27",
    "sg:postcode":"28027",
    "sg:province":"Madrid",
    "sg:website":"www.interstuhl.es",
    "wof:name":"Interstuhl S.l.",
    "wof:placetype":"venue"
},
  "geometry": {"coordinates":[-3.641561985,40.4413871765],"type":"Point"}
}