{
  "type": "Feature",
  "properties": {
    "addr:full":"Calle de Mayor, 52 Palmar  O Lugar De Don Juan Murcia 30120",
    "addr:housenumber":"52",
    "addr:postcode":"30120",
    "addr:street":"Calle De Mayor;Lugar",
    "iso:country":"ES",
    "sg:address":"Calle de Mayor, 52",
    "sg:city":"Palmar  O Lugar De Don Juan",
    "sg:orig_category":"Confecci\u00d3n (fabricaci\u00d3n, Al Por Mayor)",
    "sg:phone":"+34 968 88 51 73",
    "sg:postcode":"30120",
    "sg:province":"Murcia",
    "wof:name":"Aleman Meseguer Angel",
    "wof:placetype":"venue"
},
  "geometry": {"coordinates":[-1.1298867464,37.9834747314],"type":"Point"}
}