{
  "type": "Feature",
  "properties": {
    "addr:full":"Calle de Gigantes, 1 Malaga M\u00e1laga 29008",
    "addr:housenumber":"1",
    "addr:postcode":"29008",
    "addr:street":"Calle De Gigantes;Ma\u0301Laga",
    "iso:country":"ES",
    "sg:address":"Calle de Gigantes, 1",
    "sg:city":"Malaga",
    "sg:orig_category":"M\u00c9dicos: Oftalmolog\u00cda",
    "sg:phone":"+34 952 21 11 38",
    "sg:postcode":"29008",
    "sg:province":"M\u00e1laga",
    "wof:name":"Gomez Martinez Juan Luis",
    "wof:placetype":"venue"
},
  "geometry": {"coordinates":[-4.4235930443,36.7234077454],"type":"Point"}
}