{
  "type": "Feature",
  "properties": {
    "addr:full":"Avda Estacion (de La), 7 Almeria Almer\u00eda 04005",
    "addr:housenumber":"7",
    "addr:postcode":"04005",
    "addr:street":"Avda Estacion De La",
    "iso:country":"ES",
    "sg:address":"Avda Estacion (de La), 7",
    "sg:city":"Almeria",
    "sg:orig_category":"Ropa Para Se\u00d1oras (al Por Menor)",
    "sg:phone":"+34 950 27 15 45",
    "sg:postcode":"04005",
    "sg:province":"Almer\u00eda",
    "wof:name":"Diaz Molina Sonia",
    "wof:placetype":"venue"
},
  "geometry": {"coordinates":[-2.4596810341,36.8380889893],"type":"Point"}
}