{
  "type": "Feature",
  "properties": {
    "addr:full":"Ctra Pont De Vilomara, 103 Manresa Barcelona 08241",
    "addr:housenumber":"103",
    "addr:postcode":"08241",
    "addr:street":"Ctra Pont De Vilomara",
    "iso:country":"ES",
    "sg:address":"Ctra Pont De Vilomara, 103",
    "sg:city":"Manresa",
    "sg:orig_category":"Pescader\u00cdas (al Por Menor)",
    "sg:phone":"+34 938 73 01 84",
    "sg:postcode":"08241",
    "sg:province":"Barcelona",
    "wof:name":"Serra Prat Salvador",
    "wof:placetype":"venue"
},
  "geometry": {"coordinates":[1.837223053,41.7261238098],"type":"Point"}
}