{
  "type": "Feature",
  "properties": {
    "iso:country":"ES",
    "sg:address":"Paziano Arosa Kalea, 1",
    "sg:city":"Eibar",
    "sg:orig_category":"Arquitectos",
    "sg:phone":"+34 943 20 62 56",
    "sg:postcode":"20600",
    "sg:province":"Guip\u00f9zcoa",
    "wof:name":"Gil Eguren Jorge",
    "wof:placetype":"venue"
},
  "geometry": {"coordinates":[-2.4733040333,43.1821746826],"type":"Point"}
}