{
  "type": "Feature",
  "properties": {
    "iso:country":"ES",
    "sg:address":"Carrer de Portal Dels Romeus (del), 7",
    "sg:city":"Tortosa",
    "sg:orig_category":"Molduras, Junquillos, Listones Y Molduras Perforadas",
    "sg:phone":"+34 977 44 20 12",
    "sg:postcode":"43500",
    "sg:province":"Tarragona",
    "wof:name":"Simo Borrull Antonio",
    "wof:placetype":"venue"
},
  "geometry": {"coordinates":[0.5226510167,40.8136711121],"type":"Point"}
}