{
  "type": "Feature",
  "properties": {
    "addr:full":"Ctra Benasque, Km. 0063,0 Campo Huesca 22450",
    "addr:postcode":"22450",
    "addr:street":"Ctra Benasque Km. 0063,0",
    "iso:country":"ES",
    "sg:address":"Ctra Benasque, Km. 0063,0",
    "sg:city":"Campo",
    "sg:orig_category":"Cooperativas Agr\u00cdcolas",
    "sg:phone":"+34 974 55 01 40",
    "sg:postcode":"22450",
    "sg:province":"Huesca",
    "wof:name":"Cooperativa Agropecuaria Del Esera",
    "wof:placetype":"venue"
},
  "geometry": {"coordinates":[0.3431740105,42.4554100037],"type":"Point"}
}