{
  "type": "Feature",
  "properties": {
    "addr:full":"Avda Ingeniero Jose Alegria, 56 Zarandona Murcia 30007",
    "addr:housenumber":"56",
    "addr:postcode":"30007",
    "addr:street":"Avda Ingeniero Jose Alegria",
    "iso:country":"ES",
    "sg:address":"Avda Ingeniero Jose Alegria, 56",
    "sg:city":"Zarandona",
    "sg:orig_category":"Torrefactado De Caf\u00c9",
    "sg:phone":"+34 968 24 64 58",
    "sg:postcode":"30007",
    "sg:province":"Murcia",
    "wof:name":"La Industrial Levantina De Cafes Durban S. L.",
    "wof:placetype":"venue"
},
  "geometry": {"coordinates":[-1.1142389774,37.9970092773],"type":"Point"}
}