{
  "type": "Feature",
  "properties": {
    "addr:full":"Rua Gil Portela, S/n Fonsagrada Lugo 27100",
    "addr:housenumber":"s / n",
    "addr:postcode":"27100",
    "addr:street":"Rua Gil Portela",
    "iso:country":"ES",
    "sg:address":"Rua Gil Portela, S/n",
    "sg:city":"Fonsagrada",
    "sg:orig_category":"Centros De Educaci\u00d3n Especial",
    "sg:phone":"+34 982 34 01 84",
    "sg:postcode":"27100",
    "sg:province":"Lugo",
    "wof:name":"Colexio Publico De Educacion Xeral Basica",
    "wof:placetype":"venue"
},
  "geometry": {"coordinates":[-7.0673189163,43.125995636],"type":"Point"}
}