{
  "type": "Feature",
  "properties": {
    "addr:full":"Pl Carme, 18 Tarrega Lleida 25300",
    "addr:housenumber":"18",
    "addr:postcode":"25300",
    "addr:street":"Pl Carme",
    "iso:country":"ES",
    "sg:address":"Pl Carme, 18",
    "sg:city":"Tarrega",
    "sg:orig_category":"Ropa Para Se\u00d1oras (al Por Menor)",
    "sg:phone":"+34 973 31 39 68",
    "sg:postcode":"25300",
    "sg:province":"Lleida",
    "wof:name":"Ceerre Moda Sl",
    "wof:placetype":"venue"
},
  "geometry": {"coordinates":[1.1398570538,41.6471862793],"type":"Point"}
}