{
  "type": "Feature",
  "properties": {
    "addr:full":"Pase Altza De, 8 Donostia-san Sebastian Guip\u00f9zcoa 20017",
    "addr:postcode":"20017",
    "iso:country":"ES",
    "sg:address":"Pase Altza De, 8",
    "sg:city":"Donostia-san Sebastian",
    "sg:orig_category":"Cajas De Ahorro",
    "sg:phone":"+34 943 35 17 42",
    "sg:postcode":"20017",
    "sg:province":"Guip\u00f9zcoa",
    "sg:website":"www.cajalaboral.es",
    "wof:name":"Caja Laboral Popular",
    "wof:placetype":"venue"
},
  "geometry": {"coordinates":[-1.9794000387,43.3173789978],"type":"Point"}
}