{
  "type": "Feature",
  "properties": {
    "iso:country":"ES",
    "sg:address":"Avda Via Calatrave\u00d1o, 32",
    "sg:city":"Viso",
    "sg:orig_category":"Cl\u00cdnicas Dentales",
    "sg:phone":"+34 957 12 74 68",
    "sg:postcode":"14470",
    "sg:province":"C\u00f3rdoba",
    "wof:name":"Visodent S.l.",
    "wof:placetype":"venue"
},
  "geometry": {"coordinates":[-4.9525284767,38.4832992554],"type":"Point"}
}