{
  "type": "Feature",
  "properties": {
    "addr:full":"Calle de Quintana, 4 Aguilas Murcia 30880",
    "addr:housenumber":"4",
    "addr:postcode":"30880",
    "addr:street":"Calle De Quintana",
    "iso:country":"ES",
    "sg:address":"Calle de Quintana, 4",
    "sg:city":"Aguilas",
    "sg:orig_category":"Abogados",
    "sg:phone":"+34 968 44 83 88",
    "sg:postcode":"30880",
    "sg:province":"Murcia",
    "wof:name":"Cano Marin Ana Maria",
    "wof:placetype":"venue"
},
  "geometry": {"coordinates":[-1.5832749605,37.4029960632],"type":"Point"}
}