{
  "type": "Feature",
  "properties": {
    "iso:country":"ES",
    "sg:address":"Carrer de Canvis Vells, 2",
    "sg:city":"Barcelona",
    "sg:orig_category":"Artesan\u00cda",
    "sg:phone":"+34 932 68 42 20",
    "sg:postcode":"08003",
    "sg:province":"Barcelona",
    "wof:name":"Al Baraka S.c.p.",
    "wof:placetype":"venue"
},
  "geometry": {"coordinates":[2.1819992065,41.3830604553],"type":"Point"}
}