{
  "type": "Feature",
  "properties": {
    "iso:country":"ES",
    "sg:address":"Calle de Real, 18",
    "sg:city":"S. Juan Puerto",
    "sg:orig_category":"Supermercados Y Hipermercados",
    "sg:phone":"+34 959 35 63 07",
    "sg:postcode":"21610",
    "sg:province":"Huelva",
    "wof:name":"Alimentacion Rodriguez Franco S.l.l.",
    "wof:placetype":"venue"
},
  "geometry": {"coordinates":[-6.839993,37.3150634766],"type":"Point"}
}