{
  "type": "Feature",
  "properties": {
    "addr:full":"Av Europa, 105 Hospitalet Llobregat Barcelona 08907",
    "addr:housenumber":"105",
    "addr:postcode":"08907",
    "addr:street":"Av Europa",
    "iso:country":"ES",
    "sg:address":"Av Europa, 105",
    "sg:city":"Hospitalet Llobregat",
    "sg:orig_category":"Electricidad: Instaladores",
    "sg:phone":"+34 933 35 21 22",
    "sg:postcode":"08907",
    "sg:province":"Barcelona",
    "wof:name":"Imega 97 S. L.",
    "wof:placetype":"venue"
},
  "geometry": {"coordinates":[2.1139750481,41.354801178],"type":"Point"}
}