{
  "type": "Feature",
  "properties": {
    "iso:country":"ES",
    "sg:address":"Calle de Pescado (del), 2",
    "sg:city":"Almoguera",
    "sg:orig_category":"Alimentaci\u00d3n General (al Por Menor)",
    "sg:phone":"+34 949 38 00 41",
    "sg:postcode":"19115",
    "sg:province":"Guadalajara",
    "wof:name":"Villalba Padrino Calixto",
    "wof:placetype":"venue"
},
  "geometry": {"coordinates":[-2.9820010662,40.2974853516],"type":"Point"}
}