{
  "type": "Feature",
  "properties": {
    "iso:country":"ES",
    "sg:address":"Calle de Tortola, 21",
    "sg:city":"Granada",
    "sg:orig_category":"Industria Qu\u00cdmica",
    "sg:phone":"+34 958 29 05 61",
    "sg:postcode":"18014",
    "sg:province":"Granada",
    "wof:name":"Consorcio Provincial Residu0s Urbanos De La Provincia De Granada",
    "wof:placetype":"venue"
},
  "geometry": {"coordinates":[-3.6111850739,37.1855545044],"type":"Point"}
}