{
  "type": "Feature",
  "properties": {
    "iso:country":"ES",
    "sg:address":"Ctra. Nnal. Madrid-cadiz, S/n",
    "sg:city":"Barrio Jarana",
    "sg:orig_category":"Serrer\u00cdas De Madera",
    "sg:phone":"+34 956 83 41 14",
    "sg:postcode":"11518",
    "sg:province":"C\u00e1diz",
    "wof:name":"Serreria Enrique S.l.",
    "wof:placetype":"venue"
},
  "geometry": {"coordinates":[-6.1426901817,36.5036659241],"type":"Point"}
}