{
  "type": "Feature",
  "properties": {
    "addr:full":"Carrer de Pintor Fortuny, 26 Barcelona Barcelona 08001",
    "addr:housenumber":"26",
    "addr:postcode":"08001",
    "addr:street":"Carrer De Pintor Fortuny",
    "iso:country":"ES",
    "sg:address":"Carrer de Pintor Fortuny, 26",
    "sg:city":"Barcelona",
    "sg:orig_category":"Librer\u00cdas",
    "sg:phone":"+34 933 17 68 11",
    "sg:postcode":"08001",
    "sg:province":"Barcelona",
    "wof:name":"Rubiols Castells Josep Maria",
    "wof:placetype":"venue"
},
  "geometry": {"coordinates":[2.1690440178,41.3826522827],"type":"Point"}
}