{
  "type": "Feature",
  "properties": {
    "addr:full":"Rier Escorial (de L'), 4 Reus Tarragona 43205",
    "addr:housenumber":"4",
    "addr:postcode":"43205",
    "addr:street":"'",
    "iso:country":"ES",
    "sg:address":"Rier Escorial (de L'), 4",
    "sg:city":"Reus",
    "sg:orig_category":"Promotores Constructores",
    "sg:phone":"+34 977 75 75 11",
    "sg:postcode":"43205",
    "sg:province":"Tarragona",
    "wof:name":"Canalizaciones Canalcons Reus S.a.",
    "wof:placetype":"venue"
},
  "geometry": {"coordinates":[1.1162339449,41.1403388977],"type":"Point"}
}