{
  "type": "Feature",
  "properties": {
    "iso:country":"ES",
    "sg:address":"Avda Ricardo Curtoys Gotarredona, 18",
    "sg:city":"Santa Eulalia",
    "sg:orig_category":"Inmobiliaria (agencias)",
    "sg:phone":"+34 971 33 13 09",
    "sg:postcode":"07840",
    "sg:province":"Islas Baleares",
    "wof:name":"Sisamon Sola Francisco Javier",
    "wof:placetype":"venue"
},
  "geometry": {"coordinates":[1.53213799,38.9822273254],"type":"Point"}
}