{
  "type": "Feature",
  "properties": {
    "iso:country":"ES",
    "sg:address":"C/ Ciutat, 2",
    "sg:city":"Llucmajor",
    "sg:orig_category":"Zapatos (al Por Menor)",
    "sg:phone":"+34 971 66 01 60",
    "sg:postcode":"07620",
    "sg:province":"Islas Baleares",
    "wof:name":"Catany Palmer Miguel",
    "wof:placetype":"venue"
},
  "geometry": {"coordinates":[2.8885529041,39.4920883179],"type":"Point"}
}