{
  "type": "Feature",
  "properties": {
    "iso:country":"ES",
    "sg:address":"Avda Navalperal, 28",
    "sg:city":"Navas Del Marques",
    "sg:orig_category":"Empresas De Carpinter\u00cda De Madera",
    "sg:phone":"+34 918 97 23 51",
    "sg:postcode":"05230",
    "sg:province":"\u00c1vila",
    "wof:name":"Fernandez Herranz Jose",
    "wof:placetype":"venue"
},
  "geometry": {"coordinates":[-4.3447413445,40.6019248962],"type":"Point"}
}