{
  "type": "Feature",
  "properties": {
    "iso:country":"ES",
    "sg:address":"Carrer de Anselm Clave, 61",
    "sg:city":"Mollet Valles",
    "sg:orig_category":"Transportes Por V\u00cdas Navegables",
    "sg:phone":"+34 935 93 11 76",
    "sg:postcode":"08100",
    "sg:province":"Barcelona",
    "wof:name":"Serrano Castellano Miguel",
    "wof:placetype":"venue"
},
  "geometry": {"coordinates":[2.216919899,41.5403938293],"type":"Point"}
}