{
  "type": "Feature",
  "properties": {
    "addr:full":"Calle de Porto Lagos, 9 Alcorcon Madrid 28924",
    "addr:housenumber":"9",
    "addr:postcode":"28924",
    "addr:street":"Calle De Porto Lagos",
    "iso:country":"ES",
    "sg:address":"Calle de Porto Lagos, 9",
    "sg:city":"Alcorcon",
    "sg:orig_category":"Alquiler De V\u00cddeo",
    "sg:phone":"+34 916 10 69 34",
    "sg:postcode":"28924",
    "sg:province":"Madrid",
    "wof:name":"De Benito Michel Maria Del Carmen",
    "wof:placetype":"venue"
},
  "geometry": {"coordinates":[-3.8190169334,40.3487281799],"type":"Point"}
}