{
  "type": "Feature",
  "properties": {
    "iso:country":"ES",
    "sg:address":"Avda Alcalde Lorenzo Carbonell, 18",
    "sg:city":"Alacant",
    "sg:orig_category":"Farmacias",
    "sg:phone":"+34 965 28 05 83",
    "sg:postcode":"03007",
    "sg:province":"Alicante",
    "wof:name":"Miralles Del Pozo Maria Pilar",
    "wof:placetype":"venue"
},
  "geometry": {"coordinates":[-0.5051929951,38.3394927979],"type":"Point"}
}