{
  "type": "Feature",
  "properties": {
    "iso:country":"ES",
    "sg:address":"Juan De La Cierva, 50",
    "sg:city":"Torrellano",
    "sg:orig_category":"Zapatos: Material, Suministros, Accesorios (fabricaci\u00d3n, Al Por Mayor)",
    "sg:phone":"+34 965 68 13 66",
    "sg:postcode":"03320",
    "sg:province":"Alicante",
    "sg:website":"www.aplifor.com",
    "wof:name":"Apliflor S.l.",
    "wof:placetype":"venue"
},
  "geometry": {"coordinates":[-0.6121956706,38.2970237732],"type":"Point"}
}