{
  "type": "Feature",
  "properties": {
    "iso:country":"ES",
    "sg:address":"Calle de Ancares, 3",
    "sg:city":"Valladolid",
    "sg:orig_category":"Afiladoras, Pulidoras Y Bru\u00d1idoras",
    "sg:phone":"+34 983 24 58 21",
    "sg:postcode":"47008",
    "sg:province":"Valladolid",
    "wof:name":"Rodriguez Saez Sara",
    "wof:placetype":"venue"
},
  "geometry": {"coordinates":[-4.7463197708,41.6215248108],"type":"Point"}
}