{
  "type": "Feature",
  "properties": {
    "addr:full":"Rond Campieles, 53 Calatayud Zaragoza 50300",
    "addr:housenumber":"53",
    "addr:postcode":"50300",
    "addr:street":"Campieles",
    "iso:country":"ES",
    "sg:address":"Rond Campieles, 53",
    "sg:city":"Calatayud",
    "sg:orig_category":"Cerrajer\u00cda, Ferrallista",
    "sg:phone":"+34 976 88 60 62",
    "sg:postcode":"50300",
    "sg:province":"Zaragoza",
    "wof:name":"Langa Heredero Eduardo Pascual",
    "wof:placetype":"venue"
},
  "geometry": {"coordinates":[-1.6394540071,41.3522415161],"type":"Point"}
}