{
  "type": "Feature",
  "properties": {
    "addr:full":"Via Barcino, 119 Barcelona Barcelona 08033",
    "addr:housenumber":"119",
    "addr:postcode":"08033",
    "addr:street":"Via Barcino",
    "iso:country":"ES",
    "sg:address":"Via Barcino, 119",
    "sg:city":"Barcelona",
    "sg:orig_category":"Droguer\u00cdas (al Por Menor)",
    "sg:phone":"+34 933 11 65 70",
    "sg:postcode":"08033",
    "sg:province":"Barcelona",
    "wof:name":"Bertolin Igual Maria Del Carmen",
    "wof:placetype":"venue"
},
  "geometry": {"coordinates":[2.1907019615,41.4483261108],"type":"Point"}
}