{
  "type": "Feature",
  "properties": {
    "iso:country":"ES",
    "sg:address":"Pase Extremadura, 28",
    "sg:city":"Madrid",
    "sg:orig_category":"Chapister\u00cda",
    "sg:phone":"+34 914 64 74 34",
    "sg:postcode":"28011",
    "sg:province":"Madrid",
    "wof:name":"Herramar S. A.",
    "wof:placetype":"venue"
},
  "geometry": {"coordinates":[-3.7275409698,40.4138832092],"type":"Point"}
}