{
  "type": "Feature",
  "properties": {
    "addr:full":"Calle de Mayor, 25 S. Esteban Gormaz Soria 42330",
    "addr:housenumber":"25",
    "addr:postcode":"42330",
    "addr:street":"Calle De Mayor;S. Esteban Gormaz",
    "iso:country":"ES",
    "sg:address":"Calle de Mayor, 25",
    "sg:city":"S. Esteban Gormaz",
    "sg:orig_category":"Carnicer\u00cdas, Carnicer\u00cdas",
    "sg:phone":"+34 975 35 01 17",
    "sg:postcode":"42330",
    "sg:province":"Soria",
    "wof:name":"Lamata Cobacho Julio",
    "wof:placetype":"venue"
},
  "geometry": {"coordinates":[-3.2045791149,41.5739402771],"type":"Point"}
}