{
  "type": "Feature",
  "properties": {
    "iso:country":"ES",
    "sg:address":"Calle de Felipe Ramirez, 6",
    "sg:city":"Arahal",
    "sg:orig_category":"Electrodom\u00c9sticos (fabricaci\u00d3n, Al Por Mayor)",
    "sg:phone":"+34 954 84 01 03",
    "sg:postcode":"41600",
    "sg:province":"Sevilla",
    "wof:name":"Garcia Alba Rafael",
    "wof:placetype":"venue"
},
  "geometry": {"coordinates":[-5.5458087921,37.2622261047],"type":"Point"}
}