{
  "type": "Feature",
  "properties": {
    "iso:country":"ES",
    "sg:address":"Carrer de Segarra, 45",
    "sg:city":"Sabadell",
    "sg:orig_category":"Empresas De Carpinter\u00cda",
    "sg:phone":"+34 937 24 21 38",
    "sg:postcode":"08207",
    "sg:province":"Barcelona",
    "wof:name":"Eslava Carrero Salvador",
    "wof:placetype":"venue"
},
  "geometry": {"coordinates":[2.0924839973,41.565536499],"type":"Point"}
}