{
  "type": "Feature",
  "properties": {
    "addr:full":"Calle de Cromo, 14 Valladolid Valladolid 47012",
    "addr:housenumber":"14",
    "addr:postcode":"47012",
    "addr:street":"Calle De Cromo",
    "iso:country":"ES",
    "sg:address":"Calle de Cromo, 14",
    "sg:city":"Valladolid",
    "sg:orig_category":"Automatizaci\u00d3n De Procesos Industriales Y De Edificaci\u00d3n (estudios, Instalaci\u00d3n)",
    "sg:phone":"+34 983 29 23 25",
    "sg:postcode":"47012",
    "sg:province":"Valladolid",
    "sg:website":"www.athorindustrial.com",
    "wof:name":"Automatizacion Y Tecnologia De Organizacion Industrial S.l.",
    "wof:placetype":"venue"
},
  "geometry": {"coordinates":[-4.7041711807,41.6273727417],"type":"Point"}
}