{
  "type": "Feature",
  "properties": {
    "iso:country":"ES",
    "sg:address":"Calle de Ntra Sra Soledad, 5",
    "sg:city":"Fuensalida",
    "sg:orig_category":"Loter\u00cda Y T\u00d3mbola",
    "sg:phone":"+34 925 78 42 39",
    "sg:postcode":"45510",
    "sg:province":"Toledo",
    "wof:name":"Tenorio Hernandez Mari-cruz",
    "wof:placetype":"venue"
},
  "geometry": {"coordinates":[-4.2095799446,40.0540885925],"type":"Point"}
}