{
  "type": "Feature",
  "properties": {
    "iso:country":"ES",
    "sg:address":"Rua Fonte Da Balsa, S/n",
    "sg:city":"Vilaboa",
    "sg:orig_category":"Sindicatos De Trabajadores",
    "sg:phone":"+34 981 66 70 06",
    "sg:postcode":"15174",
    "sg:province":"A Coru\u00f1a",
    "wof:name":"Union General De Trabajadores De Galicia",
    "wof:placetype":"venue"
},
  "geometry": {"coordinates":[-8.3806333542,43.3070106506],"type":"Point"}
}