{
  "type": "Feature",
  "properties": {
    "addr:full":"Euskadi Etorbidea, 5 O\u00f1ati Guip\u00f9zcoa 20560",
    "addr:housenumber":"5",
    "addr:postcode":"20560",
    "addr:street":"Euskadi Etorbidea;Guipu\u0300Zcoa",
    "iso:country":"ES",
    "sg:address":"Euskadi Etorbidea, 5",
    "sg:city":"O\u00f1ati",
    "sg:orig_category":"M\u00c9dicos: Fisioterapia Y Rehabilitaci\u00d3n",
    "sg:phone":"+34 943 71 82 14",
    "sg:postcode":"20560",
    "sg:province":"Guip\u00f9zcoa",
    "wof:name":"Gorospe Olazabal Ainitze",
    "wof:placetype":"venue"
},
  "geometry": {"coordinates":[-2.4098920822,43.0322761536],"type":"Point"}
}