{
  "type": "Feature",
  "properties": {
    "addr:full":"Pl. Esgl\u00e9sia, 1 Roses Girona 17480",
    "addr:housenumber":"1",
    "addr:postcode":"17480",
    "addr:street":"Pl. Esgle\u0301Sia",
    "iso:country":"ES",
    "sg:address":"Pl. Esgl\u00e9sia, 1",
    "sg:city":"Roses",
    "sg:orig_category":"Ropa Para Ni\u00d1os (al Por Menor)",
    "sg:phone":"+34 972 25 72 97",
    "sg:postcode":"17480",
    "sg:province":"Girona",
    "wof:name":"Figueras Vigo Pilar",
    "wof:placetype":"venue"
},
  "geometry": {"coordinates":[3.1776371002,42.2622718811],"type":"Point"}
}