{
  "type": "Feature",
  "properties": {
    "iso:country":"ES",
    "sg:address":"Calle de Ribera, 14",
    "sg:city":"Bilbao",
    "sg:orig_category":"Edici\u00d3n De Diarios, Revistas, Boletines",
    "sg:phone":"+34 946 79 05 46",
    "sg:postcode":"48005",
    "sg:province":"Vizcaya",
    "sg:website":"www.ueu.org",
    "wof:name":"Udako Euskal Unibertsitatea Ueu",
    "wof:placetype":"venue"
},
  "geometry": {"coordinates":[-2.9263210297,43.2575035095],"type":"Point"}
}