{
  "type": "Feature",
  "properties": {
    "iso:country":"ES",
    "sg:address":"Calle de Ferrocarril Minero, S/n",
    "sg:city":"Agua Amarga",
    "sg:orig_category":"Supermercados Y Hipermercados",
    "sg:phone":"+34 950 13 82 07",
    "sg:postcode":"04149",
    "sg:province":"Almer\u00eda",
    "wof:name":"Sanchez Caparros Maria Francisca",
    "wof:placetype":"venue"
},
  "geometry": {"coordinates":[-1.9343990088,36.9395217896],"type":"Point"}
}