{
  "type": "Feature",
  "properties": {
    "addr:full":"Pda. S. Bartomeu, S/n Solsona Lleida 25280",
    "addr:housenumber":"s / n",
    "addr:postcode":"25280",
    "addr:street":"Pda.;Bartomeu",
    "iso:country":"ES",
    "sg:address":"Pda. S. Bartomeu, S/n",
    "sg:city":"Solsona",
    "sg:orig_category":"Agricultores, Agricultores",
    "sg:phone":"+34 973 48 06 93",
    "sg:postcode":"25280",
    "sg:province":"Lleida",
    "wof:name":"Andreu Priego Ramon",
    "wof:placetype":"venue"
},
  "geometry": {"coordinates":[1.5177006721,41.9936256409],"type":"Point"}
}