{
  "type": "Feature",
  "properties": {
    "iso:country":"ES",
    "sg:address":"Bidebarrieta Kalea, 5",
    "sg:city":"O\u00f1ati",
    "sg:orig_category":"Plomeros",
    "sg:phone":"+34 943 08 28 55",
    "sg:postcode":"20560",
    "sg:province":"Guip\u00f9zcoa",
    "wof:name":"Instalaciones Beloki S.l.",
    "wof:placetype":"venue"
},
  "geometry": {"coordinates":[-2.4133200645,43.0308265686],"type":"Point"}
}