{
  "type": "Feature",
  "properties": {
    "iso:country":"ES",
    "sg:address":"Calle de Antonio Espinosa, 8",
    "sg:city":"Salamanca",
    "sg:orig_category":"Gu\u00cdas Y Gu\u00cdas",
    "sg:phone":"+34 923 24 54 68",
    "sg:postcode":"37007",
    "sg:province":"Salamanca",
    "wof:name":"Garcia De Juan Juan Manuel",
    "wof:placetype":"venue"
},
  "geometry": {"coordinates":[-5.6653733253,40.9705085754],"type":"Point"}
}