{
  "type": "Feature",
  "properties": {
    "addr:full":"Carrer de General Padros, 26 Caldes Montbui Barcelona 08140",
    "addr:housenumber":"26",
    "addr:postcode":"08140",
    "addr:street":"Carrer De General Padros;Montbui Barcelona",
    "iso:country":"ES",
    "sg:address":"Carrer de General Padros, 26",
    "sg:city":"Caldes Montbui",
    "sg:orig_category":"Mec\u00c1nico Del Autom\u00d3vil",
    "sg:phone":"+34 938 65 41 93",
    "sg:postcode":"08140",
    "sg:province":"Barcelona",
    "wof:name":"Gascon Navarro Josep Maria",
    "wof:placetype":"venue"
},
  "geometry": {"coordinates":[2.1652989388,41.6285171509],"type":"Point"}
}