{
  "type": "Feature",
  "properties": {
    "iso:country":"ES",
    "sg:address":"Avda Doctor Rafael Gonzalez, 17",
    "sg:city":"Arrecife",
    "sg:orig_category":"Radiocomunicaciones, Telefon\u00cda M\u00d3vil, Radiomensajer\u00cda: Servicios, Comercializaci\u00d3n",
    "sg:phone":"+34 928 81 32 38",
    "sg:postcode":"35500",
    "sg:province":"Las Palmas",
    "sg:website":"www.telyco.es",
    "wof:name":"Teleinformatica Y Comunicaciones S.a.",
    "wof:placetype":"venue"
},
  "geometry": {"coordinates":[-13.5535354614,28.9578990936],"type":"Point"}
}