{
  "type": "Feature",
  "properties": {
    "iso:country":"ES",
    "sg:address":"Ctra. C. Golf, S/n",
    "sg:city":"Malaga",
    "sg:orig_category":"Asociaciones Y Clubs Deportivos",
    "sg:phone":"+34 952 37 66 77",
    "sg:postcode":"29004",
    "sg:province":"M\u00e1laga",
    "wof:name":"Real Club De Campo Malaga",
    "wof:placetype":"venue"
},
  "geometry": {"coordinates":[-4.4738588333,36.6577987671],"type":"Point"}
}