{
  "type": "Feature",
  "properties": {
    "iso:country":"ES",
    "sg:address":"Calle de Alhondiga, 68",
    "sg:city":"Sevilla",
    "sg:orig_category":"M\u00c9dicos: Cirug\u00cda Ortop\u00c9dica Y Traumatolog\u00cda",
    "sg:phone":"+34 954 56 44 33",
    "sg:postcode":"41003",
    "sg:province":"Sevilla",
    "wof:name":"Boz Madue\u00f1o Francisco Javier Del",
    "wof:placetype":"venue"
},
  "geometry": {"coordinates":[-5.9889278412,37.3911056519],"type":"Point"}
}