{
  "type": "Feature",
  "properties": {
    "iso:country":"ES",
    "sg:address":"Calle de Pozo Nuevo, 25",
    "sg:city":"Mairena Aljarafe",
    "sg:orig_category":"Molduras, Junquillos, Listones Y Molduras Perforadas",
    "sg:phone":"+34 955 76 81 44",
    "sg:postcode":"41927",
    "sg:province":"Sevilla",
    "wof:name":"Colchero Gavi\u00f1o Manuel",
    "wof:placetype":"venue"
},
  "geometry": {"coordinates":[-6.0663361549,37.3451347351],"type":"Point"}
}