{
  "type": "Feature",
  "properties": {
    "iso:country":"ES",
    "sg:address":"Calle de San Fernando, 6",
    "sg:city":"Meliana",
    "sg:orig_category":"Tapicer\u00cdas",
    "sg:phone":"+34 961 49 05 38",
    "sg:postcode":"46133",
    "sg:province":"Valencia",
    "wof:name":"Sevillano Morillo Santiago",
    "wof:placetype":"venue"
},
  "geometry": {"coordinates":[-0.3230139911,39.5274848938],"type":"Point"}
}