{
  "type": "Feature",
  "properties": {
    "addr:full":"Avda Caldas (das), 47 Ourense Ourense 32001",
    "addr:housenumber":"47",
    "addr:postcode":"32001",
    "addr:street":"Avda Caldas Das",
    "iso:country":"ES",
    "sg:address":"Avda Caldas (das), 47",
    "sg:city":"Ourense",
    "sg:orig_category":"Farmacias",
    "sg:phone":"+34 988 21 30 24",
    "sg:postcode":"32001",
    "sg:province":"Ourense",
    "wof:name":"Rodriguez Pernas Lourdes",
    "wof:placetype":"venue"
},
  "geometry": {"coordinates":[-7.8714761734,42.3492469788],"type":"Point"}
}