{
  "type": "Feature",
  "properties": {
    "iso:country":"ES",
    "sg:address":"Carrer de Camp De Les Moreres, 6",
    "sg:city":"Granollers",
    "sg:orig_category":"Inmobiliaria (agencias)",
    "sg:phone":"+34 938 61 35 93",
    "sg:postcode":"08401",
    "sg:province":"Barcelona",
    "wof:name":"La Llar De Silmar S.l.",
    "wof:placetype":"venue"
},
  "geometry": {"coordinates":[2.2840869427,41.6006546021],"type":"Point"}
}