{
  "type": "Feature",
  "properties": {
    "iso:country":"ES",
    "sg:address":"Calle de Diego Ni\u00d1o, 7",
    "sg:city":"Puerto De Santa Maria",
    "sg:orig_category":"Mec\u00c1nico Del Autom\u00d3vil",
    "sg:phone":"+34 956 54 26 11",
    "sg:postcode":"11500",
    "sg:province":"C\u00e1diz",
    "wof:name":"Taller Santa Maria Del Puerto S.l.",
    "wof:placetype":"venue"
},
  "geometry": {"coordinates":[-6.2234559059,36.6020240784],"type":"Point"}
}