{
  "type": "Feature",
  "properties": {
    "iso:country":"ES",
    "sg:address":"Avda Orense, 33",
    "sg:city":"Puente De Domingo Florez",
    "sg:orig_category":"Florister\u00cdas",
    "sg:phone":"+34 987 46 06 37",
    "sg:postcode":"24380",
    "sg:province":"Le\u00f3n",
    "wof:name":"Fernandez Diaz Maria Teresa",
    "wof:placetype":"venue"
},
  "geometry": {"coordinates":[-6.8225069046,42.4150733948],"type":"Point"}
}