{
  "type": "Feature",
  "properties": {
    "iso:country":"ES",
    "sg:address":"C/ Cami Dels Magros, 90",
    "sg:city":"Elche",
    "sg:orig_category":"Mec\u00c1nico Del Autom\u00d3vil",
    "sg:phone":"+34 966 67 09 37",
    "sg:postcode":"03206",
    "sg:province":"Alicante",
    "wof:name":"Rolar Motor S.l.",
    "wof:placetype":"venue"
},
  "geometry": {"coordinates":[-0.7058399916,38.2768363953],"type":"Point"}
}