{
  "type": "Feature",
  "properties": {
    "iso:country":"ES",
    "sg:address":"Calle de Magallanes, 1",
    "sg:city":"Madrid",
    "sg:orig_category":"Centros Empresariales",
    "sg:phone":"+34 914 48 55 84",
    "sg:postcode":"28015",
    "sg:province":"Madrid",
    "wof:name":"Aranda Consultores S.l.",
    "wof:placetype":"venue"
},
  "geometry": {"coordinates":[-3.7051999569,40.4322013855],"type":"Point"}
}