{
  "type": "Feature",
  "properties": {
    "addr:full":"Calle de Teodoro Cuesta, 13 Oviedo Asturias 33012",
    "addr:housenumber":"13",
    "addr:postcode":"33012",
    "addr:street":"Calle De Teodoro Cuesta",
    "iso:country":"ES",
    "sg:address":"Calle de Teodoro Cuesta, 13",
    "sg:city":"Oviedo",
    "sg:orig_category":"Ingeniero",
    "sg:phone":"+34 985 29 24 24",
    "sg:postcode":"33012",
    "sg:province":"Asturias",
    "wof:name":"Diaz Perez Eduardo",
    "wof:placetype":"venue"
},
  "geometry": {"coordinates":[-5.854724884,43.3692131042],"type":"Point"}
}