{
  "type": "Feature",
  "properties": {
    "addr:full":"Calle de Pormetxeta, 16 San Vicente De Barakaldo Vizcaya 48901",
    "addr:housenumber":"16",
    "addr:postcode":"48901",
    "addr:street":"Calle De Pormetxeta",
    "iso:country":"ES",
    "sg:address":"Calle de Pormetxeta, 16",
    "sg:city":"San Vicente De Barakaldo",
    "sg:orig_category":"Fabricaci\u00d3n De Cortinas Y Visillos",
    "sg:phone":"+34 944 38 36 14",
    "sg:postcode":"48901",
    "sg:province":"Vizcaya",
    "wof:name":"Martinez Gonzalez Victor Angel",
    "wof:placetype":"venue"
},
  "geometry": {"coordinates":[-2.9841270447,43.2976112366],"type":"Point"}
}