{
  "type": "Feature",
  "properties": {
    "iso:country":"ES",
    "sg:address":"Calle de Teatro, 7",
    "sg:city":"Fuentesauco",
    "sg:orig_category":"M\u00c9dicos: Estomatolog\u00cda",
    "sg:phone":"+34 980 60 11 07",
    "sg:postcode":"49400",
    "sg:province":"Zamora",
    "wof:name":"Garcia Prieto Carlos",
    "wof:placetype":"venue"
},
  "geometry": {"coordinates":[-5.4957962036,41.2316551208],"type":"Point"}
}