{
  "type": "Feature",
  "properties": {
    "addr:full":"Calle de Sevilla, 33 Almonte Huelva 21730",
    "addr:housenumber":"33",
    "addr:postcode":"21730",
    "addr:street":"Calle De Sevilla",
    "iso:country":"ES",
    "sg:address":"Calle de Sevilla, 33",
    "sg:city":"Almonte",
    "sg:orig_category":"Ense\u00d1anza, Formaci\u00d3n Profesional: Aprendizaje",
    "sg:phone":"+34 959 45 01 59",
    "sg:postcode":"21730",
    "sg:province":"Huelva",
    "wof:name":"Junta De Andalucia Consejeria De Medio Ambiente",
    "wof:placetype":"venue"
},
  "geometry": {"coordinates":[-6.5162320137,37.2638320923],"type":"Point"}
}