{
  "type": "Feature",
  "properties": {
    "iso:country":"ES",
    "sg:address":"Calle de Fuente Nueva, 7",
    "sg:city":"Olvega",
    "sg:orig_category":"Juegos Y Juguetes (al Por Menor)",
    "sg:phone":"+34 976 64 50 47",
    "sg:postcode":"42110",
    "sg:province":"Soria",
    "wof:name":"Jimenez Iba\u00f1ez Eliseo",
    "wof:placetype":"venue"
},
  "geometry": {"coordinates":[-1.9783666134,41.7735214233],"type":"Point"}
}