{
  "type": "Feature",
  "properties": {
    "iso:country":"ES",
    "sg:address":"Carr Canals, 12",
    "sg:city":"Eliana",
    "sg:orig_category":"Inversiones",
    "sg:phone":"+34 962 74 18 36",
    "sg:postcode":"46183",
    "sg:province":"Valencia",
    "wof:name":"Provida Inversiones Y Pensiones S.l.",
    "wof:placetype":"venue"
},
  "geometry": {"coordinates":[-0.528208971,39.5667457581],"type":"Point"}
}