{
  "type": "Feature",
  "properties": {
    "addr:full":"Calle de Ronda Del Ferrocarril, 55 Miranda Ebro Burgos 09200",
    "addr:housenumber":"55",
    "addr:postcode":"09200",
    "addr:street":"Calle De Ronda Del Ferrocarril",
    "iso:country":"ES",
    "sg:address":"Calle de Ronda Del Ferrocarril, 55",
    "sg:city":"Miranda Ebro",
    "sg:orig_category":"Electricidad: Instaladores",
    "sg:phone":"+34 947 33 16 32",
    "sg:postcode":"09200",
    "sg:province":"Burgos",
    "wof:name":"Montajes Electricos E.l.d. S.l.",
    "wof:placetype":"venue"
},
  "geometry": {"coordinates":[-2.9453029633,42.6889152527],"type":"Point"}
}