{
  "type": "Feature",
  "properties": {
    "addr:full":"Carrer de Diesel, 1 Sector Autopista Barcelona 08150",
    "addr:housenumber":"1",
    "addr:postcode":"08150",
    "addr:street":"Carrer De Diesel;Autopista Barcelona",
    "iso:country":"ES",
    "sg:address":"Carrer de Diesel, 1",
    "sg:city":"Sector Autopista",
    "sg:classifiers":[
        {
            "category":"Food & Beverages",
            "subcategory":"Candy",
            "type":"Retail Goods"
        }
    ],
    "sg:phone":"+34 935 62 53 51",
    "sg:postcode":"08150",
    "sg:province":"Barcelona",
    "sg:tags":[
        "confiter\u00cdas",
        "y",
        "de",
        "fabricaci\u00d3n",
        "chocolate"
    ],
    "sg:website":"www.disgo.es",
    "wof:name":"Disgo S. A.",
    "wof:placetype":"venue"
},
  "geometry": {"coordinates":[2.2319469452,41.5694198608],"type":"Point"}
}