{
  "type": "Feature",
  "properties": {
    "addr:full":"Pg Francesc Macia, 32 Rubi Barcelona 08191",
    "addr:housenumber":"32",
    "addr:postcode":"08191",
    "addr:street":"Pg Francesc Macia",
    "iso:country":"ES",
    "sg:address":"Pg Francesc Macia, 32",
    "sg:city":"Rubi",
    "sg:orig_category":"Quiropr\u00c1cticos",
    "sg:phone":"+34 936 99 16 67",
    "sg:postcode":"08191",
    "sg:province":"Barcelona",
    "wof:name":"Vallhonrat Blazquez Andres",
    "wof:placetype":"venue"
},
  "geometry": {"coordinates":[2.0315051079,41.4900093079],"type":"Point"}
}