{
  "type": "Feature",
  "properties": {
    "addr:full":"A Ermida, 6 Ermida Pontevedra 36154",
    "addr:housenumber":"6",
    "addr:postcode":"36154",
    "addr:street":"Ermida",
    "iso:country":"ES",
    "sg:address":"A Ermida, 6",
    "sg:city":"Ermida",
    "sg:orig_category":"Molduras, Junquillos, Listones Y Molduras Perforadas",
    "sg:phone":"+34 986 85 20 11",
    "sg:postcode":"36154",
    "sg:province":"Pontevedra",
    "wof:name":"Rodriguez Dios Edelmiro",
    "wof:placetype":"venue"
},
  "geometry": {"coordinates":[-8.6151094437,42.4113616943],"type":"Point"}
}