{
  "type": "Feature",
  "properties": {
    "iso:country":"ES",
    "sg:address":"Avda Donostiarra, 23",
    "sg:city":"Madrid",
    "sg:orig_category":"Perfumer\u00cda (al Por Menor)",
    "sg:phone":"+34 914 04 36 66",
    "sg:postcode":"28027",
    "sg:province":"Madrid",
    "wof:name":"Herraez Garcia Luciano",
    "wof:placetype":"venue"
},
  "geometry": {"coordinates":[-3.6569159031,40.4348564148],"type":"Point"}
}