{
  "type": "Feature",
  "properties": {
    "addr:full":"Calle de Capitan Blanco Argibay, 3 Madrid Madrid 28029",
    "addr:housenumber":"3",
    "addr:postcode":"28029",
    "addr:street":"Calle De Capitan Blanco Argibay",
    "iso:country":"ES",
    "sg:address":"Calle de Capitan Blanco Argibay, 3",
    "sg:city":"Madrid",
    "sg:orig_category":"Caf\u00c9s, Bares, Cervecer\u00cdas",
    "sg:phone":"+34 915 70 83 35",
    "sg:postcode":"28029",
    "sg:province":"Madrid",
    "wof:name":"Gomez Y Menor C.b.",
    "wof:placetype":"venue"
},
  "geometry": {"coordinates":[-3.6956169605,40.4644393921],"type":"Point"}
}