{
  "type": "Feature",
  "properties": {
    "iso:country":"ES",
    "sg:address":"Carrer de Talamanca, 5",
    "sg:city":"Manresa",
    "sg:orig_category":"Comunidades Religiosas",
    "sg:phone":"+34 938 72 65 63",
    "sg:postcode":"08241",
    "sg:province":"Barcelona",
    "wof:name":"Religiosas Capuchinas",
    "wof:placetype":"venue"
},
  "geometry": {"coordinates":[1.8244639635,41.7229652405],"type":"Point"}
}