{
  "type": "Feature",
  "properties": {
    "iso:country":"ES",
    "sg:address":"Carrer de Sant Carles, 40",
    "sg:city":"Santa Coloma De Gramenet",
    "sg:orig_category":"Bancos",
    "sg:phone":"+34 934 66 50 83",
    "sg:postcode":"08922",
    "sg:province":"Barcelona",
    "wof:name":"Barclays Bank S.a.e.",
    "wof:placetype":"venue"
},
  "geometry": {"coordinates":[2.208851099,41.4500350952],"type":"Point"}
}