{
  "type": "Feature",
  "properties": {
    "addr:full":"Carrer de Consell De Cent, 259 Barcelona Barcelona 08011",
    "addr:housenumber":"259",
    "addr:postcode":"08011",
    "addr:street":"Carrer De Consell De Cent",
    "iso:country":"ES",
    "sg:address":"Carrer de Consell De Cent, 259",
    "sg:city":"Barcelona",
    "sg:orig_category":"Tapiceros Y Tapiceros",
    "sg:phone":"+34 934 53 49 02",
    "sg:postcode":"08011",
    "sg:province":"Barcelona",
    "wof:name":"Mora Llonch Maria Elena",
    "wof:placetype":"venue"
},
  "geometry": {"coordinates":[2.1599760056,41.3869819641],"type":"Point"}
}