{
  "type": "Feature",
  "properties": {
    "addr:full":"Calle de Quintana, 15 Oviedo Asturias 33009",
    "addr:housenumber":"15",
    "addr:postcode":"33009",
    "addr:street":"Calle De Quintana",
    "iso:country":"ES",
    "sg:address":"Calle de Quintana, 15",
    "sg:city":"Oviedo",
    "sg:orig_category":"Centros Empresariales",
    "sg:phone":"+34 985 21 15 30",
    "sg:postcode":"33009",
    "sg:province":"Asturias",
    "wof:name":"Asociacion Profesional De Empresarios De Estaciones De Servicio",
    "wof:placetype":"venue"
},
  "geometry": {"coordinates":[-5.8484177589,43.3581809998],"type":"Point"}
}