{
  "type": "Feature",
  "properties": {
    "addr:full":"Poligono De Sabon, S/n Arteixo La Coru\u00f1a 15142",
    "addr:housenumber":"s / n",
    "addr:postcode":"15142",
    "addr:street":"La Corun\u0303A",
    "iso:country":"ES",
    "sg:address":"Poligono De Sabon, S/n",
    "sg:city":"Arteixo",
    "sg:orig_category":"Explotaci\u00d3n De Canteras",
    "sg:phone":"+34 981 64 12 18",
    "sg:postcode":"15142",
    "sg:province":"La Coru\u00f1a",
    "wof:name":"Ousinde S.l.",
    "wof:placetype":"venue"
},
  "geometry": {"coordinates":[-8.5030317307,43.3256492615],"type":"Point"}
}