{
  "type": "Feature",
  "properties": {
    "iso:country":"ES",
    "sg:address":"Carrer de Roger De Flor, 216",
    "sg:city":"Barcelona",
    "sg:orig_category":"Peluqueros: De Se\u00d1oras",
    "sg:phone":"+34 934 58 71 14",
    "sg:postcode":"08013",
    "sg:province":"Barcelona",
    "wof:name":"Coronado Garcia Maria Cruz",
    "wof:placetype":"venue"
},
  "geometry": {"coordinates":[2.1712551117,41.4000282288],"type":"Point"}
}