{
  "type": "Feature",
  "properties": {
    "addr:full":"Calle de Arturo Soria, 142 Madrid Madrid 28043",
    "addr:housenumber":"142",
    "addr:postcode":"28043",
    "addr:street":"Calle De Arturo Soria",
    "iso:country":"ES",
    "sg:address":"Calle de Arturo Soria, 142",
    "sg:city":"Madrid",
    "sg:orig_category":"Fisioterapia",
    "sg:phone":"+34 914 13 89 11",
    "sg:postcode":"28043",
    "sg:province":"Madrid",
    "wof:name":"Fisioespa\u00f1a C.b.",
    "wof:placetype":"venue"
},
  "geometry": {"coordinates":[-3.653023243,40.4519844055],"type":"Point"}
}