{
  "type": "Feature",
  "properties": {
    "iso:country":"ES",
    "sg:address":"Calle de Vasco Diaz Tanco, 64",
    "sg:city":"Fregenal Sierra",
    "sg:orig_category":"Reposter\u00cdas",
    "sg:phone":"+34 924 70 00 79",
    "sg:postcode":"06340",
    "sg:province":"Badajoz",
    "wof:name":"Panificadora Frexnense S. L.",
    "wof:placetype":"venue"
},
  "geometry": {"coordinates":[-6.6506791115,38.1689910889],"type":"Point"}
}