{
  "type": "Feature",
  "properties": {
    "iso:country":"ES",
    "sg:address":"Calle de Encomienda De Palacios, 192",
    "sg:city":"Madrid",
    "sg:orig_category":"Iglesia Cat\u00d3lica",
    "sg:phone":"+34 917 73 03 63",
    "sg:postcode":"28030",
    "sg:province":"Madrid",
    "wof:name":"Parroquia Santa Maria Del Buen Aire",
    "wof:placetype":"venue"
},
  "geometry": {"coordinates":[-3.6412231922,40.3992805481],"type":"Point"}
}