{
  "type": "Feature",
  "properties": {
    "addr:full":"Calle de Porvenir, S/n Andosilla Navarra 31261",
    "addr:housenumber":"s / n",
    "addr:postcode":"31261",
    "addr:street":"Calle De Porvenir",
    "iso:country":"ES",
    "sg:address":"Calle de Porvenir, S/n",
    "sg:city":"Andosilla",
    "sg:orig_category":"Conservas De Legumbres (fabricaci\u00d3n, Al Por Mayor)",
    "sg:phone":"+34 948 67 40 25",
    "sg:postcode":"31261",
    "sg:province":"Navarra",
    "sg:website":"www.elchaval.es",
    "wof:name":"Conservas El Chaval S.l.",
    "wof:placetype":"venue"
},
  "geometry": {"coordinates":[-1.9479709864,42.3728561401],"type":"Point"}
}