{
  "type": "Feature",
  "properties": {
    "iso:country":"ES",
    "sg:address":"Calle de Acero, 1",
    "sg:city":"Arganda",
    "sg:orig_category":"Fabricaci\u00d3n De Juguetes Autom\u00c1ticos",
    "sg:phone":"+34 918 71 02 97",
    "sg:postcode":"28500",
    "sg:province":"Madrid",
    "wof:name":"Recreativos Franco S.a.",
    "wof:placetype":"venue"
},
  "geometry": {"coordinates":[-3.4672489166,40.3018417358],"type":"Point"}
}