{
  "type": "Feature",
  "properties": {
    "iso:country":"ES",
    "sg:address":"Carrer de Puigmarti, 34",
    "sg:city":"Barcelona",
    "sg:orig_category":"Ropa Para Se\u00d1oras (al Por Menor)",
    "sg:phone":"+34 932 84 87 63",
    "sg:postcode":"08012",
    "sg:province":"Barcelona",
    "wof:name":"Hernandez Santa Victorio",
    "wof:placetype":"venue"
},
  "geometry": {"coordinates":[2.1600050926,41.401889801],"type":"Point"}
}