{
  "type": "Feature",
  "properties": {
    "iso:country":"ES",
    "sg:address":"Carr Tramuntana, 31",
    "sg:city":"Torroella Montgri",
    "sg:orig_category":"Alimentaci\u00d3n General (al Por Mayor)",
    "sg:phone":"+34 972 75 85 48",
    "sg:postcode":"17257",
    "sg:province":"Girona",
    "wof:name":"Fabrega Albalat Narciso",
    "wof:placetype":"venue"
},
  "geometry": {"coordinates":[3.1277420521,42.042766571],"type":"Point"}
}