{
  "type": "Feature",
  "properties": {
    "addr:full":"Avda Cardenal Herrera Oria, Km. 0003,1 Madrid Madrid 28035",
    "addr:postcode":"28035",
    "addr:street":"Avda Cardenal Herrera Oria Km. 0003,1",
    "iso:country":"ES",
    "sg:address":"Avda Cardenal Herrera Oria, Km. 0003,1",
    "sg:city":"Madrid",
    "sg:orig_category":"Distribuci\u00d3n De Petr\u00d3leo Y Derivados",
    "sg:phone":"+34 913 16 29 17",
    "sg:postcode":"28035",
    "sg:province":"Madrid",
    "wof:name":"Gasolinera Las Cuartillas S.l.",
    "wof:placetype":"venue"
},
  "geometry": {"coordinates":[-3.7147989273,40.4831161499],"type":"Point"}
}