{
  "type": "Feature",
  "properties": {
    "addr:full":"Calle de Eras, S/n Deleitosa C\u00e1ceres 10370",
    "addr:housenumber":"s / n",
    "addr:postcode":"10370",
    "addr:street":"Calle De Eras;Ca\u0301Ceres",
    "iso:country":"ES",
    "sg:address":"Calle de Eras, S/n",
    "sg:city":"Deleitosa",
    "sg:orig_category":"Fabricaci\u00d3n De Quesos",
    "sg:phone":"+34 927 54 02 77",
    "sg:postcode":"10370",
    "sg:province":"C\u00e1ceres",
    "wof:name":"Queserias Almonte S.l.",
    "wof:placetype":"venue"
},
  "geometry": {"coordinates":[-5.6451191902,39.6408233643],"type":"Point"}
}