{
  "type": "Feature",
  "properties": {
    "addr:full":"Psaj Bego\u00d1a, 6 Malaga M\u00e1laga 29010",
    "addr:housenumber":"6",
    "addr:postcode":"29010",
    "addr:street":"Begon\u0303A;Ma\u0301Laga",
    "iso:country":"ES",
    "sg:address":"Psaj Bego\u00d1a, 6",
    "sg:city":"Malaga",
    "sg:orig_category":"Servicios De Telecomunicaciones",
    "sg:phone":"+34 952 61 64 35",
    "sg:postcode":"29010",
    "sg:province":"M\u00e1laga",
    "wof:name":"Orange Call S.l.",
    "wof:placetype":"venue"
},
  "geometry": {"coordinates":[-4.4374542236,36.7232093811],"type":"Point"}
}