{
  "type": "Feature",
  "properties": {
    "iso:country":"ES",
    "sg:address":"Pase Lazkano De, 51",
    "sg:city":"Donostia-san Sebastian",
    "sg:orig_category":"Agencias Y Asesores De Publicidad",
    "sg:phone":"+34 943 46 19 83",
    "sg:postcode":"20009",
    "sg:province":"Guip\u00f9zcoa",
    "wof:name":"Munto Berri Promociones S.l.",
    "wof:placetype":"venue"
},
  "geometry": {"coordinates":[-1.9896440506,43.3084068298],"type":"Point"}
}