{
  "type": "Feature",
  "properties": {
    "iso:country":"ES",
    "sg:address":"Carrer de Andrea Doria, 25",
    "sg:city":"Barcelona",
    "sg:orig_category":"Asociaciones, Organismos Culturales Y Socioeducativos",
    "sg:phone":"+34 933 19 42 96",
    "sg:postcode":"08003",
    "sg:province":"Barcelona",
    "wof:name":"Club Ajedrez Barceloneta",
    "wof:placetype":"venue"
},
  "geometry": {"coordinates":[2.190071106,41.3802337646],"type":"Point"}
}