{
  "type": "Feature",
  "properties": {
    "addr:full":"Avda Jerez, 24 Sevilla Sevilla 41012",
    "addr:housenumber":"24",
    "addr:postcode":"41012",
    "addr:street":"Avda Jerez",
    "iso:country":"ES",
    "sg:address":"Avda Jerez, 24",
    "sg:city":"Sevilla",
    "sg:orig_category":"Ense\u00d1anza Secundaria: Colegios Y Escuelas Privadas",
    "sg:phone":"+34 954 69 12 97",
    "sg:postcode":"41012",
    "sg:province":"Sevilla",
    "wof:name":"Junta De Andalucia",
    "wof:placetype":"venue"
},
  "geometry": {"coordinates":[-5.9792289734,37.3547592163],"type":"Point"}
}