{
  "type": "Feature",
  "properties": {
    "addr:full":"Carrer de Marti Julia, 37 Palleja Barcelona 08780",
    "addr:housenumber":"37",
    "addr:postcode":"08780",
    "addr:street":"Carrer De Marti Julia",
    "iso:country":"ES",
    "sg:address":"Carrer de Marti Julia, 37",
    "sg:city":"Palleja",
    "sg:orig_category":"Alimentaci\u00d3n General (al Por Menor)",
    "sg:phone":"+34 936 63 00 62",
    "sg:postcode":"08780",
    "sg:province":"Barcelona",
    "wof:name":"Duran Llanas Juan",
    "wof:placetype":"venue"
},
  "geometry": {"coordinates":[1.9961290359,41.4226875305],"type":"Point"}
}