{
  "type": "Feature",
  "properties": {
    "iso:country":"ES",
    "sg:address":"Calle de Venezuela, 36",
    "sg:city":"Palmas De Gran Canaria",
    "sg:orig_category":"Peluquer\u00cdas, Peluquer\u00cda Mixta",
    "sg:phone":"+34 928 22 14 34",
    "sg:postcode":"35010",
    "sg:province":"Las Palmas",
    "wof:name":"Pe\u00f1a Herrera Sonia",
    "wof:placetype":"venue"
},
  "geometry": {"coordinates":[-15.4385347366,28.1348781586],"type":"Point"}
}