{
  "type": "Feature",
  "properties": {
    "addr:full":"Calle de Federico Garcia Lorca, 2 Arme\u00d1ime Santa Cruz De Tenerife 38678",
    "addr:housenumber":"2",
    "addr:postcode":"38678",
    "addr:street":"Calle De Federico Garcia Lorca",
    "iso:country":"ES",
    "sg:address":"Calle de Federico Garcia Lorca, 2",
    "sg:city":"Arme\u00d1ime",
    "sg:orig_category":"Alimentaci\u00d3n General (al Por Menor)",
    "sg:phone":"+34 922 74 01 80",
    "sg:postcode":"38678",
    "sg:province":"Santa Cruz De Tenerife",
    "wof:name":"Delgado Dorta Maria Luisa",
    "wof:placetype":"venue"
},
  "geometry": {"coordinates":[-16.7548103333,28.1293964386],"type":"Point"}
}