{
  "type": "Feature",
  "properties": {
    "iso:country":"ES",
    "sg:address":"Calle de Doctor J.j. Domine, 18",
    "sg:city":"Valencia",
    "sg:orig_category":"Organizaciones Profesionales",
    "sg:phone":"+34 963 67 77 83",
    "sg:postcode":"46011",
    "sg:province":"Valencia",
    "wof:name":"Consignaciones Maritimas Internacionales S.a.",
    "wof:placetype":"venue"
},
  "geometry": {"coordinates":[-0.3306570053,39.4625740051],"type":"Point"}
}