{
  "type": "Feature",
  "properties": {
    "iso:country":"ES",
    "sg:address":"Rua Orense, 121",
    "sg:city":"Monforte De Lemos",
    "sg:orig_category":"Suministros Para Carrocer\u00cdas",
    "sg:phone":"+34 982 41 13 04",
    "sg:postcode":"27400",
    "sg:province":"Lugo",
    "wof:name":"Rivero Valcarcel Felix",
    "wof:placetype":"venue"
},
  "geometry": {"coordinates":[-7.5172939301,42.5221710205],"type":"Point"}
}