{
  "type": "Feature",
  "properties": {
    "iso:country":"ES",
    "sg:address":"Calle de Alcalde Jose Luis Estrada, S/n",
    "sg:city":"Malaga",
    "sg:orig_category":"Chapister\u00cda",
    "sg:phone":"+34 952 35 64 08",
    "sg:postcode":"29011",
    "sg:province":"M\u00e1laga",
    "wof:name":"Talleres Infanco S.l",
    "wof:placetype":"venue"
},
  "geometry": {"coordinates":[-4.4436798096,36.729259491],"type":"Point"}
}