{
  "type": "Feature",
  "properties": {
    "addr:full":"Cami Sant Crist (del), 11 Mataro Barcelona 08302",
    "addr:postcode":"08302",
    "addr:street":"Sant;Del 11 Mataro Barcelona",
    "iso:country":"ES",
    "sg:address":"Cami Sant Crist (del), 11",
    "sg:city":"Mataro",
    "sg:orig_category":"Mec\u00c1nico Del Autom\u00d3vil",
    "sg:phone":"+34 937 98 46 91",
    "sg:postcode":"08302",
    "sg:province":"Barcelona",
    "wof:name":"Automobils Alejandro S.c.p.",
    "wof:placetype":"venue"
},
  "geometry": {"coordinates":[2.4274590015,41.5319252014],"type":"Point"}
}