{
  "type": "Feature",
  "properties": {
    "addr:full":"Pase Chopera (de La), 121 Alcobendas Madrid 28100",
    "addr:housenumber":"121",
    "addr:postcode":"28100",
    "addr:street":"Alcobendas",
    "iso:country":"ES",
    "sg:address":"Pase Chopera (de La), 121",
    "sg:city":"Alcobendas",
    "sg:orig_category":"Cl\u00cdnicas M\u00c9dicas",
    "sg:phone":"+34 916 62 39 24",
    "sg:postcode":"28100",
    "sg:province":"Madrid",
    "wof:name":"Centro Clinico La Chopera S.l.",
    "wof:placetype":"venue"
},
  "geometry": {"coordinates":[-3.6524751186,40.5447654724],"type":"Point"}
}