{
  "type": "Feature",
  "properties": {
    "iso:country":"ES",
    "sg:address":"Avda Zumalakarregi De, 11",
    "sg:city":"Donostia-san Sebastian",
    "sg:orig_category":"Alquiler De Casas Y Habitaciones Amuebladas",
    "sg:phone":"+34 943 21 08 00",
    "sg:postcode":"20008",
    "sg:province":"Guip\u00f9zcoa",
    "wof:name":"Religiosas Esclavas Del Sagrado Corazon",
    "wof:placetype":"venue"
},
  "geometry": {"coordinates":[-2.002696991,43.3143539429],"type":"Point"}
}