{
  "type": "Feature",
  "properties": {
    "iso:country":"ES",
    "sg:address":"Pla\u00c7 Major, 22",
    "sg:city":"Darnius",
    "sg:orig_category":"Asociaciones, Organismos Culturales Y Socioeducativos",
    "sg:phone":"+34 972 53 50 19",
    "sg:postcode":"17722",
    "sg:province":"Girona",
    "wof:name":"Baserba Gibrat Josep",
    "wof:placetype":"venue"
},
  "geometry": {"coordinates":[2.8321630955,42.3678207397],"type":"Point"}
}