{
  "type": "Feature",
  "properties": {
    "addr:full":"Carrer de Anoia, S/n Poligon Industrial Pla De La Bruguera Barcelona 08211",
    "addr:housenumber":"s / n",
    "addr:postcode":"08211",
    "addr:street":"Carrer De Anoia;Industrial;De",
    "iso:country":"ES",
    "sg:address":"Carrer de Anoia, S/n",
    "sg:city":"Poligon Industrial Pla De La Bruguera",
    "sg:orig_category":"Mec\u00c1nico Del Autom\u00d3vil",
    "sg:phone":"+34 937 14 86 68",
    "sg:postcode":"08211",
    "sg:province":"Barcelona",
    "wof:name":"Bono Flores Juan Bautista",
    "wof:placetype":"venue"
},
  "geometry": {"coordinates":[2.0857300758,41.6151885986],"type":"Point"}
}