{
  "type": "Feature",
  "properties": {
    "addr:full":"Calle de Rambla De Capuchinos, S/n Motril Granada 18600",
    "addr:housenumber":"s",
    "addr:postcode":"18600",
    "addr:street":"Calle De Rambla De Capuchinos;/ N;Granada",
    "iso:country":"ES",
    "sg:address":"Calle de Rambla De Capuchinos, S/n",
    "sg:city":"Motril",
    "sg:orig_category":"Sindicatos De Trabajadores",
    "sg:phone":"+34 958 60 01 42",
    "sg:postcode":"18600",
    "sg:province":"Granada",
    "wof:name":"Comisiones Obreras De Andalucia",
    "wof:placetype":"venue"
},
  "geometry": {"coordinates":[-3.5183041096,36.7483558655],"type":"Point"}
}