{
  "type": "Feature",
  "properties": {
    "iso:country":"ES",
    "sg:address":"Plaz Pintor Amalio Garcia Del Moral, 10",
    "sg:city":"Sevilla",
    "sg:orig_category":"Agentes, Concesionarios Y Sucursales De Veh\u00cdculos",
    "sg:phone":"+34 954 63 33 65",
    "sg:postcode":"41005",
    "sg:province":"Sevilla",
    "sg:website":"www.microauto.com",
    "wof:name":"Microauto Vsp S.a.",
    "wof:placetype":"venue"
},
  "geometry": {"coordinates":[-5.9728608131,37.3773117065],"type":"Point"}
}