{
  "type": "Feature",
  "properties": {
    "iso:country":"ES",
    "sg:address":"Calle de San Antolin, 10",
    "sg:city":"Madrid",
    "sg:orig_category":"\u00d3ptica: Instrumentos (fabricaci\u00d3n)",
    "sg:phone":"+34 914 65 27 31",
    "sg:postcode":"28025",
    "sg:province":"Madrid",
    "wof:name":"Calvo Ayuso Ernesto",
    "wof:placetype":"venue"
},
  "geometry": {"coordinates":[-3.7486150265,40.3795661926],"type":"Point"}
}