{
  "type": "Feature",
  "properties": {
    "addr:full":"Plaz Republica Dominicana, S/n Madrid Madrid 28016",
    "addr:housenumber":"s / n",
    "addr:postcode":"28016",
    "addr:street":"Dominicana",
    "iso:country":"ES",
    "sg:address":"Plaz Republica Dominicana, S/n",
    "sg:city":"Madrid",
    "sg:orig_category":"Aparcamientos (infraestructuras, Accesorios)",
    "sg:phone":"+34 913 44 02 45",
    "sg:postcode":"28016",
    "sg:province":"Madrid",
    "wof:name":"Vinci Park Espa\u00f1a S.a.",
    "wof:placetype":"venue"
},
  "geometry": {"coordinates":[-3.6766750813,40.4583969116],"type":"Point"}
}