{
  "type": "Feature",
  "properties": {
    "addr:full":"Calle de Francisco Serrano, 2 Ingenio Las Palmas 35250",
    "addr:housenumber":"2",
    "addr:postcode":"35250",
    "addr:street":"Calle De Francisco Serrano",
    "iso:country":"ES",
    "sg:address":"Calle de Francisco Serrano, 2",
    "sg:city":"Ingenio",
    "sg:orig_category":"Equipo De Refrigeraci\u00d3n Industrial",
    "sg:phone":"+34 928 78 33 29",
    "sg:postcode":"35250",
    "sg:province":"Las Palmas",
    "wof:name":"Santana Valido Carmelo",
    "wof:placetype":"venue"
},
  "geometry": {"coordinates":[-15.445980072,27.9208831787],"type":"Point"}
}