{
  "type": "Feature",
  "properties": {
    "addr:full":"R. Vinyes, S/n Palau Anglesola Lleida 25243",
    "addr:housenumber":"s / n",
    "addr:postcode":"25243",
    "addr:street":"Vinyes",
    "iso:country":"ES",
    "sg:address":"R. Vinyes, S/n",
    "sg:city":"Palau Anglesola",
    "sg:orig_category":"Producci\u00d3n De Abonos Y De Fertilizantes",
    "sg:phone":"+34 973 60 13 96",
    "sg:postcode":"25243",
    "sg:province":"Lleida",
    "wof:name":"Transfruit Costa S.l.",
    "wof:placetype":"venue"
},
  "geometry": {"coordinates":[0.8789200187,41.6502456665],"type":"Point"}
}