{
  "type": "Feature",
  "properties": {
    "addr:full":"Carr Nou D'octubre, 22 Canals Valencia 46650",
    "addr:housenumber":"22",
    "addr:postcode":"46650",
    "addr:street":"Carr Nou D'Octubre",
    "iso:country":"ES",
    "sg:address":"Carr Nou D'octubre, 22",
    "sg:city":"Canals",
    "sg:orig_category":"Promotores Constructores",
    "sg:phone":"+34 962 24 38 13",
    "sg:postcode":"46650",
    "sg:province":"Valencia",
    "wof:name":"Construcciones Jose Ramon Jornet S.l.",
    "wof:placetype":"venue"
},
  "geometry": {"coordinates":[-0.5856389999,38.9584617615],"type":"Point"}
}