{
  "type": "Feature",
  "properties": {
    "iso:country":"ES",
    "sg:address":"Calle de Paz (la), 36",
    "sg:city":"Funes",
    "sg:orig_category":"Frutas Y Legumbres Frescas (al Por Mayor)",
    "sg:phone":"+34 948 75 43 86",
    "sg:postcode":"31360",
    "sg:province":"Navarra",
    "wof:name":"Alfaro Martinez Juan Cruz",
    "wof:placetype":"venue"
},
  "geometry": {"coordinates":[-1.7987138033,42.3131942749],"type":"Point"}
}