{
  "type": "Feature",
  "properties": {
    "iso:country":"ES",
    "sg:address":"Calle de Ebro, S/n",
    "sg:city":"Lebrija",
    "sg:orig_category":"Supermercados Y Hipermercados",
    "sg:phone":"+34 955 97 37 12",
    "sg:postcode":"41740",
    "sg:province":"Sevilla",
    "wof:name":"Romero Cardoso Maria Josefa",
    "wof:placetype":"venue"
},
  "geometry": {"coordinates":[-6.0854291916,36.9153518677],"type":"Point"}
}