{
  "type": "Feature",
  "properties": {
    "addr:full":"Calle de Calvo Sotelo, 13 Tui Pontevedra 36700",
    "addr:housenumber":"13",
    "addr:postcode":"36700",
    "addr:street":"Calle De Calvo Sotelo",
    "iso:country":"ES",
    "sg:address":"Calle de Calvo Sotelo, 13",
    "sg:city":"Tui",
    "sg:orig_category":"Peluqueros: De Se\u00d1oras",
    "sg:phone":"+34 986 60 13 55",
    "sg:postcode":"36700",
    "sg:province":"Pontevedra",
    "wof:name":"Carm-ros-mel-peluqueria Y Cosmetologia S.l.",
    "wof:placetype":"venue"
},
  "geometry": {"coordinates":[-8.6448831558,42.0473251343],"type":"Point"}
}