{
  "type": "Feature",
  "properties": {
    "addr:full":"Avda Aragon, 22 Getafe Madrid 28903",
    "addr:housenumber":"22",
    "addr:postcode":"28903",
    "addr:street":"Avda Aragon",
    "iso:country":"ES",
    "sg:address":"Avda Aragon, 22",
    "sg:city":"Getafe",
    "sg:orig_category":"Muebles, Minoristas",
    "sg:phone":"+34 916 96 69 88",
    "sg:postcode":"28903",
    "sg:province":"Madrid",
    "wof:name":"Muebles Medina Y Gonzalez S.l.",
    "wof:placetype":"venue"
},
  "geometry": {"coordinates":[-3.716739893,40.3119812012],"type":"Point"}
}