{
  "type": "Feature",
  "properties": {
    "addr:full":"Calle de Cerro Mazacotero, 17 Torrijos Toledo 45500",
    "addr:housenumber":"17",
    "addr:postcode":"45500",
    "addr:street":"Calle De Cerro Mazacotero",
    "iso:country":"ES",
    "sg:address":"Calle de Cerro Mazacotero, 17",
    "sg:city":"Torrijos",
    "sg:orig_category":"Contenedores (mercanc\u00cdas)",
    "sg:phone":"+34 925 76 05 11",
    "sg:postcode":"45500",
    "sg:province":"Toledo",
    "wof:name":"Transportes Rodriguez Agudo S.l.",
    "wof:placetype":"venue"
},
  "geometry": {"coordinates":[-4.284787178,39.9844474792],"type":"Point"}
}