{
  "type": "Feature",
  "properties": {
    "addr:full":"Cra. Seu D'urgell, 48 Oliana Lleida 25790",
    "addr:housenumber":"48",
    "addr:postcode":"25790",
    "addr:street":"D'Urgell",
    "iso:country":"ES",
    "sg:address":"Cra. Seu D'urgell, 48",
    "sg:city":"Oliana",
    "sg:orig_category":"Cr\u00cda De Animales",
    "sg:phone":"+34 973 47 00 12",
    "sg:postcode":"25790",
    "sg:province":"Lleida",
    "wof:name":"Ramaderia Roque S.l.",
    "wof:placetype":"venue"
},
  "geometry": {"coordinates":[1.3131630421,42.068271637],"type":"Point"}
}