{
  "type": "Feature",
  "properties": {
    "iso:country":"ES",
    "sg:address":"Calle de Laguna Del Marquesado, 17",
    "sg:city":"Madrid",
    "sg:orig_category":"Andamiajes Y Escaleras De Mano (fabricaci\u00d3n, Al Por Mayor)",
    "sg:phone":"+34 916 73 38 82",
    "sg:postcode":"28021",
    "sg:province":"Madrid",
    "wof:name":"Layher S.a.",
    "wof:placetype":"venue"
},
  "geometry": {"coordinates":[-3.7049241066,40.3335838318],"type":"Point"}
}