{
  "type": "Feature",
  "properties": {
    "addr:full":"Carrer de Mossen A. Rodamilans, 70 Terrassa Barcelona 08222",
    "addr:housenumber":"70",
    "addr:postcode":"08222",
    "addr:street":"Carrer De Mossen A. Rodamilans",
    "iso:country":"ES",
    "sg:address":"Carrer de Mossen A. Rodamilans, 70",
    "sg:city":"Terrassa",
    "sg:orig_category":"Electricidad: Instaladores",
    "sg:phone":"+34 937 31 21 83",
    "sg:postcode":"08222",
    "sg:province":"Barcelona",
    "wof:name":"Valcas Instalacions S.l",
    "wof:placetype":"venue"
},
  "geometry": {"coordinates":[2.0300149918,41.5605010986],"type":"Point"}
}