{
  "type": "Feature",
  "properties": {
    "iso:country":"ES",
    "sg:address":"Calle de Secretario Basilio Sala (del), 3",
    "sg:city":"Sant Joan D'alacant",
    "sg:orig_category":"M\u00c9dicos: Pediatr\u00cda. Enfermedades De Los Ni\u00d1os",
    "sg:phone":"+34 965 65 43 27",
    "sg:postcode":"03550",
    "sg:province":"Alicante",
    "wof:name":"Sevilla Salvador Francisco",
    "wof:placetype":"venue"
},
  "geometry": {"coordinates":[-0.4919199944,38.3387565613],"type":"Point"}
}