{
  "type": "Feature",
  "properties": {
    "iso:country":"ES",
    "sg:address":"Ptda Cotes Baixes, 13",
    "sg:city":"Alcoi",
    "sg:orig_category":"Maquinaria Para Industrias Diversas",
    "sg:phone":"+34 965 33 07 44",
    "sg:postcode":"03804",
    "sg:province":"Alicante",
    "wof:name":"Espi Gonzalez Bernardo Jose",
    "wof:placetype":"venue"
},
  "geometry": {"coordinates":[-0.4650489986,38.712688446],"type":"Point"}
}