{
  "type": "Feature",
  "properties": {
    "iso:country":"ES",
    "sg:address":"Pase Tomas Morales, 17",
    "sg:city":"Palmas De Gran Canaria",
    "sg:orig_category":"\u00d3ptica: Instrumentos (fabricaci\u00d3n)",
    "sg:phone":"+34 928 36 35 37",
    "sg:postcode":"35003",
    "sg:province":"Las Palmas",
    "wof:name":"Artiles Artiles Jeronimo",
    "wof:placetype":"venue"
},
  "geometry": {"coordinates":[-15.4199867249,28.1103744507],"type":"Point"}
}