{
  "type": "Feature",
  "properties": {
    "iso:country":"ES",
    "sg:address":"Calle de Lagasca, 57",
    "sg:city":"San Pedro Alcantara",
    "sg:orig_category":"Bisuter\u00cda, Joyer\u00cda, Relojer\u00cda (al Por Menor)",
    "sg:phone":"+34 952 78 84 84",
    "sg:postcode":"29670",
    "sg:province":"M\u00e1laga",
    "wof:name":"Martinez Gonzalez Jose Alberto",
    "wof:placetype":"venue"
},
  "geometry": {"coordinates":[-4.9894537926,36.4840698242],"type":"Point"}
}