{
  "type": "Feature",
  "properties": {
    "iso:country":"ES",
    "sg:address":"Carr Alcodar, S/n",
    "sg:city":"Xeresa",
    "sg:orig_category":"Arboricultura Y Producci\u00d3n De Frutas",
    "sg:phone":"+34 962 89 52 38",
    "sg:postcode":"46790",
    "sg:province":"Valencia",
    "wof:name":"Fruxeresa S.l.",
    "wof:placetype":"venue"
},
  "geometry": {"coordinates":[-0.2177589983,39.0110244751],"type":"Point"}
}