{
  "type": "Feature",
  "properties": {
    "iso:country":"ES",
    "sg:address":"Calle de General Moscardo, 6",
    "sg:city":"Madrid",
    "sg:orig_category":"Agencias Y Agentes Comerciales, Representantes",
    "sg:phone":"+34 915 54 14 82",
    "sg:postcode":"28020",
    "sg:province":"Madrid",
    "wof:name":"Rubio Vazquez Maria Jose",
    "wof:placetype":"venue"
},
  "geometry": {"coordinates":[-3.6969060898,40.4470901489],"type":"Point"}
}