{
  "type": "Feature",
  "properties": {
    "addr:full":"Av Llibertat, 56 Sant Joan De Palamos Girona 17230",
    "addr:housenumber":"56",
    "addr:postcode":"17230",
    "addr:street":"Av Llibertat",
    "iso:country":"ES",
    "sg:address":"Av Llibertat, 56",
    "sg:city":"Sant Joan De Palamos",
    "sg:orig_category":"Aparcamientos (infraestructuras, Accesorios)",
    "sg:phone":"+34 972 31 66 31",
    "sg:postcode":"17230",
    "sg:province":"Girona",
    "wof:name":"Pont Coll Ramon",
    "wof:placetype":"venue"
},
  "geometry": {"coordinates":[3.1290481091,41.8557891846],"type":"Point"}
}