{
  "type": "Feature",
  "properties": {
    "addr:full":"Trva Socorro (del), 15 San Sebastian De Los Reyes Madrid 28700",
    "addr:housenumber":"15",
    "addr:postcode":"28700",
    "addr:street":"Trva Socorro Del",
    "iso:country":"ES",
    "sg:address":"Trva Socorro (del), 15",
    "sg:city":"San Sebastian De Los Reyes",
    "sg:orig_category":"Estancos",
    "sg:phone":"+34 916 53 74 44",
    "sg:postcode":"28700",
    "sg:province":"Madrid",
    "wof:name":"Ramirez Cordones Francisco",
    "wof:placetype":"venue"
},
  "geometry": {"coordinates":[-3.6265571117,40.5498657227],"type":"Point"}
}