{
  "type": "Feature",
  "properties": {
    "addr:full":"Calle de Olleta, 1 Tafalla Navarra 31300",
    "addr:housenumber":"1",
    "addr:postcode":"31300",
    "addr:street":"Calle De Olleta",
    "iso:country":"ES",
    "sg:address":"Calle de Olleta, 1",
    "sg:city":"Tafalla",
    "sg:orig_category":"Trajes Y Adornos De Boda (confecci\u00d3n, Al Por Menor)",
    "sg:phone":"+34 948 70 04 74",
    "sg:postcode":"31300",
    "sg:province":"Navarra",
    "wof:name":"Riolaya S.l.",
    "wof:placetype":"venue"
},
  "geometry": {"coordinates":[-1.6716250181,42.5298347473],"type":"Point"}
}