{
  "type": "Feature",
  "properties": {
    "iso:country":"ES",
    "sg:address":"Calle de Vid (la), 8",
    "sg:city":"Chiclana De La Frontera",
    "sg:orig_category":"Institutos De Belleza",
    "sg:phone":"+34 956 53 64 25",
    "sg:postcode":"11130",
    "sg:province":"C\u00e1diz",
    "wof:name":"Hernandez Salas Africa",
    "wof:placetype":"venue"
},
  "geometry": {"coordinates":[-6.1640839577,36.4197006226],"type":"Point"}
}