{
  "type": "Feature",
  "properties": {
    "addr:full":"Carrer de Santa Esperan\u00c7a, 6 Granollers Barcelona 08401",
    "addr:housenumber":"6",
    "addr:postcode":"08401",
    "addr:street":"Carrer De Santa Esperanc\u0327A",
    "iso:country":"ES",
    "sg:address":"Carrer de Santa Esperan\u00c7a, 6",
    "sg:city":"Granollers",
    "sg:orig_category":"Cl\u00cdnicas Dentales",
    "sg:phone":"+34 938 70 26 69",
    "sg:postcode":"08401",
    "sg:province":"Barcelona",
    "wof:name":"Bossy Azpelicueta Alejandro",
    "wof:placetype":"venue"
},
  "geometry": {"coordinates":[2.2879009247,41.6076278687],"type":"Point"}
}