{
  "type": "Feature",
  "properties": {
    "iso:country":"ES",
    "sg:address":"Pl Pastoreta, 6",
    "sg:city":"Reus",
    "sg:orig_category":"Asesor\u00cda Sobre Comunicaci\u00d3n De Empresas",
    "sg:phone":"+34 977 33 12 15",
    "sg:postcode":"43205",
    "sg:province":"Tarragona",
    "wof:name":"Duran Talamino Florentino",
    "wof:placetype":"venue"
},
  "geometry": {"coordinates":[1.1051260233,41.1496734619],"type":"Point"}
}