{
  "type": "Feature",
  "properties": {
    "iso:country":"ES",
    "sg:address":"Av Jaume I, 300",
    "sg:city":"Terrassa",
    "sg:orig_category":"Venta, Montaje De Neum\u00c1ticos",
    "sg:phone":"+34 937 35 47 92",
    "sg:postcode":"08226",
    "sg:province":"Barcelona",
    "sg:website":"www.autojaume.com",
    "wof:name":"Clua Gonzalez Xavier",
    "wof:placetype":"venue"
},
  "geometry": {"coordinates":[2.0198359489,41.5734176636],"type":"Point"}
}