{
  "type": "Feature",
  "properties": {
    "iso:country":"ES",
    "sg:address":"Castellon, Km. 0028,0",
    "sg:city":"Fuentes Ebro",
    "sg:orig_category":"Frutas Y Legumbres Secas (al Por Mayor)",
    "sg:phone":"+34 976 16 01 88",
    "sg:postcode":"50740",
    "sg:province":"Zaragoza",
    "wof:name":"Agroindustria Aragonesa S. A.",
    "wof:placetype":"venue"
},
  "geometry": {"coordinates":[-0.6805104017,41.5383415222],"type":"Point"}
}