{
  "type": "Feature",
  "properties": {
    "iso:country":"ES",
    "sg:address":"Carrer de Manuel Marine, 8",
    "sg:city":"Cornella Llobregat",
    "sg:orig_category":"Comidas Por Encargo Para Colectivos",
    "sg:phone":"+34 933 76 02 93",
    "sg:postcode":"08940",
    "sg:province":"Barcelona",
    "wof:name":"Garcia Zurita Jose Luis",
    "wof:placetype":"venue"
},
  "geometry": {"coordinates":[2.0781109333,41.3657073975],"type":"Point"}
}