{
  "type": "Feature",
  "properties": {
    "addr:full":"Pg Doctor Moragas, 274 Barbera Valles Barcelona 08210",
    "addr:housenumber":"274",
    "addr:postcode":"08210",
    "addr:street":"Pg Doctor Moragas",
    "iso:country":"ES",
    "sg:address":"Pg Doctor Moragas, 274",
    "sg:city":"Barbera Valles",
    "sg:orig_category":"Empresarios",
    "sg:phone":"+34 937 18 90 03",
    "sg:postcode":"08210",
    "sg:province":"Barcelona",
    "wof:name":"Bany-gres Barbera S.l.",
    "wof:placetype":"venue"
},
  "geometry": {"coordinates":[2.1228199005,41.5181999207],"type":"Point"}
}