{
  "type": "Feature",
  "properties": {
    "iso:country":"ES",
    "sg:address":"Calle de San Vicente, 91",
    "sg:city":"Alfara Patriarca",
    "sg:orig_category":"Fabricaci\u00d3n, Instalaci\u00d3n De Armarios",
    "sg:phone":"+34 961 39 36 09",
    "sg:postcode":"46115",
    "sg:province":"Valencia",
    "wof:name":"Lopez Parra Fidel",
    "wof:placetype":"venue"
},
  "geometry": {"coordinates":[-0.3825039864,39.5448112488],"type":"Point"}
}