{
  "type": "Feature",
  "properties": {
    "addr:full":"Carr Major, 57 Riudellots Selva Girona 17457",
    "addr:housenumber":"57",
    "addr:postcode":"17457",
    "addr:street":"Carr Major",
    "iso:country":"ES",
    "sg:address":"Carr Major, 57",
    "sg:city":"Riudellots Selva",
    "sg:orig_category":"Charcuter\u00cdas (al Por Mayor)",
    "sg:phone":"+34 972 47 81 76",
    "sg:postcode":"17457",
    "sg:province":"Girona",
    "sg:website":"www.jaumeabras.com",
    "wof:name":"Frigorificos Costa Brava S.a.",
    "wof:placetype":"venue"
},
  "geometry": {"coordinates":[2.8304951191,41.8967056274],"type":"Point"}
}