{
  "type": "Feature",
  "properties": {
    "addr:full":"Calle de Elcano, 5 Bilbao Vizcaya 48011",
    "addr:housenumber":"5",
    "addr:postcode":"48011",
    "addr:street":"Calle De Elcano",
    "iso:country":"ES",
    "sg:address":"Calle de Elcano, 5",
    "sg:city":"Bilbao",
    "sg:orig_category":"Abogados",
    "sg:phone":"+34 944 23 12 66",
    "sg:postcode":"48011",
    "sg:province":"Vizcaya",
    "wof:name":"Carnicero Santiago Pedro",
    "wof:placetype":"venue"
},
  "geometry": {"coordinates":[-2.9354169369,43.2638969421],"type":"Point"}
}