{
  "type": "Feature",
  "properties": {
    "addr:full":"Aveni Tierno Galvan, 1 Puntal Murcia 30100",
    "addr:housenumber":"1",
    "addr:postcode":"30100",
    "iso:country":"ES",
    "sg:address":"Aveni Tierno Galvan, 1",
    "sg:city":"Puntal",
    "sg:orig_category":"Material Y Suministros Para Pesca Y Piscicultura",
    "sg:phone":"+34 968 89 90 00",
    "sg:postcode":"30100",
    "sg:province":"Murcia",
    "wof:name":"Valera Ortu\u00d1o Jose Antonio",
    "wof:placetype":"venue"
},
  "geometry": {"coordinates":[-1.153594017,38.0103034973],"type":"Point"}
}