{
  "type": "Feature",
  "properties": {
    "iso:country":"ES",
    "sg:address":"Calle de Santiago Apostol, 1",
    "sg:city":"Burgos",
    "sg:orig_category":"Asesor\u00cda Sobre Comunicaci\u00d3n De Empresas",
    "sg:phone":"+34 947 22 26 44",
    "sg:postcode":"09007",
    "sg:province":"Burgos",
    "wof:name":"Perez De Pedro Carlos",
    "wof:placetype":"venue"
},
  "geometry": {"coordinates":[-3.6751790047,42.3497695923],"type":"Point"}
}