{
  "type": "Feature",
  "properties": {
    "addr:full":"Pol Ind Marismas, 45 Lebrija Sevilla 41740",
    "addr:housenumber":"45",
    "addr:postcode":"41740",
    "iso:country":"ES",
    "sg:address":"Pol Ind Marismas, 45",
    "sg:city":"Lebrija",
    "sg:orig_category":"Electricidad Veh\u00cdculo",
    "sg:phone":"+34 955 97 16 32",
    "sg:postcode":"41740",
    "sg:province":"Sevilla",
    "wof:name":"Electrofrio Lebrija S.l.",
    "wof:placetype":"venue"
},
  "geometry": {"coordinates":[-6.0658698082,36.9205932617],"type":"Point"}
}