{
  "type": "Feature",
  "properties": {
    "addr:full":"Pase Guerra (de), 6 San Cristobal Murcia 30800",
    "addr:postcode":"30800",
    "iso:country":"ES",
    "sg:address":"Pase Guerra (de), 6",
    "sg:city":"San Cristobal",
    "sg:orig_category":"Animales (al Por Menor)",
    "sg:phone":"+34 968 47 74 82",
    "sg:postcode":"30800",
    "sg:province":"Murcia",
    "wof:name":"Linares Vidal Andres",
    "wof:placetype":"venue"
},
  "geometry": {"coordinates":[-1.6905640364,37.680557251],"type":"Point"}
}