{
  "type": "Feature",
  "properties": {
    "addr:full":"Rbla Prim, 155 Barcelona Barcelona 08020",
    "addr:housenumber":"155",
    "addr:postcode":"08020",
    "addr:street":"Rbla Prim",
    "iso:country":"ES",
    "sg:address":"Rbla Prim, 155",
    "sg:city":"Barcelona",
    "sg:orig_category":"Electricidad: Instaladores",
    "sg:phone":"+34 932 78 00 49",
    "sg:postcode":"08020",
    "sg:province":"Barcelona",
    "wof:name":"Instalaciones Dalixa S.l.",
    "wof:placetype":"venue"
},
  "geometry": {"coordinates":[2.2053077221,41.4216194153],"type":"Point"}
}