{
  "type": "Feature",
  "properties": {
    "addr:full":"Calle de Oso, 7 Jerez De La Frontera C\u00e1diz 11405",
    "addr:housenumber":"7",
    "addr:postcode":"11405",
    "addr:street":"Calle De Oso",
    "iso:country":"ES",
    "sg:address":"Calle de Oso, 7",
    "sg:city":"Jerez De La Frontera",
    "sg:orig_category":"Centros Empresariales",
    "sg:phone":"+34 956 30 74 50",
    "sg:postcode":"11405",
    "sg:province":"C\u00e1diz",
    "wof:name":"Easa Naval S.l.",
    "wof:placetype":"venue"
},
  "geometry": {"coordinates":[-6.1261458397,36.6918029785],"type":"Point"}
}