{
  "type": "Feature",
  "properties": {
    "addr:full":"Carrer de Portalet, 14 Granollers Barcelona 08401",
    "addr:housenumber":"14",
    "addr:postcode":"08401",
    "addr:street":"Carrer De Portalet",
    "iso:country":"ES",
    "sg:address":"Carrer de Portalet, 14",
    "sg:city":"Granollers",
    "sg:orig_category":"Herboristas (al Por Menor)",
    "sg:phone":"+34 938 70 21 44",
    "sg:postcode":"08401",
    "sg:province":"Barcelona",
    "wof:name":"Sanchez Bravo Ana",
    "wof:placetype":"venue"
},
  "geometry": {"coordinates":[2.2874500751,41.6074752808],"type":"Point"}
}