{
  "type": "Feature",
  "properties": {
    "iso:country":"ES",
    "sg:address":"Calle de Emilio Calzadilla, 6",
    "sg:city":"Santa Cruz De Tenerife",
    "sg:orig_category":"Masajes",
    "sg:phone":"+34 922 24 71 71",
    "sg:postcode":"38002",
    "sg:province":"Santa Cruz De Tenerife",
    "wof:name":"Atienza Cuellar Estrella",
    "wof:placetype":"venue"
},
  "geometry": {"coordinates":[-16.2483062744,28.4688148499],"type":"Point"}
}