{
  "type": "Feature",
  "properties": {
    "addr:full":"Calle de Benigno Vazquez, 21 Monterroso Lugo 27560",
    "addr:housenumber":"21",
    "addr:postcode":"27560",
    "addr:street":"Calle De Benigno Vazquez",
    "iso:country":"ES",
    "sg:address":"Calle de Benigno Vazquez, 21",
    "sg:city":"Monterroso",
    "sg:orig_category":"Ropa Para Se\u00d1oras (al Por Menor)",
    "sg:phone":"+34 982 37 76 53",
    "sg:postcode":"27560",
    "sg:province":"Lugo",
    "wof:name":"Ramos Ledo Segundo",
    "wof:placetype":"venue"
},
  "geometry": {"coordinates":[-7.8348851204,42.7941856384],"type":"Point"}
}