{
  "type": "Feature",
  "properties": {
    "iso:country":"ES",
    "sg:address":"Calle de Munich, S/n",
    "sg:city":"Alcorcon",
    "sg:orig_category":"Reposter\u00cdas",
    "sg:phone":"+34 916 10 23 69",
    "sg:postcode":"28923",
    "sg:province":"Madrid",
    "wof:name":"Donoso Anguita Maria Paz",
    "wof:placetype":"venue"
},
  "geometry": {"coordinates":[-3.8153231144,40.3446578979],"type":"Point"}
}