{
  "type": "Feature",
  "properties": {
    "addr:full":"Mercado Gorbea-zaldiaran, S/n Vitoria-gasteiz \u00c1lava 01008",
    "addr:housenumber":"s",
    "addr:postcode":"01008",
    "addr:street":"/ N",
    "iso:country":"ES",
    "sg:address":"Mercado Gorbea-zaldiaran, S/n",
    "sg:city":"Vitoria-gasteiz",
    "sg:orig_category":"Carnicer\u00cdas, Carnicer\u00cdas",
    "sg:phone":"+34 945 22 59 39",
    "sg:postcode":"01008",
    "sg:province":"\u00c1lava",
    "wof:name":"Vizcaino Fernandez Maria Teresa",
    "wof:placetype":"venue"
},
  "geometry": {"coordinates":[-2.6847200394,42.8482475281],"type":"Point"}
}