{
  "type": "Feature",
  "properties": {
    "iso:country":"ES",
    "sg:address":"Carrer de Gandia, 29",
    "sg:city":"Terrassa",
    "sg:orig_category":"Molduras, Junquillos, Listones Y Molduras Perforadas",
    "sg:phone":"+34 937 88 11 45",
    "sg:postcode":"08224",
    "sg:province":"Barcelona",
    "wof:name":"Ramirez Cascilla Luis Mariano",
    "wof:placetype":"venue"
},
  "geometry": {"coordinates":[1.9950649738,41.5628242493],"type":"Point"}
}