{
  "type": "Feature",
  "properties": {
    "addr:full":"Calle de Villatorres, 1 Jaen Ja\u00e9n 23009",
    "addr:housenumber":"1;jae\u0301n",
    "addr:postcode":"23009",
    "addr:street":"Calle De Villatorres",
    "iso:country":"ES",
    "sg:address":"Calle de Villatorres, 1",
    "sg:city":"Jaen",
    "sg:orig_category":"Cester\u00cda (fabricaci\u00d3n)",
    "sg:phone":"+34 953 28 16 22",
    "sg:postcode":"23009",
    "sg:province":"Ja\u00e9n",
    "wof:name":"Senda Artesana S.l.",
    "wof:placetype":"venue"
},
  "geometry": {"coordinates":[-3.7831740379,37.796081543],"type":"Point"}
}