{
  "type": "Feature",
  "properties": {
    "iso:country":"ES",
    "sg:address":"Calle de San Roque (de), 12",
    "sg:city":"Navalcarnero",
    "sg:orig_category":"Abogados",
    "sg:phone":"+34 918 11 45 06",
    "sg:postcode":"28600",
    "sg:province":"Madrid",
    "wof:name":"Fernandez Colomo Margarita",
    "wof:placetype":"venue"
},
  "geometry": {"coordinates":[-4.0136270523,40.2870635986],"type":"Point"}
}