{
  "type": "Feature",
  "properties": {
    "addr:full":"Fco. De Paula, Km. 0002,5 San Cristobal De La Laguna Santa Cruz De Tenerife 38205",
    "addr:postcode":"38205",
    "addr:street":"Fco.;Paula;0002,5",
    "iso:country":"ES",
    "sg:address":"Fco. De Paula, Km. 0002,5",
    "sg:city":"San Cristobal De La Laguna",
    "sg:orig_category":"Distribuci\u00d3n De Petr\u00d3leo Y Derivados",
    "sg:phone":"+34 922 26 34 21",
    "sg:postcode":"38205",
    "sg:province":"Santa Cruz De Tenerife",
    "wof:name":"Hermanos Sanchez Galdran S.l.",
    "wof:placetype":"venue"
},
  "geometry": {"coordinates":[-16.298746109,28.4750785828],"type":"Point"}
}