{
  "type": "Feature",
  "properties": {
    "addr:full":"Avda Nuestra Se\u00d1ora Del Pilar, 4 Binefar Huesca 22500",
    "addr:housenumber":"4",
    "addr:postcode":"22500",
    "addr:street":"Avda Nuestra Sen\u0303Ora Del Pilar",
    "iso:country":"ES",
    "sg:address":"Avda Nuestra Se\u00d1ora Del Pilar, 4",
    "sg:city":"Binefar",
    "sg:orig_category":"Deportes Y Programas De Aventura",
    "sg:phone":"+34 974 43 19 72",
    "sg:postcode":"22500",
    "sg:province":"Huesca",
    "wof:name":"Vertigo Deportes S.c.p",
    "wof:placetype":"venue"
},
  "geometry": {"coordinates":[0.2927339971,41.8517494202],"type":"Point"}
}