{
  "type": "Feature",
  "properties": {
    "iso:country":"ES",
    "sg:address":"Av. Progres (pol Ind Garrofers), 71",
    "sg:city":"Vilassar",
    "sg:orig_category":"Chapister\u00cda",
    "sg:phone":"+34 937 59 43 43",
    "sg:postcode":"08340",
    "sg:province":"Barcelona",
    "wof:name":"Industrial Joyvi S.l.",
    "wof:placetype":"venue"
},
  "geometry": {"coordinates":[2.3907299042,41.5019264221],"type":"Point"}
}