{
  "type": "Feature",
  "properties": {
    "addr:full":"Avda Reina Victoria, 27 Santander Cantabria 39004",
    "addr:housenumber":"27",
    "addr:postcode":"39004",
    "addr:street":"Avda Reina Victoria",
    "iso:country":"ES",
    "sg:address":"Avda Reina Victoria, 27",
    "sg:city":"Santander",
    "sg:orig_category":"Estancos",
    "sg:phone":"+34 942 21 84 54",
    "sg:postcode":"39004",
    "sg:province":"Cantabria",
    "wof:name":"Martin Conde Maria Del Carmen",
    "wof:placetype":"venue"
},
  "geometry": {"coordinates":[-3.7897539139,43.4635696411],"type":"Point"}
}