{
  "type": "Feature",
  "properties": {
    "iso:country":"ES",
    "sg:address":"Calle de Francisco Renau, 4",
    "sg:city":"Sant Joan Moro",
    "sg:orig_category":"Peluquer\u00cdas, Peluquer\u00cda Mixta",
    "sg:phone":"+34 964 32 81 23",
    "sg:postcode":"12130",
    "sg:province":"Castell\u00f3n",
    "wof:name":"Moratalla Benet Maria Jose",
    "wof:placetype":"venue"
},
  "geometry": {"coordinates":[-0.1355562061,40.060131073],"type":"Point"}
}