{
  "type": "Feature",
  "properties": {
    "iso:country":"ES",
    "sg:address":"Avda Doctor Rafael Gonzalez, 15",
    "sg:city":"Arrecife",
    "sg:orig_category":"Perfumer\u00cda, Art\u00cdculos De Ba\u00d1o (fabricaci\u00d3n, Al Por Mayor)",
    "sg:phone":"+34 928 81 76 04",
    "sg:postcode":"35500",
    "sg:province":"Las Palmas",
    "wof:name":"Perfumeria Evora",
    "wof:placetype":"venue"
},
  "geometry": {"coordinates":[-13.5533323288,28.9579296112],"type":"Point"}
}