{
  "type": "Feature",
  "properties": {
    "addr:full":"Ctra Berga, Km. 0002,0 S. Fruitos Bages Barcelona 08272",
    "addr:postcode":"08272",
    "addr:street":"Ctra Berga Km. 0002,0 S. Fruitos Bages Barcelona",
    "iso:country":"ES",
    "sg:address":"Ctra Berga, Km. 0002,0",
    "sg:city":"S. Fruitos Bages",
    "sg:orig_category":"Ropa Para Se\u00d1oras (al Por Menor)",
    "sg:phone":"+34 938 77 05 10",
    "sg:postcode":"08272",
    "sg:province":"Barcelona",
    "wof:name":"Guitart Castellvi Jose",
    "wof:placetype":"venue"
},
  "geometry": {"coordinates":[1.8779350519,41.7520599365],"type":"Point"}
}