{
  "type": "Feature",
  "properties": {
    "addr:full":"Calle de Servando Batanero, 50 Madrid Madrid 28017",
    "addr:housenumber":"50",
    "addr:postcode":"madrid;28017",
    "addr:street":"Calle De Servando Batanero",
    "iso:country":"ES",
    "sg:address":"Calle de Servando Batanero, 50",
    "sg:city":"Madrid",
    "sg:orig_category":"Fabricaci\u00d3n De Muebles Y De Accesorios De Cuartos De Ba\u00d1o",
    "sg:phone":"+34 914 07 07 04",
    "sg:postcode":"28017",
    "sg:province":"Madrid",
    "wof:name":"Representaciones Mena Revenga S.l.",
    "wof:placetype":"venue"
},
  "geometry": {"coordinates":[-3.6455700397,40.4297637939],"type":"Point"}
}