{
  "type": "Feature",
  "properties": {
    "iso:country":"ES",
    "sg:address":"Calle de Hormigoneras, 13",
    "sg:city":"Alcorcon",
    "sg:orig_category":"Maquinaria Para Industrias Diversas",
    "sg:phone":"+34 916 41 81 58",
    "sg:postcode":"28925",
    "sg:province":"Madrid",
    "sg:website":"www.matcosl.com",
    "wof:name":"Maquinaria Auxiliar Transporte Y Construccion",
    "wof:placetype":"venue"
},
  "geometry": {"coordinates":[-3.803579092,40.3442382812],"type":"Point"}
}