{
  "type": "Feature",
  "properties": {
    "addr:full":"Calle de Cortina Del Muelle, 11 Malaga M\u00e1laga 29015",
    "addr:housenumber":"11",
    "addr:postcode":"29015",
    "addr:street":"Calle De Cortina Del Muelle;Ma\u0301Laga",
    "iso:country":"ES",
    "sg:address":"Calle de Cortina Del Muelle, 11",
    "sg:city":"Malaga",
    "sg:orig_category":"Inmobiliaria (agencias)",
    "sg:phone":"+34 952 12 24 69",
    "sg:postcode":"29015",
    "sg:province":"M\u00e1laga",
    "wof:name":"Grupo De Inversiones Noga S.a.u.",
    "wof:placetype":"venue"
},
  "geometry": {"coordinates":[-4.4187660217,36.7193603516],"type":"Point"}
}