{
  "type": "Feature",
  "properties": {
    "iso:country":"ES",
    "sg:address":"Rua Real, 48",
    "sg:city":"Quiroga",
    "sg:orig_category":"Loter\u00cda Y T\u00d3mbola",
    "sg:phone":"+34 982 43 51 93",
    "sg:postcode":"27320",
    "sg:province":"Lugo",
    "wof:name":"Romero Vedo Maria Del Rosario",
    "wof:placetype":"venue"
},
  "geometry": {"coordinates":[-7.2724590302,42.4760818481],"type":"Point"}
}