{
  "type": "Feature",
  "properties": {
    "iso:country":"ES",
    "sg:address":"Carrer de Rafael Mas Ripoll, 26",
    "sg:city":"Llagostera",
    "sg:orig_category":"Revestimiento De Suelos Industriales",
    "sg:phone":"+34 972 80 55 47",
    "sg:postcode":"17240",
    "sg:province":"Girona",
    "wof:name":"Paviments Industrials Del Girones S.l.",
    "wof:placetype":"venue"
},
  "geometry": {"coordinates":[2.8970251083,41.8234024048],"type":"Point"}
}