{
  "type": "Feature",
  "properties": {
    "addr:full":"Avda Cuba, 32 Badolatosa Sevilla 41570",
    "addr:housenumber":"32",
    "addr:postcode":"41570",
    "addr:street":"Avda Cuba",
    "iso:country":"ES",
    "sg:address":"Avda Cuba, 32",
    "sg:city":"Badolatosa",
    "sg:orig_category":"Administraciones Regionales, Departamentales Y Locales",
    "sg:phone":"+34 954 01 70 64",
    "sg:postcode":"41570",
    "sg:province":"Sevilla",
    "wof:name":"Ayuntamiento De Badolatosa",
    "wof:placetype":"venue"
},
  "geometry": {"coordinates":[-4.6727929115,37.3087348938],"type":"Point"}
}