{
  "type": "Feature",
  "properties": {
    "iso:country":"ES",
    "sg:address":"Calle de Reina Victoria, 21",
    "sg:city":"Parla",
    "sg:orig_category":"Laboratorios Y Trabajos De Fotograf\u00cda, V\u00cddeo Y Cine",
    "sg:phone":"+34 916 99 90 09",
    "sg:postcode":"28980",
    "sg:province":"Madrid",
    "wof:name":"Ruiz Perez Jose Luis",
    "wof:placetype":"venue"
},
  "geometry": {"coordinates":[-3.7703061104,40.2339706421],"type":"Point"}
}