{
  "type": "Feature",
  "properties": {
    "iso:country":"ES",
    "sg:address":"Calle de Virgen Del Sagrario, 6",
    "sg:city":"Labores",
    "sg:orig_category":"Venta, Instalaci\u00d3n De Calefacci\u00d3n",
    "sg:phone":"+34 926 89 22 09",
    "sg:postcode":"13660",
    "sg:province":"Ciudad Real",
    "wof:name":"Gil-ortega Calcerrada Luis",
    "wof:placetype":"venue"
},
  "geometry": {"coordinates":[-3.5206539631,39.2732315063],"type":"Point"}
}