{
  "type": "Feature",
  "properties": {
    "iso:country":"ES",
    "sg:address":"Calle de Morillas, 52",
    "sg:city":"Malaga",
    "sg:orig_category":"Empresas De Pintura Y Revestimientos",
    "sg:phone":"+34 952 30 51 17",
    "sg:postcode":"29010",
    "sg:province":"M\u00e1laga",
    "wof:name":"Ballesteros Cristeta Francisco",
    "wof:placetype":"venue"
},
  "geometry": {"coordinates":[-4.4668369293,36.7223777771],"type":"Point"}
}