{
  "type": "Feature",
  "properties": {
    "iso:country":"ES",
    "sg:address":"Avgd Del Cami Nou, 64",
    "sg:city":"Xirivella",
    "sg:orig_category":"Ropa Para Se\u00d1oras Y Caballeros (al Por Menor)",
    "sg:phone":"+34 963 59 33 38",
    "sg:postcode":"46950",
    "sg:province":"Valencia",
    "wof:name":"Saz Quicios Domingo Del",
    "wof:placetype":"venue"
},
  "geometry": {"coordinates":[-0.4287039936,39.4665184021],"type":"Point"}
}