{
  "type": "Feature",
  "properties": {
    "addr:full":"Av Duran I Sanpere, 39 Cervera Lleida 25200",
    "addr:housenumber":"39",
    "addr:postcode":"25200",
    "addr:street":"Av Duran I Sanpere",
    "iso:country":"ES",
    "sg:address":"Av Duran I Sanpere, 39",
    "sg:city":"Cervera",
    "sg:orig_category":"Cr\u00cda De Animales",
    "sg:phone":"+34 973 53 02 85",
    "sg:postcode":"25200",
    "sg:province":"Lleida",
    "wof:name":"Sisquella Rigal Isidro",
    "wof:placetype":"venue"
},
  "geometry": {"coordinates":[1.2713420391,41.6700248718],"type":"Point"}
}