{
  "type": "Feature",
  "properties": {
    "addr:full":"Calle de Acera Del Arrecife, 6 Cordoba C\u00f3rdoba 14009",
    "addr:housenumber":"6",
    "addr:postcode":"14009",
    "addr:street":"Calle De Acera Del Arrecife;Co\u0301Rdoba",
    "iso:country":"ES",
    "sg:address":"Calle de Acera Del Arrecife, 6",
    "sg:city":"Cordoba",
    "sg:orig_category":"Molduras, Junquillos, Listones Y Molduras Perforadas",
    "sg:phone":"+34 957 29 04 01",
    "sg:postcode":"14009",
    "sg:province":"C\u00f3rdoba",
    "wof:name":"Gallardo Baena Antonio",
    "wof:placetype":"venue"
},
  "geometry": {"coordinates":[-4.775578022,37.8754692078],"type":"Point"}
}