{
  "type": "Feature",
  "properties": {
    "iso:country":"ES",
    "sg:address":"Garciez, S/n",
    "sg:city":"Garciez",
    "sg:orig_category":"Aceites Y Grasas Alimentarias (fabricaci\u00d3n, Al Por Mayor)",
    "sg:phone":"+34 953 12 00 86",
    "sg:postcode":"23640",
    "sg:province":"Ja\u00e9n",
    "wof:name":"Santa Catalina S.c.a",
    "wof:placetype":"venue"
},
  "geometry": {"coordinates":[-3.8929290771,37.7755012512],"type":"Point"}
}