{
  "type": "Feature",
  "properties": {
    "iso:country":"ES",
    "sg:address":"Calle de Ponce De Leon, 7",
    "sg:city":"Alhama Granada",
    "sg:orig_category":"Electrodom\u00c9sticos (al Por Menor)",
    "sg:phone":"+34 958 35 01 55",
    "sg:postcode":"18120",
    "sg:province":"Granada",
    "wof:name":"Lopez Fernandez Jose Luis",
    "wof:placetype":"venue"
},
  "geometry": {"coordinates":[-3.9901189804,37.0048370361],"type":"Point"}
}