{
  "type": "Feature",
  "properties": {
    "iso:country":"ES",
    "sg:address":"Rua Calpurnia Abana, 3",
    "sg:city":"Ourense",
    "sg:orig_category":"Ense\u00d1anza Variada",
    "sg:phone":"+34 988 23 83 38",
    "sg:postcode":"32005",
    "sg:province":"Ourense",
    "wof:name":"Martinez Estevez Carlos",
    "wof:placetype":"venue"
},
  "geometry": {"coordinates":[-7.865049839,42.3350486755],"type":"Point"}
}