{
  "type": "Feature",
  "properties": {
    "addr:full":"Avda Madridejos, 68 Villaca\u00f1as Toledo 45860",
    "addr:housenumber":"68",
    "addr:postcode":"45860",
    "addr:street":"Avda Madridejos",
    "iso:country":"ES",
    "sg:address":"Avda Madridejos, 68",
    "sg:city":"Villaca\u00f1as",
    "sg:orig_category":"Cerrajer\u00cda, Ferrallista",
    "sg:phone":"+34 925 16 10 28",
    "sg:postcode":"45860",
    "sg:province":"Toledo",
    "wof:name":"Autoagricola Triguero S.l.",
    "wof:placetype":"venue"
},
  "geometry": {"coordinates":[-3.3327970505,39.6216392517],"type":"Point"}
}