{
  "type": "Feature",
  "properties": {
    "iso:country":"ES",
    "sg:address":"Pl Espanya, 1",
    "sg:city":"Sitges",
    "sg:orig_category":"Aparcamientos (infraestructuras, Accesorios)",
    "sg:phone":"+34 938 94 24 39",
    "sg:postcode":"08870",
    "sg:province":"Barcelona",
    "wof:name":"Continental Parking S.l.",
    "wof:placetype":"venue"
},
  "geometry": {"coordinates":[1.8065320253,41.2346763611],"type":"Point"}
}