{
  "type": "Feature",
  "properties": {
    "iso:country":"ES",
    "sg:address":"Urba Arenals De Mar, S/n",
    "sg:city":"Arenals De Mar",
    "sg:orig_category":"Inmobiliaria (agencias)",
    "sg:phone":"+34 972 63 60 11",
    "sg:postcode":"17256",
    "sg:province":"Girona",
    "wof:name":"Inmobiliaria Arenales Del Mar S. A.",
    "wof:placetype":"venue"
},
  "geometry": {"coordinates":[3.1962299347,42.0007705688],"type":"Point"}
}