{
  "type": "Feature",
  "properties": {
    "addr:full":"Calle de Parroquia De Rois, S/n Poligono Industrial A Coru\u00f1a 15166",
    "addr:housenumber":"s / n",
    "addr:postcode":"15166",
    "addr:street":"Calle De Parroquia;Rois;Poligono Industrial A Corun\u0303A",
    "iso:country":"ES",
    "sg:address":"Calle de Parroquia De Rois, S/n",
    "sg:city":"Poligono Industrial",
    "sg:orig_category":"Inform\u00c1tica (estudios, Servicios, Asesor\u00cda, Formaci\u00d3n)",
    "sg:phone":"+34 981 78 35 11",
    "sg:postcode":"15166",
    "sg:province":"A Coru\u00f1a",
    "sg:website":"www.sermatica.es",
    "wof:name":"Sermatica S.a.",
    "wof:placetype":"venue"
},
  "geometry": {"coordinates":[-8.2616682053,43.3274726868],"type":"Point"}
}