{
  "type": "Feature",
  "properties": {
    "addr:full":"Carrer de Miquel Calafell, 17 Son Sardina Islas Baleares 07120",
    "addr:housenumber":"17",
    "addr:postcode":"07120",
    "addr:street":"Carrer De Miquel Calafell",
    "iso:country":"ES",
    "sg:address":"Carrer de Miquel Calafell, 17",
    "sg:city":"Son Sardina",
    "sg:orig_category":"Enfermeras: Consultas, Atenci\u00d3n A Domicilio",
    "sg:phone":"+34 971 43 91 90",
    "sg:postcode":"07120",
    "sg:province":"Islas Baleares",
    "wof:name":"Navarro Febrer Tomas",
    "wof:placetype":"venue"
},
  "geometry": {"coordinates":[2.6561980247,39.6212921143],"type":"Point"}
}