{
  "type": "Feature",
  "properties": {
    "addr:full":"Avda Aragon (de), 10 Alhama Aragon Zaragoza 50230",
    "addr:housenumber":"10",
    "addr:postcode":"50230",
    "addr:street":"Avda Aragon De",
    "iso:country":"ES",
    "sg:address":"Avda Aragon (de), 10",
    "sg:city":"Alhama Aragon",
    "sg:orig_category":"Pescader\u00cdas (al Por Menor)",
    "sg:phone":"+34 976 84 00 93",
    "sg:postcode":"50230",
    "sg:province":"Zaragoza",
    "wof:name":"Garrido De La Cruz Maria Del Pilar",
    "wof:placetype":"venue"
},
  "geometry": {"coordinates":[-1.8845490217,41.2986297607],"type":"Point"}
}