{
  "type": "Feature",
  "properties": {
    "iso:country":"ES",
    "sg:address":"Calle de Arriba, 14",
    "sg:city":"Tejina",
    "sg:orig_category":"Perfumer\u00cda, Art\u00cdculos De Ba\u00d1o (fabricaci\u00d3n, Al Por Mayor)",
    "sg:phone":"+34 922 54 30 03",
    "sg:postcode":"38260",
    "sg:province":"Santa Cruz De Tenerife",
    "wof:name":"Obon Paris S.l.",
    "wof:placetype":"venue"
},
  "geometry": {"coordinates":[-16.361415863,28.5332336426],"type":"Point"}
}