{
  "type": "Feature",
  "properties": {
    "iso:country":"ES",
    "sg:address":"Virgen De Los Desamparados, 4",
    "sg:city":"Oliva",
    "sg:orig_category":"Tractores Agr\u00cdcolas Y Remolques",
    "sg:phone":"+34 962 85 33 22",
    "sg:postcode":"46780",
    "sg:province":"Valencia",
    "wof:name":"Sansaloni Mi\u00f1ana Manuel",
    "wof:placetype":"venue"
},
  "geometry": {"coordinates":[-0.1248750016,38.9212684631],"type":"Point"}
}