{
  "type": "Feature",
  "properties": {
    "iso:country":"ES",
    "sg:address":"Plaza Solymar, S/n",
    "sg:city":"Benalmadena-costa",
    "sg:orig_category":"Discotecas Y Salas De Baile",
    "sg:phone":"+34 952 56 27 00",
    "sg:postcode":"29630",
    "sg:province":"M\u00e1laga",
    "wof:name":"Silva Campos Jose Luis",
    "wof:placetype":"venue"
},
  "geometry": {"coordinates":[-4.5173339844,36.5992050171],"type":"Point"}
}