{
  "type": "Feature",
  "properties": {
    "iso:country":"ES",
    "sg:address":"Calle de Meson De Paredes, 44",
    "sg:city":"Madrid",
    "sg:orig_category":"Fabricaci\u00d3n, Importaci\u00d3n De Material Y Sistemas De Telecomunicaciones",
    "sg:phone":"+34 915 39 78 55",
    "sg:postcode":"28012",
    "sg:province":"Madrid",
    "wof:name":"Diagramanet S.l.",
    "wof:placetype":"venue"
},
  "geometry": {"coordinates":[-3.7041399479,40.4096450806],"type":"Point"}
}