{
  "type": "Feature",
  "properties": {
    "iso:country":"ES",
    "sg:address":"Calle de Carretera Nueva, 68",
    "sg:city":"Rinconada",
    "sg:orig_category":"Pintura Y Barniz (al Por Menor)",
    "sg:phone":"+34 955 79 87 18",
    "sg:postcode":"41309",
    "sg:province":"Sevilla",
    "wof:name":"Garcia Yebenes Juan",
    "wof:placetype":"venue"
},
  "geometry": {"coordinates":[-5.9795331955,37.4865951538],"type":"Point"}
}