{
  "type": "Feature",
  "properties": {
    "addr:full":"Carrer de Moli, 52 Hospitalet Llobregat Barcelona 08906",
    "addr:housenumber":"52",
    "addr:postcode":"08906",
    "addr:street":"Carrer De Moli",
    "iso:country":"ES",
    "sg:address":"Carrer de Moli, 52",
    "sg:city":"Hospitalet Llobregat",
    "sg:orig_category":"Confecci\u00d3n (fabricaci\u00d3n, Al Por Mayor)",
    "sg:phone":"+34 934 37 71 86",
    "sg:postcode":"08906",
    "sg:province":"Barcelona",
    "wof:name":"Sanchez Martinez Jose",
    "wof:placetype":"venue"
},
  "geometry": {"coordinates":[2.1003630161,41.3702011108],"type":"Point"}
}