{
  "type": "Feature",
  "properties": {
    "addr:full":"Carrer de Manuel De Falla, 20 Barcelona Barcelona 08034",
    "addr:housenumber":"20",
    "addr:postcode":"08034",
    "addr:street":"Carrer De Manuel De Falla",
    "iso:country":"ES",
    "sg:address":"Carrer de Manuel De Falla, 20",
    "sg:city":"Barcelona",
    "sg:orig_category":"Extinci\u00d3n De Incendios: Material Y Suministros (fabricaci\u00d3n, Al Por Mayor)",
    "sg:phone":"+34 932 05 23 24",
    "sg:postcode":"08034",
    "sg:province":"Barcelona",
    "wof:name":"Extintores Gmc S.l.",
    "wof:placetype":"venue"
},
  "geometry": {"coordinates":[2.1253290176,41.393573761],"type":"Point"}
}