{
  "type": "Feature",
  "properties": {
    "addr:full":"Carr Ribarroja, 58 Manises Valencia 46940",
    "addr:housenumber":"58",
    "addr:postcode":"46940",
    "addr:street":"Carr Ribarroja",
    "iso:country":"ES",
    "sg:address":"Carr Ribarroja, 58",
    "sg:city":"Manises",
    "sg:orig_category":"Panader\u00cdas, Panader\u00cdas",
    "sg:phone":"+34 961 52 39 79",
    "sg:postcode":"46940",
    "sg:province":"Valencia",
    "wof:name":"Comercial Igove 94 S.l.",
    "wof:placetype":"venue"
},
  "geometry": {"coordinates":[-0.461488992,39.4922943115],"type":"Point"}
}