{
  "type": "Feature",
  "properties": {
    "addr:full":"Calle de Arboleda, 8 Getafe Madrid 28901",
    "addr:housenumber":"8",
    "addr:postcode":"28901",
    "addr:street":"Calle De Arboleda",
    "iso:country":"ES",
    "sg:address":"Calle de Arboleda, 8",
    "sg:city":"Getafe",
    "sg:orig_category":"Inmobiliaria (agencias)",
    "sg:phone":"+34 916 84 02 82",
    "sg:postcode":"28901",
    "sg:province":"Madrid",
    "wof:name":"Cas Punto Asesor S.l.",
    "wof:placetype":"venue"
},
  "geometry": {"coordinates":[-3.7287926674,40.3049621582],"type":"Point"}
}