{
  "type": "Feature",
  "properties": {
    "addr:full":"Calle de Sol, 6 Plasencia C\u00e1ceres 10600",
    "addr:housenumber":"6",
    "addr:postcode":"10600",
    "addr:street":"Calle De Sol;Ca\u0301Ceres",
    "iso:country":"ES",
    "sg:address":"Calle de Sol, 6",
    "sg:city":"Plasencia",
    "sg:orig_category":"Electricidad, Electr\u00d3nica: Material Y Suministros (al Por Mayor)",
    "sg:phone":"+34 927 42 41 31",
    "sg:postcode":"10600",
    "sg:province":"C\u00e1ceres",
    "wof:name":"Gonzalez Moreno Francisco",
    "wof:placetype":"venue"
},
  "geometry": {"coordinates":[-6.0890169144,40.0299415588],"type":"Point"}
}