{
  "type": "Feature",
  "properties": {
    "addr:full":"Latxartegi Kalea, 4 Legazpi Guip\u00f9zcoa 20230",
    "addr:housenumber":"4",
    "addr:postcode":"20230",
    "addr:street":"Latxartegi Kalea;Guipu\u0300Zcoa",
    "iso:country":"ES",
    "sg:address":"Latxartegi Kalea, 4",
    "sg:city":"Legazpi",
    "sg:orig_category":"Guarder\u00cdas",
    "sg:phone":"+34 943 73 16 13",
    "sg:postcode":"20230",
    "sg:province":"Guip\u00f9zcoa",
    "wof:name":"Haztegi Ikastola Koop Elk",
    "wof:placetype":"venue"
},
  "geometry": {"coordinates":[-2.3343338966,43.0522918701],"type":"Point"}
}