{
  "type": "Feature",
  "properties": {
    "addr:full":"Ctra Andalucia, Km. 0058,4 Oca\u00f1a Toledo 45300",
    "addr:postcode":"45300",
    "addr:street":"Ctra Andalucia Km. 0058,4",
    "iso:country":"ES",
    "sg:address":"Ctra Andalucia, Km. 0058,4",
    "sg:city":"Oca\u00f1a",
    "sg:orig_category":"Mec\u00c1nico Del Autom\u00d3vil",
    "sg:phone":"+34 925 13 00 06",
    "sg:postcode":"45300",
    "sg:province":"Toledo",
    "wof:name":"Gonzalez Guio Miguel",
    "wof:placetype":"venue"
},
  "geometry": {"coordinates":[-4.3996291161,38.0070762634],"type":"Point"}
}