{
  "type": "Feature",
  "properties": {
    "addr:full":"Ctra San Sebastian De Los Ballesteros, 1 Rambla C\u00f3rdoba 14540",
    "addr:housenumber":"1",
    "addr:postcode":"14540",
    "addr:street":"Ctra San Sebastian De Los Ballesteros;Rambla Co\u0301Rdoba",
    "iso:country":"ES",
    "sg:address":"Ctra San Sebastian De Los Ballesteros, 1",
    "sg:city":"Rambla",
    "sg:orig_category":"Alfarer\u00cda",
    "sg:phone":"+34 957 68 40 75",
    "sg:postcode":"14540",
    "sg:province":"C\u00f3rdoba",
    "wof:name":"Alfarera Artistica Ramble\u00f1a S. C. L.",
    "wof:placetype":"venue"
},
  "geometry": {"coordinates":[-4.8220720291,37.7124824524],"type":"Point"}
}