{
  "type": "Feature",
  "properties": {
    "addr:full":"Rua Republica De El Salvador (da), 28 Santiago De Compostela La Coru\u00f1a 15701",
    "addr:housenumber":"28",
    "addr:postcode":"15701",
    "addr:street":"Rua Republica De El;Corun\u0303A",
    "iso:country":"ES",
    "sg:address":"Rua Republica De El Salvador (da), 28",
    "sg:city":"Santiago De Compostela",
    "sg:orig_category":"Seguridad Social",
    "sg:phone":"+34 981 59 77 97",
    "sg:postcode":"15701",
    "sg:province":"La Coru\u00f1a",
    "sg:website":"www.mutual-cyclops.com",
    "wof:name":"Mutual Midat Cyclops Mutua De Accidentes De Trabajo Y Enfermedades Profesionales De La Seguridad Soc",
    "wof:placetype":"venue"
},
  "geometry": {"coordinates":[-8.5483217239,42.8746185303],"type":"Point"}
}