{
  "type": "Feature",
  "properties": {
    "addr:full":"Avda Portet (del), 42 Moraira Alicante 03724",
    "addr:housenumber":"42",
    "addr:postcode":"03724",
    "addr:street":"Avda Portet Del",
    "iso:country":"ES",
    "sg:address":"Avda Portet (del), 42",
    "sg:city":"Moraira",
    "sg:orig_category":"Asesor\u00cda Fiscal Y Jur\u00cddica",
    "sg:phone":"+34 966 49 13 19",
    "sg:postcode":"03724",
    "sg:province":"Alicante",
    "wof:name":"Moraira Fernandez Multi Service S.l.",
    "wof:placetype":"venue"
},
  "geometry": {"coordinates":[0.1316400021,38.6928710938],"type":"Point"}
}