{
  "type": "Feature",
  "properties": {
    "iso:country":"ES",
    "sg:address":"Calle de Leon Tolstoi, 24",
    "sg:city":"Palmas De Gran Canaria",
    "sg:orig_category":"Fotograf\u00cda Art\u00cdstica Y Retratos",
    "sg:phone":"+34 928 22 78 84",
    "sg:postcode":"35010",
    "sg:province":"Las Palmas",
    "wof:name":"Honaine Correa Jorge",
    "wof:placetype":"venue"
},
  "geometry": {"coordinates":[-15.4359436035,28.1347446442],"type":"Point"}
}