{
  "type": "Feature",
  "properties": {
    "addr:full":"Calle de Los Buesa, 3 Vitoria-gasteiz \u00c1lava 01006",
    "addr:housenumber":"3",
    "addr:postcode":"01006",
    "addr:street":"Calle De Los Buesa",
    "iso:country":"ES",
    "sg:address":"Calle de Los Buesa, 3",
    "sg:city":"Vitoria-gasteiz",
    "sg:orig_category":"Artes Gr\u00c1ficas, Artes Pl\u00c1sticas: Material Y Suministros (al Por Menor)",
    "sg:phone":"+34 945 15 50 03",
    "sg:postcode":"01006",
    "sg:province":"\u00c1lava",
    "wof:name":"Lanvall Estructuras S.l.",
    "wof:placetype":"venue"
},
  "geometry": {"coordinates":[-2.6743850708,42.8365592957],"type":"Point"}
}