{
  "type": "Feature",
  "properties": {
    "addr:full":"G. Brenan, 64 Alhaurin Grande M\u00e1laga 29120",
    "addr:housenumber":"64",
    "addr:postcode":"29120",
    "addr:street":"G. Brenan",
    "iso:country":"ES",
    "sg:address":"G. Brenan, 64",
    "sg:city":"Alhaurin Grande",
    "sg:orig_category":"Frutas Y Legumbres Frescas (al Por Mayor)",
    "sg:phone":"+34 952 59 47 36",
    "sg:postcode":"29120",
    "sg:province":"M\u00e1laga",
    "wof:name":"Rueda Jimenez Jose Antonio",
    "wof:placetype":"venue"
},
  "geometry": {"coordinates":[-4.6911292076,36.6420783997],"type":"Point"}
}