{
  "type": "Feature",
  "properties": {
    "addr:full":"Carrer de Riera Baste, 48 S. Boi Llobregat Barcelona 08830",
    "addr:housenumber":"48",
    "addr:postcode":"08830",
    "addr:street":"Carrer De Riera Baste",
    "iso:country":"ES",
    "sg:address":"Carrer de Riera Baste, 48",
    "sg:city":"S. Boi Llobregat",
    "sg:orig_category":"Asilos De Ancianos. Centros Privados",
    "sg:phone":"+34 936 40 04 64",
    "sg:postcode":"08830",
    "sg:province":"Barcelona",
    "wof:name":"Llar Sant Josep",
    "wof:placetype":"venue"
},
  "geometry": {"coordinates":[2.032063961,41.3447227478],"type":"Point"}
}