{
  "type": "Feature",
  "properties": {
    "addr:full":"Plaz Cruz Verde, 5 Motril Granada 18600",
    "addr:postcode":"18600",
    "addr:street":"Plaz;Verde",
    "iso:country":"ES",
    "sg:address":"Plaz Cruz Verde, 5",
    "sg:city":"Motril",
    "sg:orig_category":"M\u00c9dicos: Oftalmolog\u00cda",
    "sg:phone":"+34 958 60 44 16",
    "sg:postcode":"18600",
    "sg:province":"Granada",
    "wof:name":"Iboleon Lopez Enrique",
    "wof:placetype":"venue"
},
  "geometry": {"coordinates":[-3.5179290771,36.7452697754],"type":"Point"}
}