{
  "type": "Feature",
  "properties": {
    "iso:country":"ES",
    "sg:address":"Cra Ca L'alaio, 34",
    "sg:city":"Prat Llobregat",
    "sg:orig_category":"Lavado, Limpieza De Veh\u00cdculos",
    "sg:phone":"+34 933 70 27 62",
    "sg:postcode":"08820",
    "sg:province":"Barcelona",
    "wof:name":"Traesbar S.l.",
    "wof:placetype":"venue"
},
  "geometry": {"coordinates":[2.0822968483,41.3293800354],"type":"Point"}
}