{
  "type": "Feature",
  "properties": {
    "addr:full":"F. L. Guaridas, Km. 0002,0 Villafranca Barros Badajoz 06220",
    "addr:postcode":"06220",
    "addr:street":"F. L. Guaridas Km. 0002,0 Villafranca Barros",
    "iso:country":"ES",
    "sg:address":"F. L. Guaridas, Km. 0002,0",
    "sg:city":"Villafranca Barros",
    "sg:orig_category":"Aguas (distribuci\u00d3n, Servicios)",
    "sg:phone":"+34 924 12 40 23",
    "sg:postcode":"06220",
    "sg:province":"Badajoz",
    "wof:name":"Aqualia Gestion Integral Del Agua S.a.",
    "wof:placetype":"venue"
},
  "geometry": {"coordinates":[-6.9702835083,38.8785972595],"type":"Point"}
}