{
  "type": "Feature",
  "properties": {
    "iso:country":"ES",
    "sg:address":"Calle de Eduardo Domingo Y Cea, 17",
    "sg:city":"Polan",
    "sg:orig_category":"Confecci\u00d3n (fabricaci\u00d3n, Al Por Mayor)",
    "sg:phone":"+34 925 37 00 33",
    "sg:postcode":"45161",
    "sg:province":"Toledo",
    "wof:name":"Cama\u00f1o Peces Vidal",
    "wof:placetype":"venue"
},
  "geometry": {"coordinates":[-4.1654839516,39.7871551514],"type":"Point"}
}