{
  "type": "Feature",
  "properties": {
    "iso:country":"ES",
    "sg:address":"Avda Perez Galdos, 46",
    "sg:city":"Logro\u00f1o",
    "sg:orig_category":"Pescader\u00cdas (al Por Menor)",
    "sg:phone":"+34 941 22 87 74",
    "sg:postcode":"26002",
    "sg:province":"La Rioja",
    "wof:name":"Bengoechea Escalona Maria Paloma",
    "wof:placetype":"venue"
},
  "geometry": {"coordinates":[-2.4512588978,42.462146759],"type":"Point"}
}