{
  "type": "Feature",
  "properties": {
    "iso:country":"ES",
    "sg:address":"Avda Leizaur, 67",
    "sg:city":"Peralta",
    "sg:orig_category":"Metalurgia",
    "sg:phone":"+34 948 75 11 12",
    "sg:postcode":"31350",
    "sg:province":"Navarra",
    "sg:website":"www.koxka.com",
    "wof:name":"Hussmann Koxka S.l.",
    "wof:placetype":"venue"
},
  "geometry": {"coordinates":[-1.8066689968,42.3411407471],"type":"Point"}
}