{
  "type": "Feature",
  "properties": {
    "iso:country":"ES",
    "sg:address":"Calle de Calvario, 32",
    "sg:city":"Bogarra",
    "sg:orig_category":"Transportes Por V\u00cdas Navegables",
    "sg:phone":"+34 967 29 01 81",
    "sg:postcode":"02130",
    "sg:province":"Albacete",
    "wof:name":"Garcia Rodriguez Fernando",
    "wof:placetype":"venue"
},
  "geometry": {"coordinates":[-2.2122819424,38.5829162598],"type":"Point"}
}