{
  "type": "Feature",
  "properties": {
    "iso:country":"ES",
    "sg:address":"Carrer de Arago, 465",
    "sg:city":"Barcelona",
    "sg:orig_category":"Promotores Constructores",
    "sg:phone":"+34 932 65 53 27",
    "sg:postcode":"08013",
    "sg:province":"Barcelona",
    "wof:name":"Rafols Raventos Arago 469 S.l.",
    "wof:placetype":"venue"
},
  "geometry": {"coordinates":[2.1792559624,41.403175354],"type":"Point"}
}