{
  "type": "Feature",
  "properties": {
    "addr:full":"Calle de Sol, 16 Villaviciosa Asturias 33300",
    "addr:housenumber":"16",
    "addr:postcode":"33300",
    "addr:street":"Calle De Sol",
    "iso:country":"ES",
    "sg:address":"Calle de Sol, 16",
    "sg:city":"Villaviciosa",
    "sg:orig_category":"Ropa Para Caballeros (al Por Menor)",
    "sg:phone":"+34 985 89 06 64",
    "sg:postcode":"33300",
    "sg:province":"Asturias",
    "wof:name":"Redondo Francisco Jose",
    "wof:placetype":"venue"
},
  "geometry": {"coordinates":[-5.4347949028,43.4808120728],"type":"Point"}
}