{
  "type": "Feature",
  "properties": {
    "iso:country":"ES",
    "sg:address":"Calle de Fraternidad, 3",
    "sg:city":"Tias",
    "sg:orig_category":"Agencias De Viajes",
    "sg:phone":"+34 928 83 39 38",
    "sg:postcode":"35572",
    "sg:province":"Las Palmas",
    "wof:name":"Rodriguez Perdomo Carmen Teresa",
    "wof:placetype":"venue"
},
  "geometry": {"coordinates":[-13.6531267166,28.9532012939],"type":"Point"}
}