{
  "type": "Feature",
  "properties": {
    "iso:country":"ES",
    "sg:address":"Carrer de Seneca, 4",
    "sg:city":"Barcelona",
    "sg:orig_category":"Importaci\u00d3n",
    "sg:phone":"+34 932 18 09 72",
    "sg:postcode":"08006",
    "sg:province":"Barcelona",
    "wof:name":"Estunac S.l.",
    "wof:placetype":"venue"
},
  "geometry": {"coordinates":[2.1569190025,41.3974533081],"type":"Point"}
}