{
  "type": "Feature",
  "properties": {
    "iso:country":"ES",
    "sg:address":"Avda Marques De Corbera, 48",
    "sg:city":"Madrid",
    "sg:orig_category":"Peluqueros: De Se\u00d1oras",
    "sg:phone":"+34 914 04 31 79",
    "sg:postcode":"28017",
    "sg:province":"Madrid",
    "wof:name":"Romera Villar Palmira",
    "wof:placetype":"venue"
},
  "geometry": {"coordinates":[-3.6517100334,40.4256134033],"type":"Point"}
}