{
  "type": "Feature",
  "properties": {
    "iso:country":"ES",
    "sg:address":"Avda Valladolid, S/n",
    "sg:city":"Soria",
    "sg:orig_category":"Muebles, Minoristas",
    "sg:phone":"+34 975 22 02 98",
    "sg:postcode":"42004",
    "sg:province":"Soria",
    "wof:name":"Hermanos Miguel S.a.",
    "wof:placetype":"venue"
},
  "geometry": {"coordinates":[-2.4828391075,41.7677268982],"type":"Point"}
}