{
  "type": "Feature",
  "properties": {
    "iso:country":"ES",
    "sg:address":"Calle de San Vicente, 34",
    "sg:city":"San Vicente De Barakaldo",
    "sg:orig_category":"Puertas Y Portales",
    "sg:phone":"+34 944 37 46 00",
    "sg:postcode":"48902",
    "sg:province":"Vizcaya",
    "wof:name":"Puertas Y Ventanas San Vicente",
    "wof:placetype":"venue"
},
  "geometry": {"coordinates":[-2.9949569702,43.2960281372],"type":"Point"}
}