{
  "type": "Feature",
  "properties": {
    "iso:country":"ES",
    "sg:address":"Carrer de Corsega, 615",
    "sg:city":"Barcelona",
    "sg:orig_category":"Agentes Generales De Seguros",
    "sg:phone":"+34 934 35 91 93",
    "sg:postcode":"08025",
    "sg:province":"Barcelona",
    "wof:name":"Espla Molina Maria Pilar",
    "wof:placetype":"venue"
},
  "geometry": {"coordinates":[2.1756029129,41.4089584351],"type":"Point"}
}