{
  "type": "Feature",
  "properties": {
    "addr:full":"Calle de Isaac Peral, 2 Huelva Huelva 21002",
    "addr:housenumber":"2",
    "addr:postcode":"21002",
    "addr:street":"Calle De Isaac Peral",
    "iso:country":"ES",
    "sg:address":"Calle de Isaac Peral, 2",
    "sg:city":"Huelva",
    "sg:orig_category":"Ense\u00d1anza: Idiomas",
    "sg:phone":"+34 959 28 28 29",
    "sg:postcode":"21002",
    "sg:province":"Huelva",
    "wof:name":"Centro De Idiomas Covent Garden S.l.",
    "wof:placetype":"venue"
},
  "geometry": {"coordinates":[-6.9519929886,37.2593574524],"type":"Point"}
}