{
  "type": "Feature",
  "properties": {
    "addr:full":"Avda Pamplona, 5 Tafalla Navarra 31300",
    "addr:housenumber":"5",
    "addr:postcode":"31300",
    "addr:street":"Avda Pamplona",
    "iso:country":"ES",
    "sg:address":"Avda Pamplona, 5",
    "sg:city":"Tafalla",
    "sg:orig_category":"Venta, Montaje De Neum\u00c1ticos",
    "sg:phone":"+34 948 70 09 28",
    "sg:postcode":"31300",
    "sg:province":"Navarra",
    "wof:name":"Neumaticos Montero Pacheco S.l.",
    "wof:placetype":"venue"
},
  "geometry": {"coordinates":[-1.6720670462,42.5321769714],"type":"Point"}
}