{
  "type": "Feature",
  "properties": {
    "addr:full":"Calle de Espa\u00d1oleto, 5 Mostoles Madrid 28932",
    "addr:housenumber":"5",
    "addr:postcode":"28932",
    "addr:street":"Calle De Espan\u0303Oleto",
    "iso:country":"ES",
    "sg:address":"Calle de Espa\u00d1oleto, 5",
    "sg:city":"Mostoles",
    "sg:orig_category":"Peluquer\u00cdas, Peluquer\u00cda Mixta",
    "sg:phone":"+34 916 18 42 22",
    "sg:postcode":"28932",
    "sg:province":"Madrid",
    "wof:name":"Juste Vera Marta",
    "wof:placetype":"venue"
},
  "geometry": {"coordinates":[-3.862251997,40.3326072693],"type":"Point"}
}