{
  "type": "Feature",
  "properties": {
    "iso:country":"ES",
    "sg:address":"Carr Lleida, 101",
    "sg:city":"Alpicat",
    "sg:orig_category":"Fachadas",
    "sg:phone":"+34 973 73 66 95",
    "sg:postcode":"25110",
    "sg:province":"Lleida",
    "wof:name":"Multinet-rapid,s.l",
    "wof:placetype":"venue"
},
  "geometry": {"coordinates":[0.5569900274,41.6662216187],"type":"Point"}
}