{
  "type": "Feature",
  "properties": {
    "addr:full":"Calle de Caleruega, 45 Madrid Madrid 28033",
    "addr:housenumber":"45",
    "addr:postcode":"madrid;28033",
    "addr:street":"Calle De Caleruega",
    "iso:country":"ES",
    "sg:address":"Calle de Caleruega, 45",
    "sg:city":"Madrid",
    "sg:orig_category":"Arquitectos",
    "sg:phone":"+34 913 83 87 58",
    "sg:postcode":"28033",
    "sg:province":"Madrid",
    "wof:name":"Gesmisa S.l.",
    "wof:placetype":"venue"
},
  "geometry": {"coordinates":[-3.6712522507,40.4801902771],"type":"Point"}
}