{
  "type": "Feature",
  "properties": {
    "iso:country":"ES",
    "sg:address":"Rua Dolores, 60",
    "sg:city":"Ferrol",
    "sg:orig_category":"Complementos De Vestir (al Por Menor)",
    "sg:phone":"+34 981 30 00 59",
    "sg:postcode":"15402",
    "sg:province":"La Coru\u00f1a",
    "wof:name":"Lopez Perez Maria Sheila",
    "wof:placetype":"venue"
},
  "geometry": {"coordinates":[-8.2368183136,43.482925415],"type":"Point"}
}