{
  "type": "Feature",
  "properties": {
    "iso:country":"ES",
    "sg:address":"Calle de Esperanza, 48",
    "sg:city":"Calasparra",
    "sg:orig_category":"Electricidad: Instaladores",
    "sg:phone":"+34 968 74 50 33",
    "sg:postcode":"30420",
    "sg:province":"Murcia",
    "wof:name":"Torrente Martinez Francisco",
    "wof:placetype":"venue"
},
  "geometry": {"coordinates":[-1.6986989975,38.2286071777],"type":"Point"}
}