{
  "type": "Feature",
  "properties": {
    "iso:country":"ES",
    "sg:address":"Calle de Jazmin, 19",
    "sg:city":"Ubeda",
    "sg:orig_category":"Reposter\u00cdas",
    "sg:phone":"+34 953 75 31 91",
    "sg:postcode":"23400",
    "sg:province":"Ja\u00e9n",
    "wof:name":"Pulpillo Catena Antonio",
    "wof:placetype":"venue"
},
  "geometry": {"coordinates":[-3.3649361134,38.0138435364],"type":"Point"}
}