{
  "type": "Feature",
  "properties": {
    "iso:country":"ES",
    "sg:address":"Carrer de Aribau, 184",
    "sg:city":"Barcelona",
    "sg:orig_category":"Inmobiliaria (agencias)",
    "sg:phone":"+34 932 00 02 73",
    "sg:postcode":"08036",
    "sg:province":"Barcelona",
    "wof:name":"Consell I Assessorament Inmobiliari S.l.",
    "wof:placetype":"venue"
},
  "geometry": {"coordinates":[2.1527431011,41.3935699463],"type":"Point"}
}