{
  "type": "Feature",
  "properties": {
    "addr:full":"Calle de Antonio Cabrera Sanchez, 39 Arriate M\u00e1laga 29350",
    "addr:housenumber":"39",
    "addr:postcode":"29350",
    "addr:street":"Calle De Antonio Cabrera Sanchez;Ma\u0301Laga",
    "iso:country":"ES",
    "sg:address":"Calle de Antonio Cabrera Sanchez, 39",
    "sg:city":"Arriate",
    "sg:orig_category":"Porcelanas, Azulejos (fabricaci\u00d3n, Al Por Mayor)",
    "sg:phone":"+34 952 16 61 49",
    "sg:postcode":"29350",
    "sg:province":"M\u00e1laga",
    "wof:name":"Serrato Anet S.l.",
    "wof:placetype":"venue"
},
  "geometry": {"coordinates":[-5.1362991333,36.7949409485],"type":"Point"}
}