{
  "type": "Feature",
  "properties": {
    "addr:full":"Calle de Florista, 7 Valencia Valencia 46015",
    "addr:housenumber":"7",
    "addr:postcode":"46015",
    "addr:street":"Calle De Florista",
    "iso:country":"ES",
    "sg:address":"Calle de Florista, 7",
    "sg:city":"Valencia",
    "sg:orig_category":"Guarder\u00cdas",
    "sg:phone":"+34 963 40 75 60",
    "sg:postcode":"46015",
    "sg:province":"Valencia",
    "wof:name":"Herrero Rubio Maria De Los Desamparados",
    "wof:placetype":"venue"
},
  "geometry": {"coordinates":[-0.3915269971,39.4902038574],"type":"Point"}
}