{
  "type": "Feature",
  "properties": {
    "addr:full":"Pase Ramon Y Cajal, 2 Calatayud Zaragoza 50300",
    "addr:housenumber":"2",
    "addr:postcode":"50300",
    "addr:street":"Ramon Y Cajal",
    "iso:country":"ES",
    "sg:address":"Pase Ramon Y Cajal, 2",
    "sg:city":"Calatayud",
    "sg:orig_category":"Servicios Gsm",
    "sg:phone":"+34 976 88 70 24",
    "sg:postcode":"50300",
    "sg:province":"Zaragoza",
    "wof:name":"Franco Ferrer S.l.",
    "wof:placetype":"venue"
},
  "geometry": {"coordinates":[-1.6448210478,41.350151062],"type":"Point"}
}