{
  "type": "Feature",
  "properties": {
    "addr:full":"Lleida, 2 Artesa Lleida Lleida 25150",
    "addr:housenumber":"2",
    "addr:postcode":"25150",
    "addr:street":"Lleida",
    "iso:country":"ES",
    "sg:address":"Lleida, 2",
    "sg:city":"Artesa Lleida",
    "sg:orig_category":"Distribuci\u00d3n De Petr\u00d3leo Y Derivados",
    "sg:phone":"+34 973 16 71 73",
    "sg:postcode":"25150",
    "sg:province":"Lleida",
    "wof:name":"Carburants Artesa 2002 S.l.",
    "wof:placetype":"venue"
},
  "geometry": {"coordinates":[0.7054510117,41.5533065796],"type":"Point"}
}