{
  "type": "Feature",
  "properties": {
    "iso:country":"ES",
    "sg:address":"Carr Alcalde Costa, 2",
    "sg:city":"Lleida",
    "sg:orig_category":"M\u00c9dicos: Cirug\u00cda Urol\u00d3gica",
    "sg:phone":"+34 973 28 28 31",
    "sg:postcode":"25002",
    "sg:province":"Lleida",
    "wof:name":"Recasens Guinjuan Jose Ricardo",
    "wof:placetype":"venue"
},
  "geometry": {"coordinates":[0.6205130219,41.6113739014],"type":"Point"}
}