{
  "type": "Feature",
  "properties": {
    "addr:full":"Calle de Fray Juan, 15 Bilbao Vizcaya 48013",
    "addr:housenumber":"15",
    "addr:postcode":"48013",
    "addr:street":"Calle De Fray Juan",
    "iso:country":"ES",
    "sg:address":"Calle de Fray Juan, 15",
    "sg:city":"Bilbao",
    "sg:orig_category":"Centros Comerciales Y Grandes Tiendas",
    "sg:phone":"+34 944 85 11 81",
    "sg:postcode":"48013",
    "sg:province":"Vizcaya",
    "wof:name":"Qi Ming Chen",
    "wof:placetype":"venue"
},
  "geometry": {"coordinates":[-2.9722430706,43.2765693665],"type":"Point"}
}