{
  "type": "Feature",
  "properties": {
    "iso:country":"ES",
    "sg:address":"Luga Perdiz La, S/n",
    "sg:city":"Gijon",
    "sg:orig_category":"Deportes Diversos",
    "sg:phone":"+34 985 16 77 80",
    "sg:postcode":"33209",
    "sg:province":"Asturias",
    "wof:name":"Real Federacion De Futbol Del Principado",
    "wof:placetype":"venue"
},
  "geometry": {"coordinates":[-5.6620330811,43.5045127869],"type":"Point"}
}