{
  "type": "Feature",
  "properties": {
    "addr:full":"Avda Mejico, 30 Huelva Huelva 21001",
    "addr:housenumber":"30",
    "addr:postcode":"21001",
    "addr:street":"Avda Mejico",
    "iso:country":"ES",
    "sg:address":"Avda Mejico, 30",
    "sg:city":"Huelva",
    "sg:orig_category":"Maquinaria Para Industrias Diversas",
    "sg:phone":"+34 959 25 14 62",
    "sg:postcode":"21001",
    "sg:province":"Huelva",
    "wof:name":"Fernandez Beltran Inocencio",
    "wof:placetype":"venue"
},
  "geometry": {"coordinates":[-6.9495940208,37.256313324],"type":"Point"}
}