{
  "type": "Feature",
  "properties": {
    "iso:country":"ES",
    "sg:address":"Pol Ind Sant Lluis, S/n",
    "sg:city":"Sant Lluis",
    "sg:orig_category":"Reposter\u00cdas",
    "sg:phone":"+34 971 15 13 20",
    "sg:postcode":"07710",
    "sg:province":"Islas Baleares",
    "wof:name":"Panaderia Luis Pons S.l.",
    "wof:placetype":"venue"
},
  "geometry": {"coordinates":[4.2691421509,39.8487739563],"type":"Point"}
}