{
  "type": "Feature",
  "properties": {
    "iso:country":"ES",
    "sg:address":"Calle de Victor Chavarri, 25",
    "sg:city":"Oviedo",
    "sg:orig_category":"Farmacias",
    "sg:phone":"+34 985 21 73 39",
    "sg:postcode":"33001",
    "sg:province":"Asturias",
    "wof:name":"Pozo Martinez Rafael Del",
    "wof:placetype":"venue"
},
  "geometry": {"coordinates":[-5.8423571587,43.3657989502],"type":"Point"}
}