{
  "type": "Feature",
  "properties": {
    "addr:full":"Avda Oriental (sp), 2 San Pedro Alcantara M\u00e1laga 29670",
    "addr:postcode":"29670",
    "addr:street":"Avda Oriental Sp 2",
    "iso:country":"ES",
    "sg:address":"Avda Oriental (sp), 2",
    "sg:city":"San Pedro Alcantara",
    "sg:orig_category":"Frutas Y Legumbres Frescas (al Por Mayor)",
    "sg:phone":"+34 952 78 11 91",
    "sg:postcode":"29670",
    "sg:province":"M\u00e1laga",
    "wof:name":"Morito Marin Lorenzo",
    "wof:placetype":"venue"
},
  "geometry": {"coordinates":[-5.003718853,36.4735946655],"type":"Point"}
}