{
  "type": "Feature",
  "properties": {
    "addr:full":"Ctra. San Vicente, S/n Alburquerque Badajoz 06510",
    "addr:housenumber":"s / n",
    "addr:street":"Ctra. San Vicente",
    "iso:country":"ES",
    "sg:address":"Ctra. San Vicente, S/n",
    "sg:city":"Alburquerque",
    "sg:orig_category":"Distribuci\u00d3n De Petr\u00d3leo Y Derivados",
    "sg:phone":"+34 924 40 13 92",
    "sg:postcode":"06510",
    "sg:province":"Badajoz",
    "wof:name":"Galpgest Petrogal Estaciones De Servicio S.l.u.",
    "wof:placetype":"venue"
},
  "geometry": {"coordinates":[-7.0032339096,39.2224388123],"type":"Point"}
}