{
  "type": "Feature",
  "properties": {
    "iso:country":"ES",
    "sg:address":"Carrer de Villarroel, 131",
    "sg:city":"Barcelona",
    "sg:orig_category":"Muebles, Minoristas",
    "sg:phone":"+34 934 51 80 34",
    "sg:postcode":"08036",
    "sg:province":"Barcelona",
    "wof:name":"Kit Paris S.l.",
    "wof:placetype":"venue"
},
  "geometry": {"coordinates":[2.1547789574,41.3865242004],"type":"Point"}
}