{
  "type": "Feature",
  "properties": {
    "addr:full":"Calle de Bardegueral, 16 Madrid Madrid 28023",
    "addr:housenumber":"16",
    "addr:postcode":"madrid;28023",
    "addr:street":"Calle De Bardegueral",
    "iso:country":"ES",
    "sg:address":"Calle de Bardegueral, 16",
    "sg:city":"Madrid",
    "sg:orig_category":"Centros De Educaci\u00d3n Especial",
    "sg:phone":"+34 913 57 06 61",
    "sg:postcode":"28023",
    "sg:province":"Madrid",
    "wof:name":"Colegio Publico Rosa Luxemburgo",
    "wof:placetype":"venue"
},
  "geometry": {"coordinates":[-3.7717123032,40.4499778748],"type":"Point"}
}