{
  "type": "Feature",
  "properties": {
    "iso:country":"ES",
    "sg:address":"Carrer de Joan Larrea, 11",
    "sg:city":"Mataro",
    "sg:orig_category":"Asociaciones Y Clubs Deportivos",
    "sg:phone":"+34 937 57 41 55",
    "sg:postcode":"08302",
    "sg:province":"Barcelona",
    "wof:name":"Imbernon Rumin Maria Rosa",
    "wof:placetype":"venue"
},
  "geometry": {"coordinates":[2.432612896,41.5379486084],"type":"Point"}
}