{
  "type": "Feature",
  "properties": {
    "iso:country":"ES",
    "sg:address":"Calle de Juan Pedro Vidal, 10",
    "sg:city":"Lebrija",
    "sg:orig_category":"Promotores Constructores",
    "sg:phone":"+34 955 97 26 11",
    "sg:postcode":"41740",
    "sg:province":"Sevilla",
    "wof:name":"Calderon Romero S.l.",
    "wof:placetype":"venue"
},
  "geometry": {"coordinates":[-6.0801491737,36.9196205139],"type":"Point"}
}