{
  "type": "Feature",
  "properties": {
    "iso:country":"ES",
    "sg:address":"Luga Mercado Central, S/n",
    "sg:city":"Palmas De Gran Canaria",
    "sg:orig_category":"Frutas, Legumbres Frescas Y Tempranas (al Por Menor)",
    "sg:phone":"+34 928 24 25 83",
    "sg:postcode":"35006",
    "sg:province":"Las Palmas",
    "wof:name":"Armas Mendoza Antonio Armando",
    "wof:placetype":"venue"
},
  "geometry": {"coordinates":[-15.4317026138,28.1318531036],"type":"Point"}
}