{
  "type": "Feature",
  "properties": {
    "iso:country":"ES",
    "sg:address":"Avda La Barrosa, 63",
    "sg:city":"Chiclana",
    "sg:orig_category":"Centros Empresariales",
    "sg:phone":"+34 956 49 46 84",
    "sg:postcode":"11130",
    "sg:province":"C\u00e1diz",
    "wof:name":"Bocchari S.l.",
    "wof:placetype":"venue"
},
  "geometry": {"coordinates":[-6.1783599854,36.3923721313],"type":"Point"}
}