{
  "type": "Feature",
  "properties": {
    "iso:country":"ES",
    "sg:address":"A Cerca, 26",
    "sg:city":"Cerca",
    "sg:orig_category":"Empresarios",
    "sg:phone":"+34 986 55 52 26",
    "sg:postcode":"36620",
    "sg:province":"Pontevedra",
    "wof:name":"Construcciones Peleteira 24 S.l.",
    "wof:placetype":"venue"
},
  "geometry": {"coordinates":[-8.8285036087,42.5618782043],"type":"Point"}
}