{
  "type": "Feature",
  "properties": {
    "iso:country":"ES",
    "sg:address":"Ctra N-340, Km. 1040,0",
    "sg:city":"Pe\u00f1iscola",
    "sg:orig_category":"Art\u00cdculos De Madera (fabricaci\u00d3n Y Al Por Mayor)",
    "sg:phone":"+34 964 46 51 10",
    "sg:postcode":"12598",
    "sg:province":"Castell\u00f3n",
    "wof:name":"Practic Moble S.l.",
    "wof:placetype":"venue"
},
  "geometry": {"coordinates":[-0.0456800014,39.9851417542],"type":"Point"}
}