{
  "type": "Feature",
  "properties": {
    "addr:full":"Carrer de Sant Quirze, 56 Sabadell Barcelona 08201",
    "addr:housenumber":"56",
    "addr:postcode":"08201",
    "addr:street":"Carrer De Sant Quirze",
    "iso:country":"ES",
    "sg:address":"Carrer de Sant Quirze, 56",
    "sg:city":"Sabadell",
    "sg:orig_category":"Organizaciones Internacionales",
    "sg:phone":"+34 902 30 23 20",
    "sg:postcode":"08201",
    "sg:province":"Barcelona",
    "sg:website":"www.asociacionshare.org",
    "wof:name":"Share Espa\u00d1a",
    "wof:placetype":"venue"
},
  "geometry": {"coordinates":[2.105825901,41.5462989807],"type":"Point"}
}