{
  "type": "Feature",
  "properties": {
    "iso:country":"ES",
    "sg:address":"Bernard Vicent (p I Dos Octubre), S/n",
    "sg:city":"Santa Fe",
    "sg:orig_category":"Caf\u00c9s (al Por Menor)",
    "sg:phone":"+34 958 44 06 57",
    "sg:postcode":"18320",
    "sg:province":"Granada",
    "wof:name":"Gallego Aranda Granada S.l.",
    "wof:placetype":"venue"
},
  "geometry": {"coordinates":[-3.7536664009,37.1630401611],"type":"Point"}
}