{
  "type": "Feature",
  "properties": {
    "addr:full":"Calle de Natalio Rivas, 60 Adra Almer\u00eda 04770",
    "addr:housenumber":"60",
    "addr:postcode":"04770",
    "addr:street":"Calle De Natalio Rivas;Almeri\u0301A",
    "iso:country":"ES",
    "sg:address":"Calle de Natalio Rivas, 60",
    "sg:city":"Adra",
    "sg:orig_category":"Servicios Gsm",
    "sg:phone":"+34 950 60 45 01",
    "sg:postcode":"04770",
    "sg:province":"Almer\u00eda",
    "wof:name":"Electromar Comunicacion S.l.",
    "wof:placetype":"venue"
},
  "geometry": {"coordinates":[-3.0175800323,36.7482719421],"type":"Point"}
}