{
  "type": "Feature",
  "properties": {
    "iso:country":"ES",
    "sg:address":"Avda Brasil, S/n",
    "sg:city":"Madrid",
    "sg:orig_category":"Aparcamientos (infraestructuras, Accesorios)",
    "sg:phone":"+34 915 56 17 92",
    "sg:postcode":"28020",
    "sg:province":"Madrid",
    "wof:name":"Estacionamientos Hernani S.a.",
    "wof:placetype":"venue"
},
  "geometry": {"coordinates":[-3.6940529346,40.4535636902],"type":"Point"}
}