{
  "type": "Feature",
  "properties": {
    "iso:country":"ES",
    "sg:address":"Calle de Gurutzondo, 5",
    "sg:city":"Elorrio",
    "sg:orig_category":"Promotores Constructores",
    "sg:phone":"+34 946 82 00 50",
    "sg:postcode":"48230",
    "sg:province":"Vizcaya",
    "wof:name":"Alba\u00f1ileria Kurutzondo S.l.",
    "wof:placetype":"venue"
},
  "geometry": {"coordinates":[-2.5495409966,43.1337928772],"type":"Point"}
}