{
  "type": "Feature",
  "properties": {
    "addr:full":"Calle de Cervantes, 14 Coria Rio Sevilla 41100",
    "addr:housenumber":"14",
    "addr:postcode":"41100",
    "addr:street":"Calle De Cervantes;Rio Sevilla",
    "iso:country":"ES",
    "sg:address":"Calle de Cervantes, 14",
    "sg:city":"Coria Rio",
    "sg:orig_category":"Reposter\u00cdas",
    "sg:phone":"+34 954 77 00 95",
    "sg:postcode":"41100",
    "sg:province":"Sevilla",
    "wof:name":"Toro Alfaro Manuel",
    "wof:placetype":"venue"
},
  "geometry": {"coordinates":[-6.0509681702,37.2864112854],"type":"Point"}
}