{
  "type": "Feature",
  "properties": {
    "addr:full":"Ctra Aguilas (de), 66 Campillo Murcia 30813",
    "addr:housenumber":"66",
    "addr:postcode":"30813",
    "addr:street":"Ctra Aguilas De",
    "iso:country":"ES",
    "sg:address":"Ctra Aguilas (de), 66",
    "sg:city":"Campillo",
    "sg:orig_category":"Asociaciones Y Clubs Deportivos",
    "sg:phone":"+34 968 46 13 00",
    "sg:postcode":"30813",
    "sg:province":"Murcia",
    "wof:name":"Club De Tenis Los Alamos",
    "wof:placetype":"venue"
},
  "geometry": {"coordinates":[-1.7215889692,37.491394043],"type":"Point"}
}