{
  "type": "Feature",
  "properties": {
    "addr:full":"Calle de Tamarguillo, 29 Sevilla Sevilla 41013",
    "addr:housenumber":"29",
    "addr:postcode":"41013",
    "addr:street":"Calle De Tamarguillo",
    "iso:country":"ES",
    "sg:address":"Calle de Tamarguillo, 29",
    "sg:city":"Sevilla",
    "sg:orig_category":"Aparatos De Medida, Control, Regulaci\u00d3n Y Detecci\u00d3n",
    "sg:phone":"+34 954 63 45 67",
    "sg:postcode":"41013",
    "sg:province":"Sevilla",
    "wof:name":"Telvent Outsourcing S.a.",
    "wof:placetype":"venue"
},
  "geometry": {"coordinates":[-5.9701633453,37.3672332764],"type":"Point"}
}