{
  "type": "Feature",
  "properties": {
    "addr:full":"Calle de Cervantes, 23 Burgos Burgos 09002",
    "addr:housenumber":"23",
    "addr:postcode":"09002",
    "addr:street":"Calle De Cervantes",
    "iso:country":"ES",
    "sg:address":"Calle de Cervantes, 23",
    "sg:city":"Burgos",
    "sg:orig_category":"Electrodom\u00c9sticos (al Por Menor)",
    "sg:phone":"+34 947 27 32 18",
    "sg:postcode":"09002",
    "sg:province":"Burgos",
    "wof:name":"Sematec Burgos Servicio De Asistencia Al Cliente S.l.",
    "wof:placetype":"venue"
},
  "geometry": {"coordinates":[-3.6918489933,42.3352012634],"type":"Point"}
}