{
  "type": "Feature",
  "properties": {
    "iso:country":"ES",
    "sg:address":"Calle de Maestro (del), 1",
    "sg:city":"Leganes",
    "sg:orig_category":"Organizaciones Profesionales",
    "sg:phone":"+34 916 89 85 54",
    "sg:postcode":"28914",
    "sg:province":"Madrid",
    "wof:name":"Marmoratus S.l.",
    "wof:placetype":"venue"
},
  "geometry": {"coordinates":[-3.7569739819,40.3264961243],"type":"Point"}
}