{
  "type": "Feature",
  "properties": {
    "iso:country":"ES",
    "sg:address":"Plaz San Pedro (de), 12",
    "sg:city":"Almeria",
    "sg:orig_category":"Tapicer\u00cdas",
    "sg:phone":"+34 950 23 09 96",
    "sg:postcode":"04001",
    "sg:province":"Almer\u00eda",
    "wof:name":"Garcia Pardo Jose Antonio",
    "wof:placetype":"venue"
},
  "geometry": {"coordinates":[-2.4647417068,36.8379211426],"type":"Point"}
}