{
  "type": "Feature",
  "properties": {
    "addr:full":"Calle de Santa Teresa (de), 5 Pinto Madrid 28320",
    "addr:housenumber":"5",
    "addr:postcode":"28320",
    "addr:street":"Calle De Santa Teresa De;Pinto",
    "iso:country":"ES",
    "sg:address":"Calle de Santa Teresa (de), 5",
    "sg:city":"Pinto",
    "sg:orig_category":"Trajes Y Adornos De Boda (confecci\u00d3n, Al Por Menor)",
    "sg:phone":"+34 916 91 61 83",
    "sg:postcode":"28320",
    "sg:province":"Madrid",
    "wof:name":"Perez Pascual Miguel Angel",
    "wof:placetype":"venue"
},
  "geometry": {"coordinates":[-3.6962690353,40.2393913269],"type":"Point"}
}