{
  "type": "Feature",
  "properties": {
    "addr:full":"Ptda Barxell, 13 Alcoi Alicante 03800",
    "addr:housenumber":"13",
    "addr:postcode":"03800",
    "addr:street":"Ptda Barxell",
    "iso:country":"ES",
    "sg:address":"Ptda Barxell, 13",
    "sg:city":"Alcoi",
    "sg:orig_category":"Pintores",
    "sg:phone":"+34 965 52 20 72",
    "sg:postcode":"03800",
    "sg:province":"Alicante",
    "wof:name":"Egea Berzosa Francisco",
    "wof:placetype":"venue"
},
  "geometry": {"coordinates":[-0.4732739925,38.6984100342],"type":"Point"}
}