{
  "type": "Feature",
  "properties": {
    "iso:country":"ES",
    "sg:address":"Calle de Miguel Perez, 11",
    "sg:city":"Mendavia",
    "sg:orig_category":"Delegados, Agentes De Tr\u00c1nsito, Auxiliares De Transporte Internacional",
    "sg:phone":"+34 948 68 52 20",
    "sg:postcode":"31587",
    "sg:province":"Navarra",
    "wof:name":"Elvira Aramendia Victor Angel",
    "wof:placetype":"venue"
},
  "geometry": {"coordinates":[-2.1990060806,42.4418983459],"type":"Point"}
}