{
  "type": "Feature",
  "properties": {
    "iso:country":"ES",
    "sg:address":"Carr Major, 10",
    "sg:city":"Alcudia",
    "sg:orig_category":"M\u00c9dicos: Estomatolog\u00cda",
    "sg:phone":"+34 971 54 88 14",
    "sg:postcode":"07400",
    "sg:province":"Islas Baleares",
    "wof:name":"Ventayol Ventayol Sebastian",
    "wof:placetype":"venue"
},
  "geometry": {"coordinates":[3.1211149693,39.853187561],"type":"Point"}
}