{
  "type": "Feature",
  "properties": {
    "iso:country":"ES",
    "sg:address":"Maestro Don Joaquin, 13",
    "sg:city":"Monovar",
    "sg:orig_category":"Bisuter\u00cda, Joyer\u00cda, Relojer\u00cda (al Por Menor)",
    "sg:phone":"+34 965 47 11 80",
    "sg:postcode":"03640",
    "sg:province":"Alicante",
    "wof:name":"Vidal Guillen Aurora",
    "wof:placetype":"venue"
},
  "geometry": {"coordinates":[-0.8384190202,38.4362716675],"type":"Point"}
}