{
  "type": "Feature",
  "properties": {
    "iso:country":"ES",
    "sg:address":"Calle de Cervantes, 9",
    "sg:city":"Madrid",
    "sg:orig_category":"Librer\u00cdas",
    "sg:phone":"+34 914 29 93 13",
    "sg:postcode":"28014",
    "sg:province":"Madrid",
    "wof:name":"Linares Martinez Rosario",
    "wof:placetype":"venue"
},
  "geometry": {"coordinates":[-3.6977968216,40.4143333435],"type":"Point"}
}