{
  "type": "Feature",
  "properties": {
    "addr:full":"Carrer de Carreras I Candi, 1 Barcelona Barcelona 08028",
    "addr:housenumber":"1",
    "addr:postcode":"08028",
    "addr:street":"Carrer De Carreras I Candi",
    "iso:country":"ES",
    "sg:address":"Carrer de Carreras I Candi, 1",
    "sg:city":"Barcelona",
    "sg:orig_category":"Agencias Y Agentes Comerciales, Representantes",
    "sg:phone":"+34 934 31 25 06",
    "sg:postcode":"08028",
    "sg:province":"Barcelona",
    "wof:name":"Cordomi Sala Antonia",
    "wof:placetype":"venue"
},
  "geometry": {"coordinates":[2.1262700558,41.3753890991],"type":"Point"}
}