{
  "type": "Feature",
  "properties": {
    "iso:country":"ES",
    "sg:address":"Calle de Rodriguez Hernandez, 21",
    "sg:city":"Salamanca",
    "sg:orig_category":"Promotores Constructores",
    "sg:phone":"+34 923 12 44 85",
    "sg:postcode":"37006",
    "sg:province":"Salamanca",
    "wof:name":"Comunidad De Propietarios Rodriguez Hernandez 21-25",
    "wof:placetype":"venue"
},
  "geometry": {"coordinates":[-5.6773281097,40.9770545959],"type":"Point"}
}