{
  "type": "Feature",
  "properties": {
    "addr:full":"Calle de San Isidro, 37 Villena Alicante 03400",
    "addr:housenumber":"37",
    "addr:postcode":"03400",
    "addr:street":"Calle De San Isidro",
    "iso:country":"ES",
    "sg:address":"Calle de San Isidro, 37",
    "sg:city":"Villena",
    "sg:orig_category":"Confecci\u00d3n De Zapatos",
    "sg:phone":"+34 965 80 44 17",
    "sg:postcode":"03400",
    "sg:province":"Alicante",
    "sg:website":"www.sanmi.es",
    "wof:name":"Martinez Galbis S.l.",
    "wof:placetype":"venue"
},
  "geometry": {"coordinates":[-0.8690649867,38.6371994019],"type":"Point"}
}