{
  "type": "Feature",
  "properties": {
    "addr:full":"Pg Fonts, De Ses, 5 S. Antoni Portmany Islas Baleares 07820",
    "addr:housenumber":"5",
    "addr:postcode":"07820",
    "addr:street":"Pg Fonts De Ses",
    "iso:country":"ES",
    "sg:address":"Pg Fonts, De Ses, 5",
    "sg:city":"S. Antoni Portmany",
    "sg:orig_category":"Cajas De Ahorro",
    "sg:phone":"+34 971 80 33 12",
    "sg:postcode":"07820",
    "sg:province":"Islas Baleares",
    "sg:website":"www.cam.es",
    "wof:name":"Caja De Ahorros Del Mediterraneo",
    "wof:placetype":"venue"
},
  "geometry": {"coordinates":[1.5188339949,39.1094055176],"type":"Point"}
}