{
  "type": "Feature",
  "properties": {
    "iso:country":"ES",
    "sg:address":"Calle de Santo Cristo, 38",
    "sg:city":"Monturque",
    "sg:orig_category":"Plomeros",
    "sg:phone":"+34 957 53 56 44",
    "sg:postcode":"14930",
    "sg:province":"C\u00f3rdoba",
    "wof:name":"Zamora Ruiz Nicasio",
    "wof:placetype":"venue"
},
  "geometry": {"coordinates":[-4.5824408531,37.4722862244],"type":"Point"}
}