{
  "type": "Feature",
  "properties": {
    "addr:full":"Calle de Jose Calvo, 26 Madrid Madrid 28039",
    "addr:housenumber":"26",
    "addr:postcode":"madrid;28039",
    "addr:street":"Calle De Jose Calvo",
    "iso:country":"ES",
    "sg:address":"Calle de Jose Calvo, 26",
    "sg:city":"Madrid",
    "sg:orig_category":"Electricidad: Instaladores",
    "sg:phone":"+34 913 11 80 44",
    "sg:postcode":"28039",
    "sg:province":"Madrid",
    "wof:name":"Asime Electricidad S.l.",
    "wof:placetype":"venue"
},
  "geometry": {"coordinates":[-3.7083427906,40.4584960938],"type":"Point"}
}