{
  "type": "Feature",
  "properties": {
    "addr:full":"Avda Manoteras, 22 Madrid Madrid 28050",
    "addr:housenumber":"22",
    "addr:postcode":"madrid;28050",
    "addr:street":"Avda Manoteras",
    "iso:country":"ES",
    "sg:address":"Avda Manoteras, 22",
    "sg:city":"Madrid",
    "sg:orig_category":"Muebles",
    "sg:phone":"+34 913 83 38 12",
    "sg:postcode":"28050",
    "sg:province":"Madrid",
    "wof:name":"Sistal S. A.",
    "wof:placetype":"venue"
},
  "geometry": {"coordinates":[-3.6676080227,40.4865875244],"type":"Point"}
}