{
  "type": "Feature",
  "properties": {
    "iso:country":"ES",
    "sg:address":"Av Valencia, 16",
    "sg:city":"Pego",
    "sg:orig_category":"Muebles, Minoristas",
    "sg:phone":"+34 965 57 08 51",
    "sg:postcode":"03780",
    "sg:province":"Alicante",
    "wof:name":"Salort Cloquell Remedios",
    "wof:placetype":"venue"
},
  "geometry": {"coordinates":[-0.1156250015,38.8446121216],"type":"Point"}
}