{
  "type": "Feature",
  "properties": {
    "iso:country":"ES",
    "sg:address":"Carrer de Musica, 9",
    "sg:city":"Rubi",
    "sg:orig_category":"Instalaci\u00d3n De Aspiraci\u00d3n De Gases Y Humos",
    "sg:phone":"+34 935 86 04 44",
    "sg:postcode":"08191",
    "sg:province":"Barcelona",
    "wof:name":"Antonio Boira Gas S.l.",
    "wof:placetype":"venue"
},
  "geometry": {"coordinates":[2.0352168083,41.4808883667],"type":"Point"}
}