{
  "type": "Feature",
  "properties": {
    "iso:country":"ES",
    "sg:address":"Ctra. Alcorcon-plasencia, S/n",
    "sg:city":"Gavilanes",
    "sg:orig_category":"Ingeniero",
    "sg:phone":"+34 920 37 71 24",
    "sg:postcode":"05460",
    "sg:province":"\u00c1vila",
    "sg:website":"www.irena.es",
    "wof:name":"Ingenieria Recursos Naturales S. A.",
    "wof:placetype":"venue"
},
  "geometry": {"coordinates":[-4.8831849098,40.2978820801],"type":"Point"}
}