{
  "type": "Feature",
  "properties": {
    "addr:full":"Calle de Madrid, 6 Rozas De Madrid Madrid 28230",
    "addr:housenumber":"6",
    "addr:postcode":"28230",
    "addr:street":"Calle De Madrid",
    "iso:country":"ES",
    "sg:address":"Calle de Madrid, 6",
    "sg:city":"Rozas De Madrid",
    "sg:orig_category":"Mec\u00c1nico Del Autom\u00d3vil",
    "sg:phone":"+34 916 37 53 14",
    "sg:postcode":"28230",
    "sg:province":"Madrid",
    "wof:name":"Undiano Manco Francisco",
    "wof:placetype":"venue"
},
  "geometry": {"coordinates":[-3.868710041,40.4932823181],"type":"Point"}
}