{
  "type": "Feature",
  "properties": {
    "addr:full":"Rond Sant Pere, 13 Barcelona Barcelona 08010",
    "addr:housenumber":"13",
    "addr:postcode":"08010",
    "addr:street":"Sant Pere",
    "iso:country":"ES",
    "sg:address":"Rond Sant Pere, 13",
    "sg:city":"Barcelona",
    "sg:orig_category":"Financiaci\u00d3n Y Cr\u00c9ditos",
    "sg:phone":"+34 933 42 40 62",
    "sg:postcode":"08010",
    "sg:province":"Barcelona",
    "wof:name":"Barcelona Gestio Economica I Immobiliaria",
    "wof:placetype":"venue"
},
  "geometry": {"coordinates":[2.1713569164,41.3885803223],"type":"Point"}
}