{
  "type": "Feature",
  "properties": {
    "iso:country":"ES",
    "sg:address":"Calle de Concepcion, 3",
    "sg:city":"Hellin",
    "sg:orig_category":"Ropa Para Ni\u00d1os (al Por Menor)",
    "sg:phone":"+34 967 30 37 04",
    "sg:postcode":"02400",
    "sg:province":"Albacete",
    "wof:name":"Padilla Martinez Consuelo",
    "wof:placetype":"venue"
},
  "geometry": {"coordinates":[-1.699218154,38.5087089539],"type":"Point"}
}