{
  "type": "Feature",
  "properties": {
    "addr:full":"Calle de Real, 31 Mengibar Ja\u00e9n 23620",
    "addr:housenumber":"31",
    "addr:postcode":"23620",
    "addr:street":"Calle De Real;Jae\u0301N",
    "iso:country":"ES",
    "sg:address":"Calle de Real, 31",
    "sg:city":"Mengibar",
    "sg:orig_category":"\u00d3ptica: Instrumentos (fabricaci\u00d3n)",
    "sg:phone":"+34 953 37 09 95",
    "sg:postcode":"23620",
    "sg:province":"Ja\u00e9n",
    "wof:name":"Carrillo Castillo Antonio Jesus",
    "wof:placetype":"venue"
},
  "geometry": {"coordinates":[-3.8085451126,37.9699172974],"type":"Point"}
}