{
  "type": "Feature",
  "properties": {
    "iso:country":"ES",
    "sg:address":"Plaz Mayor, 26",
    "sg:city":"Salamanca",
    "sg:orig_category":"Caf\u00c9s, Bares, Cervecer\u00cdas",
    "sg:phone":"+34 923 21 52 44",
    "sg:postcode":"37002",
    "sg:province":"Salamanca",
    "wof:name":"Labrador Rozas Jose Manuel",
    "wof:placetype":"venue"
},
  "geometry": {"coordinates":[-5.6654667854,40.9631118774],"type":"Point"}
}