{
  "type": "Feature",
  "properties": {
    "iso:country":"ES",
    "sg:address":"Ctra Cardedeu, Km. 0015,0",
    "sg:city":"Corro D'avall",
    "sg:orig_category":"Fabrica De Cer\u00c1micas",
    "sg:phone":"+34 938 46 72 29",
    "sg:postcode":"08520",
    "sg:province":"Barcelona",
    "wof:name":"Ceramicas Font S.a.",
    "wof:placetype":"venue"
},
  "geometry": {"coordinates":[2.2963228226,41.6181106567],"type":"Point"}
}