{
  "type": "Feature",
  "properties": {
    "addr:full":"Ctra Valverde, 2600 Badajoz Badajoz 06010",
    "addr:postcode":"2600;06010",
    "addr:street":"Ctra Valverde",
    "iso:country":"ES",
    "sg:address":"Ctra Valverde, 2600",
    "sg:city":"Badajoz",
    "sg:orig_category":"Remolques, Carretillas De Mano Para Operaciones Portuarias",
    "sg:phone":"+34 924 26 84 79",
    "sg:postcode":"06010",
    "sg:province":"Badajoz",
    "wof:name":"Jusacarret Maquinaria S.l.",
    "wof:placetype":"venue"
},
  "geometry": {"coordinates":[-6.9719491005,38.8619689941],"type":"Point"}
}