{
  "type": "Feature",
  "properties": {
    "addr:full":"Cra. Penelles, Km. 0002,0 Linyola Lleida 25240",
    "addr:postcode":"25240",
    "addr:street":"Km. 0002,0",
    "iso:country":"ES",
    "sg:address":"Cra. Penelles, Km. 0002,0",
    "sg:city":"Linyola",
    "sg:orig_category":"Agricultores, Agricultores",
    "sg:phone":"+34 973 57 55 31",
    "sg:postcode":"25240",
    "sg:province":"Lleida",
    "wof:name":"Penell S.a.",
    "wof:placetype":"venue"
},
  "geometry": {"coordinates":[0.9033300281,41.7112731934],"type":"Point"}
}