{
  "type": "Feature",
  "properties": {
    "iso:country":"ES",
    "sg:address":"Ctra Cosario, 36",
    "sg:city":"Mojonera",
    "sg:orig_category":"Promotores Constructores",
    "sg:phone":"+34 950 55 81 37",
    "sg:postcode":"04745",
    "sg:province":"Almer\u00eda",
    "wof:name":"Magravic 95 S.l.",
    "wof:placetype":"venue"
},
  "geometry": {"coordinates":[-2.6798489094,36.7567443848],"type":"Point"}
}