{
  "type": "Feature",
  "properties": {
    "addr:full":"Rond Sant Ramon, 102 S. Boi Llobregat Barcelona 08830",
    "addr:postcode":"08830",
    "addr:street":"Ramon 102 S.",
    "iso:country":"ES",
    "sg:address":"Rond Sant Ramon, 102",
    "sg:city":"S. Boi Llobregat",
    "sg:orig_category":"Inmobiliaria (agencias)",
    "sg:phone":"+34 936 30 80 80",
    "sg:postcode":"08830",
    "sg:province":"Barcelona",
    "wof:name":"Alcarma Gestion Inmobiliaria S.l.",
    "wof:placetype":"venue"
},
  "geometry": {"coordinates":[2.0280311108,41.3468856812],"type":"Point"}
}