{
  "type": "Feature",
  "properties": {
    "iso:country":"ES",
    "sg:address":"Carrer de Concordia, 10",
    "sg:city":"Barcelona",
    "sg:orig_category":"Alimentaci\u00d3n General (al Por Menor)",
    "sg:phone":"+34 934 42 18 45",
    "sg:postcode":"08004",
    "sg:province":"Barcelona",
    "wof:name":"Syid Iftikhar Mushtaq",
    "wof:placetype":"venue"
},
  "geometry": {"coordinates":[2.1608700752,41.3743209839],"type":"Point"}
}