{
  "type": "Feature",
  "properties": {
    "iso:country":"ES",
    "sg:address":"Calle de Archena, 17",
    "sg:city":"San Javier",
    "sg:orig_category":"Cajas De Ahorro",
    "sg:phone":"+34 968 19 16 07",
    "sg:postcode":"30730",
    "sg:province":"Murcia",
    "wof:name":"Caja De Ahorros Del Mediterraneo",
    "wof:placetype":"venue"
},
  "geometry": {"coordinates":[-0.8268175125,37.8007926941],"type":"Point"}
}