{
  "type": "Feature",
  "properties": {
    "iso:country":"ES",
    "sg:address":"Carrer de Canuda, 15",
    "sg:city":"Barcelona",
    "sg:orig_category":"Decoraci\u00d3n: Instalaci\u00d3n Y Talleres",
    "sg:phone":"+34 933 02 32 15",
    "sg:postcode":"08002",
    "sg:province":"Barcelona",
    "wof:name":"Valero Zabala Antonio",
    "wof:placetype":"venue"
},
  "geometry": {"coordinates":[2.1718430519,41.3847427368],"type":"Point"}
}