{
  "type": "Feature",
  "properties": {
    "addr:full":"Ptda Boqueres-a, 1 Boqueres Alicante 03690",
    "addr:housenumber":"1",
    "addr:postcode":"03690",
    "addr:street":"Ptda Boqueres-A;Alicante",
    "iso:country":"ES",
    "sg:address":"Ptda Boqueres-a, 1",
    "sg:city":"Boqueres",
    "sg:orig_category":"Producci\u00d3n, Venta De Productos De Agricultura Biol\u00d3gica",
    "sg:phone":"+34 965 66 34 27",
    "sg:postcode":"03690",
    "sg:province":"Alicante",
    "wof:name":"Sat El Sabinar",
    "wof:placetype":"venue"
},
  "geometry": {"coordinates":[-0.5231339931,38.3981590271],"type":"Point"}
}