{
  "type": "Feature",
  "properties": {
    "addr:full":"Calle de Alfileritos, 13 Toledo Toledo 45003",
    "addr:housenumber":"13",
    "addr:postcode":"45003",
    "addr:street":"Calle De Alfileritos",
    "iso:country":"ES",
    "sg:address":"Calle de Alfileritos, 13",
    "sg:city":"Toledo",
    "sg:orig_category":"Abogados",
    "sg:phone":"+34 925 22 40 02",
    "sg:postcode":"45003",
    "sg:province":"Toledo",
    "wof:name":"Angulo Rubin De Celis Angel",
    "wof:placetype":"venue"
},
  "geometry": {"coordinates":[-4.0239672661,39.8598098755],"type":"Point"}
}