{
  "type": "Feature",
  "properties": {
    "iso:country":"ES",
    "sg:address":"Carrer de Sant Ramon, 12",
    "sg:city":"Santa Coloma De Gramenet",
    "sg:orig_category":"Ropa Para Se\u00d1oras (al Por Menor)",
    "sg:phone":"+34 933 86 19 66",
    "sg:postcode":"08922",
    "sg:province":"Barcelona",
    "wof:name":"Montes Carrillo Aurora",
    "wof:placetype":"venue"
},
  "geometry": {"coordinates":[2.2114489079,41.4498748779],"type":"Point"}
}