{
  "type": "Feature",
  "properties": {
    "addr:full":"Badia Polesine, 3 Estepa Sevilla 41560",
    "addr:housenumber":"3",
    "addr:postcode":"41560",
    "addr:street":"Polesine;Sevilla",
    "iso:country":"ES",
    "sg:address":"Badia Polesine, 3",
    "sg:city":"Estepa",
    "sg:orig_category":"Motocicletas (agentes, Concesionarios)",
    "sg:phone":"+34 954 82 09 12",
    "sg:postcode":"41560",
    "sg:province":"Sevilla",
    "wof:name":"Motos Mu\u00f1oz S.c.",
    "wof:placetype":"venue"
},
  "geometry": {"coordinates":[-4.8810458183,37.2948608398],"type":"Point"}
}