{
  "type": "Feature",
  "properties": {
    "iso:country":"ES",
    "sg:address":"Irunlarrea, 30",
    "sg:city":"Iru\u00f1a",
    "sg:orig_category":"Productos Qu\u00cdmicos (fabricaci\u00d3n, Al Por Mayor)",
    "sg:phone":"+34 948 26 52 23",
    "sg:postcode":"31008",
    "sg:province":"Navarra",
    "wof:name":"Cenal S. A.",
    "wof:placetype":"venue"
},
  "geometry": {"coordinates":[-1.6726609468,42.8102264404],"type":"Point"}
}