{
  "type": "Feature",
  "properties": {
    "iso:country":"ES",
    "sg:address":"Plaz Zarzuela (de La), 4",
    "sg:city":"Abaran",
    "sg:orig_category":"Asesor\u00cda Fiscal Y Jur\u00cddica",
    "sg:phone":"+34 968 45 12 56",
    "sg:postcode":"30550",
    "sg:province":"Murcia",
    "wof:name":"Morte Molina Antonio",
    "wof:placetype":"venue"
},
  "geometry": {"coordinates":[-1.3944859505,38.2074737549],"type":"Point"}
}