{
  "type": "Feature",
  "properties": {
    "addr:full":"Carr Esteban Bilbao, 3 Quart Poblet Valencia 46930",
    "addr:housenumber":"3",
    "addr:postcode":"46930",
    "addr:street":"Carr Esteban Bilbao;Poblet",
    "iso:country":"ES",
    "sg:address":"Carr Esteban Bilbao, 3",
    "sg:city":"Quart Poblet",
    "sg:orig_category":"Confecci\u00d3n (fabricaci\u00d3n, Al Por Mayor)",
    "sg:phone":"+34 961 53 34 45",
    "sg:postcode":"46930",
    "sg:province":"Valencia",
    "wof:name":"Fos Alabajos Peregrin",
    "wof:placetype":"venue"
},
  "geometry": {"coordinates":[-0.4419890046,39.482711792],"type":"Point"}
}