{
  "type": "Feature",
  "properties": {
    "iso:country":"ES",
    "sg:address":"Plaz Espa\u00d1a, 3",
    "sg:city":"Montoro",
    "sg:orig_category":"Mercer\u00cda, Lencer\u00cda (al Por Menor)",
    "sg:phone":"+34 957 16 04 08",
    "sg:postcode":"14600",
    "sg:province":"C\u00f3rdoba",
    "wof:name":"Aguilar Benitez Carlos",
    "wof:placetype":"venue"
},
  "geometry": {"coordinates":[-4.3565130234,38.1094436646],"type":"Point"}
}