{
  "type": "Feature",
  "properties": {
    "iso:country":"ES",
    "sg:address":"Carrer de Pelai, 12",
    "sg:city":"Barcelona",
    "sg:orig_category":"Sindicatos Y Colegios Profesionales",
    "sg:phone":"+34 933 02 65 60",
    "sg:postcode":"08001",
    "sg:province":"Barcelona",
    "sg:website":"www.acesc.net",
    "wof:name":"Associacio De Catedratics D'ensenyaments Secundaris De Catalunya",
    "wof:placetype":"venue"
},
  "geometry": {"coordinates":[2.1657011509,41.3858413696],"type":"Point"}
}