{
  "type": "Feature",
  "properties": {
    "addr:full":"Carr Bs Perello, 36 Igualada Barcelona 08700",
    "addr:housenumber":"36",
    "addr:postcode":"08700",
    "addr:street":"Carr Bs Perello",
    "iso:country":"ES",
    "sg:address":"Carr Bs Perello, 36",
    "sg:city":"Igualada",
    "sg:orig_category":"Herboristas (al Por Menor)",
    "sg:phone":"+34 938 04 27 34",
    "sg:postcode":"08700",
    "sg:province":"Barcelona",
    "wof:name":"Dieta Line S.c.p.",
    "wof:placetype":"venue"
},
  "geometry": {"coordinates":[1.6322200298,41.5782852173],"type":"Point"}
}