{
  "type": "Feature",
  "properties": {
    "addr:full":"Zubierreka Industri Poligonoa, 41 Zubierreka Guip\u00f9zcoa 20210",
    "addr:housenumber":"41",
    "addr:postcode":"20210",
    "addr:street":"Zubierreka Industri Poligonoa;Guipu\u0300Zcoa",
    "iso:country":"ES",
    "sg:address":"Zubierreka Industri Poligonoa, 41",
    "sg:city":"Zubierreka",
    "sg:orig_category":"Venta, Montaje De Neum\u00c1ticos",
    "sg:phone":"+34 943 88 20 79",
    "sg:postcode":"20210",
    "sg:province":"Guip\u00f9zcoa",
    "wof:name":"Ibarlaburu S.l.",
    "wof:placetype":"venue"
},
  "geometry": {"coordinates":[-2.1873590946,43.0314903259],"type":"Point"}
}