{
  "type": "Feature",
  "properties": {
    "iso:country":"ES",
    "sg:address":"Carrer de Barcelona, 2",
    "sg:city":"Hospitalet Llobregat",
    "sg:orig_category":"Fabricaci\u00d3n, Importaci\u00d3n, Venta De Material De Telefon\u00cda, Peritelefon\u00cda",
    "sg:phone":"+34 933 38 45 15",
    "sg:postcode":"08901",
    "sg:province":"Barcelona",
    "wof:name":"Softpair S.l.",
    "wof:placetype":"venue"
},
  "geometry": {"coordinates":[2.1044960022,41.3615684509],"type":"Point"}
}