{
  "type": "Feature",
  "properties": {
    "iso:country":"ES",
    "sg:address":"Carrer de Tavertet, S/n",
    "sg:city":"Vic",
    "sg:orig_category":"Fabricaci\u00d3n, Venta, Instalaci\u00d3n De R\u00d3tulos, De R\u00d3tulos Luminosos",
    "sg:phone":"+34 938 89 27 92",
    "sg:postcode":"08500",
    "sg:province":"Barcelona",
    "wof:name":"Palau Bartrina Josep",
    "wof:placetype":"venue"
},
  "geometry": {"coordinates":[2.2793300152,41.9461708069],"type":"Point"}
}