{
  "type": "Feature",
  "properties": {
    "iso:country":"ES",
    "sg:address":"Calle de Francisco Neila, 4",
    "sg:city":"Santa Marta",
    "sg:orig_category":"Arquitectos",
    "sg:phone":"+34 924 69 03 95",
    "sg:postcode":"06150",
    "sg:province":"Badajoz",
    "wof:name":"Pinillos Montero Gregorio",
    "wof:placetype":"venue"
},
  "geometry": {"coordinates":[-6.6247987747,38.6142082214],"type":"Point"}
}