{
  "type": "Feature",
  "properties": {
    "iso:country":"ES",
    "sg:address":"Pl Miguel Hernandez, 6",
    "sg:city":"Alcoi",
    "sg:orig_category":"M\u00c1quinas Textiles, Accesorios Y Suministros (fabricaci\u00d3n)",
    "sg:phone":"+34 965 33 92 53",
    "sg:postcode":"03802",
    "sg:province":"Alicante",
    "wof:name":"Gomar Calatayud Salvador",
    "wof:placetype":"venue"
},
  "geometry": {"coordinates":[-0.4840340018,38.6964225769],"type":"Point"}
}