{
  "type": "Feature",
  "properties": {
    "iso:country":"ES",
    "sg:address":"Plaz Hernandez Amores, 3",
    "sg:city":"Catedral",
    "sg:orig_category":"Arquitectos",
    "sg:phone":"+34 968 21 63 68",
    "sg:postcode":"30001",
    "sg:province":"Murcia",
    "wof:name":"Santiuste De Pablos Felix",
    "wof:placetype":"venue"
},
  "geometry": {"coordinates":[-1.1286309958,37.9846725464],"type":"Point"}
}