{
  "type": "Feature",
  "properties": {
    "iso:country":"ES",
    "sg:address":"Calle de Alejandro Ballesteros, 5",
    "sg:city":"Langreo",
    "sg:orig_category":"Farmacias",
    "sg:phone":"+34 985 69 65 85",
    "sg:postcode":"33900",
    "sg:province":"Asturias",
    "wof:name":"Garcia Baraga\u00f1o Ricardo",
    "wof:placetype":"venue"
},
  "geometry": {"coordinates":[-5.682592392,43.2969169617],"type":"Point"}
}