{
  "type": "Feature",
  "properties": {
    "iso:country":"ES",
    "sg:address":"Los Coches, 9",
    "sg:city":"Carrion Calatrava",
    "sg:orig_category":"Plomeros",
    "sg:phone":"+34 926 81 44 44",
    "sg:postcode":"13150",
    "sg:province":"Ciudad Real",
    "wof:name":"Perez Rodriguez Pascual",
    "wof:placetype":"venue"
},
  "geometry": {"coordinates":[-3.8139801025,39.0179367065],"type":"Point"}
}