{
  "type": "Feature",
  "properties": {
    "addr:full":"Ctra Huesca Zoza, Km. 0642,6 Jaca Huesca 22700",
    "addr:postcode":"22700",
    "addr:street":"Ctra Huesca Zoza Km. 0642,6",
    "iso:country":"ES",
    "sg:address":"Ctra Huesca Zoza, Km. 0642,6",
    "sg:city":"Jaca",
    "sg:orig_category":"Distribuci\u00d3n De Petr\u00d3leo Y Derivados",
    "sg:phone":"+34 974 35 58 99",
    "sg:postcode":"22700",
    "sg:province":"Huesca",
    "wof:name":"Repsol Ypf S.a.",
    "wof:placetype":"venue"
},
  "geometry": {"coordinates":[-0.5519520044,42.5658493042],"type":"Point"}
}