{
  "type": "Feature",
  "properties": {
    "addr:full":"Calle de Tresano, S/n Cabez\u00f3n Sal Cantabria 39500",
    "addr:housenumber":"s",
    "addr:postcode":"39500",
    "addr:street":"Calle De Tresano;/ N",
    "iso:country":"ES",
    "sg:address":"Calle de Tresano, S/n",
    "sg:city":"Cabez\u00f3n Sal",
    "sg:orig_category":"Institutos De Belleza",
    "sg:phone":"+34 942 70 05 05",
    "sg:postcode":"39500",
    "sg:province":"Cantabria",
    "wof:name":"Alonso Diaz Andres",
    "wof:placetype":"venue"
},
  "geometry": {"coordinates":[-4.2402448654,43.3070335388],"type":"Point"}
}