{
  "type": "Feature",
  "properties": {
    "iso:country":"ES",
    "sg:address":"Carrer de Montserrat, 64",
    "sg:city":"Martorell",
    "sg:orig_category":"Carnicer\u00cdas, Carnicer\u00cdas",
    "sg:phone":"+34 937 75 03 31",
    "sg:postcode":"08760",
    "sg:province":"Barcelona",
    "wof:name":"Centellas Morral Rosa Maria",
    "wof:placetype":"venue"
},
  "geometry": {"coordinates":[1.9256659746,41.4778518677],"type":"Point"}
}