{
  "type": "Feature",
  "properties": {
    "addr:full":"Calle de Flecha Jover Coll, 9 Son Ferriol Islas Baleares 07198",
    "addr:housenumber":"9",
    "addr:postcode":"07198",
    "addr:street":"Calle De Flecha Jover Coll",
    "iso:country":"ES",
    "sg:address":"Calle de Flecha Jover Coll, 9",
    "sg:city":"Son Ferriol",
    "sg:orig_category":"Inmobiliaria (agencias)",
    "sg:phone":"+34 971 42 80 72",
    "sg:postcode":"07198",
    "sg:province":"Islas Baleares",
    "wof:name":"Andes Publicitat S.l.",
    "wof:placetype":"venue"
},
  "geometry": {"coordinates":[2.7149310112,39.5749206543],"type":"Point"}
}