{
  "type": "Feature",
  "properties": {
    "addr:full":"Avda Ermita (de La), S/n Puebla Alfinden Zaragoza 50171",
    "addr:postcode":"50171",
    "addr:street":"Avda Ermita;La S / N",
    "iso:country":"ES",
    "sg:address":"Avda Ermita (de La), S/n",
    "sg:city":"Puebla Alfinden",
    "sg:orig_category":"Metales (labores, Pulido)",
    "sg:phone":"+34 976 10 77 11",
    "sg:postcode":"50171",
    "sg:province":"Zaragoza",
    "wof:name":"Talleres Uncastillo S. L.",
    "wof:placetype":"venue"
},
  "geometry": {"coordinates":[-0.7473840117,41.630821228],"type":"Point"}
}