{
  "type": "Feature",
  "properties": {
    "iso:country":"ES",
    "sg:address":"Pque Hermanos Millares, 7",
    "sg:city":"Palmas De Gran Canaria",
    "sg:orig_category":"Mercer\u00cda, Lencer\u00cda (al Por Menor)",
    "sg:phone":"+34 928 25 21 14",
    "sg:postcode":"35011",
    "sg:province":"Las Palmas",
    "wof:name":"Sanchez Perez Rafael",
    "wof:placetype":"venue"
},
  "geometry": {"coordinates":[-15.4375810623,28.1157207489],"type":"Point"}
}