{
  "type": "Feature",
  "properties": {
    "iso:country":"ES",
    "sg:address":"Rua Real, 7",
    "sg:city":"Ferrol",
    "sg:orig_category":"Cl\u00cdnicas M\u00c9dicas",
    "sg:phone":"+34 981 37 00 55",
    "sg:postcode":"15402",
    "sg:province":"La Coru\u00f1a",
    "wof:name":"Ferrolterra S.l.",
    "wof:placetype":"venue"
},
  "geometry": {"coordinates":[-8.2287368774,43.4855804443],"type":"Point"}
}