{
  "type": "Feature",
  "properties": {
    "iso:country":"ES",
    "sg:address":"A Malata, S/n",
    "sg:city":"Malata",
    "sg:orig_category":"Asociaciones De Vecinos, Centros De Juventud",
    "sg:phone":"+34 981 33 33 98",
    "sg:postcode":"15405",
    "sg:province":"La Coru\u00f1a",
    "wof:name":"Asociacion Costa Artabra",
    "wof:placetype":"venue"
},
  "geometry": {"coordinates":[-8.2390165329,43.4912567139],"type":"Point"}
}