{
  "type": "Feature",
  "properties": {
    "iso:country":"ES",
    "sg:address":"Artesanos, 37",
    "sg:city":"Boadilla",
    "sg:orig_category":"Mec\u00c1nico Del Autom\u00d3vil",
    "sg:phone":"+34 916 32 07 20",
    "sg:postcode":"28660",
    "sg:province":"Madrid",
    "wof:name":"Espacio Para Automoviles S.l.",
    "wof:placetype":"venue"
},
  "geometry": {"coordinates":[-3.8481481075,40.3921012878],"type":"Point"}
}