{
  "type": "Feature",
  "properties": {
    "addr:full":"Plaz Espa\u00d1a, 4 Alconchel Badajoz 06131",
    "addr:housenumber":"4",
    "addr:postcode":"06131",
    "addr:street":"Plaz Espan\u0303A",
    "iso:country":"ES",
    "sg:address":"Plaz Espa\u00d1a, 4",
    "sg:city":"Alconchel",
    "sg:orig_category":"Bancos",
    "sg:phone":"+34 924 42 01 03",
    "sg:postcode":"06131",
    "sg:province":"Badajoz",
    "wof:name":"Banco Caixa Geral S.a.",
    "wof:placetype":"venue"
},
  "geometry": {"coordinates":[-7.0678539276,38.5165748596],"type":"Point"}
}