{
  "type": "Feature",
  "properties": {
    "iso:country":"ES",
    "sg:address":"Pase Conde De Sepulveda (del), 20",
    "sg:city":"Segovia",
    "sg:orig_category":"Alimentaci\u00d3n General (al Por Menor)",
    "sg:phone":"+34 921 44 33 17",
    "sg:postcode":"40006",
    "sg:province":"Segovia",
    "wof:name":"Distralicon S.l.",
    "wof:placetype":"venue"
},
  "geometry": {"coordinates":[-4.1147689819,40.9382591248],"type":"Point"}
}