{
  "type": "Feature",
  "properties": {
    "addr:full":"Carr Argenteria, 13 Girona Girona 17004",
    "addr:housenumber":"13",
    "addr:postcode":"17004",
    "addr:street":"Carr Argenteria",
    "iso:country":"ES",
    "sg:address":"Carr Argenteria, 13",
    "sg:city":"Girona",
    "sg:orig_category":"Ropa Para Caballeros (al Por Menor)",
    "sg:phone":"+34 972 41 41 22",
    "sg:postcode":"17004",
    "sg:province":"Girona",
    "sg:website":"www.antoniomiro.es",
    "wof:name":"Intima Julia S.l.",
    "wof:placetype":"venue"
},
  "geometry": {"coordinates":[2.8244140148,41.9849815369],"type":"Point"}
}