{
  "type": "Feature",
  "properties": {
    "iso:country":"ES",
    "sg:address":"Calle de Jose Iturbi, 5",
    "sg:city":"Marbella",
    "sg:orig_category":"Carnicer\u00cdas, Carnicer\u00cdas",
    "sg:phone":"+34 952 82 99 73",
    "sg:postcode":"29600",
    "sg:province":"M\u00e1laga",
    "wof:name":"Gavira Sanchez Manuel",
    "wof:placetype":"venue"
},
  "geometry": {"coordinates":[-4.8762040138,36.5140762329],"type":"Point"}
}