{
  "type": "Feature",
  "properties": {
    "iso:country":"ES",
    "sg:address":"Avda Doce De Agosto, 5",
    "sg:city":"Andujar",
    "sg:orig_category":"Abogados",
    "sg:phone":"+34 953 50 31 88",
    "sg:postcode":"23740",
    "sg:province":"Ja\u00e9n",
    "wof:name":"Bellido Mu\u00f1oz Maria Del Carmen",
    "wof:placetype":"venue"
},
  "geometry": {"coordinates":[-4.0547380447,38.0390052795],"type":"Point"}
}