{
  "type": "Feature",
  "properties": {
    "addr:full":"Calle de Antonio Lopez, 138 Madrid Madrid 28026",
    "addr:housenumber":"138",
    "addr:postcode":"28026",
    "addr:street":"Calle De Antonio Lopez",
    "iso:country":"ES",
    "sg:address":"Calle de Antonio Lopez, 138",
    "sg:city":"Madrid",
    "sg:classifiers":[
        {
            "category":"Arts & Performance",
            "subcategory":"Art Gallery",
            "type":"Entertainment"
        }
    ],
    "sg:phone":"+34 915 00 25 34",
    "sg:postcode":"28026",
    "sg:province":"Madrid",
    "sg:tags":[
        "arte",
        "de",
        "galer\u00cdas"
    ],
    "wof:name":"Gomez De Orgaz Valle Miguel Angel",
    "wof:placetype":"venue"
},
  "geometry": {"coordinates":[-3.7030718327,40.3910942078],"type":"Point"}
}