{
  "type": "Feature",
  "properties": {
    "addr:full":"Calle de Camino De La Tejera, Km. 0002,5 Zambrana \u00c1lava 01212",
    "addr:housenumber":"zambrana",
    "addr:postcode":"01212",
    "addr:street":"Calle De Camino De La Tejera Km. 0002,5",
    "iso:country":"ES",
    "sg:address":"Calle de Camino De La Tejera, Km. 0002,5",
    "sg:city":"Zambrana",
    "sg:orig_category":"F\u00c1bricas De Ladrillo Y Tejas",
    "sg:phone":"+34 945 33 70 76",
    "sg:postcode":"01212",
    "sg:province":"\u00c1lava",
    "wof:name":"Bt Espa\u00d1a Compa\u00d1ia De Servicios Globales De Telecomunicaciones S.a.u.",
    "wof:placetype":"venue"
},
  "geometry": {"coordinates":[-2.7121989727,42.6439056396],"type":"Point"}
}