{
  "type": "Feature",
  "properties": {
    "iso:country":"ES",
    "sg:address":"Plaz Calvo Sotelo (de), 1",
    "sg:city":"Braojos",
    "sg:orig_category":"Administraciones Regionales, Departamentales Y Locales",
    "sg:phone":"+34 918 68 04 27",
    "sg:postcode":"28737",
    "sg:province":"Madrid",
    "wof:name":"Ayuntamiento",
    "wof:placetype":"venue"
},
  "geometry": {"coordinates":[-3.6423649788,41.0393371582],"type":"Point"}
}