{
  "type": "Feature",
  "properties": {
    "iso:country":"ES",
    "sg:address":"Calle de Lauaxeta Olerkari, 58",
    "sg:city":"Mungia",
    "sg:orig_category":"Estudios, Instalaci\u00d3n De Climatizaci\u00d3n",
    "sg:phone":"+34 946 74 19 62",
    "sg:postcode":"48100",
    "sg:province":"Vizcaya",
    "wof:name":"Brunnschweiler S. A.",
    "wof:placetype":"venue"
},
  "geometry": {"coordinates":[-2.8594660759,43.3583068848],"type":"Point"}
}