{
  "type": "Feature",
  "properties": {
    "addr:full":"Carrer de Sant Rafael, 8 Pego Alicante 03780",
    "addr:housenumber":"8",
    "addr:postcode":"03780",
    "addr:street":"Carrer De Sant Rafael",
    "iso:country":"ES",
    "sg:address":"Carrer de Sant Rafael, 8",
    "sg:city":"Pego",
    "sg:orig_category":"Cajas Para Embalar",
    "sg:phone":"+34 965 57 21 06",
    "sg:postcode":"03780",
    "sg:province":"Alicante",
    "sg:website":"www.ruralvia.com",
    "wof:name":"Caja Rural Del Mediterraneo Ruralcaja S Coop De Credito",
    "wof:placetype":"venue"
},
  "geometry": {"coordinates":[-0.1148480028,38.841053009],"type":"Point"}
}