{
  "type": "Feature",
  "properties": {
    "iso:country":"ES",
    "sg:address":"Rua Nova, 11",
    "sg:city":"Lugo",
    "sg:orig_category":"\u00d3ptica: Instrumentos (fabricaci\u00d3n)",
    "sg:phone":"+34 982 22 99 19",
    "sg:postcode":"27001",
    "sg:province":"Lugo",
    "wof:name":"Vazquez Lopez Maria Consuelo",
    "wof:placetype":"venue"
},
  "geometry": {"coordinates":[-7.5588331223,43.0105552673],"type":"Point"}
}