{
  "type": "Feature",
  "properties": {
    "iso:country":"ES",
    "sg:address":"Av Mistral, 40",
    "sg:city":"Barcelona",
    "sg:orig_category":"Pod\u00d3logos: Pedicuros",
    "sg:phone":"+34 934 26 65 41",
    "sg:postcode":"08015",
    "sg:province":"Barcelona",
    "wof:name":"Rodicio Heras Eva",
    "wof:placetype":"venue"
},
  "geometry": {"coordinates":[2.1555030346,41.3766212463],"type":"Point"}
}