{
  "type": "Feature",
  "properties": {
    "iso:country":"ES",
    "sg:address":"Avda Martinez Catena, S/n",
    "sg:city":"Ceuta",
    "sg:orig_category":"Distribuci\u00d3n De Petr\u00d3leo Y Derivados",
    "sg:phone":"+34 956 52 15 24",
    "sg:postcode":"51002",
    "sg:province":"Ceuta",
    "wof:name":"Estacion De Servicios El Chorrillo",
    "wof:placetype":"venue"
},
  "geometry": {"coordinates":[-5.3244409561,35.8832550049],"type":"Point"}
}