{
  "type": "Feature",
  "properties": {
    "addr:full":"Plaz General Palacio, 5 Getafe Madrid 28901",
    "addr:housenumber":"5",
    "addr:postcode":"28901",
    "addr:street":"Palacio",
    "iso:country":"ES",
    "sg:address":"Plaz General Palacio, 5",
    "sg:city":"Getafe",
    "sg:orig_category":"Peluquer\u00cdas, Peluquer\u00cda Mixta",
    "sg:phone":"+34 916 82 28 77",
    "sg:postcode":"28901",
    "sg:province":"Madrid",
    "wof:name":"Sanchez Sanchez Telesfora",
    "wof:placetype":"venue"
},
  "geometry": {"coordinates":[-3.7282729149,40.3088989258],"type":"Point"}
}