{
  "type": "Feature",
  "properties": {
    "addr:full":"F Poligono, S/n Soria Soria 42005",
    "addr:postcode":"42005",
    "addr:street":"Poligono S / N",
    "iso:country":"ES",
    "sg:address":"F Poligono, S/n",
    "sg:city":"Soria",
    "sg:orig_category":"Goma: Productos De Consumo, De Hogar, Higi\u00c9nicos (fabricaci\u00d3n)",
    "sg:phone":"+34 975 23 02 52",
    "sg:postcode":"42005",
    "sg:province":"Soria",
    "wof:name":"Woco Iberica S.a.",
    "wof:placetype":"venue"
},
  "geometry": {"coordinates":[-2.4798560143,41.9514465332],"type":"Point"}
}