{
  "type": "Feature",
  "properties": {
    "iso:country":"ES",
    "sg:address":"Poli Industrial Las Casas, S/n",
    "sg:city":"Soria",
    "sg:orig_category":"Puertas Y Portales",
    "sg:phone":"+34 975 23 08 19",
    "sg:postcode":"42005",
    "sg:province":"Soria",
    "wof:name":"Maderas Madurga S.l.",
    "wof:placetype":"venue"
},
  "geometry": {"coordinates":[-2.4691669941,41.7646598816],"type":"Point"}
}