{
  "type": "Feature",
  "properties": {
    "iso:country":"ES",
    "sg:address":"Plaz Julio Verne, 1",
    "sg:city":"Valencia",
    "sg:orig_category":"Caf\u00c9s, Bares, Cervecer\u00cdas",
    "sg:phone":"+34 963 57 66 15",
    "sg:postcode":"46017",
    "sg:province":"Valencia",
    "wof:name":"Pancuenca S.l.",
    "wof:placetype":"venue"
},
  "geometry": {"coordinates":[-0.3912400007,39.4504852295],"type":"Point"}
}