{
  "type": "Feature",
  "properties": {
    "addr:full":"Calle de Camino Real, 156 Gineta Albacete 02110",
    "addr:housenumber":"156",
    "addr:postcode":"02110",
    "addr:street":"Calle De Camino Real",
    "iso:country":"ES",
    "sg:address":"Calle de Camino Real, 156",
    "sg:city":"Gineta",
    "sg:orig_category":"Muebles, Minoristas",
    "sg:phone":"+34 967 27 60 18",
    "sg:postcode":"02110",
    "sg:province":"Albacete",
    "wof:name":"Muebles Rosillo S.l.",
    "wof:placetype":"venue"
},
  "geometry": {"coordinates":[-1.9962018728,39.1131401062],"type":"Point"}
}