{
  "type": "Feature",
  "properties": {
    "addr:full":"Calle de Ceperos, 16 Lucena C\u00f3rdoba 14900",
    "addr:housenumber":"16",
    "addr:postcode":"14900",
    "addr:street":"Calle De Ceperos",
    "iso:country":"ES",
    "sg:address":"Calle de Ceperos, 16",
    "sg:city":"Lucena",
    "sg:orig_category":"Fabricaci\u00d3n De Juguetes Autom\u00c1ticos",
    "sg:phone":"+34 957 51 35 36",
    "sg:postcode":"14900",
    "sg:province":"C\u00f3rdoba",
    "wof:name":"Automaticos Fuengirola S.l.",
    "wof:placetype":"venue"
},
  "geometry": {"coordinates":[-4.480243206,37.4092750549],"type":"Point"}
}