{
  "type": "Feature",
  "properties": {
    "iso:country":"ES",
    "sg:address":"Carr Ferrer I Busquets, 132",
    "sg:city":"Mollerussa",
    "sg:orig_category":"Fabricaci\u00d3n, Importaci\u00d3n, Venta De Material De Telefon\u00cda, Peritelefon\u00cda",
    "sg:phone":"+34 973 71 16 16",
    "sg:postcode":"25230",
    "sg:province":"Lleida",
    "wof:name":"Movicentre Lleida S.l.",
    "wof:placetype":"venue"
},
  "geometry": {"coordinates":[0.8989599943,41.6300582886],"type":"Point"}
}