{
  "type": "Feature",
  "properties": {
    "addr:full":"Calle de Cornisa, 21 Rozas De Madrid Madrid 28230",
    "addr:housenumber":"21",
    "addr:postcode":"28230",
    "addr:street":"Calle De Cornisa",
    "iso:country":"ES",
    "sg:address":"Calle de Cornisa, 21",
    "sg:city":"Rozas De Madrid",
    "sg:orig_category":"Producci\u00d3n, Venta De Productos De Agricultura Biol\u00d3gica",
    "sg:phone":"+34 916 34 54 14",
    "sg:postcode":"28230",
    "sg:province":"Madrid",
    "wof:name":"Pioneer Hi Bred Spain S.l.",
    "wof:placetype":"venue"
},
  "geometry": {"coordinates":[-3.8543686867,40.4797668457],"type":"Point"}
}