{
  "type": "Feature",
  "properties": {
    "addr:full":"Av Andalucia (zi Renault-saez Tejada), 28 Granada Granada 18014",
    "addr:housenumber":"28",
    "addr:postcode":"18014",
    "addr:street":"Av Andalucia Zi Renault-Saez Tejada",
    "iso:country":"ES",
    "sg:address":"Av Andalucia (zi Renault-saez Tejada), 28",
    "sg:city":"Granada",
    "sg:orig_category":"Inform\u00c1tica, Ofim\u00c1tica (estudios, Asesor\u00cda, Ingenier\u00cda, Formaci\u00d3n)",
    "sg:phone":"+34 958 29 64 68",
    "sg:postcode":"18014",
    "sg:province":"Granada",
    "wof:name":"Lopez Cespedes Antonio Miguel",
    "wof:placetype":"venue"
},
  "geometry": {"coordinates":[-3.612719059,37.1884117126],"type":"Point"}
}