{
  "type": "Feature",
  "properties": {
    "iso:country":"ES",
    "sg:address":"Carrer de Berga, 3",
    "sg:city":"Barcelona",
    "sg:orig_category":"Alimentaci\u00d3n General (al Por Menor)",
    "sg:phone":"+34 932 37 92 76",
    "sg:postcode":"08012",
    "sg:province":"Barcelona",
    "wof:name":"Ponsa Bonada Jose",
    "wof:placetype":"venue"
},
  "geometry": {"coordinates":[2.1531479359,41.400302887],"type":"Point"}
}