{
  "type": "Feature",
  "properties": {
    "addr:full":"Calle de Lope De Vega, 13 Alcala Henares Madrid 28805",
    "addr:housenumber":"13",
    "addr:postcode":"28805",
    "addr:street":"Calle De Lope De Vega",
    "iso:country":"ES",
    "sg:address":"Calle de Lope De Vega, 13",
    "sg:city":"Alcala Henares",
    "sg:orig_category":"Peluqueros: De Se\u00d1oras",
    "sg:phone":"+34 918 80 00 96",
    "sg:postcode":"28805",
    "sg:province":"Madrid",
    "wof:name":"Vega Estilistas S.l.",
    "wof:placetype":"venue"
},
  "geometry": {"coordinates":[-3.3599050045,40.4895095825],"type":"Point"}
}