{
  "type": "Feature",
  "properties": {
    "iso:country":"ES",
    "sg:address":"Avda Barcelona (de), 26",
    "sg:city":"Granada",
    "sg:orig_category":"Electrodom\u00c9sticos (al Por Menor)",
    "sg:phone":"+34 958 12 24 31",
    "sg:postcode":"18006",
    "sg:province":"Granada",
    "wof:name":"Carrillo Mi\u00f1an Francisco",
    "wof:placetype":"venue"
},
  "geometry": {"coordinates":[-3.6020441055,37.1619338989],"type":"Point"}
}