{
  "type": "Feature",
  "properties": {
    "addr:full":"Calle de Puentedeume, 11 Coru\u00d1a La Coru\u00f1a 15005",
    "addr:housenumber":"11",
    "addr:postcode":"15005",
    "addr:street":"Calle De Puentedeume;La Corun\u0303A",
    "iso:country":"ES",
    "sg:address":"Calle de Puentedeume, 11",
    "sg:city":"Coru\u00d1a",
    "sg:orig_category":"Poller\u00cda Y Caza (al Por Menor)",
    "sg:phone":"+34 981 24 15 92",
    "sg:postcode":"15005",
    "sg:province":"La Coru\u00f1a",
    "wof:name":"Lopez Pernas Raquel",
    "wof:placetype":"venue"
},
  "geometry": {"coordinates":[-8.4143333435,43.3582267761],"type":"Point"}
}