{
  "type": "Feature",
  "properties": {
    "addr:full":"Av Jaume Iii, 26 Palma Islas Baleares 07012",
    "addr:housenumber":"26",
    "addr:postcode":"07012",
    "addr:street":"Av Jaume Iii",
    "iso:country":"ES",
    "sg:address":"Av Jaume Iii, 26",
    "sg:city":"Palma",
    "sg:orig_category":"Estancos",
    "sg:phone":"+34 971 71 32 24",
    "sg:postcode":"07012",
    "sg:province":"Islas Baleares",
    "wof:name":"Bergas Garau Magdalena",
    "wof:placetype":"venue"
},
  "geometry": {"coordinates":[2.6428170204,39.57264328],"type":"Point"}
}