{
  "type": "Feature",
  "properties": {
    "iso:country":"ES",
    "sg:address":"Cmno Viejo Del Puerto, S/n",
    "sg:city":"Alberquilla",
    "sg:orig_category":"Centros Empresariales",
    "sg:phone":"+34 968 47 15 54",
    "sg:postcode":"30800",
    "sg:province":"Murcia",
    "wof:name":"Comunidad De Regantes De Lorca",
    "wof:placetype":"venue"
},
  "geometry": {"coordinates":[-1.6905640364,37.680557251],"type":"Point"}
}