{
  "type": "Feature",
  "properties": {
    "addr:full":"Calle de Veintiocho De Febrero, 84 Mancha Real Ja\u00e9n 23100",
    "addr:housenumber":"84",
    "addr:postcode":"23100",
    "addr:street":"Calle De Veintiocho De Febrero",
    "iso:country":"ES",
    "sg:address":"Calle de Veintiocho De Febrero, 84",
    "sg:city":"Mancha Real",
    "sg:orig_category":"Reposter\u00cdas",
    "sg:phone":"+34 953 35 07 08",
    "sg:postcode":"23100",
    "sg:province":"Ja\u00e9n",
    "wof:name":"Barranco Gomez Lorenzo",
    "wof:placetype":"venue"
},
  "geometry": {"coordinates":[-3.6112880707,37.7846031189],"type":"Point"}
}