{
  "type": "Feature",
  "properties": {
    "iso:country":"ES",
    "sg:address":"Trva Andalucia, 2",
    "sg:city":"Getafe",
    "sg:orig_category":"Plomeros",
    "sg:phone":"+34 916 96 54 96",
    "sg:postcode":"28903",
    "sg:province":"Madrid",
    "wof:name":"Sanchez Gonzalez Jesus",
    "wof:placetype":"venue"
},
  "geometry": {"coordinates":[-3.7183029652,40.3096618652],"type":"Point"}
}