{
  "type": "Feature",
  "properties": {
    "iso:country":"ES",
    "sg:address":"Real, S/n",
    "sg:city":"Arcones",
    "sg:orig_category":"T\u00c9cnicos Veterinarios",
    "sg:phone":"+34 921 50 41 51",
    "sg:postcode":"40164",
    "sg:province":"Segovia",
    "wof:name":"Santos Sanz Roberto",
    "wof:placetype":"venue"
},
  "geometry": {"coordinates":[-3.7307291031,41.1218681335],"type":"Point"}
}