{
  "type": "Feature",
  "properties": {
    "addr:full":"Carr Nou, 4 Alcoletge Lleida 25660",
    "addr:housenumber":"4",
    "addr:postcode":"25660",
    "addr:street":"Carr Nou",
    "iso:country":"ES",
    "sg:address":"Carr Nou, 4",
    "sg:city":"Alcoletge",
    "sg:orig_category":"Quincaller\u00cda (al Por Menor)",
    "sg:phone":"+34 973 19 70 98",
    "sg:postcode":"25660",
    "sg:province":"Lleida",
    "wof:name":"Ingles Fargues Teresa",
    "wof:placetype":"venue"
},
  "geometry": {"coordinates":[0.694265008,41.649433136],"type":"Point"}
}