{
  "type": "Feature",
  "properties": {
    "iso:country":"ES",
    "sg:address":"Carr Santa Llucia, 19",
    "sg:city":"Villafranca Cid",
    "sg:orig_category":"Plomeros",
    "sg:phone":"+34 964 44 01 51",
    "sg:postcode":"12150",
    "sg:province":"Castell\u00f3n",
    "wof:name":"Mestre Adell Jose Antonio",
    "wof:placetype":"venue"
},
  "geometry": {"coordinates":[-0.2569360137,40.4276580811],"type":"Point"}
}