{
  "type": "Feature",
  "properties": {
    "addr:full":"Calle de Iglesia, 2 Irun Guip\u00f9zcoa 20302",
    "addr:housenumber":"2",
    "addr:postcode":"20302",
    "addr:street":"Calle De Iglesia;Guipu\u0300Zcoa",
    "iso:country":"ES",
    "sg:address":"Calle de Iglesia, 2",
    "sg:city":"Irun",
    "sg:orig_category":"Agencias De Prensa E Informaci\u00d3n",
    "sg:phone":"+34 943 62 05 04",
    "sg:postcode":"20302",
    "sg:province":"Guip\u00f9zcoa",
    "wof:name":"Lecuona Narvarte Juan Antonio",
    "wof:placetype":"venue"
},
  "geometry": {"coordinates":[-1.788203001,43.3390617371],"type":"Point"}
}