{
  "type": "Feature",
  "properties": {
    "addr:full":"Calle de Empedrada, 49 Ecija Sevilla 41400",
    "addr:housenumber":"49",
    "addr:postcode":"41400",
    "addr:street":"Calle De Empedrada",
    "iso:country":"ES",
    "sg:address":"Calle de Empedrada, 49",
    "sg:city":"Ecija",
    "sg:orig_category":"Veh\u00cdculos De Ocasi\u00d3n",
    "sg:phone":"+34 955 90 39 78",
    "sg:postcode":"41400",
    "sg:province":"Sevilla",
    "wof:name":"Reparaciones Suministros Y Servicios Del Sur S.l",
    "wof:placetype":"venue"
},
  "geometry": {"coordinates":[-5.0845890045,37.5365982056],"type":"Point"}
}