{
  "type": "Feature",
  "properties": {
    "iso:country":"ES",
    "sg:address":"Calle de Filipinos, S/n",
    "sg:city":"Palencia",
    "sg:orig_category":"Ense\u00d1anza, Formaci\u00d3n Profesional: Aprendizaje",
    "sg:phone":"+34 979 71 26 78",
    "sg:postcode":"34004",
    "sg:province":"Palencia",
    "wof:name":"Hijas De La Caridad Casa Provincial",
    "wof:placetype":"venue"
},
  "geometry": {"coordinates":[-4.522397995,42.0015335083],"type":"Point"}
}