{
  "type": "Feature",
  "properties": {
    "addr:full":"Ctra Freginals, S/n Amposta Tarragona 43870",
    "addr:housenumber":"s / n",
    "addr:postcode":"43870",
    "addr:street":"Ctra Freginals",
    "iso:country":"ES",
    "sg:address":"Ctra Freginals, S/n",
    "sg:city":"Amposta",
    "sg:orig_category":"Fabricaci\u00d3n De Muebles",
    "sg:phone":"+34 977 70 47 50",
    "sg:postcode":"43870",
    "sg:province":"Tarragona",
    "wof:name":"Eldeco 2000 S.l.",
    "wof:placetype":"venue"
},
  "geometry": {"coordinates":[0.5356559753,40.6872596741],"type":"Point"}
}