{
  "type": "Feature",
  "properties": {
    "addr:full":"Calle de Azalea (de La), 279 Alcobendas Madrid 28109",
    "addr:housenumber":"279",
    "addr:postcode":"28109",
    "addr:street":"Calle De Azalea De La",
    "iso:country":"ES",
    "sg:address":"Calle de Azalea (de La), 279",
    "sg:city":"Alcobendas",
    "sg:orig_category":"Inmobiliaria (agencias)",
    "sg:phone":"+34 916 50 27 35",
    "sg:postcode":"28109",
    "sg:province":"Madrid",
    "wof:name":"Inmobiliaria Vanure S.a.",
    "wof:placetype":"venue"
},
  "geometry": {"coordinates":[-3.6463477612,40.5248031616],"type":"Point"}
}