{
  "type": "Feature",
  "properties": {
    "addr:full":"C/ Corredora, 42 Elche Alicante 03202",
    "addr:housenumber":"42",
    "addr:postcode":"03202",
    "addr:street":"C / Corredora",
    "iso:country":"ES",
    "sg:address":"C/ Corredora, 42",
    "sg:city":"Elche",
    "sg:orig_category":"Ropa Para Se\u00d1oras (al Por Menor)",
    "sg:phone":"+34 966 61 07 99",
    "sg:postcode":"03202",
    "sg:province":"Alicante",
    "sg:website":"www.purificaciongarcia.es",
    "wof:name":"Sociedad Textil Lonia S.a.",
    "wof:placetype":"venue"
},
  "geometry": {"coordinates":[-0.6955249906,38.266254425],"type":"Point"}
}