{
  "type": "Feature",
  "properties": {
    "iso:country":"ES",
    "sg:address":"Pl Mossen Vidal, 1",
    "sg:city":"Manresa",
    "sg:classifiers":[
        {
            "category":"Autos & Motor Vehicles",
            "subcategory":"Automobile Sales",
            "type":"Retail Goods"
        }
    ],
    "sg:phone":"+34 902 15 79 61",
    "sg:postcode":"08242",
    "sg:province":"Barcelona",
    "wof:name":"Autoescola Font S.l.",
    "wof:placetype":"venue"
},
  "geometry": {"coordinates":[1.8255405426,41.7332954407],"type":"Point"}
}