{
  "type": "Feature",
  "properties": {
    "addr:full":"C/ Manuel Carrasco I Formiguera, 1 Tarrega Lleida 25300",
    "addr:housenumber":"1",
    "addr:postcode":"25300",
    "addr:street":"C / Manuel Carrasco I Formiguera",
    "iso:country":"ES",
    "sg:address":"C/ Manuel Carrasco I Formiguera, 1",
    "sg:city":"Tarrega",
    "sg:orig_category":"Agentes Generales De Seguros",
    "sg:phone":"+34 973 31 12 79",
    "sg:postcode":"25300",
    "sg:province":"Lleida",
    "wof:name":"Assessoria Estany Prim S.c.c.l.",
    "wof:placetype":"venue"
},
  "geometry": {"coordinates":[1.1486517191,41.6516342163],"type":"Point"}
}