{
  "type": "Feature",
  "properties": {
    "iso:country":"ES",
    "sg:address":"Calle de Felix De La Torre, 8",
    "sg:city":"Balmaseda",
    "sg:orig_category":"Abogados",
    "sg:phone":"+34 946 10 30 06",
    "sg:postcode":"48800",
    "sg:province":"Vizcaya",
    "wof:name":"Mendez Maeso Lilian",
    "wof:placetype":"venue"
},
  "geometry": {"coordinates":[-3.1967539787,43.1935348511],"type":"Point"}
}