{
  "type": "Feature",
  "properties": {
    "iso:country":"ES",
    "sg:address":"Avda Jose Luis Lasa, 69",
    "sg:city":"Arroyo De La Encomienda",
    "sg:orig_category":"Papeler\u00cdas, Librer\u00cdas",
    "sg:phone":"+34 983 40 71 68",
    "sg:postcode":"47195",
    "sg:province":"Valladolid",
    "wof:name":"Noval Casta\u00f1era Olga",
    "wof:placetype":"venue"
},
  "geometry": {"coordinates":[-4.7912130356,41.6108055115],"type":"Point"}
}