{
  "type": "Feature",
  "properties": {
    "addr:full":"Avda Juan Carlos I, 51 Merida Badajoz 06800",
    "addr:housenumber":"51",
    "addr:postcode":"06800",
    "addr:street":"Avda Juan Carlos I",
    "iso:country":"ES",
    "sg:address":"Avda Juan Carlos I, 51",
    "sg:city":"Merida",
    "sg:classifiers":[
        {
            "category":"Personal",
            "subcategory":"Barber",
            "type":"Services"
        }
    ],
    "sg:phone":"+34 924 30 16 07",
    "sg:postcode":"06800",
    "sg:province":"Badajoz",
    "sg:tags":[
        "caballeros",
        "de",
        "peluqueros"
    ],
    "wof:name":"Naranjo German Adrian",
    "wof:placetype":"venue"
},
  "geometry": {"coordinates":[-6.3356890678,38.9200782776],"type":"Point"}
}