{
  "type": "Feature",
  "properties": {
    "iso:country":"ES",
    "sg:address":"Calle de Benito Vicioso, 14",
    "sg:city":"Calatayud",
    "sg:orig_category":"Centros Comerciales Y Grandes Tiendas",
    "sg:phone":"+34 976 88 65 60",
    "sg:postcode":"50300",
    "sg:province":"Zaragoza",
    "wof:name":"Multiprecios Bilbilitanos S.l.u.",
    "wof:placetype":"venue"
},
  "geometry": {"coordinates":[-1.6405502558,41.3493156433],"type":"Point"}
}