{
  "type": "Feature",
  "properties": {
    "addr:full":"Avgd Pais Valencia, 18 Silla Valencia 46460",
    "addr:housenumber":"18",
    "addr:postcode":"46460",
    "addr:street":"Valencia",
    "iso:country":"ES",
    "sg:address":"Avgd Pais Valencia, 18",
    "sg:city":"Silla",
    "sg:orig_category":"Peluquer\u00cdas, Peluquer\u00cda Mixta",
    "sg:phone":"+34 961 21 31 29",
    "sg:postcode":"46460",
    "sg:province":"Valencia",
    "wof:name":"Peluqueria Silvia San Andres S.l.",
    "wof:placetype":"venue"
},
  "geometry": {"coordinates":[-0.4109809995,39.3661956787],"type":"Point"}
}