{
  "type": "Feature",
  "properties": {
    "addr:full":"Calle de Marsella, 5 Madrid Madrid 28022",
    "addr:housenumber":"5",
    "addr:postcode":"28022",
    "addr:street":"Calle De Marsella",
    "iso:country":"ES",
    "sg:address":"Calle de Marsella, 5",
    "sg:city":"Madrid",
    "sg:orig_category":"Jardiner\u00cdas, Vegetales, Art\u00cdculos De Jardiner\u00cda (al Por Menor)",
    "sg:phone":"+34 917 60 08 84",
    "sg:postcode":"28022",
    "sg:province":"Madrid",
    "wof:name":"Gamez Baldomero Alfonso",
    "wof:placetype":"venue"
},
  "geometry": {"coordinates":[-3.610656023,40.4224472046],"type":"Point"}
}