{
  "type": "Feature",
  "properties": {
    "iso:country":"ES",
    "sg:address":"Calle de Eraso, 15",
    "sg:city":"Madrid",
    "sg:orig_category":"Tiendas De Grano, Frutas Y Legumbres Secas (al Por Menor)",
    "sg:phone":"+34 917 26 34 95",
    "sg:postcode":"28028",
    "sg:province":"Madrid",
    "wof:name":"Ye  Sugin",
    "wof:placetype":"venue"
},
  "geometry": {"coordinates":[-3.6714234352,40.4340019226],"type":"Point"}
}