{
  "type": "Feature",
  "properties": {
    "iso:country":"ES",
    "sg:address":"Carr Dr. Carles Pol I Aleu, 25",
    "sg:city":"Sort",
    "sg:orig_category":"Electromec\u00c1nica",
    "sg:phone":"+34 973 62 10 28",
    "sg:postcode":"25560",
    "sg:province":"Lleida",
    "wof:name":"Arcalis Vidal Albert",
    "wof:placetype":"venue"
},
  "geometry": {"coordinates":[1.1318759918,42.4144554138],"type":"Point"}
}