{
  "type": "Feature",
  "properties": {
    "iso:country":"ES",
    "sg:address":"Calle de Roma, 3",
    "sg:city":"Almazan",
    "sg:orig_category":"Promotores Constructores",
    "sg:phone":"+34 975 30 02 50",
    "sg:postcode":"42200",
    "sg:province":"Soria",
    "wof:name":"Soltero Redondo Manuel",
    "wof:placetype":"venue"
},
  "geometry": {"coordinates":[-2.5344161987,41.481754303],"type":"Point"}
}