{
  "type": "Feature",
  "properties": {
    "iso:country":"ES",
    "sg:address":"Calle de Audiencia, 14",
    "sg:city":"Montiel",
    "sg:orig_category":"Abogados",
    "sg:phone":"+34 926 35 30 99",
    "sg:postcode":"13326",
    "sg:province":"Ciudad Real",
    "wof:name":"Asesoria Y Gestion Arcos S.l.",
    "wof:placetype":"venue"
},
  "geometry": {"coordinates":[-2.8620724678,38.6969528198],"type":"Point"}
}