{
  "type": "Feature",
  "properties": {
    "iso:country":"ES",
    "sg:address":"Calle de San Francisco, 2",
    "sg:city":"Villena",
    "sg:orig_category":"Farmacias",
    "sg:phone":"+34 965 80 21 49",
    "sg:postcode":"03400",
    "sg:province":"Alicante",
    "wof:name":"Belda Juan Maria Jose",
    "wof:placetype":"venue"
},
  "geometry": {"coordinates":[-0.8657870293,38.6305541992],"type":"Point"}
}