{
  "type": "Feature",
  "properties": {
    "addr:full":"Maestre Don Jose, 1 San Javier Murcia 30730",
    "addr:housenumber":"1",
    "addr:postcode":"30730",
    "addr:street":"Jose",
    "iso:country":"ES",
    "sg:address":"Maestre Don Jose, 1",
    "sg:city":"San Javier",
    "sg:orig_category":"Fabricaci\u00d3n De Cortinas Y Visillos",
    "sg:phone":"+34 968 57 14 38",
    "sg:postcode":"30730",
    "sg:province":"Murcia",
    "wof:name":"Ros Saez Paulino",
    "wof:placetype":"venue"
},
  "geometry": {"coordinates":[-0.8377289772,37.8054389954],"type":"Point"}
}