{
  "type": "Feature",
  "properties": {
    "addr:full":"Calle de Fari\u00d1as, 78 Sanlucar De Barrameda C\u00e1diz 11540",
    "addr:housenumber":"78",
    "addr:postcode":"11540",
    "addr:street":"Calle De Farin\u0303As;Ca\u0301Diz",
    "iso:country":"ES",
    "sg:address":"Calle de Fari\u00d1as, 78",
    "sg:city":"Sanlucar De Barrameda",
    "sg:orig_category":"Chapa Y Pintura Veh\u00cdculos",
    "sg:phone":"+34 956 36 22 17",
    "sg:postcode":"11540",
    "sg:province":"C\u00e1diz",
    "wof:name":"Fernandez Nieves Adolfo",
    "wof:placetype":"venue"
},
  "geometry": {"coordinates":[-6.3490219116,36.7803649902],"type":"Point"}
}