{
  "type": "Feature",
  "properties": {
    "iso:country":"ES",
    "sg:address":"Calle de Constitucion, 23",
    "sg:city":"Langreo",
    "sg:orig_category":"Fotocopias, Reprograf\u00cda",
    "sg:phone":"+34 984 18 25 54",
    "sg:postcode":"33900",
    "sg:province":"Asturias",
    "wof:name":"Copisteria Langreo Grafiques La Fueya C.",
    "wof:placetype":"venue"
},
  "geometry": {"coordinates":[-5.6837458611,43.2961120605],"type":"Point"}
}