{
  "type": "Feature",
  "properties": {
    "iso:country":"ES",
    "sg:address":"Calle de Moreal, 8",
    "sg:city":"Bigastro",
    "sg:orig_category":"Electrodom\u00c9sticos (al Por Menor)",
    "sg:phone":"+34 965 35 01 84",
    "sg:postcode":"03380",
    "sg:province":"Alicante",
    "wof:name":"Pamies Escobedo Isabelo",
    "wof:placetype":"venue"
},
  "geometry": {"coordinates":[-0.8978459835,38.0635566711],"type":"Point"}
}