{
  "type": "Feature",
  "properties": {
    "iso:country":"ES",
    "sg:address":"Calle de Hernani, 10",
    "sg:city":"Donostia-san Sebastian",
    "sg:orig_category":"Inmobiliaria (agencias)",
    "sg:phone":"+34 943 42 61 61",
    "sg:postcode":"20004",
    "sg:province":"Guip\u00f9zcoa",
    "wof:name":"Ugarte Lilly Javier",
    "wof:placetype":"venue"
},
  "geometry": {"coordinates":[-1.9836200476,43.3193054199],"type":"Point"}
}