{
  "type": "Feature",
  "properties": {
    "iso:country":"ES",
    "sg:address":"Avda Fundacion Hogar, 13",
    "sg:city":"Santurtzi",
    "sg:orig_category":"Escayola Y Productos De Escayola (fabricaci\u00d3n, Al Por Mayor)",
    "sg:phone":"+34 944 83 52 25",
    "sg:postcode":"48980",
    "sg:province":"Vizcaya",
    "wof:name":"Juan Manuel Cortes Rodriguez",
    "wof:placetype":"venue"
},
  "geometry": {"coordinates":[-3.0526120663,43.3322906494],"type":"Point"}
}