{
  "type": "Feature",
  "properties": {
    "iso:country":"ES",
    "sg:address":"Plaza De Los Pachorros, 1",
    "sg:city":"Luarca",
    "sg:orig_category":"Peluqueros: De Se\u00d1oras",
    "sg:phone":"+34 985 64 03 41",
    "sg:postcode":"33700",
    "sg:province":"Asturias",
    "wof:name":"Suarez Suarez Maria Del Carmen",
    "wof:placetype":"venue"
},
  "geometry": {"coordinates":[-6.5351290703,43.5427055359],"type":"Point"}
}