{
  "type": "Feature",
  "properties": {
    "addr:full":"Carrer de Santes Creus, 11 Reus Tarragona 43205",
    "addr:housenumber":"11",
    "addr:postcode":"43205",
    "addr:street":"Carrer De;Creus",
    "iso:country":"ES",
    "sg:address":"Carrer de Santes Creus, 11",
    "sg:city":"Reus",
    "sg:orig_category":"Venta, Instalaci\u00d3n, Reparaci\u00d3n De Antenas Para Televisi\u00d3n",
    "sg:phone":"+34 977 77 49 79",
    "sg:postcode":"43205",
    "sg:province":"Tarragona",
    "wof:name":"Sevitel S.l.",
    "wof:placetype":"venue"
},
  "geometry": {"coordinates":[1.1055370569,41.1476669312],"type":"Point"}
}