{
  "type": "Feature",
  "properties": {
    "addr:full":"Calle de Trafalgar, 51 Guadalajara Guadalajara 19004",
    "addr:housenumber":"51",
    "addr:postcode":"19004",
    "addr:street":"Calle De Trafalgar",
    "iso:country":"ES",
    "sg:address":"Calle de Trafalgar, 51",
    "sg:city":"Guadalajara",
    "sg:orig_category":"Mensajer\u00cda Express, Portes Internacionales",
    "sg:phone":"+34 949 20 80 20",
    "sg:postcode":"19004",
    "sg:province":"Guadalajara",
    "wof:name":"Transporte Urgente De Guadalajara S.l.",
    "wof:placetype":"venue"
},
  "geometry": {"coordinates":[-3.1896066666,40.6263084412],"type":"Point"}
}