{
  "type": "Feature",
  "properties": {
    "addr:full":"Calle de Zu\u00d1iga, S/n Valladolid Valladolid 47001",
    "addr:housenumber":"s / n",
    "addr:postcode":"47001",
    "addr:street":"Calle De Zun\u0303Iga",
    "iso:country":"ES",
    "sg:address":"Calle de Zu\u00d1iga, S/n",
    "sg:city":"Valladolid",
    "sg:orig_category":"Ropa Y Accesorios",
    "sg:phone":"+34 983 34 39 09",
    "sg:postcode":"47001",
    "sg:province":"Valladolid",
    "wof:name":"Comercios Valladolid S.l.",
    "wof:placetype":"venue"
},
  "geometry": {"coordinates":[-4.730219841,41.6507301331],"type":"Point"}
}