{
  "type": "Feature",
  "properties": {
    "addr:full":"Cromo (p I Calonge), 45 Sevilla Sevilla 41007",
    "addr:housenumber":"45",
    "addr:postcode":"41007",
    "addr:street":"Calonge",
    "iso:country":"ES",
    "sg:address":"Cromo (p I Calonge), 45",
    "sg:city":"Sevilla",
    "sg:orig_category":"Muebles Y Accesorios Para Cocinas Y Cuartos De Ba\u00d1o (al Por Menor)",
    "sg:phone":"+34 954 31 39 01",
    "sg:postcode":"41007",
    "sg:province":"Sevilla",
    "wof:name":"Kocinas Sevilla S.l.l.",
    "wof:placetype":"venue"
},
  "geometry": {"coordinates":[-5.9572339058,37.406463623],"type":"Point"}
}