{
  "type": "Feature",
  "properties": {
    "addr:full":"Avgd Del Cami Nou, Km. 0000,1 Xirivella Valencia 46950",
    "addr:postcode":"46950",
    "addr:street":"Nou Km. 0000,1",
    "iso:country":"ES",
    "sg:address":"Avgd Del Cami Nou, Km. 0000,1",
    "sg:city":"Xirivella",
    "sg:orig_category":"Supermercados Y Hipermercados",
    "sg:phone":"+34 963 83 46 40",
    "sg:postcode":"46950",
    "sg:province":"Valencia",
    "wof:name":"Distribuidora Internacional De Alimentacion S.a.",
    "wof:placetype":"venue"
},
  "geometry": {"coordinates":[-0.4249159992,39.4676742554],"type":"Point"}
}