{
  "type": "Feature",
  "properties": {
    "iso:country":"ES",
    "sg:address":"Calle de Campito, 31",
    "sg:city":"Aracena",
    "sg:orig_category":"Zapatos (al Por Menor)",
    "sg:phone":"+34 959 12 80 27",
    "sg:postcode":"21200",
    "sg:province":"Huelva",
    "sg:website":"www.martacorral.com",
    "wof:name":"Corral Rufino Marta",
    "wof:placetype":"venue"
},
  "geometry": {"coordinates":[-6.5615177155,37.8955039978],"type":"Point"}
}