{
  "type": "Feature",
  "properties": {
    "iso:country":"ES",
    "sg:address":"Pl Catalunya, 40",
    "sg:city":"Mataro",
    "sg:orig_category":"Peluquer\u00cdas, Peluquer\u00cda Mixta",
    "sg:phone":"+34 937 98 62 20",
    "sg:postcode":"08303",
    "sg:province":"Barcelona",
    "wof:name":"Pratdesaba Estragues Maria Dolores",
    "wof:placetype":"venue"
},
  "geometry": {"coordinates":[2.4324729443,41.5389518738],"type":"Point"}
}