{
  "type": "Feature",
  "properties": {
    "iso:country":"ES",
    "sg:address":"Idiazabal Kalea, 18",
    "sg:city":"Urnieta",
    "sg:orig_category":"Electricidad: Instaladores",
    "sg:phone":"+34 943 33 22 07",
    "sg:postcode":"20130",
    "sg:province":"Guip\u00f9zcoa",
    "wof:name":"Elur Instalaciones Electricas S.l.",
    "wof:placetype":"venue"
},
  "geometry": {"coordinates":[-1.9915089607,43.2497253418],"type":"Point"}
}