{
  "type": "Feature",
  "properties": {
    "iso:country":"ES",
    "sg:address":"Calle de Carreteria, 6",
    "sg:city":"Almagro",
    "sg:orig_category":"Molduras, Junquillos, Listones Y Molduras Perforadas",
    "sg:phone":"+34 926 86 09 01",
    "sg:postcode":"13270",
    "sg:province":"Ciudad Real",
    "wof:name":"Bermejo Del Castillo Agustin",
    "wof:placetype":"venue"
},
  "geometry": {"coordinates":[-3.7156889439,38.8874511719],"type":"Point"}
}