{
  "type": "Feature",
  "properties": {
    "iso:country":"ES",
    "sg:address":"Pg Rocamora, 11",
    "sg:city":"Montcada Centre",
    "sg:orig_category":"Doctores En Medicina",
    "sg:phone":"+34 935 64 23 93",
    "sg:postcode":"08110",
    "sg:province":"Barcelona",
    "wof:name":"Gonzalez Benito Maria Del Carmen",
    "wof:placetype":"venue"
},
  "geometry": {"coordinates":[2.1897261143,41.4854393005],"type":"Point"}
}