{
  "type": "Feature",
  "properties": {
    "iso:country":"ES",
    "sg:address":"Avda Rubians, 1",
    "sg:city":"Barbeitos",
    "sg:orig_category":"Negocio De Materiales De Construcci\u00d3n",
    "sg:phone":"+34 986 51 17 46",
    "sg:postcode":"36619",
    "sg:province":"Pontevedra",
    "wof:name":"Intermaco S.l.",
    "wof:placetype":"venue"
},
  "geometry": {"coordinates":[-8.7645044327,42.5797958374],"type":"Point"}
}