{
  "type": "Feature",
  "properties": {
    "iso:country":"ES",
    "sg:address":"Hist. Fdez. Ortega, S/n",
    "sg:city":"Albox",
    "sg:orig_category":"Agentes, Concesionarios Y Sucursales De Veh\u00cdculos",
    "sg:phone":"+34 950 43 01 75",
    "sg:postcode":"04800",
    "sg:province":"Almer\u00eda",
    "wof:name":"Talleres Lopez Y Sanchez S.l.",
    "wof:placetype":"venue"
},
  "geometry": {"coordinates":[-2.1350660324,37.3806228638],"type":"Point"}
}