{
  "type": "Feature",
  "properties": {
    "iso:country":"ES",
    "sg:address":"Ramon Y Cajal, S/n",
    "sg:city":"Larres",
    "sg:orig_category":"Producci\u00d3n, Venta De Productos De Agricultura Biol\u00d3gica",
    "sg:phone":"+34 974 48 22 62",
    "sg:postcode":"22612",
    "sg:province":"Huesca",
    "wof:name":"Sociedad Agraria De Transformacion San Cosme Num 2316",
    "wof:placetype":"venue"
},
  "geometry": {"coordinates":[-0.4052470028,42.5576477051],"type":"Point"}
}