{
  "type": "Feature",
  "properties": {
    "addr:full":"Calle de Cristobal Sanz, 2 Santa Pola Alicante 03130",
    "addr:housenumber":"2",
    "addr:postcode":"03130",
    "addr:street":"Calle De Cristobal Sanz",
    "iso:country":"ES",
    "sg:address":"Calle de Cristobal Sanz, 2",
    "sg:city":"Santa Pola",
    "sg:orig_category":"Heladeros",
    "sg:phone":"+34 965 41 26 80",
    "sg:postcode":"03130",
    "sg:province":"Alicante",
    "wof:name":"Vicedo Linares Edilberto Juan",
    "wof:placetype":"venue"
},
  "geometry": {"coordinates":[-0.5801129937,38.1915054321],"type":"Point"}
}