{
  "type": "Feature",
  "properties": {
    "addr:full":"Carr Cifre, 38 Felanitx Islas Baleares 07200",
    "addr:housenumber":"38",
    "addr:postcode":"07200",
    "addr:street":"Carr Cifre",
    "iso:country":"ES",
    "sg:address":"Carr Cifre, 38",
    "sg:city":"Felanitx",
    "sg:orig_category":"Transportes Por Carretera: Lotes Completos, Mercanc\u00cdas Diversas",
    "sg:phone":"+34 971 58 23 52",
    "sg:postcode":"07200",
    "sg:province":"Islas Baleares",
    "wof:name":"Vicens Ramon Antonio",
    "wof:placetype":"venue"
},
  "geometry": {"coordinates":[3.145772934,39.4655456543],"type":"Point"}
}