{
  "type": "Feature",
  "properties": {
    "iso:country":"ES",
    "sg:address":"Carr Mozart, 57",
    "sg:city":"Badalona",
    "sg:orig_category":"Limpieza Industrial",
    "sg:phone":"+34 933 99 31 02",
    "sg:postcode":"08917",
    "sg:province":"Barcelona",
    "wof:name":"Pardo Cabrera Oscar",
    "wof:placetype":"venue"
},
  "geometry": {"coordinates":[2.2227830887,41.45079422],"type":"Point"}
}