{
  "type": "Feature",
  "properties": {
    "iso:country":"ES",
    "sg:address":"Pl Lluis Companys, S/n",
    "sg:city":"Cornella Llobregat",
    "sg:orig_category":"Aparcamientos (infraestructuras, Accesorios)",
    "sg:phone":"+34 933 77 57 01",
    "sg:postcode":"08940",
    "sg:province":"Barcelona",
    "wof:name":"Parbla S.l.",
    "wof:placetype":"venue"
},
  "geometry": {"coordinates":[2.0711390972,41.352809906],"type":"Point"}
}