{
  "type": "Feature",
  "properties": {
    "addr:full":"Carretera Carbajosa, S/n Villacil Le\u00f3n 24228",
    "addr:housenumber":"s / n",
    "addr:postcode":"24228",
    "addr:street":"Carretera Carbajosa;Leo\u0301N",
    "iso:country":"ES",
    "sg:address":"Carretera Carbajosa, S/n",
    "sg:city":"Villacil",
    "sg:orig_category":"Armas Y Municiones (fabricaci\u00d3n, Al Por Mayor)",
    "sg:phone":"+34 987 21 52 08",
    "sg:postcode":"24228",
    "sg:province":"Le\u00f3n",
    "wof:name":"Excopesa 2000 S.l.",
    "wof:placetype":"venue"
},
  "geometry": {"coordinates":[-5.4931898117,42.5947647095],"type":"Point"}
}