{
  "type": "Feature",
  "properties": {
    "iso:country":"ES",
    "sg:address":"Calle de Victoria, 100",
    "sg:city":"Malaga",
    "sg:orig_category":"Tintes (fabricaci\u00d3n, Al Por Mayor)",
    "sg:phone":"+34 952 25 10 08",
    "sg:postcode":"29012",
    "sg:province":"M\u00e1laga",
    "wof:name":"Limpiezas Aladin S.l.u.",
    "wof:placetype":"venue"
},
  "geometry": {"coordinates":[-4.4141168594,36.7262458801],"type":"Point"}
}