{
  "type": "Feature",
  "properties": {
    "iso:country":"ES",
    "sg:address":"Avda Capuchinos, 4",
    "sg:city":"Castellon",
    "sg:orig_category":"Alimentaci\u00d3n General (al Por Menor)",
    "sg:phone":"+34 964 22 13 18",
    "sg:postcode":"12004",
    "sg:province":"Castell\u00f3n",
    "wof:name":"Alcoceba Llobregat Angel",
    "wof:placetype":"venue"
},
  "geometry": {"coordinates":[-0.0340989009,39.9891166687],"type":"Point"}
}