{
  "type": "Feature",
  "properties": {
    "iso:country":"ES",
    "sg:address":"C/ Ciutat De Sevilla, 2",
    "sg:city":"Paterna",
    "sg:orig_category":"Agentes, Concesionarios Y Sucursales De Veh\u00cdculos",
    "sg:phone":"+34 961 34 15 84",
    "sg:postcode":"46988",
    "sg:province":"Valencia",
    "sg:website":"www.trimoti.es",
    "wof:name":"Primoti S.l.",
    "wof:placetype":"venue"
},
  "geometry": {"coordinates":[-0.4601989985,39.5143203735],"type":"Point"}
}