{
  "type": "Feature",
  "properties": {
    "iso:country":"ES",
    "sg:address":"Calle de Loto, 14",
    "sg:city":"Valladolid",
    "sg:orig_category":"Puertas Y Portales",
    "sg:phone":"+34 983 30 77 60",
    "sg:postcode":"47012",
    "sg:province":"Valladolid",
    "wof:name":"Muelas Alonso Tomas",
    "wof:placetype":"venue"
},
  "geometry": {"coordinates":[-4.6970891953,41.6448516846],"type":"Point"}
}