{
  "type": "Feature",
  "properties": {
    "iso:country":"ES",
    "sg:address":"C/ Daoiz, 3",
    "sg:city":"Elche",
    "sg:orig_category":"Abogados",
    "sg:phone":"+34 965 45 99 76",
    "sg:postcode":"03203",
    "sg:province":"Alicante",
    "wof:name":"Padilla Garcia De Arboleya Alberto",
    "wof:placetype":"venue"
},
  "geometry": {"coordinates":[-0.6934329867,38.2664108276],"type":"Point"}
}