{
  "type": "Feature",
  "properties": {
    "iso:country":"ES",
    "sg:address":"Carr Canigo, 5",
    "sg:city":"Blanes",
    "sg:orig_category":"Aguas (distribuci\u00d3n, Servicios)",
    "sg:phone":"+34 972 33 39 14",
    "sg:postcode":"17300",
    "sg:province":"Girona",
    "wof:name":"Aigues De Blanes S.a.",
    "wof:placetype":"venue"
},
  "geometry": {"coordinates":[2.7834510803,41.6720237732],"type":"Point"}
}