{
  "type": "Feature",
  "properties": {
    "addr:full":"Calle de Gaspar Torrente (santa Isabel), 70 Zaragoza Zaragoza 50016",
    "addr:housenumber":"70",
    "addr:postcode":"50016",
    "addr:street":"Calle De Gaspar Torrente Santa Isabel",
    "iso:country":"ES",
    "sg:address":"Calle de Gaspar Torrente (santa Isabel), 70",
    "sg:city":"Zaragoza",
    "sg:orig_category":"Estudios, Instalaci\u00d3n De Climatizaci\u00d3n",
    "sg:phone":"+34 976 57 20 99",
    "sg:postcode":"50016",
    "sg:province":"Zaragoza",
    "wof:name":"Maher Electrificaciones S.l.",
    "wof:placetype":"venue"
},
  "geometry": {"coordinates":[-0.8264589906,41.6683197021],"type":"Point"}
}