{
  "type": "Feature",
  "properties": {
    "iso:country":"ES",
    "sg:address":"Ptda Pla De La Vallonga, 4",
    "sg:city":"Pla De La Vallonga",
    "sg:orig_category":"Materiales De Aislamiento T\u00c9rmico Y Ac\u00dastico",
    "sg:phone":"+34 965 10 77 19",
    "sg:postcode":"03113",
    "sg:province":"Alicante",
    "sg:website":"www.aislenvas.com",
    "wof:name":"Aislamientos Y Envases S.l.",
    "wof:placetype":"venue"
},
  "geometry": {"coordinates":[-0.5889509916,38.3436164856],"type":"Point"}
}