{
  "type": "Feature",
  "properties": {
    "iso:country":"ES",
    "sg:address":"Calle de Dos De Mayo, 5",
    "sg:city":"Valladolid",
    "sg:orig_category":"Cl\u00cdnicas Dentales",
    "sg:phone":"+34 983 21 86 86",
    "sg:postcode":"47004",
    "sg:province":"Valladolid",
    "wof:name":"Cantero Perez S.l.",
    "wof:placetype":"venue"
},
  "geometry": {"coordinates":[-4.7252545357,41.6479148865],"type":"Point"}
}