{
  "type": "Feature",
  "properties": {
    "iso:country":"ES",
    "sg:address":"Calle de Bordadores, 9",
    "sg:city":"Madrid",
    "sg:orig_category":"Bisuter\u00cda, Joyer\u00cda, Relojer\u00cda (al Por Menor)",
    "sg:phone":"+34 915 48 45 19",
    "sg:postcode":"28013",
    "sg:province":"Madrid",
    "wof:name":"Perez Pareja Antonio",
    "wof:placetype":"venue"
},
  "geometry": {"coordinates":[-3.7073311806,40.4170646667],"type":"Point"}
}