{
  "type": "Feature",
  "properties": {
    "addr:full":"Pla\u00c7 Sant Joan, 7 Lleida Lleida 25007",
    "addr:housenumber":"7",
    "addr:postcode":"25007",
    "addr:street":"Sant Joan",
    "iso:country":"ES",
    "sg:address":"Pla\u00c7 Sant Joan, 7",
    "sg:city":"Lleida",
    "sg:orig_category":"Peluqueros: De Se\u00d1oras",
    "sg:phone":"+34 973 24 87 41",
    "sg:postcode":"25007",
    "sg:province":"Lleida",
    "wof:name":"Domenech Drudis Teresa Maria",
    "wof:placetype":"venue"
},
  "geometry": {"coordinates":[0.6270139813,41.6156463623],"type":"Point"}
}