{
  "type": "Feature",
  "properties": {
    "addr:full":"Calle de Antonio Merchan, 8 Cazalla Sierra Sevilla 41370",
    "addr:housenumber":"8",
    "addr:postcode":"41370",
    "addr:street":"Calle De Antonio Merchan",
    "iso:country":"ES",
    "sg:address":"Calle de Antonio Merchan, 8",
    "sg:city":"Cazalla Sierra",
    "sg:orig_category":"Mercer\u00cda, Lencer\u00cda (al Por Menor)",
    "sg:phone":"+34 954 88 42 11",
    "sg:postcode":"41370",
    "sg:province":"Sevilla",
    "wof:name":"Garcia Martinez Francisco",
    "wof:placetype":"venue"
},
  "geometry": {"coordinates":[-5.7593274117,37.9320068359],"type":"Point"}
}