{
  "type": "Feature",
  "properties": {
    "iso:country":"ES",
    "sg:address":"Pol Ind La Barrena, S/n",
    "sg:city":"Tudela",
    "sg:orig_category":"Fabricaci\u00d3n, Instalaci\u00d3n De Contadores",
    "sg:phone":"+34 948 41 09 92",
    "sg:postcode":"31500",
    "sg:province":"Navarra",
    "wof:name":"Repsol Ypf S.a.",
    "wof:placetype":"venue"
},
  "geometry": {"coordinates":[-1.60295403,42.0619239807],"type":"Point"}
}