{
  "type": "Feature",
  "properties": {
    "iso:country":"ES",
    "sg:address":"Calle de Delgado, 4",
    "sg:city":"Sevilla",
    "sg:orig_category":"Clubes, Asociaciones De Ocio",
    "sg:phone":"+34 954 90 06 24",
    "sg:postcode":"41002",
    "sg:province":"Sevilla",
    "sg:website":"www.games-workshop.es",
    "wof:name":"Games Workshop S.l.",
    "wof:placetype":"venue"
},
  "geometry": {"coordinates":[-5.9946846962,37.396068573],"type":"Point"}
}