{
  "type": "Feature",
  "properties": {
    "addr:full":"Calle de Doctor Esquerdo, 112 Madrid Madrid 28007",
    "addr:housenumber":"112",
    "addr:postcode":"28007",
    "addr:street":"Calle De Doctor Esquerdo",
    "iso:country":"ES",
    "sg:address":"Calle de Doctor Esquerdo, 112",
    "sg:city":"Madrid",
    "sg:orig_category":"Pod\u00d3logos: Pedicuros",
    "sg:phone":"+34 915 01 27 79",
    "sg:postcode":"28007",
    "sg:province":"Madrid",
    "wof:name":"Sanchez Frias Emilio Emeterio",
    "wof:placetype":"venue"
},
  "geometry": {"coordinates":[-3.6701529026,40.4088554382],"type":"Point"}
}