{
  "type": "Feature",
  "properties": {
    "addr:full":"Plaz Leon Y Castillo (de), 3 Santa Brigida Las Palmas 35300",
    "addr:postcode":"35300",
    "addr:street":"Plaz Leon Y Castillo",
    "iso:country":"ES",
    "sg:address":"Plaz Leon Y Castillo (de), 3",
    "sg:city":"Santa Brigida",
    "sg:orig_category":"Iglesia Cat\u00d3lica",
    "sg:phone":"+34 928 64 06 38",
    "sg:postcode":"35300",
    "sg:province":"Las Palmas",
    "wof:name":"Parroquia De Santa Brigida",
    "wof:placetype":"venue"
},
  "geometry": {"coordinates":[-15.5002202988,28.0337238312],"type":"Point"}
}