{
  "type": "Feature",
  "properties": {
    "addr:full":"Avda Andalucia, 1 Guillena Sevilla 41210",
    "addr:housenumber":"1",
    "addr:postcode":"41210",
    "addr:street":"Avda Andalucia",
    "iso:country":"ES",
    "sg:address":"Avda Andalucia, 1",
    "sg:city":"Guillena",
    "sg:orig_category":"Farmacias",
    "sg:phone":"+34 955 78 50 41",
    "sg:postcode":"41210",
    "sg:province":"Sevilla",
    "wof:name":"Algora Castro Maria",
    "wof:placetype":"venue"
},
  "geometry": {"coordinates":[-6.0541110039,37.53931427],"type":"Point"}
}