{
  "type": "Feature",
  "properties": {
    "iso:country":"ES",
    "sg:address":"Carrer de Joaquim Sorolla, 18",
    "sg:city":"Sabadell",
    "sg:orig_category":"Institutos De Belleza",
    "sg:phone":"+34 937 26 24 80",
    "sg:postcode":"08206",
    "sg:province":"Barcelona",
    "wof:name":"Darol Salon De Belleza S.l.",
    "wof:placetype":"venue"
},
  "geometry": {"coordinates":[2.0875720978,41.5486831665],"type":"Point"}
}