{
  "type": "Feature",
  "properties": {
    "iso:country":"ES",
    "sg:address":"Calle de Princesa De Eboli, 7",
    "sg:city":"Pastrana",
    "sg:orig_category":"Quincaller\u00cda (al Por Menor)",
    "sg:phone":"+34 949 37 10 70",
    "sg:postcode":"19100",
    "sg:province":"Guadalajara",
    "wof:name":"R.r.eguizabal S.l.",
    "wof:placetype":"venue"
},
  "geometry": {"coordinates":[-2.9206290245,40.4144630432],"type":"Point"}
}