{
  "type": "Feature",
  "properties": {
    "iso:country":"ES",
    "sg:address":"Pisuerga Del, S/n",
    "sg:city":"Lantadilla",
    "sg:orig_category":"Centros De Educaci\u00d3n Especial",
    "sg:phone":"+34 979 15 22 49",
    "sg:postcode":"34468",
    "sg:province":"Palencia",
    "wof:name":"Eei Alonso Berrugete",
    "wof:placetype":"venue"
},
  "geometry": {"coordinates":[-4.2758622169,42.3399887085],"type":"Point"}
}