{
  "type": "Feature",
  "properties": {
    "iso:country":"ES",
    "sg:address":"Poli Santa Barbara, 15",
    "sg:city":"Utrillas",
    "sg:orig_category":"Asociaciones Humanitarias, De Cooperaci\u00d3n, De Acci\u00d3n Social",
    "sg:phone":"+34 978 75 73 12",
    "sg:postcode":"44760",
    "sg:province":"Teruel",
    "wof:name":"Agrupacion Turolense De Asociaciones De Discapacitados",
    "wof:placetype":"venue"
},
  "geometry": {"coordinates":[-0.857981801,40.8038597107],"type":"Point"}
}