{
  "type": "Feature",
  "properties": {
    "iso:country":"ES",
    "sg:address":"Carrer de Rector Ubach, 29",
    "sg:city":"Barcelona",
    "sg:orig_category":"Bisuter\u00cda, Joyer\u00cda, Relojer\u00cda (al Por Menor)",
    "sg:phone":"+34 932 40 55 92",
    "sg:postcode":"08021",
    "sg:province":"Barcelona",
    "wof:name":"Sunyer Vives Rafael",
    "wof:placetype":"venue"
},
  "geometry": {"coordinates":[2.1433699131,41.397819519],"type":"Point"}
}