{
  "type": "Feature",
  "properties": {
    "iso:country":"ES",
    "sg:address":"Avda General Mola (del), 124",
    "sg:city":"Santa Cruz De Tenerife",
    "sg:orig_category":"Herboristas (al Por Menor)",
    "sg:phone":"+34 922 22 53 92",
    "sg:postcode":"38007",
    "sg:province":"Santa Cruz De Tenerife",
    "wof:name":"Housediet S.l. Sociedad Unipersonal",
    "wof:placetype":"venue"
},
  "geometry": {"coordinates":[-16.2697753906,28.4652233124],"type":"Point"}
}