{
  "type": "Feature",
  "properties": {
    "iso:country":"ES",
    "sg:address":"Plaz Gonzalez Gallarza, 9",
    "sg:city":"Rincon Soto",
    "sg:orig_category":"Cajas De Ahorro",
    "sg:phone":"+34 941 16 00 40",
    "sg:postcode":"26550",
    "sg:province":"La Rioja",
    "sg:website":"wwww.ibercaja.es",
    "wof:name":"Caja De Ahorros Y Monte De Piedad De Zaragoza Aragon Y Rioja",
    "wof:placetype":"venue"
},
  "geometry": {"coordinates":[-1.8486180305,42.2304801941],"type":"Point"}
}