{
  "type": "Feature",
  "properties": {
    "addr:full":"Calle de San Marcial, 3 Irun Guip\u00f9zcoa 20304",
    "addr:housenumber":"3",
    "addr:postcode":"20304",
    "addr:street":"Calle De San Marcial;Guipu\u0300Zcoa",
    "iso:country":"ES",
    "sg:address":"Calle de San Marcial, 3",
    "sg:city":"Irun",
    "sg:orig_category":"Carnicer\u00cdas, Carnicer\u00cdas",
    "sg:phone":"+34 943 62 13 61",
    "sg:postcode":"20304",
    "sg:province":"Guip\u00f9zcoa",
    "wof:name":"Echeverria Irazoqui Jose Luis",
    "wof:placetype":"venue"
},
  "geometry": {"coordinates":[-1.7883050442,43.3384361267],"type":"Point"}
}