{
  "type": "Feature",
  "properties": {
    "addr:full":"Carrer de Major, 20 Ulldecona Tarragona 43550",
    "addr:postcode":"43550",
    "addr:street":"Carrer De Major 20",
    "iso:country":"ES",
    "sg:address":"Carrer de Major, 20",
    "sg:city":"Ulldecona",
    "sg:orig_category":"Mec\u00c1nico Del Autom\u00d3vil",
    "sg:phone":"+34 977 72 01 06",
    "sg:postcode":"43550",
    "sg:province":"Tarragona",
    "wof:name":"Carrascoso Fibla Maria Dolores",
    "wof:placetype":"venue"
},
  "geometry": {"coordinates":[0.4496459961,40.5991249084],"type":"Point"}
}