{
  "type": "Feature",
  "properties": {
    "iso:country":"ES",
    "sg:address":"Calle de Francisco Garcia Gongora, S/n",
    "sg:city":"Almeria",
    "sg:orig_category":"Delegados, Agentes De Tr\u00c1nsito, Auxiliares De Transporte Internacional",
    "sg:phone":"+34 950 24 47 30",
    "sg:postcode":"04006",
    "sg:province":"Almer\u00eda",
    "wof:name":"Redtrans Almeria S.l.",
    "wof:placetype":"venue"
},
  "geometry": {"coordinates":[-2.4491341114,36.8388557434],"type":"Point"}
}