{
  "type": "Feature",
  "properties": {
    "iso:country":"ES",
    "sg:address":"Carr Sant Maurici, S/n",
    "sg:city":"Empuriabrava",
    "sg:orig_category":"Inmobiliaria (agencias)",
    "sg:phone":"+34 972 45 05 20",
    "sg:postcode":"17487",
    "sg:province":"Girona",
    "sg:website":"www.immo-montse.com",
    "wof:name":"Inmobiliaria Montse 1997 S.l",
    "wof:placetype":"venue"
},
  "geometry": {"coordinates":[3.1106040478,42.2554473877],"type":"Point"}
}