{
  "type": "Feature",
  "properties": {
    "iso:country":"ES",
    "sg:address":"Pg Jaume I (de), 20",
    "sg:city":"Salou",
    "sg:orig_category":"Heladeros",
    "sg:phone":"+34 977 38 22 11",
    "sg:postcode":"43840",
    "sg:province":"Tarragona",
    "wof:name":"Jordimar S.a.",
    "wof:placetype":"venue"
},
  "geometry": {"coordinates":[1.136950016,41.0749702454],"type":"Point"}
}