{
  "type": "Feature",
  "properties": {
    "addr:full":"Carrer de Gil Vernet, 11 Hospitalet De L'infant Tarragona 43890",
    "addr:housenumber":"11",
    "addr:postcode":"43890",
    "addr:street":"Carrer De Gil Vernet",
    "iso:country":"ES",
    "sg:address":"Carrer de Gil Vernet, 11",
    "sg:city":"Hospitalet De L'infant",
    "sg:orig_category":"Fabricaci\u00d3n De Su\u00c9ters Y Chalecos De Punto",
    "sg:phone":"+34 977 82 04 47",
    "sg:postcode":"43890",
    "sg:province":"Tarragona",
    "wof:name":"Manufacturas Pigot S.l.",
    "wof:placetype":"venue"
},
  "geometry": {"coordinates":[1.2455840111,41.1117019653],"type":"Point"}
}