{
  "type": "Feature",
  "properties": {
    "addr:full":"Carrer de Velez Rubio, 9 Terrassa Barcelona 08225",
    "addr:housenumber":"9",
    "addr:postcode":"08225",
    "addr:street":"Carrer De Velez Rubio",
    "iso:country":"ES",
    "sg:address":"Carrer de Velez Rubio, 9",
    "sg:city":"Terrassa",
    "sg:orig_category":"Centros Empresariales",
    "sg:phone":"+34 937 33 73 48",
    "sg:postcode":"08225",
    "sg:province":"Barcelona",
    "wof:name":"Sertec S.l.l.",
    "wof:placetype":"venue"
},
  "geometry": {"coordinates":[2.0048079491,41.5793380737],"type":"Point"}
}