{
  "type": "Feature",
  "properties": {
    "addr:full":"Ctra Tf-324-la Perdoma, 32 Perdoma Santa Cruz De Tenerife 38315",
    "addr:housenumber":"32",
    "addr:postcode":"38315",
    "addr:street":"Ctra Tf-324-La Perdoma",
    "iso:country":"ES",
    "sg:address":"Ctra Tf-324-la Perdoma, 32",
    "sg:city":"Perdoma",
    "sg:orig_category":"Agentes, Concesionarios Y Sucursales De Veh\u00cdculos",
    "sg:phone":"+34 922 30 92 25",
    "sg:postcode":"38315",
    "sg:province":"Santa Cruz De Tenerife",
    "wof:name":"Romiar-motor C.b",
    "wof:placetype":"venue"
},
  "geometry": {"coordinates":[-16.5055618286,28.3659114838],"type":"Point"}
}