{
  "type": "Feature",
  "properties": {
    "addr:full":"Calle de San Vicente, 55 Alacant Alicante 03004",
    "addr:housenumber":"55",
    "addr:postcode":"03004",
    "addr:street":"Calle De San Vicente",
    "iso:country":"ES",
    "sg:address":"Calle de San Vicente, 55",
    "sg:city":"Alacant",
    "sg:orig_category":"Sindicatos De Trabajadores",
    "sg:phone":"+34 965 14 45 22",
    "sg:postcode":"03004",
    "sg:province":"Alicante",
    "wof:name":"Sindicato Independiente De La Comunidad Valenciana",
    "wof:placetype":"venue"
},
  "geometry": {"coordinates":[-0.4848279953,38.3508377075],"type":"Point"}
}