{
  "type": "Feature",
  "properties": {
    "iso:country":"ES",
    "sg:address":"C/ Santa Rosa, 47",
    "sg:city":"Alcoi",
    "sg:orig_category":"Venta, Instalaci\u00d3n, Reparaci\u00d3n De Antenas Para Televisi\u00d3n",
    "sg:phone":"+34 965 52 34 94",
    "sg:postcode":"03802",
    "sg:province":"Alicante",
    "sg:website":"www.alcoytronic.com",
    "wof:name":"Vila Jorda Antonio Francisco",
    "wof:placetype":"venue"
},
  "geometry": {"coordinates":[-0.4846349955,38.6931915283],"type":"Point"}
}