{
  "type": "Feature",
  "properties": {
    "addr:full":"Plaz Cabildo (el), 5 Alcala Guadaira Sevilla 41500",
    "addr:postcode":"41500",
    "addr:street":"El",
    "iso:country":"ES",
    "sg:address":"Plaz Cabildo (el), 5",
    "sg:city":"Alcala Guadaira",
    "sg:orig_category":"Carnicer\u00cdas, Carnicer\u00cdas",
    "sg:phone":"+34 955 68 29 52",
    "sg:postcode":"41500",
    "sg:province":"Sevilla",
    "wof:name":"Martagon Verdugo Gardenia",
    "wof:placetype":"venue"
},
  "geometry": {"coordinates":[-5.8398590088,37.3383140564],"type":"Point"}
}