{
  "type": "Feature",
  "properties": {
    "addr:full":"Jose Echegaray, 55 Mairena Alcor Sevilla 41510",
    "addr:housenumber":"55",
    "addr:postcode":"41510",
    "addr:street":"Jose Echegaray",
    "iso:country":"ES",
    "sg:address":"Jose Echegaray, 55",
    "sg:city":"Mairena Alcor",
    "sg:orig_category":"Empresarios",
    "sg:phone":"+34 955 94 32 50",
    "sg:postcode":"41510",
    "sg:province":"Sevilla",
    "wof:name":"Espinosa Mateo Antonio",
    "wof:placetype":"venue"
},
  "geometry": {"coordinates":[-5.7603139877,37.3685302734],"type":"Point"}
}