{
  "type": "Feature",
  "properties": {
    "iso:country":"ES",
    "sg:address":"Ptge Mercader, 11",
    "sg:city":"Barcelona",
    "sg:orig_category":"Museos",
    "sg:phone":"+34 932 16 05 00",
    "sg:postcode":"08008",
    "sg:province":"Barcelona",
    "wof:name":"Fundacio Museu D'historia De La Medicina De Catalunya",
    "wof:placetype":"venue"
},
  "geometry": {"coordinates":[2.1600871086,41.3925704956],"type":"Point"}
}