{
  "type": "Feature",
  "properties": {
    "addr:full":"Barr Llana (la), 34 Arespalditza \u00c1lava 01476",
    "addr:housenumber":"34",
    "addr:postcode":"01476",
    "addr:street":"Llana;Arespalditza A\u0301Lava",
    "iso:country":"ES",
    "sg:address":"Barr Llana (la), 34",
    "sg:city":"Arespalditza",
    "sg:orig_category":"Asilos De Ancianos. Centros Privados",
    "sg:phone":"+34 945 39 90 23",
    "sg:postcode":"01476",
    "sg:province":"\u00c1lava",
    "wof:name":"Residencia De Ancianos Fundacion Alday",
    "wof:placetype":"venue"
},
  "geometry": {"coordinates":[-3.0558218956,43.0860595703],"type":"Point"}
}