{
  "type": "Feature",
  "properties": {
    "iso:country":"ES",
    "sg:address":"Carrer de Major, 27",
    "sg:city":"Palma D'ebre",
    "sg:orig_category":"Cr\u00cda De Animales",
    "sg:phone":"+34 977 81 93 03",
    "sg:postcode":"43370",
    "sg:province":"Tarragona",
    "wof:name":"Gil Mar S.c.p.",
    "wof:placetype":"venue"
},
  "geometry": {"coordinates":[1.2789340019,41.1215934753],"type":"Point"}
}