{
  "type": "Feature",
  "properties": {
    "iso:country":"ES",
    "sg:address":"Calle de Pedro Antonio De Alarcon, 30",
    "sg:city":"Granada",
    "sg:orig_category":"Doctores En Medicina",
    "sg:phone":"+34 958 25 49 61",
    "sg:postcode":"18002",
    "sg:province":"Granada",
    "wof:name":"Revilla Ahumada Luis De La",
    "wof:placetype":"venue"
},
  "geometry": {"coordinates":[-3.6053988934,37.1715736389],"type":"Point"}
}