{
  "type": "Feature",
  "properties": {
    "iso:country":"ES",
    "sg:address":"Calle de Burgo Nuevo, 5",
    "sg:city":"Le\u00f3n",
    "sg:orig_category":"M\u00c9dicos: Cirug\u00cda General",
    "sg:phone":"+34 987 25 04 06",
    "sg:postcode":"24001",
    "sg:province":"Le\u00f3n",
    "wof:name":"Rodriguez Simarro Enrique",
    "wof:placetype":"venue"
},
  "geometry": {"coordinates":[-5.572245121,42.5967407227],"type":"Point"}
}