{
  "type": "Feature",
  "properties": {
    "iso:country":"ES",
    "sg:address":"Ctra. Palamos, Km. 0038,0",
    "sg:city":"Mont-ras",
    "sg:orig_category":"Negocio De Materiales De Construcci\u00d3n",
    "sg:phone":"+34 972 30 21 46",
    "sg:postcode":"17253",
    "sg:province":"Girona",
    "wof:name":"Mercamat S.l.",
    "wof:placetype":"venue"
},
  "geometry": {"coordinates":[3.1464159489,41.9082527161],"type":"Point"}
}