{
  "type": "Feature",
  "properties": {
    "iso:country":"ES",
    "sg:address":"Carrer de Doctor Trueta, 196",
    "sg:city":"Barcelona",
    "sg:orig_category":"Estudios De Cine Y Televisi\u00d3n",
    "sg:phone":"+34 932 25 00 06",
    "sg:postcode":"08005",
    "sg:province":"Barcelona",
    "wof:name":"Plato Ideal S. A.",
    "wof:placetype":"venue"
},
  "geometry": {"coordinates":[2.2026059628,41.397769928],"type":"Point"}
}