{
  "type": "Feature",
  "properties": {
    "addr:full":"Rua Paio Gomez De Soutomaior, 3 Pontevedra Pontevedra 36005",
    "addr:housenumber":"3",
    "addr:postcode":"36005",
    "addr:street":"Rua Paio Gomez De Soutomaior",
    "iso:country":"ES",
    "sg:address":"Rua Paio Gomez De Soutomaior, 3",
    "sg:city":"Pontevedra",
    "sg:orig_category":"Molduras, Junquillos, Listones Y Molduras Perforadas",
    "sg:phone":"+34 986 87 05 26",
    "sg:postcode":"36005",
    "sg:province":"Pontevedra",
    "wof:name":"Carro Souto Manuel",
    "wof:placetype":"venue"
},
  "geometry": {"coordinates":[-8.6403722763,42.4429244995],"type":"Point"}
}