{
  "type": "Feature",
  "properties": {
    "addr:full":"Calle de Toledo, 5 Villasequilla Toledo 45740",
    "addr:housenumber":"5",
    "addr:postcode":"45740",
    "addr:street":"Calle De Toledo",
    "iso:country":"ES",
    "sg:address":"Calle de Toledo, 5",
    "sg:city":"Villasequilla",
    "sg:orig_category":"Cajas Para Embalar",
    "sg:phone":"+34 925 31 01 56",
    "sg:postcode":"45740",
    "sg:province":"Toledo",
    "wof:name":"Caja Rural Provincial De Toledo",
    "wof:placetype":"venue"
},
  "geometry": {"coordinates":[-3.7313840389,39.8772201538],"type":"Point"}
}