{
  "type": "Feature",
  "properties": {
    "iso:country":"ES",
    "sg:address":"Carrer de Cranc, 6",
    "sg:city":"Marines",
    "sg:orig_category":"M\u00c9dicos: Estomatolog\u00cda",
    "sg:phone":"+34 965 78 80 05",
    "sg:postcode":"03700",
    "sg:province":"Alicante",
    "wof:name":"Estudio Dental Medident S.l.",
    "wof:placetype":"venue"
},
  "geometry": {"coordinates":[0.0944750011,38.851020813],"type":"Point"}
}