{
  "type": "Feature",
  "properties": {
    "iso:country":"ES",
    "sg:address":"Calle de Ramon Y Cajal, S/n",
    "sg:city":"Coru\u00d1a",
    "sg:orig_category":"Autob\u00das (explotaci\u00d3n Y Servicios De)",
    "sg:phone":"+34 981 24 91 92",
    "sg:postcode":"15006",
    "sg:province":"La Coru\u00f1a",
    "sg:website":"www.castromil.com",
    "wof:name":"Monfobus S.l.",
    "wof:placetype":"venue"
},
  "geometry": {"coordinates":[-8.4033336639,43.3547935486],"type":"Point"}
}