{
  "type": "Feature",
  "properties": {
    "addr:full":"Carrer de Vic, 18 Barcelona Barcelona 08006",
    "addr:housenumber":"18",
    "addr:postcode":"08006",
    "addr:street":"Carrer De Vic",
    "iso:country":"ES",
    "sg:address":"Carrer de Vic, 18",
    "sg:city":"Barcelona",
    "sg:orig_category":"Cerrajer\u00cda, Ferrallista",
    "sg:phone":"+34 932 18 16 23",
    "sg:postcode":"08006",
    "sg:province":"Barcelona",
    "wof:name":"Union Cerrajera Catalana S.l",
    "wof:placetype":"venue"
},
  "geometry": {"coordinates":[2.1550729275,41.3991279602],"type":"Point"}
}