{
  "type": "Feature",
  "properties": {
    "iso:country":"ES",
    "sg:address":"Luga Villademoros, S/n",
    "sg:city":"Villademoros",
    "sg:orig_category":"Material Y Herramientas Agr\u00cdcolas",
    "sg:phone":"+34 985 64 51 21",
    "sg:postcode":"33788",
    "sg:province":"Asturias",
    "wof:name":"Suarez Cortina Balbino",
    "wof:placetype":"venue"
},
  "geometry": {"coordinates":[-6.3870611191,43.5456581116],"type":"Point"}
}