{
  "type": "Feature",
  "properties": {
    "iso:country":"ES",
    "sg:address":"Avda Camp De Morvedre, 108",
    "sg:city":"Puerto",
    "sg:orig_category":"Almacenes Para Venta: Muebles Y Varios",
    "sg:phone":"+34 962 68 05 96",
    "sg:postcode":"46520",
    "sg:province":"Valencia",
    "wof:name":"Soriano Perez Rafael",
    "wof:placetype":"venue"
},
  "geometry": {"coordinates":[-0.2268439978,39.6643218994],"type":"Point"}
}