{
  "type": "Feature",
  "properties": {
    "iso:country":"ES",
    "sg:address":"Rua De Abaixo, 6",
    "sg:city":"Rianxo",
    "sg:orig_category":"Bisuter\u00cda, Joyer\u00cda, Relojer\u00cda (al Por Menor)",
    "sg:phone":"+34 981 86 62 77",
    "sg:postcode":"15920",
    "sg:province":"La Coru\u00f1a",
    "wof:name":"Blanco Barcala Gonzalo",
    "wof:placetype":"venue"
},
  "geometry": {"coordinates":[-8.8187446594,42.6518592834],"type":"Point"}
}