{
  "type": "Feature",
  "properties": {
    "addr:full":"Avda Olivo, 18 Mora Toledo 45400",
    "addr:housenumber":"18",
    "addr:postcode":"45400",
    "addr:street":"Avda Olivo",
    "iso:country":"ES",
    "sg:address":"Avda Olivo, 18",
    "sg:city":"Mora",
    "sg:orig_category":"Insecticidas, Fumigaci\u00d3n",
    "sg:phone":"+34 925 30 05 00",
    "sg:postcode":"45400",
    "sg:province":"Toledo",
    "wof:name":"Carmona Quintanero Miguel",
    "wof:placetype":"venue"
},
  "geometry": {"coordinates":[-3.7721810341,39.6868057251],"type":"Point"}
}