{
  "type": "Feature",
  "properties": {
    "addr:full":"Calle de San Blas, 47 Vilamarxant Valencia 46191",
    "addr:housenumber":"47",
    "addr:postcode":"46191",
    "addr:street":"Calle De San Blas",
    "iso:country":"ES",
    "sg:address":"Calle de San Blas, 47",
    "sg:city":"Vilamarxant",
    "sg:orig_category":"Florister\u00cdas",
    "sg:phone":"+34 961 65 01 94",
    "sg:postcode":"46191",
    "sg:province":"Valencia",
    "wof:name":"Faus Domingo Angeles",
    "wof:placetype":"venue"
},
  "geometry": {"coordinates":[-0.6247249842,39.5680465698],"type":"Point"}
}