{
  "type": "Feature",
  "properties": {
    "addr:full":"Trva Meicende, 202 Meicende La Coru\u00f1a 15140",
    "addr:housenumber":"202",
    "addr:postcode":"15140",
    "addr:street":"Trva Meicende;La Corun\u0303A",
    "iso:country":"ES",
    "sg:address":"Trva Meicende, 202",
    "sg:city":"Meicende",
    "sg:orig_category":"Chapister\u00cda",
    "sg:phone":"+34 981 27 81 97",
    "sg:postcode":"15140",
    "sg:province":"La Coru\u00f1a",
    "wof:name":"Cancela Rama Jose",
    "wof:placetype":"venue"
},
  "geometry": {"coordinates":[-8.46671772,43.3288497925],"type":"Point"}
}