{
  "type": "Feature",
  "properties": {
    "addr:full":"Calle de Cantabra, 3 Potes Cantabria 39570",
    "addr:housenumber":"3",
    "addr:postcode":"39570",
    "addr:street":"Calle De Cantabra",
    "iso:country":"ES",
    "sg:address":"Calle de Cantabra, 3",
    "sg:city":"Potes",
    "sg:orig_category":"Restaurantes",
    "sg:phone":"+34 942 73 22 01",
    "sg:postcode":"39570",
    "sg:province":"Cantabria",
    "wof:name":"Matesanz Agueros Ignacio",
    "wof:placetype":"venue"
},
  "geometry": {"coordinates":[-4.6237182617,43.1533241272],"type":"Point"}
}