{
  "type": "Feature",
  "properties": {
    "addr:full":"Carrer de Teodora Lamadrid, 41 Barcelona Barcelona 08022",
    "addr:housenumber":"41",
    "addr:postcode":"08022",
    "addr:street":"Carrer De Teodora Lamadrid",
    "iso:country":"ES",
    "sg:address":"Carrer de Teodora Lamadrid, 41",
    "sg:city":"Barcelona",
    "sg:orig_category":"Ense\u00d1anza Variada",
    "sg:phone":"+34 932 11 21 03",
    "sg:postcode":"08022",
    "sg:province":"Barcelona",
    "wof:name":"Rius Serra Pedro",
    "wof:placetype":"venue"
},
  "geometry": {"coordinates":[2.1353330612,41.4074630737],"type":"Point"}
}