{
  "type": "Feature",
  "properties": {
    "addr:full":"Calle de Anselmo Perez De Brito, 26 Santa Cruz Palma Santa Cruz De Tenerife 38700",
    "addr:housenumber":"26",
    "addr:postcode":"38700",
    "addr:street":"Calle De Anselmo Perez De Brito",
    "iso:country":"ES",
    "sg:address":"Calle de Anselmo Perez De Brito, 26",
    "sg:city":"Santa Cruz Palma",
    "sg:orig_category":"Fabricaci\u00d3n De Productos Textiles Sin Tejer",
    "sg:phone":"+34 922 41 14 31",
    "sg:postcode":"38700",
    "sg:province":"Santa Cruz De Tenerife",
    "wof:name":"Triana Triana Carlos Manuel",
    "wof:placetype":"venue"
},
  "geometry": {"coordinates":[-17.7634353638,28.6843128204],"type":"Point"}
}