{
  "type": "Feature",
  "properties": {
    "iso:country":"ES",
    "sg:address":"Carrer de Valencia, 145",
    "sg:city":"Barcelona",
    "sg:orig_category":"Barcos",
    "sg:phone":"+34 934 53 94 38",
    "sg:postcode":"08011",
    "sg:province":"Barcelona",
    "wof:name":"Pujol Poch Daniel",
    "wof:placetype":"venue"
},
  "geometry": {"coordinates":[2.1562199593,41.387550354],"type":"Point"}
}