{
  "type": "Feature",
  "properties": {
    "addr:full":"Plaz Constitucion, 7 Navia Asturias 33710",
    "addr:housenumber":"7",
    "addr:postcode":"33710",
    "addr:street":"Constitucion",
    "iso:country":"ES",
    "sg:address":"Plaz Constitucion, 7",
    "sg:city":"Navia",
    "sg:orig_category":"Perfumer\u00cda (al Por Menor)",
    "sg:phone":"+34 985 63 09 36",
    "sg:postcode":"33710",
    "sg:province":"Asturias",
    "wof:name":"Fernandez Rodriguez Vicenta Maria",
    "wof:placetype":"venue"
},
  "geometry": {"coordinates":[-6.7237291336,43.5387802124],"type":"Point"}
}