{
  "type": "Feature",
  "properties": {
    "iso:country":"ES",
    "sg:address":"Avda El Minero, 44",
    "sg:city":"Gallarta",
    "sg:orig_category":"Peluqueros: De Se\u00d1oras",
    "sg:phone":"+34 946 36 36 69",
    "sg:postcode":"48500",
    "sg:province":"Vizcaya",
    "wof:name":"Bolzoni Brazala Elena",
    "wof:placetype":"venue"
},
  "geometry": {"coordinates":[-3.0733671188,43.3141403198],"type":"Point"}
}