{
  "type": "Feature",
  "properties": {
    "iso:country":"ES",
    "sg:address":"Calle de Jose Ortega Y Gasset, 85",
    "sg:city":"Madrid",
    "sg:orig_category":"Farmacias",
    "sg:phone":"+34 914 01 03 29",
    "sg:postcode":"28006",
    "sg:province":"Madrid",
    "wof:name":"Tenorio Marquez Reyes",
    "wof:placetype":"venue"
},
  "geometry": {"coordinates":[-3.6715333462,40.4297409058],"type":"Point"}
}