{
  "type": "Feature",
  "properties": {
    "addr:full":"Calle de Federica Montseny, 10 Talavera Reina Toledo 45600",
    "addr:housenumber":"10",
    "addr:postcode":"45600",
    "addr:street":"Calle De Federica Montseny",
    "iso:country":"ES",
    "sg:address":"Calle de Federica Montseny, 10",
    "sg:city":"Talavera Reina",
    "sg:orig_category":"Laboratorios Y Cl\u00cdnicas Veterinarias",
    "sg:phone":"+34 925 81 84 54",
    "sg:postcode":"45600",
    "sg:province":"Toledo",
    "wof:name":"Agricentro Talavera S.a.l.",
    "wof:placetype":"venue"
},
  "geometry": {"coordinates":[-4.8486590385,39.9601325989],"type":"Point"}
}