{
  "type": "Feature",
  "properties": {
    "iso:country":"ES",
    "sg:address":"Calle de Pintada, 35",
    "sg:city":"Nerja",
    "sg:orig_category":"Procuradores",
    "sg:phone":"+34 952 52 32 98",
    "sg:postcode":"29780",
    "sg:province":"M\u00e1laga",
    "wof:name":"Leon Fernandez Pedro Angel",
    "wof:placetype":"venue"
},
  "geometry": {"coordinates":[-3.8764090538,36.7472724915],"type":"Point"}
}