{
  "type": "Feature",
  "properties": {
    "iso:country":"ES",
    "sg:address":"Carrer de Manacor, 82",
    "sg:city":"Palma",
    "sg:orig_category":"Electrodom\u00c9sticos (al Por Menor)",
    "sg:phone":"+34 971 24 86 06",
    "sg:postcode":"07007",
    "sg:province":"Islas Baleares",
    "wof:name":"Manzano Castro Soledad",
    "wof:placetype":"venue"
},
  "geometry": {"coordinates":[2.668487072,39.5711708069],"type":"Point"}
}