{
  "type": "Feature",
  "properties": {
    "iso:country":"ES",
    "sg:address":"Calle de Paulino Vicente, 1",
    "sg:city":"Langreo",
    "sg:orig_category":"Ense\u00d1anza Variada",
    "sg:phone":"+34 985 67 45 18",
    "sg:postcode":"33930",
    "sg:province":"Asturias",
    "wof:name":"Garcia Y Fraile C.b.",
    "wof:placetype":"venue"
},
  "geometry": {"coordinates":[-5.6949868202,43.3097915649],"type":"Point"}
}