{
  "type": "Feature",
  "properties": {
    "addr:full":"Avda General Aviles, 32 Valencia Valencia 46015",
    "addr:housenumber":"32",
    "addr:postcode":"46015",
    "addr:street":"Avda General Aviles",
    "iso:country":"ES",
    "sg:address":"Avda General Aviles, 32",
    "sg:city":"Valencia",
    "sg:classifiers":[
        {
            "category":"Banks & Credit Unions",
            "subcategory":"Bureau De Change",
            "type":"Services"
        }
    ],
    "sg:phone":"+34 963 48 50 09",
    "sg:postcode":"46015",
    "sg:province":"Valencia",
    "sg:tags":[
        "organismos",
        "control"
    ],
    "sg:website":"www.valenciaeca.es",
    "wof:name":"Eca Entidad Colaboradora De La Administracion S.a.u.",
    "wof:placetype":"venue"
},
  "geometry": {"coordinates":[-0.3948090076,39.4865264893],"type":"Point"}
}