{
  "type": "Feature",
  "properties": {
    "addr:full":"Av Sra. Magdalena Martorell, 69 Borges Del Camp Tarragona 43350",
    "addr:housenumber":"69",
    "addr:postcode":"43350",
    "addr:street":"Av Sra.;Martorell",
    "iso:country":"ES",
    "sg:address":"Av Sra. Magdalena Martorell, 69",
    "sg:city":"Borges Del Camp",
    "sg:orig_category":"Venta, Instalaci\u00d3n De Calefacci\u00d3n",
    "sg:phone":"+34 977 81 72 03",
    "sg:postcode":"43350",
    "sg:province":"Tarragona",
    "wof:name":"Pares Nolla Ramon",
    "wof:placetype":"venue"
},
  "geometry": {"coordinates":[1.0229049921,41.1683387756],"type":"Point"}
}