{
  "type": "Feature",
  "properties": {
    "iso:country":"ES",
    "sg:address":"Ctra. Villamayor (sis), Km. 0004,7",
    "sg:city":"Zaragoza",
    "sg:orig_category":"Refiner\u00cdas De Petr\u00d3leo",
    "sg:phone":"+34 976 57 31 23",
    "sg:postcode":"50016",
    "sg:province":"Zaragoza",
    "wof:name":"Serviaragon S.a.",
    "wof:placetype":"venue"
},
  "geometry": {"coordinates":[-0.8234919906,41.6667442322],"type":"Point"}
}