{
  "type": "Feature",
  "properties": {
    "iso:country":"ES",
    "sg:address":"Calle de Andres Mellado, 37",
    "sg:city":"Madrid",
    "sg:orig_category":"Pescader\u00cdas (al Por Menor)",
    "sg:phone":"+34 915 44 70 04",
    "sg:postcode":"28015",
    "sg:province":"Madrid",
    "wof:name":"Dimapes S.l.",
    "wof:placetype":"venue"
},
  "geometry": {"coordinates":[-3.7144153118,40.4344291687],"type":"Point"}
}