{
  "type": "Feature",
  "properties": {
    "iso:country":"ES",
    "sg:address":"Calle de Agustin Cabrera Diaz, 5",
    "sg:city":"Santa Cruz De Tenerife",
    "sg:orig_category":"Administradores De Bienes Y Delegados De Comunidades De Propietarios",
    "sg:phone":"+34 922 21 47 53",
    "sg:postcode":"38008",
    "sg:province":"Santa Cruz De Tenerife",
    "wof:name":"Iuris Mundi S.l.v",
    "wof:placetype":"venue"
},
  "geometry": {"coordinates":[-16.2728404999,28.465713501],"type":"Point"}
}