{
  "type": "Feature",
  "properties": {
    "addr:full":"Geltoki Bidea, 11 Zarautz Guip\u00f9zcoa 20800",
    "addr:housenumber":"11",
    "addr:postcode":"20800",
    "addr:street":"Geltoki Bidea;Guipu\u0300Zcoa",
    "iso:country":"ES",
    "sg:address":"Geltoki Bidea, 11",
    "sg:city":"Zarautz",
    "sg:orig_category":"Tapicer\u00cdas",
    "sg:phone":"+34 943 13 04 03",
    "sg:postcode":"20800",
    "sg:province":"Guip\u00f9zcoa",
    "wof:name":"Elorza Larrabeiti Genaro",
    "wof:placetype":"venue"
},
  "geometry": {"coordinates":[-2.1728310585,43.2846412659],"type":"Point"}
}