{
  "type": "Feature",
  "properties": {
    "addr:full":"Calle de Sierra De Grazalema, 31 Malaga M\u00e1laga 29016",
    "addr:housenumber":"31",
    "addr:postcode":"29016",
    "addr:street":"Calle De Sierra De Grazalema;Ma\u0301Laga",
    "iso:country":"ES",
    "sg:address":"Calle de Sierra De Grazalema, 31",
    "sg:city":"Malaga",
    "sg:orig_category":"Arquitectos",
    "sg:phone":"+34 952 60 09 88",
    "sg:postcode":"29016",
    "sg:province":"M\u00e1laga",
    "wof:name":"Diaz Guerrero Miguel Angel",
    "wof:placetype":"venue"
},
  "geometry": {"coordinates":[-4.4029679298,36.7307739258],"type":"Point"}
}