{
  "type": "Feature",
  "properties": {
    "iso:country":"ES",
    "sg:address":"Plaz Parque De Capuchinos, 2",
    "sg:city":"Jerez De La Frontera",
    "sg:orig_category":"Pescader\u00cdas (al Por Menor)",
    "sg:phone":"+34 956 18 23 95",
    "sg:postcode":"11405",
    "sg:province":"C\u00e1diz",
    "wof:name":"Chulian Iba\u00f1ez Rafael",
    "wof:placetype":"venue"
},
  "geometry": {"coordinates":[-6.130821228,36.6930465698],"type":"Point"}
}