{
  "type": "Feature",
  "properties": {
    "iso:country":"ES",
    "sg:address":"Poligono De Las Arobias, S/n",
    "sg:city":"Aviles",
    "sg:orig_category":"Agentes, Concesionarios Y Sucursales De Camiones Y Veh\u00cdculos Industriales",
    "sg:phone":"+34 985 56 66 46",
    "sg:postcode":"33409",
    "sg:province":"Asturias",
    "wof:name":"Vehiculos Industriales De Aviles S. A.",
    "wof:placetype":"venue"
},
  "geometry": {"coordinates":[-5.9211349487,43.5584754944],"type":"Point"}
}