{
  "type": "Feature",
  "properties": {
    "addr:full":"Calle de Aire, S/n Antas Almer\u00eda 04628",
    "addr:postcode":"04628",
    "addr:street":"Calle De Aire S / N",
    "iso:country":"ES",
    "sg:address":"Calle de Aire, S/n",
    "sg:city":"Antas",
    "sg:orig_category":"Centros De Educaci\u00d3n Especial",
    "sg:phone":"+34 950 45 35 37",
    "sg:postcode":"04628",
    "sg:province":"Almer\u00eda",
    "wof:name":"Delegacion Provincial De La Consejeria De Educacion Y Ciencia",
    "wof:placetype":"venue"
},
  "geometry": {"coordinates":[-1.9179575443,37.245174408],"type":"Point"}
}