{
  "type": "Feature",
  "properties": {
    "iso:country":"ES",
    "sg:address":"Avda Chamberi, 33",
    "sg:city":"Salas",
    "sg:orig_category":"Promotores Constructores",
    "sg:phone":"+34 985 83 11 12",
    "sg:postcode":"33860",
    "sg:province":"Asturias",
    "wof:name":"Salas U.t.e.",
    "wof:placetype":"venue"
},
  "geometry": {"coordinates":[-6.2549891472,43.4073295593],"type":"Point"}
}