{
  "type": "Feature",
  "properties": {
    "iso:country":"ES",
    "sg:address":"Carrer de Ruiz De Padron, 26",
    "sg:city":"Barcelona",
    "sg:orig_category":"T\u00c9cnicos Veterinarios",
    "sg:phone":"+34 934 56 06 84",
    "sg:postcode":"08026",
    "sg:province":"Barcelona",
    "wof:name":"Vilaret Reig Ramon",
    "wof:placetype":"venue"
},
  "geometry": {"coordinates":[2.18343997,41.4135780334],"type":"Point"}
}