{
  "type": "Feature",
  "properties": {
    "addr:full":"Calle de Electricistas, 7 Villaviciosa Odon Madrid 28670",
    "addr:housenumber":"7",
    "addr:postcode":"28670",
    "addr:street":"Calle De Electricistas;Odon",
    "iso:country":"ES",
    "sg:address":"Calle de Electricistas, 7",
    "sg:city":"Villaviciosa Odon",
    "sg:orig_category":"Audiovisuales (producci\u00d3n, Edici\u00d3n, Realizaci\u00d3n)",
    "sg:phone":"+34 916 65 75 34",
    "sg:postcode":"28670",
    "sg:province":"Madrid",
    "wof:name":"Arbol Producciones S.a.",
    "wof:placetype":"venue"
},
  "geometry": {"coordinates":[-3.907186985,40.3485145569],"type":"Point"}
}