{
  "type": "Feature",
  "properties": {
    "addr:full":"Calle de Jesus Fernandez Duro, 1 Langreo Asturias 33930",
    "addr:housenumber":"1",
    "addr:postcode":"33930",
    "addr:street":"Calle De Jesus Fernandez Duro",
    "iso:country":"ES",
    "sg:address":"Calle de Jesus Fernandez Duro, 1",
    "sg:city":"Langreo",
    "sg:orig_category":"Electrodom\u00c9sticos (al Por Menor)",
    "sg:phone":"+34 985 68 36 15",
    "sg:postcode":"33930",
    "sg:province":"Asturias",
    "wof:name":"Electrodomesticos Jose Luis Diaz S.l.",
    "wof:placetype":"venue"
},
  "geometry": {"coordinates":[-5.6889190674,43.3080101013],"type":"Point"}
}