{
  "type": "Feature",
  "properties": {
    "addr:full":"Ctra Torrecilla (p I La Paz), S/n Maracena Granada 18200",
    "addr:housenumber":"s / n",
    "addr:postcode":"18200",
    "addr:street":"Ctra Torrecilla P;La Paz",
    "iso:country":"ES",
    "sg:address":"Ctra Torrecilla (p I La Paz), S/n",
    "sg:city":"Maracena",
    "sg:orig_category":"Negocio De Madera",
    "sg:phone":"+34 958 41 02 43",
    "sg:postcode":"18200",
    "sg:province":"Granada",
    "wof:name":"Jose Bullejos Blanca Y Otro Cdad",
    "wof:placetype":"venue"
},
  "geometry": {"coordinates":[-3.63884902,37.2039909363],"type":"Point"}
}