{
  "type": "Feature",
  "properties": {
    "iso:country":"ES",
    "sg:address":"Calle de Santa Catalina, 1",
    "sg:city":"Urda",
    "sg:orig_category":"Arquitectos",
    "sg:phone":"+34 925 47 20 45",
    "sg:postcode":"45480",
    "sg:province":"Toledo",
    "wof:name":"Debeza Tapia Manuel",
    "wof:placetype":"venue"
},
  "geometry": {"coordinates":[-3.7164540291,39.4122848511],"type":"Point"}
}