{
  "type": "Feature",
  "properties": {
    "iso:country":"ES",
    "sg:address":"Calle de Manuel Alonso Perez, 15",
    "sg:city":"Gondomar",
    "sg:orig_category":"Fisioterapia",
    "sg:phone":"+34 986 38 91 05",
    "sg:postcode":"36380",
    "sg:province":"Pontevedra",
    "wof:name":"Berride Soto Irene",
    "wof:placetype":"venue"
},
  "geometry": {"coordinates":[-8.7605190277,42.1122817993],"type":"Point"}
}