{
  "type": "Feature",
  "properties": {
    "iso:country":"ES",
    "sg:address":"Calle de Monovar, 4",
    "sg:city":"Pinoso",
    "sg:orig_category":"Empresas De Carpinter\u00cda De Madera",
    "sg:phone":"+34 965 47 83 10",
    "sg:postcode":"03650",
    "sg:province":"Alicante",
    "wof:name":"Alejandro Santiago S.l.",
    "wof:placetype":"venue"
},
  "geometry": {"coordinates":[-1.0378141403,38.4035873413],"type":"Point"}
}