{
  "type": "Feature",
  "properties": {
    "addr:full":"Avda Joaquin Costa, 78 Alcampell Huesca 22560",
    "addr:housenumber":"78",
    "addr:postcode":"22560",
    "addr:street":"Avda Joaquin Costa",
    "iso:country":"ES",
    "sg:address":"Avda Joaquin Costa, 78",
    "sg:city":"Alcampell",
    "sg:orig_category":"Venta, Alquiler De Toldos",
    "sg:phone":"+34 974 42 14 88",
    "sg:postcode":"22560",
    "sg:province":"Huesca",
    "wof:name":"Cubiertas Fabian S.l.",
    "wof:placetype":"venue"
},
  "geometry": {"coordinates":[0.4360029995,41.9062690735],"type":"Point"}
}