{
  "type": "Feature",
  "properties": {
    "addr:full":"Pase Constitucion De (la), 17 Arnedo La Rioja 26580",
    "addr:postcode":"26580",
    "addr:street":"Arnedo;Rioja",
    "iso:country":"ES",
    "sg:address":"Pase Constitucion De (la), 17",
    "sg:city":"Arnedo",
    "sg:orig_category":"Quincaller\u00cda (al Por Menor)",
    "sg:phone":"+34 941 38 04 73",
    "sg:postcode":"26580",
    "sg:province":"La Rioja",
    "wof:name":"Electricidad Y Ferreteria Hernandez S.l.",
    "wof:placetype":"venue"
},
  "geometry": {"coordinates":[-2.0974490643,42.2273826599],"type":"Point"}
}