{
  "type": "Feature",
  "properties": {
    "iso:country":"ES",
    "sg:address":"Carrer de Lepant, 388",
    "sg:city":"Barcelona",
    "sg:orig_category":"Inform\u00c1tica: Consultores",
    "sg:phone":"+34 934 35 00 95",
    "sg:postcode":"08025",
    "sg:province":"Barcelona",
    "wof:name":"Elkassem Balquis Nemer",
    "wof:placetype":"venue"
},
  "geometry": {"coordinates":[2.1701300144,41.4096298218],"type":"Point"}
}