{
  "type": "Feature",
  "properties": {
    "addr:full":"Plaz Espa\u00d1a, 3 Solana De Los Barros Badajoz 06209",
    "addr:housenumber":"3",
    "addr:postcode":"06209",
    "addr:street":"Plaz Espan\u0303A;Barros",
    "iso:country":"ES",
    "sg:address":"Plaz Espa\u00d1a, 3",
    "sg:city":"Solana De Los Barros",
    "sg:orig_category":"Agentes Generales De Seguros",
    "sg:phone":"+34 924 68 40 67",
    "sg:postcode":"06209",
    "sg:province":"Badajoz",
    "wof:name":"Sanchez Becerra Jorge Manuel",
    "wof:placetype":"venue"
},
  "geometry": {"coordinates":[-6.5375151634,38.7246551514],"type":"Point"}
}