{
  "type": "Feature",
  "properties": {
    "iso:country":"ES",
    "sg:address":"Calle de Alfonso Xii, 35",
    "sg:city":"Mostoles",
    "sg:orig_category":"Ropa Para Beb\u00c9s Y Ni\u00d1os (confecci\u00d3n, Al Por Mayor)",
    "sg:phone":"+34 916 64 04 69",
    "sg:postcode":"28934",
    "sg:province":"Madrid",
    "wof:name":"Julio Fernandez Sabio Y Otro C.b.",
    "wof:placetype":"venue"
},
  "geometry": {"coordinates":[-3.8743617535,40.3177223206],"type":"Point"}
}