{
  "type": "Feature",
  "properties": {
    "addr:full":"Calle de Pilar (el), 12 Santa Cruz De Tenerife Santa Cruz De Tenerife 38002",
    "addr:postcode":"38002",
    "addr:street":"Calle De Pilar El",
    "iso:country":"ES",
    "sg:address":"Calle de Pilar (el), 12",
    "sg:city":"Santa Cruz De Tenerife",
    "sg:orig_category":"Trajes Y Adornos De Boda (confecci\u00d3n, Al Por Menor)",
    "sg:phone":"+34 922 28 79 44",
    "sg:postcode":"38002",
    "sg:province":"Santa Cruz De Tenerife",
    "wof:name":"Suarez Perez Clara Elisa",
    "wof:placetype":"venue"
},
  "geometry": {"coordinates":[-16.2515869141,28.4690647125],"type":"Point"}
}