{
  "type": "Feature",
  "properties": {
    "iso:country":"ES",
    "sg:address":"Calle de Puerto De Cotos, 8",
    "sg:city":"Madrid",
    "sg:orig_category":"Alimentaci\u00d3n General (al Por Menor)",
    "sg:phone":"+34 914 39 53 65",
    "sg:postcode":"28038",
    "sg:province":"Madrid",
    "wof:name":"Abarquero Encinas Felix",
    "wof:placetype":"venue"
},
  "geometry": {"coordinates":[-3.658688,40.400692],"type":"Point"}
}