{
  "type": "Feature",
  "properties": {
    "addr:full":"Carr Montnegre, 23 Girona Girona 17006",
    "addr:housenumber":"23",
    "addr:postcode":"17006",
    "addr:street":"Carr Montnegre",
    "iso:country":"ES",
    "sg:address":"Carr Montnegre, 23",
    "sg:city":"Girona",
    "sg:orig_category":"Empresas De Carpinter\u00cda",
    "sg:phone":"+34 972 24 00 48",
    "sg:postcode":"17006",
    "sg:province":"Girona",
    "wof:name":"Carrillo Ag\u00fcera Pedro",
    "wof:placetype":"venue"
},
  "geometry": {"coordinates":[2.8060588837,41.9753189087],"type":"Point"}
}