{
  "type": "Feature",
  "properties": {
    "iso:country":"ES",
    "sg:address":"Carrer de Casanova, 55",
    "sg:city":"Barcelona",
    "sg:orig_category":"Sociedades, Compa\u00d1\u00cdas Aseguradoras",
    "sg:phone":"+34 934 51 07 87",
    "sg:postcode":"08011",
    "sg:province":"Barcelona",
    "sg:website":"www.brokers88.es",
    "wof:name":"Dotstation S.l.",
    "wof:placetype":"venue"
},
  "geometry": {"coordinates":[2.1596450806,41.3845901489],"type":"Point"}
}