{
  "type": "Feature",
  "properties": {
    "addr:full":"Calle de Sangenis, 37 Zaragoza Zaragoza 50010",
    "addr:housenumber":"37",
    "addr:postcode":"50010",
    "addr:street":"Calle De Sangenis",
    "iso:country":"ES",
    "sg:address":"Calle de Sangenis, 37",
    "sg:city":"Zaragoza",
    "sg:orig_category":"Inform\u00c1tica: Material Y Suministros",
    "sg:phone":"+34 976 53 60 93",
    "sg:postcode":"50010",
    "sg:province":"Zaragoza",
    "wof:name":"Comercial Rosa-mari S.a.",
    "wof:placetype":"venue"
},
  "geometry": {"coordinates":[-0.9034579992,41.6507720947],"type":"Point"}
}