{
  "type": "Feature",
  "properties": {
    "addr:full":"Ptda Tosal, 35 Denia Alicante 03700",
    "addr:housenumber":"35",
    "addr:postcode":"03700",
    "addr:street":"Ptda Tosal",
    "iso:country":"ES",
    "sg:address":"Ptda Tosal, 35",
    "sg:city":"Denia",
    "sg:orig_category":"Importaci\u00d3n",
    "sg:phone":"+34 966 43 51 76",
    "sg:postcode":"03700",
    "sg:province":"Alicante",
    "wof:name":"Transavella S.a.",
    "wof:placetype":"venue"
},
  "geometry": {"coordinates":[0.1039630026,38.8354949951],"type":"Point"}
}