{
  "type": "Feature",
  "properties": {
    "addr:full":"Calle de Escuelas, 26 Huetor-tajar Granada 18360",
    "addr:housenumber":"26",
    "addr:postcode":"18360",
    "addr:street":"Calle De Escuelas",
    "iso:country":"ES",
    "sg:address":"Calle de Escuelas, 26",
    "sg:city":"Huetor-tajar",
    "sg:classifiers":[
        {
            "category":"Taxi",
            "type":"Transportation"
        }
    ],
    "sg:phone":"+34 958 33 34 11",
    "sg:postcode":"18360",
    "sg:province":"Granada",
    "wof:name":"Salas Perez Pedro",
    "wof:placetype":"venue"
},
  "geometry": {"coordinates":[-4.0510101318,37.1998596191],"type":"Point"}
}