{
  "type": "Feature",
  "properties": {
    "iso:country":"ES",
    "sg:address":"Americas, 28",
    "sg:city":"Maspalomas",
    "sg:orig_category":"Muebles Y Accesorios Para Cocinas Y Cuartos De Ba\u00d1o (al Por Menor)",
    "sg:phone":"+34 928 14 07 64",
    "sg:postcode":"35100",
    "sg:province":"Las Palmas",
    "wof:name":"Garcia Perera Juan Carlos",
    "wof:placetype":"venue"
},
  "geometry": {"coordinates":[-15.5830888748,27.7700748444],"type":"Point"}
}