{
  "type": "Feature",
  "properties": {
    "iso:country":"ES",
    "sg:address":"Calle de Iglesia, 12",
    "sg:city":"Tiemblo",
    "sg:orig_category":"Supermercados Y Hipermercados",
    "sg:phone":"+34 918 62 51 53",
    "sg:postcode":"05270",
    "sg:province":"\u00c1vila",
    "wof:name":"Heralor S.r.l.",
    "wof:placetype":"venue"
},
  "geometry": {"coordinates":[-4.5064268112,40.4125747681],"type":"Point"}
}