{
  "type": "Feature",
  "properties": {
    "addr:full":"Ctra Aranda, 14 Illueca Zaragoza 50250",
    "addr:housenumber":"14",
    "addr:postcode":"50250",
    "addr:street":"Ctra Aranda",
    "iso:country":"ES",
    "sg:address":"Ctra Aranda, 14",
    "sg:city":"Illueca",
    "sg:orig_category":"\u00d3ptica: Instrumentos (fabricaci\u00d3n)",
    "sg:phone":"+34 976 82 23 39",
    "sg:postcode":"50250",
    "sg:province":"Zaragoza",
    "wof:name":"Alnarpa S.l.",
    "wof:placetype":"venue"
},
  "geometry": {"coordinates":[-1.6297762394,41.537322998],"type":"Point"}
}