{
  "type": "Feature",
  "properties": {
    "addr:full":"Calle de Jeronima Belver, 6 Almeria Almer\u00eda 04006",
    "addr:housenumber":"6",
    "addr:postcode":"04006",
    "addr:street":"Calle De Jeronima Belver",
    "iso:country":"ES",
    "sg:address":"Calle de Jeronima Belver, 6",
    "sg:city":"Almeria",
    "sg:orig_category":"Almacenes Frigor\u00cdficos",
    "sg:phone":"+34 950 62 22 57",
    "sg:postcode":"04006",
    "sg:province":"Almer\u00eda",
    "wof:name":"Refrigeraciones Santiago S.l.l.",
    "wof:placetype":"venue"
},
  "geometry": {"coordinates":[-2.4473791122,36.8428916931],"type":"Point"}
}