{
  "type": "Feature",
  "properties": {
    "addr:full":"Calle de Ave Del Paraiso, 6 Puerto De Santa Maria C\u00e1diz 11500",
    "addr:housenumber":"6",
    "addr:postcode":"11500",
    "addr:street":"Calle De Ave Del Paraiso;Ca\u0301Diz",
    "iso:country":"ES",
    "sg:address":"Calle de Ave Del Paraiso, 6",
    "sg:city":"Puerto De Santa Maria",
    "sg:orig_category":"Ense\u00d1anza: Idiomas",
    "sg:phone":"+34 956 87 19 26",
    "sg:postcode":"11500",
    "sg:province":"C\u00e1diz",
    "sg:website":"www.atschool.net",
    "wof:name":"Trinity School S.l.",
    "wof:placetype":"venue"
},
  "geometry": {"coordinates":[-6.2338790894,36.5949516296],"type":"Point"}
}