{
  "type": "Feature",
  "properties": {
    "iso:country":"ES",
    "sg:address":"Carrer de Manxa, 2",
    "sg:city":"Barcelona",
    "sg:orig_category":"Prot\u00c9sicos Dentales",
    "sg:phone":"+34 933 57 63 23",
    "sg:postcode":"08032",
    "sg:province":"Barcelona",
    "wof:name":"Taboada Castro Francisco Javier",
    "wof:placetype":"venue"
},
  "geometry": {"coordinates":[2.1538031101,41.4211616516],"type":"Point"}
}