{
  "type": "Feature",
  "properties": {
    "addr:full":"Carrer de Congost, 28 Barcelona Barcelona 08024",
    "addr:housenumber":"28",
    "addr:postcode":"08024",
    "addr:street":"Carrer De Congost",
    "iso:country":"ES",
    "sg:address":"Carrer de Congost, 28",
    "sg:city":"Barcelona",
    "sg:orig_category":"Electromedicina: Equipo",
    "sg:phone":"+34 932 85 39 90",
    "sg:postcode":"08024",
    "sg:province":"Barcelona",
    "wof:name":"Sonmedica S.a.",
    "wof:placetype":"venue"
},
  "geometry": {"coordinates":[2.1588480473,41.406337738],"type":"Point"}
}