{
  "type": "Feature",
  "properties": {
    "addr:full":"Cami Santa Creu D'olorda, 23 Molins Rei Barcelona 08750",
    "addr:housenumber":"23",
    "addr:postcode":"08750",
    "addr:street":"D'Olorda;Barcelona",
    "iso:country":"ES",
    "sg:address":"Cami Santa Creu D'olorda, 23",
    "sg:city":"Molins Rei",
    "sg:orig_category":"Carnicer\u00cdas, Carnicer\u00cdas",
    "sg:phone":"+34 936 68 24 44",
    "sg:postcode":"08750",
    "sg:province":"Barcelona",
    "wof:name":"Garcia Comis Rosa Maria",
    "wof:placetype":"venue"
},
  "geometry": {"coordinates":[2.0222601891,41.4131851196],"type":"Point"}
}