{
  "type": "Feature",
  "properties": {
    "iso:country":"ES",
    "sg:address":"Carr Valencia, 3",
    "sg:city":"Moncada",
    "sg:orig_category":"Organizaci\u00d3n De Actos, Seminarios Y Congresos",
    "sg:phone":"+34 961 39 07 29",
    "sg:postcode":"46113",
    "sg:province":"Valencia",
    "wof:name":"Familia Agudo Martinez S.l.",
    "wof:placetype":"venue"
},
  "geometry": {"coordinates":[-0.4012649953,39.5455436707],"type":"Point"}
}