{
  "type": "Feature",
  "properties": {
    "addr:full":"Pase Alameda De Osuna, 74 Madrid Madrid 28042",
    "addr:housenumber":"74",
    "addr:postcode":"madrid;28042",
    "addr:street":"Alameda;Osuna",
    "iso:country":"ES",
    "sg:address":"Pase Alameda De Osuna, 74",
    "sg:city":"Madrid",
    "sg:orig_category":"Ingenier\u00cda, Centros De Estudios (diversos)",
    "sg:phone":"+34 917 47 27 41",
    "sg:postcode":"28042",
    "sg:province":"Madrid",
    "wof:name":"Tomas Hormigo Damaso",
    "wof:placetype":"venue"
},
  "geometry": {"coordinates":[-3.5894138813,40.4580917358],"type":"Point"}
}