{
  "type": "Feature",
  "properties": {
    "addr:full":"Cmno Horno De Alcedo, 11 Horno De Alcedo Valencia 46026",
    "addr:housenumber":"11",
    "addr:postcode":"46026",
    "addr:street":"Cmno Horno De Alcedo;De Alcedo",
    "iso:country":"ES",
    "sg:address":"Cmno Horno De Alcedo, 11",
    "sg:city":"Horno De Alcedo",
    "sg:orig_category":"Tapicer\u00cdas",
    "sg:phone":"+34 963 76 64 87",
    "sg:postcode":"46026",
    "sg:province":"Valencia",
    "wof:name":"Bachiller Garcia Juan",
    "wof:placetype":"venue"
},
  "geometry": {"coordinates":[-0.3771870136,39.4316444397],"type":"Point"}
}