{
  "type": "Feature",
  "properties": {
    "iso:country":"ES",
    "sg:address":"Ctra Madrid, Km. 0398,0",
    "sg:city":"Badajoz",
    "sg:orig_category":"Frutas Y Legumbres Secas (al Por Mayor)",
    "sg:phone":"+34 924 24 27 20",
    "sg:postcode":"06008",
    "sg:province":"Badajoz",
    "wof:name":"Frutos Secos Koke's S.l.",
    "wof:placetype":"venue"
},
  "geometry": {"coordinates":[-6.9430441856,38.8723373413],"type":"Point"}
}