{
  "type": "Feature",
  "properties": {
    "iso:country":"ES",
    "sg:address":"Carr Cura Pleban, 3",
    "sg:city":"Oliva",
    "sg:orig_category":"M\u00c9dicos: Estomatolog\u00cda",
    "sg:phone":"+34 962 85 19 44",
    "sg:postcode":"46780",
    "sg:province":"Valencia",
    "wof:name":"Peiro Peiro Jesus",
    "wof:placetype":"venue"
},
  "geometry": {"coordinates":[-0.1184580028,38.9199371338],"type":"Point"}
}