{
  "type": "Feature",
  "properties": {
    "iso:country":"ES",
    "sg:address":"Luga Diseminado Matorral, 39",
    "sg:city":"Castillo",
    "sg:orig_category":"Reposter\u00cdas",
    "sg:phone":"+34 928 16 37 72",
    "sg:postcode":"35610",
    "sg:province":"Las Palmas",
    "wof:name":"Panaderia Costa Antigua S.l.",
    "wof:placetype":"venue"
},
  "geometry": {"coordinates":[-13.863199234,28.3980941772],"type":"Point"}
}