{
  "type": "Feature",
  "properties": {
    "iso:country":"ES",
    "sg:address":"Carrer de Francesc Moragas, 1",
    "sg:city":"Manresa",
    "sg:orig_category":"Muebles, Minoristas",
    "sg:phone":"+34 938 76 83 44",
    "sg:postcode":"08241",
    "sg:province":"Barcelona",
    "wof:name":"Aguilera Jimenez Ana Maria",
    "wof:placetype":"venue"
},
  "geometry": {"coordinates":[1.8158073425,41.7238578796],"type":"Point"}
}