{
  "type": "Feature",
  "properties": {
    "addr:full":"Trva Espi\u00d1eiro 1, 44 Vigo Pontevedra 36207",
    "addr:housenumber":"1 44",
    "addr:postcode":"36207",
    "addr:street":"Trva Espin\u0303Eiro",
    "iso:country":"ES",
    "sg:address":"Trva Espi\u00d1eiro 1, 44",
    "sg:city":"Vigo",
    "sg:orig_category":"Serigraf\u00cda (material Y Suministros)",
    "sg:phone":"+34 986 37 30 75",
    "sg:postcode":"36207",
    "sg:province":"Pontevedra",
    "wof:name":"Roman Cabral Maria De Los Angeles",
    "wof:placetype":"venue"
},
  "geometry": {"coordinates":[-8.7039985657,42.2523803711],"type":"Point"}
}