{
  "type": "Feature",
  "properties": {
    "addr:full":"Pla\u00c7 Espanya, D', 1 Soller Islas Baleares 07100",
    "addr:housenumber":"1",
    "addr:postcode":"07100",
    "iso:country":"ES",
    "sg:address":"Pla\u00c7 Espanya, D', 1",
    "sg:city":"Soller",
    "sg:orig_category":"Cajas De Ahorro",
    "sg:phone":"+34 971 63 01 52",
    "sg:postcode":"07100",
    "sg:province":"Islas Baleares",
    "sg:website":"www.lacaxa.es",
    "wof:name":"Caixa D'estalvis I Pensions De Barcelona",
    "wof:placetype":"venue"
},
  "geometry": {"coordinates":[2.7148981094,39.7653884888],"type":"Point"}
}