{
  "type": "Feature",
  "properties": {
    "iso:country":"ES",
    "sg:address":"Ptda Bovalar, S/n",
    "sg:city":"Polop",
    "sg:orig_category":"Electrodom\u00c9sticos (fabricaci\u00d3n, Al Por Mayor)",
    "sg:phone":"+34 965 87 02 48",
    "sg:postcode":"03520",
    "sg:province":"Alicante",
    "wof:name":"Frau Moll Jose",
    "wof:placetype":"venue"
},
  "geometry": {"coordinates":[-0.1381530017,38.6176605225],"type":"Point"}
}