{
  "type": "Feature",
  "properties": {
    "addr:full":"Rond Zamenhof, 65 Sabadell Barcelona 08201",
    "addr:housenumber":"65",
    "addr:postcode":"08201",
    "addr:street":"Zamenhof",
    "iso:country":"ES",
    "sg:address":"Rond Zamenhof, 65",
    "sg:city":"Sabadell",
    "sg:orig_category":"Zapatos (al Por Menor)",
    "sg:phone":"+34 937 27 15 38",
    "sg:postcode":"08201",
    "sg:province":"Barcelona",
    "wof:name":"Martinez Usero Gabriel",
    "wof:placetype":"venue"
},
  "geometry": {"coordinates":[2.1036500931,41.5513801575],"type":"Point"}
}