{
  "type": "Feature",
  "properties": {
    "iso:country":"ES",
    "sg:address":"Carr Roger De Flor, 9",
    "sg:city":"Puerto De Pollen\u00c7a",
    "sg:orig_category":"Empresas De Carpinter\u00cda De Madera",
    "sg:phone":"+34 971 86 41 34",
    "sg:postcode":"07470",
    "sg:province":"Islas Baleares",
    "wof:name":"Fusteria Taco S.l.",
    "wof:placetype":"venue"
},
  "geometry": {"coordinates":[3.0798010826,39.9065971375],"type":"Point"}
}