{
  "type": "Feature",
  "properties": {
    "iso:country":"ES",
    "sg:address":"Ctra San Rafael, S/n",
    "sg:city":"Segovia",
    "sg:orig_category":"Ense\u00d1anza, Formaci\u00d3n Profesional: Aprendizaje",
    "sg:phone":"+34 921 41 34 71",
    "sg:postcode":"40006",
    "sg:province":"Segovia",
    "wof:name":"Academia De Artilleria Poligono De Baterias",
    "wof:placetype":"venue"
},
  "geometry": {"coordinates":[-4.109415,40.933838],"type":"Point"}
}