{
  "type": "Feature",
  "properties": {
    "addr:full":"Ctra Carrion, 8 Ciudad Real Ciudad Real 13004",
    "addr:housenumber":"8",
    "addr:postcode":"13004",
    "addr:street":"Ctra Carrion",
    "iso:country":"ES",
    "sg:address":"Ctra Carrion, 8",
    "sg:city":"Ciudad Real",
    "sg:orig_category":"Agentes, Concesionarios Y Sucursales De Veh\u00cdculos",
    "sg:phone":"+34 926 25 17 85",
    "sg:postcode":"13004",
    "sg:province":"Ciudad Real",
    "wof:name":"Autos Carretero 4x4 S.l.",
    "wof:placetype":"venue"
},
  "geometry": {"coordinates":[-3.9177951813,38.9866790771],"type":"Point"}
}