{
  "type": "Feature",
  "properties": {
    "iso:country":"ES",
    "sg:address":"Calle de Juan Bravo, 26",
    "sg:city":"Madrid",
    "sg:orig_category":"Zapatos (al Por Menor)",
    "sg:phone":"+34 914 35 71 19",
    "sg:postcode":"28006",
    "sg:province":"Madrid",
    "wof:name":"China Blue Children S.l.",
    "wof:placetype":"venue"
},
  "geometry": {"coordinates":[-3.6815319061,40.4325218201],"type":"Point"}
}