{
  "type": "Feature",
  "properties": {
    "addr:full":"Partida Cap-blanch, 42 Cap-blanch Alicante 03590",
    "addr:housenumber":"42",
    "addr:postcode":"03590",
    "addr:street":"Partida Cap-Blanch;Alicante",
    "iso:country":"ES",
    "sg:address":"Partida Cap-blanch, 42",
    "sg:city":"Cap-blanch",
    "sg:orig_category":"Electricidad: Instaladores",
    "sg:phone":"+34 965 84 06 89",
    "sg:postcode":"03590",
    "sg:province":"Alicante",
    "wof:name":"Sevila Berenguer Miguel Antonio",
    "wof:placetype":"venue"
},
  "geometry": {"coordinates":[-0.0522690006,38.601108551],"type":"Point"}
}