{
  "type": "Feature",
  "properties": {
    "iso:country":"ES",
    "sg:address":"Cno San Agustin, S/n",
    "sg:city":"Villamalea",
    "sg:orig_category":"Promotores Constructores",
    "sg:phone":"+34 967 48 33 94",
    "sg:postcode":"02270",
    "sg:province":"Albacete",
    "wof:name":"Codeman S.c.l.",
    "wof:placetype":"venue"
},
  "geometry": {"coordinates":[-1.5969090462,39.364200592],"type":"Point"}
}