{
  "type": "Feature",
  "properties": {
    "addr:full":"Carrer de Circumval.lacio, 129 Viladecans Barcelona 08840",
    "addr:housenumber":"129",
    "addr:postcode":"08840",
    "addr:street":"Carrer De Circumval.Lacio",
    "iso:country":"ES",
    "sg:address":"Carrer de Circumval.lacio, 129",
    "sg:city":"Viladecans",
    "sg:orig_category":"Chapister\u00cda",
    "sg:phone":"+34 936 59 04 58",
    "sg:postcode":"08840",
    "sg:province":"Barcelona",
    "wof:name":"Caceres Gallardo Jose Antonio",
    "wof:placetype":"venue"
},
  "geometry": {"coordinates":[2.0071339607,41.3197937012],"type":"Point"}
}