{
  "type": "Feature",
  "properties": {
    "iso:country":"ES",
    "sg:address":"Av Rhode, 171",
    "sg:city":"Roses",
    "sg:orig_category":"Bancos",
    "sg:phone":"+34 972 15 47 50",
    "sg:postcode":"17480",
    "sg:province":"Girona",
    "wof:name":"Banc Sabadell S.a.",
    "wof:placetype":"venue"
},
  "geometry": {"coordinates":[3.172369957,42.2646903992],"type":"Point"}
}