{
  "type": "Feature",
  "properties": {
    "addr:full":"Calle de San Miguel Alta, 19 Granada Granada 18002",
    "addr:housenumber":"19",
    "addr:postcode":"18002",
    "addr:street":"Calle De San;Alta",
    "iso:country":"ES",
    "sg:address":"Calle de San Miguel Alta, 19",
    "sg:city":"Granada",
    "sg:orig_category":"Obras Y Organismos Sociales",
    "sg:phone":"+34 958 26 50 66",
    "sg:postcode":"18002",
    "sg:province":"Granada",
    "wof:name":"Institucion Activas Del Apostolado Social",
    "wof:placetype":"venue"
},
  "geometry": {"coordinates":[-3.6040449142,37.1738586426],"type":"Point"}
}