{
  "type": "Feature",
  "properties": {
    "iso:country":"ES",
    "sg:address":"Avda Sierra (la), 17",
    "sg:city":"Najera",
    "sg:orig_category":"Art\u00cdculos Funerarios (al Por Menor)",
    "sg:phone":"+34 941 36 11 08",
    "sg:postcode":"26300",
    "sg:province":"La Rioja",
    "wof:name":"Funeraria Tanatorio San Jose S.l.",
    "wof:placetype":"venue"
},
  "geometry": {"coordinates":[-2.7294909954,42.4169883728],"type":"Point"}
}