{
  "type": "Feature",
  "properties": {
    "addr:full":"Calle de Victor Garcia, 22 San Xulian Pontevedra 36640",
    "addr:housenumber":"22",
    "addr:postcode":"36640",
    "addr:street":"Calle De Victor Garcia",
    "iso:country":"ES",
    "sg:address":"Calle de Victor Garcia, 22",
    "sg:city":"San Xulian",
    "sg:orig_category":"Velas Y Cirios (fabricaci\u00d3n, Al Por Menor)",
    "sg:phone":"+34 986 55 70 55",
    "sg:postcode":"36640",
    "sg:province":"Pontevedra",
    "wof:name":"Dieguez Quintas Joaquin",
    "wof:placetype":"venue"
},
  "geometry": {"coordinates":[-8.6507349014,42.7232513428],"type":"Point"}
}