{
  "type": "Feature",
  "properties": {
    "addr:full":"Calle de Doctor Fleming, 6 Calatayud Zaragoza 50300",
    "addr:housenumber":"6",
    "addr:postcode":"50300",
    "addr:street":"Calle De Doctor Fleming",
    "iso:country":"ES",
    "sg:address":"Calle de Doctor Fleming, 6",
    "sg:city":"Calatayud",
    "sg:orig_category":"Electrodom\u00c9sticos (al Por Menor)",
    "sg:phone":"+34 976 88 18 58",
    "sg:postcode":"50300",
    "sg:province":"Zaragoza",
    "wof:name":"Electrodomesticos German S. L.",
    "wof:placetype":"venue"
},
  "geometry": {"coordinates":[-1.6399450302,41.3532676697],"type":"Point"}
}