{
  "type": "Feature",
  "properties": {
    "addr:full":"Calle de Jupiter, 34 Alacant Alicante 03006",
    "addr:housenumber":"34",
    "addr:postcode":"03006",
    "addr:street":"Calle De Jupiter",
    "iso:country":"ES",
    "sg:address":"Calle de Jupiter, 34",
    "sg:city":"Alacant",
    "sg:orig_category":"Electricidad Veh\u00cdculo",
    "sg:phone":"+34 965 28 00 46",
    "sg:postcode":"03006",
    "sg:province":"Alicante",
    "wof:name":"Rodriguez Carratala Domingo Manuel",
    "wof:placetype":"venue"
},
  "geometry": {"coordinates":[-0.5268009901,38.3427429199],"type":"Point"}
}