{
  "type": "Feature",
  "properties": {
    "addr:full":"Avda Ca\u00d1ete De Las Torres, 33 Baena C\u00f3rdoba 14850",
    "addr:housenumber":"33",
    "addr:postcode":"14850",
    "addr:street":"Avda Can\u0303Ete De Las Torres",
    "iso:country":"ES",
    "sg:address":"Avda Ca\u00d1ete De Las Torres, 33",
    "sg:city":"Baena",
    "sg:orig_category":"Productores Recolectores, Venta Directa De Vinos",
    "sg:phone":"+34 957 69 08 73",
    "sg:postcode":"14850",
    "sg:province":"C\u00f3rdoba",
    "wof:name":"Bodegas Jesus Nazareno Sdad.coop.andaluza",
    "wof:placetype":"venue"
},
  "geometry": {"coordinates":[-4.3259711266,37.6193771362],"type":"Point"}
}