{
  "type": "Feature",
  "properties": {
    "addr:full":"Rua Fabrica, 44 Carballo La Coru\u00f1a 15100",
    "addr:housenumber":"44",
    "addr:postcode":"15100",
    "addr:street":"Rua Fabrica;La Corun\u0303A",
    "iso:country":"ES",
    "sg:address":"Rua Fabrica, 44",
    "sg:city":"Carballo",
    "sg:orig_category":"Escayola Y Productos De Escayola (fabricaci\u00d3n, Al Por Mayor)",
    "sg:phone":"+34 981 70 29 69",
    "sg:postcode":"15100",
    "sg:province":"La Coru\u00f1a",
    "wof:name":"Escayolas Rivera S.l.",
    "wof:placetype":"venue"
},
  "geometry": {"coordinates":[-8.6971302032,43.2157058716],"type":"Point"}
}