{
  "type": "Feature",
  "properties": {
    "addr:full":"Avda Area, 1 Cedeira La Coru\u00f1a 15350",
    "addr:housenumber":"1",
    "addr:postcode":"15350",
    "addr:street":"Avda Area;La Corun\u0303A",
    "iso:country":"ES",
    "sg:address":"Avda Area, 1",
    "sg:city":"Cedeira",
    "sg:orig_category":"Bancos",
    "sg:phone":"+34 981 48 01 50",
    "sg:postcode":"15350",
    "sg:province":"La Coru\u00f1a",
    "sg:website":"www.bancogallego.es",
    "wof:name":"Banco Gallego S.a.",
    "wof:placetype":"venue"
},
  "geometry": {"coordinates":[-8.0512285233,43.6613082886],"type":"Point"}
}