{
  "type": "Feature",
  "properties": {
    "iso:country":"ES",
    "sg:address":"Avda Grecia, S/n",
    "sg:city":"Sevilla",
    "sg:orig_category":"Inform\u00c1tica (estudios, Servicios, Asesor\u00cda, Formaci\u00d3n)",
    "sg:phone":"+34 954 61 62 30",
    "sg:postcode":"41012",
    "sg:province":"Sevilla",
    "sg:website":"www.sitres.com",
    "wof:name":"Servicios Informaticos Y Economicos S.l.",
    "wof:placetype":"venue"
},
  "geometry": {"coordinates":[-5.9843511581,37.3512878418],"type":"Point"}
}