{
  "type": "Feature",
  "properties": {
    "iso:country":"ES",
    "sg:address":"Carrer de Bassols, 4",
    "sg:city":"Barcelona",
    "sg:orig_category":"Empresarios",
    "sg:phone":"+34 932 31 88 28",
    "sg:postcode":"08026",
    "sg:province":"Barcelona",
    "wof:name":"Danirga Asociados S.l.",
    "wof:placetype":"venue"
},
  "geometry": {"coordinates":[2.1832048893,41.4082145691],"type":"Point"}
}