{
  "type": "Feature",
  "properties": {
    "addr:full":"Carrer de Bordeus, 13 Barcelona Barcelona 08029",
    "addr:housenumber":"13",
    "addr:postcode":"08029",
    "addr:street":"Carrer De Bordeus",
    "iso:country":"ES",
    "sg:address":"Carrer de Bordeus, 13",
    "sg:city":"Barcelona",
    "sg:orig_category":"Periodistas Profesionales",
    "sg:phone":"+34 933 22 86 54",
    "sg:postcode":"08029",
    "sg:province":"Barcelona",
    "wof:name":"Baratech Sales Manuel",
    "wof:placetype":"venue"
},
  "geometry": {"coordinates":[2.1412489414,41.3885269165],"type":"Point"}
}