{
  "type": "Feature",
  "properties": {
    "iso:country":"ES",
    "sg:address":"Calle de Ramon Lujan, 83",
    "sg:city":"Madrid",
    "sg:orig_category":"Mec\u00c1nico Del Autom\u00d3vil",
    "sg:phone":"+34 914 75 94 64",
    "sg:postcode":"28026",
    "sg:province":"Madrid",
    "wof:name":"Diaz Riveira Jesus",
    "wof:placetype":"venue"
},
  "geometry": {"coordinates":[-3.7039120197,40.3832054138],"type":"Point"}
}