{
  "type": "Feature",
  "properties": {
    "addr:full":"Pl Prat De La Riba, 1 Mollet Valles Barcelona 08100",
    "addr:housenumber":"1",
    "addr:postcode":"08100",
    "addr:street":"Pl Prat De La Riba",
    "iso:country":"ES",
    "sg:address":"Pl Prat De La Riba, 1",
    "sg:city":"Mollet Valles",
    "sg:orig_category":"\u00d3ptica: Instrumentos (fabricaci\u00d3n)",
    "sg:phone":"+34 935 93 02 03",
    "sg:postcode":"08100",
    "sg:province":"Barcelona",
    "wof:name":"Salvado Cavalle Juan",
    "wof:placetype":"venue"
},
  "geometry": {"coordinates":[2.2133100033,41.538520813],"type":"Point"}
}