{
  "type": "Feature",
  "properties": {
    "iso:country":"ES",
    "sg:address":"Avda Reconquista, 36",
    "sg:city":"Ayllon",
    "sg:orig_category":"Negocio De Materiales De Construcci\u00d3n",
    "sg:phone":"+34 921 55 30 79",
    "sg:postcode":"40520",
    "sg:province":"Segovia",
    "wof:name":"Materiales De Construccion Navas Molinero S.l.",
    "wof:placetype":"venue"
},
  "geometry": {"coordinates":[-3.3720591068,41.4192008972],"type":"Point"}
}