{
  "type": "Feature",
  "properties": {
    "addr:full":"Carrer de Rossello, 60 Barcelona Barcelona 08029",
    "addr:housenumber":"60",
    "addr:postcode":"08029",
    "addr:street":"Carrer De Rossello",
    "iso:country":"ES",
    "sg:address":"Carrer de Rossello, 60",
    "sg:city":"Barcelona",
    "sg:orig_category":"Comercio De Piezas De Recambio Y De Accesorios De Veh\u00cdculos, Veh\u00cdculos Industriales",
    "sg:phone":"+34 933 21 30 87",
    "sg:postcode":"08029",
    "sg:province":"Barcelona",
    "wof:name":"Gusi I Martinez S.c.p.",
    "wof:placetype":"venue"
},
  "geometry": {"coordinates":[2.1479809284,41.3860740662],"type":"Point"}
}