{
  "type": "Feature",
  "properties": {
    "iso:country":"ES",
    "sg:address":"Carr Roger De Lluria, 14",
    "sg:city":"Puerto De Pollen\u00c7a",
    "sg:orig_category":"Electricidad: Instaladores",
    "sg:phone":"+34 971 86 53 07",
    "sg:postcode":"07470",
    "sg:province":"Islas Baleares",
    "wof:name":"Capllonch Socias Mateo",
    "wof:placetype":"venue"
},
  "geometry": {"coordinates":[3.0782520771,39.9059791565],"type":"Point"}
}