{
  "type": "Feature",
  "properties": {
    "iso:country":"ES",
    "sg:address":"Centro Comercial Bonaire, S/n",
    "sg:city":"Aldaia",
    "sg:orig_category":"Bisuter\u00cda, Joyer\u00cda, Relojer\u00cda (al Por Menor)",
    "sg:phone":"+34 961 92 03 89",
    "sg:postcode":"46960",
    "sg:province":"Valencia",
    "wof:name":"Giocorp 1948 S.l.",
    "wof:placetype":"venue"
},
  "geometry": {"coordinates":[-0.4853590131,39.4696578979],"type":"Point"}
}