{
  "type": "Feature",
  "properties": {
    "addr:full":"Calle de Guadalquivir, 32 Horno De Alcedo Valencia 46026",
    "addr:housenumber":"32",
    "addr:postcode":"46026",
    "addr:street":"Calle De Guadalquivir;De Alcedo",
    "iso:country":"ES",
    "sg:address":"Calle de Guadalquivir, 32",
    "sg:city":"Horno De Alcedo",
    "sg:orig_category":"Molduras, Junquillos, Listones Y Molduras Perforadas",
    "sg:phone":"+34 963 76 67 81",
    "sg:postcode":"46026",
    "sg:province":"Valencia",
    "wof:name":"Sistelcom-telemensaje S.a.",
    "wof:placetype":"venue"
},
  "geometry": {"coordinates":[-0.3763850033,39.4321937561],"type":"Point"}
}