{
  "type": "Feature",
  "properties": {
    "iso:country":"ES",
    "sg:address":"Av. Pio Xii, 26",
    "sg:city":"Iru\u00f1a",
    "sg:orig_category":"Cajas De Ahorro",
    "sg:phone":"+34 948 19 97 50",
    "sg:postcode":"31008",
    "sg:province":"Navarra",
    "sg:website":"www.bancaja.es",
    "wof:name":"Caja De Ahorros De Valencia Castellon Y Alicante",
    "wof:placetype":"venue"
},
  "geometry": {"coordinates":[-1.6605529785,42.8074188232],"type":"Point"}
}