{
  "type": "Feature",
  "properties": {
    "addr:full":"Calle de Alonso De Ojeda, S/n Huelva Huelva 21002",
    "addr:housenumber":"s / n",
    "addr:postcode":"21002",
    "addr:street":"Calle De Alonso De Ojeda",
    "iso:country":"ES",
    "sg:address":"Calle de Alonso De Ojeda, S/n",
    "sg:city":"Huelva",
    "sg:orig_category":"Mec\u00c1nico Del Autom\u00d3vil",
    "sg:phone":"+34 959 28 09 99",
    "sg:postcode":"21002",
    "sg:province":"Huelva",
    "wof:name":"Vazquez Vargas Jose Maria",
    "wof:placetype":"venue"
},
  "geometry": {"coordinates":[-6.9591441154,37.265789032],"type":"Point"}
}