{
  "type": "Feature",
  "properties": {
    "iso:country":"ES",
    "sg:address":"Joaquin Beunza, 39",
    "sg:city":"Iru\u00f1a",
    "sg:orig_category":"Farmacias",
    "sg:phone":"+34 948 13 67 83",
    "sg:postcode":"31014",
    "sg:province":"Navarra",
    "wof:name":"Garralda Morras S.i",
    "wof:placetype":"venue"
},
  "geometry": {"coordinates":[-1.6540212631,42.8243675232],"type":"Point"}
}