{
  "type": "Feature",
  "properties": {
    "iso:country":"ES",
    "sg:address":"Calle de Xuquer, 10",
    "sg:city":"Alzira",
    "sg:orig_category":"Fabricaci\u00d3n, Instalaci\u00d3n Y Reparaci\u00d3n De Bombas",
    "sg:phone":"+34 962 41 04 30",
    "sg:postcode":"46600",
    "sg:province":"Valencia",
    "wof:name":"Cortina Garrido Manuel",
    "wof:placetype":"venue"
},
  "geometry": {"coordinates":[-0.4372650087,39.15184021],"type":"Point"}
}