{
  "type": "Feature",
  "properties": {
    "addr:full":"S. Fabia, 8 Bossost Lleida 25550",
    "addr:housenumber":"8",
    "addr:postcode":"25550",
    "addr:street":"Fabia",
    "iso:country":"ES",
    "sg:address":"S. Fabia, 8",
    "sg:city":"Bossost",
    "sg:orig_category":"Ropa Y Accesorios",
    "sg:phone":"+34 973 64 73 41",
    "sg:postcode":"25550",
    "sg:province":"Lleida",
    "wof:name":"Simply Helpul S.l.",
    "wof:placetype":"venue"
},
  "geometry": {"coordinates":[0.6910129786,42.7821159363],"type":"Point"}
}