{
  "type": "Feature",
  "properties": {
    "iso:country":"ES",
    "sg:address":"Pase Alberto Palacios, S/n",
    "sg:city":"Madrid",
    "sg:orig_category":"Herboristas (al Por Menor)",
    "sg:phone":"+34 917 98 58 10",
    "sg:postcode":"28021",
    "sg:province":"Madrid",
    "wof:name":"Acevedo Peralta Angelita",
    "wof:placetype":"venue"
},
  "geometry": {"coordinates":[-3.7129302025,40.3447227478],"type":"Point"}
}