{
  "type": "Feature",
  "properties": {
    "iso:country":"ES",
    "sg:address":"Calle de Santa Teresa, 4",
    "sg:city":"Valencia",
    "sg:orig_category":"Fabricaci\u00d3n De Instrumentos Y Accesorios Musicales",
    "sg:phone":"+34 963 15 36 59",
    "sg:postcode":"46001",
    "sg:province":"Valencia",
    "sg:website":"www.luthieres.com",
    "wof:name":"Schneider Legros C.b.",
    "wof:placetype":"venue"
},
  "geometry": {"coordinates":[-0.3812110126,39.4743461609],"type":"Point"}
}