{
  "type": "Feature",
  "properties": {
    "addr:full":"Calle de Sombra, 11 Madrid Madrid 28025",
    "addr:housenumber":"11",
    "addr:postcode":"madrid;28025",
    "addr:street":"Calle De Sombra",
    "iso:country":"ES",
    "sg:address":"Calle de Sombra, 11",
    "sg:city":"Madrid",
    "sg:orig_category":"Promotores Constructores",
    "sg:phone":"+34 914 61 30 05",
    "sg:postcode":"28025",
    "sg:province":"Madrid",
    "wof:name":"Comunidad Propietarios Calle Sombra N\u00ba 11",
    "wof:placetype":"venue"
},
  "geometry": {"coordinates":[-3.7408189774,40.3797187805],"type":"Point"}
}