{
  "type": "Feature",
  "properties": {
    "addr:full":"Avgd Mura, 3 Villarreal Castell\u00f3n 12540",
    "addr:housenumber":"3",
    "addr:postcode":"12540",
    "iso:country":"ES",
    "sg:address":"Avgd Mura, 3",
    "sg:city":"Villarreal",
    "sg:orig_category":"Agencias De Viajes",
    "sg:phone":"+34 964 52 93 60",
    "sg:postcode":"12540",
    "sg:province":"Castell\u00f3n",
    "sg:website":"www.viajeselcorteingles.es",
    "wof:name":"Viajes El Corte Ingles S.a.",
    "wof:placetype":"venue"
},
  "geometry": {"coordinates":[-0.0952939987,39.9453048706],"type":"Point"}
}