{
  "type": "Feature",
  "properties": {
    "iso:country":"ES",
    "sg:address":"Rond Olivenza (san Francisco De Olivenza), 7",
    "sg:city":"S. Francisco Olivenza",
    "sg:orig_category":"Agencias Y Agentes Comerciales, Representantes",
    "sg:phone":"+34 924 49 78 00",
    "sg:postcode":"06109",
    "sg:province":"Badajoz",
    "wof:name":"Olivera Lagoa Antonio",
    "wof:placetype":"venue"
},
  "geometry": {"coordinates":[-7.0521411896,38.7200546265],"type":"Point"}
}