{
  "type": "Feature",
  "properties": {
    "iso:country":"ES",
    "sg:address":"Merindad C. Vieja, 29",
    "sg:city":"Villalonquejar",
    "sg:orig_category":"Material Y Equipo Para Vinificaci\u00d3n",
    "sg:phone":"+34 947 29 82 82",
    "sg:postcode":"09001",
    "sg:province":"Burgos",
    "wof:name":"Jovic S.a.(ignacio Garcia",
    "wof:placetype":"venue"
},
  "geometry": {"coordinates":[-3.7360639572,42.3661956787],"type":"Point"}
}