{
  "type": "Feature",
  "properties": {
    "iso:country":"ES",
    "sg:address":"Calle de Francisco Gourie, 22",
    "sg:city":"Palmas De Gran Canaria",
    "sg:orig_category":"Abogados",
    "sg:phone":"+34 928 36 80 23",
    "sg:postcode":"35002",
    "sg:province":"Las Palmas",
    "wof:name":"Fe De La Fe Bernabe De La",
    "wof:placetype":"venue"
},
  "geometry": {"coordinates":[-15.4154968262,28.1053638458],"type":"Point"}
}