{
  "type": "Feature",
  "properties": {
    "iso:country":"ES",
    "sg:address":"Carrer de Cecs De La Boqueria, 3",
    "sg:city":"Barcelona",
    "sg:orig_category":"Bisuter\u00cda, Joyer\u00cda, Relojer\u00cda (al Por Menor)",
    "sg:phone":"+34 934 12 51 88",
    "sg:postcode":"08002",
    "sg:province":"Barcelona",
    "wof:name":"Gavidia Carre\u00f1o Jose Maria",
    "wof:placetype":"venue"
},
  "geometry": {"coordinates":[2.1746640205,41.381816864],"type":"Point"}
}