{
  "type": "Feature",
  "properties": {
    "iso:country":"ES",
    "sg:address":"Calle de Cantarranas, 26",
    "sg:city":"Navalvillar Pela",
    "sg:orig_category":"Telas Y Sedas (al Por Menor)",
    "sg:phone":"+34 924 86 03 02",
    "sg:postcode":"06760",
    "sg:province":"Badajoz",
    "wof:name":"Corvillo Mu\u00f1ino Pedro",
    "wof:placetype":"venue"
},
  "geometry": {"coordinates":[-5.4683051109,39.0907859802],"type":"Point"}
}