{
  "type": "Feature",
  "properties": {
    "iso:country":"ES",
    "sg:address":"Via Augusta, 173",
    "sg:city":"Barcelona",
    "sg:orig_category":"Complementos De Vestir (al Por Menor)",
    "sg:phone":"+34 932 09 41 15",
    "sg:postcode":"08021",
    "sg:province":"Barcelona",
    "wof:name":"Serra Cerdan Jose",
    "wof:placetype":"venue"
},
  "geometry": {"coordinates":[2.1421630383,41.3982467651],"type":"Point"}
}