{
  "type": "Feature",
  "properties": {
    "addr:full":"Carrer de Prat De La Riba, 5 Vendrell Tarragona 43700",
    "addr:housenumber":"5",
    "addr:postcode":"43700",
    "addr:street":"Carrer De Prat De La Riba",
    "iso:country":"ES",
    "sg:address":"Carrer de Prat De La Riba, 5",
    "sg:city":"Vendrell",
    "sg:orig_category":"Asesor\u00cda Sobre Comunicaci\u00d3n De Empresas",
    "sg:phone":"+34 977 15 51 83",
    "sg:postcode":"43700",
    "sg:province":"Tarragona",
    "wof:name":"Asde Assessors 2002 S.l.",
    "wof:placetype":"venue"
},
  "geometry": {"coordinates":[1.5359374285,41.2202339172],"type":"Point"}
}