{
  "type": "Feature",
  "properties": {
    "addr:full":"Calle de Canalejas, 11 Alacant Alicante 03001",
    "addr:housenumber":"11",
    "addr:postcode":"03001",
    "addr:street":"Calle De Canalejas",
    "iso:country":"ES",
    "sg:address":"Calle de Canalejas, 11",
    "sg:city":"Alacant",
    "sg:orig_category":"Abogados",
    "sg:phone":"+34 965 14 20 83",
    "sg:postcode":"03001",
    "sg:province":"Alicante",
    "wof:name":"Esteve Villaescusa Francisco",
    "wof:placetype":"venue"
},
  "geometry": {"coordinates":[-0.4876722991,38.343120575],"type":"Point"}
}