{
  "type": "Feature",
  "properties": {
    "addr:full":"Avda Ultramar, 2 Arenal Alicante 03730",
    "addr:housenumber":"2",
    "addr:postcode":"03730",
    "addr:street":"Avda Ultramar",
    "iso:country":"ES",
    "sg:address":"Avda Ultramar, 2",
    "sg:city":"Arenal",
    "sg:orig_category":"Caf\u00c9s, Bares, Cervecer\u00cdas",
    "sg:phone":"+34 966 47 15 57",
    "sg:postcode":"03730",
    "sg:province":"Alicante",
    "wof:name":"Meyer  Brigitte",
    "wof:placetype":"venue"
},
  "geometry": {"coordinates":[0.1668650061,38.7890739441],"type":"Point"}
}