{
  "type": "Feature",
  "properties": {
    "addr:full":"Ctra Mijas (de), Km. 2300,0 Coin M\u00e1laga 29100",
    "addr:postcode":"29100",
    "addr:street":"Ctra Mijas De Km. 2300,0 Coin Ma\u0301Laga",
    "iso:country":"ES",
    "sg:address":"Ctra Mijas (de), Km. 2300,0",
    "sg:city":"Coin",
    "sg:orig_category":"Electricidad: Instaladores",
    "sg:phone":"+34 952 45 24 84",
    "sg:postcode":"29100",
    "sg:province":"M\u00e1laga",
    "wof:name":"Rovelectri Sl",
    "wof:placetype":"venue"
},
  "geometry": {"coordinates":[-4.7576842308,36.659740448],"type":"Point"}
}