{
  "type": "Feature",
  "properties": {
    "iso:country":"ES",
    "sg:address":"Avda Galicia De, 20",
    "sg:city":"Piedras Blancas",
    "sg:orig_category":"Ingenier\u00cda, Centros De Estudios (diversos)",
    "sg:phone":"+34 985 50 83 24",
    "sg:postcode":"33450",
    "sg:province":"Asturias",
    "wof:name":"Ingenieria Y Tecnologia Castrillon S.l.",
    "wof:placetype":"venue"
},
  "geometry": {"coordinates":[-5.9807701111,43.5585441589],"type":"Point"}
}