{
  "type": "Feature",
  "properties": {
    "iso:country":"ES",
    "sg:address":"Avgd Lloreda, 70",
    "sg:city":"Badalona",
    "sg:orig_category":"Supermercados Y Hipermercados",
    "sg:phone":"+34 933 98 66 02",
    "sg:postcode":"08917",
    "sg:province":"Barcelona",
    "wof:name":"Hijo Garne S.l.",
    "wof:placetype":"venue"
},
  "geometry": {"coordinates":[2.2269001007,41.4512290955],"type":"Point"}
}