{
  "type": "Feature",
  "properties": {
    "addr:full":"Pase Goya (de), 3 Mostoles Madrid 28931",
    "addr:postcode":"28931",
    "addr:street":"Mostoles",
    "iso:country":"ES",
    "sg:address":"Pase Goya (de), 3",
    "sg:city":"Mostoles",
    "sg:orig_category":"Centros De Educaci\u00d3n Especial",
    "sg:phone":"+34 916 13 61 88",
    "sg:postcode":"28931",
    "sg:province":"Madrid",
    "wof:name":"Colegio Publico Beato Simon De Rojas",
    "wof:placetype":"venue"
},
  "geometry": {"coordinates":[-3.8649389744,40.3230667114],"type":"Point"}
}