{
  "type": "Feature",
  "properties": {
    "addr:full":"Carrer de Sant Elm, 1 Roses Girona 17480",
    "addr:housenumber":"1",
    "addr:postcode":"17480",
    "addr:street":"Carrer De Sant Elm",
    "iso:country":"ES",
    "sg:address":"Carrer de Sant Elm, 1",
    "sg:city":"Roses",
    "sg:orig_category":"Cajas De Ahorro",
    "sg:phone":"+34 972 25 62 40",
    "sg:postcode":"17480",
    "sg:province":"Girona",
    "wof:name":"Caixa D'estalvis I Pensions De Barcelona",
    "wof:placetype":"venue"
},
  "geometry": {"coordinates":[3.1760630608,42.26171875],"type":"Point"}
}