{
  "type": "Feature",
  "properties": {
    "addr:full":"Plaz Cardenal Belluga, 4 Dolores Alicante 03150",
    "addr:housenumber":"4",
    "addr:postcode":"03150",
    "addr:street":"Plaz Cardenal Belluga",
    "iso:country":"ES",
    "sg:address":"Plaz Cardenal Belluga, 4",
    "sg:city":"Dolores",
    "sg:orig_category":"Asesor\u00cda Sobre Comunicaci\u00d3n De Empresas",
    "sg:phone":"+34 965 72 62 12",
    "sg:postcode":"03150",
    "sg:province":"Alicante",
    "wof:name":"Esquitino Trives Y Berenguer S.l.",
    "wof:placetype":"venue"
},
  "geometry": {"coordinates":[-0.769069016,38.139503479],"type":"Point"}
}