{
  "type": "Feature",
  "properties": {
    "addr:full":"Mas Llado, S/n Navata Girona 17744",
    "addr:housenumber":"s / n",
    "addr:postcode":"17744",
    "iso:country":"ES",
    "sg:address":"Mas Llado, S/n",
    "sg:city":"Navata",
    "sg:orig_category":"Cr\u00cda De Animales",
    "sg:phone":"+34 972 55 36 33",
    "sg:postcode":"17744",
    "sg:province":"Girona",
    "wof:name":"Mas Llado Cdad.",
    "wof:placetype":"venue"
},
  "geometry": {"coordinates":[2.8589949608,42.2212905884],"type":"Point"}
}