{
  "type": "Feature",
  "properties": {
    "iso:country":"ES",
    "sg:address":"Calle de Veintinueve De Abril, 36",
    "sg:city":"Palmas De Gran Canaria",
    "sg:orig_category":"Importaci\u00d3n",
    "sg:phone":"+34 928 26 96 02",
    "sg:postcode":"35007",
    "sg:province":"Las Palmas",
    "wof:name":"Comercial Euluan S.a.",
    "wof:placetype":"venue"
},
  "geometry": {"coordinates":[-15.4324092865,28.1377544403],"type":"Point"}
}