{
  "type": "Feature",
  "properties": {
    "addr:full":"Carrer de Bernat Visca, 18 Palma Islas Baleares 07006",
    "addr:housenumber":"18",
    "addr:postcode":"07006",
    "addr:street":"Carrer De Bernat Visca",
    "iso:country":"ES",
    "sg:address":"Carrer de Bernat Visca, 18",
    "sg:city":"Palma",
    "sg:orig_category":"Abogados",
    "sg:phone":"+34 971 24 04 02",
    "sg:postcode":"07006",
    "sg:province":"Islas Baleares",
    "wof:name":"Coll Covas Maria Isabel",
    "wof:placetype":"venue"
},
  "geometry": {"coordinates":[2.6792171001,39.5574417114],"type":"Point"}
}