{
  "type": "Feature",
  "properties": {
    "iso:country":"ES",
    "sg:address":"Pol. Can Pruna, 25",
    "sg:city":"Riudarenes",
    "sg:orig_category":"M\u00c1rmoles, Granitos Y Piedras Naturales",
    "sg:phone":"+34 972 85 64 26",
    "sg:postcode":"17421",
    "sg:province":"Girona",
    "wof:name":"Escobar Arenas David",
    "wof:placetype":"venue"
},
  "geometry": {"coordinates":[2.7224509716,41.8221893311],"type":"Point"}
}