{
  "type": "Feature",
  "properties": {
    "iso:country":"ES",
    "sg:address":"Calle de Fuentes De Andalucia, 17",
    "sg:city":"Marchena",
    "sg:orig_category":"Negocio De Enlosados, Soler\u00cdas",
    "sg:phone":"+34 955 84 62 95",
    "sg:postcode":"41620",
    "sg:province":"Sevilla",
    "wof:name":"Leones Materiales De Construccion S.l.",
    "wof:placetype":"venue"
},
  "geometry": {"coordinates":[-5.4179720879,37.3231124878],"type":"Point"}
}