{
  "type": "Feature",
  "properties": {
    "addr:full":"C/ Coll Des Palmer, Des, 4 Alaior Islas Baleares 07730",
    "addr:postcode":"07730",
    "addr:street":"C / Coll Des Palmer",
    "iso:country":"ES",
    "sg:address":"C/ Coll Des Palmer, Des, 4",
    "sg:city":"Alaior",
    "sg:orig_category":"Centros De Educaci\u00d3n Especial",
    "sg:phone":"+34 971 37 20 05",
    "sg:postcode":"07730",
    "sg:province":"Islas Baleares",
    "wof:name":"Centro Docente Publico No Universitario Cea Menorca",
    "wof:placetype":"venue"
},
  "geometry": {"coordinates":[4.1394782066,39.9334831238],"type":"Point"}
}