{
  "type": "Feature",
  "properties": {
    "iso:country":"ES",
    "sg:address":"Calle de Proclamacion, 8",
    "sg:city":"Carmen",
    "sg:orig_category":"Farmacias",
    "sg:phone":"+34 968 21 04 80",
    "sg:postcode":"30002",
    "sg:province":"Murcia",
    "wof:name":"Farmacia Floridablanca C.b.",
    "wof:placetype":"venue"
},
  "geometry": {"coordinates":[-1.1296750307,37.9805717468],"type":"Point"}
}