{
  "type": "Feature",
  "properties": {
    "addr:full":"Carr Vallier, 10 Gandia Valencia 46700",
    "addr:housenumber":"10",
    "addr:postcode":"46700",
    "addr:street":"Carr Vallier;Valencia",
    "iso:country":"ES",
    "sg:address":"Carr Vallier, 10",
    "sg:city":"Gandia",
    "sg:orig_category":"Florister\u00cdas",
    "sg:phone":"+34 962 87 26 15",
    "sg:postcode":"46700",
    "sg:province":"Valencia",
    "wof:name":"Floristeria Noguera C.b.",
    "wof:placetype":"venue"
},
  "geometry": {"coordinates":[-0.1913339943,38.960735321],"type":"Point"}
}