{
  "type": "Feature",
  "properties": {
    "iso:country":"ES",
    "sg:address":"Calle de Fuencarral, 126",
    "sg:city":"Madrid",
    "sg:orig_category":"Frutas, Legumbres Frescas Y Tempranas (al Por Menor)",
    "sg:phone":"+34 914 48 78 13",
    "sg:postcode":"28010",
    "sg:province":"Madrid",
    "wof:name":"Menendez Sanchez Maria Covadonga",
    "wof:placetype":"venue"
},
  "geometry": {"coordinates":[-3.7029573917,40.4304656982],"type":"Point"}
}