{
  "type": "Feature",
  "properties": {
    "iso:country":"ES",
    "sg:address":"Avda Santiago (de), 71",
    "sg:city":"Ourense",
    "sg:orig_category":"Bancos",
    "sg:phone":"+34 988 21 75 60",
    "sg:postcode":"32001",
    "sg:province":"Ourense",
    "wof:name":"Banco Popular Espa\u00f1ol",
    "wof:placetype":"venue"
},
  "geometry": {"coordinates":[-7.8653907776,42.3533859253],"type":"Point"}
}