{
  "type": "Feature",
  "properties": {
    "addr:full":"Ernesto Andreu Minguet, 9 Sedavi Valencia 46910",
    "addr:housenumber":"9",
    "addr:postcode":"46910",
    "addr:street":"Ernesto Andreu Minguet",
    "iso:country":"ES",
    "sg:address":"Ernesto Andreu Minguet, 9",
    "sg:city":"Sedavi",
    "sg:orig_category":"Fabricaci\u00d3n De Moldes Y Modelos",
    "sg:phone":"+34 963 75 86 68",
    "sg:postcode":"46910",
    "sg:province":"Valencia",
    "wof:name":"Talleres Bomar S. A.",
    "wof:placetype":"venue"
},
  "geometry": {"coordinates":[-0.3787420094,39.4262466431],"type":"Point"}
}