{
  "type": "Feature",
  "properties": {
    "iso:country":"ES",
    "sg:address":"Carrer de Sas, 21",
    "sg:city":"Barcelona",
    "sg:orig_category":"Supermercados Y Hipermercados",
    "sg:phone":"+34 933 45 77 83",
    "sg:postcode":"08030",
    "sg:province":"Barcelona",
    "wof:name":"Superficies De Alimentacion S. A.",
    "wof:placetype":"venue"
},
  "geometry": {"coordinates":[2.2041079998,41.4370918274],"type":"Point"}
}