{
  "type": "Feature",
  "properties": {
    "iso:country":"ES",
    "sg:address":"Calle de Ronda, 16",
    "sg:city":"Villanueva Alcardete",
    "sg:orig_category":"Arreglo E Instalaci\u00d3n De Caf\u00c9s, Hoteles Y Restaurantes",
    "sg:phone":"+34 925 16 63 55",
    "sg:postcode":"45810",
    "sg:province":"Toledo",
    "wof:name":"Diaz Montejano Luis Carlos",
    "wof:placetype":"venue"
},
  "geometry": {"coordinates":[-3.01532197,39.6717376709],"type":"Point"}
}