{
  "type": "Feature",
  "properties": {
    "iso:country":"ES",
    "sg:address":"Carr Arravaleta, 14",
    "sg:city":"Mao",
    "sg:orig_category":"Molduras, Junquillos, Listones Y Molduras Perforadas",
    "sg:phone":"+34 971 35 45 92",
    "sg:postcode":"07702",
    "sg:province":"Islas Baleares",
    "wof:name":"Ponti  Michele",
    "wof:placetype":"venue"
},
  "geometry": {"coordinates":[4.265625,39.8903694153],"type":"Point"}
}