{
  "type": "Feature",
  "properties": {
    "iso:country":"ES",
    "sg:address":"Calle de Magallanes, S/n",
    "sg:city":"Velez-malaga",
    "sg:orig_category":"Bricolaje, Herramientas (al Por Menor)",
    "sg:phone":"+34 952 50 78 87",
    "sg:postcode":"29700",
    "sg:province":"M\u00e1laga",
    "wof:name":"Garcia Lopez Maria Victoria",
    "wof:placetype":"venue"
},
  "geometry": {"coordinates":[-4.104033947,36.7750244141],"type":"Point"}
}