{
  "type": "Feature",
  "properties": {
    "addr:full":"Calle de Cidro, 6 Madrid Madrid 28044",
    "addr:housenumber":"6",
    "addr:postcode":"28044",
    "addr:street":"Calle De Cidro",
    "iso:country":"ES",
    "sg:address":"Calle de Cidro, 6",
    "sg:city":"Madrid",
    "sg:orig_category":"Asesor\u00cda, Estudio Y Control Medioambiental",
    "sg:phone":"+34 915 08 49 85",
    "sg:postcode":"28044",
    "sg:province":"Madrid",
    "wof:name":"Fomento De Construcciones Y Contratas S.a.",
    "wof:placetype":"venue"
},
  "geometry": {"coordinates":[-3.7459163666,40.3680381775],"type":"Point"}
}