{
  "type": "Feature",
  "properties": {
    "addr:full":"Calle de Dos De Mayo, 88 Badajoz Badajoz 06008",
    "addr:housenumber":"88",
    "addr:postcode":"06008",
    "addr:street":"Calle De Dos;Mayo",
    "iso:country":"ES",
    "sg:address":"Calle de Dos De Mayo, 88",
    "sg:city":"Badajoz",
    "sg:orig_category":"Carnicer\u00cdas, Carnicer\u00cdas",
    "sg:phone":"+34 924 24 26 54",
    "sg:postcode":"06008",
    "sg:province":"Badajoz",
    "wof:name":"Pagador Hermosell Eduardo",
    "wof:placetype":"venue"
},
  "geometry": {"coordinates":[-6.9561290741,38.8795089722],"type":"Point"}
}