{
  "type": "Feature",
  "properties": {
    "iso:country":"ES",
    "sg:address":"Calle de Alcalde Ruiz Cu\u00d1ales, 4",
    "sg:city":"Nerva",
    "sg:orig_category":"Quincaller\u00cda (al Por Menor)",
    "sg:phone":"+34 959 58 04 02",
    "sg:postcode":"21670",
    "sg:province":"Huelva",
    "wof:name":"Franco Gonzalez Manuel",
    "wof:placetype":"venue"
},
  "geometry": {"coordinates":[-6.5249757767,37.702747345],"type":"Point"}
}