{
  "type": "Feature",
  "properties": {
    "addr:full":"Calle de Radio, 28 Madrid Madrid 28019",
    "addr:housenumber":"28",
    "addr:postcode":"madrid;28019",
    "addr:street":"Calle De Radio",
    "iso:country":"ES",
    "sg:address":"Calle de Radio, 28",
    "sg:city":"Madrid",
    "sg:orig_category":"Electrodom\u00c9sticos (al Por Menor)",
    "sg:phone":"+34 915 69 94 44",
    "sg:postcode":"28019",
    "sg:province":"Madrid",
    "wof:name":"Olmeda Cava Eugenio",
    "wof:placetype":"venue"
},
  "geometry": {"coordinates":[-3.7221651077,40.3920822144],"type":"Point"}
}