{
  "type": "Feature",
  "properties": {
    "iso:country":"ES",
    "sg:address":"Calle de Monte (del), 1",
    "sg:city":"Alcorcon",
    "sg:orig_category":"Carnicer\u00cdas, Carnicer\u00cdas",
    "sg:phone":"+34 916 12 84 05",
    "sg:postcode":"28921",
    "sg:province":"Madrid",
    "wof:name":"Martin Sanchez Constancio",
    "wof:placetype":"venue"
},
  "geometry": {"coordinates":[-3.8243288994,40.3479309082],"type":"Point"}
}