{
  "type": "Feature",
  "properties": {
    "addr:full":"Calle de Ruidera, 17 Coria Rio Sevilla 41100",
    "addr:housenumber":"17",
    "addr:postcode":"41100",
    "addr:street":"Calle De Ruidera;Rio Sevilla",
    "iso:country":"ES",
    "sg:address":"Calle de Ruidera, 17",
    "sg:city":"Coria Rio",
    "sg:orig_category":"Promotores Constructores",
    "sg:phone":"+34 954 77 07 59",
    "sg:postcode":"41100",
    "sg:province":"Sevilla",
    "wof:name":"Coriana De Construcciones Y Contratas S.l.",
    "wof:placetype":"venue"
},
  "geometry": {"coordinates":[-6.0515742302,37.2925949097],"type":"Point"}
}