{
  "type": "Feature",
  "properties": {
    "iso:country":"ES",
    "sg:address":"Carrer de Sant Isidre, 20",
    "sg:city":"Gava",
    "sg:orig_category":"Molduras, Junquillos, Listones Y Molduras Perforadas",
    "sg:phone":"+34 936 62 22 37",
    "sg:postcode":"08850",
    "sg:province":"Barcelona",
    "wof:name":"Ma\u00f1as Comas Enric",
    "wof:placetype":"venue"
},
  "geometry": {"coordinates":[2.0040290356,41.3055381775],"type":"Point"}
}