{
  "type": "Feature",
  "properties": {
    "iso:country":"ES",
    "sg:address":"Carrer de Muntaner, 182",
    "sg:city":"Barcelona",
    "sg:orig_category":"Cer\u00c1micas: Material Y Suministros",
    "sg:phone":"+34 934 05 25 27",
    "sg:postcode":"08036",
    "sg:province":"Barcelona",
    "sg:website":"www.arenaprofessional.com",
    "wof:name":"Arena Profesional S.l.",
    "wof:placetype":"venue"
},
  "geometry": {"coordinates":[2.1520159245,41.3922424316],"type":"Point"}
}