{
  "type": "Feature",
  "properties": {
    "iso:country":"ES",
    "sg:address":"Calle de Euskalduna, 1",
    "sg:city":"Bilbao",
    "sg:orig_category":"Reposter\u00cdas",
    "sg:phone":"+34 944 43 00 07",
    "sg:postcode":"48008",
    "sg:province":"Vizcaya",
    "wof:name":"Harino Panadera S.a.",
    "wof:placetype":"venue"
},
  "geometry": {"coordinates":[-2.9318909645,43.2588806152],"type":"Point"}
}