{
  "type": "Feature",
  "properties": {
    "addr:full":"Calle de Santa Catalina, 16 Segovia Segovia 40003",
    "addr:housenumber":"16",
    "addr:postcode":"40003",
    "addr:street":"Calle De Santa Catalina",
    "iso:country":"ES",
    "sg:address":"Calle de Santa Catalina, 16",
    "sg:city":"Segovia",
    "sg:orig_category":"Farmacias",
    "sg:phone":"+34 921 43 42 91",
    "sg:postcode":"40003",
    "sg:province":"Segovia",
    "wof:name":"Basterrechea De Las Heras Carmen",
    "wof:placetype":"venue"
},
  "geometry": {"coordinates":[-4.1128330231,40.9521865845],"type":"Point"}
}