{
  "type": "Feature",
  "properties": {
    "addr:full":"Calle de Jose Arcones Gil, 8 Madrid Madrid 28017",
    "addr:housenumber":"8",
    "addr:postcode":"madrid;28017",
    "addr:street":"Calle De Jose Arcones Gil",
    "iso:country":"ES",
    "sg:address":"Calle de Jose Arcones Gil, 8",
    "sg:city":"Madrid",
    "sg:orig_category":"Caf\u00c9s, Bares, Cervecer\u00cdas",
    "sg:phone":"+34 914 07 78 48",
    "sg:postcode":"28017",
    "sg:province":"Madrid",
    "wof:name":"Alonso Yusta Alberto",
    "wof:placetype":"venue"
},
  "geometry": {"coordinates":[-3.639169693,40.4364280701],"type":"Point"}
}