{
  "type": "Feature",
  "properties": {
    "addr:full":"Calle de Puentecilla, 15 Caravaca Cruz Murcia 30400",
    "addr:housenumber":"15",
    "addr:postcode":"30400",
    "addr:street":"Calle De Puentecilla",
    "iso:country":"ES",
    "sg:address":"Calle de Puentecilla, 15",
    "sg:city":"Caravaca Cruz",
    "sg:orig_category":"Estancos",
    "sg:phone":"+34 968 70 26 29",
    "sg:postcode":"30400",
    "sg:province":"Murcia",
    "wof:name":"Lopez Abad Maria Angustias",
    "wof:placetype":"venue"
},
  "geometry": {"coordinates":[-1.8598190546,38.107509613],"type":"Point"}
}