{
  "type": "Feature",
  "properties": {
    "iso:country":"ES",
    "sg:address":"Av Castelldefels, 189",
    "sg:city":"Castelldefels",
    "sg:orig_category":"Restaurantes",
    "sg:phone":"+34 936 36 61 72",
    "sg:postcode":"08860",
    "sg:province":"Barcelona",
    "wof:name":"Gimenez Rodriguez Francisco",
    "wof:placetype":"venue"
},
  "geometry": {"coordinates":[1.9720220566,41.2685050964],"type":"Point"}
}