{
  "type": "Feature",
  "properties": {
    "addr:full":"Calle de Lindo, 2 Cordoba C\u00f3rdoba 14001",
    "addr:housenumber":"2",
    "addr:postcode":"14001",
    "addr:street":"Calle De Lindo;Co\u0301Rdoba",
    "iso:country":"ES",
    "sg:address":"Calle de Lindo, 2",
    "sg:city":"Cordoba",
    "sg:orig_category":"Expertos Contables, Revisores De Cuentas",
    "sg:phone":"+34 957 47 36 48",
    "sg:postcode":"14001",
    "sg:province":"C\u00f3rdoba",
    "wof:name":"Servicios Reunidos Andaluces S. A.",
    "wof:placetype":"venue"
},
  "geometry": {"coordinates":[-4.7795491219,37.8876609802],"type":"Point"}
}