{
  "type": "Feature",
  "properties": {
    "addr:full":"Ctra. Hostalric S. Celoni, S/n Riells Girona 17404",
    "addr:housenumber":"s / n",
    "addr:postcode":"17404",
    "addr:street":"Ctra. Hostalric S. Celoni",
    "iso:country":"ES",
    "sg:address":"Ctra. Hostalric S. Celoni, S/n",
    "sg:city":"Riells",
    "sg:orig_category":"Transporte En General",
    "sg:phone":"+34 972 87 01 13",
    "sg:postcode":"17404",
    "sg:province":"Girona",
    "wof:name":"Rocalba S. A.",
    "wof:placetype":"venue"
},
  "geometry": {"coordinates":[2.5116300583,41.7771339417],"type":"Point"}
}