{
  "type": "Feature",
  "properties": {
    "iso:country":"ES",
    "sg:address":"Avda Castilla (de), 32",
    "sg:city":"Poligono De San Fernando De Henares",
    "sg:orig_category":"Tubos Y Tuber\u00cdas De Goma Y Pl\u00c1stico (fabricaci\u00d3n, Al Por Mayor)",
    "sg:phone":"+34 916 75 07 15",
    "sg:postcode":"28830",
    "sg:province":"Madrid",
    "wof:name":"Material De Aireacion S.a.",
    "wof:placetype":"venue"
},
  "geometry": {"coordinates":[-3.4944779873,40.4541397095],"type":"Point"}
}