{
  "type": "Feature",
  "properties": {
    "iso:country":"ES",
    "sg:address":"Calle de Comendador Salda\u00d1a, 3",
    "sg:city":"Bembibre",
    "sg:orig_category":"Carnicer\u00cdas, Carnicer\u00cdas",
    "sg:phone":"+34 987 51 00 45",
    "sg:postcode":"24300",
    "sg:province":"Le\u00f3n",
    "wof:name":"Ramos De La Puente Miguel",
    "wof:placetype":"venue"
},
  "geometry": {"coordinates":[-6.4202752113,42.6173210144],"type":"Point"}
}