{
  "type": "Feature",
  "properties": {
    "addr:full":"La Iglesia, S/n S. Llorente Paramo Palencia 34113",
    "addr:housenumber":"s / n",
    "addr:postcode":"34113",
    "iso:country":"ES",
    "sg:address":"La Iglesia, S/n",
    "sg:city":"S. Llorente Paramo",
    "sg:orig_category":"Cr\u00cda De Animales",
    "sg:phone":"+34 979 88 34 90",
    "sg:postcode":"34113",
    "sg:province":"Palencia",
    "wof:name":"Gutierrez Francia Pedro",
    "wof:placetype":"venue"
},
  "geometry": {"coordinates":[-4.746363163,42.4803886414],"type":"Point"}
}