{
  "type": "Feature",
  "properties": {
    "addr:full":"Pase Extremadura, 47 Madrid Madrid 28011",
    "addr:housenumber":"47",
    "addr:postcode":"madrid;28011",
    "addr:street":"Extremadura",
    "iso:country":"ES",
    "sg:address":"Pase Extremadura, 47",
    "sg:city":"Madrid",
    "sg:orig_category":"Comercio De Piezas De Recambio Y De Accesorios De Veh\u00cdculos, Veh\u00cdculos Industriales",
    "sg:phone":"+34 914 63 67 10",
    "sg:postcode":"28011",
    "sg:province":"Madrid",
    "sg:website":"www.garajelasflores.com",
    "wof:name":"Garaje Las Flores S. A.",
    "wof:placetype":"venue"
},
  "geometry": {"coordinates":[-3.7299325466,40.4130821228],"type":"Point"}
}