{
  "type": "Feature",
  "properties": {
    "addr:full":"Calle de Medio, 5 Santander Cantabria 39003",
    "addr:housenumber":"5",
    "addr:postcode":"39003",
    "addr:street":"Calle De Medio",
    "iso:country":"ES",
    "sg:address":"Calle de Medio, 5",
    "sg:city":"Santander",
    "sg:orig_category":"Molduras, Junquillos, Listones Y Molduras Perforadas",
    "sg:phone":"+34 942 22 10 12",
    "sg:postcode":"39003",
    "sg:province":"Cantabria",
    "wof:name":"Sociedad Regional De Informatica S.a.",
    "wof:placetype":"venue"
},
  "geometry": {"coordinates":[-3.8049619198,43.462726593],"type":"Point"}
}