{
  "type": "Feature",
  "properties": {
    "addr:full":"Carrer de Josep Anselm Clave, 11 Esplugues Llobregat Barcelona 08950",
    "addr:housenumber":"11",
    "addr:postcode":"08950",
    "addr:street":"Carrer De Josep Anselm Clave",
    "iso:country":"ES",
    "sg:address":"Carrer de Josep Anselm Clave, 11",
    "sg:city":"Esplugues Llobregat",
    "sg:orig_category":"Edici\u00d3n De Mapas, Gu\u00cdas Y Planos",
    "sg:phone":"+34 933 72 17 80",
    "sg:postcode":"08950",
    "sg:province":"Barcelona",
    "wof:name":"E2 Internacional Knives Sl",
    "wof:placetype":"venue"
},
  "geometry": {"coordinates":[2.0915219784,41.3765029907],"type":"Point"}
}