{
  "type": "Feature",
  "properties": {
    "addr:full":"Pase Andres Segovia, 20 Herradura Granada 18697",
    "addr:housenumber":"20",
    "addr:postcode":"18697",
    "addr:street":"Segovia",
    "iso:country":"ES",
    "sg:address":"Pase Andres Segovia, 20",
    "sg:city":"Herradura",
    "sg:orig_category":"Inmobiliaria (agencias)",
    "sg:phone":"+34 958 82 78 11",
    "sg:postcode":"18697",
    "sg:province":"Granada",
    "sg:website":"www.inmobiliakarcher.com",
    "wof:name":"Karcher  Maria Teresa",
    "wof:placetype":"venue"
},
  "geometry": {"coordinates":[-3.7390809059,36.7353096008],"type":"Point"}
}