{
  "type": "Feature",
  "properties": {
    "addr:full":"Zafra, 1 Bodonal De La Sierra Badajoz 06394",
    "addr:housenumber":"1",
    "addr:postcode":"06394",
    "addr:street":"Zafra",
    "iso:country":"ES",
    "sg:address":"Zafra, 1",
    "sg:city":"Bodonal De La Sierra",
    "sg:classifiers":[
        {
            "category":"Banks & Credit Unions",
            "subcategory":"Bureau De Change",
            "type":"Services"
        }
    ],
    "sg:phone":"+34 924 72 15 22",
    "sg:postcode":"06394",
    "sg:province":"Badajoz",
    "sg:tags":[
        "organismos",
        "control"
    ],
    "wof:name":"Agroaacion S.l.",
    "wof:placetype":"venue"
},
  "geometry": {"coordinates":[-6.54631567,38.1659545898],"type":"Point"}
}