{
  "type": "Feature",
  "properties": {
    "addr:full":"Calle de Isilla, 6 Aranda Duero Burgos 09400",
    "addr:housenumber":"6",
    "addr:postcode":"09400",
    "addr:street":"Calle De Isilla",
    "iso:country":"ES",
    "sg:address":"Calle de Isilla, 6",
    "sg:city":"Aranda Duero",
    "sg:orig_category":"Confecci\u00d3n De Zapatos",
    "sg:phone":"+34 947 54 60 94",
    "sg:postcode":"09400",
    "sg:province":"Burgos",
    "wof:name":"San Martin Garcia Elena",
    "wof:placetype":"venue"
},
  "geometry": {"coordinates":[-3.6867649555,41.6710777283],"type":"Point"}
}