{
  "type": "Feature",
  "properties": {
    "iso:country":"ES",
    "sg:address":"Cjon San Adrian, S/n",
    "sg:city":"Valladolid",
    "sg:orig_category":"Mataderos De Poller\u00cda",
    "sg:phone":"+34 983 22 30 34",
    "sg:postcode":"47008",
    "sg:province":"Valladolid",
    "wof:name":"Sada P.a. Castilla-galicia S.a.",
    "wof:placetype":"venue"
},
  "geometry": {"coordinates":[-4.7927489281,41.6193618774],"type":"Point"}
}