{
  "type": "Feature",
  "properties": {
    "iso:country":"ES",
    "sg:address":"Calle de Virgen Del Rocio, 16",
    "sg:city":"Majadahonda",
    "sg:orig_category":"Abogados",
    "sg:phone":"+34 916 38 56 22",
    "sg:postcode":"28220",
    "sg:province":"Madrid",
    "wof:name":"Cremades Tudela Juan",
    "wof:placetype":"venue"
},
  "geometry": {"coordinates":[-3.8647611141,40.4737701416],"type":"Point"}
}