{
  "type": "Feature",
  "properties": {
    "addr:full":"Calle de Antonio Bernal, 9 Cehegin Murcia 30430",
    "addr:housenumber":"9",
    "addr:postcode":"30430",
    "addr:street":"Calle De Antonio Bernal",
    "iso:country":"ES",
    "sg:address":"Calle de Antonio Bernal, 9",
    "sg:city":"Cehegin",
    "sg:orig_category":"Confiter\u00cda, Galletas Y Pastas, Chocolater\u00cda (al Por Mayor)",
    "sg:phone":"+34 968 74 02 44",
    "sg:postcode":"30430",
    "sg:province":"Murcia",
    "wof:name":"Exclusivas Crstobal Pintor,sl",
    "wof:placetype":"venue"
},
  "geometry": {"coordinates":[-1.7949393988,38.0965118408],"type":"Point"}
}