{
  "type": "Feature",
  "properties": {
    "iso:country":"ES",
    "sg:address":"Avda Santander, 3",
    "sg:city":"Noja",
    "sg:orig_category":"Ropa Para Se\u00d1oras Y Caballeros (al Por Menor)",
    "sg:phone":"+34 942 63 00 85",
    "sg:postcode":"39180",
    "sg:province":"Cantabria",
    "wof:name":"Bafler  Klaus Aloes",
    "wof:placetype":"venue"
},
  "geometry": {"coordinates":[-3.5228636265,43.4794578552],"type":"Point"}
}