{
  "type": "Feature",
  "properties": {
    "addr:full":"Calle de Chaparil (el), 11 Nerja M\u00e1laga 29780",
    "addr:housenumber":"11",
    "addr:postcode":"29780",
    "addr:street":"Calle De Chaparil El",
    "iso:country":"ES",
    "sg:address":"Calle de Chaparil (el), 11",
    "sg:city":"Nerja",
    "sg:orig_category":"Alquiler De Veh\u00cdculos: Turismos Y Utilitarios",
    "sg:phone":"+34 952 52 67 70",
    "sg:postcode":"29780",
    "sg:province":"M\u00e1laga",
    "sg:website":"www.nizacars.es",
    "wof:name":"Niza Cars S.l.u.",
    "wof:placetype":"venue"
},
  "geometry": {"coordinates":[-3.8812851906,36.7457199097],"type":"Point"}
}