{
  "type": "Feature",
  "properties": {
    "iso:country":"ES",
    "sg:address":"Carrer de Septimania, 44",
    "sg:city":"Barcelona",
    "sg:orig_category":"Arquitectos",
    "sg:phone":"+34 934 18 16 41",
    "sg:postcode":"08006",
    "sg:province":"Barcelona",
    "wof:name":"Iglesias Rey Javier",
    "wof:placetype":"venue"
},
  "geometry": {"coordinates":[2.1460239887,41.4048919678],"type":"Point"}
}