{
  "type": "Feature",
  "properties": {
    "iso:country":"ES",
    "sg:address":"Plaz Miraflores, 44",
    "sg:city":"Marbella",
    "sg:orig_category":"Alumbrados",
    "sg:phone":"+34 952 86 55 03",
    "sg:postcode":"29600",
    "sg:province":"M\u00e1laga",
    "wof:name":"Romero Oliver Isabel",
    "wof:placetype":"venue"
},
  "geometry": {"coordinates":[-4.8833007812,36.5079956055],"type":"Point"}
}