{
  "type": "Feature",
  "properties": {
    "iso:country":"ES",
    "sg:address":"Avda Andalucia, 50",
    "sg:city":"Alhaurin El Grande",
    "sg:orig_category":"Material Y Herramientas Agr\u00cdcolas",
    "sg:phone":"+34 952 49 12 51",
    "sg:postcode":"29120",
    "sg:province":"M\u00e1laga",
    "wof:name":"Gator S.l.",
    "wof:placetype":"venue"
},
  "geometry": {"coordinates":[-4.6952810287,36.6377067566],"type":"Point"}
}