{
  "type": "Feature",
  "properties": {
    "addr:full":"Pase Berio De, 13 Donostia-san Sebastian Guip\u00f9zcoa 20018",
    "addr:housenumber":"13",
    "addr:postcode":"20018",
    "iso:country":"ES",
    "sg:address":"Pase Berio De, 13",
    "sg:city":"Donostia-san Sebastian",
    "sg:orig_category":"Asesor\u00cdas En Comunicaci\u00d3n",
    "sg:phone":"+34 943 21 53 72",
    "sg:postcode":"20018",
    "sg:province":"Guip\u00f9zcoa",
    "sg:website":"www.rcrasesiria.com",
    "wof:name":"Roberto Gomez Grado Y Otra C.b.",
    "wof:placetype":"venue"
},
  "geometry": {"coordinates":[-2.0029520988,43.2836837769],"type":"Point"}
}