{
  "type": "Feature",
  "properties": {
    "addr:full":"Alhama, Km. 0024,0 Cuevas Reyllo Murcia 30333",
    "addr:postcode":"30333",
    "addr:street":"Alhama;0024,0",
    "iso:country":"ES",
    "sg:address":"Alhama, Km. 0024,0",
    "sg:city":"Cuevas Reyllo",
    "sg:orig_category":"Hormigonados",
    "sg:phone":"+34 968 15 26 73",
    "sg:postcode":"30333",
    "sg:province":"Murcia",
    "wof:name":"Falla Castillejo Jose Antonio",
    "wof:placetype":"venue"
},
  "geometry": {"coordinates":[-1.2445290089,37.7351493835],"type":"Point"}
}