{
  "type": "Feature",
  "properties": {
    "addr:full":"Avda Victoria (la), S/n Laredo Cantabria 39770",
    "addr:housenumber":"/ n",
    "addr:postcode":"39770",
    "addr:street":"Avda Victoria La S",
    "iso:country":"ES",
    "sg:address":"Avda Victoria (la), S/n",
    "sg:city":"Laredo",
    "sg:orig_category":"Agencias Y Agentes Comerciales, Representantes",
    "sg:phone":"+34 942 60 31 32",
    "sg:postcode":"39770",
    "sg:province":"Cantabria",
    "wof:name":"Pellon Araujo Jose Manuel",
    "wof:placetype":"venue"
},
  "geometry": {"coordinates":[-3.4265539646,43.4092788696],"type":"Point"}
}