{
  "type": "Feature",
  "properties": {
    "addr:full":"Calle de Julio Rey Pastor, 4 Madrid Madrid 28007",
    "addr:housenumber":"4",
    "addr:postcode":"28007",
    "addr:street":"Calle De Julio Rey Pastor",
    "iso:country":"ES",
    "sg:address":"Calle de Julio Rey Pastor, 4",
    "sg:city":"Madrid",
    "sg:orig_category":"Promotores Constructores",
    "sg:phone":"+34 915 01 71 35",
    "sg:postcode":"28007",
    "sg:province":"Madrid",
    "wof:name":"Arroyo Perales Irene",
    "wof:placetype":"venue"
},
  "geometry": {"coordinates":[-3.676006794,40.4079666138],"type":"Point"}
}