{
  "type": "Feature",
  "properties": {
    "iso:country":"ES",
    "sg:address":"Calle de San Bernardo, 20",
    "sg:city":"Madrid",
    "sg:orig_category":"Cine (producci\u00d3n, Realizaci\u00d3n)",
    "sg:phone":"+34 915 32 66 20",
    "sg:postcode":"28015",
    "sg:province":"Madrid",
    "wof:name":"Arturo Gonzalez Reproducciones Cinematograficas S. A.",
    "wof:placetype":"venue"
},
  "geometry": {"coordinates":[-3.7075953484,40.4228668213],"type":"Point"}
}