{
  "type": "Feature",
  "properties": {
    "iso:country":"ES",
    "sg:address":"Ctra Valdegalindo, Km. 0002,0",
    "sg:city":"Villamediana Iregua",
    "sg:orig_category":"Cerrajer\u00cda, Ferrallista",
    "sg:phone":"+34 941 43 50 34",
    "sg:postcode":"26142",
    "sg:province":"La Rioja",
    "wof:name":"Talleres Y Cerrajeria Resa S.l.",
    "wof:placetype":"venue"
},
  "geometry": {"coordinates":[-2.417953968,42.4283485413],"type":"Point"}
}