{
  "type": "Feature",
  "properties": {
    "addr:full":"Carrer de Tajo, S/n Barcelona Barcelona 08032",
    "addr:housenumber":"s / n",
    "addr:postcode":"08032",
    "addr:street":"Carrer De Tajo",
    "iso:country":"ES",
    "sg:address":"Carrer de Tajo, S/n",
    "sg:city":"Barcelona",
    "sg:orig_category":"Pescader\u00cdas (al Por Menor)",
    "sg:phone":"+34 934 07 00 09",
    "sg:postcode":"08032",
    "sg:province":"Barcelona",
    "wof:name":"Olivart Pla Francisca",
    "wof:placetype":"venue"
},
  "geometry": {"coordinates":[2.159514904,41.4296798706],"type":"Point"}
}