{
  "type": "Feature",
  "properties": {
    "iso:country":"ES",
    "sg:address":"Carrer de Major, 64",
    "sg:city":"Sabadell",
    "sg:orig_category":"Abogados",
    "sg:phone":"+34 937 27 43 66",
    "sg:postcode":"08208",
    "sg:province":"Barcelona",
    "wof:name":"Romero Casquero Sergio",
    "wof:placetype":"venue"
},
  "geometry": {"coordinates":[2.100538969,41.5559387207],"type":"Point"}
}