{
  "type": "Feature",
  "properties": {
    "iso:country":"ES",
    "sg:address":"Plaz San Miguel, 2",
    "sg:city":"Zamora",
    "sg:orig_category":"Promotores Constructores",
    "sg:phone":"+34 980 53 21 48",
    "sg:postcode":"49001",
    "sg:province":"Zamora",
    "wof:name":"Anton Prieto Jose",
    "wof:placetype":"venue"
},
  "geometry": {"coordinates":[-5.7425556183,41.5056266785],"type":"Point"}
}