{
  "type": "Feature",
  "properties": {
    "iso:country":"ES",
    "sg:address":"Pg Maria Auxiliadora, 3",
    "sg:city":"Casc Urba",
    "sg:orig_category":"Concepci\u00d3n Y Realizaci\u00d3n De Maquetas Profesionales Y Prototipos",
    "sg:phone":"+34 935 40 11 11",
    "sg:postcode":"08328",
    "sg:province":"Barcelona",
    "wof:name":"Productos Para Modelismo S.l.",
    "wof:placetype":"venue"
},
  "geometry": {"coordinates":[2.2946848869,41.4925308228],"type":"Point"}
}