{
  "type": "Feature",
  "properties": {
    "iso:country":"ES",
    "sg:address":"Av Mistral, 6",
    "sg:city":"Barcelona",
    "sg:orig_category":"Arquitectos",
    "sg:phone":"+34 933 25 05 62",
    "sg:postcode":"08015",
    "sg:province":"Barcelona",
    "wof:name":"Vizcarro Pedrol Jaime",
    "wof:placetype":"venue"
},
  "geometry": {"coordinates":[2.1593196392,41.3776435852],"type":"Point"}
}