{
  "type": "Feature",
  "properties": {
    "addr:full":"Carrer de Princesa, 55 Barcelona Barcelona 08003",
    "addr:housenumber":"55",
    "addr:postcode":"08003",
    "addr:street":"Carrer De Princesa",
    "iso:country":"ES",
    "sg:address":"Carrer de Princesa, 55",
    "sg:city":"Barcelona",
    "sg:orig_category":"Comerciantes Al Por Mayor De Vinos, Licores Y Alcoholes",
    "sg:phone":"+34 933 19 10 62",
    "sg:postcode":"08003",
    "sg:province":"Barcelona",
    "wof:name":"Tesi Saez S.l.",
    "wof:placetype":"venue"
},
  "geometry": {"coordinates":[2.1823689938,41.3870658875],"type":"Point"}
}