{
  "type": "Feature",
  "properties": {
    "iso:country":"ES",
    "sg:address":"Calle de Beato Juan De Avila, 7",
    "sg:city":"Fuensalida",
    "sg:orig_category":"Caf\u00c9s, Bares, Cervecer\u00cdas",
    "sg:phone":"+34 925 78 52 97",
    "sg:postcode":"45510",
    "sg:province":"Toledo",
    "wof:name":"Mapayoli S.l.",
    "wof:placetype":"venue"
},
  "geometry": {"coordinates":[-4.2135925293,40.0488853455],"type":"Point"}
}