{
  "type": "Feature",
  "properties": {
    "addr:full":"Calle de Ribadesella, S/n Bomberos Madrid 28250",
    "addr:housenumber":"s",
    "addr:postcode":"28250",
    "addr:street":"Calle De Ribadesella;/ N",
    "iso:country":"ES",
    "sg:address":"Calle de Ribadesella, S/n",
    "sg:city":"Bomberos",
    "sg:orig_category":"Inversiones",
    "sg:phone":"+34 918 59 56 00",
    "sg:postcode":"28250",
    "sg:province":"Madrid",
    "wof:name":"Hans Sevilla Inversiones S.l.",
    "wof:placetype":"venue"
},
  "geometry": {"coordinates":[-3.9306790829,40.57654953],"type":"Point"}
}