{
  "type": "Feature",
  "properties": {
    "iso:country":"ES",
    "sg:address":"Calle de Cullera, 19",
    "sg:city":"Benimamet-beniferri",
    "sg:orig_category":"Inform\u00c1tica: Mantenimiento Y Reparaci\u00d3n De Ordenadores",
    "sg:phone":"+34 963 16 00 86",
    "sg:postcode":"46035",
    "sg:province":"Valencia",
    "wof:name":"Jose Dura Instalaciones Informaticas S.l.",
    "wof:placetype":"venue"
},
  "geometry": {"coordinates":[-0.3768048882,39.4702377319],"type":"Point"}
}