{
  "type": "Feature",
  "properties": {
    "addr:full":"Ctra Fuente Del Gallo, S/n Fuente Del Gallo C\u00e1diz 11140",
    "addr:postcode":"11140",
    "addr:street":"Ctra Fuente Del Gallo S / N Fuente Del Gallo Ca\u0301Diz",
    "iso:country":"ES",
    "sg:address":"Ctra Fuente Del Gallo, S/n",
    "sg:city":"Fuente Del Gallo",
    "sg:orig_category":"Restaurantes",
    "sg:phone":"+34 956 44 02 05",
    "sg:postcode":"11140",
    "sg:province":"C\u00e1diz",
    "wof:name":"Restaurante El Roqueo S.a.l.",
    "wof:placetype":"venue"
},
  "geometry": {"coordinates":[-6.0870790482,36.2767066956],"type":"Point"}
}