{
  "type": "Feature",
  "properties": {
    "iso:country":"ES",
    "sg:address":"Calle de Guipuzcoa, 4",
    "sg:city":"Alsasua",
    "sg:orig_category":"M\u00c9dicos: Medicina General",
    "sg:phone":"+34 948 46 87 35",
    "sg:postcode":"31800",
    "sg:province":"Navarra",
    "wof:name":"Campo Guinea Maria Teresa",
    "wof:placetype":"venue"
},
  "geometry": {"coordinates":[-2.1741199493,42.8938026428],"type":"Point"}
}