{
  "type": "Feature",
  "properties": {
    "iso:country":"ES",
    "sg:address":"Calle de Rio Gallego, 1",
    "sg:city":"Ejea De Los Caballeros",
    "sg:orig_category":"Peluquer\u00cdas, Peluquer\u00cda Mixta",
    "sg:phone":"+34 976 66 37 14",
    "sg:postcode":"50600",
    "sg:province":"Zaragoza",
    "wof:name":"Ba\u00f1os Garrido Maria Pilar",
    "wof:placetype":"venue"
},
  "geometry": {"coordinates":[-1.1315040588,42.1252098083],"type":"Point"}
}