{
  "type": "Feature",
  "properties": {
    "iso:country":"ES",
    "sg:address":"Calle de Heraclio Sanchez, 14",
    "sg:city":"San Cristobal De La Laguna",
    "sg:orig_category":"Ropa Para Se\u00d1oras (al Por Menor)",
    "sg:phone":"+34 922 63 01 10",
    "sg:postcode":"38204",
    "sg:province":"Santa Cruz De Tenerife",
    "wof:name":"Encuentros Moda S.a.",
    "wof:placetype":"venue"
},
  "geometry": {"coordinates":[-16.3153972626,28.4862442017],"type":"Point"}
}