{
  "type": "Feature",
  "properties": {
    "addr:full":"Calle de Caldereria, 7 Malaga M\u00e1laga 29008",
    "addr:housenumber":"7",
    "addr:postcode":"29008",
    "addr:street":"Calle De Caldereria;Ma\u0301Laga",
    "iso:country":"ES",
    "sg:address":"Calle de Caldereria, 7",
    "sg:city":"Malaga",
    "sg:orig_category":"Promotores Constructores",
    "sg:phone":"+34 952 22 99 88",
    "sg:postcode":"29008",
    "sg:province":"M\u00e1laga",
    "sg:website":"www.jochr.com",
    "wof:name":"Construcciones Jochr S.l.",
    "wof:placetype":"venue"
},
  "geometry": {"coordinates":[-4.4206619263,36.7221412659],"type":"Point"}
}