{
  "type": "Feature",
  "properties": {
    "iso:country":"ES",
    "sg:address":"Covadonga, 11",
    "sg:city":"Infiesto",
    "sg:orig_category":"Cl\u00cdnicas Dentales",
    "sg:phone":"+34 985 71 04 60",
    "sg:postcode":"33530",
    "sg:province":"Asturias",
    "wof:name":"Clinica Dental San Esteban S.l.",
    "wof:placetype":"venue"
},
  "geometry": {"coordinates":[-5.3617148399,43.3456230164],"type":"Point"}
}