{
  "type": "Feature",
  "properties": {
    "addr:full":"Carrer de Roca I Humbert, 30 Hospitalet Llobregat Barcelona 08907",
    "addr:housenumber":"30",
    "addr:postcode":"08907",
    "addr:street":"Carrer De Roca I Humbert",
    "iso:country":"ES",
    "sg:address":"Carrer de Roca I Humbert, 30",
    "sg:city":"Hospitalet Llobregat",
    "sg:orig_category":"Cerrajer\u00cda, Ferrallista",
    "sg:phone":"+34 933 38 18 46",
    "sg:postcode":"08907",
    "sg:province":"Barcelona",
    "wof:name":"Talleres Ruesca S.c.p.",
    "wof:placetype":"venue"
},
  "geometry": {"coordinates":[2.1025240421,41.3549804688],"type":"Point"}
}