{
  "type": "Feature",
  "properties": {
    "addr:full":"Las Chafiras, 7 Las Chafiras Santa Cruz De Tenerife 38639",
    "addr:housenumber":"7",
    "addr:postcode":"38639",
    "addr:street":"Las Chafiras",
    "iso:country":"ES",
    "sg:address":"Las Chafiras, 7",
    "sg:city":"Las Chafiras",
    "sg:orig_category":"Caf\u00c9s, Bares, Cervecer\u00cdas",
    "sg:phone":"+34 922 73 52 07",
    "sg:postcode":"38639",
    "sg:province":"Santa Cruz De Tenerife",
    "sg:website":"www.club_larosa.com",
    "wof:name":"Munnia  Guy Joseph",
    "wof:placetype":"venue"
},
  "geometry": {"coordinates":[-16.6115474701,28.0350246429],"type":"Point"}
}