{
  "type": "Feature",
  "properties": {
    "iso:country":"ES",
    "sg:address":"Rsdal. Vista Alegre, S/n",
    "sg:city":"Alcoceber",
    "sg:orig_category":"Caf\u00c9s, Bares, Cervecer\u00cdas",
    "sg:phone":"+34 964 41 29 20",
    "sg:postcode":"12579",
    "sg:province":"Castell\u00f3n",
    "wof:name":"Bar La Maya S.c.",
    "wof:placetype":"venue"
},
  "geometry": {"coordinates":[0.2850950062,40.2547187805],"type":"Point"}
}