{
  "type": "Feature",
  "properties": {
    "addr:full":"Calle de Puerto Bajo, 1 Nava Huelva 21370",
    "addr:housenumber":"1",
    "addr:postcode":"21370",
    "addr:street":"Calle De Puerto Bajo",
    "iso:country":"ES",
    "sg:address":"Calle de Puerto Bajo, 1",
    "sg:city":"Nava",
    "sg:orig_category":"Empresas De Desmonte",
    "sg:phone":"+34 959 12 15 77",
    "sg:postcode":"21370",
    "sg:province":"Huelva",
    "wof:name":"Fernandez Fructos Federico",
    "wof:placetype":"venue"
},
  "geometry": {"coordinates":[-6.9495902061,37.2563095093],"type":"Point"}
}