{
  "type": "Feature",
  "properties": {
    "iso:country":"ES",
    "sg:address":"Carrer de Industria, 17",
    "sg:city":"Sabadell",
    "sg:orig_category":"Expertos Contables Pasantes Autorizados",
    "sg:phone":"+34 937 27 61 55",
    "sg:postcode":"08202",
    "sg:province":"Barcelona",
    "wof:name":"Serveis Juridic Economic I Fiscals.l.",
    "wof:placetype":"venue"
},
  "geometry": {"coordinates":[2.111107111,41.5473060608],"type":"Point"}
}