{
  "type": "Feature",
  "properties": {
    "iso:country":"ES",
    "sg:address":"P. Nueva Antequera, S/n",
    "sg:city":"Antequera",
    "sg:orig_category":"Mec\u00c1nico Del Autom\u00d3vil",
    "sg:phone":"+34 952 70 30 73",
    "sg:postcode":"29200",
    "sg:province":"M\u00e1laga",
    "wof:name":"Rodriguez Rodriguez Francisco Jesus",
    "wof:placetype":"venue"
},
  "geometry": {"coordinates":[-4.5957288742,37.0245895386],"type":"Point"}
}