{
  "type": "Feature",
  "properties": {
    "addr:full":"Calle de Corazon De Jesus, 5 Lucena C\u00f3rdoba 14900",
    "addr:housenumber":"5",
    "addr:postcode":"14900",
    "addr:street":"Calle De Corazon;Jesus",
    "iso:country":"ES",
    "sg:address":"Calle de Corazon De Jesus, 5",
    "sg:city":"Lucena",
    "sg:orig_category":"Charcuter\u00cdas (al Por Mayor)",
    "sg:phone":"+34 957 50 33 35",
    "sg:postcode":"14900",
    "sg:province":"C\u00f3rdoba",
    "wof:name":"Exclusivas Campa\u00f1a Garcia S.l.",
    "wof:placetype":"venue"
},
  "geometry": {"coordinates":[-4.4960546494,37.4077415466],"type":"Point"}
}