{
  "type": "Feature",
  "properties": {
    "iso:country":"ES",
    "sg:address":"Avgd Cerdanya, S/n",
    "sg:city":"Badalona",
    "sg:orig_category":"Negocio De Materiales De Construcci\u00d3n",
    "sg:phone":"+34 934 65 77 11",
    "sg:postcode":"08915",
    "sg:province":"Barcelona",
    "wof:name":"Nuria Antonijoan S.l.",
    "wof:placetype":"venue"
},
  "geometry": {"coordinates":[2.2451078892,41.4662322998],"type":"Point"}
}