{
  "type": "Feature",
  "properties": {
    "addr:full":"Avda Muel, 15 Zaragoza Zaragoza 50014",
    "addr:housenumber":"15",
    "addr:postcode":"50014",
    "addr:street":"Avda Muel",
    "iso:country":"ES",
    "sg:address":"Avda Muel, 15",
    "sg:city":"Zaragoza",
    "sg:orig_category":"Mec\u00c1nico Del Autom\u00d3vil",
    "sg:phone":"+34 976 29 29 10",
    "sg:postcode":"50014",
    "sg:province":"Zaragoza",
    "wof:name":"Cartie Castillo Jacinto Jose",
    "wof:placetype":"venue"
},
  "geometry": {"coordinates":[-0.8693429828,41.6598205566],"type":"Point"}
}