{
  "type": "Feature",
  "properties": {
    "iso:country":"ES",
    "sg:address":"Avgd Denia, 65",
    "sg:city":"Orba",
    "sg:orig_category":"Fabrica De Cer\u00c1micas",
    "sg:phone":"+34 965 58 30 14",
    "sg:postcode":"03790",
    "sg:province":"Alicante",
    "wof:name":"Prats Zaragoza Jose Vicente",
    "wof:placetype":"venue"
},
  "geometry": {"coordinates":[-0.0612829998,38.7821502686],"type":"Point"}
}