{
  "type": "Feature",
  "properties": {
    "addr:full":"Avda Jose Luis Arrese, 35 Valladolid Valladolid 47014",
    "addr:housenumber":"35",
    "addr:postcode":"47014",
    "addr:street":"Avda Jose Luis Arrese",
    "iso:country":"ES",
    "sg:address":"Avda Jose Luis Arrese, 35",
    "sg:city":"Valladolid",
    "sg:orig_category":"Alumbrados",
    "sg:phone":"+34 983 37 96 77",
    "sg:postcode":"47014",
    "sg:province":"Valladolid",
    "wof:name":"Daisalux S.a.",
    "wof:placetype":"venue"
},
  "geometry": {"coordinates":[-4.7438549995,41.6522979736],"type":"Point"}
}