{
  "type": "Feature",
  "properties": {
    "iso:country":"ES",
    "sg:address":"Carrer de N Trescientos Veinticuatro, S/n",
    "sg:city":"Dolar",
    "sg:orig_category":"Agricultura: Abastecimiento Y Cosechado (negocio)",
    "sg:phone":"+34 958 34 51 57",
    "sg:postcode":"18512",
    "sg:province":"Granada",
    "wof:name":"Peregrin S.l.",
    "wof:placetype":"venue"
},
  "geometry": {"coordinates":[-3.0600171089,37.1826705933],"type":"Point"}
}