{
  "type": "Feature",
  "properties": {
    "iso:country":"ES",
    "sg:address":"Calle de Antonio Lopez, 11",
    "sg:city":"S. Fernando",
    "sg:orig_category":"Telas Y Sedas (al Por Menor)",
    "sg:phone":"+34 956 88 15 12",
    "sg:postcode":"11100",
    "sg:province":"C\u00e1diz",
    "wof:name":"Rendon Sainz Juan Jose",
    "wof:placetype":"venue"
},
  "geometry": {"coordinates":[-6.1986060143,36.466178894],"type":"Point"}
}