{
  "type": "Feature",
  "properties": {
    "addr:full":"Calle de Lope De Vega-campoamor, S/n Dehesa Campoamor Alicante 03189",
    "addr:housenumber":"s / n",
    "addr:postcode":"03189",
    "addr:street":"Calle De Lope De Vega-Campoamor",
    "iso:country":"ES",
    "sg:address":"Calle de Lope De Vega-campoamor, S/n",
    "sg:city":"Dehesa Campoamor",
    "sg:orig_category":"Oficinas Y Gesti\u00d3n De Inmuebles",
    "sg:phone":"+34 965 32 27 37",
    "sg:postcode":"03189",
    "sg:province":"Alicante",
    "wof:name":"Pepe Ballester S.l.",
    "wof:placetype":"venue"
},
  "geometry": {"coordinates":[-0.7677609921,37.9303321838],"type":"Point"}
}