{
  "type": "Feature",
  "properties": {
    "iso:country":"ES",
    "sg:address":"Avda Andalucia, S/n",
    "sg:city":"Puente Genave",
    "sg:orig_category":"Molduras, Junquillos, Listones Y Molduras Perforadas",
    "sg:phone":"+34 953 43 50 33",
    "sg:postcode":"23350",
    "sg:province":"Ja\u00e9n",
    "wof:name":"Torres Fernandez Jose",
    "wof:placetype":"venue"
},
  "geometry": {"coordinates":[-2.8031339645,38.3540000916],"type":"Point"}
}