{
  "type": "Feature",
  "properties": {
    "addr:full":"Carr Guifre, 156 Badalona Barcelona 08912",
    "addr:housenumber":"156",
    "addr:postcode":"08912",
    "addr:street":"Carr Guifre",
    "iso:country":"ES",
    "sg:address":"Carr Guifre, 156",
    "sg:city":"Badalona",
    "sg:orig_category":"Institutos De Belleza",
    "sg:phone":"+34 933 97 69 76",
    "sg:postcode":"08912",
    "sg:province":"Barcelona",
    "sg:website":"www.monseandurell.com",
    "wof:name":"Andurell Samper Montserrat",
    "wof:placetype":"venue"
},
  "geometry": {"coordinates":[2.2429456711,41.4449005127],"type":"Point"}
}