{
  "type": "Feature",
  "properties": {
    "iso:country":"ES",
    "sg:address":"Luga Mercado Las Palmas, S/n",
    "sg:city":"Palmas De Gran Canaria",
    "sg:orig_category":"Transportes Por Carretera: Lotes Completos, Mercanc\u00cdas Diversas",
    "sg:phone":"+34 928 31 11 73",
    "sg:postcode":"35001",
    "sg:province":"Las Palmas",
    "wof:name":"Garcia Suarez Placido Ramon",
    "wof:placetype":"venue"
},
  "geometry": {"coordinates":[-15.4160404205,28.0998096466],"type":"Point"}
}