{
  "type": "Feature",
  "properties": {
    "addr:full":"Carrer de Doctor Trueta, 46 Barcelona Barcelona 08005",
    "addr:housenumber":"46",
    "addr:postcode":"08005",
    "addr:street":"Carrer De Doctor Trueta",
    "iso:country":"ES",
    "sg:address":"Carrer de Doctor Trueta, 46",
    "sg:city":"Barcelona",
    "sg:orig_category":"Venta, Localizaci\u00d3n, Reparaci\u00d3n De Material E Instrumental M\u00c9dico",
    "sg:phone":"+34 932 25 65 00",
    "sg:postcode":"08005",
    "sg:province":"Barcelona",
    "wof:name":"Mediform Tecnologias Medicas S.l.",
    "wof:placetype":"venue"
},
  "geometry": {"coordinates":[2.1945960522,41.3917884827],"type":"Point"}
}