{
  "type": "Feature",
  "properties": {
    "addr:full":"Calle de San Jose, 37 Cantillana Sevilla 41320",
    "addr:housenumber":"37",
    "addr:postcode":"41320",
    "addr:street":"Calle De San",
    "iso:country":"ES",
    "sg:address":"Calle de San Jose, 37",
    "sg:city":"Cantillana",
    "sg:orig_category":"Persianas Interiores, Exteriores",
    "sg:phone":"+34 955 73 01 82",
    "sg:postcode":"41320",
    "sg:province":"Sevilla",
    "wof:name":"Rios Lozano Manuel",
    "wof:placetype":"venue"
},
  "geometry": {"coordinates":[-5.823677063,37.60779953],"type":"Point"}
}