{
  "type": "Feature",
  "properties": {
    "addr:full":"Barr Usabal Auzoa, 123 Usabal Guip\u00f9zcoa 20400",
    "addr:housenumber":"123",
    "addr:postcode":"20400",
    "addr:street":"Usabal Auzoa;Guipu\u0300Zcoa",
    "iso:country":"ES",
    "sg:address":"Barr Usabal Auzoa, 123",
    "sg:city":"Usabal",
    "sg:orig_category":"Fabricaci\u00d3n Y Comercio De M\u00c1quinas",
    "sg:phone":"+34 943 67 01 66",
    "sg:postcode":"20400",
    "sg:province":"Guip\u00f9zcoa",
    "wof:name":"Tax S. Coop.",
    "wof:placetype":"venue"
},
  "geometry": {"coordinates":[-2.0789339542,43.1339912415],"type":"Point"}
}