{
  "type": "Feature",
  "properties": {
    "iso:country":"ES",
    "sg:address":"Carrer de Alfons Iv, 42",
    "sg:city":"Granollers",
    "sg:orig_category":"Carnicer\u00cdas, Carnicer\u00cdas",
    "sg:phone":"+34 938 70 04 74",
    "sg:postcode":"08401",
    "sg:province":"Barcelona",
    "wof:name":"Sararols Oliveros Jaume",
    "wof:placetype":"venue"
},
  "geometry": {"coordinates":[2.2879550457,41.6045227051],"type":"Point"}
}