{
  "type": "Feature",
  "properties": {
    "iso:country":"ES",
    "sg:address":"Calle de Bolsa, 50",
    "sg:city":"Sanlucar De Barrameda",
    "sg:orig_category":"Asesor\u00cda Fiscal Y Jur\u00cddica",
    "sg:phone":"+34 956 38 33 77",
    "sg:postcode":"11540",
    "sg:province":"C\u00e1diz",
    "wof:name":"Aseconfis Asesores S.l.",
    "wof:placetype":"venue"
},
  "geometry": {"coordinates":[-6.3518815041,36.7812194824],"type":"Point"}
}