{
  "type": "Feature",
  "properties": {
    "iso:country":"ES",
    "sg:address":"Calle de Literato Azorin, 4",
    "sg:city":"Xirivella",
    "sg:orig_category":"Cristaler\u00cdas",
    "sg:phone":"+34 963 83 77 18",
    "sg:postcode":"46950",
    "sg:province":"Valencia",
    "wof:name":"Copercris S.c.v.",
    "wof:placetype":"venue"
},
  "geometry": {"coordinates":[-0.424439013,39.4640541077],"type":"Point"}
}