{
  "type": "Feature",
  "properties": {
    "addr:full":"Calle de Zarco, 4 Baena C\u00f3rdoba 14850",
    "addr:housenumber":"4",
    "addr:postcode":"14850",
    "addr:street":"Calle De Zarco",
    "iso:country":"ES",
    "sg:address":"Calle de Zarco, 4",
    "sg:city":"Baena",
    "sg:orig_category":"Asesor\u00cda Sobre Comunicaci\u00d3n De Empresas",
    "sg:phone":"+34 957 67 07 15",
    "sg:postcode":"14850",
    "sg:province":"C\u00f3rdoba",
    "wof:name":"Lara Vivar Antonio",
    "wof:placetype":"venue"
},
  "geometry": {"coordinates":[-4.3234171867,37.6148490906],"type":"Point"}
}