{
  "type": "Feature",
  "properties": {
    "addr:full":"Rua Rocon, 1 Cambre La Coru\u00f1a 15660",
    "addr:housenumber":"1",
    "addr:postcode":"15660",
    "addr:street":"Rua Rocon;La Corun\u0303A",
    "iso:country":"ES",
    "sg:address":"Rua Rocon, 1",
    "sg:city":"Cambre",
    "sg:orig_category":"Fisioterapia",
    "sg:phone":"+34 981 65 62 56",
    "sg:postcode":"15660",
    "sg:province":"La Coru\u00f1a",
    "wof:name":"Paz Vazquez Susana",
    "wof:placetype":"venue"
},
  "geometry": {"coordinates":[-8.3557987213,43.3154907227],"type":"Point"}
}