{
  "type": "Feature",
  "properties": {
    "addr:full":"Calle de Duque De Montemar, 13 Sevilla Sevilla 41003",
    "addr:housenumber":"13",
    "addr:postcode":"41003",
    "addr:street":"Calle De Duque De Montemar",
    "iso:country":"ES",
    "sg:address":"Calle de Duque De Montemar, 13",
    "sg:city":"Sevilla",
    "sg:orig_category":"Centros De Coordinaci\u00d3n",
    "sg:phone":"+34 954 90 08 50",
    "sg:postcode":"41003",
    "sg:province":"Sevilla",
    "wof:name":"Lopez Rodriguez Alejandro",
    "wof:placetype":"venue"
},
  "geometry": {"coordinates":[-5.9879989624,37.4002876282],"type":"Point"}
}