{
  "type": "Feature",
  "properties": {
    "addr:full":"Carrer de Fra Juniper Serra, 46 Masnou Barcelona 08320",
    "addr:housenumber":"46",
    "addr:postcode":"08320",
    "addr:street":"Carrer De Fra Juniper Serra",
    "iso:country":"ES",
    "sg:address":"Carrer de Fra Juniper Serra, 46",
    "sg:city":"Masnou",
    "sg:orig_category":"Centros De Educaci\u00d3n Especial",
    "sg:phone":"+34 935 55 49 50",
    "sg:postcode":"08320",
    "sg:province":"Barcelona",
    "wof:name":"Fundacio Privada Pedagogica Be",
    "wof:placetype":"venue"
},
  "geometry": {"coordinates":[2.319890976,41.4857978821],"type":"Point"}
}