{
  "type": "Feature",
  "properties": {
    "iso:country":"ES",
    "sg:address":"Carr Santa Eugenia, 99",
    "sg:city":"Girona",
    "sg:orig_category":"Asociaciones Y Clubs Deportivos",
    "sg:phone":"+34 972 40 60 51",
    "sg:postcode":"17006",
    "sg:province":"Girona",
    "wof:name":"Gimnas Profesional Fitness S.l",
    "wof:placetype":"venue"
},
  "geometry": {"coordinates":[2.8079600334,41.9778404236],"type":"Point"}
}