{
  "type": "Feature",
  "properties": {
    "addr:full":"Calle de Luis Diaz, 1 Cordoba C\u00f3rdoba 14002",
    "addr:housenumber":"1",
    "addr:postcode":"14002",
    "addr:street":"Calle De Luis Diaz;Co\u0301Rdoba",
    "iso:country":"ES",
    "sg:address":"Calle de Luis Diaz, 1",
    "sg:city":"Cordoba",
    "sg:orig_category":"Plomeros",
    "sg:phone":"+34 957 43 47 08",
    "sg:postcode":"14002",
    "sg:province":"C\u00f3rdoba",
    "wof:name":"Agrelu Servicio De Fontaneria S.l",
    "wof:placetype":"venue"
},
  "geometry": {"coordinates":[-4.7677555084,37.8814544678],"type":"Point"}
}