{
  "type": "Feature",
  "properties": {
    "addr:full":"Calle de Virgen De Los Milagros, 82 Puerto De Santa Maria C\u00e1diz 11500",
    "addr:housenumber":"82",
    "addr:postcode":"11500",
    "addr:street":"Calle De Virgen De Los Milagros;Ca\u0301Diz",
    "iso:country":"ES",
    "sg:address":"Calle de Virgen De Los Milagros, 82",
    "sg:city":"Puerto De Santa Maria",
    "sg:orig_category":"Servicios Gsm",
    "sg:phone":"+34 956 87 68 25",
    "sg:postcode":"11500",
    "sg:province":"C\u00e1diz",
    "wof:name":"Integral Phone S.l.",
    "wof:placetype":"venue"
},
  "geometry": {"coordinates":[-6.2251048088,36.5996932983],"type":"Point"}
}