{
  "type": "Feature",
  "properties": {
    "iso:country":"ES",
    "sg:address":"Carrer de Francesc Macia, 31",
    "sg:city":"Cunit",
    "sg:orig_category":"Centros Comerciales Y Grandes Tiendas",
    "sg:phone":"+34 977 67 40 87",
    "sg:postcode":"43881",
    "sg:province":"Tarragona",
    "wof:name":"Vacas Garcia Fernando",
    "wof:placetype":"venue"
},
  "geometry": {"coordinates":[1.635043025,41.1972465515],"type":"Point"}
}