{
  "type": "Feature",
  "properties": {
    "addr:full":"Rua Monte Da Vila, S/n Grove Pontevedra 36980",
    "addr:housenumber":"s / n",
    "addr:postcode":"36980",
    "addr:street":"Rua Monte Da Vila;Grove Pontevedra",
    "iso:country":"ES",
    "sg:address":"Rua Monte Da Vila, S/n",
    "sg:city":"Grove",
    "sg:orig_category":"Sanatorios M\u00c9dico",
    "sg:phone":"+34 986 73 04 79",
    "sg:postcode":"36980",
    "sg:province":"Pontevedra",
    "wof:name":"Sergas-gerencia Atencion Primaria Pontevedra-area Norte",
    "wof:placetype":"venue"
},
  "geometry": {"coordinates":[-8.8605632782,42.4887084961],"type":"Point"}
}