{
  "type": "Feature",
  "properties": {
    "addr:full":"Calle de Fernando El Santo, 25 Madrid Madrid 28010",
    "addr:housenumber":"25",
    "addr:postcode":"madrid;28010",
    "addr:street":"Calle De Fernando El Santo",
    "iso:country":"ES",
    "sg:address":"Calle de Fernando El Santo, 25",
    "sg:city":"Madrid",
    "sg:orig_category":"Molduras, Junquillos, Listones Y Molduras Perforadas",
    "sg:phone":"+34 913 08 49 08",
    "sg:postcode":"28010",
    "sg:province":"Madrid",
    "wof:name":"Megia Cantera Maria De La Paloma",
    "wof:placetype":"venue"
},
  "geometry": {"coordinates":[-3.6908745766,40.4280776978],"type":"Point"}
}