{
  "type": "Feature",
  "properties": {
    "addr:full":"Pque Cial San Jeronimo, 19 Sevilla Sevilla 41015",
    "addr:housenumber":"19",
    "addr:postcode":"41015",
    "addr:street":"San Jeronimo",
    "iso:country":"ES",
    "sg:address":"Pque Cial San Jeronimo, 19",
    "sg:city":"Sevilla",
    "sg:orig_category":"Electrodom\u00c9sticos (al Por Menor)",
    "sg:phone":"+34 954 91 62 92",
    "sg:postcode":"41015",
    "sg:province":"Sevilla",
    "wof:name":"Tecnipuente Del Sur S.l.",
    "wof:placetype":"venue"
},
  "geometry": {"coordinates":[-6.0018129349,37.3876953125],"type":"Point"}
}