{
  "type": "Feature",
  "properties": {
    "addr:full":"Cami Triguero, 1 Muro Alcoy Alicante 03830",
    "addr:housenumber":"1",
    "addr:postcode":"03830",
    "addr:street":"Triguero",
    "iso:country":"ES",
    "sg:address":"Cami Triguero, 1",
    "sg:city":"Muro Alcoy",
    "sg:orig_category":"M\u00c9dicos: Cirug\u00cda Urol\u00d3gica",
    "sg:phone":"+34 965 53 17 56",
    "sg:postcode":"03830",
    "sg:province":"Alicante",
    "wof:name":"Garcia Zamora Jose Antonio",
    "wof:placetype":"venue"
},
  "geometry": {"coordinates":[-0.4466783106,38.7716712952],"type":"Point"}
}