{
  "type": "Feature",
  "properties": {
    "iso:country":"ES",
    "sg:address":"Mestra Senyora Rosario, 2",
    "sg:city":"Pallaresos",
    "sg:orig_category":"Dibujantes (diversos)",
    "sg:phone":"+34 977 61 05 41",
    "sg:postcode":"43151",
    "sg:province":"Tarragona",
    "wof:name":"Alvarez Crespo Jose Manuel",
    "wof:placetype":"venue"
},
  "geometry": {"coordinates":[1.265034914,41.1684265137],"type":"Point"}
}