{
  "type": "Feature",
  "properties": {
    "iso:country":"ES",
    "sg:address":"Calle de Janubio, S/n",
    "sg:city":"Costa De Papagayo",
    "sg:orig_category":"Agencias De Viajes",
    "sg:phone":"+34 928 51 70 93",
    "sg:postcode":"35580",
    "sg:province":"Las Palmas",
    "wof:name":"Travelplan S A",
    "wof:placetype":"venue"
},
  "geometry": {"coordinates":[-15.4300060272,28.1248226166],"type":"Point"}
}