{
  "type": "Feature",
  "properties": {
    "iso:country":"ES",
    "sg:address":"Carrer de Onze De Setembre, 43",
    "sg:city":"Poblenou",
    "sg:orig_category":"Escayola Y Productos De Escayola (fabricaci\u00d3n, Al Por Mayor)",
    "sg:phone":"+34 937 69 03 46",
    "sg:postcode":"08397",
    "sg:province":"Barcelona",
    "wof:name":"Navarro Bou Raquel",
    "wof:placetype":"venue"
},
  "geometry": {"coordinates":[2.670386076,41.6173400879],"type":"Point"}
}