{
  "type": "Feature",
  "properties": {
    "addr:full":"Calle de Rio Guatizalema, 7 Zaragoza Zaragoza 50003",
    "addr:housenumber":"7",
    "addr:postcode":"50003",
    "addr:street":"Calle De Rio Guatizalema",
    "iso:country":"ES",
    "sg:address":"Calle de Rio Guatizalema, 7",
    "sg:city":"Zaragoza",
    "sg:orig_category":"Reparaciones Y Remolcado De Veh\u00cdculos",
    "sg:phone":"+34 976 43 23 39",
    "sg:postcode":"50003",
    "sg:province":"Zaragoza",
    "wof:name":"Perez Barcelon Gloria",
    "wof:placetype":"venue"
},
  "geometry": {"coordinates":[-0.8950070143,41.6615409851],"type":"Point"}
}