{
  "type": "Feature",
  "properties": {
    "iso:country":"ES",
    "sg:address":"Avda Navarro Reverter, S/n",
    "sg:city":"Segorbe",
    "sg:orig_category":"Fabricaci\u00d3n De Harinas, S\u00c9molas, Productos De Elaboraci\u00d3n Del Grano",
    "sg:phone":"+34 964 71 06 36",
    "sg:postcode":"12400",
    "sg:province":"Castell\u00f3n",
    "wof:name":"La Harinera Segorbina S. L.",
    "wof:placetype":"venue"
},
  "geometry": {"coordinates":[-0.4833039939,39.8464851379],"type":"Point"}
}