{
  "type": "Feature",
  "properties": {
    "iso:country":"ES",
    "sg:address":"Ctra. B-granada, S/n",
    "sg:city":"Sta Marta",
    "sg:orig_category":"Contenedores (mercanc\u00cdas)",
    "sg:phone":"+34 924 69 08 03",
    "sg:postcode":"06150",
    "sg:province":"Badajoz",
    "sg:website":"www.traslimus.es",
    "wof:name":"Translimus S.a.",
    "wof:placetype":"venue"
},
  "geometry": {"coordinates":[-6.6212978363,38.6202507019],"type":"Point"}
}