{
  "type": "Feature",
  "properties": {
    "iso:country":"ES",
    "sg:address":"Calle de Concepcion Arenal, 8",
    "sg:city":"Madrid",
    "sg:orig_category":"M\u00c9dicos: Ginecolog\u00cda M\u00c9dica, Obstetricia",
    "sg:phone":"+34 915 23 00 30",
    "sg:postcode":"28004",
    "sg:province":"Madrid",
    "wof:name":"Clinica Ginecologica Callao S.l.",
    "wof:placetype":"venue"
},
  "geometry": {"coordinates":[-3.7047841549,40.4207000732],"type":"Point"}
}