{
  "type": "Feature",
  "properties": {
    "addr:full":"Calle de Reyes Catolicos, 16 Almeria Almer\u00eda 04001",
    "addr:housenumber":"16",
    "addr:postcode":"04001",
    "addr:street":"Calle De Reyes Catolicos",
    "iso:country":"ES",
    "sg:address":"Calle de Reyes Catolicos, 16",
    "sg:city":"Almeria",
    "sg:orig_category":"Arquitectos",
    "sg:phone":"+34 950 24 08 18",
    "sg:postcode":"04001",
    "sg:province":"Almer\u00eda",
    "wof:name":"Ordaz Rebollar Jose Antonio",
    "wof:placetype":"venue"
},
  "geometry": {"coordinates":[-2.4625029564,36.839050293],"type":"Point"}
}