{
  "type": "Feature",
  "properties": {
    "addr:full":"Carrer de Sant Antoni Maria Claret, 193 Barcelona Barcelona 08041",
    "addr:housenumber":"193",
    "addr:postcode":"08041",
    "addr:street":"Carrer De Sant Antoni Maria Claret",
    "iso:country":"ES",
    "sg:address":"Carrer de Sant Antoni Maria Claret, 193",
    "sg:city":"Barcelona",
    "sg:orig_category":"Administradores De Bienes Y Delegados De Comunidades De Propietarios",
    "sg:phone":"+34 934 33 46 78",
    "sg:postcode":"08041",
    "sg:province":"Barcelona",
    "wof:name":"Mu\u00d1oz Mu\u00d1oz Saturnino",
    "wof:placetype":"venue"
},
  "geometry": {"coordinates":[2.1786310673,41.4144744873],"type":"Point"}
}