{
  "type": "Feature",
  "properties": {
    "addr:full":"Avda Astudillo (de), Km. 5710,0 Puerto Lumbreras Murcia 30890",
    "addr:postcode":"30890",
    "addr:street":"Avda Astudillo De Km. 5710,0",
    "iso:country":"ES",
    "sg:address":"Avda Astudillo (de), Km. 5710,0",
    "sg:city":"Puerto Lumbreras",
    "sg:orig_category":"Veh\u00cdculos De Ocasi\u00d3n",
    "sg:phone":"+34 968 40 14 10",
    "sg:postcode":"30890",
    "sg:province":"Murcia",
    "wof:name":"Munera Soto Jose Antonio",
    "wof:placetype":"venue"
},
  "geometry": {"coordinates":[-1.9274189472,37.6259460449],"type":"Point"}
}