{
  "type": "Feature",
  "properties": {
    "iso:country":"ES",
    "sg:address":"Carr Reina De La, 21",
    "sg:city":"Xativa",
    "sg:orig_category":"Asesor\u00cda Fiscal Y Jur\u00cddica",
    "sg:phone":"+34 962 28 31 30",
    "sg:postcode":"46800",
    "sg:province":"Valencia",
    "wof:name":"Fuset Alos Salvador",
    "wof:placetype":"venue"
},
  "geometry": {"coordinates":[-0.5200830102,38.9934272766],"type":"Point"}
}