{
  "type": "Feature",
  "properties": {
    "iso:country":"ES",
    "sg:address":"Avda Miguel De Cervantes, 14",
    "sg:city":"Tarancon",
    "sg:orig_category":"Centros De Coordinaci\u00d3n",
    "sg:phone":"+34 969 32 26 60",
    "sg:postcode":"16400",
    "sg:province":"Cuenca",
    "wof:name":"Romeo Pinillos Maria Del Carmen",
    "wof:placetype":"venue"
},
  "geometry": {"coordinates":[-3.0079209805,40.0102806091],"type":"Point"}
}