{
  "type": "Feature",
  "properties": {
    "iso:country":"ES",
    "sg:address":"Calle de Lagasca, 85",
    "sg:city":"Madrid",
    "sg:orig_category":"Promotores Constructores",
    "sg:phone":"+34 917 81 12 19",
    "sg:postcode":"28006",
    "sg:province":"Madrid",
    "wof:name":"Promarnof S.l. Sociedad Unipersonal",
    "wof:placetype":"venue"
},
  "geometry": {"coordinates":[-3.684885025,40.4313926697],"type":"Point"}
}