{
  "type": "Feature",
  "properties": {
    "addr:full":"Carretera De Baza, 123 Pozo Alcon Ja\u00e9n 23485",
    "addr:housenumber":"123",
    "addr:postcode":"23485",
    "addr:street":"Carretera De Baza;Alcon Jae\u0301N",
    "iso:country":"ES",
    "sg:address":"Carretera De Baza, 123",
    "sg:city":"Pozo Alcon",
    "sg:orig_category":"Empresas De Carpinter\u00cda De Madera",
    "sg:phone":"+34 953 73 88 15",
    "sg:postcode":"23485",
    "sg:province":"Ja\u00e9n",
    "wof:name":"Moreno Ortiz Antonio",
    "wof:placetype":"venue"
},
  "geometry": {"coordinates":[-2.8763370514,37.7938575745],"type":"Point"}
}