{
  "type": "Feature",
  "properties": {
    "addr:full":"Carrer de Sant Josep (de), 16 Vilassar De Mar Barcelona 08340",
    "addr:housenumber":"16",
    "addr:postcode":"08340",
    "addr:street":"Carrer De Sant Josep De",
    "iso:country":"ES",
    "sg:address":"Carrer de Sant Josep (de), 16",
    "sg:city":"Vilassar De Mar",
    "sg:orig_category":"Material Y Suministros Para Horticultura, Arboricultura",
    "sg:phone":"+34 937 59 56 08",
    "sg:postcode":"08340",
    "sg:province":"Barcelona",
    "wof:name":"Aldrufeu Vidal Josep Joaquim",
    "wof:placetype":"venue"
},
  "geometry": {"coordinates":[2.3923215866,41.5038566589],"type":"Point"}
}