{
  "type": "Feature",
  "properties": {
    "iso:country":"ES",
    "sg:address":"Carrer de Corsega, 650",
    "sg:city":"Barcelona",
    "sg:orig_category":"Colchones (fabricaci\u00d3n, Al Por Mayor, Al Por Menor)",
    "sg:phone":"+34 934 36 80 35",
    "sg:postcode":"08026",
    "sg:province":"Barcelona",
    "wof:name":"Deskansus S.c.p.",
    "wof:placetype":"venue"
},
  "geometry": {"coordinates":[2.1787340641,41.4109153748],"type":"Point"}
}