{
  "type": "Feature",
  "properties": {
    "addr:full":"Carrer de Guitard, 74 Barcelona Barcelona 08014",
    "addr:housenumber":"74",
    "addr:postcode":"08014",
    "addr:street":"Carrer De Guitard",
    "iso:country":"ES",
    "sg:address":"Carrer de Guitard, 74",
    "sg:city":"Barcelona",
    "sg:orig_category":"Fiesta: Art\u00cdculos De (al Por Menor)",
    "sg:phone":"+34 934 19 36 34",
    "sg:postcode":"08014",
    "sg:province":"Barcelona",
    "wof:name":"Skarel S.l.",
    "wof:placetype":"venue"
},
  "geometry": {"coordinates":[2.1366639137,41.3840484619],"type":"Point"}
}