{
  "type": "Feature",
  "properties": {
    "addr:full":"Plaz Abajo De, 9 Pola De Allande Asturias 33880",
    "addr:postcode":"33880",
    "iso:country":"ES",
    "sg:address":"Plaz Abajo De, 9",
    "sg:city":"Pola De Allande",
    "sg:classifiers":[
        {
            "category":"Taxi",
            "type":"Transportation"
        }
    ],
    "sg:phone":"+34 985 80 73 82",
    "sg:postcode":"33880",
    "sg:province":"Asturias",
    "wof:name":"Rodriguez Menendez Manuel",
    "wof:placetype":"venue"
},
  "geometry": {"coordinates":[-6.6110310555,43.2716369629],"type":"Point"}
}