{
  "type": "Feature",
  "properties": {
    "iso:country":"ES",
    "sg:address":"Avda Monte Segovia (del), S/n",
    "sg:city":"Boadilla Del Monte",
    "sg:orig_category":"Inmobiliaria (agencias)",
    "sg:phone":"+34 916 33 32 51",
    "sg:postcode":"28660",
    "sg:province":"Madrid",
    "sg:website":"www.grupocambrija.com",
    "wof:name":"Argance S.a.",
    "wof:placetype":"venue"
},
  "geometry": {"coordinates":[-3.8972153664,40.4130401611],"type":"Point"}
}