{
  "type": "Feature",
  "properties": {
    "iso:country":"ES",
    "sg:address":"Calle de Carmen, 8",
    "sg:city":"Madrid",
    "sg:orig_category":"Ciencias Ocultas",
    "sg:phone":"+34 915 22 98 70",
    "sg:postcode":"28013",
    "sg:province":"Madrid",
    "sg:website":"www.albertogarcia.net",
    "wof:name":"Garcia  Edgardo Alberto",
    "wof:placetype":"venue"
},
  "geometry": {"coordinates":[-3.7039299011,40.4179000854],"type":"Point"}
}