{
  "type": "Feature",
  "properties": {
    "iso:country":"ES",
    "sg:address":"Via Augusta, 17",
    "sg:city":"Barcelona",
    "sg:orig_category":"Puertas Y Portales",
    "sg:phone":"+34 932 18 28 94",
    "sg:postcode":"08006",
    "sg:province":"Barcelona",
    "sg:website":"www.manusa.com",
    "wof:name":"Manuporta S.l.",
    "wof:placetype":"venue"
},
  "geometry": {"coordinates":[2.1545259953,41.3968658447],"type":"Point"}
}