{
  "type": "Feature",
  "properties": {
    "addr:full":"Plza. Cultura, S/n Mostoles Madrid 28934",
    "addr:housenumber":"s",
    "addr:postcode":"28934",
    "addr:street":"/ N Mostoles",
    "iso:country":"ES",
    "sg:address":"Plza. Cultura, S/n",
    "sg:city":"Mostoles",
    "sg:orig_category":"Asociaciones, Instituciones De Consumidores Y Usuarios",
    "sg:phone":"+34 916 17 83 67",
    "sg:postcode":"28934",
    "sg:province":"Madrid",
    "wof:name":"Asociacion De Consumidores De Mostoles",
    "wof:placetype":"venue"
},
  "geometry": {"coordinates":[-3.8718934059,40.3195114136],"type":"Point"}
}