{
  "type": "Feature",
  "properties": {
    "iso:country":"ES",
    "sg:address":"Avda Cid, 80",
    "sg:city":"Valencia",
    "sg:orig_category":"Agencias Y Agentes Comerciales, Representantes",
    "sg:phone":"+34 963 79 91 84",
    "sg:postcode":"46018",
    "sg:province":"Valencia",
    "wof:name":"Sayas Ca\u00f1izares Josefa",
    "wof:placetype":"venue"
},
  "geometry": {"coordinates":[-0.4023280144,39.4694480896],"type":"Point"}
}