{
  "type": "Feature",
  "properties": {
    "iso:country":"ES",
    "sg:address":"Calle de Sagasta, 28",
    "sg:city":"Moron Frontera",
    "sg:orig_category":"Agentes Generales De Seguros",
    "sg:phone":"+34 955 85 14 88",
    "sg:postcode":"41530",
    "sg:province":"Sevilla",
    "wof:name":"Guardado Coronado Francisco",
    "wof:placetype":"venue"
},
  "geometry": {"coordinates":[-5.4551258087,37.1201896667],"type":"Point"}
}