{
  "type": "Feature",
  "properties": {
    "iso:country":"ES",
    "sg:address":"Carrer de Centre, 37",
    "sg:city":"Garriga",
    "sg:orig_category":"Pescader\u00cdas (al Por Menor)",
    "sg:phone":"+34 938 71 60 01",
    "sg:postcode":"08530",
    "sg:province":"Barcelona",
    "wof:name":"Garcia Ortega Cesar",
    "wof:placetype":"venue"
},
  "geometry": {"coordinates":[2.2853150368,41.6854286194],"type":"Point"}
}