{
  "type": "Feature",
  "properties": {
    "iso:country":"ES",
    "sg:address":"Calle de Alvaro De Bazan, 3",
    "sg:city":"Valencia",
    "sg:orig_category":"Embajadas, Consulados Y Otras Representaciones Diplom\u00c1ticas",
    "sg:phone":"+34 963 93 36 31",
    "sg:postcode":"46010",
    "sg:province":"Valencia",
    "wof:name":"Goerlich Lledo Andres",
    "wof:placetype":"venue"
},
  "geometry": {"coordinates":[-0.3645671904,39.4817123413],"type":"Point"}
}