{
  "type": "Feature",
  "properties": {
    "addr:full":"Pl Jaume Balmes, 9 Gava Barcelona 08850",
    "addr:housenumber":"9",
    "addr:postcode":"08850",
    "addr:street":"Pl Jaume Balmes",
    "iso:country":"ES",
    "sg:address":"Pl Jaume Balmes, 9",
    "sg:city":"Gava",
    "sg:orig_category":"Zapatos (al Por Menor)",
    "sg:phone":"+34 936 38 39 59",
    "sg:postcode":"08850",
    "sg:province":"Barcelona",
    "wof:name":"Valero Martinez Rafael",
    "wof:placetype":"venue"
},
  "geometry": {"coordinates":[2.0001780987,41.3039474487],"type":"Point"}
}