{
  "type": "Feature",
  "properties": {
    "iso:country":"ES",
    "sg:address":"Cmno Valdepega, 19",
    "sg:city":"Cabrerizos",
    "sg:orig_category":"Abogados",
    "sg:phone":"+34 923 28 92 26",
    "sg:postcode":"37193",
    "sg:province":"Salamanca",
    "wof:name":"Vergas Sanchez Carmen",
    "wof:placetype":"venue"
},
  "geometry": {"coordinates":[-5.7458281517,40.7879104614],"type":"Point"}
}