{
  "type": "Feature",
  "properties": {
    "addr:full":"El Peral, 11 Covaleda Soria 42157",
    "addr:housenumber":"11",
    "addr:postcode":"42157",
    "addr:street":"El Peral",
    "iso:country":"ES",
    "sg:address":"El Peral, 11",
    "sg:city":"Covaleda",
    "sg:orig_category":"Pescader\u00cdas (al Por Menor)",
    "sg:phone":"+34 975 37 01 11",
    "sg:postcode":"42157",
    "sg:province":"Soria",
    "wof:name":"Milla Pacheco Eugenio",
    "wof:placetype":"venue"
},
  "geometry": {"coordinates":[-2.8832380772,41.9334182739],"type":"Point"}
}