{
  "type": "Feature",
  "properties": {
    "iso:country":"ES",
    "sg:address":"Calle de Lorenzo Gonzalez Iglesias, 28",
    "sg:city":"Salamanca",
    "sg:orig_category":"Molduras, Junquillos, Listones Y Molduras Perforadas",
    "sg:phone":"+34 923 19 17 10",
    "sg:postcode":"37008",
    "sg:province":"Salamanca",
    "wof:name":"Lorenzo Vicente Miguel",
    "wof:placetype":"venue"
},
  "geometry": {"coordinates":[-5.6824889183,40.9575805664],"type":"Point"}
}