{
  "type": "Feature",
  "properties": {
    "addr:full":"Jose Migel Iturriotz Kalea, 16 Beasain Guip\u00f9zcoa 20200",
    "addr:housenumber":"16",
    "addr:postcode":"20200",
    "addr:street":"Jose Migel Iturriotz Kalea;Guipu\u0300Zcoa",
    "iso:country":"ES",
    "sg:address":"Jose Migel Iturriotz Kalea, 16",
    "sg:city":"Beasain",
    "sg:orig_category":"Peluquer\u00cdas, Peluquer\u00cda Mixta",
    "sg:phone":"+34 943 88 97 33",
    "sg:postcode":"20200",
    "sg:province":"Guip\u00f9zcoa",
    "wof:name":"Peluqueria Agus,agustin Sanchez Crespo",
    "wof:placetype":"venue"
},
  "geometry": {"coordinates":[-2.1932458878,43.0477333069],"type":"Point"}
}