{
  "type": "Feature",
  "properties": {
    "iso:country":"ES",
    "sg:address":"Calle de Molino, 9",
    "sg:city":"Camarena",
    "sg:orig_category":"Material Y Suministros Para Perforaciones, Sondeos",
    "sg:phone":"+34 918 17 42 72",
    "sg:postcode":"45180",
    "sg:province":"Toledo",
    "wof:name":"Exvader S.l.",
    "wof:placetype":"venue"
},
  "geometry": {"coordinates":[-4.1166191101,40.0928153992],"type":"Point"}
}