{
  "type": "Feature",
  "properties": {
    "addr:full":"Calle de Corazon De Maria, 39 Madrid Madrid 28002",
    "addr:housenumber":"39",
    "addr:postcode":"madrid;28002",
    "addr:street":"Calle De Corazon;Maria",
    "iso:country":"ES",
    "sg:address":"Calle de Corazon De Maria, 39",
    "sg:city":"Madrid",
    "sg:orig_category":"Abogados",
    "sg:phone":"+34 915 19 70 21",
    "sg:postcode":"28002",
    "sg:province":"Madrid",
    "wof:name":"Garcia-herranz Armendariz Jose Manuel",
    "wof:placetype":"venue"
},
  "geometry": {"coordinates":[-3.6670999527,40.4451828003],"type":"Point"}
}