{
  "type": "Feature",
  "properties": {
    "addr:full":"Afueras, S/n S. Jordi Salines Islas Baleares 07817",
    "addr:postcode":"07817",
    "addr:street":"Afueras S / N S. Jordi",
    "iso:country":"ES",
    "sg:address":"Afueras, S/n",
    "sg:city":"S. Jordi Salines",
    "sg:orig_category":"Discotecas Y Salas De Baile",
    "sg:phone":"+34 971 30 85 85",
    "sg:postcode":"07817",
    "sg:province":"Islas Baleares",
    "wof:name":"Space Beach Club S.a.",
    "wof:placetype":"venue"
},
  "geometry": {"coordinates":[1.4075000286,38.8912010193],"type":"Point"}
}