{
  "type": "Feature",
  "properties": {
    "addr:full":"Calle de Socuellamos, 19 Ciudad Real Ciudad Real 13005",
    "addr:housenumber":"19",
    "addr:postcode":"13005",
    "addr:street":"Calle De Socuellamos",
    "iso:country":"ES",
    "sg:address":"Calle de Socuellamos, 19",
    "sg:city":"Ciudad Real",
    "sg:orig_category":"Promotores Constructores",
    "sg:phone":"+34 926 21 68 60",
    "sg:postcode":"13005",
    "sg:province":"Ciudad Real",
    "wof:name":"Construcciones Blasierra S.l.",
    "wof:placetype":"venue"
},
  "geometry": {"coordinates":[-3.9297139645,38.9766311646],"type":"Point"}
}