{
  "type": "Feature",
  "properties": {
    "iso:country":"ES",
    "sg:address":"Calle de Coronel Ceballos, 26",
    "sg:city":"Algeciras",
    "sg:orig_category":"M\u00c9dicos: Oftalmolog\u00cda",
    "sg:phone":"+34 956 65 55 81",
    "sg:postcode":"11201",
    "sg:province":"C\u00e1diz",
    "wof:name":"Cabrerizo Morillas Miguel Angel",
    "wof:placetype":"venue"
},
  "geometry": {"coordinates":[-5.4472908974,36.132434845],"type":"Point"}
}