{
  "type": "Feature",
  "properties": {
    "iso:country":"ES",
    "sg:address":"Avda Andalucia (de), 9",
    "sg:city":"Montilla",
    "sg:orig_category":"Sindicatos De Trabajadores",
    "sg:phone":"+34 957 65 04 39",
    "sg:postcode":"14550",
    "sg:province":"C\u00f3rdoba",
    "wof:name":"Comisiones Obreras De Andalucia",
    "wof:placetype":"venue"
},
  "geometry": {"coordinates":[-4.6428852081,37.583820343],"type":"Point"}
}