{
  "type": "Feature",
  "properties": {
    "addr:full":"Calle de Cronista Carreres, 9 Valencia Valencia 46003",
    "addr:housenumber":"9",
    "addr:postcode":"46003",
    "addr:street":"Calle De Cronista Carreres",
    "iso:country":"ES",
    "sg:address":"Calle de Cronista Carreres, 9",
    "sg:city":"Valencia",
    "sg:orig_category":"Agencias Y Asesores De Publicidad",
    "sg:phone":"+34 963 52 10 80",
    "sg:postcode":"46003",
    "sg:province":"Valencia",
    "wof:name":"Stand Up S.l.",
    "wof:placetype":"venue"
},
  "geometry": {"coordinates":[-0.3677935004,39.4729576111],"type":"Point"}
}