{
  "type": "Feature",
  "properties": {
    "iso:country":"ES",
    "sg:address":"Avda Estacion, 87",
    "sg:city":"Torrijos",
    "sg:orig_category":"Electricidad: Instaladores",
    "sg:phone":"+34 925 76 10 93",
    "sg:postcode":"45500",
    "sg:province":"Toledo",
    "wof:name":"Ordo\u00f1ez Rodriguez Enrique",
    "wof:placetype":"venue"
},
  "geometry": {"coordinates":[-4.2822489738,39.9811515808],"type":"Point"}
}