{
  "type": "Feature",
  "properties": {
    "addr:full":"Poli Pol.indust. Cami Dels Frares, 20 Lleida Lleida 25191",
    "addr:housenumber":"20",
    "addr:postcode":"25191",
    "iso:country":"ES",
    "sg:address":"Poli Pol.indust. Cami Dels Frares, 20",
    "sg:city":"Lleida",
    "sg:orig_category":"Barnizadores",
    "sg:phone":"+34 973 25 70 71",
    "sg:postcode":"25191",
    "sg:province":"Lleida",
    "wof:name":"Barnizados Ruiz S.c.p.",
    "wof:placetype":"venue"
},
  "geometry": {"coordinates":[0.6831650138,41.5832138062],"type":"Point"}
}