{
  "type": "Feature",
  "properties": {
    "iso:country":"ES",
    "sg:address":"Plaz Mayor, 2",
    "sg:city":"Estadilla",
    "sg:orig_category":"Transporte En General",
    "sg:phone":"+34 974 30 51 22",
    "sg:postcode":"22423",
    "sg:province":"Huesca",
    "wof:name":"Villega De Antonio Maria",
    "wof:placetype":"venue"
},
  "geometry": {"coordinates":[0.243889004,42.0562324524],"type":"Point"}
}