{
  "type": "Feature",
  "properties": {
    "addr:full":"Carr Sant Antoni, De, 3 Carcaixent Valencia 46740",
    "addr:housenumber":"3",
    "addr:postcode":"46740",
    "addr:street":"Carr Sant Antoni De",
    "iso:country":"ES",
    "sg:address":"Carr Sant Antoni, De, 3",
    "sg:city":"Carcaixent",
    "sg:orig_category":"Oficinas: Suministros Para (fabricaci\u00d3n, Al Por Mayor)",
    "sg:phone":"+34 962 43 10 80",
    "sg:postcode":"46740",
    "sg:province":"Valencia",
    "wof:name":"Papeleria San Antonio S.l.",
    "wof:placetype":"venue"
},
  "geometry": {"coordinates":[-0.4498789907,39.1257591248],"type":"Point"}
}