{
  "type": "Feature",
  "properties": {
    "iso:country":"ES",
    "sg:address":"Rond Sant Ramon, 124",
    "sg:city":"S. Boi Llobregat",
    "sg:orig_category":"Arquitectos",
    "sg:phone":"+34 936 40 60 47",
    "sg:postcode":"08830",
    "sg:province":"Barcelona",
    "wof:name":"Galan Santacana Ignacio",
    "wof:placetype":"venue"
},
  "geometry": {"coordinates":[2.0298376083,41.343624115],"type":"Point"}
}