{
  "type": "Feature",
  "properties": {
    "iso:country":"ES",
    "sg:address":"Estacion, 10",
    "sg:city":"Ujo",
    "sg:orig_category":"Explotaci\u00d3n De Minas",
    "sg:phone":"+34 985 42 21 71",
    "sg:postcode":"33640",
    "sg:province":"Asturias",
    "wof:name":"Hulleras Del Norte S.a.",
    "wof:placetype":"venue"
},
  "geometry": {"coordinates":[-5.7913818359,43.2042694092],"type":"Point"}
}