{
  "type": "Feature",
  "properties": {
    "addr:full":"Pla\u00c7 Passeig, 8 Cadaques Girona 17488",
    "addr:housenumber":"8",
    "addr:postcode":"17488",
    "addr:street":"Passeig",
    "iso:country":"ES",
    "sg:address":"Pla\u00c7 Passeig, 8",
    "sg:city":"Cadaques",
    "sg:orig_category":"Discotecas Y Salas De Baile",
    "sg:phone":"+34 972 25 80 00",
    "sg:postcode":"17488",
    "sg:province":"Girona",
    "wof:name":"Pogany  Maurizio",
    "wof:placetype":"venue"
},
  "geometry": {"coordinates":[3.2777349949,42.2890510559],"type":"Point"}
}