{
  "type": "Feature",
  "properties": {
    "addr:full":"I. Albeniz, 9 Iru\u00f1a Navarra 31005",
    "addr:housenumber":"9",
    "addr:postcode":"31005",
    "addr:street":"I. Albeniz",
    "iso:country":"ES",
    "sg:address":"I. Albeniz, 9",
    "sg:city":"Iru\u00f1a",
    "sg:orig_category":"Chapister\u00cda",
    "sg:phone":"+34 948 24 70 36",
    "sg:postcode":"31005",
    "sg:province":"Navarra",
    "wof:name":"Arilla Belzuz Pedro",
    "wof:placetype":"venue"
},
  "geometry": {"coordinates":[-1.642190218,42.8052787781],"type":"Point"}
}