{
  "type": "Feature",
  "properties": {
    "iso:country":"ES",
    "sg:address":"Carr 9 D'octubre, 2",
    "sg:city":"Oliva",
    "sg:orig_category":"Confecci\u00d3n De Trajes Para Se\u00d1oras",
    "sg:phone":"+34 962 83 88 96",
    "sg:postcode":"46780",
    "sg:province":"Valencia",
    "wof:name":"Anahit Oliva S.l.",
    "wof:placetype":"venue"
},
  "geometry": {"coordinates":[-0.1482906938,38.9608764648],"type":"Point"}
}