{
  "type": "Feature",
  "properties": {
    "addr:full":"Calle de Cardenal Cisneros, 16 Huelva Huelva 21003",
    "addr:housenumber":"16",
    "addr:postcode":"21003",
    "addr:street":"Calle De Cardenal Cisneros",
    "iso:country":"ES",
    "sg:address":"Calle de Cardenal Cisneros, 16",
    "sg:city":"Huelva",
    "sg:orig_category":"Promotores Constructores",
    "sg:phone":"+34 959 25 55 36",
    "sg:postcode":"21003",
    "sg:province":"Huelva",
    "wof:name":"Nuevo Trigueros S.l.",
    "wof:placetype":"venue"
},
  "geometry": {"coordinates":[-6.948884964,37.2569160461],"type":"Point"}
}