{
  "type": "Feature",
  "properties": {
    "iso:country":"ES",
    "sg:address":"Plaz Paz (la), S/n",
    "sg:city":"Alhendin",
    "sg:orig_category":"Asociaciones, Organismos Culturales Y Socioeducativos",
    "sg:phone":"+34 958 57 67 88",
    "sg:postcode":"18620",
    "sg:province":"Granada",
    "wof:name":"Asociacion De Mujeres Amlh",
    "wof:placetype":"venue"
},
  "geometry": {"coordinates":[-3.6461181641,37.1085090637],"type":"Point"}
}