{
  "type": "Feature",
  "properties": {
    "addr:full":"Avda Portugal, 67 Jerez De Los Caballeros Badajoz 06380",
    "addr:housenumber":"67",
    "addr:postcode":"06380",
    "addr:street":"Avda Portugal",
    "iso:country":"ES",
    "sg:address":"Avda Portugal, 67",
    "sg:city":"Jerez De Los Caballeros",
    "sg:orig_category":"Seguridad En El Trabajo Y Prevenci\u00d3n De Riesgos Laborales",
    "sg:phone":"+34 924 75 19 65",
    "sg:postcode":"06380",
    "sg:province":"Badajoz",
    "wof:name":"Preving Consultores S.l.",
    "wof:placetype":"venue"
},
  "geometry": {"coordinates":[-6.7700591087,38.3265914917],"type":"Point"}
}