{
  "type": "Feature",
  "properties": {
    "addr:full":"Urb Acuario, S/n San Francisco Cavero Toledo 45280",
    "addr:housenumber":"s / n",
    "addr:postcode":"45280",
    "addr:street":"Urb Acuario",
    "iso:country":"ES",
    "sg:address":"Urb Acuario, S/n",
    "sg:city":"San Francisco Cavero",
    "sg:orig_category":"Abogados",
    "sg:phone":"+34 925 35 39 91",
    "sg:postcode":"45280",
    "sg:province":"Toledo",
    "wof:name":"Lopez Briones Jose Carlos",
    "wof:placetype":"venue"
},
  "geometry": {"coordinates":[-3.9949450493,39.9150466919],"type":"Point"}
}