{
  "type": "Feature",
  "properties": {
    "iso:country":"ES",
    "sg:address":"Carrer de Altamira, 25",
    "sg:city":"Campello",
    "sg:orig_category":"Fabricaci\u00d3n, Importaci\u00d3n De L\u00c1mparas Y Bombillas",
    "sg:phone":"+34 965 63 68 32",
    "sg:postcode":"03560",
    "sg:province":"Alicante",
    "wof:name":"Luzlamp Factory S.l.u",
    "wof:placetype":"venue"
},
  "geometry": {"coordinates":[-0.402839005,38.4275894165],"type":"Point"}
}