{
  "type": "Feature",
  "properties": {
    "iso:country":"ES",
    "sg:address":"Calle de Extremadura, 4",
    "sg:city":"Orihuela",
    "sg:classifiers":[
        {
            "category":"Autos & Motor Vehicles",
            "subcategory":"Automobile Sales",
            "type":"Retail Goods"
        }
    ],
    "sg:phone":"+34 965 30 41 04",
    "sg:postcode":"03300",
    "sg:province":"Alicante",
    "wof:name":"Navarro Fernandez Francisco",
    "wof:placetype":"venue"
},
  "geometry": {"coordinates":[-0.9467840195,38.0811004639],"type":"Point"}
}