{
  "type": "Feature",
  "properties": {
    "iso:country":"ES",
    "sg:address":"Avda Centro Excursionista Eldense, 9",
    "sg:city":"Elda",
    "sg:orig_category":"Artes Gr\u00c1ficas, Artes Pl\u00c1sticas (curso)",
    "sg:phone":"+34 965 39 45 49",
    "sg:postcode":"03600",
    "sg:province":"Alicante",
    "wof:name":"Troquelados Rueda S.l.",
    "wof:placetype":"venue"
},
  "geometry": {"coordinates":[-0.8067989945,38.470161438],"type":"Point"}
}