{
  "type": "Feature",
  "properties": {
    "iso:country":"ES",
    "sg:address":"Calle de Gallo (el), 4",
    "sg:city":"Utrera",
    "sg:orig_category":"Arquitectos",
    "sg:phone":"+34 954 86 10 24",
    "sg:postcode":"41710",
    "sg:province":"Sevilla",
    "wof:name":"Andreu Requena Emilio",
    "wof:placetype":"venue"
},
  "geometry": {"coordinates":[-5.7799224854,37.1859321594],"type":"Point"}
}