{
  "type": "Feature",
  "properties": {
    "addr:full":"Calle de Comarca De La Serena, 2 Caceres C\u00e1ceres 10195",
    "addr:housenumber":"2",
    "addr:postcode":"10195",
    "addr:street":"Calle De Comarca De La;Caceres Ca\u0301Ceres",
    "iso:country":"ES",
    "sg:address":"Calle de Comarca De La Serena, 2",
    "sg:city":"Caceres",
    "sg:orig_category":"Alimentaci\u00d3n General (al Por Menor)",
    "sg:phone":"+34 927 23 32 95",
    "sg:postcode":"10195",
    "sg:province":"C\u00e1ceres",
    "wof:name":"Galan Diaz Juana",
    "wof:placetype":"venue"
},
  "geometry": {"coordinates":[-6.3860325813,39.4458656311],"type":"Point"}
}