{
  "type": "Feature",
  "properties": {
    "iso:country":"ES",
    "sg:address":"Calle de Juan Xxiii, 10",
    "sg:city":"Aviles",
    "sg:orig_category":"Agencias Y Agentes Comerciales, Representantes",
    "sg:phone":"+34 985 56 32 86",
    "sg:postcode":"33401",
    "sg:province":"Asturias",
    "wof:name":"Machado Garcia Rufino Manuel",
    "wof:placetype":"venue"
},
  "geometry": {"coordinates":[-5.9288430214,43.5560379028],"type":"Point"}
}