{
  "type": "Feature",
  "properties": {
    "addr:full":"Carrer de Armanya, 5 Tarragona Tarragona 43004",
    "addr:housenumber":"5",
    "addr:postcode":"43004",
    "addr:street":"Carrer De Armanya",
    "iso:country":"ES",
    "sg:address":"Carrer de Armanya, 5",
    "sg:city":"Tarragona",
    "sg:orig_category":"Molduras, Junquillos, Listones Y Molduras Perforadas",
    "sg:phone":"+34 977 24 46 37",
    "sg:postcode":"43004",
    "sg:province":"Tarragona",
    "wof:name":"Maldonado Gil Carlos Arturo",
    "wof:placetype":"venue"
},
  "geometry": {"coordinates":[1.2525810003,41.1147232056],"type":"Point"}
}