{
  "type": "Feature",
  "properties": {
    "iso:country":"ES",
    "sg:address":"Rond President Irla, 33",
    "sg:city":"Mataro",
    "sg:orig_category":"Abogados",
    "sg:phone":"+34 937 98 44 63",
    "sg:postcode":"08302",
    "sg:province":"Barcelona",
    "wof:name":"New Narvik S.l",
    "wof:placetype":"venue"
},
  "geometry": {"coordinates":[2.4400560856,41.5315704346],"type":"Point"}
}