{
  "type": "Feature",
  "properties": {
    "addr:full":"Av Matadepera, 135 Sabadell Barcelona 08207",
    "addr:housenumber":"135",
    "addr:postcode":"08207",
    "addr:street":"Av Matadepera",
    "iso:country":"ES",
    "sg:address":"Av Matadepera, 135",
    "sg:city":"Sabadell",
    "sg:orig_category":"Escayola Y Productos De Escayola (fabricaci\u00d3n, Al Por Mayor)",
    "sg:phone":"+34 937 23 87 46",
    "sg:postcode":"08207",
    "sg:province":"Barcelona",
    "wof:name":"Larrosa Perez Dolores",
    "wof:placetype":"venue"
},
  "geometry": {"coordinates":[2.0885910988,41.5670585632],"type":"Point"}
}