{
  "type": "Feature",
  "properties": {
    "addr:full":"Avda Angeles (los), 9 Loja Granada 18300",
    "addr:housenumber":"9",
    "addr:postcode":"18300",
    "addr:street":"Avda Angeles Los",
    "iso:country":"ES",
    "sg:address":"Avda Angeles (los), 9",
    "sg:city":"Loja",
    "sg:orig_category":"Pod\u00d3logos: Pedicuros",
    "sg:phone":"+34 958 32 54 29",
    "sg:postcode":"18300",
    "sg:province":"Granada",
    "wof:name":"Moreno Jimenez Juan Antonio",
    "wof:placetype":"venue"
},
  "geometry": {"coordinates":[-4.147397995,37.1658363342],"type":"Point"}
}