{
  "type": "Feature",
  "properties": {
    "addr:full":"Calle de Tres De Noviembre, 36 Santander Cantabria 39010",
    "addr:housenumber":"36",
    "addr:postcode":"39010",
    "addr:street":"Calle De Tres De Noviembre",
    "iso:country":"ES",
    "sg:address":"Calle de Tres De Noviembre, 36",
    "sg:city":"Santander",
    "sg:orig_category":"Pintores",
    "sg:phone":"+34 942 23 98 03",
    "sg:postcode":"39010",
    "sg:province":"Cantabria",
    "wof:name":"Martin Martin Rosario",
    "wof:placetype":"venue"
},
  "geometry": {"coordinates":[-3.8199813366,43.4595146179],"type":"Point"}
}