{
  "type": "Feature",
  "properties": {
    "addr:full":"Carr Maestro Lope, 74 Burjassot Valencia 46100",
    "addr:housenumber":"74",
    "addr:postcode":"46100",
    "addr:street":"Carr Maestro Lope",
    "iso:country":"ES",
    "sg:address":"Carr Maestro Lope, 74",
    "sg:city":"Burjassot",
    "sg:orig_category":"Empresas De Escayolas",
    "sg:phone":"+34 963 63 71 47",
    "sg:postcode":"46100",
    "sg:province":"Valencia",
    "wof:name":"Bailach Lleonart Vicente",
    "wof:placetype":"venue"
},
  "geometry": {"coordinates":[-0.4074440002,39.5074996948],"type":"Point"}
}