{
  "type": "Feature",
  "properties": {
    "iso:country":"ES",
    "sg:address":"Carrer de Doctor Pi I Molist, 17",
    "sg:city":"Barcelona",
    "sg:orig_category":"Zapatos (al Por Menor)",
    "sg:phone":"+34 934 08 63 93",
    "sg:postcode":"08031",
    "sg:province":"Barcelona",
    "wof:name":"Cobaro S.a.",
    "wof:placetype":"venue"
},
  "geometry": {"coordinates":[2.1741409302,41.431312561],"type":"Point"}
}