{
  "type": "Feature",
  "properties": {
    "addr:full":"Carr Valencia, 13 Camprodon Girona 17867",
    "addr:housenumber":"13",
    "addr:postcode":"17867",
    "addr:street":"Carr Valencia",
    "iso:country":"ES",
    "sg:address":"Carr Valencia, 13",
    "sg:city":"Camprodon",
    "sg:orig_category":"Confiter\u00cda, Galletas Y Pastas, Chocolater\u00cda (al Por Mayor)",
    "sg:phone":"+34 972 74 01 14",
    "sg:postcode":"17867",
    "sg:province":"Girona",
    "wof:name":"Sala Pujol Javier",
    "wof:placetype":"venue"
},
  "geometry": {"coordinates":[2.3658130169,42.3134918213],"type":"Point"}
}