{
  "type": "Feature",
  "properties": {
    "addr:full":"Calle de Brasil, 1 Alcala Henares Madrid 28806",
    "addr:housenumber":"1",
    "addr:postcode":"28806",
    "addr:street":"Calle De Brasil",
    "iso:country":"ES",
    "sg:address":"Calle de Brasil, 1",
    "sg:city":"Alcala Henares",
    "sg:orig_category":"Empresas De Desmonte",
    "sg:phone":"+34 918 81 33 03",
    "sg:postcode":"28806",
    "sg:province":"Madrid",
    "wof:name":"Retropalas Alcala S. L.",
    "wof:placetype":"venue"
},
  "geometry": {"coordinates":[-3.4004395008,40.508354187],"type":"Point"}
}