{
  "type": "Feature",
  "properties": {
    "addr:full":"Carrer de Angel Ara\u00d1o, 55 Viladecans Barcelona 08840",
    "addr:housenumber":"55",
    "addr:postcode":"08840",
    "addr:street":"Carrer De Angel Aran\u0303O",
    "iso:country":"ES",
    "sg:address":"Carrer de Angel Ara\u00d1o, 55",
    "sg:city":"Viladecans",
    "sg:orig_category":"Inmobiliaria (agencias)",
    "sg:phone":"+34 936 58 24 86",
    "sg:postcode":"08840",
    "sg:province":"Barcelona",
    "wof:name":"Soto Durante Teresa",
    "wof:placetype":"venue"
},
  "geometry": {"coordinates":[2.0134840012,41.3183555603],"type":"Point"}
}