{
  "type": "Feature",
  "properties": {
    "iso:country":"ES",
    "sg:address":"Calle de Juana Jugan, 3",
    "sg:city":"Vitoria-gasteiz",
    "sg:orig_category":"Zapatos (al Por Menor)",
    "sg:phone":"+34 945 27 11 45",
    "sg:postcode":"01009",
    "sg:province":"\u00c1lava",
    "wof:name":"Calzado Marisa",
    "wof:placetype":"venue"
},
  "geometry": {"coordinates":[-2.6849970818,42.8564796448],"type":"Point"}
}