{
  "type": "Feature",
  "properties": {
    "addr:full":"Av. Rafael Cavestany, S/n Castromonte Valladolid 47641",
    "addr:housenumber":"s / n",
    "addr:postcode":"47641",
    "addr:street":"Av. Rafael Cavestany",
    "iso:country":"ES",
    "sg:address":"Av. Rafael Cavestany, S/n",
    "sg:city":"Castromonte",
    "sg:orig_category":"Centros De Educaci\u00d3n Especial",
    "sg:phone":"+34 983 56 66 30",
    "sg:postcode":"47641",
    "sg:province":"Valladolid",
    "wof:name":"Colegio Publico Rural Agrupado De Medina De Rioseco",
    "wof:placetype":"venue"
},
  "geometry": {"coordinates":[-5.0401439667,41.7733802795],"type":"Point"}
}