{
  "type": "Feature",
  "properties": {
    "iso:country":"ES",
    "sg:address":"Av Catalunya, 37",
    "sg:city":"Cerdanyola Valles",
    "sg:orig_category":"Cajas De Ahorro",
    "sg:phone":"+34 935 80 78 87",
    "sg:postcode":"08290",
    "sg:province":"Barcelona",
    "wof:name":"Caixa D'estalvis Del Penedes",
    "wof:placetype":"venue"
},
  "geometry": {"coordinates":[2.1447930336,41.4928512573],"type":"Point"}
}