{
  "type": "Feature",
  "properties": {
    "addr:full":"Calle de Rafael Terol, 1 Alacant Alicante 03001",
    "addr:housenumber":"1",
    "addr:postcode":"03001",
    "addr:street":"Calle De Rafael Terol",
    "iso:country":"ES",
    "sg:address":"Calle de Rafael Terol, 1",
    "sg:city":"Alacant",
    "sg:orig_category":"Agentes Generales De Seguros",
    "sg:phone":"+34 965 14 05 66",
    "sg:postcode":"03001",
    "sg:province":"Alicante",
    "wof:name":"Agencia Seguros Sucesores Daniel Berenguer S.l.",
    "wof:placetype":"venue"
},
  "geometry": {"coordinates":[-0.4855982959,38.34349823],"type":"Point"}
}