{
  "type": "Feature",
  "properties": {
    "addr:full":"Calle de Amparo, 101 Madrid Madrid 28012",
    "addr:housenumber":"101",
    "addr:postcode":"28012",
    "addr:street":"Calle De Amparo",
    "iso:country":"ES",
    "sg:address":"Calle de Amparo, 101",
    "sg:city":"Madrid",
    "sg:orig_category":"Perfumer\u00cda (al Por Menor)",
    "sg:phone":"+34 914 68 35 05",
    "sg:postcode":"28012",
    "sg:province":"Madrid",
    "wof:name":"Rubin Rodriguez Jose",
    "wof:placetype":"venue"
},
  "geometry": {"coordinates":[-3.7002456188,40.4060745239],"type":"Point"}
}