{
  "type": "Feature",
  "properties": {
    "addr:full":"Pase General Davila, 22 Santander Cantabria 39005",
    "addr:housenumber":"22",
    "addr:postcode":"39005",
    "addr:street":"Davila",
    "iso:country":"ES",
    "sg:address":"Pase General Davila, 22",
    "sg:city":"Santander",
    "sg:orig_category":"Ense\u00d1anza Variada",
    "sg:phone":"+34 942 27 03 15",
    "sg:postcode":"39005",
    "sg:province":"Cantabria",
    "wof:name":"Adoz Siglo Xxi S.l.",
    "wof:placetype":"venue"
},
  "geometry": {"coordinates":[-3.7916402817,43.4685516357],"type":"Point"}
}