{
  "type": "Feature",
  "properties": {
    "addr:full":"Calle de Campo Real, 4 Madrid Madrid 28039",
    "addr:housenumber":"4",
    "addr:postcode":"28039",
    "addr:street":"Calle De Campo",
    "iso:country":"ES",
    "sg:address":"Calle de Campo Real, 4",
    "sg:city":"Madrid",
    "sg:orig_category":"Electricidad: Instaladores",
    "sg:phone":"+34 914 59 68 94",
    "sg:postcode":"28039",
    "sg:province":"Madrid",
    "wof:name":"Benito Sanz Ambrosio",
    "wof:placetype":"venue"
},
  "geometry": {"coordinates":[-3.7092130184,40.4587020874],"type":"Point"}
}