{
  "type": "Feature",
  "properties": {
    "iso:country":"ES",
    "sg:address":"Calle de Nicolas Navas, S/n",
    "sg:city":"Roquetas Mar",
    "sg:orig_category":"Laboratorios Y Trabajos De Fotograf\u00cda, V\u00cddeo Y Cine",
    "sg:phone":"+34 950 32 05 32",
    "sg:postcode":"04740",
    "sg:province":"Almer\u00eda",
    "wof:name":"Garcia Bonachera Francisco",
    "wof:placetype":"venue"
},
  "geometry": {"coordinates":[-2.6143600941,36.7647590637],"type":"Point"}
}