{
  "type": "Feature",
  "properties": {
    "iso:country":"ES",
    "sg:address":"Calle de Ribera, La, 7",
    "sg:city":"Torrent",
    "sg:orig_category":"Molduras, Junquillos, Listones Y Molduras Perforadas",
    "sg:phone":"+34 961 55 22 39",
    "sg:postcode":"46900",
    "sg:province":"Valencia",
    "wof:name":"Esteban Ordu\u00f1a Juan",
    "wof:placetype":"venue"
},
  "geometry": {"coordinates":[-0.4741829932,39.4335289001],"type":"Point"}
}