{
  "type": "Feature",
  "properties": {
    "iso:country":"ES",
    "sg:address":"Eras, 10",
    "sg:city":"Tamames",
    "sg:orig_category":"Cerrajer\u00cda, Ferrallista",
    "sg:phone":"+34 923 44 93 72",
    "sg:postcode":"37600",
    "sg:province":"Salamanca",
    "wof:name":"Martin Fonseca Eulogio",
    "wof:placetype":"venue"
},
  "geometry": {"coordinates":[-6.1087841988,40.656791687],"type":"Point"}
}