{
  "type": "Feature",
  "properties": {
    "addr:full":"Calle de Garci Perez, 8 Sevilla Sevilla 41003",
    "addr:housenumber":"8",
    "addr:postcode":"41003",
    "addr:street":"Calle De Garci Perez",
    "iso:country":"ES",
    "sg:address":"Calle de Garci Perez, 8",
    "sg:city":"Sevilla",
    "sg:orig_category":"Inmobiliaria (agencias)",
    "sg:phone":"+34 954 41 25 84",
    "sg:postcode":"41003",
    "sg:province":"Sevilla",
    "wof:name":"Inmobiliaria Chapina S.l.",
    "wof:placetype":"venue"
},
  "geometry": {"coordinates":[-5.9862236977,37.3880157471],"type":"Point"}
}