{
  "type": "Feature",
  "properties": {
    "addr:full":"Calle de Marbella, 64 Madrid Madrid 28034",
    "addr:housenumber":"64",
    "addr:postcode":"madrid;28034",
    "addr:street":"Calle De Marbella",
    "iso:country":"ES",
    "sg:address":"Calle de Marbella, 64",
    "sg:city":"Madrid",
    "sg:orig_category":"Agencias Y Agentes Comerciales, Representantes",
    "sg:phone":"+34 917 34 22 81",
    "sg:postcode":"28034",
    "sg:province":"Madrid",
    "wof:name":"Mu\u00f1oz Marti Jose",
    "wof:placetype":"venue"
},
  "geometry": {"coordinates":[-3.7079741955,40.4962463379],"type":"Point"}
}