{
  "type": "Feature",
  "properties": {
    "addr:full":"Carrer de Sant Carles, 50 Santa Coloma De Gramenet Barcelona 08922",
    "addr:housenumber":"50",
    "addr:postcode":"08922",
    "addr:street":"Carrer De Sant Carles",
    "iso:country":"ES",
    "sg:address":"Carrer de Sant Carles, 50",
    "sg:city":"Santa Coloma De Gramenet",
    "sg:orig_category":"Empresarios",
    "sg:phone":"+34 934 66 27 53",
    "sg:postcode":"08922",
    "sg:province":"Barcelona",
    "wof:name":"Reforma Dil Rodriguez S.c.p.",
    "wof:placetype":"venue"
},
  "geometry": {"coordinates":[2.208532095,41.4499092102],"type":"Point"}
}