{
  "type": "Feature",
  "properties": {
    "addr:full":"Pla\u00c7 Bomba, 9 Igualada Barcelona 08700",
    "addr:postcode":"08700",
    "iso:country":"ES",
    "sg:address":"Pla\u00c7 Bomba, 9",
    "sg:city":"Igualada",
    "sg:orig_category":"Carros Elevadores, Carros De Operaciones Portuarias",
    "sg:phone":"+34 938 03 57 06",
    "sg:postcode":"08700",
    "sg:province":"Barcelona",
    "wof:name":"Auto-bomba S. A.",
    "wof:placetype":"venue"
},
  "geometry": {"coordinates":[1.6129490137,41.5849189758],"type":"Point"}
}