{
  "type": "Feature",
  "properties": {
    "addr:full":"Calle de Atabalero, S/n Malaga M\u00e1laga 29010",
    "addr:housenumber":"s",
    "addr:postcode":"29010",
    "addr:street":"Calle De Atabalero;/ N;Ma\u0301Laga",
    "iso:country":"ES",
    "sg:address":"Calle de Atabalero, S/n",
    "sg:city":"Malaga",
    "sg:orig_category":"Agencias Y Agentes Comerciales, Representantes",
    "sg:phone":"+34 952 39 34 94",
    "sg:postcode":"29010",
    "sg:province":"M\u00e1laga",
    "wof:name":"Navarro Rodriguez Miguel",
    "wof:placetype":"venue"
},
  "geometry": {"coordinates":[-4.47082901,36.7312889099],"type":"Point"}
}