{
  "type": "Feature",
  "properties": {
    "addr:full":"Calle de Timanfaya (de), 3 Humanes De Madrid Madrid 28970",
    "addr:postcode":"28970",
    "addr:street":"Calle De Timanfaya De 3",
    "iso:country":"ES",
    "sg:address":"Calle de Timanfaya (de), 3",
    "sg:city":"Humanes De Madrid",
    "sg:orig_category":"Caf\u00c9s, Bares, Cervecer\u00cdas",
    "sg:phone":"+34 916 15 23 97",
    "sg:postcode":"28970",
    "sg:province":"Madrid",
    "wof:name":"Rodriguez Y Lopez C.b.",
    "wof:placetype":"venue"
},
  "geometry": {"coordinates":[-3.8180449009,40.2726364136],"type":"Point"}
}