{
  "type": "Feature",
  "properties": {
    "addr:full":"Carrer de General Moragues, 113 Reus Tarragona 43203",
    "addr:housenumber":"113",
    "addr:postcode":"43203",
    "addr:street":"Carrer De General Moragues",
    "iso:country":"ES",
    "sg:address":"Carrer de General Moragues, 113",
    "sg:city":"Reus",
    "sg:orig_category":"Mercer\u00cda, Lencer\u00cda (al Por Menor)",
    "sg:phone":"+34 977 32 26 72",
    "sg:postcode":"43203",
    "sg:province":"Tarragona",
    "wof:name":"Herrera Roca Noemi",
    "wof:placetype":"venue"
},
  "geometry": {"coordinates":[1.1042749882,41.16198349],"type":"Point"}
}