{
  "type": "Feature",
  "properties": {
    "addr:full":"Aeropuerto, S/n Playa Honda Las Palmas 35509",
    "addr:housenumber":"s / n",
    "addr:postcode":"35509",
    "iso:country":"ES",
    "sg:address":"Aeropuerto, S/n",
    "sg:city":"Playa Honda",
    "sg:orig_category":"Artes Gr\u00c1ficas, Artes Pl\u00c1sticas: Material Y Suministros (al Por Menor)",
    "sg:phone":"+34 928 82 05 28",
    "sg:postcode":"35509",
    "sg:province":"Las Palmas",
    "wof:name":"Select Service Partner S.a.",
    "wof:placetype":"venue"
},
  "geometry": {"coordinates":[-13.5916891098,28.955160141],"type":"Point"}
}