{
  "type": "Feature",
  "properties": {
    "addr:full":"Calle de Monte Sueve, 17 Arriondas Asturias 33540",
    "addr:housenumber":"17",
    "addr:postcode":"33540",
    "addr:street":"Calle De Monte Sueve",
    "iso:country":"ES",
    "sg:address":"Calle de Monte Sueve, 17",
    "sg:city":"Arriondas",
    "sg:orig_category":"M\u00c9dicos: Estomatolog\u00cda",
    "sg:phone":"+34 985 84 08 07",
    "sg:postcode":"33540",
    "sg:province":"Asturias",
    "wof:name":"Garcia Prestamo Jose Carlos",
    "wof:placetype":"venue"
},
  "geometry": {"coordinates":[-5.1880989075,43.3891906738],"type":"Point"}
}