{
  "type": "Feature",
  "properties": {
    "iso:country":"ES",
    "sg:address":"Carrer de Sant Miquel, 41",
    "sg:city":"Barcelona",
    "sg:orig_category":"Papeler\u00cdas, Librer\u00cdas",
    "sg:phone":"+34 932 25 47 94",
    "sg:postcode":"08003",
    "sg:province":"Barcelona",
    "wof:name":"Garcia Borras Agustin",
    "wof:placetype":"venue"
},
  "geometry": {"coordinates":[2.1884260178,41.3796043396],"type":"Point"}
}