{
  "type": "Feature",
  "properties": {
    "iso:country":"ES",
    "sg:address":"Ctra Cervera (de), 33",
    "sg:city":"Agramunt",
    "sg:orig_category":"Contenedores (mercanc\u00cdas)",
    "sg:phone":"+34 973 39 17 46",
    "sg:postcode":"25310",
    "sg:province":"Lleida",
    "wof:name":"Perez Marquez Ramon",
    "wof:placetype":"venue"
},
  "geometry": {"coordinates":[1.1030199528,41.7843093872],"type":"Point"}
}