{
  "type": "Feature",
  "properties": {
    "addr:full":"Calle de Requena Espinar, 9 Guadix Granada 18500",
    "addr:housenumber":"9",
    "addr:postcode":"18500",
    "addr:street":"Calle De Requena Espinar",
    "iso:country":"ES",
    "sg:address":"Calle de Requena Espinar, 9",
    "sg:city":"Guadix",
    "sg:orig_category":"Mercer\u00cda, Lencer\u00cda (al Por Menor)",
    "sg:phone":"+34 958 66 00 90",
    "sg:postcode":"18500",
    "sg:province":"Granada",
    "wof:name":"Gomez Benavente Manuel",
    "wof:placetype":"venue"
},
  "geometry": {"coordinates":[-3.1342520714,37.3007659912],"type":"Point"}
}