{
  "type": "Feature",
  "properties": {
    "iso:country":"ES",
    "sg:address":"Calle de Guillen Robles, 13",
    "sg:city":"Malaga",
    "sg:orig_category":"Promotores Constructores",
    "sg:phone":"+34 952 25 59 59",
    "sg:postcode":"29013",
    "sg:province":"M\u00e1laga",
    "wof:name":"Gonzalez Retamero Antonio",
    "wof:placetype":"venue"
},
  "geometry": {"coordinates":[-4.4142074585,36.7345581055],"type":"Point"}
}