{
  "type": "Feature",
  "properties": {
    "addr:full":"Calle de Alamo (del), 12 Humanes De Madrid Madrid 28970",
    "addr:housenumber":"12",
    "addr:postcode":"28970",
    "addr:street":"Calle De Alamo Del",
    "iso:country":"ES",
    "sg:address":"Calle de Alamo (del), 12",
    "sg:city":"Humanes De Madrid",
    "sg:orig_category":"Serigraf\u00cda (material Y Suministros)",
    "sg:phone":"+34 916 04 89 77",
    "sg:postcode":"28970",
    "sg:province":"Madrid",
    "wof:name":"Industrial Serigrafica S.l.",
    "wof:placetype":"venue"
},
  "geometry": {"coordinates":[-3.8105971813,40.2666931152],"type":"Point"}
}