{
  "type": "Feature",
  "properties": {
    "addr:full":"Avda Constitucion, S/n Miranda Del Casta\u00e7ar Salamanca 37660",
    "addr:postcode":"37660",
    "addr:street":"Avda Constitucion S / N Miranda Del",
    "iso:country":"ES",
    "sg:address":"Avda Constitucion, S/n",
    "sg:city":"Miranda Del Casta\u00e7ar",
    "sg:orig_category":"Centros De Educaci\u00d3n Especial",
    "sg:phone":"+34 923 43 20 66",
    "sg:postcode":"37660",
    "sg:province":"Salamanca",
    "wof:name":"Colegio Nacional Comarcal",
    "wof:placetype":"venue"
},
  "geometry": {"coordinates":[-5.9989438057,40.4845161438],"type":"Point"}
}