{
  "type": "Feature",
  "properties": {
    "addr:full":"Calle de Santo Domingo De La Calzada, 5 Arnedo La Rioja 26580",
    "addr:housenumber":"5",
    "addr:postcode":"26580",
    "addr:street":"Calle De Santo Domingo De La Calzada;Rioja",
    "iso:country":"ES",
    "sg:address":"Calle de Santo Domingo De La Calzada, 5",
    "sg:city":"Arnedo",
    "sg:orig_category":"Fabricaci\u00d3n, Venta De Cuadros, Accesorios Para Enmarcar",
    "sg:phone":"+34 941 38 23 46",
    "sg:postcode":"26580",
    "sg:province":"La Rioja",
    "wof:name":"Perez Gil De Gomez Juan Antonio",
    "wof:placetype":"venue"
},
  "geometry": {"coordinates":[-2.099891901,42.226184845],"type":"Point"}
}