{
  "type": "Feature",
  "properties": {
    "addr:full":"Calle de Buenos Aires, 1 Coslada Madrid 28820",
    "addr:housenumber":"1",
    "addr:postcode":"28820",
    "addr:street":"Calle De Buenos Aires",
    "iso:country":"ES",
    "sg:address":"Calle de Buenos Aires, 1",
    "sg:city":"Coslada",
    "sg:orig_category":"Comercio De Piezas De Recambio Y De Accesorios De Veh\u00cdculos, Veh\u00cdculos Industriales",
    "sg:phone":"+34 916 69 61 11",
    "sg:postcode":"28820",
    "sg:province":"Madrid",
    "wof:name":"Auto Recambios Cortegana S.l.",
    "wof:placetype":"venue"
},
  "geometry": {"coordinates":[-3.5577480793,40.4253959656],"type":"Point"}
}