{
  "type": "Feature",
  "properties": {
    "iso:country":"ES",
    "sg:address":"Calle de Lope De Vega, 14",
    "sg:city":"Andujar",
    "sg:orig_category":"Plomeros",
    "sg:phone":"+34 953 50 10 53",
    "sg:postcode":"23740",
    "sg:province":"Ja\u00e9n",
    "wof:name":"Exposito Garcia Alfonso",
    "wof:placetype":"venue"
},
  "geometry": {"coordinates":[-4.050178051,38.0427284241],"type":"Point"}
}