{
  "type": "Feature",
  "properties": {
    "addr:full":"Carrer de Joan Torruella I Urpina, 9 Cervello Barcelona 08758",
    "addr:housenumber":"9",
    "addr:postcode":"08758",
    "addr:street":"Carrer De Joan Torruella;Urpina;Barcelona",
    "iso:country":"ES",
    "sg:address":"Carrer de Joan Torruella I Urpina, 9",
    "sg:city":"Cervello",
    "sg:orig_category":"Confecci\u00d3n De Trajes De Ba\u00d1o Y De Ropa De Playa",
    "sg:phone":"+34 936 60 16 12",
    "sg:postcode":"08758",
    "sg:province":"Barcelona",
    "wof:name":"Basmar S. A.",
    "wof:placetype":"venue"
},
  "geometry": {"coordinates":[1.9601069689,41.3991394043],"type":"Point"}
}