{
  "type": "Feature",
  "properties": {
    "addr:full":"Calle de Toledo, 33 Madrid Madrid 28005",
    "addr:housenumber":"33",
    "addr:postcode":"madrid;28005",
    "addr:street":"Calle De Toledo",
    "iso:country":"ES",
    "sg:address":"Calle de Toledo, 33",
    "sg:city":"Madrid",
    "sg:orig_category":"Bancos",
    "sg:phone":"+34 913 64 20 24",
    "sg:postcode":"28005",
    "sg:province":"Madrid",
    "sg:website":"www.deutsche-bank.es",
    "wof:name":"Deutsche Bank S.a.e.",
    "wof:placetype":"venue"
},
  "geometry": {"coordinates":[-3.7078590393,40.4121398926],"type":"Point"}
}