{
  "type": "Feature",
  "properties": {
    "addr:full":"Calle de Miguel De Unamuno, 1 Laguna Duero Valladolid 47140",
    "addr:housenumber":"1",
    "addr:postcode":"47140",
    "addr:street":"Calle De Miguel De Unamuno",
    "iso:country":"ES",
    "sg:address":"Calle de Miguel De Unamuno, 1",
    "sg:city":"Laguna Duero",
    "sg:orig_category":"Ebanister\u00cda",
    "sg:phone":"+34 983 54 18 80",
    "sg:postcode":"47140",
    "sg:province":"Valladolid",
    "wof:name":"Hernandez Garrote Faustino",
    "wof:placetype":"venue"
},
  "geometry": {"coordinates":[-4.7257342339,41.581451416],"type":"Point"}
}