{
  "type": "Feature",
  "properties": {
    "addr:full":"Carr Moll De Llevant, 15 Mao Islas Baleares 07703",
    "addr:housenumber":"15",
    "addr:postcode":"07703",
    "addr:street":"Carr Moll De Llevant",
    "iso:country":"ES",
    "sg:address":"Carr Moll De Llevant, 15",
    "sg:city":"Mao",
    "sg:orig_category":"Caf\u00c9s, Bares, Cervecer\u00cdas",
    "sg:phone":"+34 971 36 52 26",
    "sg:postcode":"07703",
    "sg:province":"Islas Baleares",
    "wof:name":"Pons Cardona Jose Mario",
    "wof:placetype":"venue"
},
  "geometry": {"coordinates":[4.265625,39.8903694153],"type":"Point"}
}