{
  "type": "Feature",
  "properties": {
    "addr:full":"Calle de Lyon, 9 Madrid Madrid 28030",
    "addr:housenumber":"9",
    "addr:postcode":"madrid;28030",
    "addr:street":"Calle De Lyon",
    "iso:country":"ES",
    "sg:address":"Calle de Lyon, 9",
    "sg:city":"Madrid",
    "sg:orig_category":"Instalaci\u00d3n De Aspiraci\u00d3n De Gases Y Humos",
    "sg:phone":"+34 914 30 38 67",
    "sg:postcode":"28030",
    "sg:province":"Madrid",
    "wof:name":"Centralgas S.l.",
    "wof:placetype":"venue"
},
  "geometry": {"coordinates":[-3.628524065,40.4080657959],"type":"Point"}
}