{
  "type": "Feature",
  "properties": {
    "addr:full":"Carrer de Balmes, 109 Barcelona Barcelona 08008",
    "addr:housenumber":"109",
    "addr:postcode":"08008",
    "addr:street":"Carrer De Balmes",
    "iso:country":"ES",
    "sg:address":"Carrer de Balmes, 109",
    "sg:city":"Barcelona",
    "sg:orig_category":"Ense\u00d1anza, Formaci\u00d3n Profesional: Aprendizaje",
    "sg:phone":"+34 934 87 58 58",
    "sg:postcode":"08008",
    "sg:province":"Barcelona",
    "wof:name":"Associacio De Consumidors De La Provincia De Barcelona-acpb",
    "wof:placetype":"venue"
},
  "geometry": {"coordinates":[2.1589553356,41.3920669556],"type":"Point"}
}