{
  "type": "Feature",
  "properties": {
    "addr:full":"Calle de Rosario (del), 56 Valdetorres Jarama Madrid 28150",
    "addr:housenumber":"56",
    "addr:postcode":"28150",
    "addr:street":"Calle De Rosario Del",
    "iso:country":"ES",
    "sg:address":"Calle de Rosario (del), 56",
    "sg:city":"Valdetorres Jarama",
    "sg:orig_category":"Empresas De Electricidad En General",
    "sg:phone":"+34 918 41 42 03",
    "sg:postcode":"28150",
    "sg:province":"Madrid",
    "wof:name":"Gumalux S.l.l.",
    "wof:placetype":"venue"
},
  "geometry": {"coordinates":[-3.5151240826,40.6987876892],"type":"Point"}
}