{
  "type": "Feature",
  "properties": {
    "iso:country":"ES",
    "sg:address":"Calle de Murillo, S/n",
    "sg:city":"Le\u00f3n",
    "sg:orig_category":"Centros De Educaci\u00d3n Especial",
    "sg:phone":"+34 987 20 24 14",
    "sg:postcode":"24005",
    "sg:province":"Le\u00f3n",
    "wof:name":"Colegio Publico Luis Vives",
    "wof:placetype":"venue"
},
  "geometry": {"coordinates":[-5.5633940697,42.5897941589],"type":"Point"}
}