{
  "type": "Feature",
  "properties": {
    "addr:full":"Carr Sant Frederic, 8 Badalona Barcelona 08913",
    "addr:housenumber":"8",
    "addr:postcode":"08913",
    "addr:street":"Carr Sant Frederic",
    "iso:country":"ES",
    "sg:address":"Carr Sant Frederic, 8",
    "sg:city":"Badalona",
    "sg:orig_category":"Telefon\u00cda: Instaladores Varios",
    "sg:phone":"+34 933 83 93 49",
    "sg:postcode":"08913",
    "sg:province":"Barcelona",
    "wof:name":"P.b.c.s.l.",
    "wof:placetype":"venue"
},
  "geometry": {"coordinates":[2.2158429623,41.4413452148],"type":"Point"}
}