{
  "type": "Feature",
  "properties": {
    "addr:full":"Cn Camarrocha, 69 Teulada Alicante 03725",
    "addr:housenumber":"69",
    "addr:postcode":"03725",
    "addr:street":"Camarrocha",
    "iso:country":"ES",
    "sg:address":"Cn Camarrocha, 69",
    "sg:city":"Teulada",
    "sg:orig_category":"Laboratorios Y Cl\u00cdnicas Veterinarias",
    "sg:phone":"+34 966 49 15 66",
    "sg:postcode":"03725",
    "sg:province":"Alicante",
    "wof:name":"Carbonell Tatay Jose Maria",
    "wof:placetype":"venue"
},
  "geometry": {"coordinates":[0.1042950004,38.7289505005],"type":"Point"}
}