{
  "type": "Feature",
  "properties": {
    "addr:full":"Carrer de Xammar (d'en), 2 Mataro Barcelona 08301",
    "addr:housenumber":"2",
    "addr:postcode":"08301",
    "addr:street":"Carrer De Xammar D'En",
    "iso:country":"ES",
    "sg:address":"Carrer de Xammar (d'en), 2",
    "sg:city":"Mataro",
    "sg:orig_category":"Arquitectos",
    "sg:phone":"+34 937 55 18 54",
    "sg:postcode":"08301",
    "sg:province":"Barcelona",
    "wof:name":"Imoscap Arquitectures S.l.",
    "wof:placetype":"venue"
},
  "geometry": {"coordinates":[2.4474830627,41.53956604],"type":"Point"}
}