{
  "type": "Feature",
  "properties": {
    "iso:country":"ES",
    "sg:address":"Betote, Km. 0021,2",
    "sg:city":"Sarria",
    "sg:orig_category":"Venta, Instalaci\u00d3n De Calefacci\u00d3n",
    "sg:phone":"+34 982 53 25 22",
    "sg:postcode":"27617",
    "sg:province":"Lugo",
    "wof:name":"Instalaciones Perez Rio S.",
    "wof:placetype":"venue"
},
  "geometry": {"coordinates":[-7.4039049149,42.8337631226],"type":"Point"}
}