{
  "type": "Feature",
  "properties": {
    "iso:country":"ES",
    "sg:address":"El Prado, 2",
    "sg:city":"S. Vicente Sonsierra",
    "sg:orig_category":"Bebidas",
    "sg:phone":"+34 941 33 42 08",
    "sg:postcode":"26338",
    "sg:province":"La Rioja",
    "wof:name":"Vi\u00f1a Arnillas S.l.",
    "wof:placetype":"venue"
},
  "geometry": {"coordinates":[-2.7569282055,42.5635681152],"type":"Point"}
}