{
  "type": "Feature",
  "properties": {
    "iso:country":"ES",
    "sg:address":"Calle de Ingeniero Torres Quevedo, 29",
    "sg:city":"Cordoba",
    "sg:orig_category":"Muebles",
    "sg:phone":"+34 957 42 90 42",
    "sg:postcode":"14013",
    "sg:province":"C\u00f3rdoba",
    "wof:name":"Nazca Sur S.l.",
    "wof:placetype":"venue"
},
  "geometry": {"coordinates":[-4.7938671112,37.8535499573],"type":"Point"}
}