{
  "type": "Feature",
  "properties": {
    "iso:country":"ES",
    "sg:address":"Avda Aragon, 34",
    "sg:city":"Ainsa",
    "sg:orig_category":"Empresas De Carpinter\u00cda De Madera",
    "sg:phone":"+34 974 51 00 69",
    "sg:postcode":"22330",
    "sg:province":"Huesca",
    "wof:name":"Carpinteria A.araguas S.l.",
    "wof:placetype":"venue"
},
  "geometry": {"coordinates":[0.1395249963,42.4117431641],"type":"Point"}
}