{
  "type": "Feature",
  "properties": {
    "iso:country":"ES",
    "sg:address":"Avda Ricardo Soriano, 56",
    "sg:city":"Marbella",
    "sg:orig_category":"Panader\u00cdas, Panader\u00cdas",
    "sg:phone":"+34 952 85 93 27",
    "sg:postcode":"29600",
    "sg:province":"M\u00e1laga",
    "wof:name":"Qariaqos  Adiba",
    "wof:placetype":"venue"
},
  "geometry": {"coordinates":[-4.8951830864,36.5105476379],"type":"Point"}
}