{
  "type": "Feature",
  "properties": {
    "addr:full":"Carrer de Pi I Margall, 11 Viladecans Barcelona 08840",
    "addr:housenumber":"11",
    "addr:postcode":"08840",
    "addr:street":"Carrer De Pi I Margall",
    "iso:country":"ES",
    "sg:address":"Carrer de Pi I Margall, 11",
    "sg:city":"Viladecans",
    "sg:orig_category":"M\u00c9dicos: Pediatr\u00cda. Enfermedades De Los Ni\u00d1os",
    "sg:phone":"+34 936 58 29 39",
    "sg:postcode":"08840",
    "sg:province":"Barcelona",
    "wof:name":"Ros Viladom Joan",
    "wof:placetype":"venue"
},
  "geometry": {"coordinates":[2.0180399418,41.3149795532],"type":"Point"}
}