{
  "type": "Feature",
  "properties": {
    "iso:country":"ES",
    "sg:address":"Calle de Mayor, 45",
    "sg:city":"Toral De Los Guzmanes",
    "sg:orig_category":"Cr\u00cda De Animales",
    "sg:phone":"+34 987 76 02 68",
    "sg:postcode":"24237",
    "sg:province":"Le\u00f3n",
    "wof:name":"Ciembeda S.c.",
    "wof:placetype":"venue"
},
  "geometry": {"coordinates":[-5.5667891502,42.2423591614],"type":"Point"}
}