{
  "type": "Feature",
  "properties": {
    "iso:country":"ES",
    "sg:address":"Calle de Soraluze, 3",
    "sg:city":"Donostia-san Sebastian",
    "sg:orig_category":"Comidas Por Encargo, Organizaci\u00d3n De Recepciones",
    "sg:phone":"+34 943 42 67 08",
    "sg:postcode":"20003",
    "sg:province":"Guip\u00f9zcoa",
    "wof:name":"Ziganda Apaolaza Ainhoa",
    "wof:placetype":"venue"
},
  "geometry": {"coordinates":[-1.983602643,43.3249282837],"type":"Point"}
}