{
  "type": "Feature",
  "properties": {
    "iso:country":"ES",
    "sg:address":"Calle de Adolfo De Castro, 39",
    "sg:city":"Cadiz",
    "sg:orig_category":"Pod\u00d3logos: Pedicuros",
    "sg:phone":"+34 956 22 28 18",
    "sg:postcode":"11003",
    "sg:province":"C\u00e1diz",
    "wof:name":"Esborronda Gonzalez Jose",
    "wof:placetype":"venue"
},
  "geometry": {"coordinates":[-6.3003196716,36.5368804932],"type":"Point"}
}