{
  "type": "Feature",
  "properties": {
    "iso:country":"ES",
    "sg:address":"Calle de Basauri, 17",
    "sg:city":"Madrid",
    "sg:orig_category":"Financiaci\u00d3n Y Cr\u00c9ditos",
    "sg:phone":"+34 913 07 63 00",
    "sg:postcode":"28023",
    "sg:province":"Madrid",
    "wof:name":"Corporacion Financiera Alba S.a.",
    "wof:placetype":"venue"
},
  "geometry": {"coordinates":[-3.8041250706,40.4669570923],"type":"Point"}
}