{
  "type": "Feature",
  "properties": {
    "addr:full":"Calle de Pedro Ortiz Ramos, 63 Santa Olalla Toledo 45530",
    "addr:housenumber":"63",
    "addr:postcode":"45530",
    "addr:street":"Calle De Pedro Ortiz Ramos",
    "iso:country":"ES",
    "sg:address":"Calle de Pedro Ortiz Ramos, 63",
    "sg:city":"Santa Olalla",
    "sg:orig_category":"Fabricaci\u00d3n De Bordes Y Molduras Para Edificaci\u00d3n Y Decoraci\u00d3n",
    "sg:phone":"+34 925 79 79 80",
    "sg:postcode":"45530",
    "sg:province":"Toledo",
    "wof:name":"Molduras Rosino S.l.",
    "wof:placetype":"venue"
},
  "geometry": {"coordinates":[-4.4363288879,40.0238342285],"type":"Point"}
}