{
  "type": "Feature",
  "properties": {
    "addr:full":"Calle de Sabino Berthelot, 13 San Lazaro Santa Cruz De Tenerife 38206",
    "addr:housenumber":"13",
    "addr:postcode":"38206",
    "addr:street":"Calle De Sabino Berthelot",
    "iso:country":"ES",
    "sg:address":"Calle de Sabino Berthelot, 13",
    "sg:city":"San Lazaro",
    "sg:orig_category":"Venta, Montaje De Neum\u00c1ticos",
    "sg:phone":"+34 922 25 35 52",
    "sg:postcode":"38206",
    "sg:province":"Santa Cruz De Tenerife",
    "wof:name":"Albertos Pulido Fernando",
    "wof:placetype":"venue"
},
  "geometry": {"coordinates":[-16.2548561096,28.4698104858],"type":"Point"}
}