{
  "type": "Feature",
  "properties": {
    "iso:country":"ES",
    "sg:address":"Calle de Buen Aire, 1",
    "sg:city":"Camas",
    "sg:classifiers":[
        {
            "category":"Home & Garden",
            "subcategory":"Household Appliances",
            "type":"Retail Goods"
        }
    ],
    "sg:phone":"+34 954 39 16 40",
    "sg:postcode":"41900",
    "sg:province":"Sevilla",
    "sg:tags":[
        "bodega",
        "de",
        "vino",
        "acondicionamiento"
    ],
    "wof:name":"Dominguez Pavon Manuel",
    "wof:placetype":"venue"
},
  "geometry": {"coordinates":[-6.0454707146,37.4011039734],"type":"Point"}
}