{
  "type": "Feature",
  "properties": {
    "addr:full":"Calle de Rios, 84 Paredilla I Las Palmas 35110",
    "addr:housenumber":"84",
    "addr:postcode":"35110",
    "addr:street":"Calle De Rios",
    "iso:country":"ES",
    "sg:address":"Calle de Rios, 84",
    "sg:city":"Paredilla I",
    "sg:orig_category":"Supermercados Y Hipermercados",
    "sg:phone":"+34 928 75 16 52",
    "sg:postcode":"35110",
    "sg:province":"Las Palmas",
    "wof:name":"Alvymat S.a.",
    "wof:placetype":"venue"
},
  "geometry": {"coordinates":[-15.4510936737,27.8392524719],"type":"Point"}
}