{
  "type": "Feature",
  "properties": {
    "addr:full":"C/ Migdia, 10 Banyoles Girona 17820",
    "addr:housenumber":"10",
    "addr:postcode":"17820",
    "addr:street":"C / Migdia",
    "iso:country":"ES",
    "sg:address":"C/ Migdia, 10",
    "sg:city":"Banyoles",
    "sg:orig_category":"Camas (al Por Menor)",
    "sg:phone":"+34 972 57 54 54",
    "sg:postcode":"17820",
    "sg:province":"Girona",
    "wof:name":"Banyoles Alberg S.l.",
    "wof:placetype":"venue"
},
  "geometry": {"coordinates":[2.766340971,42.1175689697],"type":"Point"}
}