{
  "type": "Feature",
  "properties": {
    "addr:full":"Avda Alfonso Pe\u00d1a, 5 Santo Domingo De La Calzada La Rioja 26250",
    "addr:housenumber":"5",
    "addr:postcode":"26250",
    "addr:street":"Avda Alfonso Pen\u0303A;Calzada;Rioja",
    "iso:country":"ES",
    "sg:address":"Avda Alfonso Pe\u00d1a, 5",
    "sg:city":"Santo Domingo De La Calzada",
    "sg:orig_category":"Negocio De Materiales De Construcci\u00d3n",
    "sg:phone":"+34 941 34 09 13",
    "sg:postcode":"26250",
    "sg:province":"La Rioja",
    "wof:name":"Robredo Saez Aurelio",
    "wof:placetype":"venue"
},
  "geometry": {"coordinates":[-2.9532029629,42.4378967285],"type":"Point"}
}