{
  "type": "Feature",
  "properties": {
    "iso:country":"ES",
    "sg:address":"Calle de Sagasta, 85",
    "sg:city":"Jumilla",
    "sg:orig_category":"Tapicer\u00cdas",
    "sg:phone":"+34 968 78 36 37",
    "sg:postcode":"30520",
    "sg:province":"Murcia",
    "wof:name":"Navarro Gonzalez Francisco",
    "wof:placetype":"venue"
},
  "geometry": {"coordinates":[-1.3240474463,38.4773101807],"type":"Point"}
}