{
  "type": "Feature",
  "properties": {
    "iso:country":"ES",
    "sg:address":"Calle de Muro, 1",
    "sg:city":"Algeciras",
    "sg:orig_category":"Bancos",
    "sg:phone":"+34 956 66 68 07",
    "sg:postcode":"11201",
    "sg:province":"C\u00e1diz",
    "wof:name":"Rodriguez Rodriguez Francisco",
    "wof:placetype":"venue"
},
  "geometry": {"coordinates":[-5.4460310936,36.1310310364],"type":"Point"}
}