{
  "type": "Feature",
  "properties": {
    "iso:country":"ES",
    "sg:address":"Calle de Maestro Bartolome, 3",
    "sg:city":"Jaen",
    "sg:orig_category":"Arquitectos",
    "sg:phone":"+34 953 25 74 20",
    "sg:postcode":"23007",
    "sg:province":"Ja\u00e9n",
    "wof:name":"Quesada Eliche Manuel",
    "wof:placetype":"venue"
},
  "geometry": {"coordinates":[-3.7906799316,37.777557373],"type":"Point"}
}