{
  "type": "Feature",
  "properties": {
    "addr:full":"Avda Emigrantes, 6 Puebla Del Principe Ciudad Real 13342",
    "addr:housenumber":"6",
    "addr:postcode":"13342",
    "addr:street":"Avda Emigrantes;Del Principe",
    "iso:country":"ES",
    "sg:address":"Avda Emigrantes, 6",
    "sg:city":"Puebla Del Principe",
    "sg:orig_category":"Cajas Para Embalar",
    "sg:phone":"+34 926 35 90 94",
    "sg:postcode":"13342",
    "sg:province":"Ciudad Real",
    "wof:name":"Caja Rural De Ciudad Real",
    "wof:placetype":"venue"
},
  "geometry": {"coordinates":[-2.9268960953,38.5677261353],"type":"Point"}
}