{
  "type": "Feature",
  "properties": {
    "iso:country":"ES",
    "sg:address":"Calle de Ruzafa, 19",
    "sg:city":"Valencia",
    "sg:orig_category":"Frutas, Legumbres Frescas Y Tempranas (al Por Menor)",
    "sg:phone":"+34 963 52 03 14",
    "sg:postcode":"46004",
    "sg:province":"Valencia",
    "wof:name":"Anton Blasco Dionisio",
    "wof:placetype":"venue"
},
  "geometry": {"coordinates":[-0.3744193912,39.466091156],"type":"Point"}
}