{
  "type": "Feature",
  "properties": {
    "iso:country":"ES",
    "sg:address":"Plaz Fuero Real De Gran Canaria, 2",
    "sg:city":"Palmas De Gran Canaria",
    "sg:orig_category":"Asesor\u00cda Sobre Comunicaci\u00d3n De Empresas",
    "sg:phone":"+34 928 23 41 95",
    "sg:postcode":"35004",
    "sg:province":"Las Palmas",
    "wof:name":"Del Rio Fresen, Cristina 000654445n,slne",
    "wof:placetype":"venue"
},
  "geometry": {"coordinates":[-15.4191379547,28.114900589],"type":"Point"}
}