{
  "type": "Feature",
  "properties": {
    "iso:country":"ES",
    "sg:address":"Calle de Real, 80",
    "sg:city":"Cuadros",
    "sg:orig_category":"Material Y Suministros Para Perforaciones, Sondeos",
    "sg:phone":"+34 987 57 73 50",
    "sg:postcode":"24620",
    "sg:province":"Le\u00f3n",
    "wof:name":"Garcia Garcia Jorge",
    "wof:placetype":"venue"
},
  "geometry": {"coordinates":[-5.6431288719,42.7060012817],"type":"Point"}
}