{
  "type": "Feature",
  "properties": {
    "iso:country":"ES",
    "sg:address":"Carrer de Despuig, 7",
    "sg:city":"Palma",
    "sg:orig_category":"Molduras, Junquillos, Listones Y Molduras Perforadas",
    "sg:phone":"+34 971 28 01 35",
    "sg:postcode":"07013",
    "sg:province":"Islas Baleares",
    "wof:name":"Colom Deya Lucas",
    "wof:placetype":"venue"
},
  "geometry": {"coordinates":[2.6365089417,39.5751876831],"type":"Point"}
}