{
  "type": "Feature",
  "properties": {
    "iso:country":"ES",
    "sg:address":"Avda. Finisterre, 106",
    "sg:city":"A Coru\u00f1a",
    "sg:orig_category":"Colchones (fabricaci\u00d3n, Al Por Mayor, Al Por Menor)",
    "sg:phone":"+34 981 25 12 26",
    "sg:postcode":"15004",
    "sg:province":"La Coru\u00f1a",
    "wof:name":"Salcines Martinez Francisco",
    "wof:placetype":"venue"
},
  "geometry": {"coordinates":[-8.4129447937,43.3638076782],"type":"Point"}
}