{
  "type": "Feature",
  "properties": {
    "iso:country":"ES",
    "sg:address":"Grup Alonso Allende, S/n",
    "sg:city":"Portugalete",
    "sg:orig_category":"Iglesia Cat\u00d3lica",
    "sg:phone":"+34 944 96 21 04",
    "sg:postcode":"48920",
    "sg:province":"Vizcaya",
    "wof:name":"Parroquia San Cristobal De Repelega",
    "wof:placetype":"venue"
},
  "geometry": {"coordinates":[-3.0176389217,43.3117141724],"type":"Point"}
}