{
  "type": "Feature",
  "properties": {
    "iso:country":"ES",
    "sg:address":"Calle de Floranes, 63",
    "sg:city":"Santander",
    "sg:orig_category":"Muebles, Minoristas",
    "sg:phone":"+34 942 23 03 56",
    "sg:postcode":"39010",
    "sg:province":"Cantabria",
    "sg:website":"www.eltrasterodefloranes.com",
    "wof:name":"Alvarez Sanz Importacion Exportacion Y Comercializacion S.l",
    "wof:placetype":"venue"
},
  "geometry": {"coordinates":[-3.8254683018,43.4596939087],"type":"Point"}
}