{
  "type": "Feature",
  "properties": {
    "iso:country":"ES",
    "sg:address":"Carrer de Sabadell, 41",
    "sg:city":"Rubi",
    "sg:orig_category":"Peluquer\u00cdas, Peluquer\u00cda Mixta",
    "sg:phone":"+34 935 88 76 86",
    "sg:postcode":"08191",
    "sg:province":"Barcelona",
    "wof:name":"Querol Diaz Juan",
    "wof:placetype":"venue"
},
  "geometry": {"coordinates":[2.0322239399,41.4981231689],"type":"Point"}
}