{
  "type": "Feature",
  "properties": {
    "iso:country":"ES",
    "sg:address":"Calle de Santa Clara, 18",
    "sg:city":"Zamora",
    "sg:orig_category":"Cajas De Ahorro",
    "sg:phone":"+34 980 50 98 00",
    "sg:postcode":"49014",
    "sg:province":"Zamora",
    "wof:name":"Caja Espa\u00f1a De Inversiones Caja De Ahorros Y Monte De Piedad",
    "wof:placetype":"venue"
},
  "geometry": {"coordinates":[-5.7426519394,41.5059051514],"type":"Point"}
}