{
  "type": "Feature",
  "properties": {
    "addr:full":"Calle de Espinosa De Los Monteros, 2 Sevilla Sevilla 41005",
    "addr:housenumber":"2",
    "addr:postcode":"41005",
    "addr:street":"Calle De Espinosa De Los Monteros",
    "iso:country":"ES",
    "sg:address":"Calle de Espinosa De Los Monteros, 2",
    "sg:city":"Sevilla",
    "sg:orig_category":"Empresas De Pintura Y Revestimientos",
    "sg:phone":"+34 954 66 15 71",
    "sg:postcode":"41005",
    "sg:province":"Sevilla",
    "wof:name":"Marquez Diaz Manuel",
    "wof:placetype":"venue"
},
  "geometry": {"coordinates":[-5.9643149376,37.3811416626],"type":"Point"}
}