{
  "type": "Feature",
  "properties": {
    "addr:full":"Calle de Espada, 25 Alcorcon Madrid 28921",
    "addr:housenumber":"25",
    "addr:postcode":"28921",
    "addr:street":"Calle De Espada",
    "iso:country":"ES",
    "sg:address":"Calle de Espada, 25",
    "sg:city":"Alcorcon",
    "sg:orig_category":"Molduras, Junquillos, Listones Y Molduras Perforadas",
    "sg:phone":"+34 916 44 32 62",
    "sg:postcode":"28921",
    "sg:province":"Madrid",
    "wof:name":"Rodriguez Lopez Rafael",
    "wof:placetype":"venue"
},
  "geometry": {"coordinates":[-3.8260149956,40.3461265564],"type":"Point"}
}