{
  "type": "Feature",
  "properties": {
    "iso:country":"ES",
    "sg:address":"Calle de Itsasbide Kalea, 28",
    "sg:city":"Elexalde Auzoa",
    "sg:orig_category":"Edici\u00d3n De Diarios, Revistas, Boletines",
    "sg:phone":"+34 946 77 14 34",
    "sg:postcode":"48630",
    "sg:province":"Vizcaya",
    "wof:name":"Echevarria Alvarez Maria Carmen",
    "wof:placetype":"venue"
},
  "geometry": {"coordinates":[-2.9439508915,43.4078445435],"type":"Point"}
}