{
  "type": "Feature",
  "properties": {
    "addr:full":"Carrer de Samuntada, 77 Sabadell Barcelona 08203",
    "addr:housenumber":"77",
    "addr:postcode":"08203",
    "addr:street":"Carrer De Samuntada",
    "iso:country":"ES",
    "sg:address":"Carrer de Samuntada, 77",
    "sg:city":"Sabadell",
    "sg:orig_category":"Panader\u00cdas, Panader\u00cdas",
    "sg:phone":"+34 937 12 10 07",
    "sg:postcode":"08203",
    "sg:province":"Barcelona",
    "wof:name":"Pastisserias Guardia S.l.",
    "wof:placetype":"venue"
},
  "geometry": {"coordinates":[2.1191859245,41.5352592468],"type":"Point"}
}