{
  "type": "Feature",
  "properties": {
    "addr:full":"Calle de Ramon Y Cajal, 10 Alagon Zaragoza 50630",
    "addr:housenumber":"10",
    "addr:postcode":"50630",
    "addr:street":"Calle De Ramon Y Cajal",
    "iso:country":"ES",
    "sg:address":"Calle de Ramon Y Cajal, 10",
    "sg:city":"Alagon",
    "sg:orig_category":"Internados & Ense\u00d1anza Privada",
    "sg:phone":"+34 976 61 13 74",
    "sg:postcode":"50630",
    "sg:province":"Zaragoza",
    "wof:name":"Becerril Gutierrez Jose Maria",
    "wof:placetype":"venue"
},
  "geometry": {"coordinates":[-1.1210700274,41.7708435059],"type":"Point"}
}