{
  "type": "Feature",
  "properties": {
    "addr:full":"Calle de Mayor, 36 Tafalla Navarra 31300",
    "addr:housenumber":"36",
    "addr:postcode":"31300",
    "addr:street":"Calle De Mayor",
    "iso:country":"ES",
    "sg:address":"Calle de Mayor, 36",
    "sg:city":"Tafalla",
    "sg:classifiers":[
        {
            "category":"Taxi",
            "type":"Transportation"
        }
    ],
    "sg:phone":"+34 948 70 12 77",
    "sg:postcode":"31300",
    "sg:province":"Navarra",
    "wof:name":"Rodriguez Merino Ignacio",
    "wof:placetype":"venue"
},
  "geometry": {"coordinates":[-1.6749459505,42.5292396545],"type":"Point"}
}