{
  "type": "Feature",
  "properties": {
    "iso:country":"ES",
    "sg:address":"Cmno Encinas (somio), 405",
    "sg:city":"Gijon",
    "sg:orig_category":"Agencias Y Agentes Comerciales, Representantes",
    "sg:phone":"+34 985 33 69 69",
    "sg:postcode":"33203",
    "sg:province":"Asturias",
    "wof:name":"Rafael Riera Cadavieco Josefina Martinez Villase\u00f1or Y Otros Cdad",
    "wof:placetype":"venue"
},
  "geometry": {"coordinates":[-5.5962839127,43.5261116028],"type":"Point"}
}