{
  "type": "Feature",
  "properties": {
    "iso:country":"ES",
    "sg:address":"Avda Moratalaz, 162",
    "sg:city":"Madrid",
    "sg:orig_category":"Inmobiliaria (agencias)",
    "sg:phone":"+34 914 30 25 97",
    "sg:postcode":"28030",
    "sg:province":"Madrid",
    "wof:name":"Propietas Gonzalez Servicios Inmobiliarios S.l.",
    "wof:placetype":"venue"
},
  "geometry": {"coordinates":[-3.6468229294,40.4072952271],"type":"Point"}
}