{
  "type": "Feature",
  "properties": {
    "iso:country":"ES",
    "sg:address":"Las Vi\u00f1as, 12",
    "sg:city":"Herrera",
    "sg:orig_category":"Empresas De Carpinter\u00cda",
    "sg:phone":"+34 954 01 23 18",
    "sg:postcode":"41567",
    "sg:province":"Sevilla",
    "wof:name":"Aluminios Francisco S.l",
    "wof:placetype":"venue"
},
  "geometry": {"coordinates":[-4.8458638191,37.3695106506],"type":"Point"}
}