{
  "type": "Feature",
  "properties": {
    "addr:full":"Ctra La Murada, Km. 0030,5 Benferri Alicante 03315",
    "addr:postcode":"03315",
    "addr:street":"Ctra La Murada Km. 0030,5",
    "iso:country":"ES",
    "sg:address":"Ctra La Murada, Km. 0030,5",
    "sg:city":"Benferri",
    "sg:orig_category":"Empresas De Electricidad En General",
    "sg:phone":"+34 965 36 95 55",
    "sg:postcode":"03315",
    "sg:province":"Alicante",
    "sg:website":"www.ree.es",
    "wof:name":"Red Electrica De Espa\u00f1a S.a.",
    "wof:placetype":"venue"
},
  "geometry": {"coordinates":[-0.9639940262,38.1715431213],"type":"Point"}
}