{
  "type": "Feature",
  "properties": {
    "addr:full":"Calle de Arrospide Jon, 20 Bilbao Vizcaya 48014",
    "addr:housenumber":"20",
    "addr:postcode":"48014",
    "addr:street":"Calle De Arrospide Jon",
    "iso:country":"ES",
    "sg:address":"Calle de Arrospide Jon, 20",
    "sg:city":"Bilbao",
    "sg:orig_category":"Maquinaria Para Industrias Diversas",
    "sg:phone":"+34 944 74 62 63",
    "sg:postcode":"48014",
    "sg:province":"Vizcaya",
    "sg:website":"www.eni.es",
    "wof:name":"Electronica Y Neumatica Industrial S. A.",
    "wof:placetype":"venue"
},
  "geometry": {"coordinates":[-2.9503221512,43.2685966492],"type":"Point"}
}