{
  "type": "Feature",
  "properties": {
    "addr:full":"Pol Ind Huercal Overa, 41 Huercal-overa Almer\u00eda 04600",
    "addr:housenumber":"41",
    "addr:postcode":"04600",
    "addr:street":"Huercal Overa;Almeri\u0301A",
    "iso:country":"ES",
    "sg:address":"Pol Ind Huercal Overa, 41",
    "sg:city":"Huercal-overa",
    "sg:orig_category":"Fabricaci\u00d3n De Muebles De Cocina",
    "sg:phone":"+34 950 13 50 50",
    "sg:postcode":"04600",
    "sg:province":"Almer\u00eda",
    "wof:name":"Codelor S.l",
    "wof:placetype":"venue"
},
  "geometry": {"coordinates":[-1.7358249426,37.4396438599],"type":"Point"}
}