{
  "type": "Feature",
  "properties": {
    "addr:full":"Plaz Salvador, 8 Sevilla Sevilla 41004",
    "addr:housenumber":"8",
    "addr:postcode":"41004",
    "addr:street":"Salvador",
    "iso:country":"ES",
    "sg:address":"Plaz Salvador, 8",
    "sg:city":"Sevilla",
    "sg:orig_category":"Industria Qu\u00cdmica",
    "sg:phone":"+34 954 21 65 27",
    "sg:postcode":"41004",
    "sg:province":"Sevilla",
    "wof:name":"Lopez Martin Manuel",
    "wof:placetype":"venue"
},
  "geometry": {"coordinates":[-5.9931540489,37.3903694153],"type":"Point"}
}