{
  "type": "Feature",
  "properties": {
    "addr:full":"Crri Serranos, 18 Beniajan Murcia 30570",
    "addr:housenumber":"18",
    "addr:postcode":"30570",
    "addr:street":"Serranos",
    "iso:country":"ES",
    "sg:address":"Crri Serranos, 18",
    "sg:city":"Beniajan",
    "sg:orig_category":"Promotores Constructores",
    "sg:phone":"+34 968 82 04 52",
    "sg:postcode":"30570",
    "sg:province":"Murcia",
    "wof:name":"Shien 2003 S.l.",
    "wof:placetype":"venue"
},
  "geometry": {"coordinates":[-1.0715739727,37.9755134583],"type":"Point"}
}