{
  "type": "Feature",
  "properties": {
    "addr:full":"Calle de Santa Dorotea, 32 Burgos Burgos 09001",
    "addr:housenumber":"32",
    "addr:postcode":"09001",
    "addr:street":"Calle De Santa Dorotea",
    "iso:country":"ES",
    "sg:address":"Calle de Santa Dorotea, 32",
    "sg:city":"Burgos",
    "sg:orig_category":"Venta, Instalaci\u00d3n, Mantenimiento De Chimeneas De Interior Y Accesorios",
    "sg:phone":"+34 947 26 46 37",
    "sg:postcode":"09001",
    "sg:province":"Burgos",
    "wof:name":"Casta\u00f1eda Alvear Maria Belen",
    "wof:placetype":"venue"
},
  "geometry": {"coordinates":[-3.703537941,42.3332710266],"type":"Point"}
}