{
  "type": "Feature",
  "properties": {
    "iso:country":"ES",
    "sg:address":"Calle de Arce, 3",
    "sg:city":"Zafra",
    "sg:classifiers":[
        {
            "category":"Autos & Motor Vehicles",
            "subcategory":"Automobile Sales",
            "type":"Retail Goods"
        }
    ],
    "sg:phone":"+34 924 55 36 40",
    "sg:postcode":"06300",
    "sg:province":"Badajoz",
    "wof:name":"Autoescuela Jerez S.l.",
    "wof:placetype":"venue"
},
  "geometry": {"coordinates":[-6.4123592377,38.4194908142],"type":"Point"}
}