{
  "type": "Feature",
  "properties": {
    "iso:country":"ES",
    "sg:address":"Carrer de Terrissaires (dels), S/n",
    "sg:city":"Vendrell",
    "sg:orig_category":"Puertas Y Portales",
    "sg:phone":"+34 977 66 86 33",
    "sg:postcode":"43700",
    "sg:province":"Tarragona",
    "wof:name":"Puertas Cano S.l.",
    "wof:placetype":"venue"
},
  "geometry": {"coordinates":[1.5299799442,41.2311897278],"type":"Point"}
}