{
  "type": "Feature",
  "properties": {
    "addr:full":"Castillo-gazteleku, 39 Iru\u00f1a Navarra 31001",
    "addr:housenumber":"39",
    "addr:postcode":"31001",
    "addr:street":"Castillo-Gazteleku",
    "iso:country":"ES",
    "sg:address":"Castillo-gazteleku, 39",
    "sg:city":"Iru\u00f1a",
    "sg:orig_category":"Bancos",
    "sg:phone":"+34 948 20 69 00",
    "sg:postcode":"31001",
    "sg:province":"Navarra",
    "wof:name":"Banco De Vasconia",
    "wof:placetype":"venue"
},
  "geometry": {"coordinates":[-1.6437540054,42.81275177],"type":"Point"}
}