{
  "type": "Feature",
  "properties": {
    "addr:full":"Avda De Los Emigrantes, 4 Navia Asturias 33710",
    "addr:housenumber":"4",
    "addr:postcode":"33710",
    "addr:street":"Avda De Los Emigrantes",
    "iso:country":"ES",
    "sg:address":"Avda De Los Emigrantes, 4",
    "sg:city":"Navia",
    "sg:orig_category":"Art\u00cdculos De Regalo (al Por Menor)",
    "sg:phone":"+34 985 47 33 08",
    "sg:postcode":"33710",
    "sg:province":"Asturias",
    "wof:name":"De Cosas Hogar Y Moda",
    "wof:placetype":"venue"
},
  "geometry": {"coordinates":[-6.7242560387,43.5367050171],"type":"Point"}
}