{
  "type": "Feature",
  "properties": {
    "iso:country":"ES",
    "sg:address":"Carrer de Dalia, 7",
    "sg:city":"Cornella Llobregat",
    "sg:orig_category":"Fabricaci\u00d3n De Productos Textiles Sin Tejer",
    "sg:phone":"+34 933 75 18 53",
    "sg:postcode":"08940",
    "sg:province":"Barcelona",
    "wof:name":"Berdun Lucas Lourdes",
    "wof:placetype":"venue"
},
  "geometry": {"coordinates":[2.0830059052,41.3606643677],"type":"Point"}
}