{
  "type": "Feature",
  "properties": {
    "addr:full":"Rbla Sant Domenec, 20 Vic Barcelona 08500",
    "addr:housenumber":"20",
    "addr:postcode":"08500",
    "addr:street":"Rbla Sant Domenec",
    "iso:country":"ES",
    "sg:address":"Rbla Sant Domenec, 20",
    "sg:city":"Vic",
    "sg:orig_category":"Producci\u00d3n, Comercio De Cereales",
    "sg:phone":"+34 938 85 08 89",
    "sg:postcode":"08500",
    "sg:province":"Barcelona",
    "wof:name":"Morell Sanglas Jose",
    "wof:placetype":"venue"
},
  "geometry": {"coordinates":[2.2533919811,41.9272537231],"type":"Point"}
}