{
  "type": "Feature",
  "properties": {
    "iso:country":"ES",
    "sg:address":"Santiago, 33",
    "sg:city":"Isla Cristina",
    "sg:orig_category":"Alimentaci\u00d3n General (al Por Menor)",
    "sg:phone":"+34 959 33 15 42",
    "sg:postcode":"21410",
    "sg:province":"Huelva",
    "wof:name":"Abreu Garcia Juan Francisco",
    "wof:placetype":"venue"
},
  "geometry": {"coordinates":[-7.325253,37.204987],"type":"Point"}
}