{
  "type": "Feature",
  "properties": {
    "iso:country":"ES",
    "sg:address":"Ctra Alquerias (de), 6",
    "sg:city":"Santomera",
    "sg:orig_category":"Empresas De Carpinter\u00cda De Madera",
    "sg:phone":"+34 968 27 70 72",
    "sg:postcode":"30140",
    "sg:province":"Murcia",
    "wof:name":"Comercial Olmur S.l.",
    "wof:placetype":"venue"
},
  "geometry": {"coordinates":[-1.0524469614,38.0561790466],"type":"Point"}
}