{
  "type": "Feature",
  "properties": {
    "addr:full":"Finc Camino Del Rincon, 1 Aljaraque Huelva 21110",
    "addr:housenumber":"1",
    "addr:postcode":"21110",
    "addr:street":"Camino Del Rincon",
    "iso:country":"ES",
    "sg:address":"Finc Camino Del Rincon, 1",
    "sg:city":"Aljaraque",
    "sg:orig_category":"Administradores De Bienes Y Delegados De Comunidades De Propietarios",
    "sg:phone":"+34 959 31 65 92",
    "sg:postcode":"21110",
    "sg:province":"Huelva",
    "wof:name":"Active Admin S.l",
    "wof:placetype":"venue"
},
  "geometry": {"coordinates":[-7.0220365524,37.2674674988],"type":"Point"}
}