{
  "type": "Feature",
  "properties": {
    "iso:country":"ES",
    "sg:address":"Plaz Magdalena, 9",
    "sg:city":"Sevilla",
    "sg:orig_category":"Centros P\u00dablicos De Formaci\u00d3n Profesional Y T\u00c9cnica",
    "sg:phone":"+34 954 21 09 70",
    "sg:postcode":"41001",
    "sg:province":"Sevilla",
    "wof:name":"Colegio Oficial De Corredores De Comercio",
    "wof:placetype":"venue"
},
  "geometry": {"coordinates":[-5.9967441559,37.3911743164],"type":"Point"}
}