{
  "type": "Feature",
  "properties": {
    "iso:country":"ES",
    "sg:address":"Reino Unido Ciudad Del Transporte, 5",
    "sg:city":"Imarcoain",
    "sg:orig_category":"Transportes Por V\u00cdas Navegables",
    "sg:phone":"+34 948 24 92 00",
    "sg:postcode":"31119",
    "sg:province":"Navarra",
    "sg:website":"www.integra2.es",
    "wof:name":"Transportes Leoz Tranvis S.l.",
    "wof:placetype":"venue"
},
  "geometry": {"coordinates":[-1.5951639414,42.7345542908],"type":"Point"}
}