{
  "type": "Feature",
  "properties": {
    "iso:country":"ES",
    "sg:address":"Calle de Olimpiada, 1",
    "sg:city":"Alcorcon",
    "sg:orig_category":"Peluquer\u00cdas, Peluquer\u00cda Mixta",
    "sg:phone":"+34 916 10 03 14",
    "sg:postcode":"28923",
    "sg:province":"Madrid",
    "wof:name":"Hermanos Queija Revestimientos S.l.",
    "wof:placetype":"venue"
},
  "geometry": {"coordinates":[-3.8167591095,40.3448638916],"type":"Point"}
}