{
  "type": "Feature",
  "properties": {
    "iso:country":"ES",
    "sg:address":"Avda Santiago, 25",
    "sg:city":"Vitoria-gasteiz",
    "sg:orig_category":"Ense\u00d1anza Variada",
    "sg:phone":"+34 945 27 91 33",
    "sg:postcode":"01003",
    "sg:province":"\u00c1lava",
    "wof:name":"Perez De Albeniz Martinez Maria Teresa",
    "wof:placetype":"venue"
},
  "geometry": {"coordinates":[-2.6641850471,42.8474578857],"type":"Point"}
}