{
  "type": "Feature",
  "properties": {
    "iso:country":"ES",
    "sg:address":"Calle de Luis Oliag, 54",
    "sg:city":"Valencia",
    "sg:orig_category":"Inform\u00c1tica (estudios, Servicios, Asesor\u00cda, Formaci\u00d3n)",
    "sg:phone":"+34 963 16 31 29",
    "sg:postcode":"46006",
    "sg:province":"Valencia",
    "sg:website":"www.gestinpe.com",
    "wof:name":"Gestion Informatica De Pensiones S.l",
    "wof:placetype":"venue"
},
  "geometry": {"coordinates":[-0.3624329865,39.4609260559],"type":"Point"}
}