{
  "type": "Feature",
  "properties": {
    "addr:full":"Calle de Platero Suarez, 5 Valencia Valencia 46009",
    "addr:housenumber":"5",
    "addr:postcode":"46009",
    "addr:street":"Calle De Platero Suarez",
    "iso:country":"ES",
    "sg:address":"Calle de Platero Suarez, 5",
    "sg:city":"Valencia",
    "sg:orig_category":"Asesor\u00cda Fiscal Y Jur\u00cddica",
    "sg:phone":"+34 963 68 03 27",
    "sg:postcode":"46009",
    "sg:province":"Valencia",
    "wof:name":"Pastor Marco Julian",
    "wof:placetype":"venue"
},
  "geometry": {"coordinates":[-0.3719489872,39.4850883484],"type":"Point"}
}