{
  "type": "Feature",
  "properties": {
    "iso:country":"ES",
    "sg:address":"Barrio Nuv San Clemente, 1",
    "sg:city":"Huescar",
    "sg:orig_category":"Farmacias",
    "sg:phone":"+34 958 74 01 32",
    "sg:postcode":"18830",
    "sg:province":"Granada",
    "wof:name":"Garcia-espona Pancorbo Jose Luis",
    "wof:placetype":"venue"
},
  "geometry": {"coordinates":[-2.5371389389,37.8127250671],"type":"Point"}
}