{
  "type": "Feature",
  "properties": {
    "iso:country":"ES",
    "sg:address":"Calle de San Erasmo, 42",
    "sg:city":"Madrid",
    "sg:orig_category":"Trabajos De Aislamiento T\u00c9rmico Y Ac\u00dastico",
    "sg:phone":"+34 915 05 06 33",
    "sg:postcode":"28021",
    "sg:province":"Madrid",
    "wof:name":"Aislamientos J.m. Calvillo S.l.",
    "wof:placetype":"venue"
},
  "geometry": {"coordinates":[-3.7064712048,40.3334083557],"type":"Point"}
}