{
  "type": "Feature",
  "properties": {
    "iso:country":"ES",
    "sg:address":"Ctra Daganzo, Km. 0000,2",
    "sg:city":"Ajalvir",
    "sg:orig_category":"Quincaller\u00cda (fabricaci\u00d3n)",
    "sg:phone":"+34 918 84 40 23",
    "sg:postcode":"28864",
    "sg:province":"Madrid",
    "sg:website":"www.clavosespa\u00f1oles.com",
    "wof:name":"Clavos Espa\u00f1oles S. L.",
    "wof:placetype":"venue"
},
  "geometry": {"coordinates":[-3.4845490456,40.5355567932],"type":"Point"}
}