{
  "type": "Feature",
  "properties": {
    "iso:country":"ES",
    "sg:address":"Calle de Archiduque Carlos, 21",
    "sg:city":"Valencia",
    "sg:orig_category":"Relojer\u00cda (al Por Menor, Reparaci\u00d3n)",
    "sg:phone":"+34 963 84 09 52",
    "sg:postcode":"46018",
    "sg:province":"Valencia",
    "wof:name":"Relojeria Paris C.b.",
    "wof:placetype":"venue"
},
  "geometry": {"coordinates":[-0.3935394883,39.4662666321],"type":"Point"}
}