{
  "type": "Feature",
  "properties": {
    "iso:country":"ES",
    "sg:address":"Avda Estacion (la), 35",
    "sg:city":"Astorga",
    "sg:orig_category":"Caf\u00c9s, Bares, Cervecer\u00cdas",
    "sg:phone":"+34 987 61 51 55",
    "sg:postcode":"24700",
    "sg:province":"Le\u00f3n",
    "wof:name":"Lopez Garcia Angel",
    "wof:placetype":"venue"
},
  "geometry": {"coordinates":[-6.0479960442,42.4593925476],"type":"Point"}
}