{
  "type": "Feature",
  "properties": {
    "iso:country":"ES",
    "sg:address":"Calle de Joaquin Costa, 37",
    "sg:city":"Valencia",
    "sg:orig_category":"Abogados",
    "sg:phone":"+34 963 95 76 81",
    "sg:postcode":"46005",
    "sg:province":"Valencia",
    "wof:name":"Mellado Porres Manuel",
    "wof:placetype":"venue"
},
  "geometry": {"coordinates":[-0.3664604127,39.4651451111],"type":"Point"}
}