{
  "type": "Feature",
  "properties": {
    "iso:country":"ES",
    "sg:address":"C/ Riu Sec, 40",
    "sg:city":"Cerdanyola Valles",
    "sg:orig_category":"Promotores Constructores",
    "sg:phone":"+34 935 94 71 25",
    "sg:postcode":"08290",
    "sg:province":"Barcelona",
    "wof:name":"Tipe S.a.",
    "wof:placetype":"venue"
},
  "geometry": {"coordinates":[2.1470150948,41.4924812317],"type":"Point"}
}