{
  "type": "Feature",
  "properties": {
    "iso:country":"ES",
    "sg:address":"Calle de Panama, 4",
    "sg:city":"Madrid",
    "sg:orig_category":"M\u00c9dicos: Cardiolog\u00cda Y Afecciones Cardiovasculares",
    "sg:phone":"+34 914 58 78 88",
    "sg:postcode":"28036",
    "sg:province":"Madrid",
    "wof:name":"Martinez Sanchez Jose Ignacio",
    "wof:placetype":"venue"
},
  "geometry": {"coordinates":[-3.6891579628,40.4564399719],"type":"Point"}
}