{
  "type": "Feature",
  "properties": {
    "iso:country":"ES",
    "sg:address":"Pg Estacio (de L'), 7",
    "sg:city":"Torredembarra",
    "sg:orig_category":"Administradores De Bienes Y Delegados De Comunidades De Propietarios",
    "sg:phone":"+34 977 64 54 96",
    "sg:postcode":"43830",
    "sg:province":"Tarragona",
    "wof:name":"Centre Comptable Estacio S.l.",
    "wof:placetype":"venue"
},
  "geometry": {"coordinates":[1.4047620296,41.1440658569],"type":"Point"}
}