{
  "type": "Feature",
  "properties": {
    "addr:full":"Carrer de Arx Lluis Salvador, 17 Palma Islas Baleares 07004",
    "addr:housenumber":"17",
    "addr:postcode":"07004",
    "addr:street":"Carrer De Arx Lluis Salvador",
    "iso:country":"ES",
    "sg:address":"Carrer de Arx Lluis Salvador, 17",
    "sg:city":"Palma",
    "sg:orig_category":"Arquitectos",
    "sg:phone":"+34 971 75 15 02",
    "sg:postcode":"07004",
    "sg:province":"Islas Baleares",
    "wof:name":"Bennasar Martin Arquitectes S.l.",
    "wof:placetype":"venue"
},
  "geometry": {"coordinates":[2.653758049,39.5790367126],"type":"Point"}
}