{
  "type": "Feature",
  "properties": {
    "addr:full":"Calle de Estacion, 33 Miranda Ebro Burgos 09200",
    "addr:housenumber":"33",
    "addr:postcode":"09200",
    "addr:street":"Calle De Estacion",
    "iso:country":"ES",
    "sg:address":"Calle de Estacion, 33",
    "sg:city":"Miranda Ebro",
    "sg:orig_category":"Agencias De Viajes",
    "sg:phone":"+34 947 33 31 19",
    "sg:postcode":"09200",
    "sg:province":"Burgos",
    "sg:website":"www.viajeseroski.es",
    "wof:name":"Viajes Eroski S.a.",
    "wof:placetype":"venue"
},
  "geometry": {"coordinates":[-2.9435949326,42.6882133484],"type":"Point"}
}