{
  "type": "Feature",
  "properties": {
    "addr:full":"Calle de Olavide, 22 Carolina Ja\u00e9n 23200",
    "addr:housenumber":"22",
    "addr:postcode":"23200",
    "addr:street":"Calle De Olavide;Jae\u0301N",
    "iso:country":"ES",
    "sg:address":"Calle de Olavide, 22",
    "sg:city":"Carolina",
    "sg:orig_category":"Lavander\u00cdas Para Particulares, Autoservicio De Lavander\u00cdas",
    "sg:phone":"+34 953 68 17 70",
    "sg:postcode":"23200",
    "sg:province":"Ja\u00e9n",
    "wof:name":"Lucas Alarcon Maria Teresa",
    "wof:placetype":"venue"
},
  "geometry": {"coordinates":[-3.6178219318,38.2735977173],"type":"Point"}
}