{
  "type": "Feature",
  "properties": {
    "addr:full":"Calle de Francisco Fontecha, 5 Albacete Albacete 02001",
    "addr:housenumber":"5",
    "addr:postcode":"02001",
    "addr:street":"Calle De Francisco Fontecha",
    "iso:country":"ES",
    "sg:address":"Calle de Francisco Fontecha, 5",
    "sg:city":"Albacete",
    "sg:orig_category":"Promotores Constructores",
    "sg:phone":"+34 967 21 15 87",
    "sg:postcode":"02001",
    "sg:province":"Albacete",
    "wof:name":"Proyectos Civiles Del Sureste S.l.",
    "wof:placetype":"venue"
},
  "geometry": {"coordinates":[-1.8548090458,38.9948196411],"type":"Point"}
}