{
  "type": "Feature",
  "properties": {
    "addr:full":"Pl Sant Cristofol, 1 Barcelona Barcelona 08038",
    "addr:housenumber":"1",
    "addr:postcode":"08038",
    "addr:street":"Pl Sant Cristofol",
    "iso:country":"ES",
    "sg:address":"Pl Sant Cristofol, 1",
    "sg:city":"Barcelona",
    "sg:orig_category":"Alquiler De Camiones Y Veh\u00cdculos Industriales",
    "sg:phone":"+34 934 21 39 40",
    "sg:postcode":"08038",
    "sg:province":"Barcelona",
    "wof:name":"Gruas Y Servicios Diez S.l.",
    "wof:placetype":"venue"
},
  "geometry": {"coordinates":[2.137034893,41.3587417603],"type":"Point"}
}