{
  "type": "Feature",
  "properties": {
    "addr:full":"Carrer de Moli Del Llobet, 37 Vic Barcelona 08500",
    "addr:housenumber":"37",
    "addr:postcode":"08500",
    "addr:street":"Carrer De Moli Del Llobet",
    "iso:country":"ES",
    "sg:address":"Carrer de Moli Del Llobet, 37",
    "sg:city":"Vic",
    "sg:orig_category":"Art\u00cdculos De Regalo (al Por Menor)",
    "sg:phone":"+34 938 89 23 16",
    "sg:postcode":"08500",
    "sg:province":"Barcelona",
    "wof:name":"Osona Box S.l.",
    "wof:placetype":"venue"
},
  "geometry": {"coordinates":[2.280299902,41.9483108521],"type":"Point"}
}