{
  "type": "Feature",
  "properties": {
    "iso:country":"ES",
    "sg:address":"Calle de Prado, S/n",
    "sg:city":"Valdestillas",
    "sg:orig_category":"Alumbrados",
    "sg:phone":"+34 983 55 13 65",
    "sg:postcode":"47240",
    "sg:province":"Valladolid",
    "sg:website":"www.alselux.net",
    "wof:name":"Alselux Iluminacion S.l.",
    "wof:placetype":"venue"
},
  "geometry": {"coordinates":[-4.7732410431,41.4794845581],"type":"Point"}
}