{
  "type": "Feature",
  "properties": {
    "addr:full":"Carrer de Ali Bei, 10 Barcelona Barcelona 08010",
    "addr:housenumber":"10",
    "addr:postcode":"08010",
    "addr:street":"Carrer De Ali Bei",
    "iso:country":"ES",
    "sg:address":"Carrer de Ali Bei, 10",
    "sg:city":"Barcelona",
    "sg:orig_category":"Fabricaci\u00d3n De Productos Textiles Sin Tejer",
    "sg:phone":"+34 932 32 98 64",
    "sg:postcode":"08010",
    "sg:province":"Barcelona",
    "wof:name":"Organizacion Freaks S.l.",
    "wof:placetype":"venue"
},
  "geometry": {"coordinates":[2.1786971092,41.3917694092],"type":"Point"}
}