{
  "type": "Feature",
  "properties": {
    "addr:full":"Calle de Arias, 7 Valderas Le\u00f3n 24220",
    "addr:housenumber":"7",
    "addr:postcode":"24220",
    "addr:street":"Calle De Arias",
    "iso:country":"ES",
    "sg:address":"Calle de Arias, 7",
    "sg:city":"Valderas",
    "sg:orig_category":"Iglesia Cat\u00d3lica",
    "sg:phone":"+34 987 76 21 16",
    "sg:postcode":"24220",
    "sg:province":"Le\u00f3n",
    "wof:name":"Parroquia De Valderas",
    "wof:placetype":"venue"
},
  "geometry": {"coordinates":[-5.4568133354,42.0870323181],"type":"Point"}
}