{
  "type": "Feature",
  "properties": {
    "iso:country":"ES",
    "sg:address":"Calle de Fernando Iii El Santo, 10",
    "sg:city":"Parla",
    "sg:orig_category":"M\u00c9dicos: Estomatolog\u00cda",
    "sg:phone":"+34 916 05 28 22",
    "sg:postcode":"28980",
    "sg:province":"Madrid",
    "wof:name":"Martinez Hernandez Maritza",
    "wof:placetype":"venue"
},
  "geometry": {"coordinates":[-3.7679834366,40.2323417664],"type":"Point"}
}