{
  "type": "Feature",
  "properties": {
    "iso:country":"ES",
    "sg:address":"Calle de Ramon Y Cajal, 5",
    "sg:city":"Jaca",
    "sg:orig_category":"Pescader\u00cdas (al Por Menor)",
    "sg:phone":"+34 974 36 22 49",
    "sg:postcode":"22700",
    "sg:province":"Huesca",
    "wof:name":"Pescados Blasco S.cv.",
    "wof:placetype":"venue"
},
  "geometry": {"coordinates":[-0.549274981,42.5688438416],"type":"Point"}
}