{
  "type": "Feature",
  "properties": {
    "iso:country":"ES",
    "sg:address":"Calle de Gonzalo De Mafra, 21",
    "sg:city":"Badajoz",
    "sg:orig_category":"Doctores En Medicina",
    "sg:phone":"+34 924 24 70 77",
    "sg:postcode":"06011",
    "sg:province":"Badajoz",
    "wof:name":"Gonzalez Alvarez Manuel Antonio",
    "wof:placetype":"venue"
},
  "geometry": {"coordinates":[-6.9916853905,38.866268158],"type":"Point"}
}