{
  "type": "Feature",
  "properties": {
    "addr:full":"Psaj Ventura Feliu, 16 Valencia Valencia 46...",
    "addr:housenumber":"16",
    "addr:street":"Feliu;Valencia",
    "iso:country":"ES",
    "sg:address":"Psaj Ventura Feliu, 16",
    "sg:city":"Valencia",
    "sg:orig_category":"Agencias De Viajes",
    "sg:phone":"+34 963 98 27 00",
    "sg:postcode":"46...",
    "sg:province":"Valencia",
    "sg:website":"www.cavaltour.es",
    "wof:name":"Cavaltour Agencia De Viajes S.a.",
    "wof:placetype":"venue"
},
  "geometry": {"coordinates":[-0.3836970031,39.4625282288],"type":"Point"}
}