{
  "type": "Feature",
  "properties": {
    "addr:full":"Calle de Ancha, 1 Valenzuela C\u00f3rdoba 14670",
    "addr:housenumber":"1",
    "addr:postcode":"14670",
    "addr:street":"Calle De Ancha;Co\u0301Rdoba",
    "iso:country":"ES",
    "sg:address":"Calle de Ancha, 1",
    "sg:city":"Valenzuela",
    "sg:orig_category":"C\u00c1maras De Comercio E Industria, Oficios, Agricultura",
    "sg:phone":"+34 957 18 80 04",
    "sg:postcode":"14670",
    "sg:province":"C\u00f3rdoba",
    "wof:name":"Camara Agraria Local De Valenzuela",
    "wof:placetype":"venue"
},
  "geometry": {"coordinates":[-4.2198028564,37.7752075195],"type":"Point"}
}