{
  "type": "Feature",
  "properties": {
    "addr:full":"Carrer de Major, 53 Montblanc Tarragona 43400",
    "addr:housenumber":"53",
    "addr:postcode":"43400",
    "addr:street":"Carrer De Major",
    "iso:country":"ES",
    "sg:address":"Carrer de Major, 53",
    "sg:city":"Montblanc",
    "sg:orig_category":"Ropa Para Se\u00d1oras Y Caballeros (al Por Menor)",
    "sg:phone":"+34 977 86 00 73",
    "sg:postcode":"43400",
    "sg:province":"Tarragona",
    "wof:name":"Borras Vidal Maria Del Carmen",
    "wof:placetype":"venue"
},
  "geometry": {"coordinates":[1.1620110273,41.3766555786],"type":"Point"}
}