{
  "type": "Feature",
  "properties": {
    "iso:country":"ES",
    "sg:address":"Pase Santa Maria De La Cabeza, 167",
    "sg:city":"Madrid",
    "sg:orig_category":"Farmacias",
    "sg:phone":"+34 914 69 11 05",
    "sg:postcode":"28026",
    "sg:province":"Madrid",
    "wof:name":"Galicia Galicia Maria Del Rosario",
    "wof:placetype":"venue"
},
  "geometry": {"coordinates":[-3.7148139477,40.3871536255],"type":"Point"}
}