{
  "type": "Feature",
  "properties": {
    "iso:country":"ES",
    "sg:address":"Avda Lopez Ballesteros, S/n",
    "sg:city":"Vilagarcia",
    "sg:orig_category":"Autob\u00das (explotaci\u00d3n Y Servicios De)",
    "sg:phone":"+34 986 50 12 93",
    "sg:postcode":"36600",
    "sg:province":"Pontevedra",
    "wof:name":"Transportes Jose Nu\u00f1ez Barros S. A.",
    "wof:placetype":"venue"
},
  "geometry": {"coordinates":[-8.7612752914,42.5993690491],"type":"Point"}
}