{
  "type": "Feature",
  "properties": {
    "iso:country":"ES",
    "sg:address":"Crri Molino Del, 12",
    "sg:city":"Malaga",
    "sg:orig_category":"Alimentaci\u00d3n General (al Por Mayor)",
    "sg:phone":"+34 952 43 97 97",
    "sg:postcode":"29190",
    "sg:province":"M\u00e1laga",
    "wof:name":"Almacen De Piensos Pepe Lopez S.l.",
    "wof:placetype":"venue"
},
  "geometry": {"coordinates":[-4.5025129318,36.7206001282],"type":"Point"}
}