{
  "type": "Feature",
  "properties": {
    "addr:full":"Avda Carde\u00d1a (de), S/n Villanueva Cordoba C\u00f3rdoba 14440",
    "addr:postcode":"14440",
    "addr:street":"Avda Carden\u0303A De S / N;Cordoba Co\u0301Rdoba",
    "iso:country":"ES",
    "sg:address":"Avda Carde\u00d1a (de), S/n",
    "sg:city":"Villanueva Cordoba",
    "sg:orig_category":"Empresarios",
    "sg:phone":"+34 957 12 90 21",
    "sg:postcode":"14440",
    "sg:province":"C\u00f3rdoba",
    "wof:name":"Fundacion Red Andalucia Emprende",
    "wof:placetype":"venue"
},
  "geometry": {"coordinates":[-4.6203789711,38.3221359253],"type":"Point"}
}