{
  "type": "Feature",
  "properties": {
    "addr:full":"Avgd Ausias March, 74 Burjassot Valencia 46100",
    "addr:housenumber":"74",
    "addr:postcode":"46100",
    "addr:street":"March",
    "iso:country":"ES",
    "sg:address":"Avgd Ausias March, 74",
    "sg:city":"Burjassot",
    "sg:orig_category":"Librer\u00cdas",
    "sg:phone":"+34 961 53 71 00",
    "sg:postcode":"46100",
    "sg:province":"Valencia",
    "wof:name":"Grasvac S.l.",
    "wof:placetype":"venue"
},
  "geometry": {"coordinates":[-0.4105049968,39.5149154663],"type":"Point"}
}