{
  "type": "Feature",
  "properties": {
    "iso:country":"ES",
    "sg:address":"Calle de Alcalde Gomez Gomez, 54",
    "sg:city":"Malaga",
    "sg:orig_category":"Cer\u00c1mica Art\u00cdstica Y Decorativa",
    "sg:phone":"+34 952 34 14 37",
    "sg:postcode":"29006",
    "sg:province":"M\u00e1laga",
    "sg:website":"www.artenetmalaga.com",
    "wof:name":"Alfajar S.l.",
    "wof:placetype":"venue"
},
  "geometry": {"coordinates":[-4.4809961319,36.7104988098],"type":"Point"}
}