{
  "type": "Feature",
  "properties": {
    "addr:full":"Portela De Puxeiros, 119 Mos Pontevedra 36416",
    "addr:housenumber":"119",
    "addr:postcode":"36416",
    "iso:country":"ES",
    "sg:address":"Portela De Puxeiros, 119",
    "sg:city":"Mos",
    "sg:orig_category":"Tubos Y Tuber\u00cdas De Goma Y Pl\u00c1stico (fabricaci\u00d3n, Al Por Mayor)",
    "sg:phone":"+34 986 48 79 43",
    "sg:postcode":"36416",
    "sg:province":"Pontevedra",
    "wof:name":"Uralita Sistemas De Tuberias",
    "wof:placetype":"venue"
},
  "geometry": {"coordinates":[-8.6403799057,42.1906967163],"type":"Point"}
}