{
  "type": "Feature",
  "properties": {
    "addr:full":"Calle de Nueve De Mayo, 13 Oviedo Asturias 33002",
    "addr:housenumber":"13",
    "addr:postcode":"33002",
    "addr:street":"Calle De Nueve De Mayo",
    "iso:country":"ES",
    "sg:address":"Calle de Nueve De Mayo, 13",
    "sg:city":"Oviedo",
    "sg:orig_category":"Gas: Botellas Y Contenedores",
    "sg:phone":"+34 985 21 43 48",
    "sg:postcode":"33002",
    "sg:province":"Asturias",
    "wof:name":"Gonzalez Garcia Lucia",
    "wof:placetype":"venue"
},
  "geometry": {"coordinates":[-5.850856781,43.3657493591],"type":"Point"}
}