{
  "type": "Feature",
  "properties": {
    "iso:country":"ES",
    "sg:address":"Calle de Jumilla, 8",
    "sg:city":"Tomillares",
    "sg:orig_category":"Inmobiliaria (agencias)",
    "sg:phone":"+34 952 42 67 62",
    "sg:postcode":"29130",
    "sg:province":"M\u00e1laga",
    "wof:name":"Rajunda Malaga S.l.",
    "wof:placetype":"venue"
},
  "geometry": {"coordinates":[-4.5667190552,36.6618614197],"type":"Point"}
}