{
  "type": "Feature",
  "properties": {
    "addr:full":"Calle de Lagunas De Villafafila, 90 Salamanca Salamanca 37008",
    "addr:housenumber":"90",
    "addr:postcode":"37008",
    "addr:street":"Calle De Lagunas De Villafafila",
    "iso:country":"ES",
    "sg:address":"Calle de Lagunas De Villafafila, 90",
    "sg:city":"Salamanca",
    "sg:orig_category":"Ense\u00d1anza: Comercio, Gesti\u00d3n, Inform\u00c1tica",
    "sg:phone":"+34 923 19 41 34",
    "sg:postcode":"37008",
    "sg:province":"Salamanca",
    "wof:name":"Gestores De Proyectos Multimedia",
    "wof:placetype":"venue"
},
  "geometry": {"coordinates":[-5.6648359299,40.935092926],"type":"Point"}
}