{
  "type": "Feature",
  "properties": {
    "iso:country":"ES",
    "sg:address":"Calle de Doctor Bergez, 29",
    "sg:city":"Alacant",
    "sg:orig_category":"Garajes De Veh\u00cdculos",
    "sg:phone":"+34 965 24 20 02",
    "sg:postcode":"03012",
    "sg:province":"Alicante",
    "wof:name":"Diaz-toledo Jaurena Juan Carlos",
    "wof:placetype":"venue"
},
  "geometry": {"coordinates":[-0.4802925885,38.3573799133],"type":"Point"}
}