{
  "type": "Feature",
  "properties": {
    "addr:full":"Calle de Mayor, 37 Lecera Zaragoza 50131",
    "addr:housenumber":"37",
    "addr:postcode":"50131",
    "addr:street":"Calle De Mayor",
    "iso:country":"ES",
    "sg:address":"Calle de Mayor, 37",
    "sg:city":"Lecera",
    "sg:orig_category":"Producci\u00d3n, Venta De Productos De Agricultura Biol\u00d3gica",
    "sg:phone":"+34 976 83 50 31",
    "sg:postcode":"50131",
    "sg:province":"Zaragoza",
    "wof:name":"Perez Argote Cdad",
    "wof:placetype":"venue"
},
  "geometry": {"coordinates":[-0.7088829875,41.2036705017],"type":"Point"}
}