{
  "type": "Feature",
  "properties": {
    "addr:full":"Calle de Primero De Mayo (del), 3 Aranjuez Madrid 28300",
    "addr:postcode":"28300",
    "addr:street":"Calle De Primero",
    "iso:country":"ES",
    "sg:address":"Calle de Primero De Mayo (del), 3",
    "sg:city":"Aranjuez",
    "sg:orig_category":"Herboristas (al Por Menor)",
    "sg:phone":"+34 918 91 02 02",
    "sg:postcode":"28300",
    "sg:province":"Madrid",
    "wof:name":"Naturaranjuez S.l.u.",
    "wof:placetype":"venue"
},
  "geometry": {"coordinates":[-3.5927350521,40.0338745117],"type":"Point"}
}