{
  "type": "Feature",
  "properties": {
    "addr:full":"Calle de Teide, 3 Zaragoza Zaragoza 50012",
    "addr:housenumber":"3",
    "addr:postcode":"50012",
    "addr:street":"Calle De Teide",
    "iso:country":"ES",
    "sg:address":"Calle de Teide, 3",
    "sg:city":"Zaragoza",
    "sg:orig_category":"Promotores Constructores",
    "sg:phone":"+34 976 33 76 27",
    "sg:postcode":"50012",
    "sg:province":"Zaragoza",
    "wof:name":"Comunidad De Propietarios Calle Teide 3",
    "wof:placetype":"venue"
},
  "geometry": {"coordinates":[-0.9296690226,41.6436805725],"type":"Point"}
}