{
  "type": "Feature",
  "properties": {
    "addr:full":"Calle de Mozarabe, 3 Mocejon Toledo 45270",
    "addr:housenumber":"3",
    "addr:postcode":"45270",
    "addr:street":"Calle De Mozarabe",
    "iso:country":"ES",
    "sg:address":"Calle de Mozarabe, 3",
    "sg:city":"Mocejon",
    "sg:orig_category":"Contenedores (mercanc\u00cdas)",
    "sg:phone":"+34 925 36 06 68",
    "sg:postcode":"45270",
    "sg:province":"Toledo",
    "wof:name":"Perez Ruano Angel",
    "wof:placetype":"venue"
},
  "geometry": {"coordinates":[-3.915651083,39.939781189],"type":"Point"}
}