{
  "type": "Feature",
  "properties": {
    "addr:full":"Carrer de L'abat Odo, 63 Barcelona Barcelona 08030",
    "addr:housenumber":"63",
    "addr:postcode":"08030",
    "addr:street":"Carrer De L'Abat Odo",
    "iso:country":"ES",
    "sg:address":"Carrer de L'abat Odo, 63",
    "sg:city":"Barcelona",
    "sg:orig_category":"Grafistas",
    "sg:phone":"+34 932 74 53 29",
    "sg:postcode":"08030",
    "sg:province":"Barcelona",
    "wof:name":"Lac Estudio S.l",
    "wof:placetype":"venue"
},
  "geometry": {"coordinates":[2.1864600182,41.4323997498],"type":"Point"}
}