{
  "type": "Feature",
  "properties": {
    "addr:full":"Gernika Ibilbidea, 9 Usurbil Guip\u00f9zcoa 20170",
    "addr:housenumber":"9",
    "addr:postcode":"20170",
    "addr:street":"Gernika Ibilbidea;Guipu\u0300Zcoa",
    "iso:country":"ES",
    "sg:address":"Gernika Ibilbidea, 9",
    "sg:city":"Usurbil",
    "sg:orig_category":"Equipo Y Material Deportivo Y De Actividades Invernales Y De Monta\u00d1a",
    "sg:phone":"+34 943 36 57 48",
    "sg:postcode":"20170",
    "sg:province":"Guip\u00f9zcoa",
    "wof:name":"Usurbilgo Udal Kirol Patronatua",
    "wof:placetype":"venue"
},
  "geometry": {"coordinates":[-2.0501010418,43.2719612122],"type":"Point"}
}