{
  "type": "Feature",
  "properties": {
    "iso:country":"ES",
    "sg:address":"Carr Ramon Llull, 19",
    "sg:city":"Deya",
    "sg:orig_category":"Albergues",
    "sg:phone":"+34 971 63 90 37",
    "sg:postcode":"07179",
    "sg:province":"Islas Baleares",
    "wof:name":"Colom Bibiloni Antonio Miguel",
    "wof:placetype":"venue"
},
  "geometry": {"coordinates":[2.6499259472,39.7486763],"type":"Point"}
}