{
  "type": "Feature",
  "properties": {
    "addr:full":"Avda Andalucia, 31 Palmones C\u00e1diz 11379",
    "addr:housenumber":"31",
    "addr:postcode":"11379",
    "addr:street":"Avda Andalucia;Ca\u0301Diz",
    "iso:country":"ES",
    "sg:address":"Avda Andalucia, 31",
    "sg:city":"Palmones",
    "sg:orig_category":"Cajas De Ahorro",
    "sg:phone":"+34 956 67 57 34",
    "sg:postcode":"11379",
    "sg:province":"C\u00e1diz",
    "wof:name":"Unicaja",
    "wof:placetype":"venue"
},
  "geometry": {"coordinates":[-5.4382691383,36.1758804321],"type":"Point"}
}