{
  "type": "Feature",
  "properties": {
    "addr:full":"Plaz Abad Penalva, 1 Alacant Alicante 03002",
    "addr:housenumber":"1",
    "addr:postcode":"03002",
    "addr:street":"Penalva",
    "iso:country":"ES",
    "sg:address":"Plaz Abad Penalva, 1",
    "sg:city":"Alacant",
    "sg:orig_category":"M\u00c9dicos: Otorrinolaringolog\u00cda",
    "sg:phone":"+34 965 20 28 77",
    "sg:postcode":"03002",
    "sg:province":"Alicante",
    "wof:name":"Lopez Rico Juan Jose",
    "wof:placetype":"venue"
},
  "geometry": {"coordinates":[-0.4829019904,38.3453826904],"type":"Point"}
}