{
  "type": "Feature",
  "properties": {
    "iso:country":"ES",
    "sg:address":"A Chainza(obre), S/n",
    "sg:city":"Chainza",
    "sg:orig_category":"Ferreter\u00cda (diversos)",
    "sg:phone":"+34 981 82 02 57",
    "sg:postcode":"15200",
    "sg:province":"La Coru\u00f1a",
    "wof:name":"Avelino Suarez E Hijos S.l.",
    "wof:placetype":"venue"
},
  "geometry": {"coordinates":[-8.8883037567,42.788608551],"type":"Point"}
}