{
  "type": "Feature",
  "properties": {
    "addr:full":"Calle de Pe\u00d1a Y Go\u00d1i, 2 Donostia-san Sebastian Guip\u00f9zcoa 20002",
    "addr:housenumber":"2",
    "addr:postcode":"20002",
    "addr:street":"Calle De Pen\u0303A Y Gon\u0303I",
    "iso:country":"ES",
    "sg:address":"Calle de Pe\u00d1a Y Go\u00d1i, 2",
    "sg:city":"Donostia-san Sebastian",
    "sg:orig_category":"Abogados",
    "sg:phone":"+34 943 27 89 77",
    "sg:postcode":"20002",
    "sg:province":"Guip\u00f9zcoa",
    "wof:name":"Emparanza Sobejano Lourdes",
    "wof:placetype":"venue"
},
  "geometry": {"coordinates":[-1.9783060551,43.3238868713],"type":"Point"}
}