{
  "type": "Feature",
  "properties": {
    "iso:country":"ES",
    "sg:address":"Calle de Juan De Castilla, 9",
    "sg:city":"Palencia",
    "sg:orig_category":"Perfumer\u00cda (al Por Menor)",
    "sg:phone":"+34 979 74 30 24",
    "sg:postcode":"34001",
    "sg:province":"Palencia",
    "wof:name":"Saez Lloren Alicia",
    "wof:placetype":"venue"
},
  "geometry": {"coordinates":[-4.5355591774,42.0113487244],"type":"Point"}
}