{
  "type": "Feature",
  "properties": {
    "addr:full":"Avda Campoamor, S/n Tahiche Las Palmas 35509",
    "addr:housenumber":"s / n",
    "addr:postcode":"35509",
    "addr:street":"Avda Campoamor",
    "iso:country":"ES",
    "sg:address":"Avda Campoamor, S/n",
    "sg:city":"Tahiche",
    "sg:orig_category":"Distribuci\u00d3n De Petr\u00d3leo Y Derivados",
    "sg:phone":"+34 928 80 58 96",
    "sg:postcode":"35509",
    "sg:province":"Las Palmas",
    "wof:name":"Estaciones De Servicio De Lanzarote",
    "wof:placetype":"venue"
},
  "geometry": {"coordinates":[-13.545583725,29.0103359222],"type":"Point"}
}