{
  "type": "Feature",
  "properties": {
    "iso:country":"ES",
    "sg:address":"Calle de Parroquia, 11",
    "sg:city":"Doneztebe",
    "sg:orig_category":"Lencer\u00cda Femenina, Corseter\u00cda, Trajes De Ba\u00d1o (al Por Menor)",
    "sg:phone":"+34 948 45 01 12",
    "sg:postcode":"31740",
    "sg:province":"Navarra",
    "wof:name":"Arregui Apeztegui Maria Cruz",
    "wof:placetype":"venue"
},
  "geometry": {"coordinates":[-1.6701724529,43.1317138672],"type":"Point"}
}