{
  "type": "Feature",
  "properties": {
    "addr:full":"Carrer de Bernat Metge, 27 Gava Barcelona 08850",
    "addr:housenumber":"27",
    "addr:postcode":"08850",
    "addr:street":"Carrer De Bernat Metge",
    "iso:country":"ES",
    "sg:address":"Carrer de Bernat Metge, 27",
    "sg:city":"Gava",
    "sg:orig_category":"Muebles, Minoristas",
    "sg:phone":"+34 936 62 29 43",
    "sg:postcode":"08850",
    "sg:province":"Barcelona",
    "wof:name":"Hernandez Salmeron Francisco",
    "wof:placetype":"venue"
},
  "geometry": {"coordinates":[1.9975240231,41.3024864197],"type":"Point"}
}