{
  "type": "Feature",
  "properties": {
    "addr:full":"Calle de Torres Miranda, 26 Madrid Madrid 28045",
    "addr:housenumber":"26",
    "addr:postcode":"madrid;28045",
    "addr:street":"Calle De Torres Miranda",
    "iso:country":"ES",
    "sg:address":"Calle de Torres Miranda, 26",
    "sg:city":"Madrid",
    "sg:orig_category":"Lavado, Limpieza De Veh\u00cdculos",
    "sg:phone":"+34 914 73 85 20",
    "sg:postcode":"28045",
    "sg:province":"Madrid",
    "wof:name":"Farrera Calero Antonio",
    "wof:placetype":"venue"
},
  "geometry": {"coordinates":[-3.7012040615,40.3983612061],"type":"Point"}
}