{
  "type": "Feature",
  "properties": {
    "iso:country":"ES",
    "sg:address":"Rua Da Cruz, 4",
    "sg:city":"Verin",
    "sg:orig_category":"Alquiler De V\u00cddeo",
    "sg:phone":"+34 988 41 25 33",
    "sg:postcode":"32600",
    "sg:province":"Ourense",
    "wof:name":"Ares Rodriguez Ramon",
    "wof:placetype":"venue"
},
  "geometry": {"coordinates":[-7.4373846054,41.941608429],"type":"Point"}
}