{
  "type": "Feature",
  "properties": {
    "iso:country":"ES",
    "sg:address":"Calle de Concepcion Arenal, 37",
    "sg:city":"Miranda Ebro",
    "sg:orig_category":"Inform\u00c1tica (estudios, Servicios, Asesor\u00cda, Formaci\u00d3n)",
    "sg:phone":"+34 947 33 58 57",
    "sg:postcode":"09200",
    "sg:province":"Burgos",
    "wof:name":"Garcia Cibrian Informatica S.l.",
    "wof:placetype":"venue"
},
  "geometry": {"coordinates":[-2.9400682449,42.6868972778],"type":"Point"}
}