{
  "type": "Feature",
  "properties": {
    "iso:country":"ES",
    "sg:address":"Trav Mtro Casanova, S/n",
    "sg:city":"Torrevieja",
    "sg:orig_category":"Electrodom\u00c9sticos (al Por Menor)",
    "sg:phone":"+34 965 71 23 29",
    "sg:postcode":"03180",
    "sg:province":"Alicante",
    "wof:name":"Sanchez Esparcia Jose",
    "wof:placetype":"venue"
},
  "geometry": {"coordinates":[-0.6536790133,38.0173606873],"type":"Point"}
}