{
  "type": "Feature",
  "properties": {
    "addr:full":"Calle de Casimiro Escudero, 11 Madrid Madrid 28025",
    "addr:housenumber":"11",
    "addr:postcode":"madrid;28025",
    "addr:street":"Calle De Casimiro Escudero",
    "iso:country":"ES",
    "sg:address":"Calle de Casimiro Escudero, 11",
    "sg:city":"Madrid",
    "sg:orig_category":"Muebles, Minoristas",
    "sg:phone":"+34 914 65 25 16",
    "sg:postcode":"28025",
    "sg:province":"Madrid",
    "wof:name":"Mi Hogar Decoracion Y Dise\u00f1o S.l.",
    "wof:placetype":"venue"
},
  "geometry": {"coordinates":[-3.7432489395,40.3897323608],"type":"Point"}
}