{
  "type": "Feature",
  "properties": {
    "addr:full":"Calle de San Gregorio, 34 Azagra Navarra 31560",
    "addr:housenumber":"34",
    "addr:postcode":"31560",
    "addr:street":"Calle De San Gregorio",
    "iso:country":"ES",
    "sg:address":"Calle de San Gregorio, 34",
    "sg:city":"Azagra",
    "sg:orig_category":"Mec\u00c1nico Del Autom\u00d3vil",
    "sg:phone":"+34 948 69 29 46",
    "sg:postcode":"31560",
    "sg:province":"Navarra",
    "wof:name":"Talleres Esran S.l.l.",
    "wof:placetype":"venue"
},
  "geometry": {"coordinates":[-1.8980139494,42.3146514893],"type":"Point"}
}