{
  "type": "Feature",
  "properties": {
    "addr:full":"Calle de Prevision, 1 Sevilla Sevilla 41008",
    "addr:housenumber":"1",
    "addr:postcode":"41008",
    "addr:street":"Calle De Prevision",
    "iso:country":"ES",
    "sg:address":"Calle de Prevision, 1",
    "sg:city":"Sevilla",
    "sg:orig_category":"Molduras, Junquillos, Listones Y Molduras Perforadas",
    "sg:phone":"+34 954 36 02 10",
    "sg:postcode":"41008",
    "sg:province":"Sevilla",
    "wof:name":"Pacheco Ba\u00f1egil Manuela",
    "wof:placetype":"venue"
},
  "geometry": {"coordinates":[-5.9786667824,37.4020271301],"type":"Point"}
}