{
  "type": "Feature",
  "properties": {
    "addr:full":"Avda Ricardo Carapeto Zambrano, 132 Badajoz Badajoz 06008",
    "addr:housenumber":"132",
    "addr:postcode":"06008",
    "addr:street":"Avda Ricardo Carapeto Zambrano",
    "iso:country":"ES",
    "sg:address":"Avda Ricardo Carapeto Zambrano, 132",
    "sg:city":"Badajoz",
    "sg:orig_category":"Agentes, Concesionarios Y Sucursales De Veh\u00cdculos",
    "sg:phone":"+34 924 25 76 29",
    "sg:postcode":"06008",
    "sg:province":"Badajoz",
    "wof:name":"Dumar Motor S.l.",
    "wof:placetype":"venue"
},
  "geometry": {"coordinates":[-6.9473338127,38.8786468506],"type":"Point"}
}