{
  "type": "Feature",
  "properties": {
    "iso:country":"ES",
    "sg:address":"Calle de Santa Isabel, 6",
    "sg:city":"Cordoba",
    "sg:orig_category":"Tapicer\u00cdas",
    "sg:phone":"+34 957 47 73 87",
    "sg:postcode":"14001",
    "sg:province":"C\u00f3rdoba",
    "wof:name":"Recio Melgarejo Rafael",
    "wof:placetype":"venue"
},
  "geometry": {"coordinates":[-4.7745800018,37.8890266418],"type":"Point"}
}