{
  "type": "Feature",
  "properties": {
    "addr:full":"Vilanovi\u00f1a, 20 Meis Pontevedra 36616",
    "addr:housenumber":"20",
    "addr:postcode":"36616",
    "addr:street":"Vilanovin\u0303A",
    "iso:country":"ES",
    "sg:address":"Vilanovi\u00f1a, 20",
    "sg:city":"Meis",
    "sg:orig_category":"Alimentaci\u00d3n General (al Por Mayor)",
    "sg:phone":"+34 986 71 55 94",
    "sg:postcode":"36616",
    "sg:province":"Pontevedra",
    "wof:name":"Agricola Cullereiro S.l.",
    "wof:placetype":"venue"
},
  "geometry": {"coordinates":[-8.6913290024,42.5137329102],"type":"Point"}
}