{
  "type": "Feature",
  "properties": {
    "iso:country":"ES",
    "sg:address":"Calle de Juan De Vera, 6",
    "sg:city":"San Cristobal De La Laguna",
    "sg:orig_category":"Concepci\u00d3n Y Realizaci\u00d3n De Maquetas Profesionales Y Prototipos",
    "sg:phone":"+34 922 63 40 16",
    "sg:postcode":"38201",
    "sg:province":"Santa Cruz De Tenerife",
    "wof:name":"Pacar De Nivaria S.l.",
    "wof:placetype":"venue"
},
  "geometry": {"coordinates":[-16.3163757324,28.489648819],"type":"Point"}
}