{
  "type": "Feature",
  "properties": {
    "iso:country":"ES",
    "sg:address":"Paseo De La Bahia (cc Bahia Sur), S/n",
    "sg:city":"S. Fernando",
    "sg:orig_category":"Fabricaci\u00d3n De Su\u00c9ters Y Chalecos De Punto",
    "sg:phone":"+34 956 88 32 70",
    "sg:postcode":"11100",
    "sg:province":"C\u00e1diz",
    "sg:website":"www.trece.com",
    "wof:name":"Famastor S. L.",
    "wof:placetype":"venue"
},
  "geometry": {"coordinates":[-6.1967391968,36.4654541016],"type":"Point"}
}