{
  "type": "Feature",
  "properties": {
    "addr:full":"Avda Romero Donallo (de), S/n Santiago De Compostela La Coru\u00f1a 15706",
    "addr:postcode":"15706",
    "addr:street":"Avda Romero Donallo De S / N;Corun\u0303A",
    "iso:country":"ES",
    "sg:address":"Avda Romero Donallo (de), S/n",
    "sg:city":"Santiago De Compostela",
    "sg:orig_category":"Pescader\u00cdas (al Por Menor)",
    "sg:phone":"+34 981 59 31 96",
    "sg:postcode":"15706",
    "sg:province":"La Coru\u00f1a",
    "wof:name":"Pescados Oliveira S.l.",
    "wof:placetype":"venue"
},
  "geometry": {"coordinates":[-8.5489864349,42.8700752258],"type":"Point"}
}