{
  "type": "Feature",
  "properties": {
    "iso:country":"ES",
    "sg:address":"Ctra. Ca\u00f1ete Torres, 3",
    "sg:city":"Baena",
    "sg:orig_category":"Aceites Y Grasas Alimentarias (fabricaci\u00d3n, Al Por Mayor)",
    "sg:phone":"+34 957 67 11 84",
    "sg:postcode":"14850",
    "sg:province":"C\u00f3rdoba",
    "wof:name":"Canoexport S.l.",
    "wof:placetype":"venue"
},
  "geometry": {"coordinates":[-4.323964119,37.6170043945],"type":"Point"}
}