{
  "type": "Feature",
  "properties": {
    "iso:country":"ES",
    "sg:address":"Trva Pintor Pareja, 1",
    "sg:city":"Socovos",
    "sg:orig_category":"Farmacias",
    "sg:phone":"+34 967 42 00 13",
    "sg:postcode":"02435",
    "sg:province":"Albacete",
    "wof:name":"Farmacia Socovos C.b.",
    "wof:placetype":"venue"
},
  "geometry": {"coordinates":[-1.9850360155,38.3315925598],"type":"Point"}
}