{
  "type": "Feature",
  "properties": {
    "addr:full":"Calle de Rafael De Riego, 5 Madrid Madrid 28045",
    "addr:housenumber":"5",
    "addr:postcode":"28045",
    "addr:street":"Calle De Rafael De Riego",
    "iso:country":"ES",
    "sg:address":"Calle de Rafael De Riego, 5",
    "sg:city":"Madrid",
    "sg:orig_category":"Televisi\u00d3n, V\u00cddeo: Aparatos Y Accesorios (venta)",
    "sg:phone":"+34 914 67 16 28",
    "sg:postcode":"28045",
    "sg:province":"Madrid",
    "sg:website":"www.grupoifg.com",
    "wof:name":"Film Corporation 2000 S.a.",
    "wof:placetype":"venue"
},
  "geometry": {"coordinates":[-3.6918959618,40.4047889709],"type":"Point"}
}