{
  "type": "Feature",
  "properties": {
    "iso:country":"ES",
    "sg:address":"Calle de Moreto, 8",
    "sg:city":"Madrid",
    "sg:orig_category":"Art\u00cdculos De Decoraci\u00d3n",
    "sg:phone":"+34 914 20 34 60",
    "sg:postcode":"28014",
    "sg:province":"Madrid",
    "wof:name":"Grupo Octogono S. A.",
    "wof:placetype":"venue"
},
  "geometry": {"coordinates":[-3.6905319691,40.4135665894],"type":"Point"}
}