{
  "type": "Feature",
  "properties": {
    "addr:full":"Calle de Juan Xxiii (de), 4 Parla Madrid 28980",
    "addr:postcode":"28980",
    "addr:street":"Calle De Juan Xxiii De 4",
    "iso:country":"ES",
    "sg:address":"Calle de Juan Xxiii (de), 4",
    "sg:city":"Parla",
    "sg:classifiers":[
        {
            "category":"Personal",
            "subcategory":"Barber",
            "type":"Services"
        }
    ],
    "sg:phone":"+34 916 05 37 22",
    "sg:postcode":"28980",
    "sg:province":"Madrid",
    "sg:tags":[
        "caballeros",
        "de",
        "peluqueros"
    ],
    "sg:website":"www.concecta.es/rizos",
    "wof:name":"Cezon Caminos Jesus Manuel",
    "wof:placetype":"venue"
},
  "geometry": {"coordinates":[-3.7631568909,40.2401504517],"type":"Point"}
}