{
  "type": "Feature",
  "properties": {
    "iso:country":"ES",
    "sg:address":"Plaz Emilio Diez De Revenga, 3",
    "sg:city":"San Miguel",
    "sg:orig_category":"Negocio De Materiales De Construcci\u00d3n",
    "sg:phone":"+34 968 23 47 09",
    "sg:postcode":"30008",
    "sg:province":"Murcia",
    "wof:name":"Distribuciones Y Materiales S. A.",
    "wof:placetype":"venue"
},
  "geometry": {"coordinates":[-1.135841012,37.9912147522],"type":"Point"}
}