{
  "type": "Feature",
  "properties": {
    "addr:full":"Calle de Virgen Desamparados, 33 Mislata Valencia 46920",
    "addr:housenumber":"33",
    "addr:postcode":"46920",
    "addr:street":"Calle De Virgen Desamparados",
    "iso:country":"ES",
    "sg:address":"Calle de Virgen Desamparados, 33",
    "sg:city":"Mislata",
    "sg:orig_category":"Agencias Y Agentes Comerciales, Representantes",
    "sg:phone":"+34 963 83 52 23",
    "sg:postcode":"46920",
    "sg:province":"Valencia",
    "wof:name":"Perez Ribero Antonio Miguel",
    "wof:placetype":"venue"
},
  "geometry": {"coordinates":[-0.4169259965,39.4775238037],"type":"Point"}
}