{
  "type": "Feature",
  "properties": {
    "iso:country":"ES",
    "sg:address":"Calle de Berriobide, 33",
    "sg:city":"Ansoain",
    "sg:orig_category":"Rectificaci\u00d3n, Mecanizado, Fresado",
    "sg:phone":"+34 948 13 27 91",
    "sg:postcode":"31013",
    "sg:province":"Navarra",
    "wof:name":"Mecanizados Echavarri S.l.",
    "wof:placetype":"venue"
},
  "geometry": {"coordinates":[-1.6463404894,42.8337860107],"type":"Point"}
}