{
  "type": "Feature",
  "properties": {
    "iso:country":"ES",
    "sg:address":"Calle de Fernan Perez De Oliva, 26",
    "sg:city":"Albacete",
    "sg:orig_category":"Electricidad Veh\u00cdculo",
    "sg:phone":"+34 967 21 85 05",
    "sg:postcode":"02005",
    "sg:province":"Albacete",
    "wof:name":"Reypecar C.b",
    "wof:placetype":"venue"
},
  "geometry": {"coordinates":[-1.8614840508,39.0028152466],"type":"Point"}
}