{
  "type": "Feature",
  "properties": {
    "addr:full":"Calle de Cortijo, 7 Yebenes Toledo 45470",
    "addr:housenumber":"7",
    "addr:postcode":"45470",
    "addr:street":"Calle De Cortijo",
    "iso:country":"ES",
    "sg:address":"Calle de Cortijo, 7",
    "sg:city":"Yebenes",
    "sg:orig_category":"Agricultores, Agricultores",
    "sg:phone":"+34 925 32 00 94",
    "sg:postcode":"45470",
    "sg:province":"Toledo",
    "wof:name":"Sat Hermanos Pineda Moraleda.",
    "wof:placetype":"venue"
},
  "geometry": {"coordinates":[-3.8726289272,39.580291748],"type":"Point"}
}