{
  "type": "Feature",
  "properties": {
    "iso:country":"ES",
    "sg:address":"Calle de Iquitos, 59",
    "sg:city":"Madrid",
    "sg:orig_category":"Inform\u00c1tica (estudios, Servicios, Asesor\u00cda, Formaci\u00d3n)",
    "sg:phone":"+34 917 28 06 26",
    "sg:postcode":"28027",
    "sg:province":"Madrid",
    "sg:website":"www.newcomlab.com",
    "wof:name":"Newcomlab L.l.",
    "wof:placetype":"venue"
},
  "geometry": {"coordinates":[-3.631000042,40.4413452148],"type":"Point"}
}