{
  "type": "Feature",
  "properties": {
    "addr:full":"Villanueva, S/n Villanueva Asturias 33559",
    "addr:housenumber":"s",
    "addr:postcode":"33559",
    "addr:street":"Villanueva;/ N",
    "iso:country":"ES",
    "sg:address":"Villanueva, S/n",
    "sg:city":"Villanueva",
    "sg:orig_category":"Empresarios",
    "sg:phone":"+34 985 84 88 31",
    "sg:postcode":"33559",
    "sg:province":"Asturias",
    "wof:name":"Vega Laruelo Jose Luis",
    "wof:placetype":"venue"
},
  "geometry": {"coordinates":[-5.8496661186,43.4044342041],"type":"Point"}
}