{
  "type": "Feature",
  "properties": {
    "iso:country":"ES",
    "sg:address":"Calle de Ricardo Leon, 5",
    "sg:city":"Fuengirola",
    "sg:orig_category":"Fabricaci\u00d3n, Importaci\u00d3n, Venta De Material De Telefon\u00cda, Peritelefon\u00cda",
    "sg:phone":"+34 952 19 93 29",
    "sg:postcode":"29640",
    "sg:province":"M\u00e1laga",
    "wof:name":"Interspace Movil 1 S.l.",
    "wof:placetype":"venue"
},
  "geometry": {"coordinates":[-4.6059660912,36.5628623962],"type":"Point"}
}