{
  "type": "Feature",
  "properties": {
    "addr:full":"Plaz Sauces (los), 11 Bara\u00f1ain Navarra 31010",
    "addr:postcode":"31010",
    "addr:street":"Plaz;Los;Baran\u0303Ain Navarra",
    "iso:country":"ES",
    "sg:address":"Plaz Sauces (los), 11",
    "sg:city":"Bara\u00f1ain",
    "sg:orig_category":"Alimentaci\u00d3n General (al Por Menor)",
    "sg:phone":"+34 948 25 02 82",
    "sg:postcode":"31010",
    "sg:province":"Navarra",
    "wof:name":"Impala 2000 S.l.",
    "wof:placetype":"venue"
},
  "geometry": {"coordinates":[-97.78224945069999,45.7040786743],"type":"Point"}
}