{
  "type": "Feature",
  "properties": {
    "addr:full":"Calle de Santa Cruz De Ardoi Kalea, 41 Zizur Mayor Navarra 31180",
    "addr:housenumber":"41",
    "addr:postcode":"31180",
    "addr:street":"Calle De Santa Cruz De Ardoi Kalea",
    "iso:country":"ES",
    "sg:address":"Calle de Santa Cruz De Ardoi Kalea, 41",
    "sg:city":"Zizur Mayor",
    "sg:orig_category":"Panader\u00cdas, Panader\u00cdas",
    "sg:phone":"+34 948 18 28 98",
    "sg:postcode":"31180",
    "sg:province":"Navarra",
    "wof:name":"Moreno Cortes Maria Dolores",
    "wof:placetype":"venue"
},
  "geometry": {"coordinates":[-1.6927540302,42.7928657532],"type":"Point"}
}