{
  "type": "Feature",
  "properties": {
    "addr:full":"Carr Tigre, 14 Vilanova I La Geltru Barcelona 08800",
    "addr:housenumber":"14",
    "addr:postcode":"08800",
    "addr:street":"Carr Tigre",
    "iso:country":"ES",
    "sg:address":"Carr Tigre, 14",
    "sg:city":"Vilanova I La Geltru",
    "sg:orig_category":"Frutas Y Legumbres Frescas (al Por Mayor)",
    "sg:phone":"+34 938 93 29 96",
    "sg:postcode":"08800",
    "sg:province":"Barcelona",
    "wof:name":"Rodrigo Porras Niceto",
    "wof:placetype":"venue"
},
  "geometry": {"coordinates":[1.7299280167,41.2262077332],"type":"Point"}
}