{
  "type": "Feature",
  "properties": {
    "addr:full":"Calle de Tormes, 24 Jerez De La Frontera C\u00e1diz 11406",
    "addr:housenumber":"24",
    "addr:postcode":"11406",
    "addr:street":"Calle De Tormes",
    "iso:country":"ES",
    "sg:address":"Calle de Tormes, 24",
    "sg:city":"Jerez De La Frontera",
    "sg:orig_category":"Garajes De Veh\u00cdculos",
    "sg:phone":"+34 956 33 66 32",
    "sg:postcode":"11406",
    "sg:province":"C\u00e1diz",
    "wof:name":"Nieto Menacho Martin",
    "wof:placetype":"venue"
},
  "geometry": {"coordinates":[-6.1003661156,36.6891746521],"type":"Point"}
}