{
  "type": "Feature",
  "properties": {
    "iso:country":"ES",
    "sg:address":"Carretera De Villasarracino, S/n",
    "sg:city":"Arenillas S. Pelayo",
    "sg:orig_category":"Transportes Por V\u00cdas Navegables",
    "sg:phone":"+34 979 89 51 83",
    "sg:postcode":"34474",
    "sg:province":"Palencia",
    "wof:name":"Doncel Montes Rogelio",
    "wof:placetype":"venue"
},
  "geometry": {"coordinates":[-4.5392599106,42.0104293823],"type":"Point"}
}