{
  "type": "Feature",
  "properties": {
    "iso:country":"ES",
    "sg:address":"Calle de Belen, 35",
    "sg:city":"Palma Rio",
    "sg:orig_category":"Peluqueros: De Se\u00d1oras",
    "sg:phone":"+34 957 64 66 73",
    "sg:postcode":"14700",
    "sg:province":"C\u00f3rdoba",
    "wof:name":"Mu\u00f1oz Gomez Juan Carlos",
    "wof:placetype":"venue"
},
  "geometry": {"coordinates":[-5.2794914246,37.6963157654],"type":"Point"}
}