{
  "type": "Feature",
  "properties": {
    "iso:country":"ES",
    "sg:address":"Pol P. Hincada, 6",
    "sg:city":"Alcala Guadaira",
    "sg:orig_category":"Barnizadores",
    "sg:phone":"+34 955 61 07 27",
    "sg:postcode":"41500",
    "sg:province":"Sevilla",
    "wof:name":"Mecu Ebanisteria S.l.",
    "wof:placetype":"venue"
},
  "geometry": {"coordinates":[-5.8398590088,37.3383140564],"type":"Point"}
}