{
  "type": "Feature",
  "properties": {
    "iso:country":"ES",
    "sg:address":"Calle de Colon, 22",
    "sg:city":"Castellon",
    "sg:orig_category":"Telas Y Sedas (al Por Menor)",
    "sg:phone":"+34 964 22 44 70",
    "sg:postcode":"12001",
    "sg:province":"Castell\u00f3n",
    "wof:name":"Guia Vidal Jose",
    "wof:placetype":"venue"
},
  "geometry": {"coordinates":[-0.0375867002,39.986530304],"type":"Point"}
}