{
  "type": "Feature",
  "properties": {
    "iso:country":"ES",
    "sg:address":"Calle de Marques De Comillas, 7",
    "sg:city":"Benidorm",
    "sg:orig_category":"Fabricaci\u00d3n De Art\u00cdculos Para Papeler\u00cdas",
    "sg:phone":"+34 966 88 94 12",
    "sg:postcode":"03500",
    "sg:province":"Alicante",
    "sg:website":"www.carlin.es",
    "wof:name":"Ofiaimon Sl",
    "wof:placetype":"venue"
},
  "geometry": {"coordinates":[-0.1330859959,38.5375518799],"type":"Point"}
}