{
  "type": "Feature",
  "properties": {
    "iso:country":"ES",
    "sg:address":"Calle de Juan Valera, 12",
    "sg:city":"Oviedo",
    "sg:orig_category":"Empresas De Portes Y Mensajer\u00cda",
    "sg:phone":"+34 985 11 02 05",
    "sg:postcode":"33012",
    "sg:province":"Asturias",
    "wof:name":"Zelast Logistica S.l.",
    "wof:placetype":"venue"
},
  "geometry": {"coordinates":[-5.8644018173,43.3745346069],"type":"Point"}
}