{
  "type": "Feature",
  "properties": {
    "addr:full":"Carrer de Deu I Mata, 6 Barcelona Barcelona 08014",
    "addr:housenumber":"6",
    "addr:postcode":"08014",
    "addr:street":"Carrer De Deu I Mata",
    "iso:country":"ES",
    "sg:address":"Carrer de Deu I Mata, 6",
    "sg:city":"Barcelona",
    "sg:orig_category":"Restaurantes",
    "sg:phone":"+34 934 30 33 44",
    "sg:postcode":"08014",
    "sg:province":"Barcelona",
    "wof:name":"Ali Aura Sl",
    "wof:placetype":"venue"
},
  "geometry": {"coordinates":[2.1314263344,41.3860473633],"type":"Point"}
}