{
  "type": "Feature",
  "properties": {
    "iso:country":"ES",
    "sg:address":"Calle de Corazon De Maria, 53",
    "sg:city":"Madrid",
    "sg:orig_category":"Electrodom\u00c9sticos (al Por Menor)",
    "sg:phone":"+34 914 15 33 50",
    "sg:postcode":"28002",
    "sg:province":"Madrid",
    "wof:name":"Menaje Del Hogar-reparacion Electrodomesticos S.l.",
    "wof:placetype":"venue"
},
  "geometry": {"coordinates":[-3.6667230129,40.4468002319],"type":"Point"}
}