{
  "type": "Feature",
  "properties": {
    "addr:full":"Calle de Jose Maria Ligues, 11 Cintruenigo Navarra 31592",
    "addr:housenumber":"11",
    "addr:postcode":"31592",
    "addr:street":"Calle De Jose Maria Ligues",
    "iso:country":"ES",
    "sg:address":"Calle de Jose Maria Ligues, 11",
    "sg:city":"Cintruenigo",
    "sg:orig_category":"Peluqueros: De Se\u00d1oras",
    "sg:phone":"+34 948 81 13 54",
    "sg:postcode":"31592",
    "sg:province":"Navarra",
    "wof:name":"Gil Fernandez Resurreccion",
    "wof:placetype":"venue"
},
  "geometry": {"coordinates":[-1.8062570095,42.0814094543],"type":"Point"}
}