{
  "type": "Feature",
  "properties": {
    "addr:full":"Plaz Mayor, S/n Castellon Castell\u00f3n 12001",
    "addr:housenumber":"s / n",
    "addr:postcode":"12001",
    "addr:street":"Plaz Mayor",
    "iso:country":"ES",
    "sg:address":"Plaz Mayor, S/n",
    "sg:city":"Castellon",
    "sg:orig_category":"Iglesia Cat\u00d3lica",
    "sg:phone":"+34 964 22 34 63",
    "sg:postcode":"12001",
    "sg:province":"Castell\u00f3n",
    "wof:name":"Parroquia De Santa Maria",
    "wof:placetype":"venue"
},
  "geometry": {"coordinates":[-0.0390199982,39.9866409302],"type":"Point"}
}