{
  "type": "Feature",
  "properties": {
    "iso:country":"ES",
    "sg:address":"Carrer de Terra Alta, 84",
    "sg:city":"Poligono Industrial Can Carner",
    "sg:orig_category":"Calefacci\u00d3n Central: Material (fabricaci\u00d3n, Al Por Mayor)",
    "sg:phone":"+34 937 14 46 84",
    "sg:postcode":"08211",
    "sg:province":"Barcelona",
    "wof:name":"Serra Calor S.l.",
    "wof:placetype":"venue"
},
  "geometry": {"coordinates":[2.0857300758,41.6151885986],"type":"Point"}
}