{
  "type": "Feature",
  "properties": {
    "iso:country":"ES",
    "sg:address":"Carrer de Galileu, 93",
    "sg:city":"Barcelona",
    "sg:orig_category":"Juegos Y Juguetes (al Por Menor)",
    "sg:phone":"+34 933 39 15 94",
    "sg:postcode":"08028",
    "sg:province":"Barcelona",
    "wof:name":"Vidal Mestres Jorge",
    "wof:placetype":"venue"
},
  "geometry": {"coordinates":[2.1347079277,41.3783035278],"type":"Point"}
}