{
  "type": "Feature",
  "properties": {
    "addr:full":"Rua Calvario, 17 Noia La Coru\u00f1a 15200",
    "addr:housenumber":"17",
    "addr:postcode":"15200",
    "addr:street":"Rua Calvario;La Corun\u0303A",
    "iso:country":"ES",
    "sg:address":"Rua Calvario, 17",
    "sg:city":"Noia",
    "sg:orig_category":"Asociaciones, Organismos Culturales Y Socioeducativos",
    "sg:phone":"+34 981 82 58 26",
    "sg:postcode":"15200",
    "sg:province":"La Coru\u00f1a",
    "wof:name":"Bretema Ocio E Tempo Libre S.l.",
    "wof:placetype":"venue"
},
  "geometry": {"coordinates":[-8.8886260986,42.7876167297],"type":"Point"}
}