{
  "type": "Feature",
  "properties": {
    "addr:full":"Carrer de Aribau, 245 Barcelona Barcelona 08021",
    "addr:housenumber":"245",
    "addr:postcode":"08021",
    "addr:street":"Carrer De Aribau",
    "iso:country":"ES",
    "sg:address":"Carrer de Aribau, 245",
    "sg:city":"Barcelona",
    "sg:orig_category":"Agencias Y Agentes Comerciales, Representantes",
    "sg:phone":"+34 934 14 58 87",
    "sg:postcode":"08021",
    "sg:province":"Barcelona",
    "wof:name":"Cellmark Iberica S.l.",
    "wof:placetype":"venue"
},
  "geometry": {"coordinates":[2.1467978954,41.3981666565],"type":"Point"}
}