{
  "type": "Feature",
  "properties": {
    "addr:full":"Calle de Lorenzo Abru\u00d1edo, 18 Oviedo Asturias 33012",
    "addr:housenumber":"18",
    "addr:postcode":"33012",
    "addr:street":"Calle De Lorenzo Abrun\u0303Edo",
    "iso:country":"ES",
    "sg:address":"Calle de Lorenzo Abru\u00d1edo, 18",
    "sg:city":"Oviedo",
    "sg:orig_category":"Garajes De Veh\u00cdculos",
    "sg:phone":"+34 985 11 91 61",
    "sg:postcode":"33012",
    "sg:province":"Asturias",
    "wof:name":"Distribucion Astur De Productos Exclusivos S.l.",
    "wof:placetype":"venue"
},
  "geometry": {"coordinates":[-5.8553638458,43.3699569702],"type":"Point"}
}