{
  "type": "Feature",
  "properties": {
    "addr:full":"Avda Salvador Allende, 1 Zaragoza Zaragoza 50015",
    "addr:housenumber":"1",
    "addr:postcode":"50015",
    "addr:street":"Avda Salvador Allende",
    "iso:country":"ES",
    "sg:address":"Avda Salvador Allende, 1",
    "sg:city":"Zaragoza",
    "sg:orig_category":"Agencias Y Agentes Comerciales, Representantes",
    "sg:phone":"+34 976 52 74 25",
    "sg:postcode":"50015",
    "sg:province":"Zaragoza",
    "wof:name":"Sobresueldos S.a.",
    "wof:placetype":"venue"
},
  "geometry": {"coordinates":[-0.877022028,41.6671257019],"type":"Point"}
}