{
  "type": "Feature",
  "properties": {
    "iso:country":"ES",
    "sg:address":"Pase Teruel, 15",
    "sg:city":"Zaragoza",
    "sg:orig_category":"Poller\u00cda Y Caza (al Por Menor)",
    "sg:phone":"+34 976 21 30 17",
    "sg:postcode":"50004",
    "sg:province":"Zaragoza",
    "wof:name":"Vendrell Salvador Ramon",
    "wof:placetype":"venue"
},
  "geometry": {"coordinates":[-0.8907589912,41.6485481262],"type":"Point"}
}