{
  "type": "Feature",
  "properties": {
    "addr:full":"Avda Aguirre Lehendakari, 131 Bilbao Vizcaya 48015",
    "addr:housenumber":"131",
    "addr:postcode":"48015",
    "addr:street":"Avda Aguirre Lehendakari",
    "iso:country":"ES",
    "sg:address":"Avda Aguirre Lehendakari, 131",
    "sg:city":"Bilbao",
    "sg:orig_category":"Ropa Para Se\u00d1oras (al Por Menor)",
    "sg:phone":"+34 944 75 48 07",
    "sg:postcode":"48015",
    "sg:province":"Vizcaya",
    "wof:name":"Narro Saiz Maria Angeles",
    "wof:placetype":"venue"
},
  "geometry": {"coordinates":[-2.9594860077,43.2752723694],"type":"Point"}
}