{
  "type": "Feature",
  "properties": {
    "iso:country":"ES",
    "sg:address":"Calle de Victoriano Perez De La Riva, S/n",
    "sg:city":"Comillas",
    "sg:orig_category":"Producci\u00d3n, Distribuci\u00d3n De Electricidad",
    "sg:phone":"+34 942 72 00 94",
    "sg:postcode":"39520",
    "sg:province":"Cantabria",
    "sg:website":"www.electricidadcesar.com",
    "wof:name":"Garcia Lavin Cesar",
    "wof:placetype":"venue"
},
  "geometry": {"coordinates":[-4.2900362015,43.3862724304],"type":"Point"}
}