{
  "type": "Feature",
  "properties": {
    "iso:country":"ES",
    "sg:address":"Calle de Martinez De La Rosa, 130",
    "sg:city":"Malaga",
    "sg:orig_category":"Caf\u00c9s, Bares, Cervecer\u00cdas",
    "sg:phone":"+34 952 30 89 83",
    "sg:postcode":"29010",
    "sg:province":"M\u00e1laga",
    "wof:name":"Diaz Gomez Jose",
    "wof:placetype":"venue"
},
  "geometry": {"coordinates":[-4.4443101883,36.7284736633],"type":"Point"}
}