{
  "type": "Feature",
  "properties": {
    "iso:country":"ES",
    "sg:address":"Calle de Joaquin Costa, 31",
    "sg:city":"Palmas De Gran Canaria",
    "sg:orig_category":"Ingenier\u00cda, Centros De Estudios (diversos)",
    "sg:phone":"+34 928 26 70 29",
    "sg:postcode":"35007",
    "sg:province":"Las Palmas",
    "wof:name":"Garcia Sosa Cesar",
    "wof:placetype":"venue"
},
  "geometry": {"coordinates":[-15.4339427948,28.1377601624],"type":"Point"}
}