{
  "type": "Feature",
  "properties": {
    "iso:country":"ES",
    "sg:address":"Calle de Villamartin, S/n",
    "sg:city":"Arahal",
    "sg:orig_category":"Empresas De Electricidad En General",
    "sg:phone":"+34 954 84 02 59",
    "sg:postcode":"41600",
    "sg:province":"Sevilla",
    "wof:name":"Endesa Servicios S.l. Sociedad Unipersonal",
    "wof:placetype":"venue"
},
  "geometry": {"coordinates":[-5.5461940765,37.2693901062],"type":"Point"}
}