{
  "type": "Feature",
  "properties": {
    "iso:country":"ES",
    "sg:address":"Calle de Dalmacio Garcia Izcara, 4",
    "sg:city":"Cuenca",
    "sg:orig_category":"Lanas (al Por Mayor)",
    "sg:phone":"+34 969 22 09 22",
    "sg:postcode":"16004",
    "sg:province":"Cuenca",
    "wof:name":"Lucas Vallejo Maria Del Carmen",
    "wof:placetype":"venue"
},
  "geometry": {"coordinates":[-2.1365485191,40.0688705444],"type":"Point"}
}