{
  "type": "Feature",
  "properties": {
    "iso:country":"ES",
    "sg:address":"Carr Sant Anastasi, 40",
    "sg:city":"Badalona",
    "sg:orig_category":"Ropa Para Se\u00d1oras (al Por Menor)",
    "sg:phone":"+34 933 84 57 15",
    "sg:postcode":"08911",
    "sg:province":"Barcelona",
    "wof:name":"Bueno Yudes Encarnacion",
    "wof:placetype":"venue"
},
  "geometry": {"coordinates":[2.2468090057,41.4509239197],"type":"Point"}
}