{
  "type": "Feature",
  "properties": {
    "addr:full":"Agrupacion Santo Tome, Km. 0001,2 Agrup Sto Tome Ja\u00e9n 23311",
    "addr:postcode":"23311",
    "addr:street":"Santo Tome Km. 0001,2 Agrup Sto Tome Jae\u0301N",
    "iso:country":"ES",
    "sg:address":"Agrupacion Santo Tome, Km. 0001,2",
    "sg:city":"Agrup Sto Tome",
    "sg:orig_category":"Producci\u00d3n, Venta De Productos De Agricultura Biol\u00d3gica",
    "sg:phone":"+34 953 73 64 15",
    "sg:postcode":"23311",
    "sg:province":"Ja\u00e9n",
    "sg:website":"www.aceitenet.com",
    "wof:name":"Explotacion Ba\u00f1on S.a.",
    "wof:placetype":"venue"
},
  "geometry": {"coordinates":[-3.1006410122,38.0286064148],"type":"Point"}
}