{
  "type": "Feature",
  "properties": {
    "addr:full":"Carrer de Finlandia, 15 Barcelona Barcelona 08014",
    "addr:housenumber":"15",
    "addr:postcode":"08014",
    "addr:street":"Carrer De Finlandia",
    "iso:country":"ES",
    "sg:address":"Carrer de Finlandia, 15",
    "sg:city":"Barcelona",
    "sg:orig_category":"Peluquer\u00cdas, Peluquer\u00cda Mixta",
    "sg:phone":"+34 934 31 02 90",
    "sg:postcode":"08014",
    "sg:province":"Barcelona",
    "wof:name":"Fusio Inedita 15 S.l.",
    "wof:placetype":"venue"
},
  "geometry": {"coordinates":[2.1355168819,41.3737182617],"type":"Point"}
}