{
  "type": "Feature",
  "properties": {
    "addr:full":"Carr Baro De Maials, 18 Lleida Lleida 25005",
    "addr:housenumber":"18",
    "addr:postcode":"25005",
    "addr:street":"Carr Baro De Maials",
    "iso:country":"ES",
    "sg:address":"Carr Baro De Maials, 18",
    "sg:city":"Lleida",
    "sg:orig_category":"Pintores",
    "sg:phone":"+34 973 24 16 38",
    "sg:postcode":"25005",
    "sg:province":"Lleida",
    "wof:name":"Fontanet Aixut Maria Soledad",
    "wof:placetype":"venue"
},
  "geometry": {"coordinates":[0.6362349987,41.622089386],"type":"Point"}
}