{
  "type": "Feature",
  "properties": {
    "addr:full":"Carrer de Mercuri (del), 188 Floresta Tarragona 43006",
    "addr:housenumber":"188",
    "addr:postcode":"43006",
    "addr:street":"Carrer De Mercuri Del",
    "iso:country":"ES",
    "sg:address":"Carrer de Mercuri (del), 188",
    "sg:city":"Floresta",
    "sg:orig_category":"Reparaciones Y Remolcado De Veh\u00cdculos",
    "sg:phone":"+34 977 54 88 80",
    "sg:postcode":"43006",
    "sg:province":"Tarragona",
    "wof:name":"Gruas David Tarragona S.a.",
    "wof:placetype":"venue"
},
  "geometry": {"coordinates":[1.2209249735,41.1154441833],"type":"Point"}
}