{
  "type": "Feature",
  "properties": {
    "iso:country":"ES",
    "sg:address":"Avda Juan Carlos I, 10",
    "sg:city":"Mazarron",
    "sg:orig_category":"Promotores Constructores",
    "sg:phone":"+34 968 59 01 87",
    "sg:postcode":"30870",
    "sg:province":"Murcia",
    "wof:name":"Lorente Garcia Miguel",
    "wof:placetype":"venue"
},
  "geometry": {"coordinates":[-1.3112419844,37.6011276245],"type":"Point"}
}