{
  "type": "Feature",
  "properties": {
    "iso:country":"ES",
    "sg:address":"Calle de Jose Mendez, 11",
    "sg:city":"Poligono Industrial Los Villares",
    "sg:orig_category":"Panader\u00cdas, Panader\u00cdas",
    "sg:phone":"+34 923 23 35 48",
    "sg:postcode":"37184",
    "sg:province":"Salamanca",
    "wof:name":"Marjesto S.l.",
    "wof:placetype":"venue"
},
  "geometry": {"coordinates":[-5.6448731422,40.9875640869],"type":"Point"}
}