{
  "type": "Feature",
  "properties": {
    "addr:full":"Avda Tierra Llana, Km. 0120,0 Vilalba Lugo 27800",
    "addr:postcode":"27800",
    "addr:street":"Avda Tierra Llana Km. 0120,0",
    "iso:country":"ES",
    "sg:address":"Avda Tierra Llana, Km. 0120,0",
    "sg:city":"Vilalba",
    "sg:orig_category":"Venta, Montaje De Neum\u00c1ticos",
    "sg:phone":"+34 982 51 28 34",
    "sg:postcode":"27800",
    "sg:province":"Lugo",
    "wof:name":"Camba Lozano Servando",
    "wof:placetype":"venue"
},
  "geometry": {"coordinates":[-7.6737589836,43.2951507568],"type":"Point"}
}