{
  "type": "Feature",
  "properties": {
    "addr:full":"Avda Estacion, 42 Azuaga Badajoz 06920",
    "addr:housenumber":"42",
    "addr:postcode":"06920",
    "addr:street":"Avda Estacion",
    "iso:country":"ES",
    "sg:address":"Avda Estacion, 42",
    "sg:city":"Azuaga",
    "sg:orig_category":"Mec\u00c1nico Del Autom\u00d3vil",
    "sg:phone":"+34 924 89 07 82",
    "sg:postcode":"06920",
    "sg:province":"Badajoz",
    "wof:name":"Talleres Victoriano Ramirez S.l.",
    "wof:placetype":"venue"
},
  "geometry": {"coordinates":[-5.6781702042,38.2620201111],"type":"Point"}
}