{
  "type": "Feature",
  "properties": {
    "iso:country":"ES",
    "sg:address":"Avda Italia, 41",
    "sg:city":"Salamanca",
    "sg:orig_category":"Bancos",
    "sg:phone":"+34 923 24 66 01",
    "sg:postcode":"37007",
    "sg:province":"Salamanca",
    "wof:name":"Bt Espa\u00d1a Compa\u00d1ia De Servicios Globales De Telecomunicaciones S.a.u.",
    "wof:placetype":"venue"
},
  "geometry": {"coordinates":[-5.6667718887,40.9716377258],"type":"Point"}
}