{
  "type": "Feature",
  "properties": {
    "iso:country":"ES",
    "sg:address":"Calle de Caceres, 18",
    "sg:city":"Madrid",
    "sg:orig_category":"Colchones (fabricaci\u00d3n, Al Por Mayor, Al Por Menor)",
    "sg:phone":"+34 914 67 50 77",
    "sg:postcode":"28045",
    "sg:province":"Madrid",
    "wof:name":"Exclusivas Del Confort S.l.",
    "wof:placetype":"venue"
},
  "geometry": {"coordinates":[-3.6964931488,40.3986854553],"type":"Point"}
}