{
  "type": "Feature",
  "properties": {
    "addr:full":"Carrer de Antiga Carretera Barcelona, S/n Amposta Tarragona 43870",
    "addr:housenumber":"/ n",
    "addr:postcode":"43870",
    "addr:street":"Carrer De Antiga Carretera Barcelona S",
    "iso:country":"ES",
    "sg:address":"Carrer de Antiga Carretera Barcelona, S/n",
    "sg:city":"Amposta",
    "sg:orig_category":"Goma: Productos De Uso Industrial (fabricaci\u00d3n, Al Por Mayor)",
    "sg:phone":"+34 977 70 53 84",
    "sg:postcode":"43870",
    "sg:province":"Tarragona",
    "wof:name":"Benito Beltri Amadeo",
    "wof:placetype":"venue"
},
  "geometry": {"coordinates":[0.5804650187,40.6995582581],"type":"Point"}
}