{
  "type": "Feature",
  "properties": {
    "addr:full":"Electricidad, S/n Leganes Madrid 28918",
    "addr:housenumber":"/ n",
    "addr:postcode":"28918",
    "addr:street":"S",
    "iso:country":"ES",
    "sg:address":"Electricidad, S/n",
    "sg:city":"Leganes",
    "sg:orig_category":"Chapister\u00cda",
    "sg:phone":"+34 916 11 64 85",
    "sg:postcode":"28918",
    "sg:province":"Madrid",
    "wof:name":"Yague Jimeno Segundo",
    "wof:placetype":"venue"
},
  "geometry": {"coordinates":[-3.7998874187,40.3502998352],"type":"Point"}
}