{
  "type": "Feature",
  "properties": {
    "iso:country":"ES",
    "sg:address":"Calle de Correria, 38",
    "sg:city":"Balmaseda",
    "sg:orig_category":"Empresas De Pintura Y Revestimientos",
    "sg:phone":"+34 946 80 04 34",
    "sg:postcode":"48800",
    "sg:province":"Vizcaya",
    "wof:name":"Cantero Fernandez Jose Angel",
    "wof:placetype":"venue"
},
  "geometry": {"coordinates":[-3.1947336197,43.1945991516],"type":"Point"}
}