{
  "type": "Feature",
  "properties": {
    "iso:country":"ES",
    "sg:address":"Calle de Primautzar, 40",
    "sg:city":"Irun",
    "sg:orig_category":"Poli\u00c9ster",
    "sg:phone":"+34 943 62 64 63",
    "sg:postcode":"20305",
    "sg:province":"Guip\u00f9zcoa",
    "wof:name":"Zalacain Caba\u00f1as Cesareo",
    "wof:placetype":"venue"
},
  "geometry": {"coordinates":[-1.8259400129,43.3267478943],"type":"Point"}
}