{
  "type": "Feature",
  "properties": {
    "addr:full":"Calle de Donoso Cortes, 64 Madrid Madrid 28015",
    "addr:housenumber":"64",
    "addr:postcode":"madrid;28015",
    "addr:street":"Calle De Donoso Cortes",
    "iso:country":"ES",
    "sg:address":"Calle de Donoso Cortes, 64",
    "sg:city":"Madrid",
    "sg:orig_category":"Bisuter\u00cda De Fantas\u00cda (al Por Menor)",
    "sg:phone":"+34 915 44 21 47",
    "sg:postcode":"28015",
    "sg:province":"Madrid",
    "wof:name":"Groas Carmelo Maria Del Mar",
    "wof:placetype":"venue"
},
  "geometry": {"coordinates":[-3.7127666473,40.4364051819],"type":"Point"}
}