{
  "type": "Feature",
  "properties": {
    "addr:full":"Ctra Tomares, 1 San J. Aznalfarache Sevilla 41920",
    "addr:housenumber":"1",
    "addr:postcode":"41920",
    "addr:street":"Ctra Tomares",
    "iso:country":"ES",
    "sg:address":"Ctra Tomares, 1",
    "sg:city":"San J. Aznalfarache",
    "sg:orig_category":"Transportes Por Carretera: Lotes Completos, Mercanc\u00cdas Diversas",
    "sg:phone":"+34 954 76 66 02",
    "sg:postcode":"41920",
    "sg:province":"Sevilla",
    "wof:name":"Productos Alimenticios Belros S.a.",
    "wof:placetype":"venue"
},
  "geometry": {"coordinates":[-6.0296092033,37.3624992371],"type":"Point"}
}