{
  "type": "Feature",
  "properties": {
    "addr:full":"Rbla Doctor Pearson, 29 Tremp Lleida 25620",
    "addr:housenumber":"29",
    "addr:postcode":"25620",
    "addr:street":"Rbla Doctor Pearson",
    "iso:country":"ES",
    "sg:address":"Rbla Doctor Pearson, 29",
    "sg:city":"Tremp",
    "sg:orig_category":"Abogados",
    "sg:phone":"+34 973 65 27 07",
    "sg:postcode":"25620",
    "sg:province":"Lleida",
    "wof:name":"Llimi\u00f1ana Montanuy Maria Luisa",
    "wof:placetype":"venue"
},
  "geometry": {"coordinates":[0.8942869902,42.1644744873],"type":"Point"}
}