{
  "type": "Feature",
  "properties": {
    "iso:country":"ES",
    "sg:address":"Ctra Algezares(bo Progreso), 26",
    "sg:city":"Murcia",
    "sg:orig_category":"Molduras, Junquillos, Listones Y Molduras Perforadas",
    "sg:phone":"+34 968 34 22 48",
    "sg:postcode":"30012",
    "sg:province":"Murcia",
    "wof:name":"Andreu Lopez Juan Jose",
    "wof:placetype":"venue"
},
  "geometry": {"coordinates":[-1.1421569586,37.9413452148],"type":"Point"}
}