{
  "type": "Feature",
  "properties": {
    "addr:full":"Plaz Virgen De La Salud, S/n Posadas C\u00f3rdoba 14730",
    "addr:housenumber":"co\u0301rdoba",
    "addr:postcode":"14730",
    "addr:street":"Plaz Virgen De La Salud S / N",
    "iso:country":"ES",
    "sg:address":"Plaz Virgen De La Salud, S/n",
    "sg:city":"Posadas",
    "sg:orig_category":"Molduras, Junquillos, Listones Y Molduras Perforadas",
    "sg:phone":"+34 957 63 21 84",
    "sg:postcode":"14730",
    "sg:province":"C\u00f3rdoba",
    "wof:name":"Santiago Ramos Rafael",
    "wof:placetype":"venue"
},
  "geometry": {"coordinates":[-97.78224945069999,45.7040786743],"type":"Point"}
}