{
  "type": "Feature",
  "properties": {
    "addr:full":"Calle de Extremadura, 24 Valle Serena Badajoz 06458",
    "addr:housenumber":"24",
    "addr:postcode":"06458",
    "addr:street":"Calle De Extremadura;Serena",
    "iso:country":"ES",
    "sg:address":"Calle de Extremadura, 24",
    "sg:city":"Valle Serena",
    "sg:orig_category":"Bares, Piano",
    "sg:phone":"+34 924 77 80 62",
    "sg:postcode":"06458",
    "sg:province":"Badajoz",
    "wof:name":"Cabezas Barquero Antonio",
    "wof:placetype":"venue"
},
  "geometry": {"coordinates":[-5.7996997833,38.7005805969],"type":"Point"}
}