{
  "type": "Feature",
  "properties": {
    "addr:full":"Avda Molinos (de Los), 7 Cordoba C\u00f3rdoba 14001",
    "addr:housenumber":"7",
    "addr:postcode":"14001",
    "addr:street":"Avda Molinos De Los;Co\u0301Rdoba",
    "iso:country":"ES",
    "sg:address":"Avda Molinos (de Los), 7",
    "sg:city":"Cordoba",
    "sg:orig_category":"Abogados",
    "sg:phone":"+34 957 49 15 25",
    "sg:postcode":"14001",
    "sg:province":"C\u00f3rdoba",
    "wof:name":"Alcaide Aranda Rafael",
    "wof:placetype":"venue"
},
  "geometry": {"coordinates":[-4.7792840004,37.8917961121],"type":"Point"}
}