{
  "type": "Feature",
  "properties": {
    "iso:country":"ES",
    "sg:address":"Pg Pla\u00c7a Major, 70",
    "sg:city":"Sabadell",
    "sg:orig_category":"Inform\u00c1tica: Material Y Suministros",
    "sg:phone":"+34 937 26 05 44",
    "sg:postcode":"08202",
    "sg:province":"Barcelona",
    "wof:name":"Articulos De Oficina Y Papeleria S.a.",
    "wof:placetype":"venue"
},
  "geometry": {"coordinates":[2.1087350845,41.5481758118],"type":"Point"}
}