{
  "type": "Feature",
  "properties": {
    "iso:country":"ES",
    "sg:address":"Calle de Olof Palme, 43",
    "sg:city":"Palmas De Gran Canaria",
    "sg:orig_category":"Cl\u00cdnicas Dentales",
    "sg:phone":"+34 928 26 34 78",
    "sg:postcode":"35010",
    "sg:province":"Las Palmas",
    "wof:name":"Clinica Dental Sanchez Vi\u00f1uela S.l.",
    "wof:placetype":"venue"
},
  "geometry": {"coordinates":[-15.4354867935,28.1334705353],"type":"Point"}
}