{
  "type": "Feature",
  "properties": {
    "iso:country":"ES",
    "sg:address":"Plaz Voluntarios, S/n",
    "sg:city":"Pe\u00f1afiel",
    "sg:orig_category":"M\u00c9dicos: Estomatolog\u00cda",
    "sg:phone":"+34 983 88 11 80",
    "sg:postcode":"47300",
    "sg:province":"Valladolid",
    "wof:name":"Reyes Montero Juan Jose",
    "wof:placetype":"venue"
},
  "geometry": {"coordinates":[-4.1203889847,41.5947990417],"type":"Point"}
}