{
  "type": "Feature",
  "properties": {
    "iso:country":"ES",
    "sg:address":"Pg Maritim, 107",
    "sg:city":"Vilanova I La Geltru",
    "sg:orig_category":"Contenedores (mercanc\u00cdas)",
    "sg:phone":"+34 938 15 71 11",
    "sg:postcode":"08800",
    "sg:province":"Barcelona",
    "wof:name":"Arrastres Portuarios De Vilanova S.l.",
    "wof:placetype":"venue"
},
  "geometry": {"coordinates":[1.7310554981,41.2159309387],"type":"Point"}
}