{
  "type": "Feature",
  "properties": {
    "iso:country":"ES",
    "sg:address":"Avda Constitucion, 33",
    "sg:city":"Cenes Vega",
    "sg:orig_category":"Agencias Y Agentes Comerciales, Representantes",
    "sg:phone":"+34 958 48 63 63",
    "sg:postcode":"18190",
    "sg:province":"Granada",
    "wof:name":"Rodriguez Alarcon Veronica",
    "wof:placetype":"venue"
},
  "geometry": {"coordinates":[-3.5355250835,37.1599807739],"type":"Point"}
}