{
  "type": "Feature",
  "properties": {
    "iso:country":"ES",
    "sg:address":"Calle de Pinos, 21",
    "sg:city":"Gijon",
    "sg:orig_category":"Promotores Constructores",
    "sg:phone":"+34 985 31 75 28",
    "sg:postcode":"33211",
    "sg:province":"Asturias",
    "wof:name":"Desarrollos Integrales Trema\u00f1es 2000 S.l.",
    "wof:placetype":"venue"
},
  "geometry": {"coordinates":[-5.6957092285,43.5318336487],"type":"Point"}
}