{
  "type": "Feature",
  "properties": {
    "addr:full":"C/ Juan Orts Roman, 6 Elche Alicante 03201",
    "addr:housenumber":"6",
    "addr:postcode":"03201",
    "addr:street":"C / Juan Orts Roman",
    "iso:country":"ES",
    "sg:address":"C/ Juan Orts Roman, 6",
    "sg:city":"Elche",
    "sg:orig_category":"Cueros Y Pieles (al Por Mayor)",
    "sg:phone":"+34 965 44 84 62",
    "sg:postcode":"03201",
    "sg:province":"Alicante",
    "wof:name":"Plasancur S.l.",
    "wof:placetype":"venue"
},
  "geometry": {"coordinates":[-0.7034850121,38.2637481689],"type":"Point"}
}