{
  "type": "Feature",
  "properties": {
    "iso:country":"ES",
    "sg:address":"Carr Cervantes, 20",
    "sg:city":"Moncada",
    "sg:orig_category":"Molduras, Junquillos, Listones Y Molduras Perforadas",
    "sg:phone":"+34 961 39 17 23",
    "sg:postcode":"46113",
    "sg:province":"Valencia",
    "wof:name":"Tamarit Company Manuel",
    "wof:placetype":"venue"
},
  "geometry": {"coordinates":[-0.3989579976,39.5449485779],"type":"Point"}
}