{
  "type": "Feature",
  "properties": {
    "iso:country":"ES",
    "sg:address":"C/ Antonio Machado, 13",
    "sg:city":"Elche",
    "sg:orig_category":"Abogados",
    "sg:phone":"+34 966 66 10 85",
    "sg:postcode":"03204",
    "sg:province":"Alicante",
    "wof:name":"Perez Garcia Cristina",
    "wof:placetype":"venue"
},
  "geometry": {"coordinates":[-0.7041890025,38.2625656128],"type":"Point"}
}