{
  "type": "Feature",
  "properties": {
    "addr:full":"Carrer de Binefar, 27 Barcelona Barcelona 08020",
    "addr:housenumber":"27",
    "addr:postcode":"08020",
    "addr:street":"Carrer De Binefar",
    "iso:country":"ES",
    "sg:address":"Carrer de Binefar, 27",
    "sg:city":"Barcelona",
    "sg:orig_category":"Mec\u00c1nico Del Autom\u00d3vil",
    "sg:phone":"+34 932 78 80 88",
    "sg:postcode":"08020",
    "sg:province":"Barcelona",
    "wof:name":"Mateo Torrents Josep",
    "wof:placetype":"venue"
},
  "geometry": {"coordinates":[2.2050299644,41.4261703491],"type":"Point"}
}