{
  "type": "Feature",
  "properties": {
    "iso:country":"ES",
    "sg:address":"Calle de Sedavi (de), 25",
    "sg:city":"Alaquas",
    "sg:orig_category":"Carnes De Carnicer\u00cda (al Por Mayor)",
    "sg:phone":"+34 961 32 20 75",
    "sg:postcode":"46970",
    "sg:province":"Valencia",
    "sg:website":"www.sucar.com",
    "wof:name":"Sucarn S. A.",
    "wof:placetype":"venue"
},
  "geometry": {"coordinates":[-0.4617154002,39.4507064819],"type":"Point"}
}