{
  "type": "Feature",
  "properties": {
    "iso:country":"ES",
    "sg:address":"Avda Generalisimo, S/n",
    "sg:city":"Mi\u00f1o",
    "sg:orig_category":"Art\u00cdculos Funerarios (al Por Menor)",
    "sg:phone":"+34 981 78 31 77",
    "sg:postcode":"15630",
    "sg:province":"La Coru\u00f1a",
    "wof:name":"Lorenzo Garcia Andres",
    "wof:placetype":"venue"
},
  "geometry": {"coordinates":[-8.2014837265,43.3393096924],"type":"Point"}
}