{
  "type": "Feature",
  "properties": {
    "addr:full":"Calle de Txiki Otaegi, 24 Amorebieta Vizcaya 48340",
    "addr:housenumber":"24",
    "addr:postcode":"48340",
    "addr:street":"Calle De Txiki Otaegi",
    "iso:country":"ES",
    "sg:address":"Calle de Txiki Otaegi, 24",
    "sg:city":"Amorebieta",
    "sg:orig_category":"Frutas, Legumbres Frescas Y Tempranas (al Por Menor)",
    "sg:phone":"+34 946 30 80 77",
    "sg:postcode":"48340",
    "sg:province":"Vizcaya",
    "wof:name":"Otxandategi Induarrizaga Miren Itziar",
    "wof:placetype":"venue"
},
  "geometry": {"coordinates":[-2.7369580269,43.2203598022],"type":"Point"}
}