{
  "type": "Feature",
  "properties": {
    "addr:full":"Calle de Joaquin Chapaprieta, 44 Torrevieja Alicante 03180",
    "addr:housenumber":"44",
    "addr:postcode":"03180",
    "addr:street":"Calle De Joaquin Chapaprieta",
    "iso:country":"ES",
    "sg:address":"Calle de Joaquin Chapaprieta, 44",
    "sg:city":"Torrevieja",
    "sg:orig_category":"Institutos De Belleza",
    "sg:phone":"+34 965 70 85 67",
    "sg:postcode":"03180",
    "sg:province":"Alicante",
    "wof:name":"Ca\u00f1ete Mures Silvia",
    "wof:placetype":"venue"
},
  "geometry": {"coordinates":[-0.6810610294,37.978679657],"type":"Point"}
}