{
  "type": "Feature",
  "properties": {
    "iso:country":"ES",
    "sg:address":"Calle de Trafalgar, 10",
    "sg:city":"Algeciras",
    "sg:orig_category":"Bazares, Art\u00cdculos De Limpieza Y De Cocina (al Por Menor)",
    "sg:phone":"+34 956 66 72 77",
    "sg:postcode":"11201",
    "sg:province":"C\u00e1diz",
    "wof:name":"Cao  Yizhong",
    "wof:placetype":"venue"
},
  "geometry": {"coordinates":[-5.4474191666,36.132068634],"type":"Point"}
}