{
  "type": "Feature",
  "properties": {
    "iso:country":"ES",
    "sg:address":"Calle de Ascension Del Se\u00d1or, 21",
    "sg:city":"S. Asensio",
    "sg:orig_category":"Ropa De Trabajo Y Profesionales (fabricaci\u00d3n, Al Por Mayor)",
    "sg:phone":"+34 941 45 71 01",
    "sg:postcode":"26340",
    "sg:province":"La Rioja",
    "wof:name":"Del Campo Avalos Estela",
    "wof:placetype":"venue"
},
  "geometry": {"coordinates":[-2.7475543022,42.5007476807],"type":"Point"}
}