{
  "type": "Feature",
  "properties": {
    "addr:full":"Ctra Huesca, S/n Sari\u00f1ena Huesca 22200",
    "addr:housenumber":"s / n",
    "addr:postcode":"22200",
    "addr:street":"Ctra Huesca",
    "iso:country":"ES",
    "sg:address":"Ctra Huesca, S/n",
    "sg:city":"Sari\u00f1ena",
    "sg:orig_category":"Comercio, Reparaci\u00d3n De Motocicletas, Bicicletas Y Piezas Sueltas",
    "sg:phone":"+34 974 57 12 15",
    "sg:postcode":"22200",
    "sg:province":"Huesca",
    "wof:name":"Charrymotor S.coop.",
    "wof:placetype":"venue"
},
  "geometry": {"coordinates":[-0.158118993,41.7977485657],"type":"Point"}
}