{
  "type": "Feature",
  "properties": {
    "addr:full":"Calle de Andalucia, 32 Melilla Melilla 52006",
    "addr:housenumber":"32",
    "addr:postcode":"52006",
    "addr:street":"Calle De Andalucia",
    "iso:country":"ES",
    "sg:address":"Calle de Andalucia, 32",
    "sg:city":"Melilla",
    "sg:orig_category":"Empresas De Limpieza",
    "sg:phone":"+34 952 69 65 65",
    "sg:postcode":"52006",
    "sg:province":"Melilla",
    "wof:name":"Eulen S.a.",
    "wof:placetype":"venue"
},
  "geometry": {"coordinates":[-2.9459891319,35.273639679],"type":"Point"}
}