{
  "type": "Feature",
  "properties": {
    "addr:full":"Kale Nagusia, 92 Azkoitia Guip\u00f9zcoa 20720",
    "addr:housenumber":"92",
    "addr:postcode":"20720",
    "addr:street":"Kale Nagusia;Guipu\u0300Zcoa",
    "iso:country":"ES",
    "sg:address":"Kale Nagusia, 92",
    "sg:city":"Azkoitia",
    "sg:orig_category":"Caf\u00c9s, Bares, Cervecer\u00cdas",
    "sg:phone":"+34 943 85 11 96",
    "sg:postcode":"20720",
    "sg:province":"Guip\u00f9zcoa",
    "wof:name":"Aizpuru Urdalleta Luis Y Otros C.b.",
    "wof:placetype":"venue"
},
  "geometry": {"coordinates":[-2.3112244606,43.1784286499],"type":"Point"}
}