{
  "type": "Feature",
  "properties": {
    "iso:country":"ES",
    "sg:address":"Calle de Julian Ceballos, 20",
    "sg:city":"Torrelavega",
    "sg:orig_category":"Inmobiliaria (agencias)",
    "sg:phone":"+34 942 88 13 31",
    "sg:postcode":"39300",
    "sg:province":"Cantabria",
    "wof:name":"Barrio Gomez Santiago",
    "wof:placetype":"venue"
},
  "geometry": {"coordinates":[-4.0489940643,43.3485832214],"type":"Point"}
}