{
  "type": "Feature",
  "properties": {
    "addr:full":"Calle de Bailen, 1 Malaga M\u00e1laga 29009",
    "addr:housenumber":"1",
    "addr:postcode":"29009",
    "addr:street":"Calle De Bailen;Ma\u0301Laga",
    "iso:country":"ES",
    "sg:address":"Calle de Bailen, 1",
    "sg:city":"Malaga",
    "sg:orig_category":"Art\u00cdculos De Decoraci\u00d3n",
    "sg:phone":"+34 952 28 04 43",
    "sg:postcode":"29009",
    "sg:province":"M\u00e1laga",
    "wof:name":"Guerrero Postigo Estrella",
    "wof:placetype":"venue"
},
  "geometry": {"coordinates":[-4.432082653,36.7241630554],"type":"Point"}
}