{
  "type": "Feature",
  "properties": {
    "iso:country":"ES",
    "sg:address":"Carrer de Pep Ventura, 13",
    "sg:city":"Martorell",
    "sg:orig_category":"Sociedades, Compa\u00d1\u00cdas Aseguradoras",
    "sg:phone":"+34 937 75 10 78",
    "sg:postcode":"08760",
    "sg:province":"Barcelona",
    "wof:name":"Cep Correduria De Seguros S A",
    "wof:placetype":"venue"
},
  "geometry": {"coordinates":[1.9169950485,41.4792327881],"type":"Point"}
}