{
  "type": "Feature",
  "properties": {
    "iso:country":"ES",
    "sg:address":"Ptge Gira Sol, 4",
    "sg:city":"Barcelona",
    "sg:orig_category":"Peluqueros: De Se\u00d1oras",
    "sg:phone":"+34 934 35 03 89",
    "sg:postcode":"08041",
    "sg:province":"Barcelona",
    "wof:name":"Sanchez Perez Rosario",
    "wof:placetype":"venue"
},
  "geometry": {"coordinates":[2.1791899204,41.4154968262],"type":"Point"}
}