{
  "type": "Feature",
  "properties": {
    "addr:full":"Calle de Pilar (el), 8 Santa Cruz De Tenerife Santa Cruz De Tenerife 38002",
    "addr:housenumber":"8",
    "addr:postcode":"38002",
    "addr:street":"Calle De Pilar El",
    "iso:country":"ES",
    "sg:address":"Calle de Pilar (el), 8",
    "sg:city":"Santa Cruz De Tenerife",
    "sg:orig_category":"Abogados",
    "sg:phone":"+34 922 24 47 08",
    "sg:postcode":"38002",
    "sg:province":"Santa Cruz De Tenerife",
    "wof:name":"Comenge Acosta Fernando",
    "wof:placetype":"venue"
},
  "geometry": {"coordinates":[-16.2514820099,28.4689235687],"type":"Point"}
}