{
  "type": "Feature",
  "properties": {
    "iso:country":"ES",
    "sg:address":"Calle de Huertas De La Villa, 27",
    "sg:city":"Bilbao",
    "sg:orig_category":"Supermercados Y Hipermercados",
    "sg:phone":"+34 944 45 78 85",
    "sg:postcode":"48007",
    "sg:province":"Vizcaya",
    "wof:name":"Bertoko S.l.",
    "wof:placetype":"venue"
},
  "geometry": {"coordinates":[-2.9285650253,43.268573761],"type":"Point"}
}