{
  "type": "Feature",
  "properties": {
    "addr:full":"Carrer de Antoni Cusido, 72 Sabadell Barcelona 08208",
    "addr:housenumber":"72",
    "addr:postcode":"08208",
    "addr:street":"Carrer De Antoni Cusido",
    "iso:country":"ES",
    "sg:address":"Carrer de Antoni Cusido, 72",
    "sg:city":"Sabadell",
    "sg:orig_category":"Papeler\u00cdas: Art\u00cdculos (al Por Mayor)",
    "sg:phone":"+34 937 17 15 14",
    "sg:postcode":"08208",
    "sg:province":"Barcelona",
    "sg:website":"www.codekbink.net",
    "wof:name":"Borrell Serrat Miquel",
    "wof:placetype":"venue"
},
  "geometry": {"coordinates":[2.1071000099,41.5551147461],"type":"Point"}
}