{
  "type": "Feature",
  "properties": {
    "iso:country":"ES",
    "sg:address":"Carrer de B Pons I Fabregues, 8",
    "sg:city":"Palma",
    "sg:orig_category":"Panader\u00cdas, Panader\u00cdas",
    "sg:phone":"+34 971 27 89 41",
    "sg:postcode":"07007",
    "sg:province":"Islas Baleares",
    "wof:name":"Heredia Arjona Facundo",
    "wof:placetype":"venue"
},
  "geometry": {"coordinates":[2.6673169136,39.573009491],"type":"Point"}
}