{
  "type": "Feature",
  "properties": {
    "addr:full":"Psaj Doctor Serra, 2 Valencia Valencia 46004",
    "addr:housenumber":"2",
    "addr:postcode":"46004",
    "addr:street":"Doctor Serra",
    "iso:country":"ES",
    "sg:address":"Psaj Doctor Serra, 2",
    "sg:city":"Valencia",
    "sg:orig_category":"\u00d3ptica: Instrumentos (fabricaci\u00d3n)",
    "sg:phone":"+34 963 52 43 28",
    "sg:postcode":"46004",
    "sg:province":"Valencia",
    "wof:name":"Gimeno Zaragoza Angela",
    "wof:placetype":"venue"
},
  "geometry": {"coordinates":[-0.3755170107,39.4668655396],"type":"Point"}
}