{
  "type": "Feature",
  "properties": {
    "addr:full":"Ctra General, S/n Sevares Asturias 33584",
    "addr:postcode":"33584",
    "addr:street":"Ctra General S / N Sevares Asturias",
    "iso:country":"ES",
    "sg:address":"Ctra General, S/n",
    "sg:city":"Sevares",
    "sg:orig_category":"Transportes Internacionales",
    "sg:phone":"+34 985 70 67 20",
    "sg:postcode":"33584",
    "sg:province":"Asturias",
    "wof:name":"Transevares S.l.",
    "wof:placetype":"venue"
},
  "geometry": {"coordinates":[-5.2554249763,43.3480644226],"type":"Point"}
}