{
  "type": "Feature",
  "properties": {
    "addr:full":"Carrer de Enamorats, 154 Barcelona Barcelona 08026",
    "addr:housenumber":"154",
    "addr:postcode":"08026",
    "addr:street":"Carrer De Enamorats",
    "iso:country":"ES",
    "sg:address":"Carrer de Enamorats, 154",
    "sg:city":"Barcelona",
    "sg:orig_category":"Chapister\u00cda",
    "sg:phone":"+34 932 45 93 54",
    "sg:postcode":"08026",
    "sg:province":"Barcelona",
    "wof:name":"Suchanek Bednarik Ivan Eduardo",
    "wof:placetype":"venue"
},
  "geometry": {"coordinates":[2.185295105,41.4087562561],"type":"Point"}
}