{
  "type": "Feature",
  "properties": {
    "addr:full":"Carrer de Saragossa, 15 S. Adria Besos Barcelona 08930",
    "addr:housenumber":"15",
    "addr:postcode":"08930",
    "addr:street":"Carrer De Saragossa;S. Adria Besos Barcelona",
    "iso:country":"ES",
    "sg:address":"Carrer de Saragossa, 15",
    "sg:city":"S. Adria Besos",
    "sg:orig_category":"Empresas De Carpinter\u00cda Met\u00c1lica",
    "sg:phone":"+34 934 62 66 26",
    "sg:postcode":"08930",
    "sg:province":"Barcelona",
    "wof:name":"Flores Galilea Miguel",
    "wof:placetype":"venue"
},
  "geometry": {"coordinates":[2.2265350819,41.4261894226],"type":"Point"}
}