{
  "type": "Feature",
  "properties": {
    "iso:country":"ES",
    "sg:address":"Avda Libertad De La, 23",
    "sg:city":"Donostia-san Sebastian",
    "sg:orig_category":"Ropa Para Se\u00d1oras Y Caballeros (al Por Menor)",
    "sg:phone":"+34 943 42 68 49",
    "sg:postcode":"20004",
    "sg:province":"Guip\u00f9zcoa",
    "sg:website":"www.ramonhernandez.com",
    "wof:name":"Ramon Hernandez S. L.",
    "wof:placetype":"venue"
},
  "geometry": {"coordinates":[-1.9826259613,43.319229126],"type":"Point"}
}