{
  "type": "Feature",
  "properties": {
    "addr:full":"Avda Prensa (la), 71 Sevilla Sevilla 41007",
    "addr:housenumber":"71",
    "addr:postcode":"41007",
    "addr:street":"Avda Prensa La",
    "iso:country":"ES",
    "sg:address":"Avda Prensa (la), 71",
    "sg:city":"Sevilla",
    "sg:orig_category":"Electricidad: Equipos Industriales, Componentes (fabricaci\u00d3n)",
    "sg:phone":"+34 954 67 54 19",
    "sg:postcode":"41007",
    "sg:province":"Sevilla",
    "sg:website":"www.lopezbaena-sa.es",
    "wof:name":"Lopez Baena S.a.",
    "wof:placetype":"venue"
},
  "geometry": {"coordinates":[-5.956264019,37.3898506165],"type":"Point"}
}