{
  "type": "Feature",
  "properties": {
    "iso:country":"ES",
    "sg:address":"Calle de Alfonso X, 3",
    "sg:city":"Madrid",
    "sg:classifiers":[
        {
            "category":"Professional",
            "subcategory":"Management & Consulting",
            "type":"Services"
        }
    ],
    "sg:phone":"+34 913 19 32 30",
    "sg:postcode":"28010",
    "sg:province":"Madrid",
    "sg:tags":[
        "asesor\u00cda",
        "en",
        "marketing"
    ],
    "wof:name":"Prieto Lopez Jose",
    "wof:placetype":"venue"
},
  "geometry": {"coordinates":[-3.6921498775,40.4334793091],"type":"Point"}
}