{
  "type": "Feature",
  "properties": {
    "iso:country":"ES",
    "sg:address":"Calle de Ronda Mijares, 8",
    "sg:city":"Castellon",
    "sg:orig_category":"Sociedades, Compa\u00d1\u00cdas Aseguradoras",
    "sg:phone":"+34 964 34 12 34",
    "sg:postcode":"12001",
    "sg:province":"Castell\u00f3n",
    "wof:name":"Mutua Universal Mugenat",
    "wof:placetype":"venue"
},
  "geometry": {"coordinates":[-0.0390900001,39.9866714478],"type":"Point"}
}