{
  "type": "Feature",
  "properties": {
    "iso:country":"ES",
    "sg:address":"C. Maya, 42",
    "sg:city":"Iru\u00f1a",
    "sg:orig_category":"Cl\u00cdnicas Dentales",
    "sg:phone":"+34 948 24 00 21",
    "sg:postcode":"31003",
    "sg:province":"Navarra",
    "wof:name":"Asenjo Madoz Maria Angeles",
    "wof:placetype":"venue"
},
  "geometry": {"coordinates":[-1.6365510225,42.81067276],"type":"Point"}
}