{
  "type": "Feature",
  "properties": {
    "addr:full":"Calle de Leo, 5 Miraval Madrid 28130",
    "addr:housenumber":"5",
    "addr:postcode":"28130",
    "addr:street":"Calle De Leo",
    "iso:country":"ES",
    "sg:address":"Calle de Leo, 5",
    "sg:city":"Miraval",
    "sg:orig_category":"Enfermeras: Consultas, Atenci\u00d3n A Domicilio",
    "sg:phone":"+34 916 20 21 13",
    "sg:postcode":"28130",
    "sg:province":"Madrid",
    "wof:name":"Servicios Sanitarios Y Sociales Galdana",
    "wof:placetype":"venue"
},
  "geometry": {"coordinates":[-3.470662117,40.6132392883],"type":"Point"}
}