{
  "type": "Feature",
  "properties": {
    "iso:country":"ES",
    "sg:address":"Calle de Pe\u00d1a Citores, 9",
    "sg:city":"Madrid",
    "sg:orig_category":"Centros Empresariales",
    "sg:phone":"+34 917 34 39 96",
    "sg:postcode":"28034",
    "sg:province":"Madrid",
    "wof:name":"Jandri S.a.",
    "wof:placetype":"venue"
},
  "geometry": {"coordinates":[-3.7005939484,40.489818573],"type":"Point"}
}