{
  "type": "Feature",
  "properties": {
    "addr:full":"Calle de Alcon, 35 Ponferrada Le\u00f3n 24400",
    "addr:housenumber":"35",
    "addr:postcode":"24400",
    "addr:street":"Calle De Alcon",
    "iso:country":"ES",
    "sg:address":"Calle de Alcon, 35",
    "sg:city":"Ponferrada",
    "sg:orig_category":"Empresas De Carpinter\u00cda De Madera",
    "sg:phone":"+34 987 41 37 32",
    "sg:postcode":"24400",
    "sg:province":"Le\u00f3n",
    "wof:name":"Pozo Rodriguez Luis Del",
    "wof:placetype":"venue"
},
  "geometry": {"coordinates":[-6.6001343727,42.5511131287],"type":"Point"}
}