{
  "type": "Feature",
  "properties": {
    "iso:country":"ES",
    "sg:address":"Elkano Kalea, 12",
    "sg:city":"Hernani",
    "sg:orig_category":"Caf\u00c9s, Bares, Cervecer\u00cdas",
    "sg:phone":"+34 943 55 10 09",
    "sg:postcode":"20120",
    "sg:province":"Guip\u00f9zcoa",
    "wof:name":"Arrozpide Goicoechea Jose Maria",
    "wof:placetype":"venue"
},
  "geometry": {"coordinates":[-1.9769438505,43.2665557861],"type":"Point"}
}