{
  "type": "Feature",
  "properties": {
    "iso:country":"ES",
    "sg:address":"Calle de Toboso, 14",
    "sg:city":"Madrid",
    "sg:orig_category":"Alimentaci\u00d3n General (al Por Menor)",
    "sg:phone":"+34 914 71 79 18",
    "sg:postcode":"28019",
    "sg:province":"Madrid",
    "wof:name":"Casado Llorente Jose Luis",
    "wof:placetype":"venue"
},
  "geometry": {"coordinates":[-3.7260260582,40.3927307129],"type":"Point"}
}