{
  "type": "Feature",
  "properties": {
    "addr:full":"Calle de Frias, 1 Oca\u00f1a Toledo 45300",
    "addr:housenumber":"1",
    "addr:postcode":"45300",
    "addr:street":"Calle De Frias",
    "iso:country":"ES",
    "sg:address":"Calle de Frias, 1",
    "sg:city":"Oca\u00f1a",
    "sg:orig_category":"Doctores En Medicina",
    "sg:phone":"+34 925 12 10 71",
    "sg:postcode":"45300",
    "sg:province":"Toledo",
    "wof:name":"Mayor Oca\u00f1a S.l.",
    "wof:placetype":"venue"
},
  "geometry": {"coordinates":[-3.4991190434,39.9589157104],"type":"Point"}
}