{
  "type": "Feature",
  "properties": {
    "addr:full":"Calle de S Miguel De Los Angeles, 22 Toledo Toledo 45002",
    "addr:housenumber":"22",
    "addr:postcode":"45002",
    "addr:street":"Calle De S Miguel De Los Angeles",
    "iso:country":"ES",
    "sg:address":"Calle de S Miguel De Los Angeles, 22",
    "sg:city":"Toledo",
    "sg:orig_category":"Internados & Ense\u00d1anza Privada",
    "sg:phone":"+34 925 22 27 60",
    "sg:postcode":"45002",
    "sg:province":"Toledo",
    "wof:name":"Religiosas Terciarias Colegio De La Divina Pastora",
    "wof:placetype":"venue"
},
  "geometry": {"coordinates":[-4.0268092155,39.8556213379],"type":"Point"}
}