{
  "type": "Feature",
  "properties": {
    "iso:country":"ES",
    "sg:address":"Rua Rias Baixas, 1",
    "sg:city":"Sarria",
    "sg:orig_category":"Molduras, Junquillos, Listones Y Molduras Perforadas",
    "sg:phone":"+34 982 53 37 83",
    "sg:postcode":"27600",
    "sg:province":"Lugo",
    "wof:name":"Fernandez Herbon Concepcion",
    "wof:placetype":"venue"
},
  "geometry": {"coordinates":[-7.4113068581,42.7799339294],"type":"Point"}
}