{
  "type": "Feature",
  "properties": {
    "addr:full":"Calle de Dulzaina, 9 Madrid Madrid 28033",
    "addr:housenumber":"9",
    "addr:postcode":"madrid;28033",
    "addr:street":"Calle De Dulzaina",
    "iso:country":"ES",
    "sg:address":"Calle de Dulzaina, 9",
    "sg:city":"Madrid",
    "sg:orig_category":"Peluquer\u00cdas, Peluquer\u00cda Mixta",
    "sg:phone":"+34 913 83 08 47",
    "sg:postcode":"28033",
    "sg:province":"Madrid",
    "wof:name":"Ramiro Uria Sonia",
    "wof:placetype":"venue"
},
  "geometry": {"coordinates":[-3.6629116535,40.4809532166],"type":"Point"}
}