{
  "type": "Feature",
  "properties": {
    "iso:country":"ES",
    "sg:address":"Calle de Mayor, 46",
    "sg:city":"Alcala Henares",
    "sg:orig_category":"Asilos De Ancianos. Centros Privados",
    "sg:phone":"+34 918 81 94 47",
    "sg:postcode":"28801",
    "sg:province":"Madrid",
    "wof:name":"Hospital De Antesana",
    "wof:placetype":"venue"
},
  "geometry": {"coordinates":[-3.3669350147,40.4822349548],"type":"Point"}
}