{
  "type": "Feature",
  "properties": {
    "iso:country":"ES",
    "sg:address":"Muel Alfau, S/n",
    "sg:city":"Ceuta",
    "sg:orig_category":"Frutas Y Legumbres Frescas (al Por Mayor)",
    "sg:phone":"+34 956 51 86 56",
    "sg:postcode":"51001",
    "sg:province":"Ceuta",
    "wof:name":"Rocher Gamero Andres",
    "wof:placetype":"venue"
},
  "geometry": {"coordinates":[-5.3302302361,35.8947601318],"type":"Point"}
}