{
  "type": "Feature",
  "properties": {
    "iso:country":"ES",
    "sg:address":"Barr Upomendi, S/n",
    "sg:city":"Kurtzea",
    "sg:orig_category":"Explosivos",
    "sg:phone":"+34 944 56 03 16",
    "sg:postcode":"48960",
    "sg:province":"Vizcaya",
    "wof:name":"Maxamcorp S.a.u.",
    "wof:placetype":"venue"
},
  "geometry": {"coordinates":[-2.8470389843,43.2298049927],"type":"Point"}
}