{
  "type": "Feature",
  "properties": {
    "iso:country":"ES",
    "sg:address":"Calle de Antonio Trueba, 2",
    "sg:city":"Arizgoiti",
    "sg:orig_category":"Peluquer\u00cdas, Peluquer\u00cda Mixta",
    "sg:phone":"+34 944 49 05 97",
    "sg:postcode":"48970",
    "sg:province":"Vizcaya",
    "wof:name":"Marquez Lopez Susana",
    "wof:placetype":"venue"
},
  "geometry": {"coordinates":[-2.8837203979,43.236530304],"type":"Point"}
}