{
  "type": "Feature",
  "properties": {
    "iso:country":"ES",
    "sg:address":"S. Farriols, 136",
    "sg:city":"S. Bartomeu Valldan",
    "sg:orig_category":"Fabricaci\u00d3n De Tejidos Para Exteriores",
    "sg:phone":"+34 938 22 10 48",
    "sg:postcode":"08600",
    "sg:province":"Barcelona",
    "sg:website":"www.sauleda.com",
    "wof:name":"Sauleda S. A.",
    "wof:placetype":"venue"
},
  "geometry": {"coordinates":[1.8460960388,42.1036682129],"type":"Point"}
}