{
  "type": "Feature",
  "properties": {
    "iso:country":"ES",
    "sg:address":"Calle de Estaca, 10",
    "sg:city":"Palmas De Gran Canaria",
    "sg:orig_category":"Asociaciones Y Clubs Deportivos",
    "sg:phone":"+34 928 31 91 76",
    "sg:postcode":"35015",
    "sg:province":"Las Palmas",
    "wof:name":"Sociedad Colombofila San Jose",
    "wof:placetype":"venue"
},
  "geometry": {"coordinates":[-15.4232616425,28.095746994],"type":"Point"}
}