{
  "type": "Feature",
  "properties": {
    "iso:country":"ES",
    "sg:address":"Avda Galicia (de), 55",
    "sg:city":"Monforte De Lemos",
    "sg:orig_category":"Ingeniero",
    "sg:phone":"+34 982 40 03 68",
    "sg:postcode":"27400",
    "sg:province":"Lugo",
    "wof:name":"Vilaboa Lopez Manuel",
    "wof:placetype":"venue"
},
  "geometry": {"coordinates":[-7.5106229782,42.5179862976],"type":"Point"}
}