{
  "type": "Feature",
  "properties": {
    "addr:full":"Carr D'hernan Cortes, 47 Benicarlo Castell\u00f3n 12580",
    "addr:housenumber":"47",
    "addr:postcode":"12580",
    "addr:street":"Carr D'Hernan Cortes",
    "iso:country":"ES",
    "sg:address":"Carr D'hernan Cortes, 47",
    "sg:city":"Benicarlo",
    "sg:orig_category":"Agencias Y Agentes Comerciales, Representantes",
    "sg:phone":"+34 964 47 21 99",
    "sg:postcode":"12580",
    "sg:province":"Castell\u00f3n",
    "wof:name":"Mieles Miranda Nelson",
    "wof:placetype":"venue"
},
  "geometry": {"coordinates":[0.4277229905,40.4163665771],"type":"Point"}
}