{
  "type": "Feature",
  "properties": {
    "iso:country":"ES",
    "sg:address":"Av Onze De Setembre, 5",
    "sg:city":"Sant Joan De Palamos",
    "sg:orig_category":"Panader\u00cdas, Panader\u00cdas",
    "sg:phone":"+34 972 60 02 77",
    "sg:postcode":"17230",
    "sg:province":"Girona",
    "wof:name":"Salvador Salvador Enrique",
    "wof:placetype":"venue"
},
  "geometry": {"coordinates":[3.1294400692,41.8499794006],"type":"Point"}
}