{
  "type": "Feature",
  "properties": {
    "addr:full":"Calle de Sierra Salvada, 46 Madrid Madrid 28038",
    "addr:housenumber":"46",
    "addr:postcode":"madrid;28038",
    "addr:street":"Calle De Sierra Salvada",
    "iso:country":"ES",
    "sg:address":"Calle de Sierra Salvada, 46",
    "sg:city":"Madrid",
    "sg:orig_category":"Cultos Diversos",
    "sg:phone":"+34 913 03 45 63",
    "sg:postcode":"28038",
    "sg:province":"Madrid",
    "wof:name":"Testigos Cristianos De Jehova",
    "wof:placetype":"venue"
},
  "geometry": {"coordinates":[-3.6489191055,40.3886108398],"type":"Point"}
}