{
  "type": "Feature",
  "properties": {
    "iso:country":"ES",
    "sg:address":"Avda Constitucion, 49",
    "sg:city":"Roda",
    "sg:orig_category":"Fabricaci\u00d3n De Enlosados, Soler\u00cdas",
    "sg:phone":"+34 967 44 06 54",
    "sg:postcode":"02630",
    "sg:province":"Albacete",
    "wof:name":"Hermanos Tebar Serrano S. A.",
    "wof:placetype":"venue"
},
  "geometry": {"coordinates":[-2.1627779007,39.2123413086],"type":"Point"}
}