{
  "type": "Feature",
  "properties": {
    "iso:country":"ES",
    "sg:address":"Calle de Rusia, 27",
    "sg:city":"Torre-pacheco",
    "sg:orig_category":"Centros Empresariales",
    "sg:phone":"+34 968 57 77 31",
    "sg:postcode":"30700",
    "sg:province":"Murcia",
    "wof:name":"Solin Conesa S.l",
    "wof:placetype":"venue"
},
  "geometry": {"coordinates":[-0.9433124065,37.7364883423],"type":"Point"}
}