{
  "type": "Feature",
  "properties": {
    "addr:full":"Luga Prado Acedinos, S/n Getafe Madrid 28904",
    "addr:housenumber":"s / n",
    "addr:postcode":"28904",
    "iso:country":"ES",
    "sg:address":"Luga Prado Acedinos, S/n",
    "sg:city":"Getafe",
    "sg:orig_category":"Mataderos Y Talleres De Despiezado",
    "sg:phone":"+34 916 81 89 63",
    "sg:postcode":"28904",
    "sg:province":"Madrid",
    "wof:name":"Industrias Mafasa S.a.",
    "wof:placetype":"venue"
},
  "geometry": {"coordinates":[-3.7467160225,40.2754325867],"type":"Point"}
}