{
  "type": "Feature",
  "properties": {
    "iso:country":"ES",
    "sg:address":"Rier Sant Jordi, 151",
    "sg:city":"Mallorquines",
    "sg:orig_category":"Establecimientos De Cura, Prevenci\u00d3n Y Readaptaci\u00d3n",
    "sg:phone":"+34 934 69 32 25",
    "sg:postcode":"08390",
    "sg:province":"Barcelona",
    "wof:name":"Fundacio Gresol Projecte Home",
    "wof:placetype":"venue"
},
  "geometry": {"coordinates":[2.2785899639,41.4666290283],"type":"Point"}
}