{
  "type": "Feature",
  "properties": {
    "addr:full":"Cmno Algesares, S/n Aspe Alicante 03680",
    "addr:housenumber":"s",
    "addr:postcode":"03680",
    "addr:street":"Cmno Algesares;/ N",
    "iso:country":"ES",
    "sg:address":"Cmno Algesares, S/n",
    "sg:city":"Aspe",
    "sg:orig_category":"Confecci\u00d3n De Zapatos",
    "sg:phone":"+34 965 49 56 98",
    "sg:postcode":"03680",
    "sg:province":"Alicante",
    "wof:name":"D'patty Shoes S.l.u.",
    "wof:placetype":"venue"
},
  "geometry": {"coordinates":[-0.7689840198,38.3471984863],"type":"Point"}
}