{
  "type": "Feature",
  "properties": {
    "addr:full":"Calle de Collados, 7 Madrid Madrid 28017",
    "addr:housenumber":"7",
    "addr:postcode":"madrid;28017",
    "addr:street":"Calle De Collados",
    "iso:country":"ES",
    "sg:address":"Calle de Collados, 7",
    "sg:city":"Madrid",
    "sg:orig_category":"Inmobiliaria (agencias)",
    "sg:phone":"+34 914 06 13 25",
    "sg:postcode":"28017",
    "sg:province":"Madrid",
    "wof:name":"Thomasgut S.l.",
    "wof:placetype":"venue"
},
  "geometry": {"coordinates":[-3.6493480206,40.4312400818],"type":"Point"}
}