{
  "type": "Feature",
  "properties": {
    "iso:country":"ES",
    "sg:address":"Avda. Andalucia, 4",
    "sg:city":"Bedmar",
    "sg:orig_category":"Cajas Para Embalar",
    "sg:phone":"+34 953 76 01 51",
    "sg:postcode":"23537",
    "sg:province":"Ja\u00e9n",
    "wof:name":"Caja Rural De Jaen",
    "wof:placetype":"venue"
},
  "geometry": {"coordinates":[-3.4123740196,37.8219833374],"type":"Point"}
}