{
  "type": "Feature",
  "properties": {
    "addr:full":"Calle de Limonero (del), 7 Arganda Madrid 28500",
    "addr:housenumber":"7",
    "addr:postcode":"28500",
    "addr:street":"Calle De Limonero Del",
    "iso:country":"ES",
    "sg:address":"Calle de Limonero (del), 7",
    "sg:city":"Arganda",
    "sg:orig_category":"Empresas De Carpinter\u00cda De Madera",
    "sg:phone":"+34 918 71 63 59",
    "sg:postcode":"28500",
    "sg:province":"Madrid",
    "wof:name":"Perfiles Govi S.l.",
    "wof:placetype":"venue"
},
  "geometry": {"coordinates":[-3.4621479511,40.3126182556],"type":"Point"}
}