{
  "type": "Feature",
  "properties": {
    "iso:country":"ES",
    "sg:address":"Oca De Abaixo, S/n",
    "sg:city":"Oca De Abaixo",
    "sg:orig_category":"Material Y Herramientas Agr\u00cdcolas",
    "sg:phone":"+34 981 51 87 52",
    "sg:postcode":"15824",
    "sg:province":"La Coru\u00f1a",
    "wof:name":"Freire Bahamonde Juan Carlos",
    "wof:placetype":"venue"
},
  "geometry": {"coordinates":[-8.2708034515,42.8849906921],"type":"Point"}
}