{
  "type": "Feature",
  "properties": {
    "iso:country":"ES",
    "sg:address":"Calle de Morales (los), 5",
    "sg:city":"Cacabelos",
    "sg:orig_category":"Abogados",
    "sg:phone":"+34 987 54 90 74",
    "sg:postcode":"24540",
    "sg:province":"Le\u00f3n",
    "wof:name":"Gonzalez Santos Maria Jesus",
    "wof:placetype":"venue"
},
  "geometry": {"coordinates":[-6.7255740166,42.5985908508],"type":"Point"}
}