{
  "type": "Feature",
  "properties": {
    "addr:full":"San Jose Obrero, 11 Conil C\u00e1diz 11140",
    "addr:housenumber":"11",
    "addr:postcode":"11140",
    "addr:street":"Obrero",
    "iso:country":"ES",
    "sg:address":"San Jose Obrero, 11",
    "sg:city":"Conil",
    "sg:orig_category":"Promotores Constructores",
    "sg:phone":"+34 956 44 21 38",
    "sg:postcode":"11140",
    "sg:province":"C\u00e1diz",
    "sg:website":"www.perez-salvado.com",
    "wof:name":"Promociones Perez Salvado S.l.",
    "wof:placetype":"venue"
},
  "geometry": {"coordinates":[-6.0837841034,36.2822532654],"type":"Point"}
}