{
  "type": "Feature",
  "properties": {
    "addr:full":"Via Pollentia, 8 Pollen\u00e7a Islas Baleares 07460",
    "addr:housenumber":"8",
    "addr:postcode":"07460",
    "addr:street":"Via Pollentia;Islas",
    "iso:country":"ES",
    "sg:address":"Via Pollentia, 8",
    "sg:city":"Pollen\u00e7a",
    "sg:orig_category":"Transportes Por Carretera: Lotes Completos, Mercanc\u00cdas Diversas",
    "sg:phone":"+34 971 53 06 88",
    "sg:postcode":"07460",
    "sg:province":"Islas Baleares",
    "wof:name":"Canaves Pallicer Ignacio",
    "wof:placetype":"venue"
},
  "geometry": {"coordinates":[3.0176069736,39.875667572],"type":"Point"}
}