{
  "type": "Feature",
  "properties": {
    "addr:full":"Rond Carmen (del), 25 Caceres C\u00e1ceres 10002",
    "addr:postcode":"10002",
    "addr:street":"Ca\u0301Ceres",
    "iso:country":"ES",
    "sg:address":"Rond Carmen (del), 25",
    "sg:city":"Caceres",
    "sg:orig_category":"Peluquer\u00cdas, Peluquer\u00cda Mixta",
    "sg:phone":"+34 927 24 02 07",
    "sg:postcode":"10002",
    "sg:province":"C\u00e1ceres",
    "wof:name":"Flores Espada Gonzalo",
    "wof:placetype":"venue"
},
  "geometry": {"coordinates":[-6.3768582344,39.4682388306],"type":"Point"}
}