{
  "type": "Feature",
  "properties": {
    "iso:country":"ES",
    "sg:address":"Ctra Torrefrades, S/n",
    "sg:city":"Bermillo Sayago",
    "sg:orig_category":"Centros De Educaci\u00d3n Especial",
    "sg:phone":"+34 980 61 00 55",
    "sg:postcode":"49200",
    "sg:province":"Zamora",
    "wof:name":"Colegio Nacional Mixto Comarcal De Bermillo De Sayago",
    "wof:placetype":"venue"
},
  "geometry": {"coordinates":[-6.0795769691,41.3564567566],"type":"Point"}
}