{
  "type": "Feature",
  "properties": {
    "iso:country":"ES",
    "sg:address":"Calle de Virgen De Lourdes, 36",
    "sg:city":"Madrid",
    "sg:orig_category":"Cl\u00cdnicas Dentales",
    "sg:phone":"+34 914 05 09 14",
    "sg:postcode":"28027",
    "sg:province":"Madrid",
    "wof:name":"Caras Odonto-tecnia S.l.",
    "wof:placetype":"venue"
},
  "geometry": {"coordinates":[-3.6561939716,40.4357032776],"type":"Point"}
}