{
  "type": "Feature",
  "properties": {
    "addr:full":"Calle de Devesa, 5 Alacant Alicante 03010",
    "addr:housenumber":"5",
    "addr:postcode":"03010",
    "addr:street":"Calle De Devesa",
    "iso:country":"ES",
    "sg:address":"Calle de Devesa, 5",
    "sg:city":"Alacant",
    "sg:orig_category":"Pr\u00c1ctica De Vela, Navegaci\u00d3n Y Deportes N\u00c1uticos Y Acu\u00c1ticos",
    "sg:phone":"+34 965 24 31 90",
    "sg:postcode":"03010",
    "sg:province":"Alicante",
    "wof:name":"Marcos Navarrete Jose",
    "wof:placetype":"venue"
},
  "geometry": {"coordinates":[-0.4844388962,38.3593711853],"type":"Point"}
}