{
  "type": "Feature",
  "properties": {
    "iso:country":"ES",
    "sg:address":"Calle de Acebal Idigoras, 4",
    "sg:city":"Bilbao",
    "sg:orig_category":"Peluquer\u00cdas, Peluquer\u00cda Mixta",
    "sg:phone":"+34 944 23 25 12",
    "sg:postcode":"48001",
    "sg:province":"Vizcaya",
    "wof:name":"Lorena San Martin Y Maider Aperribai C.b",
    "wof:placetype":"venue"
},
  "geometry": {"coordinates":[-2.9250965118,43.2632789612],"type":"Point"}
}