{
  "type": "Feature",
  "properties": {
    "iso:country":"ES",
    "sg:address":"Carrer de Energia, 50",
    "sg:city":"Mataro",
    "sg:orig_category":"Medias Y Calcetines (fabricaci\u00d3n, Al Por Mayor)",
    "sg:phone":"+34 937 90 71 43",
    "sg:postcode":"08304",
    "sg:province":"Barcelona",
    "sg:website":"www.pantymaresme.com",
    "wof:name":"Panty Maresme Coop.",
    "wof:placetype":"venue"
},
  "geometry": {"coordinates":[2.4497599602,41.5544013977],"type":"Point"}
}