{
  "type": "Feature",
  "properties": {
    "iso:country":"ES",
    "sg:address":"Avda Madrid, 38",
    "sg:city":"Toledo",
    "sg:orig_category":"Venta, Montaje De Neum\u00c1ticos",
    "sg:phone":"+34 925 22 20 95",
    "sg:postcode":"45003",
    "sg:province":"Toledo",
    "wof:name":"Autodisco S. A.",
    "wof:placetype":"venue"
},
  "geometry": {"coordinates":[-4.0198111534,39.8695678711],"type":"Point"}
}