{
  "type": "Feature",
  "properties": {
    "addr:full":"Urb Mirador De Nueva Alcantara, S/n San Pedro Alcantara M\u00e1laga 29670",
    "addr:housenumber":"s / n",
    "addr:postcode":"29670",
    "addr:street":"Alcantara",
    "iso:country":"ES",
    "sg:address":"Urb Mirador De Nueva Alcantara, S/n",
    "sg:city":"San Pedro Alcantara",
    "sg:orig_category":"Guarder\u00cdas",
    "sg:phone":"+34 952 85 37 77",
    "sg:postcode":"29670",
    "sg:province":"M\u00e1laga",
    "sg:website":"www.dolthinursey.com",
    "wof:name":"Dolphin Day Nursery S.l.",
    "wof:placetype":"venue"
},
  "geometry": {"coordinates":[-4.9902391434,36.4866333008],"type":"Point"}
}