{
  "type": "Feature",
  "properties": {
    "addr:full":"Avda Joaquin Costa, 2 Porcuna Ja\u00e9n 23790",
    "addr:housenumber":"2",
    "addr:postcode":"23790",
    "addr:street":"Avda Joaquin Costa",
    "iso:country":"ES",
    "sg:address":"Avda Joaquin Costa, 2",
    "sg:city":"Porcuna",
    "sg:orig_category":"Muebles, Minoristas",
    "sg:phone":"+34 953 54 48 61",
    "sg:postcode":"23790",
    "sg:province":"Ja\u00e9n",
    "wof:name":"Antonio Heredia Cespedosa Y Otro C.b.",
    "wof:placetype":"venue"
},
  "geometry": {"coordinates":[-4.1805119514,37.872253418],"type":"Point"}
}