{
  "type": "Feature",
  "properties": {
    "iso:country":"ES",
    "sg:address":"Carrer de Ribot I Serra, 74",
    "sg:city":"Sabadell",
    "sg:orig_category":"Telas Y Sedas (al Por Menor)",
    "sg:phone":"+34 937 16 20 41",
    "sg:postcode":"08208",
    "sg:province":"Barcelona",
    "wof:name":"Reginaldo Carles Pedro",
    "wof:placetype":"venue"
},
  "geometry": {"coordinates":[2.1080150604,41.5564880371],"type":"Point"}
}