{
  "type": "Feature",
  "properties": {
    "addr:full":"Calle de Don Juan De Austria, 32 Valencia Valencia 46002",
    "addr:housenumber":"32",
    "addr:postcode":"46002",
    "addr:street":"Calle De Don Juan De Austria",
    "iso:country":"ES",
    "sg:address":"Calle de Don Juan De Austria, 32",
    "sg:city":"Valencia",
    "sg:orig_category":"Inversiones",
    "sg:phone":"+34 963 51 88 80",
    "sg:postcode":"46002",
    "sg:province":"Valencia",
    "sg:website":"www.ca-indosuez.es",
    "wof:name":"Indosuez Levante S.a.",
    "wof:placetype":"venue"
},
  "geometry": {"coordinates":[-0.3719775975,39.4703178406],"type":"Point"}
}