{
  "type": "Feature",
  "properties": {
    "iso:country":"ES",
    "sg:address":"Calle de Herrera, 22",
    "sg:city":"Bullas",
    "sg:orig_category":"Laboratorios Y Asesor\u00cda En Enolog\u00cda",
    "sg:phone":"+34 968 65 42 05",
    "sg:postcode":"30180",
    "sg:province":"Murcia",
    "wof:name":"Quesada Gil Maria Pilar",
    "wof:placetype":"venue"
},
  "geometry": {"coordinates":[-1.6713910103,38.0410499573],"type":"Point"}
}