{
  "type": "Feature",
  "properties": {
    "addr:full":"Avda Federico Garcia Lorca, 20 Almeria Almer\u00eda 04004",
    "addr:housenumber":"20",
    "addr:postcode":"04004",
    "addr:street":"Avda Federico Garcia Lorca",
    "iso:country":"ES",
    "sg:address":"Avda Federico Garcia Lorca, 20",
    "sg:city":"Almeria",
    "sg:orig_category":"Arquitectos",
    "sg:phone":"+34 950 24 04 50",
    "sg:postcode":"04004",
    "sg:province":"Almer\u00eda",
    "wof:name":"Lillo Soler Jose",
    "wof:placetype":"venue"
},
  "geometry": {"coordinates":[-2.461067915,36.8365859985],"type":"Point"}
}