{
  "type": "Feature",
  "properties": {
    "iso:country":"ES",
    "sg:address":"Calle de Antonio Machado (de), 67",
    "sg:city":"San Fernando De Henares",
    "sg:orig_category":"Cervecer\u00cdas",
    "sg:phone":"+34 916 74 28 29",
    "sg:postcode":"28830",
    "sg:province":"Madrid",
    "wof:name":"Quality Phone S.l.",
    "wof:placetype":"venue"
},
  "geometry": {"coordinates":[-3.5367274284,40.4236068726],"type":"Point"}
}