{
  "type": "Feature",
  "properties": {
    "addr:full":"Plaz Beltran Martinez, 1 Zaragoza Zaragoza 50001",
    "addr:housenumber":"1",
    "addr:postcode":"50001",
    "addr:street":"Martinez",
    "iso:country":"ES",
    "sg:address":"Plaz Beltran Martinez, 1",
    "sg:city":"Zaragoza",
    "sg:orig_category":"Reciclaje Y Tratamiento De Desechos Varios",
    "sg:phone":"+34 976 20 33 31",
    "sg:postcode":"50001",
    "sg:province":"Zaragoza",
    "wof:name":"Urbaser, S.a. Y Vertederos De Residuos, S.a. Union Temporal De Empresas",
    "wof:placetype":"venue"
},
  "geometry": {"coordinates":[-0.8813189864,41.6517295837],"type":"Point"}
}