{
  "type": "Feature",
  "properties": {
    "addr:full":"Luga Poligono 20, S/n Llucmajor Islas Baleares 07620",
    "addr:housenumber":"s / n",
    "addr:postcode":"07620",
    "addr:street":"Poligono 20",
    "iso:country":"ES",
    "sg:address":"Luga Poligono 20, S/n",
    "sg:city":"Llucmajor",
    "sg:orig_category":"Promotores Constructores",
    "sg:phone":"+34 971 66 11 84",
    "sg:postcode":"07620",
    "sg:province":"Islas Baleares",
    "wof:name":"Llucmajor Construcciones Y Obras S.l.",
    "wof:placetype":"venue"
},
  "geometry": {"coordinates":[2.8897550106,39.486114502],"type":"Point"}
}