{
  "type": "Feature",
  "properties": {
    "iso:country":"ES",
    "sg:address":"Calle de Huerta De La Papachina, S/n",
    "sg:city":"Sevilla",
    "sg:orig_category":"Alimentaci\u00d3n General (al Por Menor)",
    "sg:phone":"+34 954 38 05 01",
    "sg:postcode":"41015",
    "sg:province":"Sevilla",
    "wof:name":"Ramirez Martin Rosa",
    "wof:placetype":"venue"
},
  "geometry": {"coordinates":[-5.9865841866,37.4264450073],"type":"Point"}
}