{
  "type": "Feature",
  "properties": {
    "addr:full":"Avda Moratalaz, 151 Madrid Madrid 28030",
    "addr:housenumber":"151",
    "addr:postcode":"28030",
    "addr:street":"Avda Moratalaz",
    "iso:country":"ES",
    "sg:address":"Avda Moratalaz, 151",
    "sg:city":"Madrid",
    "sg:orig_category":"Sociedades, Compa\u00d1\u00cdas Aseguradoras",
    "sg:phone":"+34 913 28 71 62",
    "sg:postcode":"28030",
    "sg:province":"Madrid",
    "sg:website":"www.mmtseguros.es",
    "wof:name":"Mutua Mmt Seguros",
    "wof:placetype":"venue"
},
  "geometry": {"coordinates":[-3.6475069523,40.4072952271],"type":"Point"}
}