{
  "type": "Feature",
  "properties": {
    "iso:country":"ES",
    "sg:address":"Avgd Picassent, 28",
    "sg:city":"Silla",
    "sg:orig_category":"Chapister\u00cda",
    "sg:phone":"+34 961 21 14 04",
    "sg:postcode":"46460",
    "sg:province":"Valencia",
    "wof:name":"Auto-silla Motor S.l.",
    "wof:placetype":"venue"
},
  "geometry": {"coordinates":[-0.4201675951,39.3642578125],"type":"Point"}
}