{
  "type": "Feature",
  "properties": {
    "iso:country":"ES",
    "sg:address":"Calle de Bolseria, 28",
    "sg:city":"Valencia",
    "sg:orig_category":"Dorados, Plater\u00cda (orfebrer\u00cda)",
    "sg:phone":"+34 963 92 17 20",
    "sg:postcode":"46001",
    "sg:province":"Valencia",
    "sg:website":"www.ochometroscuadrados.com",
    "wof:name":"Martin Hernaez Jorge",
    "wof:placetype":"venue"
},
  "geometry": {"coordinates":[-0.3799901009,39.4754714966],"type":"Point"}
}