{
  "type": "Feature",
  "properties": {
    "iso:country":"ES",
    "sg:address":"Carrer de Major, 13",
    "sg:city":"Salou",
    "sg:orig_category":"Producci\u00d3n, Distribuci\u00d3n De Gas Butano Y Propano",
    "sg:phone":"+34 977 38 11 43",
    "sg:postcode":"43840",
    "sg:province":"Tarragona",
    "wof:name":"Electro-ciuret S.l.",
    "wof:placetype":"venue"
},
  "geometry": {"coordinates":[1.1349129677,41.0766296387],"type":"Point"}
}