{
  "type": "Feature",
  "properties": {
    "addr:full":"Pl Major, 2 Pobla De Massaluca Tarragona 43783",
    "addr:housenumber":"2",
    "addr:postcode":"43783",
    "addr:street":"Pl Major",
    "iso:country":"ES",
    "sg:address":"Pl Major, 2",
    "sg:city":"Pobla De Massaluca",
    "sg:orig_category":"Cooperativas Agr\u00cdcolas",
    "sg:phone":"+34 977 43 97 38",
    "sg:postcode":"43783",
    "sg:province":"Tarragona",
    "wof:name":"Cooperativa Agricola Terra Alta Y Sec.cto.",
    "wof:placetype":"venue"
},
  "geometry": {"coordinates":[0.3539139926,41.1800613403],"type":"Point"}
}