{
  "type": "Feature",
  "properties": {
    "iso:country":"ES",
    "sg:address":"Bda. Los Arenales, S/n",
    "sg:city":"Los Arenales",
    "sg:orig_category":"Centros De Educaci\u00d3n Especial",
    "sg:phone":"+34 957 60 28 57",
    "sg:postcode":"14500",
    "sg:province":"C\u00f3rdoba",
    "wof:name":"Junta De Andalucia",
    "wof:placetype":"venue"
},
  "geometry": {"coordinates":[-4.7779579163,37.3909187317],"type":"Point"}
}