{
  "type": "Feature",
  "properties": {
    "addr:full":"Calle de Ignacio Martinez De Azcoitia, 11 Palencia Palencia 34001",
    "addr:housenumber":"11",
    "addr:postcode":"34001",
    "addr:street":"Calle De Ignacio Martinez De Azcoitia",
    "iso:country":"ES",
    "sg:address":"Calle de Ignacio Martinez De Azcoitia, 11",
    "sg:city":"Palencia",
    "sg:orig_category":"Molduras, Junquillos, Listones Y Molduras Perforadas",
    "sg:phone":"+34 979 70 30 81",
    "sg:postcode":"34001",
    "sg:province":"Palencia",
    "wof:name":"Gomez Polo Antonio",
    "wof:placetype":"venue"
},
  "geometry": {"coordinates":[-4.5318951607,42.0117912292],"type":"Point"}
}