{
  "type": "Feature",
  "properties": {
    "iso:country":"ES",
    "sg:address":"L'alqueria, 45",
    "sg:city":"Beniparrell",
    "sg:orig_category":"Calderer\u00cda",
    "sg:phone":"+34 961 21 33 27",
    "sg:postcode":"46469",
    "sg:province":"Valencia",
    "sg:website":"www.caldema.com",
    "wof:name":"Caldema Industrias S.l.",
    "wof:placetype":"venue"
},
  "geometry": {"coordinates":[-0.4136700034,39.3834381104],"type":"Point"}
}