{
  "type": "Feature",
  "properties": {
    "iso:country":"ES",
    "sg:address":"Carrer de Son Amer, S/n",
    "sg:city":"Llombards",
    "sg:orig_category":"Servicios De Telecomunicaciones",
    "sg:phone":"+34 971 64 21 21",
    "sg:postcode":"07690",
    "sg:province":"Islas Baleares",
    "wof:name":"Networld Marketing S.l. Unipersonal",
    "wof:placetype":"venue"
},
  "geometry": {"coordinates":[3.1323549747,39.3185157776],"type":"Point"}
}