{
  "type": "Feature",
  "properties": {
    "addr:full":"Avgd Primer De Maig (del), 100 Betxi Castell\u00f3n 12549",
    "addr:postcode":"12549",
    "addr:street":"Castello\u0301N",
    "iso:country":"ES",
    "sg:address":"Avgd Primer De Maig (del), 100",
    "sg:city":"Betxi",
    "sg:orig_category":"Centros De Coordinaci\u00d3n",
    "sg:phone":"+34 964 62 06 08",
    "sg:postcode":"12549",
    "sg:province":"Castell\u00f3n",
    "wof:name":"A.f.c. Serveis I Llei S.l.",
    "wof:placetype":"venue"
},
  "geometry": {"coordinates":[-0.1963364035,39.9297142029],"type":"Point"}
}