{
  "type": "Feature",
  "properties": {
    "addr:full":"Calle de Pirineos, 27 Benabarre Huesca 22580",
    "addr:housenumber":"27",
    "addr:postcode":"22580",
    "addr:street":"Calle De Pirineos",
    "iso:country":"ES",
    "sg:address":"Calle de Pirineos, 27",
    "sg:city":"Benabarre",
    "sg:orig_category":"Electrodom\u00c9sticos (al Por Menor)",
    "sg:phone":"+34 974 54 35 43",
    "sg:postcode":"22580",
    "sg:province":"Huesca",
    "wof:name":"Bruguera Pociello Jose Manuel",
    "wof:placetype":"venue"
},
  "geometry": {"coordinates":[0.4777399898,42.1105194092],"type":"Point"}
}