{
  "type": "Feature",
  "properties": {
    "iso:country":"ES",
    "sg:address":"Grup Arriberri, 8",
    "sg:city":"Donostia-san Sebastian",
    "sg:classifiers":[
        {
            "category":"Autos & Motor Vehicles",
            "subcategory":"Automobile Sales",
            "type":"Retail Goods"
        }
    ],
    "sg:phone":"+34 943 35 33 83",
    "sg:postcode":"20017",
    "sg:province":"Guip\u00f9zcoa",
    "sg:website":"www.auto-eskolak.com",
    "wof:name":"Autoescuela Alza S.c.",
    "wof:placetype":"venue"
},
  "geometry": {"coordinates":[-1.9284600019,43.3172454834],"type":"Point"}
}