{
  "type": "Feature",
  "properties": {
    "addr:full":"Rua Carpinteiros (dos), 2 Lugo Lugo 27003",
    "addr:housenumber":"2",
    "addr:postcode":"27003",
    "addr:street":"Rua Carpinteiros Dos",
    "iso:country":"ES",
    "sg:address":"Rua Carpinteiros (dos), 2",
    "sg:city":"Lugo",
    "sg:orig_category":"Delegados, Agentes De Tr\u00c1nsito, Auxiliares De Transporte Internacional",
    "sg:phone":"+34 982 20 92 20",
    "sg:postcode":"27003",
    "sg:province":"Lugo",
    "wof:name":"Transportes Martinez Souto S. L.",
    "wof:placetype":"venue"
},
  "geometry": {"coordinates":[-7.5599241257,43.0418548584],"type":"Point"}
}