{
  "type": "Feature",
  "properties": {
    "addr:full":"Trav De Gracia, 105 Barcelona Barcelona 08006",
    "addr:housenumber":"105",
    "addr:postcode":"08006",
    "addr:street":"Trav De Gracia",
    "iso:country":"ES",
    "sg:address":"Trav De Gracia, 105",
    "sg:city":"Barcelona",
    "sg:orig_category":"Peluqueros: De Se\u00d1oras",
    "sg:phone":"+34 932 17 20 96",
    "sg:postcode":"08006",
    "sg:province":"Barcelona",
    "wof:name":"Miro Elfa Sara",
    "wof:placetype":"venue"
},
  "geometry": {"coordinates":[2.1528000832,41.3981781006],"type":"Point"}
}