{
  "type": "Feature",
  "properties": {
    "iso:country":"ES",
    "sg:address":"Calle de Federico Mayo, 13",
    "sg:city":"Huesca",
    "sg:orig_category":"Plomeros",
    "sg:phone":"+34 974 22 29 15",
    "sg:postcode":"22006",
    "sg:province":"Huesca",
    "wof:name":"Bruno Caceres Guillermo",
    "wof:placetype":"venue"
},
  "geometry": {"coordinates":[-0.3951550126,42.1423072815],"type":"Point"}
}