{
  "type": "Feature",
  "properties": {
    "addr:full":"Ctra. Alcudia-arta, 40 Can Picafort Islas Baleares 07458",
    "addr:housenumber":"40",
    "addr:postcode":"07458",
    "addr:street":"Ctra. Alcudia-Arta",
    "iso:country":"ES",
    "sg:address":"Ctra. Alcudia-arta, 40",
    "sg:city":"Can Picafort",
    "sg:orig_category":"Alquiler De V\u00cddeo",
    "sg:phone":"+34 971 85 23 24",
    "sg:postcode":"07458",
    "sg:province":"Islas Baleares",
    "wof:name":"Lopez Maireles Mercedes",
    "wof:placetype":"venue"
},
  "geometry": {"coordinates":[3.1990671158,39.7262954712],"type":"Point"}
}