{
  "type": "Feature",
  "properties": {
    "iso:country":"ES",
    "sg:address":"Carrer de Llunetes, 1",
    "sg:city":"Cornella Llobregat",
    "sg:orig_category":"Venta, Instalaci\u00d3n De Calefacci\u00d3n",
    "sg:phone":"+34 933 75 38 51",
    "sg:postcode":"08940",
    "sg:province":"Barcelona",
    "wof:name":"Instalaciones Y Montajes Baladon",
    "wof:placetype":"venue"
},
  "geometry": {"coordinates":[2.0816099644,41.3608131409],"type":"Point"}
}