{
  "type": "Feature",
  "properties": {
    "iso:country":"ES",
    "sg:address":"Mercado De Abastos, S/n",
    "sg:city":"Alzira",
    "sg:orig_category":"Restaurantes",
    "sg:phone":"+34 962 40 40 06",
    "sg:postcode":"46600",
    "sg:province":"Valencia",
    "wof:name":"Jose Garcia Francisco",
    "wof:placetype":"venue"
},
  "geometry": {"coordinates":[-0.4378489852,39.1517295837],"type":"Point"}
}