{
  "type": "Feature",
  "properties": {
    "addr:full":"Plaz Constitucion, 2 Tudela Navarra 31500",
    "addr:postcode":"31500",
    "addr:street":"Constitucion 2",
    "iso:country":"ES",
    "sg:address":"Plaz Constitucion, 2",
    "sg:city":"Tudela",
    "sg:orig_category":"Peleter\u00cdas",
    "sg:phone":"+34 948 82 48 07",
    "sg:postcode":"31500",
    "sg:province":"Navarra",
    "wof:name":"Marques Roncal Julian",
    "wof:placetype":"venue"
},
  "geometry": {"coordinates":[-1.60295403,42.0619239807],"type":"Point"}
}