{
  "type": "Feature",
  "properties": {
    "iso:country":"ES",
    "sg:address":"Calle de Ca\u00d1ete, 19",
    "sg:city":"Madrid",
    "sg:orig_category":"Bisuteros (fabricaci\u00d3n, Al Por Mayor)",
    "sg:phone":"+34 914 71 11 78",
    "sg:postcode":"28019",
    "sg:province":"Madrid",
    "wof:name":"Joaquin Iglesias S.l.",
    "wof:placetype":"venue"
},
  "geometry": {"coordinates":[-3.7349932194,40.3921127319],"type":"Point"}
}