{
  "type": "Feature",
  "properties": {
    "iso:country":"ES",
    "sg:address":"Calle de Bolta\u00d1a, 5",
    "sg:city":"Madrid",
    "sg:orig_category":"Fabricaci\u00d3n De Juegos Y Juguetes",
    "sg:phone":"+34 913 71 71 87",
    "sg:postcode":"28022",
    "sg:province":"Madrid",
    "wof:name":"Alcol Y Vazquez S.l.",
    "wof:placetype":"venue"
},
  "geometry": {"coordinates":[-3.6141424179,40.444278717],"type":"Point"}
}