{
  "type": "Feature",
  "properties": {
    "iso:country":"ES",
    "sg:address":"Carrer de Nicaragua, 132",
    "sg:city":"Barcelona",
    "sg:orig_category":"Abrasivos Y Superabrasivos (fabricaci\u00d3n, Al Por Mayor)",
    "sg:phone":"+34 933 63 40 53",
    "sg:postcode":"08029",
    "sg:province":"Barcelona",
    "wof:name":"Wheelabrator Alleward Espa\u00f1ola S.a.",
    "wof:placetype":"venue"
},
  "geometry": {"coordinates":[2.1370623112,41.3868331909],"type":"Point"}
}