{
  "type": "Feature",
  "properties": {
    "addr:full":"Humilladero, S/n Virgen De La Vega Teruel 44431",
    "addr:housenumber":"s",
    "addr:postcode":"44431",
    "addr:street":"Humilladero;/ N Virgen De La",
    "iso:country":"ES",
    "sg:address":"Humilladero, S/n",
    "sg:city":"Virgen De La Vega",
    "sg:orig_category":"Compraventa De Antig\u00dcedades",
    "sg:phone":"+34 978 80 11 00",
    "sg:postcode":"44431",
    "sg:province":"Teruel",
    "wof:name":"Lopez Garcia Miguel",
    "wof:placetype":"venue"
},
  "geometry": {"coordinates":[-1.1069096327,40.3441085815],"type":"Point"}
}