{
  "type": "Feature",
  "properties": {
    "addr:full":"Antziola Auzoa, 30 Hernani Guip\u00f9zcoa 20120",
    "addr:housenumber":"30",
    "addr:postcode":"20120",
    "addr:street":"Antziola Auzoa;Guipu\u0300Zcoa",
    "iso:country":"ES",
    "sg:address":"Antziola Auzoa, 30",
    "sg:city":"Hernani",
    "sg:orig_category":"Caf\u00c9s, Bares, Cervecer\u00cdas",
    "sg:phone":"+34 943 33 07 83",
    "sg:postcode":"20120",
    "sg:province":"Guip\u00f9zcoa",
    "wof:name":"Pastoriza Nieto Elena",
    "wof:placetype":"venue"
},
  "geometry": {"coordinates":[-1.9767249823,43.2717247009],"type":"Point"}
}