{
  "type": "Feature",
  "properties": {
    "iso:country":"ES",
    "sg:address":"Plaz Encarnacion, 24",
    "sg:city":"Sevilla",
    "sg:orig_category":"Caf\u00c9s, Bares, Cervecer\u00cdas",
    "sg:phone":"+34 954 22 20 91",
    "sg:postcode":"41003",
    "sg:province":"Sevilla",
    "wof:name":"Escalona Recuerda Andres",
    "wof:placetype":"venue"
},
  "geometry": {"coordinates":[-5.9919681549,37.3939399719],"type":"Point"}
}