{
  "type": "Feature",
  "properties": {
    "addr:full":"Carrer de Lusacia, 35 Vall Suau-can Feliu Barcelona 08192",
    "addr:housenumber":"35",
    "addr:postcode":"08192",
    "addr:street":"Carrer De Lusacia",
    "iso:country":"ES",
    "sg:address":"Carrer de Lusacia, 35",
    "sg:city":"Vall Suau-can Feliu",
    "sg:orig_category":"Empresas De Carpinter\u00cda Met\u00c1lica",
    "sg:phone":"+34 937 21 34 81",
    "sg:postcode":"08192",
    "sg:province":"Barcelona",
    "wof:name":"Rios Lara Jose Maria",
    "wof:placetype":"venue"
},
  "geometry": {"coordinates":[2.0703930855,41.5291976929],"type":"Point"}
}