{
  "type": "Feature",
  "properties": {
    "addr:full":"Avda Campones, S/n Gijon Asturias 33211",
    "addr:housenumber":"s",
    "addr:postcode":"33211",
    "addr:street":"Avda Campones;/ N",
    "iso:country":"ES",
    "sg:address":"Avda Campones, S/n",
    "sg:city":"Gijon",
    "sg:orig_category":"Asociaciones Y Clubs Deportivos",
    "sg:phone":"+34 985 31 65 42",
    "sg:postcode":"33211",
    "sg:province":"Asturias",
    "wof:name":"Grupo Tiro Olimpico Ensidesa Gijon",
    "wof:placetype":"venue"
},
  "geometry": {"coordinates":[-5.6857228279,43.5342826843],"type":"Point"}
}