{
  "type": "Feature",
  "properties": {
    "addr:full":"Carr Concepcion Arenal, 8 Burjassot Valencia 46100",
    "addr:housenumber":"8",
    "addr:postcode":"46100",
    "addr:street":"Carr Concepcion Arenal",
    "iso:country":"ES",
    "sg:address":"Carr Concepcion Arenal, 8",
    "sg:city":"Burjassot",
    "sg:orig_category":"Molduras, Junquillos, Listones Y Molduras Perforadas",
    "sg:phone":"+34 963 90 25 14",
    "sg:postcode":"46100",
    "sg:province":"Valencia",
    "wof:name":"Fernandez Garcia Concepcion",
    "wof:placetype":"venue"
},
  "geometry": {"coordinates":[-0.4112899899,39.509601593],"type":"Point"}
}