{
  "type": "Feature",
  "properties": {
    "iso:country":"ES",
    "sg:address":"Pase Reding, 22",
    "sg:city":"Malaga",
    "sg:orig_category":"Centros P\u00dablicos De Formaci\u00d3n Profesional Y T\u00c9cnica",
    "sg:phone":"+34 952 60 34 60",
    "sg:postcode":"29016",
    "sg:province":"M\u00e1laga",
    "wof:name":"Colegio Abogados De Malaga",
    "wof:placetype":"venue"
},
  "geometry": {"coordinates":[-4.4081940651,36.7208480835],"type":"Point"}
}