{
  "type": "Feature",
  "properties": {
    "iso:country":"ES",
    "sg:address":"Calle de San Mateo, 22",
    "sg:city":"Madrid",
    "sg:orig_category":"M\u00c9dicos: Estomatolog\u00cda",
    "sg:phone":"+34 913 08 72 21",
    "sg:postcode":"28004",
    "sg:province":"Madrid",
    "wof:name":"Garcia Rodriguez Maria Dolores",
    "wof:placetype":"venue"
},
  "geometry": {"coordinates":[-3.6987979412,40.4256401062],"type":"Point"}
}