{
  "type": "Feature",
  "properties": {
    "iso:country":"ES",
    "sg:address":"Carr Robines, De, 16",
    "sg:city":"Binissalem",
    "sg:orig_category":"Inmobiliaria (agencias)",
    "sg:phone":"+34 971 88 62 58",
    "sg:postcode":"07350",
    "sg:province":"Islas Baleares",
    "wof:name":"Solivellas Mulet Loreto",
    "wof:placetype":"venue"
},
  "geometry": {"coordinates":[2.8436501026,39.6915512085],"type":"Point"}
}