{
  "type": "Feature",
  "properties": {
    "iso:country":"ES",
    "sg:address":"Carrer de Corsega, 496",
    "sg:city":"Barcelona",
    "sg:orig_category":"Psic\u00d3logos",
    "sg:phone":"+34 932 07 34 62",
    "sg:postcode":"08025",
    "sg:province":"Barcelona",
    "wof:name":"Vargas Sotelo Purificacion",
    "wof:placetype":"venue"
},
  "geometry": {"coordinates":[2.1701509953,41.4044952393],"type":"Point"}
}