{
  "type": "Feature",
  "properties": {
    "addr:full":"Avda Jesus Rescatado (de), 34 Cordoba C\u00f3rdoba 14007",
    "addr:housenumber":"34",
    "addr:postcode":"14007",
    "addr:street":"Avda Jesus Rescatado De;Co\u0301Rdoba",
    "iso:country":"ES",
    "sg:address":"Avda Jesus Rescatado (de), 34",
    "sg:city":"Cordoba",
    "sg:orig_category":"Ropa Para Se\u00d1oras (al Por Menor)",
    "sg:phone":"+34 957 44 20 90",
    "sg:postcode":"14007",
    "sg:province":"C\u00f3rdoba",
    "wof:name":"De Dios Montoro Maria Del Carmen",
    "wof:placetype":"venue"
},
  "geometry": {"coordinates":[-4.7598619461,37.8905258179],"type":"Point"}
}