{
  "type": "Feature",
  "properties": {
    "addr:full":"Pirineus (urb Rectoret), 22 Cunit Tarragona 43881",
    "addr:housenumber":"22",
    "addr:postcode":"43881",
    "addr:street":"Urb Rectoret",
    "iso:country":"ES",
    "sg:address":"Pirineus (urb Rectoret), 22",
    "sg:city":"Cunit",
    "sg:orig_category":"Promotores Constructores",
    "sg:phone":"+34 977 67 22 06",
    "sg:postcode":"43881",
    "sg:province":"Tarragona",
    "wof:name":"Laborda Talon Antonio",
    "wof:placetype":"venue"
},
  "geometry": {"coordinates":[1.6175450087,41.211730957],"type":"Point"}
}