{
  "type": "Feature",
  "properties": {
    "iso:country":"ES",
    "sg:address":"Calle de Borjas, 10",
    "sg:city":"Ciudad Real",
    "sg:orig_category":"Locales Y Clases De Danza",
    "sg:phone":"+34 926 22 31 84",
    "sg:postcode":"13002",
    "sg:province":"Ciudad Real",
    "sg:website":"www.centronavarrete.com",
    "wof:name":"Navarrete Perdices Consuelo",
    "wof:placetype":"venue"
},
  "geometry": {"coordinates":[-3.9393925667,38.9865455627],"type":"Point"}
}