{
  "type": "Feature",
  "properties": {
    "addr:full":"Las Higueras, 14 Tacoronte Santa Cruz De Tenerife 38350",
    "addr:housenumber":"14",
    "addr:postcode":"38350",
    "addr:street":"Las Higueras",
    "iso:country":"ES",
    "sg:address":"Las Higueras, 14",
    "sg:city":"Tacoronte",
    "sg:orig_category":"Centros Empresariales",
    "sg:phone":"+34 922 57 19 61",
    "sg:postcode":"38350",
    "sg:province":"Santa Cruz De Tenerife",
    "wof:name":"Comunicaciones Costa Norte S.l.",
    "wof:placetype":"venue"
},
  "geometry": {"coordinates":[-16.4136180878,28.4759502411],"type":"Point"}
}