{
  "type": "Feature",
  "properties": {
    "addr:full":"Calle de Jaime I, 52 Alaquas Valencia 46970",
    "addr:housenumber":"52",
    "addr:postcode":"46970",
    "addr:street":"Calle De Jaime I",
    "iso:country":"ES",
    "sg:address":"Calle de Jaime I, 52",
    "sg:city":"Alaquas",
    "sg:orig_category":"Venta, Montaje De Neum\u00c1ticos",
    "sg:phone":"+34 961 50 19 92",
    "sg:postcode":"46970",
    "sg:province":"Valencia",
    "wof:name":"Neumaticos Escudero S.l.",
    "wof:placetype":"venue"
},
  "geometry": {"coordinates":[-0.4578439891,39.4546356201],"type":"Point"}
}