{
  "type": "Feature",
  "properties": {
    "addr:full":"Calle de Pablo Sahun, 38 Barbastro Huesca 22300",
    "addr:housenumber":"38",
    "addr:postcode":"22300",
    "addr:street":"Calle De Pablo Sahun",
    "iso:country":"ES",
    "sg:address":"Calle de Pablo Sahun, 38",
    "sg:city":"Barbastro",
    "sg:orig_category":"Venta, Alquiler De Instrumentos Y Accesorios De M\u00dasica",
    "sg:phone":"+34 974 31 19 85",
    "sg:postcode":"22300",
    "sg:province":"Huesca",
    "wof:name":"Buil Lardies Juan Antonio",
    "wof:placetype":"venue"
},
  "geometry": {"coordinates":[0.1282729954,42.0353889465],"type":"Point"}
}