{
  "type": "Feature",
  "properties": {
    "iso:country":"ES",
    "sg:address":"Carrer de Salvador Espriu, 31",
    "sg:city":"Barcelona",
    "sg:orig_category":"Electricidad, Electr\u00d3nica: Material Y Suministros (al Por Mayor)",
    "sg:phone":"+34 932 21 28 90",
    "sg:postcode":"08005",
    "sg:province":"Barcelona",
    "wof:name":"Guerin S.a.",
    "wof:placetype":"venue"
},
  "geometry": {"coordinates":[2.197040081,41.388874054],"type":"Point"}
}