{
  "type": "Feature",
  "properties": {
    "addr:full":"Labradores, 25 Boadilla Madrid 28660",
    "addr:housenumber":"25",
    "addr:postcode":"28660",
    "addr:street":"Labradores",
    "iso:country":"ES",
    "sg:address":"Labradores, 25",
    "sg:city":"Boadilla",
    "sg:orig_category":"Cristaler\u00cdas",
    "sg:phone":"+34 914 63 11 02",
    "sg:postcode":"28660",
    "sg:province":"Madrid",
    "wof:name":"Abarca Vidrios Espa\u00f1a S.l.",
    "wof:placetype":"venue"
},
  "geometry": {"coordinates":[-3.849417,40.395027],"type":"Point"}
}