{
  "type": "Feature",
  "properties": {
    "iso:country":"ES",
    "sg:address":"Avda Sinforiano Madro\u00d1ero, 19",
    "sg:city":"Badajoz",
    "sg:orig_category":"Caf\u00c9s, Bares, Cervecer\u00cdas",
    "sg:phone":"+34 924 24 35 03",
    "sg:postcode":"06011",
    "sg:province":"Badajoz",
    "wof:name":"Habana Cafe",
    "wof:placetype":"venue"
},
  "geometry": {"coordinates":[-6.9875459671,38.8683853149],"type":"Point"}
}