{
  "type": "Feature",
  "properties": {
    "addr:full":"Calle de Remedios, 11 Fregenal Sierra Badajoz 06340",
    "addr:housenumber":"11",
    "addr:postcode":"06340",
    "addr:street":"Calle De Remedios",
    "iso:country":"ES",
    "sg:address":"Calle de Remedios, 11",
    "sg:city":"Fregenal Sierra",
    "sg:orig_category":"Cr\u00cda De Cerdos",
    "sg:phone":"+34 924 70 00 33",
    "sg:postcode":"06340",
    "sg:province":"Badajoz",
    "wof:name":"Agropecuaria Dehesa De Pajares S.a.",
    "wof:placetype":"venue"
},
  "geometry": {"coordinates":[-6.655155,38.170994],"type":"Point"}
}