{
  "type": "Feature",
  "properties": {
    "iso:country":"ES",
    "sg:address":"Calle de Angel Puech, 1",
    "sg:city":"Madrid",
    "sg:orig_category":"Carnicer\u00cdas, Carnicer\u00cdas",
    "sg:phone":"+34 913 11 54 93",
    "sg:postcode":"28039",
    "sg:province":"Madrid",
    "wof:name":"Martin Moreno Jose",
    "wof:placetype":"venue"
},
  "geometry": {"coordinates":[-3.7035262585,40.4634094238],"type":"Point"}
}