{
  "type": "Feature",
  "properties": {
    "iso:country":"ES",
    "sg:address":"Calle de Santa Engracia, 72",
    "sg:city":"Madrid",
    "sg:orig_category":"Centros De Coordinaci\u00d3n",
    "sg:phone":"+34 914 45 58 36",
    "sg:postcode":"28010",
    "sg:province":"Madrid",
    "wof:name":"Valiente Tiemblo Gonzalo",
    "wof:placetype":"venue"
},
  "geometry": {"coordinates":[-3.6993396282,40.436340332],"type":"Point"}
}