{
  "type": "Feature",
  "properties": {
    "addr:full":"Carrer de Miquel Romeu, 33 Hospitalet Llobregat Barcelona 08901",
    "addr:housenumber":"33",
    "addr:postcode":"08901",
    "addr:street":"Carrer De Miquel Romeu",
    "iso:country":"ES",
    "sg:address":"Carrer de Miquel Romeu, 33",
    "sg:city":"Hospitalet Llobregat",
    "sg:orig_category":"Relojer\u00cda (al Por Menor, Reparaci\u00d3n)",
    "sg:phone":"+34 933 38 07 95",
    "sg:postcode":"08901",
    "sg:province":"Barcelona",
    "wof:name":"Cuesta Belenguer Maria De Los Angeles",
    "wof:placetype":"venue"
},
  "geometry": {"coordinates":[2.1106278896,41.3618469238],"type":"Point"}
}