{
  "type": "Feature",
  "properties": {
    "iso:country":"ES",
    "sg:address":"Carrer de Rossello, 39",
    "sg:city":"Mataro",
    "sg:orig_category":"Comerciantes Al Por Mayor De Vinos, Licores Y Alcoholes",
    "sg:phone":"+34 937 98 12 91",
    "sg:postcode":"08303",
    "sg:province":"Barcelona",
    "wof:name":"Susana Mederos S.l.",
    "wof:placetype":"venue"
},
  "geometry": {"coordinates":[2.4250659943,41.5390472412],"type":"Point"}
}