{
  "type": "Feature",
  "properties": {
    "addr:full":"Pg Sant Jordi, 51 Mas Rampinyo Barcelona 08110",
    "addr:housenumber":"51",
    "addr:postcode":"08110",
    "addr:street":"Pg Sant Jordi",
    "iso:country":"ES",
    "sg:address":"Pg Sant Jordi, 51",
    "sg:city":"Mas Rampinyo",
    "sg:orig_category":"Electricidad: Equipos Industriales, Componentes (fabricaci\u00d3n)",
    "sg:phone":"+34 935 64 23 78",
    "sg:postcode":"08110",
    "sg:province":"Barcelona",
    "wof:name":"I.b.v.e. S.l.",
    "wof:placetype":"venue"
},
  "geometry": {"coordinates":[2.1776719093,41.49426651],"type":"Point"}
}