{
  "type": "Feature",
  "properties": {
    "iso:country":"ES",
    "sg:address":"Calle de Prudencio Morales, 67",
    "sg:city":"Palmas De Gran Canaria",
    "sg:orig_category":"Suministros Y Materiales Industriales",
    "sg:phone":"+34 928 46 04 48",
    "sg:postcode":"35009",
    "sg:province":"Las Palmas",
    "wof:name":"Gonzalez Perez Esther Lidia",
    "wof:placetype":"venue"
},
  "geometry": {"coordinates":[-15.4289999008,28.149389267],"type":"Point"}
}