{
  "type": "Feature",
  "properties": {
    "iso:country":"ES",
    "sg:address":"Calle de Sabino Arana, 4",
    "sg:city":"Amorebieta",
    "sg:orig_category":"Reposter\u00cdas",
    "sg:phone":"+34 946 73 29 51",
    "sg:postcode":"48340",
    "sg:province":"Vizcaya",
    "wof:name":"Garay Dudagitia Maria Teresa",
    "wof:placetype":"venue"
},
  "geometry": {"coordinates":[-2.7321588993,43.2210960388],"type":"Point"}
}