{
  "type": "Feature",
  "properties": {
    "iso:country":"ES",
    "sg:address":"Carrer de Borrasca, 25",
    "sg:city":"Monovar",
    "sg:orig_category":"Art\u00cdculos Funerarios (al Por Menor)",
    "sg:phone":"+34 965 47 10 19",
    "sg:postcode":"03640",
    "sg:province":"Alicante",
    "wof:name":"Unisanbel S.l.",
    "wof:placetype":"venue"
},
  "geometry": {"coordinates":[-0.8324480057,38.4382324219],"type":"Point"}
}