{
  "type": "Feature",
  "properties": {
    "iso:country":"ES",
    "sg:address":"Lizardi Kalea, 5",
    "sg:city":"Urnieta",
    "sg:orig_category":"Centros De Educaci\u00d3n Especial",
    "sg:phone":"+34 943 55 55 09",
    "sg:postcode":"20130",
    "sg:province":"Guip\u00f9zcoa",
    "wof:name":"Gobierno Vasco-eusko Jaurlaritza",
    "wof:placetype":"venue"
},
  "geometry": {"coordinates":[-1.9913799763,43.249797821],"type":"Point"}
}