{
  "type": "Feature",
  "properties": {
    "addr:full":"Plaz Espa\u00d1a (de), S/n Alcala Guadaira Sevilla 41500",
    "addr:housenumber":"s",
    "addr:postcode":"41500",
    "addr:street":"Plaz;/ N",
    "iso:country":"ES",
    "sg:address":"Plaz Espa\u00d1a (de), S/n",
    "sg:city":"Alcala Guadaira",
    "sg:orig_category":"Centros De Educaci\u00d3n Especial",
    "sg:phone":"+34 955 68 54 56",
    "sg:postcode":"41500",
    "sg:province":"Sevilla",
    "wof:name":"Junta De Andalucia",
    "wof:placetype":"venue"
},
  "geometry": {"coordinates":[-5.8398590088,37.3383140564],"type":"Point"}
}