{
  "type": "Feature",
  "properties": {
    "addr:full":"Carrer de Alcolea, 57 Barcelona Barcelona 08014",
    "addr:housenumber":"57",
    "addr:postcode":"08014",
    "addr:street":"Carrer De Alcolea",
    "iso:country":"ES",
    "sg:address":"Carrer de Alcolea, 57",
    "sg:city":"Barcelona",
    "sg:orig_category":"Serigraf\u00cda (material Y Suministros)",
    "sg:phone":"+34 934 91 42 00",
    "sg:postcode":"08014",
    "sg:province":"Barcelona",
    "wof:name":"Cesarini Fondevila Ernesto",
    "wof:placetype":"venue"
},
  "geometry": {"coordinates":[2.1361079216,41.3770751953],"type":"Point"}
}