{
  "type": "Feature",
  "properties": {
    "addr:full":"Calle de Sureres, 2 Valencia Valencia 46014",
    "addr:housenumber":"2",
    "addr:postcode":"46014",
    "addr:street":"Calle De Sureres",
    "iso:country":"ES",
    "sg:address":"Calle de Sureres, 2",
    "sg:city":"Valencia",
    "sg:orig_category":"Fisioterapia",
    "sg:phone":"+34 963 50 16 14",
    "sg:postcode":"46014",
    "sg:province":"Valencia",
    "wof:name":"Garcia Jesuardo Salvador Vicente",
    "wof:placetype":"venue"
},
  "geometry": {"coordinates":[-0.4129799902,39.4691543579],"type":"Point"}
}