{
  "type": "Feature",
  "properties": {
    "addr:full":"Calle de Francisco Vitoria, 23 Zaragoza Zaragoza 50008",
    "addr:housenumber":"23",
    "addr:postcode":"50008",
    "addr:street":"Calle De Francisco Vitoria",
    "iso:country":"ES",
    "sg:address":"Calle de Francisco Vitoria, 23",
    "sg:city":"Zaragoza",
    "sg:orig_category":"Centros Empresariales",
    "sg:phone":"+34 976 23 97 38",
    "sg:postcode":"50008",
    "sg:province":"Zaragoza",
    "sg:website":"www.centralfax.com",
    "wof:name":"Central Fax S.l.",
    "wof:placetype":"venue"
},
  "geometry": {"coordinates":[-0.8792570233,41.6455078125],"type":"Point"}
}