{
  "type": "Feature",
  "properties": {
    "addr:full":"Calle de Sur, 8 Molina Segura Murcia 30500",
    "addr:housenumber":"8",
    "addr:postcode":"30500",
    "addr:street":"Calle De Sur",
    "iso:country":"ES",
    "sg:address":"Calle de Sur, 8",
    "sg:city":"Molina Segura",
    "sg:orig_category":"Asociaciones Y Clubs Deportivos",
    "sg:phone":"+34 968 64 01 15",
    "sg:postcode":"30500",
    "sg:province":"Murcia",
    "wof:name":"Sanchez Barba Angel",
    "wof:placetype":"venue"
},
  "geometry": {"coordinates":[-1.2119740248,38.0535736084],"type":"Point"}
}