{
  "type": "Feature",
  "properties": {
    "addr:full":"Calle de Everardo Villamil, S/n Boal Asturias 33720",
    "addr:housenumber":"s / n",
    "addr:postcode":"33720",
    "addr:street":"Calle De Everardo Villamil",
    "iso:country":"ES",
    "sg:address":"Calle de Everardo Villamil, S/n",
    "sg:city":"Boal",
    "sg:orig_category":"Papeler\u00cdas, Librer\u00cdas",
    "sg:phone":"+34 985 62 05 94",
    "sg:postcode":"33720",
    "sg:province":"Asturias",
    "wof:name":"Sanzo Fernandez Pablo",
    "wof:placetype":"venue"
},
  "geometry": {"coordinates":[-6.8171257973,43.4296646118],"type":"Point"}
}