{
  "type": "Feature",
  "properties": {
    "addr:full":"Carrer de Bellesguard, 6 Cabrils Barcelona 08348",
    "addr:housenumber":"6",
    "addr:postcode":"08348",
    "addr:street":"Carrer De Bellesguard",
    "iso:country":"ES",
    "sg:address":"Carrer de Bellesguard, 6",
    "sg:city":"Cabrils",
    "sg:orig_category":"Inform\u00c1tica, Ofim\u00c1tica (estudios, Asesor\u00cda, Ingenier\u00cda, Formaci\u00d3n)",
    "sg:phone":"+34 937 53 21 69",
    "sg:postcode":"08348",
    "sg:province":"Barcelona",
    "sg:website":"www.straussmilligan.com",
    "wof:name":"Wtv Management Scp",
    "wof:placetype":"venue"
},
  "geometry": {"coordinates":[2.361082077,41.5254859924],"type":"Point"}
}