{
  "type": "Feature",
  "properties": {
    "addr:full":"Carr Son Sureda, 1 Pont D'inca Islas Baleares 07009",
    "addr:housenumber":"1",
    "addr:postcode":"07009",
    "addr:street":"Carr Son Sureda;Pont D'Inca",
    "iso:country":"ES",
    "sg:address":"Carr Son Sureda, 1",
    "sg:city":"Pont D'inca",
    "sg:orig_category":"Asociaciones Y Clubs Deportivos",
    "sg:phone":"+34 971 60 07 44",
    "sg:postcode":"07009",
    "sg:province":"Islas Baleares",
    "wof:name":"Gil Martin Antonio",
    "wof:placetype":"venue"
},
  "geometry": {"coordinates":[2.9117100239,39.6136398315],"type":"Point"}
}