{
  "type": "Feature",
  "properties": {
    "addr:full":"Calle de San Pablo, 6 Majadahonda Madrid 28220",
    "addr:housenumber":"6",
    "addr:postcode":"28220",
    "addr:street":"Calle De San Pablo",
    "iso:country":"ES",
    "sg:address":"Calle de San Pablo, 6",
    "sg:city":"Majadahonda",
    "sg:orig_category":"Carnicer\u00cdas, Carnicer\u00cdas",
    "sg:phone":"+34 916 38 20 50",
    "sg:postcode":"28220",
    "sg:province":"Madrid",
    "wof:name":"Perez Garcia Jose Luis",
    "wof:placetype":"venue"
},
  "geometry": {"coordinates":[-3.8759539127,40.4725570679],"type":"Point"}
}