{
  "type": "Feature",
  "properties": {
    "iso:country":"ES",
    "sg:address":"Calle de Ramiro I, 24",
    "sg:city":"Jaca",
    "sg:orig_category":"Grafistas",
    "sg:phone":"+34 974 35 60 22",
    "sg:postcode":"22700",
    "sg:province":"Huesca",
    "wof:name":"Rovira Guirao David",
    "wof:placetype":"venue"
},
  "geometry": {"coordinates":[-0.5513259768,42.5676231384],"type":"Point"}
}