{
  "type": "Feature",
  "properties": {
    "addr:full":"Avda Espa\u00d1a, S/n Caceres C\u00e1ceres 10002",
    "addr:housenumber":"s",
    "addr:postcode":"10002",
    "addr:street":"Avda Espan\u0303A;/ N;Ca\u0301Ceres",
    "iso:country":"ES",
    "sg:address":"Avda Espa\u00d1a, S/n",
    "sg:city":"Caceres",
    "sg:orig_category":"Electrodom\u00c9sticos (al Por Menor)",
    "sg:phone":"+34 927 22 66 00",
    "sg:postcode":"10002",
    "sg:province":"C\u00e1ceres",
    "wof:name":"Jose Luis Panadero S.a.",
    "wof:placetype":"venue"
},
  "geometry": {"coordinates":[-6.3773140907,39.4708747864],"type":"Point"}
}