{
  "type": "Feature",
  "properties": {
    "addr:full":"Avda Ciclista Mariano Rojas, S/n Ranero Murcia 30009",
    "addr:housenumber":"s / n",
    "addr:postcode":"30009",
    "addr:street":"Avda Ciclista Mariano Rojas",
    "iso:country":"ES",
    "sg:address":"Avda Ciclista Mariano Rojas, S/n",
    "sg:city":"Ranero",
    "sg:orig_category":"Mec\u00c1nico Del Autom\u00d3vil",
    "sg:phone":"+34 968 28 47 00",
    "sg:postcode":"30009",
    "sg:province":"Murcia",
    "wof:name":"Lopez Martinez Mariano",
    "wof:placetype":"venue"
},
  "geometry": {"coordinates":[-1.1528439522,37.9883460999],"type":"Point"}
}