{
  "type": "Feature",
  "properties": {
    "iso:country":"ES",
    "sg:address":"Calle de Tellez, 20",
    "sg:city":"Madrid",
    "sg:orig_category":"Cl\u00cdnicas Dentales",
    "sg:phone":"+34 914 33 76 53",
    "sg:postcode":"28007",
    "sg:province":"Madrid",
    "wof:name":"Guisado Moya Blanca Flora",
    "wof:placetype":"venue"
},
  "geometry": {"coordinates":[-3.680216074,40.4025154114],"type":"Point"}
}