{
  "type": "Feature",
  "properties": {
    "addr:full":"Calle de Brasil, 6 Gijon Asturias 33213",
    "addr:housenumber":"6",
    "addr:postcode":"33213",
    "addr:street":"Calle De Brasil",
    "iso:country":"ES",
    "sg:address":"Calle de Brasil, 6",
    "sg:city":"Gijon",
    "sg:orig_category":"Peluquer\u00cdas, Peluquer\u00cda Mixta",
    "sg:phone":"+34 985 31 59 76",
    "sg:postcode":"33213",
    "sg:province":"Asturias",
    "wof:name":"Gonzalez Perez Manuel",
    "wof:placetype":"venue"
},
  "geometry": {"coordinates":[-5.6980600357,43.5409965515],"type":"Point"}
}