{
  "type": "Feature",
  "properties": {
    "iso:country":"ES",
    "sg:address":"Calle de Don Jorge, 8",
    "sg:city":"Solana",
    "sg:orig_category":"Agentes Generales De Seguros",
    "sg:phone":"+34 926 63 43 02",
    "sg:postcode":"13240",
    "sg:province":"Ciudad Real",
    "wof:name":"Moreno Martin De Las Mulas Andres",
    "wof:placetype":"venue"
},
  "geometry": {"coordinates":[-3.2386026382,38.941028595],"type":"Point"}
}