{
  "type": "Feature",
  "properties": {
    "iso:country":"ES",
    "sg:address":"Cami Camp De L'empedrat, 7",
    "sg:city":"Almeda Mercader",
    "sg:orig_category":"Agencias Y Agentes Comerciales, Representantes",
    "sg:phone":"+34 934 74 65 14",
    "sg:postcode":"08940",
    "sg:province":"Barcelona",
    "wof:name":"Marques Martinez Hector",
    "wof:placetype":"venue"
},
  "geometry": {"coordinates":[2.0873317719,41.356136322],"type":"Point"}
}