{
  "type": "Feature",
  "properties": {
    "addr:full":"Ctra. Logro\u00f1o, Km. 0276,2 Luceni Zaragoza 50640",
    "addr:postcode":"50640",
    "addr:street":"Ctra. Logron\u0303O Km. 0276,2",
    "iso:country":"ES",
    "sg:address":"Ctra. Logro\u00f1o, Km. 0276,2",
    "sg:city":"Luceni",
    "sg:orig_category":"Estaciones De Servicio",
    "sg:phone":"+34 976 65 20 81",
    "sg:postcode":"50640",
    "sg:province":"Zaragoza",
    "wof:name":"Petrolaim S.l.",
    "wof:placetype":"venue"
},
  "geometry": {"coordinates":[-1.2420140505,41.8287811279],"type":"Point"}
}