{
  "type": "Feature",
  "properties": {
    "iso:country":"ES",
    "sg:address":"Carrer de Miquel Llor, 2",
    "sg:city":"Vic",
    "sg:orig_category":"Asociaciones Y Clubs Deportivos",
    "sg:phone":"+34 938 83 16 44",
    "sg:postcode":"08500",
    "sg:province":"Barcelona",
    "wof:name":"Fitness Vic Sl",
    "wof:placetype":"venue"
},
  "geometry": {"coordinates":[2.2439949512,41.9310760498],"type":"Point"}
}