{
  "type": "Feature",
  "properties": {
    "addr:full":"Carr Horts (dels), S/n Seros Lleida 25183",
    "addr:postcode":"25183",
    "addr:street":"Carr Horts Dels S / N Seros",
    "iso:country":"ES",
    "sg:address":"Carr Horts (dels), S/n",
    "sg:city":"Seros",
    "sg:orig_category":"Ense\u00d1anza, Formaci\u00d3n Profesional: Aprendizaje",
    "sg:phone":"+34 973 78 03 28",
    "sg:postcode":"25183",
    "sg:province":"Lleida",
    "wof:name":"Centre De Telecomunicaciones De Catalunya",
    "wof:placetype":"venue"
},
  "geometry": {"coordinates":[0.4135330021,41.4638633728],"type":"Point"}
}