{
  "type": "Feature",
  "properties": {
    "addr:full":"Calle de Manuel Aleixandre, 14 Madrid Madrid 28045",
    "addr:housenumber":"14",
    "addr:postcode":"madrid;28045",
    "addr:street":"Calle De Manuel Aleixandre",
    "iso:country":"ES",
    "sg:address":"Calle de Manuel Aleixandre, 14",
    "sg:city":"Madrid",
    "sg:orig_category":"Contenedores (mercanc\u00cdas)",
    "sg:phone":"+34 915 39 66 49",
    "sg:postcode":"28045",
    "sg:province":"Madrid",
    "wof:name":"Fletacar 3 S.l.",
    "wof:placetype":"venue"
},
  "geometry": {"coordinates":[-3.6933660507,40.3912162781],"type":"Point"}
}