{
  "type": "Feature",
  "properties": {
    "addr:full":"Carr Colon, 5 Moncada Valencia 46113",
    "addr:housenumber":"5",
    "addr:postcode":"46113",
    "addr:street":"Carr Colon",
    "iso:country":"ES",
    "sg:address":"Carr Colon, 5",
    "sg:city":"Moncada",
    "sg:orig_category":"Reposter\u00cdas",
    "sg:phone":"+34 961 39 13 01",
    "sg:postcode":"46113",
    "sg:province":"Valencia",
    "wof:name":"Bernabe Marques Vicente",
    "wof:placetype":"venue"
},
  "geometry": {"coordinates":[-0.3918629885,39.5469665527],"type":"Point"}
}