{
  "type": "Feature",
  "properties": {
    "addr:full":"A Poligono Industrial Cordovilla, 21 Cordovilla Navarra 31191",
    "addr:housenumber":"21",
    "addr:postcode":"31191",
    "addr:street":"Cordovilla",
    "iso:country":"ES",
    "sg:address":"A Poligono Industrial Cordovilla, 21",
    "sg:city":"Cordovilla",
    "sg:orig_category":"Pintura, Barniz, Productos Asimilables (fabricaci\u00d3n, Al Por Mayor)",
    "sg:phone":"+34 948 29 13 89",
    "sg:postcode":"31191",
    "sg:province":"Navarra",
    "wof:name":"Esber S.a.",
    "wof:placetype":"venue"
},
  "geometry": {"coordinates":[-1.6518089771,42.7533912659],"type":"Point"}
}