{
  "type": "Feature",
  "properties": {
    "addr:full":"Av Rey De Espa\u00f1a (p E Espartal), S/n Espartinas Sevilla 41807",
    "addr:housenumber":"s / n",
    "addr:postcode":"41807",
    "addr:street":"Av Rey;Espartal",
    "iso:country":"ES",
    "sg:address":"Av Rey De Espa\u00f1a (p E Espartal), S/n",
    "sg:city":"Espartinas",
    "sg:orig_category":"Caf\u00c9s, Bares, Cervecer\u00cdas",
    "sg:phone":"+34 955 71 37 45",
    "sg:postcode":"41807",
    "sg:province":"Sevilla",
    "wof:name":"Coffe & Baguettes S.l.",
    "wof:placetype":"venue"
},
  "geometry": {"coordinates":[-6.1235818863,37.3828926086],"type":"Point"}
}