{
  "type": "Feature",
  "properties": {
    "iso:country":"ES",
    "sg:address":"Calle de Pedro Casti\u00d1eiras, S/n",
    "sg:city":"Ortigueira",
    "sg:orig_category":"Centros De Educaci\u00d3n Especial",
    "sg:phone":"+34 981 40 08 04",
    "sg:postcode":"15330",
    "sg:province":"La Coru\u00f1a",
    "wof:name":"Colexio E.i.p. Jose Maria Lage",
    "wof:placetype":"venue"
},
  "geometry": {"coordinates":[-7.8530597687,43.6817398071],"type":"Point"}
}