{
  "type": "Feature",
  "properties": {
    "iso:country":"ES",
    "sg:address":"Fuencaliente, S/n",
    "sg:city":"Taco",
    "sg:orig_category":"Fabricaci\u00d3n, Importaci\u00d3n, Venta De Material De Telefon\u00cda, Peritelefon\u00cda",
    "sg:phone":"+34 922 82 18 05",
    "sg:postcode":"38108",
    "sg:province":"Santa Cruz De Tenerife",
    "wof:name":"Puerta Diaz Miguel",
    "wof:placetype":"venue"
},
  "geometry": {"coordinates":[-16.2957706451,28.4491081238],"type":"Point"}
}