{
  "type": "Feature",
  "properties": {
    "iso:country":"ES",
    "sg:address":"Ctra Castellon, S/n",
    "sg:city":"Sant Mateu",
    "sg:orig_category":"Freidur\u00cdas",
    "sg:phone":"+34 964 41 62 20",
    "sg:postcode":"12170",
    "sg:province":"Castell\u00f3n",
    "wof:name":"Productos Geysel S.l.",
    "wof:placetype":"venue"
},
  "geometry": {"coordinates":[0.1794400066,40.467414856],"type":"Point"}
}