{
  "type": "Feature",
  "properties": {
    "iso:country":"ES",
    "sg:address":"Calle de Montevideo, 11",
    "sg:city":"Malaga",
    "sg:orig_category":"Textil",
    "sg:phone":"+34 952 36 07 06",
    "sg:postcode":"29006",
    "sg:province":"M\u00e1laga",
    "wof:name":"Bordados Industriales Del Sur S.l.",
    "wof:placetype":"venue"
},
  "geometry": {"coordinates":[-4.4729628563,36.7118301392],"type":"Point"}
}