{
  "type": "Feature",
  "properties": {
    "addr:full":"Calle de Artesanos, 1 Velez-malaga M\u00e1laga 29700",
    "addr:housenumber":"1",
    "addr:postcode":"29700",
    "addr:street":"Calle De Artesanos",
    "iso:country":"ES",
    "sg:address":"Calle de Artesanos, 1",
    "sg:city":"Velez-malaga",
    "sg:orig_category":"Sales (al Por Mayor)",
    "sg:phone":"+34 952 54 91 24",
    "sg:postcode":"29700",
    "sg:province":"M\u00e1laga",
    "wof:name":"Pinturas Menape S.l.",
    "wof:placetype":"venue"
},
  "geometry": {"coordinates":[-4.0973520279,36.7773094177],"type":"Point"}
}