{
  "type": "Feature",
  "properties": {
    "addr:full":"Calle de La Ba\u00d1eza, 12 Madrid Madrid 28029",
    "addr:housenumber":"12",
    "addr:postcode":"madrid;28029",
    "addr:street":"Calle De La Ban\u0303Eza",
    "iso:country":"ES",
    "sg:address":"Calle de La Ba\u00d1eza, 12",
    "sg:city":"Madrid",
    "sg:orig_category":"Molduras, Junquillos, Listones Y Molduras Perforadas",
    "sg:phone":"+34 913 73 14 67",
    "sg:postcode":"28029",
    "sg:province":"Madrid",
    "wof:name":"San Jose Martin Amador",
    "wof:placetype":"venue"
},
  "geometry": {"coordinates":[-3.7138869762,40.4763069153],"type":"Point"}
}