{
  "type": "Feature",
  "properties": {
    "iso:country":"ES",
    "sg:address":"Carr Sant Francesc De Borja, 49",
    "sg:city":"Gandia",
    "sg:orig_category":"M\u00c9dicos: Pediatr\u00cda. Enfermedades De Los Ni\u00d1os",
    "sg:phone":"+34 962 87 08 56",
    "sg:postcode":"46700",
    "sg:province":"Valencia",
    "wof:name":"Sequi Canet Jose Miguel",
    "wof:placetype":"venue"
},
  "geometry": {"coordinates":[-0.1913339943,38.960735321],"type":"Point"}
}