{
  "type": "Feature",
  "properties": {
    "iso:country":"ES",
    "sg:address":"Calle de Gonzalo De Ocampo, 11",
    "sg:city":"Trujillo",
    "sg:orig_category":"Asociaciones Y Clubs Deportivos",
    "sg:phone":"+34 927 32 32 15",
    "sg:postcode":"10200",
    "sg:province":"C\u00e1ceres",
    "wof:name":"Fernandez Mu\u00f1oz Maria Luz",
    "wof:placetype":"venue"
},
  "geometry": {"coordinates":[-5.8774061203,39.4595375061],"type":"Point"}
}