{
  "type": "Feature",
  "properties": {
    "iso:country":"ES",
    "sg:address":"Avda Mirat, 12",
    "sg:city":"Salamanca",
    "sg:orig_category":"Ingenier\u00cda, Centros De Estudios (diversos)",
    "sg:phone":"+34 923 24 63 72",
    "sg:postcode":"37005",
    "sg:province":"Salamanca",
    "wof:name":"Delgado Terron Carlos",
    "wof:placetype":"venue"
},
  "geometry": {"coordinates":[-5.6602759361,40.9693756104],"type":"Point"}
}