{
  "type": "Feature",
  "properties": {
    "addr:full":"Carr. De Archidona Salinas, S/n Archidona M\u00e1laga 29300",
    "addr:housenumber":"s / n",
    "addr:postcode":"29300",
    "addr:street":"Carr. De Archidona Salinas;Ma\u0301Laga",
    "iso:country":"ES",
    "sg:address":"Carr. De Archidona Salinas, S/n",
    "sg:city":"Archidona",
    "sg:orig_category":"Promotores Constructores",
    "sg:phone":"+34 952 71 70 50",
    "sg:postcode":"29300",
    "sg:province":"M\u00e1laga",
    "wof:name":"Aguila Caballero Alberto",
    "wof:placetype":"venue"
},
  "geometry": {"coordinates":[-4.3770704269,37.1096076965],"type":"Point"}
}