{
  "type": "Feature",
  "properties": {
    "iso:country":"ES",
    "sg:address":"Calle de Corredera, 264",
    "sg:city":"Viso Del Alcor",
    "sg:orig_category":"Alquiler De V\u00cddeo",
    "sg:phone":"+34 955 74 07 70",
    "sg:postcode":"41520",
    "sg:province":"Sevilla",
    "wof:name":"Martin Vilches Juan Antonio",
    "wof:placetype":"venue"
},
  "geometry": {"coordinates":[-5.718146801,37.3919029236],"type":"Point"}
}