{
  "type": "Feature",
  "properties": {
    "iso:country":"ES",
    "sg:address":"Barr Rua Nova, 11",
    "sg:city":"Rua Nova",
    "sg:orig_category":"Caf\u00c9s, Bares, Cervecer\u00cdas",
    "sg:phone":"+34 982 56 16 07",
    "sg:postcode":"27850",
    "sg:province":"Lugo",
    "wof:name":"Maria Isabel Basanta Cabeza",
    "wof:placetype":"venue"
},
  "geometry": {"coordinates":[-7.5959348679,43.6629714966],"type":"Point"}
}