{
  "type": "Feature",
  "properties": {
    "iso:country":"ES",
    "sg:address":"Carrer de Santalo, 88",
    "sg:city":"Barcelona",
    "sg:orig_category":"Asesores De Gesti\u00d3n Del Patrimonio",
    "sg:phone":"+34 932 00 49 88",
    "sg:postcode":"08021",
    "sg:province":"Barcelona",
    "wof:name":"Tronc S.a.",
    "wof:placetype":"venue"
},
  "geometry": {"coordinates":[2.1433830261,41.3977622986],"type":"Point"}
}