{
  "type": "Feature",
  "properties": {
    "iso:country":"ES",
    "sg:address":"Calle de Veintinueve De Abril, 67",
    "sg:city":"Palmas De Gran Canaria",
    "sg:orig_category":"Bisuter\u00cda, Joyer\u00cda, Relojer\u00cda (al Por Menor)",
    "sg:phone":"+34 928 26 24 48",
    "sg:postcode":"35007",
    "sg:province":"Las Palmas",
    "wof:name":"Suarez Perez Hugo",
    "wof:placetype":"venue"
},
  "geometry": {"coordinates":[-15.4325895309,28.1411476135],"type":"Point"}
}