{
  "type": "Feature",
  "properties": {
    "iso:country":"ES",
    "sg:address":"Calle de Cervantes, 4",
    "sg:city":"Toboso",
    "sg:orig_category":"Farmacias",
    "sg:phone":"+34 925 19 70 45",
    "sg:postcode":"45820",
    "sg:province":"Toledo",
    "wof:name":"Ortiz Lozano Jose Luis",
    "wof:placetype":"venue"
},
  "geometry": {"coordinates":[-2.9962480068,39.5124855042],"type":"Point"}
}