{
  "type": "Feature",
  "properties": {
    "addr:full":"Carrer de Consell De Cent, 617 Barcelona Barcelona 08026",
    "addr:housenumber":"617",
    "addr:postcode":"08026",
    "addr:street":"Carrer De Consell De Cent",
    "iso:country":"ES",
    "sg:address":"Carrer de Consell De Cent, 617",
    "sg:city":"Barcelona",
    "sg:orig_category":"Droguer\u00cdas (al Por Menor)",
    "sg:phone":"+34 932 31 26 16",
    "sg:postcode":"08026",
    "sg:province":"Barcelona",
    "wof:name":"Mitja Pascual Eduardo",
    "wof:placetype":"venue"
},
  "geometry": {"coordinates":[2.1858010292,41.4063568115],"type":"Point"}
}