{
  "type": "Feature",
  "properties": {
    "addr:full":"Avda Betanzos, 63 Madrid Madrid 28029",
    "addr:housenumber":"63",
    "addr:postcode":"madrid;28029",
    "addr:street":"Avda Betanzos",
    "iso:country":"ES",
    "sg:address":"Avda Betanzos, 63",
    "sg:city":"Madrid",
    "sg:orig_category":"Ropa Para Se\u00d1oras (al Por Menor)",
    "sg:phone":"+34 913 86 29 70",
    "sg:postcode":"28029",
    "sg:province":"Madrid",
    "wof:name":"Burgue\u00f1o Cerme\u00f1o Amancio",
    "wof:placetype":"venue"
},
  "geometry": {"coordinates":[-3.7125849724,40.4786491394],"type":"Point"}
}