{
  "type": "Feature",
  "properties": {
    "iso:country":"ES",
    "sg:address":"Calle de General Prim, 66",
    "sg:city":"Alcala Guadaira",
    "sg:orig_category":"Venta, Colocaci\u00d3n, Reparaci\u00d3n De Parabrisas, Techos Descapotables",
    "sg:phone":"+34 955 61 58 97",
    "sg:postcode":"41500",
    "sg:province":"Sevilla",
    "sg:website":"www.autocristalsevilla.com",
    "wof:name":"Grupo Autocristal Repair S.l.",
    "wof:placetype":"venue"
},
  "geometry": {"coordinates":[-5.8384561539,37.3441543579],"type":"Point"}
}