{
  "type": "Feature",
  "properties": {
    "iso:country":"ES",
    "sg:address":"Calle de San Fernando, S/n",
    "sg:city":"Torrejon Ardoz",
    "sg:orig_category":"Centros De Educaci\u00d3n Especial",
    "sg:phone":"+34 916 78 00 48",
    "sg:postcode":"28850",
    "sg:province":"Madrid",
    "wof:name":"Cepa Buen Gobernador",
    "wof:placetype":"venue"
},
  "geometry": {"coordinates":[-3.4892089367,40.4613685608],"type":"Point"}
}