{
  "type": "Feature",
  "properties": {
    "iso:country":"ES",
    "sg:address":"Calle de Pilar (del), 23",
    "sg:city":"San Sebastian De Los Reyes",
    "sg:orig_category":"Limpieza De Alfombras",
    "sg:phone":"+34 916 54 84 42",
    "sg:postcode":"28700",
    "sg:province":"Madrid",
    "wof:name":"Garcia Fernandez Javier",
    "wof:placetype":"venue"
},
  "geometry": {"coordinates":[-3.6286830902,40.5475616455],"type":"Point"}
}