{
  "type": "Feature",
  "properties": {
    "addr:full":"Rua Faustino Santalices, 35 Bande Ourense 32840",
    "addr:housenumber":"35",
    "addr:postcode":"32840",
    "addr:street":"Rua Faustino Santalices",
    "iso:country":"ES",
    "sg:address":"Rua Faustino Santalices, 35",
    "sg:city":"Bande",
    "sg:orig_category":"Promotores Constructores",
    "sg:phone":"+34 988 44 31 05",
    "sg:postcode":"32840",
    "sg:province":"Ourense",
    "wof:name":"Conyel S.l.",
    "wof:placetype":"venue"
},
  "geometry": {"coordinates":[-7.9769148827,42.0334396362],"type":"Point"}
}