{
  "type": "Feature",
  "properties": {
    "addr:full":"Calle de Sanchez Ramade, 3 Linares Ja\u00e9n 23700",
    "addr:housenumber":"3",
    "addr:postcode":"23700",
    "addr:street":"Calle De Sanchez Ramade;Jae\u0301N",
    "iso:country":"ES",
    "sg:address":"Calle de Sanchez Ramade, 3",
    "sg:city":"Linares",
    "sg:orig_category":"Ense\u00d1anza Variada",
    "sg:phone":"+34 953 60 13 49",
    "sg:postcode":"23700",
    "sg:province":"Ja\u00e9n",
    "wof:name":"Abu-helaiel Jadallah Khader Faiez",
    "wof:placetype":"venue"
},
  "geometry": {"coordinates":[-3.630937,38.093048],"type":"Point"}
}