{
  "type": "Feature",
  "properties": {
    "addr:full":"Calle de Bellver, 20 Madrid Madrid 28039",
    "addr:housenumber":"20",
    "addr:postcode":"madrid;28039",
    "addr:street":"Calle De Bellver",
    "iso:country":"ES",
    "sg:address":"Calle de Bellver, 20",
    "sg:city":"Madrid",
    "sg:orig_category":"Servicios De Telecomunicaciones",
    "sg:phone":"+34 914 50 44 17",
    "sg:postcode":"28039",
    "sg:province":"Madrid",
    "sg:website":"www.impactware.com",
    "wof:name":"Inpactware Y Comm.s.l",
    "wof:placetype":"venue"
},
  "geometry": {"coordinates":[-3.7048492432,40.4628448486],"type":"Point"}
}