{
  "type": "Feature",
  "properties": {
    "iso:country":"ES",
    "sg:address":"Rua Norte, 5",
    "sg:city":"Ribadavia",
    "sg:orig_category":"Alimentaci\u00d3n General (al Por Menor)",
    "sg:phone":"+34 988 47 00 72",
    "sg:postcode":"32400",
    "sg:province":"Ourense",
    "wof:name":"Morgade Martinez Manuela",
    "wof:placetype":"venue"
},
  "geometry": {"coordinates":[-8.1429386139,42.2902145386],"type":"Point"}
}