{
  "type": "Feature",
  "properties": {
    "addr:full":"Carrer de Vinya, 2 Barcelona Barcelona 08041",
    "addr:housenumber":"2",
    "addr:postcode":"08041",
    "addr:street":"Carrer De Vinya",
    "iso:country":"ES",
    "sg:address":"Carrer de Vinya, 2",
    "sg:city":"Barcelona",
    "sg:orig_category":"Electrodom\u00c9sticos (al Por Menor)",
    "sg:phone":"+34 934 55 41 41",
    "sg:postcode":"08041",
    "sg:province":"Barcelona",
    "wof:name":"Vidal Domenech Juan",
    "wof:placetype":"venue"
},
  "geometry": {"coordinates":[2.1787331104,41.4180526733],"type":"Point"}
}