{
  "type": "Feature",
  "properties": {
    "addr:full":"Carrer de Pi I Margall, 66 Castellbisbal Barcelona 08755",
    "addr:housenumber":"66",
    "addr:postcode":"08755",
    "addr:street":"Carrer De Pi I Margall",
    "iso:country":"ES",
    "sg:address":"Carrer de Pi I Margall, 66",
    "sg:city":"Castellbisbal",
    "sg:orig_category":"Centros Empresariales",
    "sg:phone":"+34 937 72 12 58",
    "sg:postcode":"08755",
    "sg:province":"Barcelona",
    "wof:name":"Castell Gestio S.c.c.l.",
    "wof:placetype":"venue"
},
  "geometry": {"coordinates":[1.979279995,41.4734191895],"type":"Point"}
}