{
  "type": "Feature",
  "properties": {
    "iso:country":"ES",
    "sg:address":"Ctra Madrid Ciudad Real, Km. 0097,9",
    "sg:city":"Sonseca",
    "sg:orig_category":"Fabricaci\u00d3n De Su\u00c9ters Y Chalecos De Punto",
    "sg:phone":"+34 925 38 16 30",
    "sg:postcode":"45100",
    "sg:province":"Toledo",
    "wof:name":"Dise\u00f1os Gumar S.l.",
    "wof:placetype":"venue"
},
  "geometry": {"coordinates":[-3.9706120491,39.6791915894],"type":"Point"}
}