{
  "type": "Feature",
  "properties": {
    "addr:full":"Calle de Zabaleta, 30 Madrid Madrid 28002",
    "addr:housenumber":"30",
    "addr:postcode":"madrid;28002",
    "addr:street":"Calle De Zabaleta",
    "iso:country":"ES",
    "sg:address":"Calle de Zabaleta, 30",
    "sg:city":"Madrid",
    "sg:orig_category":"Deportes Diversos",
    "sg:phone":"+34 915 10 20 36",
    "sg:postcode":"28002",
    "sg:province":"Madrid",
    "wof:name":"W.u.tang Madrid S.a.l.",
    "wof:placetype":"venue"
},
  "geometry": {"coordinates":[-3.6732301712,40.4425315857],"type":"Point"}
}