{
  "type": "Feature",
  "properties": {
    "iso:country":"ES",
    "sg:address":"Avda Mar, 57",
    "sg:city":"Xara",
    "sg:orig_category":"Maquinaria Para Industrias Diversas",
    "sg:phone":"+34 966 42 33 82",
    "sg:postcode":"03700",
    "sg:province":"Alicante",
    "wof:name":"Lino Rosello S.l.",
    "wof:placetype":"venue"
},
  "geometry": {"coordinates":[0.1039630026,38.8354949951],"type":"Point"}
}