{
  "type": "Feature",
  "properties": {
    "addr:full":"Carr Mossen Anton, 75 Badalona Barcelona 08912",
    "addr:housenumber":"75",
    "addr:postcode":"08912",
    "addr:street":"Carr Mossen Anton",
    "iso:country":"ES",
    "sg:address":"Carr Mossen Anton, 75",
    "sg:city":"Badalona",
    "sg:orig_category":"Asociaciones Humanitarias, De Cooperaci\u00d3n, De Acci\u00d3n Social",
    "sg:phone":"+34 934 64 34 09",
    "sg:postcode":"08912",
    "sg:province":"Barcelona",
    "wof:name":"Associacio De Familiars De Malalts D'alzheimer De Badalona Santa Coloma I Sant Adria",
    "wof:placetype":"venue"
},
  "geometry": {"coordinates":[2.2465150356,41.4448623657],"type":"Point"}
}