{
  "type": "Feature",
  "properties": {
    "addr:full":"Calle de Azalea (de La), 275 Alcobendas Madrid 28109",
    "addr:housenumber":"275",
    "addr:postcode":"28109",
    "addr:street":"Calle De Azalea De La",
    "iso:country":"ES",
    "sg:address":"Calle de Azalea (de La), 275",
    "sg:city":"Alcobendas",
    "sg:orig_category":"Arquitectos",
    "sg:phone":"+34 916 25 05 57",
    "sg:postcode":"28109",
    "sg:province":"Madrid",
    "wof:name":"Valero De La Parra Francisco",
    "wof:placetype":"venue"
},
  "geometry": {"coordinates":[-3.6468091011,40.5241317749],"type":"Point"}
}