{
  "type": "Feature",
  "properties": {
    "addr:full":"Cra. Sant Sadurni D'anoia, Km. 0009,8 Vilafranca Penedes Barcelona 08720",
    "addr:postcode":"08720",
    "addr:street":"Sadurni D'Anoia Km. 0009,8 Vilafranca;Barcelona",
    "iso:country":"ES",
    "sg:address":"Cra. Sant Sadurni D'anoia, Km. 0009,8",
    "sg:city":"Vilafranca Penedes",
    "sg:orig_category":"Animales: Material Y Suministros Para (fabricaci\u00d3n, Al Por Mayor)",
    "sg:phone":"+34 938 92 20 69",
    "sg:postcode":"08720",
    "sg:province":"Barcelona",
    "sg:website":"www.tigsa.com",
    "wof:name":"Tecnica E Innovaciones Ganaderas S. A.",
    "wof:placetype":"venue"
},
  "geometry": {"coordinates":[2.1699187756,41.3879165649],"type":"Point"}
}