{
  "type": "Feature",
  "properties": {
    "addr:full":"Av Matadepera, 172 Sabadell Barcelona 08207",
    "addr:housenumber":"172",
    "addr:postcode":"08207",
    "addr:street":"Av Matadepera",
    "iso:country":"ES",
    "sg:address":"Av Matadepera, 172",
    "sg:city":"Sabadell",
    "sg:orig_category":"Bisuter\u00cda, Joyer\u00cda, Relojer\u00cda (al Por Menor)",
    "sg:phone":"+34 937 16 39 85",
    "sg:postcode":"08207",
    "sg:province":"Barcelona",
    "sg:website":"www.joyeriarelojeriavilort.com",
    "wof:name":"Jaen Ortega Francisco",
    "wof:placetype":"venue"
},
  "geometry": {"coordinates":[2.0864388943,41.5688819885],"type":"Point"}
}