{
  "type": "Feature",
  "properties": {
    "addr:full":"Trva Salto Del Caballo, 3 Toledo Toledo 45003",
    "addr:housenumber":"3",
    "addr:postcode":"45003",
    "addr:street":"Trva Salto Del Caballo",
    "iso:country":"ES",
    "sg:address":"Trva Salto Del Caballo, 3",
    "sg:city":"Toledo",
    "sg:orig_category":"Abogados",
    "sg:phone":"+34 925 21 07 64",
    "sg:postcode":"45003",
    "sg:province":"Toledo",
    "wof:name":"Lopez-rey Garcia-rojo Santiago",
    "wof:placetype":"venue"
},
  "geometry": {"coordinates":[-4.0207929611,39.865562439],"type":"Point"}
}