{
  "type": "Feature",
  "properties": {
    "addr:full":"Calle de Feria, 159 Sevilla Sevilla 41002",
    "addr:housenumber":"159",
    "addr:postcode":"41002",
    "addr:street":"Calle De Feria",
    "iso:country":"ES",
    "sg:address":"Calle de Feria, 159",
    "sg:city":"Sevilla",
    "sg:orig_category":"Muebles, Minoristas",
    "sg:phone":"+34 954 37 07 34",
    "sg:postcode":"41002",
    "sg:province":"Sevilla",
    "wof:name":"Feria Del Mueble Sl",
    "wof:placetype":"venue"
},
  "geometry": {"coordinates":[-5.9918479919,37.4026374817],"type":"Point"}
}