{
  "type": "Feature",
  "properties": {
    "iso:country":"ES",
    "sg:address":"Calle de Constitucion (de La), 108",
    "sg:city":"Alcobendas",
    "sg:orig_category":"Papeler\u00cdas, Librer\u00cdas",
    "sg:phone":"+34 916 51 72 30",
    "sg:postcode":"28100",
    "sg:province":"Madrid",
    "wof:name":"Morales Megias Rosario",
    "wof:placetype":"venue"
},
  "geometry": {"coordinates":[-3.6456542015,40.5475997925],"type":"Point"}
}