{
  "type": "Feature",
  "properties": {
    "iso:country":"ES",
    "sg:address":"Calle de Mayor, 1",
    "sg:city":"Villabona",
    "sg:orig_category":"M\u00c9dicos: Estomatolog\u00cda",
    "sg:phone":"+34 943 69 17 19",
    "sg:postcode":"20150",
    "sg:province":"Guip\u00f9zcoa",
    "wof:name":"Elisabet Aguirrebengoa Ibarguren",
    "wof:placetype":"venue"
},
  "geometry": {"coordinates":[-2.0527589321,43.186000824],"type":"Point"}
}