{
  "type": "Feature",
  "properties": {
    "iso:country":"ES",
    "sg:address":"Calle de Tantin, 11",
    "sg:city":"Santander",
    "sg:orig_category":"Promotores Constructores",
    "sg:phone":"+34 942 21 22 47",
    "sg:postcode":"39001",
    "sg:province":"Cantabria",
    "wof:name":"Bericht Stern Fomento Y Construccion S.l.",
    "wof:placetype":"venue"
},
  "geometry": {"coordinates":[-3.8070230484,43.4644508362],"type":"Point"}
}