{
  "type": "Feature",
  "properties": {
    "addr:full":"Calle de Real, 38 Linea De La Concepcion C\u00e1diz 11300",
    "addr:housenumber":"38",
    "addr:postcode":"11300",
    "addr:street":"Calle De Real;Ca\u0301Diz",
    "iso:country":"ES",
    "sg:address":"Calle de Real, 38",
    "sg:city":"Linea De La Concepcion",
    "sg:orig_category":"Cajas De Ahorro",
    "sg:phone":"+34 956 17 66 90",
    "sg:postcode":"11300",
    "sg:province":"C\u00e1diz",
    "sg:website":"www.unicaja.es",
    "wof:name":"Unicaja",
    "wof:placetype":"venue"
},
  "geometry": {"coordinates":[-5.3506669998,36.1621360779],"type":"Point"}
}