{
  "type": "Feature",
  "properties": {
    "addr:full":"Calle de Bekoetxe, 3 Zaldibar Vizcaya 48250",
    "addr:housenumber":"3",
    "addr:postcode":"48250",
    "addr:street":"Calle De Bekoetxe",
    "iso:country":"ES",
    "sg:address":"Calle de Bekoetxe, 3",
    "sg:city":"Zaldibar",
    "sg:orig_category":"Farmacias",
    "sg:phone":"+34 946 82 70 83",
    "sg:postcode":"48250",
    "sg:province":"Vizcaya",
    "wof:name":"Ega\u00f1a Garita Goitia Elisabete",
    "wof:placetype":"venue"
},
  "geometry": {"coordinates":[-2.5463116169,43.170249939],"type":"Point"}
}