{
  "type": "Feature",
  "properties": {
    "addr:full":"Calle de Sangenis, 50 Zaragoza Zaragoza 50010",
    "addr:housenumber":"50",
    "addr:postcode":"50010",
    "addr:street":"Calle De Sangenis",
    "iso:country":"ES",
    "sg:address":"Calle de Sangenis, 50",
    "sg:city":"Zaragoza",
    "sg:orig_category":"Equipo De Refrigeraci\u00d3n Industrial",
    "sg:phone":"+34 976 53 86 79",
    "sg:postcode":"50010",
    "sg:province":"Zaragoza",
    "wof:name":"Ara Navarro Oscar",
    "wof:placetype":"venue"
},
  "geometry": {"coordinates":[-0.90362221,41.650680542],"type":"Point"}
}