{
  "type": "Feature",
  "properties": {
    "iso:country":"ES",
    "sg:address":"Pl Porta Pintada, 1",
    "sg:city":"Palma",
    "sg:orig_category":"Alimentaci\u00d3n General (al Por Menor)",
    "sg:phone":"+34 971 72 07 48",
    "sg:postcode":"07002",
    "sg:province":"Islas Baleares",
    "wof:name":"Son Vivot S.l.",
    "wof:placetype":"venue"
},
  "geometry": {"coordinates":[2.6524689198,39.575138092],"type":"Point"}
}