{
  "type": "Feature",
  "properties": {
    "addr:full":"Los Rosales, S/n Mairena Aljarafe Sevilla 41927",
    "addr:housenumber":"/ n",
    "addr:postcode":"41927",
    "addr:street":"Los Rosales S",
    "iso:country":"ES",
    "sg:address":"Los Rosales, S/n",
    "sg:city":"Mairena Aljarafe",
    "sg:orig_category":"Ense\u00d1anza Superior Privada",
    "sg:phone":"+34 954 48 58 88",
    "sg:postcode":"41927",
    "sg:province":"Sevilla",
    "wof:name":"Fundacion Publica Colegio Mayor Maese Rodrigo",
    "wof:placetype":"venue"
},
  "geometry": {"coordinates":[-6.0544991493,37.3526382446],"type":"Point"}
}