{
  "type": "Feature",
  "properties": {
    "addr:full":"Plaz Autonomia (de La), 4 Andujar Ja\u00e9n 23740",
    "addr:postcode":"23740",
    "addr:street":"Jae\u0301N",
    "iso:country":"ES",
    "sg:address":"Plaz Autonomia (de La), 4",
    "sg:city":"Andujar",
    "sg:orig_category":"Zapatos (al Por Menor)",
    "sg:phone":"+34 953 51 02 29",
    "sg:postcode":"23740",
    "sg:province":"Ja\u00e9n",
    "wof:name":"Criado Garcia Eduardo",
    "wof:placetype":"venue"
},
  "geometry": {"coordinates":[-4.0551371574,38.0401306152],"type":"Point"}
}