{
  "type": "Feature",
  "properties": {
    "addr:full":"Calle de Rey (del), 74 Aranjuez Madrid 28300",
    "addr:housenumber":"74",
    "addr:postcode":"28300",
    "addr:street":"Calle De Rey Del",
    "iso:country":"ES",
    "sg:address":"Calle de Rey (del), 74",
    "sg:city":"Aranjuez",
    "sg:orig_category":"Inversiones",
    "sg:phone":"+34 918 92 32 21",
    "sg:postcode":"28300",
    "sg:province":"Madrid",
    "wof:name":"Analisis De Inversiones Castellana",
    "wof:placetype":"venue"
},
  "geometry": {"coordinates":[-3.6003854275,40.0322723389],"type":"Point"}
}