{
  "type": "Feature",
  "properties": {
    "iso:country":"ES",
    "sg:address":"Carrer de Eduard Toda, 58",
    "sg:city":"Barcelona",
    "sg:orig_category":"Instalaci\u00d3n, Preparaci\u00d3n De Exposiciones, Ferias, Salones",
    "sg:phone":"+34 934 28 64 25",
    "sg:postcode":"08031",
    "sg:province":"Barcelona",
    "wof:name":"Wiecker S.l.",
    "wof:placetype":"venue"
},
  "geometry": {"coordinates":[2.1566324234,41.4358444214],"type":"Point"}
}