{
  "type": "Feature",
  "properties": {
    "iso:country":"ES",
    "sg:address":"Calle de Reina, 44",
    "sg:city":"Valencia",
    "sg:orig_category":"Barcos",
    "sg:phone":"+34 963 72 89 83",
    "sg:postcode":"46011",
    "sg:province":"Valencia",
    "wof:name":"Shiprovision Co. S.a.",
    "wof:placetype":"venue"
},
  "geometry": {"coordinates":[-0.3290320039,39.4655838013],"type":"Point"}
}