{
  "type": "Feature",
  "properties": {
    "addr:full":"Calle de Cartagena, 10 Puerto Mazarron Murcia 30860",
    "addr:housenumber":"10",
    "addr:postcode":"30860",
    "addr:street":"Calle De Cartagena",
    "iso:country":"ES",
    "sg:address":"Calle de Cartagena, 10",
    "sg:city":"Puerto Mazarron",
    "sg:orig_category":"Librer\u00cdas",
    "sg:phone":"+34 968 15 44 63",
    "sg:postcode":"30860",
    "sg:province":"Murcia",
    "wof:name":"Lopez Acosta Teresa Maria",
    "wof:placetype":"venue"
},
  "geometry": {"coordinates":[-1.2591124773,37.5673217773],"type":"Point"}
}