{
  "type": "Feature",
  "properties": {
    "addr:full":"Cmno Lilas (somio), S/n Gijon Asturias 33203",
    "addr:housenumber":"s",
    "addr:postcode":"33203",
    "addr:street":"Cmno Lilas Somio;/ N",
    "iso:country":"ES",
    "sg:address":"Cmno Lilas (somio), S/n",
    "sg:city":"Gijon",
    "sg:orig_category":"Arenas, Guijarros Y Granulados",
    "sg:phone":"+34 985 33 65 80",
    "sg:postcode":"33203",
    "sg:province":"Asturias",
    "wof:name":"Transportes Gelado Y Riesco S.l.",
    "wof:placetype":"venue"
},
  "geometry": {"coordinates":[-5.6151480675,43.5303153992],"type":"Point"}
}