{
  "type": "Feature",
  "properties": {
    "iso:country":"ES",
    "sg:address":"Calle de Arroyo Del Pozanco (del), 12",
    "sg:city":"Colmenar Viejo",
    "sg:orig_category":"Alquiler De Veh\u00cdculos: Turismos Y Utilitarios",
    "sg:phone":"+34 918 46 70 30",
    "sg:postcode":"28770",
    "sg:province":"Madrid",
    "sg:website":"www.atesa.es",
    "wof:name":"Autotransporte Turistico Espa\u00d1ol",
    "wof:placetype":"venue"
},
  "geometry": {"coordinates":[-3.761302948,40.6635742188],"type":"Point"}
}