{
  "type": "Feature",
  "properties": {
    "addr:full":"Fca. Garcisanchez, S/n Sta. Marta Tormes Salamanca 37900",
    "addr:housenumber":"s / n",
    "addr:postcode":"37900",
    "addr:street":"Marta",
    "iso:country":"ES",
    "sg:address":"Fca. Garcisanchez, S/n",
    "sg:city":"Sta. Marta Tormes",
    "sg:orig_category":"Carnes De Carnicer\u00cda (al Por Mayor)",
    "sg:phone":"+34 923 20 01 83",
    "sg:postcode":"37900",
    "sg:province":"Salamanca",
    "wof:name":"Garsan S.a.t.",
    "wof:placetype":"venue"
},
  "geometry": {"coordinates":[-5.6265788078,40.9506187439],"type":"Point"}
}