{
  "type": "Feature",
  "properties": {
    "addr:full":"Calle de Ausias March, 5 Paiporta Valencia 46200",
    "addr:housenumber":"5",
    "addr:postcode":"46200",
    "addr:street":"Calle De Ausias March",
    "iso:country":"ES",
    "sg:address":"Calle de Ausias March, 5",
    "sg:city":"Paiporta",
    "sg:orig_category":"Poller\u00cda Y Caza (al Por Menor)",
    "sg:phone":"+34 963 97 05 18",
    "sg:postcode":"46200",
    "sg:province":"Valencia",
    "wof:name":"Bonet Ruiz Maria De Los Desamparados",
    "wof:placetype":"venue"
},
  "geometry": {"coordinates":[-0.4166649878,39.4303131104],"type":"Point"}
}