{
  "type": "Feature",
  "properties": {
    "addr:full":"Carrer de Artesans, 80 Valls Tarragona 43800",
    "addr:housenumber":"80",
    "addr:postcode":"43800",
    "addr:street":"Carrer De Artesans",
    "iso:country":"ES",
    "sg:address":"Carrer de Artesans, 80",
    "sg:city":"Valls",
    "sg:orig_category":"Fabricaci\u00d3n De Camas",
    "sg:phone":"+34 977 60 88 45",
    "sg:postcode":"43800",
    "sg:province":"Tarragona",
    "wof:name":"Dimaflex S.a.",
    "wof:placetype":"venue"
},
  "geometry": {"coordinates":[1.2630560398,41.3012046814],"type":"Point"}
}