{
  "type": "Feature",
  "properties": {
    "addr:full":"Pol Ind Caseta Blanca, S/n Vall Alba Castell\u00f3n 12194",
    "addr:housenumber":"s / n",
    "addr:postcode":"12194",
    "iso:country":"ES",
    "sg:address":"Pol Ind Caseta Blanca, S/n",
    "sg:city":"Vall Alba",
    "sg:orig_category":"Estilistas Y Estudios De Estilo De Corte Y Confecci\u00d3n",
    "sg:phone":"+34 964 33 01 42",
    "sg:postcode":"12194",
    "sg:province":"Castell\u00f3n",
    "wof:name":"Scipione Dise\u00f1o Y Distribucion S. L.",
    "wof:placetype":"venue"
},
  "geometry": {"coordinates":[-0.0346090011,40.1753311157],"type":"Point"}
}