{
  "type": "Feature",
  "properties": {
    "addr:full":"Calle de Serranos, 28 Salamanca Salamanca 37008",
    "addr:housenumber":"28",
    "addr:postcode":"37008",
    "addr:street":"Calle De Serranos",
    "iso:country":"ES",
    "sg:address":"Calle de Serranos, 28",
    "sg:city":"Salamanca",
    "sg:orig_category":"Caf\u00c9s, Bares, Cervecer\u00cdas",
    "sg:phone":"+34 923 26 83 75",
    "sg:postcode":"37008",
    "sg:province":"Salamanca",
    "wof:name":"Rodriguez Fuentes Emilio",
    "wof:placetype":"venue"
},
  "geometry": {"coordinates":[-5.6679749489,40.9622688293],"type":"Point"}
}