{
  "type": "Feature",
  "properties": {
    "addr:full":"Calle de Okeluri, 4 Barakaldo Vizcaya 48903",
    "addr:housenumber":"4",
    "addr:postcode":"48903",
    "addr:street":"Calle De Okeluri",
    "iso:country":"ES",
    "sg:address":"Calle de Okeluri, 4",
    "sg:city":"Barakaldo",
    "sg:orig_category":"Venta, Instalaci\u00d3n De Calefacci\u00d3n",
    "sg:phone":"+34 944 90 08 11",
    "sg:postcode":"48903",
    "sg:province":"Vizcaya",
    "wof:name":"Manuel Barcala Martin",
    "wof:placetype":"venue"
},
  "geometry": {"coordinates":[-2.9827959538,43.2855033875],"type":"Point"}
}