{
  "type": "Feature",
  "properties": {
    "addr:full":"Calle de Euskal Herria, 21 Algorta Vizcaya 48991",
    "addr:housenumber":"21",
    "addr:postcode":"48991",
    "addr:street":"Calle De Euskal Herria",
    "iso:country":"ES",
    "sg:address":"Calle de Euskal Herria, 21",
    "sg:city":"Algorta",
    "sg:orig_category":"Decoraci\u00d3n: Instalaci\u00d3n Y Talleres",
    "sg:phone":"+34 944 91 18 97",
    "sg:postcode":"48991",
    "sg:province":"Vizcaya",
    "wof:name":"Torre Sanz Itziar",
    "wof:placetype":"venue"
},
  "geometry": {"coordinates":[-3.0077517033,43.3479537964],"type":"Point"}
}