{
  "type": "Feature",
  "properties": {
    "addr:full":"Calle de Algarrada, 18 Viana Navarra 31230",
    "addr:housenumber":"18",
    "addr:postcode":"31230",
    "addr:street":"Calle De Algarrada",
    "iso:country":"ES",
    "sg:address":"Calle de Algarrada, 18",
    "sg:city":"Viana",
    "sg:orig_category":"Organismos Y Centros De Vacaciones Y Esparcimiento Para Ni\u00d1os Y Adolescentes",
    "sg:phone":"+34 948 64 50 79",
    "sg:postcode":"31230",
    "sg:province":"Navarra",
    "wof:name":"Sociedad Deportivo Ultreya",
    "wof:placetype":"venue"
},
  "geometry": {"coordinates":[-2.3698689938,42.5153236389],"type":"Point"}
}