{
  "type": "Feature",
  "properties": {
    "addr:full":"Avda Principe De Asturias, 199 Villaviciosa Odon Madrid 28670",
    "addr:housenumber":"199",
    "addr:postcode":"28670",
    "addr:street":"Avda Principe De Asturias;Odon",
    "iso:country":"ES",
    "sg:address":"Avda Principe De Asturias, 199",
    "sg:city":"Villaviciosa Odon",
    "sg:orig_category":"Pe\u00d1as Y Asociaciones Varias",
    "sg:phone":"+34 916 16 42 12",
    "sg:postcode":"28670",
    "sg:province":"Madrid",
    "wof:name":"Ayuntamiento-area De La Mujer",
    "wof:placetype":"venue"
},
  "geometry": {"coordinates":[-3.9050171375,40.3576583862],"type":"Point"}
}