{
  "type": "Feature",
  "properties": {
    "iso:country":"ES",
    "sg:address":"Pza. Del Camarin, S/n",
    "sg:city":"Torrijos",
    "sg:orig_category":"Supermercados Y Hipermercados",
    "sg:phone":"+34 925 76 24 81",
    "sg:postcode":"45500",
    "sg:province":"Toledo",
    "wof:name":"Torrijos Diaz Saturnino",
    "wof:placetype":"venue"
},
  "geometry": {"coordinates":[-4.2831439972,39.9830322266],"type":"Point"}
}