{
  "type": "Feature",
  "properties": {
    "addr:full":"Iturrama, 14 Iru\u00f1a Navarra 31007",
    "addr:housenumber":"14",
    "addr:postcode":"31007",
    "addr:street":"Iturrama",
    "iso:country":"ES",
    "sg:address":"Iturrama, 14",
    "sg:city":"Iru\u00f1a",
    "sg:orig_category":"M\u00c9dicos: Pediatr\u00cda. Enfermedades De Los Ni\u00d1os",
    "sg:phone":"+34 948 25 33 95",
    "sg:postcode":"31007",
    "sg:province":"Navarra",
    "wof:name":"Irizar Ortega Jose Luis",
    "wof:placetype":"venue"
},
  "geometry": {"coordinates":[-1.6523009539,42.8048095703],"type":"Point"}
}