{
  "type": "Feature",
  "properties": {
    "addr:full":"Calle de Albarderos, 7 Albacete Albacete 02004",
    "addr:housenumber":"7",
    "addr:postcode":"02004",
    "addr:street":"Calle De Albarderos",
    "iso:country":"ES",
    "sg:address":"Calle de Albarderos, 7",
    "sg:city":"Albacete",
    "sg:orig_category":"Electrodom\u00c9sticos (al Por Menor)",
    "sg:phone":"+34 967 22 45 16",
    "sg:postcode":"02004",
    "sg:province":"Albacete",
    "wof:name":"Garcia Tebar Juan Jose",
    "wof:placetype":"venue"
},
  "geometry": {"coordinates":[-1.8579046726,38.9948806763],"type":"Point"}
}