{
  "type": "Feature",
  "properties": {
    "iso:country":"ES",
    "sg:address":"Ctra. Cadiz-malaga, Km. 0076,0",
    "sg:city":"Tarifa",
    "sg:orig_category":"Hoteles",
    "sg:phone":"+34 956 68 99 90",
    "sg:postcode":"11380",
    "sg:province":"C\u00e1diz",
    "wof:name":"El Retiro De Tarifa S.l.",
    "wof:placetype":"venue"
},
  "geometry": {"coordinates":[-5.6030340195,36.0151596069],"type":"Point"}
}