{
  "type": "Feature",
  "properties": {
    "iso:country":"ES",
    "sg:address":"Calle de Fernando Camino, 9",
    "sg:city":"Malaga",
    "sg:orig_category":"Platos Preparados Refrigerados (fabricaci\u00d3n, Al Por Mayor)",
    "sg:phone":"+34 952 21 12 98",
    "sg:postcode":"29016",
    "sg:province":"M\u00e1laga",
    "wof:name":"Precocinados Maestranza S.c.",
    "wof:placetype":"venue"
},
  "geometry": {"coordinates":[-4.4089369774,36.7199401855],"type":"Point"}
}