{
  "type": "Feature",
  "properties": {
    "iso:country":"ES",
    "sg:address":"Calle de Azoque, 60",
    "sg:city":"Zaragoza",
    "sg:orig_category":"Servicio De Salud",
    "sg:phone":"+34 976 23 35 32",
    "sg:postcode":"50004",
    "sg:province":"Zaragoza",
    "wof:name":"Saneamientos Marin S. A.",
    "wof:placetype":"venue"
},
  "geometry": {"coordinates":[-0.8843703866,41.651550293],"type":"Point"}
}