{
  "type": "Feature",
  "properties": {
    "addr:full":"Calle de Blas De Otero, 5 Zamora Zamora 49017",
    "addr:housenumber":"5",
    "addr:postcode":"49017",
    "addr:street":"Calle De Blas De Otero",
    "iso:country":"ES",
    "sg:address":"Calle de Blas De Otero, 5",
    "sg:city":"Zamora",
    "sg:orig_category":"Prot\u00c9sicos Dentales",
    "sg:phone":"+34 980 55 74 73",
    "sg:postcode":"49017",
    "sg:province":"Zamora",
    "wof:name":"Laboratorio Dental Castellanos S.l.",
    "wof:placetype":"venue"
},
  "geometry": {"coordinates":[-5.734688282,41.5043754578],"type":"Point"}
}