{
  "type": "Feature",
  "properties": {
    "addr:full":"Calle de Doctor Cerrada, 14 Zaragoza Zaragoza 50005",
    "addr:housenumber":"14",
    "addr:postcode":"50005",
    "addr:street":"Calle De Doctor Cerrada",
    "iso:country":"ES",
    "sg:address":"Calle de Doctor Cerrada, 14",
    "sg:city":"Zaragoza",
    "sg:orig_category":"Transportes Por Carretera: Lotes Completos, Mercanc\u00cdas Diversas",
    "sg:phone":"+34 976 22 93 42",
    "sg:postcode":"50005",
    "sg:province":"Zaragoza",
    "wof:name":"Dagesa",
    "wof:placetype":"venue"
},
  "geometry": {"coordinates":[-0.8882488012,41.647567749],"type":"Point"}
}