{
  "type": "Feature",
  "properties": {
    "iso:country":"ES",
    "sg:address":"Plaz Belen, 3",
    "sg:city":"Zamora",
    "sg:orig_category":"Restaurantes",
    "sg:phone":"+34 980 53 32 67",
    "sg:postcode":"49027",
    "sg:province":"Zamora",
    "wof:name":"Santos Poyo S.l.",
    "wof:placetype":"venue"
},
  "geometry": {"coordinates":[-5.7481060028,41.4973449707],"type":"Point"}
}