{
  "type": "Feature",
  "properties": {
    "iso:country":"ES",
    "sg:address":"Platja Llarga, S/n",
    "sg:city":"Tarragona",
    "sg:orig_category":"Supermercados Y Hipermercados",
    "sg:phone":"+34 977 20 79 49",
    "sg:postcode":"43007",
    "sg:province":"Tarragona",
    "wof:name":"Calix Povedano Rafael",
    "wof:placetype":"venue"
},
  "geometry": {"coordinates":[1.3119449615,41.1314506531],"type":"Point"}
}