{
  "type": "Feature",
  "properties": {
    "iso:country":"ES",
    "sg:address":"Calle de Santa Maria, 3",
    "sg:city":"Villalba Alcor",
    "sg:orig_category":"Telas Y Sedas (al Por Menor)",
    "sg:phone":"+34 959 42 11 02",
    "sg:postcode":"21860",
    "sg:province":"Huelva",
    "wof:name":"Toro Beltran Juan Del",
    "wof:placetype":"venue"
},
  "geometry": {"coordinates":[-6.4762301445,37.3966255188],"type":"Point"}
}