{
  "type": "Feature",
  "properties": {
    "addr:full":"Calle de Desenga\u00d1o, S/n Hinojosa Del Duque C\u00f3rdoba 14270",
    "addr:housenumber":"s",
    "addr:postcode":"14270",
    "addr:street":"Calle De Desengan\u0303O;/ N;Co\u0301Rdoba",
    "iso:country":"ES",
    "sg:address":"Calle de Desenga\u00d1o, S/n",
    "sg:city":"Hinojosa Del Duque",
    "sg:orig_category":"Frutas Y Legumbres Frescas (al Por Mayor)",
    "sg:phone":"+34 957 14 09 43",
    "sg:postcode":"14270",
    "sg:province":"C\u00f3rdoba",
    "wof:name":"Frutas Ruiz S.l.",
    "wof:placetype":"venue"
},
  "geometry": {"coordinates":[-5.1506590843,38.5080108643],"type":"Point"}
}