{
  "type": "Feature",
  "properties": {
    "addr:full":"Calle de Tierno Galvan, 9 Pizarra M\u00e1laga 29560",
    "addr:housenumber":"9",
    "addr:postcode":"29560",
    "addr:street":"Calle De Tierno Galvan",
    "iso:country":"ES",
    "sg:address":"Calle de Tierno Galvan, 9",
    "sg:city":"Pizarra",
    "sg:orig_category":"Empresas De Desmonte",
    "sg:phone":"+34 952 48 32 54",
    "sg:postcode":"29560",
    "sg:province":"M\u00e1laga",
    "wof:name":"Transformaciones Agricolas Del Guadalhorce S.l.",
    "wof:placetype":"venue"
},
  "geometry": {"coordinates":[-4.709856987,36.7627105713],"type":"Point"}
}