{
  "type": "Feature",
  "properties": {
    "iso:country":"ES",
    "sg:address":"Calle de Haya (de La), 20",
    "sg:city":"Parque Coimbra",
    "sg:orig_category":"M\u00c1rmoles, Granitos Y Piedras Naturales",
    "sg:phone":"+34 916 45 95 83",
    "sg:postcode":"28935",
    "sg:province":"Madrid",
    "wof:name":"Gonzalez Rodriguez Dolores",
    "wof:placetype":"venue"
},
  "geometry": {"coordinates":[-3.9278662205,40.3097877502],"type":"Point"}
}