{
  "type": "Feature",
  "properties": {
    "addr:full":"Calle de Marroquina, 82 Madrid Madrid 28030",
    "addr:housenumber":"82",
    "addr:postcode":"madrid;28030",
    "addr:street":"Calle De Marroquina",
    "iso:country":"ES",
    "sg:address":"Calle de Marroquina, 82",
    "sg:city":"Madrid",
    "sg:orig_category":"Comercio, Reparaci\u00d3n De Bicicletas, De Motocicletas, De Accesorios",
    "sg:phone":"+34 913 28 35 64",
    "sg:postcode":"28030",
    "sg:province":"Madrid",
    "wof:name":"Agirre Perez Jose Luis",
    "wof:placetype":"venue"
},
  "geometry": {"coordinates":[-3.6461856365,40.4097137451],"type":"Point"}
}