{
  "type": "Feature",
  "properties": {
    "addr:full":"Calle de Infanta Mercedes, 96 Madrid Madrid 28020",
    "addr:housenumber":"96",
    "addr:postcode":"madrid;28020",
    "addr:street":"Calle De Infanta Mercedes",
    "iso:country":"ES",
    "sg:address":"Calle de Infanta Mercedes, 96",
    "sg:city":"Madrid",
    "sg:orig_category":"Alumbrados",
    "sg:phone":"+34 915 79 35 65",
    "sg:postcode":"28020",
    "sg:province":"Madrid",
    "sg:website":"www.lamparasoliva.com",
    "wof:name":"Lamparas Oliva S. A.",
    "wof:placetype":"venue"
},
  "geometry": {"coordinates":[-3.6935429573,40.4633331299],"type":"Point"}
}