{
  "type": "Feature",
  "properties": {
    "iso:country":"ES",
    "sg:address":"Calle de B, S/n",
    "sg:city":"Pol. Plano-las Canales",
    "sg:orig_category":"Colchones (fabricaci\u00d3n, Al Por Mayor, Al Por Menor)",
    "sg:phone":"+34 976 12 60 64",
    "sg:postcode":"50430",
    "sg:province":"Zaragoza",
    "wof:name":"Tecnicas De Descanso S.l.",
    "wof:placetype":"venue"
},
  "geometry": {"coordinates":[-0.9965239763,41.5399703979],"type":"Point"}
}