{
  "type": "Feature",
  "properties": {
    "iso:country":"ES",
    "sg:address":"Valtierra, 16",
    "sg:city":"Iru\u00f1a",
    "sg:orig_category":"Metalurgia",
    "sg:phone":"+34 948 35 57 81",
    "sg:postcode":"31015",
    "sg:province":"Navarra",
    "wof:name":"Ortiz Claver Monica",
    "wof:placetype":"venue"
},
  "geometry": {"coordinates":[-1.629866004,42.8338813782],"type":"Point"}
}