{
  "type": "Feature",
  "properties": {
    "addr:full":"Calle de Rodrigo Canto, 33 Meliana Valencia 46133",
    "addr:housenumber":"33",
    "addr:postcode":"46133",
    "addr:street":"Calle De Rodrigo Canto",
    "iso:country":"ES",
    "sg:address":"Calle de Rodrigo Canto, 33",
    "sg:city":"Meliana",
    "sg:orig_category":"Molduras, Junquillos, Listones Y Molduras Perforadas",
    "sg:phone":"+34 961 49 62 19",
    "sg:postcode":"46133",
    "sg:province":"Valencia",
    "wof:name":"Hermanos Paton C.b",
    "wof:placetype":"venue"
},
  "geometry": {"coordinates":[-0.3230139911,39.5274848938],"type":"Point"}
}