{
  "type": "Feature",
  "properties": {
    "iso:country":"ES",
    "sg:address":"Carr Muralla, 12",
    "sg:city":"Morella",
    "sg:orig_category":"Albergues",
    "sg:phone":"+34 964 16 02 43",
    "sg:postcode":"12300",
    "sg:province":"Castell\u00f3n",
    "wof:name":"Moralla C.b.",
    "wof:placetype":"venue"
},
  "geometry": {"coordinates":[-0.0977939963,40.6189155579],"type":"Point"}
}