{
  "type": "Feature",
  "properties": {
    "addr:full":"Calle de San Juan De Dios, 14 Granada Granada 18001",
    "addr:housenumber":"14",
    "addr:postcode":"18001",
    "addr:street":"Calle De San Juan;Dios",
    "iso:country":"ES",
    "sg:address":"Calle de San Juan De Dios, 14",
    "sg:city":"Granada",
    "sg:orig_category":"Formaci\u00d3n A Distancia, Por Correspondencia",
    "sg:phone":"+34 958 29 46 65",
    "sg:postcode":"18001",
    "sg:province":"Granada",
    "wof:name":"Martinez Caparros Francisco",
    "wof:placetype":"venue"
},
  "geometry": {"coordinates":[-3.6026029587,37.1803741455],"type":"Point"}
}