{
  "type": "Feature",
  "properties": {
    "iso:country":"ES",
    "sg:address":"Carr Siurells, S/n",
    "sg:city":"Cabaneta",
    "sg:orig_category":"Artes Gr\u00c1ficas, Artes Pl\u00c1sticas: Material Y Suministros (al Por Menor)",
    "sg:phone":"+34 971 22 62 32",
    "sg:postcode":"07141",
    "sg:province":"Islas Baleares",
    "sg:website":"www.palmapictures.es",
    "wof:name":"Palma Pictures The Mediterranean Producc",
    "wof:placetype":"venue"
},
  "geometry": {"coordinates":[2.741590023,39.6156005859],"type":"Point"}
}