{
  "type": "Feature",
  "properties": {
    "addr:full":"Calle de Tetuan, 40 Linares Ja\u00e9n 23700",
    "addr:housenumber":"40",
    "addr:postcode":"23700",
    "addr:street":"Calle De Tetuan;Jae\u0301N",
    "iso:country":"ES",
    "sg:address":"Calle de Tetuan, 40",
    "sg:city":"Linares",
    "sg:orig_category":"Contenedores (mercanc\u00cdas)",
    "sg:phone":"+34 953 69 01 11",
    "sg:postcode":"23700",
    "sg:province":"Ja\u00e9n",
    "wof:name":"Catena Arance Miguel Angel",
    "wof:placetype":"venue"
},
  "geometry": {"coordinates":[-3.6349298954,38.0975418091],"type":"Point"}
}