{
  "type": "Feature",
  "properties": {
    "addr:full":"Carr Mar Adriatico, 24 Complejo Residencial De Vera Valencia 46120",
    "addr:housenumber":"24",
    "addr:postcode":"46120",
    "addr:street":"Carr Mar Adriatico",
    "iso:country":"ES",
    "sg:address":"Carr Mar Adriatico, 24",
    "sg:city":"Complejo Residencial De Vera",
    "sg:orig_category":"Radiocomunicaciones, Telefon\u00cda M\u00d3vil, Radiomensajer\u00cda: Servicios, Comercializaci\u00d3n",
    "sg:phone":"+34 963 71 75 77",
    "sg:postcode":"46120",
    "sg:province":"Valencia",
    "wof:name":"Patricanvi 2002 S.l.",
    "wof:placetype":"venue"
},
  "geometry": {"coordinates":[-0.3405140042,39.4990692139],"type":"Point"}
}