{
  "type": "Feature",
  "properties": {
    "addr:full":"Ptda Saboya, 39 Alboraya Valencia 46120",
    "addr:housenumber":"39",
    "addr:postcode":"46120",
    "addr:street":"Ptda Saboya",
    "iso:country":"ES",
    "sg:address":"Ptda Saboya, 39",
    "sg:city":"Alboraya",
    "sg:orig_category":"Semiller\u00cdas",
    "sg:phone":"+34 961 85 58 50",
    "sg:postcode":"46120",
    "sg:province":"Valencia",
    "wof:name":"Albogarden S.l.",
    "wof:placetype":"venue"
},
  "geometry": {"coordinates":[-0.3395406902,39.4937095642],"type":"Point"}
}