{
  "type": "Feature",
  "properties": {
    "addr:full":"Avda Campanar, 3 Valencia Valencia 46009",
    "addr:housenumber":"3",
    "addr:postcode":"46009",
    "addr:street":"Avda Campanar",
    "iso:country":"ES",
    "sg:address":"Avda Campanar, 3",
    "sg:city":"Valencia",
    "sg:orig_category":"Agencias De Viajes",
    "sg:phone":"+34 963 46 64 57",
    "sg:postcode":"46009",
    "sg:province":"Valencia",
    "sg:website":"www.viajesiberia.com",
    "wof:name":"Viajes Iberia S.a.",
    "wof:placetype":"venue"
},
  "geometry": {"coordinates":[-0.3898139894,39.4874839783],"type":"Point"}
}