{
  "type": "Feature",
  "properties": {
    "iso:country":"ES",
    "sg:address":"Av Generalitat, 16",
    "sg:city":"Barri Maritim De Comarruga",
    "sg:orig_category":"Reposter\u00cdas",
    "sg:phone":"+34 977 68 07 22",
    "sg:postcode":"43880",
    "sg:province":"Tarragona",
    "wof:name":"Forn Sant Francesc S.l.u.",
    "wof:placetype":"venue"
},
  "geometry": {"coordinates":[1.5386699438,41.1833496094],"type":"Point"}
}