{
  "type": "Feature",
  "properties": {
    "addr:full":"Plaz Poeta Miguel Hernandez, 3 Zaragoza Zaragoza 50007",
    "addr:housenumber":"3",
    "addr:postcode":"50007",
    "addr:street":"Plaz Poeta Miguel Hernandez",
    "iso:country":"ES",
    "sg:address":"Plaz Poeta Miguel Hernandez, 3",
    "sg:city":"Zaragoza",
    "sg:orig_category":"Peluqueros: De Se\u00d1oras",
    "sg:phone":"+34 976 37 55 86",
    "sg:postcode":"50007",
    "sg:province":"Zaragoza",
    "wof:name":"Estaun Peluqueros S.l.",
    "wof:placetype":"venue"
},
  "geometry": {"coordinates":[-0.8824920058,41.638835907],"type":"Point"}
}