{
  "type": "Feature",
  "properties": {
    "addr:full":"Carrer de Benidorm, 3 Reus Tarragona 43205",
    "addr:housenumber":"3",
    "addr:postcode":"43205",
    "addr:street":"Carrer De Benidorm",
    "iso:country":"ES",
    "sg:address":"Carrer de Benidorm, 3",
    "sg:city":"Reus",
    "sg:orig_category":"Molduras, Junquillos, Listones Y Molduras Perforadas",
    "sg:phone":"+34 977 75 18 72",
    "sg:postcode":"43205",
    "sg:province":"Tarragona",
    "wof:name":"Zaguirre Martinez Juan",
    "wof:placetype":"venue"
},
  "geometry": {"coordinates":[1.1070518494,41.1461029053],"type":"Point"}
}