{
  "type": "Feature",
  "properties": {
    "addr:full":"Avda Guadalquivir (del), 16 Cazorla Ja\u00e9n 23470",
    "addr:housenumber":"16",
    "addr:postcode":"23470",
    "addr:street":"Avda Guadalquivir Del",
    "iso:country":"ES",
    "sg:address":"Avda Guadalquivir (del), 16",
    "sg:city":"Cazorla",
    "sg:orig_category":"Contenedores (mercanc\u00cdas)",
    "sg:phone":"+34 953 72 07 98",
    "sg:postcode":"23470",
    "sg:province":"Ja\u00e9n",
    "wof:name":"Gomez Mu\u00f1oz Alfredo",
    "wof:placetype":"venue"
},
  "geometry": {"coordinates":[-3.004502058,37.9170837402],"type":"Point"}
}