{
  "type": "Feature",
  "properties": {
    "addr:full":"Ctra Nacional 340, S/n Pueblo Nuevo C\u00e1diz 11360",
    "addr:housenumber":"s / n",
    "addr:postcode":"11360",
    "addr:street":"Ctra Nacional 340",
    "iso:country":"ES",
    "sg:address":"Ctra Nacional 340, S/n",
    "sg:city":"Pueblo Nuevo",
    "sg:classifiers":[
        {
            "category":"Sports & Exercise",
            "subcategory":"Golf",
            "type":"Entertainment"
        }
    ],
    "sg:phone":"+34 956 79 41 00",
    "sg:postcode":"11360",
    "sg:province":"C\u00e1diz",
    "sg:tags":[
        "y",
        "de",
        "campos",
        "clases"
    ],
    "wof:name":"Club De Golf La Ca\u00f1ada",
    "wof:placetype":"venue"
},
  "geometry": {"coordinates":[-5.3897438049,36.209690094],"type":"Point"}
}