{
  "type": "Feature",
  "properties": {
    "addr:full":"Av Catalunya, 15 Bellpuig Lleida 25250",
    "addr:housenumber":"15",
    "addr:postcode":"25250",
    "addr:street":"Av Catalunya",
    "iso:country":"ES",
    "sg:address":"Av Catalunya, 15",
    "sg:city":"Bellpuig",
    "sg:orig_category":"Vestidos De Se\u00d1ora (tallas Grandes)",
    "sg:phone":"+34 973 32 12 00",
    "sg:postcode":"25250",
    "sg:province":"Lleida",
    "wof:name":"Bague Bosch Rosa Maria",
    "wof:placetype":"venue"
},
  "geometry": {"coordinates":[1.0109219551,41.6276702881],"type":"Point"}
}