{
  "type": "Feature",
  "properties": {
    "addr:full":"Calle de Calvo Sotelo, 39 Logro\u00f1o La Rioja 26003",
    "addr:housenumber":"39",
    "addr:postcode":"26003",
    "addr:street":"Calle De Calvo Sotelo;Rioja",
    "iso:country":"ES",
    "sg:address":"Calle de Calvo Sotelo, 39",
    "sg:city":"Logro\u00f1o",
    "sg:orig_category":"Calzados Ortop\u00c9dicos",
    "sg:phone":"+34 941 24 07 21",
    "sg:postcode":"26003",
    "sg:province":"La Rioja",
    "wof:name":"Orto-rioja S. L.",
    "wof:placetype":"venue"
},
  "geometry": {"coordinates":[-2.4395513535,42.4639511108],"type":"Point"}
}