{
  "type": "Feature",
  "properties": {
    "iso:country":"ES",
    "sg:address":"Calle de Malvarrosa, 4",
    "sg:city":"Torrent",
    "sg:orig_category":"Farmacias",
    "sg:phone":"+34 961 56 38 69",
    "sg:postcode":"46900",
    "sg:province":"Valencia",
    "wof:name":"Ros Orti Maria",
    "wof:placetype":"venue"
},
  "geometry": {"coordinates":[-0.4703730047,39.4403305054],"type":"Point"}
}