{
  "type": "Feature",
  "properties": {
    "addr:full":"Pol Ind Piscis, 14 Jerez C\u00e1diz 11408",
    "addr:housenumber":"14",
    "addr:postcode":"11408",
    "addr:street":"Ind Piscis",
    "iso:country":"ES",
    "sg:address":"Pol Ind Piscis, 14",
    "sg:city":"Jerez",
    "sg:orig_category":"Ambulancias",
    "sg:phone":"+34 956 14 70 58",
    "sg:postcode":"11408",
    "sg:province":"C\u00e1diz",
    "wof:name":"Ambulancias Royda S.l.",
    "wof:placetype":"venue"
},
  "geometry": {"coordinates":[-6.1633043289,36.6765556335],"type":"Point"}
}