{
  "type": "Feature",
  "properties": {
    "iso:country":"ES",
    "sg:address":"Carrer de Valencia, 480",
    "sg:city":"Barcelona",
    "sg:orig_category":"Agencias Y Agentes Comerciales, Representantes",
    "sg:phone":"+34 932 46 94 79",
    "sg:postcode":"08013",
    "sg:province":"Barcelona",
    "wof:name":"Micola Carles Jose",
    "wof:placetype":"venue"
},
  "geometry": {"coordinates":[2.1784510612,41.4038734436],"type":"Point"}
}