{
  "type": "Feature",
  "properties": {
    "iso:country":"ES",
    "sg:address":"Fco. Orellana, 24",
    "sg:city":"Villa Del Campo",
    "sg:orig_category":"Cerrajer\u00cda, Ferrallista",
    "sg:phone":"+34 927 44 80 73",
    "sg:postcode":"10814",
    "sg:province":"C\u00e1ceres",
    "wof:name":"Retortillo Olivera Diego",
    "wof:placetype":"venue"
},
  "geometry": {"coordinates":[-6.4298620224,40.1414794922],"type":"Point"}
}