{
  "type": "Feature",
  "properties": {
    "addr:full":"Calle de Bravo Murillo, 13 Palmas De Gran Canaria Las Palmas 35003",
    "addr:housenumber":"13",
    "addr:postcode":"35003",
    "addr:street":"Calle De Bravo Murillo",
    "iso:country":"ES",
    "sg:address":"Calle de Bravo Murillo, 13",
    "sg:city":"Palmas De Gran Canaria",
    "sg:orig_category":"Alquiler De Veh\u00cdculos: Turismos Y Utilitarios",
    "sg:phone":"+34 928 36 88 77",
    "sg:postcode":"35003",
    "sg:province":"Las Palmas",
    "wof:name":"Agencia Guanche S.a.",
    "wof:placetype":"venue"
},
  "geometry": {"coordinates":[-15.419377327,28.1082744598],"type":"Point"}
}