{
  "type": "Feature",
  "properties": {
    "addr:full":"Carrer de Masets, 13 Gratallops Tarragona 43737",
    "addr:housenumber":"13",
    "addr:postcode":"43737",
    "addr:street":"Carrer De Masets",
    "iso:country":"ES",
    "sg:address":"Carrer de Masets, 13",
    "sg:city":"Gratallops",
    "sg:orig_category":"Enfermeras: Consultas, Atenci\u00d3n A Domicilio",
    "sg:phone":"+34 977 83 93 50",
    "sg:postcode":"43737",
    "sg:province":"Tarragona",
    "wof:name":"Delgado Pe\u00f1a Jorge",
    "wof:placetype":"venue"
},
  "geometry": {"coordinates":[0.7776929736,41.1925735474],"type":"Point"}
}