{
  "type": "Feature",
  "properties": {
    "addr:full":"N. Monturiol, 55 Pineda Mar Barcelona 08397",
    "addr:housenumber":"55",
    "addr:postcode":"08397",
    "addr:street":"N. Monturiol;Barcelona",
    "iso:country":"ES",
    "sg:address":"N. Monturiol, 55",
    "sg:city":"Pineda Mar",
    "sg:orig_category":"Centros De Educaci\u00d3n Especial",
    "sg:phone":"+34 937 67 14 60",
    "sg:postcode":"08397",
    "sg:province":"Barcelona",
    "wof:name":"Ajuntament De Pineda De Mar",
    "wof:placetype":"venue"
},
  "geometry": {"coordinates":[2.6796431541,41.6198959351],"type":"Point"}
}