{
  "type": "Feature",
  "properties": {
    "addr:full":"Rua Circunvalacion (da), 3 Carballi\u00f1o Ourense 32500",
    "addr:postcode":"32500",
    "addr:street":"Rua Circunvalacion Da 3 Carballin\u0303O",
    "iso:country":"ES",
    "sg:address":"Rua Circunvalacion (da), 3",
    "sg:city":"Carballi\u00f1o",
    "sg:orig_category":"Caf\u00c9s, Bares, Cervecer\u00cdas",
    "sg:phone":"+34 988 27 30 07",
    "sg:postcode":"32500",
    "sg:province":"Ourense",
    "wof:name":"Galtelcom",
    "wof:placetype":"venue"
},
  "geometry": {"coordinates":[-8.082159996,42.4297637939],"type":"Point"}
}