{
  "type": "Feature",
  "properties": {
    "iso:country":"ES",
    "sg:address":"Carr Masquefa, 4",
    "sg:city":"Igualada",
    "sg:orig_category":"Perfumer\u00cda (al Por Menor)",
    "sg:phone":"+34 938 04 05 22",
    "sg:postcode":"08700",
    "sg:province":"Barcelona",
    "wof:name":"Domingo Sabate Jose Maria",
    "wof:placetype":"venue"
},
  "geometry": {"coordinates":[1.6142619848,41.5875892639],"type":"Point"}
}