{
  "type": "Feature",
  "properties": {
    "iso:country":"ES",
    "sg:address":"San Juan Kalea, 3",
    "sg:city":"Eibar",
    "sg:orig_category":"Abogados",
    "sg:phone":"+34 943 82 05 08",
    "sg:postcode":"20600",
    "sg:province":"Guip\u00f9zcoa",
    "wof:name":"Ron Crucelegui Santiago",
    "wof:placetype":"venue"
},
  "geometry": {"coordinates":[-2.4732489586,43.184841156],"type":"Point"}
}