{
  "type": "Feature",
  "properties": {
    "iso:country":"ES",
    "sg:address":"Carrer de Bruc, 3",
    "sg:city":"Cornella Llobregat",
    "sg:orig_category":"Peluqueros: De Se\u00d1oras",
    "sg:phone":"+34 933 76 08 20",
    "sg:postcode":"08940",
    "sg:province":"Barcelona",
    "wof:name":"Nu\u00f1ez Gonzalez Manuel",
    "wof:placetype":"venue"
},
  "geometry": {"coordinates":[2.0807189941,41.3608665466],"type":"Point"}
}