{
  "type": "Feature",
  "properties": {
    "addr:full":"Calle de Goikoplaza, 22 Llodio \u00c1lava 01400",
    "addr:housenumber":"22",
    "addr:postcode":"01400",
    "addr:street":"Calle De Goikoplaza",
    "iso:country":"ES",
    "sg:address":"Calle de Goikoplaza, 22",
    "sg:city":"Llodio",
    "sg:orig_category":"Mec\u00c1nico Del Autom\u00d3vil",
    "sg:phone":"+34 946 72 01 83",
    "sg:postcode":"01400",
    "sg:province":"\u00c1lava",
    "wof:name":"Gruas Ojembarrena S.l.",
    "wof:placetype":"venue"
},
  "geometry": {"coordinates":[-2.9658615589,43.1377830505],"type":"Point"}
}