{
  "type": "Feature",
  "properties": {
    "addr:full":"Calle de Infantas, 1 Alcorcon Madrid 28922",
    "addr:housenumber":"1",
    "addr:postcode":"28922",
    "addr:street":"Calle De Infantas",
    "iso:country":"ES",
    "sg:address":"Calle de Infantas, 1",
    "sg:city":"Alcorcon",
    "sg:orig_category":"Danza, Cursos, Asociaciones Y M\u00dasicos",
    "sg:phone":"+34 916 43 57 29",
    "sg:postcode":"28922",
    "sg:province":"Madrid",
    "wof:name":"Viejo Donaire Carmelo",
    "wof:placetype":"venue"
},
  "geometry": {"coordinates":[-3.8317770958,40.3470039368],"type":"Point"}
}