{
  "type": "Feature",
  "properties": {
    "iso:country":"ES",
    "sg:address":"Ptda Pla De La Vallonga, 17",
    "sg:city":"Pla De La Vallonga",
    "sg:orig_category":"Mec\u00c1nico Del Autom\u00d3vil",
    "sg:phone":"+34 965 10 76 30",
    "sg:postcode":"03113",
    "sg:province":"Alicante",
    "wof:name":"Alicantina De Camiones S.a.l.",
    "wof:placetype":"venue"
},
  "geometry": {"coordinates":[-0.5889509916,38.3436164856],"type":"Point"}
}