{
  "type": "Feature",
  "properties": {
    "iso:country":"ES",
    "sg:address":"Edisson, 24",
    "sg:city":"Linyola",
    "sg:orig_category":"Empresarios",
    "sg:phone":"+34 973 57 55 24",
    "sg:postcode":"25240",
    "sg:province":"Lleida",
    "wof:name":"Rosell Pedros Juan",
    "wof:placetype":"venue"
},
  "geometry": {"coordinates":[0.9022499919,41.7065086365],"type":"Point"}
}