{
  "type": "Feature",
  "properties": {
    "addr:full":"Calle de Nicolas Asenjo, 59 Duruelo Sierra Soria 42158",
    "addr:housenumber":"59",
    "addr:postcode":"42158",
    "addr:street":"Calle De Nicolas Asenjo",
    "iso:country":"ES",
    "sg:address":"Calle de Nicolas Asenjo, 59",
    "sg:city":"Duruelo Sierra",
    "sg:orig_category":"Bancos",
    "sg:phone":"+34 975 37 10 20",
    "sg:postcode":"42158",
    "sg:province":"Soria",
    "wof:name":"Bartolome Villa Silvia",
    "wof:placetype":"venue"
},
  "geometry": {"coordinates":[-2.9333488941,41.9540214539],"type":"Point"}
}