{
  "type": "Feature",
  "properties": {
    "addr:full":"Avda Emperatriz Isabel, 14 Madrid Madrid 28019",
    "addr:housenumber":"14",
    "addr:postcode":"madrid;28019",
    "addr:street":"Avda Emperatriz Isabel",
    "iso:country":"ES",
    "sg:address":"Avda Emperatriz Isabel, 14",
    "sg:city":"Madrid",
    "sg:orig_category":"Empresas De Limpieza",
    "sg:phone":"+34 914 69 51 78",
    "sg:postcode":"28019",
    "sg:province":"Madrid",
    "wof:name":"Chica Vallejo Jose De La",
    "wof:placetype":"venue"
},
  "geometry": {"coordinates":[-3.7188611031,40.398815155],"type":"Point"}
}