{
  "type": "Feature",
  "properties": {
    "addr:full":"Ctra Madrid-cadiz(bellavista), Km. 0549,0 Sevilla Sevilla 41014",
    "addr:postcode":"41014",
    "addr:street":"Ctra Madrid-Cadiz Bellavista Km. 0549,0",
    "iso:country":"ES",
    "sg:address":"Ctra Madrid-cadiz(bellavista), Km. 0549,0",
    "sg:city":"Sevilla",
    "sg:orig_category":"Alimentaci\u00d3n General (al Por Mayor)",
    "sg:phone":"+34 954 69 06 00",
    "sg:postcode":"41014",
    "sg:province":"Sevilla",
    "wof:name":"Piensos Andaluces Compuestos S. A.",
    "wof:placetype":"venue"
},
  "geometry": {"coordinates":[-5.9596791267,37.3278617859],"type":"Point"}
}