{
  "type": "Feature",
  "properties": {
    "iso:country":"ES",
    "sg:address":"Carrer de Albert Einstein, 23",
    "sg:city":"Castelldefels",
    "sg:orig_category":"Electricidad Veh\u00cdculo",
    "sg:phone":"+34 936 64 26 50",
    "sg:postcode":"08860",
    "sg:province":"Barcelona",
    "wof:name":"Agut Latorre Jorge",
    "wof:placetype":"venue"
},
  "geometry": {"coordinates":[1.9790788889,41.2824554443],"type":"Point"}
}