{
  "type": "Feature",
  "properties": {
    "addr:full":"Ctra Zamora, S/n Ribaseca Le\u00f3n 24391",
    "addr:postcode":"24391",
    "addr:street":"Ctra Zamora S / N Ribaseca Leo\u0301N",
    "iso:country":"ES",
    "sg:address":"Ctra Zamora, S/n",
    "sg:city":"Ribaseca",
    "sg:orig_category":"Venta, Montaje De Neum\u00c1ticos",
    "sg:phone":"+34 987 21 53 25",
    "sg:postcode":"24391",
    "sg:province":"Le\u00f3n",
    "wof:name":"Neumaticos Suarez S.l.",
    "wof:placetype":"venue"
},
  "geometry": {"coordinates":[-5.6244401932,42.5436477661],"type":"Point"}
}