{
  "type": "Feature",
  "properties": {
    "iso:country":"ES",
    "sg:address":"Calle de Orfebres, 10",
    "sg:city":"Rota",
    "sg:orig_category":"Veh\u00cdculos De Ocasi\u00d3n",
    "sg:phone":"+34 956 81 04 96",
    "sg:postcode":"11520",
    "sg:province":"C\u00e1diz",
    "wof:name":"Ni\u00f1o Granado Juan Jesus",
    "wof:placetype":"venue"
},
  "geometry": {"coordinates":[-6.365913868,36.6311035156],"type":"Point"}
}