{
  "type": "Feature",
  "properties": {
    "iso:country":"ES",
    "sg:address":"Carrer de Doctor Klein, 9",
    "sg:city":"Cardedeu",
    "sg:orig_category":"Papeler\u00cdas, Librer\u00cdas",
    "sg:phone":"+34 938 46 11 85",
    "sg:postcode":"08440",
    "sg:province":"Barcelona",
    "wof:name":"Ulldemolins Gonzalez Luis",
    "wof:placetype":"venue"
},
  "geometry": {"coordinates":[2.3551530838,41.6393890381],"type":"Point"}
}