{
  "type": "Feature",
  "properties": {
    "addr:full":"Rua Irmans Jose E Severino Trigo, 2 Estrada Pontevedra 36680",
    "addr:housenumber":"2",
    "addr:postcode":"36680",
    "addr:street":"Rua Irmans Jose E Severino Trigo;Estrada Pontevedra",
    "iso:country":"ES",
    "sg:address":"Rua Irmans Jose E Severino Trigo, 2",
    "sg:city":"Estrada",
    "sg:orig_category":"Ambulancias",
    "sg:phone":"+34 986 57 24 62",
    "sg:postcode":"36680",
    "sg:province":"Pontevedra",
    "wof:name":"Castro Sanmartin Jose Luis",
    "wof:placetype":"venue"
},
  "geometry": {"coordinates":[-8.4873838425,42.6900444031],"type":"Point"}
}