{
  "type": "Feature",
  "properties": {
    "addr:full":"Calle de Paneras, 3 Caceres C\u00e1ceres 10003",
    "addr:housenumber":"3",
    "addr:postcode":"10003",
    "addr:street":"Calle De Paneras;Ca\u0301Ceres",
    "iso:country":"ES",
    "sg:address":"Calle de Paneras, 3",
    "sg:city":"Caceres",
    "sg:orig_category":"Mercer\u00cda, Lencer\u00cda (al Por Menor)",
    "sg:phone":"+34 927 21 08 07",
    "sg:postcode":"10003",
    "sg:province":"C\u00e1ceres",
    "wof:name":"Monta\u00f1a Rodriguez Francisca De La",
    "wof:placetype":"venue"
},
  "geometry": {"coordinates":[-6.3727197647,39.4748420715],"type":"Point"}
}