{
  "type": "Feature",
  "properties": {
    "iso:country":"ES",
    "sg:address":"Trva Torno Del, S/n",
    "sg:city":"Aviles",
    "sg:orig_category":"Fabricaci\u00d3n De Pernos, Tornillos Y Clavos",
    "sg:phone":"+34 985 56 82 95",
    "sg:postcode":"33401",
    "sg:province":"Asturias",
    "wof:name":"Suministros Cusan S.l.",
    "wof:placetype":"venue"
},
  "geometry": {"coordinates":[-5.9235539436,43.5704231262],"type":"Point"}
}