{
  "type": "Feature",
  "properties": {
    "iso:country":"ES",
    "sg:address":"Avda Gredos, 11",
    "sg:city":"Gran Chaparral  I Fase",
    "sg:orig_category":"Promotores Constructores",
    "sg:phone":"+34 925 70 17 16",
    "sg:postcode":"45638",
    "sg:province":"Toledo",
    "wof:name":"Planes E Inversiones Clm S.a.",
    "wof:placetype":"venue"
},
  "geometry": {"coordinates":[-4.8094291687,40.0079994202],"type":"Point"}
}