{
  "type": "Feature",
  "properties": {
    "addr:full":"Avda Carlos V, 53 Carrizal Las Palmas 35240",
    "addr:housenumber":"53",
    "addr:postcode":"35240",
    "addr:street":"Avda Carlos V",
    "iso:country":"ES",
    "sg:address":"Avda Carlos V, 53",
    "sg:city":"Carrizal",
    "sg:orig_category":"Asesor\u00cda De Formaci\u00d3n Y Gesti\u00d3n De Personal",
    "sg:phone":"+34 928 78 76 86",
    "sg:postcode":"35240",
    "sg:province":"Las Palmas",
    "wof:name":"Sanchez Leon Ricardo",
    "wof:placetype":"venue"
},
  "geometry": {"coordinates":[-15.4052448273,27.9114131927],"type":"Point"}
}