{
  "type": "Feature",
  "properties": {
    "addr:full":"Calle de Simon Ruiz, 4 Medina Campo Valladolid 47400",
    "addr:housenumber":"4",
    "addr:postcode":"47400",
    "addr:street":"Calle De Simon Ruiz",
    "iso:country":"ES",
    "sg:address":"Calle de Simon Ruiz, 4",
    "sg:city":"Medina Campo",
    "sg:orig_category":"Mercer\u00cda, Lencer\u00cda (al Por Menor)",
    "sg:phone":"+34 983 80 37 55",
    "sg:postcode":"47400",
    "sg:province":"Valladolid",
    "wof:name":"Rodriguez Fernandez Purificacion",
    "wof:placetype":"venue"
},
  "geometry": {"coordinates":[-4.9129090309,41.3068161011],"type":"Point"}
}