{
  "type": "Feature",
  "properties": {
    "iso:country":"ES",
    "sg:address":"Calle de Antonio Garcia Larrosa, 14",
    "sg:city":"Benejuzar",
    "sg:orig_category":"Suministros Para Exposiciones, Ferias, Salones",
    "sg:phone":"+34 965 35 67 40",
    "sg:postcode":"03390",
    "sg:province":"Alicante",
    "sg:website":"www.parallelexpo.com",
    "wof:name":"Paralelle Euro Expo S.l.",
    "wof:placetype":"venue"
},
  "geometry": {"coordinates":[-0.8389053941,38.0740013123],"type":"Point"}
}