{
  "type": "Feature",
  "properties": {
    "addr:full":"Calle de Praga, 3 Chiclana De La Frontera C\u00e1diz 11130",
    "addr:housenumber":"3",
    "addr:postcode":"11130",
    "addr:street":"Calle De Praga",
    "iso:country":"ES",
    "sg:address":"Calle de Praga, 3",
    "sg:city":"Chiclana De La Frontera",
    "sg:orig_category":"M\u00c9dicos: Naturistas",
    "sg:phone":"+34 956 40 52 98",
    "sg:postcode":"11130",
    "sg:province":"C\u00e1diz",
    "wof:name":"Previament",
    "wof:placetype":"venue"
},
  "geometry": {"coordinates":[-6.1501049995,36.4115753174],"type":"Point"}
}