{
  "type": "Feature",
  "properties": {
    "iso:country":"ES",
    "sg:address":"Canar Es, 100",
    "sg:city":"Sta. Eularia Riu",
    "sg:orig_category":"Electrodom\u00c9sticos (al Por Menor)",
    "sg:phone":"+34 971 33 28 16",
    "sg:postcode":"07840",
    "sg:province":"Islas Baleares",
    "wof:name":"Noguera Jose Alejandro",
    "wof:placetype":"venue"
},
  "geometry": {"coordinates":[1.5341850519,38.9850311279],"type":"Point"}
}