{
  "type": "Feature",
  "properties": {
    "addr:full":"Avda Lugo, 15 Pontevedra Pontevedra 36004",
    "addr:housenumber":"15",
    "addr:postcode":"36004",
    "addr:street":"Avda Lugo",
    "iso:country":"ES",
    "sg:address":"Avda Lugo, 15",
    "sg:city":"Pontevedra",
    "sg:orig_category":"Pintura, Barniz, Productos Asimilables (fabricaci\u00d3n, Al Por Mayor)",
    "sg:phone":"+34 986 85 33 14",
    "sg:postcode":"36004",
    "sg:province":"Pontevedra",
    "wof:name":"Gallega De Revestimientos S.l.",
    "wof:placetype":"venue"
},
  "geometry": {"coordinates":[-8.6219539642,42.4348869324],"type":"Point"}
}