{
  "type": "Feature",
  "properties": {
    "addr:full":"Avda Castros (los), 73 Santander Cantabria 39005",
    "addr:housenumber":"73",
    "addr:postcode":"39005",
    "addr:street":"Avda Castros Los",
    "iso:country":"ES",
    "sg:address":"Avda Castros (los), 73",
    "sg:city":"Santander",
    "sg:orig_category":"Mercer\u00cda, Lencer\u00cda (al Por Menor)",
    "sg:phone":"+34 942 21 37 66",
    "sg:postcode":"39005",
    "sg:province":"Cantabria",
    "wof:name":"Fundacion Cadah",
    "wof:placetype":"venue"
},
  "geometry": {"coordinates":[-3.8096990585,43.4695663452],"type":"Point"}
}