{
  "type": "Feature",
  "properties": {
    "iso:country":"ES",
    "sg:address":"Avda Elche, S/n",
    "sg:city":"Alacant",
    "sg:orig_category":"Agencias Y Agentes Comerciales, Representantes",
    "sg:phone":"+34 965 28 05 38",
    "sg:postcode":"03008",
    "sg:province":"Alicante",
    "wof:name":"Alburquerque Esteban Victoriano",
    "wof:placetype":"venue"
},
  "geometry": {"coordinates":[-0.5352352858,38.3008804321],"type":"Point"}
}