{
  "type": "Feature",
  "properties": {
    "iso:country":"ES",
    "sg:address":"Calle de Galileo, 70",
    "sg:city":"Madrid",
    "sg:orig_category":"Caf\u00c9s, Bares, Cervecer\u00cdas",
    "sg:phone":"+34 914 46 56 75",
    "sg:postcode":"28015",
    "sg:province":"Madrid",
    "wof:name":"Cafeteria Sabando S.l.",
    "wof:placetype":"venue"
},
  "geometry": {"coordinates":[-3.7099640369,40.4359550476],"type":"Point"}
}