{
  "type": "Feature",
  "properties": {
    "iso:country":"ES",
    "sg:address":"Avda. Adelfas, 9",
    "sg:city":"Matalasca\u00f1as",
    "sg:orig_category":"Estancos",
    "sg:phone":"+34 959 44 85 54",
    "sg:postcode":"21760",
    "sg:province":"Huelva",
    "wof:name":"Diaz Leal Francisco",
    "wof:placetype":"venue"
},
  "geometry": {"coordinates":[-6.5641069412,37.008480072],"type":"Point"}
}