{
  "type": "Feature",
  "properties": {
    "iso:country":"ES",
    "sg:address":"Calle de Primo De Rivera, 30",
    "sg:city":"Pe\u00f1iscola",
    "sg:orig_category":"Inmobiliaria (agencias)",
    "sg:phone":"+34 964 48 95 68",
    "sg:postcode":"12598",
    "sg:province":"Castell\u00f3n",
    "wof:name":"I.k. Inora S.l.",
    "wof:placetype":"venue"
},
  "geometry": {"coordinates":[0.4027990103,40.3603897095],"type":"Point"}
}