{
  "type": "Feature",
  "properties": {
    "addr:full":"Plaz San Rafael, 18 Vecindario Las Palmas 35110",
    "addr:housenumber":"18",
    "addr:postcode":"35110",
    "addr:street":"Plaz San Rafael;Palmas",
    "iso:country":"ES",
    "sg:address":"Plaz San Rafael, 18",
    "sg:city":"Vecindario",
    "sg:orig_category":"Inmobiliaria (agencias)",
    "sg:phone":"+34 928 12 21 69",
    "sg:postcode":"35110",
    "sg:province":"Las Palmas",
    "wof:name":"Hijos De Dominguez Cordero S.l",
    "wof:placetype":"venue"
},
  "geometry": {"coordinates":[-15.4429092407,27.8477802277],"type":"Point"}
}