{
  "type": "Feature",
  "properties": {
    "addr:full":"Calle de Virgen De La Paz, S/n Manzanares Ciudad Real 13200",
    "addr:housenumber":"s / n",
    "addr:postcode":"13200",
    "addr:street":"Calle De Virgen De La Paz",
    "iso:country":"ES",
    "sg:address":"Calle de Virgen De La Paz, S/n",
    "sg:city":"Manzanares",
    "sg:orig_category":"Frutas, Legumbres Frescas Y Tempranas (al Por Menor)",
    "sg:phone":"+34 926 61 38 21",
    "sg:postcode":"13200",
    "sg:province":"Ciudad Real",
    "wof:name":"Frutas Guillen S.l.",
    "wof:placetype":"venue"
},
  "geometry": {"coordinates":[-3.3721790314,39.0001411438],"type":"Point"}
}