{
  "type": "Feature",
  "properties": {
    "iso:country":"ES",
    "sg:address":"Carr Estacio, S/n",
    "sg:city":"S. Guim Freixenet",
    "sg:orig_category":"Fabricaci\u00d3n, Importaci\u00d3n De L\u00c1mparas Y Bombillas",
    "sg:phone":"+34 973 55 64 90",
    "sg:postcode":"25270",
    "sg:province":"Lleida",
    "wof:name":"Morillas Serna Raimundo",
    "wof:placetype":"venue"
},
  "geometry": {"coordinates":[1.4212708473,41.6552581787],"type":"Point"}
}