{
  "type": "Feature",
  "properties": {
    "addr:full":"Calle de San Miguel, 83 Ossa Montiel Albacete 02611",
    "addr:housenumber":"83",
    "addr:postcode":"02611",
    "addr:street":"Calle De San Miguel;Montiel",
    "iso:country":"ES",
    "sg:address":"Calle de San Miguel, 83",
    "sg:city":"Ossa Montiel",
    "sg:orig_category":"Cr\u00cda De Poller\u00cda Y De Conejos",
    "sg:phone":"+34 967 37 80 19",
    "sg:postcode":"02611",
    "sg:province":"Albacete",
    "wof:name":"Moreno Oliver Francisco",
    "wof:placetype":"venue"
},
  "geometry": {"coordinates":[-2.7466540337,38.9612350464],"type":"Point"}
}