{
  "type": "Feature",
  "properties": {
    "iso:country":"ES",
    "sg:address":"Plaz Alcalde J. R. Aguirreche, S/n",
    "sg:city":"Irun",
    "sg:classifiers":[
        {
            "category":"Taxi",
            "type":"Transportation"
        }
    ],
    "sg:phone":"+34 943 63 56 26",
    "sg:postcode":"20302",
    "sg:province":"Guip\u00f9zcoa",
    "wof:name":"Gremio De Taxistas",
    "wof:placetype":"venue"
},
  "geometry": {"coordinates":[-1.7919529676,43.3395576477],"type":"Point"}
}