{
  "type": "Feature",
  "properties": {
    "addr:full":"Calle de Francisco Sicilia, 4 Torrelodones Madrid 28250",
    "addr:housenumber":"4",
    "addr:postcode":"28250",
    "addr:street":"Calle De Francisco Sicilia",
    "iso:country":"ES",
    "sg:address":"Calle de Francisco Sicilia, 4",
    "sg:city":"Torrelodones",
    "sg:orig_category":"Asociaciones, Organismos Culturales Y Socioeducativos",
    "sg:phone":"+34 918 59 47 79",
    "sg:postcode":"28250",
    "sg:province":"Madrid",
    "wof:name":"Ayuntamiento De Torrelodones",
    "wof:placetype":"venue"
},
  "geometry": {"coordinates":[-3.9258089066,40.5773582458],"type":"Point"}
}