{
  "type": "Feature",
  "properties": {
    "iso:country":"ES",
    "sg:address":"Calle de Juan Rejon, 99",
    "sg:city":"Palmas De Gran Canaria",
    "sg:orig_category":"Bazares, Art\u00cdculos De Limpieza Y De Cocina (al Por Menor)",
    "sg:phone":"+34 928 47 02 51",
    "sg:postcode":"35008",
    "sg:province":"Las Palmas",
    "wof:name":"Lettingco S.l.",
    "wof:placetype":"venue"
},
  "geometry": {"coordinates":[-15.4241456985,28.1494979858],"type":"Point"}
}