{
  "type": "Feature",
  "properties": {
    "iso:country":"ES",
    "sg:address":"Avda Mediterraneo, S/n",
    "sg:city":"Salobre\u00f1a",
    "sg:orig_category":"Inmobiliaria (agencias)",
    "sg:phone":"+34 958 61 21 42",
    "sg:postcode":"18680",
    "sg:province":"Granada",
    "wof:name":"Rocamar Construcciones Sociedad Limitada",
    "wof:placetype":"venue"
},
  "geometry": {"coordinates":[-3.5825889111,36.7434005737],"type":"Point"}
}