{
  "type": "Feature",
  "properties": {
    "addr:full":"Pg Ribera, 121 Barriada Nova Barcelona 08420",
    "addr:housenumber":"121",
    "addr:postcode":"08420",
    "addr:street":"Ribera;Nova Barcelona",
    "iso:country":"ES",
    "sg:address":"Pg Ribera, 121",
    "sg:city":"Barriada Nova",
    "sg:orig_category":"Abrasivos Y Superabrasivos (fabricaci\u00d3n, Al Por Mayor)",
    "sg:phone":"+34 938 46 80 30",
    "sg:postcode":"08420",
    "sg:province":"Barcelona",
    "wof:name":"Abraflex S.a.",
    "wof:placetype":"venue"
},
  "geometry": {"coordinates":[2.169919,41.387917],"type":"Point"}
}