{
  "type": "Feature",
  "properties": {
    "addr:full":"Plaz Mayor, 5 Marisma Y Puntales Adriano Sevilla 41728",
    "addr:housenumber":"5",
    "addr:postcode":"41728",
    "addr:street":"Plaz Mayor;Y",
    "iso:country":"ES",
    "sg:address":"Plaz Mayor, 5",
    "sg:city":"Marisma Y Puntales Adriano",
    "sg:orig_category":"Productos Fitosanitarios (negocio, Aplicaci\u00d3n)",
    "sg:phone":"+34 955 95 08 03",
    "sg:postcode":"41728",
    "sg:province":"Sevilla",
    "wof:name":"El Monte Adriano Sociedad Cooperativa Andaluza",
    "wof:placetype":"venue"
},
  "geometry": {"coordinates":[-5.9843139648,37.1528396606],"type":"Point"}
}