{
  "type": "Feature",
  "properties": {
    "iso:country":"ES",
    "sg:address":"Calle de Marques De Hinojares (del), 8",
    "sg:city":"Mejorada Campo",
    "sg:orig_category":"Estancos",
    "sg:phone":"+34 916 68 23 23",
    "sg:postcode":"28840",
    "sg:province":"Madrid",
    "wof:name":"Zamorano Peral Luis Mariano",
    "wof:placetype":"venue"
},
  "geometry": {"coordinates":[-3.486923933,40.3986854553],"type":"Point"}
}