{
  "type": "Feature",
  "properties": {
    "addr:full":"Calle de Navarra, 9 Toledo Toledo 45005",
    "addr:housenumber":"9",
    "addr:postcode":"45005",
    "addr:street":"Calle De Navarra",
    "iso:country":"ES",
    "sg:address":"Calle de Navarra, 9",
    "sg:city":"Toledo",
    "sg:orig_category":"Electricidad: Instaladores",
    "sg:phone":"+34 925 21 00 19",
    "sg:postcode":"45005",
    "sg:province":"Toledo",
    "wof:name":"Pancho Instalaciones Electricas S.l.",
    "wof:placetype":"venue"
},
  "geometry": {"coordinates":[-4.0361418724,39.874797821],"type":"Point"}
}