{
  "type": "Feature",
  "properties": {
    "addr:full":"Calle de Madrid, 1 Burgos Burgos 09002",
    "addr:housenumber":"1",
    "addr:postcode":"09002",
    "addr:street":"Calle De Madrid",
    "iso:country":"ES",
    "sg:address":"Calle de Madrid, 1",
    "sg:city":"Burgos",
    "sg:orig_category":"Inmobiliaria (agencias)",
    "sg:phone":"+34 947 25 69 96",
    "sg:postcode":"09002",
    "sg:province":"Burgos",
    "wof:name":"Inmobiliaria Vaolmi S.l.",
    "wof:placetype":"venue"
},
  "geometry": {"coordinates":[-3.7016539574,42.3382492065],"type":"Point"}
}