{
  "type": "Feature",
  "properties": {
    "iso:country":"ES",
    "sg:address":"Ctra Campo Real (de), Km. 0003,1",
    "sg:city":"Arganda",
    "sg:orig_category":"Piedra Natural",
    "sg:phone":"+34 918 71 05 16",
    "sg:postcode":"28500",
    "sg:province":"Madrid",
    "wof:name":"Alsana S.a.",
    "wof:placetype":"venue"
},
  "geometry": {"coordinates":[-3.4566385746,40.3201751709],"type":"Point"}
}