{
  "type": "Feature",
  "properties": {
    "iso:country":"ES",
    "sg:address":"Carrer de Anselm Clave, 7",
    "sg:city":"Barri Maritim De Comarruga",
    "sg:orig_category":"Molduras, Junquillos, Listones Y Molduras Perforadas",
    "sg:phone":"+34 977 68 22 35",
    "sg:postcode":"43880",
    "sg:province":"Tarragona",
    "wof:name":"Padilla Rodriguez Antonio",
    "wof:placetype":"venue"
},
  "geometry": {"coordinates":[1.5386699438,41.1833496094],"type":"Point"}
}