{
  "type": "Feature",
  "properties": {
    "iso:country":"ES",
    "sg:address":"Calle de Bernabe Soriano, 1",
    "sg:city":"Jaen",
    "sg:orig_category":"Cl\u00cdnicas Dentales",
    "sg:phone":"+34 953 24 21 26",
    "sg:postcode":"23001",
    "sg:province":"Ja\u00e9n",
    "wof:name":"Sanchez Cobo Paulino",
    "wof:placetype":"venue"
},
  "geometry": {"coordinates":[-3.7891476154,37.7659606934],"type":"Point"}
}