{
  "type": "Feature",
  "properties": {
    "iso:country":"ES",
    "sg:address":"Rua Pexigo De Arriba (do), 34",
    "sg:city":"Santiago De Compostela",
    "sg:orig_category":"Alimentaci\u00d3n General (al Por Menor)",
    "sg:phone":"+34 981 57 56 92",
    "sg:postcode":"15703",
    "sg:province":"La Coru\u00f1a",
    "wof:name":"Sanchez Balsa Manuel",
    "wof:placetype":"venue"
},
  "geometry": {"coordinates":[-8.5401163101,42.8766670227],"type":"Point"}
}