{
  "type": "Feature",
  "properties": {
    "addr:full":"Carrer de Sequia, 24 Manresa Barcelona 08242",
    "addr:housenumber":"24",
    "addr:postcode":"08242",
    "addr:street":"Carrer De Sequia",
    "iso:country":"ES",
    "sg:address":"Carrer de Sequia, 24",
    "sg:city":"Manresa",
    "sg:orig_category":"Poli\u00c9ster",
    "sg:phone":"+34 938 73 52 44",
    "sg:postcode":"08242",
    "sg:province":"Barcelona",
    "wof:name":"Torra Pi\u00f1era Antonia",
    "wof:placetype":"venue"
},
  "geometry": {"coordinates":[1.8297770023,41.7305259705],"type":"Point"}
}