{
  "type": "Feature",
  "properties": {
    "iso:country":"ES",
    "sg:address":"Pg Cortils I Vieta, 24",
    "sg:city":"Blanes",
    "sg:orig_category":"Inmobiliaria (agencias)",
    "sg:phone":"+34 972 33 27 38",
    "sg:postcode":"17300",
    "sg:province":"Girona",
    "sg:website":"www.mapicassa.com",
    "wof:name":"Estudio Lloret S.l.",
    "wof:placetype":"venue"
},
  "geometry": {"coordinates":[2.7920069695,41.6735687256],"type":"Point"}
}