{
  "type": "Feature",
  "properties": {
    "addr:full":"Porto Do Souto, S/n Cea Ourense 32130",
    "addr:housenumber":"s / n",
    "addr:postcode":"32130",
    "iso:country":"ES",
    "sg:address":"Porto Do Souto, S/n",
    "sg:city":"Cea",
    "sg:orig_category":"Empresas De Carpinter\u00cda De Madera",
    "sg:phone":"+34 988 28 20 73",
    "sg:postcode":"32130",
    "sg:province":"Ourense",
    "wof:name":"Vazquez Janeiro Manuel",
    "wof:placetype":"venue"
},
  "geometry": {"coordinates":[-7.9874720573,42.4763221741],"type":"Point"}
}