{
  "type": "Feature",
  "properties": {
    "iso:country":"ES",
    "sg:address":"Carr Joan Pau Climent, 18",
    "sg:city":"Villafranca Cid",
    "sg:orig_category":"Empresas De Desmonte",
    "sg:phone":"+34 964 44 12 32",
    "sg:postcode":"12150",
    "sg:province":"Castell\u00f3n",
    "wof:name":"Pitarch Bono Abelardo",
    "wof:placetype":"venue"
},
  "geometry": {"coordinates":[-0.2566420138,40.4288673401],"type":"Point"}
}