{
  "type": "Feature",
  "properties": {
    "addr:full":"Calle de Vall De Uxo, 13 Nules Castell\u00f3n 12520",
    "addr:housenumber":"13",
    "addr:postcode":"12520",
    "addr:street":"Calle De Vall De Uxo",
    "iso:country":"ES",
    "sg:address":"Calle de Vall De Uxo, 13",
    "sg:city":"Nules",
    "sg:orig_category":"Empresarios",
    "sg:phone":"+34 964 67 39 93",
    "sg:postcode":"12520",
    "sg:province":"Castell\u00f3n",
    "wof:name":"Saura Herrero Juan Jose",
    "wof:placetype":"venue"
},
  "geometry": {"coordinates":[-0.1542440057,39.852596283],"type":"Point"}
}