{
  "type": "Feature",
  "properties": {
    "iso:country":"ES",
    "sg:address":"Calle de Virgen Del Coro, 3",
    "sg:city":"Madrid",
    "sg:orig_category":"Cerrajer\u00cda, Ferrallista",
    "sg:phone":"+34 914 03 84 00",
    "sg:postcode":"28027",
    "sg:province":"Madrid",
    "wof:name":"Grupo Eurominio S.l.",
    "wof:placetype":"venue"
},
  "geometry": {"coordinates":[-3.6582980156,40.433883667],"type":"Point"}
}