{
  "type": "Feature",
  "properties": {
    "iso:country":"ES",
    "sg:address":"Calle de Constitucion, 11",
    "sg:city":"Azuaga",
    "sg:orig_category":"Servicios Gsm",
    "sg:phone":"+34 924 13 78 43",
    "sg:postcode":"06920",
    "sg:province":"Badajoz",
    "wof:name":"Digital Sur S.l.l.",
    "wof:placetype":"venue"
},
  "geometry": {"coordinates":[-5.6766695976,38.2603569031],"type":"Point"}
}