{
  "type": "Feature",
  "properties": {
    "iso:country":"ES",
    "sg:address":"Puerto, 12",
    "sg:city":"Laxe",
    "sg:orig_category":"Fabricaci\u00d3n, Reparaci\u00d3n Y Mantenimiento De Construcciones Navales Y Fluviales",
    "sg:phone":"+34 981 72 81 50",
    "sg:postcode":"15117",
    "sg:province":"La Coru\u00f1a",
    "wof:name":"Pose De La Fuente Salvador",
    "wof:placetype":"venue"
},
  "geometry": {"coordinates":[-9.0046443939,43.2222595215],"type":"Point"}
}