{
  "type": "Feature",
  "properties": {
    "iso:country":"ES",
    "sg:address":"Calle de Dos De Mayo, 8",
    "sg:city":"Callosa Segura",
    "sg:orig_category":"Plomeros",
    "sg:phone":"+34 965 31 02 18",
    "sg:postcode":"03360",
    "sg:province":"Alicante",
    "wof:name":"Cerro Lidon Filomeno Del",
    "wof:placetype":"venue"
},
  "geometry": {"coordinates":[-0.8769571781,38.1285476685],"type":"Point"}
}