{
  "type": "Feature",
  "properties": {
    "addr:full":"Calle de Doctor Cornago, 20 Pozuelo De Alarcon Madrid 28223",
    "addr:housenumber":"20",
    "addr:postcode":"28223",
    "addr:street":"Calle De Doctor Cornago",
    "iso:country":"ES",
    "sg:address":"Calle de Doctor Cornago, 20",
    "sg:city":"Pozuelo De Alarcon",
    "sg:orig_category":"Papeler\u00cdas, Librer\u00cdas",
    "sg:phone":"+34 917 15 65 95",
    "sg:postcode":"28223",
    "sg:province":"Madrid",
    "wof:name":"Gomez-chacon Rodriguez Maria Pilar",
    "wof:placetype":"venue"
},
  "geometry": {"coordinates":[-3.8138313293,40.436882019],"type":"Point"}
}