{
  "type": "Feature",
  "properties": {
    "iso:country":"ES",
    "sg:address":"Avda Navarra (de), 27",
    "sg:city":"Alberite",
    "sg:orig_category":"Promotores Constructores",
    "sg:phone":"+34 941 43 65 03",
    "sg:postcode":"26141",
    "sg:province":"La Rioja",
    "wof:name":"Mozun Jadraque Luis",
    "wof:placetype":"venue"
},
  "geometry": {"coordinates":[-2.4390790462,42.4073791504],"type":"Point"}
}