{
  "type": "Feature",
  "properties": {
    "addr:full":"Jose Hernandez, 14 Espinardo Murcia 30100",
    "addr:housenumber":"14",
    "addr:postcode":"30100",
    "addr:street":"Jose Hernandez",
    "iso:country":"ES",
    "sg:address":"Jose Hernandez, 14",
    "sg:city":"Espinardo",
    "sg:orig_category":"Condimentos, Especias, Vinagres, Salsas Preparadas (fabricaci\u00d3n, Al Por Mayor)",
    "sg:phone":"+34 968 30 70 45",
    "sg:postcode":"30100",
    "sg:province":"Murcia",
    "wof:name":"Tres Flores Del Sureste S.l.",
    "wof:placetype":"venue"
},
  "geometry": {"coordinates":[-1.1514029503,38.009262085],"type":"Point"}
}