{
  "type": "Feature",
  "properties": {
    "iso:country":"ES",
    "sg:address":"Calle de Villafranca, 1",
    "sg:city":"Madrid",
    "sg:orig_category":"Peluquer\u00cdas, Peluquer\u00cda Mixta",
    "sg:phone":"+34 913 61 02 66",
    "sg:postcode":"28028",
    "sg:province":"Madrid",
    "wof:name":"Luque Martin Sacramento",
    "wof:placetype":"venue"
},
  "geometry": {"coordinates":[-3.6653499603,40.4336357117],"type":"Point"}
}