{
  "type": "Feature",
  "properties": {
    "iso:country":"ES",
    "sg:address":"Poli Poligon Industrial, S/n",
    "sg:city":"Picassent",
    "sg:orig_category":"F\u00c1bricas De Ladrillo Y Tejas",
    "sg:phone":"+34 961 24 03 75",
    "sg:postcode":"46220",
    "sg:province":"Valencia",
    "wof:name":"Jorda Such Y Cia S.l.",
    "wof:placetype":"venue"
},
  "geometry": {"coordinates":[-0.4524689913,39.3585700989],"type":"Point"}
}