{
  "type": "Feature",
  "properties": {
    "iso:country":"ES",
    "sg:address":"Pase General Davila, 30",
    "sg:city":"Santander",
    "sg:orig_category":"Sociedades, Compa\u00d1\u00cdas Aseguradoras",
    "sg:phone":"+34 942 29 13 48",
    "sg:postcode":"39005",
    "sg:province":"Cantabria",
    "wof:name":"Atlantis Mediacion, S.a.",
    "wof:placetype":"venue"
},
  "geometry": {"coordinates":[-3.793201685,43.4685440063],"type":"Point"}
}