{
  "type": "Feature",
  "properties": {
    "addr:full":"Carrer de Sort (de La), 1 Torredembarra Tarragona 43830",
    "addr:housenumber":"1",
    "addr:postcode":"43830",
    "addr:street":"Carrer De Sort De La",
    "iso:country":"ES",
    "sg:address":"Carrer de Sort (de La), 1",
    "sg:city":"Torredembarra",
    "sg:orig_category":"Artesan\u00cda Y Trabajos Manuales: Suministros (al Por Menor)",
    "sg:phone":"+34 977 64 43 37",
    "sg:postcode":"43830",
    "sg:province":"Tarragona",
    "wof:name":"Perez De La Vega Sergio",
    "wof:placetype":"venue"
},
  "geometry": {"coordinates":[1.3972990513,41.1441917419],"type":"Point"}
}