{
  "type": "Feature",
  "properties": {
    "iso:country":"ES",
    "sg:address":"Avda Constitucion, 16",
    "sg:city":"Talavera Reina",
    "sg:orig_category":"Ingenier\u00cda, Centros De Estudios (diversos)",
    "sg:phone":"+34 925 81 35 13",
    "sg:postcode":"45600",
    "sg:province":"Toledo",
    "wof:name":"Corrochano Garcia Jose Manuel",
    "wof:placetype":"venue"
},
  "geometry": {"coordinates":[-4.8141322136,39.9644622803],"type":"Point"}
}