{
  "type": "Feature",
  "properties": {
    "addr:full":"Rond Doctor Turro, 18 Mataro Barcelona 08304",
    "addr:housenumber":"18",
    "addr:postcode":"08304",
    "addr:street":"Doctor Turro",
    "iso:country":"ES",
    "sg:address":"Rond Doctor Turro, 18",
    "sg:city":"Mataro",
    "sg:orig_category":"Ense\u00d1anza: Comercio, Gesti\u00d3n, Inform\u00c1tica",
    "sg:phone":"+34 937 56 91 54",
    "sg:postcode":"08304",
    "sg:province":"Barcelona",
    "wof:name":"Rodriguez Fernandez Marco Antonio",
    "wof:placetype":"venue"
},
  "geometry": {"coordinates":[2.4403870106,41.5708694458],"type":"Point"}
}