{
  "type": "Feature",
  "properties": {
    "iso:country":"ES",
    "sg:address":"Rbla Rambla Nova, 114",
    "sg:city":"Tarragona",
    "sg:orig_category":"Abogados",
    "sg:phone":"+34 977 21 27 34",
    "sg:postcode":"43001",
    "sg:province":"Tarragona",
    "wof:name":"Alegret Tondo Jose Maria",
    "wof:placetype":"venue"
},
  "geometry": {"coordinates":[1.2460945845,41.118637085],"type":"Point"}
}