{
  "type": "Feature",
  "properties": {
    "addr:full":"Calle de Ferrocarril, 4 Valladolid Valladolid 47004",
    "addr:housenumber":"4",
    "addr:postcode":"47004",
    "addr:street":"Calle De Ferrocarril",
    "iso:country":"ES",
    "sg:address":"Calle de Ferrocarril, 4",
    "sg:city":"Valladolid",
    "sg:orig_category":"Expertos Contables, Revisores De Cuentas",
    "sg:phone":"+34 983 39 53 80",
    "sg:postcode":"47004",
    "sg:province":"Valladolid",
    "wof:name":"Rivero Asociados S.l.",
    "wof:placetype":"venue"
},
  "geometry": {"coordinates":[-4.7232060432,41.645740509],"type":"Point"}
}