{
  "type": "Feature",
  "properties": {
    "iso:country":"ES",
    "sg:address":"Calle de Cervantes, 11",
    "sg:city":"Soto Marina",
    "sg:orig_category":"Muebles",
    "sg:phone":"+34 942 57 82 76",
    "sg:postcode":"39110",
    "sg:province":"Cantabria",
    "wof:name":"Perez Perez Jose Luis",
    "wof:placetype":"venue"
},
  "geometry": {"coordinates":[-3.8932683468,43.4682579041],"type":"Point"}
}