{
  "type": "Feature",
  "properties": {
    "iso:country":"ES",
    "sg:address":"Calle de Batalla Del Salado, 14",
    "sg:city":"Madrid",
    "sg:orig_category":"Audiovisuales (producci\u00d3n, Edici\u00d3n, Realizaci\u00d3n)",
    "sg:phone":"+34 915 39 78 44",
    "sg:postcode":"28045",
    "sg:province":"Madrid",
    "wof:name":"Carrillo Flores Carmen",
    "wof:placetype":"venue"
},
  "geometry": {"coordinates":[-3.6960186958,40.402671814],"type":"Point"}
}