{
  "type": "Feature",
  "properties": {
    "iso:country":"ES",
    "sg:address":"Carrer de Murcia, 24",
    "sg:city":"Barcelona",
    "sg:orig_category":"Mec\u00c1nico Del Autom\u00d3vil",
    "sg:phone":"+34 933 40 08 50",
    "sg:postcode":"08027",
    "sg:province":"Barcelona",
    "wof:name":"Barcelona Dealer Motor Internacional Company S.l.",
    "wof:placetype":"venue"
},
  "geometry": {"coordinates":[2.1887559891,41.4150238037],"type":"Point"}
}