{
  "type": "Feature",
  "properties": {
    "addr:full":"Calle de San Vicente Martir, 114 Valencia Valencia 46007",
    "addr:housenumber":"114",
    "addr:postcode":"46007",
    "addr:street":"Calle De San Vicente Martir",
    "iso:country":"ES",
    "sg:address":"Calle de San Vicente Martir, 114",
    "sg:city":"Valencia",
    "sg:orig_category":"Bancos",
    "sg:phone":"+34 963 52 22 10",
    "sg:postcode":"46007",
    "sg:province":"Valencia",
    "wof:name":"Banco De Valencia S.a.",
    "wof:placetype":"venue"
},
  "geometry": {"coordinates":[-0.3815610111,39.4663009644],"type":"Point"}
}