{
  "type": "Feature",
  "properties": {
    "addr:full":"Carrer de Creu Coberta, 126 Barcelona Barcelona 08014",
    "addr:housenumber":"126",
    "addr:postcode":"08014",
    "addr:street":"Carrer De Creu Coberta",
    "iso:country":"ES",
    "sg:address":"Carrer de Creu Coberta, 126",
    "sg:city":"Barcelona",
    "sg:orig_category":"Caf\u00c9s, Bares, Cervecer\u00cdas",
    "sg:phone":"+34 934 31 98 08",
    "sg:postcode":"08014",
    "sg:province":"Barcelona",
    "wof:name":"Jm Center S.l.",
    "wof:placetype":"venue"
},
  "geometry": {"coordinates":[2.1410648823,41.3754310608],"type":"Point"}
}