{
  "type": "Feature",
  "properties": {
    "addr:full":"Calle de Cervantes, 10 Merida Badajoz 06800",
    "addr:housenumber":"10",
    "addr:postcode":"06800",
    "addr:street":"Calle De Cervantes",
    "iso:country":"ES",
    "sg:address":"Calle de Cervantes, 10",
    "sg:city":"Merida",
    "sg:orig_category":"Abogados",
    "sg:phone":"+34 924 30 20 66",
    "sg:postcode":"06800",
    "sg:province":"Badajoz",
    "wof:name":"Bezos Mari\u00d1o Gerardo",
    "wof:placetype":"venue"
},
  "geometry": {"coordinates":[-6.3428678513,38.9186172485],"type":"Point"}
}