{
  "type": "Feature",
  "properties": {
    "iso:country":"ES",
    "sg:address":"Carr Solades, 16",
    "sg:city":"Villarreal",
    "sg:orig_category":"Promotores Constructores",
    "sg:phone":"+34 964 53 46 00",
    "sg:postcode":"12540",
    "sg:province":"Castell\u00f3n",
    "wof:name":"Obravil S.l.",
    "wof:placetype":"venue"
},
  "geometry": {"coordinates":[-0.0952939987,39.9453048706],"type":"Point"}
}