{
  "type": "Feature",
  "properties": {
    "addr:full":"Calle de Fuente El Sol, 99 Valladolid Valladolid 47009",
    "addr:housenumber":"99",
    "addr:postcode":"47009",
    "addr:street":"Calle De Fuente El Sol",
    "iso:country":"ES",
    "sg:address":"Calle de Fuente El Sol, 99",
    "sg:city":"Valladolid",
    "sg:orig_category":"Artes Gr\u00c1ficas, Artes Pl\u00c1sticas (curso)",
    "sg:phone":"+34 983 35 47 55",
    "sg:postcode":"47009",
    "sg:province":"Valladolid",
    "wof:name":"Gasllar S.a.",
    "wof:placetype":"venue"
},
  "geometry": {"coordinates":[-4.7344126701,41.6640930176],"type":"Point"}
}