{
  "type": "Feature",
  "properties": {
    "addr:full":"Alcoy, 22 Cocentaina Alicante 03820",
    "addr:housenumber":"22",
    "addr:postcode":"03820",
    "addr:street":"Alcoy",
    "iso:country":"ES",
    "sg:address":"Alcoy, 22",
    "sg:city":"Cocentaina",
    "sg:orig_category":"Deportes Y Programas De Aventura",
    "sg:phone":"+34 966 50 01 01",
    "sg:postcode":"03820",
    "sg:province":"Alicante",
    "wof:name":"Aquabelum S.l.",
    "wof:placetype":"venue"
},
  "geometry": {"coordinates":[-0.4404967129,38.7392120361],"type":"Point"}
}