{
  "type": "Feature",
  "properties": {
    "iso:country":"ES",
    "sg:address":"Calle de Pio Baroja, 10",
    "sg:city":"Rota",
    "sg:orig_category":"Establecimientos De Cura, Prevenci\u00d3n Y Readaptaci\u00d3n",
    "sg:phone":"+34 956 81 43 11",
    "sg:postcode":"11520",
    "sg:province":"C\u00e1diz",
    "wof:name":"Asociacion Local De Ayuda Al Toxicomano",
    "wof:placetype":"venue"
},
  "geometry": {"coordinates":[-6.3592672348,36.6231117249],"type":"Point"}
}