{
  "type": "Feature",
  "properties": {
    "addr:full":"Calle de San Juan De Letran, 17 Granada Granada 18012",
    "addr:housenumber":"17",
    "addr:postcode":"18012",
    "addr:street":"Calle De San",
    "iso:country":"ES",
    "sg:address":"Calle de San Juan De Letran, 17",
    "sg:city":"Granada",
    "sg:orig_category":"Caf\u00c9s, Bares, Cervecer\u00cdas",
    "sg:phone":"+34 958 29 60 18",
    "sg:postcode":"18012",
    "sg:province":"Granada",
    "wof:name":"Lucena Jimenez Manuel",
    "wof:placetype":"venue"
},
  "geometry": {"coordinates":[-3.6076750755,37.1862182617],"type":"Point"}
}