{
  "type": "Feature",
  "properties": {
    "addr:full":"G.v. Corts Catalanes, 464 Barcelona Barcelona 08015",
    "addr:housenumber":"464",
    "addr:postcode":"08015",
    "addr:street":"Catalanes",
    "iso:country":"ES",
    "sg:address":"G.v. Corts Catalanes, 464",
    "sg:city":"Barcelona",
    "sg:orig_category":"Reposter\u00cdas",
    "sg:phone":"+34 933 25 21 48",
    "sg:postcode":"08015",
    "sg:province":"Barcelona",
    "wof:name":"Iglesias Teixidor Luis",
    "wof:placetype":"venue"
},
  "geometry": {"coordinates":[2.155217886,41.3791885376],"type":"Point"}
}