{
  "type": "Feature",
  "properties": {
    "iso:country":"ES",
    "sg:address":"Carrer de Mestre Sunyer, 36",
    "sg:city":"Amposta",
    "sg:orig_category":"Empresas De Carpinter\u00cda De Madera",
    "sg:phone":"+34 977 70 26 37",
    "sg:postcode":"43870",
    "sg:province":"Tarragona",
    "wof:name":"Fusteria I Interiors Porres I Bellot S.l.",
    "wof:placetype":"venue"
},
  "geometry": {"coordinates":[0.5808600187,40.7092208862],"type":"Point"}
}