{
  "type": "Feature",
  "properties": {
    "addr:full":"Av Cavall Bernat (del), S/n Platja D'aro Girona 17250",
    "addr:housenumber":"/ n",
    "addr:postcode":"17250",
    "addr:street":"Av Cavall Bernat Del S",
    "iso:country":"ES",
    "sg:address":"Av Cavall Bernat (del), S/n",
    "sg:city":"Platja D'aro",
    "sg:orig_category":"Peluquer\u00cdas, Peluquer\u00cda Mixta",
    "sg:phone":"+34 972 81 76 63",
    "sg:postcode":"17250",
    "sg:province":"Girona",
    "wof:name":"Maya Saubi Carmen",
    "wof:placetype":"venue"
},
  "geometry": {"coordinates":[2.8163490295,41.9701499939],"type":"Point"}
}