{
  "type": "Feature",
  "properties": {
    "iso:country":"ES",
    "sg:address":"Calle de Orilla De La Via, 124",
    "sg:city":"Infante Juan Manuel",
    "sg:orig_category":"Autob\u00das (explotaci\u00d3n Y Servicios De)",
    "sg:phone":"+34 968 34 43 49",
    "sg:postcode":"30012",
    "sg:province":"Murcia",
    "wof:name":"Cris-bus S.l.",
    "wof:placetype":"venue"
},
  "geometry": {"coordinates":[-1.1131169796,37.972618103],"type":"Point"}
}