{
  "type": "Feature",
  "properties": {
    "addr:full":"Barr Ladredo, 91 Camargo Cantabria 39609",
    "addr:housenumber":"91",
    "addr:postcode":"39609",
    "addr:street":"Ladredo",
    "iso:country":"ES",
    "sg:address":"Barr Ladredo, 91",
    "sg:city":"Camargo",
    "sg:orig_category":"Transportes Por Carretera: Lotes Completos, Mercanc\u00cdas Diversas",
    "sg:phone":"+34 942 25 90 74",
    "sg:postcode":"39609",
    "sg:province":"Cantabria",
    "wof:name":"Lorenzo Revuelta Esther",
    "wof:placetype":"venue"
},
  "geometry": {"coordinates":[-3.8822391033,43.4023246765],"type":"Point"}
}