{
  "type": "Feature",
  "properties": {
    "addr:full":"Calle de Sauces (los), 8 Santa Cruz De Tenerife Santa Cruz De Tenerife 38009",
    "addr:housenumber":"8",
    "addr:postcode":"38009",
    "addr:street":"Calle De Sauces Los",
    "iso:country":"ES",
    "sg:address":"Calle de Sauces (los), 8",
    "sg:city":"Santa Cruz De Tenerife",
    "sg:orig_category":"Ropa Y Accesorios",
    "sg:phone":"+34 922 20 68 84",
    "sg:postcode":"38009",
    "sg:province":"Santa Cruz De Tenerife",
    "wof:name":"Yujara S.l.",
    "wof:placetype":"venue"
},
  "geometry": {"coordinates":[-16.27409935,28.4599285126],"type":"Point"}
}