{
  "type": "Feature",
  "properties": {
    "addr:full":"Calle de Mendiko Kalea, 1 Arteaga Vizcaya 48170",
    "addr:housenumber":"1",
    "addr:postcode":"48170",
    "addr:street":"Calle De Mendiko Kalea",
    "iso:country":"ES",
    "sg:address":"Calle de Mendiko Kalea, 1",
    "sg:city":"Arteaga",
    "sg:orig_category":"Instalaci\u00d3n De Aspiraci\u00d3n De Gases Y Humos",
    "sg:phone":"+34 944 52 26 63",
    "sg:postcode":"48170",
    "sg:province":"Vizcaya",
    "wof:name":"Acuster S.a.",
    "wof:placetype":"venue"
},
  "geometry": {"coordinates":[-2.8639864922,43.2837562561],"type":"Point"}
}