{
  "type": "Feature",
  "properties": {
    "addr:full":"Calle de Alamos, 14 Jaen Ja\u00e9n 23003",
    "addr:housenumber":"14;jae\u0301n",
    "addr:postcode":"23003",
    "addr:street":"Calle De Alamos",
    "iso:country":"ES",
    "sg:address":"Calle de Alamos, 14",
    "sg:city":"Jaen",
    "sg:orig_category":"Carnicer\u00cdas, Carnicer\u00cdas",
    "sg:phone":"+34 953 23 71 92",
    "sg:postcode":"23003",
    "sg:province":"Ja\u00e9n",
    "wof:name":"Moral Aranda Blas",
    "wof:placetype":"venue"
},
  "geometry": {"coordinates":[-3.7906563282,37.7669487],"type":"Point"}
}