{
  "type": "Feature",
  "properties": {
    "iso:country":"ES",
    "sg:address":"Carrer de Bisbe Lorenzana, 17",
    "sg:city":"Olot",
    "sg:orig_category":"Diarios, Revistas Y Boletines (distribuidores)",
    "sg:phone":"+34 972 26 75 00",
    "sg:postcode":"17800",
    "sg:province":"Girona",
    "wof:name":"Reclam Publicitari S.l.",
    "wof:placetype":"venue"
},
  "geometry": {"coordinates":[2.4912929535,42.1814651489],"type":"Point"}
}