{
  "type": "Feature",
  "properties": {
    "iso:country":"ES",
    "sg:address":"Calle de Jose Marron, 18",
    "sg:city":"Benameji",
    "sg:orig_category":"Laboratorios Y Trabajos De Fotograf\u00cda, V\u00cddeo Y Cine",
    "sg:phone":"+34 957 53 07 29",
    "sg:postcode":"14910",
    "sg:province":"C\u00f3rdoba",
    "wof:name":"Melero Plasencia Jose",
    "wof:placetype":"venue"
},
  "geometry": {"coordinates":[-4.5406560898,37.2677726746],"type":"Point"}
}