{
  "type": "Feature",
  "properties": {
    "addr:full":"Pda Boverals, S/n Vinaros Castell\u00f3n 12500",
    "addr:housenumber":"s / n",
    "addr:postcode":"12500",
    "iso:country":"ES",
    "sg:address":"Pda Boverals, S/n",
    "sg:city":"Vinaros",
    "sg:orig_category":"Contenedores (mercanc\u00cdas)",
    "sg:phone":"+34 964 45 10 68",
    "sg:postcode":"12500",
    "sg:province":"Castell\u00f3n",
    "wof:name":"Chesa Casas Javier",
    "wof:placetype":"venue"
},
  "geometry": {"coordinates":[0.4797500074,40.4777603149],"type":"Point"}
}