{
  "type": "Feature",
  "properties": {
    "iso:country":"ES",
    "sg:address":"Avda Miguel De Cervantes, 85",
    "sg:city":"Tarancon",
    "sg:orig_category":"Decoraci\u00d3n: Instalaci\u00d3n Y Talleres",
    "sg:phone":"+34 969 32 52 48",
    "sg:postcode":"16400",
    "sg:province":"Cuenca",
    "wof:name":"Pinturas Montalban Varea S.l.",
    "wof:placetype":"venue"
},
  "geometry": {"coordinates":[-3.016931057,40.0107803345],"type":"Point"}
}