{
  "type": "Feature",
  "properties": {
    "addr:full":"Calle de Ruperto Urquijo, 3 Llodio \u00c1lava 01400",
    "addr:housenumber":"3",
    "addr:postcode":"01400",
    "addr:street":"Calle De Ruperto Urquijo",
    "iso:country":"ES",
    "sg:address":"Calle de Ruperto Urquijo, 3",
    "sg:city":"Llodio",
    "sg:orig_category":"Asociaciones, Organismos Culturales Y Socioeducativos",
    "sg:phone":"+34 946 72 10 00",
    "sg:postcode":"01400",
    "sg:province":"\u00c1lava",
    "wof:name":"Centro Gallego",
    "wof:placetype":"venue"
},
  "geometry": {"coordinates":[-2.9637770653,43.144985199],"type":"Point"}
}