{
  "type": "Feature",
  "properties": {
    "addr:full":"Calle de Langreo, 10 Gijon Asturias 33206",
    "addr:housenumber":"10",
    "addr:postcode":"33206",
    "addr:street":"Calle De Langreo",
    "iso:country":"ES",
    "sg:address":"Calle de Langreo, 10",
    "sg:city":"Gijon",
    "sg:orig_category":"Inmobiliaria (agencias)",
    "sg:phone":"+34 985 17 26 23",
    "sg:postcode":"33206",
    "sg:province":"Asturias",
    "wof:name":"Naves Gijon S. A.",
    "wof:placetype":"venue"
},
  "geometry": {"coordinates":[-5.6652040482,43.5406723022],"type":"Point"}
}