{
  "type": "Feature",
  "properties": {
    "addr:full":"Grup Manzanera, S/n Ceuta Ceuta 51002",
    "addr:housenumber":"s / n",
    "addr:postcode":"51002",
    "addr:street":"Manzanera",
    "iso:country":"ES",
    "sg:address":"Grup Manzanera, S/n",
    "sg:city":"Ceuta",
    "sg:orig_category":"Centros De Educaci\u00d3n Especial",
    "sg:phone":"+34 956 52 20 37",
    "sg:postcode":"51002",
    "sg:province":"Ceuta",
    "wof:name":"Colegio Publico Vicente Aleixandre",
    "wof:placetype":"venue"
},
  "geometry": {"coordinates":[-5.3299298286,35.8878097534],"type":"Point"}
}