{
  "type": "Feature",
  "properties": {
    "iso:country":"ES",
    "sg:address":"Calle de Marques De Paradas, S/n",
    "sg:city":"Sevilla",
    "sg:orig_category":"Asociaciones Y Clubs Deportivos",
    "sg:phone":"+34 954 90 87 95",
    "sg:postcode":"41001",
    "sg:province":"Sevilla",
    "sg:website":"www.decimas.es",
    "wof:name":"Tinmar Sport S.l.",
    "wof:placetype":"venue"
},
  "geometry": {"coordinates":[-6.0022039413,37.3930892944],"type":"Point"}
}