{
  "type": "Feature",
  "properties": {
    "addr:full":"Calle de Yebenes, 241 Madrid Madrid 28047",
    "addr:housenumber":"241",
    "addr:postcode":"28047",
    "addr:street":"Calle De Yebenes",
    "iso:country":"ES",
    "sg:address":"Calle de Yebenes, 241",
    "sg:city":"Madrid",
    "sg:orig_category":"Asociaciones, Organismos Culturales Y Socioeducativos",
    "sg:phone":"+34 917 17 45 58",
    "sg:postcode":"28047",
    "sg:province":"Madrid",
    "wof:name":"Centro Cultural Castellano Manchego De Latina",
    "wof:placetype":"venue"
},
  "geometry": {"coordinates":[-3.7507019043,40.3915557861],"type":"Point"}
}