{
  "type": "Feature",
  "properties": {
    "addr:full":"Carrer de Major, 7 Reus Tarragona 43201",
    "addr:housenumber":"7",
    "addr:postcode":"43201",
    "addr:street":"Carrer De Major",
    "iso:country":"ES",
    "sg:address":"Carrer de Major, 7",
    "sg:city":"Reus",
    "sg:orig_category":"Ropa Para Se\u00d1oras (al Por Menor)",
    "sg:phone":"+34 977 34 23 63",
    "sg:postcode":"43201",
    "sg:province":"Tarragona",
    "wof:name":"Casas Rom Maria",
    "wof:placetype":"venue"
},
  "geometry": {"coordinates":[1.1088420153,41.1545829773],"type":"Point"}
}