{
  "type": "Feature",
  "properties": {
    "iso:country":"ES",
    "sg:address":"Carrer de Pau (la), 14",
    "sg:city":"Muro Alcoy",
    "sg:orig_category":"Agencias Y Asesores De Publicidad",
    "sg:phone":"+34 966 51 65 31",
    "sg:postcode":"03830",
    "sg:province":"Alicante",
    "wof:name":"Faus Perona Vicente",
    "wof:placetype":"venue"
},
  "geometry": {"coordinates":[-0.4375559986,38.7817497253],"type":"Point"}
}