{
  "type": "Feature",
  "properties": {
    "iso:country":"ES",
    "sg:address":"Pza. Al-andalus, 1",
    "sg:city":"Maracena",
    "sg:orig_category":"Caf\u00c9s, Bares, Cervecer\u00cdas",
    "sg:phone":"+34 958 41 22 67",
    "sg:postcode":"18200",
    "sg:province":"Granada",
    "wof:name":"Martin Gutierrez Guadalupe",
    "wof:placetype":"venue"
},
  "geometry": {"coordinates":[-3.6313939095,37.2102813721],"type":"Point"}
}