{
  "type": "Feature",
  "properties": {
    "addr:full":"Calle de Marques De San Juan, 5 Valencia Valencia 46015",
    "addr:housenumber":"5",
    "addr:postcode":"46015",
    "addr:street":"Calle De Marques De San Juan",
    "iso:country":"ES",
    "sg:address":"Calle de Marques De San Juan, 5",
    "sg:city":"Valencia",
    "sg:orig_category":"Ingeniero",
    "sg:phone":"+34 963 40 33 98",
    "sg:postcode":"46015",
    "sg:province":"Valencia",
    "wof:name":"Bori Perez Miguel",
    "wof:placetype":"venue"
},
  "geometry": {"coordinates":[-0.3951640129,39.47864151],"type":"Point"}
}