{
  "type": "Feature",
  "properties": {
    "iso:country":"ES",
    "sg:address":"Carrer de Convent S Francesc, 1",
    "sg:city":"Palma",
    "sg:orig_category":"Procuradores",
    "sg:phone":"+34 971 71 83 03",
    "sg:postcode":"07001",
    "sg:province":"Islas Baleares",
    "wof:name":"Pascual Fiol Juan Jose",
    "wof:placetype":"venue"
},
  "geometry": {"coordinates":[2.6512899399,39.5689811707],"type":"Point"}
}