{
  "type": "Feature",
  "properties": {
    "addr:full":"Calle de Laguna, 121 Madrid Madrid 28025",
    "addr:housenumber":"121",
    "addr:postcode":"28025",
    "addr:street":"Calle De Laguna",
    "iso:country":"ES",
    "sg:address":"Calle de Laguna, 121",
    "sg:city":"Madrid",
    "sg:orig_category":"Art\u00cdculos De Decoraci\u00d3n",
    "sg:phone":"+34 914 62 84 50",
    "sg:postcode":"28025",
    "sg:province":"Madrid",
    "sg:website":"www.nido.es",
    "wof:name":"Casa Tempo S.a.",
    "wof:placetype":"venue"
},
  "geometry": {"coordinates":[-3.7418138981,40.3882446289],"type":"Point"}
}