{
  "type": "Feature",
  "properties": {
    "addr:full":"Calle de Vasco Nu\u00d1ez De Balboa, 2 Plasencia C\u00e1ceres 10600",
    "addr:housenumber":"2",
    "addr:postcode":"10600",
    "addr:street":"Calle De Vasco Nun\u0303Ez De Balboa;Ca\u0301Ceres",
    "iso:country":"ES",
    "sg:address":"Calle de Vasco Nu\u00d1ez De Balboa, 2",
    "sg:city":"Plasencia",
    "sg:orig_category":"Imprenta",
    "sg:phone":"+34 927 41 53 98",
    "sg:postcode":"10600",
    "sg:province":"C\u00e1ceres",
    "wof:name":"Plasencia Dise\u00f1o Grafico S.l.",
    "wof:placetype":"venue"
},
  "geometry": {"coordinates":[-6.0689821243,40.0425109863],"type":"Point"}
}