{
  "type": "Feature",
  "properties": {
    "iso:country":"ES",
    "sg:address":"Calle de Iglesia, S/n",
    "sg:city":"Valdei\u00d1igos",
    "sg:orig_category":"Supermercados Y Hipermercados",
    "sg:phone":"+34 927 47 72 30",
    "sg:postcode":"10697",
    "sg:province":"C\u00e1ceres",
    "wof:name":"Alvarez Terron Santiago",
    "wof:placetype":"venue"
},
  "geometry": {"coordinates":[-5.8572192192,39.9613952637],"type":"Point"}
}