{
  "type": "Feature",
  "properties": {
    "iso:country":"ES",
    "sg:address":"Yerri, 21",
    "sg:city":"Estella",
    "sg:orig_category":"Electrodom\u00c9sticos (al Por Menor)",
    "sg:phone":"+34 948 55 19 61",
    "sg:postcode":"31200",
    "sg:province":"Navarra",
    "wof:name":"Pagola Legarreta Jose Antonio",
    "wof:placetype":"venue"
},
  "geometry": {"coordinates":[-2.035296917,42.6745605469],"type":"Point"}
}