{
  "type": "Feature",
  "properties": {
    "addr:full":"Calle de Nueva, 35 Cebreros \u00c1vila 05260",
    "addr:housenumber":"35",
    "addr:postcode":"05260",
    "addr:street":"Calle De Nueva",
    "iso:country":"ES",
    "sg:address":"Calle de Nueva, 35",
    "sg:city":"Cebreros",
    "sg:orig_category":"Reposter\u00cdas",
    "sg:phone":"+34 918 63 03 08",
    "sg:postcode":"05260",
    "sg:province":"\u00c1vila",
    "wof:name":"Jimenez Gonzalez Angel Luis",
    "wof:placetype":"venue"
},
  "geometry": {"coordinates":[-4.4632401466,40.4560966492],"type":"Point"}
}