{
  "type": "Feature",
  "properties": {
    "iso:country":"ES",
    "sg:address":"Calle de Emperatriz Eugenia, 21",
    "sg:city":"Granada",
    "sg:orig_category":"Cl\u00cdnicas Dentales",
    "sg:phone":"+34 958 28 99 45",
    "sg:postcode":"18003",
    "sg:province":"Granada",
    "wof:name":"Gonzalez Marquez Maria Isabel",
    "wof:placetype":"venue"
},
  "geometry": {"coordinates":[-3.6081879139,37.1752128601],"type":"Point"}
}