{
  "type": "Feature",
  "properties": {
    "addr:full":"Calle de Gutierrez De Los Rios, 58 Cordoba C\u00f3rdoba 14002",
    "addr:housenumber":"58",
    "addr:postcode":"14002",
    "addr:street":"Calle De Gutierrez De Los Rios;Co\u0301Rdoba",
    "iso:country":"ES",
    "sg:address":"Calle de Gutierrez De Los Rios, 58",
    "sg:city":"Cordoba",
    "sg:orig_category":"Maquinaria Para Industrias Diversas",
    "sg:phone":"+34 957 47 03 70",
    "sg:postcode":"14002",
    "sg:province":"C\u00f3rdoba",
    "wof:name":"Molina Herruzo Angel A.",
    "wof:placetype":"venue"
},
  "geometry": {"coordinates":[-4.7718648911,37.8861961365],"type":"Point"}
}