{
  "type": "Feature",
  "properties": {
    "iso:country":"ES",
    "sg:address":"Calle de Alcorce, 9",
    "sg:city":"Puerto Del Carmen",
    "sg:orig_category":"Inmobiliaria (agencias)",
    "sg:phone":"+34 928 51 26 58",
    "sg:postcode":"35510",
    "sg:province":"Las Palmas",
    "wof:name":"Ramirez Curbelo Nieves",
    "wof:placetype":"venue"
},
  "geometry": {"coordinates":[-13.6610574722,28.9243392944],"type":"Point"}
}