{
  "type": "Feature",
  "properties": {
    "iso:country":"ES",
    "sg:address":"Calle de Marbella, 54",
    "sg:city":"Madrid",
    "sg:orig_category":"Urbanistas",
    "sg:phone":"+34 914 48 27 51",
    "sg:postcode":"28034",
    "sg:province":"Madrid",
    "wof:name":"Cuadrado Bueno Alfonso",
    "wof:placetype":"venue"
},
  "geometry": {"coordinates":[-3.7064828873,40.4951019287],"type":"Point"}
}