{
  "type": "Feature",
  "properties": {
    "iso:country":"ES",
    "sg:address":"Calle de Piedrafita (de), 21",
    "sg:city":"Fuenlabrada",
    "sg:orig_category":"Ropa Para Se\u00d1oras (al Por Menor)",
    "sg:phone":"+34 916 42 08 47",
    "sg:postcode":"28947",
    "sg:province":"Madrid",
    "wof:name":"Comercio Modaland S.l.",
    "wof:placetype":"venue"
},
  "geometry": {"coordinates":[-3.7928040028,40.2826004028],"type":"Point"}
}