{
  "type": "Feature",
  "properties": {
    "iso:country":"ES",
    "sg:address":"Carrer de Fenolleda (la), 18",
    "sg:city":"Terrassa",
    "sg:orig_category":"Cerrajer\u00cda, Ferrallista",
    "sg:phone":"+34 937 35 55 50",
    "sg:postcode":"08226",
    "sg:province":"Barcelona",
    "wof:name":"Tallers Carmac S.l.",
    "wof:placetype":"venue"
},
  "geometry": {"coordinates":[2.0256340504,41.5822601318],"type":"Point"}
}