{
  "type": "Feature",
  "properties": {
    "iso:country":"ES",
    "sg:address":"Urb. Porto Avieira(gandara), 1",
    "sg:city":"Sigueiro",
    "sg:orig_category":"Cine: Pel\u00cdculas Educativas, Industriales Y Publicitarias (producci\u00d3n)",
    "sg:phone":"+34 981 68 89 27",
    "sg:postcode":"15888",
    "sg:province":"A Coru\u00f1a",
    "sg:website":"vangardaicom@telefonica.net",
    "wof:name":"Vangarda Imaxe E Comunicacion S L",
    "wof:placetype":"venue"
},
  "geometry": {"coordinates":[-8.4441986084,42.966709137],"type":"Point"}
}