{
  "type": "Feature",
  "properties": {
    "addr:full":"Carrer de Balmes, 12 Santa Perpetua De Mogoda Barcelona 08130",
    "addr:housenumber":"12",
    "addr:postcode":"08130",
    "addr:street":"Carrer De Balmes",
    "iso:country":"ES",
    "sg:address":"Carrer de Balmes, 12",
    "sg:city":"Santa Perpetua De Mogoda",
    "sg:orig_category":"Cajas Y Embalajes De Pl\u00c1stico",
    "sg:phone":"+34 935 74 90 37",
    "sg:postcode":"08130",
    "sg:province":"Barcelona",
    "wof:name":"Farras Lopez Esteban",
    "wof:placetype":"venue"
},
  "geometry": {"coordinates":[2.184253931,41.5338134766],"type":"Point"}
}