{
  "type": "Feature",
  "properties": {
    "iso:country":"ES",
    "sg:address":"Calle de Melchor Fernandez Almagro, 23",
    "sg:city":"Madrid",
    "sg:orig_category":"Tubos Met\u00c1licos",
    "sg:phone":"+34 917 33 68 60",
    "sg:postcode":"28029",
    "sg:province":"Madrid",
    "wof:name":"Freyssinet S.a.",
    "wof:placetype":"venue"
},
  "geometry": {"coordinates":[-3.6994009018,40.4775772095],"type":"Point"}
}