{
  "type": "Feature",
  "properties": {
    "addr:full":"Calle de Erlaiz, 3 Irun Guip\u00f9zcoa 20304",
    "addr:housenumber":"3",
    "addr:postcode":"20304",
    "addr:street":"Calle De Erlaiz;Guipu\u0300Zcoa",
    "iso:country":"ES",
    "sg:address":"Calle de Erlaiz, 3",
    "sg:city":"Irun",
    "sg:orig_category":"M\u00c9dicos: An\u00c1lisis Cl\u00cdnicos",
    "sg:phone":"+34 943 62 39 54",
    "sg:postcode":"20304",
    "sg:province":"Guip\u00f9zcoa",
    "wof:name":"Tejero Monzon Ana Maria",
    "wof:placetype":"venue"
},
  "geometry": {"coordinates":[-1.7835190296,43.3396377563],"type":"Point"}
}