{
  "type": "Feature",
  "properties": {
    "iso:country":"ES",
    "sg:address":"Calle de Bernardo Lopez Garcia, 11",
    "sg:city":"Madrid",
    "sg:orig_category":"Cervecer\u00cdas",
    "sg:phone":"+34 915 41 02 03",
    "sg:postcode":"28015",
    "sg:province":"Madrid",
    "wof:name":"Moran Vacas Jose",
    "wof:placetype":"venue"
},
  "geometry": {"coordinates":[-3.7098164558,40.4265060425],"type":"Point"}
}