{
  "type": "Feature",
  "properties": {
    "addr:full":"Carrer de Narcis De Monturiol, 130 Hospitalet Llobregat Barcelona 08902",
    "addr:housenumber":"130",
    "addr:postcode":"08902",
    "addr:street":"Carrer De Narcis De Monturiol",
    "iso:country":"ES",
    "sg:address":"Carrer de Narcis De Monturiol, 130",
    "sg:city":"Hospitalet Llobregat",
    "sg:orig_category":"Trajes Y Adornos De Boda (confecci\u00d3n, Al Por Menor)",
    "sg:phone":"+34 934 19 04 04",
    "sg:postcode":"08902",
    "sg:province":"Barcelona",
    "sg:website":"www.rosaclara.es",
    "wof:name":"Exponovias S.l.",
    "wof:placetype":"venue"
},
  "geometry": {"coordinates":[2.1175999641,41.3608093262],"type":"Point"}
}