{
  "type": "Feature",
  "properties": {
    "iso:country":"ES",
    "sg:address":"Carrer de Mallorca, 665",
    "sg:city":"Barcelona",
    "sg:orig_category":"Electricidad (montaje, Ensamblaje De Componentes)",
    "sg:phone":"+34 933 52 60 60",
    "sg:postcode":"08027",
    "sg:province":"Barcelona",
    "wof:name":"Montajes Cordero S.l.",
    "wof:placetype":"venue"
},
  "geometry": {"coordinates":[2.1901578903,41.4147338867],"type":"Point"}
}