{
  "type": "Feature",
  "properties": {
    "addr:full":"Carr Nou, 1 Mao Islas Baleares 07701",
    "addr:housenumber":"1",
    "addr:postcode":"07701",
    "addr:street":"Carr Nou",
    "iso:country":"ES",
    "sg:address":"Carr Nou, 1",
    "sg:city":"Mao",
    "sg:orig_category":"Molduras, Junquillos, Listones Y Molduras Perforadas",
    "sg:phone":"+34 971 36 55 00",
    "sg:postcode":"07701",
    "sg:province":"Islas Baleares",
    "wof:name":"Nou Bar S. C.",
    "wof:placetype":"venue"
},
  "geometry": {"coordinates":[4.265625,39.8903694153],"type":"Point"}
}