{
  "type": "Feature",
  "properties": {
    "iso:country":"ES",
    "sg:address":"Cno. De La Fuente, S/n",
    "sg:city":"Durcal",
    "sg:orig_category":"Mataderos Y Talleres De Despiezado",
    "sg:phone":"+34 958 78 15 70",
    "sg:postcode":"18650",
    "sg:province":"Granada",
    "wof:name":"Ferrer Castilla Antonio Manuel",
    "wof:placetype":"venue"
},
  "geometry": {"coordinates":[-3.5704190731,36.9924316406],"type":"Point"}
}