{
  "type": "Feature",
  "properties": {
    "addr:full":"Calle de Narciso Hernandez Vaquero, 1 Oviedo Asturias 33011",
    "addr:housenumber":"1",
    "addr:postcode":"33011",
    "addr:street":"Calle De Narciso Hernandez Vaquero",
    "iso:country":"ES",
    "sg:address":"Calle de Narciso Hernandez Vaquero, 1",
    "sg:city":"Oviedo",
    "sg:orig_category":"Mec\u00c1nico Del Autom\u00d3vil",
    "sg:phone":"+34 985 22 73 81",
    "sg:postcode":"33011",
    "sg:province":"Asturias",
    "wof:name":"Automecanica Tino S.l.",
    "wof:placetype":"venue"
},
  "geometry": {"coordinates":[-5.8411717415,43.3569259644],"type":"Point"}
}