{
  "type": "Feature",
  "properties": {
    "addr:full":"Pago Los Ardales, S/n Medina-sidonia C\u00e1diz 11170",
    "addr:housenumber":"s / n",
    "addr:postcode":"11170",
    "addr:street":"Medina-Sidonia Ca\u0301Diz",
    "iso:country":"ES",
    "sg:address":"Pago Los Ardales, S/n",
    "sg:city":"Medina-sidonia",
    "sg:orig_category":"Agricultores, Agricultores",
    "sg:phone":"+34 956 23 32 59",
    "sg:postcode":"11170",
    "sg:province":"C\u00e1diz",
    "wof:name":"Hermanos Mateos C.b.",
    "wof:placetype":"venue"
},
  "geometry": {"coordinates":[-5.9282741547,36.463180542],"type":"Point"}
}