{
  "type": "Feature",
  "properties": {
    "addr:full":"Calle de Rioja, 35 Leganes Madrid 28915",
    "addr:housenumber":"35",
    "addr:postcode":"28915",
    "addr:street":"Calle De Rioja",
    "iso:country":"ES",
    "sg:address":"Calle de Rioja, 35",
    "sg:city":"Leganes",
    "sg:orig_category":"Instalaci\u00d3n, Mantenimiento De Porteros Electr\u00d3nicos Y Controles De Acceso",
    "sg:phone":"+34 916 88 43 06",
    "sg:postcode":"28915",
    "sg:province":"Madrid",
    "wof:name":"Ecn Telecom Comunidad",
    "wof:placetype":"venue"
},
  "geometry": {"coordinates":[-3.7548749447,40.3310928345],"type":"Point"}
}