{
  "type": "Feature",
  "properties": {
    "addr:full":"Avda Paz (la), S/n Tarazona Zaragoza 50500",
    "addr:postcode":"50500",
    "addr:street":"Avda Paz La S / N",
    "iso:country":"ES",
    "sg:address":"Avda Paz (la), S/n",
    "sg:city":"Tarazona",
    "sg:orig_category":"Polideportivos",
    "sg:phone":"+34 976 64 20 20",
    "sg:postcode":"50500",
    "sg:province":"Zaragoza",
    "wof:name":"Ayuntamiento De Tarazona-polideportivo",
    "wof:placetype":"venue"
},
  "geometry": {"coordinates":[-1.7153398991,41.9113121033],"type":"Point"}
}