{
  "type": "Feature",
  "properties": {
    "addr:full":"Calle de D(campollano), 8 Albacete Albacete 02006",
    "addr:housenumber":"8",
    "addr:postcode":"02006",
    "addr:street":"Calle De D Campollano",
    "iso:country":"ES",
    "sg:address":"Calle de D(campollano), 8",
    "sg:city":"Albacete",
    "sg:orig_category":"Pintura, Barniz, Productos Asimilables (fabricaci\u00d3n, Al Por Mayor)",
    "sg:phone":"+34 967 21 16 38",
    "sg:postcode":"02006",
    "sg:province":"Albacete",
    "wof:name":"Teodoro Manuel Garcia Soria S.l",
    "wof:placetype":"venue"
},
  "geometry": {"coordinates":[-1.9363039732,39.0603866577],"type":"Point"}
}