{
  "type": "Feature",
  "properties": {
    "iso:country":"ES",
    "sg:address":"U A (zona Militar), S/n",
    "sg:city":"Corro D'avall",
    "sg:orig_category":"Suministros Para Hoteles",
    "sg:phone":"+34 938 61 65 30",
    "sg:postcode":"08520",
    "sg:province":"Barcelona",
    "sg:website":"www.intelservice.es",
    "wof:name":"Intel Service S.l.",
    "wof:placetype":"venue"
},
  "geometry": {"coordinates":[2.2962567806,41.6326560974],"type":"Point"}
}