{
  "type": "Feature",
  "properties": {
    "addr:full":"Calle de Paco Lanza, S/n Ribadeo Lugo 27700",
    "addr:housenumber":"s / n",
    "addr:postcode":"27700",
    "addr:street":"Calle De Paco Lanza",
    "iso:country":"ES",
    "sg:address":"Calle de Paco Lanza, S/n",
    "sg:city":"Ribadeo",
    "sg:orig_category":"Negocio De Materiales De Construcci\u00d3n",
    "sg:phone":"+34 982 12 87 30",
    "sg:postcode":"27700",
    "sg:province":"Lugo",
    "wof:name":"Solloso Orol Jose Luis",
    "wof:placetype":"venue"
},
  "geometry": {"coordinates":[-7.052816391,43.5368881226],"type":"Point"}
}