{
  "type": "Feature",
  "properties": {
    "addr:full":"Calle de Luis Bu\u00d1uel, 5 Almoradi Alicante 03160",
    "addr:housenumber":"5",
    "addr:postcode":"03160",
    "addr:street":"Calle De Luis Bun\u0303Uel",
    "iso:country":"ES",
    "sg:address":"Calle de Luis Bu\u00d1uel, 5",
    "sg:city":"Almoradi",
    "sg:orig_category":"Molduras, Junquillos, Listones Y Molduras Perforadas",
    "sg:phone":"+34 966 78 07 04",
    "sg:postcode":"03160",
    "sg:province":"Alicante",
    "wof:name":"Diaz Palomar Jose Antonio",
    "wof:placetype":"venue"
},
  "geometry": {"coordinates":[-0.7921990156,38.1106452942],"type":"Point"}
}