{
  "type": "Feature",
  "properties": {
    "addr:full":"Calle de Maldonadas, 3 Madrid Madrid 28005",
    "addr:housenumber":"3",
    "addr:postcode":"28005",
    "addr:street":"Calle De Maldonadas",
    "iso:country":"ES",
    "sg:address":"Calle de Maldonadas, 3",
    "sg:city":"Madrid",
    "sg:orig_category":"Fabricaci\u00d3n De Peines Y De Accesorios De Peluquer\u00cda",
    "sg:phone":"+34 913 66 38 31",
    "sg:postcode":"28005",
    "sg:province":"Madrid",
    "wof:name":"Comercial Jose Campo S.l.",
    "wof:placetype":"venue"
},
  "geometry": {"coordinates":[-3.7077620029,40.4107666016],"type":"Point"}
}