{
  "type": "Feature",
  "properties": {
    "addr:full":"Calle de Ronda De Las Ventas, 15 Burlada Navarra 31600",
    "addr:housenumber":"15",
    "addr:postcode":"31600",
    "addr:street":"Calle De Ronda De Las Ventas",
    "iso:country":"ES",
    "sg:address":"Calle de Ronda De Las Ventas, 15",
    "sg:city":"Burlada",
    "sg:orig_category":"Farmacias",
    "sg:phone":"+34 948 13 66 93",
    "sg:postcode":"31600",
    "sg:province":"Navarra",
    "wof:name":"Garcia Castillejo Maria Carmen",
    "wof:placetype":"venue"
},
  "geometry": {"coordinates":[-1.6152689457,42.8264541626],"type":"Point"}
}