{
  "type": "Feature",
  "properties": {
    "iso:country":"ES",
    "sg:address":"Calle de Alemania, 6",
    "sg:city":"Valdemoro",
    "sg:orig_category":"Agencias Y Agentes Comerciales, Representantes",
    "sg:phone":"+34 918 95 26 54",
    "sg:postcode":"28340",
    "sg:province":"Madrid",
    "wof:name":"Sanchez Ampuero Miguel Angel",
    "wof:placetype":"venue"
},
  "geometry": {"coordinates":[-3.6743659973,40.1835098267],"type":"Point"}
}