{
  "type": "Feature",
  "properties": {
    "addr:full":"C/ Ciutat De Ferrol, 77 Paterna Valencia 46988",
    "addr:housenumber":"77",
    "addr:postcode":"46988",
    "addr:street":"C / Ciutat De Ferrol",
    "iso:country":"ES",
    "sg:address":"C/ Ciutat De Ferrol, 77",
    "sg:city":"Paterna",
    "sg:orig_category":"Albergues",
    "sg:phone":"+34 961 32 02 58",
    "sg:postcode":"46988",
    "sg:province":"Valencia",
    "sg:website":"www.indumarna.com",
    "wof:name":"Industrias Marna S.a.",
    "wof:placetype":"venue"
},
  "geometry": {"coordinates":[-0.4395389855,39.500629425],"type":"Point"}
}