{
  "type": "Feature",
  "properties": {
    "iso:country":"ES",
    "sg:address":"Calle de Panaderos, 2",
    "sg:city":"Le\u00f3n",
    "sg:orig_category":"Asociaciones Humanitarias, De Cooperaci\u00d3n, De Acci\u00d3n Social",
    "sg:phone":"+34 987 21 18 74",
    "sg:postcode":"24006",
    "sg:province":"Le\u00f3n",
    "wof:name":"Clinica San Juan De Dios De Leon Orden Hospitalaria De San Juan De Dios Provincia De Castilla",
    "wof:placetype":"venue"
},
  "geometry": {"coordinates":[-5.5651578903,42.5982398987],"type":"Point"}
}