{
  "type": "Feature",
  "properties": {
    "addr:full":"Carr Verge Maria, 2 Figueres Girona 17600",
    "addr:postcode":"17600",
    "addr:street":"Carr Verge Maria",
    "iso:country":"ES",
    "sg:address":"Carr Verge Maria, 2",
    "sg:city":"Figueres",
    "sg:orig_category":"Persianas Interiores, Exteriores",
    "sg:phone":"+34 972 50 17 28",
    "sg:postcode":"17600",
    "sg:province":"Girona",
    "wof:name":"Pujadas Mora Bernardo",
    "wof:placetype":"venue"
},
  "geometry": {"coordinates":[2.96053195,42.2653121948],"type":"Point"}
}