{
  "type": "Feature",
  "properties": {
    "iso:country":"ES",
    "sg:address":"Calle de Padilla, 6",
    "sg:city":"Salamanca",
    "sg:orig_category":"Frutas, Legumbres Frescas Y Tempranas (al Por Menor)",
    "sg:phone":"+34 923 21 91 06",
    "sg:postcode":"37003",
    "sg:province":"Salamanca",
    "wof:name":"Andres Sanchez Benito",
    "wof:placetype":"venue"
},
  "geometry": {"coordinates":[-5.6573147774,40.9660568237],"type":"Point"}
}