{
  "type": "Feature",
  "properties": {
    "addr:full":"Carr Manuel Fdez Marquez, 45 Badalona Barcelona 08918",
    "addr:housenumber":"45",
    "addr:postcode":"08918",
    "addr:street":"Carr Manuel Fdez Marquez",
    "iso:country":"ES",
    "sg:address":"Carr Manuel Fdez Marquez, 45",
    "sg:city":"Badalona",
    "sg:orig_category":"Electricidad: Equipos Industriales, Componentes (fabricaci\u00d3n)",
    "sg:phone":"+34 933 20 56 56",
    "sg:postcode":"08918",
    "sg:province":"Barcelona",
    "wof:name":"Mercantil Intercontinental S.l.u",
    "wof:placetype":"venue"
},
  "geometry": {"coordinates":[2.2347939014,41.4319915771],"type":"Point"}
}