{
  "type": "Feature",
  "properties": {
    "addr:full":"Av Valles, S/n Fonts Barcelona 08228",
    "addr:housenumber":"s / n",
    "addr:postcode":"08228",
    "addr:street":"Av Valles",
    "iso:country":"ES",
    "sg:address":"Av Valles, S/n",
    "sg:city":"Fonts",
    "sg:orig_category":"Moquetas, Alfombras (al Por Menor)",
    "sg:phone":"+34 937 31 85 45",
    "sg:postcode":"08228",
    "sg:province":"Barcelona",
    "wof:name":"Serra Perich Lorenzo",
    "wof:placetype":"venue"
},
  "geometry": {"coordinates":[2.0344440937,41.5328903198],"type":"Point"}
}