{
  "type": "Feature",
  "properties": {
    "iso:country":"ES",
    "sg:address":"Calle de Santa Maria, S/n",
    "sg:city":"Portugalete",
    "sg:orig_category":"Iglesia Cat\u00d3lica",
    "sg:phone":"+34 944 95 10 66",
    "sg:postcode":"48920",
    "sg:province":"Vizcaya",
    "wof:name":"Parroquia De Santa Maria De Portugalete",
    "wof:placetype":"venue"
},
  "geometry": {"coordinates":[-3.017234087,43.3208847046],"type":"Point"}
}