{
  "type": "Feature",
  "properties": {
    "addr:full":"D. Cardenal, 36 Linyola Lleida 25240",
    "addr:housenumber":"36",
    "addr:postcode":"25240",
    "addr:street":"Cardenal",
    "iso:country":"ES",
    "sg:address":"D. Cardenal, 36",
    "sg:city":"Linyola",
    "sg:orig_category":"Reposter\u00cdas",
    "sg:phone":"+34 973 57 50 43",
    "sg:postcode":"25240",
    "sg:province":"Lleida",
    "wof:name":"Coca Sumalla Manuel",
    "wof:placetype":"venue"
},
  "geometry": {"coordinates":[0.9046580195,41.7092475891],"type":"Point"}
}