{
  "type": "Feature",
  "properties": {
    "addr:full":"Carrer de Enric Borras, 196 Premia Mar Barcelona 08330",
    "addr:housenumber":"196",
    "addr:postcode":"08330",
    "addr:street":"Carrer De Enric Borras",
    "iso:country":"ES",
    "sg:address":"Carrer de Enric Borras, 196",
    "sg:city":"Premia Mar",
    "sg:orig_category":"Arquitectos",
    "sg:phone":"+34 937 51 70 60",
    "sg:postcode":"08330",
    "sg:province":"Barcelona",
    "wof:name":"Rodriguez Hernandez Bartolome",
    "wof:placetype":"venue"
},
  "geometry": {"coordinates":[2.3512399197,41.4873809814],"type":"Point"}
}