{
  "type": "Feature",
  "properties": {
    "addr:full":"Carrer de Sant Adria, 133 Barcelona Barcelona 08030",
    "addr:housenumber":"133",
    "addr:postcode":"08030",
    "addr:street":"Carrer De Sant Adria",
    "iso:country":"ES",
    "sg:address":"Carrer de Sant Adria, 133",
    "sg:city":"Barcelona",
    "sg:orig_category":"Cajas De Ahorro",
    "sg:phone":"+34 933 46 62 19",
    "sg:postcode":"08030",
    "sg:province":"Barcelona",
    "sg:website":"www.caixacatalunya.es",
    "wof:name":"Caixa D'estalvis De Catalunya",
    "wof:placetype":"venue"
},
  "geometry": {"coordinates":[2.2057960033,41.4363670349],"type":"Point"}
}