{
  "type": "Feature",
  "properties": {
    "iso:country":"ES",
    "sg:address":"Calle de Sorbas, 1",
    "sg:city":"Carboneras",
    "sg:orig_category":"Ropa Para Se\u00d1oras Y Caballeros (al Por Menor)",
    "sg:phone":"+34 950 45 48 43",
    "sg:postcode":"04140",
    "sg:province":"Almer\u00eda",
    "wof:name":"Gomez Parra Juan",
    "wof:placetype":"venue"
},
  "geometry": {"coordinates":[-1.8943300247,36.9970855713],"type":"Point"}
}