{
  "type": "Feature",
  "properties": {
    "addr:full":"Carrer de Verge De Montserrat, 1 Sant Marti Sarroca Barcelona 08731",
    "addr:housenumber":"1",
    "addr:postcode":"08731",
    "addr:street":"Carrer De Verge De Montserrat;Sarroca Barcelona",
    "iso:country":"ES",
    "sg:address":"Carrer de Verge De Montserrat, 1",
    "sg:city":"Sant Marti Sarroca",
    "sg:orig_category":"Reparaciones Y Remolcado De Veh\u00cdculos",
    "sg:phone":"+34 938 99 00 53",
    "sg:postcode":"08731",
    "sg:province":"Barcelona",
    "wof:name":"Rafecas Gutierrez Margarida",
    "wof:placetype":"venue"
},
  "geometry": {"coordinates":[1.6086250544,41.3865356445],"type":"Point"}
}