{
  "type": "Feature",
  "properties": {
    "addr:full":"Avda Mar (del), 37 Almeria Almer\u00eda 04002",
    "addr:housenumber":"37",
    "addr:postcode":"04002",
    "addr:street":"Avda Mar Del",
    "iso:country":"ES",
    "sg:address":"Avda Mar (del), 37",
    "sg:city":"Almeria",
    "sg:orig_category":"Droguer\u00cdas (al Por Menor)",
    "sg:phone":"+34 950 26 76 21",
    "sg:postcode":"04002",
    "sg:province":"Almer\u00eda",
    "wof:name":"Pinturas Y Decoraciones Salmeron E Hijos S.l.",
    "wof:placetype":"venue"
},
  "geometry": {"coordinates":[-2.4758839607,36.8388442993],"type":"Point"}
}