{
  "type": "Feature",
  "properties": {
    "iso:country":"ES",
    "sg:address":"Carrer de Mallorca, 188",
    "sg:city":"Barcelona",
    "sg:classifiers":[
        {
            "category":"Professional",
            "subcategory":"Research",
            "type":"Services"
        }
    ],
    "sg:phone":"+34 933 23 85 00",
    "sg:postcode":"08036",
    "sg:province":"Barcelona",
    "sg:tags":[
        "mercado",
        "de",
        "estudios"
    ],
    "wof:name":"Sbr Europe Ltd",
    "wof:placetype":"venue"
},
  "geometry": {"coordinates":[2.1570770741,41.3895263672],"type":"Point"}
}