{
  "type": "Feature",
  "properties": {
    "addr:full":"Calle de Pedro De Alvarado, 39 Badajoz Badajoz 06006",
    "addr:housenumber":"39",
    "addr:postcode":"06006",
    "addr:street":"Calle De Pedro De Alvarado",
    "iso:country":"ES",
    "sg:address":"Calle de Pedro De Alvarado, 39",
    "sg:city":"Badajoz",
    "sg:orig_category":"Fabricaci\u00d3n, Instalaci\u00d3n Y Reparaci\u00d3n De Bombas",
    "sg:phone":"+34 924 27 54 35",
    "sg:postcode":"06006",
    "sg:province":"Badajoz",
    "wof:name":"Brieva Barjola Froilan",
    "wof:placetype":"venue"
},
  "geometry": {"coordinates":[-6.9857058525,38.8893432617],"type":"Point"}
}