{
  "type": "Feature",
  "properties": {
    "iso:country":"ES",
    "sg:address":"Carrer de Carreras Candi, 36",
    "sg:city":"Argentona",
    "sg:orig_category":"Inmobiliaria (agencias)",
    "sg:phone":"+34 937 56 07 57",
    "sg:postcode":"08310",
    "sg:province":"Barcelona",
    "wof:name":"Inmobiliaria J. Y P. S.a.",
    "wof:placetype":"venue"
},
  "geometry": {"coordinates":[2.4036650658,41.5564155579],"type":"Point"}
}