{
  "type": "Feature",
  "properties": {
    "addr:full":"Avda Cid Campeador, 12 Burgos Burgos 09005",
    "addr:housenumber":"12",
    "addr:postcode":"09005",
    "addr:street":"Avda Cid Campeador",
    "iso:country":"ES",
    "sg:address":"Avda Cid Campeador, 12",
    "sg:city":"Burgos",
    "sg:orig_category":"Aguas (distribuci\u00d3n, Servicios)",
    "sg:phone":"+34 947 25 71 11",
    "sg:postcode":"09005",
    "sg:province":"Burgos",
    "wof:name":"Ayuntamiento De Burgos",
    "wof:placetype":"venue"
},
  "geometry": {"coordinates":[-3.6980009079,42.3451805115],"type":"Point"}
}