{
  "type": "Feature",
  "properties": {
    "addr:full":"Rua Armanya, 6 Lugo Lugo 27001",
    "addr:housenumber":"6",
    "addr:postcode":"27001",
    "addr:street":"Rua Armanya",
    "iso:country":"ES",
    "sg:address":"Rua Armanya, 6",
    "sg:city":"Lugo",
    "sg:orig_category":"Ingeniero",
    "sg:phone":"+34 982 24 55 76",
    "sg:postcode":"27001",
    "sg:province":"Lugo",
    "wof:name":"Rivero Castro Jose Fernando",
    "wof:placetype":"venue"
},
  "geometry": {"coordinates":[-7.5579972267,43.0106582642],"type":"Point"}
}