{
  "type": "Feature",
  "properties": {
    "iso:country":"ES",
    "sg:address":"Calle de Almirante Eulate, 6",
    "sg:city":"Coru\u00d1a",
    "sg:orig_category":"Promotores Constructores",
    "sg:phone":"+34 981 25 88 43",
    "sg:postcode":"15011",
    "sg:province":"La Coru\u00f1a",
    "wof:name":"Lopez Alonso Ramon",
    "wof:placetype":"venue"
},
  "geometry": {"coordinates":[-8.417222023,43.3700027466],"type":"Point"}
}