{
  "type": "Feature",
  "properties": {
    "addr:full":"Calle de Francisco Legorburu De, 6 Aviles Asturias 33403",
    "addr:housenumber":"6",
    "addr:postcode":"33403",
    "addr:street":"Calle De Francisco Legorburu De",
    "iso:country":"ES",
    "sg:address":"Calle de Francisco Legorburu De, 6",
    "sg:city":"Aviles",
    "sg:orig_category":"Fotograf\u00cda Art\u00cdstica Y Retratos",
    "sg:phone":"+34 985 51 58 28",
    "sg:postcode":"33403",
    "sg:province":"Asturias",
    "wof:name":"Menendez Mayo Maria Consuelo",
    "wof:placetype":"venue"
},
  "geometry": {"coordinates":[-5.9036178589,43.5377540588],"type":"Point"}
}