{
  "type": "Feature",
  "properties": {
    "addr:full":"Jaume Roig, 4 Puerto Sagunto Valencia 46520",
    "addr:housenumber":"4",
    "addr:postcode":"46520",
    "addr:street":"Jaume Roig",
    "iso:country":"ES",
    "sg:address":"Jaume Roig, 4",
    "sg:city":"Puerto Sagunto",
    "sg:orig_category":"Muebles, Minoristas",
    "sg:phone":"+34 962 68 00 91",
    "sg:postcode":"46520",
    "sg:province":"Valencia",
    "wof:name":"Hipermueble Provenzal S.l.",
    "wof:placetype":"venue"
},
  "geometry": {"coordinates":[-0.2278539985,39.6646537781],"type":"Point"}
}