{
  "type": "Feature",
  "properties": {
    "iso:country":"ES",
    "sg:address":"Calle de Camara La, 32",
    "sg:city":"Aviles",
    "sg:orig_category":"Perfumer\u00cda, Art\u00cdculos De Ba\u00d1o (fabricaci\u00d3n, Al Por Mayor)",
    "sg:phone":"+34 985 56 16 67",
    "sg:postcode":"33402",
    "sg:province":"Asturias",
    "wof:name":"Mu\u00f1iz Hevia Eloina",
    "wof:placetype":"venue"
},
  "geometry": {"coordinates":[-5.9240159988,43.5571060181],"type":"Point"}
}