{
  "type": "Feature",
  "properties": {
    "addr:full":"Calle de Francisco Miranda, 27 Icod De Los Vinos Santa Cruz De Tenerife 38430",
    "addr:housenumber":"27",
    "addr:postcode":"38430",
    "addr:street":"Calle De Francisco Miranda",
    "iso:country":"ES",
    "sg:address":"Calle de Francisco Miranda, 27",
    "sg:city":"Icod De Los Vinos",
    "sg:orig_category":"Fisioterapia",
    "sg:phone":"+34 922 12 21 96",
    "sg:postcode":"38430",
    "sg:province":"Santa Cruz De Tenerife",
    "wof:name":"C.b.centro De Fisioterapia Icod",
    "wof:placetype":"venue"
},
  "geometry": {"coordinates":[-16.7210521698,28.3695755005],"type":"Point"}
}