{
  "type": "Feature",
  "properties": {
    "addr:full":"Carrer de Joan Maragall, 1 Mataro Barcelona 08303",
    "addr:housenumber":"1",
    "addr:postcode":"08303",
    "addr:street":"Carrer De Joan Maragall",
    "iso:country":"ES",
    "sg:address":"Carrer de Joan Maragall, 1",
    "sg:city":"Mataro",
    "sg:orig_category":"Mec\u00c1nico Del Autom\u00d3vil",
    "sg:phone":"+34 937 98 69 67",
    "sg:postcode":"08303",
    "sg:province":"Barcelona",
    "wof:name":"Kempf  Herburt Bruno",
    "wof:placetype":"venue"
},
  "geometry": {"coordinates":[2.4284191132,41.5402946472],"type":"Point"}
}