{
  "type": "Feature",
  "properties": {
    "iso:country":"ES",
    "sg:address":"La Tercia, 8",
    "sg:city":"Cambil",
    "sg:orig_category":"Estancos",
    "sg:phone":"+34 953 30 05 72",
    "sg:postcode":"23120",
    "sg:province":"Ja\u00e9n",
    "wof:name":"Almagro Martos Ascension",
    "wof:placetype":"venue"
},
  "geometry": {"coordinates":[-3.5658929348,37.6765060425],"type":"Point"}
}