{
  "type": "Feature",
  "properties": {
    "iso:country":"ES",
    "sg:address":"Carrer de B, 1",
    "sg:city":"Colonia Guell",
    "sg:orig_category":"Inform\u00c1tica: Soportes De Informaci\u00d3n, Suministros & Accesorios",
    "sg:phone":"+34 936 30 02 04",
    "sg:postcode":"08690",
    "sg:province":"Barcelona",
    "wof:name":"Catalana De Informatica 90 S.l.",
    "wof:placetype":"venue"
},
  "geometry": {"coordinates":[2.0219130516,41.3697509766],"type":"Point"}
}