{
  "type": "Feature",
  "properties": {
    "iso:country":"ES",
    "sg:address":"Ctra Barcelona, 85",
    "sg:city":"Cerdanyola Valles",
    "sg:orig_category":"Cerrajer\u00cda, Ferrallista",
    "sg:phone":"+34 935 80 16 78",
    "sg:postcode":"08290",
    "sg:province":"Barcelona",
    "wof:name":"A.gestion Telefonica Oficinas Y Despachos S.l.",
    "wof:placetype":"venue"
},
  "geometry": {"coordinates":[2.1490604877,41.4925918579],"type":"Point"}
}