{
  "type": "Feature",
  "properties": {
    "addr:full":"Calle de San Melchor Garcia Sampedro, 59 Oviedo Asturias 33008",
    "addr:housenumber":"59",
    "addr:postcode":"33008",
    "addr:street":"Calle De San;Sampedro",
    "iso:country":"ES",
    "sg:address":"Calle de San Melchor Garcia Sampedro, 59",
    "sg:city":"Oviedo",
    "sg:orig_category":"Tapiceros Y Tapiceros",
    "sg:phone":"+34 985 20 39 77",
    "sg:postcode":"33008",
    "sg:province":"Asturias",
    "wof:name":"Construcciones Gonzalo Reguera S.l.",
    "wof:placetype":"venue"
},
  "geometry": {"coordinates":[-5.8345990181,43.3571090698],"type":"Point"}
}