{
  "type": "Feature",
  "properties": {
    "addr:full":"Av Tres-cents Deu, 1 Castelldefels Barcelona 08860",
    "addr:postcode":"08860",
    "addr:street":"Av Tres-Cents",
    "iso:country":"ES",
    "sg:address":"Av Tres-cents Deu, 1",
    "sg:city":"Castelldefels",
    "sg:orig_category":"Molduras, Junquillos, Listones Y Molduras Perforadas",
    "sg:phone":"+34 936 65 04 00",
    "sg:postcode":"08860",
    "sg:province":"Barcelona",
    "wof:name":"Blasco Torres Arturo",
    "wof:placetype":"venue"
},
  "geometry": {"coordinates":[1.9784450531,41.2793083191],"type":"Point"}
}