{
  "type": "Feature",
  "properties": {
    "iso:country":"ES",
    "sg:address":"Cm\u00d1o Chumba, 32",
    "sg:city":"Vigo",
    "sg:orig_category":"Agencias Y Agentes Comerciales, Representantes",
    "sg:phone":"+34 986 45 08 12",
    "sg:postcode":"36216",
    "sg:province":"Pontevedra",
    "wof:name":"Carre\u00f1o Peleteiro Manuel Angel",
    "wof:placetype":"venue"
},
  "geometry": {"coordinates":[-8.6801509857,42.2590141296],"type":"Point"}
}