{
  "type": "Feature",
  "properties": {
    "addr:full":"Rua Francisco Ya\u00d1ez, 19 Mugardos La Coru\u00f1a 15620",
    "addr:housenumber":"19",
    "addr:postcode":"15620",
    "addr:street":"Rua Francisco Yan\u0303Ez;La Corun\u0303A",
    "iso:country":"ES",
    "sg:address":"Rua Francisco Ya\u00d1ez, 19",
    "sg:city":"Mugardos",
    "sg:orig_category":"Montaje (empresas De)",
    "sg:phone":"+34 981 47 21 15",
    "sg:postcode":"15620",
    "sg:province":"La Coru\u00f1a",
    "wof:name":"Metalurgica Del Atlantico S.l.",
    "wof:placetype":"venue"
},
  "geometry": {"coordinates":[-8.252620697,43.4547615051],"type":"Point"}
}