{
  "type": "Feature",
  "properties": {
    "iso:country":"ES",
    "sg:address":"Calle de Vendederas, 16",
    "sg:city":"Andujar",
    "sg:orig_category":"Electrodom\u00c9sticos (al Por Menor)",
    "sg:phone":"+34 953 50 19 99",
    "sg:postcode":"23740",
    "sg:province":"Ja\u00e9n",
    "wof:name":"Canton Rodriguez Andres",
    "wof:placetype":"venue"
},
  "geometry": {"coordinates":[-4.0570950508,38.0404624939],"type":"Point"}
}