{
  "type": "Feature",
  "properties": {
    "addr:full":"Calle de Cruz Verde, 8 Ronda M\u00e1laga 29400",
    "addr:housenumber":"8",
    "addr:postcode":"29400",
    "addr:street":"Calle De Cruz Verde;Ronda Ma\u0301Laga",
    "iso:country":"ES",
    "sg:address":"Calle de Cruz Verde, 8",
    "sg:city":"Ronda",
    "sg:orig_category":"Art\u00cdculos De Decoraci\u00d3n",
    "sg:phone":"+34 952 87 40 50",
    "sg:postcode":"29400",
    "sg:province":"M\u00e1laga",
    "wof:name":"Badillo Villanueva Juan Javier",
    "wof:placetype":"venue"
},
  "geometry": {"coordinates":[-5.1631531715,36.7443351746],"type":"Point"}
}