{
  "type": "Feature",
  "properties": {
    "iso:country":"ES",
    "sg:address":"Carrer de Serradal, 11",
    "sg:city":"Seva",
    "sg:orig_category":"Producci\u00d3n, Comercio De Cereales",
    "sg:phone":"+34 938 84 00 76",
    "sg:postcode":"08553",
    "sg:province":"Barcelona",
    "wof:name":"Cooperativa Agropecuaria Matagalls S.c.l.",
    "wof:placetype":"venue"
},
  "geometry": {"coordinates":[2.2751309872,41.8237876892],"type":"Point"}
}