{
  "type": "Feature",
  "properties": {
    "addr:full":"Avda Ejercito, 80 Coru\u00d1a La Coru\u00f1a 15006",
    "addr:housenumber":"80",
    "addr:postcode":"15006",
    "addr:street":"Avda Ejercito;Corun\u0303A",
    "iso:country":"ES",
    "sg:address":"Avda Ejercito, 80",
    "sg:city":"Coru\u00d1a",
    "sg:orig_category":"Contenedores (mercanc\u00cdas)",
    "sg:phone":"+34 981 29 21 11",
    "sg:postcode":"15006",
    "sg:province":"La Coru\u00f1a",
    "wof:name":"Coru\u00f1a Hercules S.l.",
    "wof:placetype":"venue"
},
  "geometry": {"coordinates":[-8.3923845291,43.3536109924],"type":"Point"}
}