{
  "type": "Feature",
  "properties": {
    "addr:full":"Avda Moreras (de Las), 27 Mazarron Murcia 30870",
    "addr:housenumber":"27",
    "addr:postcode":"30870",
    "addr:street":"Avda Moreras De Las",
    "iso:country":"ES",
    "sg:address":"Avda Moreras (de Las), 27",
    "sg:city":"Mazarron",
    "sg:orig_category":"Comercio, Reparaci\u00d3n De Motocicletas, Bicicletas Y Piezas Sueltas",
    "sg:phone":"+34 968 59 02 31",
    "sg:postcode":"30870",
    "sg:province":"Murcia",
    "wof:name":"Hernandez Moreno Juan",
    "wof:placetype":"venue"
},
  "geometry": {"coordinates":[-1.3163440228,37.5916786194],"type":"Point"}
}