{
  "type": "Feature",
  "properties": {
    "addr:full":"Calle de Joaquin Chapaprieta, 26 Torrevieja Alicante 03180",
    "addr:housenumber":"26",
    "addr:postcode":"03180",
    "addr:street":"Calle De Joaquin Chapaprieta",
    "iso:country":"ES",
    "sg:address":"Calle de Joaquin Chapaprieta, 26",
    "sg:city":"Torrevieja",
    "sg:orig_category":"Asesor\u00cda Fiscal Y Jur\u00cddica",
    "sg:phone":"+34 966 70 49 94",
    "sg:postcode":"03180",
    "sg:province":"Alicante",
    "wof:name":"West Med Consulting S.l.",
    "wof:placetype":"venue"
},
  "geometry": {"coordinates":[-0.680997014,37.9777946472],"type":"Point"}
}