{
  "type": "Feature",
  "properties": {
    "addr:full":"Carrer de Diputacio, 305 Barcelona Barcelona 08009",
    "addr:housenumber":"305",
    "addr:postcode":"08009",
    "addr:street":"Carrer De Diputacio",
    "iso:country":"ES",
    "sg:address":"Carrer de Diputacio, 305",
    "sg:city":"Barcelona",
    "sg:orig_category":"M\u00c9dicos: Cirug\u00cda Ortop\u00c9dica Y Traumatolog\u00cda",
    "sg:phone":"+34 934 88 08 38",
    "sg:postcode":"08009",
    "sg:province":"Barcelona",
    "wof:name":"Arranz Bayod Julio",
    "wof:placetype":"venue"
},
  "geometry": {"coordinates":[2.1699259281,41.3925933838],"type":"Point"}
}