{
  "type": "Feature",
  "properties": {
    "addr:full":"Av Princep D'asturies, 34 Barcelona Barcelona 08012",
    "addr:housenumber":"34",
    "addr:postcode":"08012",
    "addr:street":"Av Princep D'Asturies",
    "iso:country":"ES",
    "sg:address":"Av Princep D'asturies, 34",
    "sg:city":"Barcelona",
    "sg:orig_category":"Asesor\u00cda Fiscal Y Jur\u00cddica",
    "sg:phone":"+34 934 15 91 67",
    "sg:postcode":"08012",
    "sg:province":"Barcelona",
    "wof:name":"Bufet Marti & Lopez S.l.",
    "wof:placetype":"venue"
},
  "geometry": {"coordinates":[2.1500239372,41.4036827087],"type":"Point"}
}