{
  "type": "Feature",
  "properties": {
    "iso:country":"ES",
    "sg:address":"Calle de Antonio Trueba, 5",
    "sg:city":"Sestao",
    "sg:orig_category":"Sindicatos De Trabajadores",
    "sg:phone":"+34 944 72 32 21",
    "sg:postcode":"48910",
    "sg:province":"Vizcaya",
    "wof:name":"Comisiones Obreras De Euskadi",
    "wof:placetype":"venue"
},
  "geometry": {"coordinates":[-3.0057990551,43.3072128296],"type":"Point"}
}