{
  "type": "Feature",
  "properties": {
    "iso:country":"ES",
    "sg:address":"Calle de Calzada De Castro, 12",
    "sg:city":"Almeria",
    "sg:orig_category":"Telas Y Sedas (al Por Menor)",
    "sg:phone":"+34 950 25 78 20",
    "sg:postcode":"04006",
    "sg:province":"Almer\u00eda",
    "wof:name":"El Hogar De Las Cortinas S.l.",
    "wof:placetype":"venue"
},
  "geometry": {"coordinates":[-2.4546980858,36.8376617432],"type":"Point"}
}