{
  "type": "Feature",
  "properties": {
    "iso:country":"ES",
    "sg:address":"Santesteban, 5",
    "sg:city":"Iru\u00f1a",
    "sg:orig_category":"Asociaciones, Organismos Culturales Y Socioeducativos",
    "sg:phone":"+34 948 12 51 07",
    "sg:postcode":"31015",
    "sg:province":"Navarra",
    "wof:name":"Sarteneko",
    "wof:placetype":"venue"
},
  "geometry": {"coordinates":[-1.6304370165,42.8254852295],"type":"Point"}
}