{
  "type": "Feature",
  "properties": {
    "addr:full":"Calle de General Casta\u00d1os, 71 Portugalete Vizcaya 48920",
    "addr:housenumber":"71",
    "addr:postcode":"48920",
    "addr:street":"Calle De General Castan\u0303Os",
    "iso:country":"ES",
    "sg:address":"Calle de General Casta\u00d1os, 71",
    "sg:city":"Portugalete",
    "sg:orig_category":"Fabricaci\u00d3n, Importaci\u00d3n, Venta De Material De Telefon\u00cda, Peritelefon\u00cda",
    "sg:phone":"+34 944 83 02 44",
    "sg:postcode":"48920",
    "sg:province":"Vizcaya",
    "sg:website":"www.tecmotel.com",
    "wof:name":"Slhtecmotel S.l.",
    "wof:placetype":"venue"
},
  "geometry": {"coordinates":[-3.0241880417,43.3221473694],"type":"Point"}
}