{
  "type": "Feature",
  "properties": {
    "addr:full":"Carrer de Jacint Verdaguer, 78 S. Joan Despi Barcelona 08970",
    "addr:housenumber":"78",
    "addr:postcode":"08970",
    "addr:street":"Carrer De Jacint Verdaguer;S. Joan Despi",
    "iso:country":"ES",
    "sg:address":"Carrer de Jacint Verdaguer, 78",
    "sg:city":"S. Joan Despi",
    "sg:orig_category":"Caf\u00c9s, Bares, Cervecer\u00cdas",
    "sg:phone":"+34 933 73 91 69",
    "sg:postcode":"08970",
    "sg:province":"Barcelona",
    "wof:name":"Pildo Dinner's S.l.",
    "wof:placetype":"venue"
},
  "geometry": {"coordinates":[2.068226099,41.3733253479],"type":"Point"}
}