{
  "type": "Feature",
  "properties": {
    "addr:full":"Calle de Carmen Bordon Lopez, 26 Juan Grande Las Palmas 35107",
    "addr:postcode":"35107",
    "addr:street":"Calle De Carmen Bordon Lopez 26 Juan Grande Las",
    "iso:country":"ES",
    "sg:address":"Calle de Carmen Bordon Lopez, 26",
    "sg:city":"Juan Grande",
    "sg:orig_category":"Molduras, Junquillos, Listones Y Molduras Perforadas",
    "sg:phone":"+34 928 72 84 18",
    "sg:postcode":"35107",
    "sg:province":"Las Palmas",
    "wof:name":"Santana Rodriguez Vicente",
    "wof:placetype":"venue"
},
  "geometry": {"coordinates":[-15.4727249146,27.8063087463],"type":"Point"}
}