{
  "type": "Feature",
  "properties": {
    "addr:full":"Ctra Madrona, 1 Segovia Segovia 40002",
    "addr:housenumber":"1",
    "addr:postcode":"40002",
    "addr:street":"Ctra Madrona",
    "iso:country":"ES",
    "sg:address":"Ctra Madrona, 1",
    "sg:city":"Segovia",
    "sg:orig_category":"Doctores En Medicina",
    "sg:phone":"+34 921 44 22 20",
    "sg:postcode":"40002",
    "sg:province":"Segovia",
    "wof:name":"Centro De Reconocimiento Goya S.l.",
    "wof:placetype":"venue"
},
  "geometry": {"coordinates":[-4.1201891899,40.9433059692],"type":"Point"}
}