{
  "type": "Feature",
  "properties": {
    "iso:country":"ES",
    "sg:address":"Calle de Rudolf Diesel, 23",
    "sg:city":"Zaragoza",
    "sg:orig_category":"Importaci\u00d3n",
    "sg:phone":"+34 976 73 65 41",
    "sg:postcode":"50015",
    "sg:province":"Zaragoza",
    "wof:name":"Totaal Concept Professional S. L.",
    "wof:placetype":"venue"
},
  "geometry": {"coordinates":[-0.8636890054,41.6791496277],"type":"Point"}
}