{
  "type": "Feature",
  "properties": {
    "addr:full":"Calle de Betica, 22 Ejido Almer\u00eda 04700",
    "addr:housenumber":"22 ejido",
    "addr:postcode":"04700",
    "addr:street":"Calle De Betica;Almeri\u0301A",
    "iso:country":"ES",
    "sg:address":"Calle de Betica, 22",
    "sg:city":"Ejido",
    "sg:orig_category":"Venta, Colocaci\u00d3n, Reparaci\u00d3n De Parabrisas, Techos Descapotables",
    "sg:phone":"+34 950 48 13 13",
    "sg:postcode":"04700",
    "sg:province":"Almer\u00eda",
    "wof:name":"Almerividrio S.l.",
    "wof:placetype":"venue"
},
  "geometry": {"coordinates":[-2.8026344776,36.7780189514],"type":"Point"}
}