{
  "type": "Feature",
  "properties": {
    "addr:full":"Calle de General Moscardo, 25 Madrid Madrid 28020",
    "addr:housenumber":"25",
    "addr:postcode":"madrid;28020",
    "addr:street":"Calle De General Moscardo",
    "iso:country":"ES",
    "sg:address":"Calle de General Moscardo, 25",
    "sg:city":"Madrid",
    "sg:orig_category":"Ingenier\u00cda, Centros De Estudios (diversos)",
    "sg:phone":"+34 915 33 95 40",
    "sg:postcode":"28020",
    "sg:province":"Madrid",
    "wof:name":"Laherran Perez Enrique",
    "wof:placetype":"venue"
},
  "geometry": {"coordinates":[-3.6968071461,40.4499588013],"type":"Point"}
}