{
  "type": "Feature",
  "properties": {
    "addr:full":"Carrer de Sau, 7 Vic Barcelona 08500",
    "addr:housenumber":"7",
    "addr:postcode":"08500",
    "addr:street":"Carrer De Sau",
    "iso:country":"ES",
    "sg:address":"Carrer de Sau, 7",
    "sg:city":"Vic",
    "sg:orig_category":"Cueros Y Pieles (al Por Mayor)",
    "sg:phone":"+34 938 86 91 10",
    "sg:postcode":"08500",
    "sg:province":"Barcelona",
    "wof:name":"Francopell S.l.",
    "wof:placetype":"venue"
},
  "geometry": {"coordinates":[2.2828319073,41.9462966919],"type":"Point"}
}