{
  "type": "Feature",
  "properties": {
    "addr:full":"Rua Lepanto, 11 Pontevedra Pontevedra 36099",
    "addr:housenumber":"11",
    "addr:postcode":"36099",
    "addr:street":"Rua Lepanto",
    "iso:country":"ES",
    "sg:address":"Rua Lepanto, 11",
    "sg:city":"Pontevedra",
    "sg:orig_category":"Asesor\u00cdas Y Estudios Financieros",
    "sg:phone":"+34 986 86 44 68",
    "sg:postcode":"36099",
    "sg:province":"Pontevedra",
    "wof:name":"Vidal Mauricio Jose Antonio",
    "wof:placetype":"venue"
},
  "geometry": {"coordinates":[-8.6388692856,42.4304351807],"type":"Point"}
}