{
  "type": "Feature",
  "properties": {
    "addr:full":"Calle de Mayor, 91 Alcorcon Madrid 28922",
    "addr:housenumber":"91",
    "addr:postcode":"28922",
    "addr:street":"Calle De Mayor",
    "iso:country":"ES",
    "sg:address":"Calle de Mayor, 91",
    "sg:city":"Alcorcon",
    "sg:orig_category":"Lencer\u00cda Femenina, Corseter\u00cda, Trajes De Ba\u00d1o (al Por Menor)",
    "sg:phone":"+34 916 41 69 56",
    "sg:postcode":"28922",
    "sg:province":"Madrid",
    "wof:name":"Coso Daoiz Juana Maria",
    "wof:placetype":"venue"
},
  "geometry": {"coordinates":[-3.8274080753,40.3411865234],"type":"Point"}
}