{
  "type": "Feature",
  "properties": {
    "iso:country":"ES",
    "sg:address":"C/ Trencadors, 47",
    "sg:city":"Arenal",
    "sg:orig_category":"Fisioterapia",
    "sg:phone":"+34 971 44 51 60",
    "sg:postcode":"07600",
    "sg:province":"Islas Baleares",
    "wof:name":"Miralles Tomas Antonia",
    "wof:placetype":"venue"
},
  "geometry": {"coordinates":[2.752327919,39.5086097717],"type":"Point"}
}