{
  "type": "Feature",
  "properties": {
    "addr:full":"Presa De Alende, 2 Pontes Garcia Rodriguez La Coru\u00f1a 15320",
    "addr:housenumber":"2",
    "addr:postcode":"15320",
    "addr:street":"Pontes Garcia Rodriguez La Corun\u0303A",
    "iso:country":"ES",
    "sg:address":"Presa De Alende, 2",
    "sg:city":"Pontes Garcia Rodriguez",
    "sg:orig_category":"Mec\u00c1nico Del Autom\u00d3vil",
    "sg:phone":"+34 981 45 25 82",
    "sg:postcode":"15320",
    "sg:province":"La Coru\u00f1a",
    "wof:name":"Neumaticos Soledad S.l.",
    "wof:placetype":"venue"
},
  "geometry": {"coordinates":[-7.8479528427,43.4449768066],"type":"Point"}
}