{
  "type": "Feature",
  "properties": {
    "addr:full":"Calle de Sevilla, 21 Mostoles Madrid 28931",
    "addr:housenumber":"21",
    "addr:postcode":"28931",
    "addr:street":"Calle De Sevilla",
    "iso:country":"ES",
    "sg:address":"Calle de Sevilla, 21",
    "sg:city":"Mostoles",
    "sg:orig_category":"Caf\u00c9s, Bares, Cervecer\u00cdas",
    "sg:phone":"+34 916 14 16 60",
    "sg:postcode":"28931",
    "sg:province":"Madrid",
    "wof:name":"Herrero Gallego Vicente",
    "wof:placetype":"venue"
},
  "geometry": {"coordinates":[-3.8690209389,40.3244514465],"type":"Point"}
}