{
  "type": "Feature",
  "properties": {
    "iso:country":"ES",
    "sg:address":"Carrer de Castellnou, 36",
    "sg:city":"Barcelona",
    "sg:orig_category":"Promotores Constructores",
    "sg:phone":"+34 932 52 56 56",
    "sg:postcode":"08017",
    "sg:province":"Barcelona",
    "wof:name":"New Grange Holding Espa\u00f1a S.l.",
    "wof:placetype":"venue"
},
  "geometry": {"coordinates":[2.1296679974,41.3958091736],"type":"Point"}
}