{
  "type": "Feature",
  "properties": {
    "addr:full":"Calle de Carlos Arniches, 11 Calpe Alicante 03710",
    "addr:housenumber":"11",
    "addr:postcode":"03710",
    "addr:street":"Calle De Carlos Arniches",
    "iso:country":"ES",
    "sg:address":"Calle de Carlos Arniches, 11",
    "sg:city":"Calpe",
    "sg:orig_category":"Cerrajer\u00cda, Ferrallista",
    "sg:phone":"+34 965 83 76 41",
    "sg:postcode":"03710",
    "sg:province":"Alicante",
    "wof:name":"Rodriguez Pereiro Jose Antonio",
    "wof:placetype":"venue"
},
  "geometry": {"coordinates":[0.0404947996,38.6448440552],"type":"Point"}
}