{
  "type": "Feature",
  "properties": {
    "addr:full":"Carretera De Allariz, S/n Merca Ourense 32830",
    "addr:housenumber":"s / n",
    "addr:postcode":"32830",
    "addr:street":"Carretera De Allariz",
    "iso:country":"ES",
    "sg:address":"Carretera De Allariz, S/n",
    "sg:city":"Merca",
    "sg:orig_category":"Cajas De Ahorro",
    "sg:phone":"+34 988 26 00 56",
    "sg:postcode":"32830",
    "sg:province":"Ourense",
    "wof:name":"Caixa De Aforros De Vigo Ourense E Pontevedra",
    "wof:placetype":"venue"
},
  "geometry": {"coordinates":[-7.9057488441,42.2220458984],"type":"Point"}
}