{
  "type": "Feature",
  "properties": {
    "iso:country":"ES",
    "sg:address":"Pl Lluis Perpinya, 8",
    "sg:city":"Granollers",
    "sg:orig_category":"Bazares, Art\u00cdculos De Limpieza Y De Cocina (al Por Menor)",
    "sg:phone":"+34 938 79 45 98",
    "sg:postcode":"08401",
    "sg:province":"Barcelona",
    "sg:website":"www.bazarelregalo.es",
    "wof:name":"Agrupacion Bazar El Regalo S.a.",
    "wof:placetype":"venue"
},
  "geometry": {"coordinates":[2.2891764641,41.6094779968],"type":"Point"}
}