{
  "type": "Feature",
  "properties": {
    "addr:full":"Avda Almozara, 34 Zaragoza Zaragoza 50003",
    "addr:housenumber":"34",
    "addr:postcode":"50003",
    "addr:street":"Avda Almozara",
    "iso:country":"ES",
    "sg:address":"Avda Almozara, 34",
    "sg:city":"Zaragoza",
    "sg:orig_category":"Ense\u00d1anza Variada",
    "sg:phone":"+34 976 28 28 73",
    "sg:postcode":"50003",
    "sg:province":"Zaragoza",
    "wof:name":"Pascual Moya Maria Visitacion",
    "wof:placetype":"venue"
},
  "geometry": {"coordinates":[-0.896378994,41.6618499756],"type":"Point"}
}