{
  "type": "Feature",
  "properties": {
    "addr:full":"Pol. Bakiola (parcela), 20 Arrankudiaga Vizcaya 48498",
    "addr:postcode":"48498",
    "addr:street":"Parcela",
    "iso:country":"ES",
    "sg:address":"Pol. Bakiola (parcela), 20",
    "sg:city":"Arrankudiaga",
    "sg:orig_category":"Madera Para Construcci\u00d3n E Industria",
    "sg:phone":"+34 944 05 57 60",
    "sg:postcode":"48498",
    "sg:province":"Vizcaya",
    "wof:name":"Escaleras Solachi, Jose Ignacio Solachi Arzuaga",
    "wof:placetype":"venue"
},
  "geometry": {"coordinates":[-2.9183759689,43.1738014221],"type":"Point"}
}