{
  "type": "Feature",
  "properties": {
    "iso:country":"ES",
    "sg:address":"Avda Prudencio Gonzalez, 67",
    "sg:city":"Posada",
    "sg:orig_category":"Alimentaci\u00d3n General (al Por Mayor)",
    "sg:phone":"+34 985 77 01 67",
    "sg:postcode":"33424",
    "sg:province":"Asturias",
    "wof:name":"Llana C.b.",
    "wof:placetype":"venue"
},
  "geometry": {"coordinates":[-5.8537387848,43.4417686462],"type":"Point"}
}