{
  "type": "Feature",
  "properties": {
    "addr:full":"Calle de Diamantino Garcia Acosta, 29 Sevilla Sevilla 41006",
    "addr:housenumber":"29",
    "addr:postcode":"41006",
    "addr:street":"Calle De Diamantino Garcia Acosta",
    "iso:country":"ES",
    "sg:address":"Calle de Diamantino Garcia Acosta, 29",
    "sg:city":"Sevilla",
    "sg:orig_category":"Agentes Generales De Seguros",
    "sg:phone":"+34 954 63 68 90",
    "sg:postcode":"41006",
    "sg:province":"Sevilla",
    "wof:name":"Vargas Cardoso Rafael",
    "wof:placetype":"venue"
},
  "geometry": {"coordinates":[-5.9580388069,37.3707618713],"type":"Point"}
}