{
  "type": "Feature",
  "properties": {
    "addr:full":"Kale Nagusia, 16 Beasain Guip\u00f9zcoa 20200",
    "addr:housenumber":"16",
    "addr:postcode":"20200",
    "addr:street":"Kale Nagusia;Guipu\u0300Zcoa",
    "iso:country":"ES",
    "sg:address":"Kale Nagusia, 16",
    "sg:city":"Beasain",
    "sg:orig_category":"Agencias De Viajes",
    "sg:phone":"+34 943 88 56 67",
    "sg:postcode":"20200",
    "sg:province":"Guip\u00f9zcoa",
    "sg:website":"www.viajeseroski.es",
    "wof:name":"Viajes Eroski S.a.",
    "wof:placetype":"venue"
},
  "geometry": {"coordinates":[-2.1944589615,43.0469207764],"type":"Point"}
}