{
  "type": "Feature",
  "properties": {
    "iso:country":"ES",
    "sg:address":"Carr Sant Gervasi, 50",
    "sg:city":"Vilanova I La Geltru",
    "sg:classifiers":[
        {
            "category":"Personal",
            "subcategory":"Barber",
            "type":"Services"
        }
    ],
    "sg:phone":"+34 938 93 82 29",
    "sg:postcode":"08800",
    "sg:province":"Barcelona",
    "sg:tags":[
        "caballeros",
        "de",
        "peluqueros"
    ],
    "wof:name":"Alvarez Moral Jose",
    "wof:placetype":"venue"
},
  "geometry": {"coordinates":[1.7247468233,41.225643158],"type":"Point"}
}