{
  "type": "Feature",
  "properties": {
    "iso:country":"ES",
    "sg:address":"Carr Sils, 1",
    "sg:city":"Serres",
    "sg:orig_category":"Asociaciones Y Clubs Deportivos",
    "sg:phone":"+34 972 85 17 01",
    "sg:postcode":"17411",
    "sg:province":"Girona",
    "wof:name":"Bort Gimeno Josefa",
    "wof:placetype":"venue"
},
  "geometry": {"coordinates":[2.7773220539,41.789768219],"type":"Point"}
}