{
  "type": "Feature",
  "properties": {
    "iso:country":"ES",
    "sg:address":"Mer. Mancomunitat S. Terrassa, S/n",
    "sg:city":"Sabadell",
    "sg:orig_category":"Frutas Y Legumbres Frescas (al Por Mayor)",
    "sg:phone":"+34 937 26 45 04",
    "sg:postcode":"08206",
    "sg:province":"Barcelona",
    "wof:name":"Siurana Fruits S.l.",
    "wof:placetype":"venue"
},
  "geometry": {"coordinates":[2.0747048855,41.5592803955],"type":"Point"}
}