{
  "type": "Feature",
  "properties": {
    "iso:country":"ES",
    "sg:address":"Ibarkurutze Plaza, 3",
    "sg:city":"Eibar",
    "sg:classifiers":[
        {
            "category":"Casinos & Gambling",
            "type":"Entertainment"
        }
    ],
    "sg:phone":"+34 943 20 70 03",
    "sg:postcode":"20600",
    "sg:province":"Guip\u00f9zcoa",
    "sg:tags":[
        "locale",
        "de",
        "juego"
    ],
    "wof:name":"Casino Artista Eibarres",
    "wof:placetype":"venue"
},
  "geometry": {"coordinates":[-2.4668180943,43.1858863831],"type":"Point"}
}