{
  "type": "Feature",
  "properties": {
    "addr:full":"Ctra Se-ma-gr (p I Piedra Hincada), Km. 0011,0 Alcala Guadaira Sevilla 41500",
    "addr:postcode":"41500",
    "addr:street":"Ctra Se-Ma-Gr P;Piedra Hincada Km. 0011,0",
    "iso:country":"ES",
    "sg:address":"Ctra Se-ma-gr (p I Piedra Hincada), Km. 0011,0",
    "sg:city":"Alcala Guadaira",
    "sg:orig_category":"Muebles, Minoristas",
    "sg:phone":"+34 954 10 20 00",
    "sg:postcode":"41500",
    "sg:province":"Sevilla",
    "sg:website":"www.flandes.com",
    "wof:name":"Flandes S. A.",
    "wof:placetype":"venue"
},
  "geometry": {"coordinates":[-5.8398590088,37.3383140564],"type":"Point"}
}