{
  "type": "Feature",
  "properties": {
    "addr:full":"Calle de Mayor, 15 Arenas -areeta Vizcaya 48930",
    "addr:housenumber":"15;areeta",
    "addr:postcode":"48930",
    "addr:street":"Calle De Mayor",
    "iso:country":"ES",
    "sg:address":"Calle de Mayor, 15",
    "sg:city":"Arenas -areeta",
    "sg:orig_category":"Bisuter\u00cda, Joyer\u00cda, Relojer\u00cda (al Por Menor)",
    "sg:phone":"+34 944 80 52 05",
    "sg:postcode":"48930",
    "sg:province":"Vizcaya",
    "wof:name":"Senra Bros S.l.",
    "wof:placetype":"venue"
},
  "geometry": {"coordinates":[-3.0138239861,43.325504303],"type":"Point"}
}