{
  "type": "Feature",
  "properties": {
    "addr:full":"C/ Alvarez De Castro, 54 Banyoles Girona 17820",
    "addr:housenumber":"54",
    "addr:postcode":"17820",
    "addr:street":"C / Alvarez De Castro",
    "iso:country":"ES",
    "sg:address":"C/ Alvarez De Castro, 54",
    "sg:city":"Banyoles",
    "sg:orig_category":"\u00d3ptica: Instrumentos (fabricaci\u00d3n)",
    "sg:phone":"+34 972 58 02 49",
    "sg:postcode":"17820",
    "sg:province":"Girona",
    "wof:name":"Pro-optics C. B.",
    "wof:placetype":"venue"
},
  "geometry": {"coordinates":[2.7657361031,42.1166572571],"type":"Point"}
}