{
  "type": "Feature",
  "properties": {
    "addr:full":"Carrer de Gaieta Ventallo, 120 Mollet Valles Barcelona 08100",
    "addr:housenumber":"120",
    "addr:postcode":"08100",
    "addr:street":"Carrer De Gaieta Ventallo",
    "iso:country":"ES",
    "sg:address":"Carrer de Gaieta Ventallo, 120",
    "sg:city":"Mollet Valles",
    "sg:orig_category":"Arreglo, Reparaci\u00d3n, Piezas Sueltas De Televisi\u00d3n, V\u00cddeo, Hi",
    "sg:phone":"+34 935 93 69 11",
    "sg:postcode":"08100",
    "sg:province":"Barcelona",
    "wof:name":"Martinez Rico Pedro Antonio",
    "wof:placetype":"venue"
},
  "geometry": {"coordinates":[2.2180008888,41.5422096252],"type":"Point"}
}