{
  "type": "Feature",
  "properties": {
    "iso:country":"ES",
    "sg:address":"Calle de Corral De La Encarnacion, 13",
    "sg:city":"Sevilla",
    "sg:orig_category":"Electricidad, Electr\u00d3nica: Material Y Suministros (al Por Mayor)",
    "sg:phone":"+34 954 96 06 53",
    "sg:postcode":"41008",
    "sg:province":"Sevilla",
    "wof:name":"Grupos Electrogenos Gesan S.a.",
    "wof:placetype":"venue"
},
  "geometry": {"coordinates":[-5.9717140198,37.4188919067],"type":"Point"}
}