{
  "type": "Feature",
  "properties": {
    "addr:full":"Carr Lleida, 11 Tremp Lleida 25620",
    "addr:housenumber":"11",
    "addr:postcode":"25620",
    "addr:street":"Carr Lleida",
    "iso:country":"ES",
    "sg:address":"Carr Lleida, 11",
    "sg:city":"Tremp",
    "sg:orig_category":"Supermercados Y Hipermercados",
    "sg:phone":"+34 973 65 26 17",
    "sg:postcode":"25620",
    "sg:province":"Lleida",
    "wof:name":"Caprabo S.a.",
    "wof:placetype":"venue"
},
  "geometry": {"coordinates":[0.8948950171,42.1686935425],"type":"Point"}
}