{
  "type": "Feature",
  "properties": {
    "iso:country":"ES",
    "sg:address":"Carrer de Josep Pla, 19",
    "sg:city":"Barcelona",
    "sg:orig_category":"Inmobiliaria (agencias)",
    "sg:phone":"+34 933 56 10 68",
    "sg:postcode":"08019",
    "sg:province":"Barcelona",
    "wof:name":"Juve Raventos Jose",
    "wof:placetype":"venue"
},
  "geometry": {"coordinates":[2.2193880081,41.4061813354],"type":"Point"}
}