{
  "type": "Feature",
  "properties": {
    "addr:full":"Rua Condominguez, S/n Sanroman Pontevedra 36391",
    "addr:housenumber":"s",
    "addr:postcode":"36391",
    "addr:street":"Rua Condominguez;/ N",
    "iso:country":"ES",
    "sg:address":"Rua Condominguez, S/n",
    "sg:city":"Sanroman",
    "sg:orig_category":"Asociaciones Y Clubs Deportivos",
    "sg:phone":"+34 986 36 38 44",
    "sg:postcode":"36391",
    "sg:province":"Pontevedra",
    "wof:name":"Club De Futbol Priegue",
    "wof:placetype":"venue"
},
  "geometry": {"coordinates":[-8.8210258484,42.1536941528],"type":"Point"}
}