{
  "type": "Feature",
  "properties": {
    "iso:country":"ES",
    "sg:address":"Calle de Padre Vicente Salgado, S/n",
    "sg:city":"Puebla Sanabria",
    "sg:orig_category":"Abogados",
    "sg:phone":"+34 980 62 04 54",
    "sg:postcode":"49300",
    "sg:province":"Zamora",
    "wof:name":"Barreiros Gonzalez Maria Esther",
    "wof:placetype":"venue"
},
  "geometry": {"coordinates":[-6.6313939095,42.0552215576],"type":"Point"}
}