{
  "type": "Feature",
  "properties": {
    "addr:full":"Barr Lauroeta, 9 Asua-lauroeta Vizcaya 48950",
    "addr:housenumber":"9",
    "addr:postcode":"48950",
    "addr:street":"Lauroeta",
    "iso:country":"ES",
    "sg:address":"Barr Lauroeta, 9",
    "sg:city":"Asua-lauroeta",
    "sg:orig_category":"Venta, Instalaci\u00d3n De Cocinas",
    "sg:phone":"+34 944 53 24 40",
    "sg:postcode":"48950",
    "sg:province":"Vizcaya",
    "wof:name":"Jatetxea Aurregoiti S.l.",
    "wof:placetype":"venue"
},
  "geometry": {"coordinates":[-2.9769239426,43.302646637],"type":"Point"}
}