{
  "type": "Feature",
  "properties": {
    "addr:full":"Pase Reina Cristina, 5 Madrid Madrid 28014",
    "addr:housenumber":"5",
    "addr:postcode":"28014",
    "addr:street":"Cristina",
    "iso:country":"ES",
    "sg:address":"Pase Reina Cristina, 5",
    "sg:city":"Madrid",
    "sg:orig_category":"Inform\u00c1tica Equipo Y Programas (al Por Mayor)",
    "sg:phone":"+34 914 33 91 53",
    "sg:postcode":"28014",
    "sg:province":"Madrid",
    "wof:name":"Softlabor S.l.",
    "wof:placetype":"venue"
},
  "geometry": {"coordinates":[-3.6840779781,40.4067611694],"type":"Point"}
}