{
  "type": "Feature",
  "properties": {
    "iso:country":"ES",
    "sg:address":"Jose M. Labrador, 6",
    "sg:city":"Huelva",
    "sg:orig_category":"Animales (al Por Menor)",
    "sg:phone":"+34 959 22 27 47",
    "sg:postcode":"21007",
    "sg:province":"Huelva",
    "wof:name":"Rosa Arenas Juan Manuel De La",
    "wof:placetype":"venue"
},
  "geometry": {"coordinates":[-6.9275298119,37.2629203796],"type":"Point"}
}