{
  "type": "Feature",
  "properties": {
    "addr:full":"Rua Cardenal Cisneros, 42 Solana A Coru\u00f1a 15407",
    "addr:housenumber":"42",
    "addr:postcode":"15407",
    "addr:street":"Rua Cardenal Cisneros;Corun\u0303A",
    "iso:country":"ES",
    "sg:address":"Rua Cardenal Cisneros, 42",
    "sg:city":"Solana",
    "sg:orig_category":"M\u00c9dicos: Estomatolog\u00cda",
    "sg:phone":"+34 981 38 50 28",
    "sg:postcode":"15407",
    "sg:province":"A Coru\u00f1a",
    "wof:name":"Vila Martinez Maria Angeles",
    "wof:placetype":"venue"
},
  "geometry": {"coordinates":[-8.1969175339,43.5052642822],"type":"Point"}
}