{
  "type": "Feature",
  "properties": {
    "iso:country":"ES",
    "sg:address":"Ctra Santa Fe, S/n",
    "sg:city":"Atarfe",
    "sg:orig_category":"Promotores Constructores",
    "sg:phone":"+34 958 43 62 03",
    "sg:postcode":"18230",
    "sg:province":"Granada",
    "wof:name":"Construcciones Lopez Porras S.a.",
    "wof:placetype":"venue"
},
  "geometry": {"coordinates":[-3.6984341145,37.2160606384],"type":"Point"}
}