{
  "type": "Feature",
  "properties": {
    "iso:country":"ES",
    "sg:address":"Calle de Mayor, 83",
    "sg:city":"Alcorcon",
    "sg:orig_category":"Psic\u00d3logos",
    "sg:phone":"+34 916 43 42 00",
    "sg:postcode":"28922",
    "sg:province":"Madrid",
    "wof:name":"Ayuda Psicologica Senda Cb",
    "wof:placetype":"venue"
},
  "geometry": {"coordinates":[-3.8272829056,40.3437652588],"type":"Point"}
}