{
  "type": "Feature",
  "properties": {
    "iso:country":"ES",
    "sg:address":"Carrer de Jacinto Guerrero, 5",
    "sg:city":"Cornella Llobregat",
    "sg:orig_category":"Cerrajer\u00cda, Ferrallista",
    "sg:phone":"+34 933 75 67 00",
    "sg:postcode":"08940",
    "sg:province":"Barcelona",
    "wof:name":"Garcia Casellas Mariano",
    "wof:placetype":"venue"
},
  "geometry": {"coordinates":[2.0780510902,41.3619499207],"type":"Point"}
}