{
  "type": "Feature",
  "properties": {
    "iso:country":"ES",
    "sg:address":"Avda Arcadio Pardi\u00d1as, 211",
    "sg:city":"Burela",
    "sg:orig_category":"Chapister\u00cda",
    "sg:phone":"+34 982 58 06 75",
    "sg:postcode":"27880",
    "sg:province":"Lugo",
    "wof:name":"Garaje San Andres S.a.",
    "wof:placetype":"venue"
},
  "geometry": {"coordinates":[-7.3530597687,43.6500091553],"type":"Point"}
}