{
  "type": "Feature",
  "properties": {
    "addr:full":"Carr Amadori, 61 Vila Joiosa Alicante 03570",
    "addr:housenumber":"61",
    "addr:postcode":"03570",
    "addr:street":"Carr Amadori",
    "iso:country":"ES",
    "sg:address":"Carr Amadori, 61",
    "sg:city":"Vila Joiosa",
    "sg:orig_category":"Empresas De Carpinter\u00cda De Madera",
    "sg:phone":"+34 965 89 43 91",
    "sg:postcode":"03570",
    "sg:province":"Alicante",
    "wof:name":"Cano Lloret Miguel",
    "wof:placetype":"venue"
},
  "geometry": {"coordinates":[-0.7466139793,38.3102035522],"type":"Point"}
}