{
  "type": "Feature",
  "properties": {
    "addr:full":"Carrer de Beat Almato, 39 Barcelona Barcelona 08023",
    "addr:housenumber":"39",
    "addr:postcode":"08023",
    "addr:street":"Carrer De;Almato",
    "iso:country":"ES",
    "sg:address":"Carrer de Beat Almato, 39",
    "sg:city":"Barcelona",
    "sg:orig_category":"Peluqueros: De Se\u00d1oras",
    "sg:phone":"+34 932 84 85 81",
    "sg:postcode":"08023",
    "sg:province":"Barcelona",
    "wof:name":"Soriano Garcia Sonia",
    "wof:placetype":"venue"
},
  "geometry": {"coordinates":[2.1480560303,41.4176292419],"type":"Point"}
}