{
  "type": "Feature",
  "properties": {
    "iso:country":"ES",
    "sg:address":"Av Mare Deu De Montserrat, 39",
    "sg:city":"Barcelona",
    "sg:orig_category":"M\u00c9dicos: Estomatolog\u00cda",
    "sg:phone":"+34 932 84 60 39",
    "sg:postcode":"08024",
    "sg:province":"Barcelona",
    "wof:name":"Sterpetti Pagliaricchi Rodolfo Hugo",
    "wof:placetype":"venue"
},
  "geometry": {"coordinates":[2.1630539894,41.4144744873],"type":"Point"}
}