{
  "type": "Feature",
  "properties": {
    "addr:full":"Calle de Conde De Salvatierra, 29 Valencia Valencia 46004",
    "addr:housenumber":"29",
    "addr:postcode":"46004",
    "addr:street":"Calle De Conde De Salvatierra",
    "iso:country":"ES",
    "sg:address":"Calle de Conde De Salvatierra, 29",
    "sg:city":"Valencia",
    "sg:orig_category":"Ense\u00d1ante, Direcci\u00d3n",
    "sg:phone":"+34 963 52 80 55",
    "sg:postcode":"46004",
    "sg:province":"Valencia",
    "wof:name":"Navarro Consultores Juridicos",
    "wof:placetype":"venue"
},
  "geometry": {"coordinates":[-0.3676949143,39.4690132141],"type":"Point"}
}