{
  "type": "Feature",
  "properties": {
    "addr:full":"Plaz Josu Murueta, 2 Astrabudua Vizcaya 48950",
    "addr:housenumber":"2",
    "addr:postcode":"48950",
    "addr:street":"Plaz;Murueta",
    "iso:country":"ES",
    "sg:address":"Plaz Josu Murueta, 2",
    "sg:city":"Astrabudua",
    "sg:orig_category":"Molduras, Junquillos, Listones Y Molduras Perforadas",
    "sg:phone":"+34 944 17 50 79",
    "sg:postcode":"48950",
    "sg:province":"Vizcaya",
    "wof:name":"Ramos Barriuso Maria Pilar",
    "wof:placetype":"venue"
},
  "geometry": {"coordinates":[-2.9835391045,43.3166275024],"type":"Point"}
}