{
  "type": "Feature",
  "properties": {
    "addr:full":"El Parque, 7 Cangas Onis Asturias 33550",
    "addr:housenumber":"7",
    "addr:postcode":"33550",
    "addr:street":"El Parque;Onis Asturias",
    "iso:country":"ES",
    "sg:address":"El Parque, 7",
    "sg:city":"Cangas Onis",
    "sg:orig_category":"Centros Empresariales",
    "sg:phone":"+34 985 84 95 68",
    "sg:postcode":"33550",
    "sg:province":"Asturias",
    "sg:website":"www.rgcinformatica.telefonica.net",
    "wof:name":"Rgc Informatica C.b.",
    "wof:placetype":"venue"
},
  "geometry": {"coordinates":[-5.1302790642,43.3507957458],"type":"Point"}
}