{
  "type": "Feature",
  "properties": {
    "addr:full":"Sa Placa, 147 Sa Pobla Islas Baleares 07420",
    "addr:housenumber":"147",
    "addr:postcode":"07420",
    "addr:street":"Placa",
    "iso:country":"ES",
    "sg:address":"Sa Placa, 147",
    "sg:city":"Sa Pobla",
    "sg:orig_category":"Carnicer\u00cdas, Carnicer\u00cdas",
    "sg:phone":"+34 971 54 09 52",
    "sg:postcode":"07420",
    "sg:province":"Islas Baleares",
    "wof:name":"Rebassa Serra Gabriel",
    "wof:placetype":"venue"
},
  "geometry": {"coordinates":[3.0276100636,39.7656288147],"type":"Point"}
}