{
  "type": "Feature",
  "properties": {
    "iso:country":"ES",
    "sg:address":"Calle de Virgen, 56",
    "sg:city":"Valdepe\u00f1as",
    "sg:orig_category":"Papeler\u00cdas, Librer\u00cdas",
    "sg:phone":"+34 926 32 11 05",
    "sg:postcode":"13300",
    "sg:province":"Ciudad Real",
    "wof:name":"Olmedilla Bellot Jose Luis",
    "wof:placetype":"venue"
},
  "geometry": {"coordinates":[-3.3846290112,38.7596702576],"type":"Point"}
}