{
  "type": "Feature",
  "properties": {
    "addr:full":"Carrer de Antoni Rubio I Lluch, 39 Reus Tarragona 43206",
    "addr:housenumber":"39",
    "addr:postcode":"43206",
    "addr:street":"Carrer De Antoni Rubio I Lluch",
    "iso:country":"ES",
    "sg:address":"Carrer de Antoni Rubio I Lluch, 39",
    "sg:city":"Reus",
    "sg:orig_category":"Art\u00cdculos De Regalo (al Por Menor)",
    "sg:phone":"+34 977 33 16 89",
    "sg:postcode":"43206",
    "sg:province":"Tarragona",
    "wof:name":"Souvermon S.l.",
    "wof:placetype":"venue"
},
  "geometry": {"coordinates":[1.0797849894,41.1560287476],"type":"Point"}
}