{
  "type": "Feature",
  "properties": {
    "iso:country":"ES",
    "sg:address":"Ctra. Mahide, S/n",
    "sg:city":"San Vitero",
    "sg:orig_category":"Charcuter\u00cdas (al Por Mayor)",
    "sg:phone":"+34 980 68 15 13",
    "sg:postcode":"49523",
    "sg:province":"Zamora",
    "wof:name":"Granjas Alistanas S.l.",
    "wof:placetype":"venue"
},
  "geometry": {"coordinates":[-6.3472437859,41.777015686],"type":"Point"}
}