{
  "type": "Feature",
  "properties": {
    "iso:country":"ES",
    "sg:address":"Mayor, 4",
    "sg:city":"Ollogoyen",
    "sg:orig_category":"Iglesia Cat\u00d3lica",
    "sg:phone":"+34 948 39 50 59",
    "sg:postcode":"31241",
    "sg:province":"Navarra",
    "wof:name":"Parroquia De Villabona",
    "wof:placetype":"venue"
},
  "geometry": {"coordinates":[-2.0844779015,42.6449813843],"type":"Point"}
}