{
  "type": "Feature",
  "properties": {
    "addr:full":"Rua Policarpo Sanz, 27 Vigo Pontevedra 36202",
    "addr:housenumber":"27",
    "addr:postcode":"36202",
    "addr:street":"Rua Policarpo Sanz",
    "iso:country":"ES",
    "sg:address":"Rua Policarpo Sanz, 27",
    "sg:city":"Vigo",
    "sg:orig_category":"Bisuter\u00cda, Joyer\u00cda, Relojer\u00cda (al Por Menor)",
    "sg:phone":"+34 986 43 95 90",
    "sg:postcode":"36202",
    "sg:province":"Pontevedra",
    "wof:name":"Celada Campos Jose Carlos",
    "wof:placetype":"venue"
},
  "geometry": {"coordinates":[-8.7231664658,42.2376823425],"type":"Point"}
}