{
  "type": "Feature",
  "properties": {
    "addr:full":"Calle de Gil Vicente, 17 Coru\u00d1a La Coru\u00f1a 15011",
    "addr:housenumber":"17",
    "addr:postcode":"15011",
    "addr:street":"Calle De Gil Vicente;La Corun\u0303A",
    "iso:country":"ES",
    "sg:address":"Calle de Gil Vicente, 17",
    "sg:city":"Coru\u00d1a",
    "sg:orig_category":"Arreglo E Instalaci\u00d3n De Caf\u00c9s, Hoteles Y Restaurantes",
    "sg:phone":"+34 981 27 36 10",
    "sg:postcode":"15011",
    "sg:province":"La Coru\u00f1a",
    "wof:name":"Fagor Industrial S. Coop.",
    "wof:placetype":"venue"
},
  "geometry": {"coordinates":[-8.4205331802,43.3647537231],"type":"Point"}
}