{
  "type": "Feature",
  "properties": {
    "addr:full":"Plaz Regla, 9 Le\u00f3n Le\u00f3n 24003",
    "addr:housenumber":"9",
    "addr:postcode":"24003",
    "addr:street":"Plaz Regla;Leo\u0301N",
    "iso:country":"ES",
    "sg:address":"Plaz Regla, 9",
    "sg:city":"Le\u00f3n",
    "sg:orig_category":"Regalos, Souvenires (fabricaci\u00d3n, Al Por Mayor)",
    "sg:phone":"+34 987 24 95 21",
    "sg:postcode":"24003",
    "sg:province":"Le\u00f3n",
    "wof:name":"Maria Del Carmen Sanchez Ferreras Y Otros Cdad.",
    "wof:placetype":"venue"
},
  "geometry": {"coordinates":[-5.5671710968,42.5988540649],"type":"Point"}
}