{
  "type": "Feature",
  "properties": {
    "addr:full":"Calle de Colombia, 20 Madrid Madrid 28016",
    "addr:housenumber":"20",
    "addr:postcode":"madrid;28016",
    "addr:street":"Calle De Colombia",
    "iso:country":"ES",
    "sg:address":"Calle de Colombia, 20",
    "sg:city":"Madrid",
    "sg:orig_category":"Abogados",
    "sg:phone":"+34 913 50 43 96",
    "sg:postcode":"28016",
    "sg:province":"Madrid",
    "wof:name":"Estevez Coello Candido",
    "wof:placetype":"venue"
},
  "geometry": {"coordinates":[-3.6742112637,40.4570198059],"type":"Point"}
}