{
  "type": "Feature",
  "properties": {
    "addr:full":"Calle de Rabal (el), 4 Hellin Albacete 02400",
    "addr:housenumber":"4",
    "addr:postcode":"02400",
    "addr:street":"Calle De Rabal El",
    "iso:country":"ES",
    "sg:address":"Calle de Rabal (el), 4",
    "sg:city":"Hellin",
    "sg:orig_category":"Farmacias",
    "sg:phone":"+34 967 30 18 97",
    "sg:postcode":"02400",
    "sg:province":"Albacete",
    "wof:name":"Espinosa Fernandez Presentacion",
    "wof:placetype":"venue"
},
  "geometry": {"coordinates":[-1.7010070086,38.513092041],"type":"Point"}
}