{
  "type": "Feature",
  "properties": {
    "addr:full":"Cami Ral, 160 Mataro Barcelona 08301",
    "addr:housenumber":"160",
    "addr:postcode":"08301",
    "addr:street":"Ral",
    "iso:country":"ES",
    "sg:address":"Cami Ral, 160",
    "sg:city":"Mataro",
    "sg:orig_category":"Herboristas (al Por Menor)",
    "sg:phone":"+34 937 55 32 54",
    "sg:postcode":"08301",
    "sg:province":"Barcelona",
    "wof:name":"Dra. Naturaleza S.l.",
    "wof:placetype":"venue"
},
  "geometry": {"coordinates":[2.4511599541,41.5401115417],"type":"Point"}
}