{
  "type": "Feature",
  "properties": {
    "iso:country":"ES",
    "sg:address":"Avda Reina Victoria, 16",
    "sg:city":"Madrid",
    "sg:orig_category":"Zapatos (al Por Menor)",
    "sg:phone":"+34 915 33 49 50",
    "sg:postcode":"28003",
    "sg:province":"Madrid",
    "wof:name":"Garcia Fillol Maria Jose",
    "wof:placetype":"venue"
},
  "geometry": {"coordinates":[-3.7073020935,40.4472885132],"type":"Point"}
}