{
  "type": "Feature",
  "properties": {
    "addr:full":"Mi\u00f1o, 25 Lugo Lugo 27001",
    "addr:housenumber":"25",
    "addr:postcode":"27001",
    "addr:street":"Min\u0303O",
    "iso:country":"ES",
    "sg:address":"Mi\u00f1o, 25",
    "sg:city":"Lugo",
    "sg:orig_category":"Cervecer\u00cdas",
    "sg:phone":"+34 982 23 14 65",
    "sg:postcode":"27001",
    "sg:province":"Lugo",
    "wof:name":"Chain C.b.",
    "wof:placetype":"venue"
},
  "geometry": {"coordinates":[-7.5595550537,43.0101242065],"type":"Point"}
}