{
  "type": "Feature",
  "properties": {
    "addr:full":"Calle de Corregidor Ruiz De Pereda, 2 Malaga M\u00e1laga 29006",
    "addr:housenumber":"2",
    "addr:postcode":"29006",
    "addr:street":"Calle De Corregidor Ruiz De Pereda;Ma\u0301Laga",
    "iso:country":"ES",
    "sg:address":"Calle de Corregidor Ruiz De Pereda, 2",
    "sg:city":"Malaga",
    "sg:orig_category":"Papeler\u00cdas, Librer\u00cdas",
    "sg:phone":"+34 952 34 73 55",
    "sg:postcode":"29006",
    "sg:province":"M\u00e1laga",
    "wof:name":"Medina Fuentes Ginesa",
    "wof:placetype":"venue"
},
  "geometry": {"coordinates":[-4.447766304,36.7111740112],"type":"Point"}
}