{
  "type": "Feature",
  "properties": {
    "addr:full":"Trva Garbera, 1 Donostia-san Sebastian Guip\u00f9zcoa 20017",
    "addr:housenumber":"1",
    "addr:postcode":"20017",
    "addr:street":"Trva Garbera",
    "iso:country":"ES",
    "sg:address":"Trva Garbera, 1",
    "sg:city":"Donostia-san Sebastian",
    "sg:orig_category":"Bisuter\u00cda, Joyer\u00cda, Relojer\u00cda (al Por Menor)",
    "sg:phone":"+34 943 39 59 42",
    "sg:postcode":"20017",
    "sg:province":"Guip\u00f9zcoa",
    "sg:website":"www.orovivo.es",
    "wof:name":"Orpiel S.l.",
    "wof:placetype":"venue"
},
  "geometry": {"coordinates":[-1.9393490553,43.3108291626],"type":"Point"}
}