{
  "type": "Feature",
  "properties": {
    "addr:full":"Av Josep Fontcuberta, 145 Caldes Montbui Barcelona 08140",
    "addr:housenumber":"145",
    "addr:postcode":"08140",
    "addr:street":"Av Josep Fontcuberta;Montbui Barcelona",
    "iso:country":"ES",
    "sg:address":"Av Josep Fontcuberta, 145",
    "sg:city":"Caldes Montbui",
    "sg:orig_category":"Centros Empresariales",
    "sg:phone":"+34 938 65 46 25",
    "sg:postcode":"08140",
    "sg:province":"Barcelona",
    "wof:name":"Dsv Associats S.l.",
    "wof:placetype":"venue"
},
  "geometry": {"coordinates":[2.1705598831,41.6338806152],"type":"Point"}
}