{
  "type": "Feature",
  "properties": {
    "iso:country":"ES",
    "sg:address":"Calle de Capitanenea, 12",
    "sg:city":"Errenteria",
    "sg:orig_category":"Perfumer\u00cda (al Por Menor)",
    "sg:phone":"+34 943 52 71 14",
    "sg:postcode":"20100",
    "sg:province":"Guip\u00f9zcoa",
    "wof:name":"Sarasola Martiarena Aranzau",
    "wof:placetype":"venue"
},
  "geometry": {"coordinates":[-1.8989629745,43.3132095337],"type":"Point"}
}