{
  "type": "Feature",
  "properties": {
    "addr:full":"Carrer de Bonaplata, 5 Barcelona Barcelona 08034",
    "addr:housenumber":"5",
    "addr:postcode":"08034",
    "addr:street":"Carrer De Bonaplata",
    "iso:country":"ES",
    "sg:address":"Carrer de Bonaplata, 5",
    "sg:city":"Barcelona",
    "sg:orig_category":"Perfumer\u00cda (al Por Menor)",
    "sg:phone":"+34 932 03 12 21",
    "sg:postcode":"08034",
    "sg:province":"Barcelona",
    "wof:name":"Ponce Nieto Antonio",
    "wof:placetype":"venue"
},
  "geometry": {"coordinates":[2.1221709251,41.3972625732],"type":"Point"}
}