{
  "type": "Feature",
  "properties": {
    "addr:full":"Calle de Ramos Carrion, 4 Madrid Madrid 28002",
    "addr:housenumber":"4",
    "addr:postcode":"28002",
    "addr:street":"Calle De Ramos Carrion",
    "iso:country":"ES",
    "sg:address":"Calle de Ramos Carrion, 4",
    "sg:city":"Madrid",
    "sg:orig_category":"Inmobiliaria (agencias)",
    "sg:phone":"+34 915 10 30 31",
    "sg:postcode":"28002",
    "sg:province":"Madrid",
    "wof:name":"Last Homel Y Hause S.l.",
    "wof:placetype":"venue"
},
  "geometry": {"coordinates":[-3.6693642139,40.4468574524],"type":"Point"}
}