{
  "type": "Feature",
  "properties": {
    "addr:full":"Trav De Gracia, 243 Barcelona Barcelona 08024",
    "addr:housenumber":"243",
    "addr:postcode":"08024",
    "addr:street":"Trav De Gracia",
    "iso:country":"ES",
    "sg:address":"Trav De Gracia, 243",
    "sg:city":"Barcelona",
    "sg:orig_category":"Carnicer\u00cdas, Carnicer\u00cdas",
    "sg:phone":"+34 932 13 41 85",
    "sg:postcode":"08024",
    "sg:province":"Barcelona",
    "wof:name":"Subirats Vi\u00f1allonga Agustin",
    "wof:placetype":"venue"
},
  "geometry": {"coordinates":[2.1620221138,41.4041366577],"type":"Point"}
}