{
  "type": "Feature",
  "properties": {
    "iso:country":"ES",
    "sg:address":"Carrer de Governador Gonzalez, 28",
    "sg:city":"Tarragona",
    "sg:orig_category":"Centros De Coordinaci\u00d3n",
    "sg:phone":"+34 977 21 91 76",
    "sg:postcode":"43001",
    "sg:province":"Tarragona",
    "wof:name":"Gabin.gest.assumptes Jurididics Scp",
    "wof:placetype":"venue"
},
  "geometry": {"coordinates":[1.2502069473,41.1157417297],"type":"Point"}
}