{
  "type": "Feature",
  "properties": {
    "addr:full":"Calle de Juan Carlos I, 19 Arnedo La Rioja 26580",
    "addr:housenumber":"19",
    "addr:postcode":"26580",
    "addr:street":"Calle De Juan Carlos I;Rioja",
    "iso:country":"ES",
    "sg:address":"Calle de Juan Carlos I, 19",
    "sg:city":"Arnedo",
    "sg:orig_category":"Molduras, Junquillos, Listones Y Molduras Perforadas",
    "sg:phone":"+34 941 38 38 58",
    "sg:postcode":"26580",
    "sg:province":"La Rioja",
    "wof:name":"Barreno Espinosa Pedro",
    "wof:placetype":"venue"
},
  "geometry": {"coordinates":[-2.100440979,42.2267494202],"type":"Point"}
}