{
  "type": "Feature",
  "properties": {
    "addr:full":"Avda Mairena Del Aljarafe, 5 Bollullos Mitacion Sevilla 41110",
    "addr:housenumber":"5",
    "addr:postcode":"41110",
    "addr:street":"Avda Mairena Del Aljarafe",
    "iso:country":"ES",
    "sg:address":"Avda Mairena Del Aljarafe, 5",
    "sg:city":"Bollullos Mitacion",
    "sg:orig_category":"Perfumer\u00cda: Materias Primas Y Esencias",
    "sg:phone":"+34 955 77 65 63",
    "sg:postcode":"41110",
    "sg:province":"Sevilla",
    "wof:name":"Derivados Esenciales De Limon S.a.",
    "wof:placetype":"venue"
},
  "geometry": {"coordinates":[-6.1373138428,37.3355293274],"type":"Point"}
}