{
  "type": "Feature",
  "properties": {
    "iso:country":"ES",
    "sg:address":"Rua Picouto (do), 12",
    "sg:city":"Picouto",
    "sg:orig_category":"Molduras, Junquillos, Listones Y Molduras Perforadas",
    "sg:phone":"+34 988 40 50 57",
    "sg:postcode":"32900",
    "sg:province":"Ourense",
    "wof:name":"Araujo Cid Rosa",
    "wof:placetype":"venue"
},
  "geometry": {"coordinates":[-7.823495388,42.3110694885],"type":"Point"}
}