{
  "type": "Feature",
  "properties": {
    "iso:country":"ES",
    "sg:address":"Via Roma, 15",
    "sg:city":"Salou",
    "sg:orig_category":"Carnicer\u00cdas, Carnicer\u00cdas",
    "sg:phone":"+34 977 38 58 16",
    "sg:postcode":"43840",
    "sg:province":"Tarragona",
    "wof:name":"Sanchez Pont Fernando",
    "wof:placetype":"venue"
},
  "geometry": {"coordinates":[1.1337740421,41.0791015625],"type":"Point"}
}