{
  "type": "Feature",
  "properties": {
    "addr:full":"Carrer de Aribau, 146 Barcelona Barcelona 08036",
    "addr:housenumber":"146",
    "addr:postcode":"08036",
    "addr:street":"Carrer De Aribau",
    "iso:country":"ES",
    "sg:address":"Carrer de Aribau, 146",
    "sg:city":"Barcelona",
    "sg:orig_category":"Dietistas",
    "sg:phone":"+34 932 37 55 35",
    "sg:postcode":"08036",
    "sg:province":"Barcelona",
    "wof:name":"Mayteva Natura S.c.p.",
    "wof:placetype":"venue"
},
  "geometry": {"coordinates":[2.1548750401,41.3919715881],"type":"Point"}
}