{
  "type": "Feature",
  "properties": {
    "iso:country":"ES",
    "sg:address":"Av Roma, 141",
    "sg:city":"Barcelona",
    "sg:orig_category":"Agentes, Concesionarios Y Sucursales De Veh\u00cdculos",
    "sg:phone":"+34 934 53 89 85",
    "sg:postcode":"08011",
    "sg:province":"Barcelona",
    "wof:name":"Hermanos Perez Beltran S. A.",
    "wof:placetype":"venue"
},
  "geometry": {"coordinates":[2.1560940742,41.3863754272],"type":"Point"}
}