{
  "type": "Feature",
  "properties": {
    "iso:country":"ES",
    "sg:address":"Calle de Juan Ramon Jimenez, 45",
    "sg:city":"Palmas De Gran Canaria",
    "sg:orig_category":"Frutas, Legumbres Frescas Y Tempranas (al Por Menor)",
    "sg:phone":"+34 928 20 08 34",
    "sg:postcode":"35011",
    "sg:province":"Las Palmas",
    "wof:name":"Quintana Quintana Fernando",
    "wof:placetype":"venue"
},
  "geometry": {"coordinates":[-15.4353942871,28.1156101227],"type":"Point"}
}