{
  "type": "Feature",
  "properties": {
    "addr:full":"Avda Constitucion, S/n Campillos M\u00e1laga 29320",
    "addr:housenumber":"/ n",
    "addr:postcode":"29320",
    "addr:street":"Avda Constitucion S",
    "iso:country":"ES",
    "sg:address":"Avda Constitucion, S/n",
    "sg:city":"Campillos",
    "sg:orig_category":"Carnicer\u00cdas, Carnicer\u00cdas",
    "sg:phone":"+34 952 72 46 71",
    "sg:postcode":"29320",
    "sg:province":"M\u00e1laga",
    "wof:name":"Agropecuaria Del Sur S. Coop. Andaluza",
    "wof:placetype":"venue"
},
  "geometry": {"coordinates":[-4.8665018082,37.0478630066],"type":"Point"}
}