{
  "type": "Feature",
  "properties": {
    "addr:full":"Via Argentina, 4 Pollen\u00e7a Islas Baleares 07460",
    "addr:housenumber":"4",
    "addr:postcode":"07460",
    "addr:street":"Via Argentina;Islas",
    "iso:country":"ES",
    "sg:address":"Via Argentina, 4",
    "sg:city":"Pollen\u00e7a",
    "sg:orig_category":"Electricidad: Instaladores",
    "sg:phone":"+34 971 53 06 22",
    "sg:postcode":"07460",
    "sg:province":"Islas Baleares",
    "wof:name":"Canaves Cabanellas Martin",
    "wof:placetype":"venue"
},
  "geometry": {"coordinates":[3.0192050934,39.8766288757],"type":"Point"}
}