{
  "type": "Feature",
  "properties": {
    "iso:country":"ES",
    "sg:address":"Calle de Cruz Del Monaguillo, 1",
    "sg:city":"Sanlucar De Barrameda",
    "sg:orig_category":"Contenedores (mercanc\u00cdas)",
    "sg:phone":"+34 956 36 09 81",
    "sg:postcode":"11540",
    "sg:province":"C\u00e1diz",
    "wof:name":"Lorenzo Rodriguez Jose Angel",
    "wof:placetype":"venue"
},
  "geometry": {"coordinates":[-6.3498187065,36.7723617554],"type":"Point"}
}