{
  "type": "Feature",
  "properties": {
    "iso:country":"ES",
    "sg:address":"Carrer de Josep Ricart, 52",
    "sg:city":"Sant Feliu Llobregat",
    "sg:orig_category":"Art\u00cdculos De Regalo (al Por Menor)",
    "sg:phone":"+34 936 85 14 04",
    "sg:postcode":"08980",
    "sg:province":"Barcelona",
    "sg:website":"www.casi-todo.com",
    "wof:name":"Garcia Horta Francisco",
    "wof:placetype":"venue"
},
  "geometry": {"coordinates":[2.0516450405,41.3830718994],"type":"Point"}
}