{
  "type": "Feature",
  "properties": {
    "iso:country":"ES",
    "sg:address":"Calle de Hermanos Gomez, 37",
    "sg:city":"Madrid",
    "sg:orig_category":"Promotores Constructores",
    "sg:phone":"+34 913 68 25 20",
    "sg:postcode":"28017",
    "sg:province":"Madrid",
    "wof:name":"Comunidad Propietarios Hermanos Gomez 37",
    "wof:placetype":"venue"
},
  "geometry": {"coordinates":[-3.649668932,40.4305725098],"type":"Point"}
}