{
  "type": "Feature",
  "properties": {
    "addr:full":"Calle de Misericordia, 46 Fuente Cantos Badajoz 06240",
    "addr:housenumber":"46",
    "addr:postcode":"06240",
    "addr:street":"Calle De Misericordia",
    "iso:country":"ES",
    "sg:address":"Calle de Misericordia, 46",
    "sg:city":"Fuente Cantos",
    "sg:orig_category":"Peluqueros: De Se\u00d1oras",
    "sg:phone":"+34 924 50 03 58",
    "sg:postcode":"06240",
    "sg:province":"Badajoz",
    "wof:name":"Mo\u00f1ino Nu\u00f1ez Maria Isabel",
    "wof:placetype":"venue"
},
  "geometry": {"coordinates":[-6.3078255653,38.2456321716],"type":"Point"}
}