{
  "type": "Feature",
  "properties": {
    "addr:full":"Pg Bonanova, 5 Barcelona Barcelona 08022",
    "addr:housenumber":"5",
    "addr:postcode":"08022",
    "addr:street":"Pg Bonanova",
    "iso:country":"ES",
    "sg:address":"Pg Bonanova, 5",
    "sg:city":"Barcelona",
    "sg:orig_category":"Papeler\u00cdas, Librer\u00cdas",
    "sg:phone":"+34 934 17 76 68",
    "sg:postcode":"08022",
    "sg:province":"Barcelona",
    "wof:name":"Maestre Menendez Maria Victoria",
    "wof:placetype":"venue"
},
  "geometry": {"coordinates":[2.1328549385,41.4062004089],"type":"Point"}
}