{
  "type": "Feature",
  "properties": {
    "iso:country":"ES",
    "sg:address":"Calle de Hellin, 25",
    "sg:city":"Albacete",
    "sg:orig_category":"Restaurantes",
    "sg:phone":"+34 967 50 59 97",
    "sg:postcode":"02002",
    "sg:province":"Albacete",
    "wof:name":"Hosteleria Lozano S.a.l.",
    "wof:placetype":"venue"
},
  "geometry": {"coordinates":[-1.8533289433,38.9834785461],"type":"Point"}
}