{
  "type": "Feature",
  "properties": {
    "iso:country":"ES",
    "sg:address":"Calle de Cuatro Calles, 20",
    "sg:city":"Tembleque",
    "sg:classifiers":[
        {
            "category":"Autos & Motor Vehicles",
            "subcategory":"Automobile Sales",
            "type":"Retail Goods"
        }
    ],
    "sg:phone":"+34 925 14 53 34",
    "sg:postcode":"45780",
    "sg:province":"Toledo",
    "wof:name":"Autoescula Tembleque S.l",
    "wof:placetype":"venue"
},
  "geometry": {"coordinates":[-3.5035789013,39.6947860718],"type":"Point"}
}