{
  "type": "Feature",
  "properties": {
    "iso:country":"ES",
    "sg:address":"Carr Ponent, 168",
    "sg:city":"Badalona",
    "sg:orig_category":"Maquinaria Para Industrias Diversas",
    "sg:phone":"+34 933 83 03 53",
    "sg:postcode":"08912",
    "sg:province":"Barcelona",
    "wof:name":"Papmatic Sl",
    "wof:placetype":"venue"
},
  "geometry": {"coordinates":[2.2329630852,41.4429206848],"type":"Point"}
}