{
  "type": "Feature",
  "properties": {
    "iso:country":"ES",
    "sg:address":"Plaz Carballo, 16",
    "sg:city":"Madrid",
    "sg:orig_category":"Tintorer\u00cdas, Limpieza En Seco",
    "sg:phone":"+34 917 39 11 44",
    "sg:postcode":"28029",
    "sg:province":"Madrid",
    "wof:name":"Vego Isla Angel",
    "wof:placetype":"venue"
},
  "geometry": {"coordinates":[-3.7047579288,40.4776268005],"type":"Point"}
}