{
  "type": "Feature",
  "properties": {
    "iso:country":"ES",
    "sg:address":"Anunciata, 35",
    "sg:city":"Trobajo Camino",
    "sg:classifiers":[
        {
            "category":"Communications",
            "type":"Services"
        }
    ],
    "sg:phone":"+34 987 27 32 52",
    "sg:postcode":"24010",
    "sg:province":"Le\u00f3n",
    "sg:tags":[
        "televisiones",
        "y",
        "radio"
    ],
    "wof:name":"Auna Telecomunicaciones S.a.u.",
    "wof:placetype":"venue"
},
  "geometry": {"coordinates":[-5.5920529366,42.6019554138],"type":"Point"}
}