{
  "type": "Feature",
  "properties": {
    "iso:country":"ES",
    "sg:address":"Calle de Real, S/n",
    "sg:city":"Castrillo De La Ribera",
    "sg:orig_category":"Empresarios",
    "sg:phone":"+34 987 68 00 67",
    "sg:postcode":"24199",
    "sg:province":"Le\u00f3n",
    "wof:name":"Asfaltos Naturales De Campezo S.a.",
    "wof:placetype":"venue"
},
  "geometry": {"coordinates":[-5.552397728,42.5292472839],"type":"Point"}
}