{
  "type": "Feature",
  "properties": {
    "addr:full":"Rua Canovas Del Castillo, 12 Vigo Pontevedra 36202",
    "addr:housenumber":"12",
    "addr:postcode":"36202",
    "addr:street":"Rua Canovas Del Castillo",
    "iso:country":"ES",
    "sg:address":"Rua Canovas Del Castillo, 12",
    "sg:city":"Vigo",
    "sg:orig_category":"Pescader\u00cdas (al Por Menor)",
    "sg:phone":"+34 986 22 31 07",
    "sg:postcode":"36202",
    "sg:province":"Pontevedra",
    "wof:name":"Faro Silleiro S.l.",
    "wof:placetype":"venue"
},
  "geometry": {"coordinates":[-8.7271766663,42.2398986816],"type":"Point"}
}