{
  "type": "Feature",
  "properties": {
    "iso:country":"ES",
    "sg:address":"Calle de San Deogracias, 3",
    "sg:city":"Madrid",
    "sg:orig_category":"Asesor\u00cda Fiscal Y Jur\u00cddica",
    "sg:phone":"+34 915 08 68 61",
    "sg:postcode":"28044",
    "sg:province":"Madrid",
    "wof:name":"Perales Espinosa Jaime",
    "wof:placetype":"venue"
},
  "geometry": {"coordinates":[-3.759816885,40.3717460632],"type":"Point"}
}