{
  "type": "Feature",
  "properties": {
    "addr:full":"Avda Pablo Ruiz Picasso, 10 Alora M\u00e1laga 29500",
    "addr:housenumber":"10",
    "addr:postcode":"29500",
    "addr:street":"Avda Pablo Ruiz Picasso;Ma\u0301Laga",
    "iso:country":"ES",
    "sg:address":"Avda Pablo Ruiz Picasso, 10",
    "sg:city":"Alora",
    "sg:orig_category":"Imprenta",
    "sg:phone":"+34 952 49 88 28",
    "sg:postcode":"29500",
    "sg:province":"M\u00e1laga",
    "wof:name":"Imprenta Castillo S.c.",
    "wof:placetype":"venue"
},
  "geometry": {"coordinates":[-4.7038178444,36.830368042],"type":"Point"}
}