{
  "type": "Feature",
  "properties": {
    "addr:full":"Avda Cerro Del Rubal, 5 Parla Madrid 28980",
    "addr:housenumber":"5",
    "addr:postcode":"28980",
    "addr:street":"Avda Cerro Del Rubal",
    "iso:country":"ES",
    "sg:address":"Avda Cerro Del Rubal, 5",
    "sg:city":"Parla",
    "sg:orig_category":"Inform\u00c1tica (estudios, Servicios, Asesor\u00cda, Formaci\u00d3n)",
    "sg:phone":"+34 916 98 93 15",
    "sg:postcode":"28980",
    "sg:province":"Madrid",
    "sg:website":"www.jfformacion.com",
    "wof:name":"Tecnydis Servicios De Montaje Y Decoracion S.a.",
    "wof:placetype":"venue"
},
  "geometry": {"coordinates":[-3.7734539509,40.237449646],"type":"Point"}
}