{
  "type": "Feature",
  "properties": {
    "iso:country":"ES",
    "sg:address":"Calle de Santa Teresa, 8",
    "sg:city":"San Nicolas",
    "sg:orig_category":"Asesor\u00cda Fiscal Y Jur\u00cddica",
    "sg:phone":"+34 968 28 43 98",
    "sg:postcode":"30005",
    "sg:province":"Murcia",
    "wof:name":"Asesorias Torrano S.l.",
    "wof:placetype":"venue"
},
  "geometry": {"coordinates":[-1.7970391512,37.9042510986],"type":"Point"}
}