{
  "type": "Feature",
  "properties": {
    "iso:country":"ES",
    "sg:address":"Calle de Somontin, 100",
    "sg:city":"Madrid",
    "sg:orig_category":"Artes Gr\u00c1ficas, Artes Pl\u00c1sticas (curso)",
    "sg:phone":"+34 913 83 07 49",
    "sg:postcode":"28033",
    "sg:province":"Madrid",
    "wof:name":"Entadent S.l.",
    "wof:placetype":"venue"
},
  "geometry": {"coordinates":[-3.6587688923,40.4785957336],"type":"Point"}
}