{
  "type": "Feature",
  "properties": {
    "addr:full":"Avda Sagunto (de), 68 Teruel Teruel 44002",
    "addr:housenumber":"68",
    "addr:postcode":"44002",
    "addr:street":"Avda Sagunto De",
    "iso:country":"ES",
    "sg:address":"Avda Sagunto (de), 68",
    "sg:city":"Teruel",
    "sg:orig_category":"Semiller\u00cdas",
    "sg:phone":"+34 978 60 98 98",
    "sg:postcode":"44002",
    "sg:province":"Teruel",
    "wof:name":"Conejos Edo Andres",
    "wof:placetype":"venue"
},
  "geometry": {"coordinates":[-1.0992809534,40.3329658508],"type":"Point"}
}