{
  "type": "Feature",
  "properties": {
    "iso:country":"ES",
    "sg:address":"Carrer de Creu Roja, 29",
    "sg:city":"Hospitalet Llobregat",
    "sg:orig_category":"Chapister\u00cda",
    "sg:phone":"+34 934 49 19 78",
    "sg:postcode":"08904",
    "sg:province":"Barcelona",
    "wof:name":"Chicote Herrero Antonio",
    "wof:placetype":"venue"
},
  "geometry": {"coordinates":[2.1159129143,41.3745918274],"type":"Point"}
}