{
  "type": "Feature",
  "properties": {
    "iso:country":"ES",
    "sg:address":"Pg. Radio Mora Ebre, 2",
    "sg:city":"Mora Ebre",
    "sg:orig_category":"Contenedores (mercanc\u00cdas)",
    "sg:phone":"+34 977 40 00 72",
    "sg:postcode":"43740",
    "sg:province":"Tarragona",
    "wof:name":"Abella Gomez Elena",
    "wof:placetype":"venue"
},
  "geometry": {"coordinates":[0.63964,41.091553],"type":"Point"}
}