{
  "type": "Feature",
  "properties": {
    "addr:full":"Calle de Alta, S/n Cortes De Baza Granada 18814",
    "addr:housenumber":"s / n",
    "addr:postcode":"18814",
    "addr:street":"Calle De Alta",
    "iso:country":"ES",
    "sg:address":"Calle de Alta, S/n",
    "sg:city":"Cortes De Baza",
    "sg:orig_category":"Aguas (distribuci\u00d3n, Servicios)",
    "sg:phone":"+34 958 73 65 01",
    "sg:postcode":"18814",
    "sg:province":"Granada",
    "wof:name":"Gestion Y Tecnicas Del Agua S.a.",
    "wof:placetype":"venue"
},
  "geometry": {"coordinates":[-2.7670149803,37.6553573608],"type":"Point"}
}