{
  "type": "Feature",
  "properties": {
    "addr:full":"Calle de Pintor Rosales (del), 9 Alcobendas Madrid 28100",
    "addr:postcode":"28100",
    "addr:street":"Calle De Pintor Rosales Del;Alcobendas",
    "iso:country":"ES",
    "sg:address":"Calle de Pintor Rosales (del), 9",
    "sg:city":"Alcobendas",
    "sg:orig_category":"Muebles, Minoristas",
    "sg:phone":"+34 916 61 27 45",
    "sg:postcode":"28100",
    "sg:province":"Madrid",
    "wof:name":"Instalaciones Hergusa S.l.",
    "wof:placetype":"venue"
},
  "geometry": {"coordinates":[-3.6395668983,40.5380783081],"type":"Point"}
}