{
  "type": "Feature",
  "properties": {
    "addr:full":"Calle de Rio Saja, 14 S. Vicente Barquera Cantabria 39540",
    "addr:housenumber":"14",
    "addr:postcode":"39540",
    "addr:street":"Calle De Rio Saja;S. Vicente",
    "iso:country":"ES",
    "sg:address":"Calle de Rio Saja, 14",
    "sg:city":"S. Vicente Barquera",
    "sg:orig_category":"Inmobiliaria (agencias)",
    "sg:phone":"+34 942 71 16 57",
    "sg:postcode":"39540",
    "sg:province":"Cantabria",
    "wof:name":"Promociones Cuesta Caballo S.l.",
    "wof:placetype":"venue"
},
  "geometry": {"coordinates":[-4.3965239525,43.3895874023],"type":"Point"}
}