{
  "type": "Feature",
  "properties": {
    "addr:full":"Vega De Porrillas, S/n Alcolea C\u00f3rdoba 14610",
    "addr:housenumber":"s / n",
    "addr:postcode":"14610",
    "addr:street":"Vega",
    "iso:country":"ES",
    "sg:address":"Vega De Porrillas, S/n",
    "sg:city":"Alcolea",
    "sg:orig_category":"Maquinaria Para Industrias Diversas",
    "sg:phone":"+34 957 32 03 62",
    "sg:postcode":"14610",
    "sg:province":"C\u00f3rdoba",
    "wof:name":"Guijarro Granados Juan Manuel",
    "wof:placetype":"venue"
},
  "geometry": {"coordinates":[-4.6729812622,37.932182312],"type":"Point"}
}