{
  "type": "Feature",
  "properties": {
    "addr:full":"Calle de Campanero, 6 Churriana M\u00e1laga 29140",
    "addr:housenumber":"6",
    "addr:postcode":"29140",
    "addr:street":"Calle De Campanero",
    "iso:country":"ES",
    "sg:address":"Calle de Campanero, 6",
    "sg:city":"Churriana",
    "sg:orig_category":"Arquitectos",
    "sg:phone":"+34 952 43 55 61",
    "sg:postcode":"29140",
    "sg:province":"M\u00e1laga",
    "wof:name":"Guerrero Cantizano Francisco Javier",
    "wof:placetype":"venue"
},
  "geometry": {"coordinates":[-4.5132160187,36.6626091003],"type":"Point"}
}