{
  "type": "Feature",
  "properties": {
    "addr:full":"Carr Carles V, 28 Eivissa Islas Baleares 07800",
    "addr:housenumber":"28",
    "addr:postcode":"07800",
    "addr:street":"Carr Carles V",
    "iso:country":"ES",
    "sg:address":"Carr Carles V, 28",
    "sg:city":"Eivissa",
    "sg:orig_category":"Asesor\u00cda Fiscal Y Jur\u00cddica",
    "sg:phone":"+34 971 31 57 05",
    "sg:postcode":"07800",
    "sg:province":"Islas Baleares",
    "wof:name":"Mayans Asenjo Juan",
    "wof:placetype":"venue"
},
  "geometry": {"coordinates":[1.4322140217,38.9111213684],"type":"Point"}
}