{
  "type": "Feature",
  "properties": {
    "iso:country":"ES",
    "sg:address":"Calle de Carrera, 43",
    "sg:city":"Osuna",
    "sg:orig_category":"Pr\u00c9stamos Personales E Hipotecarios",
    "sg:phone":"+34 954 81 01 67",
    "sg:postcode":"41640",
    "sg:province":"Sevilla",
    "wof:name":"Mugica Alcorta Maria Elena",
    "wof:placetype":"venue"
},
  "geometry": {"coordinates":[-5.1037979126,37.2385902405],"type":"Point"}
}