{
  "type": "Feature",
  "properties": {
    "iso:country":"ES",
    "sg:address":"Guillermo Reina, 3",
    "sg:city":"Huercal-overa",
    "sg:orig_category":"\u00d3pticos Optometristas (al Por Menor)",
    "sg:phone":"+34 950 47 15 30",
    "sg:postcode":"04600",
    "sg:province":"Almer\u00eda",
    "wof:name":"Optica Albatros S.l",
    "wof:placetype":"venue"
},
  "geometry": {"coordinates":[-1.9433549643,37.3898963928],"type":"Point"}
}