{
  "type": "Feature",
  "properties": {
    "addr:full":"Calle de Nicolas Copernico, 1 Lomo De La Herradura Las Palmas 35200",
    "addr:housenumber":"1",
    "addr:postcode":"35200",
    "addr:street":"Calle De Nicolas Copernico;Herradura Las",
    "iso:country":"ES",
    "sg:address":"Calle de Nicolas Copernico, 1",
    "sg:city":"Lomo De La Herradura",
    "sg:orig_category":"Fabricaci\u00d3n De Material Y Sistemas De Se\u00d1alizaci\u00d3n De Carreteras, Urbanos Y De Obras",
    "sg:phone":"+34 928 69 80 61",
    "sg:postcode":"35200",
    "sg:province":"Las Palmas",
    "wof:name":"Se\u00f1alizacion Y Balizamientos 7 Islas S.l",
    "wof:placetype":"venue"
},
  "geometry": {"coordinates":[-15.4144220352,28.0029888153],"type":"Point"}
}