{
  "type": "Feature",
  "properties": {
    "addr:full":"Calle de Via Complutense, 108 Alcala Henares Madrid 28805",
    "addr:housenumber":"108",
    "addr:postcode":"28805",
    "addr:street":"Calle De Via Complutense",
    "iso:country":"ES",
    "sg:address":"Calle de Via Complutense, 108",
    "sg:city":"Alcala Henares",
    "sg:orig_category":"Agentes, Concesionarios Y Sucursales De Veh\u00cdculos",
    "sg:phone":"+34 918 82 66 58",
    "sg:postcode":"28805",
    "sg:province":"Madrid",
    "sg:website":"www.deysa.com",
    "wof:name":"Dealer Y Servicio Postventa S.a.",
    "wof:placetype":"venue"
},
  "geometry": {"coordinates":[-3.35283494,40.490562439],"type":"Point"}
}