{
  "type": "Feature",
  "properties": {
    "addr:full":"Carrer de Laguna (la), 1 Sant Vicen\u00c7 Dels Horts Barcelona 08620",
    "addr:postcode":"08620",
    "addr:street":"Carrer De Laguna La 1 Sant Vicenc\u0327 Dels Horts Barcelona",
    "iso:country":"ES",
    "sg:address":"Carrer de Laguna (la), 1",
    "sg:city":"Sant Vicen\u00c7 Dels Horts",
    "sg:orig_category":"Asociaciones, Organismos Culturales Y Socioeducativos",
    "sg:phone":"+34 936 56 63 58",
    "sg:postcode":"08620",
    "sg:province":"Barcelona",
    "wof:name":"Centro De Amigos",
    "wof:placetype":"venue"
},
  "geometry": {"coordinates":[2.0016739368,41.3894042969],"type":"Point"}
}