{
  "type": "Feature",
  "properties": {
    "addr:full":"Av Alameda (l'), 43 Alcoi Alicante 03803",
    "addr:housenumber":"43",
    "addr:postcode":"03803",
    "addr:street":"Av Alameda L '",
    "iso:country":"ES",
    "sg:address":"Av Alameda (l'), 43",
    "sg:city":"Alcoi",
    "sg:orig_category":"Ingeniero",
    "sg:phone":"+34 965 33 56 76",
    "sg:postcode":"03803",
    "sg:province":"Alicante",
    "wof:name":"Miro Cloquell Francisco",
    "wof:placetype":"venue"
},
  "geometry": {"coordinates":[-0.4780620039,38.7015380859],"type":"Point"}
}