{
  "type": "Feature",
  "properties": {
    "iso:country":"ES",
    "sg:address":"Polig Ind La Pachares, S/n",
    "sg:city":"Huetor-tajar",
    "sg:orig_category":"Negocio De Materiales De Construcci\u00d3n",
    "sg:phone":"+34 958 33 25 76",
    "sg:postcode":"18360",
    "sg:province":"Granada",
    "wof:name":"Materiales De Construccion Tobal S.l.",
    "wof:placetype":"venue"
},
  "geometry": {"coordinates":[-4.0706038475,37.2185134888],"type":"Point"}
}