{
  "type": "Feature",
  "properties": {
    "addr:full":"Carrer de Sant Rafel (de), 3 Montbrio Del Camp Tarragona 43340",
    "addr:postcode":"43340",
    "addr:street":"Carrer De Sant Rafel De 3",
    "iso:country":"ES",
    "sg:address":"Carrer de Sant Rafel (de), 3",
    "sg:city":"Montbrio Del Camp",
    "sg:orig_category":"Inversiones",
    "sg:phone":"+34 977 83 30 08",
    "sg:postcode":"43340",
    "sg:province":"Tarragona",
    "wof:name":"Inversions Campassos De Montbrio, S.l.",
    "wof:placetype":"venue"
},
  "geometry": {"coordinates":[1.0012999773,41.1213111877],"type":"Point"}
}