{
  "type": "Feature",
  "properties": {
    "addr:full":"Calle de Rodriguez Marin, 30 Madrid Madrid 28002",
    "addr:housenumber":"30",
    "addr:postcode":"madrid;28002",
    "addr:street":"Calle De Rodriguez Marin",
    "iso:country":"ES",
    "sg:address":"Calle de Rodriguez Marin, 30",
    "sg:city":"Madrid",
    "sg:orig_category":"Internados & Ense\u00d1anza Privada",
    "sg:phone":"+34 915 63 52 50",
    "sg:postcode":"28002",
    "sg:province":"Madrid",
    "wof:name":"Union Chretienne De Saint Chaumond",
    "wof:placetype":"venue"
},
  "geometry": {"coordinates":[-3.6810874939,40.4459457397],"type":"Point"}
}