{
  "type": "Feature",
  "properties": {
    "addr:full":"Calle de Alcala De La Selva, 1 Zaragoza Zaragoza 50017",
    "addr:housenumber":"1",
    "addr:postcode":"50017",
    "addr:street":"Calle De Alcala De La Selva",
    "iso:country":"ES",
    "sg:address":"Calle de Alcala De La Selva, 1",
    "sg:city":"Zaragoza",
    "sg:orig_category":"M\u00c9dicos: Evaluaci\u00d3n Y Tratamiento Del Dolor",
    "sg:phone":"+34 976 34 64 91",
    "sg:postcode":"50017",
    "sg:province":"Zaragoza",
    "wof:name":"Tediax S.a.",
    "wof:placetype":"venue"
},
  "geometry": {"coordinates":[-0.9136642218,41.645904541],"type":"Point"}
}