{
  "type": "Feature",
  "properties": {
    "iso:country":"ES",
    "sg:address":"Carrer de Calabria, 204",
    "sg:city":"Barcelona",
    "sg:orig_category":"Inmobiliaria (agencias)",
    "sg:phone":"+34 934 10 70 18",
    "sg:postcode":"08029",
    "sg:province":"Barcelona",
    "wof:name":"Llars Calabria S.l.",
    "wof:placetype":"venue"
},
  "geometry": {"coordinates":[2.1488060951,41.3845863342],"type":"Point"}
}