{
  "type": "Feature",
  "properties": {
    "addr:full":"Calle de Ca\u00d1as (las), 71 Logro\u00f1o La Rioja 26006",
    "addr:housenumber":"71",
    "addr:postcode":"26006",
    "addr:street":"Calle De Can\u0303As Las;Rioja",
    "iso:country":"ES",
    "sg:address":"Calle de Ca\u00d1as (las), 71",
    "sg:city":"Logro\u00f1o",
    "sg:orig_category":"Zapatos: Material, Suministros, Accesorios (fabricaci\u00d3n, Al Por Mayor)",
    "sg:phone":"+34 941 24 65 23",
    "sg:postcode":"26006",
    "sg:province":"La Rioja",
    "wof:name":"Manufacturas Rivera S.a.",
    "wof:placetype":"venue"
},
  "geometry": {"coordinates":[-2.4126567841,42.4782714844],"type":"Point"}
}