{
  "type": "Feature",
  "properties": {
    "addr:full":"Calle de Stendhal, 1 Malaga M\u00e1laga 29006",
    "addr:housenumber":"1",
    "addr:postcode":"29006",
    "addr:street":"Calle De Stendhal;Ma\u0301Laga",
    "iso:country":"ES",
    "sg:address":"Calle de Stendhal, 1",
    "sg:city":"Malaga",
    "sg:orig_category":"Papeler\u00cdas, Librer\u00cdas",
    "sg:phone":"+34 952 34 08 04",
    "sg:postcode":"29006",
    "sg:province":"M\u00e1laga",
    "wof:name":"Poyato Poyato Jose Agustin",
    "wof:placetype":"venue"
},
  "geometry": {"coordinates":[-4.4546408653,36.7171669006],"type":"Point"}
}