{
  "type": "Feature",
  "properties": {
    "iso:country":"ES",
    "sg:address":"Calle de Velazquez, 14",
    "sg:city":"Madrid",
    "sg:orig_category":"Financiaci\u00d3n Y Cr\u00c9ditos",
    "sg:phone":"+34 914 31 32 71",
    "sg:postcode":"28001",
    "sg:province":"Madrid",
    "wof:name":"Gb Global Corporate Finanace S.a.",
    "wof:placetype":"venue"
},
  "geometry": {"coordinates":[-3.6841371059,40.4228935242],"type":"Point"}
}