{
  "type": "Feature",
  "properties": {
    "iso:country":"ES",
    "sg:address":"Calle de Guabairo, 32",
    "sg:city":"Madrid",
    "sg:orig_category":"Fotograf\u00cda Publicitaria E Industrial",
    "sg:phone":"+34 914 61 37 47",
    "sg:postcode":"28047",
    "sg:province":"Madrid",
    "wof:name":"Yamazawa  Nobuyuki",
    "wof:placetype":"venue"
},
  "geometry": {"coordinates":[-3.7459712029,40.3854141235],"type":"Point"}
}