{
  "type": "Feature",
  "properties": {
    "iso:country":"ES",
    "sg:address":"Avda Carabanchel Alto, 23",
    "sg:city":"Madrid",
    "sg:orig_category":"Farmacias",
    "sg:phone":"+34 915 08 03 58",
    "sg:postcode":"28044",
    "sg:province":"Madrid",
    "wof:name":"Solis Zu\u00f1iga Angela Maria De",
    "wof:placetype":"venue"
},
  "geometry": {"coordinates":[-3.7530009747,40.3699417114],"type":"Point"}
}