{
  "type": "Feature",
  "properties": {
    "addr:full":"Avda Fama, 26 Paz Murcia 30006",
    "addr:housenumber":"26",
    "addr:postcode":"30006",
    "addr:street":"Avda Fama",
    "iso:country":"ES",
    "sg:address":"Avda Fama, 26",
    "sg:city":"Paz",
    "sg:orig_category":"Farmacias",
    "sg:phone":"+34 968 25 91 02",
    "sg:postcode":"30006",
    "sg:province":"Murcia",
    "wof:name":"Aleman Aleman Maria Jose",
    "wof:placetype":"venue"
},
  "geometry": {"coordinates":[-1.1298867464,37.9834747314],"type":"Point"}
}