{
  "type": "Feature",
  "properties": {
    "iso:country":"ES",
    "sg:address":"Fco. Y Jacinto Alcantara, S/n",
    "sg:city":"La Alberca",
    "sg:orig_category":"M\u00c9dicos: Psicopedagogos",
    "sg:phone":"+34 923 41 53 98",
    "sg:postcode":"37624",
    "sg:province":"Salamanca",
    "wof:name":"Equipo De Orientacion Psicopedagogica Sierra De Francia",
    "wof:placetype":"venue"
},
  "geometry": {"coordinates":[-6.1116552353,40.4892883301],"type":"Point"}
}