{
  "type": "Feature",
  "properties": {
    "iso:country":"ES",
    "sg:address":"Calle de Leon, 26",
    "sg:city":"Ceuti",
    "sg:orig_category":"Electrodom\u00c9sticos (al Por Menor)",
    "sg:phone":"+34 968 69 33 50",
    "sg:postcode":"30562",
    "sg:province":"Murcia",
    "wof:name":"Arce Asistencia S.l.",
    "wof:placetype":"venue"
},
  "geometry": {"coordinates":[-1.2735142708,38.074962616],"type":"Point"}
}