{
  "type": "Feature",
  "properties": {
    "addr:full":"Carrer de Anselm Clave, 3 Mollet Valles Barcelona 08100",
    "addr:housenumber":"3",
    "addr:postcode":"08100",
    "addr:street":"Carrer De Anselm Clave",
    "iso:country":"ES",
    "sg:address":"Carrer de Anselm Clave, 3",
    "sg:city":"Mollet Valles",
    "sg:orig_category":"Droguer\u00cdas (al Por Menor)",
    "sg:phone":"+34 935 70 80 49",
    "sg:postcode":"08100",
    "sg:province":"Barcelona",
    "wof:name":"El Punt Del Peix S.l.",
    "wof:placetype":"venue"
},
  "geometry": {"coordinates":[2.2138199806,41.5380249023],"type":"Point"}
}