{
  "type": "Feature",
  "properties": {
    "iso:country":"ES",
    "sg:address":"Calle de La Albericia, 20",
    "sg:city":"Madrid",
    "sg:orig_category":"Cerrajer\u00cda, Ferrallista",
    "sg:phone":"+34 913 06 34 86",
    "sg:postcode":"28037",
    "sg:province":"Madrid",
    "wof:name":"Hernanz Herranz Jose",
    "wof:placetype":"venue"
},
  "geometry": {"coordinates":[-3.6143059731,40.4235267639],"type":"Point"}
}