{
  "type": "Feature",
  "properties": {
    "addr:full":"Rua Antonio Vazquez Mouzo, 45 Vimianzo La Coru\u00f1a 15120",
    "addr:housenumber":"45",
    "addr:postcode":"15120",
    "addr:street":"Rua Antonio;Mouzo;La Corun\u0303A",
    "iso:country":"ES",
    "sg:address":"Rua Antonio Vazquez Mouzo, 45",
    "sg:city":"Vimianzo",
    "sg:orig_category":"Caf\u00c9s, Bares, Cervecer\u00cdas",
    "sg:phone":"+34 981 71 71 18",
    "sg:postcode":"15120",
    "sg:province":"La Coru\u00f1a",
    "wof:name":"Galtelcom",
    "wof:placetype":"venue"
},
  "geometry": {"coordinates":[-9.0348310471,43.1090965271],"type":"Point"}
}