{
  "type": "Feature",
  "properties": {
    "iso:country":"ES",
    "sg:address":"Calle de Gallo, 13",
    "sg:city":"Valladolid",
    "sg:orig_category":"Peluquer\u00cdas, Peluquer\u00cda Mixta",
    "sg:phone":"+34 983 20 91 67",
    "sg:postcode":"47012",
    "sg:province":"Valladolid",
    "wof:name":"Andres Moyano Bego\u00f1a",
    "wof:placetype":"venue"
},
  "geometry": {"coordinates":[-4.7085251808,41.6466331482],"type":"Point"}
}