{
  "type": "Feature",
  "properties": {
    "addr:full":"Calle de Valdelarco, 10 Sevilla Sevilla 41008",
    "addr:housenumber":"10",
    "addr:postcode":"41008",
    "addr:street":"Calle De Valdelarco",
    "iso:country":"ES",
    "sg:address":"Calle de Valdelarco, 10",
    "sg:city":"Sevilla",
    "sg:orig_category":"Caf\u00c9s, Bares, Cervecer\u00cdas",
    "sg:phone":"+34 954 36 12 68",
    "sg:postcode":"41008",
    "sg:province":"Sevilla",
    "wof:name":"Vargas Mendez E Hijos S.l.",
    "wof:placetype":"venue"
},
  "geometry": {"coordinates":[-5.9767298698,37.4091148376],"type":"Point"}
}