{
  "type": "Feature",
  "properties": {
    "iso:country":"ES",
    "sg:address":"Calle de Gran Capitan, 3",
    "sg:city":"Puertollano",
    "sg:orig_category":"Perfumer\u00cda (al Por Menor)",
    "sg:phone":"+34 926 41 11 95",
    "sg:postcode":"13500",
    "sg:province":"Ciudad Real",
    "sg:website":"www.bodybell.com",
    "wof:name":"Iberica De Drogueria Y Perfumeria S.a.",
    "wof:placetype":"venue"
},
  "geometry": {"coordinates":[-4.1051092148,38.6824188232],"type":"Point"}
}