{
  "type": "Feature",
  "properties": {
    "iso:country":"ES",
    "sg:address":"Calle de San Sebastian, 2",
    "sg:city":"Mijas",
    "sg:orig_category":"Caf\u00c9s, Bares, Cervecer\u00cdas",
    "sg:phone":"+34 952 48 50 46",
    "sg:postcode":"29650",
    "sg:province":"M\u00e1laga",
    "wof:name":"Mu\u00f1oz Ramos Jose Antonio",
    "wof:placetype":"venue"
},
  "geometry": {"coordinates":[-4.6387171745,36.5952911377],"type":"Point"}
}