{
  "type": "Feature",
  "properties": {
    "addr:full":"Pase Martin J.iraola Etorbidea, 1 San Blas Guip\u00f9zcoa 20400",
    "addr:housenumber":"1",
    "addr:postcode":"20400",
    "addr:street":"J.Iraola Etorbidea",
    "iso:country":"ES",
    "sg:address":"Pase Martin J.iraola Etorbidea, 1",
    "sg:city":"San Blas",
    "sg:orig_category":"Librer\u00cdas",
    "sg:phone":"+34 943 67 38 68",
    "sg:postcode":"20400",
    "sg:province":"Guip\u00f9zcoa",
    "wof:name":"Echaburua Velasco Maria Purificacion",
    "wof:placetype":"venue"
},
  "geometry": {"coordinates":[-2.0789339542,43.1339912415],"type":"Point"}
}