{
  "type": "Feature",
  "properties": {
    "iso:country":"ES",
    "sg:address":"Carrer de Sant Antoni Maria Claret, 8",
    "sg:city":"Manresa",
    "sg:orig_category":"Inmobiliaria (agencias)",
    "sg:phone":"+34 938 74 48 61",
    "sg:postcode":"08243",
    "sg:province":"Barcelona",
    "wof:name":"Comunitat De Propietaris De Carrer Sant Antoni Maria Claret 8",
    "wof:placetype":"venue"
},
  "geometry": {"coordinates":[1.8321119547,41.7307357788],"type":"Point"}
}