{
  "type": "Feature",
  "properties": {
    "addr:full":"Calle de Hortaleza, 51 Madrid Madrid 28004",
    "addr:housenumber":"51",
    "addr:postcode":"madrid;28004",
    "addr:street":"Calle De Hortaleza",
    "iso:country":"ES",
    "sg:address":"Calle de Hortaleza, 51",
    "sg:city":"Madrid",
    "sg:orig_category":"Caf\u00c9s, Bares, Cervecer\u00cdas",
    "sg:phone":"+34 915 21 25 64",
    "sg:postcode":"28004",
    "sg:province":"Madrid",
    "wof:name":"Saber Beber Sl",
    "wof:placetype":"venue"
},
  "geometry": {"coordinates":[-3.6992049217,40.4231491089],"type":"Point"}
}