{
  "type": "Feature",
  "properties": {
    "addr:full":"Anzofe, S/n Sta Maria Guia Las Palmas 35450",
    "addr:housenumber":"/ n",
    "addr:postcode":"35450",
    "addr:street":"Anzofe S;Sta Maria Guia",
    "iso:country":"ES",
    "sg:address":"Anzofe, S/n",
    "sg:city":"Sta Maria Guia",
    "sg:orig_category":"Agricultura: Abastecimiento Y Cosechado (negocio)",
    "sg:phone":"+34 928 88 30 94",
    "sg:postcode":"35450",
    "sg:province":"Las Palmas",
    "wof:name":"Blomia S. A.",
    "wof:placetype":"venue"
},
  "geometry": {"coordinates":[-15.6436672211,28.1351528168],"type":"Point"}
}