{
  "type": "Feature",
  "properties": {
    "addr:full":"Calle de San Cesar, 3 Madrid Madrid 28039",
    "addr:housenumber":"3",
    "addr:postcode":"28039",
    "addr:street":"Calle De San Cesar",
    "iso:country":"ES",
    "sg:address":"Calle de San Cesar, 3",
    "sg:city":"Madrid",
    "sg:classifiers":[
        {
            "category":"Taxi",
            "type":"Transportation"
        }
    ],
    "sg:phone":"+34 914 59 06 03",
    "sg:postcode":"28039",
    "sg:province":"Madrid",
    "wof:name":"Gonzalez Corral Jose",
    "wof:placetype":"venue"
},
  "geometry": {"coordinates":[-3.7107748985,40.4590606689],"type":"Point"}
}