{
  "type": "Feature",
  "properties": {
    "iso:country":"ES",
    "sg:address":"B (pol Talluntxe), 26",
    "sg:city":"Noain",
    "sg:orig_category":"Electrodom\u00c9sticos (al Por Menor)",
    "sg:phone":"+34 948 31 80 52",
    "sg:postcode":"31110",
    "sg:province":"Navarra",
    "wof:name":"Sotelnor S.l.",
    "wof:placetype":"venue"
},
  "geometry": {"coordinates":[-1.6433140039,42.7574806213],"type":"Point"}
}