{
  "type": "Feature",
  "properties": {
    "iso:country":"ES",
    "sg:address":"Av Barcelona, 21",
    "sg:city":"Molins Rei",
    "sg:orig_category":"Agencias Y Agentes Comerciales, Representantes",
    "sg:phone":"+34 936 68 01 57",
    "sg:postcode":"08750",
    "sg:province":"Barcelona",
    "wof:name":"Navarro Gil Manuel",
    "wof:placetype":"venue"
},
  "geometry": {"coordinates":[2.0201408863,41.4095535278],"type":"Point"}
}