{
  "type": "Feature",
  "properties": {
    "iso:country":"ES",
    "sg:address":"Calle de Neptuno, 3",
    "sg:city":"Granada",
    "sg:orig_category":"M\u00c9dicos: Cirug\u00cda General",
    "sg:phone":"+34 958 52 11 07",
    "sg:postcode":"18004",
    "sg:province":"Granada",
    "wof:name":"Rodriguez Galindo Juan Antonio",
    "wof:placetype":"venue"
},
  "geometry": {"coordinates":[-3.6063230038,37.1697425842],"type":"Point"}
}