{
  "type": "Feature",
  "properties": {
    "addr:full":"Pol Ind Cala, S/n Cala Huelva 21270",
    "addr:housenumber":"s / n",
    "addr:postcode":"21270",
    "addr:street":"Cala",
    "iso:country":"ES",
    "sg:address":"Pol Ind Cala, S/n",
    "sg:city":"Cala",
    "sg:orig_category":"Heladeros",
    "sg:phone":"+34 959 19 13 91",
    "sg:postcode":"21270",
    "sg:province":"Huelva",
    "wof:name":"Diaz Aguilar Pedro Ezequiel",
    "wof:placetype":"venue"
},
  "geometry": {"coordinates":[-6.3188099861,37.9726524353],"type":"Point"}
}