{
  "type": "Feature",
  "properties": {
    "iso:country":"ES",
    "sg:address":"Calle de Noblejas, 7",
    "sg:city":"Madrid",
    "sg:orig_category":"Abogados",
    "sg:phone":"+34 915 48 40 88",
    "sg:postcode":"28013",
    "sg:province":"Madrid",
    "wof:name":"Chamorro Gay Margarita",
    "wof:placetype":"venue"
},
  "geometry": {"coordinates":[-3.7126851082,40.416759491],"type":"Point"}
}