{
  "type": "Feature",
  "properties": {
    "addr:full":"Calle de Pedro De Contreras, 4 Malaga M\u00e1laga 29014",
    "addr:housenumber":"4",
    "addr:postcode":"29014",
    "addr:street":"Calle De Pedro De Contreras;Ma\u0301Laga",
    "iso:country":"ES",
    "sg:address":"Calle de Pedro De Contreras, 4",
    "sg:city":"Malaga",
    "sg:orig_category":"Electrodom\u00c9sticos (al Por Menor)",
    "sg:phone":"+34 952 25 38 40",
    "sg:postcode":"29014",
    "sg:province":"M\u00e1laga",
    "wof:name":"Bazar San Juan S. A.",
    "wof:placetype":"venue"
},
  "geometry": {"coordinates":[-4.4204740524,36.7471733093],"type":"Point"}
}