{
  "type": "Feature",
  "properties": {
    "iso:country":"ES",
    "sg:address":"Calle de Orquidea, 6",
    "sg:city":"Lepe",
    "sg:orig_category":"Asociaciones Humanitarias, De Cooperaci\u00d3n, De Acci\u00d3n Social",
    "sg:phone":"+34 959 38 17 07",
    "sg:postcode":"21440",
    "sg:province":"Huelva",
    "wof:name":"Asociacion C.e.t.a.f. Estuario",
    "wof:placetype":"venue"
},
  "geometry": {"coordinates":[-7.1935143471,37.2575378418],"type":"Point"}
}