{
  "type": "Feature",
  "properties": {
    "iso:country":"ES",
    "sg:address":"Calle de Jesus Nazareno, 8",
    "sg:city":"Palmas De Gran Canaria",
    "sg:orig_category":"Imprenta",
    "sg:phone":"+34 928 46 30 33",
    "sg:postcode":"35009",
    "sg:province":"Las Palmas",
    "wof:name":"Argrafic S.l.",
    "wof:placetype":"venue"
},
  "geometry": {"coordinates":[-15.4347629547,28.1653614044],"type":"Point"}
}