{
  "type": "Feature",
  "properties": {
    "iso:country":"ES",
    "sg:address":"Calle de Calvario, 15",
    "sg:city":"Miajadas",
    "sg:orig_category":"Negocio De Materiales De Construcci\u00d3n",
    "sg:phone":"+34 927 16 01 22",
    "sg:postcode":"10100",
    "sg:province":"C\u00e1ceres",
    "wof:name":"Trujiconst S.l.",
    "wof:placetype":"venue"
},
  "geometry": {"coordinates":[-5.9115099907,39.1546173096],"type":"Point"}
}