{
  "type": "Feature",
  "properties": {
    "addr:full":"N. Carriquiri, 11 Iru\u00f1a Navarra 31014",
    "addr:housenumber":"11",
    "addr:postcode":"31014",
    "addr:street":"Carriquiri",
    "iso:country":"ES",
    "sg:address":"N. Carriquiri, 11",
    "sg:city":"Iru\u00f1a",
    "sg:orig_category":"Pintura, Barniz, Productos Asimilables (fabricaci\u00d3n, Al Por Mayor)",
    "sg:phone":"+34 948 12 21 53",
    "sg:postcode":"31014",
    "sg:province":"Navarra",
    "wof:name":"Aplitec S.l.",
    "wof:placetype":"venue"
},
  "geometry": {"coordinates":[-1.6555310488,42.8269042969],"type":"Point"}
}