{
  "type": "Feature",
  "properties": {
    "addr:full":"Universidad, S/n Iru\u00f1a Navarra 31...",
    "addr:housenumber":"s / n;31 ...",
    "addr:street":"Universidad;Navarra",
    "iso:country":"ES",
    "sg:address":"Universidad, S/n",
    "sg:city":"Iru\u00f1a",
    "sg:orig_category":"Universidades",
    "sg:phone":"+34 948 42 56 00",
    "sg:postcode":"31...",
    "sg:province":"Navarra",
    "sg:website":"www.unav.es",
    "wof:name":"Universidad De Navarra",
    "wof:placetype":"venue"
},
  "geometry": {"coordinates":[-1.668544054,42.8011398315],"type":"Point"}
}