{
  "type": "Feature",
  "properties": {
    "addr:full":"Calle de Bermejeros, 22 Salamanca Salamanca 37001",
    "addr:housenumber":"22",
    "addr:postcode":"37001",
    "addr:street":"Calle De Bermejeros",
    "iso:country":"ES",
    "sg:address":"Calle de Bermejeros, 22",
    "sg:city":"Salamanca",
    "sg:orig_category":"Tintorer\u00cdas, Limpieza En Seco",
    "sg:phone":"+34 923 26 16 50",
    "sg:postcode":"37001",
    "sg:province":"Salamanca",
    "sg:website":"www.pressto.com",
    "wof:name":"Garcia Valverde Alfonso",
    "wof:placetype":"venue"
},
  "geometry": {"coordinates":[-5.6608257294,40.966091156],"type":"Point"}
}