{
  "type": "Feature",
  "properties": {
    "addr:full":"Carr Vicari Pastor, De, 5 Soller Islas Baleares 07100",
    "addr:housenumber":"5",
    "addr:postcode":"07100",
    "addr:street":"Carr Vicari Pastor De",
    "iso:country":"ES",
    "sg:address":"Carr Vicari Pastor, De, 5",
    "sg:city":"Soller",
    "sg:orig_category":"Psic\u00d3logos",
    "sg:phone":"+34 971 63 22 64",
    "sg:postcode":"07100",
    "sg:province":"Islas Baleares",
    "wof:name":"Coll Barcelo Antonia",
    "wof:placetype":"venue"
},
  "geometry": {"coordinates":[2.7145628929,39.766078949],"type":"Point"}
}