{
  "type": "Feature",
  "properties": {
    "addr:full":"Calle de Santiago, 18 Madrid Madrid 28013",
    "addr:housenumber":"18",
    "addr:postcode":"madrid;28013",
    "addr:street":"Calle De Santiago",
    "iso:country":"ES",
    "sg:address":"Calle de Santiago, 18",
    "sg:city":"Madrid",
    "sg:orig_category":"Florister\u00cdas",
    "sg:phone":"+34 915 40 08 64",
    "sg:postcode":"28013",
    "sg:province":"Madrid",
    "wof:name":"Topiarii Division Floral S.l.l.",
    "wof:placetype":"venue"
},
  "geometry": {"coordinates":[-3.7103550434,40.4165802002],"type":"Point"}
}