{
  "type": "Feature",
  "properties": {
    "addr:full":"Calle de Domingo Ram, 51 Zaragoza Zaragoza 50017",
    "addr:housenumber":"51",
    "addr:postcode":"50017",
    "addr:street":"Calle De Domingo Ram",
    "iso:country":"ES",
    "sg:address":"Calle de Domingo Ram, 51",
    "sg:city":"Zaragoza",
    "sg:orig_category":"Electricidad: Instaladores",
    "sg:phone":"+34 976 33 16 92",
    "sg:postcode":"50017",
    "sg:province":"Zaragoza",
    "wof:name":"Electricidad Caso S.l",
    "wof:placetype":"venue"
},
  "geometry": {"coordinates":[-0.9060204029,41.6481018066],"type":"Point"}
}