{
  "type": "Feature",
  "properties": {
    "iso:country":"ES",
    "sg:address":"Calle de Bergondo, S/n",
    "sg:city":"Coru\u00d1a",
    "sg:classifiers":[
        {
            "category":"Taxi",
            "type":"Transportation"
        }
    ],
    "sg:phone":"+34 981 13 79 36",
    "sg:postcode":"15009",
    "sg:province":"La Coru\u00f1a",
    "wof:name":"Asociacion Local De Trabajadores Autonomos De Autotaxis",
    "wof:placetype":"venue"
},
  "geometry": {"coordinates":[-8.3966493607,43.3483963013],"type":"Point"}
}