{
  "type": "Feature",
  "properties": {
    "iso:country":"ES",
    "sg:address":"Avda. Nieves, S/n",
    "sg:city":"Las Gabias",
    "sg:orig_category":"Empresas De Carpinter\u00cda De Madera",
    "sg:phone":"+34 958 58 50 00",
    "sg:postcode":"18110",
    "sg:province":"Granada",
    "wof:name":"Carpinteria Benrumar S.l.",
    "wof:placetype":"venue"
},
  "geometry": {"coordinates":[-97.78224945069999,45.7040786743],"type":"Point"}
}