{
  "type": "Feature",
  "properties": {
    "addr:full":"Calle de Bernabe Soriano, 28 Jaen Ja\u00e9n 23001",
    "addr:housenumber":"28;jae\u0301n",
    "addr:postcode":"23001",
    "addr:street":"Calle De Bernabe Soriano",
    "iso:country":"ES",
    "sg:address":"Calle de Bernabe Soriano, 28",
    "sg:city":"Jaen",
    "sg:orig_category":"Cajas De Ahorro",
    "sg:phone":"+34 953 24 03 00",
    "sg:postcode":"23001",
    "sg:province":"Ja\u00e9n",
    "wof:name":"Monte De Piedad Y Caja De Ahorros De Huelva Y Sevilla",
    "wof:placetype":"venue"
},
  "geometry": {"coordinates":[-3.78829813,37.7664337158],"type":"Point"}
}