{
  "type": "Feature",
  "properties": {
    "addr:full":"Ctra Posadas, 2 Villaviciosa Cordoba C\u00f3rdoba 14300",
    "addr:housenumber":"2",
    "addr:postcode":"14300",
    "addr:street":"Ctra Posadas",
    "iso:country":"ES",
    "sg:address":"Ctra Posadas, 2",
    "sg:city":"Villaviciosa Cordoba",
    "sg:orig_category":"Contenedores (mercanc\u00cdas)",
    "sg:phone":"+34 957 36 02 45",
    "sg:postcode":"14300",
    "sg:province":"C\u00f3rdoba",
    "wof:name":"Porras Moreno Francisco Angel",
    "wof:placetype":"venue"
},
  "geometry": {"coordinates":[-5.0143089294,38.0761260986],"type":"Point"}
}