{
  "type": "Feature",
  "properties": {
    "addr:full":"Calle de Regocijos, 112 Almeria Almer\u00eda 04003",
    "addr:housenumber":"112",
    "addr:postcode":"04003",
    "addr:street":"Calle De Regocijos",
    "iso:country":"ES",
    "sg:address":"Calle de Regocijos, 112",
    "sg:city":"Almeria",
    "sg:orig_category":"Impresiones Sobre Tela",
    "sg:phone":"+34 950 25 71 33",
    "sg:postcode":"04003",
    "sg:province":"Almer\u00eda",
    "wof:name":"Hernandez Alonso Antonio",
    "wof:placetype":"venue"
},
  "geometry": {"coordinates":[-2.4660909176,36.8453063965],"type":"Point"}
}