{
  "type": "Feature",
  "properties": {
    "iso:country":"ES",
    "sg:address":"Avda Virgen Del Rocio, S/n",
    "sg:city":"Santiponce",
    "sg:orig_category":"Ferreter\u00cda (diversos)",
    "sg:phone":"+34 955 99 62 29",
    "sg:postcode":"41970",
    "sg:province":"Sevilla",
    "wof:name":"Hierros Y Ferrallas Paramio E Hijos S.l.",
    "wof:placetype":"venue"
},
  "geometry": {"coordinates":[-6.0435438156,37.4332618713],"type":"Point"}
}