{
  "type": "Feature",
  "properties": {
    "iso:country":"ES",
    "sg:address":"Calle de Vinaroz, 1",
    "sg:city":"Madrid",
    "sg:orig_category":"Confecci\u00d3n De Trajes Para Se\u00d1oras",
    "sg:phone":"+34 914 16 14 04",
    "sg:postcode":"28002",
    "sg:province":"Madrid",
    "wof:name":"Vicens Segarra Encarnacion",
    "wof:placetype":"venue"
},
  "geometry": {"coordinates":[-3.674973011,40.4445915222],"type":"Point"}
}