{
  "type": "Feature",
  "properties": {
    "addr:full":"Camp De Marte, S/n Tarragona Tarragona 43002",
    "addr:housenumber":"s / n",
    "addr:postcode":"43002",
    "iso:country":"ES",
    "sg:address":"Camp De Marte, S/n",
    "sg:city":"Tarragona",
    "sg:orig_category":"Ense\u00d1anza, Formaci\u00d3n Profesional: Aprendizaje",
    "sg:phone":"+34 977 24 06 81",
    "sg:postcode":"43002",
    "sg:province":"Tarragona",
    "wof:name":"Ajuntament De Tarragona",
    "wof:placetype":"venue"
},
  "geometry": {"coordinates":[1.2493976355,41.1220626831],"type":"Point"}
}