{
  "type": "Feature",
  "properties": {
    "iso:country":"ES",
    "sg:address":"Calle de Puerto De San Glorio, S/n",
    "sg:city":"Prado Overa",
    "sg:orig_category":"Engranajes Y Elementos De Transmisi\u00d3n",
    "sg:phone":"+34 913 41 95 40",
    "sg:postcode":"28919",
    "sg:province":"Madrid",
    "sg:website":"www.pujolmuntala.es",
    "wof:name":"Pujol Muntala S.a.",
    "wof:placetype":"venue"
},
  "geometry": {"coordinates":[-3.7468090057,40.3436431885],"type":"Point"}
}