{
  "type": "Feature",
  "properties": {
    "iso:country":"ES",
    "sg:address":"Calle de Oudrid, 21",
    "sg:city":"Madrid",
    "sg:orig_category":"Ense\u00d1anza: Profesiones Art\u00cdsticas",
    "sg:phone":"+34 914 50 95 31",
    "sg:postcode":"28039",
    "sg:province":"Madrid",
    "wof:name":"Ferrer Loewinsohn Santiago",
    "wof:placetype":"venue"
},
  "geometry": {"coordinates":[-3.7078130245,40.4548835754],"type":"Point"}
}