{
  "type": "Feature",
  "properties": {
    "addr:full":"Avda Rompido El, 47 Cartaya Huelva 21450",
    "addr:postcode":"21450",
    "addr:street":"Avda Rompido El",
    "iso:country":"ES",
    "sg:address":"Avda Rompido El, 47",
    "sg:city":"Cartaya",
    "sg:orig_category":"Florister\u00cdas",
    "sg:phone":"+34 959 39 17 06",
    "sg:postcode":"21450",
    "sg:province":"Huelva",
    "wof:name":"Cabaco Alvarez Manuel",
    "wof:placetype":"venue"
},
  "geometry": {"coordinates":[-7.1488251686,37.2846755981],"type":"Point"}
}