{
  "type": "Feature",
  "properties": {
    "addr:full":"Calle de Nueva Del Cuartel, 2 Medina Campo Valladolid 47400",
    "addr:housenumber":"2",
    "addr:postcode":"47400",
    "addr:street":"Calle De Nueva Del Cuartel",
    "iso:country":"ES",
    "sg:address":"Calle de Nueva Del Cuartel, 2",
    "sg:city":"Medina Campo",
    "sg:orig_category":"Bares, Piano",
    "sg:phone":"+34 983 80 08 44",
    "sg:postcode":"47400",
    "sg:province":"Valladolid",
    "wof:name":"Mohino Andres Antonio",
    "wof:placetype":"venue"
},
  "geometry": {"coordinates":[-4.9108781815,41.305480957],"type":"Point"}
}