{
  "type": "Feature",
  "properties": {
    "addr:full":"Pase Andres Vergara (de), 26 Estacion Madrid 28250",
    "addr:housenumber":"26 estacion",
    "addr:postcode":"28250",
    "addr:street":"Andres Vergara De",
    "iso:country":"ES",
    "sg:address":"Pase Andres Vergara (de), 26",
    "sg:city":"Estacion",
    "sg:orig_category":"Asesor\u00cda Fiscal Y Jur\u00cddica",
    "sg:phone":"+34 918 59 25 93",
    "sg:postcode":"28250",
    "sg:province":"Madrid",
    "wof:name":"Asesoramiento Fiscal Informatizado, S.l.",
    "wof:placetype":"venue"
},
  "geometry": {"coordinates":[-3.7003455162,40.4166908264],"type":"Point"}
}