{
  "type": "Feature",
  "properties": {
    "iso:country":"ES",
    "sg:address":"Calle de Sor Valentina Miron, 41",
    "sg:city":"Plasencia",
    "sg:orig_category":"Camiser\u00cda Y Ropa Interior Masculina (al Por Menor)",
    "sg:phone":"+34 927 42 70 24",
    "sg:postcode":"10600",
    "sg:province":"C\u00e1ceres",
    "wof:name":"Suministros Picote S.l.",
    "wof:placetype":"venue"
},
  "geometry": {"coordinates":[-6.0887460709,40.0337371826],"type":"Point"}
}