{
  "type": "Feature",
  "properties": {
    "addr:full":"Calle de Real, 7 Cantimpalos Segovia 40360",
    "addr:housenumber":"7",
    "addr:postcode":"40360",
    "addr:street":"Calle De Real;Segovia",
    "iso:country":"ES",
    "sg:address":"Calle de Real, 7",
    "sg:city":"Cantimpalos",
    "sg:orig_category":"Cajas De Ahorro",
    "sg:phone":"+34 921 49 69 01",
    "sg:postcode":"40360",
    "sg:province":"Segovia",
    "wof:name":"Caja De Ahorros Y Monte De Piedad De Segovia",
    "wof:placetype":"venue"
},
  "geometry": {"coordinates":[-4.1580181122,41.0733299255],"type":"Point"}
}