{
  "type": "Feature",
  "properties": {
    "iso:country":"ES",
    "sg:address":"Calle de San Agustin, 1",
    "sg:city":"Jerez De Los Caballeros",
    "sg:orig_category":"Ense\u00d1anza, Formaci\u00d3n Profesional: Aprendizaje",
    "sg:phone":"+34 924 75 18 11",
    "sg:postcode":"06380",
    "sg:province":"Badajoz",
    "wof:name":"Ayuntamiento De Jerez De Los Caballeros-emisora De Radio",
    "wof:placetype":"venue"
},
  "geometry": {"coordinates":[-6.7718172073,38.3197898865],"type":"Point"}
}