{
  "type": "Feature",
  "properties": {
    "addr:full":"Calle de Azabacheria, 16 Le\u00f3n Le\u00f3n 24003",
    "addr:housenumber":"16",
    "addr:postcode":"24003",
    "addr:street":"Calle De Azabacheria;Leo\u0301N",
    "iso:country":"ES",
    "sg:address":"Calle de Azabacheria, 16",
    "sg:city":"Le\u00f3n",
    "sg:orig_category":"Fabricaci\u00d3n, Distribuci\u00d3n De Discos, V\u00cddeodiscos Y Musicassettes",
    "sg:phone":"+34 987 20 63 08",
    "sg:postcode":"24003",
    "sg:province":"Le\u00f3n",
    "wof:name":"Macias Gonzalez Alvaro",
    "wof:placetype":"venue"
},
  "geometry": {"coordinates":[-5.568444252,42.5971336365],"type":"Point"}
}