{
  "type": "Feature",
  "properties": {
    "iso:country":"ES",
    "sg:address":"Calle de Dos Amigos, 12",
    "sg:city":"Cangas Narcea",
    "sg:orig_category":"Producci\u00d3n De Sidra",
    "sg:phone":"+34 985 81 00 38",
    "sg:postcode":"33800",
    "sg:province":"Asturias",
    "wof:name":"Sidreria Narcea S.l.",
    "wof:placetype":"venue"
},
  "geometry": {"coordinates":[-6.5502290726,43.1801643372],"type":"Point"}
}