{
  "type": "Feature",
  "properties": {
    "addr:full":"Ptge Obrer, S/n Terrassa Barcelona 08224",
    "addr:housenumber":"s / n",
    "addr:postcode":"08224",
    "addr:street":"Ptge Obrer",
    "iso:country":"ES",
    "sg:address":"Ptge Obrer, S/n",
    "sg:city":"Terrassa",
    "sg:orig_category":"Ropa Para Ni\u00d1os (al Por Menor)",
    "sg:phone":"+34 937 33 62 71",
    "sg:postcode":"08224",
    "sg:province":"Barcelona",
    "sg:website":"www.nensinenes.com",
    "wof:name":"Modes Per Nens I Nenes S.l.",
    "wof:placetype":"venue"
},
  "geometry": {"coordinates":[2.003264904,41.5651359558],"type":"Point"}
}