{
  "type": "Feature",
  "properties": {
    "iso:country":"ES",
    "sg:address":"Calle de Postas, 32",
    "sg:city":"Vitoria-gasteiz",
    "sg:orig_category":"\u00d3ptica: Instrumentos (fabricaci\u00d3n)",
    "sg:phone":"+34 945 23 11 81",
    "sg:postcode":"01001",
    "sg:province":"\u00c1lava",
    "wof:name":"Lindner Dominguez Maria Isabel",
    "wof:placetype":"venue"
},
  "geometry": {"coordinates":[-2.6710789204,42.8459014893],"type":"Point"}
}