{
  "type": "Feature",
  "properties": {
    "addr:full":"Avda Andalucia, S/n Loja Granada 18300",
    "addr:housenumber":"/ n loja",
    "addr:postcode":"18300",
    "addr:street":"Avda Andalucia S",
    "iso:country":"ES",
    "sg:address":"Avda Andalucia, S/n",
    "sg:city":"Loja",
    "sg:orig_category":"Mec\u00c1nico Del Autom\u00d3vil",
    "sg:phone":"+34 958 32 23 71",
    "sg:postcode":"18300",
    "sg:province":"Granada",
    "wof:name":"Talleres Bejar Mellado S.l.",
    "wof:placetype":"venue"
},
  "geometry": {"coordinates":[-4.1554489136,37.1660728455],"type":"Point"}
}