{
  "type": "Feature",
  "properties": {
    "addr:full":"Calle de Larga, 77 Villamalea Albacete 02270",
    "addr:housenumber":"77",
    "addr:postcode":"02270",
    "addr:street":"Calle De Larga",
    "iso:country":"ES",
    "sg:address":"Calle de Larga, 77",
    "sg:city":"Villamalea",
    "sg:orig_category":"Guarder\u00cdas",
    "sg:phone":"+34 967 48 30 70",
    "sg:postcode":"02270",
    "sg:province":"Albacete",
    "wof:name":"Ayuntamiento De Villamalea",
    "wof:placetype":"venue"
},
  "geometry": {"coordinates":[-1.6016499996,39.3619194031],"type":"Point"}
}