{
  "type": "Feature",
  "properties": {
    "addr:full":"Avda Barranquilla, 13 Madrid Madrid 28033",
    "addr:housenumber":"13",
    "addr:postcode":"madrid;28033",
    "addr:street":"Avda Barranquilla",
    "iso:country":"ES",
    "sg:address":"Avda Barranquilla, 13",
    "sg:city":"Madrid",
    "sg:orig_category":"Alimentaci\u00d3n General (al Por Menor)",
    "sg:phone":"+34 913 81 14 62",
    "sg:postcode":"28033",
    "sg:province":"Madrid",
    "wof:name":"Yang  Xudong",
    "wof:placetype":"venue"
},
  "geometry": {"coordinates":[-3.6394724846,40.4747238159],"type":"Point"}
}