{
  "type": "Feature",
  "properties": {
    "addr:full":"Rier Miro (de), 74 Reus Tarragona 43202",
    "addr:postcode":"43202",
    "iso:country":"ES",
    "sg:address":"Rier Miro (de), 74",
    "sg:city":"Reus",
    "sg:orig_category":"Mantenimiento Y Reparaci\u00d3n De Motores Industriales",
    "sg:phone":"+34 977 34 58 31",
    "sg:postcode":"43202",
    "sg:province":"Tarragona",
    "wof:name":"Sarda Ribe Jose Maria",
    "wof:placetype":"venue"
},
  "geometry": {"coordinates":[1.107929945,41.1519889832],"type":"Point"}
}