{
  "type": "Feature",
  "properties": {
    "addr:full":"Calle de Carlos Aurioles, 8 Madrid Madrid 28018",
    "addr:housenumber":"8",
    "addr:postcode":"madrid;28018",
    "addr:street":"Calle De Carlos Aurioles",
    "iso:country":"ES",
    "sg:address":"Calle de Carlos Aurioles, 8",
    "sg:city":"Madrid",
    "sg:orig_category":"Electricidad Veh\u00cdculo",
    "sg:phone":"+34 917 85 61 43",
    "sg:postcode":"28018",
    "sg:province":"Madrid",
    "wof:name":"Electromecanica Hnos Toca C.b",
    "wof:placetype":"venue"
},
  "geometry": {"coordinates":[-3.6655502319,40.3835906982],"type":"Point"}
}