{
  "type": "Feature",
  "properties": {
    "addr:full":"Avda Navarra, 180 Zaragoza Zaragoza 50011",
    "addr:housenumber":"180",
    "addr:postcode":"50011",
    "addr:street":"Avda Navarra",
    "iso:country":"ES",
    "sg:address":"Avda Navarra, 180",
    "sg:city":"Zaragoza",
    "sg:orig_category":"Ropa Para Se\u00d1oras Y Caballeros (al Por Menor)",
    "sg:phone":"+34 976 33 13 03",
    "sg:postcode":"50011",
    "sg:province":"Zaragoza",
    "sg:website":"www.womensecret.com",
    "wof:name":"Cortefiel S.a.",
    "wof:placetype":"venue"
},
  "geometry": {"coordinates":[-0.920807004,41.6590461731],"type":"Point"}
}