{
  "type": "Feature",
  "properties": {
    "addr:full":"Avda Ricardo Mella, 127 San Xurxo Pontevedra 36330",
    "addr:housenumber":"127",
    "addr:postcode":"36330",
    "addr:street":"Avda Ricardo Mella",
    "iso:country":"ES",
    "sg:address":"Avda Ricardo Mella, 127",
    "sg:city":"San Xurxo",
    "sg:orig_category":"Confiter\u00cda, Galletas Y Pastas, Chocolater\u00cda (al Por Mayor)",
    "sg:phone":"+34 986 29 61 00",
    "sg:postcode":"36330",
    "sg:province":"Pontevedra",
    "wof:name":"Chocolates Rama S.l.",
    "wof:placetype":"venue"
},
  "geometry": {"coordinates":[-8.694773674,42.6678962708],"type":"Point"}
}