{
  "type": "Feature",
  "properties": {
    "iso:country":"ES",
    "sg:address":"Avda Francia, S/n",
    "sg:city":"Benasque",
    "sg:orig_category":"Caf\u00c9s, Bares, Cervecer\u00cdas",
    "sg:phone":"+34 974 55 17 49",
    "sg:postcode":"22440",
    "sg:province":"Huesca",
    "wof:name":"Latorre Giron Margarita",
    "wof:placetype":"venue"
},
  "geometry": {"coordinates":[0.5243260264,42.6036720276],"type":"Point"}
}