{
  "type": "Feature",
  "properties": {
    "addr:full":"Avda Vilalba (de), 92 Rabade Lugo 27370",
    "addr:postcode":"27370",
    "addr:street":"Avda",
    "iso:country":"ES",
    "sg:address":"Avda Vilalba (de), 92",
    "sg:city":"Rabade",
    "sg:orig_category":"Vinos Y Licores (venta Al Por Menor)",
    "sg:phone":"+34 982 39 03 70",
    "sg:postcode":"27370",
    "sg:province":"Lugo",
    "wof:name":"Nistal Castro Jose Antonio",
    "wof:placetype":"venue"
},
  "geometry": {"coordinates":[-7.7674250603,43.1950416565],"type":"Point"}
}