{
  "type": "Feature",
  "properties": {
    "iso:country":"ES",
    "sg:address":"Calle de Santa Teresa, 24",
    "sg:city":"Tafira Alta",
    "sg:orig_category":"Arquitectos",
    "sg:phone":"+34 928 35 19 92",
    "sg:postcode":"35017",
    "sg:province":"Las Palmas",
    "wof:name":"Farinos Pe\u00f1ate Eduardo",
    "wof:placetype":"venue"
},
  "geometry": {"coordinates":[-15.4631290436,28.0548477173],"type":"Point"}
}