{
  "type": "Feature",
  "properties": {
    "addr:full":"Calle de Fray Martin De Murua, 10 Gernika-lumo Vizcaya 48300",
    "addr:housenumber":"10",
    "addr:postcode":"48300",
    "addr:street":"Calle De Fray;De Murua",
    "iso:country":"ES",
    "sg:address":"Calle de Fray Martin De Murua, 10",
    "sg:city":"Gernika-lumo",
    "sg:orig_category":"Comunidades Religiosas",
    "sg:phone":"+34 946 25 27 89",
    "sg:postcode":"48300",
    "sg:province":"Vizcaya",
    "wof:name":"Religiosas Hijas De San Jose",
    "wof:placetype":"venue"
},
  "geometry": {"coordinates":[-2.6819028854,43.3109741211],"type":"Point"}
}