{
  "type": "Feature",
  "properties": {
    "addr:full":"Calle de Santo Tirso, 18 Le\u00f3n Le\u00f3n 24006",
    "addr:housenumber":"18",
    "addr:postcode":"24006",
    "addr:street":"Calle De Santo Tirso;Leo\u0301N",
    "iso:country":"ES",
    "sg:address":"Calle de Santo Tirso, 18",
    "sg:city":"Le\u00f3n",
    "sg:orig_category":"Asesor\u00cda Fiscal Y Jur\u00cddica",
    "sg:phone":"+34 987 25 69 58",
    "sg:postcode":"24006",
    "sg:province":"Le\u00f3n",
    "wof:name":"Asesoria Juridica Leonesa S.l.",
    "wof:placetype":"venue"
},
  "geometry": {"coordinates":[-5.5652785301,42.5944976807],"type":"Point"}
}