{
  "type": "Feature",
  "properties": {
    "addr:full":"Calle de Mesones, 77 Tiemblo \u00c1vila 05270",
    "addr:housenumber":"77",
    "addr:postcode":"05270",
    "addr:street":"Calle De Mesones;A\u0301Vila",
    "iso:country":"ES",
    "sg:address":"Calle de Mesones, 77",
    "sg:city":"Tiemblo",
    "sg:classifiers":[
        {
            "category":"Taxi",
            "type":"Transportation"
        }
    ],
    "sg:phone":"+34 918 62 56 97",
    "sg:postcode":"05270",
    "sg:province":"\u00c1vila",
    "wof:name":"Reviejo Diaz Felipe",
    "wof:placetype":"venue"
},
  "geometry": {"coordinates":[-4.4978151321,40.4108924866],"type":"Point"}
}