{
  "type": "Feature",
  "properties": {
    "iso:country":"ES",
    "sg:address":"Calle de Padre Ignacio Ellacuria, 2",
    "sg:city":"Laredo",
    "sg:orig_category":"Arquitectos",
    "sg:phone":"+34 942 60 70 16",
    "sg:postcode":"39770",
    "sg:province":"Cantabria",
    "wof:name":"Solana Gomez Manuel",
    "wof:placetype":"venue"
},
  "geometry": {"coordinates":[-3.4158065319,43.410949707],"type":"Point"}
}