{
  "type": "Feature",
  "properties": {
    "iso:country":"ES",
    "sg:address":"Mayor, 5",
    "sg:city":"Estella",
    "sg:orig_category":"Cortinas, Visillos Y Tejidos Para Muebles (al Por Menor)",
    "sg:phone":"+34 948 55 50 90",
    "sg:postcode":"31200",
    "sg:province":"Navarra",
    "wof:name":"Vallejo Ramos Pilar",
    "wof:placetype":"venue"
},
  "geometry": {"coordinates":[-2.0331509113,42.6720542908],"type":"Point"}
}