{
  "type": "Feature",
  "properties": {
    "addr:full":"Calle de Estocolmo, 7 Torrejon Ardoz Madrid 28850",
    "addr:housenumber":"7",
    "addr:postcode":"28850",
    "addr:street":"Calle De Estocolmo",
    "iso:country":"ES",
    "sg:address":"Calle de Estocolmo, 7",
    "sg:city":"Torrejon Ardoz",
    "sg:classifiers":[
        {
            "category":"Taxi",
            "type":"Transportation"
        }
    ],
    "sg:phone":"+34 916 77 49 07",
    "sg:postcode":"28850",
    "sg:province":"Madrid",
    "wof:name":"Paz Lopez Julian De La",
    "wof:placetype":"venue"
},
  "geometry": {"coordinates":[-3.4685759544,40.4619789124],"type":"Point"}
}