{
  "type": "Feature",
  "properties": {
    "addr:full":"Calle de Pe\u00d1a Cavero, 33 Madrid Madrid 28031",
    "addr:housenumber":"33",
    "addr:postcode":"madrid;28031",
    "addr:street":"Calle De Pen\u0303A Cavero",
    "iso:country":"ES",
    "sg:address":"Calle de Pe\u00d1a Cavero, 33",
    "sg:city":"Madrid",
    "sg:orig_category":"Tapicer\u00cdas",
    "sg:phone":"+34 913 32 41 70",
    "sg:postcode":"28031",
    "sg:province":"Madrid",
    "wof:name":"Pe\u00f1a Rodriguez Francisco",
    "wof:placetype":"venue"
},
  "geometry": {"coordinates":[-3.6216409206,40.3733520508],"type":"Point"}
}