{
  "type": "Feature",
  "properties": {
    "iso:country":"ES",
    "sg:address":"Disseminat, S/n",
    "sg:city":"Boscassos I Vallserena",
    "sg:orig_category":"Agricultores, Agricultores",
    "sg:phone":"+34 938 45 04 00",
    "sg:postcode":"08458",
    "sg:province":"Barcelona",
    "wof:name":"Bellvehi Portet Miguel",
    "wof:placetype":"venue"
},
  "geometry": {"coordinates":[2.3912398815,41.6868400574],"type":"Point"}
}