{
  "type": "Feature",
  "properties": {
    "addr:full":"Plaz Alfonso Vi, S/n Miranda Ebro Burgos 09200",
    "addr:housenumber":"s / n",
    "addr:postcode":"09200",
    "addr:street":"Plaz Alfonso Vi",
    "iso:country":"ES",
    "sg:address":"Plaz Alfonso Vi, S/n",
    "sg:city":"Miranda Ebro",
    "sg:orig_category":"Empresas De Limpieza",
    "sg:phone":"+34 947 33 27 07",
    "sg:postcode":"09200",
    "sg:province":"Burgos",
    "wof:name":"Fuente Martinez Pilar De La",
    "wof:placetype":"venue"
},
  "geometry": {"coordinates":[-2.9461290836,42.684009552],"type":"Point"}
}