{
  "type": "Feature",
  "properties": {
    "iso:country":"ES",
    "sg:address":"Calle de Orion, 12",
    "sg:city":"Madrid",
    "sg:orig_category":"Doctores En Medicina",
    "sg:phone":"+34 913 05 86 20",
    "sg:postcode":"28042",
    "sg:province":"Madrid",
    "wof:name":"Cayon Sanchez Jose",
    "wof:placetype":"venue"
},
  "geometry": {"coordinates":[-3.5784840584,40.4751014709],"type":"Point"}
}