{
  "type": "Feature",
  "properties": {
    "addr:full":"Calle de Arzua, 28 Madrid Madrid 28033",
    "addr:housenumber":"28",
    "addr:postcode":"madrid;28033",
    "addr:street":"Calle De Arzua",
    "iso:country":"ES",
    "sg:address":"Calle de Arzua, 28",
    "sg:city":"Madrid",
    "sg:orig_category":"Centros De Educaci\u00d3n Especial",
    "sg:phone":"+34 917 63 07 22",
    "sg:postcode":"28033",
    "sg:province":"Madrid",
    "wof:name":"Colegio Azorin (jose Luis Zabala Merchan C.b.",
    "wof:placetype":"venue"
},
  "geometry": {"coordinates":[-3.646904707,40.4744224548],"type":"Point"}
}