{
  "type": "Feature",
  "properties": {
    "iso:country":"ES",
    "sg:address":"Avda Badajoz, 47",
    "sg:city":"San Vicente Alcantara",
    "sg:orig_category":"Negocio De Materiales De Construcci\u00d3n",
    "sg:phone":"+34 924 41 07 59",
    "sg:postcode":"06500",
    "sg:province":"Badajoz",
    "wof:name":"Magro Carballo Francisco",
    "wof:placetype":"venue"
},
  "geometry": {"coordinates":[-7.1387081146,39.3638305664],"type":"Point"}
}