{
  "type": "Feature",
  "properties": {
    "iso:country":"ES",
    "sg:address":"Plaz Esperanza, S/n",
    "sg:city":"Santander",
    "sg:orig_category":"Pescader\u00cdas (al Por Menor)",
    "sg:phone":"+34 942 22 65 35",
    "sg:postcode":"39001",
    "sg:province":"Cantabria",
    "wof:name":"Reventun G\u00fcemes Aurora",
    "wof:placetype":"venue"
},
  "geometry": {"coordinates":[-3.8099420071,43.463054657],"type":"Point"}
}