{
  "type": "Feature",
  "properties": {
    "addr:full":"Calle de Magnus Blikstad, 58 Gijon Asturias 33207",
    "addr:housenumber":"58",
    "addr:postcode":"33207",
    "addr:street":"Calle De Magnus Blikstad",
    "iso:country":"ES",
    "sg:address":"Calle de Magnus Blikstad, 58",
    "sg:city":"Gijon",
    "sg:orig_category":"Fabricaci\u00d3n De Mobiliario Met\u00c1lico",
    "sg:phone":"+34 985 34 40 91",
    "sg:postcode":"33207",
    "sg:province":"Asturias",
    "sg:website":"www.sagastumebuzones.com",
    "wof:name":"Sagastume Sagastume M Dolores",
    "wof:placetype":"venue"
},
  "geometry": {"coordinates":[-5.6699571609,43.5341491699],"type":"Point"}
}