{
  "type": "Feature",
  "properties": {
    "addr:full":"Carr Balmes, 2 Girona Girona 17002",
    "addr:housenumber":"2",
    "addr:postcode":"17002",
    "addr:street":"Carr Balmes",
    "iso:country":"ES",
    "sg:address":"Carr Balmes, 2",
    "sg:city":"Girona",
    "sg:orig_category":"Edici\u00d3n De Diarios, Revistas, Boletines",
    "sg:phone":"+34 972 21 30 87",
    "sg:postcode":"17002",
    "sg:province":"Girona",
    "wof:name":"Colleldemont Oliva Josep",
    "wof:placetype":"venue"
},
  "geometry": {"coordinates":[2.8191120625,41.9752960205],"type":"Point"}
}