{
  "type": "Feature",
  "properties": {
    "iso:country":"ES",
    "sg:address":"Calle de Onesimo Redondo, 7",
    "sg:city":"Olmedo",
    "sg:orig_category":"Carnicer\u00cdas, Carnicer\u00cdas",
    "sg:phone":"+34 983 60 01 07",
    "sg:postcode":"47410",
    "sg:province":"Valladolid",
    "wof:name":"Conde Maroto Arsenio",
    "wof:placetype":"venue"
},
  "geometry": {"coordinates":[-4.6871910095,41.2885398865],"type":"Point"}
}