{
  "type": "Feature",
  "properties": {
    "iso:country":"ES",
    "sg:address":"Calle de Rosales, 2",
    "sg:city":"Santovenia Pisuerga",
    "sg:orig_category":"Suministros Y Materiales Industriales",
    "sg:phone":"+34 983 40 09 65",
    "sg:postcode":"47155",
    "sg:province":"Valladolid",
    "wof:name":"Manzano Redondo Maria Yolanda",
    "wof:placetype":"venue"
},
  "geometry": {"coordinates":[-4.681055069,41.689540863],"type":"Point"}
}