{
  "type": "Feature",
  "properties": {
    "iso:country":"ES",
    "sg:address":"La Matanza, S/n",
    "sg:city":"Padron",
    "sg:orig_category":"Animales (al Por Menor)",
    "sg:phone":"+34 981 81 16 58",
    "sg:postcode":"15900",
    "sg:province":"La Coru\u00f1a",
    "wof:name":"Bueno Cai\u00f1o Teodoro",
    "wof:placetype":"venue"
},
  "geometry": {"coordinates":[-8.6533441544,42.7381210327],"type":"Point"}
}