{
  "type": "Feature",
  "properties": {
    "iso:country":"ES",
    "sg:address":"Carretera De Celulosas, Km. 0199,0",
    "sg:city":"Motril",
    "sg:orig_category":"Puertas Y Portales",
    "sg:phone":"+34 958 82 16 27",
    "sg:postcode":"18600",
    "sg:province":"Granada",
    "wof:name":"Ceretta Cazzin Aldo",
    "wof:placetype":"venue"
},
  "geometry": {"coordinates":[-3.5152790546,36.7456130981],"type":"Point"}
}