{
  "type": "Feature",
  "properties": {
    "addr:full":"Calle de Doctor Castelo, 43 Madrid Madrid 28009",
    "addr:housenumber":"43",
    "addr:postcode":"madrid;28009",
    "addr:street":"Calle De Doctor Castelo",
    "iso:country":"ES",
    "sg:address":"Calle de Doctor Castelo, 43",
    "sg:city":"Madrid",
    "sg:orig_category":"Administradores De Bienes Y Delegados De Comunidades De Propietarios",
    "sg:phone":"+34 915 74 08 51",
    "sg:postcode":"28009",
    "sg:province":"Madrid",
    "wof:name":"Equitadre S.l.",
    "wof:placetype":"venue"
},
  "geometry": {"coordinates":[-3.6733720303,40.4202461243],"type":"Point"}
}