{
  "type": "Feature",
  "properties": {
    "addr:full":"Avgd Doctor Fleming, 12 Lleida Lleida 25006",
    "addr:housenumber":"12",
    "addr:postcode":"25006",
    "addr:street":"Doctor Fleming",
    "iso:country":"ES",
    "sg:address":"Avgd Doctor Fleming, 12",
    "sg:city":"Lleida",
    "sg:orig_category":"Pescader\u00cdas (al Por Mayor)",
    "sg:phone":"+34 973 23 22 57",
    "sg:postcode":"25006",
    "sg:province":"Lleida",
    "wof:name":"Comercial De Pescados Y Mariscos S. A.",
    "wof:placetype":"venue"
},
  "geometry": {"coordinates":[0.6160240173,41.619594574],"type":"Point"}
}