{
  "type": "Feature",
  "properties": {
    "addr:full":"Calle de Lomo San Lazaro, 2 Palmas De Gran Canaria Las Palmas 35018",
    "addr:housenumber":"2",
    "addr:postcode":"35018",
    "addr:street":"Calle De Lomo San Lazaro",
    "iso:country":"ES",
    "sg:address":"Calle de Lomo San Lazaro, 2",
    "sg:city":"Palmas De Gran Canaria",
    "sg:orig_category":"Centros De Adelgazamiento Y De Est\u00c9tica",
    "sg:phone":"+34 928 41 69 90",
    "sg:postcode":"35018",
    "sg:province":"Las Palmas",
    "wof:name":"Cardenes Cardenes Nieves",
    "wof:placetype":"venue"
},
  "geometry": {"coordinates":[-15.4784650803,28.0919818878],"type":"Point"}
}