{
  "type": "Feature",
  "properties": {
    "addr:full":"Calle de Carlos Iii, 30 Cartagena Murcia 30203",
    "addr:housenumber":"30",
    "addr:postcode":"30203",
    "addr:street":"Calle De Carlos Iii",
    "iso:country":"ES",
    "sg:address":"Calle de Carlos Iii, 30",
    "sg:city":"Cartagena",
    "sg:orig_category":"Audiovisuales, Tv, Hi",
    "sg:phone":"+34 968 52 75 19",
    "sg:postcode":"30203",
    "sg:province":"Murcia",
    "wof:name":"Megason Hi-fi S.l.",
    "wof:placetype":"venue"
},
  "geometry": {"coordinates":[-0.9829084277,37.6058921814],"type":"Point"}
}