{
  "type": "Feature",
  "properties": {
    "addr:full":"Avgd Conflent, S/n Badalona Barcelona 08915",
    "addr:housenumber":"s / n",
    "addr:postcode":"08915",
    "addr:street":"Avgd Conflent",
    "iso:country":"ES",
    "sg:address":"Avgd Conflent, S/n",
    "sg:city":"Badalona",
    "sg:orig_category":"Art\u00cdculos De Limpieza Y De Cocina (fabricaci\u00d3n, Al Por Mayor)",
    "sg:phone":"+34 934 65 89 51",
    "sg:postcode":"08915",
    "sg:province":"Barcelona",
    "sg:website":"www.dyssanic.com",
    "wof:name":"Dyssanic S.l.",
    "wof:placetype":"venue"
},
  "geometry": {"coordinates":[2.240240097,41.465045929],"type":"Point"}
}