{
  "type": "Feature",
  "properties": {
    "addr:full":"Lloc Poligon 13, S/n Campos Islas Baleares 07630",
    "addr:housenumber":"13 s / n",
    "addr:postcode":"07630",
    "addr:street":"Poligon",
    "iso:country":"ES",
    "sg:address":"Lloc Poligon 13, S/n",
    "sg:city":"Campos",
    "sg:orig_category":"Asociaciones, Organismos Culturales Y Socioeducativos",
    "sg:phone":"+34 971 65 02 11",
    "sg:postcode":"07630",
    "sg:province":"Islas Baleares",
    "wof:name":"Iniciativas Sociedades Educativas S.a.",
    "wof:placetype":"venue"
},
  "geometry": {"coordinates":[2.9981989861,39.4063606262],"type":"Point"}
}