{
  "type": "Feature",
  "properties": {
    "iso:country":"ES",
    "sg:address":"Calle de Fortuny, 31",
    "sg:city":"Alacant",
    "sg:orig_category":"Fabricaci\u00d3n De Distribuidores Autom\u00c1ticos",
    "sg:phone":"+34 965 18 39 36",
    "sg:postcode":"03009",
    "sg:province":"Alicante",
    "sg:website":"www.cascada-arcoiris.com",
    "wof:name":"Cascada Arco Iris S.l.",
    "wof:placetype":"venue"
},
  "geometry": {"coordinates":[-0.5036200285,38.3741645813],"type":"Point"}
}