{
  "type": "Feature",
  "properties": {
    "addr:full":"Calle de Juan Crisostomo Mangas, 53 Rute C\u00f3rdoba 14960",
    "addr:housenumber":"mangas 53",
    "addr:postcode":"14960",
    "addr:street":"Calle De Juan Crisostomo;Co\u0301Rdoba",
    "iso:country":"ES",
    "sg:address":"Calle de Juan Crisostomo Mangas, 53",
    "sg:city":"Rute",
    "sg:orig_category":"Mec\u00c1nico Del Autom\u00d3vil",
    "sg:phone":"+34 957 53 82 51",
    "sg:postcode":"14960",
    "sg:province":"C\u00f3rdoba",
    "wof:name":"Hinojosa Ortega Cristobal",
    "wof:placetype":"venue"
},
  "geometry": {"coordinates":[-4.3730268478,37.3249816895],"type":"Point"}
}