{
  "type": "Feature",
  "properties": {
    "addr:full":"Padre Maldonado, 10 Llerena Badajoz 06900",
    "addr:housenumber":"10",
    "addr:postcode":"06900",
    "addr:street":"Maldonado",
    "iso:country":"ES",
    "sg:address":"Padre Maldonado, 10",
    "sg:city":"Llerena",
    "sg:orig_category":"Alquiler De Gr\u00daas",
    "sg:phone":"+34 924 87 05 39",
    "sg:postcode":"06900",
    "sg:province":"Badajoz",
    "wof:name":"Rafael Carre\u00f1o Felipe",
    "wof:placetype":"venue"
},
  "geometry": {"coordinates":[-6.0153741837,38.2413711548],"type":"Point"}
}