{
  "type": "Feature",
  "properties": {
    "iso:country":"ES",
    "sg:address":"Cno Benitxa, S/n",
    "sg:city":"Orba",
    "sg:orig_category":"Aguas (distribuci\u00d3n, Servicios)",
    "sg:phone":"+34 965 58 33 06",
    "sg:postcode":"03790",
    "sg:province":"Alicante",
    "wof:name":"Empresa Municipal De Abastecimientos Y Servicios De Calpe S.a.",
    "wof:placetype":"venue"
},
  "geometry": {"coordinates":[-0.0630289987,38.7785987854],"type":"Point"}
}