{
  "type": "Feature",
  "properties": {
    "addr:full":"Foya Del Port, S/n Olleria Valencia 46850",
    "addr:housenumber":"s / n",
    "addr:postcode":"46850",
    "addr:street":"Foya;Port",
    "iso:country":"ES",
    "sg:address":"Foya Del Port, S/n",
    "sg:city":"Olleria",
    "sg:orig_category":"Ingenier\u00cda, Centros De Estudios (diversos)",
    "sg:phone":"+34 962 20 12 68",
    "sg:postcode":"46850",
    "sg:province":"Valencia",
    "wof:name":"Tecnica Y Proyectos S.a.",
    "wof:placetype":"venue"
},
  "geometry": {"coordinates":[-0.5478360057,38.9096603394],"type":"Point"}
}