{
  "type": "Feature",
  "properties": {
    "iso:country":"ES",
    "sg:address":"Carr Unio, 13",
    "sg:city":"Lleida",
    "sg:orig_category":"Loter\u00cda Y T\u00d3mbola",
    "sg:phone":"+34 973 27 11 00",
    "sg:postcode":"25002",
    "sg:province":"Lleida",
    "wof:name":"Codesal Puy Mercedes",
    "wof:placetype":"venue"
},
  "geometry": {"coordinates":[0.627129972,41.6145210266],"type":"Point"}
}