{
  "type": "Feature",
  "properties": {
    "addr:full":"Calle de Juan Ramon Jimenez, S/n Burgos Burgos 09007",
    "addr:postcode":"09007",
    "addr:street":"Calle De Juan Ramon Jimenez S / N",
    "iso:country":"ES",
    "sg:address":"Calle de Juan Ramon Jimenez, S/n",
    "sg:city":"Burgos",
    "sg:orig_category":"Cajas De Ahorro",
    "sg:phone":"+34 947 48 65 26",
    "sg:postcode":"09007",
    "sg:province":"Burgos",
    "wof:name":"Caja De Ahorros Del Circulo Catolico Obrero De Burgos",
    "wof:placetype":"venue"
},
  "geometry": {"coordinates":[-3.662375927,42.347492218],"type":"Point"}
}