{
  "type": "Feature",
  "properties": {
    "addr:full":"Carrer de Empedrat, 45 Ibi Alicante 03440",
    "addr:housenumber":"45",
    "addr:postcode":"03440",
    "addr:street":"Carrer De Empedrat",
    "iso:country":"ES",
    "sg:address":"Carrer de Empedrat, 45",
    "sg:city":"Ibi",
    "sg:orig_category":"Electrodom\u00c9sticos (al Por Menor)",
    "sg:phone":"+34 966 55 21 82",
    "sg:postcode":"03440",
    "sg:province":"Alicante",
    "wof:name":"Electrohogar Huerga Ibi S.l.",
    "wof:placetype":"venue"
},
  "geometry": {"coordinates":[-0.5755400062,38.625919342],"type":"Point"}
}