{
  "type": "Feature",
  "properties": {
    "iso:country":"ES",
    "sg:address":"Calle de Alto De Leon, 6",
    "sg:city":"Valencia De Don Juan",
    "sg:orig_category":"Alimentaci\u00d3n General (al Por Mayor)",
    "sg:phone":"+34 987 75 11 92",
    "sg:postcode":"24200",
    "sg:province":"Le\u00f3n",
    "wof:name":"Rofer Agro Ganadera S.l.",
    "wof:placetype":"venue"
},
  "geometry": {"coordinates":[-5.5160856247,42.2961006165],"type":"Point"}
}