{
  "type": "Feature",
  "properties": {
    "iso:country":"ES",
    "sg:address":"Calle de Santa Teresa, 4",
    "sg:city":"Almansa",
    "sg:orig_category":"Muebles, Minoristas",
    "sg:phone":"+34 967 34 55 03",
    "sg:postcode":"02640",
    "sg:province":"Albacete",
    "wof:name":"Almansa Dise\u00f1o S. A.",
    "wof:placetype":"venue"
},
  "geometry": {"coordinates":[-1.0937124491,38.8658218384],"type":"Point"}
}