{
  "type": "Feature",
  "properties": {
    "addr:full":"Av Estacio, S/n Blanes Girona 17300",
    "addr:housenumber":"s / n",
    "addr:postcode":"17300",
    "addr:street":"Av Estacio",
    "iso:country":"ES",
    "sg:address":"Av Estacio, S/n",
    "sg:city":"Blanes",
    "sg:orig_category":"Refiner\u00cdas De Petr\u00d3leo",
    "sg:phone":"+34 972 35 43 68",
    "sg:postcode":"17300",
    "sg:province":"Girona",
    "wof:name":"Blanes Carburantes S.l.",
    "wof:placetype":"venue"
},
  "geometry": {"coordinates":[2.7755870819,41.6759109497],"type":"Point"}
}