{
  "type": "Feature",
  "properties": {
    "addr:full":"Cerdedelo, 24 Cerdedelo Pontevedra 36417",
    "addr:housenumber":"24",
    "addr:postcode":"36417",
    "addr:street":"Cerdedelo",
    "iso:country":"ES",
    "sg:address":"Cerdedelo, 24",
    "sg:city":"Cerdedelo",
    "sg:orig_category":"Material Y Herramientas Agr\u00cdcolas",
    "sg:phone":"+34 986 48 76 06",
    "sg:postcode":"36417",
    "sg:province":"Pontevedra",
    "wof:name":"Raiblan S.l.",
    "wof:placetype":"venue"
},
  "geometry": {"coordinates":[-8.6178617477,42.2033996582],"type":"Point"}
}