{
  "type": "Feature",
  "properties": {
    "iso:country":"ES",
    "sg:address":"Calle de Gaztambide, 24",
    "sg:city":"Madrid",
    "sg:orig_category":"Ense\u00d1anza: Peluquer\u00cda Est\u00c9tica",
    "sg:phone":"+34 915 44 22 74",
    "sg:postcode":"28015",
    "sg:province":"Madrid",
    "wof:name":"Ibarra Lopez Luis",
    "wof:placetype":"venue"
},
  "geometry": {"coordinates":[-3.7155866623,40.433921814],"type":"Point"}
}