{
  "type": "Feature",
  "properties": {
    "addr:full":"Avda Parque (del), 18 Fuentidue\u00e7a De Tajo Madrid 28597",
    "addr:housenumber":"18",
    "addr:postcode":"28597",
    "addr:street":"Avda Parque Del",
    "iso:country":"ES",
    "sg:address":"Avda Parque (del), 18",
    "sg:city":"Fuentidue\u00e7a De Tajo",
    "sg:orig_category":"Fabricaci\u00d3n De Juguetes Autom\u00c1ticos",
    "sg:phone":"+34 918 72 82 20",
    "sg:postcode":"28597",
    "sg:province":"Madrid",
    "wof:name":"Automaticos Navelsa S.l.",
    "wof:placetype":"venue"
},
  "geometry": {"coordinates":[-3.7003455162,40.4166908264],"type":"Point"}
}