{
  "type": "Feature",
  "properties": {
    "iso:country":"ES",
    "sg:address":"Calle de Virgen De La Paz, 42",
    "sg:city":"Ronda",
    "sg:orig_category":"Hoteles",
    "sg:phone":"+34 952 87 11 41",
    "sg:postcode":"29400",
    "sg:province":"M\u00e1laga",
    "wof:name":"Fernandez Fernandez Marcelo",
    "wof:placetype":"venue"
},
  "geometry": {"coordinates":[-5.167057991,36.7439308167],"type":"Point"}
}