{
  "type": "Feature",
  "properties": {
    "iso:country":"ES",
    "sg:address":"Avda Ruta De La Plata, 8",
    "sg:city":"Caceres",
    "sg:orig_category":"Arquitectos",
    "sg:phone":"+34 927 23 43 10",
    "sg:postcode":"10001",
    "sg:province":"C\u00e1ceres",
    "wof:name":"Salas Collazos Diego",
    "wof:placetype":"venue"
},
  "geometry": {"coordinates":[-6.3843770027,39.4701690674],"type":"Point"}
}