{
  "type": "Feature",
  "properties": {
    "addr:full":"Calle de Heros, 21 Bilbao Vizcaya 48009",
    "addr:housenumber":"21",
    "addr:postcode":"48009",
    "addr:street":"Calle De Heros",
    "iso:country":"ES",
    "sg:address":"Calle de Heros, 21",
    "sg:city":"Bilbao",
    "sg:orig_category":"Camiser\u00cda Y Ropa Interior Masculina (al Por Menor)",
    "sg:phone":"+34 944 23 23 36",
    "sg:postcode":"48009",
    "sg:province":"Vizcaya",
    "wof:name":"Martinez Manso Sonia",
    "wof:placetype":"venue"
},
  "geometry": {"coordinates":[-2.9326000214,43.2643547058],"type":"Point"}
}