{
  "type": "Feature",
  "properties": {
    "iso:country":"ES",
    "sg:address":"Calle de Telmo Maqueda, 2",
    "sg:city":"Alcala Guadaira",
    "sg:orig_category":"Sociedades, Compa\u00d1\u00cdas Aseguradoras",
    "sg:phone":"+34 955 68 37 10",
    "sg:postcode":"41500",
    "sg:province":"Sevilla",
    "wof:name":"Mu\u00f1oz Gomez Maria Del Aguila",
    "wof:placetype":"venue"
},
  "geometry": {"coordinates":[-5.844648838,37.3394966125],"type":"Point"}
}