{
  "type": "Feature",
  "properties": {
    "iso:country":"ES",
    "sg:address":"Calle de Camino Viejo De Leganes, 123",
    "sg:city":"Madrid",
    "sg:orig_category":"Electrodom\u00c9sticos (al Por Menor)",
    "sg:phone":"+34 915 25 14 35",
    "sg:postcode":"28025",
    "sg:province":"Madrid",
    "wof:name":"Electrocavi S.l.",
    "wof:placetype":"venue"
},
  "geometry": {"coordinates":[-3.7282073498,40.3851280212],"type":"Point"}
}