{
  "type": "Feature",
  "properties": {
    "iso:country":"ES",
    "sg:address":"Urb Los Llanos, S/n",
    "sg:city":"Alhendin",
    "sg:orig_category":"Inmobiliaria (agencias)",
    "sg:phone":"+34 958 57 35 41",
    "sg:postcode":"18620",
    "sg:province":"Granada",
    "wof:name":"Cartuja Inmobiliaria S.a.",
    "wof:placetype":"venue"
},
  "geometry": {"coordinates":[-3.6293690205,37.12733078],"type":"Point"}
}