{
  "type": "Feature",
  "properties": {
    "addr:full":"Avda Lola Flores, S/n Jerez De La Frontera C\u00e1diz 11405",
    "addr:housenumber":"s",
    "addr:postcode":"11405",
    "addr:street":"Avda Lola Flores;/ N",
    "iso:country":"ES",
    "sg:address":"Avda Lola Flores, S/n",
    "sg:city":"Jerez De La Frontera",
    "sg:orig_category":"Art\u00cdculos De Regalo (al Por Menor)",
    "sg:phone":"+34 956 33 98 91",
    "sg:postcode":"11405",
    "sg:province":"C\u00e1diz",
    "wof:name":"Ruiz Oliva Eugenio",
    "wof:placetype":"venue"
},
  "geometry": {"coordinates":[-6.1133828163,36.6920776367],"type":"Point"}
}