{
  "type": "Feature",
  "properties": {
    "addr:full":"Calle de Iglesia, S/n Golpejas Salamanca 37170",
    "addr:housenumber":"s / n",
    "addr:postcode":"37170",
    "addr:street":"Calle De Iglesia",
    "iso:country":"ES",
    "sg:address":"Calle de Iglesia, S/n",
    "sg:city":"Golpejas",
    "sg:orig_category":"Iglesia Cat\u00d3lica",
    "sg:phone":"+34 923 32 00 02",
    "sg:postcode":"37170",
    "sg:province":"Salamanca",
    "wof:name":"Parroquia De San Nicolas",
    "wof:placetype":"venue"
},
  "geometry": {"coordinates":[-5.9087510109,40.9988441467],"type":"Point"}
}