{
  "type": "Feature",
  "properties": {
    "addr:full":"G.v. Pau Casals, 178 Suredes D'en Mairo-grecs-muntanyeta Girona 17480",
    "addr:housenumber":"178",
    "addr:postcode":"17480",
    "addr:street":"Suredes D'En Mairo-Grecs-Muntanyeta",
    "iso:country":"ES",
    "sg:address":"G.v. Pau Casals, 178",
    "sg:city":"Suredes D'en Mairo-grecs-muntanyeta",
    "sg:orig_category":"Asociaciones Y Clubs Deportivos",
    "sg:phone":"+34 972 15 20 09",
    "sg:postcode":"17480",
    "sg:province":"Girona",
    "wof:name":"Shoes Gestion S.a.",
    "wof:placetype":"venue"
},
  "geometry": {"coordinates":[2.8156359196,41.9840202332],"type":"Point"}
}