{
  "type": "Feature",
  "properties": {
    "addr:full":"Barr Pozas (las), S/n Castillo Cantabria 39193",
    "addr:postcode":"39193",
    "addr:street":"Las S / N",
    "iso:country":"ES",
    "sg:address":"Barr Pozas (las), S/n",
    "sg:city":"Castillo",
    "sg:orig_category":"Chapister\u00cda",
    "sg:phone":"+34 942 67 49 98",
    "sg:postcode":"39193",
    "sg:province":"Cantabria",
    "wof:name":"Sierra Herrero Juan Jose",
    "wof:placetype":"venue"
},
  "geometry": {"coordinates":[-3.5410709381,43.4605445862],"type":"Point"}
}