{
  "type": "Feature",
  "properties": {
    "addr:full":"Calle de Eduardo Romero, 1 Meliana Valencia 46133",
    "addr:housenumber":"1",
    "addr:postcode":"46133",
    "addr:street":"Calle De Eduardo Romero",
    "iso:country":"ES",
    "sg:address":"Calle de Eduardo Romero, 1",
    "sg:city":"Meliana",
    "sg:orig_category":"Importaci\u00d3n",
    "sg:phone":"+34 961 48 08 19",
    "sg:postcode":"46133",
    "sg:province":"Valencia",
    "wof:name":"Moran Chele Edgar Leonardo",
    "wof:placetype":"venue"
},
  "geometry": {"coordinates":[-0.3474259973,39.5288391113],"type":"Point"}
}