{
  "type": "Feature",
  "properties": {
    "iso:country":"ES",
    "sg:address":"Calle de Calvario, 91",
    "sg:city":"Chiclana De La Frontera",
    "sg:orig_category":"Molduras, Junquillos, Listones Y Molduras Perforadas",
    "sg:phone":"+34 956 53 14 04",
    "sg:postcode":"11130",
    "sg:province":"C\u00e1diz",
    "wof:name":"Butron Fernandez Agustin",
    "wof:placetype":"venue"
},
  "geometry": {"coordinates":[-6.1392021179,36.4209861755],"type":"Point"}
}