{
  "type": "Feature",
  "properties": {
    "addr:full":"Partida Torres, 14 Torres Alicante 03570",
    "addr:housenumber":"14",
    "addr:postcode":"03570",
    "addr:street":"Partida Torres",
    "iso:country":"ES",
    "sg:address":"Partida Torres, 14",
    "sg:city":"Torres",
    "sg:orig_category":"Estudios Y Construcci\u00d3n De Acuarios Y Viveros",
    "sg:phone":"+34 966 81 03 28",
    "sg:postcode":"03570",
    "sg:province":"Alicante",
    "wof:name":"Gramamed S.l.",
    "wof:placetype":"venue"
},
  "geometry": {"coordinates":[-0.2327190042,38.505821228],"type":"Point"}
}