{
  "type": "Feature",
  "properties": {
    "iso:country":"ES",
    "sg:address":"Carr Gran, 2",
    "sg:city":"Garriguella",
    "sg:orig_category":"Iglesia Cat\u00d3lica",
    "sg:phone":"+34 972 53 01 06",
    "sg:postcode":"17780",
    "sg:province":"Girona",
    "wof:name":"Bisbat De Girona",
    "wof:placetype":"venue"
},
  "geometry": {"coordinates":[3.0643210411,42.3423805237],"type":"Point"}
}