{
  "type": "Feature",
  "properties": {
    "addr:full":"Carr Vallcalent, 22 Lleida Lleida 25006",
    "addr:housenumber":"22",
    "addr:postcode":"25006",
    "addr:street":"Carr Vallcalent",
    "iso:country":"ES",
    "sg:address":"Carr Vallcalent, 22",
    "sg:city":"Lleida",
    "sg:orig_category":"Fabricaci\u00d3n De Juguetes Autom\u00c1ticos",
    "sg:phone":"+34 973 27 55 30",
    "sg:postcode":"25006",
    "sg:province":"Lleida",
    "sg:website":"www.paginasamarillas.es",
    "wof:name":"Jomesa S.l.",
    "wof:placetype":"venue"
},
  "geometry": {"coordinates":[0.6183789968,41.6175498962],"type":"Point"}
}