{
  "type": "Feature",
  "properties": {
    "addr:full":"Carrer de Mossen A. Rodamilans, 120 Terrassa Barcelona 08222",
    "addr:housenumber":"120",
    "addr:postcode":"08222",
    "addr:street":"Carrer De Mossen A. Rodamilans",
    "iso:country":"ES",
    "sg:address":"Carrer de Mossen A. Rodamilans, 120",
    "sg:city":"Terrassa",
    "sg:orig_category":"Venta, Instalaci\u00d3n De Sistemas De Alarmas Y Vigilancia",
    "sg:phone":"+34 937 86 49 59",
    "sg:postcode":"08222",
    "sg:province":"Barcelona",
    "wof:name":"Argemi Ribas Eduard",
    "wof:placetype":"venue"
},
  "geometry": {"coordinates":[2.0293328762,41.5621185303],"type":"Point"}
}