{
  "type": "Feature",
  "properties": {
    "iso:country":"ES",
    "sg:address":"Calle de San Vicente, 82",
    "sg:city":"Borriol",
    "sg:orig_category":"Promotores Constructores",
    "sg:phone":"+34 964 32 15 45",
    "sg:postcode":"12190",
    "sg:province":"Castell\u00f3n",
    "wof:name":"Construcciones Proborriol S.l.",
    "wof:placetype":"venue"
},
  "geometry": {"coordinates":[-0.0679090023,40.0418968201],"type":"Point"}
}