{
  "type": "Feature",
  "properties": {
    "iso:country":"ES",
    "sg:address":"Av Lluis Companys, 29",
    "sg:city":"S. Cugat Valles",
    "sg:orig_category":"Comercio De Mobiliario De Oficina",
    "sg:phone":"+34 935 89 34 09",
    "sg:postcode":"08172",
    "sg:province":"Barcelona",
    "wof:name":"Fernandez Perez Miguel",
    "wof:placetype":"venue"
},
  "geometry": {"coordinates":[2.0793809891,41.4722671509],"type":"Point"}
}