{
  "type": "Feature",
  "properties": {
    "addr:full":"Pase Esperanza, 16 Madrid Madrid 28005",
    "addr:housenumber":"16",
    "addr:postcode":"madrid;28005",
    "addr:street":"Esperanza",
    "iso:country":"ES",
    "sg:address":"Pase Esperanza, 16",
    "sg:city":"Madrid",
    "sg:orig_category":"Contenedores (mercanc\u00cdas)",
    "sg:phone":"+34 915 17 90 91",
    "sg:postcode":"28005",
    "sg:province":"Madrid",
    "wof:name":"Comercial Kin Cosmetics S.l",
    "wof:placetype":"venue"
},
  "geometry": {"coordinates":[-3.7031450272,40.3988723755],"type":"Point"}
}