{
  "type": "Feature",
  "properties": {
    "addr:full":"Av Sarria, 35 Barcelona Barcelona 08029",
    "addr:housenumber":"35",
    "addr:postcode":"08029",
    "addr:street":"Av Sarria",
    "iso:country":"ES",
    "sg:address":"Av Sarria, 35",
    "sg:city":"Barcelona",
    "sg:orig_category":"Administradores De Bienes Y Delegados De Comunidades De Propietarios",
    "sg:phone":"+34 934 19 78 74",
    "sg:postcode":"08029",
    "sg:province":"Barcelona",
    "wof:name":"Administracion De Fincas Trave S. L.",
    "wof:placetype":"venue"
},
  "geometry": {"coordinates":[2.1445336342,41.3903579712],"type":"Point"}
}