{
  "type": "Feature",
  "properties": {
    "iso:country":"ES",
    "sg:address":"La Plaza, S/n",
    "sg:city":"Sta. Eulalia Oscos",
    "sg:orig_category":"Agricultores, Agricultores",
    "sg:phone":"+34 985 62 62 02",
    "sg:postcode":"33776",
    "sg:province":"Asturias",
    "wof:name":"Ventoso Agricola S.l.",
    "wof:placetype":"venue"
},
  "geometry": {"coordinates":[-7.0293540955,43.4368476868],"type":"Point"}
}