{
  "type": "Feature",
  "properties": {
    "addr:full":"Calle de Vidal De Blanes, 34 Valencia Valencia 46024",
    "addr:housenumber":"34",
    "addr:postcode":"46024",
    "addr:street":"Calle De Vidal De Blanes",
    "iso:country":"ES",
    "sg:address":"Calle de Vidal De Blanes, 34",
    "sg:city":"Valencia",
    "sg:orig_category":"Centros Empresariales",
    "sg:phone":"+34 963 30 32 17",
    "sg:postcode":"46024",
    "sg:province":"Valencia",
    "wof:name":"Gestion Y Servicios Maritimos Valencia S.l",
    "wof:placetype":"venue"
},
  "geometry": {"coordinates":[-0.3344910145,39.4593353271],"type":"Point"}
}