{
  "type": "Feature",
  "properties": {
    "iso:country":"ES",
    "sg:address":"Calle de Luises, 25",
    "sg:city":"Donostia-san Sebastian",
    "sg:orig_category":"Electricidad: Instaladores",
    "sg:phone":"+34 943 29 03 62",
    "sg:postcode":"20015",
    "sg:province":"Guip\u00f9zcoa",
    "wof:name":"Fernandez De Bobadilla Carasusan Manuel",
    "wof:placetype":"venue"
},
  "geometry": {"coordinates":[-1.9545400143,43.3192214966],"type":"Point"}
}