{
  "type": "Feature",
  "properties": {
    "iso:country":"ES",
    "sg:address":"Carrer de Treball, 243",
    "sg:city":"Barcelona",
    "sg:orig_category":"Animales (al Por Menor)",
    "sg:phone":"+34 933 14 21 60",
    "sg:postcode":"08020",
    "sg:province":"Barcelona",
    "wof:name":"Lopez Gracia Maria Rosa",
    "wof:placetype":"venue"
},
  "geometry": {"coordinates":[2.1988060474,41.418132782],"type":"Point"}
}