{
  "type": "Feature",
  "properties": {
    "iso:country":"ES",
    "sg:address":"Calle de Ingeniero Garcia Pimentel, 21",
    "sg:city":"Martos",
    "sg:orig_category":"Alimentaci\u00d3n General (al Por Menor)",
    "sg:phone":"+34 953 70 47 48",
    "sg:postcode":"23600",
    "sg:province":"Ja\u00e9n",
    "wof:name":"Ruano Moreno Maria Jose",
    "wof:placetype":"venue"
},
  "geometry": {"coordinates":[-3.9699420929,37.7146949768],"type":"Point"}
}