{
  "type": "Feature",
  "properties": {
    "addr:full":"Carrer de Sant Josep, 25 Arenys Munt Barcelona 08358",
    "addr:housenumber":"25",
    "addr:postcode":"08358",
    "addr:street":"Carrer De Sant Josep;Munt Barcelona",
    "iso:country":"ES",
    "sg:address":"Carrer de Sant Josep, 25",
    "sg:city":"Arenys Munt",
    "sg:orig_category":"Ferreter\u00cda (diversos)",
    "sg:phone":"+34 937 95 13 94",
    "sg:postcode":"08358",
    "sg:province":"Barcelona",
    "wof:name":"Torras Salmeron Manuel",
    "wof:placetype":"venue"
},
  "geometry": {"coordinates":[2.541369915,41.6100692749],"type":"Point"}
}