{
  "type": "Feature",
  "properties": {
    "iso:country":"ES",
    "sg:address":"Calle de Virrey Pedro De Aragon, 1",
    "sg:city":"Cordoba",
    "sg:orig_category":"Asesor\u00cda Fiscal Y Jur\u00cddica",
    "sg:phone":"+34 957 27 46 74",
    "sg:postcode":"14011",
    "sg:province":"C\u00f3rdoba",
    "wof:name":"Carmona Latorre Ana",
    "wof:placetype":"venue"
},
  "geometry": {"coordinates":[-4.7920541763,37.892326355],"type":"Point"}
}