{
  "type": "Feature",
  "properties": {
    "addr:full":"Calle de Langaran, 1 Bilbao Vizcaya 48004",
    "addr:housenumber":"1",
    "addr:postcode":"48004",
    "addr:street":"Calle De Langaran",
    "iso:country":"ES",
    "sg:address":"Calle de Langaran, 1",
    "sg:city":"Bilbao",
    "sg:orig_category":"Carnicer\u00cdas, Carnicer\u00cdas",
    "sg:phone":"+34 944 11 74 56",
    "sg:postcode":"48004",
    "sg:province":"Vizcaya",
    "wof:name":"Carnicas Pam S.l",
    "wof:placetype":"venue"
},
  "geometry": {"coordinates":[-2.8980369568,43.2590179443],"type":"Point"}
}