{
  "type": "Feature",
  "properties": {
    "iso:country":"ES",
    "sg:address":"Avda Carlos Iii, 292",
    "sg:city":"Campillo Del Moro",
    "sg:orig_category":"Ropa Para Se\u00d1oras Y Caballeros (al Por Menor)",
    "sg:phone":"+34 950 34 88 17",
    "sg:postcode":"04720",
    "sg:province":"Almer\u00eda",
    "wof:name":"Ferrero Espejo Elena",
    "wof:placetype":"venue"
},
  "geometry": {"coordinates":[-2.5741510391,36.8138160706],"type":"Point"}
}