{
  "type": "Feature",
  "properties": {
    "iso:country":"ES",
    "sg:address":"Carrer de Tecnica, 30",
    "sg:city":"S. Andreu Barca",
    "sg:orig_category":"Negocio De Materiales De Construcci\u00d3n",
    "sg:phone":"+34 936 82 32 50",
    "sg:postcode":"08740",
    "sg:province":"Barcelona",
    "wof:name":"Aquaflex S.l.",
    "wof:placetype":"venue"
},
  "geometry": {"coordinates":[2.1699187756,41.3879165649],"type":"Point"}
}