{
  "type": "Feature",
  "properties": {
    "iso:country":"ES",
    "sg:address":"Avda Carlos I De, 12",
    "sg:city":"Donostia-san Sebastian",
    "sg:orig_category":"Reposter\u00cdas",
    "sg:phone":"+34 943 46 41 07",
    "sg:postcode":"20011",
    "sg:province":"Guip\u00f9zcoa",
    "wof:name":"Gabirondo Balda Itziar",
    "wof:placetype":"venue"
},
  "geometry": {"coordinates":[-1.9793889523,43.3050422668],"type":"Point"}
}