{
  "type": "Feature",
  "properties": {
    "iso:country":"ES",
    "sg:address":"Calle de Rosa De Los Vientos, 36",
    "sg:city":"Conil De La Frontera",
    "sg:orig_category":"Explotaci\u00d3n De Canteras",
    "sg:phone":"+34 956 44 08 71",
    "sg:postcode":"11140",
    "sg:province":"C\u00e1diz",
    "wof:name":"Hijos De Juan Moreno Amaya S.l.",
    "wof:placetype":"venue"
},
  "geometry": {"coordinates":[-6.0884847641,36.2796669006],"type":"Point"}
}