{
  "type": "Feature",
  "properties": {
    "iso:country":"ES",
    "sg:address":"Carrer de L'equador, 22",
    "sg:city":"Barcelona",
    "sg:orig_category":"Doctores En Medicina",
    "sg:phone":"+34 933 22 35 20",
    "sg:postcode":"08029",
    "sg:province":"Barcelona",
    "wof:name":"Gimenez Gaibar Antonio",
    "wof:placetype":"venue"
},
  "geometry": {"coordinates":[2.14026618,41.3857765198],"type":"Point"}
}