{
  "type": "Feature",
  "properties": {
    "addr:full":"Alam Urquijo, 27 Bilbao Vizcaya 48008",
    "addr:housenumber":"27",
    "addr:postcode":"48008",
    "addr:street":"Alam Urquijo",
    "iso:country":"ES",
    "sg:address":"Alam Urquijo, 27",
    "sg:city":"Bilbao",
    "sg:orig_category":"Reposter\u00cdas",
    "sg:phone":"+34 944 44 46 01",
    "sg:postcode":"48008",
    "sg:province":"Vizcaya",
    "wof:name":"Rosa Marin Garcia Gomez (panaderia Lemona)",
    "wof:placetype":"venue"
},
  "geometry": {"coordinates":[-2.9336299896,43.2595062256],"type":"Point"}
}