{
  "type": "Feature",
  "properties": {
    "iso:country":"ES",
    "sg:address":"Carrer de Lluis Companys, 7",
    "sg:city":"Viladecans",
    "sg:orig_category":"Muebles, Minoristas",
    "sg:phone":"+34 936 47 01 09",
    "sg:postcode":"08840",
    "sg:province":"Barcelona",
    "wof:name":"Alvarez Gelado Sergio Daniel",
    "wof:placetype":"venue"
},
  "geometry": {"coordinates":[2.0102720261,41.3159179688],"type":"Point"}
}