{
  "type": "Feature",
  "properties": {
    "addr:full":"Pase Luis Cortes, 1 Salamanca Salamanca 37008",
    "addr:housenumber":"1",
    "addr:postcode":"37008",
    "addr:street":"Luis Cortes",
    "iso:country":"ES",
    "sg:address":"Pase Luis Cortes, 1",
    "sg:city":"Salamanca",
    "sg:orig_category":"Art\u00cdculos Funerarios (al Por Menor)",
    "sg:phone":"+34 923 19 39 59",
    "sg:postcode":"37008",
    "sg:province":"Salamanca",
    "wof:name":"Servicios Funerarios Virgen De La Vega S.l.",
    "wof:placetype":"venue"
},
  "geometry": {"coordinates":[-5.6805381775,40.9568099976],"type":"Point"}
}