{
  "type": "Feature",
  "properties": {
    "iso:country":"ES",
    "sg:address":"Calle de San Mariano, 27",
    "sg:city":"Madrid",
    "sg:orig_category":"Estudios, Instalaci\u00d3n De Climatizaci\u00d3n",
    "sg:phone":"+34 913 20 59 27",
    "sg:postcode":"28022",
    "sg:province":"Madrid",
    "wof:name":"Reparaciones Electronicas Y Climatizacio",
    "wof:placetype":"venue"
},
  "geometry": {"coordinates":[-3.6125459671,40.4431495667],"type":"Point"}
}