{
  "type": "Feature",
  "properties": {
    "addr:full":"Calle de Carmen, 4 Madrid Madrid 28013",
    "addr:housenumber":"4",
    "addr:postcode":"28013",
    "addr:street":"Calle De Carmen",
    "iso:country":"ES",
    "sg:address":"Calle de Carmen, 4",
    "sg:city":"Madrid",
    "sg:orig_category":"Caf\u00c9s, Bares, Cervecer\u00cdas",
    "sg:phone":"+34 915 22 59 05",
    "sg:postcode":"28013",
    "sg:province":"Madrid",
    "wof:name":"Industrial Hostelera S. A.",
    "wof:placetype":"venue"
},
  "geometry": {"coordinates":[-3.7036318779,40.4174118042],"type":"Point"}
}