{
  "type": "Feature",
  "properties": {
    "addr:full":"Calle de Comendador Salda\u00d1a, 1 Bembibre Le\u00f3n 24300",
    "addr:housenumber":"1",
    "addr:postcode":"24300",
    "addr:street":"Calle De Comendador Saldan\u0303A;Leo\u0301N",
    "iso:country":"ES",
    "sg:address":"Calle de Comendador Salda\u00d1a, 1",
    "sg:city":"Bembibre",
    "sg:classifiers":[
        {
            "category":"Autos & Motor Vehicles",
            "subcategory":"Automobile Sales",
            "type":"Retail Goods"
        }
    ],
    "sg:phone":"+34 987 51 03 65",
    "sg:postcode":"24300",
    "sg:province":"Le\u00f3n",
    "wof:name":"Gonzalez Arias Augusto",
    "wof:placetype":"venue"
},
  "geometry": {"coordinates":[-6.4204716682,42.6170387268],"type":"Point"}
}