{
  "type": "Feature",
  "properties": {
    "addr:full":"Calle de Ca\u00d1as, 1 Ciudad Real Ciudad Real 13004",
    "addr:housenumber":"1",
    "addr:postcode":"13004",
    "addr:street":"Calle De Can\u0303As",
    "iso:country":"ES",
    "sg:address":"Calle de Ca\u00d1as, 1",
    "sg:city":"Ciudad Real",
    "sg:orig_category":"Tintes (fabricaci\u00d3n, Al Por Mayor)",
    "sg:phone":"+34 926 22 70 40",
    "sg:postcode":"13004",
    "sg:province":"Ciudad Real",
    "wof:name":"Usero Serrano Maria De Gracia",
    "wof:placetype":"venue"
},
  "geometry": {"coordinates":[-3.9217391014,38.9856796265],"type":"Point"}
}