{
  "type": "Feature",
  "properties": {
    "addr:full":"Carr Carme, 50 Lleida Lleida 25007",
    "addr:housenumber":"50",
    "addr:postcode":"25007",
    "addr:street":"Carr Carme",
    "iso:country":"ES",
    "sg:address":"Carr Carme, 50",
    "sg:city":"Lleida",
    "sg:orig_category":"Lencer\u00cda Femenina, Corseter\u00cda, Trajes De Ba\u00d1o (al Por Menor)",
    "sg:phone":"+34 973 23 67 91",
    "sg:postcode":"25007",
    "sg:province":"Lleida",
    "wof:name":"Almacenes Urgell S.l.",
    "wof:placetype":"venue"
},
  "geometry": {"coordinates":[0.6300917864,41.618598938],"type":"Point"}
}