{
  "type": "Feature",
  "properties": {
    "iso:country":"ES",
    "sg:address":"Calle de Machaquito, 20",
    "sg:city":"Cordoba",
    "sg:orig_category":"Guarder\u00cdas",
    "sg:phone":"+34 957 45 26 57",
    "sg:postcode":"14005",
    "sg:province":"C\u00f3rdoba",
    "wof:name":"Alvarado Parron Maria Victoria",
    "wof:placetype":"venue"
},
  "geometry": {"coordinates":[-4.7958345413,37.8822631836],"type":"Point"}
}