{
  "type": "Feature",
  "properties": {
    "iso:country":"ES",
    "sg:address":"Carrer de L'agricultura, 145",
    "sg:city":"Barcelona",
    "sg:orig_category":"Imprenta",
    "sg:phone":"+34 933 03 37 20",
    "sg:postcode":"08019",
    "sg:province":"Barcelona",
    "wof:name":"Hernandez Vizcarra Josep",
    "wof:placetype":"venue"
},
  "geometry": {"coordinates":[2.206594944,41.4140930176],"type":"Point"}
}