{
  "type": "Feature",
  "properties": {
    "addr:full":"Rond Industria (de La), S/n Huesca Huesca 22006",
    "addr:housenumber":"s",
    "addr:postcode":"22006",
    "addr:street":"Rond;/ N",
    "iso:country":"ES",
    "sg:address":"Rond Industria (de La), S/n",
    "sg:city":"Huesca",
    "sg:orig_category":"Transportes En Volquetes Basculantes",
    "sg:phone":"+34 974 24 52 37",
    "sg:postcode":"22006",
    "sg:province":"Huesca",
    "wof:name":"Araujo Fernandez Manuel",
    "wof:placetype":"venue"
},
  "geometry": {"coordinates":[-0.3842526972,42.1665077209],"type":"Point"}
}