{
  "type": "Feature",
  "properties": {
    "iso:country":"ES",
    "sg:address":"Calle de Fray Luis Urbano, 2",
    "sg:city":"Zaragoza",
    "sg:orig_category":"Limpieza De Alfombras",
    "sg:phone":"+34 976 20 01 23",
    "sg:postcode":"50002",
    "sg:province":"Zaragoza",
    "wof:name":"Minueval S.l.",
    "wof:placetype":"venue"
},
  "geometry": {"coordinates":[-0.8591989875,41.6449584961],"type":"Point"}
}