{
  "type": "Feature",
  "properties": {
    "iso:country":"ES",
    "sg:address":"Calle de Poniente, S/n",
    "sg:city":"Fuente Maestre",
    "sg:orig_category":"Tapicer\u00cdas",
    "sg:phone":"+34 924 53 13 49",
    "sg:postcode":"06360",
    "sg:province":"Badajoz",
    "wof:name":"Lopez Llamazares Ramon",
    "wof:placetype":"venue"
},
  "geometry": {"coordinates":[-6.4515385628,38.5253257751],"type":"Point"}
}