{
  "type": "Feature",
  "properties": {
    "iso:country":"ES",
    "sg:address":"Calle de Concepcion Arenal, 7",
    "sg:city":"Puerto",
    "sg:orig_category":"Zapatos (al Por Menor)",
    "sg:phone":"+34 962 67 01 55",
    "sg:postcode":"46520",
    "sg:province":"Valencia",
    "wof:name":"Calzados Biosca S.a.",
    "wof:placetype":"venue"
},
  "geometry": {"coordinates":[-0.2187777013,39.6596870422],"type":"Point"}
}