{
  "type": "Feature",
  "properties": {
    "addr:full":"Calle de Santa Teresa De Jesus, 45 Talavera Reina Toledo 45600",
    "addr:housenumber":"45",
    "addr:postcode":"45600",
    "addr:street":"Calle De Santa Teresa De Jesus",
    "iso:country":"ES",
    "sg:address":"Calle de Santa Teresa De Jesus, 45",
    "sg:city":"Talavera Reina",
    "sg:orig_category":"Fabricaci\u00d3n, Distribuci\u00d3n De Material Para La Climatizaci\u00d3n, Aireaci\u00d3n Y Ventilaci\u00d3n",
    "sg:phone":"+34 925 80 28 59",
    "sg:postcode":"45600",
    "sg:province":"Toledo",
    "wof:name":"Peveceka S.l.",
    "wof:placetype":"venue"
},
  "geometry": {"coordinates":[-4.8280339241,39.9656028748],"type":"Point"}
}