{
  "type": "Feature",
  "properties": {
    "iso:country":"ES",
    "sg:address":"Rua Arcebispo Xelmirez, 13",
    "sg:city":"Vilagarcia",
    "sg:orig_category":"Agencias Y Agentes Comerciales, Representantes",
    "sg:phone":"+34 986 50 19 14",
    "sg:postcode":"36600",
    "sg:province":"Pontevedra",
    "wof:name":"Santos Cerdeiri\u00f1a Luis",
    "wof:placetype":"venue"
},
  "geometry": {"coordinates":[-8.7646608353,42.5925064087],"type":"Point"}
}