{
  "type": "Feature",
  "properties": {
    "iso:country":"ES",
    "sg:address":"Moble, 14",
    "sg:city":"Beniparrell",
    "sg:orig_category":"Limpieza Con Chorro De Arena Y Con Granalla, Pulido",
    "sg:phone":"+34 961 21 20 11",
    "sg:postcode":"46469",
    "sg:province":"Valencia",
    "wof:name":"Decoraciones Esteban Belda S.l.",
    "wof:placetype":"venue"
},
  "geometry": {"coordinates":[-0.4133599997,39.3861732483],"type":"Point"}
}