{
  "type": "Feature",
  "properties": {
    "addr:full":"Av Roma, 10 Barcelona Barcelona 08015",
    "addr:housenumber":"10",
    "addr:postcode":"08015",
    "addr:street":"Av Roma",
    "iso:country":"ES",
    "sg:address":"Av Roma, 10",
    "sg:city":"Barcelona",
    "sg:orig_category":"Ingenier\u00cda, Centros De Estudios (diversos)",
    "sg:phone":"+34 932 26 88 44",
    "sg:postcode":"08015",
    "sg:province":"Barcelona",
    "sg:website":"www.sba.es",
    "wof:name":"S.b. Ambiaudit S.l.",
    "wof:placetype":"venue"
},
  "geometry": {"coordinates":[2.1435410976,41.3804855347],"type":"Point"}
}