{
  "type": "Feature",
  "properties": {
    "iso:country":"ES",
    "sg:address":"Calle de Molino, 3",
    "sg:city":"Zeneta",
    "sg:orig_category":"Arboricultura Y Producci\u00d3n De Frutas",
    "sg:phone":"+34 968 85 41 96",
    "sg:postcode":"30588",
    "sg:province":"Murcia",
    "wof:name":"Palacios Mu\u00f1oz Murcia S.l.",
    "wof:placetype":"venue"
},
  "geometry": {"coordinates":[-0.9983580112,38.0101165771],"type":"Point"}
}