{
  "type": "Feature",
  "properties": {
    "iso:country":"ES",
    "sg:address":"Calle de Pedreguer, 11",
    "sg:city":"Denia",
    "sg:orig_category":"Quincaller\u00cda (al Por Menor)",
    "sg:phone":"+34 965 78 08 51",
    "sg:postcode":"03700",
    "sg:province":"Alicante",
    "wof:name":"Coloma Mulet Francisco",
    "wof:placetype":"venue"
},
  "geometry": {"coordinates":[0.1068999991,38.8356018066],"type":"Point"}
}