{
  "type": "Feature",
  "properties": {
    "addr:full":"Calle de Pradillo, S/n Hontanaya Cuenca 16416",
    "addr:housenumber":"s",
    "addr:postcode":"16416",
    "addr:street":"Calle De Pradillo;/ N Hontanaya",
    "iso:country":"ES",
    "sg:address":"Calle de Pradillo, S/n",
    "sg:city":"Hontanaya",
    "sg:orig_category":"Productores Recolectores, Venta Directa De Vinos",
    "sg:phone":"+34 969 12 91 62",
    "sg:postcode":"16416",
    "sg:province":"Cuenca",
    "wof:name":"Cooperativa Del Socorro",
    "wof:placetype":"venue"
},
  "geometry": {"coordinates":[-2.8339290619,39.7142601013],"type":"Point"}
}