{
  "type": "Feature",
  "properties": {
    "iso:country":"ES",
    "sg:address":"Carrer de Llu\u00c7anes, 8",
    "sg:city":"Barcelona",
    "sg:orig_category":"Doctores En Medicina",
    "sg:phone":"+34 932 12 45 07",
    "sg:postcode":"08022",
    "sg:province":"Barcelona",
    "wof:name":"Cruz Armstrong Jose Ramon De La",
    "wof:placetype":"venue"
},
  "geometry": {"coordinates":[2.1333088875,41.4073257446],"type":"Point"}
}