{
  "type": "Feature",
  "properties": {
    "iso:country":"ES",
    "sg:address":"Calle de Iglesia (de La), 8",
    "sg:city":"Ceuti",
    "sg:orig_category":"Empresas De Demolici\u00d3n",
    "sg:phone":"+34 968 69 32 48",
    "sg:postcode":"30562",
    "sg:province":"Murcia",
    "wof:name":"Angajunior S.l.",
    "wof:placetype":"venue"
},
  "geometry": {"coordinates":[-1.2695167065,38.0791358948],"type":"Point"}
}