{
  "type": "Feature",
  "properties": {
    "iso:country":"ES",
    "sg:address":"Ctra Zamora, Km. 0011,0",
    "sg:city":"Onzonilla",
    "sg:orig_category":"M\u00c1rmoles, Granitos Y Piedras Naturales",
    "sg:phone":"+34 987 28 20 04",
    "sg:postcode":"24231",
    "sg:province":"Le\u00f3n",
    "sg:website":"www.paginasamarillas.es",
    "wof:name":"Leon Granitos S.l.",
    "wof:placetype":"venue"
},
  "geometry": {"coordinates":[-5.5846152306,42.4846572876],"type":"Point"}
}