{
  "type": "Feature",
  "properties": {
    "iso:country":"ES",
    "sg:address":"Calle de Hernando De Zafra, 4",
    "sg:city":"Melilla",
    "sg:orig_category":"Abogados",
    "sg:phone":"+34 952 67 00 02",
    "sg:postcode":"52003",
    "sg:province":"Melilla",
    "wof:name":"Cabo Tuero Antonio Jose",
    "wof:placetype":"venue"
},
  "geometry": {"coordinates":[-2.9469799995,35.2918052673],"type":"Point"}
}