{
  "type": "Feature",
  "properties": {
    "addr:full":"Autovia De Levante, Km. 0052,9 Villena Alicante 03400",
    "addr:postcode":"03400",
    "addr:street":"Autovia De Levante Km. 0052,9",
    "iso:country":"ES",
    "sg:address":"Autovia De Levante, Km. 0052,9",
    "sg:city":"Villena",
    "sg:orig_category":"Cristaler\u00cdas",
    "sg:phone":"+34 965 34 83 87",
    "sg:postcode":"03400",
    "sg:province":"Alicante",
    "sg:website":"www.vidriare.com",
    "wof:name":"Vidriarte S.l.",
    "wof:placetype":"venue"
},
  "geometry": {"coordinates":[-0.8584110141,38.6305541992],"type":"Point"}
}