{
  "type": "Feature",
  "properties": {
    "addr:full":"Rua Espa\u00d1oleto, 33 Ferrol La Coru\u00f1a 15402",
    "addr:housenumber":"33",
    "addr:postcode":"15402",
    "addr:street":"Rua Espan\u0303Oleto;La Corun\u0303A",
    "iso:country":"ES",
    "sg:address":"Rua Espa\u00d1oleto, 33",
    "sg:city":"Ferrol",
    "sg:orig_category":"Cajas De Ahorro",
    "sg:phone":"+34 981 33 30 38",
    "sg:postcode":"15402",
    "sg:province":"La Coru\u00f1a",
    "wof:name":"Caixa De Aforros De Vigo Ourense E Pontevedra",
    "wof:placetype":"venue"
},
  "geometry": {"coordinates":[-8.2265586853,43.4844436646],"type":"Point"}
}