{
  "type": "Feature",
  "properties": {
    "addr:full":"Carrer de Belgica, 7 Coveta Fuma Alicante 03560",
    "addr:housenumber":"7",
    "addr:postcode":"03560",
    "addr:street":"Carrer De Belgica",
    "iso:country":"ES",
    "sg:address":"Carrer de Belgica, 7",
    "sg:city":"Coveta Fuma",
    "sg:orig_category":"Molduras, Junquillos, Listones Y Molduras Perforadas",
    "sg:phone":"+34 965 63 83 07",
    "sg:postcode":"03560",
    "sg:province":"Alicante",
    "wof:name":"Mallen  Steven",
    "wof:placetype":"venue"
},
  "geometry": {"coordinates":[-0.3617269993,38.4501953125],"type":"Point"}
}