{
  "type": "Feature",
  "properties": {
    "iso:country":"ES",
    "sg:address":"Calle de Calvo Sotelo, 16",
    "sg:city":"Logro\u00f1o",
    "sg:orig_category":"Confecci\u00d3n De Trajes Para Se\u00d1oras",
    "sg:phone":"+34 941 24 21 92",
    "sg:postcode":"26003",
    "sg:province":"La Rioja",
    "wof:name":"Vidrio Galicia S.l.",
    "wof:placetype":"venue"
},
  "geometry": {"coordinates":[-2.4428899288,42.4638938904],"type":"Point"}
}