{
  "type": "Feature",
  "properties": {
    "addr:full":"Calle de Parroco Juan Perez, 20 Carrizal Las Palmas 35240",
    "addr:housenumber":"20",
    "addr:postcode":"35240",
    "addr:street":"Calle De Parroco Juan Perez",
    "iso:country":"ES",
    "sg:address":"Calle de Parroco Juan Perez, 20",
    "sg:city":"Carrizal",
    "sg:orig_category":"Centros Empresariales",
    "sg:phone":"+34 928 78 34 10",
    "sg:postcode":"35240",
    "sg:province":"Las Palmas",
    "wof:name":"Macrise Pinturas S.l",
    "wof:placetype":"venue"
},
  "geometry": {"coordinates":[-15.4111309052,27.9141216278],"type":"Point"}
}