{
  "type": "Feature",
  "properties": {
    "addr:full":"Carrer de Berruguete, 116 Barcelona Barcelona 08035",
    "addr:housenumber":"116",
    "addr:postcode":"08035",
    "addr:street":"Carrer De Berruguete",
    "iso:country":"ES",
    "sg:address":"Carrer de Berruguete, 116",
    "sg:city":"Barcelona",
    "sg:orig_category":"Agencias Y Asesores De Publicidad",
    "sg:phone":"+34 934 28 90 00",
    "sg:postcode":"08035",
    "sg:province":"Barcelona",
    "wof:name":"Art Comunicacio Agencia De Publicitat S.l.",
    "wof:placetype":"venue"
},
  "geometry": {"coordinates":[2.1488490105,41.4332542419],"type":"Point"}
}