{
  "type": "Feature",
  "properties": {
    "iso:country":"ES",
    "sg:address":"Calle de Real, 33",
    "sg:city":"Torrelodones",
    "sg:orig_category":"Molduras, Junquillos, Listones Y Molduras Perforadas",
    "sg:phone":"+34 918 59 61 93",
    "sg:postcode":"28250",
    "sg:province":"Madrid",
    "wof:name":"Martinez Cascarano C.b.",
    "wof:placetype":"venue"
},
  "geometry": {"coordinates":[-3.9271104336,40.5752792358],"type":"Point"}
}