{
  "type": "Feature",
  "properties": {
    "iso:country":"ES",
    "sg:address":"Calle de Tomas Borras, 4",
    "sg:city":"Madrid",
    "sg:orig_category":"Alimentaci\u00d3n General (al Por Menor)",
    "sg:phone":"+34 915 17 34 43",
    "sg:postcode":"28045",
    "sg:province":"Madrid",
    "wof:name":"Chen  Ai Yu",
    "wof:placetype":"venue"
},
  "geometry": {"coordinates":[-3.6964581013,40.3957672119],"type":"Point"}
}