{
  "type": "Feature",
  "properties": {
    "iso:country":"ES",
    "sg:address":"Av Sant Salvador, 128",
    "sg:city":"Sant Salvador",
    "sg:orig_category":"Inform\u00c1tica: Consultores",
    "sg:phone":"+34 977 52 05 74",
    "sg:postcode":"43130",
    "sg:province":"Tarragona",
    "wof:name":"Biosca Regalado German",
    "wof:placetype":"venue"
},
  "geometry": {"coordinates":[1.2410689592,41.1561126709],"type":"Point"}
}