{
  "type": "Feature",
  "properties": {
    "iso:country":"ES",
    "sg:address":"Calle de Brasilia, 69",
    "sg:city":"Caceres",
    "sg:orig_category":"Teatro, Ballet, Danza (agrupaciones, Compa\u00d1\u00cdas)",
    "sg:phone":"+34 927 23 65 57",
    "sg:postcode":"10005",
    "sg:province":"C\u00e1ceres",
    "sg:website":"www.raquelpalma.com",
    "wof:name":"Gp Extremusic S.l.",
    "wof:placetype":"venue"
},
  "geometry": {"coordinates":[-6.3798670769,39.4540977478],"type":"Point"}
}