{
  "type": "Feature",
  "properties": {
    "iso:country":"ES",
    "sg:address":"Avda San Javier, 1",
    "sg:city":"Dolores",
    "sg:orig_category":"Cerrajer\u00cda, Ferrallista",
    "sg:phone":"+34 968 17 32 74",
    "sg:postcode":"30739",
    "sg:province":"Murcia",
    "wof:name":"Canovas Garcia Joaquin",
    "wof:placetype":"venue"
},
  "geometry": {"coordinates":[-0.8662269711,37.7786636353],"type":"Point"}
}