{
  "type": "Feature",
  "properties": {
    "iso:country":"ES",
    "sg:address":"Pl Garrigo, 24",
    "sg:city":"Barcelona",
    "sg:classifiers":[
        {
            "category":"Professional",
            "subcategory":"Business Services",
            "type":"Services"
        }
    ],
    "sg:phone":"+34 932 43 04 00",
    "sg:postcode":"08016",
    "sg:province":"Barcelona",
    "sg:tags":[
        "control",
        "asesor\u00cda",
        "organizaci\u00d3n",
        "la",
        "de",
        "gesti\u00d3n",
        "y"
    ],
    "wof:name":"Ediciones Cica Scp",
    "wof:placetype":"venue"
},
  "geometry": {"coordinates":[2.1812419891,41.4285583496],"type":"Point"}
}