{
  "type": "Feature",
  "properties": {
    "addr:full":"Avda Constitucion, 29 Gijon Asturias 33208",
    "addr:housenumber":"29",
    "addr:postcode":"33208",
    "addr:street":"Avda Constitucion",
    "iso:country":"ES",
    "sg:address":"Avda Constitucion, 29",
    "sg:city":"Gijon",
    "sg:orig_category":"Inmobiliaria (agencias)",
    "sg:phone":"+34 985 99 06 09",
    "sg:postcode":"33208",
    "sg:province":"Asturias",
    "wof:name":"Garcia Losa Jose Manuel",
    "wof:placetype":"venue"
},
  "geometry": {"coordinates":[-5.6669998169,43.5355682373],"type":"Point"}
}