{
  "type": "Feature",
  "properties": {
    "iso:country":"ES",
    "sg:address":"Ctra. Valencia-ademuz, Km. 0013,5",
    "sg:city":"S. Antonio Benageber",
    "sg:orig_category":"Muebles, Minoristas",
    "sg:phone":"+34 961 35 10 98",
    "sg:postcode":"46184",
    "sg:province":"Valencia",
    "sg:website":"domus.sh",
    "wof:name":"Eider Dos S.l.",
    "wof:placetype":"venue"
},
  "geometry": {"coordinates":[-0.5012540221,39.5620651245],"type":"Point"}
}