{
  "type": "Feature",
  "properties": {
    "iso:country":"ES",
    "sg:address":"Calle de Santa Escolastica, 1",
    "sg:city":"Madrid",
    "sg:orig_category":"Farmacias",
    "sg:phone":"+34 913 17 52 53",
    "sg:postcode":"28041",
    "sg:province":"Madrid",
    "wof:name":"Calle Rubio Rosa Maria",
    "wof:placetype":"venue"
},
  "geometry": {"coordinates":[-3.6997270584,40.3625679016],"type":"Point"}
}