{
  "type": "Feature",
  "properties": {
    "addr:full":"Calle de Campoamor, 11 Carboneras Guadazaon Cuenca 16350",
    "addr:housenumber":"11",
    "addr:postcode":"16350",
    "addr:street":"Calle De Campoamor",
    "iso:country":"ES",
    "sg:address":"Calle de Campoamor, 11",
    "sg:city":"Carboneras Guadazaon",
    "sg:orig_category":"Cr\u00cda De Animales",
    "sg:phone":"+34 969 34 17 76",
    "sg:postcode":"16350",
    "sg:province":"Cuenca",
    "wof:name":"Herraiz Abalos Pedro",
    "wof:placetype":"venue"
},
  "geometry": {"coordinates":[-1.8124990463,39.8940238953],"type":"Point"}
}