{
  "type": "Feature",
  "properties": {
    "iso:country":"ES",
    "sg:address":"Plaz Rey Chindasvinto, 5",
    "sg:city":"Covarrubias",
    "sg:orig_category":"Hoteles",
    "sg:phone":"+34 947 40 65 60",
    "sg:postcode":"09346",
    "sg:province":"Burgos",
    "wof:name":"Hostelerias Sala S.l.",
    "wof:placetype":"venue"
},
  "geometry": {"coordinates":[-3.5193519592,42.0582885742],"type":"Point"}
}