{
  "type": "Feature",
  "properties": {
    "addr:full":"Calle de Compositor Lehmberg Ruiz, 5 Malaga M\u00e1laga 29007",
    "addr:housenumber":"5",
    "addr:postcode":"29007",
    "addr:street":"Calle De Compositor Lehmberg Ruiz;Ma\u0301Laga",
    "iso:country":"ES",
    "sg:address":"Calle de Compositor Lehmberg Ruiz, 5",
    "sg:city":"Malaga",
    "sg:orig_category":"M\u00c9dicos: Otorrinolaringolog\u00cda",
    "sg:phone":"+34 952 30 56 37",
    "sg:postcode":"29007",
    "sg:province":"M\u00e1laga",
    "wof:name":"Alcoholado Lozano Antonio",
    "wof:placetype":"venue"
},
  "geometry": {"coordinates":[-4.4318413734,36.7177429199],"type":"Point"}
}