{
  "type": "Feature",
  "properties": {
    "iso:country":"ES",
    "sg:address":"Calle de Elizkale, 3",
    "sg:city":"Zumarraga",
    "sg:orig_category":"M\u00c9dicos: Estomatolog\u00cda",
    "sg:phone":"+34 943 72 25 07",
    "sg:postcode":"20700",
    "sg:province":"Guip\u00f9zcoa",
    "wof:name":"Itziar O\u00f1atibia Bag\u00dces",
    "wof:placetype":"venue"
},
  "geometry": {"coordinates":[-2.3129777908,43.0890769958],"type":"Point"}
}