{
  "type": "Feature",
  "properties": {
    "iso:country":"ES",
    "sg:address":"San Miguel Auzoa, 7",
    "sg:city":"Legorreta",
    "sg:orig_category":"Papel, Reciclaje",
    "sg:phone":"+34 943 80 64 39",
    "sg:postcode":"20250",
    "sg:province":"Guip\u00f9zcoa",
    "wof:name":"Eurokarpa S.l.",
    "wof:placetype":"venue"
},
  "geometry": {"coordinates":[-2.1445519924,43.0843505859],"type":"Point"}
}