{
  "type": "Feature",
  "properties": {
    "addr:full":"Av Catalunya, 21 Blanes Girona 17300",
    "addr:housenumber":"21",
    "addr:postcode":"17300",
    "addr:street":"Av Catalunya",
    "iso:country":"ES",
    "sg:address":"Av Catalunya, 21",
    "sg:city":"Blanes",
    "sg:orig_category":"Institutos De Belleza",
    "sg:phone":"+34 972 33 71 28",
    "sg:postcode":"17300",
    "sg:province":"Girona",
    "wof:name":"Mollfulleda Vieta Ana Maria",
    "wof:placetype":"venue"
},
  "geometry": {"coordinates":[2.7748908997,41.6671333313],"type":"Point"}
}