{
  "type": "Feature",
  "properties": {
    "addr:full":"Calle de Gines Martinez Aranda, 1 Castillo Locubin Ja\u00e9n 23670",
    "addr:housenumber":"1",
    "addr:postcode":"23670",
    "addr:street":"Calle De Gines Martinez Aranda;Castillo Locubin Jae\u0301N",
    "iso:country":"ES",
    "sg:address":"Calle de Gines Martinez Aranda, 1",
    "sg:city":"Castillo Locubin",
    "sg:orig_category":"Bebidas",
    "sg:phone":"+34 953 59 05 01",
    "sg:postcode":"23670",
    "sg:province":"Ja\u00e9n",
    "wof:name":"Lopez Gallardo Juan",
    "wof:placetype":"venue"
},
  "geometry": {"coordinates":[-3.9386370182,37.5237770081],"type":"Point"}
}