{
  "type": "Feature",
  "properties": {
    "addr:full":"Plaz Suso Gayoso, 7 Vilalba Lugo 27800",
    "addr:housenumber":"7",
    "addr:postcode":"27800",
    "addr:street":"Gayoso",
    "iso:country":"ES",
    "sg:address":"Plaz Suso Gayoso, 7",
    "sg:city":"Vilalba",
    "sg:orig_category":"Relojer\u00cda (al Por Menor, Reparaci\u00d3n)",
    "sg:phone":"+34 982 51 01 03",
    "sg:postcode":"27800",
    "sg:province":"Lugo",
    "wof:name":"Mato Rego Victor Agustin",
    "wof:placetype":"venue"
},
  "geometry": {"coordinates":[-7.6818261147,43.2979507446],"type":"Point"}
}