{
  "type": "Feature",
  "properties": {
    "iso:country":"ES",
    "sg:address":"Carrer de Colombia, 50",
    "sg:city":"Mataro",
    "sg:orig_category":"Molduras, Junquillos, Listones Y Molduras Perforadas",
    "sg:phone":"+34 937 90 75 89",
    "sg:postcode":"08304",
    "sg:province":"Barcelona",
    "wof:name":"Garcia Cayuela Francisco",
    "wof:placetype":"venue"
},
  "geometry": {"coordinates":[2.4498670101,41.5480079651],"type":"Point"}
}