{
  "type": "Feature",
  "properties": {
    "addr:full":"Avda Ricardo Soriano, 10 Marbella M\u00e1laga 29600",
    "addr:housenumber":"10",
    "addr:postcode":"29600",
    "addr:street":"Avda Ricardo Soriano;Ma\u0301Laga",
    "iso:country":"ES",
    "sg:address":"Avda Ricardo Soriano, 10",
    "sg:city":"Marbella",
    "sg:orig_category":"Alquiler De Veh\u00cdculos: Turismos Y Utilitarios",
    "sg:phone":"+34 952 77 12 87",
    "sg:postcode":"29600",
    "sg:province":"M\u00e1laga",
    "wof:name":"Delta 2000 Rent A Car S.l.",
    "wof:placetype":"venue"
},
  "geometry": {"coordinates":[-4.8875379562,36.5098304749],"type":"Point"}
}