{
  "type": "Feature",
  "properties": {
    "iso:country":"ES",
    "sg:address":"Calle de Jose Artes De Arcos, 18",
    "sg:city":"Almeria",
    "sg:orig_category":"Confiter\u00cdas, Chocolater\u00cdas (al Por Menor)",
    "sg:phone":"+34 950 28 00 77",
    "sg:postcode":"04004",
    "sg:province":"Almer\u00eda",
    "wof:name":"Lopez Usero Juan Ignacio",
    "wof:placetype":"venue"
},
  "geometry": {"coordinates":[-2.4591488838,36.8366203308],"type":"Point"}
}