{
  "type": "Feature",
  "properties": {
    "addr:full":"Calle de Corazon De Maria, 4 Albaladejo Ciudad Real 13340",
    "addr:housenumber":"4",
    "addr:postcode":"albaladejo;13340",
    "addr:street":"Calle De Corazon;Maria",
    "iso:country":"ES",
    "sg:address":"Calle de Corazon De Maria, 4",
    "sg:city":"Albaladejo",
    "sg:orig_category":"Delegados, Agentes De Tr\u00c1nsito, Auxiliares De Transporte Internacional",
    "sg:phone":"+34 926 38 74 65",
    "sg:postcode":"13340",
    "sg:province":"Ciudad Real",
    "wof:name":"Macias Castellanos Jose",
    "wof:placetype":"venue"
},
  "geometry": {"coordinates":[-2.8088059425,38.6186676025],"type":"Point"}
}