{
  "type": "Feature",
  "properties": {
    "iso:country":"ES",
    "sg:address":"Avgd Llosar, 57",
    "sg:city":"Villafranca Cid",
    "sg:orig_category":"Mercer\u00cda, Lencer\u00cda (al Por Menor)",
    "sg:phone":"+34 964 44 11 32",
    "sg:postcode":"12150",
    "sg:province":"Castell\u00f3n",
    "wof:name":"Tena Casanova Rafael",
    "wof:placetype":"venue"
},
  "geometry": {"coordinates":[-0.2569360137,40.4276580811],"type":"Point"}
}