{
  "type": "Feature",
  "properties": {
    "iso:country":"ES",
    "sg:address":"Avda Blasco Iba\u00d1ez, 162",
    "sg:city":"Valencia",
    "sg:orig_category":"Rejas Y Cortinas Met\u00c1licas",
    "sg:phone":"+34 963 55 01 01",
    "sg:postcode":"46022",
    "sg:province":"Valencia",
    "wof:name":"Puertas Cava S.l.",
    "wof:placetype":"venue"
},
  "geometry": {"coordinates":[-0.3418250084,39.4717330933],"type":"Point"}
}