{
  "type": "Feature",
  "properties": {
    "addr:full":"Calle de Huerta Los Guerra, S/n Marbella M\u00e1laga 29600",
    "addr:postcode":"29600",
    "addr:street":"Calle De Huerta Los Guerra S / N;Ma\u0301Laga",
    "iso:country":"ES",
    "sg:address":"Calle de Huerta Los Guerra, S/n",
    "sg:city":"Marbella",
    "sg:orig_category":"Ense\u00d1anza Variada",
    "sg:phone":"+34 952 76 63 67",
    "sg:postcode":"29600",
    "sg:province":"M\u00e1laga",
    "wof:name":"Gomez Odero Maria Belen",
    "wof:placetype":"venue"
},
  "geometry": {"coordinates":[-4.8852977753,36.5154190063],"type":"Point"}
}