{
  "type": "Feature",
  "properties": {
    "iso:country":"ES",
    "sg:address":"Calle de Pleyades, 4",
    "sg:city":"Madrid",
    "sg:orig_category":"Perfumer\u00cda (al Por Menor)",
    "sg:phone":"+34 913 07 94 31",
    "sg:postcode":"28023",
    "sg:province":"Madrid",
    "wof:name":"Mas Masats Maria Josefa",
    "wof:placetype":"venue"
},
  "geometry": {"coordinates":[-3.7839400768,40.4594421387],"type":"Point"}
}