{
  "type": "Feature",
  "properties": {
    "addr:full":"Ptge Masor, 24 Sant Feliu Llobregat Barcelona 08980",
    "addr:housenumber":"24",
    "addr:postcode":"08980",
    "addr:street":"Ptge Masor",
    "iso:country":"ES",
    "sg:address":"Ptge Masor, 24",
    "sg:city":"Sant Feliu Llobregat",
    "sg:orig_category":"Goma: Productos De Uso Industrial (fabricaci\u00d3n, Al Por Mayor)",
    "sg:phone":"+34 936 85 12 67",
    "sg:postcode":"08980",
    "sg:province":"Barcelona",
    "wof:name":"Larrad Villalba Francisco",
    "wof:placetype":"venue"
},
  "geometry": {"coordinates":[2.0486500263,41.3884811401],"type":"Point"}
}