{
  "type": "Feature",
  "properties": {
    "addr:full":"Calle de Lila, 3 Oviedo Asturias 33002",
    "addr:housenumber":"3",
    "addr:postcode":"33002",
    "addr:street":"Calle De Lila",
    "iso:country":"ES",
    "sg:address":"Calle de Lila, 3",
    "sg:city":"Oviedo",
    "sg:orig_category":"Centros P\u00dablicos De Formaci\u00d3n Profesional Y T\u00c9cnica",
    "sg:phone":"+34 985 22 80 44",
    "sg:postcode":"33002",
    "sg:province":"Asturias",
    "wof:name":"Colegio Oficial De Ingenieros Tecnicos De Informatica Del Principado De Asturias",
    "wof:placetype":"venue"
},
  "geometry": {"coordinates":[-5.8480811119,43.3651885986],"type":"Point"}
}