{
  "type": "Feature",
  "properties": {
    "addr:full":"Ctra. Llubi, Km. 0001,5 Inca Islas Baleares 07300",
    "addr:postcode":"07300",
    "addr:street":"Ctra. Llubi Km. 0001,5",
    "iso:country":"ES",
    "sg:address":"Ctra. Llubi, Km. 0001,5",
    "sg:city":"Inca",
    "sg:orig_category":"Aguas (distribuci\u00d3n, Servicios)",
    "sg:phone":"+34 971 50 46 43",
    "sg:postcode":"07300",
    "sg:province":"Islas Baleares",
    "wof:name":"Ute Searsa Man",
    "wof:placetype":"venue"
},
  "geometry": {"coordinates":[2.9208989143,39.7179527283],"type":"Point"}
}