{
  "type": "Feature",
  "properties": {
    "addr:full":"Calle de San Mateo, 12 Teruel Teruel 44003",
    "addr:housenumber":"12",
    "addr:postcode":"44003",
    "addr:street":"Calle De San Mateo",
    "iso:country":"ES",
    "sg:address":"Calle de San Mateo, 12",
    "sg:city":"Teruel",
    "sg:orig_category":"Empresas De Pintura Y Revestimientos",
    "sg:phone":"+34 978 60 59 68",
    "sg:postcode":"44003",
    "sg:province":"Teruel",
    "wof:name":"Tartaj Higuera Carlos",
    "wof:placetype":"venue"
},
  "geometry": {"coordinates":[-1.1022559404,40.3471450806],"type":"Point"}
}