{
  "type": "Feature",
  "properties": {
    "iso:country":"ES",
    "sg:address":"Avda Ciudad Real, 12",
    "sg:city":"Puertollano",
    "sg:orig_category":"Molduras, Junquillos, Listones Y Molduras Perforadas",
    "sg:phone":"+34 926 42 70 13",
    "sg:postcode":"13500",
    "sg:province":"Ciudad Real",
    "wof:name":"Gonzalez Reina Juan",
    "wof:placetype":"venue"
},
  "geometry": {"coordinates":[-4.1062197685,38.6975250244],"type":"Point"}
}