{
  "type": "Feature",
  "properties": {
    "iso:country":"ES",
    "sg:address":"Calle de Fidias, 10",
    "sg:city":"Malaga",
    "sg:orig_category":"Deportes N\u00c1uticos, Acu\u00c1ticos Y Subacu\u00c1ticos: Art\u00cdculos Y Equipo (al Por Menor)",
    "sg:phone":"+34 952 17 07 84",
    "sg:postcode":"29004",
    "sg:province":"M\u00e1laga",
    "sg:website":"www.cascoantiguo.com",
    "wof:name":"Casco Antiguo Comercial S.l.",
    "wof:placetype":"venue"
},
  "geometry": {"coordinates":[-4.4639539719,36.6918182373],"type":"Point"}
}