{
  "type": "Feature",
  "properties": {
    "addr:full":"Av Riera De Sant Lloren\u00c7, S/n Viladecans Barcelona 08840",
    "addr:housenumber":"s / n",
    "addr:postcode":"08840",
    "addr:street":"Av Riera De Sant Llorenc\u0327",
    "iso:country":"ES",
    "sg:address":"Av Riera De Sant Lloren\u00c7, S/n",
    "sg:city":"Viladecans",
    "sg:orig_category":"Pintura Industrial (trabajos De)",
    "sg:phone":"+34 936 37 55 90",
    "sg:postcode":"08840",
    "sg:province":"Barcelona",
    "wof:name":"Framar S.l.",
    "wof:placetype":"venue"
},
  "geometry": {"coordinates":[1.9979549646,41.311958313],"type":"Point"}
}