{
  "type": "Feature",
  "properties": {
    "addr:full":"Calle de Spengler, 10 Malaga M\u00e1laga 29007",
    "addr:housenumber":"10",
    "addr:postcode":"29007",
    "addr:street":"Calle De Spengler;Ma\u0301Laga",
    "iso:country":"ES",
    "sg:address":"Calle de Spengler, 10",
    "sg:city":"Malaga",
    "sg:orig_category":"Alimentaci\u00d3n General (al Por Menor)",
    "sg:phone":"+34 952 33 77 99",
    "sg:postcode":"29007",
    "sg:province":"M\u00e1laga",
    "sg:website":"www.asesorianeo.com",
    "wof:name":"Asesoria Neo S.l.",
    "wof:placetype":"venue"
},
  "geometry": {"coordinates":[-4.4556236267,36.7178382874],"type":"Point"}
}