{
  "type": "Feature",
  "properties": {
    "iso:country":"ES",
    "sg:address":"Rio Ega, 23",
    "sg:city":"Iru\u00f1a",
    "sg:orig_category":"Ense\u00d1anza Variada",
    "sg:phone":"+34 948 24 80 98",
    "sg:postcode":"31005",
    "sg:province":"Navarra",
    "wof:name":"Mu\u00f1oz Vizcaino Miguel",
    "wof:placetype":"venue"
},
  "geometry": {"coordinates":[-1.6457769871,42.8050308228],"type":"Point"}
}