{
  "type": "Feature",
  "properties": {
    "iso:country":"ES",
    "sg:address":"Calle de Fornillos, 32",
    "sg:city":"Madrid",
    "sg:orig_category":"Agentes, Concesionarios Y Sucursales De Veh\u00cdculos",
    "sg:phone":"+34 915 65 28 27",
    "sg:postcode":"28026",
    "sg:province":"Madrid",
    "wof:name":"Autos P.j.martin S.l.",
    "wof:placetype":"venue"
},
  "geometry": {"coordinates":[-3.7130060196,40.38256073],"type":"Point"}
}