{
  "type": "Feature",
  "properties": {
    "addr:full":"Calle de Valle De La Ballestera, 25 Valencia Valencia 46015",
    "addr:housenumber":"25",
    "addr:postcode":"46015",
    "addr:street":"Calle De Valle De La Ballestera",
    "iso:country":"ES",
    "sg:address":"Calle de Valle De La Ballestera, 25",
    "sg:city":"Valencia",
    "sg:orig_category":"Cajas De Ahorro",
    "sg:phone":"+34 963 47 25 55",
    "sg:postcode":"46015",
    "sg:province":"Valencia",
    "sg:website":"www.cam.es",
    "wof:name":"Caja De Ahorros Del Mediterraneo",
    "wof:placetype":"venue"
},
  "geometry": {"coordinates":[-0.3955120146,39.4801254272],"type":"Point"}
}