{
  "type": "Feature",
  "properties": {
    "iso:country":"ES",
    "sg:address":"Calle de San Lorenzo, 5",
    "sg:city":"Madrid",
    "sg:orig_category":"Costura (alta Costura, Creaci\u00d3n)",
    "sg:phone":"+34 913 08 34 47",
    "sg:postcode":"28004",
    "sg:province":"Madrid",
    "wof:name":"Mabel Sanz G-o S.l.u.",
    "wof:placetype":"venue"
},
  "geometry": {"coordinates":[-3.6985929012,40.4248046875],"type":"Point"}
}