{
  "type": "Feature",
  "properties": {
    "addr:full":"Calle de Veracruz, 41 Malaga M\u00e1laga 29006",
    "addr:housenumber":"41",
    "addr:postcode":"29006",
    "addr:street":"Calle De Veracruz;Ma\u0301Laga",
    "iso:country":"ES",
    "sg:address":"Calle de Veracruz, 41",
    "sg:city":"Malaga",
    "sg:orig_category":"Fabricaci\u00d3n De Enlosados, Soler\u00cdas",
    "sg:phone":"+34 952 31 29 07",
    "sg:postcode":"29006",
    "sg:province":"M\u00e1laga",
    "wof:name":"Gresmacer S.l.",
    "wof:placetype":"venue"
},
  "geometry": {"coordinates":[-4.4745559692,36.70495224],"type":"Point"}
}