{
  "type": "Feature",
  "properties": {
    "iso:country":"ES",
    "sg:address":"Calle de Alzania, 3",
    "sg:city":"Alsasua",
    "sg:orig_category":"Cajas De Ahorro",
    "sg:phone":"+34 948 56 28 12",
    "sg:postcode":"31800",
    "sg:province":"Navarra",
    "wof:name":"Caja De Ahorros Y Monte De Piedad De Navarra",
    "wof:placetype":"venue"
},
  "geometry": {"coordinates":[-2.1715869904,42.8948898315],"type":"Point"}
}