{
  "type": "Feature",
  "properties": {
    "iso:country":"ES",
    "sg:address":"Calle de Coru\u00d1a La, 9",
    "sg:city":"Oviedo",
    "sg:orig_category":"Art\u00cdculos De Regalo (al Por Menor)",
    "sg:phone":"+34 985 27 02 20",
    "sg:postcode":"33006",
    "sg:province":"Asturias",
    "wof:name":"Cueva Diaz Paulina Raquel",
    "wof:placetype":"venue"
},
  "geometry": {"coordinates":[-5.8821821213,43.3510742188],"type":"Point"}
}