{
  "type": "Feature",
  "properties": {
    "addr:full":"Av El Textil, 140 Ontinyent Valencia 46870",
    "addr:housenumber":"140",
    "addr:postcode":"46870",
    "addr:street":"Av El Textil",
    "iso:country":"ES",
    "sg:address":"Av El Textil, 140",
    "sg:city":"Ontinyent",
    "sg:orig_category":"Confecci\u00d3n (fabricaci\u00d3n, Al Por Mayor)",
    "sg:phone":"+34 962 91 12 11",
    "sg:postcode":"46870",
    "sg:province":"Valencia",
    "wof:name":"Textiles Ferpil S.l.",
    "wof:placetype":"venue"
},
  "geometry": {"coordinates":[-0.5956889987,38.8260192871],"type":"Point"}
}