{
  "type": "Feature",
  "properties": {
    "iso:country":"ES",
    "sg:address":"Carrer de Riera Baixa, 5",
    "sg:city":"Barcelona",
    "sg:orig_category":"Ropa De Ocasi\u00d3n (al Por Mayor)",
    "sg:phone":"+34 934 42 07 55",
    "sg:postcode":"08001",
    "sg:province":"Barcelona",
    "wof:name":"Mies & Felj S.l.",
    "wof:placetype":"venue"
},
  "geometry": {"coordinates":[2.1682519913,41.3800888062],"type":"Point"}
}