{
  "type": "Feature",
  "properties": {
    "addr:full":"Calle de Calasparra, 13 Molina Segura Murcia 30500",
    "addr:housenumber":"13",
    "addr:postcode":"30500",
    "addr:street":"Calle De Calasparra",
    "iso:country":"ES",
    "sg:address":"Calle de Calasparra, 13",
    "sg:city":"Molina Segura",
    "sg:orig_category":"Productos Qu\u00cdmicos (fabricaci\u00d3n, Al Por Mayor)",
    "sg:phone":"+34 968 64 37 62",
    "sg:postcode":"30500",
    "sg:province":"Murcia",
    "wof:name":"Quimigama S.l.",
    "wof:placetype":"venue"
},
  "geometry": {"coordinates":[-1.1855347157,38.0384216309],"type":"Point"}
}