{
  "type": "Feature",
  "properties": {
    "addr:full":"Carr Jorge Juan, 74 Burjassot Valencia 46100",
    "addr:housenumber":"74",
    "addr:postcode":"46100",
    "addr:street":"Carr Jorge Juan",
    "iso:country":"ES",
    "sg:address":"Carr Jorge Juan, 74",
    "sg:city":"Burjassot",
    "sg:orig_category":"Farmacias",
    "sg:phone":"+34 963 63 85 06",
    "sg:postcode":"46100",
    "sg:province":"Valencia",
    "wof:name":"Gomez Miralles Juan Rafael",
    "wof:placetype":"venue"
},
  "geometry": {"coordinates":[-0.4089510143,39.5076065063],"type":"Point"}
}