{
  "type": "Feature",
  "properties": {
    "iso:country":"ES",
    "sg:address":"Calle de Rio Ebro, 17",
    "sg:city":"Fuentes Ebro",
    "sg:orig_category":"Bares, Piano",
    "sg:phone":"+34 976 16 90 55",
    "sg:postcode":"50740",
    "sg:province":"Zaragoza",
    "wof:name":"Monforte Salvador Manuel",
    "wof:placetype":"venue"
},
  "geometry": {"coordinates":[-0.6238459945,41.5103263855],"type":"Point"}
}