{
  "type": "Feature",
  "properties": {
    "addr:full":"Calle de Barquillo, 17 Madrid Madrid 28004",
    "addr:housenumber":"17",
    "addr:postcode":"madrid;28004",
    "addr:street":"Calle De Barquillo",
    "iso:country":"ES",
    "sg:address":"Calle de Barquillo, 17",
    "sg:city":"Madrid",
    "sg:orig_category":"Librer\u00cdas",
    "sg:phone":"+34 915 23 31 71",
    "sg:postcode":"28004",
    "sg:province":"Madrid",
    "wof:name":"Sanchez Ortega Teresa",
    "wof:placetype":"venue"
},
  "geometry": {"coordinates":[-3.6957066059,40.4217796326],"type":"Point"}
}