{
  "type": "Feature",
  "properties": {
    "iso:country":"ES",
    "sg:address":"Calle de Melchor Fernandez Almagro, 84",
    "sg:city":"Madrid",
    "sg:orig_category":"Farmacias",
    "sg:phone":"+34 917 38 42 08",
    "sg:postcode":"28029",
    "sg:province":"Madrid",
    "wof:name":"Garcia Fernandez Maria Gloria",
    "wof:placetype":"venue"
},
  "geometry": {"coordinates":[-3.7107810974,40.4754943848],"type":"Point"}
}