{
  "type": "Feature",
  "properties": {
    "addr:full":"Avda Trujillo (de), 82 Miajadas C\u00e1ceres 10100",
    "addr:housenumber":"82",
    "addr:postcode":"10100",
    "addr:street":"Avda Trujillo De;Ca\u0301Ceres",
    "iso:country":"ES",
    "sg:address":"Avda Trujillo (de), 82",
    "sg:city":"Miajadas",
    "sg:orig_category":"Ropa Para Se\u00d1oras Y Caballeros (al Por Menor)",
    "sg:phone":"+34 927 34 86 67",
    "sg:postcode":"10100",
    "sg:province":"C\u00e1ceres",
    "wof:name":"Stamp02, C.b.",
    "wof:placetype":"venue"
},
  "geometry": {"coordinates":[-5.9033918381,39.153881073],"type":"Point"}
}