{
  "type": "Feature",
  "properties": {
    "addr:full":"Barr Casta\u00d1al (el), 14 Selaya Cantabria 39696",
    "addr:postcode":"39696",
    "iso:country":"ES",
    "sg:address":"Barr Casta\u00d1al (el), 14",
    "sg:city":"Selaya",
    "sg:orig_category":"Empresas De Carpinter\u00cda De Madera",
    "sg:phone":"+34 942 59 06 49",
    "sg:postcode":"39696",
    "sg:province":"Cantabria",
    "wof:name":"Fernandez Sainz Jose Manuel",
    "wof:placetype":"venue"
},
  "geometry": {"coordinates":[-3.8065640926,43.2147674561],"type":"Point"}
}