{
  "type": "Feature",
  "properties": {
    "iso:country":"ES",
    "sg:address":"Avda Consell Del Pais Valencia, 13",
    "sg:city":"Agost",
    "sg:orig_category":"Sociedades, Compa\u00d1\u00cdas Aseguradoras",
    "sg:phone":"+34 965 69 19 91",
    "sg:postcode":"03698",
    "sg:province":"Alicante",
    "wof:name":"Medrano Garcia S.l.",
    "wof:placetype":"venue"
},
  "geometry": {"coordinates":[-0.6387199759,38.4366836548],"type":"Point"}
}