{
  "type": "Feature",
  "properties": {
    "iso:country":"ES",
    "sg:address":"Carr M Ramon Artigues, 9",
    "sg:city":"Alguaire",
    "sg:orig_category":"Promotores Constructores",
    "sg:phone":"+34 973 75 60 63",
    "sg:postcode":"25125",
    "sg:province":"Lleida",
    "wof:name":"Construccions Alguaire S.l.",
    "wof:placetype":"venue"
},
  "geometry": {"coordinates":[0.5842350125,41.7354736328],"type":"Point"}
}