{
  "type": "Feature",
  "properties": {
    "addr:full":"Carrer de Cabestany, 13 Barcelona Barcelona 08014",
    "addr:housenumber":"13",
    "addr:postcode":"08014",
    "addr:street":"Carrer De Cabestany",
    "iso:country":"ES",
    "sg:address":"Carrer de Cabestany, 13",
    "sg:city":"Barcelona",
    "sg:orig_category":"Fotocopias, Reprograf\u00cda",
    "sg:phone":"+34 934 19 36 79",
    "sg:postcode":"08014",
    "sg:province":"Barcelona",
    "wof:name":"Copi-star S. Pc",
    "wof:placetype":"venue"
},
  "geometry": {"coordinates":[2.1324429512,41.3859710693],"type":"Point"}
}