{
  "type": "Feature",
  "properties": {
    "addr:full":"Calle de Colon De Larreategui, 12 Bilbao Vizcaya 48001",
    "addr:housenumber":"12",
    "addr:postcode":"48001",
    "addr:street":"Calle De Colon De Larreategui",
    "iso:country":"ES",
    "sg:address":"Calle de Colon De Larreategui, 12",
    "sg:city":"Bilbao",
    "sg:orig_category":"Abogados",
    "sg:phone":"+34 944 24 35 22",
    "sg:postcode":"48001",
    "sg:province":"Vizcaya",
    "wof:name":"Foru-argi S.l.",
    "wof:placetype":"venue"
},
  "geometry": {"coordinates":[-2.9298622608,43.2629852295],"type":"Point"}
}