{
  "type": "Feature",
  "properties": {
    "iso:country":"ES",
    "sg:address":"Pl Vila (la), 8",
    "sg:city":"Prat Llobregat",
    "sg:orig_category":"Cajas De Ahorro",
    "sg:phone":"+34 933 79 03 51",
    "sg:postcode":"08820",
    "sg:province":"Barcelona",
    "wof:name":"Caixa D'estalvis I Pensions De Barcelona",
    "wof:placetype":"venue"
},
  "geometry": {"coordinates":[2.0932219028,41.3302574158],"type":"Point"}
}