{
  "type": "Feature",
  "properties": {
    "iso:country":"ES",
    "sg:address":"Calle de Caballero Rejoneador Gines Cartagena, 22",
    "sg:city":"Benidorm",
    "sg:orig_category":"Molduras, Junquillos, Listones Y Molduras Perforadas",
    "sg:phone":"+34 966 80 90 35",
    "sg:postcode":"03500",
    "sg:province":"Alicante",
    "wof:name":"Ribero Nogales Santiago",
    "wof:placetype":"venue"
},
  "geometry": {"coordinates":[-0.1345016062,38.5467071533],"type":"Point"}
}