{
  "type": "Feature",
  "properties": {
    "addr:full":"Avda Reina Victoria Eugenia, 23 Cartagena Murcia 30204",
    "addr:housenumber":"23",
    "addr:postcode":"30204",
    "addr:street":"Avda Reina Victoria Eugenia",
    "iso:country":"ES",
    "sg:address":"Avda Reina Victoria Eugenia, 23",
    "sg:city":"Cartagena",
    "sg:orig_category":"Abogados",
    "sg:phone":"+34 968 52 49 17",
    "sg:postcode":"30204",
    "sg:province":"Murcia",
    "wof:name":"Fuster Sanchez Vicente Miguel",
    "wof:placetype":"venue"
},
  "geometry": {"coordinates":[-0.9881780148,37.6097450256],"type":"Point"}
}