{
  "type": "Feature",
  "properties": {
    "addr:full":"Palacio De Elsedo, S/n La Herran Cantabria 39718",
    "addr:housenumber":"s / n",
    "addr:postcode":"39718",
    "addr:street":"La Herran",
    "iso:country":"ES",
    "sg:address":"Palacio De Elsedo, S/n",
    "sg:city":"La Herran",
    "sg:orig_category":"Museos",
    "sg:phone":"+34 942 52 82 73",
    "sg:postcode":"39718",
    "sg:province":"Cantabria",
    "wof:name":"H. Santos D. Elsedo S. A.",
    "wof:placetype":"venue"
},
  "geometry": {"coordinates":[-3.7712659836,43.3571395874],"type":"Point"}
}