{
  "type": "Feature",
  "properties": {
    "addr:full":"Calle de Calzada (la), S/n San Roman De Bembibre Le\u00f3n 24318",
    "addr:housenumber":"/ n",
    "addr:postcode":"24318",
    "addr:street":"Calle De Calzada La S;San Roman De Bembibre Leo\u0301N",
    "iso:country":"ES",
    "sg:address":"Calle de Calzada (la), S/n",
    "sg:city":"San Roman De Bembibre",
    "sg:orig_category":"Centros De Educaci\u00d3n Especial",
    "sg:phone":"+34 987 51 07 37",
    "sg:postcode":"24318",
    "sg:province":"Le\u00f3n",
    "wof:name":"Colegio Rural Agrupado Matachana",
    "wof:placetype":"venue"
},
  "geometry": {"coordinates":[-6.436314106,42.6228981018],"type":"Point"}
}