{
  "type": "Feature",
  "properties": {
    "addr:full":"Calle de Zorrilla, 64 Elda Alicante 03600",
    "addr:housenumber":"64",
    "addr:postcode":"03600",
    "addr:street":"Calle De Zorrilla",
    "iso:country":"ES",
    "sg:address":"Calle de Zorrilla, 64",
    "sg:city":"Elda",
    "sg:orig_category":"Asociaciones, Organismos Culturales Y Socioeducativos",
    "sg:phone":"+34 965 38 53 25",
    "sg:postcode":"03600",
    "sg:province":"Alicante",
    "wof:name":"Sociedad Instructiva Musical Santa Cecilia",
    "wof:placetype":"venue"
},
  "geometry": {"coordinates":[-0.7926229835,38.475402832],"type":"Point"}
}