{
  "type": "Feature",
  "properties": {
    "iso:country":"ES",
    "sg:address":"Bda Ntra Sra Aguila, S/n",
    "sg:city":"Sevilla",
    "sg:orig_category":"Transportes Por V\u00cdas Navegables",
    "sg:phone":"+34 954 64 21 95",
    "sg:postcode":"41006",
    "sg:province":"Sevilla",
    "wof:name":"Tebar Perez Herminio",
    "wof:placetype":"venue"
},
  "geometry": {"coordinates":[-5.9525737762,37.3671302795],"type":"Point"}
}