{
  "type": "Feature",
  "properties": {
    "addr:full":"Calle de Manuel Mas, 4 Talayuela C\u00e1ceres 10310",
    "addr:housenumber":"4",
    "addr:postcode":"10310",
    "addr:street":"Calle De Manuel Mas;Ca\u0301Ceres",
    "iso:country":"ES",
    "sg:address":"Calle de Manuel Mas, 4",
    "sg:city":"Talayuela",
    "sg:orig_category":"Supermercados Y Hipermercados",
    "sg:phone":"+34 927 55 12 42",
    "sg:postcode":"10310",
    "sg:province":"C\u00e1ceres",
    "wof:name":"Caceres Pulido Manuel",
    "wof:placetype":"venue"
},
  "geometry": {"coordinates":[-5.609896183,39.9891891479],"type":"Point"}
}