{
  "type": "Feature",
  "properties": {
    "addr:full":"O Telleiro, 23 Telleiro Pontevedra 36378",
    "addr:housenumber":"23",
    "addr:postcode":"36378",
    "addr:street":"Telleiro Pontevedra",
    "iso:country":"ES",
    "sg:address":"O Telleiro, 23",
    "sg:city":"Telleiro",
    "sg:orig_category":"Empresarios",
    "sg:phone":"+34 986 35 08 40",
    "sg:postcode":"36378",
    "sg:province":"Pontevedra",
    "wof:name":"Fernandez Pinzas Manuel",
    "wof:placetype":"venue"
},
  "geometry": {"coordinates":[-8.8027610779,42.109413147],"type":"Point"}
}