{
  "type": "Feature",
  "properties": {
    "iso:country":"ES",
    "sg:address":"Calle de Manzano, 13",
    "sg:city":"Puebla Alfinden",
    "sg:orig_category":"Fabricaci\u00d3n Y Venta De Volquetes Y Remolques",
    "sg:phone":"+34 976 10 98 19",
    "sg:postcode":"50171",
    "sg:province":"Zaragoza",
    "wof:name":"Remolques Jucal S.l.",
    "wof:placetype":"venue"
},
  "geometry": {"coordinates":[-0.7696250081,41.6444282532],"type":"Point"}
}