{
  "type": "Feature",
  "properties": {
    "addr:full":"Rava Sant Pere, 1 Reus Tarragona 43204",
    "addr:housenumber":"1",
    "addr:postcode":"43204",
    "addr:street":"Sant Pere",
    "iso:country":"ES",
    "sg:address":"Rava Sant Pere, 1",
    "sg:city":"Reus",
    "sg:orig_category":"Inmobiliaria (agencias)",
    "sg:phone":"+34 977 75 47 91",
    "sg:postcode":"43204",
    "sg:province":"Tarragona",
    "wof:name":"Vidal Caballe Monica",
    "wof:placetype":"venue"
},
  "geometry": {"coordinates":[1.1294599771,41.1497001648],"type":"Point"}
}