{
  "type": "Feature",
  "properties": {
    "addr:full":"Carrer de Moles, 24 Barcelona Barcelona 08002",
    "addr:housenumber":"24",
    "addr:postcode":"08002",
    "addr:street":"Carrer De Moles",
    "iso:country":"ES",
    "sg:address":"Carrer de Moles, 24",
    "sg:city":"Barcelona",
    "sg:orig_category":"Empresas De Portes Y Mensajer\u00cda",
    "sg:phone":"+34 932 70 10 91",
    "sg:postcode":"08002",
    "sg:province":"Barcelona",
    "wof:name":"Guarde\u00f1o Granados Miguel Angel",
    "wof:placetype":"venue"
},
  "geometry": {"coordinates":[2.1729431152,41.3874397278],"type":"Point"}
}