{
  "type": "Feature",
  "properties": {
    "addr:full":"Calle de Daoiz Y Velarde, 8 Valencia Valencia 46021",
    "addr:housenumber":"8",
    "addr:postcode":"46021",
    "addr:street":"Calle De Daoiz Y Velarde",
    "iso:country":"ES",
    "sg:address":"Calle de Daoiz Y Velarde, 8",
    "sg:city":"Valencia",
    "sg:orig_category":"Ingenier\u00cda, Centros De Estudios (diversos)",
    "sg:phone":"+34 963 69 82 15",
    "sg:postcode":"46021",
    "sg:province":"Valencia",
    "wof:name":"Martinez Climent Manuel",
    "wof:placetype":"venue"
},
  "geometry": {"coordinates":[-0.3496685922,39.4739532471],"type":"Point"}
}