{
  "type": "Feature",
  "properties": {
    "iso:country":"ES",
    "sg:address":"Poli Industrial C/a, S/n",
    "sg:city":"Rozas De Madrid",
    "sg:orig_category":"Venta, Montaje De Neum\u00c1ticos",
    "sg:phone":"+34 916 37 72 08",
    "sg:postcode":"28230",
    "sg:province":"Madrid",
    "wof:name":"Neuropolis S.l.",
    "wof:placetype":"venue"
},
  "geometry": {"coordinates":[-3.8913800716,40.5247497559],"type":"Point"}
}