{
  "type": "Feature",
  "properties": {
    "iso:country":"ES",
    "sg:address":"Coiron, S/n",
    "sg:city":"Coiron",
    "sg:orig_category":"Empresas De Hormig\u00d3n, Hormig\u00d3n Armado Y Pretensado",
    "sg:phone":"+34 986 74 58 60",
    "sg:postcode":"36967",
    "sg:province":"Pontevedra",
    "wof:name":"Prefabricados Angel Alvarez Castro S.l.",
    "wof:placetype":"venue"
},
  "geometry": {"coordinates":[-8.8113698959,42.4530296326],"type":"Point"}
}