{
  "type": "Feature",
  "properties": {
    "addr:full":"Calle de General Pardi\u00d1as, 99 Madrid Madrid 28006",
    "addr:housenumber":"99",
    "addr:postcode":"madrid;28006",
    "addr:street":"Calle De General Pardin\u0303As",
    "iso:country":"ES",
    "sg:address":"Calle de General Pardi\u00d1as, 99",
    "sg:city":"Madrid",
    "sg:orig_category":"Empresas De Portes Y Mensajer\u00cda",
    "sg:phone":"+34 915 61 74 05",
    "sg:postcode":"28006",
    "sg:province":"Madrid",
    "wof:name":"Mensaico S.l.",
    "wof:placetype":"venue"
},
  "geometry": {"coordinates":[-3.6777267456,40.4365768433],"type":"Point"}
}