{
  "type": "Feature",
  "properties": {
    "addr:full":"Grup Rey Don Garcia, S/n Najera La Rioja 26300",
    "addr:postcode":"26300",
    "addr:street":"Rey Don Garcia S / N Najera;Rioja",
    "iso:country":"ES",
    "sg:address":"Grup Rey Don Garcia, S/n",
    "sg:city":"Najera",
    "sg:classifiers":[
        {
            "category":"Personal",
            "subcategory":"Barber",
            "type":"Services"
        }
    ],
    "sg:phone":"+34 941 36 09 36",
    "sg:postcode":"26300",
    "sg:province":"La Rioja",
    "sg:tags":[
        "caballeros",
        "de",
        "peluqueros"
    ],
    "wof:name":"Martinez Espiga Primitivo",
    "wof:placetype":"venue"
},
  "geometry": {"coordinates":[-2.7314140797,42.4178352356],"type":"Point"}
}