{
  "type": "Feature",
  "properties": {
    "addr:full":"Calle de Sierra De Grazalema, S/n Viator Almer\u00eda 04240",
    "addr:housenumber":"s / n",
    "addr:postcode":"04240",
    "addr:street":"Calle De Sierra De Grazalema;Almeri\u0301A",
    "iso:country":"ES",
    "sg:address":"Calle de Sierra De Grazalema, S/n",
    "sg:city":"Viator",
    "sg:orig_category":"Venta, Instalaci\u00d3n, Mantenimiento De Chimeneas De Interior Y Accesorios",
    "sg:phone":"+34 950 30 44 40",
    "sg:postcode":"04240",
    "sg:province":"Almer\u00eda",
    "wof:name":"Meriuse S.l.",
    "wof:placetype":"venue"
},
  "geometry": {"coordinates":[-2.4173090458,36.8845710754],"type":"Point"}
}