{
  "type": "Feature",
  "properties": {
    "iso:country":"ES",
    "sg:address":"Avda Miguel De Cervantes, 31",
    "sg:city":"Ecija",
    "sg:orig_category":"Agencias De Viajes",
    "sg:phone":"+34 955 90 24 74",
    "sg:postcode":"41400",
    "sg:province":"Sevilla",
    "sg:website":"www.viajeselmonte.com",
    "wof:name":"Viajes El Monte S.a.",
    "wof:placetype":"venue"
},
  "geometry": {"coordinates":[-5.0779619217,37.5388908386],"type":"Point"}
}