{
  "type": "Feature",
  "properties": {
    "iso:country":"ES",
    "sg:address":"Calle de Caballero De Rodas, 20",
    "sg:city":"Torrevieja",
    "sg:orig_category":"Abogados",
    "sg:phone":"+34 965 71 79 94",
    "sg:postcode":"03180",
    "sg:province":"Alicante",
    "wof:name":"German Escudero Carlos Maria",
    "wof:placetype":"venue"
},
  "geometry": {"coordinates":[-0.6819602251,37.9778366089],"type":"Point"}
}