{
  "type": "Feature",
  "properties": {
    "iso:country":"ES",
    "sg:address":"Av Madrid, 5",
    "sg:city":"Platja D'aro",
    "sg:orig_category":"Asilos De Ancianos. Centros Privados",
    "sg:phone":"+34 972 81 75 50",
    "sg:postcode":"17250",
    "sg:province":"Girona",
    "wof:name":"Palatio Maris S.l.",
    "wof:placetype":"venue"
},
  "geometry": {"coordinates":[3.0635445118,41.8132781982],"type":"Point"}
}