{
  "type": "Feature",
  "properties": {
    "iso:country":"ES",
    "sg:address":"Calle de Pedro De Elejalde Kalea, 20",
    "sg:city":"Gernika-lumo",
    "sg:orig_category":"Plomeros",
    "sg:phone":"+34 946 25 58 77",
    "sg:postcode":"48300",
    "sg:province":"Vizcaya",
    "wof:name":"Fontaneria Chorroburu C.b.",
    "wof:placetype":"venue"
},
  "geometry": {"coordinates":[-2.6808319092,43.3168678284],"type":"Point"}
}