{
  "type": "Feature",
  "properties": {
    "addr:full":"Avda Euskadi Etorbidea, 51 Pasaia Guip\u00f9zcoa 20110",
    "addr:housenumber":"51",
    "addr:postcode":"20110",
    "addr:street":"Avda Euskadi Etorbidea;Guipu\u0300Zcoa",
    "iso:country":"ES",
    "sg:address":"Avda Euskadi Etorbidea, 51",
    "sg:city":"Pasaia",
    "sg:orig_category":"Muebles Y Accesorios Para Cocinas Y Cuartos De Ba\u00d1o (al Por Menor)",
    "sg:phone":"+34 943 39 27 22",
    "sg:postcode":"20110",
    "sg:province":"Guip\u00f9zcoa",
    "sg:website":"www.euskanet.net/cocinas.mendiola",
    "wof:name":"Carpinteria Mendiola, S.a.",
    "wof:placetype":"venue"
},
  "geometry": {"coordinates":[-1.9217879772,43.3260040283],"type":"Point"}
}