{
  "type": "Feature",
  "properties": {
    "addr:full":"Calle de San Fernando, 17 Valencia Valencia 46001",
    "addr:housenumber":"17",
    "addr:postcode":"46001",
    "addr:street":"Calle De San Fernando",
    "iso:country":"ES",
    "sg:address":"Calle de San Fernando, 17",
    "sg:city":"Valencia",
    "sg:orig_category":"Bisuter\u00cda, Joyer\u00cda, Relojer\u00cda (al Por Menor)",
    "sg:phone":"+34 963 92 26 52",
    "sg:postcode":"46001",
    "sg:province":"Valencia",
    "wof:name":"Novecento Bisuteria S.l.",
    "wof:placetype":"venue"
},
  "geometry": {"coordinates":[-0.3771029115,39.4729652405],"type":"Point"}
}