{
  "type": "Feature",
  "properties": {
    "iso:country":"ES",
    "sg:address":"Calle de Gran Via, 22",
    "sg:city":"Elche Sierra",
    "sg:orig_category":"Asesor\u00cda Fiscal Y Jur\u00cddica",
    "sg:phone":"+34 967 41 09 80",
    "sg:postcode":"02430",
    "sg:province":"Albacete",
    "wof:name":"Asesoria Prosierra Sociedad Limitada",
    "wof:placetype":"venue"
},
  "geometry": {"coordinates":[-2.0466856956,38.4501609802],"type":"Point"}
}