{
  "type": "Feature",
  "properties": {
    "iso:country":"ES",
    "sg:address":"Calle de Jorge Juan, 29",
    "sg:city":"Madrid",
    "sg:orig_category":"Oficinas De Estudios De Dise\u00d1o Industrial",
    "sg:phone":"+34 914 26 24 98",
    "sg:postcode":"28001",
    "sg:province":"Madrid",
    "sg:website":"www.artcompany.org",
    "wof:name":"Ca\u00f1as Pita De La Vega Ana",
    "wof:placetype":"venue"
},
  "geometry": {"coordinates":[-3.6836519241,40.4238929749],"type":"Point"}
}