{
  "type": "Feature",
  "properties": {
    "iso:country":"ES",
    "sg:address":"Calle de San Antonio, 6",
    "sg:city":"Mazarron",
    "sg:orig_category":"Relojer\u00cda (al Por Menor, Reparaci\u00d3n)",
    "sg:phone":"+34 968 59 18 93",
    "sg:postcode":"30870",
    "sg:province":"Murcia",
    "wof:name":"Verdu Blaya Antonio",
    "wof:placetype":"venue"
},
  "geometry": {"coordinates":[-1.3159569502,37.5973815918],"type":"Point"}
}