{
  "type": "Feature",
  "properties": {
    "addr:full":"Calle de General Davila, 1 Alcorcon Madrid 28924",
    "addr:housenumber":"1",
    "addr:postcode":"28924",
    "addr:street":"Calle De General Davila",
    "iso:country":"ES",
    "sg:address":"Calle de General Davila, 1",
    "sg:city":"Alcorcon",
    "sg:orig_category":"Prot\u00c9sicos Dentales",
    "sg:phone":"+34 916 11 20 55",
    "sg:postcode":"28924",
    "sg:province":"Madrid",
    "wof:name":"Garcia Domingo Joaquin",
    "wof:placetype":"venue"
},
  "geometry": {"coordinates":[-3.8147749901,40.3472900391],"type":"Point"}
}