{
  "type": "Feature",
  "properties": {
    "iso:country":"ES",
    "sg:address":"Calle de Castilla Y Leon (de), 14",
    "sg:city":"Jaen",
    "sg:orig_category":"Librer\u00cdas",
    "sg:phone":"+34 953 22 20 50",
    "sg:postcode":"23006",
    "sg:province":"Ja\u00e9n",
    "wof:name":"Mesa Valle Jose Carlos",
    "wof:placetype":"venue"
},
  "geometry": {"coordinates":[-3.7878456116,37.7831916809],"type":"Point"}
}