{
  "type": "Feature",
  "properties": {
    "iso:country":"ES",
    "sg:address":"Carrer de Alfabrega, 16",
    "sg:city":"Valles Parc",
    "sg:orig_category":"Asesor\u00cda Sobre Comunicaci\u00d3n De Empresas",
    "sg:phone":"+34 937 21 33 13",
    "sg:postcode":"08192",
    "sg:province":"Barcelona",
    "wof:name":"Culubret Oliva Monserrat",
    "wof:placetype":"venue"
},
  "geometry": {"coordinates":[2.0741159916,41.5268173218],"type":"Point"}
}