{
  "type": "Feature",
  "properties": {
    "addr:full":"Calle de Mariano Vela, 29 Madrid Madrid 28026",
    "addr:housenumber":"29",
    "addr:postcode":"madrid;28026",
    "addr:street":"Calle De Mariano Vela",
    "iso:country":"ES",
    "sg:address":"Calle de Mariano Vela, 29",
    "sg:city":"Madrid",
    "sg:orig_category":"Restaurantes",
    "sg:phone":"+34 914 76 32 12",
    "sg:postcode":"28026",
    "sg:province":"Madrid",
    "wof:name":"Churrreria San Isidro S.l.",
    "wof:placetype":"venue"
},
  "geometry": {"coordinates":[-3.7103919983,40.3846664429],"type":"Point"}
}