{
  "type": "Feature",
  "properties": {
    "iso:country":"ES",
    "sg:address":"Plaza Espa\u00f1a-san Martin, 2",
    "sg:city":"Plaza",
    "sg:orig_category":"Empresarios",
    "sg:phone":"+34 985 76 41 15",
    "sg:postcode":"33111",
    "sg:province":"Asturias",
    "wof:name":"Varela Blanco Manuel",
    "wof:placetype":"venue"
},
  "geometry": {"coordinates":[-6.0963587761,43.161693573],"type":"Point"}
}