{
  "type": "Feature",
  "properties": {
    "addr:full":"Calle de Ramon Garcia Arguelles, S/n Langreo Asturias 33930",
    "addr:housenumber":"s",
    "addr:postcode":"33930",
    "addr:street":"Calle De Ramon Garcia Arguelles;/ N",
    "iso:country":"ES",
    "sg:address":"Calle de Ramon Garcia Arguelles, S/n",
    "sg:city":"Langreo",
    "sg:orig_category":"Loter\u00cda Y T\u00d3mbola",
    "sg:phone":"+34 985 69 03 41",
    "sg:postcode":"33930",
    "sg:province":"Asturias",
    "wof:name":"Fanjul Lopez Eduardo",
    "wof:placetype":"venue"
},
  "geometry": {"coordinates":[-5.6929020882,43.3144111633],"type":"Point"}
}