{
  "type": "Feature",
  "properties": {
    "iso:country":"ES",
    "sg:address":"Calle de Bolivar Simon, 21",
    "sg:city":"Bilbao",
    "sg:orig_category":"Centros M\u00c9dicos Y Sociales, Dispensarios",
    "sg:phone":"+34 944 42 46 82",
    "sg:postcode":"48013",
    "sg:province":"Vizcaya",
    "wof:name":"Maria Bego\u00f1a Torrontegui Alvaro",
    "wof:placetype":"venue"
},
  "geometry": {"coordinates":[-2.9448742867,43.2606582642],"type":"Point"}
}