{
  "type": "Feature",
  "properties": {
    "iso:country":"ES",
    "sg:address":"Calle de Rio Jucar, 11",
    "sg:city":"Gangosa",
    "sg:orig_category":"Venta, Instalaci\u00d3n De Calefacci\u00d3n",
    "sg:phone":"+34 950 55 45 27",
    "sg:postcode":"04738",
    "sg:province":"Almer\u00eda",
    "wof:name":"Interclisa Vicar S.l",
    "wof:placetype":"venue"
},
  "geometry": {"coordinates":[-2.6261250973,36.8052635193],"type":"Point"}
}