{
  "type": "Feature",
  "properties": {
    "addr:full":"Calle de Victor De La Serna, 37 Madrid Madrid 28016",
    "addr:housenumber":"37",
    "addr:postcode":"madrid;28016",
    "addr:street":"Calle De Victor De La Serna",
    "iso:country":"ES",
    "sg:address":"Calle de Victor De La Serna, 37",
    "sg:city":"Madrid",
    "sg:classifiers":[
        {
            "category":"Personal",
            "subcategory":"Barber",
            "type":"Services"
        }
    ],
    "sg:phone":"+34 913 50 73 70",
    "sg:postcode":"28016",
    "sg:province":"Madrid",
    "sg:tags":[
        "caballeros",
        "de",
        "peluqueros"
    ],
    "wof:name":"Onjil Alvarez Angel",
    "wof:placetype":"venue"
},
  "geometry": {"coordinates":[-3.6720600128,40.4566192627],"type":"Point"}
}