{
  "type": "Feature",
  "properties": {
    "addr:full":"Cno. Convento, S/n Pastrana Guadalajara 19100",
    "addr:housenumber":"s / n",
    "addr:postcode":"19100",
    "addr:street":"Cno. Convento",
    "iso:country":"ES",
    "sg:address":"Cno. Convento, S/n",
    "sg:city":"Pastrana",
    "sg:orig_category":"Empresas De Carpinter\u00cda De Madera",
    "sg:phone":"+34 949 37 02 28",
    "sg:postcode":"19100",
    "sg:province":"Guadalajara",
    "wof:name":"Zamader S.l.",
    "wof:placetype":"venue"
},
  "geometry": {"coordinates":[-2.9251031876,40.4159660339],"type":"Point"}
}