{
  "type": "Feature",
  "properties": {
    "addr:full":"Calle de Ciudad De Frias, 23 Madrid Madrid 28021",
    "addr:housenumber":"23",
    "addr:postcode":"madrid;28021",
    "addr:street":"Calle De Ciudad De Frias",
    "iso:country":"ES",
    "sg:address":"Calle de Ciudad De Frias, 23",
    "sg:city":"Madrid",
    "sg:orig_category":"Maquinaria Para Industrias Diversas",
    "sg:phone":"+34 917 10 92 03",
    "sg:postcode":"28021",
    "sg:province":"Madrid",
    "sg:website":"www.adasasistemas.com",
    "wof:name":"Adasa Sistemas S.a.",
    "wof:placetype":"venue"
},
  "geometry": {"coordinates":[-3.7139565945,40.3385810852],"type":"Point"}
}