{
  "type": "Feature",
  "properties": {
    "iso:country":"ES",
    "sg:address":"Atva. Zaragoza-logro\u00f1o, 58",
    "sg:city":"Casetas",
    "sg:orig_category":"Inform\u00c1tica, Ofim\u00c1tica (estudios, Asesor\u00cda, Ingenier\u00cda, Formaci\u00d3n)",
    "sg:phone":"+34 976 77 42 22",
    "sg:postcode":"50620",
    "sg:province":"Zaragoza",
    "wof:name":"Computers Casetas S.l.",
    "wof:placetype":"venue"
},
  "geometry": {"coordinates":[-1.0303390026,41.7199440002],"type":"Point"}
}