{
  "type": "Feature",
  "properties": {
    "addr:full":"Calle de San Torcuato, 6 Guadix Granada 18500",
    "addr:housenumber":"6",
    "addr:postcode":"18500",
    "addr:street":"Calle De San Torcuato",
    "iso:country":"ES",
    "sg:address":"Calle de San Torcuato, 6",
    "sg:city":"Guadix",
    "sg:orig_category":"Agencias Y Agentes Comerciales, Representantes",
    "sg:phone":"+34 958 66 02 23",
    "sg:postcode":"18500",
    "sg:province":"Granada",
    "wof:name":"Comercial Andaluza Textil C.b.",
    "wof:placetype":"venue"
},
  "geometry": {"coordinates":[-3.1339979172,37.3013191223],"type":"Point"}
}