{
  "type": "Feature",
  "properties": {
    "addr:full":"Calle de Afrodita, S/n Gevora Caudillo Badajoz 06180",
    "addr:postcode":"06180",
    "addr:street":"Calle De Afrodita S / N",
    "iso:country":"ES",
    "sg:address":"Calle de Afrodita, S/n",
    "sg:city":"Gevora Caudillo",
    "sg:orig_category":"Promotores Constructores",
    "sg:phone":"+34 924 14 00 70",
    "sg:postcode":"06180",
    "sg:province":"Badajoz",
    "wof:name":"Ferrovial-agroman S.a",
    "wof:placetype":"venue"
},
  "geometry": {"coordinates":[-6.9702835083,38.8785972595],"type":"Point"}
}