{
  "type": "Feature",
  "properties": {
    "addr:full":"Urano, 1 Ciudad Real Ciudad Real 13005",
    "addr:housenumber":"1",
    "addr:postcode":"13005",
    "addr:street":"Urano",
    "iso:country":"ES",
    "sg:address":"Urano, 1",
    "sg:city":"Ciudad Real",
    "sg:orig_category":"Mataderos Y Talleres De Despiezado",
    "sg:phone":"+34 926 25 29 69",
    "sg:postcode":"13005",
    "sg:province":"Ciudad Real",
    "wof:name":"Carnicas Puertollano S.l.",
    "wof:placetype":"venue"
},
  "geometry": {"coordinates":[-3.9280889034,39.0020256042],"type":"Point"}
}