{
  "type": "Feature",
  "properties": {
    "addr:full":"Plaz Coronacion (de La), 5 Quesada Ja\u00e9n 23480",
    "addr:housenumber":"5",
    "addr:postcode":"23480",
    "addr:street":"Plaz",
    "iso:country":"ES",
    "sg:address":"Plaz Coronacion (de La), 5",
    "sg:city":"Quesada",
    "sg:orig_category":"Empresarios Y Productoras De Espect\u00c1culos",
    "sg:phone":"+34 953 73 39 01",
    "sg:postcode":"23480",
    "sg:province":"Ja\u00e9n",
    "wof:name":"Musicar Sanchez Gamez S.l.",
    "wof:placetype":"venue"
},
  "geometry": {"coordinates":[-3.0666520596,37.8461112976],"type":"Point"}
}