{
  "type": "Feature",
  "properties": {
    "iso:country":"ES",
    "sg:address":"Calle de Carolina Alvarez, 11",
    "sg:city":"Valencia",
    "sg:orig_category":"Naipes, Carteles, Artilugios",
    "sg:phone":"+34 963 31 80 43",
    "sg:postcode":"46023",
    "sg:province":"Valencia",
    "wof:name":"Eurolux 2000 S.l.",
    "wof:placetype":"venue"
},
  "geometry": {"coordinates":[-0.3458676934,39.4609146118],"type":"Point"}
}