{
  "type": "Feature",
  "properties": {
    "iso:country":"ES",
    "sg:address":"Carr Major, 97",
    "sg:city":"Alcarras",
    "sg:orig_category":"Molduras, Junquillos, Listones Y Molduras Perforadas",
    "sg:phone":"+34 973 79 03 02",
    "sg:postcode":"25180",
    "sg:province":"Lleida",
    "wof:name":"Charles Cami Ramona",
    "wof:placetype":"venue"
},
  "geometry": {"coordinates":[0.5282099843,41.5634155273],"type":"Point"}
}