{
  "type": "Feature",
  "properties": {
    "addr:full":"Calle de Marques De Casa Valdes, 80 Gijon Asturias 33202",
    "addr:housenumber":"80",
    "addr:postcode":"33202",
    "addr:street":"Calle De Marques De Casa Valdes",
    "iso:country":"ES",
    "sg:address":"Calle de Marques De Casa Valdes, 80",
    "sg:city":"Gijon",
    "sg:orig_category":"Librer\u00cdas",
    "sg:phone":"+34 985 33 91 13",
    "sg:postcode":"33202",
    "sg:province":"Asturias",
    "wof:name":"Blazquez Manzanares Maria Del Mar",
    "wof:placetype":"venue"
},
  "geometry": {"coordinates":[-5.6499938965,43.5373344421],"type":"Point"}
}