{
  "type": "Feature",
  "properties": {
    "addr:full":"Rois, S/n Rois La Coru\u00f1a 15166",
    "addr:housenumber":"s / n",
    "addr:postcode":"15166",
    "addr:street":"Rois;La Corun\u0303A",
    "iso:country":"ES",
    "sg:address":"Rois, S/n",
    "sg:city":"Rois",
    "sg:orig_category":"Puertas De Acorde\u00d3n Y Flexibles",
    "sg:phone":"+34 981 79 55 75",
    "sg:postcode":"15166",
    "sg:province":"La Coru\u00f1a",
    "wof:name":"Bipanel S.l.",
    "wof:placetype":"venue"
},
  "geometry": {"coordinates":[-8.2616682053,43.3274726868],"type":"Point"}
}