{
  "type": "Feature",
  "properties": {
    "iso:country":"ES",
    "sg:address":"Calle de Norias, S/n",
    "sg:city":"Norias De Daza",
    "sg:orig_category":"Semiller\u00cdas",
    "sg:phone":"+34 950 58 78 24",
    "sg:postcode":"04716",
    "sg:province":"Almer\u00eda",
    "wof:name":"Dismot S.l.",
    "wof:placetype":"venue"
},
  "geometry": {"coordinates":[-2.7460141182,36.7571296692],"type":"Point"}
}