{
  "type": "Feature",
  "properties": {
    "iso:country":"ES",
    "sg:address":"Calle de Diputacion, 3",
    "sg:city":"Guitiriz",
    "sg:orig_category":"Reposter\u00cdas",
    "sg:phone":"+34 982 37 20 33",
    "sg:postcode":"27300",
    "sg:province":"Lugo",
    "wof:name":"Guitipan C.b.",
    "wof:placetype":"venue"
},
  "geometry": {"coordinates":[-7.8945441246,43.1819458008],"type":"Point"}
}