{
  "type": "Feature",
  "properties": {
    "addr:full":"Calle de Santo Domingo De Silos, 6 Toro Zamora 49800",
    "addr:housenumber":"6",
    "addr:postcode":"49800",
    "addr:street":"Calle De Santo Domingo;Silos",
    "iso:country":"ES",
    "sg:address":"Calle de Santo Domingo De Silos, 6",
    "sg:city":"Toro",
    "sg:orig_category":"Abogados",
    "sg:phone":"+34 980 69 04 06",
    "sg:postcode":"49800",
    "sg:province":"Zamora",
    "wof:name":"Fernandez Bragado Jesus",
    "wof:placetype":"venue"
},
  "geometry": {"coordinates":[-5.3979091644,41.5253791809],"type":"Point"}
}