{
  "type": "Feature",
  "properties": {
    "iso:country":"ES",
    "sg:address":"Calle de Zorrilla, 2",
    "sg:city":"Palmas De Gran Canaria",
    "sg:orig_category":"Importaci\u00d3n",
    "sg:phone":"+34 928 23 27 27",
    "sg:postcode":"35005",
    "sg:province":"Las Palmas",
    "wof:name":"Grupo Ramchand Tejumal Aswani S.l.",
    "wof:placetype":"venue"
},
  "geometry": {"coordinates":[-15.4304885864,28.1259803772],"type":"Point"}
}