{
  "type": "Feature",
  "properties": {
    "iso:country":"ES",
    "sg:address":"Carr Castelldans, Km. 0003,0",
    "sg:city":"Lleida",
    "sg:orig_category":"Cajas Y Embalajes De Cart\u00d3n Y Papel",
    "sg:phone":"+34 973 20 12 13",
    "sg:postcode":"25001",
    "sg:province":"Lleida",
    "wof:name":"Cartonajes Del Segre S. A.",
    "wof:placetype":"venue"
},
  "geometry": {"coordinates":[0.6414020061,41.604057312],"type":"Point"}
}