{
  "type": "Feature",
  "properties": {
    "addr:full":"Calle de Astilleros, General, 96 Melilla Melilla 52006",
    "addr:housenumber":"96",
    "addr:postcode":"52006",
    "addr:street":"Calle De Astilleros General",
    "iso:country":"ES",
    "sg:address":"Calle de Astilleros, General, 96",
    "sg:city":"Melilla",
    "sg:orig_category":"Alimentaci\u00d3n General (al Por Menor)",
    "sg:phone":"+34 952 67 17 18",
    "sg:postcode":"52006",
    "sg:province":"Melilla",
    "wof:name":"Mouloud Mohamed Mohamedi",
    "wof:placetype":"venue"
},
  "geometry": {"coordinates":[-2.9363136292,35.2729682922],"type":"Point"}
}