{
  "type": "Feature",
  "properties": {
    "addr:full":"Calle de Cruz Blanca, 15 Vitoria-gasteiz \u00c1lava 01012",
    "addr:housenumber":"15",
    "addr:postcode":"01012",
    "addr:street":"Calle De Cruz Blanca",
    "iso:country":"ES",
    "sg:address":"Calle de Cruz Blanca, 15",
    "sg:city":"Vitoria-gasteiz",
    "sg:orig_category":"Confecci\u00d3n De Trajes Para Se\u00d1oras",
    "sg:phone":"+34 945 22 18 06",
    "sg:postcode":"01012",
    "sg:province":"\u00c1lava",
    "wof:name":"Lopez Crespo Jose",
    "wof:placetype":"venue"
},
  "geometry": {"coordinates":[-2.6784725189,42.8525428772],"type":"Point"}
}