{
  "type": "Feature",
  "properties": {
    "addr:full":"Santa Catalina, S/n Lucena C\u00f3rdoba 14900",
    "addr:housenumber":"s",
    "addr:postcode":"14900",
    "addr:street":"Santa Catalina;/ N",
    "iso:country":"ES",
    "sg:address":"Santa Catalina, S/n",
    "sg:city":"Lucena",
    "sg:orig_category":"Cajas Para Embalar",
    "sg:phone":"+34 957 50 01 54",
    "sg:postcode":"14900",
    "sg:province":"C\u00f3rdoba",
    "wof:name":"Caja Rural De Cordoba",
    "wof:placetype":"venue"
},
  "geometry": {"coordinates":[-4.4908938408,37.4099082947],"type":"Point"}
}