{
  "type": "Feature",
  "properties": {
    "iso:country":"ES",
    "sg:address":"Calle de Del Cristo, 31",
    "sg:city":"Jerte",
    "sg:orig_category":"Inmobiliaria (agencias)",
    "sg:phone":"+34 927 47 00 76",
    "sg:postcode":"10612",
    "sg:province":"C\u00e1ceres",
    "wof:name":"Promociones Inmobiliarias Provajer S.l.",
    "wof:placetype":"venue"
},
  "geometry": {"coordinates":[-5.7470412254,40.2247886658],"type":"Point"}
}