{
  "type": "Feature",
  "properties": {
    "iso:country":"ES",
    "sg:address":"Calle de Manolo Escobar, 37",
    "sg:city":"Ejido",
    "sg:orig_category":"Ense\u00d1anza, Formaci\u00d3n Profesional: Aprendizaje",
    "sg:phone":"+34 950 48 64 63",
    "sg:postcode":"04700",
    "sg:province":"Almer\u00eda",
    "wof:name":"U.g.t. De Andalucia",
    "wof:placetype":"venue"
},
  "geometry": {"coordinates":[-2.8194689751,36.7746124268],"type":"Point"}
}