{
  "type": "Feature",
  "properties": {
    "addr:full":"Avda Sabino Arana P E Ibarrabarri, 18 Elexalde Vizcaya 48940",
    "addr:housenumber":"18",
    "addr:postcode":"48940",
    "addr:street":"Avda Sabino Arana P E Ibarrabarri",
    "iso:country":"ES",
    "sg:address":"Avda Sabino Arana P E Ibarrabarri, 18",
    "sg:city":"Elexalde",
    "sg:orig_category":"Asesor\u00cda Sobre Comunicaci\u00d3n De Empresas",
    "sg:phone":"+34 944 80 55 21",
    "sg:postcode":"48940",
    "sg:province":"Vizcaya",
    "wof:name":"Aresti Uriarte Felix",
    "wof:placetype":"venue"
},
  "geometry": {"coordinates":[-2.8873260021,43.2208213806],"type":"Point"}
}