{
  "type": "Feature",
  "properties": {
    "addr:full":"Calle de Garay, 23 Almunia De Do\u00e7a Godina Zaragoza 50100",
    "addr:housenumber":"23",
    "addr:postcode":"50100",
    "addr:street":"Calle De Garay",
    "iso:country":"ES",
    "sg:address":"Calle de Garay, 23",
    "sg:city":"Almunia De Do\u00e7a Godina",
    "sg:orig_category":"Papeler\u00cdas, Librer\u00cdas",
    "sg:phone":"+34 976 81 23 85",
    "sg:postcode":"50100",
    "sg:province":"Zaragoza",
    "wof:name":"Godina Audiobisuals",
    "wof:placetype":"venue"
},
  "geometry": {"coordinates":[-0.8765661716,41.6563491821],"type":"Point"}
}