{
  "type": "Feature",
  "properties": {
    "addr:full":"Roldan, Km. 0000,5 Torre-pacheco Murcia 30700",
    "addr:postcode":"30700",
    "addr:street":"Roldan Km. 0000,5",
    "iso:country":"ES",
    "sg:address":"Roldan, Km. 0000,5",
    "sg:city":"Torre-pacheco",
    "sg:orig_category":"Molduras, Junquillos, Listones Y Molduras Perforadas",
    "sg:phone":"+34 968 57 78 96",
    "sg:postcode":"30700",
    "sg:province":"Murcia",
    "wof:name":"Gonzalez Flores Jose Maria",
    "wof:placetype":"venue"
},
  "geometry": {"coordinates":[-0.9535620213,37.7442855835],"type":"Point"}
}