{
  "type": "Feature",
  "properties": {
    "addr:full":"Ctra Tarajal (del), S/n Principe Felipe Ceuta 51003",
    "addr:postcode":"51003",
    "addr:street":"Ctra Tarajal Del S / N Principe Felipe Ceuta",
    "iso:country":"ES",
    "sg:address":"Ctra Tarajal (del), S/n",
    "sg:city":"Principe Felipe",
    "sg:orig_category":"Ropa Para Se\u00d1oras Y Caballeros (al Por Menor)",
    "sg:phone":"+34 956 50 67 65",
    "sg:postcode":"51003",
    "sg:province":"Ceuta",
    "wof:name":"Confecciones Izoukaren S.l.",
    "wof:placetype":"venue"
},
  "geometry": {"coordinates":[-5.3157300949,35.8891601562],"type":"Point"}
}