{
  "type": "Feature",
  "properties": {
    "iso:country":"ES",
    "sg:address":"Ctra Prats De Llu\u00c7anes, 170",
    "sg:city":"Sabadell",
    "sg:orig_category":"Peluqueros: De Se\u00d1oras",
    "sg:phone":"+34 937 17 19 10",
    "sg:postcode":"08208",
    "sg:province":"Barcelona",
    "wof:name":"Soler Carne Magda",
    "wof:placetype":"venue"
},
  "geometry": {"coordinates":[2.1017429829,41.5587997437],"type":"Point"}
}