{
  "type": "Feature",
  "properties": {
    "addr:full":"Calle de Fernando Cadalso, 8 Oca\u00f1a Toledo 45300",
    "addr:housenumber":"8",
    "addr:postcode":"45300",
    "addr:street":"Calle De Fernando Cadalso",
    "iso:country":"ES",
    "sg:address":"Calle de Fernando Cadalso, 8",
    "sg:city":"Oca\u00f1a",
    "sg:orig_category":"Asesor\u00cda Sobre Comunicaci\u00d3n De Empresas",
    "sg:phone":"+34 925 13 10 50",
    "sg:postcode":"45300",
    "sg:province":"Toledo",
    "wof:name":"Moraleda Galan Rafael",
    "wof:placetype":"venue"
},
  "geometry": {"coordinates":[-3.5000550747,39.9558448792],"type":"Point"}
}