{
  "type": "Feature",
  "properties": {
    "addr:full":"Ctra Nova, 91 Garriga Barcelona 08530",
    "addr:housenumber":"91",
    "addr:postcode":"08530",
    "addr:street":"Ctra Nova",
    "iso:country":"ES",
    "sg:address":"Ctra Nova, 91",
    "sg:city":"Garriga",
    "sg:orig_category":"Agentes, Concesionarios Y Sucursales De Veh\u00cdculos",
    "sg:phone":"+34 938 71 41 30",
    "sg:postcode":"08530",
    "sg:province":"Barcelona",
    "wof:name":"Automobils Gotanegra S.l.",
    "wof:placetype":"venue"
},
  "geometry": {"coordinates":[2.2830410004,41.6812095642],"type":"Point"}
}