{
  "type": "Feature",
  "properties": {
    "addr:full":"Cno. Vell Bunyola, 37 Pol.ind.son Castello Islas Baleares 07009",
    "addr:housenumber":"37",
    "addr:postcode":"07009",
    "addr:street":"Cno. Vell Bunyola;Islas",
    "iso:country":"ES",
    "sg:address":"Cno. Vell Bunyola, 37",
    "sg:city":"Pol.ind.son Castello",
    "sg:orig_category":"Fabricaci\u00d3n, Distribuci\u00d3n De Material Para La Climatizaci\u00d3n, Aireaci\u00d3n Y Ventilaci\u00d3n",
    "sg:phone":"+34 971 75 47 51",
    "sg:postcode":"07009",
    "sg:province":"Islas Baleares",
    "sg:website":"www.humiclima.com",
    "wof:name":"Humiclima Est. S.a.",
    "wof:placetype":"venue"
},
  "geometry": {"coordinates":[2.6741399765,39.6011390686],"type":"Point"}
}