{
  "type": "Feature",
  "properties": {
    "addr:full":"Calle de Anton Tobalo, 117 Torres Cotillas Murcia 30565",
    "addr:housenumber":"117",
    "addr:postcode":"30565",
    "addr:street":"Calle De Anton Tobalo",
    "iso:country":"ES",
    "sg:address":"Calle de Anton Tobalo, 117",
    "sg:city":"Torres Cotillas",
    "sg:orig_category":"Venta, Montaje De Neum\u00c1ticos",
    "sg:phone":"+34 968 62 81 39",
    "sg:postcode":"30565",
    "sg:province":"Murcia",
    "wof:name":"Gil Martinez Jose",
    "wof:placetype":"venue"
},
  "geometry": {"coordinates":[-1.2436412573,38.036441803],"type":"Point"}
}