{
  "type": "Feature",
  "properties": {
    "iso:country":"ES",
    "sg:address":"Pase Infanta Isabel, 19",
    "sg:city":"Madrid",
    "sg:orig_category":"Alimentaci\u00d3n General (al Por Menor)",
    "sg:phone":"+34 915 51 18 31",
    "sg:postcode":"28014",
    "sg:province":"Madrid",
    "wof:name":"Fernandez-escribano Garcia Vicente",
    "wof:placetype":"venue"
},
  "geometry": {"coordinates":[-3.6873149872,40.4067573547],"type":"Point"}
}