{
  "type": "Feature",
  "properties": {
    "iso:country":"ES",
    "sg:address":"Calle de Conde De Trenor, 12",
    "sg:city":"Valencia",
    "sg:orig_category":"M\u00c9dicos: Psiquiatr\u00cda",
    "sg:phone":"+34 963 91 36 74",
    "sg:postcode":"46003",
    "sg:province":"Valencia",
    "wof:name":"Herrera Barros Federico",
    "wof:placetype":"venue"
},
  "geometry": {"coordinates":[-0.375387311,39.4792327881],"type":"Point"}
}