{
  "type": "Feature",
  "properties": {
    "iso:country":"ES",
    "sg:address":"Pase Doctor Torres Villarroel, 16",
    "sg:city":"Salamanca",
    "sg:orig_category":"M\u00c9dicos: Estomatolog\u00cda",
    "sg:phone":"+34 923 22 26 07",
    "sg:postcode":"37005",
    "sg:province":"Salamanca",
    "wof:name":"Nieto Garcia Angel Luis",
    "wof:placetype":"venue"
},
  "geometry": {"coordinates":[-5.6632847786,40.9715118408],"type":"Point"}
}