{
  "type": "Feature",
  "properties": {
    "addr:full":"Carrer de Roger De Lluria, 151 Barcelona Barcelona 08037",
    "addr:housenumber":"151",
    "addr:postcode":"08037",
    "addr:street":"Carrer De Roger De Lluria",
    "iso:country":"ES",
    "sg:address":"Carrer de Roger De Lluria, 151",
    "sg:city":"Barcelona",
    "sg:orig_category":"Piscinas, Accesorios, Suministros (fabricaci\u00d3n, Al Por Mayor)",
    "sg:phone":"+34 932 18 69 50",
    "sg:postcode":"08037",
    "sg:province":"Barcelona",
    "sg:website":"www.espaiip.com",
    "wof:name":"Espai Integral De Piscines S.l.",
    "wof:placetype":"venue"
},
  "geometry": {"coordinates":[2.1622509956,41.3979187012],"type":"Point"}
}