{
  "type": "Feature",
  "properties": {
    "addr:full":"Miguel De Cervantes, 30 Zaragoza Zaragoza 50006",
    "addr:housenumber":"30",
    "addr:postcode":"50006",
    "addr:street":"Miguel;Cervantes",
    "iso:country":"ES",
    "sg:address":"Miguel De Cervantes, 30",
    "sg:city":"Zaragoza",
    "sg:orig_category":"Arquitectos",
    "sg:phone":"+34 976 21 69 89",
    "sg:postcode":"50006",
    "sg:province":"Zaragoza",
    "wof:name":"Jj Fau Hernando Y Asociados S.l",
    "wof:placetype":"venue"
},
  "geometry": {"coordinates":[-0.8889930248,41.644329071],"type":"Point"}
}