{
  "type": "Feature",
  "properties": {
    "iso:country":"ES",
    "sg:address":"Calle de Txiki Otaegi, 4",
    "sg:city":"Amorebieta",
    "sg:orig_category":"Alimentaci\u00d3n General (al Por Menor)",
    "sg:phone":"+34 946 73 03 86",
    "sg:postcode":"48340",
    "sg:province":"Vizcaya",
    "wof:name":"Sagarduy Bilbao Santos",
    "wof:placetype":"venue"
},
  "geometry": {"coordinates":[-2.7344520092,43.2211723328],"type":"Point"}
}