{
  "type": "Feature",
  "properties": {
    "addr:full":"Calle de Portu, 3 San Vicente De Barakaldo Vizcaya 48901",
    "addr:housenumber":"3",
    "addr:postcode":"48901",
    "addr:street":"Calle De Portu",
    "iso:country":"ES",
    "sg:address":"Calle de Portu, 3",
    "sg:city":"San Vicente De Barakaldo",
    "sg:orig_category":"Agencias Y Asesores De Publicidad",
    "sg:phone":"+34 944 37 35 79",
    "sg:postcode":"48901",
    "sg:province":"Vizcaya",
    "wof:name":"Bueno Gutierrez Noemi",
    "wof:placetype":"venue"
},
  "geometry": {"coordinates":[-2.9843850136,43.2982368469],"type":"Point"}
}