{
  "type": "Feature",
  "properties": {
    "addr:full":"Calle de General Primo De Rivera, 63 Pe\u00e7arroya-pueblonuevo C\u00f3rdoba 14200",
    "addr:housenumber":"63",
    "addr:postcode":"14200",
    "addr:street":"Calle De General Primo De Rivera;Co\u0301Rdoba",
    "iso:country":"ES",
    "sg:address":"Calle de General Primo De Rivera, 63",
    "sg:city":"Pe\u00e7arroya-pueblonuevo",
    "sg:orig_category":"Pintura, Barniz, Productos Asimilables (fabricaci\u00d3n, Al Por Mayor)",
    "sg:phone":"+34 957 57 09 41",
    "sg:postcode":"14200",
    "sg:province":"C\u00f3rdoba",
    "wof:name":"Sanchez Merino Vicente",
    "wof:placetype":"venue"
},
  "geometry": {"coordinates":[-5.2802939415,38.3091964722],"type":"Point"}
}