{
  "type": "Feature",
  "properties": {
    "iso:country":"ES",
    "sg:address":"Calle de Cordoba, 1",
    "sg:city":"Teruel",
    "sg:orig_category":"Agentes De Seguros",
    "sg:phone":"+34 978 60 10 64",
    "sg:postcode":"44002",
    "sg:province":"Teruel",
    "wof:name":"Garzaran Aguilar Joaquin",
    "wof:placetype":"venue"
},
  "geometry": {"coordinates":[-1.1036592722,40.3362426758],"type":"Point"}
}