{
  "type": "Feature",
  "properties": {
    "iso:country":"ES",
    "sg:address":"Calle de Juan Xxiii, 3",
    "sg:city":"Caceres",
    "sg:orig_category":"Laboratorios Y Cl\u00cdnicas Veterinarias",
    "sg:phone":"+34 927 22 39 24",
    "sg:postcode":"10001",
    "sg:province":"C\u00e1ceres",
    "wof:name":"Marquez Duran Santiago",
    "wof:placetype":"venue"
},
  "geometry": {"coordinates":[-6.3826589584,39.4677047729],"type":"Point"}
}