{
  "type": "Feature",
  "properties": {
    "addr:full":"Calle de Pintor Salvador Abril, 14 Valencia Valencia 46005",
    "addr:housenumber":"14",
    "addr:postcode":"46005",
    "addr:street":"Calle De Pintor Salvador Abril",
    "iso:country":"ES",
    "sg:address":"Calle de Pintor Salvador Abril, 14",
    "sg:city":"Valencia",
    "sg:orig_category":"Poller\u00cda Y Caza (al Por Menor)",
    "sg:phone":"+34 963 34 58 14",
    "sg:postcode":"46005",
    "sg:province":"Valencia",
    "wof:name":"Entraigues Saez Francisca Otilia",
    "wof:placetype":"venue"
},
  "geometry": {"coordinates":[-0.371329993,39.4641265869],"type":"Point"}
}