{
  "type": "Feature",
  "properties": {
    "addr:full":"Avda Lugo (de), 13 Antas Ulla Lugo 27570",
    "addr:housenumber":"13",
    "addr:postcode":"27570",
    "addr:street":"Avda Lugo De",
    "iso:country":"ES",
    "sg:address":"Avda Lugo (de), 13",
    "sg:city":"Antas Ulla",
    "sg:orig_category":"Asesor\u00cda De Formaci\u00d3n Y Gesti\u00d3n De Personal",
    "sg:phone":"+34 982 37 92 55",
    "sg:postcode":"27570",
    "sg:province":"Lugo",
    "wof:name":"Meijide Espa\u00f1a Juan Carlos",
    "wof:placetype":"venue"
},
  "geometry": {"coordinates":[-7.8898887634,42.7823143005],"type":"Point"}
}