{
  "type": "Feature",
  "properties": {
    "addr:full":"Calle de Altagracia, 2 Ciudad Real Ciudad Real 13003",
    "addr:housenumber":"2",
    "addr:postcode":"13003",
    "addr:street":"Calle De Altagracia",
    "iso:country":"ES",
    "sg:address":"Calle de Altagracia, 2",
    "sg:city":"Ciudad Real",
    "sg:orig_category":"Peluquer\u00cdas, Peluquer\u00cda Mixta",
    "sg:phone":"+34 926 23 09 84",
    "sg:postcode":"13003",
    "sg:province":"Ciudad Real",
    "wof:name":"Soanez Garcia Leonor",
    "wof:placetype":"venue"
},
  "geometry": {"coordinates":[-3.9257509708,38.9888420105],"type":"Point"}
}