{
  "type": "Feature",
  "properties": {
    "iso:country":"ES",
    "sg:address":"Calle de Castelar, 77",
    "sg:city":"Zaragoza",
    "sg:orig_category":"Chapister\u00cda",
    "sg:phone":"+34 976 41 21 13",
    "sg:postcode":"50013",
    "sg:province":"Zaragoza",
    "wof:name":"Talleres Castelar S. A. L.",
    "wof:placetype":"venue"
},
  "geometry": {"coordinates":[-0.869073987,41.6391181946],"type":"Point"}
}