{
  "type": "Feature",
  "properties": {
    "iso:country":"ES",
    "sg:address":"Carrer de Muntanya, 63",
    "sg:city":"Mataro",
    "sg:orig_category":"Cerrajer\u00cda, Ferrallista",
    "sg:phone":"+34 937 98 58 09",
    "sg:postcode":"08304",
    "sg:province":"Barcelona",
    "wof:name":"Baides Garcia Ramon",
    "wof:placetype":"venue"
},
  "geometry": {"coordinates":[2.433893919,41.5498504639],"type":"Point"}
}