{
  "type": "Feature",
  "properties": {
    "iso:country":"ES",
    "sg:address":"Pigara, 9",
    "sg:city":"O Temple",
    "sg:orig_category":"Agencias Y Agentes Comerciales, Representantes",
    "sg:phone":"+34 981 65 31 11",
    "sg:postcode":"15679",
    "sg:province":"La Coru\u00f1a",
    "wof:name":"Bugallo Abuin Oscar",
    "wof:placetype":"venue"
},
  "geometry": {"coordinates":[-8.3566465378,43.3202438354],"type":"Point"}
}