{
  "type": "Feature",
  "properties": {
    "addr:full":"Carrer de Barcelona, 28 Constanti Tarragona 43120",
    "addr:housenumber":"28",
    "addr:postcode":"43120",
    "addr:street":"Carrer De Barcelona",
    "iso:country":"ES",
    "sg:address":"Carrer de Barcelona, 28",
    "sg:city":"Constanti",
    "sg:orig_category":"Electrodom\u00c9sticos (al Por Menor)",
    "sg:phone":"+34 977 52 33 44",
    "sg:postcode":"43120",
    "sg:province":"Tarragona",
    "wof:name":"Montes Recio Antonio",
    "wof:placetype":"venue"
},
  "geometry": {"coordinates":[1.2151470184,41.1509017944],"type":"Point"}
}