{
  "type": "Feature",
  "properties": {
    "iso:country":"ES",
    "sg:address":"Calle de Miraflores, 8",
    "sg:city":"Santa Cruz De Tenerife",
    "sg:orig_category":"Asesor\u00cda De Comercio Exterior",
    "sg:phone":"+34 922 24 36 88",
    "sg:postcode":"38003",
    "sg:province":"Santa Cruz De Tenerife",
    "wof:name":"Altair Consultores Logisticos S.l.",
    "wof:placetype":"venue"
},
  "geometry": {"coordinates":[-16.2533626556,28.465839386],"type":"Point"}
}