{
  "type": "Feature",
  "properties": {
    "addr:full":"Avda Nuevo Mundo (del), 2 Boadilla Del Monte Madrid 28660",
    "addr:housenumber":"2",
    "addr:postcode":"28660",
    "addr:street":"Avda Nuevo Mundo Del",
    "iso:country":"ES",
    "sg:address":"Avda Nuevo Mundo (del), 2",
    "sg:city":"Boadilla Del Monte",
    "sg:orig_category":"Controles De Edificaci\u00d3n (construcci\u00d3n, Seguridad)",
    "sg:phone":"+34 916 32 09 82",
    "sg:postcode":"28660",
    "sg:province":"Madrid",
    "wof:name":"G.j.0030 Jardineria S.l.",
    "wof:placetype":"venue"
},
  "geometry": {"coordinates":[-3.8873038292,40.4058456421],"type":"Point"}
}