{
  "type": "Feature",
  "properties": {
    "iso:country":"ES",
    "sg:address":"Calle de Jose Maria Peman, 19",
    "sg:city":"Barbate",
    "sg:orig_category":"Asociaciones Y Clubs Deportivos",
    "sg:phone":"+34 956 43 23 05",
    "sg:postcode":"11160",
    "sg:province":"C\u00e1diz",
    "wof:name":"Pe\u00f1a De Cazadores El Cartucho",
    "wof:placetype":"venue"
},
  "geometry": {"coordinates":[-5.9204192162,36.193359375],"type":"Point"}
}