{
  "type": "Feature",
  "properties": {
    "addr:full":"Calle de Antonio Abellan Abellan, 4 Paz Murcia 30006",
    "addr:housenumber":"4",
    "addr:postcode":"30006",
    "addr:street":"Calle De Antonio Abellan Abellan",
    "iso:country":"ES",
    "sg:address":"Calle de Antonio Abellan Abellan, 4",
    "sg:city":"Paz",
    "sg:orig_category":"Electricidad: Equipos Industriales, Componentes (fabricaci\u00d3n)",
    "sg:phone":"+34 968 23 30 52",
    "sg:postcode":"30006",
    "sg:province":"Murcia",
    "wof:name":"Electro Murcia S.a.",
    "wof:placetype":"venue"
},
  "geometry": {"coordinates":[-1.1298867464,37.9834747314],"type":"Point"}
}