{
  "type": "Feature",
  "properties": {
    "addr:full":"Poligon E, S/n Xativa Valencia 46800",
    "addr:housenumber":"s / n",
    "addr:postcode":"46800",
    "iso:country":"ES",
    "sg:address":"Poligon E, S/n",
    "sg:city":"Xativa",
    "sg:orig_category":"Automatizaci\u00d3n De Procesos Industriales Y De Edificaci\u00d3n (estudios, Instalaci\u00d3n)",
    "sg:phone":"+34 962 28 30 91",
    "sg:postcode":"46800",
    "sg:province":"Valencia",
    "sg:website":"www.gipsistemes.com",
    "wof:name":"G I P Sistemes I Projectes S.l.",
    "wof:placetype":"venue"
},
  "geometry": {"coordinates":[-0.5139240026,38.9975814819],"type":"Point"}
}