{
  "type": "Feature",
  "properties": {
    "addr:full":"Otaola Hiribidea, 5 Eibar Guip\u00f9zcoa 20600",
    "addr:housenumber":"5",
    "addr:postcode":"20600",
    "addr:street":"Otaola Hiribidea;Guipu\u0300Zcoa",
    "iso:country":"ES",
    "sg:address":"Otaola Hiribidea, 5",
    "sg:city":"Eibar",
    "sg:orig_category":"Cajas De Ahorro",
    "sg:phone":"+34 943 20 04 72",
    "sg:postcode":"20600",
    "sg:province":"Guip\u00f9zcoa",
    "wof:name":"Caja Laboral Popular",
    "wof:placetype":"venue"
},
  "geometry": {"coordinates":[-2.48199296,43.1828041077],"type":"Point"}
}