{
  "type": "Feature",
  "properties": {
    "iso:country":"ES",
    "sg:address":"Calle de Galileo, 61",
    "sg:city":"Madrid",
    "sg:orig_category":"Ropa Para Se\u00d1oras (al Por Menor)",
    "sg:phone":"+34 915 43 39 23",
    "sg:postcode":"28015",
    "sg:province":"Madrid",
    "wof:name":"Qmp C.b.",
    "wof:placetype":"venue"
},
  "geometry": {"coordinates":[-3.7103099823,40.4360656738],"type":"Point"}
}