{
  "type": "Feature",
  "properties": {
    "iso:country":"ES",
    "sg:address":"Plaz Dalias (de), S/n",
    "sg:city":"Almeria",
    "sg:orig_category":"Ingenier\u00cda, Centros De Estudios (diversos)",
    "sg:phone":"+34 950 15 19 99",
    "sg:postcode":"04006",
    "sg:province":"Almer\u00eda",
    "wof:name":"Eca Entidad Colaboradora De La Administracion S.a.u.",
    "wof:placetype":"venue"
},
  "geometry": {"coordinates":[-2.4608390331,36.8422698975],"type":"Point"}
}