{
  "type": "Feature",
  "properties": {
    "addr:full":"Calle de San Pablo, 42 Alacant Alicante 03012",
    "addr:housenumber":"42",
    "addr:postcode":"03012",
    "addr:street":"Calle De San Pablo",
    "iso:country":"ES",
    "sg:address":"Calle de San Pablo, 42",
    "sg:city":"Alacant",
    "sg:orig_category":"Empresas De Limpieza",
    "sg:phone":"+34 965 24 77 84",
    "sg:postcode":"03012",
    "sg:province":"Alicante",
    "sg:website":"www.limcamar.es",
    "wof:name":"Limcamar S.l.",
    "wof:placetype":"venue"
},
  "geometry": {"coordinates":[-0.4779681861,38.359500885],"type":"Point"}
}