{
  "type": "Feature",
  "properties": {
    "iso:country":"ES",
    "sg:address":"Rua Urzaiz, 61",
    "sg:city":"Vigo",
    "sg:orig_category":"M\u00c9dicos: Cirug\u00cda General",
    "sg:phone":"+34 986 22 30 94",
    "sg:postcode":"36201",
    "sg:province":"Pontevedra",
    "wof:name":"Mui\u00f1o Vaz Jose Maria",
    "wof:placetype":"venue"
},
  "geometry": {"coordinates":[-8.7153892517,42.2341575623],"type":"Point"}
}