{
  "type": "Feature",
  "properties": {
    "iso:country":"ES",
    "sg:address":"Calle de Alcalde Pelegrin Rodriguez, 25",
    "sg:city":"San Cristobal",
    "sg:orig_category":"Art\u00cdculos Funerarios (al Por Menor)",
    "sg:phone":"+34 968 46 67 27",
    "sg:postcode":"30800",
    "sg:province":"Murcia",
    "wof:name":"Minguez Ferra Juan",
    "wof:placetype":"venue"
},
  "geometry": {"coordinates":[-1.1298867464,37.9834747314],"type":"Point"}
}