{
  "type": "Feature",
  "properties": {
    "addr:full":"Plaz San Juan, 3 Consuegra Toledo 45700",
    "addr:housenumber":"3",
    "addr:postcode":"45700",
    "addr:street":"Plaz San Juan",
    "iso:country":"ES",
    "sg:address":"Plaz San Juan, 3",
    "sg:city":"Consuegra",
    "sg:orig_category":"Sanatorios M\u00c9dico",
    "sg:phone":"+34 925 47 51 94",
    "sg:postcode":"45700",
    "sg:province":"Toledo",
    "wof:name":"Servicio De Salud De Castilla La Mancha",
    "wof:placetype":"venue"
},
  "geometry": {"coordinates":[-3.6006700993,39.4584350586],"type":"Point"}
}