{
  "type": "Feature",
  "properties": {
    "iso:country":"ES",
    "sg:address":"Ctra Zorrotza-kastrexana, 42",
    "sg:city":"Bilbao",
    "sg:orig_category":"Artes Gr\u00c1ficas, Artes Pl\u00c1sticas (curso)",
    "sg:phone":"+34 944 10 57 57",
    "sg:postcode":"48013",
    "sg:province":"Vizcaya",
    "wof:name":"Bilbo-graf S.l.",
    "wof:placetype":"venue"
},
  "geometry": {"coordinates":[-2.9736530781,43.2736206055],"type":"Point"}
}