{
  "type": "Feature",
  "properties": {
    "addr:full":"Pol Ind Red, S/n Alcala Guadaira Sevilla 41500",
    "addr:postcode":"41500",
    "addr:street":"S / N",
    "iso:country":"ES",
    "sg:address":"Pol Ind Red, S/n",
    "sg:city":"Alcala Guadaira",
    "sg:orig_category":"Materias Pl\u00c1sticas: Productos De Consumo Masivo (fabricaci\u00d3n, Al Por Mayor)",
    "sg:phone":"+34 955 63 06 71",
    "sg:postcode":"41500",
    "sg:province":"Sevilla",
    "wof:name":"Nacabel S.l.",
    "wof:placetype":"venue"
},
  "geometry": {"coordinates":[-5.8398590088,37.3383140564],"type":"Point"}
}