{
  "type": "Feature",
  "properties": {
    "iso:country":"ES",
    "sg:address":"Ctra Freixo, 15",
    "sg:city":"Barrocas",
    "sg:orig_category":"Construcciones Navales Y Fluviales",
    "sg:phone":"+34 986 47 10 16",
    "sg:postcode":"36214",
    "sg:province":"Pontevedra",
    "wof:name":"Obras Y Construcciones Dios S.a.",
    "wof:placetype":"venue"
},
  "geometry": {"coordinates":[-8.7059106827,42.2124443054],"type":"Point"}
}