{
  "type": "Feature",
  "properties": {
    "iso:country":"ES",
    "sg:address":"Calle de Ildefonso Sanchez Del Rio, 1",
    "sg:city":"Pola De Siero",
    "sg:orig_category":"Laboratorios Y Trabajos De Fotograf\u00cda, V\u00cddeo Y Cine",
    "sg:phone":"+34 985 72 22 40",
    "sg:postcode":"33510",
    "sg:province":"Asturias",
    "wof:name":"Asturmex-photo S.c.",
    "wof:placetype":"venue"
},
  "geometry": {"coordinates":[-5.6624712944,43.391708374],"type":"Point"}
}