{
  "type": "Feature",
  "properties": {
    "addr:full":"C/ Nou, S/n Ripollet Barcelona 08291",
    "addr:housenumber":"s / n",
    "addr:postcode":"08291",
    "addr:street":"C / Nou",
    "iso:country":"ES",
    "sg:address":"C/ Nou, S/n",
    "sg:city":"Ripollet",
    "sg:orig_category":"Marroquiner\u00cda (confecci\u00d3n)",
    "sg:phone":"+34 935 80 28 87",
    "sg:postcode":"08291",
    "sg:province":"Barcelona",
    "wof:name":"Ruiz Baena Felisa",
    "wof:placetype":"venue"
},
  "geometry": {"coordinates":[2.1599349976,41.499584198],"type":"Point"}
}