{
  "type": "Feature",
  "properties": {
    "iso:country":"ES",
    "sg:address":"Calle de Miraflores, 1",
    "sg:city":"Mallen",
    "sg:orig_category":"Ense\u00d1anza Secundaria: Colegios Y Escuelas Privadas",
    "sg:phone":"+34 976 86 14 09",
    "sg:postcode":"50550",
    "sg:province":"Zaragoza",
    "wof:name":"Ies Valle Del Huecha-dga-mallen",
    "wof:placetype":"venue"
},
  "geometry": {"coordinates":[-1.4178030491,41.9011077881],"type":"Point"}
}