{
  "type": "Feature",
  "properties": {
    "iso:country":"ES",
    "sg:address":"Cmno Quinteras (las), 1",
    "sg:city":"Dehesas",
    "sg:orig_category":"Centros Empresariales",
    "sg:phone":"+34 922 37 47 61",
    "sg:postcode":"38400",
    "sg:province":"Santa Cruz De Tenerife",
    "wof:name":"Perez Guillama Juan Carlos",
    "wof:placetype":"venue"
},
  "geometry": {"coordinates":[-16.5473842621,28.4141807556],"type":"Point"}
}