{
  "type": "Feature",
  "properties": {
    "iso:country":"ES",
    "sg:address":"Rua Santa Tegra, 42",
    "sg:city":"Vigo",
    "sg:orig_category":"Molduras, Junquillos, Listones Y Molduras Perforadas",
    "sg:phone":"+34 986 37 31 06",
    "sg:postcode":"36207",
    "sg:province":"Pontevedra",
    "wof:name":"Marquez Gonzalez Dionisio",
    "wof:placetype":"venue"
},
  "geometry": {"coordinates":[-8.7012958527,42.2499504089],"type":"Point"}
}