{
  "type": "Feature",
  "properties": {
    "addr:full":"Calle de Casta\u00d1o, 20 Sotogrande C\u00e1diz 11310",
    "addr:housenumber":"20",
    "addr:postcode":"11310",
    "addr:street":"Calle De Castan\u0303O;Ca\u0301Diz",
    "iso:country":"ES",
    "sg:address":"Calle de Casta\u00d1o, 20",
    "sg:city":"Sotogrande",
    "sg:orig_category":"Clubes, Asociaciones De Ocio",
    "sg:phone":"+34 956 79 41 39",
    "sg:postcode":"11310",
    "sg:province":"C\u00e1diz",
    "wof:name":"Richard Arthur David",
    "wof:placetype":"venue"
},
  "geometry": {"coordinates":[-5.2761974335,36.2879981995],"type":"Point"}
}