{
  "type": "Feature",
  "properties": {
    "addr:full":"Calle de Enrique Ruiz Cabello, 14 Atarfe Granada 18230",
    "addr:housenumber":"14",
    "addr:postcode":"18230",
    "addr:street":"Calle De Enrique Ruiz Cabello",
    "iso:country":"ES",
    "sg:address":"Calle de Enrique Ruiz Cabello, 14",
    "sg:city":"Atarfe",
    "sg:orig_category":"Peluqueros: De Se\u00d1oras",
    "sg:phone":"+34 958 43 88 17",
    "sg:postcode":"18230",
    "sg:province":"Granada",
    "wof:name":"Diaz Jimenez Josefina",
    "wof:placetype":"venue"
},
  "geometry": {"coordinates":[-3.6891729832,37.2239112854],"type":"Point"}
}