{
  "type": "Feature",
  "properties": {
    "iso:country":"ES",
    "sg:address":"Calle de San Vicente, 5",
    "sg:city":"Bilbao",
    "sg:orig_category":"Abogados",
    "sg:phone":"+34 944 24 16 36",
    "sg:postcode":"48001",
    "sg:province":"Vizcaya",
    "wof:name":"I\u00f1aki Martinez Lopez-javier Del Solar Llamosas Y Otros C.b.",
    "wof:placetype":"venue"
},
  "geometry": {"coordinates":[-2.9281721115,43.2640914917],"type":"Point"}
}