{
  "type": "Feature",
  "properties": {
    "iso:country":"ES",
    "sg:address":"Avda Jesus, S/n",
    "sg:city":"Fiscal",
    "sg:orig_category":"Cajas De Ahorro",
    "sg:phone":"+34 974 50 30 51",
    "sg:postcode":"22373",
    "sg:province":"Huesca",
    "wof:name":"Caja De Ahorros Y Monte De Piedad De Zaragoza Aragon Y Rioja",
    "wof:placetype":"venue"
},
  "geometry": {"coordinates":[-0.1174120009,42.499080658],"type":"Point"}
}