{
  "type": "Feature",
  "properties": {
    "addr:full":"Garibalda, S/n Salas Asturias 33860",
    "addr:postcode":"33860",
    "addr:street":"Garibalda S / N",
    "iso:country":"ES",
    "sg:address":"Garibalda, S/n",
    "sg:city":"Salas",
    "sg:orig_category":"Centros De Educaci\u00d3n Especial",
    "sg:phone":"+34 985 83 07 59",
    "sg:postcode":"33860",
    "sg:province":"Asturias",
    "wof:name":"Colegio Nacional Mixto",
    "wof:placetype":"venue"
},
  "geometry": {"coordinates":[-6.2553191185,43.4068603516],"type":"Point"}
}