{
  "type": "Feature",
  "properties": {
    "iso:country":"ES",
    "sg:address":"Ctra. Nal. Madrid, 36",
    "sg:city":"Rotgla I Corbera",
    "sg:orig_category":"Alquiler De Gr\u00daas",
    "sg:phone":"+34 962 25 40 17",
    "sg:postcode":"46816",
    "sg:province":"Valencia",
    "wof:name":"Talleres Y Gruas Cuquerella S.l.",
    "wof:placetype":"venue"
},
  "geometry": {"coordinates":[-0.565680027,39.0042419434],"type":"Point"}
}