{
  "type": "Feature",
  "properties": {
    "iso:country":"ES",
    "sg:address":"Av. Son Matias, 3",
    "sg:city":"Palmanova",
    "sg:orig_category":"Plomeros",
    "sg:phone":"+34 971 68 22 35",
    "sg:postcode":"07181",
    "sg:province":"Islas Baleares",
    "wof:name":"Garcia Gonzalez Maria Antonia",
    "wof:placetype":"venue"
},
  "geometry": {"coordinates":[2.5366148949,39.5149726868],"type":"Point"}
}