{
  "type": "Feature",
  "properties": {
    "addr:full":"Pedro Alcatarena, 5 Iru\u00f1a Navarra 31014",
    "addr:housenumber":"5",
    "addr:postcode":"31014",
    "addr:street":"Pedro Alcatarena",
    "iso:country":"ES",
    "sg:address":"Pedro Alcatarena, 5",
    "sg:city":"Iru\u00f1a",
    "sg:orig_category":"Arquitectos",
    "sg:phone":"+34 948 38 25 87",
    "sg:postcode":"31014",
    "sg:province":"Navarra",
    "wof:name":"Carlos Aznares S.l.",
    "wof:placetype":"venue"
},
  "geometry": {"coordinates":[-1.6524510384,42.822719574],"type":"Point"}
}