{
  "type": "Feature",
  "properties": {
    "iso:country":"ES",
    "sg:address":"Carr Jaume I, 10",
    "sg:city":"Pollen\u00e7a",
    "sg:orig_category":"Promotores Constructores",
    "sg:phone":"+34 971 53 40 77",
    "sg:postcode":"07460",
    "sg:province":"Islas Baleares",
    "wof:name":"Romero Santos Rafael",
    "wof:placetype":"venue"
},
  "geometry": {"coordinates":[3.0176041126,39.8750419617],"type":"Point"}
}