{
  "type": "Feature",
  "properties": {
    "addr:full":"Calle de Toscon, 6 Puerto Del Carmen Las Palmas 35510",
    "addr:housenumber":"6",
    "addr:postcode":"35510",
    "addr:street":"Calle De Toscon",
    "iso:country":"ES",
    "sg:address":"Calle de Toscon, 6",
    "sg:city":"Puerto Del Carmen",
    "sg:orig_category":"Caf\u00c9s, Bares, Cervecer\u00cdas",
    "sg:phone":"+34 928 84 96 40",
    "sg:postcode":"35510",
    "sg:province":"Las Palmas",
    "wof:name":"Anduphone S.l.",
    "wof:placetype":"venue"
},
  "geometry": {"coordinates":[-13.6747236252,28.9233818054],"type":"Point"}
}