{
  "type": "Feature",
  "properties": {
    "addr:full":"Carr Hernan Cortes, 6 Burjassot Valencia 46100",
    "addr:housenumber":"6",
    "addr:postcode":"46100",
    "addr:street":"Carr Hernan Cortes",
    "iso:country":"ES",
    "sg:address":"Carr Hernan Cortes, 6",
    "sg:city":"Burjassot",
    "sg:orig_category":"Centros Empresariales",
    "sg:phone":"+34 963 18 61 97",
    "sg:postcode":"46100",
    "sg:province":"Valencia",
    "wof:name":"Medilimp S.l",
    "wof:placetype":"venue"
},
  "geometry": {"coordinates":[-0.4188336134,39.5103530884],"type":"Point"}
}