{
  "type": "Feature",
  "properties": {
    "iso:country":"ES",
    "sg:address":"Calle de Mayor, 27",
    "sg:city":"Pradejon",
    "sg:orig_category":"Reposter\u00cdas",
    "sg:phone":"+34 941 14 13 68",
    "sg:postcode":"26510",
    "sg:province":"La Rioja",
    "wof:name":"Caballero Lorente Lucia",
    "wof:placetype":"venue"
},
  "geometry": {"coordinates":[-2.0680890083,42.3338394165],"type":"Point"}
}