{
  "type": "Feature",
  "properties": {
    "iso:country":"ES",
    "sg:address":"Calle de Miguel Angel, 11",
    "sg:city":"Madrid",
    "sg:orig_category":"Fabricaci\u00d3n, Distribuci\u00d3n De Discos, V\u00cddeodiscos Y Musicassettes",
    "sg:phone":"+34 913 19 40 65",
    "sg:postcode":"28010",
    "sg:province":"Madrid",
    "sg:website":"www.clubvips.com",
    "wof:name":"Sigla S.a.",
    "wof:placetype":"venue"
},
  "geometry": {"coordinates":[-3.6914439201,40.4353713989],"type":"Point"}
}