{
  "type": "Feature",
  "properties": {
    "iso:country":"ES",
    "sg:address":"Carrer de Ovidi, 9",
    "sg:city":"Sabadell",
    "sg:orig_category":"Arreglo, Reparaci\u00d3n, Piezas Sueltas De Televisi\u00d3n, V\u00cddeo, Hi",
    "sg:phone":"+34 937 17 14 06",
    "sg:postcode":"08206",
    "sg:province":"Barcelona",
    "wof:name":"Cortes Sanchez Francisco Jose",
    "wof:placetype":"venue"
},
  "geometry": {"coordinates":[2.0873310566,41.5541915894],"type":"Point"}
}