{
  "type": "Feature",
  "properties": {
    "addr:full":"Kalegoi, 21 Antzuola Guip\u00f9zcoa 20577",
    "addr:housenumber":"21",
    "addr:postcode":"20577",
    "addr:street":"Kalegoi;Guipu\u0300Zcoa",
    "iso:country":"ES",
    "sg:address":"Kalegoi, 21",
    "sg:city":"Antzuola",
    "sg:orig_category":"Decoraci\u00d3n: Instalaci\u00d3n Y Talleres",
    "sg:phone":"+34 943 76 64 07",
    "sg:postcode":"20577",
    "sg:province":"Guip\u00f9zcoa",
    "wof:name":"Guezalaga Larrea Tomas",
    "wof:placetype":"venue"
},
  "geometry": {"coordinates":[-2.3784418106,43.0964393616],"type":"Point"}
}