{
  "type": "Feature",
  "properties": {
    "addr:full":"Urb Arenal, S/n Hospitalet Infant Tarragona 43890",
    "addr:housenumber":"s",
    "addr:postcode":"43890",
    "addr:street":"Urb;/ N",
    "iso:country":"ES",
    "sg:address":"Urb Arenal, S/n",
    "sg:city":"Hospitalet Infant",
    "sg:orig_category":"Promotores Constructores",
    "sg:phone":"+34 977 82 04 72",
    "sg:postcode":"43890",
    "sg:province":"Tarragona",
    "wof:name":"Danison S.l.",
    "wof:placetype":"venue"
},
  "geometry": {"coordinates":[0.9211760163,40.9912872314],"type":"Point"}
}