{
  "type": "Feature",
  "properties": {
    "addr:full":"Calle de Portalegre, 1 Badajoz Badajoz 06007",
    "addr:housenumber":"1",
    "addr:postcode":"06007",
    "addr:street":"Calle De Portalegre",
    "iso:country":"ES",
    "sg:address":"Calle de Portalegre, 1",
    "sg:city":"Badajoz",
    "sg:orig_category":"Peluqueros: De Se\u00d1oras",
    "sg:phone":"+34 924 27 26 75",
    "sg:postcode":"06007",
    "sg:province":"Badajoz",
    "wof:name":"Cora Suarez Oscar Luis",
    "wof:placetype":"venue"
},
  "geometry": {"coordinates":[-6.9818210602,38.8881759644],"type":"Point"}
}