{
  "type": "Feature",
  "properties": {
    "addr:full":"Avda Rafaela Ybarra, 35 Madrid Madrid 28026",
    "addr:housenumber":"35",
    "addr:postcode":"madrid;28026",
    "addr:street":"Avda Rafaela Ybarra",
    "iso:country":"ES",
    "sg:address":"Avda Rafaela Ybarra, 35",
    "sg:city":"Madrid",
    "sg:orig_category":"Carnicer\u00cdas, Carnicer\u00cdas",
    "sg:phone":"+34 914 60 55 05",
    "sg:postcode":"28026",
    "sg:province":"Madrid",
    "wof:name":"Cuesta Martinez Andres",
    "wof:placetype":"venue"
},
  "geometry": {"coordinates":[-3.7111620903,40.3832702637],"type":"Point"}
}