{
  "type": "Feature",
  "properties": {
    "addr:full":"Calle de Santa Magdalena, S/n Biota Zaragoza 50695",
    "addr:housenumber":"s / n",
    "addr:postcode":"50695",
    "addr:street":"Calle De Santa Magdalena",
    "iso:country":"ES",
    "sg:address":"Calle de Santa Magdalena, S/n",
    "sg:city":"Biota",
    "sg:orig_category":"Molduras, Junquillos, Listones Y Molduras Perforadas",
    "sg:phone":"+34 976 67 02 13",
    "sg:postcode":"50695",
    "sg:province":"Zaragoza",
    "wof:name":"Laita Anaut Antonio",
    "wof:placetype":"venue"
},
  "geometry": {"coordinates":[-1.1954430342,42.2611083984],"type":"Point"}
}