{
  "type": "Feature",
  "properties": {
    "iso:country":"ES",
    "sg:address":"Calle de Navalcarnero (de), 4",
    "sg:city":"Fuenlabrada",
    "sg:orig_category":"Molduras, Junquillos, Listones Y Molduras Perforadas",
    "sg:phone":"+34 916 97 45 03",
    "sg:postcode":"28944",
    "sg:province":"Madrid",
    "wof:name":"Campos Martinez Miguel",
    "wof:placetype":"venue"
},
  "geometry": {"coordinates":[-3.7948338985,40.2810401917],"type":"Point"}
}