{
  "type": "Feature",
  "properties": {
    "addr:full":"Carrer de Riber, 17 Montblanc Tarragona 43400",
    "addr:housenumber":"17",
    "addr:postcode":"43400",
    "addr:street":"Carrer De Riber",
    "iso:country":"ES",
    "sg:address":"Carrer de Riber, 17",
    "sg:city":"Montblanc",
    "sg:classifiers":[
        {
            "category":"Arts & Performance",
            "subcategory":"Art Gallery",
            "type":"Entertainment"
        }
    ],
    "sg:phone":"+34 977 86 08 33",
    "sg:postcode":"43400",
    "sg:province":"Tarragona",
    "sg:tags":[
        "arte",
        "de",
        "galer\u00cdas"
    ],
    "wof:name":"Fundacio D'art Palau Ferre",
    "wof:placetype":"venue"
},
  "geometry": {"coordinates":[1.1632479429,41.3764533997],"type":"Point"}
}