{
  "type": "Feature",
  "properties": {
    "iso:country":"ES",
    "sg:address":"Pl Paradis, 2",
    "sg:city":"Vic",
    "sg:orig_category":"Comit\u00c9s De Organizaci\u00d3n De Exposiciones, Ferias, Salones",
    "sg:phone":"+34 938 86 30 35",
    "sg:postcode":"08500",
    "sg:province":"Barcelona",
    "sg:website":"www.articolor.es",
    "wof:name":"Tatche Soler Jose",
    "wof:placetype":"venue"
},
  "geometry": {"coordinates":[2.2562139034,41.9297828674],"type":"Point"}
}