{
  "type": "Feature",
  "properties": {
    "iso:country":"ES",
    "sg:address":"Avda Lecuona Pintor, 3",
    "sg:city":"Bilbao",
    "sg:orig_category":"Pintura, Barniz, Productos Asimilables (fabricaci\u00d3n, Al Por Mayor)",
    "sg:phone":"+34 944 27 53 58",
    "sg:postcode":"48012",
    "sg:province":"Vizcaya",
    "wof:name":"Color Movil S.l.",
    "wof:placetype":"venue"
},
  "geometry": {"coordinates":[-2.9475450516,43.2568778992],"type":"Point"}
}