{
  "type": "Feature",
  "properties": {
    "iso:country":"ES",
    "sg:address":"Calle de Ceuta, S/n",
    "sg:city":"Estepona",
    "sg:orig_category":"Bordado, Marcado A Medida",
    "sg:phone":"+34 952 80 58 49",
    "sg:postcode":"29680",
    "sg:province":"M\u00e1laga",
    "wof:name":"Mr Estampaciones Y Bordados S.c.",
    "wof:placetype":"venue"
},
  "geometry": {"coordinates":[-5.1517553329,36.4218788147],"type":"Point"}
}