{
  "type": "Feature",
  "properties": {
    "iso:country":"ES",
    "sg:address":"Av J.a.clave, 28",
    "sg:city":"Mao",
    "sg:orig_category":"Agencias De Viajes",
    "sg:phone":"+34 971 35 17 00",
    "sg:postcode":"07...",
    "sg:province":"Islas Baleares",
    "wof:name":"Viajes Magon S.a.",
    "wof:placetype":"venue"
},
  "geometry": {"coordinates":[4.2597179413,39.8859901428],"type":"Point"}
}