{
  "type": "Feature",
  "properties": {
    "iso:country":"ES",
    "sg:address":"Calle de Jose Maria Pereda, 20",
    "sg:city":"Alcala Henares",
    "sg:orig_category":"Administradores De Bienes Y Delegados De Comunidades De Propietarios",
    "sg:phone":"+34 918 02 32 10",
    "sg:postcode":"28806",
    "sg:province":"Madrid",
    "wof:name":"Jaenes Cf Asesores S.l.",
    "wof:placetype":"venue"
},
  "geometry": {"coordinates":[-3.3647630215,40.4989509583],"type":"Point"}
}