{
  "type": "Feature",
  "properties": {
    "addr:full":"Falmuria, 29 Falmuria Asturias 33438",
    "addr:housenumber":"29",
    "addr:postcode":"33438",
    "addr:street":"Falmuria;Asturias",
    "iso:country":"ES",
    "sg:address":"Falmuria, 29",
    "sg:city":"Falmuria",
    "sg:orig_category":"Montaje (empresas De)",
    "sg:phone":"+34 985 88 76 61",
    "sg:postcode":"33438",
    "sg:province":"Asturias",
    "wof:name":"A.c.g. Ingenieria S.a.",
    "wof:placetype":"venue"
},
  "geometry": {"coordinates":[-5.9832577705,43.2504386902],"type":"Point"}
}