{
  "type": "Feature",
  "properties": {
    "addr:full":"Avda Gasteiz, 56 Vitoria-gasteiz \u00c1lava 01012",
    "addr:housenumber":"56",
    "addr:postcode":"01012",
    "addr:street":"Avda Gasteiz",
    "iso:country":"ES",
    "sg:address":"Avda Gasteiz, 56",
    "sg:city":"Vitoria-gasteiz",
    "sg:classifiers":[
        {
            "category":"Personal",
            "subcategory":"Barber",
            "type":"Services"
        }
    ],
    "sg:phone":"+34 945 24 22 34",
    "sg:postcode":"01012",
    "sg:province":"\u00c1lava",
    "sg:tags":[
        "caballeros",
        "de",
        "peluqueros"
    ],
    "wof:name":"Peluqueria Vivanco",
    "wof:placetype":"venue"
},
  "geometry": {"coordinates":[-2.6804020405,42.8504867554],"type":"Point"}
}