{
  "type": "Feature",
  "properties": {
    "iso:country":"ES",
    "sg:address":"Carr Gran Bretanya, 36",
    "sg:city":"Igualada",
    "sg:orig_category":"Prendas Y Chalecos De Punto (al Por Menor)",
    "sg:phone":"+34 938 05 11 37",
    "sg:postcode":"08700",
    "sg:province":"Barcelona",
    "wof:name":"Zeriouh  Rachida",
    "wof:placetype":"venue"
},
  "geometry": {"coordinates":[1.6349681616,41.5853157043],"type":"Point"}
}