{
  "type": "Feature",
  "properties": {
    "addr:full":"Calle de Loto, 2 Getafe Madrid 28903",
    "addr:housenumber":"2",
    "addr:postcode":"28903",
    "addr:street":"Calle De Loto",
    "iso:country":"ES",
    "sg:address":"Calle de Loto, 2",
    "sg:city":"Getafe",
    "sg:orig_category":"Inmobiliaria (agencias)",
    "sg:phone":"+34 916 01 69 13",
    "sg:postcode":"28903",
    "sg:province":"Madrid",
    "sg:website":"www.tecnocasa.com",
    "wof:name":"Estudio Las Margaritas S.l.",
    "wof:placetype":"venue"
},
  "geometry": {"coordinates":[-3.7231481075,40.3174819946],"type":"Point"}
}