{
  "type": "Feature",
  "properties": {
    "iso:country":"ES",
    "sg:address":"Carrer de Baluard, 28",
    "sg:city":"Barcelona",
    "sg:orig_category":"Carros Elevadores, Carros De Operaciones Portuarias",
    "sg:phone":"+34 932 21 70 53",
    "sg:postcode":"08003",
    "sg:province":"Barcelona",
    "wof:name":"Josep Llinas E Hijos S.l.",
    "wof:placetype":"venue"
},
  "geometry": {"coordinates":[2.1886560917,41.3805236816],"type":"Point"}
}