{
  "type": "Feature",
  "properties": {
    "addr:full":"Carrer de Santander, 26 Barcelona Barcelona 08020",
    "addr:housenumber":"26",
    "addr:postcode":"08020",
    "addr:street":"Carrer De Santander",
    "iso:country":"ES",
    "sg:address":"Carrer de Santander, 26",
    "sg:city":"Barcelona",
    "sg:orig_category":"Panader\u00cdas, Panader\u00cdas",
    "sg:phone":"+34 933 14 83 71",
    "sg:postcode":"08020",
    "sg:province":"Barcelona",
    "wof:name":"Bon Catering De Torres S.l.",
    "wof:placetype":"venue"
},
  "geometry": {"coordinates":[2.2007710934,41.4258003235],"type":"Point"}
}