{
  "type": "Feature",
  "properties": {
    "iso:country":"ES",
    "sg:address":"Calle de Barrio (el), 19",
    "sg:city":"Nerja",
    "sg:orig_category":"Promotores Constructores",
    "sg:phone":"+34 952 52 70 95",
    "sg:postcode":"29780",
    "sg:province":"M\u00e1laga",
    "wof:name":"Escopania S.l.",
    "wof:placetype":"venue"
},
  "geometry": {"coordinates":[-3.8783640862,36.7448959351],"type":"Point"}
}