{
  "type": "Feature",
  "properties": {
    "iso:country":"ES",
    "sg:address":"Rua Luis Otero, 6",
    "sg:city":"Pontevedra",
    "sg:orig_category":"Alquiler De V\u00cddeo",
    "sg:phone":"+34 986 87 41 88",
    "sg:postcode":"36005",
    "sg:province":"Pontevedra",
    "wof:name":"Inversiones Mar De Galicia S.l.",
    "wof:placetype":"venue"
},
  "geometry": {"coordinates":[-8.6412696838,42.4393348694],"type":"Point"}
}