{
  "type": "Feature",
  "properties": {
    "addr:full":"Calle de Arenal, 8 Madrid Madrid 28013",
    "addr:housenumber":"8",
    "addr:postcode":"madrid;28013",
    "addr:street":"Calle De Arenal",
    "iso:country":"ES",
    "sg:address":"Calle de Arenal, 8",
    "sg:city":"Madrid",
    "sg:orig_category":"Bisuter\u00cda, Joyer\u00cda, Relojer\u00cda (al Por Menor)",
    "sg:phone":"+34 915 23 04 59",
    "sg:postcode":"28013",
    "sg:province":"Madrid",
    "wof:name":"Francisco Javier Peno Moreno Y Otro C.b.",
    "wof:placetype":"venue"
},
  "geometry": {"coordinates":[-3.7053759098,40.4169654846],"type":"Point"}
}