{
  "type": "Feature",
  "properties": {
    "iso:country":"ES",
    "sg:address":"Calle de Trefacio, 17",
    "sg:city":"Madrid",
    "sg:orig_category":"Alimentaci\u00d3n General (al Por Menor)",
    "sg:phone":"+34 917 59 30 12",
    "sg:postcode":"28043",
    "sg:province":"Madrid",
    "wof:name":"Alvarez Garcia Pedro Antonio",
    "wof:placetype":"venue"
},
  "geometry": {"coordinates":[-3.6339101791,40.4672851562],"type":"Point"}
}