{
  "type": "Feature",
  "properties": {
    "iso:country":"ES",
    "sg:address":"Calle de Bernardo Balbuena, 5",
    "sg:city":"Ciudad Real",
    "sg:orig_category":"Centros De Educaci\u00d3n Especial",
    "sg:phone":"+34 926 21 75 15",
    "sg:postcode":"13002",
    "sg:province":"Ciudad Real",
    "wof:name":"Centro Profesores Ciudad Real",
    "wof:placetype":"venue"
},
  "geometry": {"coordinates":[-3.9332630634,38.9839439392],"type":"Point"}
}