{
  "type": "Feature",
  "properties": {
    "iso:country":"ES",
    "sg:address":"Carrer de Sol I Padris, 64",
    "sg:city":"Sabadell",
    "sg:orig_category":"Sociedades, Compa\u00d1\u00cdas Aseguradoras",
    "sg:phone":"+34 937 12 00 66",
    "sg:postcode":"08203",
    "sg:province":"Barcelona",
    "sg:website":"www.finqueselniu.com",
    "wof:name":"Fernandez Juanes Ramon",
    "wof:placetype":"venue"
},
  "geometry": {"coordinates":[2.118172884,41.5381736755],"type":"Point"}
}