{
  "type": "Feature",
  "properties": {
    "iso:country":"ES",
    "sg:address":"Calle de Alcala, 119",
    "sg:city":"Madrid",
    "sg:orig_category":"Asesor\u00cda Sobre Comunicaci\u00d3n De Empresas",
    "sg:phone":"+34 914 26 32 00",
    "sg:postcode":"28009",
    "sg:province":"Madrid",
    "wof:name":"Grupo 94 Asesores S.l.",
    "wof:placetype":"venue"
},
  "geometry": {"coordinates":[-3.6807627678,40.4225616455],"type":"Point"}
}