{
  "type": "Feature",
  "properties": {
    "iso:country":"ES",
    "sg:address":"Ctra. Nacional V, Km. 0196,8",
    "sg:city":"Almaraz",
    "sg:orig_category":"Empresas De Electricidad En General",
    "sg:phone":"+34 927 54 43 60",
    "sg:postcode":"10350",
    "sg:province":"C\u00e1ceres",
    "wof:name":"Cb Central Nuclear De Almaraz",
    "wof:placetype":"venue"
},
  "geometry": {"coordinates":[-5.6808218956,39.8129959106],"type":"Point"}
}