{
  "type": "Feature",
  "properties": {
    "iso:country":"ES",
    "sg:address":"Calle de Motilla, 1",
    "sg:city":"Daimiel",
    "sg:orig_category":"Comercio De Piezas De Recambio Y De Accesorios De Veh\u00cdculos, Veh\u00cdculos Industriales",
    "sg:phone":"+34 926 85 05 02",
    "sg:postcode":"13250",
    "sg:province":"Ciudad Real",
    "wof:name":"Gomez Villoldo Carmen",
    "wof:placetype":"venue"
},
  "geometry": {"coordinates":[-3.6102519035,39.0729370117],"type":"Point"}
}