{
  "type": "Feature",
  "properties": {
    "iso:country":"ES",
    "sg:address":"Avda Galicia, 20",
    "sg:city":"Barco",
    "sg:orig_category":"Productores Recolectores, Venta Directa De Vinos",
    "sg:phone":"+34 988 32 53 09",
    "sg:postcode":"32300",
    "sg:province":"Ourense",
    "sg:website":"www.godeval.com",
    "wof:name":"Sat Godeval",
    "wof:placetype":"venue"
},
  "geometry": {"coordinates":[-6.9837059975,42.4104614258],"type":"Point"}
}