{
  "type": "Feature",
  "properties": {
    "addr:full":"Plaz San Jose Vitoria-gasteiz \u00c1lava 01003",
    "addr:postcode":"01003",
    "addr:street":"Plaz",
    "iso:country":"ES",
    "sg:address":"Plaz San Jose",
    "sg:city":"Vitoria-gasteiz",
    "sg:orig_category":"Obras Y Organismos Sociales",
    "sg:phone":"+34 945 28 85 92",
    "sg:postcode":"01003",
    "sg:province":"\u00c1lava",
    "wof:name":"Caritas Diocesana De Vitoria",
    "wof:placetype":"venue"
},
  "geometry": {"coordinates":[-2.660918951,42.8501205444],"type":"Point"}
}