{
  "type": "Feature",
  "properties": {
    "addr:full":"Crta. Mao-ciutadella, Km. 0033,0 Ferreries Islas Baleares 07750",
    "addr:postcode":"07750",
    "addr:street":"Crta. Mao-Ciutadella Km. 0033,0",
    "iso:country":"ES",
    "sg:address":"Crta. Mao-ciutadella, Km. 0033,0",
    "sg:city":"Ferreries",
    "sg:orig_category":"Agricultura: Abastecimiento Y Cosechado (negocio)",
    "sg:phone":"+34 971 15 51 54",
    "sg:postcode":"07750",
    "sg:province":"Islas Baleares",
    "wof:name":"Santa Barbara S.r.m.",
    "wof:placetype":"venue"
},
  "geometry": {"coordinates":[4.0080771446,39.9823303223],"type":"Point"}
}