{
  "type": "Feature",
  "properties": {
    "addr:full":"Calle de Lope De Vega, 8 Ceuta Ceuta 51002",
    "addr:housenumber":"8",
    "addr:postcode":"51002",
    "addr:street":"Calle De Lope De Vega",
    "iso:country":"ES",
    "sg:address":"Calle de Lope De Vega, 8",
    "sg:city":"Ceuta",
    "sg:orig_category":"Peluqueros: De Se\u00d1oras",
    "sg:phone":"+34 956 50 25 44",
    "sg:postcode":"51002",
    "sg:province":"Ceuta",
    "wof:name":"Ferrera Millan Africa Del Pilar",
    "wof:placetype":"venue"
},
  "geometry": {"coordinates":[-5.3314080238,35.8926239014],"type":"Point"}
}