{
  "type": "Feature",
  "properties": {
    "iso:country":"ES",
    "sg:address":"L. Vega, 27",
    "sg:city":"Fuente Obejuna",
    "sg:orig_category":"Farmacias",
    "sg:phone":"+34 957 58 42 10",
    "sg:postcode":"14290",
    "sg:province":"C\u00f3rdoba",
    "wof:name":"Amador Vela Purificacion",
    "wof:placetype":"venue"
},
  "geometry": {"coordinates":[-5.4199771881,38.2666625977],"type":"Point"}
}