{
  "type": "Feature",
  "properties": {
    "addr:full":"Calle de Granados, 18 Le\u00f3n Le\u00f3n 24006",
    "addr:housenumber":"18",
    "addr:postcode":"24006",
    "addr:street":"Calle De Granados;Leo\u0301N",
    "iso:country":"ES",
    "sg:address":"Calle de Granados, 18",
    "sg:city":"Le\u00f3n",
    "sg:orig_category":"Comercio, Reparaci\u00d3n De Motocicletas, Bicicletas Y Piezas Sueltas",
    "sg:phone":"+34 987 21 09 63",
    "sg:postcode":"24006",
    "sg:province":"Le\u00f3n",
    "wof:name":"Henry Moreno Marcos",
    "wof:placetype":"venue"
},
  "geometry": {"coordinates":[-5.5605649948,42.5929527283],"type":"Point"}
}