{
  "type": "Feature",
  "properties": {
    "iso:country":"ES",
    "sg:address":"Calle de Puerto Real, S/n",
    "sg:city":"Cadiz",
    "sg:orig_category":"Agentes, Concesionarios Y Sucursales De Veh\u00cdculos",
    "sg:phone":"+34 956 27 24 61",
    "sg:postcode":"11011",
    "sg:province":"C\u00e1diz",
    "wof:name":"Autovin S.l.",
    "wof:placetype":"venue"
},
  "geometry": {"coordinates":[-6.2640352249,36.4910964966],"type":"Point"}
}