{
  "type": "Feature",
  "properties": {
    "addr:full":"Carrer de Anselm Clave, 19 Granollers Barcelona 08402",
    "addr:housenumber":"19",
    "addr:postcode":"08402",
    "addr:street":"Carrer De Anselm Clave",
    "iso:country":"ES",
    "sg:address":"Carrer de Anselm Clave, 19",
    "sg:city":"Granollers",
    "sg:orig_category":"M\u00c9dicos: Otorrinolaringolog\u00cda",
    "sg:phone":"+34 938 70 44 58",
    "sg:postcode":"08402",
    "sg:province":"Barcelona",
    "wof:name":"Robleda Prats Enrique",
    "wof:placetype":"venue"
},
  "geometry": {"coordinates":[2.2890720367,41.6078491211],"type":"Point"}
}