{
  "type": "Feature",
  "properties": {
    "iso:country":"ES",
    "sg:address":"Calle de Libertad (de La), 51",
    "sg:city":"Alcobendas",
    "sg:orig_category":"Molduras, Junquillos, Listones Y Molduras Perforadas",
    "sg:phone":"+34 916 62 20 81",
    "sg:postcode":"28100",
    "sg:province":"Madrid",
    "wof:name":"Pe\u00f1a Fernandez Maria Del Carmen",
    "wof:placetype":"venue"
},
  "geometry": {"coordinates":[-3.6361548901,40.5393028259],"type":"Point"}
}