{
  "type": "Feature",
  "properties": {
    "iso:country":"ES",
    "sg:address":"Calle de Eolo, 20",
    "sg:city":"Valencia",
    "sg:orig_category":"Inmobiliaria (agencias)",
    "sg:phone":"+34 963 69 17 78",
    "sg:postcode":"46021",
    "sg:province":"Valencia",
    "wof:name":"Gesfesa Valencia S.l.",
    "wof:placetype":"venue"
},
  "geometry": {"coordinates":[-0.3565790057,39.4710388184],"type":"Point"}
}