{
  "type": "Feature",
  "properties": {
    "addr:full":"Los Llanos Del Padron, S/n Estepona M\u00e1laga 29680",
    "addr:housenumber":"s / n",
    "addr:postcode":"29680",
    "iso:country":"ES",
    "sg:address":"Los Llanos Del Padron, S/n",
    "sg:city":"Estepona",
    "sg:orig_category":"Empresas De Hormig\u00d3n, Hormig\u00d3n Armado Y Pretensado",
    "sg:phone":"+34 952 80 33 94",
    "sg:postcode":"29680",
    "sg:province":"M\u00e1laga",
    "wof:name":"Hormigones Y Morteros Preparados S.a.",
    "wof:placetype":"venue"
},
  "geometry": {"coordinates":[-5.1088891029,36.4361686707],"type":"Point"}
}