{
  "type": "Feature",
  "properties": {
    "iso:country":"ES",
    "sg:address":"Calle de Garay Juan De, 2",
    "sg:city":"Bilbao",
    "sg:orig_category":"Art\u00cdculos De Decoraci\u00d3n (fabricaci\u00d3n Y Al Por Mayor)",
    "sg:phone":"+34 944 10 31 94",
    "sg:postcode":"48003",
    "sg:province":"Vizcaya",
    "wof:name":"Fernando Aisa Aida De",
    "wof:placetype":"venue"
},
  "geometry": {"coordinates":[-2.933760643,43.2567176819],"type":"Point"}
}