{
  "type": "Feature",
  "properties": {
    "iso:country":"ES",
    "sg:address":"Carr Maset, 13",
    "sg:city":"Silla",
    "sg:orig_category":"Vidrio, Fabricaci\u00d3n Y Comercio",
    "sg:phone":"+34 961 20 07 51",
    "sg:postcode":"46460",
    "sg:province":"Valencia",
    "wof:name":"Lampisteria Valenciana S.l.",
    "wof:placetype":"venue"
},
  "geometry": {"coordinates":[-0.4175559878,39.3743171692],"type":"Point"}
}