{
  "type": "Feature",
  "properties": {
    "addr:full":"Zirkuitu Ibilbidea - Camino Del Circuito, 6 Oztaran Guip\u00f9zcoa 20160",
    "addr:housenumber":"6",
    "addr:postcode":"20160",
    "addr:street":"Zirkuitu Ibilbidea Camino Del Circuito;Guipu\u0300Zcoa",
    "iso:country":"ES",
    "sg:address":"Zirkuitu Ibilbidea - Camino Del Circuito, 6",
    "sg:city":"Oztaran",
    "sg:orig_category":"Mec\u00c1nico Del Autom\u00d3vil",
    "sg:phone":"+34 943 36 65 08",
    "sg:postcode":"20160",
    "sg:province":"Guip\u00f9zcoa",
    "wof:name":"Talleres Mecanicos San Jose Olaiz S.l.",
    "wof:placetype":"venue"
},
  "geometry": {"coordinates":[-2.020414114,43.2698173523],"type":"Point"}
}