{
  "type": "Feature",
  "properties": {
    "addr:full":"Calle de Encomienda, S/n Benavente Zamora 49600",
    "addr:housenumber":"s / n",
    "addr:postcode":"49600",
    "addr:street":"Calle De Encomienda",
    "iso:country":"ES",
    "sg:address":"Calle de Encomienda, S/n",
    "sg:city":"Benavente",
    "sg:orig_category":"Asociaciones, Organismos Culturales Y Socioeducativos",
    "sg:phone":"+34 980 63 33 32",
    "sg:postcode":"49600",
    "sg:province":"Zamora",
    "wof:name":"Ayuntamiento De Benavente",
    "wof:placetype":"venue"
},
  "geometry": {"coordinates":[-5.6774783134,42.003162384],"type":"Point"}
}