{
  "type": "Feature",
  "properties": {
    "addr:full":"Calle de Jake, S/n Molina Segura Murcia 30500",
    "addr:housenumber":"s",
    "addr:postcode":"30500",
    "addr:street":"Calle De Jake;/ N Molina",
    "iso:country":"ES",
    "sg:address":"Calle de Jake, S/n",
    "sg:city":"Molina Segura",
    "sg:orig_category":"Plomeros",
    "sg:phone":"+34 968 64 03 30",
    "sg:postcode":"30500",
    "sg:province":"Murcia",
    "wof:name":"Fontaneria Pastor S.l.",
    "wof:placetype":"venue"
},
  "geometry": {"coordinates":[-1.2195689678,38.0719337463],"type":"Point"}
}