{
  "type": "Feature",
  "properties": {
    "iso:country":"ES",
    "sg:address":"Rua Caldeireria (da), 9",
    "sg:city":"Santiago De Compostela",
    "sg:orig_category":"Lencer\u00cda Femenina, Corseter\u00cda, Trajes De Ba\u00d1o (al Por Menor)",
    "sg:phone":"+34 981 56 28 11",
    "sg:postcode":"15704",
    "sg:province":"La Coru\u00f1a",
    "wof:name":"Castro Tarela Manuela",
    "wof:placetype":"venue"
},
  "geometry": {"coordinates":[-8.5422143936,42.8794250488],"type":"Point"}
}