{
  "type": "Feature",
  "properties": {
    "addr:full":"El Molino, 14 Marbella M\u00e1laga 29600",
    "addr:housenumber":"14",
    "addr:postcode":"29600",
    "addr:street":"El Molino;Ma\u0301Laga",
    "iso:country":"ES",
    "sg:address":"El Molino, 14",
    "sg:city":"Marbella",
    "sg:orig_category":"Empresas De Carpinter\u00cda",
    "sg:phone":"+34 952 76 60 59",
    "sg:postcode":"29600",
    "sg:province":"M\u00e1laga",
    "wof:name":"Todocon Marbella S.l.",
    "wof:placetype":"venue"
},
  "geometry": {"coordinates":[-4.8569488525,36.5147094727],"type":"Point"}
}