{
  "type": "Feature",
  "properties": {
    "iso:country":"ES",
    "sg:address":"Calle de Capitan Rojas, 20",
    "sg:city":"Pe\u00f1afiel",
    "sg:orig_category":"Peluquer\u00cdas, Peluquer\u00cda Mixta",
    "sg:phone":"+34 983 88 01 52",
    "sg:postcode":"47300",
    "sg:province":"Valladolid",
    "wof:name":"Frias Ortega Laura",
    "wof:placetype":"venue"
},
  "geometry": {"coordinates":[-4.1192126274,41.5970611572],"type":"Point"}
}