{
  "type": "Feature",
  "properties": {
    "addr:full":"Calle de Cardenal Torquemada, S/n Valladolid Valladolid 47010",
    "addr:housenumber":"s / n",
    "addr:postcode":"47010",
    "addr:street":"Calle De Cardenal Torquemada",
    "iso:country":"ES",
    "sg:address":"Calle de Cardenal Torquemada, S/n",
    "sg:city":"Valladolid",
    "sg:orig_category":"Deportes Diversos",
    "sg:phone":"+34 983 25 79 53",
    "sg:postcode":"47010",
    "sg:province":"Valladolid",
    "wof:name":"Federacion Castellana Leonesa De Piraguismo",
    "wof:placetype":"venue"
},
  "geometry": {"coordinates":[-4.719016552,41.6651115417],"type":"Point"}
}