{
  "type": "Feature",
  "properties": {
    "iso:country":"ES",
    "sg:address":"Calle de Puerto De Barrameda, 14",
    "sg:city":"Bonanza",
    "sg:orig_category":"Aguas (distribuci\u00d3n, Servicios)",
    "sg:phone":"+34 956 38 45 66",
    "sg:postcode":"11540",
    "sg:province":"C\u00e1diz",
    "wof:name":"Aqualia Gestion Integral Del Agua S.a.",
    "wof:placetype":"venue"
},
  "geometry": {"coordinates":[-6.3367652893,36.7989959717],"type":"Point"}
}