{
  "type": "Feature",
  "properties": {
    "iso:country":"ES",
    "sg:address":"Calle de Mayor, 34",
    "sg:city":"Zubieta",
    "sg:orig_category":"Empresas De Desmonte",
    "sg:phone":"+34 948 45 14 68",
    "sg:postcode":"31746",
    "sg:province":"Navarra",
    "wof:name":"Pitti Eskabazyoak S.l",
    "wof:placetype":"venue"
},
  "geometry": {"coordinates":[-1.7424850464,43.1236877441],"type":"Point"}
}