{
  "type": "Feature",
  "properties": {
    "addr:full":"Carrer de Santa Magdalena, 49 Vilafranca Penedes Barcelona 08720",
    "addr:housenumber":"49",
    "addr:postcode":"08720",
    "addr:street":"Carrer De Santa Magdalena",
    "iso:country":"ES",
    "sg:address":"Carrer de Santa Magdalena, 49",
    "sg:city":"Vilafranca Penedes",
    "sg:orig_category":"Molduras, Junquillos, Listones Y Molduras Perforadas",
    "sg:phone":"+34 938 18 05 12",
    "sg:postcode":"08720",
    "sg:province":"Barcelona",
    "wof:name":"Balastegui Miguel Alberto",
    "wof:placetype":"venue"
},
  "geometry": {"coordinates":[1.7006164789,41.350189209],"type":"Point"}
}