{
  "type": "Feature",
  "properties": {
    "iso:country":"ES",
    "sg:address":"Calle de Goya, 1",
    "sg:city":"Torredelcampo",
    "sg:orig_category":"Trabajos De Topograf\u00cda",
    "sg:phone":"+34 953 41 14 58",
    "sg:postcode":"23640",
    "sg:province":"Ja\u00e9n",
    "wof:name":"Procardi S.l.",
    "wof:placetype":"venue"
},
  "geometry": {"coordinates":[-3.9001269341,37.7738647461],"type":"Point"}
}