{
  "type": "Feature",
  "properties": {
    "addr:full":"Carrer de Casals I Cubero, 187 Barcelona Barcelona 08042",
    "addr:housenumber":"187",
    "addr:postcode":"08042",
    "addr:street":"Carrer De Casals I Cubero",
    "iso:country":"ES",
    "sg:address":"Carrer de Casals I Cubero, 187",
    "sg:city":"Barcelona",
    "sg:orig_category":"Retoques De Vestidos",
    "sg:phone":"+34 933 53 35 28",
    "sg:postcode":"08042",
    "sg:province":"Barcelona",
    "wof:name":"Reboa Masiel Luis Alberto",
    "wof:placetype":"venue"
},
  "geometry": {"coordinates":[2.1742858887,41.4408683777],"type":"Point"}
}