{
  "type": "Feature",
  "properties": {
    "iso:country":"ES",
    "sg:address":"Calle de Pastor Y Landero, S/n",
    "sg:city":"Sevilla",
    "sg:orig_category":"Poller\u00cda Y Caza (al Por Menor)",
    "sg:phone":"+34 954 22 02 42",
    "sg:postcode":"41001",
    "sg:province":"Sevilla",
    "wof:name":"Sobrino Garcia Ana Maria",
    "wof:placetype":"venue"
},
  "geometry": {"coordinates":[-6.0002589226,37.3882637024],"type":"Point"}
}