{
  "type": "Feature",
  "properties": {
    "addr:full":"Avda Balaidos, 1 Vigo Pontevedra 36210",
    "addr:housenumber":"1",
    "addr:postcode":"36210",
    "addr:street":"Avda Balaidos",
    "iso:country":"ES",
    "sg:address":"Avda Balaidos, 1",
    "sg:city":"Vigo",
    "sg:orig_category":"Librer\u00cdas",
    "sg:phone":"+34 986 29 59 57",
    "sg:postcode":"36210",
    "sg:province":"Pontevedra",
    "wof:name":"Alonso Fernandez Servando",
    "wof:placetype":"venue"
},
  "geometry": {"coordinates":[-8.7323856354,42.2136268616],"type":"Point"}
}