{
  "type": "Feature",
  "properties": {
    "iso:country":"ES",
    "sg:address":"Estd Castela, 893",
    "sg:city":"Ponto",
    "sg:orig_category":"Muebles, Minoristas",
    "sg:phone":"+34 981 38 70 93",
    "sg:postcode":"15570",
    "sg:province":"A Coru\u00f1a",
    "wof:name":"Yedra Decoracion S.c.",
    "wof:placetype":"venue"
},
  "geometry": {"coordinates":[-8.3959693909,43.3714904785],"type":"Point"}
}