{
  "type": "Feature",
  "properties": {
    "iso:country":"ES",
    "sg:address":"San Antonio Kalea, 1",
    "sg:city":"Bergara",
    "sg:orig_category":"Telas Y Sedas (al Por Menor)",
    "sg:phone":"+34 943 76 22 93",
    "sg:postcode":"20570",
    "sg:province":"Guip\u00f9zcoa",
    "wof:name":"Tejidos Fernandez Cb",
    "wof:placetype":"venue"
},
  "geometry": {"coordinates":[-2.4134020805,43.1108474731],"type":"Point"}
}