{
  "type": "Feature",
  "properties": {
    "iso:country":"ES",
    "sg:address":"La Pedreguera, S/n",
    "sg:city":"Los Corrales",
    "sg:orig_category":"Reposter\u00cdas",
    "sg:phone":"+34 942 83 11 88",
    "sg:postcode":"39400",
    "sg:province":"Cantabria",
    "wof:name":"Panaderia Los Corrales S.l.",
    "wof:placetype":"venue"
},
  "geometry": {"coordinates":[-4.0666542053,43.2560577393],"type":"Point"}
}