{
  "type": "Feature",
  "properties": {
    "addr:full":"Ptda Agua Amarga, 1 Alacant Alicante 03008",
    "addr:housenumber":"1",
    "addr:postcode":"03008",
    "addr:street":"Ptda Agua Amarga",
    "iso:country":"ES",
    "sg:address":"Ptda Agua Amarga, 1",
    "sg:city":"Alacant",
    "sg:orig_category":"Promotores Constructores",
    "sg:phone":"+34 965 10 21 25",
    "sg:postcode":"03008",
    "sg:province":"Alicante",
    "wof:name":"Ute Desaladora Alicante",
    "wof:placetype":"venue"
},
  "geometry": {"coordinates":[-0.5224840045,38.2840309143],"type":"Point"}
}