{
  "type": "Feature",
  "properties": {
    "addr:full":"San Bartolome Kalea, 16 Elgoibar Guip\u00f9zcoa 20870",
    "addr:housenumber":"16",
    "addr:postcode":"20870",
    "addr:street":"San Bartolome Kalea;Guipu\u0300Zcoa",
    "iso:country":"ES",
    "sg:address":"San Bartolome Kalea, 16",
    "sg:city":"Elgoibar",
    "sg:orig_category":"Inmobiliaria (agencias)",
    "sg:phone":"+34 943 74 23 06",
    "sg:postcode":"20870",
    "sg:province":"Guip\u00f9zcoa",
    "wof:name":"Patricia Santander Coca",
    "wof:placetype":"venue"
},
  "geometry": {"coordinates":[-2.4167311192,43.2145385742],"type":"Point"}
}