{
  "type": "Feature",
  "properties": {
    "addr:full":"Av. Onze De Setembre, 279 Prat Llobregat Barcelona 08820",
    "addr:housenumber":"279",
    "addr:postcode":"08820",
    "addr:street":"Av. Onze De Setembre;Llobregat",
    "iso:country":"ES",
    "sg:address":"Av. Onze De Setembre, 279",
    "sg:city":"Prat Llobregat",
    "sg:orig_category":"Agentes, Concesionarios Y Sucursales De Veh\u00cdculos",
    "sg:phone":"+34 934 78 21 00",
    "sg:postcode":"08820",
    "sg:province":"Barcelona",
    "wof:name":"Automocion Prat S.l.",
    "wof:placetype":"venue"
},
  "geometry": {"coordinates":[2.1048603058,41.3227767944],"type":"Point"}
}