{
  "type": "Feature",
  "properties": {
    "iso:country":"ES",
    "sg:address":"Rua Mahatma Gandhi, 16",
    "sg:city":"Seixal",
    "sg:orig_category":"Arquitectos",
    "sg:phone":"+34 981 66 07 41",
    "sg:postcode":"15176",
    "sg:province":"La Coru\u00f1a",
    "wof:name":"Meijide Tomas Jorge Vicente",
    "wof:placetype":"venue"
},
  "geometry": {"coordinates":[-8.3503141403,43.3230743408],"type":"Point"}
}