{
  "type": "Feature",
  "properties": {
    "iso:country":"ES",
    "sg:address":"Calle de Rio Henares, 22",
    "sg:city":"Arroyomolinos",
    "sg:orig_category":"Embalajes",
    "sg:phone":"+34 916 09 10 79",
    "sg:postcode":"28939",
    "sg:province":"Madrid",
    "wof:name":"Cepherco Embalajes",
    "wof:placetype":"venue"
},
  "geometry": {"coordinates":[-3.919508934,40.2774505615],"type":"Point"}
}