{
  "type": "Feature",
  "properties": {
    "iso:country":"ES",
    "sg:address":"Calle de Bravo Murillo, 219",
    "sg:city":"Madrid",
    "sg:orig_category":"Cristaler\u00cdas",
    "sg:phone":"+34 915 79 25 88",
    "sg:postcode":"28020",
    "sg:province":"Madrid",
    "wof:name":"Cristaleria Jaf Marcris S.l.",
    "wof:placetype":"venue"
},
  "geometry": {"coordinates":[-3.7020661831,40.4566078186],"type":"Point"}
}