{
  "type": "Feature",
  "properties": {
    "iso:country":"ES",
    "sg:address":"Ctra Extremadura (zona Ind Camas), Km. 0437,5",
    "sg:city":"Camas",
    "sg:orig_category":"Delegados, Agentes De Tr\u00c1nsito, Auxiliares De Transporte Internacional",
    "sg:phone":"+34 955 98 05 17",
    "sg:postcode":"41900",
    "sg:province":"Sevilla",
    "wof:name":"Duran Castillo Francisco",
    "wof:placetype":"venue"
},
  "geometry": {"coordinates":[-6.0344491005,37.4007263184],"type":"Point"}
}