{
  "type": "Feature",
  "properties": {
    "iso:country":"ES",
    "sg:address":"Calle de Colegios (de Los), S/n",
    "sg:city":"Baralla",
    "sg:orig_category":"Quincaller\u00cda (al Por Menor)",
    "sg:phone":"+34 982 36 35 37",
    "sg:postcode":"27680",
    "sg:province":"Lugo",
    "wof:name":"Vazquez Martinez Emilio",
    "wof:placetype":"venue"
},
  "geometry": {"coordinates":[-7.2496991158,42.8941955566],"type":"Point"}
}