{
  "type": "Feature",
  "properties": {
    "addr:full":"Bilbao, 1 Espinosa Monteros Burgos 09560",
    "addr:housenumber":"1",
    "addr:postcode":"09560",
    "addr:street":"Bilbao",
    "iso:country":"ES",
    "sg:address":"Bilbao, 1",
    "sg:city":"Espinosa Monteros",
    "sg:orig_category":"Notarios",
    "sg:phone":"+34 947 12 03 14",
    "sg:postcode":"09560",
    "sg:province":"Burgos",
    "wof:name":"Giner Barcelo Elia",
    "wof:placetype":"venue"
},
  "geometry": {"coordinates":[-3.5772109032,43.0979499817],"type":"Point"}
}