{
  "type": "Feature",
  "properties": {
    "addr:full":"Calle de Poeta Vila Y Blanco, 15 Alacant Alicante 03003",
    "addr:housenumber":"15",
    "addr:postcode":"03003",
    "addr:street":"Calle De Poeta Vila Y Blanco",
    "iso:country":"ES",
    "sg:address":"Calle de Poeta Vila Y Blanco, 15",
    "sg:city":"Alacant",
    "sg:orig_category":"M\u00c9dicos: Medicina Interna",
    "sg:phone":"+34 965 92 81 36",
    "sg:postcode":"03003",
    "sg:province":"Alicante",
    "wof:name":"Teresa Parre\u00f1o Luis De",
    "wof:placetype":"venue"
},
  "geometry": {"coordinates":[-0.491241008,38.343875885],"type":"Point"}
}