{
  "type": "Feature",
  "properties": {
    "addr:full":"Calle de Joaquin Pascualita, 24 Casavieja \u00c1vila 05450",
    "addr:housenumber":"24",
    "addr:postcode":"05450",
    "addr:street":"Calle De Joaquin Pascualita;A\u0301Vila",
    "iso:country":"ES",
    "sg:address":"Calle de Joaquin Pascualita, 24",
    "sg:city":"Casavieja",
    "sg:orig_category":"Bisuter\u00cda, Joyer\u00cda, Relojer\u00cda (al Por Menor)",
    "sg:phone":"+34 918 67 83 29",
    "sg:postcode":"05450",
    "sg:province":"\u00c1vila",
    "wof:name":"Gregori Bensussan Claudio Roberto",
    "wof:placetype":"venue"
},
  "geometry": {"coordinates":[-4.7581248283,40.2964401245],"type":"Point"}
}