{
  "type": "Feature",
  "properties": {
    "addr:full":"Carrer de L'acer, 39 Barcelona Barcelona 08038",
    "addr:housenumber":"39",
    "addr:postcode":"08038",
    "addr:street":"Carrer De L'Acer",
    "iso:country":"ES",
    "sg:address":"Carrer de L'acer, 39",
    "sg:city":"Barcelona",
    "sg:orig_category":"Transporte En General",
    "sg:phone":"+34 932 23 30 67",
    "sg:postcode":"08038",
    "sg:province":"Barcelona",
    "wof:name":"Mct S. L.",
    "wof:placetype":"venue"
},
  "geometry": {"coordinates":[2.1358840466,41.3530158997],"type":"Point"}
}