{
  "type": "Feature",
  "properties": {
    "addr:full":"Calle de Duquesa De Parcent, 6 Malaga M\u00e1laga 29001",
    "addr:housenumber":"6",
    "addr:postcode":"29001",
    "addr:street":"Calle De Duquesa De Parcent;Ma\u0301Laga",
    "iso:country":"ES",
    "sg:address":"Calle de Duquesa De Parcent, 6",
    "sg:city":"Malaga",
    "sg:orig_category":"Asesor\u00cda Fiscal Y Jur\u00cddica",
    "sg:phone":"+34 952 22 67 47",
    "sg:postcode":"29001",
    "sg:province":"M\u00e1laga",
    "wof:name":"Paneque&troughton S.c",
    "wof:placetype":"venue"
},
  "geometry": {"coordinates":[-4.4229726791,36.7151031494],"type":"Point"}
}