{
  "type": "Feature",
  "properties": {
    "iso:country":"ES",
    "sg:address":"Calle de Fontanales, 81",
    "sg:city":"Palmas De Gran Canaria",
    "sg:orig_category":"Alimentaci\u00d3n General (al Por Menor)",
    "sg:phone":"+34 928 46 59 65",
    "sg:postcode":"35009",
    "sg:province":"Las Palmas",
    "wof:name":"Garcia Pulido Juan",
    "wof:placetype":"venue"
},
  "geometry": {"coordinates":[-15.4234323502,28.1517372131],"type":"Point"}
}