{
  "type": "Feature",
  "properties": {
    "iso:country":"ES",
    "sg:address":"Calle de Albacora (la), 20",
    "sg:city":"Algeciras",
    "sg:orig_category":"Empresas Portuarias",
    "sg:phone":"+34 956 60 24 39",
    "sg:postcode":"11207",
    "sg:province":"C\u00e1diz",
    "wof:name":"Abs Europe Limited Sucursal En Espa\u00f1a",
    "wof:placetype":"venue"
},
  "geometry": {"coordinates":[-5.438581,36.110043],"type":"Point"}
}