{
  "type": "Feature",
  "properties": {
    "addr:full":"Calle de Bruil, 2 Zaragoza Zaragoza 50001",
    "addr:housenumber":"2",
    "addr:postcode":"50001",
    "addr:street":"Calle De Bruil",
    "iso:country":"ES",
    "sg:address":"Calle de Bruil, 2",
    "sg:city":"Zaragoza",
    "sg:orig_category":"Promotores Constructores",
    "sg:phone":"+34 976 23 31 32",
    "sg:postcode":"50001",
    "sg:province":"Zaragoza",
    "wof:name":"Cyopsa Sisocia S.a.",
    "wof:placetype":"venue"
},
  "geometry": {"coordinates":[-0.8835222721,41.6485366821],"type":"Point"}
}