{
  "type": "Feature",
  "properties": {
    "iso:country":"ES",
    "sg:address":"Calle de Pozo, 2",
    "sg:city":"Arrabal De Portillo",
    "sg:orig_category":"Alfarer\u00cda",
    "sg:phone":"+34 983 55 62 43",
    "sg:postcode":"47160",
    "sg:province":"Valladolid",
    "wof:name":"Jose Antonio De La Calle Y Otros C.b.",
    "wof:placetype":"venue"
},
  "geometry": {"coordinates":[-4.5958600044,41.4751815796],"type":"Point"}
}