{
  "type": "Feature",
  "properties": {
    "addr:full":"Pase J.mig.barandiaran, 6 Donostia-san Sebastian Guip\u00f9zcoa 20013",
    "addr:housenumber":"6",
    "addr:postcode":"20013",
    "addr:street":"J.Mig.Barandiaran",
    "iso:country":"ES",
    "sg:address":"Pase J.mig.barandiaran, 6",
    "sg:city":"Donostia-san Sebastian",
    "sg:orig_category":"Empresarios",
    "sg:phone":"+34 943 27 08 40",
    "sg:postcode":"20013",
    "sg:province":"Guip\u00f9zcoa",
    "wof:name":"Iriarte Insausti Manuel",
    "wof:placetype":"venue"
},
  "geometry": {"coordinates":[-1.9711359739,43.3268165588],"type":"Point"}
}