{
  "type": "Feature",
  "properties": {
    "iso:country":"ES",
    "sg:address":"Calle de Blas Infante, 7",
    "sg:city":"Garciez",
    "sg:orig_category":"Asociaciones, Organismos Culturales Y Socioeducativos",
    "sg:phone":"+34 953 35 91 46",
    "sg:postcode":"23539",
    "sg:province":"Ja\u00e9n",
    "wof:name":"Asociacion Sociocultural Recreativa Y Deportiva Circulo De Amigos",
    "wof:placetype":"venue"
},
  "geometry": {"coordinates":[-3.4571456909,37.8739967346],"type":"Point"}
}