{
  "type": "Feature",
  "properties": {
    "addr:full":"Carrer de Vint, S/n Bonavista Tarragona 43100",
    "addr:housenumber":"s / n",
    "addr:postcode":"43100",
    "addr:street":"Carrer De Vint",
    "iso:country":"ES",
    "sg:address":"Carrer de Vint, S/n",
    "sg:city":"Bonavista",
    "sg:orig_category":"Asociaciones, Organismos Culturales Y Socioeducativos",
    "sg:phone":"+34 977 55 11 85",
    "sg:postcode":"43100",
    "sg:province":"Tarragona",
    "wof:name":"Asociacion Educativa El Trampoli",
    "wof:placetype":"venue"
},
  "geometry": {"coordinates":[1.1942013502,41.118309021],"type":"Point"}
}