{
  "type": "Feature",
  "properties": {
    "iso:country":"ES",
    "sg:address":"Alam San Mames, 37",
    "sg:city":"Bilbao",
    "sg:orig_category":"Promotores Constructores",
    "sg:phone":"+34 944 21 41 32",
    "sg:postcode":"48010",
    "sg:province":"Vizcaya",
    "wof:name":"Edificaciones Bietamendi S.l.",
    "wof:placetype":"venue"
},
  "geometry": {"coordinates":[-2.9382989407,43.2593727112],"type":"Point"}
}