{
  "type": "Feature",
  "properties": {
    "iso:country":"ES",
    "sg:address":"Avda Galicia (de), 29",
    "sg:city":"Monforte De Lemos",
    "sg:orig_category":"Abogados",
    "sg:phone":"+34 982 40 10 40",
    "sg:postcode":"27400",
    "sg:province":"Lugo",
    "wof:name":"Rodriguez Guitian Ruben Jose",
    "wof:placetype":"venue"
},
  "geometry": {"coordinates":[-7.5141239166,42.5200958252],"type":"Point"}
}