{
  "type": "Feature",
  "properties": {
    "addr:full":"Carr Marques De Campo, 38 Algemesi Valencia 46680",
    "addr:housenumber":"38",
    "addr:postcode":"46680",
    "addr:street":"Carr Marques De Campo",
    "iso:country":"ES",
    "sg:address":"Carr Marques De Campo, 38",
    "sg:city":"Algemesi",
    "sg:orig_category":"Escayola Y Productos De Escayola (fabricaci\u00d3n, Al Por Mayor)",
    "sg:phone":"+34 962 42 49 67",
    "sg:postcode":"46680",
    "sg:province":"Valencia",
    "wof:name":"Talamantes Lazaro S.l.",
    "wof:placetype":"venue"
},
  "geometry": {"coordinates":[-0.4317390025,39.1892738342],"type":"Point"}
}