{
  "type": "Feature",
  "properties": {
    "iso:country":"ES",
    "sg:address":"Pg Sant Joan Baptista La Salle, 9",
    "sg:city":"Cambrils",
    "sg:orig_category":"Inmobiliaria (agencias)",
    "sg:phone":"+34 977 36 69 15",
    "sg:postcode":"43850",
    "sg:province":"Tarragona",
    "wof:name":"Logicgest Inversion Inmobiliaria S.l.",
    "wof:placetype":"venue"
},
  "geometry": {"coordinates":[1.0553979874,41.0710639954],"type":"Point"}
}