{
  "type": "Feature",
  "properties": {
    "addr:full":"Calle de Fragua, 2 Coreses Zamora 49530",
    "addr:housenumber":"2",
    "addr:postcode":"49530",
    "addr:street":"Calle De Fragua",
    "iso:country":"ES",
    "sg:address":"Calle de Fragua, 2",
    "sg:city":"Coreses",
    "sg:orig_category":"Farmacias",
    "sg:phone":"+34 980 50 02 45",
    "sg:postcode":"49530",
    "sg:province":"Zamora",
    "wof:name":"Gomez Fidalgo Maria Jose",
    "wof:placetype":"venue"
},
  "geometry": {"coordinates":[-5.6216578484,41.5468711853],"type":"Point"}
}