{
  "type": "Feature",
  "properties": {
    "addr:full":"Av Flors, De Les, 9 Pont D'inca Islas Baleares 07009",
    "addr:housenumber":"9",
    "addr:postcode":"07009",
    "addr:street":"Av Flors De Les",
    "iso:country":"ES",
    "sg:address":"Av Flors, De Les, 9",
    "sg:city":"Pont D'inca",
    "sg:orig_category":"Animales (al Por Menor)",
    "sg:phone":"+34 971 79 55 90",
    "sg:postcode":"07009",
    "sg:province":"Islas Baleares",
    "wof:name":"Alonso Corcoles Doroteo",
    "wof:placetype":"venue"
},
  "geometry": {"coordinates":[2.6851475239,39.612071991],"type":"Point"}
}