{
  "type": "Feature",
  "properties": {
    "addr:full":"Carrer de Antoni Maura, 1 Terrassa Barcelona 08225",
    "addr:housenumber":"1",
    "addr:postcode":"08225",
    "addr:street":"Carrer De Antoni Maura",
    "iso:country":"ES",
    "sg:address":"Carrer de Antoni Maura, 1",
    "sg:city":"Terrassa",
    "sg:orig_category":"Pescader\u00cdas (al Por Menor)",
    "sg:phone":"+34 937 89 25 91",
    "sg:postcode":"08225",
    "sg:province":"Barcelona",
    "wof:name":"Aguirre Aguirre Pedro",
    "wof:placetype":"venue"
},
  "geometry": {"coordinates":[2.0028469563,41.571975708],"type":"Point"}
}