{
  "type": "Feature",
  "properties": {
    "addr:full":"Pl. Mercado, 30 Roquetas Mar Almer\u00eda 04740",
    "addr:postcode":"04740",
    "addr:street":"Mercado;Roquetas;Almeri\u0301A",
    "iso:country":"ES",
    "sg:address":"Pl. Mercado, 30",
    "sg:city":"Roquetas Mar",
    "sg:orig_category":"Productos Fitosanitarios (negocio, Aplicaci\u00d3n)",
    "sg:phone":"+34 950 32 31 09",
    "sg:postcode":"04740",
    "sg:province":"Almer\u00eda",
    "wof:name":"Agromarin S. A",
    "wof:placetype":"venue"
},
  "geometry": {"coordinates":[-2.595769,36.807377],"type":"Point"}
}