{
  "type": "Feature",
  "properties": {
    "iso:country":"ES",
    "sg:address":"Calle de Leon, 23",
    "sg:city":"Estepona",
    "sg:orig_category":"Centros Empresariales",
    "sg:phone":"+34 952 88 88 45",
    "sg:postcode":"29680",
    "sg:province":"M\u00e1laga",
    "wof:name":"Despacho De Asistencia Y Servicios Legales S.l.",
    "wof:placetype":"venue"
},
  "geometry": {"coordinates":[-5.0079360008,36.4618530273],"type":"Point"}
}