{
  "type": "Feature",
  "properties": {
    "addr:full":"Plaz Gabriel Alonso De Herrera, 8 Talavera La Nueva Toledo 45694",
    "addr:housenumber":"8",
    "addr:postcode":"45694",
    "iso:country":"ES",
    "sg:address":"Plaz Gabriel Alonso De Herrera, 8",
    "sg:city":"Talavera La Nueva",
    "sg:orig_category":"Confecci\u00d3n De Trajes Para Se\u00d1oras",
    "sg:phone":"+34 925 85 00 88",
    "sg:postcode":"45694",
    "sg:province":"Toledo",
    "wof:name":"Redondo Caja Alejandro",
    "wof:placetype":"venue"
},
  "geometry": {"coordinates":[-4.8914380074,39.9354743958],"type":"Point"}
}