{
  "type": "Feature",
  "properties": {
    "iso:country":"ES",
    "sg:address":"Poli Industrial Golparc, Km. 0489,0",
    "sg:city":"Codis",
    "sg:orig_category":"Venta, Montaje De Neum\u00c1ticos",
    "sg:phone":"+34 973 60 07 59",
    "sg:postcode":"25241",
    "sg:province":"Lleida",
    "wof:name":"Rodi Tr S.l.",
    "wof:placetype":"venue"
},
  "geometry": {"coordinates":[0.9323819876,41.6301574707],"type":"Point"}
}