{
  "type": "Feature",
  "properties": {
    "iso:country":"ES",
    "sg:address":"Calle de Pando, 8",
    "sg:city":"Torrelavega",
    "sg:orig_category":"Inmobiliaria (agencias)",
    "sg:phone":"+34 942 80 80 04",
    "sg:postcode":"39300",
    "sg:province":"Cantabria",
    "wof:name":"Construcciones Pinta S.l.",
    "wof:placetype":"venue"
},
  "geometry": {"coordinates":[-4.0461001396,43.3466873169],"type":"Point"}
}