{
  "type": "Feature",
  "properties": {
    "addr:full":"Calle de Teniente Serra, 2 Algeciras C\u00e1diz 11201",
    "addr:housenumber":"2;ca\u0301diz",
    "addr:postcode":"11201",
    "addr:street":"Calle De Teniente Serra",
    "iso:country":"ES",
    "sg:address":"Calle de Teniente Serra, 2",
    "sg:city":"Algeciras",
    "sg:orig_category":"Ropa Para Caballeros (al Por Menor)",
    "sg:phone":"+34 956 66 99 60",
    "sg:postcode":"11201",
    "sg:province":"C\u00e1diz",
    "wof:name":"Tacho Basic S.l.",
    "wof:placetype":"venue"
},
  "geometry": {"coordinates":[-5.446835041,36.1295776367],"type":"Point"}
}