{
  "type": "Feature",
  "properties": {
    "iso:country":"ES",
    "sg:address":"Calle de Simon Bolivar, 22",
    "sg:city":"Santa Cruz De Tenerife",
    "sg:orig_category":"Cristaler\u00cdas",
    "sg:phone":"+34 922 22 55 39",
    "sg:postcode":"38007",
    "sg:province":"Santa Cruz De Tenerife",
    "wof:name":"Regas Casellas Ramon",
    "wof:placetype":"venue"
},
  "geometry": {"coordinates":[-16.2717494965,28.4629096985],"type":"Point"}
}