{
  "type": "Feature",
  "properties": {
    "addr:full":"Ctra Molins De Rei, Km. 0013,5 Rubi Barcelona 08191",
    "addr:postcode":"08191",
    "addr:street":"Ctra Molins De Rei Km. 0013,5",
    "iso:country":"ES",
    "sg:address":"Ctra Molins De Rei, Km. 0013,5",
    "sg:city":"Rubi",
    "sg:orig_category":"Goma: Productos De Uso Industrial (fabricaci\u00d3n, Al Por Mayor)",
    "sg:phone":"+34 936 99 86 49",
    "sg:postcode":"08191",
    "sg:province":"Barcelona",
    "sg:website":"wwww.vigar-sa.es",
    "wof:name":"Vigar S. A.",
    "wof:placetype":"venue"
},
  "geometry": {"coordinates":[2.0307109356,41.4825019836],"type":"Point"}
}