{
  "type": "Feature",
  "properties": {
    "iso:country":"ES",
    "sg:address":"Calle de San Juan, 24",
    "sg:city":"Medina-sidonia",
    "sg:orig_category":"Relojer\u00cda (al Por Menor, Reparaci\u00d3n)",
    "sg:phone":"+34 956 41 02 90",
    "sg:postcode":"11170",
    "sg:province":"C\u00e1diz",
    "wof:name":"Joyeria Medina Cozar Sl",
    "wof:placetype":"venue"
},
  "geometry": {"coordinates":[-5.9279842377,36.4586639404],"type":"Point"}
}