{
  "type": "Feature",
  "properties": {
    "iso:country":"ES",
    "sg:address":"Calle de Hernando Colon, 6",
    "sg:city":"Sevilla",
    "sg:orig_category":"Art\u00cdculos De Regalo (al Por Menor)",
    "sg:phone":"+34 954 56 51 56",
    "sg:postcode":"41004",
    "sg:province":"Sevilla",
    "wof:name":"Acosta Avila Maria",
    "wof:placetype":"venue"
},
  "geometry": {"coordinates":[-5.993645668,37.3878517151],"type":"Point"}
}