{
  "type": "Feature",
  "properties": {
    "addr:full":"Calle de Ronda Mijares, 14 Castellon Castell\u00f3n 12001",
    "addr:housenumber":"14",
    "addr:postcode":"12001",
    "addr:street":"Calle De Ronda Mijares",
    "iso:country":"ES",
    "sg:address":"Calle de Ronda Mijares, 14",
    "sg:city":"Castellon",
    "sg:orig_category":"Promotores Constructores",
    "sg:phone":"+34 964 20 97 02",
    "sg:postcode":"12001",
    "sg:province":"Castell\u00f3n",
    "wof:name":"Roca Valles Jose",
    "wof:placetype":"venue"
},
  "geometry": {"coordinates":[-0.0390900001,39.9866714478],"type":"Point"}
}