{
  "type": "Feature",
  "properties": {
    "iso:country":"ES",
    "sg:address":"Pla\u00c7 Escola Pia (de L'), 3",
    "sg:city":"Gandia",
    "sg:orig_category":"Prendas Y Chalecos De Punto (al Por Menor)",
    "sg:phone":"+34 962 87 15 49",
    "sg:postcode":"46700",
    "sg:province":"Valencia",
    "wof:name":"Campos Almenar Enrique",
    "wof:placetype":"venue"
},
  "geometry": {"coordinates":[-0.1913339943,38.960735321],"type":"Point"}
}