{
  "type": "Feature",
  "properties": {
    "iso:country":"ES",
    "sg:address":"Rua Alfredo Bra\u00d1as (de), 23",
    "sg:city":"Santiago De Compostela",
    "sg:orig_category":"M\u00c9dicos: Estomatolog\u00cda",
    "sg:phone":"+34 981 59 63 65",
    "sg:postcode":"15701",
    "sg:province":"La Coru\u00f1a",
    "wof:name":"Pillado Vi\u00f1a Carlos Amador",
    "wof:placetype":"venue"
},
  "geometry": {"coordinates":[-8.5472660065,42.8737754822],"type":"Point"}
}