{
  "type": "Feature",
  "properties": {
    "addr:full":"Ubarburu Pasalekua, 71 Astigarraga Guip\u00f9zcoa 20115",
    "addr:housenumber":"71",
    "addr:postcode":"20115",
    "addr:street":"Ubarburu Pasalekua;Guipu\u0300Zcoa",
    "iso:country":"ES",
    "sg:address":"Ubarburu Pasalekua, 71",
    "sg:city":"Astigarraga",
    "sg:orig_category":"Transporte En General",
    "sg:phone":"+34 943 47 47 99",
    "sg:postcode":"20115",
    "sg:province":"Guip\u00f9zcoa",
    "wof:name":"Almacenes Integrales Del Norte S.l.",
    "wof:placetype":"venue"
},
  "geometry": {"coordinates":[-1.9427675009,43.2963218689],"type":"Point"}
}