{
  "type": "Feature",
  "properties": {
    "iso:country":"ES",
    "sg:address":"Barr Villanueva, 57",
    "sg:city":"G\u00fcemes",
    "sg:orig_category":"Bordado, Marcado A Medida",
    "sg:phone":"+34 942 62 19 80",
    "sg:postcode":"39191",
    "sg:province":"Cantabria",
    "sg:website":"www.bordatex.com",
    "wof:name":"Carral Llano Lidia",
    "wof:placetype":"venue"
},
  "geometry": {"coordinates":[-3.6366839409,43.4557189941],"type":"Point"}
}