{
  "type": "Feature",
  "properties": {
    "iso:country":"ES",
    "sg:address":"Calle de Valdelomar, 26",
    "sg:city":"Membrilla",
    "sg:orig_category":"Cer\u00c1mica Art\u00cdstica Y Decorativa",
    "sg:phone":"+34 926 63 67 19",
    "sg:postcode":"13230",
    "sg:province":"Ciudad Real",
    "wof:name":"Santiago Gavi\u00f1a Cristino De",
    "wof:placetype":"venue"
},
  "geometry": {"coordinates":[-3.3482170105,38.9753303528],"type":"Point"}
}