{
  "type": "Feature",
  "properties": {
    "iso:country":"ES",
    "sg:address":"Avda Fernandez Ladreda, 25",
    "sg:city":"Pontevedra",
    "sg:orig_category":"Fisioterapia",
    "sg:phone":"+34 986 86 48 70",
    "sg:postcode":"36003",
    "sg:province":"Pontevedra",
    "wof:name":"Gabinete Rivas S.l.",
    "wof:placetype":"venue"
},
  "geometry": {"coordinates":[-8.6424655914,42.4247894287],"type":"Point"}
}