{
  "type": "Feature",
  "properties": {
    "addr:full":"Punta Mala(el Alamillo), 24 Puerto Mazarron Murcia 30860",
    "addr:housenumber":"24",
    "addr:postcode":"30860",
    "addr:street":"El Alamillo",
    "iso:country":"ES",
    "sg:address":"Punta Mala(el Alamillo), 24",
    "sg:city":"Puerto Mazarron",
    "sg:orig_category":"Ferreter\u00cda (diversos)",
    "sg:phone":"+34 968 15 45 94",
    "sg:postcode":"30860",
    "sg:province":"Murcia",
    "wof:name":"Chatarra Hijos De Rojo S.l.",
    "wof:placetype":"venue"
},
  "geometry": {"coordinates":[-1.2754739523,37.5660057068],"type":"Point"}
}