{
  "type": "Feature",
  "properties": {
    "addr:full":"Avgd Pere Mas I Reus, S/n Platja D'alcudia Islas Baleares 07408",
    "addr:housenumber":"s / n",
    "addr:postcode":"07408",
    "addr:street":"D'Alcudia",
    "iso:country":"ES",
    "sg:address":"Avgd Pere Mas I Reus, S/n",
    "sg:city":"Platja D'alcudia",
    "sg:orig_category":"Alquiler De Veh\u00cdculos: Turismos Y Utilitarios",
    "sg:phone":"+34 971 89 13 53",
    "sg:postcode":"07408",
    "sg:province":"Islas Baleares",
    "wof:name":"Betacar S.a.",
    "wof:placetype":"venue"
},
  "geometry": {"coordinates":[3.1255340576,39.8456192017],"type":"Point"}
}