{
  "type": "Feature",
  "properties": {
    "iso:country":"ES",
    "sg:address":"Carrer de Santcliment, 9",
    "sg:city":"Barcelona",
    "sg:orig_category":"Asesor\u00cda Sobre Comunicaci\u00d3n De Empresas",
    "sg:phone":"+34 934 41 07 55",
    "sg:postcode":"08001",
    "sg:province":"Barcelona",
    "wof:name":"Jimeno Ramiro Mireya",
    "wof:placetype":"venue"
},
  "geometry": {"coordinates":[2.1652638912,41.3789024353],"type":"Point"}
}