{
  "type": "Feature",
  "properties": {
    "iso:country":"ES",
    "sg:address":"Torrealqueria, S/n",
    "sg:city":"Torrealqueria",
    "sg:orig_category":"Serigraf\u00cda (material Y Suministros)",
    "sg:phone":"+34 952 41 28 52",
    "sg:postcode":"29130",
    "sg:province":"M\u00e1laga",
    "sg:website":"www.harlequin.es",
    "wof:name":"Harlequin Nature Graphics S.a.",
    "wof:placetype":"venue"
},
  "geometry": {"coordinates":[-4.5667190552,36.6618614197],"type":"Point"}
}