{
  "type": "Feature",
  "properties": {
    "iso:country":"ES",
    "sg:address":"Calle de Argensola, 2",
    "sg:city":"Madrid",
    "sg:orig_category":"Molduras, Junquillos, Listones Y Molduras Perforadas",
    "sg:phone":"+34 913 08 13 52",
    "sg:postcode":"28004",
    "sg:province":"Madrid",
    "sg:website":"www.losada-ati.com",
    "wof:name":"Losada Asesoramiento Tecnico E Inmobiliario",
    "wof:placetype":"venue"
},
  "geometry": {"coordinates":[-3.6953854561,40.4246253967],"type":"Point"}
}