{
  "type": "Feature",
  "properties": {
    "addr:full":"Calle de Puente El, 2 Grado Asturias 33820",
    "addr:housenumber":"2",
    "addr:postcode":"33820",
    "addr:street":"Calle De Puente El",
    "iso:country":"ES",
    "sg:address":"Calle de Puente El, 2",
    "sg:city":"Grado",
    "sg:orig_category":"Mec\u00c1nico Del Autom\u00d3vil",
    "sg:phone":"+34 985 75 10 52",
    "sg:postcode":"33820",
    "sg:province":"Asturias",
    "wof:name":"Fernandez Martinez Jose Antonio",
    "wof:placetype":"venue"
},
  "geometry": {"coordinates":[-6.0709972382,43.3890724182],"type":"Point"}
}