{
  "type": "Feature",
  "properties": {
    "iso:country":"ES",
    "sg:address":"Avgd Generalitat De La, 4",
    "sg:city":"Igualada",
    "sg:orig_category":"Institutos De Belleza",
    "sg:phone":"+34 938 04 63 00",
    "sg:postcode":"08700",
    "sg:province":"Barcelona",
    "wof:name":"Ortiz Tironi Sonia",
    "wof:placetype":"venue"
},
  "geometry": {"coordinates":[1.6154839993,41.5915336609],"type":"Point"}
}