{
  "type": "Feature",
  "properties": {
    "iso:country":"ES",
    "sg:address":"Carrer de Eix Onze De Setembre, 16",
    "sg:city":"Vic",
    "sg:orig_category":"Venta, Montaje De Neum\u00c1ticos",
    "sg:phone":"+34 938 85 66 01",
    "sg:postcode":"08500",
    "sg:province":"Barcelona",
    "wof:name":"Neumatics Marcelino S.l.",
    "wof:placetype":"venue"
},
  "geometry": {"coordinates":[2.2525210381,41.9338531494],"type":"Point"}
}