{
  "type": "Feature",
  "properties": {
    "addr:full":"Avda Fisterra, 104 Cee La Coru\u00f1a 15270",
    "addr:housenumber":"104",
    "addr:postcode":"15270",
    "addr:street":"Avda Fisterra;La",
    "iso:country":"ES",
    "sg:address":"Avda Fisterra, 104",
    "sg:city":"Cee",
    "sg:orig_category":"Albergues",
    "sg:phone":"+34 981 74 59 47",
    "sg:postcode":"15270",
    "sg:province":"La Coru\u00f1a",
    "wof:name":"Crego Casas Adolfo",
    "wof:placetype":"venue"
},
  "geometry": {"coordinates":[-9.1939477921,42.9623794556],"type":"Point"}
}