{
  "type": "Feature",
  "properties": {
    "iso:country":"ES",
    "sg:address":"Calle de Zeletabe Kalea, 10",
    "sg:city":"Abadi\u00f1o",
    "sg:orig_category":"Aguas (distribuci\u00d3n, Servicios)",
    "sg:phone":"+34 944 66 90 00",
    "sg:postcode":"48220",
    "sg:province":"Vizcaya",
    "wof:name":"Ayuntamiento De La Anteiglesia De Abadi\u00f1o",
    "wof:placetype":"venue"
},
  "geometry": {"coordinates":[-2.6091356277,43.1517753601],"type":"Point"}
}