{
  "type": "Feature",
  "properties": {
    "addr:full":"Carr Castell, 35 Solsona Lleida 25280",
    "addr:housenumber":"35",
    "addr:postcode":"25280",
    "addr:street":"Carr Castell",
    "iso:country":"ES",
    "sg:address":"Carr Castell, 35",
    "sg:city":"Solsona",
    "sg:orig_category":"Carnicer\u00cdas, Carnicer\u00cdas",
    "sg:phone":"+34 973 48 11 67",
    "sg:postcode":"25280",
    "sg:province":"Lleida",
    "wof:name":"Xarcuteria Can Solvi S.l.",
    "wof:placetype":"venue"
},
  "geometry": {"coordinates":[1.5164539814,41.9945106506],"type":"Point"}
}