{
  "type": "Feature",
  "properties": {
    "iso:country":"ES",
    "sg:address":"Calle de Sierra Vicor, 41",
    "sg:city":"Zaragoza",
    "sg:orig_category":"Inmobiliaria (agencias)",
    "sg:phone":"+34 976 43 15 58",
    "sg:postcode":"50003",
    "sg:province":"Zaragoza",
    "wof:name":"Plurirent S.l.",
    "wof:placetype":"venue"
},
  "geometry": {"coordinates":[-0.8957579732,41.6625900269],"type":"Point"}
}