{
  "type": "Feature",
  "properties": {
    "addr:full":"Avda Reyes Catolicos, 2 Torres Cotillas Murcia 30565",
    "addr:housenumber":"2",
    "addr:postcode":"30565",
    "addr:street":"Avda Reyes Catolicos",
    "iso:country":"ES",
    "sg:address":"Avda Reyes Catolicos, 2",
    "sg:city":"Torres Cotillas",
    "sg:orig_category":"Maquinaria Para Industrias Diversas",
    "sg:phone":"+34 968 38 73 55",
    "sg:postcode":"30565",
    "sg:province":"Murcia",
    "wof:name":"Maquinaria Riquelme S.l.",
    "wof:placetype":"venue"
},
  "geometry": {"coordinates":[-1.2404979467,38.0278549194],"type":"Point"}
}