{
  "type": "Feature",
  "properties": {
    "addr:full":"C/ Manuel De Falla, 36 Salt Girona 17190",
    "addr:housenumber":"36",
    "addr:postcode":"17190",
    "addr:street":"C / Manuel De Falla",
    "iso:country":"ES",
    "sg:address":"C/ Manuel De Falla, 36",
    "sg:city":"Salt",
    "sg:orig_category":"Peluqueros: De Se\u00d1oras",
    "sg:phone":"+34 972 24 50 08",
    "sg:postcode":"17190",
    "sg:province":"Girona",
    "wof:name":"Guerrero Palma Maria Pilar",
    "wof:placetype":"venue"
},
  "geometry": {"coordinates":[2.7923150063,41.9758911133],"type":"Point"}
}