{
  "type": "Feature",
  "properties": {
    "iso:country":"ES",
    "sg:address":"Calle de Aldehuela (la), 7",
    "sg:city":"Berlanga Duero",
    "sg:orig_category":"Promotores Constructores",
    "sg:phone":"+34 975 34 32 85",
    "sg:postcode":"42360",
    "sg:province":"Soria",
    "wof:name":"Construcciones Robles Arranz S.l.",
    "wof:placetype":"venue"
},
  "geometry": {"coordinates":[-2.8618414402,41.4656448364],"type":"Point"}
}