{
  "type": "Feature",
  "properties": {
    "iso:country":"ES",
    "sg:address":"Rond General Mitre, 25",
    "sg:city":"Barcelona",
    "sg:orig_category":"Agencias De Trabajo Temporal",
    "sg:phone":"+34 932 80 53 96",
    "sg:postcode":"08017",
    "sg:province":"Barcelona",
    "wof:name":"Empleo A Tiempo Empresa De Trabajo Tempo",
    "wof:placetype":"venue"
},
  "geometry": {"coordinates":[2.132117033,41.393825531],"type":"Point"}
}