{
  "type": "Feature",
  "properties": {
    "iso:country":"ES",
    "sg:address":"Cno. Dehesa Vieja, S/n",
    "sg:city":"Guadamur",
    "sg:orig_category":"Lecher\u00cdas",
    "sg:phone":"+34 925 29 10 03",
    "sg:postcode":"45160",
    "sg:province":"Toledo",
    "wof:name":"Ganaderia Alonso S.l.",
    "wof:placetype":"venue"
},
  "geometry": {"coordinates":[-4.1539449692,39.8125419617],"type":"Point"}
}