{
  "type": "Feature",
  "properties": {
    "iso:country":"ES",
    "sg:address":"Av Ponent, 29",
    "sg:city":"Hospitalet Llobregat",
    "sg:orig_category":"Arquitectos",
    "sg:phone":"+34 934 49 51 30",
    "sg:postcode":"08905",
    "sg:province":"Barcelona",
    "wof:name":"Lopez Galan Juan Francisco",
    "wof:placetype":"venue"
},
  "geometry": {"coordinates":[2.1142499447,41.3692207336],"type":"Point"}
}