{
  "type": "Feature",
  "properties": {
    "addr:full":"C/ Soledat, De La, 31 S. Antoni Portmany Islas Baleares 07820",
    "addr:housenumber":"31",
    "addr:postcode":"07820",
    "addr:street":"C / Soledat De La",
    "iso:country":"ES",
    "sg:address":"C/ Soledat, De La, 31",
    "sg:city":"S. Antoni Portmany",
    "sg:orig_category":"Molduras, Junquillos, Listones Y Molduras Perforadas",
    "sg:phone":"+34 971 80 36 25",
    "sg:postcode":"07820",
    "sg:province":"Islas Baleares",
    "wof:name":"Costa Escandell Josefa",
    "wof:placetype":"venue"
},
  "geometry": {"coordinates":[1.5188339949,39.1094055176],"type":"Point"}
}