{
  "type": "Feature",
  "properties": {
    "iso:country":"ES",
    "sg:address":"Calle de Jacinto Labaila, 43",
    "sg:city":"Valencia",
    "sg:orig_category":"Centros Empresariales",
    "sg:phone":"+34 963 58 05 05",
    "sg:postcode":"46017",
    "sg:province":"Valencia",
    "wof:name":"Daniel Zurriaga S.l.",
    "wof:placetype":"venue"
},
  "geometry": {"coordinates":[-0.3929390013,39.4570617676],"type":"Point"}
}