{
  "type": "Feature",
  "properties": {
    "iso:country":"ES",
    "sg:address":"Calle de Jose Antonio, 1",
    "sg:city":"Armunia",
    "sg:orig_category":"Chapister\u00cda",
    "sg:phone":"+34 987 21 51 79",
    "sg:postcode":"24009",
    "sg:province":"Le\u00f3n",
    "wof:name":"Calvo Lopez Florentino",
    "wof:placetype":"venue"
},
  "geometry": {"coordinates":[-5.5877590179,42.5731925964],"type":"Point"}
}