{
  "type": "Feature",
  "properties": {
    "addr:full":"Gta Deportista Sergio Cardell, 1 Alacant Alicante 03540",
    "addr:housenumber":"1",
    "addr:postcode":"03540",
    "addr:street":"Cardell",
    "iso:country":"ES",
    "sg:address":"Gta Deportista Sergio Cardell, 1",
    "sg:city":"Alacant",
    "sg:orig_category":"Agencias Y Agentes Comerciales, Representantes",
    "sg:phone":"+34 965 26 29 93",
    "sg:postcode":"03540",
    "sg:province":"Alicante",
    "wof:name":"Laboratorios Normon S.a.",
    "wof:placetype":"venue"
},
  "geometry": {"coordinates":[-0.4320279956,38.3653755188],"type":"Point"}
}