{
  "type": "Feature",
  "properties": {
    "iso:country":"ES",
    "sg:address":"Ctra Antigua Nal Ciento Veinte, S/n",
    "sg:city":"Vilamartin Valdeorras",
    "sg:orig_category":"Pizzer\u00cdas",
    "sg:phone":"+34 988 30 00 06",
    "sg:postcode":"32340",
    "sg:province":"Ourense",
    "wof:name":"Pizarras Gallegas S.a.",
    "wof:placetype":"venue"
},
  "geometry": {"coordinates":[-7.0608639717,42.414264679],"type":"Point"}
}