{
  "type": "Feature",
  "properties": {
    "iso:country":"ES",
    "sg:address":"Rua Areal (do), 47",
    "sg:city":"Lalin",
    "sg:orig_category":"T\u00c9cnicos Veterinarios",
    "sg:phone":"+34 986 78 09 06",
    "sg:postcode":"36500",
    "sg:province":"Pontevedra",
    "wof:name":"Ocampo Cardalda Antonio",
    "wof:placetype":"venue"
},
  "geometry": {"coordinates":[-8.1106138229,42.6577606201],"type":"Point"}
}