{
  "type": "Feature",
  "properties": {
    "iso:country":"ES",
    "sg:address":"Calle de Mariano Ayala, 13",
    "sg:city":"Bollullos Par Condado",
    "sg:orig_category":"Confiter\u00cdas, Chocolater\u00cdas (al Por Menor)",
    "sg:phone":"+34 959 41 14 07",
    "sg:postcode":"21710",
    "sg:province":"Huelva",
    "wof:name":"Golosinas Y Ocio S.l.l.",
    "wof:placetype":"venue"
},
  "geometry": {"coordinates":[-6.5409269333,37.3387069702],"type":"Point"}
}