{
  "type": "Feature",
  "properties": {
    "addr:full":"Estd Palma, 245 Pombal La Coru\u00f1a 15520",
    "addr:housenumber":"245",
    "addr:postcode":"15520",
    "addr:street":"Palma;La Corun\u0303A",
    "iso:country":"ES",
    "sg:address":"Estd Palma, 245",
    "sg:city":"Pombal",
    "sg:orig_category":"Electricidad, Electr\u00d3nica: Material Y Suministros (al Por Mayor)",
    "sg:phone":"+34 981 49 20 03",
    "sg:postcode":"15520",
    "sg:province":"La Coru\u00f1a",
    "wof:name":"Ielec Industria Y Electricidad Sl",
    "wof:placetype":"venue"
},
  "geometry": {"coordinates":[-8.1830301285,43.4555435181],"type":"Point"}
}