{
  "type": "Feature",
  "properties": {
    "iso:country":"ES",
    "sg:address":"Calle de Leon, 3",
    "sg:city":"Madrid",
    "sg:orig_category":"Molduras, Junquillos, Listones Y Molduras Perforadas",
    "sg:phone":"+34 914 20 20 38",
    "sg:postcode":"28014",
    "sg:province":"Madrid",
    "wof:name":"Mariba\u00f1ez Y Larriba S.l.",
    "wof:placetype":"venue"
},
  "geometry": {"coordinates":[-3.6983880997,40.4146537781],"type":"Point"}
}