{
  "type": "Feature",
  "properties": {
    "addr:full":"Calle de Rincones (los), S/n Zuera Zaragoza 50800",
    "addr:postcode":"50800",
    "addr:street":"Calle De;Los S / N",
    "iso:country":"ES",
    "sg:address":"Calle de Rincones (los), S/n",
    "sg:city":"Zuera",
    "sg:orig_category":"Ense\u00d1anza Secundaria: Colegios Y Escuelas Privadas",
    "sg:phone":"+34 976 68 05 02",
    "sg:postcode":"50800",
    "sg:province":"Zaragoza",
    "wof:name":"Colegio El Pilar Maristas Hermanos Maristas Provincia Norte",
    "wof:placetype":"venue"
},
  "geometry": {"coordinates":[-0.7892619967,41.873878479],"type":"Point"}
}