{
  "type": "Feature",
  "properties": {
    "addr:full":"Trva Meicende, 140 Meicende La Coru\u00f1a 15140",
    "addr:housenumber":"140",
    "addr:postcode":"15140",
    "addr:street":"Trva Meicende;La Corun\u0303A",
    "iso:country":"ES",
    "sg:address":"Trva Meicende, 140",
    "sg:city":"Meicende",
    "sg:orig_category":"Frutas, Legumbres Frescas Y Tempranas (al Por Menor)",
    "sg:phone":"+34 981 27 72 67",
    "sg:postcode":"15140",
    "sg:province":"La Coru\u00f1a",
    "wof:name":"Pensado Varela Francisco Javier",
    "wof:placetype":"venue"
},
  "geometry": {"coordinates":[-8.448767662,43.3449821472],"type":"Point"}
}