{
  "type": "Feature",
  "properties": {
    "iso:country":"ES",
    "sg:address":"Rua Montevideo, 4",
    "sg:city":"Lugo",
    "sg:orig_category":"Psic\u00d3logos",
    "sg:phone":"+34 982 25 09 07",
    "sg:postcode":"27001",
    "sg:province":"Lugo",
    "wof:name":"Novo Teijeiro Maria Celia",
    "wof:placetype":"venue"
},
  "geometry": {"coordinates":[-7.5602011681,43.0125656128],"type":"Point"}
}