{
  "type": "Feature",
  "properties": {
    "addr:full":"Avda Almerimar, S/n Almerimar Almer\u00eda 04711",
    "addr:housenumber":"s / n",
    "addr:postcode":"04711",
    "addr:street":"Avda Almerimar;Almerimar Almeri\u0301A",
    "iso:country":"ES",
    "sg:address":"Avda Almerimar, S/n",
    "sg:city":"Almerimar",
    "sg:orig_category":"Arboricultura Y Producci\u00d3n De Frutas",
    "sg:phone":"+34 950 60 77 37",
    "sg:postcode":"04711",
    "sg:province":"Almer\u00eda",
    "wof:name":"Eurespa S.a.",
    "wof:placetype":"venue"
},
  "geometry": {"coordinates":[-2.7796189785,36.6923789978],"type":"Point"}
}