{
  "type": "Feature",
  "properties": {
    "iso:country":"ES",
    "sg:address":"Calle de Conde De Sobradiel, 7",
    "sg:city":"Zaragoza",
    "sg:orig_category":"Contenedores (mercanc\u00cdas)",
    "sg:phone":"+34 976 53 74 85",
    "sg:postcode":"50011",
    "sg:province":"Zaragoza",
    "wof:name":"Transportes Monterde 2002 S.l.",
    "wof:placetype":"venue"
},
  "geometry": {"coordinates":[-0.9224780202,41.6489257812],"type":"Point"}
}