{
  "type": "Feature",
  "properties": {
    "iso:country":"ES",
    "sg:address":"Calle de Pantano, 1",
    "sg:city":"San Isidro Nijar",
    "sg:orig_category":"Panader\u00cdas, Panader\u00cdas",
    "sg:phone":"+34 950 36 61 82",
    "sg:postcode":"04117",
    "sg:province":"Almer\u00eda",
    "wof:name":"Hernandez Jimenez Diego",
    "wof:placetype":"venue"
},
  "geometry": {"coordinates":[-2.1761538982,36.9084358215],"type":"Point"}
}