{
  "type": "Feature",
  "properties": {
    "addr:full":"Avda Ribera De Axpe Etorbidea, 1 D Erandio Vizcaya 48950",
    "addr:housenumber":"1 d",
    "addr:postcode":"48950",
    "addr:street":"Avda Ribera De Axpe Etorbidea",
    "iso:country":"ES",
    "sg:address":"Avda Ribera De Axpe Etorbidea, 1 D",
    "sg:city":"Erandio",
    "sg:orig_category":"Asesor\u00cda, Estudio Y Control Medioambiental",
    "sg:phone":"+34 944 04 19 19",
    "sg:postcode":"48950",
    "sg:province":"Vizcaya",
    "sg:website":"www.ekotek.euskalnet.net",
    "wof:name":"Ekotek, S.l.",
    "wof:placetype":"venue"
},
  "geometry": {"coordinates":[-2.9769239426,43.302646637],"type":"Point"}
}