{
  "type": "Feature",
  "properties": {
    "iso:country":"ES",
    "sg:address":"Calle de Cadiz, 80",
    "sg:city":"Valencia",
    "sg:orig_category":"Farmacias",
    "sg:phone":"+34 963 74 41 26",
    "sg:postcode":"46006",
    "sg:province":"Valencia",
    "wof:name":"Lopez Oroval Josefina",
    "wof:placetype":"venue"
},
  "geometry": {"coordinates":[-0.3724152148,39.4601325989],"type":"Point"}
}