{
  "type": "Feature",
  "properties": {
    "addr:full":"Calle de Palmita La, 18 Ag\u00fcimes Las Palmas 35260",
    "addr:housenumber":"18",
    "addr:postcode":"35260",
    "addr:street":"Calle De Palmita La",
    "iso:country":"ES",
    "sg:address":"Calle de Palmita La, 18",
    "sg:city":"Ag\u00fcimes",
    "sg:orig_category":"Ropa Para Se\u00d1oras Y Caballeros (al Por Menor)",
    "sg:phone":"+34 928 78 19 26",
    "sg:postcode":"35260",
    "sg:province":"Las Palmas",
    "wof:name":"Vega Bordon Isabel",
    "wof:placetype":"venue"
},
  "geometry": {"coordinates":[-15.4453115463,27.9044952393],"type":"Point"}
}