{
  "type": "Feature",
  "properties": {
    "addr:full":"Ctra Arahal-coronil, Km. 0001,0 Arahal Sevilla 41600",
    "addr:postcode":"41600",
    "addr:street":"Ctra Arahal-Coronil Km. 0001,0",
    "iso:country":"ES",
    "sg:address":"Ctra Arahal-coronil, Km. 0001,0",
    "sg:city":"Arahal",
    "sg:orig_category":"Productos Alimentarios",
    "sg:phone":"+34 954 84 11 02",
    "sg:postcode":"41600",
    "sg:province":"Sevilla",
    "wof:name":"Fernandez Gamboa Manuel",
    "wof:placetype":"venue"
},
  "geometry": {"coordinates":[-5.5452737808,37.2582397461],"type":"Point"}
}