{
  "type": "Feature",
  "properties": {
    "addr:full":"Calle de Capitan Cortes, 43 Huesas Las Palmas 35200",
    "addr:housenumber":"43",
    "addr:postcode":"35200",
    "addr:street":"Calle De Capitan Cortes;Las Palmas",
    "iso:country":"ES",
    "sg:address":"Calle de Capitan Cortes, 43",
    "sg:city":"Huesas",
    "sg:orig_category":"Peluquer\u00cdas, Peluquer\u00cda Mixta",
    "sg:phone":"+34 928 68 40 59",
    "sg:postcode":"35200",
    "sg:province":"Las Palmas",
    "wof:name":"Suarez Gonzalez Ana Maria",
    "wof:placetype":"venue"
},
  "geometry": {"coordinates":[-15.3956928253,27.9842014313],"type":"Point"}
}