{
  "type": "Feature",
  "properties": {
    "iso:country":"ES",
    "sg:address":"Carrer de Major (sant Celoni), 150",
    "sg:city":"S. Celoni",
    "sg:orig_category":"Zapatos (al Por Menor)",
    "sg:phone":"+34 938 67 37 66",
    "sg:postcode":"08470",
    "sg:province":"Barcelona",
    "wof:name":"Recio Diaz Maria Pilar",
    "wof:placetype":"venue"
},
  "geometry": {"coordinates":[2.4915819168,41.6897354126],"type":"Point"}
}