{
  "type": "Feature",
  "properties": {
    "addr:full":"D'ondara, S/n Alfarp Valencia 46197",
    "addr:housenumber":"s / n",
    "addr:postcode":"46197",
    "addr:street":"D'Ondara",
    "iso:country":"ES",
    "sg:address":"D'ondara, S/n",
    "sg:city":"Alfarp",
    "sg:orig_category":"Explotaci\u00d3n De Canteras",
    "sg:phone":"+34 962 55 02 67",
    "sg:postcode":"46197",
    "sg:province":"Valencia",
    "wof:name":"Pala Arre S.a.",
    "wof:placetype":"venue"
},
  "geometry": {"coordinates":[-0.5605800152,39.2781639099],"type":"Point"}
}