{
  "type": "Feature",
  "properties": {
    "addr:full":"Pase Cerrado De Calderon, 14 Malaga M\u00e1laga 29018",
    "addr:housenumber":"14",
    "addr:postcode":"29018",
    "addr:street":"Malaga Ma\u0301Laga",
    "iso:country":"ES",
    "sg:address":"Pase Cerrado De Calderon, 14",
    "sg:city":"Malaga",
    "sg:orig_category":"Peluquer\u00cdas, Peluquer\u00cda Mixta",
    "sg:phone":"+34 952 29 66 05",
    "sg:postcode":"29018",
    "sg:province":"M\u00e1laga",
    "wof:name":"Caravaca Perez Francisco",
    "wof:placetype":"venue"
},
  "geometry": {"coordinates":[-4.3814778328,36.7250518799],"type":"Point"}
}