{
  "type": "Feature",
  "properties": {
    "addr:full":"A Condomi\u00f1a, S/n Orto\u00f1o A Coru\u00f1a 15228",
    "addr:housenumber":"s",
    "addr:postcode":"15228",
    "addr:street":"/ N;Corun\u0303A",
    "iso:country":"ES",
    "sg:address":"A Condomi\u00f1a, S/n",
    "sg:city":"Orto\u00f1o",
    "sg:orig_category":"Centros Empresariales",
    "sg:phone":"+34 981 89 19 59",
    "sg:postcode":"15228",
    "sg:province":"A Coru\u00f1a",
    "wof:name":"Servicios Renovables De Galicia S.l.",
    "wof:placetype":"venue"
},
  "geometry": {"coordinates":[-8.6333398819,42.8469085693],"type":"Point"}
}