{
  "type": "Feature",
  "properties": {
    "iso:country":"ES",
    "sg:address":"Calle de Domingo Miral, 23",
    "sg:city":"Zaragoza",
    "sg:orig_category":"Ense\u00d1anza: Idiomas",
    "sg:phone":"+34 976 35 74 00",
    "sg:postcode":"50009",
    "sg:province":"Zaragoza",
    "wof:name":"Escuela Oficial De Idiomas Numero Uno",
    "wof:placetype":"venue"
},
  "geometry": {"coordinates":[-0.9018247128,41.6407089233],"type":"Point"}
}