{
  "type": "Feature",
  "properties": {
    "addr:full":"Av Catalunya, 43 Sant Joan De Palamos Girona 17230",
    "addr:housenumber":"43",
    "addr:postcode":"17230",
    "addr:street":"Av Catalunya",
    "iso:country":"ES",
    "sg:address":"Av Catalunya, 43",
    "sg:city":"Sant Joan De Palamos",
    "sg:orig_category":"Molduras, Junquillos, Listones Y Molduras Perforadas",
    "sg:phone":"+34 972 31 41 50",
    "sg:postcode":"17230",
    "sg:province":"Girona",
    "wof:name":"Fernandez Gomez Luis",
    "wof:placetype":"venue"
},
  "geometry": {"coordinates":[3.1241919994,41.8523483276],"type":"Point"}
}