{
  "type": "Feature",
  "properties": {
    "iso:country":"ES",
    "sg:address":"San Andres, 18",
    "sg:city":"Cuevas Almanzora",
    "sg:orig_category":"Escayola Y Productos De Escayola (fabricaci\u00d3n, Al Por Mayor)",
    "sg:phone":"+34 950 45 67 69",
    "sg:postcode":"04610",
    "sg:province":"Almer\u00eda",
    "wof:name":"Larios Segura Miguel",
    "wof:placetype":"venue"
},
  "geometry": {"coordinates":[-1.8822439909,37.2990951538],"type":"Point"}
}