{
  "type": "Feature",
  "properties": {
    "addr:full":"Cjon De San Marcos, S/n Baza Granada 18800",
    "addr:housenumber":"s",
    "addr:postcode":"18800",
    "addr:street":"Cjon De San Marcos;/ N",
    "iso:country":"ES",
    "sg:address":"Cjon De San Marcos, S/n",
    "sg:city":"Baza",
    "sg:orig_category":"Supermercados Y Hipermercados",
    "sg:phone":"+34 958 70 22 84",
    "sg:postcode":"18800",
    "sg:province":"Granada",
    "wof:name":"Checa Garcia Juana",
    "wof:placetype":"venue"
},
  "geometry": {"coordinates":[-2.7749290466,37.4826889038],"type":"Point"}
}