{
  "type": "Feature",
  "properties": {
    "iso:country":"ES",
    "sg:address":"Carrer de Aribau, 263",
    "sg:city":"Barcelona",
    "sg:orig_category":"Arquitectos",
    "sg:phone":"+34 934 14 20 94",
    "sg:postcode":"08021",
    "sg:province":"Barcelona",
    "wof:name":"Garcia Gabarro Gustavo",
    "wof:placetype":"venue"
},
  "geometry": {"coordinates":[2.1457109451,41.3990058899],"type":"Point"}
}