{
  "type": "Feature",
  "properties": {
    "addr:full":"Calle de Montserrat, 1 Linea De La Concepcion C\u00e1diz 11300",
    "addr:housenumber":"1",
    "addr:postcode":"11300",
    "addr:street":"Calle De Montserrat;Ca\u0301Diz",
    "iso:country":"ES",
    "sg:address":"Calle de Montserrat, 1",
    "sg:city":"Linea De La Concepcion",
    "sg:orig_category":"Asociaciones Y Clubs Deportivos",
    "sg:phone":"+34 956 76 72 05",
    "sg:postcode":"11300",
    "sg:province":"C\u00e1diz",
    "wof:name":"Club Deportivo Andalucia",
    "wof:placetype":"venue"
},
  "geometry": {"coordinates":[-5.340939045,36.1683044434],"type":"Point"}
}