{
  "type": "Feature",
  "properties": {
    "iso:country":"ES",
    "sg:address":"Carrer de Ferreria, 9",
    "sg:city":"Roquetes",
    "sg:orig_category":"Empresas De Carpinter\u00cda De Madera",
    "sg:phone":"+34 977 50 15 73",
    "sg:postcode":"43520",
    "sg:province":"Tarragona",
    "wof:name":"Fusteria Fabregat S.l.",
    "wof:placetype":"venue"
},
  "geometry": {"coordinates":[0.5061810017,40.8211402893],"type":"Point"}
}