{
  "type": "Feature",
  "properties": {
    "iso:country":"ES",
    "sg:address":"Avda Machupichu, 27",
    "sg:city":"Madrid",
    "sg:orig_category":"Caf\u00c9s, Bares, Cervecer\u00cdas",
    "sg:phone":"+34 917 59 14 10",
    "sg:postcode":"28043",
    "sg:province":"Madrid",
    "wof:name":"Narciso Y Vicenta S.l.",
    "wof:placetype":"venue"
},
  "geometry": {"coordinates":[-3.6262331009,40.4586791992],"type":"Point"}
}