{
  "type": "Feature",
  "properties": {
    "iso:country":"ES",
    "sg:address":"Av Pais Valencia, 116",
    "sg:city":"Benissa",
    "sg:orig_category":"M\u00c9dicos: Medicina General",
    "sg:phone":"+34 965 73 18 71",
    "sg:postcode":"03720",
    "sg:province":"Alicante",
    "wof:name":"Cabrera Amoros Pedro Juan",
    "wof:placetype":"venue"
},
  "geometry": {"coordinates":[0.0509429984,38.7146224976],"type":"Point"}
}