{
  "type": "Feature",
  "properties": {
    "addr:full":"Calle de Alvarado, 3 Villanueva Serena Badajoz 06700",
    "addr:housenumber":"3",
    "addr:postcode":"06700",
    "addr:street":"Calle De Alvarado",
    "iso:country":"ES",
    "sg:address":"Calle de Alvarado, 3",
    "sg:city":"Villanueva Serena",
    "sg:orig_category":"Molduras, Junquillos, Listones Y Molduras Perforadas",
    "sg:phone":"+34 924 84 19 86",
    "sg:postcode":"06700",
    "sg:province":"Badajoz",
    "wof:name":"Nieto Jimenez Antonio",
    "wof:placetype":"venue"
},
  "geometry": {"coordinates":[-5.7972707748,38.9752655029],"type":"Point"}
}