{
  "type": "Feature",
  "properties": {
    "addr:full":"Calle de Alcala, 96 Madrid Madrid 28009",
    "addr:housenumber":"96",
    "addr:postcode":"madrid;28009",
    "addr:street":"Calle De Alcala",
    "iso:country":"ES",
    "sg:address":"Calle de Alcala, 96",
    "sg:city":"Madrid",
    "sg:orig_category":"Centros Empresariales",
    "sg:phone":"+34 915 78 24 87",
    "sg:postcode":"28009",
    "sg:province":"Madrid",
    "wof:name":"Carlos Miguelez & Co S.l.",
    "wof:placetype":"venue"
},
  "geometry": {"coordinates":[-3.6762502193,40.4245147705],"type":"Point"}
}