{
  "type": "Feature",
  "properties": {
    "addr:full":"Calle de Leon, 21 Fuenlabrada Madrid 28947",
    "addr:housenumber":"21",
    "addr:postcode":"28947",
    "addr:street":"Calle De Leon",
    "iso:country":"ES",
    "sg:address":"Calle de Leon, 21",
    "sg:city":"Fuenlabrada",
    "sg:orig_category":"Art\u00cdculos De Regalo (al Por Menor)",
    "sg:phone":"+34 916 42 29 45",
    "sg:postcode":"28947",
    "sg:province":"Madrid",
    "wof:name":"Yu  Xiaoqiang",
    "wof:placetype":"venue"
},
  "geometry": {"coordinates":[-3.7447366714,40.2637634277],"type":"Point"}
}