{
  "type": "Feature",
  "properties": {
    "iso:country":"ES",
    "sg:address":"Carr Teulera, 39",
    "sg:city":"Santa Cristina D'aro",
    "sg:orig_category":"Centros De Coordinaci\u00d3n",
    "sg:phone":"+34 972 83 71 65",
    "sg:postcode":"17246",
    "sg:province":"Girona",
    "wof:name":"Vilanova Gestio I Assessorament S.l.",
    "wof:placetype":"venue"
},
  "geometry": {"coordinates":[2.8381810188,41.9668312073],"type":"Point"}
}