{
  "type": "Feature",
  "properties": {
    "addr:full":"Calle de Artal De Huerta, S/n Montalban Teruel 44700",
    "addr:housenumber":"s / n",
    "addr:postcode":"44700",
    "addr:street":"Calle De Artal De Huerta",
    "iso:country":"ES",
    "sg:address":"Calle de Artal De Huerta, S/n",
    "sg:city":"Montalban",
    "sg:orig_category":"Notarios",
    "sg:phone":"+34 978 75 00 78",
    "sg:postcode":"44700",
    "sg:province":"Teruel",
    "wof:name":"Peiro Fernandez-checa Eva Maria",
    "wof:placetype":"venue"
},
  "geometry": {"coordinates":[-0.8007196784,40.8315963745],"type":"Point"}
}