{
  "type": "Feature",
  "properties": {
    "addr:full":"Calle de Francia, 6 Monta\u00e7a Roja Las Palmas 35580",
    "addr:housenumber":"6",
    "addr:postcode":"35580",
    "addr:street":"Calle De Francia",
    "iso:country":"ES",
    "sg:address":"Calle de Francia, 6",
    "sg:city":"Monta\u00e7a Roja",
    "sg:orig_category":"Inmobiliaria (agencias)",
    "sg:phone":"+34 928 51 85 45",
    "sg:postcode":"35580",
    "sg:province":"Las Palmas",
    "wof:name":"Grupo Alcala 70 S.a.",
    "wof:placetype":"venue"
},
  "geometry": {"coordinates":[-15.4300060272,28.1248226166],"type":"Point"}
}