{
  "type": "Feature",
  "properties": {
    "iso:country":"ES",
    "sg:address":"Calle de Pizarro, 1",
    "sg:city":"Valencia",
    "sg:orig_category":"Loter\u00cda Y T\u00d3mbola",
    "sg:phone":"+34 963 51 77 82",
    "sg:postcode":"46004",
    "sg:province":"Valencia",
    "wof:name":"Bayo Diaz Jesus Antonio",
    "wof:placetype":"venue"
},
  "geometry": {"coordinates":[-0.3725999892,39.4683570862],"type":"Point"}
}