{
  "type": "Feature",
  "properties": {
    "addr:full":"Av. Andalucia, 3 Jun Granada 18213",
    "addr:housenumber":"3",
    "addr:postcode":"18213",
    "addr:street":"Av. Andalucia",
    "iso:country":"ES",
    "sg:address":"Av. Andalucia, 3",
    "sg:city":"Jun",
    "sg:orig_category":"Bazares, Art\u00cdculos De Limpieza Y De Cocina (al Por Menor)",
    "sg:phone":"+34 958 41 61 01",
    "sg:postcode":"18213",
    "sg:province":"Granada",
    "wof:name":"Maldonado Cortes Trinidad",
    "wof:placetype":"venue"
},
  "geometry": {"coordinates":[-3.593818903,37.220161438],"type":"Point"}
}