{
  "type": "Feature",
  "properties": {
    "addr:full":"Calle de Angela Gonzalez, 18 Madrid Madrid 28038",
    "addr:housenumber":"18",
    "addr:postcode":"madrid;28038",
    "addr:street":"Calle De Angela Gonzalez",
    "iso:country":"ES",
    "sg:address":"Calle de Angela Gonzalez, 18",
    "sg:city":"Madrid",
    "sg:orig_category":"Empresas De Carpinter\u00cda De Madera",
    "sg:phone":"+34 914 39 90 32",
    "sg:postcode":"28038",
    "sg:province":"Madrid",
    "wof:name":"Villaseca Fontan Jose Antonio",
    "wof:placetype":"venue"
},
  "geometry": {"coordinates":[-3.66010499,40.3983039856],"type":"Point"}
}