{
  "type": "Feature",
  "properties": {
    "addr:full":"Pase Delicias, S/n Madrid Madrid 28045",
    "addr:housenumber":"s / n",
    "addr:postcode":"28045",
    "addr:street":"Delicias",
    "iso:country":"ES",
    "sg:address":"Pase Delicias, S/n",
    "sg:city":"Madrid",
    "sg:orig_category":"Edici\u00d3n De Diarios, Revistas, Boletines",
    "sg:phone":"+34 914 74 54 12",
    "sg:postcode":"28045",
    "sg:province":"Madrid",
    "wof:name":"Garcia Garcia Vicente",
    "wof:placetype":"venue"
},
  "geometry": {"coordinates":[-3.6959691048,40.4042663574],"type":"Point"}
}