{
  "type": "Feature",
  "properties": {
    "addr:full":"Avda Andalucia, 23 Medina-sidonia C\u00e1diz 11170",
    "addr:housenumber":"23",
    "addr:postcode":"11170",
    "addr:street":"Avda Andalucia;Ca\u0301Diz",
    "iso:country":"ES",
    "sg:address":"Avda Andalucia, 23",
    "sg:city":"Medina-sidonia",
    "sg:orig_category":"Pr\u00c9stamos Personales E Hipotecarios",
    "sg:phone":"+34 956 41 00 36",
    "sg:postcode":"11170",
    "sg:province":"C\u00e1diz",
    "wof:name":"Registro De La Propiedad",
    "wof:placetype":"venue"
},
  "geometry": {"coordinates":[-5.9287109375,36.4624061584],"type":"Point"}
}