{
  "type": "Feature",
  "properties": {
    "iso:country":"ES",
    "sg:address":"Calle de Noria (la), 10",
    "sg:city":"Tomares",
    "sg:orig_category":"Ingeniero",
    "sg:phone":"+34 954 15 16 88",
    "sg:postcode":"41940",
    "sg:province":"Sevilla",
    "wof:name":"Ingenieria Y Calculo De Puentes S.l",
    "wof:placetype":"venue"
},
  "geometry": {"coordinates":[-6.0381441116,37.3758544922],"type":"Point"}
}