{
  "type": "Feature",
  "properties": {
    "iso:country":"ES",
    "sg:address":"Calle de Hilados, 24",
    "sg:city":"Torrejon Ardoz",
    "sg:orig_category":"Empresas De Portes Y Mensajer\u00cda",
    "sg:phone":"+34 916 60 09 58",
    "sg:postcode":"28850",
    "sg:province":"Madrid",
    "wof:name":"Peral Burgos Lucila",
    "wof:placetype":"venue"
},
  "geometry": {"coordinates":[-3.4602851868,40.4456787109],"type":"Point"}
}