{
  "type": "Feature",
  "properties": {
    "iso:country":"ES",
    "sg:address":"Calle de Trinidad Y Tobago, 18",
    "sg:city":"Tablero",
    "sg:orig_category":"Art\u00cdculos De Regalo (al Por Menor)",
    "sg:phone":"+34 928 14 53 69",
    "sg:postcode":"35100",
    "sg:province":"Las Palmas",
    "wof:name":"Martinez Miranda Tomasa Maria Angeles",
    "wof:placetype":"venue"
},
  "geometry": {"coordinates":[-15.6046075821,27.7724609375],"type":"Point"}
}