{
  "type": "Feature",
  "properties": {
    "addr:full":"Carrer de Alguersuari I Pascual, 29 Sabadell Barcelona 08203",
    "addr:housenumber":"29",
    "addr:postcode":"08203",
    "addr:street":"Carrer De Alguersuari I Pascual",
    "iso:country":"ES",
    "sg:address":"Carrer de Alguersuari I Pascual, 29",
    "sg:city":"Sabadell",
    "sg:orig_category":"Administradores De Bienes Y Delegados De Comunidades De Propietarios",
    "sg:phone":"+34 937 25 59 75",
    "sg:postcode":"08203",
    "sg:province":"Barcelona",
    "wof:name":"Perez Pozo S. L.",
    "wof:placetype":"venue"
},
  "geometry": {"coordinates":[2.1164588928,41.5409851074],"type":"Point"}
}