{
  "type": "Feature",
  "properties": {
    "addr:full":"Plaz Mayor, S/n Alcadozo Albacete 02124",
    "addr:housenumber":"s / n",
    "addr:postcode":"02124",
    "addr:street":"Plaz Mayor;Alcadozo",
    "iso:country":"ES",
    "sg:address":"Plaz Mayor, S/n",
    "sg:city":"Alcadozo",
    "sg:orig_category":"Supermercados Y Hipermercados",
    "sg:phone":"+34 967 29 13 88",
    "sg:postcode":"02124",
    "sg:province":"Albacete",
    "wof:name":"Garcia Lopez Augusto",
    "wof:placetype":"venue"
},
  "geometry": {"coordinates":[-1.9835549593,38.6488418579],"type":"Point"}
}