{
  "type": "Feature",
  "properties": {
    "iso:country":"ES",
    "sg:address":"Carr Font Martina, 14",
    "sg:city":"Colomina",
    "sg:orig_category":"Escayola Y Productos De Escayola (fabricaci\u00d3n, Al Por Mayor)",
    "sg:phone":"+34 972 30 08 95",
    "sg:postcode":"17213",
    "sg:province":"Girona",
    "wof:name":"Benito Garcia Cipriano",
    "wof:placetype":"venue"
},
  "geometry": {"coordinates":[3.2090060711,41.93775177],"type":"Point"}
}