{
  "type": "Feature",
  "properties": {
    "addr:full":"Avda Calvo Sotelo, 2 San Cristobal De La Laguna Santa Cruz De Tenerife 38205",
    "addr:housenumber":"2",
    "addr:postcode":"38205",
    "addr:street":"Avda Calvo Sotelo",
    "iso:country":"ES",
    "sg:address":"Avda Calvo Sotelo, 2",
    "sg:city":"San Cristobal De La Laguna",
    "sg:orig_category":"\u00d3pticos Optometristas (al Por Menor)",
    "sg:phone":"+34 922 26 13 66",
    "sg:postcode":"38205",
    "sg:province":"Santa Cruz De Tenerife",
    "wof:name":"Optica Y Ortopedia Kripton S. L.",
    "wof:placetype":"venue"
},
  "geometry": {"coordinates":[-16.3129653931,28.4808654785],"type":"Point"}
}