{
  "type": "Feature",
  "properties": {
    "addr:full":"Rio Mi\u00f1o, 27 Pqe. Boadilla Madrid 28669",
    "addr:housenumber":"27",
    "addr:postcode":"28669",
    "addr:street":"Rio Min\u0303O",
    "iso:country":"ES",
    "sg:address":"Rio Mi\u00f1o, 27",
    "sg:city":"Pqe. Boadilla",
    "sg:orig_category":"Artes Gr\u00c1ficas, Artes Pl\u00c1sticas (curso)",
    "sg:phone":"+34 916 32 09 62",
    "sg:postcode":"28669",
    "sg:province":"Madrid",
    "wof:name":"Breemar English Services S.l.",
    "wof:placetype":"venue"
},
  "geometry": {"coordinates":[-3.9107859135,40.4343452454],"type":"Point"}
}