{
  "type": "Feature",
  "properties": {
    "iso:country":"ES",
    "sg:address":"Calle de Casuarinas, S/n",
    "sg:city":"Poligono Industrial De Arinaga",
    "sg:orig_category":"Aluminio Y Aleaciones (producci\u00d3n, Transformaci\u00d3n, Negocio)",
    "sg:phone":"+34 928 18 49 74",
    "sg:postcode":"35118",
    "sg:province":"Las Palmas",
    "sg:website":"www.aluminiostorralba.com",
    "wof:name":"Aluminios Torralba S. A.",
    "wof:placetype":"venue"
},
  "geometry": {"coordinates":[-15.3927698135,27.8557987213],"type":"Point"}
}