{
  "type": "Feature",
  "properties": {
    "iso:country":"ES",
    "sg:address":"Avda Marina Espa\u00d1ola, 6",
    "sg:city":"Flota",
    "sg:orig_category":"Centros De Educaci\u00d3n Especial",
    "sg:phone":"+34 968 27 05 43",
    "sg:postcode":"30007",
    "sg:province":"Murcia",
    "wof:name":"Colegio Publico La Flota",
    "wof:placetype":"venue"
},
  "geometry": {"coordinates":[-1.1142389774,37.9970092773],"type":"Point"}
}