{
  "type": "Feature",
  "properties": {
    "iso:country":"ES",
    "sg:address":"Pol Ind Carboneras, S/n",
    "sg:city":"Carboneras",
    "sg:orig_category":"Mec\u00c1nico Del Autom\u00d3vil",
    "sg:phone":"+34 950 13 03 14",
    "sg:postcode":"04140",
    "sg:province":"Almer\u00eda",
    "wof:name":"Carbomotor S.l.l.",
    "wof:placetype":"venue"
},
  "geometry": {"coordinates":[-1.8956240416,36.9959602356],"type":"Point"}
}