{
  "type": "Feature",
  "properties": {
    "iso:country":"ES",
    "sg:address":"Calle de Acacias, 26",
    "sg:city":"Ciudad Real",
    "sg:orig_category":"Molduras, Junquillos, Listones Y Molduras Perforadas",
    "sg:phone":"+34 926 21 31 25",
    "sg:postcode":"13002",
    "sg:province":"Ciudad Real",
    "wof:name":"Franco Monteagudo Jesus",
    "wof:placetype":"venue"
},
  "geometry": {"coordinates":[-3.9387001991,38.9790878296],"type":"Point"}
}