{
  "type": "Feature",
  "properties": {
    "addr:full":"Calle de Diego De Vargas, 4 Madrid Madrid 28022",
    "addr:housenumber":"4",
    "addr:postcode":"28022",
    "addr:street":"Calle De Diego De Vargas",
    "iso:country":"ES",
    "sg:address":"Calle de Diego De Vargas, 4",
    "sg:city":"Madrid",
    "sg:orig_category":"Vidrieras De Seguridad, De Protecci\u00d3n Solar, Suministros (fabricaci\u00d3n, Instalaci\u00d3n)",
    "sg:phone":"+34 913 20 35 12",
    "sg:postcode":"28022",
    "sg:province":"Madrid",
    "wof:name":"Factor Solar S.l.",
    "wof:placetype":"venue"
},
  "geometry": {"coordinates":[-3.6134068966,40.4492492676],"type":"Point"}
}