{
  "type": "Feature",
  "properties": {
    "iso:country":"ES",
    "sg:address":"Calle de Resurreccion M.azkue, 8",
    "sg:city":"Donostia-san Sebastian",
    "sg:orig_category":"Peluquer\u00cdas",
    "sg:phone":"+34 943 31 43 49",
    "sg:postcode":"20018",
    "sg:province":"Guip\u00f9zcoa",
    "wof:name":"Alberto Martinez Duran Y Otro C.b.",
    "wof:placetype":"venue"
},
  "geometry": {"coordinates":[-2.0085778236,43.3105163574],"type":"Point"}
}