{
  "type": "Feature",
  "properties": {
    "addr:full":"Avda Carlos Iii, 621 Aguadulce Almer\u00eda 04720",
    "addr:housenumber":"621",
    "addr:postcode":"04720",
    "addr:street":"Avda Carlos Iii;Almeri\u0301A",
    "iso:country":"ES",
    "sg:address":"Avda Carlos Iii, 621",
    "sg:city":"Aguadulce",
    "sg:orig_category":"Inmobiliaria (agencias)",
    "sg:phone":"+34 950 34 99 69",
    "sg:postcode":"04720",
    "sg:province":"Almer\u00eda",
    "wof:name":"Moreno Sanchez Dolores",
    "wof:placetype":"venue"
},
  "geometry": {"coordinates":[-2.5684089661,36.8155517578],"type":"Point"}
}