{
  "type": "Feature",
  "properties": {
    "addr:full":"Calle de Reyes Catolicos, 32 Vitoria-gasteiz \u00c1lava 01002",
    "addr:housenumber":"32",
    "addr:postcode":"01002",
    "addr:street":"Calle De Reyes Catolicos",
    "iso:country":"ES",
    "sg:address":"Calle de Reyes Catolicos, 32",
    "sg:city":"Vitoria-gasteiz",
    "sg:orig_category":"Quincaller\u00cda (al Por Menor)",
    "sg:phone":"+34 945 27 41 48",
    "sg:postcode":"01002",
    "sg:province":"\u00c1lava",
    "wof:name":"Jose Ramon Bengoa Dias De Heredia",
    "wof:placetype":"venue"
},
  "geometry": {"coordinates":[-2.6661779881,42.8539962769],"type":"Point"}
}