{
  "type": "Feature",
  "properties": {
    "iso:country":"ES",
    "sg:address":"C/ Ciutat De Sagunt, 4",
    "sg:city":"Paterna",
    "sg:orig_category":"Mec\u00c1nico Del Autom\u00d3vil",
    "sg:phone":"+34 961 34 10 26",
    "sg:postcode":"46988",
    "sg:province":"Valencia",
    "wof:name":"Autocentro Poligono S.l.",
    "wof:placetype":"venue"
},
  "geometry": {"coordinates":[-0.4572690129,39.5139045715],"type":"Point"}
}