{
  "type": "Feature",
  "properties": {
    "iso:country":"ES",
    "sg:address":"Calle de Serrano Galvache, 1",
    "sg:city":"Madrid",
    "sg:orig_category":"Arquitectos",
    "sg:phone":"+34 917 66 57 39",
    "sg:postcode":"28033",
    "sg:province":"Madrid",
    "wof:name":"Alonso Vera Juan Antonio",
    "wof:placetype":"venue"
},
  "geometry": {"coordinates":[-3.6676886082,40.4714660645],"type":"Point"}
}