{
  "type": "Feature",
  "properties": {
    "iso:country":"ES",
    "sg:address":"Calle de Cristo De La Epidemia, 54",
    "sg:city":"Malaga",
    "sg:orig_category":"Cl\u00cdnicas Dentales",
    "sg:phone":"+34 952 26 51 46",
    "sg:postcode":"29013",
    "sg:province":"M\u00e1laga",
    "wof:name":"Somodevilla Ariza Antonio",
    "wof:placetype":"venue"
},
  "geometry": {"coordinates":[-4.4147729874,36.7299461365],"type":"Point"}
}