{
  "type": "Feature",
  "properties": {
    "addr:full":"Pl Milagros Consarnau I Saba, 43 Hospitalet Llobregat Barcelona 08902",
    "addr:housenumber":"43",
    "addr:postcode":"08902",
    "addr:street":"Pl",
    "iso:country":"ES",
    "sg:address":"Pl Milagros Consarnau I Saba, 43",
    "sg:city":"Hospitalet Llobregat",
    "sg:orig_category":"Molduras, Junquillos, Listones Y Molduras Perforadas",
    "sg:phone":"+34 934 21 01 85",
    "sg:postcode":"08902",
    "sg:province":"Barcelona",
    "wof:name":"Sinde Fernandez Juan Carlos",
    "wof:placetype":"venue"
},
  "geometry": {"coordinates":[2.1293849945,41.3654098511],"type":"Point"}
}