{
  "type": "Feature",
  "properties": {
    "addr:full":"Bard Virgen De La Cabeza, S/n Andujar Ja\u00e9n 23740",
    "addr:housenumber":"s / n",
    "addr:postcode":"23740",
    "addr:street":"Virgen;Cabeza",
    "iso:country":"ES",
    "sg:address":"Bard Virgen De La Cabeza, S/n",
    "sg:city":"Andujar",
    "sg:orig_category":"Plomeros",
    "sg:phone":"+34 953 50 33 01",
    "sg:postcode":"23740",
    "sg:province":"Ja\u00e9n",
    "wof:name":"Pe\u00f1a Molina Francisco",
    "wof:placetype":"venue"
},
  "geometry": {"coordinates":[-4.0570287704,38.0423431396],"type":"Point"}
}