{
  "type": "Feature",
  "properties": {
    "addr:full":"Cmno Aurin (de), S/n Sabi\u00f1anigo Huesca 22600",
    "addr:postcode":"22600",
    "addr:street":"Cmno Aurin De S / N Sabin\u0303Anigo",
    "iso:country":"ES",
    "sg:address":"Cmno Aurin (de), S/n",
    "sg:city":"Sabi\u00f1anigo",
    "sg:orig_category":"Montaje (empresas De)",
    "sg:phone":"+34 974 48 44 41",
    "sg:postcode":"22600",
    "sg:province":"Huesca",
    "wof:name":"Montajes Industriales Del Alto Gallego S.l.l",
    "wof:placetype":"venue"
},
  "geometry": {"coordinates":[-0.3508209884,42.5240402222],"type":"Point"}
}