{
  "type": "Feature",
  "properties": {
    "iso:country":"ES",
    "sg:address":"Calle de Santa Lucia, 4",
    "sg:city":"Caspe",
    "sg:orig_category":"Ense\u00d1anza: Profesiones Art\u00cdsticas",
    "sg:phone":"+34 976 63 15 64",
    "sg:postcode":"50700",
    "sg:province":"Zaragoza",
    "wof:name":"Caspe Foto S.l.",
    "wof:placetype":"venue"
},
  "geometry": {"coordinates":[-0.0411820002,41.2367553711],"type":"Point"}
}