{
  "type": "Feature",
  "properties": {
    "iso:country":"ES",
    "sg:address":"Carr Germanes Sastre Font, S/n",
    "sg:city":"Selva",
    "sg:orig_category":"Barquillos De Miel (fabricaci\u00d3n)",
    "sg:phone":"+34 971 87 53 93",
    "sg:postcode":"07313",
    "sg:province":"Islas Baleares",
    "wof:name":"Alhama Lopez Juan Jaime",
    "wof:placetype":"venue"
},
  "geometry": {"coordinates":[2.9015963078,39.7570877075],"type":"Point"}
}