{
  "type": "Feature",
  "properties": {
    "addr:full":"Urb. Josa Eras, 1 Moraleja Vino Zamora 49150",
    "addr:housenumber":"1",
    "addr:postcode":"49150",
    "addr:street":"Eras;Zamora",
    "iso:country":"ES",
    "sg:address":"Urb. Josa Eras, 1",
    "sg:city":"Moraleja Vino",
    "sg:orig_category":"Farmacias",
    "sg:phone":"+34 980 57 10 04",
    "sg:postcode":"49150",
    "sg:province":"Zamora",
    "wof:name":"Rubio Gonzalez Aurora",
    "wof:placetype":"venue"
},
  "geometry": {"coordinates":[-5.6560359001,41.4629325867],"type":"Point"}
}