{
  "type": "Feature",
  "properties": {
    "iso:country":"ES",
    "sg:address":"Rua Carpinteiros (dos), 11",
    "sg:city":"Lugo",
    "sg:orig_category":"Promotores Constructores",
    "sg:phone":"+34 982 20 70 68",
    "sg:postcode":"27003",
    "sg:province":"Lugo",
    "wof:name":"Asogal Construcciones S.l.",
    "wof:placetype":"venue"
},
  "geometry": {"coordinates":[-7.5652823448,43.0442237854],"type":"Point"}
}