{
  "type": "Feature",
  "properties": {
    "iso:country":"ES",
    "sg:address":"Calle de Reyes Catolicos, 20",
    "sg:city":"Palmas De Gran Canaria",
    "sg:orig_category":"Abogados",
    "sg:phone":"+34 928 32 20 43",
    "sg:postcode":"35001",
    "sg:province":"Las Palmas",
    "wof:name":"Suarez Rodriguez Maria Dolores",
    "wof:placetype":"venue"
},
  "geometry": {"coordinates":[-15.4139051437,28.099445343],"type":"Point"}
}