{
  "type": "Feature",
  "properties": {
    "iso:country":"ES",
    "sg:address":"Calle de Mu\u00d1oz Leon, 15",
    "sg:city":"Sevilla",
    "sg:orig_category":"M\u00c9dicos: An\u00c1lisis Cl\u00cdnicos",
    "sg:phone":"+34 954 37 41 98",
    "sg:postcode":"41009",
    "sg:province":"Sevilla",
    "wof:name":"Montes Zamora Concepcion De",
    "wof:placetype":"venue"
},
  "geometry": {"coordinates":[-5.9855899811,37.4017982483],"type":"Point"}
}