{
  "type": "Feature",
  "properties": {
    "addr:full":"Calle de Jesus Guridi, 6 Vitoria-gasteiz \u00c1lava 01004",
    "addr:housenumber":"6",
    "addr:postcode":"01004",
    "addr:street":"Calle De Jesus Guridi",
    "iso:country":"ES",
    "sg:address":"Calle de Jesus Guridi, 6",
    "sg:city":"Vitoria-gasteiz",
    "sg:orig_category":"Fabricaci\u00d3n De Su\u00c9ters Y Chalecos De Punto",
    "sg:phone":"+34 945 27 06 50",
    "sg:postcode":"01004",
    "sg:province":"\u00c1lava",
    "wof:name":"Barrios Hidalgo Maria Del Mar",
    "wof:placetype":"venue"
},
  "geometry": {"coordinates":[-2.6663589478,42.8437156677],"type":"Point"}
}