{
  "type": "Feature",
  "properties": {
    "iso:country":"ES",
    "sg:address":"Calle de Damas, 13",
    "sg:city":"Pe\u00f1afiel",
    "sg:orig_category":"Peluquer\u00cdas, Peluquer\u00cda Mixta",
    "sg:phone":"+34 983 88 01 22",
    "sg:postcode":"47300",
    "sg:province":"Valladolid",
    "wof:name":"Martin Diez Esperanza",
    "wof:placetype":"venue"
},
  "geometry": {"coordinates":[-4.1193432808,41.5974273682],"type":"Point"}
}