{
  "type": "Feature",
  "properties": {
    "addr:full":"Ctra. Graus, 10 Barbastro Huesca 22300",
    "addr:housenumber":"10",
    "addr:postcode":"22300",
    "addr:street":"Ctra. Graus",
    "iso:country":"ES",
    "sg:address":"Ctra. Graus, 10",
    "sg:city":"Barbastro",
    "sg:orig_category":"Edici\u00d3n De Diarios, Revistas, Boletines",
    "sg:phone":"+34 974 31 06 33",
    "sg:postcode":"22300",
    "sg:province":"Huesca",
    "wof:name":"Obispado De Barbastro",
    "wof:placetype":"venue"
},
  "geometry": {"coordinates":[0.1278450042,42.0377731323],"type":"Point"}
}