{
  "type": "Feature",
  "properties": {
    "iso:country":"ES",
    "sg:address":"Calle de Pico De Los Artilleros, 60",
    "sg:city":"Madrid",
    "sg:orig_category":"Sociedades, Compa\u00d1\u00cdas Aseguradoras",
    "sg:phone":"+34 917 72 02 49",
    "sg:postcode":"28030",
    "sg:province":"Madrid",
    "wof:name":"Cleda S.l.",
    "wof:placetype":"venue"
},
  "geometry": {"coordinates":[-3.6409640312,40.4074707031],"type":"Point"}
}