{
  "type": "Feature",
  "properties": {
    "iso:country":"ES",
    "sg:address":"Calle de Catedratico Ferre Vidiella, 9",
    "sg:city":"Alacant",
    "sg:orig_category":"Alimentaci\u00d3n General (al Por Menor)",
    "sg:phone":"+34 965 92 55 73",
    "sg:postcode":"03005",
    "sg:province":"Alicante",
    "wof:name":"Irigoyen  Benjamin Cesar",
    "wof:placetype":"venue"
},
  "geometry": {"coordinates":[-0.4933654964,38.3461723328],"type":"Point"}
}