{
  "type": "Feature",
  "properties": {
    "iso:country":"ES",
    "sg:address":"Carr Pare Pacific, 2",
    "sg:city":"Vilanova Bellpuig",
    "sg:orig_category":"Asilos De Ancianos. Centros Privados",
    "sg:phone":"+34 973 32 43 92",
    "sg:postcode":"25264",
    "sg:province":"Lleida",
    "wof:name":"Llar Municipal De Gent Grant",
    "wof:placetype":"venue"
},
  "geometry": {"coordinates":[0.9624040127,41.6136856079],"type":"Point"}
}