{
  "type": "Feature",
  "properties": {
    "iso:country":"ES",
    "sg:address":"Calle de Gonzalez Del Valle, 9",
    "sg:city":"Oviedo",
    "sg:orig_category":"Administradores De Bienes Y Delegados De Comunidades De Propietarios",
    "sg:phone":"+34 985 27 76 18",
    "sg:postcode":"33003",
    "sg:province":"Asturias",
    "wof:name":"Perez Garcia Eva",
    "wof:placetype":"venue"
},
  "geometry": {"coordinates":[-5.8522090912,43.3631401062],"type":"Point"}
}