{
  "type": "Feature",
  "properties": {
    "iso:country":"ES",
    "sg:address":"Calle de Juan Carlos I, 18",
    "sg:city":"Sanlucar Mayor",
    "sg:orig_category":"Confecci\u00d3n (fabricaci\u00d3n, Al Por Mayor)",
    "sg:phone":"+34 955 70 20 18",
    "sg:postcode":"41800",
    "sg:province":"Sevilla",
    "wof:name":"Galerias Vargas S.l.",
    "wof:placetype":"venue"
},
  "geometry": {"coordinates":[-6.2030568123,37.3863372803],"type":"Point"}
}