{
  "type": "Feature",
  "properties": {
    "iso:country":"ES",
    "sg:address":"Calle de Arzua, 6",
    "sg:city":"Madrid",
    "sg:orig_category":"Plomeros",
    "sg:phone":"+34 917 63 73 90",
    "sg:postcode":"28033",
    "sg:province":"Madrid",
    "wof:name":"Zapardiel Hernandez Amalio",
    "wof:placetype":"venue"
},
  "geometry": {"coordinates":[-3.6458330154,40.4742431641],"type":"Point"}
}