{
  "type": "Feature",
  "properties": {
    "iso:country":"ES",
    "sg:address":"Calle de Regocijos, 73",
    "sg:city":"Almeria",
    "sg:orig_category":"Estancos",
    "sg:phone":"+34 950 23 59 92",
    "sg:postcode":"04003",
    "sg:province":"Almer\u00eda",
    "wof:name":"Garcia Gomez Pablo Jesus",
    "wof:placetype":"venue"
},
  "geometry": {"coordinates":[-2.4656701088,36.8440437317],"type":"Point"}
}