{
  "type": "Feature",
  "properties": {
    "iso:country":"ES",
    "sg:address":"Ctra Pandorado, 19",
    "sg:city":"Astorga",
    "sg:classifiers":[
        {
            "category":"Autos & Motor Vehicles",
            "subcategory":"Automobile Sales",
            "type":"Retail Goods"
        }
    ],
    "sg:phone":"+34 987 61 51 42",
    "sg:postcode":"24700",
    "sg:province":"Le\u00f3n",
    "wof:name":"Ferreras Carro Santiago",
    "wof:placetype":"venue"
},
  "geometry": {"coordinates":[-6.0533699989,42.4585037231],"type":"Point"}
}