{
  "type": "Feature",
  "properties": {
    "addr:full":"Plaz Virgencilla, 10 Aranda Duero Burgos 09400",
    "addr:housenumber":"10",
    "addr:postcode":"09400",
    "addr:street":"Plaz Virgencilla",
    "iso:country":"ES",
    "sg:address":"Plaz Virgencilla, 10",
    "sg:city":"Aranda Duero",
    "sg:orig_category":"Pescader\u00cdas (al Por Menor)",
    "sg:phone":"+34 947 51 04 24",
    "sg:postcode":"09400",
    "sg:province":"Burgos",
    "wof:name":"Frescos Vivos Y Cocidos S.l.",
    "wof:placetype":"venue"
},
  "geometry": {"coordinates":[-3.6889948845,41.6699256897],"type":"Point"}
}