{
  "type": "Feature",
  "properties": {
    "addr:full":"Karobieta Auzoa, 63 Hernani Guip\u00f9zcoa 20120",
    "addr:housenumber":"63",
    "addr:postcode":"20120",
    "addr:street":"Karobieta Auzoa;Guipu\u0300Zcoa",
    "iso:country":"ES",
    "sg:address":"Karobieta Auzoa, 63",
    "sg:city":"Hernani",
    "sg:orig_category":"Asociaciones Humanitarias, De Cooperaci\u00d3n, De Acci\u00d3n Social",
    "sg:phone":"+34 943 33 55 33",
    "sg:postcode":"20120",
    "sg:province":"Guip\u00f9zcoa",
    "wof:name":"Asociacion Ayuda En Carretera De Guipuzcoa",
    "wof:placetype":"venue"
},
  "geometry": {"coordinates":[-1.9793721437,43.2679481506],"type":"Point"}
}