{
  "type": "Feature",
  "properties": {
    "addr:full":"Pase Julia (la), 3 Palencia Palencia 34002",
    "addr:postcode":"34002",
    "iso:country":"ES",
    "sg:address":"Pase Julia (la), 3",
    "sg:city":"Palencia",
    "sg:orig_category":"Prot\u00c9sicos Dentales",
    "sg:phone":"+34 979 71 15 45",
    "sg:postcode":"34002",
    "sg:province":"Palencia",
    "wof:name":"Rodrigo Alario Ignacio Alberto",
    "wof:placetype":"venue"
},
  "geometry": {"coordinates":[-4.5288228989,42.00258255],"type":"Point"}
}