{
  "type": "Feature",
  "properties": {
    "addr:full":"Calle de Lagasca, 131 Madrid Madrid 28006",
    "addr:housenumber":"131",
    "addr:postcode":"28006",
    "addr:street":"Calle De Lagasca",
    "iso:country":"ES",
    "sg:address":"Calle de Lagasca, 131",
    "sg:city":"Madrid",
    "sg:orig_category":"Loter\u00cda Y T\u00d3mbola",
    "sg:phone":"+34 915 64 27 54",
    "sg:postcode":"28006",
    "sg:province":"Madrid",
    "wof:name":"Gomez Peso Maria Sonsoles",
    "wof:placetype":"venue"
},
  "geometry": {"coordinates":[-3.6843810081,40.4372558594],"type":"Point"}
}