{
  "type": "Feature",
  "properties": {
    "iso:country":"ES",
    "sg:address":"Carrer de Ignasi Iglesias, 29",
    "sg:city":"Vilafranca Penedes",
    "sg:orig_category":"Empresarios",
    "sg:phone":"+34 938 19 94 45",
    "sg:postcode":"08720",
    "sg:province":"Barcelona",
    "wof:name":"Asistencia Al Hogar A24h S.l.",
    "wof:placetype":"venue"
},
  "geometry": {"coordinates":[1.6975498199,41.3396835327],"type":"Point"}
}