{
  "type": "Feature",
  "properties": {
    "addr:full":"Sector Area 17, 20 Le\u00f3n Le\u00f3n 24008",
    "addr:housenumber":"20",
    "addr:postcode":"24008",
    "addr:street":"Leo\u0301N Leo\u0301N",
    "iso:country":"ES",
    "sg:address":"Sector Area 17, 20",
    "sg:city":"Le\u00f3n",
    "sg:orig_category":"Cajas De Ahorro",
    "sg:phone":"+34 987 22 87 74",
    "sg:postcode":"24008",
    "sg:province":"Le\u00f3n",
    "wof:name":"Caja De Ahorros Y Monte De Piedad De Zaragoza Aragon Y Rioja",
    "wof:placetype":"venue"
},
  "geometry": {"coordinates":[-5.5550928116,42.6448745728],"type":"Point"}
}