{
  "type": "Feature",
  "properties": {
    "iso:country":"ES",
    "sg:address":"Plaza Pr\u00edncipe De Espa\u00f1a, S/n",
    "sg:city":"Coin",
    "sg:orig_category":"Inmobiliaria (agencias)",
    "sg:phone":"+34 952 45 39 00",
    "sg:postcode":"29100",
    "sg:province":"M\u00e1laga",
    "wof:name":"Ortega Marmol Magdalena",
    "wof:placetype":"venue"
},
  "geometry": {"coordinates":[-4.7547988892,36.6622505188],"type":"Point"}
}