{
  "type": "Feature",
  "properties": {
    "addr:full":"Rua Reza, 3 Ourense Ourense 32003",
    "addr:housenumber":"3",
    "addr:postcode":"32003",
    "addr:street":"Rua Reza",
    "iso:country":"ES",
    "sg:address":"Rua Reza, 3",
    "sg:city":"Ourense",
    "sg:orig_category":"Ense\u00d1anza Variada",
    "sg:phone":"+34 988 36 60 63",
    "sg:postcode":"32003",
    "sg:province":"Ourense",
    "sg:website":"www.academiapostal.es",
    "wof:name":"Academia Postal Uno S.l.",
    "wof:placetype":"venue"
},
  "geometry": {"coordinates":[-7.8660669327,42.3373603821],"type":"Point"}
}