{
  "type": "Feature",
  "properties": {
    "iso:country":"ES",
    "sg:address":"Calle de San Andres, 8",
    "sg:city":"Don Benito",
    "sg:classifiers":[
        {
            "category":"Autos & Motor Vehicles",
            "subcategory":"Automobile Sales",
            "type":"Retail Goods"
        }
    ],
    "sg:phone":"+34 924 80 80 88",
    "sg:postcode":"06400",
    "sg:province":"Badajoz",
    "wof:name":"Autoescuela Don Benito S.l.",
    "wof:placetype":"venue"
},
  "geometry": {"coordinates":[-5.8630256653,38.9538993835],"type":"Point"}
}