{
  "type": "Feature",
  "properties": {
    "addr:full":"N Uno(pe\u00f1isc Azahar), 111 Pe\u00f1iscola Castell\u00f3n 12598",
    "addr:housenumber":"111",
    "addr:postcode":"12598",
    "addr:street":"Azahar;Castello\u0301N",
    "iso:country":"ES",
    "sg:address":"N Uno(pe\u00f1isc Azahar), 111",
    "sg:city":"Pe\u00f1iscola",
    "sg:orig_category":"Supermercados Y Hipermercados",
    "sg:phone":"+34 964 48 99 78",
    "sg:postcode":"12598",
    "sg:province":"Castell\u00f3n",
    "wof:name":"Cotorvis S.l.",
    "wof:placetype":"venue"
},
  "geometry": {"coordinates":[-0.0456800014,39.9851417542],"type":"Point"}
}