{
  "type": "Feature",
  "properties": {
    "addr:full":"Calle de Alhondiga, 3 Sevilla Sevilla 41003",
    "addr:housenumber":"3",
    "addr:postcode":"41003",
    "addr:street":"Calle De Alhondiga",
    "iso:country":"ES",
    "sg:address":"Calle de Alhondiga, 3",
    "sg:city":"Sevilla",
    "sg:orig_category":"Ropa Para Ni\u00d1os (al Por Menor)",
    "sg:phone":"+34 954 56 38 15",
    "sg:postcode":"41003",
    "sg:province":"Sevilla",
    "wof:name":"Martinez Martin Manuela",
    "wof:placetype":"venue"
},
  "geometry": {"coordinates":[-5.9883093834,37.3932495117],"type":"Point"}
}