{
  "type": "Feature",
  "properties": {
    "iso:country":"ES",
    "sg:address":"Benalmadena, 7",
    "sg:city":"Las Palmas",
    "sg:orig_category":"Ense\u00d1anza, Formaci\u00d3n Profesional: Aprendizaje",
    "sg:phone":"+34 928 33 32 99",
    "sg:postcode":"35016",
    "sg:province":"Las Palmas",
    "wof:name":"Gobierno De Canarias",
    "wof:placetype":"venue"
},
  "geometry": {"coordinates":[-15.4343700409,28.0745296478],"type":"Point"}
}