{
  "type": "Feature",
  "properties": {
    "addr:full":"Plaz Doctor Gomez Ulla, S/n Alacant Alicante 03013",
    "addr:housenumber":"s / n",
    "addr:postcode":"03013",
    "addr:street":"Gomez",
    "iso:country":"ES",
    "sg:address":"Plaz Doctor Gomez Ulla, S/n",
    "sg:city":"Alacant",
    "sg:orig_category":"Instalaci\u00d3n De Sanitarios",
    "sg:phone":"+34 965 14 40 00",
    "sg:postcode":"03013",
    "sg:province":"Alicante",
    "wof:name":"Generalitat Valenciana",
    "wof:placetype":"venue"
},
  "geometry": {"coordinates":[-0.4765239954,38.3529891968],"type":"Point"}
}