{
  "type": "Feature",
  "properties": {
    "addr:full":"Pol Ind Dos De Octubre, S/n Santa Fe Granada 18320",
    "addr:housenumber":"s / n",
    "addr:postcode":"18320",
    "addr:street":"Octubre",
    "iso:country":"ES",
    "sg:address":"Pol Ind Dos De Octubre, S/n",
    "sg:city":"Santa Fe",
    "sg:orig_category":"Moda",
    "sg:phone":"+34 958 51 32 83",
    "sg:postcode":"18320",
    "sg:province":"Granada",
    "wof:name":"Marcano Dise\u00d1os S.l.",
    "wof:placetype":"venue"
},
  "geometry": {"coordinates":[-3.714564085,37.1907157898],"type":"Point"}
}