{
  "type": "Feature",
  "properties": {
    "iso:country":"ES",
    "sg:address":"Avda Habaneras (de Las), 89",
    "sg:city":"Torrevieja",
    "sg:orig_category":"Cervecer\u00cdas",
    "sg:phone":"+34 966 70 04 91",
    "sg:postcode":"03180",
    "sg:province":"Alicante",
    "wof:name":"Chen  Yuequn",
    "wof:placetype":"venue"
},
  "geometry": {"coordinates":[-0.6536790133,38.0173606873],"type":"Point"}
}