{
  "type": "Feature",
  "properties": {
    "iso:country":"ES",
    "sg:address":"Carr San Jose, 38",
    "sg:city":"Silla",
    "sg:orig_category":"Transportes Por Carretera: Lotes Completos, Mercanc\u00cdas Diversas",
    "sg:phone":"+34 961 20 22 00",
    "sg:postcode":"46460",
    "sg:province":"Valencia",
    "wof:name":"Hernandez Exposito Francisco",
    "wof:placetype":"venue"
},
  "geometry": {"coordinates":[-0.410454005,39.3621902466],"type":"Point"}
}