{
  "type": "Feature",
  "properties": {
    "addr:full":"Calle de Real, 14 Cajar Granada 18198",
    "addr:housenumber":"14",
    "addr:postcode":"18198",
    "addr:street":"Calle De Real",
    "iso:country":"ES",
    "sg:address":"Calle de Real, 14",
    "sg:city":"Cajar",
    "sg:orig_category":"Internados & Ense\u00d1anza Privada",
    "sg:phone":"+34 958 50 15 17",
    "sg:postcode":"18198",
    "sg:province":"Granada",
    "wof:name":"Religiosas Hijas Del Patrocinio De Maria",
    "wof:placetype":"venue"
},
  "geometry": {"coordinates":[-3.5720300674,37.1343307495],"type":"Point"}
}