{
  "type": "Feature",
  "properties": {
    "iso:country":"ES",
    "sg:address":"Carrer de Metge Juan Bellot, 5",
    "sg:city":"Monovar",
    "sg:orig_category":"Reposter\u00cdas",
    "sg:phone":"+34 966 96 01 45",
    "sg:postcode":"03640",
    "sg:province":"Alicante",
    "wof:name":"Requena Olivares Rosario",
    "wof:placetype":"venue"
},
  "geometry": {"coordinates":[-0.8423069715,38.4370956421],"type":"Point"}
}