{
  "type": "Feature",
  "properties": {
    "addr:full":"Carrer de Tarragona, 58 Vilassar Dalt Barcelona 08339",
    "addr:housenumber":"58",
    "addr:postcode":"08339",
    "addr:street":"Carrer De Tarragona;Dalt Barcelona",
    "iso:country":"ES",
    "sg:address":"Carrer de Tarragona, 58",
    "sg:city":"Vilassar Dalt",
    "sg:orig_category":"Inmobiliaria (agencias)",
    "sg:phone":"+34 937 50 77 38",
    "sg:postcode":"08339",
    "sg:province":"Barcelona",
    "wof:name":"G.t.i.ibercasa",
    "wof:placetype":"venue"
},
  "geometry": {"coordinates":[2.3675119877,41.5181770325],"type":"Point"}
}