{
  "type": "Feature",
  "properties": {
    "iso:country":"ES",
    "sg:address":"Calle de Comandante Fortea, 10",
    "sg:city":"Teruel",
    "sg:orig_category":"Cervecer\u00cdas",
    "sg:phone":"+34 978 60 95 96",
    "sg:postcode":"44001",
    "sg:province":"Teruel",
    "wof:name":"Franlis S.l.",
    "wof:placetype":"venue"
},
  "geometry": {"coordinates":[-1.1066380739,40.3420257568],"type":"Point"}
}