{
  "type": "Feature",
  "properties": {
    "iso:country":"ES",
    "sg:address":"Calle de Marmol, 7",
    "sg:city":"Torrejon Ardoz",
    "sg:orig_category":"Molduras, Junquillos, Listones Y Molduras Perforadas",
    "sg:phone":"+34 916 75 02 60",
    "sg:postcode":"28850",
    "sg:province":"Madrid",
    "wof:name":"Barroso Hidalgo Juan",
    "wof:placetype":"venue"
},
  "geometry": {"coordinates":[-3.4683990479,40.4499778748],"type":"Point"}
}