{
  "type": "Feature",
  "properties": {
    "iso:country":"ES",
    "sg:address":"Calle de Gremio De Los Caldereros (del), S/n",
    "sg:city":"Hontoria",
    "sg:orig_category":"Cajas Registradoras, Terminales De Puntos De Venta",
    "sg:phone":"+34 921 43 20 13",
    "sg:postcode":"40195",
    "sg:province":"Segovia",
    "wof:name":"Alberto Ganzalez Maseda S.l.",
    "wof:placetype":"venue"
},
  "geometry": {"coordinates":[-4.108215332,40.9125480652],"type":"Point"}
}