{
  "type": "Feature",
  "properties": {
    "addr:full":"Carrer de Guardia Civil, De Sa, 14 Santanyi Islas Baleares 07650",
    "addr:housenumber":"14",
    "addr:postcode":"07650",
    "addr:street":"Carrer De Guardia;Santanyi Islas",
    "iso:country":"ES",
    "sg:address":"Carrer de Guardia Civil, De Sa, 14",
    "sg:city":"Santanyi",
    "sg:orig_category":"Producci\u00d3n, Distribuci\u00d3n De Electricidad",
    "sg:phone":"+34 971 65 36 47",
    "sg:postcode":"07650",
    "sg:province":"Islas Baleares",
    "wof:name":"Coll Vallespir Juana",
    "wof:placetype":"venue"
},
  "geometry": {"coordinates":[3.1275970936,39.3539619446],"type":"Point"}
}