{
  "type": "Feature",
  "properties": {
    "addr:full":"Calle de Reyes De Navarra, 20 Vitoria-gasteiz \u00c1lava 01013",
    "addr:housenumber":"20",
    "addr:postcode":"01013",
    "addr:street":"Calle De Reyes De Navarra",
    "iso:country":"ES",
    "sg:address":"Calle de Reyes De Navarra, 20",
    "sg:city":"Vitoria-gasteiz",
    "sg:orig_category":"Congelados: Productos Alimentarios (al Por Menor)",
    "sg:phone":"+34 945 27 45 31",
    "sg:postcode":"01013",
    "sg:province":"\u00c1lava",
    "wof:name":"Altamar Congelados S.a.",
    "wof:placetype":"venue"
},
  "geometry": {"coordinates":[-2.6671161652,42.8557357788],"type":"Point"}
}