{
  "type": "Feature",
  "properties": {
    "iso:country":"ES",
    "sg:address":"Calle de San Isidro, 1",
    "sg:city":"Palencia",
    "sg:orig_category":"Promotores Constructores",
    "sg:phone":"+34 979 72 89 41",
    "sg:postcode":"34002",
    "sg:province":"Palencia",
    "wof:name":"Pevimi S.a.",
    "wof:placetype":"venue"
},
  "geometry": {"coordinates":[-4.5294098854,42.0021820068],"type":"Point"}
}