{
  "type": "Feature",
  "properties": {
    "addr:full":"Calle de General Casta\u00d1os, 42 Portugalete Vizcaya 48920",
    "addr:housenumber":"42",
    "addr:postcode":"48920",
    "addr:street":"Calle De General Castan\u0303Os",
    "iso:country":"ES",
    "sg:address":"Calle de General Casta\u00d1os, 42",
    "sg:city":"Portugalete",
    "sg:orig_category":"Inmobiliaria (agencias)",
    "sg:phone":"+34 944 61 11 02",
    "sg:postcode":"48920",
    "sg:province":"Vizcaya",
    "wof:name":"Noble Villa Gestion Inmobiliaria",
    "wof:placetype":"venue"
},
  "geometry": {"coordinates":[-3.0226290226,43.3217964172],"type":"Point"}
}