{
  "type": "Feature",
  "properties": {
    "iso:country":"ES",
    "sg:address":"Calle de Virgen De Guadalupe, 22",
    "sg:city":"Badajoz",
    "sg:orig_category":"Discapacitados",
    "sg:phone":"+34 924 24 07 94",
    "sg:postcode":"06003",
    "sg:province":"Badajoz",
    "wof:name":"Amifp",
    "wof:placetype":"venue"
},
  "geometry": {"coordinates":[-6.9188785553,38.2745857239],"type":"Point"}
}