{
  "type": "Feature",
  "properties": {
    "iso:country":"ES",
    "sg:address":"El Chaparral, 90",
    "sg:city":"Costa Del Silencio",
    "sg:orig_category":"Bazares, Art\u00cdculos De Limpieza Y De Cocina (al Por Menor)",
    "sg:phone":"+34 922 73 15 19",
    "sg:postcode":"38630",
    "sg:province":"Santa Cruz De Tenerife",
    "wof:name":"Singh Banga Tejinder",
    "wof:placetype":"venue"
},
  "geometry": {"coordinates":[-16.6446456909,28.0110435486],"type":"Point"}
}