{
  "type": "Feature",
  "properties": {
    "addr:full":"Plaz Lannion (de), 4 Viveiro Lugo 27850",
    "addr:postcode":"27850",
    "addr:street":"Plaz;De",
    "iso:country":"ES",
    "sg:address":"Plaz Lannion (de), 4",
    "sg:city":"Viveiro",
    "sg:orig_category":"Ingeniero",
    "sg:phone":"+34 982 55 18 72",
    "sg:postcode":"27850",
    "sg:province":"Lugo",
    "wof:name":"Fernandez Andia Jose Maria",
    "wof:placetype":"venue"
},
  "geometry": {"coordinates":[-7.5959348679,43.6629714966],"type":"Point"}
}