{
  "type": "Feature",
  "properties": {
    "addr:full":"Avda Republica Argentina, 7 Palencia Palencia 34002",
    "addr:housenumber":"7",
    "addr:postcode":"34002",
    "addr:street":"Avda Republica Argentina",
    "iso:country":"ES",
    "sg:address":"Avda Republica Argentina, 7",
    "sg:city":"Palencia",
    "sg:orig_category":"Sociedades, Compa\u00d1\u00cdas Aseguradoras",
    "sg:phone":"+34 979 16 58 54",
    "sg:postcode":"34002",
    "sg:province":"Palencia",
    "sg:website":"www.vitalicio.es",
    "wof:name":"Banco Vitalicio De Espa\u00f1a C.a.",
    "wof:placetype":"venue"
},
  "geometry": {"coordinates":[-4.5288419724,42.0038948059],"type":"Point"}
}