{
  "type": "Feature",
  "properties": {
    "addr:full":"Av Rei En Jaume, 74 Cardedeu Barcelona 08440",
    "addr:housenumber":"74",
    "addr:postcode":"08440",
    "addr:street":"Av Rei En Jaume",
    "iso:country":"ES",
    "sg:address":"Av Rei En Jaume, 74",
    "sg:city":"Cardedeu",
    "sg:orig_category":"Patatas (al Por Mayor)",
    "sg:phone":"+34 938 46 10 19",
    "sg:postcode":"08440",
    "sg:province":"Barcelona",
    "wof:name":"Turro Mas Luis",
    "wof:placetype":"venue"
},
  "geometry": {"coordinates":[2.3567230701,41.6370277405],"type":"Point"}
}