{
  "type": "Feature",
  "properties": {
    "addr:full":"Avda Campo De Futbol, S/n Carlota C\u00f3rdoba 14100",
    "addr:housenumber":"s / n",
    "addr:postcode":"14100",
    "addr:street":"Avda Campo;Carlota Co\u0301Rdoba",
    "iso:country":"ES",
    "sg:address":"Avda Campo De Futbol, S/n",
    "sg:city":"Carlota",
    "sg:orig_category":"Agentes Generales De Seguros",
    "sg:phone":"+34 957 30 00 19",
    "sg:postcode":"14100",
    "sg:province":"C\u00f3rdoba",
    "wof:name":"Agrogileto S.a.",
    "wof:placetype":"venue"
},
  "geometry": {"coordinates":[-4.9353189468,37.6667098999],"type":"Point"}
}