{
  "type": "Feature",
  "properties": {
    "addr:full":"Calle de Alcala, 290 Madrid Madrid 28027",
    "addr:housenumber":"290",
    "addr:postcode":"28027",
    "addr:street":"Calle De Alcala",
    "iso:country":"ES",
    "sg:address":"Calle de Alcala, 290",
    "sg:city":"Madrid",
    "sg:orig_category":"Fabricaci\u00d3n, Importaci\u00d3n, Venta De Material De Telefon\u00cda, Peritelefon\u00cda",
    "sg:phone":"+34 914 05 17 82",
    "sg:postcode":"28027",
    "sg:province":"Madrid",
    "wof:name":"Master Dis S.l.",
    "wof:placetype":"venue"
},
  "geometry": {"coordinates":[-3.6513278484,40.4326515198],"type":"Point"}
}