{
  "type": "Feature",
  "properties": {
    "addr:full":"Rbla Sant Sebastia, 32 Santa Coloma De Gramenet Barcelona 08922",
    "addr:housenumber":"32",
    "addr:postcode":"08922",
    "addr:street":"Rbla Sant Sebastia",
    "iso:country":"ES",
    "sg:address":"Rbla Sant Sebastia, 32",
    "sg:city":"Santa Coloma De Gramenet",
    "sg:orig_category":"Cajas De Ahorro",
    "sg:phone":"+34 934 66 53 41",
    "sg:postcode":"08922",
    "sg:province":"Barcelona",
    "wof:name":"Caja De Ahorros Del Mediterraneo",
    "wof:placetype":"venue"
},
  "geometry": {"coordinates":[2.2108180523,41.4506568909],"type":"Point"}
}