{
  "type": "Feature",
  "properties": {
    "iso:country":"ES",
    "sg:address":"Calle de Elias Serra Rafols, 21",
    "sg:city":"San Cristobal De La Laguna",
    "sg:orig_category":"Supermercados Y Hipermercados",
    "sg:phone":"+34 922 26 13 42",
    "sg:postcode":"38204",
    "sg:province":"Santa Cruz De Tenerife",
    "wof:name":"Pick-up Laguna S.l.",
    "wof:placetype":"venue"
},
  "geometry": {"coordinates":[-16.313993454,28.4822273254],"type":"Point"}
}