{
  "type": "Feature",
  "properties": {
    "iso:country":"ES",
    "sg:address":"Avda Cantabrico, 2",
    "sg:city":"Vitoria-gasteiz",
    "sg:orig_category":"Productos Qu\u00cdmicos (fabricaci\u00d3n, Al Por Mayor)",
    "sg:phone":"+34 945 27 15 38",
    "sg:postcode":"01013",
    "sg:province":"\u00c1lava",
    "wof:name":"Sarachu Villodas Jose Luis",
    "wof:placetype":"venue"
},
  "geometry": {"coordinates":[-2.6554229259,42.864440918],"type":"Point"}
}