{
  "type": "Feature",
  "properties": {
    "iso:country":"ES",
    "sg:address":"Calle de Atenea, 6",
    "sg:city":"Valdemoro",
    "sg:orig_category":"Guarder\u00cdas",
    "sg:phone":"+34 918 08 04 65",
    "sg:postcode":"28340",
    "sg:province":"Madrid",
    "wof:name":"Guarderia Los Delfines Siglo Xxi S.l.",
    "wof:placetype":"venue"
},
  "geometry": {"coordinates":[-3.6836106777,40.1775283813],"type":"Point"}
}