{
  "type": "Feature",
  "properties": {
    "iso:country":"ES",
    "sg:address":"Avda Suero De Qui\u00d1ones, 14",
    "sg:city":"Le\u00f3n",
    "sg:orig_category":"Confecci\u00d3n De Trajes Para Se\u00d1oras",
    "sg:phone":"+34 987 22 46 25",
    "sg:postcode":"24002",
    "sg:province":"Le\u00f3n",
    "wof:name":"Jose Garcia Tascon S. A.",
    "wof:placetype":"venue"
},
  "geometry": {"coordinates":[-5.5769681931,42.6019020081],"type":"Point"}
}