{
  "type": "Feature",
  "properties": {
    "addr:full":"Calle de Alamo, 21 Torrejon Ardoz Madrid 28850",
    "addr:housenumber":"21",
    "addr:postcode":"28850",
    "addr:street":"Calle De Alamo",
    "iso:country":"ES",
    "sg:address":"Calle de Alamo, 21",
    "sg:city":"Torrejon Ardoz",
    "sg:orig_category":"Agentes, Concesionarios Y Sucursales De Veh\u00cdculos",
    "sg:phone":"+34 916 75 01 47",
    "sg:postcode":"28850",
    "sg:province":"Madrid",
    "wof:name":"Vergara Flores Isidro",
    "wof:placetype":"venue"
},
  "geometry": {"coordinates":[-3.4570000172,40.4461479187],"type":"Point"}
}