{
  "type": "Feature",
  "properties": {
    "iso:country":"ES",
    "sg:address":"Calle de Benjamin Dominguez, 15",
    "sg:city":"Tarancon",
    "sg:orig_category":"Frutas Y Legumbres Secas (al Por Mayor)",
    "sg:phone":"+34 969 32 08 52",
    "sg:postcode":"16400",
    "sg:province":"Cuenca",
    "wof:name":"Olmeca Tarancon S.l",
    "wof:placetype":"venue"
},
  "geometry": {"coordinates":[-3.0045363903,40.0072822571],"type":"Point"}
}