{
  "type": "Feature",
  "properties": {
    "addr:full":"Pase Magnolios De Los (montecarlo), 45 Talavera Reina Toledo 45600",
    "addr:housenumber":"45",
    "addr:postcode":"45600",
    "addr:street":"Magnolios;Los Montecarlo",
    "iso:country":"ES",
    "sg:address":"Pase Magnolios De Los (montecarlo), 45",
    "sg:city":"Talavera Reina",
    "sg:orig_category":"Arquitectos",
    "sg:phone":"+34 925 80 62 93",
    "sg:postcode":"45600",
    "sg:province":"Toledo",
    "wof:name":"Frutos Alonso Victoriano De",
    "wof:placetype":"venue"
},
  "geometry": {"coordinates":[-4.8326292038,39.9584884644],"type":"Point"}
}