{
  "type": "Feature",
  "properties": {
    "addr:full":"Ctra. Villamuelas, Km. 0567,5 Villasequilla Toledo 45740",
    "addr:postcode":"45740",
    "addr:street":"Ctra. Villamuelas Km. 0567,5",
    "iso:country":"ES",
    "sg:address":"Ctra. Villamuelas, Km. 0567,5",
    "sg:city":"Villasequilla",
    "sg:orig_category":"Productores Recolectores, Venta Directa De Vinos",
    "sg:phone":"+34 925 32 51 33",
    "sg:postcode":"45740",
    "sg:province":"Toledo",
    "wof:name":"Bodegas Hermanos Rubio S. L.",
    "wof:placetype":"venue"
},
  "geometry": {"coordinates":[-3.7288589478,39.8753967285],"type":"Point"}
}