{
  "type": "Feature",
  "properties": {
    "iso:country":"ES",
    "sg:address":"Calle de Bolivia, 5",
    "sg:city":"Valencina Concepcion",
    "sg:orig_category":"Importaci\u00d3n",
    "sg:phone":"+34 955 72 81 10",
    "sg:postcode":"41907",
    "sg:province":"Sevilla",
    "sg:website":"www.lautaleuropa.com",
    "wof:name":"Lautal Europa S.l.",
    "wof:placetype":"venue"
},
  "geometry": {"coordinates":[-6.0812344551,37.4156608582],"type":"Point"}
}