{
  "type": "Feature",
  "properties": {
    "addr:full":"Calle de Salvador Allende, S/n Almagro Ciudad Real 13270",
    "addr:housenumber":"/ n",
    "addr:postcode":"13270",
    "addr:street":"Calle De Salvador Allende S",
    "iso:country":"ES",
    "sg:address":"Calle de Salvador Allende, S/n",
    "sg:city":"Almagro",
    "sg:orig_category":"Partidos Pol\u00cdticos",
    "sg:phone":"+34 926 86 11 49",
    "sg:postcode":"13270",
    "sg:province":"Ciudad Real",
    "wof:name":"Partido Socialista Obrero Espa\u00f1ol",
    "wof:placetype":"venue"
},
  "geometry": {"coordinates":[-3.7175579071,38.8875083923],"type":"Point"}
}