{
  "type": "Feature",
  "properties": {
    "iso:country":"ES",
    "sg:address":"Carrer de Joan Prim, 52",
    "sg:city":"Premia Mar",
    "sg:orig_category":"Ropa Para Caballeros (al Por Menor)",
    "sg:phone":"+34 937 54 71 65",
    "sg:postcode":"08330",
    "sg:province":"Barcelona",
    "wof:name":"Mateos S.c.p.",
    "wof:placetype":"venue"
},
  "geometry": {"coordinates":[2.3586649895,41.4925193787],"type":"Point"}
}