{
  "type": "Feature",
  "properties": {
    "iso:country":"ES",
    "sg:address":"Calle de San Francisco, 14",
    "sg:city":"Santander",
    "sg:orig_category":"Lencer\u00cda Femenina, Corseter\u00cda, Trajes De Ba\u00d1o (al Por Menor)",
    "sg:phone":"+34 942 21 22 13",
    "sg:postcode":"39002",
    "sg:province":"Cantabria",
    "wof:name":"Alvarez Villama\u00f1an Mercedes",
    "wof:placetype":"venue"
},
  "geometry": {"coordinates":[-3.8083679676,43.4618110657],"type":"Point"}
}