{
  "type": "Feature",
  "properties": {
    "iso:country":"ES",
    "sg:address":"Calle de Vitoria, 5",
    "sg:city":"Miranda Ebro",
    "sg:orig_category":"Asociaciones, Instituciones De Consumidores Y Usuarios",
    "sg:phone":"+34 947 31 27 44",
    "sg:postcode":"09200",
    "sg:province":"Burgos",
    "wof:name":"Asociacion Amas De Casa Y Consumidores Allende",
    "wof:placetype":"venue"
},
  "geometry": {"coordinates":[-2.9487481117,42.6855316162],"type":"Point"}
}