{
  "type": "Feature",
  "properties": {
    "iso:country":"ES",
    "sg:address":"Carrer de Miguel Hernandez, 13",
    "sg:city":"Guardamar Segura",
    "sg:orig_category":"Plomeros",
    "sg:phone":"+34 965 72 82 96",
    "sg:postcode":"03140",
    "sg:province":"Alicante",
    "wof:name":"Fontaneria Senent S.l.",
    "wof:placetype":"venue"
},
  "geometry": {"coordinates":[-0.6537110209,38.0893325806],"type":"Point"}
}