{
  "type": "Feature",
  "properties": {
    "addr:full":"Plaz Teniente Ruiz, 3 Ceuta Ceuta 51001",
    "addr:housenumber":"3",
    "addr:postcode":"51001",
    "addr:street":"Plaz Teniente Ruiz",
    "iso:country":"ES",
    "sg:address":"Plaz Teniente Ruiz, 3",
    "sg:city":"Ceuta",
    "sg:orig_category":"Seguros",
    "sg:phone":"+34 956 51 31 27",
    "sg:postcode":"51001",
    "sg:province":"Ceuta",
    "wof:name":"Segurotecnia Biosca S.l.",
    "wof:placetype":"venue"
},
  "geometry": {"coordinates":[-5.3302302361,35.8947601318],"type":"Point"}
}