{
  "type": "Feature",
  "properties": {
    "iso:country":"ES",
    "sg:address":"Calle de Archipielago, 6",
    "sg:city":"Arganda",
    "sg:orig_category":"Transporte En General",
    "sg:phone":"+34 918 71 39 36",
    "sg:postcode":"28500",
    "sg:province":"Madrid",
    "wof:name":"Localizaciones Mobiles S.l.",
    "wof:placetype":"venue"
},
  "geometry": {"coordinates":[-3.4659450054,40.3101158142],"type":"Point"}
}