{
  "type": "Feature",
  "properties": {
    "addr:full":"P Ind Risco Prieto, 17 Pto. Rosario Las Palmas 35600",
    "addr:housenumber":"17",
    "addr:postcode":"35600",
    "addr:street":"Prieto;Pto. Rosario Las",
    "iso:country":"ES",
    "sg:address":"P Ind Risco Prieto, 17",
    "sg:city":"Pto. Rosario",
    "sg:orig_category":"Importaci\u00d3n",
    "sg:phone":"+34 928 53 16 60",
    "sg:postcode":"35600",
    "sg:province":"Las Palmas",
    "wof:name":"Nordfrost Canarias S.a.",
    "wof:placetype":"venue"
},
  "geometry": {"coordinates":[-13.8644685745,28.5023498535],"type":"Point"}
}