{
  "type": "Feature",
  "properties": {
    "addr:full":"Calle de Cambroneras, 46 Lominchar Toledo 45212",
    "addr:housenumber":"46",
    "addr:postcode":"45212",
    "addr:street":"Calle De Cambroneras",
    "iso:country":"ES",
    "sg:address":"Calle de Cambroneras, 46",
    "sg:city":"Lominchar",
    "sg:orig_category":"Molinos",
    "sg:phone":"+34 925 55 81 32",
    "sg:postcode":"45212",
    "sg:province":"Toledo",
    "wof:name":"Hermanos Martin Hernandez C.b.",
    "wof:placetype":"venue"
},
  "geometry": {"coordinates":[-3.9649674892,40.0889778137],"type":"Point"}
}