{
  "type": "Feature",
  "properties": {
    "iso:country":"ES",
    "sg:address":"Calle de Cuchilleria, 4",
    "sg:city":"Ciudad Real",
    "sg:orig_category":"Seguridad Social",
    "sg:phone":"+34 926 27 44 60",
    "sg:postcode":"13001",
    "sg:province":"Ciudad Real",
    "wof:name":"Asepeyo Mutua Patronal De Accidentes De Trabajo",
    "wof:placetype":"venue"
},
  "geometry": {"coordinates":[-3.9280238152,38.9850006104],"type":"Point"}
}