{
  "type": "Feature",
  "properties": {
    "iso:country":"ES",
    "sg:address":"Calle de Pintor Maximino Pe\u00d1a, 1",
    "sg:city":"Soria",
    "sg:orig_category":"Molduras, Junquillos, Listones Y Molduras Perforadas",
    "sg:phone":"+34 975 23 03 92",
    "sg:postcode":"42004",
    "sg:province":"Soria",
    "wof:name":"Pascual Leal Lorenzo",
    "wof:placetype":"venue"
},
  "geometry": {"coordinates":[-2.473195076,41.7605247498],"type":"Point"}
}