{
  "type": "Feature",
  "properties": {
    "iso:country":"ES",
    "sg:address":"Carrer de Music Rafael Rodriguez Albert, 12",
    "sg:city":"Mutxamel",
    "sg:orig_category":"Mec\u00c1nico Del Autom\u00d3vil",
    "sg:phone":"+34 965 95 10 32",
    "sg:postcode":"03110",
    "sg:province":"Alicante",
    "wof:name":"Ayela Barbero Jose",
    "wof:placetype":"venue"
},
  "geometry": {"coordinates":[-0.445558995,38.4134483337],"type":"Point"}
}