{
  "type": "Feature",
  "properties": {
    "iso:country":"ES",
    "sg:address":"Send Almazara, S/n",
    "sg:city":"Huerta De Monteagudo",
    "sg:orig_category":"Empresas De Carpinter\u00cda Met\u00c1lica",
    "sg:phone":"+34 968 83 54 17",
    "sg:postcode":"30160",
    "sg:province":"Murcia",
    "wof:name":"Wiron Construcciones Modulares S.a.",
    "wof:placetype":"venue"
},
  "geometry": {"coordinates":[-1.0980267525,38.0188407898],"type":"Point"}
}