{
  "type": "Feature",
  "properties": {
    "addr:full":"Calle de Batalla Del Salado, 12 Madrid Madrid 28045",
    "addr:housenumber":"12",
    "addr:postcode":"madrid;28045",
    "addr:street":"Calle De Batalla Del Salado",
    "iso:country":"ES",
    "sg:address":"Calle de Batalla Del Salado, 12",
    "sg:city":"Madrid",
    "sg:orig_category":"Frutas, Legumbres Frescas Y Tempranas (al Por Menor)",
    "sg:phone":"+34 914 67 53 01",
    "sg:postcode":"28045",
    "sg:province":"Madrid",
    "wof:name":"De Grado Garzon Maria Dolores",
    "wof:placetype":"venue"
},
  "geometry": {"coordinates":[-3.6959705353,40.4029846191],"type":"Point"}
}