{
  "type": "Feature",
  "properties": {
    "addr:full":"Carr Pirineus, 2 Quart Girona 17242",
    "addr:housenumber":"2",
    "addr:postcode":"17242",
    "addr:street":"Carr Pirineus",
    "iso:country":"ES",
    "sg:address":"Carr Pirineus, 2",
    "sg:city":"Quart",
    "sg:orig_category":"Molduras, Junquillos, Listones Y Molduras Perforadas",
    "sg:phone":"+34 972 46 80 96",
    "sg:postcode":"17242",
    "sg:province":"Girona",
    "wof:name":"Perez Salas Angel",
    "wof:placetype":"venue"
},
  "geometry": {"coordinates":[2.8420550823,41.9365539551],"type":"Point"}
}