{
  "type": "Feature",
  "properties": {
    "addr:full":"Carr Pedraforca, 3 Girona Girona 17006",
    "addr:housenumber":"3",
    "addr:postcode":"17006",
    "addr:street":"Carr Pedraforca",
    "iso:country":"ES",
    "sg:address":"Carr Pedraforca, 3",
    "sg:city":"Girona",
    "sg:orig_category":"Lencer\u00cda Femenina, Corseter\u00cda, Trajes De Ba\u00d1o (al Por Menor)",
    "sg:phone":"+34 972 23 36 48",
    "sg:postcode":"17006",
    "sg:province":"Girona",
    "wof:name":"Wu  Xiaoquin",
    "wof:placetype":"venue"
},
  "geometry": {"coordinates":[2.8015220165,41.9736404419],"type":"Point"}
}