{
  "type": "Feature",
  "properties": {
    "iso:country":"ES",
    "sg:address":"Pg Sant Joan Bosco, 49",
    "sg:city":"Girona",
    "sg:orig_category":"Chapister\u00cda",
    "sg:phone":"+34 972 20 94 69",
    "sg:postcode":"17007",
    "sg:province":"Girona",
    "wof:name":"Tallers Robicar 2 Mil S.c.c.l.",
    "wof:placetype":"venue"
},
  "geometry": {"coordinates":[2.8247070312,42.0083084106],"type":"Point"}
}