{
  "type": "Feature",
  "properties": {
    "addr:full":"Calle de Karl Braun, 14 San Fernando De Henares Madrid 28830",
    "addr:housenumber":"14",
    "addr:postcode":"28830",
    "addr:street":"Calle De Karl Braun",
    "iso:country":"ES",
    "sg:address":"Calle de Karl Braun, 14",
    "sg:city":"San Fernando De Henares",
    "sg:orig_category":"Importaci\u00d3n",
    "sg:phone":"+34 916 74 33 38",
    "sg:postcode":"28830",
    "sg:province":"Madrid",
    "wof:name":"Gestion Metalicas S.l.",
    "wof:placetype":"venue"
},
  "geometry": {"coordinates":[-3.5218698978,40.4181594849],"type":"Point"}
}