{
  "type": "Feature",
  "properties": {
    "addr:full":"Calle de Ancha, 52 Sanlucar De Barrameda C\u00e1diz 11540",
    "addr:housenumber":"52",
    "addr:postcode":"11540",
    "addr:street":"Calle De Ancha;Ca\u0301Diz",
    "iso:country":"ES",
    "sg:address":"Calle de Ancha, 52",
    "sg:city":"Sanlucar De Barrameda",
    "sg:orig_category":"Deportes Y Programas De Aventura",
    "sg:phone":"+34 956 36 70 51",
    "sg:postcode":"11540",
    "sg:province":"C\u00e1diz",
    "wof:name":"Radical Sport Costaluz S.l.",
    "wof:placetype":"venue"
},
  "geometry": {"coordinates":[-6.3527994156,36.7791290283],"type":"Point"}
}