{
  "type": "Feature",
  "properties": {
    "iso:country":"ES",
    "sg:address":"Pase Profesor Enrique Tierno Galvan, S/n",
    "sg:city":"Santa Marta De Tormes",
    "sg:orig_category":"Asociaciones Y Clubs Deportivos",
    "sg:phone":"+34 923 13 30 05",
    "sg:postcode":"37900",
    "sg:province":"Salamanca",
    "wof:name":"Club Union Deportiva Santa Marta",
    "wof:placetype":"venue"
},
  "geometry": {"coordinates":[-5.6253638268,40.945148468],"type":"Point"}
}