{
  "type": "Feature",
  "properties": {
    "addr:full":"Calle de Eduardo Dominguez Avila, 3 Malaga M\u00e1laga 29014",
    "addr:housenumber":"3",
    "addr:postcode":"29014",
    "addr:street":"Calle De Eduardo Dominguez Avila;Ma\u0301Laga",
    "iso:country":"ES",
    "sg:address":"Calle de Eduardo Dominguez Avila, 3",
    "sg:city":"Malaga",
    "sg:orig_category":"Cajas De Ahorro",
    "sg:phone":"+34 952 25 92 36",
    "sg:postcode":"29014",
    "sg:province":"M\u00e1laga",
    "wof:name":"Unicaja",
    "wof:placetype":"venue"
},
  "geometry": {"coordinates":[-4.4215250015,36.7298355103],"type":"Point"}
}