{
  "type": "Feature",
  "properties": {
    "iso:country":"ES",
    "sg:address":"Avda Granada, 51",
    "sg:city":"Jaen",
    "sg:orig_category":"Piscinas, Accesorios, Suministros (fabricaci\u00d3n, Al Por Mayor)",
    "sg:phone":"+34 953 24 23 86",
    "sg:postcode":"23001",
    "sg:province":"Ja\u00e9n",
    "wof:name":"Covalsan S. L.",
    "wof:placetype":"venue"
},
  "geometry": {"coordinates":[-3.781224966,37.7696304321],"type":"Point"}
}