{
  "type": "Feature",
  "properties": {
    "iso:country":"ES",
    "sg:address":"Pol Ind Gallardo, 1",
    "sg:city":"La Carlota",
    "sg:orig_category":"Albergues",
    "sg:phone":"+34 957 30 16 30",
    "sg:postcode":"14100",
    "sg:province":"C\u00f3rdoba",
    "wof:name":"Ceramica La Carlota S.l.",
    "wof:placetype":"venue"
},
  "geometry": {"coordinates":[-4.9374890327,37.6685142517],"type":"Point"}
}