{
  "type": "Feature",
  "properties": {
    "addr:full":"Calle de Bailio (del), 19 Tudela Navarra 31500",
    "addr:postcode":"31500",
    "addr:street":"Calle De Bailio Del",
    "iso:country":"ES",
    "sg:address":"Calle de Bailio (del), 19",
    "sg:city":"Tudela",
    "sg:orig_category":"Restaurantes",
    "sg:phone":"+34 948 82 22 07",
    "sg:postcode":"31500",
    "sg:province":"Navarra",
    "wof:name":"Alvarez Zugasti Jose Luis",
    "wof:placetype":"venue"
},
  "geometry": {"coordinates":[-1.6044313908,42.0510406494],"type":"Point"}
}