{
  "type": "Feature",
  "properties": {
    "iso:country":"ES",
    "sg:address":"Praz Bugallal, 1",
    "sg:city":"Ponteareas",
    "sg:orig_category":"Alimentaci\u00d3n General (al Por Menor)",
    "sg:phone":"+34 986 64 07 58",
    "sg:postcode":"36860",
    "sg:province":"Pontevedra",
    "wof:name":"Wagner Optik S.l",
    "wof:placetype":"venue"
},
  "geometry": {"coordinates":[-8.5391435623,42.2035446167],"type":"Point"}
}