{
  "type": "Feature",
  "properties": {
    "addr:full":"Calle de San Esteban, S/n Almazcara Le\u00f3n 24398",
    "addr:housenumber":"s",
    "addr:postcode":"24398",
    "addr:street":"Calle De San;/ N Almazcara Leo\u0301N",
    "iso:country":"ES",
    "sg:address":"Calle de San Esteban, S/n",
    "sg:city":"Almazcara",
    "sg:orig_category":"M\u00c1rmoles, Granitos Y Piedras Naturales",
    "sg:phone":"+34 987 46 70 74",
    "sg:postcode":"24398",
    "sg:province":"Le\u00f3n",
    "sg:website":"www.paginasamarillas.es",
    "wof:name":"Marmoles Luengo S.l",
    "wof:placetype":"venue"
},
  "geometry": {"coordinates":[-6.497563839,42.5967712402],"type":"Point"}
}