{
  "type": "Feature",
  "properties": {
    "iso:country":"ES",
    "sg:address":"Avda General (del), 8",
    "sg:city":"El Cruce",
    "sg:orig_category":"Mec\u00c1nico Del Autom\u00d3vil",
    "sg:phone":"+34 916 58 11 41",
    "sg:postcode":"28860",
    "sg:province":"Madrid",
    "wof:name":"Motor Holgado S.l.",
    "wof:placetype":"venue"
},
  "geometry": {"coordinates":[-3.5296940804,40.5049209595],"type":"Point"}
}