{
  "type": "Feature",
  "properties": {
    "addr:full":"Avda Noruega, 5 Gran Alacant Alicante 03130",
    "addr:housenumber":"5",
    "addr:postcode":"03130",
    "addr:street":"Avda Noruega",
    "iso:country":"ES",
    "sg:address":"Avda Noruega, 5",
    "sg:city":"Gran Alacant",
    "sg:orig_category":"Cajas De Ahorro",
    "sg:phone":"+34 966 69 88 94",
    "sg:postcode":"03130",
    "sg:province":"Alicante",
    "wof:name":"Caja De Ahorros Del Mediterraneo",
    "wof:placetype":"venue"
},
  "geometry": {"coordinates":[-0.55775702,38.2050170898],"type":"Point"}
}