{
  "type": "Feature",
  "properties": {
    "iso:country":"ES",
    "sg:address":"Carrer de Padua, 104",
    "sg:city":"Barcelona",
    "sg:orig_category":"Ense\u00d1anza: Profesiones Art\u00cdsticas",
    "sg:phone":"+34 934 17 95 22",
    "sg:postcode":"08006",
    "sg:province":"Barcelona",
    "wof:name":"X.p.fotograf S.l.",
    "wof:placetype":"venue"
},
  "geometry": {"coordinates":[2.1432180405,41.4037437439],"type":"Point"}
}