{
  "type": "Feature",
  "properties": {
    "iso:country":"ES",
    "sg:address":"Poligon Industrial De Girona, S/n",
    "sg:city":"Riudellots Selva",
    "sg:orig_category":"M\u00c1quinas Y Material Para La Industria De La Alimentaci\u00d3n",
    "sg:phone":"+34 972 47 84 36",
    "sg:postcode":"17457",
    "sg:province":"Girona",
    "sg:website":"wwwtecnical.com",
    "wof:name":"Tecnical Tecnologia Aplicada Sll",
    "wof:placetype":"venue"
},
  "geometry": {"coordinates":[2.8304951191,41.8967056274],"type":"Point"}
}