{
  "type": "Feature",
  "properties": {
    "iso:country":"ES",
    "sg:address":"Calle de Ronda Del Peliron, 26",
    "sg:city":"Jerez De La Frontera",
    "sg:orig_category":"Higiene, Belleza: Art\u00cdculos (al Por Menor)",
    "sg:phone":"+34 956 16 88 03",
    "sg:postcode":"11405",
    "sg:province":"C\u00e1diz",
    "wof:name":"Rutesa S.l.",
    "wof:placetype":"venue"
},
  "geometry": {"coordinates":[-6.1005191803,36.7067260742],"type":"Point"}
}