{
  "type": "Feature",
  "properties": {
    "iso:country":"ES",
    "sg:address":"Carrer de Sant Pau, 10",
    "sg:city":"Barcelona",
    "sg:orig_category":"Molduras, Junquillos, Listones Y Molduras Perforadas",
    "sg:phone":"+34 933 02 55 32",
    "sg:postcode":"08001",
    "sg:province":"Barcelona",
    "wof:name":"Bolos Santagueda Nicasio",
    "wof:placetype":"venue"
},
  "geometry": {"coordinates":[2.1729199886,41.3806686401],"type":"Point"}
}