{
  "type": "Feature",
  "properties": {
    "addr:full":"Avda Granada (de), 10 Chipiona C\u00e1diz 11550",
    "addr:housenumber":"10",
    "addr:postcode":"11550",
    "addr:street":"Avda Granada De",
    "iso:country":"ES",
    "sg:address":"Avda Granada (de), 10",
    "sg:city":"Chipiona",
    "sg:orig_category":"Empresas De Carpinter\u00cda De Madera",
    "sg:phone":"+34 956 37 29 54",
    "sg:postcode":"11550",
    "sg:province":"C\u00e1diz",
    "wof:name":"Mellado Espinosa Jose",
    "wof:placetype":"venue"
},
  "geometry": {"coordinates":[-6.4308590889,36.7408981323],"type":"Point"}
}