{
  "type": "Feature",
  "properties": {
    "addr:full":"Avda Ciudad De Pescia, 16 Nerja M\u00e1laga 29780",
    "addr:housenumber":"16",
    "addr:postcode":"29780",
    "addr:street":"Avda Ciudad De Pescia",
    "iso:country":"ES",
    "sg:address":"Avda Ciudad De Pescia, 16",
    "sg:city":"Nerja",
    "sg:orig_category":"Cajas Para Embalar",
    "sg:phone":"+34 952 52 73 74",
    "sg:postcode":"29780",
    "sg:province":"M\u00e1laga",
    "sg:website":"www.cajamar.es",
    "wof:name":"Cajamar",
    "wof:placetype":"venue"
},
  "geometry": {"coordinates":[-3.8762149811,36.751914978],"type":"Point"}
}