{
  "type": "Feature",
  "properties": {
    "iso:country":"ES",
    "sg:address":"Calle de Fuente Del Real, 18",
    "sg:city":"Gijon",
    "sg:orig_category":"Peluqueros: De Se\u00d1oras",
    "sg:phone":"+34 985 16 07 73",
    "sg:postcode":"33209",
    "sg:province":"Asturias",
    "wof:name":"Ordo\u00f1ez Canga Noemi",
    "wof:placetype":"venue"
},
  "geometry": {"coordinates":[-5.6564722061,43.531879425],"type":"Point"}
}