{
  "type": "Feature",
  "properties": {
    "addr:full":"Avda Aragon, 83 Alca\u00f1iz Teruel 44600",
    "addr:housenumber":"83",
    "addr:postcode":"44600",
    "addr:street":"Avda Aragon",
    "iso:country":"ES",
    "sg:address":"Avda Aragon, 83",
    "sg:city":"Alca\u00f1iz",
    "sg:orig_category":"\u00d3ptica: Instrumentos (fabricaci\u00d3n)",
    "sg:phone":"+34 978 83 30 69",
    "sg:postcode":"44600",
    "sg:province":"Teruel",
    "wof:name":"Novella Rivilla Ruben",
    "wof:placetype":"venue"
},
  "geometry": {"coordinates":[-0.1293150038,41.0452461243],"type":"Point"}
}