{
  "type": "Feature",
  "properties": {
    "iso:country":"ES",
    "sg:address":"Calle de Casta\u00d1uelos, 32",
    "sg:city":"Candeleda",
    "sg:orig_category":"Agencias Y Agentes Comerciales, Representantes",
    "sg:phone":"+34 920 38 10 68",
    "sg:postcode":"05480",
    "sg:province":"\u00c1vila",
    "wof:name":"Mechasa S.l.",
    "wof:placetype":"venue"
},
  "geometry": {"coordinates":[-5.2396755219,40.1569976807],"type":"Point"}
}