{
  "type": "Feature",
  "properties": {
    "addr:full":"Calle de Castillo, 15 Santa Cruz De Tenerife Santa Cruz De Tenerife 38002",
    "addr:housenumber":"15",
    "addr:postcode":"38002",
    "addr:street":"Calle De Castillo",
    "iso:country":"ES",
    "sg:address":"Calle de Castillo, 15",
    "sg:city":"Santa Cruz De Tenerife",
    "sg:orig_category":"Ingenier\u00cda, Centros De Estudios (diversos)",
    "sg:phone":"+34 922 28 60 02",
    "sg:postcode":"38002",
    "sg:province":"Santa Cruz De Tenerife",
    "wof:name":"Geohidro S.l.",
    "wof:placetype":"venue"
},
  "geometry": {"coordinates":[-16.2502269745,28.4669799805],"type":"Point"}
}