{
  "type": "Feature",
  "properties": {
    "addr:full":"Pg Lluis Companys, 10 Barcelona Barcelona 08018",
    "addr:housenumber":"10",
    "addr:postcode":"08018",
    "addr:street":"Pg Lluis Companys",
    "iso:country":"ES",
    "sg:address":"Pg Lluis Companys, 10",
    "sg:city":"Barcelona",
    "sg:orig_category":"Procuradores",
    "sg:phone":"+34 933 00 18 00",
    "sg:postcode":"08018",
    "sg:province":"Barcelona",
    "wof:name":"Fontquerni Bas Jorge",
    "wof:placetype":"venue"
},
  "geometry": {"coordinates":[2.1830890179,41.3899612427],"type":"Point"}
}