{
  "type": "Feature",
  "properties": {
    "addr:full":"Calle de Francos, 6 Sevilla Sevilla 41004",
    "addr:housenumber":"6",
    "addr:postcode":"41004",
    "addr:street":"Calle De Francos",
    "iso:country":"ES",
    "sg:address":"Calle de Francos, 6",
    "sg:city":"Sevilla",
    "sg:orig_category":"Complementos De Vestir (al Por Menor)",
    "sg:phone":"+34 954 21 58 29",
    "sg:postcode":"41004",
    "sg:province":"Sevilla",
    "wof:name":"Angela Y Lucia S.l.",
    "wof:placetype":"venue"
},
  "geometry": {"coordinates":[-5.9925093651,37.3895187378],"type":"Point"}
}