{
  "type": "Feature",
  "properties": {
    "addr:full":"Plaz Juan Grandia, 1 Requena Valencia 46340",
    "addr:housenumber":"1",
    "addr:postcode":"46340",
    "addr:street":"Plaz Juan Grandia",
    "iso:country":"ES",
    "sg:address":"Plaz Juan Grandia, 1",
    "sg:city":"Requena",
    "sg:orig_category":"Molduras, Junquillos, Listones Y Molduras Perforadas",
    "sg:phone":"+34 962 30 53 36",
    "sg:postcode":"46340",
    "sg:province":"Valencia",
    "wof:name":"Marin Navarro Juan",
    "wof:placetype":"venue"
},
  "geometry": {"coordinates":[-1.108232975,39.4883003235],"type":"Point"}
}