{
  "type": "Feature",
  "properties": {
    "iso:country":"ES",
    "sg:address":"Rond Universitat, 20",
    "sg:city":"Barcelona",
    "sg:orig_category":"Asesor\u00cda Fiscal Y Jur\u00cddica",
    "sg:phone":"+34 933 18 92 96",
    "sg:postcode":"08007",
    "sg:province":"Barcelona",
    "wof:name":"Davalillo Batlle Carmen",
    "wof:placetype":"venue"
},
  "geometry": {"coordinates":[2.1679649353,41.3870201111],"type":"Point"}
}