{
  "type": "Feature",
  "properties": {
    "addr:full":"Calle de Horizonte, 2 Mairena Aljarafe Sevilla 41927",
    "addr:housenumber":"2",
    "addr:postcode":"41927",
    "addr:street":"Calle De Horizonte",
    "iso:country":"ES",
    "sg:address":"Calle de Horizonte, 2",
    "sg:city":"Mairena Aljarafe",
    "sg:orig_category":"Reciclaje Y Tratamiento De Desechos Varios",
    "sg:phone":"+34 954 18 04 08",
    "sg:postcode":"41927",
    "sg:province":"Sevilla",
    "wof:name":"Bio Clean S.a.",
    "wof:placetype":"venue"
},
  "geometry": {"coordinates":[-6.0560789108,37.3539085388],"type":"Point"}
}