{
  "type": "Feature",
  "properties": {
    "iso:country":"ES",
    "sg:address":"Calle de Avila, 1",
    "sg:city":"Bilbao",
    "sg:orig_category":"Relojer\u00cda Industrial",
    "sg:phone":"+34 944 21 56 06",
    "sg:postcode":"48012",
    "sg:province":"Vizcaya",
    "wof:name":"Abdon Casta\u00f1os Fernandez",
    "wof:placetype":"venue"
},
  "geometry": {"coordinates":[-2.939495,43.257267],"type":"Point"}
}