{
  "type": "Feature",
  "properties": {
    "iso:country":"ES",
    "sg:address":"Carrer de Juan De La Cierva, 64",
    "sg:city":"Romanica",
    "sg:orig_category":"Materias Pl\u00c1sticas: Productos De Consumo Masivo (fabricaci\u00d3n, Al Por Mayor)",
    "sg:phone":"+34 937 29 14 65",
    "sg:postcode":"08210",
    "sg:province":"Barcelona",
    "sg:website":"www.papelessalvi.es",
    "wof:name":"Papeles Salvi S.a.",
    "wof:placetype":"venue"
},
  "geometry": {"coordinates":[2.1271760464,41.5150566101],"type":"Point"}
}