{
  "type": "Feature",
  "properties": {
    "addr:full":"Calle de Caridad, 2 Almazora Castell\u00f3n 12550",
    "addr:housenumber":"2",
    "addr:postcode":"12550",
    "addr:street":"Calle De Caridad",
    "iso:country":"ES",
    "sg:address":"Calle de Caridad, 2",
    "sg:city":"Almazora",
    "sg:orig_category":"\u00d3ptica: Instrumentos (fabricaci\u00d3n)",
    "sg:phone":"+34 964 56 17 23",
    "sg:postcode":"12550",
    "sg:province":"Castell\u00f3n",
    "wof:name":"Miralles Vives Vicente",
    "wof:placetype":"venue"
},
  "geometry": {"coordinates":[-0.0632951036,39.9460029602],"type":"Point"}
}