{
  "type": "Feature",
  "properties": {
    "addr:full":"Avda Marco (del), 11 Monterroso Lugo 27560",
    "addr:housenumber":"11",
    "addr:postcode":"27560",
    "addr:street":"Avda Marco Del",
    "iso:country":"ES",
    "sg:address":"Avda Marco (del), 11",
    "sg:city":"Monterroso",
    "sg:orig_category":"Artes Gr\u00c1ficas, Artes Pl\u00c1sticas (curso)",
    "sg:phone":"+34 982 37 76 13",
    "sg:postcode":"27560",
    "sg:province":"Lugo",
    "wof:name":"Filgraf S.l.",
    "wof:placetype":"venue"
},
  "geometry": {"coordinates":[-7.8329892159,42.7931404114],"type":"Point"}
}