{
  "type": "Feature",
  "properties": {
    "addr:full":"Calle de Gallinato, 9 Sevilla Sevilla 41018",
    "addr:housenumber":"9",
    "addr:postcode":"41018",
    "addr:street":"Calle De Gallinato",
    "iso:country":"ES",
    "sg:address":"Calle de Gallinato, 9",
    "sg:city":"Sevilla",
    "sg:orig_category":"Agencias Y Asesores De Publicidad",
    "sg:phone":"+34 954 41 97 04",
    "sg:postcode":"41018",
    "sg:province":"Sevilla",
    "sg:website":"www.hontoria.com",
    "wof:name":"Hontoria Producciones S.l.",
    "wof:placetype":"venue"
},
  "geometry": {"coordinates":[-5.9825987816,37.3829231262],"type":"Point"}
}