{
  "type": "Feature",
  "properties": {
    "addr:full":"Avda Pio Xii, 10 Logro\u00f1o La Rioja 26003",
    "addr:housenumber":"10",
    "addr:postcode":"26003",
    "addr:street":"Avda Pio Xii;Rioja",
    "iso:country":"ES",
    "sg:address":"Avda Pio Xii, 10",
    "sg:city":"Logro\u00f1o",
    "sg:orig_category":"Organizaciones Internacionales",
    "sg:phone":"+34 941 24 33 85",
    "sg:postcode":"26003",
    "sg:province":"La Rioja",
    "sg:website":"www.es.amnesty.org",
    "wof:name":"Amnistia Internacional Del Estado Espa\u00f1ol",
    "wof:placetype":"venue"
},
  "geometry": {"coordinates":[-2.4447436333,42.4605903625],"type":"Point"}
}