{
  "type": "Feature",
  "properties": {
    "iso:country":"ES",
    "sg:address":"Calle de Fray Luis Urbano, 59",
    "sg:city":"Zaragoza",
    "sg:orig_category":"Plomeros",
    "sg:phone":"+34 976 59 47 27",
    "sg:postcode":"50002",
    "sg:province":"Zaragoza",
    "wof:name":"Fontaneria Y Calefaccion Jose Y Luis S.l.",
    "wof:placetype":"venue"
},
  "geometry": {"coordinates":[-0.8596559763,41.6425094604],"type":"Point"}
}