{
  "type": "Feature",
  "properties": {
    "addr:full":"Calle de Eskurtze, 8 Bilbao Vizcaya 48012",
    "addr:housenumber":"8",
    "addr:postcode":"48012",
    "addr:street":"Calle De Eskurtze",
    "iso:country":"ES",
    "sg:address":"Calle de Eskurtze, 8",
    "sg:city":"Bilbao",
    "sg:orig_category":"T\u00c9cnicos Veterinarios",
    "sg:phone":"+34 944 21 85 75",
    "sg:postcode":"48012",
    "sg:province":"Vizcaya",
    "wof:name":"Aresti Aguado Irune",
    "wof:placetype":"venue"
},
  "geometry": {"coordinates":[-2.9379837513,43.2517814636],"type":"Point"}
}