{
  "type": "Feature",
  "properties": {
    "addr:full":"Avda General Aviles, 58 Valencia Valencia 46015",
    "addr:housenumber":"58",
    "addr:postcode":"46015",
    "addr:street":"Avda General Aviles",
    "iso:country":"ES",
    "sg:address":"Avda General Aviles, 58",
    "sg:city":"Valencia",
    "sg:orig_category":"Inform\u00c1tica (estudios, Servicios, Asesor\u00cda, Formaci\u00d3n)",
    "sg:phone":"+34 963 48 77 70",
    "sg:postcode":"46015",
    "sg:province":"Valencia",
    "sg:website":"www.myp-asociados.com",
    "wof:name":"Sistemas Informaticos De Gestion Marti Y Palacios Asociados S.l.",
    "wof:placetype":"venue"
},
  "geometry": {"coordinates":[-0.3998099864,39.4844589233],"type":"Point"}
}