{
  "type": "Feature",
  "properties": {
    "addr:full":"Calle de Belchite, 12 Sevilla Sevilla 41016",
    "addr:housenumber":"12",
    "addr:postcode":"41016",
    "addr:street":"Calle De Belchite",
    "iso:country":"ES",
    "sg:address":"Calle de Belchite, 12",
    "sg:city":"Sevilla",
    "sg:orig_category":"Almacenes Frigor\u00cdficos",
    "sg:phone":"+34 954 51 28 34",
    "sg:postcode":"41016",
    "sg:province":"Sevilla",
    "wof:name":"Suministros Y Mantenimientos Herrera Sociedad Limitada",
    "wof:placetype":"venue"
},
  "geometry": {"coordinates":[-5.9180812836,37.3847579956],"type":"Point"}
}