{
  "type": "Feature",
  "properties": {
    "addr:full":"Cril Sernas, 8 Algezares Murcia 30157",
    "addr:housenumber":"8",
    "addr:postcode":"30157",
    "addr:street":"Sernas",
    "iso:country":"ES",
    "sg:address":"Cril Sernas, 8",
    "sg:city":"Algezares",
    "sg:orig_category":"Contables",
    "sg:phone":"+34 968 37 95 05",
    "sg:postcode":"30157",
    "sg:province":"Murcia",
    "wof:name":"Tomas Escudero Alfonso David",
    "wof:placetype":"venue"
},
  "geometry": {"coordinates":[-1.111479044,37.9454307556],"type":"Point"}
}