{
  "type": "Feature",
  "properties": {
    "addr:full":"Avgd Horchata, 21 Alboraya Valencia 46120",
    "addr:housenumber":"21",
    "addr:postcode":"46120",
    "addr:street":"Horchata",
    "iso:country":"ES",
    "sg:address":"Avgd Horchata, 21",
    "sg:city":"Alboraya",
    "sg:orig_category":"Cajas De Ahorro",
    "sg:phone":"+34 961 85 94 07",
    "sg:postcode":"46120",
    "sg:province":"Valencia",
    "wof:name":"Caja De Ahorros De Valencia Castellon Y Alicante",
    "wof:placetype":"venue"
},
  "geometry": {"coordinates":[-0.3405140042,39.4990692139],"type":"Point"}
}