{
  "type": "Feature",
  "properties": {
    "iso:country":"ES",
    "sg:address":"Calle de Alamillo, 6",
    "sg:city":"Navas San Juan",
    "sg:orig_category":"Cajas De Ahorro",
    "sg:phone":"+34 953 68 93 05",
    "sg:postcode":"23240",
    "sg:province":"Ja\u00e9n",
    "sg:website":"www.unicaja.es",
    "wof:name":"Unicaja",
    "wof:placetype":"venue"
},
  "geometry": {"coordinates":[-3.3155910969,38.1846122742],"type":"Point"}
}