{
  "type": "Feature",
  "properties": {
    "iso:country":"ES",
    "sg:address":"Calle de Villamediana, 18",
    "sg:city":"Logro\u00f1o",
    "sg:orig_category":"Electrodom\u00c9sticos (al Por Menor)",
    "sg:phone":"+34 941 26 15 16",
    "sg:postcode":"26003",
    "sg:province":"La Rioja",
    "wof:name":"Mesanza Laya Angel",
    "wof:placetype":"venue"
},
  "geometry": {"coordinates":[-2.4427490234,42.4617576599],"type":"Point"}
}