{
  "type": "Feature",
  "properties": {
    "iso:country":"ES",
    "sg:address":"Plaz Parres Pi\u00d1era, 46",
    "sg:city":"Posada",
    "sg:classifiers":[
        {
            "category":"Personal",
            "subcategory":"Barber",
            "type":"Services"
        }
    ],
    "sg:phone":"+34 985 40 76 65",
    "sg:postcode":"33594",
    "sg:province":"Asturias",
    "sg:tags":[
        "caballeros",
        "de",
        "peluqueros"
    ],
    "wof:name":"Gutierrez Covian Jose Carlos",
    "wof:placetype":"venue"
},
  "geometry": {"coordinates":[-4.8618822098,43.4186553955],"type":"Point"}
}