{
  "type": "Feature",
  "properties": {
    "iso:country":"ES",
    "sg:address":"Calle de Jose Maria Valdenebro, 15",
    "sg:city":"Cordoba",
    "sg:orig_category":"Plomeros",
    "sg:phone":"+34 957 41 46 05",
    "sg:postcode":"14004",
    "sg:province":"C\u00f3rdoba",
    "wof:name":"Cabello Rivas Rafael",
    "wof:placetype":"venue"
},
  "geometry": {"coordinates":[-4.7899751663,37.8797454834],"type":"Point"}
}