{
  "type": "Feature",
  "properties": {
    "addr:full":"Calle de Misionero Lekuona, 38 Irun Guip\u00f9zcoa 20305",
    "addr:housenumber":"38",
    "addr:postcode":"20305",
    "addr:street":"Calle De Misionero Lekuona;Guipu\u0300Zcoa",
    "iso:country":"ES",
    "sg:address":"Calle de Misionero Lekuona, 38",
    "sg:city":"Irun",
    "sg:orig_category":"Iglesias Evang\u00c9licas",
    "sg:phone":"+34 943 66 02 37",
    "sg:postcode":"20305",
    "sg:province":"Guip\u00f9zcoa",
    "wof:name":"Iglesia Bautista Biblica",
    "wof:placetype":"venue"
},
  "geometry": {"coordinates":[-1.8099370003,43.3380813599],"type":"Point"}
}