{
  "type": "Feature",
  "properties": {
    "iso:country":"ES",
    "sg:address":"Calle de Ferrerets, 49",
    "sg:city":"Alcora",
    "sg:orig_category":"Aguas (distribuci\u00d3n, Servicios)",
    "sg:phone":"+34 964 36 23 60",
    "sg:postcode":"12110",
    "sg:province":"Castell\u00f3n",
    "wof:name":"Sociedad De Fomento Agricola Castellonense S.a.",
    "wof:placetype":"venue"
},
  "geometry": {"coordinates":[-0.212973997,40.0783309937],"type":"Point"}
}