{
  "type": "Feature",
  "properties": {
    "addr:full":"Calle de Camino De Santiago, 17 Ponferrada Le\u00f3n 24400",
    "addr:housenumber":"17",
    "addr:postcode":"24400",
    "addr:street":"Calle De Camino De Santiago",
    "iso:country":"ES",
    "sg:address":"Calle de Camino De Santiago, 17",
    "sg:city":"Ponferrada",
    "sg:orig_category":"M\u00c9dicos: Cirug\u00cda Urol\u00d3gica",
    "sg:phone":"+34 987 41 87 70",
    "sg:postcode":"24400",
    "sg:province":"Le\u00f3n",
    "sg:website":"www.paginasamarillas.es",
    "wof:name":"Monsalve Rodriguez Manuel",
    "wof:placetype":"venue"
},
  "geometry": {"coordinates":[-6.6009788513,42.548828125],"type":"Point"}
}