{
  "type": "Feature",
  "properties": {
    "iso:country":"ES",
    "sg:address":"Carr Sueca, S/n",
    "sg:city":"Cullera",
    "sg:orig_category":"Centros De Educaci\u00d3n Especial",
    "sg:phone":"+34 961 72 32 61",
    "sg:postcode":"46400",
    "sg:province":"Valencia",
    "wof:name":"Ayuntamiento De Cullera",
    "wof:placetype":"venue"
},
  "geometry": {"coordinates":[-0.2615965009,39.1729774475],"type":"Point"}
}