{
  "type": "Feature",
  "properties": {
    "addr:full":"Carrer de Bofarull, 48 Barcelona Barcelona 08027",
    "addr:housenumber":"48",
    "addr:postcode":"08027",
    "addr:street":"Carrer De Bofarull",
    "iso:country":"ES",
    "sg:address":"Carrer de Bofarull, 48",
    "sg:city":"Barcelona",
    "sg:orig_category":"Peluquer\u00cdas, Peluquer\u00cda Mixta",
    "sg:phone":"+34 934 08 29 44",
    "sg:postcode":"08027",
    "sg:province":"Barcelona",
    "wof:name":"Dilla Ferrer Vicente",
    "wof:placetype":"venue"
},
  "geometry": {"coordinates":[2.1890809536,41.4184570312],"type":"Point"}
}