{
  "type": "Feature",
  "properties": {
    "iso:country":"ES",
    "sg:address":"Av Riera, 11",
    "sg:city":"S. Just Desvern",
    "sg:orig_category":"Electricidad: Instaladores",
    "sg:phone":"+34 936 66 21 00",
    "sg:postcode":"08960",
    "sg:province":"Barcelona",
    "sg:website":"www.ingem-aut.com",
    "wof:name":"Ingem Automatizacion S.l.",
    "wof:placetype":"venue"
},
  "geometry": {"coordinates":[2.0599327087,41.382598877],"type":"Point"}
}