{
  "type": "Feature",
  "properties": {
    "iso:country":"ES",
    "sg:address":"Calle de Isaac Albeniz, 34",
    "sg:city":"Ecija",
    "sg:orig_category":"Arquitectos",
    "sg:phone":"+34 954 83 49 06",
    "sg:postcode":"41400",
    "sg:province":"Sevilla",
    "wof:name":"Gonzalez Laguna Francisco Javier",
    "wof:placetype":"venue"
},
  "geometry": {"coordinates":[-5.0911049843,37.5426139832],"type":"Point"}
}