{
  "type": "Feature",
  "properties": {
    "iso:country":"ES",
    "sg:address":"C/ Torres Quevedo, 109",
    "sg:city":"Elche",
    "sg:orig_category":"Transporte En General",
    "sg:phone":"+34 966 63 46 25",
    "sg:postcode":"03204",
    "sg:province":"Alicante",
    "wof:name":"Ramon Ortigosa Asuncion",
    "wof:placetype":"venue"
},
  "geometry": {"coordinates":[-0.7070350051,38.2562904358],"type":"Point"}
}