{
  "type": "Feature",
  "properties": {
    "addr:full":"Carrer de Menta, 5 Reus Tarragona 43206",
    "addr:housenumber":"5",
    "addr:postcode":"43206",
    "addr:street":"Carrer De Menta",
    "iso:country":"ES",
    "sg:address":"Carrer de Menta, 5",
    "sg:city":"Reus",
    "sg:orig_category":"Fabricaci\u00d3n, Distribuci\u00d3n De Material Para La Climatizaci\u00d3n, Aireaci\u00d3n Y Ventilaci\u00d3n",
    "sg:phone":"+34 977 33 26 41",
    "sg:postcode":"43206",
    "sg:province":"Tarragona",
    "wof:name":"Villacorta Ferre Frigoristas S.l.",
    "wof:placetype":"venue"
},
  "geometry": {"coordinates":[1.0943579674,41.1578788757],"type":"Point"}
}