{
  "type": "Feature",
  "properties": {
    "addr:full":"Calle de Korreo Kalea, 12 Tolosa Guip\u00f9zcoa 20400",
    "addr:housenumber":"12",
    "addr:postcode":"20400",
    "addr:street":"Calle De Korreo Kalea;Guipu\u0300Zcoa",
    "iso:country":"ES",
    "sg:address":"Calle de Korreo Kalea, 12",
    "sg:city":"Tolosa",
    "sg:orig_category":"Agencias De Viajes",
    "sg:phone":"+34 943 67 45 66",
    "sg:postcode":"20400",
    "sg:province":"Guip\u00f9zcoa",
    "sg:website":"www.halconviajes.com",
    "wof:name":"Halcon Viajes S.a.",
    "wof:placetype":"venue"
},
  "geometry": {"coordinates":[-2.0733070374,43.1373062134],"type":"Point"}
}