{
  "type": "Feature",
  "properties": {
    "iso:country":"ES",
    "sg:address":"Calle de Guillen De Brocar, 7",
    "sg:city":"Logro\u00f1o",
    "sg:orig_category":"Asociaciones Y Clubs Deportivos",
    "sg:phone":"+34 941 20 27 74",
    "sg:postcode":"26005",
    "sg:province":"La Rioja",
    "wof:name":"Milleniun Srm 04 S.l.",
    "wof:placetype":"venue"
},
  "geometry": {"coordinates":[-2.4599919319,42.46352005],"type":"Point"}
}