{
  "type": "Feature",
  "properties": {
    "addr:full":"Calle de San Pablo, 34 Alacant Alicante 03012",
    "addr:housenumber":"34",
    "addr:postcode":"03012",
    "addr:street":"Calle De San Pablo",
    "iso:country":"ES",
    "sg:address":"Calle de San Pablo, 34",
    "sg:city":"Alacant",
    "sg:orig_category":"Electromec\u00c1nica",
    "sg:phone":"+34 965 24 32 14",
    "sg:postcode":"03012",
    "sg:province":"Alicante",
    "wof:name":"Perez Martinez Miguel",
    "wof:placetype":"venue"
},
  "geometry": {"coordinates":[-0.4780730009,38.3590202332],"type":"Point"}
}