{
  "type": "Feature",
  "properties": {
    "addr:full":"Montero De Espinosa, 3 Almendralejo Badajoz 06200",
    "addr:housenumber":"3",
    "addr:postcode":"06200",
    "iso:country":"ES",
    "sg:address":"Montero De Espinosa, 3",
    "sg:city":"Almendralejo",
    "sg:orig_category":"Abogados",
    "sg:phone":"+34 924 67 09 39",
    "sg:postcode":"06200",
    "sg:province":"Badajoz",
    "wof:name":"Sanchez Benitez Alfonso",
    "wof:placetype":"venue"
},
  "geometry": {"coordinates":[-6.4068241119,38.6845092773],"type":"Point"}
}