{
  "type": "Feature",
  "properties": {
    "iso:country":"ES",
    "sg:address":"Calle de Rio Tajo, 8",
    "sg:city":"Alcorcon",
    "sg:orig_category":"Cl\u00cdnicas Dentales",
    "sg:phone":"+34 916 10 12 30",
    "sg:postcode":"28923",
    "sg:province":"Madrid",
    "wof:name":"Mombiedro Sandoval Rafael",
    "wof:placetype":"venue"
},
  "geometry": {"coordinates":[-3.8154387474,40.3432846069],"type":"Point"}
}