{
  "type": "Feature",
  "properties": {
    "iso:country":"ES",
    "sg:address":"Rua Calvo Sotelo, 1",
    "sg:city":"Quiroga",
    "sg:orig_category":"Empresas De Desmonte",
    "sg:phone":"+34 982 42 10 42",
    "sg:postcode":"27320",
    "sg:province":"Lugo",
    "wof:name":"Excavaciones Hermanos Paris",
    "wof:placetype":"venue"
},
  "geometry": {"coordinates":[-7.2718701363,42.4770736694],"type":"Point"}
}