{
  "type": "Feature",
  "properties": {
    "addr:full":"Avda Europa, 32 Colloto Asturias 33010",
    "addr:housenumber":"32",
    "addr:postcode":"33010",
    "addr:street":"Avda Europa",
    "iso:country":"ES",
    "sg:address":"Avda Europa, 32",
    "sg:city":"Colloto",
    "sg:orig_category":"Restaurantes",
    "sg:phone":"+34 985 79 20 11",
    "sg:postcode":"33010",
    "sg:province":"Asturias",
    "wof:name":"Nachon Pantiga Enrique Julian",
    "wof:placetype":"venue"
},
  "geometry": {"coordinates":[-5.7993540764,43.3772239685],"type":"Point"}
}