{
  "type": "Feature",
  "properties": {
    "addr:full":"Calle de Acero, 14 Valladolid Valladolid 47012",
    "addr:housenumber":"14",
    "addr:postcode":"47012",
    "addr:street":"Calle De Acero",
    "iso:country":"ES",
    "sg:address":"Calle de Acero, 14",
    "sg:city":"Valladolid",
    "sg:orig_category":"Marketing Directo",
    "sg:phone":"+34 983 21 04 89",
    "sg:postcode":"47012",
    "sg:province":"Valladolid",
    "wof:name":"Servicios Postales S.a.",
    "wof:placetype":"venue"
},
  "geometry": {"coordinates":[-4.7062292099,41.6123504639],"type":"Point"}
}