{
  "type": "Feature",
  "properties": {
    "addr:full":"Calle de San Antonio, 45 Belver De Cinca Huesca 22533",
    "addr:housenumber":"45",
    "addr:postcode":"22533",
    "addr:street":"Calle De San Antonio",
    "iso:country":"ES",
    "sg:address":"Calle de San Antonio, 45",
    "sg:city":"Belver De Cinca",
    "sg:orig_category":"Plomeros",
    "sg:phone":"+34 974 46 84 04",
    "sg:postcode":"22533",
    "sg:province":"Huesca",
    "wof:name":"Espurz Blanch Cesar",
    "wof:placetype":"venue"
},
  "geometry": {"coordinates":[0.1768410057,41.6922645569],"type":"Point"}
}