{
  "type": "Feature",
  "properties": {
    "iso:country":"ES",
    "sg:address":"Carrer de Carrasco I Formiguera, 6",
    "sg:city":"Manresa",
    "sg:orig_category":"Alquiler De V\u00cddeo",
    "sg:phone":"+34 938 73 47 46",
    "sg:postcode":"08242",
    "sg:province":"Barcelona",
    "wof:name":"Urbano Perez Juan",
    "wof:placetype":"venue"
},
  "geometry": {"coordinates":[1.8231710196,41.7297592163],"type":"Point"}
}