{
  "type": "Feature",
  "properties": {
    "addr:full":"Calle de Infanta Isabel, 14 Icod De Los Vinos Santa Cruz De Tenerife 38430",
    "addr:housenumber":"14",
    "addr:postcode":"38430",
    "addr:street":"Calle De Infanta Isabel",
    "iso:country":"ES",
    "sg:address":"Calle de Infanta Isabel, 14",
    "sg:city":"Icod De Los Vinos",
    "sg:orig_category":"Asesor\u00cda Sobre Comunicaci\u00d3n De Empresas",
    "sg:phone":"+34 922 12 23 62",
    "sg:postcode":"38430",
    "sg:province":"Santa Cruz De Tenerife",
    "wof:name":"Cooper  Ray",
    "wof:placetype":"venue"
},
  "geometry": {"coordinates":[-16.7175388336,28.3680934906],"type":"Point"}
}