{
  "type": "Feature",
  "properties": {
    "iso:country":"ES",
    "sg:address":"Avda Comuneros, 17",
    "sg:city":"Morales Toro",
    "sg:orig_category":"Bancos",
    "sg:phone":"+34 980 69 82 12",
    "sg:postcode":"49810",
    "sg:province":"Zamora",
    "wof:name":"Caja Rural De Zamora",
    "wof:placetype":"venue"
},
  "geometry": {"coordinates":[-5.3105387688,41.5355224609],"type":"Point"}
}