{
  "type": "Feature",
  "properties": {
    "iso:country":"ES",
    "sg:address":"Avda Puerto, S/n",
    "sg:city":"S. Pedro Pinatar",
    "sg:orig_category":"Promotores Constructores",
    "sg:phone":"+34 968 13 82 52",
    "sg:postcode":"30740",
    "sg:province":"Murcia",
    "wof:name":"Edar San Pedro U.t.e",
    "wof:placetype":"venue"
},
  "geometry": {"coordinates":[-0.7775840163,37.8340835571],"type":"Point"}
}