{
  "type": "Feature",
  "properties": {
    "addr:full":"Calle de Sanchez Abarca, 42 Fuente S. Esteban Salamanca 37200",
    "addr:housenumber":"42",
    "addr:postcode":"37200",
    "addr:street":"Calle De Sanchez Abarca;Fuente S. Esteban",
    "iso:country":"ES",
    "sg:address":"Calle de Sanchez Abarca, 42",
    "sg:city":"Fuente S. Esteban",
    "sg:orig_category":"Peluquer\u00cdas",
    "sg:phone":"+34 923 44 02 54",
    "sg:postcode":"37200",
    "sg:province":"Salamanca",
    "wof:name":"Hernandez Estevez Maria Josefa",
    "wof:placetype":"venue"
},
  "geometry": {"coordinates":[-6.1650328636,40.826171875],"type":"Point"}
}