{
  "type": "Feature",
  "properties": {
    "iso:country":"ES",
    "sg:address":"Riveira De Creo, 1",
    "sg:city":"Ribeira De Creo",
    "sg:orig_category":"M\u00c9dicos: Pediatr\u00cda. Enfermedades De Los Ni\u00d1os",
    "sg:phone":"+34 981 76 30 49",
    "sg:postcode":"15240",
    "sg:province":"La Coru\u00f1a",
    "wof:name":"Rodriguez Fernandez Angel",
    "wof:placetype":"venue"
},
  "geometry": {"coordinates":[-8.9819307327,42.7900466919],"type":"Point"}
}