{
  "type": "Feature",
  "properties": {
    "addr:full":"Trva Puente Virrey, 53 Zaragoza Zaragoza 50007",
    "addr:housenumber":"53",
    "addr:postcode":"50007",
    "addr:street":"Trva Puente Virrey",
    "iso:country":"ES",
    "sg:address":"Trva Puente Virrey, 53",
    "sg:city":"Zaragoza",
    "sg:orig_category":"Molduras, Junquillos, Listones Y Molduras Perforadas",
    "sg:phone":"+34 976 37 77 50",
    "sg:postcode":"50007",
    "sg:province":"Zaragoza",
    "wof:name":"Gomez Perez Andres",
    "wof:placetype":"venue"
},
  "geometry": {"coordinates":[-0.8750870228,41.6351127625],"type":"Point"}
}