{
  "type": "Feature",
  "properties": {
    "addr:full":"Carr Doctor Fleming, 1 Aldaia Valencia 46960",
    "addr:housenumber":"1",
    "addr:postcode":"46960",
    "addr:street":"Carr Doctor Fleming",
    "iso:country":"ES",
    "sg:address":"Carr Doctor Fleming, 1",
    "sg:city":"Aldaia",
    "sg:orig_category":"Molduras, Junquillos, Listones Y Molduras Perforadas",
    "sg:phone":"+34 961 51 70 06",
    "sg:postcode":"46960",
    "sg:province":"Valencia",
    "wof:name":"Hontangas Vazquez Eva",
    "wof:placetype":"venue"
},
  "geometry": {"coordinates":[-0.4673407078,39.4632225037],"type":"Point"}
}