{
  "type": "Feature",
  "properties": {
    "iso:country":"ES",
    "sg:address":"Avda Independencia, 8",
    "sg:city":"Zaragoza",
    "sg:orig_category":"Abogados",
    "sg:phone":"+34 976 23 37 98",
    "sg:postcode":"50004",
    "sg:province":"Zaragoza",
    "wof:name":"Zaraiuris S.l.",
    "wof:placetype":"venue"
},
  "geometry": {"coordinates":[-0.8811250925,41.6517829895],"type":"Point"}
}