{
  "type": "Feature",
  "properties": {
    "addr:full":"Cmno Corte (de La), S/n Alguazas Murcia 30560",
    "addr:postcode":"30560",
    "addr:street":"Cmno Corte De La S / N",
    "iso:country":"ES",
    "sg:address":"Cmno Corte (de La), S/n",
    "sg:city":"Alguazas",
    "sg:orig_category":"Confecci\u00d3n De Cinturones Y De Tirantes",
    "sg:phone":"+34 968 62 00 03",
    "sg:postcode":"30560",
    "sg:province":"Murcia",
    "sg:website":"www.elranchero.es",
    "wof:name":"Perez Campillo Francisco",
    "wof:placetype":"venue"
},
  "geometry": {"coordinates":[-1.2520090342,38.0536766052],"type":"Point"}
}