{
  "type": "Feature",
  "properties": {
    "iso:country":"ES",
    "sg:address":"Gale Vallehermoso, 4",
    "sg:city":"Madrid",
    "sg:orig_category":"Mec\u00c1nico Del Autom\u00d3vil",
    "sg:phone":"+34 915 35 36 16",
    "sg:postcode":"28003",
    "sg:province":"Madrid",
    "wof:name":"Garcia Martinez Enrique",
    "wof:placetype":"venue"
},
  "geometry": {"coordinates":[-3.707914114,40.4393348694],"type":"Point"}
}