{
  "type": "Feature",
  "properties": {
    "addr:full":"Afores, 23 Llan\u00e7a Girona 17490",
    "addr:housenumber":"23",
    "addr:postcode":"17490",
    "addr:street":"Afores",
    "iso:country":"ES",
    "sg:address":"Afores, 23",
    "sg:city":"Llan\u00e7a",
    "sg:orig_category":"Negocio De Materiales De Construcci\u00d3n",
    "sg:phone":"+34 972 12 06 01",
    "sg:postcode":"17490",
    "sg:province":"Girona",
    "wof:name":"Ferros I Acers Corrugats S.l.",
    "wof:placetype":"venue"
},
  "geometry": {"coordinates":[3.1502261162,42.3620529175],"type":"Point"}
}