{
  "type": "Feature",
  "properties": {
    "addr:full":"Calle de Lima (de), 44 Fuenlabrada Madrid 28945",
    "addr:housenumber":"44",
    "addr:postcode":"28945",
    "addr:street":"Calle De Lima De",
    "iso:country":"ES",
    "sg:address":"Calle de Lima (de), 44",
    "sg:city":"Fuenlabrada",
    "sg:orig_category":"Caf\u00c9s, Bares, Cervecer\u00cdas",
    "sg:phone":"+34 916 15 64 14",
    "sg:postcode":"28945",
    "sg:province":"Madrid",
    "wof:name":"Gonzalez Rodriguez Marcelino",
    "wof:placetype":"venue"
},
  "geometry": {"coordinates":[-3.7886838913,40.2916870117],"type":"Point"}
}