{
  "type": "Feature",
  "properties": {
    "addr:full":"Pl Major, 33 Santa Coloma De Queralt Tarragona 43420",
    "addr:housenumber":"33",
    "addr:postcode":"43420",
    "addr:street":"Pl Major",
    "iso:country":"ES",
    "sg:address":"Pl Major, 33",
    "sg:city":"Santa Coloma De Queralt",
    "sg:orig_category":"Agencias Y Agentes Comerciales, Representantes",
    "sg:phone":"+34 977 88 13 43",
    "sg:postcode":"43420",
    "sg:province":"Tarragona",
    "wof:name":"Cases Sendra Maria Teresa",
    "wof:placetype":"venue"
},
  "geometry": {"coordinates":[1.3832240105,41.5318450928],"type":"Point"}
}