{
  "type": "Feature",
  "properties": {
    "addr:full":"Pl Tarrega, S/n Cornella Llobregat Barcelona 08940",
    "addr:housenumber":"s / n",
    "addr:postcode":"08940",
    "addr:street":"Pl Tarrega",
    "iso:country":"ES",
    "sg:address":"Pl Tarrega, S/n",
    "sg:city":"Cornella Llobregat",
    "sg:orig_category":"Organismos De Investigaciones Cient\u00cdficas Y T\u00c9cnicas",
    "sg:phone":"+34 933 75 03 20",
    "sg:postcode":"08940",
    "sg:province":"Barcelona",
    "wof:name":"Pascual Gomez Roberto",
    "wof:placetype":"venue"
},
  "geometry": {"coordinates":[2.0708940029,41.3559417725],"type":"Point"}
}