{
  "type": "Feature",
  "properties": {
    "addr:full":"Avda Reina Sofia, 37 Tobarra Albacete 02500",
    "addr:housenumber":"37",
    "addr:postcode":"02500",
    "addr:street":"Avda Reina Sofia",
    "iso:country":"ES",
    "sg:address":"Avda Reina Sofia, 37",
    "sg:city":"Tobarra",
    "sg:orig_category":"Iglesia Cat\u00d3lica",
    "sg:phone":"+34 967 32 51 90",
    "sg:postcode":"02500",
    "sg:province":"Albacete",
    "wof:name":"Obispado De Albacete",
    "wof:placetype":"venue"
},
  "geometry": {"coordinates":[-1.6871589422,38.5937309265],"type":"Point"}
}