{
  "type": "Feature",
  "properties": {
    "addr:full":"Plaz Emperatriz, 10 Madrid Madrid 28044",
    "addr:housenumber":"10",
    "addr:postcode":"28044",
    "addr:street":"Madrid",
    "iso:country":"ES",
    "sg:address":"Plaz Emperatriz, 10",
    "sg:city":"Madrid",
    "sg:orig_category":"Farmacias",
    "sg:phone":"+34 915 08 53 03",
    "sg:postcode":"28044",
    "sg:province":"Madrid",
    "wof:name":"Llorca Gallego Maria Del Carmen",
    "wof:placetype":"venue"
},
  "geometry": {"coordinates":[-3.751584053,40.3735733032],"type":"Point"}
}