{
  "type": "Feature",
  "properties": {
    "iso:country":"ES",
    "sg:address":"Psaj Pablo Ruiz Picasso, 4",
    "sg:city":"Cadiz",
    "sg:orig_category":"Inform\u00c1tica, Ofim\u00c1tica (estudios, Asesor\u00cda, Ingenier\u00cda, Formaci\u00d3n)",
    "sg:phone":"+34 956 26 07 60",
    "sg:postcode":"11009",
    "sg:province":"C\u00e1diz",
    "wof:name":"Informatizacion Para La Empresa Melgom Sl",
    "wof:placetype":"venue"
},
  "geometry": {"coordinates":[-6.2761387825,36.5091438293],"type":"Point"}
}