{
  "type": "Feature",
  "properties": {
    "iso:country":"ES",
    "sg:address":"Avgd Pais Valencia, 27",
    "sg:city":"Almenara",
    "sg:orig_category":"Inmobiliaria (agencias)",
    "sg:phone":"+34 962 62 48 34",
    "sg:postcode":"12590",
    "sg:province":"Castell\u00f3n",
    "wof:name":"Inmobiliaria Llorens-segarra S.c.p.",
    "wof:placetype":"venue"
},
  "geometry": {"coordinates":[-0.2252819985,39.7522544861],"type":"Point"}
}