{
  "type": "Feature",
  "properties": {
    "iso:country":"ES",
    "sg:address":"Calle de Obispo Varela, 9",
    "sg:city":"Plasencia",
    "sg:orig_category":"Juegos Y Juguetes (al Por Menor)",
    "sg:phone":"+34 927 42 54 29",
    "sg:postcode":"10600",
    "sg:province":"C\u00e1ceres",
    "wof:name":"Hermanas Casado Sarti S.l.",
    "wof:placetype":"venue"
},
  "geometry": {"coordinates":[-6.0832691193,40.0333709717],"type":"Point"}
}