{
  "type": "Feature",
  "properties": {
    "addr:full":"Avda Doctor Artero Guirao, 35 S. Pedro Pinatar Murcia 30740",
    "addr:housenumber":"35",
    "addr:postcode":"30740",
    "addr:street":"Avda Doctor Artero Guirao",
    "iso:country":"ES",
    "sg:address":"Avda Doctor Artero Guirao, 35",
    "sg:city":"S. Pedro Pinatar",
    "sg:orig_category":"Fabricaci\u00d3n De Muebles",
    "sg:phone":"+34 968 18 57 96",
    "sg:postcode":"30740",
    "sg:province":"Murcia",
    "wof:name":"Mu\u00f1oz Murcia Mercedes",
    "wof:placetype":"venue"
},
  "geometry": {"coordinates":[-0.7900819778,37.8377571106],"type":"Point"}
}