{
  "type": "Feature",
  "properties": {
    "iso:country":"ES",
    "sg:address":"Calle de Penitencia, 4",
    "sg:city":"Valladolid",
    "sg:orig_category":"Empresarios Y Productoras De Espect\u00c1culos",
    "sg:phone":"+34 983 26 84 32",
    "sg:postcode":"47011",
    "sg:province":"Valladolid",
    "wof:name":"Delta Producciones S.l.",
    "wof:placetype":"venue"
},
  "geometry": {"coordinates":[-4.7164077759,41.6603050232],"type":"Point"}
}