{
  "type": "Feature",
  "properties": {
    "addr:full":"Carr Jonquet, 38 Pollen\u00e7a Islas Baleares 07460",
    "addr:housenumber":"38",
    "addr:postcode":"07460",
    "addr:street":"Carr Jonquet",
    "iso:country":"ES",
    "sg:address":"Carr Jonquet, 38",
    "sg:city":"Pollen\u00e7a",
    "sg:orig_category":"Comercio, Reparaci\u00d3n De Motocicletas, Bicicletas Y Piezas Sueltas",
    "sg:phone":"+34 971 53 08 53",
    "sg:postcode":"07460",
    "sg:province":"Islas Baleares",
    "wof:name":"Vives Cerda Juan",
    "wof:placetype":"venue"
},
  "geometry": {"coordinates":[3.0176320076,39.8770370483],"type":"Point"}
}