{
  "type": "Feature",
  "properties": {
    "iso:country":"ES",
    "sg:address":"Carrer de Boccacio, S/n",
    "sg:city":"Sabadell",
    "sg:orig_category":"Asociaciones Y Clubs Deportivos",
    "sg:phone":"+34 937 11 20 54",
    "sg:postcode":"08205",
    "sg:province":"Barcelona",
    "wof:name":"O. A. R. Gracia",
    "wof:placetype":"venue"
},
  "geometry": {"coordinates":[2.0969750881,41.5355453491],"type":"Point"}
}