{
  "type": "Feature",
  "properties": {
    "iso:country":"ES",
    "sg:address":"Calle de Doctor Fleming, 3",
    "sg:city":"Calahorra",
    "sg:orig_category":"Florister\u00cdas",
    "sg:phone":"+34 941 13 28 53",
    "sg:postcode":"26500",
    "sg:province":"La Rioja",
    "wof:name":"Gil De Gomez Bermejo Jesus Angel",
    "wof:placetype":"venue"
},
  "geometry": {"coordinates":[-1.9631940126,42.3023529053],"type":"Point"}
}