{
  "type": "Feature",
  "properties": {
    "addr:full":"Calle de Cabanzo, S/n Noja Cantabria 39180",
    "addr:housenumber":"s / n",
    "addr:postcode":"39180",
    "addr:street":"Calle De Cabanzo",
    "iso:country":"ES",
    "sg:address":"Calle de Cabanzo, S/n",
    "sg:city":"Noja",
    "sg:orig_category":"Transporte En General",
    "sg:phone":"+34 942 63 12 74",
    "sg:postcode":"39180",
    "sg:province":"Cantabria",
    "wof:name":"Grupo El Arbol Distribucion Y Supermercados S.a. Unipersonal",
    "wof:placetype":"venue"
},
  "geometry": {"coordinates":[-3.5306529999,43.4762382507],"type":"Point"}
}