{
  "type": "Feature",
  "properties": {
    "addr:full":"Calle de Maya, 7 Badajoz Badajoz 06003",
    "addr:housenumber":"7",
    "addr:postcode":"06003",
    "addr:street":"Calle De Maya",
    "iso:country":"ES",
    "sg:address":"Calle de Maya, 7",
    "sg:city":"Badajoz",
    "sg:orig_category":"Fabricaci\u00d3n De Juguetes Autom\u00c1ticos",
    "sg:phone":"+34 924 25 05 12",
    "sg:postcode":"06003",
    "sg:province":"Badajoz",
    "wof:name":"Operoeste S.a.",
    "wof:placetype":"venue"
},
  "geometry": {"coordinates":[-6.9695291519,38.8700904846],"type":"Point"}
}