{
  "type": "Feature",
  "properties": {
    "addr:full":"Calle de Marbella, 60 Madrid Madrid 28034",
    "addr:housenumber":"60",
    "addr:postcode":"madrid;28034",
    "addr:street":"Calle De Marbella",
    "iso:country":"ES",
    "sg:address":"Calle de Marbella, 60",
    "sg:city":"Madrid",
    "sg:orig_category":"Ense\u00d1anza Superior Privada",
    "sg:phone":"+34 917 35 06 21",
    "sg:postcode":"28034",
    "sg:province":"Madrid",
    "wof:name":"Colegio Mayor Universitario Santillana",
    "wof:placetype":"venue"
},
  "geometry": {"coordinates":[-3.7066969872,40.4952125549],"type":"Point"}
}