{
  "type": "Feature",
  "properties": {
    "addr:full":"Poli Ind. Las Arenas, S/n Malpartida Caceres C\u00e1ceres 10910",
    "addr:housenumber":"s / n",
    "addr:postcode":"10910",
    "addr:street":"Ca\u0301Ceres",
    "iso:country":"ES",
    "sg:address":"Poli Ind. Las Arenas, S/n",
    "sg:city":"Malpartida Caceres",
    "sg:orig_category":"Mec\u00c1nico Del Autom\u00d3vil",
    "sg:phone":"+34 927 27 62 43",
    "sg:postcode":"10910",
    "sg:province":"C\u00e1ceres",
    "wof:name":"Auto-ramos Extreme\u00f1os S.l.",
    "wof:placetype":"venue"
},
  "geometry": {"coordinates":[-6.3707604408,39.4761772156],"type":"Point"}
}