{
  "type": "Feature",
  "properties": {
    "iso:country":"ES",
    "sg:address":"Calle de Jaen, 2",
    "sg:city":"Cabezas S. Juan",
    "sg:orig_category":"Panader\u00cdas, Panader\u00cdas",
    "sg:phone":"+34 955 87 12 13",
    "sg:postcode":"41730",
    "sg:province":"Sevilla",
    "wof:name":"Jimenez Gonzalez Antonio",
    "wof:placetype":"venue"
},
  "geometry": {"coordinates":[-5.935195446,36.9817276001],"type":"Point"}
}