{
  "type": "Feature",
  "properties": {
    "iso:country":"ES",
    "sg:address":"Pase Alameda De Osuna, 50",
    "sg:city":"Madrid",
    "sg:orig_category":"Inform\u00c1tica Equipo Y Programas (al Por Mayor)",
    "sg:phone":"+34 913 20 61 96",
    "sg:postcode":"28042",
    "sg:province":"Madrid",
    "wof:name":"Accesing Future Technologies S.l.",
    "wof:placetype":"venue"
},
  "geometry": {"coordinates":[-3.5957231522,40.4552993774],"type":"Point"}
}