{
  "type": "Feature",
  "properties": {
    "addr:full":"Calle de Francisco Llorens, 18 Catarroja Valencia 46470",
    "addr:housenumber":"18",
    "addr:postcode":"46470",
    "addr:street":"Calle De Francisco Llorens",
    "iso:country":"ES",
    "sg:address":"Calle de Francisco Llorens, 18",
    "sg:city":"Catarroja",
    "sg:orig_category":"Fabricaci\u00d3n De Muebles",
    "sg:phone":"+34 961 26 71 00",
    "sg:postcode":"46470",
    "sg:province":"Valencia",
    "wof:name":"Muebles Catarroja S.l.",
    "wof:placetype":"venue"
},
  "geometry": {"coordinates":[-0.4050309956,39.4016113281],"type":"Point"}
}