{
  "type": "Feature",
  "properties": {
    "iso:country":"ES",
    "sg:address":"Calle de Pilares (los), 19",
    "sg:city":"Agreda",
    "sg:orig_category":"Mudanzas",
    "sg:phone":"+34 976 64 69 43",
    "sg:postcode":"42100",
    "sg:province":"Soria",
    "wof:name":"Rubio Jimenez Rosalina",
    "wof:placetype":"venue"
},
  "geometry": {"coordinates":[-1.9183189869,41.8537597656],"type":"Point"}
}