{
  "type": "Feature",
  "properties": {
    "addr:full":"Ctra Villaviciosa-pinto, Km. 0010,6 Fuenlabrada Madrid 28946",
    "addr:postcode":"28946",
    "addr:street":"Ctra Villaviciosa-Pinto Km. 0010,6",
    "iso:country":"ES",
    "sg:address":"Ctra Villaviciosa-pinto, Km. 0010,6",
    "sg:city":"Fuenlabrada",
    "sg:orig_category":"Peluquer\u00cdas",
    "sg:phone":"+34 916 08 28 84",
    "sg:postcode":"28946",
    "sg:province":"Madrid",
    "wof:name":"Alameda Fuenlabrada S.l.",
    "wof:placetype":"venue"
},
  "geometry": {"coordinates":[-3.7684760094,40.2787055969],"type":"Point"}
}