{
  "type": "Feature",
  "properties": {
    "iso:country":"ES",
    "sg:address":"Calle de Victoriano Perez Vidal, 31",
    "sg:city":"Esfarrapada",
    "sg:orig_category":"Veh\u00cdculos De Ocasi\u00d3n",
    "sg:phone":"+34 986 34 75 40",
    "sg:postcode":"36470",
    "sg:province":"Pontevedra",
    "wof:name":"Fernandez Perez Manuel",
    "wof:placetype":"venue"
},
  "geometry": {"coordinates":[-8.5589160919,42.101108551],"type":"Point"}
}