{
  "type": "Feature",
  "properties": {
    "addr:full":"Carrer de Tarragona, 75 Sabadell Barcelona 08207",
    "addr:housenumber":"75",
    "addr:postcode":"08207",
    "addr:street":"Carrer De Tarragona",
    "iso:country":"ES",
    "sg:address":"Carrer de Tarragona, 75",
    "sg:city":"Sabadell",
    "sg:orig_category":"Electrodom\u00c9sticos (al Por Menor)",
    "sg:phone":"+34 937 16 03 67",
    "sg:postcode":"08207",
    "sg:province":"Barcelona",
    "wof:name":"Bataller Riera Jordi",
    "wof:placetype":"venue"
},
  "geometry": {"coordinates":[2.0898890495,41.5659866333],"type":"Point"}
}