{
  "type": "Feature",
  "properties": {
    "iso:country":"ES",
    "sg:address":"Av Matadepera, 254",
    "sg:city":"Sabadell",
    "sg:orig_category":"Radiocomunicaciones, Telefon\u00cda M\u00d3vil, Radiomensajer\u00cda: Servicios, Comercializaci\u00d3n",
    "sg:phone":"+34 937 17 70 19",
    "sg:postcode":"08207",
    "sg:province":"Barcelona",
    "wof:name":"Erazo Ramirez Carmen Haydee",
    "wof:placetype":"venue"
},
  "geometry": {"coordinates":[2.0832519531,41.5711326599],"type":"Point"}
}