{
  "type": "Feature",
  "properties": {
    "iso:country":"ES",
    "sg:address":"C/ Vicente Fuentes Sansano, 25",
    "sg:city":"Elche",
    "sg:orig_category":"Herboristas (al Por Menor)",
    "sg:phone":"+34 966 67 57 12",
    "sg:postcode":"03205",
    "sg:province":"Alicante",
    "wof:name":"Sanchez Lopez Maria Dolores",
    "wof:placetype":"venue"
},
  "geometry": {"coordinates":[-0.71498698,38.269744873],"type":"Point"}
}