{
  "type": "Feature",
  "properties": {
    "iso:country":"ES",
    "sg:address":"Calle de Due\u00d1as, S/n",
    "sg:city":"Cigales",
    "sg:orig_category":"Escotaduras, Torneados",
    "sg:phone":"+34 983 58 06 78",
    "sg:postcode":"47270",
    "sg:province":"Valladolid",
    "wof:name":"Mecanizados Y Soldaduras Anzama S.l.",
    "wof:placetype":"venue"
},
  "geometry": {"coordinates":[-4.696264267,41.7600250244],"type":"Point"}
}