{
  "type": "Feature",
  "properties": {
    "addr:full":"Plaz San Trokaz, 8 Abadi\u00e7o-zelaieta Vizcaya 48220",
    "addr:housenumber":"8",
    "addr:postcode":"48220",
    "addr:street":"Plaz San Trokaz",
    "iso:country":"ES",
    "sg:address":"Plaz San Trokaz, 8",
    "sg:city":"Abadi\u00e7o-zelaieta",
    "sg:orig_category":"Iglesia Cat\u00d3lica",
    "sg:phone":"+34 946 81 42 69",
    "sg:postcode":"48220",
    "sg:province":"Vizcaya",
    "wof:name":"Parroquia San Torcuato De Abadi\u00f1o",
    "wof:placetype":"venue"
},
  "geometry": {"coordinates":[-2.6077280045,43.1519889832],"type":"Point"}
}