{
  "type": "Feature",
  "properties": {
    "addr:full":"Avda Gasteiz, 90 Vitoria-gasteiz \u00c1lava 01012",
    "addr:housenumber":"90",
    "addr:postcode":"01012",
    "addr:street":"Avda Gasteiz",
    "iso:country":"ES",
    "sg:address":"Avda Gasteiz, 90",
    "sg:city":"Vitoria-gasteiz",
    "sg:orig_category":"Muebles, Minoristas",
    "sg:phone":"+34 945 00 13 73",
    "sg:postcode":"01012",
    "sg:province":"\u00c1lava",
    "wof:name":"Vasmobel, S.a.",
    "wof:placetype":"venue"
},
  "geometry": {"coordinates":[-2.6795730591,42.8543205261],"type":"Point"}
}