{
  "type": "Feature",
  "properties": {
    "iso:country":"ES",
    "sg:address":"Carrer de Gerds (dels), S/n",
    "sg:city":"Poligono Industrial",
    "sg:orig_category":"Aceites Y Grasas Alimentarias (fabricaci\u00d3n, Al Por Mayor)",
    "sg:phone":"+34 937 60 49 10",
    "sg:postcode":"08395",
    "sg:province":"Barcelona",
    "wof:name":"Aceites Millas S. A.",
    "wof:placetype":"venue"
},
  "geometry": {"coordinates":[2.1699187756,41.3879165649],"type":"Point"}
}