{
  "type": "Feature",
  "properties": {
    "iso:country":"ES",
    "sg:address":"Carrer de L'encarnacio, 123",
    "sg:city":"Barcelona",
    "sg:orig_category":"Frutas, Legumbres Frescas Y Tempranas (al Por Menor)",
    "sg:phone":"+34 932 10 34 69",
    "sg:postcode":"08024",
    "sg:province":"Barcelona",
    "wof:name":"Angel Y Alberto Atochero S.c.p.",
    "wof:placetype":"venue"
},
  "geometry": {"coordinates":[2.1635420322,41.4085769653],"type":"Point"}
}