{
  "type": "Feature",
  "properties": {
    "addr:full":"Calle de Simon Benito Boxoyo, S/n Caceres C\u00e1ceres 10004",
    "addr:housenumber":"s",
    "addr:postcode":"10004",
    "addr:street":"Calle De Simon Benito Boxoyo;/ N;Ca\u0301Ceres",
    "iso:country":"ES",
    "sg:address":"Calle de Simon Benito Boxoyo, S/n",
    "sg:city":"Caceres",
    "sg:orig_category":"Alimentaci\u00d3n General (al Por Menor)",
    "sg:phone":"+34 927 18 10 13",
    "sg:postcode":"10004",
    "sg:province":"C\u00e1ceres",
    "wof:name":"Multitiendas La Mejostilla C.b.",
    "wof:placetype":"venue"
},
  "geometry": {"coordinates":[-6.3626790047,39.4929618835],"type":"Point"}
}