{
  "type": "Feature",
  "properties": {
    "iso:country":"ES",
    "sg:address":"Plaz Fray Pedro De La Cruz, 1",
    "sg:city":"Amparo",
    "sg:orig_category":"Supermercados Y Hipermercados",
    "sg:phone":"+34 922 12 13 69",
    "sg:postcode":"38430",
    "sg:province":"Santa Cruz De Tenerife",
    "wof:name":"Hernandez Gonzalez Maria Hilda",
    "wof:placetype":"venue"
},
  "geometry": {"coordinates":[-16.7204761505,28.3677654266],"type":"Point"}
}