{
  "type": "Feature",
  "properties": {
    "iso:country":"ES",
    "sg:address":"Calle de Rio Bravo, 17",
    "sg:city":"Madrid",
    "sg:orig_category":"Marketing Telef\u00d3nico",
    "sg:phone":"+34 913 80 66 72",
    "sg:postcode":"28018",
    "sg:province":"Madrid",
    "wof:name":"Merchanwar Sl",
    "wof:placetype":"venue"
},
  "geometry": {"coordinates":[-3.6518468857,40.3872032166],"type":"Point"}
}