{
  "type": "Feature",
  "properties": {
    "iso:country":"ES",
    "sg:address":"Calle de Obispo Cobos, 22",
    "sg:city":"Ubeda",
    "sg:orig_category":"Fabricaci\u00d3n, Distribuci\u00d3n De Discos, V\u00cddeodiscos Y Musicassettes",
    "sg:phone":"+34 953 79 07 28",
    "sg:postcode":"23400",
    "sg:province":"Ja\u00e9n",
    "wof:name":"Ruiz Garcia Manuel",
    "wof:placetype":"venue"
},
  "geometry": {"coordinates":[-3.3760390282,38.011390686],"type":"Point"}
}