{
  "type": "Feature",
  "properties": {
    "iso:country":"ES",
    "sg:address":"Avda Constitucion, 9",
    "sg:city":"San Miguel",
    "sg:orig_category":"Ropa Para Se\u00d1oras (al Por Menor)",
    "sg:phone":"+34 968 24 73 68",
    "sg:postcode":"30008",
    "sg:province":"Murcia",
    "wof:name":"Granseti S.l.",
    "wof:placetype":"venue"
},
  "geometry": {"coordinates":[-1.1313459873,37.9907684326],"type":"Point"}
}