{
  "type": "Feature",
  "properties": {
    "addr:full":"Calle de Juan De Zu\u00d1iga, 123 Argamasilla Alba Ciudad Real 13710",
    "addr:housenumber":"123",
    "addr:postcode":"alba;13710",
    "addr:street":"Calle De Juan De Zun\u0303Iga",
    "iso:country":"ES",
    "sg:address":"Calle de Juan De Zu\u00d1iga, 123",
    "sg:city":"Argamasilla Alba",
    "sg:orig_category":"Mec\u00c1nico Del Autom\u00d3vil",
    "sg:phone":"+34 926 52 17 91",
    "sg:postcode":"13710",
    "sg:province":"Ciudad Real",
    "wof:name":"Talleres Borreguero Casarrubios S.%.",
    "wof:placetype":"venue"
},
  "geometry": {"coordinates":[-3.0829439163,39.1299705505],"type":"Point"}
}