{
  "type": "Feature",
  "properties": {
    "iso:country":"ES",
    "sg:address":"Calle de Antonio Machado, 21",
    "sg:city":"Tudela Duero",
    "sg:orig_category":"Librer\u00cdas",
    "sg:phone":"+34 983 52 15 30",
    "sg:postcode":"47320",
    "sg:province":"Valladolid",
    "wof:name":"Lobo Garcia Blanca",
    "wof:placetype":"venue"
},
  "geometry": {"coordinates":[-4.5817956924,41.5857429504],"type":"Point"}
}