{
  "type": "Feature",
  "properties": {
    "iso:country":"ES",
    "sg:address":"Calle de Ramon J. Sender, 8",
    "sg:city":"Alca\u00f1iz",
    "sg:orig_category":"Peluquer\u00cdas, Peluquer\u00cda Mixta",
    "sg:phone":"+34 978 83 03 21",
    "sg:postcode":"44600",
    "sg:province":"Teruel",
    "wof:name":"Insa Gil Ana Maria",
    "wof:placetype":"venue"
},
  "geometry": {"coordinates":[-0.1285450011,41.0509796143],"type":"Point"}
}