{
  "type": "Feature",
  "properties": {
    "iso:country":"ES",
    "sg:address":"Calle de Juan Hurtado De Mendoza, 9",
    "sg:city":"Madrid",
    "sg:orig_category":"M\u00c9dicos: Estomatolog\u00cda",
    "sg:phone":"+34 913 50 66 79",
    "sg:postcode":"28036",
    "sg:province":"Madrid",
    "wof:name":"Orozco Zea Juan Guillermo",
    "wof:placetype":"venue"
},
  "geometry": {"coordinates":[-3.6876070499,40.4605751038],"type":"Point"}
}