{
  "type": "Feature",
  "properties": {
    "addr:full":"Calle de Padre Claret, 17 Madrid Madrid 28002",
    "addr:housenumber":"17",
    "addr:postcode":"madrid;28002",
    "addr:street":"Calle De Padre Claret",
    "iso:country":"ES",
    "sg:address":"Calle de Padre Claret, 17",
    "sg:city":"Madrid",
    "sg:orig_category":"Mayoristas E Intermediarios En Alcoholes",
    "sg:phone":"+34 914 13 58 34",
    "sg:postcode":"28002",
    "sg:province":"Madrid",
    "wof:name":"Casta\u00f1eda Casanova Ricardo",
    "wof:placetype":"venue"
},
  "geometry": {"coordinates":[-3.6643180847,40.4480705261],"type":"Point"}
}