{
  "type": "Feature",
  "properties": {
    "addr:full":"Calle de Avelino Fernandez De La Poza, 6 Madrid Madrid 28053",
    "addr:housenumber":"6",
    "addr:postcode":"28053",
    "addr:street":"Calle De Avelino Fernandez De La Poza",
    "iso:country":"ES",
    "sg:address":"Calle de Avelino Fernandez De La Poza, 6",
    "sg:city":"Madrid",
    "sg:orig_category":"Inmobiliaria (agencias)",
    "sg:phone":"+34 915 00 80 17",
    "sg:postcode":"28053",
    "sg:province":"Madrid",
    "sg:website":"www.alfainmo.com/entrevias",
    "wof:name":"La Vi\u00f1a 21 Inmuebles S.l.",
    "wof:placetype":"venue"
},
  "geometry": {"coordinates":[-3.6731367111,40.3845024109],"type":"Point"}
}