{
  "type": "Feature",
  "properties": {
    "iso:country":"ES",
    "sg:address":"Calle de Napoles, 2",
    "sg:city":"Leganes",
    "sg:orig_category":"M\u00c9dicos: Medicina General Orientada A La Acupuntura",
    "sg:phone":"+34 916 80 14 23",
    "sg:postcode":"28912",
    "sg:province":"Madrid",
    "wof:name":"Lee Ma Sook Hiy",
    "wof:placetype":"venue"
},
  "geometry": {"coordinates":[-3.7638170719,40.3305511475],"type":"Point"}
}