{
  "type": "Feature",
  "properties": {
    "iso:country":"ES",
    "sg:address":"General, S/n",
    "sg:city":"Mendivil",
    "sg:orig_category":"Reciclaje, Tratamiento De Desechos Varios",
    "sg:phone":"+34 948 72 02 79",
    "sg:postcode":"31395",
    "sg:province":"Navarra",
    "wof:name":"Mendipal S.l.",
    "wof:placetype":"venue"
},
  "geometry": {"coordinates":[-1.6455440521,42.6051712036],"type":"Point"}
}