{
  "type": "Feature",
  "properties": {
    "addr:full":"Avda Portugal (de), 31 Avila \u00c1vila 05001",
    "addr:housenumber":"31",
    "addr:postcode":"05001",
    "addr:street":"Avda Portugal De;A\u0301Vila",
    "iso:country":"ES",
    "sg:address":"Avda Portugal (de), 31",
    "sg:city":"Avila",
    "sg:orig_category":"Ense\u00d1anza: Profesiones Art\u00cdsticas",
    "sg:phone":"+34 920 21 19 79",
    "sg:postcode":"05001",
    "sg:province":"\u00c1vila",
    "wof:name":"Esgueva Collado Jesus",
    "wof:placetype":"venue"
},
  "geometry": {"coordinates":[-4.6924409866,40.6576004028],"type":"Point"}
}