{
  "type": "Feature",
  "properties": {
    "addr:full":"Avda Mari\u00d1as, Km. 0599,0 Perillo A Coru\u00f1a 15172",
    "addr:postcode":"15172",
    "addr:street":"Avda Marin\u0303As Km. 0599,0 Perillo A Corun\u0303A",
    "iso:country":"ES",
    "sg:address":"Avda Mari\u00d1as, Km. 0599,0",
    "sg:city":"Perillo",
    "sg:orig_category":"Venta, Montaje De Neum\u00c1ticos",
    "sg:phone":"+34 981 63 51 54",
    "sg:postcode":"15172",
    "sg:province":"A Coru\u00f1a",
    "wof:name":"Ximenez Y Cia S.a.",
    "wof:placetype":"venue"
},
  "geometry": {"coordinates":[-8.3694000244,43.3298568726],"type":"Point"}
}