{
  "type": "Feature",
  "properties": {
    "iso:country":"ES",
    "sg:address":"Carr Benet Julia, 24",
    "sg:city":"Torroella Montgri",
    "sg:orig_category":"Doctores En Medicina",
    "sg:phone":"+34 972 76 14 61",
    "sg:postcode":"17257",
    "sg:province":"Girona",
    "wof:name":"Saenz Berbejillo Juan Carlos",
    "wof:placetype":"venue"
},
  "geometry": {"coordinates":[3.1034500599,42.0303268433],"type":"Point"}
}