{
  "type": "Feature",
  "properties": {
    "iso:country":"ES",
    "sg:address":"Trv Ancha, S/n",
    "sg:city":"Yeste",
    "sg:orig_category":"Charcuter\u00cdas (al Por Mayor)",
    "sg:phone":"+34 967 43 20 23",
    "sg:postcode":"02480",
    "sg:province":"Albacete",
    "wof:name":"Martinez Simon Jose Luis",
    "wof:placetype":"venue"
},
  "geometry": {"coordinates":[-2.3224990368,38.3649749756],"type":"Point"}
}