{
  "type": "Feature",
  "properties": {
    "iso:country":"ES",
    "sg:address":"Rincon De Loix, S/n",
    "sg:city":"Benidorm",
    "sg:orig_category":"Regalos, Souvenires (fabricaci\u00d3n, Al Por Mayor)",
    "sg:phone":"+34 965 85 51 28",
    "sg:postcode":"03500",
    "sg:province":"Alicante",
    "wof:name":"Oca\u00f1a Casero Antonio",
    "wof:placetype":"venue"
},
  "geometry": {"coordinates":[-0.0913219973,38.5457992554],"type":"Point"}
}