{
  "type": "Feature",
  "properties": {
    "iso:country":"ES",
    "sg:address":"Carrer de Sant Jaume, 44",
    "sg:city":"Granollers",
    "sg:orig_category":"Abogados",
    "sg:phone":"+34 938 70 65 67",
    "sg:postcode":"08401",
    "sg:province":"Barcelona",
    "wof:name":"Qu4tre Associats S.c.p.",
    "wof:placetype":"venue"
},
  "geometry": {"coordinates":[2.2855188847,41.6075401306],"type":"Point"}
}