{
  "type": "Feature",
  "properties": {
    "addr:full":"Av Ponent, 25 Hospitalet Llobregat Barcelona 08905",
    "addr:housenumber":"25",
    "addr:postcode":"08905",
    "addr:street":"Av Ponent",
    "iso:country":"ES",
    "sg:address":"Av Ponent, 25",
    "sg:city":"Hospitalet Llobregat",
    "sg:orig_category":"Papeler\u00cdas, Librer\u00cdas",
    "sg:phone":"+34 934 48 06 61",
    "sg:postcode":"08905",
    "sg:province":"Barcelona",
    "wof:name":"Cubel Gil Carmen",
    "wof:placetype":"venue"
},
  "geometry": {"coordinates":[2.1144840717,41.3691825867],"type":"Point"}
}