{
  "type": "Feature",
  "properties": {
    "addr:full":"Calle de Calibre, 66 Estacion Madrid 28400",
    "addr:housenumber":"66",
    "addr:postcode":"28400",
    "addr:street":"Calle De Calibre",
    "iso:country":"ES",
    "sg:address":"Calle de Calibre, 66",
    "sg:city":"Estacion",
    "sg:orig_category":"Artes Gr\u00c1ficas, Artes Pl\u00c1sticas (curso)",
    "sg:phone":"+34 918 50 05 78",
    "sg:postcode":"28400",
    "sg:province":"Madrid",
    "wof:name":"Graficas Calatrava S. L.",
    "wof:placetype":"venue"
},
  "geometry": {"coordinates":[-3.7003455162,40.4166908264],"type":"Point"}
}