{
  "type": "Feature",
  "properties": {
    "addr:full":"Rua Parque De San Lazaro, 11 Ourense Ourense 32003",
    "addr:housenumber":"11",
    "addr:postcode":"32003",
    "addr:street":"Rua Parque De San Lazaro",
    "iso:country":"ES",
    "sg:address":"Rua Parque De San Lazaro, 11",
    "sg:city":"Ourense",
    "sg:orig_category":"Abogados",
    "sg:phone":"+34 988 23 28 27",
    "sg:postcode":"32003",
    "sg:province":"Ourense",
    "wof:name":"Abelairas Portome\u00f1e Jose",
    "wof:placetype":"venue"
},
  "geometry": {"coordinates":[-7.863888,42.340981],"type":"Point"}
}