{
  "type": "Feature",
  "properties": {
    "addr:full":"Calle de Lopez De Hoyos, 142 Madrid Madrid 28002",
    "addr:housenumber":"142",
    "addr:postcode":"28002",
    "addr:street":"Calle De Lopez De Hoyos",
    "iso:country":"ES",
    "sg:address":"Calle de Lopez De Hoyos, 142",
    "sg:city":"Madrid",
    "sg:orig_category":"Agentes De Seguros",
    "sg:phone":"+34 914 13 87 63",
    "sg:postcode":"28002",
    "sg:province":"Madrid",
    "wof:name":"Moreno De Alaiz S.l.",
    "wof:placetype":"venue"
},
  "geometry": {"coordinates":[-3.6722109318,40.4452438354],"type":"Point"}
}