{
  "type": "Feature",
  "properties": {
    "addr:full":"Calle de Trascorrales, S/n Cervatos De La Cueza Palencia 34308",
    "addr:housenumber":"s / n",
    "addr:postcode":"34308",
    "addr:street":"Calle De Trascorrales",
    "iso:country":"ES",
    "sg:address":"Calle de Trascorrales, S/n",
    "sg:city":"Cervatos De La Cueza",
    "sg:orig_category":"Iglesia Cat\u00d3lica",
    "sg:phone":"+34 979 88 30 18",
    "sg:postcode":"34308",
    "sg:province":"Palencia",
    "wof:name":"Parroquia De San Miguel Y Santa Columba",
    "wof:placetype":"venue"
},
  "geometry": {"coordinates":[-4.7722392082,42.2890586853],"type":"Point"}
}