{
  "type": "Feature",
  "properties": {
    "addr:full":"Carrer de Joaquim Rubio I Ors, 50 S. Boi Llobregat Barcelona 08830",
    "addr:housenumber":"50",
    "addr:postcode":"08830",
    "addr:street":"Carrer De Joaquim Rubio;Ors",
    "iso:country":"ES",
    "sg:address":"Carrer de Joaquim Rubio I Ors, 50",
    "sg:city":"S. Boi Llobregat",
    "sg:orig_category":"Farmacias",
    "sg:phone":"+34 936 54 28 81",
    "sg:postcode":"08830",
    "sg:province":"Barcelona",
    "wof:name":"Gabarro Ballesteros Rosa Maria",
    "wof:placetype":"venue"
},
  "geometry": {"coordinates":[2.0286159515,41.3503303528],"type":"Point"}
}