{
  "type": "Feature",
  "properties": {
    "iso:country":"ES",
    "sg:address":"Cmno Lekubaso, 3",
    "sg:city":"Usansolo",
    "sg:orig_category":"Rectificaci\u00d3n, Mecanizado, Fresado",
    "sg:phone":"+34 944 56 13 36",
    "sg:postcode":"48960",
    "sg:province":"Vizcaya",
    "wof:name":"Larrinoa Goti Fidel",
    "wof:placetype":"venue"
},
  "geometry": {"coordinates":[-2.8204469681,43.2165222168],"type":"Point"}
}