{
  "type": "Feature",
  "properties": {
    "iso:country":"ES",
    "sg:address":"Franco(pol Atalayas), 2",
    "sg:city":"Alacant",
    "sg:orig_category":"Lecher\u00cdas",
    "sg:phone":"+34 965 10 62 88",
    "sg:postcode":"03006",
    "sg:province":"Alicante",
    "wof:name":"Leche Pascual S.a.",
    "wof:placetype":"venue"
},
  "geometry": {"coordinates":[-0.5655009747,38.3430404663],"type":"Point"}
}