{
  "type": "Feature",
  "properties": {
    "addr:full":"Calle de Corregidor Pueyo, 8 Vista Alegre Murcia 30007",
    "addr:housenumber":"8",
    "addr:postcode":"30007",
    "addr:street":"Calle De Corregidor Pueyo",
    "iso:country":"ES",
    "sg:address":"Calle de Corregidor Pueyo, 8",
    "sg:city":"Vista Alegre",
    "sg:orig_category":"Electrodom\u00c9sticos (al Por Menor)",
    "sg:phone":"+34 968 23 06 12",
    "sg:postcode":"30007",
    "sg:province":"Murcia",
    "wof:name":"Martinez Gonzalez Jose Manuel",
    "wof:placetype":"venue"
},
  "geometry": {"coordinates":[-1.1298867464,37.9834747314],"type":"Point"}
}