{
  "type": "Feature",
  "properties": {
    "addr:full":"Avda Antonio Hernandez Gil, 52 Badajoz Badajoz 06009",
    "addr:housenumber":"52",
    "addr:postcode":"06009",
    "addr:street":"Avda Antonio Hernandez Gil",
    "iso:country":"ES",
    "sg:address":"Avda Antonio Hernandez Gil, 52",
    "sg:city":"Badajoz",
    "sg:orig_category":"Ense\u00d1anza, Formaci\u00d3n Profesional: Aprendizaje",
    "sg:phone":"+34 924 26 29 29",
    "sg:postcode":"06009",
    "sg:province":"Badajoz",
    "wof:name":"Pe\u00f1as Hurtado Antonio",
    "wof:placetype":"venue"
},
  "geometry": {"coordinates":[-6.9555139542,38.8710594177],"type":"Point"}
}