{
  "type": "Feature",
  "properties": {
    "addr:full":"Mercado, 2 Callosa Segura Alicante 03360",
    "addr:housenumber":"2",
    "addr:postcode":"03360",
    "addr:street":"Mercado",
    "iso:country":"ES",
    "sg:address":"Mercado, 2",
    "sg:city":"Callosa Segura",
    "sg:orig_category":"Frutas Y Legumbres Frescas (al Por Mayor)",
    "sg:phone":"+34 965 31 09 75",
    "sg:postcode":"03360",
    "sg:province":"Alicante",
    "wof:name":"Medives Hortofruits S.l.",
    "wof:placetype":"venue"
},
  "geometry": {"coordinates":[-0.8776689768,38.1256752014],"type":"Point"}
}