{
  "type": "Feature",
  "properties": {
    "addr:full":"Calle de Soria, 3 Torrejoncillo Rey Cuenca 16161",
    "addr:housenumber":"3",
    "addr:postcode":"16161",
    "addr:street":"Calle De Soria;Rey",
    "iso:country":"ES",
    "sg:address":"Calle de Soria, 3",
    "sg:city":"Torrejoncillo Rey",
    "sg:orig_category":"Empresarios",
    "sg:phone":"+34 969 27 80 70",
    "sg:postcode":"16161",
    "sg:province":"Cuenca",
    "wof:name":"Garcia Cubillo Pedro",
    "wof:placetype":"venue"
},
  "geometry": {"coordinates":[-2.5738649368,40.0075569153],"type":"Point"}
}