{
  "type": "Feature",
  "properties": {
    "addr:full":"Carrer de Pere Ii, 42 Palma Islas Baleares 07007",
    "addr:housenumber":"42",
    "addr:postcode":"07007",
    "addr:street":"Carrer De Pere Ii",
    "iso:country":"ES",
    "sg:address":"Carrer de Pere Ii, 42",
    "sg:city":"Palma",
    "sg:orig_category":"Internados & Ense\u00d1anza Privada",
    "sg:phone":"+34 971 24 82 53",
    "sg:postcode":"07007",
    "sg:province":"Islas Baleares",
    "wof:name":"C.e. Col.legi Balmes S.l.",
    "wof:placetype":"venue"
},
  "geometry": {"coordinates":[2.6694860458,39.571849823],"type":"Point"}
}