{
  "type": "Feature",
  "properties": {
    "iso:country":"ES",
    "sg:address":"Carrer de Corsega, 184",
    "sg:city":"Barcelona",
    "sg:orig_category":"Caf\u00c9s, Bares, Cervecer\u00cdas",
    "sg:phone":"+34 934 19 07 16",
    "sg:postcode":"08036",
    "sg:province":"Barcelona",
    "wof:name":"Mollete S.l.",
    "wof:placetype":"venue"
},
  "geometry": {"coordinates":[2.1505188942,41.389705658],"type":"Point"}
}