{
  "type": "Feature",
  "properties": {
    "iso:country":"ES",
    "sg:address":"Carrer de Mossen Antoni Solanas, 103",
    "sg:city":"S. Boi Llobregat",
    "sg:orig_category":"Empresas De Carpinter\u00cda",
    "sg:phone":"+34 936 52 05 55",
    "sg:postcode":"08830",
    "sg:province":"Barcelona",
    "wof:name":"Ortega Liasid Francisco",
    "wof:placetype":"venue"
},
  "geometry": {"coordinates":[2.0412669182,41.3353996277],"type":"Point"}
}