{
  "type": "Feature",
  "properties": {
    "addr:full":"Calle de Castilla, 6 Donostia-san Sebastian Guip\u00f9zcoa 20015",
    "addr:housenumber":"6",
    "addr:postcode":"20015",
    "addr:street":"Calle De Castilla",
    "iso:country":"ES",
    "sg:address":"Calle de Castilla, 6",
    "sg:city":"Donostia-san Sebastian",
    "sg:orig_category":"Promotores Constructores",
    "sg:phone":"+34 943 29 28 02",
    "sg:postcode":"20015",
    "sg:province":"Guip\u00f9zcoa",
    "wof:name":"Zelata, S.l.",
    "wof:placetype":"venue"
},
  "geometry": {"coordinates":[-1.9556419849,43.3131484985],"type":"Point"}
}