{
  "type": "Feature",
  "properties": {
    "iso:country":"ES",
    "sg:address":"Calle de Ramon Y Cajal, 72",
    "sg:city":"Llanos Alba",
    "sg:orig_category":"Empresas De Carpinter\u00cda Met\u00c1lica",
    "sg:phone":"+34 987 57 11 92",
    "sg:postcode":"24649",
    "sg:province":"Le\u00f3n",
    "wof:name":"Martinez Garcia Alberto",
    "wof:placetype":"venue"
},
  "geometry": {"coordinates":[-5.6433639526,42.805519104],"type":"Point"}
}