{
  "type": "Feature",
  "properties": {
    "addr:full":"Calle de Minerva, 85 Madrid Madrid 28032",
    "addr:housenumber":"85",
    "addr:postcode":"madrid;28032",
    "addr:street":"Calle De Minerva",
    "iso:country":"ES",
    "sg:address":"Calle de Minerva, 85",
    "sg:city":"Madrid",
    "sg:orig_category":"Alquiler De V\u00cddeo",
    "sg:phone":"+34 913 71 83 33",
    "sg:postcode":"28032",
    "sg:province":"Madrid",
    "wof:name":"Djd Video Take Away S.l.",
    "wof:placetype":"venue"
},
  "geometry": {"coordinates":[-3.6051769257,40.397102356],"type":"Point"}
}