{
  "type": "Feature",
  "properties": {
    "addr:full":"Av Pais Valencia, 14 Alcoi Alicante 03801",
    "addr:housenumber":"14",
    "addr:postcode":"03801",
    "addr:street":"Av Pais Valencia",
    "iso:country":"ES",
    "sg:address":"Av Pais Valencia, 14",
    "sg:city":"Alcoi",
    "sg:orig_category":"Centros De Coordinaci\u00d3n",
    "sg:phone":"+34 965 54 03 80",
    "sg:postcode":"03801",
    "sg:province":"Alicante",
    "wof:name":"Sorolla Garcia Jaime",
    "wof:placetype":"venue"
},
  "geometry": {"coordinates":[-0.4756970108,38.6973495483],"type":"Point"}
}