{
  "type": "Feature",
  "properties": {
    "addr:full":"Carrer de Fastenrath, 12 Barcelona Barcelona 08035",
    "addr:housenumber":"12",
    "addr:postcode":"08035",
    "addr:street":"Carrer De Fastenrath",
    "iso:country":"ES",
    "sg:address":"Carrer de Fastenrath, 12",
    "sg:city":"Barcelona",
    "sg:orig_category":"Edici\u00d3n De Diarios, Revistas, Boletines",
    "sg:phone":"+34 934 17 38 76",
    "sg:postcode":"08035",
    "sg:province":"Barcelona",
    "wof:name":"Amvf Espa\u00f1a S.l.",
    "wof:placetype":"venue"
},
  "geometry": {"coordinates":[2.1431159973,41.4216003418],"type":"Point"}
}