{
  "type": "Feature",
  "properties": {
    "iso:country":"ES",
    "sg:address":"Avda Maria Auxiliadora, 10",
    "sg:city":"Badajoz",
    "sg:orig_category":"Institutos De Belleza",
    "sg:phone":"+34 924 24 47 12",
    "sg:postcode":"06011",
    "sg:province":"Badajoz",
    "wof:name":"Gragera Moreno Maria Francisca",
    "wof:placetype":"venue"
},
  "geometry": {"coordinates":[-6.9795298576,38.8688545227],"type":"Point"}
}