{
  "type": "Feature",
  "properties": {
    "addr:full":"Pg Fabra I Puig, 125 Barcelona Barcelona 08016",
    "addr:housenumber":"125",
    "addr:postcode":"08016",
    "addr:street":"Pg Fabra I Puig",
    "iso:country":"ES",
    "sg:address":"Pg Fabra I Puig, 125",
    "sg:city":"Barcelona",
    "sg:orig_category":"Empresas De Carpinter\u00cda Met\u00c1lica",
    "sg:phone":"+34 933 12 03 53",
    "sg:postcode":"08016",
    "sg:province":"Barcelona",
    "sg:website":"www.hnos-almansa.net",
    "wof:name":"Montajes Almansa S.l.",
    "wof:placetype":"venue"
},
  "geometry": {"coordinates":[2.1810510159,41.430103302],"type":"Point"}
}