{
  "type": "Feature",
  "properties": {
    "addr:full":"Ctra. Aeropuerto, Km. 0001,7 Zaragoza Zaragoza 50011",
    "addr:postcode":"50011",
    "addr:street":"Ctra. Aeropuerto Km. 0001,7",
    "iso:country":"ES",
    "sg:address":"Ctra. Aeropuerto, Km. 0001,7",
    "sg:city":"Zaragoza",
    "sg:orig_category":"Reciclaje, Desguace De Veh\u00cdculos",
    "sg:phone":"+34 976 32 40 74",
    "sg:postcode":"50011",
    "sg:province":"Zaragoza",
    "wof:name":"Martinez Pinilla Pablo Jesus",
    "wof:placetype":"venue"
},
  "geometry": {"coordinates":[-0.9387440085,41.6622886658],"type":"Point"}
}