{
  "type": "Feature",
  "properties": {
    "addr:full":"Calle de Cartero German, 10 Santurtzi Vizcaya 48980",
    "addr:housenumber":"10",
    "addr:postcode":"48980",
    "addr:street":"Calle De Cartero German",
    "iso:country":"ES",
    "sg:address":"Calle de Cartero German, 10",
    "sg:city":"Santurtzi",
    "sg:orig_category":"Fabricaci\u00d3n De Juegos Y Juguetes",
    "sg:phone":"+34 944 61 03 60",
    "sg:postcode":"48980",
    "sg:province":"Vizcaya",
    "wof:name":"Juguetes Y Puericultura Seyma S.l.",
    "wof:placetype":"venue"
},
  "geometry": {"coordinates":[-3.0352790356,43.3280639648],"type":"Point"}
}