{
  "type": "Feature",
  "properties": {
    "addr:full":"Nubledo, S/n Cancienes Asturias 33416",
    "addr:postcode":"33416",
    "addr:street":"Nubledo S / N Cancienes Asturias",
    "iso:country":"ES",
    "sg:address":"Nubledo, S/n",
    "sg:city":"Cancienes",
    "sg:classifiers":[
        {
            "category":"Manufacturing",
            "subcategory":"Metals",
            "type":"Manufacturing & Wholesale Goods"
        }
    ],
    "sg:phone":"+34 985 50 52 28",
    "sg:postcode":"33416",
    "sg:province":"Asturias",
    "sg:tags":[
        "en",
        "fundiciones"
    ],
    "sg:website":"www.hiasa.es",
    "wof:name":"Hierros Y Aplanaciones S. A.",
    "wof:placetype":"venue"
},
  "geometry": {"coordinates":[-5.9928798676,43.5280570984],"type":"Point"}
}