{
  "type": "Feature",
  "properties": {
    "addr:full":"Calle de Rodriguez San Pedro, 54 Madrid Madrid 28015",
    "addr:housenumber":"54",
    "addr:postcode":"madrid;28015",
    "addr:street":"Calle De Rodriguez San Pedro",
    "iso:country":"ES",
    "sg:address":"Calle de Rodriguez San Pedro, 54",
    "sg:city":"Madrid",
    "sg:orig_category":"Panader\u00cdas, Panader\u00cdas",
    "sg:phone":"+34 915 43 84 52",
    "sg:postcode":"28015",
    "sg:province":"Madrid",
    "wof:name":"Boix Larraya Vicente",
    "wof:placetype":"venue"
},
  "geometry": {"coordinates":[-3.7140860558,40.4319496155],"type":"Point"}
}