{
  "type": "Feature",
  "properties": {
    "addr:full":"Calle de San Miguel, 10 Jerez De La Frontera C\u00e1diz 11403",
    "addr:housenumber":"10",
    "addr:postcode":"11403",
    "addr:street":"Calle De San Miguel",
    "iso:country":"ES",
    "sg:address":"Calle de San Miguel, 10",
    "sg:city":"Jerez De La Frontera",
    "sg:orig_category":"Fisioterapia",
    "sg:phone":"+34 956 33 13 59",
    "sg:postcode":"11403",
    "sg:province":"C\u00e1diz",
    "wof:name":"Servicio Andaluz De Salud",
    "wof:placetype":"venue"
},
  "geometry": {"coordinates":[-6.1374850273,36.6806526184],"type":"Point"}
}