{
  "type": "Feature",
  "properties": {
    "addr:full":"Ezponda, S/n Huarte Navarra 31620",
    "addr:housenumber":"/ n",
    "addr:postcode":"31620",
    "addr:street":"Ezponda S;Navarra",
    "iso:country":"ES",
    "sg:address":"Ezponda, S/n",
    "sg:city":"Huarte",
    "sg:orig_category":"Metales (labores, Pulido)",
    "sg:phone":"+34 948 33 33 27",
    "sg:postcode":"31620",
    "sg:province":"Navarra",
    "wof:name":"Estampaciones Arsan S.l.",
    "wof:placetype":"venue"
},
  "geometry": {"coordinates":[-1.6036440134,42.8262634277],"type":"Point"}
}