{
  "type": "Feature",
  "properties": {
    "addr:full":"Calle de Duque De Alba, 11 Avila \u00c1vila 05001",
    "addr:housenumber":"11",
    "addr:postcode":"05001",
    "addr:street":"Calle De Duque De Alba;A\u0301Vila",
    "iso:country":"ES",
    "sg:address":"Calle de Duque De Alba, 11",
    "sg:city":"Avila",
    "sg:orig_category":"Molduras, Junquillos, Listones Y Molduras Perforadas",
    "sg:phone":"+34 920 25 74 34",
    "sg:postcode":"05001",
    "sg:province":"\u00c1vila",
    "wof:name":"Sistelcom-telemensaje S.a.",
    "wof:placetype":"venue"
},
  "geometry": {"coordinates":[-4.6925940514,40.6556015015],"type":"Point"}
}