{
  "type": "Feature",
  "properties": {
    "iso:country":"ES",
    "sg:address":"Carr Aigua, 29",
    "sg:city":"Vilanova I La Geltru",
    "sg:orig_category":"Asociaciones, Organismos Culturales Y Socioeducativos",
    "sg:phone":"+34 938 93 12 05",
    "sg:postcode":"08800",
    "sg:province":"Barcelona",
    "wof:name":"Asociacion Recreativa La Gresca",
    "wof:placetype":"venue"
},
  "geometry": {"coordinates":[1.7223200798,41.2254638672],"type":"Point"}
}