{
  "type": "Feature",
  "properties": {
    "iso:country":"ES",
    "sg:address":"Calle de Jose Luis Mesias Iglesias, 24",
    "sg:city":"Almendralejo",
    "sg:orig_category":"Molduras, Junquillos, Listones Y Molduras Perforadas",
    "sg:phone":"+34 924 67 14 27",
    "sg:postcode":"06200",
    "sg:province":"Badajoz",
    "wof:name":"Perez Garcia Francisco",
    "wof:placetype":"venue"
},
  "geometry": {"coordinates":[-6.4021539688,38.6832695007],"type":"Point"}
}