{
  "type": "Feature",
  "properties": {
    "iso:country":"ES",
    "sg:address":"Ctra. Biniali, Km. 0001,3",
    "sg:city":"Binissalem",
    "sg:orig_category":"Hormigonados",
    "sg:phone":"+34 971 87 04 08",
    "sg:postcode":"07350",
    "sg:province":"Islas Baleares",
    "sg:website":"www.mabasfaltos.com",
    "wof:name":"Matias Arrom Bibiloni S.l.",
    "wof:placetype":"venue"
},
  "geometry": {"coordinates":[2.8462650776,39.6886405945],"type":"Point"}
}