{
  "type": "Feature",
  "properties": {
    "iso:country":"ES",
    "sg:address":"Calle de Sagrada Familia (de La), 3",
    "sg:city":"Pinto",
    "sg:orig_category":"Internados & Ense\u00d1anza Privada",
    "sg:phone":"+34 916 91 10 26",
    "sg:postcode":"28320",
    "sg:province":"Madrid",
    "wof:name":"Congregacion Sagrada Familia De Burdeos",
    "wof:placetype":"venue"
},
  "geometry": {"coordinates":[-3.696297884,40.2411651611],"type":"Point"}
}