{
  "type": "Feature",
  "properties": {
    "iso:country":"ES",
    "sg:address":"C/ Sant Narcis, 23",
    "sg:city":"Vilobi D'onyar",
    "sg:orig_category":"Cl\u00cdnicas Dentales",
    "sg:phone":"+34 972 47 31 37",
    "sg:postcode":"17185",
    "sg:province":"Girona",
    "wof:name":"Dentli S.l.",
    "wof:placetype":"venue"
},
  "geometry": {"coordinates":[2.8152348995,41.9678573608],"type":"Point"}
}