{
  "type": "Feature",
  "properties": {
    "iso:country":"ES",
    "sg:address":"Avda Merced, 15",
    "sg:city":"Salamanca",
    "sg:orig_category":"Internados & Ense\u00d1anza Privada",
    "sg:phone":"+34 923 22 09 89",
    "sg:postcode":"37005",
    "sg:province":"Salamanca",
    "wof:name":"Residencia De Los Sagrados Corazones",
    "wof:placetype":"venue"
},
  "geometry": {"coordinates":[-5.6623740196,40.9769935608],"type":"Point"}
}