{
  "type": "Feature",
  "properties": {
    "addr:full":"La Rosa, 25 Sta Cruz Tenerife Santa Cruz De Tenerife 38002",
    "addr:housenumber":"25",
    "addr:postcode":"38002",
    "addr:street":"Rosa;Sta Cruz Tenerife",
    "iso:country":"ES",
    "sg:address":"La Rosa, 25",
    "sg:city":"Sta Cruz Tenerife",
    "sg:orig_category":"Asociaciones Y Clubs Deportivos",
    "sg:phone":"+34 922 27 11 33",
    "sg:postcode":"38002",
    "sg:province":"Santa Cruz De Tenerife",
    "wof:name":"Rodriguez Casanova Maria Elsa",
    "wof:placetype":"venue"
},
  "geometry": {"coordinates":[-16.2498226166,28.4709968567],"type":"Point"}
}