{
  "type": "Feature",
  "properties": {
    "addr:full":"Carrer de Eusebi Estada, 90 Palma Islas Baleares 07009",
    "addr:housenumber":"90",
    "addr:postcode":"07009",
    "addr:street":"Carrer De Eusebi Estada",
    "iso:country":"ES",
    "sg:address":"Carrer de Eusebi Estada, 90",
    "sg:city":"Palma",
    "sg:orig_category":"Herradores, Herreros, Carreteros",
    "sg:phone":"+34 971 20 44 21",
    "sg:postcode":"07009",
    "sg:province":"Islas Baleares",
    "wof:name":"Roig Pol Pedro",
    "wof:placetype":"venue"
},
  "geometry": {"coordinates":[2.6634590626,39.5864906311],"type":"Point"}
}