{
  "type": "Feature",
  "properties": {
    "addr:full":"Carr Alfonso Franch (d'), 38 Betxi Castell\u00f3n 12549",
    "addr:housenumber":"38",
    "addr:postcode":"12549",
    "addr:street":"Carr Alfonso Franch D ';Castello\u0301N",
    "iso:country":"ES",
    "sg:address":"Carr Alfonso Franch (d'), 38",
    "sg:city":"Betxi",
    "sg:orig_category":"Ropa Para Se\u00d1oras Y Caballeros (al Por Menor)",
    "sg:phone":"+34 964 62 00 95",
    "sg:postcode":"12549",
    "sg:province":"Castell\u00f3n",
    "wof:name":"Iba\u00f1ez Solsona Elias",
    "wof:placetype":"venue"
},
  "geometry": {"coordinates":[-0.1997649968,39.924949646],"type":"Point"}
}