{
  "type": "Feature",
  "properties": {
    "iso:country":"ES",
    "sg:address":"Plaz Luca De Tena, 2",
    "sg:city":"Madrid",
    "sg:orig_category":"Carnicer\u00cdas, Carnicer\u00cdas",
    "sg:phone":"+34 915 30 88 00",
    "sg:postcode":"28045",
    "sg:province":"Madrid",
    "wof:name":"Rodriguez Duran Felipe",
    "wof:placetype":"venue"
},
  "geometry": {"coordinates":[-3.6932849884,40.4024581909],"type":"Point"}
}