{
  "type": "Feature",
  "properties": {
    "iso:country":"ES",
    "sg:address":"Calle de Oca\u00d1a, 96",
    "sg:city":"Madrid",
    "sg:classifiers":[
        {
            "category":"Taxi",
            "type":"Transportation"
        }
    ],
    "sg:phone":"+34 914 61 65 47",
    "sg:postcode":"28047",
    "sg:province":"Madrid",
    "wof:name":"Sebastian Contreras Juan",
    "wof:placetype":"venue"
},
  "geometry": {"coordinates":[-3.7528839111,40.3852233887],"type":"Point"}
}