{
  "type": "Feature",
  "properties": {
    "iso:country":"ES",
    "sg:address":"Calle de Ercavica, 4",
    "sg:city":"Cuenca",
    "sg:orig_category":"Muebles, Minoristas",
    "sg:phone":"+34 969 21 43 97",
    "sg:postcode":"16001",
    "sg:province":"Cuenca",
    "wof:name":"Fernandez Garcia Carlos",
    "wof:placetype":"venue"
},
  "geometry": {"coordinates":[-2.1326305866,40.0716171265],"type":"Point"}
}