{
  "type": "Feature",
  "properties": {
    "addr:full":"Ctra Barcelona, 626 Sabadell Barcelona 08204",
    "addr:housenumber":"626",
    "addr:postcode":"08204",
    "addr:street":"Ctra Barcelona",
    "iso:country":"ES",
    "sg:address":"Ctra Barcelona, 626",
    "sg:city":"Sabadell",
    "sg:orig_category":"Colchones (fabricaci\u00d3n, Al Por Mayor, Al Por Menor)",
    "sg:phone":"+34 937 12 30 66",
    "sg:postcode":"08204",
    "sg:province":"Barcelona",
    "wof:name":"Perez Fuentes Pepita",
    "wof:placetype":"venue"
},
  "geometry": {"coordinates":[2.1165380478,41.5315666199],"type":"Point"}
}