{
  "type": "Feature",
  "properties": {
    "addr:full":"Calle de Pintor Cabrera, 8 Alacant Alicante 03003",
    "addr:housenumber":"8",
    "addr:postcode":"03003",
    "addr:street":"Calle De Pintor Cabrera",
    "iso:country":"ES",
    "sg:address":"Calle de Pintor Cabrera, 8",
    "sg:city":"Alacant",
    "sg:orig_category":"Prot\u00c9sicos Dentales",
    "sg:phone":"+34 965 14 04 09",
    "sg:postcode":"03003",
    "sg:province":"Alicante",
    "wof:name":"Profdent S.c.",
    "wof:placetype":"venue"
},
  "geometry": {"coordinates":[-0.4907880127,38.3451156616],"type":"Point"}
}