{
  "type": "Feature",
  "properties": {
    "addr:full":"Plaz Constitucion (la), S/n Cambil Ja\u00e9n 23120",
    "addr:housenumber":"/ n",
    "addr:postcode":"23120",
    "addr:street":"Constitucion La S",
    "iso:country":"ES",
    "sg:address":"Plaz Constitucion (la), S/n",
    "sg:city":"Cambil",
    "sg:orig_category":"Iglesia Cat\u00d3lica",
    "sg:phone":"+34 953 30 01 26",
    "sg:postcode":"23120",
    "sg:province":"Ja\u00e9n",
    "wof:name":"Parroquia De La Encarnacion",
    "wof:placetype":"venue"
},
  "geometry": {"coordinates":[-3.5657339096,37.6770553589],"type":"Point"}
}