{
  "type": "Feature",
  "properties": {
    "iso:country":"ES",
    "sg:address":"Calle de Enrique Segura Ota\u00d1o, 15",
    "sg:city":"Badajoz",
    "sg:orig_category":"Asesor\u00cdas Y Estudios Financieros",
    "sg:phone":"+34 924 23 19 59",
    "sg:postcode":"06004",
    "sg:province":"Badajoz",
    "wof:name":"Bigeriego Porras Fernando",
    "wof:placetype":"venue"
},
  "geometry": {"coordinates":[-6.9714460373,38.8731651306],"type":"Point"}
}