{
  "type": "Feature",
  "properties": {
    "iso:country":"ES",
    "sg:address":"Marie Curie, 11",
    "sg:city":"Gijon",
    "sg:orig_category":"Caf\u00c9s (al Por Menor)",
    "sg:phone":"+34 985 15 46 16",
    "sg:postcode":"33211",
    "sg:province":"Asturias",
    "wof:name":"Cafes Toscaf S.a.",
    "wof:placetype":"venue"
},
  "geometry": {"coordinates":[-5.6902341843,43.5291786194],"type":"Point"}
}