{
  "type": "Feature",
  "properties": {
    "iso:country":"ES",
    "sg:address":"Calle de Arroyo Del Pilar, 12",
    "sg:city":"Pedro Abad",
    "sg:orig_category":"Confecci\u00d3n (fabricaci\u00d3n, Al Por Mayor)",
    "sg:phone":"+34 957 18 61 84",
    "sg:postcode":"14630",
    "sg:province":"C\u00f3rdoba",
    "wof:name":"Martin Ruiz Francisco",
    "wof:placetype":"venue"
},
  "geometry": {"coordinates":[-4.4574999809,37.9655151367],"type":"Point"}
}