{
  "type": "Feature",
  "properties": {
    "iso:country":"ES",
    "sg:address":"Carrer de Consell De Cent, 343",
    "sg:city":"Barcelona",
    "sg:orig_category":"Abogados",
    "sg:phone":"+34 934 87 32 68",
    "sg:postcode":"08007",
    "sg:province":"Barcelona",
    "wof:name":"Bas Vi\u00f1uales Jose Eduardo",
    "wof:placetype":"venue"
},
  "geometry": {"coordinates":[2.1649830341,41.390750885],"type":"Point"}
}