{
  "type": "Feature",
  "properties": {
    "addr:full":"Carrer de Proven\u00c7a, 136 Barcelona Barcelona 08029",
    "addr:housenumber":"136",
    "addr:postcode":"08029",
    "addr:street":"Carrer De Provenc\u0327A",
    "iso:country":"ES",
    "sg:address":"Carrer de Proven\u00c7a, 136",
    "sg:city":"Barcelona",
    "sg:orig_category":"Reposter\u00cdas",
    "sg:phone":"+34 933 23 49 37",
    "sg:postcode":"08029",
    "sg:province":"Barcelona",
    "wof:name":"Moli Vell S.l.",
    "wof:placetype":"venue"
},
  "geometry": {"coordinates":[2.1511540413,41.3867683411],"type":"Point"}
}