{
  "type": "Feature",
  "properties": {
    "addr:full":"Avda Ogijares, 11 Armilla Granada 18100",
    "addr:housenumber":"11",
    "addr:postcode":"18100",
    "addr:street":"Avda Ogijares",
    "iso:country":"ES",
    "sg:address":"Avda Ogijares, 11",
    "sg:city":"Armilla",
    "sg:orig_category":"Supermercados Y Hipermercados",
    "sg:phone":"+34 958 55 21 00",
    "sg:postcode":"18100",
    "sg:province":"Granada",
    "wof:name":"Supermercados Santaella S.l.",
    "wof:placetype":"venue"
},
  "geometry": {"coordinates":[-3.6246109009,37.1380958557],"type":"Point"}
}