{
  "type": "Feature",
  "properties": {
    "addr:full":"El Salvador, 13 Villarramiel Palencia 34140",
    "addr:housenumber":"13",
    "addr:postcode":"34140",
    "addr:street":"El Salvador",
    "iso:country":"ES",
    "sg:address":"El Salvador, 13",
    "sg:city":"Villarramiel",
    "sg:orig_category":"Transportes De Material De Construcci\u00d3n",
    "sg:phone":"+34 979 83 71 91",
    "sg:postcode":"34140",
    "sg:province":"Palencia",
    "wof:name":"Quintas Plaza Felix",
    "wof:placetype":"venue"
},
  "geometry": {"coordinates":[-4.9164381027,42.0407714844],"type":"Point"}
}