{
  "type": "Feature",
  "properties": {
    "iso:country":"ES",
    "sg:address":"Avda Espa\u00d1a, 244",
    "sg:city":"Estepona",
    "sg:orig_category":"Inmobiliaria (agencias)",
    "sg:phone":"+34 952 79 09 35",
    "sg:postcode":"29680",
    "sg:province":"M\u00e1laga",
    "wof:name":"Cabanillas Gil Mariano",
    "wof:placetype":"venue"
},
  "geometry": {"coordinates":[-5.15082407,36.4200248718],"type":"Point"}
}