{
  "type": "Feature",
  "properties": {
    "addr:full":"Calle de Bahia De Almeria, 40 Madrid Madrid 28042",
    "addr:housenumber":"40",
    "addr:postcode":"madrid;28042",
    "addr:street":"Calle De Bahia De Almeria",
    "iso:country":"ES",
    "sg:address":"Calle de Bahia De Almeria, 40",
    "sg:city":"Madrid",
    "sg:orig_category":"Inform\u00c1tica: Mantenimiento Y Reparaci\u00d3n De Ordenadores",
    "sg:phone":"+34 913 12 16 33",
    "sg:postcode":"28042",
    "sg:province":"Madrid",
    "wof:name":"Desarrollo De Entornos Informaticos J&n Systems S.l.",
    "wof:placetype":"venue"
},
  "geometry": {"coordinates":[-3.5923366547,40.461681366],"type":"Point"}
}