{
  "type": "Feature",
  "properties": {
    "iso:country":"ES",
    "sg:address":"Calle de Madrid, 9",
    "sg:city":"Torrejon Ardoz",
    "sg:orig_category":"Ense\u00d1anza: Profesiones Art\u00cdsticas",
    "sg:phone":"+34 916 75 45 26",
    "sg:postcode":"28850",
    "sg:province":"Madrid",
    "wof:name":"Luengo Sastre Juan Francisco",
    "wof:placetype":"venue"
},
  "geometry": {"coordinates":[-3.4772379398,40.46301651],"type":"Point"}
}