{
  "type": "Feature",
  "properties": {
    "iso:country":"ES",
    "sg:address":"Avda Cervantes (de), 11",
    "sg:city":"Granada",
    "sg:orig_category":"Frutas, Legumbres Frescas Y Tempranas (al Por Menor)",
    "sg:phone":"+34 958 13 33 22",
    "sg:postcode":"18008",
    "sg:province":"Granada",
    "wof:name":"Maldonado Escudero Jose Maria",
    "wof:placetype":"venue"
},
  "geometry": {"coordinates":[-3.589040041,37.1656417847],"type":"Point"}
}