{
  "type": "Feature",
  "properties": {
    "addr:full":"Calle de Fray Julian Garas, 1 Zaragoza Zaragoza 50006",
    "addr:housenumber":"1",
    "addr:postcode":"50006",
    "addr:street":"Calle De Fray Julian Garas",
    "iso:country":"ES",
    "sg:address":"Calle de Fray Julian Garas, 1",
    "sg:city":"Zaragoza",
    "sg:orig_category":"Internados & Ense\u00d1anza Privada",
    "sg:phone":"+34 976 38 51 55",
    "sg:postcode":"50006",
    "sg:province":"Zaragoza",
    "wof:name":"Colegio S Antonio De Padua En Zaragoza Capuchinos Orden Frailes Menores Provincia Navarra Cantabria ",
    "wof:placetype":"venue"
},
  "geometry": {"coordinates":[-0.8869850039,41.6340637207],"type":"Point"}
}