{
  "type": "Feature",
  "properties": {
    "addr:full":"Calle de Marques De La Ensenada, 16 Madrid Madrid 28004",
    "addr:housenumber":"16",
    "addr:postcode":"madrid;28004",
    "addr:street":"Calle De Marques De La Ensenada",
    "iso:country":"ES",
    "sg:address":"Calle de Marques De La Ensenada, 16",
    "sg:city":"Madrid",
    "sg:orig_category":"Artes Gr\u00c1ficas, Artes Pl\u00c1sticas (curso)",
    "sg:phone":"+34 913 10 35 96",
    "sg:postcode":"28004",
    "sg:province":"Madrid",
    "wof:name":"Granados Bravo Luis Fernando",
    "wof:placetype":"venue"
},
  "geometry": {"coordinates":[-3.6919679642,40.4252738953],"type":"Point"}
}