{
  "type": "Feature",
  "properties": {
    "iso:country":"ES",
    "sg:address":"Avda Alcalde De Mostoles (del), 27",
    "sg:city":"Mostoles",
    "sg:orig_category":"Electricidad, Electr\u00d3nica: Suministros (al Por Menor)",
    "sg:phone":"+34 916 17 70 40",
    "sg:postcode":"28933",
    "sg:province":"Madrid",
    "wof:name":"Zarko Comunicaciones S.l.",
    "wof:placetype":"venue"
},
  "geometry": {"coordinates":[-3.8686349392,40.3350753784],"type":"Point"}
}