{
  "type": "Feature",
  "properties": {
    "addr:full":"Carrer de Anselm Clave, 97 Sant Vicen\u00c7 Dels Horts Barcelona 08620",
    "addr:housenumber":"97",
    "addr:postcode":"08620",
    "addr:street":"Carrer De Anselm Clave",
    "iso:country":"ES",
    "sg:address":"Carrer de Anselm Clave, 97",
    "sg:city":"Sant Vicen\u00c7 Dels Horts",
    "sg:orig_category":"Molduras, Junquillos, Listones Y Molduras Perforadas",
    "sg:phone":"+34 936 56 06 58",
    "sg:postcode":"08620",
    "sg:province":"Barcelona",
    "wof:name":"Sistelcom-telemensaje S.a.",
    "wof:placetype":"venue"
},
  "geometry": {"coordinates":[2.0127499104,41.3881492615],"type":"Point"}
}