{
  "type": "Feature",
  "properties": {
    "addr:full":"Rond Pais Valencia, 46 Sueca Valencia 46410",
    "addr:housenumber":"46",
    "addr:postcode":"46410",
    "addr:street":"Rond Pais Valencia",
    "iso:country":"ES",
    "sg:address":"Rond Pais Valencia, 46",
    "sg:city":"Sueca",
    "sg:orig_category":"Ingenier\u00cda, Centros De Estudios (diversos)",
    "sg:phone":"+34 961 70 62 52",
    "sg:postcode":"46410",
    "sg:province":"Valencia",
    "wof:name":"Carrasquer Sigues Ana",
    "wof:placetype":"venue"
},
  "geometry": {"coordinates":[-0.30873999,39.1996803284],"type":"Point"}
}