{
  "type": "Feature",
  "properties": {
    "addr:full":"Avda Beiramar, 213 Vigo Pontevedra 36208",
    "addr:housenumber":"213",
    "addr:postcode":"36208",
    "addr:street":"Avda Beiramar",
    "iso:country":"ES",
    "sg:address":"Avda Beiramar, 213",
    "sg:city":"Vigo",
    "sg:orig_category":"Peritos Mar\u00cdtimos",
    "sg:phone":"+34 986 23 99 06",
    "sg:postcode":"36208",
    "sg:province":"Pontevedra",
    "wof:name":"Armada Anido Angel",
    "wof:placetype":"venue"
},
  "geometry": {"coordinates":[-8.748916626,42.2248764038],"type":"Point"}
}