{
  "type": "Feature",
  "properties": {
    "iso:country":"ES",
    "sg:address":"Pase Prado (del), 74",
    "sg:city":"Talayuelas",
    "sg:orig_category":"Cajas De Ahorro",
    "sg:phone":"+34 969 36 31 95",
    "sg:postcode":"16320",
    "sg:province":"Cuenca",
    "wof:name":"Caja De Ahorros De Castilla La Mancha",
    "wof:placetype":"venue"
},
  "geometry": {"coordinates":[-1.2841750383,39.8494186401],"type":"Point"}
}