{
  "type": "Feature",
  "properties": {
    "addr:full":"Calle de Correria, 17 Balmaseda Vizcaya 48800",
    "addr:housenumber":"17",
    "addr:postcode":"48800",
    "addr:street":"Calle De Correria",
    "iso:country":"ES",
    "sg:address":"Calle de Correria, 17",
    "sg:city":"Balmaseda",
    "sg:orig_category":"Transporte En General",
    "sg:phone":"+34 946 80 03 17",
    "sg:postcode":"48800",
    "sg:province":"Vizcaya",
    "wof:name":"Pe\u00f1a Linares Iciar",
    "wof:placetype":"venue"
},
  "geometry": {"coordinates":[-3.1935873032,43.195186615],"type":"Point"}
}