{
  "type": "Feature",
  "properties": {
    "addr:full":"Carrer de Balmes, 391 Barcelona Barcelona 08022",
    "addr:housenumber":"391",
    "addr:postcode":"08022",
    "addr:street":"Carrer De Balmes",
    "iso:country":"ES",
    "sg:address":"Carrer de Balmes, 391",
    "sg:city":"Barcelona",
    "sg:orig_category":"M\u00c9dicos: Dermatolog\u00cda Y Venereolog\u00cda",
    "sg:phone":"+34 934 18 79 79",
    "sg:postcode":"08022",
    "sg:province":"Barcelona",
    "wof:name":"Bassas Vila Julio",
    "wof:placetype":"venue"
},
  "geometry": {"coordinates":[2.1386930943,41.4062728882],"type":"Point"}
}