{
  "type": "Feature",
  "properties": {
    "iso:country":"ES",
    "sg:address":"Cmno Gavias (las), 2",
    "sg:city":"San Cristobal De La Laguna",
    "sg:orig_category":"Bazares, Art\u00cdculos De Limpieza Y De Cocina (al Por Menor)",
    "sg:phone":"+34 922 63 26 38",
    "sg:postcode":"38202",
    "sg:province":"Santa Cruz De Tenerife",
    "wof:name":"Perez Padilla Luciano",
    "wof:placetype":"venue"
},
  "geometry": {"coordinates":[-16.3253059387,28.4909076691],"type":"Point"}
}