{
  "type": "Feature",
  "properties": {
    "iso:country":"ES",
    "sg:address":"Av Levante, 50",
    "sg:city":"Beniparrell",
    "sg:orig_category":"Alquiler De Veh\u00cdculos: Turismos Y Utilitarios",
    "sg:phone":"+34 961 21 26 89",
    "sg:postcode":"46469",
    "sg:province":"Valencia",
    "wof:name":"Furgo Car S. A.",
    "wof:placetype":"venue"
},
  "geometry": {"coordinates":[-0.4116789997,39.383228302],"type":"Point"}
}