{
  "type": "Feature",
  "properties": {
    "iso:country":"ES",
    "sg:address":"Rua Real, 195",
    "sg:city":"Ferrol",
    "sg:orig_category":"Arquitectos",
    "sg:phone":"+34 981 35 16 44",
    "sg:postcode":"15402",
    "sg:province":"La Coru\u00f1a",
    "wof:name":"Nu\u00f1ez Mille Maria Manuela",
    "wof:placetype":"venue"
},
  "geometry": {"coordinates":[-8.2369737625,43.4821128845],"type":"Point"}
}