{
  "type": "Feature",
  "properties": {
    "iso:country":"ES",
    "sg:address":"Av Diagonal, 612",
    "sg:city":"Barcelona",
    "sg:orig_category":"Publicidad (soportes Y Gesti\u00d3n)",
    "sg:phone":"+34 934 14 11 17",
    "sg:postcode":"08021",
    "sg:province":"Barcelona",
    "wof:name":"Angel Rozas Promedios S.c.p.",
    "wof:placetype":"venue"
},
  "geometry": {"coordinates":[2.1421129704,41.3924636841],"type":"Point"}
}