{
  "type": "Feature",
  "properties": {
    "addr:full":"Calle de Rufino Blanco, 10 Madrid Madrid 28028",
    "addr:housenumber":"10",
    "addr:postcode":"madrid;28028",
    "addr:street":"Calle De Rufino Blanco",
    "iso:country":"ES",
    "sg:address":"Calle de Rufino Blanco, 10",
    "sg:city":"Madrid",
    "sg:orig_category":"Vulcanizado",
    "sg:phone":"+34 913 56 38 27",
    "sg:postcode":"28028",
    "sg:province":"Madrid",
    "wof:name":"Aguilera Bartolome Blas",
    "wof:placetype":"venue"
},
  "geometry": {"coordinates":[-3.6662766933,40.4276390076],"type":"Point"}
}