{
  "type": "Feature",
  "properties": {
    "addr:full":"Av Mossen Jaume Soler, 25 Playa De Calafell Tarragona 43820",
    "addr:housenumber":"25",
    "addr:postcode":"43820",
    "addr:street":"Av Mossen Jaume Soler",
    "iso:country":"ES",
    "sg:address":"Av Mossen Jaume Soler, 25",
    "sg:city":"Playa De Calafell",
    "sg:orig_category":"Inmobiliaria (agencias)",
    "sg:phone":"+34 977 69 26 58",
    "sg:postcode":"43820",
    "sg:province":"Tarragona",
    "wof:name":"Fincas Progres S.l.",
    "wof:placetype":"venue"
},
  "geometry": {"coordinates":[1.5835683346,41.1900444031],"type":"Point"}
}