{
  "type": "Feature",
  "properties": {
    "addr:full":"Calle de Salamanca, 1 Caceres C\u00e1ceres 10002",
    "addr:housenumber":"1",
    "addr:postcode":"10002",
    "addr:street":"Calle De Salamanca;Ca\u0301Ceres",
    "iso:country":"ES",
    "sg:address":"Calle de Salamanca, 1",
    "sg:city":"Caceres",
    "sg:orig_category":"Bisuter\u00cda, Joyer\u00cda, Relojer\u00cda (al Por Menor)",
    "sg:phone":"+34 927 24 98 56",
    "sg:postcode":"10002",
    "sg:province":"C\u00e1ceres",
    "wof:name":"Creaciones Moncal S.l.",
    "wof:placetype":"venue"
},
  "geometry": {"coordinates":[-6.3720030785,39.4745063782],"type":"Point"}
}