{
  "type": "Feature",
  "properties": {
    "iso:country":"ES",
    "sg:address":"Carrer de Galanes, 4",
    "sg:city":"Reus",
    "sg:orig_category":"Confecci\u00d3n De Alpargatas",
    "sg:phone":"+34 977 34 14 40",
    "sg:postcode":"43201",
    "sg:province":"Tarragona",
    "wof:name":"Casas Olle Maria Josefa",
    "wof:placetype":"venue"
},
  "geometry": {"coordinates":[1.1090040207,41.1555023193],"type":"Point"}
}