{
  "type": "Feature",
  "properties": {
    "addr:full":"Rua Orense, 68 Monforte De Lemos Lugo 27400",
    "addr:housenumber":"68",
    "addr:postcode":"27400",
    "addr:street":"Rua Orense",
    "iso:country":"ES",
    "sg:address":"Rua Orense, 68",
    "sg:city":"Monforte De Lemos",
    "sg:orig_category":"Empresarios",
    "sg:phone":"+34 982 40 22 21",
    "sg:postcode":"27400",
    "sg:province":"Lugo",
    "wof:name":"Arias Meira Emilio",
    "wof:placetype":"venue"
},
  "geometry": {"coordinates":[-7.6246848106,42.5065422058],"type":"Point"}
}