{
  "type": "Feature",
  "properties": {
    "addr:full":"Calle de Barcelona, S/n Palomares Del Campo Cuenca 16160",
    "addr:housenumber":"/ n",
    "addr:postcode":"16160",
    "addr:street":"Calle De Barcelona S",
    "iso:country":"ES",
    "sg:address":"Calle de Barcelona, S/n",
    "sg:city":"Palomares Del Campo",
    "sg:classifiers":[
        {
            "category":"Taxi",
            "type":"Transportation"
        }
    ],
    "sg:phone":"+34 969 27 75 27",
    "sg:postcode":"16160",
    "sg:province":"Cuenca",
    "wof:name":"Zamora Miranzo Angel",
    "wof:placetype":"venue"
},
  "geometry": {"coordinates":[-2.594949007,39.9451751709],"type":"Point"}
}