{
  "type": "Feature",
  "properties": {
    "iso:country":"ES",
    "sg:address":"Calle de Doctor Fleming, 6",
    "sg:city":"Miranda Ebro",
    "sg:orig_category":"Inform\u00c1tica: Material Y Suministros",
    "sg:phone":"+34 947 33 11 11",
    "sg:postcode":"09200",
    "sg:province":"Burgos",
    "wof:name":"Soft 5 S.l.",
    "wof:placetype":"venue"
},
  "geometry": {"coordinates":[-3.0124723911,42.5816574097],"type":"Point"}
}