{
  "type": "Feature",
  "properties": {
    "iso:country":"ES",
    "sg:address":"Calle de San Diego, 38",
    "sg:city":"Coru\u00d1a",
    "sg:orig_category":"Peluqueros: De Se\u00d1oras",
    "sg:phone":"+34 981 13 42 49",
    "sg:postcode":"15009",
    "sg:province":"A Coru\u00f1a",
    "wof:name":"Sendon Calvi\u00f1o Veronica",
    "wof:placetype":"venue"
},
  "geometry": {"coordinates":[-8.4014883041,43.3524856567],"type":"Point"}
}