{
  "type": "Feature",
  "properties": {
    "addr:full":"Avda Ciudades (de Las), 96 Getafe Madrid 28903",
    "addr:housenumber":"96",
    "addr:postcode":"28903",
    "addr:street":"Avda Ciudades De Las",
    "iso:country":"ES",
    "sg:address":"Avda Ciudades (de Las), 96",
    "sg:city":"Getafe",
    "sg:orig_category":"Papeler\u00cdas, Librer\u00cdas",
    "sg:phone":"+34 916 01 85 91",
    "sg:postcode":"28903",
    "sg:province":"Madrid",
    "wof:name":"Papelchip S.l.",
    "wof:placetype":"venue"
},
  "geometry": {"coordinates":[-3.7153699398,40.313331604],"type":"Point"}
}