{
  "type": "Feature",
  "properties": {
    "iso:country":"ES",
    "sg:address":"Calle de Adelfa, 43",
    "sg:city":"Puebla Alfinden",
    "sg:orig_category":"Maquinaria Para Industrias Diversas",
    "sg:phone":"+34 976 45 50 90",
    "sg:postcode":"50171",
    "sg:province":"Zaragoza",
    "sg:website":"www.escoeurope.com",
    "wof:name":"Byg S.a.",
    "wof:placetype":"venue"
},
  "geometry": {"coordinates":[-0.7659859061,41.6427383423],"type":"Point"}
}