{
  "type": "Feature",
  "properties": {
    "addr:full":"Calle de Solera, 29 Mojonera Almer\u00eda 04745",
    "addr:housenumber":"29",
    "addr:postcode":"04745",
    "addr:street":"Calle De Solera",
    "iso:country":"ES",
    "sg:address":"Calle de Solera, 29",
    "sg:city":"Mojonera",
    "sg:orig_category":"Servicios De Telecomunicaciones",
    "sg:phone":"+34 950 62 77 68",
    "sg:postcode":"04745",
    "sg:province":"Almer\u00eda",
    "wof:name":"Amghar Telecomunicaciones S.l.",
    "wof:placetype":"venue"
},
  "geometry": {"coordinates":[-2.6810297966,36.7544593811],"type":"Point"}
}