{
  "type": "Feature",
  "properties": {
    "addr:full":"Autopista Terrassa, S/n S. Quirze Valles Barcelona 08192",
    "addr:housenumber":"s",
    "addr:postcode":"08192",
    "addr:street":"/ N S.;Valles Barcelona",
    "iso:country":"ES",
    "sg:address":"Autopista Terrassa, S/n",
    "sg:city":"S. Quirze Valles",
    "sg:orig_category":"Herboristas (al Por Menor)",
    "sg:phone":"+34 937 21 23 29",
    "sg:postcode":"08192",
    "sg:province":"Barcelona",
    "wof:name":"Sanjurjo Ruiz Maria Isabel",
    "wof:placetype":"venue"
},
  "geometry": {"coordinates":[2.0799798965,41.5347747803],"type":"Point"}
}