{
  "type": "Feature",
  "properties": {
    "iso:country":"ES",
    "sg:address":"Pg Pins, 7",
    "sg:city":"Rubi",
    "sg:orig_category":"Molduras, Junquillos, Listones Y Molduras Perforadas",
    "sg:phone":"+34 936 97 40 71",
    "sg:postcode":"08191",
    "sg:province":"Barcelona",
    "wof:name":"Lopez Ochoa Rafael",
    "wof:placetype":"venue"
},
  "geometry": {"coordinates":[2.0171968937,41.4857559204],"type":"Point"}
}