{
  "type": "Feature",
  "properties": {
    "addr:full":"Pg Font Del Cirerer, 43 S. Hilari Sacalm Girona 17403",
    "addr:housenumber":"43",
    "addr:postcode":"17403",
    "addr:street":"Pg;Del Cirerer;S. Hilari",
    "iso:country":"ES",
    "sg:address":"Pg Font Del Cirerer, 43",
    "sg:city":"S. Hilari Sacalm",
    "sg:orig_category":"Distribuci\u00d3n De Petr\u00d3leo Y Derivados",
    "sg:phone":"+34 972 86 81 68",
    "sg:postcode":"17403",
    "sg:province":"Girona",
    "wof:name":"Benzinera Sant Hilari S.l.",
    "wof:placetype":"venue"
},
  "geometry": {"coordinates":[2.5095000267,41.878238678],"type":"Point"}
}