{
  "type": "Feature",
  "properties": {
    "addr:full":"Rua Bola\u00d1o Rivadeneira, 13 Lugo Lugo 27001",
    "addr:housenumber":"13",
    "addr:postcode":"27001",
    "addr:street":"Rua Bolan\u0303O Rivadeneira",
    "iso:country":"ES",
    "sg:address":"Rua Bola\u00d1o Rivadeneira, 13",
    "sg:city":"Lugo",
    "sg:orig_category":"Confecci\u00d3n (fabricaci\u00d3n, Al Por Mayor)",
    "sg:phone":"+34 982 25 23 23",
    "sg:postcode":"27001",
    "sg:province":"Lugo",
    "wof:name":"Galan Del Campo Maria",
    "wof:placetype":"venue"
},
  "geometry": {"coordinates":[-7.558327198,43.0128898621],"type":"Point"}
}