{
  "type": "Feature",
  "properties": {
    "addr:full":"Carrer de Vila-seca, 39 Barcelona Barcelona 08031",
    "addr:housenumber":"39",
    "addr:postcode":"08031",
    "addr:street":"Carrer De Vila-Seca",
    "iso:country":"ES",
    "sg:address":"Carrer de Vila-seca, 39",
    "sg:city":"Barcelona",
    "sg:orig_category":"Farmacias",
    "sg:phone":"+34 934 29 31 09",
    "sg:postcode":"08031",
    "sg:province":"Barcelona",
    "wof:name":"Garzon Grane Carlos",
    "wof:placetype":"venue"
},
  "geometry": {"coordinates":[2.1652090549,41.4347114563],"type":"Point"}
}