{
  "type": "Feature",
  "properties": {
    "addr:full":"Praz Irmans Garcia Naveira, 19 Betanzos A Coru\u00f1a 15300",
    "addr:housenumber":"19",
    "addr:postcode":"15300",
    "addr:street":"Praz Irmans Garcia Naveira",
    "iso:country":"ES",
    "sg:address":"Praz Irmans Garcia Naveira, 19",
    "sg:city":"Betanzos",
    "sg:orig_category":"Cl\u00cdnicas M\u00c9dicas",
    "sg:phone":"+34 981 77 08 06",
    "sg:postcode":"15300",
    "sg:province":"A Coru\u00f1a",
    "wof:name":"Vazquez Fernandez Jose Angel",
    "wof:placetype":"venue"
},
  "geometry": {"coordinates":[-8.2098836899,43.2795906067],"type":"Point"}
}