{
  "type": "Feature",
  "properties": {
    "addr:full":"Avda Vega (p I Antequera), 10 Antequera M\u00e1laga 29200",
    "addr:housenumber":"10",
    "addr:postcode":"29200",
    "addr:street":"Avda Vega P;Antequera",
    "iso:country":"ES",
    "sg:address":"Avda Vega (p I Antequera), 10",
    "sg:city":"Antequera",
    "sg:orig_category":"Cooperativas Agr\u00cdcolas",
    "sg:phone":"+34 952 70 25 39",
    "sg:postcode":"29200",
    "sg:province":"M\u00e1laga",
    "wof:name":"Cubinal Sociedad Cooperativa Andalucia",
    "wof:placetype":"venue"
},
  "geometry": {"coordinates":[-4.5614161491,37.0214653015],"type":"Point"}
}