{
  "type": "Feature",
  "properties": {
    "iso:country":"ES",
    "sg:address":"Carrer de Nonell, 1",
    "sg:city":"Pinemar",
    "sg:orig_category":"Molduras, Junquillos, Listones Y Molduras Perforadas",
    "sg:phone":"+34 937 62 60 88",
    "sg:postcode":"08397",
    "sg:province":"Barcelona",
    "wof:name":"Fernandez Jimenez Antonio",
    "wof:placetype":"venue"
},
  "geometry": {"coordinates":[2.6826798916,41.6266517639],"type":"Point"}
}