{
  "type": "Feature",
  "properties": {
    "iso:country":"ES",
    "sg:address":"Calle de Melquiades Alvarez, 26",
    "sg:city":"Oviedo",
    "sg:orig_category":"M\u00c9dicos: Cardiolog\u00cda Y Afecciones Cardiovasculares",
    "sg:phone":"+34 985 22 08 96",
    "sg:postcode":"33003",
    "sg:province":"Asturias",
    "wof:name":"De La Vega Gonzalez Jesus",
    "wof:placetype":"venue"
},
  "geometry": {"coordinates":[-5.8526887894,43.3649597168],"type":"Point"}
}