{
  "type": "Feature",
  "properties": {
    "iso:country":"ES",
    "sg:address":"Avda Santa Ana, 20",
    "sg:city":"Palma Rio",
    "sg:orig_category":"Cajas De Ahorro",
    "sg:phone":"+34 957 71 06 14",
    "sg:postcode":"14700",
    "sg:province":"C\u00f3rdoba",
    "sg:website":"www.ruraldia.com",
    "wof:name":"Caja Rural De Cordoba",
    "wof:placetype":"venue"
},
  "geometry": {"coordinates":[-5.2792577744,37.7001914978],"type":"Point"}
}