{
  "type": "Feature",
  "properties": {
    "addr:full":"Rua Ponte Do Sar (da), 62 Santiago De Compostela La Coru\u00f1a 15702",
    "addr:housenumber":"62",
    "addr:postcode":"15702",
    "addr:street":"Rua Ponte Do Sar Da;Corun\u0303A",
    "iso:country":"ES",
    "sg:address":"Rua Ponte Do Sar (da), 62",
    "sg:city":"Santiago De Compostela",
    "sg:orig_category":"Farmacias",
    "sg:phone":"+34 981 56 07 93",
    "sg:postcode":"15702",
    "sg:province":"La Coru\u00f1a",
    "wof:name":"Codesido Lopez Maria Del Carmen",
    "wof:placetype":"venue"
},
  "geometry": {"coordinates":[-8.5337915421,42.8700752258],"type":"Point"}
}