{
  "type": "Feature",
  "properties": {
    "addr:full":"Cra. Nal. Tres-cents Quaranta, Km. 1167,0 Tarragona Tarragona 43007",
    "addr:postcode":"43007",
    "addr:street":"Km. 1167,0",
    "iso:country":"ES",
    "sg:address":"Cra. Nal. Tres-cents Quaranta, Km. 1167,0",
    "sg:city":"Tarragona",
    "sg:orig_category":"Distribuci\u00d3n De Petr\u00d3leo Y Derivados",
    "sg:phone":"+34 977 20 70 05",
    "sg:postcode":"43007",
    "sg:province":"Tarragona",
    "wof:name":"Repsol Ypf S.a.",
    "wof:placetype":"venue"
},
  "geometry": {"coordinates":[1.2959779501,41.1377334595],"type":"Point"}
}