{
  "type": "Feature",
  "properties": {
    "addr:full":"Calle de Mora\u00d1a, 18 Leganes Madrid 28915",
    "addr:housenumber":"18",
    "addr:postcode":"28915",
    "addr:street":"Calle De Moran\u0303A",
    "iso:country":"ES",
    "sg:address":"Calle de Mora\u00d1a, 18",
    "sg:city":"Leganes",
    "sg:orig_category":"Fabricaci\u00d3n, Instalaci\u00d3n De Armarios",
    "sg:phone":"+34 914 81 06 16",
    "sg:postcode":"28915",
    "sg:province":"Madrid",
    "wof:name":"Timbrados El Molino S. L.",
    "wof:placetype":"venue"
},
  "geometry": {"coordinates":[-3.7548980713,40.3321609497],"type":"Point"}
}