{
  "type": "Feature",
  "properties": {
    "iso:country":"ES",
    "sg:address":"Calle de San Sebastian, S/n",
    "sg:city":"Puente-genil",
    "sg:orig_category":"Distribuci\u00d3n De Petr\u00d3leo Y Derivados",
    "sg:phone":"+34 957 60 05 80",
    "sg:postcode":"14500",
    "sg:province":"C\u00f3rdoba",
    "wof:name":"Estacion De Servicio La Barca S.a.",
    "wof:placetype":"venue"
},
  "geometry": {"coordinates":[-4.7797861099,37.3905448914],"type":"Point"}
}