{
  "type": "Feature",
  "properties": {
    "addr:full":"Barr El Valle, 21 San Juan De Muskiz Vizcaya 48550",
    "addr:housenumber":"21",
    "addr:postcode":"48550",
    "addr:street":"Valle",
    "iso:country":"ES",
    "sg:address":"Barr El Valle, 21",
    "sg:city":"San Juan De Muskiz",
    "sg:orig_category":"Contenedores (mercanc\u00cdas)",
    "sg:phone":"+34 946 70 69 48",
    "sg:postcode":"48550",
    "sg:province":"Vizcaya",
    "wof:name":"Gutierrez Pellon Jose Maria",
    "wof:placetype":"venue"
},
  "geometry": {"coordinates":[-3.1228249073,43.3224563599],"type":"Point"}
}