{
  "type": "Feature",
  "properties": {
    "iso:country":"ES",
    "sg:address":"Rua Ourense, 59",
    "sg:city":"Lugo",
    "sg:orig_category":"M\u00c9dicos: Neurolog\u00cda",
    "sg:phone":"+34 982 21 37 75",
    "sg:postcode":"27004",
    "sg:province":"Lugo",
    "wof:name":"Cortes Lai\u00f1o Jose Antonio",
    "wof:placetype":"venue"
},
  "geometry": {"coordinates":[-7.5648589134,43.014919281],"type":"Point"}
}