{
  "type": "Feature",
  "properties": {
    "iso:country":"ES",
    "sg:address":"Republica Argentina, 13",
    "sg:city":"Sada",
    "sg:orig_category":"Perfumer\u00cda (al Por Menor)",
    "sg:phone":"+34 981 62 10 43",
    "sg:postcode":"15160",
    "sg:province":"La Coru\u00f1a",
    "wof:name":"Garcia Canle Maria Teresa",
    "wof:placetype":"venue"
},
  "geometry": {"coordinates":[-8.2521305084,43.3488197327],"type":"Point"}
}