{
  "type": "Feature",
  "properties": {
    "addr:full":"Calle de Bernardino Obregon, 18 Madrid Madrid 28012",
    "addr:housenumber":"18",
    "addr:postcode":"madrid;28012",
    "addr:street":"Calle De Bernardino Obregon",
    "iso:country":"ES",
    "sg:address":"Calle de Bernardino Obregon, 18",
    "sg:city":"Madrid",
    "sg:orig_category":"Arte, Cultura, Edici\u00d3n",
    "sg:phone":"+34 915 27 35 94",
    "sg:postcode":"28012",
    "sg:province":"Madrid",
    "wof:name":"Sala De Espectaculos Caracol S.l.",
    "wof:placetype":"venue"
},
  "geometry": {"coordinates":[-3.6999490261,40.4040336609],"type":"Point"}
}