{
  "type": "Feature",
  "properties": {
    "iso:country":"ES",
    "sg:address":"Avda. De Vilalba, 69",
    "sg:city":"Pontes Garcia Rodriguez",
    "sg:orig_category":"Inform\u00c1tica, Ofim\u00c1tica (estudios, Asesor\u00cda, Ingenier\u00cda, Formaci\u00d3n)",
    "sg:phone":"+34 981 44 08 40",
    "sg:postcode":"15320",
    "sg:province":"La Coru\u00f1a",
    "sg:website":"www.informouzo.com",
    "wof:name":"Mouzo Villar Jose Bernardino",
    "wof:placetype":"venue"
},
  "geometry": {"coordinates":[-7.8519802094,43.4437828064],"type":"Point"}
}