{
  "type": "Feature",
  "properties": {
    "iso:country":"ES",
    "sg:address":"Rua Taboada (de), 1",
    "sg:city":"Chantada",
    "sg:orig_category":"Notarios",
    "sg:phone":"+34 982 44 02 29",
    "sg:postcode":"27500",
    "sg:province":"Lugo",
    "wof:name":"Boisan Ca\u00f1amero Ignacio Javier",
    "wof:placetype":"venue"
},
  "geometry": {"coordinates":[-7.7677288055,42.6097297668],"type":"Point"}
}