{
  "type": "Feature",
  "properties": {
    "iso:country":"ES",
    "sg:address":"Avda Federico Garcia Lorca, 12",
    "sg:city":"Nijar",
    "sg:orig_category":"Artesan\u00cda Y Trabajos Manuales: Suministros (al Por Menor)",
    "sg:phone":"+34 950 36 04 45",
    "sg:postcode":"04100",
    "sg:province":"Almer\u00eda",
    "wof:name":"Lores Garcia Maria Dolores",
    "wof:placetype":"venue"
},
  "geometry": {"coordinates":[-2.2080829144,36.9657936096],"type":"Point"}
}