{
  "type": "Feature",
  "properties": {
    "iso:country":"ES",
    "sg:address":"Pla\u00c7 Generalitat, 8",
    "sg:city":"Vila Joiosa",
    "sg:orig_category":"Bancos",
    "sg:phone":"+34 966 81 02 80",
    "sg:postcode":"03570",
    "sg:province":"Alicante",
    "wof:name":"Banco Guipuzcoano S.a.",
    "wof:placetype":"venue"
},
  "geometry": {"coordinates":[-0.7466139793,38.3102035522],"type":"Point"}
}