{
  "type": "Feature",
  "properties": {
    "iso:country":"ES",
    "sg:address":"Carr Primavera, 5",
    "sg:city":"Burjassot",
    "sg:orig_category":"Agencias Y Agentes Comerciales, Representantes",
    "sg:phone":"+34 963 63 71 76",
    "sg:postcode":"46100",
    "sg:province":"Valencia",
    "wof:name":"Estevez Iborra Carmen",
    "wof:placetype":"venue"
},
  "geometry": {"coordinates":[-0.4143339992,39.5114479065],"type":"Point"}
}