{
  "type": "Feature",
  "properties": {
    "addr:full":"Avda Trece De Octubre, 101 Alcazares Murcia 30710",
    "addr:housenumber":"101",
    "addr:postcode":"30710",
    "addr:street":"Avda Trece De Octubre",
    "iso:country":"ES",
    "sg:address":"Avda Trece De Octubre, 101",
    "sg:city":"Alcazares",
    "sg:orig_category":"Agencias Y Asesores De Publicidad",
    "sg:phone":"+34 968 57 59 37",
    "sg:postcode":"30710",
    "sg:province":"Murcia",
    "wof:name":"Promociones Radecon S.l",
    "wof:placetype":"venue"
},
  "geometry": {"coordinates":[-0.8591089845,37.7385902405],"type":"Point"}
}