{
  "type": "Feature",
  "properties": {
    "iso:country":"ES",
    "sg:address":"Calle de Andres Llorente (de), 15",
    "sg:city":"Anchuelo",
    "sg:orig_category":"Material Y Herramientas Agr\u00cdcolas",
    "sg:phone":"+34 918 84 02 23",
    "sg:postcode":"28818",
    "sg:province":"Madrid",
    "wof:name":"Espilete S. L.",
    "wof:placetype":"venue"
},
  "geometry": {"coordinates":[-3.2685854435,40.4654922485],"type":"Point"}
}