{
  "type": "Feature",
  "properties": {
    "addr:full":"Carrer de Blanes, 13 Mataro Barcelona 08303",
    "addr:housenumber":"13",
    "addr:postcode":"08303",
    "addr:street":"Carrer De Blanes",
    "iso:country":"ES",
    "sg:address":"Carrer de Blanes, 13",
    "sg:city":"Mataro",
    "sg:orig_category":"Fabricaci\u00d3n De Su\u00c9ters Y Chalecos De Punto",
    "sg:phone":"+34 937 57 23 11",
    "sg:postcode":"08303",
    "sg:province":"Barcelona",
    "wof:name":"Generos De Punto Zovil S.a.",
    "wof:placetype":"venue"
},
  "geometry": {"coordinates":[2.4294281006,41.5490684509],"type":"Point"}
}