{
  "type": "Feature",
  "properties": {
    "addr:full":"Ctra. Lliria-olocau, S/n Benisano Valencia 46181",
    "addr:housenumber":"s",
    "addr:postcode":"46181",
    "addr:street":"Ctra. Lliria-Olocau;/ N",
    "iso:country":"ES",
    "sg:address":"Ctra. Lliria-olocau, S/n",
    "sg:city":"Benisano",
    "sg:orig_category":"Poller\u00cda Y Caza (al Por Menor)",
    "sg:phone":"+34 962 78 23 01",
    "sg:postcode":"46181",
    "sg:province":"Valencia",
    "wof:name":"Avicola Benisano S.l.",
    "wof:placetype":"venue"
},
  "geometry": {"coordinates":[-0.5707054734,39.6168632507],"type":"Point"}
}