{
  "type": "Feature",
  "properties": {
    "iso:country":"ES",
    "sg:address":"Carrer de Progres, 78",
    "sg:city":"Hospitalet Llobregat",
    "sg:orig_category":"Perfumer\u00cda, Art\u00cdculos De Ba\u00d1o (fabricaci\u00d3n, Al Por Mayor)",
    "sg:phone":"+34 934 49 52 18",
    "sg:postcode":"08904",
    "sg:province":"Barcelona",
    "wof:name":"Maite Vives Distribucion Sl",
    "wof:placetype":"venue"
},
  "geometry": {"coordinates":[2.120251894,41.3729629517],"type":"Point"}
}