{
  "type": "Feature",
  "properties": {
    "iso:country":"ES",
    "sg:address":"Calle de Buigas, 1",
    "sg:city":"Estepona",
    "sg:orig_category":"Asesor\u00cda De Formaci\u00d3n Y Gesti\u00d3n De Personal",
    "sg:phone":"+34 951 31 84 71",
    "sg:postcode":"29680",
    "sg:province":"M\u00e1laga",
    "wof:name":"Gonzalez Jimenez Manuel",
    "wof:placetype":"venue"
},
  "geometry": {"coordinates":[-5.1683459282,36.4309387207],"type":"Point"}
}