{
  "type": "Feature",
  "properties": {
    "iso:country":"ES",
    "sg:address":"Carr Alaior, 45",
    "sg:city":"Ciutadella Menorca",
    "sg:orig_category":"Agencias De Viajes",
    "sg:phone":"+34 971 48 12 07",
    "sg:postcode":"07760",
    "sg:province":"Islas Baleares",
    "sg:website":"www.zafirotoursciudadela.com",
    "wof:name":"Alzina Genestar S.c.",
    "wof:placetype":"venue"
},
  "geometry": {"coordinates":[3.8408420086,40.00207901],"type":"Point"}
}