{
  "type": "Feature",
  "properties": {
    "addr:full":"Calle de Bolivar Elorduy Julian, 1 Bilbao Vizcaya 48004",
    "addr:housenumber":"1",
    "addr:postcode":"48004",
    "addr:street":"Calle De Bolivar Elorduy Julian",
    "iso:country":"ES",
    "sg:address":"Calle de Bolivar Elorduy Julian, 1",
    "sg:city":"Bilbao",
    "sg:orig_category":"Ropa De Trabajo Y Profesionales (al Por Menor)",
    "sg:phone":"+34 944 33 00 09",
    "sg:postcode":"48004",
    "sg:province":"Vizcaya",
    "wof:name":"Proteccion Laboral Adipa S.l.",
    "wof:placetype":"venue"
},
  "geometry": {"coordinates":[-2.9151124954,43.2538757324],"type":"Point"}
}