{
  "type": "Feature",
  "properties": {
    "addr:full":"Calle de Londres, 22 Madrid Madrid 28028",
    "addr:housenumber":"22",
    "addr:postcode":"madrid;28028",
    "addr:street":"Calle De Londres",
    "iso:country":"ES",
    "sg:address":"Calle de Londres, 22",
    "sg:city":"Madrid",
    "sg:orig_category":"Productos Qu\u00cdmicos (fabricaci\u00d3n, Al Por Mayor)",
    "sg:phone":"+34 913 56 44 27",
    "sg:postcode":"28028",
    "sg:province":"Madrid",
    "wof:name":"Kemira Iberica S.a.",
    "wof:placetype":"venue"
},
  "geometry": {"coordinates":[-3.6689646244,40.4314079285],"type":"Point"}
}