{
  "type": "Feature",
  "properties": {
    "addr:full":"Rua Dr Lalinde Del Rio, 3 Portonovo Pontevedra 36970",
    "addr:housenumber":"3",
    "addr:postcode":"36970",
    "addr:street":"Rua Dr;Del Rio",
    "iso:country":"ES",
    "sg:address":"Rua Dr Lalinde Del Rio, 3",
    "sg:city":"Portonovo",
    "sg:orig_category":"Ropa Para Caballeros (al Por Menor)",
    "sg:phone":"+34 986 69 16 73",
    "sg:postcode":"36970",
    "sg:province":"Pontevedra",
    "wof:name":"Carballla Taboas Judith",
    "wof:placetype":"venue"
},
  "geometry": {"coordinates":[-8.8259830475,42.3940124512],"type":"Point"}
}