{
  "type": "Feature",
  "properties": {
    "addr:full":"S. Aguilar, S/n Seva Barcelona 08553",
    "addr:housenumber":"s / n",
    "addr:postcode":"08553",
    "addr:street":"S. Aguilar",
    "iso:country":"ES",
    "sg:address":"S. Aguilar, S/n",
    "sg:city":"Seva",
    "sg:orig_category":"Reciclaje, Desguace De Veh\u00cdculos",
    "sg:phone":"+34 938 12 46 66",
    "sg:postcode":"08553",
    "sg:province":"Barcelona",
    "wof:name":"Desballastaments Pol S.l.",
    "wof:placetype":"venue"
},
  "geometry": {"coordinates":[2.304858923,41.8166046143],"type":"Point"}
}