{
  "type": "Feature",
  "properties": {
    "addr:full":"Carrer de Rafael Gay De Montella, 10 Vic Barcelona 08500",
    "addr:housenumber":"10",
    "addr:postcode":"08500",
    "addr:street":"Carrer De Rafael Gay De Montella",
    "iso:country":"ES",
    "sg:address":"Carrer de Rafael Gay De Montella, 10",
    "sg:city":"Vic",
    "sg:orig_category":"Electricidad: Equipos Industriales, Componentes (fabricaci\u00d3n)",
    "sg:phone":"+34 938 81 42 00",
    "sg:postcode":"08500",
    "sg:province":"Barcelona",
    "sg:website":"www.infinegocio-taisa",
    "wof:name":"Tecno-automatica Industrial S. A.",
    "wof:placetype":"venue"
},
  "geometry": {"coordinates":[2.2487750053,41.918800354],"type":"Point"}
}