{
  "type": "Feature",
  "properties": {
    "addr:full":"Calle de Ricardo Provencio, 9 Riaza Segovia 40500",
    "addr:housenumber":"9",
    "addr:postcode":"40500",
    "addr:street":"Calle De Ricardo Provencio",
    "iso:country":"ES",
    "sg:address":"Calle de Ricardo Provencio, 9",
    "sg:city":"Riaza",
    "sg:orig_category":"Cajas De Ahorro",
    "sg:phone":"+34 921 55 00 42",
    "sg:postcode":"40500",
    "sg:province":"Segovia",
    "wof:name":"Caja De Ahorros Y Monte De Piedad De Segovia",
    "wof:placetype":"venue"
},
  "geometry": {"coordinates":[-3.4820048809,41.2783088684],"type":"Point"}
}