{
  "type": "Feature",
  "properties": {
    "addr:full":"Rua Catalu\u00d1a, S/n Gandara De Abajo La Coru\u00f1a 15570",
    "addr:housenumber":"s",
    "addr:postcode":"15570",
    "addr:street":"Rua Catalun\u0303A;/ N;Corun\u0303A",
    "iso:country":"ES",
    "sg:address":"Rua Catalu\u00d1a, S/n",
    "sg:city":"Gandara De Abajo",
    "sg:orig_category":"Ropa Para Se\u00d1oras Y Caballeros (al Por Menor)",
    "sg:phone":"+34 981 38 90 48",
    "sg:postcode":"15570",
    "sg:province":"La Coru\u00f1a",
    "sg:website":"www.massimodutti.com",
    "wof:name":"Grupo Massimo Dutti S.a.",
    "wof:placetype":"venue"
},
  "geometry": {"coordinates":[-8.1647539139,43.5165405273],"type":"Point"}
}