{
  "type": "Feature",
  "properties": {
    "iso:country":"ES",
    "sg:address":"Av Sant Jordi, De, S/n",
    "sg:city":"Eivissa",
    "sg:orig_category":"Inform\u00c1tica, Ofim\u00c1tica (estudios, Asesor\u00cda, Ingenier\u00cda, Formaci\u00d3n)",
    "sg:phone":"+34 971 30 40 27",
    "sg:postcode":"07800",
    "sg:province":"Islas Baleares",
    "wof:name":"Tisa Internacional Equipos Y Aplicaciones S.l.",
    "wof:placetype":"venue"
},
  "geometry": {"coordinates":[1.4198950529,38.9056243896],"type":"Point"}
}