{
  "type": "Feature",
  "properties": {
    "addr:full":"Calle de Mayor, 65 Puente Tocinos Murcia 30006",
    "addr:housenumber":"65",
    "addr:postcode":"30006",
    "addr:street":"Calle De Mayor",
    "iso:country":"ES",
    "sg:address":"Calle de Mayor, 65",
    "sg:city":"Puente Tocinos",
    "sg:orig_category":"Cajas Para Embalar",
    "sg:phone":"+34 968 30 40 16",
    "sg:postcode":"30006",
    "sg:province":"Murcia",
    "sg:website":"www.cajamar.es",
    "wof:name":"Cajamar",
    "wof:placetype":"venue"
},
  "geometry": {"coordinates":[-1.1043319702,37.992893219],"type":"Point"}
}