{
  "type": "Feature",
  "properties": {
    "addr:full":"Calle de Camino De La Virgen, Km. 0001,0 Albacete Albacete 02005",
    "addr:postcode":"02005",
    "addr:street":"Calle De Camino De La Virgen Km. 0001,0",
    "iso:country":"ES",
    "sg:address":"Calle de Camino De La Virgen, Km. 0001,0",
    "sg:city":"Albacete",
    "sg:orig_category":"Promotores Constructores",
    "sg:phone":"+34 967 58 06 79",
    "sg:postcode":"02005",
    "sg:province":"Albacete",
    "wof:name":"Granja Santo Angel S.a.",
    "wof:placetype":"venue"
},
  "geometry": {"coordinates":[-1.8623210192,39.0002479553],"type":"Point"}
}