{
  "type": "Feature",
  "properties": {
    "iso:country":"ES",
    "sg:address":"Ctra. Daganzo, Km. 0003,2",
    "sg:city":"Alcala Henares",
    "sg:orig_category":"Autom\u00d3viles Y Camiones",
    "sg:phone":"+34 918 82 93 05",
    "sg:postcode":"28806",
    "sg:province":"Madrid",
    "wof:name":"Friauto Complutense S.l.",
    "wof:placetype":"venue"
},
  "geometry": {"coordinates":[-3.422385931,40.5286216736],"type":"Point"}
}