{
  "type": "Feature",
  "properties": {
    "addr:full":"Pol Ind Malecon, S/n San Jose Rinconada Sevilla 41300",
    "addr:housenumber":"/ n",
    "addr:postcode":"41300",
    "addr:street":"Malecon S",
    "iso:country":"ES",
    "sg:address":"Pol Ind Malecon, S/n",
    "sg:city":"San Jose Rinconada",
    "sg:orig_category":"Empresas De Carpinter\u00cda Met\u00c1lica",
    "sg:phone":"+34 954 79 09 00",
    "sg:postcode":"41300",
    "sg:province":"Sevilla",
    "wof:name":"Carrasco Uceda Servando",
    "wof:placetype":"venue"
},
  "geometry": {"coordinates":[-5.9507889748,37.4823112488],"type":"Point"}
}