{
  "type": "Feature",
  "properties": {
    "iso:country":"ES",
    "sg:address":"Calle de Onda, 13",
    "sg:city":"Alzira",
    "sg:orig_category":"Negocio De Madera",
    "sg:phone":"+34 962 41 78 22",
    "sg:postcode":"46600",
    "sg:province":"Valencia",
    "wof:name":"Comercial Uni-port S. L.",
    "wof:placetype":"venue"
},
  "geometry": {"coordinates":[-0.4390990138,39.1462593079],"type":"Point"}
}