{
  "type": "Feature",
  "properties": {
    "addr:full":"E. De Santa Lucia, S/n Antequera M\u00e1laga 29200",
    "addr:postcode":"29200",
    "addr:street":"E.;Lucia S / N;Ma\u0301Laga",
    "iso:country":"ES",
    "sg:address":"E. De Santa Lucia, S/n",
    "sg:city":"Antequera",
    "sg:classifiers":[
        {
            "category":"Communications",
            "type":"Services"
        }
    ],
    "sg:phone":"+34 952 84 50 21",
    "sg:postcode":"29200",
    "sg:province":"M\u00e1laga",
    "sg:tags":[
        "televisiones",
        "y",
        "radio"
    ],
    "sg:website":"www.ondacero.es",
    "wof:name":"Uniprex-onda Cero",
    "wof:placetype":"venue"
},
  "geometry": {"coordinates":[-4.5636138916,37.0203018188],"type":"Point"}
}