{
  "type": "Feature",
  "properties": {
    "iso:country":"ES",
    "sg:address":"Pase Mesones (de Los), 5",
    "sg:city":"Lerma",
    "sg:orig_category":"M\u00c9dicos: Estomatolog\u00cda",
    "sg:phone":"+34 947 17 12 07",
    "sg:postcode":"09340",
    "sg:province":"Burgos",
    "wof:name":"Garcia Alberdi Maximino",
    "wof:placetype":"venue"
},
  "geometry": {"coordinates":[-3.7541589737,42.0238113403],"type":"Point"}
}