{
  "type": "Feature",
  "properties": {
    "addr:full":"Avda Fuenlabrada (de), 82 Humanes De Madrid Madrid 28970",
    "addr:housenumber":"82",
    "addr:postcode":"28970",
    "addr:street":"Avda Fuenlabrada De",
    "iso:country":"ES",
    "sg:address":"Avda Fuenlabrada (de), 82",
    "sg:city":"Humanes De Madrid",
    "sg:orig_category":"Alquiler De Veh\u00cdculos: Turismos Y Utilitarios",
    "sg:phone":"+34 916 04 83 45",
    "sg:postcode":"28970",
    "sg:province":"Madrid",
    "wof:name":"Jl Asociados Cars & Vans S.l.",
    "wof:placetype":"venue"
},
  "geometry": {"coordinates":[-3.813491106,40.2664680481],"type":"Point"}
}