{
  "type": "Feature",
  "properties": {
    "iso:country":"ES",
    "sg:address":"Avda Ordesa, 9",
    "sg:city":"Ainsa",
    "sg:orig_category":"Carnicer\u00cdas, Carnicer\u00cdas",
    "sg:phone":"+34 974 50 02 33",
    "sg:postcode":"22330",
    "sg:province":"Huesca",
    "wof:name":"Bielsa Castillon Jose",
    "wof:placetype":"venue"
},
  "geometry": {"coordinates":[0.1377930045,42.4156837463],"type":"Point"}
}