{
  "type": "Feature",
  "properties": {
    "addr:full":"Calle de Nueva, 3 Picazo Cuenca 16211",
    "addr:housenumber":"3",
    "addr:postcode":"16211",
    "addr:street":"Calle De Nueva",
    "iso:country":"ES",
    "sg:address":"Calle de Nueva, 3",
    "sg:city":"Picazo",
    "sg:orig_category":"Frutas Y Legumbres Frescas (al Por Mayor)",
    "sg:phone":"+34 969 38 00 29",
    "sg:postcode":"16211",
    "sg:province":"Cuenca",
    "wof:name":"Hortimancha S.coop.l.",
    "wof:placetype":"venue"
},
  "geometry": {"coordinates":[-2.0915839672,39.4455566406],"type":"Point"}
}