{
  "type": "Feature",
  "properties": {
    "addr:full":"Rua Borron (o), 13 Cambados Pontevedra 36630",
    "addr:housenumber":"13",
    "addr:postcode":"36630",
    "addr:street":"Rua Borron O",
    "iso:country":"ES",
    "sg:address":"Rua Borron (o), 13",
    "sg:city":"Cambados",
    "sg:orig_category":"Tapiceros Y Tapiceros",
    "sg:phone":"+34 986 52 09 57",
    "sg:postcode":"36630",
    "sg:province":"Pontevedra",
    "wof:name":"Proxectos Integrais Dese\u00f1o Interior Gali",
    "wof:placetype":"venue"
},
  "geometry": {"coordinates":[-8.8156194687,42.5122261047],"type":"Point"}
}