{
  "type": "Feature",
  "properties": {
    "iso:country":"ES",
    "sg:address":"Avda Concentracion Parcelaria, S/n",
    "sg:city":"Osorno",
    "sg:orig_category":"Asilos De Ancianos. Centros Privados",
    "sg:phone":"+34 979 81 74 39",
    "sg:postcode":"34460",
    "sg:province":"Palencia",
    "wof:name":"Residencia De La Tercera Edad De Osorno",
    "wof:placetype":"venue"
},
  "geometry": {"coordinates":[-4.3629641533,42.4078330994],"type":"Point"}
}