{
  "type": "Feature",
  "properties": {
    "addr:full":"Carrer de Belgica, 41 Santa Pon\u00c7a Islas Baleares 07180",
    "addr:housenumber":"41",
    "addr:postcode":"07180",
    "addr:street":"Carrer De Belgica",
    "iso:country":"ES",
    "sg:address":"Carrer de Belgica, 41",
    "sg:city":"Santa Pon\u00c7a",
    "sg:orig_category":"Inmobiliaria (agencias)",
    "sg:phone":"+34 971 23 71 63",
    "sg:postcode":"07180",
    "sg:province":"Islas Baleares",
    "wof:name":"Golf Events Mallorca S.l",
    "wof:placetype":"venue"
},
  "geometry": {"coordinates":[2.4773919582,39.5003814697],"type":"Point"}
}