{
  "type": "Feature",
  "properties": {
    "iso:country":"ES",
    "sg:address":"Calle de Estrella Polar, 4",
    "sg:city":"Madrid",
    "sg:orig_category":"Inmobiliaria (agencias)",
    "sg:phone":"+34 914 09 22 13",
    "sg:postcode":"28007",
    "sg:province":"Madrid",
    "wof:name":"House And Summer European Real State S.l.",
    "wof:placetype":"venue"
},
  "geometry": {"coordinates":[-3.6675674915,40.4102516174],"type":"Point"}
}