{
  "type": "Feature",
  "properties": {
    "addr:full":"Avda Chile, 34 Villanueva Serena Badajoz 06700",
    "addr:housenumber":"34",
    "addr:postcode":"06700",
    "addr:street":"Avda Chile",
    "iso:country":"ES",
    "sg:address":"Avda Chile, 34",
    "sg:city":"Villanueva Serena",
    "sg:orig_category":"Promotores Constructores",
    "sg:phone":"+34 924 84 34 03",
    "sg:postcode":"06700",
    "sg:province":"Badajoz",
    "wof:name":"Agrosegon S.l.",
    "wof:placetype":"venue"
},
  "geometry": {"coordinates":[-5.7907204628,38.9723587036],"type":"Point"}
}