{
  "type": "Feature",
  "properties": {
    "iso:country":"ES",
    "sg:address":"Avda Pais Valencia, 116",
    "sg:city":"Torrent",
    "sg:orig_category":"Alimentaci\u00d3n General (al Por Menor)",
    "sg:phone":"+34 961 55 55 33",
    "sg:postcode":"46900",
    "sg:province":"Valencia",
    "wof:name":"Grupo Seynava5,s.l.",
    "wof:placetype":"venue"
},
  "geometry": {"coordinates":[-0.474593997,39.4310379028],"type":"Point"}
}