{
  "type": "Feature",
  "properties": {
    "addr:full":"Carrer de Francesc Cambo, 25 S. Joan Despi Barcelona 08970",
    "addr:housenumber":"25",
    "addr:postcode":"08970",
    "addr:street":"Carrer De Francesc Cambo;S. Joan Despi",
    "iso:country":"ES",
    "sg:address":"Carrer de Francesc Cambo, 25",
    "sg:city":"S. Joan Despi",
    "sg:orig_category":"Prendas Y Chalecos De Punto (al Por Menor)",
    "sg:phone":"+34 933 73 28 61",
    "sg:postcode":"08970",
    "sg:province":"Barcelona",
    "wof:name":"Izquierdo Sanchez Maria Matilde",
    "wof:placetype":"venue"
},
  "geometry": {"coordinates":[2.0746231079,41.3688392639],"type":"Point"}
}