{
  "type": "Feature",
  "properties": {
    "iso:country":"ES",
    "sg:address":"D.irala Kalea, 2",
    "sg:city":"Bergara",
    "sg:orig_category":"Molduras, Junquillos, Listones Y Molduras Perforadas",
    "sg:phone":"+34 943 76 38 57",
    "sg:postcode":"20570",
    "sg:province":"Guip\u00f9zcoa",
    "wof:name":"Zabala Larra\u00f1aga Florentino",
    "wof:placetype":"venue"
},
  "geometry": {"coordinates":[-2.4233329296,43.1255264282],"type":"Point"}
}