{
  "type": "Feature",
  "properties": {
    "addr:full":"Pase Canalejas, 188 Salamanca Salamanca 37008",
    "addr:housenumber":"188",
    "addr:postcode":"37008",
    "addr:street":"Canalejas",
    "iso:country":"ES",
    "sg:address":"Pase Canalejas, 188",
    "sg:city":"Salamanca",
    "sg:orig_category":"Aparcamientos (infraestructuras, Accesorios)",
    "sg:phone":"+34 923 26 60 74",
    "sg:postcode":"37008",
    "sg:province":"Salamanca",
    "wof:name":"Cacho Corredera Marceliano",
    "wof:placetype":"venue"
},
  "geometry": {"coordinates":[-5.6601448059,40.9595870972],"type":"Point"}
}