{
  "type": "Feature",
  "properties": {
    "iso:country":"ES",
    "sg:address":"Calle de Ramon Y Cajal (de), 21",
    "sg:city":"Daganzo Arriba",
    "sg:orig_category":"Puertas Autom\u00c1ticas, Puertas De Garaje",
    "sg:phone":"+34 918 84 10 11",
    "sg:postcode":"28814",
    "sg:province":"Madrid",
    "sg:website":"www.combursa.com",
    "wof:name":"Grupo Combursa S.l.",
    "wof:placetype":"venue"
},
  "geometry": {"coordinates":[-3.4641358852,40.5401191711],"type":"Point"}
}