{
  "type": "Feature",
  "properties": {
    "addr:full":"Rbla. Concepcio, 43 S. Quirze Besora Barcelona 08580",
    "addr:housenumber":"43",
    "addr:postcode":"08580",
    "addr:street":"Concepcio",
    "iso:country":"ES",
    "sg:address":"Rbla. Concepcio, 43",
    "sg:city":"S. Quirze Besora",
    "sg:orig_category":"Fabricaci\u00d3n Y Refinado De Az\u00dacares",
    "sg:phone":"+34 938 52 92 16",
    "sg:postcode":"08580",
    "sg:province":"Barcelona",
    "wof:name":"Sucres Del Ter S.l.",
    "wof:placetype":"venue"
},
  "geometry": {"coordinates":[2.2155148983,42.1017684937],"type":"Point"}
}