{
  "type": "Feature",
  "properties": {
    "iso:country":"ES",
    "sg:address":"Intxaurdia Cent Com Itaroa, 5",
    "sg:city":"Huarte",
    "sg:orig_category":"Asociaciones, Organismos Culturales Y Socioeducativos",
    "sg:phone":"+34 948 34 88 33",
    "sg:postcode":"31620",
    "sg:province":"Navarra",
    "wof:name":"Paris Da-kart S.a.",
    "wof:placetype":"venue"
},
  "geometry": {"coordinates":[-1.5902739763,42.83177948],"type":"Point"}
}