{
  "type": "Feature",
  "properties": {
    "iso:country":"ES",
    "sg:address":"Avda Valdefierro, 36",
    "sg:city":"Zaragoza",
    "sg:orig_category":"Peluquer\u00cdas, Peluquer\u00cda Mixta",
    "sg:phone":"+34 976 31 21 39",
    "sg:postcode":"50012",
    "sg:province":"Zaragoza",
    "wof:name":"Nuova S.cv.",
    "wof:placetype":"venue"
},
  "geometry": {"coordinates":[-0.9296579957,41.6398468018],"type":"Point"}
}