{
  "type": "Feature",
  "properties": {
    "iso:country":"ES",
    "sg:address":"Calle de Blasco, 30",
    "sg:city":"Alca\u00f1iz",
    "sg:orig_category":"Loter\u00cda Y T\u00d3mbola",
    "sg:phone":"+34 978 83 15 86",
    "sg:postcode":"44600",
    "sg:province":"Teruel",
    "wof:name":"Bosque Margeli Maria Pilar",
    "wof:placetype":"venue"
},
  "geometry": {"coordinates":[-0.1309729964,41.0508956909],"type":"Point"}
}