{
  "type": "Feature",
  "properties": {
    "addr:full":"Calle de Plaza San Pancracio, 18 Ribaforada Navarra 31550",
    "addr:housenumber":"18",
    "addr:postcode":"31550",
    "addr:street":"Calle De Plaza San Pancracio",
    "iso:country":"ES",
    "sg:address":"Calle de Plaza San Pancracio, 18",
    "sg:city":"Ribaforada",
    "sg:orig_category":"Empresas De Carpinter\u00cda Met\u00c1lica",
    "sg:phone":"+34 948 81 95 55",
    "sg:postcode":"31550",
    "sg:province":"Navarra",
    "wof:name":"Talleres Ferromecanicos S.l.",
    "wof:placetype":"venue"
},
  "geometry": {"coordinates":[-1.5151189566,41.9949760437],"type":"Point"}
}