{
  "type": "Feature",
  "properties": {
    "addr:full":"Avda Alfonso Molina (de), 16 Santa Comba La Coru\u00f1a 15840",
    "addr:housenumber":"16",
    "addr:postcode":"15840",
    "addr:street":"Avda Alfonso Molina De;Corun\u0303A",
    "iso:country":"ES",
    "sg:address":"Avda Alfonso Molina (de), 16",
    "sg:city":"Santa Comba",
    "sg:orig_category":"Relojer\u00cda (al Por Menor, Reparaci\u00d3n)",
    "sg:phone":"+34 981 88 00 56",
    "sg:postcode":"15840",
    "sg:province":"La Coru\u00f1a",
    "wof:name":"Joyeria Romar",
    "wof:placetype":"venue"
},
  "geometry": {"coordinates":[-8.8162002563,43.0355224609],"type":"Point"}
}