{
  "type": "Feature",
  "properties": {
    "iso:country":"ES",
    "sg:address":"Ctra Villanueva (de), Km. 0001,0",
    "sg:city":"Archena",
    "sg:orig_category":"Distribuci\u00d3n De Petr\u00d3leo Y Derivados",
    "sg:phone":"+34 968 67 06 59",
    "sg:postcode":"30600",
    "sg:province":"Murcia",
    "wof:name":"Hilario Lopez E Hijos S.l.",
    "wof:placetype":"venue"
},
  "geometry": {"coordinates":[-1.3030389547,38.1182861328],"type":"Point"}
}