{
  "type": "Feature",
  "properties": {
    "iso:country":"ES",
    "sg:address":"Carretera De Linares-orcera, Km. 0048,0",
    "sg:city":"Santisteban Puerto",
    "sg:orig_category":"Agentes, Concesionarios Y Sucursales De Veh\u00cdculos",
    "sg:phone":"+34 953 40 20 63",
    "sg:postcode":"23250",
    "sg:province":"Ja\u00e9n",
    "wof:name":"Lopez Perez Santiago",
    "wof:placetype":"venue"
},
  "geometry": {"coordinates":[-3.2013289928,38.250743866],"type":"Point"}
}