{
  "type": "Feature",
  "properties": {
    "addr:full":"Carrer de Sabino Arana, 56 Barcelona Barcelona 08028",
    "addr:housenumber":"56",
    "addr:postcode":"08028",
    "addr:street":"Carrer De Sabino Arana",
    "iso:country":"ES",
    "sg:address":"Carrer de Sabino Arana, 56",
    "sg:city":"Barcelona",
    "sg:orig_category":"Doctores En Medicina",
    "sg:phone":"+34 933 30 74 03",
    "sg:postcode":"08028",
    "sg:province":"Barcelona",
    "wof:name":"Jordi Llop Juan Jose",
    "wof:placetype":"venue"
},
  "geometry": {"coordinates":[2.1234610081,41.3866577148],"type":"Point"}
}