{
  "type": "Feature",
  "properties": {
    "iso:country":"ES",
    "sg:address":"Avda Campanar, 106",
    "sg:city":"Valencia",
    "sg:orig_category":"Asociaciones Humanitarias, De Cooperaci\u00d3n, De Acci\u00d3n Social",
    "sg:phone":"+34 963 46 14 14",
    "sg:postcode":"46015",
    "sg:province":"Valencia",
    "sg:website":"www.fibrosis.org",
    "wof:name":"Federacion Espa\u00f1ola Contra La Fibrosis Quistica",
    "wof:placetype":"venue"
},
  "geometry": {"coordinates":[-0.3940069973,39.479598999],"type":"Point"}
}