{
  "type": "Feature",
  "properties": {
    "addr:full":"Calle de San Sebastian, 2 Calasparra Murcia 30420",
    "addr:housenumber":"2",
    "addr:postcode":"30420",
    "addr:street":"Calle De San Sebastian",
    "iso:country":"ES",
    "sg:address":"Calle de San Sebastian, 2",
    "sg:city":"Calasparra",
    "sg:orig_category":"Inmobiliaria (agencias)",
    "sg:phone":"+34 968 72 10 02",
    "sg:postcode":"30420",
    "sg:province":"Murcia",
    "wof:name":"Pi\u00f1ero Garcia Roque",
    "wof:placetype":"venue"
},
  "geometry": {"coordinates":[-1.6966830492,38.2310791016],"type":"Point"}
}