{
  "type": "Feature",
  "properties": {
    "addr:full":"Calle de Tendaleras, 18 Huelva Huelva 21001",
    "addr:housenumber":"18",
    "addr:postcode":"21001",
    "addr:street":"Calle De Tendaleras",
    "iso:country":"ES",
    "sg:address":"Calle de Tendaleras, 18",
    "sg:city":"Huelva",
    "sg:orig_category":"Carnicer\u00cdas, Carnicer\u00cdas",
    "sg:phone":"+34 959 24 55 37",
    "sg:postcode":"21001",
    "sg:province":"Huelva",
    "sg:website":"www.tartesso.es",
    "wof:name":"Eulogio Casta\u00d1o Rodriguez S.a.",
    "wof:placetype":"venue"
},
  "geometry": {"coordinates":[-6.9555411339,37.2557487488],"type":"Point"}
}