{
  "type": "Feature",
  "properties": {
    "addr:full":"Gta Francisco De Las Cabezas, 3 Madrid Madrid 28027",
    "addr:housenumber":"3",
    "addr:postcode":"28027",
    "addr:street":"Gta Francisco De Las Cabezas",
    "iso:country":"ES",
    "sg:address":"Gta Francisco De Las Cabezas, 3",
    "sg:city":"Madrid",
    "sg:orig_category":"Abogados",
    "sg:phone":"+34 917 41 81 51",
    "sg:postcode":"28027",
    "sg:province":"Madrid",
    "wof:name":"Escarpizo-lorenzana Martinez Jorge",
    "wof:placetype":"venue"
},
  "geometry": {"coordinates":[-3.6374430656,40.4468269348],"type":"Point"}
}