{
  "type": "Feature",
  "properties": {
    "iso:country":"ES",
    "sg:address":"Abaix, 1",
    "sg:city":"Llampaies",
    "sg:orig_category":"Agricultura: Abastecimiento Y Cosechado (negocio)",
    "sg:phone":"+34 972 79 40 28",
    "sg:postcode":"17465",
    "sg:province":"Girona",
    "wof:name":"Ramaderia Ribas S.cv.",
    "wof:placetype":"venue"
},
  "geometry": {"coordinates":[2.9636991024,42.1225204468],"type":"Point"}
}