{
  "type": "Feature",
  "properties": {
    "addr:full":"Ctra Playas, 1 Puerto Del Carmen Las Palmas 35510",
    "addr:housenumber":"1",
    "addr:postcode":"35510",
    "addr:street":"Ctra Playas",
    "iso:country":"ES",
    "sg:address":"Ctra Playas, 1",
    "sg:city":"Puerto Del Carmen",
    "sg:orig_category":"Bazares, Art\u00cdculos De Limpieza Y De Cocina (al Por Menor)",
    "sg:phone":"+34 928 51 46 72",
    "sg:postcode":"35510",
    "sg:province":"Las Palmas",
    "wof:name":"Charlie Lanza S.l.",
    "wof:placetype":"venue"
},
  "geometry": {"coordinates":[-13.6657676697,28.921163559],"type":"Point"}
}