{
  "type": "Feature",
  "properties": {
    "iso:country":"ES",
    "sg:address":"Calle de Colon, 57",
    "sg:city":"Bu\u00f1ol",
    "sg:orig_category":"Peluqueros: De Se\u00d1oras",
    "sg:phone":"+34 962 50 17 35",
    "sg:postcode":"46360",
    "sg:province":"Valencia",
    "wof:name":"Ferrus Galarza Vicenta",
    "wof:placetype":"venue"
},
  "geometry": {"coordinates":[-0.7922126055,39.4181518555],"type":"Point"}
}