{
  "type": "Feature",
  "properties": {
    "addr:full":"Carr Bonaire, 22 Mao Islas Baleares 07701",
    "addr:housenumber":"22",
    "addr:postcode":"07701",
    "addr:street":"Carr Bonaire",
    "iso:country":"ES",
    "sg:address":"Carr Bonaire, 22",
    "sg:city":"Mao",
    "sg:orig_category":"Zapatos (al Por Menor)",
    "sg:phone":"+34 971 35 03 46",
    "sg:postcode":"07701",
    "sg:province":"Islas Baleares",
    "wof:name":"Corral Vivanco Josefa",
    "wof:placetype":"venue"
},
  "geometry": {"coordinates":[4.2635660172,39.8897323608],"type":"Point"}
}