{
  "type": "Feature",
  "properties": {
    "addr:full":"Avda Reina Victoria Eugenia, 19 Cartagena Murcia 30204",
    "addr:housenumber":"19",
    "addr:postcode":"30204",
    "addr:street":"Avda Reina Victoria Eugenia",
    "iso:country":"ES",
    "sg:address":"Avda Reina Victoria Eugenia, 19",
    "sg:city":"Cartagena",
    "sg:orig_category":"Abogados",
    "sg:phone":"+34 968 12 48 74",
    "sg:postcode":"30204",
    "sg:province":"Murcia",
    "wof:name":"Segado Vazquez Maria De Los Angeles",
    "wof:placetype":"venue"
},
  "geometry": {"coordinates":[-0.9889460206,37.6097183228],"type":"Point"}
}