{
  "type": "Feature",
  "properties": {
    "iso:country":"ES",
    "sg:address":"Calle de Miami, 13",
    "sg:city":"Tablero",
    "sg:orig_category":"Fabricaci\u00d3n De Juegos Y Juguetes",
    "sg:phone":"+34 928 14 30 88",
    "sg:postcode":"35100",
    "sg:province":"Las Palmas",
    "wof:name":"Island Deal S.l.",
    "wof:placetype":"venue"
},
  "geometry": {"coordinates":[-15.6056413651,27.7692928314],"type":"Point"}
}