{
  "type": "Feature",
  "properties": {
    "addr:full":"C/ San Fernando, 19 Torrellano Alicante 03320",
    "addr:housenumber":"19",
    "addr:postcode":"03320",
    "addr:street":"C / San Fernando",
    "iso:country":"ES",
    "sg:address":"C/ San Fernando, 19",
    "sg:city":"Torrellano",
    "sg:orig_category":"Empresas De Carpinter\u00cda De Madera",
    "sg:phone":"+34 965 68 05 82",
    "sg:postcode":"03320",
    "sg:province":"Alicante",
    "wof:name":"Factory Wood Shop S.l.",
    "wof:placetype":"venue"
},
  "geometry": {"coordinates":[-0.5858690143,38.2909851074],"type":"Point"}
}