{
  "type": "Feature",
  "properties": {
    "iso:country":"ES",
    "sg:address":"Calle de Jose Leon Sanz, 2",
    "sg:city":"Sevilla",
    "sg:orig_category":"Peluqueros: De Se\u00d1oras",
    "sg:phone":"+34 954 33 81 99",
    "sg:postcode":"41010",
    "sg:province":"Sevilla",
    "wof:name":"Garcia Lara Consolacion",
    "wof:placetype":"venue"
},
  "geometry": {"coordinates":[-6.0133628845,37.380859375],"type":"Point"}
}