{
  "type": "Feature",
  "properties": {
    "iso:country":"ES",
    "sg:address":"Ctra. N. 340, Km. 0423,0",
    "sg:city":"Puebla Vicar",
    "sg:orig_category":"Arboricultura Y Producci\u00d3n De Frutas",
    "sg:phone":"+34 950 55 70 11",
    "sg:postcode":"04738",
    "sg:province":"Almer\u00eda",
    "wof:name":"Sociedad Cooperativa Andaluza Vicasol",
    "wof:placetype":"venue"
},
  "geometry": {"coordinates":[-2.635559082,36.7998008728],"type":"Point"}
}