{
  "type": "Feature",
  "properties": {
    "iso:country":"ES",
    "sg:address":"Pg Bonanova, 45",
    "sg:city":"Barcelona",
    "sg:orig_category":"Bancos",
    "sg:phone":"+34 934 17 31 61",
    "sg:postcode":"08022",
    "sg:province":"Barcelona",
    "sg:website":"www.bancosabadell.es",
    "wof:name":"Banc Sabadell S.a.",
    "wof:placetype":"venue"
},
  "geometry": {"coordinates":[2.1296980381,41.4043731689],"type":"Point"}
}