{
  "type": "Feature",
  "properties": {
    "addr:full":"Calle de Solana, 9 Torrejon Ardoz Madrid 28850",
    "addr:housenumber":"9",
    "addr:postcode":"28850",
    "addr:street":"Calle De Solana",
    "iso:country":"ES",
    "sg:address":"Calle de Solana, 9",
    "sg:city":"Torrejon Ardoz",
    "sg:orig_category":"Suministros Para Hoteles",
    "sg:phone":"+34 916 75 82 58",
    "sg:postcode":"28850",
    "sg:province":"Madrid",
    "wof:name":"Unigran Torrejon S.l.l.",
    "wof:placetype":"venue"
},
  "geometry": {"coordinates":[-3.4705770016,40.4541778564],"type":"Point"}
}