{
  "type": "Feature",
  "properties": {
    "addr:full":"Calle de Calahorra, 58 Madrid Madrid 28032",
    "addr:housenumber":"58",
    "addr:postcode":"madrid;28032",
    "addr:street":"Calle De Calahorra",
    "iso:country":"ES",
    "sg:address":"Calle de Calahorra, 58",
    "sg:city":"Madrid",
    "sg:orig_category":"Electricidad: Instaladores",
    "sg:phone":"+34 913 71 86 39",
    "sg:postcode":"28032",
    "sg:province":"Madrid",
    "wof:name":"Air-electric Proyectos E Instalaciones S",
    "wof:placetype":"venue"
},
  "geometry": {"coordinates":[-3.6122980118,40.40883255],"type":"Point"}
}