{
  "type": "Feature",
  "properties": {
    "iso:country":"ES",
    "sg:address":"Avda Andalucia, 20",
    "sg:city":"Huescar",
    "sg:orig_category":"Electricidad: Instaladores",
    "sg:phone":"+34 958 74 10 87",
    "sg:postcode":"18830",
    "sg:province":"Granada",
    "wof:name":"Pedro Martinez Lara C.b.",
    "wof:placetype":"venue"
},
  "geometry": {"coordinates":[-2.5450050831,37.8094444275],"type":"Point"}
}