{
  "type": "Feature",
  "properties": {
    "addr:full":"Calle de Duque De Alba, 6 Madrid Madrid 28012",
    "addr:housenumber":"6",
    "addr:postcode":"28012",
    "addr:street":"Calle De Duque De Alba",
    "iso:country":"ES",
    "sg:address":"Calle de Duque De Alba, 6",
    "sg:city":"Madrid",
    "sg:orig_category":"Ropa Para Ni\u00d1os (al Por Menor)",
    "sg:phone":"+34 914 29 29 13",
    "sg:postcode":"28012",
    "sg:province":"Madrid",
    "wof:name":"Setubal Novo And Company S.l.",
    "wof:placetype":"venue"
},
  "geometry": {"coordinates":[-3.7061789036,40.411655426],"type":"Point"}
}