{
  "type": "Feature",
  "properties": {
    "addr:full":"Pol Ind Fadrell, 11 Castello Plana Castell\u00f3n 12005",
    "addr:housenumber":"11",
    "addr:postcode":"12005",
    "addr:street":"Fadrell;Castello\u0301N",
    "iso:country":"ES",
    "sg:address":"Pol Ind Fadrell, 11",
    "sg:city":"Castello Plana",
    "sg:orig_category":"Transportes Por V\u00cdas Navegables",
    "sg:phone":"+34 964 24 28 85",
    "sg:postcode":"12005",
    "sg:province":"Castell\u00f3n",
    "sg:website":"www.redur.es",
    "wof:name":"Lozano Transportes S.a.u.",
    "wof:placetype":"venue"
},
  "geometry": {"coordinates":[-0.0360242017,39.9860687256],"type":"Point"}
}