{
  "type": "Feature",
  "properties": {
    "iso:country":"ES",
    "sg:address":"Calle de Nu\u00d1ez De Balboa, 3",
    "sg:city":"Palmas De Gran Canaria",
    "sg:orig_category":"Inform\u00c1tica (estudios, Servicios, Asesor\u00cda, Formaci\u00d3n)",
    "sg:phone":"+34 928 25 92 18",
    "sg:postcode":"35012",
    "sg:province":"Las Palmas",
    "wof:name":"Aplicaciones Y Soportes Informatico Paralelo S.l.",
    "wof:placetype":"venue"
},
  "geometry": {"coordinates":[-15.4299478531,28.1123638153],"type":"Point"}
}