{
  "type": "Feature",
  "properties": {
    "addr:full":"Rua Pablo Iglesias, S/n Ourense Ourense 32004",
    "addr:postcode":"32004",
    "addr:street":"Rua Pablo Iglesias S / N",
    "iso:country":"ES",
    "sg:address":"Rua Pablo Iglesias, S/n",
    "sg:city":"Ourense",
    "sg:orig_category":"Conservatorios",
    "sg:phone":"+34 988 39 10 47",
    "sg:postcode":"32004",
    "sg:province":"Ourense",
    "wof:name":"Conservatorio De Musica De Orense",
    "wof:placetype":"venue"
},
  "geometry": {"coordinates":[-7.8561310768,42.3491134644],"type":"Point"}
}