{
  "type": "Feature",
  "properties": {
    "addr:full":"Avda Pablo Iglesias (de), 61 Almeria Almer\u00eda 04003",
    "addr:housenumber":"61",
    "addr:postcode":"04003",
    "addr:street":"Avda Pablo Iglesias De",
    "iso:country":"ES",
    "sg:address":"Avda Pablo Iglesias (de), 61",
    "sg:city":"Almeria",
    "sg:orig_category":"Ropa Para Ni\u00d1os (al Por Menor)",
    "sg:phone":"+34 950 23 42 89",
    "sg:postcode":"04003",
    "sg:province":"Almer\u00eda",
    "wof:name":"Moreno Moreno Maria Del Carmen",
    "wof:placetype":"venue"
},
  "geometry": {"coordinates":[-2.4646010399,36.8447990417],"type":"Point"}
}