{
  "type": "Feature",
  "properties": {
    "addr:full":"Trva Industria De La, 58 Aviles Asturias 33401",
    "addr:housenumber":"58",
    "addr:postcode":"33401",
    "addr:street":"Trva Industria De La",
    "iso:country":"ES",
    "sg:address":"Trva Industria De La, 58",
    "sg:city":"Aviles",
    "sg:orig_category":"Distribuci\u00d3n De Petr\u00d3leo Y Derivados",
    "sg:phone":"+34 985 56 58 95",
    "sg:postcode":"33401",
    "sg:province":"Asturias",
    "wof:name":"Pescados Carbajal S. L.",
    "wof:placetype":"venue"
},
  "geometry": {"coordinates":[-5.9211349487,43.5584754944],"type":"Point"}
}