{
  "type": "Feature",
  "properties": {
    "iso:country":"ES",
    "sg:address":"Calle de Herrador, 2",
    "sg:city":"Puerto Santiago",
    "sg:orig_category":"Quincaller\u00cda (al Por Menor)",
    "sg:phone":"+34 922 86 16 24",
    "sg:postcode":"38683",
    "sg:province":"Santa Cruz De Tenerife",
    "wof:name":"Manuel Forte Herrera Sl",
    "wof:placetype":"venue"
},
  "geometry": {"coordinates":[-16.8408279419,28.2384128571],"type":"Point"}
}