{
  "type": "Feature",
  "properties": {
    "addr:full":"Plaz Segovia, 12 Valencia Valencia 46017",
    "addr:housenumber":"12",
    "addr:postcode":"46017",
    "addr:street":"Segovia",
    "iso:country":"ES",
    "sg:address":"Plaz Segovia, 12",
    "sg:city":"Valencia",
    "sg:orig_category":"Bisuter\u00cda, Joyer\u00cda, Relojer\u00cda (al Por Menor)",
    "sg:phone":"+34 963 77 38 57",
    "sg:postcode":"46017",
    "sg:province":"Valencia",
    "sg:website":"www.inicia.es/d/alpama",
    "wof:name":"Alpama Joyeros S.l.",
    "wof:placetype":"venue"
},
  "geometry": {"coordinates":[-0.3911552131,39.448841095],"type":"Point"}
}