{
  "type": "Feature",
  "properties": {
    "addr:full":"Calle de Bonal, 13 Valverde Leganes Badajoz 06130",
    "addr:housenumber":"13",
    "addr:postcode":"06130",
    "addr:street":"Calle De Bonal",
    "iso:country":"ES",
    "sg:address":"Calle de Bonal, 13",
    "sg:city":"Valverde Leganes",
    "sg:orig_category":"Carnicer\u00cdas, Carnicer\u00cdas",
    "sg:phone":"+34 924 49 65 39",
    "sg:postcode":"06130",
    "sg:province":"Badajoz",
    "wof:name":"Torres Borrallo Manuel",
    "wof:placetype":"venue"
},
  "geometry": {"coordinates":[-6.97935009,38.6704063416],"type":"Point"}
}