{
  "type": "Feature",
  "properties": {
    "addr:full":"Calle de Carmen (del), 27 Cartagena Murcia 30201",
    "addr:postcode":"30201",
    "addr:street":"Calle De Carmen Del",
    "iso:country":"ES",
    "sg:address":"Calle de Carmen (del), 27",
    "sg:city":"Cartagena",
    "sg:orig_category":"M\u00c9dicos: Estomatolog\u00cda",
    "sg:phone":"+34 968 52 59 17",
    "sg:postcode":"30201",
    "sg:province":"Murcia",
    "wof:name":"Barcelo Gutierrez Andres",
    "wof:placetype":"venue"
},
  "geometry": {"coordinates":[-0.9890540242,37.6040496826],"type":"Point"}
}