{
  "type": "Feature",
  "properties": {
    "iso:country":"ES",
    "sg:address":"Carrer de Consell De Cent, 313",
    "sg:city":"Barcelona",
    "sg:orig_category":"Ingenier\u00cda, Centros De Estudios (diversos)",
    "sg:phone":"+34 934 87 19 10",
    "sg:postcode":"08007",
    "sg:province":"Barcelona",
    "wof:name":"Perals Descamps Miguel",
    "wof:placetype":"venue"
},
  "geometry": {"coordinates":[2.1631350517,41.3893585205],"type":"Point"}
}