{
  "type": "Feature",
  "properties": {
    "addr:full":"Luga Porceyo (casares), Km. 0004,5 Casares Asturias 33392",
    "addr:postcode":"33392",
    "addr:street":"Casares Km. 0004,5",
    "iso:country":"ES",
    "sg:address":"Luga Porceyo (casares), Km. 0004,5",
    "sg:city":"Casares",
    "sg:orig_category":"Agentes, Concesionarios Y Sucursales De Veh\u00cdculos",
    "sg:phone":"+34 985 16 85 54",
    "sg:postcode":"33392",
    "sg:province":"Asturias",
    "wof:name":"Don Pelayo Motor S.a.",
    "wof:placetype":"venue"
},
  "geometry": {"coordinates":[-5.7052330971,43.5063514709],"type":"Point"}
}