{
  "type": "Feature",
  "properties": {
    "iso:country":"ES",
    "sg:address":"Calle de Mirador De La Reina, 115",
    "sg:city":"Madrid",
    "sg:orig_category":"Discapacitados",
    "sg:phone":"+34 913 76 71 90",
    "sg:postcode":"28035",
    "sg:province":"Madrid",
    "wof:name":"Fundacion Bobath",
    "wof:placetype":"venue"
},
  "geometry": {"coordinates":[-3.7239770889,40.4893951416],"type":"Point"}
}