{
  "type": "Feature",
  "properties": {
    "addr:full":"Barr El Campillo, S/n Campillo Vizcaya 48509",
    "addr:housenumber":"s / n",
    "addr:postcode":"48509",
    "addr:street":"El Campillo",
    "iso:country":"ES",
    "sg:address":"Barr El Campillo, S/n",
    "sg:city":"Campillo",
    "sg:orig_category":"Empresas De Limpieza",
    "sg:phone":"+34 946 35 32 41",
    "sg:postcode":"48509",
    "sg:province":"Vizcaya",
    "wof:name":"Eskurto S.l.",
    "wof:placetype":"venue"
},
  "geometry": {"coordinates":[-2.9316000938,43.2383995056],"type":"Point"}
}