{
  "type": "Feature",
  "properties": {
    "addr:full":"Calle de Gayria, 6 Valles Ortega Las Palmas 35638",
    "addr:housenumber":"6",
    "addr:postcode":"35638",
    "addr:street":"Calle De Gayria;Ortega Las",
    "iso:country":"ES",
    "sg:address":"Calle de Gayria, 6",
    "sg:city":"Valles Ortega",
    "sg:orig_category":"Fabricaci\u00d3n De Cervezas",
    "sg:phone":"+34 928 87 85 29",
    "sg:postcode":"35638",
    "sg:province":"Las Palmas",
    "wof:name":"Distribuciones Estella Maxorata S.l.",
    "wof:placetype":"venue"
},
  "geometry": {"coordinates":[-14.0129852295,28.3873958588],"type":"Point"}
}