{
  "type": "Feature",
  "properties": {
    "addr:full":"Plaz Nafarroa Beherea, 5 Donostia-san Sebastian Guip\u00f9zcoa 20002",
    "addr:housenumber":"5",
    "addr:postcode":"20002",
    "addr:street":"Beherea",
    "iso:country":"ES",
    "sg:address":"Plaz Nafarroa Beherea, 5",
    "sg:city":"Donostia-san Sebastian",
    "sg:orig_category":"Telas Para Tapizar, Cortinas, Pasamaner\u00cda (fabricaci\u00d3n, Al Por Mayor)",
    "sg:phone":"+34 943 29 36 11",
    "sg:postcode":"20002",
    "sg:province":"Guip\u00f9zcoa",
    "wof:name":"Ines C.b",
    "wof:placetype":"venue"
},
  "geometry": {"coordinates":[-1.9794000387,43.3173789978],"type":"Point"}
}