{
  "type": "Feature",
  "properties": {
    "iso:country":"ES",
    "sg:address":"Gartzia Goldaraz Kalea, 1",
    "sg:city":"Hernani",
    "sg:orig_category":"Muebles, Minoristas",
    "sg:phone":"+34 943 55 71 54",
    "sg:postcode":"20120",
    "sg:province":"Guip\u00f9zcoa",
    "wof:name":"Muebles Balbi Cb",
    "wof:placetype":"venue"
},
  "geometry": {"coordinates":[-1.9720569849,43.2683563232],"type":"Point"}
}