{
  "type": "Feature",
  "properties": {
    "addr:full":"Carr Metge Reynes, 3 Port D'alcudia Islas Baleares 07410",
    "addr:housenumber":"3",
    "addr:postcode":"07410",
    "addr:street":"Carr Metge Reynes",
    "iso:country":"ES",
    "sg:address":"Carr Metge Reynes, 3",
    "sg:city":"Port D'alcudia",
    "sg:orig_category":"Producci\u00d3n, Distribuci\u00d3n De Gas Butano Y Propano",
    "sg:phone":"+34 971 54 51 91",
    "sg:postcode":"07410",
    "sg:province":"Islas Baleares",
    "wof:name":"Jaime Canaves E Hijos S.l.",
    "wof:placetype":"venue"
},
  "geometry": {"coordinates":[2.9117100239,39.6136398315],"type":"Point"}
}