{
  "type": "Feature",
  "properties": {
    "addr:full":"Carrer de Gran, 20 Esparreguera Barcelona 08292",
    "addr:housenumber":"20",
    "addr:postcode":"08292",
    "addr:street":"Carrer De Gran",
    "iso:country":"ES",
    "sg:address":"Carrer de Gran, 20",
    "sg:city":"Esparreguera",
    "sg:orig_category":"Cajas De Ahorro",
    "sg:phone":"+34 937 08 01 83",
    "sg:postcode":"08292",
    "sg:province":"Barcelona",
    "wof:name":"Caixa De Girona",
    "wof:placetype":"venue"
},
  "geometry": {"coordinates":[1.8689899445,41.5402984619],"type":"Point"}
}