{
  "type": "Feature",
  "properties": {
    "iso:country":"ES",
    "sg:address":"Calle de Askatasun Bidea, 1",
    "sg:city":"Bermeo",
    "sg:orig_category":"Molduras, Junquillos, Listones Y Molduras Perforadas",
    "sg:phone":"+34 946 88 28 41",
    "sg:postcode":"48370",
    "sg:province":"Vizcaya",
    "wof:name":"Jose Gorordo ( Bar Itsas-ondo ).",
    "wof:placetype":"venue"
},
  "geometry": {"coordinates":[-2.7239634991,43.418384552],"type":"Point"}
}