{
  "type": "Feature",
  "properties": {
    "iso:country":"ES",
    "sg:address":"Gta Rosales, S/n",
    "sg:city":"Aranda Duero",
    "sg:orig_category":"Centros De Educaci\u00d3n Especial",
    "sg:phone":"+34 947 54 62 82",
    "sg:postcode":"09400",
    "sg:province":"Burgos",
    "wof:name":"Colegio Publico Fernan Gonzalez",
    "wof:placetype":"venue"
},
  "geometry": {"coordinates":[-3.6908290386,41.6658554077],"type":"Point"}
}