{
  "type": "Feature",
  "properties": {
    "addr:full":"Calle de Moriones, 47 Torrevieja Alicante 03180",
    "addr:housenumber":"47",
    "addr:postcode":"03180",
    "addr:street":"Calle De Moriones",
    "iso:country":"ES",
    "sg:address":"Calle de Moriones, 47",
    "sg:city":"Torrevieja",
    "sg:orig_category":"M\u00c9dicos: Estomatolog\u00cda",
    "sg:phone":"+34 965 71 07 67",
    "sg:postcode":"03180",
    "sg:province":"Alicante",
    "wof:name":"Clinica Dental Sol S.l.",
    "wof:placetype":"venue"
},
  "geometry": {"coordinates":[-0.6536790133,38.0173606873],"type":"Point"}
}