{
  "type": "Feature",
  "properties": {
    "iso:country":"ES",
    "sg:address":"Calle de Luis Lopez Oses, 26",
    "sg:city":"Arenas -areeta",
    "sg:orig_category":"Frutas, Legumbres Frescas Y Tempranas (al Por Menor)",
    "sg:phone":"+34 944 64 24 13",
    "sg:postcode":"48930",
    "sg:province":"Vizcaya",
    "wof:name":"Gomez Salado Rafael",
    "wof:placetype":"venue"
},
  "geometry": {"coordinates":[-3.0068490505,43.3258285522],"type":"Point"}
}