{
  "type": "Feature",
  "properties": {
    "addr:full":"Carrer de Felip Ii, 126 Barcelona Barcelona 08027",
    "addr:housenumber":"126",
    "addr:postcode":"08027",
    "addr:street":"Carrer De Felip Ii",
    "iso:country":"ES",
    "sg:address":"Carrer de Felip Ii, 126",
    "sg:city":"Barcelona",
    "sg:orig_category":"Supermercados Y Hipermercados",
    "sg:phone":"+34 933 52 73 01",
    "sg:postcode":"08027",
    "sg:province":"Barcelona",
    "sg:website":"www.capraboacasa.com",
    "wof:name":"Caprabo S.a.",
    "wof:placetype":"venue"
},
  "geometry": {"coordinates":[2.1848499775,41.4221992493],"type":"Point"}
}