{
  "type": "Feature",
  "properties": {
    "addr:full":"Calle de Alpedrete, 7 Estacion Madrid 28400",
    "addr:housenumber":"7 estacion",
    "addr:postcode":"28400",
    "addr:street":"Calle De Alpedrete",
    "iso:country":"ES",
    "sg:address":"Calle de Alpedrete, 7",
    "sg:city":"Estacion",
    "sg:orig_category":"Cristaler\u00cdas",
    "sg:phone":"+34 918 50 65 63",
    "sg:postcode":"28400",
    "sg:province":"Madrid",
    "sg:website":"www.cristalerias-villalba.com",
    "wof:name":"Cristaleria Villalba S.l.",
    "wof:placetype":"venue"
},
  "geometry": {"coordinates":[-3.7003455162,40.4166908264],"type":"Point"}
}