{
  "type": "Feature",
  "properties": {
    "addr:full":"Plaz Aurora (de La), 1 Motril Granada 18600",
    "addr:housenumber":"1",
    "addr:postcode":"18600",
    "addr:street":"Aurora De La",
    "iso:country":"ES",
    "sg:address":"Plaz Aurora (de La), 1",
    "sg:city":"Motril",
    "sg:classifiers":[
        {
            "category":"Personal",
            "subcategory":"Barber",
            "type":"Services"
        }
    ],
    "sg:phone":"+34 958 60 06 88",
    "sg:postcode":"18600",
    "sg:province":"Granada",
    "sg:tags":[
        "caballeros",
        "de",
        "peluqueros"
    ],
    "wof:name":"Rivas Morente Felix",
    "wof:placetype":"venue"
},
  "geometry": {"coordinates":[-3.5167350769,36.7456932068],"type":"Point"}
}