{
  "type": "Feature",
  "properties": {
    "addr:full":"Carrer de Castelao, 42 Hospitalet Llobregat Barcelona 08902",
    "addr:housenumber":"42",
    "addr:postcode":"08902",
    "addr:street":"Carrer De Castelao",
    "iso:country":"ES",
    "sg:address":"Carrer de Castelao, 42",
    "sg:city":"Hospitalet Llobregat",
    "sg:orig_category":"Mec\u00c1nico Del Autom\u00d3vil",
    "sg:phone":"+34 934 22 13 83",
    "sg:postcode":"08902",
    "sg:province":"Barcelona",
    "wof:name":"Gavalda Mas Miguel",
    "wof:placetype":"venue"
},
  "geometry": {"coordinates":[2.1237399578,41.3645515442],"type":"Point"}
}