{
  "type": "Feature",
  "properties": {
    "addr:full":"Calle de Boticas, 19 Mula Murcia 30170",
    "addr:housenumber":"19",
    "addr:postcode":"30170",
    "addr:street":"Calle De Boticas",
    "iso:country":"ES",
    "sg:address":"Calle de Boticas, 19",
    "sg:city":"Mula",
    "sg:orig_category":"Lencer\u00cda Femenina, Corseter\u00cda, Trajes De Ba\u00d1o (al Por Menor)",
    "sg:phone":"+34 968 66 28 22",
    "sg:postcode":"30170",
    "sg:province":"Murcia",
    "wof:name":"Valero Cascales Maria Jesus",
    "wof:placetype":"venue"
},
  "geometry": {"coordinates":[-1.4913409948,38.0414237976],"type":"Point"}
}