{
  "type": "Feature",
  "properties": {
    "addr:full":"Calle de Madrid, 3 Burgos Burgos 09002",
    "addr:housenumber":"3",
    "addr:postcode":"09002",
    "addr:street":"Calle De Madrid",
    "iso:country":"ES",
    "sg:address":"Calle de Madrid, 3",
    "sg:city":"Burgos",
    "sg:orig_category":"Molduras, Junquillos, Listones Y Molduras Perforadas",
    "sg:phone":"+34 947 26 59 81",
    "sg:postcode":"09002",
    "sg:province":"Burgos",
    "wof:name":"Quintana Ortega Juan Jose",
    "wof:placetype":"venue"
},
  "geometry": {"coordinates":[-3.7025170326,42.3388633728],"type":"Point"}
}