{
  "type": "Feature",
  "properties": {
    "addr:full":"Calle de Vicente Aleixandre, 31 Cox Alicante 03350",
    "addr:housenumber":"31",
    "addr:postcode":"03350",
    "addr:street":"Calle De Vicente Aleixandre",
    "iso:country":"ES",
    "sg:address":"Calle de Vicente Aleixandre, 31",
    "sg:city":"Cox",
    "sg:orig_category":"Alimentaci\u00d3n General (al Por Menor)",
    "sg:phone":"+34 966 75 04 62",
    "sg:postcode":"03350",
    "sg:province":"Alicante",
    "wof:name":"Bernabeu Pic Trinidad",
    "wof:placetype":"venue"
},
  "geometry": {"coordinates":[-0.8855350018,38.1399688721],"type":"Point"}
}