{
  "type": "Feature",
  "properties": {
    "addr:full":"Calle de Victoriano Cremer, 5 Le\u00f3n Le\u00f3n 24007",
    "addr:housenumber":"5",
    "addr:postcode":"24007",
    "addr:street":"Calle De Victoriano Cremer;Leo\u0301N",
    "iso:country":"ES",
    "sg:address":"Calle de Victoriano Cremer, 5",
    "sg:city":"Le\u00f3n",
    "sg:orig_category":"Contenedores (mercanc\u00cdas)",
    "sg:phone":"+34 987 23 09 16",
    "sg:postcode":"24007",
    "sg:province":"Le\u00f3n",
    "wof:name":"Zapico Rodriguez Anacleto Jesus",
    "wof:placetype":"venue"
},
  "geometry": {"coordinates":[-5.5635271072,42.606590271],"type":"Point"}
}