{
  "type": "Feature",
  "properties": {
    "iso:country":"ES",
    "sg:address":"Urb Las Lagunillas, 17",
    "sg:city":"Coria",
    "sg:orig_category":"Mec\u00c1nico Del Autom\u00d3vil",
    "sg:phone":"+34 927 50 62 52",
    "sg:postcode":"10800",
    "sg:province":"C\u00e1ceres",
    "wof:name":"Talleres Rodriguez Marquez C.b.",
    "wof:placetype":"venue"
},
  "geometry": {"coordinates":[-6.5274357796,39.9835395813],"type":"Point"}
}