{
  "type": "Feature",
  "properties": {
    "addr:full":"Calle de Juan Ismael, 6 Ejido Las Palmas 35200",
    "addr:housenumber":"6",
    "addr:postcode":"35200",
    "addr:street":"Calle De Juan Ismael;Las Palmas",
    "iso:country":"ES",
    "sg:address":"Calle de Juan Ismael, 6",
    "sg:city":"Ejido",
    "sg:orig_category":"Alimentaci\u00d3n General (al Por Menor)",
    "sg:phone":"+34 928 69 05 96",
    "sg:postcode":"35200",
    "sg:province":"Las Palmas",
    "wof:name":"Sanchez Macias Antonio",
    "wof:placetype":"venue"
},
  "geometry": {"coordinates":[-15.4250087738,27.9897003174],"type":"Point"}
}