{
  "type": "Feature",
  "properties": {
    "iso:country":"ES",
    "sg:address":"Carr Salt De L'aigua, 5",
    "sg:city":"Manises",
    "sg:orig_category":"Madera Para Construcci\u00d3n E Industria",
    "sg:phone":"+34 961 53 35 06",
    "sg:postcode":"46940",
    "sg:province":"Valencia",
    "sg:website":"www.levantinadeparquets.com",
    "wof:name":"Levantina De Parquets S.r. L.",
    "wof:placetype":"venue"
},
  "geometry": {"coordinates":[-0.4669575989,39.487739563],"type":"Point"}
}