{
  "type": "Feature",
  "properties": {
    "addr:full":"Calle de Bolsa, 35 Sanlucar De Barrameda C\u00e1diz 11540",
    "addr:housenumber":"35",
    "addr:postcode":"11540",
    "addr:street":"Calle De Bolsa;Ca\u0301Diz",
    "iso:country":"ES",
    "sg:address":"Calle de Bolsa, 35",
    "sg:city":"Sanlucar De Barrameda",
    "sg:orig_category":"Promotores Constructores",
    "sg:phone":"+34 956 36 18 75",
    "sg:postcode":"11540",
    "sg:province":"C\u00e1diz",
    "wof:name":"Coprasa",
    "wof:placetype":"venue"
},
  "geometry": {"coordinates":[-6.3535089493,36.7797698975],"type":"Point"}
}