{
  "type": "Feature",
  "properties": {
    "iso:country":"ES",
    "sg:address":"Carr Parets, 1",
    "sg:city":"Bascara",
    "sg:orig_category":"Electrodom\u00c9sticos (al Por Menor)",
    "sg:phone":"+34 972 56 00 19",
    "sg:postcode":"17483",
    "sg:province":"Girona",
    "wof:name":"Soler Y Noguer S.l.",
    "wof:placetype":"venue"
},
  "geometry": {"coordinates":[2.9103629589,42.1592712402],"type":"Point"}
}