{
  "type": "Feature",
  "properties": {
    "iso:country":"ES",
    "sg:address":"Rua Ourense, 59",
    "sg:city":"Sarreaus",
    "sg:orig_category":"Carnicer\u00cdas, Carnicer\u00cdas",
    "sg:phone":"+34 988 45 40 13",
    "sg:postcode":"32638",
    "sg:province":"Ourense",
    "wof:name":"Nova Era S.c.",
    "wof:placetype":"venue"
},
  "geometry": {"coordinates":[-7.6044688225,42.0873184204],"type":"Point"}
}