{
  "type": "Feature",
  "properties": {
    "addr:full":"Calle de Segovia, S/n Linea De La Concepcion C\u00e1diz 11300",
    "addr:housenumber":"/ n",
    "addr:postcode":"11300",
    "addr:street":"Calle De Segovia S;Ca\u0301Diz",
    "iso:country":"ES",
    "sg:address":"Calle de Segovia, S/n",
    "sg:city":"Linea De La Concepcion",
    "sg:orig_category":"Asociaciones Humanitarias, De Cooperaci\u00d3n, De Acci\u00d3n Social",
    "sg:phone":"+34 956 17 67 74",
    "sg:postcode":"11300",
    "sg:province":"C\u00e1diz",
    "wof:name":"Asociacion Alatim",
    "wof:placetype":"venue"
},
  "geometry": {"coordinates":[-5.3548126221,36.1730422974],"type":"Point"}
}