{
  "type": "Feature",
  "properties": {
    "iso:country":"ES",
    "sg:address":"Avda Gasteiz, 91",
    "sg:city":"Vitoria-gasteiz",
    "sg:orig_category":"Electrodom\u00c9sticos (al Por Menor)",
    "sg:phone":"+34 945 24 49 94",
    "sg:postcode":"01009",
    "sg:province":"\u00c1lava",
    "wof:name":"Fuente Pascual Gabriel",
    "wof:placetype":"venue"
},
  "geometry": {"coordinates":[-2.6804990768,42.8537979126],"type":"Point"}
}