{
  "type": "Feature",
  "properties": {
    "iso:country":"ES",
    "sg:address":"Calle de Estacion (la), S/n",
    "sg:city":"Cantoria",
    "sg:orig_category":"Asociaciones De Vecinos, Centros De Juventud",
    "sg:phone":"+34 950 63 48 12",
    "sg:postcode":"04850",
    "sg:province":"Almer\u00eda",
    "wof:name":"Grupo De Accion Local Almanzora-proder",
    "wof:placetype":"venue"
},
  "geometry": {"coordinates":[-2.1366150379,37.3473739624],"type":"Point"}
}