{
  "type": "Feature",
  "properties": {
    "addr:full":"Calle de Alcala, 8 Caba\u00d1uelas Almer\u00eda 04738",
    "addr:housenumber":"8",
    "addr:postcode":"04738",
    "addr:street":"Calle De Alcala;Almeri\u0301A",
    "iso:country":"ES",
    "sg:address":"Calle de Alcala, 8",
    "sg:city":"Caba\u00d1uelas",
    "sg:orig_category":"Farmacias",
    "sg:phone":"+34 950 55 42 25",
    "sg:postcode":"04738",
    "sg:province":"Almer\u00eda",
    "wof:name":"Garcia-valdecasas Valverde Maria Jesus",
    "wof:placetype":"venue"
},
  "geometry": {"coordinates":[-2.4679217339,36.8401641846],"type":"Point"}
}