{
  "type": "Feature",
  "properties": {
    "addr:full":"C/ Sant Vicent, 21 Elche Alicante 03202",
    "addr:housenumber":"21",
    "addr:postcode":"03202",
    "addr:street":"C / Sant Vicent",
    "iso:country":"ES",
    "sg:address":"C/ Sant Vicent, 21",
    "sg:city":"Elche",
    "sg:orig_category":"Institutos De Belleza",
    "sg:phone":"+34 965 45 76 10",
    "sg:postcode":"03202",
    "sg:province":"Alicante",
    "wof:name":"Sansano Sarabia Maria Asuncion",
    "wof:placetype":"venue"
},
  "geometry": {"coordinates":[-0.694265008,38.2680206299],"type":"Point"}
}