{
  "type": "Feature",
  "properties": {
    "addr:full":"Calle de Valle Inclan, 4 Cehegin Murcia 30430",
    "addr:housenumber":"4",
    "addr:postcode":"30430",
    "addr:street":"Calle De Valle Inclan",
    "iso:country":"ES",
    "sg:address":"Calle de Valle Inclan, 4",
    "sg:city":"Cehegin",
    "sg:orig_category":"Institutos De Belleza",
    "sg:phone":"+34 968 74 05 40",
    "sg:postcode":"30430",
    "sg:province":"Murcia",
    "wof:name":"Abril Sanchez Maria",
    "wof:placetype":"venue"
},
  "geometry": {"coordinates":[-1.796925,38.092079],"type":"Point"}
}