{
  "type": "Feature",
  "properties": {
    "addr:full":"Calle de Cochabamba, 21 Madrid Madrid 28016",
    "addr:housenumber":"21",
    "addr:postcode":"madrid;28016",
    "addr:street":"Calle De Cochabamba",
    "iso:country":"ES",
    "sg:address":"Calle de Cochabamba, 21",
    "sg:city":"Madrid",
    "sg:orig_category":"Inmobiliaria (agencias)",
    "sg:phone":"+34 914 57 25 08",
    "sg:postcode":"28016",
    "sg:province":"Madrid",
    "wof:name":"Sistemas De Arrendamientos Y Localizaciones S.a.",
    "wof:placetype":"venue"
},
  "geometry": {"coordinates":[-3.6795120239,40.4561195374],"type":"Point"}
}