{
  "type": "Feature",
  "properties": {
    "addr:full":"Av Canaletes, 55 Cerdanyola Valles Barcelona 08290",
    "addr:housenumber":"55",
    "addr:postcode":"08290",
    "addr:street":"Av Canaletes;Valles Barcelona",
    "iso:country":"ES",
    "sg:address":"Av Canaletes, 55",
    "sg:city":"Cerdanyola Valles",
    "sg:orig_category":"Arquitectos",
    "sg:phone":"+34 935 80 31 75",
    "sg:postcode":"08290",
    "sg:province":"Barcelona",
    "wof:name":"Fernandez Rascado Jaime",
    "wof:placetype":"venue"
},
  "geometry": {"coordinates":[2.1515500546,41.4837188721],"type":"Point"}
}