{
  "type": "Feature",
  "properties": {
    "addr:full":"Pg Doctor Moragas, 187 Barbera Valles Barcelona 08210",
    "addr:housenumber":"187",
    "addr:postcode":"08210",
    "addr:street":"Pg Doctor Moragas",
    "iso:country":"ES",
    "sg:address":"Pg Doctor Moragas, 187",
    "sg:city":"Barbera Valles",
    "sg:orig_category":"Radiocomunicaciones, Telefon\u00cda M\u00d3vil, Radiomensajer\u00cda: Servicios, Comercializaci\u00d3n",
    "sg:phone":"+34 902 31 10 04",
    "sg:postcode":"08210",
    "sg:province":"Barcelona",
    "wof:name":"Vetel Comunicaciones S.l.",
    "wof:placetype":"venue"
},
  "geometry": {"coordinates":[2.124104023,41.5158004761],"type":"Point"}
}