{
  "type": "Feature",
  "properties": {
    "addr:full":"Calle de Camino Viejo De Leganes, 261 Madrid Madrid 28025",
    "addr:housenumber":"261",
    "addr:postcode":"28025",
    "addr:street":"Calle De Camino Viejo De Leganes",
    "iso:country":"ES",
    "sg:address":"Calle de Camino Viejo De Leganes, 261",
    "sg:city":"Madrid",
    "sg:orig_category":"Tapicer\u00cdas",
    "sg:phone":"+34 915 60 74 55",
    "sg:postcode":"28025",
    "sg:province":"Madrid",
    "wof:name":"Alcazar Alonso Juan",
    "wof:placetype":"venue"
},
  "geometry": {"coordinates":[-3.7310230732,40.3813209534],"type":"Point"}
}