{
  "type": "Feature",
  "properties": {
    "addr:full":"Calle de Real, 14 Horcajo Santiago Cuenca 16410",
    "addr:housenumber":"14",
    "addr:postcode":"16410",
    "addr:street":"Calle De Real;Cuenca",
    "iso:country":"ES",
    "sg:address":"Calle de Real, 14",
    "sg:city":"Horcajo Santiago",
    "sg:orig_category":"Alimentaci\u00d3n General (al Por Menor)",
    "sg:phone":"+34 969 12 71 43",
    "sg:postcode":"16410",
    "sg:province":"Cuenca",
    "wof:name":"La Tia Isabel S.l.",
    "wof:placetype":"venue"
},
  "geometry": {"coordinates":[-2.9965760708,39.8429107666],"type":"Point"}
}