{
  "type": "Feature",
  "properties": {
    "iso:country":"ES",
    "sg:address":"Carrer de Major, 13",
    "sg:city":"Riba-roja D'ebre",
    "sg:orig_category":"Electrodom\u00c9sticos (fabricaci\u00d3n, Al Por Mayor)",
    "sg:phone":"+34 977 41 65 54",
    "sg:postcode":"43790",
    "sg:province":"Tarragona",
    "wof:name":"Esteve Riba-roja S.l.",
    "wof:placetype":"venue"
},
  "geometry": {"coordinates":[1.2784659863,41.1214179993],"type":"Point"}
}