{
  "type": "Feature",
  "properties": {
    "iso:country":"ES",
    "sg:address":"Carr Manuel Fdez Marquez, 72",
    "sg:city":"Badalona",
    "sg:orig_category":"Sales (al Por Mayor)",
    "sg:phone":"+34 933 99 33 77",
    "sg:postcode":"08918",
    "sg:province":"Barcelona",
    "wof:name":"Giorno Spress S.l.",
    "wof:placetype":"venue"
},
  "geometry": {"coordinates":[2.2356181145,41.4323425293],"type":"Point"}
}