{
  "type": "Feature",
  "properties": {
    "iso:country":"ES",
    "sg:address":"Ctra Castellar, 119",
    "sg:city":"Terrassa",
    "sg:orig_category":"Confecci\u00d3n De Ropa Interior",
    "sg:phone":"+34 937 85 20 00",
    "sg:postcode":"08222",
    "sg:province":"Barcelona",
    "wof:name":"Lenceria Mitjans S. A.",
    "wof:placetype":"venue"
},
  "geometry": {"coordinates":[2.0250089169,41.5676689148],"type":"Point"}
}