{
  "type": "Feature",
  "properties": {
    "iso:country":"ES",
    "sg:address":"Calle de Pedro De Valdivia, 18",
    "sg:city":"Villafranca De Los Barros",
    "sg:orig_category":"Maquinaria Para Industrias Diversas",
    "sg:phone":"+34 924 52 46 42",
    "sg:postcode":"06220",
    "sg:province":"Badajoz",
    "wof:name":"Lopez Villarroya Jose",
    "wof:placetype":"venue"
},
  "geometry": {"coordinates":[-6.3448843956,38.559677124],"type":"Point"}
}