{
  "type": "Feature",
  "properties": {
    "addr:full":"Trac, S/n Almodovar C\u00f3rdoba 14720",
    "addr:housenumber":"s / n",
    "addr:postcode":"14720",
    "addr:street":"Trac",
    "iso:country":"ES",
    "sg:address":"Trac, S/n",
    "sg:city":"Almodovar",
    "sg:orig_category":"Producci\u00d3n, Venta De Productos De Agricultura Biol\u00d3gica",
    "sg:phone":"+34 957 33 83 46",
    "sg:postcode":"14720",
    "sg:province":"C\u00f3rdoba",
    "wof:name":"Abecera S.l.",
    "wof:placetype":"venue"
},
  "geometry": {"coordinates":[-4.997446,37.85149],"type":"Point"}
}