{
  "type": "Feature",
  "properties": {
    "iso:country":"ES",
    "sg:address":"Rua Veiga (a), Km. 0518,5",
    "sg:city":"Monforte De Lemos",
    "sg:orig_category":"Asociaciones De Vecinos, Centros De Juventud",
    "sg:phone":"+34 982 41 60 45",
    "sg:postcode":"27400",
    "sg:province":"Lugo",
    "wof:name":"Sociedad Para O Desenvolvemento Comarcal De Galicia",
    "wof:placetype":"venue"
},
  "geometry": {"coordinates":[-7.5172939301,42.5221710205],"type":"Point"}
}