{
  "type": "Feature",
  "properties": {
    "iso:country":"ES",
    "sg:address":"Avda Juventud (de La), 27",
    "sg:city":"Avila",
    "sg:orig_category":"Financiaci\u00d3n Y Cr\u00c9ditos",
    "sg:phone":"+34 920 25 15 35",
    "sg:postcode":"05003",
    "sg:province":"\u00c1vila",
    "wof:name":"Toledano Garcia Francisco Javier",
    "wof:placetype":"venue"
},
  "geometry": {"coordinates":[-4.6840391159,40.6470985413],"type":"Point"}
}