{
  "type": "Feature",
  "properties": {
    "addr:full":"Crt Roda-almodovar, Km. 0053,0 Villalgordo Jucar Albacete 02636",
    "addr:postcode":"02636",
    "addr:street":"Roda-Almodovar Km. 0053,0 Villalgordo",
    "iso:country":"ES",
    "sg:address":"Crt Roda-almodovar, Km. 0053,0",
    "sg:city":"Villalgordo Jucar",
    "sg:orig_category":"Empresas De Carpinter\u00cda Met\u00c1lica",
    "sg:phone":"+34 967 45 53 19",
    "sg:postcode":"02636",
    "sg:province":"Albacete",
    "wof:name":"Francisco Javier Serna Toboso Y Antonio Serna Toboso Cdad.",
    "wof:placetype":"venue"
},
  "geometry": {"coordinates":[-2.0632429123,39.296333313],"type":"Point"}
}