{
  "type": "Feature",
  "properties": {
    "addr:full":"Carrer de Concepcion Arenal, 55 Barcelona Barcelona 08027",
    "addr:housenumber":"55",
    "addr:postcode":"08027",
    "addr:street":"Carrer De Concepcion Arenal",
    "iso:country":"ES",
    "sg:address":"Carrer de Concepcion Arenal, 55",
    "sg:city":"Barcelona",
    "sg:orig_category":"Textiles: Suministros Y Accesorios Para Industrias (fabricaci\u00d3n, Negocio)",
    "sg:phone":"+34 934 08 09 22",
    "sg:postcode":"08027",
    "sg:province":"Barcelona",
    "wof:name":"Mielgo Dominguez Bienvenido Claudio",
    "wof:placetype":"venue"
},
  "geometry": {"coordinates":[2.1837949753,41.4211158752],"type":"Point"}
}