{
  "type": "Feature",
  "properties": {
    "addr:full":"Plaz Coso, 2 Pe\u00f1afiel Valladolid 47300",
    "addr:housenumber":"2",
    "addr:postcode":"47300",
    "addr:street":"Coso",
    "iso:country":"ES",
    "sg:address":"Plaz Coso, 2",
    "sg:city":"Pe\u00f1afiel",
    "sg:orig_category":"Oficinas De Turismo, Asociaciones De Iniciativa",
    "sg:phone":"+34 983 87 80 01",
    "sg:postcode":"47300",
    "sg:province":"Valladolid",
    "sg:website":"www.turismopenafile.com",
    "wof:name":"Turifiel S. L. U.",
    "wof:placetype":"venue"
},
  "geometry": {"coordinates":[-4.1158537865,41.6017112732],"type":"Point"}
}