{
  "type": "Feature",
  "properties": {
    "addr:full":"Calle de Real, 107 S. Fernando C\u00e1diz 11100",
    "addr:housenumber":"107",
    "addr:postcode":"11100",
    "addr:street":"Calle De Real;S. Fernando Ca\u0301Diz",
    "iso:country":"ES",
    "sg:address":"Calle de Real, 107",
    "sg:city":"S. Fernando",
    "sg:orig_category":"M\u00c9dicos: Pediatr\u00cda. Enfermedades De Los Ni\u00d1os",
    "sg:phone":"+34 956 88 16 81",
    "sg:postcode":"11100",
    "sg:province":"C\u00e1diz",
    "wof:name":"Casanova Bellido Manuel",
    "wof:placetype":"venue"
},
  "geometry": {"coordinates":[-6.1966171265,36.4654960632],"type":"Point"}
}