{
  "type": "Feature",
  "properties": {
    "iso:country":"ES",
    "sg:address":"Calle de Orgaz, 6",
    "sg:city":"Torrijos",
    "sg:orig_category":"Transporte En General",
    "sg:phone":"+34 925 76 22 21",
    "sg:postcode":"45500",
    "sg:province":"Toledo",
    "wof:name":"Coaliment Castilla S.a.u.",
    "wof:placetype":"venue"
},
  "geometry": {"coordinates":[-4.2822418213,39.9870796204],"type":"Point"}
}