{
  "type": "Feature",
  "properties": {
    "iso:country":"ES",
    "sg:address":"Calle de Mayor, 22",
    "sg:city":"Lecera",
    "sg:orig_category":"Asistencia Social",
    "sg:phone":"+34 976 83 25 89",
    "sg:postcode":"50131",
    "sg:province":"Zaragoza",
    "wof:name":"Comarca Campo De Belchite",
    "wof:placetype":"venue"
},
  "geometry": {"coordinates":[-0.7098469734,41.2039718628],"type":"Point"}
}