{
  "type": "Feature",
  "properties": {
    "addr:full":"Calle de Viriato, 27 Linares Ja\u00e9n 23700",
    "addr:housenumber":"27",
    "addr:postcode":"23700",
    "addr:street":"Calle De Viriato;Jae\u0301N",
    "iso:country":"ES",
    "sg:address":"Calle de Viriato, 27",
    "sg:city":"Linares",
    "sg:orig_category":"Asociaciones, Organismos Culturales Y Socioeducativos",
    "sg:phone":"+34 953 69 24 08",
    "sg:postcode":"23700",
    "sg:province":"Ja\u00e9n",
    "wof:name":"Asociacion Amigos De Manuel Lozano Garrido-lolo",
    "wof:placetype":"venue"
},
  "geometry": {"coordinates":[-3.6299085617,38.0947036743],"type":"Point"}
}