{
  "type": "Feature",
  "properties": {
    "addr:full":"Rua Alfonso R Castelao, 8 Cambados Pontevedra 36630",
    "addr:housenumber":"8",
    "addr:postcode":"36630",
    "addr:street":"Rua Alfonso R Castelao",
    "iso:country":"ES",
    "sg:address":"Rua Alfonso R Castelao, 8",
    "sg:city":"Cambados",
    "sg:orig_category":"Empresarios",
    "sg:phone":"+34 986 54 24 11",
    "sg:postcode":"36630",
    "sg:province":"Pontevedra",
    "wof:name":"Promocion Y Construccion Martiare S.l.",
    "wof:placetype":"venue"
},
  "geometry": {"coordinates":[-8.8135643005,42.5124855042],"type":"Point"}
}