{
  "type": "Feature",
  "properties": {
    "addr:full":"Avda Marques De Los Velez, 16 Vista Alegre Murcia 30008",
    "addr:housenumber":"16",
    "addr:postcode":"30008",
    "addr:street":"Avda Marques De Los Velez",
    "iso:country":"ES",
    "sg:address":"Avda Marques De Los Velez, 16",
    "sg:city":"Vista Alegre",
    "sg:orig_category":"Alimentaci\u00d3n General (al Por Menor)",
    "sg:phone":"+34 968 23 32 64",
    "sg:postcode":"30008",
    "sg:province":"Murcia",
    "wof:name":"Hernandez Cerezo Jose",
    "wof:placetype":"venue"
},
  "geometry": {"coordinates":[-1.1288950443,37.9932670593],"type":"Point"}
}