{
  "type": "Feature",
  "properties": {
    "addr:full":"Calle de Toril, 25 Antequera M\u00e1laga 29200",
    "addr:housenumber":"25",
    "addr:postcode":"29200",
    "addr:street":"Calle De Toril",
    "iso:country":"ES",
    "sg:address":"Calle de Toril, 25",
    "sg:city":"Antequera",
    "sg:orig_category":"Electrodom\u00c9sticos (al Por Menor)",
    "sg:phone":"+34 952 84 29 30",
    "sg:postcode":"29200",
    "sg:province":"M\u00e1laga",
    "wof:name":"Sanchez Rubio Antonio",
    "wof:placetype":"venue"
},
  "geometry": {"coordinates":[-4.5580391884,37.0211105347],"type":"Point"}
}