{
  "type": "Feature",
  "properties": {
    "addr:full":"Afores, S/n Naves Lleida 25286",
    "addr:housenumber":"s / n",
    "addr:postcode":"25286",
    "addr:street":"Afores",
    "iso:country":"ES",
    "sg:address":"Afores, S/n",
    "sg:city":"Naves",
    "sg:orig_category":"Iglesia Cat\u00d3lica",
    "sg:phone":"+34 973 29 91 29",
    "sg:postcode":"25286",
    "sg:province":"Lleida",
    "wof:name":"Del Jesus Mendez Pedro",
    "wof:placetype":"venue"
},
  "geometry": {"coordinates":[1.4181050062,41.9509010315],"type":"Point"}
}