{
  "type": "Feature",
  "properties": {
    "iso:country":"ES",
    "sg:address":"C/ Pintor Soler Jorba, 1",
    "sg:city":"Cerdanyola Valles",
    "sg:orig_category":"Tapicer\u00cdas",
    "sg:phone":"+34 936 92 77 79",
    "sg:postcode":"08290",
    "sg:province":"Barcelona",
    "wof:name":"Romero Malaver Juan Manuel",
    "wof:placetype":"venue"
},
  "geometry": {"coordinates":[2.1470150948,41.4924812317],"type":"Point"}
}