{
  "type": "Feature",
  "properties": {
    "iso:country":"ES",
    "sg:address":"Cmno Villaespesa, 70",
    "sg:city":"Cruz De Caba\u00e7i",
    "sg:orig_category":"Empresas De Carpinter\u00cda Met\u00c1lica",
    "sg:phone":"+34 968 46 21 78",
    "sg:postcode":"30815",
    "sg:province":"Murcia",
    "wof:name":"Sistemas Alumisur S.l.",
    "wof:placetype":"venue"
},
  "geometry": {"coordinates":[-1.5774840117,37.5886192322],"type":"Point"}
}