{
  "type": "Feature",
  "properties": {
    "iso:country":"ES",
    "sg:address":"Pg Joan Borbo Comte Barcelo, 12",
    "sg:city":"Barcelona",
    "sg:orig_category":"Importaci\u00d3n",
    "sg:phone":"+34 932 21 82 21",
    "sg:postcode":"08003",
    "sg:province":"Barcelona",
    "wof:name":"Baliber Komora S.l.",
    "wof:placetype":"venue"
},
  "geometry": {"coordinates":[2.1855573654,41.3842697144],"type":"Point"}
}