{
  "type": "Feature",
  "properties": {
    "iso:country":"ES",
    "sg:address":"Calle de Bejar, 8",
    "sg:city":"Aranda Duero",
    "sg:orig_category":"Agencias De Viajes",
    "sg:phone":"+34 947 51 18 64",
    "sg:postcode":"09400",
    "sg:province":"Burgos",
    "sg:website":"www.marsans.es",
    "wof:name":"Viajes Marsans S.a.",
    "wof:placetype":"venue"
},
  "geometry": {"coordinates":[-3.6881949902,41.670841217],"type":"Point"}
}