{
  "type": "Feature",
  "properties": {
    "addr:full":"Calle de Cardiales, S/n Pedrajas S. Esteban Valladolid 47430",
    "addr:housenumber":"s / n",
    "addr:postcode":"47430",
    "addr:street":"Calle De Cardiales;Pedrajas S. Esteban Valladolid",
    "iso:country":"ES",
    "sg:address":"Calle de Cardiales, S/n",
    "sg:city":"Pedrajas S. Esteban",
    "sg:orig_category":"Poller\u00cda Y Caza (al Por Menor)",
    "sg:phone":"+34 983 62 58 21",
    "sg:postcode":"47430",
    "sg:province":"Valladolid",
    "wof:name":"Granja Baeza Fraile S.l.",
    "wof:placetype":"venue"
},
  "geometry": {"coordinates":[-4.5786356926,41.3392562866],"type":"Point"}
}