{
  "type": "Feature",
  "properties": {
    "addr:full":"La Albada, 7 Zaragoza Zaragoza 50014",
    "addr:housenumber":"7",
    "addr:postcode":"50014",
    "iso:country":"ES",
    "sg:address":"La Albada, 7",
    "sg:city":"Zaragoza",
    "sg:orig_category":"Peluquer\u00cdas, Peluquer\u00cda Mixta",
    "sg:phone":"+34 976 29 00 44",
    "sg:postcode":"50014",
    "sg:province":"Zaragoza",
    "wof:name":"Mur Maza Silvia",
    "wof:placetype":"venue"
},
  "geometry": {"coordinates":[-0.8813189864,41.6517295837],"type":"Point"}
}