{
  "type": "Feature",
  "properties": {
    "iso:country":"ES",
    "sg:address":"Carrer de Vilamari, 103",
    "sg:city":"Barcelona",
    "sg:orig_category":"Alimentaci\u00d3n General (al Por Menor)",
    "sg:phone":"+34 933 21 14 49",
    "sg:postcode":"08029",
    "sg:province":"Barcelona",
    "wof:name":"Veiga Leon Angeles",
    "wof:placetype":"venue"
},
  "geometry": {"coordinates":[2.1452589035,41.3817596436],"type":"Point"}
}