{
  "type": "Feature",
  "properties": {
    "addr:full":"Calle de Daroca, 69 Zaragoza Zaragoza 50017",
    "addr:housenumber":"69",
    "addr:postcode":"50017",
    "addr:street":"Calle De Daroca",
    "iso:country":"ES",
    "sg:address":"Calle de Daroca, 69",
    "sg:city":"Zaragoza",
    "sg:orig_category":"Supermercados Y Hipermercados",
    "sg:phone":"+34 976 34 30 15",
    "sg:postcode":"50017",
    "sg:province":"Zaragoza",
    "wof:name":"Galerias Primero S.a.",
    "wof:placetype":"venue"
},
  "geometry": {"coordinates":[-0.9083834291,41.6497001648],"type":"Point"}
}