{
  "type": "Feature",
  "properties": {
    "addr:full":"Calle de Beas, 5 Huelva Huelva 21006",
    "addr:housenumber":"5",
    "addr:postcode":"21006",
    "addr:street":"Calle De Beas",
    "iso:country":"ES",
    "sg:address":"Calle de Beas, 5",
    "sg:city":"Huelva",
    "sg:orig_category":"Empresas De Desmonte",
    "sg:phone":"+34 959 23 05 13",
    "sg:postcode":"21006",
    "sg:province":"Huelva",
    "wof:name":"Gomez De Las Torres Pedro",
    "wof:placetype":"venue"
},
  "geometry": {"coordinates":[-6.9335970879,37.2597389221],"type":"Point"}
}