{
  "type": "Feature",
  "properties": {
    "addr:full":"Bda. Constitucion, 49 Beas Huelva 21630",
    "addr:housenumber":"49",
    "addr:postcode":"21630",
    "addr:street":"Constitucion;Huelva",
    "iso:country":"ES",
    "sg:address":"Bda. Constitucion, 49",
    "sg:city":"Beas",
    "sg:orig_category":"Comercio, Reparaci\u00d3n De Motocicletas, Bicicletas Y Piezas Sueltas",
    "sg:phone":"+34 959 30 85 33",
    "sg:postcode":"21630",
    "sg:province":"Huelva",
    "wof:name":"Valenciano Ramirez Sebastian",
    "wof:placetype":"venue"
},
  "geometry": {"coordinates":[-6.7896289825,37.4269218445],"type":"Point"}
}