{
  "type": "Feature",
  "properties": {
    "addr:full":"Calle de Braulio Navas, 25 Hervas C\u00e1ceres 10700",
    "addr:housenumber":"25",
    "addr:postcode":"10700",
    "addr:street":"Calle De Braulio Navas;Ca\u0301Ceres",
    "iso:country":"ES",
    "sg:address":"Calle de Braulio Navas, 25",
    "sg:city":"Hervas",
    "sg:orig_category":"Farmacias",
    "sg:phone":"+34 927 47 31 54",
    "sg:postcode":"10700",
    "sg:province":"C\u00e1ceres",
    "wof:name":"Gonzalez Garcia Emilio",
    "wof:placetype":"venue"
},
  "geometry": {"coordinates":[-5.8602390289,40.272731781],"type":"Point"}
}