{
  "type": "Feature",
  "properties": {
    "addr:full":"Av Espanya, 106 Eivissa Islas Baleares 07800",
    "addr:housenumber":"106",
    "addr:postcode":"07800",
    "addr:street":"Av Espanya",
    "iso:country":"ES",
    "sg:address":"Av Espanya, 106",
    "sg:city":"Eivissa",
    "sg:orig_category":"Sociedades, Compa\u00d1\u00cdas Aseguradoras",
    "sg:phone":"+34 971 39 47 48",
    "sg:postcode":"07800",
    "sg:province":"Islas Baleares",
    "wof:name":"Mapfre Servicios De Informatica S.a.",
    "wof:placetype":"venue"
},
  "geometry": {"coordinates":[1.4216599464,38.9066886902],"type":"Point"}
}