{
  "type": "Feature",
  "properties": {
    "iso:country":"ES",
    "sg:address":"Plaz Lazaras, 5",
    "sg:city":"Villanueva Jara",
    "sg:orig_category":"Carnicer\u00cdas, Carnicer\u00cdas",
    "sg:phone":"+34 967 49 86 17",
    "sg:postcode":"16230",
    "sg:province":"Cuenca",
    "wof:name":"Carnicer C.b.",
    "wof:placetype":"venue"
},
  "geometry": {"coordinates":[-1.9583890438,39.4429244995],"type":"Point"}
}