{
  "type": "Feature",
  "properties": {
    "iso:country":"ES",
    "sg:address":"Calle de Campaners, 22",
    "sg:city":"Valencia",
    "sg:orig_category":"Administraci\u00d3n En Agricultura",
    "sg:phone":"+34 963 17 08 82",
    "sg:postcode":"46014",
    "sg:province":"Valencia",
    "wof:name":"Olmos Benlloch Carmen",
    "wof:placetype":"venue"
},
  "geometry": {"coordinates":[-0.400783807,39.4580345154],"type":"Point"}
}