{
  "type": "Feature",
  "properties": {
    "iso:country":"ES",
    "sg:address":"Avda Malaga, 18",
    "sg:city":"Cala Moral",
    "sg:orig_category":"Reposter\u00cdas",
    "sg:phone":"+34 952 40 13 97",
    "sg:postcode":"29720",
    "sg:province":"M\u00e1laga",
    "wof:name":"Guijarro Fernandez Jose",
    "wof:placetype":"venue"
},
  "geometry": {"coordinates":[-4.6767678261,36.5055274963],"type":"Point"}
}