{
  "type": "Feature",
  "properties": {
    "addr:full":"Calle de Paloma, 6 Le\u00f3n Le\u00f3n 24003",
    "addr:housenumber":"6",
    "addr:postcode":"24003",
    "addr:street":"Calle De Paloma;Leo\u0301N",
    "iso:country":"ES",
    "sg:address":"Calle de Paloma, 6",
    "sg:city":"Le\u00f3n",
    "sg:orig_category":"Artesan\u00cda",
    "sg:phone":"+34 987 21 86 97",
    "sg:postcode":"24003",
    "sg:province":"Le\u00f3n",
    "wof:name":"Cascanueces Norte C.b.",
    "wof:placetype":"venue"
},
  "geometry": {"coordinates":[-5.5673851967,42.5984230042],"type":"Point"}
}