{
  "type": "Feature",
  "properties": {
    "iso:country":"ES",
    "sg:address":"Calle de Campana (la), S/n",
    "sg:city":"Chorrillo",
    "sg:orig_category":"Asesor\u00cda Sobre Comunicaci\u00d3n De Empresas",
    "sg:phone":"+34 922 68 44 04",
    "sg:postcode":"38108",
    "sg:province":"Santa Cruz De Tenerife",
    "wof:name":"Neumaticos Atlantico S.l.",
    "wof:placetype":"venue"
},
  "geometry": {"coordinates":[-16.3173675537,28.4172515869],"type":"Point"}
}