{
  "type": "Feature",
  "properties": {
    "iso:country":"ES",
    "sg:address":"Calle de Julia Garcia Boutan, 37",
    "sg:city":"Madrid",
    "sg:orig_category":"Asesor\u00cda Fiscal Y Jur\u00cddica",
    "sg:phone":"+34 913 06 15 02",
    "sg:postcode":"28022",
    "sg:province":"Madrid",
    "wof:name":"Blanco Iba\u00f1ez De Opacua Raquel",
    "wof:placetype":"venue"
},
  "geometry": {"coordinates":[-3.6047389507,40.4304771423],"type":"Point"}
}