{
  "type": "Feature",
  "properties": {
    "iso:country":"ES",
    "sg:address":"Carrer de Misser Rufet, 3",
    "sg:city":"Vilafranca Penedes",
    "sg:orig_category":"Fotocopias, Reprograf\u00cda",
    "sg:phone":"+34 938 17 12 99",
    "sg:postcode":"08720",
    "sg:province":"Barcelona",
    "sg:website":"www.copiflash.com",
    "wof:name":"Gavalda Aliaga Pedro Vicente",
    "wof:placetype":"venue"
},
  "geometry": {"coordinates":[1.7028729916,41.3458404541],"type":"Point"}
}