{
  "type": "Feature",
  "properties": {
    "addr:full":"Av Paisos Catalans, 23 Quatre Garrofers Tarragona 43007",
    "addr:housenumber":"23",
    "addr:postcode":"43007",
    "addr:street":"Av Paisos Catalans",
    "iso:country":"ES",
    "sg:address":"Av Paisos Catalans, 23",
    "sg:city":"Quatre Garrofers",
    "sg:orig_category":"Ingenier\u00cda, Centros De Estudios (diversos)",
    "sg:phone":"+34 977 20 49 12",
    "sg:postcode":"43007",
    "sg:province":"Tarragona",
    "wof:name":"Gibert Girona Decoracio I Project Sl",
    "wof:placetype":"venue"
},
  "geometry": {"coordinates":[1.2457669973,41.1321372986],"type":"Point"}
}