{
  "type": "Feature",
  "properties": {
    "iso:country":"ES",
    "sg:address":"Calle de Pi\u00d1a Blasco, 3",
    "sg:city":"Carrion De Los Condes",
    "sg:orig_category":"Supermercados Y Hipermercados",
    "sg:phone":"+34 979 88 05 25",
    "sg:postcode":"34120",
    "sg:province":"Palencia",
    "wof:name":"Supermercado David C.b.",
    "wof:placetype":"venue"
},
  "geometry": {"coordinates":[-4.6047301292,42.3393859863],"type":"Point"}
}