{
  "type": "Feature",
  "properties": {
    "addr:full":"Pl Sant Vicen\u00c7 De Sarria, 2 Barcelona Barcelona 08017",
    "addr:housenumber":"2",
    "addr:postcode":"08017",
    "addr:street":"Pl Sant Vicenc\u0327;Sarria",
    "iso:country":"ES",
    "sg:address":"Pl Sant Vicen\u00c7 De Sarria, 2",
    "sg:city":"Barcelona",
    "sg:orig_category":"Audiovisuales (producci\u00d3n, Edici\u00d3n, Realizaci\u00d3n)",
    "sg:phone":"+34 932 03 42 00",
    "sg:postcode":"08017",
    "sg:province":"Barcelona",
    "wof:name":"L.q.mosquito Corporation S.l.",
    "wof:placetype":"venue"
},
  "geometry": {"coordinates":[2.1240038872,41.3972244263],"type":"Point"}
}