{
  "type": "Feature",
  "properties": {
    "iso:country":"ES",
    "sg:address":"Carr Llevant, 7",
    "sg:city":"Arbeca",
    "sg:orig_category":"Electricidad: Instaladores",
    "sg:phone":"+34 973 14 90 95",
    "sg:postcode":"25140",
    "sg:province":"Lleida",
    "wof:name":"Electricitat Llugema S.l.",
    "wof:placetype":"venue"
},
  "geometry": {"coordinates":[0.9253410101,41.5425262451],"type":"Point"}
}