{
  "type": "Feature",
  "properties": {
    "addr:full":"Calle de Carretas, 13 Madrid Madrid 28012",
    "addr:housenumber":"13",
    "addr:postcode":"madrid;28012",
    "addr:street":"Calle De Carretas",
    "iso:country":"ES",
    "sg:address":"Calle de Carretas, 13",
    "sg:city":"Madrid",
    "sg:orig_category":"Parques De Atracciones Y Centros De Esparcimiento",
    "sg:phone":"+34 915 32 76 18",
    "sg:postcode":"28012",
    "sg:province":"Madrid",
    "wof:name":"Rank Centro S.a.",
    "wof:placetype":"venue"
},
  "geometry": {"coordinates":[-3.7032301426,40.4160308838],"type":"Point"}
}