{
  "type": "Feature",
  "properties": {
    "addr:full":"Pg Maragall, 282 Barcelona Barcelona 08031",
    "addr:housenumber":"282",
    "addr:postcode":"08031",
    "addr:street":"Pg Maragall",
    "iso:country":"ES",
    "sg:address":"Pg Maragall, 282",
    "sg:city":"Barcelona",
    "sg:orig_category":"Peluquer\u00cdas, Peluquer\u00cda Mixta",
    "sg:phone":"+34 933 57 45 79",
    "sg:postcode":"08031",
    "sg:province":"Barcelona",
    "wof:name":"Ferreira Penelo Remedios",
    "wof:placetype":"venue"
},
  "geometry": {"coordinates":[2.1707808971,41.4271316528],"type":"Point"}
}