{
  "type": "Feature",
  "properties": {
    "iso:country":"ES",
    "sg:address":"Calle de Canarias, 2",
    "sg:city":"Adra",
    "sg:orig_category":"Muebles Y Accesorios Para Cocinas Y Cuartos De Ba\u00d1o (al Por Menor)",
    "sg:phone":"+34 950 40 07 80",
    "sg:postcode":"04770",
    "sg:province":"Almer\u00eda",
    "wof:name":"Lidue\u00f1a Galdeano Jose Ramon",
    "wof:placetype":"venue"
},
  "geometry": {"coordinates":[-3.0235610008,36.7481803894],"type":"Point"}
}