{
  "type": "Feature",
  "properties": {
    "addr:full":"Calle de Antonio Hernandez Paez, 2 Corralejo Las Palmas 35660",
    "addr:housenumber":"2",
    "addr:postcode":"35660",
    "addr:street":"Calle De Antonio Hernandez Paez",
    "iso:country":"ES",
    "sg:address":"Calle de Antonio Hernandez Paez, 2",
    "sg:city":"Corralejo",
    "sg:orig_category":"Molduras, Junquillos, Listones Y Molduras Perforadas",
    "sg:phone":"+34 928 53 54 69",
    "sg:postcode":"35660",
    "sg:province":"Las Palmas",
    "sg:website":"www.arena-fuenteventura.com",
    "wof:name":"Fuertesolrac S.l.",
    "wof:placetype":"venue"
},
  "geometry": {"coordinates":[-13.8685207367,28.7377567291],"type":"Point"}
}