{
  "type": "Feature",
  "properties": {
    "addr:full":"Bo El Baden, S/n Rafal Alicante 03369",
    "addr:housenumber":"s / n",
    "addr:postcode":"03369",
    "iso:country":"ES",
    "sg:address":"Bo El Baden, S/n",
    "sg:city":"Rafal",
    "sg:orig_category":"Hilaturas, Hilos Y Actividades Relacionadas",
    "sg:phone":"+34 966 75 25 14",
    "sg:postcode":"03369",
    "sg:province":"Alicante",
    "wof:name":"Ortu\u00f1o Ferrandez Joaquin",
    "wof:placetype":"venue"
},
  "geometry": {"coordinates":[-0.8546590209,38.1019706726],"type":"Point"}
}