{
  "type": "Feature",
  "properties": {
    "addr:full":"Calle de Jardin (el), 5 Laguna Negrillos Le\u00f3n 24234",
    "addr:housenumber":"5",
    "addr:postcode":"24234",
    "addr:street":"Calle De Jardin El;Leo\u0301N",
    "iso:country":"ES",
    "sg:address":"Calle de Jardin (el), 5",
    "sg:city":"Laguna Negrillos",
    "sg:orig_category":"Molduras, Junquillos, Listones Y Molduras Perforadas",
    "sg:phone":"+34 987 75 50 63",
    "sg:postcode":"24234",
    "sg:province":"Le\u00f3n",
    "wof:name":"Blanco Moran Cristina",
    "wof:placetype":"venue"
},
  "geometry": {"coordinates":[-5.6589889526,42.2384681702],"type":"Point"}
}