{
  "type": "Feature",
  "properties": {
    "addr:full":"Cra. Sant Sadurni D'anoia, 2 Vilafranca Penedes Barcelona 08720",
    "addr:housenumber":"2",
    "addr:postcode":"08720",
    "addr:street":"Sadurni D'Anoia;Penedes Barcelona",
    "iso:country":"ES",
    "sg:address":"Cra. Sant Sadurni D'anoia, 2",
    "sg:city":"Vilafranca Penedes",
    "sg:orig_category":"Cristaler\u00cdas",
    "sg:phone":"+34 938 18 03 07",
    "sg:postcode":"08720",
    "sg:province":"Barcelona",
    "wof:name":"Cristaleria Anoia Arsal S.l.",
    "wof:placetype":"venue"
},
  "geometry": {"coordinates":[2.1699187756,41.3879165649],"type":"Point"}
}