{
  "type": "Feature",
  "properties": {
    "iso:country":"ES",
    "sg:address":"Calle de Espronceda, 4",
    "sg:city":"Huelva",
    "sg:orig_category":"Promotores Constructores",
    "sg:phone":"+34 959 25 17 52",
    "sg:postcode":"21001",
    "sg:province":"Huelva",
    "wof:name":"Hucoman S.l. Unipersonal",
    "wof:placetype":"venue"
},
  "geometry": {"coordinates":[-6.9520897865,37.2571296692],"type":"Point"}
}