{
  "type": "Feature",
  "properties": {
    "iso:country":"ES",
    "sg:address":"Ctra. Madrid(poligono), Km. 0322,0",
    "sg:city":"Valdelafuente",
    "sg:orig_category":"Agentes, Concesionarios Y Sucursales De Veh\u00cdculos",
    "sg:phone":"+34 987 22 53 70",
    "sg:postcode":"24227",
    "sg:province":"Le\u00f3n",
    "sg:website":"www.volvocars.es",
    "wof:name":"Martin Garcia Autos S.l.",
    "wof:placetype":"venue"
},
  "geometry": {"coordinates":[-5.5140891075,42.5692138672],"type":"Point"}
}