{
  "type": "Feature",
  "properties": {
    "iso:country":"ES",
    "sg:address":"Carrer de Disset, 4",
    "sg:city":"Florida",
    "sg:orig_category":"Ropa Para Ni\u00d1os (al Por Menor)",
    "sg:phone":"+34 935 44 84 21",
    "sg:postcode":"08130",
    "sg:province":"Barcelona",
    "wof:name":"Baby Nit S.l.",
    "wof:placetype":"venue"
},
  "geometry": {"coordinates":[2.1864778996,41.5200386047],"type":"Point"}
}