{
  "type": "Feature",
  "properties": {
    "addr:full":"Avda Primero De Mayo, 6 Coria Rio Sevilla 41100",
    "addr:housenumber":"6",
    "addr:postcode":"41100",
    "addr:street":"Avda Primero De Mayo;Rio Sevilla",
    "iso:country":"ES",
    "sg:address":"Avda Primero De Mayo, 6",
    "sg:city":"Coria Rio",
    "sg:orig_category":"Sociedades, Compa\u00d1\u00cdas Aseguradoras",
    "sg:phone":"+34 954 77 50 08",
    "sg:postcode":"41100",
    "sg:province":"Sevilla",
    "wof:name":"Sebastian Cordero Salas Correduria De Seguros S.l.",
    "wof:placetype":"venue"
},
  "geometry": {"coordinates":[-6.0509738922,37.2873153687],"type":"Point"}
}