{
  "type": "Feature",
  "properties": {
    "iso:country":"ES",
    "sg:address":"Calle de Artekalea, 27",
    "sg:city":"Durango",
    "sg:orig_category":"Papel Pintado (al Por Menor)",
    "sg:phone":"+34 944 66 86 93",
    "sg:postcode":"48200",
    "sg:province":"Vizcaya",
    "wof:name":"Itziar Castillo Lopez",
    "wof:placetype":"venue"
},
  "geometry": {"coordinates":[-2.6317203045,43.1668663025],"type":"Point"}
}