{
  "type": "Feature",
  "properties": {
    "addr:full":"Carrer de Reixago, 51 Can Sant Joan Barcelona 08110",
    "addr:housenumber":"51",
    "addr:postcode":"08110",
    "addr:street":"Carrer De Reixago",
    "iso:country":"ES",
    "sg:address":"Carrer de Reixago, 51",
    "sg:city":"Can Sant Joan",
    "sg:orig_category":"Molduras, Junquillos, Listones Y Molduras Perforadas",
    "sg:phone":"+34 935 64 86 09",
    "sg:postcode":"08110",
    "sg:province":"Barcelona",
    "wof:name":"Romero Fernandez Manuel",
    "wof:placetype":"venue"
},
  "geometry": {"coordinates":[2.1817800999,41.4892234802],"type":"Point"}
}