{
  "type": "Feature",
  "properties": {
    "addr:full":"Calle de Santo Tomas De Aquino, 41 Parla Madrid 28980",
    "addr:postcode":"28980",
    "addr:street":"Calle De Santo",
    "iso:country":"ES",
    "sg:address":"Calle de Santo Tomas De Aquino, 41",
    "sg:city":"Parla",
    "sg:orig_category":"Molduras, Junquillos, Listones Y Molduras Perforadas",
    "sg:phone":"+34 916 99 49 41",
    "sg:postcode":"28980",
    "sg:province":"Madrid",
    "wof:name":"Ovejero Iba\u00f1ez Sergio",
    "wof:placetype":"venue"
},
  "geometry": {"coordinates":[-3.7627360821,40.2384719849],"type":"Point"}
}