{
  "type": "Feature",
  "properties": {
    "iso:country":"ES",
    "sg:address":"Carrer de Camprodon, 29",
    "sg:city":"Barcelona",
    "sg:orig_category":"Artes Gr\u00c1ficas, Artes Pl\u00c1sticas (curso)",
    "sg:phone":"+34 934 59 09 90",
    "sg:postcode":"08012",
    "sg:province":"Barcelona",
    "wof:name":"Arrasec S.l.",
    "wof:placetype":"venue"
},
  "geometry": {"coordinates":[2.1644353867,41.4012451172],"type":"Point"}
}