{
  "type": "Feature",
  "properties": {
    "addr:full":"Carrer de Reina Victoria, 1 Barcelona Barcelona 08021",
    "addr:housenumber":"1",
    "addr:postcode":"08021",
    "addr:street":"Carrer De Reina Victoria",
    "iso:country":"ES",
    "sg:address":"Carrer de Reina Victoria, 1",
    "sg:city":"Barcelona",
    "sg:orig_category":"Asesor\u00cdas Y Estudios Financieros",
    "sg:phone":"+34 932 09 01 18",
    "sg:postcode":"08021",
    "sg:province":"Barcelona",
    "wof:name":"Ribera Esteban Alvaro",
    "wof:placetype":"venue"
},
  "geometry": {"coordinates":[2.1413650513,41.3975143433],"type":"Point"}
}