{
  "type": "Feature",
  "properties": {
    "addr:full":"Carrer de Varsovia, 118 Barcelona Barcelona 08041",
    "addr:housenumber":"118",
    "addr:postcode":"08041",
    "addr:street":"Carrer De Varsovia",
    "iso:country":"ES",
    "sg:address":"Carrer de Varsovia, 118",
    "sg:city":"Barcelona",
    "sg:orig_category":"Concepci\u00d3n Y Realizaci\u00d3n De Maquetas Profesionales Y Prototipos",
    "sg:phone":"+34 934 55 57 19",
    "sg:postcode":"08041",
    "sg:province":"Barcelona",
    "wof:name":"Marin Almor Juan Pablo",
    "wof:placetype":"venue"
},
  "geometry": {"coordinates":[2.1735670567,41.4200134277],"type":"Point"}
}