{
  "type": "Feature",
  "properties": {
    "addr:full":"Ctra Jaen (de), 94 Granada Granada 18013",
    "addr:housenumber":"94",
    "addr:postcode":"18013",
    "addr:street":"Ctra Jaen De",
    "iso:country":"ES",
    "sg:address":"Ctra Jaen (de), 94",
    "sg:city":"Granada",
    "sg:orig_category":"Cajas De Ahorro",
    "sg:phone":"+34 958 16 34 80",
    "sg:postcode":"18013",
    "sg:province":"Granada",
    "wof:name":"Unicaja",
    "wof:placetype":"venue"
},
  "geometry": {"coordinates":[-3.6117789745,37.1989517212],"type":"Point"}
}