{
  "type": "Feature",
  "properties": {
    "iso:country":"ES",
    "sg:address":"Plaz Nuestra Se\u00d1ora Del Pilar, 9",
    "sg:city":"Madrid",
    "sg:orig_category":"Empresas De Carpinter\u00cda De Madera",
    "sg:phone":"+34 915 63 99 53",
    "sg:postcode":"28002",
    "sg:province":"Madrid",
    "wof:name":"German Sanchez Jose Manuel",
    "wof:placetype":"venue"
},
  "geometry": {"coordinates":[-3.6750004292,40.4468460083],"type":"Point"}
}