{
  "type": "Feature",
  "properties": {
    "addr:full":"Av Mollet, 5 Santa Perpetua De Mogoda Barcelona 08130",
    "addr:housenumber":"5",
    "addr:postcode":"08130",
    "addr:street":"Av Mollet",
    "iso:country":"ES",
    "sg:address":"Av Mollet, 5",
    "sg:city":"Santa Perpetua De Mogoda",
    "sg:orig_category":"Maquinaria Para Industrias Diversas",
    "sg:phone":"+34 935 74 25 04",
    "sg:postcode":"08130",
    "sg:province":"Barcelona",
    "wof:name":"Vicantal S.l.",
    "wof:placetype":"venue"
},
  "geometry": {"coordinates":[2.1802799702,41.5371818542],"type":"Point"}
}