{
  "type": "Feature",
  "properties": {
    "iso:country":"ES",
    "sg:address":"Carrer de Cuba, 39",
    "sg:city":"Mataro",
    "sg:orig_category":"Caf\u00c9s (al Por Menor)",
    "sg:phone":"+34 937 90 61 68",
    "sg:postcode":"08302",
    "sg:province":"Barcelona",
    "wof:name":"Dubliner's",
    "wof:placetype":"venue"
},
  "geometry": {"coordinates":[2.4415769577,41.5365867615],"type":"Point"}
}