{
  "type": "Feature",
  "properties": {
    "iso:country":"ES",
    "sg:address":"Ctra Valencia, Km. 0124,0",
    "sg:city":"Benidorm",
    "sg:orig_category":"Chapister\u00cda",
    "sg:phone":"+34 965 85 43 95",
    "sg:postcode":"03500",
    "sg:province":"Alicante",
    "wof:name":"Astoria Cars S.l.",
    "wof:placetype":"venue"
},
  "geometry": {"coordinates":[-0.1306636035,38.5529975891],"type":"Point"}
}