{
  "type": "Feature",
  "properties": {
    "addr:full":"Avda Canarias De, S/n Palmas De Gran Canaria Las Palmas 35016",
    "addr:postcode":"35016",
    "addr:street":"Avda Canarias De S / N",
    "iso:country":"ES",
    "sg:address":"Avda Canarias De, S/n",
    "sg:city":"Palmas De Gran Canaria",
    "sg:orig_category":"Promotores Constructores",
    "sg:phone":"+34 928 33 49 50",
    "sg:postcode":"35016",
    "sg:province":"Las Palmas",
    "wof:name":"Insular U.t.e.",
    "wof:placetype":"venue"
},
  "geometry": {"coordinates":[-15.4127941132,28.0932807922],"type":"Point"}
}