{
  "type": "Feature",
  "properties": {
    "addr:full":"Carr Masia De La Cova, 23 Manises Valencia 46940",
    "addr:housenumber":"23",
    "addr:postcode":"46940",
    "addr:street":"Carr Masia De La Cova",
    "iso:country":"ES",
    "sg:address":"Carr Masia De La Cova, 23",
    "sg:city":"Manises",
    "sg:orig_category":"Estancos",
    "sg:phone":"+34 961 54 56 21",
    "sg:postcode":"46940",
    "sg:province":"Valencia",
    "wof:name":"Diez Calatrava Vicente",
    "wof:placetype":"venue"
},
  "geometry": {"coordinates":[-0.4622460008,39.493927002],"type":"Point"}
}