{
  "type": "Feature",
  "properties": {
    "iso:country":"ES",
    "sg:address":"Carrer de Independencia, 283",
    "sg:city":"Barcelona",
    "sg:orig_category":"Asociaciones Y Clubs Deportivos",
    "sg:phone":"+34 932 45 11 18",
    "sg:postcode":"08026",
    "sg:province":"Barcelona",
    "wof:name":"Club Billar Clot",
    "wof:placetype":"venue"
},
  "geometry": {"coordinates":[2.183052063,41.4078369141],"type":"Point"}
}