{
  "type": "Feature",
  "properties": {
    "iso:country":"ES",
    "sg:address":"Calle de Ca\u00d1averal, 103",
    "sg:city":"Madrid",
    "sg:orig_category":"Fabrica De Cer\u00c1micas",
    "sg:phone":"+34 913 14 65 85",
    "sg:postcode":"28029",
    "sg:province":"Madrid",
    "wof:name":"Revestimientos Alcit",
    "wof:placetype":"venue"
},
  "geometry": {"coordinates":[-3.6913480759,40.4719696045],"type":"Point"}
}