{
  "type": "Feature",
  "properties": {
    "addr:full":"Calle de Jose Barcena, 43 Talavera Reina Toledo 45600",
    "addr:housenumber":"43",
    "addr:postcode":"45600",
    "addr:street":"Calle De Jose Barcena",
    "iso:country":"ES",
    "sg:address":"Calle de Jose Barcena, 43",
    "sg:city":"Talavera Reina",
    "sg:orig_category":"Arquitectos",
    "sg:phone":"+34 925 80 82 58",
    "sg:postcode":"45600",
    "sg:province":"Toledo",
    "wof:name":"Pinilla Blazquez Jose Maria",
    "wof:placetype":"venue"
},
  "geometry": {"coordinates":[-4.8200531006,39.9687080383],"type":"Point"}
}