{
  "type": "Feature",
  "properties": {
    "iso:country":"ES",
    "sg:address":"Plaz Calvario (el), S/n",
    "sg:city":"Beceite",
    "sg:orig_category":"Empresas De Carpinter\u00cda De Madera",
    "sg:phone":"+34 978 85 05 51",
    "sg:postcode":"44588",
    "sg:province":"Teruel",
    "wof:name":"Carpinteria Beceite S.l.",
    "wof:placetype":"venue"
},
  "geometry": {"coordinates":[0.183694005,40.8300476074],"type":"Point"}
}