{
  "type": "Feature",
  "properties": {
    "iso:country":"ES",
    "sg:address":"Calle de Ochandiano, 6",
    "sg:city":"Madrid",
    "sg:orig_category":"Ense\u00d1anza Variada",
    "sg:phone":"+34 913 07 66 71",
    "sg:postcode":"28023",
    "sg:province":"Madrid",
    "wof:name":"Krauthammer International S.a.",
    "wof:placetype":"venue"
},
  "geometry": {"coordinates":[-3.8165380955,40.4681129456],"type":"Point"}
}