{
  "type": "Feature",
  "properties": {
    "addr:full":"C/ Nadal, 12 Manacor Islas Baleares 07500",
    "addr:housenumber":"12",
    "addr:postcode":"07500",
    "addr:street":"C / Nadal",
    "iso:country":"ES",
    "sg:address":"C/ Nadal, 12",
    "sg:city":"Manacor",
    "sg:orig_category":"Peluqueros: De Se\u00d1oras",
    "sg:phone":"+34 971 55 33 26",
    "sg:postcode":"07500",
    "sg:province":"Islas Baleares",
    "wof:name":"Ferrer Sureda Catalina",
    "wof:placetype":"venue"
},
  "geometry": {"coordinates":[3.2073709965,39.5655784607],"type":"Point"}
}