{
  "type": "Feature",
  "properties": {
    "iso:country":"ES",
    "sg:address":"Calle de Fontanilla, 27",
    "sg:city":"Hinojosa Del Duque",
    "sg:orig_category":"Asociaciones Y Clubs Deportivos",
    "sg:phone":"+34 957 14 22 52",
    "sg:postcode":"14270",
    "sg:province":"C\u00f3rdoba",
    "wof:name":"Pla Rubio Maria Josefa",
    "wof:placetype":"venue"
},
  "geometry": {"coordinates":[-5.1442918777,38.4992713928],"type":"Point"}
}