{
  "type": "Feature",
  "properties": {
    "addr:full":"Iglesia, 6 Terrateig Valencia 46842",
    "addr:housenumber":"6",
    "addr:postcode":"46842",
    "addr:street":"Iglesia",
    "iso:country":"ES",
    "sg:address":"Iglesia, 6",
    "sg:city":"Terrateig",
    "sg:orig_category":"Aguas (distribuci\u00d3n, Servicios)",
    "sg:phone":"+34 962 89 63 71",
    "sg:postcode":"46842",
    "sg:province":"Valencia",
    "wof:name":"Sociedad Espa\u00f1ola De Abastecimientos S.a.",
    "wof:placetype":"venue"
},
  "geometry": {"coordinates":[-0.3388890028,38.8918914795],"type":"Point"}
}