{
  "type": "Feature",
  "properties": {
    "iso:country":"ES",
    "sg:address":"Calle de Juan Xxiii, 11",
    "sg:city":"Caceres",
    "sg:orig_category":"Grafistas",
    "sg:phone":"+34 927 21 49 85",
    "sg:postcode":"10005",
    "sg:province":"C\u00e1ceres",
    "wof:name":"Ramos Llano Joaquin",
    "wof:placetype":"venue"
},
  "geometry": {"coordinates":[-6.3834872246,39.4664611816],"type":"Point"}
}