{
  "type": "Feature",
  "properties": {
    "iso:country":"ES",
    "sg:address":"Calle de Principe (del), S/n",
    "sg:city":"Aranjuez",
    "sg:orig_category":"Iglesia Cat\u00d3lica",
    "sg:phone":"+34 918 91 05 13",
    "sg:postcode":"28300",
    "sg:province":"Madrid",
    "wof:name":"Obispado De Getafe",
    "wof:placetype":"venue"
},
  "geometry": {"coordinates":[-3.6014590263,40.0356483459],"type":"Point"}
}