{
  "type": "Feature",
  "properties": {
    "addr:full":"Pla\u00c7 Esglesia, S/n Begur Girona 17255",
    "addr:housenumber":"s / n",
    "addr:postcode":"17255",
    "addr:street":"Plac\u0327 Esglesia",
    "iso:country":"ES",
    "sg:address":"Pla\u00c7 Esglesia, S/n",
    "sg:city":"Begur",
    "sg:orig_category":"Inmobiliaria (agencias)",
    "sg:phone":"+34 972 62 48 12",
    "sg:postcode":"17255",
    "sg:province":"Girona",
    "wof:name":"Gual Moliner Jose",
    "wof:placetype":"venue"
},
  "geometry": {"coordinates":[3.2071499825,41.9543266296],"type":"Point"}
}