{
  "type": "Feature",
  "properties": {
    "addr:full":"Carrer de Porres, 2 Palma Islas Baleares 07015",
    "addr:housenumber":"2",
    "addr:postcode":"07015",
    "addr:street":"Carrer De Porres",
    "iso:country":"ES",
    "sg:address":"Carrer de Porres, 2",
    "sg:city":"Palma",
    "sg:orig_category":"Prot\u00c9sicos Dentales",
    "sg:phone":"+34 971 28 17 28",
    "sg:postcode":"07015",
    "sg:province":"Islas Baleares",
    "wof:name":"Pons Niza Francisco Jose",
    "wof:placetype":"venue"
},
  "geometry": {"coordinates":[2.6249690056,39.5618553162],"type":"Point"}
}