{
  "type": "Feature",
  "properties": {
    "iso:country":"ES",
    "sg:address":"Avda Real De Madrid, 146",
    "sg:city":"Valencia",
    "sg:orig_category":"Promotores Constructores",
    "sg:phone":"+34 963 75 03 71",
    "sg:postcode":"46017",
    "sg:province":"Valencia",
    "wof:name":"Raviaval S.l.",
    "wof:placetype":"venue"
},
  "geometry": {"coordinates":[-0.393907994,39.4274864197],"type":"Point"}
}