{
  "type": "Feature",
  "properties": {
    "addr:full":"Av Roma (de), 22 Tarragona Tarragona 43005",
    "addr:housenumber":"22",
    "addr:postcode":"43005",
    "addr:street":"Av Roma De",
    "iso:country":"ES",
    "sg:address":"Av Roma (de), 22",
    "sg:city":"Tarragona",
    "sg:orig_category":"Inmobiliaria (agencias)",
    "sg:phone":"+34 977 21 29 38",
    "sg:postcode":"43005",
    "sg:province":"Tarragona",
    "wof:name":"Kadeiko S.l",
    "wof:placetype":"venue"
},
  "geometry": {"coordinates":[1.2405970097,41.1180114746],"type":"Point"}
}