{
  "type": "Feature",
  "properties": {
    "addr:full":"Ctra Sagunto-burgos (zaragoza), Km. 0122,0 Teruel Teruel 44002",
    "addr:postcode":"44002",
    "addr:street":"Ctra Sagunto-Burgos Zaragoza Km. 0122,0;Teruel",
    "iso:country":"ES",
    "sg:address":"Ctra Sagunto-burgos (zaragoza), Km. 0122,0",
    "sg:city":"Teruel",
    "sg:orig_category":"Empresas De Carpinter\u00cda",
    "sg:phone":"+34 978 61 10 60",
    "sg:postcode":"44002",
    "sg:province":"Teruel",
    "wof:name":"Ballestero De Atienza Jose Luis",
    "wof:placetype":"venue"
},
  "geometry": {"coordinates":[-1.0912590027,40.3269119263],"type":"Point"}
}