{
  "type": "Feature",
  "properties": {
    "addr:full":"Calle de Perez Galdos, 29 Almeria Almer\u00eda 04006",
    "addr:housenumber":"29",
    "addr:postcode":"04006",
    "addr:street":"Calle De Perez Galdos",
    "iso:country":"ES",
    "sg:address":"Calle de Perez Galdos, 29",
    "sg:city":"Almeria",
    "sg:orig_category":"Fabricaci\u00d3n De Juguetes Autom\u00c1ticos",
    "sg:phone":"+34 950 22 77 02",
    "sg:postcode":"04006",
    "sg:province":"Almer\u00eda",
    "wof:name":"Recreativos Virgen Del Mar S.l.",
    "wof:placetype":"venue"
},
  "geometry": {"coordinates":[-2.4483709335,36.8425331116],"type":"Point"}
}