{
  "type": "Feature",
  "properties": {
    "iso:country":"ES",
    "sg:address":"Calle de Ciudad De Martos, 4",
    "sg:city":"Mora",
    "sg:orig_category":"Asociaciones Y Clubs Deportivos",
    "sg:phone":"+34 925 34 18 16",
    "sg:postcode":"45400",
    "sg:province":"Toledo",
    "sg:website":"www.jimbukan.net",
    "wof:name":"Gimnasio Jinbukan Sl",
    "wof:placetype":"venue"
},
  "geometry": {"coordinates":[-3.7731328011,39.6856765747],"type":"Point"}
}