{
  "type": "Feature",
  "properties": {
    "addr:full":"Calle de Eras, 25 Nuevo Baztan Madrid 28514",
    "addr:housenumber":"25",
    "addr:postcode":"28514",
    "addr:street":"Calle De Eras",
    "iso:country":"ES",
    "sg:address":"Calle de Eras, 25",
    "sg:city":"Nuevo Baztan",
    "sg:orig_category":"Cerrajer\u00cda, Ferrallista",
    "sg:phone":"+34 918 73 51 07",
    "sg:postcode":"28514",
    "sg:province":"Madrid",
    "wof:name":"Cerrajeria Casa Sl",
    "wof:placetype":"venue"
},
  "geometry": {"coordinates":[-3.2461879253,40.3698921204],"type":"Point"}
}