{
  "type": "Feature",
  "properties": {
    "addr:full":"Pantano Del, S/n Valdeobispo C\u00e1ceres 10672",
    "addr:postcode":"10672",
    "addr:street":"S / N;Ca\u0301Ceres",
    "iso:country":"ES",
    "sg:address":"Pantano Del, S/n",
    "sg:city":"Valdeobispo",
    "sg:orig_category":"Empresas De Carpinter\u00cda",
    "sg:phone":"+34 927 45 60 51",
    "sg:postcode":"10672",
    "sg:province":"C\u00e1ceres",
    "wof:name":"Dominguez Retortillo Juan Miguel",
    "wof:placetype":"venue"
},
  "geometry": {"coordinates":[-6.24477911,40.0817756653],"type":"Point"}
}