{
  "type": "Feature",
  "properties": {
    "iso:country":"ES",
    "sg:address":"Carrer de Montblanc, S/n",
    "sg:city":"Terrassa",
    "sg:orig_category":"Agencias Y Agentes Comerciales, Representantes",
    "sg:phone":"+34 937 31 19 84",
    "sg:postcode":"08223",
    "sg:province":"Barcelona",
    "wof:name":"Mistic Model S.l.",
    "wof:placetype":"venue"
},
  "geometry": {"coordinates":[2.0190210342,41.5481834412],"type":"Point"}
}