{
  "type": "Feature",
  "properties": {
    "addr:full":"Calle de Pirita, 2 Torrejon Ardoz Madrid 28850",
    "addr:housenumber":"2",
    "addr:postcode":"28850",
    "addr:street":"Calle De Pirita",
    "iso:country":"ES",
    "sg:address":"Calle de Pirita, 2",
    "sg:city":"Torrejon Ardoz",
    "sg:orig_category":"Empresas De Carpinter\u00cda Met\u00c1lica",
    "sg:phone":"+34 916 56 98 35",
    "sg:postcode":"28850",
    "sg:province":"Madrid",
    "wof:name":"Rivero Serrano Daniel",
    "wof:placetype":"venue"
},
  "geometry": {"coordinates":[-3.4659759998,40.4531364441],"type":"Point"}
}