{
  "type": "Feature",
  "properties": {
    "addr:full":"Calle de Gerardo Diego, 15 Arcos Jalon Soria 42250",
    "addr:housenumber":"15",
    "addr:postcode":"42250",
    "addr:street":"Calle De Gerardo Diego",
    "iso:country":"ES",
    "sg:address":"Calle de Gerardo Diego, 15",
    "sg:city":"Arcos Jalon",
    "sg:orig_category":"Telas Y Sedas (al Por Menor)",
    "sg:phone":"+34 975 32 00 06",
    "sg:postcode":"42250",
    "sg:province":"Soria",
    "wof:name":"Sanz Galan Marta Maria",
    "wof:placetype":"venue"
},
  "geometry": {"coordinates":[-2.2726109028,41.2135391235],"type":"Point"}
}