{
  "type": "Feature",
  "properties": {
    "iso:country":"ES",
    "sg:address":"Ctra Santpedor, 228",
    "sg:city":"Manresa",
    "sg:orig_category":"Perfumer\u00cda Y Cosm\u00c9tica (fabricaci\u00d3n, Al Por Mayor)",
    "sg:phone":"+34 938 77 23 71",
    "sg:postcode":"08243",
    "sg:province":"Barcelona",
    "wof:name":"N9 Cosmetics S.l.",
    "wof:placetype":"venue"
},
  "geometry": {"coordinates":[1.8332560062,41.7400169373],"type":"Point"}
}