{
  "type": "Feature",
  "properties": {
    "iso:country":"ES",
    "sg:address":"Luga Poligono Industrial De Roces, S/n",
    "sg:city":"Gijon",
    "sg:orig_category":"Asociaciones Y Clubs Deportivos",
    "sg:phone":"+34 985 30 71 90",
    "sg:postcode":"33211",
    "sg:province":"Asturias",
    "sg:website":"www.decathlon.es",
    "wof:name":"Decathlon Espa\u00f1a S. A. U.",
    "wof:placetype":"venue"
},
  "geometry": {"coordinates":[-5.6863942146,43.5233383179],"type":"Point"}
}