{
  "type": "Feature",
  "properties": {
    "iso:country":"ES",
    "sg:address":"Calle de Faro, 55",
    "sg:city":"Palmas De Gran Canaria",
    "sg:orig_category":"Bazares, Art\u00cdculos De Limpieza Y De Cocina (al Por Menor)",
    "sg:phone":"+34 928 46 60 09",
    "sg:postcode":"35009",
    "sg:province":"Las Palmas",
    "wof:name":"Gonzalez Castillo Nieves",
    "wof:placetype":"venue"
},
  "geometry": {"coordinates":[-15.4306640625,28.1510810852],"type":"Point"}
}