{
  "type": "Feature",
  "properties": {
    "iso:country":"ES",
    "sg:address":"Calle de Carlos Sole, 31",
    "sg:city":"Madrid",
    "sg:orig_category":"Electricidad Veh\u00cdculo",
    "sg:phone":"+34 917 77 34 12",
    "sg:postcode":"28038",
    "sg:province":"Madrid",
    "wof:name":"Sanchez De La Blanca Gonzalez Francisco",
    "wof:placetype":"venue"
},
  "geometry": {"coordinates":[-3.6482586861,40.3919029236],"type":"Point"}
}