{
  "type": "Feature",
  "properties": {
    "iso:country":"ES",
    "sg:address":"Calle de Ovalle, 34",
    "sg:city":"Salamanca",
    "sg:orig_category":"Peluquer\u00cdas, Peluquer\u00cda Mixta",
    "sg:phone":"+34 923 12 05 93",
    "sg:postcode":"37004",
    "sg:province":"Salamanca",
    "wof:name":"Crisan Salamanca C.b.",
    "wof:placetype":"venue"
},
  "geometry": {"coordinates":[-5.6541528702,40.9719467163],"type":"Point"}
}