{
  "type": "Feature",
  "properties": {
    "iso:country":"ES",
    "sg:address":"Rua Greco, S/n",
    "sg:city":"Sarria",
    "sg:orig_category":"Cajas Y Embalajes De Cart\u00d3n Y Papel",
    "sg:phone":"+34 982 53 13 10",
    "sg:postcode":"27600",
    "sg:province":"Lugo",
    "wof:name":"Graficas Nogueira C.b.",
    "wof:placetype":"venue"
},
  "geometry": {"coordinates":[-7.4093141556,42.7827186584],"type":"Point"}
}