{
  "type": "Feature",
  "properties": {
    "iso:country":"ES",
    "sg:address":"Ptda Seniola, 129",
    "sg:city":"Javea",
    "sg:orig_category":"Ense\u00d1ante, Direcci\u00d3n",
    "sg:phone":"+34 965 79 23 79",
    "sg:postcode":"03730",
    "sg:province":"Alicante",
    "wof:name":"Estopi\u00f1an Tapp Maria",
    "wof:placetype":"venue"
},
  "geometry": {"coordinates":[0.1570300013,38.7885093689],"type":"Point"}
}