{
  "type": "Feature",
  "properties": {
    "addr:full":"Ptda Alzabares Bajo, 63 Elche Alicante 03290",
    "addr:housenumber":"63",
    "addr:postcode":"03290",
    "addr:street":"Ptda Alzabares Bajo",
    "iso:country":"ES",
    "sg:address":"Ptda Alzabares Bajo, 63",
    "sg:city":"Elche",
    "sg:orig_category":"Empresas De Desmonte",
    "sg:phone":"+34 965 42 38 71",
    "sg:postcode":"03290",
    "sg:province":"Alicante",
    "wof:name":"Excavaciones Fany S.l.",
    "wof:placetype":"venue"
},
  "geometry": {"coordinates":[-0.6995239854,38.2634811401],"type":"Point"}
}