{
  "type": "Feature",
  "properties": {
    "iso:country":"ES",
    "sg:address":"Calle de Sor Policarpa, 1",
    "sg:city":"Almeria",
    "sg:orig_category":"Iglesia Cat\u00d3lica",
    "sg:phone":"+34 950 25 16 41",
    "sg:postcode":"04005",
    "sg:province":"Almer\u00eda",
    "wof:name":"Parroquia De San Jose",
    "wof:placetype":"venue"
},
  "geometry": {"coordinates":[-2.457036972,36.8448257446],"type":"Point"}
}