{
  "type": "Feature",
  "properties": {
    "iso:country":"ES",
    "sg:address":"Ptge Llivia, 70",
    "sg:city":"Barcelona",
    "sg:orig_category":"Cl\u00cdnicas Dentales",
    "sg:phone":"+34 934 36 92 74",
    "sg:postcode":"08041",
    "sg:province":"Barcelona",
    "wof:name":"Lopez Ramos Fernando",
    "wof:placetype":"venue"
},
  "geometry": {"coordinates":[2.1761929989,41.4209823608],"type":"Point"}
}