{
  "type": "Feature",
  "properties": {
    "iso:country":"ES",
    "sg:address":"Avda Madrid De, 51",
    "sg:city":"Fraga",
    "sg:orig_category":"Armas Y Municiones (fabricaci\u00d3n, Al Por Mayor)",
    "sg:phone":"+34 974 47 27 68",
    "sg:postcode":"22520",
    "sg:province":"Huesca",
    "wof:name":"Audio Sport Sc",
    "wof:placetype":"venue"
},
  "geometry": {"coordinates":[0.3364729881,41.5208396912],"type":"Point"}
}