{
  "type": "Feature",
  "properties": {
    "addr:full":"Calle de Manuel De La Quintana, 5 Jerez De La Frontera C\u00e1diz 11405",
    "addr:housenumber":"5",
    "addr:postcode":"11405",
    "addr:street":"Calle De Manuel De La Quintana",
    "iso:country":"ES",
    "sg:address":"Calle de Manuel De La Quintana, 5",
    "sg:city":"Jerez De La Frontera",
    "sg:orig_category":"Producci\u00d3n, Venta De Productos De Agricultura Biol\u00d3gica",
    "sg:phone":"+34 956 34 11 25",
    "sg:postcode":"11405",
    "sg:province":"C\u00e1diz",
    "wof:name":"Bohorquez Y Mora-figueroa Jose",
    "wof:placetype":"venue"
},
  "geometry": {"coordinates":[-6.1327900887,36.6909599304],"type":"Point"}
}