{
  "type": "Feature",
  "properties": {
    "addr:full":"Carrer de Mare De Deu Dels Angels, 76 Terrassa Barcelona 08221",
    "addr:postcode":"08221",
    "addr:street":"Carrer De Mare De Deu",
    "iso:country":"ES",
    "sg:address":"Carrer de Mare De Deu Dels Angels, 76",
    "sg:city":"Terrassa",
    "sg:orig_category":"Artes Gr\u00c1ficas, Artes Pl\u00c1sticas (curso)",
    "sg:phone":"+34 937 80 73 98",
    "sg:postcode":"08221",
    "sg:province":"Barcelona",
    "wof:name":"Enne Industria Grafica Scp",
    "wof:placetype":"venue"
},
  "geometry": {"coordinates":[2.0085089207,41.568107605],"type":"Point"}
}