{
  "type": "Feature",
  "properties": {
    "addr:full":"Rua Augusto Gonzalez Besada, 12 Sanxenxo Pontevedra 36960",
    "addr:housenumber":"12",
    "addr:postcode":"36960",
    "addr:street":"Rua Augusto Gonzalez Besada",
    "iso:country":"ES",
    "sg:address":"Rua Augusto Gonzalez Besada, 12",
    "sg:city":"Sanxenxo",
    "sg:orig_category":"Estancos",
    "sg:phone":"+34 986 72 41 16",
    "sg:postcode":"36960",
    "sg:province":"Pontevedra",
    "wof:name":"Baleiron Quiroga Santiago",
    "wof:placetype":"venue"
},
  "geometry": {"coordinates":[-8.8064231873,42.3996734619],"type":"Point"}
}