{
  "type": "Feature",
  "properties": {
    "iso:country":"ES",
    "sg:address":"Ctra Oca\u00d1a, 39",
    "sg:city":"Alacant",
    "sg:orig_category":"Fabricaci\u00d3n De Enlosados, Soler\u00cdas",
    "sg:phone":"+34 965 10 64 65",
    "sg:postcode":"03006",
    "sg:province":"Alicante",
    "wof:name":"Inbania Design Sl",
    "wof:placetype":"venue"
},
  "geometry": {"coordinates":[-0.5353680253,38.3439369202],"type":"Point"}
}