{
  "type": "Feature",
  "properties": {
    "iso:country":"ES",
    "sg:address":"Av Cortes Valencianes, 1",
    "sg:city":"Elche",
    "sg:orig_category":"Zapatos: Material, Suministros, Accesorios (fabricaci\u00d3n, Al Por Mayor)",
    "sg:phone":"+34 966 66 22 29",
    "sg:postcode":"03205",
    "sg:province":"Alicante",
    "wof:name":"J. Bernad Complementos S.l.",
    "wof:placetype":"venue"
},
  "geometry": {"coordinates":[-0.7165049911,38.2748947144],"type":"Point"}
}