{
  "type": "Feature",
  "properties": {
    "addr:full":"Calle de Tintetieso, 23 Urda Toledo 45480",
    "addr:housenumber":"23",
    "addr:postcode":"45480",
    "addr:street":"Calle De Tintetieso",
    "iso:country":"ES",
    "sg:address":"Calle de Tintetieso, 23",
    "sg:city":"Urda",
    "sg:orig_category":"Alimentaci\u00d3n General (al Por Menor)",
    "sg:phone":"+34 925 47 21 09",
    "sg:postcode":"45480",
    "sg:province":"Toledo",
    "wof:name":"Villa Garcia Antoliana",
    "wof:placetype":"venue"
},
  "geometry": {"coordinates":[-3.7219750881,39.4137535095],"type":"Point"}
}