{
  "type": "Feature",
  "properties": {
    "iso:country":"ES",
    "sg:address":"A Valenza, 21",
    "sg:city":"Valenza",
    "sg:orig_category":"Carnicer\u00cdas, Carnicer\u00cdas",
    "sg:phone":"+34 988 24 36 68",
    "sg:postcode":"32002",
    "sg:province":"Ourense",
    "wof:name":"Gallego Caride Jose Alberto",
    "wof:placetype":"venue"
},
  "geometry": {"coordinates":[-7.8811202049,42.3190994263],"type":"Point"}
}