{
  "type": "Feature",
  "properties": {
    "addr:full":"Calle de Art Major De La Seda, 15 Xirivella Valencia 46950",
    "addr:housenumber":"15",
    "addr:postcode":"46950",
    "addr:street":"Calle De Art Major De La Seda",
    "iso:country":"ES",
    "sg:address":"Calle de Art Major De La Seda, 15",
    "sg:city":"Xirivella",
    "sg:orig_category":"Mec\u00c1nico Del Autom\u00d3vil",
    "sg:phone":"+34 963 70 08 77",
    "sg:postcode":"46950",
    "sg:province":"Valencia",
    "wof:name":"Roca Fuentes Monica",
    "wof:placetype":"venue"
},
  "geometry": {"coordinates":[-0.426658392,39.4597816467],"type":"Point"}
}