{
  "type": "Feature",
  "properties": {
    "addr:full":"Calle de Almarza, 24 Madrid Madrid 28033",
    "addr:housenumber":"24",
    "addr:postcode":"madrid;28033",
    "addr:street":"Calle De Almarza",
    "iso:country":"ES",
    "sg:address":"Calle de Almarza, 24",
    "sg:city":"Madrid",
    "sg:orig_category":"Guarder\u00cdas",
    "sg:phone":"+34 917 66 85 02",
    "sg:postcode":"28033",
    "sg:province":"Madrid",
    "wof:name":"La Rana Glotona S.l.",
    "wof:placetype":"venue"
},
  "geometry": {"coordinates":[-3.6614723206,40.4677581787],"type":"Point"}
}