{
  "type": "Feature",
  "properties": {
    "iso:country":"ES",
    "sg:address":"Calle de Cruz, 22",
    "sg:city":"Torres Cotillas",
    "sg:orig_category":"Reposter\u00cdas",
    "sg:phone":"+34 968 62 67 72",
    "sg:postcode":"30565",
    "sg:province":"Murcia",
    "wof:name":"Sarabia Carrillo Alfonso",
    "wof:placetype":"venue"
},
  "geometry": {"coordinates":[-1.2417930365,38.0333786011],"type":"Point"}
}