{
  "type": "Feature",
  "properties": {
    "iso:country":"ES",
    "sg:address":"Calle de Uria, 39",
    "sg:city":"Oviedo",
    "sg:orig_category":"M\u00c9dicos: Cirug\u00cda General",
    "sg:phone":"+34 985 21 81 25",
    "sg:postcode":"33003",
    "sg:province":"Asturias",
    "wof:name":"Casas Tineo Miguel",
    "wof:placetype":"venue"
},
  "geometry": {"coordinates":[-5.8497238159,43.3631706238],"type":"Point"}
}