{
  "type": "Feature",
  "properties": {
    "addr:full":"Avda Tajo (del), 631 Atalaya \u00c1vila 05279",
    "addr:housenumber":"631",
    "addr:postcode":"05279",
    "addr:street":"Avda Tajo Del",
    "iso:country":"ES",
    "sg:address":"Avda Tajo (del), 631",
    "sg:city":"Atalaya",
    "sg:orig_category":"Plomeros",
    "sg:phone":"+34 918 64 80 40",
    "sg:postcode":"05279",
    "sg:province":"\u00c1vila",
    "wof:name":"Instalaciones Pinoe S.l.",
    "wof:placetype":"venue"
},
  "geometry": {"coordinates":[-4.462767601,40.3839187622],"type":"Point"}
}