{
  "type": "Feature",
  "properties": {
    "iso:country":"ES",
    "sg:address":"Carr Pere Canya, 1",
    "sg:city":"Bisbal D'emporda",
    "sg:orig_category":"Motocicletas (agentes, Concesionarios)",
    "sg:phone":"+34 972 64 07 76",
    "sg:postcode":"17100",
    "sg:province":"Girona",
    "wof:name":"Mercader Farrero Jordi",
    "wof:placetype":"venue"
},
  "geometry": {"coordinates":[3.0373883247,41.9572105408],"type":"Point"}
}