{
  "type": "Feature",
  "properties": {
    "addr:full":"La Calilla, 16 S Jose Almer\u00eda 04118",
    "addr:housenumber":"16",
    "addr:postcode":"04118",
    "addr:street":"S Jose Almeri\u0301A",
    "iso:country":"ES",
    "sg:address":"La Calilla, 16",
    "sg:city":"S Jose",
    "sg:orig_category":"Estancos",
    "sg:phone":"+34 950 38 03 78",
    "sg:postcode":"04118",
    "sg:province":"Almer\u00eda",
    "wof:name":"Vergel Camacho Josefa",
    "wof:placetype":"venue"
},
  "geometry": {"coordinates":[-2.1107029915,36.7560501099],"type":"Point"}
}