{
  "type": "Feature",
  "properties": {
    "iso:country":"ES",
    "sg:address":"Ctra Avila-casavieja, 34",
    "sg:city":"Mijares",
    "sg:orig_category":"Peluqueros: De Se\u00d1oras",
    "sg:phone":"+34 920 38 52 05",
    "sg:postcode":"05461",
    "sg:province":"\u00c1vila",
    "wof:name":"Alonso Mu\u00f1oz Maria Teresa",
    "wof:placetype":"venue"
},
  "geometry": {"coordinates":[-4.8358902931,40.2973823547],"type":"Point"}
}