{
  "type": "Feature",
  "properties": {
    "addr:full":"Calle de Nicolas Usera, 37 Madrid Madrid 28026",
    "addr:housenumber":"37",
    "addr:postcode":"madrid;28026",
    "addr:street":"Calle De Nicolas Usera",
    "iso:country":"ES",
    "sg:address":"Calle de Nicolas Usera, 37",
    "sg:city":"Madrid",
    "sg:orig_category":"Artes Gr\u00c1ficas, Artes Pl\u00c1sticas (curso)",
    "sg:phone":"+34 915 00 21 95",
    "sg:postcode":"28026",
    "sg:province":"Madrid",
    "wof:name":"Grafimar Impresores S.l.",
    "wof:placetype":"venue"
},
  "geometry": {"coordinates":[-3.7054080963,40.3850402832],"type":"Point"}
}