{
  "type": "Feature",
  "properties": {
    "iso:country":"ES",
    "sg:address":"Calle de San Esteban, 11",
    "sg:city":"Alba Tormes",
    "sg:orig_category":"Cerrajer\u00cda, Ferrallista",
    "sg:phone":"+34 923 30 04 78",
    "sg:postcode":"37800",
    "sg:province":"Salamanca",
    "wof:name":"Muriel Blanco Ricardo",
    "wof:placetype":"venue"
},
  "geometry": {"coordinates":[-5.5158295631,40.8291816711],"type":"Point"}
}