{
  "type": "Feature",
  "properties": {
    "iso:country":"ES",
    "sg:address":"Carr Carme, 17",
    "sg:city":"Girona",
    "sg:orig_category":"Farmacias",
    "sg:phone":"+34 972 20 00 79",
    "sg:postcode":"17004",
    "sg:province":"Girona",
    "wof:name":"Puig Salellas Ignacio",
    "wof:placetype":"venue"
},
  "geometry": {"coordinates":[2.8244891167,41.9803161621],"type":"Point"}
}