{
  "type": "Feature",
  "properties": {
    "iso:country":"ES",
    "sg:address":"Cordero, S/n",
    "sg:city":"S. Felices Gallegos",
    "sg:orig_category":"Bebidas",
    "sg:phone":"+34 923 52 15 57",
    "sg:postcode":"37270",
    "sg:province":"Salamanca",
    "wof:name":"Distribuciones Hermanos Redero S.l.",
    "wof:placetype":"venue"
},
  "geometry": {"coordinates":[-6.7035517693,40.8477401733],"type":"Point"}
}