{
  "type": "Feature",
  "properties": {
    "addr:full":"Plaz San Juan De Sahagun, S/n Salamanca Salamanca 37002",
    "addr:housenumber":"s / n",
    "addr:postcode":"37002",
    "addr:street":"Plaz;Sahagun",
    "iso:country":"ES",
    "sg:address":"Plaz San Juan De Sahagun, S/n",
    "sg:city":"Salamanca",
    "sg:orig_category":"Iglesia Cat\u00d3lica",
    "sg:phone":"+34 923 21 01 78",
    "sg:postcode":"37002",
    "sg:province":"Salamanca",
    "wof:name":"Obispado De Salamanca",
    "wof:placetype":"venue"
},
  "geometry": {"coordinates":[-5.6610388756,40.9683609009],"type":"Point"}
}