{
  "type": "Feature",
  "properties": {
    "iso:country":"ES",
    "sg:address":"Plaz Mayor, 16",
    "sg:city":"Aranda Duero",
    "sg:orig_category":"Procuradores",
    "sg:phone":"+34 947 50 80 40",
    "sg:postcode":"09400",
    "sg:province":"Burgos",
    "wof:name":"Arnaiz De Ugarte Marcos Maria",
    "wof:placetype":"venue"
},
  "geometry": {"coordinates":[-3.688498497,41.6704444885],"type":"Point"}
}