{
  "type": "Feature",
  "properties": {
    "addr:full":"Carrer de Valls (les), 11 Sabadell Barcelona 08201",
    "addr:housenumber":"11",
    "addr:postcode":"08201",
    "addr:street":"Carrer De Valls Les",
    "iso:country":"ES",
    "sg:address":"Carrer de Valls (les), 11",
    "sg:city":"Sabadell",
    "sg:orig_category":"Escuelas De Maternidad P\u00dablicas",
    "sg:phone":"+34 937 25 66 92",
    "sg:postcode":"08201",
    "sg:province":"Barcelona",
    "wof:name":"Sampere Guitart Vicente",
    "wof:placetype":"venue"
},
  "geometry": {"coordinates":[2.1002891064,41.5466918945],"type":"Point"}
}