{
  "type": "Feature",
  "properties": {
    "addr:full":"Calle de Antonio Maura, 35 Elda Alicante 03600",
    "addr:housenumber":"35",
    "addr:postcode":"03600",
    "addr:street":"Calle De Antonio Maura",
    "iso:country":"ES",
    "sg:address":"Calle de Antonio Maura, 35",
    "sg:city":"Elda",
    "sg:orig_category":"Promotores Constructores",
    "sg:phone":"+34 965 39 59 11",
    "sg:postcode":"03600",
    "sg:province":"Alicante",
    "wof:name":"Construcciones Zowamar S.l.",
    "wof:placetype":"venue"
},
  "geometry": {"coordinates":[-0.7966842055,38.4769248962],"type":"Point"}
}