{
  "type": "Feature",
  "properties": {
    "iso:country":"ES",
    "sg:address":"Carrer de Industria, 23",
    "sg:city":"Barcelona",
    "sg:orig_category":"Tapiceros Y Tapiceros",
    "sg:phone":"+34 934 59 01 48",
    "sg:postcode":"08037",
    "sg:province":"Barcelona",
    "wof:name":"Dissenyadores Cmdos S.l.l.",
    "wof:placetype":"venue"
},
  "geometry": {"coordinates":[2.1658840179,41.4032173157],"type":"Point"}
}