{
  "type": "Feature",
  "properties": {
    "addr:full":"Pase Zorrilla, 338 Valladolid Valladolid 47008",
    "addr:housenumber":"338",
    "addr:postcode":"47008",
    "addr:street":"Zorrilla",
    "iso:country":"ES",
    "sg:address":"Pase Zorrilla, 338",
    "sg:city":"Valladolid",
    "sg:orig_category":"Ingeniero",
    "sg:phone":"+34 983 24 60 79",
    "sg:postcode":"47008",
    "sg:province":"Valladolid",
    "wof:name":"El Jardin De Monet, S L",
    "wof:placetype":"venue"
},
  "geometry": {"coordinates":[-4.7482872009,41.6205787659],"type":"Point"}
}