{
  "type": "Feature",
  "properties": {
    "iso:country":"ES",
    "sg:address":"Av President Companys, 5",
    "sg:city":"Reus",
    "sg:orig_category":"Caf\u00c9s, Bares, Cervecer\u00cdas",
    "sg:phone":"+34 977 32 12 65",
    "sg:postcode":"43201",
    "sg:province":"Tarragona",
    "wof:name":"Cafeteria Restaurant Alex S.l.",
    "wof:placetype":"venue"
},
  "geometry": {"coordinates":[1.1029859781,41.1552391052],"type":"Point"}
}