{
  "type": "Feature",
  "properties": {
    "addr:full":"Calle de Tortola (de La), 4 Puerto De Santa Maria C\u00e1diz 11500",
    "addr:postcode":"11500",
    "addr:street":"Calle De Tortola De La 4;Ca\u0301Diz",
    "iso:country":"ES",
    "sg:address":"Calle de Tortola (de La), 4",
    "sg:city":"Puerto De Santa Maria",
    "sg:orig_category":"Agentes Generales De Seguros",
    "sg:phone":"+34 956 85 79 04",
    "sg:postcode":"11500",
    "sg:province":"C\u00e1diz",
    "wof:name":"Martinez Y Bellvis S.l.",
    "wof:placetype":"venue"
},
  "geometry": {"coordinates":[-6.2361178398,36.5931892395],"type":"Point"}
}