{
  "type": "Feature",
  "properties": {
    "iso:country":"ES",
    "sg:address":"P I Ntra Sra Soledad, 8",
    "sg:city":"Cantillana",
    "sg:orig_category":"Negocio De Materiales De Construcci\u00d3n",
    "sg:phone":"+34 955 73 08 30",
    "sg:postcode":"41320",
    "sg:province":"Sevilla",
    "wof:name":"Perez Ortiz Jose",
    "wof:placetype":"venue"
},
  "geometry": {"coordinates":[-5.8235311508,37.6100616455],"type":"Point"}
}