{
  "type": "Feature",
  "properties": {
    "addr:full":"Calle de Bravo Murillo, 298 Madrid Madrid 28020",
    "addr:housenumber":"298",
    "addr:postcode":"28020",
    "addr:street":"Calle De Bravo Murillo",
    "iso:country":"ES",
    "sg:address":"Calle de Bravo Murillo, 298",
    "sg:city":"Madrid",
    "sg:orig_category":"Bisuter\u00cda, Joyer\u00cda, Relojer\u00cda (al Por Menor)",
    "sg:phone":"+34 915 72 15 04",
    "sg:postcode":"28020",
    "sg:province":"Madrid",
    "wof:name":"Fernandez Lopez Marta",
    "wof:placetype":"venue"
},
  "geometry": {"coordinates":[-3.6973674297,40.4624977112],"type":"Point"}
}