{
  "type": "Feature",
  "properties": {
    "addr:full":"Carrer de Saragossa (de), 2 Salou Tarragona 43840",
    "addr:housenumber":"2",
    "addr:postcode":"43840",
    "addr:street":"Carrer De Saragossa De",
    "iso:country":"ES",
    "sg:address":"Carrer de Saragossa (de), 2",
    "sg:city":"Salou",
    "sg:orig_category":"Molduras, Junquillos, Listones Y Molduras Perforadas",
    "sg:phone":"+34 977 38 51 92",
    "sg:postcode":"43840",
    "sg:province":"Tarragona",
    "wof:name":"Martinez Romero Salou S.l.",
    "wof:placetype":"venue"
},
  "geometry": {"coordinates":[1.1450070143,41.0731315613],"type":"Point"}
}