{
  "type": "Feature",
  "properties": {
    "iso:country":"ES",
    "sg:address":"Camino Viejo Simancas, S/n",
    "sg:city":"Valladolid",
    "sg:orig_category":"Zapatos (al Por Menor)",
    "sg:phone":"+34 983 47 71 35",
    "sg:postcode":"47008",
    "sg:province":"Valladolid",
    "wof:name":"Fosco Zapatos Y Accesorios S.a.",
    "wof:placetype":"venue"
},
  "geometry": {"coordinates":[-4.7458910942,41.6271781921],"type":"Point"}
}