{
  "type": "Feature",
  "properties": {
    "iso:country":"ES",
    "sg:address":"Rua Rio Xubia, 161",
    "sg:city":"Ferrol",
    "sg:orig_category":"Pescader\u00cdas (al Por Mayor)",
    "sg:phone":"+34 981 32 06 51",
    "sg:postcode":"15403",
    "sg:province":"La Coru\u00f1a",
    "wof:name":"Pi\u00f1eiro Lourido Jose",
    "wof:placetype":"venue"
},
  "geometry": {"coordinates":[-8.2221393585,43.492351532],"type":"Point"}
}