{
  "type": "Feature",
  "properties": {
    "addr:full":"Grup Mendialde, 13 Ortuella Vizcaya 48530",
    "addr:housenumber":"13",
    "addr:postcode":"48530",
    "addr:street":"Mendialde",
    "iso:country":"ES",
    "sg:address":"Grup Mendialde, 13",
    "sg:city":"Ortuella",
    "sg:orig_category":"Supermercados Y Hipermercados",
    "sg:phone":"+34 946 64 21 08",
    "sg:postcode":"48530",
    "sg:province":"Vizcaya",
    "wof:name":"Supermercados Ercoreca S.a.",
    "wof:placetype":"venue"
},
  "geometry": {"coordinates":[-3.0558180809,43.3110237122],"type":"Point"}
}