{
  "type": "Feature",
  "properties": {
    "addr:full":"Carrer de Ferran Agullo, 6 Barcelona Barcelona 08021",
    "addr:housenumber":"6",
    "addr:postcode":"08021",
    "addr:street":"Carrer De Ferran Agullo",
    "iso:country":"ES",
    "sg:address":"Carrer de Ferran Agullo, 6",
    "sg:city":"Barcelona",
    "sg:orig_category":"Ropa Para Se\u00d1oras (al Por Menor)",
    "sg:phone":"+34 932 01 32 68",
    "sg:postcode":"08021",
    "sg:province":"Barcelona",
    "wof:name":"Upsumpco S.l.",
    "wof:placetype":"venue"
},
  "geometry": {"coordinates":[2.1415801048,41.3952102661],"type":"Point"}
}