{
  "type": "Feature",
  "properties": {
    "addr:full":"Calle de Abderraman, 46 Malaga M\u00e1laga 29006",
    "addr:housenumber":"46",
    "addr:postcode":"29006",
    "addr:street":"Calle De Abderraman;Ma\u0301Laga",
    "iso:country":"ES",
    "sg:address":"Calle de Abderraman, 46",
    "sg:city":"Malaga",
    "sg:orig_category":"Plomeros",
    "sg:phone":"+34 952 31 84 23",
    "sg:postcode":"29006",
    "sg:province":"M\u00e1laga",
    "wof:name":"Bonela Instalaciones Y Proyectos S.l.",
    "wof:placetype":"venue"
},
  "geometry": {"coordinates":[-4.4819536209,36.7062950134],"type":"Point"}
}