{
  "type": "Feature",
  "properties": {
    "addr:full":"Plaz Peru, 5 Madrid Madrid 28016",
    "addr:housenumber":"5",
    "addr:postcode":"28016",
    "addr:street":"Peru",
    "iso:country":"ES",
    "sg:address":"Plaz Peru, 5",
    "sg:city":"Madrid",
    "sg:classifiers":[
        {
            "category":"Arts & Performance",
            "subcategory":"Art Gallery",
            "type":"Entertainment"
        }
    ],
    "sg:phone":"+34 913 59 28 16",
    "sg:postcode":"28016",
    "sg:province":"Madrid",
    "sg:tags":[
        "arte",
        "de",
        "galer\u00cdas"
    ],
    "wof:name":"Alonso Blasi Montserrat",
    "wof:placetype":"venue"
},
  "geometry": {"coordinates":[-3.6765537262,40.4602394104],"type":"Point"}
}