{
  "type": "Feature",
  "properties": {
    "addr:full":"Calle de Justino Bernad, 6 Calamocha Teruel 44200",
    "addr:housenumber":"6",
    "addr:postcode":"44200",
    "addr:street":"Calle De Justino Bernad",
    "iso:country":"ES",
    "sg:address":"Calle de Justino Bernad, 6",
    "sg:city":"Calamocha",
    "sg:orig_category":"Agencias De Viajes",
    "sg:phone":"+34 978 73 20 00",
    "sg:postcode":"44200",
    "sg:province":"Teruel",
    "sg:website":"www.halconviajes.com",
    "wof:name":"Viajes Halcon S.a.",
    "wof:placetype":"venue"
},
  "geometry": {"coordinates":[-1.2983219624,40.9193496704],"type":"Point"}
}