{
  "type": "Feature",
  "properties": {
    "iso:country":"ES",
    "sg:address":"Carrer de L'hort De La Vila, 6",
    "sg:city":"Barcelona",
    "sg:orig_category":"Deportes N\u00c1uticos, Acu\u00c1ticos Y Subacu\u00c1ticos: Art\u00cdculos Y Equipo (al Por Menor)",
    "sg:phone":"+34 932 80 25 34",
    "sg:postcode":"08017",
    "sg:province":"Barcelona",
    "wof:name":"Tratamientos Integrales De Acastillaje Vasud S.l.",
    "wof:placetype":"venue"
},
  "geometry": {"coordinates":[2.1224637032,41.3987693787],"type":"Point"}
}