{
  "type": "Feature",
  "properties": {
    "iso:country":"ES",
    "sg:address":"Calle de Alemania, 19",
    "sg:city":"Malaga",
    "sg:orig_category":"Sindicatos De Trabajadores",
    "sg:phone":"+34 952 22 59 29",
    "sg:postcode":"29001",
    "sg:province":"M\u00e1laga",
    "wof:name":"Fetese-ugt",
    "wof:placetype":"venue"
},
  "geometry": {"coordinates":[-4.4248137474,36.7134895325],"type":"Point"}
}