{
  "type": "Feature",
  "properties": {
    "addr:full":"Calle de Iparragirre, 20 Gernika-lumo Vizcaya 48300",
    "addr:housenumber":"20",
    "addr:postcode":"48300",
    "addr:street":"Calle De Iparragirre",
    "iso:country":"ES",
    "sg:address":"Calle de Iparragirre, 20",
    "sg:city":"Gernika-lumo",
    "sg:orig_category":"M\u00c9dicos: Estomatolog\u00cda",
    "sg:phone":"+34 946 25 53 79",
    "sg:postcode":"48300",
    "sg:province":"Vizcaya",
    "sg:website":"paginasamarillas.es",
    "wof:name":"Goicoechea Jimenez Jose Miguel",
    "wof:placetype":"venue"
},
  "geometry": {"coordinates":[-2.6772220135,43.3129425049],"type":"Point"}
}