{
  "type": "Feature",
  "properties": {
    "iso:country":"ES",
    "sg:address":"Calle de San Pablo, 68",
    "sg:city":"Salamanca",
    "sg:orig_category":"Abogados",
    "sg:phone":"+34 923 21 81 83",
    "sg:postcode":"37008",
    "sg:province":"Salamanca",
    "wof:name":"Prado Santos Francisco Javier",
    "wof:placetype":"venue"
},
  "geometry": {"coordinates":[-5.6640510559,40.9607086182],"type":"Point"}
}