{
  "type": "Feature",
  "properties": {
    "iso:country":"ES",
    "sg:address":"Galileo (z. Ind Cami Ral), 38",
    "sg:city":"Gava",
    "sg:orig_category":"Fabricaci\u00d3n, Importaci\u00d3n De L\u00c1mparas Y Bombillas",
    "sg:phone":"+34 936 33 38 10",
    "sg:postcode":"08850",
    "sg:province":"Barcelona",
    "sg:website":"www.ecalux.com",
    "wof:name":"Ecalux Group S.a.",
    "wof:placetype":"venue"
},
  "geometry": {"coordinates":[1.9944449663,41.2862434387],"type":"Point"}
}