{
  "type": "Feature",
  "properties": {
    "addr:full":"Pase Aragon, 52 Alboraya Valencia 46120",
    "addr:housenumber":"52",
    "addr:postcode":"46120",
    "addr:street":"Aragon",
    "iso:country":"ES",
    "sg:address":"Pase Aragon, 52",
    "sg:city":"Alboraya",
    "sg:orig_category":"Farmacias (repartici\u00d3n Y Al Por Mayor)",
    "sg:phone":"+34 961 85 93 05",
    "sg:postcode":"46120",
    "sg:province":"Valencia",
    "wof:name":"Distribuidora Disesven S.l.",
    "wof:placetype":"venue"
},
  "geometry": {"coordinates":[-0.3405140042,39.4990692139],"type":"Point"}
}