{
  "type": "Feature",
  "properties": {
    "addr:full":"Calle de Gonzalez Besada, 9 Oviedo Asturias 33007",
    "addr:housenumber":"9",
    "addr:postcode":"33007",
    "addr:street":"Calle De Gonzalez Besada",
    "iso:country":"ES",
    "sg:address":"Calle de Gonzalez Besada, 9",
    "sg:city":"Oviedo",
    "sg:orig_category":"M\u00c9dicos: Ginecolog\u00cda Y Obstetricia",
    "sg:phone":"+34 985 27 52 29",
    "sg:postcode":"33007",
    "sg:province":"Asturias",
    "wof:name":"Ferrer Barriendos Francisco Javier",
    "wof:placetype":"venue"
},
  "geometry": {"coordinates":[-5.8484988213,43.3570137024],"type":"Point"}
}