{
  "type": "Feature",
  "properties": {
    "addr:full":"Carrer de Carles Buigas, 54 Sant Feliu Llobregat Barcelona 08980",
    "addr:housenumber":"54",
    "addr:postcode":"08980",
    "addr:street":"Carrer De Carles Buigas",
    "iso:country":"ES",
    "sg:address":"Carrer de Carles Buigas, 54",
    "sg:city":"Sant Feliu Llobregat",
    "sg:orig_category":"Peluquer\u00cdas, Peluquer\u00cda Mixta",
    "sg:phone":"+34 936 32 64 86",
    "sg:postcode":"08980",
    "sg:province":"Barcelona",
    "wof:name":"Gimenez Martinez Silvia",
    "wof:placetype":"venue"
},
  "geometry": {"coordinates":[2.0518920422,41.3865203857],"type":"Point"}
}