{
  "type": "Feature",
  "properties": {
    "addr:full":"Calle de Ventas (las), 19 Aranguren Navarra 31192",
    "addr:housenumber":"19",
    "addr:postcode":"31192",
    "addr:street":"Calle De Ventas Las;Navarra",
    "iso:country":"ES",
    "sg:address":"Calle de Ventas (las), 19",
    "sg:city":"Aranguren",
    "sg:orig_category":"Ropa Para Se\u00d1oras (al Por Menor)",
    "sg:phone":"+34 948 33 90 53",
    "sg:postcode":"31192",
    "sg:province":"Navarra",
    "wof:name":"Martin Moreno Blanca",
    "wof:placetype":"venue"
},
  "geometry": {"coordinates":[-1.5395410061,42.7857170105],"type":"Point"}
}