{
  "type": "Feature",
  "properties": {
    "addr:full":"Calle de Jose Lopez, 33 Santa Cruz Palma Santa Cruz De Tenerife 38700",
    "addr:housenumber":"33",
    "addr:postcode":"38700",
    "addr:street":"Calle De Jose Lopez",
    "iso:country":"ES",
    "sg:address":"Calle de Jose Lopez, 33",
    "sg:city":"Santa Cruz Palma",
    "sg:orig_category":"Cristaler\u00cdas",
    "sg:phone":"+34 922 41 21 38",
    "sg:postcode":"38700",
    "sg:province":"Santa Cruz De Tenerife",
    "wof:name":"Garcia Sanchez Fermin",
    "wof:placetype":"venue"
},
  "geometry": {"coordinates":[-17.766084671,28.6862697601],"type":"Point"}
}