{
  "type": "Feature",
  "properties": {
    "iso:country":"ES",
    "sg:address":"Plaz Ayuntamiento, 1",
    "sg:city":"Mendavia",
    "sg:orig_category":"Asistencia Social",
    "sg:phone":"+34 948 69 51 01",
    "sg:postcode":"31587",
    "sg:province":"Navarra",
    "wof:name":"Mancomunidad De Servicios Sociales De Lazagurria Mendavia Sartaguda Y Sesma",
    "wof:placetype":"venue"
},
  "geometry": {"coordinates":[-2.2004408836,42.4421157837],"type":"Point"}
}