{
  "type": "Feature",
  "properties": {
    "addr:full":"Calle de Griferia, 1 Madrid Madrid 28037",
    "addr:housenumber":"1",
    "addr:postcode":"28037",
    "addr:street":"Calle De Griferia",
    "iso:country":"ES",
    "sg:address":"Calle de Griferia, 1",
    "sg:city":"Madrid",
    "sg:orig_category":"Molduras, Junquillos, Listones Y Molduras Perforadas",
    "sg:phone":"+34 913 06 10 81",
    "sg:postcode":"28037",
    "sg:province":"Madrid",
    "wof:name":"Garcia Sanchez Juan Antonio",
    "wof:placetype":"venue"
},
  "geometry": {"coordinates":[-3.6232161522,40.4260215759],"type":"Point"}
}