{
  "type": "Feature",
  "properties": {
    "addr:full":"Carrer de Barcelona (de), 54 Salou Tarragona 43840",
    "addr:housenumber":"54",
    "addr:postcode":"43840",
    "addr:street":"Carrer De Barcelona De",
    "iso:country":"ES",
    "sg:address":"Carrer de Barcelona (de), 54",
    "sg:city":"Salou",
    "sg:orig_category":"Venta De Caravanas, Casas M\u00d3viles, Camping",
    "sg:phone":"+34 977 35 28 10",
    "sg:postcode":"43840",
    "sg:province":"Tarragona",
    "wof:name":"George Caravanas Gabbers Scp",
    "wof:placetype":"venue"
},
  "geometry": {"coordinates":[1.1315360069,41.0815811157],"type":"Point"}
}