{
  "type": "Feature",
  "properties": {
    "iso:country":"ES",
    "sg:address":"Carrer de Pisa, 10",
    "sg:city":"Mas D'en Bosch",
    "sg:orig_category":"Molduras, Junquillos, Listones Y Molduras Perforadas",
    "sg:phone":"+34 977 36 47 59",
    "sg:postcode":"43850",
    "sg:province":"Tarragona",
    "wof:name":"Huguet Peris Joan Albert",
    "wof:placetype":"venue"
},
  "geometry": {"coordinates":[1.2455010414,41.1136932373],"type":"Point"}
}