{
  "type": "Feature",
  "properties": {
    "addr:full":"Ctra Almeria, 45 Abla Almer\u00eda 04510",
    "addr:housenumber":"45",
    "addr:postcode":"04510",
    "addr:street":"Ctra Almeria",
    "iso:country":"ES",
    "sg:address":"Ctra Almeria, 45",
    "sg:city":"Abla",
    "sg:orig_category":"Inmobiliaria (agencias)",
    "sg:phone":"+34 950 35 17 09",
    "sg:postcode":"04510",
    "sg:province":"Almer\u00eda",
    "sg:website":"www.invergestion.com",
    "wof:name":"Oliva & Ortiz Asociados, S.l.",
    "wof:placetype":"venue"
},
  "geometry": {"coordinates":[-2.7757019997,37.1436309814],"type":"Point"}
}