{
  "type": "Feature",
  "properties": {
    "addr:full":"Calle de Duque De La Victoria, 8 Malaga M\u00e1laga 29015",
    "addr:housenumber":"8",
    "addr:postcode":"29015",
    "addr:street":"Calle De Duque De La Victoria;Ma\u0301Laga",
    "iso:country":"ES",
    "sg:address":"Calle de Duque De La Victoria, 8",
    "sg:city":"Malaga",
    "sg:orig_category":"M\u00c9dicos: Cirug\u00cda Ortop\u00c9dica Y Traumatolog\u00cda",
    "sg:phone":"+34 952 22 60 57",
    "sg:postcode":"29015",
    "sg:province":"M\u00e1laga",
    "wof:name":"Zurita Ortiz-tallo Rafael",
    "wof:placetype":"venue"
},
  "geometry": {"coordinates":[-4.4196329117,36.7212333679],"type":"Point"}
}