{
  "type": "Feature",
  "properties": {
    "iso:country":"ES",
    "sg:address":"Calle de Bravo Murillo, 243",
    "sg:city":"Madrid",
    "sg:orig_category":"Institutos De Belleza",
    "sg:phone":"+34 915 70 62 41",
    "sg:postcode":"28020",
    "sg:province":"Madrid",
    "sg:website":"www.jofer.com",
    "wof:name":"Alfainterbautex S.l.",
    "wof:placetype":"venue"
},
  "geometry": {"coordinates":[-3.7005519867,40.4586334229],"type":"Point"}
}