{
  "type": "Feature",
  "properties": {
    "addr:full":"Arquitecto Pedro Cerdran, 6 Torre-pacheco Murcia 30700",
    "addr:housenumber":"6",
    "addr:postcode":"30700",
    "addr:street":"Arquitecto Pedro Cerdran",
    "iso:country":"ES",
    "sg:address":"Arquitecto Pedro Cerdran, 6",
    "sg:city":"Torre-pacheco",
    "sg:orig_category":"Papeler\u00cdas, Librer\u00cdas",
    "sg:phone":"+34 968 57 91 19",
    "sg:postcode":"30700",
    "sg:province":"Murcia",
    "wof:name":"Perez Madrid Ramon",
    "wof:placetype":"venue"
},
  "geometry": {"coordinates":[-0.9501640201,37.7475128174],"type":"Point"}
}