{
  "type": "Feature",
  "properties": {
    "iso:country":"ES",
    "sg:address":"Calle de Julio Cervera, 11",
    "sg:city":"Segorbe",
    "sg:orig_category":"Ropa Para Caballeros (al Por Menor)",
    "sg:phone":"+34 964 71 12 85",
    "sg:postcode":"12400",
    "sg:province":"Castell\u00f3n",
    "wof:name":"Escolano Lazaro Joaquin",
    "wof:placetype":"venue"
},
  "geometry": {"coordinates":[-0.4889430106,39.8517341614],"type":"Point"}
}