{
  "type": "Feature",
  "properties": {
    "addr:full":"Calle de Oliva De Plasencia, 1 Madrid Madrid 28044",
    "addr:housenumber":"1",
    "addr:postcode":"28044",
    "addr:street":"Calle De Oliva De Plasencia",
    "iso:country":"ES",
    "sg:address":"Calle de Oliva De Plasencia, 1",
    "sg:city":"Madrid",
    "sg:orig_category":"Centros Empresariales",
    "sg:phone":"+34 917 05 96 35",
    "sg:postcode":"28044",
    "sg:province":"Madrid",
    "wof:name":"Centro Empresarial Pinar San Jose S.a.",
    "wof:placetype":"venue"
},
  "geometry": {"coordinates":[-3.7792000771,40.3785476685],"type":"Point"}
}