{
  "type": "Feature",
  "properties": {
    "addr:full":"Urbanizacion Costabella, S/n Elviria M\u00e1laga 29604",
    "addr:housenumber":"s / n",
    "addr:postcode":"29604",
    "addr:street":"Urbanizacion Costabella;Ma\u0301Laga",
    "iso:country":"ES",
    "sg:address":"Urbanizacion Costabella, S/n",
    "sg:city":"Elviria",
    "sg:orig_category":"Empresas De Desmonte",
    "sg:phone":"+34 952 83 56 38",
    "sg:postcode":"29604",
    "sg:province":"M\u00e1laga",
    "wof:name":"El Capricho De Tres S.l.",
    "wof:placetype":"venue"
},
  "geometry": {"coordinates":[-4.7747840881,36.4966812134],"type":"Point"}
}