{
  "type": "Feature",
  "properties": {
    "iso:country":"ES",
    "sg:address":"Rbla Hospital, 52",
    "sg:city":"Vic",
    "sg:orig_category":"Asociaciones Humanitarias, De Cooperaci\u00d3n, De Acci\u00d3n Social",
    "sg:phone":"+34 938 85 12 41",
    "sg:postcode":"08500",
    "sg:province":"Barcelona",
    "wof:name":"Osona Contra El Cancer",
    "wof:placetype":"venue"
},
  "geometry": {"coordinates":[2.2520430088,41.9284210205],"type":"Point"}
}