{
  "type": "Feature",
  "properties": {
    "iso:country":"ES",
    "sg:address":"Calle de Madrid, 93",
    "sg:city":"San Jose Rinconada",
    "sg:orig_category":"Promotores Constructores",
    "sg:phone":"+34 955 79 13 56",
    "sg:postcode":"41300",
    "sg:province":"Sevilla",
    "wof:name":"Expo San Jose S.a.",
    "wof:placetype":"venue"
},
  "geometry": {"coordinates":[-5.9451971054,37.488697052],"type":"Point"}
}