{
  "type": "Feature",
  "properties": {
    "addr:full":"Barr Ferial (el), 147 Saron Cantabria 39620",
    "addr:housenumber":"147",
    "addr:postcode":"39620",
    "addr:street":"Saron",
    "iso:country":"ES",
    "sg:address":"Barr Ferial (el), 147",
    "sg:city":"Saron",
    "sg:orig_category":"M\u00c9dicos: Estomatolog\u00cda",
    "sg:phone":"+34 942 56 39 69",
    "sg:postcode":"39620",
    "sg:province":"Cantabria",
    "wof:name":"Santurtun De La Hoz Juan Carlos",
    "wof:placetype":"venue"
},
  "geometry": {"coordinates":[-3.8524339199,43.3249206543],"type":"Point"}
}