{
  "type": "Feature",
  "properties": {
    "iso:country":"ES",
    "sg:address":"Calle de Encarnacion, 6",
    "sg:city":"Valladolid",
    "sg:orig_category":"Arte, Cultura, Edici\u00d3n",
    "sg:phone":"+34 983 35 21 39",
    "sg:postcode":"47003",
    "sg:province":"Valladolid",
    "wof:name":"Madres Clarisas De Santa Isabel",
    "wof:placetype":"venue"
},
  "geometry": {"coordinates":[-4.7295007706,41.6550254822],"type":"Point"}
}