{
  "type": "Feature",
  "properties": {
    "addr:full":"Calle de Santiago, 33 Don Benito Badajoz 06400",
    "addr:housenumber":"33",
    "addr:postcode":"06400",
    "addr:street":"Calle De Santiago",
    "iso:country":"ES",
    "sg:address":"Calle de Santiago, 33",
    "sg:city":"Don Benito",
    "sg:orig_category":"Servicios Gsm",
    "sg:phone":"+34 924 80 34 62",
    "sg:postcode":"06400",
    "sg:province":"Badajoz",
    "wof:name":"Telefonia Garcia S.l.",
    "wof:placetype":"venue"
},
  "geometry": {"coordinates":[-5.8618788719,38.960849762],"type":"Point"}
}