{
  "type": "Feature",
  "properties": {
    "addr:full":"Ctra Soria-plasencia, S/n Barco De Avila \u00c1vila 05600",
    "addr:housenumber":"s / n",
    "addr:postcode":"05600",
    "addr:street":"Ctra Soria-Plasencia;A\u0301Vila",
    "iso:country":"ES",
    "sg:address":"Ctra Soria-plasencia, S/n",
    "sg:city":"Barco De Avila",
    "sg:orig_category":"Carnicer\u00cdas, Carnicer\u00cdas",
    "sg:phone":"+34 920 34 04 96",
    "sg:postcode":"05600",
    "sg:province":"\u00c1vila",
    "wof:name":"Francisco Lazaro Garcia-maria Luz Gonzalez Martin Cdad.",
    "wof:placetype":"venue"
},
  "geometry": {"coordinates":[-5.5109491348,40.3599700928],"type":"Point"}
}