{
  "type": "Feature",
  "properties": {
    "iso:country":"ES",
    "sg:address":"Carrer de Valls (de), 4",
    "sg:city":"Salou",
    "sg:orig_category":"Doctores En Medicina",
    "sg:phone":"+34 977 38 24 03",
    "sg:postcode":"43840",
    "sg:province":"Tarragona",
    "wof:name":"Simon Junqueras Antonio",
    "wof:placetype":"venue"
},
  "geometry": {"coordinates":[1.150496006,41.0694656372],"type":"Point"}
}