{
  "type": "Feature",
  "properties": {
    "addr:full":"Calle de Madrid, 33 Marina-oasis Alicante 03177",
    "addr:housenumber":"33",
    "addr:postcode":"03177",
    "addr:street":"Calle De Madrid;Alicante",
    "iso:country":"ES",
    "sg:address":"Calle de Madrid, 33",
    "sg:city":"Marina-oasis",
    "sg:orig_category":"Molduras, Junquillos, Listones Y Molduras Perforadas",
    "sg:phone":"+34 966 79 63 06",
    "sg:postcode":"03177",
    "sg:province":"Alicante",
    "wof:name":"Gomez Reguera Jose Manuel",
    "wof:placetype":"venue"
},
  "geometry": {"coordinates":[-0.6843640208,38.1279182434],"type":"Point"}
}