{
  "type": "Feature",
  "properties": {
    "addr:full":"Rua Eduardo Pondal, 21 Vilagarcia Pontevedra 36600",
    "addr:housenumber":"21",
    "addr:postcode":"36600",
    "addr:street":"Rua Eduardo Pondal",
    "iso:country":"ES",
    "sg:address":"Rua Eduardo Pondal, 21",
    "sg:city":"Vilagarcia",
    "sg:orig_category":"Ambulancias",
    "sg:phone":"+34 986 52 40 40",
    "sg:postcode":"36600",
    "sg:province":"Pontevedra",
    "wof:name":"Ambulancias De Arousa S.l.",
    "wof:placetype":"venue"
},
  "geometry": {"coordinates":[-8.7614088058,42.5986480713],"type":"Point"}
}