{
  "type": "Feature",
  "properties": {
    "addr:full":"Calle de Donostia-san Sebastian, 15 Errenteria Guip\u00f9zcoa 20100",
    "addr:postcode":"15;20100",
    "addr:street":"Calle De;Guipu\u0300Zcoa",
    "iso:country":"ES",
    "sg:address":"Calle de Donostia-san Sebastian, 15",
    "sg:city":"Errenteria",
    "sg:orig_category":"Negocio De Materiales De Construcci\u00d3n",
    "sg:phone":"+34 943 51 12 44",
    "sg:postcode":"20100",
    "sg:province":"Guip\u00f9zcoa",
    "wof:name":"Zapirain Odriozola Maria Antonia",
    "wof:placetype":"venue"
},
  "geometry": {"coordinates":[-1.9030697346,43.3155250549],"type":"Point"}
}