{
  "type": "Feature",
  "properties": {
    "iso:country":"ES",
    "sg:address":"Pla\u00c7 Doctor Turon, 1",
    "sg:city":"Arbucies",
    "sg:orig_category":"Panader\u00cdas, Panader\u00cdas",
    "sg:phone":"+34 972 86 00 64",
    "sg:postcode":"17401",
    "sg:province":"Girona",
    "wof:name":"Ayma Pastisseria I Pizzeria S.l.",
    "wof:placetype":"venue"
},
  "geometry": {"coordinates":[2.518239975,41.8144645691],"type":"Point"}
}