{
  "type": "Feature",
  "properties": {
    "addr:full":"Calle de Fuentes Carrionas, S/n Velilla Rio Carrion Palencia 34886",
    "addr:housenumber":"s",
    "addr:postcode":"34886",
    "addr:street":"Calle De Fuentes Carrionas;/ N",
    "iso:country":"ES",
    "sg:address":"Calle de Fuentes Carrionas, S/n",
    "sg:city":"Velilla Rio Carrion",
    "sg:orig_category":"Supermercados Y Hipermercados",
    "sg:phone":"+34 979 86 14 08",
    "sg:postcode":"34886",
    "sg:province":"Palencia",
    "wof:name":"Nieto Mancebo Jose Maria",
    "wof:placetype":"venue"
},
  "geometry": {"coordinates":[-4.8473639488,42.8258285522],"type":"Point"}
}