{
  "type": "Feature",
  "properties": {
    "iso:country":"ES",
    "sg:address":"Calle de Mesones, 1",
    "sg:city":"Granada",
    "sg:orig_category":"M\u00c9dicos: Estomatolog\u00cda",
    "sg:phone":"+34 958 25 54 49",
    "sg:postcode":"18001",
    "sg:province":"Granada",
    "wof:name":"Linares Garcia Maria",
    "wof:placetype":"venue"
},
  "geometry": {"coordinates":[-3.5997190475,37.1737098694],"type":"Point"}
}