{
  "type": "Feature",
  "properties": {
    "iso:country":"ES",
    "sg:address":"Calle de Collado De La Mina, 7",
    "sg:city":"Madrid",
    "sg:orig_category":"Arquitectos",
    "sg:phone":"+34 913 78 41 25",
    "sg:postcode":"28035",
    "sg:province":"Madrid",
    "wof:name":"Cezar Toledo Carlos",
    "wof:placetype":"venue"
},
  "geometry": {"coordinates":[-3.7180433273,40.4902381897],"type":"Point"}
}