{
  "type": "Feature",
  "properties": {
    "iso:country":"ES",
    "sg:address":"Calle de Santa Cristina, 1",
    "sg:city":"Olias Rey",
    "sg:orig_category":"Negocio De Materiales De Construcci\u00d3n",
    "sg:phone":"+34 925 49 00 06",
    "sg:postcode":"45280",
    "sg:province":"Toledo",
    "wof:name":"Balleteros Dise\u00f1os Ba\u00f1os S.l.",
    "wof:placetype":"venue"
},
  "geometry": {"coordinates":[-3.9923288822,39.9453010559],"type":"Point"}
}