{
  "type": "Feature",
  "properties": {
    "iso:country":"ES",
    "sg:address":"Ctra La Magdalena, S/n",
    "sg:city":"Guardo",
    "sg:orig_category":"Empresas De Carpinter\u00cda",
    "sg:phone":"+34 979 85 26 56",
    "sg:postcode":"34880",
    "sg:province":"Palencia",
    "sg:website":"www.paginasamarillas.es",
    "wof:name":"Perez Perez Carlos",
    "wof:placetype":"venue"
},
  "geometry": {"coordinates":[-4.866874218,42.7786102295],"type":"Point"}
}