{
  "type": "Feature",
  "properties": {
    "iso:country":"ES",
    "sg:address":"Calle de Marcos Grijalvo, 8",
    "sg:city":"Sestao",
    "sg:orig_category":"Peluqueros: De Se\u00d1oras",
    "sg:phone":"+34 944 72 32 06",
    "sg:postcode":"48910",
    "sg:province":"Vizcaya",
    "wof:name":"C.b. Estilistas",
    "wof:placetype":"venue"
},
  "geometry": {"coordinates":[-2.998652935,43.3084106445],"type":"Point"}
}