{
  "type": "Feature",
  "properties": {
    "iso:country":"ES",
    "sg:address":"Calle de Jardines, 24",
    "sg:city":"Viana Cega",
    "sg:orig_category":"Suministros Y Materiales Industriales",
    "sg:phone":"+34 983 55 42 18",
    "sg:postcode":"47150",
    "sg:province":"Valladolid",
    "wof:name":"Torniduero S.l.",
    "wof:placetype":"venue"
},
  "geometry": {"coordinates":[-4.7527589798,41.5244483948],"type":"Point"}
}