{
  "type": "Feature",
  "properties": {
    "addr:full":"Plg Ind Base Dos Mil, 2 Lorqui Murcia 30564",
    "addr:postcode":"30564",
    "iso:country":"ES",
    "sg:address":"Plg Ind Base Dos Mil, 2",
    "sg:city":"Lorqui",
    "sg:orig_category":"Limpieza Industrial",
    "sg:phone":"+34 968 67 60 73",
    "sg:postcode":"30564",
    "sg:province":"Murcia",
    "wof:name":"Camaches Pardo Encarnacion",
    "wof:placetype":"venue"
},
  "geometry": {"coordinates":[-1.2517440319,38.0802001953],"type":"Point"}
}