{
  "type": "Feature",
  "properties": {
    "iso:country":"ES",
    "sg:address":"Avda Chapi, 2",
    "sg:city":"Elda",
    "sg:orig_category":"Ense\u00d1anza: Idiomas",
    "sg:phone":"+34 965 38 34 55",
    "sg:postcode":"03600",
    "sg:province":"Alicante",
    "wof:name":"Teruel Pardo Francisco",
    "wof:placetype":"venue"
},
  "geometry": {"coordinates":[-0.792106986,38.4723701477],"type":"Point"}
}