{
  "type": "Feature",
  "properties": {
    "iso:country":"ES",
    "sg:address":"Avda Alamos (los), 2",
    "sg:city":"Jerez De La Frontera",
    "sg:orig_category":"Cl\u00cdnicas M\u00c9dicas",
    "sg:phone":"+34 956 18 07 56",
    "sg:postcode":"11407",
    "sg:province":"C\u00e1diz",
    "wof:name":"Policlinica San Mauricio S.a.",
    "wof:placetype":"venue"
},
  "geometry": {"coordinates":[-6.1364450455,36.7021408081],"type":"Point"}
}