{
  "type": "Feature",
  "properties": {
    "iso:country":"ES",
    "sg:address":"Calle de Santa Doradia, 14",
    "sg:city":"Gijon",
    "sg:orig_category":"Agencias Y Agentes Comerciales, Representantes",
    "sg:phone":"+34 985 33 80 19",
    "sg:postcode":"33202",
    "sg:province":"Asturias",
    "sg:website":"www.felipegonzalez.info",
    "wof:name":"Servicios De Comercio Y Exclusivas S.l.",
    "wof:placetype":"venue"
},
  "geometry": {"coordinates":[-5.6571130753,43.5390625],"type":"Point"}
}