{
  "type": "Feature",
  "properties": {
    "iso:country":"ES",
    "sg:address":"Avda Maisonnave, 53",
    "sg:city":"Alacant",
    "sg:orig_category":"Centros Comerciales Y Grandes Tiendas",
    "sg:phone":"+34 965 92 50 01",
    "sg:postcode":"03...",
    "sg:province":"Alicante",
    "sg:website":"www.elcorteingles.es",
    "wof:name":"El Corte Ingles S.a.",
    "wof:placetype":"venue"
},
  "geometry": {"coordinates":[-0.4933019876,38.3432617188],"type":"Point"}
}