{
  "type": "Feature",
  "properties": {
    "iso:country":"ES",
    "sg:address":"Calle de Rosario, 5",
    "sg:city":"Munera",
    "sg:orig_category":"Pintura, Barniz, Productos Asimilables (fabricaci\u00d3n, Al Por Mayor)",
    "sg:phone":"+34 967 37 26 06",
    "sg:postcode":"02612",
    "sg:province":"Albacete",
    "wof:name":"Resin Alba S.l.",
    "wof:placetype":"venue"
},
  "geometry": {"coordinates":[-2.481304884,39.0438613892],"type":"Point"}
}