{
  "type": "Feature",
  "properties": {
    "iso:country":"ES",
    "sg:address":"Carrer de Duero, 68",
    "sg:city":"Barcelona",
    "sg:orig_category":"Inform\u00c1tica (estudios, Servicios, Asesor\u00cda, Formaci\u00d3n)",
    "sg:phone":"+34 933 58 58 78",
    "sg:postcode":"08031",
    "sg:province":"Barcelona",
    "wof:name":"Jolis Informatic S.l.",
    "wof:placetype":"venue"
},
  "geometry": {"coordinates":[2.1634850502,41.4303665161],"type":"Point"}
}