{
  "type": "Feature",
  "properties": {
    "addr:full":"Calle de Arenal, 1 S. Fernando C\u00e1diz 11100",
    "addr:housenumber":"1",
    "addr:postcode":"11100",
    "addr:street":"Calle De Arenal;S. Fernando Ca\u0301Diz",
    "iso:country":"ES",
    "sg:address":"Calle de Arenal, 1",
    "sg:city":"S. Fernando",
    "sg:orig_category":"Laboratorios Y Cl\u00cdnicas Veterinarias",
    "sg:phone":"+34 956 88 72 75",
    "sg:postcode":"11100",
    "sg:province":"C\u00e1diz",
    "wof:name":"Cifuentes Luna Francisco Joaquin",
    "wof:placetype":"venue"
},
  "geometry": {"coordinates":[-6.2662034035,36.5071029663],"type":"Point"}
}