{
  "type": "Feature",
  "properties": {
    "addr:full":"Calle de Mayor, 356 Raal Murcia 30139",
    "addr:housenumber":"356",
    "addr:postcode":"30139",
    "addr:street":"Calle De Mayor",
    "iso:country":"ES",
    "sg:address":"Calle de Mayor, 356",
    "sg:city":"Raal",
    "sg:orig_category":"Centros Empresariales",
    "sg:phone":"+34 968 60 27 30",
    "sg:postcode":"30139",
    "sg:province":"Murcia",
    "wof:name":"Hemahe S.l.",
    "wof:placetype":"venue"
},
  "geometry": {"coordinates":[-1.016692996,38.0462188721],"type":"Point"}
}