{
  "type": "Feature",
  "properties": {
    "iso:country":"ES",
    "sg:address":"Rond San Cristobal Ingurubidea, 242",
    "sg:city":"Zizur Mayor",
    "sg:orig_category":"Alquiler De Veh\u00cdculos: Turismos Y Utilitarios",
    "sg:phone":"+34 948 18 93 33",
    "sg:postcode":"31180",
    "sg:province":"Navarra",
    "wof:name":"Microbuses J Brun S.l.",
    "wof:placetype":"venue"
},
  "geometry": {"coordinates":[-1.689563036,42.7820053101],"type":"Point"}
}