{
  "type": "Feature",
  "properties": {
    "iso:country":"ES",
    "sg:address":"Avda Carmen Miranda, 8",
    "sg:city":"Pravia",
    "sg:orig_category":"Panader\u00cdas, Panader\u00cdas",
    "sg:phone":"+34 985 82 09 82",
    "sg:postcode":"33120",
    "sg:province":"Asturias",
    "wof:name":"Pastur Cancio David",
    "wof:placetype":"venue"
},
  "geometry": {"coordinates":[-6.1124000549,43.4886741638],"type":"Point"}
}