{
  "type": "Feature",
  "properties": {
    "addr:full":"Calle de Trinidad, 46 Valverde Camino Huelva 21600",
    "addr:housenumber":"46",
    "addr:postcode":"21600",
    "addr:street":"Calle De Trinidad;Camino Huelva",
    "iso:country":"ES",
    "sg:address":"Calle de Trinidad, 46",
    "sg:city":"Valverde Camino",
    "sg:orig_category":"Inform\u00c1tica: Mantenimiento Y Reparaci\u00d3n De Ordenadores",
    "sg:phone":"+34 959 55 33 53",
    "sg:postcode":"21600",
    "sg:province":"Huelva",
    "wof:name":"Centro De Estudios Informaticos 91 S.l.",
    "wof:placetype":"venue"
},
  "geometry": {"coordinates":[-6.7562527657,37.5727996826],"type":"Point"}
}