{
  "type": "Feature",
  "properties": {
    "addr:full":"Calle de Villarrobledo, 41 Socuellamos Ciudad Real 13630",
    "addr:housenumber":"41",
    "addr:postcode":"13630",
    "addr:street":"Calle De Villarrobledo",
    "iso:country":"ES",
    "sg:address":"Calle de Villarrobledo, 41",
    "sg:city":"Socuellamos",
    "sg:orig_category":"Contenedores (mercanc\u00cdas)",
    "sg:phone":"+34 926 53 07 12",
    "sg:postcode":"13630",
    "sg:province":"Ciudad Real",
    "wof:name":"Huertas Ruiz Pedro",
    "wof:placetype":"venue"
},
  "geometry": {"coordinates":[-2.7840590477,39.2855224609],"type":"Point"}
}