{
  "type": "Feature",
  "properties": {
    "iso:country":"ES",
    "sg:address":"Calle de San Anton, 44",
    "sg:city":"Toro",
    "sg:orig_category":"Comerciantes Al Por Mayor De Vinos, Licores Y Alcoholes",
    "sg:phone":"+34 980 69 16 83",
    "sg:postcode":"49800",
    "sg:province":"Zamora",
    "wof:name":"Aldisza S.l.",
    "wof:placetype":"venue"
},
  "geometry": {"coordinates":[-5.4009647369,41.5246429443],"type":"Point"}
}