{
  "type": "Feature",
  "properties": {
    "addr:full":"Carrer de Botanica, 21 Hospitalet Llobregat Barcelona 08908",
    "addr:housenumber":"21",
    "addr:postcode":"08908",
    "addr:street":"Carrer De Botanica",
    "iso:country":"ES",
    "sg:address":"Carrer de Botanica, 21",
    "sg:city":"Hospitalet Llobregat",
    "sg:orig_category":"Promotores Constructores",
    "sg:phone":"+34 933 35 12 38",
    "sg:postcode":"08908",
    "sg:province":"Barcelona",
    "wof:name":"Urbanismo Y Contratas S.a.",
    "wof:placetype":"venue"
},
  "geometry": {"coordinates":[2.1301000118,41.3514099121],"type":"Point"}
}