{
  "type": "Feature",
  "properties": {
    "addr:full":"Calle de Portillo De Balboa, 47 Valladolid Valladolid 47010",
    "addr:housenumber":"47",
    "addr:postcode":"47010",
    "addr:street":"Calle De Portillo De Balboa",
    "iso:country":"ES",
    "sg:address":"Calle de Portillo De Balboa, 47",
    "sg:city":"Valladolid",
    "sg:orig_category":"Molduras, Junquillos, Listones Y Molduras Perforadas",
    "sg:phone":"+34 983 25 10 86",
    "sg:postcode":"47010",
    "sg:province":"Valladolid",
    "wof:name":"Gomez Senovilla Maria De Guadalupe",
    "wof:placetype":"venue"
},
  "geometry": {"coordinates":[-4.7194328308,41.6623077393],"type":"Point"}
}