{
  "type": "Feature",
  "properties": {
    "addr:full":"Ptda Bovalar, S/n Polop Alicante 03520",
    "addr:housenumber":"s / n",
    "addr:postcode":"03520",
    "addr:street":"Ptda Bovalar",
    "iso:country":"ES",
    "sg:address":"Ptda Bovalar, S/n",
    "sg:city":"Polop",
    "sg:orig_category":"Agricultores, Agricultores",
    "sg:phone":"+34 965 87 01 16",
    "sg:postcode":"03520",
    "sg:province":"Alicante",
    "wof:name":"Sanchez Ripoll Carmen",
    "wof:placetype":"venue"
},
  "geometry": {"coordinates":[-0.1381530017,38.6176605225],"type":"Point"}
}