{
  "type": "Feature",
  "properties": {
    "addr:full":"Calle de Isidro Diaz, S/n Tarajalejo Las Palmas 35627",
    "addr:postcode":"35627",
    "addr:street":"Calle De Isidro Diaz S / N;Palmas",
    "iso:country":"ES",
    "sg:address":"Calle de Isidro Diaz, S/n",
    "sg:city":"Tarajalejo",
    "sg:orig_category":"Ropa Para Se\u00d1oras Y Caballeros (al Por Menor)",
    "sg:phone":"+34 928 16 10 54",
    "sg:postcode":"35627",
    "sg:province":"Las Palmas",
    "wof:name":"Acosta Cabrera Lorena",
    "wof:placetype":"venue"
},
  "geometry": {"coordinates":[-14.1162796021,28.1919937134],"type":"Point"}
}