{
  "type": "Feature",
  "properties": {
    "addr:full":"Ctra Cadiz, S/n Dos Hermanas Sevilla 41700",
    "addr:housenumber":"s / n",
    "addr:postcode":"41700",
    "addr:street":"Ctra Cadiz",
    "iso:country":"ES",
    "sg:address":"Ctra Cadiz, S/n",
    "sg:city":"Dos Hermanas",
    "sg:orig_category":"Tiendas De Grano, Frutas Y Legumbres Secas (al Por Menor)",
    "sg:phone":"+34 955 66 37 36",
    "sg:postcode":"41700",
    "sg:province":"Sevilla",
    "wof:name":"Productos Alimenticios Belros S.a.",
    "wof:placetype":"venue"
},
  "geometry": {"coordinates":[-5.9281339645,37.2829055786],"type":"Point"}
}