{
  "type": "Feature",
  "properties": {
    "addr:full":"Avda. Erasa, S/n Benalmadena-costa M\u00e1laga 29630",
    "addr:housenumber":"s",
    "addr:postcode":"29630",
    "addr:street":"Avda. Erasa;/ N Benalmadena-Costa Ma\u0301Laga",
    "iso:country":"ES",
    "sg:address":"Avda. Erasa, S/n",
    "sg:city":"Benalmadena-costa",
    "sg:orig_category":"Ingenier\u00cda, Centros De Estudios (diversos)",
    "sg:phone":"+34 952 44 78 36",
    "sg:postcode":"29630",
    "sg:province":"M\u00e1laga",
    "wof:name":"Zemholitour S.l.",
    "wof:placetype":"venue"
},
  "geometry": {"coordinates":[-4.5366225243,36.59998703],"type":"Point"}
}