{
  "type": "Feature",
  "properties": {
    "addr:full":"Calle de Ramon Poll, 7 Llanos De Aridane Santa Cruz De Tenerife 38760",
    "addr:housenumber":"7",
    "addr:postcode":"38760",
    "addr:street":"Calle De Ramon Poll",
    "iso:country":"ES",
    "sg:address":"Calle de Ramon Poll, 7",
    "sg:city":"Llanos De Aridane",
    "sg:orig_category":"Cooperativas Agr\u00cdcolas",
    "sg:phone":"+34 922 46 16 56",
    "sg:postcode":"38760",
    "sg:province":"Santa Cruz De Tenerife",
    "wof:name":"Cooperativa Covalle",
    "wof:placetype":"venue"
},
  "geometry": {"coordinates":[-17.9158535004,28.6609325409],"type":"Point"}
}