{
  "type": "Feature",
  "properties": {
    "iso:country":"ES",
    "sg:address":"Cmno Larragane Bidea, 12",
    "sg:city":"Trobika",
    "sg:orig_category":"Puertas Y Portales",
    "sg:phone":"+34 946 74 32 01",
    "sg:postcode":"48100",
    "sg:province":"Vizcaya",
    "sg:website":"www.talleres-barrena.com",
    "wof:name":"Talleres Barrena S.l.",
    "wof:placetype":"venue"
},
  "geometry": {"coordinates":[-2.8507039547,43.3569412231],"type":"Point"}
}