{
  "type": "Feature",
  "properties": {
    "iso:country":"ES",
    "sg:address":"Pase Maritimo Rey De Espa\u00d1a, 118",
    "sg:city":"Fuengirola",
    "sg:orig_category":"Aguas (distribuci\u00d3n, Servicios)",
    "sg:phone":"+34 952 66 10 37",
    "sg:postcode":"29640",
    "sg:province":"M\u00e1laga",
    "wof:name":"Reina Moreno Rafael",
    "wof:placetype":"venue"
},
  "geometry": {"coordinates":[-4.6188530922,36.5424423218],"type":"Point"}
}