{
  "type": "Feature",
  "properties": {
    "addr:full":"Calle de Jose Costa, 5 San Ildefonso O La Granja Segovia 40100",
    "addr:housenumber":"5",
    "addr:postcode":"40100",
    "addr:street":"Calle De Jose Costa;O",
    "iso:country":"ES",
    "sg:address":"Calle de Jose Costa, 5",
    "sg:city":"San Ildefonso O La Granja",
    "sg:orig_category":"Peluquer\u00cdas, Peluquer\u00cda Mixta",
    "sg:phone":"+34 921 47 13 40",
    "sg:postcode":"40100",
    "sg:province":"Segovia",
    "wof:name":"Herrero Valverde Pablo Antonio",
    "wof:placetype":"venue"
},
  "geometry": {"coordinates":[-4.0059990883,40.9014167786],"type":"Point"}
}