{
  "type": "Feature",
  "properties": {
    "iso:country":"ES",
    "sg:address":"Avda Fuentesauco, 78",
    "sg:city":"Poligono Industrial Los Villares",
    "sg:orig_category":"Venta, Instalaci\u00d3n De Sistemas De Alarmas Y Vigilancia",
    "sg:phone":"+34 923 20 33 65",
    "sg:postcode":"37184",
    "sg:province":"Salamanca",
    "wof:name":"Blindados Del Norte S.a.",
    "wof:placetype":"venue"
},
  "geometry": {"coordinates":[-5.6465888023,40.9933815002],"type":"Point"}
}