{
  "type": "Feature",
  "properties": {
    "addr:full":"Calle de General Primo De Rivera, S/n Tapia Casariego Asturias 33740",
    "addr:housenumber":"s / n",
    "addr:postcode":"33740",
    "addr:street":"Calle De General Primo De Rivera;Casariego",
    "iso:country":"ES",
    "sg:address":"Calle de General Primo De Rivera, S/n",
    "sg:city":"Tapia Casariego",
    "sg:orig_category":"Mec\u00c1nico Del Autom\u00d3vil",
    "sg:phone":"+34 985 62 80 27",
    "sg:postcode":"33740",
    "sg:province":"Asturias",
    "wof:name":"Talleres Catuxo S. A.",
    "wof:placetype":"venue"
},
  "geometry": {"coordinates":[-6.9389953613,43.5678291321],"type":"Point"}
}