{
  "type": "Feature",
  "properties": {
    "iso:country":"ES",
    "sg:address":"Urb Balcon Del Golf, 21",
    "sg:city":"Nueva Andalucia",
    "sg:orig_category":"Asociaciones Y Clubs Deportivos",
    "sg:phone":"+34 952 81 39 95",
    "sg:postcode":"29660",
    "sg:province":"M\u00e1laga",
    "sg:website":"www.h2o-sports.org",
    "wof:name":"H2o Sports S.l.",
    "wof:placetype":"venue"
},
  "geometry": {"coordinates":[-4.9712438583,36.5208396912],"type":"Point"}
}