{
  "type": "Feature",
  "properties": {
    "addr:full":"Calle de Fotografos Darblade, 21 Torrevieja Alicante 03180",
    "addr:housenumber":"21",
    "addr:postcode":"03180",
    "addr:street":"Calle De Fotografos Darblade",
    "iso:country":"ES",
    "sg:address":"Calle de Fotografos Darblade, 21",
    "sg:city":"Torrevieja",
    "sg:orig_category":"Bisuter\u00cda, Joyer\u00cda, Relojer\u00cda (al Por Menor)",
    "sg:phone":"+34 965 71 11 89",
    "sg:postcode":"03180",
    "sg:province":"Alicante",
    "wof:name":"Sanchez Tordjman Maria Luisa",
    "wof:placetype":"venue"
},
  "geometry": {"coordinates":[-0.6819390059,37.9769096375],"type":"Point"}
}