{
  "type": "Feature",
  "properties": {
    "iso:country":"ES",
    "sg:address":"C/ Eivissa, S/n",
    "sg:city":"Inca",
    "sg:orig_category":"Transportes Por V\u00cdas Navegables",
    "sg:phone":"+34 971 50 39 47",
    "sg:postcode":"07300",
    "sg:province":"Islas Baleares",
    "wof:name":"Amer E Hijos S.a.",
    "wof:placetype":"venue"
},
  "geometry": {"coordinates":[2.9194977283,39.7217483521],"type":"Point"}
}