{
  "type": "Feature",
  "properties": {
    "iso:country":"ES",
    "sg:address":"Calle de Romeria, 5",
    "sg:city":"Ajalvir",
    "sg:orig_category":"Muebles Y Accesorios Para Cocinas Y Cuartos De Ba\u00d1o (al Por Menor)",
    "sg:phone":"+34 918 84 32 36",
    "sg:postcode":"28864",
    "sg:province":"Madrid",
    "sg:website":"www.masave.com",
    "wof:name":"Masave Sociedad Cooperativa Madrile\u00f1a",
    "wof:placetype":"venue"
},
  "geometry": {"coordinates":[-3.4807798862,40.5031318665],"type":"Point"}
}