{
  "type": "Feature",
  "properties": {
    "addr:full":"Calle de Ingeniero La Cierva, 31 Sevilla Sevilla 41006",
    "addr:housenumber":"31",
    "addr:postcode":"41006",
    "addr:street":"Calle De Ingeniero La Cierva",
    "iso:country":"ES",
    "sg:address":"Calle de Ingeniero La Cierva, 31",
    "sg:city":"Sevilla",
    "sg:orig_category":"Centros De Coordinaci\u00d3n",
    "sg:phone":"+34 954 66 00 05",
    "sg:postcode":"41006",
    "sg:province":"Sevilla",
    "wof:name":"Suarez Penalver S.l",
    "wof:placetype":"venue"
},
  "geometry": {"coordinates":[-5.9498033524,37.3720016479],"type":"Point"}
}