{
  "type": "Feature",
  "properties": {
    "addr:full":"Calle de Gutenberg, 16 Madrid Madrid 28014",
    "addr:housenumber":"16",
    "addr:postcode":"madrid;28014",
    "addr:street":"Calle De Gutenberg",
    "iso:country":"ES",
    "sg:address":"Calle de Gutenberg, 16",
    "sg:city":"Madrid",
    "sg:orig_category":"Empresarios Y Productoras De Espect\u00c1culos",
    "sg:phone":"+34 914 33 32 05",
    "sg:postcode":"28014",
    "sg:province":"Madrid",
    "wof:name":"Recuenco Sanchez-aguilera Maria Luz",
    "wof:placetype":"venue"
},
  "geometry": {"coordinates":[-3.680711031,40.4059944153],"type":"Point"}
}