{
  "type": "Feature",
  "properties": {
    "iso:country":"ES",
    "sg:address":"Calle de Virgen De La Piedad, 1",
    "sg:city":"Villaharta",
    "sg:orig_category":"Administraciones Regionales, Departamentales Y Locales",
    "sg:phone":"+34 957 36 71 35",
    "sg:postcode":"14210",
    "sg:province":"C\u00f3rdoba",
    "wof:name":"Ayuntamiento De Villaharta",
    "wof:placetype":"venue"
},
  "geometry": {"coordinates":[-4.9019389153,38.1395339966],"type":"Point"}
}