{
  "type": "Feature",
  "properties": {
    "iso:country":"ES",
    "sg:address":"Urb Altos Del Limonar, 13",
    "sg:city":"El Chaparral",
    "sg:orig_category":"Caf\u00c9s, Bares, Cervecer\u00cdas",
    "sg:phone":"+34 966 78 94 06",
    "sg:postcode":"03180",
    "sg:province":"Alicante",
    "wof:name":"Hernandez Garcia Josefa",
    "wof:placetype":"venue"
},
  "geometry": {"coordinates":[-0.6536790133,38.0173606873],"type":"Point"}
}