{
  "type": "Feature",
  "properties": {
    "iso:country":"ES",
    "sg:address":"Rua Paz (da), 16",
    "sg:city":"Ourense",
    "sg:orig_category":"Bisuter\u00cda, Joyer\u00cda, Relojer\u00cda (al Por Menor)",
    "sg:phone":"+34 988 22 17 42",
    "sg:postcode":"32005",
    "sg:province":"Ourense",
    "wof:name":"Fernandez Saco Odilo",
    "wof:placetype":"venue"
},
  "geometry": {"coordinates":[-7.8632659912,42.3371925354],"type":"Point"}
}