{
  "type": "Feature",
  "properties": {
    "iso:country":"ES",
    "sg:address":"Plaz Canterias (de Las), 7",
    "sg:city":"Caceres",
    "sg:orig_category":"Promotores Constructores",
    "sg:phone":"+34 927 26 12 05",
    "sg:postcode":"10003",
    "sg:province":"C\u00e1ceres",
    "wof:name":"Delphi 98 S.l.",
    "wof:placetype":"venue"
},
  "geometry": {"coordinates":[-6.3703651428,39.4777412415],"type":"Point"}
}