{
  "type": "Feature",
  "properties": {
    "addr:full":"Carrer de Mare De Deu Del Carmen, 6 Monovar Alicante 03640",
    "addr:housenumber":"6",
    "addr:postcode":"03640",
    "addr:street":"Carrer De Mare De Deu Del Carmen;Alicante",
    "iso:country":"ES",
    "sg:address":"Carrer de Mare De Deu Del Carmen, 6",
    "sg:city":"Monovar",
    "sg:orig_category":"Confecci\u00d3n De Zapatos",
    "sg:phone":"+34 965 47 22 11",
    "sg:postcode":"03640",
    "sg:province":"Alicante",
    "wof:name":"Femoc S.l.",
    "wof:placetype":"venue"
},
  "geometry": {"coordinates":[-0.8328149915,38.4376945496],"type":"Point"}
}