{
  "type": "Feature",
  "properties": {
    "iso:country":"ES",
    "sg:address":"Carrer de Esglesia, 7",
    "sg:city":"Sabadell",
    "sg:orig_category":"Asociaciones, Organismos Culturales Y Socioeducativos",
    "sg:phone":"+34 937 27 41 11",
    "sg:postcode":"08204",
    "sg:province":"Barcelona",
    "wof:name":"Oficina De Dinamitzacio Del Centre De Sabadell",
    "wof:placetype":"venue"
},
  "geometry": {"coordinates":[2.1084399223,41.5470085144],"type":"Point"}
}