{
  "type": "Feature",
  "properties": {
    "addr:full":"Calle de Estella, 12 Azagra Navarra 31560",
    "addr:housenumber":"12",
    "addr:postcode":"31560",
    "addr:street":"Calle De Estella",
    "iso:country":"ES",
    "sg:address":"Calle de Estella, 12",
    "sg:city":"Azagra",
    "sg:orig_category":"Conservas De Legumbres (fabricaci\u00d3n, Al Por Mayor)",
    "sg:phone":"+34 948 69 21 62",
    "sg:postcode":"31560",
    "sg:province":"Navarra",
    "wof:name":"Conservas Teo San Marcelino S.l.",
    "wof:placetype":"venue"
},
  "geometry": {"coordinates":[-1.8947319984,42.3080444336],"type":"Point"}
}