{
  "type": "Feature",
  "properties": {
    "iso:country":"ES",
    "sg:address":"Mogor(mogor), 5",
    "sg:city":"Mogor",
    "sg:orig_category":"Iglesia Cat\u00d3lica",
    "sg:phone":"+34 981 41 40 20",
    "sg:postcode":"15337",
    "sg:province":"La Coru\u00f1a",
    "wof:name":"Parroquia De Santa Maria De Mogor",
    "wof:placetype":"venue"
},
  "geometry": {"coordinates":[-7.7050490379,43.7389259338],"type":"Point"}
}