{
  "type": "Feature",
  "properties": {
    "addr:full":"Avda Paz De (la), 36 Logro\u00f1o La Rioja 26004",
    "addr:housenumber":"36",
    "addr:postcode":"26004",
    "addr:street":"Avda Paz De La;Rioja",
    "iso:country":"ES",
    "sg:address":"Avda Paz De (la), 36",
    "sg:city":"Logro\u00f1o",
    "sg:orig_category":"Ense\u00d1anza: Idiomas",
    "sg:phone":"+34 941 23 08 55",
    "sg:postcode":"26004",
    "sg:province":"La Rioja",
    "wof:name":"Centro De Ense\u00f1anza De La Rioja S.l.",
    "wof:placetype":"venue"
},
  "geometry": {"coordinates":[-2.4364690781,42.4647216797],"type":"Point"}
}