{
  "type": "Feature",
  "properties": {
    "addr:full":"Av Ignasi Wallis, 36 Eivissa Islas Baleares 07800",
    "addr:housenumber":"36",
    "addr:postcode":"07800",
    "addr:street":"Av Ignasi Wallis",
    "iso:country":"ES",
    "sg:address":"Av Ignasi Wallis, 36",
    "sg:city":"Eivissa",
    "sg:orig_category":"Muebles",
    "sg:phone":"+34 971 31 11 72",
    "sg:postcode":"07800",
    "sg:province":"Islas Baleares",
    "wof:name":"Vivienda Pitiusa S.l",
    "wof:placetype":"venue"
},
  "geometry": {"coordinates":[1.4301947355,38.9125556946],"type":"Point"}
}