{
  "type": "Feature",
  "properties": {
    "addr:full":"Calle de Rafael Alberti, S/n Velez-malaga M\u00e1laga 29700",
    "addr:housenumber":"s / n",
    "addr:postcode":"29700",
    "addr:street":"Calle De Rafael Alberti",
    "iso:country":"ES",
    "sg:address":"Calle de Rafael Alberti, S/n",
    "sg:city":"Velez-malaga",
    "sg:orig_category":"Quincaller\u00cda (al Por Menor)",
    "sg:phone":"+34 952 50 01 47",
    "sg:postcode":"29700",
    "sg:province":"M\u00e1laga",
    "wof:name":"Vicente Cabello Jose De",
    "wof:placetype":"venue"
},
  "geometry": {"coordinates":[-4.0973138809,36.775554657],"type":"Point"}
}