{
  "type": "Feature",
  "properties": {
    "iso:country":"ES",
    "sg:address":"Calle de Infanta Isabel, 1",
    "sg:city":"Icod De Los Vinos",
    "sg:orig_category":"Cl\u00cdnicas Dentales",
    "sg:phone":"+34 922 12 23 83",
    "sg:postcode":"38430",
    "sg:province":"Santa Cruz De Tenerife",
    "wof:name":"Luis-ravelo Rodriguez Dario",
    "wof:placetype":"venue"
},
  "geometry": {"coordinates":[-16.7186164856,28.3691616058],"type":"Point"}
}