{
  "type": "Feature",
  "properties": {
    "iso:country":"ES",
    "sg:address":"Las Margaritas, S/n",
    "sg:city":"S. Agustin-playa Ingles",
    "sg:orig_category":"Ense\u00d1anza, Formaci\u00d3n Profesional: Aprendizaje",
    "sg:phone":"+34 928 77 52 35",
    "sg:postcode":"35100",
    "sg:province":"Las Palmas",
    "wof:name":"Ayuntamiento De San Bartolome De Tirajana",
    "wof:placetype":"venue"
},
  "geometry": {"coordinates":[-15.4397096634,28.1302204132],"type":"Point"}
}