{
  "type": "Feature",
  "properties": {
    "addr:full":"Carr Anna Tugas, 16 Badalona Barcelona 08917",
    "addr:housenumber":"16",
    "addr:postcode":"08917",
    "addr:street":"Carr Anna Tugas",
    "iso:country":"ES",
    "sg:address":"Carr Anna Tugas, 16",
    "sg:city":"Badalona",
    "sg:orig_category":"Art\u00cdculos De Decoraci\u00d3n",
    "sg:phone":"+34 934 65 54 28",
    "sg:postcode":"08917",
    "sg:province":"Barcelona",
    "wof:name":"Prieto Garcia Eloy",
    "wof:placetype":"venue"
},
  "geometry": {"coordinates":[2.2281200886,41.4553184509],"type":"Point"}
}