{
  "type": "Feature",
  "properties": {
    "iso:country":"ES",
    "sg:address":"Carrer de Bellaterra, 26",
    "sg:city":"Cornella Llobregat",
    "sg:orig_category":"Reposter\u00cdas",
    "sg:phone":"+34 933 76 62 05",
    "sg:postcode":"08940",
    "sg:province":"Barcelona",
    "wof:name":"Blatpa S.a.",
    "wof:placetype":"venue"
},
  "geometry": {"coordinates":[2.0737419128,41.3575668335],"type":"Point"}
}