{
  "type": "Feature",
  "properties": {
    "iso:country":"ES",
    "sg:address":"Rbla Antoni Vidal, 48",
    "sg:city":"S. Feliu Guixols",
    "sg:orig_category":"Museos",
    "sg:phone":"+34 972 82 22 49",
    "sg:postcode":"17220",
    "sg:province":"Girona",
    "sg:website":"www.correumuseudelajoguina.com",
    "wof:name":"Museu D'historia De La Joguina 1860-1960 S.l.",
    "wof:placetype":"venue"
},
  "geometry": {"coordinates":[3.029309988,41.7817497253],"type":"Point"}
}