{
  "type": "Feature",
  "properties": {
    "iso:country":"ES",
    "sg:address":"Pl. M. Sants, S/n",
    "sg:city":"Barcelona",
    "sg:orig_category":"Florister\u00cdas",
    "sg:phone":"+34 933 32 97 38",
    "sg:postcode":"08038",
    "sg:province":"Barcelona",
    "wof:name":"Cernuda Jodar Jose Manuel",
    "wof:placetype":"venue"
},
  "geometry": {"coordinates":[2.1389250755,41.3604545593],"type":"Point"}
}