{
  "type": "Feature",
  "properties": {
    "addr:full":"Calle de Ramon Herrera, 10 Villanueva De Los Infantes Ciudad Real 13320",
    "addr:housenumber":"10",
    "addr:postcode":"13320",
    "addr:street":"Calle De Ramon Herrera;Infantes",
    "iso:country":"ES",
    "sg:address":"Calle de Ramon Herrera, 10",
    "sg:city":"Villanueva De Los Infantes",
    "sg:orig_category":"Pr\u00c9stamos Personales E Hipotecarios",
    "sg:phone":"+34 926 36 06 91",
    "sg:postcode":"13320",
    "sg:province":"Ciudad Real",
    "wof:name":"Garcia Pedro Consuelo",
    "wof:placetype":"venue"
},
  "geometry": {"coordinates":[-3.0148859024,38.7361831665],"type":"Point"}
}