{
  "type": "Feature",
  "properties": {
    "addr:full":"Av En Joan Carles I, 59 Elche Alicante 03202",
    "addr:housenumber":"59",
    "addr:postcode":"03202",
    "addr:street":"Av En Joan Carles I",
    "iso:country":"ES",
    "sg:address":"Av En Joan Carles I, 59",
    "sg:city":"Elche",
    "sg:orig_category":"Comercio, Reparaci\u00d3n De Bicicletas, De Motocicletas, De Accesorios",
    "sg:phone":"+34 965 45 99 14",
    "sg:postcode":"03202",
    "sg:province":"Alicante",
    "wof:name":"Brotons Aguilar Ricardo Manuel",
    "wof:placetype":"venue"
},
  "geometry": {"coordinates":[-0.691264987,38.2674179077],"type":"Point"}
}