{
  "type": "Feature",
  "properties": {
    "addr:full":"A Pedreira, 20 Ponteareas Pontevedra 36865",
    "addr:housenumber":"20",
    "addr:postcode":"36865",
    "addr:street":"A Pedreira",
    "iso:country":"ES",
    "sg:address":"A Pedreira, 20",
    "sg:city":"Ponteareas",
    "sg:orig_category":"Cerrajer\u00cda, Ferrallista",
    "sg:phone":"+34 986 64 21 41",
    "sg:postcode":"36865",
    "sg:province":"Pontevedra",
    "wof:name":"Penabella Gonzalez Hermindo",
    "wof:placetype":"venue"
},
  "geometry": {"coordinates":[-8.5024337769,42.1738243103],"type":"Point"}
}