{
  "type": "Feature",
  "properties": {
    "iso:country":"ES",
    "sg:address":"Calle de Cruz Verde, 23",
    "sg:city":"Santa Cruz De Tenerife",
    "sg:orig_category":"Arquitectos",
    "sg:phone":"+34 922 53 14 84",
    "sg:postcode":"38003",
    "sg:province":"Santa Cruz De Tenerife",
    "wof:name":"Calcularq S.l.",
    "wof:placetype":"venue"
},
  "geometry": {"coordinates":[-16.2491512299,28.4666996002],"type":"Point"}
}