{
  "type": "Feature",
  "properties": {
    "iso:country":"ES",
    "sg:address":"Calle de Hilarion Eslava, 28",
    "sg:city":"Madrid",
    "sg:orig_category":"Art\u00cdculos De Regalo (al Por Menor)",
    "sg:phone":"+34 915 44 03 28",
    "sg:postcode":"28015",
    "sg:province":"Madrid",
    "wof:name":"Amaro Fornos Myriam 000607662g S.l.n.e.",
    "wof:placetype":"venue"
},
  "geometry": {"coordinates":[-3.7166616917,40.4348182678],"type":"Point"}
}