{
  "type": "Feature",
  "properties": {
    "addr:full":"Calle de Doctor Fleming, 13 Martos Ja\u00e9n 23600",
    "addr:housenumber":"13",
    "addr:postcode":"23600",
    "addr:street":"Calle De Doctor Fleming;Jae\u0301N",
    "iso:country":"ES",
    "sg:address":"Calle de Doctor Fleming, 13",
    "sg:city":"Martos",
    "sg:orig_category":"Empresas De Desmonte",
    "sg:phone":"+34 953 70 24 96",
    "sg:postcode":"23600",
    "sg:province":"Ja\u00e9n",
    "wof:name":"Herjans S.l.",
    "wof:placetype":"venue"
},
  "geometry": {"coordinates":[-3.9737300873,37.7256813049],"type":"Point"}
}