{
  "type": "Feature",
  "properties": {
    "iso:country":"ES",
    "sg:address":"Ctra. Huelva, Km. 0135,0",
    "sg:city":"Ayamonte",
    "sg:orig_category":"Estudios Y Construcci\u00d3n De Acuarios Y Viveros",
    "sg:phone":"+34 959 32 13 13",
    "sg:postcode":"21400",
    "sg:province":"Huelva",
    "wof:name":"Punta Bandera S.l.",
    "wof:placetype":"venue"
},
  "geometry": {"coordinates":[-7.3137159348,37.2268180847],"type":"Point"}
}