{
  "type": "Feature",
  "properties": {
    "addr:full":"As Bornugueiras, S/n Ferreira Lugo 27430",
    "addr:housenumber":"s",
    "addr:postcode":"27430",
    "addr:street":"/ N Ferreira",
    "iso:country":"ES",
    "sg:address":"As Bornugueiras, S/n",
    "sg:city":"Ferreira",
    "sg:orig_category":"Producci\u00d3n, Venta De Productos De Agricultura Biol\u00d3gica",
    "sg:phone":"+34 982 15 21 07",
    "sg:postcode":"27430",
    "sg:province":"Lugo",
    "wof:name":"Bornagra S.l.",
    "wof:placetype":"venue"
},
  "geometry": {"coordinates":[-7.6298079491,42.5048904419],"type":"Point"}
}