{
  "type": "Feature",
  "properties": {
    "addr:full":"Avda Portugal, 131 Salamanca Salamanca 37006",
    "addr:housenumber":"131",
    "addr:postcode":"37006",
    "addr:street":"Avda Portugal",
    "iso:country":"ES",
    "sg:address":"Avda Portugal, 131",
    "sg:city":"Salamanca",
    "sg:orig_category":"Molduras, Junquillos, Listones Y Molduras Perforadas",
    "sg:phone":"+34 923 12 13 60",
    "sg:postcode":"37006",
    "sg:province":"Salamanca",
    "wof:name":"Rollan Diaz Eugenio",
    "wof:placetype":"venue"
},
  "geometry": {"coordinates":[-5.6648449898,40.9726409912],"type":"Point"}
}