{
  "type": "Feature",
  "properties": {
    "iso:country":"ES",
    "sg:address":"Carrer de Pujada Del Castell, 1",
    "sg:city":"Manresa",
    "sg:orig_category":"Reposter\u00cdas",
    "sg:phone":"+34 938 73 46 47",
    "sg:postcode":"08241",
    "sg:province":"Barcelona",
    "wof:name":"Coma Garcia Ramon",
    "wof:placetype":"venue"
},
  "geometry": {"coordinates":[1.8275569677,41.7274513245],"type":"Point"}
}