{
  "type": "Feature",
  "properties": {
    "addr:full":"Pase Salut, 87 Badalona Barcelona 08914",
    "addr:housenumber":"87",
    "addr:postcode":"08914",
    "iso:country":"ES",
    "sg:address":"Pase Salut, 87",
    "sg:city":"Badalona",
    "sg:orig_category":"Importaci\u00d3n, Exportaci\u00d3n Y Comercios De Productos Textiles",
    "sg:phone":"+34 933 87 61 95",
    "sg:postcode":"08914",
    "sg:province":"Barcelona",
    "wof:name":"Baseiria Viver Juan",
    "wof:placetype":"venue"
},
  "geometry": {"coordinates":[2.2258551121,41.4421806335],"type":"Point"}
}