{
  "type": "Feature",
  "properties": {
    "iso:country":"ES",
    "sg:address":"Cmno Aguas, 59",
    "sg:city":"Salamanca",
    "sg:orig_category":"Farmacias",
    "sg:phone":"+34 923 18 10 85",
    "sg:postcode":"37003",
    "sg:province":"Salamanca",
    "wof:name":"Hebrero Gomez Maria Belen",
    "wof:placetype":"venue"
},
  "geometry": {"coordinates":[-5.650053978,40.9630126953],"type":"Point"}
}