{
  "type": "Feature",
  "properties": {
    "iso:country":"ES",
    "sg:address":"Calle de Puerto Rico, 3",
    "sg:city":"Ejido",
    "sg:orig_category":"Estancos",
    "sg:phone":"+34 950 48 63 78",
    "sg:postcode":"04700",
    "sg:province":"Almer\u00eda",
    "wof:name":"Romero Torres Maria Angelica",
    "wof:placetype":"venue"
},
  "geometry": {"coordinates":[-2.8176040649,36.7727012634],"type":"Point"}
}