{
  "type": "Feature",
  "properties": {
    "addr:full":"Calle de Gurtubay, 4 Madrid Madrid 28001",
    "addr:housenumber":"4",
    "addr:postcode":"28001",
    "addr:street":"Calle De Gurtubay",
    "iso:country":"ES",
    "sg:address":"Calle de Gurtubay, 4",
    "sg:city":"Madrid",
    "sg:orig_category":"Compraventa De Antig\u00dcedades",
    "sg:phone":"+34 915 75 85 35",
    "sg:postcode":"28001",
    "sg:province":"Madrid",
    "wof:name":"Pelta Martin Enrique",
    "wof:placetype":"venue"
},
  "geometry": {"coordinates":[-3.6848208904,40.4232292175],"type":"Point"}
}