{
  "type": "Feature",
  "properties": {
    "iso:country":"ES",
    "sg:address":"Calle de Santa Barbara, 82",
    "sg:city":"Polan",
    "sg:orig_category":"Empresas De Carpinter\u00cda De Madera",
    "sg:phone":"+34 925 37 08 41",
    "sg:postcode":"45161",
    "sg:province":"Toledo",
    "wof:name":"Afer Carpinteria S.l.",
    "wof:placetype":"venue"
},
  "geometry": {"coordinates":[-4.176217556,39.7843551636],"type":"Point"}
}