{
  "type": "Feature",
  "properties": {
    "addr:full":"Zuberoa Kalea, 22 Zarautz Guip\u00f9zcoa 20800",
    "addr:housenumber":"22",
    "addr:postcode":"20800",
    "addr:street":"Zuberoa Kalea;Guipu\u0300Zcoa",
    "iso:country":"ES",
    "sg:address":"Zuberoa Kalea, 22",
    "sg:city":"Zarautz",
    "sg:orig_category":"Metalurgia",
    "sg:phone":"+34 943 13 01 81",
    "sg:postcode":"20800",
    "sg:province":"Guip\u00f9zcoa",
    "wof:name":"Reformas Bizkor S.l",
    "wof:placetype":"venue"
},
  "geometry": {"coordinates":[-2.1698019505,43.2798995972],"type":"Point"}
}