{
  "type": "Feature",
  "properties": {
    "addr:full":"Avda Atlantico Del, S/n Vecindario Las Palmas 35110",
    "addr:postcode":"35110",
    "addr:street":"Avda Atlantico Del S / N Vecindario Las Palmas",
    "iso:country":"ES",
    "sg:address":"Avda Atlantico Del, S/n",
    "sg:city":"Vecindario",
    "sg:orig_category":"Perfumer\u00cda, Art\u00cdculos De Ba\u00d1o (fabricaci\u00d3n, Al Por Mayor)",
    "sg:phone":"+34 928 79 33 26",
    "sg:postcode":"35110",
    "sg:province":"Las Palmas",
    "wof:name":"Fransuca S.l.",
    "wof:placetype":"venue"
},
  "geometry": {"coordinates":[-15.45058918,27.8365402222],"type":"Point"}
}