{
  "type": "Feature",
  "properties": {
    "addr:full":"Calle de Cuestablanca (de), S/n Alcobendas Madrid 28108",
    "addr:postcode":"28108",
    "addr:street":"Calle De Cuestablanca De S / N",
    "iso:country":"ES",
    "sg:address":"Calle de Cuestablanca (de), S/n",
    "sg:city":"Alcobendas",
    "sg:orig_category":"Lencer\u00cda Femenina, Corseter\u00cda, Trajes De Ba\u00d1o (al Por Menor)",
    "sg:phone":"+34 916 50 35 71",
    "sg:postcode":"28108",
    "sg:province":"Madrid",
    "sg:website":"www.paginasamarillas.es",
    "wof:name":"Manzanaro Bonet Susana",
    "wof:placetype":"venue"
},
  "geometry": {"coordinates":[-3.6544620991,40.5215072632],"type":"Point"}
}