{
  "type": "Feature",
  "properties": {
    "addr:full":"Avgd Dos De Mayo, 20 Aldaia Valencia 46960",
    "addr:housenumber":"20",
    "addr:postcode":"46960",
    "addr:street":"Dos;Mayo",
    "iso:country":"ES",
    "sg:address":"Avgd Dos De Mayo, 20",
    "sg:city":"Aldaia",
    "sg:orig_category":"Bancos",
    "sg:phone":"+34 961 50 22 12",
    "sg:postcode":"46960",
    "sg:province":"Valencia",
    "sg:website":"www.bancopopular.es",
    "wof:name":"Banco Popular Espa\u00d1ol S.a.",
    "wof:placetype":"venue"
},
  "geometry": {"coordinates":[-0.460878998,39.4649238586],"type":"Point"}
}