{
  "type": "Feature",
  "properties": {
    "addr:full":"Calle de Pablo Iglesias, 7 Aguilas Murcia 30880",
    "addr:housenumber":"7",
    "addr:postcode":"30880",
    "addr:street":"Calle De Pablo Iglesias",
    "iso:country":"ES",
    "sg:address":"Calle de Pablo Iglesias, 7",
    "sg:city":"Aguilas",
    "sg:orig_category":"Asesor\u00cda Fiscal Y Jur\u00cddica",
    "sg:phone":"+34 968 41 39 81",
    "sg:postcode":"30880",
    "sg:province":"Murcia",
    "wof:name":"Lorca Jimenez Sebastian",
    "wof:placetype":"venue"
},
  "geometry": {"coordinates":[-1.5845400095,37.4072647095],"type":"Point"}
}