{
  "type": "Feature",
  "properties": {
    "iso:country":"ES",
    "sg:address":"Calle de Pesquera, 26",
    "sg:city":"Torrejon Ardoz",
    "sg:orig_category":"Inmobiliaria (agencias)",
    "sg:phone":"+34 916 56 83 20",
    "sg:postcode":"28850",
    "sg:province":"Madrid",
    "wof:name":"Ardoz Gestion S.l.",
    "wof:placetype":"venue"
},
  "geometry": {"coordinates":[-3.4786002636,40.4565658569],"type":"Point"}
}