{
  "type": "Feature",
  "properties": {
    "addr:full":"Calle de Virgen De Las Angustias (de La), 2 Mejorada Campo Madrid 28840",
    "addr:housenumber":"2",
    "addr:postcode":"28840",
    "addr:street":"Calle De Virgen De Las Angustias De La",
    "iso:country":"ES",
    "sg:address":"Calle de Virgen De Las Angustias (de La), 2",
    "sg:city":"Mejorada Campo",
    "sg:orig_category":"Centros De Educaci\u00d3n Especial",
    "sg:phone":"+34 916 79 26 34",
    "sg:postcode":"28840",
    "sg:province":"Madrid",
    "wof:name":"Colegio Publico Jarama",
    "wof:placetype":"venue"
},
  "geometry": {"coordinates":[-3.4865651131,40.3964576721],"type":"Point"}
}