{
  "type": "Feature",
  "properties": {
    "addr:full":"Calle de Orinque, 9 Punta Umbria Huelva 21100",
    "addr:housenumber":"9",
    "addr:postcode":"21100",
    "addr:street":"Calle De Orinque",
    "iso:country":"ES",
    "sg:address":"Calle de Orinque, 9",
    "sg:city":"Punta Umbria",
    "sg:orig_category":"Estancos",
    "sg:phone":"+34 959 31 56 03",
    "sg:postcode":"21100",
    "sg:province":"Huelva",
    "wof:name":"Perdigones Sanchez Jose Luis",
    "wof:placetype":"venue"
},
  "geometry": {"coordinates":[-6.9694828987,37.1868209839],"type":"Point"}
}