{
  "type": "Feature",
  "properties": {
    "iso:country":"ES",
    "sg:address":"Av Magaluf, 2",
    "sg:city":"Magaluf",
    "sg:orig_category":"Molduras, Junquillos, Listones Y Molduras Perforadas",
    "sg:phone":"+34 971 13 23 55",
    "sg:postcode":"07181",
    "sg:province":"Islas Baleares",
    "wof:name":"Bar Rodas Alfaro C.b.",
    "wof:placetype":"venue"
},
  "geometry": {"coordinates":[2.5322680473,39.5054855347],"type":"Point"}
}