{
  "type": "Feature",
  "properties": {
    "addr:full":"Carrer de Santa Teresa, 7 Gava Barcelona 08850",
    "addr:housenumber":"7",
    "addr:postcode":"08850",
    "addr:street":"Carrer De Santa Teresa",
    "iso:country":"ES",
    "sg:address":"Carrer de Santa Teresa, 7",
    "sg:city":"Gava",
    "sg:orig_category":"Peluquer\u00cdas, Peluquer\u00cda Mixta",
    "sg:phone":"+34 936 62 38 99",
    "sg:postcode":"08850",
    "sg:province":"Barcelona",
    "wof:name":"Pizarro Blanco Maria Jose",
    "wof:placetype":"venue"
},
  "geometry": {"coordinates":[2.0015521049,41.307182312],"type":"Point"}
}