{
  "type": "Feature",
  "properties": {
    "addr:full":"Calle de Bodegas, 14 Villamediana Iregua La Rioja 26142",
    "addr:housenumber":"14",
    "addr:postcode":"26142",
    "addr:street":"Calle De Bodegas;Rioja",
    "iso:country":"ES",
    "sg:address":"Calle de Bodegas, 14",
    "sg:city":"Villamediana Iregua",
    "sg:orig_category":"Muebles Y Accesorios Para Cocinas Y Cuartos De Ba\u00d1o (al Por Menor)",
    "sg:phone":"+34 941 43 54 56",
    "sg:postcode":"26142",
    "sg:province":"La Rioja",
    "wof:name":"Alonso Maya Anunciacion",
    "wof:placetype":"venue"
},
  "geometry": {"coordinates":[-2.4156444073,42.427028656],"type":"Point"}
}