{
  "type": "Feature",
  "properties": {
    "iso:country":"ES",
    "sg:address":"Carrer de Benet Mateu, 28",
    "sg:city":"Barcelona",
    "sg:orig_category":"Laboratorios Dentales",
    "sg:phone":"+34 932 80 54 99",
    "sg:postcode":"08034",
    "sg:province":"Barcelona",
    "wof:name":"Ayza Ortodoncia S.l.",
    "wof:placetype":"venue"
},
  "geometry": {"coordinates":[2.1268870831,41.3926200867],"type":"Point"}
}