{
  "type": "Feature",
  "properties": {
    "addr:full":"Calle de Alcazar De Toledo, 7 Le\u00f3n Le\u00f3n 24001",
    "addr:housenumber":"7",
    "addr:postcode":"24001",
    "addr:street":"Calle De Alcazar De Toledo;Leo\u0301N",
    "iso:country":"ES",
    "sg:address":"Calle de Alcazar De Toledo, 7",
    "sg:city":"Le\u00f3n",
    "sg:orig_category":"Doctores En Medicina",
    "sg:phone":"+34 987 24 85 64",
    "sg:postcode":"24001",
    "sg:province":"Le\u00f3n",
    "wof:name":"Moro Sanchez Maria Jesus",
    "wof:placetype":"venue"
},
  "geometry": {"coordinates":[-5.5756201744,42.5980262756],"type":"Point"}
}