{
  "type": "Feature",
  "properties": {
    "addr:full":"Atva. Zaragoza-logro\u00f1o, Km. 0011,5 Utebo Zaragoza 50180",
    "addr:postcode":"50180",
    "addr:street":"Zaragoza-Logron\u0303O Km. 0011,5",
    "iso:country":"ES",
    "sg:address":"Atva. Zaragoza-logro\u00f1o, Km. 0011,5",
    "sg:city":"Utebo",
    "sg:orig_category":"Electricidad: Equipos Industriales, Componentes (fabricaci\u00d3n)",
    "sg:phone":"+34 976 77 06 39",
    "sg:postcode":"50180",
    "sg:province":"Zaragoza",
    "sg:website":"www.layrton.com",
    "wof:name":"Industrias Ventura S. L.",
    "wof:placetype":"venue"
},
  "geometry": {"coordinates":[-0.9998990297,41.7043800354],"type":"Point"}
}