{
  "type": "Feature",
  "properties": {
    "iso:country":"ES",
    "sg:address":"Carrer de Miguel De Cervantes, 4",
    "sg:city":"Cornella Llobregat",
    "sg:orig_category":"Comercio De Piezas De Recambio Y De Accesorios De Veh\u00cdculos, Veh\u00cdculos Industriales",
    "sg:phone":"+34 933 75 22 61",
    "sg:postcode":"08940",
    "sg:province":"Barcelona",
    "wof:name":"Recampadro 95 S.l.",
    "wof:placetype":"venue"
},
  "geometry": {"coordinates":[2.0717079639,41.3648300171],"type":"Point"}
}