{
  "type": "Feature",
  "properties": {
    "addr:full":"Carrer de Priorat (del), 13 Salou Tarragona 43840",
    "addr:postcode":"43840",
    "addr:street":"Carrer De;Del",
    "iso:country":"ES",
    "sg:address":"Carrer de Priorat (del), 13",
    "sg:city":"Salou",
    "sg:orig_category":"Armaduras De Hormig\u00d3n",
    "sg:phone":"+34 977 38 41 40",
    "sg:postcode":"43840",
    "sg:province":"Tarragona",
    "wof:name":"Catalanomediterranea De Trabajos De Extructura S.l.",
    "wof:placetype":"venue"
},
  "geometry": {"coordinates":[1.153061986,41.0727386475],"type":"Point"}
}