{
  "type": "Feature",
  "properties": {
    "iso:country":"ES",
    "sg:address":"Calle de Juan Xxiii, 2",
    "sg:city":"Casco Nuevo",
    "sg:orig_category":"Asociaciones, Organismos Culturales Y Socioeducativos",
    "sg:phone":"+34 948 31 06 76",
    "sg:postcode":"31191",
    "sg:province":"Navarra",
    "wof:name":"Guatkis S.r.c",
    "wof:placetype":"venue"
},
  "geometry": {"coordinates":[-1.6518089771,42.7533912659],"type":"Point"}
}