{
  "type": "Feature",
  "properties": {
    "iso:country":"ES",
    "sg:address":"Carr Major, 74",
    "sg:city":"Picassent",
    "sg:orig_category":"Droguer\u00cdas (al Por Menor)",
    "sg:phone":"+34 961 23 01 22",
    "sg:postcode":"46220",
    "sg:province":"Valencia",
    "wof:name":"Drogueria El Mercat S.l.",
    "wof:placetype":"venue"
},
  "geometry": {"coordinates":[-0.4607239962,39.3608818054],"type":"Point"}
}