{
  "type": "Feature",
  "properties": {
    "iso:country":"ES",
    "sg:address":"Calle de Serrano, 118",
    "sg:city":"Madrid",
    "sg:orig_category":"Plomeros",
    "sg:phone":"+34 915 61 27 83",
    "sg:postcode":"28006",
    "sg:province":"Madrid",
    "sg:website":"www.casalinda.es",
    "wof:name":"Diaz Blanco Pilar",
    "wof:placetype":"venue"
},
  "geometry": {"coordinates":[-3.6862840652,40.436164856],"type":"Point"}
}