{
  "type": "Feature",
  "properties": {
    "iso:country":"ES",
    "sg:address":"Carrer de Gabriel Miro, 4",
    "sg:city":"Crevillent",
    "sg:orig_category":"Asociaciones, Organismos Culturales Y Socioeducativos",
    "sg:phone":"+34 966 68 08 70",
    "sg:postcode":"03330",
    "sg:province":"Alicante",
    "wof:name":"Penya Barcelonista De Crevillent",
    "wof:placetype":"venue"
},
  "geometry": {"coordinates":[-0.8065850139,38.250087738],"type":"Point"}
}