{
  "type": "Feature",
  "properties": {
    "iso:country":"ES",
    "sg:address":"Calle de Claudio Alvargonzalez, 22",
    "sg:city":"Gijon",
    "sg:orig_category":"Molduras, Junquillos, Listones Y Molduras Perforadas",
    "sg:phone":"+34 985 34 32 55",
    "sg:postcode":"33201",
    "sg:province":"Asturias",
    "wof:name":"La Zapatarranca S.l.",
    "wof:placetype":"venue"
},
  "geometry": {"coordinates":[-5.6653299332,43.5464553833],"type":"Point"}
}