{
  "type": "Feature",
  "properties": {
    "addr:full":"Calle de Pablo Morillo, 8 Zamora Zamora 49013",
    "addr:housenumber":"8",
    "addr:postcode":"49013",
    "addr:street":"Calle De Pablo Morillo",
    "iso:country":"ES",
    "sg:address":"Calle de Pablo Morillo, 8",
    "sg:city":"Zamora",
    "sg:orig_category":"Lanas (al Por Mayor)",
    "sg:phone":"+34 980 52 04 94",
    "sg:postcode":"49013",
    "sg:province":"Zamora",
    "wof:name":"Vi\u00f1uela Benavente Francisco",
    "wof:placetype":"venue"
},
  "geometry": {"coordinates":[-5.7413620949,41.5080604553],"type":"Point"}
}