{
  "type": "Feature",
  "properties": {
    "iso:country":"ES",
    "sg:address":"Carrer de Gravina, 24",
    "sg:city":"Roses",
    "sg:orig_category":"Agentes Generales De Seguros",
    "sg:phone":"+34 972 25 68 91",
    "sg:postcode":"17480",
    "sg:province":"Girona",
    "wof:name":"Parra Gallardo Maria Rosa",
    "wof:placetype":"venue"
},
  "geometry": {"coordinates":[3.1807360649,42.2623062134],"type":"Point"}
}