{
  "type": "Feature",
  "properties": {
    "addr:full":"Av M. Celayeta, 109 Iru\u00f1a Navarra 31014",
    "addr:housenumber":"109",
    "addr:postcode":"31014",
    "addr:street":"Av M. Celayeta",
    "iso:country":"ES",
    "sg:address":"Av M. Celayeta, 109",
    "sg:city":"Iru\u00f1a",
    "sg:classifiers":[
        {
            "category":"Autos & Motor Vehicles",
            "subcategory":"Automobile Sales",
            "type":"Retail Goods"
        }
    ],
    "sg:phone":"+34 948 38 25 31",
    "sg:postcode":"31014",
    "sg:province":"Navarra",
    "wof:name":"Iru\u00f1a Servicios De Formacion Vial S.l.",
    "wof:placetype":"venue"
},
  "geometry": {"coordinates":[-1.6437540054,42.81275177],"type":"Point"}
}