{
  "type": "Feature",
  "properties": {
    "addr:full":"Calle de San Pedro, S/n Cotillas Antigua Murcia 30565",
    "addr:housenumber":"/ n",
    "addr:postcode":"30565",
    "addr:street":"Calle De San Pedro S",
    "iso:country":"ES",
    "sg:address":"Calle de San Pedro, S/n",
    "sg:city":"Cotillas Antigua",
    "sg:orig_category":"Molduras, Junquillos, Listones Y Molduras Perforadas",
    "sg:phone":"+34 968 62 11 06",
    "sg:postcode":"30565",
    "sg:province":"Murcia",
    "wof:name":"Rosauro Torres Maria Jose",
    "wof:placetype":"venue"
},
  "geometry": {"coordinates":[-1.2395490408,38.0263290405],"type":"Point"}
}