{
  "type": "Feature",
  "properties": {
    "addr:full":"Calle de Vid (la), 8 Chiclana De La Frontera C\u00e1diz 11130",
    "addr:postcode":"11130",
    "addr:street":"Calle De Vid La 8",
    "iso:country":"ES",
    "sg:address":"Calle de Vid (la), 8",
    "sg:city":"Chiclana De La Frontera",
    "sg:orig_category":"Fabricaci\u00d3n, Venta, Instalaci\u00d3n De R\u00d3tulos, De R\u00d3tulos Luminosos",
    "sg:phone":"+34 956 40 43 87",
    "sg:postcode":"11130",
    "sg:province":"C\u00e1diz",
    "wof:name":"Marin Magan Virginia",
    "wof:placetype":"venue"
},
  "geometry": {"coordinates":[-6.1640839577,36.4197006226],"type":"Point"}
}