{
  "type": "Feature",
  "properties": {
    "iso:country":"ES",
    "sg:address":"Calle de Embalse, 4",
    "sg:city":"Fuenlabrada",
    "sg:orig_category":"Empresarios",
    "sg:phone":"+34 916 08 15 19",
    "sg:postcode":"28942",
    "sg:province":"Madrid",
    "wof:name":"Vayro Reformas Y Construcciones S.l.",
    "wof:placetype":"venue"
},
  "geometry": {"coordinates":[-3.813254118,40.2927131653],"type":"Point"}
}