{
  "type": "Feature",
  "properties": {
    "addr:full":"Calle de Capitan Mendizabal, 11 Santurtzi Vizcaya 48980",
    "addr:housenumber":"11",
    "addr:postcode":"48980",
    "addr:street":"Calle De Capitan Mendizabal",
    "iso:country":"ES",
    "sg:address":"Calle de Capitan Mendizabal, 11",
    "sg:city":"Santurtzi",
    "sg:orig_category":"Complementos De Vestir (al Por Menor)",
    "sg:phone":"+34 944 61 75 97",
    "sg:postcode":"48980",
    "sg:province":"Vizcaya",
    "wof:name":"Maria Aranzazu Gonzalez Uribe Etxebarria",
    "wof:placetype":"venue"
},
  "geometry": {"coordinates":[-3.0336885452,43.3309860229],"type":"Point"}
}