{
  "type": "Feature",
  "properties": {
    "iso:country":"ES",
    "sg:address":"Calle de San Benito, 35",
    "sg:city":"Madrid",
    "sg:orig_category":"Empresas De Portes Y Mensajer\u00cda",
    "sg:phone":"+34 913 14 70 55",
    "sg:postcode":"28029",
    "sg:province":"Madrid",
    "wof:name":"Almenara Express",
    "wof:placetype":"venue"
},
  "geometry": {"coordinates":[-3.6948838234,40.470375061],"type":"Point"}
}