{
  "type": "Feature",
  "properties": {
    "iso:country":"ES",
    "sg:address":"Calle de Cervantes, 10",
    "sg:city":"Pozoblanco",
    "sg:orig_category":"Peluquer\u00cdas, Peluquer\u00cda Mixta",
    "sg:phone":"+34 957 77 10 13",
    "sg:postcode":"14400",
    "sg:province":"C\u00f3rdoba",
    "wof:name":"Rodriguez Pastor Isabel",
    "wof:placetype":"venue"
},
  "geometry": {"coordinates":[-4.8525791168,38.3788642883],"type":"Point"}
}