{
  "type": "Feature",
  "properties": {
    "iso:country":"ES",
    "sg:address":"Calle de Suarez Guerra, 48",
    "sg:city":"Santa Cruz De Tenerife",
    "sg:orig_category":"Art\u00cdculos De Regalo (al Por Menor)",
    "sg:phone":"+34 922 24 22 51",
    "sg:postcode":"38002",
    "sg:province":"Santa Cruz De Tenerife",
    "wof:name":"Urios Rodenas Haydee",
    "wof:placetype":"venue"
},
  "geometry": {"coordinates":[-16.2510223389,28.4690074921],"type":"Point"}
}