{
  "type": "Feature",
  "properties": {
    "addr:full":"Rua San Xoan, 3 Ponto La Coru\u00f1a 15572",
    "addr:housenumber":"3",
    "addr:postcode":"15572",
    "addr:street":"Rua San Xoan;Corun\u0303A",
    "iso:country":"ES",
    "sg:address":"Rua San Xoan, 3",
    "sg:city":"Ponto",
    "sg:orig_category":"Trabajos De Perforaciones, Sondeos, Construcci\u00d3n De Pozos",
    "sg:phone":"+34 981 38 37 92",
    "sg:postcode":"15572",
    "sg:province":"La Coru\u00f1a",
    "wof:name":"Gayoso Garcia Jose",
    "wof:placetype":"venue"
},
  "geometry": {"coordinates":[-8.1741094589,43.516078949],"type":"Point"}
}