{
  "type": "Feature",
  "properties": {
    "iso:country":"ES",
    "sg:address":"Rua Ervedelo, 31",
    "sg:city":"Ourense",
    "sg:orig_category":"Doctores En Medicina",
    "sg:phone":"+34 988 24 65 32",
    "sg:postcode":"32002",
    "sg:province":"Ourense",
    "wof:name":"Villar Suares Maria Del Carmen",
    "wof:placetype":"venue"
},
  "geometry": {"coordinates":[-7.8704152107,42.3392944336],"type":"Point"}
}