{
  "type": "Feature",
  "properties": {
    "addr:full":"Calle de Adriano Vi, 11 Vitoria-gasteiz \u00c1lava 01008",
    "addr:housenumber":"11",
    "addr:postcode":"01008",
    "addr:street":"Calle De Adriano Vi",
    "iso:country":"ES",
    "sg:address":"Calle de Adriano Vi, 11",
    "sg:city":"Vitoria-gasteiz",
    "sg:orig_category":"Carnicer\u00cdas, Carnicer\u00cdas",
    "sg:phone":"+34 945 13 48 99",
    "sg:postcode":"01008",
    "sg:province":"\u00c1lava",
    "wof:name":"Marquinez Diaz De Junguitu Enrique",
    "wof:placetype":"venue"
},
  "geometry": {"coordinates":[-2.6815085411,42.8471603394],"type":"Point"}
}