{
  "type": "Feature",
  "properties": {
    "addr:full":"Calle de Division Azul, 10 Santander Cantabria 39010",
    "addr:housenumber":"10",
    "addr:postcode":"39010",
    "addr:street":"Calle De Division Azul",
    "iso:country":"ES",
    "sg:address":"Calle de Division Azul, 10",
    "sg:city":"Santander",
    "sg:orig_category":"Agencias Y Agentes Comerciales, Representantes",
    "sg:phone":"+34 942 33 55 08",
    "sg:postcode":"39010",
    "sg:province":"Cantabria",
    "wof:name":"Arenal Gandarillas Aureliano",
    "wof:placetype":"venue"
},
  "geometry": {"coordinates":[-3.8270671368,43.4590797424],"type":"Point"}
}