{
  "type": "Feature",
  "properties": {
    "iso:country":"ES",
    "sg:address":"Calle de Torre Barri, 7",
    "sg:city":"Landa",
    "sg:orig_category":"Molduras, Junquillos, Listones Y Molduras Perforadas",
    "sg:phone":"+34 946 76 58 53",
    "sg:postcode":"48610",
    "sg:province":"Vizcaya",
    "wof:name":"Fresnedo Alboniga Pedro Maria",
    "wof:placetype":"venue"
},
  "geometry": {"coordinates":[-2.9578540325,43.3789749146],"type":"Point"}
}