{
  "type": "Feature",
  "properties": {
    "iso:country":"ES",
    "sg:address":"Calle de Ravena, 32",
    "sg:city":"Madrid",
    "sg:orig_category":"Asesor\u00cda Fiscal Y Jur\u00cddica",
    "sg:phone":"+34 917 75 59 97",
    "sg:postcode":"28032",
    "sg:province":"Madrid",
    "wof:name":"Martin Garcia Carlos",
    "wof:placetype":"venue"
},
  "geometry": {"coordinates":[-3.6118769646,40.4198875427],"type":"Point"}
}