{
  "type": "Feature",
  "properties": {
    "iso:country":"ES",
    "sg:address":"Calle de Vega, 25",
    "sg:city":"Valladolid",
    "sg:orig_category":"Peluquer\u00cdas, Peluquer\u00cda Mixta",
    "sg:phone":"+34 983 29 41 65",
    "sg:postcode":"47004",
    "sg:province":"Valladolid",
    "wof:name":"Pe\u00f1as Cobos Miguel Angel",
    "wof:placetype":"venue"
},
  "geometry": {"coordinates":[-4.7221131325,41.6481056213],"type":"Point"}
}