{
  "type": "Feature",
  "properties": {
    "iso:country":"ES",
    "sg:address":"Llames De Parres, 74",
    "sg:city":"Viaba\u00f1o",
    "sg:classifiers":[
        {
            "category":"Taxi",
            "type":"Transportation"
        }
    ],
    "sg:phone":"+34 985 84 14 29",
    "sg:postcode":"33585",
    "sg:province":"Asturias",
    "wof:name":"Fernandez Gonzalez Maria Pilar Covadonga",
    "wof:placetype":"venue"
},
  "geometry": {"coordinates":[-5.2315578461,43.3588829041],"type":"Point"}
}