{
  "type": "Feature",
  "properties": {
    "addr:full":"Calle de Burgos, 10 Palencia Palencia 34001",
    "addr:housenumber":"10",
    "addr:postcode":"34001",
    "addr:street":"Calle De Burgos",
    "iso:country":"ES",
    "sg:address":"Calle de Burgos, 10",
    "sg:city":"Palencia",
    "sg:orig_category":"Abogados",
    "sg:phone":"+34 979 70 00 71",
    "sg:postcode":"34001",
    "sg:province":"Palencia",
    "wof:name":"Valin Tovar Tomas",
    "wof:placetype":"venue"
},
  "geometry": {"coordinates":[-4.530230999,42.0094795227],"type":"Point"}
}