{
  "type": "Feature",
  "properties": {
    "addr:full":"Sepulveda, S/n Navares De Ayuso Segovia 40531",
    "addr:postcode":"40531",
    "addr:street":"Sepulveda S / N",
    "iso:country":"ES",
    "sg:address":"Sepulveda, S/n",
    "sg:city":"Navares De Ayuso",
    "sg:orig_category":"Cr\u00cda De Corderos Y De Cabras",
    "sg:phone":"+34 921 53 21 21",
    "sg:postcode":"40531",
    "sg:province":"Segovia",
    "wof:name":"Carlos Guijarro Redondo Y Ramon Guijarro Redondo C.b.",
    "wof:placetype":"venue"
},
  "geometry": {"coordinates":[-3.6681659222,41.3744697571],"type":"Point"}
}