{
  "type": "Feature",
  "properties": {
    "iso:country":"ES",
    "sg:address":"Carrer de Llibertat, 13",
    "sg:city":"Castelldefels",
    "sg:orig_category":"Frutas, Legumbres Frescas Y Tempranas (al Por Menor)",
    "sg:phone":"+34 936 65 51 01",
    "sg:postcode":"08860",
    "sg:province":"Barcelona",
    "wof:name":"Capaces Gil Antonio",
    "wof:placetype":"venue"
},
  "geometry": {"coordinates":[1.9766910076,41.2785110474],"type":"Point"}
}