{
  "type": "Feature",
  "properties": {
    "iso:country":"ES",
    "sg:address":"Calle de Antonio Arag\u00fcas, 1",
    "sg:city":"Rozas De Madrid",
    "sg:orig_category":"Agentes, Concesionarios Y Sucursales De Veh\u00cdculos",
    "sg:phone":"+34 916 37 07 51",
    "sg:postcode":"28230",
    "sg:province":"Madrid",
    "wof:name":"Aradai S.a.",
    "wof:placetype":"venue"
},
  "geometry": {"coordinates":[-3.8863763809,40.4987487793],"type":"Point"}
}