{
  "type": "Feature",
  "properties": {
    "iso:country":"ES",
    "sg:address":"Carrer de Gran, 85",
    "sg:city":"Argentona",
    "sg:orig_category":"Ropa Para Se\u00d1oras (al Por Menor)",
    "sg:phone":"+34 937 56 02 74",
    "sg:postcode":"08310",
    "sg:province":"Barcelona",
    "wof:name":"Ruta La Cote S.l.",
    "wof:placetype":"venue"
},
  "geometry": {"coordinates":[2.4003400803,41.5564422607],"type":"Point"}
}