{
  "type": "Feature",
  "properties": {
    "iso:country":"ES",
    "sg:address":"Av Diputacio, S/n",
    "sg:city":"Mora D'ebre",
    "sg:orig_category":"Fisioterapia",
    "sg:phone":"+34 977 40 07 82",
    "sg:postcode":"43740",
    "sg:province":"Tarragona",
    "wof:name":"Asociacion De Rehabilitacion Jeroni De Moragas",
    "wof:placetype":"venue"
},
  "geometry": {"coordinates":[0.5920026898,41.108417511],"type":"Point"}
}