{
  "type": "Feature",
  "properties": {
    "iso:country":"ES",
    "sg:address":"Pl Nova, 1",
    "sg:city":"Santa Perpetua De Mogoda",
    "sg:orig_category":"Empresas De Empaquetado, Embalajes Por Encargo",
    "sg:phone":"+34 935 60 01 62",
    "sg:postcode":"08130",
    "sg:province":"Barcelona",
    "wof:name":"Envasats Franpack S.l.",
    "wof:placetype":"venue"
},
  "geometry": {"coordinates":[2.1826400757,41.5343589783],"type":"Point"}
}