{
  "type": "Feature",
  "properties": {
    "addr:full":"Carr Baldomer Sola, 63 Badalona Barcelona 08912",
    "addr:housenumber":"63",
    "addr:postcode":"08912",
    "addr:street":"Carr Baldomer Sola",
    "iso:country":"ES",
    "sg:address":"Carr Baldomer Sola, 63",
    "sg:city":"Badalona",
    "sg:orig_category":"Persianas Interiores, Exteriores",
    "sg:phone":"+34 933 99 01 00",
    "sg:postcode":"08912",
    "sg:province":"Barcelona",
    "sg:website":"www.toldoszaballos.com",
    "wof:name":"Toldos Zaballos S.l.",
    "wof:placetype":"venue"
},
  "geometry": {"coordinates":[2.2381401062,41.4457969666],"type":"Point"}
}