{
  "type": "Feature",
  "properties": {
    "iso:country":"ES",
    "sg:address":"Calle de Julian Fernandez Ollero, 5",
    "sg:city":"Haro",
    "sg:orig_category":"Pr\u00c9stamos Personales E Hipotecarios",
    "sg:phone":"+34 941 30 38 27",
    "sg:postcode":"26200",
    "sg:province":"La Rioja",
    "wof:name":"Caraba\u00f1a Aguado Fernando Jose",
    "wof:placetype":"venue"
},
  "geometry": {"coordinates":[-2.8529028893,42.5723342896],"type":"Point"}
}