{
  "type": "Feature",
  "properties": {
    "addr:full":"Via Julia, 117 Barcelona Barcelona 08042",
    "addr:housenumber":"117",
    "addr:postcode":"08042",
    "addr:street":"Via Julia",
    "iso:country":"ES",
    "sg:address":"Via Julia, 117",
    "sg:city":"Barcelona",
    "sg:orig_category":"Farmacias",
    "sg:phone":"+34 933 54 99 82",
    "sg:postcode":"08042",
    "sg:province":"Barcelona",
    "wof:name":"Segarra March Federico",
    "wof:placetype":"venue"
},
  "geometry": {"coordinates":[2.1776890755,41.4424247742],"type":"Point"}
}