{
  "type": "Feature",
  "properties": {
    "addr:full":"San Fermin, 24 Iru\u00f1a Navarra 31003",
    "addr:housenumber":"24",
    "addr:postcode":"31003",
    "addr:street":"San Fermin",
    "iso:country":"ES",
    "sg:address":"San Fermin, 24",
    "sg:city":"Iru\u00f1a",
    "sg:orig_category":"Empresas De Pintura Y Revestimientos",
    "sg:phone":"+34 948 23 42 64",
    "sg:postcode":"31003",
    "sg:province":"Navarra",
    "wof:name":"Gonzalez Torreblanca Carlos",
    "wof:placetype":"venue"
},
  "geometry": {"coordinates":[-1.6415580511,42.8108062744],"type":"Point"}
}