{
  "type": "Feature",
  "properties": {
    "addr:full":"Calle de Prim, 27 Donostia-san Sebastian Guip\u00f9zcoa 20006",
    "addr:housenumber":"27",
    "addr:postcode":"20006",
    "addr:street":"Calle De Prim",
    "iso:country":"ES",
    "sg:address":"Calle de Prim, 27",
    "sg:city":"Donostia-san Sebastian",
    "sg:orig_category":"Guarder\u00cdas",
    "sg:phone":"+34 943 47 00 55",
    "sg:postcode":"20006",
    "sg:province":"Guip\u00f9zcoa",
    "wof:name":"Enparantza Agirre Mikel",
    "wof:placetype":"venue"
},
  "geometry": {"coordinates":[-1.9799000025,43.3159484863],"type":"Point"}
}