{
  "type": "Feature",
  "properties": {
    "addr:full":"Rbla Egara, 190 Terrassa Barcelona 08221",
    "addr:housenumber":"190",
    "addr:postcode":"08221",
    "addr:street":"Rbla Egara",
    "iso:country":"ES",
    "sg:address":"Rbla Egara, 190",
    "sg:city":"Terrassa",
    "sg:orig_category":"Perfumer\u00cda (al Por Menor)",
    "sg:phone":"+34 937 80 00 35",
    "sg:postcode":"08221",
    "sg:province":"Barcelona",
    "sg:website":"www.atalayaperfumeria.com",
    "wof:name":"Perfumerias Atalaya S.l.",
    "wof:placetype":"venue"
},
  "geometry": {"coordinates":[2.0081079006,41.5627708435],"type":"Point"}
}