{
  "type": "Feature",
  "properties": {
    "addr:full":"Carrer de Bisbe Bernat Nadal, 3 Palma Islas Baleares 07010",
    "addr:housenumber":"3",
    "addr:postcode":"07010",
    "addr:street":"Carrer De Bisbe Bernat Nadal",
    "iso:country":"ES",
    "sg:address":"Carrer de Bisbe Bernat Nadal, 3",
    "sg:city":"Palma",
    "sg:orig_category":"Controles De Edificaci\u00d3n (construcci\u00d3n, Seguridad)",
    "sg:phone":"+34 971 20 19 08",
    "sg:postcode":"07010",
    "sg:province":"Islas Baleares",
    "wof:name":"Proyectos Promestar S.l.",
    "wof:placetype":"venue"
},
  "geometry": {"coordinates":[2.6466550827,39.5941390991],"type":"Point"}
}