{
  "type": "Feature",
  "properties": {
    "iso:country":"ES",
    "sg:address":"Calle de Licenciado Madrid, S/n",
    "sg:city":"Alcala Henares",
    "sg:orig_category":"Poller\u00cda Y Caza (al Por Menor)",
    "sg:phone":"+34 918 81 40 93",
    "sg:postcode":"28802",
    "sg:province":"Madrid",
    "wof:name":"Garcia Cid Mariano",
    "wof:placetype":"venue"
},
  "geometry": {"coordinates":[-3.3762190342,40.4766349792],"type":"Point"}
}