{
  "type": "Feature",
  "properties": {
    "iso:country":"ES",
    "sg:address":"Calle de O\u00d1ati, 7",
    "sg:city":"Vitoria-gasteiz",
    "sg:orig_category":"Agencias Y Asesores De Publicidad",
    "sg:phone":"+34 945 25 97 55",
    "sg:postcode":"01013",
    "sg:province":"\u00c1lava",
    "wof:name":"Kertar Araba S.l.",
    "wof:placetype":"venue"
},
  "geometry": {"coordinates":[-2.6580440998,42.8577308655],"type":"Point"}
}