{
  "type": "Feature",
  "properties": {
    "addr:full":"Kurtzebide Kalea, 13 O\u00f1ati Guip\u00f9zcoa 20560",
    "addr:housenumber":"13",
    "addr:postcode":"20560",
    "addr:street":"Kurtzebide Kalea;Guipu\u0300Zcoa",
    "iso:country":"ES",
    "sg:address":"Kurtzebide Kalea, 13",
    "sg:city":"O\u00f1ati",
    "sg:orig_category":"Tubos Met\u00c1licos",
    "sg:phone":"+34 943 78 14 60",
    "sg:postcode":"20560",
    "sg:province":"Guip\u00f9zcoa",
    "wof:name":"Hijos De Juan De Garay S. A.",
    "wof:placetype":"venue"
},
  "geometry": {"coordinates":[-2.4083518982,43.0321960449],"type":"Point"}
}