{
  "type": "Feature",
  "properties": {
    "iso:country":"ES",
    "sg:address":"Avda Constitucion, 105",
    "sg:city":"Trobajo Camino",
    "sg:orig_category":"Pintura, Barniz, Productos Asimilables (fabricaci\u00d3n, Al Por Mayor)",
    "sg:phone":"+34 987 80 05 80",
    "sg:postcode":"24010",
    "sg:province":"Le\u00f3n",
    "wof:name":"Decoraciones Esfer S.l.",
    "wof:placetype":"venue"
},
  "geometry": {"coordinates":[-5.5716600418,42.5981292725],"type":"Point"}
}