{
  "type": "Feature",
  "properties": {
    "iso:country":"ES",
    "sg:address":"Plaz Almas (las), 3",
    "sg:city":"Caudete",
    "sg:orig_category":"Art\u00cdculos De Pvc (fabricaci\u00d3n Y Al Por Mayor)",
    "sg:phone":"+34 965 82 55 55",
    "sg:postcode":"02660",
    "sg:province":"Albacete",
    "wof:name":"P.v.c.beca S.l.",
    "wof:placetype":"venue"
},
  "geometry": {"coordinates":[-0.991632998,38.7066917419],"type":"Point"}
}