{
  "type": "Feature",
  "properties": {
    "iso:country":"ES",
    "sg:address":"Carr Nou Del Convent, 25",
    "sg:city":"Algemesi",
    "sg:orig_category":"Abogados",
    "sg:phone":"+34 962 48 06 33",
    "sg:postcode":"46680",
    "sg:province":"Valencia",
    "wof:name":"Puchades Carbonell Maria Carmen",
    "wof:placetype":"venue"
},
  "geometry": {"coordinates":[-0.4387579858,39.1896476746],"type":"Point"}
}