{
  "type": "Feature",
  "properties": {
    "addr:full":"Calle de Alfonso Viii, 2 Palencia Palencia 34002",
    "addr:housenumber":"2",
    "addr:postcode":"34002",
    "addr:street":"Calle De Alfonso Viii",
    "iso:country":"ES",
    "sg:address":"Calle de Alfonso Viii, 2",
    "sg:city":"Palencia",
    "sg:orig_category":"M\u00c9dicos: Cardiolog\u00cda Y Afecciones Cardiovasculares",
    "sg:phone":"+34 979 72 24 72",
    "sg:postcode":"34002",
    "sg:province":"Palencia",
    "wof:name":"Ramos Fernandez Alberto",
    "wof:placetype":"venue"
},
  "geometry": {"coordinates":[-4.5297193527,42.0084075928],"type":"Point"}
}