{
  "type": "Feature",
  "properties": {
    "addr:full":"Ctra Lorca, S/n Totana Murcia 30850",
    "addr:housenumber":"/ n",
    "addr:postcode":"30850",
    "addr:street":"Ctra Lorca S",
    "iso:country":"ES",
    "sg:address":"Ctra Lorca, S/n",
    "sg:city":"Totana",
    "sg:orig_category":"Empresas De Carpinter\u00cda De Madera",
    "sg:phone":"+34 968 42 10 96",
    "sg:postcode":"30850",
    "sg:province":"Murcia",
    "wof:name":"Arias E Hijos S. L.",
    "wof:placetype":"venue"
},
  "geometry": {"coordinates":[-1.5030734539,37.7649536133],"type":"Point"}
}