{
  "type": "Feature",
  "properties": {
    "addr:full":"Avda Andalucia, 6 Cabra C\u00f3rdoba 14940",
    "addr:housenumber":"6",
    "addr:postcode":"14940",
    "addr:street":"Avda Andalucia;Co\u0301Rdoba",
    "iso:country":"ES",
    "sg:address":"Avda Andalucia, 6",
    "sg:city":"Cabra",
    "sg:orig_category":"Farmacias",
    "sg:phone":"+34 957 52 02 19",
    "sg:postcode":"14940",
    "sg:province":"C\u00f3rdoba",
    "wof:name":"Diaz Salazar Carmen",
    "wof:placetype":"venue"
},
  "geometry": {"coordinates":[-4.438639164,37.4751243591],"type":"Point"}
}