{
  "type": "Feature",
  "properties": {
    "addr:full":"Carr De Francisco Pizarro, 11 Benicarlo Castell\u00f3n 12580",
    "addr:housenumber":"11",
    "addr:postcode":"12580",
    "addr:street":"Carr De Francisco Pizarro",
    "iso:country":"ES",
    "sg:address":"Carr De Francisco Pizarro, 11",
    "sg:city":"Benicarlo",
    "sg:orig_category":"Vestidos De Se\u00d1ora (tallas Grandes)",
    "sg:phone":"+34 964 47 28 02",
    "sg:postcode":"12580",
    "sg:province":"Castell\u00f3n",
    "wof:name":"Botiga De Roba Anna S.c.",
    "wof:placetype":"venue"
},
  "geometry": {"coordinates":[0.4042100012,40.4457893372],"type":"Point"}
}