{
  "type": "Feature",
  "properties": {
    "addr:full":"Calle de Pascual Junquera, 36 Conil De La Frontera C\u00e1diz 11140",
    "addr:housenumber":"36",
    "addr:postcode":"11140",
    "addr:street":"Calle De Pascual Junquera",
    "iso:country":"ES",
    "sg:address":"Calle de Pascual Junquera, 36",
    "sg:city":"Conil De La Frontera",
    "sg:orig_category":"Reposter\u00cdas",
    "sg:phone":"+34 956 44 28 65",
    "sg:postcode":"11140",
    "sg:province":"C\u00e1diz",
    "wof:name":"Panaiso C.b",
    "wof:placetype":"venue"
},
  "geometry": {"coordinates":[-6.0847969055,36.2764053345],"type":"Point"}
}