{
  "type": "Feature",
  "properties": {
    "iso:country":"ES",
    "sg:address":"Calle de Huerta (la), 18",
    "sg:city":"Alcorcon",
    "sg:orig_category":"Ense\u00d1anza Variada",
    "sg:phone":"+34 916 44 14 94",
    "sg:postcode":"28921",
    "sg:province":"Madrid",
    "wof:name":"Academia Alcorcon S.l.",
    "wof:placetype":"venue"
},
  "geometry": {"coordinates":[-3.824216,40.344891],"type":"Point"}
}