{
  "type": "Feature",
  "properties": {
    "iso:country":"ES",
    "sg:address":"Carrer de Nou De La Rambla, 148",
    "sg:city":"Barcelona",
    "sg:orig_category":"Alimentaci\u00d3n General (al Por Menor)",
    "sg:phone":"+34 933 24 86 61",
    "sg:postcode":"08004",
    "sg:province":"Barcelona",
    "wof:name":"Baig 786 S.l.",
    "wof:placetype":"venue"
},
  "geometry": {"coordinates":[2.1674511433,41.3725166321],"type":"Point"}
}