{
  "type": "Feature",
  "properties": {
    "iso:country":"ES",
    "sg:address":"Calle de Platero Suarez, 14",
    "sg:city":"Valencia",
    "sg:orig_category":"Librer\u00cdas",
    "sg:phone":"+34 963 65 63 17",
    "sg:postcode":"46009",
    "sg:province":"Valencia",
    "wof:name":"Ca\u00f1averas Montero Esperanza",
    "wof:placetype":"venue"
},
  "geometry": {"coordinates":[-0.3727279902,39.4854621887],"type":"Point"}
}