{
  "type": "Feature",
  "properties": {
    "iso:country":"ES",
    "sg:address":"Carrer de Miquel Biada, 117",
    "sg:city":"Mataro",
    "sg:orig_category":"Art\u00cdculos De Regalo (al Por Menor)",
    "sg:phone":"+34 937 57 74 74",
    "sg:postcode":"08302",
    "sg:province":"Barcelona",
    "wof:name":"Marques Alarte Natalia",
    "wof:placetype":"venue"
},
  "geometry": {"coordinates":[2.4336910248,41.5371017456],"type":"Point"}
}