{
  "type": "Feature",
  "properties": {
    "iso:country":"ES",
    "sg:address":"Cust Matadero, 5",
    "sg:city":"Guadalajara",
    "sg:orig_category":"Alimentaci\u00d3n General (al Por Menor)",
    "sg:phone":"+34 949 21 44 77",
    "sg:postcode":"19001",
    "sg:province":"Guadalajara",
    "wof:name":"El Doradito Asador De Pollos S.l.",
    "wof:placetype":"venue"
},
  "geometry": {"coordinates":[-3.1674900055,40.6324424744],"type":"Point"}
}