{
  "type": "Feature",
  "properties": {
    "addr:full":"Plaz Nuestra Se\u00d1ora Del Buen Camino, 8 Madrid Madrid 28023",
    "addr:housenumber":"8",
    "addr:postcode":"madrid;28023",
    "addr:street":"Camino",
    "iso:country":"ES",
    "sg:address":"Plaz Nuestra Se\u00d1ora Del Buen Camino, 8",
    "sg:city":"Madrid",
    "sg:orig_category":"Caf\u00c9s, Bares, Cervecer\u00cdas",
    "sg:phone":"+34 913 07 16 39",
    "sg:postcode":"28023",
    "sg:province":"Madrid",
    "wof:name":"Hernandez Hernandez Lucio",
    "wof:placetype":"venue"
},
  "geometry": {"coordinates":[-3.7817807198,40.4573631287],"type":"Point"}
}