{
  "type": "Feature",
  "properties": {
    "addr:full":"Calle de Santa Teresa, 14 Novelda Alicante 03660",
    "addr:housenumber":"14",
    "addr:postcode":"03660",
    "addr:street":"Calle De Santa Teresa",
    "iso:country":"ES",
    "sg:address":"Calle de Santa Teresa, 14",
    "sg:city":"Novelda",
    "sg:orig_category":"Peluqueros: De Se\u00d1oras",
    "sg:phone":"+34 965 60 52 96",
    "sg:postcode":"03660",
    "sg:province":"Alicante",
    "wof:name":"Ba\u00f1o Sala Susana Del Socorro",
    "wof:placetype":"venue"
},
  "geometry": {"coordinates":[-0.7673820257,38.3872375488],"type":"Point"}
}