{
  "type": "Feature",
  "properties": {
    "iso:country":"ES",
    "sg:address":"Calle de Royal, 12",
    "sg:city":"Alcorisa",
    "sg:orig_category":"Mec\u00c1nico Del Autom\u00d3vil",
    "sg:phone":"+34 978 88 33 06",
    "sg:postcode":"44550",
    "sg:province":"Teruel",
    "wof:name":"Talleres El Royal S.l.",
    "wof:placetype":"venue"
},
  "geometry": {"coordinates":[-0.3736859858,40.8959503174],"type":"Point"}
}