{
  "type": "Feature",
  "properties": {
    "addr:full":"Calle de Maria De La Rocha, 10 Castillo Del Romeral Las Palmas 35107",
    "addr:housenumber":"10",
    "addr:postcode":"35107",
    "addr:street":"Calle De Maria De La Rocha",
    "iso:country":"ES",
    "sg:address":"Calle de Maria De La Rocha, 10",
    "sg:city":"Castillo Del Romeral",
    "sg:orig_category":"Fabricaci\u00d3n De Bebidas No Alcoh\u00d3licas",
    "sg:phone":"+34 928 72 80 43",
    "sg:postcode":"35107",
    "sg:province":"Las Palmas",
    "wof:name":"Concentrados Inmedio S.l.",
    "wof:placetype":"venue"
},
  "geometry": {"coordinates":[-15.4611282349,27.7993202209],"type":"Point"}
}