{
  "type": "Feature",
  "properties": {
    "iso:country":"ES",
    "sg:address":"Carrer de Copernic, 47",
    "sg:city":"Barcelona",
    "sg:orig_category":"Inform\u00c1tica: Consultores",
    "sg:phone":"+34 932 00 89 77",
    "sg:postcode":"08021",
    "sg:province":"Barcelona",
    "wof:name":"Lallier  Jerome",
    "wof:placetype":"venue"
},
  "geometry": {"coordinates":[2.1400918961,41.4008712769],"type":"Point"}
}