{
  "type": "Feature",
  "properties": {
    "addr:full":"Vall, 6 Tora Lleida 25750",
    "addr:housenumber":"6",
    "addr:postcode":"25750",
    "addr:street":"Vall",
    "iso:country":"ES",
    "sg:address":"Vall, 6",
    "sg:city":"Tora",
    "sg:orig_category":"Electricidad, Electr\u00d3nica: Suministros (al Por Menor)",
    "sg:phone":"+34 973 47 33 50",
    "sg:postcode":"25750",
    "sg:province":"Lleida",
    "wof:name":"Coscollola Andreu Magi",
    "wof:placetype":"venue"
},
  "geometry": {"coordinates":[1.4030200243,41.8117408752],"type":"Point"}
}