{
  "type": "Feature",
  "properties": {
    "addr:full":"Ctra Puebla, Km. 0130,5 Quintanar Orden Toledo 45800",
    "addr:postcode":"45800",
    "addr:street":"Ctra Puebla Km. 0130,5 Quintanar Orden",
    "iso:country":"ES",
    "sg:address":"Ctra Puebla, Km. 0130,5",
    "sg:city":"Quintanar Orden",
    "sg:orig_category":"Comercio De Piezas De Recambio Y De Accesorios De Veh\u00cdculos, Veh\u00cdculos Industriales",
    "sg:phone":"+34 925 56 43 20",
    "sg:postcode":"45800",
    "sg:province":"Toledo",
    "wof:name":"Quinmotor S.l.",
    "wof:placetype":"venue"
},
  "geometry": {"coordinates":[-3.047492981,39.5965499878],"type":"Point"}
}