{
  "type": "Feature",
  "properties": {
    "iso:country":"ES",
    "sg:address":"Calle de Osa De La Vega, 10",
    "sg:city":"Madrid",
    "sg:orig_category":"Molduras, Junquillos, Listones Y Molduras Perforadas",
    "sg:phone":"+34 917 05 23 94",
    "sg:postcode":"28044",
    "sg:province":"Madrid",
    "wof:name":"Jimenez Turon Agustin",
    "wof:placetype":"venue"
},
  "geometry": {"coordinates":[-3.7744379044,40.3753356934],"type":"Point"}
}