{
  "type": "Feature",
  "properties": {
    "addr:full":"Calle de Encomienda, 9 Madrid Madrid 28012",
    "addr:housenumber":"9",
    "addr:postcode":"madrid;28012",
    "addr:street":"Calle De Encomienda",
    "iso:country":"ES",
    "sg:address":"Calle de Encomienda, 9",
    "sg:city":"Madrid",
    "sg:orig_category":"Alimentaci\u00d3n General (al Por Menor)",
    "sg:phone":"+34 914 67 36 33",
    "sg:postcode":"28012",
    "sg:province":"Madrid",
    "wof:name":"Shun Tian Fan S.l.",
    "wof:placetype":"venue"
},
  "geometry": {"coordinates":[-3.7054979801,40.4106712341],"type":"Point"}
}