{
  "type": "Feature",
  "properties": {
    "iso:country":"ES",
    "sg:address":"Carr Corunya (la), 8",
    "sg:city":"Girona",
    "sg:orig_category":"Librer\u00cdas",
    "sg:phone":"+34 972 23 55 44",
    "sg:postcode":"17005",
    "sg:province":"Girona",
    "wof:name":"Ripoll Pi\u00f1ol Ramon",
    "wof:placetype":"venue"
},
  "geometry": {"coordinates":[2.8113689423,41.9715690613],"type":"Point"}
}