{
  "type": "Feature",
  "properties": {
    "iso:country":"ES",
    "sg:address":"Pla\u00c7 Paeria, 6",
    "sg:city":"Lleida",
    "sg:orig_category":"Danza, Cursos, Asociaciones Y M\u00dasicos",
    "sg:phone":"+34 973 24 66 36",
    "sg:postcode":"25007",
    "sg:province":"Lleida",
    "wof:name":"Sicoris Club",
    "wof:placetype":"venue"
},
  "geometry": {"coordinates":[0.627129972,41.6145210266],"type":"Point"}
}