{
  "type": "Feature",
  "properties": {
    "iso:country":"ES",
    "sg:address":"Carrer de Europa, 7",
    "sg:city":"Sitges",
    "sg:orig_category":"Sociedades, Compa\u00d1\u00cdas Aseguradoras",
    "sg:phone":"+34 938 11 33 64",
    "sg:postcode":"08870",
    "sg:province":"Barcelona",
    "wof:name":"Segurengin S.a.",
    "wof:placetype":"venue"
},
  "geometry": {"coordinates":[1.8058689833,41.2375259399],"type":"Point"}
}