{
  "type": "Feature",
  "properties": {
    "addr:full":"Calle de Jaime I, 23 Fraga Huesca 22520",
    "addr:housenumber":"23",
    "addr:postcode":"22520",
    "addr:street":"Calle De Jaime I",
    "iso:country":"ES",
    "sg:address":"Calle de Jaime I, 23",
    "sg:city":"Fraga",
    "sg:orig_category":"Servicio De Salud",
    "sg:phone":"+34 974 47 12 98",
    "sg:postcode":"22520",
    "sg:province":"Huesca",
    "sg:website":"www.dismatcuchi.com",
    "wof:name":"Dismat Cuchi S.l.",
    "wof:placetype":"venue"
},
  "geometry": {"coordinates":[0.3398149908,41.5205802917],"type":"Point"}
}