{
  "type": "Feature",
  "properties": {
    "iso:country":"ES",
    "sg:address":"Carrer de Catalunya, 11",
    "sg:city":"Castellar Valles",
    "sg:orig_category":"Institutos De Belleza",
    "sg:phone":"+34 937 14 42 05",
    "sg:postcode":"08211",
    "sg:province":"Barcelona",
    "wof:name":"Pla Gisbert Marta",
    "wof:placetype":"venue"
},
  "geometry": {"coordinates":[2.087250948,41.6122283936],"type":"Point"}
}