{
  "type": "Feature",
  "properties": {
    "iso:country":"ES",
    "sg:address":"Ctra. Palafrugell-torroella, S/n",
    "sg:city":"Palafrugell",
    "sg:orig_category":"Tapones Y Art\u00cdculos De Corcho",
    "sg:phone":"+34 972 30 29 51",
    "sg:postcode":"17200",
    "sg:province":"Girona",
    "wof:name":"J. Vigas S. A.",
    "wof:placetype":"venue"
},
  "geometry": {"coordinates":[3.1848859787,41.8965911865],"type":"Point"}
}