{
  "type": "Feature",
  "properties": {
    "iso:country":"ES",
    "sg:address":"Carr Montesa, 64",
    "sg:city":"Silla",
    "sg:orig_category":"Confecci\u00d3n (fabricaci\u00d3n, Al Por Mayor)",
    "sg:phone":"+34 961 21 23 27",
    "sg:postcode":"46460",
    "sg:province":"Valencia",
    "wof:name":"Martinez Navarro Ascension",
    "wof:placetype":"venue"
},
  "geometry": {"coordinates":[-0.4126380086,39.3598899841],"type":"Point"}
}