{
  "type": "Feature",
  "properties": {
    "iso:country":"ES",
    "sg:address":"Gral. Franco, 13",
    "sg:city":"Salillas De Jalon",
    "sg:orig_category":"Iglesia Cat\u00d3lica",
    "sg:phone":"+34 976 60 70 61",
    "sg:postcode":"50294",
    "sg:province":"Zaragoza",
    "wof:name":"Parroquia De San Martin",
    "wof:placetype":"venue"
},
  "geometry": {"coordinates":[-1.3237990141,41.5662460327],"type":"Point"}
}