{
  "type": "Feature",
  "properties": {
    "addr:full":"Rua Concepcion Arenal, 12 Betanzos La Coru\u00f1a 15300",
    "addr:housenumber":"12",
    "addr:postcode":"15300",
    "addr:street":"Rua Concepcion Arenal;La",
    "iso:country":"ES",
    "sg:address":"Rua Concepcion Arenal, 12",
    "sg:city":"Betanzos",
    "sg:orig_category":"Arquitectos",
    "sg:phone":"+34 981 77 58 14",
    "sg:postcode":"15300",
    "sg:province":"La Coru\u00f1a",
    "wof:name":"Maria Esther Casado De La Fuente S.l",
    "wof:placetype":"venue"
},
  "geometry": {"coordinates":[-8.2119092941,43.279914856],"type":"Point"}
}