{
  "type": "Feature",
  "properties": {
    "addr:full":"Avda Cantabrico Del, 1 Arroyo De La Miel-benalmadena Costa M\u00e1laga 29630",
    "addr:housenumber":"1",
    "addr:postcode":"29630",
    "addr:street":"Avda Cantabrico Del;Arroyo De La Miel-Benalmadena Costa Ma\u0301Laga",
    "iso:country":"ES",
    "sg:address":"Avda Cantabrico Del, 1",
    "sg:city":"Arroyo De La Miel-benalmadena Costa",
    "sg:orig_category":"Turismo: Lugares, Circuitos Y Curiosidades",
    "sg:phone":"+34 952 56 38 58",
    "sg:postcode":"29630",
    "sg:province":"M\u00e1laga",
    "wof:name":"Costasol Cruceros S.l.",
    "wof:placetype":"venue"
},
  "geometry": {"coordinates":[-4.521381855,36.5971374512],"type":"Point"}
}