{
  "type": "Feature",
  "properties": {
    "iso:country":"ES",
    "sg:address":"Vilar, 5",
    "sg:city":"Vilar",
    "sg:orig_category":"Art\u00cdculos Funerarios (al Por Menor)",
    "sg:phone":"+34 981 72 50 56",
    "sg:postcode":"15108",
    "sg:province":"La Coru\u00f1a",
    "wof:name":"Ramilo Cancela Ivan",
    "wof:placetype":"venue"
},
  "geometry": {"coordinates":[-8.6454324722,43.2194480896],"type":"Point"}
}