{
  "type": "Feature",
  "properties": {
    "addr:full":"Av Josep Tarradellas, 107 Barcelona Barcelona 08029",
    "addr:housenumber":"107",
    "addr:postcode":"08029",
    "addr:street":"Av Josep Tarradellas",
    "iso:country":"ES",
    "sg:address":"Av Josep Tarradellas, 107",
    "sg:city":"Barcelona",
    "sg:orig_category":"Ense\u00d1anza Variada",
    "sg:phone":"+34 934 19 56 90",
    "sg:postcode":"08029",
    "sg:province":"Barcelona",
    "wof:name":"Torrente Tomas Maria Jose",
    "wof:placetype":"venue"
},
  "geometry": {"coordinates":[2.1426899433,41.3880958557],"type":"Point"}
}