{
  "type": "Feature",
  "properties": {
    "addr:full":"Avda Galicia, 34 Vegadeo Asturias 33770",
    "addr:housenumber":"34",
    "addr:postcode":"33770",
    "addr:street":"Avda Galicia",
    "iso:country":"ES",
    "sg:address":"Avda Galicia, 34",
    "sg:city":"Vegadeo",
    "sg:orig_category":"Negocio De Madera",
    "sg:phone":"+34 985 63 40 29",
    "sg:postcode":"33770",
    "sg:province":"Asturias",
    "wof:name":"Maderas Vijande S.a.",
    "wof:placetype":"venue"
},
  "geometry": {"coordinates":[-7.0533261299,43.4646911621],"type":"Point"}
}