{
  "type": "Feature",
  "properties": {
    "addr:full":"Calle de Santa Florentina, 20 Cartagena Murcia 30201",
    "addr:housenumber":"20",
    "addr:postcode":"30201",
    "addr:street":"Calle De Santa Florentina",
    "iso:country":"ES",
    "sg:address":"Calle de Santa Florentina, 20",
    "sg:city":"Cartagena",
    "sg:orig_category":"Ropa Para Ni\u00d1os (al Por Menor)",
    "sg:phone":"+34 968 50 30 61",
    "sg:postcode":"30201",
    "sg:province":"Murcia",
    "wof:name":"Velasco Cervantes Maria Jose",
    "wof:placetype":"venue"
},
  "geometry": {"coordinates":[-0.98739779,37.6039009094],"type":"Point"}
}