{
  "type": "Feature",
  "properties": {
    "addr:full":"Calle de San Francisco, 8 Le\u00f3n Le\u00f3n 24003",
    "addr:housenumber":"8",
    "addr:postcode":"24003",
    "addr:street":"Calle De San Francisco;Leo\u0301N",
    "iso:country":"ES",
    "sg:address":"Calle de San Francisco, 8",
    "sg:city":"Le\u00f3n",
    "sg:orig_category":"Promotores Constructores",
    "sg:phone":"+34 987 21 18 72",
    "sg:postcode":"24003",
    "sg:province":"Le\u00f3n",
    "wof:name":"Euroques S.l.",
    "wof:placetype":"venue"
},
  "geometry": {"coordinates":[-5.5698251724,42.5948982239],"type":"Point"}
}