{
  "type": "Feature",
  "properties": {
    "iso:country":"ES",
    "sg:address":"Calle de Santiago, 27",
    "sg:city":"Arzua",
    "sg:orig_category":"Promotores Constructores",
    "sg:phone":"+34 981 50 10 80",
    "sg:postcode":"15810",
    "sg:province":"La Coru\u00f1a",
    "wof:name":"Comunidad De Propietarios Santiago 7",
    "wof:placetype":"venue"
},
  "geometry": {"coordinates":[-8.1651191711,42.9270210266],"type":"Point"}
}