{
  "type": "Feature",
  "properties": {
    "addr:full":"Calle de Iglesia, 11 Navaluenga \u00c1vila 05100",
    "addr:housenumber":"11",
    "addr:postcode":"05100",
    "addr:street":"Calle De Iglesia",
    "iso:country":"ES",
    "sg:address":"Calle de Iglesia, 11",
    "sg:city":"Navaluenga",
    "sg:orig_category":"Molduras, Junquillos, Listones Y Molduras Perforadas",
    "sg:phone":"+34 920 28 60 12",
    "sg:postcode":"05100",
    "sg:province":"\u00c1vila",
    "wof:name":"Martin Gonzalez Isaac",
    "wof:placetype":"venue"
},
  "geometry": {"coordinates":[-4.7079091072,40.4109916687],"type":"Point"}
}