{
  "type": "Feature",
  "properties": {
    "addr:full":"Calle de Campo De Criptana, 70 Socuellamos Ciudad Real 13630",
    "addr:housenumber":"70",
    "addr:postcode":"13630",
    "addr:street":"Calle De Campo De Criptana",
    "iso:country":"ES",
    "sg:address":"Calle de Campo De Criptana, 70",
    "sg:city":"Socuellamos",
    "sg:orig_category":"Empresas De Carpinter\u00cda",
    "sg:phone":"+34 926 53 01 28",
    "sg:postcode":"13630",
    "sg:province":"Ciudad Real",
    "wof:name":"Aluminios Olivares Esparcia S.l.",
    "wof:placetype":"venue"
},
  "geometry": {"coordinates":[-2.8036251068,39.285736084],"type":"Point"}
}