{
  "type": "Feature",
  "properties": {
    "addr:full":"Calle de Maria Estrada, 1 Pto. Rosario Las Palmas 35600",
    "addr:housenumber":"1",
    "addr:postcode":"35600",
    "addr:street":"Calle De Maria Estrada;Pto. Rosario Las",
    "iso:country":"ES",
    "sg:address":"Calle de Maria Estrada, 1",
    "sg:city":"Pto. Rosario",
    "sg:orig_category":"Inform\u00c1tica, Ofim\u00c1tica (estudios, Asesor\u00cda, Ingenier\u00cda, Formaci\u00d3n)",
    "sg:phone":"+34 928 53 02 38",
    "sg:postcode":"35600",
    "sg:province":"Las Palmas",
    "sg:website":"www.telmax.es",
    "wof:name":"Telecomunicaciones Maxorata S.l.",
    "wof:placetype":"venue"
},
  "geometry": {"coordinates":[-13.8721561432,28.502696991],"type":"Point"}
}