{
  "type": "Feature",
  "properties": {
    "iso:country":"ES",
    "sg:address":"Carrer de Valencia, 359",
    "sg:city":"Barcelona",
    "sg:orig_category":"Grafistas",
    "sg:phone":"+34 934 58 90 26",
    "sg:postcode":"08009",
    "sg:province":"Barcelona",
    "wof:name":"Vilet Estudi Grafic S.l.",
    "wof:placetype":"venue"
},
  "geometry": {"coordinates":[2.1710810661,41.3987236023],"type":"Point"}
}