{
  "type": "Feature",
  "properties": {
    "addr:full":"Rbla Xavier Cugat, 23 Girona Girona 17007",
    "addr:housenumber":"23",
    "addr:postcode":"17007",
    "addr:street":"Rbla Xavier Cugat",
    "iso:country":"ES",
    "sg:address":"Rbla Xavier Cugat, 23",
    "sg:city":"Girona",
    "sg:orig_category":"Peluquer\u00cdas, Peluquer\u00cda Mixta",
    "sg:phone":"+34 972 41 07 36",
    "sg:postcode":"17007",
    "sg:province":"Girona",
    "wof:name":"Brugada Marin Ester",
    "wof:placetype":"venue"
},
  "geometry": {"coordinates":[2.8161270618,41.9924583435],"type":"Point"}
}