{
  "type": "Feature",
  "properties": {
    "addr:full":"Calle de San Francisco, 2 Baeza Ja\u00e9n 23440",
    "addr:housenumber":"2",
    "addr:postcode":"23440",
    "addr:street":"Calle De San Francisco",
    "iso:country":"ES",
    "sg:address":"Calle de San Francisco, 2",
    "sg:city":"Baeza",
    "sg:orig_category":"Quincaller\u00cda (al Por Menor)",
    "sg:phone":"+34 953 74 06 97",
    "sg:postcode":"23440",
    "sg:province":"Ja\u00e9n",
    "wof:name":"Palomares Gamez S.l.",
    "wof:placetype":"venue"
},
  "geometry": {"coordinates":[-3.4684009552,37.9934921265],"type":"Point"}
}