{
  "type": "Feature",
  "properties": {
    "addr:full":"Alde Salgueiras, S/n Caridad Asturias 33750",
    "addr:housenumber":"/ n",
    "addr:postcode":"33750",
    "addr:street":"Alde;S",
    "iso:country":"ES",
    "sg:address":"Alde Salgueiras, S/n",
    "sg:city":"Caridad",
    "sg:orig_category":"Hormig\u00d3n (m\u00c1quinas E Instalaci\u00d3n)",
    "sg:phone":"+34 985 47 81 76",
    "sg:postcode":"33750",
    "sg:province":"Asturias",
    "wof:name":"Hormigones La Caridad S.a.",
    "wof:placetype":"venue"
},
  "geometry": {"coordinates":[-6.8270339966,43.5506744385],"type":"Point"}
}