{
  "type": "Feature",
  "properties": {
    "addr:full":"Calle de Agustina De Aragon, 72 Altorricon Huesca 22540",
    "addr:housenumber":"72",
    "addr:postcode":"22540",
    "addr:street":"Calle De Agustina De Aragon",
    "iso:country":"ES",
    "sg:address":"Calle de Agustina De Aragon, 72",
    "sg:city":"Altorricon",
    "sg:orig_category":"Promotores Constructores",
    "sg:phone":"+34 974 42 54 24",
    "sg:postcode":"22540",
    "sg:province":"Huesca",
    "wof:name":"Ramiral Hermanos S.l.l.",
    "wof:placetype":"venue"
},
  "geometry": {"coordinates":[0.4150558114,41.8028869629],"type":"Point"}
}