{
  "type": "Feature",
  "properties": {
    "addr:full":"Calle de Benaque, 11 Malaga M\u00e1laga 29004",
    "addr:housenumber":"11",
    "addr:postcode":"29004",
    "addr:street":"Calle De Benaque;Ma\u0301Laga",
    "iso:country":"ES",
    "sg:address":"Calle de Benaque, 11",
    "sg:city":"Malaga",
    "sg:orig_category":"Vinos Y Licores (venta Al Por Menor)",
    "sg:phone":"+34 952 24 68 39",
    "sg:postcode":"29004",
    "sg:province":"M\u00e1laga",
    "sg:website":"www.sanchezmancebo.com",
    "wof:name":"Sanchez Mancebo Francisco",
    "wof:placetype":"venue"
},
  "geometry": {"coordinates":[-4.4678406715,36.6842956543],"type":"Point"}
}