{
  "type": "Feature",
  "properties": {
    "iso:country":"ES",
    "sg:address":"Avda Ferrol (del), 11",
    "sg:city":"Viveiro",
    "sg:orig_category":"Partidos Pol\u00cdticos",
    "sg:phone":"+34 982 56 14 09",
    "sg:postcode":"27850",
    "sg:province":"Lugo",
    "wof:name":"Coalicion Electoral Izquierda Unida",
    "wof:placetype":"venue"
},
  "geometry": {"coordinates":[-7.5992488861,43.6569519043],"type":"Point"}
}