{
  "type": "Feature",
  "properties": {
    "addr:full":"Carr Carme, 32 Rosell Castell\u00f3n 12511",
    "addr:housenumber":"32",
    "addr:postcode":"12511",
    "addr:street":"Carr Carme;Castello\u0301N",
    "iso:country":"ES",
    "sg:address":"Carr Carme, 32",
    "sg:city":"Rosell",
    "sg:orig_category":"Transportes Por Carretera: Lotes Completos, Mercanc\u00cdas Diversas",
    "sg:phone":"+34 977 57 11 19",
    "sg:postcode":"12511",
    "sg:province":"Castell\u00f3n",
    "wof:name":"Gabalda Sabater Josefa",
    "wof:placetype":"venue"
},
  "geometry": {"coordinates":[0.2241230011,40.6156044006],"type":"Point"}
}