{
  "type": "Feature",
  "properties": {
    "iso:country":"ES",
    "sg:address":"Pl Don Fco Martin, S/n",
    "sg:city":"Caminomorisco",
    "sg:orig_category":"Bancos",
    "sg:phone":"+34 927 43 51 96",
    "sg:postcode":"10620",
    "sg:province":"C\u00e1ceres",
    "wof:name":"Palomo Rivero Eufemio",
    "wof:placetype":"venue"
},
  "geometry": {"coordinates":[-6.2905039787,40.3265113831],"type":"Point"}
}