{
  "type": "Feature",
  "properties": {
    "addr:full":"Calle de Mesiego, S/n Mesiego Ourense 32500",
    "addr:housenumber":"s",
    "addr:postcode":"32500",
    "addr:street":"Calle De Mesiego;/ N",
    "iso:country":"ES",
    "sg:address":"Calle de Mesiego, S/n",
    "sg:city":"Mesiego",
    "sg:orig_category":"Promotores Constructores",
    "sg:phone":"+34 988 27 30 58",
    "sg:postcode":"32500",
    "sg:province":"Ourense",
    "wof:name":"Barreiros Rodriguez Maximo",
    "wof:placetype":"venue"
},
  "geometry": {"coordinates":[-8.0741043091,42.433265686],"type":"Point"}
}