{
  "type": "Feature",
  "properties": {
    "iso:country":"ES",
    "sg:address":"Rua Fernandez Varela, 51",
    "sg:city":"Pobra Do Carami\u00e7al",
    "sg:orig_category":"Bebidas",
    "sg:phone":"+34 981 83 12 53",
    "sg:postcode":"15940",
    "sg:province":"La Coru\u00f1a",
    "wof:name":"Gaseosas Barbanza S.l.",
    "wof:placetype":"venue"
},
  "geometry": {"coordinates":[-8.3959693909,43.3714904785],"type":"Point"}
}