{
  "type": "Feature",
  "properties": {
    "iso:country":"ES",
    "sg:address":"Pla\u00c7 Cotxes, 3",
    "sg:city":"Vilanova I La Geltru",
    "sg:orig_category":"Centros De Educaci\u00d3n Especial",
    "sg:phone":"+34 938 93 02 80",
    "sg:postcode":"08800",
    "sg:province":"Barcelona",
    "wof:name":"Fundacio El Cim De Vilanova I La Geltru",
    "wof:placetype":"venue"
},
  "geometry": {"coordinates":[1.705232501,41.2381515503],"type":"Point"}
}