{
  "type": "Feature",
  "properties": {
    "addr:full":"Calle de Catorcena (la), 1 Segovia Segovia 40001",
    "addr:housenumber":"1",
    "addr:postcode":"40001",
    "addr:street":"Calle De Catorcena La",
    "iso:country":"ES",
    "sg:address":"Calle de Catorcena (la), 1",
    "sg:city":"Segovia",
    "sg:orig_category":"Procuradores",
    "sg:phone":"+34 921 46 04 44",
    "sg:postcode":"40001",
    "sg:province":"Segovia",
    "wof:name":"Ascension Diaz Carmen",
    "wof:placetype":"venue"
},
  "geometry": {"coordinates":[-4.1199297905,40.9500694275],"type":"Point"}
}