{
  "type": "Feature",
  "properties": {
    "iso:country":"ES",
    "sg:address":"Carrer de Joan Estelrich Art, 34",
    "sg:city":"Palma",
    "sg:orig_category":"Administradores De Bienes Y Delegados De Comunidades De Propietarios",
    "sg:phone":"+34 971 47 56 67",
    "sg:postcode":"07008",
    "sg:province":"Islas Baleares",
    "wof:name":"Vaquer Mariano Rafael",
    "wof:placetype":"venue"
},
  "geometry": {"coordinates":[2.6758658886,39.5826644897],"type":"Point"}
}