{
  "type": "Feature",
  "properties": {
    "iso:country":"ES",
    "sg:address":"Av Diputacio, 141",
    "sg:city":"Cambrils",
    "sg:orig_category":"Alquiler De Veh\u00cdculos: Turismos Y Utilitarios",
    "sg:phone":"+34 977 79 30 11",
    "sg:postcode":"43850",
    "sg:province":"Tarragona",
    "wof:name":"Jet Car Salou",
    "wof:placetype":"venue"
},
  "geometry": {"coordinates":[1.1002149582,41.0709457397],"type":"Point"}
}