{
  "type": "Feature",
  "properties": {
    "addr:full":"Afueras, S/n S. Francesc Formentera Islas Baleares 07860",
    "addr:postcode":"07860",
    "addr:street":"Afueras S / N S. Francesc",
    "iso:country":"ES",
    "sg:address":"Afueras, S/n",
    "sg:city":"S. Francesc Formentera",
    "sg:orig_category":"Negocio De Materiales De Construcci\u00d3n",
    "sg:phone":"+34 971 32 23 74",
    "sg:postcode":"07860",
    "sg:province":"Islas Baleares",
    "wof:name":"Portas Mari Vicente",
    "wof:placetype":"venue"
},
  "geometry": {"coordinates":[1.4309200048,38.7072410583],"type":"Point"}
}