{
  "type": "Feature",
  "properties": {
    "addr:full":"Calle de Diego Jimenez, 16 Cuenca Cuenca 16004",
    "addr:housenumber":"16",
    "addr:postcode":"16004",
    "addr:street":"Calle De Diego Jimenez",
    "iso:country":"ES",
    "sg:address":"Calle de Diego Jimenez, 16",
    "sg:city":"Cuenca",
    "sg:orig_category":"Muebles, Minoristas",
    "sg:phone":"+34 969 22 02 67",
    "sg:postcode":"16004",
    "sg:province":"Cuenca",
    "wof:name":"Evangelio Mobiliario Y Decoracion S.l.",
    "wof:placetype":"venue"
},
  "geometry": {"coordinates":[-2.1371517181,40.0693397522],"type":"Point"}
}