{
  "type": "Feature",
  "properties": {
    "iso:country":"ES",
    "sg:address":"Carrer de Alts Forns, 21",
    "sg:city":"Barcelona",
    "sg:orig_category":"Reposter\u00cdas",
    "sg:phone":"+34 934 31 14 41",
    "sg:postcode":"08038",
    "sg:province":"Barcelona",
    "wof:name":"Distribuidora Del Gornal S. A.",
    "wof:placetype":"venue"
},
  "geometry": {"coordinates":[2.1350979805,41.3564414978],"type":"Point"}
}