{
  "type": "Feature",
  "properties": {
    "addr:full":"Carrer de Victor Catala, 2 Barri Maritim De Comarruga Tarragona 43880",
    "addr:housenumber":"2",
    "addr:postcode":"43880",
    "addr:street":"Carrer De Victor Catala",
    "iso:country":"ES",
    "sg:address":"Carrer de Victor Catala, 2",
    "sg:city":"Barri Maritim De Comarruga",
    "sg:orig_category":"Bancos",
    "sg:phone":"+34 977 68 00 29",
    "sg:postcode":"43880",
    "sg:province":"Tarragona",
    "wof:name":"Banco Popular Espa\u00f1ol",
    "wof:placetype":"venue"
},
  "geometry": {"coordinates":[1.5386699438,41.1833496094],"type":"Point"}
}