{
  "type": "Feature",
  "properties": {
    "addr:full":"Calle de Conquistadores, S/n Ca\u00f1amero C\u00e1ceres 10136",
    "addr:housenumber":"s / n",
    "addr:postcode":"10136",
    "addr:street":"Calle De Conquistadores;Ca\u0301Ceres",
    "iso:country":"ES",
    "sg:address":"Calle de Conquistadores, S/n",
    "sg:city":"Ca\u00f1amero",
    "sg:orig_category":"Reposter\u00cdas",
    "sg:phone":"+34 927 36 91 03",
    "sg:postcode":"10136",
    "sg:province":"C\u00e1ceres",
    "wof:name":"Solano Plaza Maria Paz",
    "wof:placetype":"venue"
},
  "geometry": {"coordinates":[-5.3885989189,39.3804588318],"type":"Point"}
}