{
  "type": "Feature",
  "properties": {
    "addr:full":"I Newton(pi Estanquillo), 14 Burguillos Sevilla 41220",
    "addr:housenumber":"14",
    "addr:postcode":"41220",
    "addr:street":"I;Pi Estanquillo",
    "iso:country":"ES",
    "sg:address":"I Newton(pi Estanquillo), 14",
    "sg:city":"Burguillos",
    "sg:orig_category":"Embalajes",
    "sg:phone":"+34 955 73 82 76",
    "sg:postcode":"41220",
    "sg:province":"Sevilla",
    "wof:name":"Sevicaja S.l.",
    "wof:placetype":"venue"
},
  "geometry": {"coordinates":[-5.9713540077,37.5882263184],"type":"Point"}
}