{
  "type": "Feature",
  "properties": {
    "addr:full":"Carrer de Duquessa D'orleans, 23 Barcelona Barcelona 08034",
    "addr:housenumber":"23",
    "addr:postcode":"08034",
    "addr:street":"Carrer De Duquessa D'Orleans",
    "iso:country":"ES",
    "sg:address":"Carrer de Duquessa D'orleans, 23",
    "sg:city":"Barcelona",
    "sg:orig_category":"Art\u00cdculos De Decoraci\u00d3n (fabricaci\u00d3n Y Al Por Mayor)",
    "sg:phone":"+34 932 80 26 09",
    "sg:postcode":"08034",
    "sg:province":"Barcelona",
    "wof:name":"Doico Proyectes S.l.",
    "wof:placetype":"venue"
},
  "geometry": {"coordinates":[2.1200499535,41.3983001709],"type":"Point"}
}