{
  "type": "Feature",
  "properties": {
    "iso:country":"ES",
    "sg:address":"Calle de Doctor Villalobos, 24",
    "sg:city":"Zamora",
    "sg:orig_category":"Instalaci\u00d3n, Reparaci\u00d3n De Ascensores Y Montacargas",
    "sg:phone":"+34 980 51 69 70",
    "sg:postcode":"49017",
    "sg:province":"Zamora",
    "sg:website":"www.zener.org",
    "wof:name":"Zener Elevadores Del Noroeste S.l.",
    "wof:placetype":"venue"
},
  "geometry": {"coordinates":[-5.7335448265,41.504360199],"type":"Point"}
}