{
  "type": "Feature",
  "properties": {
    "iso:country":"ES",
    "sg:address":"Plaz Comercio, 11",
    "sg:city":"San Sebastian De Los Reyes",
    "sg:orig_category":"Ropa Para Se\u00d1oras (al Por Menor)",
    "sg:phone":"+34 916 51 53 45",
    "sg:postcode":"28700",
    "sg:province":"Madrid",
    "wof:name":"Acebo 2004 S.l.",
    "wof:placetype":"venue"
},
  "geometry": {"coordinates":[-3.6263942719,40.5475120544],"type":"Point"}
}