{
  "type": "Feature",
  "properties": {
    "iso:country":"ES",
    "sg:address":"Carrer de Pare Claret, 58",
    "sg:city":"Roses",
    "sg:orig_category":"Empresas De Pintura Y Revestimientos",
    "sg:phone":"+34 972 25 68 58",
    "sg:postcode":"17480",
    "sg:province":"Girona",
    "wof:name":"Llambrich Barbara Augusto",
    "wof:placetype":"venue"
},
  "geometry": {"coordinates":[3.1824169159,42.2627601624],"type":"Point"}
}