{
  "type": "Feature",
  "properties": {
    "iso:country":"ES",
    "sg:address":"Calle de Pasion, 15",
    "sg:city":"Valladolid",
    "sg:orig_category":"Promotores Constructores",
    "sg:phone":"+34 983 33 73 57",
    "sg:postcode":"47001",
    "sg:province":"Valladolid",
    "wof:name":"Alberto Perez Medina E Isidoro Perez Medina Cdad.",
    "wof:placetype":"venue"
},
  "geometry": {"coordinates":[-4.7304077148,41.6513252258],"type":"Point"}
}