{
  "type": "Feature",
  "properties": {
    "addr:full":"Avda Velazquez, 52 Malaga M\u00e1laga 29003",
    "addr:housenumber":"52",
    "addr:postcode":"29003",
    "addr:street":"Avda Velazquez;Ma\u0301Laga",
    "iso:country":"ES",
    "sg:address":"Avda Velazquez, 52",
    "sg:city":"Malaga",
    "sg:orig_category":"Cl\u00cdnicas Dentales",
    "sg:phone":"+34 952 36 38 70",
    "sg:postcode":"29003",
    "sg:province":"M\u00e1laga",
    "wof:name":"Corporacion Dental Bucodente S.l.u.",
    "wof:placetype":"venue"
},
  "geometry": {"coordinates":[-4.4479990005,36.6980285645],"type":"Point"}
}