{
  "type": "Feature",
  "properties": {
    "addr:full":"Carrer de Ramon Y Cajal, 83 Barcelona Barcelona 08024",
    "addr:housenumber":"83",
    "addr:postcode":"08024",
    "addr:street":"Carrer De Ramon Y Cajal",
    "iso:country":"ES",
    "sg:address":"Carrer de Ramon Y Cajal, 83",
    "sg:city":"Barcelona",
    "sg:orig_category":"Radiocomunicaciones, Telefon\u00cda M\u00d3vil, Radiomensajer\u00cda: Servicios, Comercializaci\u00d3n",
    "sg:phone":"+34 932 85 34 67",
    "sg:postcode":"08024",
    "sg:province":"Barcelona",
    "wof:name":"Ali  Ansar",
    "wof:placetype":"venue"
},
  "geometry": {"coordinates":[2.1615223885,41.4043960571],"type":"Point"}
}