{
  "type": "Feature",
  "properties": {
    "addr:full":"Carrer de Desclapers, 19 Malgrat Mar Barcelona 08380",
    "addr:housenumber":"19",
    "addr:postcode":"08380",
    "addr:street":"Carrer De Desclapers",
    "iso:country":"ES",
    "sg:address":"Carrer de Desclapers, 19",
    "sg:city":"Malgrat Mar",
    "sg:orig_category":"Inmobiliaria (agencias)",
    "sg:phone":"+34 937 66 05 55",
    "sg:postcode":"08380",
    "sg:province":"Barcelona",
    "wof:name":"Serveis Inmobiliaris Nova-llar 2004 S.l.",
    "wof:placetype":"venue"
},
  "geometry": {"coordinates":[2.7414069176,41.6461791992],"type":"Point"}
}