{
  "type": "Feature",
  "properties": {
    "addr:full":"Calle de Cacere\u00d1os, 62 Madrid Madrid 28021",
    "addr:housenumber":"62",
    "addr:postcode":"madrid;28021",
    "addr:street":"Calle De Caceren\u0303Os",
    "iso:country":"ES",
    "sg:address":"Calle de Cacere\u00d1os, 62",
    "sg:city":"Madrid",
    "sg:orig_category":"Cerrajer\u00cda, Ferrallista",
    "sg:phone":"+34 917 95 23 32",
    "sg:postcode":"28021",
    "sg:province":"Madrid",
    "wof:name":"Garcia Garcia Ricardo",
    "wof:placetype":"venue"
},
  "geometry": {"coordinates":[-3.7144377232,40.3445587158],"type":"Point"}
}