{
  "type": "Feature",
  "properties": {
    "addr:full":"Calle de Azahar, 13 Puente Tocinos Murcia 30006",
    "addr:housenumber":"13",
    "addr:postcode":"30006",
    "addr:street":"Calle De Azahar",
    "iso:country":"ES",
    "sg:address":"Calle de Azahar, 13",
    "sg:city":"Puente Tocinos",
    "sg:orig_category":"Alimentaci\u00d3n General (al Por Menor)",
    "sg:phone":"+34 968 30 23 49",
    "sg:postcode":"30006",
    "sg:province":"Murcia",
    "wof:name":"Mu\u00f1oz Mu\u00f1oz Juan Jose",
    "wof:placetype":"venue"
},
  "geometry": {"coordinates":[-1.0994383097,37.9939041138],"type":"Point"}
}