{
  "type": "Feature",
  "properties": {
    "addr:full":"M. Yurramendi Kalea, 24 Urnieta Guip\u00f9zcoa 20130",
    "addr:housenumber":"24",
    "addr:postcode":"20130",
    "addr:street":"M. Yurramendi Kalea;Guipu\u0300Zcoa",
    "iso:country":"ES",
    "sg:address":"M. Yurramendi Kalea, 24",
    "sg:city":"Urnieta",
    "sg:orig_category":"Loter\u00cda Y T\u00d3mbola",
    "sg:phone":"+34 943 55 61 50",
    "sg:postcode":"20130",
    "sg:province":"Guip\u00f9zcoa",
    "wof:name":"Roteta Garate Maria Victoria",
    "wof:placetype":"venue"
},
  "geometry": {"coordinates":[-1.9927469492,43.2471237183],"type":"Point"}
}