{
  "type": "Feature",
  "properties": {
    "iso:country":"ES",
    "sg:address":"Calle de Constantino Rodriguez, 21",
    "sg:city":"Pozuelo De Alarcon",
    "sg:orig_category":"Promotores Constructores",
    "sg:phone":"+34 913 51 61 29",
    "sg:postcode":"28224",
    "sg:province":"Madrid",
    "wof:name":"Arquitectura Construccion E Ingenieria S. A.",
    "wof:placetype":"venue"
},
  "geometry": {"coordinates":[-3.8099908829,40.4485015869],"type":"Point"}
}