{
  "type": "Feature",
  "properties": {
    "addr:full":"Calle de Diego Betancor Suarez, 21 Palmas De Gran Canaria Las Palmas 35012",
    "addr:housenumber":"21",
    "addr:postcode":"35012",
    "addr:street":"Calle De Diego Betancor Suarez",
    "iso:country":"ES",
    "sg:address":"Calle de Diego Betancor Suarez, 21",
    "sg:city":"Palmas De Gran Canaria",
    "sg:orig_category":"Peluquer\u00cdas, Peluquer\u00cda Mixta",
    "sg:phone":"+34 928 42 77 27",
    "sg:postcode":"35012",
    "sg:province":"Las Palmas",
    "wof:name":"Benjamin Alejo Madeline",
    "wof:placetype":"venue"
},
  "geometry": {"coordinates":[-15.4450492859,28.1105823517],"type":"Point"}
}