{
  "type": "Feature",
  "properties": {
    "iso:country":"ES",
    "sg:address":"Calle de Culantrillo, 25",
    "sg:city":"Mozaga",
    "sg:orig_category":"Chapister\u00cda",
    "sg:phone":"+34 928 52 07 18",
    "sg:postcode":"35530",
    "sg:province":"Las Palmas",
    "wof:name":"Perez Perez Florencio",
    "wof:placetype":"venue"
},
  "geometry": {"coordinates":[-13.6147766113,29.0248031616],"type":"Point"}
}