{
  "type": "Feature",
  "properties": {
    "addr:full":"Calle de Navalmoral De La Mata, 21 Coria C\u00e1ceres 10800",
    "addr:postcode":"10800",
    "addr:street":"Calle De Navalmoral",
    "iso:country":"ES",
    "sg:address":"Calle de Navalmoral De La Mata, 21",
    "sg:city":"Coria",
    "sg:orig_category":"Transportes Por V\u00cdas Navegables",
    "sg:phone":"+34 927 50 01 98",
    "sg:postcode":"10800",
    "sg:province":"C\u00e1ceres",
    "wof:name":"Zanca Dominguez Jose Luis",
    "wof:placetype":"venue"
},
  "geometry": {"coordinates":[-6.5315537453,39.9836997986],"type":"Point"}
}