{
  "type": "Feature",
  "properties": {
    "iso:country":"ES",
    "sg:address":"Calle de Anden, 20",
    "sg:city":"Burriana",
    "sg:orig_category":"Arquitectos",
    "sg:phone":"+34 964 51 33 50",
    "sg:postcode":"12530",
    "sg:province":"Castell\u00f3n",
    "wof:name":"Lopez Soler Miguel Angel",
    "wof:placetype":"venue"
},
  "geometry": {"coordinates":[-0.0840215012,39.8887367249],"type":"Point"}
}