{
  "type": "Feature",
  "properties": {
    "addr:full":"Carrer de Freixa, 48 Barcelona Barcelona 08021",
    "addr:housenumber":"48",
    "addr:postcode":"08021",
    "addr:street":"Carrer De Freixa",
    "iso:country":"ES",
    "sg:address":"Carrer de Freixa, 48",
    "sg:city":"Barcelona",
    "sg:orig_category":"Muebles Y Accesorios Para Cocinas Y Cuartos De Ba\u00d1o (al Por Menor)",
    "sg:phone":"+34 932 40 04 10",
    "sg:postcode":"08021",
    "sg:province":"Barcelona",
    "sg:website":"www.bulthaup.com",
    "wof:name":"Bulthaup Iberia S.l.",
    "wof:placetype":"venue"
},
  "geometry": {"coordinates":[2.1395099163,41.3991584778],"type":"Point"}
}