{
  "type": "Feature",
  "properties": {
    "addr:full":"Ctra Illora De Zujaira, 2 Zujaira Granada 18291",
    "addr:housenumber":"2",
    "addr:postcode":"18291",
    "addr:street":"Ctra Illora De Zujaira",
    "iso:country":"ES",
    "sg:address":"Ctra Illora De Zujaira, 2",
    "sg:city":"Zujaira",
    "sg:orig_category":"Aceites Y Grasas Alimentarias (fabricaci\u00d3n, Al Por Mayor)",
    "sg:phone":"+34 958 46 17 26",
    "sg:postcode":"18291",
    "sg:province":"Granada",
    "wof:name":"Vega Oliva S.l.",
    "wof:placetype":"venue"
},
  "geometry": {"coordinates":[-3.7914540768,37.257270813],"type":"Point"}
}