{
  "type": "Feature",
  "properties": {
    "iso:country":"ES",
    "sg:address":"Calle de Musica (de La), 8",
    "sg:city":"Alaquas",
    "sg:orig_category":"Torneros Sobre Madera",
    "sg:phone":"+34 961 50 36 68",
    "sg:postcode":"46970",
    "sg:province":"Valencia",
    "wof:name":"Cases Garcia Federico",
    "wof:placetype":"venue"
},
  "geometry": {"coordinates":[-0.4591600001,39.4566459656],"type":"Point"}
}