{
  "type": "Feature",
  "properties": {
    "iso:country":"ES",
    "sg:address":"Calle de Magdalena, 1",
    "sg:city":"Madrid",
    "sg:orig_category":"Caf\u00c9s, Bares, Cervecer\u00cdas",
    "sg:phone":"+34 913 69 36 47",
    "sg:postcode":"28012",
    "sg:province":"Madrid",
    "wof:name":"Garcia Garcia Valentin",
    "wof:placetype":"venue"
},
  "geometry": {"coordinates":[-3.703097105,40.4125518799],"type":"Point"}
}