{
  "type": "Feature",
  "properties": {
    "addr:full":"Gral. Cirujeda, 9 Chella Valencia 46821",
    "addr:housenumber":"9",
    "addr:postcode":"46821",
    "addr:street":"Gral. Cirujeda",
    "iso:country":"ES",
    "sg:address":"Gral. Cirujeda, 9",
    "sg:city":"Chella",
    "sg:orig_category":"Negocio De Enlosados, Soler\u00cdas",
    "sg:phone":"+34 962 22 01 27",
    "sg:postcode":"46821",
    "sg:province":"Valencia",
    "wof:name":"Garcia Ortiz Rafael",
    "wof:placetype":"venue"
},
  "geometry": {"coordinates":[-0.6867939234,39.0377998352],"type":"Point"}
}