{
  "type": "Feature",
  "properties": {
    "iso:country":"ES",
    "sg:address":"Calle de Don Sancho, 14",
    "sg:city":"Palencia",
    "sg:orig_category":"Florister\u00cdas",
    "sg:phone":"+34 979 74 05 34",
    "sg:postcode":"34001",
    "sg:province":"Palencia",
    "wof:name":"La Orquidea C.b.",
    "wof:placetype":"venue"
},
  "geometry": {"coordinates":[-4.5318489075,42.0097045898],"type":"Point"}
}