{
  "type": "Feature",
  "properties": {
    "iso:country":"ES",
    "sg:address":"Calle de Dahellos, 3",
    "sg:city":"Elda",
    "sg:orig_category":"Electrodom\u00c9sticos (al Por Menor)",
    "sg:phone":"+34 965 38 04 29",
    "sg:postcode":"03600",
    "sg:province":"Alicante",
    "wof:name":"Riesma S. A.",
    "wof:placetype":"venue"
},
  "geometry": {"coordinates":[-0.7943912745,38.4772644043],"type":"Point"}
}