{
  "type": "Feature",
  "properties": {
    "iso:country":"ES",
    "sg:address":"Barr Montorra, 1",
    "sg:city":"Amorebieta",
    "sg:orig_category":"Restaurantes",
    "sg:phone":"+34 946 73 36 93",
    "sg:postcode":"48340",
    "sg:province":"Vizcaya",
    "wof:name":"Federico Tundidor Pe\u00f1a Y Roberto Tundidor Pe\u00f1a Cb",
    "wof:placetype":"venue"
},
  "geometry": {"coordinates":[-2.7321588993,43.2210960388],"type":"Point"}
}