{
  "type": "Feature",
  "properties": {
    "iso:country":"ES",
    "sg:address":"Cmno Valencia, 21",
    "sg:city":"Riba-roja Turia",
    "sg:orig_category":"Laboratorios Y Cl\u00cdnicas Veterinarias",
    "sg:phone":"+34 962 77 06 20",
    "sg:postcode":"46190",
    "sg:province":"Valencia",
    "wof:name":"Jorda Alcaraz Inmaculada",
    "wof:placetype":"venue"
},
  "geometry": {"coordinates":[-0.5666975975,39.5453262329],"type":"Point"}
}