{
  "type": "Feature",
  "properties": {
    "addr:full":"Monasterio De La Oliva, 5 Iru\u00f1a Navarra 31011",
    "addr:housenumber":"5",
    "addr:postcode":"31011",
    "addr:street":"Oliva",
    "iso:country":"ES",
    "sg:address":"Monasterio De La Oliva, 5",
    "sg:city":"Iru\u00f1a",
    "sg:orig_category":"Arquitectos",
    "sg:phone":"+34 948 25 50 75",
    "sg:postcode":"31011",
    "sg:province":"Navarra",
    "wof:name":"Sarobe Pueyo Francisco Javier",
    "wof:placetype":"venue"
},
  "geometry": {"coordinates":[-1.6581120491,42.8159255981],"type":"Point"}
}