{
  "type": "Feature",
  "properties": {
    "addr:full":"Pol Ramonet, 7 Almassora Pol. Ind. Castell\u00f3n 12550",
    "addr:housenumber":"7",
    "addr:postcode":"12550",
    "addr:street":"Ramonet;Pol. Ind. Castello\u0301N",
    "iso:country":"ES",
    "sg:address":"Pol Ramonet, 7",
    "sg:city":"Almassora Pol. Ind.",
    "sg:orig_category":"Intercambios, Trueques",
    "sg:phone":"+34 964 52 70 16",
    "sg:postcode":"12550",
    "sg:province":"Castell\u00f3n",
    "wof:name":"Comercial Matiner S.l.",
    "wof:placetype":"venue"
},
  "geometry": {"coordinates":[-0.0631740019,39.9439582825],"type":"Point"}
}