{
  "type": "Feature",
  "properties": {
    "addr:full":"Avda El Ferrol, 37 Madrid Madrid 28029",
    "addr:housenumber":"37",
    "addr:postcode":"madrid;28029",
    "addr:street":"Avda El Ferrol",
    "iso:country":"ES",
    "sg:address":"Avda El Ferrol, 37",
    "sg:city":"Madrid",
    "sg:orig_category":"Asesor\u00cda Sobre Comunicaci\u00d3n De Empresas",
    "sg:phone":"+34 913 15 05 19",
    "sg:postcode":"28029",
    "sg:province":"Madrid",
    "wof:name":"Yrache Esteban Fernando",
    "wof:placetype":"venue"
},
  "geometry": {"coordinates":[-3.7062990665,40.4746017456],"type":"Point"}
}