{
  "type": "Feature",
  "properties": {
    "addr:full":"Calle de Correos, 8 Portugalete Vizcaya 48920",
    "addr:housenumber":"8",
    "addr:postcode":"48920",
    "addr:street":"Calle De Correos",
    "iso:country":"ES",
    "sg:address":"Calle de Correos, 8",
    "sg:city":"Portugalete",
    "sg:orig_category":"Psic\u00d3logos",
    "sg:phone":"+34 944 96 44 38",
    "sg:postcode":"48920",
    "sg:province":"Vizcaya",
    "wof:name":"Lopez Martinez Maria Angeles",
    "wof:placetype":"venue"
},
  "geometry": {"coordinates":[-3.0194160938,43.319732666],"type":"Point"}
}