{
  "type": "Feature",
  "properties": {
    "iso:country":"ES",
    "sg:address":"Calle de Puerto De Navacerrada, 18",
    "sg:city":"Madrid",
    "sg:orig_category":"Agencias De Relaciones P\u00dablicas",
    "sg:phone":"+34 913 28 71 31",
    "sg:postcode":"28038",
    "sg:province":"Madrid",
    "wof:name":"Asthar Comunicacion S.l.",
    "wof:placetype":"venue"
},
  "geometry": {"coordinates":[-3.658449173,40.3988800049],"type":"Point"}
}