{
  "type": "Feature",
  "properties": {
    "iso:country":"ES",
    "sg:address":"Calle de Doctor Casal, 12",
    "sg:city":"Oviedo",
    "sg:orig_category":"Asesor\u00cda Fiscal Y Jur\u00cddica",
    "sg:phone":"+34 985 22 49 60",
    "sg:postcode":"33001",
    "sg:province":"Asturias",
    "wof:name":"Damian Vallina S.l.",
    "wof:placetype":"venue"
},
  "geometry": {"coordinates":[-5.8504605293,43.3651161194],"type":"Point"}
}