{
  "type": "Feature",
  "properties": {
    "iso:country":"ES",
    "sg:address":"Calle de Cervantes, 13",
    "sg:city":"Ayamonte",
    "sg:orig_category":"Telas Y Sedas (al Por Menor)",
    "sg:phone":"+34 959 32 04 22",
    "sg:postcode":"21400",
    "sg:province":"Huelva",
    "wof:name":"Gonzalez Menendez Manuel",
    "wof:placetype":"venue"
},
  "geometry": {"coordinates":[-7.4083738327,37.2129592896],"type":"Point"}
}