{
  "type": "Feature",
  "properties": {
    "addr:full":"Calle de Neptuno, 5 Ejido Almer\u00eda 04700",
    "addr:housenumber":"5",
    "addr:postcode":"04700",
    "addr:street":"Calle De Neptuno;Almeri\u0301A",
    "iso:country":"ES",
    "sg:address":"Calle de Neptuno, 5",
    "sg:city":"Ejido",
    "sg:classifiers":[
        {
            "category":"Autos & Motor Vehicles",
            "subcategory":"Automobile Sales",
            "type":"Retail Goods"
        }
    ],
    "sg:phone":"+34 950 48 08 15",
    "sg:postcode":"04700",
    "sg:province":"Almer\u00eda",
    "wof:name":"Martin Jimenez Juan Jose",
    "wof:placetype":"venue"
},
  "geometry": {"coordinates":[-2.8107988834,36.7732543945],"type":"Point"}
}