{
  "type": "Feature",
  "properties": {
    "iso:country":"ES",
    "sg:address":"Carrer de Lleialtat, 52",
    "sg:city":"Esplugues Llobregat",
    "sg:orig_category":"Inform\u00c1tica: Mantenimiento Y Reparaci\u00d3n De Ordenadores",
    "sg:phone":"+34 933 71 94 11",
    "sg:postcode":"08950",
    "sg:province":"Barcelona",
    "sg:website":"www.afianza.net",
    "wof:name":"Afianza Telecomunicaciones S.l.",
    "wof:placetype":"venue"
},
  "geometry": {"coordinates":[2.0929794312,41.3734893799],"type":"Point"}
}