{
  "type": "Feature",
  "properties": {
    "iso:country":"ES",
    "sg:address":"Carrer de Guardia, 6",
    "sg:city":"Barcelona",
    "sg:orig_category":"Oficinas De Cambio",
    "sg:phone":"+34 933 42 82 56",
    "sg:postcode":"08001",
    "sg:province":"Barcelona",
    "wof:name":"Shah Barna Integra S.l.",
    "wof:placetype":"venue"
},
  "geometry": {"coordinates":[2.173625946,41.3778572083],"type":"Point"}
}