{
  "type": "Feature",
  "properties": {
    "iso:country":"ES",
    "sg:address":"Calle de Boveda, 4",
    "sg:city":"Tudela",
    "sg:orig_category":"Publicidad (soportes Y Gesti\u00d3n)",
    "sg:phone":"+34 948 82 37 63",
    "sg:postcode":"31500",
    "sg:province":"Navarra",
    "wof:name":"Rodriguez De Guzman Deba Raul",
    "wof:placetype":"venue"
},
  "geometry": {"coordinates":[-1.6076686382,42.0631103516],"type":"Point"}
}