{
  "type": "Feature",
  "properties": {
    "iso:country":"ES",
    "sg:address":"Carrer de Miquel Romeu, 110",
    "sg:city":"Hospitalet Llobregat",
    "sg:orig_category":"Pintura, Barniz, Productos Asimilables (fabricaci\u00d3n, Al Por Mayor)",
    "sg:phone":"+34 933 37 06 43",
    "sg:postcode":"08907",
    "sg:province":"Barcelona",
    "wof:name":"Mongay S. A.",
    "wof:placetype":"venue"
},
  "geometry": {"coordinates":[2.1125590801,41.3590545654],"type":"Point"}
}