{
  "type": "Feature",
  "properties": {
    "addr:full":"Avda Teatinos (los), 60 Sevilla Sevilla 41013",
    "addr:housenumber":"60",
    "addr:postcode":"41013",
    "addr:street":"Avda Teatinos Los",
    "iso:country":"ES",
    "sg:address":"Avda Teatinos (los), 60",
    "sg:city":"Sevilla",
    "sg:orig_category":"Comercio, Reparaci\u00d3n De Motocicletas, Bicicletas Y Piezas Sueltas",
    "sg:phone":"+34 954 62 88 88",
    "sg:postcode":"41013",
    "sg:province":"Sevilla",
    "wof:name":"Lucenilla De La Rosa Jose",
    "wof:placetype":"venue"
},
  "geometry": {"coordinates":[-5.9765610695,37.3685340881],"type":"Point"}
}