{
  "type": "Feature",
  "properties": {
    "addr:full":"Carrer de Angels, 1 Benidorm Alicante 03500",
    "addr:housenumber":"1",
    "addr:postcode":"03500",
    "addr:street":"Carrer De Angels",
    "iso:country":"ES",
    "sg:address":"Carrer de Angels, 1",
    "sg:city":"Benidorm",
    "sg:orig_category":"Procuradores",
    "sg:phone":"+34 965 85 28 10",
    "sg:postcode":"03500",
    "sg:province":"Alicante",
    "wof:name":"Lloret Mayor Francisco",
    "wof:placetype":"venue"
},
  "geometry": {"coordinates":[-0.1296550035,38.5359992981],"type":"Point"}
}