{
  "type": "Feature",
  "properties": {
    "iso:country":"ES",
    "sg:address":"Calle de Hormigoneras, 7",
    "sg:city":"Alcorcon",
    "sg:orig_category":"Comercio De Hierro",
    "sg:phone":"+34 916 41 23 12",
    "sg:postcode":"28925",
    "sg:province":"Madrid",
    "wof:name":"Suministros Alvarez S.a.",
    "wof:placetype":"venue"
},
  "geometry": {"coordinates":[-3.8040595055,40.3435401917],"type":"Point"}
}