{
  "type": "Feature",
  "properties": {
    "iso:country":"ES",
    "sg:address":"Carr Germana Assumpta, 8",
    "sg:city":"Arbucies",
    "sg:orig_category":"Venta, Instalaci\u00d3n De Calefacci\u00d3n",
    "sg:phone":"+34 972 86 07 02",
    "sg:postcode":"17401",
    "sg:province":"Girona",
    "wof:name":"Vela Torres Juan",
    "wof:placetype":"venue"
},
  "geometry": {"coordinates":[2.5163021088,41.8148384094],"type":"Point"}
}