{
  "type": "Feature",
  "properties": {
    "addr:full":"Calle de Principe De Vergara, 266 Madrid Madrid 28016",
    "addr:housenumber":"266",
    "addr:postcode":"28016",
    "addr:street":"Calle De Principe De Vergara",
    "iso:country":"ES",
    "sg:address":"Calle de Principe De Vergara, 266",
    "sg:city":"Madrid",
    "sg:orig_category":"Asesor\u00cda Fiscal Y Jur\u00cddica",
    "sg:phone":"+34 914 57 04 45",
    "sg:postcode":"28016",
    "sg:province":"Madrid",
    "wof:name":"Amat Torres Juan M.",
    "wof:placetype":"venue"
},
  "geometry": {"coordinates":[-3.6768257618,40.4577484131],"type":"Point"}
}