{
  "type": "Feature",
  "properties": {
    "iso:country":"ES",
    "sg:address":"Calle de La Porta, 12",
    "sg:city":"Cumbres Mayores",
    "sg:orig_category":"Notarios",
    "sg:phone":"+34 959 71 06 24",
    "sg:postcode":"21380",
    "sg:province":"Huelva",
    "wof:name":"Tirado Dominguez Macarena",
    "wof:placetype":"venue"
},
  "geometry": {"coordinates":[-6.6443052292,38.0619544983],"type":"Point"}
}