{
  "type": "Feature",
  "properties": {
    "iso:country":"ES",
    "sg:address":"Loiolako Inazio Hiribidea, 27",
    "sg:city":"Azpeitia",
    "sg:orig_category":"Promotores Constructores",
    "sg:phone":"+34 943 81 16 22",
    "sg:postcode":"20730",
    "sg:province":"Guip\u00f9zcoa",
    "wof:name":"Construcciones Izarraitzpe S.l.",
    "wof:placetype":"venue"
},
  "geometry": {"coordinates":[-2.2697920799,43.1801986694],"type":"Point"}
}