{
  "type": "Feature",
  "properties": {
    "iso:country":"ES",
    "sg:address":"Avda Palomeras, 21",
    "sg:city":"Madrid",
    "sg:orig_category":"Molduras, Junquillos, Listones Y Molduras Perforadas",
    "sg:phone":"+34 913 03 55 13",
    "sg:postcode":"28018",
    "sg:province":"Madrid",
    "wof:name":"Sanchez Cabrero Jose Luis",
    "wof:placetype":"venue"
},
  "geometry": {"coordinates":[-3.6587669849,40.3890991211],"type":"Point"}
}