{
  "type": "Feature",
  "properties": {
    "addr:full":"Calle de Ca\u00d1o, 43 Santiba\u00e7ez De Bejar Salamanca 37740",
    "addr:housenumber":"43",
    "addr:postcode":"37740",
    "addr:street":"Calle De Can\u0303O",
    "iso:country":"ES",
    "sg:address":"Calle de Ca\u00d1o, 43",
    "sg:city":"Santiba\u00e7ez De Bejar",
    "sg:orig_category":"Venta Al Preg\u00d3n",
    "sg:phone":"+34 923 59 43 09",
    "sg:postcode":"37740",
    "sg:province":"Salamanca",
    "wof:name":"Dominguez Sanchez Jaime",
    "wof:placetype":"venue"
},
  "geometry": {"coordinates":[-5.6103391647,40.4861412048],"type":"Point"}
}