{
  "type": "Feature",
  "properties": {
    "iso:country":"ES",
    "sg:address":"Calle de Jose Maria Fernandez, 5",
    "sg:city":"Jodar",
    "sg:orig_category":"Molduras, Junquillos, Listones Y Molduras Perforadas",
    "sg:phone":"+34 953 78 55 19",
    "sg:postcode":"23500",
    "sg:province":"Ja\u00e9n",
    "wof:name":"Navarrete Morales Antonio",
    "wof:placetype":"venue"
},
  "geometry": {"coordinates":[-3.3529279232,37.8391571045],"type":"Point"}
}