{
  "type": "Feature",
  "properties": {
    "iso:country":"ES",
    "sg:address":"Calle de Kresaltzu, 9",
    "sg:city":"Arenas -areeta",
    "sg:orig_category":"Complementos De Vestir (al Por Menor)",
    "sg:phone":"+34 944 63 20 15",
    "sg:postcode":"48930",
    "sg:province":"Vizcaya",
    "wof:name":"Careaga Gajardo Ana Maria",
    "wof:placetype":"venue"
},
  "geometry": {"coordinates":[-3.0081419945,43.3280677795],"type":"Point"}
}