{
  "type": "Feature",
  "properties": {
    "addr:full":"Rua Emilia Pardo Bazan, 13 Celanova Ourense 32800",
    "addr:housenumber":"13",
    "addr:postcode":"32800",
    "addr:street":"Rua Emilia Pardo Bazan",
    "iso:country":"ES",
    "sg:address":"Rua Emilia Pardo Bazan, 13",
    "sg:city":"Celanova",
    "sg:orig_category":"Abogados",
    "sg:phone":"+34 988 43 22 25",
    "sg:postcode":"32800",
    "sg:province":"Ourense",
    "wof:name":"Puga Rodriguez Antonio",
    "wof:placetype":"venue"
},
  "geometry": {"coordinates":[-7.9576539993,42.1530227661],"type":"Point"}
}