{
  "type": "Feature",
  "properties": {
    "iso:country":"ES",
    "sg:address":"Calle de Llana, 2",
    "sg:city":"Nueva-carteya",
    "sg:orig_category":"Bancos",
    "sg:phone":"+34 957 67 81 41",
    "sg:postcode":"14857",
    "sg:province":"C\u00f3rdoba",
    "sg:website":"www.banesto.es",
    "wof:name":"Banco Espa\u00d1ol De Credito S.a.",
    "wof:placetype":"venue"
},
  "geometry": {"coordinates":[-4.4690480232,37.5859527588],"type":"Point"}
}