{
  "type": "Feature",
  "properties": {
    "addr:full":"Plaz Quintero Baez, 6 Huelva Huelva 21003",
    "addr:housenumber":"6",
    "addr:postcode":"21003",
    "addr:street":"Baez",
    "iso:country":"ES",
    "sg:address":"Plaz Quintero Baez, 6",
    "sg:city":"Huelva",
    "sg:orig_category":"Desinfecci\u00d3n, Desinsectaci\u00d3n, Desratizaci\u00d3n",
    "sg:phone":"+34 959 28 35 51",
    "sg:postcode":"21003",
    "sg:province":"Huelva",
    "wof:name":"Rodriguez Romero Margarita",
    "wof:placetype":"venue"
},
  "geometry": {"coordinates":[-6.9503211975,37.2586669922],"type":"Point"}
}