{
  "type": "Feature",
  "properties": {
    "addr:full":"Calle de Alfonso Xii, 5 Osuna Sevilla 41640",
    "addr:housenumber":"5",
    "addr:postcode":"41640",
    "addr:street":"Calle De Alfonso Xii",
    "iso:country":"ES",
    "sg:address":"Calle de Alfonso Xii, 5",
    "sg:city":"Osuna",
    "sg:orig_category":"Muebles, Minoristas",
    "sg:phone":"+34 954 81 23 22",
    "sg:postcode":"41640",
    "sg:province":"Sevilla",
    "wof:name":"Confraper S.l.",
    "wof:placetype":"venue"
},
  "geometry": {"coordinates":[-5.1075520515,37.2415390015],"type":"Point"}
}