{
  "type": "Feature",
  "properties": {
    "iso:country":"ES",
    "sg:address":"Calle de Pablo Casals, 11",
    "sg:city":"Marbella",
    "sg:orig_category":"Ropa Para Ni\u00d1os (al Por Menor)",
    "sg:phone":"+34 952 82 97 01",
    "sg:postcode":"29600",
    "sg:province":"M\u00e1laga",
    "wof:name":"Gibrand  Staffan",
    "wof:placetype":"venue"
},
  "geometry": {"coordinates":[-4.8949999809,36.5089035034],"type":"Point"}
}