{
  "type": "Feature",
  "properties": {
    "iso:country":"ES",
    "sg:address":"Calle de Emilio Ferrari, 60",
    "sg:city":"Madrid",
    "sg:orig_category":"Colchones (fabricaci\u00d3n, Al Por Mayor, Al Por Menor)",
    "sg:phone":"+34 913 68 16 52",
    "sg:postcode":"28017",
    "sg:province":"Madrid",
    "wof:name":"Lude\u00f1a Lopez Santos Pedro",
    "wof:placetype":"venue"
},
  "geometry": {"coordinates":[-3.6411380768,40.4309501648],"type":"Point"}
}