{
  "type": "Feature",
  "properties": {
    "iso:country":"ES",
    "sg:address":"Calle de Fueros (los)/foruen Kalea, 2",
    "sg:city":"Amurrio",
    "sg:orig_category":"Asesor\u00cda Sobre Comunicaci\u00d3n De Empresas",
    "sg:phone":"+34 945 39 33 51",
    "sg:postcode":"01470",
    "sg:province":"\u00c1lava",
    "sg:website":"www.elkarlan.com",
    "wof:name":"Elkarlan U&p Asesores C.b.",
    "wof:placetype":"venue"
},
  "geometry": {"coordinates":[-3.0217339993,43.0432891846],"type":"Point"}
}