{
  "type": "Feature",
  "properties": {
    "iso:country":"ES",
    "sg:address":"Rua Lopez Mora, 24",
    "sg:city":"Vigo",
    "sg:orig_category":"Empresarios Y Productoras De Espect\u00c1culos",
    "sg:phone":"+34 986 29 91 48",
    "sg:postcode":"36211",
    "sg:province":"Pontevedra",
    "wof:name":"Feijoo Bidueira Ana Belen",
    "wof:placetype":"venue"
},
  "geometry": {"coordinates":[-8.7305517197,42.2256355286],"type":"Point"}
}