{
  "type": "Feature",
  "properties": {
    "addr:full":"Calle de Ogo\u00d1o, 4 Arenas -areeta Vizcaya 48930",
    "addr:housenumber":"4;areeta",
    "addr:postcode":"48930",
    "addr:street":"Calle De Ogon\u0303O",
    "iso:country":"ES",
    "sg:address":"Calle de Ogo\u00d1o, 4",
    "sg:city":"Arenas -areeta",
    "sg:orig_category":"Ropa Para Ni\u00d1os (al Por Menor)",
    "sg:phone":"+34 944 63 19 37",
    "sg:postcode":"48930",
    "sg:province":"Vizcaya",
    "wof:name":"Rodriguez De La Viuda Blanca",
    "wof:placetype":"venue"
},
  "geometry": {"coordinates":[-3.0068490505,43.3258285522],"type":"Point"}
}