{
  "type": "Feature",
  "properties": {
    "iso:country":"ES",
    "sg:address":"Calle de Bernardino Beotas (de), 24",
    "sg:city":"Navalcarnero",
    "sg:orig_category":"Partidos Pol\u00cdticos",
    "sg:phone":"+34 918 11 22 38",
    "sg:postcode":"28600",
    "sg:province":"Madrid",
    "wof:name":"Grupo Municipal Socialista De Navalcarnero",
    "wof:placetype":"venue"
},
  "geometry": {"coordinates":[-4.0152864456,40.2900009155],"type":"Point"}
}