{
  "type": "Feature",
  "properties": {
    "addr:full":"Calle de Velayos, 2 Madrid Madrid 28035",
    "addr:housenumber":"2",
    "addr:postcode":"28035",
    "addr:street":"Calle De Velayos",
    "iso:country":"ES",
    "sg:address":"Calle de Velayos, 2",
    "sg:city":"Madrid",
    "sg:orig_category":"Tintes (fabricaci\u00d3n, Al Por Mayor)",
    "sg:phone":"+34 913 16 92 20",
    "sg:postcode":"28035",
    "sg:province":"Madrid",
    "wof:name":"Morla Mu\u00f1iz Emigdio",
    "wof:placetype":"venue"
},
  "geometry": {"coordinates":[-3.7257640362,40.4649963379],"type":"Point"}
}