{
  "type": "Feature",
  "properties": {
    "addr:full":"Avda Este, S/n Casas De Cementerio De Nuestro Padre Jesus Murcia 30100",
    "addr:housenumber":"s",
    "addr:postcode":"30100",
    "addr:street":"Avda Este;/ N Casas De Cementerio",
    "iso:country":"ES",
    "sg:address":"Avda Este, S/n",
    "sg:city":"Casas De Cementerio De Nuestro Padre Jesus",
    "sg:orig_category":"Fabricaci\u00d3n De Jabones, Detergentes Y Lej\u00cdas",
    "sg:phone":"+34 968 83 13 16",
    "sg:postcode":"30100",
    "sg:province":"Murcia",
    "wof:name":"Industrias Gamer S.l.",
    "wof:placetype":"venue"
},
  "geometry": {"coordinates":[-1.1694890261,38.0283966064],"type":"Point"}
}