{
  "type": "Feature",
  "properties": {
    "iso:country":"ES",
    "sg:address":"Avda Encartaciones, 28",
    "sg:city":"Balmaseda",
    "sg:orig_category":"Mec\u00c1nico Del Autom\u00d3vil",
    "sg:phone":"+34 946 80 05 60",
    "sg:postcode":"48800",
    "sg:province":"Vizcaya",
    "wof:name":"Ruiz Ulanga Carmelo",
    "wof:placetype":"venue"
},
  "geometry": {"coordinates":[-3.2010130882,43.1898498535],"type":"Point"}
}