{
  "type": "Feature",
  "properties": {
    "addr:full":"Barr Orconera, S/n Orconera Vizcaya 48530",
    "addr:postcode":"48530",
    "addr:street":"Orconera S / N",
    "iso:country":"ES",
    "sg:address":"Barr Orconera, S/n",
    "sg:city":"Orconera",
    "sg:orig_category":"Empresas De Demolici\u00d3n",
    "sg:phone":"+34 946 64 04 23",
    "sg:postcode":"48530",
    "sg:province":"Vizcaya",
    "wof:name":"B.t.b. S.a.",
    "wof:placetype":"venue"
},
  "geometry": {"coordinates":[-3.0566248894,43.3107376099],"type":"Point"}
}