{
  "type": "Feature",
  "properties": {
    "iso:country":"ES",
    "sg:address":"Carrer de Raurich, 2",
    "sg:city":"S. Boi Llobregat",
    "sg:orig_category":"Frutas, Legumbres Frescas Y Tempranas (al Por Menor)",
    "sg:phone":"+34 936 54 49 17",
    "sg:postcode":"08830",
    "sg:province":"Barcelona",
    "wof:name":"Trejo Lopez Manuel",
    "wof:placetype":"venue"
},
  "geometry": {"coordinates":[2.0348200798,41.3460998535],"type":"Point"}
}