{
  "type": "Feature",
  "properties": {
    "iso:country":"ES",
    "sg:address":"Calle de Sebastian Elcano, 14",
    "sg:city":"Sevilla",
    "sg:orig_category":"Abogados",
    "sg:phone":"+34 954 45 00 38",
    "sg:postcode":"41011",
    "sg:province":"Sevilla",
    "wof:name":"Aguilar Saenz Salud",
    "wof:placetype":"venue"
},
  "geometry": {"coordinates":[-5.9959130287,37.3773231506],"type":"Point"}
}