{
  "type": "Feature",
  "properties": {
    "iso:country":"ES",
    "sg:address":"Cra Estacion, 15",
    "sg:city":"Vicien",
    "sg:orig_category":"Agricultores, Agricultores",
    "sg:phone":"+34 974 28 31 73",
    "sg:postcode":"22190",
    "sg:province":"Huesca",
    "wof:name":"Sociedad Agraria De Transformacion",
    "wof:placetype":"venue"
},
  "geometry": {"coordinates":[-0.4398609996,42.0551071167],"type":"Point"}
}