{
  "type": "Feature",
  "properties": {
    "addr:full":"Calle de Rua Del Sol, 12 Ciudad Rodrigo Salamanca 37500",
    "addr:housenumber":"12",
    "addr:postcode":"37500",
    "addr:street":"Calle De Rua Del Sol",
    "iso:country":"ES",
    "sg:address":"Calle de Rua Del Sol, 12",
    "sg:city":"Ciudad Rodrigo",
    "sg:orig_category":"Peluquer\u00cdas, Peluquer\u00cda Mixta",
    "sg:phone":"+34 923 48 00 58",
    "sg:postcode":"37500",
    "sg:province":"Salamanca",
    "wof:name":"Vicente Casta\u00f1o Maria",
    "wof:placetype":"venue"
},
  "geometry": {"coordinates":[-6.5328979492,40.5976028442],"type":"Point"}
}