{
  "type": "Feature",
  "properties": {
    "addr:full":"Calle de Cristo De La Epidemia, 60 Malaga M\u00e1laga 29013",
    "addr:housenumber":"60",
    "addr:postcode":"29013",
    "addr:street":"Calle De Cristo De La Epidemia;Ma\u0301Laga",
    "iso:country":"ES",
    "sg:address":"Calle de Cristo De La Epidemia, 60",
    "sg:city":"Malaga",
    "sg:orig_category":"Quincaller\u00cda (fabricaci\u00d3n)",
    "sg:phone":"+34 952 25 10 17",
    "sg:postcode":"29013",
    "sg:province":"M\u00e1laga",
    "wof:name":"Cuevas Galvan Francisco Javier",
    "wof:placetype":"venue"
},
  "geometry": {"coordinates":[-4.4148540497,36.7303733826],"type":"Point"}
}