{
  "type": "Feature",
  "properties": {
    "iso:country":"ES",
    "sg:address":"Calle de Doctor Eduardo Garcia-trivi\u00d1o Lopez, 1",
    "sg:city":"Jaen",
    "sg:orig_category":"Loter\u00cda Y T\u00d3mbola",
    "sg:phone":"+34 953 22 23 15",
    "sg:postcode":"23007",
    "sg:province":"Ja\u00e9n",
    "wof:name":"Cazorla Garcia Francisco Javier",
    "wof:placetype":"venue"
},
  "geometry": {"coordinates":[-3.7947719097,37.7759819031],"type":"Point"}
}