{
  "type": "Feature",
  "properties": {
    "addr:full":"Carr Major, 12 Torrebesses Lleida 25176",
    "addr:housenumber":"12",
    "addr:postcode":"25176",
    "addr:street":"Carr Major",
    "iso:country":"ES",
    "sg:address":"Carr Major, 12",
    "sg:city":"Torrebesses",
    "sg:orig_category":"Farmacias",
    "sg:phone":"+34 973 12 61 01",
    "sg:postcode":"25176",
    "sg:province":"Lleida",
    "wof:name":"Herrero Pedruelo Ignacio",
    "wof:placetype":"venue"
},
  "geometry": {"coordinates":[0.5935930014,41.4262046814],"type":"Point"}
}