{
  "type": "Feature",
  "properties": {
    "addr:full":"Avda Ronda Intermedia, 6 Antequera M\u00e1laga 29200",
    "addr:housenumber":"6",
    "addr:postcode":"29200",
    "addr:street":"Avda Ronda Intermedia",
    "iso:country":"ES",
    "sg:address":"Avda Ronda Intermedia, 6",
    "sg:city":"Antequera",
    "sg:orig_category":"Cajas De Ahorro",
    "sg:phone":"+34 952 70 48 47",
    "sg:postcode":"29200",
    "sg:province":"M\u00e1laga",
    "wof:name":"Caixa D'estalvis I Pensions De Barcelona",
    "wof:placetype":"venue"
},
  "geometry": {"coordinates":[-4.5636138916,37.0203018188],"type":"Point"}
}