{
  "type": "Feature",
  "properties": {
    "addr:full":"Rua Rubalcava, 13 Ferrol La Coru\u00f1a 15402",
    "addr:housenumber":"13",
    "addr:postcode":"15402",
    "addr:street":"Rua Rubalcava;La Corun\u0303A",
    "iso:country":"ES",
    "sg:address":"Rua Rubalcava, 13",
    "sg:city":"Ferrol",
    "sg:orig_category":"Agencias De Trabajo Temporal",
    "sg:phone":"+34 981 35 18 55",
    "sg:postcode":"15402",
    "sg:province":"La Coru\u00f1a",
    "wof:name":"Manpower Team Empresas De Trabajo Temporal",
    "wof:placetype":"venue"
},
  "geometry": {"coordinates":[-8.2320699692,43.4842453003],"type":"Point"}
}