{
  "type": "Feature",
  "properties": {
    "addr:full":"Avda Andalucia, 16 Arjonilla Ja\u00e9n 23750",
    "addr:housenumber":"16",
    "addr:postcode":"23750",
    "addr:street":"Avda Andalucia",
    "iso:country":"ES",
    "sg:address":"Avda Andalucia, 16",
    "sg:city":"Arjonilla",
    "sg:orig_category":"Cajas Para Embalar",
    "sg:phone":"+34 953 52 00 89",
    "sg:postcode":"23750",
    "sg:province":"Ja\u00e9n",
    "wof:name":"Caja Rural De Jaen",
    "wof:placetype":"venue"
},
  "geometry": {"coordinates":[-4.1056828499,37.9735488892],"type":"Point"}
}