{
  "type": "Feature",
  "properties": {
    "addr:full":"Carrer de Abat Oliba, 26 Malgrat Mar Barcelona 08380",
    "addr:housenumber":"26",
    "addr:postcode":"08380",
    "addr:street":"Carrer De Abat Oliba",
    "iso:country":"ES",
    "sg:address":"Carrer de Abat Oliba, 26",
    "sg:city":"Malgrat Mar",
    "sg:orig_category":"Porcelana Decorativa",
    "sg:phone":"+34 937 61 91 24",
    "sg:postcode":"08380",
    "sg:province":"Barcelona",
    "sg:website":"www.larosaitaliana.com",
    "wof:name":"La Rosa Italiana S.l.",
    "wof:placetype":"venue"
},
  "geometry": {"coordinates":[2.7460811138,41.6458702087],"type":"Point"}
}