{
  "type": "Feature",
  "properties": {
    "iso:country":"ES",
    "sg:address":"Calle de San Bartolome, 17",
    "sg:city":"Torredelcampo",
    "sg:orig_category":"Empresas De Carpinter\u00cda Met\u00c1lica",
    "sg:phone":"+34 953 41 02 30",
    "sg:postcode":"23640",
    "sg:province":"Ja\u00e9n",
    "wof:name":"Parras Moral Cristobal",
    "wof:placetype":"venue"
},
  "geometry": {"coordinates":[-3.8876171112,37.777431488],"type":"Point"}
}