{
  "type": "Feature",
  "properties": {
    "addr:full":"Calle de Jose Maria Mortes Lerma, 17 Valencia Valencia 46014",
    "addr:housenumber":"17",
    "addr:postcode":"46014",
    "addr:street":"Calle De Jose Maria Mortes Lerma",
    "iso:country":"ES",
    "sg:address":"Calle de Jose Maria Mortes Lerma, 17",
    "sg:city":"Valencia",
    "sg:orig_category":"Mercer\u00cda, Lencer\u00cda (al Por Menor)",
    "sg:phone":"+34 963 57 61 69",
    "sg:postcode":"46014",
    "sg:province":"Valencia",
    "wof:name":"Cortes Aguilar Trinidad",
    "wof:placetype":"venue"
},
  "geometry": {"coordinates":[-0.400135994,39.4628753662],"type":"Point"}
}