{
  "type": "Feature",
  "properties": {
    "iso:country":"ES",
    "sg:address":"Rond Industria, 22",
    "sg:city":"Barbera Valles",
    "sg:orig_category":"Ingenier\u00cda, Centros De Estudios (diversos)",
    "sg:phone":"+34 937 29 27 66",
    "sg:postcode":"08210",
    "sg:province":"Barcelona",
    "wof:name":"Enginyeria Teknics Sabadell S.l.",
    "wof:placetype":"venue"
},
  "geometry": {"coordinates":[2.1271760464,41.5150566101],"type":"Point"}
}