{
  "type": "Feature",
  "properties": {
    "iso:country":"ES",
    "sg:address":"Calle de Fortuny, 9",
    "sg:city":"Madrid",
    "sg:orig_category":"Peritos Mar\u00cdtimos",
    "sg:phone":"+34 913 08 62 10",
    "sg:postcode":"28010",
    "sg:province":"Madrid",
    "sg:website":"www.perezycia.com",
    "wof:name":"A. Perez Y Cia S.l.",
    "wof:placetype":"venue"
},
  "geometry": {"coordinates":[-3.6910734177,40.4289627075],"type":"Point"}
}