{
  "type": "Feature",
  "properties": {
    "iso:country":"ES",
    "sg:address":"Avda Estacion (de La), 36",
    "sg:city":"Almeria",
    "sg:orig_category":"Panader\u00cdas, Panader\u00cdas",
    "sg:phone":"+34 950 27 42 37",
    "sg:postcode":"04005",
    "sg:province":"Almer\u00eda",
    "wof:name":"Mensales Sanchez Manuel",
    "wof:placetype":"venue"
},
  "geometry": {"coordinates":[-2.4569504261,36.8367233276],"type":"Point"}
}