{
  "type": "Feature",
  "properties": {
    "addr:full":"Ctra. De Madrid Barcelona, S/n Almunia D. Godina Zaragoza 50100",
    "addr:housenumber":"/ n",
    "addr:postcode":"50100",
    "addr:street":"Ctra. De Madrid Barcelona S;Almunia D. Godina",
    "iso:country":"ES",
    "sg:address":"Ctra. De Madrid Barcelona, S/n",
    "sg:city":"Almunia D. Godina",
    "sg:orig_category":"Alquiler De Casas Y Habitaciones Amuebladas",
    "sg:phone":"+34 976 60 01 50",
    "sg:postcode":"50100",
    "sg:province":"Zaragoza",
    "wof:name":"Casa Salesiana Don Bosco Residencia Don Bosco De La Almunia De D Godina Salesianos",
    "wof:placetype":"venue"
},
  "geometry": {"coordinates":[-1.3779189587,41.4772033691],"type":"Point"}
}