{
  "type": "Feature",
  "properties": {
    "addr:full":"C/ Porta D'alacant, 6 Elche Alicante 03202",
    "addr:housenumber":"6",
    "addr:postcode":"03202",
    "addr:street":"C / Porta D'Alacant",
    "iso:country":"ES",
    "sg:address":"C/ Porta D'alacant, 6",
    "sg:city":"Elche",
    "sg:orig_category":"Fotocopias, Reprograf\u00cda",
    "sg:phone":"+34 966 61 10 43",
    "sg:postcode":"03202",
    "sg:province":"Alicante",
    "wof:name":"Ferrandez Almela Jose Esteban",
    "wof:placetype":"venue"
},
  "geometry": {"coordinates":[-0.6949149966,38.2675018311],"type":"Point"}
}