{
  "type": "Feature",
  "properties": {
    "iso:country":"ES",
    "sg:address":"Carrer de Josep Bastus I Planes, 15",
    "sg:city":"S. Joan Despi",
    "sg:orig_category":"Asociaciones Ecologistas",
    "sg:phone":"+34 933 73 06 51",
    "sg:postcode":"08970",
    "sg:province":"Barcelona",
    "sg:website":"www.plastoquimica.com",
    "wof:name":"Plastoquimica S. L.",
    "wof:placetype":"venue"
},
  "geometry": {"coordinates":[2.0638389587,41.3729095459],"type":"Point"}
}