{
  "type": "Feature",
  "properties": {
    "iso:country":"ES",
    "sg:address":"Av Marques De Comillas, S/n",
    "sg:city":"Barcelona",
    "sg:orig_category":"Artesan\u00cda Y Trabajos Manuales: Suministros (al Por Menor)",
    "sg:phone":"+34 933 25 04 71",
    "sg:postcode":"08038",
    "sg:province":"Barcelona",
    "wof:name":"Rodo Montamat Montserrat",
    "wof:placetype":"venue"
},
  "geometry": {"coordinates":[2.1455280781,41.368888855],"type":"Point"}
}