{
  "type": "Feature",
  "properties": {
    "addr:full":"Rua Vilar (do), 28 Santiago De Compostela La Coru\u00f1a 15705",
    "addr:housenumber":"28",
    "addr:postcode":"15705",
    "addr:street":"Rua Vilar Do;Corun\u0303A",
    "iso:country":"ES",
    "sg:address":"Rua Vilar (do), 28",
    "sg:city":"Santiago De Compostela",
    "sg:orig_category":"Artesan\u00cda Y Trabajos Manuales: Suministros (al Por Menor)",
    "sg:phone":"+34 981 58 40 51",
    "sg:postcode":"15705",
    "sg:province":"La Coru\u00f1a",
    "wof:name":"Crisol Artesan S.c.",
    "wof:placetype":"venue"
},
  "geometry": {"coordinates":[-8.5446033478,42.8790473938],"type":"Point"}
}