{
  "type": "Feature",
  "properties": {
    "iso:country":"ES",
    "sg:address":"Calle de Muralla La, 5",
    "sg:city":"Gijon",
    "sg:orig_category":"Ropa Para Ni\u00d1os (al Por Menor)",
    "sg:phone":"+34 985 34 86 92",
    "sg:postcode":"33202",
    "sg:province":"Asturias",
    "wof:name":"Shop 1999 S.l.",
    "wof:placetype":"venue"
},
  "geometry": {"coordinates":[-5.6592359543,43.5410919189],"type":"Point"}
}