{
  "type": "Feature",
  "properties": {
    "addr:full":"Trva Teatinos, 1 Soria Soria 42002",
    "addr:housenumber":"1",
    "addr:postcode":"42002",
    "addr:street":"Trva Teatinos",
    "iso:country":"ES",
    "sg:address":"Trva Teatinos, 1",
    "sg:city":"Soria",
    "sg:orig_category":"Art\u00cdculos De Regalo (al Por Menor)",
    "sg:phone":"+34 975 22 71 15",
    "sg:postcode":"42002",
    "sg:province":"Soria",
    "wof:name":"Mu\u00f1oz Delgado Amelia",
    "wof:placetype":"venue"
},
  "geometry": {"coordinates":[-2.4657831192,41.7645759583],"type":"Point"}
}