{
  "type": "Feature",
  "properties": {
    "iso:country":"ES",
    "sg:address":"Calle de Cardenal Cisneros, 60",
    "sg:city":"Coru\u00d1a",
    "sg:orig_category":"Asociaciones, Organismos Culturales Y Socioeducativos",
    "sg:phone":"+34 981 23 91 08",
    "sg:postcode":"15007",
    "sg:province":"La Coru\u00f1a",
    "wof:name":"Asociacion De Pasivos De Telefonica",
    "wof:placetype":"venue"
},
  "geometry": {"coordinates":[-8.4161520004,43.3585624695],"type":"Point"}
}