{
  "type": "Feature",
  "properties": {
    "addr:full":"Carr Alfons Carles I (d'), 2 Lliria Valencia 46160",
    "addr:housenumber":"2",
    "addr:postcode":"46160",
    "addr:street":"Carr Alfons Carles I D '",
    "iso:country":"ES",
    "sg:address":"Carr Alfons Carles I (d'), 2",
    "sg:city":"Lliria",
    "sg:orig_category":"Promotores Constructores",
    "sg:phone":"+34 962 78 23 25",
    "sg:postcode":"46160",
    "sg:province":"Valencia",
    "wof:name":"Ma\u00f1ez Y Monta\u00f1es S. L.",
    "wof:placetype":"venue"
},
  "geometry": {"coordinates":[-0.5932620168,39.6314201355],"type":"Point"}
}