{
  "type": "Feature",
  "properties": {
    "iso:country":"ES",
    "sg:address":"Poli Poligon Industrial, S/n",
    "sg:city":"Picassent",
    "sg:orig_category":"Artes Gr\u00c1ficas, Artes Pl\u00c1sticas (curso)",
    "sg:phone":"+34 961 23 01 53",
    "sg:postcode":"46220",
    "sg:province":"Valencia",
    "wof:name":"Exclusivas Graficas S.l.",
    "wof:placetype":"venue"
},
  "geometry": {"coordinates":[-0.4524689913,39.3585700989],"type":"Point"}
}