{
  "type": "Feature",
  "properties": {
    "addr:full":"Calle de Canonigo, 64 Dos Hermanas Sevilla 41700",
    "addr:housenumber":"64",
    "addr:postcode":"41700",
    "addr:street":"Calle De Canonigo",
    "iso:country":"ES",
    "sg:address":"Calle de Canonigo, 64",
    "sg:city":"Dos Hermanas",
    "sg:orig_category":"Abogados",
    "sg:phone":"+34 954 72 66 99",
    "sg:postcode":"41700",
    "sg:province":"Sevilla",
    "wof:name":"Tornay Siguenza Antonio Eduardo",
    "wof:placetype":"venue"
},
  "geometry": {"coordinates":[-5.92309618,37.2836036682],"type":"Point"}
}