{
  "type": "Feature",
  "properties": {
    "iso:country":"ES",
    "sg:address":"Rua Cerca (da), 17",
    "sg:city":"Carballi\u00f1o",
    "sg:orig_category":"Molduras, Junquillos, Listones Y Molduras Perforadas",
    "sg:phone":"+34 988 27 02 26",
    "sg:postcode":"32500",
    "sg:province":"Ourense",
    "wof:name":"Hermida Vazquez Juan Francisco",
    "wof:placetype":"venue"
},
  "geometry": {"coordinates":[-8.0755386353,42.4309883118],"type":"Point"}
}