{
  "type": "Feature",
  "properties": {
    "iso:country":"ES",
    "sg:address":"Calle de Carmelo, 5",
    "sg:city":"Valladolid",
    "sg:orig_category":"Asociaciones Y Clubs Deportivos",
    "sg:phone":"+34 983 22 64 62",
    "sg:postcode":"47013",
    "sg:province":"Valladolid",
    "wof:name":"Harcisport S.l.",
    "wof:placetype":"venue"
},
  "geometry": {"coordinates":[-4.7166185379,41.6394424438],"type":"Point"}
}