{
  "type": "Feature",
  "properties": {
    "addr:full":"Calle de Altillo, 21 Benquerencia De La Serena Badajoz 06429",
    "addr:housenumber":"21",
    "addr:postcode":"06429",
    "addr:street":"Calle De Altillo",
    "iso:country":"ES",
    "sg:address":"Calle de Altillo, 21",
    "sg:city":"Benquerencia De La Serena",
    "sg:orig_category":"M\u00c1quinas De Caf\u00c9 (fabricaci\u00d3n, Al Por Mayor)",
    "sg:phone":"+34 924 77 45 38",
    "sg:postcode":"06429",
    "sg:province":"Badajoz",
    "wof:name":"Acedo Sanchez Magdalena",
    "wof:placetype":"venue"
},
  "geometry": {"coordinates":[-5.4943499565,38.6995353699],"type":"Point"}
}