{
  "type": "Feature",
  "properties": {
    "iso:country":"ES",
    "sg:address":"Pque Parque Del Carmen, 5",
    "sg:city":"Logro\u00f1o",
    "sg:orig_category":"Delegados, Agentes De Tr\u00c1nsito, Auxiliares De Transporte Internacional",
    "sg:phone":"+34 941 24 84 36",
    "sg:postcode":"26003",
    "sg:province":"La Rioja",
    "wof:name":"Aguilar Mansilla Antonio",
    "wof:placetype":"venue"
},
  "geometry": {"coordinates":[-2.4431800842,42.4612426758],"type":"Point"}
}