{
  "type": "Feature",
  "properties": {
    "addr:full":"Avda Bormujos, S/n Castilleja Cuesta Sevilla 41950",
    "addr:housenumber":"s / n",
    "addr:postcode":"41950",
    "addr:street":"Avda Bormujos;Castilleja Cuesta Sevilla",
    "iso:country":"ES",
    "sg:address":"Avda Bormujos, S/n",
    "sg:city":"Castilleja Cuesta",
    "sg:orig_category":"Venta, Colocaci\u00d3n De Autoradios",
    "sg:phone":"+34 954 16 06 52",
    "sg:postcode":"41950",
    "sg:province":"Sevilla",
    "sg:website":"www.viatuning.com",
    "wof:name":"Rodriguez Aguilera Jose Antonio",
    "wof:placetype":"venue"
},
  "geometry": {"coordinates":[-6.0623540878,37.3823738098],"type":"Point"}
}