{
  "type": "Feature",
  "properties": {
    "addr:full":"Calle de Fray Junipero Serra, 22 Salamanca Salamanca 37005",
    "addr:housenumber":"22",
    "addr:postcode":"37005",
    "addr:street":"Calle De Fray Junipero Serra",
    "iso:country":"ES",
    "sg:address":"Calle de Fray Junipero Serra, 22",
    "sg:city":"Salamanca",
    "sg:orig_category":"Ense\u00d1anza, Formaci\u00d3n Profesional: Aprendizaje",
    "sg:phone":"+34 923 22 64 07",
    "sg:postcode":"37005",
    "sg:province":"Salamanca",
    "wof:name":"Instituto De Ense\u00f1anzas Aplicadas S.c.l.",
    "wof:placetype":"venue"
},
  "geometry": {"coordinates":[-5.657749176,40.9769706726],"type":"Point"}
}