{
  "type": "Feature",
  "properties": {
    "iso:country":"ES",
    "sg:address":"Plaz Colon (de), 10",
    "sg:city":"Cordoba",
    "sg:orig_category":"Inmobiliaria (agencias)",
    "sg:phone":"+34 957 47 01 02",
    "sg:postcode":"14001",
    "sg:province":"C\u00f3rdoba",
    "wof:name":"Compa\u00f1ia Cordobesa De Renta Inmobiliaria S.a.",
    "wof:placetype":"venue"
},
  "geometry": {"coordinates":[-4.7797689438,37.8908004761],"type":"Point"}
}