{
  "type": "Feature",
  "properties": {
    "addr:full":"Calle de Barrio, 11 Cerro Andevalo Huelva 21320",
    "addr:housenumber":"11",
    "addr:postcode":"21320",
    "addr:street":"Calle De Barrio;Andevalo",
    "iso:country":"ES",
    "sg:address":"Calle de Barrio, 11",
    "sg:city":"Cerro Andevalo",
    "sg:classifiers":[
        {
            "category":"Taxi",
            "type":"Transportation"
        }
    ],
    "sg:phone":"+34 959 56 72 28",
    "sg:postcode":"21320",
    "sg:province":"Huelva",
    "wof:name":"Rufo Patricio Julian",
    "wof:placetype":"venue"
},
  "geometry": {"coordinates":[-6.9376583099,37.7341918945],"type":"Point"}
}