{
  "type": "Feature",
  "properties": {
    "addr:full":"Pase Reina Cristina, 11 Madrid Madrid 28014",
    "addr:housenumber":"11",
    "addr:postcode":"madrid;28014",
    "iso:country":"ES",
    "sg:address":"Pase Reina Cristina, 11",
    "sg:city":"Madrid",
    "sg:orig_category":"Laboratorios Y Cl\u00cdnicas Veterinarias",
    "sg:phone":"+34 915 01 96 63",
    "sg:postcode":"28014",
    "sg:province":"Madrid",
    "wof:name":"Gabinete Veterinario De Madrid S.l.",
    "wof:placetype":"venue"
},
  "geometry": {"coordinates":[-3.682612896,40.4070091248],"type":"Point"}
}