{
  "type": "Feature",
  "properties": {
    "iso:country":"ES",
    "sg:address":"Rond Pedro, 8",
    "sg:city":"Escala",
    "sg:orig_category":"M\u00c9dicos: Ginecolog\u00cda Y Obstetricia",
    "sg:phone":"+34 972 77 19 49",
    "sg:postcode":"17130",
    "sg:province":"Girona",
    "wof:name":"Gomez Nicolau Monica",
    "wof:placetype":"venue"
},
  "geometry": {"coordinates":[3.1321649551,42.1229934692],"type":"Point"}
}