{
  "type": "Feature",
  "properties": {
    "addr:full":"Carrer de Ferran Agullo, 6 Molins Rei Barcelona 08750",
    "addr:housenumber":"6",
    "addr:postcode":"08750",
    "addr:street":"Carrer De Ferran Agullo;Barcelona",
    "iso:country":"ES",
    "sg:address":"Carrer de Ferran Agullo, 6",
    "sg:city":"Molins Rei",
    "sg:orig_category":"Peluquer\u00cdas, Peluquer\u00cda Mixta",
    "sg:phone":"+34 936 68 00 97",
    "sg:postcode":"08750",
    "sg:province":"Barcelona",
    "wof:name":"De Amo Salcedo Dolores",
    "wof:placetype":"venue"
},
  "geometry": {"coordinates":[2.0205249786,41.4071731567],"type":"Point"}
}