{
  "type": "Feature",
  "properties": {
    "iso:country":"ES",
    "sg:address":"Calle de Jose Latorre, 6",
    "sg:city":"Caspe",
    "sg:orig_category":"Ense\u00d1anza Variada",
    "sg:phone":"+34 976 63 17 38",
    "sg:postcode":"50700",
    "sg:province":"Zaragoza",
    "wof:name":"Centro De Formacion Brik S.c.",
    "wof:placetype":"venue"
},
  "geometry": {"coordinates":[-0.0438840017,41.2381248474],"type":"Point"}
}