{
  "type": "Feature",
  "properties": {
    "addr:full":"Calle de Don Miguel Eza, 12 Tudela Navarra 31500",
    "addr:housenumber":"12",
    "addr:postcode":"31500",
    "addr:street":"Calle De Don;Eza",
    "iso:country":"ES",
    "sg:address":"Calle de Don Miguel Eza, 12",
    "sg:city":"Tudela",
    "sg:orig_category":"Droguer\u00cdas (al Por Menor)",
    "sg:phone":"+34 948 84 79 31",
    "sg:postcode":"31500",
    "sg:province":"Navarra",
    "wof:name":"Elguezabal Franquet S.l.",
    "wof:placetype":"venue"
},
  "geometry": {"coordinates":[-1.6049407721,42.0606880188],"type":"Point"}
}