{
  "type": "Feature",
  "properties": {
    "addr:full":"Avda. Ejercito, 5 Plasencia C\u00e1ceres 10600",
    "addr:housenumber":"5",
    "addr:postcode":"10600",
    "addr:street":"Avda. Ejercito;Ca\u0301Ceres",
    "iso:country":"ES",
    "sg:address":"Avda. Ejercito, 5",
    "sg:city":"Plasencia",
    "sg:orig_category":"Cajas De Ahorro",
    "sg:phone":"+34 927 41 18 38",
    "sg:postcode":"10600",
    "sg:province":"C\u00e1ceres",
    "wof:name":"Caja De Ahorros Y Monte De Piedad De Extremadura",
    "wof:placetype":"venue"
},
  "geometry": {"coordinates":[-6.0898518562,40.0299453735],"type":"Point"}
}