{
  "type": "Feature",
  "properties": {
    "addr:full":"Avda Cid, 11 Son Ferriol Islas Baleares 07198",
    "addr:housenumber":"11",
    "addr:postcode":"07198",
    "addr:street":"Avda Cid",
    "iso:country":"ES",
    "sg:address":"Avda Cid, 11",
    "sg:city":"Son Ferriol",
    "sg:orig_category":"Agencias De Viajes",
    "sg:phone":"+34 971 42 81 84",
    "sg:postcode":"07198",
    "sg:province":"Islas Baleares",
    "sg:website":"www.halconviajes.com",
    "wof:name":"Viajes Halcon S.a.",
    "wof:placetype":"venue"
},
  "geometry": {"coordinates":[2.7178099155,39.5789794922],"type":"Point"}
}