{
  "type": "Feature",
  "properties": {
    "addr:full":"Carretera De Sahag\u00fan, 4 Mayorga Valladolid 47680",
    "addr:housenumber":"4",
    "addr:postcode":"47680",
    "addr:street":"Carretera De Sahagu\u0301N",
    "iso:country":"ES",
    "sg:address":"Carretera De Sahag\u00fan, 4",
    "sg:city":"Mayorga",
    "sg:orig_category":"Negocio De Materiales De Construcci\u00d3n",
    "sg:phone":"+34 983 76 26 07",
    "sg:postcode":"47680",
    "sg:province":"Valladolid",
    "wof:name":"Martinez Martinez Ricardo",
    "wof:placetype":"venue"
},
  "geometry": {"coordinates":[-5.2684402466,42.1662445068],"type":"Point"}
}