{
  "type": "Feature",
  "properties": {
    "iso:country":"ES",
    "sg:address":"Barr Corral (el), 132",
    "sg:city":"Santiba\u00d1ez",
    "sg:orig_category":"Perreras, Pensiones Para Perros, Gatos Y Otros Animales",
    "sg:phone":"+34 942 59 32 51",
    "sg:postcode":"39649",
    "sg:province":"Cantabria",
    "wof:name":"Equigen De Xindu S.l.",
    "wof:placetype":"venue"
},
  "geometry": {"coordinates":[-3.8257930279,43.2210731506],"type":"Point"}
}