{
  "type": "Feature",
  "properties": {
    "addr:full":"Calle de Menendez Y Pelayo, 21 Valverde Camino Huelva 21600",
    "addr:housenumber":"21",
    "addr:postcode":"21600",
    "addr:street":"Calle De Menendez Y Pelayo;Camino Huelva",
    "iso:country":"ES",
    "sg:address":"Calle de Menendez Y Pelayo, 21",
    "sg:city":"Valverde Camino",
    "sg:orig_category":"Agencias Y Agentes Comerciales, Representantes",
    "sg:phone":"+34 959 55 04 03",
    "sg:postcode":"21600",
    "sg:province":"Huelva",
    "wof:name":"Rodriguez Idalgo Agustin",
    "wof:placetype":"venue"
},
  "geometry": {"coordinates":[-6.7557320595,37.5752220154],"type":"Point"}
}