{
  "type": "Feature",
  "properties": {
    "iso:country":"ES",
    "sg:address":"Calle de Fraguas, 10",
    "sg:city":"Alcorcon",
    "sg:orig_category":"Carnes De Carnicer\u00cda (al Por Mayor)",
    "sg:phone":"+34 916 43 33 78",
    "sg:postcode":"28925",
    "sg:province":"Madrid",
    "wof:name":"Suministros Carnicos Coello S.l.",
    "wof:placetype":"venue"
},
  "geometry": {"coordinates":[-3.8116037846,40.3393630981],"type":"Point"}
}