{
  "type": "Feature",
  "properties": {
    "addr:full":"Calle de San Ignacio De Loyola, 4 Cuesta Santa Cruz De Tenerife 38320",
    "addr:housenumber":"4",
    "addr:postcode":"38320",
    "addr:street":"Calle De San Ignacio De Loyola",
    "iso:country":"ES",
    "sg:address":"Calle de San Ignacio De Loyola, 4",
    "sg:city":"Cuesta",
    "sg:orig_category":"Electricidad Veh\u00cdculo",
    "sg:phone":"+34 922 64 61 11",
    "sg:postcode":"38320",
    "sg:province":"Santa Cruz De Tenerife",
    "wof:name":"Mas Garcia Rafael",
    "wof:placetype":"venue"
},
  "geometry": {"coordinates":[-16.2880134583,28.468454361],"type":"Point"}
}