{
  "type": "Feature",
  "properties": {
    "addr:full":"Santisimo Cristo De Burgos, 9 Cabra Sto Cristo Ja\u00e9n 23550",
    "addr:housenumber":"9",
    "addr:postcode":"23550",
    "addr:street":"Burgos;Sto;Jae\u0301N",
    "iso:country":"ES",
    "sg:address":"Santisimo Cristo De Burgos, 9",
    "sg:city":"Cabra Sto Cristo",
    "sg:orig_category":"Transportes Por Carretera: Lotes Completos, Mercanc\u00cdas Diversas",
    "sg:phone":"+34 953 39 75 18",
    "sg:postcode":"23550",
    "sg:province":"Ja\u00e9n",
    "wof:name":"Fernandez Fernandez,sergio",
    "wof:placetype":"venue"
},
  "geometry": {"coordinates":[-3.2850489616,37.7046966553],"type":"Point"}
}