{
  "type": "Feature",
  "properties": {
    "iso:country":"ES",
    "sg:address":"Calle de Veleta, 13",
    "sg:city":"Madrid",
    "sg:orig_category":"Importaci\u00d3n",
    "sg:phone":"+34 917 40 23 50",
    "sg:postcode":"28023",
    "sg:province":"Madrid",
    "wof:name":"Comercio Inteligente S.l.",
    "wof:placetype":"venue"
},
  "geometry": {"coordinates":[-3.7837719917,40.4549636841],"type":"Point"}
}