{
  "type": "Feature",
  "properties": {
    "iso:country":"ES",
    "sg:address":"Pg Gracia, 78",
    "sg:city":"Barcelona",
    "sg:orig_category":"Inform\u00c1tica: Consultores",
    "sg:phone":"+34 932 15 57 74",
    "sg:postcode":"08008",
    "sg:province":"Barcelona",
    "sg:website":"www.altran.net",
    "wof:name":"Software De Base S.a.",
    "wof:placetype":"venue"
},
  "geometry": {"coordinates":[2.1632969379,41.3939170837],"type":"Point"}
}