{
  "type": "Feature",
  "properties": {
    "iso:country":"ES",
    "sg:address":"Carrer de M D Montserrat, 124",
    "sg:city":"Viladecans",
    "sg:orig_category":"Aparcamientos (infraestructuras, Accesorios)",
    "sg:phone":"+34 936 58 28 35",
    "sg:postcode":"08840",
    "sg:province":"Barcelona",
    "wof:name":"Gestio D' Aparcamentes",
    "wof:placetype":"venue"
},
  "geometry": {"coordinates":[2.0112099648,41.3260803223],"type":"Point"}
}