{
  "type": "Feature",
  "properties": {
    "addr:full":"Rond Nelle, 95 Coru\u00d1a La Coru\u00f1a 15010",
    "addr:housenumber":"95",
    "addr:postcode":"15010",
    "addr:street":"Rond Nelle;Corun\u0303A",
    "iso:country":"ES",
    "sg:address":"Rond Nelle, 95",
    "sg:city":"Coru\u00d1a",
    "sg:orig_category":"Supermercados Y Hipermercados",
    "sg:phone":"+34 981 14 43 60",
    "sg:postcode":"15010",
    "sg:province":"La Coru\u00f1a",
    "wof:name":"Compa\u00f1ia Gallega De Supermercados S.a.",
    "wof:placetype":"venue"
},
  "geometry": {"coordinates":[-8.4162569046,43.3616142273],"type":"Point"}
}