{
  "type": "Feature",
  "properties": {
    "addr:full":"Rua Gerona, 16 Vigo Pontevedra 36211",
    "addr:housenumber":"16",
    "addr:postcode":"36211",
    "addr:street":"Rua Gerona",
    "iso:country":"ES",
    "sg:address":"Rua Gerona, 16",
    "sg:city":"Vigo",
    "sg:orig_category":"M\u00c9dicos: Estomatolog\u00cda",
    "sg:phone":"+34 986 23 02 02",
    "sg:postcode":"36211",
    "sg:province":"Pontevedra",
    "wof:name":"Caldelas Mu\u00f1oa Alicia Cristina",
    "wof:placetype":"venue"
},
  "geometry": {"coordinates":[-8.7298374176,42.221321106],"type":"Point"}
}