{
  "type": "Feature",
  "properties": {
    "addr:full":"C/ Major, 111 Salt Girona 17190",
    "addr:housenumber":"111",
    "addr:postcode":"17190",
    "addr:street":"C / Major",
    "iso:country":"ES",
    "sg:address":"C/ Major, 111",
    "sg:city":"Salt",
    "sg:orig_category":"Tintorer\u00cdas, Limpieza En Seco",
    "sg:phone":"+34 972 23 84 86",
    "sg:postcode":"17190",
    "sg:province":"Girona",
    "wof:name":"Rodriguez Rodriguez Francisco",
    "wof:placetype":"venue"
},
  "geometry": {"coordinates":[2.7870519161,41.9741821289],"type":"Point"}
}