{
  "type": "Feature",
  "properties": {
    "iso:country":"ES",
    "sg:address":"Pl Anselm Clave, 12",
    "sg:city":"Cardedeu",
    "sg:orig_category":"Bancos",
    "sg:phone":"+34 938 46 13 00",
    "sg:postcode":"08440",
    "sg:province":"Barcelona",
    "sg:website":"www.bancsabadell.com",
    "wof:name":"Banc Sabadell S.a.",
    "wof:placetype":"venue"
},
  "geometry": {"coordinates":[2.3559930325,41.6380729675],"type":"Point"}
}