{
  "type": "Feature",
  "properties": {
    "addr:full":"Urb Montesol, 99 Baradello-sargento Alicante 03800",
    "addr:housenumber":"99",
    "addr:postcode":"03800",
    "addr:street":"Urb Montesol;Alicante",
    "iso:country":"ES",
    "sg:address":"Urb Montesol, 99",
    "sg:city":"Baradello-sargento",
    "sg:orig_category":"M\u00c9dicos: Cirug\u00cda General",
    "sg:phone":"+34 966 52 56 49",
    "sg:postcode":"03800",
    "sg:province":"Alicante",
    "wof:name":"Baltasar Torrejon Aniceto",
    "wof:placetype":"venue"
},
  "geometry": {"coordinates":[-0.4804700017,38.3440818787],"type":"Point"}
}