{
  "type": "Feature",
  "properties": {
    "iso:country":"ES",
    "sg:address":"Pase Extremadura, 45",
    "sg:city":"Madrid",
    "sg:orig_category":"Quincaller\u00cda (al Por Menor)",
    "sg:phone":"+34 915 26 59 45",
    "sg:postcode":"28011",
    "sg:province":"Madrid",
    "wof:name":"Ferreteria Jara S.a.",
    "wof:placetype":"venue"
},
  "geometry": {"coordinates":[-3.7296979427,40.4130554199],"type":"Point"}
}