{
  "type": "Feature",
  "properties": {
    "addr:full":"Calle de Betis, S/n Sevilla Sevilla 41010",
    "addr:housenumber":"/ n",
    "addr:postcode":"41010",
    "addr:street":"Calle De Betis S",
    "iso:country":"ES",
    "sg:address":"Calle de Betis, S/n",
    "sg:city":"Sevilla",
    "sg:orig_category":"Molduras, Junquillos, Listones Y Molduras Perforadas",
    "sg:phone":"+34 954 33 14 99",
    "sg:postcode":"41010",
    "sg:province":"Sevilla",
    "wof:name":"Costa Silva Josefa",
    "wof:placetype":"venue"
},
  "geometry": {"coordinates":[-5.9996581078,37.3832397461],"type":"Point"}
}