{
  "type": "Feature",
  "properties": {
    "addr:full":"Avda Espa\u00d1a (de), 48 Alcobendas Madrid 28100",
    "addr:housenumber":"48",
    "addr:postcode":"28100",
    "addr:street":"Avda Espan\u0303A De",
    "iso:country":"ES",
    "sg:address":"Avda Espa\u00d1a (de), 48",
    "sg:city":"Alcobendas",
    "sg:orig_category":"Carnicer\u00cdas, Carnicer\u00cdas",
    "sg:phone":"+34 916 54 05 86",
    "sg:postcode":"28100",
    "sg:province":"Madrid",
    "wof:name":"Sastre Pelaez Enrique",
    "wof:placetype":"venue"
},
  "geometry": {"coordinates":[-3.638324976,40.5477905273],"type":"Point"}
}