{
  "type": "Feature",
  "properties": {
    "iso:country":"ES",
    "sg:address":"Pg Deu D'abril, 27",
    "sg:city":"Puigcerda",
    "sg:orig_category":"Carnicer\u00cdas, Carnicer\u00cdas",
    "sg:phone":"+34 972 14 03 95",
    "sg:postcode":"17520",
    "sg:province":"Girona",
    "wof:name":"Meya Sindreu Juan",
    "wof:placetype":"venue"
},
  "geometry": {"coordinates":[1.9272170067,42.432888031],"type":"Point"}
}