{
  "type": "Feature",
  "properties": {
    "iso:country":"ES",
    "sg:address":"C/ Obispo Winibal, 40",
    "sg:city":"Elche",
    "sg:orig_category":"Alimentaci\u00d3n General (al Por Menor)",
    "sg:phone":"+34 965 45 63 47",
    "sg:postcode":"03202",
    "sg:province":"Alicante",
    "wof:name":"Peral Agullo Juan",
    "wof:placetype":"venue"
},
  "geometry": {"coordinates":[-0.6842979789,38.2727546692],"type":"Point"}
}