{
  "type": "Feature",
  "properties": {
    "addr:full":"Avda Badajoz, Km. 0095,6 Don Benito Badajoz 06400",
    "addr:postcode":"06400",
    "addr:street":"Avda Badajoz Km. 0095,6",
    "iso:country":"ES",
    "sg:address":"Avda Badajoz, Km. 0095,6",
    "sg:city":"Don Benito",
    "sg:orig_category":"Reparaciones Y Remolcado De Veh\u00cdculos",
    "sg:phone":"+34 924 80 37 04",
    "sg:postcode":"06400",
    "sg:province":"Badajoz",
    "wof:name":"Paredes Rebolledo Pedro",
    "wof:placetype":"venue"
},
  "geometry": {"coordinates":[-5.8750867844,38.9542579651],"type":"Point"}
}