{
  "type": "Feature",
  "properties": {
    "addr:full":"Cllo Gandesa, 2 Sevilla Sevilla 41004",
    "addr:housenumber":"2",
    "addr:postcode":"41004",
    "iso:country":"ES",
    "sg:address":"Cllo Gandesa, 2",
    "sg:city":"Sevilla",
    "sg:orig_category":"Arquitectos",
    "sg:phone":"+34 954 22 99 02",
    "sg:postcode":"41004",
    "sg:province":"Sevilla",
    "wof:name":"Diaz Sanchez Francisco",
    "wof:placetype":"venue"
},
  "geometry": {"coordinates":[-5.9904289246,37.3886184692],"type":"Point"}
}