{
  "type": "Feature",
  "properties": {
    "iso:country":"ES",
    "sg:address":"Pase Larratxo De, 26",
    "sg:city":"Donostia-san Sebastian",
    "sg:orig_category":"Laboratorios Y Trabajos De Fotograf\u00cda, V\u00cddeo Y Cine",
    "sg:phone":"+34 943 39 01 60",
    "sg:postcode":"20017",
    "sg:province":"Guip\u00f9zcoa",
    "wof:name":"Kattagorri",
    "wof:placetype":"venue"
},
  "geometry": {"coordinates":[-1.9394210577,43.313117981],"type":"Point"}
}