{
  "type": "Feature",
  "properties": {
    "iso:country":"ES",
    "sg:address":"Calle de Pedro De Arguello, 12",
    "sg:city":"Galdar",
    "sg:orig_category":"Internados & Ense\u00d1anza Privada",
    "sg:phone":"+34 928 88 07 23",
    "sg:postcode":"35460",
    "sg:province":"Las Palmas",
    "wof:name":"Colegio De Jesus Sacramentado",
    "wof:placetype":"venue"
},
  "geometry": {"coordinates":[-15.6495609283,28.143945694],"type":"Point"}
}