{
  "type": "Feature",
  "properties": {
    "addr:full":"General Franco, 38 Outes La Coru\u00f1a 15230",
    "addr:housenumber":"38",
    "addr:postcode":"15230",
    "addr:street":"Franco;La Corun\u0303A",
    "iso:country":"ES",
    "sg:address":"General Franco, 38",
    "sg:city":"Outes",
    "sg:orig_category":"Prot\u00c9sicos Dentales",
    "sg:phone":"+34 981 85 08 34",
    "sg:postcode":"15230",
    "sg:province":"La Coru\u00f1a",
    "wof:name":"Atan Pi\u00f1eiro Victor",
    "wof:placetype":"venue"
},
  "geometry": {"coordinates":[-8.9190149307,42.8512496948],"type":"Point"}
}