{
  "type": "Feature",
  "properties": {
    "iso:country":"ES",
    "sg:address":"Calle de Condes De Aragon, 20",
    "sg:city":"Zaragoza",
    "sg:orig_category":"Arquitectos",
    "sg:phone":"+34 976 15 92 69",
    "sg:postcode":"50009",
    "sg:province":"Zaragoza",
    "wof:name":"Sanz Camara Carlos",
    "wof:placetype":"venue"
},
  "geometry": {"coordinates":[-0.9065600038,41.6386566162],"type":"Point"}
}