{
  "type": "Feature",
  "properties": {
    "iso:country":"ES",
    "sg:address":"Calle de Estacion, S/n",
    "sg:city":"Medina Rioseco",
    "sg:orig_category":"Molduras, Junquillos, Listones Y Molduras Perforadas",
    "sg:phone":"+34 983 72 03 15",
    "sg:postcode":"47800",
    "sg:province":"Valladolid",
    "wof:name":"Vigo-barcelona S.a.",
    "wof:placetype":"venue"
},
  "geometry": {"coordinates":[-5.0455641747,41.8804016113],"type":"Point"}
}