{
  "type": "Feature",
  "properties": {
    "addr:full":"Carr Sant Antoni, 25 Lleida Lleida 25002",
    "addr:housenumber":"25",
    "addr:postcode":"25002",
    "addr:street":"Carr Sant Antoni",
    "iso:country":"ES",
    "sg:address":"Carr Sant Antoni, 25",
    "sg:city":"Lleida",
    "sg:orig_category":"Bisuter\u00cda, Joyer\u00cda, Relojer\u00cda (al Por Menor)",
    "sg:phone":"+34 973 27 24 38",
    "sg:postcode":"25002",
    "sg:province":"Lleida",
    "wof:name":"Ramon Miranda S.l.",
    "wof:placetype":"venue"
},
  "geometry": {"coordinates":[0.6222199798,41.6120414734],"type":"Point"}
}