{
  "type": "Feature",
  "properties": {
    "iso:country":"ES",
    "sg:address":"Calle de Fermin Mur, 22",
    "sg:city":"Graus",
    "sg:orig_category":"Lencer\u00cda Femenina, Corseter\u00cda, Trajes De Ba\u00d1o (al Por Menor)",
    "sg:phone":"+34 974 54 10 27",
    "sg:postcode":"22430",
    "sg:province":"Huesca",
    "wof:name":"Fumanal Guerri Raquel",
    "wof:placetype":"venue"
},
  "geometry": {"coordinates":[0.3370774984,42.1898345947],"type":"Point"}
}