{
  "type": "Feature",
  "properties": {
    "addr:full":"Calle de Compostela, 12 Esfarrapada Pontevedra 36470",
    "addr:housenumber":"12",
    "addr:postcode":"36470",
    "addr:street":"Calle De Compostela",
    "iso:country":"ES",
    "sg:address":"Calle de Compostela, 12",
    "sg:city":"Esfarrapada",
    "sg:orig_category":"Inmobiliaria (agencias)",
    "sg:phone":"+34 986 34 93 65",
    "sg:postcode":"36470",
    "sg:province":"Pontevedra",
    "wof:name":"Immosalceda C.b.",
    "wof:placetype":"venue"
},
  "geometry": {"coordinates":[-8.5593519211,42.1009902954],"type":"Point"}
}