{
  "type": "Feature",
  "properties": {
    "iso:country":"ES",
    "sg:address":"Carrer de Carme (del), 94",
    "sg:city":"Mataro",
    "sg:orig_category":"Tratamiento Y Transformaci\u00d3n De Tejidos",
    "sg:phone":"+34 937 99 25 56",
    "sg:postcode":"08302",
    "sg:province":"Barcelona",
    "wof:name":"Danacap Textil S.c.p.",
    "wof:placetype":"venue"
},
  "geometry": {"coordinates":[2.4383890629,41.542263031],"type":"Point"}
}