{
  "type": "Feature",
  "properties": {
    "addr:full":"Calle de Isla Graciosa, 4 Madrid Madrid 28034",
    "addr:housenumber":"4",
    "addr:postcode":"28034",
    "addr:street":"Calle De Isla Graciosa",
    "iso:country":"ES",
    "sg:address":"Calle de Isla Graciosa, 4",
    "sg:city":"Madrid",
    "sg:orig_category":"Inmobiliaria (agencias)",
    "sg:phone":"+34 913 58 02 05",
    "sg:postcode":"28034",
    "sg:province":"Madrid",
    "wof:name":"Ledesma Thalheimer Fernando",
    "wof:placetype":"venue"
},
  "geometry": {"coordinates":[-3.6857419014,40.4927711487],"type":"Point"}
}