{
  "type": "Feature",
  "properties": {
    "addr:full":"Calle de Alcala, 502 Madrid Madrid 28027",
    "addr:housenumber":"502",
    "addr:postcode":"28027",
    "addr:street":"Calle De Alcala",
    "iso:country":"ES",
    "sg:address":"Calle de Alcala, 502",
    "sg:city":"Madrid",
    "sg:orig_category":"Productores Recolectores, Venta Directa De Vinos",
    "sg:phone":"+34 913 04 19 11",
    "sg:postcode":"28027",
    "sg:province":"Madrid",
    "wof:name":"Tejedor Martin Fernando",
    "wof:placetype":"venue"
},
  "geometry": {"coordinates":[-3.6287677288,40.4403533936],"type":"Point"}
}