{
  "type": "Feature",
  "properties": {
    "addr:full":"Ctra. Tarragona-san Sebastian, Km. 0171,0 Barbastro Huesca 22300",
    "addr:postcode":"22300",
    "addr:street":"Ctra. Tarragona-San Sebastian Km. 0171,0",
    "iso:country":"ES",
    "sg:address":"Ctra. Tarragona-san Sebastian, Km. 0171,0",
    "sg:city":"Barbastro",
    "sg:orig_category":"\u00d3ptica: Instrumentos (fabricaci\u00d3n)",
    "sg:phone":"+34 974 30 89 28",
    "sg:postcode":"22300",
    "sg:province":"Huesca",
    "wof:name":"Optica San Ramon S.cv.",
    "wof:placetype":"venue"
},
  "geometry": {"coordinates":[0.1047969982,42.0337791443],"type":"Point"}
}