{
  "type": "Feature",
  "properties": {
    "addr:full":"Calle de Doctor Toledo Hijo, 5 Rozas De Madrid Madrid 28230",
    "addr:housenumber":"5",
    "addr:postcode":"28230",
    "addr:street":"Calle De Doctor Toledo Hijo",
    "iso:country":"ES",
    "sg:address":"Calle de Doctor Toledo Hijo, 5",
    "sg:city":"Rozas De Madrid",
    "sg:orig_category":"Laboratorios Y Cl\u00cdnicas Veterinarias",
    "sg:phone":"+34 916 37 02 77",
    "sg:postcode":"28230",
    "sg:province":"Madrid",
    "wof:name":"Dorcat Y Veterinm Sl",
    "wof:placetype":"venue"
},
  "geometry": {"coordinates":[-3.8739602566,40.4916534424],"type":"Point"}
}