{
  "type": "Feature",
  "properties": {
    "addr:full":"Poli Pol.indust. Cami Dels Frares, S/n Lleida Lleida 25191",
    "addr:housenumber":"s / n",
    "addr:postcode":"25191",
    "iso:country":"ES",
    "sg:address":"Poli Pol.indust. Cami Dels Frares, S/n",
    "sg:city":"Lleida",
    "sg:orig_category":"Inform\u00c1tica: Mantenimiento Y Reparaci\u00d3n De Ordenadores",
    "sg:phone":"+34 973 20 37 03",
    "sg:postcode":"25191",
    "sg:province":"Lleida",
    "wof:name":"Electronica Salto S.l.",
    "wof:placetype":"venue"
},
  "geometry": {"coordinates":[0.6831650138,41.5832138062],"type":"Point"}
}