{
  "type": "Feature",
  "properties": {
    "addr:full":"Rua Urzaiz, 48 Vigo Pontevedra 36201",
    "addr:housenumber":"48",
    "addr:postcode":"36201",
    "addr:street":"Rua Urzaiz",
    "iso:country":"ES",
    "sg:address":"Rua Urzaiz, 48",
    "sg:city":"Vigo",
    "sg:orig_category":"Ropa Para Se\u00d1oras (al Por Menor)",
    "sg:phone":"+34 986 22 97 95",
    "sg:postcode":"36201",
    "sg:province":"Pontevedra",
    "wof:name":"Vidrio Galicia S.l.",
    "wof:placetype":"venue"
},
  "geometry": {"coordinates":[-8.7167673111,42.2345161438],"type":"Point"}
}