{
  "type": "Feature",
  "properties": {
    "iso:country":"ES",
    "sg:address":"Plaz Ensanche, S/n",
    "sg:city":"Bilbao",
    "sg:orig_category":"Reposter\u00cdas",
    "sg:phone":"+34 944 23 32 67",
    "sg:postcode":"48009",
    "sg:province":"Vizcaya",
    "wof:name":"Obrador Del Ensanche S.l.",
    "wof:placetype":"venue"
},
  "geometry": {"coordinates":[-2.9313290119,43.2632904053],"type":"Point"}
}