{
  "type": "Feature",
  "properties": {
    "addr:full":"Forxan, S/n Forxan Pontevedra 36979",
    "addr:postcode":"36979",
    "addr:street":"Forxan S / N",
    "iso:country":"ES",
    "sg:address":"Forxan, S/n",
    "sg:city":"Forxan",
    "sg:orig_category":"Mec\u00c1nico Del Autom\u00d3vil",
    "sg:phone":"+34 986 72 33 87",
    "sg:postcode":"36979",
    "sg:province":"Pontevedra",
    "wof:name":"Blanco Dominguez Isidoro",
    "wof:placetype":"venue"
},
  "geometry": {"coordinates":[-8.8151941299,42.4157600403],"type":"Point"}
}