{
  "type": "Feature",
  "properties": {
    "addr:full":"Calle de Joaquin Benlloch, 41 Valencia Valencia 46026",
    "addr:housenumber":"41",
    "addr:postcode":"46026",
    "addr:street":"Calle De Joaquin Benlloch",
    "iso:country":"ES",
    "sg:address":"Calle de Joaquin Benlloch, 41",
    "sg:city":"Valencia",
    "sg:orig_category":"Doctores En Medicina",
    "sg:phone":"+34 963 33 04 71",
    "sg:postcode":"46026",
    "sg:province":"Valencia",
    "wof:name":"Lucia Cortes Maria Jesus",
    "wof:placetype":"venue"
},
  "geometry": {"coordinates":[-0.3757730126,39.4525184631],"type":"Point"}
}