{
  "type": "Feature",
  "properties": {
    "iso:country":"ES",
    "sg:address":"Carrer de Regent Mendieta, 10",
    "sg:city":"Barcelona",
    "sg:orig_category":"Carnicer\u00cdas, Carnicer\u00cdas",
    "sg:phone":"+34 933 34 51 87",
    "sg:postcode":"08028",
    "sg:province":"Barcelona",
    "wof:name":"Gonzalez Morais Maria Del Carmen",
    "wof:placetype":"venue"
},
  "geometry": {"coordinates":[2.1222610474,41.3766555786],"type":"Point"}
}