{
  "type": "Feature",
  "properties": {
    "addr:full":"Calle de Barrenkale-barrena, 1 Gernika-lumo Vizcaya 48300",
    "addr:housenumber":"1",
    "addr:postcode":"48300",
    "addr:street":"Calle De Barrenkale-Barrena",
    "iso:country":"ES",
    "sg:address":"Calle de Barrenkale-barrena, 1",
    "sg:city":"Gernika-lumo",
    "sg:orig_category":"Art\u00cdculos De Decoraci\u00d3n",
    "sg:phone":"+34 946 25 80 88",
    "sg:postcode":"48300",
    "sg:province":"Vizcaya",
    "wof:name":"Maite Bilbao Ormaza",
    "wof:placetype":"venue"
},
  "geometry": {"coordinates":[-2.677693367,43.3161468506],"type":"Point"}
}