{
  "type": "Feature",
  "properties": {
    "addr:full":"Ctra Caboalles, Km. 0002,5 Villabalter Le\u00f3n 24010",
    "addr:postcode":"24010",
    "addr:street":"Ctra Caboalles Km. 0002,5 Villabalter Leo\u0301N",
    "iso:country":"ES",
    "sg:address":"Ctra Caboalles, Km. 0002,5",
    "sg:city":"Villabalter",
    "sg:orig_category":"Empresas De Desmonte",
    "sg:phone":"+34 987 24 88 45",
    "sg:postcode":"24010",
    "sg:province":"Le\u00f3n",
    "wof:name":"Crespo Gonzalez Benigno",
    "wof:placetype":"venue"
},
  "geometry": {"coordinates":[-5.5932598114,42.6119194031],"type":"Point"}
}