{
  "type": "Feature",
  "properties": {
    "addr:full":"Carrer de Florida, 125 Hospitalet Llobregat Barcelona 08905",
    "addr:housenumber":"125",
    "addr:postcode":"08905",
    "addr:street":"Carrer De Florida",
    "iso:country":"ES",
    "sg:address":"Carrer de Florida, 125",
    "sg:city":"Hospitalet Llobregat",
    "sg:orig_category":"Centros Empresariales",
    "sg:phone":"+34 902 18 19 08",
    "sg:postcode":"08905",
    "sg:province":"Barcelona",
    "wof:name":"Vn Intel Marketing Group S.l.",
    "wof:placetype":"venue"
},
  "geometry": {"coordinates":[2.1081945896,41.3687019348],"type":"Point"}
}