{
  "type": "Feature",
  "properties": {
    "addr:full":"Carrer de Osca, 9 S. Boi Llobregat Barcelona 08830",
    "addr:housenumber":"9",
    "addr:postcode":"08830",
    "addr:street":"Carrer De Osca",
    "iso:country":"ES",
    "sg:address":"Carrer de Osca, 9",
    "sg:city":"S. Boi Llobregat",
    "sg:orig_category":"Alimentaci\u00d3n General (al Por Menor)",
    "sg:phone":"+34 936 54 46 58",
    "sg:postcode":"08830",
    "sg:province":"Barcelona",
    "wof:name":"Iniciativas Pax S.l.",
    "wof:placetype":"venue"
},
  "geometry": {"coordinates":[2.0483369827,41.3388633728],"type":"Point"}
}