{
  "type": "Feature",
  "properties": {
    "iso:country":"ES",
    "sg:address":"Calle de Resbaladero, 24",
    "sg:city":"San Vicente Alcantara",
    "sg:orig_category":"Empresas De Carpinter\u00cda Met\u00c1lica",
    "sg:phone":"+34 924 41 00 19",
    "sg:postcode":"06500",
    "sg:province":"Badajoz",
    "wof:name":"Diaz Piriz Juan",
    "wof:placetype":"venue"
},
  "geometry": {"coordinates":[-7.1370401382,39.3596534729],"type":"Point"}
}