{
  "type": "Feature",
  "properties": {
    "iso:country":"ES",
    "sg:address":"Avda Venezuela (de), 7",
    "sg:city":"Santa Cruz De Tenerife",
    "sg:orig_category":"Zapatos (al Por Menor)",
    "sg:phone":"+34 922 23 19 41",
    "sg:postcode":"38007",
    "sg:province":"Santa Cruz De Tenerife",
    "wof:name":"Calzados Suarez S.l.",
    "wof:placetype":"venue"
},
  "geometry": {"coordinates":[-16.2702007294,28.4655132294],"type":"Point"}
}