{
  "type": "Feature",
  "properties": {
    "addr:full":"Carrer de Puresa, 12 Palma Islas Baleares 07001",
    "addr:housenumber":"12",
    "addr:postcode":"07001",
    "addr:street":"Carrer De Puresa",
    "iso:country":"ES",
    "sg:address":"Carrer de Puresa, 12",
    "sg:city":"Palma",
    "sg:orig_category":"Internados & Ense\u00d1anza Privada",
    "sg:phone":"+34 971 72 12 33",
    "sg:postcode":"07001",
    "sg:province":"Islas Baleares",
    "wof:name":"Religiosas Pureza De Maria",
    "wof:placetype":"venue"
},
  "geometry": {"coordinates":[2.6511099339,39.5672988892],"type":"Point"}
}