{
  "type": "Feature",
  "properties": {
    "iso:country":"ES",
    "sg:address":"C/ Galeote, 9",
    "sg:city":"Altet",
    "sg:orig_category":"Pescader\u00cdas (al Por Menor)",
    "sg:phone":"+34 965 68 77 93",
    "sg:postcode":"03195",
    "sg:province":"Alicante",
    "wof:name":"Miralles Martinez Manuel Francisco",
    "wof:placetype":"venue"
},
  "geometry": {"coordinates":[-0.5177140236,38.2559547424],"type":"Point"}
}