{
  "type": "Feature",
  "properties": {
    "addr:full":"Calle de Pleyades (las), 29 Zaragoza Zaragoza 50012",
    "addr:housenumber":"29",
    "addr:postcode":"50012",
    "addr:street":"Calle De Pleyades Las",
    "iso:country":"ES",
    "sg:address":"Calle de Pleyades (las), 29",
    "sg:city":"Zaragoza",
    "sg:orig_category":"Guarder\u00cdas",
    "sg:phone":"+34 976 75 84 61",
    "sg:postcode":"50012",
    "sg:province":"Zaragoza",
    "wof:name":"Jardin De Infancia Los Andes 4, S.c.",
    "wof:placetype":"venue"
},
  "geometry": {"coordinates":[-0.9363309741,41.6403808594],"type":"Point"}
}