{
  "type": "Feature",
  "properties": {
    "iso:country":"ES",
    "sg:address":"Calle de Montalban, 2",
    "sg:city":"Granada",
    "sg:orig_category":"Laboratorios Y Cl\u00cdnicas Veterinarias",
    "sg:phone":"+34 958 80 08 20",
    "sg:postcode":"18002",
    "sg:province":"Granada",
    "wof:name":"Santos Lopez Trinidad",
    "wof:placetype":"venue"
},
  "geometry": {"coordinates":[-3.6037199497,37.1771354675],"type":"Point"}
}