{
  "type": "Feature",
  "properties": {
    "addr:full":"Calle de Paraiso, 4 Cuarte Huerva Zaragoza 50410",
    "addr:housenumber":"4",
    "addr:postcode":"50410",
    "addr:street":"Calle De Paraiso",
    "iso:country":"ES",
    "sg:address":"Calle de Paraiso, 4",
    "sg:city":"Cuarte Huerva",
    "sg:orig_category":"Art\u00cdculos De Regalo (al Por Menor)",
    "sg:phone":"+34 976 50 33 38",
    "sg:postcode":"50410",
    "sg:province":"Zaragoza",
    "wof:name":"Navarro Tomas Jesus",
    "wof:placetype":"venue"
},
  "geometry": {"coordinates":[-0.9303190112,41.6046066284],"type":"Point"}
}