{
  "type": "Feature",
  "properties": {
    "addr:full":"Calle de San Roque, 1 Burgos Burgos 09006",
    "addr:housenumber":"1",
    "addr:postcode":"09006",
    "addr:street":"Calle De San Roque",
    "iso:country":"ES",
    "sg:address":"Calle de San Roque, 1",
    "sg:city":"Burgos",
    "sg:orig_category":"Fabricaci\u00d3n, Instalaci\u00d3n De Armarios",
    "sg:phone":"+34 947 23 13 64",
    "sg:postcode":"09006",
    "sg:province":"Burgos",
    "wof:name":"Muebles San Roque S.l.",
    "wof:placetype":"venue"
},
  "geometry": {"coordinates":[-3.6801700592,42.3486633301],"type":"Point"}
}