{
  "type": "Feature",
  "properties": {
    "iso:country":"ES",
    "sg:address":"Calle de Flora Florez, 7",
    "sg:city":"Sahagun",
    "sg:orig_category":"Mercer\u00cda, Lencer\u00cda (al Por Menor)",
    "sg:phone":"+34 987 78 09 73",
    "sg:postcode":"24320",
    "sg:province":"Le\u00f3n",
    "wof:name":"Ferreiro Andres Rudesindo",
    "wof:placetype":"venue"
},
  "geometry": {"coordinates":[-5.0315499306,42.3711395264],"type":"Point"}
}