{
  "type": "Feature",
  "properties": {
    "addr:full":"Avda Europa, 125 Alfajarin Zaragoza 50172",
    "addr:housenumber":"125",
    "addr:postcode":"50172",
    "addr:street":"Avda Europa",
    "iso:country":"ES",
    "sg:address":"Avda Europa, 125",
    "sg:city":"Alfajarin",
    "sg:orig_category":"Molduras, Junquillos, Listones Y Molduras Perforadas",
    "sg:phone":"+34 976 10 11 52",
    "sg:postcode":"50172",
    "sg:province":"Zaragoza",
    "wof:name":"Solano Guio Mercedes",
    "wof:placetype":"venue"
},
  "geometry": {"coordinates":[-0.7056540251,41.6152801514],"type":"Point"}
}