{
  "type": "Feature",
  "properties": {
    "addr:full":"Avda Reino De Leon, 5 Santa Maria Del Paramo Le\u00f3n 24240",
    "addr:housenumber":"5",
    "addr:postcode":"24240",
    "addr:street":"Avda Reino De Leon",
    "iso:country":"ES",
    "sg:address":"Avda Reino De Leon, 5",
    "sg:city":"Santa Maria Del Paramo",
    "sg:orig_category":"Producci\u00d3n, Comercio De Cereales",
    "sg:phone":"+34 987 36 01 84",
    "sg:postcode":"24240",
    "sg:province":"Le\u00f3n",
    "wof:name":"Santos Barrio E Hijos S.l.",
    "wof:placetype":"venue"
},
  "geometry": {"coordinates":[-5.7469739914,42.3569259644],"type":"Point"}
}