{
  "type": "Feature",
  "properties": {
    "addr:full":"Plaz Naranjos (los), 1 Guadix Granada 18500",
    "addr:postcode":"18500",
    "addr:street":"Plaz;Los",
    "iso:country":"ES",
    "sg:address":"Plaz Naranjos (los), 1",
    "sg:city":"Guadix",
    "sg:orig_category":"Electrodom\u00c9sticos (al Por Menor)",
    "sg:phone":"+34 958 66 48 64",
    "sg:postcode":"18500",
    "sg:province":"Granada",
    "wof:name":"Antonio Hernandez Martinez Y Luis Encinas Sanchez",
    "wof:placetype":"venue"
},
  "geometry": {"coordinates":[-3.1341116428,37.3018569946],"type":"Point"}
}