{
  "type": "Feature",
  "properties": {
    "iso:country":"ES",
    "sg:address":"Calle de Francisco Garcia Pavon, 110",
    "sg:city":"Tomelloso",
    "sg:orig_category":"Contenedores (mercanc\u00cdas)",
    "sg:phone":"+34 926 51 14 31",
    "sg:postcode":"13700",
    "sg:province":"Ciudad Real",
    "wof:name":"Sanchez Palomar Juan Manuel",
    "wof:placetype":"venue"
},
  "geometry": {"coordinates":[-3.0052940845,39.1665611267],"type":"Point"}
}