{
  "type": "Feature",
  "properties": {
    "addr:full":"Ctra Seu D'urgell(la), S/n Ponts Lleida 25740",
    "addr:postcode":"25740",
    "addr:street":"Ctra Seu D'Urgell La S / N",
    "iso:country":"ES",
    "sg:address":"Ctra Seu D'urgell(la), S/n",
    "sg:city":"Ponts",
    "sg:orig_category":"Empresas De Carpinter\u00cda Met\u00c1lica",
    "sg:phone":"+34 973 46 03 33",
    "sg:postcode":"25740",
    "sg:province":"Lleida",
    "wof:name":"Abellana-viladrich S.l.",
    "wof:placetype":"venue"
},
  "geometry": {"coordinates":[1.20229,41.922165],"type":"Point"}
}