{
  "type": "Feature",
  "properties": {
    "addr:full":"Calle de Samuel Eijan, 12 Ourense Ourense 32003",
    "addr:housenumber":"12",
    "addr:postcode":"32003",
    "addr:street":"Calle De Samuel Eijan",
    "iso:country":"ES",
    "sg:address":"Calle de Samuel Eijan, 12",
    "sg:city":"Ourense",
    "sg:orig_category":"Agencias Y Agentes Comerciales, Representantes",
    "sg:phone":"+34 988 37 20 85",
    "sg:postcode":"32003",
    "sg:province":"Ourense",
    "wof:name":"Vazquez Fernandez Mario",
    "wof:placetype":"venue"
},
  "geometry": {"coordinates":[-7.8639750481,42.3439407349],"type":"Point"}
}