{
  "type": "Feature",
  "properties": {
    "iso:country":"ES",
    "sg:address":"Feria Del Tres, 12",
    "sg:city":"Vilarmaior",
    "sg:orig_category":"Trabajos De Perforaciones, Sondeos, Construcci\u00d3n De Pozos",
    "sg:phone":"+34 981 79 84 67",
    "sg:postcode":"15637",
    "sg:province":"La Coru\u00f1a",
    "wof:name":"Grandal Martinez Jose Antonio",
    "wof:placetype":"venue"
},
  "geometry": {"coordinates":[-8.1984739304,43.3606491089],"type":"Point"}
}