{
  "type": "Feature",
  "properties": {
    "iso:country":"ES",
    "sg:address":"Calle de Calvo Sotelo, 12",
    "sg:city":"Oviedo",
    "sg:orig_category":"Importaci\u00d3n, Negocio De Caf\u00c9, Cacao",
    "sg:phone":"+34 985 25 74 83",
    "sg:postcode":"33007",
    "sg:province":"Asturias",
    "wof:name":"Rodriguez Menendez Juan Carlos",
    "wof:placetype":"venue"
},
  "geometry": {"coordinates":[-5.8516345024,43.3586730957],"type":"Point"}
}