{
  "type": "Feature",
  "properties": {
    "addr:full":"Carrer de Maria Ibars (de), 12 Pedreguer Alicante 03750",
    "addr:housenumber":"12",
    "addr:postcode":"03750",
    "addr:street":"Carrer De Maria Ibars De",
    "iso:country":"ES",
    "sg:address":"Carrer de Maria Ibars (de), 12",
    "sg:city":"Pedreguer",
    "sg:orig_category":"Guarder\u00cdas",
    "sg:phone":"+34 965 76 12 39",
    "sg:postcode":"03750",
    "sg:province":"Alicante",
    "wof:name":"Fundacion Publica Guarderia Infantil La Glorieta",
    "wof:placetype":"venue"
},
  "geometry": {"coordinates":[0.0275199991,38.7957992554],"type":"Point"}
}