{
  "type": "Feature",
  "properties": {
    "addr:full":"Ptda Almafra, 32 Benidorm Alicante 03500",
    "addr:housenumber":"32",
    "addr:postcode":"03500",
    "addr:street":"Ptda Almafra",
    "iso:country":"ES",
    "sg:address":"Ptda Almafra, 32",
    "sg:city":"Benidorm",
    "sg:classifiers":[
        {
            "category":"Arts & Performance",
            "subcategory":"Art Gallery",
            "type":"Entertainment"
        }
    ],
    "sg:phone":"+34 966 88 93 34",
    "sg:postcode":"03500",
    "sg:province":"Alicante",
    "sg:tags":[
        "arte",
        "de",
        "galer\u00cdas"
    ],
    "wof:name":"Bengas S.l.",
    "wof:placetype":"venue"
},
  "geometry": {"coordinates":[-0.1739459932,38.5365180969],"type":"Point"}
}