{
  "type": "Feature",
  "properties": {
    "iso:country":"ES",
    "sg:address":"Avda 28 De Febrero, 1",
    "sg:city":"Ca\u00d1ico",
    "sg:orig_category":"Transportes Por V\u00cdas Navegables",
    "sg:phone":"+34 950 12 03 92",
    "sg:postcode":"04800",
    "sg:province":"Almer\u00eda",
    "wof:name":"Perez Rizos Luis",
    "wof:placetype":"venue"
},
  "geometry": {"coordinates":[-2.1415529251,37.4031028748],"type":"Point"}
}