{
  "type": "Feature",
  "properties": {
    "iso:country":"ES",
    "sg:address":"Calle de Felix Sanz, 2",
    "sg:city":"Olvega",
    "sg:orig_category":"Agencias Y Agentes Comerciales, Representantes",
    "sg:phone":"+34 976 64 54 52",
    "sg:postcode":"42110",
    "sg:province":"Soria",
    "wof:name":"Cereales Eve Hernandez S.l.",
    "wof:placetype":"venue"
},
  "geometry": {"coordinates":[-1.9864670038,41.7802009583],"type":"Point"}
}