{
  "type": "Feature",
  "properties": {
    "iso:country":"ES",
    "sg:address":"Calle de Bernardo De La Torre, 6",
    "sg:city":"Palmas De Gran Canaria",
    "sg:orig_category":"Navegaci\u00d3n (equipos De Pesca)",
    "sg:phone":"+34 928 26 12 17",
    "sg:postcode":"35007",
    "sg:province":"Las Palmas",
    "wof:name":"Ferafontof  Oleg",
    "wof:placetype":"venue"
},
  "geometry": {"coordinates":[-15.4343614578,28.1354656219],"type":"Point"}
}