{
  "type": "Feature",
  "properties": {
    "addr:full":"Avgd Rei Juan Carlos I, 6 Vila Joiosa Alicante 03570",
    "addr:housenumber":"6",
    "addr:postcode":"03570",
    "addr:street":"Juan Carlos I",
    "iso:country":"ES",
    "sg:address":"Avgd Rei Juan Carlos I, 6",
    "sg:city":"Vila Joiosa",
    "sg:orig_category":"Alimentaci\u00d3n General (al Por Menor)",
    "sg:phone":"+34 965 89 08 48",
    "sg:postcode":"03570",
    "sg:province":"Alicante",
    "wof:name":"Zaragoza Aragones Maria",
    "wof:placetype":"venue"
},
  "geometry": {"coordinates":[-0.2326133996,38.5077514648],"type":"Point"}
}