{
  "type": "Feature",
  "properties": {
    "addr:full":"Maria Zambrano, 3 Albacete Albacete 02006",
    "addr:housenumber":"3",
    "addr:postcode":"02006",
    "iso:country":"ES",
    "sg:address":"Maria Zambrano, 3",
    "sg:city":"Albacete",
    "sg:orig_category":"Servicios De Telecomunicaciones",
    "sg:phone":"+34 967 50 11 03",
    "sg:postcode":"02006",
    "sg:province":"Albacete",
    "sg:website":"www.fobostelecom.com",
    "wof:name":"Fobos Telecom S.l.",
    "wof:placetype":"venue"
},
  "geometry": {"coordinates":[-1.8544900417,38.9797363281],"type":"Point"}
}