{
  "type": "Feature",
  "properties": {
    "addr:full":"Carrer de Puig I Xoriguer, 18 Barcelona Barcelona 08004",
    "addr:housenumber":"18",
    "addr:postcode":"08004",
    "addr:street":"Carrer De Puig I Xoriguer",
    "iso:country":"ES",
    "sg:address":"Carrer de Puig I Xoriguer, 18",
    "sg:city":"Barcelona",
    "sg:orig_category":"Peluquer\u00cdas, Peluquer\u00cda Mixta",
    "sg:phone":"+34 934 41 18 79",
    "sg:postcode":"08004",
    "sg:province":"Barcelona",
    "wof:name":"Perez Sena Ligia",
    "wof:placetype":"venue"
},
  "geometry": {"coordinates":[2.1734321117,41.3737449646],"type":"Point"}
}