{
  "type": "Feature",
  "properties": {
    "iso:country":"ES",
    "sg:address":"Calle de Don Juan De Austria, 4",
    "sg:city":"Valencia",
    "sg:orig_category":"Ropa Para Ni\u00d1os (al Por Menor)",
    "sg:phone":"+34 963 52 90 58",
    "sg:postcode":"46002",
    "sg:province":"Valencia",
    "wof:name":"Abad Torres Asuncion",
    "wof:placetype":"venue"
},
  "geometry": {"coordinates":[-0.373695,39.470379],"type":"Point"}
}