{
  "type": "Feature",
  "properties": {
    "addr:full":"Avda Antonio Hurtado, 22 Caceres C\u00e1ceres 10002",
    "addr:housenumber":"22",
    "addr:postcode":"10002",
    "addr:street":"Avda Antonio Hurtado;Ca\u0301Ceres",
    "iso:country":"ES",
    "sg:address":"Avda Antonio Hurtado, 22",
    "sg:city":"Caceres",
    "sg:orig_category":"Muebles, Minoristas",
    "sg:phone":"+34 927 22 32 64",
    "sg:postcode":"10002",
    "sg:province":"C\u00e1ceres",
    "wof:name":"Muebles La Ganga S.l.",
    "wof:placetype":"venue"
},
  "geometry": {"coordinates":[-6.3767490387,39.4657707214],"type":"Point"}
}