{
  "type": "Feature",
  "properties": {
    "iso:country":"ES",
    "sg:address":"Pase Cerezos, 21",
    "sg:city":"Madrid",
    "sg:orig_category":"Agencias Y Agentes Comerciales, Representantes",
    "sg:phone":"+34 915 19 21 50",
    "sg:postcode":"28016",
    "sg:province":"Madrid",
    "wof:name":"Rocedem S.l.",
    "wof:placetype":"venue"
},
  "geometry": {"coordinates":[-3.6645340919,40.4553451538],"type":"Point"}
}