{
  "type": "Feature",
  "properties": {
    "addr:full":"V. Castillo, 13 Iru\u00f1a Navarra 31007",
    "addr:housenumber":"13",
    "addr:postcode":"31007",
    "addr:street":"V. Castillo",
    "iso:country":"ES",
    "sg:address":"V. Castillo, 13",
    "sg:city":"Iru\u00f1a",
    "sg:orig_category":"Seguridad Social",
    "sg:phone":"+34 948 27 04 40",
    "sg:postcode":"31007",
    "sg:province":"Navarra",
    "wof:name":"Fraternidad-muprespa Mutua De Accidentes De Trabajo Y Enfermedades Profesionales",
    "wof:placetype":"venue"
},
  "geometry": {"coordinates":[-1.6419249773,42.8169670105],"type":"Point"}
}