{
  "type": "Feature",
  "properties": {
    "addr:full":"Luga Diseminado El Sitjar, S/n Salt Girona 17190",
    "addr:housenumber":"s / n",
    "addr:postcode":"17190",
    "addr:street":"Luga Diseminado El Sitjar",
    "iso:country":"ES",
    "sg:address":"Luga Diseminado El Sitjar, S/n",
    "sg:city":"Salt",
    "sg:orig_category":"Semiller\u00cdas",
    "sg:phone":"+34 972 24 41 45",
    "sg:postcode":"17190",
    "sg:province":"Girona",
    "wof:name":"El Sitjar S.a.t.",
    "wof:placetype":"venue"
},
  "geometry": {"coordinates":[2.7923600674,41.9727516174],"type":"Point"}
}