{
  "type": "Feature",
  "properties": {
    "iso:country":"ES",
    "sg:address":"Av Iii, 70",
    "sg:city":"Albacete",
    "sg:orig_category":"Escotaduras, Torneados",
    "sg:phone":"+34 967 24 04 56",
    "sg:postcode":"02006",
    "sg:province":"Albacete",
    "wof:name":"Julian Y Hernandez C.b.",
    "wof:placetype":"venue"
},
  "geometry": {"coordinates":[-1.874483943,39.0174789429],"type":"Point"}
}