{
  "type": "Feature",
  "properties": {
    "addr:full":"Calle de Lladro Y Malli, 3 Valencia Valencia 46007",
    "addr:housenumber":"3",
    "addr:postcode":"46007",
    "addr:street":"Calle De Lladro Y Malli",
    "iso:country":"ES",
    "sg:address":"Calle de Lladro Y Malli, 3",
    "sg:city":"Valencia",
    "sg:orig_category":"Frutas, Legumbres Frescas Y Tempranas (al Por Menor)",
    "sg:phone":"+34 963 80 89 40",
    "sg:postcode":"46007",
    "sg:province":"Valencia",
    "wof:name":"Alvaro Hernandez Jose Ramon",
    "wof:placetype":"venue"
},
  "geometry": {"coordinates":[-0.3875871897,39.4623794556],"type":"Point"}
}