{
  "type": "Feature",
  "properties": {
    "iso:country":"ES",
    "sg:address":"Calle de Doctor Villalobos, 6",
    "sg:city":"Zamora",
    "sg:orig_category":"Autob\u00das (explotaci\u00d3n Y Servicios De)",
    "sg:phone":"+34 980 52 57 71",
    "sg:postcode":"49017",
    "sg:province":"Zamora",
    "wof:name":"Monsalvo Anton Bartolome",
    "wof:placetype":"venue"
},
  "geometry": {"coordinates":[-5.7368822098,41.5040512085],"type":"Point"}
}