{
  "type": "Feature",
  "properties": {
    "addr:full":"Avda Alcalde Gregorio Espino, 35 Vigo Pontevedra 36205",
    "addr:housenumber":"35",
    "addr:postcode":"36205",
    "addr:street":"Avda Alcalde Gregorio Espino",
    "iso:country":"ES",
    "sg:address":"Avda Alcalde Gregorio Espino, 35",
    "sg:city":"Vigo",
    "sg:orig_category":"Mec\u00c1nico Del Autom\u00d3vil",
    "sg:phone":"+34 986 27 13 32",
    "sg:postcode":"36205",
    "sg:province":"Pontevedra",
    "wof:name":"Automocion Axi\u00f1a S.l.",
    "wof:placetype":"venue"
},
  "geometry": {"coordinates":[-8.7068481445,42.2298049927],"type":"Point"}
}