{
  "type": "Feature",
  "properties": {
    "iso:country":"ES",
    "sg:address":"Calle de Basilio Paraiso, 24",
    "sg:city":"Madrid",
    "sg:orig_category":"Internados & Ense\u00d1anza Privada",
    "sg:phone":"+34 915 73 65 16",
    "sg:postcode":"28028",
    "sg:province":"Madrid",
    "wof:name":"Congregacion Hijas De La Caridad De San",
    "wof:placetype":"venue"
},
  "geometry": {"coordinates":[-3.6642150879,40.4213752747],"type":"Point"}
}