{
  "type": "Feature",
  "properties": {
    "iso:country":"ES",
    "sg:address":"Carrer de Raurich, 2",
    "sg:city":"S. Boi Llobregat",
    "sg:orig_category":"Reposter\u00cdas",
    "sg:phone":"+34 936 40 89 54",
    "sg:postcode":"08830",
    "sg:province":"Barcelona",
    "wof:name":"Silvestre Murla Julian",
    "wof:placetype":"venue"
},
  "geometry": {"coordinates":[2.0348200798,41.3460998535],"type":"Point"}
}