{
  "type": "Feature",
  "properties": {
    "addr:full":"Calle de Uria, 1 Luarca Asturias 33700",
    "addr:housenumber":"1",
    "addr:postcode":"33700",
    "addr:street":"Calle De Uria",
    "iso:country":"ES",
    "sg:address":"Calle de Uria, 1",
    "sg:city":"Luarca",
    "sg:orig_category":"Telas Y Sedas (al Por Menor)",
    "sg:phone":"+34 985 64 02 61",
    "sg:postcode":"33700",
    "sg:province":"Asturias",
    "wof:name":"Textiles Luarca S.l.",
    "wof:placetype":"venue"
},
  "geometry": {"coordinates":[-6.535220623,43.5435638428],"type":"Point"}
}