{
  "type": "Feature",
  "properties": {
    "iso:country":"ES",
    "sg:address":"Avda Jota (la), 46",
    "sg:city":"Zaragoza",
    "sg:orig_category":"Muebles Y Accesorios Para Cocinas Y Cuartos De Ba\u00d1o (al Por Menor)",
    "sg:phone":"+34 976 47 64 69",
    "sg:postcode":"50014",
    "sg:province":"Zaragoza",
    "wof:name":"Morata Mu\u00f1oz Maria Luisa",
    "wof:placetype":"venue"
},
  "geometry": {"coordinates":[-0.8580150008,41.6614723206],"type":"Point"}
}