{
  "type": "Feature",
  "properties": {
    "addr:full":"Calle de Obieta Kalea, 27 Erandio Vizcaya 48950",
    "addr:housenumber":"27",
    "addr:postcode":"48950",
    "addr:street":"Calle De Obieta Kalea",
    "iso:country":"ES",
    "sg:address":"Calle de Obieta Kalea, 27",
    "sg:city":"Erandio",
    "sg:orig_category":"Peluqueros: De Se\u00d1oras",
    "sg:phone":"+34 944 67 68 91",
    "sg:postcode":"48950",
    "sg:province":"Vizcaya",
    "wof:name":"Ignacio Vidal Castro Royo",
    "wof:placetype":"venue"
},
  "geometry": {"coordinates":[-2.97321105,43.3038787842],"type":"Point"}
}