{
  "type": "Feature",
  "properties": {
    "addr:full":"Calle de Ruiz De Alda, 2 Huelva Huelva 21002",
    "addr:housenumber":"2",
    "addr:postcode":"21002",
    "addr:street":"Calle De Ruiz De Alda",
    "iso:country":"ES",
    "sg:address":"Calle de Ruiz De Alda, 2",
    "sg:city":"Huelva",
    "sg:orig_category":"Organizaciones Profesionales",
    "sg:phone":"+34 959 25 00 81",
    "sg:postcode":"21002",
    "sg:province":"Huelva",
    "wof:name":"Nieto Lamas Ricardo",
    "wof:placetype":"venue"
},
  "geometry": {"coordinates":[-6.9531745911,37.2621803284],"type":"Point"}
}