{
  "type": "Feature",
  "properties": {
    "addr:full":"Carrer de Negrevernis, 11 Barcelona Barcelona 08034",
    "addr:housenumber":"11",
    "addr:postcode":"08034",
    "addr:street":"Carrer De Negrevernis",
    "iso:country":"ES",
    "sg:address":"Carrer de Negrevernis, 11",
    "sg:city":"Barcelona",
    "sg:orig_category":"M\u00c9dicos: Psiquiatr\u00cda",
    "sg:phone":"+34 932 05 13 80",
    "sg:postcode":"08034",
    "sg:province":"Barcelona",
    "wof:name":"Vaimberg Grillo Raul Horacio",
    "wof:placetype":"venue"
},
  "geometry": {"coordinates":[2.120855093,41.3989601135],"type":"Point"}
}