{
  "type": "Feature",
  "properties": {
    "addr:full":"Avda Espa\u00d1a, 126 Isla Cristina Huelva 21410",
    "addr:housenumber":"126",
    "addr:postcode":"21410",
    "addr:street":"Avda Espan\u0303A",
    "iso:country":"ES",
    "sg:address":"Avda Espa\u00d1a, 126",
    "sg:city":"Isla Cristina",
    "sg:orig_category":"Cajas Para Embalar",
    "sg:phone":"+34 959 34 44 66",
    "sg:postcode":"21410",
    "sg:province":"Huelva",
    "wof:name":"Caja Rural Del Sur Sociedad Cooperativa",
    "wof:placetype":"venue"
},
  "geometry": {"coordinates":[-7.3197760582,37.1994552612],"type":"Point"}
}