{
  "type": "Feature",
  "properties": {
    "iso:country":"ES",
    "sg:address":"Calle de Puerta De Sevilla, 69",
    "sg:city":"Aroche",
    "sg:orig_category":"Mec\u00c1nico Del Autom\u00d3vil",
    "sg:phone":"+34 959 14 00 75",
    "sg:postcode":"21240",
    "sg:province":"Huelva",
    "wof:name":"Vazquez Zarza Antonio",
    "wof:placetype":"venue"
},
  "geometry": {"coordinates":[-6.9510030746,37.9434967041],"type":"Point"}
}