{
  "type": "Feature",
  "properties": {
    "iso:country":"ES",
    "sg:address":"Carrer de Ronda Sud, 21",
    "sg:city":"Crevillent",
    "sg:orig_category":"Promotores Constructores",
    "sg:phone":"+34 965 40 40 20",
    "sg:postcode":"03330",
    "sg:province":"Alicante",
    "wof:name":"Edificaciones Loreme Sl",
    "wof:placetype":"venue"
},
  "geometry": {"coordinates":[-0.8076789975,38.2441482544],"type":"Point"}
}