{
  "type": "Feature",
  "properties": {
    "addr:full":"Calle de Viar, 6 Carmona Sevilla 41410",
    "addr:housenumber":"6",
    "addr:postcode":"41410",
    "addr:street":"Calle De Viar",
    "iso:country":"ES",
    "sg:address":"Calle de Viar, 6",
    "sg:city":"Carmona",
    "sg:orig_category":"Maquinaria Para Industrias Diversas",
    "sg:phone":"+34 954 14 13 66",
    "sg:postcode":"41410",
    "sg:province":"Sevilla",
    "wof:name":"Cortazar Rodriguez Jose",
    "wof:placetype":"venue"
},
  "geometry": {"coordinates":[-5.6462039948,37.4729270935],"type":"Point"}
}