{
  "type": "Feature",
  "properties": {
    "iso:country":"ES",
    "sg:address":"Calle de Garcia Mas, 14",
    "sg:city":"Albacete",
    "sg:orig_category":"Contenedores (mercanc\u00cdas)",
    "sg:phone":"+34 967 23 69 38",
    "sg:postcode":"02005",
    "sg:province":"Albacete",
    "wof:name":"Cutanda Gutierrez Manuel Javier",
    "wof:placetype":"venue"
},
  "geometry": {"coordinates":[-1.8626079559,38.997543335],"type":"Point"}
}