{
  "type": "Feature",
  "properties": {
    "iso:country":"ES",
    "sg:address":"Pase Sancha, 12",
    "sg:city":"Malaga",
    "sg:orig_category":"Peluquer\u00cdas, Peluquer\u00cda Mixta",
    "sg:phone":"+34 952 21 15 74",
    "sg:postcode":"29016",
    "sg:province":"M\u00e1laga",
    "wof:name":"Fernandez Morales Juan Jose",
    "wof:placetype":"venue"
},
  "geometry": {"coordinates":[-4.4040379524,36.721534729],"type":"Point"}
}