{
  "type": "Feature",
  "properties": {
    "addr:full":"Esp\u00edritu Santo Alto, 24 Baza Granada 18800",
    "addr:postcode":"18800",
    "iso:country":"ES",
    "sg:address":"Esp\u00edritu Santo Alto, 24",
    "sg:city":"Baza",
    "sg:orig_category":"Industria Qu\u00cdmica",
    "sg:phone":"+34 958 70 18 98",
    "sg:postcode":"18800",
    "sg:province":"Granada",
    "wof:name":"Vidal Espin Mariano",
    "wof:placetype":"venue"
},
  "geometry": {"coordinates":[-2.7704100609,37.4930000305],"type":"Point"}
}