{
  "type": "Feature",
  "properties": {
    "iso:country":"ES",
    "sg:address":"Calle de Acosta, 4",
    "sg:city":"Hormilla",
    "sg:orig_category":"Farmacias",
    "sg:phone":"+34 941 41 78 95",
    "sg:postcode":"26223",
    "sg:province":"La Rioja",
    "wof:name":"Fernandez Santos Felix Miguel",
    "wof:placetype":"venue"
},
  "geometry": {"coordinates":[-2.7756140232,42.4379234314],"type":"Point"}
}