{
  "type": "Feature",
  "properties": {
    "iso:country":"ES",
    "sg:address":"Carrer de Ramon Moncada, 38",
    "sg:city":"Santa Pon\u00c7a",
    "sg:orig_category":"Productores Recolectores, Venta Directa De Vinos",
    "sg:phone":"+34 971 69 46 02",
    "sg:postcode":"07180",
    "sg:province":"Islas Baleares",
    "wof:name":"Garcia Sanchez Luis",
    "wof:placetype":"venue"
},
  "geometry": {"coordinates":[2.4837698936,39.5131607056],"type":"Point"}
}