{
  "type": "Feature",
  "properties": {
    "iso:country":"ES",
    "sg:address":"Calle de Pablo Sarasate, 31",
    "sg:city":"Corella",
    "sg:orig_category":"Madera Para Construcci\u00d3n E Industria",
    "sg:phone":"+34 948 40 14 47",
    "sg:postcode":"31591",
    "sg:province":"Navarra",
    "wof:name":"Frances Sanz Jesus",
    "wof:placetype":"venue"
},
  "geometry": {"coordinates":[-1.7882390022,42.1167106628],"type":"Point"}
}