{
  "type": "Feature",
  "properties": {
    "addr:full":"Calle de Libertad, S/n Carrion Calatrava Ciudad Real 13150",
    "addr:housenumber":"s / n",
    "addr:postcode":"13150",
    "addr:street":"Calle De Libertad",
    "iso:country":"ES",
    "sg:address":"Calle de Libertad, S/n",
    "sg:city":"Carrion Calatrava",
    "sg:orig_category":"Sanatorios M\u00c9dico",
    "sg:phone":"+34 926 81 52 11",
    "sg:postcode":"13150",
    "sg:province":"Ciudad Real",
    "wof:name":"Servicio De Salud De Castilla La Mancha",
    "wof:placetype":"venue"
},
  "geometry": {"coordinates":[-3.8158810139,39.0161056519],"type":"Point"}
}