{
  "type": "Feature",
  "properties": {
    "addr:full":"Calle de Cortes De Aragon, 57 Zaragoza Zaragoza 50005",
    "addr:housenumber":"57",
    "addr:postcode":"50005",
    "addr:street":"Calle De Cortes De Aragon",
    "iso:country":"ES",
    "sg:address":"Calle de Cortes De Aragon, 57",
    "sg:city":"Zaragoza",
    "sg:orig_category":"Inform\u00c1tica: Soportes De Informaci\u00d3n, Suministros & Accesorios",
    "sg:phone":"+34 976 56 89 12",
    "sg:postcode":"50005",
    "sg:province":"Zaragoza",
    "wof:name":"Gil Madurga Milagros",
    "wof:placetype":"venue"
},
  "geometry": {"coordinates":[-0.8946681023,41.6428451538],"type":"Point"}
}