{
  "type": "Feature",
  "properties": {
    "addr:full":"Calle de Tauro, 106 Palmas De Gran Canaria Las Palmas 35009",
    "addr:housenumber":"106",
    "addr:postcode":"35009",
    "addr:street":"Calle De Tauro",
    "iso:country":"ES",
    "sg:address":"Calle de Tauro, 106",
    "sg:city":"Palmas De Gran Canaria",
    "sg:orig_category":"Sonorizaci\u00d3n, Iluminaci\u00d3n Para Cine, Teatro Y Discotecas (al Por Mayor, Al Por Menor)",
    "sg:phone":"+34 928 46 48 59",
    "sg:postcode":"35009",
    "sg:province":"Las Palmas",
    "wof:name":"Perez Aguilar Manuel Rafael",
    "wof:placetype":"venue"
},
  "geometry": {"coordinates":[-15.4229192734,28.1509056091],"type":"Point"}
}