{
  "type": "Feature",
  "properties": {
    "iso:country":"ES",
    "sg:address":"Calle de Bami, 33",
    "sg:city":"Sevilla",
    "sg:orig_category":"Internados & Ense\u00d1anza Privada",
    "sg:phone":"+34 954 62 07 11",
    "sg:postcode":"41013",
    "sg:province":"Sevilla",
    "wof:name":"Instituto De La Bienaventurada Virgen Maria",
    "wof:placetype":"venue"
},
  "geometry": {"coordinates":[-5.9778552055,37.3578834534],"type":"Point"}
}