{
  "type": "Feature",
  "properties": {
    "iso:country":"ES",
    "sg:address":"Carrer de Mina, 7",
    "sg:city":"Hospitalet Llobregat",
    "sg:orig_category":"T\u00c9cnicos Veterinarios",
    "sg:phone":"+34 934 38 44 74",
    "sg:postcode":"08906",
    "sg:province":"Barcelona",
    "wof:name":"Martinez Alcaraz David",
    "wof:placetype":"venue"
},
  "geometry": {"coordinates":[2.1014618874,41.37241745],"type":"Point"}
}