{
  "type": "Feature",
  "properties": {
    "iso:country":"ES",
    "sg:address":"Avda. Cruz, 37",
    "sg:city":"Combarro",
    "sg:orig_category":"Pescader\u00cdas (al Por Menor)",
    "sg:phone":"+34 986 77 00 07",
    "sg:postcode":"36993",
    "sg:province":"Pontevedra",
    "wof:name":"Pescaderia A Ria S.l.",
    "wof:placetype":"venue"
},
  "geometry": {"coordinates":[-8.6917266846,42.4410018921],"type":"Point"}
}