{
  "type": "Feature",
  "properties": {
    "addr:full":"Calle de San Francisco, 2 Enguera Valencia 46810",
    "addr:housenumber":"2",
    "addr:postcode":"46810",
    "addr:street":"Calle De San Francisco",
    "iso:country":"ES",
    "sg:address":"Calle de San Francisco, 2",
    "sg:city":"Enguera",
    "sg:orig_category":"Serrer\u00cdas De Madera",
    "sg:phone":"+34 962 22 55 21",
    "sg:postcode":"46810",
    "sg:province":"Valencia",
    "wof:name":"Ferri Moll Juan Jose",
    "wof:placetype":"venue"
},
  "geometry": {"coordinates":[-0.6866480112,38.9805488586],"type":"Point"}
}