{
  "type": "Feature",
  "properties": {
    "iso:country":"ES",
    "sg:address":"Ptda Lo Blanc, 31",
    "sg:city":"Los Montesinos",
    "sg:orig_category":"Soportes L\u00d3gicos, Programas Integradores De Aplicaciones (progiciels)",
    "sg:phone":"+34 966 72 19 21",
    "sg:postcode":"03187",
    "sg:province":"Alicante",
    "wof:name":"Alimentacion, Vinos Y Bebidas S L",
    "wof:placetype":"venue"
},
  "geometry": {"coordinates":[-0.7627879977,38.0289344788],"type":"Point"}
}