{
  "type": "Feature",
  "properties": {
    "iso:country":"ES",
    "sg:address":"Cami Coma Lliris, S/n",
    "sg:city":"Balaguer",
    "sg:orig_category":"Fabricaci\u00d3n De Productos L\u00c1cteos Y Derivados",
    "sg:phone":"+34 973 45 01 52",
    "sg:postcode":"25600",
    "sg:province":"Lleida",
    "wof:name":"Danone S.a.",
    "wof:placetype":"venue"
},
  "geometry": {"coordinates":[0.7989240289,41.7801971436],"type":"Point"}
}