{
  "type": "Feature",
  "properties": {
    "addr:full":"Calle de Ramon Jimenez, 9 Pozuelo De Alarcon Madrid 28223",
    "addr:housenumber":"9",
    "addr:postcode":"28223",
    "addr:street":"Calle De Ramon Jimenez",
    "iso:country":"ES",
    "sg:address":"Calle de Ramon Jimenez, 9",
    "sg:city":"Pozuelo De Alarcon",
    "sg:orig_category":"Centros Empresariales",
    "sg:phone":"+34 917 99 11 97",
    "sg:postcode":"28223",
    "sg:province":"Madrid",
    "wof:name":"Trikadica S.l.",
    "wof:placetype":"venue"
},
  "geometry": {"coordinates":[-3.815073967,40.4350776672],"type":"Point"}
}