{
  "type": "Feature",
  "properties": {
    "iso:country":"ES",
    "sg:address":"Calle de Constitucion, 10",
    "sg:city":"Valladolid",
    "sg:orig_category":"Arquitectos",
    "sg:phone":"+34 983 39 91 94",
    "sg:postcode":"47001",
    "sg:province":"Valladolid",
    "wof:name":"Arki-polis S.l",
    "wof:placetype":"venue"
},
  "geometry": {"coordinates":[-4.7271227837,41.6511802673],"type":"Point"}
}