{
  "type": "Feature",
  "properties": {
    "addr:full":"Santamaria-andre Mari Kalea, 17 Ordizia Guip\u00f9zcoa 20240",
    "addr:housenumber":"17",
    "addr:postcode":"20240",
    "addr:street":"Mari Kalea;Guipu\u0300Zcoa",
    "iso:country":"ES",
    "sg:address":"Santamaria-andre Mari Kalea, 17",
    "sg:city":"Ordizia",
    "sg:orig_category":"Ropa Para Se\u00d1oras Y Caballeros (al Por Menor)",
    "sg:phone":"+34 943 88 12 20",
    "sg:postcode":"20240",
    "sg:province":"Guip\u00f9zcoa",
    "wof:name":"Ajuria Vicu\u00f1a Alberto",
    "wof:placetype":"venue"
},
  "geometry": {"coordinates":[-2.1773040295,43.0538711548],"type":"Point"}
}