{
  "type": "Feature",
  "properties": {
    "iso:country":"ES",
    "sg:address":"Calle de San Bernardo, 21",
    "sg:city":"Peal Becerro",
    "sg:orig_category":"Electricidad: Instaladores",
    "sg:phone":"+34 953 73 02 43",
    "sg:postcode":"23460",
    "sg:province":"Ja\u00e9n",
    "wof:name":"Soria Perez Angel",
    "wof:placetype":"venue"
},
  "geometry": {"coordinates":[-3.1217041016,37.9136810303],"type":"Point"}
}