{
  "type": "Feature",
  "properties": {
    "iso:country":"ES",
    "sg:address":"Calle de Pelayo, 56",
    "sg:city":"Madrid",
    "sg:orig_category":"Empresas De Limpieza",
    "sg:phone":"+34 913 19 61 44",
    "sg:postcode":"28004",
    "sg:province":"Madrid",
    "wof:name":"Contrataciones Segovia S. L.",
    "wof:placetype":"venue"
},
  "geometry": {"coordinates":[-3.6974389553,40.4239654541],"type":"Point"}
}