{
  "type": "Feature",
  "properties": {
    "addr:full":"Carrer de Juan De La Cierva, 52 Castelldefels Barcelona 08860",
    "addr:housenumber":"52",
    "addr:postcode":"08860",
    "addr:street":"Carrer De Juan De La Cierva",
    "iso:country":"ES",
    "sg:address":"Carrer de Juan De La Cierva, 52",
    "sg:city":"Castelldefels",
    "sg:orig_category":"Papeler\u00cdas, Librer\u00cdas",
    "sg:phone":"+34 936 65 65 50",
    "sg:postcode":"08860",
    "sg:province":"Barcelona",
    "wof:name":"Padilla Linehan Patricia",
    "wof:placetype":"venue"
},
  "geometry": {"coordinates":[1.9812450409,41.2855682373],"type":"Point"}
}