{
  "type": "Feature",
  "properties": {
    "iso:country":"ES",
    "sg:address":"Avda Costa Blanca, 117",
    "sg:city":"Alacant",
    "sg:orig_category":"Telas Y Sedas (al Por Menor)",
    "sg:phone":"+34 965 26 37 90",
    "sg:postcode":"03540",
    "sg:province":"Alicante",
    "wof:name":"Saez Molto Cristina",
    "wof:placetype":"venue"
},
  "geometry": {"coordinates":[-0.412225008,38.3693122864],"type":"Point"}
}