{
  "type": "Feature",
  "properties": {
    "addr:full":"Avda Guijar (del), 37 Arganda Madrid 28500",
    "addr:housenumber":"37",
    "addr:postcode":"28500",
    "addr:street":"Avda Guijar Del",
    "iso:country":"ES",
    "sg:address":"Avda Guijar (del), 37",
    "sg:city":"Arganda",
    "sg:classifiers":[
        {
            "category":"Manufacturing",
            "subcategory":"Building Materials",
            "type":"Manufacturing & Wholesale Goods"
        }
    ],
    "sg:phone":"+34 918 70 34 86",
    "sg:postcode":"28500",
    "sg:province":"Madrid",
    "sg:tags":[
        "cemento",
        "y",
        "de",
        "fabricaci\u00d3n",
        "cal"
    ],
    "wof:name":"Pumacen S.l",
    "wof:placetype":"venue"
},
  "geometry": {"coordinates":[-3.457750082,40.3145637512],"type":"Point"}
}