{
  "type": "Feature",
  "properties": {
    "addr:full":"Calle de Rondilla Santa Teresa, 17 Valladolid Valladolid 47010",
    "addr:housenumber":"17",
    "addr:postcode":"47010",
    "addr:street":"Calle De Rondilla Santa Teresa",
    "iso:country":"ES",
    "sg:address":"Calle de Rondilla Santa Teresa, 17",
    "sg:city":"Valladolid",
    "sg:orig_category":"Reposter\u00cdas",
    "sg:phone":"+34 983 35 41 37",
    "sg:postcode":"47010",
    "sg:province":"Valladolid",
    "wof:name":"Perez Gonzalez Maria Cristina",
    "wof:placetype":"venue"
},
  "geometry": {"coordinates":[-4.7284297943,41.6598358154],"type":"Point"}
}