{
  "type": "Feature",
  "properties": {
    "addr:full":"Avda Madariaga, 1 Bilbao Vizcaya 48014",
    "addr:housenumber":"1",
    "addr:postcode":"48014",
    "addr:street":"Avda Madariaga",
    "iso:country":"ES",
    "sg:address":"Avda Madariaga, 1",
    "sg:city":"Bilbao",
    "sg:orig_category":"Inform\u00c1tica (estudios, Servicios, Asesor\u00cda, Formaci\u00d3n)",
    "sg:phone":"+34 944 75 19 10",
    "sg:postcode":"48014",
    "sg:province":"Vizcaya",
    "wof:name":"Agmsoft Consulting, S.l.",
    "wof:placetype":"venue"
},
  "geometry": {"coordinates":[-2.9517939091,43.2709770203],"type":"Point"}
}