{
  "type": "Feature",
  "properties": {
    "addr:full":"Av Sant Ferran, 36 Palma Islas Baleares 07013",
    "addr:housenumber":"36",
    "addr:postcode":"07013",
    "addr:street":"Av Sant Ferran",
    "iso:country":"ES",
    "sg:address":"Av Sant Ferran, 36",
    "sg:city":"Palma",
    "sg:orig_category":"Agencias De Viajes",
    "sg:phone":"+34 971 73 75 78",
    "sg:postcode":"07013",
    "sg:province":"Islas Baleares",
    "sg:website":"www.halconviajes.com",
    "wof:name":"Viajes Halcon S.a.",
    "wof:placetype":"venue"
},
  "geometry": {"coordinates":[2.6345419884,39.5784759521],"type":"Point"}
}