{
  "type": "Feature",
  "properties": {
    "addr:full":"Calle de Diodoro, 9 Malaga M\u00e1laga 29006",
    "addr:housenumber":"9",
    "addr:postcode":"29006",
    "addr:street":"Calle De Diodoro;Ma\u0301Laga",
    "iso:country":"ES",
    "sg:address":"Calle de Diodoro, 9",
    "sg:city":"Malaga",
    "sg:orig_category":"Ferreter\u00cda (diversos)",
    "sg:phone":"+34 952 17 82 08",
    "sg:postcode":"29006",
    "sg:province":"M\u00e1laga",
    "wof:name":"Ferrallados Jofran S.l",
    "wof:placetype":"venue"
},
  "geometry": {"coordinates":[-4.5146818161,36.7050437927],"type":"Point"}
}