{
  "type": "Feature",
  "properties": {
    "addr:full":"Pedra Do Sal, 95 Pedra Do Sal La Coru\u00f1a 15105",
    "addr:housenumber":"95",
    "addr:postcode":"15105",
    "addr:street":"Pedra;Pedra;Corun\u0303A",
    "iso:country":"ES",
    "sg:address":"Pedra Do Sal, 95",
    "sg:city":"Pedra Do Sal",
    "sg:orig_category":"Comercio De Minerales, F\u00d3siles Y Conchas",
    "sg:phone":"+34 981 73 95 73",
    "sg:postcode":"15105",
    "sg:province":"La Coru\u00f1a",
    "wof:name":"A\u00f1on Esmoris Francisco Jose",
    "wof:placetype":"venue"
},
  "geometry": {"coordinates":[-8.605348587,43.3203735352],"type":"Point"}
}