{
  "type": "Feature",
  "properties": {
    "addr:full":"Calle de Doctor Guijarro, 8 Requena Valencia 46340",
    "addr:housenumber":"8",
    "addr:postcode":"46340",
    "addr:street":"Calle De Doctor Guijarro",
    "iso:country":"ES",
    "sg:address":"Calle de Doctor Guijarro, 8",
    "sg:city":"Requena",
    "sg:orig_category":"Ingenier\u00cda, Centros De Estudios (diversos)",
    "sg:phone":"+34 962 30 31 78",
    "sg:postcode":"46340",
    "sg:province":"Valencia",
    "wof:name":"Enlucidosy Proyectos Requena S.l.",
    "wof:placetype":"venue"
},
  "geometry": {"coordinates":[-1.1065995693,39.4892807007],"type":"Point"}
}