{
  "type": "Feature",
  "properties": {
    "addr:full":"Calle de Rio Deba, 8 Donostia-san Sebastian Guip\u00f9zcoa 20012",
    "addr:housenumber":"8",
    "addr:postcode":"20012",
    "addr:street":"Calle De Rio Deba",
    "iso:country":"ES",
    "sg:address":"Calle de Rio Deba, 8",
    "sg:city":"Donostia-san Sebastian",
    "sg:orig_category":"Empresas De Pintura Y Revestimientos",
    "sg:phone":"+34 943 28 38 08",
    "sg:postcode":"20012",
    "sg:province":"Guip\u00f9zcoa",
    "wof:name":"Berrio Hernaiz Emilio",
    "wof:placetype":"venue"
},
  "geometry": {"coordinates":[-1.969113946,43.3164329529],"type":"Point"}
}