{
  "type": "Feature",
  "properties": {
    "addr:full":"Avda Santander, 23 Palencia Palencia 34003",
    "addr:housenumber":"23",
    "addr:postcode":"34003",
    "addr:street":"Avda Santander",
    "iso:country":"ES",
    "sg:address":"Avda Santander, 23",
    "sg:city":"Palencia",
    "sg:orig_category":"Bancos",
    "sg:phone":"+34 979 74 96 44",
    "sg:postcode":"34003",
    "sg:province":"Palencia",
    "sg:website":"www.bancocastilla.es",
    "wof:name":"Banco De Castilla",
    "wof:placetype":"venue"
},
  "geometry": {"coordinates":[-4.5313038826,42.0176048279],"type":"Point"}
}