{
  "type": "Feature",
  "properties": {
    "iso:country":"ES",
    "sg:address":"Finc Boyero El, S/n",
    "sg:city":"Villablanca",
    "sg:orig_category":"Producci\u00d3n, Venta De Productos De Agricultura Biol\u00d3gica",
    "sg:phone":"+34 959 50 20 21",
    "sg:postcode":"21590",
    "sg:province":"Huelva",
    "wof:name":"Jemysa Agricola S.a.",
    "wof:placetype":"venue"
},
  "geometry": {"coordinates":[-7.3429589272,37.3055267334],"type":"Point"}
}