{
  "type": "Feature",
  "properties": {
    "iso:country":"ES",
    "sg:address":"Av Constitucio, 133",
    "sg:city":"Castelldefels",
    "sg:orig_category":"Librer\u00cdas",
    "sg:phone":"+34 936 65 14 38",
    "sg:postcode":"08860",
    "sg:province":"Barcelona",
    "wof:name":"Canillo Botinas Jordi",
    "wof:placetype":"venue"
},
  "geometry": {"coordinates":[1.9779100418,41.2788085938],"type":"Point"}
}