{
  "type": "Feature",
  "properties": {
    "addr:full":"Avda Emilio Castelar, 113 S. Pedro Pinatar Murcia 30740",
    "addr:housenumber":"113",
    "addr:postcode":"30740",
    "addr:street":"Avda Emilio Castelar",
    "iso:country":"ES",
    "sg:address":"Avda Emilio Castelar, 113",
    "sg:city":"S. Pedro Pinatar",
    "sg:orig_category":"Inmobiliaria (agencias)",
    "sg:phone":"+34 968 18 17 31",
    "sg:postcode":"30740",
    "sg:province":"Murcia",
    "wof:name":"Rodriguez Alcaina Jose Antonio",
    "wof:placetype":"venue"
},
  "geometry": {"coordinates":[-0.7868030071,37.8277664185],"type":"Point"}
}