{
  "type": "Feature",
  "properties": {
    "iso:country":"ES",
    "sg:address":"Calle de Periodista Quesada Chacon, 1",
    "sg:city":"Cordoba",
    "sg:orig_category":"Agencias Y Agentes Comerciales, Representantes",
    "sg:phone":"+34 957 23 20 98",
    "sg:postcode":"14005",
    "sg:province":"C\u00f3rdoba",
    "wof:name":"Elias Caraba\u00f1o Antonio",
    "wof:placetype":"venue"
},
  "geometry": {"coordinates":[-4.7959308624,37.8845024109],"type":"Point"}
}