{
  "type": "Feature",
  "properties": {
    "iso:country":"ES",
    "sg:address":"Plaz Corredera, 21",
    "sg:city":"Cazorla",
    "sg:orig_category":"Vinos Y Licores (venta Al Por Menor)",
    "sg:phone":"+34 953 72 02 58",
    "sg:postcode":"23470",
    "sg:province":"Ja\u00e9n",
    "wof:name":"Real Mata Jose Del",
    "wof:placetype":"venue"
},
  "geometry": {"coordinates":[-3.002779007,37.9112014771],"type":"Point"}
}