{
  "type": "Feature",
  "properties": {
    "iso:country":"ES",
    "sg:address":"Carr Lluis Besa, 25",
    "sg:city":"Lleida",
    "sg:orig_category":"Perfumer\u00cda (al Por Menor)",
    "sg:phone":"+34 973 26 76 19",
    "sg:postcode":"25002",
    "sg:province":"Lleida",
    "wof:name":"Morell Costa Ramon",
    "wof:placetype":"venue"
},
  "geometry": {"coordinates":[0.6218339801,41.6128921509],"type":"Point"}
}