{
  "type": "Feature",
  "properties": {
    "addr:full":"Rond Calvari (del), S/n Algemesi Valencia 46680",
    "addr:housenumber":"/ n",
    "addr:postcode":"46680",
    "addr:street":"S",
    "iso:country":"ES",
    "sg:address":"Rond Calvari (del), S/n",
    "sg:city":"Algemesi",
    "sg:orig_category":"M\u00c1rmoles, Granitos Y Piedras Naturales",
    "sg:phone":"+34 962 48 44 67",
    "sg:postcode":"46680",
    "sg:province":"Valencia",
    "wof:name":"Marmoles Costa-valencia S.l.",
    "wof:placetype":"venue"
},
  "geometry": {"coordinates":[-0.4404140115,39.193561554],"type":"Point"}
}