{
  "type": "Feature",
  "properties": {
    "iso:country":"ES",
    "sg:address":"Carrer de Maria Auxiliadora, 19",
    "sg:city":"Barcelona",
    "sg:orig_category":"Tapicer\u00cdas",
    "sg:phone":"+34 932 03 05 36",
    "sg:postcode":"08017",
    "sg:province":"Barcelona",
    "wof:name":"Garcia Garcia Gines",
    "wof:placetype":"venue"
},
  "geometry": {"coordinates":[2.1291439533,41.3948135376],"type":"Point"}
}