{
  "type": "Feature",
  "properties": {
    "iso:country":"ES",
    "sg:address":"Calle de Duque De Ahumada, 5",
    "sg:city":"Laredo",
    "sg:orig_category":"Ense\u00d1anza Secundaria: Colegios Y Escuelas Privadas",
    "sg:phone":"+34 942 60 51 31",
    "sg:postcode":"39770",
    "sg:province":"Cantabria",
    "wof:name":"Instituto Nacional Ense\u00d1anza Media",
    "wof:placetype":"venue"
},
  "geometry": {"coordinates":[-3.4137055874,43.4093894958],"type":"Point"}
}