{
  "type": "Feature",
  "properties": {
    "addr:full":"Carr Bonico, 35 Salines Islas Baleares 07640",
    "addr:housenumber":"35",
    "addr:postcode":"07640",
    "addr:street":"Carr Bonico",
    "iso:country":"ES",
    "sg:address":"Carr Bonico, 35",
    "sg:city":"Salines",
    "sg:orig_category":"Psic\u00d3logos",
    "sg:phone":"+34 971 64 97 14",
    "sg:postcode":"07640",
    "sg:province":"Islas Baleares",
    "wof:name":"Mestre Sabater Margarita",
    "wof:placetype":"venue"
},
  "geometry": {"coordinates":[3.0467898846,39.3404006958],"type":"Point"}
}