{
  "type": "Feature",
  "properties": {
    "addr:full":"Carrer de Joanot Martorell, 5 Sabadell Barcelona 08203",
    "addr:housenumber":"5",
    "addr:postcode":"08203",
    "addr:street":"Carrer De Joanot Martorell",
    "iso:country":"ES",
    "sg:address":"Carrer de Joanot Martorell, 5",
    "sg:city":"Sabadell",
    "sg:orig_category":"Asesor\u00cda Sobre Comunicaci\u00d3n De Empresas",
    "sg:phone":"+34 937 10 44 84",
    "sg:postcode":"08203",
    "sg:province":"Barcelona",
    "wof:name":"A.t.f. Assessors Tecnics Formatius S.l.",
    "wof:placetype":"venue"
},
  "geometry": {"coordinates":[2.1048760414,41.5351028442],"type":"Point"}
}