{
  "type": "Feature",
  "properties": {
    "iso:country":"ES",
    "sg:address":"Carr Camprodon, 28",
    "sg:city":"Arbucies",
    "sg:orig_category":"Cajas De Ahorro",
    "sg:phone":"+34 972 86 00 02",
    "sg:postcode":"17401",
    "sg:province":"Girona",
    "sg:website":"www.lacaixa.es",
    "wof:name":"Caixa D'estalvis I Pensions De Barcelona",
    "wof:placetype":"venue"
},
  "geometry": {"coordinates":[2.5159409046,41.8157997131],"type":"Point"}
}