{
  "type": "Feature",
  "properties": {
    "addr:full":"Trva Arteixo, 270 Arteixo La Coru\u00f1a 15142",
    "addr:housenumber":"270",
    "addr:postcode":"15142",
    "addr:street":"Trva Arteixo;La Corun\u0303A",
    "iso:country":"ES",
    "sg:address":"Trva Arteixo, 270",
    "sg:city":"Arteixo",
    "sg:orig_category":"Ropa Y Art\u00cdculos Pre",
    "sg:phone":"+34 981 64 02 90",
    "sg:postcode":"15142",
    "sg:province":"La Coru\u00f1a",
    "wof:name":"A Tenda De Uxia",
    "wof:placetype":"venue"
},
  "geometry": {"coordinates":[-8.5171804428,43.3106918335],"type":"Point"}
}