{
  "type": "Feature",
  "properties": {
    "addr:full":"Ctra. Reus-vinyols, Km. 0006,0 Riudoms Tarragona 43330",
    "addr:postcode":"43330",
    "addr:street":"Ctra. Reus-Vinyols Km. 0006,0",
    "iso:country":"ES",
    "sg:address":"Ctra. Reus-vinyols, Km. 0006,0",
    "sg:city":"Riudoms",
    "sg:orig_category":"Fabricaci\u00d3n De Bebidas No Alcoh\u00d3licas",
    "sg:phone":"+34 977 85 03 00",
    "sg:postcode":"43330",
    "sg:province":"Tarragona",
    "sg:website":"www.concentradospalleja.com",
    "wof:name":"Concentrados Palleja S.l.",
    "wof:placetype":"venue"
},
  "geometry": {"coordinates":[1.0541909933,41.1382713318],"type":"Point"}
}