{
  "type": "Feature",
  "properties": {
    "addr:full":"Carrer de Joan Antoni Samaranch, 18 Sant Feliu Llobregat Barcelona 08980",
    "addr:housenumber":"18",
    "addr:postcode":"08980",
    "addr:street":"Carrer De Joan Antoni Samaranch",
    "iso:country":"ES",
    "sg:address":"Carrer de Joan Antoni Samaranch, 18",
    "sg:city":"Sant Feliu Llobregat",
    "sg:orig_category":"Molduras, Junquillos, Listones Y Molduras Perforadas",
    "sg:phone":"+34 936 66 22 21",
    "sg:postcode":"08980",
    "sg:province":"Barcelona",
    "wof:name":"Fernandez Barroso Antonio",
    "wof:placetype":"venue"
},
  "geometry": {"coordinates":[2.0400381088,41.381401062],"type":"Point"}
}