{
  "type": "Feature",
  "properties": {
    "iso:country":"ES",
    "sg:address":"Calle de Corredera De San Marcos, 33",
    "sg:city":"Linares",
    "sg:orig_category":"Radiocomunicaciones, Telefon\u00cda M\u00d3vil, Radiomensajer\u00cda: Servicios, Comercializaci\u00d3n",
    "sg:phone":"+34 953 60 67 67",
    "sg:postcode":"23700",
    "sg:province":"Ja\u00e9n",
    "wof:name":"Oleo Motor S.l.",
    "wof:placetype":"venue"
},
  "geometry": {"coordinates":[-3.6338086128,38.0970726013],"type":"Point"}
}