{
  "type": "Feature",
  "properties": {
    "addr:full":"Av Abat Marcet, 354 Terrassa Barcelona 08225",
    "addr:housenumber":"354",
    "addr:postcode":"08225",
    "addr:street":"Av Abat Marcet",
    "iso:country":"ES",
    "sg:address":"Av Abat Marcet, 354",
    "sg:city":"Terrassa",
    "sg:orig_category":"Contenedores (mercanc\u00cdas)",
    "sg:phone":"+34 937 88 94 39",
    "sg:postcode":"08225",
    "sg:province":"Barcelona",
    "wof:name":"Ramirez Ortiz Bartolome",
    "wof:placetype":"venue"
},
  "geometry": {"coordinates":[2.0037469864,41.5743026733],"type":"Point"}
}