{
  "type": "Feature",
  "properties": {
    "iso:country":"ES",
    "sg:address":"Cmno Igara De, 19",
    "sg:city":"Donostia-san Sebastian",
    "sg:orig_category":"Molduras, Junquillos, Listones Y Molduras Perforadas",
    "sg:phone":"+34 943 21 80 78",
    "sg:postcode":"20018",
    "sg:province":"Guip\u00f9zcoa",
    "wof:name":"Arocena Altuna Jose Francisco",
    "wof:placetype":"venue"
},
  "geometry": {"coordinates":[-2.0092580318,43.3019065857],"type":"Point"}
}