{
  "type": "Feature",
  "properties": {
    "iso:country":"ES",
    "sg:address":"Plaz Nueva, 3",
    "sg:city":"Bilbao",
    "sg:orig_category":"Peluqueros: De Se\u00d1oras",
    "sg:phone":"+34 944 15 26 26",
    "sg:postcode":"48005",
    "sg:province":"Vizcaya",
    "wof:name":"Ipi\u00f1a Arazosa Felix",
    "wof:placetype":"venue"
},
  "geometry": {"coordinates":[-2.9251329899,43.2587203979],"type":"Point"}
}