{
  "type": "Feature",
  "properties": {
    "addr:full":"Carrer de Major (sant Celoni), 95 S. Celoni Barcelona 08470",
    "addr:housenumber":"95",
    "addr:postcode":"08470",
    "addr:street":"Carrer De Major Sant Celoni;S. Celoni Barcelona",
    "iso:country":"ES",
    "sg:address":"Carrer de Major (sant Celoni), 95",
    "sg:city":"S. Celoni",
    "sg:orig_category":"Cajas De Ahorro",
    "sg:phone":"+34 938 67 48 93",
    "sg:postcode":"08470",
    "sg:province":"Barcelona",
    "wof:name":"Caixa D'estalvis Laietana",
    "wof:placetype":"venue"
},
  "geometry": {"coordinates":[2.4907848835,41.6896934509],"type":"Point"}
}