{
  "type": "Feature",
  "properties": {
    "addr:full":"Avda Cuarta Avenida, 26 Zaragoza Zaragoza 50007",
    "addr:housenumber":"26",
    "addr:postcode":"50007",
    "addr:street":"Avda Cuarta Avenida",
    "iso:country":"ES",
    "sg:address":"Avda Cuarta Avenida, 26",
    "sg:city":"Zaragoza",
    "sg:orig_category":"Molduras, Junquillos, Listones Y Molduras Perforadas",
    "sg:phone":"+34 976 37 18 02",
    "sg:postcode":"50007",
    "sg:province":"Zaragoza",
    "wof:name":"Marin Gil Juan Antonio",
    "wof:placetype":"venue"
},
  "geometry": {"coordinates":[-0.8813189864,41.6517295837],"type":"Point"}
}