{
  "type": "Feature",
  "properties": {
    "iso:country":"ES",
    "sg:address":"Carr Verge Del Carme, 22",
    "sg:city":"Picanya",
    "sg:orig_category":"Muebles, Minoristas",
    "sg:phone":"+34 961 59 29 25",
    "sg:postcode":"46210",
    "sg:province":"Valencia",
    "wof:name":"Muebles Carla S.l.",
    "wof:placetype":"venue"
},
  "geometry": {"coordinates":[-0.4386909902,39.4338531494],"type":"Point"}
}