{
  "type": "Feature",
  "properties": {
    "iso:country":"ES",
    "sg:address":"Calle de Menendez Y Pelayo, 20",
    "sg:city":"Puerto",
    "sg:orig_category":"Reposter\u00cdas",
    "sg:phone":"+34 962 67 26 39",
    "sg:postcode":"46520",
    "sg:province":"Valencia",
    "wof:name":"E.f.forment's S.l.",
    "wof:placetype":"venue"
},
  "geometry": {"coordinates":[-0.2198349983,39.6594734192],"type":"Point"}
}