{
  "type": "Feature",
  "properties": {
    "addr:full":"Calle de Jose Perez-fuster (metge), 22 Valencia Valencia 46007",
    "addr:housenumber":"22",
    "addr:postcode":"46007",
    "addr:street":"Calle De Jose Perez-Fuster Metge",
    "iso:country":"ES",
    "sg:address":"Calle de Jose Perez-fuster (metge), 22",
    "sg:city":"Valencia",
    "sg:orig_category":"Inform\u00c1tica, Ofim\u00c1tica (estudios, Asesor\u00cda, Ingenier\u00cda, Formaci\u00d3n)",
    "sg:phone":"+34 963 77 06 74",
    "sg:postcode":"46007",
    "sg:province":"Valencia",
    "wof:name":"Soluciones Informaticas Y Logisticas S.l.",
    "wof:placetype":"venue"
},
  "geometry": {"coordinates":[-0.3905526996,39.4590911865],"type":"Point"}
}