{
  "type": "Feature",
  "properties": {
    "iso:country":"ES",
    "sg:address":"Carrer de Hoquei, 144",
    "sg:city":"Terrassa",
    "sg:orig_category":"Chapister\u00cda",
    "sg:phone":"+34 937 85 73 38",
    "sg:postcode":"08226",
    "sg:province":"Barcelona",
    "wof:name":"Escamilla Valverde Ramon",
    "wof:placetype":"venue"
},
  "geometry": {"coordinates":[2.0309700966,41.572883606],"type":"Point"}
}