{
  "type": "Feature",
  "properties": {
    "addr:full":"Carr Burgos, 33 Cervera Lleida 25200",
    "addr:housenumber":"33",
    "addr:postcode":"25200",
    "addr:street":"Carr Burgos",
    "iso:country":"ES",
    "sg:address":"Carr Burgos, 33",
    "sg:city":"Cervera",
    "sg:orig_category":"Florister\u00cdas",
    "sg:phone":"+34 973 53 05 32",
    "sg:postcode":"25200",
    "sg:province":"Lleida",
    "wof:name":"Flors Montserrat C.b.",
    "wof:placetype":"venue"
},
  "geometry": {"coordinates":[1.2737760544,41.6714019775],"type":"Point"}
}