{
  "type": "Feature",
  "properties": {
    "addr:full":"Calle de Sargento Veiga Perez, 1 Coru\u00d1a La Coru\u00f1a 15009",
    "addr:housenumber":"1",
    "addr:postcode":"15009",
    "addr:street":"Calle De Sargento Veiga Perez;La Corun\u0303A",
    "iso:country":"ES",
    "sg:address":"Calle de Sargento Veiga Perez, 1",
    "sg:city":"Coru\u00d1a",
    "sg:orig_category":"Mec\u00c1nico Del Autom\u00d3vil",
    "sg:phone":"+34 981 28 39 41",
    "sg:postcode":"15009",
    "sg:province":"La Coru\u00f1a",
    "wof:name":"Penelas Rodriguez Vicente",
    "wof:placetype":"venue"
},
  "geometry": {"coordinates":[-8.3970756531,43.3473739624],"type":"Point"}
}