{
  "type": "Feature",
  "properties": {
    "addr:full":"Calle de Somera, 3 Requena Valencia 46340",
    "addr:housenumber":"3",
    "addr:postcode":"46340",
    "addr:street":"Calle De Somera",
    "iso:country":"ES",
    "sg:address":"Calle de Somera, 3",
    "sg:city":"Requena",
    "sg:orig_category":"Reposter\u00cdas",
    "sg:phone":"+34 962 30 12 89",
    "sg:postcode":"46340",
    "sg:province":"Valencia",
    "wof:name":"Lopez Piqueras Esteban",
    "wof:placetype":"venue"
},
  "geometry": {"coordinates":[-1.1014610529,39.4845619202],"type":"Point"}
}