{
  "type": "Feature",
  "properties": {
    "iso:country":"ES",
    "sg:address":"Calle de Calahorra, 17",
    "sg:city":"Varea",
    "sg:orig_category":"Carnicer\u00cdas, Carnicer\u00cdas",
    "sg:phone":"+34 941 24 09 98",
    "sg:postcode":"26006",
    "sg:province":"La Rioja",
    "wof:name":"Moreno Martinez Balbino",
    "wof:placetype":"venue"
},
  "geometry": {"coordinates":[-2.4079759121,42.4613113403],"type":"Point"}
}