{
  "type": "Feature",
  "properties": {
    "addr:full":"Abejeras, 18 Iru\u00f1a Navarra 31007",
    "addr:housenumber":"18",
    "addr:postcode":"31007",
    "addr:street":"Abejeras",
    "iso:country":"ES",
    "sg:address":"Abejeras, 18",
    "sg:city":"Iru\u00f1a",
    "sg:orig_category":"Papeler\u00cdas: Art\u00cdculos (al Por Mayor)",
    "sg:phone":"+34 948 27 29 04",
    "sg:postcode":"31007",
    "sg:province":"Navarra",
    "wof:name":"Arizcun Sagues Javier Y Ramon Maria S.cv.",
    "wof:placetype":"venue"
},
  "geometry": {"coordinates":[-1.6461180449,42.8059196472],"type":"Point"}
}