{
  "type": "Feature",
  "properties": {
    "iso:country":"ES",
    "sg:address":"Calle de Alcira, 12",
    "sg:city":"Ejido",
    "sg:orig_category":"Formaci\u00d3n Continuada (variada)",
    "sg:phone":"+34 950 48 78 62",
    "sg:postcode":"04700",
    "sg:province":"Almer\u00eda",
    "wof:name":"Lirola Maldonado Maria Dolores",
    "wof:placetype":"venue"
},
  "geometry": {"coordinates":[-2.8159065247,36.775806427],"type":"Point"}
}