{
  "type": "Feature",
  "properties": {
    "addr:full":"Av Castell De Barbera, 12 Barbera Valles Barcelona 08210",
    "addr:housenumber":"12",
    "addr:postcode":"08210",
    "addr:street":"Av Castell De Barbera",
    "iso:country":"ES",
    "sg:address":"Av Castell De Barbera, 12",
    "sg:city":"Barbera Valles",
    "sg:orig_category":"Ferreter\u00cda Artesanal",
    "sg:phone":"+34 937 19 00 88",
    "sg:postcode":"08210",
    "sg:province":"Barcelona",
    "wof:name":"Fet Forja S.l.",
    "wof:placetype":"venue"
},
  "geometry": {"coordinates":[2.146559,41.5237998962],"type":"Point"}
}