{
  "type": "Feature",
  "properties": {
    "iso:country":"ES",
    "sg:address":"Carrer de Comte Borrell, 162",
    "sg:city":"Barcelona",
    "sg:orig_category":"Arquitectos",
    "sg:phone":"+34 934 53 82 80",
    "sg:postcode":"08015",
    "sg:province":"Barcelona",
    "wof:name":"Gangolells Feixas Juan",
    "wof:placetype":"venue"
},
  "geometry": {"coordinates":[2.1547930241,41.3834877014],"type":"Point"}
}