{
  "type": "Feature",
  "properties": {
    "iso:country":"ES",
    "sg:address":"Ptda Rio Solana, S/n",
    "sg:city":"Benasal",
    "sg:orig_category":"Alimentaci\u00d3n General (al Por Menor)",
    "sg:phone":"+34 964 76 20 03",
    "sg:postcode":"12160",
    "sg:province":"Castell\u00f3n",
    "wof:name":"Trias Garcia S.l.",
    "wof:placetype":"venue"
},
  "geometry": {"coordinates":[-0.1405189931,40.3801345825],"type":"Point"}
}