{
  "type": "Feature",
  "properties": {
    "addr:full":"Calle de San Lazaro, 13 Oviedo Asturias 33008",
    "addr:housenumber":"13",
    "addr:postcode":"33008",
    "addr:street":"Calle De San Lazaro",
    "iso:country":"ES",
    "sg:address":"Calle de San Lazaro, 13",
    "sg:city":"Oviedo",
    "sg:orig_category":"Estancos",
    "sg:phone":"+34 985 21 63 43",
    "sg:postcode":"33008",
    "sg:province":"Asturias",
    "wof:name":"Garcia Perez Ricardo",
    "wof:placetype":"venue"
},
  "geometry": {"coordinates":[-5.8418622017,43.3530006409],"type":"Point"}
}