{
  "type": "Feature",
  "properties": {
    "iso:country":"ES",
    "sg:address":"Cno Marcota, 2",
    "sg:city":"Biar",
    "sg:orig_category":"Artes Gr\u00c1ficas, Artes Pl\u00c1sticas: Material Y Suministros (al Por Menor)",
    "sg:phone":"+34 965 81 02 18",
    "sg:postcode":"03410",
    "sg:province":"Alicante",
    "wof:name":"Marcon Biar S.l.",
    "wof:placetype":"venue"
},
  "geometry": {"coordinates":[-0.7617329955,38.6268768311],"type":"Point"}
}