{
  "type": "Feature",
  "properties": {
    "iso:country":"ES",
    "sg:address":"Poli Las Capellanias, S/n",
    "sg:city":"Caceres",
    "sg:orig_category":"Cristaler\u00cda Art\u00cdstica, Vidrio Soplado (fabricaci\u00d3n, Al Por Mayor)",
    "sg:phone":"+34 927 23 02 06",
    "sg:postcode":"10005",
    "sg:province":"C\u00e1ceres",
    "wof:name":"Perfiles Y Manufacturas Del Vidrio S.a.l.",
    "wof:placetype":"venue"
},
  "geometry": {"coordinates":[-6.5341739655,39.4675254822],"type":"Point"}
}