{
  "type": "Feature",
  "properties": {
    "addr:full":"Nevazo, S/n Caravaca Cruz Murcia 30400",
    "addr:postcode":"30400",
    "addr:street":"Nevazo S / N Caravaca Cruz",
    "iso:country":"ES",
    "sg:address":"Nevazo, S/n",
    "sg:city":"Caravaca Cruz",
    "sg:orig_category":"Bosques (trabajos, Asesor\u00cda, Gesti\u00d3n)",
    "sg:phone":"+34 968 70 70 18",
    "sg:postcode":"30400",
    "sg:province":"Murcia",
    "wof:name":"Grupo Generala S.l.",
    "wof:placetype":"venue"
},
  "geometry": {"coordinates":[-1.8638550043,38.1011772156],"type":"Point"}
}