{
  "type": "Feature",
  "properties": {
    "iso:country":"ES",
    "sg:address":"Calle de Heroe De Sostoa, 93",
    "sg:city":"Malaga",
    "sg:orig_category":"Servicios De Telecomunicaciones",
    "sg:phone":"+34 952 31 46 89",
    "sg:postcode":"29002",
    "sg:province":"M\u00e1laga",
    "wof:name":"Cardas Bilbao Jesus Jose Maria",
    "wof:placetype":"venue"
},
  "geometry": {"coordinates":[-4.4390001297,36.7048873901],"type":"Point"}
}