{
  "type": "Feature",
  "properties": {
    "iso:country":"ES",
    "sg:address":"Carr Compositor Mundi, 24",
    "sg:city":"Figueres",
    "sg:orig_category":"Molduras, Junquillos, Listones Y Molduras Perforadas",
    "sg:phone":"+34 972 50 85 58",
    "sg:postcode":"17600",
    "sg:province":"Girona",
    "wof:name":"Snack Bar El Raco S.c.",
    "wof:placetype":"venue"
},
  "geometry": {"coordinates":[2.9665000439,42.2718009949],"type":"Point"}
}