{
  "type": "Feature",
  "properties": {
    "iso:country":"ES",
    "sg:address":"Carrer de Saragossa, 12",
    "sg:city":"S. Adria Besos",
    "sg:orig_category":"Afilado",
    "sg:phone":"+34 933 81 21 55",
    "sg:postcode":"08930",
    "sg:province":"Barcelona",
    "wof:name":"Afilados Y Suministros Industriales Jcm Girona S.l.",
    "wof:placetype":"venue"
},
  "geometry": {"coordinates":[2.2264595032,41.4263725281],"type":"Point"}
}