{
  "type": "Feature",
  "properties": {
    "iso:country":"ES",
    "sg:address":"Avda Doctor Fleming, 11",
    "sg:city":"Alange",
    "sg:orig_category":"Electricidad: Instaladores",
    "sg:phone":"+34 924 36 54 60",
    "sg:postcode":"06840",
    "sg:province":"Badajoz",
    "wof:name":"Montero Rodriguez Juan Pedro",
    "wof:placetype":"venue"
},
  "geometry": {"coordinates":[-6.2428851128,38.7873268127],"type":"Point"}
}