{
  "type": "Feature",
  "properties": {
    "iso:country":"ES",
    "sg:address":"Carr Valls D'en Colomer, 18",
    "sg:city":"Bisbal D'emporda",
    "sg:orig_category":"Peluquer\u00cdas, Peluquer\u00cda Mixta",
    "sg:phone":"+34 972 64 33 08",
    "sg:postcode":"17100",
    "sg:province":"Girona",
    "wof:name":"Puigvert Moner Rosa",
    "wof:placetype":"venue"
},
  "geometry": {"coordinates":[3.0381269455,41.9589271545],"type":"Point"}
}