{
  "type": "Feature",
  "properties": {
    "iso:country":"ES",
    "sg:address":"Carrer de Cadis, 52",
    "sg:city":"Terrassa",
    "sg:orig_category":"Aluminio Y Aleaciones (producci\u00d3n, Transformaci\u00d3n, Negocio)",
    "sg:phone":"+34 937 85 46 64",
    "sg:postcode":"08226",
    "sg:province":"Barcelona",
    "wof:name":"Aluminios Labi S.l.",
    "wof:placetype":"venue"
},
  "geometry": {"coordinates":[2.0311381817,41.571685791],"type":"Point"}
}