{
  "type": "Feature",
  "properties": {
    "iso:country":"ES",
    "sg:address":"Calle de Ponferrada, 15",
    "sg:city":"Madrid",
    "sg:orig_category":"Molduras, Junquillos, Listones Y Molduras Perforadas",
    "sg:phone":"+34 917 38 46 08",
    "sg:postcode":"28029",
    "sg:province":"Madrid",
    "wof:name":"Merodio Cogolludo Jesus",
    "wof:placetype":"venue"
},
  "geometry": {"coordinates":[-3.7136731148,40.4749298096],"type":"Point"}
}