{
  "type": "Feature",
  "properties": {
    "addr:full":"Carrer de Rafael Campalans, 44 Hospitalet Llobregat Barcelona 08903",
    "addr:housenumber":"44",
    "addr:postcode":"08903",
    "addr:street":"Carrer De Rafael Campalans",
    "iso:country":"ES",
    "sg:address":"Carrer de Rafael Campalans, 44",
    "sg:city":"Hospitalet Llobregat",
    "sg:orig_category":"Empresas De Carpinter\u00cda Met\u00c1lica",
    "sg:phone":"+34 934 40 54 77",
    "sg:postcode":"08903",
    "sg:province":"Barcelona",
    "wof:name":"Gonzalez Guallarte Juan",
    "wof:placetype":"venue"
},
  "geometry": {"coordinates":[2.121721983,41.3732147217],"type":"Point"}
}