{
  "type": "Feature",
  "properties": {
    "iso:country":"ES",
    "sg:address":"Doctor Juaristi, 12",
    "sg:city":"Iru\u00f1a",
    "sg:orig_category":"Perfumer\u00cda (al Por Menor)",
    "sg:phone":"+34 948 35 58 24",
    "sg:postcode":"31012",
    "sg:province":"Navarra",
    "wof:name":"Eva & Eva",
    "wof:placetype":"venue"
},
  "geometry": {"coordinates":[-1.6670370102,42.8200836182],"type":"Point"}
}