{
  "type": "Feature",
  "properties": {
    "addr:full":"Avda. Joaquin Planells Riera, 9 A Coru\u00f1a La Coru\u00f1a 15008",
    "addr:housenumber":"9 a",
    "addr:postcode":"15008",
    "addr:street":"Avda. Joaquin Planells Riera;Corun\u0303A La Corun\u0303A",
    "iso:country":"ES",
    "sg:address":"Avda. Joaquin Planells Riera, 9",
    "sg:city":"A Coru\u00f1a",
    "sg:orig_category":"Venta, Montaje De Neum\u00c1ticos",
    "sg:phone":"+34 981 14 87 69",
    "sg:postcode":"15008",
    "sg:province":"La Coru\u00f1a",
    "wof:name":"Disgamovil S.l.",
    "wof:placetype":"venue"
},
  "geometry": {"coordinates":[-8.4090642929,43.3521232605],"type":"Point"}
}