{
  "type": "Feature",
  "properties": {
    "addr:full":"Calle de San Mateo, 1 Cuenca Cuenca 16004",
    "addr:housenumber":"1",
    "addr:postcode":"16004",
    "addr:street":"Calle De San Mateo",
    "iso:country":"ES",
    "sg:address":"Calle de San Mateo, 1",
    "sg:city":"Cuenca",
    "sg:orig_category":"Empresas De Pintura Y Revestimientos",
    "sg:phone":"+34 969 22 66 93",
    "sg:postcode":"16004",
    "sg:province":"Cuenca",
    "wof:name":"Alcocer Fernandez Tomas",
    "wof:placetype":"venue"
},
  "geometry": {"coordinates":[-2.138217926,40.0684280396],"type":"Point"}
}