{
  "type": "Feature",
  "properties": {
    "iso:country":"ES",
    "sg:address":"Carrer de Occident, 12",
    "sg:city":"Hospitalet Llobregat",
    "sg:orig_category":"Electrodom\u00c9sticos (al Por Menor)",
    "sg:phone":"+34 933 33 35 92",
    "sg:postcode":"08903",
    "sg:province":"Barcelona",
    "wof:name":"Cafes Caracas S.l.",
    "wof:placetype":"venue"
},
  "geometry": {"coordinates":[2.1198260784,41.3751525879],"type":"Point"}
}