{
  "type": "Feature",
  "properties": {
    "iso:country":"ES",
    "sg:address":"Calle de Entre Arroyos, 17",
    "sg:city":"Madrid",
    "sg:orig_category":"Panader\u00cdas, Panader\u00cdas",
    "sg:phone":"+34 913 28 31 17",
    "sg:postcode":"28030",
    "sg:province":"Madrid",
    "wof:name":"Garcia Fernandez Jose Antonio",
    "wof:placetype":"venue"
},
  "geometry": {"coordinates":[-3.6551759243,40.408454895],"type":"Point"}
}