{
  "type": "Feature",
  "properties": {
    "iso:country":"ES",
    "sg:address":"Rond Castillo (del), 6",
    "sg:city":"Burjassot",
    "sg:orig_category":"Molduras, Junquillos, Listones Y Molduras Perforadas",
    "sg:phone":"+34 963 63 12 75",
    "sg:postcode":"46100",
    "sg:province":"Valencia",
    "wof:name":"Bar Restaurante Brigido S.l.",
    "wof:placetype":"venue"
},
  "geometry": {"coordinates":[-0.4095050097,39.5104103088],"type":"Point"}
}