{
  "type": "Feature",
  "properties": {
    "iso:country":"ES",
    "sg:address":"Carr Industria, 10",
    "sg:city":"Aldaia",
    "sg:orig_category":"Supermercados Y Hipermercados",
    "sg:phone":"+34 961 51 57 45",
    "sg:postcode":"46960",
    "sg:province":"Valencia",
    "sg:website":"www.mercadona.es",
    "wof:name":"Mercadona S.a.",
    "wof:placetype":"venue"
},
  "geometry": {"coordinates":[-0.4611020088,39.4631233215],"type":"Point"}
}