{
  "type": "Feature",
  "properties": {
    "iso:country":"ES",
    "sg:address":"Carrer de Industria, 1",
    "sg:city":"Sabadell",
    "sg:orig_category":"Cl\u00cdnicas Dentales",
    "sg:phone":"+34 937 26 81 07",
    "sg:postcode":"08202",
    "sg:province":"Barcelona",
    "wof:name":"Odontin S.l.",
    "wof:placetype":"venue"
},
  "geometry": {"coordinates":[2.1098299026,41.5470085144],"type":"Point"}
}