{
  "type": "Feature",
  "properties": {
    "addr:full":"Urb Guajara Delta, 40 Guajara Santa Cruz De Tenerife 38296",
    "addr:housenumber":"40",
    "addr:postcode":"38296",
    "addr:street":"Urb;Delta",
    "iso:country":"ES",
    "sg:address":"Urb Guajara Delta, 40",
    "sg:city":"Guajara",
    "sg:orig_category":"Costureras",
    "sg:phone":"+34 922 31 18 18",
    "sg:postcode":"38296",
    "sg:province":"Santa Cruz De Tenerife",
    "wof:name":"Hajje Wehbe David",
    "wof:placetype":"venue"
},
  "geometry": {"coordinates":[-16.3148498535,28.4583091736],"type":"Point"}
}