{
  "type": "Feature",
  "properties": {
    "iso:country":"ES",
    "sg:address":"Carrer de Crom, 8",
    "sg:city":"Hospitalet Llobregat",
    "sg:orig_category":"Artes Gr\u00c1ficas, Artes Pl\u00c1sticas (curso)",
    "sg:phone":"+34 932 64 02 69",
    "sg:postcode":"08907",
    "sg:province":"Barcelona",
    "sg:website":"www.codiprint.com",
    "wof:name":"Codiprint S.l.",
    "wof:placetype":"venue"
},
  "geometry": {"coordinates":[2.1049070358,41.3534584045],"type":"Point"}
}