{
  "type": "Feature",
  "properties": {
    "addr:full":"Carrer de Berruguete, 64 Barcelona Barcelona 08035",
    "addr:housenumber":"64",
    "addr:postcode":"08035",
    "addr:street":"Carrer De Berruguete",
    "iso:country":"ES",
    "sg:address":"Carrer de Berruguete, 64",
    "sg:city":"Barcelona",
    "sg:orig_category":"Inform\u00c1tica (estudios, Servicios, Asesor\u00cda, Formaci\u00d3n)",
    "sg:phone":"+34 934 28 06 71",
    "sg:postcode":"08035",
    "sg:province":"Barcelona",
    "wof:name":"Cibercat S.l.",
    "wof:placetype":"venue"
},
  "geometry": {"coordinates":[2.1492071152,41.4333267212],"type":"Point"}
}