{
  "type": "Feature",
  "properties": {
    "addr:full":"Plaz Autonomia Extreme\u00d1a, 3 Badajoz Badajoz 06011",
    "addr:housenumber":"3",
    "addr:postcode":"06011",
    "addr:street":"Extremen\u0303A",
    "iso:country":"ES",
    "sg:address":"Plaz Autonomia Extreme\u00d1a, 3",
    "sg:city":"Badajoz",
    "sg:orig_category":"Farmacias",
    "sg:phone":"+34 924 25 09 12",
    "sg:postcode":"06011",
    "sg:province":"Badajoz",
    "wof:name":"Alarcon Benitez Laureano",
    "wof:placetype":"venue"
},
  "geometry": {"coordinates":[-7.082116127,38.8044891357],"type":"Point"}
}