{
  "type": "Feature",
  "properties": {
    "iso:country":"ES",
    "sg:address":"Avda Cruz Verde, 2",
    "sg:city":"Puebla Montalban",
    "sg:orig_category":"Confecci\u00d3n (fabricaci\u00d3n, Al Por Mayor)",
    "sg:phone":"+34 925 75 02 85",
    "sg:postcode":"45516",
    "sg:province":"Toledo",
    "wof:name":"Marcos Martin Maria Teresa",
    "wof:placetype":"venue"
},
  "geometry": {"coordinates":[-4.3624839783,39.8655433655],"type":"Point"}
}