{
  "type": "Feature",
  "properties": {
    "addr:full":"Via Europa, 41 Mataro Barcelona 08303",
    "addr:housenumber":"41",
    "addr:postcode":"08303",
    "addr:street":"Via Europa",
    "iso:country":"ES",
    "sg:address":"Via Europa, 41",
    "sg:city":"Mataro",
    "sg:orig_category":"Art\u00cdculos De Decoraci\u00d3n",
    "sg:phone":"+34 937 57 39 35",
    "sg:postcode":"08303",
    "sg:province":"Barcelona",
    "wof:name":"Unica S.c.p.",
    "wof:placetype":"venue"
},
  "geometry": {"coordinates":[2.4337239265,41.5427093506],"type":"Point"}
}