{
  "type": "Feature",
  "properties": {
    "iso:country":"ES",
    "sg:address":"Cami Ca La Madrona (de), 6",
    "sg:city":"Mataro",
    "sg:orig_category":"Fabricaci\u00d3n De Su\u00c9ters Y Chalecos De Punto",
    "sg:phone":"+34 937 55 36 11",
    "sg:postcode":"08304",
    "sg:province":"Barcelona",
    "wof:name":"Bonany Homs Jaime",
    "wof:placetype":"venue"
},
  "geometry": {"coordinates":[2.4524979591,41.5534744263],"type":"Point"}
}