{
  "type": "Feature",
  "properties": {
    "addr:full":"Carrer de Angli, 55 Barcelona Barcelona 08017",
    "addr:housenumber":"55",
    "addr:postcode":"08017",
    "addr:street":"Carrer De Angli",
    "iso:country":"ES",
    "sg:address":"Carrer de Angli, 55",
    "sg:city":"Barcelona",
    "sg:orig_category":"Comunidades Religiosas",
    "sg:phone":"+34 932 03 89 15",
    "sg:postcode":"08017",
    "sg:province":"Barcelona",
    "wof:name":"Monasterio De San Pedro De Las Puellas",
    "wof:placetype":"venue"
},
  "geometry": {"coordinates":[2.1231238842,41.4028167725],"type":"Point"}
}