{
  "type": "Feature",
  "properties": {
    "iso:country":"ES",
    "sg:address":"Calle de Ricardo Cangas, 17",
    "sg:city":"Ribadesella",
    "sg:orig_category":"Hoteles",
    "sg:phone":"+34 985 86 01 50",
    "sg:postcode":"33560",
    "sg:province":"Asturias",
    "wof:name":"Gran Hotel Del Sella S.l.",
    "wof:placetype":"venue"
},
  "geometry": {"coordinates":[-5.0662322044,43.46484375],"type":"Point"}
}