{
  "type": "Feature",
  "properties": {
    "addr:full":"Urb Fuentebella (de La), 47 Parla Madrid 28980",
    "addr:housenumber":"47",
    "addr:postcode":"28980",
    "addr:street":"Urb Fuentebella De La",
    "iso:country":"ES",
    "sg:address":"Urb Fuentebella (de La), 47",
    "sg:city":"Parla",
    "sg:orig_category":"Molduras, Junquillos, Listones Y Molduras Perforadas",
    "sg:phone":"+34 916 98 05 73",
    "sg:postcode":"28980",
    "sg:province":"Madrid",
    "wof:name":"Peinado Sanchez Manuel",
    "wof:placetype":"venue"
},
  "geometry": {"coordinates":[-3.7738280296,40.2308120728],"type":"Point"}
}