{
  "type": "Feature",
  "properties": {
    "iso:country":"ES",
    "sg:address":"Carr Nou, 8",
    "sg:city":"S. Julia Llor",
    "sg:orig_category":"Cerrajer\u00cda, Ferrallista",
    "sg:phone":"+34 972 42 32 64",
    "sg:postcode":"17164",
    "sg:province":"Girona",
    "wof:name":"Capdevila Torrent Joan",
    "wof:placetype":"venue"
},
  "geometry": {"coordinates":[2.6903998852,41.9815826416],"type":"Point"}
}