{
  "type": "Feature",
  "properties": {
    "iso:country":"ES",
    "sg:address":"Rua Eduardo Pondal (de), 4",
    "sg:city":"Santiago De Compostela",
    "sg:orig_category":"Ingeniero",
    "sg:phone":"+34 981 56 09 65",
    "sg:postcode":"15702",
    "sg:province":"A Coru\u00f1a",
    "wof:name":"Urbeplan S.l.",
    "wof:placetype":"venue"
},
  "geometry": {"coordinates":[-8.5432462692,42.8739624023],"type":"Point"}
}