{
  "type": "Feature",
  "properties": {
    "addr:full":"Avda Doctor Severo Ochoa (del), 39 Alcobendas Madrid 28100",
    "addr:postcode":"28100",
    "addr:street":"Avda Doctor Severo Ochoa Del;Alcobendas",
    "iso:country":"ES",
    "sg:address":"Avda Doctor Severo Ochoa (del), 39",
    "sg:city":"Alcobendas",
    "sg:orig_category":"Fabricaci\u00d3n De Peines Y De Accesorios De Peluquer\u00cda",
    "sg:phone":"+34 916 61 39 77",
    "sg:postcode":"28100",
    "sg:province":"Madrid",
    "wof:name":"Beauty Network S.a.",
    "wof:placetype":"venue"
},
  "geometry": {"coordinates":[-3.6541700363,40.5413665771],"type":"Point"}
}