{
  "type": "Feature",
  "properties": {
    "iso:country":"ES",
    "sg:address":"Carrer de Giriti, 5",
    "sg:city":"Barcelona",
    "sg:orig_category":"Concepci\u00d3n Y Realizaci\u00d3n De Maquetas Profesionales Y Prototipos",
    "sg:phone":"+34 933 10 21 89",
    "sg:postcode":"08003",
    "sg:province":"Barcelona",
    "wof:name":"Farreras Casanovas Ignacio",
    "wof:placetype":"venue"
},
  "geometry": {"coordinates":[2.1798400879,41.3841056824],"type":"Point"}
}