{
  "type": "Feature",
  "properties": {
    "iso:country":"ES",
    "sg:address":"Calle de Ramon Gomez De La Serna, 62",
    "sg:city":"Madrid",
    "sg:orig_category":"Internados & Ense\u00d1anza Privada",
    "sg:phone":"+34 913 73 23 28",
    "sg:postcode":"28035",
    "sg:province":"Madrid",
    "wof:name":"Fuente La Reina 82 Coop. Ltd.",
    "wof:placetype":"venue"
},
  "geometry": {"coordinates":[-3.7258110046,40.4813423157],"type":"Point"}
}