{
  "type": "Feature",
  "properties": {
    "iso:country":"ES",
    "sg:address":"Calle de Hinojosa, 3",
    "sg:city":"Viso",
    "sg:orig_category":"Mercer\u00cda, Lencer\u00cda (al Por Menor)",
    "sg:phone":"+34 957 12 70 45",
    "sg:postcode":"14470",
    "sg:province":"C\u00f3rdoba",
    "wof:name":"Sanchez Moreno Virtudes",
    "wof:placetype":"venue"
},
  "geometry": {"coordinates":[-4.9558939934,38.4837226868],"type":"Point"}
}