{
  "type": "Feature",
  "properties": {
    "addr:full":"Zona Ind. Ergoien, S/n Urnieta Guip\u00f9zcoa 20130",
    "addr:housenumber":"s",
    "addr:postcode":"20130",
    "addr:street":"Ergoien;/ N;Guipu\u0300Zcoa",
    "iso:country":"ES",
    "sg:address":"Zona Ind. Ergoien, S/n",
    "sg:city":"Urnieta",
    "sg:orig_category":"Mec\u00c1nico Del Autom\u00d3vil",
    "sg:phone":"+34 943 55 24 32",
    "sg:postcode":"20130",
    "sg:province":"Guip\u00f9zcoa",
    "wof:name":"Pineda Gonzalez Fernando",
    "wof:placetype":"venue"
},
  "geometry": {"coordinates":[-1.992429018,43.248588562],"type":"Point"}
}