{
  "type": "Feature",
  "properties": {
    "addr:full":"Calle de Jose De Velilla, 6 Sevilla Sevilla 41001",
    "addr:housenumber":"6",
    "addr:postcode":"41001",
    "addr:street":"Calle De Jose De Velilla",
    "iso:country":"ES",
    "sg:address":"Calle de Jose De Velilla, 6",
    "sg:city":"Sevilla",
    "sg:orig_category":"Inmobiliaria (agencias)",
    "sg:phone":"+34 954 21 26 16",
    "sg:postcode":"41001",
    "sg:province":"Sevilla",
    "wof:name":"Ocio Y Bienestar S.l.",
    "wof:placetype":"venue"
},
  "geometry": {"coordinates":[-5.9958648682,37.3914451599],"type":"Point"}
}