{
  "type": "Feature",
  "properties": {
    "addr:full":"Calle de Narrica, 1 Donostia-san Sebastian Guip\u00f9zcoa 20003",
    "addr:housenumber":"1",
    "addr:postcode":"20003",
    "addr:street":"Calle De Narrica",
    "iso:country":"ES",
    "sg:address":"Calle de Narrica, 1",
    "sg:city":"Donostia-san Sebastian",
    "sg:orig_category":"Inmobiliaria (agencias)",
    "sg:phone":"+34 943 42 61 43",
    "sg:postcode":"20003",
    "sg:province":"Guip\u00f9zcoa",
    "wof:name":"Mari Carmen Mena Lucea",
    "wof:placetype":"venue"
},
  "geometry": {"coordinates":[-1.9840650558,43.3225288391],"type":"Point"}
}