{
  "type": "Feature",
  "properties": {
    "addr:full":"Pol Ind, 21 Puerto Lumbreras Murcia 30890",
    "addr:housenumber":"21",
    "addr:postcode":"30890",
    "addr:street":"Ind",
    "iso:country":"ES",
    "sg:address":"Pol Ind, 21",
    "sg:city":"Puerto Lumbreras",
    "sg:orig_category":"Equipo De Refrigeraci\u00d3n Industrial",
    "sg:phone":"+34 968 40 28 59",
    "sg:postcode":"30890",
    "sg:province":"Murcia",
    "wof:name":"Mayfrind S.l.",
    "wof:placetype":"venue"
},
  "geometry": {"coordinates":[-1.9274189472,37.6259460449],"type":"Point"}
}