{
  "type": "Feature",
  "properties": {
    "addr:full":"Calle de Cesar Vallejo, 8 Malaga M\u00e1laga 29004",
    "addr:housenumber":"8",
    "addr:postcode":"29004",
    "addr:street":"Calle De Cesar Vallejo;Ma\u0301Laga",
    "iso:country":"ES",
    "sg:address":"Calle de Cesar Vallejo, 8",
    "sg:city":"Malaga",
    "sg:orig_category":"Electrodom\u00c9sticos (fabricaci\u00d3n, Al Por Mayor)",
    "sg:phone":"+34 952 96 09 57",
    "sg:postcode":"29004",
    "sg:province":"M\u00e1laga",
    "wof:name":"Casa Sita S.l.",
    "wof:placetype":"venue"
},
  "geometry": {"coordinates":[-4.4825248718,36.6939659119],"type":"Point"}
}