{
  "type": "Feature",
  "properties": {
    "addr:full":"Plaz Fuente Dorada, 14 Valladolid Valladolid 47001",
    "addr:housenumber":"14",
    "addr:postcode":"47001",
    "addr:street":"Plaz Fuente Dorada",
    "iso:country":"ES",
    "sg:address":"Plaz Fuente Dorada, 14",
    "sg:city":"Valladolid",
    "sg:orig_category":"Bisuter\u00cda, Joyer\u00cda, Relojer\u00cda (al Por Menor)",
    "sg:phone":"+34 983 30 17 28",
    "sg:postcode":"47001",
    "sg:province":"Valladolid",
    "wof:name":"Hijos De Antonio Potente Yag\u00fce, S.l",
    "wof:placetype":"venue"
},
  "geometry": {"coordinates":[-4.7321238518,41.6541938782],"type":"Point"}
}