{
  "type": "Feature",
  "properties": {
    "iso:country":"ES",
    "sg:address":"Calle de Puente Colgante, 38",
    "sg:city":"Valladolid",
    "sg:orig_category":"Arquitectos",
    "sg:phone":"+34 983 23 92 49",
    "sg:postcode":"47006",
    "sg:province":"Valladolid",
    "wof:name":"Casanova Roque Maria Mercedes",
    "wof:placetype":"venue"
},
  "geometry": {"coordinates":[-4.7380189896,41.6408996582],"type":"Point"}
}