{
  "type": "Feature",
  "properties": {
    "iso:country":"ES",
    "sg:address":"Calle de Compa\u00d1ia, 16",
    "sg:city":"Osuna",
    "sg:orig_category":"Abogados",
    "sg:phone":"+34 954 81 03 00",
    "sg:postcode":"41640",
    "sg:province":"Sevilla",
    "wof:name":"Garcia Carvajal Jose Luis",
    "wof:placetype":"venue"
},
  "geometry": {"coordinates":[-5.1047725677,37.2380752563],"type":"Point"}
}