{
  "type": "Feature",
  "properties": {
    "addr:full":"Calle de Martinez Izquierdo, 6 Madrid Madrid 28028",
    "addr:housenumber":"6",
    "addr:postcode":"28028",
    "addr:street":"Calle De Martinez Izquierdo",
    "iso:country":"ES",
    "sg:address":"Calle de Martinez Izquierdo, 6",
    "sg:city":"Madrid",
    "sg:orig_category":"Veh\u00cdculos De Ocasi\u00d3n",
    "sg:phone":"+34 917 25 41 54",
    "sg:postcode":"28028",
    "sg:province":"Madrid",
    "wof:name":"Coversia Trade S.l.",
    "wof:placetype":"venue"
},
  "geometry": {"coordinates":[-3.6715331078,40.4323921204],"type":"Point"}
}