{
  "type": "Feature",
  "properties": {
    "addr:full":"Carr Ample, 17 Bisbal D'emporda Girona 17100",
    "addr:housenumber":"17",
    "addr:postcode":"17100",
    "addr:street":"Carr Ample",
    "iso:country":"ES",
    "sg:address":"Carr Ample, 17",
    "sg:city":"Bisbal D'emporda",
    "sg:orig_category":"Lencer\u00cda Femenina, Corseter\u00cda, Trajes De Ba\u00d1o (al Por Menor)",
    "sg:phone":"+34 972 64 52 65",
    "sg:postcode":"17100",
    "sg:province":"Girona",
    "wof:name":"Mir Font Montserrat",
    "wof:placetype":"venue"
},
  "geometry": {"coordinates":[2.813131094,41.9749221802],"type":"Point"}
}