{
  "type": "Feature",
  "properties": {
    "addr:full":"Calle de Vicente Aleixandre, S/n Alguazas Murcia 30560",
    "addr:housenumber":"s / n",
    "addr:postcode":"30560",
    "addr:street":"Calle De Vicente Aleixandre",
    "iso:country":"ES",
    "sg:address":"Calle de Vicente Aleixandre, S/n",
    "sg:city":"Alguazas",
    "sg:orig_category":"Polideportivos",
    "sg:phone":"+34 968 62 12 68",
    "sg:postcode":"30560",
    "sg:province":"Murcia",
    "wof:name":"Ayuntamiento De Alguazas-polideportivo",
    "wof:placetype":"venue"
},
  "geometry": {"coordinates":[-1.2502249479,38.0573883057],"type":"Point"}
}