{
  "type": "Feature",
  "properties": {
    "iso:country":"ES",
    "sg:address":"Carr Horta D'en Fina, 12",
    "sg:city":"Palafrugell",
    "sg:orig_category":"Papeler\u00cdas: Art\u00cdculos (al Por Mayor)",
    "sg:phone":"+34 972 30 00 17",
    "sg:postcode":"17200",
    "sg:province":"Girona",
    "sg:website":"www.esquitx.com",
    "wof:name":"Esquitx Oficina S.l.",
    "wof:placetype":"venue"
},
  "geometry": {"coordinates":[3.1600840092,41.9146728516],"type":"Point"}
}