{
  "type": "Feature",
  "properties": {
    "addr:full":"Pase Estacion, 101 Salamanca Salamanca 37004",
    "addr:housenumber":"101",
    "addr:postcode":"37004",
    "addr:street":"Estacion",
    "iso:country":"ES",
    "sg:address":"Pase Estacion, 101",
    "sg:city":"Salamanca",
    "sg:orig_category":"Comercio Y Bancos",
    "sg:phone":"+34 923 22 24 34",
    "sg:postcode":"37004",
    "sg:province":"Salamanca",
    "sg:website":"www.stylsaf.com",
    "wof:name":"Garcia Guerra Jesus",
    "wof:placetype":"venue"
},
  "geometry": {"coordinates":[-5.6500749588,40.9719581604],"type":"Point"}
}