{
  "type": "Feature",
  "properties": {
    "iso:country":"ES",
    "sg:address":"Pase Gran Capitan, 23",
    "sg:city":"Salamanca",
    "sg:orig_category":"Comidas Por Encargo, Organizaci\u00d3n De Recepciones",
    "sg:phone":"+34 923 25 57 87",
    "sg:postcode":"37006",
    "sg:province":"Salamanca",
    "wof:name":"Uffizzi Cons. Rest. Bienes Culturales",
    "wof:placetype":"venue"
},
  "geometry": {"coordinates":[-5.6678228378,40.977973938],"type":"Point"}
}