{
  "type": "Feature",
  "properties": {
    "addr:full":"Calle de Joan Miro, 80 Hueros Madrid 28810",
    "addr:housenumber":"80",
    "addr:postcode":"28810",
    "addr:street":"Calle De Joan Miro",
    "iso:country":"ES",
    "sg:address":"Calle de Joan Miro, 80",
    "sg:city":"Hueros",
    "sg:orig_category":"Agencias De Prensa E Informaci\u00d3n",
    "sg:phone":"+34 918 79 30 52",
    "sg:postcode":"28810",
    "sg:province":"Madrid",
    "wof:name":"Instituto Del Caballo S.l.",
    "wof:placetype":"venue"
},
  "geometry": {"coordinates":[-3.300317049,40.4334030151],"type":"Point"}
}