{
  "type": "Feature",
  "properties": {
    "addr:full":"Calle de Calveros, 82 Puertollano Ciudad Real 13500",
    "addr:housenumber":"82",
    "addr:postcode":"13500",
    "addr:street":"Calle De Calveros",
    "iso:country":"ES",
    "sg:address":"Calle de Calveros, 82",
    "sg:city":"Puertollano",
    "sg:orig_category":"Negocio De Materiales De Construcci\u00d3n",
    "sg:phone":"+34 926 42 88 02",
    "sg:postcode":"13500",
    "sg:province":"Ciudad Real",
    "wof:name":"Materiales De Construccion Jose Manuel Gimenez S.l.",
    "wof:placetype":"venue"
},
  "geometry": {"coordinates":[-4.1115098,38.680229187],"type":"Point"}
}