{
  "type": "Feature",
  "properties": {
    "addr:full":"Calle de Gran Via, 55 Madrid Madrid 28013",
    "addr:housenumber":"55",
    "addr:postcode":"madrid;28013",
    "addr:street":"Calle De Gran Via",
    "iso:country":"ES",
    "sg:address":"Calle de Gran Via, 55",
    "sg:city":"Madrid",
    "sg:orig_category":"Agencias De Viajes",
    "sg:phone":"+34 915 47 83 64",
    "sg:postcode":"28013",
    "sg:province":"Madrid",
    "wof:name":"Viajes Mundirama S.l.",
    "wof:placetype":"venue"
},
  "geometry": {"coordinates":[-3.7085680962,40.4217453003],"type":"Point"}
}