{
  "type": "Feature",
  "properties": {
    "addr:full":"Av Segadors, S/n Riudarenes Girona 17421",
    "addr:housenumber":"s / n",
    "addr:postcode":"17421",
    "addr:street":"Av Segadors",
    "iso:country":"ES",
    "sg:address":"Av Segadors, S/n",
    "sg:city":"Riudarenes",
    "sg:orig_category":"Charcuter\u00cdas (al Por Mayor)",
    "sg:phone":"+34 972 85 60 46",
    "sg:postcode":"17421",
    "sg:province":"Girona",
    "sg:website":"www.batalle.com",
    "wof:name":"Carnicas Batalle S.a.",
    "wof:placetype":"venue"
},
  "geometry": {"coordinates":[2.718485117,41.8208808899],"type":"Point"}
}