{
  "type": "Feature",
  "properties": {
    "iso:country":"ES",
    "sg:address":"Rio Altzania, 19",
    "sg:city":"Iru\u00f1a",
    "sg:orig_category":"Artes Gr\u00c1ficas, Artes Pl\u00c1sticas (curso)",
    "sg:phone":"+34 948 15 19 11",
    "sg:postcode":"31005",
    "sg:province":"Navarra",
    "wof:name":"Fraile Garcia Carlos",
    "wof:placetype":"venue"
},
  "geometry": {"coordinates":[-1.6456090212,42.8039703369],"type":"Point"}
}