{
  "type": "Feature",
  "properties": {
    "addr:full":"Calle de Doctor Iranzo, 59 Zaragoza Zaragoza 50002",
    "addr:housenumber":"59",
    "addr:postcode":"50002",
    "addr:street":"Calle De Doctor Iranzo",
    "iso:country":"ES",
    "sg:address":"Calle de Doctor Iranzo, 59",
    "sg:city":"Zaragoza",
    "sg:orig_category":"M\u00c9dicos: Medicina General Orientada A La Acupuntura",
    "sg:phone":"+34 976 42 01 98",
    "sg:postcode":"50002",
    "sg:province":"Zaragoza",
    "wof:name":"Bono Ari\u00f1o Josefina",
    "wof:placetype":"venue"
},
  "geometry": {"coordinates":[-0.8641049862,41.647315979],"type":"Point"}
}