{
  "type": "Feature",
  "properties": {
    "iso:country":"ES",
    "sg:address":"Calle de Concejo, 8",
    "sg:city":"Galapagar",
    "sg:orig_category":"Librer\u00cdas",
    "sg:phone":"+34 918 58 00 88",
    "sg:postcode":"28260",
    "sg:province":"Madrid",
    "wof:name":"Gil-delgado Alberti Gonzalo",
    "wof:placetype":"venue"
},
  "geometry": {"coordinates":[-4.0042424202,40.5771102905],"type":"Point"}
}