{
  "type": "Feature",
  "properties": {
    "iso:country":"ES",
    "sg:address":"Mcdo Central, 81",
    "sg:city":"Onda",
    "sg:orig_category":"Frutas Y Legumbres Frescas (al Por Mayor)",
    "sg:phone":"+34 964 60 19 00",
    "sg:postcode":"12200",
    "sg:province":"Castell\u00f3n",
    "wof:name":"Iba\u00f1ez Santaeulalia Manuel",
    "wof:placetype":"venue"
},
  "geometry": {"coordinates":[-0.2432307005,39.9604454041],"type":"Point"}
}