{
  "type": "Feature",
  "properties": {
    "iso:country":"ES",
    "sg:address":"Ctra. P. De Becerro, S/n",
    "sg:city":"Hornos",
    "sg:orig_category":"Condimentos, Especias, Vinagres, Salsas Preparadas (fabricaci\u00d3n, Al Por Mayor)",
    "sg:phone":"+34 953 73 10 09",
    "sg:postcode":"23468",
    "sg:province":"Ja\u00e9n",
    "wof:name":"Jugosan S.l.",
    "wof:placetype":"venue"
},
  "geometry": {"coordinates":[-2.7172999382,38.216091156],"type":"Point"}
}