{
  "type": "Feature",
  "properties": {
    "addr:full":"Pase Ezequiel Gonzalez, 25 Segovia Segovia 40002",
    "addr:housenumber":"25",
    "addr:postcode":"40002",
    "addr:street":"Gonzalez",
    "iso:country":"ES",
    "sg:address":"Pase Ezequiel Gonzalez, 25",
    "sg:city":"Segovia",
    "sg:orig_category":"Panader\u00cdas, Panader\u00cdas",
    "sg:phone":"+34 921 46 15 40",
    "sg:postcode":"40002",
    "sg:province":"Segovia",
    "wof:name":"Sanz Prieto Miguel Angel",
    "wof:placetype":"venue"
},
  "geometry": {"coordinates":[-4.1207580566,40.9443702698],"type":"Point"}
}