{
  "type": "Feature",
  "properties": {
    "addr:full":"Calle de Palmera (la), 20 Cordoba C\u00f3rdoba 14006",
    "addr:housenumber":"20",
    "addr:postcode":"14006",
    "addr:street":"Calle De Palmera La;Co\u0301Rdoba",
    "iso:country":"ES",
    "sg:address":"Calle de Palmera (la), 20",
    "sg:city":"Cordoba",
    "sg:orig_category":"Agencias Y Agentes Comerciales, Representantes",
    "sg:phone":"+34 957 27 36 97",
    "sg:postcode":"14006",
    "sg:province":"C\u00f3rdoba",
    "wof:name":"Leon Troyano Maria Elena",
    "wof:placetype":"venue"
},
  "geometry": {"coordinates":[-4.7811231613,37.8974113464],"type":"Point"}
}