{
  "type": "Feature",
  "properties": {
    "addr:full":"Calle de Mayor, S/n Villanueva Alcardete Toledo 45810",
    "addr:housenumber":"s",
    "addr:postcode":"45810",
    "addr:street":"Calle De Mayor;/ N",
    "iso:country":"ES",
    "sg:address":"Calle de Mayor, S/n",
    "sg:city":"Villanueva Alcardete",
    "sg:orig_category":"Animales (al Por Menor)",
    "sg:phone":"+34 925 16 65 26",
    "sg:postcode":"45810",
    "sg:province":"Toledo",
    "sg:website":"www.comercial-gallego.com",
    "wof:name":"Avicola La Mancha S.l.",
    "wof:placetype":"venue"
},
  "geometry": {"coordinates":[-3.0126934052,39.6733856201],"type":"Point"}
}