{
  "type": "Feature",
  "properties": {
    "iso:country":"ES",
    "sg:address":"Calle de Buenos Aires, 5",
    "sg:city":"Bilbao",
    "sg:orig_category":"Laboratorios Y Trabajos De Fotograf\u00cda, V\u00cddeo Y Cine",
    "sg:phone":"+34 944 23 58 56",
    "sg:postcode":"48001",
    "sg:province":"Vizcaya",
    "wof:name":"Foto Ortega C.b.",
    "wof:placetype":"venue"
},
  "geometry": {"coordinates":[-2.9256877899,43.2621383667],"type":"Point"}
}