{
  "type": "Feature",
  "properties": {
    "iso:country":"ES",
    "sg:address":"Carrer de Sant Pere Mes Alt, 28",
    "sg:city":"Barcelona",
    "sg:orig_category":"Caf\u00c9s, Bares, Cervecer\u00cdas",
    "sg:phone":"+34 933 10 70 84",
    "sg:postcode":"08003",
    "sg:province":"Barcelona",
    "wof:name":"Fors Guillot Maria Del Carmen",
    "wof:placetype":"venue"
},
  "geometry": {"coordinates":[2.1763560772,41.3879508972],"type":"Point"}
}