{
  "type": "Feature",
  "properties": {
    "iso:country":"ES",
    "sg:address":"Calle de Preciados, 26",
    "sg:city":"Madrid",
    "sg:orig_category":"Confecci\u00d3n De Trajes Para Se\u00d1oras",
    "sg:phone":"+34 915 31 24 14",
    "sg:postcode":"28013",
    "sg:province":"Madrid",
    "wof:name":"Perez Garcia-lajara Irene",
    "wof:placetype":"venue"
},
  "geometry": {"coordinates":[-3.7050509453,40.4187164307],"type":"Point"}
}