{
  "type": "Feature",
  "properties": {
    "addr:full":"Doade, 54 Doade Lugo 27425",
    "addr:housenumber":"54",
    "addr:postcode":"27425",
    "addr:street":"Doade",
    "iso:country":"ES",
    "sg:address":"Doade, 54",
    "sg:city":"Doade",
    "sg:orig_category":"Productores Recolectores, Venta Directa De Vinos",
    "sg:phone":"+34 982 15 24 58",
    "sg:postcode":"27425",
    "sg:province":"Lugo",
    "wof:name":"Lopez Fernandez Domingo",
    "wof:placetype":"venue"
},
  "geometry": {"coordinates":[-7.6001591682,42.421333313],"type":"Point"}
}