{
  "type": "Feature",
  "properties": {
    "addr:full":"Av Barcelona, 62 Vilafranca Penedes Barcelona 08720",
    "addr:housenumber":"62",
    "addr:postcode":"08720",
    "addr:street":"Av Barcelona;Penedes Barcelona",
    "iso:country":"ES",
    "sg:address":"Av Barcelona, 62",
    "sg:city":"Vilafranca Penedes",
    "sg:orig_category":"Material Y Herramientas Agr\u00cdcolas",
    "sg:phone":"+34 938 18 18 75",
    "sg:postcode":"08720",
    "sg:province":"Barcelona",
    "wof:name":"Antoni Marcer S.l.",
    "wof:placetype":"venue"
},
  "geometry": {"coordinates":[1.7094489336,41.3476066589],"type":"Point"}
}