{
  "type": "Feature",
  "properties": {
    "addr:full":"Calle de Mayor, 94 Alcala Henares Madrid 28801",
    "addr:housenumber":"94",
    "addr:postcode":"28801",
    "addr:street":"Calle De Mayor",
    "iso:country":"ES",
    "sg:address":"Calle de Mayor, 94",
    "sg:city":"Alcala Henares",
    "sg:orig_category":"Inform\u00c1tica: Material Y Suministros",
    "sg:phone":"+34 918 81 55 26",
    "sg:postcode":"28801",
    "sg:province":"Madrid",
    "wof:name":"Computerma Informatica S.l.",
    "wof:placetype":"venue"
},
  "geometry": {"coordinates":[-3.3686740398,40.4812507629],"type":"Point"}
}