{
  "type": "Feature",
  "properties": {
    "addr:full":"Avda Francisco Javier Sauquillo, 29 Fuenlabrada Madrid 28944",
    "addr:housenumber":"29",
    "addr:postcode":"28944",
    "addr:street":"Avda Francisco Javier Sauquillo",
    "iso:country":"ES",
    "sg:address":"Avda Francisco Javier Sauquillo, 29",
    "sg:city":"Fuenlabrada",
    "sg:orig_category":"Caf\u00c9s, Bares, Cervecer\u00cdas",
    "sg:phone":"+34 916 97 31 19",
    "sg:postcode":"28944",
    "sg:province":"Madrid",
    "wof:name":"Gascon Alvarez De Soto Mayor Antonio Joaquin",
    "wof:placetype":"venue"
},
  "geometry": {"coordinates":[-3.7898573875,40.2838439941],"type":"Point"}
}