{
  "type": "Feature",
  "properties": {
    "iso:country":"ES",
    "sg:address":"Avda Fernando Calzadilla, 7",
    "sg:city":"Badajoz",
    "sg:orig_category":"M\u00c9dicos: Estomatolog\u00cda",
    "sg:phone":"+34 924 24 52 41",
    "sg:postcode":"06004",
    "sg:province":"Badajoz",
    "wof:name":"Herrera Claver Angela",
    "wof:placetype":"venue"
},
  "geometry": {"coordinates":[-6.9726161957,38.8715858459],"type":"Point"}
}