{
  "type": "Feature",
  "properties": {
    "addr:full":"Calle de San Bartolome, 4 Caspe Zaragoza 50700",
    "addr:housenumber":"4",
    "addr:postcode":"50700",
    "addr:street":"Calle De San Bartolome",
    "iso:country":"ES",
    "sg:address":"Calle de San Bartolome, 4",
    "sg:city":"Caspe",
    "sg:orig_category":"Cr\u00cda De Animales",
    "sg:phone":"+34 976 63 02 68",
    "sg:postcode":"50700",
    "sg:province":"Zaragoza",
    "wof:name":"Ganados Pueyo S.a.",
    "wof:placetype":"venue"
},
  "geometry": {"coordinates":[-0.0489489995,41.2497634888],"type":"Point"}
}