{
  "type": "Feature",
  "properties": {
    "iso:country":"ES",
    "sg:address":"Calle de Rogelio Mu\u00d1oz, S/n",
    "sg:city":"Madrid",
    "sg:orig_category":"Pintura Y Barniz (al Por Menor)",
    "sg:phone":"+34 913 82 10 69",
    "sg:postcode":"28033",
    "sg:province":"Madrid",
    "wof:name":"Guerra Alvarez Jose Maria",
    "wof:placetype":"venue"
},
  "geometry": {"coordinates":[-3.6431760788,40.4724006653],"type":"Point"}
}