{
  "type": "Feature",
  "properties": {
    "addr:full":"Calle de Villanubla, 30 Valladolid Valladolid 47009",
    "addr:housenumber":"30",
    "addr:postcode":"47009",
    "addr:street":"Calle De Villanubla",
    "iso:country":"ES",
    "sg:address":"Calle de Villanubla, 30",
    "sg:city":"Valladolid",
    "sg:orig_category":"Mec\u00c1nico Del Autom\u00d3vil",
    "sg:phone":"+34 983 33 18 18",
    "sg:postcode":"47009",
    "sg:province":"Valladolid",
    "wof:name":"Diez Dominguez Antonio",
    "wof:placetype":"venue"
},
  "geometry": {"coordinates":[-4.7347378731,41.6629486084],"type":"Point"}
}