{
  "type": "Feature",
  "properties": {
    "addr:full":"Calle de San Roque, 52 Pradoluengo Burgos 09260",
    "addr:housenumber":"52",
    "addr:postcode":"09260",
    "addr:street":"Calle De San Roque",
    "iso:country":"ES",
    "sg:address":"Calle de San Roque, 52",
    "sg:city":"Pradoluengo",
    "sg:orig_category":"Textil",
    "sg:phone":"+34 947 58 67 10",
    "sg:postcode":"09260",
    "sg:province":"Burgos",
    "wof:name":"Mingo Gomez Jose Manuel",
    "wof:placetype":"venue"
},
  "geometry": {"coordinates":[-3.2049489021,42.3269500732],"type":"Point"}
}