{
  "type": "Feature",
  "properties": {
    "iso:country":"ES",
    "sg:address":"Calle de Goikosoloa, 6",
    "sg:city":"Basauri",
    "sg:orig_category":"Empresarios",
    "sg:phone":"+34 944 49 00 89",
    "sg:postcode":"48970",
    "sg:province":"Vizcaya",
    "wof:name":"Carpinteria Metalica D.g. Del Moral, S. L.",
    "wof:placetype":"venue"
},
  "geometry": {"coordinates":[-2.8835439682,43.2382011414],"type":"Point"}
}