{
  "type": "Feature",
  "properties": {
    "iso:country":"ES",
    "sg:address":"Carrer de Mallorca, 637",
    "sg:city":"Barcelona",
    "sg:orig_category":"Tintes (fabricaci\u00d3n, Al Por Mayor)",
    "sg:phone":"+34 933 52 30 60",
    "sg:postcode":"08026",
    "sg:province":"Barcelona",
    "wof:name":"Martinez Martinez Javier",
    "wof:placetype":"venue"
},
  "geometry": {"coordinates":[2.1884489059,41.4134140015],"type":"Point"}
}