{
  "type": "Feature",
  "properties": {
    "iso:country":"ES",
    "sg:address":"Rond Alfons X El Savi (d'), 2",
    "sg:city":"Mataro",
    "sg:orig_category":"Molduras, Junquillos, Listones Y Molduras Perforadas",
    "sg:phone":"+34 937 90 18 29",
    "sg:postcode":"08301",
    "sg:province":"Barcelona",
    "wof:name":"Pujol-alum S.c.p",
    "wof:placetype":"venue"
},
  "geometry": {"coordinates":[2.4427170753,41.5447692871],"type":"Point"}
}