{
  "type": "Feature",
  "properties": {
    "addr:full":"Calle de David Milian, 6 Beceite Teruel 44588",
    "addr:housenumber":"6",
    "addr:postcode":"44588",
    "addr:street":"Calle De David Milian",
    "iso:country":"ES",
    "sg:address":"Calle de David Milian, 6",
    "sg:city":"Beceite",
    "sg:orig_category":"Contenedores (mercanc\u00cdas)",
    "sg:phone":"+34 978 85 02 57",
    "sg:postcode":"44588",
    "sg:province":"Teruel",
    "wof:name":"Royo Pallares Gregorio",
    "wof:placetype":"venue"
},
  "geometry": {"coordinates":[0.2057107985,40.8169784546],"type":"Point"}
}