{
  "type": "Feature",
  "properties": {
    "iso:country":"ES",
    "sg:address":"Carr Lluis Companys, 31",
    "sg:city":"Lleida",
    "sg:orig_category":"Librer\u00cdas",
    "sg:phone":"+34 973 26 23 16",
    "sg:postcode":"25003",
    "sg:province":"Lleida",
    "wof:name":"Corretti Couste Juan Jose",
    "wof:placetype":"venue"
},
  "geometry": {"coordinates":[0.6150929928,41.6117706299],"type":"Point"}
}