{
  "type": "Feature",
  "properties": {
    "iso:country":"ES",
    "sg:address":"Calle de Eduardo Balmaseda, 12",
    "sg:city":"Galilea",
    "sg:orig_category":"Charcuter\u00cdas (al Por Mayor)",
    "sg:phone":"+34 941 48 00 78",
    "sg:postcode":"26144",
    "sg:province":"La Rioja",
    "wof:name":"Herederos De Jose Manuel Ca\u00f1as Uru\u00f1uela C.b.",
    "wof:placetype":"venue"
},
  "geometry": {"coordinates":[-2.2349255085,42.3452339172],"type":"Point"}
}