{
  "type": "Feature",
  "properties": {
    "iso:country":"ES",
    "sg:address":"Ctra Montcada, 192",
    "sg:city":"Terrassa",
    "sg:orig_category":"Agentes, Concesionarios Y Sucursales De Veh\u00cdculos",
    "sg:phone":"+34 937 31 80 22",
    "sg:postcode":"08223",
    "sg:province":"Barcelona",
    "wof:name":"Motor Munich S.a.",
    "wof:placetype":"venue"
},
  "geometry": {"coordinates":[2.0137729645,41.5573692322],"type":"Point"}
}