{
  "type": "Feature",
  "properties": {
    "addr:full":"Rua Valle Inclan, 25 Ourense Ourense 32004",
    "addr:housenumber":"25",
    "addr:postcode":"32004",
    "addr:street":"Rua Valle Inclan",
    "iso:country":"ES",
    "sg:address":"Rua Valle Inclan, 25",
    "sg:city":"Ourense",
    "sg:orig_category":"Abogados",
    "sg:phone":"+34 988 25 14 12",
    "sg:postcode":"32004",
    "sg:province":"Ourense",
    "wof:name":"Gonzalez Calvo Aurelia",
    "wof:placetype":"venue"
},
  "geometry": {"coordinates":[-7.8622279167,42.3408622742],"type":"Point"}
}