{
  "type": "Feature",
  "properties": {
    "iso:country":"ES",
    "sg:address":"Calle de Fray Isidoro De Sevilla, 15",
    "sg:city":"Sevilla",
    "sg:orig_category":"Agentes, Concesionarios Y Sucursales De Camiones Y Veh\u00cdculos Industriales",
    "sg:phone":"+34 954 35 64 10",
    "sg:postcode":"41009",
    "sg:province":"Sevilla",
    "wof:name":"Revuelta Castro Jose Diego",
    "wof:placetype":"venue"
},
  "geometry": {"coordinates":[-5.9829912186,37.4039154053],"type":"Point"}
}