{
  "type": "Feature",
  "properties": {
    "iso:country":"ES",
    "sg:address":"Avda. I. Gonzalez, 48",
    "sg:city":"Galaroza",
    "sg:orig_category":"Empresas De Carpinter\u00cda De Madera",
    "sg:phone":"+34 959 12 30 06",
    "sg:postcode":"21291",
    "sg:province":"Huelva",
    "wof:name":"Andreu Olivera Juan Luis",
    "wof:placetype":"venue"
},
  "geometry": {"coordinates":[-6.7055635452,37.9251747131],"type":"Point"}
}