{
  "type": "Feature",
  "properties": {
    "iso:country":"ES",
    "sg:address":"Avda Rufo G Rendueles, 22",
    "sg:city":"Gijon",
    "sg:orig_category":"Transportes Por V\u00cdas Navegables",
    "sg:phone":"+34 985 37 03 39",
    "sg:postcode":"33203",
    "sg:province":"Asturias",
    "wof:name":"Aguilera Alberto Alcubilla",
    "wof:placetype":"venue"
},
  "geometry": {"coordinates":[-5.6450119019,43.5399398804],"type":"Point"}
}