{
  "type": "Feature",
  "properties": {
    "addr:full":"Calle de Arquitecto Morell, 8 Alacant Alicante 03003",
    "addr:housenumber":"8",
    "addr:postcode":"03003",
    "addr:street":"Calle De Arquitecto Morell",
    "iso:country":"ES",
    "sg:address":"Calle de Arquitecto Morell, 8",
    "sg:city":"Alacant",
    "sg:orig_category":"Ingeniero",
    "sg:phone":"+34 965 12 30 48",
    "sg:postcode":"03003",
    "sg:province":"Alicante",
    "wof:name":"France Telecom Espa\u00d1a S.a.",
    "wof:placetype":"venue"
},
  "geometry": {"coordinates":[-0.4921920002,38.3422393799],"type":"Point"}
}