{
  "type": "Feature",
  "properties": {
    "iso:country":"ES",
    "sg:address":"Calle de Eduardo Rivas, 18",
    "sg:city":"Madrid",
    "sg:orig_category":"Molduras, Junquillos, Listones Y Molduras Perforadas",
    "sg:phone":"+34 915 69 82 75",
    "sg:postcode":"28019",
    "sg:province":"Madrid",
    "wof:name":"Bonoko Riva Antonia Magdalena",
    "wof:placetype":"venue"
},
  "geometry": {"coordinates":[-3.7134299278,40.3907279968],"type":"Point"}
}