{
  "type": "Feature",
  "properties": {
    "addr:full":"Calle de Gran Avenida, 39 Madrid Madrid 28041",
    "addr:housenumber":"39",
    "addr:postcode":"madrid;28041",
    "addr:street":"Calle De Gran Avenida",
    "iso:country":"ES",
    "sg:address":"Calle de Gran Avenida, 39",
    "sg:city":"Madrid",
    "sg:orig_category":"Pintura, Barniz, Productos Asimilables (fabricaci\u00d3n, Al Por Mayor)",
    "sg:phone":"+34 913 41 72 16",
    "sg:postcode":"28041",
    "sg:province":"Madrid",
    "wof:name":"M. Fuentes Alonso Decoraciones S.l.",
    "wof:placetype":"venue"
},
  "geometry": {"coordinates":[-3.7049589157,40.3697166443],"type":"Point"}
}