{
  "type": "Feature",
  "properties": {
    "iso:country":"ES",
    "sg:address":"Carrer de Riu De L'or, 4",
    "sg:city":"Barcelona",
    "sg:orig_category":"Art\u00cdculos De Decoraci\u00d3n",
    "sg:phone":"+34 932 03 38 60",
    "sg:postcode":"08034",
    "sg:province":"Barcelona",
    "wof:name":"Lal A Mano Dise\u00f1o S.l.",
    "wof:placetype":"venue"
},
  "geometry": {"coordinates":[2.1242761612,41.3926925659],"type":"Point"}
}