{
  "type": "Feature",
  "properties": {
    "addr:full":"Carrer de Cadi, S/n Roca Valles Barcelona 08430",
    "addr:housenumber":"s / n",
    "addr:postcode":"08430",
    "addr:street":"Carrer De Cadi;Barcelona",
    "iso:country":"ES",
    "sg:address":"Carrer de Cadi, S/n",
    "sg:city":"Roca Valles",
    "sg:orig_category":"Promotores Constructores",
    "sg:phone":"+34 938 42 40 31",
    "sg:postcode":"08430",
    "sg:province":"Barcelona",
    "wof:name":"Orthogar S.l.",
    "wof:placetype":"venue"
},
  "geometry": {"coordinates":[2.3770260811,41.6025276184],"type":"Point"}
}