{
  "type": "Feature",
  "properties": {
    "addr:full":"Calle de Quevedo Y Quintana, 5 Badajoz Badajoz 06008",
    "addr:housenumber":"5",
    "addr:postcode":"06008",
    "addr:street":"Calle De Quevedo Y Quintana",
    "iso:country":"ES",
    "sg:address":"Calle de Quevedo Y Quintana, 5",
    "sg:city":"Badajoz",
    "sg:orig_category":"Quincaller\u00cda (al Por Menor)",
    "sg:phone":"+34 924 23 70 12",
    "sg:postcode":"06008",
    "sg:province":"Badajoz",
    "wof:name":"Calderon Manzano Adela",
    "wof:placetype":"venue"
},
  "geometry": {"coordinates":[-6.9604167938,38.8786087036],"type":"Point"}
}