{
  "type": "Feature",
  "properties": {
    "iso:country":"ES",
    "sg:address":"Juan Gisasola Kalea, 18",
    "sg:city":"Eibar",
    "sg:orig_category":"Alimentaci\u00d3n General (al Por Menor)",
    "sg:phone":"+34 943 20 37 34",
    "sg:postcode":"20600",
    "sg:province":"Guip\u00f9zcoa",
    "wof:name":"Elena Lopez Arrizabalaga",
    "wof:placetype":"venue"
},
  "geometry": {"coordinates":[-2.4717280865,43.1819000244],"type":"Point"}
}