{
  "type": "Feature",
  "properties": {
    "iso:country":"ES",
    "sg:address":"Calle de Mayor, 70",
    "sg:city":"Raal",
    "sg:orig_category":"Supermercados Y Hipermercados",
    "sg:phone":"+34 968 81 12 35",
    "sg:postcode":"30139",
    "sg:province":"Murcia",
    "wof:name":"Supermercados El Jarabe S.l.",
    "wof:placetype":"venue"
},
  "geometry": {"coordinates":[-1.0524971485,38.016242981],"type":"Point"}
}