{
  "type": "Feature",
  "properties": {
    "iso:country":"ES",
    "sg:address":"Calle de Manuel Tovar, 19",
    "sg:city":"Madrid",
    "sg:orig_category":"Ortopedia General",
    "sg:phone":"+34 917 28 04 40",
    "sg:postcode":"28034",
    "sg:province":"Madrid",
    "wof:name":"Establecimientos Ortopedicos Prim S.a.",
    "wof:placetype":"venue"
},
  "geometry": {"coordinates":[-3.6887230873,40.4882087708],"type":"Point"}
}