{
  "type": "Feature",
  "properties": {
    "iso:country":"ES",
    "sg:address":"Calle de Eras, 9",
    "sg:city":"Iscar",
    "sg:orig_category":"Comercio De Piezas De Recambio Y De Accesorios De Veh\u00cdculos, Veh\u00cdculos Industriales",
    "sg:phone":"+34 983 61 27 17",
    "sg:postcode":"47420",
    "sg:province":"Valladolid",
    "wof:name":"Digimovil S.a.",
    "wof:placetype":"venue"
},
  "geometry": {"coordinates":[-4.5278577805,41.358543396],"type":"Point"}
}