{
  "type": "Feature",
  "properties": {
    "iso:country":"ES",
    "sg:address":"Ctra Agost, 23",
    "sg:city":"San Vicente Del Raspeig-sant Vicent Del Raspeig",
    "sg:orig_category":"Masajistas Kinesiterapeutas",
    "sg:phone":"+34 965 67 52 57",
    "sg:postcode":"03690",
    "sg:province":"Alicante",
    "wof:name":"Mateo Robles Roberto Cayetano",
    "wof:placetype":"venue"
},
  "geometry": {"coordinates":[-0.523845017,38.3996315002],"type":"Point"}
}