{
  "type": "Feature",
  "properties": {
    "iso:country":"ES",
    "sg:address":"Pl Major, 27",
    "sg:city":"Vic",
    "sg:orig_category":"Reposter\u00cdas",
    "sg:phone":"+34 938 86 16 50",
    "sg:postcode":"08500",
    "sg:province":"Barcelona",
    "wof:name":"Mas Masvidal Carmen",
    "wof:placetype":"venue"
},
  "geometry": {"coordinates":[2.2547879219,41.9307861328],"type":"Point"}
}