{
  "type": "Feature",
  "properties": {
    "iso:country":"ES",
    "sg:address":"Calle de Astilleros, General, 122",
    "sg:city":"Melilla",
    "sg:orig_category":"Telas Y Sedas (al Por Menor)",
    "sg:phone":"+34 952 67 02 58",
    "sg:postcode":"52006",
    "sg:province":"Melilla",
    "wof:name":"Arrandani Boualam Mohamed",
    "wof:placetype":"venue"
},
  "geometry": {"coordinates":[-2.938021183,35.2766456604],"type":"Point"}
}