{
  "type": "Feature",
  "properties": {
    "iso:country":"ES",
    "sg:address":"Calle de Alcarria (de La), 7",
    "sg:city":"Coslada",
    "sg:orig_category":"Transportes Internacionales",
    "sg:phone":"+34 916 74 26 88",
    "sg:postcode":"28820",
    "sg:province":"Madrid",
    "wof:name":"G.v.expres S.a.",
    "wof:placetype":"venue"
},
  "geometry": {"coordinates":[-3.5493452549,40.4310455322],"type":"Point"}
}