{
  "type": "Feature",
  "properties": {
    "addr:full":"Avgd Paral.lel (del), 50 Almussafes Valencia 46440",
    "addr:postcode":"46440",
    "iso:country":"ES",
    "sg:address":"Avgd Paral.lel (del), 50",
    "sg:city":"Almussafes",
    "sg:orig_category":"Alimentaci\u00d3n General (al Por Menor)",
    "sg:phone":"+34 961 78 30 47",
    "sg:postcode":"46440",
    "sg:province":"Valencia",
    "wof:name":"Reines Rodrigo Francisca",
    "wof:placetype":"venue"
},
  "geometry": {"coordinates":[-0.4124459922,39.2940826416],"type":"Point"}
}