{
  "type": "Feature",
  "properties": {
    "addr:full":"Calle de San Antonio, 46 Sonseca Toledo 45100",
    "addr:housenumber":"46",
    "addr:postcode":"45100",
    "addr:street":"Calle De San Antonio",
    "iso:country":"ES",
    "sg:address":"Calle de San Antonio, 46",
    "sg:city":"Sonseca",
    "sg:orig_category":"Agentes Generales De Seguros",
    "sg:phone":"+34 925 38 08 91",
    "sg:postcode":"45100",
    "sg:province":"Toledo",
    "wof:name":"Cerde\u00f1o Sanchez Francisco",
    "wof:placetype":"venue"
},
  "geometry": {"coordinates":[-3.966299057,39.6773414612],"type":"Point"}
}