{
  "type": "Feature",
  "properties": {
    "addr:full":"Calle de Ugarte, 1 Elexalde Vizcaya 48970",
    "addr:housenumber":"1",
    "addr:postcode":"48970",
    "addr:street":"Calle De Ugarte",
    "iso:country":"ES",
    "sg:address":"Calle de Ugarte, 1",
    "sg:city":"Elexalde",
    "sg:orig_category":"Supermercados Y Hipermercados",
    "sg:phone":"+34 944 26 26 30",
    "sg:postcode":"48970",
    "sg:province":"Vizcaya",
    "wof:name":"Alimentacion Mas Por Menos S.l.",
    "wof:placetype":"venue"
},
  "geometry": {"coordinates":[-2.8884935379,43.2259216309],"type":"Point"}
}