{
  "type": "Feature",
  "properties": {
    "iso:country":"ES",
    "sg:address":"Calle de Salvino Sierra, 4",
    "sg:city":"Palencia",
    "sg:orig_category":"Asociaciones Humanitarias, De Cooperaci\u00d3n, De Acci\u00d3n Social",
    "sg:phone":"+34 979 75 27 15",
    "sg:postcode":"34005",
    "sg:province":"Palencia",
    "wof:name":"Asociacion De Enfermos Contra El Ri\u00f1on",
    "wof:placetype":"venue"
},
  "geometry": {"coordinates":[-4.5386252403,42.0108528137],"type":"Point"}
}