{
  "type": "Feature",
  "properties": {
    "addr:full":"Calle de Alfonso Xii, 26 Madrid Madrid 28014",
    "addr:housenumber":"26",
    "addr:postcode":"madrid;28014",
    "addr:street":"Calle De Alfonso Xii",
    "iso:country":"ES",
    "sg:address":"Calle de Alfonso Xii, 26",
    "sg:city":"Madrid",
    "sg:orig_category":"Empresarios",
    "sg:phone":"+34 915 32 92 64",
    "sg:postcode":"28014",
    "sg:province":"Madrid",
    "wof:name":"Fundacion Endesa",
    "wof:placetype":"venue"
},
  "geometry": {"coordinates":[-3.6890690327,40.4157295227],"type":"Point"}
}