{
  "type": "Feature",
  "properties": {
    "addr:full":"Avda Almozara, 5 Zaragoza Zaragoza 50003",
    "addr:housenumber":"5",
    "addr:postcode":"50003",
    "addr:street":"Avda Almozara",
    "iso:country":"ES",
    "sg:address":"Avda Almozara, 5",
    "sg:city":"Zaragoza",
    "sg:orig_category":"Caf\u00c9s, Bares, Cervecer\u00cdas",
    "sg:phone":"+34 976 44 67 81",
    "sg:postcode":"50003",
    "sg:province":"Zaragoza",
    "wof:name":"Sistelcom-telemensaje S.a.",
    "wof:placetype":"venue"
},
  "geometry": {"coordinates":[-0.8963879943,41.6613731384],"type":"Point"}
}