{
  "type": "Feature",
  "properties": {
    "iso:country":"ES",
    "sg:address":"Calle de Miguel Arredondo, 4",
    "sg:city":"Madrid",
    "sg:orig_category":"Bisuter\u00cda, Joyer\u00cda, Relojer\u00cda (al Por Menor)",
    "sg:phone":"+34 914 74 07 98",
    "sg:postcode":"28045",
    "sg:province":"Madrid",
    "wof:name":"Matamala Guerra Andres",
    "wof:placetype":"venue"
},
  "geometry": {"coordinates":[-3.6960179806,40.3950004578],"type":"Point"}
}