{
  "type": "Feature",
  "properties": {
    "addr:full":"Calle de Correos, 6 Banyeres Mariola Alicante 03450",
    "addr:housenumber":"6",
    "addr:postcode":"03450",
    "addr:street":"Calle De Correos",
    "iso:country":"ES",
    "sg:address":"Calle de Correos, 6",
    "sg:city":"Banyeres Mariola",
    "sg:orig_category":"M\u00c9dicos: Estomatolog\u00cda",
    "sg:phone":"+34 965 56 74 71",
    "sg:postcode":"03450",
    "sg:province":"Alicante",
    "wof:name":"Randaxhe Heredero Mabel",
    "wof:placetype":"venue"
},
  "geometry": {"coordinates":[-0.6595144272,38.7171783447],"type":"Point"}
}