{
  "type": "Feature",
  "properties": {
    "iso:country":"ES",
    "sg:address":"Calle de Condes De Crespo Rascon, 12",
    "sg:city":"Salamanca",
    "sg:orig_category":"Abogados",
    "sg:phone":"+34 923 26 86 78",
    "sg:postcode":"37002",
    "sg:province":"Salamanca",
    "wof:name":"Lopez Diaz Rafael",
    "wof:placetype":"venue"
},
  "geometry": {"coordinates":[-5.6657853127,40.9670181274],"type":"Point"}
}