{
  "type": "Feature",
  "properties": {
    "addr:full":"Calle de Cementerio, S/n Yeste Albacete 02480",
    "addr:housenumber":"s",
    "addr:postcode":"02480",
    "addr:street":"Calle De Cementerio;/ N Yeste",
    "iso:country":"ES",
    "sg:address":"Calle de Cementerio, S/n",
    "sg:city":"Yeste",
    "sg:orig_category":"Empresas De Carpinter\u00cda De Madera",
    "sg:phone":"+34 967 54 00 17",
    "sg:postcode":"02480",
    "sg:province":"Albacete",
    "wof:name":"Martinez Torrecillas Miguel Angel",
    "wof:placetype":"venue"
},
  "geometry": {"coordinates":[-2.3418869972,38.3354225159],"type":"Point"}
}