{
  "type": "Feature",
  "properties": {
    "iso:country":"ES",
    "sg:address":"Carrer de Pujades, 69",
    "sg:city":"Barcelona",
    "sg:orig_category":"Adhesivos (fabricaci\u00d3n, Al Por Mayor)",
    "sg:phone":"+34 933 03 04 15",
    "sg:postcode":"08005",
    "sg:province":"Barcelona",
    "sg:website":"www.caubis.es",
    "wof:name":"Cintas Adhesivas Ubis S. A.",
    "wof:placetype":"venue"
},
  "geometry": {"coordinates":[2.1939070225,41.3967437744],"type":"Point"}
}