{
  "type": "Feature",
  "properties": {
    "addr:full":"Trva Collado, 2 Bejar Salamanca 37700",
    "addr:housenumber":"2",
    "addr:postcode":"37700",
    "addr:street":"Trva Collado",
    "iso:country":"ES",
    "sg:address":"Trva Collado, 2",
    "sg:city":"Bejar",
    "sg:orig_category":"Seguridad Social",
    "sg:phone":"+34 923 40 41 12",
    "sg:postcode":"37700",
    "sg:province":"Salamanca",
    "wof:name":"Mutua Universal Mugenat Matepss 10",
    "wof:placetype":"venue"
},
  "geometry": {"coordinates":[-5.7651867867,40.3871917725],"type":"Point"}
}