{
  "type": "Feature",
  "properties": {
    "addr:full":"Bule Buenos Aires (de), 1 Alcala Henares Madrid 28806",
    "addr:postcode":"28806",
    "iso:country":"ES",
    "sg:address":"Bule Buenos Aires (de), 1",
    "sg:city":"Alcala Henares",
    "sg:orig_category":"Comercio De Piezas De Recambio Y De Accesorios De Veh\u00cdculos, Veh\u00cdculos Industriales",
    "sg:phone":"+34 918 02 16 44",
    "sg:postcode":"28806",
    "sg:province":"Madrid",
    "wof:name":"Comercial Colmenar Corredor Del Henares S.l.",
    "wof:placetype":"venue"
},
  "geometry": {"coordinates":[-3.4063129425,40.5129585266],"type":"Point"}
}