{
  "type": "Feature",
  "properties": {
    "iso:country":"ES",
    "sg:address":"Cillobre, S/n",
    "sg:city":"Laracha",
    "sg:orig_category":"Empresas De Carpinter\u00cda De Madera",
    "sg:phone":"+34 981 60 51 76",
    "sg:postcode":"15145",
    "sg:province":"La Coru\u00f1a",
    "wof:name":"Manuel Ricardo Borrallo Verdio Y Otros S.c.",
    "wof:placetype":"venue"
},
  "geometry": {"coordinates":[-8.5813436508,43.2482681274],"type":"Point"}
}