{
  "type": "Feature",
  "properties": {
    "addr:full":"Av Onze De Setembre, 1 Olot Girona 17800",
    "addr:housenumber":"1",
    "addr:postcode":"17800",
    "addr:street":"Av Onze De Setembre",
    "iso:country":"ES",
    "sg:address":"Av Onze De Setembre, 1",
    "sg:city":"Olot",
    "sg:classifiers":[
        {
            "category":"Autos & Motor Vehicles",
            "subcategory":"Automobile Sales",
            "type":"Retail Goods"
        }
    ],
    "sg:phone":"+34 972 26 23 10",
    "sg:postcode":"17800",
    "sg:province":"Girona",
    "wof:name":"Auto Escola Pirineu",
    "wof:placetype":"venue"
},
  "geometry": {"coordinates":[2.4928126335,42.1821174622],"type":"Point"}
}