{
  "type": "Feature",
  "properties": {
    "addr:full":"Calle de Washington, 1 Coru\u00d1a La Coru\u00f1a 15002",
    "addr:housenumber":"1",
    "addr:postcode":"15002",
    "addr:street":"Calle De Washington;La Corun\u0303A",
    "iso:country":"ES",
    "sg:address":"Calle de Washington, 1",
    "sg:city":"Coru\u00d1a",
    "sg:orig_category":"Alimentaci\u00d3n General (al Por Menor)",
    "sg:phone":"+34 981 20 00 03",
    "sg:postcode":"15002",
    "sg:province":"La Coru\u00f1a",
    "wof:name":"Alvarez Fernandez Maria Emerita",
    "wof:placetype":"venue"
},
  "geometry": {"coordinates":[-8.4065151215,43.3791236877],"type":"Point"}
}