{
  "type": "Feature",
  "properties": {
    "addr:full":"Avda Oviedo, 4 Alacant Alicante 03540",
    "addr:housenumber":"4",
    "addr:postcode":"03540",
    "addr:street":"Avda Oviedo",
    "iso:country":"ES",
    "sg:address":"Avda Oviedo, 4",
    "sg:city":"Alacant",
    "sg:orig_category":"Ingenier\u00cda, Centros De Estudios (diversos)",
    "sg:phone":"+34 965 26 05 79",
    "sg:postcode":"03540",
    "sg:province":"Alicante",
    "wof:name":"Pe\u00f1afiel De Rio Antonio",
    "wof:placetype":"venue"
},
  "geometry": {"coordinates":[-0.4182980061,38.3771133423],"type":"Point"}
}