{
  "type": "Feature",
  "properties": {
    "addr:full":"Carrer de Muntaner, 565 Barcelona Barcelona 08022",
    "addr:housenumber":"565",
    "addr:postcode":"08022",
    "addr:street":"Carrer De Muntaner",
    "iso:country":"ES",
    "sg:address":"Carrer de Muntaner, 565",
    "sg:city":"Barcelona",
    "sg:orig_category":"Confecci\u00d3n De Trajes Para Se\u00d1oras",
    "sg:phone":"+34 932 12 68 00",
    "sg:postcode":"08022",
    "sg:province":"Barcelona",
    "sg:website":"www.induyco.com",
    "wof:name":"Industrias Y Confecciones S. A.",
    "wof:placetype":"venue"
},
  "geometry": {"coordinates":[2.1344790459,41.4055480957],"type":"Point"}
}