{
  "type": "Feature",
  "properties": {
    "iso:country":"ES",
    "sg:address":"Bellavista, 11",
    "sg:city":"Mijas Costa",
    "sg:orig_category":"Agencias Y Asesores De Publicidad",
    "sg:phone":"+34 952 49 32 91",
    "sg:postcode":"29649",
    "sg:province":"M\u00e1laga",
    "wof:name":"Galantis Soportes Publicitarios S.l.",
    "wof:placetype":"venue"
},
  "geometry": {"coordinates":[-4.6675100327,36.5081253052],"type":"Point"}
}