{
  "type": "Feature",
  "properties": {
    "iso:country":"ES",
    "sg:address":"Calle de Doctor Fleming, 1",
    "sg:city":"Armilla",
    "sg:orig_category":"Chapister\u00cda",
    "sg:phone":"+34 958 55 36 00",
    "sg:postcode":"18100",
    "sg:province":"Granada",
    "wof:name":"Chapa Y Pintura Autocolor Almilla S.l.",
    "wof:placetype":"venue"
},
  "geometry": {"coordinates":[-3.6238963604,37.1456489563],"type":"Point"}
}