{
  "type": "Feature",
  "properties": {
    "iso:country":"ES",
    "sg:address":"Calle de Camino De Los Vinateros, 125",
    "sg:city":"Madrid",
    "sg:orig_category":"Frutas, Legumbres Frescas Y Tempranas (al Por Menor)",
    "sg:phone":"+34 917 73 20 46",
    "sg:postcode":"28030",
    "sg:province":"Madrid",
    "wof:name":"Frutas Periqui S.l.",
    "wof:placetype":"venue"
},
  "geometry": {"coordinates":[-3.6434304714,40.4063529968],"type":"Point"}
}