{
  "type": "Feature",
  "properties": {
    "iso:country":"ES",
    "sg:address":"Calle de Murillo, 18",
    "sg:city":"Torrijos",
    "sg:orig_category":"Asilos De Ancianos. Centros Privados",
    "sg:phone":"+34 925 76 09 51",
    "sg:postcode":"45500",
    "sg:province":"Toledo",
    "wof:name":"Residencia Los Enlaces S.l.",
    "wof:placetype":"venue"
},
  "geometry": {"coordinates":[-4.288351059,39.981754303],"type":"Point"}
}