{
  "type": "Feature",
  "properties": {
    "iso:country":"ES",
    "sg:address":"Carrer de Grases, 1",
    "sg:city":"Barcelona",
    "sg:orig_category":"Tintes (fabricaci\u00d3n, Al Por Mayor)",
    "sg:phone":"+34 934 26 89 17",
    "sg:postcode":"08004",
    "sg:province":"Barcelona",
    "wof:name":"Llano Mosteirin Carmen",
    "wof:placetype":"venue"
},
  "geometry": {"coordinates":[2.1566989422,41.3736152649],"type":"Point"}
}