{
  "type": "Feature",
  "properties": {
    "iso:country":"ES",
    "sg:address":"Vereda Del Vicario, S/n",
    "sg:city":"Ciudad Real",
    "sg:orig_category":"Ense\u00d1anza Agr\u00cdcola",
    "sg:phone":"+34 926 69 02 41",
    "sg:postcode":"13005",
    "sg:province":"Ciudad Real",
    "wof:name":"Granja Escuela Orea",
    "wof:placetype":"venue"
},
  "geometry": {"coordinates":[-3.9288609028,38.9996757507],"type":"Point"}
}