{
  "type": "Feature",
  "properties": {
    "iso:country":"ES",
    "sg:address":"Av Badalona, 31",
    "sg:city":"Mollet Valles",
    "sg:orig_category":"Ingenier\u00cda, Centros De Estudios (diversos)",
    "sg:phone":"+34 935 79 27 88",
    "sg:postcode":"08100",
    "sg:province":"Barcelona",
    "wof:name":"Enbolf S.a.",
    "wof:placetype":"venue"
},
  "geometry": {"coordinates":[2.2166249752,41.5438613892],"type":"Point"}
}