{
  "type": "Feature",
  "properties": {
    "iso:country":"ES",
    "sg:address":"Av. B. Navarra, 8",
    "sg:city":"Iru\u00f1a",
    "sg:orig_category":"Comisarios",
    "sg:phone":"+34 948 24 82 38",
    "sg:postcode":"31003",
    "sg:province":"Navarra",
    "wof:name":"Iruretagoyena Ubarrechena Maria Rosario",
    "wof:placetype":"venue"
},
  "geometry": {"coordinates":[-1.6700780392,42.8215179443],"type":"Point"}
}