{
  "type": "Feature",
  "properties": {
    "iso:country":"ES",
    "sg:address":"Pase Mu\u00d1oz Grandes, 31",
    "sg:city":"Madrid",
    "sg:orig_category":"Molduras, Junquillos, Listones Y Molduras Perforadas",
    "sg:phone":"+34 914 65 10 55",
    "sg:postcode":"28025",
    "sg:province":"Madrid",
    "wof:name":"Rodriguez Rey Ambrosio",
    "wof:placetype":"venue"
},
  "geometry": {"coordinates":[-3.7423129082,40.386554718],"type":"Point"}
}