{
  "type": "Feature",
  "properties": {
    "addr:full":"Calle de Peru, 4 Valladolid Valladolid 47004",
    "addr:housenumber":"4",
    "addr:postcode":"47004",
    "addr:street":"Calle De Peru",
    "iso:country":"ES",
    "sg:address":"Calle de Peru, 4",
    "sg:city":"Valladolid",
    "sg:orig_category":"Ense\u00d1anza: Idiomas",
    "sg:phone":"+34 983 29 94 75",
    "sg:postcode":"47004",
    "sg:province":"Valladolid",
    "wof:name":"Carnero San Jose Maria Eugenia",
    "wof:placetype":"venue"
},
  "geometry": {"coordinates":[-4.7264318466,41.6480407715],"type":"Point"}
}