{
  "type": "Feature",
  "properties": {
    "addr:full":"Avda Huesca (de), 16 Sabi\u00f1anigo Huesca 22600",
    "addr:housenumber":"16",
    "addr:postcode":"22600",
    "addr:street":"Avda Huesca De",
    "iso:country":"ES",
    "sg:address":"Avda Huesca (de), 16",
    "sg:city":"Sabi\u00f1anigo",
    "sg:orig_category":"Agentes Generales De Seguros",
    "sg:phone":"+34 974 48 01 29",
    "sg:postcode":"22600",
    "sg:province":"Huesca",
    "wof:name":"Bandres De Los Reyes S.c.",
    "wof:placetype":"venue"
},
  "geometry": {"coordinates":[-0.3615919948,42.5153503418],"type":"Point"}
}