{
  "type": "Feature",
  "properties": {
    "addr:full":"Calle de Poligono, 40 Jerez De Los Caballeros Badajoz 06380",
    "addr:housenumber":"40",
    "addr:postcode":"06380",
    "addr:street":"Calle De Poligono",
    "iso:country":"ES",
    "sg:address":"Calle de Poligono, 40",
    "sg:city":"Jerez De Los Caballeros",
    "sg:orig_category":"Mec\u00c1nico Del Autom\u00d3vil",
    "sg:phone":"+34 924 75 01 02",
    "sg:postcode":"06380",
    "sg:province":"Badajoz",
    "wof:name":"Mu\u00f1oz Rubio Eleuterio",
    "wof:placetype":"venue"
},
  "geometry": {"coordinates":[-6.7697892189,38.3272514343],"type":"Point"}
}