{
  "type": "Feature",
  "properties": {
    "addr:full":"Carrer de Menendez Pelayo, 46 Amposta Tarragona 43870",
    "addr:housenumber":"46",
    "addr:postcode":"43870",
    "addr:street":"Carrer De Menendez Pelayo",
    "iso:country":"ES",
    "sg:address":"Carrer de Menendez Pelayo, 46",
    "sg:city":"Amposta",
    "sg:orig_category":"Cristaler\u00cdas",
    "sg:phone":"+34 977 70 42 57",
    "sg:postcode":"43870",
    "sg:province":"Tarragona",
    "wof:name":"Vidres I Persianes Amposta S.l.",
    "wof:placetype":"venue"
},
  "geometry": {"coordinates":[0.5784670115,40.7072753906],"type":"Point"}
}