{
  "type": "Feature",
  "properties": {
    "addr:full":"La Vega, 3 Salas Asturias 33860",
    "addr:housenumber":"3",
    "addr:postcode":"33860",
    "addr:street":"La Vega",
    "iso:country":"ES",
    "sg:address":"La Vega, 3",
    "sg:city":"Salas",
    "sg:orig_category":"Formaci\u00d3n Continuada (variada)",
    "sg:phone":"+34 985 83 03 32",
    "sg:postcode":"33860",
    "sg:province":"Asturias",
    "wof:name":"Lafuente Alvarez Jose Antonio",
    "wof:placetype":"venue"
},
  "geometry": {"coordinates":[-6.2297859192,43.4426383972],"type":"Point"}
}