{
  "type": "Feature",
  "properties": {
    "addr:full":"Av Santiga, S/n Santa Perpetua De Mogoda Barcelona 08130",
    "addr:housenumber":"s / n",
    "addr:postcode":"08130",
    "addr:street":"Av Santiga",
    "iso:country":"ES",
    "sg:address":"Av Santiga, S/n",
    "sg:city":"Santa Perpetua De Mogoda",
    "sg:orig_category":"Pescader\u00cdas (al Por Menor)",
    "sg:phone":"+34 935 44 80 17",
    "sg:postcode":"08130",
    "sg:province":"Barcelona",
    "wof:name":"Pacheco Bermudez Remedios",
    "wof:placetype":"venue"
},
  "geometry": {"coordinates":[2.181319952,41.5372200012],"type":"Point"}
}