{
  "type": "Feature",
  "properties": {
    "addr:full":"Carrer de Muntaner, 239 Barcelona Barcelona 08021",
    "addr:housenumber":"239",
    "addr:postcode":"08021",
    "addr:street":"Carrer De Muntaner",
    "iso:country":"ES",
    "sg:address":"Carrer de Muntaner, 239",
    "sg:city":"Barcelona",
    "sg:orig_category":"Abogados",
    "sg:phone":"+34 932 02 12 22",
    "sg:postcode":"08021",
    "sg:province":"Barcelona",
    "wof:name":"Carcel Miret Valentin",
    "wof:placetype":"venue"
},
  "geometry": {"coordinates":[2.1486930847,41.3945617676],"type":"Point"}
}