{
  "type": "Feature",
  "properties": {
    "addr:full":"Rier Pahissa, S/n Sant Feliu Llobregat Barcelona 08980",
    "addr:housenumber":"s",
    "addr:postcode":"08980",
    "addr:street":"/ N",
    "iso:country":"ES",
    "sg:address":"Rier Pahissa, S/n",
    "sg:city":"Sant Feliu Llobregat",
    "sg:orig_category":"Ense\u00d1anza, Formaci\u00d3n Profesional: Aprendizaje",
    "sg:phone":"+34 936 66 11 95",
    "sg:postcode":"08980",
    "sg:province":"Barcelona",
    "wof:name":"Associacio Taller Sant Miquel",
    "wof:placetype":"venue"
},
  "geometry": {"coordinates":[2.0453329086,41.3774414062],"type":"Point"}
}