{
  "type": "Feature",
  "properties": {
    "iso:country":"ES",
    "sg:address":"Pol. Ind. Mas Roquet, S/n",
    "sg:city":"Palafolls",
    "sg:orig_category":"Productos Qu\u00cdmicos (fabricaci\u00d3n, Al Por Mayor)",
    "sg:phone":"+34 937 64 09 75",
    "sg:postcode":"08389",
    "sg:province":"Barcelona",
    "wof:name":"Sociedad Anonima Robama",
    "wof:placetype":"venue"
},
  "geometry": {"coordinates":[2.7497739792,41.6659660339],"type":"Point"}
}