{
  "type": "Feature",
  "properties": {
    "iso:country":"ES",
    "sg:address":"Calle de Borroto, 16",
    "sg:city":"Donostia-san Sebastian",
    "sg:orig_category":"Peluquer\u00cdas",
    "sg:phone":"+34 943 21 78 70",
    "sg:postcode":"20009",
    "sg:province":"Guip\u00f9zcoa",
    "wof:name":"Legarreta Escudero Maria Paz",
    "wof:placetype":"venue"
},
  "geometry": {"coordinates":[-1.9886269569,43.3013572693],"type":"Point"}
}