{
  "type": "Feature",
  "properties": {
    "iso:country":"ES",
    "sg:address":"Calle de Colon (de), S/n",
    "sg:city":"San Eugenio Bajo",
    "sg:orig_category":"Deportes N\u00c1uticos, Acu\u00c1ticos Y Subacu\u00c1ticos: Art\u00cdculos Y Equipo (al Por Menor)",
    "sg:phone":"+34 922 71 48 02",
    "sg:postcode":"38660",
    "sg:province":"Santa Cruz De Tenerife",
    "wof:name":"Peje Canarias S.a.",
    "wof:placetype":"venue"
},
  "geometry": {"coordinates":[-16.7354431152,28.0784606934],"type":"Point"}
}