{
  "type": "Feature",
  "properties": {
    "iso:country":"ES",
    "sg:address":"Carrer de Montseny, 17",
    "sg:city":"Poligon Industrial De Sant Pere Molanta",
    "sg:orig_category":"M\u00c1quinas Y Material Para La Industria De La Alimentaci\u00d3n",
    "sg:phone":"+34 938 92 35 00",
    "sg:postcode":"08799",
    "sg:province":"Barcelona",
    "sg:website":"www.serraprofess.com",
    "wof:name":"Construcciones Mecanicas J.serra S.a.",
    "wof:placetype":"venue"
},
  "geometry": {"coordinates":[1.7355200052,41.3499908447],"type":"Point"}
}