{
  "type": "Feature",
  "properties": {
    "iso:country":"ES",
    "sg:address":"Rua Arce, S/n",
    "sg:city":"Ferrol",
    "sg:classifiers":[
        {
            "category":"Communications",
            "type":"Services"
        }
    ],
    "sg:phone":"+34 981 35 45 84",
    "sg:postcode":"15401",
    "sg:province":"La Coru\u00f1a",
    "sg:tags":[
        "televisiones",
        "y",
        "radio"
    ],
    "wof:name":"Ferrolvision S.l.",
    "wof:placetype":"venue"
},
  "geometry": {"coordinates":[-8.2381238937,43.4820137024],"type":"Point"}
}