{
  "type": "Feature",
  "properties": {
    "iso:country":"ES",
    "sg:address":"Ctra Vic, 26",
    "sg:city":"Manresa",
    "sg:orig_category":"Carnicer\u00cdas, Carnicer\u00cdas",
    "sg:phone":"+34 938 74 69 05",
    "sg:postcode":"08241",
    "sg:province":"Barcelona",
    "wof:name":"Fornells Vilades Jose",
    "wof:placetype":"venue"
},
  "geometry": {"coordinates":[1.8271030188,41.7265968323],"type":"Point"}
}