{
  "type": "Feature",
  "properties": {
    "addr:full":"Calle de Rioja, 22 Sevilla Sevilla 41001",
    "addr:housenumber":"22",
    "addr:postcode":"41001",
    "addr:street":"Calle De Rioja",
    "iso:country":"ES",
    "sg:address":"Calle de Rioja, 22",
    "sg:city":"Sevilla",
    "sg:orig_category":"Ense\u00d1anza: Profesiones Art\u00cdsticas",
    "sg:phone":"+34 954 21 75 50",
    "sg:postcode":"41001",
    "sg:province":"Sevilla",
    "wof:name":"Enrique Estudio S.l.",
    "wof:placetype":"venue"
},
  "geometry": {"coordinates":[-5.996117115,37.3910751343],"type":"Point"}
}