{
  "type": "Feature",
  "properties": {
    "iso:country":"ES",
    "sg:address":"Poligono Uno, 6",
    "sg:city":"La Gineta",
    "sg:orig_category":"Producci\u00d3n, Venta De Productos De Agricultura Biol\u00d3gica",
    "sg:phone":"+34 967 27 50 80",
    "sg:postcode":"02110",
    "sg:province":"Albacete",
    "wof:name":"Cooperativas Agricolas Albacetenses S.c.l.",
    "wof:placetype":"venue"
},
  "geometry": {"coordinates":[-1.9937520027,39.1147003174],"type":"Point"}
}