{
  "type": "Feature",
  "properties": {
    "iso:country":"ES",
    "sg:address":"Calle de Gibraleon, 12",
    "sg:city":"Villanueva De Los Castillejos",
    "sg:orig_category":"Fabricaci\u00d3n De Cervezas",
    "sg:phone":"+34 959 38 71 03",
    "sg:postcode":"21540",
    "sg:province":"Huelva",
    "wof:name":"Distribuciones Vicasti S.l",
    "wof:placetype":"venue"
},
  "geometry": {"coordinates":[-7.2716670036,37.5004806519],"type":"Point"}
}