{
  "type": "Feature",
  "properties": {
    "iso:country":"ES",
    "sg:address":"Calle de Sabino Berthelot, 5",
    "sg:city":"Santa Cruz De Tenerife",
    "sg:orig_category":"Quincaller\u00cda (al Por Menor)",
    "sg:phone":"+34 922 53 14 65",
    "sg:postcode":"38003",
    "sg:province":"Santa Cruz De Tenerife",
    "wof:name":"Comercial Ferretera Canarias S. A.",
    "wof:placetype":"venue"
},
  "geometry": {"coordinates":[-16.2549476624,28.4677562714],"type":"Point"}
}