{
  "type": "Feature",
  "properties": {
    "iso:country":"ES",
    "sg:address":"Avda Galicia, 79",
    "sg:city":"Ponferrada",
    "sg:orig_category":"Asesor\u00cda Fiscal Y Jur\u00cddica",
    "sg:phone":"+34 987 41 99 66",
    "sg:postcode":"24400",
    "sg:province":"Le\u00f3n",
    "wof:name":"Lopez Crespo Maria Blanca Encarnacion",
    "wof:placetype":"venue"
},
  "geometry": {"coordinates":[-6.6145567894,42.5554351807],"type":"Point"}
}