{
  "type": "Feature",
  "properties": {
    "addr:full":"Carrer de Argentina, 5 Coloma Alicante 03530",
    "addr:housenumber":"5",
    "addr:postcode":"03530",
    "addr:street":"Carrer De Argentina",
    "iso:country":"ES",
    "sg:address":"Carrer de Argentina, 5",
    "sg:city":"Coloma",
    "sg:orig_category":"Molduras, Junquillos, Listones Y Molduras Perforadas",
    "sg:phone":"+34 966 87 50 41",
    "sg:postcode":"03530",
    "sg:province":"Alicante",
    "wof:name":"Kostetska  Erika",
    "wof:placetype":"venue"
},
  "geometry": {"coordinates":[-0.1249789968,38.6157951355],"type":"Point"}
}