{
  "type": "Feature",
  "properties": {
    "addr:full":"Ctra. Guijo, Km. 0001,0 Ahigal C\u00e1ceres 10650",
    "addr:postcode":"10650",
    "addr:street":"Ctra. Guijo Km. 0001,0 Ahigal Ca\u0301Ceres",
    "iso:country":"ES",
    "sg:address":"Ctra. Guijo, Km. 0001,0",
    "sg:city":"Ahigal",
    "sg:orig_category":"Distribuci\u00d3n De Petr\u00d3leo Y Derivados",
    "sg:phone":"+34 927 43 92 68",
    "sg:postcode":"10650",
    "sg:province":"C\u00e1ceres",
    "wof:name":"Estacion De Servicio Ahigal S.l.",
    "wof:placetype":"venue"
},
  "geometry": {"coordinates":[-6.1873140335,40.1892547607],"type":"Point"}
}