{
  "type": "Feature",
  "properties": {
    "addr:full":"Crt. Calzada, Km. 0024,5 Puertollano Ciudad Real 13500",
    "addr:postcode":"13500",
    "addr:street":"Calzada Km. 0024,5",
    "iso:country":"ES",
    "sg:address":"Crt. Calzada, Km. 0024,5",
    "sg:city":"Puertollano",
    "sg:orig_category":"Producci\u00d3n, Venta De Productos De Agricultura Biol\u00d3gica",
    "sg:phone":"+34 926 69 80 63",
    "sg:postcode":"13500",
    "sg:province":"Ciudad Real",
    "wof:name":"Garcia Fernandez Alejandro",
    "wof:placetype":"venue"
},
  "geometry": {"coordinates":[-4.1123538017,38.6858253479],"type":"Point"}
}