{
  "type": "Feature",
  "properties": {
    "iso:country":"ES",
    "sg:address":"Calle de Hornos (los), 36",
    "sg:city":"Andujar",
    "sg:orig_category":"Fabricaci\u00d3n De Cortinas Y Visillos",
    "sg:phone":"+34 953 51 34 09",
    "sg:postcode":"23740",
    "sg:province":"Ja\u00e9n",
    "wof:name":"Lopez Gomez Francisco",
    "wof:placetype":"venue"
},
  "geometry": {"coordinates":[-4.0499591827,38.0385284424],"type":"Point"}
}