{
  "type": "Feature",
  "properties": {
    "addr:full":"Pg Salzereda, 65 Santa Coloma De Gramenet Barcelona 08921",
    "addr:housenumber":"65",
    "addr:postcode":"08921",
    "addr:street":"Pg Salzereda",
    "iso:country":"ES",
    "sg:address":"Pg Salzereda, 65",
    "sg:city":"Santa Coloma De Gramenet",
    "sg:orig_category":"Carnicer\u00cdas, Carnicer\u00cdas",
    "sg:phone":"+34 933 85 13 99",
    "sg:postcode":"08921",
    "sg:province":"Barcelona",
    "wof:name":"Garcia Carranza Antonio",
    "wof:placetype":"venue"
},
  "geometry": {"coordinates":[2.2056460381,41.4469833374],"type":"Point"}
}