{
  "type": "Feature",
  "properties": {
    "iso:country":"ES",
    "sg:address":"Carrer de Josep Tarradellas (de), 7",
    "sg:city":"Montornes Centre",
    "sg:orig_category":"Comercio, Reparaci\u00d3n De Motocicletas, Bicicletas Y Piezas Sueltas",
    "sg:phone":"+34 935 79 90 12",
    "sg:postcode":"08170",
    "sg:province":"Barcelona",
    "wof:name":"Motos Blanchart S.c.p.",
    "wof:placetype":"venue"
},
  "geometry": {"coordinates":[2.2704920769,41.538230896],"type":"Point"}
}