{
  "type": "Feature",
  "properties": {
    "addr:full":"Calle de Cuesta La Estacion, 5 Valverde Camino Huelva 21600",
    "addr:housenumber":"5",
    "addr:postcode":"21600",
    "addr:street":"Calle De Cuesta La Estacion;Camino Huelva",
    "iso:country":"ES",
    "sg:address":"Calle de Cuesta La Estacion, 5",
    "sg:city":"Valverde Camino",
    "sg:orig_category":"Telas Y Sedas (al Por Menor)",
    "sg:phone":"+34 959 55 21 96",
    "sg:postcode":"21600",
    "sg:province":"Huelva",
    "wof:name":"Castelo Ponce Alicia",
    "wof:placetype":"venue"
},
  "geometry": {"coordinates":[-6.7505617142,37.5745353699],"type":"Point"}
}