{
  "type": "Feature",
  "properties": {
    "iso:country":"ES",
    "sg:address":"Calle de Joaquin Costa, 80",
    "sg:city":"Vall D'uixo",
    "sg:orig_category":"Reposter\u00cdas",
    "sg:phone":"+34 964 66 26 09",
    "sg:postcode":"12600",
    "sg:province":"Castell\u00f3n",
    "wof:name":"Gimeno Rivas Jose Antonio",
    "wof:placetype":"venue"
},
  "geometry": {"coordinates":[-0.0432350002,39.9907569885],"type":"Point"}
}