{
  "type": "Feature",
  "properties": {
    "iso:country":"ES",
    "sg:address":"Carrer de Sant Josep, 17",
    "sg:city":"Sant Feliu Llobregat",
    "sg:orig_category":"Empresas De Pintura Y Revestimientos",
    "sg:phone":"+34 936 66 06 14",
    "sg:postcode":"08980",
    "sg:province":"Barcelona",
    "wof:name":"Fatsini Arnal Juan",
    "wof:placetype":"venue"
},
  "geometry": {"coordinates":[2.0418729782,41.3800697327],"type":"Point"}
}