{
  "type": "Feature",
  "properties": {
    "iso:country":"ES",
    "sg:address":"Avda Ramon Y Cajal, 24",
    "sg:city":"Albacete",
    "sg:orig_category":"Caf\u00c9s, Bares, Cervecer\u00cdas",
    "sg:phone":"+34 967 52 26 48",
    "sg:postcode":"02005",
    "sg:province":"Albacete",
    "wof:name":"Merkalba S.a.l.",
    "wof:placetype":"venue"
},
  "geometry": {"coordinates":[-1.8583329916,39.0000801086],"type":"Point"}
}