{
  "type": "Feature",
  "properties": {
    "iso:country":"ES",
    "sg:address":"Calle de Alameda De Santa Eufemia, 24",
    "sg:city":"Tomares",
    "sg:orig_category":"Laboratorios Y Trabajos De Fotograf\u00cda, V\u00cddeo Y Cine",
    "sg:phone":"+34 954 15 16 10",
    "sg:postcode":"41940",
    "sg:province":"Sevilla",
    "wof:name":"Reche Arguijo Isabel Maria",
    "wof:placetype":"venue"
},
  "geometry": {"coordinates":[-6.0437202454,37.3759155273],"type":"Point"}
}