{
  "type": "Feature",
  "properties": {
    "iso:country":"ES",
    "sg:address":"Pg Elx, 51",
    "sg:city":"Crevillent",
    "sg:orig_category":"Fabricaci\u00d3n De Tapices Y Moquetas Para Suelos Y Paredes",
    "sg:phone":"+34 965 40 14 12",
    "sg:postcode":"03330",
    "sg:province":"Alicante",
    "wof:name":"Persiahan Gruphogar Textil S.l.",
    "wof:placetype":"venue"
},
  "geometry": {"coordinates":[-0.801379025,38.2479705811],"type":"Point"}
}