{
  "type": "Feature",
  "properties": {
    "iso:country":"ES",
    "sg:address":"Carrer de F Zona Franca, S/n",
    "sg:city":"Barcelona",
    "sg:orig_category":"Transporte En General",
    "sg:phone":"+34 933 35 30 64",
    "sg:postcode":"08040",
    "sg:province":"Barcelona",
    "wof:name":"Adisa Logistica S.a.",
    "wof:placetype":"venue"
},
  "geometry": {"coordinates":[2.1306078434,41.3355941772],"type":"Point"}
}