{
  "type": "Feature",
  "properties": {
    "addr:full":"Barr Cruz (la), S/n Queveda Cantabria 39314",
    "addr:postcode":"39314",
    "addr:street":"Cruz La S / N",
    "iso:country":"ES",
    "sg:address":"Barr Cruz (la), S/n",
    "sg:city":"Queveda",
    "sg:orig_category":"Chapister\u00cda",
    "sg:phone":"+34 942 89 74 68",
    "sg:postcode":"39314",
    "sg:province":"Cantabria",
    "wof:name":"Alvaro Castillo Antonio",
    "wof:placetype":"venue"
},
  "geometry": {"coordinates":[-4.0728316307,43.3795089722],"type":"Point"}
}