{
  "type": "Feature",
  "properties": {
    "addr:full":"Calle de Favareta, 59 Alzira Valencia 46600",
    "addr:housenumber":"59",
    "addr:postcode":"46600",
    "addr:street":"Calle De Favareta",
    "iso:country":"ES",
    "sg:address":"Calle de Favareta, 59",
    "sg:city":"Alzira",
    "sg:orig_category":"Plomeros",
    "sg:phone":"+34 962 40 00 02",
    "sg:postcode":"46600",
    "sg:province":"Valencia",
    "wof:name":"Fontaneria Perea Montero S.l.",
    "wof:placetype":"venue"
},
  "geometry": {"coordinates":[-0.4287360907,39.1537704468],"type":"Point"}
}