{
  "type": "Feature",
  "properties": {
    "iso:country":"ES",
    "sg:address":"Calle de Mariano Vergara, 17",
    "sg:city":"Santa Eulalia",
    "sg:orig_category":"Reposter\u00cdas",
    "sg:phone":"+34 968 23 93 22",
    "sg:postcode":"30003",
    "sg:province":"Murcia",
    "wof:name":"Martinez Robles Felix",
    "wof:placetype":"venue"
},
  "geometry": {"coordinates":[-1.1234329939,37.9866523743],"type":"Point"}
}