{
  "type": "Feature",
  "properties": {
    "addr:full":"Carrer de Carrio, 15 Manresa Barcelona 08242",
    "addr:housenumber":"15",
    "addr:postcode":"08242",
    "addr:street":"Carrer De Carrio",
    "iso:country":"ES",
    "sg:address":"Carrer de Carrio, 15",
    "sg:city":"Manresa",
    "sg:orig_category":"Peluquer\u00cdas, Peluquer\u00cda Mixta",
    "sg:phone":"+34 938 72 31 79",
    "sg:postcode":"08242",
    "sg:province":"Barcelona",
    "wof:name":"Olga Cris Perruqueres Cdad.",
    "wof:placetype":"venue"
},
  "geometry": {"coordinates":[1.8224439621,41.7281150818],"type":"Point"}
}