{
  "type": "Feature",
  "properties": {
    "addr:full":"Psaj Recogidas, 6 Granada Granada 18005",
    "addr:housenumber":"6",
    "addr:postcode":"18005",
    "addr:street":"Recogidas",
    "iso:country":"ES",
    "sg:address":"Psaj Recogidas, 6",
    "sg:city":"Granada",
    "sg:orig_category":"Ropa Para Ni\u00d1os (al Por Menor)",
    "sg:phone":"+34 958 25 21 36",
    "sg:postcode":"18005",
    "sg:province":"Granada",
    "wof:name":"Velasco Martinez Manuela",
    "wof:placetype":"venue"
},
  "geometry": {"coordinates":[-3.6005990505,37.1731491089],"type":"Point"}
}