{
  "type": "Feature",
  "properties": {
    "addr:full":"Avda Lopez Ballesteros, 32 Vilagarcia Pontevedra 36600",
    "addr:housenumber":"32",
    "addr:postcode":"36600",
    "addr:street":"Avda Lopez Ballesteros",
    "iso:country":"ES",
    "sg:address":"Avda Lopez Ballesteros, 32",
    "sg:city":"Vilagarcia",
    "sg:orig_category":"Alimentaci\u00d3n General (al Por Menor)",
    "sg:phone":"+34 986 50 25 36",
    "sg:postcode":"36600",
    "sg:province":"Pontevedra",
    "wof:name":"Cascallar Puga Leandro",
    "wof:placetype":"venue"
},
  "geometry": {"coordinates":[-8.7608985901,42.5997085571],"type":"Point"}
}