{
  "type": "Feature",
  "properties": {
    "addr:full":"Calle de Madre Soledad Torres Acosta, 2 Jaen Ja\u00e9n 23001",
    "addr:housenumber":"2;jae\u0301n",
    "addr:postcode":"23001",
    "addr:street":"Calle De Madre Soledad Torres Acosta",
    "iso:country":"ES",
    "sg:address":"Calle de Madre Soledad Torres Acosta, 2",
    "sg:city":"Jaen",
    "sg:orig_category":"Seguridad En El Trabajo Y Prevenci\u00d3n De Riesgos Laborales",
    "sg:phone":"+34 953 25 03 88",
    "sg:postcode":"23001",
    "sg:province":"Ja\u00e9n",
    "wof:name":"Medios De Prevencion Externos S.l.",
    "wof:placetype":"venue"
},
  "geometry": {"coordinates":[-3.7882568836,37.7691802979],"type":"Point"}
}