{
  "type": "Feature",
  "properties": {
    "addr:full":"Calvo Sotelo, 3 Pobra Carami\u00f1al La Coru\u00f1a 15940",
    "addr:housenumber":"3",
    "addr:postcode":"15940",
    "addr:street":"Calvo Sotelo;Corun\u0303A",
    "iso:country":"ES",
    "sg:address":"Calvo Sotelo, 3",
    "sg:city":"Pobra Carami\u00f1al",
    "sg:orig_category":"Centros De Educaci\u00d3n Especial",
    "sg:phone":"+34 981 83 07 08",
    "sg:postcode":"15940",
    "sg:province":"La Coru\u00f1a",
    "wof:name":"Colegio Publico Fernandez Varela",
    "wof:placetype":"venue"
},
  "geometry": {"coordinates":[-8.9388437271,42.6042404175],"type":"Point"}
}