{
  "type": "Feature",
  "properties": {
    "addr:full":"Parroco Pablo Diez, 243 Trobajo Camino Le\u00f3n 24010",
    "addr:housenumber":"243",
    "addr:postcode":"24010",
    "addr:street":"Camino Leo\u0301N",
    "iso:country":"ES",
    "sg:address":"Parroco Pablo Diez, 243",
    "sg:city":"Trobajo Camino",
    "sg:orig_category":"Cajas De Ahorro",
    "sg:phone":"+34 987 80 06 57",
    "sg:postcode":"24010",
    "sg:province":"Le\u00f3n",
    "wof:name":"Caja Espa\u00f1a De Inversiones Caja De Ahorros Y Monte De Piedad",
    "wof:placetype":"venue"
},
  "geometry": {"coordinates":[-5.5716600418,42.5981292725],"type":"Point"}
}