{
  "type": "Feature",
  "properties": {
    "iso:country":"ES",
    "sg:address":"Calle de Felix Rodriguez De La Fuente, 11",
    "sg:city":"Granada",
    "sg:orig_category":"Pintura Y Barniz (al Por Menor)",
    "sg:phone":"+34 958 12 56 33",
    "sg:postcode":"18006",
    "sg:province":"Granada",
    "wof:name":"Pinturas Tesapin S.l.",
    "wof:placetype":"venue"
},
  "geometry": {"coordinates":[-3.6429746151,37.1427536011],"type":"Point"}
}