{
  "type": "Feature",
  "properties": {
    "addr:full":"Avda Navarra, 28 Errenteria Guip\u00f9zcoa 20100",
    "addr:housenumber":"28",
    "addr:postcode":"20100",
    "addr:street":"Avda Navarra;Guipu\u0300Zcoa",
    "iso:country":"ES",
    "sg:address":"Avda Navarra, 28",
    "sg:city":"Errenteria",
    "sg:orig_category":"Molduras, Junquillos, Listones Y Molduras Perforadas",
    "sg:phone":"+34 943 52 31 04",
    "sg:postcode":"20100",
    "sg:province":"Guip\u00f9zcoa",
    "wof:name":"Otegui Juan Juan Carlos",
    "wof:placetype":"venue"
},
  "geometry": {"coordinates":[-1.9033180475,43.3151130676],"type":"Point"}
}