{
  "type": "Feature",
  "properties": {
    "addr:full":"Ordenacion Bahia, S/n Puerto Mazarron Murcia 30860",
    "addr:housenumber":"s / n",
    "addr:postcode":"30860",
    "iso:country":"ES",
    "sg:address":"Ordenacion Bahia, S/n",
    "sg:city":"Puerto Mazarron",
    "sg:orig_category":"Heladeros",
    "sg:phone":"+34 968 59 47 79",
    "sg:postcode":"30860",
    "sg:province":"Murcia",
    "wof:name":"Espi Verdu Leonida",
    "wof:placetype":"venue"
},
  "geometry": {"coordinates":[-1.2754739523,37.5660057068],"type":"Point"}
}