{
  "type": "Feature",
  "properties": {
    "iso:country":"ES",
    "sg:address":"De La Paz, 2",
    "sg:city":"Puente Arzobispo",
    "sg:orig_category":"Farmacias",
    "sg:phone":"+34 925 43 60 15",
    "sg:postcode":"45570",
    "sg:province":"Toledo",
    "wof:name":"Gomez Sanchez Felix",
    "wof:placetype":"venue"
},
  "geometry": {"coordinates":[-5.172894001,39.8010482788],"type":"Point"}
}