{
  "type": "Feature",
  "properties": {
    "iso:country":"ES",
    "sg:address":"Mayor Alta, 65",
    "sg:city":"Castelseras",
    "sg:orig_category":"Iglesia Cat\u00d3lica",
    "sg:phone":"+34 978 87 71 22",
    "sg:postcode":"44630",
    "sg:province":"Teruel",
    "wof:name":"Parroquia Natividad De Ntra. Sra.",
    "wof:placetype":"venue"
},
  "geometry": {"coordinates":[-0.1446930021,40.9844512939],"type":"Point"}
}