{
  "type": "Feature",
  "properties": {
    "iso:country":"ES",
    "sg:address":"Avda Bajo De Guia, S/n",
    "sg:city":"Sanlucar De Barrameda",
    "sg:orig_category":"Restaurantes",
    "sg:phone":"+34 956 36 26 95",
    "sg:postcode":"11540",
    "sg:province":"C\u00e1diz",
    "wof:name":"Orozco Cordero Juan Manuel",
    "wof:placetype":"venue"
},
  "geometry": {"coordinates":[-6.3515257835,36.7891731262],"type":"Point"}
}