{
  "type": "Feature",
  "properties": {
    "iso:country":"ES",
    "sg:address":"Plaz Iglesia (de La), 33",
    "sg:city":"Casillas Del Angel",
    "sg:orig_category":"Iglesia Cat\u00d3lica",
    "sg:phone":"+34 928 53 80 60",
    "sg:postcode":"35611",
    "sg:province":"Las Palmas",
    "wof:name":"Parroquia De Santa Ana",
    "wof:placetype":"venue"
},
  "geometry": {"coordinates":[-13.9902706146,28.5270195007],"type":"Point"}
}