{
  "type": "Feature",
  "properties": {
    "iso:country":"ES",
    "sg:address":"Calle de Cardenal Lorenzana, 1",
    "sg:city":"Alcala Henares",
    "sg:orig_category":"Empresas De Carpinter\u00cda De Madera",
    "sg:phone":"+34 918 82 94 67",
    "sg:postcode":"28802",
    "sg:province":"Madrid",
    "wof:name":"Moreno Laso Jose",
    "wof:placetype":"venue"
},
  "geometry": {"coordinates":[-3.3732793331,40.4801368713],"type":"Point"}
}