{
  "type": "Feature",
  "properties": {
    "addr:full":"Calle de Colon, 29 Segorbe Castell\u00f3n 12400",
    "addr:housenumber":"29",
    "addr:postcode":"12400",
    "addr:street":"Calle De Colon",
    "iso:country":"ES",
    "sg:address":"Calle de Colon, 29",
    "sg:city":"Segorbe",
    "sg:orig_category":"Reposter\u00cdas",
    "sg:phone":"+34 964 71 28 45",
    "sg:postcode":"12400",
    "sg:province":"Castell\u00f3n",
    "wof:name":"Mateo Sauceda Mario",
    "wof:placetype":"venue"
},
  "geometry": {"coordinates":[-0.4886009991,39.8518447876],"type":"Point"}
}