{
  "type": "Feature",
  "properties": {
    "iso:country":"ES",
    "sg:address":"Calle de Rio Deba, 5",
    "sg:city":"Donostia-san Sebastian",
    "sg:orig_category":"Molduras, Junquillos, Listones Y Molduras Perforadas",
    "sg:phone":"+34 943 27 13 15",
    "sg:postcode":"20012",
    "sg:province":"Guip\u00f9zcoa",
    "wof:name":"Vaquero Tuda Faustino",
    "wof:placetype":"venue"
},
  "geometry": {"coordinates":[-1.968701005,43.3161621094],"type":"Point"}
}