{
  "type": "Feature",
  "properties": {
    "iso:country":"ES",
    "sg:address":"Calle de Jose Garrote Tobar, 18",
    "sg:city":"Valladolid",
    "sg:orig_category":"Cl\u00cdnicas M\u00c9dicas",
    "sg:phone":"+34 983 37 87 36",
    "sg:postcode":"47014",
    "sg:province":"Valladolid",
    "wof:name":"Ribot Garcia Paloma",
    "wof:placetype":"venue"
},
  "geometry": {"coordinates":[-4.7588539124,41.6347846985],"type":"Point"}
}