{
  "type": "Feature",
  "properties": {
    "iso:country":"ES",
    "sg:address":"Calle de Vicente Guerra, 19",
    "sg:city":"Arrecife",
    "sg:orig_category":"Inmobiliaria (agencias)",
    "sg:phone":"+34 928 82 42 39",
    "sg:postcode":"35500",
    "sg:province":"Las Palmas",
    "wof:name":"Suastikrt S.l",
    "wof:placetype":"venue"
},
  "geometry": {"coordinates":[-13.5525569916,28.9682998657],"type":"Point"}
}