{
  "type": "Feature",
  "properties": {
    "iso:country":"ES",
    "sg:address":"Barr Bien Aparecida (la), S/n",
    "sg:city":"Aparecida",
    "sg:orig_category":"Organizaci\u00d3n De Actos, Seminarios Y Congresos",
    "sg:phone":"+34 942 67 68 14",
    "sg:postcode":"39849",
    "sg:province":"Cantabria",
    "wof:name":"Restaurante Somahoz S.a.",
    "wof:placetype":"venue"
},
  "geometry": {"coordinates":[-3.4229140282,43.3418464661],"type":"Point"}
}