{
  "type": "Feature",
  "properties": {
    "iso:country":"ES",
    "sg:address":"Calle de Doctor Calzada, 17",
    "sg:city":"Navia",
    "sg:orig_category":"Ense\u00d1anza: Idiomas",
    "sg:phone":"+34 985 47 30 29",
    "sg:postcode":"33710",
    "sg:province":"Asturias",
    "wof:name":"British Made S.l.",
    "wof:placetype":"venue"
},
  "geometry": {"coordinates":[-6.7247376442,43.5402908325],"type":"Point"}
}