{
  "type": "Feature",
  "properties": {
    "addr:full":"Avda Ingeniero Piqueras, S/n Manzanera Teruel 44420",
    "addr:housenumber":"s / n",
    "addr:postcode":"44420",
    "addr:street":"Avda Ingeniero Piqueras",
    "iso:country":"ES",
    "sg:address":"Avda Ingeniero Piqueras, S/n",
    "sg:city":"Manzanera",
    "sg:orig_category":"Centros De Educaci\u00d3n Especial",
    "sg:phone":"+34 978 78 18 13",
    "sg:postcode":"44420",
    "sg:province":"Teruel",
    "wof:name":"Colegio Rural Agrupado Javalambre",
    "wof:placetype":"venue"
},
  "geometry": {"coordinates":[-0.8293439746,40.05884552],"type":"Point"}
}