{
  "type": "Feature",
  "properties": {
    "addr:full":"Avda Rey Juan Carlos I, 21 Jalon Alicante 03727",
    "addr:housenumber":"21",
    "addr:postcode":"03727",
    "addr:street":"Avda Rey Juan Carlos I",
    "iso:country":"ES",
    "sg:address":"Avda Rey Juan Carlos I, 21",
    "sg:city":"Jalon",
    "sg:orig_category":"Apicultura",
    "sg:phone":"+34 966 48 08 37",
    "sg:postcode":"03727",
    "sg:province":"Alicante",
    "wof:name":"L'abella Mel S.l.",
    "wof:placetype":"venue"
},
  "geometry": {"coordinates":[-0.013119,38.7421913147],"type":"Point"}
}