{
  "type": "Feature",
  "properties": {
    "addr:full":"Calle de Fraguas, S/n Orihuela Tremedal Teruel 44366",
    "addr:postcode":"44366",
    "addr:street":"Calle De Fraguas S / N",
    "iso:country":"ES",
    "sg:address":"Calle de Fraguas, S/n",
    "sg:city":"Orihuela Tremedal",
    "sg:orig_category":"Empresas De Carpinter\u00cda De Madera",
    "sg:phone":"+34 978 71 40 67",
    "sg:postcode":"44366",
    "sg:province":"Teruel",
    "wof:name":"Casas Adobes Ramiro",
    "wof:placetype":"venue"
},
  "geometry": {"coordinates":[-1.6523139477,40.5508270264],"type":"Point"}
}