{
  "type": "Feature",
  "properties": {
    "iso:country":"ES",
    "sg:address":"Calle de Eduardo Zamacois, 13",
    "sg:city":"Laguna Duero",
    "sg:orig_category":"Muebles Y Accesorios Para Cocinas Y Cuartos De Ba\u00d1o (al Por Menor)",
    "sg:phone":"+34 983 54 53 15",
    "sg:postcode":"47140",
    "sg:province":"Valladolid",
    "wof:name":"Lanchares Perez Andres",
    "wof:placetype":"venue"
},
  "geometry": {"coordinates":[-4.7248492241,41.583404541],"type":"Point"}
}