{
  "type": "Feature",
  "properties": {
    "iso:country":"ES",
    "sg:address":"Av S'agaro, 1",
    "sg:city":"Platja D'aro",
    "sg:orig_category":"Restaurantes: Restauraci\u00d3n R\u00c1pida Y Autoservicio",
    "sg:phone":"+34 972 81 72 63",
    "sg:postcode":"17250",
    "sg:province":"Girona",
    "wof:name":"Sociedad De Restauracion Acacia S.l.",
    "wof:placetype":"venue"
},
  "geometry": {"coordinates":[2.8163490295,41.9701499939],"type":"Point"}
}