{
  "type": "Feature",
  "properties": {
    "iso:country":"ES",
    "sg:address":"Carrer de Vent, 12",
    "sg:city":"Reus",
    "sg:orig_category":"Papeler\u00cdas, Librer\u00cdas",
    "sg:phone":"+34 977 33 01 40",
    "sg:postcode":"43201",
    "sg:province":"Tarragona",
    "wof:name":"Massaguer Pujol Ramon",
    "wof:placetype":"venue"
},
  "geometry": {"coordinates":[1.107082963,41.153678894],"type":"Point"}
}