{
  "type": "Feature",
  "properties": {
    "addr:full":"Calle de Poeta Ricard Sanmarti, 5 Valencia Valencia 46020",
    "addr:housenumber":"5",
    "addr:postcode":"46020",
    "addr:street":"Calle De Poeta Ricard Sanmarti",
    "iso:country":"ES",
    "sg:address":"Calle de Poeta Ricard Sanmarti, 5",
    "sg:city":"Valencia",
    "sg:orig_category":"Fabricaci\u00d3n De Muebles",
    "sg:phone":"+34 963 62 11 30",
    "sg:postcode":"46020",
    "sg:province":"Valencia",
    "wof:name":"Brasero Pastor S.l.",
    "wof:placetype":"venue"
},
  "geometry": {"coordinates":[-0.359600991,39.4855728149],"type":"Point"}
}