{
  "type": "Feature",
  "properties": {
    "addr:full":"Avda Jose Fari\u00d1a, 42 Huelva Huelva 21006",
    "addr:housenumber":"42",
    "addr:postcode":"21006",
    "addr:street":"Avda Jose Farin\u0303A",
    "iso:country":"ES",
    "sg:address":"Avda Jose Fari\u00d1a, 42",
    "sg:city":"Huelva",
    "sg:orig_category":"Colchones (fabricaci\u00d3n, Al Por Mayor, Al Por Menor)",
    "sg:phone":"+34 959 23 52 47",
    "sg:postcode":"21006",
    "sg:province":"Huelva",
    "wof:name":"Gran Sue\u00f1o S.l.",
    "wof:placetype":"venue"
},
  "geometry": {"coordinates":[-6.9358119965,37.2601013184],"type":"Point"}
}