{
  "type": "Feature",
  "properties": {
    "iso:country":"ES",
    "sg:address":"Polig. Pocomaco, S/n",
    "sg:city":"A Coru\u00f1a",
    "sg:orig_category":"Moquetas, Alfombras (al Por Menor)",
    "sg:phone":"+34 981 28 33 58",
    "sg:postcode":"15190",
    "sg:province":"La Coru\u00f1a",
    "wof:name":"Palacio De Las Alfombras S.l.",
    "wof:placetype":"venue"
},
  "geometry": {"coordinates":[-8.4312744141,43.3228416443],"type":"Point"}
}