{
  "type": "Feature",
  "properties": {
    "addr:full":"Calle de Lora Tamayo, 1 Orgiva Granada 18400",
    "addr:housenumber":"1",
    "addr:postcode":"18400",
    "addr:street":"Calle De Lora Tamayo",
    "iso:country":"ES",
    "sg:address":"Calle de Lora Tamayo, 1",
    "sg:city":"Orgiva",
    "sg:orig_category":"T\u00c9cnicos Veterinarios",
    "sg:phone":"+34 958 78 53 69",
    "sg:postcode":"18400",
    "sg:province":"Granada",
    "wof:name":"Padial Ruiz Agustin",
    "wof:placetype":"venue"
},
  "geometry": {"coordinates":[-3.4226489067,36.8991546631],"type":"Point"}
}