{
  "type": "Feature",
  "properties": {
    "iso:country":"ES",
    "sg:address":"Calle de Teatro, 41",
    "sg:city":"Alacant",
    "sg:orig_category":"Abogados",
    "sg:phone":"+34 965 14 10 12",
    "sg:postcode":"03001",
    "sg:province":"Alicante",
    "wof:name":"Galiano Pastor Magdalena",
    "wof:placetype":"venue"
},
  "geometry": {"coordinates":[-0.4891879857,38.3447151184],"type":"Point"}
}