{
  "type": "Feature",
  "properties": {
    "addr:full":"Calle de Pinocho, 31 Torremolinos M\u00e1laga 29620",
    "addr:housenumber":"31",
    "addr:postcode":"29620",
    "addr:street":"Calle De Pinocho;Ma\u0301Laga",
    "iso:country":"ES",
    "sg:address":"Calle de Pinocho, 31",
    "sg:city":"Torremolinos",
    "sg:orig_category":"Plomeros",
    "sg:phone":"+34 952 05 13 32",
    "sg:postcode":"29620",
    "sg:province":"M\u00e1laga",
    "wof:name":"Fernandez Ortega Judith",
    "wof:placetype":"venue"
},
  "geometry": {"coordinates":[-4.5181570053,36.6098747253],"type":"Point"}
}