{
  "type": "Feature",
  "properties": {
    "addr:full":"Calle de Federico Chueca, S/n Alcala Henares Madrid 28806",
    "addr:housenumber":"s / n",
    "addr:postcode":"28806",
    "addr:street":"Calle De Federico Chueca",
    "iso:country":"ES",
    "sg:address":"Calle de Federico Chueca, S/n",
    "sg:city":"Alcala Henares",
    "sg:orig_category":"Fabricaci\u00d3n De Juegos Y Juguetes",
    "sg:phone":"+34 918 79 63 32",
    "sg:postcode":"28806",
    "sg:province":"Madrid",
    "wof:name":"Electrotren S. A.",
    "wof:placetype":"venue"
},
  "geometry": {"coordinates":[-3.3813939095,40.487285614],"type":"Point"}
}