{
  "type": "Feature",
  "properties": {
    "iso:country":"ES",
    "sg:address":"Carrer de Victor Catala, 13",
    "sg:city":"Rubi",
    "sg:orig_category":"Instalaci\u00d3n, Reparaci\u00d3n De Calefacci\u00d3n Por Gas",
    "sg:phone":"+34 936 97 79 35",
    "sg:postcode":"08191",
    "sg:province":"Barcelona",
    "wof:name":"Aba Gas Clima S.l.l.",
    "wof:placetype":"venue"
},
  "geometry": {"coordinates":[2.032325,41.484642],"type":"Point"}
}