{
  "type": "Feature",
  "properties": {
    "iso:country":"ES",
    "sg:address":"Calle de Mendez Nu\u00d1ez, 1",
    "sg:city":"Malaga",
    "sg:orig_category":"Grafistas",
    "sg:phone":"+34 952 22 45 47",
    "sg:postcode":"29008",
    "sg:province":"M\u00e1laga",
    "wof:name":"Hernandez Azorin Maria Del Mar",
    "wof:placetype":"venue"
},
  "geometry": {"coordinates":[-4.4196357727,36.7219734192],"type":"Point"}
}