{
  "type": "Feature",
  "properties": {
    "addr:full":"Calle de Jose Cruz Conde, 12 Cordoba C\u00f3rdoba 14003",
    "addr:housenumber":"12",
    "addr:postcode":"14003",
    "addr:street":"Calle De Jose Cruz Conde;Co\u0301Rdoba",
    "iso:country":"ES",
    "sg:address":"Calle de Jose Cruz Conde, 12",
    "sg:city":"Cordoba",
    "sg:orig_category":"Aud\u00cdfonos",
    "sg:phone":"+34 957 47 35 64",
    "sg:postcode":"14003",
    "sg:province":"C\u00f3rdoba",
    "wof:name":"Amian Duran Francisco Javier",
    "wof:placetype":"venue"
},
  "geometry": {"coordinates":[-4.7803945541,37.8861923218],"type":"Point"}
}