{
  "type": "Feature",
  "properties": {
    "iso:country":"ES",
    "sg:address":"Avda Moliere, 6",
    "sg:city":"Malaga",
    "sg:classifiers":[
        {
            "category":"Professional",
            "subcategory":"Management & Consulting",
            "type":"Services"
        }
    ],
    "sg:phone":"+34 952 17 16 70",
    "sg:postcode":"29004",
    "sg:province":"M\u00e1laga",
    "sg:tags":[
        "asesor\u00cda",
        "en",
        "marketing"
    ],
    "wof:name":"Gallego Berche Pedro Jose",
    "wof:placetype":"venue"
},
  "geometry": {"coordinates":[-4.45586586,36.6894683838],"type":"Point"}
}