{
  "type": "Feature",
  "properties": {
    "addr:full":"Ctr Ossa De Montiel, Km. 0001,0 Bonillo Albacete 02610",
    "addr:postcode":"02610",
    "addr:street":"Montiel Km. 0001,0 Bonillo",
    "iso:country":"ES",
    "sg:address":"Ctr Ossa De Montiel, Km. 0001,0",
    "sg:city":"Bonillo",
    "sg:orig_category":"Cr\u00cda De Cerdos",
    "sg:phone":"+34 967 37 05 99",
    "sg:postcode":"02610",
    "sg:province":"Albacete",
    "wof:name":"Santisimo Cristo De Los Milagros S.l.",
    "wof:placetype":"venue"
},
  "geometry": {"coordinates":[-2.535777092,38.952495575],"type":"Point"}
}