{
  "type": "Feature",
  "properties": {
    "addr:full":"Carr Santa Madrona, 40 Vilanova I La Geltru Barcelona 08800",
    "addr:housenumber":"40",
    "addr:postcode":"08800",
    "addr:street":"Carr Santa Madrona",
    "iso:country":"ES",
    "sg:address":"Carr Santa Madrona, 40",
    "sg:city":"Vilanova I La Geltru",
    "sg:orig_category":"Procuradores",
    "sg:phone":"+34 938 10 13 86",
    "sg:postcode":"08800",
    "sg:province":"Barcelona",
    "wof:name":"Subira Nou Vicent",
    "wof:placetype":"venue"
},
  "geometry": {"coordinates":[1.7262860537,41.2252655029],"type":"Point"}
}