{
  "type": "Feature",
  "properties": {
    "iso:country":"ES",
    "sg:address":"Calle de Hacienda De Pavones, 231",
    "sg:city":"Madrid",
    "sg:orig_category":"Farmacias",
    "sg:phone":"+34 917 73 39 71",
    "sg:postcode":"28030",
    "sg:province":"Madrid",
    "wof:name":"Garcia Ortiz Alberto",
    "wof:placetype":"venue"
},
  "geometry": {"coordinates":[-3.6348333359,40.4006233215],"type":"Point"}
}