{
  "type": "Feature",
  "properties": {
    "addr:full":"Carrer de Arago, 520 Barcelona Barcelona 08013",
    "addr:housenumber":"520",
    "addr:postcode":"08013",
    "addr:street":"Carrer De Arago",
    "iso:country":"ES",
    "sg:address":"Carrer de Arago, 520",
    "sg:city":"Barcelona",
    "sg:orig_category":"Colchones (fabricaci\u00d3n, Al Por Mayor, Al Por Menor)",
    "sg:phone":"+34 932 45 60 35",
    "sg:postcode":"08013",
    "sg:province":"Barcelona",
    "wof:name":"Procomiber S. L.",
    "wof:placetype":"venue"
},
  "geometry": {"coordinates":[2.1822400093,41.4052009583],"type":"Point"}
}