{
  "type": "Feature",
  "properties": {
    "iso:country":"ES",
    "sg:address":"G.v. Carles Iii, 51",
    "sg:city":"Barcelona",
    "sg:orig_category":"Asesor\u00cda Sobre Comunicaci\u00d3n De Empresas",
    "sg:phone":"+34 933 39 00 04",
    "sg:postcode":"08028",
    "sg:province":"Barcelona",
    "sg:website":"www.asesoriagarcialopez.es",
    "wof:name":"Asesoria Garcia Lopez S L..",
    "wof:placetype":"venue"
},
  "geometry": {"coordinates":[2.1277241707,41.3827819824],"type":"Point"}
}