{
  "type": "Feature",
  "properties": {
    "addr:full":"Calle de San Bizenti, 2 Sodupe Vizcaya 48830",
    "addr:housenumber":"2",
    "addr:postcode":"48830",
    "addr:street":"Calle De San Bizenti",
    "iso:country":"ES",
    "sg:address":"Calle de San Bizenti, 2",
    "sg:city":"Sodupe",
    "sg:orig_category":"Florister\u00cdas",
    "sg:phone":"+34 946 39 91 78",
    "sg:postcode":"48830",
    "sg:province":"Vizcaya",
    "wof:name":"Herresanchez Castresana Maria Mercedes",
    "wof:placetype":"venue"
},
  "geometry": {"coordinates":[-3.0490760803,43.2001609802],"type":"Point"}
}