{
  "type": "Feature",
  "properties": {
    "addr:full":"Calle de Arrospide Jon, 2 Bilbao Vizcaya 48014",
    "addr:housenumber":"2",
    "addr:postcode":"48014",
    "addr:street":"Calle De Arrospide Jon",
    "iso:country":"ES",
    "sg:address":"Calle de Arrospide Jon, 2",
    "sg:city":"Bilbao",
    "sg:orig_category":"Peluquer\u00cdas, Peluquer\u00cda Mixta",
    "sg:phone":"+34 944 76 13 87",
    "sg:postcode":"48014",
    "sg:province":"Vizcaya",
    "wof:name":"Maria Mar Aguirre Burgoa Y Dolores Mu\u00f1oz Lopez Cdad",
    "wof:placetype":"venue"
},
  "geometry": {"coordinates":[-2.9474186897,43.2688789368],"type":"Point"}
}