{
  "type": "Feature",
  "properties": {
    "iso:country":"ES",
    "sg:address":"Urb. Loma Rey, 57",
    "sg:city":"La Alcaidesa",
    "sg:orig_category":"Negocio De Materiales De Construcci\u00d3n",
    "sg:phone":"+34 956 79 10 67",
    "sg:postcode":"11311",
    "sg:province":"C\u00e1diz",
    "wof:name":"Mu\u00f1iz Tabares Hermogenes",
    "wof:placetype":"venue"
},
  "geometry": {"coordinates":[-5.2987089157,36.2937660217],"type":"Point"}
}