{
  "type": "Feature",
  "properties": {
    "iso:country":"ES",
    "sg:address":"Avda Zumalacarregui, 48",
    "sg:city":"Bilbao",
    "sg:orig_category":"Radiocomunicaciones, Telefon\u00cda M\u00d3vil, Radiomensajer\u00cda: Servicios, Comercializaci\u00d3n",
    "sg:phone":"+34 944 59 81 16",
    "sg:postcode":"48006",
    "sg:province":"Vizcaya",
    "sg:website":"www.optimus.es",
    "wof:name":"Optimus S. A.",
    "wof:placetype":"venue"
},
  "geometry": {"coordinates":[-2.9120800495,43.2568626404],"type":"Point"}
}