{
  "type": "Feature",
  "properties": {
    "addr:full":"Calle de Libertad (de La), 44 Alcobendas Madrid 28100",
    "addr:housenumber":"44",
    "addr:postcode":"28100",
    "addr:street":"Calle De Libertad De La",
    "iso:country":"ES",
    "sg:address":"Calle de Libertad (de La), 44",
    "sg:city":"Alcobendas",
    "sg:orig_category":"Molduras, Junquillos, Listones Y Molduras Perforadas",
    "sg:phone":"+34 916 61 91 57",
    "sg:postcode":"28100",
    "sg:province":"Madrid",
    "wof:name":"Ruiz Trivi\u00f1o Maria Del Carmen",
    "wof:placetype":"venue"
},
  "geometry": {"coordinates":[-3.636400938,40.5389900208],"type":"Point"}
}