{
  "type": "Feature",
  "properties": {
    "addr:full":"Calle de Saboya, 13 Parquelagos Madrid 28420",
    "addr:housenumber":"13",
    "addr:postcode":"28420",
    "addr:street":"Calle De Saboya",
    "iso:country":"ES",
    "sg:address":"Calle de Saboya, 13",
    "sg:city":"Parquelagos",
    "sg:orig_category":"Asociaciones Y Clubs Deportivos",
    "sg:phone":"+34 918 59 61 21",
    "sg:postcode":"28420",
    "sg:province":"Madrid",
    "sg:website":"www.paseosenglobo.com",
    "wof:name":"Escuela De Aeronautica De Aerodifusion S.l.",
    "wof:placetype":"venue"
},
  "geometry": {"coordinates":[-3.9682190418,40.5938339233],"type":"Point"}
}