{
  "type": "Feature",
  "properties": {
    "addr:full":"Calle de Tapizadores (los), 1 Chiclana De La Frontera C\u00e1diz 11130",
    "addr:postcode":"11130",
    "addr:street":"Calle De Tapizadores Los",
    "iso:country":"ES",
    "sg:address":"Calle de Tapizadores (los), 1",
    "sg:city":"Chiclana De La Frontera",
    "sg:orig_category":"Empresas De Carpinter\u00cda",
    "sg:phone":"+34 956 40 59 61",
    "sg:postcode":"11130",
    "sg:province":"C\u00e1diz",
    "wof:name":"Sanchez Morales Manuel",
    "wof:placetype":"venue"
},
  "geometry": {"coordinates":[-6.1397590637,36.410068512],"type":"Point"}
}