{
  "type": "Feature",
  "properties": {
    "addr:full":"Calle de Londres, 35 Parla Madrid 28980",
    "addr:housenumber":"35",
    "addr:postcode":"28980",
    "addr:street":"Calle De Londres",
    "iso:country":"ES",
    "sg:address":"Calle de Londres, 35",
    "sg:city":"Parla",
    "sg:orig_category":"Fabricaci\u00d3n De Tapices Y Moquetas Para Suelos Y Paredes",
    "sg:phone":"+34 916 05 22 35",
    "sg:postcode":"28980",
    "sg:province":"Madrid",
    "wof:name":"Grupo Tapizados Y Alfonbrados S.l.l.",
    "wof:placetype":"venue"
},
  "geometry": {"coordinates":[-3.7542688847,40.239364624],"type":"Point"}
}