{
  "type": "Feature",
  "properties": {
    "iso:country":"ES",
    "sg:address":"Carr Agulla, De L', 8",
    "sg:city":"Cala Ratjada",
    "sg:orig_category":"Art\u00cdculos De Decoraci\u00d3n",
    "sg:phone":"+34 971 56 47 02",
    "sg:postcode":"07590",
    "sg:province":"Islas Baleares",
    "wof:name":"Brunet Vives Pedro",
    "wof:placetype":"venue"
},
  "geometry": {"coordinates":[3.4626729488,39.7110137939],"type":"Point"}
}