{
  "type": "Feature",
  "properties": {
    "iso:country":"ES",
    "sg:address":"Carrer de Verdi, 327",
    "sg:city":"Barcelona",
    "sg:orig_category":"Pintores",
    "sg:phone":"+34 932 10 10 98",
    "sg:postcode":"08024",
    "sg:province":"Barcelona",
    "wof:name":"Marques Saguier Juan Carlos",
    "wof:placetype":"venue"
},
  "geometry": {"coordinates":[2.1492509842,41.4116134644],"type":"Point"}
}