{
  "type": "Feature",
  "properties": {
    "iso:country":"ES",
    "sg:address":"Carrer de Puig De L'ofre, 11",
    "sg:city":"Galatzo",
    "sg:orig_category":"Molduras, Junquillos, Listones Y Molduras Perforadas",
    "sg:phone":"+34 971 69 23 85",
    "sg:postcode":"07180",
    "sg:province":"Islas Baleares",
    "wof:name":"Soler Garcia Juana",
    "wof:placetype":"venue"
},
  "geometry": {"coordinates":[2.4986240864,39.5253181458],"type":"Point"}
}