{
  "type": "Feature",
  "properties": {
    "iso:country":"ES",
    "sg:address":"Calle de Jose Ignacio Avila, 2",
    "sg:city":"Madrid",
    "sg:orig_category":"Zapatos (al Por Menor)",
    "sg:phone":"+34 917 59 95 18",
    "sg:postcode":"28043",
    "sg:province":"Madrid",
    "wof:name":"Marele 98 S.l.",
    "wof:placetype":"venue"
},
  "geometry": {"coordinates":[-3.625138998,40.4591522217],"type":"Point"}
}