{
  "type": "Feature",
  "properties": {
    "addr:full":"Calle de La Florida, 19 Vitoria-gasteiz \u00c1lava 01005",
    "addr:housenumber":"19",
    "addr:postcode":"01005",
    "addr:street":"Calle De La Florida",
    "iso:country":"ES",
    "sg:address":"Calle de La Florida, 19",
    "sg:city":"Vitoria-gasteiz",
    "sg:orig_category":"Abogados",
    "sg:phone":"+34 945 13 34 52",
    "sg:postcode":"01005",
    "sg:province":"\u00c1lava",
    "wof:name":"Berisa Villamayor Francisco Javier",
    "wof:placetype":"venue"
},
  "geometry": {"coordinates":[-2.6732759476,42.8433914185],"type":"Point"}
}