{
  "type": "Feature",
  "properties": {
    "addr:full":"Barr Portilla (la), S/n Beranga Cantabria 39730",
    "addr:postcode":"39730",
    "addr:street":"Portilla La S / N",
    "iso:country":"ES",
    "sg:address":"Barr Portilla (la), S/n",
    "sg:city":"Beranga",
    "sg:orig_category":"Iglesia Cat\u00d3lica",
    "sg:phone":"+34 942 63 51 24",
    "sg:postcode":"39730",
    "sg:province":"Cantabria",
    "wof:name":"Parroquia De Beranga",
    "wof:placetype":"venue"
},
  "geometry": {"coordinates":[-3.5771279335,43.4150924683],"type":"Point"}
}