{
  "type": "Feature",
  "properties": {
    "iso:country":"ES",
    "sg:address":"Pque Ruperto Chapi, 12",
    "sg:city":"Villena",
    "sg:orig_category":"Arboricultura Y Producci\u00d3n De Frutas",
    "sg:phone":"+34 965 80 06 52",
    "sg:postcode":"03400",
    "sg:province":"Alicante",
    "wof:name":"Francisco Garcia Ayelo C.b.",
    "wof:placetype":"venue"
},
  "geometry": {"coordinates":[-0.8657540083,38.6356544495],"type":"Point"}
}