{
  "type": "Feature",
  "properties": {
    "addr:full":"Esglesia, 86 Estartit Girona 17258",
    "addr:housenumber":"86",
    "addr:postcode":"17258",
    "addr:street":"Esglesia",
    "iso:country":"ES",
    "sg:address":"Esglesia, 86",
    "sg:city":"Estartit",
    "sg:orig_category":"Organismos De Turismo",
    "sg:phone":"+34 972 75 15 99",
    "sg:postcode":"17258",
    "sg:province":"Girona",
    "wof:name":"Gou 4 Spain.net S.l.",
    "wof:placetype":"venue"
},
  "geometry": {"coordinates":[3.1957120895,42.0534667969],"type":"Point"}
}