{
  "type": "Feature",
  "properties": {
    "addr:full":"Calle de Lavanderas Del Manzanares (de Las), 6 Colmenar Viejo Madrid 28770",
    "addr:housenumber":"6",
    "addr:postcode":"28770",
    "addr:street":"Calle De Lavanderas Del Manzanares De Las",
    "iso:country":"ES",
    "sg:address":"Calle de Lavanderas Del Manzanares (de Las), 6",
    "sg:city":"Colmenar Viejo",
    "sg:orig_category":"Madera Para Construcci\u00d3n E Industria",
    "sg:phone":"+34 918 45 12 33",
    "sg:postcode":"28770",
    "sg:province":"Madrid",
    "wof:name":"Gallego Del Valle Alfonso",
    "wof:placetype":"venue"
},
  "geometry": {"coordinates":[-3.7768259048,40.6579475403],"type":"Point"}
}