{
  "type": "Feature",
  "properties": {
    "iso:country":"ES",
    "sg:address":"Calle de Atalaya, 5",
    "sg:city":"Albolote",
    "sg:orig_category":"Inform\u00c1tica Equipo Y Programas (al Por Mayor)",
    "sg:phone":"+34 958 46 67 86",
    "sg:postcode":"18220",
    "sg:province":"Granada",
    "wof:name":"Costela Abad Francisco Jose",
    "wof:placetype":"venue"
},
  "geometry": {"coordinates":[-3.6559767723,37.2356338501],"type":"Point"}
}