{
  "type": "Feature",
  "properties": {
    "iso:country":"ES",
    "sg:address":"Plaz Gabriel Miro, 10",
    "sg:city":"Alacant",
    "sg:orig_category":"Molduras, Junquillos, Listones Y Molduras Perforadas",
    "sg:phone":"+34 965 20 07 11",
    "sg:postcode":"03001",
    "sg:province":"Alicante",
    "wof:name":"Ingrid Shop,s.l.",
    "wof:placetype":"venue"
},
  "geometry": {"coordinates":[-0.4854379892,38.3434257507],"type":"Point"}
}