{
  "type": "Feature",
  "properties": {
    "iso:country":"ES",
    "sg:address":"Calle de Cervantes, 25",
    "sg:city":"Montoro",
    "sg:orig_category":"\u00d3ptica: Instrumentos (fabricaci\u00d3n)",
    "sg:phone":"+34 957 16 10 29",
    "sg:postcode":"14600",
    "sg:province":"C\u00f3rdoba",
    "wof:name":"Optybaby S.l.",
    "wof:placetype":"venue"
},
  "geometry": {"coordinates":[-4.3829779625,38.0185050964],"type":"Point"}
}