{
  "type": "Feature",
  "properties": {
    "addr:full":"Psaj Las Antillas, 8 Vitoria-gasteiz \u00c1lava 01012",
    "addr:housenumber":"8",
    "addr:postcode":"01012",
    "addr:street":"Las Antillas",
    "iso:country":"ES",
    "sg:address":"Psaj Las Antillas, 8",
    "sg:city":"Vitoria-gasteiz",
    "sg:orig_category":"Electrodom\u00c9sticos (al Por Menor)",
    "sg:phone":"+34 945 22 89 94",
    "sg:postcode":"01012",
    "sg:province":"\u00c1lava",
    "wof:name":"Achaerandio Fernandez De A\u00f1astro Cesareo",
    "wof:placetype":"venue"
},
  "geometry": {"coordinates":[-2.6760251522,42.8545417786],"type":"Point"}
}