{
  "type": "Feature",
  "properties": {
    "iso:country":"ES",
    "sg:address":"Calle de Enebros (los), 2",
    "sg:city":"Teruel",
    "sg:orig_category":"Ingeniero",
    "sg:phone":"+34 978 61 15 66",
    "sg:postcode":"44002",
    "sg:province":"Teruel",
    "wof:name":"Ibaez Sanz Jose Antonio",
    "wof:placetype":"venue"
},
  "geometry": {"coordinates":[-1.0983411074,40.3298912048],"type":"Point"}
}