{
  "type": "Feature",
  "properties": {
    "iso:country":"ES",
    "sg:address":"Sect Musicos, 11",
    "sg:city":"Tres Cantos",
    "sg:orig_category":"Ense\u00d1anza Secundaria: Colegios Y Escuelas Privadas",
    "sg:phone":"+34 918 03 09 96",
    "sg:postcode":"28760",
    "sg:province":"Madrid",
    "wof:name":"Colegio Publico Gabriel Garcia Marquez",
    "wof:placetype":"venue"
},
  "geometry": {"coordinates":[-3.7178199291,40.6086654663],"type":"Point"}
}