{
  "type": "Feature",
  "properties": {
    "iso:country":"ES",
    "sg:address":"Calle de Vicente Aleixandre, 17",
    "sg:city":"Burgos",
    "sg:orig_category":"Asociaciones Humanitarias, De Cooperaci\u00d3n, De Acci\u00d3n Social",
    "sg:phone":"+34 947 24 52 03",
    "sg:postcode":"09006",
    "sg:province":"Burgos",
    "wof:name":"Asociacion Familiar Y Afectados Esclerosis Multiple",
    "wof:placetype":"venue"
},
  "geometry": {"coordinates":[-3.6770486832,42.3548355103],"type":"Point"}
}