{
  "type": "Feature",
  "properties": {
    "iso:country":"ES",
    "sg:address":"Av Caritat Serinyana, 3",
    "sg:city":"Cadaques",
    "sg:orig_category":"Compraventa De Antig\u00dcedades",
    "sg:phone":"+34 972 15 90 11",
    "sg:postcode":"17488",
    "sg:province":"Girona",
    "wof:name":"Malla Medina Jose",
    "wof:placetype":"venue"
},
  "geometry": {"coordinates":[3.2771410942,42.2894897461],"type":"Point"}
}