{
  "type": "Feature",
  "properties": {
    "iso:country":"ES",
    "sg:address":"Plaz Uncibay, 9",
    "sg:city":"Malaga",
    "sg:orig_category":"Psicoanalistas",
    "sg:phone":"+34 952 22 35 13",
    "sg:postcode":"29008",
    "sg:province":"M\u00e1laga",
    "wof:name":"Murri Taboada Alberto",
    "wof:placetype":"venue"
},
  "geometry": {"coordinates":[-4.4198269844,36.7224960327],"type":"Point"}
}