{
  "type": "Feature",
  "properties": {
    "addr:full":"Calle de Mesones, 5 Priego Cordoba C\u00f3rdoba 14800",
    "addr:housenumber":"5",
    "addr:postcode":"14800",
    "addr:street":"Calle De Mesones;Cordoba Co\u0301Rdoba",
    "iso:country":"ES",
    "sg:address":"Calle de Mesones, 5",
    "sg:city":"Priego Cordoba",
    "sg:orig_category":"Telas Y Sedas (al Por Menor)",
    "sg:phone":"+34 957 54 08 44",
    "sg:postcode":"14800",
    "sg:province":"C\u00f3rdoba",
    "wof:name":"Portales Jurado Adriano",
    "wof:placetype":"venue"
},
  "geometry": {"coordinates":[-4.1934909821,37.4381217957],"type":"Point"}
}