{
  "type": "Feature",
  "properties": {
    "addr:full":"Ctra Burgos, Km. 0022,8 Aleson La Rioja 26315",
    "addr:postcode":"26315",
    "addr:street":"Ctra Burgos Km. 0022,8 Aleson;Rioja",
    "iso:country":"ES",
    "sg:address":"Ctra Burgos, Km. 0022,8",
    "sg:city":"Aleson",
    "sg:orig_category":"Madera (al Por Menor)",
    "sg:phone":"+34 941 36 90 32",
    "sg:postcode":"26315",
    "sg:province":"La Rioja",
    "wof:name":"Maeztu Arenzana Justino Carmelo",
    "wof:placetype":"venue"
},
  "geometry": {"coordinates":[-2.6889009476,42.405216217],"type":"Point"}
}