{
  "type": "Feature",
  "properties": {
    "iso:country":"ES",
    "sg:address":"Trva Arteixo, 213",
    "sg:city":"Arteixo",
    "sg:orig_category":"Cervecer\u00cdas",
    "sg:phone":"+34 981 60 24 00",
    "sg:postcode":"15142",
    "sg:province":"La Coru\u00f1a",
    "wof:name":"Incotel S.l.",
    "wof:placetype":"venue"
},
  "geometry": {"coordinates":[-8.5171804428,43.3106918335],"type":"Point"}
}