{
  "type": "Feature",
  "properties": {
    "addr:full":"Calle de Teide, 8 Puerto Del Carmen Las Palmas 35510",
    "addr:housenumber":"8",
    "addr:postcode":"35510",
    "addr:street":"Calle De Teide",
    "iso:country":"ES",
    "sg:address":"Calle de Teide, 8",
    "sg:city":"Puerto Del Carmen",
    "sg:orig_category":"Turismo: Lugares, Circuitos Y Curiosidades",
    "sg:phone":"+34 928 51 00 65",
    "sg:postcode":"35510",
    "sg:province":"Las Palmas",
    "wof:name":"Aquatickets Lanzarote S L.",
    "wof:placetype":"venue"
},
  "geometry": {"coordinates":[-13.672293663,28.9220523834],"type":"Point"}
}