{
  "type": "Feature",
  "properties": {
    "iso:country":"ES",
    "sg:address":"Calle de Caleta De Velez, 36",
    "sg:city":"Malaga",
    "sg:orig_category":"Cristaler\u00cdas",
    "sg:phone":"+34 952 35 23 42",
    "sg:postcode":"29196",
    "sg:province":"M\u00e1laga",
    "wof:name":"Cristaleria San Luis S.l.",
    "wof:placetype":"venue"
},
  "geometry": {"coordinates":[-4.4972810745,36.7000045776],"type":"Point"}
}