{
  "type": "Feature",
  "properties": {
    "iso:country":"ES",
    "sg:address":"Ctra Toledo, 76",
    "sg:city":"Navahermosa",
    "sg:orig_category":"Forjas Y Altos Hornos",
    "sg:phone":"+34 925 42 82 86",
    "sg:postcode":"45150",
    "sg:province":"Toledo",
    "wof:name":"Menchero Cervantes Manuel Jesus",
    "wof:placetype":"venue"
},
  "geometry": {"coordinates":[-4.4659490585,39.6377182007],"type":"Point"}
}