{
  "type": "Feature",
  "properties": {
    "addr:full":"Calle de Diesel (o), S/n Chorrillo Santa Cruz De Tenerife 38108",
    "addr:housenumber":"s / n",
    "addr:postcode":"38108",
    "addr:street":"Calle De Diesel O",
    "iso:country":"ES",
    "sg:address":"Calle de Diesel (o), S/n",
    "sg:city":"Chorrillo",
    "sg:orig_category":"Quincaller\u00cda (al Por Menor)",
    "sg:phone":"+34 922 61 88 06",
    "sg:postcode":"38108",
    "sg:province":"Santa Cruz De Tenerife",
    "wof:name":"Ferreteria Castro Delgado S.l.",
    "wof:placetype":"venue"
},
  "geometry": {"coordinates":[-16.3166999817,28.4145908356],"type":"Point"}
}