{
  "type": "Feature",
  "properties": {
    "addr:full":"Urbanizacion Bahia Jardin, S/n La Herradura Granada 18697",
    "addr:housenumber":"s / n",
    "addr:postcode":"18697",
    "iso:country":"ES",
    "sg:address":"Urbanizacion Bahia Jardin, S/n",
    "sg:city":"La Herradura",
    "sg:orig_category":"Alquiler De Veh\u00cdculos: Turismos Y Utilitarios",
    "sg:phone":"+34 958 64 05 77",
    "sg:postcode":"18697",
    "sg:province":"Granada",
    "wof:name":"Sidinsiel S.l.",
    "wof:placetype":"venue"
},
  "geometry": {"coordinates":[-3.7390809059,36.7353096008],"type":"Point"}
}