{
  "type": "Feature",
  "properties": {
    "iso:country":"ES",
    "sg:address":"Calle de Moros, 9",
    "sg:city":"Gijon",
    "sg:orig_category":"Albergues",
    "sg:phone":"+34 985 17 63 01",
    "sg:postcode":"33206",
    "sg:province":"Asturias",
    "wof:name":"Sipecusa S.l.",
    "wof:placetype":"venue"
},
  "geometry": {"coordinates":[-5.6630702019,43.5418319702],"type":"Point"}
}