{
  "type": "Feature",
  "properties": {
    "iso:country":"ES",
    "sg:address":"Calle de Corbeta, 3",
    "sg:city":"Mateos",
    "sg:orig_category":"Transportes Por Carretera: Lotes Completos, Mercanc\u00cdas Diversas",
    "sg:phone":"+34 968 12 28 23",
    "sg:postcode":"30202",
    "sg:province":"Murcia",
    "wof:name":"Garcia Vicente Isabel Concepcion",
    "wof:placetype":"venue"
},
  "geometry": {"coordinates":[-1.1302499771,37.9829597473],"type":"Point"}
}