{
  "type": "Feature",
  "properties": {
    "iso:country":"ES",
    "sg:address":"Calle de Braulio Iriarte, 64",
    "sg:city":"Elizondo",
    "sg:orig_category":"Alimentaci\u00d3n General (al Por Menor)",
    "sg:phone":"+34 948 58 06 07",
    "sg:postcode":"31700",
    "sg:province":"Navarra",
    "wof:name":"Hipolito Zunzarren Iribarren S.a.",
    "wof:placetype":"venue"
},
  "geometry": {"coordinates":[-1.5230090618,43.1426010132],"type":"Point"}
}