{
  "type": "Feature",
  "properties": {
    "addr:full":"Calle de Beato Diego De Cadiz, 34 Alacant Alicante 03009",
    "addr:housenumber":"34",
    "addr:postcode":"03009",
    "addr:street":"Calle De Beato Diego De Cadiz",
    "iso:country":"ES",
    "sg:address":"Calle de Beato Diego De Cadiz, 34",
    "sg:city":"Alacant",
    "sg:orig_category":"Mec\u00c1nico Del Autom\u00d3vil",
    "sg:phone":"+34 965 17 64 80",
    "sg:postcode":"03009",
    "sg:province":"Alicante",
    "wof:name":"Talleres Albimar S.l.",
    "wof:placetype":"venue"
},
  "geometry": {"coordinates":[-0.4988740087,38.3730316162],"type":"Point"}
}