{
  "type": "Feature",
  "properties": {
    "iso:country":"ES",
    "sg:address":"Carrer de Pou De Sant Pere, 2",
    "sg:city":"Sant Feliu Llobregat",
    "sg:orig_category":"Cajas De Ahorro",
    "sg:phone":"+34 936 32 71 61",
    "sg:postcode":"08980",
    "sg:province":"Barcelona",
    "wof:name":"Caixa D'estalvis De Catalunya",
    "wof:placetype":"venue"
},
  "geometry": {"coordinates":[2.0452098846,41.3809585571],"type":"Point"}
}