{
  "type": "Feature",
  "properties": {
    "iso:country":"ES",
    "sg:address":"Avda Agua Marina, S/n",
    "sg:city":"Algeciras",
    "sg:orig_category":"Molduras, Junquillos, Listones Y Molduras Perforadas",
    "sg:phone":"+34 956 65 08 99",
    "sg:postcode":"11203",
    "sg:province":"C\u00e1diz",
    "wof:name":"Tellez Garcia Palma",
    "wof:placetype":"venue"
},
  "geometry": {"coordinates":[-5.460999012,36.1292037964],"type":"Point"}
}