{
  "type": "Feature",
  "properties": {
    "addr:full":"Calle de Salcillo, 1 Mostoles Madrid 28932",
    "addr:housenumber":"1",
    "addr:postcode":"28932",
    "addr:street":"Calle De Salcillo",
    "iso:country":"ES",
    "sg:address":"Calle de Salcillo, 1",
    "sg:city":"Mostoles",
    "sg:orig_category":"Artes Gr\u00c1ficas, Artes Pl\u00c1sticas (curso)",
    "sg:phone":"+34 912 26 50 40",
    "sg:postcode":"28932",
    "sg:province":"Madrid",
    "wof:name":"Imprenta Marina C.b.",
    "wof:placetype":"venue"
},
  "geometry": {"coordinates":[-3.8627450466,40.3342514038],"type":"Point"}
}