{
  "type": "Feature",
  "properties": {
    "iso:country":"ES",
    "sg:address":"Calle de Urdaneta, 3",
    "sg:city":"Donostia-san Sebastian",
    "sg:orig_category":"Administradores De Bienes Y Delegados De Comunidades De Propietarios",
    "sg:phone":"+34 943 44 58 11",
    "sg:postcode":"20006",
    "sg:province":"Guip\u00f9zcoa",
    "wof:name":"Ruiz Ruiz Javier",
    "wof:placetype":"venue"
},
  "geometry": {"coordinates":[-1.9801239967,43.3165473938],"type":"Point"}
}