{
  "type": "Feature",
  "properties": {
    "iso:country":"ES",
    "sg:address":"Carr General Weyler, 244",
    "sg:city":"Badalona",
    "sg:orig_category":"Promotores Constructores",
    "sg:phone":"+34 933 83 25 43",
    "sg:postcode":"08912",
    "sg:province":"Barcelona",
    "wof:name":"Comunidad De Propietarios General Weiler 248-254",
    "wof:placetype":"venue"
},
  "geometry": {"coordinates":[2.2345728874,41.4444465637],"type":"Point"}
}