{
  "type": "Feature",
  "properties": {
    "addr:full":"Avda Constitucion, 56 Navalvillar Pela Badajoz 06760",
    "addr:housenumber":"56",
    "addr:postcode":"06760",
    "addr:street":"Avda Constitucion",
    "iso:country":"ES",
    "sg:address":"Avda Constitucion, 56",
    "sg:city":"Navalvillar Pela",
    "sg:orig_category":"Pod\u00d3logos: Pedicuros",
    "sg:phone":"+34 924 86 05 51",
    "sg:postcode":"06760",
    "sg:province":"Badajoz",
    "wof:name":"Gordillo Casimiro Jose Manuel",
    "wof:placetype":"venue"
},
  "geometry": {"coordinates":[-5.4659352303,39.0906105042],"type":"Point"}
}