{
  "type": "Feature",
  "properties": {
    "iso:country":"ES",
    "sg:address":"Calle de Profesor Tierno Galvan, 34",
    "sg:city":"Huercal Almeria",
    "sg:orig_category":"Inform\u00c1tica: Material Y Suministros",
    "sg:phone":"+34 950 26 76 44",
    "sg:postcode":"04230",
    "sg:province":"Almer\u00eda",
    "sg:website":"www.infoteco.es",
    "wof:name":"Infoteco S. L.",
    "wof:placetype":"venue"
},
  "geometry": {"coordinates":[-2.4392080307,36.8851127625],"type":"Point"}
}