{
  "type": "Feature",
  "properties": {
    "iso:country":"ES",
    "sg:address":"Calle de Emilio Laria, 9",
    "sg:city":"Cangas Onis",
    "sg:orig_category":"Carnicer\u00cdas, Carnicer\u00cdas",
    "sg:phone":"+34 985 84 93 89",
    "sg:postcode":"33550",
    "sg:province":"Asturias",
    "wof:name":"Llerandi Huerta Juan Carlos",
    "wof:placetype":"venue"
},
  "geometry": {"coordinates":[-5.1280231476,43.3494682312],"type":"Point"}
}