{
  "type": "Feature",
  "properties": {
    "addr:full":"Monasterio Fitero, 34 Iru\u00f1a Navarra 31011",
    "addr:housenumber":"34",
    "addr:postcode":"31011",
    "addr:street":"Fitero",
    "iso:country":"ES",
    "sg:address":"Monasterio Fitero, 34",
    "sg:city":"Iru\u00f1a",
    "sg:orig_category":"Calefacci\u00d3n Central: Material (fabricaci\u00d3n, Al Por Mayor)",
    "sg:phone":"+34 948 26 35 81",
    "sg:postcode":"31011",
    "sg:province":"Navarra",
    "sg:website":"www.sedical.com",
    "wof:name":"Baraibar Perez Jose Miguel",
    "wof:placetype":"venue"
},
  "geometry": {"coordinates":[-1.6578279734,42.8162879944],"type":"Point"}
}