{
  "type": "Feature",
  "properties": {
    "iso:country":"ES",
    "sg:address":"Calle de Arganda, 18",
    "sg:city":"Madrid",
    "sg:classifiers":[
        {
            "category":"Autos & Motor Vehicles",
            "subcategory":"Automobile Sales",
            "type":"Retail Goods"
        }
    ],
    "sg:phone":"+34 914 74 24 76",
    "sg:postcode":"28005",
    "sg:province":"Madrid",
    "wof:name":"Autoescuela Virgen Del Castillo S.l.",
    "wof:placetype":"venue"
},
  "geometry": {"coordinates":[-3.7076487541,40.4008903503],"type":"Point"}
}