{
  "type": "Feature",
  "properties": {
    "addr:full":"Ctra Jaen (de), 81 Granada Granada 18014",
    "addr:housenumber":"81",
    "addr:postcode":"18014",
    "addr:street":"Ctra Jaen De",
    "iso:country":"ES",
    "sg:address":"Ctra Jaen (de), 81",
    "sg:city":"Granada",
    "sg:orig_category":"Bancos",
    "sg:phone":"+34 958 17 18 11",
    "sg:postcode":"18014",
    "sg:province":"Granada",
    "wof:name":"Banco De Andalucia",
    "wof:placetype":"venue"
},
  "geometry": {"coordinates":[-3.619246006,37.2060012817],"type":"Point"}
}