{
  "type": "Feature",
  "properties": {
    "addr:full":"Carr Major, 72 Manises Valencia 46940",
    "addr:housenumber":"72",
    "addr:postcode":"46940",
    "addr:street":"Carr Major",
    "iso:country":"ES",
    "sg:address":"Carr Major, 72",
    "sg:city":"Manises",
    "sg:orig_category":"Discapacitados",
    "sg:phone":"+34 961 54 86 77",
    "sg:postcode":"46940",
    "sg:province":"Valencia",
    "wof:name":"Asociacion De Familiares Y Discapacitados De Manises",
    "wof:placetype":"venue"
},
  "geometry": {"coordinates":[-0.4597539008,39.4924278259],"type":"Point"}
}