{
  "type": "Feature",
  "properties": {
    "addr:full":"Calle de Raimundo Fernandez Villaverde, 1 Madrid Madrid 28003",
    "addr:housenumber":"1",
    "addr:postcode":"28003",
    "addr:street":"Calle De Raimundo Fernandez Villaverde",
    "iso:country":"ES",
    "sg:address":"Calle de Raimundo Fernandez Villaverde, 1",
    "sg:city":"Madrid",
    "sg:orig_category":"Ense\u00d1anza: Comercio, Gesti\u00d3n, Inform\u00c1tica",
    "sg:phone":"+34 915 36 30 71",
    "sg:postcode":"28003",
    "sg:province":"Madrid",
    "wof:name":"Soft-market S. A.",
    "wof:placetype":"venue"
},
  "geometry": {"coordinates":[-3.7036271095,40.4469947815],"type":"Point"}
}