{
  "type": "Feature",
  "properties": {
    "addr:full":"Rua Pombal (do), 34 Santiago De Compostela La Coru\u00f1a 15705",
    "addr:housenumber":"34",
    "addr:postcode":"15705",
    "addr:street":"Rua Pombal Do;Corun\u0303A",
    "iso:country":"ES",
    "sg:address":"Rua Pombal (do), 34",
    "sg:city":"Santiago De Compostela",
    "sg:orig_category":"Librer\u00cdas",
    "sg:phone":"+34 981 57 33 63",
    "sg:postcode":"15705",
    "sg:province":"La Coru\u00f1a",
    "wof:name":"Ferreira Fernandez Palmira",
    "wof:placetype":"venue"
},
  "geometry": {"coordinates":[-8.5483589172,42.8788490295],"type":"Point"}
}