{
  "type": "Feature",
  "properties": {
    "iso:country":"ES",
    "sg:address":"C/ Angel Guimera, 118",
    "sg:city":"Salt",
    "sg:orig_category":"Empresas De Carpinter\u00cda De Madera",
    "sg:phone":"+34 972 24 34 64",
    "sg:postcode":"17190",
    "sg:province":"Girona",
    "wof:name":"Reixach Costa Luis",
    "wof:placetype":"venue"
},
  "geometry": {"coordinates":[2.787801981,41.973613739],"type":"Point"}
}