{
  "type": "Feature",
  "properties": {
    "iso:country":"ES",
    "sg:address":"Calle de Jose Franchy Roca, 5",
    "sg:city":"Palmas De Gran Canaria",
    "sg:orig_category":"Formaci\u00d3n Continuada (variada)",
    "sg:phone":"+34 928 26 97 56",
    "sg:postcode":"35007",
    "sg:province":"Las Palmas",
    "wof:name":"Mu\u00f1oz Mu\u00f1oz Maria Jesus",
    "wof:placetype":"venue"
},
  "geometry": {"coordinates":[-15.431186676,28.1390190125],"type":"Point"}
}