{
  "type": "Feature",
  "properties": {
    "iso:country":"ES",
    "sg:address":"Pla\u00c7 Espanya, S/n",
    "sg:city":"Girona",
    "sg:orig_category":"Edici\u00d3n De Diarios, Revistas, Boletines",
    "sg:phone":"+34 972 22 61 10",
    "sg:postcode":"17002",
    "sg:province":"Girona",
    "wof:name":"Sociedad General Espa\u00d1ola De Libreria Diarios Y Revistas",
    "wof:placetype":"venue"
},
  "geometry": {"coordinates":[2.8171200752,41.9789161682],"type":"Point"}
}