{
  "type": "Feature",
  "properties": {
    "addr:full":"Finc Piul (el), S/n Piul Madrid 28529",
    "addr:postcode":"28529",
    "addr:street":"El S / N Piul",
    "iso:country":"ES",
    "sg:address":"Finc Piul (el), S/n",
    "sg:city":"Piul",
    "sg:orig_category":"Agricultores, Agricultores",
    "sg:phone":"+34 916 70 00 14",
    "sg:postcode":"28529",
    "sg:province":"Madrid",
    "wof:name":"Hacienda El Piul S.l.",
    "wof:placetype":"venue"
},
  "geometry": {"coordinates":[-3.5102670193,40.314289093],"type":"Point"}
}