{
  "type": "Feature",
  "properties": {
    "iso:country":"ES",
    "sg:address":"Besande, S/n",
    "sg:city":"Boca Huergano",
    "sg:orig_category":"Centros De Educaci\u00d3n Especial",
    "sg:phone":"+34 987 74 41 24",
    "sg:postcode":"24911",
    "sg:province":"Le\u00f3n",
    "wof:name":"C.r.a. De Ria\u00f1o",
    "wof:placetype":"venue"
},
  "geometry": {"coordinates":[-4.9240889549,42.9718284607],"type":"Point"}
}