{
  "type": "Feature",
  "properties": {
    "addr:full":"Calle de Marques De Monteagudo, 1 Madrid Madrid 28028",
    "addr:housenumber":"1",
    "addr:postcode":"28028",
    "addr:street":"Calle De Marques De Monteagudo",
    "iso:country":"ES",
    "sg:address":"Calle de Marques De Monteagudo, 1",
    "sg:city":"Madrid",
    "sg:orig_category":"Centros Empresariales",
    "sg:phone":"+34 913 56 30 65",
    "sg:postcode":"28028",
    "sg:province":"Madrid",
    "wof:name":"Barba Madariaga Alvaro",
    "wof:placetype":"venue"
},
  "geometry": {"coordinates":[-3.6681571007,40.4357070923],"type":"Point"}
}