{
  "type": "Feature",
  "properties": {
    "addr:full":"Puerto Alegre, 23 Ca\u00f1ada Plata C\u00f3rdoba 14500",
    "addr:housenumber":"23",
    "addr:postcode":"14500",
    "addr:street":"Can\u0303Ada Plata Co\u0301Rdoba",
    "iso:country":"ES",
    "sg:address":"Puerto Alegre, 23",
    "sg:city":"Ca\u00f1ada Plata",
    "sg:orig_category":"T\u00c9cnicos Veterinarios",
    "sg:phone":"+34 957 60 41 11",
    "sg:postcode":"14500",
    "sg:province":"C\u00f3rdoba",
    "wof:name":"Berral De La Rosa Antonio-jesus",
    "wof:placetype":"venue"
},
  "geometry": {"coordinates":[-4.7779579163,37.3909187317],"type":"Point"}
}