{
  "type": "Feature",
  "properties": {
    "addr:full":"Calle de Real, S/n Albu\u00f1ol Granada 18700",
    "addr:housenumber":"s / n",
    "addr:postcode":"18700",
    "addr:street":"Calle De Real",
    "iso:country":"ES",
    "sg:address":"Calle de Real, S/n",
    "sg:city":"Albu\u00f1ol",
    "sg:orig_category":"Internados & Ense\u00d1anza Privada",
    "sg:phone":"+34 958 82 60 50",
    "sg:postcode":"18700",
    "sg:province":"Granada",
    "wof:name":"Escuela Hogar Cristo Rey",
    "wof:placetype":"venue"
},
  "geometry": {"coordinates":[-3.202229023,36.7919197083],"type":"Point"}
}