{
  "type": "Feature",
  "properties": {
    "iso:country":"ES",
    "sg:address":"Avda Aragon, 22",
    "sg:city":"Valencia",
    "sg:orig_category":"Bares, Piano",
    "sg:phone":"+34 963 69 98 46",
    "sg:postcode":"46021",
    "sg:province":"Valencia",
    "wof:name":"Alastrue Loscos Javier",
    "wof:placetype":"venue"
},
  "geometry": {"coordinates":[-0.3580422997,39.4707565308],"type":"Point"}
}