{
  "type": "Feature",
  "properties": {
    "addr:full":"Calle de Napoleon Catarineu, 1 Torre-pacheco Murcia 30700",
    "addr:housenumber":"1",
    "addr:postcode":"30700",
    "addr:street":"Calle De Napoleon Catarineu",
    "iso:country":"ES",
    "sg:address":"Calle de Napoleon Catarineu, 1",
    "sg:city":"Torre-pacheco",
    "sg:orig_category":"Escayola Y Productos De Escayola (fabricaci\u00d3n, Al Por Mayor)",
    "sg:phone":"+34 968 57 83 20",
    "sg:postcode":"30700",
    "sg:province":"Murcia",
    "wof:name":"Fuentes Roca Jose",
    "wof:placetype":"venue"
},
  "geometry": {"coordinates":[-0.9571139812,37.7376785278],"type":"Point"}
}