{
  "type": "Feature",
  "properties": {
    "iso:country":"ES",
    "sg:address":"Pl Catalunya, 7",
    "sg:city":"S. Andreu Barca",
    "sg:orig_category":"Mec\u00c1nico Del Autom\u00d3vil",
    "sg:phone":"+34 936 82 04 13",
    "sg:postcode":"08740",
    "sg:province":"Barcelona",
    "wof:name":"Automotor S.c.p.",
    "wof:placetype":"venue"
},
  "geometry": {"coordinates":[1.9700059891,41.448184967],"type":"Point"}
}