{
  "type": "Feature",
  "properties": {
    "addr:full":"Avda Los Llanos, S/n Roda Andalucia Sevilla 41590",
    "addr:housenumber":"s / n",
    "addr:postcode":"41590",
    "addr:street":"Avda Los Llanos",
    "iso:country":"ES",
    "sg:address":"Avda Los Llanos, S/n",
    "sg:city":"Roda Andalucia",
    "sg:orig_category":"T\u00c9cnicos Veterinarios",
    "sg:phone":"+34 954 01 65 72",
    "sg:postcode":"41590",
    "sg:province":"Sevilla",
    "wof:name":"Rodalbeitar S.l.",
    "wof:placetype":"venue"
},
  "geometry": {"coordinates":[-4.7789430618,37.2011032104],"type":"Point"}
}