{
  "type": "Feature",
  "properties": {
    "iso:country":"ES",
    "sg:address":"Carrer de Tirso, 29",
    "sg:city":"Barcelona",
    "sg:orig_category":"Abogados",
    "sg:phone":"+34 932 10 54 95",
    "sg:postcode":"08023",
    "sg:province":"Barcelona",
    "wof:name":"Fortuny Comaposada Francisco",
    "wof:placetype":"venue"
},
  "geometry": {"coordinates":[2.1506369114,41.4187545776],"type":"Point"}
}