{
  "type": "Feature",
  "properties": {
    "addr:full":"Calle de San Vicente De Paul, 27 Zaragoza Zaragoza 50001",
    "addr:housenumber":"27",
    "addr:postcode":"50001",
    "addr:street":"Calle De San Vicente De Paul",
    "iso:country":"ES",
    "sg:address":"Calle de San Vicente De Paul, 27",
    "sg:city":"Zaragoza",
    "sg:orig_category":"Tintorer\u00cdas, Limpieza En Seco",
    "sg:phone":"+34 976 29 90 34",
    "sg:postcode":"50001",
    "sg:province":"Zaragoza",
    "wof:name":"Blasco Vera Erika",
    "wof:placetype":"venue"
},
  "geometry": {"coordinates":[-0.875229001,41.6532783508],"type":"Point"}
}