{
  "type": "Feature",
  "properties": {
    "addr:full":"Calle de Rivas, Km. 0005,6 Madrid Madrid 28052",
    "addr:postcode":"28052",
    "addr:street":"Calle De Rivas Km. 0005,6",
    "iso:country":"ES",
    "sg:address":"Calle de Rivas, Km. 0005,6",
    "sg:city":"Madrid",
    "sg:orig_category":"Venta, Alquiler, Mantenimiento De Calderas",
    "sg:phone":"+34 917 76 05 00",
    "sg:postcode":"28052",
    "sg:province":"Madrid",
    "sg:website":"www.vulcanosadeca.es",
    "wof:name":"Vulcano-sadeca S.a.",
    "wof:placetype":"venue"
},
  "geometry": {"coordinates":[-3.58543396,40.3961715698],"type":"Point"}
}