{
  "type": "Feature",
  "properties": {
    "iso:country":"ES",
    "sg:address":"Calle de Avenida De La Constitucion, 3",
    "sg:city":"Cintruenigo",
    "sg:orig_category":"Muebles, Minoristas",
    "sg:phone":"+34 948 81 15 86",
    "sg:postcode":"31592",
    "sg:province":"Navarra",
    "wof:name":"Muebles Jose Ballester Ballester S.l.",
    "wof:placetype":"venue"
},
  "geometry": {"coordinates":[-1.8034864664,42.0778160095],"type":"Point"}
}