{
  "type": "Feature",
  "properties": {
    "iso:country":"ES",
    "sg:address":"Mercat Sarria, 158",
    "sg:city":"Barcelona",
    "sg:orig_category":"Moda",
    "sg:phone":"+34 932 05 23 67",
    "sg:postcode":"08017",
    "sg:province":"Barcelona",
    "wof:name":"Emete Mummy S.l.",
    "wof:placetype":"venue"
},
  "geometry": {"coordinates":[2.1219000816,41.4000892639],"type":"Point"}
}