{
  "type": "Feature",
  "properties": {
    "addr:full":"Plaz Baleares, S/n Fuengirola M\u00e1laga 29640",
    "addr:housenumber":"s / n",
    "addr:postcode":"29640",
    "addr:street":"Plaz Baleares;Ma\u0301Laga",
    "iso:country":"ES",
    "sg:address":"Plaz Baleares, S/n",
    "sg:city":"Fuengirola",
    "sg:orig_category":"Grafistas",
    "sg:phone":"+34 952 66 65 68",
    "sg:postcode":"29640",
    "sg:province":"M\u00e1laga",
    "wof:name":"Estudio Rm-2 Dise\u00f1o Grafico S.l.",
    "wof:placetype":"venue"
},
  "geometry": {"coordinates":[-4.6286168098,36.5465736389],"type":"Point"}
}