{
  "type": "Feature",
  "properties": {
    "addr:full":"Carrer de Tarragona (de), 2 Vila-seca Tarragona 43480",
    "addr:housenumber":"2",
    "addr:postcode":"43480",
    "addr:street":"Carrer De Tarragona De",
    "iso:country":"ES",
    "sg:address":"Carrer de Tarragona (de), 2",
    "sg:city":"Vila-seca",
    "sg:orig_category":"Ropa Para Ni\u00d1os (al Por Menor)",
    "sg:phone":"+34 977 39 36 65",
    "sg:postcode":"43480",
    "sg:province":"Tarragona",
    "wof:name":"Marine Ferre Josefa",
    "wof:placetype":"venue"
},
  "geometry": {"coordinates":[1.1472909451,41.109588623],"type":"Point"}
}