{
  "type": "Feature",
  "properties": {
    "addr:full":"Calle de Izaburu, 39 Donostia-san Sebastian Guip\u00f9zcoa 20009",
    "addr:housenumber":"39",
    "addr:postcode":"20009",
    "addr:street":"Calle De Izaburu",
    "iso:country":"ES",
    "sg:address":"Calle de Izaburu, 39",
    "sg:city":"Donostia-san Sebastian",
    "sg:orig_category":"Doctores En Medicina",
    "sg:phone":"+34 943 21 89 05",
    "sg:postcode":"20009",
    "sg:province":"Guip\u00f9zcoa",
    "wof:name":"Ibarra Arredondo Ana",
    "wof:placetype":"venue"
},
  "geometry": {"coordinates":[-1.9936259985,43.3120994568],"type":"Point"}
}