{
  "type": "Feature",
  "properties": {
    "addr:full":"Trva Arena (de La), 17 Fuenlabrada Madrid 28944",
    "addr:housenumber":"17",
    "addr:postcode":"28944",
    "addr:street":"Trva Arena De La",
    "iso:country":"ES",
    "sg:address":"Trva Arena (de La), 17",
    "sg:city":"Fuenlabrada",
    "sg:orig_category":"Papeler\u00cdas, Librer\u00cdas",
    "sg:phone":"+34 916 06 37 42",
    "sg:postcode":"28944",
    "sg:province":"Madrid",
    "wof:name":"Gil Rosa Jose Luis",
    "wof:placetype":"venue"
},
  "geometry": {"coordinates":[-3.7950959206,40.2809524536],"type":"Point"}
}