{
  "type": "Feature",
  "properties": {
    "iso:country":"ES",
    "sg:address":"Urb Lomas Del Mar, 113",
    "sg:city":"Torrelamata",
    "sg:orig_category":"Agencias De Viajes",
    "sg:phone":"+34 966 92 19 98",
    "sg:postcode":"03188",
    "sg:province":"Alicante",
    "wof:name":"Saga Travel S.a.",
    "wof:placetype":"venue"
},
  "geometry": {"coordinates":[-0.6580709815,38.0311698914],"type":"Point"}
}