{
  "type": "Feature",
  "properties": {
    "addr:full":"Calle de Manijeros, S/n Lepe Huelva 21440",
    "addr:housenumber":"s / n",
    "addr:postcode":"21440",
    "addr:street":"Calle De Manijeros",
    "iso:country":"ES",
    "sg:address":"Calle de Manijeros, S/n",
    "sg:city":"Lepe",
    "sg:orig_category":"Frutas Y Legumbres Frescas (al Por Mayor)",
    "sg:phone":"+34 959 38 38 69",
    "sg:postcode":"21440",
    "sg:province":"Huelva",
    "wof:name":"Santana Villegas Carlos",
    "wof:placetype":"venue"
},
  "geometry": {"coordinates":[-7.1958141327,37.2498931885],"type":"Point"}
}