{
  "type": "Feature",
  "properties": {
    "addr:full":"Carrer de Ausias March, 48 Viladecans Barcelona 08840",
    "addr:housenumber":"48",
    "addr:postcode":"08840",
    "addr:street":"Carrer De Ausias March",
    "iso:country":"ES",
    "sg:address":"Carrer de Ausias March, 48",
    "sg:city":"Viladecans",
    "sg:orig_category":"Promotores Constructores",
    "sg:phone":"+34 936 37 05 26",
    "sg:postcode":"08840",
    "sg:province":"Barcelona",
    "wof:name":"Pro Vg S.l.",
    "wof:placetype":"venue"
},
  "geometry": {"coordinates":[2.0222799778,41.3196563721],"type":"Point"}
}