{
  "type": "Feature",
  "properties": {
    "addr:full":"Calle de Lope De Rueda, 53 Madrid Madrid 28009",
    "addr:housenumber":"53",
    "addr:postcode":"madrid;28009",
    "addr:street":"Calle De Lope De Rueda",
    "iso:country":"ES",
    "sg:address":"Calle de Lope De Rueda, 53",
    "sg:city":"Madrid",
    "sg:orig_category":"Panader\u00cdas, Panader\u00cdas",
    "sg:phone":"+34 915 73 41 98",
    "sg:postcode":"28009",
    "sg:province":"Madrid",
    "wof:name":"Alonso Prada Julio",
    "wof:placetype":"venue"
},
  "geometry": {"coordinates":[-3.6778538227,40.4179229736],"type":"Point"}
}