{
  "type": "Feature",
  "properties": {
    "addr:full":"Calle de Alcocer, 47 Madrid Madrid 28021",
    "addr:housenumber":"47",
    "addr:postcode":"madrid;28021",
    "addr:street":"Calle De Alcocer",
    "iso:country":"ES",
    "sg:address":"Calle de Alcocer, 47",
    "sg:city":"Madrid",
    "sg:orig_category":"Aparatos, Sistemas De Tele",
    "sg:phone":"+34 917 23 38 10",
    "sg:postcode":"28021",
    "sg:province":"Madrid",
    "wof:name":"Serygur S. A.",
    "wof:placetype":"venue"
},
  "geometry": {"coordinates":[-3.6973090172,40.3499984741],"type":"Point"}
}