{
  "type": "Feature",
  "properties": {
    "addr:full":"Calle de Miracruz, 28 Donostia-san Sebastian Guip\u00f9zcoa 20001",
    "addr:housenumber":"28",
    "addr:postcode":"20001",
    "addr:street":"Calle De Miracruz",
    "iso:country":"ES",
    "sg:address":"Calle de Miracruz, 28",
    "sg:city":"Donostia-san Sebastian",
    "sg:orig_category":"Retoques De Vestidos",
    "sg:phone":"+34 943 27 10 59",
    "sg:postcode":"20001",
    "sg:province":"Guip\u00f9zcoa",
    "wof:name":"Mateos Garcia Teodora",
    "wof:placetype":"venue"
},
  "geometry": {"coordinates":[-1.9730609655,43.3221588135],"type":"Point"}
}