{
  "type": "Feature",
  "properties": {
    "iso:country":"ES",
    "sg:address":"Av Peguera, 13",
    "sg:city":"Peguera",
    "sg:orig_category":"Regalos, Souvenires (fabricaci\u00d3n, Al Por Mayor)",
    "sg:phone":"+34 971 68 55 88",
    "sg:postcode":"07160",
    "sg:province":"Islas Baleares",
    "wof:name":"Tedeschi Sosa Martin Enrique",
    "wof:placetype":"venue"
},
  "geometry": {"coordinates":[2.4466249943,39.5372695923],"type":"Point"}
}