{
  "type": "Feature",
  "properties": {
    "addr:full":"Ctra. Almeria, S/n Esfiliana Granada 18511",
    "addr:housenumber":"s",
    "addr:postcode":"18511",
    "addr:street":"Ctra. Almeria;/ N Esfiliana",
    "iso:country":"ES",
    "sg:address":"Ctra. Almeria, S/n",
    "sg:city":"Esfiliana",
    "sg:orig_category":"Vinos Y Licores (venta Al Por Menor)",
    "sg:phone":"+34 958 69 80 36",
    "sg:postcode":"18511",
    "sg:province":"Granada",
    "wof:name":"Perez Soto Francisco",
    "wof:placetype":"venue"
},
  "geometry": {"coordinates":[-3.0988750458,37.2589302063],"type":"Point"}
}