{
  "type": "Feature",
  "properties": {
    "addr:full":"Avenida Toques, 8 Melide La Coru\u00f1a 15800",
    "addr:housenumber":"8",
    "addr:postcode":"15800",
    "addr:street":"Avenida Toques;La Corun\u0303A",
    "iso:country":"ES",
    "sg:address":"Avenida Toques, 8",
    "sg:city":"Melide",
    "sg:classifiers":[
        {
            "category":"Taxi",
            "type":"Transportation"
        }
    ],
    "sg:phone":"+34 981 50 56 11",
    "sg:postcode":"15800",
    "sg:province":"La Coru\u00f1a",
    "wof:name":"Mellid Rey Manuel Enrique",
    "wof:placetype":"venue"
},
  "geometry": {"coordinates":[-8.0158538818,42.9169311523],"type":"Point"}
}