{
  "type": "Feature",
  "properties": {
    "addr:full":"Poli Industrial 1 De Mayo, 9 Miajadas C\u00e1ceres 10100",
    "addr:housenumber":"9",
    "addr:postcode":"10100",
    "addr:street":"1 De Mayo;Ca\u0301Ceres",
    "iso:country":"ES",
    "sg:address":"Poli Industrial 1 De Mayo, 9",
    "sg:city":"Miajadas",
    "sg:orig_category":"Negocio De Enlosados, Soler\u00cdas",
    "sg:phone":"+34 927 34 74 98",
    "sg:postcode":"10100",
    "sg:province":"C\u00e1ceres",
    "wof:name":"Comercial Miajadas De Ceramica S.l.",
    "wof:placetype":"venue"
},
  "geometry": {"coordinates":[-5.9082989693,39.1555213928],"type":"Point"}
}