{
  "type": "Feature",
  "properties": {
    "iso:country":"ES",
    "sg:address":"Calle de Somoza Rivera, 8",
    "sg:city":"Badajoz",
    "sg:orig_category":"Agencias De Viajes",
    "sg:phone":"+34 924 28 64 23",
    "sg:postcode":"06006",
    "sg:province":"Badajoz",
    "wof:name":"Viajes Leyton Y Lorente C.b.",
    "wof:placetype":"venue"
},
  "geometry": {"coordinates":[-6.982293129,38.8859291077],"type":"Point"}
}