{
  "type": "Feature",
  "properties": {
    "addr:full":"Calle de Escritor Luis Manzano, 1 Huelva Huelva 21002",
    "addr:housenumber":"1",
    "addr:postcode":"21002",
    "addr:street":"Calle De Escritor Luis Manzano",
    "iso:country":"ES",
    "sg:address":"Calle de Escritor Luis Manzano, 1",
    "sg:city":"Huelva",
    "sg:orig_category":"Panader\u00cdas, Panader\u00cdas",
    "sg:phone":"+34 959 25 18 78",
    "sg:postcode":"21002",
    "sg:province":"Huelva",
    "wof:name":"Gonzalez Del Villar Luis",
    "wof:placetype":"venue"
},
  "geometry": {"coordinates":[-6.9540352821,37.2641334534],"type":"Point"}
}