{
  "type": "Feature",
  "properties": {
    "iso:country":"ES",
    "sg:address":"Plaz Constitucion (de La), 4",
    "sg:city":"Santa Cruz Palma",
    "sg:orig_category":"Ense\u00d1anza, Formaci\u00d3n Profesional: Aprendizaje",
    "sg:phone":"+34 922 41 80 07",
    "sg:postcode":"38700",
    "sg:province":"Santa Cruz De Tenerife",
    "sg:website":"www.foremcanarias.org",
    "wof:name":"Fundacion Formacion Y Empleo",
    "wof:placetype":"venue"
},
  "geometry": {"coordinates":[-17.7677326202,28.6805782318],"type":"Point"}
}