{
  "type": "Feature",
  "properties": {
    "addr:full":"Pl Ramaders, 4 Mollet Valles Barcelona 08100",
    "addr:housenumber":"4",
    "addr:postcode":"08100",
    "addr:street":"Pl Ramaders",
    "iso:country":"ES",
    "sg:address":"Pl Ramaders, 4",
    "sg:city":"Mollet Valles",
    "sg:orig_category":"Inform\u00c1tica (estudios, Servicios, Asesor\u00cda, Formaci\u00d3n)",
    "sg:phone":"+34 935 93 14 07",
    "sg:postcode":"08100",
    "sg:province":"Barcelona",
    "sg:website":"www.idok.biz",
    "wof:name":"Inteligencia Documental S.l.",
    "wof:placetype":"venue"
},
  "geometry": {"coordinates":[2.2184350491,41.5393295288],"type":"Point"}
}