{
  "type": "Feature",
  "properties": {
    "addr:full":"Calle de Virgen De Los Milagros, 54 Puerto De Santa Maria C\u00e1diz 11500",
    "addr:housenumber":"54",
    "addr:postcode":"11500",
    "addr:street":"Calle De Virgen De Los Milagros;Ca\u0301Diz",
    "iso:country":"ES",
    "sg:address":"Calle de Virgen De Los Milagros, 54",
    "sg:city":"Puerto De Santa Maria",
    "sg:orig_category":"Inmobiliaria (agencias)",
    "sg:phone":"+34 956 54 20 46",
    "sg:postcode":"11500",
    "sg:province":"C\u00e1diz",
    "sg:website":"www.inmoretamar.es",
    "wof:name":"Inmobiliaria Retamar S. A.",
    "wof:placetype":"venue"
},
  "geometry": {"coordinates":[-6.2197542191,36.6056632996],"type":"Point"}
}