{
  "type": "Feature",
  "properties": {
    "iso:country":"ES",
    "sg:address":"Calle de Miguel De Cervantes, 46",
    "sg:city":"Vilamartin Valdeorras",
    "sg:orig_category":"Peluquer\u00cdas, Peluquer\u00cda Mixta",
    "sg:phone":"+34 988 30 03 30",
    "sg:postcode":"32340",
    "sg:province":"Ourense",
    "wof:name":"Rodriguez Duran Ana Maria",
    "wof:placetype":"venue"
},
  "geometry": {"coordinates":[-7.0608639717,42.414264679],"type":"Point"}
}