{
  "type": "Feature",
  "properties": {
    "iso:country":"ES",
    "sg:address":"Calle de Matias Montero, 3",
    "sg:city":"Corrales",
    "sg:orig_category":"Electrodom\u00c9sticos (al Por Menor)",
    "sg:phone":"+34 942 83 13 00",
    "sg:postcode":"39400",
    "sg:province":"Cantabria",
    "wof:name":"Pila Cano Andres",
    "wof:placetype":"venue"
},
  "geometry": {"coordinates":[-4.0695681572,43.2612457275],"type":"Point"}
}