{
  "type": "Feature",
  "properties": {
    "iso:country":"ES",
    "sg:address":"Calle de San Bernardo, 6",
    "sg:city":"Palencia",
    "sg:orig_category":"Ropa Para Ni\u00d1os (al Por Menor)",
    "sg:phone":"+34 979 74 28 91",
    "sg:postcode":"34002",
    "sg:province":"Palencia",
    "wof:name":"Lopez Martin Gabriela",
    "wof:placetype":"venue"
},
  "geometry": {"coordinates":[-4.5311532021,42.0075378418],"type":"Point"}
}