{
  "type": "Feature",
  "properties": {
    "iso:country":"ES",
    "sg:address":"Calle de Eduardo Bosca, 21",
    "sg:city":"Valencia",
    "sg:orig_category":"Sociedades, Compa\u00d1\u00cdas Aseguradoras",
    "sg:phone":"+34 963 37 48 64",
    "sg:postcode":"46023",
    "sg:province":"Valencia",
    "sg:website":"www.seguronline.com",
    "wof:name":"Mu\u00f1iz Y Asociados Correduria Seguros S.l.",
    "wof:placetype":"venue"
},
  "geometry": {"coordinates":[-0.3576076925,39.4646339417],"type":"Point"}
}