{
  "type": "Feature",
  "properties": {
    "iso:country":"ES",
    "sg:address":"Avda Leo Delibes, 4",
    "sg:city":"Malaga",
    "sg:orig_category":"Muebles",
    "sg:phone":"+34 952 24 13 06",
    "sg:postcode":"29004",
    "sg:province":"M\u00e1laga",
    "wof:name":"Gomez Rincon Juan",
    "wof:placetype":"venue"
},
  "geometry": {"coordinates":[-4.4574260712,36.691570282],"type":"Point"}
}