{
  "type": "Feature",
  "properties": {
    "addr:full":"Miramar, S/n A Ramallosa Pontevedra 36393",
    "addr:housenumber":"/ n",
    "addr:postcode":"36393",
    "addr:street":"Miramar S;A Ramallosa",
    "iso:country":"ES",
    "sg:address":"Miramar, S/n",
    "sg:city":"A Ramallosa",
    "sg:orig_category":"Doctores En Medicina",
    "sg:phone":"+34 986 35 26 97",
    "sg:postcode":"36393",
    "sg:province":"Pontevedra",
    "wof:name":"Portela Jelusich Jose Manuel",
    "wof:placetype":"venue"
},
  "geometry": {"coordinates":[-8.8274269104,42.1040344238],"type":"Point"}
}