{
  "type": "Feature",
  "properties": {
    "addr:full":"Carrer de Antoni Gaudi, 21 Gava Barcelona 08850",
    "addr:housenumber":"21",
    "addr:postcode":"08850",
    "addr:street":"Carrer De Antoni Gaudi",
    "iso:country":"ES",
    "sg:address":"Carrer de Antoni Gaudi, 21",
    "sg:city":"Gava",
    "sg:orig_category":"Ropa De Hogar (al Por Menor)",
    "sg:phone":"+34 936 62 51 12",
    "sg:postcode":"08850",
    "sg:province":"Barcelona",
    "wof:name":"Garrido Hernandez Miguel",
    "wof:placetype":"venue"
},
  "geometry": {"coordinates":[2.0012850761,41.3040237427],"type":"Point"}
}