{
  "type": "Feature",
  "properties": {
    "iso:country":"ES",
    "sg:address":"Carr Girona, 41",
    "sg:city":"Lleida",
    "sg:orig_category":"Estancos",
    "sg:phone":"+34 973 23 62 02",
    "sg:postcode":"25005",
    "sg:province":"Lleida",
    "wof:name":"Ortega Garcia Carmina",
    "wof:placetype":"venue"
},
  "geometry": {"coordinates":[0.635011971,41.6240692139],"type":"Point"}
}