{
  "type": "Feature",
  "properties": {
    "addr:full":"Calle de Parque Eugenia De Montijo, 20 Madrid Madrid 28047",
    "addr:housenumber":"20",
    "addr:postcode":"madrid;28047",
    "addr:street":"Calle De Parque Eugenia De Montijo",
    "iso:country":"ES",
    "sg:address":"Calle de Parque Eugenia De Montijo, 20",
    "sg:city":"Madrid",
    "sg:orig_category":"Empresas De Carpinter\u00cda Met\u00c1lica",
    "sg:phone":"+34 914 22 02 02",
    "sg:postcode":"28047",
    "sg:province":"Madrid",
    "sg:website":"www.aluminiossanchez.com",
    "wof:name":"Sanchez Martinez Juan Manuel",
    "wof:placetype":"venue"
},
  "geometry": {"coordinates":[-3.7538700104,40.378528595],"type":"Point"}
}