{
  "type": "Feature",
  "properties": {
    "iso:country":"ES",
    "sg:address":"Ptda Erica, 39",
    "sg:city":"Catral",
    "sg:orig_category":"Jardiner\u00cdas, Vegetales, Art\u00cdculos De Jardiner\u00cda (al Por Menor)",
    "sg:phone":"+34 965 72 30 07",
    "sg:postcode":"03158",
    "sg:province":"Alicante",
    "wof:name":"Catral Export S.l.",
    "wof:placetype":"venue"
},
  "geometry": {"coordinates":[-0.8021739721,38.1631393433],"type":"Point"}
}