{
  "type": "Feature",
  "properties": {
    "addr:full":"Carr Chopitea, 110 Calella Girona 17210",
    "addr:housenumber":"110",
    "addr:postcode":"17210",
    "addr:street":"Carr Chopitea",
    "iso:country":"ES",
    "sg:address":"Carr Chopitea, 110",
    "sg:city":"Calella",
    "sg:orig_category":"Zonas De Acampada, Aparcamiento Para Caravanas",
    "sg:phone":"+34 972 61 51 16",
    "sg:postcode":"17210",
    "sg:province":"Girona",
    "wof:name":"Ecoci Parcs S.l.",
    "wof:placetype":"venue"
},
  "geometry": {"coordinates":[3.1871829033,41.8926353455],"type":"Point"}
}