{
  "type": "Feature",
  "properties": {
    "iso:country":"ES",
    "sg:address":"Calle de Ingeniero Ildefonso Prieto, 30",
    "sg:city":"Bonares",
    "sg:orig_category":"Farmacias",
    "sg:phone":"+34 959 36 60 30",
    "sg:postcode":"21830",
    "sg:province":"Huelva",
    "wof:name":"Vivas Gomez Maria Victoria",
    "wof:placetype":"venue"
},
  "geometry": {"coordinates":[-6.6745042801,37.2908287048],"type":"Point"}
}