{
  "type": "Feature",
  "properties": {
    "iso:country":"ES",
    "sg:address":"Calle de Zubiaurre, 2",
    "sg:city":"Errenteria",
    "sg:orig_category":"Confecci\u00d3n De Trajes Para Se\u00d1oras",
    "sg:phone":"+34 943 11 47 52",
    "sg:postcode":"20100",
    "sg:province":"Guip\u00f9zcoa",
    "wof:name":"Maria Paz Jimenez Arriada",
    "wof:placetype":"venue"
},
  "geometry": {"coordinates":[-1.8979879618,43.3136825562],"type":"Point"}
}