{
  "type": "Feature",
  "properties": {
    "iso:country":"ES",
    "sg:address":"Rond Torrassa, 78",
    "sg:city":"Hospitalet Llobregat",
    "sg:orig_category":"Tapiceros Y Tapiceros",
    "sg:phone":"+34 934 22 70 38",
    "sg:postcode":"08903",
    "sg:province":"Barcelona",
    "wof:name":"Sanchez Montilla Gabriel",
    "wof:placetype":"venue"
},
  "geometry": {"coordinates":[2.1253619194,41.3689041138],"type":"Point"}
}