{
  "type": "Feature",
  "properties": {
    "iso:country":"ES",
    "sg:address":"Calle de Fundidores, 81",
    "sg:city":"Getafe",
    "sg:orig_category":"Montaje (empresas De)",
    "sg:phone":"+34 916 65 35 30",
    "sg:postcode":"28906",
    "sg:province":"Madrid",
    "wof:name":"Emte Redes S.l",
    "wof:placetype":"venue"
},
  "geometry": {"coordinates":[-3.6950368881,40.3127326965],"type":"Point"}
}