{
  "type": "Feature",
  "properties": {
    "addr:full":"Calle de Nueva, 10 Malaga M\u00e1laga 29005",
    "addr:housenumber":"10",
    "addr:postcode":"29005",
    "addr:street":"Calle De Nueva;Ma\u0301Laga",
    "iso:country":"ES",
    "sg:address":"Calle de Nueva, 10",
    "sg:city":"Malaga",
    "sg:orig_category":"Ropa Y Accesorios",
    "sg:phone":"+34 952 21 68 95",
    "sg:postcode":"29005",
    "sg:province":"M\u00e1laga",
    "wof:name":"Pecafami S.l.",
    "wof:placetype":"venue"
},
  "geometry": {"coordinates":[-4.4228811264,36.7204589844],"type":"Point"}
}