{
  "type": "Feature",
  "properties": {
    "iso:country":"ES",
    "sg:address":"Carrer de Almeria, 37",
    "sg:city":"Masnou",
    "sg:orig_category":"Frutas, Legumbres Frescas Y Tempranas (al Por Menor)",
    "sg:phone":"+34 935 40 38 05",
    "sg:postcode":"08320",
    "sg:province":"Barcelona",
    "wof:name":"Hermanos Martinez Lopez S.c.p.",
    "wof:placetype":"venue"
},
  "geometry": {"coordinates":[2.307090044,41.4865264893],"type":"Point"}
}