{
  "type": "Feature",
  "properties": {
    "iso:country":"ES",
    "sg:address":"Carrer de Palla, 9",
    "sg:city":"Barcelona",
    "sg:orig_category":"Artesan\u00cda",
    "sg:phone":"+34 933 01 19 09",
    "sg:postcode":"08002",
    "sg:province":"Barcelona",
    "wof:name":"Nomadas Artist",
    "wof:placetype":"venue"
},
  "geometry": {"coordinates":[2.1741759777,41.3830718994],"type":"Point"}
}