{
  "type": "Feature",
  "properties": {
    "iso:country":"ES",
    "sg:address":"Calle de Mayor, 62",
    "sg:city":"Sang\u00fcesa",
    "sg:orig_category":"Centros De Coordinaci\u00d3n",
    "sg:phone":"+34 948 87 03 05",
    "sg:postcode":"31400",
    "sg:province":"Navarra",
    "wof:name":"Andia Aldave Anastasio",
    "wof:placetype":"venue"
},
  "geometry": {"coordinates":[-1.2824877501,42.5762481689],"type":"Point"}
}