{
  "type": "Feature",
  "properties": {
    "iso:country":"ES",
    "sg:address":"Praz Vigo (de), S/n",
    "sg:city":"Santiago De Compostela",
    "sg:orig_category":"Aparcamientos (infraestructuras, Accesorios)",
    "sg:phone":"+34 981 56 34 08",
    "sg:postcode":"15706",
    "sg:province":"La Coru\u00f1a",
    "wof:name":"Aparcamientos Sar S A",
    "wof:placetype":"venue"
},
  "geometry": {"coordinates":[-8.5666074753,42.8589172363],"type":"Point"}
}