{
  "type": "Feature",
  "properties": {
    "iso:country":"ES",
    "sg:address":"Dr. Gil Lopez, 2",
    "sg:city":"Massanassa",
    "sg:orig_category":"M\u00c9dicos: Estomatolog\u00cda",
    "sg:phone":"+34 961 25 08 88",
    "sg:postcode":"46470",
    "sg:province":"Valencia",
    "wof:name":"Arnao Herraiz Juan Carlos 000398912x Sln",
    "wof:placetype":"venue"
},
  "geometry": {"coordinates":[-0.3987787962,39.4107933044],"type":"Point"}
}