{
  "type": "Feature",
  "properties": {
    "addr:full":"Urb Carrizal Grande, S/n Salinas Valladolid 47400",
    "addr:housenumber":"s / n",
    "addr:postcode":"47400",
    "addr:street":"Urb Carrizal Grande",
    "iso:country":"ES",
    "sg:address":"Urb Carrizal Grande, S/n",
    "sg:city":"Salinas",
    "sg:orig_category":"Muebles Y Accesorios Para Cocinas Y Cuartos De Ba\u00d1o (al Por Menor)",
    "sg:phone":"+34 983 80 08 17",
    "sg:postcode":"47400",
    "sg:province":"Valladolid",
    "wof:name":"Jimenez Gonzalez Miguel Angel",
    "wof:placetype":"venue"
},
  "geometry": {"coordinates":[-4.913184166,41.3120155334],"type":"Point"}
}