{
  "type": "Feature",
  "properties": {
    "iso:country":"ES",
    "sg:address":"Calle de Jesus, 12",
    "sg:city":"Valencia",
    "sg:orig_category":"Zapatos (al Por Menor)",
    "sg:phone":"+34 963 94 01 79",
    "sg:postcode":"46007",
    "sg:province":"Valencia",
    "sg:website":"www.solodance.es",
    "wof:name":"Solodance S.l.",
    "wof:placetype":"venue"
},
  "geometry": {"coordinates":[-0.3817088008,39.4682121277],"type":"Point"}
}