{
  "type": "Feature",
  "properties": {
    "iso:country":"ES",
    "sg:address":"Calle de Maestro Solano, 2",
    "sg:city":"Torremolinos",
    "sg:orig_category":"Abogados",
    "sg:phone":"+34 952 37 66 32",
    "sg:postcode":"29620",
    "sg:province":"M\u00e1laga",
    "wof:name":"Caucion Y Derecho S.l.",
    "wof:placetype":"venue"
},
  "geometry": {"coordinates":[-4.503467083,36.6285858154],"type":"Point"}
}