{
  "type": "Feature",
  "properties": {
    "addr:full":"Carrer de Pomaret, 49 Barcelona Barcelona 08017",
    "addr:housenumber":"49",
    "addr:postcode":"08017",
    "addr:street":"Carrer De Pomaret",
    "iso:country":"ES",
    "sg:address":"Carrer de Pomaret, 49",
    "sg:city":"Barcelona",
    "sg:orig_category":"Asociaciones Y Clubs Deportivos",
    "sg:phone":"+34 934 34 05 27",
    "sg:postcode":"08017",
    "sg:province":"Barcelona",
    "wof:name":"Deportivo Squash Arsenal S.l.",
    "wof:placetype":"venue"
},
  "geometry": {"coordinates":[2.1222579479,41.4062767029],"type":"Point"}
}