{
  "type": "Feature",
  "properties": {
    "iso:country":"ES",
    "sg:address":"Ctra. S. Bartolome, Km. 0000,0",
    "sg:city":"Gibraleon",
    "sg:orig_category":"Molduras, Junquillos, Listones Y Molduras Perforadas",
    "sg:phone":"+34 959 30 01 25",
    "sg:postcode":"21500",
    "sg:province":"Huelva",
    "wof:name":"Gomez Gomez Diego",
    "wof:placetype":"venue"
},
  "geometry": {"coordinates":[-6.9744291306,37.3773460388],"type":"Point"}
}