{
  "type": "Feature",
  "properties": {
    "iso:country":"ES",
    "sg:address":"Barrio Triana, 190",
    "sg:city":"Vila Joiosa",
    "sg:orig_category":"Inform\u00c1tica: Redes",
    "sg:phone":"+34 965 89 04 62",
    "sg:postcode":"03570",
    "sg:province":"Alicante",
    "wof:name":"Cabos Y Redes S.a.",
    "wof:placetype":"venue"
},
  "geometry": {"coordinates":[-0.2207490057,38.5116882324],"type":"Point"}
}