{
  "type": "Feature",
  "properties": {
    "iso:country":"ES",
    "sg:address":"Elorrea Kalea, 6",
    "sg:city":"Derio",
    "sg:orig_category":"Ense\u00d1anza: Idiomas",
    "sg:phone":"+34 944 54 28 67",
    "sg:postcode":"48160",
    "sg:province":"Vizcaya",
    "wof:name":"Brendan Pierce Academia",
    "wof:placetype":"venue"
},
  "geometry": {"coordinates":[-2.8847301006,43.2978668213],"type":"Point"}
}