{
  "type": "Feature",
  "properties": {
    "iso:country":"ES",
    "sg:address":"Calle de Marques De Pickman, 13",
    "sg:city":"Sevilla",
    "sg:orig_category":"Farmacias",
    "sg:phone":"+34 954 57 76 44",
    "sg:postcode":"41005",
    "sg:province":"Sevilla",
    "wof:name":"Farmacia Mercado De Nervion C.b.",
    "wof:placetype":"venue"
},
  "geometry": {"coordinates":[-5.9638471603,37.3814506531],"type":"Point"}
}