{
  "type": "Feature",
  "properties": {
    "addr:full":"Cno. Sol, 50 Retamar Almer\u00eda 04130",
    "addr:housenumber":"50",
    "addr:postcode":"04130",
    "addr:street":"Cno. Sol;Almeri\u0301A",
    "iso:country":"ES",
    "sg:address":"Cno. Sol, 50",
    "sg:city":"Retamar",
    "sg:orig_category":"Supermercados Y Hipermercados",
    "sg:phone":"+34 950 20 83 26",
    "sg:postcode":"04130",
    "sg:province":"Almer\u00eda",
    "wof:name":"Morales Garcia Manuel",
    "wof:placetype":"venue"
},
  "geometry": {"coordinates":[-2.3529150486,36.8523406982],"type":"Point"}
}