{
  "type": "Feature",
  "properties": {
    "addr:full":"Calle de Kareaga, 89 Barakaldo Vizcaya 48903",
    "addr:housenumber":"89",
    "addr:postcode":"48903",
    "addr:street":"Calle De Kareaga",
    "iso:country":"ES",
    "sg:address":"Calle de Kareaga, 89",
    "sg:city":"Barakaldo",
    "sg:orig_category":"Electromec\u00c1nica",
    "sg:phone":"+34 944 04 39 80",
    "sg:postcode":"48903",
    "sg:province":"Vizcaya",
    "wof:name":"Asel Montajes",
    "wof:placetype":"venue"
},
  "geometry": {"coordinates":[-3.0062365532,43.286819458],"type":"Point"}
}