{
  "type": "Feature",
  "properties": {
    "addr:full":"San Xoan, 23 San Xoan Pontevedra 36658",
    "addr:housenumber":"23",
    "addr:postcode":"36658",
    "addr:street":"Xoan",
    "iso:country":"ES",
    "sg:address":"San Xoan, 23",
    "sg:city":"San Xoan",
    "sg:orig_category":"Cerrajer\u00cda, Ferrallista",
    "sg:phone":"+34 986 53 63 79",
    "sg:postcode":"36658",
    "sg:province":"Pontevedra",
    "wof:name":"Cerrajeria Luna S.l.",
    "wof:placetype":"venue"
},
  "geometry": {"coordinates":[-8.6571321487,42.5748329163],"type":"Point"}
}