{
  "type": "Feature",
  "properties": {
    "addr:full":"Avda Rosalia Castro, 30 Milladoiro A Coru\u00f1a 15895",
    "addr:housenumber":"30",
    "addr:postcode":"15895",
    "addr:street":"Avda Rosalia Castro;A Corun\u0303A",
    "iso:country":"ES",
    "sg:address":"Avda Rosalia Castro, 30",
    "sg:city":"Milladoiro",
    "sg:orig_category":"Supermercados Y Hipermercados",
    "sg:phone":"+34 981 52 35 11",
    "sg:postcode":"15895",
    "sg:province":"A Coru\u00f1a",
    "wof:name":"Vego Supermercados S.a.",
    "wof:placetype":"venue"
},
  "geometry": {"coordinates":[-8.576464653,42.845035553],"type":"Point"}
}