{
  "type": "Feature",
  "properties": {
    "addr:full":"Calle de Ca\u00d1as (las), 89 Logro\u00f1o La Rioja 26006",
    "addr:housenumber":"89",
    "addr:postcode":"26006",
    "addr:street":"Calle De Can\u0303As Las;Rioja",
    "iso:country":"ES",
    "sg:address":"Calle de Ca\u00d1as (las), 89",
    "sg:city":"Logro\u00f1o",
    "sg:orig_category":"Reciclaje, Desguace De Veh\u00cdculos",
    "sg:phone":"+34 941 26 51 20",
    "sg:postcode":"26006",
    "sg:province":"La Rioja",
    "sg:website":"desguaceslogrono.com",
    "wof:name":"Desguaces Logro\u00d1o S.l",
    "wof:placetype":"venue"
},
  "geometry": {"coordinates":[-2.4036989212,42.46043396],"type":"Point"}
}