{
  "type": "Feature",
  "properties": {
    "addr:full":"Rier Figuera Major, 49 Mataro Barcelona 08304",
    "addr:housenumber":"49",
    "addr:postcode":"08304",
    "addr:street":"Major",
    "iso:country":"ES",
    "sg:address":"Rier Figuera Major, 49",
    "sg:city":"Mataro",
    "sg:orig_category":"Reposter\u00cdas",
    "sg:phone":"+34 937 57 70 91",
    "sg:postcode":"08304",
    "sg:province":"Barcelona",
    "wof:name":"Espin Aguayo Marisol",
    "wof:placetype":"venue"
},
  "geometry": {"coordinates":[2.4444200993,41.5493888855],"type":"Point"}
}