{
  "type": "Feature",
  "properties": {
    "iso:country":"ES",
    "sg:address":"Calle de Miguel Fluiters, 33",
    "sg:city":"Guadalajara",
    "sg:orig_category":"Bisuter\u00cda, Joyer\u00cda, Relojer\u00cda (al Por Menor)",
    "sg:phone":"+34 949 21 44 26",
    "sg:postcode":"19001",
    "sg:province":"Guadalajara",
    "wof:name":"Villa Sanchez Javier",
    "wof:placetype":"venue"
},
  "geometry": {"coordinates":[-3.1677188873,40.6351356506],"type":"Point"}
}