{
  "type": "Feature",
  "properties": {
    "addr:full":"Calle de Mayor, 24 Union Murcia 30360",
    "addr:housenumber":"24",
    "addr:postcode":"30360",
    "addr:street":"Calle De Mayor",
    "iso:country":"ES",
    "sg:address":"Calle de Mayor, 24",
    "sg:city":"Union",
    "sg:orig_category":"Puertas Y Portales",
    "sg:phone":"+34 968 56 05 60",
    "sg:postcode":"30360",
    "sg:province":"Murcia",
    "wof:name":"Salazar Conesa Antonio",
    "wof:placetype":"venue"
},
  "geometry": {"coordinates":[-0.8806679845,37.6164016724],"type":"Point"}
}