{
  "type": "Feature",
  "properties": {
    "iso:country":"ES",
    "sg:address":"Carrer de Sant Pau, 13",
    "sg:city":"Barcelona",
    "sg:orig_category":"Electricidad, Electr\u00d3nica: Suministros (al Por Menor)",
    "sg:phone":"+34 933 02 24 77",
    "sg:postcode":"08001",
    "sg:province":"Barcelona",
    "wof:name":"Payphone Telecom S.l.",
    "wof:placetype":"venue"
},
  "geometry": {"coordinates":[2.1728310585,41.3797531128],"type":"Point"}
}