{
  "type": "Feature",
  "properties": {
    "iso:country":"ES",
    "sg:address":"Av Lluis Companys, 8",
    "sg:city":"S. Cugat Valles",
    "sg:orig_category":"Sociedades, Compa\u00d1\u00cdas Aseguradoras",
    "sg:phone":"+34 936 74 17 36",
    "sg:postcode":"08172",
    "sg:province":"Barcelona",
    "wof:name":"Mapfre Servicios De Informatica",
    "wof:placetype":"venue"
},
  "geometry": {"coordinates":[2.0785119534,41.4689979553],"type":"Point"}
}