{
  "type": "Feature",
  "properties": {
    "addr:full":"Calle de Banco Espa\u00d1a, 2 Bilbao Vizcaya 48005",
    "addr:housenumber":"2",
    "addr:postcode":"48005",
    "addr:street":"Calle De;Espan\u0303A",
    "iso:country":"ES",
    "sg:address":"Calle de Banco Espa\u00d1a, 2",
    "sg:city":"Bilbao",
    "sg:orig_category":"Peluquer\u00cdas, Peluquer\u00cda Mixta",
    "sg:phone":"+34 944 15 88 87",
    "sg:postcode":"48005",
    "sg:province":"Vizcaya",
    "wof:name":"Rico Ruano Ana",
    "wof:placetype":"venue"
},
  "geometry": {"coordinates":[-2.9232823849,43.2578544617],"type":"Point"}
}