{
  "type": "Feature",
  "properties": {
    "addr:full":"Plaz Espa\u00d1a, 5 Albolote Granada 18220",
    "addr:housenumber":"5",
    "addr:postcode":"18220",
    "addr:street":"Plaz Espan\u0303A",
    "iso:country":"ES",
    "sg:address":"Plaz Espa\u00d1a, 5",
    "sg:city":"Albolote",
    "sg:orig_category":"Frutas Y Legumbres Frescas (al Por Mayor)",
    "sg:phone":"+34 958 46 64 16",
    "sg:postcode":"18220",
    "sg:province":"Granada",
    "wof:name":"Ramirez Ramirez Francisco",
    "wof:placetype":"venue"
},
  "geometry": {"coordinates":[-3.656826973,37.2307167053],"type":"Point"}
}