{
  "type": "Feature",
  "properties": {
    "addr:full":"Pg Francesc Macia (de), 98 Torredembarra Tarragona 43830",
    "addr:housenumber":"98",
    "addr:postcode":"43830",
    "addr:street":"Pg Francesc Macia De",
    "iso:country":"ES",
    "sg:address":"Pg Francesc Macia (de), 98",
    "sg:city":"Torredembarra",
    "sg:orig_category":"Institutos De Belleza",
    "sg:phone":"+34 977 64 47 79",
    "sg:postcode":"43830",
    "sg:province":"Tarragona",
    "wof:name":"Pijuan Bairaguet Pilar",
    "wof:placetype":"venue"
},
  "geometry": {"coordinates":[1.4111809731,41.1439704895],"type":"Point"}
}