{
  "type": "Feature",
  "properties": {
    "addr:full":"Carr Abadia, 2 Benifaio Valencia 46450",
    "addr:housenumber":"2",
    "addr:postcode":"46450",
    "addr:street":"Carr Abadia",
    "iso:country":"ES",
    "sg:address":"Carr Abadia, 2",
    "sg:city":"Benifaio",
    "sg:orig_category":"Promotores Constructores",
    "sg:phone":"+34 961 79 40 28",
    "sg:postcode":"46450",
    "sg:province":"Valencia",
    "wof:name":"Proyectos Inmobisol S.l.",
    "wof:placetype":"venue"
},
  "geometry": {"coordinates":[-0.4229789972,39.2867202759],"type":"Point"}
}