{
  "type": "Feature",
  "properties": {
    "addr:full":"Orkolaga Kalea, 2 A Hernani Guip\u00f9zcoa 20120",
    "addr:housenumber":"2 a",
    "addr:postcode":"20120",
    "addr:street":"Orkolaga Kalea;Guipu\u0300Zcoa",
    "iso:country":"ES",
    "sg:address":"Orkolaga Kalea, 2 A",
    "sg:city":"Hernani",
    "sg:orig_category":"Restaurantes",
    "sg:phone":"+34 943 33 60 56",
    "sg:postcode":"20120",
    "sg:province":"Guip\u00f9zcoa",
    "wof:name":"Arkaitz Valle Gorrotxategi",
    "wof:placetype":"venue"
},
  "geometry": {"coordinates":[-1.9757970572,43.2680091858],"type":"Point"}
}