{
  "type": "Feature",
  "properties": {
    "addr:full":"Calle de Asturias, 5 Oviedo Asturias 33004",
    "addr:housenumber":"5",
    "addr:postcode":"33004",
    "addr:street":"Calle De Asturias",
    "iso:country":"ES",
    "sg:address":"Calle de Asturias, 5",
    "sg:city":"Oviedo",
    "sg:orig_category":"Promotores Constructores",
    "sg:phone":"+34 985 24 52 50",
    "sg:postcode":"33004",
    "sg:province":"Asturias",
    "wof:name":"Goncesco Grupo S.l.",
    "wof:placetype":"venue"
},
  "geometry": {"coordinates":[-5.8539586067,43.3621635437],"type":"Point"}
}