{
  "type": "Feature",
  "properties": {
    "iso:country":"ES",
    "sg:address":"Plz. M. Mateos, S/n",
    "sg:city":"Bejar",
    "sg:orig_category":"Museos",
    "sg:phone":"+34 923 40 07 38",
    "sg:postcode":"37700",
    "sg:province":"Salamanca",
    "wof:name":"Ayuntamiento De Bejar",
    "wof:placetype":"venue"
},
  "geometry": {"coordinates":[-5.7707138062,40.387424469],"type":"Point"}
}