{
  "type": "Feature",
  "properties": {
    "addr:full":"Avda Urdaneta, 13 Zumarraga Guip\u00f9zcoa 20700",
    "addr:housenumber":"13",
    "addr:postcode":"20700",
    "addr:street":"Avda Urdaneta;Guipu\u0300Zcoa",
    "iso:country":"ES",
    "sg:address":"Avda Urdaneta, 13",
    "sg:city":"Zumarraga",
    "sg:orig_category":"Supermercados Y Hipermercados",
    "sg:phone":"+34 943 72 21 13",
    "sg:postcode":"20700",
    "sg:province":"Guip\u00f9zcoa",
    "wof:name":"Aurole S.l.",
    "wof:placetype":"venue"
},
  "geometry": {"coordinates":[-2.3158721924,43.0878334045],"type":"Point"}
}