{
  "type": "Feature",
  "properties": {
    "addr:full":"Calle de Ingeniero Juan De La Cierva, S/n Cordoba C\u00f3rdoba 14013",
    "addr:housenumber":"s / n",
    "addr:postcode":"14013",
    "addr:street":"Calle De Ingeniero Juan De La Cierva;Co\u0301Rdoba",
    "iso:country":"ES",
    "sg:address":"Calle de Ingeniero Juan De La Cierva, S/n",
    "sg:city":"Cordoba",
    "sg:orig_category":"Fabricaci\u00d3n De Equipos Y Piezas Para Veh\u00cdculos, Veh\u00cdculos Industriales",
    "sg:phone":"+34 957 76 06 66",
    "sg:postcode":"14013",
    "sg:province":"C\u00f3rdoba",
    "wof:name":"Grupo Pe\u00f1a Automocion S.l.",
    "wof:placetype":"venue"
},
  "geometry": {"coordinates":[-4.7913241386,37.8515510559],"type":"Point"}
}