{
  "type": "Feature",
  "properties": {
    "iso:country":"ES",
    "sg:address":"Calle de Murillo, 7",
    "sg:city":"Soto Marina",
    "sg:orig_category":"Prot\u00c9sicos Dentales",
    "sg:phone":"+34 942 58 70 71",
    "sg:postcode":"39110",
    "sg:province":"Cantabria",
    "wof:name":"Laboratorio De Procesos En Prostodoncia S.l.",
    "wof:placetype":"venue"
},
  "geometry": {"coordinates":[-3.8863790035,43.4608459473],"type":"Point"}
}