{
  "type": "Feature",
  "properties": {
    "addr:full":"Pase Canalejas, 20 Salamanca Salamanca 37001",
    "addr:housenumber":"20",
    "addr:postcode":"37001",
    "addr:street":"Canalejas",
    "iso:country":"ES",
    "sg:address":"Pase Canalejas, 20",
    "sg:city":"Salamanca",
    "sg:orig_category":"Fotocopias, Reprograf\u00cda",
    "sg:phone":"+34 923 26 42 73",
    "sg:postcode":"37001",
    "sg:province":"Salamanca",
    "wof:name":"Copisteria Ope S.l.",
    "wof:placetype":"venue"
},
  "geometry": {"coordinates":[-5.6580839157,40.9668884277],"type":"Point"}
}