{
  "type": "Feature",
  "properties": {
    "iso:country":"ES",
    "sg:address":"Ctra. Lorca-baza, 46",
    "sg:city":"Olula Rio",
    "sg:orig_category":"Contenedores (mercanc\u00cdas)",
    "sg:phone":"+34 950 44 17 58",
    "sg:postcode":"04860",
    "sg:province":"Almer\u00eda",
    "wof:name":"Navarro Casta\u00f1o Manuel",
    "wof:placetype":"venue"
},
  "geometry": {"coordinates":[-2.2987639904,37.3577842712],"type":"Point"}
}