{
  "type": "Feature",
  "properties": {
    "iso:country":"ES",
    "sg:address":"Calle de Doctor Castilla, 7",
    "sg:city":"Capileira",
    "sg:orig_category":"Cueros Y Pieles (al Por Mayor)",
    "sg:phone":"+34 958 76 30 92",
    "sg:postcode":"18413",
    "sg:province":"Granada",
    "wof:name":"Moreno Gonzalez De Eiris Jose Manuel",
    "wof:placetype":"venue"
},
  "geometry": {"coordinates":[-3.3591666222,36.9611930847],"type":"Point"}
}