{
  "type": "Feature",
  "properties": {
    "iso:country":"ES",
    "sg:address":"Avda Bulevar De El Ejido, 432",
    "sg:city":"Ejido",
    "sg:orig_category":"Consultas M\u00c9dicas",
    "sg:phone":"+34 950 48 09 80",
    "sg:postcode":"04700",
    "sg:province":"Almer\u00eda",
    "wof:name":"Jofrefiv S.l.",
    "wof:placetype":"venue"
},
  "geometry": {"coordinates":[-2.8058309555,36.7609977722],"type":"Point"}
}