{
  "type": "Feature",
  "properties": {
    "iso:country":"ES",
    "sg:address":"Calle de Fontanares, 55",
    "sg:city":"Valencia",
    "sg:orig_category":"Inform\u00c1tica, Ofim\u00c1tica (estudios, Asesor\u00cda, Ingenier\u00cda, Formaci\u00d3n)",
    "sg:phone":"+34 963 57 45 11",
    "sg:postcode":"46014",
    "sg:province":"Valencia",
    "sg:website":"www.acimut.com",
    "wof:name":"Acimut Integracion De Sistemas S.l.",
    "wof:placetype":"venue"
},
  "geometry": {"coordinates":[-0.3974159062,39.4632720947],"type":"Point"}
}