{
  "type": "Feature",
  "properties": {
    "addr:full":"Calle de Andalucia, 64 Algeciras C\u00e1diz 11...",
    "addr:housenumber":"64;11 ...",
    "addr:street":"Calle De Andalucia;Ca\u0301Diz",
    "iso:country":"ES",
    "sg:address":"Calle de Andalucia, 64",
    "sg:city":"Algeciras",
    "sg:orig_category":"Cooperativas Agr\u00cdcolas",
    "sg:phone":"+34 956 57 23 40",
    "sg:postcode":"11...",
    "sg:province":"C\u00e1diz",
    "wof:name":"Cooperativa Farmaceutica Del Campo De Gibraltar",
    "wof:placetype":"venue"
},
  "geometry": {"coordinates":[-5.459663868,36.1198272705],"type":"Point"}
}