{
  "type": "Feature",
  "properties": {
    "iso:country":"ES",
    "sg:address":"Calle de Flores, 3",
    "sg:city":"Santa Fe",
    "sg:orig_category":"Molduras, Junquillos, Listones Y Molduras Perforadas",
    "sg:phone":"+34 958 44 01 69",
    "sg:postcode":"18320",
    "sg:province":"Granada",
    "wof:name":"Garcia Roldan Miguel",
    "wof:placetype":"venue"
},
  "geometry": {"coordinates":[-3.7179849148,37.190032959],"type":"Point"}
}