{
  "type": "Feature",
  "properties": {
    "addr:full":"Calle de Mateo Bidaurrazaga Alkatea, 1 Basozabal Vizcaya 48150",
    "addr:housenumber":"1",
    "addr:postcode":"48150",
    "addr:street":"Calle De Mateo Bidaurrazaga Alkatea",
    "iso:country":"ES",
    "sg:address":"Calle de Mateo Bidaurrazaga Alkatea, 1",
    "sg:city":"Basozabal",
    "sg:orig_category":"Asesor\u00cda Sobre Comunicaci\u00d3n De Empresas",
    "sg:phone":"+34 944 53 33 28",
    "sg:postcode":"48150",
    "sg:province":"Vizcaya",
    "sg:website":"www.isollex.com",
    "wof:name":"Asesoria Luis Fernando Aguirre S.l.",
    "wof:placetype":"venue"
},
  "geometry": {"coordinates":[-2.9282727242,43.2996444702],"type":"Point"}
}