{
  "type": "Feature",
  "properties": {
    "iso:country":"ES",
    "sg:address":"Pazos, S/n",
    "sg:city":"Pazos",
    "sg:orig_category":"Construcciones Navales Y Fluviales",
    "sg:phone":"+34 986 67 22 51",
    "sg:postcode":"36141",
    "sg:province":"Pontevedra",
    "wof:name":"Otero Vazquez Claudio",
    "wof:placetype":"venue"
},
  "geometry": {"coordinates":[-8.5276670456,42.29164505],"type":"Point"}
}