{
  "type": "Feature",
  "properties": {
    "iso:country":"ES",
    "sg:address":"Avda Hispanidad, 90",
    "sg:city":"Valderrobres",
    "sg:orig_category":"Discotecas Y Salas De Baile",
    "sg:phone":"+34 978 89 04 97",
    "sg:postcode":"44580",
    "sg:province":"Teruel",
    "wof:name":"Celma Guimera S.l.",
    "wof:placetype":"venue"
},
  "geometry": {"coordinates":[0.1536339968,40.8707733154],"type":"Point"}
}