{
  "type": "Feature",
  "properties": {
    "addr:full":"Calle de Hermanos Rivas, 22 Valencia Valencia 46018",
    "addr:housenumber":"22",
    "addr:postcode":"46018",
    "addr:street":"Calle De Hermanos Rivas",
    "iso:country":"ES",
    "sg:address":"Calle de Hermanos Rivas, 22",
    "sg:city":"Valencia",
    "sg:orig_category":"Ense\u00d1anza: Comercio, Gesti\u00d3n, Inform\u00c1tica",
    "sg:phone":"+34 963 70 90 93",
    "sg:postcode":"46018",
    "sg:province":"Valencia",
    "sg:website":"www.gfinformatica.com",
    "wof:name":"Acrofor S.l.",
    "wof:placetype":"venue"
},
  "geometry": {"coordinates":[-0.3964630067,39.4684028625],"type":"Point"}
}