{
  "type": "Feature",
  "properties": {
    "iso:country":"ES",
    "sg:address":"Avda Americas (das), 22",
    "sg:city":"Lugo",
    "sg:orig_category":"Empresas De Portes Y Mensajer\u00cda",
    "sg:phone":"+34 982 20 13 61",
    "sg:postcode":"27004",
    "sg:province":"Lugo",
    "wof:name":"Fast-24 S.l.",
    "wof:placetype":"venue"
},
  "geometry": {"coordinates":[-7.5679621696,43.0105705261],"type":"Point"}
}