{
  "type": "Feature",
  "properties": {
    "iso:country":"ES",
    "sg:address":"Legia Karrika, 1",
    "sg:city":"Bera",
    "sg:orig_category":"Herboristas (al Por Menor)",
    "sg:phone":"+34 948 63 06 52",
    "sg:postcode":"31780",
    "sg:province":"Navarra",
    "wof:name":"Iturbide Ibarra Ana",
    "wof:placetype":"venue"
},
  "geometry": {"coordinates":[-1.6830849648,43.281879425],"type":"Point"}
}