{
  "type": "Feature",
  "properties": {
    "addr:full":"Av Pau Casals, 9 Tarragona Tarragona 43003",
    "addr:housenumber":"9",
    "addr:postcode":"43003",
    "addr:street":"Av Pau Casals",
    "iso:country":"ES",
    "sg:address":"Av Pau Casals, 9",
    "sg:city":"Tarragona",
    "sg:orig_category":"Abogados",
    "sg:phone":"+34 977 23 98 24",
    "sg:postcode":"43003",
    "sg:province":"Tarragona",
    "wof:name":"Basora Francesch Marcos",
    "wof:placetype":"venue"
},
  "geometry": {"coordinates":[1.2497090101,41.1174621582],"type":"Point"}
}