{
  "type": "Feature",
  "properties": {
    "addr:full":"Rbla Guipuscoa, 145 Barcelona Barcelona 08020",
    "addr:housenumber":"145",
    "addr:postcode":"08020",
    "addr:street":"Rbla Guipuscoa",
    "iso:country":"ES",
    "sg:address":"Rbla Guipuscoa, 145",
    "sg:city":"Barcelona",
    "sg:orig_category":"Electricidad: Instaladores",
    "sg:phone":"+34 933 13 88 48",
    "sg:postcode":"08020",
    "sg:province":"Barcelona",
    "wof:name":"J. Jovani S. A.",
    "wof:placetype":"venue"
},
  "geometry": {"coordinates":[2.2054309845,41.4228744507],"type":"Point"}
}