{
  "type": "Feature",
  "properties": {
    "iso:country":"ES",
    "sg:address":"Ctra Santpedor, 224",
    "sg:city":"Manresa",
    "sg:orig_category":"Arreglo, Reparaci\u00d3n, Piezas Sueltas De Televisi\u00d3n, V\u00cddeo, Hi",
    "sg:phone":"+34 938 74 24 05",
    "sg:postcode":"08243",
    "sg:province":"Barcelona",
    "wof:name":"Pallares Prados Jose",
    "wof:placetype":"venue"
},
  "geometry": {"coordinates":[1.8329529762,41.7397499084],"type":"Point"}
}