{
  "type": "Feature",
  "properties": {
    "addr:full":"Calle de San Jose Obrero, 27 Jedula C\u00e1diz 11620",
    "addr:housenumber":"27",
    "addr:postcode":"11620",
    "addr:street":"Calle De;Obrero;Ca\u0301Diz",
    "iso:country":"ES",
    "sg:address":"Calle de San Jose Obrero, 27",
    "sg:city":"Jedula",
    "sg:orig_category":"Energ\u00cda Solar Y Nuevas Energ\u00cdas (equipo, Estudios)",
    "sg:phone":"+34 956 72 24 44",
    "sg:postcode":"11620",
    "sg:province":"C\u00e1diz",
    "wof:name":"Benitez Lopez Sebastian",
    "wof:placetype":"venue"
},
  "geometry": {"coordinates":[-5.932448864,36.7244110107],"type":"Point"}
}