{
  "type": "Feature",
  "properties": {
    "addr:full":"Rua Nosa Sra. Da Sainza, 24 Ourense Ourense 32005",
    "addr:housenumber":"24",
    "addr:postcode":"32005",
    "addr:street":"Rua Nosa Sra. Da Sainza",
    "iso:country":"ES",
    "sg:address":"Rua Nosa Sra. Da Sainza, 24",
    "sg:city":"Ourense",
    "sg:orig_category":"Muebles Y Accesorios Para Cocinas Y Cuartos De Ba\u00d1o (al Por Menor)",
    "sg:phone":"+34 988 23 94 12",
    "sg:postcode":"32005",
    "sg:province":"Ourense",
    "wof:name":"C.a.c.muebles S.l.",
    "wof:placetype":"venue"
},
  "geometry": {"coordinates":[-7.8622260094,42.3284072876],"type":"Point"}
}