{
  "type": "Feature",
  "properties": {
    "iso:country":"ES",
    "sg:address":"Calle de La Rivera, 2",
    "sg:city":"Guaso",
    "sg:orig_category":"Empresarios Y Productoras De Espect\u00c1culos",
    "sg:phone":"+34 974 51 00 48",
    "sg:postcode":"22349",
    "sg:province":"Huesca",
    "sg:website":"www.rondadors.com",
    "wof:name":"La Ronda De Bolta\u00f1a",
    "wof:placetype":"venue"
},
  "geometry": {"coordinates":[0.0934849977,42.4162368774],"type":"Point"}
}