{
  "type": "Feature",
  "properties": {
    "addr:full":"Carr Rutlla Alta, S/n Sant Joan De Palamos Girona 17230",
    "addr:housenumber":"s / n",
    "addr:postcode":"17230",
    "addr:street":"Carr Rutlla Alta",
    "iso:country":"ES",
    "sg:address":"Carr Rutlla Alta, S/n",
    "sg:city":"Sant Joan De Palamos",
    "sg:orig_category":"Distribuci\u00d3n De Petr\u00d3leo Y Derivados",
    "sg:phone":"+34 972 31 81 03",
    "sg:postcode":"17230",
    "sg:province":"Girona",
    "sg:website":"www.peixosdepalamos.com",
    "wof:name":"Congelats Palamos S. A.",
    "wof:placetype":"venue"
},
  "geometry": {"coordinates":[3.1342549324,41.8609924316],"type":"Point"}
}