{
  "type": "Feature",
  "properties": {
    "iso:country":"ES",
    "sg:address":"Plaz San Pedro Y San Pablo (de), 9",
    "sg:city":"Coslada",
    "sg:orig_category":"Inmobiliaria (agencias)",
    "sg:phone":"+34 916 69 60 20",
    "sg:postcode":"28820",
    "sg:province":"Madrid",
    "wof:name":"Inmocano S.l.",
    "wof:placetype":"venue"
},
  "geometry": {"coordinates":[-3.5671629906,40.425693512],"type":"Point"}
}