{
  "type": "Feature",
  "properties": {
    "iso:country":"ES",
    "sg:address":"Avda Lehendakari Agirre Etorbidea, 14",
    "sg:city":"Elexalde",
    "sg:orig_category":"Supermercados Y Hipermercados",
    "sg:phone":"+34 946 73 62 52",
    "sg:postcode":"48140",
    "sg:province":"Vizcaya",
    "wof:name":"Uvescaya S. L.",
    "wof:placetype":"venue"
},
  "geometry": {"coordinates":[-2.7780580521,43.1636619568],"type":"Point"}
}