{
  "type": "Feature",
  "properties": {
    "addr:full":"Plaz De La Torre, 10 Logrosan C\u00e1ceres 10120",
    "addr:housenumber":"10",
    "addr:postcode":"10120",
    "addr:street":"Plaz;La Torre;Ca\u0301Ceres",
    "iso:country":"ES",
    "sg:address":"Plaz De La Torre, 10",
    "sg:city":"Logrosan",
    "sg:orig_category":"Molduras, Junquillos, Listones Y Molduras Perforadas",
    "sg:phone":"+34 927 36 08 64",
    "sg:postcode":"10120",
    "sg:province":"C\u00e1ceres",
    "wof:name":"Leandro San Roman Miguel",
    "wof:placetype":"venue"
},
  "geometry": {"coordinates":[-5.5197396278,39.3144378662],"type":"Point"}
}