{
  "type": "Feature",
  "properties": {
    "iso:country":"ES",
    "sg:address":"Cmno Valdeoliva, 5",
    "sg:city":"San Agustin Del Guadalix",
    "sg:orig_category":"Suministros Para Carrocer\u00cdas",
    "sg:phone":"+34 918 48 71 90",
    "sg:postcode":"28750",
    "sg:province":"Madrid",
    "wof:name":"Herranz Concesionarios S.a.",
    "wof:placetype":"venue"
},
  "geometry": {"coordinates":[-3.6146740913,40.6783752441],"type":"Point"}
}