{
  "type": "Feature",
  "properties": {
    "addr:full":"Calle de Virgenes, 18 Sevilla Sevilla 41004",
    "addr:housenumber":"18",
    "addr:postcode":"41004",
    "addr:street":"Calle De Virgenes",
    "iso:country":"ES",
    "sg:address":"Calle de Virgenes, 18",
    "sg:city":"Sevilla",
    "sg:orig_category":"Promotores Constructores",
    "sg:phone":"+34 955 03 88 74",
    "sg:postcode":"41004",
    "sg:province":"Sevilla",
    "wof:name":"Gp7 Inmobiliaria Y Control S.l.",
    "wof:placetype":"venue"
},
  "geometry": {"coordinates":[-5.9890789986,37.3897018433],"type":"Point"}
}