{
  "type": "Feature",
  "properties": {
    "iso:country":"ES",
    "sg:address":"Praz America, 2",
    "sg:city":"Vigo",
    "sg:orig_category":"Institutos De Belleza",
    "sg:phone":"+34 986 21 28 21",
    "sg:postcode":"36211",
    "sg:province":"Pontevedra",
    "wof:name":"Martinez Cerezo Amparo",
    "wof:placetype":"venue"
},
  "geometry": {"coordinates":[-8.7330293655,42.2204666138],"type":"Point"}
}