{
  "type": "Feature",
  "properties": {
    "addr:full":"Plaz Tesillo (del), 1 Fuenlabrada Madrid 28944",
    "addr:housenumber":"1",
    "addr:postcode":"28944",
    "addr:street":"Plaz Tesillo Del",
    "iso:country":"ES",
    "sg:address":"Plaz Tesillo (del), 1",
    "sg:city":"Fuenlabrada",
    "sg:orig_category":"Abogados",
    "sg:phone":"+34 916 97 31 69",
    "sg:postcode":"28944",
    "sg:province":"Madrid",
    "wof:name":"Mu\u00f1oz Herrero Gregorio",
    "wof:placetype":"venue"
},
  "geometry": {"coordinates":[-3.7938520908,40.2837905884],"type":"Point"}
}