{
  "type": "Feature",
  "properties": {
    "addr:full":"Rua Colon, 9 Vigo Pontevedra 36201",
    "addr:housenumber":"9",
    "addr:postcode":"36201",
    "addr:street":"Rua Colon",
    "iso:country":"ES",
    "sg:address":"Rua Colon, 9",
    "sg:city":"Vigo",
    "sg:orig_category":"Diplomas Diversos",
    "sg:phone":"+34 986 22 91 98",
    "sg:postcode":"36201",
    "sg:province":"Pontevedra",
    "wof:name":"Lorenzo Gonzalez Jose",
    "wof:placetype":"venue"
},
  "geometry": {"coordinates":[-8.7201824188,42.2385444641],"type":"Point"}
}