{
  "type": "Feature",
  "properties": {
    "addr:full":"Carr Major, 22 Palamos Girona 17230",
    "addr:housenumber":"22",
    "addr:postcode":"17230",
    "addr:street":"Carr Major",
    "iso:country":"ES",
    "sg:address":"Carr Major, 22",
    "sg:city":"Palamos",
    "sg:orig_category":"Agencias Y Asesores De Publicidad",
    "sg:phone":"+34 972 31 92 72",
    "sg:postcode":"17230",
    "sg:province":"Girona",
    "wof:name":"El Taller De Las Fabulas S.l.",
    "wof:placetype":"venue"
},
  "geometry": {"coordinates":[3.1294469833,41.8476142883],"type":"Point"}
}