{
  "type": "Feature",
  "properties": {
    "addr:full":"Calle de Santa Ana, 5 Majadahonda Madrid 28220",
    "addr:housenumber":"5",
    "addr:postcode":"28220",
    "addr:street":"Calle De Santa Ana",
    "iso:country":"ES",
    "sg:address":"Calle de Santa Ana, 5",
    "sg:city":"Majadahonda",
    "sg:orig_category":"Inmobiliaria (agencias)",
    "sg:phone":"+34 916 34 14 99",
    "sg:postcode":"28220",
    "sg:province":"Madrid",
    "wof:name":"Urbitecnia Gestion Inmobiliaria S.l.",
    "wof:placetype":"venue"
},
  "geometry": {"coordinates":[-3.8712809086,40.4723320007],"type":"Point"}
}