{
  "type": "Feature",
  "properties": {
    "iso:country":"ES",
    "sg:address":"Avda Monelos, 115",
    "sg:city":"Coru\u00d1a",
    "sg:orig_category":"Peluqueros: De Se\u00d1oras",
    "sg:phone":"+34 981 29 24 35",
    "sg:postcode":"15009",
    "sg:province":"La Coru\u00f1a",
    "wof:name":"Andrade Garcia Matilde",
    "wof:placetype":"venue"
},
  "geometry": {"coordinates":[-8.4013090134,43.3469047546],"type":"Point"}
}