{
  "type": "Feature",
  "properties": {
    "iso:country":"ES",
    "sg:address":"Ptge Vilaret, 8",
    "sg:city":"Barcelona",
    "sg:orig_category":"Clubes, Asociaciones De Ocio",
    "sg:phone":"+34 932 65 85 29",
    "sg:postcode":"08013",
    "sg:province":"Barcelona",
    "wof:name":"Fernandez Jaumot Carlos Javier",
    "wof:placetype":"venue"
},
  "geometry": {"coordinates":[2.1804468632,41.4060592651],"type":"Point"}
}