{
  "type": "Feature",
  "properties": {
    "iso:country":"ES",
    "sg:address":"Calle de Dorado, 17",
    "sg:city":"Langreo",
    "sg:orig_category":"Zapatos (al Por Menor)",
    "sg:phone":"+34 985 69 40 98",
    "sg:postcode":"33900",
    "sg:province":"Asturias",
    "wof:name":"Victor Cabal Llanes Y Otro Cdad",
    "wof:placetype":"venue"
},
  "geometry": {"coordinates":[-5.6819958687,43.2939071655],"type":"Point"}
}