{
  "type": "Feature",
  "properties": {
    "addr:full":"Ptge Torre Pinyes, 9 Vic Barcelona 08500",
    "addr:housenumber":"9",
    "addr:postcode":"08500",
    "addr:street":"Ptge Torre Pinyes",
    "iso:country":"ES",
    "sg:address":"Ptge Torre Pinyes, 9",
    "sg:city":"Vic",
    "sg:orig_category":"Empresarios",
    "sg:phone":"+34 938 83 29 66",
    "sg:postcode":"08500",
    "sg:province":"Barcelona",
    "wof:name":"Fundacio Privada Centre Medic Psicopedagogic D'osona",
    "wof:placetype":"venue"
},
  "geometry": {"coordinates":[2.2550199032,41.9312210083],"type":"Point"}
}