{
  "type": "Feature",
  "properties": {
    "iso:country":"ES",
    "sg:address":"Av Cortes Valencianas, 5",
    "sg:city":"Albal",
    "sg:orig_category":"Abogados",
    "sg:phone":"+34 961 26 46 03",
    "sg:postcode":"46470",
    "sg:province":"Valencia",
    "wof:name":"Sanchis Dufau Araceli",
    "wof:placetype":"venue"
},
  "geometry": {"coordinates":[-0.4124149978,39.3970527649],"type":"Point"}
}