{
  "type": "Feature",
  "properties": {
    "addr:full":"Pl Comercial, 2 Barcelona Barcelona 08003",
    "addr:housenumber":"2",
    "addr:postcode":"08003",
    "addr:street":"Pl Comercial",
    "iso:country":"ES",
    "sg:address":"Pl Comercial, 2",
    "sg:city":"Barcelona",
    "sg:orig_category":"Frutas Y Legumbres Secas (al Por Mayor)",
    "sg:phone":"+34 933 19 56 85",
    "sg:postcode":"08003",
    "sg:province":"Barcelona",
    "wof:name":"Torras Rafi Ramon",
    "wof:placetype":"venue"
},
  "geometry": {"coordinates":[2.1828041077,41.385799408],"type":"Point"}
}