{
  "type": "Feature",
  "properties": {
    "addr:full":"Rua Colon Calle, 6 Vigo Pontevedra 36201",
    "addr:postcode":"36201",
    "addr:street":"Rua;Calle 6",
    "iso:country":"ES",
    "sg:address":"Rua Colon Calle, 6",
    "sg:city":"Vigo",
    "sg:orig_category":"Asesor\u00cda Sobre Comunicaci\u00d3n De Empresas",
    "sg:phone":"+34 986 22 93 04",
    "sg:postcode":"36201",
    "sg:province":"Pontevedra",
    "wof:name":"Infordoga Sl",
    "wof:placetype":"venue"
},
  "geometry": {"coordinates":[-8.7205562592,42.2387199402],"type":"Point"}
}