{
  "type": "Feature",
  "properties": {
    "addr:full":"Pl Catalunya, 1 Ametlla Mar Tarragona 43860",
    "addr:housenumber":"1",
    "addr:postcode":"43860",
    "addr:street":"Pl Catalunya",
    "iso:country":"ES",
    "sg:address":"Pl Catalunya, 1",
    "sg:city":"Ametlla Mar",
    "sg:orig_category":"Mec\u00c1nico Del Autom\u00d3vil",
    "sg:phone":"+34 977 45 61 38",
    "sg:postcode":"43860",
    "sg:province":"Tarragona",
    "wof:name":"Taller D'automobils I Servei De Grua Garcia S.l.",
    "wof:placetype":"venue"
},
  "geometry": {"coordinates":[0.8026040196,40.8854026794],"type":"Point"}
}