{
  "type": "Feature",
  "properties": {
    "addr:full":"Ctra Ant De Malaga, 41 Granada Granada 18015",
    "addr:housenumber":"41",
    "addr:postcode":"18015",
    "addr:street":"Ctra Ant De Malaga",
    "iso:country":"ES",
    "sg:address":"Ctra Ant De Malaga, 41",
    "sg:city":"Granada",
    "sg:orig_category":"Reposter\u00cdas",
    "sg:phone":"+34 958 27 90 07",
    "sg:postcode":"18015",
    "sg:province":"Granada",
    "wof:name":"Gamipan S.l.",
    "wof:placetype":"venue"
},
  "geometry": {"coordinates":[-3.6356139183,37.1961364746],"type":"Point"}
}