{
  "type": "Feature",
  "properties": {
    "iso:country":"ES",
    "sg:address":"Carr Irene Solsona, 4",
    "sg:city":"Lleida",
    "sg:orig_category":"Peluquer\u00cdas, Peluquer\u00cda Mixta",
    "sg:phone":"+34 973 22 47 73",
    "sg:postcode":"25005",
    "sg:province":"Lleida",
    "wof:name":"Caldero Pibrall Jorge",
    "wof:placetype":"venue"
},
  "geometry": {"coordinates":[0.6300669909,41.6263694763],"type":"Point"}
}