{
  "type": "Feature",
  "properties": {
    "addr:full":"Pol Ind Alhaurin Torre, S/n Alhaurin Torre M\u00e1laga 29130",
    "addr:housenumber":"s / n",
    "addr:postcode":"29130",
    "iso:country":"ES",
    "sg:address":"Pol Ind Alhaurin Torre, S/n",
    "sg:city":"Alhaurin Torre",
    "sg:orig_category":"Construcciones Met\u00c1licas",
    "sg:phone":"+34 952 41 62 66",
    "sg:postcode":"29130",
    "sg:province":"M\u00e1laga",
    "wof:name":"Gutierrez Osorio Javier",
    "wof:placetype":"venue"
},
  "geometry": {"coordinates":[-4.4200186729,36.7196464539],"type":"Point"}
}