{
  "type": "Feature",
  "properties": {
    "iso:country":"ES",
    "sg:address":"Calle de Bentejuy, S/n",
    "sg:city":"Solana Matorral",
    "sg:orig_category":"Agencias De Viajes",
    "sg:phone":"+34 928 54 17 68",
    "sg:postcode":"35625",
    "sg:province":"Las Palmas",
    "wof:name":"Tui Espa\u00f1a Turismo S.a.",
    "wof:placetype":"venue"
},
  "geometry": {"coordinates":[-14.3438739777,28.0489196777],"type":"Point"}
}