{
  "type": "Feature",
  "properties": {
    "iso:country":"ES",
    "sg:address":"Carretera Tamariu, 26",
    "sg:city":"Palafrugell",
    "sg:orig_category":"Organizaciones Profesionales",
    "sg:phone":"+34 972 30 09 91",
    "sg:postcode":"17200",
    "sg:province":"Girona",
    "wof:name":"Pol Girbal Jaime",
    "wof:placetype":"venue"
},
  "geometry": {"coordinates":[3.1747500896,41.9144058228],"type":"Point"}
}