{
  "type": "Feature",
  "properties": {
    "addr:full":"Ctra. Liria-tabernes De Valldigna, S/n Chiva Valencia 46370",
    "addr:housenumber":"s / n",
    "addr:postcode":"46370",
    "addr:street":"Ctra. Liria-Tabernes De Valldigna",
    "iso:country":"ES",
    "sg:address":"Ctra. Liria-tabernes De Valldigna, S/n",
    "sg:city":"Chiva",
    "sg:orig_category":"Discotecas Y Salas De Baile",
    "sg:phone":"+34 962 52 11 61",
    "sg:postcode":"46370",
    "sg:province":"Valencia",
    "wof:name":"Chiva Expasion S.l.",
    "wof:placetype":"venue"
},
  "geometry": {"coordinates":[-0.7179690003,39.4728012085],"type":"Point"}
}