{
  "type": "Feature",
  "properties": {
    "iso:country":"ES",
    "sg:address":"Calle de General Ricardos, 95",
    "sg:city":"Madrid",
    "sg:orig_category":"Centros De Coordinaci\u00d3n",
    "sg:phone":"+34 914 72 02 50",
    "sg:postcode":"28019",
    "sg:province":"Madrid",
    "wof:name":"Garcia Carrasco Maria Cristina",
    "wof:placetype":"venue"
},
  "geometry": {"coordinates":[-3.724108696,40.3930397034],"type":"Point"}
}