{
  "type": "Feature",
  "properties": {
    "iso:country":"ES",
    "sg:address":"Calle de Jara, S/n",
    "sg:city":"Cartagena",
    "sg:orig_category":"Comunidades Religiosas",
    "sg:phone":"+34 968 50 20 38",
    "sg:postcode":"30201",
    "sg:province":"Murcia",
    "wof:name":"Cofradia Nuestro Padre Jesus Nazareno",
    "wof:placetype":"venue"
},
  "geometry": {"coordinates":[-0.9861189723,37.6016311646],"type":"Point"}
}