{
  "type": "Feature",
  "properties": {
    "addr:full":"Carrer de Pau Claris, 115 Barcelona Barcelona 08009",
    "addr:housenumber":"115",
    "addr:postcode":"08009",
    "addr:street":"Carrer De Pau Claris",
    "iso:country":"ES",
    "sg:address":"Carrer de Pau Claris, 115",
    "sg:city":"Barcelona",
    "sg:orig_category":"Abogados",
    "sg:phone":"+34 934 87 97 34",
    "sg:postcode":"08009",
    "sg:province":"Barcelona",
    "wof:name":"Ruiz Rodriguez Joaquin",
    "wof:placetype":"venue"
},
  "geometry": {"coordinates":[2.1680989265,41.3918685913],"type":"Point"}
}