{
  "type": "Feature",
  "properties": {
    "iso:country":"ES",
    "sg:address":"Calle de Casablanca, 26",
    "sg:city":"Torremolinos",
    "sg:orig_category":"Muebles Y Accesorios Para Cocinas Y Cuartos De Ba\u00d1o (al Por Menor)",
    "sg:phone":"+34 952 37 15 51",
    "sg:postcode":"29620",
    "sg:province":"M\u00e1laga",
    "wof:name":"Comobil S.l.",
    "wof:placetype":"venue"
},
  "geometry": {"coordinates":[-4.4991979599,36.6198997498],"type":"Point"}
}