{
  "type": "Feature",
  "properties": {
    "iso:country":"ES",
    "sg:address":"Calle de Feria, 21",
    "sg:city":"Bonillo",
    "sg:orig_category":"Ambulancias",
    "sg:phone":"+34 967 37 11 70",
    "sg:postcode":"02610",
    "sg:province":"Albacete",
    "wof:name":"Ambulancias Ortiz S.l.",
    "wof:placetype":"venue"
},
  "geometry": {"coordinates":[-2.5415697098,38.9492988586],"type":"Point"}
}