{
  "type": "Feature",
  "properties": {
    "addr:full":"Calle de Justo Sancho Mi\u00d1ano, 5 Melilla Melilla 52004",
    "addr:housenumber":"5",
    "addr:postcode":"52004",
    "addr:street":"Calle De Justo Sancho Min\u0303Ano",
    "iso:country":"ES",
    "sg:address":"Calle de Justo Sancho Mi\u00d1ano, 5",
    "sg:city":"Melilla",
    "sg:orig_category":"M\u00c9dicos: Estomatolog\u00cda",
    "sg:phone":"+34 952 68 15 45",
    "sg:postcode":"52004",
    "sg:province":"Melilla",
    "wof:name":"Fernandez Roman Diego",
    "wof:placetype":"venue"
},
  "geometry": {"coordinates":[-2.9414598942,35.2887496948],"type":"Point"}
}