{
  "type": "Feature",
  "properties": {
    "iso:country":"ES",
    "sg:address":"Ctra. Masarac, Km. 0000,4",
    "sg:city":"S. Climent Sescebes",
    "sg:orig_category":"Minerales (al Por Mayor)",
    "sg:phone":"+34 972 54 50 77",
    "sg:postcode":"17751",
    "sg:province":"Girona",
    "wof:name":"Minerals Emporda S.a.",
    "wof:placetype":"venue"
},
  "geometry": {"coordinates":[2.973058939,42.3635139465],"type":"Point"}
}