{
  "type": "Feature",
  "properties": {
    "addr:full":"Calle de Senda De Los Huertos, 11 Jaen Ja\u00e9n 23002",
    "addr:housenumber":"11;jae\u0301n",
    "addr:postcode":"23002",
    "addr:street":"Calle De Senda De Los Huertos",
    "iso:country":"ES",
    "sg:address":"Calle de Senda De Los Huertos, 11",
    "sg:city":"Jaen",
    "sg:orig_category":"Peluqueros: De Se\u00d1oras",
    "sg:phone":"+34 953 23 55 26",
    "sg:postcode":"23002",
    "sg:province":"Ja\u00e9n",
    "wof:name":"Juana Maria Cobo Villar Y Concepcion Gordo Cruz Cdad.",
    "wof:placetype":"venue"
},
  "geometry": {"coordinates":[-3.791613102,37.7623291016],"type":"Point"}
}