{
  "type": "Feature",
  "properties": {
    "iso:country":"ES",
    "sg:address":"Calle de Mercurio, 13",
    "sg:city":"Arganda",
    "sg:orig_category":"Fabricaci\u00d3n De Muebles De Cocina",
    "sg:phone":"+34 918 70 40 81",
    "sg:postcode":"28500",
    "sg:province":"Madrid",
    "wof:name":"Cayuela Moreno Juan Jose",
    "wof:placetype":"venue"
},
  "geometry": {"coordinates":[-3.4666090012,40.299407959],"type":"Point"}
}