{
  "type": "Feature",
  "properties": {
    "iso:country":"ES",
    "sg:address":"Pl. Sta. Maria, 2",
    "sg:city":"Fuentesauco",
    "sg:orig_category":"Molduras, Junquillos, Listones Y Molduras Perforadas",
    "sg:phone":"+34 980 60 03 22",
    "sg:postcode":"49400",
    "sg:province":"Zamora",
    "wof:name":"Gomez Rodriguez Jaime",
    "wof:placetype":"venue"
},
  "geometry": {"coordinates":[-5.4962911606,41.2309646606],"type":"Point"}
}