{
  "type": "Feature",
  "properties": {
    "iso:country":"ES",
    "sg:address":"Carrer de Cami De Can Comelles, 4",
    "sg:city":"Esparreguera",
    "sg:orig_category":"Peluquer\u00cdas, Peluquer\u00cda Mixta",
    "sg:phone":"+34 937 77 40 78",
    "sg:postcode":"08292",
    "sg:province":"Barcelona",
    "wof:name":"Serra Prat Marta",
    "wof:placetype":"venue"
},
  "geometry": {"coordinates":[1.8127340078,41.5431747437],"type":"Point"}
}