{
  "type": "Feature",
  "properties": {
    "addr:full":"Carrer de Teodora Lamadrid, 29 Barcelona Barcelona 08022",
    "addr:housenumber":"29",
    "addr:postcode":"08022",
    "addr:street":"Carrer De Teodora Lamadrid",
    "iso:country":"ES",
    "sg:address":"Carrer de Teodora Lamadrid, 29",
    "sg:city":"Barcelona",
    "sg:orig_category":"Arquitectos",
    "sg:phone":"+34 934 18 27 61",
    "sg:postcode":"08022",
    "sg:province":"Barcelona",
    "wof:name":"Siensopte S.l.",
    "wof:placetype":"venue"
},
  "geometry": {"coordinates":[2.1365559101,41.4067115784],"type":"Point"}
}