{
  "type": "Feature",
  "properties": {
    "iso:country":"ES",
    "sg:address":"Plaz Espa\u00d1a (de), 4",
    "sg:city":"Vejer De La Frontera",
    "sg:orig_category":"Carnicer\u00cdas, Carnicer\u00cdas",
    "sg:phone":"+34 956 44 72 81",
    "sg:postcode":"11150",
    "sg:province":"C\u00e1diz",
    "wof:name":"Reina Perez Antonio",
    "wof:placetype":"venue"
},
  "geometry": {"coordinates":[-5.9644298553,36.2545776367],"type":"Point"}
}