{
  "type": "Feature",
  "properties": {
    "iso:country":"ES",
    "sg:address":"Calle de Patricio Redondo, 2",
    "sg:city":"Daimiel",
    "sg:orig_category":"Plomeros",
    "sg:phone":"+34 926 85 48 27",
    "sg:postcode":"13250",
    "sg:province":"Ciudad Real",
    "wof:name":"Trujillo Clemente Jose Maria",
    "wof:placetype":"venue"
},
  "geometry": {"coordinates":[-3.6058659554,39.0733032227],"type":"Point"}
}