{
  "type": "Feature",
  "properties": {
    "iso:country":"ES",
    "sg:address":"Calle de Rua Mayor, 34",
    "sg:city":"Salamanca",
    "sg:orig_category":"Art\u00cdculos De Regalo (al Por Menor)",
    "sg:phone":"+34 923 27 20 34",
    "sg:postcode":"37008",
    "sg:province":"Salamanca",
    "wof:name":"Hernandez Garcia Arturo",
    "wof:placetype":"venue"
},
  "geometry": {"coordinates":[-5.6659011841,40.9624214172],"type":"Point"}
}