{
  "type": "Feature",
  "properties": {
    "addr:full":"Avda Reyes Catolicos, 75 Villarrobledo Albacete 02600",
    "addr:housenumber":"75",
    "addr:postcode":"02600",
    "addr:street":"Avda Reyes Catolicos",
    "iso:country":"ES",
    "sg:address":"Avda Reyes Catolicos, 75",
    "sg:city":"Villarrobledo",
    "sg:orig_category":"Florister\u00cdas",
    "sg:phone":"+34 967 14 54 51",
    "sg:postcode":"02600",
    "sg:province":"Albacete",
    "wof:name":"Moyano Melero Antonino",
    "wof:placetype":"venue"
},
  "geometry": {"coordinates":[-2.5973229408,39.2661170959],"type":"Point"}
}