{
  "type": "Feature",
  "properties": {
    "iso:country":"ES",
    "sg:address":"Avda Rafael Cabrera, 9",
    "sg:city":"Palmas De Gran Canaria",
    "sg:orig_category":"Peluqueros: De Se\u00d1oras",
    "sg:phone":"+34 928 37 37 82",
    "sg:postcode":"35002",
    "sg:province":"Las Palmas",
    "wof:name":"Concepcion Diaz Miguel Angel",
    "wof:placetype":"venue"
},
  "geometry": {"coordinates":[-15.4150362015,28.1062736511],"type":"Point"}
}