{
  "type": "Feature",
  "properties": {
    "addr:full":"Calle de Sotillo, 16 Madrid Madrid 28043",
    "addr:housenumber":"16",
    "addr:postcode":"madrid;28043",
    "addr:street":"Calle De Sotillo",
    "iso:country":"ES",
    "sg:address":"Calle de Sotillo, 16",
    "sg:city":"Madrid",
    "sg:orig_category":"Inmobiliaria (agencias)",
    "sg:phone":"+34 913 88 79 88",
    "sg:postcode":"28043",
    "sg:province":"Madrid",
    "wof:name":"Ruiz Herrero S.a.",
    "wof:placetype":"venue"
},
  "geometry": {"coordinates":[-3.6369578838,40.457195282],"type":"Point"}
}