{
  "type": "Feature",
  "properties": {
    "iso:country":"ES",
    "sg:address":"Calle de Infantas (de Las), 55",
    "sg:city":"Aranjuez",
    "sg:orig_category":"Asociaciones, Organismos Culturales Y Socioeducativos",
    "sg:phone":"+34 918 92 46 56",
    "sg:postcode":"28300",
    "sg:province":"Madrid",
    "sg:website":"www.aracove.com",
    "wof:name":"Aracove",
    "wof:placetype":"venue"
},
  "geometry": {"coordinates":[-3.5998556614,40.0346984863],"type":"Point"}
}