{
  "type": "Feature",
  "properties": {
    "addr:full":"Ctra Vizcaina, 26 Gijon Asturias 33207",
    "addr:housenumber":"26",
    "addr:postcode":"33207",
    "addr:street":"Ctra Vizcaina",
    "iso:country":"ES",
    "sg:address":"Ctra Vizcaina, 26",
    "sg:city":"Gijon",
    "sg:orig_category":"Librer\u00cdas",
    "sg:phone":"+34 985 35 53 27",
    "sg:postcode":"33207",
    "sg:province":"Asturias",
    "wof:name":"Vazquez Fernandez Carmen",
    "wof:placetype":"venue"
},
  "geometry": {"coordinates":[-5.67085886,43.5393218994],"type":"Point"}
}