{
  "type": "Feature",
  "properties": {
    "iso:country":"ES",
    "sg:address":"Ctra Seu D'urgell(la), 37",
    "sg:city":"Ponts",
    "sg:orig_category":"Restaurantes",
    "sg:phone":"+34 973 46 00 02",
    "sg:postcode":"25740",
    "sg:province":"Lleida",
    "wof:name":"Ponts Paradis S.l.",
    "wof:placetype":"venue"
},
  "geometry": {"coordinates":[1.1862809658,41.917224884],"type":"Point"}
}