{
  "type": "Feature",
  "properties": {
    "iso:country":"ES",
    "sg:address":"Carrer de Calderon De La Barca, 111",
    "sg:city":"Barcelona",
    "sg:orig_category":"Relojer\u00cda (al Por Menor, Reparaci\u00d3n)",
    "sg:phone":"+34 933 57 51 63",
    "sg:postcode":"08032",
    "sg:province":"Barcelona",
    "wof:name":"Casals Bernal Enrique",
    "wof:placetype":"venue"
},
  "geometry": {"coordinates":[2.1573319435,41.419757843],"type":"Point"}
}