{
  "type": "Feature",
  "properties": {
    "addr:full":"Calle de San Juan Bosco, 93 Malaga M\u00e1laga 29014",
    "addr:housenumber":"93",
    "addr:postcode":"29014",
    "addr:street":"Calle De San Juan Bosco;Ma\u0301Laga",
    "iso:country":"ES",
    "sg:address":"Calle de San Juan Bosco, 93",
    "sg:city":"Malaga",
    "sg:orig_category":"Cristaler\u00cdas",
    "sg:phone":"+34 952 25 77 72",
    "sg:postcode":"29014",
    "sg:province":"M\u00e1laga",
    "wof:name":"Sanchez Gutierrez Maria",
    "wof:placetype":"venue"
},
  "geometry": {"coordinates":[-4.4228858948,36.7367744446],"type":"Point"}
}