{
  "type": "Feature",
  "properties": {
    "iso:country":"ES",
    "sg:address":"Carrer de Avellaners, 6",
    "sg:city":"S. Just Desvern",
    "sg:orig_category":"Inmobiliaria (agencias)",
    "sg:phone":"+34 933 72 76 71",
    "sg:postcode":"08960",
    "sg:province":"Barcelona",
    "wof:name":"Peraimi Sl",
    "wof:placetype":"venue"
},
  "geometry": {"coordinates":[2.0762789249,41.3936691284],"type":"Point"}
}