{
  "type": "Feature",
  "properties": {
    "addr:full":"Avda Nacional, 21 Arenal Islas Baleares 07600",
    "addr:postcode":"07600",
    "addr:street":"Avda Nacional 21 Arenal Islas",
    "iso:country":"ES",
    "sg:address":"Avda Nacional, 21",
    "sg:city":"Arenal",
    "sg:orig_category":"Expertos Contables",
    "sg:phone":"+34 971 49 04 02",
    "sg:postcode":"07600",
    "sg:province":"Islas Baleares",
    "wof:name":"Pericas Marti Juan",
    "wof:placetype":"venue"
},
  "geometry": {"coordinates":[2.752327919,39.5086097717],"type":"Point"}
}