{
  "type": "Feature",
  "properties": {
    "addr:full":"Calle de Diego De Leon, 51 Madrid Madrid 28006",
    "addr:housenumber":"51",
    "addr:postcode":"madrid;28006",
    "addr:street":"Calle De Diego De Leon",
    "iso:country":"ES",
    "sg:address":"Calle de Diego De Leon, 51",
    "sg:city":"Madrid",
    "sg:orig_category":"Psic\u00d3logos",
    "sg:phone":"+34 914 11 50 29",
    "sg:postcode":"28006",
    "sg:province":"Madrid",
    "wof:name":"Langelaan Alvarez Carlos",
    "wof:placetype":"venue"
},
  "geometry": {"coordinates":[-3.6779053211,40.4346923828],"type":"Point"}
}