{
  "type": "Feature",
  "properties": {
    "iso:country":"ES",
    "sg:address":"Calle de Alberola, 39",
    "sg:city":"Alacant",
    "sg:orig_category":"Suministros Para Hoteles",
    "sg:phone":"+34 965 13 03 11",
    "sg:postcode":"03007",
    "sg:province":"Alicante",
    "wof:name":"Almacenes Bodi S.l.",
    "wof:placetype":"venue"
},
  "geometry": {"coordinates":[-0.4991073012,38.3407325745],"type":"Point"}
}