{
  "type": "Feature",
  "properties": {
    "addr:full":"Calle de Veteranos, 2 Navalmoral Mata C\u00e1ceres 10300",
    "addr:housenumber":"2",
    "addr:postcode":"10300",
    "addr:street":"Calle De Veteranos;Ca\u0301Ceres",
    "iso:country":"ES",
    "sg:address":"Calle de Veteranos, 2",
    "sg:city":"Navalmoral Mata",
    "sg:orig_category":"M\u00c9dicos: Cirug\u00cda Pl\u00c1stica, Reconstructiva Y Est\u00c9tica",
    "sg:phone":"+34 927 53 38 53",
    "sg:postcode":"10300",
    "sg:province":"C\u00e1ceres",
    "wof:name":"Aragon Rodriguez Cristina",
    "wof:placetype":"venue"
},
  "geometry": {"coordinates":[-5.5338916779,39.8904380798],"type":"Point"}
}