{
  "type": "Feature",
  "properties": {
    "iso:country":"ES",
    "sg:address":"Calle de San Agustin, 32",
    "sg:city":"Icod De Los Vinos",
    "sg:orig_category":"Inform\u00c1tica, Ofim\u00c1tica (estudios, Asesor\u00cda, Ingenier\u00cda, Formaci\u00d3n)",
    "sg:phone":"+34 922 81 33 10",
    "sg:postcode":"38430",
    "sg:province":"Santa Cruz De Tenerife",
    "sg:website":"www.magnacomputer.net",
    "wof:name":"Magnacomputer S.l.",
    "wof:placetype":"venue"
},
  "geometry": {"coordinates":[-16.7171802521,28.3674964905],"type":"Point"}
}