{
  "type": "Feature",
  "properties": {
    "iso:country":"ES",
    "sg:address":"Calle de Antonio De Nebrija, 12",
    "sg:city":"Torremolinos",
    "sg:orig_category":"Mec\u00c1nico Del Autom\u00d3vil",
    "sg:phone":"+34 952 37 81 40",
    "sg:postcode":"29620",
    "sg:province":"M\u00e1laga",
    "wof:name":"Sesenta Segundos Mecanica Rapida S.l.",
    "wof:placetype":"venue"
},
  "geometry": {"coordinates":[-4.5171427727,36.6118011475],"type":"Point"}
}