{
  "type": "Feature",
  "properties": {
    "addr:full":"Calle de Espiritu Santo, 16 Moron Frontera Sevilla 41530",
    "addr:housenumber":"16",
    "addr:postcode":"41530",
    "addr:street":"Calle De Espiritu Santo",
    "iso:country":"ES",
    "sg:address":"Calle de Espiritu Santo, 16",
    "sg:city":"Moron Frontera",
    "sg:orig_category":"Peluqueros: De Se\u00d1oras",
    "sg:phone":"+34 955 85 21 87",
    "sg:postcode":"41530",
    "sg:province":"Sevilla",
    "wof:name":"Trujillo Gamero Avelina",
    "wof:placetype":"venue"
},
  "geometry": {"coordinates":[-5.4580488205,37.1192207336],"type":"Point"}
}