{
  "type": "Feature",
  "properties": {
    "iso:country":"ES",
    "sg:address":"Calle de Zubigane, 6",
    "sg:city":"Moreaga",
    "sg:orig_category":"Cl\u00cdnicas Dentales",
    "sg:phone":"+34 946 76 50 85",
    "sg:postcode":"48600",
    "sg:province":"Vizcaya",
    "wof:name":"Clinica Dental Sopelana S.l.",
    "wof:placetype":"venue"
},
  "geometry": {"coordinates":[-2.9804329872,43.3798370361],"type":"Point"}
}