{
  "type": "Feature",
  "properties": {
    "addr:full":"Av. Cruz, 7 Museros Valencia 46136",
    "addr:housenumber":"7",
    "addr:postcode":"46136",
    "addr:street":"Av. Cruz",
    "iso:country":"ES",
    "sg:address":"Av. Cruz, 7",
    "sg:city":"Museros",
    "sg:orig_category":"Electrodom\u00c9sticos (al Por Menor)",
    "sg:phone":"+34 961 45 24 43",
    "sg:postcode":"46136",
    "sg:province":"Valencia",
    "wof:name":"Tele Dia S.l.",
    "wof:placetype":"venue"
},
  "geometry": {"coordinates":[-0.3387590051,39.5613594055],"type":"Point"}
}