{
  "type": "Feature",
  "properties": {
    "iso:country":"ES",
    "sg:address":"Plaz Colon (de), 21",
    "sg:city":"Cordoba",
    "sg:orig_category":"M\u00c9dicos: Oftalmolog\u00cda",
    "sg:phone":"+34 957 47 01 89",
    "sg:postcode":"14001",
    "sg:province":"C\u00f3rdoba",
    "wof:name":"Barrera Vidal Valentin",
    "wof:placetype":"venue"
},
  "geometry": {"coordinates":[-4.7782101631,37.8911323547],"type":"Point"}
}