{
  "type": "Feature",
  "properties": {
    "iso:country":"ES",
    "sg:address":"Pritanda, 12",
    "sg:city":"Coladilla",
    "sg:orig_category":"Charcuter\u00cdas (al Por Mayor)",
    "sg:phone":"+34 987 57 83 00",
    "sg:postcode":"24836",
    "sg:province":"Le\u00f3n",
    "wof:name":"Prieto Gabela Miguel Angel",
    "wof:placetype":"venue"
},
  "geometry": {"coordinates":[-5.5589709282,42.8833580017],"type":"Point"}
}