{
  "type": "Feature",
  "properties": {
    "addr:full":"Calle de Rosario, 10 Gijon Asturias 33201",
    "addr:housenumber":"10",
    "addr:postcode":"33201",
    "addr:street":"Calle De Rosario",
    "iso:country":"ES",
    "sg:address":"Calle de Rosario, 10",
    "sg:city":"Gijon",
    "sg:orig_category":"Estancos",
    "sg:phone":"+34 985 34 01 26",
    "sg:postcode":"33201",
    "sg:province":"Asturias",
    "wof:name":"Cancer Lalanne Maria Teresa",
    "wof:placetype":"venue"
},
  "geometry": {"coordinates":[-5.6632399559,43.5461349487],"type":"Point"}
}