{
  "type": "Feature",
  "properties": {
    "addr:full":"Calle de Anton Calabres, 5 Granada Granada 18011",
    "addr:housenumber":"5",
    "addr:postcode":"18011",
    "addr:street":"Calle De Anton Calabres",
    "iso:country":"ES",
    "sg:address":"Calle de Anton Calabres, 5",
    "sg:city":"Granada",
    "sg:orig_category":"Droguer\u00cdas (al Por Menor)",
    "sg:phone":"+34 958 15 48 97",
    "sg:postcode":"18011",
    "sg:province":"Granada",
    "wof:name":"Quesada Carrillo Jose",
    "wof:placetype":"venue"
},
  "geometry": {"coordinates":[-3.6052174568,37.2058334351],"type":"Point"}
}