{
  "type": "Feature",
  "properties": {
    "addr:full":"Calle de Antonio Pedrosa, 50 San Clodio Lugo 27310",
    "addr:housenumber":"50",
    "addr:postcode":"27310",
    "addr:street":"Calle De Antonio Pedrosa",
    "iso:country":"ES",
    "sg:address":"Calle de Antonio Pedrosa, 50",
    "sg:city":"San Clodio",
    "sg:orig_category":"Empresas De Desmonte",
    "sg:phone":"+34 982 43 50 44",
    "sg:postcode":"27310",
    "sg:province":"Lugo",
    "wof:name":"Excuban S.l.",
    "wof:placetype":"venue"
},
  "geometry": {"coordinates":[-7.2897443771,42.4667472839],"type":"Point"}
}