{
  "type": "Feature",
  "properties": {
    "iso:country":"ES",
    "sg:address":"Avda America, 5",
    "sg:city":"Zaragoza",
    "sg:orig_category":"Estilistas Y Estudios De Estilo De Corte Y Confecci\u00d3n",
    "sg:phone":"+34 976 37 89 68",
    "sg:postcode":"50007",
    "sg:province":"Zaragoza",
    "wof:name":"Fashion Senior S.l.",
    "wof:placetype":"venue"
},
  "geometry": {"coordinates":[-0.8850809932,41.6320838928],"type":"Point"}
}