{
  "type": "Feature",
  "properties": {
    "addr:full":"Carrer de Calabria, 17 Barcelona Barcelona 08015",
    "addr:housenumber":"17",
    "addr:postcode":"08015",
    "addr:street":"Carrer De Calabria",
    "iso:country":"ES",
    "sg:address":"Carrer de Calabria, 17",
    "sg:city":"Barcelona",
    "sg:orig_category":"Madera Para Construcci\u00d3n E Industria",
    "sg:phone":"+34 933 25 20 81",
    "sg:postcode":"08015",
    "sg:province":"Barcelona",
    "wof:name":"Lahuerta Jarque Paulino",
    "wof:placetype":"venue"
},
  "geometry": {"coordinates":[2.1598238945,41.3758926392],"type":"Point"}
}