{
  "type": "Feature",
  "properties": {
    "addr:full":"Carrer de Duc Estremera, S/n Palmanova Islas Baleares 07181",
    "addr:housenumber":"s / n",
    "addr:postcode":"07181",
    "addr:street":"Carrer De Duc Estremera",
    "iso:country":"ES",
    "sg:address":"Carrer de Duc Estremera, S/n",
    "sg:city":"Palmanova",
    "sg:orig_category":"Art\u00cdculos De Regalo (al Por Menor)",
    "sg:phone":"+34 971 68 03 93",
    "sg:postcode":"07181",
    "sg:province":"Islas Baleares",
    "wof:name":"Rossello Canaves Antonio",
    "wof:placetype":"venue"
},
  "geometry": {"coordinates":[2.5365440845,39.5168495178],"type":"Point"}
}