{
  "type": "Feature",
  "properties": {
    "iso:country":"ES",
    "sg:address":"Pase Arco De Ladrillo, 57",
    "sg:city":"Valladolid",
    "sg:orig_category":"Mec\u00c1nico Del Autom\u00d3vil",
    "sg:phone":"+34 983 47 93 98",
    "sg:postcode":"47013",
    "sg:province":"Valladolid",
    "wof:name":"Hermanos Gomez Del Hierro S. A.",
    "wof:placetype":"venue"
},
  "geometry": {"coordinates":[-4.7277641296,41.6307868958],"type":"Point"}
}