{
  "type": "Feature",
  "properties": {
    "iso:country":"ES",
    "sg:address":"Calle de Muelle, 21",
    "sg:city":"Santa Pola",
    "sg:orig_category":"Confecci\u00d3n De Trajes De Ba\u00d1o Y De Ropa De Playa",
    "sg:phone":"+34 965 41 67 96",
    "sg:postcode":"03130",
    "sg:province":"Alicante",
    "wof:name":"Hernandez Hernandez Francisco",
    "wof:placetype":"venue"
},
  "geometry": {"coordinates":[-0.5558450222,38.1909980774],"type":"Point"}
}