{
  "type": "Feature",
  "properties": {
    "addr:full":"Calle de Menendez Pelayo, S/n Colindres Cantabria 39750",
    "addr:housenumber":"s / n",
    "addr:postcode":"39750",
    "addr:street":"Calle De Menendez Pelayo",
    "iso:country":"ES",
    "sg:address":"Calle de Menendez Pelayo, S/n",
    "sg:city":"Colindres",
    "sg:orig_category":"Promotores Constructores",
    "sg:phone":"+34 942 65 15 60",
    "sg:postcode":"39750",
    "sg:province":"Cantabria",
    "wof:name":"Viviendas Y Promociones Bolemar S.l.",
    "wof:placetype":"venue"
},
  "geometry": {"coordinates":[-3.4482591152,43.3986701965],"type":"Point"}
}