{
  "type": "Feature",
  "properties": {
    "iso:country":"ES",
    "sg:address":"Avda Coimbra (de), 6",
    "sg:city":"Santiago De Compostela",
    "sg:orig_category":"Comunidades Religiosas",
    "sg:phone":"+34 981 56 80 80",
    "sg:postcode":"15704",
    "sg:province":"La Coru\u00f1a",
    "wof:name":"Prelatura Opus Dei Delegacion De Santiago",
    "wof:placetype":"venue"
},
  "geometry": {"coordinates":[-8.5416383743,42.8857536316],"type":"Point"}
}