{
  "type": "Feature",
  "properties": {
    "addr:full":"Calle de Cabrera, S/n Barriada Virgen De La Caridad Murcia 30203",
    "addr:housenumber":"s",
    "addr:postcode":"30203",
    "addr:street":"Calle De Cabrera;/ N Barriada Virgen De",
    "iso:country":"ES",
    "sg:address":"Calle de Cabrera, S/n",
    "sg:city":"Barriada Virgen De La Caridad",
    "sg:orig_category":"Muebles, Minoristas",
    "sg:phone":"+34 968 50 48 20",
    "sg:postcode":"30203",
    "sg:province":"Murcia",
    "wof:name":"Blaya Gallego Miguel",
    "wof:placetype":"venue"
},
  "geometry": {"coordinates":[-0.9786090255,37.6140403748],"type":"Point"}
}