{
  "type": "Feature",
  "properties": {
    "addr:full":"Vena Vilamorell, 11 Vilamorell Girona 17770",
    "addr:housenumber":"11",
    "addr:postcode":"17770",
    "addr:street":"Vilamorell",
    "iso:country":"ES",
    "sg:address":"Vena Vilamorell, 11",
    "sg:city":"Vilamorell",
    "sg:orig_category":"Producci\u00d3n, Venta De Productos De Agricultura Biol\u00d3gica",
    "sg:phone":"+34 972 52 54 99",
    "sg:postcode":"17770",
    "sg:province":"Girona",
    "wof:name":"Agricola Llado S.c.",
    "wof:placetype":"venue"
},
  "geometry": {"coordinates":[2.9325785637,42.2136726379],"type":"Point"}
}