{
  "type": "Feature",
  "properties": {
    "addr:full":"Calle de Luis Bu\u00d1uel, 10 Madrid Madrid 28018",
    "addr:housenumber":"10",
    "addr:postcode":"madrid;28018",
    "addr:street":"Calle De Luis Bun\u0303Uel",
    "iso:country":"ES",
    "sg:address":"Calle de Luis Bu\u00d1uel, 10",
    "sg:city":"Madrid",
    "sg:orig_category":"Droguer\u00cdas (al Por Menor)",
    "sg:phone":"+34 913 03 95 71",
    "sg:postcode":"28018",
    "sg:province":"Madrid",
    "wof:name":"Molinero Majo Juan",
    "wof:placetype":"venue"
},
  "geometry": {"coordinates":[-3.643889904,40.3870811462],"type":"Point"}
}