{
  "type": "Feature",
  "properties": {
    "iso:country":"ES",
    "sg:address":"Carrer de Mas De L'abello, 16",
    "sg:city":"Reus",
    "sg:orig_category":"Cajas De Ahorro",
    "sg:phone":"+34 977 75 32 83",
    "sg:postcode":"43204",
    "sg:province":"Tarragona",
    "sg:website":"www.lacaixa.es",
    "wof:name":"Caixa D'estalvis I Pensions De Barcelona",
    "wof:placetype":"venue"
},
  "geometry": {"coordinates":[1.1208620071,41.1475334167],"type":"Point"}
}