{
  "type": "Feature",
  "properties": {
    "iso:country":"ES",
    "sg:address":"Av Jaume Balmes, 29",
    "sg:city":"Vilanova I La Geltru",
    "sg:orig_category":"Seguridad Social",
    "sg:phone":"+34 938 15 64 93",
    "sg:postcode":"08800",
    "sg:province":"Barcelona",
    "wof:name":"Fimac Mutua De Accidentes De Trabajo",
    "wof:placetype":"venue"
},
  "geometry": {"coordinates":[1.7228070498,41.2197494507],"type":"Point"}
}