{
  "type": "Feature",
  "properties": {
    "addr:full":"Avda Paseo De Almeria, 10 Almeria Almer\u00eda 04001",
    "addr:housenumber":"10",
    "addr:postcode":"04001",
    "addr:street":"Avda Paseo De Almeria",
    "iso:country":"ES",
    "sg:address":"Avda Paseo De Almeria, 10",
    "sg:city":"Almeria",
    "sg:orig_category":"Ropa Para Ni\u00d1os (al Por Menor)",
    "sg:phone":"+34 950 25 52 82",
    "sg:postcode":"04001",
    "sg:province":"Almer\u00eda",
    "wof:name":"El Desvan Del Bebe S.l.",
    "wof:placetype":"venue"
},
  "geometry": {"coordinates":[-2.4608390331,36.8422698975],"type":"Point"}
}