{
  "type": "Feature",
  "properties": {
    "iso:country":"ES",
    "sg:address":"Calle de Monzon, 28",
    "sg:city":"Majadahonda",
    "sg:orig_category":"Industria Qu\u00cdmica",
    "sg:phone":"+34 916 39 22 07",
    "sg:postcode":"28220",
    "sg:province":"Madrid",
    "wof:name":"Lamana Marin Antonio Jose",
    "wof:placetype":"venue"
},
  "geometry": {"coordinates":[-3.8508350849,40.4765434265],"type":"Point"}
}