{
  "type": "Feature",
  "properties": {
    "iso:country":"ES",
    "sg:address":"Calle de Senda Galiana (de La), 8",
    "sg:city":"Coslada",
    "sg:orig_category":"Agencias De Aduana",
    "sg:phone":"+34 916 73 28 74",
    "sg:postcode":"28820",
    "sg:province":"Madrid",
    "wof:name":"Ucotrans Union Comercial Transitaria S.l.",
    "wof:placetype":"venue"
},
  "geometry": {"coordinates":[-3.536803484,40.4431991577],"type":"Point"}
}