{
  "type": "Feature",
  "properties": {
    "addr:full":"Poli Industrial, S/n Aguilar Campoo Palencia 34800",
    "addr:housenumber":"/ n",
    "addr:postcode":"34800",
    "addr:street":"Industrial",
    "iso:country":"ES",
    "sg:address":"Poli Industrial, S/n",
    "sg:city":"Aguilar Campoo",
    "sg:orig_category":"Mec\u00c1nico Del Autom\u00d3vil",
    "sg:phone":"+34 979 12 25 20",
    "sg:postcode":"34800",
    "sg:province":"Palencia",
    "wof:name":"Minguez Torre S.a.",
    "wof:placetype":"venue"
},
  "geometry": {"coordinates":[-4.250898838,42.7816390991],"type":"Point"}
}