{
  "type": "Feature",
  "properties": {
    "iso:country":"ES",
    "sg:address":"Urb. Las Brisas, 234",
    "sg:city":"Brisas",
    "sg:orig_category":"Centros Empresariales",
    "sg:phone":"+34 949 35 06 22",
    "sg:postcode":"19128",
    "sg:province":"Guadalajara",
    "wof:name":"Whitehead  Jane Sheridan",
    "wof:placetype":"venue"
},
  "geometry": {"coordinates":[-3.1664927006,40.6298179626],"type":"Point"}
}