{
  "type": "Feature",
  "properties": {
    "iso:country":"ES",
    "sg:address":"Ctra Nacional 620, Km. 0005,5",
    "sg:city":"Calabazanos",
    "sg:orig_category":"Empresas De Hormig\u00d3n, Hormig\u00d3n Armado Y Pretensado",
    "sg:phone":"+34 979 77 76 07",
    "sg:postcode":"34190",
    "sg:province":"Palencia",
    "sg:website":"www.aridosantolin.es",
    "wof:name":"Aridos Antolin S.a.",
    "wof:placetype":"venue"
},
  "geometry": {"coordinates":[-4.5061578751,41.9569892883],"type":"Point"}
}