{
  "type": "Feature",
  "properties": {
    "addr:full":"Carr Blasco De Alagon, 5 Morella Castell\u00f3n 12300",
    "addr:housenumber":"5",
    "addr:postcode":"12300",
    "addr:street":"Carr Blasco De Alagon;Castello\u0301N",
    "iso:country":"ES",
    "sg:address":"Carr Blasco De Alagon, 5",
    "sg:city":"Morella",
    "sg:orig_category":"Perfumer\u00cda (al Por Menor)",
    "sg:phone":"+34 964 16 01 88",
    "sg:postcode":"12300",
    "sg:province":"Castell\u00f3n",
    "wof:name":"Gasulla Ferrer Maria Mercedes",
    "wof:placetype":"venue"
},
  "geometry": {"coordinates":[-0.1006919965,40.6183166504],"type":"Point"}
}