{
  "type": "Feature",
  "properties": {
    "iso:country":"ES",
    "sg:address":"Rua Ancha, 10",
    "sg:city":"Muros",
    "sg:orig_category":"Bazares, Art\u00cdculos De Limpieza Y De Cocina (al Por Menor)",
    "sg:phone":"+34 981 76 23 41",
    "sg:postcode":"15250",
    "sg:province":"A Coru\u00f1a",
    "wof:name":"Sendon Lago Maria Jose",
    "wof:placetype":"venue"
},
  "geometry": {"coordinates":[-9.0583667755,42.775352478],"type":"Point"}
}