{
  "type": "Feature",
  "properties": {
    "iso:country":"ES",
    "sg:address":"Calle de Mayor, 1",
    "sg:city":"Belgida",
    "sg:orig_category":"Insecticidas, Fumigaci\u00d3n",
    "sg:phone":"+34 962 90 14 67",
    "sg:postcode":"46868",
    "sg:province":"Valencia",
    "wof:name":"Jose Sevadilla Giner C.b.",
    "wof:placetype":"venue"
},
  "geometry": {"coordinates":[-0.4156725109,38.7828636169],"type":"Point"}
}