{
  "type": "Feature",
  "properties": {
    "iso:country":"ES",
    "sg:address":"Carrer de Sant Domingo, 1",
    "sg:city":"Palma",
    "sg:orig_category":"Inmobiliaria (agencias)",
    "sg:phone":"+34 971 71 58 11",
    "sg:postcode":"07001",
    "sg:province":"Islas Baleares",
    "sg:website":"www.trias-houses.com",
    "wof:name":"Trias Roig Antonio",
    "wof:placetype":"venue"
},
  "geometry": {"coordinates":[2.6494789124,39.5697402954],"type":"Point"}
}