{
  "type": "Feature",
  "properties": {
    "addr:full":"Ctra Ripollet, 6 Mas Rampinyo Barcelona 08110",
    "addr:housenumber":"6",
    "addr:postcode":"08110",
    "addr:street":"Ctra Ripollet",
    "iso:country":"ES",
    "sg:address":"Ctra Ripollet, 6",
    "sg:city":"Mas Rampinyo",
    "sg:orig_category":"Negocio De Materiales De Construcci\u00d3n",
    "sg:phone":"+34 935 72 40 40",
    "sg:postcode":"08110",
    "sg:province":"Barcelona",
    "wof:name":"Acabados De Obras Y Construcciones S.a.",
    "wof:placetype":"venue"
},
  "geometry": {"coordinates":[2.18124,41.493107],"type":"Point"}
}