{
  "type": "Feature",
  "properties": {
    "addr:full":"Calle de Santiago, 4 Villanueva Alcardete Toledo 45810",
    "addr:housenumber":"4",
    "addr:postcode":"45810",
    "addr:street":"Calle De Santiago",
    "iso:country":"ES",
    "sg:address":"Calle de Santiago, 4",
    "sg:city":"Villanueva Alcardete",
    "sg:orig_category":"Laboratorios Y Trabajos De Fotograf\u00cda, V\u00cddeo Y Cine",
    "sg:phone":"+34 925 16 62 94",
    "sg:postcode":"45810",
    "sg:province":"Toledo",
    "wof:name":"Quintanar Lopez Emilio",
    "wof:placetype":"venue"
},
  "geometry": {"coordinates":[-3.0139009953,39.6700401306],"type":"Point"}
}