{
  "type": "Feature",
  "properties": {
    "addr:full":"Calle de San Miguel, 16 Valencia De Don Juan Le\u00f3n 24200",
    "addr:housenumber":"16",
    "addr:postcode":"24200",
    "addr:street":"Calle De San Miguel",
    "iso:country":"ES",
    "sg:address":"Calle de San Miguel, 16",
    "sg:city":"Valencia De Don Juan",
    "sg:orig_category":"Organizaciones Internacionales",
    "sg:phone":"+34 987 75 08 06",
    "sg:postcode":"24200",
    "sg:province":"Le\u00f3n",
    "wof:name":"Cruz Roja Espa\u00f1ola",
    "wof:placetype":"venue"
},
  "geometry": {"coordinates":[-5.5160579681,42.2933578491],"type":"Point"}
}