{
  "type": "Feature",
  "properties": {
    "addr:full":"Carrer de Gonzalo Ortola, 16 Ondara Alicante 03760",
    "addr:housenumber":"16",
    "addr:postcode":"03760",
    "addr:street":"Carrer De Gonzalo Ortola",
    "iso:country":"ES",
    "sg:address":"Carrer de Gonzalo Ortola, 16",
    "sg:city":"Ondara",
    "sg:orig_category":"Distribuci\u00d3n De Petr\u00d3leo Y Derivados",
    "sg:phone":"+34 965 76 74 39",
    "sg:postcode":"03760",
    "sg:province":"Alicante",
    "wof:name":"Cidoncha Alimentacion S.l.",
    "wof:placetype":"venue"
},
  "geometry": {"coordinates":[0.0196889993,38.822429657],"type":"Point"}
}