{
  "type": "Feature",
  "properties": {
    "iso:country":"ES",
    "sg:address":"Carrer de Oliana, 11",
    "sg:city":"Barcelona",
    "sg:orig_category":"Locales Y Clases De Danza",
    "sg:phone":"+34 932 09 93 25",
    "sg:postcode":"08006",
    "sg:province":"Barcelona",
    "wof:name":"Padro Dalmau Jaime",
    "wof:placetype":"venue"
},
  "geometry": {"coordinates":[2.1474089622,41.398563385],"type":"Point"}
}