{
  "type": "Feature",
  "properties": {
    "addr:full":"Calle de Marques, 78 Buniel Burgos 09230",
    "addr:housenumber":"78",
    "addr:postcode":"09230",
    "addr:street":"Calle De Marques",
    "iso:country":"ES",
    "sg:address":"Calle de Marques, 78",
    "sg:city":"Buniel",
    "sg:orig_category":"Complementos De Vestir (al Por Menor)",
    "sg:phone":"+34 947 41 20 57",
    "sg:postcode":"09230",
    "sg:province":"Burgos",
    "sg:website":"www.abuscarregalos.com",
    "wof:name":"Fuentes Gomez Sergio",
    "wof:placetype":"venue"
},
  "geometry": {"coordinates":[-3.8240890503,42.311378479],"type":"Point"}
}