{
  "type": "Feature",
  "properties": {
    "addr:full":"Calle de Eras, 19 Yuncos Toledo 45210",
    "addr:housenumber":"19",
    "addr:postcode":"45210",
    "addr:street":"Calle De Eras",
    "iso:country":"ES",
    "sg:address":"Calle de Eras, 19",
    "sg:city":"Yuncos",
    "sg:classifiers":[
        {
            "category":"Autos & Motor Vehicles",
            "subcategory":"Automobile Sales",
            "type":"Retail Goods"
        }
    ],
    "sg:phone":"+34 925 55 38 80",
    "sg:postcode":"45210",
    "sg:province":"Toledo",
    "wof:name":"Gomez Perez Milagros",
    "wof:placetype":"venue"
},
  "geometry": {"coordinates":[-3.8755693436,40.0878181458],"type":"Point"}
}