{
  "type": "Feature",
  "properties": {
    "addr:full":"Calle de Calvo Sotelo, 93 Calatorao Zaragoza 50280",
    "addr:housenumber":"93",
    "addr:postcode":"50280",
    "addr:street":"Calle De Calvo Sotelo",
    "iso:country":"ES",
    "sg:address":"Calle de Calvo Sotelo, 93",
    "sg:city":"Calatorao",
    "sg:orig_category":"Prot\u00c9sicos Dentales",
    "sg:phone":"+34 976 60 78 77",
    "sg:postcode":"50280",
    "sg:province":"Zaragoza",
    "wof:name":"Escusol Cajo Jose Ramon",
    "wof:placetype":"venue"
},
  "geometry": {"coordinates":[-1.3464330435,41.5192108154],"type":"Point"}
}