{
  "type": "Feature",
  "properties": {
    "iso:country":"ES",
    "sg:address":"Poligono San Lazaro, S/n",
    "sg:city":"Sto. Domingo Calzada",
    "sg:orig_category":"Empresas De Carpinter\u00cda",
    "sg:phone":"+34 941 34 32 01",
    "sg:postcode":"26250",
    "sg:province":"La Rioja",
    "wof:name":"Aluminios Del Oja S.l",
    "wof:placetype":"venue"
},
  "geometry": {"coordinates":[-2.5396029949,42.2870750427],"type":"Point"}
}