{
  "type": "Feature",
  "properties": {
    "iso:country":"ES",
    "sg:address":"Calle de Tomas Echeverria, 16",
    "sg:city":"Malaga",
    "sg:orig_category":"Servicios Gsm",
    "sg:phone":"+34 952 31 58 39",
    "sg:postcode":"29002",
    "sg:province":"M\u00e1laga",
    "wof:name":"Nivel Futuro S.l",
    "wof:placetype":"venue"
},
  "geometry": {"coordinates":[-4.4341030121,36.7037086487],"type":"Point"}
}