{
  "type": "Feature",
  "properties": {
    "addr:full":"Ctra Tacoronte Tejina, Km. 0003,0 Tacoronte Santa Cruz De Tenerife 38350",
    "addr:postcode":"38350",
    "addr:street":"Ctra Tacoronte Tejina Km. 0003,0",
    "iso:country":"ES",
    "sg:address":"Ctra Tacoronte Tejina, Km. 0003,0",
    "sg:city":"Tacoronte",
    "sg:orig_category":"Agencias Y Agentes Comerciales, Representantes",
    "sg:phone":"+34 922 56 40 50",
    "sg:postcode":"38350",
    "sg:province":"Santa Cruz De Tenerife",
    "wof:name":"Bua Pirillo Raul",
    "wof:placetype":"venue"
},
  "geometry": {"coordinates":[-16.4152107239,28.4774570465],"type":"Point"}
}