{
  "type": "Feature",
  "properties": {
    "addr:full":"Calle de Poeta Mas Y Ros, 62 Valencia Valencia 46022",
    "addr:housenumber":"62",
    "addr:postcode":"46022",
    "addr:street":"Calle De Poeta Mas Y Ros",
    "iso:country":"ES",
    "sg:address":"Calle de Poeta Mas Y Ros, 62",
    "sg:city":"Valencia",
    "sg:orig_category":"Agencias Y Agentes Comerciales, Representantes",
    "sg:phone":"+34 963 71 46 23",
    "sg:postcode":"46022",
    "sg:province":"Valencia",
    "wof:name":"Morales Cruz Pedro",
    "wof:placetype":"venue"
},
  "geometry": {"coordinates":[-0.3459647894,39.4697303772],"type":"Point"}
}