{
  "type": "Feature",
  "properties": {
    "iso:country":"ES",
    "sg:address":"Carr Gran Bretanya, 32",
    "sg:city":"Igualada",
    "sg:orig_category":"Plomeros",
    "sg:phone":"+34 938 05 11 25",
    "sg:postcode":"08700",
    "sg:province":"Barcelona",
    "sg:website":"www.grupfabregas.com",
    "wof:name":"Fundicion Ductil Fabregas S.a.",
    "wof:placetype":"venue"
},
  "geometry": {"coordinates":[1.6319320202,41.5875930786],"type":"Point"}
}