{
  "type": "Feature",
  "properties": {
    "iso:country":"ES",
    "sg:address":"Calle de Andres Mellado, 29",
    "sg:city":"Madrid",
    "sg:orig_category":"Molduras, Junquillos, Listones Y Molduras Perforadas",
    "sg:phone":"+34 915 49 43 18",
    "sg:postcode":"28015",
    "sg:province":"Madrid",
    "wof:name":"Folgueira Fernandez Carlos",
    "wof:placetype":"venue"
},
  "geometry": {"coordinates":[-3.714495182,40.433216095],"type":"Point"}
}