{
  "type": "Feature",
  "properties": {
    "addr:full":"Mayor, S/n Valdelubiel Soria 42318",
    "addr:housenumber":"s",
    "addr:postcode":"42318",
    "addr:street":"Mayor;/ N",
    "iso:country":"ES",
    "sg:address":"Mayor, S/n",
    "sg:city":"Valdelubiel",
    "sg:orig_category":"Material Did\u00c1ctico",
    "sg:phone":"+34 975 36 36 28",
    "sg:postcode":"42318",
    "sg:province":"Soria",
    "wof:name":"Ediciones Maspe C.b.",
    "wof:placetype":"venue"
},
  "geometry": {"coordinates":[-3.0520789623,41.6258964539],"type":"Point"}
}