{
  "type": "Feature",
  "properties": {
    "addr:full":"Calle de Hospital, 1 Mislata Valencia 46920",
    "addr:housenumber":"1",
    "addr:postcode":"46920",
    "addr:street":"Calle De Hospital",
    "iso:country":"ES",
    "sg:address":"Calle de Hospital, 1",
    "sg:city":"Mislata",
    "sg:orig_category":"Materias Pl\u00c1sticas: Material, Equipos Industriales",
    "sg:phone":"+34 963 70 11 00",
    "sg:postcode":"46920",
    "sg:province":"Valencia",
    "wof:name":"Italprensas Sandretto S. A.",
    "wof:placetype":"venue"
},
  "geometry": {"coordinates":[-0.4225189984,39.4799880981],"type":"Point"}
}