{
  "type": "Feature",
  "properties": {
    "addr:full":"Av. Constitucion, 62 La Solana Ciudad Real 13240",
    "addr:housenumber":"62",
    "addr:postcode":"13240",
    "addr:street":"Av. Constitucion;La Solana;Real",
    "iso:country":"ES",
    "sg:address":"Av. Constitucion, 62",
    "sg:city":"La Solana",
    "sg:orig_category":"Empresas De Carpinter\u00cda De Madera",
    "sg:phone":"+34 926 63 30 22",
    "sg:postcode":"13240",
    "sg:province":"Ciudad Real",
    "wof:name":"Carpinteria Badillo S.l.",
    "wof:placetype":"venue"
},
  "geometry": {"coordinates":[-3.2348649502,38.9376220703],"type":"Point"}
}