{
  "type": "Feature",
  "properties": {
    "addr:full":"Calle de Ebanistas (los), 12 Alcorcon Madrid 28925",
    "addr:housenumber":"12",
    "addr:postcode":"28925",
    "addr:street":"Calle De Ebanistas Los",
    "iso:country":"ES",
    "sg:address":"Calle de Ebanistas (los), 12",
    "sg:city":"Alcorcon",
    "sg:orig_category":"Comercio De Piezas De Recambio Y De Accesorios De Veh\u00cdculos, Veh\u00cdculos Industriales",
    "sg:phone":"+34 916 43 56 12",
    "sg:postcode":"28925",
    "sg:province":"Madrid",
    "wof:name":"Vemare Sl",
    "wof:placetype":"venue"
},
  "geometry": {"coordinates":[-3.8075211048,40.3393096924],"type":"Point"}
}