{
  "type": "Feature",
  "properties": {
    "addr:full":"Pl. 19 Octubre, S/n Oviedo Asturias 33009",
    "addr:housenumber":"19;s / n",
    "addr:postcode":"33009",
    "addr:street":"Pl.;Octubre",
    "iso:country":"ES",
    "sg:address":"Pl. 19 Octubre, S/n",
    "sg:city":"Oviedo",
    "sg:orig_category":"Alimentaci\u00d3n General (al Por Menor)",
    "sg:phone":"+34 985 22 64 02",
    "sg:postcode":"33009",
    "sg:province":"Asturias",
    "wof:name":"Arrieta Balboa Maria Dolores",
    "wof:placetype":"venue"
},
  "geometry": {"coordinates":[-5.8426370621,43.3594169617],"type":"Point"}
}