{
  "type": "Feature",
  "properties": {
    "iso:country":"ES",
    "sg:address":"Calle de Gascona, 2",
    "sg:city":"Oviedo",
    "sg:orig_category":"Alumbrados",
    "sg:phone":"+34 985 20 13 05",
    "sg:postcode":"33001",
    "sg:province":"Asturias",
    "wof:name":"Luminis S.l.",
    "wof:placetype":"venue"
},
  "geometry": {"coordinates":[-5.843870163,43.3638916016],"type":"Point"}
}