{
  "type": "Feature",
  "properties": {
    "addr:full":"Carrer de General Prim, 22 Rubi Barcelona 08191",
    "addr:housenumber":"22",
    "addr:postcode":"08191",
    "addr:street":"Carrer De General Prim",
    "iso:country":"ES",
    "sg:address":"Carrer de General Prim, 22",
    "sg:city":"Rubi",
    "sg:orig_category":"Electricidad: Instaladores",
    "sg:phone":"+34 935 88 23 24",
    "sg:postcode":"08191",
    "sg:province":"Barcelona",
    "wof:name":"Electricitat Escofet S.l.",
    "wof:placetype":"venue"
},
  "geometry": {"coordinates":[2.0307059288,41.4873962402],"type":"Point"}
}