{
  "type": "Feature",
  "properties": {
    "iso:country":"ES",
    "sg:address":"Carrer de Ali Bei, S/n",
    "sg:city":"Barcelona",
    "sg:orig_category":"Pescader\u00cdas (al Por Menor)",
    "sg:phone":"+34 932 45 97 78",
    "sg:postcode":"08010",
    "sg:province":"Barcelona",
    "wof:name":"Sabate Sabadell S.l.",
    "wof:placetype":"venue"
},
  "geometry": {"coordinates":[2.1796319485,41.392665863],"type":"Point"}
}