{
  "type": "Feature",
  "properties": {
    "addr:full":"Cami Les Arenes, 22 Santpedor Barcelona 08251",
    "addr:housenumber":"22",
    "addr:postcode":"08251",
    "addr:street":"Les Arenes",
    "iso:country":"ES",
    "sg:address":"Cami Les Arenes, 22",
    "sg:city":"Santpedor",
    "sg:orig_category":"Maquinaria Neum\u00c1tica",
    "sg:phone":"+34 938 32 05 16",
    "sg:postcode":"08251",
    "sg:province":"Barcelona",
    "wof:name":"Industrias Vallma S.a.",
    "wof:placetype":"venue"
},
  "geometry": {"coordinates":[1.8371499777,41.8343658447],"type":"Point"}
}