{
  "type": "Feature",
  "properties": {
    "addr:full":"Rua Grecia, 10 Pontevedra Pontevedra 36162",
    "addr:housenumber":"10",
    "addr:postcode":"36162",
    "addr:street":"Rua Grecia",
    "iso:country":"ES",
    "sg:address":"Rua Grecia, 10",
    "sg:city":"Pontevedra",
    "sg:orig_category":"Vinos (agentes)",
    "sg:phone":"+34 986 89 64 67",
    "sg:postcode":"36162",
    "sg:province":"Pontevedra",
    "wof:name":"Representaciones Ricardo Antas S.l.l.",
    "wof:placetype":"venue"
},
  "geometry": {"coordinates":[-8.3892097473,42.2826576233],"type":"Point"}
}