{
  "type": "Feature",
  "properties": {
    "addr:full":"Esperanca, 12 Ariany Islas Baleares 07529",
    "addr:housenumber":"12",
    "addr:postcode":"07529",
    "addr:street":"Esperanca",
    "iso:country":"ES",
    "sg:address":"Esperanca, 12",
    "sg:city":"Ariany",
    "sg:orig_category":"Transportes Por V\u00cdas Navegables",
    "sg:phone":"+34 971 56 13 63",
    "sg:postcode":"07529",
    "sg:province":"Islas Baleares",
    "wof:name":"Frontera Mestre Miguel",
    "wof:placetype":"venue"
},
  "geometry": {"coordinates":[3.1162130833,39.6509590149],"type":"Point"}
}