{
  "type": "Feature",
  "properties": {
    "iso:country":"ES",
    "sg:address":"Plaz Corts Valencianes, 5",
    "sg:city":"Aldaia",
    "sg:orig_category":"Librer\u00cdas",
    "sg:phone":"+34 961 51 76 15",
    "sg:postcode":"46960",
    "sg:province":"Valencia",
    "wof:name":"Magdalena I Dauden S.l.",
    "wof:placetype":"venue"
},
  "geometry": {"coordinates":[-0.4672290087,39.4588394165],"type":"Point"}
}