{
  "type": "Feature",
  "properties": {
    "addr:full":"Pol Ind Pont Barquera, 16 Sta. Coloma Queralt Tarragona 43420",
    "addr:housenumber":"16",
    "addr:postcode":"43420",
    "addr:street":"Barquera",
    "iso:country":"ES",
    "sg:address":"Pol Ind Pont Barquera, 16",
    "sg:city":"Sta. Coloma Queralt",
    "sg:orig_category":"Electricidad: Equipos Industriales, Componentes (fabricaci\u00d3n)",
    "sg:phone":"+34 977 88 04 93",
    "sg:postcode":"43420",
    "sg:province":"Tarragona",
    "wof:name":"Nova Queraletric S.l.",
    "wof:placetype":"venue"
},
  "geometry": {"coordinates":[1.3818399906,41.5321388245],"type":"Point"}
}