{
  "type": "Feature",
  "properties": {
    "addr:full":"Ctra Benasque, S/n Campo Huesca 22450",
    "addr:housenumber":"s / n",
    "addr:postcode":"22450",
    "addr:street":"Ctra Benasque",
    "iso:country":"ES",
    "sg:address":"Ctra Benasque, S/n",
    "sg:city":"Campo",
    "sg:orig_category":"Mec\u00c1nico Del Autom\u00d3vil",
    "sg:phone":"+34 974 55 00 87",
    "sg:postcode":"22450",
    "sg:province":"Huesca",
    "wof:name":"Lanau Porte Antonio",
    "wof:placetype":"venue"
},
  "geometry": {"coordinates":[0.3431740105,42.4554100037],"type":"Point"}
}