{
  "type": "Feature",
  "properties": {
    "iso:country":"ES",
    "sg:address":"Cmno Serranillos, S/n",
    "sg:city":"Ugena",
    "sg:orig_category":"Cerrajer\u00cda, Ferrallista",
    "sg:phone":"+34 925 53 32 03",
    "sg:postcode":"45217",
    "sg:province":"Toledo",
    "wof:name":"Matfor Iberica S.l",
    "wof:placetype":"venue"
},
  "geometry": {"coordinates":[-3.8838338852,40.1856689453],"type":"Point"}
}