{
  "type": "Feature",
  "properties": {
    "addr:full":"Calle de Cruz, 14 Madrid Madrid 28012",
    "addr:housenumber":"14",
    "addr:postcode":"madrid;28012",
    "addr:street":"Calle De Cruz",
    "iso:country":"ES",
    "sg:address":"Calle de Cruz, 14",
    "sg:city":"Madrid",
    "sg:orig_category":"Cervecer\u00cdas",
    "sg:phone":"+34 915 32 25 80",
    "sg:postcode":"28012",
    "sg:province":"Madrid",
    "wof:name":"Droema S.l.",
    "wof:placetype":"venue"
},
  "geometry": {"coordinates":[-3.7017641068,40.4155731201],"type":"Point"}
}