{
  "type": "Feature",
  "properties": {
    "addr:full":"Carrer de Industria, 20 Sabadell Barcelona 08202",
    "addr:housenumber":"20",
    "addr:postcode":"08202",
    "addr:street":"Carrer De Industria",
    "iso:country":"ES",
    "sg:address":"Carrer de Industria, 20",
    "sg:city":"Sabadell",
    "sg:orig_category":"Frutas, Legumbres Frescas Y Tempranas (al Por Menor)",
    "sg:phone":"+34 937 27 62 51",
    "sg:postcode":"08202",
    "sg:province":"Barcelona",
    "wof:name":"Manchado Vargas Rafael",
    "wof:placetype":"venue"
},
  "geometry": {"coordinates":[2.111438036,41.5470733643],"type":"Point"}
}