{
  "type": "Feature",
  "properties": {
    "addr:full":"Ctra Manresa, 65 Igualada Barcelona 08700",
    "addr:housenumber":"65",
    "addr:postcode":"08700",
    "addr:street":"Ctra Manresa",
    "iso:country":"ES",
    "sg:address":"Ctra Manresa, 65",
    "sg:city":"Igualada",
    "sg:orig_category":"Centros Pms (psico",
    "sg:phone":"+34 938 04 17 33",
    "sg:postcode":"08700",
    "sg:province":"Barcelona",
    "wof:name":"Centre De Telecomunicaciones De Catalunya",
    "wof:placetype":"venue"
},
  "geometry": {"coordinates":[1.6169309616,41.584690094],"type":"Point"}
}