{
  "type": "Feature",
  "properties": {
    "iso:country":"ES",
    "sg:address":"Carrer de Joaquim Togores, 7",
    "sg:city":"Palma",
    "sg:orig_category":"Empresas De Limpieza",
    "sg:phone":"+34 971 75 76 94",
    "sg:postcode":"07010",
    "sg:province":"Islas Baleares",
    "wof:name":"Net A Net Garayalde Balears S.l.",
    "wof:placetype":"venue"
},
  "geometry": {"coordinates":[2.6524679661,39.5867004395],"type":"Point"}
}