{
  "type": "Feature",
  "properties": {
    "addr:full":"Ctra Valencia, S/n Cadrete Zaragoza 50420",
    "addr:housenumber":"s",
    "addr:postcode":"50420",
    "addr:street":"Ctra Valencia;/ N Cadrete",
    "iso:country":"ES",
    "sg:address":"Ctra Valencia, S/n",
    "sg:city":"Cadrete",
    "sg:orig_category":"Mobiliario M\u00c9dico Y Quir\u00dargico",
    "sg:phone":"+34 976 12 66 90",
    "sg:postcode":"50420",
    "sg:province":"Zaragoza",
    "wof:name":"Apotheka-imedisa 2001 S.a.",
    "wof:placetype":"venue"
},
  "geometry": {"coordinates":[-0.9608619809,41.5734024048],"type":"Point"}
}