{
  "type": "Feature",
  "properties": {
    "addr:full":"Calle de Alonso De Quiros, 3 Plasencia C\u00e1ceres 10600",
    "addr:housenumber":"3",
    "addr:postcode":"10600",
    "addr:street":"Calle De Alonso De Quiros;Ca\u0301Ceres",
    "iso:country":"ES",
    "sg:address":"Calle de Alonso De Quiros, 3",
    "sg:city":"Plasencia",
    "sg:orig_category":"Pescader\u00cdas (al Por Menor)",
    "sg:phone":"+34 927 42 23 22",
    "sg:postcode":"10600",
    "sg:province":"C\u00e1ceres",
    "wof:name":"Pescados Y Mariscos Jaime S.l.",
    "wof:placetype":"venue"
},
  "geometry": {"coordinates":[-6.0890731812,40.038444519],"type":"Point"}
}