{
  "type": "Feature",
  "properties": {
    "addr:full":"Carrer de Badajoz, 4 Hospitalet Llobregat Barcelona 08906",
    "addr:housenumber":"4",
    "addr:postcode":"08906",
    "addr:street":"Carrer De Badajoz",
    "iso:country":"ES",
    "sg:address":"Carrer de Badajoz, 4",
    "sg:city":"Hospitalet Llobregat",
    "sg:orig_category":"Mec\u00c1nico Del Autom\u00d3vil",
    "sg:phone":"+34 934 37 92 94",
    "sg:postcode":"08906",
    "sg:province":"Barcelona",
    "wof:name":"Rodriguez Santos Floreano",
    "wof:placetype":"venue"
},
  "geometry": {"coordinates":[2.0984230042,41.3669471741],"type":"Point"}
}