{
  "type": "Feature",
  "properties": {
    "iso:country":"ES",
    "sg:address":"Rond Barcelona, 57",
    "sg:city":"Figueres",
    "sg:orig_category":"Sindicatos De Trabajadores",
    "sg:phone":"+34 972 51 36 66",
    "sg:postcode":"17600",
    "sg:province":"Girona",
    "wof:name":"Unio De Pagesos De Catalunya",
    "wof:placetype":"venue"
},
  "geometry": {"coordinates":[2.961977005,42.2584724426],"type":"Point"}
}