{
  "type": "Feature",
  "properties": {
    "addr:full":"Avda Industria (de La), 17 Fuenlabrada Madrid 28947",
    "addr:housenumber":"17",
    "addr:postcode":"28947",
    "addr:street":"Avda Industria De La",
    "iso:country":"ES",
    "sg:address":"Avda Industria (de La), 17",
    "sg:city":"Fuenlabrada",
    "sg:orig_category":"Industrias Aeron\u00c1uticas Y Espaciales",
    "sg:phone":"+34 916 42 30 78",
    "sg:postcode":"28947",
    "sg:province":"Madrid",
    "wof:name":"Grupo Aeronautico Zona Centro S.a.",
    "wof:placetype":"venue"
},
  "geometry": {"coordinates":[-3.7617819309,40.2701797485],"type":"Point"}
}