{
  "type": "Feature",
  "properties": {
    "iso:country":"ES",
    "sg:address":"Calle de Fuente, 3",
    "sg:city":"Chera",
    "sg:orig_category":"Empresarios",
    "sg:phone":"+34 962 33 20 33",
    "sg:postcode":"46350",
    "sg:province":"Valencia",
    "wof:name":"Martinez Garcia Juan",
    "wof:placetype":"venue"
},
  "geometry": {"coordinates":[-0.9713500142,39.5932922363],"type":"Point"}
}