{
  "type": "Feature",
  "properties": {
    "addr:full":"Calle de Santa Eugenia, 9 Arenas -areeta Vizcaya 48930",
    "addr:housenumber":"9;areeta",
    "addr:postcode":"48930",
    "addr:street":"Calle De Santa Eugenia",
    "iso:country":"ES",
    "sg:address":"Calle de Santa Eugenia, 9",
    "sg:city":"Arenas -areeta",
    "sg:orig_category":"Productores Recolectores, Venta Directa De Vinos",
    "sg:phone":"+34 944 63 42 22",
    "sg:postcode":"48930",
    "sg:province":"Vizcaya",
    "wof:name":"Herce Ortega Jose Maria",
    "wof:placetype":"venue"
},
  "geometry": {"coordinates":[-3.0093200207,43.3268661499],"type":"Point"}
}