{
  "type": "Feature",
  "properties": {
    "iso:country":"ES",
    "sg:address":"Calle de Almansa, 1",
    "sg:city":"Madrid",
    "sg:orig_category":"Restaurantes",
    "sg:phone":"+34 915 53 40 76",
    "sg:postcode":"28039",
    "sg:province":"Madrid",
    "sg:website":"www.mangitalia.com",
    "wof:name":"Santori  Mario",
    "wof:placetype":"venue"
},
  "geometry": {"coordinates":[-3.7038080692,40.4486045837],"type":"Point"}
}