{
  "type": "Feature",
  "properties": {
    "iso:country":"ES",
    "sg:address":"Avda Lugo (de), S/n",
    "sg:city":"Monterroso",
    "sg:orig_category":"Veh\u00cdculos De Ocasi\u00d3n",
    "sg:phone":"+34 982 37 72 22",
    "sg:postcode":"27560",
    "sg:province":"Lugo",
    "wof:name":"Varela Vivero Manuel",
    "wof:placetype":"venue"
},
  "geometry": {"coordinates":[-7.8336138725,42.7924499512],"type":"Point"}
}