{
  "type": "Feature",
  "properties": {
    "addr:full":"Calle de Valdetorres De Jarama, 21 Madrid Madrid 28043",
    "addr:housenumber":"21",
    "addr:postcode":"madrid;28043",
    "addr:street":"Calle De Valdetorres",
    "iso:country":"ES",
    "sg:address":"Calle de Valdetorres De Jarama, 21",
    "sg:city":"Madrid",
    "sg:orig_category":"Electricidad: Instaladores",
    "sg:phone":"+34 913 81 36 27",
    "sg:postcode":"28043",
    "sg:province":"Madrid",
    "wof:name":"Casado Blanco C.b.",
    "wof:placetype":"venue"
},
  "geometry": {"coordinates":[-3.6446540356,40.4711036682],"type":"Point"}
}