{
  "type": "Feature",
  "properties": {
    "iso:country":"ES",
    "sg:address":"Avda Rio Guadarrama, 28",
    "sg:city":"Poligono Sta M. De Benquerencia",
    "sg:orig_category":"Peluquer\u00cdas, Peluquer\u00cda Mixta",
    "sg:phone":"+34 925 23 30 28",
    "sg:postcode":"45007",
    "sg:province":"Toledo",
    "wof:name":"Serrano Peluqueros C.b.",
    "wof:placetype":"venue"
},
  "geometry": {"coordinates":[-3.9442191124,39.8644599915],"type":"Point"}
}