{
  "type": "Feature",
  "properties": {
    "addr:full":"Carr Maestro Serrano, 43 Manises Valencia 46940",
    "addr:housenumber":"43",
    "addr:postcode":"46940",
    "addr:street":"Carr Maestro Serrano",
    "iso:country":"ES",
    "sg:address":"Carr Maestro Serrano, 43",
    "sg:city":"Manises",
    "sg:orig_category":"Chapister\u00cda",
    "sg:phone":"+34 961 52 46 58",
    "sg:postcode":"46940",
    "sg:province":"Valencia",
    "wof:name":"Manises Automocion S.l.",
    "wof:placetype":"venue"
},
  "geometry": {"coordinates":[-0.4690229893,39.4915161133],"type":"Point"}
}