{
  "type": "Feature",
  "properties": {
    "addr:full":"Pablo Mutiozabal Kalea-calle Pablo Mutioz, 7 Lasarte Guip\u00f9zcoa 20160",
    "addr:housenumber":"7",
    "addr:postcode":"20160",
    "addr:street":"Pablo;Kalea-Calle;Mutioz;Lasarte Guipu\u0300Zcoa",
    "iso:country":"ES",
    "sg:address":"Pablo Mutiozabal Kalea-calle Pablo Mutioz, 7",
    "sg:city":"Lasarte",
    "sg:orig_category":"Artes Gr\u00c1ficas, Artes Pl\u00c1sticas: Material Y Suministros (al Por Menor)",
    "sg:phone":"+34 943 36 30 23",
    "sg:postcode":"20160",
    "sg:province":"Guip\u00f9zcoa",
    "wof:name":"Coca Perez Ana Belen De La",
    "wof:placetype":"venue"
},
  "geometry": {"coordinates":[-2.020414114,43.2698173523],"type":"Point"}
}