{
  "type": "Feature",
  "properties": {
    "addr:full":"Avda Monte Igueldo, 34 Madrid Madrid 28053",
    "addr:housenumber":"34",
    "addr:postcode":"madrid;28053",
    "addr:street":"Avda Monte Igueldo",
    "iso:country":"ES",
    "sg:address":"Avda Monte Igueldo, 34",
    "sg:city":"Madrid",
    "sg:orig_category":"Alimentaci\u00d3n General (al Por Menor)",
    "sg:phone":"+34 914 33 33 24",
    "sg:postcode":"28053",
    "sg:province":"Madrid",
    "wof:name":"Feng  Zonghai",
    "wof:placetype":"venue"
},
  "geometry": {"coordinates":[-3.6691520214,40.3951301575],"type":"Point"}
}