{
  "type": "Feature",
  "properties": {
    "iso:country":"ES",
    "sg:address":"Calle de Cuchilleros, 15",
    "sg:city":"Madrid",
    "sg:classifiers":[
        {
            "category":"Personal",
            "subcategory":"Barber",
            "type":"Services"
        }
    ],
    "sg:phone":"+34 913 66 58 87",
    "sg:postcode":"28005",
    "sg:province":"Madrid",
    "sg:tags":[
        "caballeros",
        "de",
        "peluqueros"
    ],
    "wof:name":"Lopez Cenieno Rafael",
    "wof:placetype":"venue"
},
  "geometry": {"coordinates":[-3.7081155777,40.4140701294],"type":"Point"}
}