{
  "type": "Feature",
  "properties": {
    "addr:full":"Calle de Estacion, 14 Rozas De Madrid Madrid 28230",
    "addr:housenumber":"14",
    "addr:postcode":"28230",
    "addr:street":"Calle De Estacion",
    "iso:country":"ES",
    "sg:address":"Calle de Estacion, 14",
    "sg:city":"Rozas De Madrid",
    "sg:orig_category":"Sociedades, Compa\u00d1\u00cdas Aseguradoras",
    "sg:phone":"+34 916 37 49 07",
    "sg:postcode":"28230",
    "sg:province":"Madrid",
    "wof:name":"Seguros Catalana Occidente S.a. De Seguros Y Reaseguros",
    "wof:placetype":"venue"
},
  "geometry": {"coordinates":[-3.8706159592,40.4948120117],"type":"Point"}
}