{
  "type": "Feature",
  "properties": {
    "iso:country":"ES",
    "sg:address":"Calle de Puerto Mediterraneo, S/n",
    "sg:city":"Cenes Vega",
    "sg:orig_category":"Librer\u00cdas",
    "sg:phone":"+34 958 48 60 75",
    "sg:postcode":"18190",
    "sg:province":"Granada",
    "wof:name":"Castillo Castillo Bernardo",
    "wof:placetype":"venue"
},
  "geometry": {"coordinates":[-3.5423738956,37.1603355408],"type":"Point"}
}