{
  "type": "Feature",
  "properties": {
    "addr:full":"Cmno Calvario, 3 Berbinzana Navarra 31252",
    "addr:housenumber":"3",
    "addr:postcode":"31252",
    "addr:street":"Cmno Calvario",
    "iso:country":"ES",
    "sg:address":"Cmno Calvario, 3",
    "sg:city":"Berbinzana",
    "sg:orig_category":"Plomeros",
    "sg:phone":"+34 948 72 22 28",
    "sg:postcode":"31252",
    "sg:province":"Navarra",
    "wof:name":"Diez De Esteban Jesus",
    "wof:placetype":"venue"
},
  "geometry": {"coordinates":[-1.8362749815,42.5253295898],"type":"Point"}
}