{
  "type": "Feature",
  "properties": {
    "addr:full":"Calle de Eras, 85 Pedraza Alba Salamanca 37882",
    "addr:housenumber":"85",
    "addr:postcode":"37882",
    "addr:street":"Calle De Eras",
    "iso:country":"ES",
    "sg:address":"Calle de Eras, 85",
    "sg:city":"Pedraza Alba",
    "sg:orig_category":"Delegados, Agentes De Tr\u00c1nsito, Auxiliares De Transporte Internacional",
    "sg:phone":"+34 923 38 31 78",
    "sg:postcode":"37882",
    "sg:province":"Salamanca",
    "wof:name":"Sanchez Garcia Domingo",
    "wof:placetype":"venue"
},
  "geometry": {"coordinates":[-5.3752188683,40.756401062],"type":"Point"}
}