{
  "type": "Feature",
  "properties": {
    "iso:country":"ES",
    "sg:address":"Calle de Medina Albaida, 1",
    "sg:city":"Zaragoza",
    "sg:orig_category":"Reposter\u00cdas",
    "sg:phone":"+34 976 25 02 57",
    "sg:postcode":"50007",
    "sg:province":"Zaragoza",
    "wof:name":"Panificadora Luisa S.l.",
    "wof:placetype":"venue"
},
  "geometry": {"coordinates":[-0.8759610057,41.624042511],"type":"Point"}
}