{
  "type": "Feature",
  "properties": {
    "iso:country":"ES",
    "sg:address":"Avda Pio Xii, 114",
    "sg:city":"Talavera Reina",
    "sg:orig_category":"Internados & Ense\u00d1anza Privada",
    "sg:phone":"+34 925 81 80 67",
    "sg:postcode":"45600",
    "sg:province":"Toledo",
    "wof:name":"Instituto Secular De San Bonifacio",
    "wof:placetype":"venue"
},
  "geometry": {"coordinates":[-4.8340401649,39.9657478333],"type":"Point"}
}