{
  "type": "Feature",
  "properties": {
    "addr:full":"Calle de Pedro Antonio De Alarcon, 5 Granada Granada 18005",
    "addr:housenumber":"5",
    "addr:postcode":"18005",
    "addr:street":"Calle De Pedro Antonio De Alarcon",
    "iso:country":"ES",
    "sg:address":"Calle de Pedro Antonio De Alarcon, 5",
    "sg:city":"Granada",
    "sg:orig_category":"Peluquer\u00cdas",
    "sg:phone":"+34 958 25 13 94",
    "sg:postcode":"18005",
    "sg:province":"Granada",
    "wof:name":"Paniza Salcedo Maria Del Carmen",
    "wof:placetype":"venue"
},
  "geometry": {"coordinates":[-3.6034066677,37.1694526672],"type":"Point"}
}