{
  "type": "Feature",
  "properties": {
    "addr:full":"Calle de Santa Marta, 3 Martos Ja\u00e9n 23600",
    "addr:housenumber":"3",
    "addr:postcode":"23600",
    "addr:street":"Calle De Santa Marta;Jae\u0301N",
    "iso:country":"ES",
    "sg:address":"Calle de Santa Marta, 3",
    "sg:city":"Martos",
    "sg:orig_category":"Peluqueros: De Se\u00d1oras",
    "sg:phone":"+34 953 55 26 60",
    "sg:postcode":"23600",
    "sg:province":"Ja\u00e9n",
    "wof:name":"Melero Gata Dolores",
    "wof:placetype":"venue"
},
  "geometry": {"coordinates":[-3.974148035,37.7249717712],"type":"Point"}
}