{
  "type": "Feature",
  "properties": {
    "iso:country":"ES",
    "sg:address":"Ctra Nacional V Madrid-lisboa, Km. 0399,0",
    "sg:city":"Badajoz",
    "sg:orig_category":"Agentes, Concesionarios Y Sucursales De Veh\u00cdculos",
    "sg:phone":"+34 924 20 06 22",
    "sg:postcode":"06008",
    "sg:province":"Badajoz",
    "wof:name":"Trevauto S.l.",
    "wof:placetype":"venue"
},
  "geometry": {"coordinates":[-6.9430441856,38.8723373413],"type":"Point"}
}