{
  "type": "Feature",
  "properties": {
    "addr:full":"Plaz Parque De Capuchinos, 1 Jerez De La Frontera C\u00e1diz 11405",
    "addr:postcode":"11405",
    "iso:country":"ES",
    "sg:address":"Plaz Parque De Capuchinos, 1",
    "sg:city":"Jerez De La Frontera",
    "sg:orig_category":"Peluqueros: De Se\u00d1oras",
    "sg:phone":"+34 956 30 90 99",
    "sg:postcode":"11405",
    "sg:province":"C\u00e1diz",
    "wof:name":"Futuros Peluqueros Asociados Sl",
    "wof:placetype":"venue"
},
  "geometry": {"coordinates":[-6.1005191803,36.7067260742],"type":"Point"}
}