{
  "type": "Feature",
  "properties": {
    "addr:full":"Calle de Lope Baez De Herrero, 3 Plasencia C\u00e1ceres 10600",
    "addr:housenumber":"3",
    "addr:postcode":"10600",
    "addr:street":"Calle De Lope Baez De Herrero;Ca\u0301Ceres",
    "iso:country":"ES",
    "sg:address":"Calle de Lope Baez De Herrero, 3",
    "sg:city":"Plasencia",
    "sg:orig_category":"Carnicer\u00cdas, Carnicer\u00cdas",
    "sg:phone":"+34 927 41 00 00",
    "sg:postcode":"10600",
    "sg:province":"C\u00e1ceres",
    "wof:name":"Gonzalez Martin Clara",
    "wof:placetype":"venue"
},
  "geometry": {"coordinates":[-6.0819029808,40.0342063904],"type":"Point"}
}