{
  "type": "Feature",
  "properties": {
    "addr:full":"Av Puig I Ferreter, 39 Selva Del Camp Tarragona 43470",
    "addr:housenumber":"39",
    "addr:postcode":"43470",
    "addr:street":"Av Puig I Ferreter",
    "iso:country":"ES",
    "sg:address":"Av Puig I Ferreter, 39",
    "sg:city":"Selva Del Camp",
    "sg:orig_category":"Inmobiliaria (agencias)",
    "sg:phone":"+34 977 76 63 87",
    "sg:postcode":"43470",
    "sg:province":"Tarragona",
    "wof:name":"Living Alt I Baix Camp, S.l.",
    "wof:placetype":"venue"
},
  "geometry": {"coordinates":[1.1413700581,41.2123298645],"type":"Point"}
}