{
  "type": "Feature",
  "properties": {
    "iso:country":"ES",
    "sg:address":"Calle de Artesano Pepe Marin, 1",
    "sg:city":"Chiclana De La Frontera",
    "sg:orig_category":"Cristaler\u00cdas",
    "sg:phone":"+34 956 53 68 66",
    "sg:postcode":"11130",
    "sg:province":"C\u00e1diz",
    "wof:name":"Moreno Manzano Jose",
    "wof:placetype":"venue"
},
  "geometry": {"coordinates":[-6.1490616798,36.4201774597],"type":"Point"}
}