{
  "type": "Feature",
  "properties": {
    "addr:full":"Calle de Calvario, 169 Jumilla Murcia 30520",
    "addr:housenumber":"169",
    "addr:postcode":"30520",
    "addr:street":"Calle De Calvario",
    "iso:country":"ES",
    "sg:address":"Calle de Calvario, 169",
    "sg:city":"Jumilla",
    "sg:orig_category":"Tapiceros Y Tapiceros",
    "sg:phone":"+34 968 75 61 12",
    "sg:postcode":"30520",
    "sg:province":"Murcia",
    "wof:name":"Diaz Guardiola Maria",
    "wof:placetype":"venue"
},
  "geometry": {"coordinates":[-1.3241140842,38.4776916504],"type":"Point"}
}