{
  "type": "Feature",
  "properties": {
    "iso:country":"ES",
    "sg:address":"Ctra Higueron (p I Zabal Bajo), 40",
    "sg:city":"La Linea",
    "sg:orig_category":"Muebles, Minoristas",
    "sg:phone":"+34 956 64 42 28",
    "sg:postcode":"11300",
    "sg:province":"C\u00e1diz",
    "sg:website":"www.meginterior.com",
    "wof:name":"Meginterior S.l.",
    "wof:placetype":"venue"
},
  "geometry": {"coordinates":[-5.3468561172,36.1927337646],"type":"Point"}
}