{
  "type": "Feature",
  "properties": {
    "addr:full":"Carrer de Signes (de), 3 Gata Gorgos Alicante 03740",
    "addr:postcode":"03740",
    "addr:street":"Carrer De Signes De 3 Gata",
    "iso:country":"ES",
    "sg:address":"Carrer de Signes (de), 3",
    "sg:city":"Gata Gorgos",
    "sg:orig_category":"Cajas De Ahorro",
    "sg:phone":"+34 965 75 63 00",
    "sg:postcode":"03740",
    "sg:province":"Alicante",
    "sg:website":"www.cam.es",
    "wof:name":"Caja De Ahorros Del Mediterraneo",
    "wof:placetype":"venue"
},
  "geometry": {"coordinates":[0.0841849968,38.7738304138],"type":"Point"}
}