{
  "type": "Feature",
  "properties": {
    "iso:country":"ES",
    "sg:address":"Calle de Velazquez, S/n",
    "sg:city":"Gijon",
    "sg:orig_category":"Acondicionamiento De Terrenos Para Deporte Y Juegos",
    "sg:phone":"+34 985 15 59 83",
    "sg:postcode":"33211",
    "sg:province":"Asturias",
    "wof:name":"Club Deportivo Roces",
    "wof:placetype":"venue"
},
  "geometry": {"coordinates":[-5.6786689758,43.5228805542],"type":"Point"}
}