{
  "type": "Feature",
  "properties": {
    "addr:full":"Plaz Juan Xxiii, 1 Palencia Palencia 34001",
    "addr:housenumber":"1",
    "addr:postcode":"34001",
    "addr:street":"Plaz Juan Xxiii",
    "iso:country":"ES",
    "sg:address":"Plaz Juan Xxiii, 1",
    "sg:city":"Palencia",
    "sg:orig_category":"Iglesia Cat\u00d3lica",
    "sg:phone":"+34 979 74 34 15",
    "sg:postcode":"34001",
    "sg:province":"Palencia",
    "wof:name":"Parroquia De Santa Marina",
    "wof:placetype":"venue"
},
  "geometry": {"coordinates":[-4.5385951996,42.0136260986],"type":"Point"}
}