{
  "type": "Feature",
  "properties": {
    "iso:country":"ES",
    "sg:address":"Ctra Riudaura, 44",
    "sg:city":"Olot",
    "sg:orig_category":"Alimentaci\u00d3n General (al Por Menor)",
    "sg:phone":"+34 972 26 10 15",
    "sg:postcode":"17800",
    "sg:province":"Girona",
    "wof:name":"Lopez Alongina Santiago",
    "wof:placetype":"venue"
},
  "geometry": {"coordinates":[2.4772839546,42.1841926575],"type":"Point"}
}