{
  "type": "Feature",
  "properties": {
    "addr:full":"Calle de Almazan, 27 Madrid Madrid 28011",
    "addr:housenumber":"27",
    "addr:postcode":"madrid;28011",
    "addr:street":"Calle De Almazan",
    "iso:country":"ES",
    "sg:address":"Calle de Almazan, 27",
    "sg:city":"Madrid",
    "sg:orig_category":"Agencias Y Agentes Comerciales, Representantes",
    "sg:phone":"+34 915 26 12 74",
    "sg:postcode":"28011",
    "sg:province":"Madrid",
    "wof:name":"Representacion De Acero S.l.u.",
    "wof:placetype":"venue"
},
  "geometry": {"coordinates":[-3.745568037,40.4056587219],"type":"Point"}
}