{
  "type": "Feature",
  "properties": {
    "iso:country":"ES",
    "sg:address":"Calle de Olite, 48",
    "sg:city":"Madrid",
    "sg:orig_category":"Venta, Instalaci\u00d3n De Calefacci\u00d3n",
    "sg:phone":"+34 914 59 65 34",
    "sg:postcode":"28039",
    "sg:province":"Madrid",
    "sg:website":"www.roca.es",
    "wof:name":"Herves Tohux Alfonso Y Herves Dans Alfonso C.b.",
    "wof:placetype":"venue"
},
  "geometry": {"coordinates":[-3.7067239285,40.4525413513],"type":"Point"}
}