{
  "type": "Feature",
  "properties": {
    "addr:full":"Av Galicia, 4 Jonquera Girona 17700",
    "addr:housenumber":"4",
    "addr:postcode":"17700",
    "addr:street":"Av Galicia",
    "iso:country":"ES",
    "sg:address":"Av Galicia, 4",
    "sg:city":"Jonquera",
    "sg:orig_category":"Sexshops",
    "sg:phone":"+34 972 55 54 72",
    "sg:postcode":"17700",
    "sg:province":"Girona",
    "wof:name":"Sex Shop Enea's 2003 Sc",
    "wof:placetype":"venue"
},
  "geometry": {"coordinates":[2.8817451,42.3987846375],"type":"Point"}
}