{
  "type": "Feature",
  "properties": {
    "addr:full":"Carrer de Caponata, 15 Barcelona Barcelona 08034",
    "addr:housenumber":"15",
    "addr:postcode":"08034",
    "addr:street":"Carrer De Caponata",
    "iso:country":"ES",
    "sg:address":"Carrer de Caponata, 15",
    "sg:city":"Barcelona",
    "sg:orig_category":"Agencias De Relaciones P\u00dablicas",
    "sg:phone":"+34 932 04 22 57",
    "sg:postcode":"08034",
    "sg:province":"Barcelona",
    "wof:name":"Casademont La Rosa Jaime",
    "wof:placetype":"venue"
},
  "geometry": {"coordinates":[2.1217739582,41.3955154419],"type":"Point"}
}