{
  "type": "Feature",
  "properties": {
    "iso:country":"ES",
    "sg:address":"Ctra. Sevilla-coria, Km. 0003,5",
    "sg:city":"San J. Aznalfarache",
    "sg:orig_category":"Televisi\u00d3n, V\u00cddeo: Aparatos Y Accesorios (venta)",
    "sg:phone":"+34 954 17 16 67",
    "sg:postcode":"41920",
    "sg:province":"Sevilla",
    "sg:website":"www.promovisa.es",
    "wof:name":"Promotora De Video S.a.",
    "wof:placetype":"venue"
},
  "geometry": {"coordinates":[-6.0277690887,37.359916687],"type":"Point"}
}