{
  "type": "Feature",
  "properties": {
    "addr:full":"Carr Santa Anna, 6 Muro Islas Baleares 07440",
    "addr:housenumber":"6",
    "addr:postcode":"07440",
    "addr:street":"Carr Santa Anna",
    "iso:country":"ES",
    "sg:address":"Carr Santa Anna, 6",
    "sg:city":"Muro",
    "sg:orig_category":"Asociaciones, Organismos Culturales Y Socioeducativos",
    "sg:phone":"+34 971 53 71 06",
    "sg:postcode":"07440",
    "sg:province":"Islas Baleares",
    "wof:name":"Fomento De Cultura",
    "wof:placetype":"venue"
},
  "geometry": {"coordinates":[3.0570909977,39.7354011536],"type":"Point"}
}