{
  "type": "Feature",
  "properties": {
    "addr:full":"Avda Blasco Iba\u00d1ez, 134 Valencia Valencia 46022",
    "addr:housenumber":"134",
    "addr:postcode":"46022",
    "addr:street":"Avda Blasco Iban\u0303Ez",
    "iso:country":"ES",
    "sg:address":"Avda Blasco Iba\u00d1ez, 134",
    "sg:city":"Valencia",
    "sg:orig_category":"Florister\u00cdas",
    "sg:phone":"+34 963 55 71 90",
    "sg:postcode":"46022",
    "sg:province":"Valencia",
    "wof:name":"Alonso Minguez Trinidad Carmen",
    "wof:placetype":"venue"
},
  "geometry": {"coordinates":[-0.3454954028,39.4729499817],"type":"Point"}
}