{
  "type": "Feature",
  "properties": {
    "iso:country":"ES",
    "sg:address":"Calle de Alferez Provisional, 4",
    "sg:city":"Marchena",
    "sg:orig_category":"Reposter\u00cdas",
    "sg:phone":"+34 954 84 39 37",
    "sg:postcode":"41620",
    "sg:province":"Sevilla",
    "wof:name":"Panaderia Santa Clara S.l.",
    "wof:placetype":"venue"
},
  "geometry": {"coordinates":[-5.4155421257,37.3239250183],"type":"Point"}
}