{
  "type": "Feature",
  "properties": {
    "addr:full":"Pase Molino, 6 Madrid Madrid 28045",
    "addr:housenumber":"6",
    "addr:postcode":"28045",
    "addr:street":"Molino",
    "iso:country":"ES",
    "sg:address":"Pase Molino, 6",
    "sg:city":"Madrid",
    "sg:orig_category":"Pintura Y Barniz (al Por Menor)",
    "sg:phone":"+34 915 39 00 27",
    "sg:postcode":"28045",
    "sg:province":"Madrid",
    "wof:name":"Gomez Gutierrez Encarnacion",
    "wof:placetype":"venue"
},
  "geometry": {"coordinates":[-3.6934070587,40.3901062012],"type":"Point"}
}