{
  "type": "Feature",
  "properties": {
    "addr:full":"Calle de F. Toribio De Motolinia, 8 Zamora Zamora 49007",
    "addr:housenumber":"8",
    "addr:postcode":"49007",
    "addr:street":"Calle De F. Toribio De Motolinia",
    "iso:country":"ES",
    "sg:address":"Calle de F. Toribio De Motolinia, 8",
    "sg:city":"Zamora",
    "sg:orig_category":"Material Y Herramientas Agr\u00cdcolas",
    "sg:phone":"+34 980 52 17 29",
    "sg:postcode":"49007",
    "sg:province":"Zamora",
    "wof:name":"Agricola Zamorana",
    "wof:placetype":"venue"
},
  "geometry": {"coordinates":[-5.7439951897,41.5094337463],"type":"Point"}
}