{
  "type": "Feature",
  "properties": {
    "addr:full":"Carrer de Villarroel, 225 Barcelona Barcelona 08036",
    "addr:housenumber":"225",
    "addr:postcode":"08036",
    "addr:street":"Carrer De Villarroel",
    "iso:country":"ES",
    "sg:address":"Carrer de Villarroel, 225",
    "sg:city":"Barcelona",
    "sg:orig_category":"Alimentaci\u00d3n General (al Por Menor)",
    "sg:phone":"+34 934 39 60 85",
    "sg:postcode":"08036",
    "sg:province":"Barcelona",
    "wof:name":"Perez Navarro Jose",
    "wof:placetype":"venue"
},
  "geometry": {"coordinates":[2.1491239071,41.3907775879],"type":"Point"}
}