{
  "type": "Feature",
  "properties": {
    "addr:full":"Rua Augusto Gonzalez Besada, 15 Pontevedra Pontevedra 36001",
    "addr:housenumber":"15",
    "addr:postcode":"36001",
    "addr:street":"Rua Augusto Gonzalez Besada",
    "iso:country":"ES",
    "sg:address":"Rua Augusto Gonzalez Besada, 15",
    "sg:city":"Pontevedra",
    "sg:orig_category":"Abogados",
    "sg:phone":"+34 986 85 22 27",
    "sg:postcode":"36001",
    "sg:province":"Pontevedra",
    "wof:name":"Millan Gonzalez-pardo Francisco",
    "wof:placetype":"venue"
},
  "geometry": {"coordinates":[-8.6445684433,42.4287338257],"type":"Point"}
}