{
  "type": "Feature",
  "properties": {
    "iso:country":"ES",
    "sg:address":"Carrer de Constitucio, 6",
    "sg:city":"Palma",
    "sg:orig_category":"Sindicatos De Trabajadores",
    "sg:phone":"+34 971 72 23 50",
    "sg:postcode":"07001",
    "sg:province":"Islas Baleares",
    "wof:name":"Confederacio Sindical De Comissions Obreres De Les Illes",
    "wof:placetype":"venue"
},
  "geometry": {"coordinates":[2.6475389004,39.5694770813],"type":"Point"}
}