{
  "type": "Feature",
  "properties": {
    "addr:full":"Rond Pilar, 41 Badajoz Badajoz 06002",
    "addr:housenumber":"41",
    "addr:postcode":"06002",
    "addr:street":"Pilar",
    "iso:country":"ES",
    "sg:address":"Rond Pilar, 41",
    "sg:city":"Badajoz",
    "sg:orig_category":"Productos Qu\u00cdmicos (fabricaci\u00d3n, Al Por Mayor)",
    "sg:phone":"+34 924 23 76 90",
    "sg:postcode":"06002",
    "sg:province":"Badajoz",
    "wof:name":"Ingenieria De Gestion Industrial S.l.",
    "wof:placetype":"venue"
},
  "geometry": {"coordinates":[-6.9680571556,38.8760223389],"type":"Point"}
}