{
  "type": "Feature",
  "properties": {
    "iso:country":"ES",
    "sg:address":"Carrer de Santa Magdalena, 4",
    "sg:city":"Reus",
    "sg:orig_category":"Electricidad: Instaladores",
    "sg:phone":"+34 977 34 05 76",
    "sg:postcode":"43201",
    "sg:province":"Tarragona",
    "sg:website":"www.maguevi.com",
    "wof:name":"Maguevi Instalaciones S.l.",
    "wof:placetype":"venue"
},
  "geometry": {"coordinates":[1.1103800535,41.1576347351],"type":"Point"}
}