{
  "type": "Feature",
  "properties": {
    "addr:full":"Calle de Bell, 4 Getafe Madrid 28906",
    "addr:housenumber":"4",
    "addr:postcode":"28906",
    "addr:street":"Calle De Bell",
    "iso:country":"ES",
    "sg:address":"Calle de Bell, 4",
    "sg:city":"Getafe",
    "sg:orig_category":"Metales (labores, Pulido)",
    "sg:phone":"+34 916 84 21 40",
    "sg:postcode":"28906",
    "sg:province":"Madrid",
    "wof:name":"Exclusivas Jll S.l.",
    "wof:placetype":"venue"
},
  "geometry": {"coordinates":[-3.7012703419,40.2968864441],"type":"Point"}
}