{
  "type": "Feature",
  "properties": {
    "addr:full":"Calle de Cisnes (los), 24 Aguilar Campoo Palencia 34800",
    "addr:housenumber":"24",
    "addr:postcode":"34800",
    "addr:street":"Calle De Cisnes Los",
    "iso:country":"ES",
    "sg:address":"Calle de Cisnes (los), 24",
    "sg:city":"Aguilar Campoo",
    "sg:orig_category":"Comunidades Religiosas",
    "sg:phone":"+34 979 12 20 04",
    "sg:postcode":"34800",
    "sg:province":"Palencia",
    "wof:name":"Religiosas Nuestra Se\u00d1ora De La Compasio",
    "wof:placetype":"venue"
},
  "geometry": {"coordinates":[-4.2590165138,42.7977790833],"type":"Point"}
}