{
  "type": "Feature",
  "properties": {
    "iso:country":"ES",
    "sg:address":"Calle de Carretas, 21",
    "sg:city":"Villaviciosa Odon",
    "sg:orig_category":"Molduras, Junquillos, Listones Y Molduras Perforadas",
    "sg:phone":"+34 916 16 04 10",
    "sg:postcode":"28670",
    "sg:province":"Madrid",
    "wof:name":"Bravo Luna Marcelina",
    "wof:placetype":"venue"
},
  "geometry": {"coordinates":[-3.9018566608,40.3579063416],"type":"Point"}
}