{
  "type": "Feature",
  "properties": {
    "addr:full":"Carrer de Major, 73 Montcada Centre Barcelona 08110",
    "addr:housenumber":"73",
    "addr:postcode":"08110",
    "addr:street":"Carrer De Major",
    "iso:country":"ES",
    "sg:address":"Carrer de Major, 73",
    "sg:city":"Montcada Centre",
    "sg:orig_category":"Mercer\u00cda, Lencer\u00cda (al Por Menor)",
    "sg:phone":"+34 935 64 14 25",
    "sg:postcode":"08110",
    "sg:province":"Barcelona",
    "wof:name":"Ragull Gener Francisco",
    "wof:placetype":"venue"
},
  "geometry": {"coordinates":[2.1871469021,41.4839439392],"type":"Point"}
}