{
  "type": "Feature",
  "properties": {
    "addr:full":"Calle de Alcantara, 62 Madrid Madrid 28006",
    "addr:housenumber":"62",
    "addr:postcode":"madrid;28006",
    "addr:street":"Calle De Alcantara",
    "iso:country":"ES",
    "sg:address":"Calle de Alcantara, 62",
    "sg:city":"Madrid",
    "sg:orig_category":"Institutos De Belleza",
    "sg:phone":"+34 914 02 91 28",
    "sg:postcode":"28006",
    "sg:province":"Madrid",
    "wof:name":"Hernan Martinez Maria Dolores",
    "wof:placetype":"venue"
},
  "geometry": {"coordinates":[-3.6735270023,40.431427002],"type":"Point"}
}