{
  "type": "Feature",
  "properties": {
    "addr:full":"Altzutzate, 12 Huarte Navarra 31620",
    "addr:housenumber":"12",
    "addr:postcode":"31620",
    "addr:street":"Altzutzate;Navarra",
    "iso:country":"ES",
    "sg:address":"Altzutzate, 12",
    "sg:city":"Huarte",
    "sg:orig_category":"Metales (labores, Pulido)",
    "sg:phone":"+34 948 33 11 13",
    "sg:postcode":"31620",
    "sg:province":"Navarra",
    "wof:name":"Uriso S.l.",
    "wof:placetype":"venue"
},
  "geometry": {"coordinates":[-1.6007269621,42.8265075684],"type":"Point"}
}