{
  "type": "Feature",
  "properties": {
    "addr:full":"Plaz Miguel Angel Loren Mendez, 4 Estepona M\u00e1laga 29680",
    "addr:housenumber":"4",
    "addr:postcode":"29680",
    "addr:street":"Loren Mendez",
    "iso:country":"ES",
    "sg:address":"Plaz Miguel Angel Loren Mendez, 4",
    "sg:city":"Estepona",
    "sg:orig_category":"Inmobiliaria (agencias)",
    "sg:phone":"+34 952 79 79 27",
    "sg:postcode":"29680",
    "sg:province":"M\u00e1laga",
    "wof:name":"Lihonalenotre S.l.",
    "wof:placetype":"venue"
},
  "geometry": {"coordinates":[-5.1500940323,36.4232597351],"type":"Point"}
}