{
  "type": "Feature",
  "properties": {
    "iso:country":"ES",
    "sg:address":"Calle de Doctor Requejo, 32",
    "sg:city":"Sotoserrano",
    "sg:orig_category":"Frutas Y Legumbres Frescas (al Por Mayor)",
    "sg:phone":"+34 923 42 21 34",
    "sg:postcode":"37657",
    "sg:province":"Salamanca",
    "wof:name":"Sda.coop.romero Sotoserrano",
    "wof:placetype":"venue"
},
  "geometry": {"coordinates":[-6.0346531868,40.4380264282],"type":"Point"}
}