{
  "type": "Feature",
  "properties": {
    "iso:country":"ES",
    "sg:address":"Calle de Monteagudo, 54",
    "sg:city":"Quintanar Rey",
    "sg:orig_category":"Contenedores (mercanc\u00cdas)",
    "sg:phone":"+34 967 49 52 53",
    "sg:postcode":"16220",
    "sg:province":"Cuenca",
    "wof:name":"Escribano Talaya Teodoro",
    "wof:placetype":"venue"
},
  "geometry": {"coordinates":[-1.9287029505,39.3402328491],"type":"Point"}
}