{
  "type": "Feature",
  "properties": {
    "iso:country":"ES",
    "sg:address":"Rua Salamanca, 12",
    "sg:city":"Vigo",
    "sg:orig_category":"Congelados: Productos Alimentarios (al Por Menor)",
    "sg:phone":"+34 986 41 62 37",
    "sg:postcode":"36211",
    "sg:province":"Pontevedra",
    "wof:name":"Hiperxel S. L.",
    "wof:placetype":"venue"
},
  "geometry": {"coordinates":[-8.7275447845,42.2229385376],"type":"Point"}
}