{
  "type": "Feature",
  "properties": {
    "addr:full":"Plaz El Marques, 3 Balmaseda Vizcaya 48800",
    "addr:housenumber":"3",
    "addr:postcode":"48800",
    "iso:country":"ES",
    "sg:address":"Plaz El Marques, 3",
    "sg:city":"Balmaseda",
    "sg:orig_category":"Peluqueros: De Se\u00d1oras",
    "sg:phone":"+34 946 80 02 57",
    "sg:postcode":"48800",
    "sg:province":"Vizcaya",
    "wof:name":"Davila Artigas Lorena",
    "wof:placetype":"venue"
},
  "geometry": {"coordinates":[-3.1923379898,43.1956977844],"type":"Point"}
}