{
  "type": "Feature",
  "properties": {
    "iso:country":"ES",
    "sg:address":"Av Llibertat, 127",
    "sg:city":"Elche",
    "sg:orig_category":"Promotores Constructores",
    "sg:phone":"+34 965 43 64 08",
    "sg:postcode":"03201",
    "sg:province":"Alicante",
    "wof:name":"Construcciones Loguey S.l.",
    "wof:placetype":"venue"
},
  "geometry": {"coordinates":[-0.7131429911,38.2635231018],"type":"Point"}
}