{
  "type": "Feature",
  "properties": {
    "addr:full":"Avda Albufera, 145 Madrid Madrid 28038",
    "addr:housenumber":"145",
    "addr:postcode":"28038",
    "addr:street":"Avda Albufera",
    "iso:country":"ES",
    "sg:address":"Avda Albufera, 145",
    "sg:city":"Madrid",
    "sg:orig_category":"Higiene, Belleza: Art\u00cdculos (al Por Menor)",
    "sg:phone":"+34 914 78 38 82",
    "sg:postcode":"28038",
    "sg:province":"Madrid",
    "wof:name":"Tmt Stilistas S.l.",
    "wof:placetype":"venue"
},
  "geometry": {"coordinates":[-3.6577429771,40.3924407959],"type":"Point"}
}