{
  "type": "Feature",
  "properties": {
    "iso:country":"ES",
    "sg:address":"Pol Atalayas, S/n",
    "sg:city":"Alacant",
    "sg:orig_category":"Distribuci\u00d3n De Petr\u00d3leo Y Derivados",
    "sg:phone":"+34 965 10 58 60",
    "sg:postcode":"03006",
    "sg:province":"Alicante",
    "wof:name":"Alicombus S.l.",
    "wof:placetype":"venue"
},
  "geometry": {"coordinates":[-0.573071301,38.367855072],"type":"Point"}
}