{
  "type": "Feature",
  "properties": {
    "iso:country":"ES",
    "sg:address":"Pase Andalucia (de), 38",
    "sg:city":"Carde\u00f1a",
    "sg:orig_category":"Distribuci\u00d3n De Petr\u00d3leo Y Derivados",
    "sg:phone":"+34 957 17 40 03",
    "sg:postcode":"14445",
    "sg:province":"C\u00f3rdoba",
    "wof:name":"Redondo Cachinero Miguel",
    "wof:placetype":"venue"
},
  "geometry": {"coordinates":[-4.323846817,38.268825531],"type":"Point"}
}