{
  "type": "Feature",
  "properties": {
    "addr:full":"Plaz Espa\u00d1a, 1 Berrocalejo C\u00e1ceres 10392",
    "addr:housenumber":"1",
    "addr:postcode":"10392",
    "addr:street":"Plaz Espan\u0303A;Ca\u0301Ceres",
    "iso:country":"ES",
    "sg:address":"Plaz Espa\u00d1a, 1",
    "sg:city":"Berrocalejo",
    "sg:orig_category":"Administraciones Regionales, Departamentales Y Locales",
    "sg:phone":"+34 927 57 75 64",
    "sg:postcode":"10392",
    "sg:province":"C\u00e1ceres",
    "wof:name":"Ayuntamiento De Berrocalejo",
    "wof:placetype":"venue"
},
  "geometry": {"coordinates":[-5.3433690071,39.8655090332],"type":"Point"}
}