{
  "type": "Feature",
  "properties": {
    "iso:country":"ES",
    "sg:address":"Carr Concepcion, La, 10",
    "sg:city":"Eliana",
    "sg:orig_category":"Asociaciones Humanitarias, De Cooperaci\u00d3n, De Acci\u00d3n Social",
    "sg:phone":"+34 962 74 26 39",
    "sg:postcode":"46183",
    "sg:province":"Valencia",
    "wof:name":"Helpoup S.l.",
    "wof:placetype":"venue"
},
  "geometry": {"coordinates":[-0.528208971,39.5667457581],"type":"Point"}
}