{
  "type": "Feature",
  "properties": {
    "iso:country":"ES",
    "sg:address":"A Igrexa, S/n",
    "sg:city":"Iglesia",
    "sg:orig_category":"Guarder\u00cdas",
    "sg:phone":"+34 986 52 45 68",
    "sg:postcode":"36628",
    "sg:province":"Pontevedra",
    "wof:name":"Escuela De Educacion Infantil De Tremoedo",
    "wof:placetype":"venue"
},
  "geometry": {"coordinates":[-7.6025080681,43.6471633911],"type":"Point"}
}