{
  "type": "Feature",
  "properties": {
    "iso:country":"ES",
    "sg:address":"Carrer de Sants, 91",
    "sg:city":"Barcelona",
    "sg:orig_category":"Ropa Para Ni\u00d1os (al Por Menor)",
    "sg:phone":"+34 933 31 01 96",
    "sg:postcode":"08014",
    "sg:province":"Barcelona",
    "wof:name":"Brauinver S.l.",
    "wof:placetype":"venue"
},
  "geometry": {"coordinates":[2.1360480785,41.3753356934],"type":"Point"}
}