{
  "type": "Feature",
  "properties": {
    "addr:full":"Disseminat, S/n Bigues Barcelona 08415",
    "addr:housenumber":"/ n",
    "addr:postcode":"08415",
    "addr:street":"Disseminat S",
    "iso:country":"ES",
    "sg:address":"Disseminat, S/n",
    "sg:city":"Bigues",
    "sg:orig_category":"Explotaci\u00d3n De Bosques",
    "sg:phone":"+34 938 65 89 07",
    "sg:postcode":"08415",
    "sg:province":"Barcelona",
    "wof:name":"Maspons Jonqueres Francisco",
    "wof:placetype":"venue"
},
  "geometry": {"coordinates":[2.2144351006,41.67345047],"type":"Point"}
}