{
  "type": "Feature",
  "properties": {
    "addr:full":"Carrer de Esports, 8 S. Just Desvern Barcelona 08960",
    "addr:housenumber":"8",
    "addr:postcode":"08960",
    "addr:street":"Carrer De Esports",
    "iso:country":"ES",
    "sg:address":"Carrer de Esports, 8",
    "sg:city":"S. Just Desvern",
    "sg:orig_category":"Rectificaci\u00d3n, Mecanizado, Fresado",
    "sg:phone":"+34 934 73 28 61",
    "sg:postcode":"08960",
    "sg:province":"Barcelona",
    "wof:name":"Maluber S.a.",
    "wof:placetype":"venue"
},
  "geometry": {"coordinates":[2.0681641102,41.3820495605],"type":"Point"}
}