{
  "type": "Feature",
  "properties": {
    "addr:full":"Calle de Ronda, 17 Rincon Victoria M\u00e1laga 29730",
    "addr:housenumber":"17",
    "addr:postcode":"29730",
    "addr:street":"Calle De Ronda;Ma\u0301Laga",
    "iso:country":"ES",
    "sg:address":"Calle de Ronda, 17",
    "sg:city":"Rincon Victoria",
    "sg:orig_category":"Quiropr\u00c1cticos",
    "sg:phone":"+34 952 97 00 79",
    "sg:postcode":"29730",
    "sg:province":"M\u00e1laga",
    "wof:name":"Carrillo Beltran Francisco Javier",
    "wof:placetype":"venue"
},
  "geometry": {"coordinates":[-4.2807641029,36.714641571],"type":"Point"}
}