{
  "type": "Feature",
  "properties": {
    "addr:full":"Calle de Doctor Manuel Bernal, S/n Cehegin Murcia 30430",
    "addr:housenumber":"s",
    "addr:postcode":"30430",
    "addr:street":"Calle De Doctor Manuel Bernal;/ N",
    "iso:country":"ES",
    "sg:address":"Calle de Doctor Manuel Bernal, S/n",
    "sg:city":"Cehegin",
    "sg:orig_category":"Fabricaci\u00d3n De Juegos Y Juguetes",
    "sg:phone":"+34 968 74 09 16",
    "sg:postcode":"30430",
    "sg:province":"Murcia",
    "wof:name":"Donafer S.l.",
    "wof:placetype":"venue"
},
  "geometry": {"coordinates":[-1.7980949879,38.0922813416],"type":"Point"}
}