{
  "type": "Feature",
  "properties": {
    "addr:full":"Tv. Cava Baja, 4 La Pola Asturias 33630",
    "addr:postcode":"33630",
    "iso:country":"ES",
    "sg:address":"Tv. Cava Baja, 4",
    "sg:city":"La Pola",
    "sg:orig_category":"Laboratorios Y Cl\u00cdnicas Veterinarias",
    "sg:phone":"+34 985 49 19 29",
    "sg:postcode":"33630",
    "sg:province":"Asturias",
    "wof:name":"Menendez Fernandez Julia Maria",
    "wof:placetype":"venue"
},
  "geometry": {"coordinates":[-5.8283810616,43.159954071],"type":"Point"}
}