{
  "type": "Feature",
  "properties": {
    "iso:country":"ES",
    "sg:address":"Calle de Convento Santa Clara, 12",
    "sg:city":"Valencia",
    "sg:orig_category":"Ropa Para Se\u00d1oras Y Caballeros (al Por Menor)",
    "sg:phone":"+34 963 51 07 35",
    "sg:postcode":"46002",
    "sg:province":"Valencia",
    "wof:name":"Gomez Arteaga Maria",
    "wof:placetype":"venue"
},
  "geometry": {"coordinates":[-0.3765231073,39.4683036804],"type":"Point"}
}