{
  "type": "Feature",
  "properties": {
    "iso:country":"ES",
    "sg:address":"Av President Lluis Companys, 83",
    "sg:city":"Palamos",
    "sg:orig_category":"Muebles",
    "sg:phone":"+34 972 60 14 41",
    "sg:postcode":"17230",
    "sg:province":"Girona",
    "wof:name":"Ekipets C.b",
    "wof:placetype":"venue"
},
  "geometry": {"coordinates":[3.1297409534,41.8509101868],"type":"Point"}
}