{
  "type": "Feature",
  "properties": {
    "addr:full":"Calle de Quintana, 20 Suances Cantabria 39340",
    "addr:housenumber":"20",
    "addr:postcode":"39340",
    "addr:street":"Calle De Quintana",
    "iso:country":"ES",
    "sg:address":"Calle de Quintana, 20",
    "sg:city":"Suances",
    "sg:orig_category":"Empresarios",
    "sg:phone":"+34 942 81 01 03",
    "sg:postcode":"39340",
    "sg:province":"Cantabria",
    "wof:name":"Palacios Trueba Miguel Angel",
    "wof:placetype":"venue"
},
  "geometry": {"coordinates":[-4.0458431244,43.4265327454],"type":"Point"}
}