{
  "type": "Feature",
  "properties": {
    "iso:country":"ES",
    "sg:address":"Calle de Molino, S/n",
    "sg:city":"Portellada",
    "sg:orig_category":"Cooperativas Agr\u00cdcolas",
    "sg:phone":"+34 978 89 48 19",
    "sg:postcode":"44589",
    "sg:province":"Teruel",
    "wof:name":"Cooperativa San Cosme Y San Damian",
    "wof:placetype":"venue"
},
  "geometry": {"coordinates":[0.0555999987,40.8821144104],"type":"Point"}
}