{
  "type": "Feature",
  "properties": {
    "iso:country":"ES",
    "sg:address":"Pase Maritimo, S/n",
    "sg:city":"Torremolinos",
    "sg:orig_category":"Molduras, Junquillos, Listones Y Molduras Perforadas",
    "sg:phone":"+34 952 05 14 38",
    "sg:postcode":"29620",
    "sg:province":"M\u00e1laga",
    "wof:name":"Dosdecoquinas S.l",
    "wof:placetype":"venue"
},
  "geometry": {"coordinates":[-4.4882187843,36.6324462891],"type":"Point"}
}