{
  "type": "Feature",
  "properties": {
    "iso:country":"ES",
    "sg:address":"Calle de Luis Sauquillo, 57",
    "sg:city":"Fuenlabrada",
    "sg:classifiers":[
        {
            "category":"Casinos & Gambling",
            "type":"Entertainment"
        }
    ],
    "sg:phone":"+34 916 15 71 09",
    "sg:postcode":"28944",
    "sg:province":"Madrid",
    "sg:tags":[
        "locale",
        "de",
        "juego"
    ],
    "wof:name":"Fulsa 57 S.a.",
    "wof:placetype":"venue"
},
  "geometry": {"coordinates":[-3.7975919247,40.281703949],"type":"Point"}
}