{
  "type": "Feature",
  "properties": {
    "iso:country":"ES",
    "sg:address":"Calle de Vizconde De Uzqueta, 30",
    "sg:city":"Madrid",
    "sg:orig_category":"Estudios De Grabaci\u00d3n Sonora",
    "sg:phone":"+34 913 20 97 54",
    "sg:postcode":"28042",
    "sg:province":"Madrid",
    "wof:name":"Jl Reina S.l.",
    "wof:placetype":"venue"
},
  "geometry": {"coordinates":[-3.6100819111,40.4531898499],"type":"Point"}
}