{
  "type": "Feature",
  "properties": {
    "addr:full":"Pl Mercat, S/n Sabadell Barcelona 08201",
    "addr:housenumber":"s",
    "addr:postcode":"08201",
    "addr:street":"Pl Mercat;/ N",
    "iso:country":"ES",
    "sg:address":"Pl Mercat, S/n",
    "sg:city":"Sabadell",
    "sg:orig_category":"Poller\u00cda Y Caza (al Por Menor)",
    "sg:phone":"+34 937 26 13 60",
    "sg:postcode":"08201",
    "sg:province":"Barcelona",
    "wof:name":"Espasa Esteve Mateo",
    "wof:placetype":"venue"
},
  "geometry": {"coordinates":[2.1056320667,41.5475692749],"type":"Point"}
}