{
  "type": "Feature",
  "properties": {
    "iso:country":"ES",
    "sg:address":"Calle de Ayala, 17",
    "sg:city":"Madrid",
    "sg:orig_category":"Asesor\u00cdas Y Estudios Financieros",
    "sg:phone":"+34 914 31 74 46",
    "sg:postcode":"28001",
    "sg:province":"Madrid",
    "wof:name":"Gomez Bello Maria Victoria",
    "wof:placetype":"venue"
},
  "geometry": {"coordinates":[-3.6860632896,40.4278335571],"type":"Point"}
}