{
  "type": "Feature",
  "properties": {
    "iso:country":"ES",
    "sg:address":"Pl Quatre Carreteres, 4",
    "sg:city":"Callosa D'en Sarria",
    "sg:orig_category":"Partidos Pol\u00cdticos",
    "sg:phone":"+34 965 88 19 52",
    "sg:postcode":"03510",
    "sg:province":"Alicante",
    "wof:name":"Partido Socialista Obrero Espa\u00f1ol",
    "wof:placetype":"venue"
},
  "geometry": {"coordinates":[-0.1217226014,38.6498184204],"type":"Point"}
}