{
  "type": "Feature",
  "properties": {
    "iso:country":"ES",
    "sg:address":"Calle de Las Trianas, 14",
    "sg:city":"Vitoria-gasteiz",
    "sg:orig_category":"Peluqueros: De Se\u00d1oras",
    "sg:phone":"+34 945 13 94 69",
    "sg:postcode":"01006",
    "sg:province":"\u00c1lava",
    "wof:name":"Gil Barneto Araceli",
    "wof:placetype":"venue"
},
  "geometry": {"coordinates":[-2.6626179218,42.8373603821],"type":"Point"}
}