{
  "type": "Feature",
  "properties": {
    "addr:full":"C/ Jose Ramos, 2 Elche Alicante 03203",
    "addr:housenumber":"2",
    "addr:postcode":"03203",
    "addr:street":"C / Jose Ramos",
    "iso:country":"ES",
    "sg:address":"C/ Jose Ramos, 2",
    "sg:city":"Elche",
    "sg:orig_category":"Propiedad Industrial: Patentes De Inventos, Marcas, Modelos, Dise\u00d1os",
    "sg:phone":"+34 965 42 80 80",
    "sg:postcode":"03203",
    "sg:province":"Alicante",
    "sg:website":"www.regimark.es",
    "wof:name":"Patentes Y Marcas Antonio Pomares S.l.",
    "wof:placetype":"venue"
},
  "geometry": {"coordinates":[-0.6954500079,38.2648124695],"type":"Point"}
}