{
  "type": "Feature",
  "properties": {
    "addr:full":"Calle de Albaicin, S/n Busquistar Granada 18416",
    "addr:housenumber":"s",
    "addr:postcode":"18416",
    "addr:street":"Calle De Albaicin;/ N Busquistar",
    "iso:country":"ES",
    "sg:address":"Calle de Albaicin, S/n",
    "sg:city":"Busquistar",
    "sg:orig_category":"Transportes De Material De Construcci\u00d3n",
    "sg:phone":"+34 958 76 61 22",
    "sg:postcode":"18416",
    "sg:province":"Granada",
    "wof:name":"Ortega Salas Jose",
    "wof:placetype":"venue"
},
  "geometry": {"coordinates":[-3.29637146,36.9384880066],"type":"Point"}
}