{
  "type": "Feature",
  "properties": {
    "iso:country":"ES",
    "sg:address":"Calle de Comunidad De Navarra, 2",
    "sg:city":"Bara\u00f1ain",
    "sg:orig_category":"Asociaciones, Organismos Culturales Y Socioeducativos",
    "sg:phone":"+34 948 18 53 10",
    "sg:postcode":"31010",
    "sg:province":"Navarra",
    "wof:name":"Ayuntamiento De Baranain",
    "wof:placetype":"venue"
},
  "geometry": {"coordinates":[-1.6876430511,42.8015518188],"type":"Point"}
}