{
  "type": "Feature",
  "properties": {
    "addr:full":"Calle de Jacinto Benavente, 4 Torre-pacheco Murcia 30700",
    "addr:housenumber":"4",
    "addr:postcode":"30700",
    "addr:street":"Calle De Jacinto Benavente",
    "iso:country":"ES",
    "sg:address":"Calle de Jacinto Benavente, 4",
    "sg:city":"Torre-pacheco",
    "sg:orig_category":"Electromec\u00c1nica",
    "sg:phone":"+34 968 58 52 65",
    "sg:postcode":"30700",
    "sg:province":"Murcia",
    "wof:name":"Talleres Jose Ramon Gomez S.l.",
    "wof:placetype":"venue"
},
  "geometry": {"coordinates":[-0.9428369999,37.889755249],"type":"Point"}
}