{
  "type": "Feature",
  "properties": {
    "addr:full":"Calle de Goya, 2 Torrijos Toledo 45500",
    "addr:housenumber":"2",
    "addr:postcode":"45500",
    "addr:street":"Calle De Goya",
    "iso:country":"ES",
    "sg:address":"Calle de Goya, 2",
    "sg:city":"Torrijos",
    "sg:orig_category":"Abogados",
    "sg:phone":"+34 925 77 00 10",
    "sg:postcode":"45500",
    "sg:province":"Toledo",
    "wof:name":"Longobardo Sanchez Jesus",
    "wof:placetype":"venue"
},
  "geometry": {"coordinates":[-4.2802004814,39.9812889099],"type":"Point"}
}