{
  "type": "Feature",
  "properties": {
    "addr:full":"Avda Juan Carlos I, 11 Burgo Osma Soria 42300",
    "addr:housenumber":"11",
    "addr:postcode":"42300",
    "addr:street":"Avda Juan Carlos I",
    "iso:country":"ES",
    "sg:address":"Avda Juan Carlos I, 11",
    "sg:city":"Burgo Osma",
    "sg:orig_category":"Alimentaci\u00d3n General (al Por Menor)",
    "sg:phone":"+34 975 34 08 20",
    "sg:postcode":"42300",
    "sg:province":"Soria",
    "wof:name":"Hermanos Garcia Yubero S.l.",
    "wof:placetype":"venue"
},
  "geometry": {"coordinates":[-3.0694720745,41.5878067017],"type":"Point"}
}