{
  "type": "Feature",
  "properties": {
    "addr:full":"San Antonio, 10 Huesca Huesca 22002",
    "addr:housenumber":"10",
    "addr:postcode":"22002",
    "addr:street":"San Antonio",
    "iso:country":"ES",
    "sg:address":"San Antonio, 10",
    "sg:city":"Huesca",
    "sg:orig_category":"Abogados",
    "sg:phone":"+34 974 22 77 51",
    "sg:postcode":"22002",
    "sg:province":"Huesca",
    "wof:name":"Monter Gonzalez Fernando",
    "wof:placetype":"venue"
},
  "geometry": {"coordinates":[-0.4079680145,42.1352996826],"type":"Point"}
}