{
  "type": "Feature",
  "properties": {
    "addr:full":"Calle de San Roque, S/n Villanueva Alcardete Toledo 45810",
    "addr:housenumber":"s",
    "addr:postcode":"45810",
    "addr:street":"Calle De San Roque;/ N",
    "iso:country":"ES",
    "sg:address":"Calle de San Roque, S/n",
    "sg:city":"Villanueva Alcardete",
    "sg:orig_category":"Mec\u00c1nico Del Autom\u00d3vil",
    "sg:phone":"+34 925 16 71 96",
    "sg:postcode":"45810",
    "sg:province":"Toledo",
    "wof:name":"Talleres Manzanero Castillo S.l.",
    "wof:placetype":"venue"
},
  "geometry": {"coordinates":[-3.0191690922,39.6707382202],"type":"Point"}
}