{
  "type": "Feature",
  "properties": {
    "iso:country":"ES",
    "sg:address":"Avda Benito Perez Armas, 4",
    "sg:city":"Santa Cruz De Tenerife",
    "sg:orig_category":"Arquitectos",
    "sg:phone":"+34 922 22 85 85",
    "sg:postcode":"38007",
    "sg:province":"Santa Cruz De Tenerife",
    "wof:name":"Rubiera Diaz-quetcuti Jose Ramon",
    "wof:placetype":"venue"
},
  "geometry": {"coordinates":[-16.2638645172,28.4585170746],"type":"Point"}
}