{
  "type": "Feature",
  "properties": {
    "iso:country":"ES",
    "sg:address":"Carrer de Resseguidora (de La), 20",
    "sg:city":"Mataro",
    "sg:orig_category":"Importaci\u00d3n",
    "sg:phone":"+34 937 41 60 60",
    "sg:postcode":"08302",
    "sg:province":"Barcelona",
    "wof:name":"Apothekamed S.a.",
    "wof:placetype":"venue"
},
  "geometry": {"coordinates":[2.4332249165,41.5330924988],"type":"Point"}
}