{
  "type": "Feature",
  "properties": {
    "addr:full":"Simon Arrieta Plaza, 3 Bergara Guip\u00f9zcoa 20570",
    "addr:housenumber":"3",
    "addr:postcode":"20570",
    "addr:street":"Simon Arrieta Plaza;Guipu\u0300Zcoa",
    "iso:country":"ES",
    "sg:address":"Simon Arrieta Plaza, 3",
    "sg:city":"Bergara",
    "sg:orig_category":"Cl\u00cdnicas Dentales",
    "sg:phone":"+34 943 76 38 54",
    "sg:postcode":"20570",
    "sg:province":"Guip\u00f9zcoa",
    "wof:name":"Caviglia Rey Silvana",
    "wof:placetype":"venue"
},
  "geometry": {"coordinates":[-2.4139580727,43.1192626953],"type":"Point"}
}