{
  "type": "Feature",
  "properties": {
    "iso:country":"ES",
    "sg:address":"Plaz Victoria, 15",
    "sg:city":"Malaga",
    "sg:orig_category":"Esoterismo",
    "sg:phone":"+34 952 26 08 54",
    "sg:postcode":"29012",
    "sg:province":"M\u00e1laga",
    "wof:name":"Gonzalez Madue\u00f1o Erika",
    "wof:placetype":"venue"
},
  "geometry": {"coordinates":[-4.4161138535,36.724067688],"type":"Point"}
}