{
  "type": "Feature",
  "properties": {
    "iso:country":"ES",
    "sg:address":"Calle de Pelayo, 1",
    "sg:city":"Cantalejo",
    "sg:orig_category":"Empresas De Desmonte",
    "sg:phone":"+34 921 52 07 39",
    "sg:postcode":"40320",
    "sg:province":"Segovia",
    "wof:name":"Sanz De Miguel Tomas",
    "wof:placetype":"venue"
},
  "geometry": {"coordinates":[-3.9274671078,41.2608413696],"type":"Point"}
}