{
  "type": "Feature",
  "properties": {
    "iso:country":"ES",
    "sg:address":"Bard Zabal, 192",
    "sg:city":"Linea De La Concepcion",
    "sg:orig_category":"Inmobiliaria (agencias)",
    "sg:phone":"+34 956 64 33 53",
    "sg:postcode":"11300",
    "sg:province":"C\u00e1diz",
    "wof:name":"Excavaciones Y Derribos Rodriguez S.a.",
    "wof:placetype":"venue"
},
  "geometry": {"coordinates":[-5.340939045,36.1683044434],"type":"Point"}
}