{
  "type": "Feature",
  "properties": {
    "iso:country":"ES",
    "sg:address":"Calle de Antonia Diaz, 14",
    "sg:city":"Dos Hermanas",
    "sg:orig_category":"Peleter\u00cdas",
    "sg:phone":"+34 955 67 78 66",
    "sg:postcode":"41700",
    "sg:province":"Sevilla",
    "wof:name":"Aguilar Clerico Jose Joaquin",
    "wof:placetype":"venue"
},
  "geometry": {"coordinates":[-5.9242954254,37.282497406],"type":"Point"}
}