{
  "type": "Feature",
  "properties": {
    "addr:full":"Barr Lurcia, S/n Ajo Cantabria 39170",
    "addr:housenumber":"s / n",
    "addr:postcode":"39170",
    "iso:country":"ES",
    "sg:address":"Barr Lurcia, S/n",
    "sg:city":"Ajo",
    "sg:orig_category":"Molduras, Junquillos, Listones Y Molduras Perforadas",
    "sg:phone":"+34 942 67 07 83",
    "sg:postcode":"39170",
    "sg:province":"Cantabria",
    "wof:name":"Carrera Marco Pedro Luis",
    "wof:placetype":"venue"
},
  "geometry": {"coordinates":[-3.6118149757,43.4858818054],"type":"Point"}
}