{
  "type": "Feature",
  "properties": {
    "iso:country":"ES",
    "sg:address":"Calle de Barrio Gimeno, 16",
    "sg:city":"Burgos",
    "sg:orig_category":"Caf\u00c9s, Bares, Cervecer\u00cdas",
    "sg:phone":"+34 947 26 37 56",
    "sg:postcode":"09001",
    "sg:province":"Burgos",
    "wof:name":"Rodrigo Zorrilla Sancho S.l.",
    "wof:placetype":"venue"
},
  "geometry": {"coordinates":[-3.7025825977,42.3361663818],"type":"Point"}
}