{
  "type": "Feature",
  "properties": {
    "iso:country":"ES",
    "sg:address":"Luga Mercado Central, S/n",
    "sg:city":"Palmas De Gran Canaria",
    "sg:orig_category":"Molduras, Junquillos, Listones Y Molduras Perforadas",
    "sg:phone":"+34 928 24 68 66",
    "sg:postcode":"35006",
    "sg:province":"Las Palmas",
    "wof:name":"Montesdeoca Rodriguez Olivia",
    "wof:placetype":"venue"
},
  "geometry": {"coordinates":[-15.4313497543,28.1309299469],"type":"Point"}
}