{
  "type": "Feature",
  "properties": {
    "iso:country":"ES",
    "sg:address":"Rua Calvo Sotelo, 126",
    "sg:city":"Sarria",
    "sg:orig_category":"Enfermeras: Consultas, Atenci\u00d3n A Domicilio",
    "sg:phone":"+34 982 53 17 79",
    "sg:postcode":"27600",
    "sg:province":"Lugo",
    "wof:name":"Taboada Garcia Maria Carmen",
    "wof:placetype":"venue"
},
  "geometry": {"coordinates":[-7.4101309776,42.7781600952],"type":"Point"}
}