{
  "type": "Feature",
  "properties": {
    "iso:country":"ES",
    "sg:address":"Balneario, S/n",
    "sg:city":"Cortegada",
    "sg:orig_category":"Centros De Educaci\u00d3n Especial",
    "sg:phone":"+34 988 48 31 17",
    "sg:postcode":"32200",
    "sg:province":"Ourense",
    "wof:name":"Colegio Publico Otero Navas",
    "wof:placetype":"venue"
},
  "geometry": {"coordinates":[-8.1733407974,42.2002716064],"type":"Point"}
}