{
  "type": "Feature",
  "properties": {
    "iso:country":"ES",
    "sg:address":"Avda Lerida (de), 7",
    "sg:city":"Monzon",
    "sg:orig_category":"Ense\u00d1anza: Idiomas",
    "sg:phone":"+34 974 40 14 37",
    "sg:postcode":"22400",
    "sg:province":"Huesca",
    "wof:name":"Monzon English Centre S.cv.",
    "wof:placetype":"venue"
},
  "geometry": {"coordinates":[0.1941229999,41.912437439],"type":"Point"}
}