{
  "type": "Feature",
  "properties": {
    "addr:full":"Calle de San Prudencio, 1 Pilar Horadada Alicante 03190",
    "addr:housenumber":"1",
    "addr:postcode":"03190",
    "addr:street":"Calle De San Prudencio",
    "iso:country":"ES",
    "sg:address":"Calle de San Prudencio, 1",
    "sg:city":"Pilar Horadada",
    "sg:orig_category":"Controles De Edificaci\u00d3n (construcci\u00d3n, Seguridad)",
    "sg:phone":"+34 965 35 26 14",
    "sg:postcode":"03190",
    "sg:province":"Alicante",
    "wof:name":"Sayza Horadada Promociones S.l.",
    "wof:placetype":"venue"
},
  "geometry": {"coordinates":[-0.7902129889,37.8678207397],"type":"Point"}
}