{
  "type": "Feature",
  "properties": {
    "iso:country":"ES",
    "sg:address":"Carrer de Amigo, 23",
    "sg:city":"Barcelona",
    "sg:orig_category":"Agencias Y Asesores De Publicidad",
    "sg:phone":"+34 934 14 06 81",
    "sg:postcode":"08021",
    "sg:province":"Barcelona",
    "wof:name":"Beauty Condal S.l.",
    "wof:placetype":"venue"
},
  "geometry": {"coordinates":[2.1451361179,41.3946266174],"type":"Point"}
}