{
  "type": "Feature",
  "properties": {
    "iso:country":"ES",
    "sg:address":"Bda. Torres Blancas, 3",
    "sg:city":"Jerez",
    "sg:orig_category":"Centros Empresariales",
    "sg:phone":"+34 956 34 46 22",
    "sg:postcode":"11405",
    "sg:province":"C\u00e1diz",
    "wof:name":"Lopez Reinado Maria Del Pilar",
    "wof:placetype":"venue"
},
  "geometry": {"coordinates":[-6.1142091751,36.687461853],"type":"Point"}
}