{
  "type": "Feature",
  "properties": {
    "iso:country":"ES",
    "sg:address":"Ctra. Almeria, 25",
    "sg:city":"Ugijar",
    "sg:orig_category":"Molduras, Junquillos, Listones Y Molduras Perforadas",
    "sg:phone":"+34 958 76 71 99",
    "sg:postcode":"18480",
    "sg:province":"Granada",
    "wof:name":"Ruiz Robles Angeles",
    "wof:placetype":"venue"
},
  "geometry": {"coordinates":[-3.0520040989,36.9624252319],"type":"Point"}
}