{
  "type": "Feature",
  "properties": {
    "addr:full":"Calle de Carretera, 47 Rabita Granada 18760",
    "addr:housenumber":"47",
    "addr:postcode":"18760",
    "addr:street":"Calle De Carretera",
    "iso:country":"ES",
    "sg:address":"Calle de Carretera, 47",
    "sg:city":"Rabita",
    "sg:orig_category":"Ingeniero",
    "sg:phone":"+34 958 82 92 18",
    "sg:postcode":"18760",
    "sg:province":"Granada",
    "wof:name":"Navarro Lopez Andres",
    "wof:placetype":"venue"
},
  "geometry": {"coordinates":[-3.1716244221,36.7484817505],"type":"Point"}
}