{
  "type": "Feature",
  "properties": {
    "iso:country":"ES",
    "sg:address":"Avda Dos De Mayo, 5",
    "sg:city":"Leganes",
    "sg:orig_category":"Inform\u00c1tica, Ofim\u00c1tica (estudios, Asesor\u00cda, Ingenier\u00cda, Formaci\u00d3n)",
    "sg:phone":"+34 916 88 23 85",
    "sg:postcode":"28912",
    "sg:province":"Madrid",
    "wof:name":"Rivera Naharro Antonia",
    "wof:placetype":"venue"
},
  "geometry": {"coordinates":[-3.7631869316,40.3347816467],"type":"Point"}
}