{
  "type": "Feature",
  "properties": {
    "iso:country":"ES",
    "sg:address":"Calle de Fray Luis De Granada, 6",
    "sg:city":"Cordoba",
    "sg:orig_category":"M\u00c9dicos: Gastroenterolog\u00cda Y Hepatolog\u00cda (aparato Digestivo)",
    "sg:phone":"+34 957 47 35 33",
    "sg:postcode":"14008",
    "sg:province":"C\u00f3rdoba",
    "wof:name":"Altolaguirre Obrero Joaquin",
    "wof:placetype":"venue"
},
  "geometry": {"coordinates":[-4.7845525742,37.8885498047],"type":"Point"}
}