{
  "type": "Feature",
  "properties": {
    "addr:full":"Carr Bilbao, 5 Platja D'aro Girona 17250",
    "addr:housenumber":"5",
    "addr:postcode":"17250",
    "addr:street":"Carr Bilbao",
    "iso:country":"ES",
    "sg:address":"Carr Bilbao, 5",
    "sg:city":"Platja D'aro",
    "sg:orig_category":"Administradores De Bienes Y Delegados De Comunidades De Propietarios",
    "sg:phone":"+34 972 81 93 38",
    "sg:postcode":"17250",
    "sg:province":"Girona",
    "wof:name":"A.d. Assessoria I Gestions S. L.",
    "wof:placetype":"venue"
},
  "geometry": {"coordinates":[3.061851263,41.8102455139],"type":"Point"}
}