{
  "type": "Feature",
  "properties": {
    "addr:full":"Avda De Bara\u00f1ain, 27 Iru\u00f1a Navarra 31008",
    "addr:housenumber":"27",
    "addr:postcode":"31008",
    "addr:street":"Avda De Baran\u0303Ain",
    "iso:country":"ES",
    "sg:address":"Avda De Bara\u00f1ain, 27",
    "sg:city":"Iru\u00f1a",
    "sg:orig_category":"Asesor\u00cda Sobre Comunicaci\u00d3n De Empresas",
    "sg:phone":"+34 948 25 27 39",
    "sg:postcode":"31008",
    "sg:province":"Navarra",
    "wof:name":"Cilveti Lecumberri Francisco Javier",
    "wof:placetype":"venue"
},
  "geometry": {"coordinates":[-1.6628500223,42.8106231689],"type":"Point"}
}