{
  "type": "Feature",
  "properties": {
    "addr:full":"Calle de Mariano Gonzalez Bartolome, 6 Riaza Segovia 40500",
    "addr:housenumber":"6",
    "addr:postcode":"40500",
    "addr:street":"Calle De Mariano Gonzalez Bartolome",
    "iso:country":"ES",
    "sg:address":"Calle de Mariano Gonzalez Bartolome, 6",
    "sg:city":"Riaza",
    "sg:orig_category":"Art\u00cdculos De Regalo (al Por Menor)",
    "sg:phone":"+34 921 55 02 88",
    "sg:postcode":"40500",
    "sg:province":"Segovia",
    "wof:name":"Martin Arranz Agapito",
    "wof:placetype":"venue"
},
  "geometry": {"coordinates":[-3.4820048809,41.2783088684],"type":"Point"}
}