{
  "type": "Feature",
  "properties": {
    "addr:full":"Calle de Pinos Alta, 78 Madrid Madrid 28029",
    "addr:housenumber":"78",
    "addr:postcode":"madrid;28029",
    "addr:street":"Calle De Pinos Alta",
    "iso:country":"ES",
    "sg:address":"Calle de Pinos Alta, 78",
    "sg:city":"Madrid",
    "sg:orig_category":"Alimentaci\u00d3n General (al Por Menor)",
    "sg:phone":"+34 913 14 66 95",
    "sg:postcode":"28029",
    "sg:province":"Madrid",
    "wof:name":"Ara  Rosam",
    "wof:placetype":"venue"
},
  "geometry": {"coordinates":[-3.6992692947,40.469379425],"type":"Point"}
}