{
  "type": "Feature",
  "properties": {
    "addr:full":"Calle de San Cipriano, 14 Madrid Madrid 28032",
    "addr:housenumber":"14",
    "addr:postcode":"madrid;28032",
    "addr:street":"Calle De San",
    "iso:country":"ES",
    "sg:address":"Calle de San Cipriano, 14",
    "sg:city":"Madrid",
    "sg:orig_category":"Carnicer\u00cdas, Carnicer\u00cdas",
    "sg:phone":"+34 913 71 91 37",
    "sg:postcode":"28032",
    "sg:province":"Madrid",
    "wof:name":"Ripa Solano Angel",
    "wof:placetype":"venue"
},
  "geometry": {"coordinates":[-3.6079521179,40.4040985107],"type":"Point"}
}