{
  "type": "Feature",
  "properties": {
    "addr:full":"Calle de Cruz De Piedra, 20 Santa Cruz De Mudela Ciudad Real 13730",
    "addr:housenumber":"20",
    "addr:postcode":"13730",
    "addr:street":"Calle De Cruz De Piedra",
    "iso:country":"ES",
    "sg:address":"Calle de Cruz De Piedra, 20",
    "sg:city":"Santa Cruz De Mudela",
    "sg:orig_category":"Frutas, Legumbres Frescas Y Tempranas (al Por Menor)",
    "sg:phone":"+34 926 34 22 97",
    "sg:postcode":"13730",
    "sg:province":"Ciudad Real",
    "wof:name":"Marin Laguna Fausto",
    "wof:placetype":"venue"
},
  "geometry": {"coordinates":[-3.465662241,38.6405448914],"type":"Point"}
}