{
  "type": "Feature",
  "properties": {
    "iso:country":"ES",
    "sg:address":"Calle de Mas Y Prat, 23",
    "sg:city":"Ecija",
    "sg:orig_category":"Electrodom\u00c9sticos (al Por Menor)",
    "sg:phone":"+34 954 83 04 28",
    "sg:postcode":"41400",
    "sg:province":"Sevilla",
    "wof:name":"Viuda De Campoy S.l",
    "wof:placetype":"venue"
},
  "geometry": {"coordinates":[-5.0803222656,37.5419845581],"type":"Point"}
}