{
  "type": "Feature",
  "properties": {
    "iso:country":"ES",
    "sg:address":"Calle de Enrique Segura Ota\u00d1o, 11",
    "sg:city":"Badajoz",
    "sg:orig_category":"M\u00c9dicos: Estomatolog\u00cda",
    "sg:phone":"+34 924 24 91 19",
    "sg:postcode":"06004",
    "sg:province":"Badajoz",
    "wof:name":"Paz Sanchez Inocencio",
    "wof:placetype":"venue"
},
  "geometry": {"coordinates":[-6.9723463058,38.8730773926],"type":"Point"}
}