{
  "type": "Feature",
  "properties": {
    "addr:full":"Calle de Monte Carmelo, 12 Zaragoza Zaragoza 50010",
    "addr:housenumber":"12",
    "addr:postcode":"50010",
    "addr:street":"Calle De Monte Carmelo",
    "iso:country":"ES",
    "sg:address":"Calle de Monte Carmelo, 12",
    "sg:city":"Zaragoza",
    "sg:orig_category":"Contenedores (mercanc\u00cdas)",
    "sg:phone":"+34 976 34 51 30",
    "sg:postcode":"50010",
    "sg:province":"Zaragoza",
    "wof:name":"Transportes Ontiveros Kosyak S.l.",
    "wof:placetype":"venue"
},
  "geometry": {"coordinates":[-0.9006999731,41.6559295654],"type":"Point"}
}