{
  "type": "Feature",
  "properties": {
    "addr:full":"Ctra. Girona Palamos, Km. 0017,0 Cor\u00e7a Girona 17121",
    "addr:postcode":"17121",
    "addr:street":"Ctra. Girona Palamos Km. 0017,0 Corc\u0327A",
    "iso:country":"ES",
    "sg:address":"Ctra. Girona Palamos, Km. 0017,0",
    "sg:city":"Cor\u00e7a",
    "sg:orig_category":"Molduras, Junquillos, Listones Y Molduras Perforadas",
    "sg:phone":"+34 972 63 07 89",
    "sg:postcode":"17121",
    "sg:province":"Girona",
    "wof:name":"Balta Pont Joan Ramon",
    "wof:placetype":"venue"
},
  "geometry": {"coordinates":[3.0151700974,41.9888916016],"type":"Point"}
}