{
  "type": "Feature",
  "properties": {
    "iso:country":"ES",
    "sg:address":"Rua Xelmirez (de), 18",
    "sg:city":"Santiago De Compostela",
    "sg:orig_category":"Alimentaci\u00d3n General (al Por Menor)",
    "sg:phone":"+34 981 58 05 31",
    "sg:postcode":"15704",
    "sg:province":"La Coru\u00f1a",
    "wof:name":"Iglesias Sar Jose",
    "wof:placetype":"venue"
},
  "geometry": {"coordinates":[-8.5429868698,42.8795585632],"type":"Point"}
}