{
  "type": "Feature",
  "properties": {
    "iso:country":"ES",
    "sg:address":"Jose Lasa Etorbidea, 3",
    "sg:city":"Lazkao",
    "sg:orig_category":"Bisuter\u00cda, Joyer\u00cda, Relojer\u00cda (al Por Menor)",
    "sg:phone":"+34 943 16 08 30",
    "sg:postcode":"20210",
    "sg:province":"Guip\u00f9zcoa",
    "wof:name":"Hernandez Agra Manuel",
    "wof:placetype":"venue"
},
  "geometry": {"coordinates":[-2.1847195625,43.0324783325],"type":"Point"}
}