{
  "type": "Feature",
  "properties": {
    "iso:country":"ES",
    "sg:address":"Pedrera, 2",
    "sg:city":"Montferrer",
    "sg:orig_category":"Producci\u00d3n, Venta De Productos De Agricultura Biol\u00d3gica",
    "sg:phone":"+34 973 35 13 44",
    "sg:postcode":"25711",
    "sg:province":"Lleida",
    "wof:name":"Canut Tuca Domingo",
    "wof:placetype":"venue"
},
  "geometry": {"coordinates":[1.4289679527,42.341506958],"type":"Point"}
}