{
  "type": "Feature",
  "properties": {
    "addr:full":"Carr Del Trinquet De Gomis, 18 Ontinyent Valencia 46870",
    "addr:housenumber":"18",
    "addr:postcode":"46870",
    "addr:street":"Carr Del Trinquet De Gomis",
    "iso:country":"ES",
    "sg:address":"Carr Del Trinquet De Gomis, 18",
    "sg:city":"Ontinyent",
    "sg:classifiers":[
        {
            "category":"Government",
            "subcategory":"Post Office",
            "type":"Public Place"
        }
    ],
    "sg:phone":"+34 962 91 14 39",
    "sg:postcode":"46870",
    "sg:province":"Valencia",
    "sg:tags":[
        "de",
        "yoga",
        "clases"
    ],
    "wof:name":"Cytam",
    "wof:placetype":"venue"
},
  "geometry": {"coordinates":[-0.6049200296,38.8242874146],"type":"Point"}
}