{
  "type": "Feature",
  "properties": {
    "iso:country":"ES",
    "sg:address":"Carrer de Ramon Sala Sa\u00c7ala, 5",
    "sg:city":"Vic",
    "sg:orig_category":"Peluquer\u00cdas, Peluquer\u00cda Mixta",
    "sg:phone":"+34 938 89 19 35",
    "sg:postcode":"08500",
    "sg:province":"Barcelona",
    "wof:name":"Vilamajor Casellas Montserrat",
    "wof:placetype":"venue"
},
  "geometry": {"coordinates":[2.259098053,41.9356002808],"type":"Point"}
}