{
  "type": "Feature",
  "properties": {
    "addr:full":"Cmno Puerto Espindola, 3 Quinta Zoca Santa Cruz De Tenerife 38720",
    "addr:housenumber":"3",
    "addr:postcode":"38720",
    "addr:street":"Cmno Puerto Espindola",
    "iso:country":"ES",
    "sg:address":"Cmno Puerto Espindola, 3",
    "sg:city":"Quinta Zoca",
    "sg:orig_category":"Contenedores (mercanc\u00cdas)",
    "sg:phone":"+34 922 45 16 53",
    "sg:postcode":"38720",
    "sg:province":"Santa Cruz De Tenerife",
    "wof:name":"Hofecon S.l.",
    "wof:placetype":"venue"
},
  "geometry": {"coordinates":[-17.7735347748,28.8032951355],"type":"Point"}
}