{
  "type": "Feature",
  "properties": {
    "addr:full":"Calle de Merandilla, 61 Benaguasil Valencia 46180",
    "addr:housenumber":"61",
    "addr:postcode":"46180",
    "addr:street":"Calle De Merandilla",
    "iso:country":"ES",
    "sg:address":"Calle de Merandilla, 61",
    "sg:city":"Benaguasil",
    "sg:orig_category":"Promotores Constructores",
    "sg:phone":"+34 962 73 80 47",
    "sg:postcode":"46180",
    "sg:province":"Valencia",
    "wof:name":"Nova Consnaves S.l.l.",
    "wof:placetype":"venue"
},
  "geometry": {"coordinates":[-0.5869719982,39.5990142822],"type":"Point"}
}