{
  "type": "Feature",
  "properties": {
    "addr:full":"Calle de Se\u00d1or De La Expiracion, S/n Lanjaron Granada 18420",
    "addr:housenumber":"s",
    "addr:postcode":"18420",
    "addr:street":"Calle De Sen\u0303Or De La Expiracion;/ N",
    "iso:country":"ES",
    "sg:address":"Calle de Se\u00d1or De La Expiracion, S/n",
    "sg:city":"Lanjaron",
    "sg:orig_category":"Empresas De Carpinter\u00cda De Madera",
    "sg:phone":"+34 958 77 00 92",
    "sg:postcode":"18420",
    "sg:province":"Granada",
    "wof:name":"Carpinteria Mingorance Y Lopez S.l.",
    "wof:placetype":"venue"
},
  "geometry": {"coordinates":[-3.4785439968,36.9183692932],"type":"Point"}
}