{
  "type": "Feature",
  "properties": {
    "iso:country":"ES",
    "sg:address":"Calle de Doctor Merida Perez, S/n",
    "sg:city":"Ba\u00d1eza",
    "sg:orig_category":"Pompas F\u00danebres, Inhumaciones Y Cremaciones",
    "sg:phone":"+34 987 64 38 21",
    "sg:postcode":"24750",
    "sg:province":"Le\u00f3n",
    "wof:name":"Gabriel Garcia Lucio",
    "wof:placetype":"venue"
},
  "geometry": {"coordinates":[-5.9137639999,42.2951583862],"type":"Point"}
}