{
  "type": "Feature",
  "properties": {
    "addr:full":"Ctra. Belalcazar, Km. 0000,7 Monterrubio Serena Badajoz 06427",
    "addr:postcode":"06427",
    "addr:street":"Ctra. Belalcazar Km. 0000,7 Monterrubio Serena",
    "iso:country":"ES",
    "sg:address":"Ctra. Belalcazar, Km. 0000,7",
    "sg:city":"Monterrubio Serena",
    "sg:orig_category":"Negocio De Materiales De Construcci\u00d3n",
    "sg:phone":"+34 924 61 03 35",
    "sg:postcode":"06427",
    "sg:province":"Badajoz",
    "wof:name":"Azulejos Y Pavimentos Monterrubios S.l.",
    "wof:placetype":"venue"
},
  "geometry": {"coordinates":[-6.9702835083,38.8785972595],"type":"Point"}
}