{
  "type": "Feature",
  "properties": {
    "iso:country":"ES",
    "sg:address":"Calle de Crucifijo, 11",
    "sg:city":"Cordoba",
    "sg:orig_category":"Bisuter\u00cda, Joyer\u00cda, Relojer\u00cda (al Por Menor)",
    "sg:phone":"+34 957 49 14 91",
    "sg:postcode":"14002",
    "sg:province":"C\u00f3rdoba",
    "wof:name":"Dian Byor S.l.",
    "wof:placetype":"venue"
},
  "geometry": {"coordinates":[-4.7688388824,37.8868293762],"type":"Point"}
}