{
  "type": "Feature",
  "properties": {
    "iso:country":"ES",
    "sg:address":"Pase Florida, S/n",
    "sg:city":"Madrid",
    "sg:orig_category":"Centros Comerciales Y Grandes Tiendas",
    "sg:phone":"+34 917 58 00 40",
    "sg:postcode":"28008",
    "sg:province":"Madrid",
    "wof:name":"Comunidad De Usuarios Centro Comercial Y Ocio Principe Pio",
    "wof:placetype":"venue"
},
  "geometry": {"coordinates":[-3.7212738991,40.4230766296],"type":"Point"}
}