{
  "type": "Feature",
  "properties": {
    "addr:full":"Calle de Palomares (de Los), 20 Algete Madrid 28110",
    "addr:postcode":"28110",
    "addr:street":"Calle De Palomares De Los",
    "iso:country":"ES",
    "sg:address":"Calle de Palomares (de Los), 20",
    "sg:city":"Algete",
    "sg:orig_category":"Oficinas: Suministros Para (fabricaci\u00d3n, Al Por Mayor)",
    "sg:phone":"+34 916 29 07 79",
    "sg:postcode":"28110",
    "sg:province":"Madrid",
    "wof:name":"Dise\u00f1o Grafico Eurodis S.l.",
    "wof:placetype":"venue"
},
  "geometry": {"coordinates":[-3.5004470348,40.5976409912],"type":"Point"}
}