{
  "type": "Feature",
  "properties": {
    "addr:full":"Rua Travesia De Vigo, 48 Roris Pontevedra 36206",
    "addr:housenumber":"48",
    "addr:postcode":"36206",
    "addr:street":"Rua Travesia De Vigo",
    "iso:country":"ES",
    "sg:address":"Rua Travesia De Vigo, 48",
    "sg:city":"Roris",
    "sg:orig_category":"Agencias De Viajes",
    "sg:phone":"+34 986 28 17 86",
    "sg:postcode":"36206",
    "sg:province":"Pontevedra",
    "sg:website":"www.viajeseroski.es",
    "wof:name":"Viajes Eroski S.a.",
    "wof:placetype":"venue"
},
  "geometry": {"coordinates":[-8.7020702362,42.237651825],"type":"Point"}
}