{
  "type": "Feature",
  "properties": {
    "iso:country":"ES",
    "sg:address":"Carrer de Arcadi Balaguer, 77",
    "sg:city":"Castelldefels",
    "sg:orig_category":"Comercio De Piezas De Recambio Y De Accesorios De Veh\u00cdculos, Veh\u00cdculos Industriales",
    "sg:phone":"+34 936 65 82 61",
    "sg:postcode":"08860",
    "sg:province":"Barcelona",
    "wof:name":"Garcia Chaparro Tomas",
    "wof:placetype":"venue"
},
  "geometry": {"coordinates":[1.9817260504,41.2829437256],"type":"Point"}
}