{
  "type": "Feature",
  "properties": {
    "addr:full":"Calle de Nuestra Se\u00d1ora De Bego\u00d1a, 8 Leganes Madrid 28911",
    "addr:housenumber":"8",
    "addr:postcode":"28911",
    "addr:street":"Calle De Nuestra Sen\u0303Ora;Begon\u0303A",
    "iso:country":"ES",
    "sg:address":"Calle de Nuestra Se\u00d1ora De Bego\u00d1a, 8",
    "sg:city":"Leganes",
    "sg:orig_category":"Art\u00cdculos De Decoraci\u00d3n",
    "sg:phone":"+34 916 93 32 81",
    "sg:postcode":"28911",
    "sg:province":"Madrid",
    "wof:name":"Pritex S.a",
    "wof:placetype":"venue"
},
  "geometry": {"coordinates":[-3.7718069553,40.3260536194],"type":"Point"}
}