{
  "type": "Feature",
  "properties": {
    "iso:country":"ES",
    "sg:address":"Trullas, 26",
    "sg:city":"Alginet",
    "sg:orig_category":"T\u00c9cnicos Veterinarios",
    "sg:phone":"+34 961 75 10 78",
    "sg:postcode":"46230",
    "sg:province":"Valencia",
    "wof:name":"Bosch Llobell Maria Fernanda",
    "wof:placetype":"venue"
},
  "geometry": {"coordinates":[-0.4672690034,39.2622184753],"type":"Point"}
}