{
  "type": "Feature",
  "properties": {
    "addr:full":"Calle de Alberca, 7 Soria Soria 42003",
    "addr:housenumber":"7",
    "addr:postcode":"42003",
    "addr:street":"Calle De Alberca",
    "iso:country":"ES",
    "sg:address":"Calle de Alberca, 7",
    "sg:city":"Soria",
    "sg:orig_category":"Peluquer\u00cdas, Peluquer\u00cda Mixta",
    "sg:phone":"+34 975 21 36 03",
    "sg:postcode":"42003",
    "sg:province":"Soria",
    "wof:name":"Peluqueria Y Belleza Mari Carmen S.l.",
    "wof:placetype":"venue"
},
  "geometry": {"coordinates":[-2.4676833153,41.7621765137],"type":"Point"}
}