{
  "type": "Feature",
  "properties": {
    "addr:full":"Carrer de Casp, 21 Barcelona Barcelona 08010",
    "addr:housenumber":"21",
    "addr:postcode":"08010",
    "addr:street":"Carrer De Casp",
    "iso:country":"ES",
    "sg:address":"Carrer de Casp, 21",
    "sg:city":"Barcelona",
    "sg:orig_category":"Agencias Y Asesores De Publicidad",
    "sg:phone":"+34 934 12 58 38",
    "sg:postcode":"08010",
    "sg:province":"Barcelona",
    "wof:name":"Gestion Publicitaria S.a.",
    "wof:placetype":"venue"
},
  "geometry": {"coordinates":[2.1707088947,41.3895568848],"type":"Point"}
}