{
  "type": "Feature",
  "properties": {
    "addr:full":"Carrer de Salauris (de), 28 Vila-seca Tarragona 43480",
    "addr:housenumber":"28",
    "addr:postcode":"43480",
    "addr:street":"Carrer De Salauris De",
    "iso:country":"ES",
    "sg:address":"Carrer de Salauris (de), 28",
    "sg:city":"Vila-seca",
    "sg:orig_category":"Sociedades, Compa\u00d1\u00cdas Aseguradoras",
    "sg:phone":"+34 977 39 22 21",
    "sg:postcode":"43480",
    "sg:province":"Tarragona",
    "wof:name":"Art-tax Gabinete Pericial De Seguros",
    "wof:placetype":"venue"
},
  "geometry": {"coordinates":[1.1487534046,41.109992981],"type":"Point"}
}