{
  "type": "Feature",
  "properties": {
    "iso:country":"ES",
    "sg:address":"Avda Jose Marti, S/n",
    "sg:city":"Santa Cruz De Tenerife",
    "sg:orig_category":"Autob\u00das (explotaci\u00d3n Y Servicios De)",
    "sg:phone":"+34 922 59 64 07",
    "sg:postcode":"38160",
    "sg:province":"Santa Cruz De Tenerife",
    "wof:name":"Transportes Interurbanos De Tenerife S.a.",
    "wof:placetype":"venue"
},
  "geometry": {"coordinates":[-16.23595047,28.4893302917],"type":"Point"}
}