{
  "type": "Feature",
  "properties": {
    "iso:country":"ES",
    "sg:address":"Avgd Veinticinco De Abril, 18",
    "sg:city":"Aldaia",
    "sg:orig_category":"Automatizaci\u00d3n De Procesos Industriales Y De Edificaci\u00d3n (estudios, Instalaci\u00d3n)",
    "sg:phone":"+34 961 51 60 26",
    "sg:postcode":"46960",
    "sg:province":"Valencia",
    "wof:name":"Martinez Rico Jose",
    "wof:placetype":"venue"
},
  "geometry": {"coordinates":[-0.460878998,39.4649238586],"type":"Point"}
}