{
  "type": "Feature",
  "properties": {
    "addr:full":"Rua Galicia (de), 45 Vilalba Lugo 27800",
    "addr:housenumber":"45",
    "addr:postcode":"27800",
    "addr:street":"Rua Galicia De",
    "iso:country":"ES",
    "sg:address":"Rua Galicia (de), 45",
    "sg:city":"Vilalba",
    "sg:orig_category":"Molduras, Junquillos, Listones Y Molduras Perforadas",
    "sg:phone":"+34 982 51 04 99",
    "sg:postcode":"27800",
    "sg:province":"Lugo",
    "wof:name":"Gonzalez Gonzalez Juan Jose",
    "wof:placetype":"venue"
},
  "geometry": {"coordinates":[-7.6812272072,43.2957496643],"type":"Point"}
}