{
  "type": "Feature",
  "properties": {
    "addr:full":"Plza. C. Sotelo, 2 Loja Granada 18300",
    "addr:housenumber":"2 loja",
    "addr:postcode":"18300",
    "addr:street":"C. Sotelo",
    "iso:country":"ES",
    "sg:address":"Plza. C. Sotelo, 2",
    "sg:city":"Loja",
    "sg:orig_category":"Caf\u00c9s, Bares, Cervecer\u00cdas",
    "sg:phone":"+34 958 32 00 04",
    "sg:postcode":"18300",
    "sg:province":"Granada",
    "wof:name":"Cafe Bar Rufino C.b.",
    "wof:placetype":"venue"
},
  "geometry": {"coordinates":[-4.1505270004,37.1690177917],"type":"Point"}
}