{
  "type": "Feature",
  "properties": {
    "addr:full":"Finca El Cerrillo, S/n Navalmoral Mata C\u00e1ceres 10300",
    "addr:housenumber":"s / n",
    "addr:postcode":"10300",
    "addr:street":"Cerrillo;Ca\u0301Ceres",
    "iso:country":"ES",
    "sg:address":"Finca El Cerrillo, S/n",
    "sg:city":"Navalmoral Mata",
    "sg:orig_category":"Agricultores, Agricultores",
    "sg:phone":"+34 927 53 12 09",
    "sg:postcode":"10300",
    "sg:province":"C\u00e1ceres",
    "wof:name":"Artalejo Lopez Victorio",
    "wof:placetype":"venue"
},
  "geometry": {"coordinates":[-6.817340374,39.71692276],"type":"Point"}
}