{
  "type": "Feature",
  "properties": {
    "addr:full":"Calle de Jaime Vicens Vives, 3 Baeza Ja\u00e9n 23440",
    "addr:housenumber":"3",
    "addr:postcode":"23440",
    "addr:street":"Calle De Jaime Vicens Vives",
    "iso:country":"ES",
    "sg:address":"Calle de Jaime Vicens Vives, 3",
    "sg:city":"Baeza",
    "sg:orig_category":"Doctores En Medicina",
    "sg:phone":"+34 953 74 09 37",
    "sg:postcode":"23440",
    "sg:province":"Ja\u00e9n",
    "wof:name":"Arredondo Garrido Juan Bernardo",
    "wof:placetype":"venue"
},
  "geometry": {"coordinates":[-3.4707486629,37.9885520935],"type":"Point"}
}