{
  "type": "Feature",
  "properties": {
    "addr:full":"Cost Pols, 16 Palma Islas Baleares 07003",
    "addr:housenumber":"16",
    "addr:postcode":"07003",
    "addr:street":"Pols",
    "iso:country":"ES",
    "sg:address":"Cost Pols, 16",
    "sg:city":"Palma",
    "sg:orig_category":"Fabricaci\u00d3n, Distribuci\u00d3n De Discos, V\u00cddeodiscos Y Musicassettes",
    "sg:phone":"+34 971 71 33 69",
    "sg:postcode":"07003",
    "sg:province":"Islas Baleares",
    "wof:name":"Tot Classic Palma S.l.",
    "wof:placetype":"venue"
},
  "geometry": {"coordinates":[2.6515700817,39.5728492737],"type":"Point"}
}