{
  "type": "Feature",
  "properties": {
    "iso:country":"ES",
    "sg:address":"O Cruceiro, 8",
    "sg:city":"Cruceiro",
    "sg:orig_category":"Electricidad: Instaladores",
    "sg:phone":"+34 986 74 51 57",
    "sg:postcode":"36990",
    "sg:province":"Pontevedra",
    "wof:name":"Electro-villalonga S.l.",
    "wof:placetype":"venue"
},
  "geometry": {"coordinates":[-8.8619022369,42.4462432861],"type":"Point"}
}