{
  "type": "Feature",
  "properties": {
    "iso:country":"ES",
    "sg:address":"Avda Sinas (as), 44",
    "sg:city":"Sinas",
    "sg:orig_category":"Fabricaci\u00d3n, Reparaci\u00d3n Y Mantenimiento De Construcciones Navales Y Fluviales",
    "sg:phone":"+34 986 55 44 22",
    "sg:postcode":"36620",
    "sg:province":"Pontevedra",
    "wof:name":"Sinas Radionavegacion S.l.",
    "wof:placetype":"venue"
},
  "geometry": {"coordinates":[-8.8285036087,42.5618782043],"type":"Point"}
}