{
  "type": "Feature",
  "properties": {
    "iso:country":"ES",
    "sg:address":"Calle de Mayor, 85",
    "sg:city":"Burgo Ebro",
    "sg:orig_category":"Reposter\u00cdas",
    "sg:phone":"+34 976 10 50 04",
    "sg:postcode":"50730",
    "sg:province":"Zaragoza",
    "wof:name":"Gallego Aguiran Antonio",
    "wof:placetype":"venue"
},
  "geometry": {"coordinates":[-0.7444930077,41.5739974976],"type":"Point"}
}