{
  "type": "Feature",
  "properties": {
    "addr:full":"Carr Mendizabal, 33 Burjassot Valencia 46100",
    "addr:housenumber":"33",
    "addr:postcode":"46100",
    "addr:street":"Carr Mendizabal",
    "iso:country":"ES",
    "sg:address":"Carr Mendizabal, 33",
    "sg:city":"Burjassot",
    "sg:orig_category":"Molduras, Junquillos, Listones Y Molduras Perforadas",
    "sg:phone":"+34 963 64 35 42",
    "sg:postcode":"46100",
    "sg:province":"Valencia",
    "wof:name":"Moya Llorente Ricardo",
    "wof:placetype":"venue"
},
  "geometry": {"coordinates":[-0.4134599864,39.5109214783],"type":"Point"}
}