{
  "type": "Feature",
  "properties": {
    "addr:full":"Ctra. Barcelona De, Km. 1177,0 Torredembarra Tarragona 43830",
    "addr:postcode":"43830",
    "addr:street":"Ctra. Barcelona De Km. 1177,0",
    "iso:country":"ES",
    "sg:address":"Ctra. Barcelona De, Km. 1177,0",
    "sg:city":"Torredembarra",
    "sg:orig_category":"Mec\u00c1nico Del Autom\u00d3vil",
    "sg:phone":"+34 977 64 11 84",
    "sg:postcode":"43830",
    "sg:province":"Tarragona",
    "wof:name":"Casasus Jane Alberto",
    "wof:placetype":"venue"
},
  "geometry": {"coordinates":[1.395424962,41.1436691284],"type":"Point"}
}