{
  "type": "Feature",
  "properties": {
    "addr:full":"Avda Republica De Nicaragua, 14 Viso Del Alcor Sevilla 41520",
    "addr:housenumber":"14",
    "addr:postcode":"41520",
    "addr:street":"Avda Republica De Nicaragua",
    "iso:country":"ES",
    "sg:address":"Avda Republica De Nicaragua, 14",
    "sg:city":"Viso Del Alcor",
    "sg:orig_category":"Promotores Constructores",
    "sg:phone":"+34 955 94 52 78",
    "sg:postcode":"41520",
    "sg:province":"Sevilla",
    "wof:name":"Cooperativa De Viviendas Santa Maria Del Alcor",
    "wof:placetype":"venue"
},
  "geometry": {"coordinates":[-5.7248268127,37.3852462769],"type":"Point"}
}