{
  "type": "Feature",
  "properties": {
    "addr:full":"Ctra Carmona-guadajoz, Km. 0012,0 Guadajoz Sevilla 41339",
    "addr:postcode":"41339",
    "addr:street":"Ctra Carmona-Guadajoz Km. 0012,0",
    "iso:country":"ES",
    "sg:address":"Ctra Carmona-guadajoz, Km. 0012,0",
    "sg:city":"Guadajoz",
    "sg:orig_category":"Panader\u00cdas, Panader\u00cdas",
    "sg:phone":"+34 955 64 57 08",
    "sg:postcode":"41339",
    "sg:province":"Sevilla",
    "wof:name":"Industrias Metropolitanas Del Pan S.l.",
    "wof:placetype":"venue"
},
  "geometry": {"coordinates":[-5.6687679291,37.5800437927],"type":"Point"}
}