{
  "type": "Feature",
  "properties": {
    "addr:full":"Calle de Herrerias (de Las), 2 Tres Cantos Madrid 28760",
    "addr:housenumber":"2",
    "addr:postcode":"28760",
    "addr:street":"Calle De Herrerias De Las",
    "iso:country":"ES",
    "sg:address":"Calle de Herrerias (de Las), 2",
    "sg:city":"Tres Cantos",
    "sg:orig_category":"Quincaller\u00cda (al Por Menor)",
    "sg:phone":"+34 915 21 01 51",
    "sg:postcode":"28760",
    "sg:province":"Madrid",
    "wof:name":"Ferreteria Fuencarral S.l",
    "wof:placetype":"venue"
},
  "geometry": {"coordinates":[-3.7007470131,40.6139144897],"type":"Point"}
}