{
  "type": "Feature",
  "properties": {
    "iso:country":"ES",
    "sg:address":"Pol Ind El Fuerte, 57",
    "sg:city":"Ronda",
    "sg:orig_category":"Fabricaci\u00d3n De Su\u00c9ters Y Chalecos De Punto",
    "sg:phone":"+34 952 16 10 03",
    "sg:postcode":"29400",
    "sg:province":"M\u00e1laga",
    "wof:name":"Bonpunt S.a.",
    "wof:placetype":"venue"
},
  "geometry": {"coordinates":[-5.1662788391,36.7417945862],"type":"Point"}
}