{
  "type": "Feature",
  "properties": {
    "addr:full":"Plaza Salamanca, 20 Coria C\u00e1ceres 10800",
    "addr:housenumber":"20",
    "addr:postcode":"10800",
    "addr:street":"Salamanca;Ca\u0301Ceres",
    "iso:country":"ES",
    "sg:address":"Plaza Salamanca, 20",
    "sg:city":"Coria",
    "sg:orig_category":"Cl\u00cdnicas M\u00c9dicas",
    "sg:phone":"+34 927 50 19 40",
    "sg:postcode":"10800",
    "sg:province":"C\u00e1ceres",
    "wof:name":"Labor-mafer S.l.",
    "wof:placetype":"venue"
},
  "geometry": {"coordinates":[-6.5349988937,39.9900932312],"type":"Point"}
}