{
  "type": "Feature",
  "properties": {
    "iso:country":"ES",
    "sg:address":"Carrer de Doctor Reig, 60",
    "sg:city":"Viladecans",
    "sg:orig_category":"Promotores Constructores",
    "sg:phone":"+34 936 59 11 24",
    "sg:postcode":"08840",
    "sg:province":"Barcelona",
    "wof:name":"Alcanex S.l.",
    "wof:placetype":"venue"
},
  "geometry": {"coordinates":[2.0132992268,41.3192596436],"type":"Point"}
}