{
  "type": "Feature",
  "properties": {
    "addr:full":"Calle de San Pedro Del Barco, 7 Avila \u00c1vila 05003",
    "addr:housenumber":"7",
    "addr:postcode":"05003",
    "addr:street":"Calle De San Pedro Del Barco;A\u0301Vila",
    "iso:country":"ES",
    "sg:address":"Calle de San Pedro Del Barco, 7",
    "sg:city":"Avila",
    "sg:orig_category":"Asesor\u00cdas Y Estudios Financieros",
    "sg:phone":"+34 920 25 66 64",
    "sg:postcode":"05003",
    "sg:province":"\u00c1vila",
    "wof:name":"Jimenez Moreno Miguel Angel",
    "wof:placetype":"venue"
},
  "geometry": {"coordinates":[-4.6913762093,40.6537704468],"type":"Point"}
}