{
  "type": "Feature",
  "properties": {
    "iso:country":"ES",
    "sg:address":"Ctra. Esparraguera A Olesa, Km. 0001,0",
    "sg:city":"Esparreguera",
    "sg:orig_category":"Papel (al Por Mayor)",
    "sg:phone":"+34 937 77 52 46",
    "sg:postcode":"08292",
    "sg:province":"Barcelona",
    "wof:name":"Manipulados Magarola S. L.",
    "wof:placetype":"venue"
},
  "geometry": {"coordinates":[1.867759943,41.5371665955],"type":"Point"}
}