{
  "type": "Feature",
  "properties": {
    "iso:country":"ES",
    "sg:address":"Avgd Blasco Iba\u00d1ez, 108",
    "sg:city":"Almassera",
    "sg:orig_category":"Refiner\u00cdas De Petr\u00d3leo",
    "sg:phone":"+34 961 85 39 40",
    "sg:postcode":"46132",
    "sg:province":"Valencia",
    "wof:name":"Estacion Servicio Almacera S.l.",
    "wof:placetype":"venue"
},
  "geometry": {"coordinates":[-0.3611719906,39.5115203857],"type":"Point"}
}