{
  "type": "Feature",
  "properties": {
    "addr:full":"Carrer de Vilafranca, 35 Barcelona Barcelona 08024",
    "addr:housenumber":"35",
    "addr:postcode":"08024",
    "addr:street":"Carrer De Vilafranca",
    "iso:country":"ES",
    "sg:address":"Carrer de Vilafranca, 35",
    "sg:city":"Barcelona",
    "sg:orig_category":"Albergues",
    "sg:phone":"+34 932 85 31 14",
    "sg:postcode":"08024",
    "sg:province":"Barcelona",
    "wof:name":"Crealogica S.c.p",
    "wof:placetype":"venue"
},
  "geometry": {"coordinates":[2.1557769775,41.4078941345],"type":"Point"}
}