{
  "type": "Feature",
  "properties": {
    "addr:full":"Calle de Veracruz, 28 Castillo Locubin Ja\u00e9n 23670",
    "addr:housenumber":"28",
    "addr:postcode":"23670",
    "addr:street":"Calle De Veracruz;Castillo Locubin Jae\u0301N",
    "iso:country":"ES",
    "sg:address":"Calle de Veracruz, 28",
    "sg:city":"Castillo Locubin",
    "sg:orig_category":"Electrodom\u00c9sticos (al Por Menor)",
    "sg:phone":"+34 953 59 11 00",
    "sg:postcode":"23670",
    "sg:province":"Ja\u00e9n",
    "wof:name":"Castillo Castillo Manuel",
    "wof:placetype":"venue"
},
  "geometry": {"coordinates":[-3.9404060841,37.5277709961],"type":"Point"}
}