{
  "type": "Feature",
  "properties": {
    "iso:country":"ES",
    "sg:address":"Rbla Catalunya, 40",
    "sg:city":"Almacelles",
    "sg:classifiers":[
        {
            "category":"Autos & Motor Vehicles",
            "subcategory":"Automobile Sales",
            "type":"Retail Goods"
        }
    ],
    "sg:phone":"+34 973 74 00 22",
    "sg:postcode":"25100",
    "sg:province":"Lleida",
    "wof:name":"Laplana Arasanz Bienvenido",
    "wof:placetype":"venue"
},
  "geometry": {"coordinates":[0.4440200031,41.7297286987],"type":"Point"}
}