{
  "type": "Feature",
  "properties": {
    "addr:full":"Avda Bahia (la), S/n Algeciras C\u00e1diz 11206",
    "addr:postcode":"11206",
    "addr:street":"Avda Bahia La S / N;Ca\u0301Diz",
    "iso:country":"ES",
    "sg:address":"Avda Bahia (la), S/n",
    "sg:city":"Algeciras",
    "sg:orig_category":"Contenedores (mercanc\u00cdas)",
    "sg:phone":"+34 956 58 76 92",
    "sg:postcode":"11206",
    "sg:province":"C\u00e1diz",
    "wof:name":"Transportes Buitrago Andalucia S.a.",
    "wof:placetype":"venue"
},
  "geometry": {"coordinates":[-5.4710087776,36.1574859619],"type":"Point"}
}