{
  "type": "Feature",
  "properties": {
    "addr:full":"Calle de Obispo Zarranz Y Pueyo, 24 Bejar Salamanca 37700",
    "addr:housenumber":"24",
    "addr:postcode":"37700",
    "addr:street":"Calle De Obispo Zarranz Y Pueyo",
    "iso:country":"ES",
    "sg:address":"Calle de Obispo Zarranz Y Pueyo, 24",
    "sg:city":"Bejar",
    "sg:orig_category":"Autob\u00das (explotaci\u00d3n Y Servicios De)",
    "sg:phone":"+34 923 40 38 74",
    "sg:postcode":"37700",
    "sg:province":"Salamanca",
    "wof:name":"Marcos Elena Jose Luis",
    "wof:placetype":"venue"
},
  "geometry": {"coordinates":[-5.7540597916,40.3857345581],"type":"Point"}
}