{
  "type": "Feature",
  "properties": {
    "addr:full":"Calle de Huerta Nueva, S/n Estepona M\u00e1laga 29680",
    "addr:housenumber":"s / n",
    "addr:postcode":"29680",
    "addr:street":"Calle De Huerta Nueva",
    "iso:country":"ES",
    "sg:address":"Calle de Huerta Nueva, S/n",
    "sg:city":"Estepona",
    "sg:orig_category":"Ense\u00d1anza, Formaci\u00d3n Profesional: Aprendizaje",
    "sg:phone":"+34 952 80 31 50",
    "sg:postcode":"29680",
    "sg:province":"M\u00e1laga",
    "wof:name":"Ayuntamiento De Estepona",
    "wof:placetype":"venue"
},
  "geometry": {"coordinates":[-5.1540374756,36.4227867126],"type":"Point"}
}