{
  "type": "Feature",
  "properties": {
    "iso:country":"ES",
    "sg:address":"Calle de Estudiantes, 4",
    "sg:city":"Madrid",
    "sg:orig_category":"Librer\u00cdas",
    "sg:phone":"+34 915 34 04 97",
    "sg:postcode":"28040",
    "sg:province":"Madrid",
    "wof:name":"Ensayos S.l.",
    "wof:placetype":"venue"
},
  "geometry": {"coordinates":[-3.7123260498,40.4469337463],"type":"Point"}
}