{
  "type": "Feature",
  "properties": {
    "addr:full":"Calle de Iglesia, 9 Valdeverdeja Toledo 45572",
    "addr:housenumber":"9",
    "addr:postcode":"45572",
    "addr:street":"Calle De Iglesia",
    "iso:country":"ES",
    "sg:address":"Calle de Iglesia, 9",
    "sg:city":"Valdeverdeja",
    "sg:orig_category":"Hoteles",
    "sg:phone":"+34 925 45 45 86",
    "sg:postcode":"45572",
    "sg:province":"Toledo",
    "wof:name":"Casa Bermeja Investmen Corp Sucursal En Espa\u00f1a",
    "wof:placetype":"venue"
},
  "geometry": {"coordinates":[-5.2439498901,39.7963981628],"type":"Point"}
}