{
  "type": "Feature",
  "properties": {
    "iso:country":"ES",
    "sg:address":"Carrer de Creu, S/n",
    "sg:city":"S. Just Desvern",
    "sg:orig_category":"Negocio De Madera",
    "sg:phone":"+34 933 71 11 38",
    "sg:postcode":"08960",
    "sg:province":"Barcelona",
    "wof:name":"Hijos De Domingo Sarda Coret S.l.",
    "wof:placetype":"venue"
},
  "geometry": {"coordinates":[2.0789470673,41.3832321167],"type":"Point"}
}