{
  "type": "Feature",
  "properties": {
    "addr:full":"Poeta Joaquin Lobato, 1 Velez-malaga M\u00e1laga 29700",
    "addr:housenumber":"1",
    "addr:postcode":"29700",
    "addr:street":"Poeta Joaquin Lobato",
    "iso:country":"ES",
    "sg:address":"Poeta Joaquin Lobato, 1",
    "sg:city":"Velez-malaga",
    "sg:orig_category":"Electrodom\u00c9sticos (al Por Menor)",
    "sg:phone":"+34 952 50 06 99",
    "sg:postcode":"29700",
    "sg:province":"M\u00e1laga",
    "wof:name":"Recio Ruiz Jose",
    "wof:placetype":"venue"
},
  "geometry": {"coordinates":[-4.1017971039,36.7810630798],"type":"Point"}
}