{
  "type": "Feature",
  "properties": {
    "addr:full":"Ctra. Huelva, S/n Valverde Camino Huelva 21600",
    "addr:housenumber":"s / n",
    "addr:postcode":"21600",
    "addr:street":"Ctra. Huelva;Camino Huelva",
    "iso:country":"ES",
    "sg:address":"Ctra. Huelva, S/n",
    "sg:city":"Valverde Camino",
    "sg:orig_category":"Ebanister\u00cda",
    "sg:phone":"+34 959 50 83 23",
    "sg:postcode":"21600",
    "sg:province":"Huelva",
    "wof:name":"Suarez Marquez Antonio",
    "wof:placetype":"venue"
},
  "geometry": {"coordinates":[-6.7534661293,37.576335907],"type":"Point"}
}