{
  "type": "Feature",
  "properties": {
    "addr:full":"Carr Port Banyuls, 1 Empuriabrava Girona 17487",
    "addr:housenumber":"1",
    "addr:postcode":"17487",
    "addr:street":"Carr Port Banyuls",
    "iso:country":"ES",
    "sg:address":"Carr Port Banyuls, 1",
    "sg:city":"Empuriabrava",
    "sg:orig_category":"Fabricaci\u00d3n, Venta De Productos Base Farmac\u00c9uticos",
    "sg:phone":"+34 972 45 20 95",
    "sg:postcode":"17487",
    "sg:province":"Girona",
    "wof:name":"Menendez De Alvare Rodriguez Mariano",
    "wof:placetype":"venue"
},
  "geometry": {"coordinates":[3.1070549488,42.2568092346],"type":"Point"}
}