{
  "type": "Feature",
  "properties": {
    "iso:country":"ES",
    "sg:address":"Calle de San Roque, 4",
    "sg:city":"Salas De Los Infantes",
    "sg:orig_category":"Ropa Para Caballeros (al Por Menor)",
    "sg:phone":"+34 947 38 07 34",
    "sg:postcode":"09600",
    "sg:province":"Burgos",
    "wof:name":"Cabrito Camarero Pedro Antonio",
    "wof:placetype":"venue"
},
  "geometry": {"coordinates":[-3.2894790173,42.0208206177],"type":"Point"}
}