{
  "type": "Feature",
  "properties": {
    "iso:country":"ES",
    "sg:address":"Avda Paz, 219",
    "sg:city":"Yecla",
    "sg:orig_category":"Tapicer\u00cdas",
    "sg:phone":"+34 968 75 23 17",
    "sg:postcode":"30510",
    "sg:province":"Murcia",
    "sg:website":"www.candelatapizados.com",
    "wof:name":"Candela Navalon Ramon Francisco",
    "wof:placetype":"venue"
},
  "geometry": {"coordinates":[-1.1372890472,38.6116905212],"type":"Point"}
}