{
  "type": "Feature",
  "properties": {
    "addr:full":"Avda Galindez Jesus, 20 Bilbao Vizcaya 48004",
    "addr:housenumber":"20",
    "addr:postcode":"48004",
    "addr:street":"Avda Galindez Jesus",
    "iso:country":"ES",
    "sg:address":"Avda Galindez Jesus, 20",
    "sg:city":"Bilbao",
    "sg:orig_category":"Centros De Educaci\u00d3n Especial",
    "sg:phone":"+34 944 12 84 00",
    "sg:postcode":"48004",
    "sg:province":"Vizcaya",
    "wof:name":"Gobierno Vasco-eusko Jaurlaritza",
    "wof:placetype":"venue"
},
  "geometry": {"coordinates":[-2.9073159695,43.2607307434],"type":"Point"}
}