{
  "type": "Feature",
  "properties": {
    "iso:country":"ES",
    "sg:address":"Cmno Miron, 106",
    "sg:city":"Miron",
    "sg:orig_category":"Art\u00cdculos Funerarios (al Por Menor)",
    "sg:phone":"+34 981 70 13 09",
    "sg:postcode":"15105",
    "sg:province":"La Coru\u00f1a",
    "wof:name":"Pompas Funebres Santa Marta S.l.",
    "wof:placetype":"venue"
},
  "geometry": {"coordinates":[-8.605348587,43.3203735352],"type":"Point"}
}