{
  "type": "Feature",
  "properties": {
    "addr:full":"Carrer de Aribau, 150 Barcelona Barcelona 08036",
    "addr:housenumber":"150",
    "addr:postcode":"08036",
    "addr:street":"Carrer De Aribau",
    "iso:country":"ES",
    "sg:address":"Carrer de Aribau, 150",
    "sg:city":"Barcelona",
    "sg:orig_category":"Marroquiner\u00cda (confecci\u00d3n)",
    "sg:phone":"+34 932 18 18 83",
    "sg:postcode":"08036",
    "sg:province":"Barcelona",
    "wof:name":"Ribe S. A.",
    "wof:placetype":"venue"
},
  "geometry": {"coordinates":[2.1546928883,41.3921089172],"type":"Point"}
}