{
  "type": "Feature",
  "properties": {
    "addr:full":"Plaz Santa Catalina, 1 San Pedro Murcia 30004",
    "addr:housenumber":"1",
    "addr:postcode":"30004",
    "addr:street":"Santa Catalina",
    "iso:country":"ES",
    "sg:address":"Plaz Santa Catalina, 1",
    "sg:city":"San Pedro",
    "sg:orig_category":"Molduras, Junquillos, Listones Y Molduras Perforadas",
    "sg:phone":"+34 968 22 12 12",
    "sg:postcode":"30004",
    "sg:province":"Murcia",
    "wof:name":"Garcia Rabaza Mariano",
    "wof:placetype":"venue"
},
  "geometry": {"coordinates":[-1.131559968,37.9853210449],"type":"Point"}
}