{
  "type": "Feature",
  "properties": {
    "iso:country":"ES",
    "sg:address":"Calle de Valderribas, 53",
    "sg:city":"Madrid",
    "sg:orig_category":"Asociaciones Y Clubs Deportivos",
    "sg:phone":"+34 915 51 46 49",
    "sg:postcode":"28007",
    "sg:province":"Madrid",
    "wof:name":"San Roman Ramos Francisco Javier",
    "wof:placetype":"venue"
},
  "geometry": {"coordinates":[-3.6733279228,40.4034996033],"type":"Point"}
}