{
  "type": "Feature",
  "properties": {
    "addr:full":"Carr Conradors, S/n Cabaneta Islas Baleares 07141",
    "addr:housenumber":"s",
    "addr:postcode":"07141",
    "addr:street":"Carr Conradors;/ N",
    "iso:country":"ES",
    "sg:address":"Carr Conradors, S/n",
    "sg:city":"Cabaneta",
    "sg:orig_category":"Fabricaci\u00d3n, Venta, Instalaci\u00d3n De R\u00d3tulos, De R\u00d3tulos Luminosos",
    "sg:phone":"+34 971 22 95 44",
    "sg:postcode":"07141",
    "sg:province":"Islas Baleares",
    "wof:name":"Curvado Balear S.l.",
    "wof:placetype":"venue"
},
  "geometry": {"coordinates":[2.7445349693,39.6195487976],"type":"Point"}
}