{
  "type": "Feature",
  "properties": {
    "addr:full":"Barr Ermita (la), S/n Ermita Cantabria 39796",
    "addr:housenumber":"s",
    "addr:postcode":"39796",
    "addr:street":"/ N Ermita",
    "iso:country":"ES",
    "sg:address":"Barr Ermita (la), S/n",
    "sg:city":"Ermita",
    "sg:orig_category":"Ingenier\u00cda, Centros De Estudios (diversos)",
    "sg:phone":"+34 942 61 64 18",
    "sg:postcode":"39796",
    "sg:province":"Cantabria",
    "wof:name":"Viadero Rueda Fernando",
    "wof:placetype":"venue"
},
  "geometry": {"coordinates":[-4.0014500618,43.1361885071],"type":"Point"}
}