{
  "type": "Feature",
  "properties": {
    "addr:full":"Calle de Uria, 46 Cangas Narcea Asturias 33800",
    "addr:housenumber":"46",
    "addr:postcode":"33800",
    "addr:street":"Calle De Uria",
    "iso:country":"ES",
    "sg:address":"Calle de Uria, 46",
    "sg:city":"Cangas Narcea",
    "sg:orig_category":"Notarios",
    "sg:phone":"+34 985 81 02 74",
    "sg:postcode":"33800",
    "sg:province":"Asturias",
    "wof:name":"Nieto Y Moreno Notarios Cb",
    "wof:placetype":"venue"
},
  "geometry": {"coordinates":[-6.5475997925,43.1752586365],"type":"Point"}
}