{
  "type": "Feature",
  "properties": {
    "iso:country":"ES",
    "sg:address":"Rua Urzaiz, 17",
    "sg:city":"Vigo",
    "sg:orig_category":"Abogados",
    "sg:phone":"+34 986 22 86 66",
    "sg:postcode":"36201",
    "sg:province":"Pontevedra",
    "wof:name":"Barca Guitian Jose Alfredo",
    "wof:placetype":"venue"
},
  "geometry": {"coordinates":[-8.7183017731,42.2353973389],"type":"Point"}
}