{
  "type": "Feature",
  "properties": {
    "iso:country":"ES",
    "sg:address":"Calle de Santiago Apostol (de), 9",
    "sg:city":"Alcobendas",
    "sg:orig_category":"Farmacias",
    "sg:phone":"+34 916 51 11 66",
    "sg:postcode":"28100",
    "sg:province":"Madrid",
    "wof:name":"Perez Herrero Maria Luz",
    "wof:placetype":"venue"
},
  "geometry": {"coordinates":[-3.6315360069,40.5429267883],"type":"Point"}
}