{
  "type": "Feature",
  "properties": {
    "addr:full":"Carrer de Maresme, 1 Poligon Industrial Pla De La Bruguera Barcelona 08211",
    "addr:housenumber":"1",
    "addr:postcode":"08211",
    "addr:street":"Carrer De Maresme;Industrial;De",
    "iso:country":"ES",
    "sg:address":"Carrer de Maresme, 1",
    "sg:city":"Poligon Industrial Pla De La Bruguera",
    "sg:orig_category":"Materias Pl\u00c1sticas: Art\u00cdculos Para La Industria",
    "sg:phone":"+34 937 14 39 00",
    "sg:postcode":"08211",
    "sg:province":"Barcelona",
    "sg:website":"www.sabacaucho.com",
    "wof:name":"Sabacaucho S.a.",
    "wof:placetype":"venue"
},
  "geometry": {"coordinates":[2.0824799538,41.6114387512],"type":"Point"}
}