{
  "type": "Feature",
  "properties": {
    "iso:country":"ES",
    "sg:address":"Calle de Mayor, 56",
    "sg:city":"Pilar Horadada",
    "sg:orig_category":"Bazares, Art\u00cdculos De Limpieza Y De Cocina (al Por Menor)",
    "sg:phone":"+34 965 35 24 53",
    "sg:postcode":"03190",
    "sg:province":"Alicante",
    "wof:name":"Alcazar Perez Ramon",
    "wof:placetype":"venue"
},
  "geometry": {"coordinates":[-0.7883375883,37.8631134033],"type":"Point"}
}