{
  "type": "Feature",
  "properties": {
    "addr:full":"Calle de Rambla, 48 Yecla Murcia 30510",
    "addr:housenumber":"48",
    "addr:postcode":"30510",
    "addr:street":"Calle De Rambla",
    "iso:country":"ES",
    "sg:address":"Calle de Rambla, 48",
    "sg:city":"Yecla",
    "sg:orig_category":"Quincaller\u00cda (al Por Menor)",
    "sg:phone":"+34 968 79 41 06",
    "sg:postcode":"30510",
    "sg:province":"Murcia",
    "wof:name":"Soriano Martinez Juan Jose",
    "wof:placetype":"venue"
},
  "geometry": {"coordinates":[-1.1091896296,38.6151390076],"type":"Point"}
}