{
  "type": "Feature",
  "properties": {
    "iso:country":"ES",
    "sg:address":"Avda Fisterra, 227",
    "sg:city":"Arteixo",
    "sg:orig_category":"Inmobiliaria (agencias)",
    "sg:phone":"+34 981 61 36 13",
    "sg:postcode":"15142",
    "sg:province":"La Coru\u00f1a",
    "wof:name":"Inmobiliaria Cotrofe S.l.",
    "wof:placetype":"venue"
},
  "geometry": {"coordinates":[-8.5092773438,43.3054656982],"type":"Point"}
}