{
  "type": "Feature",
  "properties": {
    "addr:full":"Calle de Castillejos, S/n Palmas De Gran Canaria Las Palmas 35010",
    "addr:housenumber":"s",
    "addr:postcode":"35010",
    "addr:street":"Calle De Castillejos;/ N",
    "iso:country":"ES",
    "sg:address":"Calle de Castillejos, S/n",
    "sg:city":"Palmas De Gran Canaria",
    "sg:orig_category":"Cajas De Ahorro",
    "sg:phone":"+34 928 47 22 94",
    "sg:postcode":"35010",
    "sg:province":"Las Palmas",
    "wof:name":"Caixa D'estalvis I Pensions De Barcelona",
    "wof:placetype":"venue"
},
  "geometry": {"coordinates":[-15.4436578751,28.1291942596],"type":"Point"}
}