{
  "type": "Feature",
  "properties": {
    "iso:country":"ES",
    "sg:address":"Avda Monforte, 34",
    "sg:city":"Chantada",
    "sg:orig_category":"Abogados",
    "sg:phone":"+34 982 46 20 49",
    "sg:postcode":"27500",
    "sg:province":"Lugo",
    "wof:name":"Carnero Blanco Jose Antonio",
    "wof:placetype":"venue"
},
  "geometry": {"coordinates":[-7.7630701065,42.6085357666],"type":"Point"}
}