{
  "type": "Feature",
  "properties": {
    "addr:full":"Pl Estacio, 1 Pineda Mar Barcelona 08397",
    "addr:housenumber":"1",
    "addr:postcode":"08397",
    "addr:street":"Pl Estacio;Barcelona",
    "iso:country":"ES",
    "sg:address":"Pl Estacio, 1",
    "sg:city":"Pineda Mar",
    "sg:orig_category":"Inmobiliaria (agencias)",
    "sg:phone":"+34 937 67 12 42",
    "sg:postcode":"08397",
    "sg:province":"Barcelona",
    "wof:name":"Promofincas Maresme S.l.",
    "wof:placetype":"venue"
},
  "geometry": {"coordinates":[2.69313097,41.6227073669],"type":"Point"}
}