{
  "type": "Feature",
  "properties": {
    "iso:country":"ES",
    "sg:address":"Pla\u00c7 Palmera, 2",
    "sg:city":"Figueres",
    "sg:orig_category":"Relojer\u00cda (al Por Menor, Reparaci\u00d3n)",
    "sg:phone":"+34 972 51 08 26",
    "sg:postcode":"17600",
    "sg:province":"Girona",
    "wof:name":"Pareja Perez Jose",
    "wof:placetype":"venue"
},
  "geometry": {"coordinates":[2.9639110565,42.2674217224],"type":"Point"}
}