{
  "type": "Feature",
  "properties": {
    "addr:full":"Calle de Mariano Jose De Larra, 23 Merida Badajoz 06800",
    "addr:housenumber":"23",
    "addr:postcode":"06800",
    "addr:street":"Calle De Mariano Jose De Larra",
    "iso:country":"ES",
    "sg:address":"Calle de Mariano Jose De Larra, 23",
    "sg:city":"Merida",
    "sg:orig_category":"Peluquer\u00cdas, Peluquer\u00cda Mixta",
    "sg:phone":"+34 924 30 27 20",
    "sg:postcode":"06800",
    "sg:province":"Badajoz",
    "wof:name":"Suarez Gallego Nicasio",
    "wof:placetype":"venue"
},
  "geometry": {"coordinates":[-6.3387718201,38.9176864624],"type":"Point"}
}