{
  "type": "Feature",
  "properties": {
    "addr:full":"Calle de Manuel Simo, 26 Valencia Valencia 46007",
    "addr:housenumber":"26",
    "addr:postcode":"46007",
    "addr:street":"Calle De Manuel Simo",
    "iso:country":"ES",
    "sg:address":"Calle de Manuel Simo, 26",
    "sg:city":"Valencia",
    "sg:orig_category":"Florister\u00cdas",
    "sg:phone":"+34 963 80 11 04",
    "sg:postcode":"46007",
    "sg:province":"Valencia",
    "wof:name":"Garcia Rodriguez Cesareo",
    "wof:placetype":"venue"
},
  "geometry": {"coordinates":[-0.3911719918,39.4599571228],"type":"Point"}
}