{
  "type": "Feature",
  "properties": {
    "iso:country":"ES",
    "sg:address":"Aceria, 26",
    "sg:city":"Puerto Sagunto",
    "sg:orig_category":"Agentes, Concesionarios Y Sucursales De Veh\u00cdculos",
    "sg:phone":"+34 962 69 87 25",
    "sg:postcode":"46520",
    "sg:province":"Valencia",
    "wof:name":"Movil Maritimo S. L.",
    "wof:placetype":"venue"
},
  "geometry": {"coordinates":[-0.2241850048,39.653842926],"type":"Point"}
}