{
  "type": "Feature",
  "properties": {
    "iso:country":"ES",
    "sg:address":"Calle de Avila, 37",
    "sg:city":"Zaragoza",
    "sg:orig_category":"Loter\u00cda Y T\u00d3mbola",
    "sg:phone":"+34 976 55 20 69",
    "sg:postcode":"50005",
    "sg:province":"Zaragoza",
    "wof:name":"Hebrero Delgado Francisco Javier",
    "wof:placetype":"venue"
},
  "geometry": {"coordinates":[-0.8979105949,41.6488723755],"type":"Point"}
}