{
  "type": "Feature",
  "properties": {
    "iso:country":"ES",
    "sg:address":"Calle de Ayala, 99",
    "sg:city":"Madrid",
    "sg:orig_category":"Ropa Para Se\u00d1oras (al Por Menor)",
    "sg:phone":"+34 914 02 25 33",
    "sg:postcode":"28006",
    "sg:province":"Madrid",
    "wof:name":"Vicalcasa S.l.",
    "wof:placetype":"venue"
},
  "geometry": {"coordinates":[-3.6714570522,40.4272041321],"type":"Point"}
}