{
  "type": "Feature",
  "properties": {
    "addr:full":"Carrer de Balmes, 3 Terrassa Barcelona 08225",
    "addr:housenumber":"3",
    "addr:postcode":"08225",
    "addr:street":"Carrer De Balmes",
    "iso:country":"ES",
    "sg:address":"Carrer de Balmes, 3",
    "sg:city":"Terrassa",
    "sg:orig_category":"Confecci\u00d3n De Trajes Para Se\u00d1oras",
    "sg:phone":"+34 937 33 07 15",
    "sg:postcode":"08225",
    "sg:province":"Barcelona",
    "wof:name":"Mad-3 S.l.",
    "wof:placetype":"venue"
},
  "geometry": {"coordinates":[2.0030488968,41.572971344],"type":"Point"}
}