{
  "type": "Feature",
  "properties": {
    "iso:country":"ES",
    "sg:address":"Calle de Santa Rosalia, 57",
    "sg:city":"Santa Cruz De Tenerife",
    "sg:orig_category":"Psic\u00d3logos",
    "sg:phone":"+34 922 28 01 36",
    "sg:postcode":"38002",
    "sg:province":"Santa Cruz De Tenerife",
    "wof:name":"Fernandez Luzardo Rosa Maria",
    "wof:placetype":"venue"
},
  "geometry": {"coordinates":[-16.2513256073,28.4707355499],"type":"Point"}
}