{
  "type": "Feature",
  "properties": {
    "addr:full":"Carr San Julian, 2 Morella Castell\u00f3n 12300",
    "addr:housenumber":"2",
    "addr:postcode":"12300",
    "addr:street":"Carr San Julian;Castello\u0301N",
    "iso:country":"ES",
    "sg:address":"Carr San Julian, 2",
    "sg:city":"Morella",
    "sg:orig_category":"Formaci\u00d3n A Distancia, Por Correspondencia",
    "sg:phone":"+34 964 17 31 78",
    "sg:postcode":"12300",
    "sg:province":"Castell\u00f3n",
    "wof:name":"Labuiga Albert Eugeni",
    "wof:placetype":"venue"
},
  "geometry": {"coordinates":[-0.0977939963,40.6189155579],"type":"Point"}
}