{
  "type": "Feature",
  "properties": {
    "addr:full":"Ptda Clotas, S/n Useres Castell\u00f3n 12118",
    "addr:housenumber":"s",
    "addr:postcode":"12118",
    "addr:street":"Ptda Clotas;/ N Useres Castello\u0301N",
    "iso:country":"ES",
    "sg:address":"Ptda Clotas, S/n",
    "sg:city":"Useres",
    "sg:orig_category":"Productores Recolectores, Venta Directa De Vinos",
    "sg:phone":"+34 964 76 00 33",
    "sg:postcode":"12118",
    "sg:province":"Castell\u00f3n",
    "wof:name":"S.a.t. N\u00ba 3201 El Salvador-bodega Vinicola",
    "wof:placetype":"venue"
},
  "geometry": {"coordinates":[-0.1629720032,40.1573219299],"type":"Point"}
}