{
  "type": "Feature",
  "properties": {
    "addr:full":"Carrer de Josep Pla, 25 Mataro Barcelona 08304",
    "addr:housenumber":"25",
    "addr:postcode":"08304",
    "addr:street":"Carrer De Josep Pla",
    "iso:country":"ES",
    "sg:address":"Carrer de Josep Pla, 25",
    "sg:city":"Mataro",
    "sg:orig_category":"Automatizaci\u00d3n De Procesos Industriales Y De Edificaci\u00d3n (estudios, Instalaci\u00d3n)",
    "sg:phone":"+34 937 57 76 09",
    "sg:postcode":"08304",
    "sg:province":"Barcelona",
    "wof:name":"Term S.l.",
    "wof:placetype":"venue"
},
  "geometry": {"coordinates":[2.4416000843,41.5522041321],"type":"Point"}
}