{
  "type": "Feature",
  "properties": {
    "addr:full":"Carr Mare De Deu Dels Angels, 17 Villarreal Castell\u00f3n 12540",
    "addr:housenumber":"17",
    "addr:postcode":"12540",
    "addr:street":"Carr Mare De Deu",
    "iso:country":"ES",
    "sg:address":"Carr Mare De Deu Dels Angels, 17",
    "sg:city":"Villarreal",
    "sg:orig_category":"Material Y Suministros Para Imprenta E Industrias Gr\u00c1ficas",
    "sg:phone":"+34 964 53 56 83",
    "sg:postcode":"12540",
    "sg:province":"Castell\u00f3n",
    "wof:name":"Llorens Perez Vicente",
    "wof:placetype":"venue"
},
  "geometry": {"coordinates":[-0.1022680029,39.9389038086],"type":"Point"}
}