{
  "type": "Feature",
  "properties": {
    "iso:country":"ES",
    "sg:address":"Pase Hortaz (del), 22",
    "sg:city":"Tamarite Litera",
    "sg:orig_category":"Ropa Para Se\u00d1oras Y Caballeros (al Por Menor)",
    "sg:phone":"+34 974 42 02 66",
    "sg:postcode":"22550",
    "sg:province":"Huesca",
    "wof:name":"Castillo Llucia Ana",
    "wof:placetype":"venue"
},
  "geometry": {"coordinates":[0.4240469933,41.8659324646],"type":"Point"}
}