{
  "type": "Feature",
  "properties": {
    "addr:full":"Ctra. Andratx, 153 Port Andratx Islas Baleares 07157",
    "addr:housenumber":"153",
    "addr:postcode":"07157",
    "addr:street":"Ctra. Andratx",
    "iso:country":"ES",
    "sg:address":"Ctra. Andratx, 153",
    "sg:city":"Port Andratx",
    "sg:orig_category":"Electricidad: Instaladores",
    "sg:phone":"+34 971 67 13 98",
    "sg:postcode":"07157",
    "sg:province":"Islas Baleares",
    "sg:website":"www.intec-electric.com",
    "wof:name":"Intec Electric Puerto Andraitx S. L.",
    "wof:placetype":"venue"
},
  "geometry": {"coordinates":[2.3924639225,39.5451927185],"type":"Point"}
}