{
  "type": "Feature",
  "properties": {
    "iso:country":"ES",
    "sg:address":"Av Canaletes, 45",
    "sg:city":"Cerdanyola Valles",
    "sg:orig_category":"Promotores Constructores",
    "sg:phone":"+34 935 80 31 03",
    "sg:postcode":"08290",
    "sg:province":"Barcelona",
    "wof:name":"Colayes S.l.",
    "wof:placetype":"venue"
},
  "geometry": {"coordinates":[2.1506168842,41.4838104248],"type":"Point"}
}