{
  "type": "Feature",
  "properties": {
    "addr:full":"Plaz Nespral, S/n Langreo Asturias 33900",
    "addr:housenumber":"s",
    "addr:postcode":"33900",
    "addr:street":"Plaz Nespral;/ N",
    "iso:country":"ES",
    "sg:address":"Plaz Nespral, S/n",
    "sg:city":"Langreo",
    "sg:orig_category":"Carnicer\u00cdas, Carnicer\u00cdas",
    "sg:phone":"+34 985 68 30 73",
    "sg:postcode":"33900",
    "sg:province":"Asturias",
    "wof:name":"Gonzalez Rodriguez Nodelina",
    "wof:placetype":"venue"
},
  "geometry": {"coordinates":[-5.6845388412,43.2946968079],"type":"Point"}
}