{
  "type": "Feature",
  "properties": {
    "iso:country":"ES",
    "sg:address":"C/ Na Saurina D'enten\u00c7a, 12",
    "sg:city":"Alcoi",
    "sg:orig_category":"Telas Y Sedas (al Por Menor)",
    "sg:phone":"+34 965 33 02 66",
    "sg:postcode":"03803",
    "sg:province":"Alicante",
    "wof:name":"Oca\u00f1a Bravo Victoria",
    "wof:placetype":"venue"
},
  "geometry": {"coordinates":[-0.4810769856,38.7006607056],"type":"Point"}
}