{
  "type": "Feature",
  "properties": {
    "iso:country":"ES",
    "sg:address":"Rond Zamenhof, 3",
    "sg:city":"Sabadell",
    "sg:orig_category":"M\u00c9dicos: Estomatolog\u00cda",
    "sg:phone":"+34 937 25 88 88",
    "sg:postcode":"08201",
    "sg:province":"Barcelona",
    "wof:name":"Diaz Barrera Ivarn Fernando",
    "wof:placetype":"venue"
},
  "geometry": {"coordinates":[2.1061871052,41.551940918],"type":"Point"}
}