{
  "type": "Feature",
  "properties": {
    "addr:full":"Pla\u00c7 Ca Les Monnares, 5 Pollen\u00e7a Islas Baleares 07460",
    "addr:housenumber":"5",
    "addr:postcode":"07460",
    "addr:street":"Ca Les Monnares;Islas",
    "iso:country":"ES",
    "sg:address":"Pla\u00c7 Ca Les Monnares, 5",
    "sg:city":"Pollen\u00e7a",
    "sg:orig_category":"Agencias De Viajes",
    "sg:phone":"+34 971 53 26 51",
    "sg:postcode":"07460",
    "sg:province":"Islas Baleares",
    "sg:website":"www.halconviajes.com",
    "wof:name":"Viajes Halcon S.a.",
    "wof:placetype":"venue"
},
  "geometry": {"coordinates":[3.0190351009,39.8781204224],"type":"Point"}
}