{
  "type": "Feature",
  "properties": {
    "iso:country":"ES",
    "sg:address":"Vilanova, 10",
    "sg:city":"Vilanova",
    "sg:classifiers":[
        {
            "category":"Taxi",
            "type":"Transportation"
        }
    ],
    "sg:phone":"+34 981 67 30 78",
    "sg:postcode":"15318",
    "sg:province":"A Coru\u00f1a",
    "wof:name":"Vazquez Vicos Antonio",
    "wof:placetype":"venue"
},
  "geometry": {"coordinates":[-8.2870817184,43.2287101746],"type":"Point"}
}