{
  "type": "Feature",
  "properties": {
    "addr:full":"Calle de Nogal (el), 1 Callejones-san Silvestre Almer\u00eda 04230",
    "addr:housenumber":"1",
    "addr:postcode":"04230",
    "addr:street":"Calle De Nogal El;Silvestre Almeri\u0301A",
    "iso:country":"ES",
    "sg:address":"Calle de Nogal (el), 1",
    "sg:city":"Callejones-san Silvestre",
    "sg:orig_category":"Agentes, Concesionarios Y Sucursales De Veh\u00cdculos",
    "sg:phone":"+34 950 62 44 04",
    "sg:postcode":"04230",
    "sg:province":"Almer\u00eda",
    "wof:name":"Auto-salon Almeria S.a.",
    "wof:placetype":"venue"
},
  "geometry": {"coordinates":[-2.4478240013,36.8712463379],"type":"Point"}
}