{
  "type": "Feature",
  "properties": {
    "iso:country":"ES",
    "sg:address":"Calle de Cordoba, S/n",
    "sg:city":"Palmas De Gran Canaria",
    "sg:orig_category":"Asociaciones Y Clubs Deportivos",
    "sg:phone":"+34 928 33 20 72",
    "sg:postcode":"35016",
    "sg:province":"Las Palmas",
    "sg:website":"www.cbgrancanaria.com",
    "wof:name":"C.b.gran Canaria S.a.",
    "wof:placetype":"venue"
},
  "geometry": {"coordinates":[-15.4173250198,28.0920333862],"type":"Point"}
}