{
  "type": "Feature",
  "properties": {
    "addr:full":"Carrer de Castell D'olimbroi, 3 Denia Alicante 03700",
    "addr:housenumber":"3",
    "addr:postcode":"03700",
    "addr:street":"Carrer De Castell D'Olimbroi",
    "iso:country":"ES",
    "sg:address":"Carrer de Castell D'olimbroi, 3",
    "sg:city":"Denia",
    "sg:orig_category":"Organizaciones Internacionales",
    "sg:phone":"+34 965 78 13 58",
    "sg:postcode":"03700",
    "sg:province":"Alicante",
    "wof:name":"Cruz Roja Espa\u00f1ola",
    "wof:placetype":"venue"
},
  "geometry": {"coordinates":[0.1048989967,38.8424682617],"type":"Point"}
}