{
  "type": "Feature",
  "properties": {
    "addr:full":"Calle de Hermano Angel Mur, 11 Palmas De Gran Canaria Las Palmas 35014",
    "addr:housenumber":"11",
    "addr:postcode":"35014",
    "addr:street":"Calle De Hermano Angel Mur",
    "iso:country":"ES",
    "sg:address":"Calle de Hermano Angel Mur, 11",
    "sg:city":"Palmas De Gran Canaria",
    "sg:orig_category":"Mec\u00c1nico Del Autom\u00d3vil",
    "sg:phone":"+34 928 25 86 69",
    "sg:postcode":"35014",
    "sg:province":"Las Palmas",
    "wof:name":"Talleres Morega S.l.",
    "wof:placetype":"venue"
},
  "geometry": {"coordinates":[-15.4375352859,28.0958709717],"type":"Point"}
}