{
  "type": "Feature",
  "properties": {
    "iso:country":"ES",
    "sg:address":"Calle de Huerta Del Hospital, 9",
    "sg:city":"Guadalupe",
    "sg:orig_category":"Ense\u00d1anza: Peluquer\u00cda Est\u00c9tica",
    "sg:phone":"+34 927 36 71 93",
    "sg:postcode":"10140",
    "sg:province":"C\u00e1ceres",
    "wof:name":"Blanca Morano Raquel",
    "wof:placetype":"venue"
},
  "geometry": {"coordinates":[-5.326458931,39.4516029358],"type":"Point"}
}