{
  "type": "Feature",
  "properties": {
    "addr:full":"Cra. Nal. Tres-cents Quaranta, S/n Tarragona Tarragona 43...",
    "addr:housenumber":"s / n;43 ...",
    "addr:street":"Tarragona",
    "iso:country":"ES",
    "sg:address":"Cra. Nal. Tres-cents Quaranta, S/n",
    "sg:city":"Tarragona",
    "sg:orig_category":"Lubrificantes (fabricaci\u00d3n, Al Por Mayor)",
    "sg:phone":"+34 977 55 84 00",
    "sg:postcode":"43...",
    "sg:province":"Tarragona",
    "sg:website":"www.shell.es",
    "wof:name":"Shell Espa\u00d1a S.a.",
    "wof:placetype":"venue"
},
  "geometry": {"coordinates":[1.2541049719,41.1169281006],"type":"Point"}
}