{
  "type": "Feature",
  "properties": {
    "addr:full":"Calle de Mayor, 1 Cabezo Torres Murcia 30110",
    "addr:housenumber":"1",
    "addr:postcode":"30110",
    "addr:street":"Calle De Mayor",
    "iso:country":"ES",
    "sg:address":"Calle de Mayor, 1",
    "sg:city":"Cabezo Torres",
    "sg:orig_category":"Alimentaci\u00d3n General (al Por Menor)",
    "sg:phone":"+34 968 83 01 49",
    "sg:postcode":"30110",
    "sg:province":"Murcia",
    "wof:name":"Aleman Lopez Jose",
    "wof:placetype":"venue"
},
  "geometry": {"coordinates":[-1.1229382753,38.024066925],"type":"Point"}
}