{
  "type": "Feature",
  "properties": {
    "iso:country":"ES",
    "sg:address":"Calle de Cervantes, 11",
    "sg:city":"Onil",
    "sg:orig_category":"Peluquer\u00cdas, Peluquer\u00cda Mixta",
    "sg:phone":"+34 965 56 51 12",
    "sg:postcode":"03430",
    "sg:province":"Alicante",
    "wof:name":"Ribera Calbo Vicente",
    "wof:placetype":"venue"
},
  "geometry": {"coordinates":[-0.6746444702,38.6297111511],"type":"Point"}
}