{
  "type": "Feature",
  "properties": {
    "addr:full":"Avda Carlos I De, 10 Donostia-san Sebastian Guip\u00f9zcoa 20011",
    "addr:housenumber":"10",
    "addr:postcode":"20011",
    "addr:street":"Avda Carlos I De",
    "iso:country":"ES",
    "sg:address":"Avda Carlos I De, 10",
    "sg:city":"Donostia-san Sebastian",
    "sg:orig_category":"Comercio, Reparaci\u00d3n De Bicicletas, De Motocicletas, De Accesorios",
    "sg:phone":"+34 943 47 44 42",
    "sg:postcode":"20011",
    "sg:province":"Guip\u00f9zcoa",
    "wof:name":"Blanco Fernandez Javier",
    "wof:placetype":"venue"
},
  "geometry": {"coordinates":[-1.9794180393,43.3051872253],"type":"Point"}
}