{
  "type": "Feature",
  "properties": {
    "addr:full":"Carrer de Setze De Juliol, 56 Poligon Industrial De Son Castello Islas Baleares 07009",
    "addr:housenumber":"56",
    "addr:postcode":"07009",
    "addr:street":"Carrer De Setze De Juliol;Islas",
    "iso:country":"ES",
    "sg:address":"Carrer de Setze De Juliol, 56",
    "sg:city":"Poligon Industrial De Son Castello",
    "sg:orig_category":"Peritos Mar\u00cdtimos",
    "sg:phone":"+34 971 10 43 00",
    "sg:postcode":"07009",
    "sg:province":"Islas Baleares",
    "sg:website":"www.arguimbau.es",
    "wof:name":"Tasmar Logistica S.a.",
    "wof:placetype":"venue"
},
  "geometry": {"coordinates":[2.6776249409,39.6072845459],"type":"Point"}
}