{
  "type": "Feature",
  "properties": {
    "iso:country":"ES",
    "sg:address":"Calle de Blasco De Garay, 63",
    "sg:city":"Madrid",
    "sg:orig_category":"Relojer\u00cda Industrial",
    "sg:phone":"+34 915 44 01 49",
    "sg:postcode":"28015",
    "sg:province":"Madrid",
    "wof:name":"Cydersa S.l.",
    "wof:placetype":"venue"
},
  "geometry": {"coordinates":[-3.7112429142,40.4376525879],"type":"Point"}
}