{
  "type": "Feature",
  "properties": {
    "iso:country":"ES",
    "sg:address":"Carrer de Enrico Caruso (d'), 17",
    "sg:city":"Pineda",
    "sg:orig_category":"Droguer\u00cdas (al Por Menor)",
    "sg:phone":"+34 977 37 00 07",
    "sg:postcode":"43480",
    "sg:province":"Tarragona",
    "wof:name":"Rivares Usieto Concepcion",
    "wof:placetype":"venue"
},
  "geometry": {"coordinates":[1.1441899538,41.1080245972],"type":"Point"}
}