{
  "type": "Feature",
  "properties": {
    "addr:full":"Rua San Roque, 92 Vigo Pontevedra 36204",
    "addr:housenumber":"92",
    "addr:postcode":"36204",
    "addr:street":"Rua San Roque",
    "iso:country":"ES",
    "sg:address":"Rua San Roque, 92",
    "sg:city":"Vigo",
    "sg:orig_category":"Artes Gr\u00c1ficas, Artes Pl\u00c1sticas (curso)",
    "sg:phone":"+34 986 48 41 41",
    "sg:postcode":"36204",
    "sg:province":"Pontevedra",
    "sg:website":"www.moldiflex.com",
    "wof:name":"Moldes Y Flexograficos S.l.",
    "wof:placetype":"venue"
},
  "geometry": {"coordinates":[-8.7089185715,42.2294769287],"type":"Point"}
}