{
  "type": "Feature",
  "properties": {
    "addr:full":"Avda Republica Argentina, 35 Sevilla Sevilla 41011",
    "addr:housenumber":"35",
    "addr:postcode":"41011",
    "addr:street":"Avda Republica Argentina",
    "iso:country":"ES",
    "sg:address":"Avda Republica Argentina, 35",
    "sg:city":"Sevilla",
    "sg:orig_category":"Abogados",
    "sg:phone":"+34 954 27 20 01",
    "sg:postcode":"41011",
    "sg:province":"Sevilla",
    "wof:name":"Elias Santamaria Miguel Angel",
    "wof:placetype":"venue"
},
  "geometry": {"coordinates":[-6.0037150383,37.3767166138],"type":"Point"}
}