{
  "type": "Feature",
  "properties": {
    "addr:full":"Plaz Hernandez Amores, 4 Catedral Murcia 30001",
    "addr:housenumber":"4",
    "addr:postcode":"30001",
    "addr:street":"Plaz;Amores",
    "iso:country":"ES",
    "sg:address":"Plaz Hernandez Amores, 4",
    "sg:city":"Catedral",
    "sg:orig_category":"Ense\u00d1anza: Idiomas",
    "sg:phone":"+34 968 21 08 39",
    "sg:postcode":"30001",
    "sg:province":"Murcia",
    "wof:name":"Inlingua Murcia S.l.",
    "wof:placetype":"venue"
},
  "geometry": {"coordinates":[-1.1283040047,37.9846572876],"type":"Point"}
}