{
  "type": "Feature",
  "properties": {
    "addr:full":"Rua Nueva, 28 Coru\u00d1a La Coru\u00f1a 15003",
    "addr:housenumber":"28",
    "addr:postcode":"15003",
    "addr:street":"Rua Nueva;La Corun\u0303A",
    "iso:country":"ES",
    "sg:address":"Rua Nueva, 28",
    "sg:city":"Coru\u00d1a",
    "sg:orig_category":"Ropa Para Se\u00d1oras (al Por Menor)",
    "sg:phone":"+34 981 22 95 67",
    "sg:postcode":"15003",
    "sg:province":"La Coru\u00f1a",
    "wof:name":"Dorado Viana Josefina",
    "wof:placetype":"venue"
},
  "geometry": {"coordinates":[-8.4030771255,43.3697319031],"type":"Point"}
}