{
  "type": "Feature",
  "properties": {
    "addr:full":"Carr Cadernera, 5 Vilanova I La Geltru Barcelona 08800",
    "addr:housenumber":"5",
    "addr:postcode":"08800",
    "addr:street":"Carr Cadernera",
    "iso:country":"ES",
    "sg:address":"Carr Cadernera, 5",
    "sg:city":"Vilanova I La Geltru",
    "sg:orig_category":"Arquitectos",
    "sg:phone":"+34 938 15 40 39",
    "sg:postcode":"08800",
    "sg:province":"Barcelona",
    "wof:name":"Llaverias Baques Nuria",
    "wof:placetype":"venue"
},
  "geometry": {"coordinates":[1.7003439665,41.2139968872],"type":"Point"}
}