{
  "type": "Feature",
  "properties": {
    "addr:full":"Calle de Juan Bautista De La Concepcion, 4 Alcazar S. Juan Ciudad Real 13600",
    "addr:housenumber":"4",
    "addr:postcode":"13600",
    "addr:street":"Calle De Juan Bautista De La Concepcion;Alcazar S. Juan Ciudad Real",
    "iso:country":"ES",
    "sg:address":"Calle de Juan Bautista De La Concepcion, 4",
    "sg:city":"Alcazar S. Juan",
    "sg:orig_category":"Aparatos Y Equipo Para Tratamiento De Aguas",
    "sg:phone":"+34 926 55 22 53",
    "sg:postcode":"13600",
    "sg:province":"Ciudad Real",
    "sg:website":"www.puniagua.es",
    "wof:name":"Uniagua Alcazar C.b.",
    "wof:placetype":"venue"
},
  "geometry": {"coordinates":[-3.2177290916,39.3949890137],"type":"Point"}
}