{
  "type": "Feature",
  "properties": {
    "addr:full":"Plaz Mayor, S/n Moraleja Sayago Zamora 49177",
    "addr:housenumber":"s / n",
    "addr:postcode":"49177",
    "addr:street":"Plaz Mayor",
    "iso:country":"ES",
    "sg:address":"Plaz Mayor, S/n",
    "sg:city":"Moraleja Sayago",
    "sg:orig_category":"Centros De Educaci\u00d3n Especial",
    "sg:phone":"+34 980 61 73 03",
    "sg:postcode":"49177",
    "sg:province":"Zamora",
    "wof:name":"C.e.i.p. De Moraleja De Sayago",
    "wof:placetype":"venue"
},
  "geometry": {"coordinates":[-6.0035939217,41.1692390442],"type":"Point"}
}