{
  "type": "Feature",
  "properties": {
    "iso:country":"ES",
    "sg:address":"Calle de Santa Florentina, 23",
    "sg:city":"Cartagena",
    "sg:orig_category":"M\u00c9dicos: Cardiolog\u00cda Y Afecciones Cardiovasculares",
    "sg:phone":"+34 968 50 34 45",
    "sg:postcode":"30201",
    "sg:province":"Murcia",
    "wof:name":"Ortega Bernal Juan",
    "wof:placetype":"venue"
},
  "geometry": {"coordinates":[-0.9869139791,37.6039619446],"type":"Point"}
}