{
  "type": "Feature",
  "properties": {
    "addr:full":"Carr Padro, 1 Verges Girona 17142",
    "addr:housenumber":"1",
    "addr:postcode":"17142",
    "addr:street":"Carr Padro",
    "iso:country":"ES",
    "sg:address":"Carr Padro, 1",
    "sg:city":"Verges",
    "sg:orig_category":"Centros De Educaci\u00d3n Especial",
    "sg:phone":"+34 972 78 01 41",
    "sg:postcode":"17142",
    "sg:province":"Girona",
    "wof:name":"Co%egi Public Francesc Cambo I Batlle",
    "wof:placetype":"venue"
},
  "geometry": {"coordinates":[3.047837019,42.0620994568],"type":"Point"}
}