{
  "type": "Feature",
  "properties": {
    "iso:country":"ES",
    "sg:address":"Avgd D'almansa, 16",
    "sg:city":"Ontinyent",
    "sg:orig_category":"Sociedades, Compa\u00d1\u00cdas Aseguradoras",
    "sg:phone":"+34 962 38 29 64",
    "sg:postcode":"46870",
    "sg:province":"Valencia",
    "wof:name":"Correduria De Seguros C.marti Donat S.l.",
    "wof:placetype":"venue"
},
  "geometry": {"coordinates":[-0.613707006,38.8221206665],"type":"Point"}
}