{
  "type": "Feature",
  "properties": {
    "addr:full":"Calle de Eduardo Dato, 41 Vitoria-gasteiz \u00c1lava 01005",
    "addr:housenumber":"41",
    "addr:postcode":"01005",
    "addr:street":"Calle De Eduardo Dato",
    "iso:country":"ES",
    "sg:address":"Calle de Eduardo Dato, 41",
    "sg:city":"Vitoria-gasteiz",
    "sg:orig_category":"Inmobiliaria (agencias)",
    "sg:phone":"+34 945 14 48 50",
    "sg:postcode":"01005",
    "sg:province":"\u00c1lava",
    "wof:name":"Las Estrellas De Piedra S.l.",
    "wof:placetype":"venue"
},
  "geometry": {"coordinates":[-2.6726107597,42.842464447],"type":"Point"}
}