{
  "type": "Feature",
  "properties": {
    "iso:country":"ES",
    "sg:address":"Calle de Bencomo, 38",
    "sg:city":"San Cristobal De La Laguna",
    "sg:orig_category":"Agencias De Viajes",
    "sg:phone":"+34 922 26 01 34",
    "sg:postcode":"38201",
    "sg:province":"Santa Cruz De Tenerife",
    "wof:name":"Viajes Best Travel S.l.",
    "wof:placetype":"venue"
},
  "geometry": {"coordinates":[-16.2808303833,28.470998764],"type":"Point"}
}