{
  "type": "Feature",
  "properties": {
    "iso:country":"ES",
    "sg:address":"Av. Jose Antonio, 10",
    "sg:city":"Avila",
    "sg:orig_category":"Gerentes De Carteras",
    "sg:phone":"+34 920 35 22 73",
    "sg:postcode":"05001",
    "sg:province":"\u00c1vila",
    "wof:name":"R. Diaz O.c. S.l.",
    "wof:placetype":"venue"
},
  "geometry": {"coordinates":[-4.6878609657,40.6562232971],"type":"Point"}
}