{
  "type": "Feature",
  "properties": {
    "iso:country":"ES",
    "sg:address":"Ctra Camposancos, 88",
    "sg:city":"Verdeal",
    "sg:orig_category":"Quincaller\u00cda (al Por Menor)",
    "sg:phone":"+34 986 23 60 46",
    "sg:postcode":"36213",
    "sg:province":"Pontevedra",
    "wof:name":"Hermanos Gonzalez Paradelo S.a.",
    "wof:placetype":"venue"
},
  "geometry": {"coordinates":[-8.7210121155,42.1948318481],"type":"Point"}
}