{
  "type": "Feature",
  "properties": {
    "iso:country":"ES",
    "sg:address":"Carr Salvador Espriu, 3",
    "sg:city":"Hostal Nou",
    "sg:orig_category":"Ebanister\u00cda",
    "sg:phone":"+34 973 45 12 58",
    "sg:postcode":"25617",
    "sg:province":"Lleida",
    "wof:name":"Mas Alarcon Antonio",
    "wof:placetype":"venue"
},
  "geometry": {"coordinates":[0.822183013,41.790977478],"type":"Point"}
}