{
  "type": "Feature",
  "properties": {
    "iso:country":"ES",
    "sg:address":"Avda Sevilla (de), 112",
    "sg:city":"Rosales",
    "sg:orig_category":"Muebles Y Accesorios Para Cocinas Y Cuartos De Ba\u00d1o (al Por Menor)",
    "sg:phone":"+34 955 64 58 59",
    "sg:postcode":"41330",
    "sg:province":"Sevilla",
    "wof:name":"Serena Perez Antonio",
    "wof:placetype":"venue"
},
  "geometry": {"coordinates":[-5.7300291061,37.589717865],"type":"Point"}
}