{
  "type": "Feature",
  "properties": {
    "iso:country":"ES",
    "sg:address":"G.v. Corts Catalanes, 623",
    "sg:city":"Barcelona",
    "sg:orig_category":"Sociedades, Compa\u00d1\u00cdas Aseguradoras",
    "sg:phone":"+34 933 17 19 50",
    "sg:postcode":"08010",
    "sg:province":"Barcelona",
    "wof:name":"American Life Insurance",
    "wof:placetype":"venue"
},
  "geometry": {"coordinates":[2.1698215008,41.3908538818],"type":"Point"}
}