{
  "type": "Feature",
  "properties": {
    "addr:full":"Calle de Tte Ca\u00d1ellas Alcov, 5 Palma Islas Baleares 07006",
    "addr:housenumber":"5",
    "addr:postcode":"07006",
    "addr:street":"Calle De Tte Can\u0303Ellas Alcov",
    "iso:country":"ES",
    "sg:address":"Calle de Tte Ca\u00d1ellas Alcov, 5",
    "sg:city":"Palma",
    "sg:orig_category":"Quincaller\u00cda (al Por Menor)",
    "sg:phone":"+34 971 27 69 14",
    "sg:postcode":"07006",
    "sg:province":"Islas Baleares",
    "wof:name":"Bonet Mari Victor",
    "wof:placetype":"venue"
},
  "geometry": {"coordinates":[2.6756649017,39.5599861145],"type":"Point"}
}