{
  "type": "Feature",
  "properties": {
    "addr:full":"Calle de Cascabel, 19 Fuentes Leon Badajoz 06280",
    "addr:housenumber":"19",
    "addr:postcode":"06280",
    "addr:street":"Calle De Cascabel",
    "iso:country":"ES",
    "sg:address":"Calle de Cascabel, 19",
    "sg:city":"Fuentes Leon",
    "sg:classifiers":[
        {
            "category":"Taxi",
            "type":"Transportation"
        }
    ],
    "sg:phone":"+34 924 72 42 04",
    "sg:postcode":"06280",
    "sg:province":"Badajoz",
    "wof:name":"Guillen Sanchez Juan Manuel",
    "wof:placetype":"venue"
},
  "geometry": {"coordinates":[-6.5427451134,38.0662460327],"type":"Point"}
}