{
  "type": "Feature",
  "properties": {
    "addr:full":"Pque Cial Sevilla Pl Factory, Km. 0553,8 Dos Hermanas Sevilla 41700",
    "addr:postcode":"41700",
    "addr:street":"Pl Factory Km. 0553,8;Sevilla",
    "iso:country":"ES",
    "sg:address":"Pque Cial Sevilla Pl Factory, Km. 0553,8",
    "sg:city":"Dos Hermanas",
    "sg:orig_category":"Ropa Para Beb\u00c9s Y Ni\u00d1os (confecci\u00d3n, Al Por Mayor)",
    "sg:phone":"+34 955 66 88 68",
    "sg:postcode":"41700",
    "sg:province":"Sevilla",
    "wof:name":"Caribean Textil S.l.",
    "wof:placetype":"venue"
},
  "geometry": {"coordinates":[-5.9281339645,37.2829055786],"type":"Point"}
}