{
  "type": "Feature",
  "properties": {
    "addr:full":"Urb El Castillo, 15 Fuensalda\u00d1a Valladolid 47194",
    "addr:housenumber":"15",
    "addr:postcode":"47194",
    "addr:street":"Urb El Castillo",
    "iso:country":"ES",
    "sg:address":"Urb El Castillo, 15",
    "sg:city":"Fuensalda\u00d1a",
    "sg:orig_category":"Laboratorios Farmac\u00c9uticos",
    "sg:phone":"+34 983 58 32 02",
    "sg:postcode":"47194",
    "sg:province":"Valladolid",
    "wof:name":"Lopez Candeira Marta",
    "wof:placetype":"venue"
},
  "geometry": {"coordinates":[-4.7640070915,41.7066841125],"type":"Point"}
}