{
  "type": "Feature",
  "properties": {
    "iso:country":"ES",
    "sg:address":"Calle de Enrique Navarro, 20",
    "sg:city":"Valencia",
    "sg:orig_category":"Confecci\u00d3n (fabricaci\u00d3n, Al Por Mayor)",
    "sg:phone":"+34 963 69 98 35",
    "sg:postcode":"46020",
    "sg:province":"Valencia",
    "sg:website":"www.saldoscanarias.com",
    "wof:name":"Saldos Canarias S.l.",
    "wof:placetype":"venue"
},
  "geometry": {"coordinates":[-0.3587960005,39.4849205017],"type":"Point"}
}