{
  "type": "Feature",
  "properties": {
    "addr:full":"Avda Antonio Mairena, 26 Alcala Guadaira Sevilla 41500",
    "addr:housenumber":"26",
    "addr:postcode":"41500",
    "addr:street":"Avda Antonio Mairena",
    "iso:country":"ES",
    "sg:address":"Avda Antonio Mairena, 26",
    "sg:city":"Alcala Guadaira",
    "sg:orig_category":"Molduras, Junquillos, Listones Y Molduras Perforadas",
    "sg:phone":"+34 955 68 04 48",
    "sg:postcode":"41500",
    "sg:province":"Sevilla",
    "wof:name":"Bodeguita La Parada S.l.",
    "wof:placetype":"venue"
},
  "geometry": {"coordinates":[-5.8398771286,37.3381347656],"type":"Point"}
}