{
  "type": "Feature",
  "properties": {
    "addr:full":"Calle de Manuel Garcia Conde, 3 Oviedo Asturias 33001",
    "addr:housenumber":"3",
    "addr:postcode":"33001",
    "addr:street":"Calle De Manuel Garcia Conde",
    "iso:country":"ES",
    "sg:address":"Calle de Manuel Garcia Conde, 3",
    "sg:city":"Oviedo",
    "sg:orig_category":"Sociedades, Compa\u00d1\u00cdas Aseguradoras",
    "sg:phone":"+34 985 22 83 84",
    "sg:postcode":"33001",
    "sg:province":"Asturias",
    "sg:website":"www.segurosprincipado.com",
    "wof:name":"Correduria De Seguros Del Principado De Asturias S.a.",
    "wof:placetype":"venue"
},
  "geometry": {"coordinates":[-5.8464198112,43.3667869568],"type":"Point"}
}