{
  "type": "Feature",
  "properties": {
    "iso:country":"ES",
    "sg:address":"Carpinteria (p I Camino Hondo), S/n",
    "sg:city":"Marchena",
    "sg:orig_category":"Fabricaci\u00d3n, Venta, Instalaci\u00d3n De R\u00d3tulos, De R\u00d3tulos Luminosos",
    "sg:phone":"+34 955 84 51 05",
    "sg:postcode":"41620",
    "sg:province":"Sevilla",
    "wof:name":"Vega Lorente Jose Antonio",
    "wof:placetype":"venue"
},
  "geometry": {"coordinates":[-5.4112792015,37.3211364746],"type":"Point"}
}