{
  "type": "Feature",
  "properties": {
    "iso:country":"ES",
    "sg:address":"Calle de San Fernando, 6",
    "sg:city":"Yecla",
    "sg:orig_category":"Molduras, Junquillos, Listones Y Molduras Perforadas",
    "sg:phone":"+34 968 79 51 74",
    "sg:postcode":"30510",
    "sg:province":"Murcia",
    "wof:name":"Diaz Gonzalez Antonio",
    "wof:placetype":"venue"
},
  "geometry": {"coordinates":[-1.1104949713,38.6104393005],"type":"Point"}
}