{
  "type": "Feature",
  "properties": {
    "iso:country":"ES",
    "sg:address":"Carrer de L'abat Odo, 60",
    "sg:city":"Barcelona",
    "sg:orig_category":"Mec\u00c1nico Del Autom\u00d3vil",
    "sg:phone":"+34 933 11 41 03",
    "sg:postcode":"08030",
    "sg:province":"Barcelona",
    "wof:name":"Talleres J M Saludes Mancebon",
    "wof:placetype":"venue"
},
  "geometry": {"coordinates":[2.1848540306,41.4325637817],"type":"Point"}
}