{
  "type": "Feature",
  "properties": {
    "addr:full":"Ctra. N. 340, Km. 0075,0 Tarambana Almer\u00eda 04713",
    "addr:postcode":"04713",
    "addr:street":"Ctra. N. 340 Km. 0075,0 Tarambana Almeri\u0301A",
    "iso:country":"ES",
    "sg:address":"Ctra. N. 340, Km. 0075,0",
    "sg:city":"Tarambana",
    "sg:orig_category":"Hormigonados",
    "sg:phone":"+34 950 40 61 89",
    "sg:postcode":"04713",
    "sg:province":"Almer\u00eda",
    "wof:name":"Ojeda Hormigones Ejido S.l.",
    "wof:placetype":"venue"
},
  "geometry": {"coordinates":[-2.9070239067,36.7499694824],"type":"Point"}
}