{
  "type": "Feature",
  "properties": {
    "iso:country":"ES",
    "sg:address":"Calle de Royal, S/n",
    "sg:city":"Alcorisa",
    "sg:orig_category":"Fabricaci\u00d3n De Muebles",
    "sg:phone":"+34 978 84 02 00",
    "sg:postcode":"44550",
    "sg:province":"Teruel",
    "sg:website":"www.alcorisa.net",
    "wof:name":"Alcomobi S.l.",
    "wof:placetype":"venue"
},
  "geometry": {"coordinates":[-0.3560076058,40.9379425049],"type":"Point"}
}