{
  "type": "Feature",
  "properties": {
    "addr:full":"Carrer de Sant Cugat, 42 Rubi Barcelona 08191",
    "addr:housenumber":"42",
    "addr:postcode":"08191",
    "addr:street":"Carrer De Sant Cugat",
    "iso:country":"ES",
    "sg:address":"Carrer de Sant Cugat, 42",
    "sg:city":"Rubi",
    "sg:orig_category":"Fabricaci\u00d3n De Peines Y De Accesorios De Peluquer\u00cda",
    "sg:phone":"+34 935 88 02 48",
    "sg:postcode":"08191",
    "sg:province":"Barcelona",
    "wof:name":"Tuset Vives Fernando",
    "wof:placetype":"venue"
},
  "geometry": {"coordinates":[2.0327980518,41.4894065857],"type":"Point"}
}