{
  "type": "Feature",
  "properties": {
    "iso:country":"ES",
    "sg:address":"Plaz Lahore, 2",
    "sg:city":"Cordoba",
    "sg:orig_category":"Tapicer\u00cdas",
    "sg:phone":"+34 957 26 01 60",
    "sg:postcode":"14007",
    "sg:province":"C\u00f3rdoba",
    "wof:name":"Granadilla Gomez Jose",
    "wof:placetype":"venue"
},
  "geometry": {"coordinates":[-4.7678642273,37.8967132568],"type":"Point"}
}