{
  "type": "Feature",
  "properties": {
    "addr:full":"Concejo De Olaz, 9 Iru\u00f1a Navarra 31016",
    "addr:housenumber":"9",
    "addr:postcode":"31016",
    "addr:street":"Irun\u0303A Navarra",
    "iso:country":"ES",
    "sg:address":"Concejo De Olaz, 9",
    "sg:city":"Iru\u00f1a",
    "sg:orig_category":"Reposter\u00cdas",
    "sg:phone":"+34 948 16 19 69",
    "sg:postcode":"31016",
    "sg:province":"Navarra",
    "wof:name":"Panaderias Navarra S.a.",
    "wof:placetype":"venue"
},
  "geometry": {"coordinates":[-1.6119689941,42.8081283569],"type":"Point"}
}