{
  "type": "Feature",
  "properties": {
    "addr:full":"Rua Rosalia De Castro (de), 47 Castroverde Lugo 27120",
    "addr:housenumber":"47",
    "addr:postcode":"27120",
    "addr:street":"Rua Rosalia De Castro De",
    "iso:country":"ES",
    "sg:address":"Rua Rosalia De Castro (de), 47",
    "sg:city":"Castroverde",
    "sg:orig_category":"Sanatorios M\u00c9dico",
    "sg:phone":"+34 982 31 23 10",
    "sg:postcode":"27120",
    "sg:province":"Lugo",
    "wof:name":"Ayuntamiento De Castroverde",
    "wof:placetype":"venue"
},
  "geometry": {"coordinates":[-7.3260197639,43.0300979614],"type":"Point"}
}