{
  "type": "Feature",
  "properties": {
    "iso:country":"ES",
    "sg:address":"Carrer de Dos De Maig, 16",
    "sg:city":"Manresa",
    "sg:orig_category":"Alquiler De Veh\u00cdculos: Turismos Y Utilitarios",
    "sg:phone":"+34 938 72 36 90",
    "sg:postcode":"08241",
    "sg:province":"Barcelona",
    "wof:name":"Quads Sotrac S.l.",
    "wof:placetype":"venue"
},
  "geometry": {"coordinates":[1.829069972,41.7212295532],"type":"Point"}
}