{
  "type": "Feature",
  "properties": {
    "addr:full":"Urb El Tomillar, 24 Borriol Castell\u00f3n 12190",
    "addr:housenumber":"24",
    "addr:postcode":"12190",
    "addr:street":"Urb El Tomillar",
    "iso:country":"ES",
    "sg:address":"Urb El Tomillar, 24",
    "sg:city":"Borriol",
    "sg:orig_category":"Fabricaci\u00d3n De Enlosados, Soler\u00cdas",
    "sg:phone":"+34 964 32 18 04",
    "sg:postcode":"12190",
    "sg:province":"Castell\u00f3n",
    "wof:name":"Union Tile Cooperativa Valenciana S.a.",
    "wof:placetype":"venue"
},
  "geometry": {"coordinates":[-0.070262,40.0408325195],"type":"Point"}
}