{
  "type": "Feature",
  "properties": {
    "iso:country":"ES",
    "sg:address":"Pl Industria, 11",
    "sg:city":"Pala De Torruella",
    "sg:orig_category":"Construcciones Met\u00c1licas",
    "sg:phone":"+34 938 69 57 98",
    "sg:postcode":"08269",
    "sg:province":"Barcelona",
    "wof:name":"Gomez Soltero Sergio",
    "wof:placetype":"venue"
},
  "geometry": {"coordinates":[2.1699187756,41.3879165649],"type":"Point"}
}