{
  "type": "Feature",
  "properties": {
    "addr:full":"Calle de San Agustin, 8 Albacete Albacete 02001",
    "addr:housenumber":"8",
    "addr:postcode":"02001",
    "addr:street":"Calle De San Agustin",
    "iso:country":"ES",
    "sg:address":"Calle de San Agustin, 8",
    "sg:city":"Albacete",
    "sg:orig_category":"Sociedades, Compa\u00d1\u00cdas Aseguradoras",
    "sg:phone":"+34 967 24 08 61",
    "sg:postcode":"02001",
    "sg:province":"Albacete",
    "sg:website":"www.lopez-torrijos.com",
    "wof:name":"Correduria De Seguros Lopez Torrijos S.l.",
    "wof:placetype":"venue"
},
  "geometry": {"coordinates":[-1.8529160023,38.9944229126],"type":"Point"}
}