{
  "type": "Feature",
  "properties": {
    "iso:country":"ES",
    "sg:address":"Avda Lugo, 90",
    "sg:city":"Pontevedra",
    "sg:orig_category":"Molduras, Junquillos, Listones Y Molduras Perforadas",
    "sg:phone":"+34 986 85 21 77",
    "sg:postcode":"36004",
    "sg:province":"Pontevedra",
    "wof:name":"Guliar Barreiro Maria Concepcion",
    "wof:placetype":"venue"
},
  "geometry": {"coordinates":[-8.6220769882,42.4345397949],"type":"Point"}
}