{
  "type": "Feature",
  "properties": {
    "addr:full":"Avda Santiago (de), 8 Ourense Ourense 32001",
    "addr:postcode":"32001",
    "addr:street":"Avda Santiago De",
    "iso:country":"ES",
    "sg:address":"Avda Santiago (de), 8",
    "sg:city":"Ourense",
    "sg:orig_category":"Bancos",
    "sg:phone":"+34 988 21 83 35",
    "sg:postcode":"32001",
    "sg:province":"Ourense",
    "sg:website":"www.bancsabadell.com",
    "wof:name":"Banc Sabadell S.a.",
    "wof:placetype":"venue"
},
  "geometry": {"coordinates":[-7.8660540581,42.3506851196],"type":"Point"}
}