{
  "type": "Feature",
  "properties": {
    "iso:country":"ES",
    "sg:address":"Carrer de Narcis Monturiol, 22",
    "sg:city":"S. Quirze Valles",
    "sg:orig_category":"Productos Qu\u00cdmicos (fabricaci\u00d3n, Al Por Mayor)",
    "sg:phone":"+34 937 11 60 54",
    "sg:postcode":"08192",
    "sg:province":"Barcelona",
    "wof:name":"Goldschmidt Espa\u00f1a S.a.",
    "wof:placetype":"venue"
},
  "geometry": {"coordinates":[2.0980710983,41.5301055908],"type":"Point"}
}