{
  "type": "Feature",
  "properties": {
    "addr:full":"Carrer de Amadeu Vives, 30 Barri Maritim Del Francas Tarragona 43880",
    "addr:housenumber":"30",
    "addr:postcode":"43880",
    "addr:street":"Carrer De Amadeu Vives",
    "iso:country":"ES",
    "sg:address":"Carrer de Amadeu Vives, 30",
    "sg:city":"Barri Maritim Del Francas",
    "sg:orig_category":"Piscinas, Accesorios, Suministros (fabricaci\u00d3n, Al Por Mayor)",
    "sg:phone":"+34 977 68 41 04",
    "sg:postcode":"43880",
    "sg:province":"Tarragona",
    "wof:name":"Pisciman S.l.",
    "wof:placetype":"venue"
},
  "geometry": {"coordinates":[1.5386699438,41.1833496094],"type":"Point"}
}