{
  "type": "Feature",
  "properties": {
    "addr:full":"Carr Muntanya, 50 Pobla Islas Baleares 07420",
    "addr:housenumber":"50",
    "addr:postcode":"07420",
    "addr:street":"Carr Muntanya;Baleares",
    "iso:country":"ES",
    "sg:address":"Carr Muntanya, 50",
    "sg:city":"Pobla",
    "sg:orig_category":"Notarios",
    "sg:phone":"+34 971 54 23 40",
    "sg:postcode":"07420",
    "sg:province":"Islas Baleares",
    "wof:name":"Rodriguez De La Rubia Lopez Maria Del Rosario",
    "wof:placetype":"venue"
},
  "geometry": {"coordinates":[3.0273399353,39.7708282471],"type":"Point"}
}