{
  "type": "Feature",
  "properties": {
    "iso:country":"ES",
    "sg:address":"Forjadores, S/n",
    "sg:city":"Boadilla",
    "sg:orig_category":"Herramientas Manuales (fabricaci\u00d3n, Al Por Mayor)",
    "sg:phone":"+34 916 32 47 40",
    "sg:postcode":"28660",
    "sg:province":"Madrid",
    "sg:website":"www.metabo.es",
    "wof:name":"Herramientas Metabo S. A.",
    "wof:placetype":"venue"
},
  "geometry": {"coordinates":[-3.8508791924,40.393157959],"type":"Point"}
}