{
  "type": "Feature",
  "properties": {
    "iso:country":"ES",
    "sg:address":"Calle de Calderon De La Barca, 49",
    "sg:city":"Cuenca",
    "sg:orig_category":"Alimentaci\u00d3n General (al Por Menor)",
    "sg:phone":"+34 969 22 43 59",
    "sg:postcode":"16001",
    "sg:province":"Cuenca",
    "wof:name":"Jimenez Perez Francisco",
    "wof:placetype":"venue"
},
  "geometry": {"coordinates":[-2.1368165016,40.075340271],"type":"Point"}
}