{
  "type": "Feature",
  "properties": {
    "addr:full":"Carrer de Aribau, 38 Barcelona Barcelona 08011",
    "addr:housenumber":"38",
    "addr:postcode":"08011",
    "addr:street":"Carrer De Aribau",
    "iso:country":"ES",
    "sg:address":"Carrer de Aribau, 38",
    "sg:city":"Barcelona",
    "sg:orig_category":"Madera Para Construcci\u00d3n E Industria",
    "sg:phone":"+34 934 51 85 01",
    "sg:postcode":"08011",
    "sg:province":"Barcelona",
    "wof:name":"Aribau Gracia S.a.",
    "wof:placetype":"venue"
},
  "geometry": {"coordinates":[2.1606912613,41.3874206543],"type":"Point"}
}