{
  "type": "Feature",
  "properties": {
    "addr:full":"Poli Pol.indust. El Segre, 203 Lleida Lleida 25191",
    "addr:housenumber":"203",
    "addr:postcode":"25191",
    "addr:street":"El Segre",
    "iso:country":"ES",
    "sg:address":"Poli Pol.indust. El Segre, 203",
    "sg:city":"Lleida",
    "sg:orig_category":"Cooperativas Agr\u00cdcolas",
    "sg:phone":"+34 973 20 12 00",
    "sg:postcode":"25191",
    "sg:province":"Lleida",
    "wof:name":"Copaga S.coop.",
    "wof:placetype":"venue"
},
  "geometry": {"coordinates":[0.6831650138,41.5832138062],"type":"Point"}
}