{
  "type": "Feature",
  "properties": {
    "addr:full":"Calle de Cuba, 55 Valencia Valencia 46006",
    "addr:housenumber":"55",
    "addr:postcode":"46006",
    "addr:street":"Calle De Cuba",
    "iso:country":"ES",
    "sg:address":"Calle de Cuba, 55",
    "sg:city":"Valencia",
    "sg:orig_category":"Abogados",
    "sg:phone":"+34 963 41 67 94",
    "sg:postcode":"46006",
    "sg:province":"Valencia",
    "wof:name":"Solaz Cases Vicente",
    "wof:placetype":"venue"
},
  "geometry": {"coordinates":[-0.3754821122,39.4597969055],"type":"Point"}
}