{
  "type": "Feature",
  "properties": {
    "iso:country":"ES",
    "sg:address":"Calle de Santa Teresa, 14",
    "sg:city":"Lerma",
    "sg:orig_category":"Empresarios",
    "sg:phone":"+34 947 17 00 36",
    "sg:postcode":"09340",
    "sg:province":"Burgos",
    "wof:name":"Garcia Garcia Juan Angel",
    "wof:placetype":"venue"
},
  "geometry": {"coordinates":[-3.7628359795,42.0252532959],"type":"Point"}
}