{
  "type": "Feature",
  "properties": {
    "addr:full":"Calle de Ruda, 23 Madrid Madrid 28005",
    "addr:housenumber":"23",
    "addr:postcode":"madrid;28005",
    "addr:street":"Calle De Ruda",
    "iso:country":"ES",
    "sg:address":"Calle de Ruda, 23",
    "sg:city":"Madrid",
    "sg:orig_category":"Agencias De Viajes",
    "sg:phone":"+34 913 64 16 89",
    "sg:postcode":"28005",
    "sg:province":"Madrid",
    "wof:name":"Kalaallit Nunaat S.l.",
    "wof:placetype":"venue"
},
  "geometry": {"coordinates":[-3.7081851959,40.4105453491],"type":"Point"}
}