{
  "type": "Feature",
  "properties": {
    "iso:country":"ES",
    "sg:address":"Pl Santa Anna, S/n",
    "sg:city":"Esparreguera",
    "sg:orig_category":"Frutas, Legumbres Frescas Y Tempranas (al Por Menor)",
    "sg:phone":"+34 937 08 01 21",
    "sg:postcode":"08292",
    "sg:province":"Barcelona",
    "wof:name":"Lopez Pereda Antonio",
    "wof:placetype":"venue"
},
  "geometry": {"coordinates":[1.8681600094,41.5377349854],"type":"Point"}
}