{
  "type": "Feature",
  "properties": {
    "addr:full":"Calle de Mesena, 102 Madrid Madrid 28033",
    "addr:housenumber":"102",
    "addr:postcode":"28033",
    "addr:street":"Calle De Mesena",
    "iso:country":"ES",
    "sg:address":"Calle de Mesena, 102",
    "sg:city":"Madrid",
    "sg:orig_category":"Laboratorios Y Cl\u00cdnicas Veterinarias",
    "sg:phone":"+34 913 02 76 25",
    "sg:postcode":"28033",
    "sg:province":"Madrid",
    "wof:name":"Calvo Andres Maria Angeles",
    "wof:placetype":"venue"
},
  "geometry": {"coordinates":[-3.6634209156,40.4680595398],"type":"Point"}
}