{
  "type": "Feature",
  "properties": {
    "iso:country":"ES",
    "sg:address":"Avda Tilos (los), 1",
    "sg:city":"Benasque",
    "sg:orig_category":"Asociaciones Y Clubs Deportivos",
    "sg:phone":"+34 974 55 14 21",
    "sg:postcode":"22440",
    "sg:province":"Huesca",
    "wof:name":"Moda Click S.l.",
    "wof:placetype":"venue"
},
  "geometry": {"coordinates":[0.5218899846,42.6037712097],"type":"Point"}
}