{
  "type": "Feature",
  "properties": {
    "addr:full":"Carrer de Nord, 70 Terrassa Barcelona 08221",
    "addr:housenumber":"70",
    "addr:postcode":"08221",
    "addr:street":"Carrer De Nord",
    "iso:country":"ES",
    "sg:address":"Carrer de Nord, 70",
    "sg:city":"Terrassa",
    "sg:orig_category":"Ortopedia General",
    "sg:phone":"+34 937 31 49 64",
    "sg:postcode":"08221",
    "sg:province":"Barcelona",
    "wof:name":"Ortopedia Llorach S.l.",
    "wof:placetype":"venue"
},
  "geometry": {"coordinates":[2.0137279034,41.5673866272],"type":"Point"}
}