{
  "type": "Feature",
  "properties": {
    "iso:country":"ES",
    "sg:address":"Av Ramon I Cajal, 25",
    "sg:city":"Tarragona",
    "sg:orig_category":"Tapiceros Y Tapiceros",
    "sg:phone":"+34 977 24 54 80",
    "sg:postcode":"43001",
    "sg:province":"Tarragona",
    "wof:name":"Rivelles Llaurado Pedro",
    "wof:placetype":"venue"
},
  "geometry": {"coordinates":[1.2467739582,41.1166038513],"type":"Point"}
}