{
  "type": "Feature",
  "properties": {
    "iso:country":"ES",
    "sg:address":"Alam Barcelo, 73",
    "sg:city":"Malaga",
    "sg:orig_category":"Negocio De Materiales De Construcci\u00d3n",
    "sg:phone":"+34 952 25 05 93",
    "sg:postcode":"29014",
    "sg:province":"M\u00e1laga",
    "wof:name":"Puente Fernandez Jose",
    "wof:placetype":"venue"
},
  "geometry": {"coordinates":[-4.4186811447,36.731880188],"type":"Point"}
}