{
  "type": "Feature",
  "properties": {
    "iso:country":"ES",
    "sg:address":"Pase Maritimo, S/n",
    "sg:city":"Cristianos",
    "sg:orig_category":"Ense\u00d1anza, Formaci\u00d3n Profesional: Aprendizaje",
    "sg:phone":"+34 922 78 70 11",
    "sg:postcode":"38650",
    "sg:province":"Santa Cruz De Tenerife",
    "sg:website":"www.arona.org",
    "wof:name":"Patronato De Turismo Ayuntamiento De Arona",
    "wof:placetype":"venue"
},
  "geometry": {"coordinates":[-16.7313289642,28.0631198883],"type":"Point"}
}