{
  "type": "Feature",
  "properties": {
    "iso:country":"ES",
    "sg:address":"Plaz Santo Domingo, 5",
    "sg:city":"Merida",
    "sg:orig_category":"Empresarios Y Productoras De Espect\u00c1culos",
    "sg:phone":"+34 924 31 45 12",
    "sg:postcode":"06800",
    "sg:province":"Badajoz",
    "wof:name":"Programaciones Artisticas Ayuso S.l.",
    "wof:placetype":"venue"
},
  "geometry": {"coordinates":[-6.3447198868,38.9136695862],"type":"Point"}
}