{
  "type": "Feature",
  "properties": {
    "iso:country":"ES",
    "sg:address":"Calle de Aita Donostia, 14",
    "sg:city":"Errenteria",
    "sg:orig_category":"Pescader\u00cdas (al Por Menor)",
    "sg:phone":"+34 943 51 06 87",
    "sg:postcode":"20100",
    "sg:province":"Guip\u00f9zcoa",
    "wof:name":"Martinez De Madina Gil Yolanda",
    "wof:placetype":"venue"
},
  "geometry": {"coordinates":[-1.9113060236,43.3104972839],"type":"Point"}
}