{
  "type": "Feature",
  "properties": {
    "addr:full":"Plaza De La Iglesia, 4 Cambre La Coru\u00f1a 15660",
    "addr:housenumber":"4",
    "addr:postcode":"15660",
    "addr:street":"Iglesia;La Corun\u0303A",
    "iso:country":"ES",
    "sg:address":"Plaza De La Iglesia, 4",
    "sg:city":"Cambre",
    "sg:orig_category":"Asesor\u00cda Fiscal Y Jur\u00cddica",
    "sg:phone":"+34 981 67 64 06",
    "sg:postcode":"15660",
    "sg:province":"La Coru\u00f1a",
    "wof:name":"Asesoria Casas Y Pi\u00f1on S.l.",
    "wof:placetype":"venue"
},
  "geometry": {"coordinates":[-8.2678012848,43.3002891541],"type":"Point"}
}