{
  "type": "Feature",
  "properties": {
    "addr:full":"Calle de San Francisco, 2 Santa Cruz Palma Santa Cruz De Tenerife 38700",
    "addr:housenumber":"2",
    "addr:postcode":"38700",
    "addr:street":"Calle De San Francisco",
    "iso:country":"ES",
    "sg:address":"Calle de San Francisco, 2",
    "sg:city":"Santa Cruz Palma",
    "sg:orig_category":"Art\u00cdculos De Regalo (al Por Menor)",
    "sg:phone":"+34 922 41 43 52",
    "sg:postcode":"38700",
    "sg:province":"Santa Cruz De Tenerife",
    "wof:name":"Mu\u00f1oz Rodriguez Milagros",
    "wof:placetype":"venue"
},
  "geometry": {"coordinates":[-17.7677326202,28.6805782318],"type":"Point"}
}