{
  "type": "Feature",
  "properties": {
    "addr:full":"Carrer de Bauma, S/n Bauma Barcelona 08296",
    "addr:housenumber":"s / n",
    "addr:postcode":"08296",
    "addr:street":"Carrer De Bauma",
    "iso:country":"ES",
    "sg:address":"Carrer de Bauma, S/n",
    "sg:city":"Bauma",
    "sg:orig_category":"Cintas, Balduques Y Cierres De Tela (fabricaci\u00d3n, Al Por Mayor)",
    "sg:phone":"+34 938 34 00 77",
    "sg:postcode":"08296",
    "sg:province":"Barcelona",
    "wof:name":"Manufacturados Textiles S.a.",
    "wof:placetype":"venue"
},
  "geometry": {"coordinates":[1.8563599586,41.6318893433],"type":"Point"}
}