{
  "type": "Feature",
  "properties": {
    "iso:country":"ES",
    "sg:address":"Carrer de Pi, 39",
    "sg:city":"Barriada Nova",
    "sg:orig_category":"Molduras, Junquillos, Listones Y Molduras Perforadas",
    "sg:phone":"+34 938 49 29 23",
    "sg:postcode":"08420",
    "sg:province":"Barcelona",
    "wof:name":"Palu Grau Ramona",
    "wof:placetype":"venue"
},
  "geometry": {"coordinates":[2.2783401012,41.6220207214],"type":"Point"}
}