{
  "type": "Feature",
  "properties": {
    "iso:country":"ES",
    "sg:address":"Calle de Kandela Zubieta Kalea, 43",
    "sg:city":"Elexalde",
    "sg:orig_category":"Telas Para Tapizar, Cortinas, Pasamaner\u00cda (fabricaci\u00d3n, Al Por Mayor)",
    "sg:phone":"+34 944 80 10 04",
    "sg:postcode":"48940",
    "sg:province":"Vizcaya",
    "wof:name":"Revestimientos Feypa S.l.",
    "wof:placetype":"venue"
},
  "geometry": {"coordinates":[-2.9842998981,43.3231468201],"type":"Point"}
}