{
  "type": "Feature",
  "properties": {
    "addr:full":"Calle de Japon, 12 Sevilla Sevilla 41020",
    "addr:housenumber":"12",
    "addr:postcode":"41020",
    "addr:street":"Calle De Japon",
    "iso:country":"ES",
    "sg:address":"Calle de Japon, 12",
    "sg:city":"Sevilla",
    "sg:orig_category":"Agencias Y Agentes Comerciales, Representantes",
    "sg:phone":"+34 955 74 89 78",
    "sg:postcode":"41020",
    "sg:province":"Sevilla",
    "wof:name":"Gaseg&asociados S.c.",
    "wof:placetype":"venue"
},
  "geometry": {"coordinates":[-5.9225177765,37.4038238525],"type":"Point"}
}