{
  "type": "Feature",
  "properties": {
    "addr:full":"Afueras, 18 Soller Islas Baleares 07100",
    "addr:housenumber":"18",
    "addr:postcode":"07100",
    "addr:street":"Afueras",
    "iso:country":"ES",
    "sg:address":"Afueras, 18",
    "sg:city":"Soller",
    "sg:orig_category":"Empresas De Pintura Y Revestimientos",
    "sg:phone":"+34 971 63 38 64",
    "sg:postcode":"07100",
    "sg:province":"Islas Baleares",
    "wof:name":"Arbona Mas Miguel",
    "wof:placetype":"venue"
},
  "geometry": {"coordinates":[2.7083287239,39.7749633789],"type":"Point"}
}