{
  "type": "Feature",
  "properties": {
    "iso:country":"ES",
    "sg:address":"Calle de Ecuador, 4",
    "sg:city":"Cartaya",
    "sg:orig_category":"Alimentaci\u00d3n General (al Por Menor)",
    "sg:phone":"+34 959 39 30 98",
    "sg:postcode":"21450",
    "sg:province":"Huelva",
    "wof:name":"Super Jamon La Antilla S.l.",
    "wof:placetype":"venue"
},
  "geometry": {"coordinates":[-7.1573600769,37.2856445312],"type":"Point"}
}