{
  "type": "Feature",
  "properties": {
    "iso:country":"ES",
    "sg:address":"Calle de Gravina, 12",
    "sg:city":"Huelva",
    "sg:orig_category":"Seguridad En El Trabajo Y Prevenci\u00d3n De Riesgos Laborales",
    "sg:phone":"+34 959 24 80 80",
    "sg:postcode":"21001",
    "sg:province":"Huelva",
    "sg:website":"www.imp-andalucia.com",
    "wof:name":"Ingenieria Y Medicina Preventiva S.l.",
    "wof:placetype":"venue"
},
  "geometry": {"coordinates":[-6.9554848671,37.2578887939],"type":"Point"}
}