{
  "type": "Feature",
  "properties": {
    "addr:full":"Calle de Lopez Mu\u00d1iz, 21 Ribadesella Asturias 33560",
    "addr:housenumber":"21",
    "addr:postcode":"33560",
    "addr:street":"Calle De;Mun\u0303Iz",
    "iso:country":"ES",
    "sg:address":"Calle de Lopez Mu\u00d1iz, 21",
    "sg:city":"Ribadesella",
    "sg:orig_category":"Caf\u00c9s, Bares, Cervecer\u00cdas",
    "sg:phone":"+34 985 86 01 47",
    "sg:postcode":"33560",
    "sg:province":"Asturias",
    "wof:name":"La Llosona Renovadora S.l.",
    "wof:placetype":"venue"
},
  "geometry": {"coordinates":[-5.0586137772,43.4618301392],"type":"Point"}
}