{
  "type": "Feature",
  "properties": {
    "addr:full":"Calle de Fundacion Jado, 10 Altzaga Vizcaya 48950",
    "addr:housenumber":"10",
    "addr:postcode":"48950",
    "addr:street":"Calle De Fundacion Jado",
    "iso:country":"ES",
    "sg:address":"Calle de Fundacion Jado, 10",
    "sg:city":"Altzaga",
    "sg:orig_category":"Ense\u00d1anza: Idiomas",
    "sg:phone":"+34 944 67 63 32",
    "sg:postcode":"48950",
    "sg:province":"Vizcaya",
    "wof:name":"Bristol School Of Languages",
    "wof:placetype":"venue"
},
  "geometry": {"coordinates":[-2.9761810303,43.3034286499],"type":"Point"}
}