{
  "type": "Feature",
  "properties": {
    "iso:country":"ES",
    "sg:address":"Av Mare Deu De Montserrat, 269",
    "sg:city":"Barcelona",
    "sg:orig_category":"Cajas De Ahorro",
    "sg:phone":"+34 933 47 77 77",
    "sg:postcode":"08041",
    "sg:province":"Barcelona",
    "sg:website":"www.caixatarragona.es",
    "wof:name":"Caixa D'estalvis De Tarragona",
    "wof:placetype":"venue"
},
  "geometry": {"coordinates":[2.1762111187,41.4248313904],"type":"Point"}
}