{
  "type": "Feature",
  "properties": {
    "iso:country":"ES",
    "sg:address":"Avda Ramon Y Cajal, 14",
    "sg:city":"Ubeda",
    "sg:orig_category":"Cajas De Ahorro",
    "sg:phone":"+34 953 75 56 58",
    "sg:postcode":"23400",
    "sg:province":"Ja\u00e9n",
    "wof:name":"Caja De Ahorros Y Monte De Piedad De Cordoba",
    "wof:placetype":"venue"
},
  "geometry": {"coordinates":[-3.3739950657,38.0143661499],"type":"Point"}
}