{
  "type": "Feature",
  "properties": {
    "iso:country":"ES",
    "sg:address":"Carrer de Anna Maria Ravell, 5",
    "sg:city":"Arenys Mar",
    "sg:orig_category":"Molduras, Junquillos, Listones Y Molduras Perforadas",
    "sg:phone":"+34 937 95 87 30",
    "sg:postcode":"08350",
    "sg:province":"Barcelona",
    "wof:name":"Cesfat Servicios S.l.",
    "wof:placetype":"venue"
},
  "geometry": {"coordinates":[2.5458340645,41.5824279785],"type":"Point"}
}