{
  "type": "Feature",
  "properties": {
    "iso:country":"ES",
    "sg:address":"Calle de Maestro Francisco Baraga\u00d1a, 1",
    "sg:city":"Pola De Siero",
    "sg:orig_category":"Panader\u00cdas, Panader\u00cdas",
    "sg:phone":"+34 985 72 48 31",
    "sg:postcode":"33510",
    "sg:province":"Asturias",
    "wof:name":"Hevia Lagranda Nicanor",
    "wof:placetype":"venue"
},
  "geometry": {"coordinates":[-5.6607718468,43.3928604126],"type":"Point"}
}