{
  "type": "Feature",
  "properties": {
    "addr:full":"Calle de Libertad, 45 Bejar Salamanca 37700",
    "addr:housenumber":"45",
    "addr:postcode":"37700",
    "addr:street":"Calle De Libertad",
    "iso:country":"ES",
    "sg:address":"Calle de Libertad, 45",
    "sg:city":"Bejar",
    "sg:orig_category":"Ropa Para Se\u00d1oras Y Caballeros (al Por Menor)",
    "sg:phone":"+34 923 40 35 25",
    "sg:postcode":"37700",
    "sg:province":"Salamanca",
    "wof:name":"Hatin  Michelle Jeanine",
    "wof:placetype":"venue"
},
  "geometry": {"coordinates":[-5.7623181343,40.3861351013],"type":"Point"}
}