{
  "type": "Feature",
  "properties": {
    "iso:country":"ES",
    "sg:address":"Calle de Puentearroya, 11",
    "sg:city":"Villasana Mena",
    "sg:orig_category":"Servicios Gsm",
    "sg:phone":"+34 947 14 10 78",
    "sg:postcode":"09580",
    "sg:province":"Burgos",
    "wof:name":"Telemania S.l.",
    "wof:placetype":"venue"
},
  "geometry": {"coordinates":[-3.2813210487,43.100189209],"type":"Point"}
}