{
  "type": "Feature",
  "properties": {
    "iso:country":"ES",
    "sg:address":"Av Sant Miquel Del Pui, 52",
    "sg:city":"Pobla Segur",
    "sg:orig_category":"Mercer\u00cda, Lencer\u00cda (al Por Menor)",
    "sg:phone":"+34 973 68 14 25",
    "sg:postcode":"25500",
    "sg:province":"Lleida",
    "wof:name":"Construcciones Llimi\u00f1ana",
    "wof:placetype":"venue"
},
  "geometry": {"coordinates":[0.9664239883,42.2492980957],"type":"Point"}
}