{
  "type": "Feature",
  "properties": {
    "iso:country":"ES",
    "sg:address":"Calle de Valencia, 4",
    "sg:city":"Benasal",
    "sg:orig_category":"Farmacias",
    "sg:phone":"+34 964 43 13 82",
    "sg:postcode":"12160",
    "sg:province":"Castell\u00f3n",
    "wof:name":"Roig Vives Rosa",
    "wof:placetype":"venue"
},
  "geometry": {"coordinates":[-0.1417649984,40.3795928955],"type":"Point"}
}