{
  "type": "Feature",
  "properties": {
    "addr:full":"Ctra Sagunto-burgos, Km. 0033,6 Segorbe Castell\u00f3n 12400",
    "addr:postcode":"12400",
    "addr:street":"Ctra Sagunto-Burgos Km. 0033,6;Castello\u0301N",
    "iso:country":"ES",
    "sg:address":"Ctra Sagunto-burgos, Km. 0033,6",
    "sg:city":"Segorbe",
    "sg:orig_category":"Confecci\u00d3n De Paraguas, De Sombrillas Y De Bastones",
    "sg:phone":"+34 964 71 17 93",
    "sg:postcode":"12400",
    "sg:province":"Castell\u00f3n",
    "wof:name":"Bastones Lince S.a.l.",
    "wof:placetype":"venue"
},
  "geometry": {"coordinates":[-0.4885739982,39.8518714905],"type":"Point"}
}