{
  "type": "Feature",
  "properties": {
    "addr:full":"Avgd D'almansa, 9 Ontinyent Valencia 46870",
    "addr:housenumber":"9",
    "addr:postcode":"46870",
    "addr:street":"D'Almansa",
    "iso:country":"ES",
    "sg:address":"Avgd D'almansa, 9",
    "sg:city":"Ontinyent",
    "sg:orig_category":"Centros Empresariales",
    "sg:phone":"+34 962 91 05 00",
    "sg:postcode":"46870",
    "sg:province":"Valencia",
    "wof:name":"Sunny Glass S.l.",
    "wof:placetype":"venue"
},
  "geometry": {"coordinates":[-0.6139839888,38.8222808838],"type":"Point"}
}