{
  "type": "Feature",
  "properties": {
    "iso:country":"ES",
    "sg:address":"Avda Doctor Gadea, 24",
    "sg:city":"Alacant",
    "sg:orig_category":"Abogados",
    "sg:phone":"+34 965 20 33 67",
    "sg:postcode":"03001",
    "sg:province":"Alicante",
    "wof:name":"Del Castillo Gomez Laureano Miguel",
    "wof:placetype":"venue"
},
  "geometry": {"coordinates":[-0.4881219864,38.3430862427],"type":"Point"}
}