{
  "type": "Feature",
  "properties": {
    "addr:full":"Avgd Gregorio Molina, 16 Xativa Valencia 46800",
    "addr:housenumber":"16",
    "addr:postcode":"46800",
    "addr:street":"Gregorio Molina",
    "iso:country":"ES",
    "sg:address":"Avgd Gregorio Molina, 16",
    "sg:city":"Xativa",
    "sg:orig_category":"Confecci\u00d3n (fabricaci\u00d3n, Al Por Mayor)",
    "sg:phone":"+34 962 28 20 82",
    "sg:postcode":"46800",
    "sg:province":"Valencia",
    "wof:name":"Pakima S.l.",
    "wof:placetype":"venue"
},
  "geometry": {"coordinates":[-0.5221170187,38.9913787842],"type":"Point"}
}