{
  "type": "Feature",
  "properties": {
    "addr:full":"Carr Santa Eugenia, 52 Girona Girona 17005",
    "addr:housenumber":"52",
    "addr:postcode":"17005",
    "addr:street":"Carr Santa Eugenia",
    "iso:country":"ES",
    "sg:address":"Carr Santa Eugenia, 52",
    "sg:city":"Girona",
    "sg:orig_category":"Alumbrados",
    "sg:phone":"+34 972 21 12 32",
    "sg:postcode":"17005",
    "sg:province":"Girona",
    "wof:name":"Bertolin Rodriguez Alejandro",
    "wof:placetype":"venue"
},
  "geometry": {"coordinates":[2.8144309521,41.9806404114],"type":"Point"}
}