{
  "type": "Feature",
  "properties": {
    "addr:full":"Calle de Arzobispo Gasch, 1 Alcora Castell\u00f3n 12110",
    "addr:housenumber":"1",
    "addr:postcode":"12110",
    "addr:street":"Calle De Arzobispo Gasch;Castello\u0301N",
    "iso:country":"ES",
    "sg:address":"Calle de Arzobispo Gasch, 1",
    "sg:city":"Alcora",
    "sg:orig_category":"Bancos",
    "sg:phone":"+34 964 36 15 37",
    "sg:postcode":"12110",
    "sg:province":"Castell\u00f3n",
    "sg:website":"www.bancosabadell.com",
    "wof:name":"Banc Sabadell S.a.",
    "wof:placetype":"venue"
},
  "geometry": {"coordinates":[-0.2143000066,40.0747261047],"type":"Point"}
}