{
  "type": "Feature",
  "properties": {
    "addr:full":"Calle de Guayedra, 4 Palmas De Gran Canaria Las Palmas 35009",
    "addr:housenumber":"4",
    "addr:postcode":"35009",
    "addr:street":"Calle De Guayedra",
    "iso:country":"ES",
    "sg:address":"Calle de Guayedra, 4",
    "sg:city":"Palmas De Gran Canaria",
    "sg:orig_category":"Molduras, Junquillos, Listones Y Molduras Perforadas",
    "sg:phone":"+34 928 46 92 06",
    "sg:postcode":"35009",
    "sg:province":"Las Palmas",
    "wof:name":"Almeida Diaz Daniel",
    "wof:placetype":"venue"
},
  "geometry": {"coordinates":[-15.4265499115,28.1515312195],"type":"Point"}
}