{
  "type": "Feature",
  "properties": {
    "iso:country":"ES",
    "sg:address":"Avda Albacete, 8",
    "sg:city":"Fuentealbilla",
    "sg:orig_category":"Farmacias",
    "sg:phone":"+34 967 47 20 17",
    "sg:postcode":"02260",
    "sg:province":"Albacete",
    "wof:name":"O\u00f1ate Cebrian Maria Josefa",
    "wof:placetype":"venue"
},
  "geometry": {"coordinates":[-1.5511800051,39.2664031982],"type":"Point"}
}