{
  "type": "Feature",
  "properties": {
    "iso:country":"ES",
    "sg:address":"Calle de Sevilla, 41",
    "sg:city":"Jerez De La Frontera",
    "sg:orig_category":"Asesor\u00cda Fiscal Y Jur\u00cddica",
    "sg:phone":"+34 956 34 66 76",
    "sg:postcode":"11402",
    "sg:province":"C\u00e1diz",
    "wof:name":"Lara Farfante Cayetano",
    "wof:placetype":"venue"
},
  "geometry": {"coordinates":[-6.1365189552,36.6899642944],"type":"Point"}
}