{
  "type": "Feature",
  "properties": {
    "addr:full":"Iturralde Auzoa, 2 Lizartza Guip\u00f9zcoa 20490",
    "addr:housenumber":"2",
    "addr:postcode":"20490",
    "addr:street":"Iturralde Auzoa;Guipu\u0300Zcoa",
    "iso:country":"ES",
    "sg:address":"Iturralde Auzoa, 2",
    "sg:city":"Lizartza",
    "sg:orig_category":"Empresas De Electricidad En General",
    "sg:phone":"+34 943 68 21 99",
    "sg:postcode":"20490",
    "sg:province":"Guip\u00f9zcoa",
    "wof:name":"Minicentrales De Araxes S.a.",
    "wof:placetype":"venue"
},
  "geometry": {"coordinates":[-2.03292799,43.1034126282],"type":"Point"}
}