{
  "type": "Feature",
  "properties": {
    "addr:full":"Carrer de Balmes, 74 Sabadell Barcelona 08203",
    "addr:housenumber":"74",
    "addr:postcode":"08203",
    "addr:street":"Carrer De Balmes",
    "iso:country":"ES",
    "sg:address":"Carrer de Balmes, 74",
    "sg:city":"Sabadell",
    "sg:orig_category":"Motocicletas (agentes, Concesionarios)",
    "sg:phone":"+34 937 25 99 04",
    "sg:postcode":"08203",
    "sg:province":"Barcelona",
    "sg:website":"www.limitmotos.com",
    "wof:name":"Limit Motos S.l.",
    "wof:placetype":"venue"
},
  "geometry": {"coordinates":[2.1186571121,41.5405807495],"type":"Point"}
}