{
  "type": "Feature",
  "properties": {
    "addr:full":"Calle de Muguruza, 17 Barakaldo Vizcaya 48901",
    "addr:housenumber":"17",
    "addr:postcode":"48901",
    "addr:street":"Calle De Muguruza",
    "iso:country":"ES",
    "sg:address":"Calle de Muguruza, 17",
    "sg:city":"Barakaldo",
    "sg:orig_category":"Carnicer\u00cdas, Carnicer\u00cdas",
    "sg:phone":"+34 944 37 19 64",
    "sg:postcode":"48901",
    "sg:province":"Vizcaya",
    "wof:name":"Ascension  Cantalapiedra Gutierrez",
    "wof:placetype":"venue"
},
  "geometry": {"coordinates":[-2.9929764271,43.2993507385],"type":"Point"}
}