{
  "type": "Feature",
  "properties": {
    "iso:country":"ES",
    "sg:address":"Avda Reina Maria Cristina, S/n",
    "sg:city":"Candas",
    "sg:orig_category":"Sanatorios M\u00c9dico",
    "sg:phone":"+34 985 87 12 16",
    "sg:postcode":"33430",
    "sg:province":"Asturias",
    "wof:name":"Insalud-atencion Primaria V-ambulatorio De Gijon",
    "wof:placetype":"venue"
},
  "geometry": {"coordinates":[-5.7675280571,43.5905227661],"type":"Point"}
}