{
  "type": "Feature",
  "properties": {
    "addr:full":"Calle de Ejido, 11 Haba Badajoz 06714",
    "addr:housenumber":"11",
    "addr:postcode":"06714",
    "addr:street":"Calle De Ejido",
    "iso:country":"ES",
    "sg:address":"Calle de Ejido, 11",
    "sg:city":"Haba",
    "sg:orig_category":"Alquiler De V\u00cddeo",
    "sg:phone":"+34 924 82 33 75",
    "sg:postcode":"06714",
    "sg:province":"Badajoz",
    "wof:name":"Comunidad De Propietarios Ejido 11",
    "wof:placetype":"venue"
},
  "geometry": {"coordinates":[-5.80163908,38.9189414978],"type":"Point"}
}