{
  "type": "Feature",
  "properties": {
    "iso:country":"ES",
    "sg:address":"Ctra Huelva, S/n",
    "sg:city":"Villanueva De Los Castillejos",
    "sg:orig_category":"Agencias Y Agentes Comerciales, Representantes",
    "sg:phone":"+34 959 50 40 42",
    "sg:postcode":"21540",
    "sg:province":"Huelva",
    "wof:name":"Marquez Gomez Juana",
    "wof:placetype":"venue"
},
  "geometry": {"coordinates":[-7.2696962357,37.4989280701],"type":"Point"}
}