{
  "type": "Feature",
  "properties": {
    "addr:full":"Calle de Valverde, 29 Madrid Madrid 28004",
    "addr:housenumber":"29",
    "addr:postcode":"madrid;28004",
    "addr:street":"Calle De Valverde",
    "iso:country":"ES",
    "sg:address":"Calle de Valverde, 29",
    "sg:city":"Madrid",
    "sg:orig_category":"Reparaci\u00d3n, Mantenimiento De Instrumentos Y Accesorios De M\u00dasica",
    "sg:phone":"+34 915 31 15 38",
    "sg:postcode":"28004",
    "sg:province":"Madrid",
    "wof:name":"Coll Fabrellas Roberto",
    "wof:placetype":"venue"
},
  "geometry": {"coordinates":[-3.7018270493,40.4227142334],"type":"Point"}
}