{
  "type": "Feature",
  "properties": {
    "iso:country":"ES",
    "sg:address":"Carrer de Rosari, 45",
    "sg:city":"Barcelona",
    "sg:orig_category":"Bancos",
    "sg:phone":"+34 932 11 05 04",
    "sg:postcode":"08017",
    "sg:province":"Barcelona",
    "wof:name":"Banco Popular Espa\u00f1ol S. A.",
    "wof:placetype":"venue"
},
  "geometry": {"coordinates":[2.1318950653,41.3979530334],"type":"Point"}
}