{
  "type": "Feature",
  "properties": {
    "addr:full":"Carrer de Pau Rigalt, 74 Sabadell Barcelona 08208",
    "addr:housenumber":"74",
    "addr:postcode":"08208",
    "addr:street":"Carrer De Pau Rigalt",
    "iso:country":"ES",
    "sg:address":"Carrer de Pau Rigalt, 74",
    "sg:city":"Sabadell",
    "sg:orig_category":"Caf\u00c9s, Bares, Cervecer\u00cdas",
    "sg:phone":"+34 937 17 28 03",
    "sg:postcode":"08208",
    "sg:province":"Barcelona",
    "wof:name":"Porce Mesa Diego",
    "wof:placetype":"venue"
},
  "geometry": {"coordinates":[2.1040248871,41.5598526001],"type":"Point"}
}