{
  "type": "Feature",
  "properties": {
    "addr:full":"Carrer de Antonio Machado (d'), 14 Montornes Nord Barcelona 08170",
    "addr:housenumber":"14",
    "addr:postcode":"08170",
    "addr:street":"Carrer De Antonio Machado D '",
    "iso:country":"ES",
    "sg:address":"Carrer de Antonio Machado (d'), 14",
    "sg:city":"Montornes Nord",
    "sg:orig_category":"Resinas Sint\u00c9ticas (fabricaci\u00d3n, Al Por Mayor)",
    "sg:phone":"+34 935 72 38 55",
    "sg:postcode":"08170",
    "sg:province":"Barcelona",
    "wof:name":"Sumitomo Bakelite Europe S.l.u.",
    "wof:placetype":"venue"
},
  "geometry": {"coordinates":[2.2665019035,41.5539131165],"type":"Point"}
}