{
  "type": "Feature",
  "properties": {
    "addr:full":"Carr Valls, 3 Palafrugell Girona 17200",
    "addr:housenumber":"3",
    "addr:postcode":"17200",
    "addr:street":"Carr Valls",
    "iso:country":"ES",
    "sg:address":"Carr Valls, 3",
    "sg:city":"Palafrugell",
    "sg:orig_category":"Organismos De Turismo",
    "sg:phone":"+34 972 30 78 55",
    "sg:postcode":"17200",
    "sg:province":"Girona",
    "wof:name":"Jozurc Servei S.l.",
    "wof:placetype":"venue"
},
  "geometry": {"coordinates":[3.164511919,41.9176177979],"type":"Point"}
}