{
  "type": "Feature",
  "properties": {
    "addr:full":"Avda Playa Honda, 18 Playa Honda Las Palmas 35509",
    "addr:housenumber":"18",
    "addr:postcode":"35509",
    "addr:street":"Avda Playa Honda",
    "iso:country":"ES",
    "sg:address":"Avda Playa Honda, 18",
    "sg:city":"Playa Honda",
    "sg:orig_category":"Comercio De Piezas De Recambio Y De Accesorios De Veh\u00cdculos, Veh\u00cdculos Industriales",
    "sg:phone":"+34 928 82 21 36",
    "sg:postcode":"35509",
    "sg:province":"Las Palmas",
    "sg:website":"www.auteide.com",
    "wof:name":"Recambios Auteide S.a.",
    "wof:placetype":"venue"
},
  "geometry": {"coordinates":[-13.5858736038,28.9515094757],"type":"Point"}
}