{
  "type": "Feature",
  "properties": {
    "addr:full":"Avda Tierra Llana, 27 Vilalba Lugo 27800",
    "addr:housenumber":"27",
    "addr:postcode":"27800",
    "addr:street":"Avda Tierra Llana",
    "iso:country":"ES",
    "sg:address":"Avda Tierra Llana, 27",
    "sg:city":"Vilalba",
    "sg:orig_category":"Negocio De Materiales De Construcci\u00d3n",
    "sg:phone":"+34 982 52 33 24",
    "sg:postcode":"27800",
    "sg:province":"Lugo",
    "wof:name":"Os Do Gas Sociedad Coop. Galega",
    "wof:placetype":"venue"
},
  "geometry": {"coordinates":[-7.6792550087,43.2963905334],"type":"Point"}
}