{
  "type": "Feature",
  "properties": {
    "iso:country":"ES",
    "sg:address":"Calle de Almendro, 19",
    "sg:city":"Carranque",
    "sg:orig_category":"Agencias Y Agentes Comerciales, Representantes",
    "sg:phone":"+34 925 54 49 09",
    "sg:postcode":"45216",
    "sg:province":"Toledo",
    "wof:name":"Cama\u00f1o Poveda Santiago",
    "wof:placetype":"venue"
},
  "geometry": {"coordinates":[-3.9022862911,40.1635246277],"type":"Point"}
}