{
  "type": "Feature",
  "properties": {
    "addr:full":"Plaz Ronda (de), S/n Jerez De La Frontera C\u00e1diz 11405",
    "addr:postcode":"11405",
    "addr:street":"Ronda De S / N",
    "iso:country":"ES",
    "sg:address":"Plaz Ronda (de), S/n",
    "sg:city":"Jerez De La Frontera",
    "sg:orig_category":"Carnicer\u00cdas, Carnicer\u00cdas",
    "sg:phone":"+34 956 31 15 37",
    "sg:postcode":"11405",
    "sg:province":"C\u00e1diz",
    "wof:name":"Reguera Moron Antonio",
    "wof:placetype":"venue"
},
  "geometry": {"coordinates":[-6.1066012383,36.6959533691],"type":"Point"}
}