{
  "type": "Feature",
  "properties": {
    "iso:country":"ES",
    "sg:address":"Calle de San Luis, S/n",
    "sg:city":"Almeria",
    "sg:orig_category":"Muebles, Minoristas",
    "sg:phone":"+34 950 22 25 25",
    "sg:postcode":"04009",
    "sg:province":"Almer\u00eda",
    "sg:website":"www.merkamueble.com",
    "wof:name":"Mago Seleccion Almeria S.l.",
    "wof:placetype":"venue"
},
  "geometry": {"coordinates":[-2.4456090927,36.8483581543],"type":"Point"}
}