{
  "type": "Feature",
  "properties": {
    "addr:full":"Calle de Centro, 4 Zaragoza Zaragoza 50009",
    "addr:housenumber":"4",
    "addr:postcode":"50009",
    "addr:street":"Calle De Centro",
    "iso:country":"ES",
    "sg:address":"Calle de Centro, 4",
    "sg:city":"Zaragoza",
    "sg:orig_category":"Guarder\u00cdas",
    "sg:phone":"+34 976 56 40 26",
    "sg:postcode":"50009",
    "sg:province":"Zaragoza",
    "wof:name":"Hernandez Nu\u00d1o Blanca",
    "wof:placetype":"venue"
},
  "geometry": {"coordinates":[-0.9091361761,41.6319999695],"type":"Point"}
}