{
  "type": "Feature",
  "properties": {
    "iso:country":"ES",
    "sg:address":"Calle de General Serrano, 47",
    "sg:city":"Santa Cruz De Tenerife",
    "sg:orig_category":"Agentes Generales De Seguros",
    "sg:phone":"+34 922 24 80 27",
    "sg:postcode":"38004",
    "sg:province":"Santa Cruz De Tenerife",
    "wof:name":"Padilla Carmona Victor",
    "wof:placetype":"venue"
},
  "geometry": {"coordinates":[-16.2598190308,28.4668426514],"type":"Point"}
}