{
  "type": "Feature",
  "properties": {
    "iso:country":"ES",
    "sg:address":"Plaz Marina De La, 1",
    "sg:city":"Malaga",
    "sg:orig_category":"M\u00c9dicos: Estomatolog\u00cda",
    "sg:phone":"+34 952 60 23 20",
    "sg:postcode":"29015",
    "sg:province":"M\u00e1laga",
    "wof:name":"Sanchez La Chica Javier",
    "wof:placetype":"venue"
},
  "geometry": {"coordinates":[-4.4201588631,36.7183189392],"type":"Point"}
}