{
  "type": "Feature",
  "properties": {
    "addr:full":"Rbla San Julian (de), S/n Teruel Teruel 44003",
    "addr:postcode":"44003",
    "addr:street":"Rbla San Julian De S / N;Teruel",
    "iso:country":"ES",
    "sg:address":"Rbla San Julian (de), S/n",
    "sg:city":"Teruel",
    "sg:orig_category":"Mec\u00c1nico Del Autom\u00d3vil",
    "sg:phone":"+34 978 60 69 66",
    "sg:postcode":"44003",
    "sg:province":"Teruel",
    "wof:name":"Romero Minguez Juan",
    "wof:placetype":"venue"
},
  "geometry": {"coordinates":[-1.102504015,40.3416099548],"type":"Point"}
}