{
  "type": "Feature",
  "properties": {
    "iso:country":"ES",
    "sg:address":"Cta. Era, S/n",
    "sg:city":"Huetor-santillan",
    "sg:orig_category":"Artes Gr\u00c1ficas, Artes Pl\u00c1sticas: Material Y Suministros (al Por Menor)",
    "sg:phone":"+34 958 54 60 02",
    "sg:postcode":"18183",
    "sg:province":"Granada",
    "wof:name":"Ortega Hita Enrique",
    "wof:placetype":"venue"
},
  "geometry": {"coordinates":[-3.5175049305,37.2187614441],"type":"Point"}
}