{
  "type": "Feature",
  "properties": {
    "iso:country":"ES",
    "sg:address":"Avda Sevilla (de), S/n",
    "sg:city":"Chipiona",
    "sg:orig_category":"Doctores En Medicina",
    "sg:phone":"+34 956 37 03 81",
    "sg:postcode":"11550",
    "sg:province":"C\u00e1diz",
    "wof:name":"Timermans Ceballos Anselmo",
    "wof:placetype":"venue"
},
  "geometry": {"coordinates":[-6.4387989044,36.7361106873],"type":"Point"}
}