{
  "type": "Feature",
  "properties": {
    "addr:full":"Rua Praia De Mi\u00d1o, 4 Ferrol La Coru\u00f1a 15405",
    "addr:housenumber":"4",
    "addr:postcode":"15405",
    "addr:street":"Rua Praia De Min\u0303O;La Corun\u0303A",
    "iso:country":"ES",
    "sg:address":"Rua Praia De Mi\u00d1o, 4",
    "sg:city":"Ferrol",
    "sg:orig_category":"Transporte En General",
    "sg:phone":"+34 981 32 84 20",
    "sg:postcode":"15405",
    "sg:province":"La Coru\u00f1a",
    "wof:name":"Almacenes Los Eucaliptos S.l.",
    "wof:placetype":"venue"
},
  "geometry": {"coordinates":[-8.2185640335,43.497833252],"type":"Point"}
}