{
  "type": "Feature",
  "properties": {
    "iso:country":"ES",
    "sg:address":"Avda Paseo De Almeria, 32",
    "sg:city":"Almeria",
    "sg:orig_category":"Abogados",
    "sg:phone":"+34 950 27 24 71",
    "sg:postcode":"04001",
    "sg:province":"Almer\u00eda",
    "wof:name":"Garrido Puig Jose Javier",
    "wof:placetype":"venue"
},
  "geometry": {"coordinates":[-2.4608390331,36.8422698975],"type":"Point"}
}