{
  "type": "Feature",
  "properties": {
    "addr:full":"Avda Andalucia, 8 Monte Alto C\u00f3rdoba 14100",
    "addr:housenumber":"8",
    "addr:postcode":"14100",
    "addr:street":"Avda Andalucia;Co\u0301Rdoba",
    "iso:country":"ES",
    "sg:address":"Avda Andalucia, 8",
    "sg:city":"Monte Alto",
    "sg:orig_category":"Transportes Por V\u00cdas Navegables",
    "sg:phone":"+34 957 30 12 17",
    "sg:postcode":"14100",
    "sg:province":"C\u00f3rdoba",
    "wof:name":"Granados Galvez Tomas",
    "wof:placetype":"venue"
},
  "geometry": {"coordinates":[-4.9374890327,37.6685142517],"type":"Point"}
}