{
  "type": "Feature",
  "properties": {
    "iso:country":"ES",
    "sg:address":"Calle de Ancha, 53",
    "sg:city":"Huetor-tajar",
    "sg:orig_category":"Carnicer\u00cdas, Carnicer\u00cdas",
    "sg:phone":"+34 958 33 42 03",
    "sg:postcode":"18360",
    "sg:province":"Granada",
    "wof:name":"Perez Moldero Antonia",
    "wof:placetype":"venue"
},
  "geometry": {"coordinates":[-4.0473861694,37.1971168518],"type":"Point"}
}