{
  "type": "Feature",
  "properties": {
    "addr:full":"Calle de Empedrada, 33 Villarrubia De Los Ojos Ciudad Real 13670",
    "addr:housenumber":"33",
    "addr:postcode":"13670",
    "addr:street":"Calle De Empedrada",
    "iso:country":"ES",
    "sg:address":"Calle de Empedrada, 33",
    "sg:city":"Villarrubia De Los Ojos",
    "sg:orig_category":"Supermercados Y Hipermercados",
    "sg:phone":"+34 926 89 88 25",
    "sg:postcode":"13670",
    "sg:province":"Ciudad Real",
    "wof:name":"Obdulia Megias S.l.",
    "wof:placetype":"venue"
},
  "geometry": {"coordinates":[-3.6084492207,39.218460083],"type":"Point"}
}