{
  "type": "Feature",
  "properties": {
    "addr:full":"Plaz Uruguay (de), 4 Coslada Madrid 28820",
    "addr:postcode":"28820",
    "addr:street":"De 4",
    "iso:country":"ES",
    "sg:address":"Plaz Uruguay (de), 4",
    "sg:city":"Coslada",
    "sg:orig_category":"Lencer\u00cda Femenina, Corseter\u00cda, Trajes De Ba\u00d1o (al Por Menor)",
    "sg:phone":"+34 916 69 23 01",
    "sg:postcode":"28820",
    "sg:province":"Madrid",
    "wof:name":"Moranchel Romo Bienvenido",
    "wof:placetype":"venue"
},
  "geometry": {"coordinates":[-3.5645070076,40.4260902405],"type":"Point"}
}