{
  "type": "Feature",
  "properties": {
    "iso:country":"ES",
    "sg:address":"Calle de Doctor Gadea, 1",
    "sg:city":"Sant Joan D'alacant",
    "sg:classifiers":[
        {
            "category":"Personal",
            "subcategory":"Barber",
            "type":"Services"
        }
    ],
    "sg:phone":"+34 965 65 38 37",
    "sg:postcode":"03550",
    "sg:province":"Alicante",
    "sg:tags":[
        "caballeros",
        "de",
        "peluqueros"
    ],
    "wof:name":"Navarro Alemany Manuel",
    "wof:placetype":"venue"
},
  "geometry": {"coordinates":[-0.4326219857,38.3975372314],"type":"Point"}
}