{
  "type": "Feature",
  "properties": {
    "iso:country":"ES",
    "sg:address":"Calle de Ruiz Hernandez, 12",
    "sg:city":"Valladolid",
    "sg:orig_category":"Promotores Constructores",
    "sg:phone":"+34 983 21 37 64",
    "sg:postcode":"47002",
    "sg:province":"Valladolid",
    "wof:name":"Peninsular De Contratas S. A.",
    "wof:placetype":"venue"
},
  "geometry": {"coordinates":[-4.7197551727,41.6526947021],"type":"Point"}
}