{
  "type": "Feature",
  "properties": {
    "iso:country":"ES",
    "sg:address":"Pase General Davila, 276",
    "sg:city":"Santander",
    "sg:orig_category":"Cervecer\u00cdas",
    "sg:phone":"+34 942 34 44 62",
    "sg:postcode":"39006",
    "sg:province":"Cantabria",
    "wof:name":"Alonso Abascal Jose Antonio",
    "wof:placetype":"venue"
},
  "geometry": {"coordinates":[-3.8206059933,43.4641990662],"type":"Point"}
}