{
  "type": "Feature",
  "properties": {
    "addr:full":"Calle de Escoriaza Y Fabro, 109 Zaragoza Zaragoza 50010",
    "addr:housenumber":"109",
    "addr:postcode":"50010",
    "addr:street":"Calle De Escoriaza Y Fabro",
    "iso:country":"ES",
    "sg:address":"Calle de Escoriaza Y Fabro, 109",
    "sg:city":"Zaragoza",
    "sg:orig_category":"Aparatos, Sistemas De Tele",
    "sg:phone":"+34 976 53 54 16",
    "sg:postcode":"50010",
    "sg:province":"Zaragoza",
    "wof:name":"Comelza S.l.",
    "wof:placetype":"venue"
},
  "geometry": {"coordinates":[-0.8995040059,41.6544914246],"type":"Point"}
}