{
  "type": "Feature",
  "properties": {
    "addr:full":"Calle de Almonte, 8 Palma Condado Huelva 21700",
    "addr:housenumber":"8",
    "addr:postcode":"21700",
    "addr:street":"Calle De Almonte",
    "iso:country":"ES",
    "sg:address":"Calle de Almonte, 8",
    "sg:city":"Palma Condado",
    "sg:orig_category":"Distribuci\u00d3n De Petr\u00d3leo Y Derivados",
    "sg:phone":"+34 959 40 15 18",
    "sg:postcode":"21700",
    "sg:province":"Huelva",
    "sg:website":"www.cepsa.es",
    "wof:name":"Hijos De Alfonso Garrido Delgado S.a.",
    "wof:placetype":"venue"
},
  "geometry": {"coordinates":[-6.5521664619,37.381816864],"type":"Point"}
}