{
  "type": "Feature",
  "properties": {
    "iso:country":"ES",
    "sg:address":"Calle de Pascual Amat, 19",
    "sg:city":"Yecla",
    "sg:orig_category":"Pescader\u00cdas (al Por Menor)",
    "sg:phone":"+34 968 75 21 71",
    "sg:postcode":"30510",
    "sg:province":"Murcia",
    "wof:name":"Arres Diaz Leandro",
    "wof:placetype":"venue"
},
  "geometry": {"coordinates":[-1.1164938211,38.6147155762],"type":"Point"}
}