{
  "type": "Feature",
  "properties": {
    "iso:country":"ES",
    "sg:address":"Calle de Oviedo, 6",
    "sg:city":"Burgos",
    "sg:orig_category":"Molduras, Junquillos, Listones Y Molduras Perforadas",
    "sg:phone":"+34 947 26 62 92",
    "sg:postcode":"09002",
    "sg:province":"Burgos",
    "wof:name":"Iba\u00f1ez Arribas Jose Manuel",
    "wof:placetype":"venue"
},
  "geometry": {"coordinates":[-3.7002310753,42.3372955322],"type":"Point"}
}