{
  "type": "Feature",
  "properties": {
    "addr:full":"Lege Zaharren Enparantza, 3 Zarautz Guip\u00f9zcoa 20800",
    "addr:housenumber":"3",
    "addr:postcode":"20800",
    "addr:street":"Lege Zaharren Enparantza;Guipu\u0300Zcoa",
    "iso:country":"ES",
    "sg:address":"Lege Zaharren Enparantza, 3",
    "sg:city":"Zarautz",
    "sg:orig_category":"M\u00c9dicos: Medicina General Orientada A La Acupuntura",
    "sg:phone":"+34 943 83 22 23",
    "sg:postcode":"20800",
    "sg:province":"Guip\u00f9zcoa",
    "wof:name":"Troncoso Mosquera Eduardo",
    "wof:placetype":"venue"
},
  "geometry": {"coordinates":[-2.1749589443,43.2848472595],"type":"Point"}
}