{
  "type": "Feature",
  "properties": {
    "addr:full":"Calle de Ntra Sra Del Salz, 35 Zaragoza Zaragoza 50017",
    "addr:housenumber":"35",
    "addr:postcode":"50017",
    "addr:street":"Calle De Ntra Sra Del Salz",
    "iso:country":"ES",
    "sg:address":"Calle de Ntra Sra Del Salz, 35",
    "sg:city":"Zaragoza",
    "sg:orig_category":"Motocicletas (agentes, Concesionarios)",
    "sg:phone":"+34 976 32 05 29",
    "sg:postcode":"50017",
    "sg:province":"Zaragoza",
    "wof:name":"Motorad Zaragoza S.c",
    "wof:placetype":"venue"
},
  "geometry": {"coordinates":[-0.9145569801,41.6490898132],"type":"Point"}
}