{
  "type": "Feature",
  "properties": {
    "addr:full":"Carrer de M D Sales, 34 Viladecans Barcelona 08840",
    "addr:housenumber":"34",
    "addr:postcode":"08840",
    "addr:street":"Carrer De M;Sales",
    "iso:country":"ES",
    "sg:address":"Carrer de M D Sales, 34",
    "sg:city":"Viladecans",
    "sg:orig_category":"Frutas, Legumbres Frescas Y Tempranas (al Por Menor)",
    "sg:phone":"+34 936 58 36 14",
    "sg:postcode":"08840",
    "sg:province":"Barcelona",
    "wof:name":"Castello Salvador Isabel",
    "wof:placetype":"venue"
},
  "geometry": {"coordinates":[2.021805048,41.3167800903],"type":"Point"}
}