{
  "type": "Feature",
  "properties": {
    "addr:full":"Avda Alcalde Jose Victori Go\u00d1alons, 18 Ceuta Ceuta 51001",
    "addr:housenumber":"18",
    "addr:postcode":"51001",
    "addr:street":"Avda Alcalde Jose;Gon\u0303Alons",
    "iso:country":"ES",
    "sg:address":"Avda Alcalde Jose Victori Go\u00d1alons, 18",
    "sg:city":"Ceuta",
    "sg:orig_category":"Bazares, Art\u00cdculos De Limpieza Y De Cocina (al Por Menor)",
    "sg:phone":"+34 956 51 71 01",
    "sg:postcode":"51001",
    "sg:province":"Ceuta",
    "wof:name":"Mohamed Mohamed Jotar",
    "wof:placetype":"venue"
},
  "geometry": {"coordinates":[-5.3302302361,35.8947601318],"type":"Point"}
}