{
  "type": "Feature",
  "properties": {
    "addr:full":"Carrer de Pedraforca, 44 Hospitalet Llobregat Barcelona 08905",
    "addr:housenumber":"44",
    "addr:postcode":"08905",
    "addr:street":"Carrer De Pedraforca",
    "iso:country":"ES",
    "sg:address":"Carrer de Pedraforca, 44",
    "sg:city":"Hospitalet Llobregat",
    "sg:orig_category":"Administradores De Bienes Y Delegados De Comunidades De Propietarios",
    "sg:phone":"+34 934 49 14 55",
    "sg:postcode":"08905",
    "sg:province":"Barcelona",
    "wof:name":"Sanchez Alonso Josefa",
    "wof:placetype":"venue"
},
  "geometry": {"coordinates":[2.1099860668,41.3726654053],"type":"Point"}
}