{
  "type": "Feature",
  "properties": {
    "iso:country":"ES",
    "sg:address":"Calle de Profesor Adolfo Miaja De La Muela, 5",
    "sg:city":"Valladolid",
    "sg:orig_category":"Peluquer\u00cdas, Peluquer\u00cda Mixta",
    "sg:phone":"+34 983 34 12 51",
    "sg:postcode":"47014",
    "sg:province":"Valladolid",
    "wof:name":"Peluqueria Y Estetica Robevir S.l.l.",
    "wof:placetype":"venue"
},
  "geometry": {"coordinates":[-4.756128788,41.6412811279],"type":"Point"}
}