{
  "type": "Feature",
  "properties": {
    "iso:country":"ES",
    "sg:address":"Calle de Albareda, 18",
    "sg:city":"Sevilla",
    "sg:orig_category":"Aparcamientos (infraestructuras, Accesorios)",
    "sg:phone":"+34 954 56 06 23",
    "sg:postcode":"41001",
    "sg:province":"Sevilla",
    "wof:name":"Aparcamientos Plaza Nueva S.l.",
    "wof:placetype":"venue"
},
  "geometry": {"coordinates":[-5.9958386421,37.3895263672],"type":"Point"}
}