{
  "type": "Feature",
  "properties": {
    "addr:full":"Carrer de Rossello, 328 Barcelona Barcelona 08025",
    "addr:housenumber":"328",
    "addr:postcode":"08025",
    "addr:street":"Carrer De Rossello",
    "iso:country":"ES",
    "sg:address":"Carrer de Rossello, 328",
    "sg:city":"Barcelona",
    "sg:orig_category":"Molduras, Junquillos, Listones Y Molduras Perforadas",
    "sg:phone":"+34 934 58 57 42",
    "sg:postcode":"08025",
    "sg:province":"Barcelona",
    "wof:name":"Sebastian Fliquete Ramon",
    "wof:placetype":"venue"
},
  "geometry": {"coordinates":[2.1691789627,41.4020576477],"type":"Point"}
}