{
  "type": "Feature",
  "properties": {
    "iso:country":"ES",
    "sg:address":"Calle de Benito Vela, 18",
    "sg:city":"Lebrija",
    "sg:orig_category":"Relojer\u00cda (al Por Menor, Reparaci\u00d3n)",
    "sg:phone":"+34 955 97 19 80",
    "sg:postcode":"41740",
    "sg:province":"Sevilla",
    "wof:name":"Infante Fernandez Antonio",
    "wof:placetype":"venue"
},
  "geometry": {"coordinates":[-6.07847929,36.9182510376],"type":"Point"}
}