{
  "type": "Feature",
  "properties": {
    "addr:full":"Calle de Diputacion Foral De Alava, 14 Vitoria-gasteiz \u00c1lava 01001",
    "addr:housenumber":"14",
    "addr:postcode":"01001",
    "addr:street":"Calle De Diputacion Foral De Alava",
    "iso:country":"ES",
    "sg:address":"Calle de Diputacion Foral De Alava, 14",
    "sg:city":"Vitoria-gasteiz",
    "sg:orig_category":"Zapatos (al Por Menor)",
    "sg:phone":"+34 945 25 81 05",
    "sg:postcode":"01001",
    "sg:province":"\u00c1lava",
    "wof:name":"Marijuan Perez De Nanclares Jose Luis",
    "wof:placetype":"venue"
},
  "geometry": {"coordinates":[-2.6745438576,42.8469009399],"type":"Point"}
}