{
  "type": "Feature",
  "properties": {
    "addr:full":"Calle de Antonio Monedero, 16 Due\u00f1as Palencia 34210",
    "addr:housenumber":"16",
    "addr:postcode":"34210",
    "addr:street":"Calle De Antonio Monedero",
    "iso:country":"ES",
    "sg:address":"Calle de Antonio Monedero, 16",
    "sg:city":"Due\u00f1as",
    "sg:orig_category":"Carnicer\u00cdas, Carnicer\u00cdas",
    "sg:phone":"+34 979 78 00 89",
    "sg:postcode":"34210",
    "sg:province":"Palencia",
    "wof:name":"Resa Curiel Jesus",
    "wof:placetype":"venue"
},
  "geometry": {"coordinates":[-4.5453248024,41.8759002686],"type":"Point"}
}