{
  "type": "Feature",
  "properties": {
    "addr:full":"C/ Industria, 27 Ripollet Barcelona 08291",
    "addr:housenumber":"27",
    "addr:postcode":"08291",
    "addr:street":"C / Industria",
    "iso:country":"ES",
    "sg:address":"C/ Industria, 27",
    "sg:city":"Ripollet",
    "sg:orig_category":"Mec\u00c1nico Del Autom\u00d3vil",
    "sg:phone":"+34 935 94 26 14",
    "sg:postcode":"08291",
    "sg:province":"Barcelona",
    "wof:name":"Dulcet Calvo Jose",
    "wof:placetype":"venue"
},
  "geometry": {"coordinates":[2.1654291153,41.4933586121],"type":"Point"}
}