{
  "type": "Feature",
  "properties": {
    "addr:full":"Calle de Santa Maria, S/n Union De Campos Valladolid 47670",
    "addr:housenumber":"/ n",
    "addr:postcode":"47670",
    "addr:street":"Calle De Santa;S",
    "iso:country":"ES",
    "sg:address":"Calle de Santa Maria, S/n",
    "sg:city":"Union De Campos",
    "sg:orig_category":"Comunidades Religiosas",
    "sg:phone":"+34 983 75 41 23",
    "sg:postcode":"47670",
    "sg:province":"Valladolid",
    "wof:name":"Parroquia De La Asuncion",
    "wof:placetype":"venue"
},
  "geometry": {"coordinates":[-5.3262491226,42.0780677795],"type":"Point"}
}