{
  "type": "Feature",
  "properties": {
    "addr:full":"Calle de Tanger, 28 Madrid Madrid 28018",
    "addr:housenumber":"28",
    "addr:postcode":"madrid;28018",
    "addr:street":"Calle De Tanger",
    "iso:country":"ES",
    "sg:address":"Calle de Tanger, 28",
    "sg:city":"Madrid",
    "sg:orig_category":"Plomeros",
    "sg:phone":"+34 917 78 14 68",
    "sg:postcode":"28018",
    "sg:province":"Madrid",
    "wof:name":"Pebergas S.l.",
    "wof:placetype":"venue"
},
  "geometry": {"coordinates":[-3.6502249241,40.3833084106],"type":"Point"}
}