{
  "type": "Feature",
  "properties": {
    "iso:country":"ES",
    "sg:address":"Calle de Trebujena, 15",
    "sg:city":"Chipiona",
    "sg:classifiers":[
        {
            "category":"Autos & Motor Vehicles",
            "subcategory":"Automobile Sales",
            "type":"Retail Goods"
        }
    ],
    "sg:phone":"+34 956 37 10 51",
    "sg:postcode":"11550",
    "sg:province":"C\u00e1diz",
    "wof:name":"Ramos Rodriguez Jose Luis",
    "wof:placetype":"venue"
},
  "geometry": {"coordinates":[-6.4328188896,36.7397613525],"type":"Point"}
}