{
  "type": "Feature",
  "properties": {
    "iso:country":"ES",
    "sg:address":"Calle de Ca\u00d1ada Del Herrero, 14",
    "sg:city":"S. Sebastian Gomera",
    "sg:orig_category":"Prot\u00c9sicos Dentales",
    "sg:phone":"+34 922 87 01 13",
    "sg:postcode":"38800",
    "sg:province":"Santa Cruz De Tenerife",
    "wof:name":"Fernandez Dominguez Antonio",
    "wof:placetype":"venue"
},
  "geometry": {"coordinates":[-17.1167640686,28.0909843445],"type":"Point"}
}