{
  "type": "Feature",
  "properties": {
    "addr:full":"Calle de Villarrin, S/n Manganeses De La Lampreana Zamora 49130",
    "addr:housenumber":"s / n",
    "addr:postcode":"49130",
    "addr:street":"Calle De Villarrin",
    "iso:country":"ES",
    "sg:address":"Calle de Villarrin, S/n",
    "sg:city":"Manganeses De La Lampreana",
    "sg:orig_category":"Empresas De Carpinter\u00cda De Madera",
    "sg:phone":"+34 980 58 82 63",
    "sg:postcode":"49130",
    "sg:province":"Zamora",
    "wof:name":"Iglesia Turi\u00f1o Ruperto Jesus",
    "wof:placetype":"venue"
},
  "geometry": {"coordinates":[-5.7099838257,41.752456665],"type":"Point"}
}