{
  "type": "Feature",
  "properties": {
    "iso:country":"ES",
    "sg:address":"Calle de Cortina Del Muelle, 21",
    "sg:city":"Malaga",
    "sg:orig_category":"Abogados",
    "sg:phone":"+34 952 60 22 47",
    "sg:postcode":"29015",
    "sg:province":"M\u00e1laga",
    "wof:name":"Palma Gonzalez Carlos Manuel",
    "wof:placetype":"venue"
},
  "geometry": {"coordinates":[-4.4180335999,36.7197875977],"type":"Point"}
}