{
  "type": "Feature",
  "properties": {
    "iso:country":"ES",
    "sg:address":"Carrer de Catalunya, 18",
    "sg:city":"S. Andreu Barca",
    "sg:orig_category":"Peluquer\u00cdas, Peluquer\u00cda Mixta",
    "sg:phone":"+34 936 53 28 53",
    "sg:postcode":"08740",
    "sg:province":"Barcelona",
    "wof:name":"Lopez Bueno Adela",
    "wof:placetype":"venue"
},
  "geometry": {"coordinates":[1.9696279764,41.4472198486],"type":"Point"}
}