{
  "type": "Feature",
  "properties": {
    "iso:country":"ES",
    "sg:address":"Rbla Rambla Nova, 117",
    "sg:city":"Tarragona",
    "sg:orig_category":"Comercios E Industrias (cesi\u00d3n Y Reactivaci\u00d3n)",
    "sg:phone":"+34 977 22 82 12",
    "sg:postcode":"43001",
    "sg:province":"Tarragona",
    "sg:website":"www.degrandes.com",
    "wof:name":"De Grandes Diez Luis",
    "wof:placetype":"venue"
},
  "geometry": {"coordinates":[1.2541049719,41.1169281006],"type":"Point"}
}