{
  "type": "Feature",
  "properties": {
    "iso:country":"ES",
    "sg:address":"Calle de Gamazo, 2",
    "sg:city":"Santander",
    "sg:orig_category":"Sindicatos Y Colegios Profesionales",
    "sg:phone":"+34 942 21 51 09",
    "sg:postcode":"39004",
    "sg:province":"Cantabria",
    "wof:name":"Corporacion De Practicos Del Puerto De Santander",
    "wof:placetype":"venue"
},
  "geometry": {"coordinates":[-3.787635088,43.4619674683],"type":"Point"}
}