{
  "type": "Feature",
  "properties": {
    "addr:full":"Avda Guadiana, 1 Medellin Badajoz 06411",
    "addr:housenumber":"1",
    "addr:postcode":"06411",
    "addr:street":"Avda Guadiana",
    "iso:country":"ES",
    "sg:address":"Avda Guadiana, 1",
    "sg:city":"Medellin",
    "sg:orig_category":"Arqueolog\u00cda Y Patrimonio Cultural",
    "sg:phone":"+34 924 82 29 84",
    "sg:postcode":"06411",
    "sg:province":"Badajoz",
    "wof:name":"Arquepec S.l.",
    "wof:placetype":"venue"
},
  "geometry": {"coordinates":[-5.9615569115,38.9636611938],"type":"Point"}
}