{
  "type": "Feature",
  "properties": {
    "iso:country":"ES",
    "sg:address":"Avda Eugenio Rijo Rocha, 6",
    "sg:city":"Arrecife",
    "sg:orig_category":"Peluqueros: De Se\u00d1oras",
    "sg:phone":"+34 928 81 28 01",
    "sg:postcode":"35500",
    "sg:province":"Las Palmas",
    "wof:name":"Toro Hernandez Reyes Del",
    "wof:placetype":"venue"
},
  "geometry": {"coordinates":[-13.5568380356,28.9686431885],"type":"Point"}
}