{
  "type": "Feature",
  "properties": {
    "addr:full":"Calle de Ingeniero Salinas, 7 Palmas De Gran Canaria Las Palmas 35006",
    "addr:housenumber":"7",
    "addr:postcode":"35006",
    "addr:street":"Calle De Ingeniero Salinas",
    "iso:country":"ES",
    "sg:address":"Calle de Ingeniero Salinas, 7",
    "sg:city":"Palmas De Gran Canaria",
    "sg:orig_category":"Inmobiliaria (agencias)",
    "sg:phone":"+34 928 23 48 99",
    "sg:postcode":"35006",
    "sg:province":"Las Palmas",
    "wof:name":"Servicios Inmoviliarios Hecasa S.l.",
    "wof:placetype":"venue"
},
  "geometry": {"coordinates":[-15.434466362,28.1300201416],"type":"Point"}
}