{
  "type": "Feature",
  "properties": {
    "addr:full":"Calle de San Francisco, 38 Segovia Segovia 40001",
    "addr:housenumber":"38",
    "addr:postcode":"40001",
    "addr:street":"Calle De San Francisco",
    "iso:country":"ES",
    "sg:address":"Calle de San Francisco, 38",
    "sg:city":"Segovia",
    "sg:orig_category":"Abogados",
    "sg:phone":"+34 921 44 33 73",
    "sg:postcode":"40001",
    "sg:province":"Segovia",
    "wof:name":"Orejana Tejedor Angel",
    "wof:placetype":"venue"
},
  "geometry": {"coordinates":[-4.1176300049,40.9463768005],"type":"Point"}
}