{
  "type": "Feature",
  "properties": {
    "addr:full":"Calle de Real, 11 Aranjuez Madrid 28300",
    "addr:housenumber":"11",
    "addr:postcode":"28300",
    "addr:street":"Calle De Real",
    "iso:country":"ES",
    "sg:address":"Calle de Real, 11",
    "sg:city":"Aranjuez",
    "sg:orig_category":"Fabricaci\u00d3n De Productos L\u00c1cteos Y Derivados",
    "sg:phone":"+34 918 01 10 26",
    "sg:postcode":"28300",
    "sg:province":"Madrid",
    "wof:name":"Pedraza Apio Inmaculada",
    "wof:placetype":"venue"
},
  "geometry": {"coordinates":[-3.6028409004,40.0344848633],"type":"Point"}
}