{
  "type": "Feature",
  "properties": {
    "addr:full":"Carrer de Parres (les), 6 Argentona Barcelona 08310",
    "addr:housenumber":"6",
    "addr:postcode":"08310",
    "addr:street":"Carrer De Parres Les",
    "iso:country":"ES",
    "sg:address":"Carrer de Parres (les), 6",
    "sg:city":"Argentona",
    "sg:orig_category":"Asesor\u00cda Fiscal Y Jur\u00cddica",
    "sg:phone":"+34 937 97 02 06",
    "sg:postcode":"08310",
    "sg:province":"Barcelona",
    "wof:name":"Alcoverro Pe\u00f1alver Maria",
    "wof:placetype":"venue"
},
  "geometry": {"coordinates":[2.4040596485,41.5540390015],"type":"Point"}
}