{
  "type": "Feature",
  "properties": {
    "addr:full":"Calle de San Saturio, 10 Vitoria-gasteiz \u00c1lava 01007",
    "addr:housenumber":"10",
    "addr:postcode":"01007",
    "addr:street":"Calle De San Saturio",
    "iso:country":"ES",
    "sg:address":"Calle de San Saturio, 10",
    "sg:city":"Vitoria-gasteiz",
    "sg:orig_category":"Arquitectos",
    "sg:phone":"+34 945 13 00 84",
    "sg:postcode":"01007",
    "sg:province":"\u00c1lava",
    "wof:name":"Ercilla Abaitua Roberto",
    "wof:placetype":"venue"
},
  "geometry": {"coordinates":[-2.6982500553,42.8324356079],"type":"Point"}
}