{
  "type": "Feature",
  "properties": {
    "addr:full":"Carrer de Arago, 8 Roses Girona 17480",
    "addr:housenumber":"8",
    "addr:postcode":"17480",
    "addr:street":"Carrer De Arago",
    "iso:country":"ES",
    "sg:address":"Carrer de Arago, 8",
    "sg:city":"Roses",
    "sg:orig_category":"Ropa Para Ni\u00d1os (al Por Menor)",
    "sg:phone":"+34 972 25 67 41",
    "sg:postcode":"17480",
    "sg:province":"Girona",
    "wof:name":"Cruz Silvia Maria Aurora",
    "wof:placetype":"venue"
},
  "geometry": {"coordinates":[3.1758470535,42.2622489929],"type":"Point"}
}