{
  "type": "Feature",
  "properties": {
    "iso:country":"ES",
    "sg:address":"Calle de Negrillo, 3",
    "sg:city":"Cazorla",
    "sg:orig_category":"Cristaler\u00cdas",
    "sg:phone":"+34 953 72 12 20",
    "sg:postcode":"23470",
    "sg:province":"Ja\u00e9n",
    "wof:name":"Lara Garcia Jose",
    "wof:placetype":"venue"
},
  "geometry": {"coordinates":[-3.0038108826,37.9192123413],"type":"Point"}
}