{
  "type": "Feature",
  "properties": {
    "iso:country":"ES",
    "sg:address":"Calle de Eduardo Marquina, 22",
    "sg:city":"Avila",
    "sg:orig_category":"Ropa Para Se\u00d1oras Y Caballeros (al Por Menor)",
    "sg:phone":"+34 920 22 22 56",
    "sg:postcode":"05001",
    "sg:province":"\u00c1vila",
    "wof:name":"Alvarez Corbacho Maria",
    "wof:placetype":"venue"
},
  "geometry": {"coordinates":[-4.6920161247,40.6563606262],"type":"Point"}
}