{
  "type": "Feature",
  "properties": {
    "addr:full":"Placa De La Font, S/n Pobla Tornesa Castell\u00f3n 12191",
    "addr:housenumber":"s / n",
    "addr:postcode":"12191",
    "addr:street":"Placa De La Font;Castello\u0301N",
    "iso:country":"ES",
    "sg:address":"Placa De La Font, S/n",
    "sg:city":"Pobla Tornesa",
    "sg:orig_category":"Cr\u00cda De Animales",
    "sg:phone":"+34 964 33 81 28",
    "sg:postcode":"12191",
    "sg:province":"Castell\u00f3n",
    "wof:name":"Jose Manuel Tena Garcia Cdad",
    "wof:placetype":"venue"
},
  "geometry": {"coordinates":[-0.001599,40.1006736755],"type":"Point"}
}