{
  "type": "Feature",
  "properties": {
    "addr:full":"Quintana, 7 Quintana Pontevedra 36818",
    "addr:housenumber":"7",
    "addr:postcode":"36818",
    "addr:street":"Quintana",
    "iso:country":"ES",
    "sg:address":"Quintana, 7",
    "sg:city":"Quintana",
    "sg:orig_category":"Prendas Deportivas (fabricaci\u00d3n)",
    "sg:phone":"+34 986 40 30 20",
    "sg:postcode":"36818",
    "sg:province":"Pontevedra",
    "wof:name":"Puente Saavedra Manuel",
    "wof:placetype":"venue"
},
  "geometry": {"coordinates":[-8.609254837,42.3069534302],"type":"Point"}
}