{
  "type": "Feature",
  "properties": {
    "addr:full":"Carrer de Clemencia Isaura, 16 Sabadell Barcelona 08204",
    "addr:housenumber":"16",
    "addr:postcode":"08204",
    "addr:street":"Carrer De Clemencia Isaura",
    "iso:country":"ES",
    "sg:address":"Carrer de Clemencia Isaura, 16",
    "sg:city":"Sabadell",
    "sg:orig_category":"Alquiler De V\u00cddeo",
    "sg:phone":"+34 937 10 35 89",
    "sg:postcode":"08204",
    "sg:province":"Barcelona",
    "wof:name":"Viana Lopez Maria Rosa",
    "wof:placetype":"venue"
},
  "geometry": {"coordinates":[2.1146700382,41.5294303894],"type":"Point"}
}