{
  "type": "Feature",
  "properties": {
    "iso:country":"ES",
    "sg:address":"Calle de Rio, 6",
    "sg:city":"Malagon",
    "sg:orig_category":"Partidos Pol\u00cdticos",
    "sg:phone":"+34 926 80 00 44",
    "sg:postcode":"13420",
    "sg:province":"Ciudad Real",
    "wof:name":"Partido Socialista Obrero Espa\u00f1ol",
    "wof:placetype":"venue"
},
  "geometry": {"coordinates":[-3.8591740131,39.168346405],"type":"Point"}
}