{
  "type": "Feature",
  "properties": {
    "addr:full":"Cmno Yesera (la), 3 Pechina Almer\u00eda 04250",
    "addr:housenumber":"3",
    "addr:postcode":"04250",
    "addr:street":"Cmno Yesera La;Almeri\u0301A",
    "iso:country":"ES",
    "sg:address":"Cmno Yesera (la), 3",
    "sg:city":"Pechina",
    "sg:orig_category":"Instalaci\u00d3n De Aspiraci\u00d3n De Gases Y Humos",
    "sg:phone":"+34 950 31 77 60",
    "sg:postcode":"04250",
    "sg:province":"Almer\u00eda",
    "wof:name":"Gas San Rafael S.l.",
    "wof:placetype":"venue"
},
  "geometry": {"coordinates":[-2.4415290356,36.914730072],"type":"Point"}
}