{
  "type": "Feature",
  "properties": {
    "addr:full":"Calle de Almagro, 46 Viso Marques Ciudad Real 13770",
    "addr:housenumber":"46",
    "addr:postcode":"marques;13770",
    "addr:street":"Calle De Almagro",
    "iso:country":"ES",
    "sg:address":"Calle de Almagro, 46",
    "sg:city":"Viso Marques",
    "sg:orig_category":"Producci\u00d3n, Distribuci\u00d3n De Gas Butano Y Propano",
    "sg:phone":"+34 926 33 67 23",
    "sg:postcode":"13770",
    "sg:province":"Ciudad Real",
    "wof:name":"Rodriguez Sanchez Juan Carlos",
    "wof:placetype":"venue"
},
  "geometry": {"coordinates":[-3.5623352528,38.5252952576],"type":"Point"}
}