{
  "type": "Feature",
  "properties": {
    "addr:full":"Calle de Uruguay, 10 Toledo Toledo 45004",
    "addr:housenumber":"10",
    "addr:postcode":"45004",
    "addr:street":"Calle De Uruguay",
    "iso:country":"ES",
    "sg:address":"Calle de Uruguay, 10",
    "sg:city":"Toledo",
    "sg:orig_category":"Peluquer\u00cdas, Peluquer\u00cda Mixta",
    "sg:phone":"+34 925 21 54 61",
    "sg:postcode":"45004",
    "sg:province":"Toledo",
    "wof:name":"Rodriguez Mellado Maria Del Carmen",
    "wof:placetype":"venue"
},
  "geometry": {"coordinates":[-4.0322008133,39.8679847717],"type":"Point"}
}