{
  "type": "Feature",
  "properties": {
    "addr:full":"Carrer de L'alcalde De Mostoles, 50 Barcelona Barcelona 08025",
    "addr:housenumber":"50",
    "addr:postcode":"08025",
    "addr:street":"Carrer De L'Alcalde De Mostoles",
    "iso:country":"ES",
    "sg:address":"Carrer de L'alcalde De Mostoles, 50",
    "sg:city":"Barcelona",
    "sg:orig_category":"Muebles, Minoristas",
    "sg:phone":"+34 934 55 63 99",
    "sg:postcode":"08025",
    "sg:province":"Barcelona",
    "wof:name":"Calmet Carbo Jose Maria",
    "wof:placetype":"venue"
},
  "geometry": {"coordinates":[2.1651573181,41.4116172791],"type":"Point"}
}