{
  "type": "Feature",
  "properties": {
    "addr:full":"Calle de Colon (de), S/n San Eugenio Bajo Santa Cruz De Tenerife 38660",
    "addr:housenumber":"/ n",
    "addr:postcode":"38660",
    "addr:street":"Calle De Colon De S",
    "iso:country":"ES",
    "sg:address":"Calle de Colon (de), S/n",
    "sg:city":"San Eugenio Bajo",
    "sg:orig_category":"Deportes N\u00c1uticos, Acu\u00c1ticos Y Subacu\u00c1ticos: Art\u00cdculos Y Equipo (al Por Menor)",
    "sg:phone":"+34 922 71 43 15",
    "sg:postcode":"38660",
    "sg:province":"Santa Cruz De Tenerife",
    "wof:name":"Peje Canarias S. A.",
    "wof:placetype":"venue"
},
  "geometry": {"coordinates":[-16.7354431152,28.0784606934],"type":"Point"}
}