{
  "type": "Feature",
  "properties": {
    "addr:full":"Calle de Nueva, S/n Cabeza Del Caballo Salamanca 37214",
    "addr:housenumber":"s / n",
    "addr:postcode":"37214",
    "addr:street":"Calle De Nueva",
    "iso:country":"ES",
    "sg:address":"Calle de Nueva, S/n",
    "sg:city":"Cabeza Del Caballo",
    "sg:orig_category":"Empresas De Pintura Y Revestimientos",
    "sg:phone":"+34 923 52 26 04",
    "sg:postcode":"37214",
    "sg:province":"Salamanca",
    "wof:name":"Alvarez Perez Jose",
    "wof:placetype":"venue"
},
  "geometry": {"coordinates":[-6.5563211441,41.1294822693],"type":"Point"}
}