{
  "type": "Feature",
  "properties": {
    "iso:country":"ES",
    "sg:address":"Calle de Doctor Oloriz, 5",
    "sg:city":"Valencia",
    "sg:orig_category":"Comercio De Piezas De Recambio Y De Accesorios De Veh\u00cdculos, Veh\u00cdculos Industriales",
    "sg:phone":"+34 963 49 02 47",
    "sg:postcode":"46009",
    "sg:province":"Valencia",
    "sg:website":"www.eurosil.es",
    "wof:name":"Eurosil S.l.",
    "wof:placetype":"venue"
},
  "geometry": {"coordinates":[-0.3804925978,39.4836196899],"type":"Point"}
}