{
  "type": "Feature",
  "properties": {
    "iso:country":"ES",
    "sg:address":"Calle de Toledo, 11",
    "sg:city":"Cebolla",
    "sg:orig_category":"Molduras, Junquillos, Listones Y Molduras Perforadas",
    "sg:phone":"+34 925 86 61 53",
    "sg:postcode":"45550",
    "sg:province":"Toledo",
    "wof:name":"Trujillo Machuca Pedro",
    "wof:placetype":"venue"
},
  "geometry": {"coordinates":[-4.5676598549,39.9334411621],"type":"Point"}
}