{
  "type": "Feature",
  "properties": {
    "addr:full":"Rua Arcebispo Lago, 28 Vilagarcia Pontevedra 36600",
    "addr:housenumber":"28",
    "addr:postcode":"36600",
    "addr:street":"Rua Arcebispo Lago",
    "iso:country":"ES",
    "sg:address":"Rua Arcebispo Lago, 28",
    "sg:city":"Vilagarcia",
    "sg:orig_category":"Caf\u00c9s, Bares, Cervecer\u00cdas",
    "sg:phone":"+34 986 50 23 89",
    "sg:postcode":"36600",
    "sg:province":"Pontevedra",
    "wof:name":"Sistelcom-telemensaje S.a.",
    "wof:placetype":"venue"
},
  "geometry": {"coordinates":[-8.7665462494,42.5960464478],"type":"Point"}
}