{
  "type": "Feature",
  "properties": {
    "addr:full":"Av Bogatell, 21 Barcelona Barcelona 08005",
    "addr:housenumber":"21",
    "addr:postcode":"08005",
    "addr:street":"Av Bogatell",
    "iso:country":"ES",
    "sg:address":"Av Bogatell, 21",
    "sg:city":"Barcelona",
    "sg:orig_category":"Empresas De Limpieza",
    "sg:phone":"+34 932 21 68 78",
    "sg:postcode":"08005",
    "sg:province":"Barcelona",
    "wof:name":"Sumynet S.l.",
    "wof:placetype":"venue"
},
  "geometry": {"coordinates":[2.1962649822,41.392742157],"type":"Point"}
}