{
  "type": "Feature",
  "properties": {
    "iso:country":"ES",
    "sg:address":"Calle de Castelar, 3",
    "sg:city":"Sax",
    "sg:orig_category":"Molduras, Junquillos, Listones Y Molduras Perforadas",
    "sg:phone":"+34 966 96 78 56",
    "sg:postcode":"03630",
    "sg:province":"Alicante",
    "wof:name":"Carrillo Guillen Jose Antonio",
    "wof:placetype":"venue"
},
  "geometry": {"coordinates":[-0.817915976,38.5372238159],"type":"Point"}
}