{
  "type": "Feature",
  "properties": {
    "addr:full":"Calle de Vergara, 1 Salamanca Salamanca 37003",
    "addr:housenumber":"1",
    "addr:postcode":"37003",
    "addr:street":"Calle De Vergara",
    "iso:country":"ES",
    "sg:address":"Calle de Vergara, 1",
    "sg:city":"Salamanca",
    "sg:orig_category":"Formaci\u00d3n Continuada (variada)",
    "sg:phone":"+34 923 24 20 34",
    "sg:postcode":"37003",
    "sg:province":"Salamanca",
    "wof:name":"Alcocer Ramos Benigno",
    "wof:placetype":"venue"
},
  "geometry": {"coordinates":[-5.654358387,40.9647140503],"type":"Point"}
}