{
  "type": "Feature",
  "properties": {
    "iso:country":"ES",
    "sg:address":"Calle de Quart, 112",
    "sg:city":"Valencia",
    "sg:orig_category":"Agencias De Trabajo Temporal",
    "sg:phone":"+34 963 84 64 16",
    "sg:postcode":"46008",
    "sg:province":"Valencia",
    "sg:website":"www.synergie-ett.com",
    "wof:name":"Synergie T.t. E.t.t. S.a.",
    "wof:placetype":"venue"
},
  "geometry": {"coordinates":[-0.3892219961,39.4750213623],"type":"Point"}
}