{
  "type": "Feature",
  "properties": {
    "iso:country":"ES",
    "sg:address":"C/ Santa Barbera, 18",
    "sg:city":"Elche",
    "sg:orig_category":"Iglesia Cat\u00d3lica",
    "sg:phone":"+34 965 45 18 61",
    "sg:postcode":"03203",
    "sg:province":"Alicante",
    "wof:name":"Parroquia De El Salvador De Elche",
    "wof:placetype":"venue"
},
  "geometry": {"coordinates":[-0.6965489984,38.2643508911],"type":"Point"}
}