{
  "type": "Feature",
  "properties": {
    "iso:country":"ES",
    "sg:address":"Avda Literato Azorin, 38",
    "sg:city":"Yecla",
    "sg:orig_category":"Electricidad: Instaladores",
    "sg:phone":"+34 968 79 19 65",
    "sg:postcode":"30510",
    "sg:province":"Murcia",
    "wof:name":"Pedro Diaz Electricidad S.l.",
    "wof:placetype":"venue"
},
  "geometry": {"coordinates":[-1.1078180075,38.6133575439],"type":"Point"}
}