{
  "type": "Feature",
  "properties": {
    "iso:country":"ES",
    "sg:address":"Rua Calvos (a), S/n",
    "sg:city":"Castroverde",
    "sg:orig_category":"Empresas De Carpinter\u00cda De Madera",
    "sg:phone":"+34 988 23 84 79",
    "sg:postcode":"32915",
    "sg:province":"Ourense",
    "wof:name":"Diaz Perez Severo",
    "wof:placetype":"venue"
},
  "geometry": {"coordinates":[-7.8368210793,42.2873077393],"type":"Point"}
}