{
  "type": "Feature",
  "properties": {
    "addr:full":"Calle de Rio Ara, 17 Zaragoza Zaragoza 50014",
    "addr:housenumber":"17",
    "addr:postcode":"50014",
    "addr:street":"Calle De Rio Ara",
    "iso:country":"ES",
    "sg:address":"Calle de Rio Ara, 17",
    "sg:city":"Zaragoza",
    "sg:orig_category":"Agentes, Concesionarios Y Sucursales De Veh\u00cdculos",
    "sg:phone":"+34 976 13 81 17",
    "sg:postcode":"50014",
    "sg:province":"Zaragoza",
    "sg:website":"www.sartopina.com",
    "wof:name":"Sartopina S.a.",
    "wof:placetype":"venue"
},
  "geometry": {"coordinates":[-0.8462820053,41.6667022705],"type":"Point"}
}