{
  "type": "Feature",
  "properties": {
    "iso:country":"ES",
    "sg:address":"Urteaga Kalea, 9",
    "sg:city":"Bergara",
    "sg:orig_category":"Carnicer\u00cdas, Carnicer\u00cdas",
    "sg:phone":"+34 943 76 08 68",
    "sg:postcode":"20570",
    "sg:province":"Guip\u00f9zcoa",
    "wof:name":"Zurutuza Goiburu Jose Manuel",
    "wof:placetype":"venue"
},
  "geometry": {"coordinates":[-2.4089479446,43.1096153259],"type":"Point"}
}