{
  "type": "Feature",
  "properties": {
    "addr:full":"Calle de Granada, 20 Villanueva Algaidas M\u00e1laga 29310",
    "addr:housenumber":"20",
    "addr:postcode":"29310",
    "addr:street":"Calle De Granada;Algaidas Ma\u0301Laga",
    "iso:country":"ES",
    "sg:address":"Calle de Granada, 20",
    "sg:city":"Villanueva Algaidas",
    "sg:orig_category":"Asociaciones, Organismos Culturales Y Socioeducativos",
    "sg:phone":"+34 952 74 43 50",
    "sg:postcode":"29310",
    "sg:province":"M\u00e1laga",
    "wof:name":"Asociacion Amigos De Berrocal",
    "wof:placetype":"venue"
},
  "geometry": {"coordinates":[-4.4498653412,37.1855545044],"type":"Point"}
}