{
  "type": "Feature",
  "properties": {
    "iso:country":"ES",
    "sg:address":"Avda Chile, 9",
    "sg:city":"Coru\u00d1a",
    "sg:orig_category":"Ingenier\u00cda, Centros De Estudios (diversos)",
    "sg:phone":"+34 981 24 96 71",
    "sg:postcode":"15008",
    "sg:province":"La Coru\u00f1a",
    "sg:website":"www.certum.es",
    "wof:name":"Certum Control Tecnico De La Edificacion S.a.",
    "wof:placetype":"venue"
},
  "geometry": {"coordinates":[-8.4051828384,43.3525619507],"type":"Point"}
}