{
  "type": "Feature",
  "properties": {
    "iso:country":"ES",
    "sg:address":"Carrer de Alamos (los), 41",
    "sg:city":"Mataro",
    "sg:orig_category":"Supermercados Y Hipermercados",
    "sg:phone":"+34 937 96 00 28",
    "sg:postcode":"08301",
    "sg:province":"Barcelona",
    "wof:name":"Cobos Diaz Agustin",
    "wof:placetype":"venue"
},
  "geometry": {"coordinates":[2.4453549385,41.545425415],"type":"Point"}
}