{
  "type": "Feature",
  "properties": {
    "iso:country":"ES",
    "sg:address":"Calle de Marchales, 34",
    "sg:city":"Almeria",
    "sg:orig_category":"Perfumer\u00cda (al Por Menor)",
    "sg:phone":"+34 950 26 45 06",
    "sg:postcode":"04008",
    "sg:province":"Almer\u00eda",
    "wof:name":"Euro Damas S.l.",
    "wof:placetype":"venue"
},
  "geometry": {"coordinates":[-2.4583489895,36.8493041992],"type":"Point"}
}