{
  "type": "Feature",
  "properties": {
    "addr:full":"Calle de Doctor Ferran, 74 Albacete Albacete 02004",
    "addr:housenumber":"74",
    "addr:postcode":"02004",
    "addr:street":"Calle De Doctor Ferran",
    "iso:country":"ES",
    "sg:address":"Calle de Doctor Ferran, 74",
    "sg:city":"Albacete",
    "sg:orig_category":"Imprenta",
    "sg:phone":"+34 967 23 60 40",
    "sg:postcode":"02004",
    "sg:province":"Albacete",
    "wof:name":"Imprenta Los Llanos Artes Graficas E Impresion Digital S.l.",
    "wof:placetype":"venue"
},
  "geometry": {"coordinates":[-1.8676151037,38.9947280884],"type":"Point"}
}