{
  "type": "Feature",
  "properties": {
    "iso:country":"ES",
    "sg:address":"Calle de Alameda, 28",
    "sg:city":"Illescas",
    "sg:orig_category":"Deportes Y Ocio: Art\u00cdculos Y Ropas (al Por Menor Y Accesorios)",
    "sg:phone":"+34 925 51 26 40",
    "sg:postcode":"45200",
    "sg:province":"Toledo",
    "wof:name":"Pardo Teran Candida",
    "wof:placetype":"venue"
},
  "geometry": {"coordinates":[-3.8390576839,40.1159553528],"type":"Point"}
}