{
  "type": "Feature",
  "properties": {
    "addr:full":"Calle de Jose Calderon, 2 Campanillas M\u00e1laga 29590",
    "addr:housenumber":"2",
    "addr:postcode":"29590",
    "addr:street":"Calle De Jose Calderon;Ma\u0301Laga",
    "iso:country":"ES",
    "sg:address":"Calle de Jose Calderon, 2",
    "sg:city":"Campanillas",
    "sg:orig_category":"Sociedades, Compa\u00d1\u00cdas Aseguradoras",
    "sg:phone":"+34 952 62 62 23",
    "sg:postcode":"29590",
    "sg:province":"M\u00e1laga",
    "wof:name":"Alno 2000 S.l.",
    "wof:placetype":"venue"
},
  "geometry": {"coordinates":[-4.5362033844,36.7218475342],"type":"Point"}
}