{
  "type": "Feature",
  "properties": {
    "iso:country":"ES",
    "sg:address":"Carr S Antoni De Baix, 114",
    "sg:city":"Igualada",
    "sg:orig_category":"Cueros Y Pieles (al Por Mayor)",
    "sg:phone":"+34 938 06 80 81",
    "sg:postcode":"08700",
    "sg:province":"Barcelona",
    "wof:name":"Acabados De La Piel Oca\u00f1a S.l.",
    "wof:placetype":"venue"
},
  "geometry": {"coordinates":[1.625413,41.575409],"type":"Point"}
}