{
  "type": "Feature",
  "properties": {
    "iso:country":"ES",
    "sg:address":"Avda Industria (de La), 32",
    "sg:city":"Alcobendas",
    "sg:orig_category":"Electricidad: Instaladores",
    "sg:phone":"+34 916 61 31 32",
    "sg:postcode":"28108",
    "sg:province":"Madrid",
    "wof:name":"Crespo Y Blasco S.a.",
    "wof:placetype":"venue"
},
  "geometry": {"coordinates":[-3.6505000591,40.5345573425],"type":"Point"}
}