{
  "type": "Feature",
  "properties": {
    "iso:country":"ES",
    "sg:address":"Avda San Lucas (as), 37",
    "sg:city":"Mondo\u00f1edo",
    "sg:orig_category":"M\u00c9dicos: Estomatolog\u00cda",
    "sg:phone":"+34 982 50 71 50",
    "sg:postcode":"27740",
    "sg:province":"Lugo",
    "wof:name":"Santalla Soriano Elsa Gladys",
    "wof:placetype":"venue"
},
  "geometry": {"coordinates":[-7.3686728477,43.428237915],"type":"Point"}
}