{
  "type": "Feature",
  "properties": {
    "iso:country":"ES",
    "sg:address":"Sa Vela, 96",
    "sg:city":"Puigpunyent",
    "sg:orig_category":"Importaci\u00d3n",
    "sg:phone":"+34 971 14 70 15",
    "sg:postcode":"07194",
    "sg:province":"Islas Baleares",
    "wof:name":"Gamma Balear S.l.",
    "wof:placetype":"venue"
},
  "geometry": {"coordinates":[2.5264949799,39.6293411255],"type":"Point"}
}