{
  "type": "Feature",
  "properties": {
    "iso:country":"ES",
    "sg:address":"Ctra Badajoz Granada, Km. 0074,9",
    "sg:city":"Zafra",
    "sg:orig_category":"Transportes Por V\u00cdas Navegables",
    "sg:phone":"+34 924 55 49 42",
    "sg:postcode":"06300",
    "sg:province":"Badajoz",
    "wof:name":"Cotraex Sociedad Cooperativa Limitada",
    "wof:placetype":"venue"
},
  "geometry": {"coordinates":[-6.4075398445,38.4205284119],"type":"Point"}
}