{
  "type": "Feature",
  "properties": {
    "addr:full":"Avda Generalisimo, S/n Puerto Cruz Santa Cruz De Tenerife 38400",
    "addr:housenumber":"s / n",
    "addr:postcode":"38400",
    "addr:street":"Avda Generalisimo;Cruz",
    "iso:country":"ES",
    "sg:address":"Avda Generalisimo, S/n",
    "sg:city":"Puerto Cruz",
    "sg:orig_category":"Farmacias",
    "sg:phone":"+34 922 38 20 03",
    "sg:postcode":"38400",
    "sg:province":"Santa Cruz De Tenerife",
    "wof:name":"Padilla Lopez-ruiz Antonio Abad",
    "wof:placetype":"venue"
},
  "geometry": {"coordinates":[-16.5473842621,28.4141807556],"type":"Point"}
}