{
  "type": "Feature",
  "properties": {
    "addr:full":"Av Estacio, 50 Blanes Girona 17300",
    "addr:housenumber":"50",
    "addr:postcode":"17300",
    "addr:street":"Av Estacio",
    "iso:country":"ES",
    "sg:address":"Av Estacio, 50",
    "sg:city":"Blanes",
    "sg:orig_category":"Agentes, Concesionarios Y Sucursales De Veh\u00cdculos",
    "sg:phone":"+34 972 35 32 75",
    "sg:postcode":"17300",
    "sg:province":"Girona",
    "wof:name":"Anadauto S.l.",
    "wof:placetype":"venue"
},
  "geometry": {"coordinates":[2.7773537636,41.6759147644],"type":"Point"}
}