{
  "type": "Feature",
  "properties": {
    "iso:country":"ES",
    "sg:address":"Gallarraga, 4",
    "sg:city":"Llodio",
    "sg:classifiers":[
        {
            "category":"Taxi",
            "type":"Transportation"
        }
    ],
    "sg:phone":"+34 946 72 64 24",
    "sg:postcode":"01400",
    "sg:province":"\u00c1lava",
    "wof:name":"Gonzalez Carrillo Juan Francisco",
    "wof:placetype":"venue"
},
  "geometry": {"coordinates":[-2.9624013901,43.1373214722],"type":"Point"}
}