{
  "type": "Feature",
  "properties": {
    "iso:country":"ES",
    "sg:address":"Ctra Cadiz-barcelona Cn-340, Km. 0023,5",
    "sg:city":"Sagunt",
    "sg:orig_category":"Asesor\u00cda Sobre Comunicaci\u00d3n De Empresas",
    "sg:phone":"+34 962 66 57 23",
    "sg:postcode":"46500",
    "sg:province":"Valencia",
    "wof:name":"Proyectos Asesoria Y Servicios S.a.",
    "wof:placetype":"venue"
},
  "geometry": {"coordinates":[-0.2783089876,39.6799659729],"type":"Point"}
}