{
  "type": "Feature",
  "properties": {
    "addr:full":"Calle de Sahuquillo, 61 Gineta Albacete 02110",
    "addr:housenumber":"61",
    "addr:postcode":"02110",
    "addr:street":"Calle De Sahuquillo",
    "iso:country":"ES",
    "sg:address":"Calle de Sahuquillo, 61",
    "sg:city":"Gineta",
    "sg:orig_category":"Fabricaci\u00d3n De Taburetes, Sillas Y Sillones",
    "sg:phone":"+34 967 27 50 52",
    "sg:postcode":"02110",
    "sg:province":"Albacete",
    "wof:name":"Sillas Y Mesas Collado S.l.",
    "wof:placetype":"venue"
},
  "geometry": {"coordinates":[-1.994568944,39.1158218384],"type":"Point"}
}