{
  "type": "Feature",
  "properties": {
    "addr:full":"Carrer de Sant Antoni, 11 Fatarella Tarragona 43781",
    "addr:housenumber":"11",
    "addr:postcode":"43781",
    "addr:street":"Carrer De Sant Antoni",
    "iso:country":"ES",
    "sg:address":"Carrer de Sant Antoni, 11",
    "sg:city":"Fatarella",
    "sg:orig_category":"Estancos",
    "sg:phone":"+34 977 41 37 54",
    "sg:postcode":"43781",
    "sg:province":"Tarragona",
    "wof:name":"Girones Perello Tereseta",
    "wof:placetype":"venue"
},
  "geometry": {"coordinates":[0.4724229872,41.1627616882],"type":"Point"}
}