{
  "type": "Feature",
  "properties": {
    "iso:country":"ES",
    "sg:address":"Calle de San Agustin, 12",
    "sg:city":"Albacete",
    "sg:orig_category":"Caf\u00c9s, Bares, Cervecer\u00cdas",
    "sg:phone":"+34 967 24 13 81",
    "sg:postcode":"02001",
    "sg:province":"Albacete",
    "wof:name":"Cafeteria Jj Albacete S.l.",
    "wof:placetype":"venue"
},
  "geometry": {"coordinates":[-1.8521389961,38.9941291809],"type":"Point"}
}