{
  "type": "Feature",
  "properties": {
    "iso:country":"ES",
    "sg:address":"Pase Huertas (las), 55",
    "sg:city":"Almansa",
    "sg:orig_category":"Molduras, Junquillos, Listones Y Molduras Perforadas",
    "sg:phone":"+34 967 31 11 78",
    "sg:postcode":"02640",
    "sg:province":"Albacete",
    "wof:name":"Valiente Belmonte Pascual",
    "wof:placetype":"venue"
},
  "geometry": {"coordinates":[-1.0956139565,38.8690605164],"type":"Point"}
}