{
  "type": "Feature",
  "properties": {
    "addr:full":"Calle de Ruiz Perello, 7 Madrid Madrid 28028",
    "addr:housenumber":"7",
    "addr:postcode":"madrid;28028",
    "addr:street":"Calle De Ruiz Perello",
    "iso:country":"ES",
    "sg:address":"Calle de Ruiz Perello, 7",
    "sg:city":"Madrid",
    "sg:orig_category":"Asociaciones Humanitarias, De Cooperaci\u00d3n, De Acci\u00d3n Social",
    "sg:phone":"+34 913 61 30 01",
    "sg:postcode":"28028",
    "sg:province":"Madrid",
    "sg:website":"www.amafe.org",
    "wof:name":"Asociacion Madrile\u00f1a De Amigos Y Familiares De Enfermos Con Esquizofrenia",
    "wof:placetype":"venue"
},
  "geometry": {"coordinates":[-3.6668114662,40.4299621582],"type":"Point"}
}