{
  "type": "Feature",
  "properties": {
    "iso:country":"ES",
    "sg:address":"Avda Barcelona (de), 16",
    "sg:city":"Cordoba",
    "sg:orig_category":"Telas Y Sedas (al Por Menor)",
    "sg:phone":"+34 957 25 50 28",
    "sg:postcode":"14010",
    "sg:province":"C\u00f3rdoba",
    "wof:name":"Tejidos Amsara Comunidad De Bienes",
    "wof:placetype":"venue"
},
  "geometry": {"coordinates":[-4.7644109726,37.8883132935],"type":"Point"}
}