{
  "type": "Feature",
  "properties": {
    "addr:full":"Carrer de Tordera, 8 Barcelona Barcelona 08012",
    "addr:housenumber":"8",
    "addr:postcode":"08012",
    "addr:street":"Carrer De Tordera",
    "iso:country":"ES",
    "sg:address":"Carrer de Tordera, 8",
    "sg:city":"Barcelona",
    "sg:orig_category":"Tapicer\u00cdas",
    "sg:phone":"+34 934 58 14 06",
    "sg:postcode":"08012",
    "sg:province":"Barcelona",
    "wof:name":"Rosa Cubilo Santos De La",
    "wof:placetype":"venue"
},
  "geometry": {"coordinates":[2.1602370739,41.4004402161],"type":"Point"}
}