{
  "type": "Feature",
  "properties": {
    "addr:full":"Rua Quins, S/n Quins Ourense 32411",
    "addr:housenumber":"s",
    "addr:postcode":"32411",
    "addr:street":"Rua Quins;/ N",
    "iso:country":"ES",
    "sg:address":"Rua Quins, S/n",
    "sg:city":"Quins",
    "sg:orig_category":"Centros De Educaci\u00d3n Especial",
    "sg:phone":"+34 988 48 10 90",
    "sg:postcode":"32411",
    "sg:province":"Ourense",
    "wof:name":"Colegio Publico E.g.b.",
    "wof:placetype":"venue"
},
  "geometry": {"coordinates":[-8.2166290283,42.2567443848],"type":"Point"}
}