{
  "type": "Feature",
  "properties": {
    "addr:full":"Calle de Guipuzcoa, 6 Getafe Madrid 28901",
    "addr:housenumber":"6",
    "addr:postcode":"28901",
    "addr:street":"Calle De Guipuzcoa",
    "iso:country":"ES",
    "sg:address":"Calle de Guipuzcoa, 6",
    "sg:city":"Getafe",
    "sg:classifiers":[
        {
            "category":"Autos & Motor Vehicles",
            "subcategory":"Automobile Sales",
            "type":"Retail Goods"
        }
    ],
    "sg:phone":"+34 916 81 71 71",
    "sg:postcode":"28901",
    "sg:province":"Madrid",
    "wof:name":"Autoescuela Frutos S.l.",
    "wof:placetype":"venue"
},
  "geometry": {"coordinates":[-3.7339177132,40.3027305603],"type":"Point"}
}