{
  "type": "Feature",
  "properties": {
    "addr:full":"Ctra Palmar, 359 Barracas Murcia 30152",
    "addr:housenumber":"359",
    "addr:postcode":"30152",
    "addr:street":"Ctra Palmar",
    "iso:country":"ES",
    "sg:address":"Ctra Palmar, 359",
    "sg:city":"Barracas",
    "sg:orig_category":"Ahumados Y Salazones",
    "sg:phone":"+34 968 25 32 42",
    "sg:postcode":"30152",
    "sg:province":"Murcia",
    "wof:name":"Hernandez Martinez Pedro Jose",
    "wof:placetype":"venue"
},
  "geometry": {"coordinates":[-1.1452490091,37.9643058777],"type":"Point"}
}