{
  "type": "Feature",
  "properties": {
    "addr:full":"Calle de Montejaque, 2 Malaga M\u00e1laga 29004",
    "addr:housenumber":"2",
    "addr:postcode":"29004",
    "addr:street":"Calle De Montejaque;Ma\u0301Laga",
    "iso:country":"ES",
    "sg:address":"Calle de Montejaque, 2",
    "sg:city":"Malaga",
    "sg:orig_category":"Bricolaje, Herramientas (al Por Menor)",
    "sg:phone":"+34 952 10 53 47",
    "sg:postcode":"29004",
    "sg:province":"M\u00e1laga",
    "sg:website":"www.aki.es",
    "wof:name":"Aki Bricolage Espa\u00d1a S.l.",
    "wof:placetype":"venue"
},
  "geometry": {"coordinates":[-4.4583268166,36.6856880188],"type":"Point"}
}