{
  "type": "Feature",
  "properties": {
    "iso:country":"ES",
    "sg:address":"Av Marques De Comillas, S/n",
    "sg:city":"Barcelona",
    "sg:orig_category":"Museos",
    "sg:phone":"+34 934 23 40 16",
    "sg:postcode":"08038",
    "sg:province":"Barcelona",
    "sg:website":"www.miesbcn.com",
    "wof:name":"Fundacio-pavello Mies Van Der Rohe",
    "wof:placetype":"venue"
},
  "geometry": {"coordinates":[2.1455280781,41.368888855],"type":"Point"}
}