{
  "type": "Feature",
  "properties": {
    "iso:country":"ES",
    "sg:address":"Pl Eivissa, 8",
    "sg:city":"Barcelona",
    "sg:orig_category":"Molduras, Junquillos, Listones Y Molduras Perforadas",
    "sg:phone":"+34 933 58 36 75",
    "sg:postcode":"08032",
    "sg:province":"Barcelona",
    "wof:name":"Sanchez Gallego Gerardo",
    "wof:placetype":"venue"
},
  "geometry": {"coordinates":[2.1607670784,41.4304351807],"type":"Point"}
}