{
  "type": "Feature",
  "properties": {
    "iso:country":"ES",
    "sg:address":"Calle de San Marcos, 1",
    "sg:city":"Palmas De Gran Canaria",
    "sg:orig_category":"Inmobiliaria (agencias)",
    "sg:phone":"+34 928 33 49 11",
    "sg:postcode":"35001",
    "sg:province":"Las Palmas",
    "wof:name":"Alago2000 S.l.",
    "wof:placetype":"venue"
},
  "geometry": {"coordinates":[-15.4151277542,28.099199295],"type":"Point"}
}