{
  "type": "Feature",
  "properties": {
    "addr:full":"Rua Pi\u00f1eiro, S/n Escairon Lugo 27540",
    "addr:housenumber":"s",
    "addr:postcode":"27540",
    "addr:street":"Rua Pin\u0303Eiro;/ N",
    "iso:country":"ES",
    "sg:address":"Rua Pi\u00f1eiro, S/n",
    "sg:city":"Escairon",
    "sg:orig_category":"Empresas De Carpinter\u00cda De Madera",
    "sg:phone":"+34 982 45 21 21",
    "sg:postcode":"27540",
    "sg:province":"Lugo",
    "wof:name":"Martinez Guerrero Franciscco",
    "wof:placetype":"venue"
},
  "geometry": {"coordinates":[-7.6331982613,42.5828170776],"type":"Point"}
}