{
  "type": "Feature",
  "properties": {
    "iso:country":"ES",
    "sg:address":"Calle de Pinta, 19",
    "sg:city":"Coria Rio",
    "sg:orig_category":"Promotores Constructores",
    "sg:phone":"+34 954 77 26 11",
    "sg:postcode":"41100",
    "sg:province":"Sevilla",
    "wof:name":"Construcciones Herro S.l.",
    "wof:placetype":"venue"
},
  "geometry": {"coordinates":[-6.0515460968,37.2840270996],"type":"Point"}
}