{
  "type": "Feature",
  "properties": {
    "addr:full":"Cmno Corcullos, S/n Sari\u00f1ena Huesca 22200",
    "addr:housenumber":"s",
    "addr:postcode":"22200",
    "addr:street":"Cmno Corcullos;/ N Sarin\u0303Ena",
    "iso:country":"ES",
    "sg:address":"Cmno Corcullos, S/n",
    "sg:city":"Sari\u00f1ena",
    "sg:orig_category":"Cr\u00cda De Animales",
    "sg:phone":"+34 974 57 23 17",
    "sg:postcode":"22200",
    "sg:province":"Huesca",
    "sg:website":"www.efor.es/usuarios/henryk",
    "wof:name":"Henryk Colab S.l.",
    "wof:placetype":"venue"
},
  "geometry": {"coordinates":[-0.1592289954,41.7914009094],"type":"Point"}
}