{
  "type": "Feature",
  "properties": {
    "iso:country":"ES",
    "sg:address":"Calle de Pedro De Mena, 15",
    "sg:city":"Cullar-vega",
    "sg:orig_category":"Promotores Constructores",
    "sg:phone":"+34 958 58 13 42",
    "sg:postcode":"18195",
    "sg:province":"Granada",
    "wof:name":"Construcciones Nevasol S Coop",
    "wof:placetype":"venue"
},
  "geometry": {"coordinates":[-3.6759619713,37.156665802],"type":"Point"}
}