{
  "type": "Feature",
  "properties": {
    "addr:full":"Bertxin Kalea, 7 Andoain Guip\u00f9zcoa 20140",
    "addr:housenumber":"7",
    "addr:postcode":"20140",
    "addr:street":"Bertxin Kalea;Guipu\u0300Zcoa",
    "iso:country":"ES",
    "sg:address":"Bertxin Kalea, 7",
    "sg:city":"Andoain",
    "sg:orig_category":"Agencias Y Agentes Comerciales, Representantes",
    "sg:phone":"+34 943 59 09 11",
    "sg:postcode":"20140",
    "sg:province":"Guip\u00f9zcoa",
    "wof:name":"Cano Moles Angel",
    "wof:placetype":"venue"
},
  "geometry": {"coordinates":[-2.0195410252,43.2133598328],"type":"Point"}
}