{
  "type": "Feature",
  "properties": {
    "addr:full":"Rua Rosalia De Castro, S/n Vilamean Pontevedra 36350",
    "addr:housenumber":"s / n",
    "addr:postcode":"36350",
    "addr:street":"Rua Rosalia De Castro",
    "iso:country":"ES",
    "sg:address":"Rua Rosalia De Castro, S/n",
    "sg:city":"Vilamean",
    "sg:orig_category":"Inmobiliaria (agencias)",
    "sg:phone":"+34 986 36 86 64",
    "sg:postcode":"36350",
    "sg:province":"Pontevedra",
    "wof:name":"Inmobiliaria J.m.lagos S.l.nigran",
    "wof:placetype":"venue"
},
  "geometry": {"coordinates":[-8.8061685562,42.14087677],"type":"Point"}
}