{
  "type": "Feature",
  "properties": {
    "addr:full":"Fnc Ventorrillos, S/n Burguillos Toledo Toledo 45112",
    "addr:postcode":"45112",
    "addr:street":"Ventorrillos S / N",
    "iso:country":"ES",
    "sg:address":"Fnc Ventorrillos, S/n",
    "sg:city":"Burguillos Toledo",
    "sg:orig_category":"Agricultores, Agricultores",
    "sg:phone":"+34 925 59 00 21",
    "sg:postcode":"45112",
    "sg:province":"Toledo",
    "wof:name":"Fontes Arrendamientos Y Servicios S.a.",
    "wof:placetype":"venue"
},
  "geometry": {"coordinates":[-3.9912641048,39.7966957092],"type":"Point"}
}