{
  "type": "Feature",
  "properties": {
    "iso:country":"ES",
    "sg:address":"Calle de Marques Del Turia, 13",
    "sg:city":"Paiporta",
    "sg:orig_category":"Guarder\u00cdas",
    "sg:phone":"+34 963 97 33 19",
    "sg:postcode":"46200",
    "sg:province":"Valencia",
    "wof:name":"Guarderia El Canguro C.b.",
    "wof:placetype":"venue"
},
  "geometry": {"coordinates":[-0.4215840101,39.4280738831],"type":"Point"}
}