{
  "type": "Feature",
  "properties": {
    "iso:country":"ES",
    "sg:address":"Carr Bajoli, 62",
    "sg:city":"Poima",
    "sg:orig_category":"Transporte En General",
    "sg:phone":"+34 971 35 24 98",
    "sg:postcode":"07714",
    "sg:province":"Islas Baleares",
    "wof:name":"Safari Sub S.l.",
    "wof:placetype":"venue"
},
  "geometry": {"coordinates":[2.9117100239,39.6136398315],"type":"Point"}
}