{
  "type": "Feature",
  "properties": {
    "addr:full":"Carrer de Pare Gallissa, 15 Vic Barcelona 08500",
    "addr:housenumber":"15",
    "addr:postcode":"08500",
    "addr:street":"Carrer De Pare Gallissa",
    "iso:country":"ES",
    "sg:address":"Carrer de Pare Gallissa, 15",
    "sg:city":"Vic",
    "sg:orig_category":"Arquitectos",
    "sg:phone":"+34 938 85 16 58",
    "sg:postcode":"08500",
    "sg:province":"Barcelona",
    "wof:name":"Ylla Vilarrubia Jaume",
    "wof:placetype":"venue"
},
  "geometry": {"coordinates":[2.249414444,41.9323959351],"type":"Point"}
}