{
  "type": "Feature",
  "properties": {
    "iso:country":"ES",
    "sg:address":"Plaz Constitucion, 3",
    "sg:city":"Navalcan",
    "sg:orig_category":"Quincaller\u00cda (al Por Menor)",
    "sg:phone":"+34 925 84 40 03",
    "sg:postcode":"45610",
    "sg:province":"Toledo",
    "wof:name":"Rubio Martin Eufemia",
    "wof:placetype":"venue"
},
  "geometry": {"coordinates":[-5.0921320915,40.0699234009],"type":"Point"}
}