{
  "type": "Feature",
  "properties": {
    "iso:country":"ES",
    "sg:address":"Plaz Don Miguel Diaz De Tuesta, S/n",
    "sg:city":"Salinas De A\u00e7ana",
    "sg:orig_category":"Ense\u00d1anza, Formaci\u00d3n Profesional: Aprendizaje",
    "sg:phone":"+34 945 35 10 67",
    "sg:postcode":"01426",
    "sg:province":"\u00c1lava",
    "wof:name":"Ayuntamiento De Salinas De A\u00d1ana",
    "wof:placetype":"venue"
},
  "geometry": {"coordinates":[-2.6983869076,42.9099998474],"type":"Point"}
}