{
  "type": "Feature",
  "properties": {
    "addr:full":"Pl Forjador, S/n Castellar Valles Barcelona 08211",
    "addr:housenumber":"s",
    "addr:postcode":"08211",
    "addr:street":"Pl Forjador;/ N",
    "iso:country":"ES",
    "sg:address":"Pl Forjador, S/n",
    "sg:city":"Castellar Valles",
    "sg:orig_category":"Reposter\u00cdas",
    "sg:phone":"+34 937 14 84 01",
    "sg:postcode":"08211",
    "sg:province":"Barcelona",
    "wof:name":"Miserachs Estany Francisco",
    "wof:placetype":"venue"
},
  "geometry": {"coordinates":[2.0835499763,41.6127548218],"type":"Point"}
}