{
  "type": "Feature",
  "properties": {
    "iso:country":"ES",
    "sg:address":"Carr Garbi, 20",
    "sg:city":"Selva",
    "sg:orig_category":"Maquinaria Neum\u00c1tica",
    "sg:phone":"+34 972 47 52 22",
    "sg:postcode":"17458",
    "sg:province":"Girona",
    "wof:name":"Draulic Fren S.l.",
    "wof:placetype":"venue"
},
  "geometry": {"coordinates":[2.8099250793,41.9300727844],"type":"Point"}
}