{
  "type": "Feature",
  "properties": {
    "addr:full":"Av Catalunya, 6 Alcoletge Lleida 25660",
    "addr:housenumber":"6",
    "addr:postcode":"25660",
    "addr:street":"Av Catalunya",
    "iso:country":"ES",
    "sg:address":"Av Catalunya, 6",
    "sg:city":"Alcoletge",
    "sg:orig_category":"Centros De Coordinaci\u00d3n",
    "sg:phone":"+34 973 19 70 11",
    "sg:postcode":"25660",
    "sg:province":"Lleida",
    "wof:name":"Gestio Administracio De Serveis Alco S.l.",
    "wof:placetype":"venue"
},
  "geometry": {"coordinates":[0.6938750148,41.6499061584],"type":"Point"}
}