{
  "type": "Feature",
  "properties": {
    "iso:country":"ES",
    "sg:address":"Poligono Ind. El Pla, 5",
    "sg:city":"Alcasser",
    "sg:orig_category":"Limpieza Con Chorro De Arena Y Con Granalla, Pulido",
    "sg:phone":"+34 961 24 27 26",
    "sg:postcode":"46290",
    "sg:province":"Valencia",
    "wof:name":"Pulmundi Pulimentos S.l.",
    "wof:placetype":"venue"
},
  "geometry": {"coordinates":[-0.4453490078,39.3651695251],"type":"Point"}
}