{
  "type": "Feature",
  "properties": {
    "iso:country":"ES",
    "sg:address":"Calle de Magnus Blikstad, 37",
    "sg:city":"Gijon",
    "sg:orig_category":"Librer\u00cdas",
    "sg:phone":"+34 985 34 26 14",
    "sg:postcode":"33207",
    "sg:province":"Asturias",
    "wof:name":"Pando Rodriguez Julio Cesar",
    "wof:placetype":"venue"
},
  "geometry": {"coordinates":[-5.6682066917,43.5370178223],"type":"Point"}
}