{
  "type": "Feature",
  "properties": {
    "addr:full":"Calle de Teresa Gil, 23 Valladolid Valladolid 47002",
    "addr:housenumber":"23",
    "addr:postcode":"47002",
    "addr:street":"Calle De Teresa Gil",
    "iso:country":"ES",
    "sg:address":"Calle de Teresa Gil, 23",
    "sg:city":"Valladolid",
    "sg:orig_category":"Centros Comerciales Y Grandes Tiendas",
    "sg:phone":"+34 983 20 93 47",
    "sg:postcode":"47002",
    "sg:province":"Valladolid",
    "wof:name":"Alianda Es Carmesi S.l.",
    "wof:placetype":"venue"
},
  "geometry": {"coordinates":[-4.7254238129,41.650100708],"type":"Point"}
}