{
  "type": "Feature",
  "properties": {
    "addr:full":"Calle de General Espartero, 46 Alzira Valencia 46600",
    "addr:housenumber":"46",
    "addr:postcode":"46600",
    "addr:street":"Calle De General Espartero",
    "iso:country":"ES",
    "sg:address":"Calle de General Espartero, 46",
    "sg:city":"Alzira",
    "sg:orig_category":"Escayola Y Productos De Escayola (fabricaci\u00d3n, Al Por Mayor)",
    "sg:phone":"+34 962 41 90 21",
    "sg:postcode":"46600",
    "sg:province":"Valencia",
    "wof:name":"Olcina Oliver Federico",
    "wof:placetype":"venue"
},
  "geometry": {"coordinates":[-0.4287860096,39.1605949402],"type":"Point"}
}