{
  "type": "Feature",
  "properties": {
    "iso:country":"ES",
    "sg:address":"Calle de Arrabal, 20",
    "sg:city":"Santander",
    "sg:orig_category":"Asociaciones Y Clubs Deportivos",
    "sg:phone":"+34 942 21 24 24",
    "sg:postcode":"39003",
    "sg:province":"Cantabria",
    "wof:name":"Limite S.c",
    "wof:placetype":"venue"
},
  "geometry": {"coordinates":[-3.8043913841,43.4631690979],"type":"Point"}
}