{
  "type": "Feature",
  "properties": {
    "addr:full":"Carrer de Roure, 7 Viladecans Barcelona 08840",
    "addr:housenumber":"7",
    "addr:postcode":"08840",
    "addr:street":"Carrer De Roure",
    "iso:country":"ES",
    "sg:address":"Carrer de Roure, 7",
    "sg:city":"Viladecans",
    "sg:orig_category":"Empresas De Carpinter\u00cda Met\u00c1lica",
    "sg:phone":"+34 936 59 37 35",
    "sg:postcode":"08840",
    "sg:province":"Barcelona",
    "wof:name":"Alucap Gava S.l.",
    "wof:placetype":"venue"
},
  "geometry": {"coordinates":[2.0141515732,41.3232803345],"type":"Point"}
}