{
  "type": "Feature",
  "properties": {
    "iso:country":"ES",
    "sg:address":"Ausias March, 25",
    "sg:city":"Sollana",
    "sg:orig_category":"Agricultores, Agricultores",
    "sg:phone":"+34 961 74 00 38",
    "sg:postcode":"46430",
    "sg:province":"Valencia",
    "wof:name":"Bosch Ferrus Peregrin",
    "wof:placetype":"venue"
},
  "geometry": {"coordinates":[-0.3798069954,39.27684021],"type":"Point"}
}