{
  "type": "Feature",
  "properties": {
    "iso:country":"ES",
    "sg:address":"Calle de San Bernardo, 7",
    "sg:city":"Gijon",
    "sg:orig_category":"Cuchiller\u00cda (al Por Menor)",
    "sg:phone":"+34 985 34 59 23",
    "sg:postcode":"33201",
    "sg:province":"Asturias",
    "wof:name":"Carlos",
    "wof:placetype":"venue"
},
  "geometry": {"coordinates":[-5.6624779701,43.5440406799],"type":"Point"}
}