{
  "type": "Feature",
  "properties": {
    "addr:full":"Pl Cort, 13 Palma Islas Baleares 07001",
    "addr:housenumber":"13",
    "addr:postcode":"07001",
    "addr:street":"Pl Cort",
    "iso:country":"ES",
    "sg:address":"Pl Cort, 13",
    "sg:city":"Palma",
    "sg:orig_category":"Inmobiliaria (agencias)",
    "sg:phone":"+34 971 71 06 00",
    "sg:postcode":"07001",
    "sg:province":"Islas Baleares",
    "wof:name":"The Best Properties Under The Sun S.l.",
    "wof:placetype":"venue"
},
  "geometry": {"coordinates":[2.6497650146,39.5697975159],"type":"Point"}
}