{
  "type": "Feature",
  "properties": {
    "iso:country":"ES",
    "sg:address":"Carcavas, S/n",
    "sg:city":"Castrogonzalo",
    "sg:orig_category":"F\u00c1bricas De Ladrillo Y Tejas",
    "sg:phone":"+34 980 66 41 14",
    "sg:postcode":"49660",
    "sg:province":"Zamora",
    "wof:name":"Lorenzo Vazquez Isidro",
    "wof:placetype":"venue"
},
  "geometry": {"coordinates":[-5.6342639923,41.9707984924],"type":"Point"}
}