{
  "type": "Feature",
  "properties": {
    "iso:country":"ES",
    "sg:address":"Calle de Puerta De Almodovar, S/n",
    "sg:city":"Cordoba",
    "sg:orig_category":"Bares, Piano",
    "sg:phone":"+34 957 29 08 46",
    "sg:postcode":"14003",
    "sg:province":"C\u00f3rdoba",
    "wof:name":"Cuevas De Shangri S.l.",
    "wof:placetype":"venue"
},
  "geometry": {"coordinates":[-4.7838292122,37.8807640076],"type":"Point"}
}