{
  "type": "Feature",
  "properties": {
    "addr:full":"Calle de Cervantes, 7 Oviedo Asturias 33004",
    "addr:housenumber":"7",
    "addr:postcode":"33004",
    "addr:street":"Calle De Cervantes",
    "iso:country":"ES",
    "sg:address":"Calle de Cervantes, 7",
    "sg:city":"Oviedo",
    "sg:orig_category":"Doctores En Medicina",
    "sg:phone":"+34 985 25 09 77",
    "sg:postcode":"33004",
    "sg:province":"Asturias",
    "wof:name":"Miranda Lucas Victor",
    "wof:placetype":"venue"
},
  "geometry": {"coordinates":[-5.8549394608,43.3618736267],"type":"Point"}
}