{
  "type": "Feature",
  "properties": {
    "iso:country":"ES",
    "sg:address":"Carrer de Faraday, 107",
    "sg:city":"Terrassa",
    "sg:orig_category":"Albergues",
    "sg:phone":"+34 937 33 31 76",
    "sg:postcode":"08224",
    "sg:province":"Barcelona",
    "wof:name":"Asociacion Catalana De Ayuda Y Acogida A Toxicomanos La Encina",
    "wof:placetype":"venue"
},
  "geometry": {"coordinates":[2.0033450127,41.5589637756],"type":"Point"}
}