{
  "type": "Feature",
  "properties": {
    "iso:country":"ES",
    "sg:address":"Paso, 183",
    "sg:city":"Villamayor",
    "sg:orig_category":"Electricidad, Electr\u00d3nica: Suministros (al Por Menor)",
    "sg:phone":"+34 976 58 92 32",
    "sg:postcode":"50162",
    "sg:province":"Zaragoza",
    "wof:name":"Marin Instalaciones Y Reparaciones S.l.",
    "wof:placetype":"venue"
},
  "geometry": {"coordinates":[-0.7721989751,41.6848487854],"type":"Point"}
}