{
  "type": "Feature",
  "properties": {
    "addr:full":"Calle de Progreso, 10 Sevilla Sevilla 41013",
    "addr:housenumber":"10",
    "addr:postcode":"41013",
    "addr:street":"Calle De Progreso",
    "iso:country":"ES",
    "sg:address":"Calle de Progreso, 10",
    "sg:city":"Sevilla",
    "sg:orig_category":"Agentes Generales De Seguros",
    "sg:phone":"+34 954 29 65 60",
    "sg:postcode":"41013",
    "sg:province":"Sevilla",
    "wof:name":"Ama Sociedad Sanitaria De Agencia De Seguros S.l. Unipersonal",
    "wof:placetype":"venue"
},
  "geometry": {"coordinates":[-5.9844903946,37.3731079102],"type":"Point"}
}