{
  "type": "Feature",
  "properties": {
    "addr:full":"Calle de Tokio, 3 Mostoles Madrid 28938",
    "addr:housenumber":"3",
    "addr:postcode":"28938",
    "addr:street":"Calle De Tokio",
    "iso:country":"ES",
    "sg:address":"Calle de Tokio, 3",
    "sg:city":"Mostoles",
    "sg:orig_category":"Restaurantes",
    "sg:phone":"+34 916 14 14 18",
    "sg:postcode":"28938",
    "sg:province":"Madrid",
    "wof:name":"Pelayo Ramirez Manuel",
    "wof:placetype":"venue"
},
  "geometry": {"coordinates":[-3.8639469147,40.3196220398],"type":"Point"}
}