{
  "type": "Feature",
  "properties": {
    "iso:country":"ES",
    "sg:address":"Avia Madrid Andalucia, Km. 0190,6",
    "sg:city":"Valdepe\u00f1as",
    "sg:orig_category":"Restaurantes",
    "sg:phone":"+34 926 32 51 12",
    "sg:postcode":"13300",
    "sg:province":"Ciudad Real",
    "wof:name":"Martinez Fernandez Vicente",
    "wof:placetype":"venue"
},
  "geometry": {"coordinates":[-3.3877990246,38.7597694397],"type":"Point"}
}