{
  "type": "Feature",
  "properties": {
    "iso:country":"ES",
    "sg:address":"Calle de Juan Mari Altuna Kalea, 14",
    "sg:city":"Durango",
    "sg:orig_category":"M\u00c9dicos: Cirug\u00cda Ortop\u00c9dica Y Traumatolog\u00cda",
    "sg:phone":"+34 946 81 23 84",
    "sg:postcode":"48200",
    "sg:province":"Vizcaya",
    "wof:name":"Isasi Sagarduy Jose Luis",
    "wof:placetype":"venue"
},
  "geometry": {"coordinates":[-2.6280250549,43.1682472229],"type":"Point"}
}