{
  "type": "Feature",
  "properties": {
    "iso:country":"ES",
    "sg:address":"Avda Rosalia Castro, 34",
    "sg:city":"Milladoiro",
    "sg:orig_category":"Electrodom\u00c9sticos (al Por Menor)",
    "sg:phone":"+34 981 59 98 26",
    "sg:postcode":"15895",
    "sg:province":"La Coru\u00f1a",
    "wof:name":"Portela Gomez Santiago Ignacio",
    "wof:placetype":"venue"
},
  "geometry": {"coordinates":[-8.5771541595,42.8436088562],"type":"Point"}
}