{
  "type": "Feature",
  "properties": {
    "addr:full":"Carr Republica Argentina, S/n Ciutadella Menorca Islas Baleares 07760",
    "addr:housenumber":"s / n",
    "addr:postcode":"07760",
    "addr:street":"Carr Republica Argentina",
    "iso:country":"ES",
    "sg:address":"Carr Republica Argentina, S/n",
    "sg:city":"Ciutadella Menorca",
    "sg:orig_category":"Ense\u00d1anza, Formaci\u00d3n Profesional: Aprendizaje",
    "sg:phone":"+34 971 48 12 94",
    "sg:postcode":"07760",
    "sg:province":"Islas Baleares",
    "wof:name":"Administracion De Justicia",
    "wof:placetype":"venue"
},
  "geometry": {"coordinates":[3.834426403,39.997505188],"type":"Point"}
}