{
  "type": "Feature",
  "properties": {
    "iso:country":"ES",
    "sg:address":"Calle de Andres Mellado, 46",
    "sg:city":"Madrid",
    "sg:orig_category":"Contables",
    "sg:phone":"+34 915 43 70 43",
    "sg:postcode":"28015",
    "sg:province":"Madrid",
    "wof:name":"Fernandez Go\u00f1i Celia",
    "wof:placetype":"venue"
},
  "geometry": {"coordinates":[-3.7143855095,40.4342727661],"type":"Point"}
}