{
  "type": "Feature",
  "properties": {
    "addr:full":"Carretera Porzuna, S/n Picon Ciudad Real 13196",
    "addr:housenumber":"s / n",
    "addr:postcode":"picon;13196",
    "addr:street":"Carretera Porzuna",
    "iso:country":"ES",
    "sg:address":"Carretera Porzuna, S/n",
    "sg:city":"Picon",
    "sg:orig_category":"\u00c1rboles Frutales",
    "sg:phone":"+34 926 82 00 56",
    "sg:postcode":"13196",
    "sg:province":"Ciudad Real",
    "wof:name":"Romero Gomez Ramon",
    "wof:placetype":"venue"
},
  "geometry": {"coordinates":[-4.048635006,39.0447654724],"type":"Point"}
}