{
  "type": "Feature",
  "properties": {
    "iso:country":"ES",
    "sg:address":"Calle de Almirante Martin De Vallecilla, 9",
    "sg:city":"Portugalete",
    "sg:orig_category":"Sindicatos De Trabajadores",
    "sg:phone":"+34 944 62 64 74",
    "sg:postcode":"48920",
    "sg:province":"Vizcaya",
    "wof:name":"Union Sindical Obrera",
    "wof:placetype":"venue"
},
  "geometry": {"coordinates":[-3.0213220119,43.3174705505],"type":"Point"}
}