{
  "type": "Feature",
  "properties": {
    "addr:full":"Carrer de Columbrets (els), 38 Reus Tarragona 43206",
    "addr:housenumber":"38",
    "addr:postcode":"43206",
    "addr:street":"Carrer De Columbrets Els",
    "iso:country":"ES",
    "sg:address":"Carrer de Columbrets (els), 38",
    "sg:city":"Reus",
    "sg:orig_category":"Agentes, Concesionarios Y Sucursales De Veh\u00cdculos",
    "sg:phone":"+34 977 34 41 00",
    "sg:postcode":"43206",
    "sg:province":"Tarragona",
    "wof:name":"Hernandez Hernandez Francisco",
    "wof:placetype":"venue"
},
  "geometry": {"coordinates":[1.1274950504,41.1666221619],"type":"Point"}
}