{
  "type": "Feature",
  "properties": {
    "iso:country":"ES",
    "sg:address":"Calle de Gran Capitan, 10",
    "sg:city":"Granada",
    "sg:orig_category":"Papeler\u00cdas, Librer\u00cdas",
    "sg:phone":"+34 958 28 66 36",
    "sg:postcode":"18002",
    "sg:province":"Granada",
    "wof:name":"Fernandez Ayudarte Mario",
    "wof:placetype":"venue"
},
  "geometry": {"coordinates":[-3.6042840481,37.1782455444],"type":"Point"}
}