{
  "type": "Feature",
  "properties": {
    "addr:full":"Plaz San Ildefonso, 2 Torre Esteban Hambran Toledo 45920",
    "addr:housenumber":"2",
    "addr:postcode":"45920",
    "addr:street":"Plaz San Ildefonso",
    "iso:country":"ES",
    "sg:address":"Plaz San Ildefonso, 2",
    "sg:city":"Torre Esteban Hambran",
    "sg:orig_category":"Molduras, Junquillos, Listones Y Molduras Perforadas",
    "sg:phone":"+34 925 79 52 41",
    "sg:postcode":"45920",
    "sg:province":"Toledo",
    "wof:name":"Martin Merino Francisco Jose",
    "wof:placetype":"venue"
},
  "geometry": {"coordinates":[-4.025138855,39.8618774414],"type":"Point"}
}