{
  "type": "Feature",
  "properties": {
    "iso:country":"ES",
    "sg:address":"Calle de Limeras, 9",
    "sg:city":"Matanza De Acentejo",
    "sg:orig_category":"Ense\u00d1anza, Formaci\u00d3n Profesional: Aprendizaje",
    "sg:phone":"+34 922 57 86 17",
    "sg:postcode":"38370",
    "sg:province":"Santa Cruz De Tenerife",
    "wof:name":"Ayuntamiento De La Matanza",
    "wof:placetype":"venue"
},
  "geometry": {"coordinates":[-16.4559402466,28.4518852234],"type":"Point"}
}