{
  "type": "Feature",
  "properties": {
    "addr:full":"Av Rhode, 193 Roses Girona 17480",
    "addr:housenumber":"193",
    "addr:postcode":"17480",
    "addr:street":"Av Rhode",
    "iso:country":"ES",
    "sg:address":"Av Rhode, 193",
    "sg:city":"Roses",
    "sg:orig_category":"Molduras, Junquillos, Listones Y Molduras Perforadas",
    "sg:phone":"+34 972 25 60 91",
    "sg:postcode":"17480",
    "sg:province":"Girona",
    "wof:name":"Nimrod S.l.",
    "wof:placetype":"venue"
},
  "geometry": {"coordinates":[3.172369957,42.2646903992],"type":"Point"}
}