{
  "type": "Feature",
  "properties": {
    "iso:country":"ES",
    "sg:address":"Pl Esglesia (de L'), 3",
    "sg:city":"Senia",
    "sg:orig_category":"Carnicer\u00cdas, Carnicer\u00cdas",
    "sg:phone":"+34 977 71 31 84",
    "sg:postcode":"43560",
    "sg:province":"Tarragona",
    "wof:name":"Querol Villarroya Agusti",
    "wof:placetype":"venue"
},
  "geometry": {"coordinates":[0.284525007,40.63306427],"type":"Point"}
}