{
  "type": "Feature",
  "properties": {
    "addr:full":"Ctra Guadalcanal-alanis, S/n Cazalla Sierra Sevilla 41370",
    "addr:housenumber":"s",
    "addr:postcode":"41370",
    "addr:street":"Ctra Guadalcanal-Alanis;/ N Cazalla",
    "iso:country":"ES",
    "sg:address":"Ctra Guadalcanal-alanis, S/n",
    "sg:city":"Cazalla Sierra",
    "sg:orig_category":"Alimentaci\u00d3n General (al Por Mayor)",
    "sg:phone":"+34 954 88 41 19",
    "sg:postcode":"41370",
    "sg:province":"Sevilla",
    "wof:name":"El Noble",
    "wof:placetype":"venue"
},
  "geometry": {"coordinates":[-5.7605638504,37.9321289062],"type":"Point"}
}