{
  "type": "Feature",
  "properties": {
    "iso:country":"ES",
    "sg:address":"Calle de Francia, 39",
    "sg:city":"Palencia",
    "sg:orig_category":"Venta, Alquiler, Mantenimiento De Calderas",
    "sg:phone":"+34 979 16 50 39",
    "sg:postcode":"34004",
    "sg:province":"Palencia",
    "wof:name":"Satermi Palencia S.l.",
    "wof:placetype":"venue"
},
  "geometry": {"coordinates":[-4.5106601715,42.003742218],"type":"Point"}
}