{
  "type": "Feature",
  "properties": {
    "iso:country":"ES",
    "sg:address":"Avda Espa\u00d1a, 72",
    "sg:city":"Plasencia",
    "sg:orig_category":"Plomeros",
    "sg:phone":"+34 927 42 42 71",
    "sg:postcode":"10600",
    "sg:province":"C\u00e1ceres",
    "wof:name":"Vicente Trujillo Manjon Y Otro Cdad",
    "wof:placetype":"venue"
},
  "geometry": {"coordinates":[-6.1020197868,40.0176811218],"type":"Point"}
}