{
  "type": "Feature",
  "properties": {
    "iso:country":"ES",
    "sg:address":"Calle de Arbol Del Cielo, 38",
    "sg:city":"Madrid",
    "sg:orig_category":"Asilos De Ancianos. Centros Privados",
    "sg:phone":"+34 917 06 31 33",
    "sg:postcode":"28044",
    "sg:province":"Madrid",
    "wof:name":"Residencia De Ancianos Virgen De La Paloma",
    "wof:placetype":"venue"
},
  "geometry": {"coordinates":[-3.7639722824,40.3796424866],"type":"Point"}
}