{
  "type": "Feature",
  "properties": {
    "addr:full":"Calle de Monte Naranco, 3 Lugones Asturias 33420",
    "addr:housenumber":"3",
    "addr:postcode":"33420",
    "addr:street":"Calle De Monte Naranco",
    "iso:country":"ES",
    "sg:address":"Calle de Monte Naranco, 3",
    "sg:city":"Lugones",
    "sg:orig_category":"Caf\u00c9s, Bares, Cervecer\u00cdas",
    "sg:phone":"+34 985 26 43 63",
    "sg:postcode":"33420",
    "sg:province":"Asturias",
    "wof:name":"Mavagar C.b.",
    "wof:placetype":"venue"
},
  "geometry": {"coordinates":[-5.812420845,43.4026374817],"type":"Point"}
}