{
  "type": "Feature",
  "properties": {
    "iso:country":"ES",
    "sg:address":"Pl. Iglesia, 8",
    "sg:city":"Cullera",
    "sg:orig_category":"Confecci\u00d3n De Trajes Para Se\u00d1oras",
    "sg:phone":"+34 961 73 04 88",
    "sg:postcode":"46400",
    "sg:province":"Valencia",
    "wof:name":"Santamaria Roca Vicente",
    "wof:placetype":"venue"
},
  "geometry": {"coordinates":[-0.2546519935,39.1649780273],"type":"Point"}
}