{
  "type": "Feature",
  "properties": {
    "iso:country":"ES",
    "sg:address":"Rua Pitelos (dos), 19",
    "sg:city":"Santiago De Compostela",
    "sg:orig_category":"Caf\u00c9s, Bares, Cervecer\u00cdas",
    "sg:phone":"+34 981 58 46 28",
    "sg:postcode":"15702",
    "sg:province":"A Coru\u00f1a",
    "wof:name":"Via\u00f1o Garcia David",
    "wof:placetype":"venue"
},
  "geometry": {"coordinates":[-8.5427017212,42.8761558533],"type":"Point"}
}