{
  "type": "Feature",
  "properties": {
    "addr:full":"Calle de Diego Barquero, 25 Quintana Serena Badajoz 06450",
    "addr:housenumber":"25",
    "addr:postcode":"06450",
    "addr:street":"Calle De Diego Barquero",
    "iso:country":"ES",
    "sg:address":"Calle de Diego Barquero, 25",
    "sg:city":"Quintana Serena",
    "sg:orig_category":"Explotaci\u00d3n De Canteras",
    "sg:phone":"+34 924 77 70 44",
    "sg:postcode":"06450",
    "sg:province":"Badajoz",
    "wof:name":"Canteras Reunidas A.p.",
    "wof:placetype":"venue"
},
  "geometry": {"coordinates":[-5.6691870689,38.7406692505],"type":"Point"}
}