{
  "type": "Feature",
  "properties": {
    "iso:country":"ES",
    "sg:address":"Aveni Sotillo, 1",
    "sg:city":"Segovia",
    "sg:orig_category":"Muebles, Minoristas",
    "sg:phone":"+34 921 43 07 93",
    "sg:postcode":"40196",
    "sg:province":"Segovia",
    "wof:name":"Casado Santos Juan Felix",
    "wof:placetype":"venue"
},
  "geometry": {"coordinates":[-4.1034941673,40.9690361023],"type":"Point"}
}