{
  "type": "Feature",
  "properties": {
    "addr:full":"Av Jaume I, 20 Reus Tarragona 43205",
    "addr:housenumber":"20",
    "addr:postcode":"43205",
    "addr:street":"Av Jaume I",
    "iso:country":"ES",
    "sg:address":"Av Jaume I, 20",
    "sg:city":"Reus",
    "sg:orig_category":"Pintura Y Barniz (al Por Menor)",
    "sg:phone":"+34 977 77 68 69",
    "sg:postcode":"43205",
    "sg:province":"Tarragona",
    "wof:name":"Tost Farre Jordi",
    "wof:placetype":"venue"
},
  "geometry": {"coordinates":[1.1093770266,41.1500053406],"type":"Point"}
}