{
  "type": "Feature",
  "properties": {
    "iso:country":"ES",
    "sg:address":"Pase San Miguel, 11",
    "sg:city":"Villamayor",
    "sg:orig_category":"Ense\u00d1anza Variada",
    "sg:phone":"+34 923 28 67 64",
    "sg:postcode":"37185",
    "sg:province":"Salamanca",
    "wof:name":"Perez Tapia Victor",
    "wof:placetype":"venue"
},
  "geometry": {"coordinates":[-5.6948289871,40.9977111816],"type":"Point"}
}