{
  "type": "Feature",
  "properties": {
    "iso:country":"ES",
    "sg:address":"Rua Caldeireria (da), 37",
    "sg:city":"Santiago De Compostela",
    "sg:orig_category":"Albergues",
    "sg:phone":"+34 981 58 35 17",
    "sg:postcode":"15703",
    "sg:province":"La Coru\u00f1a",
    "wof:name":"Devesa Mouri\u00f1o Josefa",
    "wof:placetype":"venue"
},
  "geometry": {"coordinates":[-8.5427522659,42.8785438538],"type":"Point"}
}