{
  "type": "Feature",
  "properties": {
    "iso:country":"ES",
    "sg:address":"La Soledad, S/n",
    "sg:city":"Sese\u00f1a Nuevo",
    "sg:orig_category":"Empresas De Limpieza",
    "sg:phone":"+34 918 01 22 93",
    "sg:postcode":"45224",
    "sg:province":"Toledo",
    "wof:name":"Sese\u00f1a Limpieza Y Mantenimiento S.a.",
    "wof:placetype":"venue"
},
  "geometry": {"coordinates":[-3.6510140896,40.1083106995],"type":"Point"}
}