{
  "type": "Feature",
  "properties": {
    "addr:full":"Calle de Jose Maria De Pereda, 2 Sevilla Sevilla 41006",
    "addr:housenumber":"2",
    "addr:postcode":"41006",
    "addr:street":"Calle De Jose Maria De Pereda",
    "iso:country":"ES",
    "sg:address":"Calle de Jose Maria De Pereda, 2",
    "sg:city":"Sevilla",
    "sg:orig_category":"Muebles Y Accesorios Para Cocinas Y Cuartos De Ba\u00d1o (al Por Menor)",
    "sg:phone":"+34 954 93 45 59",
    "sg:postcode":"41006",
    "sg:province":"Sevilla",
    "wof:name":"Rotiner Comercial S.l.",
    "wof:placetype":"venue"
},
  "geometry": {"coordinates":[-5.9595270157,37.3705024719],"type":"Point"}
}