{
  "type": "Feature",
  "properties": {
    "addr:full":"Rua Sanjurjo Badia, 97 Vigo Pontevedra 36207",
    "addr:housenumber":"97",
    "addr:postcode":"36207",
    "addr:street":"Rua Sanjurjo Badia",
    "iso:country":"ES",
    "sg:address":"Rua Sanjurjo Badia, 97",
    "sg:city":"Vigo",
    "sg:orig_category":"Telas Y Sedas (al Por Menor)",
    "sg:phone":"+34 986 37 63 03",
    "sg:postcode":"36207",
    "sg:province":"Pontevedra",
    "wof:name":"Fernandez Dominguez Manuel",
    "wof:placetype":"venue"
},
  "geometry": {"coordinates":[-8.7022476196,42.2458572388],"type":"Point"}
}