{
  "type": "Feature",
  "properties": {
    "addr:full":"Carr Baro De Maials, 20 Lleida Lleida 25005",
    "addr:housenumber":"20",
    "addr:postcode":"25005",
    "addr:street":"Carr Baro De Maials",
    "iso:country":"ES",
    "sg:address":"Carr Baro De Maials, 20",
    "sg:city":"Lleida",
    "sg:orig_category":"Farmacias",
    "sg:phone":"+34 973 22 09 47",
    "sg:postcode":"25005",
    "sg:province":"Lleida",
    "wof:name":"Zaldivar Gonzalez-moreno Isabel",
    "wof:placetype":"venue"
},
  "geometry": {"coordinates":[0.6362347007,41.6218910217],"type":"Point"}
}