{
  "type": "Feature",
  "properties": {
    "iso:country":"ES",
    "sg:address":"Calle de Portillo San Antonio, 8",
    "sg:city":"San Miguel",
    "sg:orig_category":"Cajas Para Embalar",
    "sg:phone":"+34 968 27 48 96",
    "sg:postcode":"30005",
    "sg:province":"Murcia",
    "sg:website":"www.cajamar.com",
    "wof:name":"Cajamar",
    "wof:placetype":"venue"
},
  "geometry": {"coordinates":[-1.1326550245,37.988910675],"type":"Point"}
}