{
  "type": "Feature",
  "properties": {
    "addr:full":"Calle de Betis, S/n Lora Rio Sevilla 41440",
    "addr:postcode":"41440",
    "addr:street":"Calle De Betis S / N",
    "iso:country":"ES",
    "sg:address":"Calle de Betis, S/n",
    "sg:city":"Lora Rio",
    "sg:orig_category":"Negocio De Materiales De Construcci\u00d3n",
    "sg:phone":"+34 955 80 04 73",
    "sg:postcode":"41440",
    "sg:province":"Sevilla",
    "wof:name":"Hernandez Carballo S.l.",
    "wof:placetype":"venue"
},
  "geometry": {"coordinates":[-5.5274915695,37.6521644592],"type":"Point"}
}