{
  "type": "Feature",
  "properties": {
    "addr:full":"Carrer de Rossello, 232 Barcelona Barcelona 08008",
    "addr:housenumber":"232",
    "addr:postcode":"08008",
    "addr:street":"Carrer De Rossello",
    "iso:country":"ES",
    "sg:address":"Carrer de Rossello, 232",
    "sg:city":"Barcelona",
    "sg:orig_category":"Agencias De Viajes",
    "sg:phone":"+34 934 87 15 32",
    "sg:postcode":"08008",
    "sg:province":"Barcelona",
    "sg:website":"www.viajespeople.com",
    "wof:name":"Crazy People S. L.",
    "wof:placetype":"venue"
},
  "geometry": {"coordinates":[2.1601610184,41.3952636719],"type":"Point"}
}