{
  "type": "Feature",
  "properties": {
    "addr:full":"Calle de Emilio Ferrari, 10 Madrid Madrid 28017",
    "addr:housenumber":"10",
    "addr:postcode":"madrid;28017",
    "addr:street":"Calle De Emilio Ferrari",
    "iso:country":"ES",
    "sg:address":"Calle de Emilio Ferrari, 10",
    "sg:city":"Madrid",
    "sg:orig_category":"Fisioterapia",
    "sg:phone":"+34 914 06 14 42",
    "sg:postcode":"28017",
    "sg:province":"Madrid",
    "sg:website":"www.fisioweb.com",
    "wof:name":"Fisio Salud S.l.",
    "wof:placetype":"venue"
},
  "geometry": {"coordinates":[-3.6437261105,40.4342384338],"type":"Point"}
}