{
  "type": "Feature",
  "properties": {
    "addr:full":"Calle de Jose De Anchieta, 4 Vitoria-gasteiz \u00c1lava 01003",
    "addr:housenumber":"4",
    "addr:postcode":"01003",
    "addr:street":"Calle De Jose De Anchieta",
    "iso:country":"ES",
    "sg:address":"Calle de Jose De Anchieta, 4",
    "sg:city":"Vitoria-gasteiz",
    "sg:orig_category":"Peluquer\u00cdas, Peluquer\u00cda Mixta",
    "sg:phone":"+34 945 26 95 26",
    "sg:postcode":"01003",
    "sg:province":"\u00c1lava",
    "wof:name":"In-2 Estilistas, S.c.",
    "wof:placetype":"venue"
},
  "geometry": {"coordinates":[-2.6614971161,42.8480987549],"type":"Point"}
}