{
  "type": "Feature",
  "properties": {
    "addr:full":"Pol Ind Polirrosa, 212 Huelva Huelva 21007",
    "addr:housenumber":"212",
    "addr:postcode":"21007",
    "addr:street":"Polirrosa",
    "iso:country":"ES",
    "sg:address":"Pol Ind Polirrosa, 212",
    "sg:city":"Huelva",
    "sg:orig_category":"Empresas De Carpinter\u00cda De Madera",
    "sg:phone":"+34 959 22 17 52",
    "sg:postcode":"21007",
    "sg:province":"Huelva",
    "wof:name":"Mendoza Alfonso Sebastian",
    "wof:placetype":"venue"
},
  "geometry": {"coordinates":[-6.9495940208,37.256313324],"type":"Point"}
}