{
  "type": "Feature",
  "properties": {
    "addr:full":"Calle de Francisco Mendizabal, 3 Valladolid Valladolid 47014",
    "addr:housenumber":"3",
    "addr:postcode":"47014",
    "addr:street":"Calle De Francisco Mendizabal",
    "iso:country":"ES",
    "sg:address":"Calle de Francisco Mendizabal, 3",
    "sg:city":"Valladolid",
    "sg:orig_category":"Molduras, Junquillos, Listones Y Molduras Perforadas",
    "sg:phone":"+34 983 34 50 08",
    "sg:postcode":"47014",
    "sg:province":"Valladolid",
    "wof:name":"Rodriguez Rodriguez Enrique",
    "wof:placetype":"venue"
},
  "geometry": {"coordinates":[-4.7427668571,41.6437034607],"type":"Point"}
}