{
  "type": "Feature",
  "properties": {
    "addr:full":"Martin Azpilcueta, 18 Iru\u00f1a Navarra 31011",
    "addr:housenumber":"18",
    "addr:postcode":"31011",
    "addr:street":"Azpilcueta",
    "iso:country":"ES",
    "sg:address":"Martin Azpilcueta, 18",
    "sg:city":"Iru\u00f1a",
    "sg:orig_category":"Tapicer\u00cdas",
    "sg:phone":"+34 948 25 69 50",
    "sg:postcode":"31011",
    "sg:province":"Navarra",
    "wof:name":"Garbo Decoracion S. L.",
    "wof:placetype":"venue"
},
  "geometry": {"coordinates":[-1.6624809504,42.8136062622],"type":"Point"}
}