{
  "type": "Feature",
  "properties": {
    "addr:full":"Calle de Jesus Arambarri, 94 Salamanca Salamanca 37003",
    "addr:housenumber":"94",
    "addr:postcode":"37003",
    "addr:street":"Calle De Jesus Arambarri",
    "iso:country":"ES",
    "sg:address":"Calle de Jesus Arambarri, 94",
    "sg:city":"Salamanca",
    "sg:orig_category":"Chapister\u00cda",
    "sg:phone":"+34 923 18 28 61",
    "sg:postcode":"37003",
    "sg:province":"Salamanca",
    "wof:name":"Talleres Luitelo S. L.",
    "wof:placetype":"venue"
},
  "geometry": {"coordinates":[-5.6382632256,40.9722366333],"type":"Point"}
}