{
  "type": "Feature",
  "properties": {
    "iso:country":"ES",
    "sg:address":"Calle de Urzabal, 21",
    "sg:city":"Salvatierra O Agurain",
    "sg:orig_category":"Notarios",
    "sg:phone":"+34 945 30 03 70",
    "sg:postcode":"01200",
    "sg:province":"\u00c1lava",
    "wof:name":"Fernandez Zornoza Iciar",
    "wof:placetype":"venue"
},
  "geometry": {"coordinates":[-2.3920099735,42.8489379883],"type":"Point"}
}