{
  "type": "Feature",
  "properties": {
    "iso:country":"ES",
    "sg:address":"Avda Santuario, 2",
    "sg:city":"Virtudes",
    "sg:orig_category":"Asociaciones Humanitarias, De Cooperaci\u00d3n, De Acci\u00d3n Social",
    "sg:phone":"+34 965 80 67 01",
    "sg:postcode":"03409",
    "sg:province":"Alicante",
    "wof:name":"Asociacion Amigos De Alzheimer De Villen",
    "wof:placetype":"venue"
},
  "geometry": {"coordinates":[-0.9311690927,38.6261062622],"type":"Point"}
}