{
  "type": "Feature",
  "properties": {
    "addr:full":"Calle de Zarco Del Valle, 13 Bailen Ja\u00e9n 23710",
    "addr:housenumber":"13",
    "addr:postcode":"23710",
    "addr:street":"Calle De Zarco Del Valle;Jae\u0301N",
    "iso:country":"ES",
    "sg:address":"Calle de Zarco Del Valle, 13",
    "sg:city":"Bailen",
    "sg:orig_category":"Fotograf\u00cda Art\u00cdstica Y Retratos",
    "sg:phone":"+34 953 67 07 73",
    "sg:postcode":"23710",
    "sg:province":"Ja\u00e9n",
    "wof:name":"Garcia Vilches Narciso",
    "wof:placetype":"venue"
},
  "geometry": {"coordinates":[-3.7774391174,38.0957183838],"type":"Point"}
}