{
  "type": "Feature",
  "properties": {
    "addr:full":"Barreiro, S/n Pontes Garcia Rodriguez La Coru\u00f1a 15320",
    "addr:housenumber":"s",
    "addr:postcode":"15320",
    "addr:street":"Barreiro;/ N Pontes Garcia Rodriguez La Corun\u0303A",
    "iso:country":"ES",
    "sg:address":"Barreiro, S/n",
    "sg:city":"Pontes Garcia Rodriguez",
    "sg:orig_category":"Asilos De Ancianos. Centros Privados",
    "sg:phone":"+34 981 45 00 82",
    "sg:postcode":"15320",
    "sg:province":"La Coru\u00f1a",
    "wof:name":"Instituto Gerontologico Astur S.l.",
    "wof:placetype":"venue"
},
  "geometry": {"coordinates":[-8.3959693909,43.3714904785],"type":"Point"}
}