{
  "type": "Feature",
  "properties": {
    "addr:full":"Avda Simon Bolivar, S/n Malaga M\u00e1laga 29011",
    "addr:housenumber":"s / n",
    "addr:postcode":"29011",
    "addr:street":"Avda Simon Bolivar;Ma\u0301Laga",
    "iso:country":"ES",
    "sg:address":"Avda Simon Bolivar, S/n",
    "sg:city":"Malaga",
    "sg:orig_category":"Art\u00cdculos De Decoraci\u00d3n",
    "sg:phone":"+34 952 30 35 82",
    "sg:postcode":"29011",
    "sg:province":"M\u00e1laga",
    "sg:website":"www.casashops.com",
    "wof:name":"Galaso Casa 1 S.l.",
    "wof:placetype":"venue"
},
  "geometry": {"coordinates":[-4.433989048,36.7300300598],"type":"Point"}
}