{
  "type": "Feature",
  "properties": {
    "iso:country":"ES",
    "sg:address":"Calle de Dieciocho De Julio, 17",
    "sg:city":"Santa Brigida",
    "sg:orig_category":"Alimentaci\u00d3n General (al Por Menor)",
    "sg:phone":"+34 928 64 02 85",
    "sg:postcode":"35300",
    "sg:province":"Las Palmas",
    "wof:name":"Medina Ramos Luis",
    "wof:placetype":"venue"
},
  "geometry": {"coordinates":[-15.4964723587,28.0350074768],"type":"Point"}
}