{
  "type": "Feature",
  "properties": {
    "addr:full":"Carretera Quintanar, 9 Toboso Toledo 45820",
    "addr:housenumber":"9",
    "addr:postcode":"45820",
    "addr:street":"Carretera Quintanar",
    "iso:country":"ES",
    "sg:address":"Carretera Quintanar, 9",
    "sg:city":"Toboso",
    "sg:orig_category":"Textil",
    "sg:phone":"+34 925 56 82 52",
    "sg:postcode":"45820",
    "sg:province":"Toledo",
    "wof:name":"Dulcicama C.b.",
    "wof:placetype":"venue"
},
  "geometry": {"coordinates":[-2.998249054,39.5184020996],"type":"Point"}
}