{
  "type": "Feature",
  "properties": {
    "iso:country":"ES",
    "sg:address":"Plaz Iglesia (la), 8",
    "sg:city":"Mas Matas",
    "sg:orig_category":"Bancos",
    "sg:phone":"+34 978 84 80 84",
    "sg:postcode":"44564",
    "sg:province":"Teruel",
    "wof:name":"Bt Espa\u00d1a Compa\u00d1ia De Servicios Globales De Telecomunicaciones S.a.u.",
    "wof:placetype":"venue"
},
  "geometry": {"coordinates":[-1.104550004,40.3420906067],"type":"Point"}
}