{
  "type": "Feature",
  "properties": {
    "addr:full":"Ctra Istan, S/n Marbella M\u00e1laga 29600",
    "addr:housenumber":"s / n",
    "addr:postcode":"29600",
    "addr:street":"Ctra Istan;Ma\u0301Laga",
    "iso:country":"ES",
    "sg:address":"Ctra Istan, S/n",
    "sg:city":"Marbella",
    "sg:orig_category":"Inversiones",
    "sg:phone":"+34 952 90 01 04",
    "sg:postcode":"29600",
    "sg:province":"M\u00e1laga",
    "wof:name":"Eti Sucursal En Espa\u00d1a",
    "wof:placetype":"venue"
},
  "geometry": {"coordinates":[-4.87855196,36.5134544373],"type":"Point"}
}