{
  "type": "Feature",
  "properties": {
    "addr:full":"Calle de Caleros, 16 Ecija Sevilla 41400",
    "addr:housenumber":"16",
    "addr:postcode":"41400",
    "addr:street":"Calle De Caleros",
    "iso:country":"ES",
    "sg:address":"Calle de Caleros, 16",
    "sg:city":"Ecija",
    "sg:orig_category":"Empresarios",
    "sg:phone":"+34 954 83 40 51",
    "sg:postcode":"41400",
    "sg:province":"Sevilla",
    "wof:name":"Laguna Perez Manuel",
    "wof:placetype":"venue"
},
  "geometry": {"coordinates":[-5.0850100517,37.5445747375],"type":"Point"}
}