{
  "type": "Feature",
  "properties": {
    "addr:full":"Mas Fortuny, S/n Torroella Fluvia Girona 17474",
    "addr:housenumber":"s / n",
    "addr:postcode":"17474",
    "iso:country":"ES",
    "sg:address":"Mas Fortuny, S/n",
    "sg:city":"Torroella Fluvia",
    "sg:orig_category":"Importaci\u00d3n",
    "sg:phone":"+34 972 52 06 10",
    "sg:postcode":"17474",
    "sg:province":"Girona",
    "wof:name":"Mon Fruit Sport S.l.",
    "wof:placetype":"venue"
},
  "geometry": {"coordinates":[3.040982008,42.1750831604],"type":"Point"}
}