{
  "type": "Feature",
  "properties": {
    "addr:full":"Calle de Tejar, 1 Humanes De Madrid Madrid 28970",
    "addr:housenumber":"1",
    "addr:postcode":"28970",
    "addr:street":"Calle De Tejar",
    "iso:country":"ES",
    "sg:address":"Calle de Tejar, 1",
    "sg:city":"Humanes De Madrid",
    "sg:orig_category":"Dietistas",
    "sg:phone":"+34 914 98 21 27",
    "sg:postcode":"28970",
    "sg:province":"Madrid",
    "wof:name":"La Bolsa Del Pastor S.l.",
    "wof:placetype":"venue"
},
  "geometry": {"coordinates":[-3.8294041157,40.2527809143],"type":"Point"}
}