{
  "type": "Feature",
  "properties": {
    "iso:country":"ES",
    "sg:address":"Pl Vila, 9",
    "sg:city":"S. Celoni",
    "sg:orig_category":"Ropa Para Ni\u00d1os (al Por Menor)",
    "sg:phone":"+34 938 67 19 02",
    "sg:postcode":"08470",
    "sg:province":"Barcelona",
    "wof:name":"Miralpeix-icart S.c.p.",
    "wof:placetype":"venue"
},
  "geometry": {"coordinates":[2.4918138981,41.6901473999],"type":"Point"}
}