{
  "type": "Feature",
  "properties": {
    "addr:full":"Calle de Don Sancho, 3 Palencia Palencia 34001",
    "addr:housenumber":"3",
    "addr:postcode":"34001",
    "addr:street":"Calle De Don Sancho",
    "iso:country":"ES",
    "sg:address":"Calle de Don Sancho, 3",
    "sg:city":"Palencia",
    "sg:orig_category":"M\u00c9dicos: Estomatolog\u00cda",
    "sg:phone":"+34 979 74 25 40",
    "sg:postcode":"34001",
    "sg:province":"Palencia",
    "wof:name":"Gallardo Gala Ramon",
    "wof:placetype":"venue"
},
  "geometry": {"coordinates":[-4.5326128006,42.0096054077],"type":"Point"}
}