{
  "type": "Feature",
  "properties": {
    "addr:full":"Carrer de Francesc Cambo, 7 Canet Mar Barcelona 08360",
    "addr:housenumber":"7",
    "addr:postcode":"08360",
    "addr:street":"Carrer De Francesc Cambo",
    "iso:country":"ES",
    "sg:address":"Carrer de Francesc Cambo, 7",
    "sg:city":"Canet Mar",
    "sg:orig_category":"Arenas, Guijarros Y Granulados",
    "sg:phone":"+34 937 94 06 75",
    "sg:postcode":"08360",
    "sg:province":"Barcelona",
    "wof:name":"Tot Granit I Pedra S.l.",
    "wof:placetype":"venue"
},
  "geometry": {"coordinates":[2.5737199783,41.5902557373],"type":"Point"}
}