{
  "type": "Feature",
  "properties": {
    "addr:full":"Calle de Becquer, 4 Guardo Palencia 34880",
    "addr:housenumber":"4",
    "addr:postcode":"34880",
    "addr:street":"Calle De Becquer",
    "iso:country":"ES",
    "sg:address":"Calle de Becquer, 4",
    "sg:city":"Guardo",
    "sg:orig_category":"Peluquer\u00cdas, Peluquer\u00cda Mixta",
    "sg:phone":"+34 979 85 29 91",
    "sg:postcode":"34880",
    "sg:province":"Palencia",
    "wof:name":"Macho Iba\u00f1ez Maria Teresa",
    "wof:placetype":"venue"
},
  "geometry": {"coordinates":[-4.8452386856,42.7883758545],"type":"Point"}
}