{
  "type": "Feature",
  "properties": {
    "addr:full":"Plaz Zumarraga, 4 Bilbao Vizcaya 48006",
    "addr:housenumber":"4",
    "addr:postcode":"48006",
    "addr:street":"Zumarraga",
    "iso:country":"ES",
    "sg:address":"Plaz Zumarraga, 4",
    "sg:city":"Bilbao",
    "sg:orig_category":"Producci\u00d3n, Distribuci\u00d3n De Electricidad",
    "sg:phone":"+34 944 16 22 78",
    "sg:postcode":"48006",
    "sg:province":"Vizcaya",
    "wof:name":"Martinez Lopez Alberto",
    "wof:placetype":"venue"
},
  "geometry": {"coordinates":[-2.9197409153,43.2574195862],"type":"Point"}
}