{
  "type": "Feature",
  "properties": {
    "iso:country":"ES",
    "sg:address":"Ptda. Enchilagar Rullo, S/n",
    "sg:city":"Vilamarxant",
    "sg:orig_category":"Fabrica De Cer\u00c1micas",
    "sg:phone":"+34 962 71 08 62",
    "sg:postcode":"46191",
    "sg:province":"Valencia",
    "wof:name":"Ceramicas Ciwca S.l.",
    "wof:placetype":"venue"
},
  "geometry": {"coordinates":[-0.633942008,39.559463501],"type":"Point"}
}