{
  "type": "Feature",
  "properties": {
    "addr:full":"Calle de Garcia Andreu, 44 Alacant Alicante 03007",
    "addr:housenumber":"44",
    "addr:postcode":"03007",
    "addr:street":"Calle De Garcia Andreu",
    "iso:country":"ES",
    "sg:address":"Calle de Garcia Andreu, 44",
    "sg:city":"Alacant",
    "sg:orig_category":"Farmacias",
    "sg:phone":"+34 965 92 56 36",
    "sg:postcode":"03007",
    "sg:province":"Alicante",
    "wof:name":"Lloret Sanchez Tomas",
    "wof:placetype":"venue"
},
  "geometry": {"coordinates":[-0.4965929985,38.3399543762],"type":"Point"}
}