{
  "type": "Feature",
  "properties": {
    "iso:country":"ES",
    "sg:address":"Calle de Maria De Molina, 20",
    "sg:city":"Ubeda",
    "sg:orig_category":"Producci\u00d3n, Venta De Productos De Agricultura Biol\u00d3gica",
    "sg:phone":"+34 953 75 08 74",
    "sg:postcode":"23400",
    "sg:province":"Ja\u00e9n",
    "wof:name":"Cuadra Melero Lucia",
    "wof:placetype":"venue"
},
  "geometry": {"coordinates":[-3.368046999,38.0091934204],"type":"Point"}
}