{
  "type": "Feature",
  "properties": {
    "iso:country":"ES",
    "sg:address":"Vallehermoso, 11",
    "sg:city":"Madrid",
    "sg:orig_category":"Peluqueros: De Se\u00d1oras",
    "sg:phone":"+34 914 45 40 72",
    "sg:postcode":"28015",
    "sg:province":"Madrid",
    "wof:name":"Baca Jacome Veronica",
    "wof:placetype":"venue"
},
  "geometry": {"coordinates":[-3.7089614868,40.4309844971],"type":"Point"}
}