{
  "type": "Feature",
  "properties": {
    "addr:full":"Avda Urtiaga, S/n Mallabia Vizcaya 48269",
    "addr:housenumber":"s / n",
    "addr:postcode":"48269",
    "addr:street":"Avda Urtiaga",
    "iso:country":"ES",
    "sg:address":"Avda Urtiaga, S/n",
    "sg:city":"Mallabia",
    "sg:orig_category":"Mec\u00c1nico Del Autom\u00d3vil",
    "sg:phone":"+34 943 17 04 90",
    "sg:postcode":"48269",
    "sg:province":"Vizcaya",
    "wof:name":"Talleres Ermua S.l.",
    "wof:placetype":"venue"
},
  "geometry": {"coordinates":[-2.5238580704,43.18775177],"type":"Point"}
}