{
  "type": "Feature",
  "properties": {
    "addr:full":"C/ Patricio Ruiz Gomez, 87 Elche Alicante 03206",
    "addr:housenumber":"87",
    "addr:postcode":"03206",
    "addr:street":"C / Patricio Ruiz Gomez",
    "iso:country":"ES",
    "sg:address":"C/ Patricio Ruiz Gomez, 87",
    "sg:city":"Elche",
    "sg:orig_category":"Agencias Y Agentes Comerciales, Representantes",
    "sg:phone":"+34 966 66 00 13",
    "sg:postcode":"03206",
    "sg:province":"Alicante",
    "wof:name":"Pineda Hernandez Rosario",
    "wof:placetype":"venue"
},
  "geometry": {"coordinates":[-0.7077450156,38.2725524902],"type":"Point"}
}