{
  "type": "Feature",
  "properties": {
    "iso:country":"ES",
    "sg:address":"Calle de Brasil, 36",
    "sg:city":"Valencia",
    "sg:orig_category":"Papeler\u00cdas, Librer\u00cdas",
    "sg:phone":"+34 963 83 37 23",
    "sg:postcode":"46018",
    "sg:province":"Valencia",
    "wof:name":"Alvarez Mateo Pedro",
    "wof:placetype":"venue"
},
  "geometry": {"coordinates":[-0.399199605,39.4720954895],"type":"Point"}
}