{
  "type": "Feature",
  "properties": {
    "addr:full":"Calle de Carmona, 7 Alora M\u00e1laga 29500",
    "addr:housenumber":"7",
    "addr:postcode":"29500",
    "addr:street":"Calle De Carmona;Ma\u0301Laga",
    "iso:country":"ES",
    "sg:address":"Calle de Carmona, 7",
    "sg:city":"Alora",
    "sg:orig_category":"M\u00c9dicos: Estomatolog\u00cda",
    "sg:phone":"+34 952 49 57 18",
    "sg:postcode":"29500",
    "sg:province":"M\u00e1laga",
    "wof:name":"Borja Etayo Carlos",
    "wof:placetype":"venue"
},
  "geometry": {"coordinates":[-4.707159996,36.8233566284],"type":"Point"}
}