{
  "type": "Feature",
  "properties": {
    "iso:country":"ES",
    "sg:address":"Carrer de Esglesia, 88",
    "sg:city":"Castelldefels",
    "sg:orig_category":"Frutas, Legumbres Frescas Y Tempranas (al Por Menor)",
    "sg:phone":"+34 936 65 47 56",
    "sg:postcode":"08860",
    "sg:province":"Barcelona",
    "wof:name":"Prior Fruit, S.l.",
    "wof:placetype":"venue"
},
  "geometry": {"coordinates":[1.982033968,41.2843971252],"type":"Point"}
}