{
  "type": "Feature",
  "properties": {
    "iso:country":"ES",
    "sg:address":"Calle de Fumaxil, 4",
    "sg:city":"Oviedo",
    "sg:orig_category":"Promotores Constructores",
    "sg:phone":"+34 985 73 20 11",
    "sg:postcode":"33008",
    "sg:province":"Asturias",
    "wof:name":"Alcuba S. A.",
    "wof:placetype":"venue"
},
  "geometry": {"coordinates":[-5.8427286148,43.3537330627],"type":"Point"}
}