{
  "type": "Feature",
  "properties": {
    "iso:country":"ES",
    "sg:address":"Calle de Do\u00d1a Concha Marmol, 14",
    "sg:city":"Andujar",
    "sg:orig_category":"Empresas De Carpinter\u00cda",
    "sg:phone":"+34 953 51 16 57",
    "sg:postcode":"23740",
    "sg:province":"Ja\u00e9n",
    "wof:name":"Serrano Mu\u00f1oz Francisco Manuel",
    "wof:placetype":"venue"
},
  "geometry": {"coordinates":[-4.0526938438,38.0410690308],"type":"Point"}
}