{
  "type": "Feature",
  "properties": {
    "addr:full":"Carrer de Mare De Deu Del Socors, 3 Terrassa Barcelona 08222",
    "addr:housenumber":"3",
    "addr:postcode":"08222",
    "addr:street":"Carrer De Mare De Deu Del Socors",
    "iso:country":"ES",
    "sg:address":"Carrer de Mare De Deu Del Socors, 3",
    "sg:city":"Terrassa",
    "sg:orig_category":"Carnicer\u00cdas, Carnicer\u00cdas",
    "sg:phone":"+34 937 83 26 81",
    "sg:postcode":"08222",
    "sg:province":"Barcelona",
    "wof:name":"Martinez Rodriguez Maria Teresa",
    "wof:placetype":"venue"
},
  "geometry": {"coordinates":[2.0305540562,41.5591621399],"type":"Point"}
}