{
  "type": "Feature",
  "properties": {
    "iso:country":"ES",
    "sg:address":"Calle de Batalla Del Salado, 5",
    "sg:city":"Albacete",
    "sg:classifiers":[
        {
            "category":"Autos & Motor Vehicles",
            "subcategory":"Automobile Sales",
            "type":"Retail Goods"
        }
    ],
    "sg:phone":"+34 967 22 57 46",
    "sg:postcode":"02006",
    "sg:province":"Albacete",
    "wof:name":"Auto Escuela Avenida Jesus Y Francisco S.l.",
    "wof:placetype":"venue"
},
  "geometry": {"coordinates":[-1.8534325361,38.9870834351],"type":"Point"}
}