{
  "type": "Feature",
  "properties": {
    "addr:full":"Poligono Ind. Puente Nora, S/n Lugones Asturias 33420",
    "addr:housenumber":"s / n",
    "addr:postcode":"33420",
    "addr:street":"Poligono Ind. Puente Nora",
    "iso:country":"ES",
    "sg:address":"Poligono Ind. Puente Nora, S/n",
    "sg:city":"Lugones",
    "sg:orig_category":"Tapicer\u00cdas",
    "sg:phone":"+34 985 26 03 46",
    "sg:postcode":"33420",
    "sg:province":"Asturias",
    "wof:name":"Vigon Menendez Jose Manuel",
    "wof:placetype":"venue"
},
  "geometry": {"coordinates":[-5.8106489182,43.4009132385],"type":"Point"}
}