{
  "type": "Feature",
  "properties": {
    "iso:country":"ES",
    "sg:address":"Calle de Blasco De Garay, 65",
    "sg:city":"Madrid",
    "sg:orig_category":"Veh\u00cdculos De Ocasi\u00d3n",
    "sg:phone":"+34 915 43 12 05",
    "sg:postcode":"28015",
    "sg:province":"Madrid",
    "sg:website":"www.arguelles.com",
    "wof:name":"Arguelles Car S.l.",
    "wof:placetype":"venue"
},
  "geometry": {"coordinates":[-3.7112236023,40.4378433228],"type":"Point"}
}