{
  "type": "Feature",
  "properties": {
    "addr:full":"Ctra Sabadell, Km. 0013,0 Rubi Barcelona 08191",
    "addr:postcode":"08191",
    "addr:street":"Ctra Sabadell Km. 0013,0",
    "iso:country":"ES",
    "sg:address":"Ctra Sabadell, Km. 0013,0",
    "sg:city":"Rubi",
    "sg:orig_category":"Fabricaci\u00d3n De Mobiliario De Oficina",
    "sg:phone":"+34 935 88 53 57",
    "sg:postcode":"08191",
    "sg:province":"Barcelona",
    "wof:name":"Kroper Mobiliario S.l.",
    "wof:placetype":"venue"
},
  "geometry": {"coordinates":[2.0354149342,41.5032501221],"type":"Point"}
}