{
  "type": "Feature",
  "properties": {
    "iso:country":"ES",
    "sg:address":"Cra Laurea Miro, 321",
    "sg:city":"Sant Feliu Llobregat",
    "sg:orig_category":"Suministros Y Materiales Industriales",
    "sg:phone":"+34 936 66 57 11",
    "sg:postcode":"08980",
    "sg:province":"Barcelona",
    "wof:name":"Suministrament Industrials Miranda S.l.",
    "wof:placetype":"venue"
},
  "geometry": {"coordinates":[2.0415461063,41.3841629028],"type":"Point"}
}