{
  "type": "Feature",
  "properties": {
    "addr:full":"Manuel Garcia, 10 Telde Las Palmas 35200",
    "addr:postcode":"35200",
    "addr:street":"Manuel",
    "iso:country":"ES",
    "sg:address":"Manuel Garcia, 10",
    "sg:city":"Telde",
    "sg:orig_category":"Centros P\u00dablicos De Formaci\u00d3n Profesional Y T\u00c9cnica",
    "sg:phone":"+34 928 69 58 12",
    "sg:postcode":"35200",
    "sg:province":"Las Palmas",
    "wof:name":"Federacion Interinsular De Futbol De Las Palmas",
    "wof:placetype":"venue"
},
  "geometry": {"coordinates":[-15.4144220352,28.0029888153],"type":"Point"}
}