{
  "type": "Feature",
  "properties": {
    "addr:full":"Calle de Pescaderia, 11 Donostia-san Sebastian Guip\u00f9zcoa 20003",
    "addr:housenumber":11,
    "addr:postcode":"20003",
    "addr:street":"Calle De Pescaderia",
    "iso:country":"ES",
    "sg:address":"Calle de Pescaderia, 11",
    "sg:city":"Donostia-san Sebastian",
    "sg:orig_category":"Molduras, Junquillos, Listones Y Molduras Perforadas",
    "sg:phone":"+34 943 42 48 73",
    "sg:postcode":"20003",
    "sg:province":"Guip\u00f9zcoa",
    "wof:name":"Bar Nestor",
    "wof:placetype":"venue"
},
  "geometry": {"coordinates":[-1.983735,43.323921],"type":"Point"}
}