{
  "type": "Feature",
  "properties": {
    "addr:full":"Calle de Garzas, 1 Pinto Madrid 28320",
    "addr:housenumber":"1",
    "addr:postcode":"28320",
    "addr:street":"Calle De Garzas;Pinto",
    "iso:country":"ES",
    "sg:address":"Calle de Garzas, 1",
    "sg:city":"Pinto",
    "sg:orig_category":"Servicios De Telecomunicaciones",
    "sg:phone":"+34 917 08 92 90",
    "sg:postcode":"28320",
    "sg:province":"Madrid",
    "sg:website":"www.2020log.es",
    "wof:name":"20 20 Logistics Espa\u00d1a S.a.",
    "wof:placetype":"venue"
},
  "geometry": {"coordinates":[-3.713599,40.24786],"type":"Point"}
}