{
  "type": "Feature",
  "properties": {
    "iso:country":"ES",
    "sg:address":"Ctra Rellinars, 357",
    "sg:city":"Terrassa",
    "sg:orig_category":"Electricidad: Instaladores",
    "sg:phone":"+34 937 88 97 02",
    "sg:postcode":"08225",
    "sg:province":"Barcelona",
    "wof:name":"Torfimag Scp",
    "wof:placetype":"venue"
},
  "geometry": {"coordinates":[2.0025320053,41.5790328979],"type":"Point"}
}