{
  "type": "Feature",
  "properties": {
    "addr:full":"Avda Movera, 340 Movera Zaragoza 50194",
    "addr:housenumber":"340",
    "addr:postcode":"50194",
    "addr:street":"Avda Movera",
    "iso:country":"ES",
    "sg:address":"Avda Movera, 340",
    "sg:city":"Movera",
    "sg:orig_category":"Empresas De Carpinter\u00cda",
    "sg:phone":"+34 976 58 65 94",
    "sg:postcode":"50194",
    "sg:province":"Zaragoza",
    "wof:name":"Lanuza Martin Andres",
    "wof:placetype":"venue"
},
  "geometry": {"coordinates":[-0.8266389966,41.6508636475],"type":"Point"}
}