{
  "type": "Feature",
  "properties": {
    "iso:country":"ES",
    "sg:address":"Calle de Ferreteros, S/n",
    "sg:city":"Malaga",
    "sg:orig_category":"Empresas De Limpieza",
    "sg:phone":"+34 952 33 83 62",
    "sg:postcode":"29006",
    "sg:province":"M\u00e1laga",
    "wof:name":"Servicios De Limpieza Integral De Malaga Iii S.a.",
    "wof:placetype":"venue"
},
  "geometry": {"coordinates":[-4.4457688332,36.7089004517],"type":"Point"}
}