{
  "type": "Feature",
  "properties": {
    "iso:country":"ES",
    "sg:address":"Calle de Juan Mohedo Canales, 49",
    "sg:city":"Montoro",
    "sg:orig_category":"Transportes Por V\u00cdas Navegables",
    "sg:phone":"+34 957 16 15 32",
    "sg:postcode":"14600",
    "sg:province":"C\u00f3rdoba",
    "wof:name":"Marquez Garcia Santiago",
    "wof:placetype":"venue"
},
  "geometry": {"coordinates":[-4.3857131004,38.019203186],"type":"Point"}
}