{
  "type": "Feature",
  "properties": {
    "addr:full":"Avda Santa Ana, 15 Palma Rio C\u00f3rdoba 14700",
    "addr:housenumber":"15",
    "addr:postcode":"14700",
    "addr:street":"Avda Santa Ana;Rio Co\u0301Rdoba",
    "iso:country":"ES",
    "sg:address":"Avda Santa Ana, 15",
    "sg:city":"Palma Rio",
    "sg:orig_category":"Muebles, Minoristas",
    "sg:phone":"+34 957 64 65 24",
    "sg:postcode":"14700",
    "sg:province":"C\u00f3rdoba",
    "wof:name":"Ecomueble S.c.",
    "wof:placetype":"venue"
},
  "geometry": {"coordinates":[-5.2800397873,37.7009658813],"type":"Point"}
}