{
  "type": "Feature",
  "properties": {
    "iso:country":"ES",
    "sg:address":"Av Passeig Del Comtat, 34",
    "sg:city":"Cocentaina",
    "sg:orig_category":"Bancos",
    "sg:phone":"+34 965 59 05 19",
    "sg:postcode":"03820",
    "sg:province":"Alicante",
    "wof:name":"Banco De Valencia S.a.",
    "wof:placetype":"venue"
},
  "geometry": {"coordinates":[-0.4387629926,38.7515029907],"type":"Point"}
}