{
  "type": "Feature",
  "properties": {
    "iso:country":"ES",
    "sg:address":"Carr Rius I Tarroja, 4",
    "sg:city":"Fuliola",
    "sg:orig_category":"Empresarios",
    "sg:phone":"+34 973 57 00 76",
    "sg:postcode":"25332",
    "sg:province":"Lleida",
    "wof:name":"Isern Morgades Alfonso",
    "wof:placetype":"venue"
},
  "geometry": {"coordinates":[1.0171819925,41.7131919861],"type":"Point"}
}