{
  "type": "Feature",
  "properties": {
    "iso:country":"ES",
    "sg:address":"Calle de Mayor, 42",
    "sg:city":"Jaca",
    "sg:orig_category":"Confecci\u00d3n (fabricaci\u00d3n, Al Por Mayor)",
    "sg:phone":"+34 974 36 26 71",
    "sg:postcode":"22700",
    "sg:province":"Huesca",
    "wof:name":"Antona Gonzalez Maria Teresa",
    "wof:placetype":"venue"
},
  "geometry": {"coordinates":[-0.6532735229,42.56772995],"type":"Point"}
}