{
  "type": "Feature",
  "properties": {
    "addr:full":"Ctra Pinar De Los Franceses, S/n Franceses -vega C\u00e1diz 11130",
    "addr:housenumber":"s / n",
    "addr:postcode":"11130",
    "addr:street":"Ctra Pinar De Los;Ca\u0301Diz",
    "iso:country":"ES",
    "sg:address":"Ctra Pinar De Los Franceses, S/n",
    "sg:city":"Franceses -vega",
    "sg:orig_category":"Molduras, Junquillos, Listones Y Molduras Perforadas",
    "sg:phone":"+34 956 40 27 19",
    "sg:postcode":"11130",
    "sg:province":"C\u00e1diz",
    "wof:name":"Macias Anillo Juan",
    "wof:placetype":"venue"
},
  "geometry": {"coordinates":[-6.1447038651,36.4212188721],"type":"Point"}
}