{
  "type": "Feature",
  "properties": {
    "iso:country":"ES",
    "sg:address":"Calle de Iturriaga, 82",
    "sg:city":"Bilbao",
    "sg:orig_category":"Peluqueros: De Se\u00d1oras",
    "sg:phone":"+34 944 73 07 26",
    "sg:postcode":"48004",
    "sg:province":"Vizcaya",
    "wof:name":"Jimenez Macarrilla, Maria Antonia",
    "wof:placetype":"venue"
},
  "geometry": {"coordinates":[-2.9103770256,43.2532844543],"type":"Point"}
}