{
  "type": "Feature",
  "properties": {
    "iso:country":"ES",
    "sg:address":"Calle de Sanchez Pacheco, 38",
    "sg:city":"Madrid",
    "sg:orig_category":"Peleter\u00cdas",
    "sg:phone":"+34 914 13 49 54",
    "sg:postcode":"28002",
    "sg:province":"Madrid",
    "wof:name":"Sanchez De Agustin Maximo",
    "wof:placetype":"venue"
},
  "geometry": {"coordinates":[-3.6747989655,40.4468955994],"type":"Point"}
}