{
  "type": "Feature",
  "properties": {
    "iso:country":"ES",
    "sg:address":"Plaz Valdeserrano (de), 10",
    "sg:city":"Fuenlabrada",
    "sg:classifiers":[
        {
            "category":"Autos & Motor Vehicles",
            "subcategory":"Automobile Sales",
            "type":"Retail Goods"
        }
    ],
    "sg:phone":"+34 916 06 19 91",
    "sg:postcode":"28944",
    "sg:province":"Madrid",
    "wof:name":"Auto Escuelas Nazaret S.l.",
    "wof:placetype":"venue"
},
  "geometry": {"coordinates":[-3.8007831573,40.2767753601],"type":"Point"}
}