{
  "type": "Feature",
  "properties": {
    "iso:country":"ES",
    "sg:address":"Calle de Fuenlabrada, 10",
    "sg:city":"Alcorcon",
    "sg:orig_category":"Animales (al Por Menor)",
    "sg:phone":"+34 916 43 18 13",
    "sg:postcode":"28921",
    "sg:province":"Madrid",
    "wof:name":"Collado Sanchez Ernesto",
    "wof:placetype":"venue"
},
  "geometry": {"coordinates":[-3.8267860413,40.3452720642],"type":"Point"}
}