{
  "type": "Feature",
  "properties": {
    "iso:country":"ES",
    "sg:address":"Gombra, 20",
    "sg:city":"Gombra",
    "sg:orig_category":"Fotograf\u00cda Art\u00cdstica Y Retratos",
    "sg:phone":"+34 986 52 05 36",
    "sg:postcode":"36628",
    "sg:province":"Pontevedra",
    "wof:name":"Varela Varela Luis",
    "wof:placetype":"venue"
},
  "geometry": {"coordinates":[-7.6025080681,43.6471633911],"type":"Point"}
}