{
  "type": "Feature",
  "properties": {
    "iso:country":"ES",
    "sg:address":"Av Alacant, 25",
    "sg:city":"Elche",
    "sg:orig_category":"Electrodom\u00c9sticos (al Por Menor)",
    "sg:phone":"+34 965 45 84 02",
    "sg:postcode":"03202",
    "sg:province":"Alicante",
    "wof:name":"Lopez Jimenez Joaquin",
    "wof:placetype":"venue"
},
  "geometry": {"coordinates":[-0.6852700114,38.268989563],"type":"Point"}
}