{
  "type": "Feature",
  "properties": {
    "iso:country":"ES",
    "sg:address":"Calle de Misericordia, 67",
    "sg:city":"Viveiro",
    "sg:orig_category":"Molduras, Junquillos, Listones Y Molduras Perforadas",
    "sg:phone":"+34 982 56 29 62",
    "sg:postcode":"27850",
    "sg:province":"Lugo",
    "wof:name":"Martinez Galdo Jose",
    "wof:placetype":"venue"
},
  "geometry": {"coordinates":[-7.6015763283,43.6674728394],"type":"Point"}
}