{
  "type": "Feature",
  "properties": {
    "addr:full":"Carr Torrent, 36 Palafrugell Girona 17200",
    "addr:housenumber":"36",
    "addr:postcode":"17200",
    "addr:street":"Carr Torrent",
    "iso:country":"ES",
    "sg:address":"Carr Torrent, 36",
    "sg:city":"Palafrugell",
    "sg:orig_category":"Plomeros",
    "sg:phone":"+34 972 30 21 96",
    "sg:postcode":"17200",
    "sg:province":"Girona",
    "wof:name":"Vergo\u00f1os Molero Josep",
    "wof:placetype":"venue"
},
  "geometry": {"coordinates":[3.1597599983,41.9181594849],"type":"Point"}
}