{
  "type": "Feature",
  "properties": {
    "addr:full":"Avda Lope De Figueroa, S/n Alcala Henares Madrid 28804",
    "addr:housenumber":"s",
    "addr:postcode":"28804",
    "addr:street":"Avda Lope De Figueroa;/ N",
    "iso:country":"ES",
    "sg:address":"Avda Lope De Figueroa, S/n",
    "sg:city":"Alcala Henares",
    "sg:orig_category":"Caf\u00c9s, Bares, Cervecer\u00cdas",
    "sg:phone":"+34 918 82 63 25",
    "sg:postcode":"28804",
    "sg:province":"Madrid",
    "wof:name":"Martin Sacristan Jesus",
    "wof:placetype":"venue"
},
  "geometry": {"coordinates":[-3.3461289406,40.489490509],"type":"Point"}
}