{
  "type": "Feature",
  "properties": {
    "iso:country":"ES",
    "sg:address":"Avda Roma (de), 10",
    "sg:city":"Coslada",
    "sg:orig_category":"Decoraci\u00d3n: Instalaci\u00d3n Y Talleres",
    "sg:phone":"+34 916 73 71 15",
    "sg:postcode":"28820",
    "sg:province":"Madrid",
    "wof:name":"Decoraciones Y Reformas Del Valle S.l.",
    "wof:placetype":"venue"
},
  "geometry": {"coordinates":[-3.5394940376,40.4214286804],"type":"Point"}
}