{
  "type": "Feature",
  "properties": {
    "addr:full":"Calle de Laurel (el), 7 Cordoba C\u00f3rdoba 14006",
    "addr:housenumber":"7",
    "addr:postcode":"14006",
    "addr:street":"Calle De Laurel El;Co\u0301Rdoba",
    "iso:country":"ES",
    "sg:address":"Calle de Laurel (el), 7",
    "sg:city":"Cordoba",
    "sg:orig_category":"Consultor\u00cdas Diversas",
    "sg:phone":"+34 957 27 49 40",
    "sg:postcode":"14006",
    "sg:province":"C\u00f3rdoba",
    "wof:name":"Ballesteros Mu\u00f1oz Francisco",
    "wof:placetype":"venue"
},
  "geometry": {"coordinates":[-4.7833251953,37.8977394104],"type":"Point"}
}