{
  "type": "Feature",
  "properties": {
    "addr:full":"Carrer de Martirs Del Setge De 1714, 25 Gava Barcelona 08850",
    "addr:housenumber":"25",
    "addr:postcode":"08850",
    "addr:street":"Carrer De Martirs Del Setge De 1714",
    "iso:country":"ES",
    "sg:address":"Carrer de Martirs Del Setge De 1714, 25",
    "sg:city":"Gava",
    "sg:orig_category":"Bisuter\u00cda, Joyer\u00cda, Relojer\u00cda (al Por Menor)",
    "sg:phone":"+34 936 33 66 23",
    "sg:postcode":"08850",
    "sg:province":"Barcelona",
    "wof:name":"Subira Mateu Jose Maria",
    "wof:placetype":"venue"
},
  "geometry": {"coordinates":[2.0061380863,41.3052558899],"type":"Point"}
}