{
  "type": "Feature",
  "properties": {
    "iso:country":"ES",
    "sg:address":"Carr Mestre Tapies, 2",
    "sg:city":"Montoliu Lleida",
    "sg:orig_category":"Agencias Y Agentes Comerciales, Representantes",
    "sg:phone":"+34 973 72 02 06",
    "sg:postcode":"25172",
    "sg:province":"Lleida",
    "wof:name":"Fernandez Sole Carmen",
    "wof:placetype":"venue"
},
  "geometry": {"coordinates":[0.5887849927,41.5605354309],"type":"Point"}
}