{
  "type": "Feature",
  "properties": {
    "iso:country":"ES",
    "sg:address":"Ctra. Salamanca, S/n",
    "sg:city":"Plasencia",
    "sg:orig_category":"Mec\u00c1nico Del Autom\u00d3vil",
    "sg:phone":"+34 927 42 47 40",
    "sg:postcode":"10600",
    "sg:province":"C\u00e1ceres",
    "wof:name":"Dominguez Alonso Pedro",
    "wof:placetype":"venue"
},
  "geometry": {"coordinates":[-6.0923109055,40.0371704102],"type":"Point"}
}