{
  "type": "Feature",
  "properties": {
    "addr:full":"Calle de Florencia, 10 Madrid Madrid 28030",
    "addr:housenumber":"10",
    "addr:postcode":"madrid;28030",
    "addr:street":"Calle De Florencia",
    "iso:country":"ES",
    "sg:address":"Calle de Florencia, 10",
    "sg:city":"Madrid",
    "sg:orig_category":"Molduras, Junquillos, Listones Y Molduras Perforadas",
    "sg:phone":"+34 917 72 59 66",
    "sg:postcode":"28030",
    "sg:province":"Madrid",
    "wof:name":"Gonzalez Garcia Jose Alberto",
    "wof:placetype":"venue"
},
  "geometry": {"coordinates":[-3.6277899742,40.4020652771],"type":"Point"}
}