{
  "type": "Feature",
  "properties": {
    "iso:country":"ES",
    "sg:address":"Carr Gabriel Miro, 1",
    "sg:city":"Benissa",
    "sg:orig_category":"Empresas De Pintura Y Revestimientos",
    "sg:phone":"+34 965 73 14 24",
    "sg:postcode":"03720",
    "sg:province":"Alicante",
    "wof:name":"Bertomeu Ferrer Jaime",
    "wof:placetype":"venue"
},
  "geometry": {"coordinates":[0.0430580005,38.7126312256],"type":"Point"}
}