{
  "type": "Feature",
  "properties": {
    "iso:country":"ES",
    "sg:address":"Calle de Rambla (la), S/n",
    "sg:city":"Urbanizacion Campo De Golf",
    "sg:orig_category":"Centros Empresariales",
    "sg:phone":"+34 968 17 56 42",
    "sg:postcode":"30385",
    "sg:province":"Murcia",
    "wof:name":"Comunidad General - La Manga Club",
    "wof:placetype":"venue"
},
  "geometry": {"coordinates":[-0.7967690229,37.5958709717],"type":"Point"}
}