{
  "type": "Feature",
  "properties": {
    "addr:full":"Carrer de Canuda, 26 Barcelona Barcelona 08002",
    "addr:housenumber":"26",
    "addr:postcode":"08002",
    "addr:street":"Carrer De Canuda",
    "iso:country":"ES",
    "sg:address":"Carrer de Canuda, 26",
    "sg:city":"Barcelona",
    "sg:orig_category":"Asociaciones Y Clubs Deportivos",
    "sg:phone":"+34 933 18 44 34",
    "sg:postcode":"08002",
    "sg:province":"Barcelona",
    "wof:name":"Ma\u00f1anes Carilla Alfonso",
    "wof:placetype":"venue"
},
  "geometry": {"coordinates":[2.1733179092,41.3848457336],"type":"Point"}
}