{
  "type": "Feature",
  "properties": {
    "addr:full":"Carrer de Creueta, 71 Sabadell Barcelona 08202",
    "addr:housenumber":"71",
    "addr:postcode":"08202",
    "addr:street":"Carrer De Creueta",
    "iso:country":"ES",
    "sg:address":"Carrer de Creueta, 71",
    "sg:city":"Sabadell",
    "sg:orig_category":"Arquitectos",
    "sg:phone":"+34 937 26 51 72",
    "sg:postcode":"08202",
    "sg:province":"Barcelona",
    "wof:name":"Giribet Sanllehy Carles Joan",
    "wof:placetype":"venue"
},
  "geometry": {"coordinates":[2.1118021011,41.5495986938],"type":"Point"}
}