{
  "type": "Feature",
  "properties": {
    "iso:country":"ES",
    "sg:address":"Calle de Carmen (el), 45",
    "sg:city":"Baeza",
    "sg:orig_category":"Reposter\u00cdas",
    "sg:phone":"+34 953 74 08 63",
    "sg:postcode":"23440",
    "sg:province":"Ja\u00e9n",
    "wof:name":"Rus Garrido Pedro",
    "wof:placetype":"venue"
},
  "geometry": {"coordinates":[-3.4643089771,37.9934158325],"type":"Point"}
}