{
  "type": "Feature",
  "properties": {
    "iso:country":"ES",
    "sg:address":"Carr Joan Emili, 2",
    "sg:city":"Sant Joan De Palamos",
    "sg:orig_category":"Asesor\u00cda Sobre Comunicaci\u00d3n De Empresas",
    "sg:phone":"+34 972 60 21 93",
    "sg:postcode":"17230",
    "sg:province":"Girona",
    "wof:name":"Assessoria Costa Brava S.l.",
    "wof:placetype":"venue"
},
  "geometry": {"coordinates":[3.1294622421,41.8505706787],"type":"Point"}
}