{
  "type": "Feature",
  "properties": {
    "addr:full":"Calle de Colon, 52 Pozo Ca\u00e7ada Albacete 02510",
    "addr:housenumber":"52",
    "addr:postcode":"02510",
    "addr:street":"Calle De Colon",
    "iso:country":"ES",
    "sg:address":"Calle de Colon, 52",
    "sg:city":"Pozo Ca\u00e7ada",
    "sg:orig_category":"Agencias Y Agentes Comerciales, Representantes",
    "sg:phone":"+34 967 25 10 42",
    "sg:postcode":"02510",
    "sg:province":"Albacete",
    "wof:name":"Gonzalez Sanchez Juan Antonio",
    "wof:placetype":"venue"
},
  "geometry": {"coordinates":[-1.8600701094,38.9976501465],"type":"Point"}
}