{
  "type": "Feature",
  "properties": {
    "iso:country":"ES",
    "sg:address":"Calle de Badajoz, 65",
    "sg:city":"Albacete",
    "sg:orig_category":"Promotores Constructores",
    "sg:phone":"+34 967 50 02 07",
    "sg:postcode":"02006",
    "sg:province":"Albacete",
    "wof:name":"Comunidad De Propietarios Badajoz 65",
    "wof:placetype":"venue"
},
  "geometry": {"coordinates":[-1.877212882,38.9922065735],"type":"Point"}
}