{
  "type": "Feature",
  "properties": {
    "addr:full":"Cami L'esglesia, 4 Barcelona Barcelona 08024",
    "addr:housenumber":"4",
    "addr:postcode":"08024",
    "addr:street":"L'Esglesia",
    "iso:country":"ES",
    "sg:address":"Cami L'esglesia, 4",
    "sg:city":"Barcelona",
    "sg:orig_category":"Arquitectos",
    "sg:phone":"+34 932 17 94 43",
    "sg:postcode":"08024",
    "sg:province":"Barcelona",
    "wof:name":"Acosta Ramos Gonzalo",
    "wof:placetype":"venue"
},
  "geometry": {"coordinates":[2.1570904255,41.4053192139],"type":"Point"}
}