{
  "type": "Feature",
  "properties": {
    "iso:country":"ES",
    "sg:address":"Calle de Lozano Sidro, 27",
    "sg:city":"Priego Cordoba",
    "sg:orig_category":"Supermercados Y Hipermercados",
    "sg:phone":"+34 957 54 02 88",
    "sg:postcode":"14800",
    "sg:province":"C\u00f3rdoba",
    "wof:name":"Aguilar Gutierrez Francisco",
    "wof:placetype":"venue"
},
  "geometry": {"coordinates":[-4.1990156174,37.4375076294],"type":"Point"}
}