{
  "type": "Feature",
  "properties": {
    "iso:country":"ES",
    "sg:address":"Calle de Marva, 30",
    "sg:city":"Valencia",
    "sg:orig_category":"Psic\u00d3logos",
    "sg:phone":"+34 963 41 86 14",
    "sg:postcode":"46007",
    "sg:province":"Valencia",
    "wof:name":"Centro Psicologico De Diagnostico Terapia Y Ense\u00f1anza S.cv.",
    "wof:placetype":"venue"
},
  "geometry": {"coordinates":[-0.384611994,39.4641036987],"type":"Point"}
}