{
  "type": "Feature",
  "properties": {
    "addr:full":"Calle de Rosalia De Castro, 6 Guarda Pontevedra 36780",
    "addr:housenumber":"6",
    "addr:postcode":"36780",
    "addr:street":"Calle De Rosalia De Castro",
    "iso:country":"ES",
    "sg:address":"Calle de Rosalia De Castro, 6",
    "sg:city":"Guarda",
    "sg:orig_category":"Molduras, Junquillos, Listones Y Molduras Perforadas",
    "sg:phone":"+34 986 61 03 08",
    "sg:postcode":"36780",
    "sg:province":"Pontevedra",
    "wof:name":"Alonso Vicente Avelina",
    "wof:placetype":"venue"
},
  "geometry": {"coordinates":[-8.8672122955,41.9032440186],"type":"Point"}
}