{
  "type": "Feature",
  "properties": {
    "iso:country":"ES",
    "sg:address":"Carrer de Arago, 190",
    "sg:city":"Palma",
    "sg:classifiers":[
        {
            "category":"Personal",
            "subcategory":"Barber",
            "type":"Services"
        }
    ],
    "sg:phone":"+34 971 47 86 70",
    "sg:postcode":"07008",
    "sg:province":"Islas Baleares",
    "sg:tags":[
        "caballeros",
        "de",
        "peluqueros"
    ],
    "wof:name":"Castell Ferreiro Gaspar",
    "wof:placetype":"venue"
},
  "geometry": {"coordinates":[2.6733059883,39.5858802795],"type":"Point"}
}