{
  "type": "Feature",
  "properties": {
    "addr:full":"Plaz San Kristobal, 4 Gernika-lumo Vizcaya 48300",
    "addr:housenumber":"4",
    "addr:postcode":"48300",
    "addr:street":"Plaz San Kristobal",
    "iso:country":"ES",
    "sg:address":"Plaz San Kristobal, 4",
    "sg:city":"Gernika-lumo",
    "sg:orig_category":"Electrodom\u00c9sticos (al Por Menor)",
    "sg:phone":"+34 946 25 06 53",
    "sg:postcode":"48300",
    "sg:province":"Vizcaya",
    "wof:name":"Iratxe Iturbe Bilbao",
    "wof:placetype":"venue"
},
  "geometry": {"coordinates":[-2.7171080112,43.3564567566],"type":"Point"}
}