{
  "type": "Feature",
  "properties": {
    "addr:full":"Carr Alfons Xii, 605 Badalona Barcelona 08918",
    "addr:housenumber":"605",
    "addr:postcode":"08918",
    "addr:street":"Carr Alfons Xii",
    "iso:country":"ES",
    "sg:address":"Carr Alfons Xii, 605",
    "sg:city":"Badalona",
    "sg:orig_category":"Venta, Localizaci\u00d3n, Reparaci\u00d3n De Material E Instrumental M\u00c9dico",
    "sg:phone":"+34 933 98 82 88",
    "sg:postcode":"08918",
    "sg:province":"Barcelona",
    "sg:website":"www.ashmed.net",
    "wof:name":"Suministros Hospitalarios S.a.",
    "wof:placetype":"venue"
},
  "geometry": {"coordinates":[2.2286400795,41.4343528748],"type":"Point"}
}