{
  "type": "Feature",
  "properties": {
    "addr:full":"Via Roma, 5 Salou Tarragona 43840",
    "addr:housenumber":"5",
    "addr:postcode":"43840",
    "addr:street":"Via Roma",
    "iso:country":"ES",
    "sg:address":"Via Roma, 5",
    "sg:city":"Salou",
    "sg:orig_category":"Laboratorios Y Trabajos De Fotograf\u00cda, V\u00cddeo Y Cine",
    "sg:phone":"+34 977 35 26 37",
    "sg:postcode":"43840",
    "sg:province":"Tarragona",
    "wof:name":"Establecimientos Photo Speed S.l.",
    "wof:placetype":"venue"
},
  "geometry": {"coordinates":[1.1308540106,41.0789222717],"type":"Point"}
}