{
  "type": "Feature",
  "properties": {
    "addr:full":"Av Sant Cristofol, 26 Pla Manlleu Tarragona 43714",
    "addr:housenumber":"26",
    "addr:postcode":"43714",
    "addr:street":"Av Sant Cristofol",
    "iso:country":"ES",
    "sg:address":"Av Sant Cristofol, 26",
    "sg:city":"Pla Manlleu",
    "sg:orig_category":"Fabrica De Charcuter\u00cda",
    "sg:phone":"+34 977 63 86 82",
    "sg:postcode":"43714",
    "sg:province":"Tarragona",
    "wof:name":"Benito Llenas Anton",
    "wof:placetype":"venue"
},
  "geometry": {"coordinates":[1.5027849674,41.3509407043],"type":"Point"}
}