{
  "type": "Feature",
  "properties": {
    "iso:country":"ES",
    "sg:address":"Avda Vicente Navarro, 43",
    "sg:city":"Cheste",
    "sg:orig_category":"Muebles, Minoristas",
    "sg:phone":"+34 962 51 00 68",
    "sg:postcode":"46380",
    "sg:province":"Valencia",
    "wof:name":"Rodrigo Arevalo Arturo",
    "wof:placetype":"venue"
},
  "geometry": {"coordinates":[-0.6857600212,39.4918441772],"type":"Point"}
}