{
  "type": "Feature",
  "properties": {
    "addr:full":"Rua Alcalde Daniel Ojea, 6 Ponteareas Pontevedra 36860",
    "addr:housenumber":"6",
    "addr:postcode":"36860",
    "addr:street":"Rua Alcalde Daniel Ojea",
    "iso:country":"ES",
    "sg:address":"Rua Alcalde Daniel Ojea, 6",
    "sg:city":"Ponteareas",
    "sg:orig_category":"Servicios De Telecomunicaciones",
    "sg:phone":"+34 986 64 41 08",
    "sg:postcode":"36860",
    "sg:province":"Pontevedra",
    "wof:name":"Orge Garrido Rosario",
    "wof:placetype":"venue"
},
  "geometry": {"coordinates":[-8.5163888931,42.1783599854],"type":"Point"}
}