{
  "type": "Feature",
  "properties": {
    "addr:full":"Avda Manantiales De Los, 7 Torremolinos M\u00e1laga 29620",
    "addr:housenumber":"7",
    "addr:postcode":"29620",
    "addr:street":"Avda Manantiales De Los;Ma\u0301Laga",
    "iso:country":"ES",
    "sg:address":"Avda Manantiales De Los, 7",
    "sg:city":"Torremolinos",
    "sg:orig_category":"M\u00c9dicos: Estomatolog\u00cda",
    "sg:phone":"+34 952 38 53 94",
    "sg:postcode":"29620",
    "sg:province":"M\u00e1laga",
    "wof:name":"Navarrete Megia Miguel",
    "wof:placetype":"venue"
},
  "geometry": {"coordinates":[-4.5009851456,36.6252441406],"type":"Point"}
}