{
  "type": "Feature",
  "properties": {
    "addr:full":"Calle de Lisboa, 30 Torrejon Ardoz Madrid 28850",
    "addr:housenumber":"30",
    "addr:postcode":"28850",
    "addr:street":"Calle De Lisboa",
    "iso:country":"ES",
    "sg:address":"Calle de Lisboa, 30",
    "sg:city":"Torrejon Ardoz",
    "sg:orig_category":"Centros Comerciales Y Grandes Tiendas",
    "sg:phone":"+34 916 56 92 21",
    "sg:postcode":"28850",
    "sg:province":"Madrid",
    "wof:name":"Centro Comercial Las Veredillas",
    "wof:placetype":"venue"
},
  "geometry": {"coordinates":[-3.4701590538,40.4642601013],"type":"Point"}
}