{
  "type": "Feature",
  "properties": {
    "addr:full":"Calle de Comandante Barja, 10 Coru\u00d1a La Coru\u00f1a 15004",
    "addr:housenumber":"10",
    "addr:postcode":"15004",
    "addr:street":"Calle De Comandante Barja;La Corun\u0303A",
    "iso:country":"ES",
    "sg:address":"Calle de Comandante Barja, 10",
    "sg:city":"Coru\u00d1a",
    "sg:orig_category":"Mercer\u00cda, Lencer\u00cda (al Por Menor)",
    "sg:phone":"+34 981 25 14 86",
    "sg:postcode":"15004",
    "sg:province":"La Coru\u00f1a",
    "wof:name":"Rodriguez Saiz Maria Jose",
    "wof:placetype":"venue"
},
  "geometry": {"coordinates":[-8.4107322693,43.3675270081],"type":"Point"}
}