{
  "type": "Feature",
  "properties": {
    "addr:full":"Carr Ciutat De Laval, 33 Gandia Valencia 46700",
    "addr:housenumber":"33",
    "addr:postcode":"46700",
    "addr:street":"Carr Ciutat De Laval;Valencia",
    "iso:country":"ES",
    "sg:address":"Carr Ciutat De Laval, 33",
    "sg:city":"Gandia",
    "sg:orig_category":"Asociaciones Y Clubs Deportivos",
    "sg:phone":"+34 962 96 12 61",
    "sg:postcode":"46700",
    "sg:province":"Valencia",
    "wof:name":"Etvan Fitness Sl",
    "wof:placetype":"venue"
},
  "geometry": {"coordinates":[-0.1913339943,38.960735321],"type":"Point"}
}