{
  "type": "Feature",
  "properties": {
    "iso:country":"ES",
    "sg:address":"Avda Rafael Puig Llivina, 24",
    "sg:city":"Playa Americas",
    "sg:orig_category":"Centros Empresariales",
    "sg:phone":"+34 922 78 92 34",
    "sg:postcode":"38660",
    "sg:province":"Santa Cruz De Tenerife",
    "wof:name":"Diaz Requena Carmen",
    "wof:placetype":"venue"
},
  "geometry": {"coordinates":[-16.7317714691,28.0760765076],"type":"Point"}
}