{
  "type": "Feature",
  "properties": {
    "addr:full":"Rua Ramon Aller, 1 Lalin Pontevedra 36500",
    "addr:housenumber":"1",
    "addr:postcode":"36500",
    "addr:street":"Rua Ramon Aller",
    "iso:country":"ES",
    "sg:address":"Rua Ramon Aller, 1",
    "sg:city":"Lalin",
    "sg:orig_category":"Abogados",
    "sg:phone":"+34 986 78 03 42",
    "sg:postcode":"36500",
    "sg:province":"Pontevedra",
    "wof:name":"Nistal Gonzalez Manuel Esteban",
    "wof:placetype":"venue"
},
  "geometry": {"coordinates":[-8.1161289215,42.6587181091],"type":"Point"}
}