{
  "type": "Feature",
  "properties": {
    "addr:full":"Avda Jesus Garcia Naveira, 54 Betanzos La Coru\u00f1a 15300",
    "addr:housenumber":"54",
    "addr:postcode":"15300",
    "addr:street":"Avda Jesus Garcia Naveira;La",
    "iso:country":"ES",
    "sg:address":"Avda Jesus Garcia Naveira, 54",
    "sg:city":"Betanzos",
    "sg:orig_category":"Psic\u00d3logos",
    "sg:phone":"+34 981 77 34 70",
    "sg:postcode":"15300",
    "sg:province":"La Coru\u00f1a",
    "wof:name":"Ana Maria Lopez Corton Facal",
    "wof:placetype":"venue"
},
  "geometry": {"coordinates":[-8.2132930756,43.2763671875],"type":"Point"}
}