{
  "type": "Feature",
  "properties": {
    "addr:full":"Carr Girona, S/n Planes D'hostoles Girona 17172",
    "addr:housenumber":"s / n",
    "addr:postcode":"17172",
    "addr:street":"Carr Girona;D'Hostoles",
    "iso:country":"ES",
    "sg:address":"Carr Girona, S/n",
    "sg:city":"Planes D'hostoles",
    "sg:orig_category":"Art\u00cdculos De Limpieza Y De Cocina (fabricaci\u00d3n, Al Por Mayor)",
    "sg:phone":"+34 972 44 80 80",
    "sg:postcode":"17172",
    "sg:province":"Girona",
    "sg:website":"www.mundet.biz",
    "wof:name":"Mundet Productions S.l.",
    "wof:placetype":"venue"
},
  "geometry": {"coordinates":[2.8306620121,41.9647369385],"type":"Point"}
}