{
  "type": "Feature",
  "properties": {
    "addr:full":"Calle de Puerto Naos, 20 Arrecife Las Palmas 35500",
    "addr:housenumber":"20",
    "addr:postcode":"35500",
    "addr:street":"Calle De Puerto Naos",
    "iso:country":"ES",
    "sg:address":"Calle de Puerto Naos, 20",
    "sg:city":"Arrecife",
    "sg:orig_category":"Pescader\u00cdas (al Por Menor)",
    "sg:phone":"+34 928 80 17 05",
    "sg:postcode":"35500",
    "sg:province":"Las Palmas",
    "wof:name":"Pescaderia San Gines S.c.p.",
    "wof:placetype":"venue"
},
  "geometry": {"coordinates":[-13.541264534,28.9649829865],"type":"Point"}
}