{
  "type": "Feature",
  "properties": {
    "addr:full":"Urb Jardin Este, 12 Sevilla Sevilla 41020",
    "addr:housenumber":"12",
    "addr:postcode":"41020",
    "addr:street":"Urb Jardin Este",
    "iso:country":"ES",
    "sg:address":"Urb Jardin Este, 12",
    "sg:city":"Sevilla",
    "sg:orig_category":"Empresas De Pintura Y Revestimientos",
    "sg:phone":"+34 954 52 36 00",
    "sg:postcode":"41020",
    "sg:province":"Sevilla",
    "wof:name":"Aysur S. L.",
    "wof:placetype":"venue"
},
  "geometry": {"coordinates":[-5.9356870651,37.4206848145],"type":"Point"}
}