{
  "type": "Feature",
  "properties": {
    "iso:country":"ES",
    "sg:address":"Calle de Fuente De Las Colmenas, 12",
    "sg:city":"Galapagar",
    "sg:orig_category":"Caf\u00c9s, Bares, Cervecer\u00cdas",
    "sg:phone":"+34 918 58 43 81",
    "sg:postcode":"28260",
    "sg:province":"Madrid",
    "wof:name":"Fioressen 2000 S.l.",
    "wof:placetype":"venue"
},
  "geometry": {"coordinates":[-4.0001473427,40.571559906],"type":"Point"}
}