{
  "type": "Feature",
  "properties": {
    "addr:full":"Calle de Camino Viejo De Leganes, 90 Madrid Madrid 28025",
    "addr:housenumber":"90",
    "addr:postcode":"madrid;28025",
    "addr:street":"Calle De Camino Viejo De Leganes",
    "iso:country":"ES",
    "sg:address":"Calle de Camino Viejo De Leganes, 90",
    "sg:city":"Madrid",
    "sg:orig_category":"Ropa Para Se\u00d1oras (al Por Menor)",
    "sg:phone":"+34 914 69 65 42",
    "sg:postcode":"28025",
    "sg:province":"Madrid",
    "wof:name":"Lara Feria Josfa",
    "wof:placetype":"venue"
},
  "geometry": {"coordinates":[-3.7280409336,40.3854484558],"type":"Point"}
}