{
  "type": "Feature",
  "properties": {
    "iso:country":"ES",
    "sg:address":"Carr Vicente Boix, 10",
    "sg:city":"Xativa",
    "sg:orig_category":"Cajas De Ahorro",
    "sg:phone":"+34 962 28 72 16",
    "sg:postcode":"46800",
    "sg:province":"Valencia",
    "sg:website":"www.caixaontinyent.es",
    "wof:name":"Caja De Ahorros De Onteniente",
    "wof:placetype":"venue"
},
  "geometry": {"coordinates":[-0.5247690082,38.9905586243],"type":"Point"}
}