{
  "type": "Feature",
  "properties": {
    "addr:full":"Rua Serra Ga\u00d1idoira, 41 Lugo Lugo 27004",
    "addr:housenumber":"41",
    "addr:postcode":"27004",
    "addr:street":"Rua Serra Gan\u0303Idoira",
    "iso:country":"ES",
    "sg:address":"Rua Serra Ga\u00d1idoira, 41",
    "sg:city":"Lugo",
    "sg:orig_category":"Guarder\u00cdas",
    "sg:phone":"+34 982 20 27 67",
    "sg:postcode":"27004",
    "sg:province":"Lugo",
    "wof:name":"Gliemmo Lucasa Mirta Susana",
    "wof:placetype":"venue"
},
  "geometry": {"coordinates":[-7.5687060356,43.0145797729],"type":"Point"}
}