{
  "type": "Feature",
  "properties": {
    "addr:full":"Carrer de Diputacio, 38 Barcelona Barcelona 08015",
    "addr:housenumber":"38",
    "addr:postcode":"08015",
    "addr:street":"Carrer De Diputacio",
    "iso:country":"ES",
    "sg:address":"Carrer de Diputacio, 38",
    "sg:city":"Barcelona",
    "sg:orig_category":"Fabricaci\u00d3n, Importaci\u00d3n De L\u00c1mparas Y Bombillas",
    "sg:phone":"+34 934 25 05 10",
    "sg:postcode":"08015",
    "sg:province":"Barcelona",
    "wof:name":"Royo Gomez Francisco",
    "wof:placetype":"venue"
},
  "geometry": {"coordinates":[2.1515350342,41.3785514832],"type":"Point"}
}