{
  "type": "Feature",
  "properties": {
    "addr:full":"Calle de Nueva, 14 Quesada Ja\u00e9n 23480",
    "addr:housenumber":"14",
    "addr:postcode":"23480",
    "addr:street":"Calle De Nueva",
    "iso:country":"ES",
    "sg:address":"Calle de Nueva, 14",
    "sg:city":"Quesada",
    "sg:orig_category":"Fabricaci\u00d3n De Productos Textiles Sin Tejer",
    "sg:phone":"+34 953 73 30 80",
    "sg:postcode":"23480",
    "sg:province":"Ja\u00e9n",
    "wof:name":"Malo Lopez-roman Emilia",
    "wof:placetype":"venue"
},
  "geometry": {"coordinates":[-3.0681269169,37.8464508057],"type":"Point"}
}