{
  "type": "Feature",
  "properties": {
    "addr:full":"Calle de Ramon Y Cajal, 19 Leganes Madrid 28914",
    "addr:housenumber":"19",
    "addr:postcode":"28914",
    "addr:street":"Calle De Ramon Y Cajal",
    "iso:country":"ES",
    "sg:address":"Calle de Ramon Y Cajal, 19",
    "sg:city":"Leganes",
    "sg:classifiers":[
        {
            "category":"Manufacturing",
            "subcategory":"Metals",
            "type":"Manufacturing & Wholesale Goods"
        }
    ],
    "sg:phone":"+34 916 88 10 00",
    "sg:postcode":"28914",
    "sg:province":"Madrid",
    "sg:tags":[
        "en",
        "fundiciones"
    ],
    "wof:name":"Hermanos Perez Pardo S. L.",
    "wof:placetype":"venue"
},
  "geometry": {"coordinates":[-3.7379450798,40.3299217224],"type":"Point"}
}