{
  "type": "Feature",
  "properties": {
    "iso:country":"ES",
    "sg:address":"Crt Madrid-alicante, Km. 0172,3",
    "sg:city":"El Provencio",
    "sg:orig_category":"Albergues",
    "sg:phone":"+34 967 16 61 67",
    "sg:postcode":"16670",
    "sg:province":"Cuenca",
    "wof:name":"Hosteleros Del Zancara S.l.",
    "wof:placetype":"venue"
},
  "geometry": {"coordinates":[-2.5704939365,39.3758201599],"type":"Point"}
}