{
  "type": "Feature",
  "properties": {
    "iso:country":"ES",
    "sg:address":"Calle de Caridad (la), 1",
    "sg:city":"Cazalla Sierra",
    "sg:orig_category":"Fisioterapia",
    "sg:phone":"+34 954 88 32 32",
    "sg:postcode":"41370",
    "sg:province":"Sevilla",
    "wof:name":"Cornello Perez Calderon Maria Del Pilar",
    "wof:placetype":"venue"
},
  "geometry": {"coordinates":[-5.7595319748,37.9320373535],"type":"Point"}
}