{
  "type": "Feature",
  "properties": {
    "iso:country":"ES",
    "sg:address":"Ctra Moraira-calpe, 298",
    "sg:city":"Teulada",
    "sg:orig_category":"Agencias Y Asesores De Publicidad",
    "sg:phone":"+34 965 74 77 66",
    "sg:postcode":"03725",
    "sg:province":"Alicante",
    "wof:name":"Anomvillas Espania S.l.",
    "wof:placetype":"venue"
},
  "geometry": {"coordinates":[0.1223276034,38.6830863953],"type":"Point"}
}