{
  "type": "Feature",
  "properties": {
    "iso:country":"ES",
    "sg:address":"Calle de Perez Galdos, 12",
    "sg:city":"Fuentes Ebro",
    "sg:orig_category":"Delegados, Agentes De Tr\u00c1nsito, Auxiliares De Transporte Internacional",
    "sg:phone":"+34 976 16 00 88",
    "sg:postcode":"50740",
    "sg:province":"Zaragoza",
    "wof:name":"Soro Novallas Pablo",
    "wof:placetype":"venue"
},
  "geometry": {"coordinates":[-0.626873374,41.5133781433],"type":"Point"}
}