{
  "type": "Feature",
  "properties": {
    "addr:full":"Pla\u00c7 Mercat (del), 14 Algemesi Valencia 46680",
    "addr:postcode":"46680",
    "iso:country":"ES",
    "sg:address":"Pla\u00c7 Mercat (del), 14",
    "sg:city":"Algemesi",
    "sg:orig_category":"Bancos",
    "sg:phone":"+34 962 48 80 03",
    "sg:postcode":"46680",
    "sg:province":"Valencia",
    "wof:name":"Banco Espa\u00f1ol De Credito S.a.",
    "wof:placetype":"venue"
},
  "geometry": {"coordinates":[-0.4383490086,39.1962852478],"type":"Point"}
}