{
  "type": "Feature",
  "properties": {
    "addr:full":"Calle de San Pablo, S/n Argamasilla Calatrava Ciudad Real 13440",
    "addr:housenumber":"s / n",
    "addr:postcode":"13440",
    "addr:street":"Calle De San Pablo",
    "iso:country":"ES",
    "sg:address":"Calle de San Pablo, S/n",
    "sg:city":"Argamasilla Calatrava",
    "sg:orig_category":"Panader\u00cdas, Pasteler\u00cdas, Boller\u00cda Industriale (fabricaci\u00d3n, Al Por Mayor)",
    "sg:phone":"+34 926 47 72 52",
    "sg:postcode":"13440",
    "sg:province":"Ciudad Real",
    "wof:name":"Gomez Sanchez Manuel",
    "wof:placetype":"venue"
},
  "geometry": {"coordinates":[-4.0746688843,38.727268219],"type":"Point"}
}