{
  "type": "Feature",
  "properties": {
    "iso:country":"ES",
    "sg:address":"Carrer de Divina Pastora, 13",
    "sg:city":"Manresa",
    "sg:orig_category":"Edici\u00d3n De Diarios, Revistas, Boletines",
    "sg:phone":"+34 938 73 74 73",
    "sg:postcode":"08241",
    "sg:province":"Barcelona",
    "wof:name":"Garriga Molina Juan",
    "wof:placetype":"venue"
},
  "geometry": {"coordinates":[1.835021019,41.721950531],"type":"Point"}
}