{
  "type": "Feature",
  "properties": {
    "addr:full":"Calle de Miguel De Cervantes (de), 6 El Cruce Madrid 28860",
    "addr:postcode":"28860",
    "addr:street":"Calle De Miguel De Cervantes De 6",
    "iso:country":"ES",
    "sg:address":"Calle de Miguel De Cervantes (de), 6",
    "sg:city":"El Cruce",
    "sg:orig_category":"Electrodom\u00c9sticos (fabricaci\u00d3n, Al Por Mayor)",
    "sg:phone":"+34 916 58 14 44",
    "sg:postcode":"28860",
    "sg:province":"Madrid",
    "wof:name":"Electroparacuellos S.l.",
    "wof:placetype":"venue"
},
  "geometry": {"coordinates":[-3.5493650436,40.499912262],"type":"Point"}
}