{
  "type": "Feature",
  "properties": {
    "addr:full":"Carrer de Moli Del Llobet, 2 Vic Barcelona 08500",
    "addr:housenumber":"2",
    "addr:postcode":"08500",
    "addr:street":"Carrer De Moli Del Llobet",
    "iso:country":"ES",
    "sg:address":"Carrer de Moli Del Llobet, 2",
    "sg:city":"Vic",
    "sg:orig_category":"Limpieza Industrial",
    "sg:phone":"+34 938 89 30 49",
    "sg:postcode":"08500",
    "sg:province":"Barcelona",
    "wof:name":"Tinura Pel S.a.",
    "wof:placetype":"venue"
},
  "geometry": {"coordinates":[2.2799670696,41.9480819702],"type":"Point"}
}