{
  "type": "Feature",
  "properties": {
    "iso:country":"ES",
    "sg:address":"Calle de Independencia, 10",
    "sg:city":"Oviedo",
    "sg:orig_category":"Marroquiner\u00cda (confecci\u00d3n)",
    "sg:phone":"+34 985 25 06 08",
    "sg:postcode":"33004",
    "sg:province":"Asturias",
    "wof:name":"Rey Pantin Maria Bego\u00f1a Julia Del",
    "wof:placetype":"venue"
},
  "geometry": {"coordinates":[-5.8545079231,43.3649368286],"type":"Point"}
}