{
  "type": "Feature",
  "properties": {
    "iso:country":"ES",
    "sg:address":"Carr Cecili Metel, 12",
    "sg:city":"Pollen\u00e7a",
    "sg:orig_category":"Papeler\u00cdas, Librer\u00cdas",
    "sg:phone":"+34 971 53 15 39",
    "sg:postcode":"07460",
    "sg:province":"Islas Baleares",
    "wof:name":"Dominguez Medina Maria De Los Dolores",
    "wof:placetype":"venue"
},
  "geometry": {"coordinates":[3.0208649635,39.8767280579],"type":"Point"}
}