{
  "type": "Feature",
  "properties": {
    "addr:full":"Egileor, 101 Altzo Guip\u00f9zcoa 20268",
    "addr:housenumber":"101",
    "addr:postcode":"20268",
    "addr:street":"Egileor;Guipu\u0300Zcoa",
    "iso:country":"ES",
    "sg:address":"Egileor, 101",
    "sg:city":"Altzo",
    "sg:orig_category":"Arenas, Guijarros Y Granulados",
    "sg:phone":"+34 943 65 18 99",
    "sg:postcode":"20268",
    "sg:province":"Guip\u00f9zcoa",
    "sg:website":"www.calcinor.com",
    "wof:name":"Canteras De Tolosa S. A.",
    "wof:placetype":"venue"
},
  "geometry": {"coordinates":[-2.085203886,43.0452766418],"type":"Point"}
}