{
  "type": "Feature",
  "properties": {
    "addr:full":"Calle de Burgos, 2 Palencia Palencia 34001",
    "addr:housenumber":"2",
    "addr:postcode":"34001",
    "addr:street":"Calle De Burgos",
    "iso:country":"ES",
    "sg:address":"Calle de Burgos, 2",
    "sg:city":"Palencia",
    "sg:orig_category":"Quincaller\u00cda (al Por Menor)",
    "sg:phone":"+34 979 74 04 16",
    "sg:postcode":"34001",
    "sg:province":"Palencia",
    "wof:name":"Silva Conde Jose",
    "wof:placetype":"venue"
},
  "geometry": {"coordinates":[-4.5313749313,42.0096855164],"type":"Point"}
}