{
  "type": "Feature",
  "properties": {
    "iso:country":"ES",
    "sg:address":"Avda Club Deportivo, 28",
    "sg:city":"Logro\u00f1o",
    "sg:orig_category":"Loter\u00cda Y T\u00d3mbola",
    "sg:phone":"+34 941 20 34 99",
    "sg:postcode":"26007",
    "sg:province":"La Rioja",
    "wof:name":"Ruiz Ortega Jorge",
    "wof:placetype":"venue"
},
  "geometry": {"coordinates":[-2.4537320137,42.4569473267],"type":"Point"}
}