{
  "type": "Feature",
  "properties": {
    "iso:country":"ES",
    "sg:address":"Av Paisos Catalans, 162",
    "sg:city":"Reus",
    "sg:orig_category":"Venta, Instalaci\u00d3n De Calefacci\u00d3n",
    "sg:phone":"+34 977 32 70 90",
    "sg:postcode":"43205",
    "sg:province":"Tarragona",
    "wof:name":"Canalizaciones Instalaciones Y Servicios",
    "wof:placetype":"venue"
},
  "geometry": {"coordinates":[1.0988789797,41.1482276917],"type":"Point"}
}