{
  "type": "Feature",
  "properties": {
    "iso:country":"ES",
    "sg:address":"Calle de Carretera De Carmona, 46",
    "sg:city":"Sevilla",
    "sg:orig_category":"Garajes De Veh\u00cdculos",
    "sg:phone":"+34 954 41 07 54",
    "sg:postcode":"41008",
    "sg:province":"Sevilla",
    "wof:name":"Amortiguadores Saavedra S.l",
    "wof:placetype":"venue"
},
  "geometry": {"coordinates":[-5.8550591469,37.4141998291],"type":"Point"}
}