{
  "type": "Feature",
  "properties": {
    "iso:country":"ES",
    "sg:address":"San Roque, S/n",
    "sg:city":"Tazones",
    "sg:orig_category":"Transportes Por Carretera: Lotes Completos, Mercanc\u00cdas Diversas",
    "sg:phone":"+34 985 89 70 42",
    "sg:postcode":"33315",
    "sg:province":"Asturias",
    "wof:name":"Vi\u00f1es Barro Arturo",
    "wof:placetype":"venue"
},
  "geometry": {"coordinates":[-5.4010324478,43.5453987122],"type":"Point"}
}