{
  "type": "Feature",
  "properties": {
    "iso:country":"ES",
    "sg:address":"Av. Bayona, 26",
    "sg:city":"Iru\u00f1a",
    "sg:orig_category":"Cajas De Ahorro",
    "sg:phone":"+34 948 26 13 50",
    "sg:postcode":"31011",
    "sg:province":"Navarra",
    "sg:website":"www.cajalaboral.com",
    "wof:name":"Caja Laboral Popular",
    "wof:placetype":"venue"
},
  "geometry": {"coordinates":[-1.6583570242,42.814868927],"type":"Point"}
}