{
  "type": "Feature",
  "properties": {
    "iso:country":"ES",
    "sg:address":"Avda Reyes Catolicos, 8",
    "sg:city":"Melilla",
    "sg:orig_category":"Papel (al Por Mayor)",
    "sg:phone":"+34 952 68 41 11",
    "sg:postcode":"52002",
    "sg:province":"Melilla",
    "wof:name":"Casta\u00f1eda Fernandez Carlos",
    "wof:placetype":"venue"
},
  "geometry": {"coordinates":[-2.9427330494,35.2937583923],"type":"Point"}
}