{
  "type": "Feature",
  "properties": {
    "addr:full":"Calle de Doctor Mara\u00d1on Del, 5 Aviles Asturias 33402",
    "addr:housenumber":"5",
    "addr:postcode":"33402",
    "addr:street":"Calle De Doctor Maran\u0303On Del",
    "iso:country":"ES",
    "sg:address":"Calle de Doctor Mara\u00d1on Del, 5",
    "sg:city":"Aviles",
    "sg:orig_category":"Ense\u00d1anza Variada",
    "sg:phone":"+34 985 55 17 97",
    "sg:postcode":"33402",
    "sg:province":"Asturias",
    "wof:name":"Barrientos Chamorro Pablo",
    "wof:placetype":"venue"
},
  "geometry": {"coordinates":[-5.9286441803,43.5524139404],"type":"Point"}
}