{
  "type": "Feature",
  "properties": {
    "iso:country":"ES",
    "sg:address":"Calle de Juan Mari Altuna Kalea, 12",
    "sg:city":"Durango",
    "sg:orig_category":"Ense\u00d1anza Variada",
    "sg:phone":"+34 946 03 21 58",
    "sg:postcode":"48200",
    "sg:province":"Vizcaya",
    "wof:name":"I\u00f1aki Arrizabalaga Vicandi - Centro De Estudios Ikasi",
    "wof:placetype":"venue"
},
  "geometry": {"coordinates":[-2.6280651093,43.1682891846],"type":"Point"}
}