{
  "type": "Feature",
  "properties": {
    "addr:full":"Ctra. Madrid-toledo, Km. 0025,0 Torrejon Calzada Madrid 28991",
    "addr:postcode":"28991",
    "addr:street":"Ctra. Madrid-Toledo Km. 0025,0;Calzada",
    "iso:country":"ES",
    "sg:address":"Ctra. Madrid-toledo, Km. 0025,0",
    "sg:city":"Torrejon Calzada",
    "sg:orig_category":"Colchones (fabricaci\u00d3n, Al Por Mayor, Al Por Menor)",
    "sg:phone":"+34 918 16 95 48",
    "sg:postcode":"28991",
    "sg:province":"Madrid",
    "wof:name":"Sagu Servicios De Intermediacion S.l.",
    "wof:placetype":"venue"
},
  "geometry": {"coordinates":[-3.8016889095,40.2015762329],"type":"Point"}
}