{
  "type": "Feature",
  "properties": {
    "iso:country":"ES",
    "sg:address":"Plaz Espa\u00d1a, 13",
    "sg:city":"Novelda",
    "sg:orig_category":"Bancos",
    "sg:phone":"+34 965 60 24 04",
    "sg:postcode":"03660",
    "sg:province":"Alicante",
    "wof:name":"Deutsche Bank S.a.e.",
    "wof:placetype":"venue"
},
  "geometry": {"coordinates":[-0.7651429772,38.3858032227],"type":"Point"}
}