{
  "type": "Feature",
  "properties": {
    "iso:country":"ES",
    "sg:address":"Rua Rosalia De Castro, 10",
    "sg:city":"Pobra Trives",
    "sg:orig_category":"Supermercados Y Hipermercados",
    "sg:phone":"+34 988 33 07 26",
    "sg:postcode":"32780",
    "sg:province":"Ourense",
    "wof:name":"Juan Miguel Dieguez Rivas S.l.",
    "wof:placetype":"venue"
},
  "geometry": {"coordinates":[-7.2517571449,42.3405303955],"type":"Point"}
}