{
  "type": "Feature",
  "properties": {
    "iso:country":"ES",
    "sg:address":"Carrer de Vallvera (de La), 6",
    "sg:city":"Valls",
    "sg:orig_category":"Enfermeras: Consultas, Atenci\u00d3n A Domicilio",
    "sg:phone":"+34 977 60 64 83",
    "sg:postcode":"43800",
    "sg:province":"Tarragona",
    "wof:name":"Marti Sendra Esther",
    "wof:placetype":"venue"
},
  "geometry": {"coordinates":[1.2557640076,41.2897644043],"type":"Point"}
}