{
  "type": "Feature",
  "properties": {
    "iso:country":"ES",
    "sg:address":"Luga Poligon 4, S/n",
    "sg:city":"Alaro",
    "sg:orig_category":"Negocio De Materiales De Construcci\u00d3n",
    "sg:phone":"+34 971 51 04 93",
    "sg:postcode":"07340",
    "sg:province":"Islas Baleares",
    "wof:name":"Simonet Borras Pablo",
    "wof:placetype":"venue"
},
  "geometry": {"coordinates":[2.7968831062,39.7017936707],"type":"Point"}
}