{
  "type": "Feature",
  "properties": {
    "iso:country":"ES",
    "sg:address":"Sabaters(pol Industrial), S/n",
    "sg:city":"Valls",
    "sg:orig_category":"Electricidad Veh\u00cdculo",
    "sg:phone":"+34 977 60 00 61",
    "sg:postcode":"43800",
    "sg:province":"Tarragona",
    "wof:name":"Electro-auto Santos C.b.",
    "wof:placetype":"venue"
},
  "geometry": {"coordinates":[1.2665400505,41.3135185242],"type":"Point"}
}