{
  "type": "Feature",
  "properties": {
    "iso:country":"ES",
    "sg:address":"Calle de San Lamberto (miralbueno), 99",
    "sg:city":"Zaragoza",
    "sg:orig_category":"Bebidas",
    "sg:phone":"+34 976 34 26 59",
    "sg:postcode":"50011",
    "sg:province":"Zaragoza",
    "wof:name":"Schweppes S.a.",
    "wof:placetype":"venue"
},
  "geometry": {"coordinates":[-0.9309390187,41.655960083],"type":"Point"}
}