{
  "type": "Feature",
  "properties": {
    "addr:full":"Calle de Puntilleros, 56 Sevilla Sevilla 41007",
    "addr:housenumber":"56",
    "addr:postcode":"41007",
    "addr:street":"Calle De Puntilleros",
    "iso:country":"ES",
    "sg:address":"Calle de Puntilleros, 56",
    "sg:city":"Sevilla",
    "sg:orig_category":"Pescader\u00cdas (al Por Menor)",
    "sg:phone":"+34 954 51 93 69",
    "sg:postcode":"41007",
    "sg:province":"Sevilla",
    "wof:name":"Misa Sanchez Francisco",
    "wof:placetype":"venue"
},
  "geometry": {"coordinates":[-5.9594540596,37.3983688354],"type":"Point"}
}