{
  "type": "Feature",
  "properties": {
    "addr:full":"Carrer de Sant Lloren\u00c7, 36 Galera Tarragona 43515",
    "addr:housenumber":"36",
    "addr:postcode":"43515",
    "addr:street":"Carrer De Sant Llorenc\u0327",
    "iso:country":"ES",
    "sg:address":"Carrer de Sant Lloren\u00c7, 36",
    "sg:city":"Galera",
    "sg:orig_category":"Administraciones Regionales, Departamentales Y Locales",
    "sg:phone":"+34 977 71 83 39",
    "sg:postcode":"43515",
    "sg:province":"Tarragona",
    "wof:name":"Ajuntament De La Galera",
    "wof:placetype":"venue"
},
  "geometry": {"coordinates":[0.463568598,40.681602478],"type":"Point"}
}