{
  "type": "Feature",
  "properties": {
    "iso:country":"ES",
    "sg:address":"Carrer de Josep Cuxart, 25",
    "sg:city":"Cornella Llobregat",
    "sg:orig_category":"Peluqueros: De Se\u00d1oras",
    "sg:phone":"+34 933 77 80 57",
    "sg:postcode":"08940",
    "sg:province":"Barcelona",
    "wof:name":"Lopez Gatell Concepcion",
    "wof:placetype":"venue"
},
  "geometry": {"coordinates":[2.0730729103,41.3554725647],"type":"Point"}
}