{
  "type": "Feature",
  "properties": {
    "iso:country":"ES",
    "sg:address":"Calle de Grabador Esteve, 33",
    "sg:city":"Valencia",
    "sg:orig_category":"Abogados",
    "sg:phone":"+34 963 73 08 29",
    "sg:postcode":"46004",
    "sg:province":"Valencia",
    "wof:name":"Bernat Iba\u00f1ez Cristina",
    "wof:placetype":"venue"
},
  "geometry": {"coordinates":[-0.3660440147,39.4690513611],"type":"Point"}
}