{
  "type": "Feature",
  "properties": {
    "addr:full":"Calle de Huerta, 7 Puebla Del Rio Sevilla 41130",
    "addr:housenumber":"7",
    "addr:postcode":"41130",
    "addr:street":"Calle De Huerta",
    "iso:country":"ES",
    "sg:address":"Calle de Huerta, 7",
    "sg:city":"Puebla Del Rio",
    "sg:orig_category":"Caf\u00c9s, Bares, Cervecer\u00cdas",
    "sg:phone":"+34 955 77 17 90",
    "sg:postcode":"41130",
    "sg:province":"Sevilla",
    "wof:name":"Gonzalez Gonzalez Antonio",
    "wof:placetype":"venue"
},
  "geometry": {"coordinates":[-6.0617499352,37.2655944824],"type":"Point"}
}