{
  "type": "Feature",
  "properties": {
    "addr:full":"Carrer de Mallorca, 447 Barcelona Barcelona 08013",
    "addr:housenumber":"447",
    "addr:postcode":"08013",
    "addr:street":"Carrer De Mallorca",
    "iso:country":"ES",
    "sg:address":"Carrer de Mallorca, 447",
    "sg:city":"Barcelona",
    "sg:orig_category":"Marroquiner\u00cda Y Art\u00cdculos De Viaje (al Por Menor)",
    "sg:phone":"+34 934 56 14 47",
    "sg:postcode":"08013",
    "sg:province":"Barcelona",
    "wof:name":"Bernabe Aguirre Antonio",
    "wof:placetype":"venue"
},
  "geometry": {"coordinates":[2.1781189442,41.405708313],"type":"Point"}
}