{
  "type": "Feature",
  "properties": {
    "addr:full":"Calle de Vicente Lleo, 21 Valencia Valencia 46006",
    "addr:housenumber":"21",
    "addr:postcode":"46006",
    "addr:street":"Calle De Vicente Lleo",
    "iso:country":"ES",
    "sg:address":"Calle de Vicente Lleo, 21",
    "sg:city":"Valencia",
    "sg:orig_category":"Cerrajer\u00cda, Ferrallista",
    "sg:phone":"+34 963 95 39 36",
    "sg:postcode":"46006",
    "sg:province":"Valencia",
    "wof:name":"Perez Luciano Salvador",
    "wof:placetype":"venue"
},
  "geometry": {"coordinates":[-0.3704789877,39.4581832886],"type":"Point"}
}