{
  "type": "Feature",
  "properties": {
    "addr:full":"Pase Andrade, 22 Alca\u00f1iz Teruel 44600",
    "addr:housenumber":"22",
    "addr:postcode":"44600",
    "addr:street":"Andrade",
    "iso:country":"ES",
    "sg:address":"Pase Andrade, 22",
    "sg:city":"Alca\u00f1iz",
    "sg:orig_category":"Almacenes Frigor\u00cdficos",
    "sg:phone":"+34 978 83 09 29",
    "sg:postcode":"44600",
    "sg:province":"Teruel",
    "wof:name":"Frigorificos Velilla S.l.",
    "wof:placetype":"venue"
},
  "geometry": {"coordinates":[-0.1333030015,41.0548439026],"type":"Point"}
}