{
  "type": "Feature",
  "properties": {
    "iso:country":"ES",
    "sg:address":"Calle de Villegas Marmolejo, 3",
    "sg:city":"Sevilla",
    "sg:orig_category":"Peluqueros: De Se\u00d1oras",
    "sg:phone":"+34 954 65 44 44",
    "sg:postcode":"41005",
    "sg:province":"Sevilla",
    "wof:name":"Lopez Morales Eusebio Jaime",
    "wof:placetype":"venue"
},
  "geometry": {"coordinates":[-5.9723267555,37.3770484924],"type":"Point"}
}