{
  "type": "Feature",
  "properties": {
    "iso:country":"ES",
    "sg:address":"Ctra Logro\u00d1o (miravegas), Km. 0026,0",
    "sg:city":"Alagon",
    "sg:orig_category":"Chapister\u00cda",
    "sg:phone":"+34 976 61 07 31",
    "sg:postcode":"50630",
    "sg:province":"Zaragoza",
    "wof:name":"Comenge Torrecillas Eduardo",
    "wof:placetype":"venue"
},
  "geometry": {"coordinates":[-1.1267240047,41.768196106],"type":"Point"}
}