{
  "type": "Feature",
  "properties": {
    "addr:full":"Calle de Jesus De La Vera-cruz, 10 Sevilla Sevilla 41002",
    "addr:housenumber":"10",
    "addr:postcode":"41002",
    "addr:street":"Calle De Jesus De La Vera-Cruz",
    "iso:country":"ES",
    "sg:address":"Calle de Jesus De La Vera-cruz, 10",
    "sg:city":"Sevilla",
    "sg:orig_category":"Alquiler De Casas Y Habitaciones Amuebladas",
    "sg:phone":"+34 954 21 73 01",
    "sg:postcode":"41002",
    "sg:province":"Sevilla",
    "wof:name":"Comunidad En Jesus De La Vera Cruz 10 Congregacion R Maria Inmaculada Servicio Domestico",
    "wof:placetype":"venue"
},
  "geometry": {"coordinates":[-5.9958600998,37.3943061829],"type":"Point"}
}