{
  "type": "Feature",
  "properties": {
    "addr:full":"Calle de Braos (los), 10 Santa Maria Del Paramo Le\u00f3n 24240",
    "addr:housenumber":"10",
    "addr:postcode":"24240",
    "addr:street":"Calle De Braos Los",
    "iso:country":"ES",
    "sg:address":"Calle de Braos (los), 10",
    "sg:city":"Santa Maria Del Paramo",
    "sg:orig_category":"Madera Para Construcci\u00d3n E Industria",
    "sg:phone":"+34 987 36 00 17",
    "sg:postcode":"24240",
    "sg:province":"Le\u00f3n",
    "sg:website":"www.paginasamarillas.es",
    "wof:name":"Parquet Roberto Fierro S.l.",
    "wof:placetype":"venue"
},
  "geometry": {"coordinates":[-5.7443089485,42.3558197021],"type":"Point"}
}