{
  "type": "Feature",
  "properties": {
    "iso:country":"ES",
    "sg:address":"Avgd Bac De Roda, 24",
    "sg:city":"Badalona",
    "sg:orig_category":"Contenedores Para Transporte De Mercanc\u00cdas",
    "sg:phone":"+34 933 97 27 11",
    "sg:postcode":"08915",
    "sg:province":"Barcelona",
    "wof:name":"Containers Barcelona S. A.",
    "wof:placetype":"venue"
},
  "geometry": {"coordinates":[2.2487740517,41.4631538391],"type":"Point"}
}