{
  "type": "Feature",
  "properties": {
    "iso:country":"ES",
    "sg:address":"Calle de Alcaracejos, 16",
    "sg:city":"Pozoblanco",
    "sg:orig_category":"Bordado, Marcado A Medida",
    "sg:phone":"+34 957 13 02 80",
    "sg:postcode":"14400",
    "sg:province":"C\u00f3rdoba",
    "wof:name":"Salantai S.l.",
    "wof:placetype":"venue"
},
  "geometry": {"coordinates":[-4.862019062,38.3792724609],"type":"Point"}
}