{
  "type": "Feature",
  "properties": {
    "addr:full":"Cami Senabre, S/n Muro Alcoy Alicante 03830",
    "addr:postcode":"03830",
    "addr:street":"Senabre S / N Muro",
    "iso:country":"ES",
    "sg:address":"Cami Senabre, S/n",
    "sg:city":"Muro Alcoy",
    "sg:orig_category":"Cintas, Balduques Y Cierres De Tela (fabricaci\u00d3n, Al Por Mayor)",
    "sg:phone":"+34 965 53 22 25",
    "sg:postcode":"03830",
    "sg:province":"Alicante",
    "wof:name":"Modelpunt S.l.",
    "wof:placetype":"venue"
},
  "geometry": {"coordinates":[-0.4429390132,38.7853317261],"type":"Point"}
}