{
  "type": "Feature",
  "properties": {
    "iso:country":"ES",
    "sg:address":"Cascalla(valterna), 3",
    "sg:city":"Paterna",
    "sg:orig_category":"Inmobiliaria (agencias)",
    "sg:phone":"+34 961 35 67 07",
    "sg:postcode":"46980",
    "sg:province":"Valencia",
    "wof:name":"Bchbanif Fondo Inmobiliario F.i.i.",
    "wof:placetype":"venue"
},
  "geometry": {"coordinates":[-0.4305689931,39.511920929],"type":"Point"}
}