{
  "type": "Feature",
  "properties": {
    "iso:country":"ES",
    "sg:address":"C/ Music Gon\u00c7al Blanes, 2",
    "sg:city":"Alcoi",
    "sg:orig_category":"Molduras, Junquillos, Listones Y Molduras Perforadas",
    "sg:phone":"+34 965 54 81 86",
    "sg:postcode":"03801",
    "sg:province":"Alicante",
    "wof:name":"Macher Llorens Jesus",
    "wof:placetype":"venue"
},
  "geometry": {"coordinates":[-0.4752782881,38.690788269],"type":"Point"}
}