{
  "type": "Feature",
  "properties": {
    "iso:country":"ES",
    "sg:address":"Calle de Alfonso Gomez, 4",
    "sg:city":"Madrid",
    "sg:orig_category":"Fabricaci\u00d3n De Juguetes Autom\u00c1ticos",
    "sg:phone":"+34 914 40 92 49",
    "sg:postcode":"28...",
    "sg:province":"Madrid",
    "sg:website":"www.rfranco.com",
    "wof:name":"Recreativos Franco S.a.",
    "wof:placetype":"venue"
},
  "geometry": {"coordinates":[-3.6297473907,40.4396018982],"type":"Point"}
}