{
  "type": "Feature",
  "properties": {
    "iso:country":"ES",
    "sg:address":"Calle de Atlantico, 7",
    "sg:city":"Ajalvir",
    "sg:orig_category":"Fabricaci\u00d3n De Cervezas",
    "sg:phone":"+34 918 84 31 01",
    "sg:postcode":"28864",
    "sg:province":"Madrid",
    "wof:name":"Marcos Alvarez Amable",
    "wof:placetype":"venue"
},
  "geometry": {"coordinates":[-3.4824626446,40.5281486511],"type":"Point"}
}