{
  "type": "Feature",
  "properties": {
    "addr:full":"Po. Ind Corts, 19 Cabrera Mar Barcelona 08349",
    "addr:housenumber":"19",
    "addr:postcode":"08349",
    "addr:street":"Corts",
    "iso:country":"ES",
    "sg:address":"Po. Ind Corts, 19",
    "sg:city":"Cabrera Mar",
    "sg:orig_category":"Centros Empresariales",
    "sg:phone":"+34 937 56 60 83",
    "sg:postcode":"08349",
    "sg:province":"Barcelona",
    "wof:name":"Cami Del Mig 118 Sl",
    "wof:placetype":"venue"
},
  "geometry": {"coordinates":[2.3933050632,41.5273513794],"type":"Point"}
}