{
  "type": "Feature",
  "properties": {
    "addr:full":"Cra. Granollers-gerona, Km. 0005,5 Cardedeu Barcelona 08440",
    "addr:postcode":"08440",
    "addr:street":"Km. 0005,5",
    "iso:country":"ES",
    "sg:address":"Cra. Granollers-gerona, Km. 0005,5",
    "sg:city":"Cardedeu",
    "sg:orig_category":"Instalaci\u00d3n, Reparaci\u00d3n De Calefacci\u00d3n Por Gas",
    "sg:phone":"+34 938 46 11 45",
    "sg:postcode":"08440",
    "sg:province":"Barcelona",
    "wof:name":"Isant Sala Ramon",
    "wof:placetype":"venue"
},
  "geometry": {"coordinates":[2.3567531109,41.6367912292],"type":"Point"}
}