{
  "type": "Feature",
  "properties": {
    "addr:full":"Calle de Batalla De Brunete, 22 Fuenlabrada Madrid 28946",
    "addr:housenumber":"22",
    "addr:postcode":"28946",
    "addr:street":"Calle De Batalla De Brunete",
    "iso:country":"ES",
    "sg:address":"Calle de Batalla De Brunete, 22",
    "sg:city":"Fuenlabrada",
    "sg:orig_category":"Cerrajer\u00cda, Ferrallista",
    "sg:phone":"+34 916 06 03 50",
    "sg:postcode":"28946",
    "sg:province":"Madrid",
    "wof:name":"Vazquez Gonzalez Miguel",
    "wof:placetype":"venue"
},
  "geometry": {"coordinates":[-3.7817099094,40.2820320129],"type":"Point"}
}