{
  "type": "Feature",
  "properties": {
    "addr:full":"Teixidon(mira), 15 Zas La Coru\u00f1a 15850",
    "addr:housenumber":"15",
    "addr:postcode":"15850",
    "addr:street":"Mira;La Corun\u0303A",
    "iso:country":"ES",
    "sg:address":"Teixidon(mira), 15",
    "sg:city":"Zas",
    "sg:orig_category":"Empresarios",
    "sg:phone":"+34 981 75 14 14",
    "sg:postcode":"15850",
    "sg:province":"La Coru\u00f1a",
    "wof:name":"Blanco Rial Jose",
    "wof:placetype":"venue"
},
  "geometry": {"coordinates":[-8.9398441315,43.1045036316],"type":"Point"}
}