{
  "type": "Feature",
  "properties": {
    "iso:country":"ES",
    "sg:address":"Calle de Hilarion Eslava, 29",
    "sg:city":"Madrid",
    "sg:orig_category":"Camiser\u00cda Y Ropa Interior Masculina (al Por Menor)",
    "sg:phone":"+34 915 49 30 52",
    "sg:postcode":"28015",
    "sg:province":"Madrid",
    "wof:name":"La Caprichosa S.l.",
    "wof:placetype":"venue"
},
  "geometry": {"coordinates":[-3.7166726589,40.4351921082],"type":"Point"}
}