{
  "type": "Feature",
  "properties": {
    "addr:full":"Calle de Jesus Maria Ordo\u00d1o, 11 Burgos Burgos 09004",
    "addr:housenumber":"11",
    "addr:postcode":"09004",
    "addr:street":"Calle De Jesus;Ordon\u0303O",
    "iso:country":"ES",
    "sg:address":"Calle de Jesus Maria Ordo\u00d1o, 11",
    "sg:city":"Burgos",
    "sg:orig_category":"Electromec\u00c1nica",
    "sg:phone":"+34 947 25 01 19",
    "sg:postcode":"09004",
    "sg:province":"Burgos",
    "wof:name":"Talleres Burgos Motor S.l.",
    "wof:placetype":"venue"
},
  "geometry": {"coordinates":[-3.6868999004,42.3445625305],"type":"Point"}
}