{
  "type": "Feature",
  "properties": {
    "addr:full":"Entrevias, 4 Calzada Molinos Palencia 34129",
    "addr:housenumber":"4",
    "addr:postcode":"34129",
    "addr:street":"Entrevias;Molinos",
    "iso:country":"ES",
    "sg:address":"Entrevias, 4",
    "sg:city":"Calzada Molinos",
    "sg:orig_category":"Mec\u00c1nico Del Autom\u00d3vil",
    "sg:phone":"+34 979 88 56 24",
    "sg:postcode":"34129",
    "sg:province":"Palencia",
    "wof:name":"Acero Asenjo Gustavo",
    "wof:placetype":"venue"
},
  "geometry": {"coordinates":[-4.5311746597,42.0124588013],"type":"Point"}
}