{
  "type": "Feature",
  "properties": {
    "iso:country":"ES",
    "sg:address":"Avda Benicasim, 42",
    "sg:city":"Castellon",
    "sg:orig_category":"Molduras, Junquillos, Listones Y Molduras Perforadas",
    "sg:phone":"+34 964 21 70 89",
    "sg:postcode":"12004",
    "sg:province":"Castell\u00f3n",
    "wof:name":"Ferrando Alarcon Jose Antonio",
    "wof:placetype":"venue"
},
  "geometry": {"coordinates":[-0.0406389982,40.0005340576],"type":"Point"}
}