{
  "type": "Feature",
  "properties": {
    "addr:full":"Calle de Alcala, 420 Madrid Madrid 28027",
    "addr:housenumber":"420",
    "addr:postcode":"28027",
    "addr:street":"Calle De Alcala",
    "iso:country":"ES",
    "sg:address":"Calle de Alcala, 420",
    "sg:city":"Madrid",
    "sg:orig_category":"Caf\u00c9s, Bares, Cervecer\u00cdas",
    "sg:phone":"+34 917 42 73 33",
    "sg:postcode":"28027",
    "sg:province":"Madrid",
    "wof:name":"Garil Lopez Eduardo",
    "wof:placetype":"venue"
},
  "geometry": {"coordinates":[-3.6374013424,40.4380264282],"type":"Point"}
}