{
  "type": "Feature",
  "properties": {
    "iso:country":"ES",
    "sg:address":"Calle de Mariposa, 11",
    "sg:city":"Humera-somosaguas-prado Del Rey",
    "sg:orig_category":"Inmobiliaria (agencias)",
    "sg:phone":"+34 913 51 49 31",
    "sg:postcode":"28223",
    "sg:province":"Madrid",
    "wof:name":"Maquevi S.a.",
    "wof:placetype":"venue"
},
  "geometry": {"coordinates":[-3.7877600193,40.419719696],"type":"Point"}
}