{
  "type": "Feature",
  "properties": {
    "addr:full":"Calle de Lerida, 30 Valencia Valencia 46009",
    "addr:housenumber":"30",
    "addr:postcode":"46009",
    "addr:street":"Calle De Lerida",
    "iso:country":"ES",
    "sg:address":"Calle de Lerida, 30",
    "sg:city":"Valencia",
    "sg:orig_category":"Droguer\u00cdas (al Por Menor)",
    "sg:phone":"+34 963 47 07 75",
    "sg:postcode":"46009",
    "sg:province":"Valencia",
    "wof:name":"Ferrando Baguena Francisco",
    "wof:placetype":"venue"
},
  "geometry": {"coordinates":[-0.3785519898,39.4839820862],"type":"Point"}
}