{
  "type": "Feature",
  "properties": {
    "addr:full":"Plaza Alta Y Baja, 20 Lucena C\u00f3rdoba 14900",
    "addr:housenumber":"20",
    "addr:postcode":"14900",
    "addr:street":"Baja",
    "iso:country":"ES",
    "sg:address":"Plaza Alta Y Baja, 20",
    "sg:city":"Lucena",
    "sg:orig_category":"Electricidad: Instaladores",
    "sg:phone":"+34 957 50 07 76",
    "sg:postcode":"14900",
    "sg:province":"C\u00f3rdoba",
    "wof:name":"Servian Electricidad S.l.",
    "wof:placetype":"venue"
},
  "geometry": {"coordinates":[-4.4837379456,37.4093360901],"type":"Point"}
}