{
  "type": "Feature",
  "properties": {
    "addr:full":"Ctra Ribes, Km. 0082,9 Montesquiu Barcelona 08589",
    "addr:housenumber":"km.",
    "addr:postcode":"08589",
    "addr:street":"Ctra Ribes;0082,9 Montesquiu",
    "iso:country":"ES",
    "sg:address":"Ctra Ribes, Km. 0082,9",
    "sg:city":"Montesquiu",
    "sg:orig_category":"Mataderos Y Talleres De Despiezado",
    "sg:phone":"+34 938 52 90 33",
    "sg:postcode":"08589",
    "sg:province":"Barcelona",
    "wof:name":"Carniques Ausa S.l.",
    "wof:placetype":"venue"
},
  "geometry": {"coordinates":[2.1063570976,42.0411453247],"type":"Point"}
}