{
  "type": "Feature",
  "properties": {
    "iso:country":"ES",
    "sg:address":"Ptda Partida Portijol, S/n",
    "sg:city":"Barraca D'aigues Vives",
    "sg:orig_category":"Asociaciones Ecologistas",
    "sg:phone":"+34 962 12 02 08",
    "sg:postcode":"46792",
    "sg:province":"Valencia",
    "wof:name":"Comunidad De Regantes De Aguas Vivas Del Portichol De Alzira",
    "wof:placetype":"venue"
},
  "geometry": {"coordinates":[-0.33366099,39.4609527588],"type":"Point"}
}