{
  "type": "Feature",
  "properties": {
    "iso:country":"ES",
    "sg:address":"Carrer de L'alcalde De Mostoles, 12",
    "sg:city":"Barcelona",
    "sg:orig_category":"Mec\u00c1nico Del Autom\u00d3vil",
    "sg:phone":"+34 933 48 16 97",
    "sg:postcode":"08025",
    "sg:province":"Barcelona",
    "wof:name":"Tra Mantenimiento De Flota S.l.",
    "wof:placetype":"venue"
},
  "geometry": {"coordinates":[2.1668541431,41.4103240967],"type":"Point"}
}