{
  "type": "Feature",
  "properties": {
    "addr:full":"Carrer de Gubia, 6 Santa Coloma De Queralt Tarragona 43420",
    "addr:housenumber":"6",
    "addr:postcode":"43420",
    "addr:street":"Carrer De Gubia",
    "iso:country":"ES",
    "sg:address":"Carrer de Gubia, 6",
    "sg:city":"Santa Coloma De Queralt",
    "sg:orig_category":"Notarios",
    "sg:phone":"+34 977 88 06 63",
    "sg:postcode":"43420",
    "sg:province":"Tarragona",
    "wof:name":"Viela Castranado Miguel",
    "wof:placetype":"venue"
},
  "geometry": {"coordinates":[1.3872760534,41.5325431824],"type":"Point"}
}