{
  "type": "Feature",
  "properties": {
    "iso:country":"ES",
    "sg:address":"Calle de Asensi, 23",
    "sg:city":"Castellon",
    "sg:orig_category":"Inmobiliaria (agencias)",
    "sg:phone":"+34 964 24 53 69",
    "sg:postcode":"12002",
    "sg:province":"Castell\u00f3n",
    "wof:name":"Arrendacas S.l.u.",
    "wof:placetype":"venue"
},
  "geometry": {"coordinates":[-0.0363522992,39.9827270508],"type":"Point"}
}