{
  "type": "Feature",
  "properties": {
    "addr:full":"Carrer de Mestre Joaquim Rosal, 20 Esplugues Llobregat Barcelona 08950",
    "addr:housenumber":"20",
    "addr:postcode":"08950",
    "addr:street":"Carrer De Mestre Joaquim Rosal",
    "iso:country":"ES",
    "sg:address":"Carrer de Mestre Joaquim Rosal, 20",
    "sg:city":"Esplugues Llobregat",
    "sg:orig_category":"Inmobiliaria (agencias)",
    "sg:phone":"+34 934 80 24 21",
    "sg:postcode":"08950",
    "sg:province":"Barcelona",
    "sg:website":"www.fincas-lizana.com",
    "wof:name":"F.rosillo S.l.",
    "wof:placetype":"venue"
},
  "geometry": {"coordinates":[2.0869429111,41.3770484924],"type":"Point"}
}