{
  "type": "Feature",
  "properties": {
    "iso:country":"ES",
    "sg:address":"Alsina, S/n",
    "sg:city":"Lloren\u00e7 Penedes",
    "sg:orig_category":"Fabricaci\u00d3n, Distribuci\u00d3n De Discos, V\u00cddeodiscos Y Musicassettes",
    "sg:phone":"+34 977 67 87 10",
    "sg:postcode":"43712",
    "sg:province":"Tarragona",
    "wof:name":"Arjuar Penedes S.l.",
    "wof:placetype":"venue"
},
  "geometry": {"coordinates":[1.2454571724,41.11901474],"type":"Point"}
}