{
  "type": "Feature",
  "properties": {
    "iso:country":"ES",
    "sg:address":"Calle de Sol, 49",
    "sg:city":"Campo Criptana",
    "sg:orig_category":"Mec\u00c1nico Del Autom\u00d3vil",
    "sg:phone":"+34 926 56 31 29",
    "sg:postcode":"13610",
    "sg:province":"Ciudad Real",
    "wof:name":"Pintado Jimenez Miguel Angel",
    "wof:placetype":"venue"
},
  "geometry": {"coordinates":[-3.1293590069,39.4053192139],"type":"Point"}
}