{
  "type": "Feature",
  "properties": {
    "addr:full":"Calle de Olivo, S/n Barca De La Florida C\u00e1diz 11570",
    "addr:postcode":"11570",
    "addr:street":"Calle De Olivo S / N Barca De La;Ca\u0301Diz",
    "iso:country":"ES",
    "sg:address":"Calle de Olivo, S/n",
    "sg:city":"Barca De La Florida",
    "sg:orig_category":"Estancos",
    "sg:phone":"+34 956 16 30 33",
    "sg:postcode":"11570",
    "sg:province":"C\u00e1diz",
    "wof:name":"Robles Gomez Francisco",
    "wof:placetype":"venue"
},
  "geometry": {"coordinates":[-5.933991909,36.6463241577],"type":"Point"}
}