{
  "type": "Feature",
  "properties": {
    "addr:full":"Euskadi Etorbidea, 39 Pasai S. Pedro Guip\u00f9zcoa 20110",
    "addr:housenumber":"39",
    "addr:postcode":"20110",
    "addr:street":"Euskadi Etorbidea;Pasai S.;Guipu\u0300Zcoa",
    "iso:country":"ES",
    "sg:address":"Euskadi Etorbidea, 39",
    "sg:city":"Pasai S. Pedro",
    "sg:orig_category":"Bisuter\u00cda, Joyer\u00cda, Relojer\u00cda (al Por Menor)",
    "sg:phone":"+34 943 40 06 07",
    "sg:postcode":"20110",
    "sg:province":"Guip\u00f9zcoa",
    "wof:name":"Wifredo Ubeda Altuna Y Sagrario Erviti Saez S.cv.",
    "wof:placetype":"venue"
},
  "geometry": {"coordinates":[-1.9324934483,43.323097229],"type":"Point"}
}