{
  "type": "Feature",
  "properties": {
    "addr:full":"Avda Valencia, 39 Ibi Alicante 03440",
    "addr:housenumber":"39",
    "addr:postcode":"03440",
    "addr:street":"Avda Valencia",
    "iso:country":"ES",
    "sg:address":"Avda Valencia, 39",
    "sg:city":"Ibi",
    "sg:orig_category":"Artes Gr\u00c1ficas, Artes Pl\u00c1sticas (curso)",
    "sg:phone":"+34 965 55 09 40",
    "sg:postcode":"03440",
    "sg:province":"Alicante",
    "wof:name":"Graficas Torres S.a.",
    "wof:placetype":"venue"
},
  "geometry": {"coordinates":[-0.5975369811,38.6175575256],"type":"Point"}
}