{
  "type": "Feature",
  "properties": {
    "addr:full":"Calle de Tenerias, 12 Valdemoro Madrid 28340",
    "addr:housenumber":"12",
    "addr:postcode":"28340",
    "addr:street":"Calle De Tenerias",
    "iso:country":"ES",
    "sg:address":"Calle de Tenerias, 12",
    "sg:city":"Valdemoro",
    "sg:orig_category":"Inform\u00c1tica (estudios, Servicios, Asesor\u00cda, Formaci\u00d3n)",
    "sg:phone":"+34 918 09 58 38",
    "sg:postcode":"28340",
    "sg:province":"Madrid",
    "wof:name":"Nu\u00f1ez Martinez Luis",
    "wof:placetype":"venue"
},
  "geometry": {"coordinates":[-3.6797890663,40.1935882568],"type":"Point"}
}