{
  "type": "Feature",
  "properties": {
    "addr:full":"Calle de Luis Oliag, 50 Valencia Valencia 46006",
    "addr:housenumber":"50",
    "addr:postcode":"46006",
    "addr:street":"Calle De Luis Oliag",
    "iso:country":"ES",
    "sg:address":"Calle de Luis Oliag, 50",
    "sg:city":"Valencia",
    "sg:orig_category":"Clubes, Asociaciones De Ocio",
    "sg:phone":"+34 963 73 76 24",
    "sg:postcode":"46006",
    "sg:province":"Valencia",
    "wof:name":"Ausina Boquera Amparo De La Concepcion",
    "wof:placetype":"venue"
},
  "geometry": {"coordinates":[-0.3629049957,39.4607620239],"type":"Point"}
}