{
  "type": "Feature",
  "properties": {
    "addr:full":"Valle De Ordesa, 9 Cadrete Zaragoza 50420",
    "addr:housenumber":"9",
    "addr:postcode":"50420",
    "addr:street":"Ordesa",
    "iso:country":"ES",
    "sg:address":"Valle De Ordesa, 9",
    "sg:city":"Cadrete",
    "sg:orig_category":"Montaje (empresas De)",
    "sg:phone":"+34 976 12 60 78",
    "sg:postcode":"50420",
    "sg:province":"Zaragoza",
    "wof:name":"Montajes 976 S.l.",
    "wof:placetype":"venue"
},
  "geometry": {"coordinates":[-0.9639480114,41.565612793],"type":"Point"}
}