{
  "type": "Feature",
  "properties": {
    "iso:country":"ES",
    "sg:address":"Pla\u00c7 Santa Eugenia, 4",
    "sg:city":"Girona",
    "sg:orig_category":"Inmobiliaria (agencias)",
    "sg:phone":"+34 972 24 10 78",
    "sg:postcode":"17006",
    "sg:province":"Girona",
    "wof:name":"Vector Serveis Immobiliaris S.a.",
    "wof:placetype":"venue"
},
  "geometry": {"coordinates":[2.8032150269,41.9764556885],"type":"Point"}
}