{
  "type": "Feature",
  "properties": {
    "iso:country":"ES",
    "sg:address":"Avda Velazquez, 15",
    "sg:city":"Camino De Umbrete",
    "sg:orig_category":"Estudios, Instalaci\u00d3n De Climatizaci\u00d3n",
    "sg:phone":"+34 954 11 41 70",
    "sg:postcode":"41807",
    "sg:province":"Sevilla",
    "sg:website":"www.trox.es",
    "wof:name":"Trox Espa\u00f1ola S.a.",
    "wof:placetype":"venue"
},
  "geometry": {"coordinates":[-6.1235818863,37.3828926086],"type":"Point"}
}