{
  "type": "Feature",
  "properties": {
    "iso:country":"ES",
    "sg:address":"Calle de Repuente, 24",
    "sg:city":"Monte",
    "sg:orig_category":"Ebanister\u00cda",
    "sg:phone":"+34 942 33 36 69",
    "sg:postcode":"39012",
    "sg:province":"Cantabria",
    "wof:name":"Antonio Gomez Hoyal S.l.",
    "wof:placetype":"venue"
},
  "geometry": {"coordinates":[-3.8281333447,43.4692955017],"type":"Point"}
}