{
  "type": "Feature",
  "properties": {
    "iso:country":"ES",
    "sg:address":"Rua Concepcion Arenal, 29",
    "sg:city":"Lugo",
    "sg:orig_category":"Ropa Para Se\u00d1oras (al Por Menor)",
    "sg:phone":"+34 982 24 57 28",
    "sg:postcode":"27004",
    "sg:province":"Lugo",
    "wof:name":"Martinez Rey Dolores",
    "wof:placetype":"venue"
},
  "geometry": {"coordinates":[-7.5604848862,43.0149917603],"type":"Point"}
}