{
  "type": "Feature",
  "properties": {
    "iso:country":"ES",
    "sg:address":"Calle de Dr Layna Serrano, 6",
    "sg:city":"Guadalajara",
    "sg:orig_category":"Gu\u00cdas Y Gu\u00cdas",
    "sg:phone":"+34 949 21 37 87",
    "sg:postcode":"19002",
    "sg:province":"Guadalajara",
    "wof:name":"Rodriguez Jimenez Eugenio",
    "wof:placetype":"venue"
},
  "geometry": {"coordinates":[-3.1706519127,40.6260032654],"type":"Point"}
}