{
  "type": "Feature",
  "properties": {
    "addr:full":"Calle de Ancora, 17 Illescas Toledo 45200",
    "addr:housenumber":"17",
    "addr:postcode":"45200",
    "addr:street":"Calle De Ancora",
    "iso:country":"ES",
    "sg:address":"Calle de Ancora, 17",
    "sg:city":"Illescas",
    "sg:orig_category":"Artes Gr\u00c1ficas, Artes Pl\u00c1sticas (curso)",
    "sg:phone":"+34 925 51 23 79",
    "sg:postcode":"45200",
    "sg:province":"Toledo",
    "sg:website":"www paginasamarillas.es",
    "wof:name":"Imprenta Newborn S.l.",
    "wof:placetype":"venue"
},
  "geometry": {"coordinates":[-3.8560922146,40.1122093201],"type":"Point"}
}