{
  "type": "Feature",
  "properties": {
    "addr:full":"Calle de Teresa Gil, 19 Valladolid Valladolid 47002",
    "addr:housenumber":"19",
    "addr:postcode":"47002",
    "addr:street":"Calle De Teresa Gil",
    "iso:country":"ES",
    "sg:address":"Calle de Teresa Gil, 19",
    "sg:city":"Valladolid",
    "sg:orig_category":"Ropa Para Ni\u00d1os (al Por Menor)",
    "sg:phone":"+34 983 20 63 37",
    "sg:postcode":"47002",
    "sg:province":"Valladolid",
    "sg:website":"www.neckandneck.com",
    "wof:name":"Neck Child S.a.",
    "wof:placetype":"venue"
},
  "geometry": {"coordinates":[-4.7254071236,41.6505393982],"type":"Point"}
}