{
  "type": "Feature",
  "properties": {
    "addr:full":"Serra Magre, 1 Riudarenes Girona 17421",
    "addr:housenumber":"1",
    "addr:postcode":"17421",
    "addr:street":"Magre",
    "iso:country":"ES",
    "sg:address":"Serra Magre, 1",
    "sg:city":"Riudarenes",
    "sg:orig_category":"Alimentaci\u00d3n General (al Por Mayor)",
    "sg:phone":"+34 972 16 46 37",
    "sg:postcode":"17421",
    "sg:province":"Girona",
    "wof:name":"Armengol Masso Pere",
    "wof:placetype":"venue"
},
  "geometry": {"coordinates":[2.7216320038,41.8245391846],"type":"Point"}
}