{
  "type": "Feature",
  "properties": {
    "addr:full":"Calle de Gerardo Gombau, 17 Salamanca Salamanca 37008",
    "addr:housenumber":"17",
    "addr:postcode":"37008",
    "addr:street":"Calle De Gerardo Gombau",
    "iso:country":"ES",
    "sg:address":"Calle de Gerardo Gombau, 17",
    "sg:city":"Salamanca",
    "sg:orig_category":"Pintura, Barniz, Productos Asimilables (fabricaci\u00d3n, Al Por Mayor)",
    "sg:phone":"+34 923 21 81 95",
    "sg:postcode":"37008",
    "sg:province":"Salamanca",
    "wof:name":"Montero Merino Paz",
    "wof:placetype":"venue"
},
  "geometry": {"coordinates":[-5.6590042114,40.9463157654],"type":"Point"}
}