{
  "type": "Feature",
  "properties": {
    "addr:full":"Calle de Calera, 1 Talavera Reina Toledo 45600",
    "addr:housenumber":"1",
    "addr:postcode":"45600",
    "addr:street":"Calle De Calera",
    "iso:country":"ES",
    "sg:address":"Calle de Calera, 1",
    "sg:city":"Talavera Reina",
    "sg:orig_category":"Bancos",
    "sg:phone":"+34 925 80 02 00",
    "sg:postcode":"45600",
    "sg:province":"Toledo",
    "wof:name":"Banco Espa\u00d1ol De Credito S.a.",
    "wof:placetype":"venue"
},
  "geometry": {"coordinates":[-4.8398718834,39.9581413269],"type":"Point"}
}