{
  "type": "Feature",
  "properties": {
    "iso:country":"ES",
    "sg:address":"Avda Pueyo, 112",
    "sg:city":"Monzon",
    "sg:orig_category":"Material Y Herramientas Agr\u00cdcolas",
    "sg:phone":"+34 974 40 15 48",
    "sg:postcode":"22400",
    "sg:province":"Huesca",
    "wof:name":"Vicente Canales S. A.",
    "wof:placetype":"venue"
},
  "geometry": {"coordinates":[0.1836899966,41.9030685425],"type":"Point"}
}