{
  "type": "Feature",
  "properties": {
    "addr:full":"Calle de Misericordia (de La), 3 Arganda Madrid 28500",
    "addr:housenumber":"3",
    "addr:postcode":"28500",
    "addr:street":"Calle De Misericordia De La",
    "iso:country":"ES",
    "sg:address":"Calle de Misericordia (de La), 3",
    "sg:city":"Arganda",
    "sg:orig_category":"Ropa Para Se\u00d1oras Y Caballeros (al Por Menor)",
    "sg:phone":"+34 918 70 04 95",
    "sg:postcode":"28500",
    "sg:province":"Madrid",
    "wof:name":"Conejero Orozco Mario",
    "wof:placetype":"venue"
},
  "geometry": {"coordinates":[-3.4419291019,40.3016891479],"type":"Point"}
}