{
  "type": "Feature",
  "properties": {
    "addr:full":"Calle de Arcipreste De Hita, 13 Guadalajara Guadalajara 19001",
    "addr:housenumber":"13",
    "addr:postcode":"19001",
    "addr:street":"Calle De Arcipreste De Hita",
    "iso:country":"ES",
    "sg:address":"Calle de Arcipreste De Hita, 13",
    "sg:city":"Guadalajara",
    "sg:orig_category":"Molduras, Junquillos, Listones Y Molduras Perforadas",
    "sg:phone":"+34 949 23 20 96",
    "sg:postcode":"19001",
    "sg:province":"Guadalajara",
    "wof:name":"Valero Fernandez Maria Del Carmen",
    "wof:placetype":"venue"
},
  "geometry": {"coordinates":[-3.1627364159,40.6320838928],"type":"Point"}
}