{
  "type": "Feature",
  "properties": {
    "addr:full":"Calle de San Joaquin, 39 Paiporta Valencia 46200",
    "addr:housenumber":"39",
    "addr:postcode":"46200",
    "addr:street":"Calle De San Joaquin",
    "iso:country":"ES",
    "sg:address":"Calle de San Joaquin, 39",
    "sg:city":"Paiporta",
    "sg:orig_category":"Mantenimiento Y Limpieza De Carreteras",
    "sg:phone":"+34 963 97 62 43",
    "sg:postcode":"46200",
    "sg:province":"Valencia",
    "wof:name":"Pairservi S.l.",
    "wof:placetype":"venue"
},
  "geometry": {"coordinates":[-0.4233990014,39.4273605347],"type":"Point"}
}