{
  "type": "Feature",
  "properties": {
    "addr:full":"Leyre-leire Kalea, 14 Iru\u00f1a Navarra 31002",
    "addr:housenumber":"14",
    "addr:postcode":"31002",
    "addr:street":"Leyre-Leire Kalea",
    "iso:country":"ES",
    "sg:address":"Leyre-leire Kalea, 14",
    "sg:city":"Iru\u00f1a",
    "sg:orig_category":"Ropa Para Se\u00d1oras (al Por Menor)",
    "sg:phone":"+34 948 21 21 10",
    "sg:postcode":"31002",
    "sg:province":"Navarra",
    "wof:name":"Boutique Piedad S.l.",
    "wof:placetype":"venue"
},
  "geometry": {"coordinates":[-1.6389429569,42.8144073486],"type":"Point"}
}