{
  "type": "Feature",
  "properties": {
    "addr:full":"Calle de Lopez Gomez, 13 Valladolid Valladolid 47002",
    "addr:housenumber":"13",
    "addr:postcode":"47002",
    "addr:street":"Calle De Lopez Gomez",
    "iso:country":"ES",
    "sg:address":"Calle de Lopez Gomez, 13",
    "sg:city":"Valladolid",
    "sg:orig_category":"Relojer\u00cda (al Por Menor, Reparaci\u00d3n)",
    "sg:phone":"+34 983 30 35 93",
    "sg:postcode":"47002",
    "sg:province":"Valladolid",
    "wof:name":"Vallejo Ferreira Rosa Maria",
    "wof:placetype":"venue"
},
  "geometry": {"coordinates":[-4.7232713699,41.650932312],"type":"Point"}
}