{
  "type": "Feature",
  "properties": {
    "iso:country":"ES",
    "sg:address":"Cami Termens, S/n",
    "sg:city":"Bellvis",
    "sg:orig_category":"Frutas Y Legumbres Frescas (al Por Mayor)",
    "sg:phone":"+34 973 71 61 78",
    "sg:postcode":"25142",
    "sg:province":"Lleida",
    "wof:name":"Sat Fruitsa N 1396",
    "wof:placetype":"venue"
},
  "geometry": {"coordinates":[0.8160060048,41.6747169495],"type":"Point"}
}