{
  "type": "Feature",
  "properties": {
    "iso:country":"ES",
    "sg:address":"Calle de Gran Capitan, 9",
    "sg:city":"Marchamalo",
    "sg:orig_category":"Fabricaci\u00d3n De Juguetes Autom\u00c1ticos",
    "sg:phone":"+34 949 25 01 16",
    "sg:postcode":"19180",
    "sg:province":"Guadalajara",
    "wof:name":"Marcos De Diego Gregorio",
    "wof:placetype":"venue"
},
  "geometry": {"coordinates":[-3.2024989128,40.6665267944],"type":"Point"}
}