{
  "type": "Feature",
  "properties": {
    "addr:full":"Calle de Ribera, 12 Valencia Valencia 46002",
    "addr:housenumber":"12",
    "addr:postcode":"46002",
    "addr:street":"Calle De Ribera",
    "iso:country":"ES",
    "sg:address":"Calle de Ribera, 12",
    "sg:city":"Valencia",
    "sg:orig_category":"Farmacias",
    "sg:phone":"+34 963 51 13 58",
    "sg:postcode":"46002",
    "sg:province":"Valencia",
    "wof:name":"Gimeno Siscar Carmen",
    "wof:placetype":"venue"
},
  "geometry": {"coordinates":[-0.3760659993,39.4681015015],"type":"Point"}
}