{
  "type": "Feature",
  "properties": {
    "iso:country":"ES",
    "sg:address":"Calle de Torrelaguna, 24",
    "sg:city":"Sevilla",
    "sg:orig_category":"Bisuter\u00cda, Joyer\u00cda, Relojer\u00cda (al Por Menor)",
    "sg:phone":"+34 954 40 49 20",
    "sg:postcode":"41016",
    "sg:province":"Sevilla",
    "wof:name":"Joyeria Elite S.l.",
    "wof:placetype":"venue"
},
  "geometry": {"coordinates":[-5.9084062576,37.3854827881],"type":"Point"}
}