{
  "type": "Feature",
  "properties": {
    "addr:full":"Carrer de Verdi, 327 Barcelona Barcelona 08024",
    "addr:housenumber":"327",
    "addr:postcode":"08024",
    "addr:street":"Carrer De Verdi",
    "iso:country":"ES",
    "sg:address":"Carrer de Verdi, 327",
    "sg:city":"Barcelona",
    "sg:orig_category":"Colchones (fabricaci\u00d3n, Al Por Mayor, Al Por Menor)",
    "sg:phone":"+34 932 85 72 32",
    "sg:postcode":"08024",
    "sg:province":"Barcelona",
    "wof:name":"Quiles Alba Bocs S.c.p.",
    "wof:placetype":"venue"
},
  "geometry": {"coordinates":[2.1492509842,41.4116134644],"type":"Point"}
}