{
  "type": "Feature",
  "properties": {
    "iso:country":"ES",
    "sg:address":"Calle de Gonzalez Gallarza, 19",
    "sg:city":"Ezcaray",
    "sg:orig_category":"Inmobiliaria (agencias)",
    "sg:phone":"+34 941 42 74 24",
    "sg:postcode":"26280",
    "sg:province":"La Rioja",
    "wof:name":"Rodriguez Castro Ignacio Javier",
    "wof:placetype":"venue"
},
  "geometry": {"coordinates":[-3.0143260956,42.3241882324],"type":"Point"}
}