{
  "type": "Feature",
  "properties": {
    "addr:full":"Santamaria-andre Mari Kalea, 2 Ordizia Guip\u00f9zcoa 20240",
    "addr:housenumber":"2",
    "addr:postcode":"20240",
    "addr:street":"Mari Kalea;Guipu\u0300Zcoa",
    "iso:country":"ES",
    "sg:address":"Santamaria-andre Mari Kalea, 2",
    "sg:city":"Ordizia",
    "sg:orig_category":"Fabricaci\u00d3n, Venta De Productos Base Farmac\u00c9uticos",
    "sg:phone":"+34 943 16 09 49",
    "sg:postcode":"20240",
    "sg:province":"Guip\u00f9zcoa",
    "wof:name":"I\u00f1igo De La Cuesta Jauregui C.b.",
    "wof:placetype":"venue"
},
  "geometry": {"coordinates":[-2.1773040295,43.0538711548],"type":"Point"}
}