{
  "type": "Feature",
  "properties": {
    "iso:country":"ES",
    "sg:address":"F. Gorriti, 10",
    "sg:city":"Iru\u00f1a",
    "sg:orig_category":"Centros Empresariales",
    "sg:phone":"+34 948 24 59 04",
    "sg:postcode":"31004",
    "sg:province":"Navarra",
    "wof:name":"Asociacion Empresarial De Carpinteros Y Ebanistas De Navarra",
    "wof:placetype":"venue"
},
  "geometry": {"coordinates":[-1.634786725,42.8127479553],"type":"Point"}
}