{
  "type": "Feature",
  "properties": {
    "iso:country":"ES",
    "sg:address":"Calle de Bizkaia, 50",
    "sg:city":"San Vicente De Barakaldo",
    "sg:orig_category":"Peluqueros: De Se\u00d1oras",
    "sg:phone":"+34 944 38 23 50",
    "sg:postcode":"48902",
    "sg:province":"Vizcaya",
    "wof:name":"Bola\u00f1os Gallardo Maria",
    "wof:placetype":"venue"
},
  "geometry": {"coordinates":[-2.9838240147,43.2939682007],"type":"Point"}
}