{
  "type": "Feature",
  "properties": {
    "iso:country":"ES",
    "sg:address":"Carrer de Bellesguard, 16",
    "sg:city":"Barcelona",
    "sg:orig_category":"M\u00c9dicos: Ginecolog\u00cda Y Obstetricia",
    "sg:phone":"+34 934 17 54 01",
    "sg:postcode":"08022",
    "sg:province":"Barcelona",
    "wof:name":"Guilera Soler Luis",
    "wof:placetype":"venue"
},
  "geometry": {"coordinates":[2.127177,41.4089393616],"type":"Point"}
}