{
  "type": "Feature",
  "properties": {
    "addr:full":"Carrer de Pare Bartomeu Pou, 10 Palma Islas Baleares 07003",
    "addr:housenumber":"10",
    "addr:postcode":"07003",
    "addr:street":"Carrer De Pare Bartomeu Pou",
    "iso:country":"ES",
    "sg:address":"Carrer de Pare Bartomeu Pou, 10",
    "sg:city":"Palma",
    "sg:orig_category":"Asociaciones Y Clubs Deportivos",
    "sg:phone":"+34 971 20 70 23",
    "sg:postcode":"07003",
    "sg:province":"Islas Baleares",
    "wof:name":"Mota Santos Francisco",
    "wof:placetype":"venue"
},
  "geometry": {"coordinates":[2.6516571045,39.581577301],"type":"Point"}
}