{
  "type": "Feature",
  "properties": {
    "addr:full":"Avda Villanueva, 9 Badajoz Badajoz 06005",
    "addr:housenumber":"9",
    "addr:postcode":"06005",
    "addr:street":"Avda Villanueva",
    "iso:country":"ES",
    "sg:address":"Avda Villanueva, 9",
    "sg:city":"Badajoz",
    "sg:orig_category":"Abogados",
    "sg:phone":"+34 924 22 00 72",
    "sg:postcode":"06005",
    "sg:province":"Badajoz",
    "wof:name":"Garrancho Casas Manuel",
    "wof:placetype":"venue"
},
  "geometry": {"coordinates":[-6.9778981209,38.870891571],"type":"Point"}
}