{
  "type": "Feature",
  "properties": {
    "addr:full":"Calle de Doramas, 4 Paredilla I Las Palmas 35110",
    "addr:housenumber":"4",
    "addr:postcode":"35110",
    "addr:street":"Calle De Doramas",
    "iso:country":"ES",
    "sg:address":"Calle de Doramas, 4",
    "sg:city":"Paredilla I",
    "sg:orig_category":"Iglesias Evang\u00c9licas",
    "sg:phone":"+34 928 75 46 69",
    "sg:postcode":"35110",
    "sg:province":"Las Palmas",
    "wof:name":"Iglesia Cristiana Evangelica",
    "wof:placetype":"venue"
},
  "geometry": {"coordinates":[-15.445684433,27.8448238373],"type":"Point"}
}