{
  "type": "Feature",
  "properties": {
    "addr:full":"Calle de Alegria, S/n Garres Murcia 30158",
    "addr:postcode":"30158",
    "addr:street":"Calle De Alegria S / N",
    "iso:country":"ES",
    "sg:address":"Calle de Alegria, S/n",
    "sg:city":"Garres",
    "sg:orig_category":"Zapatos (al Por Menor)",
    "sg:phone":"+34 968 87 44 96",
    "sg:postcode":"30158",
    "sg:province":"Murcia",
    "wof:name":"Carrillo Martinez Antonia Maria",
    "wof:placetype":"venue"
},
  "geometry": {"coordinates":[-1.093051672,37.9555282593],"type":"Point"}
}