{
  "type": "Feature",
  "properties": {
    "iso:country":"ES",
    "sg:address":"Av Francesc Macia (de), 10",
    "sg:city":"Tarragona",
    "sg:orig_category":"Empresas De Pintura Y Revestimientos",
    "sg:phone":"+34 977 21 41 76",
    "sg:postcode":"43005",
    "sg:province":"Tarragona",
    "wof:name":"Arnuelos Andres Jose Vicente",
    "wof:placetype":"venue"
},
  "geometry": {"coordinates":[1.2374501228,41.1227989197],"type":"Point"}
}