{
  "type": "Feature",
  "properties": {
    "iso:country":"ES",
    "sg:address":"Muel Linares Rivas, S/n",
    "sg:city":"Coru\u00d1a",
    "sg:orig_category":"Distribuci\u00d3n De Petr\u00d3leo Y Derivados",
    "sg:phone":"+34 981 29 79 30",
    "sg:postcode":"15006",
    "sg:province":"La Coru\u00f1a",
    "sg:website":"www.mcolinaspescados.com",
    "wof:name":"M Colinas Pescados S.l.",
    "wof:placetype":"venue"
},
  "geometry": {"coordinates":[-8.4053344727,43.3629341125],"type":"Point"}
}