{
  "type": "Feature",
  "properties": {
    "addr:full":"Calle de Esca\u00d1uela, S/n Cordoba C\u00f3rdoba 14002",
    "addr:housenumber":"s",
    "addr:postcode":"14002",
    "addr:street":"Calle De Escan\u0303Uela;/ N;Co\u0301Rdoba",
    "iso:country":"ES",
    "sg:address":"Calle de Esca\u00d1uela, S/n",
    "sg:city":"Cordoba",
    "sg:orig_category":"Peluqueros: De Se\u00d1oras",
    "sg:phone":"+34 957 26 48 01",
    "sg:postcode":"14002",
    "sg:province":"C\u00f3rdoba",
    "wof:name":"Jimenez Bazan Maria Jose",
    "wof:placetype":"venue"
},
  "geometry": {"coordinates":[-4.7682418823,37.8876304626],"type":"Point"}
}