{
  "type": "Feature",
  "properties": {
    "addr:full":"Calle de Bailen, 56 Malaga M\u00e1laga 29009",
    "addr:housenumber":"56",
    "addr:postcode":"29009",
    "addr:street":"Calle De Bailen;Ma\u0301Laga",
    "iso:country":"ES",
    "sg:address":"Calle de Bailen, 56",
    "sg:city":"Malaga",
    "sg:orig_category":"Imprenta",
    "sg:phone":"+34 952 30 82 90",
    "sg:postcode":"29009",
    "sg:province":"M\u00e1laga",
    "wof:name":"Talleres Graficos Rodriguez S.l.",
    "wof:placetype":"venue"
},
  "geometry": {"coordinates":[-4.4351987839,36.725112915],"type":"Point"}
}