{
  "type": "Feature",
  "properties": {
    "iso:country":"ES",
    "sg:address":"Rua Perpetuo Socorro, 2",
    "sg:city":"Lugo",
    "sg:classifiers":[
        {
            "category":"Professional",
            "subcategory":"Management & Consulting",
            "type":"Services"
        }
    ],
    "sg:phone":"+34 982 24 14 06",
    "sg:postcode":"27003",
    "sg:province":"Lugo",
    "sg:tags":[
        "asesor\u00cda",
        "en",
        "marketing"
    ],
    "wof:name":"Novo Gil Angel",
    "wof:placetype":"venue"
},
  "geometry": {"coordinates":[-7.5623040199,43.0195007324],"type":"Point"}
}