{
  "type": "Feature",
  "properties": {
    "addr:full":"Carrer de Londres, 80 Barcelona Barcelona 08036",
    "addr:housenumber":"80",
    "addr:postcode":"08036",
    "addr:street":"Carrer De Londres",
    "iso:country":"ES",
    "sg:address":"Carrer de Londres, 80",
    "sg:city":"Barcelona",
    "sg:orig_category":"Cajas De Ahorro",
    "sg:phone":"+34 934 39 15 52",
    "sg:postcode":"08036",
    "sg:province":"Barcelona",
    "sg:website":"www.lacaixa.es",
    "wof:name":"Caixa D'estalvis I Pensions De Barcelona",
    "wof:placetype":"venue"
},
  "geometry": {"coordinates":[2.1498670578,41.3926086426],"type":"Point"}
}