{
  "type": "Feature",
  "properties": {
    "addr:full":"Ctra. Madrid, S/n Fitero Navarra 31593",
    "addr:housenumber":"s / n",
    "addr:postcode":"31593",
    "addr:street":"Ctra. Madrid",
    "iso:country":"ES",
    "sg:address":"Ctra. Madrid, S/n",
    "sg:city":"Fitero",
    "sg:orig_category":"Paneles Diversos",
    "sg:phone":"+34 948 84 49 01",
    "sg:postcode":"31593",
    "sg:province":"Navarra",
    "wof:name":"Rotulos Valentin S.l.",
    "wof:placetype":"venue"
},
  "geometry": {"coordinates":[-1.8597589731,42.0590515137],"type":"Point"}
}