{
  "type": "Feature",
  "properties": {
    "iso:country":"ES",
    "sg:address":"Avda Bilbao, 124",
    "sg:city":"Torrelavega",
    "sg:orig_category":"Muebles",
    "sg:phone":"+34 942 89 39 32",
    "sg:postcode":"39300",
    "sg:province":"Cantabria",
    "wof:name":"Muebles El Almacen S.l.",
    "wof:placetype":"venue"
},
  "geometry": {"coordinates":[-4.0301289558,43.3418083191],"type":"Point"}
}