{
  "type": "Feature",
  "properties": {
    "addr:full":"Calle de Brasil (del), 1 Algete Madrid 28110",
    "addr:postcode":"28110",
    "addr:street":"Calle De Brasil Del",
    "iso:country":"ES",
    "sg:address":"Calle de Brasil (del), 1",
    "sg:city":"Algete",
    "sg:orig_category":"Asesor\u00cda Sobre Comunicaci\u00d3n De Empresas",
    "sg:phone":"+34 916 28 12 88",
    "sg:postcode":"28110",
    "sg:province":"Madrid",
    "wof:name":"Fernandez-cruz Sequera Francisco Jose",
    "wof:placetype":"venue"
},
  "geometry": {"coordinates":[-3.4973018169,40.5910949707],"type":"Point"}
}