{
  "type": "Feature",
  "properties": {
    "iso:country":"ES",
    "sg:address":"Ctra. Rueda, S/n",
    "sg:city":"Valladolid",
    "sg:orig_category":"Asociaciones Y Clubs Deportivos",
    "sg:phone":"+34 983 24 96 59",
    "sg:postcode":"47008",
    "sg:province":"Valladolid",
    "wof:name":"Grupo De Empresa Fasa Renault",
    "wof:placetype":"venue"
},
  "geometry": {"coordinates":[-4.741517067,41.6289100647],"type":"Point"}
}