{
  "type": "Feature",
  "properties": {
    "iso:country":"ES",
    "sg:address":"Rua Blanco Rajoy, 69",
    "sg:city":"Vimianzo",
    "sg:orig_category":"Comercio De Piezas De Recambio Y De Accesorios De Veh\u00cdculos, Veh\u00cdculos Industriales",
    "sg:phone":"+34 981 71 61 59",
    "sg:postcode":"15120",
    "sg:province":"La Coru\u00f1a",
    "wof:name":"Eiroa Toja Juan Jose",
    "wof:placetype":"venue"
},
  "geometry": {"coordinates":[-9.0328435898,43.1112251282],"type":"Point"}
}