{
  "type": "Feature",
  "properties": {
    "iso:country":"ES",
    "sg:address":"Cra. Viladrau, S/n",
    "sg:city":"Seva",
    "sg:orig_category":"Empresas De Impermeabilizaci\u00d3n",
    "sg:phone":"+34 938 84 05 07",
    "sg:postcode":"08553",
    "sg:province":"Barcelona",
    "sg:website":"www.isoduri.com",
    "wof:name":"Isoduri S.l.",
    "wof:placetype":"venue"
},
  "geometry": {"coordinates":[2.2751309872,41.8237876892],"type":"Point"}
}