{
  "type": "Feature",
  "properties": {
    "iso:country":"ES",
    "sg:address":"Calle de Barcelona, 1",
    "sg:city":"Mota Cuervo",
    "sg:orig_category":"Ropa Para Se\u00d1oras Y Caballeros (al Por Menor)",
    "sg:phone":"+34 967 18 01 77",
    "sg:postcode":"16630",
    "sg:province":"Cuenca",
    "wof:name":"Lopez Lopez Antonio",
    "wof:placetype":"venue"
},
  "geometry": {"coordinates":[-2.8738934994,39.4991607666],"type":"Point"}
}