{
  "type": "Feature",
  "properties": {
    "addr:full":"Ctra Cartagena, S/n Barracas Murcia 30840",
    "addr:housenumber":"s / n",
    "addr:postcode":"30840",
    "addr:street":"Ctra Cartagena",
    "iso:country":"ES",
    "sg:address":"Ctra Cartagena, S/n",
    "sg:city":"Barracas",
    "sg:orig_category":"Confecci\u00d3n De Zapatos",
    "sg:phone":"+34 968 63 10 62",
    "sg:postcode":"30840",
    "sg:province":"Murcia",
    "wof:name":"Perti\u00f1ez Salinas Jose Miguel",
    "wof:placetype":"venue"
},
  "geometry": {"coordinates":[-1.4241490364,37.8507995605],"type":"Point"}
}