{
  "type": "Feature",
  "properties": {
    "iso:country":"ES",
    "sg:address":"Carrer de Calvet, 70",
    "sg:city":"Barcelona",
    "sg:orig_category":"Empresarios",
    "sg:phone":"+34 932 00 73 39",
    "sg:postcode":"08021",
    "sg:province":"Barcelona",
    "wof:name":"Marin Correa Manuel",
    "wof:placetype":"venue"
},
  "geometry": {"coordinates":[2.1415688992,41.3965148926],"type":"Point"}
}