{
  "type": "Feature",
  "properties": {
    "addr:full":"Calle de Zabaleta, 1 Donostia-san Sebastian Guip\u00f9zcoa 20002",
    "addr:housenumber":"1",
    "addr:postcode":"20002",
    "addr:street":"Calle De Zabaleta",
    "iso:country":"ES",
    "sg:address":"Calle de Zabaleta, 1",
    "sg:city":"Donostia-san Sebastian",
    "sg:orig_category":"Molduras, Junquillos, Listones Y Molduras Perforadas",
    "sg:phone":"+34 943 29 36 12",
    "sg:postcode":"20002",
    "sg:province":"Guip\u00f9zcoa",
    "wof:name":"Alejandro Luis Perez Aguilar Y Otros C.b.",
    "wof:placetype":"venue"
},
  "geometry": {"coordinates":[-1.9771715403,43.3224716187],"type":"Point"}
}