{
  "type": "Feature",
  "properties": {
    "addr:full":"Carrer de Ramon Llull, 62 Premia Mar Barcelona 08330",
    "addr:housenumber":"62",
    "addr:postcode":"08330",
    "addr:street":"Carrer De Ramon Llull",
    "iso:country":"ES",
    "sg:address":"Carrer de Ramon Llull, 62",
    "sg:city":"Premia Mar",
    "sg:orig_category":"Arquitectos",
    "sg:phone":"+34 937 51 66 59",
    "sg:postcode":"08330",
    "sg:province":"Barcelona",
    "wof:name":"Nogues Fernandez Isaac",
    "wof:placetype":"venue"
},
  "geometry": {"coordinates":[2.3593211174,41.4952545166],"type":"Point"}
}