{
  "type": "Feature",
  "properties": {
    "iso:country":"ES",
    "sg:address":"Avda Mercado, S/n",
    "sg:city":"Beas Segura",
    "sg:orig_category":"Aceites Y Grasas Alimentarias (fabricaci\u00d3n, Al Por Mayor)",
    "sg:phone":"+34 953 45 80 20",
    "sg:postcode":"23280",
    "sg:province":"Ja\u00e9n",
    "wof:name":"Aprol Sierra Segura",
    "wof:placetype":"venue"
},
  "geometry": {"coordinates":[-2.8927047253,38.2522697449],"type":"Point"}
}