{
  "type": "Feature",
  "properties": {
    "addr:full":"Av Josep Fontcuberta, 104 Caldes Montbui Barcelona 08140",
    "addr:housenumber":"104",
    "addr:postcode":"08140",
    "addr:street":"Av Josep Fontcuberta;Montbui Barcelona",
    "iso:country":"ES",
    "sg:address":"Av Josep Fontcuberta, 104",
    "sg:city":"Caldes Montbui",
    "sg:orig_category":"Restaurantes",
    "sg:phone":"+34 938 62 65 17",
    "sg:postcode":"08140",
    "sg:province":"Barcelona",
    "wof:name":"Fernandez Gonzalez Matilde",
    "wof:placetype":"venue"
},
  "geometry": {"coordinates":[2.1705598831,41.6338806152],"type":"Point"}
}