{
  "type": "Feature",
  "properties": {
    "addr:full":"Urb C.r. Novo Sancti-petri, S/n Barrosa C\u00e1diz 11130",
    "addr:housenumber":"s / n",
    "addr:postcode":"11130",
    "addr:street":"Urb C.R. Novo Sancti-Petri;Barrosa Ca\u0301Diz",
    "iso:country":"ES",
    "sg:address":"Urb C.r. Novo Sancti-petri, S/n",
    "sg:city":"Barrosa",
    "sg:orig_category":"Inmobiliaria (agencias)",
    "sg:phone":"+34 956 49 24 23",
    "sg:postcode":"11130",
    "sg:province":"C\u00e1diz",
    "wof:name":"Mogarizas S.l.",
    "wof:placetype":"venue"
},
  "geometry": {"coordinates":[-6.1447038651,36.4212188721],"type":"Point"}
}