{
  "type": "Feature",
  "properties": {
    "addr:full":"Avda Navarra, 63 Errenteria Guip\u00f9zcoa 20100",
    "addr:housenumber":"63",
    "addr:postcode":"20100",
    "addr:street":"Avda Navarra;Guipu\u0300Zcoa",
    "iso:country":"ES",
    "sg:address":"Avda Navarra, 63",
    "sg:city":"Errenteria",
    "sg:orig_category":"Agencias De Viajes",
    "sg:phone":"+34 943 34 49 72",
    "sg:postcode":"20100",
    "sg:province":"Guip\u00f9zcoa",
    "sg:website":"www.marsans.es",
    "wof:name":"Viajes Marsans S.a.",
    "wof:placetype":"venue"
},
  "geometry": {"coordinates":[-1.9008959532,43.3147735596],"type":"Point"}
}