{
  "type": "Feature",
  "properties": {
    "iso:country":"ES",
    "sg:address":"Avda Guardia Civil, 160",
    "sg:city":"Tobarra",
    "sg:orig_category":"Mec\u00c1nico Del Autom\u00d3vil",
    "sg:phone":"+34 967 32 82 79",
    "sg:postcode":"02500",
    "sg:province":"Albacete",
    "wof:name":"Escudero Martinez Jose",
    "wof:placetype":"venue"
},
  "geometry": {"coordinates":[-1.6842210293,38.597038269],"type":"Point"}
}