{
  "type": "Feature",
  "properties": {
    "iso:country":"ES",
    "sg:address":"Calle de Domingo De Sautu, 42",
    "sg:city":"Murguia",
    "sg:orig_category":"Molduras, Junquillos, Listones Y Molduras Perforadas",
    "sg:phone":"+34 945 43 00 29",
    "sg:postcode":"01130",
    "sg:province":"\u00c1lava",
    "wof:name":"Santana Clemente Antonio",
    "wof:placetype":"venue"
},
  "geometry": {"coordinates":[-2.8331260681,42.9575958252],"type":"Point"}
}