{
  "type": "Feature",
  "properties": {
    "addr:full":"Avda Juan Xxiii, 9 Huesca Huesca 22003",
    "addr:housenumber":"9",
    "addr:postcode":"22003",
    "addr:street":"Avda Juan Xxiii",
    "iso:country":"ES",
    "sg:address":"Avda Juan Xxiii, 9",
    "sg:city":"Huesca",
    "sg:orig_category":"Pod\u00d3logos: Pedicuros",
    "sg:phone":"+34 974 21 34 92",
    "sg:postcode":"22003",
    "sg:province":"Huesca",
    "wof:name":"Torres Ricart Juan Antonio",
    "wof:placetype":"venue"
},
  "geometry": {"coordinates":[-0.4083139896,42.1365661621],"type":"Point"}
}