{
  "type": "Feature",
  "properties": {
    "addr:full":"Avda Americas (las), S/n Playa Americas Santa Cruz De Tenerife 38660",
    "addr:housenumber":"/ n",
    "addr:postcode":"38660",
    "addr:street":"Avda Americas Las S;Americas",
    "iso:country":"ES",
    "sg:address":"Avda Americas (las), S/n",
    "sg:city":"Playa Americas",
    "sg:orig_category":"Ropa Para Se\u00d1oras Y Caballeros (al Por Menor)",
    "sg:phone":"+34 922 75 14 13",
    "sg:postcode":"38660",
    "sg:province":"Santa Cruz De Tenerife",
    "sg:website":"www.timberland.com",
    "wof:name":"Maria S.l.",
    "wof:placetype":"venue"
},
  "geometry": {"coordinates":[-16.7317714691,28.0760765076],"type":"Point"}
}