{
  "type": "Feature",
  "properties": {
    "addr:full":"Calle de Juliana Merino, 13 Alcala Henares Madrid 28804",
    "addr:housenumber":"13",
    "addr:postcode":"28804",
    "addr:street":"Calle De Juliana Merino",
    "iso:country":"ES",
    "sg:address":"Calle de Juliana Merino, 13",
    "sg:city":"Alcala Henares",
    "sg:orig_category":"Ebanister\u00cda",
    "sg:phone":"+34 918 88 45 46",
    "sg:postcode":"28804",
    "sg:province":"Madrid",
    "wof:name":"Loeches Sanchez Joaquin",
    "wof:placetype":"venue"
},
  "geometry": {"coordinates":[-3.3582229614,40.4827957153],"type":"Point"}
}