{
  "type": "Feature",
  "properties": {
    "addr:full":"Cobertizo S Mtias, 5 Granada Granada 18010",
    "addr:housenumber":"5",
    "addr:postcode":"18010",
    "addr:street":"Cobertizo;Mtias",
    "iso:country":"ES",
    "sg:address":"Cobertizo S Mtias, 5",
    "sg:city":"Granada",
    "sg:orig_category":"Abogados",
    "sg:phone":"+34 958 22 41 70",
    "sg:postcode":"18010",
    "sg:province":"Granada",
    "wof:name":"Cruz Valdivieso Jose",
    "wof:placetype":"venue"
},
  "geometry": {"coordinates":[-3.5932240486,37.1796684265],"type":"Point"}
}