{
  "type": "Feature",
  "properties": {
    "iso:country":"ES",
    "sg:address":"Calle de Tariquejo, 3",
    "sg:city":"Huelva",
    "sg:orig_category":"Peluquer\u00cdas, Peluquer\u00cda Mixta",
    "sg:phone":"+34 959 23 12 71",
    "sg:postcode":"21006",
    "sg:province":"Huelva",
    "wof:name":"Montes Moreno Isabel",
    "wof:placetype":"venue"
},
  "geometry": {"coordinates":[-6.9376769066,37.2607078552],"type":"Point"}
}