{
  "type": "Feature",
  "properties": {
    "iso:country":"ES",
    "sg:address":"Carr Pere Frances, 46",
    "sg:city":"Eivissa",
    "sg:orig_category":"Peluquer\u00cdas, Peluquer\u00cda Mixta",
    "sg:phone":"+34 971 31 30 09",
    "sg:postcode":"07800",
    "sg:province":"Islas Baleares",
    "wof:name":"Calbet Saez Nieves",
    "wof:placetype":"venue"
},
  "geometry": {"coordinates":[1.4318809509,38.9126319885],"type":"Point"}
}