{
  "type": "Feature",
  "properties": {
    "iso:country":"ES",
    "sg:address":"Calle de Mu\u00d1oz Torrero, 129",
    "sg:city":"Azuaga",
    "sg:classifiers":[
        {
            "category":"Taxi",
            "type":"Transportation"
        }
    ],
    "sg:phone":"+34 924 89 04 18",
    "sg:postcode":"06920",
    "sg:province":"Badajoz",
    "wof:name":"Guerrero Garcia Rafael",
    "wof:placetype":"venue"
},
  "geometry": {"coordinates":[-5.6847038269,38.2641868591],"type":"Point"}
}