{
  "type": "Feature",
  "properties": {
    "addr:full":"Ctra Coria, S/n Gelves Sevilla 41120",
    "addr:housenumber":"s / n",
    "addr:postcode":"41120",
    "addr:street":"Ctra Coria",
    "iso:country":"ES",
    "sg:address":"Ctra Coria, S/n",
    "sg:city":"Gelves",
    "sg:orig_category":"M\u00c9dicos: Fisioterapia Y Rehabilitaci\u00d3n",
    "sg:phone":"+34 955 95 04 58",
    "sg:postcode":"41120",
    "sg:province":"Sevilla",
    "wof:name":"Castello De Mora Fernando Enrique",
    "wof:placetype":"venue"
},
  "geometry": {"coordinates":[-6.0250048637,37.3348274231],"type":"Point"}
}