{
  "type": "Feature",
  "properties": {
    "addr:full":"Psaj Mendivil, 3 Malaga M\u00e1laga 29002",
    "addr:housenumber":"3",
    "addr:postcode":"29002",
    "addr:street":"Psaj Mendivil;Ma\u0301Laga",
    "iso:country":"ES",
    "sg:address":"Psaj Mendivil, 3",
    "sg:city":"Malaga",
    "sg:orig_category":"Formaci\u00d3n Continuada (variada)",
    "sg:phone":"+34 952 34 28 98",
    "sg:postcode":"29002",
    "sg:province":"M\u00e1laga",
    "wof:name":"Criado Romero Jose Manuel",
    "wof:placetype":"venue"
},
  "geometry": {"coordinates":[-4.4309749603,36.7129745483],"type":"Point"}
}