{
  "type": "Feature",
  "properties": {
    "iso:country":"ES",
    "sg:address":"Calle de Madre Del Buen Consejo, 3",
    "sg:city":"Torremolinos",
    "sg:orig_category":"Ropa Para Caballeros (al Por Menor)",
    "sg:phone":"+34 952 37 59 05",
    "sg:postcode":"29620",
    "sg:province":"M\u00e1laga",
    "wof:name":"Loguipiel Sl",
    "wof:placetype":"venue"
},
  "geometry": {"coordinates":[-4.5006408691,36.6247367859],"type":"Point"}
}