{
  "type": "Feature",
  "properties": {
    "iso:country":"ES",
    "sg:address":"Avda Zaragoza (de), 6",
    "sg:city":"Alagon",
    "sg:orig_category":"Centros M\u00c9dicos Y Sociales, Dispensarios",
    "sg:phone":"+34 976 61 25 39",
    "sg:postcode":"50630",
    "sg:province":"Zaragoza",
    "wof:name":"Maz Mutua De Accidentes De Trabajo Y Enfermedades De La S.s. N 11",
    "wof:placetype":"venue"
},
  "geometry": {"coordinates":[-1.1183880568,41.7686195374],"type":"Point"}
}