{
  "type": "Feature",
  "properties": {
    "iso:country":"ES",
    "sg:address":"Carrer de Mallorca, 93",
    "sg:city":"Barcelona",
    "sg:orig_category":"Asociaciones Humanitarias, De Cooperaci\u00d3n, De Acci\u00d3n Social",
    "sg:phone":"+34 934 19 33 35",
    "sg:postcode":"08029",
    "sg:province":"Barcelona",
    "wof:name":"A.i.s. Servicios Laborales",
    "wof:placetype":"venue"
},
  "geometry": {"coordinates":[2.1514923573,41.3855438232],"type":"Point"}
}