{
  "type": "Feature",
  "properties": {
    "iso:country":"ES",
    "sg:address":"Carr Son Pocapaia, S/n",
    "sg:city":"Capdepera",
    "sg:orig_category":"Lavado, Limpieza De Veh\u00cdculos",
    "sg:phone":"+34 971 81 92 97",
    "sg:postcode":"07580",
    "sg:province":"Islas Baleares",
    "wof:name":"Autorapid Angel C.b.",
    "wof:placetype":"venue"
},
  "geometry": {"coordinates":[3.4392650127,39.7040367126],"type":"Point"}
}