{
  "type": "Feature",
  "properties": {
    "iso:country":"ES",
    "sg:address":"Calle de Jose Menendez Carre\u00d1o 'cuchichi', 3",
    "sg:city":"Corredoria",
    "sg:orig_category":"Peluquer\u00cdas, Peluquer\u00cda Mixta",
    "sg:phone":"+34 985 11 06 21",
    "sg:postcode":"33011",
    "sg:province":"Asturias",
    "wof:name":"Mu\u00f1iz Gonzalez Maria Del Pilar",
    "wof:placetype":"venue"
},
  "geometry": {"coordinates":[-5.8465900421,43.2702789307],"type":"Point"}
}