{
  "type": "Feature",
  "properties": {
    "iso:country":"ES",
    "sg:address":"Carrer de Joan Prim, 6",
    "sg:city":"Premia Mar",
    "sg:orig_category":"Estancos",
    "sg:phone":"+34 937 51 65 53",
    "sg:postcode":"08330",
    "sg:province":"Barcelona",
    "wof:name":"Hoyuelos Tarte Victoria",
    "wof:placetype":"venue"
},
  "geometry": {"coordinates":[2.3604550362,41.4901885986],"type":"Point"}
}