{
  "type": "Feature",
  "properties": {
    "iso:country":"ES",
    "sg:address":"Avgd L'estacio, 24",
    "sg:city":"Oropesa",
    "sg:orig_category":"Arquitectos",
    "sg:phone":"+34 964 31 03 45",
    "sg:postcode":"12594",
    "sg:province":"Castell\u00f3n",
    "wof:name":"Dominguez Arguello Fernando Adalberto",
    "wof:placetype":"venue"
},
  "geometry": {"coordinates":[0.1377850026,40.0926132202],"type":"Point"}
}