{
  "type": "Feature",
  "properties": {
    "addr:full":"Carrer de Sol (del), 8 Gata Gorgos Alicante 03740",
    "addr:housenumber":"8",
    "addr:postcode":"03740",
    "addr:street":"Carrer De Sol Del",
    "iso:country":"ES",
    "sg:address":"Carrer de Sol (del), 8",
    "sg:city":"Gata Gorgos",
    "sg:orig_category":"Reposter\u00cdas",
    "sg:phone":"+34 965 75 62 69",
    "sg:postcode":"03740",
    "sg:province":"Alicante",
    "wof:name":"Catala Llobell Jose Vicente",
    "wof:placetype":"venue"
},
  "geometry": {"coordinates":[0.0860169977,38.7735328674],"type":"Point"}
}