{
  "type": "Feature",
  "properties": {
    "iso:country":"ES",
    "sg:address":"Calle de Capitan Cortes, 11",
    "sg:city":"Madrid",
    "sg:orig_category":"Cine: Pel\u00cdculas Educativas, Industriales Y Publicitarias (producci\u00d3n)",
    "sg:phone":"+34 913 81 91 54",
    "sg:postcode":"28033",
    "sg:province":"Madrid",
    "wof:name":"Publibotto S.l.",
    "wof:placetype":"venue"
},
  "geometry": {"coordinates":[-3.6532196999,40.4764556885],"type":"Point"}
}