{
  "type": "Feature",
  "properties": {
    "addr:full":"Ctra Cardona, 14 Manresa Barcelona 08242",
    "addr:housenumber":"14",
    "addr:postcode":"08242",
    "addr:street":"Ctra Cardona",
    "iso:country":"ES",
    "sg:address":"Ctra Cardona, 14",
    "sg:city":"Manresa",
    "sg:orig_category":"Asociaciones, Organismos Culturales Y Socioeducativos",
    "sg:phone":"+34 938 72 21 53",
    "sg:postcode":"08242",
    "sg:province":"Barcelona",
    "wof:name":"Associacio Gent Gran De Manresa",
    "wof:placetype":"venue"
},
  "geometry": {"coordinates":[1.8217656612,41.7255630493],"type":"Point"}
}