{
  "type": "Feature",
  "properties": {
    "addr:full":"Calle de Mayor, 30 Alcorcon Madrid 28921",
    "addr:housenumber":"30",
    "addr:postcode":"28921",
    "addr:street":"Calle De Mayor",
    "iso:country":"ES",
    "sg:address":"Calle de Mayor, 30",
    "sg:city":"Alcorcon",
    "sg:orig_category":"\u00d3ptica: Instrumentos (fabricaci\u00d3n)",
    "sg:phone":"+34 916 44 07 49",
    "sg:postcode":"28921",
    "sg:province":"Madrid",
    "wof:name":"Optica Alcorcon S.l.",
    "wof:placetype":"venue"
},
  "geometry": {"coordinates":[-3.8276090622,40.3471717834],"type":"Point"}
}