{
  "type": "Feature",
  "properties": {
    "iso:country":"ES",
    "sg:address":"La Gloria, 10",
    "sg:city":"Nerja",
    "sg:orig_category":"Molduras, Junquillos, Listones Y Molduras Perforadas",
    "sg:phone":"+34 952 52 04 50",
    "sg:postcode":"29780",
    "sg:province":"M\u00e1laga",
    "wof:name":"Roumd Bar Redondo S.l.",
    "wof:placetype":"venue"
},
  "geometry": {"coordinates":[-3.8758161068,36.7469787598],"type":"Point"}
}