{
  "type": "Feature",
  "properties": {
    "addr:full":"Calle de San Martin, 6 Murguia \u00c1lava 01130",
    "addr:housenumber":"6",
    "addr:postcode":"01130",
    "addr:street":"Calle De San Martin;A\u0301Lava",
    "iso:country":"ES",
    "sg:address":"Calle de San Martin, 6",
    "sg:city":"Murguia",
    "sg:orig_category":"Fotograf\u00cda Y Cine: Aparatos, Pel\u00cdculas Y Accesorios (al Por Menor)",
    "sg:phone":"+34 945 46 26 25",
    "sg:postcode":"01130",
    "sg:province":"\u00c1lava",
    "wof:name":"Mendia Celaa Itziar",
    "wof:placetype":"venue"
},
  "geometry": {"coordinates":[-2.8198809624,42.9574623108],"type":"Point"}
}