{
  "type": "Feature",
  "properties": {
    "iso:country":"ES",
    "sg:address":"Carr Rabindranath Tagore, 15",
    "sg:city":"Salines",
    "sg:orig_category":"Transportes De Material De Construcci\u00d3n",
    "sg:phone":"+34 971 64 93 08",
    "sg:postcode":"07640",
    "sg:province":"Islas Baleares",
    "wof:name":"Transmas S. A.",
    "wof:placetype":"venue"
},
  "geometry": {"coordinates":[3.0519380569,39.3370323181],"type":"Point"}
}