{
  "type": "Feature",
  "properties": {
    "addr:full":"Calle de Alhondiga, 6 Granada Granada 18001",
    "addr:housenumber":"6",
    "addr:postcode":"18001",
    "addr:street":"Calle De Alhondiga",
    "iso:country":"ES",
    "sg:address":"Calle de Alhondiga, 6",
    "sg:city":"Granada",
    "sg:orig_category":"Arquitectos",
    "sg:phone":"+34 958 52 33 97",
    "sg:postcode":"18001",
    "sg:province":"Granada",
    "wof:name":"Vera Romero Casimiro",
    "wof:placetype":"venue"
},
  "geometry": {"coordinates":[-3.6005909443,37.1738128662],"type":"Point"}
}