{
  "type": "Feature",
  "properties": {
    "addr:full":"Rua Fonseca (de), 2 Santiago De Compostela La Coru\u00f1a 15704",
    "addr:housenumber":"2",
    "addr:postcode":"15704",
    "addr:street":"Rua Fonseca De;Corun\u0303A",
    "iso:country":"ES",
    "sg:address":"Rua Fonseca (de), 2",
    "sg:city":"Santiago De Compostela",
    "sg:orig_category":"Dorados, Plater\u00cda (orfebrer\u00cda)",
    "sg:phone":"+34 981 58 33 63",
    "sg:postcode":"15704",
    "sg:province":"La Coru\u00f1a",
    "wof:name":"Plateria Fonseca S.c.",
    "wof:placetype":"venue"
},
  "geometry": {"coordinates":[-8.5457849503,42.8789253235],"type":"Point"}
}