{
  "type": "Feature",
  "properties": {
    "addr:full":"Ctra Barrosa (de La), 40 Chiclana De La Frontera C\u00e1diz 11130",
    "addr:housenumber":"40",
    "addr:postcode":"11130",
    "addr:street":"Ctra Barrosa De La",
    "iso:country":"ES",
    "sg:address":"Ctra Barrosa (de La), 40",
    "sg:city":"Chiclana De La Frontera",
    "sg:orig_category":"Discapacitados",
    "sg:phone":"+34 956 53 78 71",
    "sg:postcode":"11130",
    "sg:province":"C\u00e1diz",
    "wof:name":"Asodown",
    "wof:placetype":"venue"
},
  "geometry": {"coordinates":[-6.1672811508,36.4001846313],"type":"Point"}
}