{
  "type": "Feature",
  "properties": {
    "addr:full":"Ctra Olmedo, S/n Cuellar Segovia 40200",
    "addr:housenumber":"s / n",
    "addr:postcode":"40200",
    "addr:street":"Ctra Olmedo",
    "iso:country":"ES",
    "sg:address":"Ctra Olmedo, S/n",
    "sg:city":"Cuellar",
    "sg:orig_category":"Material Y Herramientas Agr\u00cdcolas",
    "sg:phone":"+34 921 14 33 24",
    "sg:postcode":"40200",
    "sg:province":"Segovia",
    "wof:name":"Quevedo Senovilla Pablo",
    "wof:placetype":"venue"
},
  "geometry": {"coordinates":[-4.3591589928,41.4059486389],"type":"Point"}
}