{
  "type": "Feature",
  "properties": {
    "addr:full":"Calle de Islas Aleutianas, 9 Madrid Madrid 28035",
    "addr:housenumber":"9",
    "addr:postcode":"madrid;28035",
    "addr:street":"Calle De Islas Aleutianas",
    "iso:country":"ES",
    "sg:address":"Calle de Islas Aleutianas, 9",
    "sg:city":"Madrid",
    "sg:orig_category":"M\u00c9dicos: An\u00c1lisis Cl\u00cdnicos",
    "sg:phone":"+34 913 16 98 64",
    "sg:postcode":"28035",
    "sg:province":"Madrid",
    "wof:name":"Gonzalez Garcia Maria Del Carmen",
    "wof:placetype":"venue"
},
  "geometry": {"coordinates":[-3.7293629646,40.4755172729],"type":"Point"}
}