{
  "type": "Feature",
  "properties": {
    "addr:full":"Calle de Almendro, 59 Puebla Alfinden Zaragoza 50171",
    "addr:housenumber":"59",
    "addr:postcode":"50171",
    "addr:street":"Calle De Almendro;Alfinden",
    "iso:country":"ES",
    "sg:address":"Calle de Almendro, 59",
    "sg:city":"Puebla Alfinden",
    "sg:orig_category":"Electricidad: Equipos Industriales, Componentes (fabricaci\u00d3n)",
    "sg:phone":"+34 976 10 77 08",
    "sg:postcode":"50171",
    "sg:province":"Zaragoza",
    "wof:name":"Kepar Electronica S.a.",
    "wof:placetype":"venue"
},
  "geometry": {"coordinates":[-0.7638884783,41.6440162659],"type":"Point"}
}