{
  "type": "Feature",
  "properties": {
    "addr:full":"Calle de Ciudad De Lugo, 31 Coru\u00d1a La Coru\u00f1a 15004",
    "addr:housenumber":"31",
    "addr:postcode":"15004",
    "addr:street":"Calle De Ciudad De Lugo;La Corun\u0303A",
    "iso:country":"ES",
    "sg:address":"Calle de Ciudad De Lugo, 31",
    "sg:city":"Coru\u00d1a",
    "sg:orig_category":"Agencias Y Agentes Comerciales, Representantes",
    "sg:phone":"+34 981 26 95 54",
    "sg:postcode":"15004",
    "sg:province":"La Coru\u00f1a",
    "wof:name":"Mussons Martinez Jaime",
    "wof:placetype":"venue"
},
  "geometry": {"coordinates":[-8.4115686417,43.3652801514],"type":"Point"}
}