{
  "type": "Feature",
  "properties": {
    "addr:full":"Calle de E, 41 Pol. Malpica Zaragoza 50057",
    "addr:housenumber":"41",
    "addr:postcode":"50057",
    "addr:street":"Calle De E;Pol. Malpica",
    "iso:country":"ES",
    "sg:address":"Calle de E, 41",
    "sg:city":"Pol. Malpica",
    "sg:orig_category":"Agentes, Concesionarios Y Sucursales De Veh\u00cdculos",
    "sg:phone":"+34 976 45 73 00",
    "sg:postcode":"50057",
    "sg:province":"Zaragoza",
    "sg:website":"www.miju.es",
    "wof:name":"Miju S.a.",
    "wof:placetype":"venue"
},
  "geometry": {"coordinates":[-0.8765661716,41.6563491821],"type":"Point"}
}