{
  "type": "Feature",
  "properties": {
    "addr:full":"Praz Abastos (de), 1 Ourense Ourense 32002",
    "addr:postcode":"32002",
    "iso:country":"ES",
    "sg:address":"Praz Abastos (de), 1",
    "sg:city":"Ourense",
    "sg:orig_category":"Cuchiller\u00cda (al Por Menor)",
    "sg:phone":"+34 988 22 77 43",
    "sg:postcode":"32002",
    "sg:province":"Ourense",
    "wof:name":"Suarez Alvarez Manuel",
    "wof:placetype":"venue"
},
  "geometry": {"coordinates":[-7.8661170006,42.3389396667],"type":"Point"}
}