{
  "type": "Feature",
  "properties": {
    "iso:country":"ES",
    "sg:address":"Avda Cristo De La Expiracion, S/n",
    "sg:city":"Sevilla",
    "sg:orig_category":"Arreglo, Instalaci\u00d3n Y Acondicionamiento De Talleres",
    "sg:phone":"+34 954 90 45 49",
    "sg:postcode":"41001",
    "sg:province":"Sevilla",
    "wof:name":"Tandem Asociacion",
    "wof:placetype":"venue"
},
  "geometry": {"coordinates":[-6.0035500526,37.3906135559],"type":"Point"}
}