{
  "type": "Feature",
  "properties": {
    "addr:full":"Calle de Miguel De Unamuno, 18 Alcazar S. Juan Ciudad Real 13600",
    "addr:housenumber":"18",
    "addr:postcode":"13600",
    "addr:street":"Calle De Miguel De Unamuno;Alcazar S. Juan Ciudad Real",
    "iso:country":"ES",
    "sg:address":"Calle de Miguel De Unamuno, 18",
    "sg:city":"Alcazar S. Juan",
    "sg:orig_category":"Sociedades, Compa\u00d1\u00cdas Aseguradoras",
    "sg:phone":"+34 926 54 09 99",
    "sg:postcode":"13600",
    "sg:province":"Ciudad Real",
    "wof:name":"Vic-pac Mediacion S.l.",
    "wof:placetype":"venue"
},
  "geometry": {"coordinates":[-3.2069690228,39.3924865723],"type":"Point"}
}