{
  "type": "Feature",
  "properties": {
    "addr:full":"Pase Marina Espa\u00d1ola (de La), 6 Ceuta Ceuta 51001",
    "addr:postcode":"51001",
    "iso:country":"ES",
    "sg:address":"Pase Marina Espa\u00d1ola (de La), 6",
    "sg:city":"Ceuta",
    "sg:orig_category":"Comercio De Piezas De Recambio Y De Accesorios De Veh\u00cdculos, Veh\u00cdculos Industriales",
    "sg:phone":"+34 956 51 25 10",
    "sg:postcode":"51001",
    "sg:province":"Ceuta",
    "wof:name":"Auto-repuestos S. L.",
    "wof:placetype":"venue"
},
  "geometry": {"coordinates":[-5.3302302361,35.8947601318],"type":"Point"}
}