{
  "type": "Feature",
  "properties": {
    "iso:country":"ES",
    "sg:address":"Calle de Barria, 1",
    "sg:city":"Arenas -areeta",
    "sg:orig_category":"Supermercados Y Hipermercados",
    "sg:phone":"+34 944 80 11 38",
    "sg:postcode":"48930",
    "sg:province":"Vizcaya",
    "wof:name":"Supermercado Ercoreca S.a.",
    "wof:placetype":"venue"
},
  "geometry": {"coordinates":[-3.0146811008,43.3239021301],"type":"Point"}
}