{
  "type": "Feature",
  "properties": {
    "addr:full":"Cmno Romanos (de Los), 56 Alcantarilla Murcia 30820",
    "addr:housenumber":"56",
    "addr:postcode":"30820",
    "addr:street":"Cmno Romanos De Los",
    "iso:country":"ES",
    "sg:address":"Cmno Romanos (de Los), 56",
    "sg:city":"Alcantarilla",
    "sg:orig_category":"Fabricaci\u00d3n, Importaci\u00d3n De L\u00c1mparas Y Bombillas",
    "sg:phone":"+34 968 89 37 14",
    "sg:postcode":"30820",
    "sg:province":"Murcia",
    "wof:name":"Iniesta Perez Jose Juan",
    "wof:placetype":"venue"
},
  "geometry": {"coordinates":[-1.2179280519,37.9682998657],"type":"Point"}
}