{
  "type": "Feature",
  "properties": {
    "iso:country":"ES",
    "sg:address":"Carrer de Clivillers, 15",
    "sg:city":"Olot",
    "sg:orig_category":"Confecci\u00d3n De Trajes Para Se\u00d1oras",
    "sg:phone":"+34 972 26 12 28",
    "sg:postcode":"17800",
    "sg:province":"Girona",
    "wof:name":"Su\u00f1e Corominas Carmen",
    "wof:placetype":"venue"
},
  "geometry": {"coordinates":[2.4904909134,42.1818771362],"type":"Point"}
}