{
  "type": "Feature",
  "properties": {
    "addr:full":"Avda Valladolid, 44 Tudela Duero Valladolid 47320",
    "addr:housenumber":"44;duero",
    "addr:postcode":"47320",
    "addr:street":"Avda Valladolid",
    "iso:country":"ES",
    "sg:address":"Avda Valladolid, 44",
    "sg:city":"Tudela Duero",
    "sg:orig_category":"M\u00c1rmoles, Granitos Y Piedras Naturales",
    "sg:phone":"+34 983 52 26 64",
    "sg:postcode":"47320",
    "sg:province":"Valladolid",
    "wof:name":"Marmoles Tudela De Duero S.l.l",
    "wof:placetype":"venue"
},
  "geometry": {"coordinates":[-4.5841112137,41.5874481201],"type":"Point"}
}