{
  "type": "Feature",
  "properties": {
    "iso:country":"ES",
    "sg:address":"Ctra Murcia, Km. 0174,5",
    "sg:city":"Baza",
    "sg:orig_category":"Agentes, Concesionarios Y Sucursales De Veh\u00cdculos",
    "sg:phone":"+34 958 70 30 93",
    "sg:postcode":"18800",
    "sg:province":"Granada",
    "wof:name":"Molina Perez Francisco",
    "wof:placetype":"venue"
},
  "geometry": {"coordinates":[-2.7616488934,37.4945487976],"type":"Point"}
}