{
  "type": "Feature",
  "properties": {
    "addr:full":"Carrer de Bonavista, 61 S. Just Desvern Barcelona 08960",
    "addr:housenumber":"61",
    "addr:postcode":"08960",
    "addr:street":"Carrer De Bonavista",
    "iso:country":"ES",
    "sg:address":"Carrer de Bonavista, 61",
    "sg:city":"S. Just Desvern",
    "sg:orig_category":"Farmacias",
    "sg:phone":"+34 933 71 12 88",
    "sg:postcode":"08960",
    "sg:province":"Barcelona",
    "wof:name":"Arderiu Solsona Manuela",
    "wof:placetype":"venue"
},
  "geometry": {"coordinates":[2.0772686005,41.3832626343],"type":"Point"}
}