{
  "type": "Feature",
  "properties": {
    "iso:country":"ES",
    "sg:address":"Calle de Venezuela, 2",
    "sg:city":"Sada",
    "sg:orig_category":"Bisuter\u00cda, Joyer\u00cda, Relojer\u00cda (al Por Menor)",
    "sg:phone":"+34 981 62 39 04",
    "sg:postcode":"15160",
    "sg:province":"La Coru\u00f1a",
    "wof:name":"Pati\u00f1o Ya\u00f1ez Jose Manuel",
    "wof:placetype":"venue"
},
  "geometry": {"coordinates":[-8.2528591156,43.3493499756],"type":"Point"}
}