{
  "type": "Feature",
  "properties": {
    "addr:full":"Calle de Juan De Valladolid, 13 Valladolid Valladolid 47014",
    "addr:housenumber":"13",
    "addr:postcode":"47014",
    "addr:street":"Calle De Juan De Valladolid",
    "iso:country":"ES",
    "sg:address":"Calle de Juan De Valladolid, 13",
    "sg:city":"Valladolid",
    "sg:orig_category":"Impuestos, Tesoro P\u00dablico",
    "sg:phone":"+34 983 37 45 53",
    "sg:postcode":"47014",
    "sg:province":"Valladolid",
    "wof:name":"Sanz Valdezate Buenaventura",
    "wof:placetype":"venue"
},
  "geometry": {"coordinates":[-4.7580881119,41.6388168335],"type":"Point"}
}