{
  "type": "Feature",
  "properties": {
    "iso:country":"ES",
    "sg:address":"Plaz Corredera, 18",
    "sg:city":"Hervas",
    "sg:orig_category":"Ropa Para Se\u00d1oras Y Caballeros (al Por Menor)",
    "sg:phone":"+34 927 48 10 19",
    "sg:postcode":"10700",
    "sg:province":"C\u00e1ceres",
    "wof:name":"Lumeras Comendador Constancio",
    "wof:placetype":"venue"
},
  "geometry": {"coordinates":[-5.863948822,40.2720451355],"type":"Point"}
}