{
  "type": "Feature",
  "properties": {
    "addr:full":"Calle de Duquesa De La Victoria, 17 Logro\u00f1o La Rioja 26003",
    "addr:housenumber":"17",
    "addr:postcode":"26003",
    "addr:street":"Calle De Duquesa De La Victoria;Rioja",
    "iso:country":"ES",
    "sg:address":"Calle de Duquesa De La Victoria, 17",
    "sg:city":"Logro\u00f1o",
    "sg:orig_category":"Estancos",
    "sg:phone":"+34 941 24 42 48",
    "sg:postcode":"26003",
    "sg:province":"La Rioja",
    "wof:name":"Hierro Saez Ernesto",
    "wof:placetype":"venue"
},
  "geometry": {"coordinates":[-2.4415221214,42.4650917053],"type":"Point"}
}