{
  "type": "Feature",
  "properties": {
    "iso:country":"ES",
    "sg:address":"Avda Escaleritas, 43",
    "sg:city":"Palmas De Gran Canaria",
    "sg:orig_category":"Dietistas",
    "sg:phone":"+34 928 25 15 05",
    "sg:postcode":"35011",
    "sg:province":"Las Palmas",
    "wof:name":"Molina Alvarez Doris Julieta",
    "wof:placetype":"venue"
},
  "geometry": {"coordinates":[-15.4362468719,28.1216945648],"type":"Point"}
}