{
  "type": "Feature",
  "properties": {
    "iso:country":"ES",
    "sg:address":"Av Pompeu Fabra (de), 12",
    "sg:city":"Torredembarra",
    "sg:orig_category":"Ropa De Trabajo Y Profesionales (fabricaci\u00d3n, Al Por Mayor)",
    "sg:phone":"+34 977 64 56 84",
    "sg:postcode":"43830",
    "sg:province":"Tarragona",
    "wof:name":"Artex Torredembarra C.b.",
    "wof:placetype":"venue"
},
  "geometry": {"coordinates":[1.4079101086,41.1456489563],"type":"Point"}
}