{
  "type": "Feature",
  "properties": {
    "iso:country":"ES",
    "sg:address":"Ptge Farinera Teixidor, 8",
    "sg:city":"Girona",
    "sg:orig_category":"Peluquer\u00cdas",
    "sg:phone":"+34 972 41 24 82",
    "sg:postcode":"17005",
    "sg:province":"Girona",
    "wof:name":"Pou Ventura Albert",
    "wof:placetype":"venue"
},
  "geometry": {"coordinates":[2.8158829212,41.9816093445],"type":"Point"}
}