{
  "type": "Feature",
  "properties": {
    "addr:full":"Carrer de Pica\u00d1ol, 3 Sabadell Barcelona 08208",
    "addr:housenumber":"3",
    "addr:postcode":"08208",
    "addr:street":"Carrer De Pican\u0303Ol",
    "iso:country":"ES",
    "sg:address":"Carrer de Pica\u00d1ol, 3",
    "sg:city":"Sabadell",
    "sg:orig_category":"Promotores Constructores",
    "sg:phone":"+34 937 26 41 23",
    "sg:postcode":"08208",
    "sg:province":"Barcelona",
    "wof:name":"Frank-font Construcciones S.a.",
    "wof:placetype":"venue"
},
  "geometry": {"coordinates":[2.1028079987,41.5540084839],"type":"Point"}
}