{
  "type": "Feature",
  "properties": {
    "addr:full":"Av Joan Fuster, 28 Rotes Alicante 03700",
    "addr:housenumber":"28",
    "addr:postcode":"03700",
    "addr:street":"Av Joan Fuster",
    "iso:country":"ES",
    "sg:address":"Av Joan Fuster, 28",
    "sg:city":"Rotes",
    "sg:orig_category":"Bancos",
    "sg:phone":"+34 965 78 14 98",
    "sg:postcode":"03700",
    "sg:province":"Alicante",
    "wof:name":"Banc Sabadell S.a.",
    "wof:placetype":"venue"
},
  "geometry": {"coordinates":[0.1039630026,38.8354949951],"type":"Point"}
}