{
  "type": "Feature",
  "properties": {
    "iso:country":"ES",
    "sg:address":"Rua Pizarro, 29",
    "sg:city":"Vigo",
    "sg:orig_category":"Suministros Para Hoteles",
    "sg:phone":"+34 986 41 60 55",
    "sg:postcode":"36204",
    "sg:province":"Pontevedra",
    "sg:website":"www.novofri.com",
    "wof:name":"Delegaciones Reunidas Novofri S. A.",
    "wof:placetype":"venue"
},
  "geometry": {"coordinates":[-8.715423584,42.2306747437],"type":"Point"}
}