{
  "type": "Feature",
  "properties": {
    "iso:country":"ES",
    "sg:address":"Rua A, Km. 0530,0",
    "sg:city":"Rante",
    "sg:orig_category":"Fabricaci\u00d3n De Ventanas",
    "sg:phone":"+34 988 36 30 57",
    "sg:postcode":"32910",
    "sg:province":"Ourense",
    "wof:name":"Orensana De Acustica S.l.",
    "wof:placetype":"venue"
},
  "geometry": {"coordinates":[-7.8773641586,42.2747917175],"type":"Point"}
}