{
  "type": "Feature",
  "properties": {
    "addr:full":"Calle de Serranillos, 17 Carranque Toledo 45216",
    "addr:housenumber":"17",
    "addr:postcode":"45216",
    "addr:street":"Calle De Serranillos",
    "iso:country":"ES",
    "sg:address":"Calle de Serranillos, 17",
    "sg:city":"Carranque",
    "sg:orig_category":"Cajas Para Embalar",
    "sg:phone":"+34 925 54 41 12",
    "sg:postcode":"45216",
    "sg:province":"Toledo",
    "sg:website":"www.cajarural.es",
    "wof:name":"Caja Rural Provincial De Toledo",
    "wof:placetype":"venue"
},
  "geometry": {"coordinates":[-3.8974690437,40.1705207825],"type":"Point"}
}