{
  "type": "Feature",
  "properties": {
    "addr:full":"Av. Pueblo Nuevo, 79 Alginet Valencia 46230",
    "addr:housenumber":"79",
    "addr:postcode":"46230",
    "addr:street":"Av. Pueblo Nuevo",
    "iso:country":"ES",
    "sg:address":"Av. Pueblo Nuevo, 79",
    "sg:city":"Alginet",
    "sg:orig_category":"Contenedores (mercanc\u00cdas)",
    "sg:phone":"+34 961 75 11 95",
    "sg:postcode":"46230",
    "sg:province":"Valencia",
    "wof:name":"Signes Escutia Salvador",
    "wof:placetype":"venue"
},
  "geometry": {"coordinates":[-0.470043987,39.2614898682],"type":"Point"}
}