{
  "type": "Feature",
  "properties": {
    "addr:full":"Plaza Bide-onera Barakaldo Vizcaya 48902",
    "addr:postcode":"48902",
    "iso:country":"ES",
    "sg:address":"Plaza Bide-onera",
    "sg:city":"Barakaldo",
    "sg:orig_category":"Tribunales, Administraci\u00d3n De Justicia",
    "sg:phone":"+34 944 00 10 00",
    "sg:postcode":"48902",
    "sg:province":"Vizcaya",
    "wof:name":"Departamento De Justicia, Empleo Y Seguridad Social Del Gobierno Vasco",
    "wof:placetype":"venue"
},
  "geometry": {"coordinates":[-2.988394022,43.2946853638],"type":"Point"}
}