{
  "type": "Feature",
  "properties": {
    "addr:full":"Calle de Danza Invisible, 401 Torremolinos M\u00e1laga 29620",
    "addr:housenumber":"401",
    "addr:postcode":"29620",
    "addr:street":"Calle De Danza Invisible;Ma\u0301Laga",
    "iso:country":"ES",
    "sg:address":"Calle de Danza Invisible, 401",
    "sg:city":"Torremolinos",
    "sg:orig_category":"Institutos De Belleza",
    "sg:phone":"+34 952 38 18 24",
    "sg:postcode":"29620",
    "sg:province":"M\u00e1laga",
    "wof:name":"Linna Y Pilar S.l.",
    "wof:placetype":"venue"
},
  "geometry": {"coordinates":[-4.4983010292,36.6212615967],"type":"Point"}
}