{
  "type": "Feature",
  "properties": {
    "addr:full":"Calle de Orbon, 4 Gijon Asturias 33204",
    "addr:housenumber":"4",
    "addr:postcode":"33204",
    "addr:street":"Calle De Orbon",
    "iso:country":"ES",
    "sg:address":"Calle de Orbon, 4",
    "sg:city":"Gijon",
    "sg:orig_category":"Promotores Constructores",
    "sg:phone":"+34 985 13 38 15",
    "sg:postcode":"33204",
    "sg:province":"Asturias",
    "wof:name":"Sapro Sociedad Asturiana De Promocion Sl",
    "wof:placetype":"venue"
},
  "geometry": {"coordinates":[-5.6408410072,43.5326194763],"type":"Point"}
}