{
  "type": "Feature",
  "properties": {
    "addr:full":"Calle de Oro, 53 Valladolid Valladolid 47012",
    "addr:housenumber":"53",
    "addr:postcode":"47012",
    "addr:street":"Calle De Oro",
    "iso:country":"ES",
    "sg:address":"Calle de Oro, 53",
    "sg:city":"Valladolid",
    "sg:orig_category":"Maquinaria Para Industrias Diversas",
    "sg:phone":"+34 983 21 92 33",
    "sg:postcode":"47012",
    "sg:province":"Valladolid",
    "wof:name":"Tecnoclima S.l.",
    "wof:placetype":"venue"
},
  "geometry": {"coordinates":[-4.709528923,41.6145172119],"type":"Point"}
}