{
  "type": "Feature",
  "properties": {
    "iso:country":"ES",
    "sg:address":"Pg Dintre (de), 26",
    "sg:city":"Blanes",
    "sg:orig_category":"Florister\u00cdas",
    "sg:phone":"+34 972 33 15 59",
    "sg:postcode":"17300",
    "sg:province":"Girona",
    "wof:name":"Floristeria La Camelia S.c.",
    "wof:placetype":"venue"
},
  "geometry": {"coordinates":[2.7918419838,41.6738395691],"type":"Point"}
}