{
  "type": "Feature",
  "properties": {
    "iso:country":"ES",
    "sg:address":"Ctra. Nacional Ii, S/n",
    "sg:city":"Almadrones",
    "sg:orig_category":"Gr\u00daas, Montacargas Y Elevadores Para Astilleros",
    "sg:phone":"+34 901 10 39 01",
    "sg:postcode":"19414",
    "sg:province":"Guadalajara",
    "wof:name":"Jarbyn S.l.",
    "wof:placetype":"venue"
},
  "geometry": {"coordinates":[-2.7728290558,40.9009513855],"type":"Point"}
}