{
  "type": "Feature",
  "properties": {
    "addr:full":"Carrer de Abat Copons, 9 Vilafranca Penedes Barcelona 08720",
    "addr:housenumber":"9",
    "addr:postcode":"08720",
    "addr:street":"Carrer De Abat Copons;Penedes Barcelona",
    "iso:country":"ES",
    "sg:address":"Carrer de Abat Copons, 9",
    "sg:city":"Vilafranca Penedes",
    "sg:orig_category":"Estancos",
    "sg:phone":"+34 938 90 49 05",
    "sg:postcode":"08720",
    "sg:province":"Barcelona",
    "wof:name":"Rubio Colet Montserrat",
    "wof:placetype":"venue"
},
  "geometry": {"coordinates":[1.6934269667,41.3431167603],"type":"Point"}
}