{
  "type": "Feature",
  "properties": {
    "addr:full":"Calle de Menendez Pelayo, 8 Gijon Asturias 33202",
    "addr:housenumber":"8",
    "addr:postcode":"33202",
    "addr:street":"Calle De Menendez Pelayo",
    "iso:country":"ES",
    "sg:address":"Calle de Menendez Pelayo, 8",
    "sg:city":"Gijon",
    "sg:orig_category":"Ingeniero",
    "sg:phone":"+34 985 37 37 18",
    "sg:postcode":"33202",
    "sg:province":"Asturias",
    "wof:name":"Valdes Amado Ovidio",
    "wof:placetype":"venue"
},
  "geometry": {"coordinates":[-5.652659893,43.5381622314],"type":"Point"}
}