{
  "type": "Feature",
  "properties": {
    "iso:country":"ES",
    "sg:address":"Calle de Carcel, 10",
    "sg:city":"Fregenal Sierra",
    "sg:orig_category":"Electrodom\u00c9sticos (al Por Menor)",
    "sg:phone":"+34 924 70 10 55",
    "sg:postcode":"06340",
    "sg:province":"Badajoz",
    "wof:name":"Acevedo Guridi Domingo",
    "wof:placetype":"venue"
},
  "geometry": {"coordinates":[-6.6535458565,38.1694450378],"type":"Point"}
}