{
  "type": "Feature",
  "properties": {
    "iso:country":"ES",
    "sg:address":"Camino Matalagraja, S/n",
    "sg:city":"Lucena",
    "sg:orig_category":"Promotores Constructores",
    "sg:phone":"+34 957 33 47 11",
    "sg:postcode":"14900",
    "sg:province":"C\u00f3rdoba",
    "wof:name":"Cristobal Gamiz Luque E Hijos C.b.",
    "wof:placetype":"venue"
},
  "geometry": {"coordinates":[-4.4847187996,37.4150352478],"type":"Point"}
}