{
  "type": "Feature",
  "properties": {
    "iso:country":"ES",
    "sg:address":"Calle de Crisanta (do\u00d1a), 32",
    "sg:city":"Tomelloso",
    "sg:orig_category":"Papeler\u00cdas, Librer\u00cdas",
    "sg:phone":"+34 926 51 11 25",
    "sg:postcode":"13700",
    "sg:province":"Ciudad Real",
    "wof:name":"Losa Romero Pilar",
    "wof:placetype":"venue"
},
  "geometry": {"coordinates":[-3.0189297199,39.1573066711],"type":"Point"}
}