{
  "type": "Feature",
  "properties": {
    "iso:country":"ES",
    "sg:address":"Calle de Eras, 37",
    "sg:city":"Yuncos",
    "sg:orig_category":"Muebles",
    "sg:phone":"+34 925 55 77 64",
    "sg:postcode":"45210",
    "sg:province":"Toledo",
    "wof:name":"Gomez Garcia Luis",
    "wof:placetype":"venue"
},
  "geometry": {"coordinates":[-3.8773980141,40.0879745483],"type":"Point"}
}