{
  "type": "Feature",
  "properties": {
    "addr:full":"Avda Vega (de La), 8 Alcobendas Madrid 28108",
    "addr:postcode":"28108",
    "addr:street":"Avda Vega De La 8",
    "iso:country":"ES",
    "sg:address":"Avda Vega (de La), 8",
    "sg:city":"Alcobendas",
    "sg:orig_category":"Traductores",
    "sg:phone":"+34 916 61 47 09",
    "sg:postcode":"28108",
    "sg:province":"Madrid",
    "wof:name":"Arzola Moral Maria Asuncion",
    "wof:placetype":"venue"
},
  "geometry": {"coordinates":[-3.6296472549,40.5351104736],"type":"Point"}
}