{
  "type": "Feature",
  "properties": {
    "addr:full":"Calle de San Vicente, 3 Bilbao Vizcaya 48001",
    "addr:housenumber":"3",
    "addr:postcode":"48001",
    "addr:street":"Calle De San Vicente",
    "iso:country":"ES",
    "sg:address":"Calle de San Vicente, 3",
    "sg:city":"Bilbao",
    "sg:orig_category":"Abogados",
    "sg:phone":"+34 944 24 00 95",
    "sg:postcode":"48001",
    "sg:province":"Vizcaya",
    "wof:name":"Gaurko Abokatuak",
    "wof:placetype":"venue"
},
  "geometry": {"coordinates":[-2.9282569885,43.2639389038],"type":"Point"}
}