{
  "type": "Feature",
  "properties": {
    "addr:full":"Calle de Alfaro, 10 Santa Cruz De Tenerife Santa Cruz De Tenerife 38003",
    "addr:housenumber":"10",
    "addr:postcode":"38003",
    "addr:street":"Calle De Alfaro",
    "iso:country":"ES",
    "sg:address":"Calle de Alfaro, 10",
    "sg:city":"Santa Cruz De Tenerife",
    "sg:orig_category":"Inmobiliaria (agencias)",
    "sg:phone":"+34 922 27 56 39",
    "sg:postcode":"38003",
    "sg:province":"Santa Cruz De Tenerife",
    "sg:website":"www.csinmobiliaria.com",
    "wof:name":"Cs Y Asociados Gestion Inmobiliaria Insular Sl",
    "wof:placetype":"venue"
},
  "geometry": {"coordinates":[-16.254945755,28.4661769867],"type":"Point"}
}