{
  "type": "Feature",
  "properties": {
    "addr:full":"Avda Ermita, 1 Monterrubio De Armu\u00e7a Salamanca 37184",
    "addr:housenumber":"1",
    "addr:postcode":"37184",
    "addr:street":"Avda Ermita",
    "iso:country":"ES",
    "sg:address":"Avda Ermita, 1",
    "sg:city":"Monterrubio De Armu\u00e7a",
    "sg:orig_category":"M\u00c9dicos: Oftalmolog\u00cda",
    "sg:phone":"+34 923 20 30 35",
    "sg:postcode":"37184",
    "sg:province":"Salamanca",
    "wof:name":"Marcos Robles Manuel",
    "wof:placetype":"venue"
},
  "geometry": {"coordinates":[-5.6423549652,41.0266494751],"type":"Point"}
}