{
  "type": "Feature",
  "properties": {
    "iso:country":"ES",
    "sg:address":"Mercat Sant Josep, S/n",
    "sg:city":"Barcelona",
    "sg:orig_category":"Frutas, Legumbres Frescas Y Tempranas (al Por Menor)",
    "sg:phone":"+34 933 01 07 61",
    "sg:postcode":"08002",
    "sg:province":"Barcelona",
    "wof:name":"Alonso Carro Rafael",
    "wof:placetype":"venue"
},
  "geometry": {"coordinates":[2.1719443798,41.381942749],"type":"Point"}
}