{
  "type": "Feature",
  "properties": {
    "iso:country":"ES",
    "sg:address":"Calle de Doctor Regules, 11",
    "sg:city":"Ugena",
    "sg:orig_category":"Escayola Y Productos De Escayola (fabricaci\u00d3n, Al Por Mayor)",
    "sg:phone":"+34 925 53 31 98",
    "sg:postcode":"45217",
    "sg:province":"Toledo",
    "wof:name":"Decoraciones Laven S.l.",
    "wof:placetype":"venue"
},
  "geometry": {"coordinates":[-3.8782234192,40.156414032],"type":"Point"}
}