{
  "type": "Feature",
  "properties": {
    "iso:country":"ES",
    "sg:address":"A Reza, S/n",
    "sg:city":"Arnoia",
    "sg:orig_category":"Conservas De Legumbres (fabricaci\u00d3n, Al Por Mayor)",
    "sg:phone":"+34 988 47 23 99",
    "sg:postcode":"32417",
    "sg:province":"Ourense",
    "wof:name":"Cultivos Riveiro",
    "wof:placetype":"venue"
},
  "geometry": {"coordinates":[-8.1546087265,42.2673912048],"type":"Point"}
}