{
  "type": "Feature",
  "properties": {
    "iso:country":"ES",
    "sg:address":"Calle de General Primo De Rivera, 1",
    "sg:city":"Zafra",
    "sg:orig_category":"Doctores En Medicina",
    "sg:phone":"+34 924 55 04 79",
    "sg:postcode":"06300",
    "sg:province":"Badajoz",
    "wof:name":"Martin Alvarez Gabriel",
    "wof:placetype":"venue"
},
  "geometry": {"coordinates":[-6.4164328575,38.4261474609],"type":"Point"}
}