{
  "type": "Feature",
  "properties": {
    "addr:full":"Pase Sixto Celorrio, 17 Calatayud Zaragoza 50300",
    "addr:housenumber":"17",
    "addr:postcode":"50300",
    "addr:street":"Sixto Celorrio",
    "iso:country":"ES",
    "sg:address":"Pase Sixto Celorrio, 17",
    "sg:city":"Calatayud",
    "sg:orig_category":"Cajas De Ahorro",
    "sg:phone":"+34 976 88 25 77",
    "sg:postcode":"50300",
    "sg:province":"Zaragoza",
    "wof:name":"Caja De Ahorros Y Monte De Piedad De Zaragoza Aragon Y Rioja",
    "wof:placetype":"venue"
},
  "geometry": {"coordinates":[-1.6412539482,41.3475952148],"type":"Point"}
}