{
  "type": "Feature",
  "properties": {
    "addr:full":"Avda Puente De Carlos Iii, 6 Reinosa Cantabria 39200",
    "addr:housenumber":"6",
    "addr:postcode":"39200",
    "addr:street":"Avda Puente De Carlos Iii",
    "iso:country":"ES",
    "sg:address":"Avda Puente De Carlos Iii, 6",
    "sg:city":"Reinosa",
    "sg:orig_category":"Electrodom\u00c9sticos (al Por Menor)",
    "sg:phone":"+34 942 75 31 96",
    "sg:postcode":"39200",
    "sg:province":"Cantabria",
    "wof:name":"Callejo Cabo Javier",
    "wof:placetype":"venue"
},
  "geometry": {"coordinates":[-4.1380839348,42.9991950989],"type":"Point"}
}