{
  "type": "Feature",
  "properties": {
    "iso:country":"ES",
    "sg:address":"Avda Infantes (los), 71",
    "sg:city":"Santander",
    "sg:orig_category":"Doctores En Medicina",
    "sg:phone":"+34 942 27 08 73",
    "sg:postcode":"39005",
    "sg:province":"Cantabria",
    "wof:name":"Resonancia Magnetica Palencia S.a.",
    "wof:placetype":"venue"
},
  "geometry": {"coordinates":[-3.7882890701,43.4719009399],"type":"Point"}
}