{
  "type": "Feature",
  "properties": {
    "addr:full":"Pg Ribera, 121 Barriada Nova Barcelona 08420",
    "addr:housenumber":"121",
    "addr:postcode":"08420",
    "addr:street":"Ribera;Nova Barcelona",
    "iso:country":"ES",
    "sg:address":"Pg Ribera, 121",
    "sg:city":"Barriada Nova",
    "sg:orig_category":"Ingeniero",
    "sg:phone":"+34 938 40 12 21",
    "sg:postcode":"08420",
    "sg:province":"Barcelona",
    "wof:name":"Mar-dispensing S.l.",
    "wof:placetype":"venue"
},
  "geometry": {"coordinates":[2.2780098915,41.6220703125],"type":"Point"}
}