{
  "type": "Feature",
  "properties": {
    "addr:full":"Calle de Argamasilla, 23 Madrid Madrid 28042",
    "addr:housenumber":"23",
    "addr:postcode":"madrid;28042",
    "addr:street":"Calle De Argamasilla",
    "iso:country":"ES",
    "sg:address":"Calle de Argamasilla, 23",
    "sg:city":"Madrid",
    "sg:orig_category":"Alimentaci\u00d3n General (al Por Menor)",
    "sg:phone":"+34 913 05 53 94",
    "sg:postcode":"28042",
    "sg:province":"Madrid",
    "wof:name":"Langa Higes Angel",
    "wof:placetype":"venue"
},
  "geometry": {"coordinates":[-3.5843849182,40.4731903076],"type":"Point"}
}