{
  "type": "Feature",
  "properties": {
    "iso:country":"ES",
    "sg:address":"Avda Lanzagorta, 4",
    "sg:city":"Mimetiz",
    "sg:orig_category":"Herboristas (al Por Menor)",
    "sg:phone":"+34 946 39 13 85",
    "sg:postcode":"48860",
    "sg:province":"Vizcaya",
    "wof:name":"Igoa Ortiz Gloria Maria",
    "wof:placetype":"venue"
},
  "geometry": {"coordinates":[-3.132019043,43.2127037048],"type":"Point"}
}