{
  "type": "Feature",
  "properties": {
    "addr:full":"Calle de Doctor Jimenez Neyra, 41 Palmas De Gran Canaria Las Palmas 35012",
    "addr:housenumber":"41",
    "addr:postcode":"35012",
    "addr:street":"Calle De Doctor Jimenez Neyra",
    "iso:country":"ES",
    "sg:address":"Calle de Doctor Jimenez Neyra, 41",
    "sg:city":"Palmas De Gran Canaria",
    "sg:orig_category":"Ense\u00d1anza, Formaci\u00d3n Profesional: Aprendizaje",
    "sg:phone":"+34 928 25 03 69",
    "sg:postcode":"35012",
    "sg:province":"Las Palmas",
    "wof:name":"Instituto Municipal De Deportes De Las P",
    "wof:placetype":"venue"
},
  "geometry": {"coordinates":[-15.4275140762,28.1097412109],"type":"Point"}
}