{
  "type": "Feature",
  "properties": {
    "addr:full":"Calle de Benito Gutierrez, 1 Madrid Madrid 28008",
    "addr:housenumber":"1",
    "addr:postcode":"28008",
    "addr:street":"Calle De Benito Gutierrez",
    "iso:country":"ES",
    "sg:address":"Calle de Benito Gutierrez, 1",
    "sg:city":"Madrid",
    "sg:orig_category":"Peluqueros: De Se\u00d1oras",
    "sg:phone":"+34 915 49 82 56",
    "sg:postcode":"28008",
    "sg:province":"Madrid",
    "wof:name":"Martinez Cerdan Manuel",
    "wof:placetype":"venue"
},
  "geometry": {"coordinates":[-3.7176280022,40.4322738647],"type":"Point"}
}