{
  "type": "Feature",
  "properties": {
    "iso:country":"ES",
    "sg:address":"Sol, S/n",
    "sg:city":"Sedavi",
    "sg:orig_category":"Alimentaci\u00d3n General (al Por Menor)",
    "sg:phone":"+34 963 18 61 85",
    "sg:postcode":"46910",
    "sg:province":"Valencia",
    "wof:name":"Vidal Juan Antonio",
    "wof:placetype":"venue"
},
  "geometry": {"coordinates":[-0.3833740056,39.4257354736],"type":"Point"}
}