{
  "type": "Feature",
  "properties": {
    "iso:country":"ES",
    "sg:address":"Calle de Escotilla, 15",
    "sg:city":"Arrecife",
    "sg:orig_category":"Pintura, Barniz, Productos Asimilables (fabricaci\u00d3n, Al Por Mayor)",
    "sg:phone":"+34 928 81 06 90",
    "sg:postcode":"35500",
    "sg:province":"Las Palmas",
    "wof:name":"Decoraciones De Leon S.l.",
    "wof:placetype":"venue"
},
  "geometry": {"coordinates":[-13.5414733887,28.9678153992],"type":"Point"}
}