{
  "type": "Feature",
  "properties": {
    "addr:full":"Calle de Periodista Fernando Gomez De La Cruz, 55 Granada Granada 18015",
    "addr:housenumber":"55",
    "addr:postcode":"18015",
    "addr:street":"Calle De Periodista Fernando Gomez De La Cruz",
    "iso:country":"ES",
    "sg:address":"Calle de Periodista Fernando Gomez De La Cruz, 55",
    "sg:city":"Granada",
    "sg:orig_category":"Distribuci\u00d3n De Petr\u00d3leo Y Derivados",
    "sg:phone":"+34 958 15 02 24",
    "sg:postcode":"18015",
    "sg:province":"Granada",
    "wof:name":"Estacion De Servicio Vidal S.a.",
    "wof:placetype":"venue"
},
  "geometry": {"coordinates":[-3.6231749058,37.1979446411],"type":"Point"}
}