{
  "type": "Feature",
  "properties": {
    "addr:full":"Calle de Toral, 11 Bogajo Salamanca 37260",
    "addr:housenumber":"11",
    "addr:postcode":"37260",
    "addr:street":"Calle De Toral",
    "iso:country":"ES",
    "sg:address":"Calle de Toral, 11",
    "sg:city":"Bogajo",
    "sg:orig_category":"Fabricaci\u00d3n De Quesos",
    "sg:phone":"+34 923 51 93 94",
    "sg:postcode":"37260",
    "sg:province":"Salamanca",
    "wof:name":"Hernandez Iglesias Sara",
    "wof:placetype":"venue"
},
  "geometry": {"coordinates":[-6.4716968536,40.8766021729],"type":"Point"}
}