{
  "type": "Feature",
  "properties": {
    "addr:full":"Johannes Gutenberg, 8 Parc Tecnologic Valencia 46980",
    "addr:housenumber":"8",
    "addr:postcode":"46980",
    "addr:street":"Gutenberg;Parc Tecnologic",
    "iso:country":"ES",
    "sg:address":"Johannes Gutenberg, 8",
    "sg:city":"Parc Tecnologic",
    "sg:orig_category":"Electricidad: Instaladores",
    "sg:phone":"+34 963 85 26 01",
    "sg:postcode":"46980",
    "sg:province":"Valencia",
    "sg:website":"www.electrovalencia.es",
    "wof:name":"Agrupacion Empresas Automatismos Montajes Y Servicios S.l.",
    "wof:placetype":"venue"
},
  "geometry": {"coordinates":[-0.463647306,39.5504570007],"type":"Point"}
}