{
  "type": "Feature",
  "properties": {
    "addr:full":"Carrer de La Rambla, 58 Barcelona Barcelona 08002",
    "addr:housenumber":"58",
    "addr:postcode":"08002",
    "addr:street":"Carrer De La Rambla",
    "iso:country":"ES",
    "sg:address":"Carrer de La Rambla, 58",
    "sg:city":"Barcelona",
    "sg:orig_category":"Loter\u00cda Y T\u00d3mbola",
    "sg:phone":"+34 933 18 38 92",
    "sg:postcode":"08002",
    "sg:province":"Barcelona",
    "wof:name":"Garcia Montoto Jordi",
    "wof:placetype":"venue"
},
  "geometry": {"coordinates":[2.1743559837,41.3802642822],"type":"Point"}
}