{
  "type": "Feature",
  "properties": {
    "iso:country":"ES",
    "sg:address":"Pso. Maritimo, 87",
    "sg:city":"Almeria",
    "sg:orig_category":"Bares, Piano",
    "sg:phone":"+34 950 26 88 21",
    "sg:postcode":"04007",
    "sg:province":"Almer\u00eda",
    "wof:name":"La India Centros De Recreo S.l.",
    "wof:placetype":"venue"
},
  "geometry": {"coordinates":[-2.4585568905,36.8311538696],"type":"Point"}
}