{
  "type": "Feature",
  "properties": {
    "addr:full":"Calle de Nekazari, 7 Bermeo Vizcaya 48370",
    "addr:housenumber":"7",
    "addr:postcode":"48370",
    "addr:street":"Calle De Nekazari",
    "iso:country":"ES",
    "sg:address":"Calle de Nekazari, 7",
    "sg:city":"Bermeo",
    "sg:orig_category":"Peluqueros: De Se\u00d1oras",
    "sg:phone":"+34 946 88 13 63",
    "sg:postcode":"48370",
    "sg:province":"Vizcaya",
    "wof:name":"Arang\u00fcena Meabe Maria Isabel",
    "wof:placetype":"venue"
},
  "geometry": {"coordinates":[-2.7244582176,43.4207229614],"type":"Point"}
}