{
  "type": "Feature",
  "properties": {
    "iso:country":"ES",
    "sg:address":"Vinxeira Pequena, S/n",
    "sg:city":"Vinxeira Pequena",
    "sg:orig_category":"Alimentaci\u00d3n General (al Por Mayor)",
    "sg:phone":"+34 981 66 83 28",
    "sg:postcode":"15189",
    "sg:province":"La Coru\u00f1a",
    "wof:name":"Coporc S. Coop. Ltda.",
    "wof:placetype":"venue"
},
  "geometry": {"coordinates":[-8.3897981644,43.2883262634],"type":"Point"}
}