{
  "type": "Feature",
  "properties": {
    "iso:country":"ES",
    "sg:address":"Castelao, S/n",
    "sg:city":"Nogais",
    "sg:orig_category":"Distribuci\u00d3n De Petr\u00d3leo Y Derivados",
    "sg:phone":"+34 982 36 41 10",
    "sg:postcode":"27677",
    "sg:province":"Lugo",
    "wof:name":"M. Diaz E Hijos S.l.",
    "wof:placetype":"venue"
},
  "geometry": {"coordinates":[-7.1095547676,42.8088111877],"type":"Point"}
}