{
  "type": "Feature",
  "properties": {
    "iso:country":"ES",
    "sg:address":"Calle de Gerona, 19",
    "sg:city":"Alacant",
    "sg:orig_category":"Abogados",
    "sg:phone":"+34 965 20 71 99",
    "sg:postcode":"03001",
    "sg:province":"Alicante",
    "wof:name":"Losa Rodriguez Maria Soledad",
    "wof:placetype":"venue"
},
  "geometry": {"coordinates":[-0.485747993,38.3443603516],"type":"Point"}
}