{
  "type": "Feature",
  "properties": {
    "addr:full":"Av Princep D'asturies, 26 Barcelona Barcelona 08012",
    "addr:housenumber":"26",
    "addr:postcode":"08012",
    "addr:street":"Av Princep D'Asturies",
    "iso:country":"ES",
    "sg:address":"Av Princep D'asturies, 26",
    "sg:city":"Barcelona",
    "sg:orig_category":"Fotocopias, Reprograf\u00cda",
    "sg:phone":"+34 932 18 55 59",
    "sg:postcode":"08012",
    "sg:province":"Barcelona",
    "wof:name":"Andres Majos Marcos",
    "wof:placetype":"venue"
},
  "geometry": {"coordinates":[2.1500761509,41.4029579163],"type":"Point"}
}