{
  "type": "Feature",
  "properties": {
    "addr:full":"Ptge Permanyer, 6 Barcelona Barcelona 08009",
    "addr:housenumber":"6",
    "addr:postcode":"08009",
    "addr:street":"Ptge Permanyer",
    "iso:country":"ES",
    "sg:address":"Ptge Permanyer, 6",
    "sg:city":"Barcelona",
    "sg:classifiers":[
        {
            "category":"Communications",
            "type":"Services"
        }
    ],
    "sg:phone":"+34 933 22 01 24",
    "sg:postcode":"08009",
    "sg:province":"Barcelona",
    "sg:tags":[
        "televisiones",
        "y",
        "radio"
    ],
    "wof:name":"Radio Televisio Valenciana",
    "wof:placetype":"venue"
},
  "geometry": {"coordinates":[2.1683061123,41.3923683167],"type":"Point"}
}