{
  "type": "Feature",
  "properties": {
    "addr:full":"Carr Vicen\u00c7 Buades, S/n Puerto De Pollen\u00c7a Islas Baleares 07470",
    "addr:housenumber":"s / n",
    "addr:postcode":"07470",
    "addr:street":"Carr Vicenc\u0327 Buades",
    "iso:country":"ES",
    "sg:address":"Carr Vicen\u00c7 Buades, S/n",
    "sg:city":"Puerto De Pollen\u00c7a",
    "sg:orig_category":"Ense\u00d1anza, Formaci\u00d3n Profesional: Aprendizaje",
    "sg:phone":"+34 971 86 71 72",
    "sg:postcode":"07470",
    "sg:province":"Islas Baleares",
    "wof:name":"Ayuntamiento De Pollensa",
    "wof:placetype":"venue"
},
  "geometry": {"coordinates":[3.0801565647,39.9089012146],"type":"Point"}
}