{
  "type": "Feature",
  "properties": {
    "iso:country":"ES",
    "sg:address":"Carretera Pampanico, Km. 0004,7",
    "sg:city":"Ejido",
    "sg:orig_category":"Arboricultura Y Producci\u00d3n De Frutas",
    "sg:phone":"+34 950 48 90 06",
    "sg:postcode":"04700",
    "sg:province":"Almer\u00eda",
    "wof:name":"Hermanos Daza Palmero S.l.",
    "wof:placetype":"venue"
},
  "geometry": {"coordinates":[-2.8176040649,36.7727012634],"type":"Point"}
}