{
  "type": "Feature",
  "properties": {
    "iso:country":"ES",
    "sg:address":"Avda Catalu\u00d1a, 101",
    "sg:city":"Calaceite",
    "sg:orig_category":"Cooperativas Agr\u00cdcolas",
    "sg:phone":"+34 978 85 10 14",
    "sg:postcode":"44610",
    "sg:province":"Teruel",
    "wof:name":"Cooperativa Del Campo",
    "wof:placetype":"venue"
},
  "geometry": {"coordinates":[0.1915639937,41.0161933899],"type":"Point"}
}