{
  "type": "Feature",
  "properties": {
    "addr:full":"Avda Lancia, 1 Le\u00f3n Le\u00f3n 24004",
    "addr:housenumber":"1",
    "addr:postcode":"24004",
    "addr:street":"Avda Lancia;Leo\u0301N",
    "iso:country":"ES",
    "sg:address":"Avda Lancia, 1",
    "sg:city":"Le\u00f3n",
    "sg:orig_category":"Doctores En Medicina",
    "sg:phone":"+34 987 20 30 91",
    "sg:postcode":"24004",
    "sg:province":"Le\u00f3n",
    "wof:name":"Morala Morala Jesus",
    "wof:placetype":"venue"
},
  "geometry": {"coordinates":[-5.5723700523,42.5936393738],"type":"Point"}
}