{
  "type": "Feature",
  "properties": {
    "addr:full":"Calle de Moreno De Mora, 9 Trebujena C\u00e1diz 11560",
    "addr:housenumber":"9",
    "addr:postcode":"11560",
    "addr:street":"Calle De Moreno De Mora;Ca\u0301Diz",
    "iso:country":"ES",
    "sg:address":"Calle de Moreno De Mora, 9",
    "sg:city":"Trebujena",
    "sg:classifiers":[
        {
            "category":"Personal",
            "subcategory":"Barber",
            "type":"Services"
        }
    ],
    "sg:phone":"+34 956 39 53 56",
    "sg:postcode":"11560",
    "sg:province":"C\u00e1diz",
    "sg:tags":[
        "caballeros",
        "de",
        "peluqueros"
    ],
    "wof:name":"Cabral Nu\u00f1ez Antonio",
    "wof:placetype":"venue"
},
  "geometry": {"coordinates":[-6.1762189865,36.8687553406],"type":"Point"}
}