{
  "type": "Feature",
  "properties": {
    "addr:full":"Calle de Vicario Camarena, 6 Pobla Vallbona Valencia 46185",
    "addr:housenumber":"6",
    "addr:postcode":"46185",
    "addr:street":"Calle De Vicario Camarena",
    "iso:country":"ES",
    "sg:address":"Calle de Vicario Camarena, 6",
    "sg:city":"Pobla Vallbona",
    "sg:orig_category":"Agencias Y Agentes Comerciales, Representantes",
    "sg:phone":"+34 962 76 20 43",
    "sg:postcode":"46185",
    "sg:province":"Valencia",
    "wof:name":"Vea Muniesa Carmen",
    "wof:placetype":"venue"
},
  "geometry": {"coordinates":[-0.5512161851,39.5958747864],"type":"Point"}
}