{
  "type": "Feature",
  "properties": {
    "iso:country":"ES",
    "sg:address":"Calle de Lino Casimiro Iborra, 10",
    "sg:city":"Santo\u00f1a",
    "sg:orig_category":"Asesor\u00cda Fiscal Y Jur\u00cddica",
    "sg:phone":"+34 942 66 03 43",
    "sg:postcode":"39740",
    "sg:province":"Cantabria",
    "wof:name":"As Asesores S.c.",
    "wof:placetype":"venue"
},
  "geometry": {"coordinates":[-3.4542469978,43.4424972534],"type":"Point"}
}