{
  "type": "Feature",
  "properties": {
    "iso:country":"ES",
    "sg:address":"Carr De Salvador Tormo, 29",
    "sg:city":"Ontinyent",
    "sg:orig_category":"Reposter\u00cdas",
    "sg:phone":"+34 962 38 72 16",
    "sg:postcode":"46870",
    "sg:province":"Valencia",
    "wof:name":"Guerola Grau Rafael",
    "wof:placetype":"venue"
},
  "geometry": {"coordinates":[-0.6010180116,38.8233680725],"type":"Point"}
}