{
  "type": "Feature",
  "properties": {
    "iso:country":"ES",
    "sg:address":"Carrer de Siguenza, 68",
    "sg:city":"Barcelona",
    "sg:orig_category":"Empresas De Carpinter\u00cda Met\u00c1lica",
    "sg:phone":"+34 933 58 63 62",
    "sg:postcode":"08032",
    "sg:province":"Barcelona",
    "wof:name":"Construcciones Metalicas Trenado S.l.",
    "wof:placetype":"venue"
},
  "geometry": {"coordinates":[2.1533539295,41.4239196777],"type":"Point"}
}