{
  "type": "Feature",
  "properties": {
    "iso:country":"ES",
    "sg:address":"Carrer de Atenes, 5",
    "sg:city":"Barcelona",
    "sg:orig_category":"Inmobiliaria (agencias)",
    "sg:phone":"+34 932 09 90 71",
    "sg:postcode":"08006",
    "sg:province":"Barcelona",
    "wof:name":"Ringger S.l.",
    "wof:placetype":"venue"
},
  "geometry": {"coordinates":[2.1429700851,41.4027061462],"type":"Point"}
}