{
  "type": "Feature",
  "properties": {
    "addr:full":"Calle de Portugal, 37 Fuenlabrada Madrid 28943",
    "addr:housenumber":"37",
    "addr:postcode":"28943",
    "addr:street":"Calle De Portugal",
    "iso:country":"ES",
    "sg:address":"Calle de Portugal, 37",
    "sg:city":"Fuenlabrada",
    "sg:orig_category":"Abogados",
    "sg:phone":"+34 916 07 12 52",
    "sg:postcode":"28943",
    "sg:province":"Madrid",
    "wof:name":"Lopez Rodriguez Elena",
    "wof:placetype":"venue"
},
  "geometry": {"coordinates":[-3.8094649315,40.2841758728],"type":"Point"}
}