{
  "type": "Feature",
  "properties": {
    "addr:full":"Rua Gasset, 10 Pobra Do Carami\u00e7al La Coru\u00f1a 15940",
    "addr:housenumber":"10",
    "addr:postcode":"15940",
    "addr:street":"Rua Gasset;Corun\u0303A",
    "iso:country":"ES",
    "sg:address":"Rua Gasset, 10",
    "sg:city":"Pobra Do Carami\u00e7al",
    "sg:orig_category":"M\u00c9dicos: An\u00c1lisis Cl\u00cdnicos",
    "sg:phone":"+34 981 83 20 02",
    "sg:postcode":"15940",
    "sg:province":"La Coru\u00f1a",
    "wof:name":"Laboratorio Perez Gonzalez C.b.",
    "wof:placetype":"venue"
},
  "geometry": {"coordinates":[-8.9387626648,42.6040153503],"type":"Point"}
}