{
  "type": "Feature",
  "properties": {
    "iso:country":"ES",
    "sg:address":"Calle de San Juan De Dios, 2",
    "sg:city":"Sevilla",
    "sg:orig_category":"Abogados",
    "sg:phone":"+34 954 64 19 65",
    "sg:postcode":"41005",
    "sg:province":"Sevilla",
    "wof:name":"Alegre Macias Emilio",
    "wof:placetype":"venue"
},
  "geometry": {"coordinates":[-5.9697699547,37.3820533752],"type":"Point"}
}