{
  "type": "Feature",
  "properties": {
    "iso:country":"ES",
    "sg:address":"Calle de Pacita Vigil La Guaxa, 3",
    "sg:city":"Pola De Siero",
    "sg:orig_category":"Plomeros",
    "sg:phone":"+34 985 72 23 99",
    "sg:postcode":"33510",
    "sg:province":"Asturias",
    "wof:name":"Fontaneria Fernandez Y Estrada S.l.",
    "wof:placetype":"venue"
},
  "geometry": {"coordinates":[-5.6608700752,43.3908615112],"type":"Point"}
}