{
  "type": "Feature",
  "properties": {
    "iso:country":"ES",
    "sg:address":"Plaz Campi\u00d1a (la), 2",
    "sg:city":"Marmolejo",
    "sg:orig_category":"Ingenier\u00cda, Centros De Estudios (diversos)",
    "sg:phone":"+34 953 51 78 96",
    "sg:postcode":"23770",
    "sg:province":"Ja\u00e9n",
    "wof:name":"Toro Ortega Jesus De",
    "wof:placetype":"venue"
},
  "geometry": {"coordinates":[-4.1686739922,38.0476646423],"type":"Point"}
}