{
  "type": "Feature",
  "properties": {
    "iso:country":"ES",
    "sg:address":"Calle de Ramon Corrochano, 4",
    "sg:city":"Talavera Reina",
    "sg:orig_category":"Explotaci\u00d3n De Bosques",
    "sg:phone":"+34 925 80 75 89",
    "sg:postcode":"45600",
    "sg:province":"Toledo",
    "wof:name":"Explotaciones Forestales Ramos S.l.",
    "wof:placetype":"venue"
},
  "geometry": {"coordinates":[-4.8316922188,39.965473175],"type":"Point"}
}