{
  "type": "Feature",
  "properties": {
    "addr:full":"Calle de Colombia, 33 Madrid Madrid 28016",
    "addr:housenumber":"33",
    "addr:postcode":"madrid;28016",
    "addr:street":"Calle De Colombia",
    "iso:country":"ES",
    "sg:address":"Calle de Colombia, 33",
    "sg:city":"Madrid",
    "sg:orig_category":"Peluqueros: De Se\u00d1oras",
    "sg:phone":"+34 913 59 11 30",
    "sg:postcode":"28016",
    "sg:province":"Madrid",
    "wof:name":"Garcia Aranda Maria Del Rosario",
    "wof:placetype":"venue"
},
  "geometry": {"coordinates":[-3.6728963852,40.4570045471],"type":"Point"}
}