{
  "type": "Feature",
  "properties": {
    "iso:country":"ES",
    "sg:address":"Calle de Mayor, 23",
    "sg:city":"Monreal",
    "sg:orig_category":"Granos Y Semillas (producci\u00d3n, Al Por Mayor)",
    "sg:phone":"+34 948 36 20 32",
    "sg:postcode":"31471",
    "sg:province":"Navarra",
    "wof:name":"Semillas Labiano S.l",
    "wof:placetype":"venue"
},
  "geometry": {"coordinates":[-1.5074019432,42.7048110962],"type":"Point"}
}