{
  "type": "Feature",
  "properties": {
    "addr:full":"Calle de Portal De Arriaga, 21 C Vitoria-gasteiz \u00c1lava 01012",
    "addr:housenumber":"21 c",
    "addr:postcode":"01012",
    "addr:street":"Calle De Portal De Arriaga",
    "iso:country":"ES",
    "sg:address":"Calle de Portal De Arriaga, 21 C",
    "sg:city":"Vitoria-gasteiz",
    "sg:orig_category":"Tintes (fabricaci\u00d3n, Al Por Mayor)",
    "sg:phone":"+34 945 22 26 70",
    "sg:postcode":"01012",
    "sg:province":"\u00c1lava",
    "wof:name":"M.carmen Barea Arcos(vit-sec)",
    "wof:placetype":"venue"
},
  "geometry": {"coordinates":[-2.6775500774,42.8551483154],"type":"Point"}
}