{
  "type": "Feature",
  "properties": {
    "iso:country":"ES",
    "sg:address":"Lugar Polig. Tres Caminos, 14",
    "sg:city":"S. Fernando",
    "sg:orig_category":"Fabricaci\u00d3n, Comercio De Flores Y Plantas Artificiales",
    "sg:phone":"+34 956 59 02 26",
    "sg:postcode":"11100",
    "sg:province":"C\u00e1diz",
    "wof:name":"Islatrafer S.l.",
    "wof:placetype":"venue"
},
  "geometry": {"coordinates":[-6.1967391968,36.4654541016],"type":"Point"}
}