{
  "type": "Feature",
  "properties": {
    "iso:country":"ES",
    "sg:address":"Calle de Viva Espa\u00d1a, 4",
    "sg:city":"Zaragoza",
    "sg:orig_category":"Electricidad, Electr\u00d3nica: Suministros (al Por Menor)",
    "sg:phone":"+34 976 25 95 81",
    "sg:postcode":"50006",
    "sg:province":"Zaragoza",
    "sg:website":"www.ascom.es",
    "wof:name":"Affiliated Computer Services Solution Spain S.l.",
    "wof:placetype":"venue"
},
  "geometry": {"coordinates":[-0.8891431093,41.6388473511],"type":"Point"}
}