{
  "type": "Feature",
  "properties": {
    "iso:country":"ES",
    "sg:address":"Calle de San Bernardo, 12",
    "sg:city":"Madrid",
    "sg:orig_category":"Lencer\u00cda Femenina, Corseter\u00cda, Trajes De Ba\u00d1o (al Por Menor)",
    "sg:phone":"+34 915 22 44 06",
    "sg:postcode":"28015",
    "sg:province":"Madrid",
    "wof:name":"Perez Estevez Jesus",
    "wof:placetype":"venue"
},
  "geometry": {"coordinates":[-3.707638979,40.4222717285],"type":"Point"}
}