{
  "type": "Feature",
  "properties": {
    "iso:country":"ES",
    "sg:address":"Avda Blasco Iba\u00d1ez, 134",
    "sg:city":"Valencia",
    "sg:orig_category":"Lencer\u00cda Femenina, Corseter\u00cda, Trajes De Ba\u00d1o (al Por Menor)",
    "sg:phone":"+34 963 71 35 35",
    "sg:postcode":"46022",
    "sg:province":"Valencia",
    "wof:name":"Afghans Of Spain S.l.",
    "wof:placetype":"venue"
},
  "geometry": {"coordinates":[-0.3454954028,39.4729499817],"type":"Point"}
}