{
  "type": "Feature",
  "properties": {
    "addr:full":"Calle de Consolacion, 25 Torrelavega Cantabria 39300",
    "addr:housenumber":"25",
    "addr:postcode":"39300",
    "addr:street":"Calle De Consolacion",
    "iso:country":"ES",
    "sg:address":"Calle de Consolacion, 25",
    "sg:city":"Torrelavega",
    "sg:orig_category":"Ropa Para Se\u00d1oras Y Caballeros (al Por Menor)",
    "sg:phone":"+34 942 80 42 55",
    "sg:postcode":"39300",
    "sg:province":"Cantabria",
    "wof:name":"Mazon Ceballos Isabel",
    "wof:placetype":"venue"
},
  "geometry": {"coordinates":[-4.0474572182,43.351020813],"type":"Point"}
}