{
  "type": "Feature",
  "properties": {
    "iso:country":"ES",
    "sg:address":"Calle de Velazquez, 10",
    "sg:city":"Oviedo",
    "sg:orig_category":"Caf\u00c9s, Bares, Cervecer\u00cdas",
    "sg:phone":"+34 985 11 18 77",
    "sg:postcode":"33011",
    "sg:province":"Asturias",
    "wof:name":"Garcia Martinez Felisa",
    "wof:placetype":"venue"
},
  "geometry": {"coordinates":[-5.8375239372,43.368812561],"type":"Point"}
}