{
  "type": "Feature",
  "properties": {
    "iso:country":"ES",
    "sg:address":"Calle de Federico Garcia Lorca, 2",
    "sg:city":"Huelva",
    "sg:orig_category":"Peluquer\u00cdas, Peluquer\u00cda Mixta",
    "sg:phone":"+34 959 27 01 65",
    "sg:postcode":"21007",
    "sg:province":"Huelva",
    "wof:name":"Suarez Gil Jose Manuel",
    "wof:placetype":"venue"
},
  "geometry": {"coordinates":[-6.9285106659,37.2637443542],"type":"Point"}
}