{
  "type": "Feature",
  "properties": {
    "addr:full":"Calle de Teatro, 54 Pe\u00e7arroya-pueblonuevo C\u00f3rdoba 14200",
    "addr:housenumber":"54",
    "addr:postcode":"14200",
    "addr:street":"Calle De Teatro;Co\u0301Rdoba",
    "iso:country":"ES",
    "sg:address":"Calle de Teatro, 54",
    "sg:city":"Pe\u00e7arroya-pueblonuevo",
    "sg:orig_category":"Agentes Generales De Seguros",
    "sg:phone":"+34 957 56 12 97",
    "sg:postcode":"14200",
    "sg:province":"C\u00f3rdoba",
    "wof:name":"Ortiz Dominguez Jose",
    "wof:placetype":"venue"
},
  "geometry": {"coordinates":[-5.2649888992,38.3010787964],"type":"Point"}
}