{
  "type": "Feature",
  "properties": {
    "addr:full":"Av Rei En Jaume, 58 Cardedeu Barcelona 08440",
    "addr:housenumber":"58",
    "addr:postcode":"08440",
    "addr:street":"Av Rei En Jaume",
    "iso:country":"ES",
    "sg:address":"Av Rei En Jaume, 58",
    "sg:city":"Cardedeu",
    "sg:orig_category":"Reposter\u00cdas",
    "sg:phone":"+34 938 46 17 47",
    "sg:postcode":"08440",
    "sg:province":"Barcelona",
    "wof:name":"Bonamusa Ponts Concepcio",
    "wof:placetype":"venue"
},
  "geometry": {"coordinates":[2.3579499722,41.6369781494],"type":"Point"}
}