{
  "type": "Feature",
  "properties": {
    "iso:country":"ES",
    "sg:address":"Plaz Baldomero Anabit., 1",
    "sg:city":"Donostia-san Sebastian",
    "sg:orig_category":"Abogados",
    "sg:phone":"+34 943 45 38 88",
    "sg:postcode":"20011",
    "sg:province":"Guip\u00f9zcoa",
    "wof:name":"Aparicio Barinaga I\u00f1igo",
    "wof:placetype":"venue"
},
  "geometry": {"coordinates":[-1.9728109837,43.3049736023],"type":"Point"}
}