{
  "type": "Feature",
  "properties": {
    "addr:full":"Calle de Benidorm, 9 Madrid Madrid 28017",
    "addr:housenumber":"9",
    "addr:postcode":"madrid;28017",
    "addr:street":"Calle De Benidorm",
    "iso:country":"ES",
    "sg:address":"Calle de Benidorm, 9",
    "sg:city":"Madrid",
    "sg:orig_category":"Panader\u00cdas, Panader\u00cdas",
    "sg:phone":"+34 914 04 53 95",
    "sg:postcode":"28017",
    "sg:province":"Madrid",
    "wof:name":"Suarez Hita Luis Miguel",
    "wof:placetype":"venue"
},
  "geometry": {"coordinates":[-3.6560461521,40.430847168],"type":"Point"}
}