{
  "type": "Feature",
  "properties": {
    "iso:country":"ES",
    "sg:address":"Calle de Federico Echevarria, 1",
    "sg:city":"Le\u00f3n",
    "sg:orig_category":"Promotores Constructores",
    "sg:phone":"+34 987 24 53 90",
    "sg:postcode":"24002",
    "sg:province":"Le\u00f3n",
    "wof:name":"Tecsa Empresa Constructora S. A.",
    "wof:placetype":"venue"
},
  "geometry": {"coordinates":[-5.5758509636,42.6030426025],"type":"Point"}
}