{
  "type": "Feature",
  "properties": {
    "addr:full":"Pase Reding, 47 Malaga M\u00e1laga 29016",
    "addr:housenumber":"47",
    "addr:postcode":"29016",
    "addr:street":"Reding;Ma\u0301Laga",
    "iso:country":"ES",
    "sg:address":"Pase Reding, 47",
    "sg:city":"Malaga",
    "sg:orig_category":"Abogados",
    "sg:phone":"+34 952 22 66 35",
    "sg:postcode":"29016",
    "sg:province":"M\u00e1laga",
    "wof:name":"Genova Alguacil Maria Del Rosario",
    "wof:placetype":"venue"
},
  "geometry": {"coordinates":[-4.4081401825,36.721031189],"type":"Point"}
}