{
  "type": "Feature",
  "properties": {
    "iso:country":"ES",
    "sg:address":"Rua Galiano, 14",
    "sg:city":"Ferrol",
    "sg:orig_category":"Confecci\u00d3n De Trajes Para Se\u00d1oras",
    "sg:phone":"+34 981 32 28 84",
    "sg:postcode":"15402",
    "sg:province":"La Coru\u00f1a",
    "wof:name":"Formoso Galdo Maria Del Pilar",
    "wof:placetype":"venue"
},
  "geometry": {"coordinates":[-8.2298221588,43.485874176],"type":"Point"}
}