{
  "type": "Feature",
  "properties": {
    "addr:full":"Av. Berganti\u00f1os(a Trabe), 33 Ponteceso La Coru\u00f1a 15110",
    "addr:housenumber":"33",
    "addr:postcode":"15110",
    "addr:street":"Av. Bergantin\u0303Os A Trabe;La Corun\u0303A",
    "iso:country":"ES",
    "sg:address":"Av. Berganti\u00f1os(a Trabe), 33",
    "sg:city":"Ponteceso",
    "sg:orig_category":"Distribuci\u00d3n De Petr\u00d3leo Y Derivados",
    "sg:phone":"+34 981 70 86 05",
    "sg:postcode":"15110",
    "sg:province":"La Coru\u00f1a",
    "wof:name":"Mabagas S.l.",
    "wof:placetype":"venue"
},
  "geometry": {"coordinates":[-8.8933086395,43.2439994812],"type":"Point"}
}