{
  "type": "Feature",
  "properties": {
    "iso:country":"ES",
    "sg:address":"Carrer de Empecinado, 10",
    "sg:city":"Hospitalet Llobregat",
    "sg:orig_category":"Empresas De Limpieza",
    "sg:phone":"+34 934 38 44 79",
    "sg:postcode":"08906",
    "sg:province":"Barcelona",
    "wof:name":"Antonio Ramadalid S.l.",
    "wof:placetype":"venue"
},
  "geometry": {"coordinates":[2.1046233177,41.3725814819],"type":"Point"}
}