{
  "type": "Feature",
  "properties": {
    "iso:country":"ES",
    "sg:address":"Calle de Ortega Y Gasset, S/n",
    "sg:city":"Mocejon",
    "sg:orig_category":"Ferreter\u00cda (diversos)",
    "sg:phone":"+34 925 27 05 11",
    "sg:postcode":"45270",
    "sg:province":"Toledo",
    "wof:name":"Chatarras Moreno S.l.",
    "wof:placetype":"venue"
},
  "geometry": {"coordinates":[-3.9203441143,39.9383735657],"type":"Point"}
}