{
  "type": "Feature",
  "properties": {
    "iso:country":"ES",
    "sg:address":"Rua Albari\u00d1o (do), 20",
    "sg:city":"Cambados",
    "sg:orig_category":"Peleter\u00cdas",
    "sg:phone":"+34 986 53 19 42",
    "sg:postcode":"36630",
    "sg:province":"Pontevedra",
    "wof:name":"Lopez Lopez Martin",
    "wof:placetype":"venue"
},
  "geometry": {"coordinates":[-8.814581871,42.5122299194],"type":"Point"}
}