{
  "type": "Feature",
  "properties": {
    "addr:full":"Tri\u00f1anes, 27 Tri\u00f1anes La Coru\u00f1a 15938",
    "addr:housenumber":"27",
    "addr:postcode":"15938",
    "addr:street":"Trin\u0303Anes;La Corun\u0303A",
    "iso:country":"ES",
    "sg:address":"Tri\u00f1anes, 27",
    "sg:city":"Tri\u00f1anes",
    "sg:classifiers":[
        {
            "category":"Autos & Motor Vehicles",
            "subcategory":"Automobile Sales",
            "type":"Retail Goods"
        }
    ],
    "sg:phone":"+34 981 84 68 72",
    "sg:postcode":"15938",
    "sg:province":"La Coru\u00f1a",
    "wof:name":"Outeiral Suarez Francisco",
    "wof:placetype":"venue"
},
  "geometry": {"coordinates":[-8.8609886169,42.6398506165],"type":"Point"}
}