{
  "type": "Feature",
  "properties": {
    "addr:full":"Calle de Rosario, 13 Villamartin C\u00e1diz 11650",
    "addr:housenumber":"13",
    "addr:postcode":"11650",
    "addr:street":"Calle De Rosario;Ca\u0301Diz",
    "iso:country":"ES",
    "sg:address":"Calle de Rosario, 13",
    "sg:city":"Villamartin",
    "sg:orig_category":"Molduras, Junquillos, Listones Y Molduras Perforadas",
    "sg:phone":"+34 956 73 10 37",
    "sg:postcode":"11650",
    "sg:province":"C\u00e1diz",
    "wof:name":"Solano Tellez Antonio Jesus",
    "wof:placetype":"venue"
},
  "geometry": {"coordinates":[-5.6392788887,36.8586997986],"type":"Point"}
}