{
  "type": "Feature",
  "properties": {
    "addr:full":"Avda Candevania, 23 Zuera Zaragoza 50800",
    "addr:housenumber":"23",
    "addr:postcode":"50800",
    "addr:street":"Avda Candevania",
    "iso:country":"ES",
    "sg:address":"Avda Candevania, 23",
    "sg:city":"Zuera",
    "sg:orig_category":"Carnes De Carnicer\u00cda (al Por Mayor)",
    "sg:phone":"+34 976 69 02 58",
    "sg:postcode":"50800",
    "sg:province":"Zaragoza",
    "sg:website":"www.ebroaragondecarnes.com",
    "wof:name":"Molina Sanz Maria Dolores",
    "wof:placetype":"venue"
},
  "geometry": {"coordinates":[-0.7888280153,41.8714447021],"type":"Point"}
}