{
  "type": "Feature",
  "properties": {
    "iso:country":"ES",
    "sg:address":"Calle de Inmaculada Del Pla, 3",
    "sg:city":"Alacant",
    "sg:orig_category":"Delegados, Agentes De Tr\u00c1nsito, Auxiliares De Transporte Internacional",
    "sg:phone":"+34 965 26 77 32",
    "sg:postcode":"03013",
    "sg:province":"Alicante",
    "wof:name":"Sanchez-camacho Garcia Jose Manuel",
    "wof:placetype":"venue"
},
  "geometry": {"coordinates":[-0.4738259912,38.3572998047],"type":"Point"}
}