{
  "type": "Feature",
  "properties": {
    "iso:country":"ES",
    "sg:address":"Julian Etxeberria Kalea, 2",
    "sg:city":"Eibar",
    "sg:orig_category":"Caf\u00c9s, Bares, Cervecer\u00cdas",
    "sg:phone":"+34 943 20 71 65",
    "sg:postcode":"20600",
    "sg:province":"Guip\u00f9zcoa",
    "wof:name":"Astarloa Arregui Javier",
    "wof:placetype":"venue"
},
  "geometry": {"coordinates":[-2.4695360661,43.1856994629],"type":"Point"}
}