{
  "type": "Feature",
  "properties": {
    "addr:full":"Pg Sant Joan, 189 Barcelona Barcelona 08037",
    "addr:housenumber":"189",
    "addr:postcode":"08037",
    "addr:street":"Pg Sant Joan",
    "iso:country":"ES",
    "sg:address":"Pg Sant Joan, 189",
    "sg:city":"Barcelona",
    "sg:orig_category":"Alimentaci\u00d3n General (al Por Mayor)",
    "sg:phone":"+34 932 85 74 11",
    "sg:postcode":"08037",
    "sg:province":"Barcelona",
    "sg:website":"www.cargill.com",
    "wof:name":"Cargill Espa\u00f1a S.a.",
    "wof:placetype":"venue"
},
  "geometry": {"coordinates":[2.1634221077,41.4036598206],"type":"Point"}
}