{
  "type": "Feature",
  "properties": {
    "iso:country":"ES",
    "sg:address":"Ctra Extremadura, Km. 0475,5",
    "sg:city":"Camas",
    "sg:orig_category":"Negocio De Enlosados, Soler\u00cdas",
    "sg:phone":"+34 954 39 16 70",
    "sg:postcode":"41900",
    "sg:province":"Sevilla",
    "wof:name":"Ollero Azulejos Y Pavimentos S.l.",
    "wof:placetype":"venue"
},
  "geometry": {"coordinates":[-6.0344491005,37.4007263184],"type":"Point"}
}