{
  "type": "Feature",
  "properties": {
    "iso:country":"ES",
    "sg:address":"Av Alexandre Rossello, 21",
    "sg:city":"Palma",
    "sg:orig_category":"Centros De Coordinaci\u00d3n",
    "sg:phone":"+34 971 72 72 82",
    "sg:postcode":"07002",
    "sg:province":"Islas Baleares",
    "wof:name":"Lorente De No Cabezas Anunciata",
    "wof:placetype":"venue"
},
  "geometry": {"coordinates":[2.6555089951,39.5738601685],"type":"Point"}
}