{
  "type": "Feature",
  "properties": {
    "iso:country":"ES",
    "sg:address":"Calle de Villar Y Macias, 7",
    "sg:city":"Salamanca",
    "sg:orig_category":"Molduras, Junquillos, Listones Y Molduras Perforadas",
    "sg:phone":"+34 923 26 98 28",
    "sg:postcode":"37002",
    "sg:province":"Salamanca",
    "wof:name":"Corral Miranda Aurora",
    "wof:placetype":"venue"
},
  "geometry": {"coordinates":[-5.6610741615,40.968585968],"type":"Point"}
}