{
  "type": "Feature",
  "properties": {
    "iso:country":"ES",
    "sg:address":"Calle de Batalla De Clavijo, 29",
    "sg:city":"Le\u00f3n",
    "sg:orig_category":"Peluqueros: De Se\u00d1oras",
    "sg:phone":"+34 987 21 27 66",
    "sg:postcode":"24006",
    "sg:province":"Le\u00f3n",
    "wof:name":"Santamarta Santos Maria Del Pilar",
    "wof:placetype":"venue"
},
  "geometry": {"coordinates":[-5.560781002,42.5982398987],"type":"Point"}
}