{
  "type": "Feature",
  "properties": {
    "iso:country":"ES",
    "sg:address":"Calle de Miguel De Cervantes, 14",
    "sg:city":"Alcala Real",
    "sg:orig_category":"Supermercados Y Hipermercados",
    "sg:phone":"+34 953 58 03 33",
    "sg:postcode":"23680",
    "sg:province":"Ja\u00e9n",
    "wof:name":"Cano Aguilera Francisca",
    "wof:placetype":"venue"
},
  "geometry": {"coordinates":[-3.923593998,37.4619903564],"type":"Point"}
}