{
  "type": "Feature",
  "properties": {
    "addr:full":"Carr Carme, 9 Mao Islas Baleares 07701",
    "addr:housenumber":"9",
    "addr:postcode":"07701",
    "addr:street":"Carr Carme",
    "iso:country":"ES",
    "sg:address":"Carr Carme, 9",
    "sg:city":"Mao",
    "sg:orig_category":"Traductores",
    "sg:phone":"+34 971 35 20 92",
    "sg:postcode":"07701",
    "sg:province":"Islas Baleares",
    "wof:name":"Cardona Olives Irene",
    "wof:placetype":"venue"
},
  "geometry": {"coordinates":[4.2659068108,39.8888015747],"type":"Point"}
}