{
  "type": "Feature",
  "properties": {
    "iso:country":"ES",
    "sg:address":"Plaz Perez Pastor, S/n",
    "sg:city":"Punta Umbria",
    "sg:orig_category":"Heladeros",
    "sg:phone":"+34 959 31 19 59",
    "sg:postcode":"21100",
    "sg:province":"Huelva",
    "wof:name":"Nondedeu Coloma Jorge",
    "wof:placetype":"venue"
},
  "geometry": {"coordinates":[-6.9556741714,37.1786193848],"type":"Point"}
}