{
  "type": "Feature",
  "properties": {
    "iso:country":"ES",
    "sg:address":"Barr Basadi Auzategia, 7 B",
    "sg:city":"Zumaia",
    "sg:orig_category":"Art\u00cdculos De Regalo (al Por Menor)",
    "sg:phone":"+34 943 86 23 16",
    "sg:postcode":"20750",
    "sg:province":"Guip\u00f9zcoa",
    "wof:name":"Juan Ignacio Esteve Pay",
    "wof:placetype":"venue"
},
  "geometry": {"coordinates":[-2.2583589554,43.2942314148],"type":"Point"}
}