{
  "type": "Feature",
  "properties": {
    "iso:country":"ES",
    "sg:address":"Carr Sant Ramon, 38",
    "sg:city":"Badalona",
    "sg:orig_category":"Electricidad, Electr\u00d3nica: Material Y Suministros (al Por Mayor)",
    "sg:phone":"+34 934 60 54 24",
    "sg:postcode":"08912",
    "sg:province":"Barcelona",
    "wof:name":"Almacenes Electricos Badalona S.a.",
    "wof:placetype":"venue"
},
  "geometry": {"coordinates":[2.2414708138,41.4485244751],"type":"Point"}
}