{
  "type": "Feature",
  "properties": {
    "iso:country":"ES",
    "sg:address":"Avda Antonio Machado, 104",
    "sg:city":"Arroyo De La Miel-benalmadena Costa",
    "sg:orig_category":"Promotores Constructores",
    "sg:phone":"+34 952 57 62 23",
    "sg:postcode":"29630",
    "sg:province":"M\u00e1laga",
    "wof:name":"Comunidad De Propietarios Edificio Balcon De Bil Bil",
    "wof:placetype":"venue"
},
  "geometry": {"coordinates":[-4.5364460945,36.5824203491],"type":"Point"}
}