{
  "type": "Feature",
  "properties": {
    "addr:full":"Carrer de Concili De Trento, 46 Barcelona Barcelona 08018",
    "addr:housenumber":"46",
    "addr:postcode":"08018",
    "addr:street":"Carrer De Concili De Trento",
    "iso:country":"ES",
    "sg:address":"Carrer de Concili De Trento, 46",
    "sg:city":"Barcelona",
    "sg:orig_category":"Electromec\u00c1nica",
    "sg:phone":"+34 933 03 44 99",
    "sg:postcode":"08018",
    "sg:province":"Barcelona",
    "sg:website":"www.kone.com",
    "wof:name":"Kone S.a.",
    "wof:placetype":"venue"
},
  "geometry": {"coordinates":[2.1933410168,41.4116363525],"type":"Point"}
}