{
  "type": "Feature",
  "properties": {
    "iso:country":"ES",
    "sg:address":"Ctra Simpatica (de La), 25",
    "sg:city":"Tortosa",
    "sg:orig_category":"Doctores En Medicina",
    "sg:phone":"+34 977 44 38 08",
    "sg:postcode":"43500",
    "sg:province":"Tarragona",
    "wof:name":"Oses Ramirez Luis Maria",
    "wof:placetype":"venue"
},
  "geometry": {"coordinates":[0.5314660072,40.8127708435],"type":"Point"}
}