{
  "type": "Feature",
  "properties": {
    "iso:country":"ES",
    "sg:address":"Plaz Rojas Clemente, 8",
    "sg:city":"Valencia",
    "sg:orig_category":"Frutas, Legumbres Frescas Y Tempranas (al Por Menor)",
    "sg:phone":"+34 963 92 47 29",
    "sg:postcode":"46008",
    "sg:province":"Valencia",
    "wof:name":"Montalt Aparicio Manuel",
    "wof:placetype":"venue"
},
  "geometry": {"coordinates":[-0.3857339919,39.4730682373],"type":"Point"}
}