{
  "type": "Feature",
  "properties": {
    "iso:country":"ES",
    "sg:address":"Calle de Espronceda, 61",
    "sg:city":"Ibi",
    "sg:orig_category":"Carnicer\u00cdas, Carnicer\u00cdas",
    "sg:phone":"+34 965 55 06 43",
    "sg:postcode":"03440",
    "sg:province":"Alicante",
    "wof:name":"Pastor Camarasa Joaquin",
    "wof:placetype":"venue"
},
  "geometry": {"coordinates":[-0.574826479,38.618686676],"type":"Point"}
}