{
  "type": "Feature",
  "properties": {
    "iso:country":"ES",
    "sg:address":"Avda Baleares, 2",
    "sg:city":"Torrevieja",
    "sg:orig_category":"Carnicer\u00cdas, Carnicer\u00cdas",
    "sg:phone":"+34 965 70 34 67",
    "sg:postcode":"03180",
    "sg:province":"Alicante",
    "wof:name":"Albaladejo Y Gonzalez S.l.",
    "wof:placetype":"venue"
},
  "geometry": {"coordinates":[-0.6721752286,37.9906845093],"type":"Point"}
}