{
  "type": "Feature",
  "properties": {
    "iso:country":"ES",
    "sg:address":"Veracruz, S/n",
    "sg:city":"Villanueva Arzobispo",
    "sg:orig_category":"Iglesia Cat\u00d3lica",
    "sg:phone":"+34 953 45 08 48",
    "sg:postcode":"23330",
    "sg:province":"Ja\u00e9n",
    "wof:name":"Parroquia De La Vera Cruz",
    "wof:placetype":"venue"
},
  "geometry": {"coordinates":[-3.0073859692,38.1700553894],"type":"Point"}
}