{
  "type": "Feature",
  "properties": {
    "iso:country":"ES",
    "sg:address":"Av Ramon I Cajal, 27",
    "sg:city":"Tarragona",
    "sg:orig_category":"Centros Empresariales",
    "sg:phone":"+34 977 21 59 84",
    "sg:postcode":"43001",
    "sg:province":"Tarragona",
    "wof:name":"Funyir Tarragona Seguros S.l.",
    "wof:placetype":"venue"
},
  "geometry": {"coordinates":[1.2463209629,41.1164779663],"type":"Point"}
}