{
  "type": "Feature",
  "properties": {
    "iso:country":"ES",
    "sg:address":"Carrer de Felip Ii, 189",
    "sg:city":"Barcelona",
    "sg:classifiers":[
        {
            "category":"Autos & Motor Vehicles",
            "subcategory":"Automobile Sales",
            "type":"Retail Goods"
        }
    ],
    "sg:phone":"+34 934 08 45 85",
    "sg:postcode":"08027",
    "sg:province":"Barcelona",
    "sg:website":"www.felipii.com",
    "wof:name":"Aguilar Parejo Ana Maria",
    "wof:placetype":"venue"
},
  "geometry": {"coordinates":[2.1798849106,41.4257507324],"type":"Point"}
}