{
  "type": "Feature",
  "properties": {
    "iso:country":"ES",
    "sg:address":"M. De Abastos, S/n",
    "sg:city":"Estepona",
    "sg:orig_category":"Carnicer\u00cdas, Carnicer\u00cdas",
    "sg:phone":"+34 952 80 16 91",
    "sg:postcode":"29680",
    "sg:province":"M\u00e1laga",
    "wof:name":"Pagan Diaz Ana Maria",
    "wof:placetype":"venue"
},
  "geometry": {"coordinates":[-5.1452140808,36.4275817871],"type":"Point"}
}