{
  "type": "Feature",
  "properties": {
    "addr:full":"Calle de Iglesia (la) (corralejo), 5 Corralejo Las Palmas 35660",
    "addr:housenumber":"5",
    "addr:postcode":"35660",
    "addr:street":"Calle De Iglesia La Corralejo",
    "iso:country":"ES",
    "sg:address":"Calle de Iglesia (la) (corralejo), 5",
    "sg:city":"Corralejo",
    "sg:orig_category":"Artesan\u00cda",
    "sg:phone":"+34 928 53 53 38",
    "sg:postcode":"35660",
    "sg:province":"Las Palmas",
    "wof:name":"La Fuentita S.c.p",
    "wof:placetype":"venue"
},
  "geometry": {"coordinates":[-13.8673887253,28.7396507263],"type":"Point"}
}