{
  "type": "Feature",
  "properties": {
    "addr:full":"Cno. La Boquera, S/n Barbastro Huesca 22300",
    "addr:housenumber":"s / n",
    "addr:postcode":"22300",
    "addr:street":"Cno. La Boquera",
    "iso:country":"ES",
    "sg:address":"Cno. La Boquera, S/n",
    "sg:city":"Barbastro",
    "sg:orig_category":"Panader\u00cdas, Pasteler\u00cdas, Boller\u00cda Industriale (fabricaci\u00d3n, Al Por Mayor)",
    "sg:phone":"+34 974 31 42 38",
    "sg:postcode":"22300",
    "sg:province":"Huesca",
    "sg:website":"www.terra.es/personal/pasomon",
    "wof:name":"Pasteleria Del Somontano S.l.",
    "wof:placetype":"venue"
},
  "geometry": {"coordinates":[0.1630579978,42.006603241],"type":"Point"}
}