{
  "type": "Feature",
  "properties": {
    "addr:full":"Calle de Estoril, 19 Torremolinos M\u00e1laga 29620",
    "addr:housenumber":"19",
    "addr:postcode":"29620",
    "addr:street":"Calle De Estoril;Ma\u0301Laga",
    "iso:country":"ES",
    "sg:address":"Calle de Estoril, 19",
    "sg:city":"Torremolinos",
    "sg:orig_category":"Ingenier\u00cda, Centros De Estudios (diversos)",
    "sg:phone":"+34 952 38 39 66",
    "sg:postcode":"29620",
    "sg:province":"M\u00e1laga",
    "wof:name":"Amain S.l.",
    "wof:placetype":"venue"
},
  "geometry": {"coordinates":[-4.4845762253,36.6445884705],"type":"Point"}
}