{
  "type": "Feature",
  "properties": {
    "iso:country":"ES",
    "sg:address":"Calle de Ingeniero Francisco Ruiz Martinez, 20",
    "sg:city":"Ubrique",
    "sg:orig_category":"Molduras, Junquillos, Listones Y Molduras Perforadas",
    "sg:phone":"+34 956 46 25 96",
    "sg:postcode":"11600",
    "sg:province":"C\u00e1diz",
    "wof:name":"Lobato Dominguez Francisco",
    "wof:placetype":"venue"
},
  "geometry": {"coordinates":[-5.4440670013,36.677570343],"type":"Point"}
}