{
  "type": "Feature",
  "properties": {
    "iso:country":"ES",
    "sg:address":"Rua Adro, 38",
    "sg:city":"Redondela",
    "sg:orig_category":"Arquitectos",
    "sg:phone":"+34 986 40 99 56",
    "sg:postcode":"36800",
    "sg:province":"Pontevedra",
    "wof:name":"Jose A Cuntin S.l.",
    "wof:placetype":"venue"
},
  "geometry": {"coordinates":[-8.6076841354,42.2825508118],"type":"Point"}
}