{
  "type": "Feature",
  "properties": {
    "addr:full":"Calle de Argentina, 46 Arrecife Las Palmas 35500",
    "addr:housenumber":"46",
    "addr:postcode":"35500",
    "addr:street":"Calle De Argentina",
    "iso:country":"ES",
    "sg:address":"Calle de Argentina, 46",
    "sg:city":"Arrecife",
    "sg:orig_category":"Molduras, Junquillos, Listones Y Molduras Perforadas",
    "sg:phone":"+34 928 80 62 37",
    "sg:postcode":"35500",
    "sg:province":"Las Palmas",
    "wof:name":"Fernandez Perez Jesus",
    "wof:placetype":"venue"
},
  "geometry": {"coordinates":[-13.5555582047,28.9615192413],"type":"Point"}
}