{
  "type": "Feature",
  "properties": {
    "iso:country":"ES",
    "sg:address":"Avda Juan Carlos I, 26",
    "sg:city":"Almu\u00f1ecar",
    "sg:orig_category":"Agentes Generales De Seguros",
    "sg:phone":"+34 958 63 51 48",
    "sg:postcode":"18690",
    "sg:province":"Granada",
    "wof:name":"Ozaeta Y Rodriguez S.l.",
    "wof:placetype":"venue"
},
  "geometry": {"coordinates":[-3.6871330738,36.7318458557],"type":"Point"}
}