{
  "type": "Feature",
  "properties": {
    "addr:full":"Avda Juan Carlos I, 26 Almu\u00f1ecar Granada 18690",
    "addr:housenumber":"26",
    "addr:postcode":"18690",
    "addr:street":"Avda Juan Carlos I",
    "iso:country":"ES",
    "sg:address":"Avda Juan Carlos I, 26",
    "sg:city":"Almu\u00f1ecar",
    "sg:orig_category":"Agentes Generales De Seguros",
    "sg:phone":"+34 958 63 51 48",
    "sg:postcode":"18690",
    "sg:province":"Granada",
    "wof:name":"Ozaeta Y Rodriguez S.l.",
    "wof:placetype":"venue"
},
  "geometry": {"coordinates":[-3.6871330738,36.7318458557],"type":"Point"}
}