{
  "type": "Feature",
  "properties": {
    "iso:country":"ES",
    "sg:address":"Calle de Niebla, 36",
    "sg:city":"Sevilla",
    "sg:orig_category":"Zapater\u00cdas",
    "sg:phone":"+34 954 45 06 04",
    "sg:postcode":"41011",
    "sg:province":"Sevilla",
    "wof:name":"Walls Barragan Maria Dolores",
    "wof:placetype":"venue"
},
  "geometry": {"coordinates":[-6.0012717247,37.377368927],"type":"Point"}
}