{
  "type": "Feature",
  "properties": {
    "iso:country":"ES",
    "sg:address":"Calle de Manuel Fal Conde, 10",
    "sg:city":"Sevilla",
    "sg:orig_category":"Empresas De Limpieza",
    "sg:phone":"+34 954 23 62 63",
    "sg:postcode":"41013",
    "sg:province":"Sevilla",
    "wof:name":"Teclimsur S.l",
    "wof:placetype":"venue"
},
  "geometry": {"coordinates":[-5.9721398354,37.3570976257],"type":"Point"}
}