{
  "type": "Feature",
  "properties": {
    "iso:country":"ES",
    "sg:address":"Calle de Queipo De Llano, 37",
    "sg:city":"Paredes Nava",
    "sg:orig_category":"Aparatos De Iluminaci\u00d3n (al Por Menor)",
    "sg:phone":"+34 979 83 07 91",
    "sg:postcode":"34300",
    "sg:province":"Palencia",
    "wof:name":"Baron Hoyos Mario",
    "wof:placetype":"venue"
},
  "geometry": {"coordinates":[-4.6914391518,42.1510887146],"type":"Point"}
}