{
  "type": "Feature",
  "properties": {
    "addr:full":"Calle de Triana, S/n Ibros Ja\u00e9n 23450",
    "addr:housenumber":"s / n",
    "addr:postcode":"23450",
    "addr:street":"Calle De Triana;Jae\u0301N",
    "iso:country":"ES",
    "sg:address":"Calle de Triana, S/n",
    "sg:city":"Ibros",
    "sg:orig_category":"Construcciones Met\u00c1licas",
    "sg:phone":"+34 953 76 63 03",
    "sg:postcode":"23450",
    "sg:province":"Ja\u00e9n",
    "wof:name":"Marin Rodriguez Francisco",
    "wof:placetype":"venue"
},
  "geometry": {"coordinates":[-3.5010960102,38.0249061584],"type":"Point"}
}