{
  "type": "Feature",
  "properties": {
    "addr:full":"Avda Cervantes, 23 Viveiro Lugo 27850",
    "addr:housenumber":"23",
    "addr:postcode":"27850",
    "addr:street":"Avda Cervantes",
    "iso:country":"ES",
    "sg:address":"Avda Cervantes, 23",
    "sg:city":"Viveiro",
    "sg:orig_category":"Organizaciones Profesionales",
    "sg:phone":"+34 982 56 13 10",
    "sg:postcode":"27850",
    "sg:province":"Lugo",
    "wof:name":"Mateos Chao Mariano Pablo",
    "wof:placetype":"venue"
},
  "geometry": {"coordinates":[-7.5931239128,43.6628684998],"type":"Point"}
}