{
  "type": "Feature",
  "properties": {
    "iso:country":"ES",
    "sg:address":"Masia Nadal, S/n",
    "sg:city":"Morella",
    "sg:orig_category":"Alquiler De Gr\u00daas",
    "sg:phone":"+34 964 16 10 28",
    "sg:postcode":"12300",
    "sg:province":"Castell\u00f3n",
    "wof:name":"Marti Iba\u00f1ez Alberto",
    "wof:placetype":"venue"
},
  "geometry": {"coordinates":[-0.0977939963,40.6189155579],"type":"Point"}
}