{
  "type": "Feature",
  "properties": {
    "addr:full":"Calle de Ailanto, 25 Madrid Madrid 28029",
    "addr:housenumber":"25",
    "addr:postcode":"madrid;28029",
    "addr:street":"Calle De Ailanto",
    "iso:country":"ES",
    "sg:address":"Calle de Ailanto, 25",
    "sg:city":"Madrid",
    "sg:orig_category":"Mec\u00c1nico Del Autom\u00d3vil",
    "sg:phone":"+34 913 15 85 85",
    "sg:postcode":"28029",
    "sg:province":"Madrid",
    "wof:name":"Talleres Ritmo S.l.",
    "wof:placetype":"venue"
},
  "geometry": {"coordinates":[-3.6926455498,40.4696884155],"type":"Point"}
}