{
  "type": "Feature",
  "properties": {
    "addr:full":"Calle de Eusebio Navarro, 53 Palmas De Gran Canaria Las Palmas 35003",
    "addr:postcode":"35003",
    "addr:street":"Calle De Eusebio Navarro 53",
    "iso:country":"ES",
    "sg:address":"Calle de Eusebio Navarro, 53",
    "sg:city":"Palmas De Gran Canaria",
    "sg:orig_category":"Abogados",
    "sg:phone":"+34 928 36 17 58",
    "sg:postcode":"35003",
    "sg:province":"Las Palmas",
    "wof:name":"Fernandez Manrique De Lara Jose Javier",
    "wof:placetype":"venue"
},
  "geometry": {"coordinates":[-15.4213581085,28.1112384796],"type":"Point"}
}