{
  "type": "Feature",
  "properties": {
    "addr:full":"Calle de Cervantes, 1 Fuente Cantos Badajoz 06240",
    "addr:housenumber":"1",
    "addr:postcode":"06240",
    "addr:street":"Calle De Cervantes",
    "iso:country":"ES",
    "sg:address":"Calle de Cervantes, 1",
    "sg:city":"Fuente Cantos",
    "sg:orig_category":"Estancos",
    "sg:phone":"+34 924 58 01 55",
    "sg:postcode":"06240",
    "sg:province":"Badajoz",
    "wof:name":"Rebolledo Toro Manuel Antonio",
    "wof:placetype":"venue"
},
  "geometry": {"coordinates":[-6.3089342117,38.2464103699],"type":"Point"}
}