{
  "type": "Feature",
  "properties": {
    "addr:full":"Ipintza Kalea, 19 Lezo Guip\u00f9zcoa 20100",
    "addr:housenumber":"19",
    "addr:postcode":"20100",
    "addr:street":"Ipintza Kalea;Guipu\u0300Zcoa",
    "iso:country":"ES",
    "sg:address":"Ipintza Kalea, 19",
    "sg:city":"Lezo",
    "sg:orig_category":"Pintura Industrial (trabajos De)",
    "sg:phone":"+34 943 34 45 54",
    "sg:postcode":"20100",
    "sg:province":"Guip\u00f9zcoa",
    "wof:name":"Lepoxi S.a.",
    "wof:placetype":"venue"
},
  "geometry": {"coordinates":[-1.8762619495,43.3248214722],"type":"Point"}
}