{
  "type": "Feature",
  "properties": {
    "iso:country":"ES",
    "sg:address":"Calle de Vicente Aleixandre, 24",
    "sg:city":"Vitoria-gasteiz",
    "sg:orig_category":"Arquitectos",
    "sg:phone":"+34 945 27 58 64",
    "sg:postcode":"01003",
    "sg:province":"\u00c1lava",
    "wof:name":"Nuevas Tecnicas De Construccion Nuteco S.l.",
    "wof:placetype":"venue"
},
  "geometry": {"coordinates":[-2.6566131115,42.8428459167],"type":"Point"}
}