{
  "type": "Feature",
  "properties": {
    "iso:country":"ES",
    "sg:address":"Calle de Arturo Soria, 146",
    "sg:city":"Madrid",
    "sg:orig_category":"Asilos De Ancianos. Centros Privados",
    "sg:phone":"+34 914 15 72 52",
    "sg:postcode":"28043",
    "sg:province":"Madrid",
    "wof:name":"Sanitas Residencial S.l.",
    "wof:placetype":"venue"
},
  "geometry": {"coordinates":[-3.6534831524,40.4525985718],"type":"Point"}
}