{
  "type": "Feature",
  "properties": {
    "iso:country":"ES",
    "sg:address":"Carrer de Abat Escarre, 14",
    "sg:city":"S. Boi Llobregat",
    "sg:orig_category":"Extinci\u00d3n De Incendios: Material Y Suministros (fabricaci\u00d3n, Al Por Mayor)",
    "sg:phone":"+34 936 54 48 22",
    "sg:postcode":"08830",
    "sg:province":"Barcelona",
    "wof:name":"Arias Ruiz Jordi",
    "wof:placetype":"venue"
},
  "geometry": {"coordinates":[2.0305001736,41.3441238403],"type":"Point"}
}