{
  "type": "Feature",
  "properties": {
    "addr:full":"Calle de Avila, 8 Soria Soria 42001",
    "addr:housenumber":"8",
    "addr:postcode":"42001",
    "addr:street":"Calle De Avila",
    "iso:country":"ES",
    "sg:address":"Calle de Avila, 8",
    "sg:city":"Soria",
    "sg:orig_category":"Administradores De Bienes Y Delegados De Comunidades De Propietarios",
    "sg:phone":"+34 975 22 50 75",
    "sg:postcode":"42001",
    "sg:province":"Soria",
    "wof:name":"Grande Alonso Raul",
    "wof:placetype":"venue"
},
  "geometry": {"coordinates":[-2.4768204689,41.7667999268],"type":"Point"}
}