{
  "type": "Feature",
  "properties": {
    "iso:country":"ES",
    "sg:address":"Carrer de Camprecios, 24",
    "sg:city":"Barcelona",
    "sg:orig_category":"Empresas De Carpinter\u00cda Met\u00c1lica",
    "sg:phone":"+34 933 53 16 55",
    "sg:postcode":"08042",
    "sg:province":"Barcelona",
    "wof:name":"Pe\u00f1uela Gutierrez Jesus",
    "wof:placetype":"venue"
},
  "geometry": {"coordinates":[2.1774179935,41.4466285706],"type":"Point"}
}