{
  "type": "Feature",
  "properties": {
    "iso:country":"ES",
    "sg:address":"Leizeaga Kalea, 8",
    "sg:city":"Bergara",
    "sg:orig_category":"Sierras (fabricaci\u00d3n, Al Por Mayor)",
    "sg:phone":"+34 943 76 26 78",
    "sg:postcode":"20570",
    "sg:province":"Guip\u00f9zcoa",
    "sg:website":"www.adegi.es/zuber",
    "wof:name":"Zuber S.a.",
    "wof:placetype":"venue"
},
  "geometry": {"coordinates":[-2.4249150753,43.1224212646],"type":"Point"}
}