{
  "type": "Feature",
  "properties": {
    "addr:full":"Pase Canteras Las, 68 Palmas De Gran Canaria Las Palmas 35010",
    "addr:postcode":"35010",
    "addr:street":"Las 68",
    "iso:country":"ES",
    "sg:address":"Pase Canteras Las, 68",
    "sg:city":"Palmas De Gran Canaria",
    "sg:orig_category":"Molduras, Junquillos, Listones Y Molduras Perforadas",
    "sg:phone":"+34 928 22 65 10",
    "sg:postcode":"35010",
    "sg:province":"Las Palmas",
    "wof:name":"Explotacion Zuritasa S.l.",
    "wof:placetype":"venue"
},
  "geometry": {"coordinates":[-15.4397087097,28.1302242279],"type":"Point"}
}