{
  "type": "Feature",
  "properties": {
    "iso:country":"ES",
    "sg:address":"Avda Marques De Corbera, 44",
    "sg:city":"Madrid",
    "sg:orig_category":"Inmobiliaria (agencias)",
    "sg:phone":"+34 914 05 42 29",
    "sg:postcode":"28017",
    "sg:province":"Madrid",
    "wof:name":"Jimenez Coca Gestion Inmobiliaria S.l.",
    "wof:placetype":"venue"
},
  "geometry": {"coordinates":[-3.6521120071,40.425327301],"type":"Point"}
}