{
  "type": "Feature",
  "properties": {
    "iso:country":"ES",
    "sg:address":"Avda Fragoso, 17",
    "sg:city":"Vigo",
    "sg:orig_category":"Procuradores",
    "sg:phone":"+34 986 29 70 28",
    "sg:postcode":"36210",
    "sg:province":"Pontevedra",
    "wof:name":"Barreiro Carrillo Marta",
    "wof:placetype":"venue"
},
  "geometry": {"coordinates":[-8.7332754135,42.2191772461],"type":"Point"}
}