{
  "type": "Feature",
  "properties": {
    "addr:full":"Calle de Rio Pelayo, 1 Torrejon Ardoz Madrid 28850",
    "addr:housenumber":"1",
    "addr:postcode":"28850",
    "addr:street":"Calle De Rio Pelayo",
    "iso:country":"ES",
    "sg:address":"Calle de Rio Pelayo, 1",
    "sg:city":"Torrejon Ardoz",
    "sg:orig_category":"Institutos De Belleza",
    "sg:phone":"+34 916 78 04 88",
    "sg:postcode":"28850",
    "sg:province":"Madrid",
    "wof:name":"Alejo Campos Marisol",
    "wof:placetype":"venue"
},
  "geometry": {"coordinates":[-3.7003455162,40.4166908264],"type":"Point"}
}