{
  "type": "Feature",
  "properties": {
    "addr:full":"Avda Palencia, 33 Valladolid Valladolid 47010",
    "addr:housenumber":"33",
    "addr:postcode":"47010",
    "addr:street":"Avda Palencia",
    "iso:country":"ES",
    "sg:address":"Avda Palencia, 33",
    "sg:city":"Valladolid",
    "sg:orig_category":"Empresas De Carpinter\u00cda De Madera",
    "sg:phone":"+34 983 25 77 45",
    "sg:postcode":"47010",
    "sg:province":"Valladolid",
    "wof:name":"Castillo Garrido Jose Manuel",
    "wof:placetype":"venue"
},
  "geometry": {"coordinates":[-4.7176599503,41.6607475281],"type":"Point"}
}