{
  "type": "Feature",
  "properties": {
    "iso:country":"ES",
    "sg:address":"Av Carrilet, 351",
    "sg:city":"Hospitalet Llobregat",
    "sg:orig_category":"Muebles Y Accesorios Para Cocinas Y Cuartos De Ba\u00d1o (al Por Menor)",
    "sg:phone":"+34 933 38 34 34",
    "sg:postcode":"08907",
    "sg:province":"Barcelona",
    "wof:name":"Alvic Fr. Mobiliario S.l.",
    "wof:placetype":"venue"
},
  "geometry": {"coordinates":[2.099101305,41.3561973572],"type":"Point"}
}