{
  "type": "Feature",
  "properties": {
    "addr:full":"Carrer de Bambu, 2 Cornella Llobregat Barcelona 08940",
    "addr:postcode":"08940",
    "addr:street":"Carrer De Bambu 2",
    "iso:country":"ES",
    "sg:address":"Carrer de Bambu, 2",
    "sg:city":"Cornella Llobregat",
    "sg:orig_category":"Venta Al Preg\u00d3n",
    "sg:phone":"+34 933 76 27 34",
    "sg:postcode":"08940",
    "sg:province":"Barcelona",
    "wof:name":"Martinez Rosa Carmen",
    "wof:placetype":"venue"
},
  "geometry": {"coordinates":[2.0802481174,41.3638153076],"type":"Point"}
}