{
  "type": "Feature",
  "properties": {
    "addr:full":"Ctr. Torrelaguna, 303 Torrejon Rey Guadalajara 19174",
    "addr:housenumber":"303",
    "addr:postcode":"19174",
    "addr:street":"Torrelaguna;Rey",
    "iso:country":"ES",
    "sg:address":"Ctr. Torrelaguna, 303",
    "sg:city":"Torrejon Rey",
    "sg:orig_category":"Inmobiliaria (agencias)",
    "sg:phone":"+34 949 33 95 92",
    "sg:postcode":"19174",
    "sg:province":"Guadalajara",
    "wof:name":"Inmolaqui S.l.",
    "wof:placetype":"venue"
},
  "geometry": {"coordinates":[-3.336879015,40.6445465088],"type":"Point"}
}