{
  "type": "Feature",
  "properties": {
    "iso:country":"ES",
    "sg:address":"Calle de Gamazo, 23",
    "sg:city":"Valladolid",
    "sg:orig_category":"M\u00c9dicos: Medicina General",
    "sg:phone":"+34 983 30 72 38",
    "sg:postcode":"47004",
    "sg:province":"Valladolid",
    "wof:name":"Guerro Cerrato Delio Ignacio",
    "wof:placetype":"venue"
},
  "geometry": {"coordinates":[-4.7262840271,41.6454391479],"type":"Point"}
}