{
  "type": "Feature",
  "properties": {
    "addr:full":"Trva Andres Mellado, 3 Madrid Madrid 28015",
    "addr:housenumber":"3",
    "addr:postcode":"28015",
    "addr:street":"Trva Andres Mellado",
    "iso:country":"ES",
    "sg:address":"Trva Andres Mellado, 3",
    "sg:city":"Madrid",
    "sg:orig_category":"Ense\u00d1anza Variada",
    "sg:phone":"+34 915 43 15 63",
    "sg:postcode":"28015",
    "sg:province":"Madrid",
    "wof:name":"Aerea Flying Training Organization S.a.",
    "wof:placetype":"venue"
},
  "geometry": {"coordinates":[-3.7105116844,40.4304542542],"type":"Point"}
}