{
  "type": "Feature",
  "properties": {
    "iso:country":"ES",
    "sg:address":"Calle de General Chamorro Martinez, S/n",
    "sg:city":"Sevilla",
    "sg:orig_category":"Agencias Y Agentes Comerciales, Representantes",
    "sg:phone":"+34 954 35 75 64",
    "sg:postcode":"41008",
    "sg:province":"Sevilla",
    "wof:name":"Matas Moreno Angel Bartolome",
    "wof:placetype":"venue"
},
  "geometry": {"coordinates":[-5.9717288017,37.4073295593],"type":"Point"}
}