{
  "type": "Feature",
  "properties": {
    "addr:full":"Ctra Co-761 Moriles-navas, Km. 0000,5 Moriles C\u00f3rdoba 14510",
    "addr:postcode":"14510",
    "addr:street":"Ctra Co-761 Moriles-Navas Km. 0000,5",
    "iso:country":"ES",
    "sg:address":"Ctra Co-761 Moriles-navas, Km. 0000,5",
    "sg:city":"Moriles",
    "sg:orig_category":"Muebles",
    "sg:phone":"+34 957 53 71 28",
    "sg:postcode":"14510",
    "sg:province":"C\u00f3rdoba",
    "wof:name":"Silleria Burguillos S.l.",
    "wof:placetype":"venue"
},
  "geometry": {"coordinates":[-4.6082291603,37.4353485107],"type":"Point"}
}