{
  "type": "Feature",
  "properties": {
    "addr:full":"Calle de Rey Juan Carlos I, 39 Elda Alicante 03600",
    "addr:housenumber":"39",
    "addr:postcode":"03600",
    "addr:street":"Calle De Rey Juan Carlos I",
    "iso:country":"ES",
    "sg:address":"Calle de Rey Juan Carlos I, 39",
    "sg:city":"Elda",
    "sg:orig_category":"Complementos De Vestir (al Por Menor)",
    "sg:phone":"+34 965 38 15 25",
    "sg:postcode":"03600",
    "sg:province":"Alicante",
    "wof:name":"Vera Maestre Rocio",
    "wof:placetype":"venue"
},
  "geometry": {"coordinates":[-0.7920219898,38.4785308838],"type":"Point"}
}