{
  "type": "Feature",
  "properties": {
    "addr:full":"Carrer de Valles I Ribot, 2 Palleja Barcelona 08780",
    "addr:housenumber":"2",
    "addr:postcode":"08780",
    "addr:street":"Carrer De Valles I Ribot",
    "iso:country":"ES",
    "sg:address":"Carrer de Valles I Ribot, 2",
    "sg:city":"Palleja",
    "sg:orig_category":"Fabricaci\u00d3n De Material Y Sistemas De Se\u00d1alizaci\u00d3n De Carreteras, Urbanos Y De Obras",
    "sg:phone":"+34 936 63 30 74",
    "sg:postcode":"08780",
    "sg:province":"Barcelona",
    "wof:name":"Innovacion Vision Solar S.l.",
    "wof:placetype":"venue"
},
  "geometry": {"coordinates":[1.9977860451,41.4211578369],"type":"Point"}
}