{
  "type": "Feature",
  "properties": {
    "addr:full":"Calle de Infanta Mercedes, 115 Madrid Madrid 28020",
    "addr:housenumber":"115",
    "addr:postcode":"28020",
    "addr:street":"Calle De Infanta Mercedes",
    "iso:country":"ES",
    "sg:address":"Calle de Infanta Mercedes, 115",
    "sg:city":"Madrid",
    "sg:orig_category":"Agencias Y Agentes Comerciales, Representantes",
    "sg:phone":"+34 915 70 63 95",
    "sg:postcode":"28020",
    "sg:province":"Madrid",
    "wof:name":"Arrlo S.l.",
    "wof:placetype":"venue"
},
  "geometry": {"coordinates":[-3.6928005219,40.4642906189],"type":"Point"}
}