{
  "type": "Feature",
  "properties": {
    "addr:full":"Avda Ricardo Carapeto Zambrano, 98 Badajoz Badajoz 06008",
    "addr:housenumber":"98",
    "addr:postcode":"06008",
    "addr:street":"Avda Ricardo Carapeto Zambrano",
    "iso:country":"ES",
    "sg:address":"Avda Ricardo Carapeto Zambrano, 98",
    "sg:city":"Badajoz",
    "sg:orig_category":"Loter\u00cda Y T\u00d3mbola",
    "sg:phone":"+34 924 24 98 88",
    "sg:postcode":"06008",
    "sg:province":"Badajoz",
    "wof:name":"Mangas Garcia Maria Soledad",
    "wof:placetype":"venue"
},
  "geometry": {"coordinates":[-6.9473338127,38.8786468506],"type":"Point"}
}