{
  "type": "Feature",
  "properties": {
    "addr:full":"Via Arquimedes (de), 1 Boisaca La Coru\u00f1a 15890",
    "addr:postcode":"15890",
    "addr:street":"Via Arquimedes De 1 Boisaca La Corun\u0303A",
    "iso:country":"ES",
    "sg:address":"Via Arquimedes (de), 1",
    "sg:city":"Boisaca",
    "sg:orig_category":"Quincaller\u00cda (al Por Menor)",
    "sg:phone":"+34 981 58 60 22",
    "sg:postcode":"15890",
    "sg:province":"La Coru\u00f1a",
    "wof:name":"Ferrecal S. A.",
    "wof:placetype":"venue"
},
  "geometry": {"coordinates":[-8.4769210815,42.8835983276],"type":"Point"}
}