{
  "type": "Feature",
  "properties": {
    "addr:full":"Calle de Resolana, S/n Salteras Sevilla 41909",
    "addr:housenumber":"s / n",
    "addr:postcode":"41909",
    "addr:street":"Calle De Resolana",
    "iso:country":"ES",
    "sg:address":"Calle de Resolana, S/n",
    "sg:city":"Salteras",
    "sg:orig_category":"Complementos Para Pasteler\u00cdas, Confiter\u00cdas Y Chocolater\u00cdas",
    "sg:phone":"+34 955 70 73 92",
    "sg:postcode":"41909",
    "sg:province":"Sevilla",
    "wof:name":"Alonso Silva E Hijos Sll",
    "wof:placetype":"venue"
},
  "geometry": {"coordinates":[-6.1136307716,37.4191169739],"type":"Point"}
}