{
  "type": "Feature",
  "properties": {
    "addr:full":"Calle de Prado, S/n Navahermosa Toledo 45150",
    "addr:housenumber":"s / n",
    "addr:postcode":"45150",
    "addr:street":"Calle De Prado",
    "iso:country":"ES",
    "sg:address":"Calle de Prado, S/n",
    "sg:city":"Navahermosa",
    "sg:orig_category":"Centros De Educaci\u00d3n Especial",
    "sg:phone":"+34 925 41 03 84",
    "sg:postcode":"45150",
    "sg:province":"Toledo",
    "wof:name":"Colegio Nacional San Miguel Arcangel",
    "wof:placetype":"venue"
},
  "geometry": {"coordinates":[-4.4682807922,39.6366500854],"type":"Point"}
}