{
  "type": "Feature",
  "properties": {
    "addr:full":"Carr Cova Santa, 11 Vilavella Castell\u00f3n 12526",
    "addr:housenumber":"11",
    "addr:postcode":"12526",
    "addr:street":"Carr Cova Santa;Castello\u0301N",
    "iso:country":"ES",
    "sg:address":"Carr Cova Santa, 11",
    "sg:city":"Vilavella",
    "sg:orig_category":"Cajas Para Embalar",
    "sg:phone":"+34 964 67 80 00",
    "sg:postcode":"12526",
    "sg:province":"Castell\u00f3n",
    "wof:name":"Caja Rural Villavieja",
    "wof:placetype":"venue"
},
  "geometry": {"coordinates":[-0.0456800014,39.9851417542],"type":"Point"}
}