{
  "type": "Feature",
  "properties": {
    "iso:country":"ES",
    "sg:address":"Ctr. Csta. Reina, S/n",
    "sg:city":"Sese\u00f1a Nuevo",
    "sg:orig_category":"Transportes Internacionales",
    "sg:phone":"+34 918 01 29 73",
    "sg:postcode":"45224",
    "sg:province":"Toledo",
    "sg:website":"www.dhl.com",
    "wof:name":"Exel Iberia Grupo S.l.spain S.l.u.",
    "wof:placetype":"venue"
},
  "geometry": {"coordinates":[-3.6464540958,40.1091346741],"type":"Point"}
}