{
  "type": "Feature",
  "properties": {
    "iso:country":"ES",
    "sg:address":"Avda Martin Alonso Pinzon, 14",
    "sg:city":"Huelva",
    "sg:orig_category":"Asesor\u00cdas",
    "sg:phone":"+34 959 25 63 59",
    "sg:postcode":"21003",
    "sg:province":"Huelva",
    "wof:name":"Ergos Consultores S.l.",
    "wof:placetype":"venue"
},
  "geometry": {"coordinates":[-6.9486551285,37.255695343],"type":"Point"}
}