{
  "type": "Feature",
  "properties": {
    "iso:country":"ES",
    "sg:address":"Plaz Espa\u00d1a, 1",
    "sg:city":"Valencia Del Mombuey",
    "sg:orig_category":"Administraciones Regionales, Departamentales Y Locales",
    "sg:phone":"+34 924 42 91 77",
    "sg:postcode":"06134",
    "sg:province":"Badajoz",
    "wof:name":"Ayuntamiento De Valencia Del Mombuey",
    "wof:placetype":"venue"
},
  "geometry": {"coordinates":[-7.1036396027,38.2386283875],"type":"Point"}
}