{
  "type": "Feature",
  "properties": {
    "iso:country":"ES",
    "sg:address":"Calle de Neveral, S/n",
    "sg:city":"Jaen",
    "sg:orig_category":"Asesor\u00cda, Estudio Y Control Medioambiental",
    "sg:phone":"+34 953 23 16 10",
    "sg:postcode":"23002",
    "sg:province":"Ja\u00e9n",
    "wof:name":"Empresa De Gestion Medio Ambiental S.a.",
    "wof:placetype":"venue"
},
  "geometry": {"coordinates":[-3.7952990532,37.7629966736],"type":"Point"}
}