{
  "type": "Feature",
  "properties": {
    "addr:full":"Fca. Campocerrado, S/n Martin De Yeltes Salamanca 37494",
    "addr:housenumber":"s / n",
    "addr:postcode":"37494",
    "iso:country":"ES",
    "sg:address":"Fca. Campocerrado, S/n",
    "sg:city":"Martin De Yeltes",
    "sg:orig_category":"Cr\u00cda De Animales",
    "sg:phone":"+34 923 16 42 02",
    "sg:postcode":"37494",
    "sg:province":"Salamanca",
    "wof:name":"Cobaleda Gajate Habacuc",
    "wof:placetype":"venue"
},
  "geometry": {"coordinates":[-6.2568230629,40.7408714294],"type":"Point"}
}