{
  "type": "Feature",
  "properties": {
    "addr:full":"Av Jaume I, 23 Mollet Valles Barcelona 08100",
    "addr:housenumber":"23",
    "addr:postcode":"08100",
    "addr:street":"Av Jaume I",
    "iso:country":"ES",
    "sg:address":"Av Jaume I, 23",
    "sg:city":"Mollet Valles",
    "sg:orig_category":"Telas Para Tapizar, Cortinas, Pasamaner\u00cda (fabricaci\u00d3n, Al Por Mayor)",
    "sg:phone":"+34 935 93 50 43",
    "sg:postcode":"08100",
    "sg:province":"Barcelona",
    "wof:name":"Santos Caba\u00f1eros Manuel",
    "wof:placetype":"venue"
},
  "geometry": {"coordinates":[2.2120800018,41.5387115479],"type":"Point"}
}