{
  "type": "Feature",
  "properties": {
    "addr:full":"Cmno Pi Gros, S/n Castellon De La Plana Castell\u00f3n 12005",
    "addr:housenumber":"s / n",
    "addr:postcode":"12005",
    "addr:street":"Cmno Pi Gros",
    "iso:country":"ES",
    "sg:address":"Cmno Pi Gros, S/n",
    "sg:city":"Castellon De La Plana",
    "sg:orig_category":"Negocio De Madera",
    "sg:phone":"+34 964 21 64 14",
    "sg:postcode":"12005",
    "sg:province":"Castell\u00f3n",
    "wof:name":"Maderas Farnos S. L.",
    "wof:placetype":"venue"
},
  "geometry": {"coordinates":[-0.0570270009,39.9575424194],"type":"Point"}
}