{
  "type": "Feature",
  "properties": {
    "addr:full":"Grup Sagarminaga, 9 Bilbao Vizcaya 48004",
    "addr:housenumber":"9",
    "addr:postcode":"48004",
    "addr:street":"Grup Sagarminaga",
    "iso:country":"ES",
    "sg:address":"Grup Sagarminaga, 9",
    "sg:city":"Bilbao",
    "sg:orig_category":"Empresas De Pintura Y Revestimientos",
    "sg:phone":"+34 944 11 26 39",
    "sg:postcode":"48004",
    "sg:province":"Vizcaya",
    "wof:name":"Legarreta Guezuraga Juan Ignacio",
    "wof:placetype":"venue"
},
  "geometry": {"coordinates":[-2.9111759663,43.2482376099],"type":"Point"}
}