{
  "type": "Feature",
  "properties": {
    "addr:full":"Sta. Misio, S/n Pallerols Lleida 25213",
    "addr:housenumber":"s / n",
    "addr:postcode":"25213",
    "iso:country":"ES",
    "sg:address":"Sta. Misio, S/n",
    "sg:city":"Pallerols",
    "sg:orig_category":"Cr\u00cda De Animales",
    "sg:phone":"+34 973 54 00 52",
    "sg:postcode":"25213",
    "sg:province":"Lleida",
    "wof:name":"Tous Casanovas Juan",
    "wof:placetype":"venue"
},
  "geometry": {"coordinates":[1.3533799648,41.6186103821],"type":"Point"}
}