{
  "type": "Feature",
  "properties": {
    "iso:country":"ES",
    "sg:address":"Avda Andalucia, 4",
    "sg:city":"Puente Genave",
    "sg:orig_category":"Carnicer\u00cdas, Carnicer\u00cdas",
    "sg:phone":"+34 953 43 54 07",
    "sg:postcode":"23350",
    "sg:province":"Ja\u00e9n",
    "wof:name":"Linares Gutierrez Jose Antonio",
    "wof:placetype":"venue"
},
  "geometry": {"coordinates":[-2.80479002,38.3527832031],"type":"Point"}
}