{
  "type": "Feature",
  "properties": {
    "addr:full":"Calle de Palacios, 24 Puerto De Santa Maria C\u00e1diz 11500",
    "addr:housenumber":"24",
    "addr:postcode":"11500",
    "addr:street":"Calle De Palacios;Ca\u0301Diz",
    "iso:country":"ES",
    "sg:address":"Calle de Palacios, 24",
    "sg:city":"Puerto De Santa Maria",
    "sg:orig_category":"Automatizaci\u00d3n De Procesos Industriales Y De Edificaci\u00d3n (estudios, Instalaci\u00d3n)",
    "sg:phone":"+34 956 86 13 60",
    "sg:postcode":"11500",
    "sg:province":"C\u00e1diz",
    "wof:name":"Laporte Y Moreno S.r.l.",
    "wof:placetype":"venue"
},
  "geometry": {"coordinates":[-6.2260460854,36.5980072021],"type":"Point"}
}