{
  "type": "Feature",
  "properties": {
    "addr:full":"Huerta Mahoya, 7 Abanilla Murcia 30640",
    "addr:housenumber":"7",
    "addr:postcode":"30640",
    "addr:street":"Mahoya",
    "iso:country":"ES",
    "sg:address":"Huerta Mahoya, 7",
    "sg:city":"Abanilla",
    "sg:orig_category":"Restaurantes",
    "sg:phone":"+34 968 68 01 91",
    "sg:postcode":"30640",
    "sg:province":"Murcia",
    "wof:name":"Ruiz Sanchez Jose Miguel",
    "wof:placetype":"venue"
},
  "geometry": {"coordinates":[-1.041031003,38.2053184509],"type":"Point"}
}