{
  "type": "Feature",
  "properties": {
    "addr:full":"Calle de Padre Saturnino Lopez Novoa, 5 Sig\u00fcenza Guadalajara 19250",
    "addr:housenumber":"5",
    "addr:postcode":"19250",
    "addr:street":"Calle De Padre Saturnino Lopez Novoa",
    "iso:country":"ES",
    "sg:address":"Calle de Padre Saturnino Lopez Novoa, 5",
    "sg:city":"Sig\u00fcenza",
    "sg:orig_category":"Ambulancias",
    "sg:phone":"+34 949 39 30 92",
    "sg:postcode":"19250",
    "sg:province":"Guadalajara",
    "wof:name":"Aranda Fernandez Manuel Vicente",
    "wof:placetype":"venue"
},
  "geometry": {"coordinates":[-2.6470348835,41.0657119751],"type":"Point"}
}