{
  "type": "Feature",
  "properties": {
    "iso:country":"ES",
    "sg:address":"Carpinteros, 17",
    "sg:city":"Boadilla Del Monte",
    "sg:orig_category":"Inform\u00c1tica: Material Y Suministros",
    "sg:phone":"+34 911 02 09 51",
    "sg:postcode":"28660",
    "sg:province":"Madrid",
    "wof:name":"Tecologic",
    "wof:placetype":"venue"
},
  "geometry": {"coordinates":[-3.848017931,40.3939170837],"type":"Point"}
}