{
  "type": "Feature",
  "properties": {
    "addr:full":"Calle de Tenderete, 6 Argana Alta Las Palmas 35500",
    "addr:housenumber":"6",
    "addr:postcode":"35500",
    "addr:street":"Calle De Tenderete",
    "iso:country":"ES",
    "sg:address":"Calle de Tenderete, 6",
    "sg:city":"Argana Alta",
    "sg:orig_category":"Fabricaci\u00d3n De Productos L\u00c1cteos Y Derivados",
    "sg:phone":"+34 928 80 30 67",
    "sg:postcode":"35500",
    "sg:province":"Las Palmas",
    "wof:name":"Jose Sanchez Pe\u00f1ate S.a.",
    "wof:placetype":"venue"
},
  "geometry": {"coordinates":[-13.5603542328,28.9716091156],"type":"Point"}
}