{
  "type": "Feature",
  "properties": {
    "iso:country":"ES",
    "sg:address":"Calle de Convento, 2",
    "sg:city":"Cartaya",
    "sg:orig_category":"Bisuter\u00cda, Joyer\u00cda, Relojer\u00cda (al Por Menor)",
    "sg:phone":"+34 959 39 29 65",
    "sg:postcode":"21450",
    "sg:province":"Huelva",
    "wof:name":"Cordero De Acosta Bella",
    "wof:placetype":"venue"
},
  "geometry": {"coordinates":[-7.1529488564,37.2836914062],"type":"Point"}
}