{
  "type": "Feature",
  "properties": {
    "iso:country":"ES",
    "sg:address":"Calle de Tampico, 2",
    "sg:city":"Arrecife",
    "sg:orig_category":"Cl\u00cdnicas Dentales",
    "sg:phone":"+34 928 81 33 90",
    "sg:postcode":"35500",
    "sg:province":"Las Palmas",
    "wof:name":"Cawerud S.l.",
    "wof:placetype":"venue"
},
  "geometry": {"coordinates":[-13.5576562881,28.9649925232],"type":"Point"}
}