{
  "type": "Feature",
  "properties": {
    "iso:country":"ES",
    "sg:address":"Avgd Del Cami Nou, 48",
    "sg:city":"Xirivella",
    "sg:orig_category":"\u00d3ptica: Instrumentos (fabricaci\u00d3n)",
    "sg:phone":"+34 963 59 14 36",
    "sg:postcode":"46950",
    "sg:province":"Valencia",
    "wof:name":"Cotino Sanchis Eduardo Antonio",
    "wof:placetype":"venue"
},
  "geometry": {"coordinates":[-0.4279159904,39.4667396545],"type":"Point"}
}