{
  "type": "Feature",
  "properties": {
    "addr:full":"Rond Outeiro, 202 Coru\u00d1a La Coru\u00f1a 15007",
    "addr:housenumber":"202",
    "addr:postcode":"15007",
    "addr:street":"Outeiro;Corun\u0303A",
    "iso:country":"ES",
    "sg:address":"Rond Outeiro, 202",
    "sg:city":"Coru\u00d1a",
    "sg:classifiers":[
        {
            "category":"Personal",
            "subcategory":"Barber",
            "type":"Services"
        }
    ],
    "sg:phone":"+34 981 24 02 99",
    "sg:postcode":"15007",
    "sg:province":"La Coru\u00f1a",
    "sg:tags":[
        "caballeros",
        "de",
        "peluqueros"
    ],
    "wof:name":"Precedo Riveiro Jose Luis",
    "wof:placetype":"venue"
},
  "geometry": {"coordinates":[-8.7951183319,42.9959411621],"type":"Point"}
}