{
  "type": "Feature",
  "properties": {
    "iso:country":"ES",
    "sg:address":"Calle de Mayor Baja, 18",
    "sg:city":"Perales De Taju\u00e7a",
    "sg:classifiers":[
        {
            "category":"Government",
            "subcategory":"Office",
            "type":"Public Place"
        }
    ],
    "sg:phone":"+34 918 74 80 65",
    "sg:postcode":"28540",
    "sg:province":"Madrid",
    "sg:tags":[
        "interior",
        "administraci\u00d3n",
        "en"
    ],
    "wof:name":"Direccion General De La Guardia Civil",
    "wof:placetype":"venue"
},
  "geometry": {"coordinates":[-3.3524649143,40.2341156006],"type":"Point"}
}