{
  "type": "Feature",
  "properties": {
    "addr:full":"Calle de Moratin, S/n Garrucha Almer\u00eda 04630",
    "addr:housenumber":"s / n",
    "addr:postcode":"04630",
    "addr:street":"Calle De Moratin;Almeri\u0301A",
    "iso:country":"ES",
    "sg:address":"Calle de Moratin, S/n",
    "sg:city":"Garrucha",
    "sg:orig_category":"Plomeros",
    "sg:phone":"+34 950 13 27 43",
    "sg:postcode":"04630",
    "sg:province":"Almer\u00eda",
    "wof:name":"Quesada Molina Pedro",
    "wof:placetype":"venue"
},
  "geometry": {"coordinates":[-1.8241120577,37.1778831482],"type":"Point"}
}