{
  "type": "Feature",
  "properties": {
    "addr:full":"Calle de Agastia, 82 Madrid Madrid 28043",
    "addr:housenumber":"82",
    "addr:postcode":"madrid;28043",
    "addr:street":"Calle De Agastia",
    "iso:country":"ES",
    "sg:address":"Calle de Agastia, 82",
    "sg:city":"Madrid",
    "sg:orig_category":"Centros Empresariales",
    "sg:phone":"+34 914 16 52 44",
    "sg:postcode":"28043",
    "sg:province":"Madrid",
    "wof:name":"Arion 90 S.a.",
    "wof:placetype":"venue"
},
  "geometry": {"coordinates":[-3.6554040909,40.45104599],"type":"Point"}
}