{
  "type": "Feature",
  "properties": {
    "addr:full":"Calle de Sagunto, 10 Linares Ja\u00e9n 23700",
    "addr:housenumber":"10",
    "addr:postcode":"23700",
    "addr:street":"Calle De Sagunto;Jae\u0301N",
    "iso:country":"ES",
    "sg:address":"Calle de Sagunto, 10",
    "sg:city":"Linares",
    "sg:orig_category":"Asociaciones Humanitarias, De Cooperaci\u00d3n, De Acci\u00d3n Social",
    "sg:phone":"+34 953 60 18 78",
    "sg:postcode":"23700",
    "sg:province":"Ja\u00e9n",
    "wof:name":"Asociacion De Enfermos De Crohn Y Colitis Ulcerosas",
    "wof:placetype":"venue"
},
  "geometry": {"coordinates":[-3.6305339336,38.093624115],"type":"Point"}
}