{
  "type": "Feature",
  "properties": {
    "addr:full":"Carrer de Cova Simanya (la), 47 Terrassa Barcelona 08227",
    "addr:housenumber":"47",
    "addr:postcode":"08227",
    "addr:street":"Carrer De Cova Simanya La",
    "iso:country":"ES",
    "sg:address":"Carrer de Cova Simanya (la), 47",
    "sg:city":"Terrassa",
    "sg:orig_category":"Inmobiliaria (agencias)",
    "sg:phone":"+34 937 85 84 17",
    "sg:postcode":"08227",
    "sg:province":"Barcelona",
    "wof:name":"Estudi Sant Lloren\u00c7 Dos Mil Tres Sl",
    "wof:placetype":"venue"
},
  "geometry": {"coordinates":[2.030837059,41.5790023804],"type":"Point"}
}