{
  "type": "Feature",
  "properties": {
    "addr:full":"Riu Ebro, 11 S. Jordi Salines Islas Baleares 07817",
    "addr:housenumber":"11",
    "addr:postcode":"07817",
    "addr:street":"Ebro;S. Jordi",
    "iso:country":"ES",
    "sg:address":"Riu Ebro, 11",
    "sg:city":"S. Jordi Salines",
    "sg:orig_category":"Pintura, Barniz, Productos Asimilables (fabricaci\u00d3n, Al Por Mayor)",
    "sg:phone":"+34 971 30 14 19",
    "sg:postcode":"07817",
    "sg:province":"Islas Baleares",
    "wof:name":"Pinturas Pou S.a.",
    "wof:placetype":"venue"
},
  "geometry": {"coordinates":[1.4075000286,38.8912010193],"type":"Point"}
}