{
  "type": "Feature",
  "properties": {
    "addr:full":"Calle de Horcajo De Las Torres, S/n Arevalo \u00c1vila 05200",
    "addr:postcode":"05200",
    "addr:street":"Calle De Horcajo De Las Torres S / N",
    "iso:country":"ES",
    "sg:address":"Calle de Horcajo De Las Torres, S/n",
    "sg:city":"Arevalo",
    "sg:orig_category":"Electricidad (montaje, Ensamblaje De Componentes)",
    "sg:phone":"+34 920 32 62 94",
    "sg:postcode":"05200",
    "sg:province":"\u00c1vila",
    "wof:name":"Montajes Electricos Cofi\u00f1o S.l.",
    "wof:placetype":"venue"
},
  "geometry": {"coordinates":[-4.7320990562,41.0744552612],"type":"Point"}
}