{
  "type": "Feature",
  "properties": {
    "addr:full":"Carrer de Pareto, 17 Hospitalet Llobregat Barcelona 08902",
    "addr:housenumber":"17",
    "addr:postcode":"08902",
    "addr:street":"Carrer De Pareto",
    "iso:country":"ES",
    "sg:address":"Carrer de Pareto, 17",
    "sg:city":"Hospitalet Llobregat",
    "sg:orig_category":"Marroquiner\u00cda (confecci\u00d3n)",
    "sg:phone":"+34 933 31 47 48",
    "sg:postcode":"08902",
    "sg:province":"Barcelona",
    "wof:name":"Gost Ribell Buenaventura",
    "wof:placetype":"venue"
},
  "geometry": {"coordinates":[2.1273140907,41.3664665222],"type":"Point"}
}