{
  "type": "Feature",
  "properties": {
    "iso:country":"ES",
    "sg:address":"Calle de Capitan Blanco Argibay, 4",
    "sg:city":"Madrid",
    "sg:orig_category":"Prendas De Cuero Y De Piel (al Por Menor)",
    "sg:phone":"+34 915 70 93 40",
    "sg:postcode":"28029",
    "sg:province":"Madrid",
    "wof:name":"Gumpusado S.l.",
    "wof:placetype":"venue"
},
  "geometry": {"coordinates":[-3.6956214905,40.4644813538],"type":"Point"}
}