{
  "type": "Feature",
  "properties": {
    "addr:full":"Calle de Blanca, 9 Zamora Zamora 49027",
    "addr:housenumber":"9",
    "addr:postcode":"49027",
    "addr:street":"Calle De Blanca",
    "iso:country":"ES",
    "sg:address":"Calle de Blanca, 9",
    "sg:city":"Zamora",
    "sg:orig_category":"Electricidad, Electr\u00d3nica: Suministros (al Por Menor)",
    "sg:phone":"+34 980 53 24 21",
    "sg:postcode":"49027",
    "sg:province":"Zamora",
    "wof:name":"Dimoza Zamorana S.l.",
    "wof:placetype":"venue"
},
  "geometry": {"coordinates":[-5.7465434074,41.4917602539],"type":"Point"}
}