{
  "type": "Feature",
  "properties": {
    "iso:country":"ES",
    "sg:address":"Calle de Misericordia (de La), 3",
    "sg:city":"Arganda",
    "sg:orig_category":"Panader\u00cdas, Panader\u00cdas",
    "sg:phone":"+34 918 71 77 09",
    "sg:postcode":"28500",
    "sg:province":"Madrid",
    "wof:name":"Miguel Ortiz Antonio",
    "wof:placetype":"venue"
},
  "geometry": {"coordinates":[-3.4419291019,40.3016891479],"type":"Point"}
}