{
  "type": "Feature",
  "properties": {
    "addr:full":"Calle de San Juan, 44 Gineta Albacete 02110",
    "addr:housenumber":"44",
    "addr:postcode":"02110",
    "addr:street":"Calle De San Juan",
    "iso:country":"ES",
    "sg:address":"Calle de San Juan, 44",
    "sg:city":"Gineta",
    "sg:orig_category":"Reposter\u00cdas",
    "sg:phone":"+34 967 27 50 67",
    "sg:postcode":"02110",
    "sg:province":"Albacete",
    "wof:name":"Hidalgo Cebrian Rodrigo",
    "wof:placetype":"venue"
},
  "geometry": {"coordinates":[-1.9924650192,39.1133575439],"type":"Point"}
}