{
  "type": "Feature",
  "properties": {
    "addr:full":"Torreon, 6 Pontedeume La Coru\u00f1a 15600",
    "addr:postcode":"15600",
    "addr:street":"Torreon;Pontedeume;Corun\u0303A",
    "iso:country":"ES",
    "sg:address":"Torreon, 6",
    "sg:city":"Pontedeume",
    "sg:orig_category":"Peluquer\u00cdas, Peluquer\u00cda Mixta",
    "sg:phone":"+34 981 43 28 73",
    "sg:postcode":"15600",
    "sg:province":"La Coru\u00f1a",
    "wof:name":"Mira Nieto Ana Isabel",
    "wof:placetype":"venue"
},
  "geometry": {"coordinates":[-8.171333313,43.407535553],"type":"Point"}
}