{
  "type": "Feature",
  "properties": {
    "iso:country":"ES",
    "sg:address":"Carr Fatima, 28",
    "sg:city":"Torroella Montgri",
    "sg:orig_category":"Piedra Natural",
    "sg:phone":"+34 972 75 82 96",
    "sg:postcode":"17257",
    "sg:province":"Girona",
    "wof:name":"Artificial Ter S.l.",
    "wof:placetype":"venue"
},
  "geometry": {"coordinates":[3.1272346973,42.0445137024],"type":"Point"}
}