{
  "type": "Feature",
  "properties": {
    "addr:full":"Calle de Federico Chueca, 7 Alcala Henares Madrid 28806",
    "addr:housenumber":"7",
    "addr:postcode":"28806",
    "addr:street":"Calle De Federico Chueca",
    "iso:country":"ES",
    "sg:address":"Calle de Federico Chueca, 7",
    "sg:city":"Alcala Henares",
    "sg:orig_category":"Fabricaci\u00d3n, Instalaci\u00d3n Y Reparaci\u00d3n De Bombas",
    "sg:phone":"+34 918 88 03 26",
    "sg:postcode":"28806",
    "sg:province":"Madrid",
    "wof:name":"Bombas Caprari S.a.",
    "wof:placetype":"venue"
},
  "geometry": {"coordinates":[-3.3813939095,40.487285614],"type":"Point"}
}