{
  "type": "Feature",
  "properties": {
    "addr:full":"Avda Asegra, 4 Peligros Granada 18210",
    "addr:housenumber":"4",
    "addr:postcode":"18210",
    "addr:street":"Avda Asegra",
    "iso:country":"ES",
    "sg:address":"Avda Asegra, 4",
    "sg:city":"Peligros",
    "sg:orig_category":"Promotores Constructores",
    "sg:phone":"+34 958 40 19 88",
    "sg:postcode":"18210",
    "sg:province":"Granada",
    "wof:name":"Ingeniaeria Y Agplicaciones Garcia Leon",
    "wof:placetype":"venue"
},
  "geometry": {"coordinates":[-3.62657547,37.2233886719],"type":"Point"}
}