{
  "type": "Feature",
  "properties": {
    "addr:full":"Calle de Paco Segovia, 112 Navas Del Marques \u00c1vila 05230",
    "addr:housenumber":"112",
    "addr:postcode":"05230",
    "addr:street":"Calle De Paco Segovia",
    "iso:country":"ES",
    "sg:address":"Calle de Paco Segovia, 112",
    "sg:city":"Navas Del Marques",
    "sg:orig_category":"Charcuter\u00cdas (al Por Menor)",
    "sg:phone":"+34 918 97 06 11",
    "sg:postcode":"05230",
    "sg:province":"\u00c1vila",
    "wof:name":"Soriano Mu\u00f1umel Miguel Angel",
    "wof:placetype":"venue"
},
  "geometry": {"coordinates":[-4.3390789032,40.6026802063],"type":"Point"}
}