{
  "type": "Feature",
  "properties": {
    "iso:country":"ES",
    "sg:address":"Calle de Barco (del), 3",
    "sg:city":"Pinto",
    "sg:orig_category":"Perfumer\u00cda (al Por Menor)",
    "sg:phone":"+34 916 91 63 21",
    "sg:postcode":"28320",
    "sg:province":"Madrid",
    "wof:name":"Serpa Lopez Maria Dolores",
    "wof:placetype":"venue"
},
  "geometry": {"coordinates":[-3.6960389614,40.2434463501],"type":"Point"}
}