{
  "type": "Feature",
  "properties": {
    "addr:full":"Arbelaitz Bidea, 35 Ergoien Guip\u00f9zcoa 20180",
    "addr:housenumber":"35",
    "addr:postcode":"20180",
    "addr:street":"Arbelaitz Bidea;Guipu\u0300Zcoa",
    "iso:country":"ES",
    "sg:address":"Arbelaitz Bidea, 35",
    "sg:city":"Ergoien",
    "sg:orig_category":"Reciclaje, Desguace De Veh\u00cdculos",
    "sg:phone":"+34 943 26 04 17",
    "sg:postcode":"20180",
    "sg:province":"Guip\u00f9zcoa",
    "wof:name":"Olaitz Berri S. A.",
    "wof:placetype":"venue"
},
  "geometry": {"coordinates":[-1.8629590273,43.2992401123],"type":"Point"}
}