{
  "type": "Feature",
  "properties": {
    "iso:country":"ES",
    "sg:address":"Avda Estacion (de La), 10",
    "sg:city":"Almeria",
    "sg:orig_category":"Abogados",
    "sg:phone":"+34 950 27 74 37",
    "sg:postcode":"04005",
    "sg:province":"Almer\u00eda",
    "wof:name":"Hernandez Thiel Esteban",
    "wof:placetype":"venue"
},
  "geometry": {"coordinates":[-2.4592049122,36.8375816345],"type":"Point"}
}