{
  "type": "Feature",
  "properties": {
    "iso:country":"ES",
    "sg:address":"Calle de Ledesma, 10",
    "sg:city":"Bilbao",
    "sg:orig_category":"Abogados",
    "sg:phone":"+34 944 24 92 71",
    "sg:postcode":"48001",
    "sg:province":"Vizcaya",
    "wof:name":"Arroita Berenguer Jose Maria",
    "wof:placetype":"venue"
},
  "geometry": {"coordinates":[-2.927321434,43.261920929],"type":"Point"}
}