{
  "type": "Feature",
  "properties": {
    "addr:full":"Calle de Barranco, 37 Graus Huesca 22430",
    "addr:housenumber":"37",
    "addr:postcode":"22430",
    "addr:street":"Calle De Barranco",
    "iso:country":"ES",
    "sg:address":"Calle de Barranco, 37",
    "sg:city":"Graus",
    "sg:orig_category":"Fotograf\u00cda Art\u00cdstica Y Retratos",
    "sg:phone":"+34 974 54 01 11",
    "sg:postcode":"22430",
    "sg:province":"Huesca",
    "wof:name":"Garuz Pueyo Luis Ramon",
    "wof:placetype":"venue"
},
  "geometry": {"coordinates":[0.3371061087,42.1901664734],"type":"Point"}
}