{
  "type": "Feature",
  "properties": {
    "addr:full":"Avda Parque (del), 53 Lucena C\u00f3rdoba 14900",
    "addr:housenumber":"53",
    "addr:postcode":"14900",
    "addr:street":"Avda Parque Del",
    "iso:country":"ES",
    "sg:address":"Avda Parque (del), 53",
    "sg:city":"Lucena",
    "sg:orig_category":"Aguas (distribuci\u00d3n, Servicios)",
    "sg:phone":"+34 957 51 48 18",
    "sg:postcode":"14900",
    "sg:province":"C\u00f3rdoba",
    "wof:name":"Aquagest Sur S.a.",
    "wof:placetype":"venue"
},
  "geometry": {"coordinates":[-4.492067337,37.4087219238],"type":"Point"}
}