{
  "type": "Feature",
  "properties": {
    "addr:full":"Carrer de Balmes, 90 Barcelona Barcelona 08008",
    "addr:housenumber":"90",
    "addr:postcode":"08008",
    "addr:street":"Carrer De Balmes",
    "iso:country":"ES",
    "sg:address":"Carrer de Balmes, 90",
    "sg:city":"Barcelona",
    "sg:orig_category":"Artes Gr\u00c1ficas, Artes Pl\u00c1sticas (curso)",
    "sg:phone":"+34 932 15 22 84",
    "sg:postcode":"08008",
    "sg:province":"Barcelona",
    "wof:name":"Arts Grafiques Mirabet Sl",
    "wof:placetype":"venue"
},
  "geometry": {"coordinates":[2.1600158215,41.3913192749],"type":"Point"}
}