{
  "type": "Feature",
  "properties": {
    "addr:full":"Calle de Colombia, 16 Ag\u00fcimes Las Palmas 35260",
    "addr:housenumber":"16",
    "addr:postcode":"35260",
    "addr:street":"Calle De Colombia",
    "iso:country":"ES",
    "sg:address":"Calle de Colombia, 16",
    "sg:city":"Ag\u00fcimes",
    "sg:orig_category":"Electrodom\u00c9sticos (al Por Menor)",
    "sg:phone":"+34 928 78 31 15",
    "sg:postcode":"35260",
    "sg:province":"Las Palmas",
    "wof:name":"Sanchez Guerra Sebastian",
    "wof:placetype":"venue"
},
  "geometry": {"coordinates":[-15.4459447861,27.9028739929],"type":"Point"}
}