{
  "type": "Feature",
  "properties": {
    "addr:full":"Pl. P. Catalans, S/n Barcelona Barcelona 08014",
    "addr:housenumber":"s / n",
    "addr:postcode":"08014",
    "addr:street":"Pl. P. Catalans",
    "iso:country":"ES",
    "sg:address":"Pl. P. Catalans, S/n",
    "sg:city":"Barcelona",
    "sg:orig_category":"Alquiler De Veh\u00cdculos: Turismos Y Utilitarios",
    "sg:phone":"+34 933 30 51 53",
    "sg:postcode":"08014",
    "sg:province":"Barcelona",
    "sg:website":"www.atesa.es",
    "wof:name":"Atesa",
    "wof:placetype":"venue"
},
  "geometry": {"coordinates":[2.1409583092,41.3795776367],"type":"Point"}
}