{
  "type": "Feature",
  "properties": {
    "addr:full":"O Facho, S/n Facho Pontevedra 36639",
    "addr:housenumber":"s",
    "addr:postcode":"36639",
    "addr:street":"/ N",
    "iso:country":"ES",
    "sg:address":"O Facho, S/n",
    "sg:city":"Facho",
    "sg:orig_category":"Pescader\u00cdas (al Por Mayor)",
    "sg:phone":"+34 986 52 69 40",
    "sg:postcode":"36639",
    "sg:province":"Pontevedra",
    "wof:name":"Mariscos Cordal S. L.",
    "wof:placetype":"venue"
},
  "geometry": {"coordinates":[-8.8220100403,42.4838981628],"type":"Point"}
}