{
  "type": "Feature",
  "properties": {
    "addr:full":"Ptda La Garrofera, S/n Tous Valencia 46269",
    "addr:housenumber":"s / n",
    "addr:postcode":"46269",
    "addr:street":"Ptda La Garrofera",
    "iso:country":"ES",
    "sg:address":"Ptda La Garrofera, S/n",
    "sg:city":"Tous",
    "sg:orig_category":"Fabricaci\u00d3n De Mobiliario Met\u00c1lico",
    "sg:phone":"+34 962 12 06 16",
    "sg:postcode":"46269",
    "sg:province":"Valencia",
    "wof:name":"Iron Art S.l.",
    "wof:placetype":"venue"
},
  "geometry": {"coordinates":[-0.5896350145,39.1404190063],"type":"Point"}
}