{
  "type": "Feature",
  "properties": {
    "iso:country":"ES",
    "sg:address":"Calle de Real, 1",
    "sg:city":"Aldeahermosa",
    "sg:orig_category":"Producci\u00d3n De Huevos",
    "sg:phone":"+34 953 12 31 41",
    "sg:postcode":"23267",
    "sg:province":"Ja\u00e9n",
    "wof:name":"Avicola El Encinar S.l.l.",
    "wof:placetype":"venue"
},
  "geometry": {"coordinates":[-3.1273937225,38.3282279968],"type":"Point"}
}