{
  "type": "Feature",
  "properties": {
    "iso:country":"ES",
    "sg:address":"Carr Ciutat De Castello, 5",
    "sg:city":"Vila Joiosa",
    "sg:orig_category":"Electricidad: Instaladores",
    "sg:phone":"+34 966 85 12 36",
    "sg:postcode":"03570",
    "sg:province":"Alicante",
    "wof:name":"Electecidad Amadorio S.l.",
    "wof:placetype":"venue"
},
  "geometry": {"coordinates":[-0.2328159958,38.5093269348],"type":"Point"}
}