{
  "type": "Feature",
  "properties": {
    "iso:country":"ES",
    "sg:address":"Plg La Serna, 28",
    "sg:city":"Mota Cuervo",
    "sg:orig_category":"Electricidad Veh\u00cdculo",
    "sg:phone":"+34 967 18 04 97",
    "sg:postcode":"16630",
    "sg:province":"Cuenca",
    "wof:name":"Talleres Horviauto S.l.l.",
    "wof:placetype":"venue"
},
  "geometry": {"coordinates":[-2.871309042,39.503036499],"type":"Point"}
}