{
  "type": "Feature",
  "properties": {
    "iso:country":"ES",
    "sg:address":"Calle de Eliana (la), 16",
    "sg:city":"Mislata",
    "sg:orig_category":"Hornos Industriales",
    "sg:phone":"+34 963 83 23 38",
    "sg:postcode":"46920",
    "sg:province":"Valencia",
    "wof:name":"T.algoher S.l.",
    "wof:placetype":"venue"
},
  "geometry": {"coordinates":[-0.4185679853,39.4784545898],"type":"Point"}
}