{
  "type": "Feature",
  "properties": {
    "iso:country":"ES",
    "sg:address":"Calle de Jamaica, 2",
    "sg:city":"Granada",
    "sg:orig_category":"Empresas De Carpinter\u00cda De Madera",
    "sg:phone":"+34 958 81 47 18",
    "sg:postcode":"18007",
    "sg:province":"Granada",
    "wof:name":"Uceda Terron Victoriano",
    "wof:placetype":"venue"
},
  "geometry": {"coordinates":[-3.6034491062,37.1547393799],"type":"Point"}
}