{
  "type": "Feature",
  "properties": {
    "iso:country":"ES",
    "sg:address":"De La Mona, 10",
    "sg:city":"Ventas Pe\u00f1a Aguilera",
    "sg:orig_category":"Agencias Y Asesores De Publicidad",
    "sg:phone":"+34 925 41 92 32",
    "sg:postcode":"45127",
    "sg:province":"Toledo",
    "wof:name":"Garcia Lopez Maria Reyes",
    "wof:placetype":"venue"
},
  "geometry": {"coordinates":[-4.2286472321,39.6132736206],"type":"Point"}
}