{
  "type": "Feature",
  "properties": {
    "addr:full":"Avgd Blasco Iba\u00d1ez, 48 Paterna Valencia 46980",
    "addr:housenumber":"48",
    "addr:postcode":"46980",
    "addr:street":"Iban\u0303Ez",
    "iso:country":"ES",
    "sg:address":"Avgd Blasco Iba\u00d1ez, 48",
    "sg:city":"Paterna",
    "sg:orig_category":"Cajas De Ahorro",
    "sg:phone":"+34 961 38 56 60",
    "sg:postcode":"46980",
    "sg:province":"Valencia",
    "sg:website":"www.bancaja.es",
    "wof:name":"Caja De Ahorros De Valencia Castellon Y Alicante",
    "wof:placetype":"venue"
},
  "geometry": {"coordinates":[-0.434935987,39.4986801147],"type":"Point"}
}