{
  "type": "Feature",
  "properties": {
    "iso:country":"ES",
    "sg:address":"Ctra Loja (de), Km. 0001,5",
    "sg:city":"Alhama Granada",
    "sg:orig_category":"Fabricaci\u00d3n Y Comercio De M\u00c1quinas",
    "sg:phone":"+34 958 36 01 20",
    "sg:postcode":"18120",
    "sg:province":"Granada",
    "wof:name":"Valenzuela Vias Y Servicios S.coop.",
    "wof:placetype":"venue"
},
  "geometry": {"coordinates":[-3.9909889698,37.0056495667],"type":"Point"}
}