{
  "type": "Feature",
  "properties": {
    "iso:country":"ES",
    "sg:address":"Carrer de Joan Maragall, 12",
    "sg:city":"S. Feliu Guixols",
    "sg:classifiers":[
        {
            "category":"Personal",
            "subcategory":"Barber",
            "type":"Services"
        }
    ],
    "sg:phone":"+34 972 82 25 97",
    "sg:postcode":"17220",
    "sg:province":"Girona",
    "sg:tags":[
        "caballeros",
        "de",
        "peluqueros"
    ],
    "wof:name":"Jimenez Caceres Juan",
    "wof:placetype":"venue"
},
  "geometry": {"coordinates":[3.0313000679,41.7826118469],"type":"Point"}
}