{
  "type": "Feature",
  "properties": {
    "addr:full":"Calle de Nebli, 12 Raya Del Palancar-guadamonte Madrid 28690",
    "addr:housenumber":"12",
    "addr:postcode":"28690",
    "addr:street":"Calle De Nebli",
    "iso:country":"ES",
    "sg:address":"Calle de Nebli, 12",
    "sg:city":"Raya Del Palancar-guadamonte",
    "sg:orig_category":"Jardiner\u00cdas, Vegetales, Art\u00cdculos De Jardiner\u00cda (al Por Menor)",
    "sg:phone":"+34 918 16 23 48",
    "sg:postcode":"28690",
    "sg:province":"Madrid",
    "wof:name":"Servicios A Comunidades Movi S.l.",
    "wof:placetype":"venue"
},
  "geometry": {"coordinates":[-3.9705080986,40.4236831665],"type":"Point"}
}