{
  "type": "Feature",
  "properties": {
    "iso:country":"ES",
    "sg:address":"Avda Libertad, 2",
    "sg:city":"Dos Hermanas",
    "sg:orig_category":"Transportes Por Carretera: Lotes Completos, Mercanc\u00cdas Diversas",
    "sg:phone":"+34 954 72 10 35",
    "sg:postcode":"41700",
    "sg:province":"Sevilla",
    "wof:name":"Transportes Espina S.a.",
    "wof:placetype":"venue"
},
  "geometry": {"coordinates":[-5.9311099052,37.2897262573],"type":"Point"}
}