{
  "type": "Feature",
  "properties": {
    "addr:full":"Carrer de Anselm Clave, 54 Mollet Valles Barcelona 08100",
    "addr:housenumber":"54",
    "addr:postcode":"08100",
    "addr:street":"Carrer De Anselm Clave",
    "iso:country":"ES",
    "sg:address":"Carrer de Anselm Clave, 54",
    "sg:city":"Mollet Valles",
    "sg:orig_category":"Muebles Y Accesorios Para Cocinas Y Cuartos De Ba\u00d1o (al Por Menor)",
    "sg:phone":"+34 935 79 37 28",
    "sg:postcode":"08100",
    "sg:province":"Barcelona",
    "wof:name":"Navarro Hernandez Ana",
    "wof:placetype":"venue"
},
  "geometry": {"coordinates":[2.2170751095,41.540145874],"type":"Point"}
}