{
  "type": "Feature",
  "properties": {
    "iso:country":"ES",
    "sg:address":"Calle de Virgen De Los Desamparados, 81",
    "sg:city":"Novelda",
    "sg:orig_category":"\u00d3ptica: Instrumentos (fabricaci\u00d3n)",
    "sg:phone":"+34 965 60 26 76",
    "sg:postcode":"03660",
    "sg:province":"Alicante",
    "wof:name":"Espinosa Centro Optico Auditivo",
    "wof:placetype":"venue"
},
  "geometry": {"coordinates":[-0.7677329779,38.3829498291],"type":"Point"}
}