{
  "type": "Feature",
  "properties": {
    "iso:country":"ES",
    "sg:address":"Calle de San Juan, 21",
    "sg:city":"Puerto Cruz",
    "sg:orig_category":"Importaci\u00d3n, Exportaci\u00d3n Y Comercios De Productos Textiles",
    "sg:phone":"+34 922 38 35 71",
    "sg:postcode":"38400",
    "sg:province":"Santa Cruz De Tenerife",
    "wof:name":"Sucesores De Miguel Herreros S.a.",
    "wof:placetype":"venue"
},
  "geometry": {"coordinates":[-16.5240192413,28.3872566223],"type":"Point"}
}