{
  "type": "Feature",
  "properties": {
    "iso:country":"ES",
    "sg:address":"Ctra Tahal, 7",
    "sg:city":"Macael",
    "sg:orig_category":"Mec\u00c1nico Del Autom\u00d3vil",
    "sg:phone":"+34 950 12 82 75",
    "sg:postcode":"04867",
    "sg:province":"Almer\u00eda",
    "wof:name":"Automecanicas Carrera S.cop. Andaluza",
    "wof:placetype":"venue"
},
  "geometry": {"coordinates":[-2.2989981174,37.3330726624],"type":"Point"}
}