{
  "type": "Feature",
  "properties": {
    "iso:country":"ES",
    "sg:address":"Calle de Isla De La Palma (de La), 23",
    "sg:city":"San Sebastian De Los Reyes",
    "sg:orig_category":"Jardiner\u00cdas, Vegetales, Art\u00cdculos De Jardiner\u00cda (al Por Menor)",
    "sg:phone":"+34 916 52 45 45",
    "sg:postcode":"28700",
    "sg:province":"Madrid",
    "wof:name":"Fernandez Garcia Manuel",
    "wof:placetype":"venue"
},
  "geometry": {"coordinates":[-3.6254050732,40.5573234558],"type":"Point"}
}