{
  "type": "Feature",
  "properties": {
    "addr:full":"Calle de Badajoz, 2 Santa Marta Badajoz 06150",
    "addr:housenumber":"2",
    "addr:postcode":"06150",
    "addr:street":"Calle De Badajoz",
    "iso:country":"ES",
    "sg:address":"Calle de Badajoz, 2",
    "sg:city":"Santa Marta",
    "sg:orig_category":"Muebles, Minoristas",
    "sg:phone":"+34 924 69 00 11",
    "sg:postcode":"06150",
    "sg:province":"Badajoz",
    "wof:name":"Mu\u00f1oz Benito Felix",
    "wof:placetype":"venue"
},
  "geometry": {"coordinates":[-6.7126722336,38.7185592651],"type":"Point"}
}