{
  "type": "Feature",
  "properties": {
    "addr:full":"Sta. Barbara, 22 Guijo Santa Barbara C\u00e1ceres 10459",
    "addr:housenumber":"22",
    "addr:postcode":"10459",
    "addr:street":"Sta. Barbara;Ca\u0301Ceres",
    "iso:country":"ES",
    "sg:address":"Sta. Barbara, 22",
    "sg:city":"Guijo Santa Barbara",
    "sg:orig_category":"Bancos",
    "sg:phone":"+34 927 56 09 08",
    "sg:postcode":"10459",
    "sg:province":"C\u00e1ceres",
    "wof:name":"Vicente Garcia Miguel",
    "wof:placetype":"venue"
},
  "geometry": {"coordinates":[-5.6535391808,40.1548614502],"type":"Point"}
}