{
  "type": "Feature",
  "properties": {
    "addr:full":"Calle de Almaraz, 3 Bermillo Sayago Zamora 49200",
    "addr:housenumber":"3",
    "addr:postcode":"49200",
    "addr:street":"Calle De Almaraz;Zamora",
    "iso:country":"ES",
    "sg:address":"Calle de Almaraz, 3",
    "sg:city":"Bermillo Sayago",
    "sg:orig_category":"Laboratorios Y Trabajos De Fotograf\u00cda, V\u00cddeo Y Cine",
    "sg:phone":"+34 980 61 02 77",
    "sg:postcode":"49200",
    "sg:province":"Zamora",
    "wof:name":"San Leon Miguel Alvaro",
    "wof:placetype":"venue"
},
  "geometry": {"coordinates":[-5.7462787628,41.5033454895],"type":"Point"}
}