{
  "type": "Feature",
  "properties": {
    "iso:country":"ES",
    "sg:address":"Urb Dehesa Campoamor, S/n",
    "sg:city":"Dehesa Campoamor",
    "sg:orig_category":"Asociaciones Y Clubs Deportivos",
    "sg:phone":"+34 965 32 03 86",
    "sg:postcode":"03189",
    "sg:province":"Alicante",
    "sg:website":"www.cncampoamor.es",
    "wof:name":"Club Nautico",
    "wof:placetype":"venue"
},
  "geometry": {"coordinates":[-0.7677609921,37.9303321838],"type":"Point"}
}