{
  "type": "Feature",
  "properties": {
    "iso:country":"ES",
    "sg:address":"Avda Alonso Fernandez De Lugo, 10",
    "sg:city":"Orotava",
    "sg:orig_category":"Notarios",
    "sg:phone":"+34 922 32 60 51",
    "sg:postcode":"38300",
    "sg:province":"Santa Cruz De Tenerife",
    "wof:name":"Ruiz-ayucar Seifert Alejandro",
    "wof:placetype":"venue"
},
  "geometry": {"coordinates":[-16.5272598267,28.3944072723],"type":"Point"}
}