{
  "type": "Feature",
  "properties": {
    "iso:country":"ES",
    "sg:address":"Av Cadiz, S/n",
    "sg:city":"Miami Playa",
    "sg:orig_category":"Molduras, Junquillos, Listones Y Molduras Perforadas",
    "sg:phone":"+34 977 81 07 91",
    "sg:postcode":"43892",
    "sg:province":"Tarragona",
    "wof:name":"Rodriguez Rodriguez Juan",
    "wof:placetype":"venue"
},
  "geometry": {"coordinates":[0.9318799973,41.003528595],"type":"Point"}
}