{
  "type": "Feature",
  "properties": {
    "addr:full":"Calle de Perdiz (de La), 141 Poligono Industrial Monte Boyal Toledo 45950",
    "addr:housenumber":"141",
    "addr:postcode":"45950",
    "addr:street":"Calle De Perdiz De La;Poligono Industrial Monte Boyal",
    "iso:country":"ES",
    "sg:address":"Calle de Perdiz (de La), 141",
    "sg:city":"Poligono Industrial Monte Boyal",
    "sg:orig_category":"Quincaller\u00cda (al Por Menor)",
    "sg:phone":"+34 918 17 17 56",
    "sg:postcode":"45950",
    "sg:province":"Toledo",
    "wof:name":"Ferreteria Casta\u00f1eda E Hijos S.l.",
    "wof:placetype":"venue"
},
  "geometry": {"coordinates":[-4.0585980415,40.2127113342],"type":"Point"}
}