{
  "type": "Feature",
  "properties": {
    "iso:country":"ES",
    "sg:address":"Calle de Travieso, 17",
    "sg:city":"Palmas De Gran Canaria",
    "sg:orig_category":"Ropa Para Se\u00d1oras (al Por Menor)",
    "sg:phone":"+34 928 39 10 86",
    "sg:postcode":"35002",
    "sg:province":"Las Palmas",
    "wof:name":"Outsourcing Contable S.l.",
    "wof:placetype":"venue"
},
  "geometry": {"coordinates":[-15.4161014557,28.1049842834],"type":"Point"}
}