{
  "type": "Feature",
  "properties": {
    "addr:full":"Calle de Laguna Azorin, 41 Zaragoza Zaragoza 50011",
    "addr:housenumber":"41",
    "addr:postcode":"50011",
    "addr:street":"Calle De Laguna Azorin",
    "iso:country":"ES",
    "sg:address":"Calle de Laguna Azorin, 41",
    "sg:city":"Zaragoza",
    "sg:orig_category":"Teatro, Ballet, Danza (agrupaciones, Compa\u00d1\u00cdas)",
    "sg:phone":"+34 976 40 30 88",
    "sg:postcode":"50011",
    "sg:province":"Zaragoza",
    "sg:website":"www.pingaliraina.com",
    "wof:name":"Teatro Pingaliraina S.l.",
    "wof:placetype":"venue"
},
  "geometry": {"coordinates":[-0.923150003,41.6493148804],"type":"Point"}
}