{
  "type": "Feature",
  "properties": {
    "iso:country":"ES",
    "sg:address":"Calle de Doctor Fleming, S/n",
    "sg:city":"Poligono El Montalvo",
    "sg:orig_category":"Ebanister\u00cda",
    "sg:phone":"+34 923 19 08 88",
    "sg:postcode":"37188",
    "sg:province":"Salamanca",
    "wof:name":"Sanchez Sanchez Jose Carlos",
    "wof:placetype":"venue"
},
  "geometry": {"coordinates":[-5.6630473137,40.9649734497],"type":"Point"}
}