{
  "type": "Feature",
  "properties": {
    "addr:full":"Calle de Bilbao, 296 Marina-oasis Alicante 03177",
    "addr:housenumber":"296",
    "addr:postcode":"03177",
    "addr:street":"Calle De Bilbao;Alicante",
    "iso:country":"ES",
    "sg:address":"Calle de Bilbao, 296",
    "sg:city":"Marina-oasis",
    "sg:orig_category":"Promotores Constructores",
    "sg:phone":"+34 966 79 09 02",
    "sg:postcode":"03177",
    "sg:province":"Alicante",
    "wof:name":"Morgan  Denis",
    "wof:placetype":"venue"
},
  "geometry": {"coordinates":[-0.4810059965,38.3452033997],"type":"Point"}
}