{
  "type": "Feature",
  "properties": {
    "addr:full":"Av Jacquard, 103 Terrassa Barcelona 08222",
    "addr:housenumber":"103",
    "addr:postcode":"08222",
    "addr:street":"Av Jacquard",
    "iso:country":"ES",
    "sg:address":"Av Jacquard, 103",
    "sg:city":"Terrassa",
    "sg:orig_category":"Loter\u00cda Y T\u00d3mbola",
    "sg:phone":"+34 937 85 42 36",
    "sg:postcode":"08222",
    "sg:province":"Barcelona",
    "wof:name":"Prat Boada Cristina",
    "wof:placetype":"venue"
},
  "geometry": {"coordinates":[2.0216579437,41.5641784668],"type":"Point"}
}