{
  "type": "Feature",
  "properties": {
    "iso:country":"ES",
    "sg:address":"Avda Carlos De Haya, 82",
    "sg:city":"Malaga",
    "sg:orig_category":"Productos Qu\u00cdmicos (fabricaci\u00d3n, Al Por Mayor)",
    "sg:phone":"+34 952 61 88 71",
    "sg:postcode":"29010",
    "sg:province":"M\u00e1laga",
    "wof:name":"Dade Behring S.a.",
    "wof:placetype":"venue"
},
  "geometry": {"coordinates":[-4.4490890503,36.7226371765],"type":"Point"}
}