{
  "type": "Feature",
  "properties": {
    "addr:full":"Calle de Pintor Pablo Uranga, 9 Vitoria-gasteiz \u00c1lava 01008",
    "addr:housenumber":"9",
    "addr:postcode":"01008",
    "addr:street":"Calle De Pintor Pablo Uranga",
    "iso:country":"ES",
    "sg:address":"Calle de Pintor Pablo Uranga, 9",
    "sg:city":"Vitoria-gasteiz",
    "sg:orig_category":"Electrodom\u00c9sticos (al Por Menor)",
    "sg:phone":"+34 945 22 55 31",
    "sg:postcode":"01008",
    "sg:province":"\u00c1lava",
    "wof:name":"Abad Fagundez Francisco Javier",
    "wof:placetype":"venue"
},
  "geometry": {"coordinates":[-2.685232,42.845947],"type":"Point"}
}