{
  "type": "Feature",
  "properties": {
    "addr:full":"Carrer de Montserrat, 9 Barcelona Barcelona 08001",
    "addr:housenumber":"9",
    "addr:postcode":"08001",
    "addr:street":"Carrer De Montserrat",
    "iso:country":"ES",
    "sg:address":"Carrer de Montserrat, 9",
    "sg:city":"Barcelona",
    "sg:orig_category":"Caf\u00c9s, Bares, Cervecer\u00cdas",
    "sg:phone":"+34 933 01 29 78",
    "sg:postcode":"08001",
    "sg:province":"Barcelona",
    "wof:name":"La Bella Loca S.l.",
    "wof:placetype":"venue"
},
  "geometry": {"coordinates":[2.1749310493,41.3773612976],"type":"Point"}
}