{
  "type": "Feature",
  "properties": {
    "addr:full":"Rama Hoyo, S/n Torremolinos M\u00e1laga 29620",
    "addr:housenumber":"s / n",
    "addr:postcode":"29620",
    "addr:street":"Ma\u0301Laga",
    "iso:country":"ES",
    "sg:address":"Rama Hoyo, S/n",
    "sg:city":"Torremolinos",
    "sg:orig_category":"Asilos De Ancianos. Centros Privados",
    "sg:phone":"+34 952 37 11 23",
    "sg:postcode":"29620",
    "sg:province":"M\u00e1laga",
    "wof:name":"Residencias Jacarbel",
    "wof:placetype":"venue"
},
  "geometry": {"coordinates":[-4.499666214,36.6263847351],"type":"Point"}
}