{
  "type": "Feature",
  "properties": {
    "addr:full":"Calle de Villaespesa, 63 Laujar Andarax Almer\u00eda 04470",
    "addr:housenumber":"63",
    "addr:postcode":"04470",
    "addr:street":"Calle De Villaespesa;Almeri\u0301A",
    "iso:country":"ES",
    "sg:address":"Calle de Villaespesa, 63",
    "sg:city":"Laujar Andarax",
    "sg:orig_category":"Quincaller\u00cda (al Por Menor)",
    "sg:phone":"+34 950 51 32 27",
    "sg:postcode":"04470",
    "sg:province":"Almer\u00eda",
    "wof:name":"Perez Garcia Justo",
    "wof:placetype":"venue"
},
  "geometry": {"coordinates":[-2.8938889503,36.9929962158],"type":"Point"}
}