{
  "type": "Feature",
  "properties": {
    "iso:country":"ES",
    "sg:address":"Calle de Iznalloz, S/n",
    "sg:city":"Albolote",
    "sg:orig_category":"Aluminio Y Aleaciones (producci\u00d3n, Transformaci\u00d3n, Negocio)",
    "sg:phone":"+34 958 46 69 54",
    "sg:postcode":"18220",
    "sg:province":"Granada",
    "sg:website":"www.inalum.es",
    "wof:name":"Aluminios Inalum S.l.",
    "wof:placetype":"venue"
},
  "geometry": {"coordinates":[-3.6061112881,37.3642578125],"type":"Point"}
}