{
  "type": "Feature",
  "properties": {
    "addr:full":"Calle de Esteban Pujasol, 10 Zaragoza Zaragoza 50013",
    "addr:housenumber":"10",
    "addr:postcode":"50013",
    "addr:street":"Calle De Esteban Pujasol",
    "iso:country":"ES",
    "sg:address":"Calle de Esteban Pujasol, 10",
    "sg:city":"Zaragoza",
    "sg:orig_category":"Empresarios",
    "sg:phone":"+34 976 53 25 54",
    "sg:postcode":"50013",
    "sg:province":"Zaragoza",
    "wof:name":"Albero Uson Jose Javier",
    "wof:placetype":"venue"
},
  "geometry": {"coordinates":[-0.7722973824,41.5386772156],"type":"Point"}
}