{
  "type": "Feature",
  "properties": {
    "addr:full":"Pase Joaquin Ruiz Gimenez, 35 Torrelodones Madrid 28250",
    "addr:housenumber":"35",
    "addr:postcode":"28250",
    "addr:street":"Gimenez",
    "iso:country":"ES",
    "sg:address":"Pase Joaquin Ruiz Gimenez, 35",
    "sg:city":"Torrelodones",
    "sg:orig_category":"Suministros Para Hoteles",
    "sg:phone":"+34 918 59 27 27",
    "sg:postcode":"28250",
    "sg:province":"Madrid",
    "wof:name":"Comercial E.s.h.s.l.",
    "wof:placetype":"venue"
},
  "geometry": {"coordinates":[-3.921628952,40.5737800598],"type":"Point"}
}