{
  "type": "Feature",
  "properties": {
    "addr:full":"Pol. Ind. Can Milans, S/n Masrampinyo Barcelona 08110",
    "addr:housenumber":"s",
    "addr:postcode":"08110",
    "addr:street":"/ N Masrampinyo",
    "iso:country":"ES",
    "sg:address":"Pol. Ind. Can Milans, S/n",
    "sg:city":"Masrampinyo",
    "sg:orig_category":"Fabricaci\u00d3n Y Comercio De M\u00c1quinas",
    "sg:phone":"+34 935 72 62 40",
    "sg:postcode":"08110",
    "sg:province":"Barcelona",
    "wof:name":"Fagoma S.a.",
    "wof:placetype":"venue"
},
  "geometry": {"coordinates":[2.1817800999,41.4892234802],"type":"Point"}
}