{
  "type": "Feature",
  "properties": {
    "iso:country":"ES",
    "sg:address":"Calle de Doctor Jose Ponce Arias, 13",
    "sg:city":"Palmas De Gran Canaria",
    "sg:orig_category":"Promotores Constructores",
    "sg:phone":"+34 928 29 72 23",
    "sg:postcode":"35005",
    "sg:province":"Las Palmas",
    "wof:name":"Rosario Cabrera Tavio E Hijos S.l.",
    "wof:placetype":"venue"
},
  "geometry": {"coordinates":[-15.4307765961,28.1286945343],"type":"Point"}
}