{
  "type": "Feature",
  "properties": {
    "addr:full":"Pase Henares (del), 1 Alcala Henares Madrid 28804",
    "addr:postcode":"28804",
    "iso:country":"ES",
    "sg:address":"Pase Henares (del), 1",
    "sg:city":"Alcala Henares",
    "sg:orig_category":"Iglesia Cat\u00d3lica",
    "sg:phone":"+34 918 82 83 71",
    "sg:postcode":"28804",
    "sg:province":"Madrid",
    "wof:name":"Obispado De Alcala De Henares",
    "wof:placetype":"venue"
},
  "geometry": {"coordinates":[-3.3612151146,40.4766731262],"type":"Point"}
}