{
  "type": "Feature",
  "properties": {
    "iso:country":"ES",
    "sg:address":"Avda Ciudad De Barcelona, 43",
    "sg:city":"Madrid",
    "sg:orig_category":"Perfumer\u00cda (al Por Menor)",
    "sg:phone":"+34 915 02 07 28",
    "sg:postcode":"28007",
    "sg:province":"Madrid",
    "wof:name":"Fernandez Cecilia Abraham",
    "wof:placetype":"venue"
},
  "geometry": {"coordinates":[-3.6788289547,40.4035301208],"type":"Point"}
}