{
  "type": "Feature",
  "properties": {
    "iso:country":"ES",
    "sg:address":"Calle de Santomera, S/n",
    "sg:city":"Molina Segura",
    "sg:orig_category":"Condimentos, Especias, Vinagres, Salsas Preparadas (fabricaci\u00d3n, Al Por Mayor)",
    "sg:phone":"+34 968 61 45 56",
    "sg:postcode":"30500",
    "sg:province":"Murcia",
    "wof:name":"Infusana S.l.",
    "wof:placetype":"venue"
},
  "geometry": {"coordinates":[-1.1806089878,38.0355300903],"type":"Point"}
}