{
  "type": "Feature",
  "properties": {
    "addr:full":"Calle de Mayor, 32 Molins Rei Barcelona 08750",
    "addr:housenumber":"32",
    "addr:postcode":"08750",
    "addr:street":"Calle De Mayor;Barcelona",
    "iso:country":"ES",
    "sg:address":"Calle de Mayor, 32",
    "sg:city":"Molins Rei",
    "sg:orig_category":"\u00d3ptica: Instrumentos (fabricaci\u00d3n)",
    "sg:phone":"+34 936 68 93 51",
    "sg:postcode":"08750",
    "sg:province":"Barcelona",
    "wof:name":"Murcia Robledo Francisco Javier",
    "wof:placetype":"venue"
},
  "geometry": {"coordinates":[2.0164849758,41.414604187],"type":"Point"}
}