{
  "type": "Feature",
  "properties": {
    "addr:full":"Calle de Luis Sese, 10 Mimetiz Vizcaya 48860",
    "addr:housenumber":"10",
    "addr:postcode":"48860",
    "addr:street":"Calle De Luis Sese",
    "iso:country":"ES",
    "sg:address":"Calle de Luis Sese, 10",
    "sg:city":"Mimetiz",
    "sg:orig_category":"Carnicer\u00cdas, Carnicer\u00cdas",
    "sg:phone":"+34 946 39 08 06",
    "sg:postcode":"48860",
    "sg:province":"Vizcaya",
    "wof:name":"Jauregui Velez Aurelio",
    "wof:placetype":"venue"
},
  "geometry": {"coordinates":[-3.1326520443,43.2134284973],"type":"Point"}
}