{
  "type": "Feature",
  "properties": {
    "addr:full":"Carrer de Joan Guell, 190 Barcelona Barcelona 08028",
    "addr:housenumber":"190",
    "addr:postcode":"08028",
    "addr:street":"Carrer De Joan Guell",
    "iso:country":"ES",
    "sg:address":"Carrer de Joan Guell, 190",
    "sg:city":"Barcelona",
    "sg:orig_category":"Quincaller\u00cda (al Por Menor)",
    "sg:phone":"+34 933 21 02 07",
    "sg:postcode":"08028",
    "sg:province":"Barcelona",
    "wof:name":"Ferreteria El Clau S. A.",
    "wof:placetype":"venue"
},
  "geometry": {"coordinates":[2.130628109,41.3849105835],"type":"Point"}
}