{
  "type": "Feature",
  "properties": {
    "addr:full":"Calle de Eskoriatza, 6 Vitoria-gasteiz \u00c1lava 01013",
    "addr:housenumber":"6",
    "addr:postcode":"01013",
    "addr:street":"Calle De Eskoriatza",
    "iso:country":"ES",
    "sg:address":"Calle de Eskoriatza, 6",
    "sg:city":"Vitoria-gasteiz",
    "sg:orig_category":"Empresas De Pintura Y Revestimientos",
    "sg:phone":"+34 945 27 00 00",
    "sg:postcode":"01013",
    "sg:province":"\u00c1lava",
    "wof:name":"Decofel Alava S.l.",
    "wof:placetype":"venue"
},
  "geometry": {"coordinates":[-2.6553430557,42.8589134216],"type":"Point"}
}