{
  "type": "Feature",
  "properties": {
    "iso:country":"ES",
    "sg:address":"Pol Ind Pla De Museros, S/n",
    "sg:city":"Almassora Pol. Ind.",
    "sg:orig_category":"Chapister\u00cda",
    "sg:phone":"+34 964 56 50 66",
    "sg:postcode":"12550",
    "sg:province":"Castell\u00f3n",
    "wof:name":"Corte Y Plegado Castellon S.l.",
    "wof:placetype":"venue"
},
  "geometry": {"coordinates":[-0.0631740019,39.9439582825],"type":"Point"}
}