{
  "type": "Feature",
  "properties": {
    "iso:country":"ES",
    "sg:address":"Rua Curros Enriquez, 24",
    "sg:city":"Ourense",
    "sg:orig_category":"Comercio De Piezas De Recambio Y De Accesorios De Veh\u00cdculos, Veh\u00cdculos Industriales",
    "sg:phone":"+34 988 23 39 14",
    "sg:postcode":"32003",
    "sg:province":"Ourense",
    "wof:name":"Auto Electrico Comunicaciones S.l.",
    "wof:placetype":"venue"
},
  "geometry": {"coordinates":[-7.8625788689,42.3433532715],"type":"Point"}
}