{
  "type": "Feature",
  "properties": {
    "addr:full":"San Franzisko Kalea, 26 Elgoibar Guip\u00f9zcoa 20870",
    "addr:housenumber":"26",
    "addr:postcode":"20870",
    "addr:street":"San Franzisko Kalea;Guipu\u0300Zcoa",
    "iso:country":"ES",
    "sg:address":"San Franzisko Kalea, 26",
    "sg:city":"Elgoibar",
    "sg:orig_category":"Construcciones Navales Y Fluviales",
    "sg:phone":"+34 943 74 10 78",
    "sg:postcode":"20870",
    "sg:province":"Guip\u00f9zcoa",
    "wof:name":"Raquel Dos Santos Augusto Y Otra C.b.",
    "wof:placetype":"venue"
},
  "geometry": {"coordinates":[-2.4135909081,43.2154884338],"type":"Point"}
}