{
  "type": "Feature",
  "properties": {
    "iso:country":"ES",
    "sg:address":"Calle de Juan Bravo, 11",
    "sg:city":"Madrid",
    "sg:orig_category":"Ropa Para Se\u00d1oras (al Por Menor)",
    "sg:phone":"+34 915 77 52 07",
    "sg:postcode":"28006",
    "sg:province":"Madrid",
    "wof:name":"Marien S.l.",
    "wof:placetype":"venue"
},
  "geometry": {"coordinates":[-3.682972908,40.4330177307],"type":"Point"}
}