{
  "type": "Feature",
  "properties": {
    "addr:full":"Carrer de Sant Pere, 31 Calella Barcelona 08370",
    "addr:housenumber":"31",
    "addr:postcode":"08370",
    "addr:street":"Carrer De Sant Pere",
    "iso:country":"ES",
    "sg:address":"Carrer de Sant Pere, 31",
    "sg:city":"Calella",
    "sg:orig_category":"Institutos De Belleza",
    "sg:phone":"+34 937 69 43 51",
    "sg:postcode":"08370",
    "sg:province":"Barcelona",
    "wof:name":"Chaos Lolo Irene",
    "wof:placetype":"venue"
},
  "geometry": {"coordinates":[2.662694931,41.6145515442],"type":"Point"}
}