{
  "type": "Feature",
  "properties": {
    "iso:country":"ES",
    "sg:address":"Ctra. De Munebrega, S/n",
    "sg:city":"Ateca",
    "sg:orig_category":"Empresas De Carpinter\u00cda",
    "sg:phone":"+34 976 84 21 42",
    "sg:postcode":"50200",
    "sg:province":"Zaragoza",
    "wof:name":"Jose Luis Pacheco Lozano",
    "wof:placetype":"venue"
},
  "geometry": {"coordinates":[-1.7889089584,41.3299789429],"type":"Point"}
}