{
  "type": "Feature",
  "properties": {
    "addr:full":"Plaz Moraleja (de La), S/n Alcobendas Madrid 28109",
    "addr:postcode":"28109",
    "addr:street":"La S / N",
    "iso:country":"ES",
    "sg:address":"Plaz Moraleja (de La), S/n",
    "sg:city":"Alcobendas",
    "sg:orig_category":"Electrodom\u00c9sticos (al Por Menor)",
    "sg:phone":"+34 916 50 31 67",
    "sg:postcode":"28109",
    "sg:province":"Madrid",
    "wof:name":"Perez Ayllon Marcelino",
    "wof:placetype":"venue"
},
  "geometry": {"coordinates":[-3.6530759335,40.5149269104],"type":"Point"}
}