{
  "type": "Feature",
  "properties": {
    "iso:country":"ES",
    "sg:address":"Calle de Carretas, 35",
    "sg:city":"Talavera Reina",
    "sg:orig_category":"Servicio De Salud",
    "sg:phone":"+34 925 80 20 73",
    "sg:postcode":"45600",
    "sg:province":"Toledo",
    "wof:name":"Ambulancias Hermanos Aguero S.l.",
    "wof:placetype":"venue"
},
  "geometry": {"coordinates":[-4.828168869,39.9650688171],"type":"Point"}
}