{
  "type": "Feature",
  "properties": {
    "iso:country":"ES",
    "sg:address":"Av Espanya, 6",
    "sg:city":"Cerdanyola Valles",
    "sg:orig_category":"Radiocomunicaciones, Telefon\u00cda M\u00d3vil, Radiomensajer\u00cda: Servicios, Comercializaci\u00d3n",
    "sg:phone":"+34 935 92 26 50",
    "sg:postcode":"08290",
    "sg:province":"Barcelona",
    "wof:name":"El Morabiti  Mohamed",
    "wof:placetype":"venue"
},
  "geometry": {"coordinates":[2.1319980621,41.4953155518],"type":"Point"}
}