{
  "type": "Feature",
  "properties": {
    "iso:country":"ES",
    "sg:address":"Calle de Libertad (la), 5",
    "sg:city":"Zaragoza",
    "sg:orig_category":"Cl\u00cdnicas M\u00c9dicas",
    "sg:phone":"+34 976 20 37 97",
    "sg:postcode":"50003",
    "sg:province":"Zaragoza",
    "wof:name":"Gasca Binaburo Fernando",
    "wof:placetype":"venue"
},
  "geometry": {"coordinates":[-0.8804789782,41.6534156799],"type":"Point"}
}