{
  "type": "Feature",
  "properties": {
    "iso:country":"ES",
    "sg:address":"Muralla De Sant Llorenc, 14",
    "sg:city":"Mataro",
    "sg:orig_category":"Abogados",
    "sg:phone":"+34 937 90 19 92",
    "sg:postcode":"08302",
    "sg:province":"Barcelona",
    "wof:name":"Alcalde-rodriguez Advocats Associats S.c.p.",
    "wof:placetype":"venue"
},
  "geometry": {"coordinates":[2.443628788,41.5388565063],"type":"Point"}
}