{
  "type": "Feature",
  "properties": {
    "addr:full":"Calle de Londres, 4 Torrejon Ardoz Madrid 28850",
    "addr:housenumber":"4",
    "addr:postcode":"28850",
    "addr:street":"Calle De Londres",
    "iso:country":"ES",
    "sg:address":"Calle de Londres, 4",
    "sg:city":"Torrejon Ardoz",
    "sg:orig_category":"Transportes Por V\u00cdas Navegables",
    "sg:phone":"+34 916 75 55 11",
    "sg:postcode":"28850",
    "sg:province":"Madrid",
    "wof:name":"Silva Gomez Francisco",
    "wof:placetype":"venue"
},
  "geometry": {"coordinates":[-3.4748210907,40.4597625732],"type":"Point"}
}