{
  "type": "Feature",
  "properties": {
    "iso:country":"ES",
    "sg:address":"Calle de Trinidad, 2",
    "sg:city":"Cullar-vega",
    "sg:orig_category":"Promotores Constructores",
    "sg:phone":"+34 958 58 22 78",
    "sg:postcode":"18195",
    "sg:province":"Granada",
    "wof:name":"Construcciones Promociones Salinas Benito S L",
    "wof:placetype":"venue"
},
  "geometry": {"coordinates":[-3.6712660789,37.1530532837],"type":"Point"}
}