{
  "type": "Feature",
  "properties": {
    "addr:full":"Calle de Salces Anselma De, 16 Bilbao Vizcaya 48007",
    "addr:postcode":"48007",
    "addr:street":"Calle De Salces",
    "iso:country":"ES",
    "sg:address":"Calle de Salces Anselma De, 16",
    "sg:city":"Bilbao",
    "sg:orig_category":"Dise\u00d1o Industrial",
    "sg:phone":"+34 944 00 17 97",
    "sg:postcode":"48007",
    "sg:province":"Vizcaya",
    "wof:name":"Eps 2020 S.l",
    "wof:placetype":"venue"
},
  "geometry": {"coordinates":[-2.924544096,43.2673721313],"type":"Point"}
}