{
  "type": "Feature",
  "properties": {
    "iso:country":"ES",
    "sg:address":"Calle de Carlos Diaz De La Campa, 1",
    "sg:city":"Comillas",
    "sg:orig_category":"Inmobiliaria (agencias)",
    "sg:phone":"+34 942 72 25 92",
    "sg:postcode":"39520",
    "sg:province":"Cantabria",
    "sg:website":"gumar@arrakis.es",
    "wof:name":"Martinez Poo Susana",
    "wof:placetype":"venue"
},
  "geometry": {"coordinates":[-4.2906475067,43.3854103088],"type":"Point"}
}