{
  "type": "Feature",
  "properties": {
    "iso:country":"ES",
    "sg:address":"Carrer de Diputacio, 21",
    "sg:city":"Montmelo",
    "sg:orig_category":"Ropa Y Art\u00cdculos Pre",
    "sg:phone":"+34 935 72 38 50",
    "sg:postcode":"08160",
    "sg:province":"Barcelona",
    "wof:name":"Fernandez Cano Eva Maria",
    "wof:placetype":"venue"
},
  "geometry": {"coordinates":[2.246243,41.5516662598],"type":"Point"}
}