{
  "type": "Feature",
  "properties": {
    "addr:full":"Calle de Santander Mediterraneo, 9 Calatayud Zaragoza 50300",
    "addr:housenumber":"9",
    "addr:postcode":"50300",
    "addr:street":"Calle De Santander Mediterraneo",
    "iso:country":"ES",
    "sg:address":"Calle de Santander Mediterraneo, 9",
    "sg:city":"Calatayud",
    "sg:orig_category":"Centros Empresariales",
    "sg:phone":"+34 976 89 72 00",
    "sg:postcode":"50300",
    "sg:province":"Zaragoza",
    "wof:name":"Global Interface S.l.",
    "wof:placetype":"venue"
},
  "geometry": {"coordinates":[-1.6401330233,41.3481254578],"type":"Point"}
}