{
  "type": "Feature",
  "properties": {
    "addr:full":"Calle de Esparteros, 11 Carmona Sevilla 41410",
    "addr:housenumber":"11",
    "addr:postcode":"41410",
    "addr:street":"Calle De Esparteros",
    "iso:country":"ES",
    "sg:address":"Calle de Esparteros, 11",
    "sg:city":"Carmona",
    "sg:orig_category":"Autob\u00das (explotaci\u00d3n Y Servicios De)",
    "sg:phone":"+34 954 19 11 52",
    "sg:postcode":"41410",
    "sg:province":"Sevilla",
    "wof:name":"Hansbus S.l.",
    "wof:placetype":"venue"
},
  "geometry": {"coordinates":[-5.648252964,37.4802856445],"type":"Point"}
}