{
  "type": "Feature",
  "properties": {
    "iso:country":"ES",
    "sg:address":"Avda Elda (de), 14",
    "sg:city":"Petrer",
    "sg:orig_category":"Cajas Para Embalar",
    "sg:phone":"+34 965 37 08 46",
    "sg:postcode":"03610",
    "sg:province":"Alicante",
    "wof:name":"Caja De Credito De Petrel",
    "wof:placetype":"venue"
},
  "geometry": {"coordinates":[-0.786018014,38.4818344116],"type":"Point"}
}