{
  "type": "Feature",
  "properties": {
    "addr:full":"Calle de Jabalcuza, S/n Alhaurin Torre M\u00e1laga 29130",
    "addr:housenumber":"s",
    "addr:postcode":"29130",
    "addr:street":"Calle De Jabalcuza;/ N Alhaurin Torre Ma\u0301Laga",
    "iso:country":"ES",
    "sg:address":"Calle de Jabalcuza, S/n",
    "sg:city":"Alhaurin Torre",
    "sg:orig_category":"Ense\u00d1anza, Formaci\u00d3n Profesional: Aprendizaje",
    "sg:phone":"+34 952 41 71 13",
    "sg:postcode":"29130",
    "sg:province":"M\u00e1laga",
    "wof:name":"Junta De Andalucia-consejeria De Cultura",
    "wof:placetype":"venue"
},
  "geometry": {"coordinates":[-4.5643591881,36.6614837646],"type":"Point"}
}