{
  "type": "Feature",
  "properties": {
    "iso:country":"ES",
    "sg:address":"Avda De Los Cabezudos, 1",
    "sg:city":"Almonte",
    "sg:orig_category":"Empresas De Limpieza",
    "sg:phone":"+34 959 45 16 13",
    "sg:postcode":"21730",
    "sg:province":"Huelva",
    "wof:name":"Huarbec Servicios S.a.",
    "wof:placetype":"venue"
},
  "geometry": {"coordinates":[-6.52171278,37.2582893372],"type":"Point"}
}