{
  "type": "Feature",
  "properties": {
    "addr:full":"Carr Picasso, 4 Escala Girona 17130",
    "addr:housenumber":"4",
    "addr:postcode":"17130",
    "addr:street":"Carr Picasso",
    "iso:country":"ES",
    "sg:address":"Carr Picasso, 4",
    "sg:city":"Escala",
    "sg:orig_category":"Alimentaci\u00d3n General (al Por Menor)",
    "sg:phone":"+34 972 77 07 33",
    "sg:postcode":"17130",
    "sg:province":"Girona",
    "wof:name":"Llorens Soles Jaime",
    "wof:placetype":"venue"
},
  "geometry": {"coordinates":[3.1321649551,42.1229934692],"type":"Point"}
}