{
  "type": "Feature",
  "properties": {
    "iso:country":"ES",
    "sg:address":"Cami Vileta (la), 179",
    "sg:city":"Vileta",
    "sg:orig_category":"Promotores Constructores",
    "sg:phone":"+34 971 60 67 79",
    "sg:postcode":"07011",
    "sg:province":"Islas Baleares",
    "wof:name":"Urbanpalma S.l.",
    "wof:placetype":"venue"
},
  "geometry": {"coordinates":[2.6165289879,39.5947265625],"type":"Point"}
}