{
  "type": "Feature",
  "properties": {
    "addr:full":"Cmno Daya (de La), 46 Calasparra Murcia 30420",
    "addr:housenumber":"46",
    "addr:postcode":"30420",
    "addr:street":"Cmno Daya De La",
    "iso:country":"ES",
    "sg:address":"Cmno Daya (de La), 46",
    "sg:city":"Calasparra",
    "sg:orig_category":"Empresas De Desmonte",
    "sg:phone":"+34 968 72 13 51",
    "sg:postcode":"30420",
    "sg:province":"Murcia",
    "wof:name":"Sanchez Alvarez Pascual",
    "wof:placetype":"venue"
},
  "geometry": {"coordinates":[-1.6999490261,38.2315101624],"type":"Point"}
}