{
  "type": "Feature",
  "properties": {
    "iso:country":"ES",
    "sg:address":"San Domingo, S/n",
    "sg:city":"Calo",
    "sg:orig_category":"Autopistas (explotaci\u00d3n, Guardia Civil Y Polic\u00cda)",
    "sg:phone":"+34 981 80 74 69",
    "sg:postcode":"15895",
    "sg:province":"La Coru\u00f1a",
    "wof:name":"Autopistas Del Atlantico Concesionaria Espa\u00f1ola S.a.",
    "wof:placetype":"venue"
},
  "geometry": {"coordinates":[-8.5767364502,42.8445129395],"type":"Point"}
}