{
  "type": "Feature",
  "properties": {
    "iso:country":"ES",
    "sg:address":"Calle de Antonio Cabezon, 14",
    "sg:city":"Alcala Henares",
    "sg:orig_category":"Carnicer\u00cdas, Carnicer\u00cdas",
    "sg:phone":"+34 918 81 89 62",
    "sg:postcode":"28806",
    "sg:province":"Madrid",
    "wof:name":"Rus Abad Francisco",
    "wof:placetype":"venue"
},
  "geometry": {"coordinates":[-3.3766562939,40.4901504517],"type":"Point"}
}