{
  "type": "Feature",
  "properties": {
    "addr:full":"Pase Longares, 7 Zaragoza Zaragoza 50014",
    "addr:housenumber":"7",
    "addr:postcode":"50014",
    "addr:street":"Longares",
    "iso:country":"ES",
    "sg:address":"Pase Longares, 7",
    "sg:city":"Zaragoza",
    "sg:orig_category":"Inform\u00c1tica, Ofim\u00c1tica (estudios, Asesor\u00cda, Ingenier\u00cda, Formaci\u00d3n)",
    "sg:phone":"+34 976 47 53 58",
    "sg:postcode":"50014",
    "sg:province":"Zaragoza",
    "wof:name":"Zarasistemas S.c.",
    "wof:placetype":"venue"
},
  "geometry": {"coordinates":[-0.8663744926,41.6604423523],"type":"Point"}
}