{
  "type": "Feature",
  "properties": {
    "addr:full":"Calle de Antona De Dios, 14 Jerez De La Frontera C\u00e1diz 11402",
    "addr:housenumber":"14",
    "addr:postcode":"11402",
    "addr:street":"Calle De Antona De Dios",
    "iso:country":"ES",
    "sg:address":"Calle de Antona De Dios, 14",
    "sg:city":"Jerez De La Frontera",
    "sg:orig_category":"Imprenta",
    "sg:phone":"+34 956 32 40 04",
    "sg:postcode":"11402",
    "sg:province":"C\u00e1diz",
    "wof:name":"Graficas San Luis S.l.",
    "wof:placetype":"venue"
},
  "geometry": {"coordinates":[-6.1347608566,36.6859436035],"type":"Point"}
}