{
  "type": "Feature",
  "properties": {
    "iso:country":"ES",
    "sg:address":"Calle de Quintanar, 18",
    "sg:city":"Villalgordo Jucar",
    "sg:orig_category":"Carnicer\u00cdas, Carnicer\u00cdas",
    "sg:phone":"+34 967 45 54 41",
    "sg:postcode":"02636",
    "sg:province":"Albacete",
    "wof:name":"Carniceria Serna C.b.",
    "wof:placetype":"venue"
},
  "geometry": {"coordinates":[-2.0624189377,39.2962646484],"type":"Point"}
}