{
  "type": "Feature",
  "properties": {
    "addr:full":"Av Valles(palaudaries-la Serra), Km. 0010,5 Lli\u00e7a Vall Barcelona 08185",
    "addr:postcode":"08185",
    "addr:street":"Av Valles Palaudaries-La Serra Km. 0010,5 Llic\u0327A;Barcelona",
    "iso:country":"ES",
    "sg:address":"Av Valles(palaudaries-la Serra), Km. 0010,5",
    "sg:city":"Lli\u00e7a Vall",
    "sg:orig_category":"Distribuci\u00d3n De Petr\u00d3leo Y Derivados",
    "sg:phone":"+34 938 43 74 46",
    "sg:postcode":"08185",
    "sg:province":"Barcelona",
    "wof:name":"Estacio De Servei Llica De Vall S.a.",
    "wof:placetype":"venue"
},
  "geometry": {"coordinates":[2.2324490547,41.5865364075],"type":"Point"}
}