{
  "type": "Feature",
  "properties": {
    "addr:full":"Calle de Alejandro Prieto, 4 Puertollano Ciudad Real 13500",
    "addr:housenumber":"4",
    "addr:postcode":"13500",
    "addr:street":"Calle De Alejandro Prieto",
    "iso:country":"ES",
    "sg:address":"Calle de Alejandro Prieto, 4",
    "sg:city":"Puertollano",
    "sg:orig_category":"Zapatos (al Por Menor)",
    "sg:phone":"+34 926 42 10 72",
    "sg:postcode":"13500",
    "sg:province":"Ciudad Real",
    "wof:name":"Garcia Sanchez Esteban",
    "wof:placetype":"venue"
},
  "geometry": {"coordinates":[-4.1057882309,38.6874084473],"type":"Point"}
}