{
  "type": "Feature",
  "properties": {
    "iso:country":"ES",
    "sg:address":"Calle de Se\u00d1or Ovalle, 5",
    "sg:city":"Astorga",
    "sg:orig_category":"Molduras, Junquillos, Listones Y Molduras Perforadas",
    "sg:phone":"+34 987 61 63 03",
    "sg:postcode":"24700",
    "sg:province":"Le\u00f3n",
    "wof:name":"Angel Y Luciano C.b.",
    "wof:placetype":"venue"
},
  "geometry": {"coordinates":[-6.052485466,42.4547920227],"type":"Point"}
}