{
  "type": "Feature",
  "properties": {
    "addr:full":"Carrer de Major, 32 Terrassa Barcelona 08221",
    "addr:housenumber":"32",
    "addr:postcode":"08221",
    "addr:street":"Carrer De Major",
    "iso:country":"ES",
    "sg:address":"Carrer de Major, 32",
    "sg:city":"Terrassa",
    "sg:orig_category":"Urbanistas",
    "sg:phone":"+34 937 80 56 79",
    "sg:postcode":"08221",
    "sg:province":"Barcelona",
    "wof:name":"Mira Cortadellas Maria Mercedes",
    "wof:placetype":"venue"
},
  "geometry": {"coordinates":[2.0097749233,41.5615386963],"type":"Point"}
}