{
  "type": "Feature",
  "properties": {
    "addr:full":"Calle de Francisco Gervas, 12 Madrid Madrid 28020",
    "addr:housenumber":"12",
    "addr:postcode":"madrid;28020",
    "addr:street":"Calle De Francisco Gervas",
    "iso:country":"ES",
    "sg:address":"Calle de Francisco Gervas, 12",
    "sg:city":"Madrid",
    "sg:orig_category":"Comercios E Industrias (cesi\u00d3n Y Reactivaci\u00d3n)",
    "sg:phone":"+34 915 72 17 15",
    "sg:postcode":"28020",
    "sg:province":"Madrid",
    "wof:name":"Ques Cardell Luis",
    "wof:placetype":"venue"
},
  "geometry": {"coordinates":[-3.6931760311,40.4609527588],"type":"Point"}
}