{
  "type": "Feature",
  "properties": {
    "addr:full":"Ctra Madrid-alicante, Km. 0256,4 Chinchilla Monte-aragon Albacete 02520",
    "addr:postcode":"02520",
    "addr:street":"Ctra Madrid-Alicante Km. 0256,4;Monte-Aragon",
    "iso:country":"ES",
    "sg:address":"Ctra Madrid-alicante, Km. 0256,4",
    "sg:city":"Chinchilla Monte-aragon",
    "sg:orig_category":"Distribuci\u00d3n De Petr\u00d3leo Y Derivados",
    "sg:phone":"+34 967 26 05 57",
    "sg:postcode":"02520",
    "sg:province":"Albacete",
    "wof:name":"Pedro Cifuentes S.a.",
    "wof:placetype":"venue"
},
  "geometry": {"coordinates":[-1.7232949734,38.9209251404],"type":"Point"}
}