{
  "type": "Feature",
  "properties": {
    "iso:country":"ES",
    "sg:address":"Calle de Ricardo De La Cierva, 5",
    "sg:city":"Poligono Industrial Los Villares",
    "sg:orig_category":"Mensajer\u00cda Express, Portes Internacionales",
    "sg:phone":"+34 923 25 99 67",
    "sg:postcode":"37184",
    "sg:province":"Salamanca",
    "sg:website":"www.asmred.com",
    "wof:name":"Transur-transportes Urgentes S.l.",
    "wof:placetype":"venue"
},
  "geometry": {"coordinates":[-5.6476120949,41.0065116882],"type":"Point"}
}