{
  "type": "Feature",
  "properties": {
    "iso:country":"ES",
    "sg:address":"Plaz Longoria Carbajal, 1",
    "sg:city":"Oviedo",
    "sg:orig_category":"Bisuter\u00cda, Joyer\u00cda, Relojer\u00cda (al Por Menor)",
    "sg:phone":"+34 985 21 72 30",
    "sg:postcode":"33002",
    "sg:province":"Asturias",
    "wof:name":"Alvarez Ondina Gonzalo",
    "wof:placetype":"venue"
},
  "geometry": {"coordinates":[-5.8484320641,43.3644218445],"type":"Point"}
}