{
  "type": "Feature",
  "properties": {
    "addr:full":"Pase Alfonso Xiii, 57 Cartagena Murcia 30203",
    "addr:housenumber":"57",
    "addr:postcode":"30203",
    "addr:street":"Alfonso Xiii",
    "iso:country":"ES",
    "sg:address":"Pase Alfonso Xiii, 57",
    "sg:city":"Cartagena",
    "sg:orig_category":"Ense\u00d1anza Secundaria: Colegios Y Escuelas Privadas",
    "sg:phone":"+34 968 50 62 60",
    "sg:postcode":"30203",
    "sg:province":"Murcia",
    "wof:name":"Instituto Nacional De Ense\u00d1anza Media Isaac Peral",
    "wof:placetype":"venue"
},
  "geometry": {"coordinates":[-0.9785429835,37.607208252],"type":"Point"}
}