{
  "type": "Feature",
  "properties": {
    "iso:country":"ES",
    "sg:address":"C\u00f1o. Mourelos (dimo), 11",
    "sg:city":"Catoira",
    "sg:classifiers":[
        {
            "category":"Recreation",
            "type":"Entertainment"
        }
    ],
    "sg:phone":"+34 986 54 62 38",
    "sg:postcode":"36612",
    "sg:province":"Pontevedra",
    "sg:tags":[
        "caza",
        "pr\u00c1ctica",
        "la",
        "de",
        "pesca",
        "y"
    ],
    "wof:name":"Catoira Garcia Manuel",
    "wof:placetype":"venue"
},
  "geometry": {"coordinates":[-8.7250490189,42.6708488464],"type":"Point"}
}