{
  "type": "Feature",
  "properties": {
    "iso:country":"ES",
    "sg:address":"Carrer de Santa Anna, 29",
    "sg:city":"Reus",
    "sg:orig_category":"Electrodom\u00c9sticos (al Por Menor)",
    "sg:phone":"+34 977 77 06 47",
    "sg:postcode":"43201",
    "sg:province":"Tarragona",
    "wof:name":"Lozano Nogues Jose Maria",
    "wof:placetype":"venue"
},
  "geometry": {"coordinates":[1.1086089611,41.1570358276],"type":"Point"}
}