{
  "type": "Feature",
  "properties": {
    "iso:country":"ES",
    "sg:address":"Calle de Alvarado Y Bracamonte, 32",
    "sg:city":"Cuesta",
    "sg:orig_category":"Cerrajer\u00cda, Ferrallista",
    "sg:phone":"+34 922 64 37 17",
    "sg:postcode":"38320",
    "sg:province":"Santa Cruz De Tenerife",
    "wof:name":"Cerrajeria El Competidor Comunidad De Bienes",
    "wof:placetype":"venue"
},
  "geometry": {"coordinates":[-16.2852497101,28.4712219238],"type":"Point"}
}