{
  "type": "Feature",
  "properties": {
    "addr:full":"Calle de Pozuelo, 3 Ventorro Del Cano Madrid 28925",
    "addr:housenumber":"3",
    "addr:postcode":"28925",
    "addr:street":"Calle De Pozuelo",
    "iso:country":"ES",
    "sg:address":"Calle de Pozuelo, 3",
    "sg:city":"Ventorro Del Cano",
    "sg:orig_category":"Electrodom\u00c9sticos (al Por Menor)",
    "sg:phone":"+34 916 33 26 40",
    "sg:postcode":"28925",
    "sg:province":"Madrid",
    "wof:name":"Tejube S.l.",
    "wof:placetype":"venue"
},
  "geometry": {"coordinates":[-3.8357679844,40.3951797485],"type":"Point"}
}