{
  "type": "Feature",
  "properties": {
    "iso:country":"ES",
    "sg:address":"Calle de Villajoyosa, 26",
    "sg:city":"Requena",
    "sg:orig_category":"Alimentaci\u00d3n General (al Por Mayor)",
    "sg:phone":"+34 962 30 32 76",
    "sg:postcode":"46340",
    "sg:province":"Valencia",
    "wof:name":"Bernardo Rubio Juan Manuel",
    "wof:placetype":"venue"
},
  "geometry": {"coordinates":[-1.1057020426,39.4879493713],"type":"Point"}
}