{
  "type": "Feature",
  "properties": {
    "addr:full":"Calle de Romero De Torres, S/n Hinojosa Del Duque C\u00f3rdoba 14270",
    "addr:postcode":"14270",
    "addr:street":"Calle De Romero De Torres S / N;Co\u0301Rdoba",
    "iso:country":"ES",
    "sg:address":"Calle de Romero De Torres, S/n",
    "sg:city":"Hinojosa Del Duque",
    "sg:orig_category":"Empresas De Carpinter\u00cda Met\u00c1lica",
    "sg:phone":"+34 957 14 12 58",
    "sg:postcode":"14270",
    "sg:province":"C\u00f3rdoba",
    "wof:name":"Ferricor S.c.a.",
    "wof:placetype":"venue"
},
  "geometry": {"coordinates":[-5.1389288902,38.5003585815],"type":"Point"}
}