{
  "type": "Feature",
  "properties": {
    "addr:full":"Plaz Valdehondillo, 1 Fuenlabrada Madrid 28944",
    "addr:housenumber":"1",
    "addr:postcode":"28944",
    "addr:street":"Plaz Valdehondillo",
    "iso:country":"ES",
    "sg:address":"Plaz Valdehondillo, 1",
    "sg:city":"Fuenlabrada",
    "sg:orig_category":"Alquiler De V\u00cddeo",
    "sg:phone":"+34 916 97 45 38",
    "sg:postcode":"28944",
    "sg:province":"Madrid",
    "wof:name":"Mora Revuelta Jesus Miguel",
    "wof:placetype":"venue"
},
  "geometry": {"coordinates":[-3.8006310463,40.2771606445],"type":"Point"}
}