{
  "type": "Feature",
  "properties": {
    "addr:full":"Calle de Gran Via, 41 Zaragoza Zaragoza 50006",
    "addr:housenumber":"41",
    "addr:postcode":"50006",
    "addr:street":"Calle De Gran Via",
    "iso:country":"ES",
    "sg:address":"Calle de Gran Via, 41",
    "sg:city":"Zaragoza",
    "sg:orig_category":"Abogados",
    "sg:phone":"+34 976 21 31 43",
    "sg:postcode":"50006",
    "sg:province":"Zaragoza",
    "wof:name":"Sanchez Sanz Blas Eduardo",
    "wof:placetype":"venue"
},
  "geometry": {"coordinates":[-0.8913459778,41.6443328857],"type":"Point"}
}