{
  "type": "Feature",
  "properties": {
    "addr:full":"Carrer de Amadeu Vives, S/n Cornella Llobregat Barcelona 08940",
    "addr:housenumber":"s",
    "addr:postcode":"08940",
    "addr:street":"Carrer De Amadeu Vives;/ N",
    "iso:country":"ES",
    "sg:address":"Carrer de Amadeu Vives, S/n",
    "sg:city":"Cornella Llobregat",
    "sg:orig_category":"Asociaciones, Organismos Culturales Y Socioeducativos",
    "sg:phone":"+34 933 77 25 75",
    "sg:postcode":"08940",
    "sg:province":"Barcelona",
    "wof:name":"Club D'amics Del Ferrocarril",
    "wof:placetype":"venue"
},
  "geometry": {"coordinates":[2.0716900826,41.3516769409],"type":"Point"}
}