{
  "type": "Feature",
  "properties": {
    "iso:country":"ES",
    "sg:address":"Calle de Rio Ebro, 2",
    "sg:city":"Torre-pacheco",
    "sg:orig_category":"Inmobiliaria (agencias)",
    "sg:phone":"+34 968 58 50 72",
    "sg:postcode":"30700",
    "sg:province":"Murcia",
    "wof:name":"Viviendas Y Construcciones Protegidas S. A.",
    "wof:placetype":"venue"
},
  "geometry": {"coordinates":[-0.9502941966,37.7474250793],"type":"Point"}
}