{
  "type": "Feature",
  "properties": {
    "addr:full":"Avda Constitucion, 6 Hellin Albacete 02400",
    "addr:housenumber":"6",
    "addr:postcode":"02400",
    "addr:street":"Avda Constitucion",
    "iso:country":"ES",
    "sg:address":"Avda Constitucion, 6",
    "sg:city":"Hellin",
    "sg:orig_category":"Frutas Y Legumbres Frescas (al Por Mayor)",
    "sg:phone":"+34 967 30 02 34",
    "sg:postcode":"02400",
    "sg:province":"Albacete",
    "wof:name":"Benavent Lila Rosendo",
    "wof:placetype":"venue"
},
  "geometry": {"coordinates":[-1.6962970495,38.4675941467],"type":"Point"}
}