{
  "type": "Feature",
  "properties": {
    "addr:full":"Plaz Constitucion, 1 Donostia-san Sebastian Guip\u00f9zcoa 20003",
    "addr:housenumber":"1",
    "addr:postcode":"20003",
    "addr:street":"Constitucion",
    "iso:country":"ES",
    "sg:address":"Plaz Constitucion, 1",
    "sg:city":"Donostia-san Sebastian",
    "sg:orig_category":"Renovaci\u00d3n Inmobiliaria",
    "sg:phone":"+34 943 43 13 82",
    "sg:postcode":"20003",
    "sg:province":"Guip\u00f9zcoa",
    "wof:name":"Parvisa S.a.",
    "wof:placetype":"venue"
},
  "geometry": {"coordinates":[-1.9851219654,43.3236923218],"type":"Point"}
}