{
  "type": "Feature",
  "properties": {
    "iso:country":"ES",
    "sg:address":"Calle de Cervantes, 12",
    "sg:city":"Villanueva De Los Infantes",
    "sg:orig_category":"Asociaciones Y Clubs Deportivos",
    "sg:phone":"+34 926 36 19 30",
    "sg:postcode":"13320",
    "sg:province":"Ciudad Real",
    "wof:name":"Migallon Jimenez Esteban",
    "wof:placetype":"venue"
},
  "geometry": {"coordinates":[-3.0135536194,38.7360877991],"type":"Point"}
}