{
  "type": "Feature",
  "properties": {
    "iso:country":"ES",
    "sg:address":"Ctra. S. Pablo, Km. 0001,2",
    "sg:city":"Menasalbas",
    "sg:orig_category":"Muebles, Minoristas",
    "sg:phone":"+34 925 40 74 50",
    "sg:postcode":"45128",
    "sg:province":"Toledo",
    "wof:name":"Muebles Ferpi S.l.",
    "wof:placetype":"venue"
},
  "geometry": {"coordinates":[-4.2844028473,39.636806488],"type":"Point"}
}