{
  "type": "Feature",
  "properties": {
    "addr:full":"Calle de Arroyos (los), 2 Milla Del Rio Le\u00f3n 24283",
    "addr:housenumber":"2",
    "addr:postcode":"24283",
    "addr:street":"Calle De Arroyos Los;Del;Leo\u0301N",
    "iso:country":"ES",
    "sg:address":"Calle de Arroyos (los), 2",
    "sg:city":"Milla Del Rio",
    "sg:orig_category":"Chapister\u00cda",
    "sg:phone":"+34 987 35 76 20",
    "sg:postcode":"24283",
    "sg:province":"Le\u00f3n",
    "wof:name":"Alonso Garcia Fernando",
    "wof:placetype":"venue"
},
  "geometry": {"coordinates":[-5.8479251862,42.5727157593],"type":"Point"}
}