{
  "type": "Feature",
  "properties": {
    "iso:country":"ES",
    "sg:address":"Calle de Sevilla, 1",
    "sg:city":"Palencia",
    "sg:orig_category":"Remolques, Carretillas De Mano Para Operaciones Portuarias",
    "sg:phone":"+34 979 16 58 48",
    "sg:postcode":"34004",
    "sg:province":"Palencia",
    "wof:name":"Carretillas Mayor S.a.",
    "wof:placetype":"venue"
},
  "geometry": {"coordinates":[-4.5147590637,42.0003814697],"type":"Point"}
}