{
  "type": "Feature",
  "properties": {
    "addr:full":"Calle de San Sebastian, 47 Hinojosa Del Duque C\u00f3rdoba 14270",
    "addr:housenumber":"47",
    "addr:postcode":"14270",
    "addr:street":"Calle De San Sebastian;Co\u0301Rdoba",
    "iso:country":"ES",
    "sg:address":"Calle de San Sebastian, 47",
    "sg:city":"Hinojosa Del Duque",
    "sg:orig_category":"Energ\u00cda Solar Y Nuevas Energ\u00cdas (equipo, Estudios)",
    "sg:phone":"+34 957 14 31 47",
    "sg:postcode":"14270",
    "sg:province":"C\u00f3rdoba",
    "wof:name":"Guroa Sociedad Cooperativa Andaluza",
    "wof:placetype":"venue"
},
  "geometry": {"coordinates":[-5.1431660652,38.4965324402],"type":"Point"}
}