{
  "type": "Feature",
  "properties": {
    "iso:country":"ES",
    "sg:address":"Calle de Francos Rodriguez, 50",
    "sg:city":"Madrid",
    "sg:orig_category":"Carnicer\u00cdas, Carnicer\u00cdas",
    "sg:phone":"+34 914 50 06 84",
    "sg:postcode":"28039",
    "sg:province":"Madrid",
    "sg:website":"www.biocarnes.es",
    "wof:name":"Fernandez Pacheco Domingo",
    "wof:placetype":"venue"
},
  "geometry": {"coordinates":[-3.706097126,40.4565963745],"type":"Point"}
}