{
  "type": "Feature",
  "properties": {
    "addr:full":"Carr Montagut, 383 Urbanitzacio Aigua-xellida Girona 17212",
    "addr:housenumber":"383",
    "addr:postcode":"17212",
    "addr:street":"Carr Montagut;Urbanitzacio Aigua-Xellida",
    "iso:country":"ES",
    "sg:address":"Carr Montagut, 383",
    "sg:city":"Urbanitzacio Aigua-xellida",
    "sg:orig_category":"Ingeniero",
    "sg:phone":"+34 972 62 04 11",
    "sg:postcode":"17212",
    "sg:province":"Girona",
    "wof:name":"Munster  Jean Claude",
    "wof:placetype":"venue"
},
  "geometry": {"coordinates":[3.2065498829,41.9183349609],"type":"Point"}
}