{
  "type": "Feature",
  "properties": {
    "addr:full":"Calle de Leonor Pierri Rivas, 4 Pozuelo De Alarcon Madrid 28223",
    "addr:housenumber":"4",
    "addr:postcode":"28223",
    "addr:street":"Calle De Leonor Pierri Rivas",
    "iso:country":"ES",
    "sg:address":"Calle de Leonor Pierri Rivas, 4",
    "sg:city":"Pozuelo De Alarcon",
    "sg:orig_category":"Cursos Particulares, Asistencia Escolar",
    "sg:phone":"+34 913 52 57 39",
    "sg:postcode":"28223",
    "sg:province":"Madrid",
    "wof:name":"Cervera Quilez Luis",
    "wof:placetype":"venue"
},
  "geometry": {"coordinates":[-3.8221619129,40.4366264343],"type":"Point"}
}