{
  "type": "Feature",
  "properties": {
    "iso:country":"ES",
    "sg:address":"Calle de Castellar (el), S/n",
    "sg:city":"Alagon",
    "sg:orig_category":"Promotores Constructores",
    "sg:phone":"+34 976 61 12 24",
    "sg:postcode":"50630",
    "sg:province":"Zaragoza",
    "wof:name":"Construcciones Sofi S. L.",
    "wof:placetype":"venue"
},
  "geometry": {"coordinates":[-1.1199549437,41.7730445862],"type":"Point"}
}