{
  "type": "Feature",
  "properties": {
    "addr:full":"Calle de Conde De Cartagena, 10 Madrid Madrid 28007",
    "addr:housenumber":"10",
    "addr:postcode":"madrid;28007",
    "addr:street":"Calle De Conde De Cartagena",
    "iso:country":"ES",
    "sg:address":"Calle de Conde De Cartagena, 10",
    "sg:city":"Madrid",
    "sg:orig_category":"Sociedades, Compa\u00d1\u00cdas Aseguradoras",
    "sg:phone":"+34 915 51 08 81",
    "sg:postcode":"28007",
    "sg:province":"Madrid",
    "wof:name":"Slecto Ejecutivos S.l",
    "wof:placetype":"venue"
},
  "geometry": {"coordinates":[-3.6754419804,40.407951355],"type":"Point"}
}