{
  "type": "Feature",
  "properties": {
    "addr:full":"Calle de Vegueta, 3 Alcala Guadaira Sevilla 41500",
    "addr:housenumber":"3",
    "addr:postcode":"41500",
    "addr:street":"Calle De Vegueta",
    "iso:country":"ES",
    "sg:address":"Calle de Vegueta, 3",
    "sg:city":"Alcala Guadaira",
    "sg:orig_category":"M\u00c9dicos: Medicina General Orientada A La Acupuntura",
    "sg:phone":"+34 955 61 43 81",
    "sg:postcode":"41500",
    "sg:province":"Sevilla",
    "wof:name":"Sanchez Sanchez Trinidad",
    "wof:placetype":"venue"
},
  "geometry": {"coordinates":[-5.8431820869,37.3410491943],"type":"Point"}
}