{
  "type": "Feature",
  "properties": {
    "addr:full":"Calle de Encomienda, 7 Abanilla Murcia 30640",
    "addr:housenumber":"7",
    "addr:postcode":"30640",
    "addr:street":"Calle De Encomienda",
    "iso:country":"ES",
    "sg:address":"Calle de Encomienda, 7",
    "sg:city":"Abanilla",
    "sg:orig_category":"Asociaciones, Organismos Culturales Y Socioeducativos",
    "sg:phone":"+34 968 68 07 19",
    "sg:postcode":"30640",
    "sg:province":"Murcia",
    "wof:name":"Asociacion De Moros Y Cristianos",
    "wof:placetype":"venue"
},
  "geometry": {"coordinates":[-1.042175293,38.2060546875],"type":"Point"}
}