{
  "type": "Feature",
  "properties": {
    "iso:country":"ES",
    "sg:address":"Ctra Bao, 38",
    "sg:city":"Combro",
    "sg:orig_category":"Supermercados Y Hipermercados",
    "sg:phone":"+34 986 46 09 46",
    "sg:postcode":"36330",
    "sg:province":"Pontevedra",
    "wof:name":"Ignacio De Las Cuevas S.a.",
    "wof:placetype":"venue"
},
  "geometry": {"coordinates":[-8.694773674,42.6678962708],"type":"Point"}
}