{
  "type": "Feature",
  "properties": {
    "addr:full":"Avda Santiago Ramon Y Cajal, 19 Badajoz Badajoz 06001",
    "addr:housenumber":"19",
    "addr:postcode":"06001",
    "addr:street":"Avda Santiago Ramon Y Cajal",
    "iso:country":"ES",
    "sg:address":"Avda Santiago Ramon Y Cajal, 19",
    "sg:city":"Badajoz",
    "sg:orig_category":"Ropa Para Ni\u00d1os (al Por Menor)",
    "sg:phone":"+34 924 24 22 33",
    "sg:postcode":"06001",
    "sg:province":"Badajoz",
    "wof:name":"Borrego Vazquez Natividad",
    "wof:placetype":"venue"
},
  "geometry": {"coordinates":[-6.9754900932,38.8760261536],"type":"Point"}
}