{
  "type": "Feature",
  "properties": {
    "addr:full":"Calle de Concha General, 19 Bilbao Vizcaya 48010",
    "addr:housenumber":"19",
    "addr:postcode":"48010",
    "addr:street":"Calle De Concha General",
    "iso:country":"ES",
    "sg:address":"Calle de Concha General, 19",
    "sg:city":"Bilbao",
    "sg:orig_category":"Instalaci\u00d3n De Sanitarios",
    "sg:phone":"+34 944 43 52 67",
    "sg:postcode":"48010",
    "sg:province":"Vizcaya",
    "wof:name":"Alcaraz Manzano Eduardo",
    "wof:placetype":"venue"
},
  "geometry": {"coordinates":[-2.9413208961,43.2591667175],"type":"Point"}
}