{
  "type": "Feature",
  "properties": {
    "iso:country":"ES",
    "sg:address":"Calle de Gomez Ferrer, 110",
    "sg:city":"Torrent",
    "sg:orig_category":"Internados & Ense\u00d1anza Privada",
    "sg:phone":"+34 961 55 17 19",
    "sg:postcode":"46900",
    "sg:province":"Valencia",
    "wof:name":"Colegio Torre-pinos",
    "wof:placetype":"venue"
},
  "geometry": {"coordinates":[-0.4620859921,39.44272995],"type":"Point"}
}