{
  "type": "Feature",
  "properties": {
    "iso:country":"ES",
    "sg:address":"Av Salle (la), 43",
    "sg:city":"Reus",
    "sg:orig_category":"Molduras, Junquillos, Listones Y Molduras Perforadas",
    "sg:phone":"+34 977 77 48 44",
    "sg:postcode":"43205",
    "sg:province":"Tarragona",
    "wof:name":"Prats Gaia Salvador",
    "wof:placetype":"venue"
},
  "geometry": {"coordinates":[1.1078369617,41.148147583],"type":"Point"}
}