{
  "type": "Feature",
  "properties": {
    "iso:country":"ES",
    "sg:address":"Avda Paz De (la), 64",
    "sg:city":"Logro\u00f1o",
    "sg:orig_category":"Agencias De Viajes",
    "sg:phone":"+34 941 24 98 19",
    "sg:postcode":"26004",
    "sg:province":"La Rioja",
    "sg:website":"www.viajeselcorteingles.es",
    "wof:name":"Viajes El Corte Ingles S.a.",
    "wof:placetype":"venue"
},
  "geometry": {"coordinates":[-2.4349520206,42.4642219543],"type":"Point"}
}