{
  "type": "Feature",
  "properties": {
    "iso:country":"ES",
    "sg:address":"Ctra. Chozas, S/n",
    "sg:city":"Fuensalida",
    "sg:orig_category":"Alcoholes Y Aguardientes (fabricaci\u00d3n, Al Por Mayor)",
    "sg:phone":"+34 925 73 13 06",
    "sg:postcode":"45510",
    "sg:province":"Toledo",
    "sg:website":"www.gbvinartis.com",
    "wof:name":"Bodegas Vinartis",
    "wof:placetype":"venue"
},
  "geometry": {"coordinates":[-4.1983242035,40.0570297241],"type":"Point"}
}