{
  "type": "Feature",
  "properties": {
    "iso:country":"ES",
    "sg:address":"Plaz Alcalde J. R. Aguirreche, 1",
    "sg:city":"Irun",
    "sg:orig_category":"Peluquer\u00cdas",
    "sg:phone":"+34 943 62 23 06",
    "sg:postcode":"20302",
    "sg:province":"Guip\u00f9zcoa",
    "wof:name":"Lairis Estilista Sl.",
    "wof:placetype":"venue"
},
  "geometry": {"coordinates":[-1.7918339968,43.339427948],"type":"Point"}
}