{
  "type": "Feature",
  "properties": {
    "addr:full":"Carrer de Amilcar, 166 Barcelona Barcelona 08032",
    "addr:housenumber":"166",
    "addr:postcode":"08032",
    "addr:street":"Carrer De Amilcar",
    "iso:country":"ES",
    "sg:address":"Carrer de Amilcar, 166",
    "sg:city":"Barcelona",
    "sg:orig_category":"Asociaciones, Organismos Culturales Y Socioeducativos",
    "sg:phone":"+34 933 47 11 73",
    "sg:postcode":"08032",
    "sg:province":"Barcelona",
    "wof:name":"Asociacion Para La Proclama Y El Estudio Del Monismo",
    "wof:placetype":"venue"
},
  "geometry": {"coordinates":[2.1729176044,41.4215049744],"type":"Point"}
}