{
  "type": "Feature",
  "properties": {
    "addr:full":"Avda Paz (de La), 5 Cordoba C\u00f3rdoba 14005",
    "addr:housenumber":"5",
    "addr:postcode":"14005",
    "addr:street":"Avda Paz De La;Co\u0301Rdoba",
    "iso:country":"ES",
    "sg:address":"Avda Paz (de La), 5",
    "sg:city":"Cordoba",
    "sg:orig_category":"Reposter\u00cdas",
    "sg:phone":"+34 957 46 33 87",
    "sg:postcode":"14005",
    "sg:province":"C\u00f3rdoba",
    "wof:name":"Panaderias Reunidas Cordobesas S.a.",
    "wof:placetype":"venue"
},
  "geometry": {"coordinates":[-4.8158488274,37.880531311],"type":"Point"}
}