{
  "type": "Feature",
  "properties": {
    "iso:country":"ES",
    "sg:address":"Calle de Bailarin Vicente Escudero, 2",
    "sg:city":"Valladolid",
    "sg:orig_category":"Inform\u00c1tica: Material Y Suministros",
    "sg:phone":"+34 983 30 95 05",
    "sg:postcode":"47005",
    "sg:province":"Valladolid",
    "wof:name":"Araque Print S.l.",
    "wof:placetype":"venue"
},
  "geometry": {"coordinates":[-4.7170395851,41.6497077942],"type":"Point"}
}