{
  "type": "Feature",
  "properties": {
    "iso:country":"ES",
    "sg:address":"Carr Abeurador, 6",
    "sg:city":"Felanitx",
    "sg:orig_category":"Asesor\u00cda Sobre Comunicaci\u00d3n De Empresas",
    "sg:phone":"+34 971 58 23 24",
    "sg:postcode":"07200",
    "sg:province":"Islas Baleares",
    "wof:name":"Nadal Cerda Antonio",
    "wof:placetype":"venue"
},
  "geometry": {"coordinates":[3.1469891071,39.468837738],"type":"Point"}
}