{
  "type": "Feature",
  "properties": {
    "addr:full":"Carrer de Sureda, 5 Palma Islas Baleares 07007",
    "addr:housenumber":"5",
    "addr:postcode":"07007",
    "addr:street":"Carrer De Sureda",
    "iso:country":"ES",
    "sg:address":"Carrer de Sureda, 5",
    "sg:city":"Palma",
    "sg:orig_category":"Carnicer\u00cdas, Carnicer\u00cdas",
    "sg:phone":"+34 971 27 67 60",
    "sg:postcode":"07007",
    "sg:province":"Islas Baleares",
    "wof:name":"Pi\u00f1a Aguilo Gaspar",
    "wof:placetype":"venue"
},
  "geometry": {"coordinates":[2.6713418961,39.5718650818],"type":"Point"}
}