{
  "type": "Feature",
  "properties": {
    "iso:country":"ES",
    "sg:address":"Rua Celanova (de), 56",
    "sg:city":"Ourense",
    "sg:orig_category":"Reposter\u00cdas",
    "sg:phone":"+34 988 23 51 48",
    "sg:postcode":"32004",
    "sg:province":"Ourense",
    "wof:name":"Panaderia Tito S.l.",
    "wof:placetype":"venue"
},
  "geometry": {"coordinates":[-7.8528690338,42.3383712769],"type":"Point"}
}