{
  "type": "Feature",
  "properties": {
    "addr:full":"Calle de Santa Teresa De Jesus, 20 Oviedo Asturias 33005",
    "addr:housenumber":"20",
    "addr:postcode":"33005",
    "addr:street":"Calle De Santa Teresa De Jesus",
    "iso:country":"ES",
    "sg:address":"Calle de Santa Teresa De Jesus, 20",
    "sg:city":"Oviedo",
    "sg:orig_category":"Caf\u00c9s, Bares, Cervecer\u00cdas",
    "sg:phone":"+34 985 24 06 66",
    "sg:postcode":"33005",
    "sg:province":"Asturias",
    "wof:name":"Telefonos Publicos",
    "wof:placetype":"venue"
},
  "geometry": {"coordinates":[-5.8535599709,43.3608512878],"type":"Point"}
}