{
  "type": "Feature",
  "properties": {
    "addr:full":"Avda Santa Barbara, 23 Toledo Toledo 45006",
    "addr:housenumber":"23",
    "addr:postcode":"45006",
    "addr:street":"Avda Santa Barbara",
    "iso:country":"ES",
    "sg:address":"Avda Santa Barbara, 23",
    "sg:city":"Toledo",
    "sg:orig_category":"Guarder\u00cdas",
    "sg:phone":"+34 925 22 14 25",
    "sg:postcode":"45006",
    "sg:province":"Toledo",
    "wof:name":"Guarderia Infantil Laboral Santa Barbara",
    "wof:placetype":"venue"
},
  "geometry": {"coordinates":[-4.005212307,39.859703064],"type":"Point"}
}