{
  "type": "Feature",
  "properties": {
    "addr:full":"Avda Santa Mari\u00d1a, S/n Redondela Pontevedra 36800",
    "addr:housenumber":"s / n",
    "addr:postcode":"36800",
    "addr:street":"Avda Santa Marin\u0303A",
    "iso:country":"ES",
    "sg:address":"Avda Santa Mari\u00d1a, S/n",
    "sg:city":"Redondela",
    "sg:orig_category":"Refiner\u00cdas De Petr\u00d3leo",
    "sg:phone":"+34 986 40 19 64",
    "sg:postcode":"36800",
    "sg:province":"Pontevedra",
    "wof:name":"Hevago S.a.",
    "wof:placetype":"venue"
},
  "geometry": {"coordinates":[-8.6076574326,42.2913208008],"type":"Point"}
}