{
  "type": "Feature",
  "properties": {
    "addr:full":"Avda Antonio Mairena, 48 Alcala Guadaira Sevilla 41500",
    "addr:housenumber":"48",
    "addr:postcode":"41500",
    "addr:street":"Avda Antonio Mairena",
    "iso:country":"ES",
    "sg:address":"Avda Antonio Mairena, 48",
    "sg:city":"Alcala Guadaira",
    "sg:orig_category":"Inform\u00c1tica, Ofim\u00c1tica (estudios, Asesor\u00cda, Ingenier\u00cda, Formaci\u00d3n)",
    "sg:phone":"+34 955 62 03 14",
    "sg:postcode":"41500",
    "sg:province":"Sevilla",
    "sg:website":"www.red-util.com",
    "wof:name":"Red-util S.c.a",
    "wof:placetype":"venue"
},
  "geometry": {"coordinates":[-5.8380451202,37.3390731812],"type":"Point"}
}