{
  "type": "Feature",
  "properties": {
    "iso:country":"ES",
    "sg:address":"Avda Industria (de La), 35",
    "sg:city":"Tres Cantos",
    "sg:orig_category":"Centros Empresariales",
    "sg:phone":"+34 918 03 05 54",
    "sg:postcode":"28760",
    "sg:province":"Madrid",
    "wof:name":"Iberassets Portfolio Sl",
    "wof:placetype":"venue"
},
  "geometry": {"coordinates":[-3.7019031048,40.6139602661],"type":"Point"}
}