{
  "type": "Feature",
  "properties": {
    "iso:country":"ES",
    "sg:address":"Calle de Comercio (el), 5",
    "sg:city":"Cogolludo",
    "sg:orig_category":"Quincaller\u00cda (al Por Menor)",
    "sg:phone":"+34 949 85 50 31",
    "sg:postcode":"19230",
    "sg:province":"Guadalajara",
    "wof:name":"Moreno Calvo Jose Carlos",
    "wof:placetype":"venue"
},
  "geometry": {"coordinates":[-3.088820219,40.9475364685],"type":"Point"}
}