{
  "type": "Feature",
  "properties": {
    "addr:full":"Avda Nueve De Octubre, 57 Puerto Valencia 46520",
    "addr:housenumber":"57",
    "addr:postcode":"46520",
    "addr:street":"Avda Nueve De Octubre",
    "iso:country":"ES",
    "sg:address":"Avda Nueve De Octubre, 57",
    "sg:city":"Puerto",
    "sg:orig_category":"Farmacias",
    "sg:phone":"+34 962 67 02 26",
    "sg:postcode":"46520",
    "sg:province":"Valencia",
    "wof:name":"Gimeno Oriola Daniel",
    "wof:placetype":"venue"
},
  "geometry": {"coordinates":[-0.2276879996,39.6622047424],"type":"Point"}
}