{
  "type": "Feature",
  "properties": {
    "addr:full":"Avda Castilla (de), 1 Poligono De San Fernando De Henares Madrid 28830",
    "addr:housenumber":"1",
    "addr:postcode":"28830",
    "addr:street":"Avda Castilla De",
    "iso:country":"ES",
    "sg:address":"Avda Castilla (de), 1",
    "sg:city":"Poligono De San Fernando De Henares",
    "sg:orig_category":"Servicios Gsm",
    "sg:phone":"+34 916 76 05 44",
    "sg:postcode":"28830",
    "sg:province":"Madrid",
    "wof:name":"Teleservice International S.a.",
    "wof:placetype":"venue"
},
  "geometry": {"coordinates":[-3.5086710453,40.4529304504],"type":"Point"}
}