{
  "type": "Feature",
  "properties": {
    "addr:full":"Calle de Fuerteventura, S/n Puerto Rico Las Palmas 35130",
    "addr:housenumber":"s / n",
    "addr:postcode":"35130",
    "addr:street":"Calle De Fuerteventura;Rico",
    "iso:country":"ES",
    "sg:address":"Calle de Fuerteventura, S/n",
    "sg:city":"Puerto Rico",
    "sg:orig_category":"Administradores De Bienes Y Delegados De Comunidades De Propietarios",
    "sg:phone":"+34 928 15 31 43",
    "sg:postcode":"35130",
    "sg:province":"Las Palmas",
    "wof:name":"Sunatur Canarias S.l.",
    "wof:placetype":"venue"
},
  "geometry": {"coordinates":[-15.7098083496,27.7861938477],"type":"Point"}
}