{
  "type": "Feature",
  "properties": {
    "addr:full":"Calle de Rubio (el), 8 Benacazon Sevilla 41805",
    "addr:housenumber":"8",
    "addr:postcode":"41805",
    "addr:street":"Calle De Rubio El",
    "iso:country":"ES",
    "sg:address":"Calle de Rubio (el), 8",
    "sg:city":"Benacazon",
    "sg:orig_category":"Laboratorios Y Trabajos De Fotograf\u00cda, V\u00cddeo Y Cine",
    "sg:phone":"+34 955 70 62 68",
    "sg:postcode":"41805",
    "sg:province":"Sevilla",
    "wof:name":"Soriano Sanchez Jose Manuel",
    "wof:placetype":"venue"
},
  "geometry": {"coordinates":[-6.1976203918,37.3529090881],"type":"Point"}
}