{
  "type": "Feature",
  "properties": {
    "addr:full":"Calle de San Prudencio, 31 Vitoria-gasteiz \u00c1lava 01005",
    "addr:housenumber":"31",
    "addr:postcode":"01005",
    "addr:street":"Calle De San Prudencio",
    "iso:country":"ES",
    "sg:address":"Calle de San Prudencio, 31",
    "sg:city":"Vitoria-gasteiz",
    "sg:orig_category":"M\u00c9dicos: Foniatr\u00cda Y Logopedia",
    "sg:phone":"+34 945 14 89 20",
    "sg:postcode":"01005",
    "sg:province":"\u00c1lava",
    "wof:name":"Alvarez Zubizarreta Carmen",
    "wof:placetype":"venue"
},
  "geometry": {"coordinates":[-2.6704800129,42.8438911438],"type":"Point"}
}