{
  "type": "Feature",
  "properties": {
    "iso:country":"ES",
    "sg:address":"Calle de San Juan, 2",
    "sg:city":"Alquerias",
    "sg:orig_category":"Peluquer\u00cdas, Peluquer\u00cda Mixta",
    "sg:phone":"+34 968 87 01 20",
    "sg:postcode":"30580",
    "sg:province":"Murcia",
    "wof:name":"Estefania Lopez Pagan Y Otra C.b.",
    "wof:placetype":"venue"
},
  "geometry": {"coordinates":[-1.0383820534,38.0156669617],"type":"Point"}
}