{
  "type": "Feature",
  "properties": {
    "iso:country":"ES",
    "sg:address":"C/ Pintor Marsa, 22",
    "sg:city":"Tarrega",
    "sg:orig_category":"M\u00c9dicos: Estomatolog\u00cda",
    "sg:phone":"+34 973 31 13 04",
    "sg:postcode":"25300",
    "sg:province":"Lleida",
    "wof:name":"Perez Vargas Juan Elias",
    "wof:placetype":"venue"
},
  "geometry": {"coordinates":[1.1472599506,41.6433181763],"type":"Point"}
}