{
  "type": "Feature",
  "properties": {
    "iso:country":"ES",
    "sg:address":"Carrer de Molinot, 21",
    "sg:city":"Castelldefels",
    "sg:orig_category":"Arquitectos",
    "sg:phone":"+34 936 34 23 98",
    "sg:postcode":"08860",
    "sg:province":"Barcelona",
    "wof:name":"Espacio Plano, Sl.",
    "wof:placetype":"venue"
},
  "geometry": {"coordinates":[1.9759999514,41.2747917175],"type":"Point"}
}