{
  "type": "Feature",
  "properties": {
    "iso:country":"ES",
    "sg:address":"Av Maresme, 9",
    "sg:city":"S. Cebria Vallalta",
    "sg:orig_category":"Transportes De Material De Construcci\u00d3n",
    "sg:phone":"+34 937 63 13 21",
    "sg:postcode":"08396",
    "sg:province":"Barcelona",
    "wof:name":"Ruscalleda S.a.",
    "wof:placetype":"venue"
},
  "geometry": {"coordinates":[2.6146900654,41.6515693665],"type":"Point"}
}