{
  "type": "Feature",
  "properties": {
    "addr:full":"Avda Arcangel (del), S/n Cordoba C\u00f3rdoba 14010",
    "addr:housenumber":"/ n",
    "addr:postcode":"14010",
    "addr:street":"Avda Arcangel Del S;Co\u0301Rdoba",
    "iso:country":"ES",
    "sg:address":"Avda Arcangel (del), S/n",
    "sg:city":"Cordoba",
    "sg:orig_category":"Ropa Para Ni\u00d1os (al Por Menor)",
    "sg:phone":"+34 957 75 22 29",
    "sg:postcode":"14010",
    "sg:province":"C\u00f3rdoba",
    "wof:name":"Jimenez Jurado Jose",
    "wof:placetype":"venue"
},
  "geometry": {"coordinates":[-4.7656240463,37.8785896301],"type":"Point"}
}