{
  "type": "Feature",
  "properties": {
    "iso:country":"ES",
    "sg:address":"Calle de Juan Carlos I, 124",
    "sg:city":"Alhaurin Torre",
    "sg:orig_category":"Empresas De Demolici\u00d3n",
    "sg:phone":"+34 952 41 20 82",
    "sg:postcode":"29130",
    "sg:province":"M\u00e1laga",
    "wof:name":"Garran Alvarez Jesus",
    "wof:placetype":"venue"
},
  "geometry": {"coordinates":[-4.5667190552,36.6618614197],"type":"Point"}
}