{
  "type": "Feature",
  "properties": {
    "addr:full":"Carrer de Trossets (dels), 38 Gata Gorgos Alicante 03740",
    "addr:housenumber":"38",
    "addr:postcode":"03740",
    "addr:street":"Carrer De Trossets Dels",
    "iso:country":"ES",
    "sg:address":"Carrer de Trossets (dels), 38",
    "sg:city":"Gata Gorgos",
    "sg:orig_category":"Confecci\u00d3n (fabricaci\u00d3n, Al Por Mayor)",
    "sg:phone":"+34 965 75 69 63",
    "sg:postcode":"03740",
    "sg:province":"Alicante",
    "wof:name":"Vifercher S.l.",
    "wof:placetype":"venue"
},
  "geometry": {"coordinates":[0.083025001,38.7773742676],"type":"Point"}
}