{
  "type": "Feature",
  "properties": {
    "addr:full":"Av Josep Trias, 14 Ca'n Picafort Islas Baleares 07458",
    "addr:housenumber":"14",
    "addr:postcode":"07458",
    "addr:street":"Av Josep Trias",
    "iso:country":"ES",
    "sg:address":"Av Josep Trias, 14",
    "sg:city":"Ca'n Picafort",
    "sg:orig_category":"Discotecas Y Salas De Baile",
    "sg:phone":"+34 971 85 04 09",
    "sg:postcode":"07458",
    "sg:province":"Islas Baleares",
    "wof:name":"Skau S. A.",
    "wof:placetype":"venue"
},
  "geometry": {"coordinates":[2.9117100239,39.6136398315],"type":"Point"}
}