{
  "type": "Feature",
  "properties": {
    "addr:full":"Guillermo Reina, 74 Huercal-overa Almer\u00eda 04600",
    "addr:housenumber":"74",
    "addr:postcode":"04600",
    "addr:street":"Guillermo Reina;Almeri\u0301A",
    "iso:country":"ES",
    "sg:address":"Guillermo Reina, 74",
    "sg:city":"Huercal-overa",
    "sg:orig_category":"Agentes, Concesionarios Y Sucursales De Veh\u00cdculos",
    "sg:phone":"+34 950 47 05 40",
    "sg:postcode":"04600",
    "sg:province":"Almer\u00eda",
    "wof:name":"Tomas Vilar Parra S.l.",
    "wof:placetype":"venue"
},
  "geometry": {"coordinates":[-1.9402029514,37.3980674744],"type":"Point"}
}