{
  "type": "Feature",
  "properties": {
    "iso:country":"ES",
    "sg:address":"Rond Barcelona, 61",
    "sg:city":"Figueres",
    "sg:orig_category":"Zapatos (al Por Menor)",
    "sg:phone":"+34 972 67 15 53",
    "sg:postcode":"17600",
    "sg:province":"Girona",
    "wof:name":"Merkal Calzados S.l.",
    "wof:placetype":"venue"
},
  "geometry": {"coordinates":[2.961977005,42.2584724426],"type":"Point"}
}