{
  "type": "Feature",
  "properties": {
    "iso:country":"ES",
    "sg:address":"Plaz Espa\u00d1a, 10",
    "sg:city":"Madrid",
    "sg:orig_category":"Agentes Generales De Seguros",
    "sg:phone":"+34 915 40 18 00",
    "sg:postcode":"28008",
    "sg:province":"Madrid",
    "sg:website":"www.mediadoresdesegurosdemadrid.com",
    "wof:name":"Colegio De Mediadores De Seguros Titulados De Madrid",
    "wof:placetype":"venue"
},
  "geometry": {"coordinates":[-3.7135639191,40.4219245911],"type":"Point"}
}