{
  "type": "Feature",
  "properties": {
    "addr:full":"Pi\u00f1eiral, 26 Ourense Ourense 32005",
    "addr:housenumber":"26",
    "addr:postcode":"32005",
    "addr:street":"Pin\u0303Eiral",
    "iso:country":"ES",
    "sg:address":"Pi\u00f1eiral, 26",
    "sg:city":"Ourense",
    "sg:orig_category":"Trabajos De Revestimiento De Fachadas",
    "sg:phone":"+34 988 23 87 17",
    "sg:postcode":"32005",
    "sg:province":"Ourense",
    "wof:name":"Enlucidos Bardanca S.l.l",
    "wof:placetype":"venue"
},
  "geometry": {"coordinates":[-7.8519001007,42.3053703308],"type":"Point"}
}