{
  "type": "Feature",
  "properties": {
    "addr:full":"Calle de Delicias, 3 Zaragoza Zaragoza 50017",
    "addr:housenumber":"3",
    "addr:postcode":"50017",
    "addr:street":"Calle De Delicias",
    "iso:country":"ES",
    "sg:address":"Calle de Delicias, 3",
    "sg:city":"Zaragoza",
    "sg:orig_category":"Marroquiner\u00cda (confecci\u00d3n)",
    "sg:phone":"+34 976 30 05 57",
    "sg:postcode":"50017",
    "sg:province":"Zaragoza",
    "wof:name":"Artola Jaques Victor",
    "wof:placetype":"venue"
},
  "geometry": {"coordinates":[-0.9058653116,41.6526870728],"type":"Point"}
}