{
  "type": "Feature",
  "properties": {
    "addr:full":"Calle de Nueve De Mayo, 26 Oviedo Asturias 33002",
    "addr:housenumber":"26",
    "addr:postcode":"33002",
    "addr:street":"Calle De Nueve De Mayo",
    "iso:country":"ES",
    "sg:address":"Calle de Nueve De Mayo, 26",
    "sg:city":"Oviedo",
    "sg:orig_category":"M\u00c9dicos: Estomatolog\u00cda",
    "sg:phone":"+34 985 21 23 43",
    "sg:postcode":"33002",
    "sg:province":"Asturias",
    "wof:name":"Montes Arboleya Luis Miguel",
    "wof:placetype":"venue"
},
  "geometry": {"coordinates":[-5.8516325951,43.3662223816],"type":"Point"}
}