{
  "type": "Feature",
  "properties": {
    "iso:country":"ES",
    "sg:address":"Carrer de Progres, 77",
    "sg:city":"Hospitalet Llobregat",
    "sg:orig_category":"M\u00c9dicos: Medicina General Orientada A La Acupuntura",
    "sg:phone":"+34 933 33 81 99",
    "sg:postcode":"08903",
    "sg:province":"Barcelona",
    "wof:name":"Costa Riba Rosa",
    "wof:placetype":"venue"
},
  "geometry": {"coordinates":[2.120882988,41.3725852966],"type":"Point"}
}