{
  "type": "Feature",
  "properties": {
    "iso:country":"ES",
    "sg:address":"Rond General Mitre, 148",
    "sg:city":"Barcelona",
    "sg:orig_category":"Arquitectos",
    "sg:phone":"+34 934 14 03 55",
    "sg:postcode":"08006",
    "sg:province":"Barcelona",
    "wof:name":"Cunill Crespiera Jorge",
    "wof:placetype":"venue"
},
  "geometry": {"coordinates":[2.1391839981,41.4036178589],"type":"Point"}
}