{
  "type": "Feature",
  "properties": {
    "addr:full":"Calle de Don Pedro De Luna, 63 Zaragoza Zaragoza 50010",
    "addr:housenumber":"63",
    "addr:postcode":"50010",
    "addr:street":"Calle De Don Pedro De Luna",
    "iso:country":"ES",
    "sg:address":"Calle de Don Pedro De Luna, 63",
    "sg:city":"Zaragoza",
    "sg:orig_category":"Peluqueros: De Se\u00d1oras",
    "sg:phone":"+34 976 31 65 99",
    "sg:postcode":"50010",
    "sg:province":"Zaragoza",
    "wof:name":"Garicano Moreno Flora Pilar",
    "wof:placetype":"venue"
},
  "geometry": {"coordinates":[-0.9038711786,41.6497459412],"type":"Point"}
}