{
  "type": "Feature",
  "properties": {
    "addr:full":"Pol Ind La Vaquera, S/n Hornachuelos C\u00f3rdoba 14740",
    "addr:housenumber":"/ n",
    "addr:postcode":"14740",
    "addr:street":"Vaquera S",
    "iso:country":"ES",
    "sg:address":"Pol Ind La Vaquera, S/n",
    "sg:city":"Hornachuelos",
    "sg:orig_category":"Negocio De Materiales De Construcci\u00d3n",
    "sg:phone":"+34 957 64 00 85",
    "sg:postcode":"14740",
    "sg:province":"C\u00f3rdoba",
    "wof:name":"Gonzalez Vazquez Enrique",
    "wof:placetype":"venue"
},
  "geometry": {"coordinates":[-5.2428050041,37.8309288025],"type":"Point"}
}