{
  "type": "Feature",
  "properties": {
    "iso:country":"ES",
    "sg:address":"Calle de Manuel Iradier, 9",
    "sg:city":"Vitoria-gasteiz",
    "sg:orig_category":"Peluqueros: De Se\u00d1oras",
    "sg:phone":"+34 945 13 80 80",
    "sg:postcode":"01005",
    "sg:province":"\u00c1lava",
    "wof:name":"Espinosa Caballero Maria Carmen",
    "wof:placetype":"venue"
},
  "geometry": {"coordinates":[-2.6746680737,42.8426208496],"type":"Point"}
}