{
  "type": "Feature",
  "properties": {
    "iso:country":"ES",
    "sg:address":"Juan Giner, 13",
    "sg:city":"Morella",
    "sg:orig_category":"Abogados",
    "sg:phone":"+34 964 16 01 03",
    "sg:postcode":"12300",
    "sg:province":"Castell\u00f3n",
    "wof:name":"Fabregat Advocats I Serveis Empresarials S.l.",
    "wof:placetype":"venue"
},
  "geometry": {"coordinates":[-0.0995099992,40.62059021],"type":"Point"}
}