{
  "type": "Feature",
  "properties": {
    "addr:full":"Calle de San Sebastian, 19 Moron Frontera Sevilla 41530",
    "addr:housenumber":"19",
    "addr:postcode":"41530",
    "addr:street":"Calle De San Sebastian",
    "iso:country":"ES",
    "sg:address":"Calle de San Sebastian, 19",
    "sg:city":"Moron Frontera",
    "sg:orig_category":"Centros De Coordinaci\u00d3n",
    "sg:phone":"+34 954 85 01 75",
    "sg:postcode":"41530",
    "sg:province":"Sevilla",
    "wof:name":"Montes Sancho Eduardo",
    "wof:placetype":"venue"
},
  "geometry": {"coordinates":[-5.4528231621,37.1294212341],"type":"Point"}
}