{
  "type": "Feature",
  "properties": {
    "iso:country":"ES",
    "sg:address":"Calle de Viaducto Marquina, 3",
    "sg:city":"Oviedo",
    "sg:orig_category":"Armas Y Municiones (fabricaci\u00d3n, Al Por Mayor)",
    "sg:phone":"+34 984 28 01 35",
    "sg:postcode":"33004",
    "sg:province":"Asturias",
    "wof:name":"El Pescador C.b.",
    "wof:placetype":"venue"
},
  "geometry": {"coordinates":[-5.8550071716,43.3656730652],"type":"Point"}
}