{
  "type": "Feature",
  "properties": {
    "iso:country":"ES",
    "sg:address":"Calle de Fray Julian Garces, 23",
    "sg:city":"Zaragoza",
    "sg:orig_category":"Enfermeras: Consultas, Atenci\u00d3n A Domicilio",
    "sg:phone":"+34 976 25 17 13",
    "sg:postcode":"50007",
    "sg:province":"Zaragoza",
    "wof:name":"Villa Isla Alejandro",
    "wof:placetype":"venue"
},
  "geometry": {"coordinates":[-0.886548996,41.6307754517],"type":"Point"}
}