{
  "type": "Feature",
  "properties": {
    "iso:country":"ES",
    "sg:address":"Av La Marina, 2",
    "sg:city":"Benissa",
    "sg:orig_category":"Inmobiliaria (alquileres Por Temporada Y Temporales)",
    "sg:phone":"+34 965 74 77 03",
    "sg:postcode":"03720",
    "sg:province":"Alicante",
    "wof:name":"Ideal Villas S.l.",
    "wof:placetype":"venue"
},
  "geometry": {"coordinates":[0.0841030031,38.6644058228],"type":"Point"}
}