{
  "type": "Feature",
  "properties": {
    "addr:full":"Calle de Paz (la), 1 Gador Almer\u00eda 04560",
    "addr:housenumber":"1",
    "addr:postcode":"04560",
    "addr:street":"Calle De Paz La;Almeri\u0301A",
    "iso:country":"ES",
    "sg:address":"Calle de Paz (la), 1",
    "sg:city":"Gador",
    "sg:orig_category":"Reposter\u00cdas",
    "sg:phone":"+34 950 64 51 13",
    "sg:postcode":"04560",
    "sg:province":"Almer\u00eda",
    "wof:name":"Panaderia El Valle Del Andarax S.l.",
    "wof:placetype":"venue"
},
  "geometry": {"coordinates":[-2.4912369251,36.9528274536],"type":"Point"}
}