{
  "type": "Feature",
  "properties": {
    "iso:country":"ES",
    "sg:address":"Avda Generalisimo, 31",
    "sg:city":"Puerto Cruz",
    "sg:orig_category":"Agencias De Viajes",
    "sg:phone":"+34 922 38 26 25",
    "sg:postcode":"38400",
    "sg:province":"Santa Cruz De Tenerife",
    "wof:name":"Johannes Weingand Robert",
    "wof:placetype":"venue"
},
  "geometry": {"coordinates":[-16.5473842621,28.4141807556],"type":"Point"}
}