{
  "type": "Feature",
  "properties": {
    "iso:country":"ES",
    "sg:address":"Carrer de Bordeus, 1",
    "sg:city":"Barcelona",
    "sg:orig_category":"Droguer\u00cdas (al Por Menor)",
    "sg:phone":"+34 934 30 67 50",
    "sg:postcode":"08029",
    "sg:province":"Barcelona",
    "wof:name":"Feixas Farre Miguel",
    "wof:placetype":"venue"
},
  "geometry": {"coordinates":[2.1419830322,41.3881263733],"type":"Point"}
}