{
  "type": "Feature",
  "properties": {
    "addr:full":"Avda Pino, 53 Pinar De Campoverde Alicante 03191",
    "addr:housenumber":"53",
    "addr:postcode":"03191",
    "addr:street":"Avda Pino",
    "iso:country":"ES",
    "sg:address":"Avda Pino, 53",
    "sg:city":"Pinar De Campoverde",
    "sg:orig_category":"Plomeros",
    "sg:phone":"+34 966 76 28 06",
    "sg:postcode":"03191",
    "sg:province":"Alicante",
    "wof:name":"Pagan Belmonte Juan Antonio",
    "wof:placetype":"venue"
},
  "geometry": {"coordinates":[-0.8423410058,37.90965271],"type":"Point"}
}