{
  "type": "Feature",
  "properties": {
    "addr:full":"Sect Descubridores, 17 Tres Cantos Madrid 28760",
    "addr:housenumber":"17",
    "addr:postcode":"28760",
    "addr:street":"Sect Descubridores",
    "iso:country":"ES",
    "sg:address":"Sect Descubridores, 17",
    "sg:city":"Tres Cantos",
    "sg:orig_category":"\u00d3ptica: Instrumentos (fabricaci\u00d3n)",
    "sg:phone":"+34 918 03 02 73",
    "sg:postcode":"28760",
    "sg:province":"Madrid",
    "wof:name":"Sanchez Mosquete Angel Nicolas",
    "wof:placetype":"venue"
},
  "geometry": {"coordinates":[-3.714662075,40.6101837158],"type":"Point"}
}