{
  "type": "Feature",
  "properties": {
    "iso:country":"ES",
    "sg:address":"Avda Mediterraneo, 66",
    "sg:city":"Benidorm",
    "sg:orig_category":"Art\u00cdculos De Regalo (al Por Menor)",
    "sg:phone":"+34 965 85 29 67",
    "sg:postcode":"03500",
    "sg:province":"Alicante",
    "wof:name":"Catala Simo Fernando",
    "wof:placetype":"venue"
},
  "geometry": {"coordinates":[-0.1078770012,38.5347251892],"type":"Point"}
}