{
  "type": "Feature",
  "properties": {
    "addr:full":"Calle de Conde Duque, 19 Madrid Madrid 28015",
    "addr:housenumber":"19",
    "addr:postcode":"madrid;28015",
    "addr:street":"Calle De Conde Duque",
    "iso:country":"ES",
    "sg:address":"Calle de Conde Duque, 19",
    "sg:city":"Madrid",
    "sg:orig_category":"Florister\u00cdas",
    "sg:phone":"+34 915 59 54 34",
    "sg:postcode":"28015",
    "sg:province":"Madrid",
    "wof:name":"Guajardo Sierra Cristina",
    "wof:placetype":"venue"
},
  "geometry": {"coordinates":[-3.7091524601,40.4294166565],"type":"Point"}
}