{
  "type": "Feature",
  "properties": {
    "iso:country":"ES",
    "sg:address":"Calle de Avila, 11",
    "sg:city":"Caceres",
    "sg:orig_category":"Ense\u00d1anza: Idiomas",
    "sg:phone":"+34 927 23 73 82",
    "sg:postcode":"10005",
    "sg:province":"C\u00e1ceres",
    "wof:name":"Venema  Becki",
    "wof:placetype":"venue"
},
  "geometry": {"coordinates":[-6.3803391457,39.4582901001],"type":"Point"}
}