{
  "type": "Feature",
  "properties": {
    "addr:full":"Calle de Padre Marcellan Mayayo, 6 Zaragoza Zaragoza 50015",
    "addr:housenumber":"6",
    "addr:postcode":"50015",
    "addr:street":"Calle De Padre Marcellan Mayayo",
    "iso:country":"ES",
    "sg:address":"Calle de Padre Marcellan Mayayo, 6",
    "sg:city":"Zaragoza",
    "sg:orig_category":"Metales (labores, Pulido)",
    "sg:phone":"+34 976 74 11 47",
    "sg:postcode":"50015",
    "sg:province":"Zaragoza",
    "wof:name":"Frances Jurado Mercedes",
    "wof:placetype":"venue"
},
  "geometry": {"coordinates":[-0.8629540205,41.6912841797],"type":"Point"}
}