{
  "type": "Feature",
  "properties": {
    "addr:full":"Calle de Eduardo Marquina, 39 Madrid Madrid 28019",
    "addr:housenumber":"39",
    "addr:postcode":"madrid;28019",
    "addr:street":"Calle De Eduardo Marquina",
    "iso:country":"ES",
    "sg:address":"Calle de Eduardo Marquina, 39",
    "sg:city":"Madrid",
    "sg:orig_category":"Empresas De Carpinter\u00cda De Madera",
    "sg:phone":"+34 914 69 22 54",
    "sg:postcode":"28019",
    "sg:province":"Madrid",
    "wof:name":"Dobarro Garcia Jose Mario",
    "wof:placetype":"venue"
},
  "geometry": {"coordinates":[-3.7094271183,40.3920898438],"type":"Point"}
}