{
  "type": "Feature",
  "properties": {
    "iso:country":"ES",
    "sg:address":"Bo. Palmeral, 26",
    "sg:city":"Callosa Segura",
    "sg:orig_category":"Muebles, Minoristas",
    "sg:phone":"+34 966 75 81 78",
    "sg:postcode":"03360",
    "sg:province":"Alicante",
    "wof:name":"Cajoneras Jopa S.l.",
    "wof:placetype":"venue"
},
  "geometry": {"coordinates":[-0.8776689768,38.1256752014],"type":"Point"}
}