{
  "type": "Feature",
  "properties": {
    "addr:full":"Calle de Corredera Hernando De Soto, 20 Jerez De Los Caballeros Badajoz 06380",
    "addr:housenumber":"20",
    "addr:postcode":"06380",
    "addr:street":"Calle De Corredera Hernando De Soto",
    "iso:country":"ES",
    "sg:address":"Calle de Corredera Hernando De Soto, 20",
    "sg:city":"Jerez De Los Caballeros",
    "sg:orig_category":"Iglesia Cat\u00d3lica",
    "sg:phone":"+34 924 73 14 59",
    "sg:postcode":"06380",
    "sg:province":"Badajoz",
    "wof:name":"Parroquia De San Miguel Arcangel",
    "wof:placetype":"venue"
},
  "geometry": {"coordinates":[-6.7671136856,38.3226470947],"type":"Point"}
}