{
  "type": "Feature",
  "properties": {
    "addr:full":"Calle de Mallorca, 5 Denia Alicante 03700",
    "addr:housenumber":"5",
    "addr:postcode":"03700",
    "addr:street":"Calle De Mallorca",
    "iso:country":"ES",
    "sg:address":"Calle de Mallorca, 5",
    "sg:city":"Denia",
    "sg:orig_category":"Electricidad: Instaladores",
    "sg:phone":"+34 966 42 28 21",
    "sg:postcode":"03700",
    "sg:province":"Alicante",
    "wof:name":"Instalaciones Mi-ser S.l.",
    "wof:placetype":"venue"
},
  "geometry": {"coordinates":[0.1001589969,38.8391227722],"type":"Point"}
}