{
  "type": "Feature",
  "properties": {
    "addr:full":"Rua Progreso (do), 131 Ourense Ourense 32003",
    "addr:housenumber":"131",
    "addr:postcode":"32003",
    "addr:street":"Rua Progreso Do",
    "iso:country":"ES",
    "sg:address":"Rua Progreso (do), 131",
    "sg:city":"Ourense",
    "sg:orig_category":"Abogados",
    "sg:phone":"+34 988 21 37 04",
    "sg:postcode":"32003",
    "sg:province":"Ourense",
    "wof:name":"Sotelo Novoa Eloy",
    "wof:placetype":"venue"
},
  "geometry": {"coordinates":[-7.8673801422,42.341129303],"type":"Point"}
}