{
  "type": "Feature",
  "properties": {
    "addr:full":"Calle de Gran Via, 7 Cehegin Murcia 30430",
    "addr:postcode":"30430",
    "addr:street":"Calle De Gran Via 7",
    "iso:country":"ES",
    "sg:address":"Calle de Gran Via, 7",
    "sg:city":"Cehegin",
    "sg:orig_category":"Muebles, Minoristas",
    "sg:phone":"+34 968 74 08 48",
    "sg:postcode":"30430",
    "sg:province":"Murcia",
    "wof:name":"Muebles Cehegin S.l.",
    "wof:placetype":"venue"
},
  "geometry": {"coordinates":[-1.7977739573,38.0934715271],"type":"Point"}
}