{
  "type": "Feature",
  "properties": {
    "iso:country":"ES",
    "sg:address":"Calle de Asturias, 20",
    "sg:city":"Gijon",
    "sg:orig_category":"Bancos",
    "sg:phone":"+34 985 17 58 16",
    "sg:postcode":"33206",
    "sg:province":"Asturias",
    "wof:name":"Barclays Bank S.a.e.",
    "wof:placetype":"venue"
},
  "geometry": {"coordinates":[-5.6657261848,43.5396957397],"type":"Point"}
}