{
  "type": "Feature",
  "properties": {
    "addr:full":"Calle de Antonio Lopez, 249 Madrid Madrid 28041",
    "addr:housenumber":"249",
    "addr:postcode":"28041",
    "addr:street":"Calle De Antonio Lopez",
    "iso:country":"ES",
    "sg:address":"Calle de Antonio Lopez, 249",
    "sg:city":"Madrid",
    "sg:orig_category":"Inform\u00c1tica (estudios, Servicios, Asesor\u00cda, Formaci\u00d3n)",
    "sg:phone":"+34 913 92 01 67",
    "sg:postcode":"28041",
    "sg:province":"Madrid",
    "wof:name":"Syase S.coop.",
    "wof:placetype":"venue"
},
  "geometry": {"coordinates":[-3.6934494972,40.3782348633],"type":"Point"}
}