{
  "type": "Feature",
  "properties": {
    "addr:full":"Avda Libertad (la), 23 Mairena Aljarafe Sevilla 41927",
    "addr:housenumber":"23",
    "addr:postcode":"41927",
    "addr:street":"Avda Libertad La",
    "iso:country":"ES",
    "sg:address":"Avda Libertad (la), 23",
    "sg:city":"Mairena Aljarafe",
    "sg:orig_category":"Cine (producci\u00d3n, Realizaci\u00d3n)",
    "sg:phone":"+34 954 18 82 52",
    "sg:postcode":"41927",
    "sg:province":"Sevilla",
    "wof:name":"Tonison S.l.",
    "wof:placetype":"venue"
},
  "geometry": {"coordinates":[-6.0622639656,37.3445854187],"type":"Point"}
}