{
  "type": "Feature",
  "properties": {
    "iso:country":"ES",
    "sg:address":"Calle de Serrablo (de), 19",
    "sg:city":"Sabi\u00f1anigo",
    "sg:orig_category":"Arreglo, Reparaci\u00d3n, Piezas Sueltas De Televisi\u00d3n, V\u00cddeo, Hi",
    "sg:phone":"+34 974 48 22 23",
    "sg:postcode":"22600",
    "sg:province":"Huesca",
    "wof:name":"Perez Mange Crescencio Antonio",
    "wof:placetype":"venue"
},
  "geometry": {"coordinates":[-0.3699310124,42.519115448],"type":"Point"}
}