{
  "type": "Feature",
  "properties": {
    "iso:country":"ES",
    "sg:address":"Rbla Granja, 8",
    "sg:city":"Molins Rei",
    "sg:orig_category":"Ingeniero",
    "sg:phone":"+34 936 68 44 28",
    "sg:postcode":"08750",
    "sg:province":"Barcelona",
    "wof:name":"Comunidad De Propietarios Rambla Granja 8",
    "wof:placetype":"venue"
},
  "geometry": {"coordinates":[2.013021946,41.4156532288],"type":"Point"}
}