{
  "type": "Feature",
  "properties": {
    "addr:full":"Ptge Marimon, 21 Barcelona Barcelona 08021",
    "addr:housenumber":"21",
    "addr:postcode":"08021",
    "addr:street":"Ptge Marimon",
    "iso:country":"ES",
    "sg:address":"Ptge Marimon, 21",
    "sg:city":"Barcelona",
    "sg:orig_category":"Agencias Y Agentes Comerciales, Representantes",
    "sg:phone":"+34 932 11 99 55",
    "sg:postcode":"08021",
    "sg:province":"Barcelona",
    "wof:name":"Morera Riera Juan Maria",
    "wof:placetype":"venue"
},
  "geometry": {"coordinates":[2.1478559971,41.3943099976],"type":"Point"}
}