{
  "type": "Feature",
  "properties": {
    "iso:country":"ES",
    "sg:address":"Calle de Juan Xxiii, 48",
    "sg:city":"Alaquas",
    "sg:classifiers":[
        {
            "category":"Manufacturing",
            "subcategory":"Metals",
            "type":"Manufacturing & Wholesale Goods"
        }
    ],
    "sg:phone":"+34 961 51 91 82",
    "sg:postcode":"46970",
    "sg:province":"Valencia",
    "sg:tags":[
        "en",
        "fundiciones"
    ],
    "wof:name":"Fundiciones Arribas S.l.",
    "wof:placetype":"venue"
},
  "geometry": {"coordinates":[-0.4717119932,39.4550437927],"type":"Point"}
}