{
  "type": "Feature",
  "properties": {
    "iso:country":"ES",
    "sg:address":"Central Nuclear Cofrentes, S/n",
    "sg:city":"Cofrentes",
    "sg:orig_category":"Montaje (empresas De)",
    "sg:phone":"+34 962 19 60 72",
    "sg:postcode":"46625",
    "sg:province":"Valencia",
    "wof:name":"Moncobra S.a.",
    "wof:placetype":"venue"
},
  "geometry": {"coordinates":[-1.0591789484,39.2298698425],"type":"Point"}
}