{
  "type": "Feature",
  "properties": {
    "addr:full":"Calle de Merida, 6 Madrid Madrid 28030",
    "addr:housenumber":"6",
    "addr:postcode":"28030",
    "addr:street":"Calle De Merida",
    "iso:country":"ES",
    "sg:address":"Calle de Merida, 6",
    "sg:city":"Madrid",
    "sg:orig_category":"Empresas De Portes Y Mensajer\u00cda",
    "sg:phone":"+34 913 71 27 64",
    "sg:postcode":"28030",
    "sg:province":"Madrid",
    "wof:name":"Castillo Sanchez Faustino",
    "wof:placetype":"venue"
},
  "geometry": {"coordinates":[-3.6368429661,40.4076538086],"type":"Point"}
}