{
  "type": "Feature",
  "properties": {
    "addr:full":"Cami Bara, 16 Roda De Bara Tarragona 43883",
    "addr:housenumber":"16",
    "addr:postcode":"43883",
    "addr:street":"Bara",
    "iso:country":"ES",
    "sg:address":"Cami Bara, 16",
    "sg:city":"Roda De Bara",
    "sg:orig_category":"Producci\u00d3n De Cart\u00d3n",
    "sg:phone":"+34 977 80 35 16",
    "sg:postcode":"43883",
    "sg:province":"Tarragona",
    "wof:name":"Cartonaje Roda S.l.",
    "wof:placetype":"venue"
},
  "geometry": {"coordinates":[1.4701000452,41.1674804688],"type":"Point"}
}