{
  "type": "Feature",
  "properties": {
    "iso:country":"ES",
    "sg:address":"Pl Sant Antoni, 5",
    "sg:city":"Palma",
    "sg:orig_category":"Agencias De Viajes",
    "sg:phone":"+34 971 71 56 03",
    "sg:postcode":"07002",
    "sg:province":"Islas Baleares",
    "wof:name":"Viajes Almudaina S. A.",
    "wof:placetype":"venue"
},
  "geometry": {"coordinates":[2.6557788849,39.5717849731],"type":"Point"}
}