{
  "type": "Feature",
  "properties": {
    "addr:full":"Psaj Valencia, 4 Malaga M\u00e1laga 29001",
    "addr:housenumber":"4",
    "addr:postcode":"29001",
    "addr:street":"Valencia;Ma\u0301Laga",
    "iso:country":"ES",
    "sg:address":"Psaj Valencia, 4",
    "sg:city":"Malaga",
    "sg:orig_category":"Cajas Para Embalar",
    "sg:phone":"+34 952 60 19 99",
    "sg:postcode":"29001",
    "sg:province":"M\u00e1laga",
    "wof:name":"Cajamar",
    "wof:placetype":"venue"
},
  "geometry": {"coordinates":[-4.4247732162,36.7147445679],"type":"Point"}
}