{
  "type": "Feature",
  "properties": {
    "iso:country":"ES",
    "sg:address":"Poli Las Capellanias, S/n",
    "sg:city":"Caceres",
    "sg:orig_category":"Fabricaci\u00d3n, Importaci\u00d3n De L\u00c1mparas Y Bombillas",
    "sg:phone":"+34 927 23 77 14",
    "sg:postcode":"10005",
    "sg:province":"C\u00e1ceres",
    "wof:name":"Camperluz S.l.",
    "wof:placetype":"venue"
},
  "geometry": {"coordinates":[-6.5341739655,39.4675254822],"type":"Point"}
}