{
  "type": "Feature",
  "properties": {
    "iso:country":"ES",
    "sg:address":"Carrer de Indalecio Prieto, 3",
    "sg:city":"Palma",
    "sg:orig_category":"Loter\u00cda Y T\u00d3mbola",
    "sg:phone":"+34 971 24 00 70",
    "sg:postcode":"07008",
    "sg:province":"Islas Baleares",
    "wof:name":"Soriano Lluch Manuela",
    "wof:placetype":"venue"
},
  "geometry": {"coordinates":[2.6692380905,39.5769882202],"type":"Point"}
}