{
  "type": "Feature",
  "properties": {
    "iso:country":"ES",
    "sg:address":"Calle de Cerro De La Alcazaba, 19",
    "sg:city":"Madrid",
    "sg:orig_category":"Aparcamientos (infraestructuras, Accesorios)",
    "sg:phone":"+34 914 78 10 97",
    "sg:postcode":"28053",
    "sg:province":"Madrid",
    "wof:name":"Auxiliar De Cogeneracion S.l.",
    "wof:placetype":"venue"
},
  "geometry": {"coordinates":[-3.6720752716,40.3840560913],"type":"Point"}
}