{
  "type": "Feature",
  "properties": {
    "addr:full":"Calle de Virgen De Africa, 32 Madrid Madrid 28027",
    "addr:housenumber":"32",
    "addr:postcode":"madrid;28027",
    "addr:street":"Calle De Virgen De Africa",
    "iso:country":"ES",
    "sg:address":"Calle de Virgen De Africa, 32",
    "sg:city":"Madrid",
    "sg:orig_category":"Calefacci\u00d3n Central: Material (fabricaci\u00d3n, Al Por Mayor)",
    "sg:phone":"+34 914 03 62 07",
    "sg:postcode":"28027",
    "sg:province":"Madrid",
    "sg:website":"www.ibericadelcalor.com",
    "wof:name":"Iberica Del Calor S.a.",
    "wof:placetype":"venue"
},
  "geometry": {"coordinates":[-3.654419899,40.4389610291],"type":"Point"}
}