{
  "type": "Feature",
  "properties": {
    "iso:country":"ES",
    "sg:address":"Avda Valentin Masip, 14",
    "sg:city":"Oviedo",
    "sg:orig_category":"Florister\u00cdas",
    "sg:phone":"+34 985 23 78 56",
    "sg:postcode":"33013",
    "sg:province":"Asturias",
    "wof:name":"Rosal Menendez Maria Jose Del",
    "wof:placetype":"venue"
},
  "geometry": {"coordinates":[-5.859828949,43.3615951538],"type":"Point"}
}