{
  "type": "Feature",
  "properties": {
    "addr:full":"Barr Poligono De Ria\u00d1o, S/n Langreo Asturias 33900",
    "addr:postcode":"33900",
    "addr:street":"Poligono;Rian\u0303O S / N",
    "iso:country":"ES",
    "sg:address":"Barr Poligono De Ria\u00d1o, S/n",
    "sg:city":"Langreo",
    "sg:orig_category":"Mec\u00c1nico Del Autom\u00d3vil",
    "sg:phone":"+34 985 67 33 05",
    "sg:postcode":"33900",
    "sg:province":"Asturias",
    "wof:name":"Limandi S.l.u.",
    "wof:placetype":"venue"
},
  "geometry": {"coordinates":[-5.6692090034,43.2883987427],"type":"Point"}
}