{
  "type": "Feature",
  "properties": {
    "addr:full":"Crt. Valencia, 52 Motilla Palancar Cuenca 16200",
    "addr:housenumber":"52",
    "addr:postcode":"16200",
    "addr:street":"Valencia",
    "iso:country":"ES",
    "sg:address":"Crt. Valencia, 52",
    "sg:city":"Motilla Palancar",
    "sg:orig_category":"Caf\u00c9s, Bares, Cervecer\u00cdas",
    "sg:phone":"+34 969 33 16 25",
    "sg:postcode":"16200",
    "sg:province":"Cuenca",
    "wof:name":"Mallebrera Martinez Maria Del Pilar",
    "wof:placetype":"venue"
},
  "geometry": {"coordinates":[-1.9062039852,39.5607185364],"type":"Point"}
}