{
  "type": "Feature",
  "properties": {
    "iso:country":"ES",
    "sg:address":"Avda Joaquin Costa, 2",
    "sg:city":"Porcuna",
    "sg:orig_category":"Mec\u00c1nico Del Autom\u00d3vil",
    "sg:phone":"+34 953 54 45 08",
    "sg:postcode":"23790",
    "sg:province":"Ja\u00e9n",
    "wof:name":"Grande Gascon Berenguer",
    "wof:placetype":"venue"
},
  "geometry": {"coordinates":[-4.1805119514,37.872253418],"type":"Point"}
}