{
  "type": "Feature",
  "properties": {
    "iso:country":"ES",
    "sg:address":"Avda Federico Garcia Lorca, 19",
    "sg:city":"Palmas De Gran Canaria",
    "sg:orig_category":"Sociedades, Compa\u00d1\u00cdas Aseguradoras",
    "sg:phone":"+34 928 29 82 73",
    "sg:postcode":"35011",
    "sg:province":"Las Palmas",
    "sg:website":"www.libertyseguros.es",
    "wof:name":"Galvan Jordan Raquel",
    "wof:placetype":"venue"
},
  "geometry": {"coordinates":[-15.4401979446,28.1258659363],"type":"Point"}
}