{
  "type": "Feature",
  "properties": {
    "addr:full":"Avda Acapulco, 15 Fuengirola M\u00e1laga 29640",
    "addr:housenumber":"15",
    "addr:postcode":"29640",
    "addr:street":"Avda Acapulco;Ma\u0301Laga",
    "iso:country":"ES",
    "sg:address":"Avda Acapulco, 15",
    "sg:city":"Fuengirola",
    "sg:orig_category":"Tintorer\u00cdas, Limpieza En Seco",
    "sg:phone":"+34 952 47 54 77",
    "sg:postcode":"29640",
    "sg:province":"M\u00e1laga",
    "wof:name":"Criado Espinosa Francisco",
    "wof:placetype":"venue"
},
  "geometry": {"coordinates":[-4.6204957962,36.5520744324],"type":"Point"}
}