{
  "type": "Feature",
  "properties": {
    "iso:country":"ES",
    "sg:address":"Camino Viejo Simancas, S/n",
    "sg:city":"Valladolid",
    "sg:orig_category":"Zapatos (al Por Menor)",
    "sg:phone":"+34 983 22 78 89",
    "sg:postcode":"47008",
    "sg:province":"Valladolid",
    "wof:name":"Kid Club By Tino Gonzalez S.l.",
    "wof:placetype":"venue"
},
  "geometry": {"coordinates":[-4.7458910942,41.6271781921],"type":"Point"}
}