{
  "type": "Feature",
  "properties": {
    "iso:country":"ES",
    "sg:address":"Calle de Carmi\u00d1a Prieto Rouco, 1",
    "sg:city":"Vilalba",
    "sg:orig_category":"Agentes Generales De Seguros",
    "sg:phone":"+34 982 51 20 10",
    "sg:postcode":"27800",
    "sg:province":"Lugo",
    "wof:name":"Carreiras Galdo Maria Jesus",
    "wof:placetype":"venue"
},
  "geometry": {"coordinates":[-7.6795740128,43.2989387512],"type":"Point"}
}