{
  "type": "Feature",
  "properties": {
    "addr:full":"Ctra. Corchera, 3 Merida Badajoz 06800",
    "addr:housenumber":"3",
    "addr:postcode":"06800",
    "addr:street":"Ctra. Corchera",
    "iso:country":"ES",
    "sg:address":"Ctra. Corchera, 3",
    "sg:city":"Merida",
    "sg:orig_category":"Ferreter\u00cda (diversos)",
    "sg:phone":"+34 924 30 14 74",
    "sg:postcode":"06800",
    "sg:province":"Badajoz",
    "wof:name":"Fernandez Del Amo Jose",
    "wof:placetype":"venue"
},
  "geometry": {"coordinates":[-6.3427195549,38.9247665405],"type":"Point"}
}