{
  "type": "Feature",
  "properties": {
    "iso:country":"ES",
    "sg:address":"Avda General Sanjurjo, 20",
    "sg:city":"Coru\u00d1a",
    "sg:orig_category":"Supermercados Y Hipermercados",
    "sg:phone":"+34 981 17 33 54",
    "sg:postcode":"15006",
    "sg:province":"La Coru\u00f1a",
    "wof:name":"Distribuciones Froiz S.a.",
    "wof:placetype":"venue"
},
  "geometry": {"coordinates":[-8.4029626846,43.3561439514],"type":"Point"}
}