{
  "type": "Feature",
  "properties": {
    "iso:country":"ES",
    "sg:address":"Cervantes, 1",
    "sg:city":"Montroy",
    "sg:orig_category":"Peluquer\u00cdas, Peluquer\u00cda Mixta",
    "sg:phone":"+34 962 55 60 06",
    "sg:postcode":"46193",
    "sg:province":"Valencia",
    "wof:name":"Blasco Moreno Maria Soraya",
    "wof:placetype":"venue"
},
  "geometry": {"coordinates":[-0.613763988,39.3419914246],"type":"Point"}
}