{
  "type": "Feature",
  "properties": {
    "addr:full":"Calle de Nueva Guinea, S/n Salamanca Salamanca 37003",
    "addr:housenumber":"s / n",
    "addr:postcode":"37003",
    "addr:street":"Calle De Nueva Guinea",
    "iso:country":"ES",
    "sg:address":"Calle de Nueva Guinea, S/n",
    "sg:city":"Salamanca",
    "sg:orig_category":"Financiaci\u00d3n Y Cr\u00c9ditos",
    "sg:phone":"+34 923 18 32 63",
    "sg:postcode":"37003",
    "sg:province":"Salamanca",
    "wof:name":"Marcos Granados Mariano",
    "wof:placetype":"venue"
},
  "geometry": {"coordinates":[-5.6427631378,40.9721946716],"type":"Point"}
}