{
  "type": "Feature",
  "properties": {
    "iso:country":"ES",
    "sg:address":"Carrer de Cadaques, 47",
    "sg:city":"Llagosta",
    "sg:orig_category":"Papel, Reciclaje",
    "sg:phone":"+34 935 60 53 62",
    "sg:postcode":"08120",
    "sg:province":"Barcelona",
    "wof:name":"Sans Vidal Juan",
    "wof:placetype":"venue"
},
  "geometry": {"coordinates":[2.2004990578,41.5139160156],"type":"Point"}
}