{
  "type": "Feature",
  "properties": {
    "addr:full":"Calle de Corredera De San Marcos, 46 Linares Ja\u00e9n 23700",
    "addr:housenumber":"46",
    "addr:postcode":"23700",
    "addr:street":"Calle De Corredera De San Marcos;Jae\u0301N",
    "iso:country":"ES",
    "sg:address":"Calle de Corredera De San Marcos, 46",
    "sg:city":"Linares",
    "sg:classifiers":[
        {
            "category":"Sports & Exercise",
            "subcategory":"Golf",
            "type":"Entertainment"
        }
    ],
    "sg:phone":"+34 953 60 72 54",
    "sg:postcode":"23700",
    "sg:province":"Ja\u00e9n",
    "sg:tags":[
        "y",
        "de",
        "campos",
        "clases"
    ],
    "wof:name":"Club De Golf La Garza",
    "wof:placetype":"venue"
},
  "geometry": {"coordinates":[-3.6330370903,38.0976257324],"type":"Point"}
}