{
  "type": "Feature",
  "properties": {
    "iso:country":"ES",
    "sg:address":"Av Diagonal, 437",
    "sg:city":"Barcelona",
    "sg:orig_category":"Centros Empresariales",
    "sg:phone":"+34 932 01 29 88",
    "sg:postcode":"08036",
    "sg:province":"Barcelona",
    "sg:website":"www.fecemd.org/avad.asp",
    "wof:name":"Federacion De Comercio Electronico Y Marketing Directo",
    "wof:placetype":"venue"
},
  "geometry": {"coordinates":[2.1505389214,41.393951416],"type":"Point"}
}