{
  "type": "Feature",
  "properties": {
    "addr:full":"Carrer de Gaieta Vinzia, 62 Mollet Valles Barcelona 08100",
    "addr:housenumber":"62",
    "addr:postcode":"08100",
    "addr:street":"Carrer De Gaieta Vinzia",
    "iso:country":"ES",
    "sg:address":"Carrer de Gaieta Vinzia, 62",
    "sg:city":"Mollet Valles",
    "sg:orig_category":"Institutos De Belleza",
    "sg:phone":"+34 935 93 11 68",
    "sg:postcode":"08100",
    "sg:province":"Barcelona",
    "wof:name":"Aloy Roca Vicenc",
    "wof:placetype":"venue"
},
  "geometry": {"coordinates":[2.2101473808,41.5413475037],"type":"Point"}
}