{
  "type": "Feature",
  "properties": {
    "iso:country":"ES",
    "sg:address":"Plaz Constitucion, 2",
    "sg:city":"Tapia Casariego",
    "sg:orig_category":"Ense\u00d1anza Secundaria: Colegios Y Escuelas Privadas",
    "sg:phone":"+34 985 62 80 17",
    "sg:postcode":"33740",
    "sg:province":"Asturias",
    "wof:name":"Principado De Asturias",
    "wof:placetype":"venue"
},
  "geometry": {"coordinates":[-6.9426078796,43.5692253113],"type":"Point"}
}