{
  "type": "Feature",
  "properties": {
    "addr:full":"Calle de Maestro Cebrian, 2 Jaen Ja\u00e9n 23008",
    "addr:housenumber":"2;jae\u0301n",
    "addr:postcode":"23008",
    "addr:street":"Calle De Maestro Cebrian",
    "iso:country":"ES",
    "sg:address":"Calle de Maestro Cebrian, 2",
    "sg:city":"Jaen",
    "sg:orig_category":"Dietistas",
    "sg:phone":"+34 953 08 32 46",
    "sg:postcode":"23008",
    "sg:province":"Ja\u00e9n",
    "wof:name":"C.b. Enriqueta Varo Y Otro",
    "wof:placetype":"venue"
},
  "geometry": {"coordinates":[-3.785392046,37.7755584717],"type":"Point"}
}