{
  "type": "Feature",
  "properties": {
    "iso:country":"ES",
    "sg:address":"Avda Doctor Ramon Y Cajal, 3",
    "sg:city":"Alacant",
    "sg:orig_category":"Farmacias",
    "sg:phone":"+34 965 21 44 09",
    "sg:postcode":"03001",
    "sg:province":"Alicante",
    "wof:name":"Gonzalez Solares Fernando",
    "wof:placetype":"venue"
},
  "geometry": {"coordinates":[-0.4869540036,38.3416137695],"type":"Point"}
}