{
  "type": "Feature",
  "properties": {
    "addr:full":"Cust Santo Domingo, 3 Madrid Madrid 28013",
    "addr:housenumber":"3",
    "addr:postcode":"28013",
    "addr:street":"Santo Domingo",
    "iso:country":"ES",
    "sg:address":"Cust Santo Domingo, 3",
    "sg:city":"Madrid",
    "sg:orig_category":"Arquitectos",
    "sg:phone":"+34 915 47 98 89",
    "sg:postcode":"28013",
    "sg:province":"Madrid",
    "wof:name":"Posada Moreno Carlos Maria",
    "wof:placetype":"venue"
},
  "geometry": {"coordinates":[-3.7101500034,40.4192008972],"type":"Point"}
}