{
  "type": "Feature",
  "properties": {
    "iso:country":"ES",
    "sg:address":"Rua Cando, 13",
    "sg:city":"Porri\u00f1o",
    "sg:orig_category":"Zapatos (al Por Menor)",
    "sg:phone":"+34 986 33 51 29",
    "sg:postcode":"36400",
    "sg:province":"Pontevedra",
    "wof:name":"Fernandez Lorenzo Juan Carlos",
    "wof:placetype":"venue"
},
  "geometry": {"coordinates":[-8.6220293045,42.1627311707],"type":"Point"}
}