{
  "type": "Feature",
  "properties": {
    "addr:full":"Calle de Nuncio Viejo, 2 Toledo Toledo 45002",
    "addr:housenumber":"2",
    "addr:postcode":"45002",
    "addr:street":"Calle De Nuncio Viejo",
    "iso:country":"ES",
    "sg:address":"Calle de Nuncio Viejo, 2",
    "sg:city":"Toledo",
    "sg:orig_category":"Sales (al Por Mayor)",
    "sg:phone":"+34 925 22 15 34",
    "sg:postcode":"45002",
    "sg:province":"Toledo",
    "wof:name":"Escobar Moreno Gregorio",
    "wof:placetype":"venue"
},
  "geometry": {"coordinates":[-4.0244441032,39.8580665588],"type":"Point"}
}