{
  "type": "Feature",
  "properties": {
    "iso:country":"ES",
    "sg:address":"Calle de Molino, 4",
    "sg:city":"Arcos Frontera",
    "sg:orig_category":"Art\u00cdculos De Regalo (al Por Menor)",
    "sg:phone":"+34 956 70 06 27",
    "sg:postcode":"11630",
    "sg:province":"C\u00e1diz",
    "wof:name":"Jimenez Rojas Juan",
    "wof:placetype":"venue"
},
  "geometry": {"coordinates":[-5.8168668747,36.7541007996],"type":"Point"}
}