{
  "type": "Feature",
  "properties": {
    "iso:country":"ES",
    "sg:address":"Calle de Requena, 42",
    "sg:city":"Alzira",
    "sg:orig_category":"Peritos En C\u00c1lculo Inmobiliario, Industrial Y De Fondos De Comercio",
    "sg:phone":"+34 962 41 04 71",
    "sg:postcode":"46600",
    "sg:province":"Valencia",
    "wof:name":"Prats Saez Bernardo",
    "wof:placetype":"venue"
},
  "geometry": {"coordinates":[-0.4315589964,39.1439781189],"type":"Point"}
}