{
  "type": "Feature",
  "properties": {
    "addr:full":"Avda Almargen (de), 16 Bormujos Sevilla 41930",
    "addr:housenumber":"16",
    "addr:postcode":"41930",
    "addr:street":"Avda Almargen De",
    "iso:country":"ES",
    "sg:address":"Avda Almargen (de), 16",
    "sg:city":"Bormujos",
    "sg:orig_category":"Materias Pl\u00c1sticas: Productos De Consumo Masivo (fabricaci\u00d3n, Al Por Mayor)",
    "sg:phone":"+34 955 72 57 72",
    "sg:postcode":"41930",
    "sg:province":"Sevilla",
    "wof:name":"Delgado Gallego Angel",
    "wof:placetype":"venue"
},
  "geometry": {"coordinates":[-6.0654239655,37.3722572327],"type":"Point"}
}