{
  "type": "Feature",
  "properties": {
    "iso:country":"ES",
    "sg:address":"Ctra General Tf-28 La Camella, 28",
    "sg:city":"Camella",
    "sg:orig_category":"Fabricaci\u00d3n De Productos Textiles Sin Tejer",
    "sg:phone":"+34 922 72 01 99",
    "sg:postcode":"38627",
    "sg:province":"Santa Cruz De Tenerife",
    "wof:name":"Beltran Mena Ana Cristina",
    "wof:placetype":"venue"
},
  "geometry": {"coordinates":[-16.6800937653,28.0790691376],"type":"Point"}
}