{
  "type": "Feature",
  "properties": {
    "addr:full":"Carrer de Codols, 23 Barcelona Barcelona 08002",
    "addr:housenumber":"23",
    "addr:postcode":"08002",
    "addr:street":"Carrer De Codols",
    "iso:country":"ES",
    "sg:address":"Carrer de Codols, 23",
    "sg:city":"Barcelona",
    "sg:orig_category":"Comidas Por Encargo, Organizaci\u00d3n De Recepciones",
    "sg:phone":"+34 934 12 10 89",
    "sg:postcode":"08002",
    "sg:province":"Barcelona",
    "wof:name":"Font Mascaro Margarita",
    "wof:placetype":"venue"
},
  "geometry": {"coordinates":[2.1787450314,41.3794441223],"type":"Point"}
}