{
  "type": "Feature",
  "properties": {
    "iso:country":"ES",
    "sg:address":"Pg Ferrocarrils Catalans, 138",
    "sg:city":"Cornella Llobregat",
    "sg:orig_category":"Fijaciones Industriales",
    "sg:phone":"+34 934 74 07 07",
    "sg:postcode":"08940",
    "sg:province":"Barcelona",
    "wof:name":"Fijaciones Industriales Psm S.a.",
    "wof:placetype":"venue"
},
  "geometry": {"coordinates":[2.0805630684,41.3522033691],"type":"Point"}
}