{
  "type": "Feature",
  "properties": {
    "iso:country":"ES",
    "sg:address":"Avda Aragon, 22",
    "sg:city":"Carcastillo",
    "sg:orig_category":"Supermercados Y Hipermercados",
    "sg:phone":"+34 948 71 51 20",
    "sg:postcode":"31310",
    "sg:province":"Navarra",
    "wof:name":"Perez De La Iglesia Uriaque 95 S.l.",
    "wof:placetype":"venue"
},
  "geometry": {"coordinates":[-1.444092989,42.376914978],"type":"Point"}
}