{
  "type": "Feature",
  "properties": {
    "iso:country":"ES",
    "sg:address":"Calle de Montes Claros, 3",
    "sg:city":"Soria",
    "sg:orig_category":"Delegados, Agentes De Tr\u00c1nsito, Auxiliares De Transporte Internacional",
    "sg:phone":"+34 975 24 08 85",
    "sg:postcode":"42002",
    "sg:province":"Soria",
    "wof:name":"Logistica Laguna S.l.",
    "wof:placetype":"venue"
},
  "geometry": {"coordinates":[-2.4648880959,41.7703781128],"type":"Point"}
}