{
  "type": "Feature",
  "properties": {
    "addr:full":"Calle de Gandia, 26 Alzira Valencia 46600",
    "addr:housenumber":"26",
    "addr:postcode":"46600",
    "addr:street":"Calle De Gandia",
    "iso:country":"ES",
    "sg:address":"Calle de Gandia, 26",
    "sg:city":"Alzira",
    "sg:orig_category":"Lavado, Limpieza De Veh\u00cdculos",
    "sg:phone":"+34 962 41 81 92",
    "sg:postcode":"46600",
    "sg:province":"Valencia",
    "wof:name":"Centro De Lavado La Ballena Alzira S.l.",
    "wof:placetype":"venue"
},
  "geometry": {"coordinates":[-0.4277170002,39.1442909241],"type":"Point"}
}