{
  "type": "Feature",
  "properties": {
    "addr:full":"Las Pitas, S/n S. Agustin-playa Ingles Las Palmas 35100",
    "addr:housenumber":"s",
    "addr:postcode":"35100",
    "addr:street":"Las Pitas;/ N S. Agustin-Playa",
    "iso:country":"ES",
    "sg:address":"Las Pitas, S/n",
    "sg:city":"S. Agustin-playa Ingles",
    "sg:orig_category":"Iglesia Cat\u00d3lica",
    "sg:phone":"+34 928 76 72 06",
    "sg:postcode":"35100",
    "sg:province":"Las Palmas",
    "sg:website":"www.svenskayrkangrancanaria.com",
    "wof:name":"Iglesia Sueca En Las Palmas",
    "wof:placetype":"venue"
},
  "geometry": {"coordinates":[-15.4300060272,28.1248226166],"type":"Point"}
}