{
  "type": "Feature",
  "properties": {
    "addr:full":"Calle de Cruz, 14 Arcenillas Zamora 49151",
    "addr:housenumber":"14",
    "addr:postcode":"49151",
    "addr:street":"Calle De Cruz;Zamora",
    "iso:country":"ES",
    "sg:address":"Calle de Cruz, 14",
    "sg:city":"Arcenillas",
    "sg:orig_category":"Molduras, Junquillos, Listones Y Molduras Perforadas",
    "sg:phone":"+34 980 57 13 57",
    "sg:postcode":"49151",
    "sg:province":"Zamora",
    "wof:name":"Higuera Hernandez Etelvino",
    "wof:placetype":"venue"
},
  "geometry": {"coordinates":[-5.6851825714,41.4562263489],"type":"Point"}
}