{
  "type": "Feature",
  "properties": {
    "addr:full":"Ptda Torreta, S/n Alcora Castell\u00f3n 12110",
    "addr:housenumber":"s / n",
    "addr:postcode":"12110",
    "addr:street":"Ptda Torreta;Alcora Castello\u0301N",
    "iso:country":"ES",
    "sg:address":"Ptda Torreta, S/n",
    "sg:city":"Alcora",
    "sg:orig_category":"Fabricaci\u00d3n De Enlosados, Soler\u00cdas",
    "sg:phone":"+34 964 36 32 11",
    "sg:postcode":"12110",
    "sg:province":"Castell\u00f3n",
    "sg:website":"www.bestile.es",
    "wof:name":"Bestile S.l.",
    "wof:placetype":"venue"
},
  "geometry": {"coordinates":[-0.2178789973,40.0734786987],"type":"Point"}
}