{
  "type": "Feature",
  "properties": {
    "addr:full":"Calle de Ramiro I, 29 Piedras Blancas Asturias 33450",
    "addr:housenumber":"29",
    "addr:postcode":"33450",
    "addr:street":"Calle De Ramiro I",
    "iso:country":"ES",
    "sg:address":"Calle de Ramiro I, 29",
    "sg:city":"Piedras Blancas",
    "sg:orig_category":"Droguer\u00cdas (al Por Menor)",
    "sg:phone":"+34 985 50 76 29",
    "sg:postcode":"33450",
    "sg:province":"Asturias",
    "wof:name":"Alba Fernandez Josefina",
    "wof:placetype":"venue"
},
  "geometry": {"coordinates":[-5.9761333466,43.5608100891],"type":"Point"}
}