{
  "type": "Feature",
  "properties": {
    "addr:full":"Ctra. Malaga, S/n Chauchina Granada 18330",
    "addr:postcode":"18330",
    "addr:street":"Ctra. Malaga S / N",
    "iso:country":"ES",
    "sg:address":"Ctra. Malaga, S/n",
    "sg:city":"Chauchina",
    "sg:orig_category":"Semiller\u00cdas",
    "sg:phone":"+34 958 44 63 76",
    "sg:postcode":"18330",
    "sg:province":"Granada",
    "wof:name":"Perez Mingorance Ana",
    "wof:placetype":"venue"
},
  "geometry": {"coordinates":[-3.7719919682,37.2014541626],"type":"Point"}
}