{
  "type": "Feature",
  "properties": {
    "addr:full":"Calle de Velazquez, 4 Xirivella Valencia 46950",
    "addr:housenumber":"4",
    "addr:postcode":"46950",
    "addr:street":"Calle De Velazquez",
    "iso:country":"ES",
    "sg:address":"Calle de Velazquez, 4",
    "sg:city":"Xirivella",
    "sg:orig_category":"Bisuter\u00cda, Joyer\u00cda, Relojer\u00cda (al Por Menor)",
    "sg:phone":"+34 963 50 25 07",
    "sg:postcode":"46950",
    "sg:province":"Valencia",
    "wof:name":"Mares Viana Tomas Gabriel",
    "wof:placetype":"venue"
},
  "geometry": {"coordinates":[-0.4300180078,39.4663887024],"type":"Point"}
}