{
  "type": "Feature",
  "properties": {
    "addr:full":"Avda Valentin Masip, 40 Oviedo Asturias 33013",
    "addr:housenumber":"40",
    "addr:postcode":"33013",
    "addr:street":"Avda Valentin Masip",
    "iso:country":"ES",
    "sg:address":"Avda Valentin Masip, 40",
    "sg:city":"Oviedo",
    "sg:orig_category":"Farmacias",
    "sg:phone":"+34 985 23 45 59",
    "sg:postcode":"33013",
    "sg:province":"Asturias",
    "wof:name":"Fernandez Fernandez Maria Del Carmen",
    "wof:placetype":"venue"
},
  "geometry": {"coordinates":[-5.8638319969,43.3628768921],"type":"Point"}
}