{
  "type": "Feature",
  "properties": {
    "iso:country":"ES",
    "sg:address":"Avda Modesto Hernandez Gonzalez, 27",
    "sg:city":"Chafiras",
    "sg:orig_category":"Zapatos (al Por Menor)",
    "sg:phone":"+34 922 73 54 82",
    "sg:postcode":"38639",
    "sg:province":"Santa Cruz De Tenerife",
    "wof:name":"Cadacar S.l.",
    "wof:placetype":"venue"
},
  "geometry": {"coordinates":[-16.6115474701,28.0350246429],"type":"Point"}
}