{
  "type": "Feature",
  "properties": {
    "addr:full":"Carrer de Ramon Llull, 12 Prat Llobregat Barcelona 08820",
    "addr:housenumber":"12",
    "addr:postcode":"08820",
    "addr:street":"Carrer De Ramon Llull;Llobregat",
    "iso:country":"ES",
    "sg:address":"Carrer de Ramon Llull, 12",
    "sg:city":"Prat Llobregat",
    "sg:orig_category":"Pescader\u00cdas (al Por Menor)",
    "sg:phone":"+34 934 78 18 57",
    "sg:postcode":"08820",
    "sg:province":"Barcelona",
    "wof:name":"Perez Lopez Jose",
    "wof:placetype":"venue"
},
  "geometry": {"coordinates":[2.0900070667,41.3235282898],"type":"Point"}
}