{
  "type": "Feature",
  "properties": {
    "iso:country":"ES",
    "sg:address":"Pase Miguel Unamuno, 15",
    "sg:city":"Sevilla",
    "sg:orig_category":"Psic\u00d3logos",
    "sg:phone":"+34 954 25 77 73",
    "sg:postcode":"41020",
    "sg:province":"Sevilla",
    "wof:name":"Alvarez Bolivar Maria Angeles",
    "wof:placetype":"venue"
},
  "geometry": {"coordinates":[-5.9407553673,37.4006576538],"type":"Point"}
}