{
  "type": "Feature",
  "properties": {
    "iso:country":"ES",
    "sg:address":"Calle de Delicias, 37",
    "sg:city":"Zaragoza",
    "sg:orig_category":"Fabricaci\u00d3n De Ropa De Deportes",
    "sg:phone":"+34 976 34 60 39",
    "sg:postcode":"50017",
    "sg:province":"Zaragoza",
    "wof:name":"Martin Gonzalez Juan Antonio",
    "wof:placetype":"venue"
},
  "geometry": {"coordinates":[-0.9050958753,41.6509628296],"type":"Point"}
}