{
  "type": "Feature",
  "properties": {
    "iso:country":"ES",
    "sg:address":"Plaz Espa\u00d1a, 9",
    "sg:city":"Mas Matas",
    "sg:orig_category":"Armas Y Municiones (fabricaci\u00d3n, Al Por Mayor)",
    "sg:phone":"+34 978 84 82 78",
    "sg:postcode":"44564",
    "sg:province":"Teruel",
    "wof:name":"Mir Sanz Juan Jose",
    "wof:placetype":"venue"
},
  "geometry": {"coordinates":[-1.104550004,40.3420906067],"type":"Point"}
}