{
  "type": "Feature",
  "properties": {
    "addr:full":"Plaz Juan De Austria, S/n Valladolid Valladolid 47006",
    "addr:housenumber":"s / n",
    "addr:postcode":"47006",
    "addr:street":"Plaz Juan De Austria",
    "iso:country":"ES",
    "sg:address":"Plaz Juan De Austria, S/n",
    "sg:city":"Valladolid",
    "sg:orig_category":"Asociaciones Y Clubs Deportivos",
    "sg:phone":"+34 983 27 98 08",
    "sg:postcode":"47006",
    "sg:province":"Valladolid",
    "wof:name":"Club Union Deportiva Sur De Valladolid",
    "wof:placetype":"venue"
},
  "geometry": {"coordinates":[-4.7425041199,41.6319007874],"type":"Point"}
}