{
  "type": "Feature",
  "properties": {
    "addr:full":"Carrer de Sant Antoni Maria Claret, 137 Barcelona Barcelona 08025",
    "addr:housenumber":"137",
    "addr:postcode":"08025",
    "addr:street":"Carrer De Sant Antoni Maria Claret",
    "iso:country":"ES",
    "sg:address":"Carrer de Sant Antoni Maria Claret, 137",
    "sg:city":"Barcelona",
    "sg:orig_category":"Producci\u00d3n, Distribuci\u00d3n De Electricidad",
    "sg:phone":"+34 934 33 57 88",
    "sg:postcode":"08025",
    "sg:province":"Barcelona",
    "sg:website":"www.globalelectronictrading.es",
    "wof:name":"Global Electronic Trading S.l.",
    "wof:placetype":"venue"
},
  "geometry": {"coordinates":[2.1732668877,41.4105682373],"type":"Point"}
}