{
  "type": "Feature",
  "properties": {
    "addr:full":"Calle de Virgen De Las Nieves, 1 Cenizate Albacete 02247",
    "addr:housenumber":"1",
    "addr:postcode":"02247",
    "addr:street":"Calle De Virgen De Las Nieves",
    "iso:country":"ES",
    "sg:address":"Calle de Virgen De Las Nieves, 1",
    "sg:city":"Cenizate",
    "sg:orig_category":"Productores Recolectores, Venta Directa De Vinos",
    "sg:phone":"+34 967 48 20 06",
    "sg:postcode":"02247",
    "sg:province":"Albacete",
    "wof:name":"Coop Vinicola Virgen De Las Nieves-bodega",
    "wof:placetype":"venue"
},
  "geometry": {"coordinates":[-1.6624469757,39.3020973206],"type":"Point"}
}