{
  "type": "Feature",
  "properties": {
    "addr:full":"Carrer de Barcelona, 180 Palleja Barcelona 08780",
    "addr:housenumber":"180",
    "addr:postcode":"08780",
    "addr:street":"Carrer De Barcelona",
    "iso:country":"ES",
    "sg:address":"Carrer de Barcelona, 180",
    "sg:city":"Palleja",
    "sg:orig_category":"Transportes Por Carretera: Lotes Completos, Mercanc\u00cdas Diversas",
    "sg:phone":"+34 936 63 40 55",
    "sg:postcode":"08780",
    "sg:province":"Barcelona",
    "wof:name":"Garcia Navarro Daniel",
    "wof:placetype":"venue"
},
  "geometry": {"coordinates":[1.995511055,41.425819397],"type":"Point"}
}