{
  "type": "Feature",
  "properties": {
    "addr:full":"Calle de Rosa, S/n Malaga M\u00e1laga 29010",
    "addr:housenumber":"s / n",
    "addr:postcode":"29010",
    "addr:street":"Calle De Rosa;Ma\u0301Laga",
    "iso:country":"ES",
    "sg:address":"Calle de Rosa, S/n",
    "sg:city":"Malaga",
    "sg:orig_category":"Cajas De Ahorro",
    "sg:phone":"+34 952 28 32 11",
    "sg:postcode":"29010",
    "sg:province":"M\u00e1laga",
    "sg:website":"www.unicaja.es",
    "wof:name":"Unicaja",
    "wof:placetype":"venue"
},
  "geometry": {"coordinates":[-4.4426288605,36.7229309082],"type":"Point"}
}