{
  "type": "Feature",
  "properties": {
    "iso:country":"ES",
    "sg:address":"Calle de Poeta Fco. Salinas Garcia, 7",
    "sg:city":"Callosa Segura",
    "sg:orig_category":"Sales (al Por Mayor)",
    "sg:phone":"+34 965 31 18 30",
    "sg:postcode":"03360",
    "sg:province":"Alicante",
    "wof:name":"Zaragoza Conservas Vegetales Al Vacio S.l.",
    "wof:placetype":"venue"
},
  "geometry": {"coordinates":[-0.8776689768,38.1256752014],"type":"Point"}
}