{
  "type": "Feature",
  "properties": {
    "addr:full":"Ctra Madrid-cadiz, S/n Andujar Ja\u00e9n 23740",
    "addr:postcode":"23740",
    "addr:street":"Ctra Madrid-Cadiz S / N;Jae\u0301N",
    "iso:country":"ES",
    "sg:address":"Ctra Madrid-cadiz, S/n",
    "sg:city":"Andujar",
    "sg:orig_category":"Asociaciones Y Clubs Deportivos",
    "sg:phone":"+34 953 12 25 21",
    "sg:postcode":"23740",
    "sg:province":"Ja\u00e9n",
    "wof:name":"Hortrapac S.l.",
    "wof:placetype":"venue"
},
  "geometry": {"coordinates":[-4.056040287,38.0340156555],"type":"Point"}
}