{
  "type": "Feature",
  "properties": {
    "iso:country":"ES",
    "sg:address":"Carrer de Can Brondo, 7",
    "sg:city":"Palma",
    "sg:orig_category":"Loter\u00cda Y T\u00d3mbola",
    "sg:phone":"+34 971 71 75 54",
    "sg:postcode":"07001",
    "sg:province":"Islas Baleares",
    "wof:name":"Palou De Comasema Fortuny Raimundo",
    "wof:placetype":"venue"
},
  "geometry": {"coordinates":[2.6479310989,39.5711326599],"type":"Point"}
}