{
  "type": "Feature",
  "properties": {
    "addr:full":"Carrer de Santa Creu, 27 Sant Feliu Llobregat Barcelona 08980",
    "addr:housenumber":"27",
    "addr:postcode":"08980",
    "addr:street":"Carrer De Santa Creu",
    "iso:country":"ES",
    "sg:address":"Carrer de Santa Creu, 27",
    "sg:city":"Sant Feliu Llobregat",
    "sg:orig_category":"Zapatos (al Por Menor)",
    "sg:phone":"+34 936 66 79 02",
    "sg:postcode":"08980",
    "sg:province":"Barcelona",
    "wof:name":"Valle Altozano Julio",
    "wof:placetype":"venue"
},
  "geometry": {"coordinates":[2.0467059612,41.3862991333],"type":"Point"}
}