{
  "type": "Feature",
  "properties": {
    "iso:country":"ES",
    "sg:address":"Calle de Humilladero, S/n",
    "sg:city":"Santos",
    "sg:orig_category":"Asilos De Ancianos. Centros Privados",
    "sg:phone":"+34 923 59 21 91",
    "sg:postcode":"37768",
    "sg:province":"Salamanca",
    "wof:name":"Ayuntamiento De Los Santos",
    "wof:placetype":"venue"
},
  "geometry": {"coordinates":[-5.7964510918,40.5455093384],"type":"Point"}
}