{
  "type": "Feature",
  "properties": {
    "addr:full":"Calle de Gomez Nu\u00d1ez, 24 Fabero Le\u00f3n 24420",
    "addr:housenumber":"24",
    "addr:postcode":"24420",
    "addr:street":"Calle De Gomez Nun\u0303Ez;Leo\u0301N",
    "iso:country":"ES",
    "sg:address":"Calle de Gomez Nu\u00d1ez, 24",
    "sg:city":"Fabero",
    "sg:orig_category":"Doctores En Medicina",
    "sg:phone":"+34 987 55 19 48",
    "sg:postcode":"24420",
    "sg:province":"Le\u00f3n",
    "wof:name":"Rubio Ortega Pablo",
    "wof:placetype":"venue"
},
  "geometry": {"coordinates":[-6.6266188622,42.7642745972],"type":"Point"}
}