{
  "type": "Feature",
  "properties": {
    "addr:full":"Calle de Trabajo, 7 Utrera Sevilla 41710",
    "addr:housenumber":"7",
    "addr:postcode":"41710",
    "addr:street":"Calle De Trabajo",
    "iso:country":"ES",
    "sg:address":"Calle de Trabajo, 7",
    "sg:city":"Utrera",
    "sg:orig_category":"Trabajos De Plastificado, Encolado, Pel\u00cdculas Trasparentes",
    "sg:phone":"+34 955 86 43 73",
    "sg:postcode":"41710",
    "sg:province":"Sevilla",
    "wof:name":"Moldes Sevilla S.l.",
    "wof:placetype":"venue"
},
  "geometry": {"coordinates":[-5.791738987,37.195148468],"type":"Point"}
}