{
  "type": "Feature",
  "properties": {
    "addr:full":"Calle de Canteros (de Los), 9 Colmenar Viejo Madrid 28770",
    "addr:postcode":"28770",
    "addr:street":"Calle De Canteros De Los",
    "iso:country":"ES",
    "sg:address":"Calle de Canteros (de Los), 9",
    "sg:city":"Colmenar Viejo",
    "sg:orig_category":"Empresas De Carpinter\u00cda De Madera",
    "sg:phone":"+34 918 45 67 19",
    "sg:postcode":"28770",
    "sg:province":"Madrid",
    "wof:name":"Arquero Gomez Martin",
    "wof:placetype":"venue"
},
  "geometry": {"coordinates":[-3.7598934174,40.6627197266],"type":"Point"}
}