{
  "type": "Feature",
  "properties": {
    "iso:country":"ES",
    "sg:address":"Alam Principal, 24",
    "sg:city":"Malaga",
    "sg:orig_category":"Promotores Constructores",
    "sg:phone":"+34 952 60 44 44",
    "sg:postcode":"29005",
    "sg:province":"M\u00e1laga",
    "wof:name":"Constructamp S.a.",
    "wof:placetype":"venue"
},
  "geometry": {"coordinates":[-4.4239668846,36.7175674438],"type":"Point"}
}