{
  "type": "Feature",
  "properties": {
    "addr:full":"Carrer de Cristofor Colom (de), 36 Vilassar De Mar Barcelona 08340",
    "addr:housenumber":"36",
    "addr:postcode":"08340",
    "addr:street":"Carrer De Cristofor Colom De",
    "iso:country":"ES",
    "sg:address":"Carrer de Cristofor Colom (de), 36",
    "sg:city":"Vilassar De Mar",
    "sg:orig_category":"Mec\u00c1nico Del Autom\u00d3vil",
    "sg:phone":"+34 937 59 27 91",
    "sg:postcode":"08340",
    "sg:province":"Barcelona",
    "wof:name":"More Conesa Joan",
    "wof:placetype":"venue"
},
  "geometry": {"coordinates":[2.3915679455,41.5049667358],"type":"Point"}
}