{
  "type": "Feature",
  "properties": {
    "addr:full":"Avda De Galicia, 16 Ponteareas Pontevedra 36860",
    "addr:housenumber":"16",
    "addr:postcode":"36860",
    "addr:street":"Avda De Galicia",
    "iso:country":"ES",
    "sg:address":"Avda De Galicia, 16",
    "sg:city":"Ponteareas",
    "sg:classifiers":[
        {
            "category":"Autos & Motor Vehicles",
            "subcategory":"Automobile Sales",
            "type":"Retail Goods"
        }
    ],
    "sg:phone":"+34 986 64 09 98",
    "sg:postcode":"36860",
    "sg:province":"Pontevedra",
    "wof:name":"Auto Escuela Y Tecnicos Contables San Gregorio S.l.",
    "wof:placetype":"venue"
},
  "geometry": {"coordinates":[-8.5026197433,42.1748771667],"type":"Point"}
}