{
  "type": "Feature",
  "properties": {
    "addr:full":"Carrer de Arnau Palau, 26 Mataro Barcelona 08303",
    "addr:housenumber":"26",
    "addr:postcode":"08303",
    "addr:street":"Carrer De Arnau Palau",
    "iso:country":"ES",
    "sg:address":"Carrer de Arnau Palau, 26",
    "sg:city":"Mataro",
    "sg:orig_category":"Peluqueros: De Se\u00d1oras",
    "sg:phone":"+34 937 99 35 03",
    "sg:postcode":"08303",
    "sg:province":"Barcelona",
    "wof:name":"Jimenez Olmo Higinio",
    "wof:placetype":"venue"
},
  "geometry": {"coordinates":[2.4302499294,41.538860321],"type":"Point"}
}