{
  "type": "Feature",
  "properties": {
    "iso:country":"ES",
    "sg:address":"Avda Fernandez Ladreda, 22",
    "sg:city":"Le\u00f3n",
    "sg:orig_category":"Alimentaci\u00d3n Animal (fabricaci\u00d3n, Al Por Mayor)",
    "sg:phone":"+34 987 20 47 76",
    "sg:postcode":"24005",
    "sg:province":"Le\u00f3n",
    "wof:name":"Alvarez Serrano Manuel",
    "wof:placetype":"venue"
},
  "geometry": {"coordinates":[-5.5658268929,42.5869903564],"type":"Point"}
}