{
  "type": "Feature",
  "properties": {
    "iso:country":"ES",
    "sg:address":"Plaz San Agustin, 1",
    "sg:city":"Coin",
    "sg:orig_category":"Asociaciones Y Clubs Deportivos",
    "sg:phone":"+34 952 45 02 09",
    "sg:postcode":"29100",
    "sg:province":"M\u00e1laga",
    "wof:name":"Valdivia Castilla Maria Del Carmen",
    "wof:placetype":"venue"
},
  "geometry": {"coordinates":[-4.7576842308,36.659740448],"type":"Point"}
}