{
  "type": "Feature",
  "properties": {
    "addr:full":"Calle de Rejas De Don Gome, 6 Cordoba C\u00f3rdoba 14001",
    "addr:housenumber":"6",
    "addr:postcode":"14001",
    "addr:street":"Calle De Rejas De Don Gome;Co\u0301Rdoba",
    "iso:country":"ES",
    "sg:address":"Calle de Rejas De Don Gome, 6",
    "sg:city":"Cordoba",
    "sg:orig_category":"Alimentaci\u00d3n General (al Por Menor)",
    "sg:phone":"+34 957 48 12 19",
    "sg:postcode":"14001",
    "sg:province":"C\u00f3rdoba",
    "wof:name":"Cuevas Sanchez Francisco",
    "wof:placetype":"venue"
},
  "geometry": {"coordinates":[-4.7727689743,37.8886108398],"type":"Point"}
}