{
  "type": "Feature",
  "properties": {
    "addr:full":"Avda Galicia (de), 18 Ribadeo Lugo 27700",
    "addr:housenumber":"18",
    "addr:postcode":"27700",
    "addr:street":"Avda Galicia De",
    "iso:country":"ES",
    "sg:address":"Avda Galicia (de), 18",
    "sg:city":"Ribadeo",
    "sg:orig_category":"Caf\u00c9s, Bares, Cervecer\u00cdas",
    "sg:phone":"+34 982 12 00 16",
    "sg:postcode":"27700",
    "sg:province":"Lugo",
    "wof:name":"Teldelugo Comunicacion S.l.",
    "wof:placetype":"venue"
},
  "geometry": {"coordinates":[-7.0477337837,43.5367736816],"type":"Point"}
}