{
  "type": "Feature",
  "properties": {
    "iso:country":"ES",
    "sg:address":"Avda Orense, 11",
    "sg:city":"Marin",
    "sg:orig_category":"Pescader\u00cdas (al Por Mayor)",
    "sg:phone":"+34 986 88 29 10",
    "sg:postcode":"36900",
    "sg:province":"Pontevedra",
    "wof:name":"Pi\u00f1eiro & Calvar Lda.",
    "wof:placetype":"venue"
},
  "geometry": {"coordinates":[-8.699634552,42.3929328918],"type":"Point"}
}