{
  "type": "Feature",
  "properties": {
    "iso:country":"ES",
    "sg:address":"Calle de Via Carpetana, 47",
    "sg:city":"Madrid",
    "sg:orig_category":"Obras Y Organismos Sociales",
    "sg:phone":"+34 914 71 72 62",
    "sg:postcode":"28047",
    "sg:province":"Madrid",
    "wof:name":"Fundacion Benefica San Martin De Porres",
    "wof:placetype":"venue"
},
  "geometry": {"coordinates":[-3.733948946,40.3989868164],"type":"Point"}
}