{
  "type": "Feature",
  "properties": {
    "iso:country":"ES",
    "sg:address":"Psaj Gutierrez, 4",
    "sg:city":"Valladolid",
    "sg:orig_category":"Masajistas Kinesiterapeutas",
    "sg:phone":"+34 983 39 63 17",
    "sg:postcode":"47002",
    "sg:province":"Valladolid",
    "wof:name":"Rodriguez Parra Jesus",
    "wof:placetype":"venue"
},
  "geometry": {"coordinates":[-4.7246751785,41.6516151428],"type":"Point"}
}