{
  "type": "Feature",
  "properties": {
    "iso:country":"ES",
    "sg:address":"Avgd Montserrat, 1",
    "sg:city":"Igualada",
    "sg:orig_category":"Molduras, Junquillos, Listones Y Molduras Perforadas",
    "sg:phone":"+34 938 03 51 02",
    "sg:postcode":"08700",
    "sg:province":"Barcelona",
    "wof:name":"Farres Montane Maria Teresa",
    "wof:placetype":"venue"
},
  "geometry": {"coordinates":[1.6049460173,41.5869750977],"type":"Point"}
}