{
  "type": "Feature",
  "properties": {
    "iso:country":"ES",
    "sg:address":"Calle de Doctor Mara\u00d1on, S/n",
    "sg:city":"Cadiz",
    "sg:orig_category":"Asociaciones Humanitarias, De Cooperaci\u00d3n, De Acci\u00d3n Social",
    "sg:phone":"+34 956 22 90 07",
    "sg:postcode":"11002",
    "sg:province":"C\u00e1diz",
    "wof:name":"Asociacion Diabeticos Gaditanos",
    "wof:placetype":"venue"
},
  "geometry": {"coordinates":[-6.3046693802,36.5329208374],"type":"Point"}
}