{
  "type": "Feature",
  "properties": {
    "iso:country":"ES",
    "sg:address":"Calle de Sancho Archiniega, 13",
    "sg:city":"Portugalete",
    "sg:orig_category":"Peluquer\u00cdas, Peluquer\u00cda Mixta",
    "sg:phone":"+34 944 61 61 77",
    "sg:postcode":"48920",
    "sg:province":"Vizcaya",
    "wof:name":"Marife Bernal Cuezva",
    "wof:placetype":"venue"
},
  "geometry": {"coordinates":[-3.0271980762,43.3228569031],"type":"Point"}
}