{
  "type": "Feature",
  "properties": {
    "addr:full":"Carrer de Raval (de), 18 Canonja Tarragona 43110",
    "addr:housenumber":"18",
    "addr:postcode":"43110",
    "addr:street":"Carrer De Raval De",
    "iso:country":"ES",
    "sg:address":"Carrer de Raval (de), 18",
    "sg:city":"Canonja",
    "sg:orig_category":"Droguer\u00cdas (al Por Menor)",
    "sg:phone":"+34 977 54 29 89",
    "sg:postcode":"43110",
    "sg:province":"Tarragona",
    "wof:name":"Martinez Fuentes Ramon",
    "wof:placetype":"venue"
},
  "geometry": {"coordinates":[1.1790230274,41.1225128174],"type":"Point"}
}