{
  "type": "Feature",
  "properties": {
    "addr:full":"Rua Castelao, 24 Grove Pontevedra 36980",
    "addr:housenumber":"24",
    "addr:postcode":"36980",
    "addr:street":"Rua Castelao;Grove Pontevedra",
    "iso:country":"ES",
    "sg:address":"Rua Castelao, 24",
    "sg:city":"Grove",
    "sg:orig_category":"Panader\u00cdas, Panader\u00cdas",
    "sg:phone":"+34 986 73 01 36",
    "sg:postcode":"36980",
    "sg:province":"Pontevedra",
    "wof:name":"Lorenzo Garcia Francisco",
    "wof:placetype":"venue"
},
  "geometry": {"coordinates":[-8.8619642258,42.4928627014],"type":"Point"}
}