{
  "type": "Feature",
  "properties": {
    "addr:full":"Pino, S/n San Cayetano Murcia 30592",
    "addr:housenumber":"s / n",
    "addr:postcode":"30592",
    "addr:street":"Pino",
    "iso:country":"ES",
    "sg:address":"Pino, S/n",
    "sg:city":"San Cayetano",
    "sg:orig_category":"Muebles Y Accesorios Para Cocinas Y Cuartos De Ba\u00d1o (al Por Menor)",
    "sg:phone":"+34 968 58 10 24",
    "sg:postcode":"30592",
    "sg:province":"Murcia",
    "wof:name":"Abellan Gomez Rafael",
    "wof:placetype":"venue"
},
  "geometry": {"coordinates":[-0.895038,37.816902],"type":"Point"}
}