{
  "type": "Feature",
  "properties": {
    "addr:full":"Camino De Camporredondo, 217 Cabue\u00f1es Asturias 33394",
    "addr:housenumber":"217",
    "addr:postcode":"33394",
    "addr:street":"Camino De Camporredondo;Asturias",
    "iso:country":"ES",
    "sg:address":"Camino De Camporredondo, 217",
    "sg:city":"Cabue\u00f1es",
    "sg:orig_category":"Agencias Y Agentes Comerciales, Representantes",
    "sg:phone":"+34 985 19 54 13",
    "sg:postcode":"33394",
    "sg:province":"Asturias",
    "wof:name":"Ca\u00f1as Y Baez S.l.",
    "wof:placetype":"venue"
},
  "geometry": {"coordinates":[-5.7123498917,43.5202293396],"type":"Point"}
}