{
  "type": "Feature",
  "properties": {
    "iso:country":"ES",
    "sg:address":"Avda Espa\u00d1a, 29",
    "sg:city":"Ponferrada",
    "sg:orig_category":"Zapatos (al Por Menor)",
    "sg:phone":"+34 987 42 92 64",
    "sg:postcode":"24400",
    "sg:province":"Le\u00f3n",
    "wof:name":"Uria Garcia Miguel Angel",
    "wof:placetype":"venue"
},
  "geometry": {"coordinates":[-6.6002697945,42.5475654602],"type":"Point"}
}