{
  "type": "Feature",
  "properties": {
    "addr:full":"Carrer de Muntaner, 227 Barcelona Barcelona 08021",
    "addr:housenumber":"227",
    "addr:postcode":"08021",
    "addr:street":"Carrer De Muntaner",
    "iso:country":"ES",
    "sg:address":"Carrer de Muntaner, 227",
    "sg:city":"Barcelona",
    "sg:orig_category":"Camiser\u00cda Y Ropa Interior Masculina (al Por Menor)",
    "sg:phone":"+34 932 01 08 49",
    "sg:postcode":"08021",
    "sg:province":"Barcelona",
    "wof:name":"Vinyals Vives Gloria",
    "wof:placetype":"venue"
},
  "geometry": {"coordinates":[2.1491589546,41.3942146301],"type":"Point"}
}