{
  "type": "Feature",
  "properties": {
    "addr:full":"Ctra Umbrete, S/n Bollullos Mitacion Sevilla 41110",
    "addr:housenumber":"s / n",
    "addr:postcode":"41110",
    "addr:street":"Ctra Umbrete",
    "iso:country":"ES",
    "sg:address":"Ctra Umbrete, S/n",
    "sg:city":"Bollullos Mitacion",
    "sg:orig_category":"Producci\u00d3n, Venta De Productos De Agricultura Biol\u00d3gica",
    "sg:phone":"+34 955 76 55 47",
    "sg:postcode":"41110",
    "sg:province":"Sevilla",
    "wof:name":"Torre Las Arcas S.l.",
    "wof:placetype":"venue"
},
  "geometry": {"coordinates":[-6.1381988525,37.3468666077],"type":"Point"}
}