{
  "type": "Feature",
  "properties": {
    "addr:full":"Calle de Castello, 81 Madrid Madrid 28006",
    "addr:housenumber":"81",
    "addr:postcode":"madrid;28006",
    "addr:street":"Calle De Castello",
    "iso:country":"ES",
    "sg:address":"Calle de Castello, 81",
    "sg:city":"Madrid",
    "sg:orig_category":"Mec\u00c1nico Del Autom\u00d3vil",
    "sg:phone":"+34 915 75 14 95",
    "sg:postcode":"28006",
    "sg:province":"Madrid",
    "wof:name":"Cardoso Cabezon Miguel",
    "wof:placetype":"venue"
},
  "geometry": {"coordinates":[-3.6810071468,40.4317779541],"type":"Point"}
}