{
  "type": "Feature",
  "properties": {
    "iso:country":"ES",
    "sg:address":"Rbla Marquesa De Castellbell, 71",
    "sg:city":"Sant Feliu Llobregat",
    "sg:orig_category":"Bisuter\u00cda, Joyer\u00cda, Relojer\u00cda (al Por Menor)",
    "sg:phone":"+34 936 66 63 87",
    "sg:postcode":"08980",
    "sg:province":"Barcelona",
    "wof:name":"Porras De La Torre Eva",
    "wof:placetype":"venue"
},
  "geometry": {"coordinates":[2.0489189625,41.3851852417],"type":"Point"}
}