{
  "type": "Feature",
  "properties": {
    "iso:country":"ES",
    "sg:address":"Calle de Profesor Saez, 8",
    "sg:city":"Salamanca",
    "sg:orig_category":"Quincaller\u00cda (al Por Menor)",
    "sg:phone":"+34 923 23 39 42",
    "sg:postcode":"37007",
    "sg:province":"Salamanca",
    "wof:name":"Trust Ii Cb.",
    "wof:placetype":"venue"
},
  "geometry": {"coordinates":[-5.6663160324,40.9699211121],"type":"Point"}
}