{
  "type": "Feature",
  "properties": {
    "addr:full":"Carr Sant Esteve, 52 Mao Islas Baleares 07703",
    "addr:housenumber":"52",
    "addr:postcode":"07703",
    "addr:street":"Carr Sant Esteve",
    "iso:country":"ES",
    "sg:address":"Carr Sant Esteve, 52",
    "sg:city":"Mao",
    "sg:orig_category":"Zapatos (al Por Menor)",
    "sg:phone":"+34 971 35 25 91",
    "sg:postcode":"07703",
    "sg:province":"Islas Baleares",
    "wof:name":"Real Florit Juana",
    "wof:placetype":"venue"
},
  "geometry": {"coordinates":[4.2550268173,39.8881454468],"type":"Point"}
}