{
  "type": "Feature",
  "properties": {
    "addr:full":"Calle de Villalba, 21 Poligono Industrial Los Villares Salamanca 37184",
    "addr:housenumber":"21",
    "addr:postcode":"37184",
    "addr:street":"Calle De Villalba;Industrial",
    "iso:country":"ES",
    "sg:address":"Calle de Villalba, 21",
    "sg:city":"Poligono Industrial Los Villares",
    "sg:orig_category":"Iluminaci\u00d3n Industrial, Alumbrado P\u00dablico: Material (fabricaci\u00d3n, Importaci\u00d3n)",
    "sg:phone":"+34 923 25 63 38",
    "sg:postcode":"37184",
    "sg:province":"Salamanca",
    "wof:name":"Etralux S.a.",
    "wof:placetype":"venue"
},
  "geometry": {"coordinates":[-5.6396541595,40.9895515442],"type":"Point"}
}