{
  "type": "Feature",
  "properties": {
    "addr:full":"Avda Murcia (de), S/n Jumilla Murcia 30520",
    "addr:housenumber":"/ n",
    "addr:postcode":"30520",
    "addr:street":"Avda Murcia De S",
    "iso:country":"ES",
    "sg:address":"Avda Murcia (de), S/n",
    "sg:city":"Jumilla",
    "sg:orig_category":"Chapister\u00cda",
    "sg:phone":"+34 968 78 35 32",
    "sg:postcode":"30520",
    "sg:province":"Murcia",
    "wof:name":"Gil Gonzalez Juan",
    "wof:placetype":"venue"
},
  "geometry": {"coordinates":[-1.3183139563,38.4740791321],"type":"Point"}
}