{
  "type": "Feature",
  "properties": {
    "iso:country":"ES",
    "sg:address":"Pase Habana, 5",
    "sg:city":"Madrid",
    "sg:orig_category":"Radiocomunicaciones, Telefon\u00cda M\u00d3vil, Radiomensajer\u00cda: Servicios, Comercializaci\u00d3n",
    "sg:phone":"+34 915 61 49 65",
    "sg:postcode":"28036",
    "sg:province":"Madrid",
    "wof:name":"J Creus & Asociados S.l.",
    "wof:placetype":"venue"
},
  "geometry": {"coordinates":[-3.6897449493,40.4484939575],"type":"Point"}
}