{
  "type": "Feature",
  "properties": {
    "iso:country":"ES",
    "sg:address":"Avda Romana (da), S/n",
    "sg:city":"Ramallosa",
    "sg:orig_category":"Promotores Constructores",
    "sg:phone":"+34 986 35 07 30",
    "sg:postcode":"36379",
    "sg:province":"Pontevedra",
    "sg:website":"www.viuconsa.com",
    "wof:name":"Viviendas Unifamiliares Y Construcciones S.a",
    "wof:placetype":"venue"
},
  "geometry": {"coordinates":[-8.8088216782,42.1167984009],"type":"Point"}
}