{
  "type": "Feature",
  "properties": {
    "iso:country":"ES",
    "sg:address":"Calle de Marques De La Hermida, 12",
    "sg:city":"Santander",
    "sg:orig_category":"Cajas De Ahorro",
    "sg:phone":"+34 942 36 03 00",
    "sg:postcode":"39009",
    "sg:province":"Cantabria",
    "wof:name":"Caixa D'estalvis I Pensions De Barcelona",
    "wof:placetype":"venue"
},
  "geometry": {"coordinates":[-3.813231945,43.4556884766],"type":"Point"}
}