{
  "type": "Feature",
  "properties": {
    "iso:country":"ES",
    "sg:address":"Calle de Reina Victoria, 11",
    "sg:city":"Almendralejo",
    "sg:orig_category":"Abogados",
    "sg:phone":"+34 924 66 06 77",
    "sg:postcode":"06200",
    "sg:province":"Badajoz",
    "wof:name":"Caballero Garcia Moreno Maria Del Pilar",
    "wof:placetype":"venue"
},
  "geometry": {"coordinates":[-6.409099102,38.6841201782],"type":"Point"}
}