{
  "type": "Feature",
  "properties": {
    "addr:full":"Calle de Logro\u00d1o, 7 Donostia-san Sebastian Guip\u00f9zcoa 20018",
    "addr:housenumber":"7",
    "addr:postcode":"20018",
    "addr:street":"Calle De Logron\u0303O",
    "iso:country":"ES",
    "sg:address":"Calle de Logro\u00d1o, 7",
    "sg:city":"Donostia-san Sebastian",
    "sg:orig_category":"Ingenier\u00cda, Centros De Estudios (diversos)",
    "sg:phone":"+34 943 31 21 23",
    "sg:postcode":"20018",
    "sg:province":"Guip\u00f9zcoa",
    "wof:name":"Miner Urdampilleta Miguel Maria",
    "wof:placetype":"venue"
},
  "geometry": {"coordinates":[-2.0072479248,43.3136863708],"type":"Point"}
}