{
  "type": "Feature",
  "properties": {
    "iso:country":"ES",
    "sg:address":"Carr Andreu Coll, Glosador, 10",
    "sg:city":"Soller",
    "sg:orig_category":"Guarder\u00cdas",
    "sg:phone":"+34 971 63 42 21",
    "sg:postcode":"07100",
    "sg:province":"Islas Baleares",
    "wof:name":"Crespi Isern Catalina",
    "wof:placetype":"venue"
},
  "geometry": {"coordinates":[2.7147779465,39.7659072876],"type":"Point"}
}