{
  "type": "Feature",
  "properties": {
    "addr:full":"Carrer de Jaume Balmes, 2 Viladecans Barcelona 08840",
    "addr:housenumber":"2",
    "addr:postcode":"08840",
    "addr:street":"Carrer De Jaume Balmes",
    "iso:country":"ES",
    "sg:address":"Carrer de Jaume Balmes, 2",
    "sg:city":"Viladecans",
    "sg:orig_category":"Protecci\u00d3n Contra Incendios: Material, Instalaci\u00d3n, Mantenimiento",
    "sg:phone":"+34 936 59 41 00",
    "sg:postcode":"08840",
    "sg:province":"Barcelona",
    "wof:name":"Grupo Pimexa S.l.",
    "wof:placetype":"venue"
},
  "geometry": {"coordinates":[2.022010088,41.3154296875],"type":"Point"}
}