{
  "type": "Feature",
  "properties": {
    "iso:country":"ES",
    "sg:address":"Carr Sequia De Mestalla, 5",
    "sg:city":"Picanya",
    "sg:orig_category":"Inform\u00c1tica Equipo Y Programas (al Por Mayor)",
    "sg:phone":"+34 961 59 42 90",
    "sg:postcode":"46210",
    "sg:province":"Valencia",
    "sg:website":"www.powercase.es",
    "wof:name":"Power Case Iberica S.l.",
    "wof:placetype":"venue"
},
  "geometry": {"coordinates":[-0.4349240065,39.4362945557],"type":"Point"}
}