{
  "type": "Feature",
  "properties": {
    "addr:full":"Calle de Alcalde Prospero Casta\u00d1o, 5 San Juan De Aznalfarache Sevilla 41920",
    "addr:housenumber":"5",
    "addr:postcode":"41920",
    "addr:street":"Calle De Alcalde Prospero Castan\u0303O",
    "iso:country":"ES",
    "sg:address":"Calle de Alcalde Prospero Casta\u00d1o, 5",
    "sg:city":"San Juan De Aznalfarache",
    "sg:orig_category":"Ropa Para Se\u00d1oras (al Por Menor)",
    "sg:phone":"+34 954 76 91 02",
    "sg:postcode":"41920",
    "sg:province":"Sevilla",
    "wof:name":"Gonzalez Y Fermin S. L.",
    "wof:placetype":"venue"
},
  "geometry": {"coordinates":[-6.0353827477,37.3575782776],"type":"Point"}
}