{
  "type": "Feature",
  "properties": {
    "addr:full":"Eduardo Gonzalez Pastrana, 4 Trobajo Camino Le\u00f3n 24010",
    "addr:housenumber":"4",
    "addr:postcode":"24010",
    "addr:street":"Eduardo Gonzalez Pastrana;Camino Leo\u0301N",
    "iso:country":"ES",
    "sg:address":"Eduardo Gonzalez Pastrana, 4",
    "sg:city":"Trobajo Camino",
    "sg:orig_category":"Frutas, Legumbres Frescas Y Tempranas (al Por Menor)",
    "sg:phone":"+34 987 80 01 70",
    "sg:postcode":"24010",
    "sg:province":"Le\u00f3n",
    "wof:name":"Lopez Crespo Nicolas",
    "wof:placetype":"venue"
},
  "geometry": {"coordinates":[-5.6080431938,42.595199585],"type":"Point"}
}