{
  "type": "Feature",
  "properties": {
    "iso:country":"ES",
    "sg:address":"Carrer de Balcells, 17",
    "sg:city":"Barcelona",
    "sg:orig_category":"Importaci\u00d3n",
    "sg:phone":"+34 932 10 46 01",
    "sg:postcode":"08024",
    "sg:province":"Barcelona",
    "wof:name":"Domenjo Santoll Gabriel",
    "wof:placetype":"venue"
},
  "geometry": {"coordinates":[2.159555912,41.4104690552],"type":"Point"}
}