{
  "type": "Feature",
  "properties": {
    "iso:country":"ES",
    "sg:address":"Avda Compostela, 7",
    "sg:city":"Boiro",
    "sg:orig_category":"Imprenta",
    "sg:phone":"+34 981 84 72 80",
    "sg:postcode":"15930",
    "sg:province":"La Coru\u00f1a",
    "wof:name":"Cucadas Boiro S.l.",
    "wof:placetype":"venue"
},
  "geometry": {"coordinates":[-8.8905200958,42.6451950073],"type":"Point"}
}