{
  "type": "Feature",
  "properties": {
    "addr:full":"Atvia De Logro\u00f1o, S/n Zaragoza Zaragoza 50011",
    "addr:housenumber":"s / n",
    "addr:postcode":"50011",
    "iso:country":"ES",
    "sg:address":"Atvia De Logro\u00f1o, S/n",
    "sg:city":"Zaragoza",
    "sg:orig_category":"M\u00c9dicos: Radioterapia (radioterapia Como Opci\u00d3n Oncol\u00d3gica)",
    "sg:phone":"+34 976 33 64 46",
    "sg:postcode":"50011",
    "sg:province":"Zaragoza",
    "wof:name":"Gimenez Parres Luis",
    "wof:placetype":"venue"
},
  "geometry": {"coordinates":[-0.9913589954,41.662853241],"type":"Point"}
}