{
  "type": "Feature",
  "properties": {
    "addr:full":"Calle de Paz, 48 Valencia Valencia 46...",
    "addr:housenumber":"48",
    "addr:street":"Calle De Paz;Valencia",
    "iso:country":"ES",
    "sg:address":"Calle de Paz, 48",
    "sg:city":"Valencia",
    "sg:orig_category":"Oficinas De Turismo, Asociaciones De Iniciativa",
    "sg:phone":"+34 963 98 64 22",
    "sg:postcode":"46...",
    "sg:province":"Valencia",
    "sg:website":"www.comunidad-valenciana.com",
    "wof:name":"Generalitat Valenciana",
    "wof:placetype":"venue"
},
  "geometry": {"coordinates":[-0.3769130111,39.4687919617],"type":"Point"}
}