{
  "type": "Feature",
  "properties": {
    "addr:full":"Carrer de Comte D'urgell, 259 Barcelona Barcelona 08036",
    "addr:housenumber":"259",
    "addr:postcode":"08036",
    "addr:street":"Carrer De Comte D'Urgell",
    "iso:country":"ES",
    "sg:address":"Carrer de Comte D'urgell, 259",
    "sg:city":"Barcelona",
    "sg:orig_category":"Asociaciones, Organismos Culturales Y Socioeducativos",
    "sg:phone":"+34 933 21 22 59",
    "sg:postcode":"08036",
    "sg:province":"Barcelona",
    "wof:name":"Institut Catala D'antropologia",
    "wof:placetype":"venue"
},
  "geometry": {"coordinates":[2.1454391479,41.3920516968],"type":"Point"}
}