{
  "type": "Feature",
  "properties": {
    "iso:country":"ES",
    "sg:address":"Calle de Arturo Soria, 55",
    "sg:city":"Madrid",
    "sg:orig_category":"Promotores Constructores",
    "sg:phone":"+34 914 07 67 36",
    "sg:postcode":"28027",
    "sg:province":"Madrid",
    "wof:name":"Zalduegui Guisasola Beatriz Ana",
    "wof:placetype":"venue"
},
  "geometry": {"coordinates":[-3.6444292068,40.4442672729],"type":"Point"}
}