{
  "type": "Feature",
  "properties": {
    "iso:country":"ES",
    "sg:address":"Plaz Callao (del), 6",
    "sg:city":"Mazarron",
    "sg:orig_category":"Carnicer\u00cdas, Carnicer\u00cdas",
    "sg:phone":"+34 968 59 01 60",
    "sg:postcode":"30870",
    "sg:province":"Murcia",
    "wof:name":"Raja Hernandez Fernando",
    "wof:placetype":"venue"
},
  "geometry": {"coordinates":[-1.31378901,37.598865509],"type":"Point"}
}