{
  "type": "Feature",
  "properties": {
    "iso:country":"ES",
    "sg:address":"Luga Playa De Oza, 54",
    "sg:city":"Casablanca",
    "sg:orig_category":"Navegaci\u00d3n (equipos De Pesca)",
    "sg:phone":"+34 981 28 44 80",
    "sg:postcode":"15006",
    "sg:province":"La Coru\u00f1a",
    "wof:name":"Pesquera Carpa S. A.",
    "wof:placetype":"venue"
},
  "geometry": {"coordinates":[-8.3964595795,43.3701095581],"type":"Point"}
}