{
  "type": "Feature",
  "properties": {
    "iso:country":"ES",
    "sg:address":"Avda Doctor Manuel Jarabo (del), 20",
    "sg:city":"S. Martin Vega",
    "sg:orig_category":"Productos Fitosanitarios (negocio, Aplicaci\u00d3n)",
    "sg:phone":"+34 918 94 59 62",
    "sg:postcode":"28330",
    "sg:province":"Madrid",
    "wof:name":"Caba\u00f1as Moreno Mercedes",
    "wof:placetype":"venue"
},
  "geometry": {"coordinates":[-3.5740170479,40.2106437683],"type":"Point"}
}