{
  "type": "Feature",
  "properties": {
    "iso:country":"ES",
    "sg:address":"Rbla Principal, 30",
    "sg:city":"Vilanova I La Geltru",
    "sg:orig_category":"Confecci\u00d3n De Paraguas, De Sombrillas Y De Bastones",
    "sg:phone":"+34 938 93 56 17",
    "sg:postcode":"08800",
    "sg:province":"Barcelona",
    "wof:name":"Rodriguez Rodriguez Esperanza",
    "wof:placetype":"venue"
},
  "geometry": {"coordinates":[1.7244809866,41.2245941162],"type":"Point"}
}