{
  "type": "Feature",
  "properties": {
    "iso:country":"ES",
    "sg:address":"Ctra Nacional 620, S/n",
    "sg:city":"Cubillas De Santa Marta",
    "sg:orig_category":"Distribuci\u00d3n De Petr\u00d3leo Y Derivados",
    "sg:phone":"+34 983 58 50 38",
    "sg:postcode":"47290",
    "sg:province":"Valladolid",
    "wof:name":"E.s. Bertran S.a.",
    "wof:placetype":"venue"
},
  "geometry": {"coordinates":[-4.6137828827,41.8332290649],"type":"Point"}
}