{
  "type": "Feature",
  "properties": {
    "addr:full":"Ipe\u00d1arrieta Kalea, 24 Urretxu Guip\u00f9zcoa 20700",
    "addr:housenumber":"24",
    "addr:postcode":"20700",
    "addr:street":"Ipen\u0303Arrieta Kalea;Guipu\u0300Zcoa",
    "iso:country":"ES",
    "sg:address":"Ipe\u00d1arrieta Kalea, 24",
    "sg:city":"Urretxu",
    "sg:orig_category":"Carnicer\u00cdas, Carnicer\u00cdas",
    "sg:phone":"+34 943 72 51 33",
    "sg:postcode":"20700",
    "sg:province":"Guip\u00f9zcoa",
    "wof:name":"Purificacion Kalabor Prieto",
    "wof:placetype":"venue"
},
  "geometry": {"coordinates":[-2.3217520714,43.087097168],"type":"Point"}
}