{
  "type": "Feature",
  "properties": {
    "iso:country":"ES",
    "sg:address":"Calle de Eusebio Revilla, 14",
    "sg:city":"Arevalo",
    "sg:orig_category":"Servicios Gsm",
    "sg:phone":"+34 920 30 15 52",
    "sg:postcode":"05200",
    "sg:province":"\u00c1vila",
    "wof:name":"Gonzalez Garrido Estela",
    "wof:placetype":"venue"
},
  "geometry": {"coordinates":[-4.7186489105,41.0619392395],"type":"Point"}
}