{
  "type": "Feature",
  "properties": {
    "iso:country":"ES",
    "sg:address":"Calle de Eras, 10",
    "sg:city":"Montesclaros",
    "sg:orig_category":"M\u00c1rmoles, Granitos Y Piedras Naturales",
    "sg:phone":"+34 925 86 84 03",
    "sg:postcode":"45620",
    "sg:province":"Toledo",
    "wof:name":"Marmoles Toledanos S. L.",
    "wof:placetype":"venue"
},
  "geometry": {"coordinates":[-4.9384698868,40.106628418],"type":"Point"}
}