{
  "type": "Feature",
  "properties": {
    "iso:country":"ES",
    "sg:address":"Calle de Ortega Y Gasset, 3",
    "sg:city":"Zumaia",
    "sg:orig_category":"Frutas Y Legumbres Frescas (al Por Mayor)",
    "sg:phone":"+34 943 14 32 85",
    "sg:postcode":"20750",
    "sg:province":"Guip\u00f9zcoa",
    "wof:name":"Maria Jose Gomez Idalgo",
    "wof:placetype":"venue"
},
  "geometry": {"coordinates":[-2.2561159134,43.298576355],"type":"Point"}
}