{
  "type": "Feature",
  "properties": {
    "iso:country":"ES",
    "sg:address":"Cmno San Sebastian (de), 7",
    "sg:city":"Boadilla Del Monte",
    "sg:orig_category":"Grafistas",
    "sg:phone":"+34 916 32 61 81",
    "sg:postcode":"28660",
    "sg:province":"Madrid",
    "wof:name":"Nubeo S.l.",
    "wof:placetype":"venue"
},
  "geometry": {"coordinates":[-3.8775029182,40.4062538147],"type":"Point"}
}