{
  "type": "Feature",
  "properties": {
    "addr:full":"Carrer de Torrijos, 9 Barcelona Barcelona 08012",
    "addr:housenumber":"9",
    "addr:postcode":"08012",
    "addr:street":"Carrer De Torrijos",
    "iso:country":"ES",
    "sg:address":"Carrer de Torrijos, 9",
    "sg:city":"Barcelona",
    "sg:orig_category":"Mercer\u00cda, Lencer\u00cda (al Por Menor)",
    "sg:phone":"+34 932 13 57 92",
    "sg:postcode":"08012",
    "sg:province":"Barcelona",
    "wof:name":"Lafuente Alda Pilar",
    "wof:placetype":"venue"
},
  "geometry": {"coordinates":[2.1593039036,41.4027290344],"type":"Point"}
}