{
  "type": "Feature",
  "properties": {
    "iso:country":"ES",
    "sg:address":"Calle de Ganguren Mendi, 1",
    "sg:city":"Basauri",
    "sg:orig_category":"Empresarios",
    "sg:phone":"+34 944 40 74 36",
    "sg:postcode":"48970",
    "sg:province":"Vizcaya",
    "wof:name":"Jose Fernando Perez Alonso - Tevisan",
    "wof:placetype":"venue"
},
  "geometry": {"coordinates":[-2.8883090019,43.2248954773],"type":"Point"}
}