{
  "type": "Feature",
  "properties": {
    "iso:country":"ES",
    "sg:address":"Calle de Bomba (la), 4",
    "sg:city":"Monzalbarba",
    "sg:orig_category":"Herramientas Manuales (fabricaci\u00d3n, Al Por Mayor)",
    "sg:phone":"+34 976 46 22 11",
    "sg:postcode":"50120",
    "sg:province":"Zaragoza",
    "wof:name":"Professional Tools I Accesories S.l.",
    "wof:placetype":"venue"
},
  "geometry": {"coordinates":[-0.9719756246,41.7014808655],"type":"Point"}
}