{
  "type": "Feature",
  "properties": {
    "iso:country":"ES",
    "sg:address":"D (pol Ind Brenes), 99",
    "sg:city":"Carmona",
    "sg:orig_category":"Empresas De Carpinter\u00cda Met\u00c1lica",
    "sg:phone":"+34 954 14 26 51",
    "sg:postcode":"41410",
    "sg:province":"Sevilla",
    "wof:name":"Falcon Mesa Juan",
    "wof:placetype":"venue"
},
  "geometry": {"coordinates":[-5.644464016,37.4767036438],"type":"Point"}
}