{
  "type": "Feature",
  "properties": {
    "addr:full":"La Laguna, 228 Los Llanos Aridane Santa Cruz De Tenerife 38760",
    "addr:housenumber":"228",
    "addr:postcode":"38760",
    "addr:street":"La Laguna",
    "iso:country":"ES",
    "sg:address":"La Laguna, 228",
    "sg:city":"Los Llanos Aridane",
    "sg:orig_category":"Alquiler De Veh\u00cdculos: Turismos Y Utilitarios",
    "sg:phone":"+34 922 46 18 19",
    "sg:postcode":"38760",
    "sg:province":"Santa Cruz De Tenerife",
    "wof:name":"Nguyen Weinrich S.l.",
    "wof:placetype":"venue"
},
  "geometry": {"coordinates":[-17.9085597992,28.6563796997],"type":"Point"}
}