{
  "type": "Feature",
  "properties": {
    "iso:country":"ES",
    "sg:address":"Calle de Alonso Heredia, 5",
    "sg:city":"Madrid",
    "sg:orig_category":"Equipo De Refrigeraci\u00d3n Industrial",
    "sg:phone":"+34 913 56 25 82",
    "sg:postcode":"28028",
    "sg:province":"Madrid",
    "wof:name":"Ingenieria Frigorifica Dam S. L.",
    "wof:placetype":"venue"
},
  "geometry": {"coordinates":[-3.6734097004,40.4350624084],"type":"Point"}
}