{
  "type": "Feature",
  "properties": {
    "iso:country":"ES",
    "sg:address":"Calle de Jose Abascal, 20",
    "sg:city":"Madrid",
    "sg:orig_category":"Promotores Constructores",
    "sg:phone":"+34 914 41 19 81",
    "sg:postcode":"28003",
    "sg:province":"Madrid",
    "wof:name":"Martos  Marcelino",
    "wof:placetype":"venue"
},
  "geometry": {"coordinates":[-3.6970510483,40.4381752014],"type":"Point"}
}