{
  "type": "Feature",
  "properties": {
    "addr:full":"Rond Teruel, 40 Alca\u00f1iz Teruel 44600",
    "addr:housenumber":"40",
    "addr:postcode":"44600",
    "addr:street":"Teruel",
    "iso:country":"ES",
    "sg:address":"Rond Teruel, 40",
    "sg:city":"Alca\u00f1iz",
    "sg:orig_category":"Chapister\u00cda",
    "sg:phone":"+34 978 83 28 72",
    "sg:postcode":"44600",
    "sg:province":"Teruel",
    "wof:name":"Martinez Celma Manuel Enrique",
    "wof:placetype":"venue"
},
  "geometry": {"coordinates":[-0.1312530041,41.0451965332],"type":"Point"}
}