{
  "type": "Feature",
  "properties": {
    "addr:full":"Calle de Andalucia, 15 Palencia Palencia 34004",
    "addr:housenumber":"15",
    "addr:postcode":"34004",
    "addr:street":"Calle De Andalucia",
    "iso:country":"ES",
    "sg:address":"Calle de Andalucia, 15",
    "sg:city":"Palencia",
    "sg:orig_category":"Electricidad Veh\u00cdculo",
    "sg:phone":"+34 979 71 23 19",
    "sg:postcode":"34004",
    "sg:province":"Palencia",
    "wof:name":"Talleres Cachi S.l.",
    "wof:placetype":"venue"
},
  "geometry": {"coordinates":[-4.5152111053,42.006111145],"type":"Point"}
}