{
  "type": "Feature",
  "properties": {
    "addr:full":"Calle de Nueva, 15 Motril Granada 18600",
    "addr:housenumber":"15",
    "addr:postcode":"18600",
    "addr:street":"Calle De Nueva",
    "iso:country":"ES",
    "sg:address":"Calle de Nueva, 15",
    "sg:city":"Motril",
    "sg:orig_category":"\u00d3ptica: Instrumentos (fabricaci\u00d3n)",
    "sg:phone":"+34 958 83 33 67",
    "sg:postcode":"18600",
    "sg:province":"Granada",
    "wof:name":"Oculalia S.l",
    "wof:placetype":"venue"
},
  "geometry": {"coordinates":[-3.517282486,36.7460594177],"type":"Point"}
}