{
  "type": "Feature",
  "properties": {
    "iso:country":"ES",
    "sg:address":"Poli Pol.indust. El Segre, S/n",
    "sg:city":"Lleida",
    "sg:orig_category":"Maquinaria Para Industrias Diversas",
    "sg:phone":"+34 973 21 16 15",
    "sg:postcode":"25191",
    "sg:province":"Lleida",
    "wof:name":"Motortrans S.a.",
    "wof:placetype":"venue"
},
  "geometry": {"coordinates":[0.6831650138,41.5832138062],"type":"Point"}
}