{
  "type": "Feature",
  "properties": {
    "addr:full":"Calle de Colon, 46 Pozo Ca\u00e7ada Albacete 02510",
    "addr:housenumber":"46",
    "addr:postcode":"02510",
    "addr:street":"Calle De Colon",
    "iso:country":"ES",
    "sg:address":"Calle de Colon, 46",
    "sg:city":"Pozo Ca\u00e7ada",
    "sg:orig_category":"Alimentaci\u00d3n General (al Por Menor)",
    "sg:phone":"+34 967 25 00 31",
    "sg:postcode":"02510",
    "sg:province":"Albacete",
    "wof:name":"Garcia Garcia Diego",
    "wof:placetype":"venue"
},
  "geometry": {"coordinates":[-1.8600701094,38.9976501465],"type":"Point"}
}