{
  "type": "Feature",
  "properties": {
    "iso:country":"ES",
    "sg:address":"Carrer de Santiago, 20",
    "sg:city":"Montcada Centre",
    "sg:orig_category":"Agencias Y Agentes Comerciales, Representantes",
    "sg:phone":"+34 935 65 08 69",
    "sg:postcode":"08110",
    "sg:province":"Barcelona",
    "wof:name":"Map 2 Comercial S.l.",
    "wof:placetype":"venue"
},
  "geometry": {"coordinates":[2.1817660332,41.4890899658],"type":"Point"}
}