{
  "type": "Feature",
  "properties": {
    "iso:country":"ES",
    "sg:address":"Santa Lucia, 15",
    "sg:city":"Iglesia",
    "sg:orig_category":"Veh\u00cdculos De Ocasi\u00d3n",
    "sg:phone":"+34 986 74 30 73",
    "sg:postcode":"36967",
    "sg:province":"Pontevedra",
    "wof:name":"Talleres Loyca S.l.",
    "wof:placetype":"venue"
},
  "geometry": {"coordinates":[-8.8113698959,42.4530296326],"type":"Point"}
}