{
  "type": "Feature",
  "properties": {
    "iso:country":"ES",
    "sg:address":"Pla\u00c7 Sant Faust, 1",
    "sg:city":"Alguaire",
    "sg:orig_category":"Asesor\u00cda Fiscal Y Jur\u00cddica",
    "sg:phone":"+34 973 75 69 20",
    "sg:postcode":"25125",
    "sg:province":"Lleida",
    "wof:name":"Vila Galan Assesors S.l.",
    "wof:placetype":"venue"
},
  "geometry": {"coordinates":[0.5873860121,41.7410583496],"type":"Point"}
}