{
  "type": "Feature",
  "properties": {
    "addr:full":"Calle de Pintor Mauro Ortiz De Urbina, 3 Vitoria-gasteiz \u00c1lava 01008",
    "addr:housenumber":"3",
    "addr:postcode":"01008",
    "addr:street":"Calle De Pintor Mauro Ortiz De Urbina",
    "iso:country":"ES",
    "sg:address":"Calle de Pintor Mauro Ortiz De Urbina, 3",
    "sg:city":"Vitoria-gasteiz",
    "sg:orig_category":"M\u00c9dicos: Estomatolog\u00cda",
    "sg:phone":"+34 945 22 35 82",
    "sg:postcode":"01008",
    "sg:province":"\u00c1lava",
    "wof:name":"Arbocco Mendoza Andres",
    "wof:placetype":"venue"
},
  "geometry": {"coordinates":[-2.685406208,42.8496856689],"type":"Point"}
}