{
  "type": "Feature",
  "properties": {
    "iso:country":"ES",
    "sg:address":"Carr Joan Del Rei, 15",
    "sg:city":"Lleida",
    "sg:orig_category":"Fabricaci\u00d3n, Distribuci\u00d3n De Material Para La Climatizaci\u00d3n, Aireaci\u00d3n Y Ventilaci\u00d3n",
    "sg:phone":"+34 973 24 41 36",
    "sg:postcode":"25005",
    "sg:province":"Lleida",
    "wof:name":"Lopez Cruz Jose",
    "wof:placetype":"venue"
},
  "geometry": {"coordinates":[0.6272159815,41.638217926],"type":"Point"}
}