{
  "type": "Feature",
  "properties": {
    "iso:country":"ES",
    "sg:address":"Ctra Santos, S/n",
    "sg:city":"Zafra",
    "sg:orig_category":"Centros De Salud",
    "sg:phone":"+34 924 55 27 55",
    "sg:postcode":"06300",
    "sg:province":"Badajoz",
    "wof:name":"Centro Medico Quirurgico Zafra S.l.",
    "wof:placetype":"venue"
},
  "geometry": {"coordinates":[-6.4107542038,38.4337234497],"type":"Point"}
}