{
  "type": "Feature",
  "properties": {
    "iso:country":"ES",
    "sg:address":"Avda Matapi\u00d1onera, 7",
    "sg:city":"San Sebastian De Los Reyes",
    "sg:orig_category":"Inversiones",
    "sg:phone":"+34 916 51 21 96",
    "sg:postcode":"28700",
    "sg:province":"Madrid",
    "wof:name":"Invafi S.a.",
    "wof:placetype":"venue"
},
  "geometry": {"coordinates":[-3.6183269024,40.5473403931],"type":"Point"}
}