{
  "type": "Feature",
  "properties": {
    "addr:full":"Carr Concepcio, 15 Figueres Girona 17600",
    "addr:housenumber":"15",
    "addr:postcode":"17600",
    "addr:street":"Carr Concepcio",
    "iso:country":"ES",
    "sg:address":"Carr Concepcio, 15",
    "sg:city":"Figueres",
    "sg:orig_category":"Herboristas (al Por Menor)",
    "sg:phone":"+34 972 67 23 56",
    "sg:postcode":"17600",
    "sg:province":"Girona",
    "wof:name":"Gomez Perez Maria Luisa",
    "wof:placetype":"venue"
},
  "geometry": {"coordinates":[2.9647469521,42.2671775818],"type":"Point"}
}