{
  "type": "Feature",
  "properties": {
    "addr:full":"Calle de Pablo Iglesias B, 6 Torreperogil Ja\u00e9n 23320",
    "addr:housenumber":"6",
    "addr:postcode":"23320",
    "addr:street":"Calle De Pablo Iglesias B",
    "iso:country":"ES",
    "sg:address":"Calle de Pablo Iglesias B, 6",
    "sg:city":"Torreperogil",
    "sg:orig_category":"Centros De Coordinaci\u00d3n",
    "sg:phone":"+34 953 77 72 31",
    "sg:postcode":"23320",
    "sg:province":"Ja\u00e9n",
    "wof:name":"Foronda Figueroa Jose Antonio",
    "wof:placetype":"venue"
},
  "geometry": {"coordinates":[-3.2891230583,38.0311737061],"type":"Point"}
}