{
  "type": "Feature",
  "properties": {
    "addr:full":"Avda Libertad (la), 100 Navatejera Le\u00f3n 24008",
    "addr:housenumber":"100",
    "addr:postcode":"24008",
    "addr:street":"Avda Libertad La;Leo\u0301N",
    "iso:country":"ES",
    "sg:address":"Avda Libertad (la), 100",
    "sg:city":"Navatejera",
    "sg:orig_category":"Promotores Constructores",
    "sg:phone":"+34 987 28 63 48",
    "sg:postcode":"24008",
    "sg:province":"Le\u00f3n",
    "sg:website":"www.paginasamarillas.es",
    "wof:name":"Construcciones Navaleon S.l.",
    "wof:placetype":"venue"
},
  "geometry": {"coordinates":[-5.5637359619,42.623085022],"type":"Point"}
}