{
  "type": "Feature",
  "properties": {
    "addr:full":"Calle de Telleria, 1 Bilbao Vizcaya 48004",
    "addr:housenumber":"1",
    "addr:postcode":"48004",
    "addr:street":"Calle De Telleria",
    "iso:country":"ES",
    "sg:address":"Calle de Telleria, 1",
    "sg:city":"Bilbao",
    "sg:orig_category":"Acero: Productos Sider\u00dargicos Y Transformados (fabricaci\u00d3n, Negocio)",
    "sg:phone":"+34 944 11 21 00",
    "sg:postcode":"48004",
    "sg:province":"Vizcaya",
    "sg:website":"www.sabo.es",
    "wof:name":"Sociedad Santa Ana De Bolueta S. A.",
    "wof:placetype":"venue"
},
  "geometry": {"coordinates":[-2.9025497437,43.2481231689],"type":"Point"}
}