{
  "type": "Feature",
  "properties": {
    "addr:full":"Calle de Real, 21 Ceuta Ceuta 51001",
    "addr:housenumber":"21",
    "addr:postcode":"51001",
    "addr:street":"Calle De Real",
    "iso:country":"ES",
    "sg:address":"Calle de Real, 21",
    "sg:city":"Ceuta",
    "sg:orig_category":"Bisuter\u00cda, Joyer\u00cda, Relojer\u00cda (al Por Menor)",
    "sg:phone":"+34 956 51 76 41",
    "sg:postcode":"51001",
    "sg:province":"Ceuta",
    "wof:name":"Ruiz Lazo Juan",
    "wof:placetype":"venue"
},
  "geometry": {"coordinates":[-5.3064408302,35.887928009],"type":"Point"}
}