{
  "type": "Feature",
  "properties": {
    "addr:full":"Calle de Merindades De Castilla, 14 Villarcayo Burgos 09550",
    "addr:housenumber":"14",
    "addr:postcode":"09550",
    "addr:street":"Calle De Merindades De Castilla",
    "iso:country":"ES",
    "sg:address":"Calle de Merindades De Castilla, 14",
    "sg:city":"Villarcayo",
    "sg:orig_category":"Plomeros",
    "sg:phone":"+34 947 13 23 53",
    "sg:postcode":"09550",
    "sg:province":"Burgos",
    "wof:name":"Fontaneriacalefaccionunidos S.c.",
    "wof:placetype":"venue"
},
  "geometry": {"coordinates":[-3.5752389431,42.938331604],"type":"Point"}
}