{
  "type": "Feature",
  "properties": {
    "iso:country":"ES",
    "sg:address":"Rua Reyes Catolicos, 20",
    "sg:city":"Solana",
    "sg:orig_category":"Caf\u00c9s, Bares, Cervecer\u00cdas",
    "sg:phone":"+34 981 39 22 76",
    "sg:postcode":"15570",
    "sg:province":"A Coru\u00f1a",
    "wof:name":"Sertel Atlantico S.l.",
    "wof:placetype":"venue"
},
  "geometry": {"coordinates":[-8.1647539139,43.5165405273],"type":"Point"}
}