{
  "type": "Feature",
  "properties": {
    "addr:full":"Calle de Mayor, 26 Moratalla Murcia 30440",
    "addr:housenumber":"26",
    "addr:postcode":"30440",
    "addr:street":"Calle De Mayor",
    "iso:country":"ES",
    "sg:address":"Calle de Mayor, 26",
    "sg:city":"Moratalla",
    "sg:orig_category":"Bordado, Marcado A Medida",
    "sg:phone":"+34 968 70 61 67",
    "sg:postcode":"30440",
    "sg:province":"Murcia",
    "wof:name":"Lopez Marin Antonio",
    "wof:placetype":"venue"
},
  "geometry": {"coordinates":[-1.893903017,38.1904296875],"type":"Point"}
}