{
  "type": "Feature",
  "properties": {
    "addr:full":"Ctra Navalmorales, Km. 0051,6 Navahermosa Toledo 45150",
    "addr:postcode":"45150",
    "addr:street":"Ctra Navalmorales Km. 0051,6",
    "iso:country":"ES",
    "sg:address":"Ctra Navalmorales, Km. 0051,6",
    "sg:city":"Navahermosa",
    "sg:orig_category":"Alimentaci\u00d3n General (al Por Mayor)",
    "sg:phone":"+34 925 41 04 15",
    "sg:postcode":"45150",
    "sg:province":"Toledo",
    "wof:name":"Cooperativa De Piensos Vallunco",
    "wof:placetype":"venue"
},
  "geometry": {"coordinates":[-4.4761991501,39.6348190308],"type":"Point"}
}