{
  "type": "Feature",
  "properties": {
    "iso:country":"ES",
    "sg:address":"Chacel, 6",
    "sg:city":"Melilla",
    "sg:orig_category":"Ropa Para Se\u00d1oras (al Por Menor)",
    "sg:phone":"+34 952 68 14 26",
    "sg:postcode":"52001",
    "sg:province":"Melilla",
    "wof:name":"Baltasar Martin E Hijos S. A.",
    "wof:placetype":"venue"
},
  "geometry": {"coordinates":[-2.9512500763,35.3091583252],"type":"Point"}
}