{
  "type": "Feature",
  "properties": {
    "addr:full":"Plaz Miranda (de La), 6 Palencia Palencia 34003",
    "addr:postcode":"34003",
    "iso:country":"ES",
    "sg:address":"Plaz Miranda (de La), 6",
    "sg:city":"Palencia",
    "sg:orig_category":"Molduras, Junquillos, Listones Y Molduras Perforadas",
    "sg:phone":"+34 979 17 02 44",
    "sg:postcode":"34003",
    "sg:province":"Palencia",
    "wof:name":"Calleja Pastor Julian",
    "wof:placetype":"venue"
},
  "geometry": {"coordinates":[-4.5394940376,42.0234832764],"type":"Point"}
}