{
  "type": "Feature",
  "properties": {
    "iso:country":"ES",
    "sg:address":"Carr Matematic Marzal, 8",
    "sg:city":"Sueca",
    "sg:orig_category":"Reposter\u00cdas",
    "sg:phone":"+34 961 70 08 50",
    "sg:postcode":"46410",
    "sg:province":"Valencia",
    "wof:name":"Panificadora De Sueca S.l.",
    "wof:placetype":"venue"
},
  "geometry": {"coordinates":[-0.3025290072,39.2053108215],"type":"Point"}
}