{
  "type": "Feature",
  "properties": {
    "iso:country":"ES",
    "sg:address":"Avda Valladolid, 42",
    "sg:city":"Tudela Duero",
    "sg:orig_category":"Transportes Por V\u00cdas Navegables",
    "sg:phone":"+34 983 52 01 76",
    "sg:postcode":"47320",
    "sg:province":"Valladolid",
    "wof:name":"Pe\u00f1alba Reinoso Mariano",
    "wof:placetype":"venue"
},
  "geometry": {"coordinates":[-4.5839958191,41.5874481201],"type":"Point"}
}