{
  "type": "Feature",
  "properties": {
    "iso:country":"ES",
    "sg:address":"Calle de Teniente Carrer de Castillo Olivares, S/n",
    "sg:city":"Palmas De Gran Canaria",
    "sg:orig_category":"Arquitectos",
    "sg:phone":"+34 928 25 17 05",
    "sg:postcode":"35011",
    "sg:province":"Las Palmas",
    "wof:name":"Medina Hernandez Ulises",
    "wof:placetype":"venue"
},
  "geometry": {"coordinates":[-15.4350242615,28.1238803864],"type":"Point"}
}