{
  "type": "Feature",
  "properties": {
    "iso:country":"ES",
    "sg:address":"Calle de Sisones, 5",
    "sg:city":"Pinto",
    "sg:orig_category":"Aluminio Y Aleaciones (producci\u00d3n, Transformaci\u00d3n, Negocio)",
    "sg:phone":"+34 916 92 50 13",
    "sg:postcode":"28320",
    "sg:province":"Madrid",
    "wof:name":"Merfu Aluminios S. A.",
    "wof:placetype":"venue"
},
  "geometry": {"coordinates":[-3.7151479721,40.2485198975],"type":"Point"}
}