{
  "type": "Feature",
  "properties": {
    "addr:full":"Calle de Cardenal Quevedo, 2 Ourense Ourense 32004",
    "addr:housenumber":"2",
    "addr:postcode":"32004",
    "addr:street":"Calle De Cardenal Quevedo",
    "iso:country":"ES",
    "sg:address":"Calle de Cardenal Quevedo, 2",
    "sg:city":"Ourense",
    "sg:orig_category":"Abogados",
    "sg:phone":"+34 988 23 16 05",
    "sg:postcode":"32004",
    "sg:province":"Ourense",
    "wof:name":"Cudeiro Mazaira Jose Jesus",
    "wof:placetype":"venue"
},
  "geometry": {"coordinates":[-7.8630800247,42.3416786194],"type":"Point"}
}