{
  "type": "Feature",
  "properties": {
    "addr:full":"Calle de Alozaina, 18 Malaga M\u00e1laga 29006",
    "addr:housenumber":"18",
    "addr:postcode":"29006",
    "addr:street":"Calle De Alozaina;Ma\u0301Laga",
    "iso:country":"ES",
    "sg:address":"Calle de Alozaina, 18",
    "sg:city":"Malaga",
    "sg:orig_category":"Productos Qu\u00cdmicos (fabricaci\u00d3n, Al Por Mayor)",
    "sg:phone":"+34 952 32 38 18",
    "sg:postcode":"29006",
    "sg:province":"M\u00e1laga",
    "wof:name":"Laboratorios Kin S. A.",
    "wof:placetype":"venue"
},
  "geometry": {"coordinates":[-4.4477243423,36.7099571228],"type":"Point"}
}