{
  "type": "Feature",
  "properties": {
    "iso:country":"ES",
    "sg:address":"Calle de Hernan Cortes, 12",
    "sg:city":"Petrer",
    "sg:orig_category":"Grabados",
    "sg:phone":"+34 965 37 11 83",
    "sg:postcode":"03610",
    "sg:province":"Alicante",
    "wof:name":"Parra Arcos Luis",
    "wof:placetype":"venue"
},
  "geometry": {"coordinates":[-0.785556972,38.4785385132],"type":"Point"}
}