{
  "type": "Feature",
  "properties": {
    "addr:full":"Calle de Real De Pinos Puente, 49 Pinos-puente Granada 18240",
    "addr:housenumber":"49",
    "addr:postcode":"18240",
    "addr:street":"Calle De Real De Pinos Puente",
    "iso:country":"ES",
    "sg:address":"Calle de Real De Pinos Puente, 49",
    "sg:city":"Pinos-puente",
    "sg:orig_category":"Muebles, Minoristas",
    "sg:phone":"+34 958 45 00 65",
    "sg:postcode":"18240",
    "sg:province":"Granada",
    "wof:name":"Muebles Y Electrodomesticos Martinez E Hijos S.l.",
    "wof:placetype":"venue"
},
  "geometry": {"coordinates":[-3.752723217,37.2518768311],"type":"Point"}
}