{
  "type": "Feature",
  "properties": {
    "addr:full":"Avda Marcelino Suarez, 15 Barco Ourense 32300",
    "addr:housenumber":"15",
    "addr:postcode":"32300",
    "addr:street":"Avda Marcelino Suarez",
    "iso:country":"ES",
    "sg:address":"Avda Marcelino Suarez, 15",
    "sg:city":"Barco",
    "sg:orig_category":"Congelados: Productos Alimentarios (al Por Menor)",
    "sg:phone":"+34 988 32 18 74",
    "sg:postcode":"32300",
    "sg:province":"Ourense",
    "wof:name":"Alimentos Y Congelados Unifrio S.l.",
    "wof:placetype":"venue"
},
  "geometry": {"coordinates":[-6.9829645157,42.4161758423],"type":"Point"}
}