{
  "type": "Feature",
  "properties": {
    "addr:full":"Ctra Santo Domingo, Km. 0033,0 Ezcaray La Rioja 26280",
    "addr:postcode":"26280",
    "addr:street":"Ctra Santo Domingo Km. 0033,0;Rioja",
    "iso:country":"ES",
    "sg:address":"Ctra Santo Domingo, Km. 0033,0",
    "sg:city":"Ezcaray",
    "sg:orig_category":"Art\u00cdculos De Madera (fabricaci\u00d3n Y Al Por Mayor)",
    "sg:phone":"+34 941 35 44 09",
    "sg:postcode":"26280",
    "sg:province":"La Rioja",
    "wof:name":"Cooperativa De Muebles De Ezcaray S.coop.ltda.",
    "wof:placetype":"venue"
},
  "geometry": {"coordinates":[-3.0140590668,42.3275260925],"type":"Point"}
}