{
  "type": "Feature",
  "properties": {
    "iso:country":"ES",
    "sg:address":"Avda Dilar (de), 45",
    "sg:city":"Granada",
    "sg:orig_category":"Zapatos (al Por Menor)",
    "sg:phone":"+34 958 12 48 30",
    "sg:postcode":"18007",
    "sg:province":"Granada",
    "wof:name":"Cortes Serrano Sergio Tomas",
    "wof:placetype":"venue"
},
  "geometry": {"coordinates":[-3.5997400284,37.1579551697],"type":"Point"}
}