{
  "type": "Feature",
  "properties": {
    "iso:country":"ES",
    "sg:address":"Mercabarna (zona Franca), S/n",
    "sg:city":"Barcelona",
    "sg:orig_category":"Cooperativas Agr\u00cdcolas",
    "sg:phone":"+34 933 36 53 01",
    "sg:postcode":"08040",
    "sg:province":"Barcelona",
    "wof:name":"Cooperativa Agricola San Juan Despi",
    "wof:placetype":"venue"
},
  "geometry": {"coordinates":[2.1687450409,41.3855895996],"type":"Point"}
}