{
  "type": "Feature",
  "properties": {
    "addr:full":"Pg Agusti Font, 8 Lloret Mar Girona 17310",
    "addr:housenumber":"8",
    "addr:postcode":"17310",
    "addr:street":"Pg Agusti Font",
    "iso:country":"ES",
    "sg:address":"Pg Agusti Font, 8",
    "sg:city":"Lloret Mar",
    "sg:orig_category":"Caf\u00c9s, Bares, Cervecer\u00cdas",
    "sg:phone":"+34 972 36 53 41",
    "sg:postcode":"17310",
    "sg:province":"Girona",
    "wof:name":"Classic Franchaise S.l.",
    "wof:placetype":"venue"
},
  "geometry": {"coordinates":[2.8458468914,41.6977119446],"type":"Point"}
}