{
  "type": "Feature",
  "properties": {
    "iso:country":"ES",
    "sg:address":"Calle de San Andres, 6",
    "sg:city":"Tra\u00e7a-matiena",
    "sg:orig_category":"Peluqueros: De Se\u00d1oras",
    "sg:phone":"+34 946 81 40 39",
    "sg:postcode":"48220",
    "sg:province":"Vizcaya",
    "wof:name":"Bizcarra Olabegoya Jose Maria",
    "wof:placetype":"venue"
},
  "geometry": {"coordinates":[-2.6079039574,43.1692581177],"type":"Point"}
}