{
  "type": "Feature",
  "properties": {
    "iso:country":"ES",
    "sg:address":"Calle de Angelillo, 3",
    "sg:city":"Madrid",
    "sg:orig_category":"Molduras, Junquillos, Listones Y Molduras Perforadas",
    "sg:phone":"+34 917 72 05 99",
    "sg:postcode":"28018",
    "sg:province":"Madrid",
    "wof:name":"Morillo Chamorro Maximina",
    "wof:placetype":"venue"
},
  "geometry": {"coordinates":[-3.6443395615,40.3817863464],"type":"Point"}
}