{
  "type": "Feature",
  "properties": {
    "iso:country":"ES",
    "sg:address":"Calle de Monte Aya, 22",
    "sg:city":"Madrid",
    "sg:orig_category":"Servicio De Salud",
    "sg:phone":"+34 913 03 67 65",
    "sg:postcode":"28031",
    "sg:province":"Madrid",
    "wof:name":"Amado Alonso Jacinto",
    "wof:placetype":"venue"
},
  "geometry": {"coordinates":[-3.6220850945,40.3773193359],"type":"Point"}
}