{
  "type": "Feature",
  "properties": {
    "iso:country":"ES",
    "sg:address":"Calle de Toril, 15",
    "sg:city":"Villarejo Salvanes",
    "sg:orig_category":"Acero: Productos Sider\u00dargicos Y Transformados (fabricaci\u00d3n, Negocio)",
    "sg:phone":"+34 918 74 45 68",
    "sg:postcode":"28590",
    "sg:province":"Madrid",
    "wof:name":"Mariscal De La Torre Jose",
    "wof:placetype":"venue"
},
  "geometry": {"coordinates":[-3.2789490223,40.1675224304],"type":"Point"}
}