{
  "type": "Feature",
  "properties": {
    "iso:country":"ES",
    "sg:address":"Avda Amanecer, 29",
    "sg:city":"Javea",
    "sg:orig_category":"Comercio De Piezas De Recambio Y De Accesorios De Veh\u00cdculos, Veh\u00cdculos Industriales",
    "sg:phone":"+34 965 79 51 33",
    "sg:postcode":"03730",
    "sg:province":"Alicante",
    "wof:name":"Suministros Y Recambios Rimar S.l.",
    "wof:placetype":"venue"
},
  "geometry": {"coordinates":[0.1692170054,38.7894973755],"type":"Point"}
}