{
  "type": "Feature",
  "properties": {
    "iso:country":"ES",
    "sg:address":"Send Valentin De Foronda, 24",
    "sg:city":"Vitoria-gasteiz",
    "sg:orig_category":"Farmacias",
    "sg:phone":"+34 945 17 90 69",
    "sg:postcode":"01010",
    "sg:province":"\u00c1lava",
    "wof:name":"Arrieta Aniz Blanca",
    "wof:placetype":"venue"
},
  "geometry": {"coordinates":[-2.7033574581,42.8563346863],"type":"Point"}
}