{
  "type": "Feature",
  "properties": {
    "iso:country":"ES",
    "sg:address":"Calle de Palomar, 10",
    "sg:city":"Zamora",
    "sg:orig_category":"Electrodom\u00c9sticos (al Por Menor)",
    "sg:phone":"+34 980 53 01 21",
    "sg:postcode":"49006",
    "sg:province":"Zamora",
    "wof:name":"Migadani S.l.",
    "wof:placetype":"venue"
},
  "geometry": {"coordinates":[-5.7455220222,41.5070152283],"type":"Point"}
}