{
  "type": "Feature",
  "properties": {
    "addr:full":"Calle de Martires, 7 Calahorra La Rioja 26500",
    "addr:housenumber":"7",
    "addr:postcode":"26500",
    "addr:street":"Calle De Martires",
    "iso:country":"ES",
    "sg:address":"Calle de Martires, 7",
    "sg:city":"Calahorra",
    "sg:orig_category":"Confecci\u00d3n (fabricaci\u00d3n, Al Por Mayor)",
    "sg:phone":"+34 941 13 03 47",
    "sg:postcode":"26500",
    "sg:province":"La Rioja",
    "wof:name":"Modas Queen S.l.",
    "wof:placetype":"venue"
},
  "geometry": {"coordinates":[-1.9634170532,42.3027648926],"type":"Point"}
}