{
  "type": "Feature",
  "properties": {
    "addr:full":"C/ Carlos Anton Pastor, 44 Elche Alicante 03206",
    "addr:housenumber":"44",
    "addr:postcode":"03206",
    "addr:street":"C / Carlos Anton Pastor",
    "iso:country":"ES",
    "sg:address":"C/ Carlos Anton Pastor, 44",
    "sg:city":"Elche",
    "sg:orig_category":"Reposter\u00cdas",
    "sg:phone":"+34 965 46 02 81",
    "sg:postcode":"03206",
    "sg:province":"Alicante",
    "wof:name":"Mateu Gonzalez Antonio",
    "wof:placetype":"venue"
},
  "geometry": {"coordinates":[-0.7120249867,38.2761955261],"type":"Point"}
}