{
  "type": "Feature",
  "properties": {
    "addr:full":"Ctra Villamarchante, 43 Riba-roja Turia Valencia 46190",
    "addr:housenumber":"43",
    "addr:postcode":"46190",
    "addr:street":"Ctra Villamarchante",
    "iso:country":"ES",
    "sg:address":"Ctra Villamarchante, 43",
    "sg:city":"Riba-roja Turia",
    "sg:orig_category":"Sociedades, Compa\u00d1\u00cdas Aseguradoras",
    "sg:phone":"+34 962 77 20 03",
    "sg:postcode":"46190",
    "sg:province":"Valencia",
    "wof:name":"Mapfre Servicios De Informatica",
    "wof:placetype":"venue"
},
  "geometry": {"coordinates":[-0.5716459751,39.5446052551],"type":"Point"}
}