{
  "type": "Feature",
  "properties": {
    "iso:country":"ES",
    "sg:address":"Calle de Miguel Villanueva, 7",
    "sg:city":"Logro\u00f1o",
    "sg:orig_category":"Agencias De Trabajo Temporal",
    "sg:phone":"+34 941 26 08 90",
    "sg:postcode":"26001",
    "sg:province":"La Rioja",
    "wof:name":"Ananda Gestion E.t.t. S.l.",
    "wof:placetype":"venue"
},
  "geometry": {"coordinates":[-2.445397377,42.4641914368],"type":"Point"}
}