{
  "type": "Feature",
  "properties": {
    "addr:full":"Calle de Jose Lejarreta, 41 Vitoria-gasteiz \u00c1lava 01003",
    "addr:housenumber":"41",
    "addr:postcode":"01003",
    "addr:street":"Calle De Jose Lejarreta",
    "iso:country":"ES",
    "sg:address":"Calle de Jose Lejarreta, 41",
    "sg:city":"Vitoria-gasteiz",
    "sg:orig_category":"Electricidad: Instaladores",
    "sg:phone":"+34 945 27 06 64",
    "sg:postcode":"01003",
    "sg:province":"\u00c1lava",
    "wof:name":"Electricidad Aguirrezabal S. L.",
    "wof:placetype":"venue"
},
  "geometry": {"coordinates":[-2.6622319221,42.8424873352],"type":"Point"}
}