{
  "type": "Feature",
  "properties": {
    "iso:country":"ES",
    "sg:address":"Calle de Cervantes, 16",
    "sg:city":"Oviedo",
    "sg:orig_category":"Expertos Contables, Revisores De Cuentas",
    "sg:phone":"+34 985 21 88 82",
    "sg:postcode":"33004",
    "sg:province":"Asturias",
    "wof:name":"Gabinete De Estudios Contables Fiscales S.l.",
    "wof:placetype":"venue"
},
  "geometry": {"coordinates":[-5.8561954498,43.3632011414],"type":"Point"}
}