{
  "type": "Feature",
  "properties": {
    "iso:country":"ES",
    "sg:address":"Ctra Kautela Aldapa, 13",
    "sg:city":"Gandia",
    "sg:orig_category":"Hornos Industriales",
    "sg:phone":"+34 946 77 43 33",
    "sg:postcode":"48630",
    "sg:province":"Vizcaya",
    "wof:name":"Na-stordy Combustion Ltd",
    "wof:placetype":"venue"
},
  "geometry": {"coordinates":[-2.9390060902,43.4027938843],"type":"Point"}
}