{
  "type": "Feature",
  "properties": {
    "iso:country":"ES",
    "sg:address":"Calle de Doctor Albi\u00d1ana, 7",
    "sg:city":"Torre Miguel Sesmero",
    "sg:orig_category":"Aceites Y Grasas Alimentarias (fabricaci\u00d3n, Al Por Mayor)",
    "sg:phone":"+34 924 48 27 63",
    "sg:postcode":"06172",
    "sg:province":"Badajoz",
    "wof:name":"Ruiz Valero Fernando",
    "wof:placetype":"venue"
},
  "geometry": {"coordinates":[-6.7948470116,38.6178207397],"type":"Point"}
}