{
  "type": "Feature",
  "properties": {
    "addr:full":"Calle de Ronda De La Glorieta, 29 Villanueva De Los Infantes Ciudad Real 13320",
    "addr:housenumber":"29",
    "addr:postcode":"13320",
    "addr:street":"Calle De Ronda De La Glorieta",
    "iso:country":"ES",
    "sg:address":"Calle de Ronda De La Glorieta, 29",
    "sg:city":"Villanueva De Los Infantes",
    "sg:orig_category":"Comercio, Reparaci\u00d3n De Motocicletas, Bicicletas Y Piezas Sueltas",
    "sg:phone":"+34 926 36 07 55",
    "sg:postcode":"13320",
    "sg:province":"Ciudad Real",
    "wof:name":"Perez Salido Pedro",
    "wof:placetype":"venue"
},
  "geometry": {"coordinates":[-3.0111939907,38.7334785461],"type":"Point"}
}