{
  "type": "Feature",
  "properties": {
    "iso:country":"ES",
    "sg:address":"Calle de Huete, 23",
    "sg:city":"Ceuti",
    "sg:orig_category":"Psic\u00d3logos",
    "sg:phone":"+34 968 68 75 32",
    "sg:postcode":"30562",
    "sg:province":"Murcia",
    "wof:name":"Bernal Salar Vicente",
    "wof:placetype":"venue"
},
  "geometry": {"coordinates":[-1.27344203,38.0786132812],"type":"Point"}
}