{
  "type": "Feature",
  "properties": {
    "addr:full":"Calle de Espada, 9 Madrid Madrid 28012",
    "addr:housenumber":"9",
    "addr:postcode":"madrid;28012",
    "addr:street":"Calle De Espada",
    "iso:country":"ES",
    "sg:address":"Calle de Espada, 9",
    "sg:city":"Madrid",
    "sg:orig_category":"Obras Y Organismos Sociales",
    "sg:phone":"+34 915 27 16 38",
    "sg:postcode":"28012",
    "sg:province":"Madrid",
    "wof:name":"Fundacion Obra Social Rosalia Rendu",
    "wof:placetype":"venue"
},
  "geometry": {"coordinates":[-3.704185009,40.4114456177],"type":"Point"}
}