{
  "type": "Feature",
  "properties": {
    "addr:full":"Avda Constitucion, 8 Valencia Valencia 46...",
    "addr:housenumber":"8",
    "addr:street":"Avda Constitucion;Valencia",
    "iso:country":"ES",
    "sg:address":"Avda Constitucion, 8",
    "sg:city":"Valencia",
    "sg:orig_category":"Inmobiliaria (agencias)",
    "sg:phone":"+34 963 48 97 32",
    "sg:postcode":"46...",
    "sg:province":"Valencia",
    "sg:website":"www.grupo90.com",
    "wof:name":"Grupo 90 V.z. Sociedad Limitada",
    "wof:placetype":"venue"
},
  "geometry": {"coordinates":[-0.3786759973,39.4840126038],"type":"Point"}
}