{
  "type": "Feature",
  "properties": {
    "iso:country":"ES",
    "sg:address":"Calle de Cuesta Del Molino, S/n",
    "sg:city":"Puente-genil",
    "sg:orig_category":"Agentes, Concesionarios Y Sucursales De Veh\u00cdculos",
    "sg:phone":"+34 957 60 18 19",
    "sg:postcode":"14500",
    "sg:province":"C\u00f3rdoba",
    "wof:name":"Ligero Y Caceres S. A.",
    "wof:placetype":"venue"
},
  "geometry": {"coordinates":[-4.7705054283,37.3940963745],"type":"Point"}
}