{
  "type": "Feature",
  "properties": {
    "iso:country":"ES",
    "sg:address":"Calle de Bernabe Soriano, 14",
    "sg:city":"Jaen",
    "sg:orig_category":"Importaci\u00d3n, Exportaci\u00d3n Y Comercios De Productos Textiles",
    "sg:phone":"+34 953 23 40 55",
    "sg:postcode":"23001",
    "sg:province":"Ja\u00e9n",
    "wof:name":"Castillo Morillas Francisco",
    "wof:placetype":"venue"
},
  "geometry": {"coordinates":[-3.7883210182,37.7662391663],"type":"Point"}
}