{
  "type": "Feature",
  "properties": {
    "iso:country":"ES",
    "sg:address":"Calle de Milagrosa (la)(corralejo), 33",
    "sg:city":"Corralejo",
    "sg:orig_category":"Imprenta",
    "sg:phone":"+34 928 53 59 37",
    "sg:postcode":"35660",
    "sg:province":"Las Palmas",
    "wof:name":"Reich  Thomas F.",
    "wof:placetype":"venue"
},
  "geometry": {"coordinates":[-13.8692493439,28.7350444794],"type":"Point"}
}