{
  "type": "Feature",
  "properties": {
    "iso:country":"ES",
    "sg:address":"Calle de San Isidro, 34",
    "sg:city":"Tafalla",
    "sg:classifiers":[
        {
            "category":"Taxi",
            "type":"Transportation"
        }
    ],
    "sg:phone":"+34 948 70 36 15",
    "sg:postcode":"31300",
    "sg:province":"Navarra",
    "wof:name":"Garcia Medina Maria Pilar",
    "wof:placetype":"venue"
},
  "geometry": {"coordinates":[-1.6795150042,42.5244750977],"type":"Point"}
}