{
  "type": "Feature",
  "properties": {
    "iso:country":"ES",
    "sg:address":"Crta. Ajalvir-torrejon Ardoz, Km. 0002,0",
    "sg:city":"Ajalvir",
    "sg:orig_category":"Pintura, Barniz, Productos Asimilables (fabricaci\u00d3n, Al Por Mayor)",
    "sg:phone":"+34 918 84 40 85",
    "sg:postcode":"28864",
    "sg:province":"Madrid",
    "sg:website":"www.ralva.com.",
    "wof:name":"Ralva S.a.",
    "wof:placetype":"venue"
},
  "geometry": {"coordinates":[-3.4845490456,40.5355567932],"type":"Point"}
}