{
  "type": "Feature",
  "properties": {
    "addr:full":"Calle de Jenner, 3 Madrid Madrid 28010",
    "addr:housenumber":"3",
    "addr:postcode":"28010",
    "addr:street":"Calle De Jenner",
    "iso:country":"ES",
    "sg:address":"Calle de Jenner, 3",
    "sg:city":"Madrid",
    "sg:orig_category":"Inform\u00c1tica, Ofim\u00c1tica (estudios, Asesor\u00cda, Ingenier\u00cda, Formaci\u00d3n)",
    "sg:phone":"+34 913 08 65 11",
    "sg:postcode":"28010",
    "sg:province":"Madrid",
    "sg:website":"www.options-futures.net",
    "wof:name":"Options And Futures Institute S.l.",
    "wof:placetype":"venue"
},
  "geometry": {"coordinates":[-3.6909871101,40.4316482544],"type":"Point"}
}