{
  "type": "Feature",
  "properties": {
    "iso:country":"ES",
    "sg:address":"Calle de San Bernardo, 17",
    "sg:city":"Madrid",
    "sg:orig_category":"Servidores Y Editores De Bases De Datos",
    "sg:phone":"+34 915 40 41 00",
    "sg:postcode":"28...",
    "sg:province":"Madrid",
    "sg:website":"www.lycos.es",
    "wof:name":"Lycos",
    "wof:placetype":"venue"
},
  "geometry": {"coordinates":[-3.7078480721,40.4223442078],"type":"Point"}
}