{
  "type": "Feature",
  "properties": {
    "addr:full":"Calle de Girasol (del), 8 Tres Cantos Madrid 28760",
    "addr:housenumber":"8",
    "addr:postcode":"28760",
    "addr:street":"Calle De Girasol Del",
    "iso:country":"ES",
    "sg:address":"Calle de Girasol (del), 8",
    "sg:city":"Tres Cantos",
    "sg:orig_category":"Edici\u00d3n De Diarios, Revistas, Boletines",
    "sg:phone":"+34 918 04 04 94",
    "sg:postcode":"28760",
    "sg:province":"Madrid",
    "wof:name":"Publimed",
    "wof:placetype":"venue"
},
  "geometry": {"coordinates":[-3.7113349438,40.6008300781],"type":"Point"}
}