{
  "type": "Feature",
  "properties": {
    "iso:country":"ES",
    "sg:address":"Calle de Don Fadrique, 7",
    "sg:city":"Sevilla",
    "sg:orig_category":"Loter\u00cda Y T\u00d3mbola",
    "sg:phone":"+34 954 90 28 46",
    "sg:postcode":"41009",
    "sg:province":"Sevilla",
    "wof:name":"Rizo Velez Magdalena Esperanza",
    "wof:placetype":"venue"
},
  "geometry": {"coordinates":[-5.9893298149,37.403339386],"type":"Point"}
}