{
  "type": "Feature",
  "properties": {
    "addr:full":"Calle de Conde De Altea, 16 Altea Alicante 03590",
    "addr:housenumber":"16",
    "addr:postcode":"03590",
    "addr:street":"Calle De Conde De Altea",
    "iso:country":"ES",
    "sg:address":"Calle de Conde De Altea, 16",
    "sg:city":"Altea",
    "sg:orig_category":"Art\u00cdculos De Regalo (al Por Menor)",
    "sg:phone":"+34 965 84 38 83",
    "sg:postcode":"03590",
    "sg:province":"Alicante",
    "wof:name":"Gallego Soler Jaime",
    "wof:placetype":"venue"
},
  "geometry": {"coordinates":[-0.0476614982,38.6002731323],"type":"Point"}
}