{
  "type": "Feature",
  "properties": {
    "addr:full":"Calle de Infantas, 40 Madrid Madrid 28004",
    "addr:housenumber":"40",
    "addr:postcode":"madrid;28004",
    "addr:street":"Calle De Infantas",
    "iso:country":"ES",
    "sg:address":"Calle de Infantas, 40",
    "sg:city":"Madrid",
    "sg:orig_category":"Caf\u00c9s, Bares, Cervecer\u00cdas",
    "sg:phone":"+34 915 22 03 92",
    "sg:postcode":"28004",
    "sg:province":"Madrid",
    "wof:name":"Garcia Garcia Jesus",
    "wof:placetype":"venue"
},
  "geometry": {"coordinates":[-3.697922945,40.4200515747],"type":"Point"}
}