{
  "type": "Feature",
  "properties": {
    "iso:country":"ES",
    "sg:address":"Carr Utxana, 31",
    "sg:city":"Sueca",
    "sg:orig_category":"Notarios",
    "sg:phone":"+34 961 70 22 75",
    "sg:postcode":"46410",
    "sg:province":"Valencia",
    "wof:name":"Sanjuan Pellicer Vicente Salvador",
    "wof:placetype":"venue"
},
  "geometry": {"coordinates":[-0.3118450046,39.2044372559],"type":"Point"}
}