{
  "type": "Feature",
  "properties": {
    "addr:full":"G.v. Corts Catalanes, 938 Barcelona Barcelona 08018",
    "addr:housenumber":"938",
    "addr:postcode":"08018",
    "addr:street":"Catalanes",
    "iso:country":"ES",
    "sg:address":"G.v. Corts Catalanes, 938",
    "sg:city":"Barcelona",
    "sg:orig_category":"Farmacias",
    "sg:phone":"+34 933 07 11 02",
    "sg:postcode":"08018",
    "sg:province":"Barcelona",
    "wof:name":"Perez Garcia Juan Carlos",
    "wof:placetype":"venue"
},
  "geometry": {"coordinates":[2.1949698925,41.4087638855],"type":"Point"}
}