{
  "type": "Feature",
  "properties": {
    "iso:country":"ES",
    "sg:address":"Carrer de Higini Angles, 8",
    "sg:city":"Tarragona",
    "sg:orig_category":"Procuradores",
    "sg:phone":"+34 977 24 20 79",
    "sg:postcode":"43001",
    "sg:province":"Tarragona",
    "wof:name":"Martinez Bastida Maria Josepa",
    "wof:placetype":"venue"
},
  "geometry": {"coordinates":[1.2452059984,41.1174545288],"type":"Point"}
}