{
  "type": "Feature",
  "properties": {
    "iso:country":"ES",
    "sg:address":"Calle de Iglesia, 8",
    "sg:city":"Pedrosillo Alba",
    "sg:orig_category":"Aparatos E Instalaci\u00d3n De Regad\u00cdos",
    "sg:phone":"+34 923 30 08 60",
    "sg:postcode":"37871",
    "sg:province":"Salamanca",
    "wof:name":"Riegos Y Electricidad Salamanca S.l.",
    "wof:placetype":"venue"
},
  "geometry": {"coordinates":[-5.3957390785,40.8226203918],"type":"Point"}
}