{
  "type": "Feature",
  "properties": {
    "iso:country":"ES",
    "sg:address":"Calle de Barrionuevo, 15",
    "sg:city":"Carmona",
    "sg:orig_category":"Transportes De Material De Construcci\u00d3n",
    "sg:phone":"+34 954 14 13 07",
    "sg:postcode":"41410",
    "sg:province":"Sevilla",
    "wof:name":"Rodriguez Siles Maria De Gracia",
    "wof:placetype":"venue"
},
  "geometry": {"coordinates":[-5.6417369843,37.4746360779],"type":"Point"}
}