{
  "type": "Feature",
  "properties": {
    "iso:country":"ES",
    "sg:address":"Pase Rollo, 64",
    "sg:city":"Salamanca",
    "sg:orig_category":"Farmacias",
    "sg:phone":"+34 923 18 16 26",
    "sg:postcode":"37003",
    "sg:province":"Salamanca",
    "wof:name":"Delgado Cid Carmen Josefa",
    "wof:placetype":"venue"
},
  "geometry": {"coordinates":[-5.649728775,40.9669189453],"type":"Point"}
}