{
  "type": "Feature",
  "properties": {
    "iso:country":"ES",
    "sg:address":"Luga Carretera De Granada, 2",
    "sg:city":"Guadix",
    "sg:orig_category":"Ingeniero",
    "sg:phone":"+34 958 66 19 52",
    "sg:postcode":"18500",
    "sg:province":"Granada",
    "wof:name":"Fernandez-sevilla Leyva Manuel",
    "wof:placetype":"venue"
},
  "geometry": {"coordinates":[-3.1343688965,37.303894043],"type":"Point"}
}