{
  "type": "Feature",
  "properties": {
    "addr:full":"Carrer de Garcilaso, 118 Barcelona Barcelona 08027",
    "addr:housenumber":"118",
    "addr:postcode":"08027",
    "addr:street":"Carrer De Garcilaso",
    "iso:country":"ES",
    "sg:address":"Carrer de Garcilaso, 118",
    "sg:city":"Barcelona",
    "sg:orig_category":"Bares, Piano",
    "sg:phone":"+34 934 08 69 27",
    "sg:postcode":"08027",
    "sg:province":"Barcelona",
    "wof:name":"Cybercafe Europeo S.l",
    "wof:placetype":"venue"
},
  "geometry": {"coordinates":[2.1843240261,41.4232788086],"type":"Point"}
}