{
  "type": "Feature",
  "properties": {
    "addr:full":"Calle de Arturo Vicens, 2 Denia Alicante 03700",
    "addr:housenumber":"2",
    "addr:postcode":"03700",
    "addr:street":"Calle De Arturo Vicens",
    "iso:country":"ES",
    "sg:address":"Calle de Arturo Vicens, 2",
    "sg:city":"Denia",
    "sg:orig_category":"Fabricaci\u00d3n De Productos Textiles Sin Tejer",
    "sg:phone":"+34 966 42 20 59",
    "sg:postcode":"03700",
    "sg:province":"Alicante",
    "wof:name":"Prensa Y Regalos Pastor C.b",
    "wof:placetype":"venue"
},
  "geometry": {"coordinates":[0.1115866974,38.838306427],"type":"Point"}
}