{
  "type": "Feature",
  "properties": {
    "iso:country":"ES",
    "sg:address":"Calle de Velazquez, 2",
    "sg:city":"Quintanar Rey",
    "sg:orig_category":"Cl\u00cdnicas Dentales",
    "sg:phone":"+34 967 49 63 91",
    "sg:postcode":"16220",
    "sg:province":"Cuenca",
    "wof:name":"Dahan  Hichan",
    "wof:placetype":"venue"
},
  "geometry": {"coordinates":[-1.9291479588,39.3431434631],"type":"Point"}
}