{
  "type": "Feature",
  "properties": {
    "iso:country":"ES",
    "sg:address":"Calle de Alvarez De Sotomayor, 34",
    "sg:city":"Santa Maria Aguila",
    "sg:orig_category":"Parafarmacias",
    "sg:phone":"+34 950 58 18 93",
    "sg:postcode":"04710",
    "sg:province":"Almer\u00eda",
    "wof:name":"Manzano Enciso Maria Del Pilar",
    "wof:placetype":"venue"
},
  "geometry": {"coordinates":[-2.7691140175,36.7804145813],"type":"Point"}
}