{
  "type": "Feature",
  "properties": {
    "addr:full":"Calle de San Basilio, 3 Cartagena Murcia 30205",
    "addr:housenumber":"3",
    "addr:postcode":"30205",
    "addr:street":"Calle De San Basilio",
    "iso:country":"ES",
    "sg:address":"Calle de San Basilio, 3",
    "sg:city":"Cartagena",
    "sg:orig_category":"M\u00c9dicos: Cardiolog\u00cda Y Afecciones Cardiovasculares",
    "sg:phone":"+34 968 50 41 81",
    "sg:postcode":"30205",
    "sg:province":"Murcia",
    "wof:name":"Galan Ayuso Jose Luis",
    "wof:placetype":"venue"
},
  "geometry": {"coordinates":[-0.9606140256,37.594997406],"type":"Point"}
}