{
  "type": "Feature",
  "properties": {
    "addr:full":"Calle de Martinez De Escobar Los, 51 Palmas De Gran Canaria Las Palmas 35007",
    "addr:postcode":"35007",
    "addr:street":"Calle De Martinez De Escobar Los",
    "iso:country":"ES",
    "sg:address":"Calle de Martinez De Escobar Los, 51",
    "sg:city":"Palmas De Gran Canaria",
    "sg:orig_category":"Molduras, Junquillos, Listones Y Molduras Perforadas",
    "sg:phone":"+34 928 26 08 47",
    "sg:postcode":"35007",
    "sg:province":"Las Palmas",
    "wof:name":"Aleman De La Nuez Maria",
    "wof:placetype":"venue"
},
  "geometry": {"coordinates":[-15.4357700348,28.1380844116],"type":"Point"}
}