{
  "type": "Feature",
  "properties": {
    "addr:full":"Av. Pais Leones, 12 Le\u00f3n Le\u00f3n 24010",
    "addr:housenumber":"12",
    "addr:postcode":"24010",
    "addr:street":"Av. Pais Leones;Leo\u0301N",
    "iso:country":"ES",
    "sg:address":"Av. Pais Leones, 12",
    "sg:city":"Le\u00f3n",
    "sg:orig_category":"Servicios Gsm",
    "sg:phone":"+34 987 22 76 87",
    "sg:postcode":"24010",
    "sg:province":"Le\u00f3n",
    "wof:name":"Trelles Y Carcaba S.a.",
    "wof:placetype":"venue"
},
  "geometry": {"coordinates":[-5.5968470573,42.6127891541],"type":"Point"}
}