{
  "type": "Feature",
  "properties": {
    "iso:country":"ES",
    "sg:address":"Mercat Sant Josep, 320",
    "sg:city":"Barcelona",
    "sg:orig_category":"Poller\u00cda Y Caza (al Por Menor)",
    "sg:phone":"+34 933 17 33 79",
    "sg:postcode":"08002",
    "sg:province":"Barcelona",
    "wof:name":"Arias Gonzalez Gloria",
    "wof:placetype":"venue"
},
  "geometry": {"coordinates":[2.1719443798,41.381942749],"type":"Point"}
}