{
  "type": "Feature",
  "properties": {
    "addr:full":"Calle de Garganta Los Nogales, 2 Navalmoral Mata C\u00e1ceres 10300",
    "addr:housenumber":"2",
    "addr:postcode":"10300",
    "addr:street":"Calle De Garganta Los Nogales;Ca\u0301Ceres",
    "iso:country":"ES",
    "sg:address":"Calle de Garganta Los Nogales, 2",
    "sg:city":"Navalmoral Mata",
    "sg:orig_category":"Molduras, Junquillos, Listones Y Molduras Perforadas",
    "sg:phone":"+34 927 53 09 53",
    "sg:postcode":"10300",
    "sg:province":"C\u00e1ceres",
    "wof:name":"Morales Curiel Maria Claudia",
    "wof:placetype":"venue"
},
  "geometry": {"coordinates":[-5.5461740494,39.8927574158],"type":"Point"}
}