{
  "type": "Feature",
  "properties": {
    "addr:full":"C/ Sant Francesc, 6 Cerdanyola Valles Barcelona 08290",
    "addr:housenumber":"6",
    "addr:postcode":"08290",
    "addr:street":"C / Sant Francesc;Valles Barcelona",
    "iso:country":"ES",
    "sg:address":"C/ Sant Francesc, 6",
    "sg:city":"Cerdanyola Valles",
    "sg:orig_category":"Asesor\u00cda Fiscal Y Jur\u00cddica",
    "sg:phone":"+34 935 80 36 52",
    "sg:postcode":"08290",
    "sg:province":"Barcelona",
    "wof:name":"Sero Puig Jorge",
    "wof:placetype":"venue"
},
  "geometry": {"coordinates":[2.1430859566,41.49426651],"type":"Point"}
}