{
  "type": "Feature",
  "properties": {
    "iso:country":"ES",
    "sg:address":"Av Abat Marcet, 45",
    "sg:city":"Terrassa",
    "sg:orig_category":"Librer\u00cdas",
    "sg:phone":"+34 937 35 46 39",
    "sg:postcode":"08225",
    "sg:province":"Barcelona",
    "wof:name":"Campos Miscenich Claudio",
    "wof:placetype":"venue"
},
  "geometry": {"coordinates":[2.0119988918,41.5747756958],"type":"Point"}
}