{
  "type": "Feature",
  "properties": {
    "addr:full":"Carr Sant Pau, 50 Figueres Girona 17600",
    "addr:housenumber":"50",
    "addr:postcode":"17600",
    "addr:street":"Carr Sant Pau",
    "iso:country":"ES",
    "sg:address":"Carr Sant Pau, 50",
    "sg:city":"Figueres",
    "sg:orig_category":"Electrodom\u00c9sticos (al Por Menor)",
    "sg:phone":"+34 972 50 10 84",
    "sg:postcode":"17600",
    "sg:province":"Girona",
    "wof:name":"Maso Serra Victoriano",
    "wof:placetype":"venue"
},
  "geometry": {"coordinates":[2.9581100941,42.2656898499],"type":"Point"}
}