{
  "type": "Feature",
  "properties": {
    "iso:country":"ES",
    "sg:address":"Avda Diputacion (de La), 32",
    "sg:city":"Chiclana De La Frontera",
    "sg:orig_category":"Tatuajes",
    "sg:phone":"+34 956 53 49 69",
    "sg:postcode":"11130",
    "sg:province":"C\u00e1diz",
    "wof:name":"Bahia Tatu S.c.",
    "wof:placetype":"venue"
},
  "geometry": {"coordinates":[-6.1656765938,36.4127426147],"type":"Point"}
}