{
  "type": "Feature",
  "properties": {
    "iso:country":"ES",
    "sg:address":"Plaza Del Cristo, 2",
    "sg:city":"Tacoronte",
    "sg:orig_category":"Ense\u00d1anza, Formaci\u00d3n Profesional: Aprendizaje",
    "sg:phone":"+34 922 56 04 18",
    "sg:postcode":"38350",
    "sg:province":"Santa Cruz De Tenerife",
    "wof:name":"Ayuntamiento De Tacoronte",
    "wof:placetype":"venue"
},
  "geometry": {"coordinates":[-16.4122714996,28.4808311462],"type":"Point"}
}