{
  "type": "Feature",
  "properties": {
    "addr:full":"Calle de Rio Jalon, 4 Hueros Madrid 28810",
    "addr:housenumber":"4",
    "addr:postcode":"28810",
    "addr:street":"Calle De Rio Jalon",
    "iso:country":"ES",
    "sg:address":"Calle de Rio Jalon, 4",
    "sg:city":"Hueros",
    "sg:orig_category":"Instalaci\u00d3n, Preparaci\u00d3n De Exposiciones, Ferias, Salones",
    "sg:phone":"+34 918 79 36 51",
    "sg:postcode":"28810",
    "sg:province":"Madrid",
    "wof:name":"Adecua Dise\u00f1o S.l.",
    "wof:placetype":"venue"
},
  "geometry": {"coordinates":[-3.3509397507,40.4420928955],"type":"Point"}
}