{
  "type": "Feature",
  "properties": {
    "addr:full":"C/ Bisbe Taixequet, 93 Llucmajor Islas Baleares 07620",
    "addr:housenumber":"93",
    "addr:postcode":"07620",
    "addr:street":"C / Bisbe Taixequet",
    "iso:country":"ES",
    "sg:address":"C/ Bisbe Taixequet, 93",
    "sg:city":"Llucmajor",
    "sg:orig_category":"Inmobiliaria (agencias)",
    "sg:phone":"+34 971 12 02 57",
    "sg:postcode":"07620",
    "sg:province":"Islas Baleares",
    "wof:name":"Capella Tomas Miquel",
    "wof:placetype":"venue"
},
  "geometry": {"coordinates":[2.888240099,39.4878501892],"type":"Point"}
}