{
  "type": "Feature",
  "properties": {
    "iso:country":"ES",
    "sg:address":"Carr Merce, 13",
    "sg:city":"Badalona",
    "sg:orig_category":"Molduras, Junquillos, Listones Y Molduras Perforadas",
    "sg:phone":"+34 933 89 60 30",
    "sg:postcode":"08911",
    "sg:province":"Barcelona",
    "wof:name":"Noguera Marco Roque",
    "wof:placetype":"venue"
},
  "geometry": {"coordinates":[2.2497909069,41.4514274597],"type":"Point"}
}