{
  "type": "Feature",
  "properties": {
    "addr:full":"Prol Hernan Cortes, S/n Benicarlo Castell\u00f3n 12580",
    "addr:housenumber":"s / n",
    "addr:postcode":"12580",
    "addr:street":"Prol Hernan Cortes",
    "iso:country":"ES",
    "sg:address":"Prol Hernan Cortes, S/n",
    "sg:city":"Benicarlo",
    "sg:orig_category":"Inmobiliaria (agencias)",
    "sg:phone":"+34 964 47 03 44",
    "sg:postcode":"12580",
    "sg:province":"Castell\u00f3n",
    "sg:website":"www.habitasol.com",
    "wof:name":"Habitasol Confort S.l.",
    "wof:placetype":"venue"
},
  "geometry": {"coordinates":[0.4280222058,40.4163208008],"type":"Point"}
}