{
  "type": "Feature",
  "properties": {
    "addr:full":"Avda Ricardo Carapeto Zambrano, 78 Badajoz Badajoz 06008",
    "addr:housenumber":"78",
    "addr:postcode":"06008",
    "addr:street":"Avda Ricardo Carapeto Zambrano",
    "iso:country":"ES",
    "sg:address":"Avda Ricardo Carapeto Zambrano, 78",
    "sg:city":"Badajoz",
    "sg:orig_category":"Bisuter\u00cda, Joyer\u00cda, Relojer\u00cda (al Por Menor)",
    "sg:phone":"+34 924 23 04 86",
    "sg:postcode":"06008",
    "sg:province":"Badajoz",
    "wof:name":"Carlos Castellanos E Hijos S.a.",
    "wof:placetype":"venue"
},
  "geometry": {"coordinates":[-6.9473338127,38.8786468506],"type":"Point"}
}