{
  "type": "Feature",
  "properties": {
    "iso:country":"ES",
    "sg:address":"Calle de Sidro Vilarroig, 10",
    "sg:city":"Castellon",
    "sg:orig_category":"Quincaller\u00cda (al Por Menor)",
    "sg:phone":"+34 964 20 82 48",
    "sg:postcode":"12006",
    "sg:province":"Castell\u00f3n",
    "wof:name":"Troncho Fabregat Bernardo",
    "wof:placetype":"venue"
},
  "geometry": {"coordinates":[-0.1292939931,40.0168533325],"type":"Point"}
}