{
  "type": "Feature",
  "properties": {
    "iso:country":"ES",
    "sg:address":"Calle de Doctor Fourquet, 17",
    "sg:city":"Madrid",
    "sg:orig_category":"Alimentaci\u00d3n General (al Por Menor)",
    "sg:phone":"+34 915 30 44 28",
    "sg:postcode":"28012",
    "sg:province":"Madrid",
    "sg:website":"www.asaltodemata.es",
    "wof:name":"Asaltodemata S.l.",
    "wof:placetype":"venue"
},
  "geometry": {"coordinates":[-3.6970589161,40.4075546265],"type":"Point"}
}