{
  "type": "Feature",
  "properties": {
    "iso:country":"ES",
    "sg:address":"Avda Constitucion, 56",
    "sg:city":"Peal Becerro",
    "sg:orig_category":"Maquinaria Para Industrias Diversas",
    "sg:phone":"+34 953 73 09 07",
    "sg:postcode":"23460",
    "sg:province":"Ja\u00e9n",
    "wof:name":"Requena Cazorla Pedro Jose",
    "wof:placetype":"venue"
},
  "geometry": {"coordinates":[-3.1223289967,37.9106292725],"type":"Point"}
}