{
  "type": "Feature",
  "properties": {
    "iso:country":"ES",
    "sg:address":"Els Refugis, S/n",
    "sg:city":"Serinya",
    "sg:orig_category":"Ense\u00d1anza Agr\u00cdcola",
    "sg:phone":"+34 972 59 32 33",
    "sg:postcode":"17852",
    "sg:province":"Girona",
    "wof:name":"Refugis S. A.",
    "wof:placetype":"venue"
},
  "geometry": {"coordinates":[2.744343996,42.169128418],"type":"Point"}
}