{
  "type": "Feature",
  "properties": {
    "addr:full":"Calle de San Dacio, 32 Madrid Madrid 28034",
    "addr:housenumber":"32",
    "addr:postcode":"madrid;28034",
    "addr:street":"Calle De San Dacio",
    "iso:country":"ES",
    "sg:address":"Calle de San Dacio, 32",
    "sg:city":"Madrid",
    "sg:orig_category":"Carnicer\u00cdas, Carnicer\u00cdas",
    "sg:phone":"+34 917 29 44 27",
    "sg:postcode":"28034",
    "sg:province":"Madrid",
    "wof:name":"Salinero Blazquez Emilio",
    "wof:placetype":"venue"
},
  "geometry": {"coordinates":[-3.6883718967,40.4855079651],"type":"Point"}
}