{
  "type": "Feature",
  "properties": {
    "iso:country":"ES",
    "sg:address":"Ctra. Ccal. 320, S/n",
    "sg:city":"Ontinyent",
    "sg:orig_category":"Transportes Por V\u00cdas Navegables",
    "sg:phone":"+34 962 91 01 44",
    "sg:postcode":"46870",
    "sg:province":"Valencia",
    "wof:name":"Transportes Sanchis Gandia S.a.",
    "wof:placetype":"venue"
},
  "geometry": {"coordinates":[-0.6030989885,38.8258895874],"type":"Point"}
}