{
  "type": "Feature",
  "properties": {
    "iso:country":"ES",
    "sg:address":"Calle de Serrania De Cuenca, S/n",
    "sg:city":"Arganda",
    "sg:orig_category":"Ebanister\u00cda",
    "sg:phone":"+34 918 71 97 97",
    "sg:postcode":"28500",
    "sg:province":"Madrid",
    "wof:name":"Garcia Garcia Pablo",
    "wof:placetype":"venue"
},
  "geometry": {"coordinates":[-3.4789440632,40.3061485291],"type":"Point"}
}