{
  "type": "Feature",
  "properties": {
    "addr:full":"Avda Portugal (de), 6 Caceres C\u00e1ceres 10001",
    "addr:housenumber":"6",
    "addr:postcode":"10001",
    "addr:street":"Avda Portugal De;Ca\u0301Ceres",
    "iso:country":"ES",
    "sg:address":"Avda Portugal (de), 6",
    "sg:city":"Caceres",
    "sg:orig_category":"Alquiler De V\u00cddeo",
    "sg:phone":"+34 927 21 71 54",
    "sg:postcode":"10001",
    "sg:province":"C\u00e1ceres",
    "sg:website":"www.blastervideo.com",
    "wof:name":"Alfonso Solis Juana",
    "wof:placetype":"venue"
},
  "geometry": {"coordinates":[-6.3791685104,39.4670066833],"type":"Point"}
}