{
  "type": "Feature",
  "properties": {
    "addr:full":"Carrer de Colom, 92 Terrassa Barcelona 08222",
    "addr:housenumber":"92",
    "addr:postcode":"08222",
    "addr:street":"Carrer De Colom",
    "iso:country":"ES",
    "sg:address":"Carrer de Colom, 92",
    "sg:city":"Terrassa",
    "sg:orig_category":"Encuadernaci\u00d3n E Impresi\u00d3n De Folletos",
    "sg:phone":"+34 937 31 24 56",
    "sg:postcode":"08222",
    "sg:province":"Barcelona",
    "wof:name":"Associacio Promocio Taller Del Llibre",
    "wof:placetype":"venue"
},
  "geometry": {"coordinates":[2.0232117176,41.5607452393],"type":"Point"}
}