{
  "type": "Feature",
  "properties": {
    "iso:country":"ES",
    "sg:address":"Carrer de Ample, 76",
    "sg:city":"Terrassa",
    "sg:orig_category":"Asesor\u00cda Fiscal Y Jur\u00cddica",
    "sg:phone":"+34 937 35 92 07",
    "sg:postcode":"08225",
    "sg:province":"Barcelona",
    "wof:name":"Infogestio Terrassa Consultoria S.l.",
    "wof:placetype":"venue"
},
  "geometry": {"coordinates":[2.0161650181,41.5728034973],"type":"Point"}
}