{
  "type": "Feature",
  "properties": {
    "iso:country":"ES",
    "sg:address":"Cmno Pokopandegi De, 6",
    "sg:city":"Donostia-san Sebastian",
    "sg:orig_category":"Torrefactado De Caf\u00c9",
    "sg:phone":"+34 943 21 79 03",
    "sg:postcode":"20018",
    "sg:province":"Guip\u00f9zcoa",
    "wof:name":"Consorcio De Distribucion Fortaleza S.a.",
    "wof:placetype":"venue"
},
  "geometry": {"coordinates":[-2.0029520988,43.2836837769],"type":"Point"}
}