{
  "type": "Feature",
  "properties": {
    "iso:country":"ES",
    "sg:address":"Calle de Carolina Coronado, 4",
    "sg:city":"Azuaga",
    "sg:orig_category":"Bisuter\u00cda, Joyer\u00cda, Relojer\u00cda (al Por Menor)",
    "sg:phone":"+34 924 89 00 02",
    "sg:postcode":"06920",
    "sg:province":"Badajoz",
    "wof:name":"Alamo Vaquera Pedro",
    "wof:placetype":"venue"
},
  "geometry": {"coordinates":[-5.676846981,38.2615432739],"type":"Point"}
}