{
  "type": "Feature",
  "properties": {
    "addr:full":"Avda San Sebastian, 2 Malaga M\u00e1laga 29010",
    "addr:housenumber":"2",
    "addr:postcode":"29010",
    "addr:street":"Avda San Sebastian;Ma\u0301Laga",
    "iso:country":"ES",
    "sg:address":"Avda San Sebastian, 2",
    "sg:city":"Malaga",
    "sg:orig_category":"Agentes Generales De Seguros",
    "sg:phone":"+34 952 61 24 01",
    "sg:postcode":"29010",
    "sg:province":"M\u00e1laga",
    "wof:name":"Rodriguez Canton Asesores S.l.",
    "wof:placetype":"venue"
},
  "geometry": {"coordinates":[-4.4360070229,36.7231750488],"type":"Point"}
}