{
  "type": "Feature",
  "properties": {
    "addr:full":"Calle de Pe\u00d1amefecit, S/n Jaen Ja\u00e9n 23006",
    "addr:housenumber":"s / n;jae\u0301n",
    "addr:postcode":"23006",
    "addr:street":"Calle De Pen\u0303Amefecit",
    "iso:country":"ES",
    "sg:address":"Calle de Pe\u00d1amefecit, S/n",
    "sg:city":"Jaen",
    "sg:orig_category":"Poller\u00cda Y Caza (al Por Menor)",
    "sg:phone":"+34 953 26 63 10",
    "sg:postcode":"23006",
    "sg:province":"Ja\u00e9n",
    "wof:name":"Sanchez Mena Antonio",
    "wof:placetype":"venue"
},
  "geometry": {"coordinates":[-3.7963490486,37.7781944275],"type":"Point"}
}