{
  "type": "Feature",
  "properties": {
    "iso:country":"ES",
    "sg:address":"Calle de Escalante, 1",
    "sg:city":"Puerto",
    "sg:orig_category":"Alimentaci\u00d3n General (al Por Menor)",
    "sg:phone":"+34 962 68 42 20",
    "sg:postcode":"46520",
    "sg:province":"Valencia",
    "wof:name":"Torrecillas Sanjurjo Inmaculada",
    "wof:placetype":"venue"
},
  "geometry": {"coordinates":[-0.2275020033,39.6616592407],"type":"Point"}
}