{
  "type": "Feature",
  "properties": {
    "iso:country":"ES",
    "sg:address":"Avda Jose Mesa Y Lopez, 21",
    "sg:city":"Palmas De Gran Canaria",
    "sg:orig_category":"Peluqueros: De Se\u00d1oras",
    "sg:phone":"+34 928 23 30 47",
    "sg:postcode":"35006",
    "sg:province":"Las Palmas",
    "wof:name":"Quintana Rodriguez Francisco",
    "wof:placetype":"venue"
},
  "geometry": {"coordinates":[-15.4328889847,28.1344337463],"type":"Point"}
}