{
  "type": "Feature",
  "properties": {
    "addr:full":"Calle de Adolfo Diaz Ambrona, 13 Villanueva Serena Badajoz 06700",
    "addr:housenumber":"13",
    "addr:postcode":"06700",
    "addr:street":"Calle De Adolfo Diaz Ambrona",
    "iso:country":"ES",
    "sg:address":"Calle de Adolfo Diaz Ambrona, 13",
    "sg:city":"Villanueva Serena",
    "sg:orig_category":"Caf\u00c9s, Bares, Cervecer\u00cdas",
    "sg:phone":"+34 924 84 55 32",
    "sg:postcode":"06700",
    "sg:province":"Badajoz",
    "wof:name":"Trenado Cabanillas Julio",
    "wof:placetype":"venue"
},
  "geometry": {"coordinates":[-5.798014164,38.9725990295],"type":"Point"}
}