{
  "type": "Feature",
  "properties": {
    "addr:full":"Avda Salvador De Madariaga, S/n Coru\u00d1a La Coru\u00f1a 15008",
    "addr:housenumber":"s / n",
    "addr:postcode":"15008",
    "addr:street":"Avda Salvador De Madariaga;La Corun\u0303A",
    "iso:country":"ES",
    "sg:address":"Avda Salvador De Madariaga, S/n",
    "sg:city":"Coru\u00d1a",
    "sg:orig_category":"Lavado, Limpieza De Veh\u00cdculos",
    "sg:phone":"+34 981 13 70 16",
    "sg:postcode":"15008",
    "sg:province":"La Coru\u00f1a",
    "wof:name":"Amave Elvi\u00f1a S.a.",
    "wof:placetype":"venue"
},
  "geometry": {"coordinates":[-8.405831337,43.3484077454],"type":"Point"}
}