{
  "type": "Feature",
  "properties": {
    "addr:full":"Calle de Cueva De La Pileta, 3 Malaga M\u00e1laga 29018",
    "addr:housenumber":"3",
    "addr:postcode":"29018",
    "addr:street":"Calle De Cueva De La Pileta;Ma\u0301Laga",
    "iso:country":"ES",
    "sg:address":"Calle de Cueva De La Pileta, 3",
    "sg:city":"Malaga",
    "sg:orig_category":"Agencias Y Agentes Comerciales, Representantes",
    "sg:phone":"+34 952 29 60 53",
    "sg:postcode":"29018",
    "sg:province":"M\u00e1laga",
    "wof:name":"Gonzalez De La Cruz Clara Maria",
    "wof:placetype":"venue"
},
  "geometry": {"coordinates":[-4.3462371826,36.756652832],"type":"Point"}
}