{
  "type": "Feature",
  "properties": {
    "iso:country":"ES",
    "sg:address":"Carrer de Mossen Cinto Verdaguer, 1",
    "sg:city":"Palau-solita I Plegamans",
    "sg:orig_category":"Maquinaria, Instalaci\u00d3n Y Equipo Para Garajes Y Estaciones De Servicio",
    "sg:phone":"+34 938 64 92 19",
    "sg:postcode":"08184",
    "sg:province":"Barcelona",
    "wof:name":"Tokheim Koppens Iberica S. A.",
    "wof:placetype":"venue"
},
  "geometry": {"coordinates":[2.1765999794,41.5866012573],"type":"Point"}
}