{
  "type": "Feature",
  "properties": {
    "addr:full":"Calle de Gran Via, 22 Madrid Madrid 28013",
    "addr:housenumber":"22",
    "addr:postcode":"madrid;28013",
    "addr:street":"Calle De Gran Via",
    "iso:country":"ES",
    "sg:address":"Calle de Gran Via, 22",
    "sg:city":"Madrid",
    "sg:orig_category":"Inform\u00c1tica: Consultores",
    "sg:phone":"+34 917 48 00 18",
    "sg:postcode":"28013",
    "sg:province":"Madrid",
    "wof:name":"Envision Technologies",
    "wof:placetype":"venue"
},
  "geometry": {"coordinates":[-3.7005279064,40.4200592041],"type":"Point"}
}