{
  "type": "Feature",
  "properties": {
    "addr:full":"Carrer de Antoni Baixeras, 26 Manlleu Barcelona 08560",
    "addr:housenumber":"26",
    "addr:postcode":"08560",
    "addr:street":"Carrer De Antoni Baixeras",
    "iso:country":"ES",
    "sg:address":"Carrer de Antoni Baixeras, 26",
    "sg:city":"Manlleu",
    "sg:orig_category":"Fabricaci\u00d3n De Mobiliario De Oficina",
    "sg:phone":"+34 938 50 63 71",
    "sg:postcode":"08560",
    "sg:province":"Barcelona",
    "wof:name":"Camps Bonamaison Francisca",
    "wof:placetype":"venue"
},
  "geometry": {"coordinates":[2.2925260067,42.0070228577],"type":"Point"}
}