{
  "type": "Feature",
  "properties": {
    "iso:country":"ES",
    "sg:address":"Calle de Fernando Primo De Rivera, 49",
    "sg:city":"Santa Cruz De Tenerife",
    "sg:orig_category":"Transporte En General",
    "sg:phone":"+34 922 27 01 71",
    "sg:postcode":"38006",
    "sg:province":"Santa Cruz De Tenerife",
    "wof:name":"Gonzalez Garcia Atanasio",
    "wof:placetype":"venue"
},
  "geometry": {"coordinates":[-16.2632980347,28.4691963196],"type":"Point"}
}