{
  "type": "Feature",
  "properties": {
    "iso:country":"ES",
    "sg:address":"Ed Grimaca, S/n",
    "sg:city":"Oropesa Mar",
    "sg:orig_category":"Caf\u00c9s, Bares, Cervecer\u00cdas",
    "sg:phone":"+34 964 31 07 44",
    "sg:postcode":"12594",
    "sg:province":"Castell\u00f3n",
    "wof:name":"Cafeterias Oropesa S.l.",
    "wof:placetype":"venue"
},
  "geometry": {"coordinates":[-0.0456800014,39.9851417542],"type":"Point"}
}