{
  "type": "Feature",
  "properties": {
    "addr:full":"Carrer de Rafael De Casanova (de), 2 Arbo\u00e7 Tarragona 43720",
    "addr:postcode":"43720",
    "addr:street":"Carrer De Rafael De Casanova De 2 Arboc\u0327",
    "iso:country":"ES",
    "sg:address":"Carrer de Rafael De Casanova (de), 2",
    "sg:city":"Arbo\u00e7",
    "sg:orig_category":"Empresas De Carpinter\u00cda De Madera",
    "sg:phone":"+34 977 67 05 11",
    "sg:postcode":"43720",
    "sg:province":"Tarragona",
    "wof:name":"Fusteria Querol S.c.p.",
    "wof:placetype":"venue"
},
  "geometry": {"coordinates":[1.6022349596,41.2676086426],"type":"Point"}
}