{
  "type": "Feature",
  "properties": {
    "iso:country":"ES",
    "sg:address":"Carrer de Irlanda, 90",
    "sg:city":"Santa Coloma De Gramenet",
    "sg:orig_category":"Papeler\u00cdas, Librer\u00cdas",
    "sg:phone":"+34 933 86 31 40",
    "sg:postcode":"08922",
    "sg:province":"Barcelona",
    "sg:website":"www.abacus.es",
    "wof:name":"Abacus Sdad. Coop. Catalana Limitada",
    "wof:placetype":"venue"
},
  "geometry": {"coordinates":[2.214547,41.448578],"type":"Point"}
}