{
  "type": "Feature",
  "properties": {
    "addr:full":"Av Conqueridor, 59 Ciutadella Menorca Islas Baleares 07760",
    "addr:housenumber":"59",
    "addr:postcode":"07760",
    "addr:street":"Av Conqueridor",
    "iso:country":"ES",
    "sg:address":"Av Conqueridor, 59",
    "sg:city":"Ciutadella Menorca",
    "sg:orig_category":"Alquiler De Veh\u00cdculos: Turismos Y Utilitarios",
    "sg:phone":"+34 971 38 29 98",
    "sg:postcode":"07760",
    "sg:province":"Islas Baleares",
    "sg:website":"www.betacar.biz",
    "wof:name":"Betacar Menorca S.a.",
    "wof:placetype":"venue"
},
  "geometry": {"coordinates":[3.840182066,40.0006637573],"type":"Point"}
}