{
  "type": "Feature",
  "properties": {
    "iso:country":"ES",
    "sg:address":"Carr Rioja (la), 40",
    "sg:city":"Grau I Platja",
    "sg:orig_category":"Construcciones Prefabricadas Y Desmontables",
    "sg:phone":"+34 962 84 15 80",
    "sg:postcode":"46730",
    "sg:province":"Valencia",
    "wof:name":"Navarro Llacer Salvador",
    "wof:placetype":"venue"
},
  "geometry": {"coordinates":[-0.1712210029,39.0100517273],"type":"Point"}
}