{
  "type": "Feature",
  "properties": {
    "iso:country":"ES",
    "sg:address":"Calle de San Vicente Martir, 130",
    "sg:city":"Valencia",
    "sg:orig_category":"Colchones (fabricaci\u00d3n, Al Por Mayor, Al Por Menor)",
    "sg:phone":"+34 963 41 16 94",
    "sg:postcode":"46007",
    "sg:province":"Valencia",
    "wof:name":"Colchones Elasticos Y Complementos S. A.",
    "wof:placetype":"venue"
},
  "geometry": {"coordinates":[-0.3820379972,39.4641189575],"type":"Point"}
}