{
  "type": "Feature",
  "properties": {
    "addr:full":"Avda Virgen De Guadalupe, 9 Caceres C\u00e1ceres 10001",
    "addr:housenumber":"9",
    "addr:postcode":"10001",
    "addr:street":"Avda Virgen De Guadalupe;Ca\u0301Ceres",
    "iso:country":"ES",
    "sg:address":"Avda Virgen De Guadalupe, 9",
    "sg:city":"Caceres",
    "sg:orig_category":"Agencias De Viajes",
    "sg:phone":"+34 927 21 00 22",
    "sg:postcode":"10001",
    "sg:province":"C\u00e1ceres",
    "sg:website":"www.barceloviajes.es",
    "wof:name":"Viajes Barcelo S.l.",
    "wof:placetype":"venue"
},
  "geometry": {"coordinates":[-6.3800730705,39.4715194702],"type":"Point"}
}