{
  "type": "Feature",
  "properties": {
    "addr:full":"Carrer de Pareto, 25 Hospitalet Llobregat Barcelona 08902",
    "addr:housenumber":"25",
    "addr:postcode":"08902",
    "addr:street":"Carrer De Pareto",
    "iso:country":"ES",
    "sg:address":"Carrer de Pareto, 25",
    "sg:city":"Hospitalet Llobregat",
    "sg:orig_category":"Estancos",
    "sg:phone":"+34 933 31 36 47",
    "sg:postcode":"08902",
    "sg:province":"Barcelona",
    "wof:name":"Claramunt Gras Nuria",
    "wof:placetype":"venue"
},
  "geometry": {"coordinates":[2.1274349689,41.3662185669],"type":"Point"}
}