{
  "type": "Feature",
  "properties": {
    "iso:country":"ES",
    "sg:address":"Calle de Divino Maestro, 1",
    "sg:city":"Marmolejo",
    "sg:orig_category":"Centros De Coordinaci\u00d3n",
    "sg:phone":"+34 953 54 00 17",
    "sg:postcode":"23770",
    "sg:province":"Ja\u00e9n",
    "wof:name":"Zamora Ruiz Rosa",
    "wof:placetype":"venue"
},
  "geometry": {"coordinates":[-4.1718888283,38.0454902649],"type":"Point"}
}