{
  "type": "Feature",
  "properties": {
    "iso:country":"ES",
    "sg:address":"Calle de Fuentesauco, 7",
    "sg:city":"Madrid",
    "sg:orig_category":"Centros M\u00c9dicos Y Sociales, Dispensarios",
    "sg:phone":"+34 917 11 24 54",
    "sg:postcode":"28024",
    "sg:province":"Madrid",
    "wof:name":"Castillo Fernandez Carlos Alejandro",
    "wof:placetype":"venue"
},
  "geometry": {"coordinates":[-3.7710940838,40.3980522156],"type":"Point"}
}