{
  "type": "Feature",
  "properties": {
    "addr:full":"Plaz Geltoki, S/n Gernika-lumo Vizcaya 48300",
    "addr:housenumber":"s / n",
    "addr:postcode":"48300",
    "addr:street":"Geltoki",
    "iso:country":"ES",
    "sg:address":"Plaz Geltoki, S/n",
    "sg:city":"Gernika-lumo",
    "sg:classifiers":[
        {
            "category":"Taxi",
            "type":"Transportation"
        }
    ],
    "sg:phone":"+34 946 25 10 02",
    "sg:postcode":"48300",
    "sg:province":"Vizcaya",
    "wof:name":"Gernika-lumoko Udala",
    "wof:placetype":"venue"
},
  "geometry": {"coordinates":[-97.78224945069999,45.7040786743],"type":"Point"}
}