{
  "type": "Feature",
  "properties": {
    "addr:full":"Calle de Azorin, 10 Alguazas Murcia 30560",
    "addr:housenumber":"10",
    "addr:postcode":"30560",
    "addr:street":"Calle De Azorin",
    "iso:country":"ES",
    "sg:address":"Calle de Azorin, 10",
    "sg:city":"Alguazas",
    "sg:orig_category":"Marketing Telef\u00d3nico",
    "sg:phone":"+34 968 62 00 89",
    "sg:postcode":"30560",
    "sg:province":"Murcia",
    "wof:name":"Hurtado Perez Ana Beatriz",
    "wof:placetype":"venue"
},
  "geometry": {"coordinates":[-1.2484302521,38.0532035828],"type":"Point"}
}