{
  "type": "Feature",
  "properties": {
    "iso:country":"ES",
    "sg:address":"Avda Cruz Del Campo (la), 35",
    "sg:city":"Sevilla",
    "sg:orig_category":"Agencias Y Agentes Comerciales, Representantes",
    "sg:phone":"+34 954 57 44 48",
    "sg:postcode":"41005",
    "sg:province":"Sevilla",
    "wof:name":"Carrasco Guzman Pedro",
    "wof:placetype":"venue"
},
  "geometry": {"coordinates":[-5.9655771255,37.3850975037],"type":"Point"}
}