{
  "type": "Feature",
  "properties": {
    "addr:full":"Avda Aeropuerto (del), 32 Cordoba C\u00f3rdoba 14004",
    "addr:housenumber":"32",
    "addr:postcode":"14004",
    "addr:street":"Avda Aeropuerto Del;Co\u0301Rdoba",
    "iso:country":"ES",
    "sg:address":"Avda Aeropuerto (del), 32",
    "sg:city":"Cordoba",
    "sg:orig_category":"M\u00c9dicos: An\u00c1lisis Cl\u00cdnicos",
    "sg:phone":"+34 957 45 42 14",
    "sg:postcode":"14004",
    "sg:province":"C\u00f3rdoba",
    "wof:name":"Aeropuerto Analistas Clinicos C.b.",
    "wof:placetype":"venue"
},
  "geometry": {"coordinates":[-4.7943353653,37.8768539429],"type":"Point"}
}