{
  "type": "Feature",
  "properties": {
    "iso:country":"ES",
    "sg:address":"Quintanal, S/n",
    "sg:city":"Soto Barco",
    "sg:orig_category":"Construcciones Met\u00c1licas",
    "sg:phone":"+34 985 58 80 03",
    "sg:postcode":"33126",
    "sg:province":"Asturias",
    "wof:name":"Asturiana De Cubiertas Y Estructuras S.l",
    "wof:placetype":"venue"
},
  "geometry": {"coordinates":[-6.0760650635,43.5309333801],"type":"Point"}
}