{
  "type": "Feature",
  "properties": {
    "addr:full":"Calle de Galerene, 7 Algorta Vizcaya 48993",
    "addr:housenumber":"7",
    "addr:postcode":"48993",
    "addr:street":"Calle De Galerene",
    "iso:country":"ES",
    "sg:address":"Calle de Galerene, 7",
    "sg:city":"Algorta",
    "sg:orig_category":"Empresarios Y Productoras De Espect\u00c1culos",
    "sg:phone":"+34 944 60 40 41",
    "sg:postcode":"48993",
    "sg:province":"Vizcaya",
    "wof:name":"Luengo Valderrey Maria Jesus",
    "wof:placetype":"venue"
},
  "geometry": {"coordinates":[-3.0157039165,43.3535423279],"type":"Point"}
}