{
  "type": "Feature",
  "properties": {
    "iso:country":"ES",
    "sg:address":"Calle de Martin Fernandez Villaran, 2",
    "sg:city":"Portugalete",
    "sg:classifiers":[
        {
            "category":"Casinos & Gambling",
            "type":"Entertainment"
        }
    ],
    "sg:phone":"+34 944 61 57 92",
    "sg:postcode":"48920",
    "sg:province":"Vizcaya",
    "sg:tags":[
        "locale",
        "de",
        "juego"
    ],
    "wof:name":"Felesa S. A.",
    "wof:placetype":"venue"
},
  "geometry": {"coordinates":[-3.0194170475,43.3219604492],"type":"Point"}
}