{
  "type": "Feature",
  "properties": {
    "iso:country":"ES",
    "sg:address":"Av Catalunya, 25",
    "sg:city":"Cerdanyola Valles",
    "sg:orig_category":"M\u00c9dicos: Estomatolog\u00cda",
    "sg:phone":"+34 936 92 52 53",
    "sg:postcode":"08290",
    "sg:province":"Barcelona",
    "wof:name":"Moral Gomez Carlos Narciso",
    "wof:placetype":"venue"
},
  "geometry": {"coordinates":[2.1457350254,41.4926452637],"type":"Point"}
}