{
  "type": "Feature",
  "properties": {
    "addr:full":"Calle de Nueva De La Virgen, 9 Granada Granada 18005",
    "addr:housenumber":"9",
    "addr:postcode":"18005",
    "addr:street":"Calle De Nueva De La Virgen",
    "iso:country":"ES",
    "sg:address":"Calle de Nueva De La Virgen, 9",
    "sg:city":"Granada",
    "sg:orig_category":"Arboricultura Y Producci\u00d3n De Frutas",
    "sg:phone":"+34 958 52 31 70",
    "sg:postcode":"18005",
    "sg:province":"Granada",
    "wof:name":"Granada Comercial De Aromas S.l.",
    "wof:placetype":"venue"
},
  "geometry": {"coordinates":[-3.5979158878,37.1690788269],"type":"Point"}
}