{
  "type": "Feature",
  "properties": {
    "iso:country":"ES",
    "sg:address":"Ctra Sevilla-lora Del Rio, Km. 0032,5",
    "sg:city":"Rosales",
    "sg:orig_category":"Arboricultura Y Producci\u00d3n De Frutas",
    "sg:phone":"+34 955 64 56 72",
    "sg:postcode":"41330",
    "sg:province":"Sevilla",
    "wof:name":"El Recreo S. A. T.",
    "wof:placetype":"venue"
},
  "geometry": {"coordinates":[-5.7319440842,37.5898590088],"type":"Point"}
}