{
  "type": "Feature",
  "properties": {
    "iso:country":"ES",
    "sg:address":"Carr Maragda, 10",
    "sg:city":"Blanes",
    "sg:orig_category":"Promotores Constructores",
    "sg:phone":"+34 972 35 31 85",
    "sg:postcode":"17300",
    "sg:province":"Girona",
    "wof:name":"Montemar Construcciones Y Reformas Sl",
    "wof:placetype":"venue"
},
  "geometry": {"coordinates":[2.7853069305,41.6703872681],"type":"Point"}
}