{
  "type": "Feature",
  "properties": {
    "addr:full":"La Iglesia, 1 Vinuesa Soria 42150",
    "addr:housenumber":"1",
    "addr:postcode":"42150",
    "addr:street":"Iglesia",
    "iso:country":"ES",
    "sg:address":"La Iglesia, 1",
    "sg:city":"Vinuesa",
    "sg:orig_category":"Iglesia Cat\u00d3lica",
    "sg:phone":"+34 975 37 80 67",
    "sg:postcode":"42150",
    "sg:province":"Soria",
    "wof:name":"Parroquia Nuestra Se\u00f1ora Del Pino",
    "wof:placetype":"venue"
},
  "geometry": {"coordinates":[-2.7633290291,41.9116210938],"type":"Point"}
}