{
  "type": "Feature",
  "properties": {
    "addr:full":"Carrer de Mallorca, 103 Barcelona Barcelona 08029",
    "addr:housenumber":"103",
    "addr:postcode":"08029",
    "addr:street":"Carrer De Mallorca",
    "iso:country":"ES",
    "sg:address":"Carrer de Mallorca, 103",
    "sg:city":"Barcelona",
    "sg:orig_category":"Promotores Constructores",
    "sg:phone":"+34 934 52 56 15",
    "sg:postcode":"08029",
    "sg:province":"Barcelona",
    "wof:name":"Rom Gestion Inmobiliaria S.l.",
    "wof:placetype":"venue"
},
  "geometry": {"coordinates":[2.1520299911,41.3860931396],"type":"Point"}
}