{
  "type": "Feature",
  "properties": {
    "addr:full":"Calle de Aviador Lindbergh, 3 Madrid Madrid 28002",
    "addr:housenumber":"3",
    "addr:postcode":"28002",
    "addr:street":"Calle De Aviador Lindbergh",
    "iso:country":"ES",
    "sg:address":"Calle de Aviador Lindbergh, 3",
    "sg:city":"Madrid",
    "sg:classifiers":[
        {
            "category":"Professional",
            "subcategory":"Management & Consulting",
            "type":"Services"
        }
    ],
    "sg:phone":"+34 915 70 54 75",
    "sg:postcode":"28002",
    "sg:province":"Madrid",
    "sg:tags":[
        "asesor\u00cda",
        "en",
        "marketing"
    ],
    "sg:website":"www.delfingroup.com",
    "wof:name":"Delfin Time S.l.",
    "wof:placetype":"venue"
},
  "geometry": {"coordinates":[-3.6796398163,40.4424095154],"type":"Point"}
}