{
  "type": "Feature",
  "properties": {
    "addr:full":"Calle de Pez Volador, 15 Madrid Madrid 28007",
    "addr:housenumber":"15",
    "addr:postcode":"madrid;28007",
    "addr:street":"Calle De Pez Volador",
    "iso:country":"ES",
    "sg:address":"Calle de Pez Volador, 15",
    "sg:city":"Madrid",
    "sg:orig_category":"Ingeniero",
    "sg:phone":"+34 915 73 64 98",
    "sg:postcode":"28007",
    "sg:province":"Madrid",
    "wof:name":"Alda Gonzalez Victor",
    "wof:placetype":"venue"
},
  "geometry": {"coordinates":[-3.6672434807,40.4136810303],"type":"Point"}
}