{
  "type": "Feature",
  "properties": {
    "addr:full":"Plaz Salvador Del Mundo, S/n Calzada Calatrava Ciudad Real 13370",
    "addr:postcode":"13370",
    "addr:street":"Mundo S / N Calzada Calatrava",
    "iso:country":"ES",
    "sg:address":"Plaz Salvador Del Mundo, S/n",
    "sg:city":"Calzada Calatrava",
    "sg:orig_category":"Molduras, Junquillos, Listones Y Molduras Perforadas",
    "sg:phone":"+34 926 87 50 11",
    "sg:postcode":"13370",
    "sg:province":"Ciudad Real",
    "wof:name":"Trujillo Trujillo Antonio",
    "wof:placetype":"venue"
},
  "geometry": {"coordinates":[-3.7751739025,38.7053565979],"type":"Point"}
}