{
  "type": "Feature",
  "properties": {
    "iso:country":"ES",
    "sg:address":"Carrer de El.lipse, 19",
    "sg:city":"Hospitalet Llobregat",
    "sg:orig_category":"Molduras, Junquillos, Listones Y Molduras Perforadas",
    "sg:phone":"+34 934 49 98 24",
    "sg:postcode":"08905",
    "sg:province":"Barcelona",
    "wof:name":"Luna Moran Manuel",
    "wof:placetype":"venue"
},
  "geometry": {"coordinates":[2.1078081131,41.3737792969],"type":"Point"}
}