{
  "type": "Feature",
  "properties": {
    "iso:country":"ES",
    "sg:address":"Calle de Jose Antonio, 34",
    "sg:city":"Orihuela",
    "sg:orig_category":"M\u00c9dicos: Psiquiatr\u00cda",
    "sg:phone":"+34 966 74 38 38",
    "sg:postcode":"03300",
    "sg:province":"Alicante",
    "wof:name":"Correa Esta\u00f1 Ricardo",
    "wof:placetype":"venue"
},
  "geometry": {"coordinates":[-0.9453780055,38.083240509],"type":"Point"}
}