{
  "type": "Feature",
  "properties": {
    "addr:full":"Calle de General Espartero, 14 Alzira Valencia 46600",
    "addr:housenumber":"14",
    "addr:postcode":"46600",
    "addr:street":"Calle De General Espartero",
    "iso:country":"ES",
    "sg:address":"Calle de General Espartero, 14",
    "sg:city":"Alzira",
    "sg:orig_category":"Estancos",
    "sg:phone":"+34 962 40 41 23",
    "sg:postcode":"46600",
    "sg:province":"Valencia",
    "wof:name":"March Peiro Maite",
    "wof:placetype":"venue"
},
  "geometry": {"coordinates":[-0.4291599989,39.1598587036],"type":"Point"}
}