{
  "type": "Feature",
  "properties": {
    "iso:country":"ES",
    "sg:address":"Ctra San Rafael, Km. 0092,8",
    "sg:city":"Segovia",
    "sg:orig_category":"Molduras, Junquillos, Listones Y Molduras Perforadas",
    "sg:phone":"+34 921 44 80 95",
    "sg:postcode":"40006",
    "sg:province":"Segovia",
    "wof:name":"Maria Gutierrez Roberto",
    "wof:placetype":"venue"
},
  "geometry": {"coordinates":[-4.1075577736,40.9319610596],"type":"Point"}
}