{
  "type": "Feature",
  "properties": {
    "addr:full":"Derramadero De Cabriles, S/n Ejido Almer\u00eda 04700",
    "addr:housenumber":"s",
    "addr:postcode":"04700",
    "addr:street":"/ N Ejido Almeri\u0301A",
    "iso:country":"ES",
    "sg:address":"Derramadero De Cabriles, S/n",
    "sg:city":"Ejido",
    "sg:orig_category":"Invernaderos Y Semilleros",
    "sg:phone":"+34 950 48 42 57",
    "sg:postcode":"04700",
    "sg:province":"Almer\u00eda",
    "wof:name":"Construcciones De Invernaderos Agro-inver S.l.",
    "wof:placetype":"venue"
},
  "geometry": {"coordinates":[-2.8176040649,36.7727012634],"type":"Point"}
}