{
  "type": "Feature",
  "properties": {
    "iso:country":"ES",
    "sg:address":"Ctra N-152, Km. 0023,9",
    "sg:city":"Can Gosc",
    "sg:orig_category":"Electricidad: Equipos Industriales, Componentes (fabricaci\u00d3n)",
    "sg:phone":"+34 935 62 43 52",
    "sg:postcode":"08150",
    "sg:province":"Barcelona",
    "wof:name":"Grupo Corona Espa\u00d1a-2 S.a.",
    "wof:placetype":"venue"
},
  "geometry": {"coordinates":[2.2293000221,41.5678787231],"type":"Point"}
}