{
  "type": "Feature",
  "properties": {
    "iso:country":"ES",
    "sg:address":"Carrer de Cremat, 23",
    "sg:city":"Terrassa",
    "sg:orig_category":"Bisuter\u00cda, Joyer\u00cda, Relojer\u00cda (al Por Menor)",
    "sg:phone":"+34 937 88 77 66",
    "sg:postcode":"08221",
    "sg:province":"Barcelona",
    "wof:name":"Joieria Carmina Puig S.l.",
    "wof:placetype":"venue"
},
  "geometry": {"coordinates":[2.0101959705,41.5626602173],"type":"Point"}
}