{
  "type": "Feature",
  "properties": {
    "addr:full":"Calle de Loperraez, 1 Soria Soria 42004",
    "addr:housenumber":"1",
    "addr:postcode":"42004",
    "addr:street":"Calle De Loperraez",
    "iso:country":"ES",
    "sg:address":"Calle de Loperraez, 1",
    "sg:city":"Soria",
    "sg:orig_category":"M\u00c9dicos: Otorrinolaringolog\u00cda",
    "sg:phone":"+34 975 22 43 76",
    "sg:postcode":"42004",
    "sg:province":"Soria",
    "wof:name":"Garzon Calles Jose Angel",
    "wof:placetype":"venue"
},
  "geometry": {"coordinates":[-2.4778990746,41.7644309998],"type":"Point"}
}