{
  "type": "Feature",
  "properties": {
    "addr:full":"Avda Cristo De La Expiracion, 1 Sevilla Sevilla 41001",
    "addr:housenumber":"1",
    "addr:postcode":"41001",
    "addr:street":"Avda Cristo De La Expiracion",
    "iso:country":"ES",
    "sg:address":"Avda Cristo De La Expiracion, 1",
    "sg:city":"Sevilla",
    "sg:orig_category":"Material Y Herramientas Agr\u00cdcolas",
    "sg:phone":"+34 954 22 76 83",
    "sg:postcode":"41001",
    "sg:province":"Sevilla",
    "wof:name":"Maquinaria Anguis S.l.",
    "wof:placetype":"venue"
},
  "geometry": {"coordinates":[-6.0033960342,37.3904914856],"type":"Point"}
}