{
  "type": "Feature",
  "properties": {
    "addr:full":"Psaj Doctor Bartual Moret, 5 Valencia Valencia 46010",
    "addr:housenumber":"5",
    "addr:postcode":"46010",
    "addr:street":"Doctor Bartual Moret",
    "iso:country":"ES",
    "sg:address":"Psaj Doctor Bartual Moret, 5",
    "sg:city":"Valencia",
    "sg:orig_category":"Ense\u00d1anza: Idiomas",
    "sg:phone":"+34 963 93 52 52",
    "sg:postcode":"46010",
    "sg:province":"Valencia",
    "wof:name":"Carlos Blasco Calatayud",
    "wof:placetype":"venue"
},
  "geometry": {"coordinates":[-0.3570330143,39.4776115417],"type":"Point"}
}