{
  "type": "Feature",
  "properties": {
    "iso:country":"ES",
    "sg:address":"Calle de Toledo, 7",
    "sg:city":"Badajoz",
    "sg:orig_category":"Laboratorios Y Cl\u00cdnicas Veterinarias",
    "sg:phone":"+34 924 22 22 30",
    "sg:postcode":"06008",
    "sg:province":"Badajoz",
    "wof:name":"Perez Moreno Paulina",
    "wof:placetype":"venue"
},
  "geometry": {"coordinates":[-6.9590988159,38.879650116],"type":"Point"}
}