{
  "type": "Feature",
  "properties": {
    "addr:full":"Poli Ind. Faima, Km. 0049,0 Poligono Industrial Faima Alicante 03330",
    "addr:postcode":"03330",
    "addr:street":"Faima Km. 0049,0 Poligono Industrial",
    "iso:country":"ES",
    "sg:address":"Poli Ind. Faima, Km. 0049,0",
    "sg:city":"Poligono Industrial Faima",
    "sg:orig_category":"Reciclaje, Tratamiento De Tejidos",
    "sg:phone":"+34 965 40 62 32",
    "sg:postcode":"03330",
    "sg:province":"Alicante",
    "wof:name":"Acabados Nueva-tex S.l.",
    "wof:placetype":"venue"
},
  "geometry": {"coordinates":[-0.481006,38.345203],"type":"Point"}
}