{
  "type": "Feature",
  "properties": {
    "iso:country":"ES",
    "sg:address":"Avda Andalucia, S/n",
    "sg:city":"Fuensanta Martos",
    "sg:orig_category":"Tapicer\u00cdas",
    "sg:phone":"+34 953 56 30 57",
    "sg:postcode":"23610",
    "sg:province":"Ja\u00e9n",
    "wof:name":"Ortega Torres Ramon",
    "wof:placetype":"venue"
},
  "geometry": {"coordinates":[-3.9158089161,37.6462097168],"type":"Point"}
}