{
  "type": "Feature",
  "properties": {
    "iso:country":"ES",
    "sg:address":"Calle de Pablo Picasso, S/n",
    "sg:city":"Alcala Guadaira",
    "sg:orig_category":"Asociaciones Humanitarias, De Cooperaci\u00d3n, De Acci\u00d3n Social",
    "sg:phone":"+34 955 62 01 96",
    "sg:postcode":"41500",
    "sg:province":"Sevilla",
    "wof:name":"Infotelcom Telefonia Publica S.c.",
    "wof:placetype":"venue"
},
  "geometry": {"coordinates":[-5.8448109627,37.3484077454],"type":"Point"}
}