{
  "type": "Feature",
  "properties": {
    "iso:country":"ES",
    "sg:address":"Calle de Pedro Alfaro, 5",
    "sg:city":"Burgos",
    "sg:orig_category":"Supermercados Y Hipermercados",
    "sg:phone":"+34 947 48 36 80",
    "sg:postcode":"09007",
    "sg:province":"Burgos",
    "wof:name":"Eroski Sociedad Cooperativa",
    "wof:placetype":"venue"
},
  "geometry": {"coordinates":[-3.6651010513,42.3538589478],"type":"Point"}
}