{
  "type": "Feature",
  "properties": {
    "addr:full":"Calle de Eleuterio Quintanilla, 22 Gijon Asturias 33208",
    "addr:housenumber":"22",
    "addr:postcode":"33208",
    "addr:street":"Calle De Eleuterio Quintanilla",
    "iso:country":"ES",
    "sg:address":"Calle de Eleuterio Quintanilla, 22",
    "sg:city":"Gijon",
    "sg:orig_category":"Venta, Instalaci\u00d3n De Calefacci\u00d3n",
    "sg:phone":"+34 985 38 53 54",
    "sg:postcode":"33208",
    "sg:province":"Asturias",
    "wof:name":"Lopez Rey Francisco Javier",
    "wof:placetype":"venue"
},
  "geometry": {"coordinates":[-5.6691012383,43.5315284729],"type":"Point"}
}