{
  "type": "Feature",
  "properties": {
    "iso:country":"ES",
    "sg:address":"Al-andalus, 6",
    "sg:city":"Medina-sidonia",
    "sg:orig_category":"Cr\u00cda De Animales",
    "sg:phone":"+34 956 41 04 34",
    "sg:postcode":"11170",
    "sg:province":"C\u00e1diz",
    "wof:name":"Jose Maria Avila Fornell S.l.",
    "wof:placetype":"venue"
},
  "geometry": {"coordinates":[-5.9275169373,36.4657745361],"type":"Point"}
}