{
  "type": "Feature",
  "properties": {
    "addr:full":"Av Costa Brava, 2 Tossa Girona 17320",
    "addr:housenumber":"2",
    "addr:postcode":"17320",
    "addr:street":"Av Costa Brava",
    "iso:country":"ES",
    "sg:address":"Av Costa Brava, 2",
    "sg:city":"Tossa",
    "sg:orig_category":"Laboratorios Y Trabajos De Fotograf\u00cda, V\u00cddeo Y Cine",
    "sg:phone":"+34 972 34 28 56",
    "sg:postcode":"17320",
    "sg:province":"Girona",
    "wof:name":"Tot Foto De Tossa S.l.u.",
    "wof:placetype":"venue"
},
  "geometry": {"coordinates":[2.9317729473,41.7207374573],"type":"Point"}
}