{
  "type": "Feature",
  "properties": {
    "addr:full":"Carrer de Llan\u00c7a, 35 Barcelona Barcelona 08015",
    "addr:housenumber":"35",
    "addr:postcode":"08015",
    "addr:street":"Carrer De Llanc\u0327A",
    "iso:country":"ES",
    "sg:address":"Carrer de Llan\u00c7a, 35",
    "sg:city":"Barcelona",
    "sg:orig_category":"Farmacias",
    "sg:phone":"+34 932 26 33 31",
    "sg:postcode":"08015",
    "sg:province":"Barcelona",
    "wof:name":"Miret Alvarez S.c.p",
    "wof:placetype":"venue"
},
  "geometry": {"coordinates":[2.1460709572,41.3794517517],"type":"Point"}
}