{
  "type": "Feature",
  "properties": {
    "addr:full":"Avda Entrevias, 94 Madrid Madrid 28053",
    "addr:housenumber":"94",
    "addr:postcode":"madrid;28053",
    "addr:street":"Avda Entrevias",
    "iso:country":"ES",
    "sg:address":"Avda Entrevias, 94",
    "sg:city":"Madrid",
    "sg:orig_category":"Venta, Instalaci\u00d3n De Calefacci\u00d3n",
    "sg:phone":"+34 915 07 72 80",
    "sg:postcode":"28053",
    "sg:province":"Madrid",
    "wof:name":"Af S.l.",
    "wof:placetype":"venue"
},
  "geometry": {"coordinates":[-3.6638131142,40.377948761],"type":"Point"}
}