{
  "type": "Feature",
  "properties": {
    "iso:country":"ES",
    "sg:address":"Plaza Irun De, 4",
    "sg:city":"Donostia-san Sebastian",
    "sg:orig_category":"Artes Gr\u00c1ficas, Artes Pl\u00c1sticas (curso)",
    "sg:phone":"+34 943 31 42 62",
    "sg:postcode":"20011",
    "sg:province":"Guip\u00f9zcoa",
    "wof:name":"Eusko Design Proyectos De Maquinaria Industrial, S.l.",
    "wof:placetype":"venue"
},
  "geometry": {"coordinates":[-1.9745049477,43.3049926758],"type":"Point"}
}