{
  "type": "Feature",
  "properties": {
    "iso:country":"ES",
    "sg:address":"Avda San Jose, 190",
    "sg:city":"Zaragoza",
    "sg:orig_category":"Fabricaci\u00d3n De Cortinas Y Visillos",
    "sg:phone":"+34 976 25 37 45",
    "sg:postcode":"50007",
    "sg:province":"Zaragoza",
    "wof:name":"Jaraba Ainsa Milagros",
    "wof:placetype":"venue"
},
  "geometry": {"coordinates":[-0.8791099787,41.6359558105],"type":"Point"}
}