{
  "type": "Feature",
  "properties": {
    "iso:country":"ES",
    "sg:address":"Calle de Rey Juan Carlos, 16",
    "sg:city":"Villanueva De Los Infantes",
    "sg:orig_category":"Abogados",
    "sg:phone":"+34 926 36 00 98",
    "sg:postcode":"13320",
    "sg:province":"Ciudad Real",
    "wof:name":"Fernandez De Sevilla Y Fernandez De Sevilla Miguel",
    "wof:placetype":"venue"
},
  "geometry": {"coordinates":[-3.0118889809,38.7377090454],"type":"Point"}
}