{
  "type": "Feature",
  "properties": {
    "iso:country":"ES",
    "sg:address":"Calle de San Roque, 4",
    "sg:city":"Luanco",
    "sg:orig_category":"Sociedades, Compa\u00d1\u00cdas Aseguradoras",
    "sg:phone":"+34 985 88 21 08",
    "sg:postcode":"33440",
    "sg:province":"Asturias",
    "wof:name":"Mapfre Servicios De Informatica",
    "wof:placetype":"venue"
},
  "geometry": {"coordinates":[-5.7918949127,43.6163253784],"type":"Point"}
}