{
  "type": "Feature",
  "properties": {
    "iso:country":"ES",
    "sg:address":"Calle de Ciudad Real, 3",
    "sg:city":"Medina Campo",
    "sg:orig_category":"Inmobiliaria (agencias)",
    "sg:phone":"+34 983 80 45 51",
    "sg:postcode":"47400",
    "sg:province":"Valladolid",
    "wof:name":"Velasco Rico Demetrio",
    "wof:placetype":"venue"
},
  "geometry": {"coordinates":[-4.9172902107,41.3030128479],"type":"Point"}
}