{
  "type": "Feature",
  "properties": {
    "addr:full":"Carrer de Mare De Deu Dels Desemparats, 60 Hospitalet Llobregat Barcelona 08903",
    "addr:housenumber":"60",
    "addr:postcode":"08903",
    "addr:street":"Carrer De Mare De Deu;Desemparats",
    "iso:country":"ES",
    "sg:address":"Carrer de Mare De Deu Dels Desemparats, 60",
    "sg:city":"Hospitalet Llobregat",
    "sg:orig_category":"Empresas De Carpinter\u00cda De Madera",
    "sg:phone":"+34 934 49 71 35",
    "sg:postcode":"08903",
    "sg:province":"Barcelona",
    "wof:name":"Gascon Gargallo Tomas",
    "wof:placetype":"venue"
},
  "geometry": {"coordinates":[2.1230649948,41.3713340759],"type":"Point"}
}