{
  "type": "Feature",
  "properties": {
    "iso:country":"ES",
    "sg:address":"Carr Comer\u00c7, 13",
    "sg:city":"Angles",
    "sg:orig_category":"Zapater\u00cdas",
    "sg:phone":"+34 972 42 09 97",
    "sg:postcode":"17160",
    "sg:province":"Girona",
    "wof:name":"Nadal Vila Marta",
    "wof:placetype":"venue"
},
  "geometry": {"coordinates":[2.6347820759,41.9582252502],"type":"Point"}
}