{
  "type": "Feature",
  "properties": {
    "addr:full":"Rbra Zorrotzaurre, 17 Bilbao Vizcaya 48014",
    "addr:housenumber":"17",
    "addr:postcode":"48014",
    "addr:street":"Zorrotzaurre",
    "iso:country":"ES",
    "sg:address":"Rbra Zorrotzaurre, 17",
    "sg:city":"Bilbao",
    "sg:orig_category":"Maquinaria Para Industrias Diversas",
    "sg:phone":"+34 944 75 29 86",
    "sg:postcode":"48014",
    "sg:province":"Vizcaya",
    "wof:name":"Suminan S.l.",
    "wof:placetype":"venue"
},
  "geometry": {"coordinates":[-2.9672560692,43.2752723694],"type":"Point"}
}