{
  "type": "Feature",
  "properties": {
    "iso:country":"ES",
    "sg:address":"Carrer de Elkano, 63",
    "sg:city":"Barcelona",
    "sg:orig_category":"Molduras, Junquillos, Listones Y Molduras Perforadas",
    "sg:phone":"+34 934 42 31 40",
    "sg:postcode":"08004",
    "sg:province":"Barcelona",
    "wof:name":"Lopez Fernandez Manuel",
    "wof:placetype":"venue"
},
  "geometry": {"coordinates":[2.1601769924,41.373916626],"type":"Point"}
}