{
  "type": "Feature",
  "properties": {
    "addr:full":"Carr Francesc Salva I Piza-escultor, 27 Pont D'inca Islas Baleares 07009",
    "addr:housenumber":"27",
    "addr:postcode":"07009",
    "addr:street":"Carr Francesc Salva;Piza-Escultor;Pont D'Inca",
    "iso:country":"ES",
    "sg:address":"Carr Francesc Salva I Piza-escultor, 27",
    "sg:city":"Pont D'inca",
    "sg:orig_category":"Institutos De Belleza",
    "sg:phone":"+34 971 79 40 48",
    "sg:postcode":"07009",
    "sg:province":"Islas Baleares",
    "wof:name":"Rodriguez Garrocho Raquel",
    "wof:placetype":"venue"
},
  "geometry": {"coordinates":[2.8994529247,39.7163963318],"type":"Point"}
}