{
  "type": "Feature",
  "properties": {
    "iso:country":"ES",
    "sg:address":"Rua Cami\u00d1o Real (do), 137",
    "sg:city":"Lugo",
    "sg:orig_category":"Transporte En General",
    "sg:phone":"+34 982 21 07 12",
    "sg:postcode":"27004",
    "sg:province":"Lugo",
    "wof:name":"Vego Supermercados S.a.",
    "wof:placetype":"venue"
},
  "geometry": {"coordinates":[-7.5654559135,43.0186233521],"type":"Point"}
}