{
  "type": "Feature",
  "properties": {
    "iso:country":"ES",
    "sg:address":"Calle de Buen Suceso, 25",
    "sg:city":"Madrid",
    "sg:orig_category":"Agencias Y Asesores De Publicidad",
    "sg:phone":"+34 915 47 20 77",
    "sg:postcode":"28008",
    "sg:province":"Madrid",
    "wof:name":"Creativos Asociados S. A.",
    "wof:placetype":"venue"
},
  "geometry": {"coordinates":[-3.719892025,40.4278793335],"type":"Point"}
}