{
  "type": "Feature",
  "properties": {
    "addr:full":"Calle de Cuatro Pinos, 35 Pozuelo De Alarcon Madrid 28224",
    "addr:housenumber":"35",
    "addr:postcode":"28224",
    "addr:street":"Calle De Cuatro Pinos",
    "iso:country":"ES",
    "sg:address":"Calle de Cuatro Pinos, 35",
    "sg:city":"Pozuelo De Alarcon",
    "sg:orig_category":"Importaci\u00d3n",
    "sg:phone":"+34 913 51 95 84",
    "sg:postcode":"28224",
    "sg:province":"Madrid",
    "wof:name":"Zelart S.l.",
    "wof:placetype":"venue"
},
  "geometry": {"coordinates":[-3.8070352077,40.4428100586],"type":"Point"}
}