{
  "type": "Feature",
  "properties": {
    "iso:country":"ES",
    "sg:address":"Carrer de Enric Prat De La Riba, 166",
    "sg:city":"Hospitalet Llobregat",
    "sg:orig_category":"Ropa Para Ni\u00d1os (al Por Menor)",
    "sg:phone":"+34 933 38 36 52",
    "sg:postcode":"08901",
    "sg:province":"Barcelona",
    "wof:name":"Chrisandel S.l",
    "wof:placetype":"venue"
},
  "geometry": {"coordinates":[2.1072459221,41.3618125916],"type":"Point"}
}