{
  "type": "Feature",
  "properties": {
    "addr:full":"Calle de Fragua, 31 Ontigola Toledo 45340",
    "addr:housenumber":"31",
    "addr:postcode":"45340",
    "addr:street":"Calle De Fragua",
    "iso:country":"ES",
    "sg:address":"Calle de Fragua, 31",
    "sg:city":"Ontigola",
    "sg:orig_category":"Supermercados Y Hipermercados",
    "sg:phone":"+34 925 12 71 76",
    "sg:postcode":"45340",
    "sg:province":"Toledo",
    "wof:name":"Luis Gil Jose Angel",
    "wof:placetype":"venue"
},
  "geometry": {"coordinates":[-3.571999073,40.0025787354],"type":"Point"}
}