{
  "type": "Feature",
  "properties": {
    "iso:country":"ES",
    "sg:address":"Avda Pio Baroja, 2",
    "sg:city":"Malaga",
    "sg:orig_category":"Molduras, Junquillos, Listones Y Molduras Perforadas",
    "sg:phone":"+34 952 20 18 30",
    "sg:postcode":"29017",
    "sg:province":"M\u00e1laga",
    "wof:name":"Garcia Mendoza Ramon",
    "wof:placetype":"venue"
},
  "geometry": {"coordinates":[-4.3653802872,36.720451355],"type":"Point"}
}