{
  "type": "Feature",
  "properties": {
    "addr:full":"Ansoain-antsoain Kalea, 3 Iru\u00f1a Navarra 31014",
    "addr:housenumber":"3",
    "addr:postcode":"31014",
    "addr:street":"Ansoain-Antsoain Kalea",
    "iso:country":"ES",
    "sg:address":"Ansoain-antsoain Kalea, 3",
    "sg:city":"Iru\u00f1a",
    "sg:orig_category":"Asociaciones Y Clubs Deportivos",
    "sg:phone":"+34 948 12 61 96",
    "sg:postcode":"31014",
    "sg:province":"Navarra",
    "wof:name":"Bonafau Escribano Angeles",
    "wof:placetype":"venue"
},
  "geometry": {"coordinates":[-1.6446139812,42.828994751],"type":"Point"}
}