{
  "type": "Feature",
  "properties": {
    "iso:country":"ES",
    "sg:address":"Carrer de Marconi, S/n",
    "sg:city":"Rubi",
    "sg:orig_category":"Sanatorios M\u00c9dico",
    "sg:phone":"+34 935 88 45 55",
    "sg:postcode":"08191",
    "sg:province":"Barcelona",
    "wof:name":"Consorci Sanitari De Terrassa",
    "wof:placetype":"venue"
},
  "geometry": {"coordinates":[2.0369000435,41.4851837158],"type":"Point"}
}