{
  "type": "Feature",
  "properties": {
    "iso:country":"ES",
    "sg:address":"Carr Francisco Carbonell, 22",
    "sg:city":"Rocafort",
    "sg:orig_category":"Pescader\u00cdas (al Por Menor)",
    "sg:phone":"+34 961 31 21 80",
    "sg:postcode":"46111",
    "sg:province":"Valencia",
    "wof:name":"Garcia Mestre Jose",
    "wof:placetype":"venue"
},
  "geometry": {"coordinates":[-0.4099799991,39.5304260254],"type":"Point"}
}