{
  "type": "Feature",
  "properties": {
    "iso:country":"ES",
    "sg:address":"Rier Blanca, 85",
    "sg:city":"Barcelona",
    "sg:orig_category":"Estudios Y Construcci\u00d3n De Acuarios Y Viveros",
    "sg:phone":"+34 933 33 98 87",
    "sg:postcode":"08028",
    "sg:province":"Barcelona",
    "wof:name":"Caja Merchan Jose Luis",
    "wof:placetype":"venue"
},
  "geometry": {"coordinates":[2.1259400845,41.3726730347],"type":"Point"}
}