{
  "type": "Feature",
  "properties": {
    "iso:country":"ES",
    "sg:address":"Del Bajel (p I Zabal Bajo), 7",
    "sg:city":"La Linea",
    "sg:orig_category":"Mec\u00c1nico Del Autom\u00d3vil",
    "sg:phone":"+34 956 64 30 01",
    "sg:postcode":"11300",
    "sg:province":"C\u00e1diz",
    "wof:name":"Sanchez Rojas Ana Isabel",
    "wof:placetype":"venue"
},
  "geometry": {"coordinates":[-5.3529138565,36.1851615906],"type":"Point"}
}