{
  "type": "Feature",
  "properties": {
    "addr:full":"Pol Ind Cipreses, 99 Castello Plana Castell\u00f3n 12006",
    "addr:housenumber":"99",
    "addr:postcode":"12006",
    "addr:street":"Castello\u0301N",
    "iso:country":"ES",
    "sg:address":"Pol Ind Cipreses, 99",
    "sg:city":"Castello Plana",
    "sg:orig_category":"Ingenier\u00cda, Centros De Estudios (diversos)",
    "sg:phone":"+34 964 25 72 63",
    "sg:postcode":"12006",
    "sg:province":"Castell\u00f3n",
    "wof:name":"Instalaciones Electricidad Ingenieria Y Servicios S.l.",
    "wof:placetype":"venue"
},
  "geometry": {"coordinates":[-0.1292939931,40.0168533325],"type":"Point"}
}