{
  "type": "Feature",
  "properties": {
    "addr:full":"Calle de Virgen De La Vega, 38 Haro La Rioja 26200",
    "addr:housenumber":"38",
    "addr:postcode":"26200",
    "addr:street":"Calle De Virgen De La Vega",
    "iso:country":"ES",
    "sg:address":"Calle de Virgen De La Vega, 38",
    "sg:city":"Haro",
    "sg:orig_category":"Inmobiliaria (agencias)",
    "sg:phone":"+34 941 31 26 76",
    "sg:postcode":"26200",
    "sg:province":"La Rioja",
    "wof:name":"Inmobiliaria Vicente Ceballos S.l.",
    "wof:placetype":"venue"
},
  "geometry": {"coordinates":[-2.8502039909,42.5764427185],"type":"Point"}
}