{
  "type": "Feature",
  "properties": {
    "iso:country":"ES",
    "sg:address":"Calle de San Vicente, 20",
    "sg:city":"Alacant",
    "sg:orig_category":"M\u00c9dicos: Cardiolog\u00cda Y Afecciones Cardiovasculares",
    "sg:phone":"+34 965 14 02 54",
    "sg:postcode":"03004",
    "sg:province":"Alicante",
    "wof:name":"Garcia Godinez Melchor",
    "wof:placetype":"venue"
},
  "geometry": {"coordinates":[-0.484596014,38.34923172],"type":"Point"}
}