{
  "type": "Feature",
  "properties": {
    "iso:country":"ES",
    "sg:address":"Carr Cases Noves, 122",
    "sg:city":"Palafrugell",
    "sg:orig_category":"Empresas De Carpinter\u00cda De Madera",
    "sg:phone":"+34 972 30 03 89",
    "sg:postcode":"17200",
    "sg:province":"Girona",
    "wof:name":"Vila Coll Josep",
    "wof:placetype":"venue"
},
  "geometry": {"coordinates":[3.15741992,41.9198989868],"type":"Point"}
}