{
  "type": "Feature",
  "properties": {
    "iso:country":"ES",
    "sg:address":"Calle de Marin Moll Duniach, 3",
    "sg:city":"Palma",
    "sg:orig_category":"Peluqueros: De Se\u00d1oras",
    "sg:phone":"+34 971 45 20 64",
    "sg:postcode":"07014",
    "sg:province":"Islas Baleares",
    "wof:name":"Peluqueria Comeche S.l.",
    "wof:placetype":"venue"
},
  "geometry": {"coordinates":[2.6300139427,39.5707855225],"type":"Point"}
}