{
  "type": "Feature",
  "properties": {
    "iso:country":"ES",
    "sg:address":"Rua Adro, 21",
    "sg:city":"Redondela",
    "sg:orig_category":"Ense\u00d1anza: Costura",
    "sg:phone":"+34 986 40 05 88",
    "sg:postcode":"36800",
    "sg:province":"Pontevedra",
    "wof:name":"Rodriguez Lago Carmen",
    "wof:placetype":"venue"
},
  "geometry": {"coordinates":[-8.6079177856,42.2828102112],"type":"Point"}
}