{
  "type": "Feature",
  "properties": {
    "iso:country":"ES",
    "sg:address":"Avda Diputacion (de La), S/n",
    "sg:city":"Ubrique",
    "sg:orig_category":"Ba\u00d1os Y Duchas P\u00dablicos",
    "sg:phone":"+34 956 46 30 68",
    "sg:postcode":"11600",
    "sg:province":"C\u00e1diz",
    "wof:name":"Ayuntamiento De Ubrique",
    "wof:placetype":"venue"
},
  "geometry": {"coordinates":[-5.4491453171,36.6710243225],"type":"Point"}
}