{
  "type": "Feature",
  "properties": {
    "addr:full":"Pol Ind Can Boixadera, 35 Cardedeu Barcelona 08440",
    "addr:housenumber":"35",
    "addr:postcode":"08440",
    "addr:street":"Ind;Boixadera",
    "iso:country":"ES",
    "sg:address":"Pol Ind Can Boixadera, 35",
    "sg:city":"Cardedeu",
    "sg:orig_category":"Electricidad: Instaladores",
    "sg:phone":"+34 938 44 44 03",
    "sg:postcode":"08440",
    "sg:province":"Barcelona",
    "wof:name":"Diavoletric Valles S.l Diavolectric Valles S.l Dia",
    "wof:placetype":"venue"
},
  "geometry": {"coordinates":[2.3603100777,41.6399612427],"type":"Point"}
}