{
  "type": "Feature",
  "properties": {
    "addr:full":"Alam Cervantes (de), 14 San Mateo Murcia 30800",
    "addr:housenumber":"14",
    "addr:postcode":"30800",
    "addr:street":"Alam Cervantes De",
    "iso:country":"ES",
    "sg:address":"Alam Cervantes (de), 14",
    "sg:city":"San Mateo",
    "sg:orig_category":"Mensajer\u00cda Express, Portes Internacionales",
    "sg:phone":"+34 968 47 25 61",
    "sg:postcode":"30800",
    "sg:province":"Murcia",
    "sg:website":"www.halcourier.es",
    "wof:name":"Lopez Torres Maria Jesus",
    "wof:placetype":"venue"
},
  "geometry": {"coordinates":[-1.6905640364,37.680557251],"type":"Point"}
}