{
  "type": "Feature",
  "properties": {
    "iso:country":"ES",
    "sg:address":"Avda Constitucion, 11",
    "sg:city":"San Miguel",
    "sg:orig_category":"Abogados",
    "sg:phone":"+34 968 24 52 69",
    "sg:postcode":"30008",
    "sg:province":"Murcia",
    "wof:name":"Despacho Juridico Y Tecnico A.i.e.",
    "wof:placetype":"venue"
},
  "geometry": {"coordinates":[-1.1307469606,37.9913711548],"type":"Point"}
}