{
  "type": "Feature",
  "properties": {
    "iso:country":"ES",
    "sg:address":"Calle de Plaza De Toros Vieja, 18",
    "sg:city":"Malaga",
    "sg:orig_category":"Ingeniero",
    "sg:phone":"+34 952 32 11 30",
    "sg:postcode":"29002",
    "sg:province":"M\u00e1laga",
    "wof:name":"Ramirez Arroyo Juan Manuel",
    "wof:placetype":"venue"
},
  "geometry": {"coordinates":[-4.4285578728,36.7134437561],"type":"Point"}
}