{
  "type": "Feature",
  "properties": {
    "iso:country":"ES",
    "sg:address":"Calle de Ramon Y Cajal, 31",
    "sg:city":"Villanueva Serena",
    "sg:orig_category":"Psic\u00d3logos",
    "sg:phone":"+34 924 84 57 69",
    "sg:postcode":"06700",
    "sg:province":"Badajoz",
    "wof:name":"Calderon Carmona Maria Benita",
    "wof:placetype":"venue"
},
  "geometry": {"coordinates":[-5.7979359627,38.9742279053],"type":"Point"}
}