{
  "type": "Feature",
  "properties": {
    "addr:full":"Calle de Charcon, 26 Talavera Reina Toledo 45600",
    "addr:housenumber":"26",
    "addr:postcode":"45600",
    "addr:street":"Calle De Charcon",
    "iso:country":"ES",
    "sg:address":"Calle de Charcon, 26",
    "sg:city":"Talavera Reina",
    "sg:orig_category":"Centros De Coordinaci\u00d3n",
    "sg:phone":"+34 925 81 91 53",
    "sg:postcode":"45600",
    "sg:province":"Toledo",
    "wof:name":"Alpavet S.l.",
    "wof:placetype":"venue"
},
  "geometry": {"coordinates":[-4.8352007866,39.9584197998],"type":"Point"}
}