{
  "type": "Feature",
  "properties": {
    "iso:country":"ES",
    "sg:address":"Calle de Azulejo (del), 18",
    "sg:city":"Santorcaz",
    "sg:orig_category":"Cerrajer\u00cda, Ferrallista",
    "sg:phone":"+34 918 84 04 54",
    "sg:postcode":"28818",
    "sg:province":"Madrid",
    "wof:name":"Lopez Moreno Felix",
    "wof:placetype":"venue"
},
  "geometry": {"coordinates":[-3.2374031544,40.4712638855],"type":"Point"}
}