{
  "type": "Feature",
  "properties": {
    "iso:country":"ES",
    "sg:address":"Ledo\u00f1o, S/n",
    "sg:city":"Ledo\u00d1o",
    "sg:orig_category":"Empresas De Carpinter\u00cda De Madera",
    "sg:phone":"+34 981 66 84 08",
    "sg:postcode":"15199",
    "sg:province":"La Coru\u00f1a",
    "wof:name":"Balay Barreiro Manuel",
    "wof:placetype":"venue"
},
  "geometry": {"coordinates":[-8.4283447266,43.2940483093],"type":"Point"}
}