{
  "type": "Feature",
  "properties": {
    "iso:country":"ES",
    "sg:address":"Carr Cases Noves, 51",
    "sg:city":"Fortia",
    "sg:orig_category":"Montaje (empresas De)",
    "sg:phone":"+34 972 53 41 56",
    "sg:postcode":"17469",
    "sg:province":"Girona",
    "wof:name":"Hamy  Francesc Francis",
    "wof:placetype":"venue"
},
  "geometry": {"coordinates":[3.0422298908,42.2440910339],"type":"Point"}
}