{
  "type": "Feature",
  "properties": {
    "iso:country":"ES",
    "sg:address":"Calle de Canalejas, 30",
    "sg:city":"Jumilla",
    "sg:orig_category":"Ropa De Casa (fabricaci\u00d3n, Al Por Mayor)",
    "sg:phone":"+34 968 78 01 68",
    "sg:postcode":"30520",
    "sg:province":"Murcia",
    "wof:name":"Herrero Mateo Gaspar",
    "wof:placetype":"venue"
},
  "geometry": {"coordinates":[-1.32749331,38.4759216309],"type":"Point"}
}