{
  "type": "Feature",
  "properties": {
    "iso:country":"ES",
    "sg:address":"Avda Puente De Carlos Iii, 20",
    "sg:city":"Reinosa",
    "sg:orig_category":"Bazares, Art\u00cdculos De Limpieza Y De Cocina (al Por Menor)",
    "sg:phone":"+34 942 75 41 48",
    "sg:postcode":"39200",
    "sg:province":"Cantabria",
    "wof:name":"Calvo Gutierrez Ignacio Benito",
    "wof:placetype":"venue"
},
  "geometry": {"coordinates":[-4.1386370659,42.9988365173],"type":"Point"}
}