{
  "type": "Feature",
  "properties": {
    "iso:country":"ES",
    "sg:address":"Ctra Vilches, 2",
    "sg:city":"Ubeda",
    "sg:classifiers":[
        {
            "category":"Personal",
            "subcategory":"Barber",
            "type":"Services"
        }
    ],
    "sg:phone":"+34 953 75 50 01",
    "sg:postcode":"23400",
    "sg:province":"Ja\u00e9n",
    "sg:tags":[
        "caballeros",
        "de",
        "peluqueros"
    ],
    "wof:name":"Moreno Millan Juan Antonio",
    "wof:placetype":"venue"
},
  "geometry": {"coordinates":[-3.3709290028,38.0223999023],"type":"Point"}
}