{
  "type": "Feature",
  "properties": {
    "addr:full":"Poli Industrial La Pa\u00d1oleta, S/n Velez-malaga M\u00e1laga 29700",
    "addr:housenumber":"s",
    "addr:postcode":"29700",
    "addr:street":"/ N Velez-Malaga Ma\u0301Laga",
    "iso:country":"ES",
    "sg:address":"Poli Industrial La Pa\u00d1oleta, S/n",
    "sg:city":"Velez-malaga",
    "sg:orig_category":"Empresas De Carpinter\u00cda De Madera",
    "sg:phone":"+34 952 50 33 92",
    "sg:postcode":"29700",
    "sg:province":"M\u00e1laga",
    "wof:name":"Arroyo Fortes Jose",
    "wof:placetype":"venue"
},
  "geometry": {"coordinates":[-4.141140461,36.7639465332],"type":"Point"}
}