{
  "type": "Feature",
  "properties": {
    "addr:full":"Calle de San Mateo, 28 Madrid Madrid 28004",
    "addr:housenumber":"28",
    "addr:postcode":"madrid;28004",
    "addr:street":"Calle De San Mateo",
    "iso:country":"ES",
    "sg:address":"Calle de San Mateo, 28",
    "sg:city":"Madrid",
    "sg:orig_category":"Art\u00cdculos De Decoraci\u00d3n",
    "sg:phone":"+34 913 08 30 63",
    "sg:postcode":"28004",
    "sg:province":"Madrid",
    "wof:name":"Living Etc S.l.",
    "wof:placetype":"venue"
},
  "geometry": {"coordinates":[-3.6981709003,40.4260520935],"type":"Point"}
}