{
  "type": "Feature",
  "properties": {
    "addr:full":"Calle de Navarro Rodrigo, 10 Almeria Almer\u00eda 04001",
    "addr:housenumber":"10",
    "addr:postcode":"04001",
    "addr:street":"Calle De Navarro Rodrigo",
    "iso:country":"ES",
    "sg:address":"Calle de Navarro Rodrigo, 10",
    "sg:city":"Almeria",
    "sg:orig_category":"Art\u00cdculos De Regalo (al Por Menor)",
    "sg:phone":"+34 950 27 02 69",
    "sg:postcode":"04001",
    "sg:province":"Almer\u00eda",
    "wof:name":"Bernal Lupia\u00f1ez Jose Maria",
    "wof:placetype":"venue"
},
  "geometry": {"coordinates":[-2.4628190994,36.8394927979],"type":"Point"}
}