{
  "type": "Feature",
  "properties": {
    "addr:full":"Calle de Rubio, 28 Chiva Valencia 46370",
    "addr:housenumber":"28",
    "addr:postcode":"46370",
    "addr:street":"Calle De Rubio",
    "iso:country":"ES",
    "sg:address":"Calle de Rubio, 28",
    "sg:city":"Chiva",
    "sg:orig_category":"Asociaciones, Instituciones De Consumidores Y Usuarios",
    "sg:phone":"+34 962 52 18 47",
    "sg:postcode":"46370",
    "sg:province":"Valencia",
    "wof:name":"Asociacion Provincial De Amas De Casa Y Consumidores Tiryus",
    "wof:placetype":"venue"
},
  "geometry": {"coordinates":[-0.7162724137,39.4720497131],"type":"Point"}
}