{
  "type": "Feature",
  "properties": {
    "addr:full":"Rua Vazquez De Parga, 67 Carballo La Coru\u00f1a 15100",
    "addr:housenumber":"67",
    "addr:postcode":"15100",
    "addr:street":"Rua Vazquez De Parga;La Corun\u0303A",
    "iso:country":"ES",
    "sg:address":"Rua Vazquez De Parga, 67",
    "sg:city":"Carballo",
    "sg:orig_category":"Sociedades, Compa\u00d1\u00cdas Aseguradoras",
    "sg:phone":"+34 981 75 80 75",
    "sg:postcode":"15100",
    "sg:province":"La Coru\u00f1a",
    "sg:website":"www.mapfre.com",
    "wof:name":"Mapfre Servicios De Informatica S.a.",
    "wof:placetype":"venue"
},
  "geometry": {"coordinates":[-8.686293602,43.2203025818],"type":"Point"}
}