{
  "type": "Feature",
  "properties": {
    "iso:country":"ES",
    "sg:address":"Calle de Bilbao, 18",
    "sg:city":"Pinosol",
    "sg:orig_category":"Fabrica De Cer\u00c1micas",
    "sg:phone":"+34 918 90 13 06",
    "sg:postcode":"28280",
    "sg:province":"Madrid",
    "wof:name":"Alvarez Fernandez Maria Paz",
    "wof:placetype":"venue"
},
  "geometry": {"coordinates":[-4.1230063438,40.5566940308],"type":"Point"}
}