{
  "type": "Feature",
  "properties": {
    "iso:country":"ES",
    "sg:address":"Sagastitxipi Kalea, 2",
    "sg:city":"Urretxu",
    "sg:orig_category":"Fabricaci\u00d3n De Moldes Y Modelos",
    "sg:phone":"+34 943 72 18 06",
    "sg:postcode":"20700",
    "sg:province":"Guip\u00f9zcoa",
    "wof:name":"Modelos Ezguba S. A.",
    "wof:placetype":"venue"
},
  "geometry": {"coordinates":[-2.3184199333,43.0972061157],"type":"Point"}
}