{
  "type": "Feature",
  "properties": {
    "addr:full":"Calle de Ancha, 13 Aguilas Murcia 30880",
    "addr:housenumber":"13",
    "addr:postcode":"30880",
    "addr:street":"Calle De Ancha",
    "iso:country":"ES",
    "sg:address":"Calle de Ancha, 13",
    "sg:city":"Aguilas",
    "sg:orig_category":"Pensiones Familiares",
    "sg:phone":"+34 968 44 60 06",
    "sg:postcode":"30880",
    "sg:province":"Murcia",
    "wof:name":"Ramonetero S.l.",
    "wof:placetype":"venue"
},
  "geometry": {"coordinates":[-1.5811456442,37.4077529907],"type":"Point"}
}