{
  "type": "Feature",
  "properties": {
    "addr:full":"Cm\u00d1o Rial, 55 Casas Pontevedra 36213",
    "addr:housenumber":"55",
    "addr:postcode":"36213",
    "addr:street":"Rial",
    "iso:country":"ES",
    "sg:address":"Cm\u00d1o Rial, 55",
    "sg:city":"Casas",
    "sg:orig_category":"Empresas De Vigilancia, Guardia Y Protecci\u00d3n",
    "sg:phone":"+34 986 20 31 88",
    "sg:postcode":"36213",
    "sg:province":"Pontevedra",
    "wof:name":"Fernandez Hermida Maria Del Carmen",
    "wof:placetype":"venue"
},
  "geometry": {"coordinates":[-8.6624097824,42.5275917053],"type":"Point"}
}