{
  "type": "Feature",
  "properties": {
    "addr:full":"Carr Fila (la), 10 Albuixech Valencia 46550",
    "addr:housenumber":"10",
    "addr:postcode":"46550",
    "addr:street":"Carr Fila La",
    "iso:country":"ES",
    "sg:address":"Carr Fila (la), 10",
    "sg:city":"Albuixech",
    "sg:orig_category":"Ropa De Trabajo Y Profesionales (fabricaci\u00d3n, Al Por Mayor)",
    "sg:phone":"+34 961 86 15 06",
    "sg:postcode":"46550",
    "sg:province":"Valencia",
    "sg:website":"www.chintex.net",
    "wof:name":"Chintex S.l.",
    "wof:placetype":"venue"
},
  "geometry": {"coordinates":[-0.3256070018,39.5474662781],"type":"Point"}
}