{
  "type": "Feature",
  "properties": {
    "addr:full":"Carrer de Vinyals, 38 Barcelona Barcelona 08041",
    "addr:housenumber":"38",
    "addr:postcode":"08041",
    "addr:street":"Carrer De Vinyals",
    "iso:country":"ES",
    "sg:address":"Carrer de Vinyals, 38",
    "sg:city":"Barcelona",
    "sg:orig_category":"Farmacias",
    "sg:phone":"+34 934 56 46 75",
    "sg:postcode":"08041",
    "sg:province":"Barcelona",
    "wof:name":"Hernandez Auladell Laura",
    "wof:placetype":"venue"
},
  "geometry": {"coordinates":[2.1747999191,41.4205169678],"type":"Point"}
}