{
  "type": "Feature",
  "properties": {
    "iso:country":"ES",
    "sg:address":"Carrer de Muntaner, 176",
    "sg:city":"Barcelona",
    "sg:orig_category":"M\u00c9dicos: Ginecolog\u00cda Y Obstetricia",
    "sg:phone":"+34 934 30 33 18",
    "sg:postcode":"08036",
    "sg:province":"Barcelona",
    "wof:name":"Royo Tomas Jaime",
    "wof:placetype":"venue"
},
  "geometry": {"coordinates":[2.152451992,41.3920478821],"type":"Point"}
}