{
  "type": "Feature",
  "properties": {
    "addr:full":"Carr Port, 23 Escala Girona 17130",
    "addr:housenumber":"23",
    "addr:postcode":"17130",
    "addr:street":"Carr Port",
    "iso:country":"ES",
    "sg:address":"Carr Port, 23",
    "sg:city":"Escala",
    "sg:orig_category":"Cajas De Ahorro",
    "sg:phone":"+34 972 77 01 69",
    "sg:postcode":"17130",
    "sg:province":"Girona",
    "sg:website":"www.lacaixa.es",
    "wof:name":"Caixa D'estalvis I Pensions De Barcelona",
    "wof:placetype":"venue"
},
  "geometry": {"coordinates":[3.1321649551,42.1229934692],"type":"Point"}
}