{
  "type": "Feature",
  "properties": {
    "iso:country":"ES",
    "sg:address":"Parroco Pablo Diez, 98",
    "sg:city":"Trobajo Camino",
    "sg:orig_category":"Veh\u00cdculos De Ocasi\u00d3n",
    "sg:phone":"+34 987 80 63 01",
    "sg:postcode":"24010",
    "sg:province":"Le\u00f3n",
    "wof:name":"Avicar Automoviles C.b.",
    "wof:placetype":"venue"
},
  "geometry": {"coordinates":[-5.6114397049,42.5926399231],"type":"Point"}
}