{
  "type": "Feature",
  "properties": {
    "addr:full":"Calle de Violetas (las), 1 Ponferrada Le\u00f3n 24400",
    "addr:housenumber":"1",
    "addr:postcode":"24400",
    "addr:street":"Calle De Violetas Las",
    "iso:country":"ES",
    "sg:address":"Calle de Violetas (las), 1",
    "sg:city":"Ponferrada",
    "sg:orig_category":"Peluquer\u00cdas, Peluquer\u00cda Mixta",
    "sg:phone":"+34 987 41 35 98",
    "sg:postcode":"24400",
    "sg:province":"Le\u00f3n",
    "wof:name":"Rodriguez Bernain Maria De Los Reyes",
    "wof:placetype":"venue"
},
  "geometry": {"coordinates":[-6.5840911865,42.551235199],"type":"Point"}
}