{
  "type": "Feature",
  "properties": {
    "iso:country":"ES",
    "sg:address":"Carr Baldomer Sola, 80",
    "sg:city":"Badalona",
    "sg:orig_category":"Sociedades, Compa\u00d1\u00cdas Aseguradoras",
    "sg:phone":"+34 933 99 28 11",
    "sg:postcode":"08912",
    "sg:province":"Barcelona",
    "wof:name":"Cuxart Correduria De Seguros S. A.",
    "wof:placetype":"venue"
},
  "geometry": {"coordinates":[2.2380859852,41.4460983276],"type":"Point"}
}