{
  "type": "Feature",
  "properties": {
    "addr:full":"Calle de Paseo De Espa\u00d1a, 2 Rambla C\u00f3rdoba 14540",
    "addr:housenumber":"2",
    "addr:postcode":"14540",
    "addr:street":"Calle De Paseo De Espan\u0303A;Rambla Co\u0301Rdoba",
    "iso:country":"ES",
    "sg:address":"Calle de Paseo De Espa\u00d1a, 2",
    "sg:city":"Rambla",
    "sg:classifiers":[
        {
            "category":"Casinos & Gambling",
            "type":"Entertainment"
        }
    ],
    "sg:phone":"+34 957 68 40 67",
    "sg:postcode":"14540",
    "sg:province":"C\u00f3rdoba",
    "sg:tags":[
        "locale",
        "de",
        "juego"
    ],
    "wof:name":"Ateneo De La Rambla",
    "wof:placetype":"venue"
},
  "geometry": {"coordinates":[-4.8239188194,37.6517066956],"type":"Point"}
}