{
  "type": "Feature",
  "properties": {
    "addr:full":"Calle de Coches (los), 14 Segovia Segovia 40002",
    "addr:housenumber":"14",
    "addr:postcode":"40002",
    "addr:street":"Calle De Coches Los",
    "iso:country":"ES",
    "sg:address":"Calle de Coches (los), 14",
    "sg:city":"Segovia",
    "sg:orig_category":"Centros P\u00dablicos De Formaci\u00d3n Profesional Y T\u00c9cnica",
    "sg:phone":"+34 921 42 59 06",
    "sg:postcode":"40002",
    "sg:province":"Segovia",
    "wof:name":"Colegio De Agentes Comerciales",
    "wof:placetype":"venue"
},
  "geometry": {"coordinates":[-4.1181387901,40.9447669983],"type":"Point"}
}