{
  "type": "Feature",
  "properties": {
    "iso:country":"ES",
    "sg:address":"Av Sant Josep De Sa Talaia, 18",
    "sg:city":"Eivissa",
    "sg:orig_category":"Agencias De Viajes",
    "sg:phone":"+34 971 31 15 66",
    "sg:postcode":"07800",
    "sg:province":"Islas Baleares",
    "wof:name":"Tui Espa\u00f1a Turismo S.a.",
    "wof:placetype":"venue"
},
  "geometry": {"coordinates":[1.4146569967,38.9051551819],"type":"Point"}
}