{
  "type": "Feature",
  "properties": {
    "addr:full":"Calle de Ancha, 40 Ponferrada Le\u00f3n 24400",
    "addr:housenumber":"40",
    "addr:postcode":"24400",
    "addr:street":"Calle De Ancha",
    "iso:country":"ES",
    "sg:address":"Calle de Ancha, 40",
    "sg:city":"Ponferrada",
    "sg:orig_category":"Electricidad: Instaladores",
    "sg:phone":"+34 987 45 60 83",
    "sg:postcode":"24400",
    "sg:province":"Le\u00f3n",
    "wof:name":"Hermanos Alvarez Luna S.l.",
    "wof:placetype":"venue"
},
  "geometry": {"coordinates":[-6.587305069,42.5476989746],"type":"Point"}
}