{
  "type": "Feature",
  "properties": {
    "iso:country":"ES",
    "sg:address":"Pase Estacion, 15",
    "sg:city":"Salamanca",
    "sg:orig_category":"Ropa Y Art\u00cdculos Pre",
    "sg:phone":"+34 923 12 12 09",
    "sg:postcode":"37004",
    "sg:province":"Salamanca",
    "wof:name":"Bicicletas Gomez S.l.",
    "wof:placetype":"venue"
},
  "geometry": {"coordinates":[-5.6567349434,40.9692649841],"type":"Point"}
}