{
  "type": "Feature",
  "properties": {
    "addr:full":"Calle de Londres, 4 Valdemoro Madrid 28340",
    "addr:housenumber":"4",
    "addr:postcode":"28340",
    "addr:street":"Calle De Londres",
    "iso:country":"ES",
    "sg:address":"Calle de Londres, 4",
    "sg:city":"Valdemoro",
    "sg:orig_category":"Art\u00cdculos De Limpieza Y De Cocina (fabricaci\u00d3n, Al Por Mayor)",
    "sg:phone":"+34 918 95 52 44",
    "sg:postcode":"28340",
    "sg:province":"Madrid",
    "wof:name":"Accesorios Y Componentes Jorge Y Santiago S.l.",
    "wof:placetype":"venue"
},
  "geometry": {"coordinates":[-3.685551405,40.207321167],"type":"Point"}
}