{
  "type": "Feature",
  "properties": {
    "addr:full":"Calle de Martires, 209 Roda Albacete 02630",
    "addr:housenumber":"209",
    "addr:postcode":"02630",
    "addr:street":"Calle De Martires",
    "iso:country":"ES",
    "sg:address":"Calle de Martires, 209",
    "sg:city":"Roda",
    "sg:orig_category":"Agentes, Concesionarios Y Sucursales De Veh\u00cdculos",
    "sg:phone":"+34 967 44 54 68",
    "sg:postcode":"02630",
    "sg:province":"Albacete",
    "wof:name":"Nissan Motor Espa\u00d1a S.a.",
    "wof:placetype":"venue"
},
  "geometry": {"coordinates":[-2.1672620773,39.2101402283],"type":"Point"}
}