{
  "type": "Feature",
  "properties": {
    "addr:full":"Calle de Arizonicas (de Las), 36 Parque Coimbra Madrid 28935",
    "addr:housenumber":"36",
    "addr:postcode":"28935",
    "addr:street":"Calle De Arizonicas De Las",
    "iso:country":"ES",
    "sg:address":"Calle de Arizonicas (de Las), 36",
    "sg:city":"Parque Coimbra",
    "sg:orig_category":"Asesores De Gesti\u00d3n Del Patrimonio",
    "sg:phone":"+34 916 47 84 13",
    "sg:postcode":"28935",
    "sg:province":"Madrid",
    "wof:name":"Patrimonial Hermanos Jimenez S.l.",
    "wof:placetype":"venue"
},
  "geometry": {"coordinates":[-3.922804594,40.315776825],"type":"Point"}
}