{
  "type": "Feature",
  "properties": {
    "addr:full":"Falmuria, S/n Falmuria Asturias 33438",
    "addr:postcode":"33438",
    "addr:street":"Falmuria S / N Falmuria Asturias",
    "iso:country":"ES",
    "sg:address":"Falmuria, S/n",
    "sg:city":"Falmuria",
    "sg:orig_category":"Refiner\u00cdas De Petr\u00d3leo",
    "sg:phone":"+34 985 88 76 63",
    "sg:postcode":"33438",
    "sg:province":"Asturias",
    "sg:website":"www.q8.com",
    "wof:name":"Kuwait Petroleum Espa\u00f1a S.a.",
    "wof:placetype":"venue"
},
  "geometry": {"coordinates":[-5.8532137871,43.552028656],"type":"Point"}
}