{
  "type": "Feature",
  "properties": {
    "addr:full":"Calle de Veintiocho De Febrero, S/n Bujalance C\u00f3rdoba 14650",
    "addr:housenumber":"s / n",
    "addr:postcode":"14650",
    "addr:street":"Calle De Veintiocho De Febrero",
    "iso:country":"ES",
    "sg:address":"Calle de Veintiocho De Febrero, S/n",
    "sg:city":"Bujalance",
    "sg:orig_category":"Sanatorios M\u00c9dico",
    "sg:phone":"+34 957 17 17 65",
    "sg:postcode":"14650",
    "sg:province":"C\u00f3rdoba",
    "wof:name":"Servicio Andaluz De Salud",
    "wof:placetype":"venue"
},
  "geometry": {"coordinates":[-4.3839788437,37.8970603943],"type":"Point"}
}