{
  "type": "Feature",
  "properties": {
    "addr:full":"Avda Constitucion (la), 54 Algodonales C\u00e1diz 11680",
    "addr:housenumber":"54",
    "addr:postcode":"11680",
    "addr:street":"Avda Constitucion La",
    "iso:country":"ES",
    "sg:address":"Avda Constitucion (la), 54",
    "sg:city":"Algodonales",
    "sg:orig_category":"Quincaller\u00cda (al Por Menor)",
    "sg:phone":"+34 956 13 70 77",
    "sg:postcode":"11680",
    "sg:province":"C\u00e1diz",
    "wof:name":"Rodriguez Madro\u00f1al Jose Ramon",
    "wof:placetype":"venue"
},
  "geometry": {"coordinates":[-5.4073381424,36.8804588318],"type":"Point"}
}