{
  "type": "Feature",
  "properties": {
    "iso:country":"ES",
    "sg:address":"Calle de Diputado L.jimenez Morel, S/n",
    "sg:city":"Alacant",
    "sg:orig_category":"Alimentaci\u00d3n General (al Por Menor)",
    "sg:phone":"+34 965 24 90 60",
    "sg:postcode":"03014",
    "sg:province":"Alicante",
    "wof:name":"Gonzalez Martinez Andres",
    "wof:placetype":"venue"
},
  "geometry": {"coordinates":[-0.4804914892,38.3697052002],"type":"Point"}
}