{
  "type": "Feature",
  "properties": {
    "addr:full":"Calle de Poeta Llorente, 176 Pobla Vallbona Valencia 46185",
    "addr:housenumber":"176",
    "addr:postcode":"46185",
    "addr:street":"Calle De Poeta Llorente",
    "iso:country":"ES",
    "sg:address":"Calle de Poeta Llorente, 176",
    "sg:city":"Pobla Vallbona",
    "sg:orig_category":"Inmobiliaria (agencias)",
    "sg:phone":"+34 962 76 01 08",
    "sg:postcode":"46185",
    "sg:province":"Valencia",
    "wof:name":"Inmobiliaria Pobla De Vallbona S.l.",
    "wof:placetype":"venue"
},
  "geometry": {"coordinates":[-0.5438110232,39.5893859863],"type":"Point"}
}