{
  "type": "Feature",
  "properties": {
    "addr:full":"Calle de Julio Burell, 32 Linares Ja\u00e9n 23700",
    "addr:housenumber":"32",
    "addr:postcode":"23700",
    "addr:street":"Calle De Julio Burell;Jae\u0301N",
    "iso:country":"ES",
    "sg:address":"Calle de Julio Burell, 32",
    "sg:city":"Linares",
    "sg:orig_category":"Cerrajer\u00cda, Ferrallista",
    "sg:phone":"+34 953 65 36 31",
    "sg:postcode":"23700",
    "sg:province":"Ja\u00e9n",
    "wof:name":"Robles Rodriguez Francisco",
    "wof:placetype":"venue"
},
  "geometry": {"coordinates":[-3.6306738853,38.0960006714],"type":"Point"}
}