{
  "type": "Feature",
  "properties": {
    "iso:country":"ES",
    "sg:address":"Avda General Peron, 10",
    "sg:city":"Madrid",
    "sg:orig_category":"Centros Empresariales",
    "sg:phone":"+34 915 72 27 36",
    "sg:postcode":"28020",
    "sg:province":"Madrid",
    "wof:name":"Circulo Del Cafe S.l.",
    "wof:placetype":"venue"
},
  "geometry": {"coordinates":[-3.6978590488,40.452381134],"type":"Point"}
}