{
  "type": "Feature",
  "properties": {
    "addr:full":"Monjas Altas, 25 Torredonjimeno Ja\u00e9n 23650",
    "addr:postcode":"23650",
    "addr:street":"Jae\u0301N",
    "iso:country":"ES",
    "sg:address":"Monjas Altas, 25",
    "sg:city":"Torredonjimeno",
    "sg:orig_category":"Dise\u00d1o Industrial",
    "sg:phone":"+34 953 34 12 32",
    "sg:postcode":"23650",
    "sg:province":"Ja\u00e9n",
    "wof:name":"Canada Hidalgo Antonio Jose",
    "wof:placetype":"venue"
},
  "geometry": {"coordinates":[-3.956895113,37.765537262],"type":"Point"}
}