{
  "type": "Feature",
  "properties": {
    "addr:full":"Calle de Antonio Machado, 2 Torre Mar M\u00e1laga 29740",
    "addr:housenumber":"2",
    "addr:postcode":"29740",
    "addr:street":"Calle De Antonio Machado;Ma\u0301Laga",
    "iso:country":"ES",
    "sg:address":"Calle de Antonio Machado, 2",
    "sg:city":"Torre Mar",
    "sg:orig_category":"Animales (al Por Menor)",
    "sg:phone":"+34 952 54 11 72",
    "sg:postcode":"29740",
    "sg:province":"M\u00e1laga",
    "wof:name":"Marti Ariza Manuel",
    "wof:placetype":"venue"
},
  "geometry": {"coordinates":[-4.0980286598,36.7401542664],"type":"Point"}
}