{
  "type": "Feature",
  "properties": {
    "addr:full":"Carrer de Princep De Viana, 11 Sabadell Barcelona 08207",
    "addr:housenumber":"11",
    "addr:postcode":"08207",
    "addr:street":"Carrer De Princep De Viana",
    "iso:country":"ES",
    "sg:address":"Carrer de Princep De Viana, 11",
    "sg:city":"Sabadell",
    "sg:orig_category":"Discapacitados",
    "sg:phone":"+34 937 23 49 82",
    "sg:postcode":"08207",
    "sg:province":"Barcelona",
    "wof:name":"Fundacion Privada Clavell",
    "wof:placetype":"venue"
},
  "geometry": {"coordinates":[2.0937559605,41.5629768372],"type":"Point"}
}