{
  "type": "Feature",
  "properties": {
    "iso:country":"ES",
    "sg:address":"Calle de San Nicolas, 18",
    "sg:city":"San Nicolas",
    "sg:orig_category":"Inmobiliaria (agencias)",
    "sg:phone":"+34 968 21 22 51",
    "sg:postcode":"30005",
    "sg:province":"Murcia",
    "wof:name":"Casa Abierta Plaza Mayor",
    "wof:placetype":"venue"
},
  "geometry": {"coordinates":[-1.1353130341,37.9863471985],"type":"Point"}
}