{
  "type": "Feature",
  "properties": {
    "addr:full":"Calle de Regueiro, 6 Cedeira La Coru\u00f1a 15350",
    "addr:housenumber":"6",
    "addr:postcode":"15350",
    "addr:street":"Calle De Regueiro;La Corun\u0303A",
    "iso:country":"ES",
    "sg:address":"Calle de Regueiro, 6",
    "sg:city":"Cedeira",
    "sg:orig_category":"Contenedores (mercanc\u00cdas)",
    "sg:phone":"+34 981 48 09 78",
    "sg:postcode":"15350",
    "sg:province":"La Coru\u00f1a",
    "wof:name":"Pi\u00f1on Martinez Jose",
    "wof:placetype":"venue"
},
  "geometry": {"coordinates":[-8.04804039,43.6551513672],"type":"Point"}
}