{
  "type": "Feature",
  "properties": {
    "addr:full":"Azucarera, S/n Gallur Zaragoza 50650",
    "addr:housenumber":"s / n",
    "addr:postcode":"50650",
    "iso:country":"ES",
    "sg:address":"Azucarera, S/n",
    "sg:city":"Gallur",
    "sg:orig_category":"Piscinas (establecimientos)",
    "sg:phone":"+34 976 86 40 47",
    "sg:postcode":"50650",
    "sg:province":"Zaragoza",
    "wof:name":"Ayuntamiento De Gallur",
    "wof:placetype":"venue"
},
  "geometry": {"coordinates":[-1.3180042505,41.8624763489],"type":"Point"}
}