{
  "type": "Feature",
  "properties": {
    "addr:full":"Calle de Plana Sancho, 5 Mas Matas Teruel 44564",
    "addr:housenumber":"5",
    "addr:postcode":"44564",
    "addr:street":"Calle De Plana Sancho",
    "iso:country":"ES",
    "sg:address":"Calle de Plana Sancho, 5",
    "sg:city":"Mas Matas",
    "sg:orig_category":"Carnicer\u00cdas, Carnicer\u00cdas",
    "sg:phone":"+34 978 84 80 56",
    "sg:postcode":"44564",
    "sg:province":"Teruel",
    "wof:name":"Palma Perez Manuel",
    "wof:placetype":"venue"
},
  "geometry": {"coordinates":[-0.2433429956,40.8334655762],"type":"Point"}
}