{
  "type": "Feature",
  "properties": {
    "addr:full":"Bda. Costa, 28 Llagostera Girona 17240",
    "addr:housenumber":"28",
    "addr:postcode":"17240",
    "addr:street":"Costa",
    "iso:country":"ES",
    "sg:address":"Bda. Costa, 28",
    "sg:city":"Llagostera",
    "sg:orig_category":"Construcci\u00d3n, Mantenimiento De Piscinas",
    "sg:phone":"+34 972 83 10 87",
    "sg:postcode":"17240",
    "sg:province":"Girona",
    "wof:name":"Piscinas Aquamar S.l.",
    "wof:placetype":"venue"
},
  "geometry": {"coordinates":[2.8947880268,41.8288955688],"type":"Point"}
}