{
  "type": "Feature",
  "properties": {
    "addr:full":"Rua Formigueiros, 89 Sarria Lugo 27600",
    "addr:housenumber":"89",
    "addr:postcode":"27600",
    "addr:street":"Rua Formigueiros",
    "iso:country":"ES",
    "sg:address":"Rua Formigueiros, 89",
    "sg:city":"Sarria",
    "sg:orig_category":"Alimentaci\u00d3n General (al Por Mayor)",
    "sg:phone":"+34 982 53 36 11",
    "sg:postcode":"27600",
    "sg:province":"Lugo",
    "wof:name":"Comercial Agropecuaria De Sarria S.l.",
    "wof:placetype":"venue"
},
  "geometry": {"coordinates":[-7.4147591591,42.7820091248],"type":"Point"}
}