{
  "type": "Feature",
  "properties": {
    "iso:country":"ES",
    "sg:address":"Pol. Ind Seu, S/n",
    "sg:city":"Seu Urgell",
    "sg:orig_category":"Carnicer\u00cdas, Carnicer\u00cdas",
    "sg:phone":"+34 973 35 14 16",
    "sg:postcode":"25700",
    "sg:province":"Lleida",
    "wof:name":"Pe\u00f1alvert Gomez Jose",
    "wof:placetype":"venue"
},
  "geometry": {"coordinates":[1.4592299461,42.3578453064],"type":"Point"}
}