{
  "type": "Feature",
  "properties": {
    "iso:country":"ES",
    "sg:address":"Calle de Oslo, 2",
    "sg:city":"Torreciega",
    "sg:orig_category":"Comercio De Hierro",
    "sg:phone":"+34 968 32 17 80",
    "sg:postcode":"30202",
    "sg:province":"Murcia",
    "wof:name":"Hierros Y Perfiles Cartagena S.l.",
    "wof:placetype":"venue"
},
  "geometry": {"coordinates":[-0.9694399834,37.6158409119],"type":"Point"}
}