{
  "type": "Feature",
  "properties": {
    "addr:full":"Av. Souto Vizoso, 28 Naron La Coru\u00f1a 15570",
    "addr:housenumber":"28",
    "addr:postcode":"15570",
    "addr:street":"Av. Souto Vizoso;La Corun\u0303A",
    "iso:country":"ES",
    "sg:address":"Av. Souto Vizoso, 28",
    "sg:city":"Naron",
    "sg:orig_category":"Restaurantes",
    "sg:phone":"+34 981 38 36 95",
    "sg:postcode":"15570",
    "sg:province":"La Coru\u00f1a",
    "wof:name":"Lopez Fustes Jose Salvador",
    "wof:placetype":"venue"
},
  "geometry": {"coordinates":[-8.192234993,43.4990196228],"type":"Point"}
}