{
  "type": "Feature",
  "properties": {
    "iso:country":"ES",
    "sg:address":"Carrer de Narcis Monturiol, 40",
    "sg:city":"Granollers",
    "sg:orig_category":"Contenedores (mercanc\u00cdas)",
    "sg:phone":"+34 938 40 93 17",
    "sg:postcode":"08403",
    "sg:province":"Barcelona",
    "wof:name":"Guinea  Fatoumata Camara",
    "wof:placetype":"venue"
},
  "geometry": {"coordinates":[2.282959938,41.613948822],"type":"Point"}
}