{
  "type": "Feature",
  "properties": {
    "addr:full":"Calle de Simon Bolivar, S/n Gijon Asturias 33213",
    "addr:housenumber":"s / n",
    "addr:postcode":"33213",
    "addr:street":"Calle De Simon Bolivar",
    "iso:country":"ES",
    "sg:address":"Calle de Simon Bolivar, S/n",
    "sg:city":"Gijon",
    "sg:orig_category":"Ense\u00d1anza Secundaria: Colegios Y Escuelas Privadas",
    "sg:phone":"+34 985 32 22 20",
    "sg:postcode":"33213",
    "sg:province":"Asturias",
    "wof:name":"Principado De Asturias",
    "wof:placetype":"venue"
},
  "geometry": {"coordinates":[-5.7000341415,43.536239624],"type":"Point"}
}