{
  "type": "Feature",
  "properties": {
    "iso:country":"ES",
    "sg:address":"Estd Nacional 540, 60",
    "sg:city":"Bentraces",
    "sg:orig_category":"Reposter\u00cdas",
    "sg:phone":"+34 988 38 30 13",
    "sg:postcode":"32890",
    "sg:province":"Ourense",
    "wof:name":"Blanco Rivera Antonio",
    "wof:placetype":"venue"
},
  "geometry": {"coordinates":[-7.8872189522,42.3010559082],"type":"Point"}
}