{
  "type": "Feature",
  "properties": {
    "addr:full":"Cabanas, S/n Oza La Coru\u00f1a 15107",
    "addr:housenumber":"s / n",
    "addr:postcode":"15107",
    "addr:street":"Oza La Corun\u0303A",
    "iso:country":"ES",
    "sg:address":"Cabanas, S/n",
    "sg:city":"Oza",
    "sg:orig_category":"Transportes Frigor\u00cdficos",
    "sg:phone":"+34 981 75 49 43",
    "sg:postcode":"15107",
    "sg:province":"La Coru\u00f1a",
    "wof:name":"Fernandez Bardanca Jose Antonio",
    "wof:placetype":"venue"
},
  "geometry": {"coordinates":[-8.7382974625,43.2469902039],"type":"Point"}
}