{
  "type": "Feature",
  "properties": {
    "addr:full":"Pl. San Pedro, 16 Aracena Huelva 21200",
    "addr:housenumber":"16",
    "addr:postcode":"21200",
    "addr:street":"Pl. San Pedro",
    "iso:country":"ES",
    "sg:address":"Pl. San Pedro, 16",
    "sg:city":"Aracena",
    "sg:orig_category":"Restaurantes",
    "sg:phone":"+34 959 12 88 95",
    "sg:postcode":"21200",
    "sg:province":"Huelva",
    "wof:name":"Restaurante Los Angeles",
    "wof:placetype":"venue"
},
  "geometry": {"coordinates":[-6.5664272308,37.8918075562],"type":"Point"}
}