{
  "type": "Feature",
  "properties": {
    "addr:full":"Avda. Las Cortes, 3 Medina-sidonia C\u00e1diz 11170",
    "addr:housenumber":"3",
    "addr:postcode":"11170",
    "addr:street":"Avda. Las Cortes;Ca\u0301Diz",
    "iso:country":"ES",
    "sg:address":"Avda. Las Cortes, 3",
    "sg:city":"Medina-sidonia",
    "sg:orig_category":"Neum\u00c1ticos (fabricaci\u00d3n, Al Por Mayor)",
    "sg:phone":"+34 956 41 04 87",
    "sg:postcode":"11170",
    "sg:province":"C\u00e1diz",
    "wof:name":"Vulcanizados Las Cortes S.l.",
    "wof:placetype":"venue"
},
  "geometry": {"coordinates":[-5.9282259941,36.4642677307],"type":"Point"}
}