{
  "type": "Feature",
  "properties": {
    "addr:full":"Avda Odon, 19 Villaviciosa Odon Madrid 28670",
    "addr:housenumber":"19",
    "addr:postcode":"28670",
    "addr:street":"Avda Odon;Odon",
    "iso:country":"ES",
    "sg:address":"Avda Odon, 19",
    "sg:city":"Villaviciosa Odon",
    "sg:orig_category":"Venta, Instalaci\u00d3n, Reparaci\u00d3n De Antenas Para Televisi\u00d3n",
    "sg:phone":"+34 916 16 66 74",
    "sg:postcode":"28670",
    "sg:province":"Madrid",
    "wof:name":"E.g.morante Instalaciones S.l",
    "wof:placetype":"venue"
},
  "geometry": {"coordinates":[-3.9057769775,40.3559341431],"type":"Point"}
}