{
  "type": "Feature",
  "properties": {
    "addr:full":"Calle de Obispo Perez Caceres, 16 San Cristobal De La Laguna Santa Cruz De Tenerife 38205",
    "addr:housenumber":"16",
    "addr:postcode":"38205",
    "addr:street":"Calle De Obispo Perez Caceres",
    "iso:country":"ES",
    "sg:address":"Calle de Obispo Perez Caceres, 16",
    "sg:city":"San Cristobal De La Laguna",
    "sg:orig_category":"Servicios De Telecomunicaciones",
    "sg:phone":"+34 922 25 98 39",
    "sg:postcode":"38205",
    "sg:province":"Santa Cruz De Tenerife",
    "wof:name":"Telecomunicaciones Santa Cruz S.l.",
    "wof:placetype":"venue"
},
  "geometry": {"coordinates":[-16.3121833801,28.4811954498],"type":"Point"}
}