{
  "type": "Feature",
  "properties": {
    "iso:country":"ES",
    "sg:address":"Calle de Santa Teresa, 12",
    "sg:city":"Salamanca",
    "sg:orig_category":"Concepci\u00d3n Y Realizaci\u00d3n De Maquetas Profesionales Y Prototipos",
    "sg:phone":"+34 923 21 08 63",
    "sg:postcode":"37002",
    "sg:province":"Salamanca",
    "sg:website":"www.infonegocio.com/rchobby",
    "wof:name":"Valverde Blazquez Francisco",
    "wof:placetype":"venue"
},
  "geometry": {"coordinates":[-5.665594101,40.9676322937],"type":"Point"}
}