{
  "type": "Feature",
  "properties": {
    "addr:full":"Carrer de Joan Fernandez, 149 Cornella Llobregat Barcelona 08940",
    "addr:housenumber":"149",
    "addr:postcode":"08940",
    "addr:street":"Carrer De Joan Fernandez",
    "iso:country":"ES",
    "sg:address":"Carrer de Joan Fernandez, 149",
    "sg:city":"Cornella Llobregat",
    "sg:orig_category":"Reposter\u00cdas",
    "sg:phone":"+34 933 76 59 78",
    "sg:postcode":"08940",
    "sg:province":"Barcelona",
    "wof:name":"Blatpa S.a.",
    "wof:placetype":"venue"
},
  "geometry": {"coordinates":[2.0732700825,41.3643188477],"type":"Point"}
}