{
  "type": "Feature",
  "properties": {
    "iso:country":"ES",
    "sg:address":"Calle de Corpus Christi, 62",
    "sg:city":"S. Andres Rabanedo",
    "sg:orig_category":"Molduras, Junquillos, Listones Y Molduras Perforadas",
    "sg:phone":"+34 987 84 69 30",
    "sg:postcode":"24010",
    "sg:province":"Le\u00f3n",
    "wof:name":"Gonzalez Garcia Maria Teresa",
    "wof:placetype":"venue"
},
  "geometry": {"coordinates":[-5.6095538139,42.609954834],"type":"Point"}
}