{
  "type": "Feature",
  "properties": {
    "iso:country":"ES",
    "sg:address":"Calle de Solera, 3",
    "sg:city":"Conil De La Frontera",
    "sg:orig_category":"Bisuter\u00cda, Joyer\u00cda, Relojer\u00cda (al Por Menor)",
    "sg:phone":"+34 956 45 66 73",
    "sg:postcode":"11140",
    "sg:province":"C\u00e1diz",
    "wof:name":"Barroso Torti Victor",
    "wof:placetype":"venue"
},
  "geometry": {"coordinates":[-6.0892901421,36.2791824341],"type":"Point"}
}