{
  "type": "Feature",
  "properties": {
    "iso:country":"ES",
    "sg:address":"Calle de Santa Rosa, S/n",
    "sg:city":"Santiago El Mayor",
    "sg:orig_category":"Alimentaci\u00d3n General (al Por Menor)",
    "sg:phone":"+34 968 25 12 53",
    "sg:postcode":"30012",
    "sg:province":"Murcia",
    "wof:name":"Cuartero Gracia Jesus",
    "wof:placetype":"venue"
},
  "geometry": {"coordinates":[-1.1233340502,37.9715042114],"type":"Point"}
}