{
  "type": "Feature",
  "properties": {
    "iso:country":"ES",
    "sg:address":"Via Ausetania, 8",
    "sg:city":"Manlleu",
    "sg:orig_category":"Mec\u00c1nico Del Autom\u00d3vil",
    "sg:phone":"+34 938 51 14 52",
    "sg:postcode":"08560",
    "sg:province":"Barcelona",
    "wof:name":"Jorda Vilaregut Jaume",
    "wof:placetype":"venue"
},
  "geometry": {"coordinates":[2.2843899727,41.9956474304],"type":"Point"}
}