{
  "type": "Feature",
  "properties": {
    "addr:full":"Plaz Espa\u00d1a, 2 Onda Castell\u00f3n 12200",
    "addr:housenumber":"2",
    "addr:postcode":"12200",
    "addr:street":"Plaz Espan\u0303A;Castello\u0301N",
    "iso:country":"ES",
    "sg:address":"Plaz Espa\u00d1a, 2",
    "sg:city":"Onda",
    "sg:orig_category":"Ropa Para Se\u00d1oras (al Por Menor)",
    "sg:phone":"+34 964 60 12 49",
    "sg:postcode":"12200",
    "sg:province":"Castell\u00f3n",
    "wof:name":"Pe\u00f1a Lloscos Antonia Delfina",
    "wof:placetype":"venue"
},
  "geometry": {"coordinates":[-0.2620640099,39.9651794434],"type":"Point"}
}