{
  "type": "Feature",
  "properties": {
    "iso:country":"ES",
    "sg:address":"Carrer de Stravinsky, S/n",
    "sg:city":"Rubi",
    "sg:orig_category":"Afiladoras, Pulidoras Y Bru\u00d1idoras",
    "sg:phone":"+34 935 88 76 71",
    "sg:postcode":"08191",
    "sg:province":"Barcelona",
    "wof:name":"Ruiz Hinojo Francisco Manuel",
    "wof:placetype":"venue"
},
  "geometry": {"coordinates":[2.020179987,41.4699554443],"type":"Point"}
}