{
  "type": "Feature",
  "properties": {
    "iso:country":"ES",
    "sg:address":"Calle de Isabel Ii, 27",
    "sg:city":"Parla",
    "sg:orig_category":"Alimentaci\u00d3n General (al Por Menor)",
    "sg:phone":"+34 916 99 76 39",
    "sg:postcode":"28980",
    "sg:province":"Madrid",
    "wof:name":"Privado Elvira Hilario",
    "wof:placetype":"venue"
},
  "geometry": {"coordinates":[-3.7652831078,40.231880188],"type":"Point"}
}