{
  "type": "Feature",
  "properties": {
    "iso:country":"ES",
    "sg:address":"Calle de Castro, 22",
    "sg:city":"Santa Cruz De Tenerife",
    "sg:orig_category":"Venta, Alquiler De Instrumentos Y Accesorios De M\u00dasica",
    "sg:phone":"+34 922 27 16 24",
    "sg:postcode":"38004",
    "sg:province":"Santa Cruz De Tenerife",
    "wof:name":"Musicanarias S. L.",
    "wof:placetype":"venue"
},
  "geometry": {"coordinates":[-16.2603607178,28.4677791595],"type":"Point"}
}