{
  "type": "Feature",
  "properties": {
    "addr:full":"Calle de Primavera, 22 Granada Granada 18008",
    "addr:housenumber":"22",
    "addr:postcode":"18008",
    "addr:street":"Calle De Primavera",
    "iso:country":"ES",
    "sg:address":"Calle de Primavera, 22",
    "sg:city":"Granada",
    "sg:orig_category":"Mec\u00c1nico Del Autom\u00d3vil",
    "sg:phone":"+34 958 12 53 12",
    "sg:postcode":"18008",
    "sg:province":"Granada",
    "wof:name":"Yudes Lopez Francisco",
    "wof:placetype":"venue"
},
  "geometry": {"coordinates":[-3.5929131508,37.1620330811],"type":"Point"}
}