{
  "type": "Feature",
  "properties": {
    "addr:full":"Carrer de Pais Basc, 21 Cambrils Tarragona 43850",
    "addr:housenumber":"21",
    "addr:postcode":"43850",
    "addr:street":"Carrer De Pais Basc",
    "iso:country":"ES",
    "sg:address":"Carrer de Pais Basc, 21",
    "sg:city":"Cambrils",
    "sg:orig_category":"Agencias Y Agentes Comerciales, Representantes",
    "sg:phone":"+34 977 79 20 95",
    "sg:postcode":"43850",
    "sg:province":"Tarragona",
    "wof:name":"Pierdominici  Maria Laura",
    "wof:placetype":"venue"
},
  "geometry": {"coordinates":[1.057090044,41.0693092346],"type":"Point"}
}