{
  "type": "Feature",
  "properties": {
    "addr:full":"Calle de Mercado, 15 S. Vicente Barquera Cantabria 39540",
    "addr:housenumber":"15",
    "addr:postcode":"39540",
    "addr:street":"Calle De Mercado;S. Vicente",
    "iso:country":"ES",
    "sg:address":"Calle de Mercado, 15",
    "sg:city":"S. Vicente Barquera",
    "sg:orig_category":"Carnicer\u00cdas, Carnicer\u00cdas",
    "sg:phone":"+34 942 71 00 63",
    "sg:postcode":"39540",
    "sg:province":"Cantabria",
    "wof:name":"Garcia Bastian Jose",
    "wof:placetype":"venue"
},
  "geometry": {"coordinates":[-4.399102211,43.3827323914],"type":"Point"}
}