{
  "type": "Feature",
  "properties": {
    "iso:country":"ES",
    "sg:address":"Calle de Rueda Lopez, 21",
    "sg:city":"Almeria",
    "sg:orig_category":"Ropa De Casa (fabricaci\u00d3n, Al Por Mayor)",
    "sg:phone":"+34 950 24 63 60",
    "sg:postcode":"04004",
    "sg:province":"Almer\u00eda",
    "wof:name":"Ripoll Lopez Isabel",
    "wof:placetype":"venue"
},
  "geometry": {"coordinates":[-2.461591959,36.8377723694],"type":"Point"}
}