{
  "type": "Feature",
  "properties": {
    "addr:full":"Calle de Italia, 53 Zaragoza Zaragoza 50010",
    "addr:housenumber":"53",
    "addr:postcode":"50010",
    "addr:street":"Calle De Italia",
    "iso:country":"ES",
    "sg:address":"Calle de Italia, 53",
    "sg:city":"Zaragoza",
    "sg:orig_category":"Agentes, Concesionarios Y Sucursales De Veh\u00cdculos",
    "sg:phone":"+34 976 30 08 25",
    "sg:postcode":"50010",
    "sg:province":"Zaragoza",
    "wof:name":"Voltamper S. A.",
    "wof:placetype":"venue"
},
  "geometry": {"coordinates":[-0.8998532891,41.6504745483],"type":"Point"}
}