{
  "type": "Feature",
  "properties": {
    "addr:full":"Calle de Cabrera, 6 Cordoba C\u00f3rdoba 14001",
    "addr:housenumber":"6",
    "addr:postcode":"14001",
    "addr:street":"Calle De Cabrera;Co\u0301Rdoba",
    "iso:country":"ES",
    "sg:address":"Calle de Cabrera, 6",
    "sg:city":"Cordoba",
    "sg:orig_category":"Ropa Para Ni\u00d1os (al Por Menor)",
    "sg:phone":"+34 957 47 32 02",
    "sg:postcode":"14001",
    "sg:province":"C\u00f3rdoba",
    "wof:name":"Classic Baby C.b.",
    "wof:placetype":"venue"
},
  "geometry": {"coordinates":[-4.7803997993,37.8870506287],"type":"Point"}
}