{
  "type": "Feature",
  "properties": {
    "iso:country":"ES",
    "sg:address":"Ctra. Salamanca, 24",
    "sg:city":"Cabrerizos",
    "sg:orig_category":"Empresas De Pintura Y Revestimientos",
    "sg:phone":"+34 923 28 81 62",
    "sg:postcode":"37193",
    "sg:province":"Salamanca",
    "wof:name":"Inter-pinturas Decoracion S.l.",
    "wof:placetype":"venue"
},
  "geometry": {"coordinates":[-5.6102590561,40.979434967],"type":"Point"}
}