{
  "type": "Feature",
  "properties": {
    "iso:country":"ES",
    "sg:address":"Calle de Benito Gutierrez, 31",
    "sg:city":"Madrid",
    "sg:orig_category":"Ropa Para Ni\u00d1os (al Por Menor)",
    "sg:phone":"+34 915 49 64 66",
    "sg:postcode":"28008",
    "sg:province":"Madrid",
    "wof:name":"Salazar Gomez Francisco",
    "wof:placetype":"venue"
},
  "geometry": {"coordinates":[-3.7203462124,40.4311180115],"type":"Point"}
}