{
  "type": "Feature",
  "properties": {
    "addr:full":"Calle de Grande, 43 Quintanar Orden Toledo 45800",
    "addr:housenumber":"43",
    "addr:postcode":"45800",
    "addr:street":"Calle De Grande",
    "iso:country":"ES",
    "sg:address":"Calle de Grande, 43",
    "sg:city":"Quintanar Orden",
    "sg:orig_category":"\u00d3ptica: Instrumentos (fabricaci\u00d3n)",
    "sg:phone":"+34 925 18 17 09",
    "sg:postcode":"45800",
    "sg:province":"Toledo",
    "wof:name":"Optica Quintanar C.b.",
    "wof:placetype":"venue"
},
  "geometry": {"coordinates":[-3.0421230793,39.5937805176],"type":"Point"}
}