{
  "type": "Feature",
  "properties": {
    "iso:country":"ES",
    "sg:address":"Carr Doctor Fleming, 4",
    "sg:city":"Aldaia",
    "sg:orig_category":"Panader\u00cdas, Panader\u00cdas",
    "sg:phone":"+34 961 50 93 13",
    "sg:postcode":"46960",
    "sg:province":"Valencia",
    "wof:name":"Garcia Rodriguez Jose Antonio",
    "wof:placetype":"venue"
},
  "geometry": {"coordinates":[-0.4697540104,39.4626350403],"type":"Point"}
}