{
  "type": "Feature",
  "properties": {
    "iso:country":"ES",
    "sg:address":"Calle de Leon Y Castillo, 26",
    "sg:city":"Palmas De Gran Canaria",
    "sg:orig_category":"Asesor\u00cda De Formaci\u00d3n Y Gesti\u00d3n De Personal",
    "sg:phone":"+34 928 36 09 53",
    "sg:postcode":"35003",
    "sg:province":"Las Palmas",
    "wof:name":"Quevedo Santana Rafael",
    "wof:placetype":"venue"
},
  "geometry": {"coordinates":[-15.4188508987,28.1109237671],"type":"Point"}
}