{
  "type": "Feature",
  "properties": {
    "addr:full":"Calle de Caceres, 4 Alcorcon Madrid 28921",
    "addr:housenumber":"4",
    "addr:postcode":"28921",
    "addr:street":"Calle De Caceres",
    "iso:country":"ES",
    "sg:address":"Calle de Caceres, 4",
    "sg:city":"Alcorcon",
    "sg:orig_category":"Ropa Para Se\u00d1oras (al Por Menor)",
    "sg:phone":"+34 916 12 29 29",
    "sg:postcode":"28921",
    "sg:province":"Madrid",
    "wof:name":"Jupi S.l.",
    "wof:placetype":"venue"
},
  "geometry": {"coordinates":[-3.8315939903,40.3486824036],"type":"Point"}
}