{
  "type": "Feature",
  "properties": {
    "iso:country":"ES",
    "sg:address":"Carrer de Balmes, 246",
    "sg:city":"Barcelona",
    "sg:orig_category":"Ingenier\u00cda, Centros De Estudios (diversos)",
    "sg:phone":"+34 932 17 08 09",
    "sg:postcode":"08006",
    "sg:province":"Barcelona",
    "wof:name":"Guzman Molina Antonio",
    "wof:placetype":"venue"
},
  "geometry": {"coordinates":[2.1500930786,41.3996772766],"type":"Point"}
}