{
  "type": "Feature",
  "properties": {
    "iso:country":"ES",
    "sg:address":"Carrer de Mallorca, 80",
    "sg:city":"Barcelona",
    "sg:orig_category":"Promotores Constructores",
    "sg:phone":"+34 934 39 88 06",
    "sg:postcode":"08029",
    "sg:province":"Barcelona",
    "wof:name":"Ancomi 2003 S.l.",
    "wof:placetype":"venue"
},
  "geometry": {"coordinates":[2.1506035328,41.3848457336],"type":"Point"}
}