{
  "type": "Feature",
  "properties": {
    "addr:full":"Calle de Juan Tomas De Gandarias, 14 Sestao Vizcaya 48910",
    "addr:housenumber":"14",
    "addr:postcode":"48910",
    "addr:street":"Calle De Juan Tomas De Gandarias",
    "iso:country":"ES",
    "sg:address":"Calle de Juan Tomas De Gandarias, 14",
    "sg:city":"Sestao",
    "sg:orig_category":"Carnicer\u00cdas, Carnicer\u00cdas",
    "sg:phone":"+34 944 72 35 53",
    "sg:postcode":"48910",
    "sg:province":"Vizcaya",
    "wof:name":"Carnicas Fercar S.l.",
    "wof:placetype":"venue"
},
  "geometry": {"coordinates":[-3.0074601173,43.3064193726],"type":"Point"}
}