{
  "type": "Feature",
  "properties": {
    "iso:country":"ES",
    "sg:address":"Monte De Las Mercedes, 24",
    "sg:city":"Las Mercedes",
    "sg:orig_category":"Asesor\u00cda Fiscal Y Jur\u00cddica",
    "sg:phone":"+34 922 26 82 52",
    "sg:postcode":"38293",
    "sg:province":"Santa Cruz De Tenerife",
    "wof:name":"Carlos Rivero S.l.",
    "wof:placetype":"venue"
},
  "geometry": {"coordinates":[-16.3070068359,28.5102176666],"type":"Point"}
}