{
  "type": "Feature",
  "properties": {
    "addr:full":"Calle de Sanchez Pastor, 10 Malaga M\u00e1laga 29015",
    "addr:housenumber":"10",
    "addr:postcode":"29015",
    "addr:street":"Calle De Sanchez Pastor;Ma\u0301Laga",
    "iso:country":"ES",
    "sg:address":"Calle de Sanchez Pastor, 10",
    "sg:city":"Malaga",
    "sg:orig_category":"Formaci\u00d3n Continuada (variada)",
    "sg:phone":"+34 952 21 49 90",
    "sg:postcode":"29015",
    "sg:province":"M\u00e1laga",
    "wof:name":"Benitez Del Moral Juan Miguel",
    "wof:placetype":"venue"
},
  "geometry": {"coordinates":[-4.4206662178,36.721534729],"type":"Point"}
}