{
  "type": "Feature",
  "properties": {
    "iso:country":"ES",
    "sg:address":"Av Prat De La Riba, 43",
    "sg:city":"Reus",
    "sg:classifiers":[
        {
            "category":"Autos & Motor Vehicles",
            "subcategory":"Automobile Sales",
            "type":"Retail Goods"
        }
    ],
    "sg:phone":"+34 977 31 37 35",
    "sg:postcode":"43201",
    "sg:province":"Tarragona",
    "wof:name":"Agustench Isern Luis",
    "wof:placetype":"venue"
},
  "geometry": {"coordinates":[1.1023088694,41.1573371887],"type":"Point"}
}