{
  "type": "Feature",
  "properties": {
    "iso:country":"ES",
    "sg:address":"Plaz Amarica, 4",
    "sg:city":"Vitoria-gasteiz",
    "sg:orig_category":"Abogados",
    "sg:phone":"+34 945 23 21 24",
    "sg:postcode":"01005",
    "sg:province":"\u00c1lava",
    "wof:name":"Lopez Montoya Pedro Jose",
    "wof:placetype":"venue"
},
  "geometry": {"coordinates":[-2.6722991467,42.8436660767],"type":"Point"}
}