{
  "type": "Feature",
  "properties": {
    "addr:full":"Carrer de Lepant, 20 Reus Tarragona 43202",
    "addr:housenumber":"20",
    "addr:postcode":"43202",
    "addr:street":"Carrer De Lepant",
    "iso:country":"ES",
    "sg:address":"Carrer de Lepant, 20",
    "sg:city":"Reus",
    "sg:orig_category":"Sociedades, Compa\u00d1\u00cdas Aseguradoras",
    "sg:phone":"+34 977 31 70 88",
    "sg:postcode":"43202",
    "sg:province":"Tarragona",
    "wof:name":"Mapfre Servicios De Informatica",
    "wof:placetype":"venue"
},
  "geometry": {"coordinates":[1.0976649523,41.1555633545],"type":"Point"}
}