{
  "type": "Feature",
  "properties": {
    "addr:full":"Calle de Toreno, 32 Fuenlabrada Madrid 28947",
    "addr:housenumber":"32",
    "addr:postcode":"28947",
    "addr:street":"Calle De Toreno",
    "iso:country":"ES",
    "sg:address":"Calle de Toreno, 32",
    "sg:city":"Fuenlabrada",
    "sg:orig_category":"Fabricaci\u00d3n De Sobres, Bolsas Y Fundas",
    "sg:phone":"+34 916 42 23 17",
    "sg:postcode":"28947",
    "sg:province":"Madrid",
    "wof:name":"Yong Chang S.l.",
    "wof:placetype":"venue"
},
  "geometry": {"coordinates":[-3.7493097782,40.2665405273],"type":"Point"}
}