{
  "type": "Feature",
  "properties": {
    "addr:full":"Afores(sant Marti Empuries), S/n Escala Girona 17130",
    "addr:housenumber":"/ n",
    "addr:postcode":"17130",
    "addr:street":"Empuries S",
    "iso:country":"ES",
    "sg:address":"Afores(sant Marti Empuries), S/n",
    "sg:city":"Escala",
    "sg:orig_category":"Museos",
    "sg:phone":"+34 972 77 02 13",
    "sg:postcode":"17130",
    "sg:province":"Girona",
    "wof:name":"Centre De Telecomunicaciones De Catalunya",
    "wof:placetype":"venue"
},
  "geometry": {"coordinates":[3.1321649551,42.1229934692],"type":"Point"}
}