{
  "type": "Feature",
  "properties": {
    "iso:country":"ES",
    "sg:address":"Trav De Gracia, 264",
    "sg:city":"Barcelona",
    "sg:orig_category":"Institutos De Belleza",
    "sg:phone":"+34 932 07 42 45",
    "sg:postcode":"08025",
    "sg:province":"Barcelona",
    "wof:name":"Fuxet Turiella Ester",
    "wof:placetype":"venue"
},
  "geometry": {"coordinates":[2.1652560234,41.4059524536],"type":"Point"}
}