{
  "type": "Feature",
  "properties": {
    "iso:country":"ES",
    "sg:address":"Rua Dr. Mara\u00d1on, 12",
    "sg:city":"Vigo",
    "sg:orig_category":"Edici\u00d3n De Diarios, Revistas, Boletines",
    "sg:phone":"+34 986 21 48 88",
    "sg:postcode":"36211",
    "sg:province":"Pontevedra",
    "sg:website":"www.xerais.es",
    "wof:name":"Edicions Xerais De Galicia S.a.",
    "wof:placetype":"venue"
},
  "geometry": {"coordinates":[-8.7317180634,42.2270355225],"type":"Point"}
}