{
  "type": "Feature",
  "properties": {
    "addr:full":"Gta Marques De Vadillo, 8 Madrid Madrid 28019",
    "addr:housenumber":"8",
    "addr:postcode":"madrid;28019",
    "addr:street":"Gta Marques De Vadillo",
    "iso:country":"ES",
    "sg:address":"Gta Marques De Vadillo, 8",
    "sg:city":"Madrid",
    "sg:orig_category":"Centros Empresariales",
    "sg:phone":"+34 915 60 99 99",
    "sg:postcode":"28019",
    "sg:province":"Madrid",
    "wof:name":"Equipos Medina S.l",
    "wof:placetype":"venue"
},
  "geometry": {"coordinates":[-3.7161579132,40.3977508545],"type":"Point"}
}