{
  "type": "Feature",
  "properties": {
    "iso:country":"ES",
    "sg:address":"Calle de Jose Marron, 38",
    "sg:city":"Benameji",
    "sg:orig_category":"Ropa Para Ni\u00d1os (al Por Menor)",
    "sg:phone":"+34 957 53 02 05",
    "sg:postcode":"14910",
    "sg:province":"C\u00f3rdoba",
    "wof:name":"Leiva Ortigosa Maria Jose",
    "wof:placetype":"venue"
},
  "geometry": {"coordinates":[-4.5410141945,37.2686538696],"type":"Point"}
}