{
  "type": "Feature",
  "properties": {
    "addr:full":"Ctra. Cadiz-algeciras, Km. 0000,5 Chiclana C\u00e1diz 11130",
    "addr:postcode":"11130",
    "addr:street":"Ctra. Cadiz-Algeciras Km. 0000,5",
    "iso:country":"ES",
    "sg:address":"Ctra. Cadiz-algeciras, Km. 0000,5",
    "sg:city":"Chiclana",
    "sg:orig_category":"Distribuci\u00d3n De Petr\u00d3leo Y Derivados",
    "sg:phone":"+34 956 40 04 08",
    "sg:postcode":"11130",
    "sg:province":"C\u00e1diz",
    "sg:website":"www.cepsa.es",
    "wof:name":"Cedipsa Compa\u00d1ia Espa\u00d1ola Distribuidora De Petroleos S.a.",
    "wof:placetype":"venue"
},
  "geometry": {"coordinates":[-6.1447038651,36.4212188721],"type":"Point"}
}