{
  "type": "Feature",
  "properties": {
    "addr:full":"Carrer de Granja, 3 Vilassar Dalt Barcelona 08339",
    "addr:housenumber":"3",
    "addr:postcode":"08339",
    "addr:street":"Carrer De Granja",
    "iso:country":"ES",
    "sg:address":"Carrer de Granja, 3",
    "sg:city":"Vilassar Dalt",
    "sg:orig_category":"M\u00c9dicos: Neurolog\u00cda",
    "sg:phone":"+34 937 50 86 51",
    "sg:postcode":"08339",
    "sg:province":"Barcelona",
    "wof:name":"Herrero Cerezo Fernando",
    "wof:placetype":"venue"
},
  "geometry": {"coordinates":[2.3609070778,41.50623703],"type":"Point"}
}