{
  "type": "Feature",
  "properties": {
    "addr:full":"Calle de Nicanor Villalta, 16 Zaragoza Zaragoza 50017",
    "addr:housenumber":"16",
    "addr:postcode":"50017",
    "addr:street":"Calle De Nicanor Villalta",
    "iso:country":"ES",
    "sg:address":"Calle de Nicanor Villalta, 16",
    "sg:city":"Zaragoza",
    "sg:orig_category":"Farmacias",
    "sg:phone":"+34 976 32 09 04",
    "sg:postcode":"50017",
    "sg:province":"Zaragoza",
    "wof:name":"Gaudo Barba Elena",
    "wof:placetype":"venue"
},
  "geometry": {"coordinates":[-0.9125490189,41.6536712646],"type":"Point"}
}