{
  "type": "Feature",
  "properties": {
    "addr:full":"Calle de Navarro Villoslada, 10 Vitoria-gasteiz \u00c1lava 01012",
    "addr:housenumber":"10",
    "addr:postcode":"01012",
    "addr:street":"Calle De Navarro Villoslada",
    "iso:country":"ES",
    "sg:address":"Calle de Navarro Villoslada, 10",
    "sg:city":"Vitoria-gasteiz",
    "sg:orig_category":"Molduras, Junquillos, Listones Y Molduras Perforadas",
    "sg:phone":"+34 945 24 58 72",
    "sg:postcode":"01012",
    "sg:province":"\u00c1lava",
    "wof:name":"Lacalle Novoa Leonardo",
    "wof:placetype":"venue"
},
  "geometry": {"coordinates":[-2.6788051128,42.8536987305],"type":"Point"}
}