{
  "type": "Feature",
  "properties": {
    "iso:country":"ES",
    "sg:address":"Calle de Campo Verde, 2",
    "sg:city":"Granada",
    "sg:orig_category":"Ropa Para Ni\u00d1os (al Por Menor)",
    "sg:phone":"+34 958 52 35 45",
    "sg:postcode":"18001",
    "sg:province":"Granada",
    "wof:name":"Santander Rodriguez Baldomero",
    "wof:placetype":"venue"
},
  "geometry": {"coordinates":[-3.6003470421,37.1739425659],"type":"Point"}
}