{
  "type": "Feature",
  "properties": {
    "iso:country":"ES",
    "sg:address":"Ptge Panadella, 58",
    "sg:city":"Terrassa",
    "sg:orig_category":"Fabricaci\u00d3n De Peines Y De Accesorios De Peluquer\u00cda",
    "sg:phone":"+34 937 83 72 71",
    "sg:postcode":"08227",
    "sg:province":"Barcelona",
    "wof:name":"Distribuciones Comesticas Del Valle S.l.",
    "wof:placetype":"venue"
},
  "geometry": {"coordinates":[2.0379030704,41.5717353821],"type":"Point"}
}