{
  "type": "Feature",
  "properties": {
    "iso:country":"ES",
    "sg:address":"Calle de Marcelino Sanz De Sautuola, 11",
    "sg:city":"Santander",
    "sg:orig_category":"Equitaci\u00d3n: Guarnicioner\u00cda, Equipo (al Por Menor)",
    "sg:phone":"+34 942 31 23 63",
    "sg:postcode":"39003",
    "sg:province":"Cantabria",
    "wof:name":"Noriega Preciados Carmen",
    "wof:placetype":"venue"
},
  "geometry": {"coordinates":[-3.8038599491,43.4633293152],"type":"Point"}
}