{
  "type": "Feature",
  "properties": {
    "iso:country":"ES",
    "sg:address":"Avgd Del Cami Nou, 264",
    "sg:city":"Xirivella",
    "sg:orig_category":"Mec\u00c1nico Del Autom\u00d3vil",
    "sg:phone":"+34 963 13 45 96",
    "sg:postcode":"46950",
    "sg:province":"Valencia",
    "wof:name":"J. R. A. Sociedad Limitada",
    "wof:placetype":"venue"
},
  "geometry": {"coordinates":[-0.4431500137,39.4611320496],"type":"Point"}
}