{
  "type": "Feature",
  "properties": {
    "iso:country":"ES",
    "sg:address":"Avda Playas (las), 84",
    "sg:city":"Puerto Del Carmen",
    "sg:orig_category":"Pistas Y Clases De Tenis",
    "sg:phone":"+34 928 51 33 27",
    "sg:postcode":"35510",
    "sg:province":"Las Palmas",
    "wof:name":"Cesar Monzon Dario",
    "wof:placetype":"venue"
},
  "geometry": {"coordinates":[-13.6662149429,28.9237804413],"type":"Point"}
}