{
  "type": "Feature",
  "properties": {
    "addr:full":"Avda Valencia, 158 Ademuz Valencia 46140",
    "addr:housenumber":"158",
    "addr:postcode":"46140",
    "addr:street":"Avda Valencia",
    "iso:country":"ES",
    "sg:address":"Avda Valencia, 158",
    "sg:city":"Ademuz",
    "sg:orig_category":"Hornos Industriales",
    "sg:phone":"+34 978 78 21 16",
    "sg:postcode":"46140",
    "sg:province":"Valencia",
    "wof:name":"Esojama S. L.",
    "wof:placetype":"venue"
},
  "geometry": {"coordinates":[-1.2864409685,40.0590705872],"type":"Point"}
}