{
  "type": "Feature",
  "properties": {
    "iso:country":"ES",
    "sg:address":"Calle de Barco, 38",
    "sg:city":"Madrid",
    "sg:orig_category":"Promotores Constructores",
    "sg:phone":"+34 915 31 04 47",
    "sg:postcode":"28004",
    "sg:province":"Madrid",
    "wof:name":"Instalaciones Madrid S. A.",
    "wof:placetype":"venue"
},
  "geometry": {"coordinates":[-3.7022116184,40.4235115051],"type":"Point"}
}