{
  "type": "Feature",
  "properties": {
    "addr:full":"Avda Marques De Corbera, 61 Madrid Madrid 28017",
    "addr:housenumber":"61",
    "addr:postcode":"madrid;28017",
    "addr:street":"Avda Marques De Corbera",
    "iso:country":"ES",
    "sg:address":"Avda Marques De Corbera, 61",
    "sg:city":"Madrid",
    "sg:orig_category":"Alquiler De V\u00cddeo",
    "sg:phone":"+34 913 26 18 77",
    "sg:postcode":"28017",
    "sg:province":"Madrid",
    "wof:name":"Cinelandia Video Club S.l.",
    "wof:placetype":"venue"
},
  "geometry": {"coordinates":[-3.6504340172,40.4269256592],"type":"Point"}
}