{
  "type": "Feature",
  "properties": {
    "iso:country":"ES",
    "sg:address":"Avgd Alcalde Recasens, 31",
    "sg:city":"Lleida",
    "sg:orig_category":"Bisuter\u00cda, Joyer\u00cda, Relojer\u00cda (al Por Menor)",
    "sg:phone":"+34 973 22 12 89",
    "sg:postcode":"25005",
    "sg:province":"Lleida",
    "wof:name":"La Perla D'or S.c.p.",
    "wof:placetype":"venue"
},
  "geometry": {"coordinates":[0.629685998,41.6259460449],"type":"Point"}
}