{
  "type": "Feature",
  "properties": {
    "addr:full":"Avda Fuenlabrada, 82 Leganes Madrid 28911",
    "addr:housenumber":"82",
    "addr:postcode":"28911",
    "addr:street":"Avda Fuenlabrada",
    "iso:country":"ES",
    "sg:address":"Avda Fuenlabrada, 82",
    "sg:city":"Leganes",
    "sg:orig_category":"Empresas De Limpieza",
    "sg:phone":"+34 916 93 71 39",
    "sg:postcode":"28911",
    "sg:province":"Madrid",
    "wof:name":"Dianma S.l.",
    "wof:placetype":"venue"
},
  "geometry": {"coordinates":[-3.7653980255,40.3255615234],"type":"Point"}
}