{
  "type": "Feature",
  "properties": {
    "iso:country":"ES",
    "sg:address":"Calle de Mayor, 11",
    "sg:city":"Canteras",
    "sg:orig_category":"Molduras, Junquillos, Listones Y Molduras Perforadas",
    "sg:phone":"+34 968 55 31 21",
    "sg:postcode":"30394",
    "sg:province":"Murcia",
    "wof:name":"Garcia Martinez Jose",
    "wof:placetype":"venue"
},
  "geometry": {"coordinates":[-1.0415090322,37.6120185852],"type":"Point"}
}