{
  "type": "Feature",
  "properties": {
    "iso:country":"ES",
    "sg:address":"Avda Andalucia, 26",
    "sg:city":"Arjonilla",
    "sg:orig_category":"Reposter\u00cdas",
    "sg:phone":"+34 953 52 04 72",
    "sg:postcode":"23750",
    "sg:province":"Ja\u00e9n",
    "wof:name":"Pansevilla S.l.",
    "wof:placetype":"venue"
},
  "geometry": {"coordinates":[-4.1061720848,37.9735946655],"type":"Point"}
}