{
  "type": "Feature",
  "properties": {
    "addr:full":"Avda Victoria, S/n Madrid Madrid 28023",
    "addr:housenumber":"/ n",
    "addr:postcode":"28023",
    "addr:street":"Avda Victoria S",
    "iso:country":"ES",
    "sg:address":"Avda Victoria, S/n",
    "sg:city":"Madrid",
    "sg:orig_category":"Carnicer\u00cdas, Carnicer\u00cdas",
    "sg:phone":"+34 913 72 89 91",
    "sg:postcode":"28023",
    "sg:province":"Madrid",
    "wof:name":"Bife Argentino S.l.",
    "wof:placetype":"venue"
},
  "geometry": {"coordinates":[-3.8350439072,40.474395752],"type":"Point"}
}