{
  "type": "Feature",
  "properties": {
    "addr:full":"Carrer de Blas Infante (de), 22 Montornes Centre Barcelona 08170",
    "addr:housenumber":"22",
    "addr:postcode":"08170",
    "addr:street":"Carrer De Blas Infante De;Centre Barcelona",
    "iso:country":"ES",
    "sg:address":"Carrer de Blas Infante (de), 22",
    "sg:city":"Montornes Centre",
    "sg:orig_category":"Molduras, Junquillos, Listones Y Molduras Perforadas",
    "sg:phone":"+34 935 72 23 89",
    "sg:postcode":"08170",
    "sg:province":"Barcelona",
    "wof:name":"Cabello Gonzalez Rafaela",
    "wof:placetype":"venue"
},
  "geometry": {"coordinates":[2.2636899948,41.5415153503],"type":"Point"}
}