{
  "type": "Feature",
  "properties": {
    "addr:full":"Avda Sierra, 3 Villaviciosa Odon Madrid 28670",
    "addr:housenumber":"3",
    "addr:postcode":"28670",
    "addr:street":"Avda Sierra;Odon",
    "iso:country":"ES",
    "sg:address":"Avda Sierra, 3",
    "sg:city":"Villaviciosa Odon",
    "sg:orig_category":"Doctores En Medicina",
    "sg:phone":"+34 916 16 09 52",
    "sg:postcode":"28670",
    "sg:province":"Madrid",
    "wof:name":"Rodriguez Alvarez Javier",
    "wof:placetype":"venue"
},
  "geometry": {"coordinates":[-3.8754239082,40.3543891907],"type":"Point"}
}