{
  "type": "Feature",
  "properties": {
    "addr:full":"Calle de Alcala, 14 Madrid Madrid 28014",
    "addr:housenumber":"14",
    "addr:postcode":"madrid;28014",
    "addr:street":"Calle De Alcala",
    "iso:country":"ES",
    "sg:address":"Calle de Alcala, 14",
    "sg:city":"Madrid",
    "sg:orig_category":"Bancos",
    "sg:phone":"+34 915 21 21 92",
    "sg:postcode":"28014",
    "sg:province":"Madrid",
    "wof:name":"Banco Espa\u00f1ol De Credito S.a.",
    "wof:placetype":"venue"
},
  "geometry": {"coordinates":[-3.7002141476,40.4176063538],"type":"Point"}
}