{
  "type": "Feature",
  "properties": {
    "iso:country":"ES",
    "sg:address":"Av Barcelona (de), 19",
    "sg:city":"Arbo\u00e7",
    "sg:orig_category":"Mantenimiento Industrial",
    "sg:phone":"+34 977 16 71 57",
    "sg:postcode":"43720",
    "sg:province":"Tarragona",
    "wof:name":"Instalacion Elecra L'arbo\u00e7 S.l.",
    "wof:placetype":"venue"
},
  "geometry": {"coordinates":[1.6028549671,41.2648735046],"type":"Point"}
}