{
  "type": "Feature",
  "properties": {
    "addr:full":"Alta, S/n Navas Bureba Burgos 09249",
    "addr:housenumber":"s / n",
    "addr:postcode":"09249",
    "addr:street":"Alta",
    "iso:country":"ES",
    "sg:address":"Alta, S/n",
    "sg:city":"Navas Bureba",
    "sg:orig_category":"Cr\u00cda De Animales",
    "sg:phone":"+34 947 59 81 22",
    "sg:postcode":"09249",
    "sg:province":"Burgos",
    "wof:name":"Lopez Castillo Carlos",
    "wof:placetype":"venue"
},
  "geometry": {"coordinates":[-3.3451418877,42.6353988647],"type":"Point"}
}