{
  "type": "Feature",
  "properties": {
    "iso:country":"ES",
    "sg:address":"Pase Bego\u00d1a De, 24",
    "sg:city":"Gijon",
    "sg:orig_category":"Pr\u00c9stamos Personales E Hipotecarios",
    "sg:phone":"+34 985 35 21 42",
    "sg:postcode":"33205",
    "sg:province":"Asturias",
    "wof:name":"Garcia-pumarino Ramos Emilio",
    "wof:placetype":"venue"
},
  "geometry": {"coordinates":[-5.6569690704,43.535610199],"type":"Point"}
}