{
  "type": "Feature",
  "properties": {
    "iso:country":"ES",
    "sg:address":"Calle de Iturriaga, 100",
    "sg:city":"Bilbao",
    "sg:orig_category":"T\u00c9cnicos Veterinarios",
    "sg:phone":"+34 944 11 30 83",
    "sg:postcode":"48004",
    "sg:province":"Vizcaya",
    "wof:name":"Joel Casta\u00f1on Guerrero (clinica Veterinaria El Carmelo)",
    "wof:placetype":"venue"
},
  "geometry": {"coordinates":[-2.9109730721,43.2541656494],"type":"Point"}
}