{
  "type": "Feature",
  "properties": {
    "iso:country":"ES",
    "sg:address":"Huerta De San Juan De Dios, S/n",
    "sg:city":"Los Villares",
    "sg:orig_category":"Venta, Instalaci\u00d3n De Calefacci\u00d3n",
    "sg:phone":"+34 953 32 10 50",
    "sg:postcode":"23160",
    "sg:province":"Ja\u00e9n",
    "wof:name":"Gallardo E Higueras S.l.",
    "wof:placetype":"venue"
},
  "geometry": {"coordinates":[-3.8196389675,37.6900253296],"type":"Point"}
}