{
  "type": "Feature",
  "properties": {
    "iso:country":"ES",
    "sg:address":"Calle de Escobalon (el), S/n",
    "sg:city":"Tremor Arriba",
    "sg:orig_category":"Explotaci\u00d3n De Minas",
    "sg:phone":"+34 987 53 01 48",
    "sg:postcode":"24377",
    "sg:province":"Le\u00f3n",
    "wof:name":"Alto Bierzo S. A.",
    "wof:placetype":"venue"
},
  "geometry": {"coordinates":[-6.2080435753,42.7256469727],"type":"Point"}
}