{
  "type": "Feature",
  "properties": {
    "iso:country":"ES",
    "sg:address":"La Estacion, S/n",
    "sg:city":"Valderrey",
    "sg:orig_category":"Producci\u00d3n, Venta De Productos De Agricultura Biol\u00d3gica",
    "sg:phone":"+34 987 63 20 79",
    "sg:postcode":"24793",
    "sg:province":"Le\u00f3n",
    "wof:name":"Centro Agm De Manipulacion De Productos Hortofruticolas S.l.",
    "wof:placetype":"venue"
},
  "geometry": {"coordinates":[-5.9705328941,42.4120635986],"type":"Point"}
}