{
  "type": "Feature",
  "properties": {
    "iso:country":"ES",
    "sg:address":"Calle de Isturiz, 8",
    "sg:city":"Madrid",
    "sg:orig_category":"Restaurantes",
    "sg:phone":"+34 915 54 13 99",
    "sg:postcode":"28020",
    "sg:province":"Madrid",
    "wof:name":"Gordo Mostaza Miguel Angel",
    "wof:placetype":"venue"
},
  "geometry": {"coordinates":[-3.7021279335,40.4478492737],"type":"Point"}
}