{
  "type": "Feature",
  "properties": {
    "iso:country":"ES",
    "sg:address":"Calle de Prior, 12",
    "sg:city":"Yebenes",
    "sg:orig_category":"Negocio De Materiales De Construcci\u00d3n",
    "sg:phone":"+34 925 32 03 65",
    "sg:postcode":"45470",
    "sg:province":"Toledo",
    "wof:name":"Fontecha Gomez Jose Luis",
    "wof:placetype":"venue"
},
  "geometry": {"coordinates":[-3.8704059124,39.5795898438],"type":"Point"}
}