{
  "type": "Feature",
  "properties": {
    "iso:country":"ES",
    "sg:address":"Avda Principe De Asturias, 49",
    "sg:city":"Zamora",
    "sg:orig_category":"Comunidades Religiosas",
    "sg:phone":"+34 980 67 18 86",
    "sg:postcode":"49029",
    "sg:province":"Zamora",
    "wof:name":"Obispado De Zamora",
    "wof:placetype":"venue"
},
  "geometry": {"coordinates":[-5.735918045,41.5126113892],"type":"Point"}
}