{
  "type": "Feature",
  "properties": {
    "iso:country":"ES",
    "sg:address":"Calle de Febo, 9",
    "sg:city":"Sevilla",
    "sg:orig_category":"Electromedicina: Equipo",
    "sg:phone":"+34 954 34 32 32",
    "sg:postcode":"41010",
    "sg:province":"Sevilla",
    "wof:name":"Toshiba Medical Systems S.a.",
    "wof:placetype":"venue"
},
  "geometry": {"coordinates":[-6.0036616325,37.3808097839],"type":"Point"}
}