{
  "type": "Feature",
  "properties": {
    "iso:country":"ES",
    "sg:address":"Calle de Mayor, 17",
    "sg:city":"Guardia",
    "sg:orig_category":"Cajas De Ahorro",
    "sg:phone":"+34 925 13 80 55",
    "sg:postcode":"45760",
    "sg:province":"Toledo",
    "sg:website":"www.cajacastilla.es",
    "wof:name":"Caja De Ahorros De Castilla La Mancha",
    "wof:placetype":"venue"
},
  "geometry": {"coordinates":[-3.4749879837,39.787940979],"type":"Point"}
}