{
  "type": "Feature",
  "properties": {
    "addr:full":"Calle de Urbano Pineda, 4 Coin M\u00e1laga 29100",
    "addr:housenumber":"4",
    "addr:postcode":"29100",
    "addr:street":"Calle De Urbano Pineda;Ma\u0301Laga",
    "iso:country":"ES",
    "sg:address":"Calle de Urbano Pineda, 4",
    "sg:city":"Coin",
    "sg:orig_category":"Laboratorios Y Trabajos De Fotograf\u00cda, V\u00cddeo Y Cine",
    "sg:phone":"+34 952 45 11 50",
    "sg:postcode":"29100",
    "sg:province":"M\u00e1laga",
    "wof:name":"B N Visison Fotografos S.l.",
    "wof:placetype":"venue"
},
  "geometry": {"coordinates":[-4.7551078796,36.6610603333],"type":"Point"}
}