{
  "type": "Feature",
  "properties": {
    "addr:full":"Calle de Almendro, 87 Zafra Badajoz 06300",
    "addr:housenumber":"87",
    "addr:postcode":"06300",
    "addr:street":"Calle De Almendro",
    "iso:country":"ES",
    "sg:address":"Calle de Almendro, 87",
    "sg:city":"Zafra",
    "sg:orig_category":"Aparatos De Iluminaci\u00d3n (al Por Menor)",
    "sg:phone":"+34 924 55 59 19",
    "sg:postcode":"06300",
    "sg:province":"Badajoz",
    "wof:name":"Miguel Angel El Fusible S L",
    "wof:placetype":"venue"
},
  "geometry": {"coordinates":[-6.4232950211,38.4223861694],"type":"Point"}
}