{
  "type": "Feature",
  "properties": {
    "addr:full":"Avda Real Fabrica De Sedas, 28 Talavera Reina Toledo 45600",
    "addr:housenumber":"28",
    "addr:postcode":"45600",
    "addr:street":"Avda Real",
    "iso:country":"ES",
    "sg:address":"Avda Real Fabrica De Sedas, 28",
    "sg:city":"Talavera Reina",
    "sg:orig_category":"Abogados",
    "sg:phone":"+34 925 81 94 95",
    "sg:postcode":"45600",
    "sg:province":"Toledo",
    "wof:name":"Rossi Lopez Carlos",
    "wof:placetype":"venue"
},
  "geometry": {"coordinates":[-4.8355379105,39.9557952881],"type":"Point"}
}