{
  "type": "Feature",
  "properties": {
    "addr:full":"Pol Ind Fridex, S/n Alcala Guadaira Sevilla 41500",
    "addr:housenumber":"s",
    "addr:postcode":"41500",
    "addr:street":"/ N",
    "iso:country":"ES",
    "sg:address":"Pol Ind Fridex, S/n",
    "sg:city":"Alcala Guadaira",
    "sg:orig_category":"Mec\u00c1nico Del Autom\u00d3vil",
    "sg:phone":"+34 955 63 02 60",
    "sg:postcode":"41500",
    "sg:province":"Sevilla",
    "wof:name":"Talleres Mecanicos Malagon S. L.",
    "wof:placetype":"venue"
},
  "geometry": {"coordinates":[-5.8398590088,37.3383140564],"type":"Point"}
}