{
  "type": "Feature",
  "properties": {
    "iso:country":"ES",
    "sg:address":"Cami Estacio, S/n",
    "sg:city":"Espluga Francoli",
    "sg:orig_category":"Empresas De Carpinter\u00cda De Madera",
    "sg:phone":"+34 977 87 03 20",
    "sg:postcode":"43440",
    "sg:province":"Tarragona",
    "wof:name":"Fusteria Aluminis I Fustes Germans Vendrell S.l.",
    "wof:placetype":"venue"
},
  "geometry": {"coordinates":[1.0992749929,41.3950653076],"type":"Point"}
}