{
  "type": "Feature",
  "properties": {
    "iso:country":"ES",
    "sg:address":"Calle de Cid Campeador, 9",
    "sg:city":"Linares",
    "sg:orig_category":"Aparatos, Sistemas De Tele",
    "sg:phone":"+34 953 60 11 38",
    "sg:postcode":"23700",
    "sg:province":"Ja\u00e9n",
    "wof:name":"Acacio Martinez-paseo C.b.",
    "wof:placetype":"venue"
},
  "geometry": {"coordinates":[-3.639824,38.091625],"type":"Point"}
}