{
  "type": "Feature",
  "properties": {
    "addr:full":"Avgd Marti Pujol, 280 Badalona Barcelona 08911",
    "addr:housenumber":"280",
    "addr:postcode":"08911",
    "addr:street":"Pujol",
    "iso:country":"ES",
    "sg:address":"Avgd Marti Pujol, 280",
    "sg:city":"Badalona",
    "sg:orig_category":"Armaduras De Hormig\u00d3n",
    "sg:phone":"+34 933 84 46 27",
    "sg:postcode":"08911",
    "sg:province":"Barcelona",
    "wof:name":"Menfis 2000 S.l.",
    "wof:placetype":"venue"
},
  "geometry": {"coordinates":[2.2434220314,41.4529457092],"type":"Point"}
}