{
  "type": "Feature",
  "properties": {
    "iso:country":"ES",
    "sg:address":"Calle de Juan Xxiii, 1",
    "sg:city":"Abaran",
    "sg:orig_category":"Centros De Educaci\u00d3n Especial",
    "sg:phone":"+34 968 77 03 79",
    "sg:postcode":"30550",
    "sg:province":"Murcia",
    "wof:name":"Colegio Publico Juan Xxiii",
    "wof:placetype":"venue"
},
  "geometry": {"coordinates":[-1.4009289742,38.2000007629],"type":"Point"}
}