{
  "type": "Feature",
  "properties": {
    "iso:country":"ES",
    "sg:address":"Calle de Ca\u00d1ete, 5",
    "sg:city":"Cuenca",
    "sg:orig_category":"Molduras, Junquillos, Listones Y Molduras Perforadas",
    "sg:phone":"+34 969 22 68 55",
    "sg:postcode":"16004",
    "sg:province":"Cuenca",
    "wof:name":"Martinez Solares Marcos Alfredo",
    "wof:placetype":"venue"
},
  "geometry": {"coordinates":[-2.1347658634,40.0701675415],"type":"Point"}
}