{
  "type": "Feature",
  "properties": {
    "iso:country":"ES",
    "sg:address":"San Francisco, 2",
    "sg:city":"Guazamara",
    "sg:orig_category":"Empresas De Carpinter\u00cda De Madera",
    "sg:phone":"+34 950 39 60 18",
    "sg:postcode":"04647",
    "sg:province":"Almer\u00eda",
    "wof:name":"Carpinteria Guazamara S.l.",
    "wof:placetype":"venue"
},
  "geometry": {"coordinates":[-1.7637389898,37.3934822083],"type":"Point"}
}