{
  "type": "Feature",
  "properties": {
    "iso:country":"ES",
    "sg:address":"Calle de Hilarion Eslava, 9",
    "sg:city":"Burlada",
    "sg:orig_category":"Fabricaci\u00d3n De Muebles",
    "sg:phone":"+34 948 12 21 58",
    "sg:postcode":"31600",
    "sg:province":"Navarra",
    "wof:name":"Rojo Calvo Jesus Angel",
    "wof:placetype":"venue"
},
  "geometry": {"coordinates":[-1.6151340008,42.8253479004],"type":"Point"}
}