{
  "type": "Feature",
  "properties": {
    "addr:full":"Avda Rey Santo, 25 Ciudad Real Ciudad Real 13001",
    "addr:housenumber":"25",
    "addr:postcode":"13001",
    "addr:street":"Avda Rey Santo",
    "iso:country":"ES",
    "sg:address":"Avda Rey Santo, 25",
    "sg:city":"Ciudad Real",
    "sg:orig_category":"M\u00c9dicos: Salud P\u00dablica",
    "sg:phone":"+34 926 25 28 13",
    "sg:postcode":"13001",
    "sg:province":"Ciudad Real",
    "sg:website":"www.ibermutuamur.es",
    "wof:name":"Ibermutuamur",
    "wof:placetype":"venue"
},
  "geometry": {"coordinates":[-3.9305579662,38.9821205139],"type":"Point"}
}