{
  "type": "Feature",
  "properties": {
    "iso:country":"ES",
    "sg:address":"Carrer de Setze De Juliol, 6",
    "sg:city":"Poligon Industrial De Son Castello",
    "sg:orig_category":"Muebles, Minoristas",
    "sg:phone":"+34 971 43 00 40",
    "sg:postcode":"07009",
    "sg:province":"Islas Baleares",
    "sg:website":"www.puyalto.com",
    "wof:name":"Puyalto Muebles De Oficina S.l.",
    "wof:placetype":"venue"
},
  "geometry": {"coordinates":[2.6741399765,39.6011390686],"type":"Point"}
}