{
  "type": "Feature",
  "properties": {
    "iso:country":"ES",
    "sg:address":"Calle de Cuatro Torres, 2",
    "sg:city":"Jaen",
    "sg:orig_category":"Farmacias",
    "sg:phone":"+34 953 23 99 18",
    "sg:postcode":"23001",
    "sg:province":"Ja\u00e9n",
    "wof:name":"Farmacioa Perez Fernandez Y Otros C.b.",
    "wof:placetype":"venue"
},
  "geometry": {"coordinates":[-3.7868332863,37.7673606873],"type":"Point"}
}