{
  "type": "Feature",
  "properties": {
    "iso:country":"ES",
    "sg:address":"Rua Ourense (de), 7",
    "sg:city":"Santiago De Compostela",
    "sg:orig_category":"Arquitectos",
    "sg:phone":"+34 981 56 34 11",
    "sg:postcode":"15701",
    "sg:province":"La Coru\u00f1a",
    "wof:name":"C.p. Arquitectura Y Urbanismo S.l.",
    "wof:placetype":"venue"
},
  "geometry": {"coordinates":[-8.5453214645,42.8729476929],"type":"Point"}
}