{
  "type": "Feature",
  "properties": {
    "iso:country":"ES",
    "sg:address":"Calle de Trinquete, 1",
    "sg:city":"Santas Martas",
    "sg:orig_category":"Cooperativas Agr\u00cdcolas",
    "sg:phone":"+34 987 31 40 63",
    "sg:postcode":"24330",
    "sg:province":"Le\u00f3n",
    "wof:name":"Cooperativa San Antonio De Padua",
    "wof:placetype":"venue"
},
  "geometry": {"coordinates":[-5.369658947,42.4311103821],"type":"Point"}
}