{
  "type": "Feature",
  "properties": {
    "iso:country":"ES",
    "sg:address":"Prado Llano, S/n",
    "sg:city":"Sierra Nevada",
    "sg:orig_category":"Agencias De Viajes",
    "sg:phone":"+34 958 24 91 22",
    "sg:postcode":"18196",
    "sg:province":"Granada",
    "sg:website":"www.sierranevadaski.com",
    "wof:name":"Cetursa Sierra Nevada S.a.",
    "wof:placetype":"venue"
},
  "geometry": {"coordinates":[-3.0351140499,37.0072669983],"type":"Point"}
}