{
  "type": "Feature",
  "properties": {
    "iso:country":"ES",
    "sg:address":"Calle de Veracruz, S/n",
    "sg:city":"Estepona",
    "sg:orig_category":"Inform\u00c1tica (estudios, Servicios, Asesor\u00cda, Formaci\u00d3n)",
    "sg:phone":"+34 952 79 22 84",
    "sg:postcode":"29680",
    "sg:province":"M\u00e1laga",
    "wof:name":"Benitez Caba Salvador",
    "wof:placetype":"venue"
},
  "geometry": {"coordinates":[-5.1462450027,36.4269447327],"type":"Point"}
}