{
  "type": "Feature",
  "properties": {
    "iso:country":"ES",
    "sg:address":"Calle de Victoria La, 19",
    "sg:city":"Pravia",
    "sg:orig_category":"Electricidad (montaje, Ensamblaje De Componentes)",
    "sg:phone":"+34 985 82 02 96",
    "sg:postcode":"33120",
    "sg:province":"Asturias",
    "wof:name":"Constantino Garcia Fernandez",
    "wof:placetype":"venue"
},
  "geometry": {"coordinates":[-6.1105890274,43.4896812439],"type":"Point"}
}