{
  "type": "Feature",
  "properties": {
    "addr:full":"Carrer de Canigo, S/n Manlleu Barcelona 08560",
    "addr:housenumber":"s / n",
    "addr:postcode":"08560",
    "addr:street":"Carrer De Canigo",
    "iso:country":"ES",
    "sg:address":"Carrer de Canigo, S/n",
    "sg:city":"Manlleu",
    "sg:orig_category":"Cables Y Hilos El\u00c9ctricos (fabricaci\u00d3n, Al Por Mayor)",
    "sg:phone":"+34 938 51 04 12",
    "sg:postcode":"08560",
    "sg:province":"Barcelona",
    "wof:name":"Ctc Ingenieria Dedicad S.a.",
    "wof:placetype":"venue"
},
  "geometry": {"coordinates":[2.2929201126,42.0095252991],"type":"Point"}
}