{
  "type": "Feature",
  "properties": {
    "addr:full":"Calle de Real, 15 S. Fernando C\u00e1diz 11100",
    "addr:housenumber":"15",
    "addr:postcode":"11100",
    "addr:street":"Calle De Real;S. Fernando Ca\u0301Diz",
    "iso:country":"ES",
    "sg:address":"Calle de Real, 15",
    "sg:city":"S. Fernando",
    "sg:orig_category":"Motocicletas (agentes, Concesionarios)",
    "sg:phone":"+34 956 89 15 75",
    "sg:postcode":"11100",
    "sg:province":"C\u00e1diz",
    "wof:name":"El Motorista S. L.",
    "wof:placetype":"venue"
},
  "geometry": {"coordinates":[-6.1967391968,36.4654541016],"type":"Point"}
}