{
  "type": "Feature",
  "properties": {
    "addr:full":"Carrer de Torres I Amat, S/n Barcelona Barcelona 08...",
    "addr:housenumber":"s / n",
    "addr:street":"Carrer De Torres I Amat",
    "iso:country":"ES",
    "sg:address":"Carrer de Torres I Amat, S/n",
    "sg:city":"Barcelona",
    "sg:orig_category":"Montaje (empresas De)",
    "sg:phone":"+34 934 81 78 00",
    "sg:postcode":"08...",
    "sg:province":"Barcelona",
    "sg:website":"www.emmsa.com",
    "wof:name":"Espa\u00d1ola De Montajes Metalicos S.a.",
    "wof:placetype":"venue"
},
  "geometry": {"coordinates":[2.1649239063,41.3843994141],"type":"Point"}
}