{
  "type": "Feature",
  "properties": {
    "iso:country":"ES",
    "sg:address":"Carrer de Loreto, 22",
    "sg:city":"Barcelona",
    "sg:orig_category":"Vinos (agentes)",
    "sg:phone":"+34 933 22 19 49",
    "sg:postcode":"08029",
    "sg:province":"Barcelona",
    "wof:name":"Bouquet D' Aromes",
    "wof:placetype":"venue"
},
  "geometry": {"coordinates":[2.1422460079,41.3897895813],"type":"Point"}
}