{
  "type": "Feature",
  "properties": {
    "iso:country":"ES",
    "sg:address":"Calle de Mariano Hebrero, 1",
    "sg:city":"Ajalvir",
    "sg:orig_category":"Contenedores (mercanc\u00cdas)",
    "sg:phone":"+34 918 84 44 76",
    "sg:postcode":"28864",
    "sg:province":"Madrid",
    "wof:name":"Vallejo Rivera Jesus",
    "wof:placetype":"venue"
},
  "geometry": {"coordinates":[-3.4807240963,40.5331611633],"type":"Point"}
}