{
  "type": "Feature",
  "properties": {
    "iso:country":"ES",
    "sg:address":"Av Girona, 29",
    "sg:city":"Olot",
    "sg:orig_category":"Comercio, Reparaci\u00d3n De Bicicletas, De Motocicletas, De Accesorios",
    "sg:phone":"+34 972 26 99 78",
    "sg:postcode":"17800",
    "sg:province":"Girona",
    "wof:name":"Tarres Colom Lluis",
    "wof:placetype":"venue"
},
  "geometry": {"coordinates":[2.4944090843,42.1853713989],"type":"Point"}
}