{
  "type": "Feature",
  "properties": {
    "addr:full":"Calle de Mayor (garrapinillos), 9 Garrapinillos Zaragoza 50190",
    "addr:housenumber":"9",
    "addr:postcode":"50190",
    "addr:street":"Calle De Mayor Garrapinillos",
    "iso:country":"ES",
    "sg:address":"Calle de Mayor (garrapinillos), 9",
    "sg:city":"Garrapinillos",
    "sg:orig_category":"Farmacias",
    "sg:phone":"+34 976 78 04 32",
    "sg:postcode":"50190",
    "sg:province":"Zaragoza",
    "wof:name":"Tena Altaba Celso",
    "wof:placetype":"venue"
},
  "geometry": {"coordinates":[-1.0273573399,41.6837768555],"type":"Point"}
}