{
  "type": "Feature",
  "properties": {
    "addr:full":"Calle de Villa De Mi\u00d1o, 4 Casanova De Eiris La Coru\u00f1a 15009",
    "addr:housenumber":"4",
    "addr:postcode":"15009",
    "addr:street":"Calle De Villa De Min\u0303O;Corun\u0303A",
    "iso:country":"ES",
    "sg:address":"Calle de Villa De Mi\u00d1o, 4",
    "sg:city":"Casanova De Eiris",
    "sg:orig_category":"Transporte En General",
    "sg:phone":"+34 981 13 03 88",
    "sg:postcode":"15009",
    "sg:province":"La Coru\u00f1a",
    "wof:name":"Barreiro Y Seoane S.l.",
    "wof:placetype":"venue"
},
  "geometry": {"coordinates":[-8.3976202011,43.343662262],"type":"Point"}
}