{
  "type": "Feature",
  "properties": {
    "addr:full":"C/ Filipinas, 2 Grao Castell\u00f3n 12593",
    "addr:housenumber":"2",
    "addr:postcode":"12593",
    "addr:street":"C / Filipinas;Castello\u0301N",
    "iso:country":"ES",
    "sg:address":"C/ Filipinas, 2",
    "sg:city":"Grao",
    "sg:orig_category":"Inmobiliaria (agencias)",
    "sg:phone":"+34 964 58 80 07",
    "sg:postcode":"12593",
    "sg:province":"Castell\u00f3n",
    "wof:name":"Saez & Fenollosa I. Moncofa S.l.",
    "wof:placetype":"venue"
},
  "geometry": {"coordinates":[-0.131852001,39.8013267517],"type":"Point"}
}