{
  "type": "Feature",
  "properties": {
    "iso:country":"ES",
    "sg:address":"Calle de Costanillo, 19",
    "sg:city":"Galvez",
    "sg:orig_category":"Alquiler De V\u00cddeo",
    "sg:phone":"+34 925 41 20 26",
    "sg:postcode":"45164",
    "sg:province":"Toledo",
    "wof:name":"Garcia Sanchez Ruben",
    "wof:placetype":"venue"
},
  "geometry": {"coordinates":[-4.2723684311,39.7011756897],"type":"Point"}
}