{
  "type": "Feature",
  "properties": {
    "addr:full":"Calle de La Rua, 16 Benavente Zamora 49600",
    "addr:housenumber":"16",
    "addr:postcode":"49600",
    "addr:street":"Calle De La Rua",
    "iso:country":"ES",
    "sg:address":"Calle de La Rua, 16",
    "sg:city":"Benavente",
    "sg:orig_category":"Florister\u00cdas",
    "sg:phone":"+34 980 63 05 28",
    "sg:postcode":"49600",
    "sg:province":"Zamora",
    "wof:name":"Prieto Llamas Celia",
    "wof:placetype":"venue"
},
  "geometry": {"coordinates":[-5.6792140007,42.0021514893],"type":"Point"}
}