{
  "type": "Feature",
  "properties": {
    "iso:country":"ES",
    "sg:address":"Calle de Arapiles, 21",
    "sg:city":"Ciudad Rodrigo",
    "sg:orig_category":"Confecci\u00d3n (fabricaci\u00d3n, Al Por Mayor)",
    "sg:phone":"+34 923 48 01 77",
    "sg:postcode":"37500",
    "sg:province":"Salamanca",
    "wof:name":"Confecciones Mazur S.l.",
    "wof:placetype":"venue"
},
  "geometry": {"coordinates":[-6.5264334679,40.598285675],"type":"Point"}
}