{
  "type": "Feature",
  "properties": {
    "addr:full":"Calle de Larramendi Padre, 2 Bilbao Vizcaya 48012",
    "addr:housenumber":"2",
    "addr:postcode":"48012",
    "addr:street":"Calle De Larramendi Padre",
    "iso:country":"ES",
    "sg:address":"Calle de Larramendi Padre, 2",
    "sg:city":"Bilbao",
    "sg:orig_category":"Fabricaci\u00d3n De Papel Pintado",
    "sg:phone":"+34 944 43 82 54",
    "sg:postcode":"48012",
    "sg:province":"Vizcaya",
    "wof:name":"Comercial Akelarre S. A.",
    "wof:placetype":"venue"
},
  "geometry": {"coordinates":[-2.9437150955,43.2537994385],"type":"Point"}
}