{
  "type": "Feature",
  "properties": {
    "iso:country":"ES",
    "sg:address":"Calle de Manuel Iradier, 15",
    "sg:city":"Vitoria-gasteiz",
    "sg:orig_category":"Comit\u00c9s De Organizaci\u00d3n De Exposiciones, Ferias, Salones",
    "sg:phone":"+34 945 13 76 08",
    "sg:postcode":"01005",
    "sg:province":"\u00c1lava",
    "wof:name":"Guertari S.l.",
    "wof:placetype":"venue"
},
  "geometry": {"coordinates":[-2.6718540192,42.8423080444],"type":"Point"}
}