{
  "type": "Feature",
  "properties": {
    "iso:country":"ES",
    "sg:address":"Calle de Marques Del Duero, 75",
    "sg:city":"San Pedro Alcantara",
    "sg:orig_category":"\u00d3ptica: Instrumentos (fabricaci\u00d3n)",
    "sg:phone":"+34 952 78 26 62",
    "sg:postcode":"29670",
    "sg:province":"M\u00e1laga",
    "wof:name":"Genz Opticas S.l.",
    "wof:placetype":"venue"
},
  "geometry": {"coordinates":[-4.9890890121,36.4841308594],"type":"Point"}
}