{
  "type": "Feature",
  "properties": {
    "iso:country":"ES",
    "sg:address":"Calle de Aguila, 3",
    "sg:city":"Oviedo",
    "sg:orig_category":"Molduras, Junquillos, Listones Y Molduras Perforadas",
    "sg:phone":"+34 985 21 48 28",
    "sg:postcode":"33003",
    "sg:province":"Asturias",
    "wof:name":"Rodriguez Llano Manuel",
    "wof:placetype":"venue"
},
  "geometry": {"coordinates":[-5.8439955711,43.3629875183],"type":"Point"}
}