{
  "type": "Feature",
  "properties": {
    "iso:country":"ES",
    "sg:address":"Calle de General Weyler, 1",
    "sg:city":"Ecija",
    "sg:orig_category":"Guarder\u00cdas",
    "sg:phone":"+34 955 90 27 20",
    "sg:postcode":"41400",
    "sg:province":"Sevilla",
    "wof:name":"Hijas De La Caridad",
    "wof:placetype":"venue"
},
  "geometry": {"coordinates":[-5.0763988495,37.5432510376],"type":"Point"}
}