{
  "type": "Feature",
  "properties": {
    "addr:full":"Carr Carles Iii, 16 Eivissa Islas Baleares 07800",
    "addr:housenumber":"16",
    "addr:postcode":"07800",
    "addr:street":"Carr Carles Iii",
    "iso:country":"ES",
    "sg:address":"Carr Carles Iii, 16",
    "sg:city":"Eivissa",
    "sg:classifiers":[
        {
            "category":"Manufacturing",
            "subcategory":"Building Materials",
            "type":"Manufacturing & Wholesale Goods"
        }
    ],
    "sg:phone":"+34 971 31 45 09",
    "sg:postcode":"07800",
    "sg:province":"Islas Baleares",
    "sg:tags":[
        "cemento",
        "y",
        "de",
        "fabricaci\u00d3n",
        "cal"
    ],
    "wof:name":"Gresaida Eivissa S.l.",
    "wof:placetype":"venue"
},
  "geometry": {"coordinates":[1.4333599806,38.9117088318],"type":"Point"}
}