{
  "type": "Feature",
  "properties": {
    "addr:full":"Carr Maria Auxiliadora, 126 Badalona Barcelona 08912",
    "addr:housenumber":"126",
    "addr:postcode":"08912",
    "addr:street":"Carr Maria Auxiliadora",
    "iso:country":"ES",
    "sg:address":"Carr Maria Auxiliadora, 126",
    "sg:city":"Badalona",
    "sg:orig_category":"Mec\u00c1nico Del Autom\u00d3vil",
    "sg:phone":"+34 933 99 08 03",
    "sg:postcode":"08912",
    "sg:province":"Barcelona",
    "wof:name":"Talleres Alan S. Cv",
    "wof:placetype":"venue"
},
  "geometry": {"coordinates":[2.2429749966,41.4405517578],"type":"Point"}
}