{
  "type": "Feature",
  "properties": {
    "iso:country":"ES",
    "sg:address":"Plaz Durangoko Plateruen Plaza, 4",
    "sg:city":"Durango",
    "sg:classifiers":[
        {
            "category":"Professional",
            "subcategory":"Management & Consulting",
            "type":"Services"
        }
    ],
    "sg:phone":"+34 946 20 12 12",
    "sg:postcode":"48200",
    "sg:province":"Vizcaya",
    "sg:tags":[
        "asesor\u00cda",
        "en",
        "marketing"
    ],
    "wof:name":"Gamecol-para Ti S.l.",
    "wof:placetype":"venue"
},
  "geometry": {"coordinates":[-2.6327190399,43.1716842651],"type":"Point"}
}