{
  "type": "Feature",
  "properties": {
    "iso:country":"ES",
    "sg:address":"Calle de Francia, 2",
    "sg:city":"Pozuelo De Alarcon",
    "sg:orig_category":"Inmobiliaria (agencias)",
    "sg:phone":"+34 913 51 38 30",
    "sg:postcode":"28224",
    "sg:province":"Madrid",
    "wof:name":"Maper Gestion Inmobiliaria S.l.",
    "wof:placetype":"venue"
},
  "geometry": {"coordinates":[-3.8076059818,40.4324073792],"type":"Point"}
}