{
  "type": "Feature",
  "properties": {
    "iso:country":"ES",
    "sg:address":"Calle de San Francisco Javier, 2",
    "sg:city":"Espartinas",
    "sg:orig_category":"Ense\u00d1anza, Formaci\u00d3n Profesional: Aprendizaje",
    "sg:phone":"+34 902 39 00 39",
    "sg:postcode":"41807",
    "sg:province":"Sevilla",
    "wof:name":"Mancomunidad Del Guadalquivir",
    "wof:placetype":"venue"
},
  "geometry": {"coordinates":[-6.129049778,37.3801574707],"type":"Point"}
}