{
  "type": "Feature",
  "properties": {
    "addr:full":"Calle de Brava (la), 16 Logro\u00f1o La Rioja 26001",
    "addr:housenumber":"16",
    "addr:postcode":"26001",
    "addr:street":"Calle De Brava La;Rioja",
    "iso:country":"ES",
    "sg:address":"Calle de Brava (la), 16",
    "sg:city":"Logro\u00f1o",
    "sg:orig_category":"Pe\u00d1as Y Asociaciones Varias",
    "sg:phone":"+34 941 26 31 15",
    "sg:postcode":"26001",
    "sg:province":"La Rioja",
    "wof:name":"Asociacion Rioja Acoge",
    "wof:placetype":"venue"
},
  "geometry": {"coordinates":[-2.4427537918,42.4670372009],"type":"Point"}
}