{
  "type": "Feature",
  "properties": {
    "iso:country":"ES",
    "sg:address":"Calle de Salobre\u00d1a, S/n",
    "sg:city":"Sevilla",
    "sg:orig_category":"Asociaciones Humanitarias, De Cooperaci\u00d3n, De Acci\u00d3n Social",
    "sg:phone":"+34 954 67 32 36",
    "sg:postcode":"41006",
    "sg:province":"Sevilla",
    "wof:name":"Asociacion Para La Prevencion De La Droga Y Ayuda Al Toxicomano",
    "wof:placetype":"venue"
},
  "geometry": {"coordinates":[-5.9348635674,37.3737373352],"type":"Point"}
}