{
  "type": "Feature",
  "properties": {
    "iso:country":"ES",
    "sg:address":"Carrer de Sant Josep (de), 114",
    "sg:city":"Vilassar De Mar",
    "sg:orig_category":"Centros De Adelgazamiento Y De Est\u00c9tica",
    "sg:phone":"+34 937 59 34 95",
    "sg:postcode":"08340",
    "sg:province":"Barcelona",
    "wof:name":"Guixe Serena Ramona",
    "wof:placetype":"venue"
},
  "geometry": {"coordinates":[2.3951189518,41.5053215027],"type":"Point"}
}