{
  "type": "Feature",
  "properties": {
    "iso:country":"ES",
    "sg:address":"Calle de Profesor Blanco, 18",
    "sg:city":"Valencia",
    "sg:orig_category":"Agencias Y Agentes Comerciales, Representantes",
    "sg:phone":"+34 963 57 18 36",
    "sg:postcode":"46014",
    "sg:province":"Valencia",
    "wof:name":"Amorada Ibosch S.l",
    "wof:placetype":"venue"
},
  "geometry": {"coordinates":[-0.3992601931,39.4582481384],"type":"Point"}
}