{
  "type": "Feature",
  "properties": {
    "addr:full":"Carrer de Arx Lluis Salvador, S/n Palma Islas Baleares 07004",
    "addr:housenumber":"s",
    "addr:postcode":"07004",
    "addr:street":"Carrer De Arx Lluis Salvador;/ N",
    "iso:country":"ES",
    "sg:address":"Carrer de Arx Lluis Salvador, S/n",
    "sg:city":"Palma",
    "sg:orig_category":"Agencias Y Agentes Comerciales, Representantes",
    "sg:phone":"+34 971 29 02 69",
    "sg:postcode":"07004",
    "sg:province":"Islas Baleares",
    "wof:name":"La Bigornia Balear S.l.",
    "wof:placetype":"venue"
},
  "geometry": {"coordinates":[2.6597950459,39.5886116028],"type":"Point"}
}