{
  "type": "Feature",
  "properties": {
    "iso:country":"ES",
    "sg:address":"Avda Nacional, 28",
    "sg:city":"Arenal",
    "sg:orig_category":"Electrodom\u00c9sticos (al Por Menor)",
    "sg:phone":"+34 971 26 10 93",
    "sg:postcode":"07600",
    "sg:province":"Islas Baleares",
    "wof:name":"Cafeteria Bridge",
    "wof:placetype":"venue"
},
  "geometry": {"coordinates":[2.752327919,39.5086097717],"type":"Point"}
}