{
  "type": "Feature",
  "properties": {
    "addr:full":"Calle de Villena, 22 Alacant Alicante 03008",
    "addr:housenumber":"22",
    "addr:postcode":"03008",
    "addr:street":"Calle De Villena",
    "iso:country":"ES",
    "sg:address":"Calle de Villena, 22",
    "sg:city":"Alacant",
    "sg:orig_category":"Chapister\u00cda",
    "sg:phone":"+34 965 28 81 17",
    "sg:postcode":"03008",
    "sg:province":"Alicante",
    "wof:name":"Soler Cartagena Manuel",
    "wof:placetype":"venue"
},
  "geometry": {"coordinates":[-0.510184288,38.3290061951],"type":"Point"}
}