{
  "type": "Feature",
  "properties": {
    "addr:full":"Carrer de Mossen Jacint Verdaguer, 161 S. Boi Llobregat Barcelona 08830",
    "addr:housenumber":"161",
    "addr:postcode":"08830",
    "addr:street":"Carrer De Mossen Jacint Verdaguer;S.",
    "iso:country":"ES",
    "sg:address":"Carrer de Mossen Jacint Verdaguer, 161",
    "sg:city":"S. Boi Llobregat",
    "sg:orig_category":"Asociaciones, Organismos Culturales Y Socioeducativos",
    "sg:phone":"+34 936 54 01 51",
    "sg:postcode":"08830",
    "sg:province":"Barcelona",
    "wof:name":"Hermandad Union Extreme\u00f1a",
    "wof:placetype":"venue"
},
  "geometry": {"coordinates":[2.0438070297,41.3382568359],"type":"Point"}
}