{
  "type": "Feature",
  "properties": {
    "iso:country":"ES",
    "sg:address":"Pur\u00edsima, 7",
    "sg:city":"Vinaros",
    "sg:orig_category":"Asociaciones Y Clubs Deportivos",
    "sg:phone":"+34 964 45 25 65",
    "sg:postcode":"12500",
    "sg:province":"Castell\u00f3n",
    "wof:name":"Plazara C.b",
    "wof:placetype":"venue"
},
  "geometry": {"coordinates":[0.4756270051,40.4699440002],"type":"Point"}
}