{
  "type": "Feature",
  "properties": {
    "addr:full":"Wenceslao L\u00f3pez Albo, 29 Laredo Cantabria 39770",
    "addr:housenumber":"29",
    "addr:postcode":"39770",
    "addr:street":"Wenceslao Lo\u0301Pez Albo",
    "iso:country":"ES",
    "sg:address":"Wenceslao L\u00f3pez Albo, 29",
    "sg:city":"Laredo",
    "sg:orig_category":"Carnicer\u00cdas, Carnicer\u00cdas",
    "sg:phone":"+34 942 60 30 62",
    "sg:postcode":"39770",
    "sg:province":"Cantabria",
    "wof:name":"Diego San Emeterio Miguel Angel",
    "wof:placetype":"venue"
},
  "geometry": {"coordinates":[-3.4082789421,43.4121055603],"type":"Point"}
}