{
  "type": "Feature",
  "properties": {
    "iso:country":"ES",
    "sg:address":"Avda San Sebastian, 98",
    "sg:city":"Santa Cruz De Tenerife",
    "sg:orig_category":"Agencias De Viajes",
    "sg:phone":"+34 922 20 44 99",
    "sg:postcode":"38005",
    "sg:province":"Santa Cruz De Tenerife",
    "wof:name":"Viajes Mar Travel Canarias S.l.",
    "wof:placetype":"venue"
},
  "geometry": {"coordinates":[-16.2557754517,28.4637298584],"type":"Point"}
}