{
  "type": "Feature",
  "properties": {
    "addr:full":"Ctra Lomo, 31 Arucas Las Palmas 35400",
    "addr:housenumber":"31",
    "addr:postcode":"35400",
    "addr:street":"Ctra Lomo",
    "iso:country":"ES",
    "sg:address":"Ctra Lomo, 31",
    "sg:city":"Arucas",
    "sg:orig_category":"Mec\u00c1nico Del Autom\u00d3vil",
    "sg:phone":"+34 928 60 14 13",
    "sg:postcode":"35400",
    "sg:province":"Las Palmas",
    "wof:name":"Gonzalez Medina Tomas",
    "wof:placetype":"venue"
},
  "geometry": {"coordinates":[-15.5176420212,28.1141738892],"type":"Point"}
}