{
  "type": "Feature",
  "properties": {
    "iso:country":"ES",
    "sg:address":"C/ Doctor Sempere, 23",
    "sg:city":"Alcoi",
    "sg:orig_category":"Asociaciones Y Clubs Deportivos",
    "sg:phone":"+34 965 33 91 40",
    "sg:postcode":"03803",
    "sg:province":"Alicante",
    "wof:name":"Anton Barriga Sebastian",
    "wof:placetype":"venue"
},
  "geometry": {"coordinates":[-0.478164196,38.7004051208],"type":"Point"}
}