{
  "type": "Feature",
  "properties": {
    "iso:country":"ES",
    "sg:address":"Carrer de Coves Cenia, 5",
    "sg:city":"Monovar",
    "sg:orig_category":"Zapatos: Material, Suministros, Accesorios (fabricaci\u00d3n, Al Por Mayor)",
    "sg:phone":"+34 965 47 12 18",
    "sg:postcode":"03640",
    "sg:province":"Alicante",
    "wof:name":"Gimenez Verdu Francisco",
    "wof:placetype":"venue"
},
  "geometry": {"coordinates":[-0.8440660238,38.4397201538],"type":"Point"}
}