{
  "type": "Feature",
  "properties": {
    "addr:full":"Real, S/n Turzo Burgos 09146",
    "addr:housenumber":"s / n",
    "addr:postcode":"09146",
    "addr:street":"Real",
    "iso:country":"ES",
    "sg:address":"Real, S/n",
    "sg:city":"Turzo",
    "sg:orig_category":"Velas Y Cirios (fabricaci\u00d3n, Al Por Menor)",
    "sg:phone":"+34 947 57 14 24",
    "sg:postcode":"09146",
    "sg:province":"Burgos",
    "sg:website":"turzovelas.com",
    "wof:name":"Turzo Velas S.l.",
    "wof:placetype":"venue"
},
  "geometry": {"coordinates":[-3.7365760803,42.8492927551],"type":"Point"}
}