{
  "type": "Feature",
  "properties": {
    "addr:full":"Pobla Llarga, S/n Rafelguaraf Valencia 46666",
    "addr:housenumber":"s / n",
    "addr:postcode":"46666",
    "iso:country":"ES",
    "sg:address":"Pobla Llarga, S/n",
    "sg:city":"Rafelguaraf",
    "sg:orig_category":"Agricultores, Agricultores",
    "sg:phone":"+34 962 97 90 01",
    "sg:postcode":"46666",
    "sg:province":"Valencia",
    "wof:name":"Bertomeu Fayos S.l.",
    "wof:placetype":"venue"
},
  "geometry": {"coordinates":[-0.4561139941,39.0539398193],"type":"Point"}
}