{
  "type": "Feature",
  "properties": {
    "iso:country":"ES",
    "sg:address":"Calle de Cristobal Colon, 2",
    "sg:city":"Gabia Grande",
    "sg:orig_category":"Edici\u00d3n De Diarios, Revistas, Boletines",
    "sg:phone":"+34 958 58 45 35",
    "sg:postcode":"18110",
    "sg:province":"Granada",
    "wof:name":"Ediciones Adhara S.l.",
    "wof:placetype":"venue"
},
  "geometry": {"coordinates":[-3.6610746384,37.1375923157],"type":"Point"}
}