{
  "type": "Feature",
  "properties": {
    "iso:country":"ES",
    "sg:address":"Calle de Llama (la) (sobarzo), S/n",
    "sg:city":"Sobarzo",
    "sg:orig_category":"M\u00c1rmoles, Granitos Y Piedras Naturales",
    "sg:phone":"+34 942 55 43 55",
    "sg:postcode":"39627",
    "sg:province":"Cantabria",
    "wof:name":"Marmoles Penagos S.l.",
    "wof:placetype":"venue"
},
  "geometry": {"coordinates":[-3.8065559864,43.340385437],"type":"Point"}
}