{
  "type": "Feature",
  "properties": {
    "addr:full":"Calle de Marin Garcia, 5 Malaga M\u00e1laga 29005",
    "addr:housenumber":"5",
    "addr:postcode":"29005",
    "addr:street":"Calle De Marin Garcia;Ma\u0301Laga",
    "iso:country":"ES",
    "sg:address":"Calle de Marin Garcia, 5",
    "sg:city":"Malaga",
    "sg:orig_category":"Inform\u00c1tica (estudios, Servicios, Asesor\u00cda, Formaci\u00d3n)",
    "sg:phone":"+34 952 21 19 59",
    "sg:postcode":"29005",
    "sg:province":"M\u00e1laga",
    "sg:website":"www.solariacentral.com",
    "wof:name":"Solaria Servicios Informaticos S.l.",
    "wof:placetype":"venue"
},
  "geometry": {"coordinates":[-4.4224748611,36.719379425],"type":"Point"}
}