{
  "type": "Feature",
  "properties": {
    "addr:full":"Carrer de Sant Pere (de), 1 S. Carles Rapita Tarragona 43540",
    "addr:postcode":"43540",
    "addr:street":"Carrer De;S. Carles Rapita",
    "iso:country":"ES",
    "sg:address":"Carrer de Sant Pere (de), 1",
    "sg:city":"S. Carles Rapita",
    "sg:orig_category":"Hielo Artificial (fabricaci\u00d3n, Distribuci\u00d3n)",
    "sg:phone":"+34 977 74 45 77",
    "sg:postcode":"43540",
    "sg:province":"Tarragona",
    "wof:name":"Rio Rosales Luis Miguel Del",
    "wof:placetype":"venue"
},
  "geometry": {"coordinates":[0.5954399705,40.6196098328],"type":"Point"}
}