{
  "type": "Feature",
  "properties": {
    "addr:full":"Pase Muelle Del, S/n Donostia-san Sebastian Guip\u00f9zcoa 20003",
    "addr:housenumber":"/ n",
    "addr:postcode":"20003",
    "addr:street":"S",
    "iso:country":"ES",
    "sg:address":"Pase Muelle Del, S/n",
    "sg:city":"Donostia-san Sebastian",
    "sg:orig_category":"Discotecas Y Salas De Baile",
    "sg:phone":"+34 943 42 97 85",
    "sg:postcode":"20003",
    "sg:province":"Guip\u00f9zcoa",
    "wof:name":"Diomon S. L.",
    "wof:placetype":"venue"
},
  "geometry": {"coordinates":[-1.9794000387,43.3173789978],"type":"Point"}
}