{
  "type": "Feature",
  "properties": {
    "iso:country":"ES",
    "sg:address":"Via Massague, 28",
    "sg:city":"Sabadell",
    "sg:orig_category":"Flores Y Plantas Naturales (al Por Mayor)",
    "sg:phone":"+34 937 27 69 32",
    "sg:postcode":"08202",
    "sg:province":"Barcelona",
    "wof:name":"Berello Do\u00f1ate Teresa",
    "wof:placetype":"venue"
},
  "geometry": {"coordinates":[2.1078979969,41.5500335693],"type":"Point"}
}