{
  "type": "Feature",
  "properties": {
    "addr:full":"Calle de Campo Verde, 4 Granada Granada 18001",
    "addr:housenumber":"4",
    "addr:postcode":"18001",
    "addr:street":"Calle De Campo Verde",
    "iso:country":"ES",
    "sg:address":"Calle de Campo Verde, 4",
    "sg:city":"Granada",
    "sg:orig_category":"Abogados",
    "sg:phone":"+34 958 52 27 51",
    "sg:postcode":"18001",
    "sg:province":"Granada",
    "wof:name":"Martinez Martinez Pedro Javier",
    "wof:placetype":"venue"
},
  "geometry": {"coordinates":[-3.6002151966,37.1739349365],"type":"Point"}
}