{
  "type": "Feature",
  "properties": {
    "iso:country":"ES",
    "sg:address":"Avda Felipe Iv De, 11",
    "sg:city":"Donostia-san Sebastian",
    "sg:orig_category":"Fisioterapia",
    "sg:phone":"+34 943 47 49 39",
    "sg:postcode":"20011",
    "sg:province":"Guip\u00f9zcoa",
    "wof:name":"Yarza Redondo Susana",
    "wof:placetype":"venue"
},
  "geometry": {"coordinates":[-1.9752460718,43.3056678772],"type":"Point"}
}