{
  "type": "Feature",
  "properties": {
    "iso:country":"ES",
    "sg:address":"Calle de Suecia, 75",
    "sg:city":"Madrid",
    "sg:orig_category":"Reposter\u00cdas",
    "sg:phone":"+34 913 06 15 50",
    "sg:postcode":"28022",
    "sg:province":"Madrid",
    "wof:name":"La Tahona Tarterie S.l.",
    "wof:placetype":"venue"
},
  "geometry": {"coordinates":[-3.6057040691,40.4312858582],"type":"Point"}
}