{
  "type": "Feature",
  "properties": {
    "iso:country":"ES",
    "sg:address":"Calle de Leon Y Castillo, 106",
    "sg:city":"Pto. Rosario",
    "sg:orig_category":"Ropa Y Accesorios",
    "sg:phone":"+34 928 85 23 60",
    "sg:postcode":"35600",
    "sg:province":"Las Palmas",
    "wof:name":"Martin Diaz Ismael",
    "wof:placetype":"venue"
},
  "geometry": {"coordinates":[-13.866399765,28.5009365082],"type":"Point"}
}