{
  "type": "Feature",
  "properties": {
    "iso:country":"ES",
    "sg:address":"Plaz Juan Xxiii Pz Del Carbon, 3",
    "sg:city":"Fraga",
    "sg:orig_category":"Estancos",
    "sg:phone":"+34 974 45 37 38",
    "sg:postcode":"22520",
    "sg:province":"Huesca",
    "wof:name":"Sanchez Calavera Maria Pilar",
    "wof:placetype":"venue"
},
  "geometry": {"coordinates":[0.3495959938,41.5208473206],"type":"Point"}
}