{
  "type": "Feature",
  "properties": {
    "iso:country":"ES",
    "sg:address":"Cami Cal Claramunt, S/n",
    "sg:city":"Cal Claramunt",
    "sg:orig_category":"Fabricaci\u00d3n De Cajas De Cart\u00d3n",
    "sg:phone":"+34 938 18 65 95",
    "sg:postcode":"08730",
    "sg:province":"Barcelona",
    "wof:name":"Manipulats De Carto Magi S.l.",
    "wof:placetype":"venue"
},
  "geometry": {"coordinates":[1.6629099846,41.3209686279],"type":"Point"}
}