{
  "type": "Feature",
  "properties": {
    "addr:full":"Jesus G. Poder, 5 La Linea C\u00e1diz 11300",
    "addr:housenumber":"5",
    "addr:postcode":"11300",
    "addr:street":"Jesus;Poder;La Linea Ca\u0301Diz",
    "iso:country":"ES",
    "sg:address":"Jesus G. Poder, 5",
    "sg:city":"La Linea",
    "sg:orig_category":"Asesor\u00cda De Formaci\u00d3n Y Gesti\u00d3n De Personal",
    "sg:phone":"+34 956 76 73 76",
    "sg:postcode":"11300",
    "sg:province":"C\u00e1diz",
    "wof:name":"Lebron Lobato Inmaculada",
    "wof:placetype":"venue"
},
  "geometry": {"coordinates":[-5.3529996872,36.1627197266],"type":"Point"}
}