{
  "type": "Feature",
  "properties": {
    "iso:country":"ES",
    "sg:address":"Vilatenim, 19",
    "sg:city":"Figueres",
    "sg:orig_category":"Chapister\u00cda",
    "sg:phone":"+34 972 50 03 81",
    "sg:postcode":"17600",
    "sg:province":"Girona",
    "wof:name":"Guich Debesa Eloy",
    "wof:placetype":"venue"
},
  "geometry": {"coordinates":[2.9744729996,42.2697525024],"type":"Point"}
}