{
  "type": "Feature",
  "properties": {
    "iso:country":"ES",
    "sg:address":"Rua Ourense, 93",
    "sg:city":"Lugo",
    "sg:orig_category":"Molduras, Junquillos, Listones Y Molduras Perforadas",
    "sg:phone":"+34 982 21 36 53",
    "sg:postcode":"27004",
    "sg:province":"Lugo",
    "wof:name":"Castro Lopez Benigno",
    "wof:placetype":"venue"
},
  "geometry": {"coordinates":[-7.5662021637,43.0158081055],"type":"Point"}
}