{
  "type": "Feature",
  "properties": {
    "addr:full":"Avda Cruz De La Ermita, S/n Burguillos Sevilla 41220",
    "addr:housenumber":"/ n",
    "addr:postcode":"41220",
    "addr:street":"Avda Cruz De La Ermita S",
    "iso:country":"ES",
    "sg:address":"Avda Cruz De La Ermita, S/n",
    "sg:city":"Burguillos",
    "sg:orig_category":"Barbacoas Y Accesorios",
    "sg:phone":"+34 955 73 82 65",
    "sg:postcode":"41220",
    "sg:province":"Sevilla",
    "wof:name":"Horno Asar El Fogon Segovia",
    "wof:placetype":"venue"
},
  "geometry": {"coordinates":[-5.9671640396,37.580745697],"type":"Point"}
}