{
  "type": "Feature",
  "properties": {
    "iso:country":"ES",
    "sg:address":"Calle de Rucoba, S/n",
    "sg:city":"Limpias",
    "sg:orig_category":"Venta, Instalaci\u00d3n De Cocinas",
    "sg:phone":"+34 942 62 21 40",
    "sg:postcode":"39820",
    "sg:province":"Cantabria",
    "wof:name":"Hostal Restaurante Piedra S.c",
    "wof:placetype":"venue"
},
  "geometry": {"coordinates":[-3.4168190956,43.3642616272],"type":"Point"}
}