{
  "type": "Feature",
  "properties": {
    "addr:full":"Rua Unidade (da), 8 Lugo Lugo 27004",
    "addr:postcode":"27004",
    "iso:country":"ES",
    "sg:address":"Rua Unidade (da), 8",
    "sg:city":"Lugo",
    "sg:orig_category":"Electricidad: Instaladores",
    "sg:phone":"+34 982 21 51 45",
    "sg:postcode":"27004",
    "sg:province":"Lugo",
    "wof:name":"Montecelos Vi\u00f1a Jorge",
    "wof:placetype":"venue"
},
  "geometry": {"coordinates":[-7.5655508041,43.0168685913],"type":"Point"}
}