{
  "type": "Feature",
  "properties": {
    "iso:country":"ES",
    "sg:address":"Carr Balmes, 6",
    "sg:city":"Hostalric",
    "sg:orig_category":"Doctores En Medicina",
    "sg:phone":"+34 972 86 42 48",
    "sg:postcode":"17450",
    "sg:province":"Girona",
    "wof:name":"Olive Valderrama Jose Gabriel",
    "wof:placetype":"venue"
},
  "geometry": {"coordinates":[2.6305301189,41.7464103699],"type":"Point"}
}