{
  "type": "Feature",
  "properties": {
    "iso:country":"ES",
    "sg:address":"Avda Julian Besteiro, S/n",
    "sg:city":"Olvera",
    "sg:orig_category":"Cajas De Ahorro",
    "sg:phone":"+34 956 13 08 08",
    "sg:postcode":"11690",
    "sg:province":"C\u00e1diz",
    "sg:website":"www.unicaja.es",
    "wof:name":"Unicaja",
    "wof:placetype":"venue"
},
  "geometry": {"coordinates":[-5.2563691139,36.9342689514],"type":"Point"}
}