{
  "type": "Feature",
  "properties": {
    "iso:country":"ES",
    "sg:address":"Calle de Pano Y Ruata, 2",
    "sg:city":"Zaragoza",
    "sg:orig_category":"Caf\u00c9s, Bares, Cervecer\u00cdas",
    "sg:phone":"+34 976 73 54 51",
    "sg:postcode":"50015",
    "sg:province":"Zaragoza",
    "wof:name":"Telefonia Aragonesa Escucha Rapida S.l.",
    "wof:placetype":"venue"
},
  "geometry": {"coordinates":[-0.8754940033,41.6613006592],"type":"Point"}
}