{
  "type": "Feature",
  "properties": {
    "iso:country":"ES",
    "sg:address":"Avda Andalucia, 22",
    "sg:city":"Lanjaron",
    "sg:orig_category":"Farmacias",
    "sg:phone":"+34 958 77 09 43",
    "sg:postcode":"18420",
    "sg:province":"Granada",
    "wof:name":"Sanchez Moreno Antonio",
    "wof:placetype":"venue"
},
  "geometry": {"coordinates":[-3.485033989,36.9184837341],"type":"Point"}
}