{
  "type": "Feature",
  "properties": {
    "iso:country":"ES",
    "sg:address":"Carr Lepant (de), 18",
    "sg:city":"Almisera",
    "sg:orig_category":"Venta, Alquiler De Instrumentos Y Accesorios De M\u00dasica",
    "sg:phone":"+34 962 89 61 30",
    "sg:postcode":"46726",
    "sg:province":"Valencia",
    "wof:name":"Ayuntamiento De Almiserat",
    "wof:placetype":"venue"
},
  "geometry": {"coordinates":[-0.285751909,38.9151611328],"type":"Point"}
}