{
  "type": "Feature",
  "properties": {
    "iso:country":"ES",
    "sg:address":"Pase Marina Espa\u00d1ola (de La), S/n",
    "sg:city":"Ceuta",
    "sg:orig_category":"Administraciones Regionales, Departamentales Y Locales",
    "sg:phone":"+34 956 51 34 60",
    "sg:postcode":"51001",
    "sg:province":"Ceuta",
    "wof:name":"Ciudad Autonoma De Ceuta.",
    "wof:placetype":"venue"
},
  "geometry": {"coordinates":[-5.3302302361,35.8947601318],"type":"Point"}
}