{
  "type": "Feature",
  "properties": {
    "iso:country":"ES",
    "sg:address":"Carr Major, 31",
    "sg:city":"Gandia",
    "sg:orig_category":"Relojer\u00cda (al Por Menor, Reparaci\u00d3n)",
    "sg:phone":"+34 962 87 21 54",
    "sg:postcode":"46700",
    "sg:province":"Valencia",
    "wof:name":"Relojeria Sendra C.b.",
    "wof:placetype":"venue"
},
  "geometry": {"coordinates":[-0.1913339943,38.960735321],"type":"Point"}
}