{
  "type": "Feature",
  "properties": {
    "addr:full":"Avda General Capalleja, 19 Navelgas Asturias 33873",
    "addr:housenumber":"19",
    "addr:postcode":"33873",
    "addr:street":"Avda General Capalleja;Asturias",
    "iso:country":"ES",
    "sg:address":"Avda General Capalleja, 19",
    "sg:city":"Navelgas",
    "sg:orig_category":"Cajas De Ahorro",
    "sg:phone":"+34 985 80 60 73",
    "sg:postcode":"33873",
    "sg:province":"Asturias",
    "wof:name":"Cajastur",
    "wof:placetype":"venue"
},
  "geometry": {"coordinates":[-6.5324959755,43.4251785278],"type":"Point"}
}