{
  "type": "Feature",
  "properties": {
    "iso:country":"ES",
    "sg:address":"Mourente, S/n",
    "sg:city":"Mourente",
    "sg:orig_category":"Asociaciones, Organismos Culturales Y Socioeducativos",
    "sg:phone":"+34 986 84 22 61",
    "sg:postcode":"36164",
    "sg:province":"Pontevedra",
    "wof:name":"Casino Mercantil E Industrial",
    "wof:placetype":"venue"
},
  "geometry": {"coordinates":[-8.5977182388,42.4162864685],"type":"Point"}
}