{
  "type": "Feature",
  "properties": {
    "addr:full":"Carrer de Valencia, 404 Barcelona Barcelona 08013",
    "addr:housenumber":"404",
    "addr:postcode":"08013",
    "addr:street":"Carrer De Valencia",
    "iso:country":"ES",
    "sg:address":"Carrer de Valencia, 404",
    "sg:city":"Barcelona",
    "sg:orig_category":"Arreglo, Reparaci\u00d3n, Piezas Sueltas De Televisi\u00d3n, V\u00cddeo, Hi",
    "sg:phone":"+34 934 58 53 03",
    "sg:postcode":"08013",
    "sg:province":"Barcelona",
    "wof:name":"Abad Burgos Pascual",
    "wof:placetype":"venue"
},
  "geometry": {"coordinates":[2.174917,41.401398],"type":"Point"}
}