{
  "type": "Feature",
  "properties": {
    "iso:country":"ES",
    "sg:address":"Plaz Fray Jacinto, S/n",
    "sg:city":"Pe\u00e7acerrada-urizaharra",
    "sg:orig_category":"Ense\u00d1anza, Formaci\u00d3n Profesional: Aprendizaje",
    "sg:phone":"+34 945 36 70 04",
    "sg:postcode":"01211",
    "sg:province":"\u00c1lava",
    "wof:name":"Ayuntamiento De Pe\u00f1ecerrada",
    "wof:placetype":"venue"
},
  "geometry": {"coordinates":[-2.7133746147,42.6440963745],"type":"Point"}
}