{
  "type": "Feature",
  "properties": {
    "addr:full":"Calle de Bierzo (del), 22 Fuenlabrada Madrid 28947",
    "addr:housenumber":"22",
    "addr:postcode":"28947",
    "addr:street":"Calle De Bierzo Del",
    "iso:country":"ES",
    "sg:address":"Calle de Bierzo (del), 22",
    "sg:city":"Fuenlabrada",
    "sg:orig_category":"Cerrajer\u00cda, Ferrallista",
    "sg:phone":"+34 916 42 10 10",
    "sg:postcode":"28947",
    "sg:province":"Madrid",
    "wof:name":"Francisco Martin Romero Y Angel Mu\u00f1oz Exposito Cdad",
    "wof:placetype":"venue"
},
  "geometry": {"coordinates":[-3.7424821854,40.2699279785],"type":"Point"}
}