{
  "type": "Feature",
  "properties": {
    "addr:full":"Calle de Ramon Y Cajal, S/n Algezares Murcia 30157",
    "addr:housenumber":"s / n",
    "addr:postcode":"30157",
    "addr:street":"Calle De Ramon Y Cajal",
    "iso:country":"ES",
    "sg:address":"Calle de Ramon Y Cajal, S/n",
    "sg:city":"Algezares",
    "sg:orig_category":"Centros De Educaci\u00d3n Especial",
    "sg:phone":"+34 968 84 03 41",
    "sg:postcode":"30157",
    "sg:province":"Murcia",
    "wof:name":"Colegio Nacional Saavedra Fajardo",
    "wof:placetype":"venue"
},
  "geometry": {"coordinates":[-1.1095570326,37.9452705383],"type":"Point"}
}