{
  "type": "Feature",
  "properties": {
    "iso:country":"ES",
    "sg:address":"Pg Industria, 28",
    "sg:city":"Berga-ciudad",
    "sg:orig_category":"Producci\u00d3n, Comercio De Cereales",
    "sg:phone":"+34 938 21 03 71",
    "sg:postcode":"08600",
    "sg:province":"Barcelona",
    "wof:name":"Figols Bover Enrique",
    "wof:placetype":"venue"
},
  "geometry": {"coordinates":[1.8506109715,42.1038818359],"type":"Point"}
}