{
  "type": "Feature",
  "properties": {
    "iso:country":"ES",
    "sg:address":"Carr Mayor, 6",
    "sg:city":"Aldaia",
    "sg:orig_category":"Droguer\u00cdas (al Por Menor)",
    "sg:phone":"+34 961 98 85 99",
    "sg:postcode":"46960",
    "sg:province":"Valencia",
    "wof:name":"Grupo Pedro Llobell S.l.",
    "wof:placetype":"venue"
},
  "geometry": {"coordinates":[-0.460878998,39.4649238586],"type":"Point"}
}