{
  "type": "Feature",
  "properties": {
    "iso:country":"ES",
    "sg:address":"Avda Mestra Victoria Miguez (da), 132",
    "sg:city":"Santiago De Compostela",
    "sg:orig_category":"Fabricaci\u00d3n De Papel Para Embalar",
    "sg:phone":"+34 981 52 21 33",
    "sg:postcode":"15706",
    "sg:province":"La Coru\u00f1a",
    "wof:name":"Papelera De Brandia S. A.",
    "wof:placetype":"venue"
},
  "geometry": {"coordinates":[-8.5664587021,42.8709602356],"type":"Point"}
}