{
  "type": "Feature",
  "properties": {
    "iso:country":"ES",
    "sg:address":"Poli Poligon Industrial, 5",
    "sg:city":"Picassent",
    "sg:orig_category":"Empresarios",
    "sg:phone":"+34 961 24 20 54",
    "sg:postcode":"46220",
    "sg:province":"Valencia",
    "wof:name":"Terra I Formes",
    "wof:placetype":"venue"
},
  "geometry": {"coordinates":[-0.4535759985,39.3523826599],"type":"Point"}
}