{
  "type": "Feature",
  "properties": {
    "addr:full":"Cra. Nacional Cent Cinquanta-dos, Km. 0038,5 La Garriga Barcelona 08530",
    "addr:postcode":"08530",
    "addr:street":"Km. 0038,5",
    "iso:country":"ES",
    "sg:address":"Cra. Nacional Cent Cinquanta-dos, Km. 0038,5",
    "sg:city":"La Garriga",
    "sg:orig_category":"Mec\u00c1nico Del Autom\u00d3vil",
    "sg:phone":"+34 938 71 91 57",
    "sg:postcode":"08530",
    "sg:province":"Barcelona",
    "wof:name":"Bombin Agudo Felix",
    "wof:placetype":"venue"
},
  "geometry": {"coordinates":[2.2889399529,41.6845092773],"type":"Point"}
}