{
  "type": "Feature",
  "properties": {
    "iso:country":"ES",
    "sg:address":"Calle de Mazarambroz, 8",
    "sg:city":"Sonseca",
    "sg:orig_category":"Fabricaci\u00d3n De Telas Y Sedas",
    "sg:phone":"+34 925 38 02 43",
    "sg:postcode":"45100",
    "sg:province":"Toledo",
    "wof:name":"Jimenez Lopez Jesus",
    "wof:placetype":"venue"
},
  "geometry": {"coordinates":[-3.9765388966,39.6765823364],"type":"Point"}
}