{
  "type": "Feature",
  "properties": {
    "addr:full":"Monasterio Irache, 35 Iru\u00f1a Navarra 31011",
    "addr:housenumber":"35",
    "addr:postcode":"31011",
    "addr:street":"Irache",
    "iso:country":"ES",
    "sg:address":"Monasterio Irache, 35",
    "sg:city":"Iru\u00f1a",
    "sg:orig_category":"Masajes",
    "sg:phone":"+34 948 27 55 72",
    "sg:postcode":"31011",
    "sg:province":"Navarra",
    "wof:name":"Cortazar Abarrategui Nekane",
    "wof:placetype":"venue"
},
  "geometry": {"coordinates":[-1.6635010242,42.815700531],"type":"Point"}
}