{
  "type": "Feature",
  "properties": {
    "iso:country":"ES",
    "sg:address":"Av Olivera, 11",
    "sg:city":"Magaluf",
    "sg:orig_category":"Caf\u00c9s, Bares, Cervecer\u00cdas",
    "sg:phone":"+34 971 13 31 09",
    "sg:postcode":"07181",
    "sg:province":"Islas Baleares",
    "wof:name":"Fernandez Garcia Maria",
    "wof:placetype":"venue"
},
  "geometry": {"coordinates":[2.5321509838,39.5081748962],"type":"Point"}
}