{
  "type": "Feature",
  "properties": {
    "iso:country":"ES",
    "sg:address":"Calle de B - Poligono Industrial De Asipo, 58 Nv0a",
    "sg:city":"Llanera",
    "sg:orig_category":"Comercio De Hierro",
    "sg:phone":"+34 985 26 39 09",
    "sg:postcode":"33428",
    "sg:province":"Asturias",
    "wof:name":"Ferrallas Pevigon S.l",
    "wof:placetype":"venue"
},
  "geometry": {"coordinates":[-5.8376913071,43.4152526855],"type":"Point"}
}