{
  "type": "Feature",
  "properties": {
    "iso:country":"ES",
    "sg:address":"Calle de Maximiliano Thous, 46",
    "sg:city":"Valencia",
    "sg:orig_category":"Farmacias",
    "sg:phone":"+34 963 65 11 62",
    "sg:postcode":"46009",
    "sg:province":"Valencia",
    "wof:name":"Navarro Castello Antonio Jose",
    "wof:placetype":"venue"
},
  "geometry": {"coordinates":[-0.3722670078,39.4871902466],"type":"Point"}
}