{
  "type": "Feature",
  "properties": {
    "iso:country":"ES",
    "sg:address":"Calle de Real, 21",
    "sg:city":"Villarrobledo",
    "sg:orig_category":"Cl\u00cdnicas Dentales",
    "sg:phone":"+34 967 14 51 51",
    "sg:postcode":"02600",
    "sg:province":"Albacete",
    "wof:name":"Echevarria De Rada Carlos",
    "wof:placetype":"venue"
},
  "geometry": {"coordinates":[-2.6085150242,39.2625045776],"type":"Point"}
}