{
  "type": "Feature",
  "properties": {
    "iso:country":"ES",
    "sg:address":"Calle de Pedro Castillo, 10",
    "sg:city":"Gines",
    "sg:orig_category":"Persianas Interiores, Exteriores",
    "sg:phone":"+34 954 71 66 01",
    "sg:postcode":"41960",
    "sg:province":"Sevilla",
    "wof:name":"Cuevas Perez Manuel",
    "wof:placetype":"venue"
},
  "geometry": {"coordinates":[-6.0798802376,37.386264801],"type":"Point"}
}