{
  "type": "Feature",
  "properties": {
    "iso:country":"ES",
    "sg:address":"Romero Robledo, 24",
    "sg:city":"Antequera",
    "sg:orig_category":"Producci\u00d3n, Venta De Productos De Agricultura Biol\u00d3gica",
    "sg:phone":"+34 952 84 12 75",
    "sg:postcode":"29200",
    "sg:province":"M\u00e1laga",
    "wof:name":"Canovas Y Mu\u00f1oz S.l.",
    "wof:placetype":"venue"
},
  "geometry": {"coordinates":[-4.5636138916,37.0203018188],"type":"Point"}
}