{
  "type": "Feature",
  "properties": {
    "addr:full":"Carrer de Sant Miquel, 82 Pego Alicante 03780",
    "addr:housenumber":"82",
    "addr:postcode":"03780",
    "addr:street":"Carrer De Sant Miquel",
    "iso:country":"ES",
    "sg:address":"Carrer de Sant Miquel, 82",
    "sg:city":"Pego",
    "sg:orig_category":"Molduras, Junquillos, Listones Y Molduras Perforadas",
    "sg:phone":"+34 965 57 02 57",
    "sg:postcode":"03780",
    "sg:province":"Alicante",
    "wof:name":"Dominguez Fuster Vicente",
    "wof:placetype":"venue"
},
  "geometry": {"coordinates":[-0.1160750017,38.845539093],"type":"Point"}
}