{
  "type": "Feature",
  "properties": {
    "addr:full":"Calle de Dr Castroviejo (del), 1 Coslada Madrid 28820",
    "addr:housenumber":"1",
    "addr:postcode":"28820",
    "addr:street":"Calle De Dr Castroviejo Del",
    "iso:country":"ES",
    "sg:address":"Calle de Dr Castroviejo (del), 1",
    "sg:city":"Coslada",
    "sg:orig_category":"Empresas De Portes Y Mensajer\u00cda",
    "sg:phone":"+34 916 74 04 51",
    "sg:postcode":"28820",
    "sg:province":"Madrid",
    "wof:name":"Logistica Trans Rom S.l.",
    "wof:placetype":"venue"
},
  "geometry": {"coordinates":[-3.5618345737,40.4247627258],"type":"Point"}
}