{
  "type": "Feature",
  "properties": {
    "iso:country":"ES",
    "sg:address":"Calle de Batalla De Cardela, 11",
    "sg:city":"Jerez De La Frontera",
    "sg:orig_category":"Producci\u00d3n, Venta De Productos De Agricultura Biol\u00d3gica",
    "sg:phone":"+34 956 32 51 52",
    "sg:postcode":"11405",
    "sg:province":"C\u00e1diz",
    "wof:name":"Agropecuaria Majarazotan S.l.",
    "wof:placetype":"venue"
},
  "geometry": {"coordinates":[-6.1236438751,36.6876411438],"type":"Point"}
}