{
  "type": "Feature",
  "properties": {
    "addr:full":"Plaz Constitucion (de La), 12 Hornachuelos C\u00f3rdoba 14740",
    "addr:postcode":"14740",
    "addr:street":"Co\u0301Rdoba",
    "iso:country":"ES",
    "sg:address":"Plaz Constitucion (de La), 12",
    "sg:city":"Hornachuelos",
    "sg:orig_category":"Cajas De Ahorro",
    "sg:phone":"+34 957 64 04 74",
    "sg:postcode":"14740",
    "sg:province":"C\u00f3rdoba",
    "sg:website":"www.lacaixa.es",
    "wof:name":"Caixa D'estalvis I Pensions De Barcelona",
    "wof:placetype":"venue"
},
  "geometry": {"coordinates":[-5.2427067757,37.8306846619],"type":"Point"}
}