{
  "type": "Feature",
  "properties": {
    "addr:full":"Las Eras, 2 San Emiliano Le\u00f3n 24144",
    "addr:housenumber":"2",
    "addr:postcode":"24144",
    "addr:street":"Las Eras;Leo\u0301N",
    "iso:country":"ES",
    "sg:address":"Las Eras, 2",
    "sg:city":"San Emiliano",
    "sg:orig_category":"Cajas De Ahorro",
    "sg:phone":"+34 987 59 40 31",
    "sg:postcode":"24144",
    "sg:province":"Le\u00f3n",
    "sg:website":"www.caixagalicia.es",
    "wof:name":"Bt Espa\u00d1a Compa\u00d1ia De Servicios Globales De Telecomunicaciones S.a.u.",
    "wof:placetype":"venue"
},
  "geometry": {"coordinates":[-6.0005259514,42.9714546204],"type":"Point"}
}