{
  "type": "Feature",
  "properties": {
    "addr:full":"Avda Portugal, 126 Salamanca Salamanca 37006",
    "addr:housenumber":"126",
    "addr:postcode":"37006",
    "addr:street":"Avda Portugal",
    "iso:country":"ES",
    "sg:address":"Avda Portugal, 126",
    "sg:city":"Salamanca",
    "sg:orig_category":"Importaci\u00d3n, Exportaci\u00d3n Y Comercios De Productos Textiles",
    "sg:phone":"+34 923 23 33 16",
    "sg:postcode":"37006",
    "sg:province":"Salamanca",
    "wof:name":"Delgado Ruano Maria Jose",
    "wof:placetype":"venue"
},
  "geometry": {"coordinates":[-5.6638388634,40.9725799561],"type":"Point"}
}