{
  "type": "Feature",
  "properties": {
    "addr:full":"Pg Salvat Papasseit, 6 Barcelona Barcelona 08003",
    "addr:housenumber":"6",
    "addr:postcode":"08003",
    "addr:street":"Pg Salvat Papasseit",
    "iso:country":"ES",
    "sg:address":"Pg Salvat Papasseit, 6",
    "sg:city":"Barcelona",
    "sg:orig_category":"Obras Y Organismos Sociales",
    "sg:phone":"+34 933 19 04 19",
    "sg:postcode":"08003",
    "sg:province":"Barcelona",
    "wof:name":"Obra Social San Martin Hijas De La Caridad",
    "wof:placetype":"venue"
},
  "geometry": {"coordinates":[2.1917629242,41.3816947937],"type":"Point"}
}