{
  "type": "Feature",
  "properties": {
    "iso:country":"ES",
    "sg:address":"Carrer de Frederic Chueca, 102",
    "sg:city":"Barri Maritim Del Francas",
    "sg:orig_category":"Agencias Y Agentes Comerciales, Representantes",
    "sg:phone":"+34 977 68 22 91",
    "sg:postcode":"43880",
    "sg:province":"Tarragona",
    "wof:name":"Xicc Import S.l.",
    "wof:placetype":"venue"
},
  "geometry": {"coordinates":[1.2454571724,41.11901474],"type":"Point"}
}