{
  "type": "Feature",
  "properties": {
    "iso:country":"ES",
    "sg:address":"Carrer de Pirineu, 44",
    "sg:city":"Manresa",
    "sg:orig_category":"Montaje (empresas De)",
    "sg:phone":"+34 938 73 20 74",
    "sg:postcode":"08242",
    "sg:province":"Barcelona",
    "wof:name":"Muntatges J. Clemente S.l.",
    "wof:placetype":"venue"
},
  "geometry": {"coordinates":[1.8184640408,41.7369499207],"type":"Point"}
}