{
  "type": "Feature",
  "properties": {
    "addr:full":"Av Oscar Espla, 6 Pla Parcial Platja Alicante 03580",
    "addr:housenumber":"6",
    "addr:postcode":"03580",
    "addr:street":"Av Oscar Espla",
    "iso:country":"ES",
    "sg:address":"Av Oscar Espla, 6",
    "sg:city":"Pla Parcial Platja",
    "sg:orig_category":"Cl\u00cdnicas Dentales",
    "sg:phone":"+34 966 86 68 83",
    "sg:postcode":"03580",
    "sg:province":"Alicante",
    "wof:name":"Euro Clinica Dental S.l.",
    "wof:placetype":"venue"
},
  "geometry": {"coordinates":[-0.1033039987,38.5793037415],"type":"Point"}
}