{
  "type": "Feature",
  "properties": {
    "addr:full":"Carr Doctor Esteva, Del, 48 Son Servera Islas Baleares 07550",
    "addr:housenumber":"48",
    "addr:postcode":"07550",
    "addr:street":"Carr Doctor Esteva Del",
    "iso:country":"ES",
    "sg:address":"Carr Doctor Esteva, Del, 48",
    "sg:city":"Son Servera",
    "sg:orig_category":"Fabricaci\u00d3n De Bicicletas, Motocicletas Y Piezas Sueltas",
    "sg:phone":"+34 971 56 70 46",
    "sg:postcode":"07550",
    "sg:province":"Islas Baleares",
    "wof:name":"Ballester Galmes Isabel",
    "wof:placetype":"venue"
},
  "geometry": {"coordinates":[3.3572099209,39.6203994751],"type":"Point"}
}