{
  "type": "Feature",
  "properties": {
    "iso:country":"ES",
    "sg:address":"Cjto Puerto Deportivo, 13",
    "sg:city":"Marbella",
    "sg:orig_category":"Molduras, Junquillos, Listones Y Molduras Perforadas",
    "sg:phone":"+34 952 77 93 20",
    "sg:postcode":"29600",
    "sg:province":"M\u00e1laga",
    "wof:name":"Mijema Colonier S.l.",
    "wof:placetype":"venue"
},
  "geometry": {"coordinates":[-4.8880758286,36.5063858032],"type":"Point"}
}