{
  "type": "Feature",
  "properties": {
    "addr:full":"Calle de Paris, 28 Malaga M\u00e1laga 29006",
    "addr:housenumber":"28",
    "addr:postcode":"29006",
    "addr:street":"Calle De Paris;Ma\u0301Laga",
    "iso:country":"ES",
    "sg:address":"Calle de Paris, 28",
    "sg:city":"Malaga",
    "sg:orig_category":"Bater\u00cdas",
    "sg:phone":"+34 952 33 50 34",
    "sg:postcode":"29006",
    "sg:province":"M\u00e1laga",
    "wof:name":"Cega Multidistribucion S.a.",
    "wof:placetype":"venue"
},
  "geometry": {"coordinates":[-4.472468853,36.7008552551],"type":"Point"}
}