{
  "type": "Feature",
  "properties": {
    "iso:country":"ES",
    "sg:address":"Calle de Cruz De Morera, 77",
    "sg:city":"San Francisco De Paula",
    "sg:orig_category":"Poller\u00cda Y Caza (al Por Menor)",
    "sg:phone":"+34 928 35 23 65",
    "sg:postcode":"35017",
    "sg:province":"Las Palmas",
    "wof:name":"Aboumedlej Suarez Eduardo",
    "wof:placetype":"venue"
},
  "geometry": {"coordinates":[-15.447056,28.059021],"type":"Point"}
}