{
  "type": "Feature",
  "properties": {
    "iso:country":"ES",
    "sg:address":"Calle de Tornerias, 20",
    "sg:city":"Toledo",
    "sg:orig_category":"Tiendas De Grano, Frutas Y Legumbres Secas (al Por Menor)",
    "sg:phone":"+34 925 22 34 94",
    "sg:postcode":"45001",
    "sg:province":"Toledo",
    "wof:name":"Dominguez Gonzalez Jose",
    "wof:placetype":"venue"
},
  "geometry": {"coordinates":[-4.0223450661,39.8584823608],"type":"Point"}
}