{
  "type": "Feature",
  "properties": {
    "addr:full":"Avda Europa, 9 Horno De Alcedo Valencia 46026",
    "addr:housenumber":"9",
    "addr:postcode":"46026",
    "addr:street":"Avda Europa;De Alcedo",
    "iso:country":"ES",
    "sg:address":"Avda Europa, 9",
    "sg:city":"Horno De Alcedo",
    "sg:orig_category":"Mec\u00c1nico Del Autom\u00d3vil",
    "sg:phone":"+34 963 75 34 02",
    "sg:postcode":"46026",
    "sg:province":"Valencia",
    "wof:name":"V30 Autos C.b",
    "wof:placetype":"venue"
},
  "geometry": {"coordinates":[-0.3842839897,39.4358444214],"type":"Point"}
}