{
  "type": "Feature",
  "properties": {
    "addr:full":"Calle de Real, 74 Viso Marques Ciudad Real 13770",
    "addr:housenumber":"74",
    "addr:postcode":"marques;13770",
    "addr:street":"Calle De Real",
    "iso:country":"ES",
    "sg:address":"Calle de Real, 74",
    "sg:city":"Viso Marques",
    "sg:orig_category":"Relojer\u00cda (al Por Menor, Reparaci\u00d3n)",
    "sg:phone":"+34 926 33 62 10",
    "sg:postcode":"13770",
    "sg:province":"Ciudad Real",
    "wof:name":"Bola\u00f1os Martin Ramon Manuel",
    "wof:placetype":"venue"
},
  "geometry": {"coordinates":[-3.5632278919,38.5214500427],"type":"Point"}
}