{
  "type": "Feature",
  "properties": {
    "addr:full":"Calle de San Pedro, 10 Caceres C\u00e1ceres 10003",
    "addr:housenumber":"10",
    "addr:postcode":"10003",
    "addr:street":"Calle De San Pedro;Ca\u0301Ceres",
    "iso:country":"ES",
    "sg:address":"Calle de San Pedro, 10",
    "sg:city":"Caceres",
    "sg:orig_category":"Ense\u00d1anza, Formaci\u00d3n Profesional: Aprendizaje",
    "sg:phone":"+34 927 26 04 45",
    "sg:postcode":"10003",
    "sg:province":"C\u00e1ceres",
    "wof:name":"Escuela Extreme\u00d1a Social,s.l.",
    "wof:placetype":"venue"
},
  "geometry": {"coordinates":[-6.3741822243,39.4735374451],"type":"Point"}
}