{
  "type": "Feature",
  "properties": {
    "iso:country":"ES",
    "sg:address":"Carr Ciutat, S/n",
    "sg:city":"Capdepera",
    "sg:orig_category":"Bebidas",
    "sg:phone":"+34 971 56 34 77",
    "sg:postcode":"07580",
    "sg:province":"Islas Baleares",
    "wof:name":"Juan Trobat Juan",
    "wof:placetype":"venue"
},
  "geometry": {"coordinates":[3.4261898994,39.7014389038],"type":"Point"}
}