{
  "type": "Feature",
  "properties": {
    "iso:country":"ES",
    "sg:address":"El Si, 3",
    "sg:city":"Sta Cruz Tenerife",
    "sg:orig_category":"Asesor\u00cda De Formaci\u00d3n Y Gesti\u00d3n De Personal",
    "sg:phone":"+34 922 24 30 93",
    "sg:postcode":"38002",
    "sg:province":"Santa Cruz De Tenerife",
    "wof:name":"Angel Reyes Maria Mercedes",
    "wof:placetype":"venue"
},
  "geometry": {"coordinates":[-16.2494163513,28.4677200317],"type":"Point"}
}