{
  "type": "Feature",
  "properties": {
    "iso:country":"ES",
    "sg:address":"Avda Cordoba, S/n",
    "sg:city":"Llerena",
    "sg:orig_category":"Mec\u00c1nico Del Autom\u00d3vil",
    "sg:phone":"+34 924 87 10 77",
    "sg:postcode":"06900",
    "sg:province":"Badajoz",
    "wof:name":"Lopez Barragan Antonio",
    "wof:placetype":"venue"
},
  "geometry": {"coordinates":[-6.0109591484,38.2393455505],"type":"Point"}
}