{
  "type": "Feature",
  "properties": {
    "iso:country":"ES",
    "sg:address":"Pla\u00c7 Ruiz Picasso, 7",
    "sg:city":"Grao",
    "sg:orig_category":"Albergues",
    "sg:phone":"+34 964 58 81 12",
    "sg:postcode":"12593",
    "sg:province":"Castell\u00f3n",
    "wof:name":"Marti Marti Maria Dolores",
    "wof:placetype":"venue"
},
  "geometry": {"coordinates":[-0.1429889947,39.8067741394],"type":"Point"}
}