{
  "type": "Feature",
  "properties": {
    "iso:country":"ES",
    "sg:address":"Carrer de Sant Josep, 19",
    "sg:city":"Sant Feliu Llobregat",
    "sg:orig_category":"Molduras, Junquillos, Listones Y Molduras Perforadas",
    "sg:phone":"+34 936 85 55 63",
    "sg:postcode":"08980",
    "sg:province":"Barcelona",
    "wof:name":"Santamaria Perez Jose Antonio",
    "wof:placetype":"venue"
},
  "geometry": {"coordinates":[2.041713953,41.3802947998],"type":"Point"}
}