{
  "type": "Feature",
  "properties": {
    "addr:full":"Calle de Padre Tabernero, 6 Guadalajara Guadalajara 19002",
    "addr:housenumber":"6",
    "addr:postcode":"19002",
    "addr:street":"Calle De Padre Tabernero",
    "iso:country":"ES",
    "sg:address":"Calle de Padre Tabernero, 6",
    "sg:city":"Guadalajara",
    "sg:orig_category":"Fabricaci\u00d3n, Distribuci\u00d3n De Discos, V\u00cddeodiscos Y Musicassettes",
    "sg:phone":"+34 949 21 54 67",
    "sg:postcode":"19002",
    "sg:province":"Guadalajara",
    "sg:website":"www.tipo.es",
    "wof:name":"Silver Rain S.l.",
    "wof:placetype":"venue"
},
  "geometry": {"coordinates":[-3.1625618935,40.6281051636],"type":"Point"}
}