{
  "type": "Feature",
  "properties": {
    "addr:full":"Calle de Estacion, 3 Olite Navarra 31390",
    "addr:housenumber":"3",
    "addr:postcode":"31390",
    "addr:street":"Calle De Estacion",
    "iso:country":"ES",
    "sg:address":"Calle de Estacion, 3",
    "sg:city":"Olite",
    "sg:orig_category":"Panader\u00cdas, Panader\u00cdas",
    "sg:phone":"+34 948 74 05 79",
    "sg:postcode":"31390",
    "sg:province":"Navarra",
    "wof:name":"Vidaurre Escalera Jose Maria Y Julio S.i.",
    "wof:placetype":"venue"
},
  "geometry": {"coordinates":[-1.6512830257,42.4835548401],"type":"Point"}
}