{
  "type": "Feature",
  "properties": {
    "addr:full":"Calle de Peregrinos Los, S/n Goro Las Palmas 35215",
    "addr:postcode":"35215",
    "addr:street":"Calle De Peregrinos Los S / N Goro Las",
    "iso:country":"ES",
    "sg:address":"Calle de Peregrinos Los, S/n",
    "sg:city":"Goro",
    "sg:orig_category":"Maquinaria Para Industrias Diversas",
    "sg:phone":"+34 928 70 04 55",
    "sg:postcode":"35215",
    "sg:province":"Las Palmas",
    "sg:website":"www.alvemaca.com",
    "wof:name":"Alvemaca S.l.",
    "wof:placetype":"venue"
},
  "geometry": {"coordinates":[-15.3912210464,27.9679450989],"type":"Point"}
}