{
  "type": "Feature",
  "properties": {
    "iso:country":"ES",
    "sg:address":"Carr Argenteria, 1",
    "sg:city":"Girona",
    "sg:orig_category":"Abogados",
    "sg:phone":"+34 972 20 53 00",
    "sg:postcode":"17004",
    "sg:province":"Girona",
    "wof:name":"Roca-zapata Advocats S.l.",
    "wof:placetype":"venue"
},
  "geometry": {"coordinates":[2.8243539333,41.9847068787],"type":"Point"}
}