{
  "type": "Feature",
  "properties": {
    "iso:country":"ES",
    "sg:address":"Calle de Fresadores, 18",
    "sg:city":"Alcamar",
    "sg:orig_category":"Construcciones Met\u00c1licas",
    "sg:phone":"+34 918 86 52 02",
    "sg:postcode":"28816",
    "sg:province":"Madrid",
    "wof:name":"Gomyl S.a.",
    "wof:placetype":"venue"
},
  "geometry": {"coordinates":[-3.7003455162,40.4166908264],"type":"Point"}
}