{
  "type": "Feature",
  "properties": {
    "iso:country":"ES",
    "sg:address":"Calle de San Anton, 21",
    "sg:city":"Calatayud",
    "sg:orig_category":"Animales (al Por Menor)",
    "sg:phone":"+34 976 88 02 14",
    "sg:postcode":"50300",
    "sg:province":"Zaragoza",
    "wof:name":"Marti Joven Ana Isabel",
    "wof:placetype":"venue"
},
  "geometry": {"coordinates":[-1.6419609785,41.3527488708],"type":"Point"}
}