{
  "type": "Feature",
  "properties": {
    "iso:country":"ES",
    "sg:address":"Avda Quevedo, 4",
    "sg:city":"Le\u00f3n",
    "sg:orig_category":"Reposter\u00cdas",
    "sg:phone":"+34 987 23 49 45",
    "sg:postcode":"24009",
    "sg:province":"Le\u00f3n",
    "wof:name":"Gonzalez Garcia Horacio",
    "wof:placetype":"venue"
},
  "geometry": {"coordinates":[-5.586730957,42.5999183655],"type":"Point"}
}