{
  "type": "Feature",
  "properties": {
    "iso:country":"ES",
    "sg:address":"Poli Las Capellanias, S/n",
    "sg:city":"Caceres",
    "sg:orig_category":"Autob\u00das (explotaci\u00d3n Y Servicios De)",
    "sg:phone":"+34 927 26 90 06",
    "sg:postcode":"10005",
    "sg:province":"C\u00e1ceres",
    "wof:name":"Autocares Blanco Jimenez S.l.",
    "wof:placetype":"venue"
},
  "geometry": {"coordinates":[-6.5341739655,39.4675254822],"type":"Point"}
}