{
  "type": "Feature",
  "properties": {
    "addr:full":"Calle de Josefina Mayor, 43 Goro Las Palmas 35215",
    "addr:housenumber":"43",
    "addr:postcode":"35215",
    "addr:street":"Calle De Josefina Mayor",
    "iso:country":"ES",
    "sg:address":"Calle de Josefina Mayor, 43",
    "sg:city":"Goro",
    "sg:orig_category":"Embalajes",
    "sg:phone":"+34 928 70 04 90",
    "sg:postcode":"35215",
    "sg:province":"Las Palmas",
    "wof:name":"Fragarsan S.l.",
    "wof:placetype":"venue"
},
  "geometry": {"coordinates":[-15.398223877,27.9939899445],"type":"Point"}
}