{
  "type": "Feature",
  "properties": {
    "iso:country":"ES",
    "sg:address":"Calle de Nu\u00d1ez De Balboa, 59",
    "sg:city":"Madrid",
    "sg:orig_category":"Urbanistas",
    "sg:phone":"+34 914 31 06 80",
    "sg:postcode":"28001",
    "sg:province":"Madrid",
    "wof:name":"Garcia De Mateos Alonso Angel",
    "wof:placetype":"venue"
},
  "geometry": {"coordinates":[-3.6827208996,40.4281425476],"type":"Point"}
}