{
  "type": "Feature",
  "properties": {
    "iso:country":"ES",
    "sg:address":"Avgd Marti Pujol, 84",
    "sg:city":"Badalona",
    "sg:orig_category":"Caf\u00c9s, Bares, Cervecer\u00cdas",
    "sg:phone":"+34 933 89 33 32",
    "sg:postcode":"08911",
    "sg:province":"Barcelona",
    "wof:name":"Astur Cafe S.c.p.",
    "wof:placetype":"venue"
},
  "geometry": {"coordinates":[2.2467865944,41.4479560852],"type":"Point"}
}