{
  "type": "Feature",
  "properties": {
    "iso:country":"ES",
    "sg:address":"Calle de Serranos, 15",
    "sg:city":"Valencia",
    "sg:orig_category":"Bordado, Marcado A Medida",
    "sg:phone":"+34 963 91 07 95",
    "sg:postcode":"46003",
    "sg:province":"Valencia",
    "wof:name":"Eusebio Sanchez S.a.",
    "wof:placetype":"venue"
},
  "geometry": {"coordinates":[-0.3767409921,39.4777984619],"type":"Point"}
}