{
  "type": "Feature",
  "properties": {
    "addr:full":"Calle de Usandizaga Eresgille, 1 Mungia Vizcaya 48100",
    "addr:housenumber":"1",
    "addr:postcode":"48100",
    "addr:street":"Calle De Usandizaga Eresgille",
    "iso:country":"ES",
    "sg:address":"Calle de Usandizaga Eresgille, 1",
    "sg:city":"Mungia",
    "sg:classifiers":[
        {
            "category":"Casinos & Gambling",
            "type":"Entertainment"
        }
    ],
    "sg:phone":"+34 946 55 34 30",
    "sg:postcode":"48100",
    "sg:province":"Vizcaya",
    "sg:tags":[
        "locale",
        "de",
        "juego"
    ],
    "wof:name":"Txirrist Park, S.l.",
    "wof:placetype":"venue"
},
  "geometry": {"coordinates":[-2.8501620293,43.356098175],"type":"Point"}
}