{
  "type": "Feature",
  "properties": {
    "iso:country":"ES",
    "sg:address":"Paulino Caballero, 42",
    "sg:city":"Iru\u00f1a",
    "sg:orig_category":"\u00d3ptica: Instrumentos (fabricaci\u00d3n)",
    "sg:phone":"+34 948 29 20 29",
    "sg:postcode":"31003",
    "sg:province":"Navarra",
    "wof:name":"Sanmioptic S.l.",
    "wof:placetype":"venue"
},
  "geometry": {"coordinates":[-1.6371849775,42.8098564148],"type":"Point"}
}