{
  "type": "Feature",
  "properties": {
    "iso:country":"ES",
    "sg:address":"C/ Joan Segura, 9",
    "sg:city":"Manacor",
    "sg:orig_category":"Marroquiner\u00cda Y Art\u00cdculos De Viaje (al Por Menor)",
    "sg:phone":"+34 971 55 14 09",
    "sg:postcode":"07500",
    "sg:province":"Islas Baleares",
    "wof:name":"Dalmau Gelabert Antonio",
    "wof:placetype":"venue"
},
  "geometry": {"coordinates":[3.2096860409,39.56848526],"type":"Point"}
}