{
  "type": "Feature",
  "properties": {
    "addr:full":"Luga Campo De Deportes, S/n Benavente Zamora 49600",
    "addr:housenumber":"s / n",
    "addr:postcode":"49600",
    "iso:country":"ES",
    "sg:address":"Luga Campo De Deportes, S/n",
    "sg:city":"Benavente",
    "sg:orig_category":"Asociaciones Y Clubs Deportivos",
    "sg:phone":"+34 980 63 04 62",
    "sg:postcode":"49600",
    "sg:province":"Zamora",
    "wof:name":"Club Polideportivo Comarcal",
    "wof:placetype":"venue"
},
  "geometry": {"coordinates":[-5.677795887,42.0033531189],"type":"Point"}
}