{
  "type": "Feature",
  "properties": {
    "addr:full":"Avda Alcalde Jose Aranda, 45 Alcorcon Madrid 28923",
    "addr:housenumber":"45",
    "addr:postcode":"28923",
    "addr:street":"Avda Alcalde Jose Aranda",
    "iso:country":"ES",
    "sg:address":"Avda Alcalde Jose Aranda, 45",
    "sg:city":"Alcorcon",
    "sg:orig_category":"Centros De Educaci\u00d3n Especial",
    "sg:phone":"+34 916 10 81 91",
    "sg:postcode":"28923",
    "sg:province":"Madrid",
    "wof:name":"Comunidad Autonoma De Madrid-centros De Educacion",
    "wof:placetype":"venue"
},
  "geometry": {"coordinates":[-3.823143959,40.3417396545],"type":"Point"}
}