{
  "type": "Feature",
  "properties": {
    "iso:country":"ES",
    "sg:address":"Carr Major, 38",
    "sg:city":"Palamos",
    "sg:orig_category":"Gas: Botellas Y Contenedores",
    "sg:phone":"+34 972 31 43 38",
    "sg:postcode":"17230",
    "sg:province":"Girona",
    "wof:name":"Ponsa Collboni Josep",
    "wof:placetype":"venue"
},
  "geometry": {"coordinates":[3.1296150684,41.8472061157],"type":"Point"}
}