{
  "type": "Feature",
  "properties": {
    "addr:full":"Calle de Afan De Ribera, 100 Sevilla Sevilla 41006",
    "addr:housenumber":"100",
    "addr:postcode":"41006",
    "addr:street":"Calle De Afan De Ribera",
    "iso:country":"ES",
    "sg:address":"Calle de Afan De Ribera, 100",
    "sg:city":"Sevilla",
    "sg:orig_category":"Bisuter\u00cda, Joyer\u00cda, Relojer\u00cda (al Por Menor)",
    "sg:phone":"+34 954 92 42 84",
    "sg:postcode":"41006",
    "sg:province":"Sevilla",
    "wof:name":"Jimenez Iglesias Ana Maria",
    "wof:placetype":"venue"
},
  "geometry": {"coordinates":[-5.9581956863,37.372467041],"type":"Point"}
}