{
  "type": "Feature",
  "properties": {
    "iso:country":"ES",
    "sg:address":"Carrer de Murcia, S/n",
    "sg:city":"S. Boi Llobregat",
    "sg:orig_category":"Fabricaci\u00d3n De Moldes Y Modelos",
    "sg:phone":"+34 936 52 87 30",
    "sg:postcode":"08830",
    "sg:province":"Barcelona",
    "sg:website":"www.actronic-sl.com",
    "wof:name":"Actronic S.l.",
    "wof:placetype":"venue"
},
  "geometry": {"coordinates":[2.039624691,41.3267250061],"type":"Point"}
}