{
  "type": "Feature",
  "properties": {
    "addr:full":"Carrer de Vilana, 4 Barcelona Barcelona 08017",
    "addr:housenumber":"4",
    "addr:postcode":"08017",
    "addr:street":"Carrer De Vilana",
    "iso:country":"ES",
    "sg:address":"Carrer de Vilana, 4",
    "sg:city":"Barcelona",
    "sg:orig_category":"Asesor\u00cda Fiscal Y Jur\u00cddica",
    "sg:phone":"+34 934 34 22 10",
    "sg:postcode":"08017",
    "sg:province":"Barcelona",
    "wof:name":"Meserco S.l.",
    "wof:placetype":"venue"
},
  "geometry": {"coordinates":[2.12976408,41.4042472839],"type":"Point"}
}