{
  "type": "Feature",
  "properties": {
    "addr:full":"Pase Castellana, 47 Benidorm Alicante 03500",
    "addr:housenumber":"47",
    "addr:postcode":"03500",
    "addr:street":"Castellana",
    "iso:country":"ES",
    "sg:address":"Pase Castellana, 47",
    "sg:city":"Benidorm",
    "sg:orig_category":"Molduras, Junquillos, Listones Y Molduras Perforadas",
    "sg:phone":"+34 965 86 80 59",
    "sg:postcode":"03500",
    "sg:province":"Alicante",
    "wof:name":"Ruiz Martinez Jose Francisco",
    "wof:placetype":"venue"
},
  "geometry": {"coordinates":[-0.1739459932,38.5365180969],"type":"Point"}
}