{
  "type": "Feature",
  "properties": {
    "addr:full":"Calle de Buztintxulo, 17 Donostia-san Sebastian Guip\u00f9zcoa 20015",
    "addr:housenumber":"17",
    "addr:postcode":"20015",
    "addr:street":"Calle De Buztintxulo",
    "iso:country":"ES",
    "sg:address":"Calle de Buztintxulo, 17",
    "sg:city":"Donostia-san Sebastian",
    "sg:orig_category":"Venta Al Preg\u00d3n",
    "sg:phone":"+34 943 28 83 05",
    "sg:postcode":"20015",
    "sg:province":"Guip\u00f9zcoa",
    "wof:name":"Sdad Coop De Venta Ambulante De Gipuzkoa Juncal S.coop.",
    "wof:placetype":"venue"
},
  "geometry": {"coordinates":[-1.953461051,43.3111801147],"type":"Point"}
}