{
  "type": "Feature",
  "properties": {
    "iso:country":"ES",
    "sg:address":"Calle de Jose Antonio, 5",
    "sg:city":"Val De Santo Domingo",
    "sg:orig_category":"Cajas Para Embalar",
    "sg:phone":"+34 925 77 90 12",
    "sg:postcode":"45519",
    "sg:province":"Toledo",
    "wof:name":"Caja Rural Provincial De Toledo",
    "wof:placetype":"venue"
},
  "geometry": {"coordinates":[-4.2703337669,40.0481987],"type":"Point"}
}