{
  "type": "Feature",
  "properties": {
    "addr:full":"Afueras, S/n Esplus Huesca 22535",
    "addr:postcode":"22535",
    "addr:street":"Afueras S / N Esplus",
    "iso:country":"ES",
    "sg:address":"Afueras, S/n",
    "sg:city":"Esplus",
    "sg:orig_category":"Asociaciones Humanitarias, De Cooperaci\u00d3n, De Acci\u00d3n Social",
    "sg:phone":"+34 974 33 91 56",
    "sg:postcode":"22535",
    "sg:province":"Huesca",
    "wof:name":"Asociacion De Padres De Minusvalidos Psiquicos",
    "wof:placetype":"venue"
},
  "geometry": {"coordinates":[0.2901814878,41.7702331543],"type":"Point"}
}