{
  "type": "Feature",
  "properties": {
    "addr:full":"Calle de Canovas Del Castillo, 11 Valladolid Valladolid 47002",
    "addr:housenumber":"11",
    "addr:postcode":"47002",
    "addr:street":"Calle De Canovas Del Castillo",
    "iso:country":"ES",
    "sg:address":"Calle de Canovas Del Castillo, 11",
    "sg:city":"Valladolid",
    "sg:orig_category":"Artes Gr\u00c1ficas, Artes Pl\u00c1sticas: Material Y Suministros (al Por Menor)",
    "sg:phone":"+34 983 20 51 00",
    "sg:postcode":"47002",
    "sg:province":"Valladolid",
    "wof:name":"Asemaval S.r.l.",
    "wof:placetype":"venue"
},
  "geometry": {"coordinates":[-4.7252225876,41.6520996094],"type":"Point"}
}