{
  "type": "Feature",
  "properties": {
    "addr:full":"Barr Triano, 3 Triano Vizcaya 48509",
    "addr:housenumber":"3",
    "addr:postcode":"48509",
    "addr:street":"Triano",
    "iso:country":"ES",
    "sg:address":"Barr Triano, 3",
    "sg:city":"Triano",
    "sg:orig_category":"Molduras, Junquillos, Listones Y Molduras Perforadas",
    "sg:phone":"+34 946 36 21 03",
    "sg:postcode":"48509",
    "sg:province":"Vizcaya",
    "wof:name":"Redondo Saenz Maria Jose",
    "wof:placetype":"venue"
},
  "geometry": {"coordinates":[-3.0748488903,43.2934913635],"type":"Point"}
}