{
  "type": "Feature",
  "properties": {
    "iso:country":"ES",
    "sg:address":"Carrer de Llorer, 43",
    "sg:city":"Hospitalet Llobregat",
    "sg:orig_category":"Molduras, Junquillos, Listones Y Molduras Perforadas",
    "sg:phone":"+34 934 38 01 20",
    "sg:postcode":"08905",
    "sg:province":"Barcelona",
    "wof:name":"Suarez Ramos Guillermo",
    "wof:placetype":"venue"
},
  "geometry": {"coordinates":[2.1099030972,41.3666915894],"type":"Point"}
}