{
  "type": "Feature",
  "properties": {
    "addr:full":"Catamaran, 1 Los Narejos Murcia 30710",
    "addr:housenumber":"1",
    "addr:postcode":"30710",
    "addr:street":"Catamaran;Los Narejos",
    "iso:country":"ES",
    "sg:address":"Catamaran, 1",
    "sg:city":"Los Narejos",
    "sg:orig_category":"Centros Comerciales Y Grandes Tiendas",
    "sg:phone":"+34 968 58 26 65",
    "sg:postcode":"30710",
    "sg:province":"Murcia",
    "wof:name":"Timerco S.a.",
    "wof:placetype":"venue"
},
  "geometry": {"coordinates":[-0.8345069885,37.763507843],"type":"Point"}
}