{
  "type": "Feature",
  "properties": {
    "iso:country":"ES",
    "sg:address":"Calle de Carabela, 7",
    "sg:city":"Madrid",
    "sg:orig_category":"Sanatorios M\u00c9dico",
    "sg:phone":"+34 913 29 64 58",
    "sg:postcode":"28042",
    "sg:province":"Madrid",
    "wof:name":"Organismo Autonomo De Informatica Y Comunicaciones De La Comunidad De Madrid",
    "wof:placetype":"venue"
},
  "geometry": {"coordinates":[-3.5863490105,40.4555587769],"type":"Point"}
}