{
  "type": "Feature",
  "properties": {
    "iso:country":"ES",
    "sg:address":"Calle de Sandalio Lopez, 27",
    "sg:city":"Madrid",
    "sg:orig_category":"Centros Empresariales",
    "sg:phone":"+34 913 72 10 40",
    "sg:postcode":"28034",
    "sg:province":"Madrid",
    "wof:name":"Perez Marino Salvador",
    "wof:placetype":"venue"
},
  "geometry": {"coordinates":[-3.6910369396,40.4933052063],"type":"Point"}
}