{
  "type": "Feature",
  "properties": {
    "iso:country":"ES",
    "sg:address":"Carrer de Valencia, 647",
    "sg:city":"Barcelona",
    "sg:orig_category":"Ropa Para Se\u00d1oras (al Por Menor)",
    "sg:phone":"+34 933 40 03 14",
    "sg:postcode":"08026",
    "sg:province":"Barcelona",
    "wof:name":"Luisgu S.l.",
    "wof:placetype":"venue"
},
  "geometry": {"coordinates":[2.1889460087,41.412147522],"type":"Point"}
}