{
  "type": "Feature",
  "properties": {
    "iso:country":"ES",
    "sg:address":"Plaz Magdalena, S/n",
    "sg:city":"Noblejas",
    "sg:orig_category":"Bancos",
    "sg:phone":"+34 925 14 02 30",
    "sg:postcode":"45350",
    "sg:province":"Toledo",
    "wof:name":"Banco Espa\u00f1ol De Credito S.a.",
    "wof:placetype":"venue"
},
  "geometry": {"coordinates":[-3.4397039413,39.9795951843],"type":"Point"}
}