{
  "type": "Feature",
  "properties": {
    "addr:full":"Calle de Orellana, 15 Sonseca Toledo 45100",
    "addr:housenumber":"15",
    "addr:postcode":"45100",
    "addr:street":"Calle De Orellana",
    "iso:country":"ES",
    "sg:address":"Calle de Orellana, 15",
    "sg:city":"Sonseca",
    "sg:orig_category":"Empresas De Carpinter\u00cda De Madera",
    "sg:phone":"+34 925 38 00 20",
    "sg:postcode":"45100",
    "sg:province":"Toledo",
    "wof:name":"Eusebio Burgos Sanchez S.l.",
    "wof:placetype":"venue"
},
  "geometry": {"coordinates":[-3.9806389809,39.6702766418],"type":"Point"}
}