{
  "type": "Feature",
  "properties": {
    "addr:full":"Carr Del Pintor Josep Segrelles, 18 Ontinyent Valencia 46870",
    "addr:housenumber":"18",
    "addr:postcode":"46870",
    "addr:street":"Carr Del Pintor Josep Segrelles",
    "iso:country":"ES",
    "sg:address":"Carr Del Pintor Josep Segrelles, 18",
    "sg:city":"Ontinyent",
    "sg:orig_category":"Asesor\u00cda De Formaci\u00d3n Y Gesti\u00d3n De Personal",
    "sg:phone":"+34 962 38 73 01",
    "sg:postcode":"46870",
    "sg:province":"Valencia",
    "wof:name":"Lliso Bartual Juan",
    "wof:placetype":"venue"
},
  "geometry": {"coordinates":[-0.6018999815,38.8215484619],"type":"Point"}
}