{
  "type": "Feature",
  "properties": {
    "iso:country":"ES",
    "sg:address":"Calle de Santo Cristo, S/n",
    "sg:city":"Pedrera",
    "sg:orig_category":"Pescader\u00cdas (al Por Mayor)",
    "sg:phone":"+34 955 82 74 62",
    "sg:postcode":"41566",
    "sg:province":"Sevilla",
    "wof:name":"Pescados Pareja S.l.",
    "wof:placetype":"venue"
},
  "geometry": {"coordinates":[-4.8934440613,37.2245788574],"type":"Point"}
}