{
  "type": "Feature",
  "properties": {
    "addr:full":"Calle de Obispo Nieto, 27 Zamora Zamora 49026",
    "addr:housenumber":"27",
    "addr:postcode":"49026",
    "addr:street":"Calle De Obispo Nieto",
    "iso:country":"ES",
    "sg:address":"Calle de Obispo Nieto, 27",
    "sg:city":"Zamora",
    "sg:orig_category":"Librer\u00cdas",
    "sg:phone":"+34 980 52 38 27",
    "sg:postcode":"49026",
    "sg:province":"Zamora",
    "wof:name":"Barbero Martin Cruz Palmira",
    "wof:placetype":"venue"
},
  "geometry": {"coordinates":[-5.7549519539,41.5038070679],"type":"Point"}
}