{
  "type": "Feature",
  "properties": {
    "iso:country":"ES",
    "sg:address":"Calle de Dorado, 5",
    "sg:city":"Langreo",
    "sg:orig_category":"Farmacias",
    "sg:phone":"+34 985 69 68 99",
    "sg:postcode":"33900",
    "sg:province":"Asturias",
    "wof:name":"Fernandez Huerta Alberto",
    "wof:placetype":"venue"
},
  "geometry": {"coordinates":[-5.6830973625,43.29479599],"type":"Point"}
}