{
  "type": "Feature",
  "properties": {
    "iso:country":"ES",
    "sg:address":"Nagusia, S/n",
    "sg:city":"Azpilkueta",
    "sg:orig_category":"Iglesia Cat\u00d3lica",
    "sg:phone":"+34 948 45 32 28",
    "sg:postcode":"31715",
    "sg:province":"Navarra",
    "wof:name":"Parroquia San Andres",
    "wof:placetype":"venue"
},
  "geometry": {"coordinates":[-1.4908829927,43.1807098389],"type":"Point"}
}