{
  "type": "Feature",
  "properties": {
    "iso:country":"ES",
    "sg:address":"Calle de Andaluces Del Pozo, 6",
    "sg:city":"Madrid",
    "sg:orig_category":"Empresas De Limpieza",
    "sg:phone":"+34 917 85 26 79",
    "sg:postcode":"28053",
    "sg:province":"Madrid",
    "wof:name":"Cabrera Jimenez Coral",
    "wof:placetype":"venue"
},
  "geometry": {"coordinates":[-3.6599400043,40.3715438843],"type":"Point"}
}