{
  "type": "Feature",
  "properties": {
    "addr:full":"Pol Ind Alfares, S/n Rambla C\u00f3rdoba 14540",
    "addr:housenumber":"s / n",
    "addr:postcode":"14540",
    "addr:street":"Rambla Co\u0301Rdoba",
    "iso:country":"ES",
    "sg:address":"Pol Ind Alfares, S/n",
    "sg:city":"Rambla",
    "sg:orig_category":"Fabrica De Cer\u00c1micas",
    "sg:phone":"+34 957 68 24 42",
    "sg:postcode":"14540",
    "sg:province":"C\u00f3rdoba",
    "wof:name":"Alejandres Pino Jose",
    "wof:placetype":"venue"
},
  "geometry": {"coordinates":[-4.7791519165,37.884727478],"type":"Point"}
}