{
  "type": "Feature",
  "properties": {
    "addr:full":"Carrer de Lepant, 8 Creus Barcelona 08397",
    "addr:housenumber":"8",
    "addr:postcode":"08397",
    "addr:street":"Carrer De Lepant",
    "iso:country":"ES",
    "sg:address":"Carrer de Lepant, 8",
    "sg:city":"Creus",
    "sg:orig_category":"Empresas De Carpinter\u00cda De Madera",
    "sg:phone":"+34 937 67 06 68",
    "sg:postcode":"08397",
    "sg:province":"Barcelona",
    "wof:name":"Lazaro Coca Josep",
    "wof:placetype":"venue"
},
  "geometry": {"coordinates":[2.6771550179,41.6251716614],"type":"Point"}
}