{
  "type": "Feature",
  "properties": {
    "addr:full":"Avda Pascual Marquina, S/n Calatayud Zaragoza 50300",
    "addr:housenumber":"s / n",
    "addr:postcode":"50300",
    "addr:street":"Avda Pascual Marquina",
    "iso:country":"ES",
    "sg:address":"Avda Pascual Marquina, S/n",
    "sg:city":"Calatayud",
    "sg:orig_category":"Panader\u00cdas, Panader\u00cdas",
    "sg:phone":"+34 976 88 46 01",
    "sg:postcode":"50300",
    "sg:province":"Zaragoza",
    "wof:name":"Micheto",
    "wof:placetype":"venue"
},
  "geometry": {"coordinates":[-1.6431449652,41.3493843079],"type":"Point"}
}