{
  "type": "Feature",
  "properties": {
    "iso:country":"ES",
    "sg:address":"Mayor, S/n",
    "sg:city":"Villanueva De Sigena",
    "sg:orig_category":"Arenas, Guijarros Y Granulados",
    "sg:phone":"+34 974 57 81 05",
    "sg:postcode":"22231",
    "sg:province":"Huesca",
    "wof:name":"Hormigones Del Pirineo S.a.",
    "wof:placetype":"venue"
},
  "geometry": {"coordinates":[-0.0105539998,41.7139968872],"type":"Point"}
}