{
  "type": "Feature",
  "properties": {
    "addr:full":"Calle de Virgen De Montserrat, 8 Granada Granada 18008",
    "addr:housenumber":"8",
    "addr:postcode":"18008",
    "addr:street":"Calle De Virgen De Montserrat",
    "iso:country":"ES",
    "sg:address":"Calle de Virgen De Montserrat, 8",
    "sg:city":"Granada",
    "sg:orig_category":"Guarder\u00cdas",
    "sg:phone":"+34 958 81 29 04",
    "sg:postcode":"18008",
    "sg:province":"Granada",
    "wof:name":"Blanco Zuloaga Fernanda",
    "wof:placetype":"venue"
},
  "geometry": {"coordinates":[-3.5910029411,37.1651573181],"type":"Point"}
}