{
  "type": "Feature",
  "properties": {
    "iso:country":"ES",
    "sg:address":"Calle de Manuel Brice\u00d1o, S/n",
    "sg:city":"Jaen",
    "sg:orig_category":"Empresas De Carpinter\u00cda Met\u00c1lica",
    "sg:phone":"+34 953 23 49 59",
    "sg:postcode":"23002",
    "sg:province":"Ja\u00e9n",
    "wof:name":"Lopez Lerida Manuel",
    "wof:placetype":"venue"
},
  "geometry": {"coordinates":[-3.7898259163,37.7601394653],"type":"Point"}
}