{
  "type": "Feature",
  "properties": {
    "addr:full":"Cabernet (pol Ind Pla Clota), 6 S. Miquel Olerdola Barcelona 08734",
    "addr:housenumber":"6",
    "addr:postcode":"08734",
    "addr:street":"Ind Pla Clota;S. Miquel Olerdola",
    "iso:country":"ES",
    "sg:address":"Cabernet (pol Ind Pla Clota), 6",
    "sg:city":"S. Miquel Olerdola",
    "sg:orig_category":"Confiter\u00cdas, Chocolater\u00cdas (al Por Menor)",
    "sg:phone":"+34 938 17 41 63",
    "sg:postcode":"08734",
    "sg:province":"Barcelona",
    "wof:name":"Dolcomat Llaminadures, S.l",
    "wof:placetype":"venue"
},
  "geometry": {"coordinates":[1.7646509409,41.3325309753],"type":"Point"}
}