{
  "type": "Feature",
  "properties": {
    "iso:country":"ES",
    "sg:address":"Calle de Mendialai, 10",
    "sg:city":"Donostia-san Sebastian",
    "sg:orig_category":"Empresarios",
    "sg:phone":"+34 943 21 77 97",
    "sg:postcode":"20009",
    "sg:province":"Guip\u00f9zcoa",
    "wof:name":"Arsuaga Araolaza Maria Angeles",
    "wof:placetype":"venue"
},
  "geometry": {"coordinates":[-1.9926770926,43.303894043],"type":"Point"}
}