{
  "type": "Feature",
  "properties": {
    "addr:full":"Poligono Ventilla, 35 Sotillo Adrada \u00c1vila 05420",
    "addr:housenumber":"35",
    "addr:postcode":"05420",
    "addr:street":"Poligono Ventilla",
    "iso:country":"ES",
    "sg:address":"Poligono Ventilla, 35",
    "sg:city":"Sotillo Adrada",
    "sg:orig_category":"Puertas Y Portales",
    "sg:phone":"+34 918 66 03 36",
    "sg:postcode":"05420",
    "sg:province":"\u00c1vila",
    "wof:name":"Puertas Ivan Moreno S.l.u.",
    "wof:placetype":"venue"
},
  "geometry": {"coordinates":[-4.5688381195,40.282245636],"type":"Point"}
}