{
  "type": "Feature",
  "properties": {
    "iso:country":"ES",
    "sg:address":"Calle de Sacerdote Angel Mu\u00d1oz, 21",
    "sg:city":"Almaden",
    "sg:orig_category":"Peluqueros: De Se\u00d1oras",
    "sg:phone":"+34 926 71 25 84",
    "sg:postcode":"13400",
    "sg:province":"Ciudad Real",
    "wof:name":"Palomo Sanchez Maria Jesus",
    "wof:placetype":"venue"
},
  "geometry": {"coordinates":[-4.831949234,38.7756614685],"type":"Point"}
}