{
  "type": "Feature",
  "properties": {
    "iso:country":"ES",
    "sg:address":"Calle de Amparo, 18",
    "sg:city":"Madrid",
    "sg:orig_category":"Bazares, Art\u00cdculos De Limpieza Y De Cocina (al Por Menor)",
    "sg:phone":"+34 915 30 18 98",
    "sg:postcode":"28012",
    "sg:province":"Madrid",
    "wof:name":"Modas Bagdad S.l.",
    "wof:placetype":"venue"
},
  "geometry": {"coordinates":[-3.7036550045,40.4103355408],"type":"Point"}
}