{
  "type": "Feature",
  "properties": {
    "addr:full":"Calle de Moscatelar, 15 Madrid Madrid 28043",
    "addr:housenumber":"15",
    "addr:postcode":"madrid;28043",
    "addr:street":"Calle De Moscatelar",
    "iso:country":"ES",
    "sg:address":"Calle de Moscatelar, 15",
    "sg:city":"Madrid",
    "sg:orig_category":"M\u00c9dicos: Fisioterapia Y Rehabilitaci\u00d3n",
    "sg:phone":"+34 917 59 87 79",
    "sg:postcode":"28043",
    "sg:province":"Madrid",
    "wof:name":"Fermoso De La Fuente Maria Anunciacion",
    "wof:placetype":"venue"
},
  "geometry": {"coordinates":[-3.6484599113,40.457244873],"type":"Point"}
}