{
  "type": "Feature",
  "properties": {
    "addr:full":"Calle de Julian Calderon Moreno, S/n Villanueva Serena Badajoz 06700",
    "addr:housenumber":"s",
    "addr:postcode":"06700",
    "addr:street":"Calle De Julian Calderon Moreno;/ N Villanueva Serena",
    "iso:country":"ES",
    "sg:address":"Calle de Julian Calderon Moreno, S/n",
    "sg:city":"Villanueva Serena",
    "sg:orig_category":"M\u00c1rmoles, Granitos Y Piedras Naturales",
    "sg:phone":"+34 924 84 54 02",
    "sg:postcode":"06700",
    "sg:province":"Badajoz",
    "wof:name":"Santos Perez Emilio",
    "wof:placetype":"venue"
},
  "geometry": {"coordinates":[-5.7911911011,38.9812011719],"type":"Point"}
}