{
  "type": "Feature",
  "properties": {
    "addr:full":"Calle de San Francisco, 5 Talavera Reina Toledo 45600",
    "addr:housenumber":"5",
    "addr:postcode":"45600",
    "addr:street":"Calle De San Francisco",
    "iso:country":"ES",
    "sg:address":"Calle de San Francisco, 5",
    "sg:city":"Talavera Reina",
    "sg:orig_category":"Asociaciones Y Clubs Deportivos",
    "sg:phone":"+34 925 80 71 48",
    "sg:postcode":"45600",
    "sg:province":"Toledo",
    "wof:name":"Goal Sport S.l.",
    "wof:placetype":"venue"
},
  "geometry": {"coordinates":[-4.8307781219,39.9605712891],"type":"Point"}
}