{
  "type": "Feature",
  "properties": {
    "addr:full":"Euskal-herria, 12 B Ibarra Guip\u00f9zcoa 20400",
    "addr:housenumber":"12 b",
    "addr:postcode":"20400",
    "addr:street":"Euskal-Herria;Guipu\u0300Zcoa",
    "iso:country":"ES",
    "sg:address":"Euskal-herria, 12 B",
    "sg:city":"Ibarra",
    "sg:orig_category":"Perfumer\u00cda (al Por Menor)",
    "sg:phone":"+34 943 67 41 93",
    "sg:postcode":"20400",
    "sg:province":"Guip\u00f9zcoa",
    "wof:name":"Perfumeria Y Estetica Miren Maite",
    "wof:placetype":"venue"
},
  "geometry": {"coordinates":[-2.0789339542,43.1339912415],"type":"Point"}
}