{
  "type": "Feature",
  "properties": {
    "iso:country":"ES",
    "sg:address":"Calle de Simon Hernandez (de), 68",
    "sg:city":"Mostoles",
    "sg:orig_category":"Agencias Y Agentes Comerciales, Representantes",
    "sg:phone":"+34 916 45 27 29",
    "sg:postcode":"28937",
    "sg:province":"Madrid",
    "wof:name":"Fernandez Morato Victor",
    "wof:placetype":"venue"
},
  "geometry": {"coordinates":[-3.8559710979,40.3197021484],"type":"Point"}
}