{
  "type": "Feature",
  "properties": {
    "addr:full":"Calle de Lujan Perez, 15 Palmas De Gran Canaria Las Palmas 35009",
    "addr:postcode":"35009",
    "addr:street":"Calle De Lujan Perez 15",
    "iso:country":"ES",
    "sg:address":"Calle de Lujan Perez, 15",
    "sg:city":"Palmas De Gran Canaria",
    "sg:orig_category":"Bazares, Art\u00cdculos De Limpieza Y De Cocina (al Por Menor)",
    "sg:phone":"+34 928 46 25 92",
    "sg:postcode":"35009",
    "sg:province":"Las Palmas",
    "wof:name":"Padron Rodriguez Jorge",
    "wof:placetype":"venue"
},
  "geometry": {"coordinates":[-15.4302186966,28.1520195007],"type":"Point"}
}