{
  "type": "Feature",
  "properties": {
    "addr:full":"Calle de Ramon Perez De Ayala, 44 Madrid Madrid 28038",
    "addr:housenumber":"44",
    "addr:postcode":"madrid;28038",
    "addr:street":"Calle De Ramon Perez De Ayala",
    "iso:country":"ES",
    "sg:address":"Calle de Ramon Perez De Ayala, 44",
    "sg:city":"Madrid",
    "sg:orig_category":"Comunidades Religiosas",
    "sg:phone":"+34 914 37 08 05",
    "sg:postcode":"28038",
    "sg:province":"Madrid",
    "wof:name":"Comunidad De Religiosas Adoratrices",
    "wof:placetype":"venue"
},
  "geometry": {"coordinates":[-3.6540288925,40.3993263245],"type":"Point"}
}