{
  "type": "Feature",
  "properties": {
    "iso:country":"ES",
    "sg:address":"Calle de Posada, 4",
    "sg:city":"Zahinos",
    "sg:orig_category":"Copas, Insignias, Trofeos",
    "sg:phone":"+34 924 73 82 11",
    "sg:postcode":"06129",
    "sg:province":"Badajoz",
    "wof:name":"Carbonell Martinez Maria Elena",
    "wof:placetype":"venue"
},
  "geometry": {"coordinates":[-6.9535508156,38.3281822205],"type":"Point"}
}