{
  "type": "Feature",
  "properties": {
    "iso:country":"ES",
    "sg:address":"Ctra. Parla, S/n",
    "sg:city":"Pinto",
    "sg:orig_category":"Delegados, Agentes De Tr\u00c1nsito, Auxiliares De Transporte Internacional",
    "sg:phone":"+34 916 92 89 80",
    "sg:postcode":"28320",
    "sg:province":"Madrid",
    "sg:website":"www.gafu.com",
    "wof:name":"Transportes Garcia De La Fuente S.a.",
    "wof:placetype":"venue"
},
  "geometry": {"coordinates":[-3.7129349709,40.2453384399],"type":"Point"}
}