{
  "type": "Feature",
  "properties": {
    "iso:country":"ES",
    "sg:address":"Carrer de Madrid, 27",
    "sg:city":"Mollet Valles",
    "sg:orig_category":"Postigos, Persianas Y Celos\u00cdas",
    "sg:phone":"+34 935 93 13 91",
    "sg:postcode":"08100",
    "sg:province":"Barcelona",
    "wof:name":"Abad Colas Antonio",
    "wof:placetype":"venue"
},
  "geometry": {"coordinates":[2.217284,41.53933],"type":"Point"}
}