{
  "type": "Feature",
  "properties": {
    "addr:full":"Avda Doctor Federico Rubio Y Gali, 10 Madrid Madrid 28039",
    "addr:housenumber":"10",
    "addr:postcode":"madrid;28039",
    "addr:street":"Avda Doctor Federico Rubio Y Gali",
    "iso:country":"ES",
    "sg:address":"Avda Doctor Federico Rubio Y Gali, 10",
    "sg:city":"Madrid",
    "sg:orig_category":"Bares, Piano",
    "sg:phone":"+34 915 33 16 03",
    "sg:postcode":"28039",
    "sg:province":"Madrid",
    "wof:name":"Herber Internet S.l.",
    "wof:placetype":"venue"
},
  "geometry": {"coordinates":[-3.7082660198,40.4486694336],"type":"Point"}
}