{
  "type": "Feature",
  "properties": {
    "iso:country":"ES",
    "sg:address":"Calle de Andalucia, 16",
    "sg:city":"Martos",
    "sg:orig_category":"Mec\u00c1nico Del Autom\u00d3vil",
    "sg:phone":"+34 953 55 14 33",
    "sg:postcode":"23600",
    "sg:province":"Ja\u00e9n",
    "wof:name":"Metacor J C Lopez Acebron Y Dos Mas C.b.",
    "wof:placetype":"venue"
},
  "geometry": {"coordinates":[-3.9737923145,37.7207221985],"type":"Point"}
}