{
  "type": "Feature",
  "properties": {
    "iso:country":"ES",
    "sg:address":"Calle de Caceres, 48",
    "sg:city":"Madrid",
    "sg:orig_category":"Mercer\u00cda, Lencer\u00cda (al Por Menor)",
    "sg:phone":"+34 914 73 92 33",
    "sg:postcode":"28045",
    "sg:province":"Madrid",
    "wof:name":"Manzanero Lucas Jose",
    "wof:placetype":"venue"
},
  "geometry": {"coordinates":[-3.699701786,40.3989486694],"type":"Point"}
}