{
  "type": "Feature",
  "properties": {
    "iso:country":"ES",
    "sg:address":"Calle de Portal, 13",
    "sg:city":"Lerin",
    "sg:orig_category":"Fabricaci\u00d3n De Pastas Alimentarias",
    "sg:phone":"+34 948 53 01 05",
    "sg:postcode":"31260",
    "sg:province":"Navarra",
    "wof:name":"Pastas Caseras Marisol S.l.",
    "wof:placetype":"venue"
},
  "geometry": {"coordinates":[-1.9768340588,42.4849815369],"type":"Point"}
}