{
  "type": "Feature",
  "properties": {
    "iso:country":"ES",
    "sg:address":"Calle de Clavel (del), 37",
    "sg:city":"Linea De La Concepcion",
    "sg:classifiers":[
        {
            "category":"Personal",
            "subcategory":"Barber",
            "type":"Services"
        }
    ],
    "sg:phone":"+34 956 17 54 40",
    "sg:postcode":"11300",
    "sg:province":"C\u00e1diz",
    "sg:tags":[
        "caballeros",
        "de",
        "peluqueros"
    ],
    "wof:name":"Lopez Marchena Matias",
    "wof:placetype":"venue"
},
  "geometry": {"coordinates":[-5.3477802277,36.1643028259],"type":"Point"}
}