{
  "type": "Feature",
  "properties": {
    "addr:full":"Carrer de Duquessa De La Victoria, 32 Terrassa Barcelona 08223",
    "addr:housenumber":"32",
    "addr:postcode":"08223",
    "addr:street":"Carrer De Duquessa De La Victoria",
    "iso:country":"ES",
    "sg:address":"Carrer de Duquessa De La Victoria, 32",
    "sg:city":"Terrassa",
    "sg:orig_category":"Mec\u00c1nico Del Autom\u00d3vil",
    "sg:phone":"+34 937 31 37 18",
    "sg:postcode":"08223",
    "sg:province":"Barcelona",
    "wof:name":"Camargo Seret Juan",
    "wof:placetype":"venue"
},
  "geometry": {"coordinates":[2.0219099522,41.5547790527],"type":"Point"}
}