{
  "type": "Feature",
  "properties": {
    "iso:country":"ES",
    "sg:address":"Calle de Ricardo Gil, 42",
    "sg:city":"Carmen",
    "sg:orig_category":"Agencias Y Asesores De Publicidad",
    "sg:phone":"+34 968 22 71 38",
    "sg:postcode":"30002",
    "sg:province":"Murcia",
    "wof:name":"Anvi Publicidad S.l.",
    "wof:placetype":"venue"
},
  "geometry": {"coordinates":[-1.127076149,37.9808120728],"type":"Point"}
}