{
  "type": "Feature",
  "properties": {
    "iso:country":"ES",
    "sg:address":"Calle de Padura Batalla De, 1",
    "sg:city":"Bilbao",
    "sg:orig_category":"Electrodom\u00c9sticos (al Por Menor)",
    "sg:phone":"+34 944 21 75 01",
    "sg:postcode":"48012",
    "sg:province":"Vizcaya",
    "wof:name":"Suministros Ari\u00f1o S. A.",
    "wof:placetype":"venue"
},
  "geometry": {"coordinates":[-2.9413208961,43.2543334961],"type":"Point"}
}