{
  "type": "Feature",
  "properties": {
    "addr:full":"Avda Malaga, 4 Sevilla Sevilla 41004",
    "addr:housenumber":"4",
    "addr:postcode":"41004",
    "addr:street":"Avda Malaga",
    "iso:country":"ES",
    "sg:address":"Avda Malaga, 4",
    "sg:city":"Sevilla",
    "sg:orig_category":"Bancos",
    "sg:phone":"+34 954 98 88 00",
    "sg:postcode":"41004",
    "sg:province":"Sevilla",
    "wof:name":"Banco Espa\u00f1ol De Credito S.a.",
    "wof:placetype":"venue"
},
  "geometry": {"coordinates":[-5.987183094,37.3823547363],"type":"Point"}
}