{
  "type": "Feature",
  "properties": {
    "iso:country":"ES",
    "sg:address":"Pl. Mayor, 7",
    "sg:city":"Espinosa De Cervera",
    "sg:orig_category":"Distribuci\u00d3n De Petr\u00d3leo Y Derivados",
    "sg:phone":"+34 947 53 40 65",
    "sg:postcode":"09610",
    "sg:province":"Burgos",
    "wof:name":"Alamo Manso Jesus Maria Del",
    "wof:placetype":"venue"
},
  "geometry": {"coordinates":[-3.468392849,41.8963241577],"type":"Point"}
}