{
  "type": "Feature",
  "properties": {
    "addr:full":"P Del Parque, 23 Simancas Valladolid 47130",
    "addr:housenumber":"23",
    "addr:postcode":"47130",
    "addr:street":"P Del Parque",
    "iso:country":"ES",
    "sg:address":"P Del Parque, 23",
    "sg:city":"Simancas",
    "sg:orig_category":"Centros Empresariales",
    "sg:phone":"+34 983 59 19 69",
    "sg:postcode":"47130",
    "sg:province":"Valladolid",
    "wof:name":"Palacios Aparicio Carlos Antonio",
    "wof:placetype":"venue"
},
  "geometry": {"coordinates":[-4.8235812187,41.5907974243],"type":"Point"}
}