{
  "type": "Feature",
  "properties": {
    "iso:country":"ES",
    "sg:address":"Ctra Rubi, Km. 0025,2",
    "sg:city":"Terrassa",
    "sg:orig_category":"Cogeneraci\u00d3n: Equipo Y Servicios",
    "sg:phone":"+34 937 83 82 77",
    "sg:postcode":"08228",
    "sg:province":"Barcelona",
    "wof:name":"Covislan S.l.",
    "wof:placetype":"venue"
},
  "geometry": {"coordinates":[2.0362648964,41.5310096741],"type":"Point"}
}