{
  "type": "Feature",
  "properties": {
    "iso:country":"ES",
    "sg:address":"Carr Cuba, 1",
    "sg:city":"Aldaia",
    "sg:orig_category":"Promotores Constructores",
    "sg:phone":"+34 961 50 15 10",
    "sg:postcode":"46960",
    "sg:province":"Valencia",
    "wof:name":"Midascon S.l.",
    "wof:placetype":"venue"
},
  "geometry": {"coordinates":[-0.460878998,39.4649238586],"type":"Point"}
}