{
  "type": "Feature",
  "properties": {
    "addr:full":"Avda Mancha (de La), 31 Leganes Madrid 28911",
    "addr:housenumber":"31",
    "addr:postcode":"28911",
    "addr:street":"Avda Mancha De La",
    "iso:country":"ES",
    "sg:address":"Avda Mancha (de La), 31",
    "sg:city":"Leganes",
    "sg:orig_category":"Molduras, Junquillos, Listones Y Molduras Perforadas",
    "sg:phone":"+34 916 86 55 18",
    "sg:postcode":"28911",
    "sg:province":"Madrid",
    "wof:name":"Martin Torijas Lorenza",
    "wof:placetype":"venue"
},
  "geometry": {"coordinates":[-3.759141922,40.3328552246],"type":"Point"}
}