{
  "type": "Feature",
  "properties": {
    "iso:country":"ES",
    "sg:address":"Avda Marin, 11",
    "sg:city":"Estrada",
    "sg:orig_category":"Comercio De Piezas De Recambio Y De Accesorios De Veh\u00cdculos, Veh\u00cdculos Industriales",
    "sg:phone":"+34 986 57 14 70",
    "sg:postcode":"36680",
    "sg:province":"Pontevedra",
    "wof:name":"Recambios Europa C.b.",
    "wof:placetype":"venue"
},
  "geometry": {"coordinates":[-8.4976043701,42.6854667664],"type":"Point"}
}