{
  "type": "Feature",
  "properties": {
    "addr:full":"Carr Estanys, 37 Colonia S. Jordi Islas Baleares 07638",
    "addr:housenumber":"37",
    "addr:postcode":"07638",
    "addr:street":"Carr Estanys;Colonia S. Jordi",
    "iso:country":"ES",
    "sg:address":"Carr Estanys, 37",
    "sg:city":"Colonia S. Jordi",
    "sg:orig_category":"Alquiler De V\u00cddeo",
    "sg:phone":"+34 971 65 52 18",
    "sg:postcode":"07638",
    "sg:province":"Islas Baleares",
    "wof:name":"Adrover Amengual Mateu Albert",
    "wof:placetype":"venue"
},
  "geometry": {"coordinates":[2.9938578606,39.3168563843],"type":"Point"}
}