{
  "type": "Feature",
  "properties": {
    "iso:country":"ES",
    "sg:address":"Pl Llibertat, 23",
    "sg:city":"Barcelona",
    "sg:orig_category":"Molduras, Junquillos, Listones Y Molduras Perforadas",
    "sg:phone":"+34 932 18 29 94",
    "sg:postcode":"08012",
    "sg:province":"Barcelona",
    "wof:name":"Roura Marques Joaquina",
    "wof:placetype":"venue"
},
  "geometry": {"coordinates":[2.1535758972,41.3999404907],"type":"Point"}
}