{
  "type": "Feature",
  "properties": {
    "iso:country":"ES",
    "sg:address":"Calle de Hermanos Parra, 3",
    "sg:city":"Callosa Segura",
    "sg:orig_category":"Agentes Generales De Seguros",
    "sg:phone":"+34 966 75 61 40",
    "sg:postcode":"03360",
    "sg:province":"Alicante",
    "wof:name":"Sarmiento Rodriguez Jose",
    "wof:placetype":"venue"
},
  "geometry": {"coordinates":[-0.8764089942,38.1245193481],"type":"Point"}
}