{
  "type": "Feature",
  "properties": {
    "iso:country":"ES",
    "sg:address":"Avda Camilo Alonso Vega, 28",
    "sg:city":"Santander",
    "sg:orig_category":"Zapatos (al Por Menor)",
    "sg:phone":"+34 942 23 45 88",
    "sg:postcode":"39007",
    "sg:province":"Cantabria",
    "wof:name":"Calzados El Condor S.c.",
    "wof:placetype":"venue"
},
  "geometry": {"coordinates":[-3.824919939,43.4613380432],"type":"Point"}
}