{
  "type": "Feature",
  "properties": {
    "iso:country":"ES",
    "sg:address":"Calle de Campo (del), 25",
    "sg:city":"Almansa",
    "sg:orig_category":"Peluqueros: De Se\u00d1oras",
    "sg:phone":"+34 967 34 02 36",
    "sg:postcode":"02640",
    "sg:province":"Albacete",
    "wof:name":"Cuenca Calero Maria Belen",
    "wof:placetype":"venue"
},
  "geometry": {"coordinates":[-1.0974518061,38.8701400757],"type":"Point"}
}