{
  "type": "Feature",
  "properties": {
    "iso:country":"ES",
    "sg:address":"Avgd Alacant, 19",
    "sg:city":"Lleida",
    "sg:orig_category":"Chapister\u00cda",
    "sg:phone":"+34 973 21 17 30",
    "sg:postcode":"25001",
    "sg:province":"Lleida",
    "wof:name":"Jaimejuan Paniello Jose Maria",
    "wof:placetype":"venue"
},
  "geometry": {"coordinates":[0.6334720254,41.6132164001],"type":"Point"}
}