{
  "type": "Feature",
  "properties": {
    "addr:full":"Avda Andalucia, 169 Dos Hermanas Sevilla 41700",
    "addr:housenumber":"169",
    "addr:postcode":"41700",
    "addr:street":"Avda Andalucia;Sevilla",
    "iso:country":"ES",
    "sg:address":"Avda Andalucia, 169",
    "sg:city":"Dos Hermanas",
    "sg:orig_category":"Cervecer\u00cdas",
    "sg:phone":"+34 955 66 77 53",
    "sg:postcode":"41700",
    "sg:province":"Sevilla",
    "wof:name":"Nieves Rivero Rafael",
    "wof:placetype":"venue"
},
  "geometry": {"coordinates":[-5.9202427864,37.2762145996],"type":"Point"}
}