{
  "type": "Feature",
  "properties": {
    "addr:full":"Calle de Quintin Esquembre, S/n Villena Alicante 03400",
    "addr:housenumber":"s",
    "addr:postcode":"03400",
    "addr:street":"Calle De Quintin Esquembre;/ N",
    "iso:country":"ES",
    "sg:address":"Calle de Quintin Esquembre, S/n",
    "sg:city":"Villena",
    "sg:orig_category":"M\u00c1rmoles, Granitos Y Piedras Naturales",
    "sg:phone":"+34 965 80 87 85",
    "sg:postcode":"03400",
    "sg:province":"Alicante",
    "wof:name":"Marmolijan S.l",
    "wof:placetype":"venue"
},
  "geometry": {"coordinates":[-0.8679689765,38.6414299011],"type":"Point"}
}