{
  "type": "Feature",
  "properties": {
    "addr:full":"La Gomera, 17 Las Galletas Santa Cruz De Tenerife 38631",
    "addr:housenumber":"17",
    "addr:postcode":"38631",
    "addr:street":"Gomera",
    "iso:country":"ES",
    "sg:address":"La Gomera, 17",
    "sg:city":"Las Galletas",
    "sg:orig_category":"Peluquer\u00cdas, Peluquer\u00cda Mixta",
    "sg:phone":"+34 922 73 28 21",
    "sg:postcode":"38631",
    "sg:province":"Santa Cruz De Tenerife",
    "wof:name":"Casanova Rodriguez Aliri",
    "wof:placetype":"venue"
},
  "geometry": {"coordinates":[-16.670463562,28.0141906738],"type":"Point"}
}