{
  "type": "Feature",
  "properties": {
    "iso:country":"ES",
    "sg:address":"Carr Nou, 10",
    "sg:city":"Figueres",
    "sg:orig_category":"Art\u00cdculos De Regalo (al Por Menor)",
    "sg:phone":"+34 972 50 54 23",
    "sg:postcode":"17600",
    "sg:province":"Girona",
    "wof:name":"Amiel Salleras Catalina",
    "wof:placetype":"venue"
},
  "geometry": {"coordinates":[2.9625954628,42.2661209106],"type":"Point"}
}