{
  "type": "Feature",
  "properties": {
    "iso:country":"ES",
    "sg:address":"Calle de Jose Maria Soroa, 20",
    "sg:city":"Donostia-san Sebastian",
    "sg:orig_category":"Asociaciones Y Clubs Deportivos",
    "sg:phone":"+34 943 27 81 96",
    "sg:postcode":"20013",
    "sg:province":"Guip\u00f9zcoa",
    "sg:website":"www.urruti.com",
    "wof:name":"Urrutikoetxea Arnaiz I\u00f1igo",
    "wof:placetype":"venue"
},
  "geometry": {"coordinates":[-1.9688420296,43.3231124878],"type":"Point"}
}