{
  "type": "Feature",
  "properties": {
    "iso:country":"ES",
    "sg:address":"Calle de Castello, 88",
    "sg:city":"Madrid",
    "sg:orig_category":"Ropa Para Beb\u00c9s Y Ni\u00d1os (confecci\u00d3n, Al Por Mayor)",
    "sg:phone":"+34 914 11 28 73",
    "sg:postcode":"28006",
    "sg:province":"Madrid",
    "wof:name":"Iber-ada 2000 S.l.",
    "wof:placetype":"venue"
},
  "geometry": {"coordinates":[-3.6808006763,40.4336357117],"type":"Point"}
}