{
  "type": "Feature",
  "properties": {
    "addr:full":"Avda Cadiz (de), 8 Granada Granada 18006",
    "addr:housenumber":"8",
    "addr:postcode":"18006",
    "addr:street":"Avda Cadiz De",
    "iso:country":"ES",
    "sg:address":"Avda Cadiz (de), 8",
    "sg:city":"Granada",
    "sg:orig_category":"Abogados",
    "sg:phone":"+34 958 81 15 68",
    "sg:postcode":"18006",
    "sg:province":"Granada",
    "wof:name":"Iniesta Perez Carmen",
    "wof:placetype":"venue"
},
  "geometry": {"coordinates":[-3.6005349159,37.1598968506],"type":"Point"}
}