{
  "type": "Feature",
  "properties": {
    "addr:full":"Carrer de Muntaner, 374 Barcelona Barcelona 08006",
    "addr:housenumber":"374",
    "addr:postcode":"08006",
    "addr:street":"Carrer De Muntaner",
    "iso:country":"ES",
    "sg:address":"Carrer de Muntaner, 374",
    "sg:city":"Barcelona",
    "sg:orig_category":"Aceros Inoxidables",
    "sg:phone":"+34 932 09 41 77",
    "sg:postcode":"08006",
    "sg:province":"Barcelona",
    "wof:name":"Ak Steel Merchandising S. A.",
    "wof:placetype":"venue"
},
  "geometry": {"coordinates":[2.1426520348,41.399307251],"type":"Point"}
}