{
  "type": "Feature",
  "properties": {
    "addr:full":"Cmno Magdalena, S/n Logro\u00f1o La Rioja 26006",
    "addr:housenumber":"s",
    "addr:postcode":"26006",
    "addr:street":"Cmno Magdalena;/ N Logron\u0303O;Rioja",
    "iso:country":"ES",
    "sg:address":"Cmno Magdalena, S/n",
    "sg:city":"Logro\u00f1o",
    "sg:orig_category":"Cr\u00cda De Animales",
    "sg:phone":"+34 941 25 10 87",
    "sg:postcode":"26006",
    "sg:province":"La Rioja",
    "wof:name":"Rivas Moreno Angel",
    "wof:placetype":"venue"
},
  "geometry": {"coordinates":[-2.4319930077,42.4397354126],"type":"Point"}
}