{
  "type": "Feature",
  "properties": {
    "addr:full":"Calle de Horno (del), 5 Mi\u00f1osa Guadalajara 19278",
    "addr:housenumber":"5",
    "addr:postcode":"19278",
    "addr:street":"Calle De Horno Del",
    "iso:country":"ES",
    "sg:address":"Calle de Horno (del), 5",
    "sg:city":"Mi\u00f1osa",
    "sg:orig_category":"Ense\u00d1anza Agr\u00cdcola",
    "sg:phone":"+34 949 39 92 98",
    "sg:postcode":"19278",
    "sg:province":"Guadalajara",
    "wof:name":"Las Lagartijas S.l.",
    "wof:placetype":"venue"
},
  "geometry": {"coordinates":[-2.9320549965,41.1788825989],"type":"Point"}
}