{
  "type": "Feature",
  "properties": {
    "addr:full":"Calle de Gravina, 1 Alcala Guadaira Sevilla 41500",
    "addr:housenumber":"1",
    "addr:postcode":"41500",
    "addr:street":"Calle De Gravina",
    "iso:country":"ES",
    "sg:address":"Calle de Gravina, 1",
    "sg:city":"Alcala Guadaira",
    "sg:orig_category":"Juegos Y Juguetes (al Por Menor)",
    "sg:phone":"+34 955 61 06 44",
    "sg:postcode":"41500",
    "sg:province":"Sevilla",
    "wof:name":"Bowling Alcala S.l.",
    "wof:placetype":"venue"
},
  "geometry": {"coordinates":[-5.835627079,37.3385810852],"type":"Point"}
}