{
  "type": "Feature",
  "properties": {
    "iso:country":"ES",
    "sg:address":"Pol. Ind. Mijares, S/n",
    "sg:city":"Almassora",
    "sg:orig_category":"Laboratorios Farmac\u00c9uticos",
    "sg:phone":"+34 964 56 12 04",
    "sg:postcode":"12550",
    "sg:province":"Castell\u00f3n",
    "wof:name":"Federacio Farmaceutica S.coop.",
    "wof:placetype":"venue"
},
  "geometry": {"coordinates":[-0.0631700009,39.9439582825],"type":"Point"}
}