{
  "type": "Feature",
  "properties": {
    "iso:country":"ES",
    "sg:address":"Calle de Jaime Ni\u00d1oles, 7",
    "sg:city":"Alacant",
    "sg:orig_category":"Electromec\u00c1nica",
    "sg:phone":"+34 965 28 59 33",
    "sg:postcode":"03006",
    "sg:province":"Alicante",
    "wof:name":"Quereda Baeza Ramon Jose",
    "wof:placetype":"venue"
},
  "geometry": {"coordinates":[-0.512477994,38.3459281921],"type":"Point"}
}