{
  "type": "Feature",
  "properties": {
    "iso:country":"ES",
    "sg:address":"Calle de San Onofre (de), 5",
    "sg:city":"San Sebastian De Los Reyes",
    "sg:orig_category":"Panader\u00cdas, Panader\u00cdas",
    "sg:phone":"+34 916 51 36 38",
    "sg:postcode":"28700",
    "sg:province":"Madrid",
    "wof:name":"Montes Diaz Francisco",
    "wof:placetype":"venue"
},
  "geometry": {"coordinates":[-3.6282315254,40.5499572754],"type":"Point"}
}