{
  "type": "Feature",
  "properties": {
    "addr:full":"Rua Vicente Risco, 3 Vilagarcia Pontevedra 36600",
    "addr:housenumber":"3",
    "addr:postcode":"36600",
    "addr:street":"Rua Vicente Risco",
    "iso:country":"ES",
    "sg:address":"Rua Vicente Risco, 3",
    "sg:city":"Vilagarcia",
    "sg:orig_category":"Contenedores (mercanc\u00cdas)",
    "sg:phone":"+34 986 50 01 52",
    "sg:postcode":"36600",
    "sg:province":"Pontevedra",
    "wof:name":"Ofixon Noval S.l",
    "wof:placetype":"venue"
},
  "geometry": {"coordinates":[-8.7661008835,42.5933036804],"type":"Point"}
}