{
  "type": "Feature",
  "properties": {
    "iso:country":"ES",
    "sg:address":"Rua Compostela, 29",
    "sg:city":"Ordes",
    "sg:orig_category":"Electricidad, Electr\u00d3nica: Suministros (al Por Menor)",
    "sg:phone":"+34 981 68 09 52",
    "sg:postcode":"15680",
    "sg:province":"La Coru\u00f1a",
    "wof:name":"Gonzalez Santos Roberto Jesus",
    "wof:placetype":"venue"
},
  "geometry": {"coordinates":[-8.4090108871,43.0780105591],"type":"Point"}
}