{
  "type": "Feature",
  "properties": {
    "addr:full":"Calle de Elorri, 5 Algorta Vizcaya 48991",
    "addr:housenumber":"5",
    "addr:postcode":"48991",
    "addr:street":"Calle De Elorri",
    "iso:country":"ES",
    "sg:address":"Calle de Elorri, 5",
    "sg:city":"Algorta",
    "sg:orig_category":"Fotograf\u00cda Y Cine: Aparatos, Pel\u00cdculas Y Accesorios (al Por Menor)",
    "sg:phone":"+34 944 30 45 00",
    "sg:postcode":"48991",
    "sg:province":"Vizcaya",
    "wof:name":"Saiz Moreno Concepcion",
    "wof:placetype":"venue"
},
  "geometry": {"coordinates":[-3.0083959103,43.3544311523],"type":"Point"}
}