{
  "type": "Feature",
  "properties": {
    "iso:country":"ES",
    "sg:address":"Carrer de Sant Pau, 51",
    "sg:city":"Barcelona",
    "sg:orig_category":"Empresas De Portes Y Mensajer\u00cda",
    "sg:phone":"+34 934 43 43 47",
    "sg:postcode":"08001",
    "sg:province":"Barcelona",
    "wof:name":"Harjee Spain S.l.",
    "wof:placetype":"venue"
},
  "geometry": {"coordinates":[2.1717689037,41.3786392212],"type":"Point"}
}