{
  "type": "Feature",
  "properties": {
    "iso:country":"ES",
    "sg:address":"Carrer de Ensija, Km. 0001,0",
    "sg:city":"S. Fruitos Bages",
    "sg:orig_category":"Fabricaci\u00d3n De Etiquetas",
    "sg:phone":"+34 938 77 10 01",
    "sg:postcode":"08272",
    "sg:province":"Barcelona",
    "wof:name":"Grupo Salvador Figueras S. L.",
    "wof:placetype":"venue"
},
  "geometry": {"coordinates":[1.8779350519,41.7520599365],"type":"Point"}
}