{
  "type": "Feature",
  "properties": {
    "addr:full":"Pg Sant Joan, 10 Barcelona Barcelona 08010",
    "addr:housenumber":"10",
    "addr:postcode":"08010",
    "addr:street":"Pg Sant Joan",
    "iso:country":"ES",
    "sg:address":"Pg Sant Joan, 10",
    "sg:city":"Barcelona",
    "sg:orig_category":"Fotograf\u00cda Art\u00cdstica Y Retratos",
    "sg:phone":"+34 932 46 43 90",
    "sg:postcode":"08010",
    "sg:province":"Barcelona",
    "wof:name":"Ros Ribas Jose",
    "wof:placetype":"venue"
},
  "geometry": {"coordinates":[2.1795940399,41.3920288086],"type":"Point"}
}