{
  "type": "Feature",
  "properties": {
    "addr:full":"Calle de Galeon, 27 Madrid Madrid 28042",
    "addr:housenumber":"27",
    "addr:postcode":"madrid;28042",
    "addr:street":"Calle De Galeon",
    "iso:country":"ES",
    "sg:address":"Calle de Galeon, 27",
    "sg:city":"Madrid",
    "sg:orig_category":"Molduras, Junquillos, Listones Y Molduras Perforadas",
    "sg:phone":"+34 913 29 45 65",
    "sg:postcode":"28042",
    "sg:province":"Madrid",
    "wof:name":"Ramirez Valenzuela Jose",
    "wof:placetype":"venue"
},
  "geometry": {"coordinates":[-3.582041502,40.4588279724],"type":"Point"}
}