{
  "type": "Feature",
  "properties": {
    "iso:country":"ES",
    "sg:address":"Calle de Mayor, 1",
    "sg:city":"Cangas Narcea",
    "sg:orig_category":"Bazares, Art\u00cdculos De Limpieza Y De Cocina (al Por Menor)",
    "sg:phone":"+34 985 81 02 22",
    "sg:postcode":"33800",
    "sg:province":"Asturias",
    "wof:name":"Morodo Morodo Dionisio",
    "wof:placetype":"venue"
},
  "geometry": {"coordinates":[-6.5492749214,43.1760559082],"type":"Point"}
}