{
  "type": "Feature",
  "properties": {
    "addr:full":"Calle de Abajo, 10 Fuente S. Esteban Salamanca 37200",
    "addr:housenumber":"10",
    "addr:postcode":"37200",
    "addr:street":"Calle De Abajo;Fuente S. Esteban",
    "iso:country":"ES",
    "sg:address":"Calle de Abajo, 10",
    "sg:city":"Fuente S. Esteban",
    "sg:orig_category":"Inform\u00c1tica (estudios, Servicios, Asesor\u00cda, Formaci\u00d3n)",
    "sg:phone":"+34 923 45 84 03",
    "sg:postcode":"37200",
    "sg:province":"Salamanca",
    "wof:name":"Mapfre Servicios De Informatica",
    "wof:placetype":"venue"
},
  "geometry": {"coordinates":[-6.2565155029,40.8015518188],"type":"Point"}
}