{
  "type": "Feature",
  "properties": {
    "addr:full":"Calle de Portugal, 11 Pozoblanco C\u00f3rdoba 14400",
    "addr:housenumber":"11",
    "addr:postcode":"14400",
    "addr:street":"Calle De Portugal",
    "iso:country":"ES",
    "sg:address":"Calle de Portugal, 11",
    "sg:city":"Pozoblanco",
    "sg:orig_category":"Asociaciones Humanitarias, De Cooperaci\u00d3n, De Acci\u00d3n Social",
    "sg:phone":"+34 957 13 06 68",
    "sg:postcode":"14400",
    "sg:province":"C\u00f3rdoba",
    "wof:name":"Asociacion Pozoalbense De Alcoholicos Liberados",
    "wof:placetype":"venue"
},
  "geometry": {"coordinates":[-4.8555455208,38.3758354187],"type":"Point"}
}