{
  "type": "Feature",
  "properties": {
    "addr:full":"Calle de Ramiro Ledesma, 10 Socuellamos Ciudad Real 13630",
    "addr:housenumber":"10",
    "addr:postcode":"13630",
    "addr:street":"Calle De Ramiro Ledesma",
    "iso:country":"ES",
    "sg:address":"Calle de Ramiro Ledesma, 10",
    "sg:city":"Socuellamos",
    "sg:orig_category":"Centros Empresariales",
    "sg:phone":"+34 926 53 13 45",
    "sg:postcode":"13630",
    "sg:province":"Ciudad Real",
    "wof:name":"Confederacion Provincial De Empresarios De Ciudad Real",
    "wof:placetype":"venue"
},
  "geometry": {"coordinates":[-2.7957890034,39.2847518921],"type":"Point"}
}