{
  "type": "Feature",
  "properties": {
    "addr:full":"Calle de Esta\u00d1o, 130 Valladolid Valladolid 47012",
    "addr:housenumber":"130",
    "addr:postcode":"47012",
    "addr:street":"Calle De Estan\u0303O",
    "iso:country":"ES",
    "sg:address":"Calle de Esta\u00d1o, 130",
    "sg:city":"Valladolid",
    "sg:orig_category":"Electromec\u00c1nica",
    "sg:phone":"+34 983 29 40 48",
    "sg:postcode":"47012",
    "sg:province":"Valladolid",
    "wof:name":"Vega Blanco Felicisimo",
    "wof:placetype":"venue"
},
  "geometry": {"coordinates":[-4.7073588371,41.6183815002],"type":"Point"}
}