{
  "type": "Feature",
  "properties": {
    "addr:full":"Pase Invierno, 5 Tudela Navarra 31500",
    "addr:housenumber":"5",
    "addr:postcode":"31500",
    "addr:street":"Invierno",
    "iso:country":"ES",
    "sg:address":"Pase Invierno, 5",
    "sg:city":"Tudela",
    "sg:orig_category":"M\u00c9dicos: Estomatolog\u00cda",
    "sg:phone":"+34 948 82 12 25",
    "sg:postcode":"31500",
    "sg:province":"Navarra",
    "wof:name":"Dean Rubio Joaquin",
    "wof:placetype":"venue"
},
  "geometry": {"coordinates":[-1.6015850306,42.0612487793],"type":"Point"}
}