{
  "type": "Feature",
  "properties": {
    "iso:country":"ES",
    "sg:address":"Estda. De Arcos, 6",
    "sg:city":"Corgomo",
    "sg:orig_category":"Productores Recolectores, Venta Directa De Vinos",
    "sg:phone":"+34 988 32 45 33",
    "sg:postcode":"32316",
    "sg:province":"Ourense",
    "wof:name":"Bodega Avelina Sat",
    "wof:placetype":"venue"
},
  "geometry": {"coordinates":[-7.0000519753,42.421749115],"type":"Point"}
}