{
  "type": "Feature",
  "properties": {
    "addr:full":"Carrer de Mare De Deu Del Carmel, 14 Barcelona Barcelona 08022",
    "addr:housenumber":"14",
    "addr:postcode":"08022",
    "addr:street":"Carrer De Mare De Deu Del Carmel",
    "iso:country":"ES",
    "sg:address":"Carrer de Mare De Deu Del Carmel, 14",
    "sg:city":"Barcelona",
    "sg:orig_category":"Pescader\u00cdas (al Por Menor)",
    "sg:phone":"+34 934 18 36 78",
    "sg:postcode":"08022",
    "sg:province":"Barcelona",
    "wof:name":"Oliva Vidal Maria De Los Angeles",
    "wof:placetype":"venue"
},
  "geometry": {"coordinates":[2.1400139332,41.4112167358],"type":"Point"}
}