{
  "type": "Feature",
  "properties": {
    "iso:country":"ES",
    "sg:address":"Tv. Bayona, 2",
    "sg:city":"Iru\u00f1a",
    "sg:orig_category":"Bancos",
    "sg:phone":"+34 948 26 01 62",
    "sg:postcode":"31011",
    "sg:province":"Navarra",
    "sg:website":"www.bancovasconia.es",
    "wof:name":"Banco De Vasconia",
    "wof:placetype":"venue"
},
  "geometry": {"coordinates":[-1.6555149555,42.8152084351],"type":"Point"}
}