{
  "type": "Feature",
  "properties": {
    "iso:country":"ES",
    "sg:address":"Calle de Cuellar, 1",
    "sg:city":"Almendralejo",
    "sg:orig_category":"Empresas De Limpieza",
    "sg:phone":"+34 924 66 73 80",
    "sg:postcode":"06200",
    "sg:province":"Badajoz",
    "wof:name":"Sociedad Cooperativa Limitada Minusbarro",
    "wof:placetype":"venue"
},
  "geometry": {"coordinates":[-6.4150891304,38.6827583313],"type":"Point"}
}