{
  "type": "Feature",
  "properties": {
    "iso:country":"ES",
    "sg:address":"Carrer de Carabassa, 4",
    "sg:city":"Barcelona",
    "sg:orig_category":"Bazares, Art\u00cdculos De Limpieza Y De Cocina (al Por Menor)",
    "sg:phone":"+34 933 02 05 33",
    "sg:postcode":"08002",
    "sg:province":"Barcelona",
    "wof:name":"Vilar Gomez Segundo",
    "wof:placetype":"venue"
},
  "geometry": {"coordinates":[2.1779620647,41.3802642822],"type":"Point"}
}