{
  "type": "Feature",
  "properties": {
    "iso:country":"ES",
    "sg:address":"Pase Darsena, 14",
    "sg:city":"Coru\u00d1a",
    "sg:orig_category":"Comidas Por Encargo, Organizaci\u00d3n De Recepciones",
    "sg:phone":"+34 981 20 56 95",
    "sg:postcode":"15001",
    "sg:province":"La Coru\u00f1a",
    "sg:website":"www.tio.com",
    "wof:name":"Ares Esmoris Luis",
    "wof:placetype":"venue"
},
  "geometry": {"coordinates":[-8.3951234818,43.3712844849],"type":"Point"}
}