{
  "type": "Feature",
  "properties": {
    "iso:country":"ES",
    "sg:address":"Carrer de Ca L'alegre De Dalt, 84",
    "sg:city":"Barcelona",
    "sg:orig_category":"Empresas De Carpinter\u00cda De Madera",
    "sg:phone":"+34 932 10 86 62",
    "sg:postcode":"08024",
    "sg:province":"Barcelona",
    "wof:name":"Alcala Montes Miguel",
    "wof:placetype":"venue"
},
  "geometry": {"coordinates":[2.1595568657,41.4108695984],"type":"Point"}
}