{
  "type": "Feature",
  "properties": {
    "addr:full":"Calle de Serrano, 98 Madrid Madrid 28006",
    "addr:housenumber":"98",
    "addr:postcode":"madrid;28006",
    "addr:street":"Calle De Serrano",
    "iso:country":"ES",
    "sg:address":"Calle de Serrano, 98",
    "sg:city":"Madrid",
    "sg:orig_category":"Art\u00cdculos De Decoraci\u00d3n",
    "sg:phone":"+34 914 26 28 37",
    "sg:postcode":"28006",
    "sg:province":"Madrid",
    "sg:website":"www.ibermaison.com",
    "wof:name":"Ibermaison S.l.",
    "wof:placetype":"venue"
},
  "geometry": {"coordinates":[-3.6864960194,40.4333076477],"type":"Point"}
}