{
  "type": "Feature",
  "properties": {
    "addr:full":"Calle de Unica (piedrafita De Jaca), S/n Piedrafita Jaca Huesca 22665",
    "addr:housenumber":"s / n",
    "addr:postcode":"22665",
    "addr:street":"Calle De Unica Piedrafita;Jaca",
    "iso:country":"ES",
    "sg:address":"Calle de Unica (piedrafita De Jaca), S/n",
    "sg:city":"Piedrafita Jaca",
    "sg:orig_category":"Turismo",
    "sg:phone":"+34 974 33 70 48",
    "sg:postcode":"22665",
    "sg:province":"Huesca",
    "sg:website":"www.lacuinacha.com",
    "wof:name":"Parque Faunistico De Los Pirineos S.a.",
    "wof:placetype":"venue"
},
  "geometry": {"coordinates":[-0.3248920143,42.695690155],"type":"Point"}
}