{
  "type": "Feature",
  "properties": {
    "addr:full":"Calle de Sagasta, 1 Malaga M\u00e1laga 29005",
    "addr:housenumber":"1",
    "addr:postcode":"29005",
    "addr:street":"Calle De Sagasta;Ma\u0301Laga",
    "iso:country":"ES",
    "sg:address":"Calle de Sagasta, 1",
    "sg:city":"Malaga",
    "sg:orig_category":"Reposter\u00cdas",
    "sg:phone":"+34 952 21 74 25",
    "sg:postcode":"29005",
    "sg:province":"M\u00e1laga",
    "wof:name":"Panificadora Penelope S.l.",
    "wof:placetype":"venue"
},
  "geometry": {"coordinates":[-4.4233422279,36.7189712524],"type":"Point"}
}