{
  "type": "Feature",
  "properties": {
    "addr:full":"Ctra Palamos, 488 S. Feliu Guixols Girona 17220",
    "addr:housenumber":"488",
    "addr:postcode":"17220",
    "addr:street":"Ctra Palamos;S. Feliu Guixols",
    "iso:country":"ES",
    "sg:address":"Ctra Palamos, 488",
    "sg:city":"S. Feliu Guixols",
    "sg:orig_category":"Administradores De Bienes Y Delegados De Comunidades De Propietarios",
    "sg:phone":"+34 972 32 17 32",
    "sg:postcode":"17220",
    "sg:province":"Girona",
    "wof:name":"Crua\u00f1as Pardas Armando",
    "wof:placetype":"venue"
},
  "geometry": {"coordinates":[3.0411698818,41.7891082764],"type":"Point"}
}