{
  "type": "Feature",
  "properties": {
    "addr:full":"Carrera De San Francisco, 5 Velez-malaga M\u00e1laga 29700",
    "addr:housenumber":"5",
    "addr:postcode":"29700",
    "addr:street":"Carrera De San Francisco",
    "iso:country":"ES",
    "sg:address":"Carrera De San Francisco, 5",
    "sg:city":"Velez-malaga",
    "sg:orig_category":"Abogados",
    "sg:phone":"+34 952 50 60 77",
    "sg:postcode":"29700",
    "sg:province":"M\u00e1laga",
    "wof:name":"Moreno Leon Rafael",
    "wof:placetype":"venue"
},
  "geometry": {"coordinates":[-4.1015458107,36.7823753357],"type":"Point"}
}