{
  "type": "Feature",
  "properties": {
    "iso:country":"ES",
    "sg:address":"Calle de San Antonio, S/n",
    "sg:city":"Arroyo De La Miel-benalmadena Costa",
    "sg:orig_category":"Reposter\u00cdas",
    "sg:phone":"+34 952 44 22 70",
    "sg:postcode":"29631",
    "sg:province":"M\u00e1laga",
    "wof:name":"Sibbett  Jillian",
    "wof:placetype":"venue"
},
  "geometry": {"coordinates":[-4.5346889496,36.5988082886],"type":"Point"}
}