{
  "type": "Feature",
  "properties": {
    "addr:full":"Avda Gavilanes (los), S/n Sevilla Sevilla 41006",
    "addr:postcode":"41006",
    "addr:street":"Avda Gavilanes Los S / N",
    "iso:country":"ES",
    "sg:address":"Avda Gavilanes (los), S/n",
    "sg:city":"Sevilla",
    "sg:orig_category":"Inmobiliaria (agencias)",
    "sg:phone":"+34 954 64 51 24",
    "sg:postcode":"41006",
    "sg:province":"Sevilla",
    "wof:name":"Gallo Manrique Maria Dolores",
    "wof:placetype":"venue"
},
  "geometry": {"coordinates":[-5.9541740417,37.3854103088],"type":"Point"}
}