{
  "type": "Feature",
  "properties": {
    "addr:full":"Calle de Madrid, 83 Humanes De Madrid Madrid 28970",
    "addr:housenumber":"83",
    "addr:postcode":"28970",
    "addr:street":"Calle De Madrid",
    "iso:country":"ES",
    "sg:address":"Calle de Madrid, 83",
    "sg:city":"Humanes De Madrid",
    "sg:orig_category":"Agencias De Viajes",
    "sg:phone":"+34 916 04 08 51",
    "sg:postcode":"28970",
    "sg:province":"Madrid",
    "wof:name":"Viajes Iberplaya S.l.",
    "wof:placetype":"venue"
},
  "geometry": {"coordinates":[-3.8244440556,40.2565498352],"type":"Point"}
}