{
  "type": "Feature",
  "properties": {
    "iso:country":"ES",
    "sg:address":"Avda Carlos I De, 11",
    "sg:city":"Donostia-san Sebastian",
    "sg:orig_category":"Estancos",
    "sg:phone":"+34 943 45 72 65",
    "sg:postcode":"20011",
    "sg:province":"Guip\u00f9zcoa",
    "wof:name":"Vergara Larralde Marcelino",
    "wof:placetype":"venue"
},
  "geometry": {"coordinates":[-1.9784059525,43.3036689758],"type":"Point"}
}