{
  "type": "Feature",
  "properties": {
    "addr:full":"Barraca, 1 Barraca La Coru\u00f1a 15920",
    "addr:housenumber":"1",
    "addr:postcode":"15920",
    "addr:street":"Barraca;La Corun\u0303A",
    "iso:country":"ES",
    "sg:address":"Barraca, 1",
    "sg:city":"Barraca",
    "sg:orig_category":"Empresas De Carpinter\u00cda De Madera",
    "sg:phone":"+34 981 86 10 71",
    "sg:postcode":"15920",
    "sg:province":"La Coru\u00f1a",
    "sg:website":"www.torneadostubio.com",
    "wof:name":"Alejandro Tubio E Hijos S.l.",
    "wof:placetype":"venue"
},
  "geometry": {"coordinates":[-8.3959693909,43.3714904785],"type":"Point"}
}