{
  "type": "Feature",
  "properties": {
    "addr:full":"Calle de Pintor Aparicio, 42 Alacant Alicante 03003",
    "addr:housenumber":"42",
    "addr:postcode":"03003",
    "addr:street":"Calle De Pintor Aparicio",
    "iso:country":"ES",
    "sg:address":"Calle de Pintor Aparicio, 42",
    "sg:city":"Alacant",
    "sg:orig_category":"Ropa Para Caballeros (al Por Menor)",
    "sg:phone":"+34 965 92 29 02",
    "sg:postcode":"03003",
    "sg:province":"Alicante",
    "wof:name":"Panocha 1982 S.l.",
    "wof:placetype":"venue"
},
  "geometry": {"coordinates":[-0.4924609959,38.3432388306],"type":"Point"}
}