{
  "type": "Feature",
  "properties": {
    "iso:country":"ES",
    "sg:address":"Carrer de Bon Aire, 3",
    "sg:city":"Llagostera",
    "sg:orig_category":"Asociaciones Y Clubs Deportivos",
    "sg:phone":"+34 972 80 50 51",
    "sg:postcode":"17240",
    "sg:province":"Girona",
    "wof:name":"Marzo Aguera Lidia",
    "wof:placetype":"venue"
},
  "geometry": {"coordinates":[2.8928499222,41.8272209167],"type":"Point"}
}