{
  "type": "Feature",
  "properties": {
    "addr:full":"Cami Onda (d'), S/n Betxi Castell\u00f3n 12549",
    "addr:postcode":"12549",
    "addr:street":"S / N Betxi Castello\u0301N",
    "iso:country":"ES",
    "sg:address":"Cami Onda (d'), S/n",
    "sg:city":"Betxi",
    "sg:orig_category":"Guarder\u00cdas",
    "sg:phone":"+34 964 62 03 83",
    "sg:postcode":"12549",
    "sg:province":"Castell\u00f3n",
    "wof:name":"Ayuntamiento De Betxi",
    "wof:placetype":"venue"
},
  "geometry": {"coordinates":[-0.2009685934,39.9315605164],"type":"Point"}
}