{
  "type": "Feature",
  "properties": {
    "addr:full":"Calle de Manolo Pilares, 2 Pola De Lena Asturias 33630",
    "addr:housenumber":"2",
    "addr:postcode":"33630",
    "addr:street":"Calle De;Pilares",
    "iso:country":"ES",
    "sg:address":"Calle de Manolo Pilares, 2",
    "sg:city":"Pola De Lena",
    "sg:orig_category":"Quincaller\u00cda (al Por Menor)",
    "sg:phone":"+34 985 49 04 14",
    "sg:postcode":"33630",
    "sg:province":"Asturias",
    "wof:name":"Polonio Perez Rafael",
    "wof:placetype":"venue"
},
  "geometry": {"coordinates":[-5.828083992,43.1566352844],"type":"Point"}
}