{
  "type": "Feature",
  "properties": {
    "addr:full":"Carrer de Murillo, 14 Cornella Llobregat Barcelona 08940",
    "addr:housenumber":"14",
    "addr:postcode":"08940",
    "addr:street":"Carrer De Murillo",
    "iso:country":"ES",
    "sg:address":"Carrer de Murillo, 14",
    "sg:city":"Cornella Llobregat",
    "sg:orig_category":"Agencias Y Asesores De Publicidad",
    "sg:phone":"+34 934 70 92 10",
    "sg:postcode":"08940",
    "sg:province":"Barcelona",
    "wof:name":"Britator S.l.",
    "wof:placetype":"venue"
},
  "geometry": {"coordinates":[2.0683150291,41.3551902771],"type":"Point"}
}