{
  "type": "Feature",
  "properties": {
    "addr:full":"Calle de Salvador El, 11 Palmas De Gran Canaria Las Palmas 35010",
    "addr:postcode":"35010",
    "addr:street":"Calle De Salvador El",
    "iso:country":"ES",
    "sg:address":"Calle de Salvador El, 11",
    "sg:city":"Palmas De Gran Canaria",
    "sg:orig_category":"Empresas De Carpinter\u00cda",
    "sg:phone":"+34 928 26 91 63",
    "sg:postcode":"35010",
    "sg:province":"Las Palmas",
    "wof:name":"Recco Perez Manuel",
    "wof:placetype":"venue"
},
  "geometry": {"coordinates":[-15.4437017441,28.1313037872],"type":"Point"}
}