{
  "type": "Feature",
  "properties": {
    "iso:country":"ES",
    "sg:address":"Calle de Ramon Gomez De La Serna, 5",
    "sg:city":"Madrid",
    "sg:orig_category":"Centros M\u00c9dicos Y Sociales, Dispensarios",
    "sg:phone":"+34 913 73 06 95",
    "sg:postcode":"28035",
    "sg:province":"Madrid",
    "wof:name":"Cadenas Cuenca Juan Carlos",
    "wof:placetype":"venue"
},
  "geometry": {"coordinates":[-3.7275419235,40.482383728],"type":"Point"}
}