{
  "type": "Feature",
  "properties": {
    "addr:full":"Calle de Marcelo Usera, 145 Madrid Madrid 28026",
    "addr:housenumber":"145",
    "addr:postcode":"28026",
    "addr:street":"Calle De Marcelo Usera",
    "iso:country":"ES",
    "sg:address":"Calle de Marcelo Usera, 145",
    "sg:city":"Madrid",
    "sg:orig_category":"Loter\u00cda Y T\u00d3mbola",
    "sg:phone":"+34 914 60 66 80",
    "sg:postcode":"28026",
    "sg:province":"Madrid",
    "wof:name":"Moreno Torres Jorge",
    "wof:placetype":"venue"
},
  "geometry": {"coordinates":[-3.7082157135,40.3854980469],"type":"Point"}
}