{
  "type": "Feature",
  "properties": {
    "addr:full":"Carr Aparellador Antonio Monzo, 3 Quart Poblet Valencia 46930",
    "addr:housenumber":"3",
    "addr:postcode":"46930",
    "addr:street":"Carr Aparellador Antonio Monzo;Poblet",
    "iso:country":"ES",
    "sg:address":"Carr Aparellador Antonio Monzo, 3",
    "sg:city":"Quart Poblet",
    "sg:orig_category":"Agentes, Concesionarios Y Sucursales De Veh\u00cdculos",
    "sg:phone":"+34 961 54 77 16",
    "sg:postcode":"46930",
    "sg:province":"Valencia",
    "wof:name":"Garcia Gomera Jose Ramon",
    "wof:placetype":"venue"
},
  "geometry": {"coordinates":[-0.438432008,39.4827690125],"type":"Point"}
}