{
  "type": "Feature",
  "properties": {
    "addr:full":"Calle de Poeta Zorrilla, 17 Alacant Alicante 03012",
    "addr:housenumber":"17",
    "addr:postcode":"03012",
    "addr:street":"Calle De Poeta Zorrilla",
    "iso:country":"ES",
    "sg:address":"Calle de Poeta Zorrilla, 17",
    "sg:city":"Alacant",
    "sg:orig_category":"Laboratorios Y Trabajos De Fotograf\u00cda, V\u00cddeo Y Cine",
    "sg:phone":"+34 965 24 96 29",
    "sg:postcode":"03012",
    "sg:province":"Alicante",
    "wof:name":"Reme Fotografas S.coop.valenciana",
    "wof:placetype":"venue"
},
  "geometry": {"coordinates":[-0.4816690087,38.3554916382],"type":"Point"}
}