{
  "type": "Feature",
  "properties": {
    "addr:full":"Calle de Aita Arrupe Kalea, 4 Mungia Vizcaya 48100",
    "addr:housenumber":"4",
    "addr:postcode":"48100",
    "addr:street":"Calle De Aita Arrupe Kalea",
    "iso:country":"ES",
    "sg:address":"Calle de Aita Arrupe Kalea, 4",
    "sg:city":"Mungia",
    "sg:orig_category":"Art\u00cdculos De Regalo (al Por Menor)",
    "sg:phone":"+34 946 15 66 79",
    "sg:postcode":"48100",
    "sg:province":"Vizcaya",
    "wof:name":"Maria Carmen Barriola Ortiz",
    "wof:placetype":"venue"
},
  "geometry": {"coordinates":[-2.8444898129,43.3539199829],"type":"Point"}
}