{
  "type": "Feature",
  "properties": {
    "addr:full":"Carrer de Raval De La Creu, 7 S. Just Desvern Barcelona 08960",
    "addr:housenumber":"7",
    "addr:postcode":"08960",
    "addr:street":"Carrer De Raval De La Creu",
    "iso:country":"ES",
    "sg:address":"Carrer de Raval De La Creu, 7",
    "sg:city":"S. Just Desvern",
    "sg:orig_category":"Herboristas (al Por Menor)",
    "sg:phone":"+34 933 71 20 67",
    "sg:postcode":"08960",
    "sg:province":"Barcelona",
    "wof:name":"Isern Bofarull Elisabet",
    "wof:placetype":"venue"
},
  "geometry": {"coordinates":[2.0779409409,41.3832702637],"type":"Point"}
}