{
  "type": "Feature",
  "properties": {
    "iso:country":"ES",
    "sg:address":"Calle de Tres Hermanos, 6",
    "sg:city":"Santomera",
    "sg:orig_category":"Asesor\u00cda Fiscal Y Jur\u00cddica",
    "sg:phone":"+34 968 86 21 22",
    "sg:postcode":"30140",
    "sg:province":"Murcia",
    "wof:name":"Grupo Asesant Gestion Empresarial S.l.l.",
    "wof:placetype":"venue"
},
  "geometry": {"coordinates":[-1.0482439995,38.0615234375],"type":"Point"}
}