{
  "type": "Feature",
  "properties": {
    "iso:country":"ES",
    "sg:address":"Calle de Leon Y Castillo, 95",
    "sg:city":"Pto. Rosario",
    "sg:orig_category":"Electrodom\u00c9sticos (al Por Menor)",
    "sg:phone":"+34 928 53 03 45",
    "sg:postcode":"35600",
    "sg:province":"Las Palmas",
    "wof:name":"Ramos Perez Tomas De Las Mercedes",
    "wof:placetype":"venue"
},
  "geometry": {"coordinates":[-13.8689479828,28.5014610291],"type":"Point"}
}