{
  "type": "Feature",
  "properties": {
    "iso:country":"ES",
    "sg:address":"C/ Pare Francesc Molina, Del, 9",
    "sg:city":"Porreres",
    "sg:orig_category":"Forjas Y Altos Hornos",
    "sg:phone":"+34 971 16 66 45",
    "sg:postcode":"07260",
    "sg:province":"Islas Baleares",
    "wof:name":"Casas Julia Pablo Juan",
    "wof:placetype":"venue"
},
  "geometry": {"coordinates":[3.0265328884,39.5134811401],"type":"Point"}
}