{
  "type": "Feature",
  "properties": {
    "iso:country":"ES",
    "sg:address":"Soloberrieta, S/n",
    "sg:city":"Etxarri-aranatz",
    "sg:orig_category":"Empresas De Hormig\u00d3n, Hormig\u00d3n Armado Y Pretensado",
    "sg:phone":"+34 948 46 05 11",
    "sg:postcode":"31820",
    "sg:province":"Navarra",
    "wof:name":"Imaz Hermanos S.l.",
    "wof:placetype":"venue"
},
  "geometry": {"coordinates":[-2.0638840199,42.9061965942],"type":"Point"}
}