{
  "type": "Feature",
  "properties": {
    "addr:full":"Carr Ordre De La Merce, 25 Puig Valencia 46540",
    "addr:housenumber":"25",
    "addr:postcode":"46540",
    "addr:street":"Carr Ordre De La Merce",
    "iso:country":"ES",
    "sg:address":"Carr Ordre De La Merce, 25",
    "sg:city":"Puig",
    "sg:orig_category":"Arboricultura Y Producci\u00d3n De Frutas",
    "sg:phone":"+34 961 47 22 08",
    "sg:postcode":"46540",
    "sg:province":"Valencia",
    "sg:website":"www.grupac.es",
    "wof:name":"Grupo Agricola Grupac S.a.",
    "wof:placetype":"venue"
},
  "geometry": {"coordinates":[-0.2995687127,39.5882110596],"type":"Point"}
}