{
  "type": "Feature",
  "properties": {
    "iso:country":"ES",
    "sg:address":"Calle de Trafalgar, 3",
    "sg:city":"Algeciras",
    "sg:orig_category":"Asesor\u00cda De Formaci\u00d3n Y Gesti\u00d3n De Personal",
    "sg:phone":"+34 956 63 28 29",
    "sg:postcode":"11201",
    "sg:province":"C\u00e1diz",
    "wof:name":"Contreras Jimenez Juan Antonio",
    "wof:placetype":"venue"
},
  "geometry": {"coordinates":[-5.4467592239,36.1323928833],"type":"Point"}
}