{
  "type": "Feature",
  "properties": {
    "addr:full":"Ctra Riudaura, 55 Olot Girona 17800",
    "addr:housenumber":"55",
    "addr:postcode":"17800",
    "addr:street":"Ctra Riudaura",
    "iso:country":"ES",
    "sg:address":"Ctra Riudaura, 55",
    "sg:city":"Olot",
    "sg:orig_category":"Metalurgia",
    "sg:phone":"+34 972 26 92 51",
    "sg:postcode":"17800",
    "sg:province":"Girona",
    "wof:name":"Bretcha Canal Josep",
    "wof:placetype":"venue"
},
  "geometry": {"coordinates":[2.4762890339,42.1838684082],"type":"Point"}
}