{
  "type": "Feature",
  "properties": {
    "addr:full":"Calle de Cortes (las), 18 Huesca Huesca 22002",
    "addr:housenumber":"18",
    "addr:postcode":"22002",
    "addr:street":"Calle De Cortes Las",
    "iso:country":"ES",
    "sg:address":"Calle de Cortes (las), 18",
    "sg:city":"Huesca",
    "sg:orig_category":"Estancos",
    "sg:phone":"+34 974 22 00 65",
    "sg:postcode":"22002",
    "sg:province":"Huesca",
    "wof:name":"Benito Pertusa Raul",
    "wof:placetype":"venue"
},
  "geometry": {"coordinates":[-0.4088410139,42.1400909424],"type":"Point"}
}