{
  "type": "Feature",
  "properties": {
    "iso:country":"ES",
    "sg:address":"Calle de Nicolasa Gomez, 93",
    "sg:city":"Madrid",
    "sg:orig_category":"Plomeros",
    "sg:phone":"+34 913 20 51 69",
    "sg:postcode":"28022",
    "sg:province":"Madrid",
    "wof:name":"Instalaciones Procabe S.l.",
    "wof:placetype":"venue"
},
  "geometry": {"coordinates":[-3.6108870506,40.4369430542],"type":"Point"}
}