{
  "type": "Feature",
  "properties": {
    "addr:full":"Plaz San Francisco, 7 Fuente Maestre Badajoz 06360",
    "addr:housenumber":"7",
    "addr:postcode":"06360",
    "addr:street":"Plaz San Francisco",
    "iso:country":"ES",
    "sg:address":"Plaz San Francisco, 7",
    "sg:city":"Fuente Maestre",
    "sg:orig_category":"Peluquer\u00cdas, Peluquer\u00cda Mixta",
    "sg:phone":"+34 924 53 07 10",
    "sg:postcode":"06360",
    "sg:province":"Badajoz",
    "wof:name":"Lucines S.l.",
    "wof:placetype":"venue"
},
  "geometry": {"coordinates":[-6.442150116,38.5292739868],"type":"Point"}
}