{
  "type": "Feature",
  "properties": {
    "iso:country":"ES",
    "sg:address":"Puente Congosto, Km. 0007,0",
    "sg:city":"Santiba\u00f1ez Bejar",
    "sg:orig_category":"Distribuci\u00d3n De Petr\u00d3leo Y Derivados",
    "sg:phone":"+34 923 59 41 64",
    "sg:postcode":"37740",
    "sg:province":"Salamanca",
    "wof:name":"Paraje Serillas S.l.",
    "wof:placetype":"venue"
},
  "geometry": {"coordinates":[-5.608479023,40.4874343872],"type":"Point"}
}