{
  "type": "Feature",
  "properties": {
    "iso:country":"ES",
    "sg:address":"Calle de Procesion, 2",
    "sg:city":"Jimenez Jamuz",
    "sg:orig_category":"Alfarer\u00cda",
    "sg:phone":"+34 987 66 43 86",
    "sg:postcode":"24767",
    "sg:province":"Le\u00f3n",
    "wof:name":"Garcia San Juan Esteban",
    "wof:placetype":"venue"
},
  "geometry": {"coordinates":[-5.9288592339,42.2660446167],"type":"Point"}
}