{
  "type": "Feature",
  "properties": {
    "addr:full":"Calle de Strachan, 6 Malaga M\u00e1laga 29015",
    "addr:housenumber":"6",
    "addr:postcode":"29015",
    "addr:street":"Calle De Strachan;Ma\u0301Laga",
    "iso:country":"ES",
    "sg:address":"Calle de Strachan, 6",
    "sg:city":"Malaga",
    "sg:orig_category":"Administradores De Bienes Y Delegados De Comunidades De Propietarios",
    "sg:phone":"+34 952 06 00 08",
    "sg:postcode":"29015",
    "sg:province":"M\u00e1laga",
    "wof:name":"Mu\u00f1oz Nu\u00f1ez De Castro Miguel",
    "wof:placetype":"venue"
},
  "geometry": {"coordinates":[-4.4210982323,36.7196006775],"type":"Point"}
}