{
  "type": "Feature",
  "properties": {
    "addr:full":"Calle de Valle De Aran, 16 Villafranca Del Castillo-la Mocha Chica Madrid 28692",
    "addr:housenumber":"16",
    "addr:postcode":"28692",
    "addr:street":"Calle De Valle De Aran",
    "iso:country":"ES",
    "sg:address":"Calle de Valle De Aran, 16",
    "sg:city":"Villafranca Del Castillo-la Mocha Chica",
    "sg:orig_category":"Inmobiliaria (agencias)",
    "sg:phone":"+34 918 10 00 45",
    "sg:postcode":"28692",
    "sg:province":"Madrid",
    "wof:name":"Sydimon S L",
    "wof:placetype":"venue"
},
  "geometry": {"coordinates":[-3.9472389221,40.4630851746],"type":"Point"}
}