{
  "type": "Feature",
  "properties": {
    "iso:country":"ES",
    "sg:address":"Ctra Cadiz (pi Cdad Blanca-montecillos), Km. 0557,0",
    "sg:city":"Dos Hermanas",
    "sg:orig_category":"Art\u00cdculos De Decoraci\u00d3n",
    "sg:phone":"+34 955 67 53 53",
    "sg:postcode":"41700",
    "sg:province":"Sevilla",
    "sg:website":"www.abetos.com",
    "wof:name":"Abetos Muebles De Hogar S.l.",
    "wof:placetype":"venue"
},
  "geometry": {"coordinates":[-5.922242,37.283176],"type":"Point"}
}