{
  "type": "Feature",
  "properties": {
    "iso:country":"ES",
    "sg:address":"Calle de San Juan, 4",
    "sg:city":"Quinto",
    "sg:classifiers":[
        {
            "category":"Retail",
            "subcategory":"Event Space",
            "type":"Services"
        }
    ],
    "sg:phone":"+34 976 17 70 47",
    "sg:postcode":"50770",
    "sg:province":"Zaragoza",
    "sg:tags":[
        "planchas",
        "surf",
        "alquiler",
        "de",
        "vela",
        "kayak",
        "barcos",
        "canoes",
        "y"
    ],
    "wof:name":"Carmen Gracia Gabasa Y Otros Comunidad De Bienes",
    "wof:placetype":"venue"
},
  "geometry": {"coordinates":[-0.4963389933,41.4234580994],"type":"Point"}
}