{
  "type": "Feature",
  "properties": {
    "iso:country":"ES",
    "sg:address":"Cust San Francisco, 2",
    "sg:city":"Rozas De Madrid",
    "sg:orig_category":"Inmobiliaria (agencias)",
    "sg:phone":"+34 916 37 37 24",
    "sg:postcode":"28230",
    "sg:province":"Madrid",
    "wof:name":"Sogescom Inmuebles S.l.",
    "wof:placetype":"venue"
},
  "geometry": {"coordinates":[-3.8913800716,40.5247497559],"type":"Point"}
}