{
  "type": "Feature",
  "properties": {
    "addr:full":"Calle de San Juan De Letran, 10 Malaga M\u00e1laga 29012",
    "addr:housenumber":"10",
    "addr:postcode":"29012",
    "addr:street":"Calle De San;Malaga Ma\u0301Laga",
    "iso:country":"ES",
    "sg:address":"Calle de San Juan De Letran, 10",
    "sg:city":"Malaga",
    "sg:orig_category":"Aparatos, Material Y Suministros Para Laboratorios",
    "sg:phone":"+34 952 21 73 71",
    "sg:postcode":"29012",
    "sg:province":"M\u00e1laga",
    "wof:name":"Leandro Martinez Martinez S.a.",
    "wof:placetype":"venue"
},
  "geometry": {"coordinates":[-4.4182667732,36.7242240906],"type":"Point"}
}