{
  "type": "Feature",
  "properties": {
    "addr:full":"Calle de Pintor Lorenzo Casanova, 5 Alacant Alicante 03003",
    "addr:housenumber":"5",
    "addr:postcode":"03003",
    "addr:street":"Calle De Pintor Lorenzo Casanova",
    "iso:country":"ES",
    "sg:address":"Calle de Pintor Lorenzo Casanova, 5",
    "sg:city":"Alacant",
    "sg:orig_category":"Abogados",
    "sg:phone":"+34 965 12 57 64",
    "sg:postcode":"03003",
    "sg:province":"Alicante",
    "wof:name":"Ruiz Garcia Jose",
    "wof:placetype":"venue"
},
  "geometry": {"coordinates":[-0.4888330102,38.3422660828],"type":"Point"}
}