{
  "type": "Feature",
  "properties": {
    "iso:country":"ES",
    "sg:address":"Carr Cardenal Cisneros, 51",
    "sg:city":"Gandia",
    "sg:orig_category":"Molduras, Junquillos, Listones Y Molduras Perforadas",
    "sg:phone":"+34 962 86 51 89",
    "sg:postcode":"46700",
    "sg:province":"Valencia",
    "wof:name":"Pozuelo Marquez Agustin",
    "wof:placetype":"venue"
},
  "geometry": {"coordinates":[-0.1913339943,38.960735321],"type":"Point"}
}