{
  "type": "Feature",
  "properties": {
    "iso:country":"ES",
    "sg:address":"Carrer de Crist Verd, 1",
    "sg:city":"Palma",
    "sg:orig_category":"Abogados",
    "sg:phone":"+34 971 21 40 51",
    "sg:postcode":"07002",
    "sg:province":"Islas Baleares",
    "wof:name":"Moll Linares Andres",
    "wof:placetype":"venue"
},
  "geometry": {"coordinates":[2.6522700787,39.5743904114],"type":"Point"}
}