{
  "type": "Feature",
  "properties": {
    "addr:full":"Calle de Alberche, 6 Sevilla Sevilla 41005",
    "addr:housenumber":"6",
    "addr:postcode":"41005",
    "addr:street":"Calle De Alberche",
    "iso:country":"ES",
    "sg:address":"Calle de Alberche, 6",
    "sg:city":"Sevilla",
    "sg:orig_category":"Ingenier\u00cda, Centros De Estudios (diversos)",
    "sg:phone":"+34 954 23 39 82",
    "sg:postcode":"41005",
    "sg:province":"Sevilla",
    "wof:name":"A J C Ingenieria S.l.",
    "wof:placetype":"venue"
},
  "geometry": {"coordinates":[-5.9667906761,37.3723945618],"type":"Point"}
}