{
  "type": "Feature",
  "properties": {
    "iso:country":"ES",
    "sg:address":"Carrer de Carders, 15",
    "sg:city":"Barcelona",
    "sg:orig_category":"Alimentaci\u00d3n General (al Por Menor)",
    "sg:phone":"+34 933 19 91 67",
    "sg:postcode":"08003",
    "sg:province":"Barcelona",
    "wof:name":"Moreira Salda\u00f1a Carlos Alberto",
    "wof:placetype":"venue"
},
  "geometry": {"coordinates":[2.1800210476,41.3862838745],"type":"Point"}
}