{
  "type": "Feature",
  "properties": {
    "iso:country":"ES",
    "sg:address":"Av Fabraquer, 34",
    "sg:city":"Playa Muchavista",
    "sg:orig_category":"Arquitectos",
    "sg:phone":"+34 965 65 27 42",
    "sg:postcode":"03560",
    "sg:province":"Alicante",
    "wof:name":"Anton Baeza Fernando Vicente",
    "wof:placetype":"venue"
},
  "geometry": {"coordinates":[-0.409373194,38.4060211182],"type":"Point"}
}