{
  "type": "Feature",
  "properties": {
    "addr:full":"Avda Galicia, S/n Zamora Zamora 49024",
    "addr:housenumber":"s",
    "addr:postcode":"49024",
    "addr:street":"Avda Galicia;/ N",
    "iso:country":"ES",
    "sg:address":"Avda Galicia, S/n",
    "sg:city":"Zamora",
    "sg:orig_category":"Agentes, Concesionarios Y Sucursales De Veh\u00cdculos",
    "sg:phone":"+34 980 51 14 18",
    "sg:postcode":"49024",
    "sg:province":"Zamora",
    "wof:name":"Mirauto S.a.",
    "wof:placetype":"venue"
},
  "geometry": {"coordinates":[-5.7528390884,41.5138435364],"type":"Point"}
}