{
  "type": "Feature",
  "properties": {
    "iso:country":"ES",
    "sg:address":"Calle de Leonardo Rucabado, 24",
    "sg:city":"Castro Urdiales",
    "sg:orig_category":"Ropa De Trabajo Y Profesionales (al Por Menor)",
    "sg:phone":"+34 942 86 25 29",
    "sg:postcode":"39700",
    "sg:province":"Cantabria",
    "wof:name":"Loriz Aguado Victor",
    "wof:placetype":"venue"
},
  "geometry": {"coordinates":[-3.2178618908,43.3773612976],"type":"Point"}
}