{
  "type": "Feature",
  "properties": {
    "addr:full":"Calle de General San Martin, 6 Valencia Valencia 46004",
    "addr:housenumber":"6",
    "addr:postcode":"46004",
    "addr:street":"Calle De General San Martin",
    "iso:country":"ES",
    "sg:address":"Calle de General San Martin, 6",
    "sg:city":"Valencia",
    "sg:orig_category":"Agencias De Viajes",
    "sg:phone":"+34 963 41 88 88",
    "sg:postcode":"46004",
    "sg:province":"Valencia",
    "sg:website":"www.halconviajes.com",
    "wof:name":"Viajes Halcon S.a.",
    "wof:placetype":"venue"
},
  "geometry": {"coordinates":[-0.3754900098,39.4652557373],"type":"Point"}
}