{
  "type": "Feature",
  "properties": {
    "addr:full":"Plaz Chiribitas (de Las), S/n Logro\u00f1o La Rioja 26004",
    "addr:postcode":"26004",
    "addr:street":"Plaz;S / N Logron\u0303O;Rioja",
    "iso:country":"ES",
    "sg:address":"Plaz Chiribitas (de Las), S/n",
    "sg:city":"Logro\u00f1o",
    "sg:orig_category":"Centros De Educaci\u00d3n Especial",
    "sg:phone":"+34 941 24 11 91",
    "sg:postcode":"26004",
    "sg:province":"La Rioja",
    "wof:name":"Educacion Infantil Duquesa De La Victoria",
    "wof:placetype":"venue"
},
  "geometry": {"coordinates":[-2.4355249405,42.4619941711],"type":"Point"}
}