{
  "type": "Feature",
  "properties": {
    "iso:country":"ES",
    "sg:address":"Calle de General Vives, 77",
    "sg:city":"Palmas De Gran Canaria",
    "sg:orig_category":"Centros De Coordinaci\u00d3n",
    "sg:phone":"+34 928 26 24 19",
    "sg:postcode":"35007",
    "sg:province":"Las Palmas",
    "wof:name":"Vega Sanchez Jose Juan 000385774q Slne",
    "wof:placetype":"venue"
},
  "geometry": {"coordinates":[-15.4314775467,28.140630722],"type":"Point"}
}