{
  "type": "Feature",
  "properties": {
    "iso:country":"ES",
    "sg:address":"Calle de Illescas, 81",
    "sg:city":"Madrid",
    "sg:orig_category":"Tiendas De Grano, Frutas Y Legumbres Secas (al Por Menor)",
    "sg:phone":"+34 915 18 58 47",
    "sg:postcode":"28024",
    "sg:province":"Madrid",
    "wof:name":"Martin Rodriguez Casimira",
    "wof:placetype":"venue"
},
  "geometry": {"coordinates":[-3.7591900826,40.3927001953],"type":"Point"}
}