{
  "type": "Feature",
  "properties": {
    "iso:country":"ES",
    "sg:address":"Calle de Domingo Beltran De Otazu, 25",
    "sg:city":"Vitoria-gasteiz",
    "sg:classifiers":[
        {
            "category":"Personal",
            "subcategory":"Barber",
            "type":"Services"
        }
    ],
    "sg:phone":"+34 945 22 36 31",
    "sg:postcode":"01012",
    "sg:province":"\u00c1lava",
    "sg:tags":[
        "caballeros",
        "de",
        "peluqueros"
    ],
    "wof:name":"San Martin Iba\u00f1ez Pedro",
    "wof:placetype":"venue"
},
  "geometry": {"coordinates":[-2.6774749756,42.8519859314],"type":"Point"}
}