{
  "type": "Feature",
  "properties": {
    "iso:country":"ES",
    "sg:address":"Avda Ejercito (del), 28",
    "sg:city":"Arganda",
    "sg:orig_category":"Abogados",
    "sg:phone":"+34 918 70 17 85",
    "sg:postcode":"28500",
    "sg:province":"Madrid",
    "wof:name":"Cuellar Salvanes Gregorio",
    "wof:placetype":"venue"
},
  "geometry": {"coordinates":[-3.4440360069,40.3016014099],"type":"Point"}
}