{
  "type": "Feature",
  "properties": {
    "addr:full":"Carrer de Viladomat, 43 Barcelona Barcelona 08015",
    "addr:housenumber":"43",
    "addr:postcode":"08015",
    "addr:street":"Carrer De Viladomat",
    "iso:country":"ES",
    "sg:address":"Carrer de Viladomat, 43",
    "sg:city":"Barcelona",
    "sg:orig_category":"Material Y Suministros Para Fotocopiadoras, Reprograf\u00cda",
    "sg:phone":"+34 933 25 49 32",
    "sg:postcode":"08015",
    "sg:province":"Barcelona",
    "wof:name":"Folder Serveis Digitals S.l.",
    "wof:placetype":"venue"
},
  "geometry": {"coordinates":[2.1605648994,41.377040863],"type":"Point"}
}