{
  "type": "Feature",
  "properties": {
    "iso:country":"ES",
    "sg:address":"Gudugarreta Auzoa, S/n",
    "sg:city":"Gudugarreta",
    "sg:classifiers":[
        {
            "category":"Taxi",
            "type":"Transportation"
        }
    ],
    "sg:phone":"+34 943 16 05 27",
    "sg:postcode":"20200",
    "sg:province":"Guip\u00f9zcoa",
    "wof:name":"Mikelarena Mutuberria Placido",
    "wof:placetype":"venue"
},
  "geometry": {"coordinates":[-2.1944589615,43.0469207764],"type":"Point"}
}