{
  "type": "Feature",
  "properties": {
    "addr:full":"Ctra. Nnal. 340, S/n Guadiaro C\u00e1diz 11311",
    "addr:housenumber":"340 s / n",
    "addr:postcode":"11311",
    "addr:street":"Ctra. Nnal.;Ca\u0301Diz",
    "iso:country":"ES",
    "sg:address":"Ctra. Nnal. 340, S/n",
    "sg:city":"Guadiaro",
    "sg:orig_category":"Aguas (distribuci\u00d3n, Servicios)",
    "sg:phone":"+34 956 61 42 91",
    "sg:postcode":"11311",
    "sg:province":"C\u00e1diz",
    "wof:name":"N.h. Hoteles S.a.",
    "wof:placetype":"venue"
},
  "geometry": {"coordinates":[-5.2987089157,36.2937660217],"type":"Point"}
}