{
  "type": "Feature",
  "properties": {
    "addr:full":"Praz Compostela, 30 Vigo Pontevedra 36201",
    "addr:housenumber":"30",
    "addr:postcode":"36201",
    "addr:street":"Praz Compostela",
    "iso:country":"ES",
    "sg:address":"Praz Compostela, 30",
    "sg:city":"Vigo",
    "sg:orig_category":"Sociedades, Compa\u00d1\u00cdas Aseguradoras",
    "sg:phone":"+34 986 43 28 11",
    "sg:postcode":"36201",
    "sg:province":"Pontevedra",
    "wof:name":"Mutua General Seguros",
    "wof:placetype":"venue"
},
  "geometry": {"coordinates":[-8.7234563828,42.2396125793],"type":"Point"}
}