{
  "type": "Feature",
  "properties": {
    "addr:full":"Iglesia, S/n Mojacar Almer\u00eda 04638",
    "addr:housenumber":"s / n",
    "addr:postcode":"04638",
    "addr:street":"Almeri\u0301A",
    "iso:country":"ES",
    "sg:address":"Iglesia, S/n",
    "sg:city":"Mojacar",
    "sg:orig_category":"Fabrica De Cer\u00c1micas",
    "sg:phone":"+34 950 47 50 71",
    "sg:postcode":"04638",
    "sg:province":"Almer\u00eda",
    "wof:name":"Ceramicas La Mojaquera S.l.",
    "wof:placetype":"venue"
},
  "geometry": {"coordinates":[-1.8467450142,37.1402359009],"type":"Point"}
}