{
  "type": "Feature",
  "properties": {
    "iso:country":"ES",
    "sg:address":"C/ Asp, 18",
    "sg:city":"Elche",
    "sg:orig_category":"Abogados",
    "sg:phone":"+34 965 46 06 83",
    "sg:postcode":"03201",
    "sg:province":"Alicante",
    "wof:name":"Quero Calderon Jose Angel",
    "wof:placetype":"venue"
},
  "geometry": {"coordinates":[-0.7014949918,38.2639579773],"type":"Point"}
}