{
  "type": "Feature",
  "properties": {
    "addr:full":"Carr Blasco Iba\u00d1ez, 69 Burjassot Valencia 46100",
    "addr:housenumber":"69",
    "addr:postcode":"46100",
    "addr:street":"Carr Blasco Iban\u0303Ez",
    "iso:country":"ES",
    "sg:address":"Carr Blasco Iba\u00d1ez, 69",
    "sg:city":"Burjassot",
    "sg:orig_category":"Promotores Constructores",
    "sg:phone":"+34 963 64 07 62",
    "sg:postcode":"46100",
    "sg:province":"Valencia",
    "wof:name":"Belloch Hueso Daniel Vicente",
    "wof:placetype":"venue"
},
  "geometry": {"coordinates":[-0.408555001,39.5075378418],"type":"Point"}
}