{
  "type": "Feature",
  "properties": {
    "iso:country":"ES",
    "sg:address":"Carrer de Marques De Santillana, 15",
    "sg:city":"Barcelona",
    "sg:orig_category":"Peluqueros: De Se\u00d1oras",
    "sg:phone":"+34 933 46 99 28",
    "sg:postcode":"08030",
    "sg:province":"Barcelona",
    "wof:name":"Perruqueria Nadal Scp",
    "wof:placetype":"venue"
},
  "geometry": {"coordinates":[2.1888799667,41.4290390015],"type":"Point"}
}