{
  "type": "Feature",
  "properties": {
    "iso:country":"ES",
    "sg:address":"Carrer de Rosa Ribas I Parellada, 27",
    "sg:city":"Prat Llobregat",
    "sg:orig_category":"Reposter\u00cdas",
    "sg:phone":"+34 933 70 06 64",
    "sg:postcode":"08820",
    "sg:province":"Barcelona",
    "wof:name":"Martinez Pallares Manuel",
    "wof:placetype":"venue"
},
  "geometry": {"coordinates":[2.0890870094,41.3228874207],"type":"Point"}
}