{
  "type": "Feature",
  "properties": {
    "iso:country":"ES",
    "sg:address":"Calle de Huerta (la), 13",
    "sg:city":"Felix",
    "sg:orig_category":"Farmacias",
    "sg:phone":"+34 950 55 96 21",
    "sg:postcode":"04739",
    "sg:province":"Almer\u00eda",
    "wof:name":"Vilches Martinez Fausto",
    "wof:placetype":"venue"
},
  "geometry": {"coordinates":[-2.6579880714,36.8679656982],"type":"Point"}
}