{
  "type": "Feature",
  "properties": {
    "addr:full":"Avda Libertad (la), 23 San Vicente Del Raspeig-sant Vicent Del Raspeig Alicante 03690",
    "addr:housenumber":"23",
    "addr:postcode":"03690",
    "addr:street":"Avda Libertad La",
    "iso:country":"ES",
    "sg:address":"Avda Libertad (la), 23",
    "sg:city":"San Vicente Del Raspeig-sant Vicent Del Raspeig",
    "sg:orig_category":"Agencias De Viajes",
    "sg:phone":"+34 965 66 84 15",
    "sg:postcode":"03690",
    "sg:province":"Alicante",
    "sg:website":"www.barceloviajes.com",
    "wof:name":"Viajes Sant Vicent S.a.",
    "wof:placetype":"venue"
},
  "geometry": {"coordinates":[-0.5228329897,38.3973884583],"type":"Point"}
}