{
  "type": "Feature",
  "properties": {
    "iso:country":"ES",
    "sg:address":"Ctra Su Eminencia, 14",
    "sg:city":"Sevilla",
    "sg:orig_category":"Droguer\u00cdas (al Por Mayor)",
    "sg:phone":"+34 954 63 67 16",
    "sg:postcode":"41006",
    "sg:province":"Sevilla",
    "wof:name":"A Cardoso S. A.",
    "wof:placetype":"venue"
},
  "geometry": {"coordinates":[-5.9743280411,37.3559455872],"type":"Point"}
}