{
  "type": "Feature",
  "properties": {
    "iso:country":"ES",
    "sg:address":"Pl. Andalucia, 2",
    "sg:city":"Chucena",
    "sg:orig_category":"Administraciones Regionales, Departamentales Y Locales",
    "sg:phone":"+34 959 42 41 31",
    "sg:postcode":"21891",
    "sg:province":"Huelva",
    "wof:name":"Ayuntamiento De Chucena",
    "wof:placetype":"venue"
},
  "geometry": {"coordinates":[-6.3940253258,37.3613319397],"type":"Point"}
}