{
  "type": "Feature",
  "properties": {
    "iso:country":"ES",
    "sg:address":"Avda Llanes, S/n",
    "sg:city":"Sevilla",
    "sg:orig_category":"Veh\u00cdculos De Ocasi\u00d3n",
    "sg:phone":"+34 954 35 34 34",
    "sg:postcode":"41008",
    "sg:province":"Sevilla",
    "wof:name":"Automoviles Ordas, S.c.",
    "wof:placetype":"venue"
},
  "geometry": {"coordinates":[-5.9739542007,37.4048233032],"type":"Point"}
}