{
  "type": "Feature",
  "properties": {
    "iso:country":"ES",
    "sg:address":"Avda 25 D'abril, S/n",
    "sg:city":"Riola",
    "sg:orig_category":"Organizaci\u00d3n De Actos, Seminarios Y Congresos",
    "sg:phone":"+34 961 70 19 19",
    "sg:postcode":"46417",
    "sg:province":"Valencia",
    "wof:name":"Sala Santi S.l",
    "wof:placetype":"venue"
},
  "geometry": {"coordinates":[-0.3390400112,39.1962890625],"type":"Point"}
}