{
  "type": "Feature",
  "properties": {
    "addr:full":"Rbla Carmen (del), 3 Motril Granada 18600",
    "addr:housenumber":"3",
    "addr:postcode":"18600",
    "addr:street":"Rbla Carmen Del",
    "iso:country":"ES",
    "sg:address":"Rbla Carmen (del), 3",
    "sg:city":"Motril",
    "sg:orig_category":"Ingeniero",
    "sg:phone":"+34 958 82 41 22",
    "sg:postcode":"18600",
    "sg:province":"Granada",
    "wof:name":"Naranjo Jimenez Francisco Jose",
    "wof:placetype":"venue"
},
  "geometry": {"coordinates":[-3.5152790546,36.7456130981],"type":"Point"}
}