{
  "type": "Feature",
  "properties": {
    "addr:full":"Plaz Carmen (del), 2 Granada Granada 18009",
    "addr:postcode":"18009",
    "iso:country":"ES",
    "sg:address":"Plaz Carmen (del), 2",
    "sg:city":"Granada",
    "sg:orig_category":"Peluquer\u00cdas, Peluquer\u00cda Mixta",
    "sg:phone":"+34 958 22 03 85",
    "sg:postcode":"18009",
    "sg:province":"Granada",
    "wof:name":"Cambil Martin Elisa Isabel",
    "wof:placetype":"venue"
},
  "geometry": {"coordinates":[-3.5528790951,37.1624031067],"type":"Point"}
}