{
  "type": "Feature",
  "properties": {
    "addr:full":"Pio Xii, 18 El Campello Alicante 03560",
    "addr:housenumber":"18",
    "addr:postcode":"03560",
    "addr:street":"Pio Xii",
    "iso:country":"ES",
    "sg:address":"Pio Xii, 18",
    "sg:city":"El Campello",
    "sg:orig_category":"Asesor\u00cda Fiscal Y Jur\u00cddica",
    "sg:phone":"+34 965 63 10 85",
    "sg:postcode":"03560",
    "sg:province":"Alicante",
    "wof:name":"Baeza Reig S.l.",
    "wof:placetype":"venue"
},
  "geometry": {"coordinates":[-0.3906340003,38.4271888733],"type":"Point"}
}