{
  "type": "Feature",
  "properties": {
    "addr:full":"Calle de Marques De Los Velez, S/n Velez-blanco Almer\u00eda 04830",
    "addr:housenumber":"s",
    "addr:postcode":"04830",
    "addr:street":"Calle De Marques De Los Velez;/ N Velez-Blanco Almeri\u0301A",
    "iso:country":"ES",
    "sg:address":"Calle de Marques De Los Velez, S/n",
    "sg:city":"Velez-blanco",
    "sg:orig_category":"Oficinas De Turismo, Asociaciones De Iniciativa",
    "sg:phone":"+34 950 41 53 54",
    "sg:postcode":"04830",
    "sg:province":"Almer\u00eda",
    "wof:name":"Empresa De Gestion Medio Ambiental S.a.",
    "wof:placetype":"venue"
},
  "geometry": {"coordinates":[-2.0963690281,37.695941925],"type":"Point"}
}