{
  "type": "Feature",
  "properties": {
    "addr:full":"Calle de Severo Catalina, 17 Cuenca Cuenca 16001",
    "addr:housenumber":"17",
    "addr:postcode":"16001",
    "addr:street":"Calle De Severo Catalina",
    "iso:country":"ES",
    "sg:address":"Calle de Severo Catalina, 17",
    "sg:city":"Cuenca",
    "sg:orig_category":"Grafistas",
    "sg:phone":"+34 969 23 62 85",
    "sg:postcode":"16001",
    "sg:province":"Cuenca",
    "wof:name":"Comunicacion Calygrafica S.l.",
    "wof:placetype":"venue"
},
  "geometry": {"coordinates":[-2.1302170753,40.0782814026],"type":"Point"}
}