{
  "type": "Feature",
  "properties": {
    "addr:full":"Calle de Olmo, 13 Fuenlabrada Madrid 28942",
    "addr:housenumber":"13",
    "addr:postcode":"28942",
    "addr:street":"Calle De Olmo",
    "iso:country":"ES",
    "sg:address":"Calle de Olmo, 13",
    "sg:city":"Fuenlabrada",
    "sg:orig_category":"Piscinas, Accesorios, Suministros (fabricaci\u00d3n, Al Por Mayor)",
    "sg:phone":"+34 916 00 20 54",
    "sg:postcode":"28942",
    "sg:province":"Madrid",
    "sg:website":"www.cuesport.com",
    "wof:name":"Cuesa Esport S.l.",
    "wof:placetype":"venue"
},
  "geometry": {"coordinates":[-3.8370990753,40.2988739014],"type":"Point"}
}