{
  "type": "Feature",
  "properties": {
    "addr:full":"Calle de Gloria, 25 Pedro-martinez Granada 18530",
    "addr:housenumber":"25",
    "addr:postcode":"18530",
    "addr:street":"Calle De Gloria",
    "iso:country":"ES",
    "sg:address":"Calle de Gloria, 25",
    "sg:city":"Pedro-martinez",
    "sg:orig_category":"Empresas De Carpinter\u00cda De Madera",
    "sg:phone":"+34 958 68 70 97",
    "sg:postcode":"18530",
    "sg:province":"Granada",
    "wof:name":"Burgos Martinez Antonio",
    "wof:placetype":"venue"
},
  "geometry": {"coordinates":[-3.2293820381,37.5010566711],"type":"Point"}
}