{
  "type": "Feature",
  "properties": {
    "addr:full":"Mayor, 4 Playa Honda Las Palmas 35509",
    "addr:housenumber":"4",
    "addr:postcode":"35509",
    "addr:street":"Mayor",
    "iso:country":"ES",
    "sg:address":"Mayor, 4",
    "sg:city":"Playa Honda",
    "sg:orig_category":"Peluquer\u00cdas, Peluquer\u00cda Mixta",
    "sg:phone":"+34 928 82 39 38",
    "sg:postcode":"35509",
    "sg:province":"Las Palmas",
    "wof:name":"Oromix C.b.",
    "wof:placetype":"venue"
},
  "geometry": {"coordinates":[-13.5914945602,28.9539089203],"type":"Point"}
}