{
  "type": "Feature",
  "properties": {
    "iso:country":"ES",
    "sg:address":"C/ Blas Valero, 57",
    "sg:city":"Elche",
    "sg:orig_category":"Inmobiliaria (agencias)",
    "sg:phone":"+34 965 44 04 12",
    "sg:postcode":"03201",
    "sg:province":"Alicante",
    "wof:name":"Soler Y Berna Inmobiliaria S.l.",
    "wof:placetype":"venue"
},
  "geometry": {"coordinates":[-0.7016599774,38.2683982849],"type":"Point"}
}