{
  "type": "Feature",
  "properties": {
    "addr:full":"Calle de Sargento Torres De Vides, 1 Marchena Sevilla 41620",
    "addr:housenumber":"1",
    "addr:postcode":"41620",
    "addr:street":"Calle De Sargento Torres De Vides",
    "iso:country":"ES",
    "sg:address":"Calle de Sargento Torres De Vides, 1",
    "sg:city":"Marchena",
    "sg:orig_category":"Quincaller\u00cda (al Por Menor)",
    "sg:phone":"+34 955 84 54 51",
    "sg:postcode":"41620",
    "sg:province":"Sevilla",
    "wof:name":"Parra Pavon Manuel",
    "wof:placetype":"venue"
},
  "geometry": {"coordinates":[-5.4187040329,37.3254318237],"type":"Point"}
}