{
  "type": "Feature",
  "properties": {
    "addr:full":"Carr Independencia, 256 Badalona Barcelona 08915",
    "addr:housenumber":"256",
    "addr:postcode":"08915",
    "addr:street":"Carr Independencia",
    "iso:country":"ES",
    "sg:address":"Carr Independencia, 256",
    "sg:city":"Badalona",
    "sg:orig_category":"M\u00dasica, Direcci\u00d3n",
    "sg:phone":"+34 933 98 68 41",
    "sg:postcode":"08915",
    "sg:province":"Barcelona",
    "sg:website":"www.mentesinquietas.com",
    "wof:name":"Mentes Inquietas S.l.",
    "wof:placetype":"venue"
},
  "geometry": {"coordinates":[2.241189003,41.4616584778],"type":"Point"}
}