{
  "type": "Feature",
  "properties": {
    "iso:country":"ES",
    "sg:address":"Calle de Rio Jucar, 6",
    "sg:city":"Valdemoro",
    "sg:orig_category":"Peluqueros: De Se\u00d1oras",
    "sg:phone":"+34 918 95 53 15",
    "sg:postcode":"28340",
    "sg:province":"Madrid",
    "wof:name":"Graficos Visuales Sanchez S.l.",
    "wof:placetype":"venue"
},
  "geometry": {"coordinates":[-3.681704998,40.1926574707],"type":"Point"}
}