{
  "type": "Feature",
  "properties": {
    "addr:full":"Calle de Albacete, 4 Valencia Valencia 46007",
    "addr:housenumber":"4",
    "addr:postcode":"46007",
    "addr:street":"Calle De Albacete",
    "iso:country":"ES",
    "sg:address":"Calle de Albacete, 4",
    "sg:city":"Valencia",
    "sg:orig_category":"Abogados",
    "sg:phone":"+34 963 80 26 26",
    "sg:postcode":"46007",
    "sg:province":"Valencia",
    "sg:website":"www.zarraluqui.net",
    "wof:name":"Sarraluqui Abogados De Familia En Vca S.l.",
    "wof:placetype":"venue"
},
  "geometry": {"coordinates":[-0.3826569915,39.4653625488],"type":"Point"}
}