{
  "type": "Feature",
  "properties": {
    "addr:full":"Calle de Santo Domingo, 50 Vitoria-gasteiz \u00c1lava 01001",
    "addr:housenumber":"50",
    "addr:postcode":"01001",
    "addr:street":"Calle De Santo Domingo",
    "iso:country":"ES",
    "sg:address":"Calle de Santo Domingo, 50",
    "sg:city":"Vitoria-gasteiz",
    "sg:orig_category":"Alimentaci\u00d3n General (al Por Menor)",
    "sg:phone":"+34 945 14 19 63",
    "sg:postcode":"01001",
    "sg:province":"\u00c1lava",
    "wof:name":"Gutierrez Amo Atilano",
    "wof:placetype":"venue"
},
  "geometry": {"coordinates":[-2.6730189323,42.8519515991],"type":"Point"}
}