{
  "type": "Feature",
  "properties": {
    "addr:full":"Calle de Andalucia, S/n Nerja M\u00e1laga 29780",
    "addr:housenumber":"/ n",
    "addr:postcode":"29780",
    "addr:street":"Calle De Andalucia S",
    "iso:country":"ES",
    "sg:address":"Calle de Andalucia, S/n",
    "sg:city":"Nerja",
    "sg:orig_category":"Supermercados Y Hipermercados",
    "sg:phone":"+34 952 52 87 73",
    "sg:postcode":"29780",
    "sg:province":"M\u00e1laga",
    "wof:name":"Lopez Garcia Jose Manuel",
    "wof:placetype":"venue"
},
  "geometry": {"coordinates":[-3.8731524944,36.7535896301],"type":"Point"}
}