{
  "type": "Feature",
  "properties": {
    "iso:country":"ES",
    "sg:address":"Calle de Castilla La Mancha, 3",
    "sg:city":"Carpio Tajo",
    "sg:orig_category":"Empresas De Carpinter\u00cda",
    "sg:phone":"+34 925 75 73 03",
    "sg:postcode":"45533",
    "sg:province":"Toledo",
    "wof:name":"Martinez Martinez Alberto",
    "wof:placetype":"venue"
},
  "geometry": {"coordinates":[-4.4525632858,39.8913192749],"type":"Point"}
}