{
  "type": "Feature",
  "properties": {
    "addr:full":"Carrer de Quintana, 83 Sabadell Barcelona 08205",
    "addr:housenumber":"83",
    "addr:postcode":"08205",
    "addr:street":"Carrer De Quintana",
    "iso:country":"ES",
    "sg:address":"Carrer de Quintana, 83",
    "sg:city":"Sabadell",
    "sg:orig_category":"Charcuter\u00cdas (al Por Mayor)",
    "sg:phone":"+34 937 11 31 03",
    "sg:postcode":"08205",
    "sg:province":"Barcelona",
    "wof:name":"Ruiz Teba Carmen",
    "wof:placetype":"venue"
},
  "geometry": {"coordinates":[2.0990889072,41.5374717712],"type":"Point"}
}