{
  "type": "Feature",
  "properties": {
    "addr:full":"Pl Catalunya, 25 Prat Llobregat Barcelona 08820",
    "addr:housenumber":"25",
    "addr:postcode":"08820",
    "addr:street":"Pl Catalunya;Llobregat",
    "iso:country":"ES",
    "sg:address":"Pl Catalunya, 25",
    "sg:city":"Prat Llobregat",
    "sg:orig_category":"Bares, Piano",
    "sg:phone":"+34 933 70 45 60",
    "sg:postcode":"08820",
    "sg:province":"Barcelona",
    "wof:name":"Acosta Frances S.l.",
    "wof:placetype":"venue"
},
  "geometry": {"coordinates":[2.0926511288,41.3233604431],"type":"Point"}
}