{
  "type": "Feature",
  "properties": {
    "iso:country":"ES",
    "sg:address":"Ctra Dilar, 15",
    "sg:city":"Ogijares",
    "sg:orig_category":"Caf\u00c9s, Bares, Cervecer\u00cdas",
    "sg:phone":"+34 958 50 83 28",
    "sg:postcode":"18151",
    "sg:province":"Granada",
    "wof:name":"Mata Mochon Carmen",
    "wof:placetype":"venue"
},
  "geometry": {"coordinates":[-3.6051189899,37.1205368042],"type":"Point"}
}