{
  "type": "Feature",
  "properties": {
    "iso:country":"ES",
    "sg:address":"Calle de Virgen Del Amparo, 38",
    "sg:city":"Guadalajara",
    "sg:orig_category":"Agencias Y Agentes Comerciales, Representantes",
    "sg:phone":"+34 949 22 06 91",
    "sg:postcode":"19002",
    "sg:province":"Guadalajara",
    "wof:name":"Tous Guadalajara S.l.",
    "wof:placetype":"venue"
},
  "geometry": {"coordinates":[-3.1630299091,40.6278991699],"type":"Point"}
}