{
  "type": "Feature",
  "properties": {
    "iso:country":"ES",
    "sg:address":"Calle de Castilla, 7",
    "sg:city":"Laguna Duero",
    "sg:orig_category":"Tintes (fabricaci\u00d3n, Al Por Mayor)",
    "sg:phone":"+34 983 54 45 50",
    "sg:postcode":"47140",
    "sg:province":"Valladolid",
    "wof:name":"Aguilar Lopez Sonia",
    "wof:placetype":"venue"
},
  "geometry": {"coordinates":[-4.7203836441,41.5796928406],"type":"Point"}
}