{
  "type": "Feature",
  "properties": {
    "addr:full":"Avda Valladolid, 26 Tordesillas Valladolid 47100",
    "addr:housenumber":"26",
    "addr:postcode":"47100",
    "addr:street":"Avda Valladolid",
    "iso:country":"ES",
    "sg:address":"Avda Valladolid, 26",
    "sg:city":"Tordesillas",
    "sg:orig_category":"Sociedades, Compa\u00d1\u00cdas Aseguradoras",
    "sg:phone":"+34 983 77 13 15",
    "sg:postcode":"47100",
    "sg:province":"Valladolid",
    "wof:name":"Mapfre Servicios De Informatica",
    "wof:placetype":"venue"
},
  "geometry": {"coordinates":[-4.9884839058,41.5042915344],"type":"Point"}
}