{
  "type": "Feature",
  "properties": {
    "iso:country":"ES",
    "sg:address":"Calle de Maximo Garcia Garrido, 1",
    "sg:city":"Santurtzi",
    "sg:orig_category":"Complementos De Vestir (al Por Menor)",
    "sg:phone":"+34 944 62 90 76",
    "sg:postcode":"48980",
    "sg:province":"Vizcaya",
    "wof:name":"Tele-speed, S.l.",
    "wof:placetype":"venue"
},
  "geometry": {"coordinates":[-3.0326037407,43.3275604248],"type":"Point"}
}