{
  "type": "Feature",
  "properties": {
    "iso:country":"ES",
    "sg:address":"Plaz Libertad (de La), 9",
    "sg:city":"Burgos",
    "sg:orig_category":"Expertos Contables",
    "sg:phone":"+34 947 26 00 00",
    "sg:postcode":"09004",
    "sg:province":"Burgos",
    "sg:website":"www.asfico.es",
    "wof:name":"Asfico S. A.",
    "wof:placetype":"venue"
},
  "geometry": {"coordinates":[-3.6994421482,42.3412666321],"type":"Point"}
}