{
  "type": "Feature",
  "properties": {
    "addr:full":"Calle de Jardines, 2 Guarroman Ja\u00e9n 23210",
    "addr:housenumber":"2",
    "addr:postcode":"23210",
    "addr:street":"Calle De Jardines",
    "iso:country":"ES",
    "sg:address":"Calle de Jardines, 2",
    "sg:city":"Guarroman",
    "sg:orig_category":"Transportes Por V\u00cdas Navegables",
    "sg:phone":"+34 953 61 53 02",
    "sg:postcode":"23210",
    "sg:province":"Ja\u00e9n",
    "wof:name":"Granero Dorado Jose",
    "wof:placetype":"venue"
},
  "geometry": {"coordinates":[-3.6879210472,38.1813049316],"type":"Point"}
}