{
  "type": "Feature",
  "properties": {
    "addr:full":"Calle de Fernandez Del Campo, 29 Bilbao Vizcaya 48010",
    "addr:housenumber":"29",
    "addr:postcode":"48010",
    "addr:street":"Calle De Fernandez Del Campo",
    "iso:country":"ES",
    "sg:address":"Calle de Fernandez Del Campo, 29",
    "sg:city":"Bilbao",
    "sg:orig_category":"Ense\u00d1anza: Idiomas",
    "sg:phone":"+34 944 21 64 07",
    "sg:postcode":"48010",
    "sg:province":"Vizcaya",
    "wof:name":"Marina Ugarte Arbe",
    "wof:placetype":"venue"
},
  "geometry": {"coordinates":[-2.9357409477,43.2587966919],"type":"Point"}
}