{
  "type": "Feature",
  "properties": {
    "iso:country":"ES",
    "sg:address":"Calle de Mateo Garcia, 31",
    "sg:city":"Madrid",
    "sg:orig_category":"Chapister\u00cda",
    "sg:phone":"+34 913 26 42 98",
    "sg:postcode":"28017",
    "sg:province":"Madrid",
    "wof:name":"Soria Alario Gaspar",
    "wof:placetype":"venue"
},
  "geometry": {"coordinates":[-3.6527087688,40.4302711487],"type":"Point"}
}