{
  "type": "Feature",
  "properties": {
    "iso:country":"ES",
    "sg:address":"Avda Jorge Vigon, 10",
    "sg:city":"Logro\u00f1o",
    "sg:orig_category":"Lencer\u00cda Femenina, Corseter\u00cda, Trajes De Ba\u00d1o (al Por Menor)",
    "sg:phone":"+34 941 27 00 05",
    "sg:postcode":"26003",
    "sg:province":"La Rioja",
    "wof:name":"Versa C.b.",
    "wof:placetype":"venue"
},
  "geometry": {"coordinates":[-2.4442219734,42.4622879028],"type":"Point"}
}