{
  "type": "Feature",
  "properties": {
    "addr:full":"Sect Embarcaciones, 28 Tres Cantos Madrid 28760",
    "addr:housenumber":"28",
    "addr:postcode":"28760",
    "addr:street":"Embarcaciones",
    "iso:country":"ES",
    "sg:address":"Sect Embarcaciones, 28",
    "sg:city":"Tres Cantos",
    "sg:orig_category":"M\u00c9dicos: Cirug\u00cda Urol\u00d3gica",
    "sg:phone":"+34 918 04 15 56",
    "sg:postcode":"28760",
    "sg:province":"Madrid",
    "wof:name":"Idytur Urologia S.l",
    "wof:placetype":"venue"
},
  "geometry": {"coordinates":[-3.7029280663,40.5983123779],"type":"Point"}
}