{
  "type": "Feature",
  "properties": {
    "addr:full":"Plaz Espa\u00d1a, 7 Castejon Navarra 31590",
    "addr:housenumber":"7",
    "addr:postcode":"31590",
    "addr:street":"Plaz Espan\u0303A",
    "iso:country":"ES",
    "sg:address":"Plaz Espa\u00d1a, 7",
    "sg:city":"Castejon",
    "sg:orig_category":"Sociedades, Compa\u00d1\u00cdas Aseguradoras",
    "sg:phone":"+34 948 81 42 04",
    "sg:postcode":"31590",
    "sg:province":"Navarra",
    "wof:name":"Mapfre Servicios De Informatica S.a.",
    "wof:placetype":"venue"
},
  "geometry": {"coordinates":[-1.6898540258,42.1713638306],"type":"Point"}
}