{
  "type": "Feature",
  "properties": {
    "iso:country":"ES",
    "sg:address":"Calle de Alfonso Vi, 30",
    "sg:city":"Sepulveda",
    "sg:orig_category":"Explotaci\u00d3n De Canteras",
    "sg:phone":"+34 921 54 00 38",
    "sg:postcode":"40300",
    "sg:province":"Segovia",
    "wof:name":"Arranz Martin Felix",
    "wof:placetype":"venue"
},
  "geometry": {"coordinates":[-3.7485799789,41.2977790833],"type":"Point"}
}