{
  "type": "Feature",
  "properties": {
    "addr:full":"Plaz Layana, 5 Bu\u00f1ol Valencia 46360",
    "addr:housenumber":"5",
    "addr:postcode":"46360",
    "addr:street":"Plaz Layana",
    "iso:country":"ES",
    "sg:address":"Plaz Layana, 5",
    "sg:city":"Bu\u00f1ol",
    "sg:orig_category":"M\u00c9dicos: Estomatolog\u00cda",
    "sg:phone":"+34 962 50 18 00",
    "sg:postcode":"46360",
    "sg:province":"Valencia",
    "wof:name":"Gomez Cardona Juan Jose",
    "wof:placetype":"venue"
},
  "geometry": {"coordinates":[-0.7906309962,39.4240646362],"type":"Point"}
}