{
  "type": "Feature",
  "properties": {
    "addr:full":"Calle de Santa Felicidad, 24 Madrid Madrid 28017",
    "addr:housenumber":"24",
    "addr:postcode":"madrid;28017",
    "addr:street":"Calle De Santa Felicidad",
    "iso:country":"ES",
    "sg:address":"Calle de Santa Felicidad, 24",
    "sg:city":"Madrid",
    "sg:orig_category":"Peluqueros: De Se\u00d1oras",
    "sg:phone":"+34 914 05 01 16",
    "sg:postcode":"28017",
    "sg:province":"Madrid",
    "wof:name":"Sevillano Ingelmo Candelas",
    "wof:placetype":"venue"
},
  "geometry": {"coordinates":[-3.6503329277,40.4250183105],"type":"Point"}
}