{
  "type": "Feature",
  "properties": {
    "iso:country":"ES",
    "sg:address":"Plaz Vecinos, 10",
    "sg:city":"Toledo",
    "sg:orig_category":"Asociaciones, Organismos Culturales Y Socioeducativos",
    "sg:phone":"+34 925 22 42 79",
    "sg:postcode":"45003",
    "sg:province":"Toledo",
    "wof:name":"Alianza Cristiana De Jovenes De La Ymca",
    "wof:placetype":"venue"
},
  "geometry": {"coordinates":[-4.0220336914,39.8699302673],"type":"Point"}
}