{
  "type": "Feature",
  "properties": {
    "addr:full":"Carrer de Francesc Marti I M, 1 Palma Islas Baleares 07011",
    "addr:postcode":"07011",
    "addr:street":"Carrer De Francesc Marti",
    "iso:country":"ES",
    "sg:address":"Carrer de Francesc Marti I M, 1",
    "sg:city":"Palma",
    "sg:orig_category":"Bisuter\u00cda, Joyer\u00cda, Relojer\u00cda (al Por Menor)",
    "sg:phone":"+34 971 28 46 53",
    "sg:postcode":"07011",
    "sg:province":"Islas Baleares",
    "wof:name":"Guarch Vizcarro Isabel",
    "wof:placetype":"venue"
},
  "geometry": {"coordinates":[2.640171051,39.5784187317],"type":"Point"}
}