{
  "type": "Feature",
  "properties": {
    "iso:country":"ES",
    "sg:address":"Plaz Aurora (de La), 4",
    "sg:city":"Motril",
    "sg:orig_category":"Cajas De Ahorro",
    "sg:phone":"+34 958 83 33 70",
    "sg:postcode":"18600",
    "sg:province":"Granada",
    "sg:website":"www.cam.es",
    "wof:name":"Caja De Ahorros Del Mediterraneo",
    "wof:placetype":"venue"
},
  "geometry": {"coordinates":[-3.5166649818,36.7454414368],"type":"Point"}
}