{
  "type": "Feature",
  "properties": {
    "iso:country":"ES",
    "sg:address":"Calle de Miraflores, 18",
    "sg:city":"Villalpando",
    "sg:orig_category":"Librer\u00cdas",
    "sg:phone":"+34 980 66 03 99",
    "sg:postcode":"49630",
    "sg:province":"Zamora",
    "wof:name":"Casado Martinez Maria Angeles",
    "wof:placetype":"venue"
},
  "geometry": {"coordinates":[-5.4140381813,41.863117218],"type":"Point"}
}