{
  "type": "Feature",
  "properties": {
    "addr:full":"Avda Ramon Y Cajal, 44 Olivenza Badajoz 06100",
    "addr:housenumber":"44",
    "addr:postcode":"06100",
    "addr:street":"Avda Ramon Y Cajal",
    "iso:country":"ES",
    "sg:address":"Avda Ramon Y Cajal, 44",
    "sg:city":"Olivenza",
    "sg:orig_category":"Ense\u00d1anza, Formaci\u00d3n Profesional: Aprendizaje",
    "sg:phone":"+34 924 49 06 12",
    "sg:postcode":"06100",
    "sg:province":"Badajoz",
    "wof:name":"Ayuntamiento De Olivenza",
    "wof:placetype":"venue"
},
  "geometry": {"coordinates":[-7.0980839729,38.6843605042],"type":"Point"}
}