{
  "type": "Feature",
  "properties": {
    "iso:country":"ES",
    "sg:address":"Calle de Santo Cristo, 6",
    "sg:city":"Cartaya",
    "sg:orig_category":"Agentes Generales De Seguros",
    "sg:phone":"+34 959 39 20 03",
    "sg:postcode":"21450",
    "sg:province":"Huelva",
    "wof:name":"Segur Fernando S.l.",
    "wof:placetype":"venue"
},
  "geometry": {"coordinates":[-7.1551780701,37.281867981],"type":"Point"}
}