{
  "type": "Feature",
  "properties": {
    "iso:country":"ES",
    "sg:address":"Sor Mar\u00eda De Jes\u00fas, S/n",
    "sg:city":"Agreda",
    "sg:orig_category":"Cr\u00cda De Animales",
    "sg:phone":"+34 976 64 70 88",
    "sg:postcode":"42100",
    "sg:province":"Soria",
    "wof:name":"Lapizondo Garmendia Manuel",
    "wof:placetype":"venue"
},
  "geometry": {"coordinates":[-1.9248969555,41.8551826477],"type":"Point"}
}