{
  "type": "Feature",
  "properties": {
    "iso:country":"ES",
    "sg:address":"Calle de Herri Bide, 22",
    "sg:city":"Mungia",
    "sg:orig_category":"Muebles",
    "sg:phone":"+34 946 74 87 01",
    "sg:postcode":"48100",
    "sg:province":"Vizcaya",
    "wof:name":"M.v. Y M.i. Guerrero De La Mata C.b.",
    "wof:placetype":"venue"
},
  "geometry": {"coordinates":[-2.8436439037,43.3544883728],"type":"Point"}
}