{
  "type": "Feature",
  "properties": {
    "iso:country":"ES",
    "sg:address":"Rua Gandaron, 32",
    "sg:city":"Vilar",
    "sg:orig_category":"Transportes Por Carretera: Lotes Completos, Mercanc\u00cdas Diversas",
    "sg:phone":"+34 986 27 02 12",
    "sg:postcode":"36214",
    "sg:province":"Pontevedra",
    "wof:name":"Distribuciones Luga S. L.",
    "wof:placetype":"venue"
},
  "geometry": {"coordinates":[-8.7059106827,42.2124443054],"type":"Point"}
}