{
  "type": "Feature",
  "properties": {
    "iso:country":"ES",
    "sg:address":"Calle de Cesar Elguezabal, 42",
    "sg:city":"Alacant",
    "sg:orig_category":"Peluqueros: De Se\u00d1oras",
    "sg:phone":"+34 965 20 19 80",
    "sg:postcode":"03001",
    "sg:province":"Alicante",
    "wof:name":"Agullo Llinares Josefa De La Concepcion",
    "wof:placetype":"venue"
},
  "geometry": {"coordinates":[-0.4867685139,38.3460426331],"type":"Point"}
}