{
  "type": "Feature",
  "properties": {
    "iso:country":"ES",
    "sg:address":"Luga Mandin, 53",
    "sg:city":"Mandin",
    "sg:orig_category":"Grafistas",
    "sg:phone":"+34 981 63 13 37",
    "sg:postcode":"15168",
    "sg:province":"La Coru\u00f1a",
    "wof:name":"Quian Roca Juan Francisco",
    "wof:placetype":"venue"
},
  "geometry": {"coordinates":[-8.2781639099,43.3678283691],"type":"Point"}
}