{
  "type": "Feature",
  "properties": {
    "addr:full":"Carrer de Doctor Josep Castells, 11 S. Boi Llobregat Barcelona 08830",
    "addr:housenumber":"11",
    "addr:postcode":"08830",
    "addr:street":"Carrer De Doctor Josep Castells",
    "iso:country":"ES",
    "sg:address":"Carrer de Doctor Josep Castells, 11",
    "sg:city":"S. Boi Llobregat",
    "sg:orig_category":"Acero: Productos Sider\u00dargicos Y Transformados (fabricaci\u00d3n, Negocio)",
    "sg:phone":"+34 936 54 63 11",
    "sg:postcode":"08830",
    "sg:province":"Barcelona",
    "sg:website":"www.camuber.com",
    "wof:name":"Camuber S.a.",
    "wof:placetype":"venue"
},
  "geometry": {"coordinates":[2.0336689949,41.3284568787],"type":"Point"}
}