{
  "type": "Feature",
  "properties": {
    "iso:country":"ES",
    "sg:address":"Carr Jaume I, 3",
    "sg:city":"S. Francesc Formentera",
    "sg:orig_category":"Perfumer\u00cda (al Por Menor)",
    "sg:phone":"+34 971 32 33 79",
    "sg:postcode":"07860",
    "sg:province":"Islas Baleares",
    "wof:name":"Costa Torres Carmen",
    "wof:placetype":"venue"
},
  "geometry": {"coordinates":[1.4309200048,38.7072410583],"type":"Point"}
}