{
  "type": "Feature",
  "properties": {
    "iso:country":"ES",
    "sg:address":"Avda Castilla (de), 2",
    "sg:city":"Poligono De San Fernando De Henares",
    "sg:orig_category":"Inform\u00c1tica Equipo Y Programas (al Por Mayor)",
    "sg:phone":"+34 916 76 34 12",
    "sg:postcode":"28830",
    "sg:province":"Madrid",
    "sg:website":"www.brother.es",
    "wof:name":"Brother Iberia S.l.",
    "wof:placetype":"venue"
},
  "geometry": {"coordinates":[-3.5104780197,40.4524345398],"type":"Point"}
}