{
  "type": "Feature",
  "properties": {
    "iso:country":"ES",
    "sg:address":"Cra. Cards, S/n",
    "sg:city":"S. Pere Ribes",
    "sg:orig_category":"Casas De Reposo Y Convalecencia",
    "sg:phone":"+34 938 96 00 25",
    "sg:postcode":"08810",
    "sg:province":"Barcelona",
    "wof:name":"Fundacio Privada Hospital-residencia Sant Camil",
    "wof:placetype":"venue"
},
  "geometry": {"coordinates":[1.7786300182,41.256401062],"type":"Point"}
}