{
  "type": "Feature",
  "properties": {
    "iso:country":"ES",
    "sg:address":"Pla\u00c7 Sant Joan, 27",
    "sg:city":"Lleida",
    "sg:orig_category":"Cajas De Ahorro",
    "sg:phone":"+34 973 24 37 41",
    "sg:postcode":"25007",
    "sg:province":"Lleida",
    "wof:name":"Caixa D'estalvis De Catalunya",
    "wof:placetype":"venue"
},
  "geometry": {"coordinates":[0.6273959875,41.6154327393],"type":"Point"}
}