{
  "type": "Feature",
  "properties": {
    "addr:full":"Ptda Llandells, S/n Pe\u00f1iscola Castell\u00f3n 12598",
    "addr:housenumber":"s",
    "addr:postcode":"12598",
    "addr:street":"Ptda Llandells;/ N Pen\u0303Iscola Castello\u0301N",
    "iso:country":"ES",
    "sg:address":"Ptda Llandells, S/n",
    "sg:city":"Pe\u00f1iscola",
    "sg:orig_category":"Inmobiliaria (agencias)",
    "sg:phone":"+34 964 46 75 82",
    "sg:postcode":"12598",
    "sg:province":"Castell\u00f3n",
    "wof:name":"Promociones Inmobiliarias Miraflores Y Sierra Norte De Madrid S.l.",
    "wof:placetype":"venue"
},
  "geometry": {"coordinates":[-0.0456800014,39.9851417542],"type":"Point"}
}