{
  "type": "Feature",
  "properties": {
    "addr:full":"Carr Cortes Roig, 3 Benidorm Alicante 03500",
    "addr:housenumber":"3",
    "addr:postcode":"03500",
    "addr:street":"Carr Cortes Roig",
    "iso:country":"ES",
    "sg:address":"Carr Cortes Roig, 3",
    "sg:city":"Benidorm",
    "sg:orig_category":"Inmobiliaria (agencias)",
    "sg:phone":"+34 966 80 57 08",
    "sg:postcode":"03500",
    "sg:province":"Alicante",
    "wof:name":"Beltran Y Beltran Gestion De Inmuebles S.l.",
    "wof:placetype":"venue"
},
  "geometry": {"coordinates":[-0.1743289977,38.5408058167],"type":"Point"}
}