{
  "type": "Feature",
  "properties": {
    "addr:full":"Calle de Doctor Manuel Candela, 60 Valencia Valencia 46021",
    "addr:housenumber":"60",
    "addr:postcode":"46021",
    "addr:street":"Calle De Doctor Manuel Candela",
    "iso:country":"ES",
    "sg:address":"Calle de Doctor Manuel Candela, 60",
    "sg:city":"Valencia",
    "sg:orig_category":"Estancos",
    "sg:phone":"+34 963 56 03 12",
    "sg:postcode":"46021",
    "sg:province":"Valencia",
    "wof:name":"Diez Gil Fernando",
    "wof:placetype":"venue"
},
  "geometry": {"coordinates":[-0.3487873971,39.4713058472],"type":"Point"}
}