{
  "type": "Feature",
  "properties": {
    "addr:full":"Calle de San Pascual, 22 Orihuela Alicante 03300",
    "addr:housenumber":"22",
    "addr:postcode":"03300",
    "addr:street":"Calle De San Pascual",
    "iso:country":"ES",
    "sg:address":"Calle de San Pascual, 22",
    "sg:city":"Orihuela",
    "sg:orig_category":"Fabricaci\u00d3n De Sobres, Bolsas Y Fundas",
    "sg:phone":"+34 965 30 14 98",
    "sg:postcode":"03300",
    "sg:province":"Alicante",
    "wof:name":"Corbalan Hernando Maria",
    "wof:placetype":"venue"
},
  "geometry": {"coordinates":[-0.9462260008,38.0842094421],"type":"Point"}
}