{
  "type": "Feature",
  "properties": {
    "iso:country":"ES",
    "sg:address":"Calle de Antonio Machado, 23",
    "sg:city":"Guardamar Segura",
    "sg:orig_category":"Molduras, Junquillos, Listones Y Molduras Perforadas",
    "sg:phone":"+34 965 72 92 24",
    "sg:postcode":"03140",
    "sg:province":"Alicante",
    "wof:name":"Berna Lopez Antonio",
    "wof:placetype":"venue"
},
  "geometry": {"coordinates":[-0.6540290117,38.086681366],"type":"Point"}
}