{
  "type": "Feature",
  "properties": {
    "addr:full":"Calle de Gondola, 2 Torrenueva Granada 18720",
    "addr:housenumber":"2",
    "addr:postcode":"18720",
    "addr:street":"Calle De Gondola",
    "iso:country":"ES",
    "sg:address":"Calle de Gondola, 2",
    "sg:city":"Torrenueva",
    "sg:orig_category":"Institutos De Belleza",
    "sg:phone":"+34 958 83 59 25",
    "sg:postcode":"18720",
    "sg:province":"Granada",
    "wof:name":"Ferres Rodriguez Maria Del Mar",
    "wof:placetype":"venue"
},
  "geometry": {"coordinates":[-3.4898819923,36.7043685913],"type":"Point"}
}