{
  "type": "Feature",
  "properties": {
    "addr:full":"Calle de Canario, 5 Pozuelo Toledo 45210",
    "addr:housenumber":"5",
    "addr:postcode":"45210",
    "addr:street":"Calle De Canario",
    "iso:country":"ES",
    "sg:address":"Calle de Canario, 5",
    "sg:city":"Pozuelo",
    "sg:orig_category":"Molduras, Junquillos, Listones Y Molduras Perforadas",
    "sg:phone":"+34 925 55 31 85",
    "sg:postcode":"45210",
    "sg:province":"Toledo",
    "wof:name":"Nicolas Sacristan Aurora",
    "wof:placetype":"venue"
},
  "geometry": {"coordinates":[-3.8944034576,40.090133667],"type":"Point"}
}