{
  "type": "Feature",
  "properties": {
    "iso:country":"ES",
    "sg:address":"Calle de Platon, 15",
    "sg:city":"Pto. Rosario",
    "sg:orig_category":"Promotores Constructores",
    "sg:phone":"+34 928 85 20 37",
    "sg:postcode":"35600",
    "sg:province":"Las Palmas",
    "wof:name":"Temejereque S.l.",
    "wof:placetype":"venue"
},
  "geometry": {"coordinates":[-13.8632297516,28.5018634796],"type":"Point"}
}