{
  "type": "Feature",
  "properties": {
    "addr:full":"Calle de Ciaurriz, 35 Mairena Aljarafe Sevilla 41927",
    "addr:housenumber":"35",
    "addr:postcode":"41927",
    "addr:street":"Calle De Ciaurriz",
    "iso:country":"ES",
    "sg:address":"Calle de Ciaurriz, 35",
    "sg:city":"Mairena Aljarafe",
    "sg:orig_category":"Fabricaci\u00d3n De Bibliotecas Y Estanter\u00cdas",
    "sg:phone":"+34 954 17 10 55",
    "sg:postcode":"41927",
    "sg:province":"Sevilla",
    "sg:website":"www.zaymor.com",
    "wof:name":"De Zayas Fernandez Daniel",
    "wof:placetype":"venue"
},
  "geometry": {"coordinates":[-6.0364990234,37.3392982483],"type":"Point"}
}