{
  "type": "Feature",
  "properties": {
    "iso:country":"ES",
    "sg:address":"Calle de Calzadas, 53",
    "sg:city":"Burgos",
    "sg:orig_category":"Peluquer\u00cdas, Peluquer\u00cda Mixta",
    "sg:phone":"+34 947 20 56 60",
    "sg:postcode":"09004",
    "sg:province":"Burgos",
    "wof:name":"Criado Urrutia Roberto",
    "wof:placetype":"venue"
},
  "geometry": {"coordinates":[-3.6884102821,42.3449020386],"type":"Point"}
}