{
  "type": "Feature",
  "properties": {
    "iso:country":"ES",
    "sg:address":"Calle de Cea Bermudez, 20",
    "sg:city":"Madrid",
    "sg:orig_category":"Arquitectos",
    "sg:phone":"+34 915 33 36 65",
    "sg:postcode":"28003",
    "sg:province":"Madrid",
    "wof:name":"Zapata Gonzalez Oscar",
    "wof:placetype":"venue"
},
  "geometry": {"coordinates":[-3.7079510689,40.4388122559],"type":"Point"}
}