{
  "type": "Feature",
  "properties": {
    "addr:full":"Calle de Zabalgain Kalea, 23 Zizur Mayor Navarra 31180",
    "addr:housenumber":"23",
    "addr:postcode":"31180",
    "addr:street":"Calle De Zabalgain Kalea",
    "iso:country":"ES",
    "sg:address":"Calle de Zabalgain Kalea, 23",
    "sg:city":"Zizur Mayor",
    "sg:orig_category":"Alquiler De V\u00cddeo",
    "sg:phone":"+34 948 18 54 17",
    "sg:postcode":"31180",
    "sg:province":"Navarra",
    "wof:name":"Cruz Lopez Pedro",
    "wof:placetype":"venue"
},
  "geometry": {"coordinates":[-1.6936680079,42.7872505188],"type":"Point"}
}