{
  "type": "Feature",
  "properties": {
    "addr:full":"Carr Hospital, 12 S. Hilari Sacalm Girona 17403",
    "addr:housenumber":"12",
    "addr:postcode":"17403",
    "addr:street":"Carr Hospital;S. Hilari",
    "iso:country":"ES",
    "sg:address":"Carr Hospital, 12",
    "sg:city":"S. Hilari Sacalm",
    "sg:orig_category":"Asesor\u00cda, Estudio Y Control Medioambiental",
    "sg:phone":"+34 972 86 91 27",
    "sg:postcode":"17403",
    "sg:province":"Girona",
    "wof:name":"Les Guilleries Associacio De Promocio I Educacio Mediambiental",
    "wof:placetype":"venue"
},
  "geometry": {"coordinates":[2.5119540691,41.8778266907],"type":"Point"}
}