{
  "type": "Feature",
  "properties": {
    "addr:full":"Ctra Hiniesta, 32 Zamora Zamora 49025",
    "addr:housenumber":"32",
    "addr:postcode":"49025",
    "addr:street":"Ctra Hiniesta",
    "iso:country":"ES",
    "sg:address":"Ctra Hiniesta, 32",
    "sg:city":"Zamora",
    "sg:orig_category":"Reparaciones Y Remolcado De Veh\u00cdculos",
    "sg:phone":"+34 980 52 58 81",
    "sg:postcode":"49025",
    "sg:province":"Zamora",
    "wof:name":"Martin Temprano Jose Antonio",
    "wof:placetype":"venue"
},
  "geometry": {"coordinates":[-5.7517471313,41.5091819763],"type":"Point"}
}