{
  "type": "Feature",
  "properties": {
    "iso:country":"ES",
    "sg:address":"Carr Francesc Layret, 138",
    "sg:city":"Badalona",
    "sg:orig_category":"Droguer\u00cdas (al Por Menor)",
    "sg:phone":"+34 933 89 14 24",
    "sg:postcode":"08911",
    "sg:province":"Barcelona",
    "wof:name":"Calvache Mu\u00f1oz Antonio",
    "wof:placetype":"venue"
},
  "geometry": {"coordinates":[2.2498140335,41.4520492554],"type":"Point"}
}