{
  "type": "Feature",
  "properties": {
    "addr:full":"Marzo De Abaixo, S/n Grixoa La Coru\u00f1a 15898",
    "addr:housenumber":"s / n",
    "addr:postcode":"15898",
    "addr:street":"La Corun\u0303A",
    "iso:country":"ES",
    "sg:address":"Marzo De Abaixo, S/n",
    "sg:city":"Grixoa",
    "sg:orig_category":"Aguas (distribuci\u00d3n, Servicios)",
    "sg:phone":"+34 981 57 27 23",
    "sg:postcode":"15898",
    "sg:province":"La Coru\u00f1a",
    "wof:name":"Aquagest S.a.",
    "wof:placetype":"venue"
},
  "geometry": {"coordinates":[-9.0792064667,43.0409088135],"type":"Point"}
}