{
  "type": "Feature",
  "properties": {
    "iso:country":"ES",
    "sg:address":"Carrer de Vila Cinca, 146",
    "sg:city":"Sabadell",
    "sg:orig_category":"Ebanister\u00cda",
    "sg:phone":"+34 937 16 58 78",
    "sg:postcode":"08208",
    "sg:province":"Barcelona",
    "wof:name":"Art D'model S.%.",
    "wof:placetype":"venue"
},
  "geometry": {"coordinates":[2.1064174175,41.5571594238],"type":"Point"}
}