{
  "type": "Feature",
  "properties": {
    "iso:country":"ES",
    "sg:address":"Calle de Primavera, 4",
    "sg:city":"Matas-pinar-monte Rozas",
    "sg:orig_category":"Pintores",
    "sg:phone":"+34 916 30 09 87",
    "sg:postcode":"28290",
    "sg:province":"Madrid",
    "wof:name":"Galea Barjola Juan Antonio",
    "wof:placetype":"venue"
},
  "geometry": {"coordinates":[-3.8940079212,40.5618934631],"type":"Point"}
}