{
  "type": "Feature",
  "properties": {
    "iso:country":"ES",
    "sg:address":"Av Santander",
    "sg:city":"Playa S. Juan-condomina",
    "sg:orig_category":"Restaurantes",
    "sg:phone":"+34 965 15 03 52",
    "sg:postcode":"03540",
    "sg:province":"Alicante",
    "wof:name":"Lozano Esteve Agustin",
    "wof:placetype":"venue"
},
  "geometry": {"coordinates":[-0.4143849909,38.375],"type":"Point"}
}