{
  "type": "Feature",
  "properties": {
    "iso:country":"ES",
    "sg:address":"Calle de Fernandez De Los Rios, 18",
    "sg:city":"Madrid",
    "sg:orig_category":"Centros De Coordinaci\u00d3n",
    "sg:phone":"+34 914 47 66 27",
    "sg:postcode":"28015",
    "sg:province":"Madrid",
    "wof:name":"Gestoria Administrativa Seprofisa Sl",
    "wof:placetype":"venue"
},
  "geometry": {"coordinates":[-3.7060358524,40.4349937439],"type":"Point"}
}