{
  "type": "Feature",
  "properties": {
    "addr:full":"Calle de Gijon, 20 Aviles Asturias 33461",
    "addr:housenumber":"20",
    "addr:postcode":"33461",
    "addr:street":"Calle De Gijon",
    "iso:country":"ES",
    "sg:address":"Calle de Gijon, 20",
    "sg:city":"Aviles",
    "sg:orig_category":"Almacenes Para Venta: Muebles Y Varios",
    "sg:phone":"+34 985 54 75 23",
    "sg:postcode":"33461",
    "sg:province":"Asturias",
    "wof:name":"Barril De La Vega Silvio Onesimo Jorge",
    "wof:placetype":"venue"
},
  "geometry": {"coordinates":[-5.9179420471,43.5508079529],"type":"Point"}
}