{
  "type": "Feature",
  "properties": {
    "addr:full":"Carrer de Torrent (portals Nous), 19 Portals Nous Islas Baleares 07181",
    "addr:housenumber":"19",
    "addr:postcode":"07181",
    "addr:street":"Carrer De Torrent Portals Nous",
    "iso:country":"ES",
    "sg:address":"Carrer de Torrent (portals Nous), 19",
    "sg:city":"Portals Nous",
    "sg:orig_category":"Asilos De Ancianos. Centros Privados",
    "sg:phone":"+34 971 67 91 47",
    "sg:postcode":"07181",
    "sg:province":"Islas Baleares",
    "wof:name":"Obralar S.l.",
    "wof:placetype":"venue"
},
  "geometry": {"coordinates":[2.5707309246,39.5335083008],"type":"Point"}
}