{
  "type": "Feature",
  "properties": {
    "addr:full":"Calle de Ebro, 21 Arroyo De La Encomienda Valladolid 47195",
    "addr:housenumber":"21",
    "addr:postcode":"47195",
    "addr:street":"Calle De Ebro",
    "iso:country":"ES",
    "sg:address":"Calle de Ebro, 21",
    "sg:city":"Arroyo De La Encomienda",
    "sg:orig_category":"Productos Fitosanitarios (negocio, Aplicaci\u00d3n)",
    "sg:phone":"+34 983 40 91 45",
    "sg:postcode":"47195",
    "sg:province":"Valladolid",
    "wof:name":"Suministros Rescate Valladolid S.l.l.",
    "wof:placetype":"venue"
},
  "geometry": {"coordinates":[-4.773378849,41.6290588379],"type":"Point"}
}