{
  "type": "Feature",
  "properties": {
    "addr:full":"Olivar, S/n Beniajan Murcia 30570",
    "addr:housenumber":"s / n",
    "addr:postcode":"30570",
    "iso:country":"ES",
    "sg:address":"Olivar, S/n",
    "sg:city":"Beniajan",
    "sg:orig_category":"Carros Elevadores, Carros De Operaciones Portuarias",
    "sg:phone":"+34 968 82 23 79",
    "sg:postcode":"30570",
    "sg:province":"Murcia",
    "wof:name":"Elevamur S.l.",
    "wof:placetype":"venue"
},
  "geometry": {"coordinates":[-1.0771340132,37.9602661133],"type":"Point"}
}