{
  "type": "Feature",
  "properties": {
    "addr:full":"Avda Conde Ansurez, 2 Sahagun Le\u00f3n 24320",
    "addr:housenumber":"2",
    "addr:postcode":"24320",
    "addr:street":"Avda Conde Ansurez;Leo\u0301N",
    "iso:country":"ES",
    "sg:address":"Avda Conde Ansurez, 2",
    "sg:city":"Sahagun",
    "sg:orig_category":"Sindicatos De Trabajadores",
    "sg:phone":"+34 987 78 11 54",
    "sg:postcode":"24320",
    "sg:province":"Le\u00f3n",
    "wof:name":"Coag Leon",
    "wof:placetype":"venue"
},
  "geometry": {"coordinates":[-5.0239691734,42.3690338135],"type":"Point"}
}