{
  "type": "Feature",
  "properties": {
    "iso:country":"ES",
    "sg:address":"Calle de Dibujante Pepe Cortes, 10",
    "sg:city":"Villena",
    "sg:orig_category":"Inform\u00c1tica: Soportes De Informaci\u00d3n, Suministros & Accesorios",
    "sg:phone":"+34 965 81 42 31",
    "sg:postcode":"03400",
    "sg:province":"Alicante",
    "wof:name":"Gesta Informatica Sociedad Coop Valenciana",
    "wof:placetype":"venue"
},
  "geometry": {"coordinates":[-0.8594968915,38.6343574524],"type":"Point"}
}