{
  "type": "Feature",
  "properties": {
    "addr:full":"Calle de San Agustin, 2 Le\u00f3n Le\u00f3n 24001",
    "addr:housenumber":"2",
    "addr:postcode":"24001",
    "addr:street":"Calle De San Agustin;Leo\u0301N",
    "iso:country":"ES",
    "sg:address":"Calle de San Agustin, 2",
    "sg:city":"Le\u00f3n",
    "sg:orig_category":"Estancos",
    "sg:phone":"+34 987 22 10 15",
    "sg:postcode":"24001",
    "sg:province":"Le\u00f3n",
    "wof:name":"Abad Osle Ana Isabel",
    "wof:placetype":"venue"
},
  "geometry": {"coordinates":[-5.574637,42.598587],"type":"Point"}
}