{
  "type": "Feature",
  "properties": {
    "iso:country":"ES",
    "sg:address":"Calle de Alejandro Sanchez, 12",
    "sg:city":"Madrid",
    "sg:orig_category":"Electricidad: Equipos Industriales, Componentes (fabricaci\u00d3n)",
    "sg:phone":"+34 914 72 61 22",
    "sg:postcode":"28019",
    "sg:province":"Madrid",
    "wof:name":"Casas Pulido Maximo De Las",
    "wof:placetype":"venue"
},
  "geometry": {"coordinates":[-3.7263219357,40.3908424377],"type":"Point"}
}