{
  "type": "Feature",
  "properties": {
    "addr:full":"Calle de San Fernando, 7 Casas Nuevas Las Palmas 35214",
    "addr:housenumber":"7",
    "addr:postcode":"35214",
    "addr:street":"Calle De San Fernando",
    "iso:country":"ES",
    "sg:address":"Calle de San Fernando, 7",
    "sg:city":"Casas Nuevas",
    "sg:orig_category":"Florister\u00cdas",
    "sg:phone":"+34 928 70 61 04",
    "sg:postcode":"35214",
    "sg:province":"Las Palmas",
    "wof:name":"Sosa Hernandez Rosario",
    "wof:placetype":"venue"
},
  "geometry": {"coordinates":[-15.4300060272,28.1248226166],"type":"Point"}
}