{
  "type": "Feature",
  "properties": {
    "iso:country":"ES",
    "sg:address":"Calle de San Juan, 7",
    "sg:city":"Mazarron",
    "sg:orig_category":"Ropa Para Se\u00d1oras Y Caballeros (al Por Menor)",
    "sg:phone":"+34 968 33 32 93",
    "sg:postcode":"30870",
    "sg:province":"Murcia",
    "wof:name":"Enigma Modas S.l.l.",
    "wof:placetype":"venue"
},
  "geometry": {"coordinates":[-1.3146400452,37.5977973938],"type":"Point"}
}