{
  "type": "Feature",
  "properties": {
    "iso:country":"ES",
    "sg:address":"Calle de Reina (la), 3",
    "sg:city":"Arcos Frontera",
    "sg:orig_category":"Asesor\u00cda Fiscal Y Jur\u00cddica",
    "sg:phone":"+34 956 70 09 13",
    "sg:postcode":"11630",
    "sg:province":"C\u00e1diz",
    "wof:name":"Torres Gallego Jose Maria",
    "wof:placetype":"venue"
},
  "geometry": {"coordinates":[-5.8136739731,36.7513084412],"type":"Point"}
}