{
  "type": "Feature",
  "properties": {
    "iso:country":"ES",
    "sg:address":"Calle de Nou, 23",
    "sg:city":"Banyeres Mariola",
    "sg:orig_category":"Partidos Pol\u00cdticos",
    "sg:phone":"+34 966 56 76 58",
    "sg:postcode":"03450",
    "sg:province":"Alicante",
    "wof:name":"Partido Popular",
    "wof:placetype":"venue"
},
  "geometry": {"coordinates":[-0.6572629809,38.7146568298],"type":"Point"}
}