{
  "type": "Feature",
  "properties": {
    "addr:full":"Av Tres-cents U, 104 Castelldefels Barcelona 08860",
    "addr:postcode":"08860",
    "addr:street":"Av Tres-Cents",
    "iso:country":"ES",
    "sg:address":"Av Tres-cents U, 104",
    "sg:city":"Castelldefels",
    "sg:orig_category":"Cables Y Hilos El\u00c9ctricos (fabricaci\u00d3n, Al Por Mayor)",
    "sg:phone":"+34 936 36 46 46",
    "sg:postcode":"08860",
    "sg:province":"Barcelona",
    "wof:name":"Cablering S.l.",
    "wof:placetype":"venue"
},
  "geometry": {"coordinates":[1.9784450531,41.2793083191],"type":"Point"}
}