{
  "type": "Feature",
  "properties": {
    "addr:full":"Calle de General Sanjurjo, 14 Sanlucar Guadiana Huelva 21595",
    "addr:housenumber":"14",
    "addr:postcode":"21595",
    "addr:street":"Calle De General Sanjurjo",
    "iso:country":"ES",
    "sg:address":"Calle de General Sanjurjo, 14",
    "sg:city":"Sanlucar Guadiana",
    "sg:orig_category":"Venta, Instalaci\u00d3n De Cocinas",
    "sg:phone":"+34 959 38 81 05",
    "sg:postcode":"21595",
    "sg:province":"Huelva",
    "wof:name":"Sistiaga Conde Rafael",
    "wof:placetype":"venue"
},
  "geometry": {"coordinates":[-7.466794014,37.4738693237],"type":"Point"}
}