{
  "type": "Feature",
  "properties": {
    "addr:full":"Rond Caballero De La Mancha, 123 Madrid Madrid 28034",
    "addr:housenumber":"123",
    "addr:postcode":"28034",
    "addr:street":"Rond Caballero De La Mancha",
    "iso:country":"ES",
    "sg:address":"Rond Caballero De La Mancha, 123",
    "sg:city":"Madrid",
    "sg:orig_category":"Perfumer\u00cda (al Por Menor)",
    "sg:phone":"+34 917 35 36 04",
    "sg:postcode":"28034",
    "sg:province":"Madrid",
    "wof:name":"Jovisar S.l.",
    "wof:placetype":"venue"
},
  "geometry": {"coordinates":[-3.6886610985,40.5012168884],"type":"Point"}
}