{
  "type": "Feature",
  "properties": {
    "iso:country":"ES",
    "sg:address":"Plaz Mercado, S/n",
    "sg:city":"Salamanca",
    "sg:orig_category":"Carnicer\u00cdas, Carnicer\u00cdas",
    "sg:phone":"+34 923 26 93 29",
    "sg:postcode":"37001",
    "sg:province":"Salamanca",
    "wof:name":"Carniceria Lopez Caselles",
    "wof:placetype":"venue"
},
  "geometry": {"coordinates":[-5.6633839607,40.9647140503],"type":"Point"}
}