{
  "type": "Feature",
  "properties": {
    "iso:country":"ES",
    "sg:address":"Calle de Faisan, 3",
    "sg:city":"Granada",
    "sg:orig_category":"Droguer\u00cdas (al Por Menor)",
    "sg:phone":"+34 958 20 11 86",
    "sg:postcode":"18014",
    "sg:province":"Granada",
    "wof:name":"Droguerias Y Perfumerias Ana Pilar S.l.",
    "wof:placetype":"venue"
},
  "geometry": {"coordinates":[-3.610419035,37.1864891052],"type":"Point"}
}