{
  "type": "Feature",
  "properties": {
    "iso:country":"ES",
    "sg:address":"La Fuente, 11",
    "sg:city":"Zalamea Real",
    "sg:orig_category":"Supermercados Y Hipermercados",
    "sg:phone":"+34 959 56 22 57",
    "sg:postcode":"21640",
    "sg:province":"Huelva",
    "wof:name":"Alcora Dis S.l.",
    "wof:placetype":"venue"
},
  "geometry": {"coordinates":[-6.657081604,37.6809234619],"type":"Point"}
}