{
  "type": "Feature",
  "properties": {
    "addr:full":"Calle de Real (del), 4 Colmenar Viejo Madrid 28770",
    "addr:postcode":"28770",
    "addr:street":"Calle De Real Del",
    "iso:country":"ES",
    "sg:address":"Calle de Real (del), 4",
    "sg:city":"Colmenar Viejo",
    "sg:orig_category":"Agencias De Viajes",
    "sg:phone":"+34 918 45 60 01",
    "sg:postcode":"28770",
    "sg:province":"Madrid",
    "sg:website":"www.halconviajes.com",
    "wof:name":"Viajes Halcon S.a.",
    "wof:placetype":"venue"
},
  "geometry": {"coordinates":[-3.7657399178,40.6592788696],"type":"Point"}
}