{
  "type": "Feature",
  "properties": {
    "iso:country":"ES",
    "sg:address":"Carr Sant Vicen\u00c7, 30",
    "sg:city":"Figueres",
    "sg:orig_category":"Asociaciones, Organismos Culturales Y Socioeducativos",
    "sg:phone":"+34 972 67 03 91",
    "sg:postcode":"17600",
    "sg:province":"Girona",
    "wof:name":"Institucio Alt Empordanesa Per La Defensa I Estudi De La Natura",
    "wof:placetype":"venue"
},
  "geometry": {"coordinates":[2.9599523544,42.2650146484],"type":"Point"}
}