{
  "type": "Feature",
  "properties": {
    "addr:full":"Calle de Echegaray, 17 Caudete Albacete 02660",
    "addr:housenumber":"17",
    "addr:postcode":"02660",
    "addr:street":"Calle De Echegaray",
    "iso:country":"ES",
    "sg:address":"Calle de Echegaray, 17",
    "sg:city":"Caudete",
    "sg:orig_category":"\u00d3ptica: Instrumentos (fabricaci\u00d3n)",
    "sg:phone":"+34 965 82 59 21",
    "sg:postcode":"02660",
    "sg:province":"Albacete",
    "wof:name":"Optica Caudete S.l.",
    "wof:placetype":"venue"
},
  "geometry": {"coordinates":[-0.9846463799,38.7038993835],"type":"Point"}
}