{
  "type": "Feature",
  "properties": {
    "addr:full":"Calle de Velero (del), 6 Arganda Madrid 28500",
    "addr:housenumber":"6",
    "addr:postcode":"28500",
    "addr:street":"Calle De Velero Del",
    "iso:country":"ES",
    "sg:address":"Calle de Velero (del), 6",
    "sg:city":"Arganda",
    "sg:orig_category":"C\u00c1maras De Comercio E Industria, Oficios, Agricultura",
    "sg:phone":"+34 918 74 77 12",
    "sg:postcode":"28500",
    "sg:province":"Madrid",
    "wof:name":"Torreblanca Campos Santiago",
    "wof:placetype":"venue"
},
  "geometry": {"coordinates":[-3.4338541031,40.2953834534],"type":"Point"}
}