{
  "type": "Feature",
  "properties": {
    "addr:full":"Calle de Chimidas, 20 Playa Honda Las Palmas 35509",
    "addr:housenumber":"20",
    "addr:postcode":"35509",
    "addr:street":"Calle De Chimidas",
    "iso:country":"ES",
    "sg:address":"Calle de Chimidas, 20",
    "sg:city":"Playa Honda",
    "sg:orig_category":"Flores Y Plantas Naturales (al Por Mayor)",
    "sg:phone":"+34 928 82 16 49",
    "sg:postcode":"35509",
    "sg:province":"Las Palmas",
    "wof:name":"Lanzarotes Flores S.l.",
    "wof:placetype":"venue"
},
  "geometry": {"coordinates":[-13.5917158127,28.9558792114],"type":"Point"}
}