{
  "type": "Feature",
  "properties": {
    "addr:full":"Calle de Blanca Paloma, 7 Fuengirola M\u00e1laga 29640",
    "addr:housenumber":"7",
    "addr:postcode":"29640",
    "addr:street":"Calle De Blanca Paloma;Ma\u0301Laga",
    "iso:country":"ES",
    "sg:address":"Calle de Blanca Paloma, 7",
    "sg:city":"Fuengirola",
    "sg:orig_category":"Promotores Constructores",
    "sg:phone":"+34 952 47 97 64",
    "sg:postcode":"29640",
    "sg:province":"M\u00e1laga",
    "wof:name":"A.m.g. Promotions & Investment S.l.",
    "wof:placetype":"venue"
},
  "geometry": {"coordinates":[-4.6241025925,36.5468940735],"type":"Point"}
}