{
  "type": "Feature",
  "properties": {
    "addr:full":"Calle de Estocolmo, 7 Torrejon Ardoz Madrid 28850",
    "addr:housenumber":"7",
    "addr:postcode":"28850",
    "addr:street":"Calle De Estocolmo",
    "iso:country":"ES",
    "sg:address":"Calle de Estocolmo, 7",
    "sg:city":"Torrejon Ardoz",
    "sg:orig_category":"Bricolaje, Herramientas (al Por Menor)",
    "sg:phone":"+34 916 56 65 02",
    "sg:postcode":"28850",
    "sg:province":"Madrid",
    "wof:name":"Adamuz Palomares Concepcion",
    "wof:placetype":"venue"
},
  "geometry": {"coordinates":[-3.4686820507,40.4618225098],"type":"Point"}
}