{
  "type": "Feature",
  "properties": {
    "iso:country":"ES",
    "sg:address":"Calle de Tetuan, 15",
    "sg:city":"Linares",
    "sg:orig_category":"Rectificaci\u00d3n, Mecanizado, Fresado",
    "sg:phone":"+34 953 69 31 57",
    "sg:postcode":"23700",
    "sg:province":"Ja\u00e9n",
    "wof:name":"Ba\u00f1os Martos Juan",
    "wof:placetype":"venue"
},
  "geometry": {"coordinates":[-3.636936903,38.0969429016],"type":"Point"}
}