{
  "type": "Feature",
  "properties": {
    "addr:full":"Carrer de Angel Guimera, 19 Manresa Barcelona 08241",
    "addr:housenumber":"19",
    "addr:postcode":"08241",
    "addr:street":"Carrer De Angel Guimera",
    "iso:country":"ES",
    "sg:address":"Carrer de Angel Guimera, 19",
    "sg:city":"Manresa",
    "sg:orig_category":"Pod\u00d3logos: Pedicuros",
    "sg:phone":"+34 938 72 11 64",
    "sg:postcode":"08241",
    "sg:province":"Barcelona",
    "wof:name":"Navarro Pe\u00f1a Cristina",
    "wof:placetype":"venue"
},
  "geometry": {"coordinates":[1.8243429661,41.7264633179],"type":"Point"}
}