{
  "type": "Feature",
  "properties": {
    "iso:country":"ES",
    "sg:address":"Calle de Foncalada, 3",
    "sg:city":"Oviedo",
    "sg:orig_category":"Abogados",
    "sg:phone":"+34 984 18 67 94",
    "sg:postcode":"33002",
    "sg:province":"Asturias",
    "wof:name":"Belarmina Gonzalez Fernandez",
    "wof:placetype":"venue"
},
  "geometry": {"coordinates":[-5.8470869064,43.3646583557],"type":"Point"}
}