{
  "type": "Feature",
  "properties": {
    "iso:country":"ES",
    "sg:address":"Carrer de Renclusa, 39",
    "sg:city":"Hospitalet Llobregat",
    "sg:orig_category":"Quincaller\u00cda (al Por Menor)",
    "sg:phone":"+34 934 37 32 20",
    "sg:postcode":"08905",
    "sg:province":"Barcelona",
    "wof:name":"Lopez Garcia Salvador",
    "wof:placetype":"venue"
},
  "geometry": {"coordinates":[2.1067559719,41.3705749512],"type":"Point"}
}