{
  "type": "Feature",
  "properties": {
    "iso:country":"ES",
    "sg:address":"Calle de Fernan Gonzalez, 52",
    "sg:city":"Madrid",
    "sg:orig_category":"Centros Empresariales",
    "sg:phone":"+34 915 04 68 62",
    "sg:postcode":"28009",
    "sg:province":"Madrid",
    "wof:name":"Moratinos Del Olmo Ricardo",
    "wof:placetype":"venue"
},
  "geometry": {"coordinates":[-3.6747660637,40.4189872742],"type":"Point"}
}