{
  "type": "Feature",
  "properties": {
    "iso:country":"ES",
    "sg:address":"Calle de Pozo De Los Humos, 59",
    "sg:city":"Salamanca",
    "sg:orig_category":"Alimentaci\u00d3n General (al Por Menor)",
    "sg:phone":"+34 923 19 40 86",
    "sg:postcode":"37008",
    "sg:province":"Salamanca",
    "wof:name":"Exclusivas Velasco S.l.",
    "wof:placetype":"venue"
},
  "geometry": {"coordinates":[-5.6618089676,40.9391517639],"type":"Point"}
}