{
  "type": "Feature",
  "properties": {
    "iso:country":"ES",
    "sg:address":"Calle de Antonio De Leyva, 16",
    "sg:city":"Madrid",
    "sg:orig_category":"Aguas (distribuci\u00d3n, Servicios)",
    "sg:phone":"+34 915 60 03 16",
    "sg:postcode":"28019",
    "sg:province":"Madrid",
    "wof:name":"Basilio Rivera E Hijos S.a",
    "wof:placetype":"venue"
},
  "geometry": {"coordinates":[-3.715722084,40.3942604065],"type":"Point"}
}