{
  "type": "Feature",
  "properties": {
    "addr:full":"Azkota, S/n Azkota Navarra 31746",
    "addr:postcode":"31746",
    "addr:street":"Azkota S / N Azkota Navarra",
    "iso:country":"ES",
    "sg:address":"Azkota, S/n",
    "sg:city":"Azkota",
    "sg:orig_category":"Producci\u00d3n, Venta De Productos De Agricultura Biol\u00d3gica",
    "sg:phone":"+34 948 45 04 50",
    "sg:postcode":"31746",
    "sg:province":"Navarra",
    "wof:name":"Sat Azkarate Numero 639 Na",
    "wof:placetype":"venue"
},
  "geometry": {"coordinates":[-1.7427090406,43.1255569458],"type":"Point"}
}