{
  "type": "Feature",
  "properties": {
    "addr:full":"Calle de Alfonso Paso, 8 Pozo-estrecho Murcia 30594",
    "addr:housenumber":"8",
    "addr:postcode":"30594",
    "addr:street":"Calle De Alfonso Paso",
    "iso:country":"ES",
    "sg:address":"Calle de Alfonso Paso, 8",
    "sg:city":"Pozo-estrecho",
    "sg:orig_category":"Centros Empresariales",
    "sg:phone":"+34 968 55 63 25",
    "sg:postcode":"30594",
    "sg:province":"Murcia",
    "wof:name":"Serrano Mateo Francisco",
    "wof:placetype":"venue"
},
  "geometry": {"coordinates":[-0.9947860241,37.7105026245],"type":"Point"}
}