{
  "type": "Feature",
  "properties": {
    "addr:full":"Calle de Pintor Zuloaga, 21 Cadiz C\u00e1diz 11010",
    "addr:housenumber":"21",
    "addr:postcode":"11010",
    "addr:street":"Calle De Pintor Zuloaga",
    "iso:country":"ES",
    "sg:address":"Calle de Pintor Zuloaga, 21",
    "sg:city":"Cadiz",
    "sg:orig_category":"Ropa De Hogar (al Por Menor)",
    "sg:phone":"+34 956 28 51 99",
    "sg:postcode":"11010",
    "sg:province":"C\u00e1diz",
    "wof:name":"Gonzalez Delgado Manuel",
    "wof:placetype":"venue"
},
  "geometry": {"coordinates":[-6.2752580643,36.5060424805],"type":"Point"}
}