{
  "type": "Feature",
  "properties": {
    "iso:country":"ES",
    "sg:address":"Calle de Santa Eulalia, 11",
    "sg:city":"Santurtzi",
    "sg:orig_category":"Muebles, Minoristas",
    "sg:phone":"+34 944 83 40 51",
    "sg:postcode":"48980",
    "sg:province":"Vizcaya",
    "wof:name":"Perez Hidalgo Antonia",
    "wof:placetype":"venue"
},
  "geometry": {"coordinates":[-3.0314519405,43.3265953064],"type":"Point"}
}