{
  "type": "Feature",
  "properties": {
    "addr:full":"Ptda Montcada, 30 Gualda Lleida 25006",
    "addr:housenumber":"30",
    "addr:postcode":"25006",
    "addr:street":"Ptda Montcada",
    "iso:country":"ES",
    "sg:address":"Ptda Montcada, 30",
    "sg:city":"Gualda",
    "sg:orig_category":"Cr\u00cda De Animales",
    "sg:phone":"+34 973 23 64 28",
    "sg:postcode":"25006",
    "sg:province":"Lleida",
    "wof:name":"Clop Choy Joaquin",
    "wof:placetype":"venue"
},
  "geometry": {"coordinates":[0.5619999766,41.6497535706],"type":"Point"}
}