{
  "type": "Feature",
  "properties": {
    "addr:full":"Calle de Bronce, 14 Aimayr Madrid 28320",
    "addr:housenumber":"14",
    "addr:postcode":"28320",
    "addr:street":"Calle De Bronce",
    "iso:country":"ES",
    "sg:address":"Calle de Bronce, 14",
    "sg:city":"Aimayr",
    "sg:orig_category":"Empresas De Hormig\u00d3n, Hormig\u00d3n Armado Y Pretensado",
    "sg:phone":"+34 916 91 66 00",
    "sg:postcode":"28320",
    "sg:province":"Madrid",
    "sg:website":"www.preinco.com",
    "wof:name":"Preinco S. A.",
    "wof:placetype":"venue"
},
  "geometry": {"coordinates":[-3.7003455162,40.4166908264],"type":"Point"}
}