{
  "type": "Feature",
  "properties": {
    "addr:full":"Rua Mendi\u00d1o, 2 Santa Uxia De Ribeira La Coru\u00f1a 15960",
    "addr:housenumber":"2",
    "addr:postcode":"15960",
    "addr:street":"Rua Mendin\u0303O;Corun\u0303A",
    "iso:country":"ES",
    "sg:address":"Rua Mendi\u00d1o, 2",
    "sg:city":"Santa Uxia De Ribeira",
    "sg:orig_category":"Fabricaci\u00d3n De Sobres, Bolsas Y Fundas",
    "sg:phone":"+34 981 87 52 47",
    "sg:postcode":"15960",
    "sg:province":"La Coru\u00f1a",
    "wof:name":"Gomez Crujeiras Rosa Maria",
    "wof:placetype":"venue"
},
  "geometry": {"coordinates":[-8.993730545,42.555305481],"type":"Point"}
}