{
  "type": "Feature",
  "properties": {
    "iso:country":"ES",
    "sg:address":"Calle de Jesus, 13",
    "sg:city":"Zaragoza",
    "sg:orig_category":"Empresas De Carpinter\u00cda",
    "sg:phone":"+34 976 29 46 52",
    "sg:postcode":"50014",
    "sg:province":"Zaragoza",
    "wof:name":"Laborda Carpinteria Metalica S.l.",
    "wof:placetype":"venue"
},
  "geometry": {"coordinates":[-0.8716369867,41.6583175659],"type":"Point"}
}