{
  "type": "Feature",
  "properties": {
    "iso:country":"ES",
    "sg:address":"Calle de Adelfa, 1",
    "sg:city":"Granada",
    "sg:orig_category":"Electrodom\u00c9sticos (al Por Menor)",
    "sg:phone":"+34 958 81 68 01",
    "sg:postcode":"18006",
    "sg:province":"Granada",
    "wof:name":"Pi\u00f1ar Vilchez Miguel",
    "wof:placetype":"venue"
},
  "geometry": {"coordinates":[-3.6023075581,37.1638069153],"type":"Point"}
}