{
  "type": "Feature",
  "properties": {
    "iso:country":"ES",
    "sg:address":"Agua, 12",
    "sg:city":"Leganes",
    "sg:orig_category":"Mec\u00c1nica Y Herramientas De Precisi\u00d3n",
    "sg:phone":"+34 916 11 21 60",
    "sg:postcode":"28918",
    "sg:province":"Madrid",
    "wof:name":"Serviauto-sag S. A.",
    "wof:placetype":"venue"
},
  "geometry": {"coordinates":[-3.8001170158,40.3491020203],"type":"Point"}
}