{
  "type": "Feature",
  "properties": {
    "addr:full":"Pase Doctor Torres Villarroel, 16 Salamanca Salamanca 37005",
    "addr:housenumber":"16",
    "addr:postcode":"37005",
    "addr:street":"Doctor Torres Villarroel",
    "iso:country":"ES",
    "sg:address":"Pase Doctor Torres Villarroel, 16",
    "sg:city":"Salamanca",
    "sg:orig_category":"Agencias De Viajes",
    "sg:phone":"+34 923 28 20 49",
    "sg:postcode":"37005",
    "sg:province":"Salamanca",
    "sg:website":"www.viajesiberia.com",
    "wof:name":"Viajes Iberia S.a.",
    "wof:placetype":"venue"
},
  "geometry": {"coordinates":[-5.6632847786,40.9715118408],"type":"Point"}
}