{
  "type": "Feature",
  "properties": {
    "addr:full":"Plaz San Lorenzo, 1 Velilla Cinca Huesca 22528",
    "addr:housenumber":"1",
    "addr:postcode":"22528",
    "addr:street":"Plaz San Lorenzo",
    "iso:country":"ES",
    "sg:address":"Plaz San Lorenzo, 1",
    "sg:city":"Velilla Cinca",
    "sg:orig_category":"Ense\u00d1anza, Formaci\u00d3n Profesional: Aprendizaje",
    "sg:phone":"+34 974 46 12 21",
    "sg:postcode":"22528",
    "sg:province":"Huesca",
    "wof:name":"Ayuntamiento",
    "wof:placetype":"venue"
},
  "geometry": {"coordinates":[0.2613742948,41.5867156982],"type":"Point"}
}