{
  "type": "Feature",
  "properties": {
    "iso:country":"ES",
    "sg:address":"Carrer de Arcadi Balaguer, 1",
    "sg:city":"Castelldefels",
    "sg:orig_category":"Art\u00cdculos De Regalo (al Por Menor)",
    "sg:phone":"+34 936 36 38 95",
    "sg:postcode":"08860",
    "sg:province":"Barcelona",
    "wof:name":"Ignoto Costa Carmen",
    "wof:placetype":"venue"
},
  "geometry": {"coordinates":[1.9742599726,41.2781982422],"type":"Point"}
}