{
  "type": "Feature",
  "properties": {
    "iso:country":"ES",
    "sg:address":"Calle de Aparisi Guijarro, 20",
    "sg:city":"Castellon",
    "sg:orig_category":"Agentes Generales De Seguros",
    "sg:phone":"+34 964 23 94 22",
    "sg:postcode":"12002",
    "sg:province":"Castell\u00f3n",
    "wof:name":"Naayen Y Asociados S.l.",
    "wof:placetype":"venue"
},
  "geometry": {"coordinates":[-0.0441140011,39.983795166],"type":"Point"}
}