{
  "type": "Feature",
  "properties": {
    "iso:country":"ES",
    "sg:address":"Calle de San Roque, 3",
    "sg:city":"Coru\u00d1a",
    "sg:orig_category":"Electrodom\u00c9sticos (al Por Menor)",
    "sg:phone":"+34 981 20 94 80",
    "sg:postcode":"15002",
    "sg:province":"A Coru\u00f1a",
    "wof:name":"Terron Martinez Dositeo",
    "wof:placetype":"venue"
},
  "geometry": {"coordinates":[-8.3975124359,43.37342453],"type":"Point"}
}