{
  "type": "Feature",
  "properties": {
    "addr:full":"Carrer de Comte Borrell, 151 Barcelona Barcelona 08015",
    "addr:housenumber":"151",
    "addr:postcode":"08015",
    "addr:street":"Carrer De Comte Borrell",
    "iso:country":"ES",
    "sg:address":"Carrer de Comte Borrell, 151",
    "sg:city":"Barcelona",
    "sg:orig_category":"Alquiler De V\u00cddeo",
    "sg:phone":"+34 934 51 74 01",
    "sg:postcode":"08015",
    "sg:province":"Barcelona",
    "wof:name":"Sanchez Samso Eva",
    "wof:placetype":"venue"
},
  "geometry": {"coordinates":[2.1563000679,41.3819541931],"type":"Point"}
}