{
  "type": "Feature",
  "properties": {
    "iso:country":"ES",
    "sg:address":"Poligono Diez, 4",
    "sg:city":"Cheste",
    "sg:orig_category":"Art\u00cdculos De Limpieza Y De Cocina (fabricaci\u00d3n, Al Por Mayor)",
    "sg:phone":"+34 962 51 16 05",
    "sg:postcode":"46380",
    "sg:province":"Valencia",
    "sg:website":"www.quimituria.com",
    "wof:name":"Quimicas Del Turia S.l.",
    "wof:placetype":"venue"
},
  "geometry": {"coordinates":[-0.6874480247,39.4945602417],"type":"Point"}
}