{
  "type": "Feature",
  "properties": {
    "iso:country":"ES",
    "sg:address":"Calle de Portal De Bergara, 4",
    "sg:city":"Vitoria-gasteiz",
    "sg:orig_category":"Montaje (empresas De)",
    "sg:phone":"+34 945 12 28 68",
    "sg:postcode":"01013",
    "sg:province":"\u00c1lava",
    "wof:name":"Euskoutsourcing Company S.l.",
    "wof:placetype":"venue"
},
  "geometry": {"coordinates":[-2.661221981,42.8578796387],"type":"Point"}
}