{
  "type": "Feature",
  "properties": {
    "iso:country":"ES",
    "sg:address":"Calle de Franquera, 11",
    "sg:city":"Martos",
    "sg:orig_category":"Molduras, Junquillos, Listones Y Molduras Perforadas",
    "sg:phone":"+34 953 70 05 46",
    "sg:postcode":"23600",
    "sg:province":"Ja\u00e9n",
    "wof:name":"Carazo Lopez Antonia",
    "wof:placetype":"venue"
},
  "geometry": {"coordinates":[-3.9665460587,37.7233924866],"type":"Point"}
}