{
  "type": "Feature",
  "properties": {
    "iso:country":"ES",
    "sg:address":"Totana, 2",
    "sg:city":"Madrid",
    "sg:orig_category":"Bares, Piano",
    "sg:phone":"+34 917 63 02 42",
    "sg:postcode":"28033",
    "sg:province":"Madrid",
    "wof:name":"Manzano Burgos Jose",
    "wof:placetype":"venue"
},
  "geometry": {"coordinates":[-3.6533811092,40.4735183716],"type":"Point"}
}