{
  "type": "Feature",
  "properties": {
    "iso:country":"ES",
    "sg:address":"Los Morales (zona Ind.), S/n",
    "sg:city":"Palacios Y Villafranca",
    "sg:orig_category":"Comercio De Hierro",
    "sg:phone":"+34 955 81 43 19",
    "sg:postcode":"41720",
    "sg:province":"Sevilla",
    "wof:name":"Reyes Dominguez Francisco",
    "wof:placetype":"venue"
},
  "geometry": {"coordinates":[-5.9340691566,37.1601066589],"type":"Point"}
}