{
  "type": "Feature",
  "properties": {
    "iso:country":"ES",
    "sg:address":"Plaz Mayor, S/n",
    "sg:city":"Gumiel De Izan",
    "sg:orig_category":"Contenedores Para Transporte De Mercanc\u00cdas",
    "sg:phone":"+34 947 54 42 83",
    "sg:postcode":"09370",
    "sg:province":"Burgos",
    "wof:name":"Renalte Sociedad Cooperativa Limitada",
    "wof:placetype":"venue"
},
  "geometry": {"coordinates":[-3.7510890961,41.7588348389],"type":"Point"}
}