{
  "type": "Feature",
  "properties": {
    "iso:country":"ES",
    "sg:address":"Calle de Historiador Dozy, 10",
    "sg:city":"Cordoba",
    "sg:orig_category":"Reposter\u00cdas",
    "sg:phone":"+34 957 27 00 13",
    "sg:postcode":"14011",
    "sg:province":"C\u00f3rdoba",
    "wof:name":"Martinez Romasanta Maria",
    "wof:placetype":"venue"
},
  "geometry": {"coordinates":[-4.7930288315,37.8901329041],"type":"Point"}
}