{
  "type": "Feature",
  "properties": {
    "iso:country":"ES",
    "sg:address":"C/ Major, 13",
    "sg:city":"Paterna",
    "sg:orig_category":"Arquitectos",
    "sg:phone":"+34 961 37 03 21",
    "sg:postcode":"46980",
    "sg:province":"Valencia",
    "wof:name":"Lorente Pe\u00f1a Andres Francisco",
    "wof:placetype":"venue"
},
  "geometry": {"coordinates":[-0.441783011,39.5025062561],"type":"Point"}
}