{
  "type": "Feature",
  "properties": {
    "iso:country":"ES",
    "sg:address":"La Iglesia, S/n",
    "sg:city":"Villares De Orbigo",
    "sg:orig_category":"Iglesia Cat\u00d3lica",
    "sg:phone":"+34 987 38 80 94",
    "sg:postcode":"24288",
    "sg:province":"Le\u00f3n",
    "wof:name":"Diocesis Astorga Administracion",
    "wof:placetype":"venue"
},
  "geometry": {"coordinates":[-5.9094247818,42.4706954956],"type":"Point"}
}