{
  "type": "Feature",
  "properties": {
    "addr:full":"Calle de Pelagio, 1 Cordoba C\u00f3rdoba 14010",
    "addr:housenumber":"1",
    "addr:postcode":"14010",
    "addr:street":"Calle De Pelagio;Co\u0301Rdoba",
    "iso:country":"ES",
    "sg:address":"Calle de Pelagio, 1",
    "sg:city":"Cordoba",
    "sg:orig_category":"M\u00c9dicos: Estomatolog\u00cda",
    "sg:phone":"+34 957 43 51 99",
    "sg:postcode":"14010",
    "sg:province":"C\u00f3rdoba",
    "wof:name":"Due\u00f1as Alonso Moises",
    "wof:placetype":"venue"
},
  "geometry": {"coordinates":[-4.76476717,37.8813438416],"type":"Point"}
}