{
  "type": "Feature",
  "properties": {
    "addr:full":"Carrer de Baldiri Deu I Priu, 39 S. Boi Llobregat Barcelona 08830",
    "addr:housenumber":"39",
    "addr:postcode":"08830",
    "addr:street":"Carrer De Baldiri;I Priu",
    "iso:country":"ES",
    "sg:address":"Carrer de Baldiri Deu I Priu, 39",
    "sg:city":"S. Boi Llobregat",
    "sg:orig_category":"Alimentaci\u00d3n General (al Por Menor)",
    "sg:phone":"+34 936 61 45 92",
    "sg:postcode":"08830",
    "sg:province":"Barcelona",
    "wof:name":"Martinez Camacho Antonio",
    "wof:placetype":"venue"
},
  "geometry": {"coordinates":[2.0457360744,41.3414001465],"type":"Point"}
}