{
  "type": "Feature",
  "properties": {
    "iso:country":"ES",
    "sg:address":"Calle de Barbecho, 31",
    "sg:city":"Valladolid",
    "sg:orig_category":"Alimentaci\u00d3n General (al Por Menor)",
    "sg:phone":"+34 983 34 46 81",
    "sg:postcode":"47014",
    "sg:province":"Valladolid",
    "wof:name":"Sanchez Gutierrez Tomas",
    "wof:placetype":"venue"
},
  "geometry": {"coordinates":[-4.7468013763,41.6500434875],"type":"Point"}
}