{
  "type": "Feature",
  "properties": {
    "iso:country":"ES",
    "sg:address":"Av Almassera (l'), 27",
    "sg:city":"San Vicente Del Raspeig-sant Vicent Del Raspeig",
    "sg:orig_category":"Platos Preparados Refrigerados (fabricaci\u00d3n, Al Por Mayor)",
    "sg:phone":"+34 965 67 01 02",
    "sg:postcode":"03690",
    "sg:province":"Alicante",
    "wof:name":"Cocina Artesana Lalmassera Sl",
    "wof:placetype":"venue"
},
  "geometry": {"coordinates":[-0.513858974,38.395565033],"type":"Point"}
}