{
  "type": "Feature",
  "properties": {
    "iso:country":"ES",
    "sg:address":"Calle de Fuertes Acevedo, 55",
    "sg:city":"Oviedo",
    "sg:orig_category":"Carb\u00d3n, Carb\u00d3n De Madera (al Por Mayor)",
    "sg:phone":"+34 985 23 87 80",
    "sg:postcode":"33006",
    "sg:province":"Asturias",
    "wof:name":"Martinez Fernandez Maria Pilar",
    "wof:placetype":"venue"
},
  "geometry": {"coordinates":[-5.869661808,43.3580703735],"type":"Point"}
}