{
  "type": "Feature",
  "properties": {
    "iso:country":"ES",
    "sg:address":"Avda Sierra De Gata, 117",
    "sg:city":"Perales Del Puerto",
    "sg:orig_category":"Material Y Equipo Para Vinificaci\u00d3n",
    "sg:phone":"+34 927 51 44 90",
    "sg:postcode":"10896",
    "sg:province":"C\u00e1ceres",
    "wof:name":"Lachapelle Morales Corina Leonor",
    "wof:placetype":"venue"
},
  "geometry": {"coordinates":[-6.6832089424,40.1612586975],"type":"Point"}
}