{
  "type": "Feature",
  "properties": {
    "iso:country":"ES",
    "sg:address":"Barr Medio, 10",
    "sg:city":"Zurbano",
    "sg:orig_category":"Florister\u00cdas",
    "sg:phone":"+34 945 12 06 64",
    "sg:postcode":"01192",
    "sg:province":"\u00c1lava",
    "sg:website":"www.paginasamarillas.es",
    "wof:name":"Krabelin Bouquets S.l.",
    "wof:placetype":"venue"
},
  "geometry": {"coordinates":[-2.618098259,42.871257782],"type":"Point"}
}