{
  "type": "Feature",
  "properties": {
    "iso:country":"ES",
    "sg:address":"Calle de Cronista Carlos Valcarcel, 33",
    "sg:city":"Palmar  O Lugar De Don Juan",
    "sg:orig_category":"Art\u00cdculos De Regalo (al Por Menor)",
    "sg:phone":"+34 968 88 20 41",
    "sg:postcode":"30120",
    "sg:province":"Murcia",
    "wof:name":"Lorente Inista Maria Dolores",
    "wof:placetype":"venue"
},
  "geometry": {"coordinates":[-1.1298867464,37.9834747314],"type":"Point"}
}