{
  "type": "Feature",
  "properties": {
    "iso:country":"ES",
    "sg:address":"Pg Saralegui, 6",
    "sg:city":"Puerto De Pollen\u00c7a",
    "sg:orig_category":"Regalos, Souvenires (fabricaci\u00d3n, Al Por Mayor)",
    "sg:phone":"+34 971 86 42 72",
    "sg:postcode":"07470",
    "sg:province":"Islas Baleares",
    "wof:name":"Apaolaza Garcia Jose Leonardo",
    "wof:placetype":"venue"
},
  "geometry": {"coordinates":[3.0825128555,39.9060668945],"type":"Point"}
}