{
  "type": "Feature",
  "properties": {
    "iso:country":"ES",
    "sg:address":"Carr Cristofor Colom, 30",
    "sg:city":"Portocolom",
    "sg:orig_category":"Productos Qu\u00cdmicos (fabricaci\u00d3n, Al Por Mayor)",
    "sg:phone":"+34 971 82 49 53",
    "sg:postcode":"07670",
    "sg:province":"Islas Baleares",
    "wof:name":"Sanso Estelrrich Pedro",
    "wof:placetype":"venue"
},
  "geometry": {"coordinates":[3.2615830898,39.4227333069],"type":"Point"}
}