{
  "type": "Feature",
  "properties": {
    "addr:full":"Cami Can Bruguera, 6 Campins Barcelona 08470",
    "addr:housenumber":"6",
    "addr:postcode":"08470",
    "addr:street":"Campins Barcelona",
    "iso:country":"ES",
    "sg:address":"Cami Can Bruguera, 6",
    "sg:city":"Campins",
    "sg:orig_category":"Empresarios Y Productoras De Espect\u00c1culos",
    "sg:phone":"+34 938 47 51 34",
    "sg:postcode":"08470",
    "sg:province":"Barcelona",
    "wof:name":"Circ Panic S.c.p.",
    "wof:placetype":"venue"
},
  "geometry": {"coordinates":[2.463572979,41.7227363586],"type":"Point"}
}