{
  "type": "Feature",
  "properties": {
    "iso:country":"ES",
    "sg:address":"Av Tres-cents, 24",
    "sg:city":"Castelldefels",
    "sg:orig_category":"Promotores Constructores",
    "sg:phone":"+34 936 45 28 63",
    "sg:postcode":"08860",
    "sg:province":"Barcelona",
    "wof:name":"Via Inmobiliaria 2001s.l.",
    "wof:placetype":"venue"
},
  "geometry": {"coordinates":[1.9784450531,41.2793083191],"type":"Point"}
}