{
  "type": "Feature",
  "properties": {
    "iso:country":"ES",
    "sg:address":"Calle de Ramon Y Cajal, 2",
    "sg:city":"Nava Rey",
    "sg:orig_category":"Notarios",
    "sg:phone":"+34 983 85 03 36",
    "sg:postcode":"47500",
    "sg:province":"Valladolid",
    "wof:name":"Gonzalez Pereda Maria Bego\u00f1a",
    "wof:placetype":"venue"
},
  "geometry": {"coordinates":[-5.081196785,41.3308525085],"type":"Point"}
}