{
  "type": "Feature",
  "properties": {
    "iso:country":"ES",
    "sg:address":"Carrer de Carolines, 6",
    "sg:city":"Barcelona",
    "sg:orig_category":"Molduras, Junquillos, Listones Y Molduras Perforadas",
    "sg:phone":"+34 932 17 50 73",
    "sg:postcode":"08012",
    "sg:province":"Barcelona",
    "wof:name":"Domingo Farre Maria Dolores",
    "wof:placetype":"venue"
},
  "geometry": {"coordinates":[2.1514129639,41.4038734436],"type":"Point"}
}