{
  "type": "Feature",
  "properties": {
    "iso:country":"ES",
    "sg:address":"Calle de San Juan De Dios, 49",
    "sg:city":"Granada",
    "sg:orig_category":"Dorados, Plater\u00cda (orfebrer\u00cda)",
    "sg:phone":"+34 958 28 72 19",
    "sg:postcode":"18001",
    "sg:province":"Granada",
    "wof:name":"Mesa Adamuz Benita",
    "wof:placetype":"venue"
},
  "geometry": {"coordinates":[-3.6025390625,37.1819763184],"type":"Point"}
}