{
  "type": "Feature",
  "properties": {
    "addr:full":"Polig La Cerrada, 1 Malia\u00d1o Cantabria 39600",
    "addr:housenumber":"1",
    "addr:postcode":"39600",
    "addr:street":"Polig La Cerrada",
    "iso:country":"ES",
    "sg:address":"Polig La Cerrada, 1",
    "sg:city":"Malia\u00d1o",
    "sg:orig_category":"Agentes, Concesionarios Y Sucursales De Veh\u00cdculos",
    "sg:phone":"+34 942 25 14 94",
    "sg:postcode":"39600",
    "sg:province":"Cantabria",
    "wof:name":"Martinez De La Hoz Maria Ines",
    "wof:placetype":"venue"
},
  "geometry": {"coordinates":[-3.837471962,43.4134941101],"type":"Point"}
}