{
  "type": "Feature",
  "properties": {
    "iso:country":"ES",
    "sg:address":"Partida De Yescas Y San Ram\u00f1n, S/n",
    "sg:city":"Calatayud",
    "sg:orig_category":"Arenas, Guijarros Y Granulados",
    "sg:phone":"+34 976 88 33 61",
    "sg:postcode":"50300",
    "sg:province":"Zaragoza",
    "wof:name":"Aridos Del Ribota S.l.",
    "wof:placetype":"venue"
},
  "geometry": {"coordinates":[-1.6178010702,41.3698272705],"type":"Point"}
}