{
  "type": "Feature",
  "properties": {
    "addr:full":"Calle de Coronel Bens, 5 Arrecife Las Palmas 35500",
    "addr:housenumber":"5",
    "addr:postcode":"35500",
    "addr:street":"Calle De Coronel Bens",
    "iso:country":"ES",
    "sg:address":"Calle de Coronel Bens, 5",
    "sg:city":"Arrecife",
    "sg:orig_category":"Ense\u00d1anza, Formaci\u00d3n Profesional: Aprendizaje",
    "sg:phone":"+34 928 81 09 31",
    "sg:postcode":"35500",
    "sg:province":"Las Palmas",
    "wof:name":"Gobierno De Canarias",
    "wof:placetype":"venue"
},
  "geometry": {"coordinates":[-13.5524530411,28.9582271576],"type":"Point"}
}