{
  "type": "Feature",
  "properties": {
    "addr:full":"Calle de Emilio Tuya, 64 Gijon Asturias 33203",
    "addr:housenumber":"64",
    "addr:postcode":"33203",
    "addr:street":"Calle De Emilio Tuya",
    "iso:country":"ES",
    "sg:address":"Calle de Emilio Tuya, 64",
    "sg:city":"Gijon",
    "sg:orig_category":"Ense\u00d1anza: Idiomas",
    "sg:phone":"+34 985 33 35 60",
    "sg:postcode":"33203",
    "sg:province":"Asturias",
    "wof:name":"Holdsworth  John Ronald",
    "wof:placetype":"venue"
},
  "geometry": {"coordinates":[-5.646607399,43.5377731323],"type":"Point"}
}