{
  "type": "Feature",
  "properties": {
    "addr:full":"Calle de Isidoro Macabich, 13 Santa Eulalia Islas Baleares 07840",
    "addr:housenumber":"13",
    "addr:postcode":"07840",
    "addr:street":"Calle De Isidoro Macabich",
    "iso:country":"ES",
    "sg:address":"Calle de Isidoro Macabich, 13",
    "sg:city":"Santa Eulalia",
    "sg:orig_category":"Caf\u00c9s, Bares, Cervecer\u00cdas",
    "sg:phone":"+34 971 33 61 21",
    "sg:postcode":"07840",
    "sg:province":"Islas Baleares",
    "wof:name":"Colomar Mari Miguel",
    "wof:placetype":"venue"
},
  "geometry": {"coordinates":[2.9117100239,39.6136398315],"type":"Point"}
}