{
  "type": "Feature",
  "properties": {
    "iso:country":"ES",
    "sg:address":"Pol Ind El Cruce, S/n",
    "sg:city":"Bailen",
    "sg:orig_category":"Gafas (fabricaci\u00d3n)",
    "sg:phone":"+34 953 67 81 89",
    "sg:postcode":"23710",
    "sg:province":"Ja\u00e9n",
    "wof:name":"Gruppoottico Italiano S.l.",
    "wof:placetype":"venue"
},
  "geometry": {"coordinates":[-3.763825655,38.1087646484],"type":"Point"}
}