{
  "type": "Feature",
  "properties": {
    "addr:full":"Calle de Arca, 11 Vitoria-gasteiz \u00c1lava 01005",
    "addr:housenumber":"11",
    "addr:postcode":"01005",
    "addr:street":"Calle De Arca",
    "iso:country":"ES",
    "sg:address":"Calle de Arca, 11",
    "sg:city":"Vitoria-gasteiz",
    "sg:orig_category":"Librer\u00cdas",
    "sg:phone":"+34 945 13 22 35",
    "sg:postcode":"01005",
    "sg:province":"\u00c1lava",
    "sg:website":"vitoria@casadellibro.com",
    "wof:name":"Espasa Calpe S.a.",
    "wof:placetype":"venue"
},
  "geometry": {"coordinates":[-2.6721231937,42.8431968689],"type":"Point"}
}