{
  "type": "Feature",
  "properties": {
    "iso:country":"ES",
    "sg:address":"Calle de Maria Barrientos, 4",
    "sg:city":"Madrid",
    "sg:orig_category":"Equipos De Marcado, Etiquetado",
    "sg:phone":"+34 917 97 33 32",
    "sg:postcode":"28021",
    "sg:province":"Madrid",
    "sg:website":"www.i-signo.com",
    "wof:name":"Hernandez Galan Juan Jose",
    "wof:placetype":"venue"
},
  "geometry": {"coordinates":[-3.6863489151,40.3549156189],"type":"Point"}
}