{
  "type": "Feature",
  "properties": {
    "addr:full":"Carr Reina De La, 49 Xativa Valencia 46800",
    "addr:housenumber":"49",
    "addr:postcode":"46800",
    "addr:street":"Carr Reina De La",
    "iso:country":"ES",
    "sg:address":"Carr Reina De La, 49",
    "sg:city":"Xativa",
    "sg:orig_category":"Ropa Y Accesorios",
    "sg:phone":"+34 962 27 53 62",
    "sg:postcode":"46800",
    "sg:province":"Valencia",
    "wof:name":"Marquez Ordo\u00f1ez Eltidia",
    "wof:placetype":"venue"
},
  "geometry": {"coordinates":[-0.5200830102,38.9934272766],"type":"Point"}
}