{
  "type": "Feature",
  "properties": {
    "addr:full":"Carr Pirotecnia Caballer, 14 Godella Valencia 46110",
    "addr:housenumber":"14",
    "addr:postcode":"46110",
    "addr:street":"Carr Pirotecnia Caballer",
    "iso:country":"ES",
    "sg:address":"Carr Pirotecnia Caballer, 14",
    "sg:city":"Godella",
    "sg:orig_category":"Peluqueros: De Se\u00d1oras",
    "sg:phone":"+34 963 64 14 16",
    "sg:postcode":"46110",
    "sg:province":"Valencia",
    "wof:name":"Bartual Cardo Maria Dolores",
    "wof:placetype":"venue"
},
  "geometry": {"coordinates":[-0.4154840112,39.5255889893],"type":"Point"}
}