{
  "type": "Feature",
  "properties": {
    "iso:country":"ES",
    "sg:address":"Trapani, 19",
    "sg:city":"Garrapinillos",
    "sg:orig_category":"Negocio De Madera",
    "sg:phone":"+34 976 33 33 39",
    "sg:postcode":"50197",
    "sg:province":"Zaragoza",
    "wof:name":"Maderas Izuel S.a.",
    "wof:placetype":"venue"
},
  "geometry": {"coordinates":[-1.0269140005,41.6842803955],"type":"Point"}
}