{
  "type": "Feature",
  "properties": {
    "addr:full":"Carrer de Alt De Pedrell, 60 Barcelona Barcelona 08032",
    "addr:housenumber":"60",
    "addr:postcode":"08032",
    "addr:street":"Carrer De Alt De Pedrell",
    "iso:country":"ES",
    "sg:address":"Carrer de Alt De Pedrell, 60",
    "sg:city":"Barcelona",
    "sg:orig_category":"Peluqueros: De Se\u00d1oras",
    "sg:phone":"+34 933 57 39 13",
    "sg:postcode":"08032",
    "sg:province":"Barcelona",
    "wof:name":"Claramunt Pujado Rosario",
    "wof:placetype":"venue"
},
  "geometry": {"coordinates":[2.1693940163,41.4260253906],"type":"Point"}
}