{
  "type": "Feature",
  "properties": {
    "addr:full":"Carrer de Bonavista, 92 S. Just Desvern Barcelona 08960",
    "addr:housenumber":"92",
    "addr:postcode":"08960",
    "addr:street":"Carrer De Bonavista",
    "iso:country":"ES",
    "sg:address":"Carrer de Bonavista, 92",
    "sg:city":"S. Just Desvern",
    "sg:orig_category":"\u00d3ptica: Instrumentos (fabricaci\u00d3n)",
    "sg:phone":"+34 933 71 17 98",
    "sg:postcode":"08960",
    "sg:province":"Barcelona",
    "wof:name":"Opticas G.h S.l",
    "wof:placetype":"venue"
},
  "geometry": {"coordinates":[2.0767700672,41.3845405579],"type":"Point"}
}