{
  "type": "Feature",
  "properties": {
    "addr:full":"Calle de Beato Domingo Iturrate, 1 Getxo Vizcaya 48990",
    "addr:housenumber":"1",
    "addr:postcode":"48990",
    "addr:street":"Calle De Beato Domingo Iturrate",
    "iso:country":"ES",
    "sg:address":"Calle de Beato Domingo Iturrate, 1",
    "sg:city":"Getxo",
    "sg:orig_category":"M\u00c9dicos: Medicina General Orientada A La Acupuntura",
    "sg:phone":"+34 944 30 78 66",
    "sg:postcode":"48990",
    "sg:province":"Vizcaya",
    "wof:name":"Javier Palacios Urdiain",
    "wof:placetype":"venue"
},
  "geometry": {"coordinates":[-3.0124149323,43.3582496643],"type":"Point"}
}