{
  "type": "Feature",
  "properties": {
    "iso:country":"ES",
    "sg:address":"Carrer de Ciutat D'asuncion, 8",
    "sg:city":"Barcelona",
    "sg:orig_category":"Materias Pl\u00c1sticas: Art\u00cdculos Para La Industria",
    "sg:phone":"+34 933 11 63 15",
    "sg:postcode":"08030",
    "sg:province":"Barcelona",
    "sg:website":"www.cirplastic.com",
    "wof:name":"Cirplastic S.a.",
    "wof:placetype":"venue"
},
  "geometry": {"coordinates":[2.2008650303,41.4367980957],"type":"Point"}
}