{
  "type": "Feature",
  "properties": {
    "iso:country":"ES",
    "sg:address":"C/ Major, 27",
    "sg:city":"Celra",
    "sg:orig_category":"Reposter\u00cdas",
    "sg:phone":"+34 972 49 23 74",
    "sg:postcode":"17460",
    "sg:province":"Girona",
    "wof:name":"Tio Mascaros Montserrat",
    "wof:placetype":"venue"
},
  "geometry": {"coordinates":[2.8788769245,42.0247612],"type":"Point"}
}