{
  "type": "Feature",
  "properties": {
    "addr:full":"Estd Castela, 180 Ponto La Coru\u00f1a 15570",
    "addr:housenumber":"180",
    "addr:postcode":"15570",
    "addr:street":"Castela;Corun\u0303A",
    "iso:country":"ES",
    "sg:address":"Estd Castela, 180",
    "sg:city":"Ponto",
    "sg:orig_category":"Vinos Y Licores (venta Al Por Menor)",
    "sg:phone":"+34 981 38 70 22",
    "sg:postcode":"15570",
    "sg:province":"La Coru\u00f1a",
    "wof:name":"Poupari\u00f1a Paz Antonio",
    "wof:placetype":"venue"
},
  "geometry": {"coordinates":[-8.1647539139,43.5165405273],"type":"Point"}
}