{
  "type": "Feature",
  "properties": {
    "addr:full":"Calle de Rio Manzanares, 1 Mostoles Madrid 28934",
    "addr:housenumber":"1",
    "addr:postcode":"28934",
    "addr:street":"Calle De Rio Manzanares",
    "iso:country":"ES",
    "sg:address":"Calle de Rio Manzanares, 1",
    "sg:city":"Mostoles",
    "sg:orig_category":"Farmacias",
    "sg:phone":"+34 916 17 89 07",
    "sg:postcode":"28934",
    "sg:province":"Madrid",
    "wof:name":"Valverde Montero Francisco",
    "wof:placetype":"venue"
},
  "geometry": {"coordinates":[-3.8721549511,40.3189964294],"type":"Point"}
}