{
  "type": "Feature",
  "properties": {
    "addr:full":"Calle de Acera Recoletos, S/n Valladolid Valladolid 47004",
    "addr:housenumber":"s / n",
    "addr:postcode":"47004",
    "addr:street":"Calle De Acera Recoletos",
    "iso:country":"ES",
    "sg:address":"Calle de Acera Recoletos, S/n",
    "sg:city":"Valladolid",
    "sg:orig_category":"Edici\u00d3n De Diarios, Revistas, Boletines",
    "sg:phone":"+34 983 20 65 30",
    "sg:postcode":"47004",
    "sg:province":"Valladolid",
    "wof:name":"Revuelta Polo Miguel Angel",
    "wof:placetype":"venue"
},
  "geometry": {"coordinates":[-4.7284379005,41.6462020874],"type":"Point"}
}