{
  "type": "Feature",
  "properties": {
    "iso:country":"ES",
    "sg:address":"Calle de Magallanes, 4",
    "sg:city":"Aduanas",
    "sg:orig_category":"Pensiones Familiares",
    "sg:phone":"+34 965 79 04 77",
    "sg:postcode":"03730",
    "sg:province":"Alicante",
    "wof:name":"Salines Gimenez Maria Carmen",
    "wof:placetype":"venue"
},
  "geometry": {"coordinates":[0.180975005,38.7959861755],"type":"Point"}
}