{
  "type": "Feature",
  "properties": {
    "iso:country":"ES",
    "sg:address":"Carrer de Mare De Deu De La Merce, 3",
    "sg:city":"Gava",
    "sg:classifiers":[
        {
            "category":"Personal",
            "subcategory":"Barber",
            "type":"Services"
        }
    ],
    "sg:phone":"+34 936 62 74 04",
    "sg:postcode":"08850",
    "sg:province":"Barcelona",
    "sg:tags":[
        "caballeros",
        "de",
        "peluqueros"
    ],
    "wof:name":"Rodenas Martinez Jose",
    "wof:placetype":"venue"
},
  "geometry": {"coordinates":[2.007486105,41.3049240112],"type":"Point"}
}