{
  "type": "Feature",
  "properties": {
    "addr:full":"J. Uro, 31 Salelles Barcelona 08253",
    "addr:housenumber":"31",
    "addr:postcode":"08253",
    "addr:street":"J. Uro",
    "iso:country":"ES",
    "sg:address":"J. Uro, 31",
    "sg:city":"Salelles",
    "sg:orig_category":"Pintura, Barniz, Productos Asimilables (fabricaci\u00d3n, Al Por Mayor)",
    "sg:phone":"+34 938 35 50 10",
    "sg:postcode":"08253",
    "sg:province":"Barcelona",
    "wof:name":"Bagesset S.l.",
    "wof:placetype":"venue"
},
  "geometry": {"coordinates":[1.7921687365,41.6985588074],"type":"Point"}
}