{
  "type": "Feature",
  "properties": {
    "addr:full":"Polig. Ind. A Granxa, 257 Porri\u00f1o Pontevedra 36475",
    "addr:housenumber":"257",
    "addr:postcode":"36475",
    "addr:street":"Polig. Ind. A Granxa",
    "iso:country":"ES",
    "sg:address":"Polig. Ind. A Granxa, 257",
    "sg:city":"Porri\u00f1o",
    "sg:orig_category":"Promotores Constructores",
    "sg:phone":"+34 986 34 21 69",
    "sg:postcode":"36475",
    "sg:province":"Pontevedra",
    "wof:name":"Lago Martinez Construccciones S.l.",
    "wof:placetype":"venue"
},
  "geometry": {"coordinates":[-8.606926918,42.1053466797],"type":"Point"}
}