{
  "type": "Feature",
  "properties": {
    "iso:country":"ES",
    "sg:address":"Rond San Francisco (de), S/n",
    "sg:city":"Lucena",
    "sg:orig_category":"Comercio De Piezas De Recambio Y De Accesorios De Veh\u00cdculos, Veh\u00cdculos Industriales",
    "sg:phone":"+34 957 59 14 97",
    "sg:postcode":"14900",
    "sg:province":"C\u00f3rdoba",
    "sg:website":"www.mundorecambio.com",
    "wof:name":"Grupo M. Jimenez Ma\u00d1a S.l.",
    "wof:placetype":"venue"
},
  "geometry": {"coordinates":[-4.4873490334,37.4135398865],"type":"Point"}
}