{
  "type": "Feature",
  "properties": {
    "iso:country":"ES",
    "sg:address":"Cmno De La Plana, 8",
    "sg:city":"Castellon",
    "sg:orig_category":"Insecticidas, Fumigaci\u00d3n",
    "sg:phone":"+34 964 22 52 82",
    "sg:postcode":"12004",
    "sg:province":"Castell\u00f3n",
    "wof:name":"Insecticidas Parval S. L.",
    "wof:placetype":"venue"
},
  "geometry": {"coordinates":[-0.0257600006,40.0253791809],"type":"Point"}
}