{
  "type": "Feature",
  "properties": {
    "addr:full":"Afores, S/n Lli\u00e7a Amunt Barcelona 08186",
    "addr:housenumber":"s / n",
    "addr:postcode":"08186",
    "addr:street":"Afores",
    "iso:country":"ES",
    "sg:address":"Afores, S/n",
    "sg:city":"Lli\u00e7a Amunt",
    "sg:orig_category":"Aguas (distribuci\u00d3n, Servicios)",
    "sg:phone":"+34 938 41 65 71",
    "sg:postcode":"08186",
    "sg:province":"Barcelona",
    "wof:name":"Companyia General D'aigues De Catalunya",
    "wof:placetype":"venue"
},
  "geometry": {"coordinates":[2.2382690907,41.612449646],"type":"Point"}
}