{
  "type": "Feature",
  "properties": {
    "iso:country":"ES",
    "sg:address":"Esquiroz-ezkirotz Kalea, 7",
    "sg:city":"Iru\u00f1a",
    "sg:orig_category":"M\u00c9dicos: Cirug\u00cda Maxilofacial",
    "sg:phone":"+34 948 25 27 70",
    "sg:postcode":"31007",
    "sg:province":"Navarra",
    "wof:name":"Palomero Rodriguez Ramon",
    "wof:placetype":"venue"
},
  "geometry": {"coordinates":[-1.6497609615,42.8064689636],"type":"Point"}
}