{
  "type": "Feature",
  "properties": {
    "iso:country":"ES",
    "sg:address":"Calle de Bereterretxe, 11",
    "sg:city":"Altzaga",
    "sg:classifiers":[
        {
            "category":"Manufacturing",
            "subcategory":"Metals",
            "type":"Manufacturing & Wholesale Goods"
        }
    ],
    "sg:phone":"+34 944 67 21 25",
    "sg:postcode":"48950",
    "sg:province":"Vizcaya",
    "sg:tags":[
        "en",
        "fundiciones"
    ],
    "wof:name":"Fundiciones Del Pino S.l.",
    "wof:placetype":"venue"
},
  "geometry": {"coordinates":[-2.9738202095,43.3018341064],"type":"Point"}
}