{
  "type": "Feature",
  "properties": {
    "addr:full":"Carrer de Sant Magi, 18 Manresa Barcelona 08241",
    "addr:housenumber":"18",
    "addr:postcode":"08241",
    "addr:street":"Carrer De Sant Magi",
    "iso:country":"ES",
    "sg:address":"Carrer de Sant Magi, 18",
    "sg:city":"Manresa",
    "sg:orig_category":"Promotores Constructores",
    "sg:phone":"+34 938 74 10 25",
    "sg:postcode":"08241",
    "sg:province":"Barcelona",
    "wof:name":"Construccions Cots Faine S.l.",
    "wof:placetype":"venue"
},
  "geometry": {"coordinates":[1.8357549906,41.7241668701],"type":"Point"}
}