{
  "type": "Feature",
  "properties": {
    "addr:full":"Ctra. Eivissa-s. Joan, Km. 0014,5 S. Lloren\u00e7 Balafia Islas Baleares 07812",
    "addr:postcode":"07812",
    "addr:street":"Ctra. Eivissa-S. Joan Km. 0014,5 S. Llorenc\u0327;Islas",
    "iso:country":"ES",
    "sg:address":"Ctra. Eivissa-s. Joan, Km. 0014,5",
    "sg:city":"S. Lloren\u00e7 Balafia",
    "sg:orig_category":"Centros Empresariales",
    "sg:phone":"+34 971 32 53 61",
    "sg:postcode":"07812",
    "sg:province":"Islas Baleares",
    "wof:name":"Luciano Pavarotti S.l.",
    "wof:placetype":"venue"
},
  "geometry": {"coordinates":[1.4762049913,39.0312309265],"type":"Point"}
}