{
  "type": "Feature",
  "properties": {
    "iso:country":"ES",
    "sg:address":"Carrer de Jordi De Sant Jordi, 11",
    "sg:city":"Barcelona",
    "sg:orig_category":"Asociaciones Y Clubs Deportivos",
    "sg:phone":"+34 932 43 16 26",
    "sg:postcode":"08027",
    "sg:province":"Barcelona",
    "wof:name":"Asociacion De Minusvalidos De Barcelona",
    "wof:placetype":"venue"
},
  "geometry": {"coordinates":[2.1827645302,41.4215354919],"type":"Point"}
}