{
  "type": "Feature",
  "properties": {
    "addr:full":"Carrer de Malgrat, 6 Peguera Islas Baleares 07160",
    "addr:housenumber":"6",
    "addr:postcode":"07160",
    "addr:street":"Carrer De Malgrat",
    "iso:country":"ES",
    "sg:address":"Carrer de Malgrat, 6",
    "sg:city":"Peguera",
    "sg:orig_category":"Cl\u00cdnicas M\u00c9dicas",
    "sg:phone":"+34 971 68 79 53",
    "sg:postcode":"07160",
    "sg:province":"Islas Baleares",
    "wof:name":"Policlinica Alemana S.a.",
    "wof:placetype":"venue"
},
  "geometry": {"coordinates":[2.4501929283,39.5387306213],"type":"Point"}
}