{
  "type": "Feature",
  "properties": {
    "addr:full":"Ctra Alicante, S/n Grajuela Murcia 30730",
    "addr:housenumber":"s",
    "addr:postcode":"30730",
    "addr:street":"Ctra Alicante;/ N",
    "iso:country":"ES",
    "sg:address":"Ctra Alicante, S/n",
    "sg:city":"Grajuela",
    "sg:orig_category":"Fabricaci\u00d3n De Sobres, Bolsas Y Fundas",
    "sg:phone":"+34 968 54 70 89",
    "sg:postcode":"30730",
    "sg:province":"Murcia",
    "wof:name":"Centro De Bolsos Giulia S.l.",
    "wof:placetype":"venue"
},
  "geometry": {"coordinates":[-0.8377289772,37.8054389954],"type":"Point"}
}