{
  "type": "Feature",
  "properties": {
    "iso:country":"ES",
    "sg:address":"Calle de Rio Mijares, 2",
    "sg:city":"Onda",
    "sg:orig_category":"Carnicer\u00cdas, Carnicer\u00cdas",
    "sg:phone":"+34 964 77 05 59",
    "sg:postcode":"12200",
    "sg:province":"Castell\u00f3n",
    "wof:name":"Carnes Allepuz S.l.",
    "wof:placetype":"venue"
},
  "geometry": {"coordinates":[-0.2636190057,39.9666748047],"type":"Point"}
}