{
  "type": "Feature",
  "properties": {
    "addr:full":"Carrer de Reis Catolics, 36 Gandesa Tarragona 43780",
    "addr:housenumber":"36",
    "addr:postcode":"43780",
    "addr:street":"Carrer De Reis Catolics",
    "iso:country":"ES",
    "sg:address":"Carrer de Reis Catolics, 36",
    "sg:city":"Gandesa",
    "sg:orig_category":"Agricultura: Abastecimiento Y Cosechado (negocio)",
    "sg:phone":"+34 977 42 16 55",
    "sg:postcode":"43780",
    "sg:province":"Tarragona",
    "wof:name":"Associacio Agraria Joves Agricultors De Tarragona",
    "wof:placetype":"venue"
},
  "geometry": {"coordinates":[0.4405716956,41.0539932251],"type":"Point"}
}