{
  "type": "Feature",
  "properties": {
    "addr:full":"Ladera Del Barranco, S/n Higueruelas Valencia 46170",
    "addr:housenumber":"s",
    "addr:postcode":"46170",
    "addr:street":"Ladera Del Barranco;/ N",
    "iso:country":"ES",
    "sg:address":"Ladera Del Barranco, S/n",
    "sg:city":"Higueruelas",
    "sg:orig_category":"Silicatos Y Caol\u00cdn",
    "sg:phone":"+34 962 72 61 44",
    "sg:postcode":"46170",
    "sg:province":"Valencia",
    "wof:name":"Silices Y Caolines Marti S.l.",
    "wof:placetype":"venue"
},
  "geometry": {"coordinates":[-0.8200389743,39.7326507568],"type":"Point"}
}