{
  "type": "Feature",
  "properties": {
    "iso:country":"ES",
    "sg:address":"Calle de Langileria, 98",
    "sg:city":"Lamiako",
    "sg:orig_category":"Librer\u00cdas",
    "sg:phone":"+34 944 80 55 41",
    "sg:postcode":"48940",
    "sg:province":"Vizcaya",
    "wof:name":"Saez Gomez Jose Maria",
    "wof:placetype":"venue"
},
  "geometry": {"coordinates":[-2.9860789776,43.3275489807],"type":"Point"}
}