{
  "type": "Feature",
  "properties": {
    "addr:full":"Gonzalez Tablas, 4 Iru\u00f1a Navarra 31003",
    "addr:housenumber":"4",
    "addr:postcode":"31003",
    "addr:street":"Tablas",
    "iso:country":"ES",
    "sg:address":"Gonzalez Tablas, 4",
    "sg:city":"Iru\u00f1a",
    "sg:classifiers":[
        {
            "category":"Casinos & Gambling",
            "type":"Entertainment"
        }
    ],
    "sg:phone":"+34 948 15 23 26",
    "sg:postcode":"31003",
    "sg:province":"Navarra",
    "sg:tags":[
        "locale",
        "de",
        "juego"
    ],
    "wof:name":"Sanvier S.a.",
    "wof:placetype":"venue"
},
  "geometry": {"coordinates":[-1.6371680498,42.8094367981],"type":"Point"}
}