{
  "type": "Feature",
  "properties": {
    "iso:country":"ES",
    "sg:address":"Plaz Ciudad De Nara, 1",
    "sg:city":"Toledo",
    "sg:orig_category":"Centros De Educaci\u00d3n Especial",
    "sg:phone":"+34 925 25 40 23",
    "sg:postcode":"45005",
    "sg:province":"Toledo",
    "wof:name":"Colegio Publico Garcilaso De La Vega",
    "wof:placetype":"venue"
},
  "geometry": {"coordinates":[-4.0356440544,39.8760185242],"type":"Point"}
}