{
  "type": "Feature",
  "properties": {
    "iso:country":"ES",
    "sg:address":"Calle de Via (la), 5",
    "sg:city":"Zaragoza",
    "sg:orig_category":"Carnicer\u00cdas, Carnicer\u00cdas",
    "sg:phone":"+34 976 56 33 97",
    "sg:postcode":"50009",
    "sg:province":"Zaragoza",
    "wof:name":"Gonzalez Vazquez Carlos",
    "wof:placetype":"venue"
},
  "geometry": {"coordinates":[-0.9081829786,41.6304855347],"type":"Point"}
}