{
  "type": "Feature",
  "properties": {
    "addr:full":"Avgd Balmes, 27 Igualada Barcelona 08700",
    "addr:housenumber":"27",
    "addr:postcode":"08700",
    "addr:street":"Avgd Balmes",
    "iso:country":"ES",
    "sg:address":"Avgd Balmes, 27",
    "sg:city":"Igualada",
    "sg:orig_category":"Peluquer\u00cdas",
    "sg:phone":"+34 938 04 17 05",
    "sg:postcode":"08700",
    "sg:province":"Barcelona",
    "wof:name":"Sejulima S.l.",
    "wof:placetype":"venue"
},
  "geometry": {"coordinates":[1.6114710569,41.5830841064],"type":"Point"}
}