{
  "type": "Feature",
  "properties": {
    "addr:full":"Ctra Montoro-puente Genil, Km. 0006,5 Aguilar De La Frontera C\u00f3rdoba 14920",
    "addr:postcode":"14920",
    "addr:street":"Ctra Montoro-Puente Genil Km. 0006,5;Co\u0301Rdoba",
    "iso:country":"ES",
    "sg:address":"Ctra Montoro-puente Genil, Km. 0006,5",
    "sg:city":"Aguilar De La Frontera",
    "sg:orig_category":"Porcelanas, Azulejos (fabricaci\u00d3n, Al Por Mayor)",
    "sg:phone":"+34 957 68 88 88",
    "sg:postcode":"14920",
    "sg:province":"C\u00f3rdoba",
    "sg:website":"www.proceran.es",
    "wof:name":"Proceran S.a.",
    "wof:placetype":"venue"
},
  "geometry": {"coordinates":[-4.6576538086,37.5145149231],"type":"Point"}
}