{
  "type": "Feature",
  "properties": {
    "addr:full":"Avda San Blas, S/n Bocairent Valencia 46880",
    "addr:housenumber":"s / n",
    "addr:postcode":"46880",
    "addr:street":"Avda San Blas",
    "iso:country":"ES",
    "sg:address":"Avda San Blas, S/n",
    "sg:city":"Bocairent",
    "sg:orig_category":"Electricidad Veh\u00cdculo",
    "sg:phone":"+34 962 35 12 83",
    "sg:postcode":"46880",
    "sg:province":"Valencia",
    "wof:name":"Sempere Blasco S.l.",
    "wof:placetype":"venue"
},
  "geometry": {"coordinates":[-0.6103889942,38.7667541504],"type":"Point"}
}