{
  "type": "Feature",
  "properties": {
    "addr:full":"Carrer de Culla, S/n Manresa Barcelona 08243",
    "addr:housenumber":"s / n",
    "addr:postcode":"08243",
    "addr:street":"Carrer De Culla",
    "iso:country":"ES",
    "sg:address":"Carrer de Culla, S/n",
    "sg:city":"Manresa",
    "sg:orig_category":"Cooperativas, Uniones De Productores De Vinos",
    "sg:phone":"+34 938 74 82 36",
    "sg:postcode":"08243",
    "sg:province":"Barcelona",
    "wof:name":"Consell Regulador De La Denominacio De Origen Pla De Bages",
    "wof:placetype":"venue"
},
  "geometry": {"coordinates":[1.839838028,41.7207679749],"type":"Point"}
}