{
  "type": "Feature",
  "properties": {
    "addr:full":"Avda Isaac Peral, 17 Malaga M\u00e1laga 29004",
    "addr:housenumber":"17",
    "addr:postcode":"29004",
    "addr:street":"Avda Isaac Peral;Ma\u0301Laga",
    "iso:country":"ES",
    "sg:address":"Avda Isaac Peral, 17",
    "sg:city":"Malaga",
    "sg:orig_category":"\u00d3ptica: Instrumentos (fabricaci\u00d3n)",
    "sg:phone":"+34 952 23 96 84",
    "sg:postcode":"29004",
    "sg:province":"M\u00e1laga",
    "wof:name":"Garca Mosa S.a.l.",
    "wof:placetype":"venue"
},
  "geometry": {"coordinates":[-4.4560537338,36.6961746216],"type":"Point"}
}