{
  "type": "Feature",
  "properties": {
    "iso:country":"ES",
    "sg:address":"Calle de Perfumeria (de La), S/n",
    "sg:city":"Colmenar Viejo",
    "sg:orig_category":"Chapister\u00cda",
    "sg:phone":"+34 918 46 45 00",
    "sg:postcode":"28770",
    "sg:province":"Madrid",
    "sg:website":"www.hierroscolmenar.com",
    "wof:name":"Hierros Colmenar S.a.",
    "wof:placetype":"venue"
},
  "geometry": {"coordinates":[-3.7565050125,40.6558532715],"type":"Point"}
}