{
  "type": "Feature",
  "properties": {
    "iso:country":"ES",
    "sg:address":"Carrer de Iluro, 5",
    "sg:city":"Mataro",
    "sg:orig_category":"Fabricaci\u00d3n De Productos Textiles Sin Tejer",
    "sg:phone":"+34 937 99 05 07",
    "sg:postcode":"08302",
    "sg:province":"Barcelona",
    "wof:name":"Hobby Soft S.l.",
    "wof:placetype":"venue"
},
  "geometry": {"coordinates":[2.4389081001,41.5378990173],"type":"Point"}
}