{
  "type": "Feature",
  "properties": {
    "iso:country":"ES",
    "sg:address":"Carrer de Vallespir, 1",
    "sg:city":"Urbanitzacio El Pinar",
    "sg:orig_category":"Empresas De Limpieza",
    "sg:phone":"+34 977 32 14 63",
    "sg:postcode":"43206",
    "sg:province":"Tarragona",
    "wof:name":"Pujal Rodriguez Sebastian",
    "wof:placetype":"venue"
},
  "geometry": {"coordinates":[1.1029269695,41.1759414673],"type":"Point"}
}