{
  "type": "Feature",
  "properties": {
    "addr:full":"Avda Espa\u00d1a, 104 Isla Cristina Huelva 21410",
    "addr:housenumber":"104",
    "addr:postcode":"21410",
    "addr:street":"Avda Espan\u0303A",
    "iso:country":"ES",
    "sg:address":"Avda Espa\u00d1a, 104",
    "sg:city":"Isla Cristina",
    "sg:orig_category":"Producci\u00d3n, Distribuci\u00d3n De Gas Butano Y Propano",
    "sg:phone":"+34 959 33 14 94",
    "sg:postcode":"21410",
    "sg:province":"Huelva",
    "wof:name":"Sur Atlantica De Gas S.l.",
    "wof:placetype":"venue"
},
  "geometry": {"coordinates":[-7.3206892014,37.1998214722],"type":"Point"}
}