{
  "type": "Feature",
  "properties": {
    "addr:full":"Calle de Malaga, 9 Madrid Madrid 28003",
    "addr:housenumber":"9",
    "addr:postcode":"madrid;28003",
    "addr:street":"Calle De Malaga",
    "iso:country":"ES",
    "sg:address":"Calle de Malaga, 9",
    "sg:city":"Madrid",
    "sg:orig_category":"Reciclaje Y Tratamiento De Desechos Varios",
    "sg:phone":"+34 914 42 61 86",
    "sg:postcode":"28003",
    "sg:province":"Madrid",
    "wof:name":"Limpiezas Y Contratas S. A.",
    "wof:placetype":"venue"
},
  "geometry": {"coordinates":[-3.6934278011,40.438835144],"type":"Point"}
}