{
  "type": "Feature",
  "properties": {
    "addr:full":"Rua Ribeira Sagrada (da), S/n Ourense Ourense 32002",
    "addr:postcode":"32002",
    "addr:street":"Rua Ribeira Sagrada Da S / N",
    "iso:country":"ES",
    "sg:address":"Rua Ribeira Sagrada (da), S/n",
    "sg:city":"Ourense",
    "sg:orig_category":"Aguas (distribuci\u00d3n, Servicios)",
    "sg:phone":"+34 988 25 57 30",
    "sg:postcode":"32002",
    "sg:province":"Ourense",
    "wof:name":"Aquagest S.a.",
    "wof:placetype":"venue"
},
  "geometry": {"coordinates":[-7.8776021004,42.3342933655],"type":"Point"}
}