{
  "type": "Feature",
  "properties": {
    "addr:full":"Calle de Sor Joaquina, 1 Coru\u00d1a La Coru\u00f1a 15011",
    "addr:housenumber":"1",
    "addr:postcode":"15011",
    "addr:street":"Calle De Sor Joaquina;La Corun\u0303A",
    "iso:country":"ES",
    "sg:address":"Calle de Sor Joaquina, 1",
    "sg:city":"Coru\u00d1a",
    "sg:orig_category":"Arquitectos",
    "sg:phone":"+34 981 26 96 79",
    "sg:postcode":"15011",
    "sg:province":"La Coru\u00f1a",
    "wof:name":"Dos-at S.c.",
    "wof:placetype":"venue"
},
  "geometry": {"coordinates":[-8.4191493988,43.372631073],"type":"Point"}
}