{
  "type": "Feature",
  "properties": {
    "iso:country":"ES",
    "sg:address":"Calle de Ramon Y Cajal, 8",
    "sg:city":"Ejea De Los Caballeros",
    "sg:orig_category":"Agricultores, Agricultores",
    "sg:phone":"+34 976 66 03 73",
    "sg:postcode":"50600",
    "sg:province":"Zaragoza",
    "wof:name":"Sat 2035 Hermanos Bentura",
    "wof:placetype":"venue"
},
  "geometry": {"coordinates":[-1.1369940042,42.1274604797],"type":"Point"}
}