{
  "type": "Feature",
  "properties": {
    "addr:full":"Avda Peregrinos (de Los), S/n Carrion De Los Condes Palencia 34120",
    "addr:postcode":"34120",
    "addr:street":"Avda Peregrinos De Los S / N",
    "iso:country":"ES",
    "sg:address":"Avda Peregrinos (de Los), S/n",
    "sg:city":"Carrion De Los Condes",
    "sg:orig_category":"Ense\u00d1anza Secundaria: Colegios Y Escuelas Privadas",
    "sg:phone":"+34 979 88 11 85",
    "sg:postcode":"34120",
    "sg:province":"Palencia",
    "wof:name":"Instituto De Educacion Secundaria Sem Tob",
    "wof:placetype":"venue"
},
  "geometry": {"coordinates":[-4.6005840302,42.3372039795],"type":"Point"}
}