{
  "type": "Feature",
  "properties": {
    "addr:full":"Calle de Ancha De Gracia, 5 Granada Granada 18002",
    "addr:housenumber":"5",
    "addr:postcode":"18002",
    "addr:street":"Calle De Ancha De Gracia",
    "iso:country":"ES",
    "sg:address":"Calle de Ancha De Gracia, 5",
    "sg:city":"Granada",
    "sg:orig_category":"Expertos Contables, Revisores De Cuentas",
    "sg:phone":"+34 958 52 25 39",
    "sg:postcode":"18002",
    "sg:province":"Granada",
    "wof:name":"Sanchez Bullejos Emilio",
    "wof:placetype":"venue"
},
  "geometry": {"coordinates":[-3.6052501202,37.171962738],"type":"Point"}
}