{
  "type": "Feature",
  "properties": {
    "iso:country":"ES",
    "sg:address":"Plaz Triunfo, S/n",
    "sg:city":"Sevilla",
    "sg:orig_category":"Arte, Cultura, Edici\u00d3n",
    "sg:phone":"+34 954 50 23 23",
    "sg:postcode":"41004",
    "sg:province":"Sevilla",
    "wof:name":"Patronato Del Real Alcazar De Sevilla",
    "wof:placetype":"venue"
},
  "geometry": {"coordinates":[-5.9918689728,37.3852233887],"type":"Point"}
}