{
  "type": "Feature",
  "properties": {
    "iso:country":"ES",
    "sg:address":"Ctra Zamora, 1",
    "sg:city":"Onzonilla",
    "sg:orig_category":"Suministros Y Materiales Industriales",
    "sg:phone":"+34 987 21 60 69",
    "sg:postcode":"24231",
    "sg:province":"Le\u00f3n",
    "wof:name":"Suministros Onzonilla S.l.",
    "wof:placetype":"venue"
},
  "geometry": {"coordinates":[-5.5841889381,42.5260047913],"type":"Point"}
}