{
  "type": "Feature",
  "properties": {
    "iso:country":"ES",
    "sg:address":"Calle de Vermondo Resta, S/n",
    "sg:city":"Sevilla",
    "sg:orig_category":"Estancos",
    "sg:phone":"+34 954 65 40 84",
    "sg:postcode":"41018",
    "sg:province":"Sevilla",
    "wof:name":"Florez Vidal Roberto",
    "wof:placetype":"venue"
},
  "geometry": {"coordinates":[-5.9785189629,37.3801383972],"type":"Point"}
}