{
  "type": "Feature",
  "properties": {
    "addr:full":"Carr Albereda, 12 Girona Girona 17004",
    "addr:housenumber":"12",
    "addr:postcode":"17004",
    "addr:street":"Carr Albereda",
    "iso:country":"ES",
    "sg:address":"Carr Albereda, 12",
    "sg:city":"Girona",
    "sg:orig_category":"Procuradores",
    "sg:phone":"+34 972 20 52 55",
    "sg:postcode":"17004",
    "sg:province":"Girona",
    "wof:name":"Canal Piferrer Maria Merce",
    "wof:placetype":"venue"
},
  "geometry": {"coordinates":[2.8238461018,41.9821548462],"type":"Point"}
}