{
  "type": "Feature",
  "properties": {
    "addr:full":"Calle de Plata, 19 Torrejon Ardoz Madrid 28850",
    "addr:housenumber":"19",
    "addr:postcode":"28850",
    "addr:street":"Calle De Plata",
    "iso:country":"ES",
    "sg:address":"Calle de Plata, 19",
    "sg:city":"Torrejon Ardoz",
    "sg:orig_category":"Encuadernaci\u00d3n E Impresi\u00d3n De Folletos",
    "sg:phone":"+34 916 77 78 07",
    "sg:postcode":"28850",
    "sg:province":"Madrid",
    "wof:name":"Encuadernaciones Europa S.l",
    "wof:placetype":"venue"
},
  "geometry": {"coordinates":[-3.4589440823,40.4546318054],"type":"Point"}
}