{
  "type": "Feature",
  "properties": {
    "addr:full":"Send Aire, 6 Valencia Valencia 46010",
    "addr:housenumber":"6",
    "addr:postcode":"46010",
    "addr:street":"Send Aire",
    "iso:country":"ES",
    "sg:address":"Send Aire, 6",
    "sg:city":"Valencia",
    "sg:orig_category":"Escuelas De Maternidad P\u00dablicas",
    "sg:phone":"+34 963 60 56 87",
    "sg:postcode":"46010",
    "sg:province":"Valencia",
    "wof:name":"Vilata Roca Maria Teresa",
    "wof:placetype":"venue"
},
  "geometry": {"coordinates":[-0.3769130111,39.4687919617],"type":"Point"}
}