{
  "type": "Feature",
  "properties": {
    "iso:country":"ES",
    "sg:address":"Rond Ponent, 1",
    "sg:city":"Sabadell",
    "sg:orig_category":"Venta, Instalaci\u00d3n, Mantenimiento De Chimeneas De Interior Y Accesorios",
    "sg:phone":"+34 937 26 75 88",
    "sg:postcode":"08206",
    "sg:province":"Barcelona",
    "sg:website":"www.chimeneaspio.com",
    "wof:name":"Arpon Vilella Maria Soledad",
    "wof:placetype":"venue"
},
  "geometry": {"coordinates":[2.0991044044,41.5472946167],"type":"Point"}
}