{
  "type": "Feature",
  "properties": {
    "addr:full":"Carrer de Arago, 160 Palma Islas Baleares 07008",
    "addr:housenumber":"160",
    "addr:postcode":"07008",
    "addr:street":"Carrer De Arago",
    "iso:country":"ES",
    "sg:address":"Carrer de Arago, 160",
    "sg:city":"Palma",
    "sg:orig_category":"Estancos",
    "sg:phone":"+34 971 27 35 43",
    "sg:postcode":"07008",
    "sg:province":"Islas Baleares",
    "wof:name":"Amengual Guasp Bartolome Pablo",
    "wof:placetype":"venue"
},
  "geometry": {"coordinates":[2.6683855057,39.5824203491],"type":"Point"}
}