{
  "type": "Feature",
  "properties": {
    "iso:country":"ES",
    "sg:address":"Avda Menendez Pelayo, 32",
    "sg:city":"Madrid",
    "sg:orig_category":"Fabricaci\u00d3n De Enlosados, Soler\u00cdas",
    "sg:phone":"+34 914 33 83 92",
    "sg:postcode":"28007",
    "sg:province":"Madrid",
    "wof:name":"Sanchez Rodriguez Eleuteria",
    "wof:placetype":"venue"
},
  "geometry": {"coordinates":[-3.680134058,40.4057693481],"type":"Point"}
}