{
  "type": "Feature",
  "properties": {
    "iso:country":"ES",
    "sg:address":"Calle de Madre De Dios, 9",
    "sg:city":"Jerez De La Frontera",
    "sg:orig_category":"Carnicer\u00cdas, Carnicer\u00cdas",
    "sg:phone":"+34 956 34 51 03",
    "sg:postcode":"11401",
    "sg:province":"C\u00e1diz",
    "wof:name":"Judima S.l.",
    "wof:placetype":"venue"
},
  "geometry": {"coordinates":[-6.1292171478,36.6791038513],"type":"Point"}
}