{
  "type": "Feature",
  "properties": {
    "addr:full":"Calle de Vizcaya, 14 Rozas De Madrid Madrid 28230",
    "addr:housenumber":"14",
    "addr:postcode":"28230",
    "addr:street":"Calle De Vizcaya",
    "iso:country":"ES",
    "sg:address":"Calle de Vizcaya, 14",
    "sg:city":"Rozas De Madrid",
    "sg:orig_category":"Empresarios Y Productoras De Espect\u00c1culos",
    "sg:phone":"+34 916 37 09 37",
    "sg:postcode":"28230",
    "sg:province":"Madrid",
    "wof:name":"Inversiones Chico S.l.",
    "wof:placetype":"venue"
},
  "geometry": {"coordinates":[-3.8777399063,40.5018501282],"type":"Point"}
}