{
  "type": "Feature",
  "properties": {
    "iso:country":"ES",
    "sg:address":"Avda Andalucia, 11",
    "sg:city":"Orcera",
    "sg:orig_category":"Notarios",
    "sg:phone":"+34 953 48 02 57",
    "sg:postcode":"23370",
    "sg:province":"Ja\u00e9n",
    "wof:name":"Hidalgo Garcia Inmaculada",
    "wof:placetype":"venue"
},
  "geometry": {"coordinates":[-2.6611330509,38.3171463013],"type":"Point"}
}