{
  "type": "Feature",
  "properties": {
    "addr:full":"Calle de Iglesia, 9 Arahal Sevilla 41600",
    "addr:housenumber":"9",
    "addr:postcode":"41600",
    "addr:street":"Calle De Iglesia",
    "iso:country":"ES",
    "sg:address":"Calle de Iglesia, 9",
    "sg:city":"Arahal",
    "sg:orig_category":"Ropa Para Caballeros (al Por Menor)",
    "sg:phone":"+34 955 84 10 66",
    "sg:postcode":"41600",
    "sg:province":"Sevilla",
    "wof:name":"Cooperativa Industrial De Corte Y Confeccion",
    "wof:placetype":"venue"
},
  "geometry": {"coordinates":[-5.5432271957,37.2631988525],"type":"Point"}
}