{
  "type": "Feature",
  "properties": {
    "iso:country":"ES",
    "sg:address":"Calle de Amos Olivares, 10",
    "sg:city":"Pedro Mu\u00e7oz",
    "sg:orig_category":"Cajas De Ahorro",
    "sg:phone":"+34 926 58 73 08",
    "sg:postcode":"13620",
    "sg:province":"Ciudad Real",
    "sg:website":"www.unicaja.es",
    "wof:name":"Unicaja",
    "wof:placetype":"venue"
},
  "geometry": {"coordinates":[-2.9435579777,39.4077987671],"type":"Point"}
}