{
  "type": "Feature",
  "properties": {
    "addr:full":"Calle de Villatorres, 39 Jaen Ja\u00e9n 23009",
    "addr:housenumber":"39;jae\u0301n",
    "addr:postcode":"23009",
    "addr:street":"Calle De Villatorres",
    "iso:country":"ES",
    "sg:address":"Calle de Villatorres, 39",
    "sg:city":"Jaen",
    "sg:orig_category":"Hielo Artificial (fabricaci\u00d3n, Distribuci\u00d3n)",
    "sg:phone":"+34 953 28 03 00",
    "sg:postcode":"23009",
    "sg:province":"Ja\u00e9n",
    "wof:name":"Helados Y Postres S.a.",
    "wof:placetype":"venue"
},
  "geometry": {"coordinates":[-3.7818920612,37.8004760742],"type":"Point"}
}