{
  "type": "Feature",
  "properties": {
    "addr:full":"Calle de Finlandia, 29 Alcala Henares Madrid 28802",
    "addr:housenumber":"29",
    "addr:postcode":"28802",
    "addr:street":"Calle De Finlandia",
    "iso:country":"ES",
    "sg:address":"Calle de Finlandia, 29",
    "sg:city":"Alcala Henares",
    "sg:orig_category":"Pintura Y Barniz (al Por Menor)",
    "sg:phone":"+34 918 82 94 07",
    "sg:postcode":"28802",
    "sg:province":"Madrid",
    "wof:name":"Pinturas T. Esteban S.l.",
    "wof:placetype":"venue"
},
  "geometry": {"coordinates":[-3.3819701672,40.4819755554],"type":"Point"}
}