{
  "type": "Feature",
  "properties": {
    "addr:full":"Calle de Gabriel Aresti, 10 Santurtzi Vizcaya 48980",
    "addr:housenumber":"10",
    "addr:postcode":"48980",
    "addr:street":"Calle De Gabriel Aresti",
    "iso:country":"ES",
    "sg:address":"Calle de Gabriel Aresti, 10",
    "sg:city":"Santurtzi",
    "sg:orig_category":"Inform\u00c1tica: Soportes De Informaci\u00d3n, Suministros & Accesorios",
    "sg:phone":"+34 944 06 04 67",
    "sg:postcode":"48980",
    "sg:province":"Vizcaya",
    "wof:name":"Aitor Casin Y Jon Cortegoso Cb.",
    "wof:placetype":"venue"
},
  "geometry": {"coordinates":[-3.0326666832,43.3267364502],"type":"Point"}
}