{
  "type": "Feature",
  "properties": {
    "addr:full":"Calle de Real, 25 Roda Andalucia Sevilla 41590",
    "addr:housenumber":"25",
    "addr:postcode":"41590",
    "addr:street":"Calle De Real",
    "iso:country":"ES",
    "sg:address":"Calle de Real, 25",
    "sg:city":"Roda Andalucia",
    "sg:orig_category":"Ense\u00d1anza, Formaci\u00d3n Profesional: Aprendizaje",
    "sg:phone":"+34 954 01 60 02",
    "sg:postcode":"41590",
    "sg:province":"Sevilla",
    "wof:name":"Ayutamiento De La Roda De Andalucia",
    "wof:placetype":"venue"
},
  "geometry": {"coordinates":[-4.7792758942,37.2008056641],"type":"Point"}
}