{
  "type": "Feature",
  "properties": {
    "addr:full":"Calle de Rodriguez Zapata, 3 Alanis Sevilla 41380",
    "addr:postcode":"41380",
    "addr:street":"Calle De Rodriguez Zapata 3 Alanis",
    "iso:country":"ES",
    "sg:address":"Calle de Rodriguez Zapata, 3",
    "sg:city":"Alanis",
    "sg:orig_category":"T\u00c9cnicos Veterinarios",
    "sg:phone":"+34 954 88 50 98",
    "sg:postcode":"41380",
    "sg:province":"Sevilla",
    "wof:name":"Calderon Castellano Fernando Ramon",
    "wof:placetype":"venue"
},
  "geometry": {"coordinates":[-5.7131309509,38.0372543335],"type":"Point"}
}