{
  "type": "Feature",
  "properties": {
    "addr:full":"Carrer de Arago, 16 Barbera Valles Barcelona 08210",
    "addr:housenumber":"16",
    "addr:postcode":"08210",
    "addr:street":"Carrer De Arago",
    "iso:country":"ES",
    "sg:address":"Carrer de Arago, 16",
    "sg:city":"Barbera Valles",
    "sg:orig_category":"Asesor\u00cda Sobre Comunicaci\u00d3n De Empresas",
    "sg:phone":"+34 937 19 16 14",
    "sg:postcode":"08210",
    "sg:province":"Barcelona",
    "wof:name":"Gratia Consultoris Exerceo S.l.",
    "wof:placetype":"venue"
},
  "geometry": {"coordinates":[2.1228709221,41.5216217041],"type":"Point"}
}