{
  "type": "Feature",
  "properties": {
    "iso:country":"ES",
    "sg:address":"Calle de Minerva, 98",
    "sg:city":"Madrid",
    "sg:orig_category":"Reciclaje, Tratamiento De Tejidos",
    "sg:phone":"+34 917 76 02 70",
    "sg:postcode":"28032",
    "sg:province":"Madrid",
    "wof:name":"Fijo Serrano Antonio",
    "wof:placetype":"venue"
},
  "geometry": {"coordinates":[-3.6086349487,40.3943061829],"type":"Point"}
}