{
  "type": "Feature",
  "properties": {
    "iso:country":"ES",
    "sg:address":"Calle de Azucena, 5",
    "sg:city":"Lepe",
    "sg:orig_category":"Confecci\u00d3n (fabricaci\u00d3n, Al Por Mayor)",
    "sg:phone":"+34 959 38 21 70",
    "sg:postcode":"21440",
    "sg:province":"Huelva",
    "wof:name":"Toscano Rodriguez Concepcion",
    "wof:placetype":"venue"
},
  "geometry": {"coordinates":[-7.1955552101,37.2587280273],"type":"Point"}
}