{
  "type": "Feature",
  "properties": {
    "addr:full":"Carrer de Sant Antoni, 67 Riudoms Tarragona 43330",
    "addr:housenumber":"67",
    "addr:postcode":"43330",
    "addr:street":"Carrer De Sant Antoni",
    "iso:country":"ES",
    "sg:address":"Carrer de Sant Antoni, 67",
    "sg:city":"Riudoms",
    "sg:orig_category":"Agricultores, Agricultores",
    "sg:phone":"+34 977 85 03 59",
    "sg:postcode":"43330",
    "sg:province":"Tarragona",
    "wof:name":"Font Figueras Eduardo",
    "wof:placetype":"venue"
},
  "geometry": {"coordinates":[1.049399972,41.1390113831],"type":"Point"}
}