{
  "type": "Feature",
  "properties": {
    "iso:country":"ES",
    "sg:address":"Ctra Burgohondo, S/n",
    "sg:city":"Avila",
    "sg:orig_category":"Molduras, Junquillos, Listones Y Molduras Perforadas",
    "sg:phone":"+34 920 22 73 05",
    "sg:postcode":"05002",
    "sg:province":"\u00c1vila",
    "wof:name":"Gomez Blazquez Leandro",
    "wof:placetype":"venue"
},
  "geometry": {"coordinates":[-4.7031450272,40.6497688293],"type":"Point"}
}