{
  "type": "Feature",
  "properties": {
    "addr:full":"Calle de Agustina De Aragon, 97 Altorricon Huesca 22540",
    "addr:housenumber":"97",
    "addr:postcode":"22540",
    "addr:street":"Calle De Agustina De Aragon",
    "iso:country":"ES",
    "sg:address":"Calle de Agustina De Aragon, 97",
    "sg:city":"Altorricon",
    "sg:orig_category":"Flores Y Plantas Naturales (al Por Mayor)",
    "sg:phone":"+34 974 42 55 87",
    "sg:postcode":"22540",
    "sg:province":"Huesca",
    "wof:name":"Campos Mallen Julio",
    "wof:placetype":"venue"
},
  "geometry": {"coordinates":[0.4150558114,41.8028869629],"type":"Point"}
}