{
  "type": "Feature",
  "properties": {
    "iso:country":"ES",
    "sg:address":"Ctra. Escorial-avila, Km. 0069,9",
    "sg:city":"Navalperal Pinares",
    "sg:orig_category":"Cerrajer\u00cda, Ferrallista",
    "sg:phone":"+34 918 98 02 63",
    "sg:postcode":"05240",
    "sg:province":"\u00c1vila",
    "wof:name":"Hermanos Bartolome De La Aldea C.b.",
    "wof:placetype":"venue"
},
  "geometry": {"coordinates":[-4.4111189842,40.5906181335],"type":"Point"}
}