{
  "type": "Feature",
  "properties": {
    "addr:full":"Calle de Marques De Cubas, 18 Madrid Madrid 28014",
    "addr:housenumber":"18",
    "addr:postcode":"madrid;28014",
    "addr:street":"Calle De Marques De Cubas",
    "iso:country":"ES",
    "sg:address":"Calle de Marques De Cubas, 18",
    "sg:city":"Madrid",
    "sg:orig_category":"Fotocopias, Reprograf\u00cda",
    "sg:phone":"+34 914 20 23 97",
    "sg:postcode":"28014",
    "sg:province":"Madrid",
    "wof:name":"Fuente De Neptuno. Comunidad De Bienes",
    "wof:placetype":"venue"
},
  "geometry": {"coordinates":[-3.6959609985,40.4163169861],"type":"Point"}
}