{
  "type": "Feature",
  "properties": {
    "addr:full":"Calle de Francia, 16 Vitoria-gasteiz \u00c1lava 01002",
    "addr:housenumber":"16",
    "addr:postcode":"01002",
    "addr:street":"Calle De Francia",
    "iso:country":"ES",
    "sg:address":"Calle de Francia, 16",
    "sg:city":"Vitoria-gasteiz",
    "sg:orig_category":"Cajas De Ahorro",
    "sg:phone":"+34 945 27 84 77",
    "sg:postcode":"01002",
    "sg:province":"\u00c1lava",
    "sg:website":"www.cajavital.es",
    "wof:name":"Caja De Ahorros De Vitoria Y Alava",
    "wof:placetype":"venue"
},
  "geometry": {"coordinates":[-2.6680738926,42.8484535217],"type":"Point"}
}