{
  "type": "Feature",
  "properties": {
    "iso:country":"ES",
    "sg:address":"Av Catalunya, 40",
    "sg:city":"Mas Rampinyo",
    "sg:orig_category":"Asesor\u00cda Fiscal Y Jur\u00cddica",
    "sg:phone":"+34 935 64 85 61",
    "sg:postcode":"08110",
    "sg:province":"Barcelona",
    "wof:name":"Assessoria I Gestio Montcada S.l.",
    "wof:placetype":"venue"
},
  "geometry": {"coordinates":[2.1827960014,41.4948883057],"type":"Point"}
}