{
  "type": "Feature",
  "properties": {
    "addr:full":"Av Ballester, 9 Viladecans Barcelona 08840",
    "addr:housenumber":"9",
    "addr:postcode":"08840",
    "addr:street":"Av Ballester",
    "iso:country":"ES",
    "sg:address":"Av Ballester, 9",
    "sg:city":"Viladecans",
    "sg:orig_category":"Centros M\u00c9dicos Y Sociales, Dispensarios",
    "sg:phone":"+34 936 59 23 38",
    "sg:postcode":"08840",
    "sg:province":"Barcelona",
    "wof:name":"Centro Medico Ballester S.l.",
    "wof:placetype":"venue"
},
  "geometry": {"coordinates":[2.00770998,41.3188018799],"type":"Point"}
}