{
  "type": "Feature",
  "properties": {
    "iso:country":"ES",
    "sg:address":"Carrer de Paris, 205",
    "sg:city":"Barcelona",
    "sg:orig_category":"Asesor\u00cda Sobre Comunicaci\u00d3n De Empresas",
    "sg:phone":"+34 932 00 73 78",
    "sg:postcode":"08008",
    "sg:province":"Barcelona",
    "wof:name":"Bienes Arrendados Urbanos S.l",
    "wof:placetype":"venue"
},
  "geometry": {"coordinates":[2.1536719799,41.3941612244],"type":"Point"}
}