{
  "type": "Feature",
  "properties": {
    "iso:country":"ES",
    "sg:address":"Crt. Pe\u00f1as S. Pedro, Km. 0001,5",
    "sg:city":"Albacete",
    "sg:orig_category":"Aguas (distribuci\u00d3n, Servicios)",
    "sg:phone":"+34 967 23 79 42",
    "sg:postcode":"02006",
    "sg:province":"Albacete",
    "wof:name":"Aguas De Albacete S.a.",
    "wof:placetype":"venue"
},
  "geometry": {"coordinates":[-1.8674970865,38.980266571],"type":"Point"}
}