{
  "type": "Feature",
  "properties": {
    "iso:country":"ES",
    "sg:address":"Calle de Granada, 64",
    "sg:city":"Laujar Andarax",
    "sg:orig_category":"Tractores Agr\u00cdcolas Y Remolques",
    "sg:phone":"+34 950 51 32 75",
    "sg:postcode":"04470",
    "sg:province":"Almer\u00eda",
    "wof:name":"Lopez Diaz Vicente",
    "wof:placetype":"venue"
},
  "geometry": {"coordinates":[-2.8951487541,36.9932785034],"type":"Point"}
}