{
  "type": "Feature",
  "properties": {
    "iso:country":"ES",
    "sg:address":"Plaz Cervantes, 4",
    "sg:city":"Ciudad Real",
    "sg:orig_category":"Asesor\u00cda Fiscal Y Jur\u00cddica",
    "sg:phone":"+34 926 21 17 60",
    "sg:postcode":"13001",
    "sg:province":"Ciudad Real",
    "wof:name":"Vera Asesoria Y Gestion S.l.",
    "wof:placetype":"venue"
},
  "geometry": {"coordinates":[-3.928839922,38.9841918945],"type":"Point"}
}