{
  "type": "Feature",
  "properties": {
    "iso:country":"ES",
    "sg:address":"G.v. Corts Catalanes, 839",
    "sg:city":"Barcelona",
    "sg:orig_category":"Molduras, Junquillos, Listones Y Molduras Perforadas",
    "sg:phone":"+34 933 00 50 15",
    "sg:postcode":"08018",
    "sg:province":"Barcelona",
    "wof:name":"Roca Egea Marta",
    "wof:placetype":"venue"
},
  "geometry": {"coordinates":[2.189496994,41.4057540894],"type":"Point"}
}