{
  "type": "Feature",
  "properties": {
    "addr:full":"Calle de Salzillo, 1 Puente Tocinos Murcia 30006",
    "addr:housenumber":"1",
    "addr:postcode":"30006",
    "addr:street":"Calle De Salzillo",
    "iso:country":"ES",
    "sg:address":"Calle de Salzillo, 1",
    "sg:city":"Puente Tocinos",
    "sg:orig_category":"Soldadura, Equipo Y Herramental",
    "sg:phone":"+34 968 30 12 00",
    "sg:postcode":"30006",
    "sg:province":"Murcia",
    "wof:name":"Perez Marin Francisco",
    "wof:placetype":"venue"
},
  "geometry": {"coordinates":[-1.1009750366,37.9951438904],"type":"Point"}
}