{
  "type": "Feature",
  "properties": {
    "iso:country":"ES",
    "sg:address":"Carrer de Periodista Grane, 21",
    "sg:city":"Terrassa",
    "sg:orig_category":"Molduras, Junquillos, Listones Y Molduras Perforadas",
    "sg:phone":"+34 937 31 75 81",
    "sg:postcode":"08226",
    "sg:province":"Barcelona",
    "wof:name":"Cafeteria El Tazon S.l.",
    "wof:placetype":"venue"
},
  "geometry": {"coordinates":[2.0239241123,41.5700874329],"type":"Point"}
}