{
  "type": "Feature",
  "properties": {
    "addr:full":"Calle de Afan De Ribera, 119 Sevilla Sevilla 41006",
    "addr:housenumber":"119",
    "addr:postcode":"41006",
    "addr:street":"Calle De Afan De Ribera",
    "iso:country":"ES",
    "sg:address":"Calle de Afan De Ribera, 119",
    "sg:city":"Sevilla",
    "sg:orig_category":"Cervecer\u00cdas",
    "sg:phone":"+34 954 92 06 78",
    "sg:postcode":"41006",
    "sg:province":"Sevilla",
    "wof:name":"Ramos Ballesteros Angel",
    "wof:placetype":"venue"
},
  "geometry": {"coordinates":[-5.9583883286,37.3726272583],"type":"Point"}
}