{
  "type": "Feature",
  "properties": {
    "iso:country":"ES",
    "sg:address":"Carrer de Bruc, 35",
    "sg:city":"Manresa",
    "sg:classifiers":[
        {
            "category":"Government",
            "subcategory":"Office",
            "type":"Public Place"
        }
    ],
    "sg:phone":"+34 938 72 91 00",
    "sg:postcode":"08241",
    "sg:province":"Barcelona",
    "sg:tags":[
        "interior",
        "administraci\u00d3n",
        "en"
    ],
    "wof:name":"Ajuntament-proteccio Civil",
    "wof:placetype":"venue"
},
  "geometry": {"coordinates":[1.8182841539,41.7232704163],"type":"Point"}
}