{
  "type": "Feature",
  "properties": {
    "addr:full":"Calle de Munich, S/n Alcorcon Madrid 28923",
    "addr:housenumber":"s / n",
    "addr:postcode":"28923",
    "addr:street":"Calle De Munich",
    "iso:country":"ES",
    "sg:address":"Calle de Munich, S/n",
    "sg:city":"Alcorcon",
    "sg:orig_category":"Pescader\u00cdas (al Por Menor)",
    "sg:phone":"+34 916 12 25 98",
    "sg:postcode":"28923",
    "sg:province":"Madrid",
    "wof:name":"Frances Serrano Mariano",
    "wof:placetype":"venue"
},
  "geometry": {"coordinates":[-3.8153231144,40.3446578979],"type":"Point"}
}