{
  "type": "Feature",
  "properties": {
    "addr:full":"Rua Carreira, 5 Carballi\u00f1o Ourense 32500",
    "addr:housenumber":"5",
    "addr:postcode":"32500",
    "addr:street":"Rua Carreira",
    "iso:country":"ES",
    "sg:address":"Rua Carreira, 5",
    "sg:city":"Carballi\u00f1o",
    "sg:orig_category":"Peluquer\u00cdas, Peluquer\u00cda Mixta",
    "sg:phone":"+34 988 27 52 64",
    "sg:postcode":"32500",
    "sg:province":"Ourense",
    "wof:name":"Cabel Carballino S.l.",
    "wof:placetype":"venue"
},
  "geometry": {"coordinates":[-8.0740194321,42.4299507141],"type":"Point"}
}