{
  "type": "Feature",
  "properties": {
    "iso:country":"ES",
    "sg:address":"Calle de Sarrikobaso, 7",
    "sg:city":"Algorta",
    "sg:orig_category":"Empresas De Carpinter\u00cda De Madera",
    "sg:phone":"+34 944 30 86 74",
    "sg:postcode":"48993",
    "sg:province":"Vizcaya",
    "wof:name":"Tubio Pose Maximino",
    "wof:placetype":"venue"
},
  "geometry": {"coordinates":[-3.0093226433,43.3554229736],"type":"Point"}
}