{
  "type": "Feature",
  "properties": {
    "iso:country":"ES",
    "sg:address":"Calle de Reyes Magos, 2",
    "sg:city":"Valladolid",
    "sg:orig_category":"Suministros Y Materiales Industriales",
    "sg:phone":"+34 983 39 69 90",
    "sg:postcode":"47011",
    "sg:province":"Valladolid",
    "sg:website":"www.spray-cas.com",
    "wof:name":"Spraying Systems Spain S.l.",
    "wof:placetype":"venue"
},
  "geometry": {"coordinates":[-4.7084360123,41.6587753296],"type":"Point"}
}