{
  "type": "Feature",
  "properties": {
    "addr:full":"Carrer de Joan Ripoll Trobat, 12 Palma Islas Baleares 07013",
    "addr:housenumber":"12",
    "addr:postcode":"07013",
    "addr:street":"Carrer De Joan Ripoll Trobat",
    "iso:country":"ES",
    "sg:address":"Carrer de Joan Ripoll Trobat, 12",
    "sg:city":"Palma",
    "sg:orig_category":"Molduras, Junquillos, Listones Y Molduras Perforadas",
    "sg:phone":"+34 971 45 51 50",
    "sg:postcode":"07013",
    "sg:province":"Islas Baleares",
    "wof:name":"Pildz  Alexander Friedrich",
    "wof:placetype":"venue"
},
  "geometry": {"coordinates":[2.6268789768,39.5807762146],"type":"Point"}
}