{
  "type": "Feature",
  "properties": {
    "addr:full":"Av Pont, 3 Solsona Lleida 25280",
    "addr:housenumber":"3",
    "addr:postcode":"25280",
    "addr:street":"Av Pont",
    "iso:country":"ES",
    "sg:address":"Av Pont, 3",
    "sg:city":"Solsona",
    "sg:orig_category":"Arquitectos",
    "sg:phone":"+34 973 48 00 14",
    "sg:postcode":"25280",
    "sg:province":"Lleida",
    "wof:name":"Viladrich Ros Juan",
    "wof:placetype":"venue"
},
  "geometry": {"coordinates":[1.5221300125,41.995059967],"type":"Point"}
}