{
  "type": "Feature",
  "properties": {
    "addr:full":"Calle de Maria Luisa De Orleans (de), 28 Boadilla Del Monte Madrid 28660",
    "addr:housenumber":"28",
    "addr:postcode":"28660",
    "addr:street":"Calle De Maria Luisa De Orleans De",
    "iso:country":"ES",
    "sg:address":"Calle de Maria Luisa De Orleans (de), 28",
    "sg:city":"Boadilla Del Monte",
    "sg:orig_category":"Empresarios",
    "sg:phone":"+34 916 33 42 35",
    "sg:postcode":"28660",
    "sg:province":"Madrid",
    "wof:name":"Fernandez Roldan Concepcion",
    "wof:placetype":"venue"
},
  "geometry": {"coordinates":[-3.885258913,40.4084281921],"type":"Point"}
}