{
  "type": "Feature",
  "properties": {
    "addr:full":"Fraiz, S/n Villestro La Coru\u00f1a 15896",
    "addr:postcode":"15896",
    "addr:street":"Fraiz S / N Villestro La Corun\u0303A",
    "iso:country":"ES",
    "sg:address":"Fraiz, S/n",
    "sg:city":"Villestro",
    "sg:orig_category":"Electricidad (montaje, Ensamblaje De Componentes)",
    "sg:phone":"+34 981 53 72 84",
    "sg:postcode":"15896",
    "sg:province":"La Coru\u00f1a",
    "wof:name":"Sanchez Pereira Javier",
    "wof:placetype":"venue"
},
  "geometry": {"coordinates":[-8.6102218628,42.8763961792],"type":"Point"}
}