{
  "type": "Feature",
  "properties": {
    "addr:full":"Avda Manzano (del), S/n Biescas Huesca 22630",
    "addr:housenumber":"/ n",
    "addr:postcode":"22630",
    "addr:street":"Avda Manzano Del S",
    "iso:country":"ES",
    "sg:address":"Avda Manzano (del), S/n",
    "sg:city":"Biescas",
    "sg:orig_category":"Molduras, Junquillos, Listones Y Molduras Perforadas",
    "sg:phone":"+34 974 48 52 88",
    "sg:postcode":"22630",
    "sg:province":"Huesca",
    "wof:name":"Lacasa Puertolas Luis",
    "wof:placetype":"venue"
},
  "geometry": {"coordinates":[-0.3269860148,42.6225318909],"type":"Point"}
}