{
  "type": "Feature",
  "properties": {
    "iso:country":"ES",
    "sg:address":"Avda Ramon Y Cajal, 30",
    "sg:city":"Fuengirola",
    "sg:orig_category":"Ropa De Hogar (al Por Menor)",
    "sg:phone":"+34 952 47 67 53",
    "sg:postcode":"29640",
    "sg:province":"M\u00e1laga",
    "wof:name":"Cachoui  Nadia",
    "wof:placetype":"venue"
},
  "geometry": {"coordinates":[-4.6192541122,36.5457954407],"type":"Point"}
}