{
  "type": "Feature",
  "properties": {
    "addr:full":"Finca Valbueno, S/n Cabanillas Campo Guadalajara 19171",
    "addr:housenumber":"s",
    "addr:postcode":"19171",
    "addr:street":"/ N",
    "iso:country":"ES",
    "sg:address":"Finca Valbueno, S/n",
    "sg:city":"Cabanillas Campo",
    "sg:orig_category":"Producci\u00d3n, Venta De Productos De Agricultura Biol\u00d3gica",
    "sg:phone":"+34 949 82 08 44",
    "sg:postcode":"19171",
    "sg:province":"Guadalajara",
    "wof:name":"Granja T.c. Del Jarama",
    "wof:placetype":"venue"
},
  "geometry": {"coordinates":[-3.2438578606,40.6374664307],"type":"Point"}
}