{
  "type": "Feature",
  "properties": {
    "iso:country":"ES",
    "sg:address":"G.v. Marques Del Turia, 44",
    "sg:city":"Valencia",
    "sg:orig_category":"Inmobiliaria (agencias)",
    "sg:phone":"+34 963 95 32 12",
    "sg:postcode":"46005",
    "sg:province":"Valencia",
    "sg:website":"www.impersa.com",
    "wof:name":"Imper S.l.",
    "wof:placetype":"venue"
},
  "geometry": {"coordinates":[-0.3692550063,39.466583252],"type":"Point"}
}