{
  "type": "Feature",
  "properties": {
    "iso:country":"ES",
    "sg:address":"Carrer de Tamarit, 109",
    "sg:city":"Barcelona",
    "sg:orig_category":"Molduras, Junquillos, Listones Y Molduras Perforadas",
    "sg:phone":"+34 934 24 15 05",
    "sg:postcode":"08015",
    "sg:province":"Barcelona",
    "wof:name":"Rosell Sanchez Jose Manuel",
    "wof:placetype":"venue"
},
  "geometry": {"coordinates":[2.1573131084,41.3760643005],"type":"Point"}
}