{
  "type": "Feature",
  "properties": {
    "addr:full":"Calle de Jose Ortega Y Gasset, 91 Madrid Madrid 28006",
    "addr:housenumber":"91",
    "addr:postcode":"madrid;28006",
    "addr:street":"Calle De Jose Ortega Y Gasset",
    "iso:country":"ES",
    "sg:address":"Calle de Jose Ortega Y Gasset, 91",
    "sg:city":"Madrid",
    "sg:orig_category":"Restaurantes",
    "sg:phone":"+34 914 02 83 99",
    "sg:postcode":"28006",
    "sg:province":"Madrid",
    "wof:name":"Mardel Hosteleria S.l.",
    "wof:placetype":"venue"
},
  "geometry": {"coordinates":[-3.6708440781,40.4298171997],"type":"Point"}
}