{
  "type": "Feature",
  "properties": {
    "addr:full":"Carrer de Palma (la), 6 Vilafranca Penedes Barcelona 08720",
    "addr:postcode":"08720",
    "addr:street":"Carrer De Palma;6 Vilafranca Penedes Barcelona",
    "iso:country":"ES",
    "sg:address":"Carrer de Palma (la), 6",
    "sg:city":"Vilafranca Penedes",
    "sg:orig_category":"Ropa Para Se\u00d1oras Y Caballeros (al Por Menor)",
    "sg:phone":"+34 938 18 23 18",
    "sg:postcode":"08720",
    "sg:province":"Barcelona",
    "wof:name":"Forja Singular S.c.p.",
    "wof:placetype":"venue"
},
  "geometry": {"coordinates":[1.7006189823,41.3464202881],"type":"Point"}
}