{
  "type": "Feature",
  "properties": {
    "addr:full":"Calle de Virgen Del Socorro, 23 Alacant Alicante 03002",
    "addr:housenumber":"23",
    "addr:postcode":"03002",
    "addr:street":"Calle De Virgen Del Socorro",
    "iso:country":"ES",
    "sg:address":"Calle de Virgen Del Socorro, 23",
    "sg:city":"Alacant",
    "sg:orig_category":"Agencias Y Agentes Comerciales, Representantes",
    "sg:phone":"+34 965 15 61 10",
    "sg:postcode":"03002",
    "sg:province":"Alicante",
    "wof:name":"Projar Alicante 2005 S.l.",
    "wof:placetype":"venue"
},
  "geometry": {"coordinates":[-0.4738309979,38.3495597839],"type":"Point"}
}