{
  "type": "Feature",
  "properties": {
    "iso:country":"ES",
    "sg:address":"Rua Canido, S/n",
    "sg:city":"Vilamean",
    "sg:orig_category":"Distribuci\u00d3n De Petr\u00d3leo Y Derivados",
    "sg:phone":"+34 986 36 50 41",
    "sg:postcode":"36350",
    "sg:province":"Pontevedra",
    "wof:name":"Pescaramos S.l.",
    "wof:placetype":"venue"
},
  "geometry": {"coordinates":[-8.8101167679,42.1421012878],"type":"Point"}
}