{
  "type": "Feature",
  "properties": {
    "iso:country":"ES",
    "sg:address":"Carrer de Santa Clara, 24",
    "sg:city":"Vilafranca Penedes",
    "sg:orig_category":"Arreglo, Reparaci\u00d3n, Piezas Sueltas De Televisi\u00d3n, V\u00cddeo, Hi",
    "sg:phone":"+34 938 92 24 46",
    "sg:postcode":"08720",
    "sg:province":"Barcelona",
    "wof:name":"Guilera Suriol Jordi",
    "wof:placetype":"venue"
},
  "geometry": {"coordinates":[1.7018569708,41.346660614],"type":"Point"}
}