{
  "type": "Feature",
  "properties": {
    "addr:full":"Calle de Ernesto Anastasio, 85 Valencia Valencia 46011",
    "addr:housenumber":"85",
    "addr:postcode":"46011",
    "addr:street":"Calle De Ernesto Anastasio",
    "iso:country":"ES",
    "sg:address":"Calle de Ernesto Anastasio, 85",
    "sg:city":"Valencia",
    "sg:orig_category":"Venta Al Preg\u00d3n",
    "sg:phone":"+34 963 71 68 65",
    "sg:postcode":"46011",
    "sg:province":"Valencia",
    "wof:name":"Ferrer Sanchis Facundo",
    "wof:placetype":"venue"
},
  "geometry": {"coordinates":[-0.3338451982,39.4666175842],"type":"Point"}
}