{
  "type": "Feature",
  "properties": {
    "iso:country":"ES",
    "sg:address":"Calle de Isla Redonda, 60",
    "sg:city":"Estacion",
    "sg:orig_category":"Agencias Y Asesores De Publicidad",
    "sg:phone":"+34 918 51 91 25",
    "sg:postcode":"28400",
    "sg:province":"Madrid",
    "sg:website":"www.motivacionpublicitaria.com",
    "wof:name":"Motivacion Publicitaria S.l.",
    "wof:placetype":"venue"
},
  "geometry": {"coordinates":[-4.0154080391,40.6210594177],"type":"Point"}
}