{
  "type": "Feature",
  "properties": {
    "addr:full":"Av Catalunya, 13 Vila-sana Lleida 25245",
    "addr:housenumber":"13",
    "addr:postcode":"25245",
    "addr:street":"Av Catalunya",
    "iso:country":"ES",
    "sg:address":"Av Catalunya, 13",
    "sg:city":"Vila-sana",
    "sg:orig_category":"Torneros Sobre Madera",
    "sg:phone":"+34 973 60 27 58",
    "sg:postcode":"25245",
    "sg:province":"Lleida",
    "wof:name":"Vela Chamon Enrique Felix",
    "wof:placetype":"venue"
},
  "geometry": {"coordinates":[0.9260579944,41.6637458801],"type":"Point"}
}