{
  "type": "Feature",
  "properties": {
    "iso:country":"ES",
    "sg:address":"Carrer de Palau Reial, 6",
    "sg:city":"Palma",
    "sg:orig_category":"Art\u00cdculos De Decoraci\u00d3n",
    "sg:phone":"+34 971 71 78 57",
    "sg:postcode":"07001",
    "sg:province":"Islas Baleares",
    "wof:name":"Garcia Orell Juan",
    "wof:placetype":"venue"
},
  "geometry": {"coordinates":[2.6492340565,39.567363739],"type":"Point"}
}