{
  "type": "Feature",
  "properties": {
    "iso:country":"ES",
    "sg:address":"Calle de Palma, 45",
    "sg:city":"Madrid",
    "sg:orig_category":"Droguer\u00cdas (al Por Menor)",
    "sg:phone":"+34 915 31 15 14",
    "sg:postcode":"28004",
    "sg:province":"Madrid",
    "wof:name":"Perez Marin Maria Del Carmen",
    "wof:placetype":"venue"
},
  "geometry": {"coordinates":[-3.705395937,40.4263381958],"type":"Point"}
}