{
  "type": "Feature",
  "properties": {
    "addr:full":"Pl Pau (de La), 2 Tortosa Tarragona 43500",
    "addr:housenumber":"2",
    "addr:postcode":"43500",
    "addr:street":"Pl Pau De La",
    "iso:country":"ES",
    "sg:address":"Pl Pau (de La), 2",
    "sg:city":"Tortosa",
    "sg:orig_category":"M\u00c9dicos: Dermatolog\u00cda Y Venereolog\u00cda",
    "sg:phone":"+34 977 44 09 45",
    "sg:postcode":"43500",
    "sg:province":"Tarragona",
    "wof:name":"Gilabert Vericat Emilio",
    "wof:placetype":"venue"
},
  "geometry": {"coordinates":[0.5201020241,40.8116950989],"type":"Point"}
}