{
  "type": "Feature",
  "properties": {
    "iso:country":"ES",
    "sg:address":"Av Principe Felipe De Borbon, Km. 0158,0",
    "sg:city":"Las Pedro\u00f1eras",
    "sg:orig_category":"Artesan\u00cda",
    "sg:phone":"+34 967 16 04 65",
    "sg:postcode":"16660",
    "sg:province":"Cuenca",
    "wof:name":"Escudero Martinez Francisco",
    "wof:placetype":"venue"
},
  "geometry": {"coordinates":[-2.676858902,39.4508552551],"type":"Point"}
}