{
  "type": "Feature",
  "properties": {
    "iso:country":"ES",
    "sg:address":"Urb. Parque Avenida, 5",
    "sg:city":"Jerez",
    "sg:orig_category":"M\u00c9dicos: Estomatolog\u00cda",
    "sg:phone":"+34 956 30 24 36",
    "sg:postcode":"11405",
    "sg:province":"C\u00e1diz",
    "wof:name":"Quijada Carrera Antonio",
    "wof:placetype":"venue"
},
  "geometry": {"coordinates":[-6.118347168,36.6979522705],"type":"Point"}
}