{
  "type": "Feature",
  "properties": {
    "iso:country":"ES",
    "sg:address":"Avda Zugatzarte, 8",
    "sg:city":"Getxo",
    "sg:orig_category":"Abogados",
    "sg:phone":"+34 944 64 62 66",
    "sg:postcode":"48930",
    "sg:province":"Vizcaya",
    "wof:name":"Aab Abogados, S.l.",
    "wof:placetype":"venue"
},
  "geometry": {"coordinates":[-3.014696,43.328056],"type":"Point"}
}