{
  "type": "Feature",
  "properties": {
    "iso:country":"ES",
    "sg:address":"Calle de Republica Argentina, 7",
    "sg:city":"Badajoz",
    "sg:orig_category":"Granos Y Semillas (producci\u00d3n, Al Por Mayor)",
    "sg:phone":"+34 924 25 08 10",
    "sg:postcode":"06005",
    "sg:province":"Badajoz",
    "wof:name":"Semilla Jad Iberica S. A.",
    "wof:placetype":"venue"
},
  "geometry": {"coordinates":[-6.9777979851,38.8730888367],"type":"Point"}
}