{
  "type": "Feature",
  "properties": {
    "addr:full":"Carretera De Caceres-alcantara, 7 Brozas C\u00e1ceres 10950",
    "addr:housenumber":"7",
    "addr:postcode":"10950",
    "addr:street":"Carretera De Caceres-Alcantara;Ca\u0301Ceres",
    "iso:country":"ES",
    "sg:address":"Carretera De Caceres-alcantara, 7",
    "sg:city":"Brozas",
    "sg:orig_category":"Pintura, Barniz, Productos Asimilables (fabricaci\u00d3n, Al Por Mayor)",
    "sg:phone":"+34 927 37 30 86",
    "sg:postcode":"10950",
    "sg:province":"C\u00e1ceres",
    "wof:name":"Cancho Saez Atilano",
    "wof:placetype":"venue"
},
  "geometry": {"coordinates":[-6.7763600349,39.6160469055],"type":"Point"}
}