{
  "type": "Feature",
  "properties": {
    "iso:country":"ES",
    "sg:address":"Calle de San Jose, 11",
    "sg:city":"Burgos",
    "sg:orig_category":"Panader\u00cdas, Panader\u00cdas",
    "sg:phone":"+34 947 26 18 29",
    "sg:postcode":"09002",
    "sg:province":"Burgos",
    "wof:name":"Panificadora Burgalesa S.l.",
    "wof:placetype":"venue"
},
  "geometry": {"coordinates":[-3.6927719116,42.3385734558],"type":"Point"}
}