{
  "type": "Feature",
  "properties": {
    "addr:full":"Calle de Electrodo (del), 72 Partija-santa Monica Madrid 28529",
    "addr:housenumber":"72",
    "addr:postcode":"28529",
    "addr:street":"Calle De Electrodo Del",
    "iso:country":"ES",
    "sg:address":"Calle de Electrodo (del), 72",
    "sg:city":"Partija-santa Monica",
    "sg:orig_category":"Ropa De Casa (fabricaci\u00d3n, Al Por Mayor)",
    "sg:phone":"+34 914 99 43 60",
    "sg:postcode":"28529",
    "sg:province":"Madrid",
    "wof:name":"Sicilia Rubio Maria Dolores",
    "wof:placetype":"venue"
},
  "geometry": {"coordinates":[-3.5102670193,40.314289093],"type":"Point"}
}