{
  "type": "Feature",
  "properties": {
    "iso:country":"ES",
    "sg:address":"Plaz Nuestra Se\u00d1ora Del Transito, 4",
    "sg:city":"Madrid",
    "sg:orig_category":"Asociaciones, Organismos Culturales Y Socioeducativos",
    "sg:phone":"+34 917 21 92 55",
    "sg:postcode":"28043",
    "sg:province":"Madrid",
    "wof:name":"Tritoma S.l.",
    "wof:placetype":"venue"
},
  "geometry": {"coordinates":[-3.6476199627,40.4602127075],"type":"Point"}
}