{
  "type": "Feature",
  "properties": {
    "addr:full":"Calle de Escritores, 18 G\u00fcevejar Granada 18197",
    "addr:housenumber":"18",
    "addr:postcode":"18197",
    "addr:street":"Calle De Escritores",
    "iso:country":"ES",
    "sg:address":"Calle de Escritores, 18",
    "sg:city":"G\u00fcevejar",
    "sg:orig_category":"Farmacias",
    "sg:phone":"+34 958 42 80 02",
    "sg:postcode":"18197",
    "sg:province":"Granada",
    "wof:name":"Pilar Alcaide Mercado Y Pilar Alba Mu\u00f1oz C.b.",
    "wof:placetype":"venue"
},
  "geometry": {"coordinates":[-3.5968990326,37.2574768066],"type":"Point"}
}