{
  "type": "Feature",
  "properties": {
    "iso:country":"ES",
    "sg:address":"San Miguel De Geneto, Km. 0003,0",
    "sg:city":"San Cristobal De La Laguna",
    "sg:orig_category":"Refiner\u00cdas De Petr\u00d3leo",
    "sg:phone":"+34 922 63 33 82",
    "sg:postcode":"38296",
    "sg:province":"Santa Cruz De Tenerife",
    "wof:name":"Heliodoro Estevez Rodriguez S.l.",
    "wof:placetype":"venue"
},
  "geometry": {"coordinates":[-16.3171482086,28.4719200134],"type":"Point"}
}