{
  "type": "Feature",
  "properties": {
    "iso:country":"ES",
    "sg:address":"Calle de Alcazar De Toledo, 7",
    "sg:city":"Corrales",
    "sg:orig_category":"M\u00c9dicos: Estomatolog\u00cda",
    "sg:phone":"+34 942 83 17 82",
    "sg:postcode":"39400",
    "sg:province":"Cantabria",
    "wof:name":"Ruiz Dou Eladio",
    "wof:placetype":"venue"
},
  "geometry": {"coordinates":[-4.068087101,43.2592163086],"type":"Point"}
}