{
  "type": "Feature",
  "properties": {
    "iso:country":"ES",
    "sg:address":"Calle de Escultor Martin Chirino, 25",
    "sg:city":"Carrizal",
    "sg:orig_category":"Flores Y Plantas Naturales (al Por Mayor)",
    "sg:phone":"+34 928 78 40 37",
    "sg:postcode":"35240",
    "sg:province":"Las Palmas",
    "wof:name":"Rodriguez Mendez Francisco",
    "wof:placetype":"venue"
},
  "geometry": {"coordinates":[-15.4015016556,27.909734726],"type":"Point"}
}