{
  "type": "Feature",
  "properties": {
    "iso:country":"ES",
    "sg:address":"Carrer de Espronceda, 329",
    "sg:city":"Barcelona",
    "sg:orig_category":"Ropa Para Ni\u00d1os (al Por Menor)",
    "sg:phone":"+34 934 08 50 34",
    "sg:postcode":"08027",
    "sg:province":"Barcelona",
    "wof:name":"Juis Fashion S.l.",
    "wof:placetype":"venue"
},
  "geometry": {"coordinates":[2.1906080246,41.4157447815],"type":"Point"}
}