{
  "type": "Feature",
  "properties": {
    "addr:full":"Marieluts Auzoa, 2 Hernani Guip\u00f9zcoa 20120",
    "addr:housenumber":"2",
    "addr:postcode":"20120",
    "addr:street":"Marieluts Auzoa;Guipu\u0300Zcoa",
    "iso:country":"ES",
    "sg:address":"Marieluts Auzoa, 2",
    "sg:city":"Hernani",
    "sg:orig_category":"Asociaciones, Organismos Culturales Y Socioeducativos",
    "sg:phone":"+34 943 55 56 81",
    "sg:postcode":"20120",
    "sg:province":"Guip\u00f9zcoa",
    "wof:name":"Karobi Elkartea",
    "wof:placetype":"venue"
},
  "geometry": {"coordinates":[-1.9811329842,43.2697143555],"type":"Point"}
}