{
  "type": "Feature",
  "properties": {
    "addr:full":"Pol Atalayas, S/n Alacant Alicante 03006",
    "addr:housenumber":"/ n",
    "addr:postcode":"03006",
    "addr:street":"Atalayas S",
    "iso:country":"ES",
    "sg:address":"Pol Atalayas, S/n",
    "sg:city":"Alacant",
    "sg:orig_category":"Fabricaci\u00d3n De Art\u00cdculos Y Equipos Deportivos Y De Ocio",
    "sg:phone":"+34 965 10 67 09",
    "sg:postcode":"03006",
    "sg:province":"Alicante",
    "wof:name":"Piscis Pesca S.l.",
    "wof:placetype":"venue"
},
  "geometry": {"coordinates":[-0.4804739952,38.3440856934],"type":"Point"}
}