{
  "type": "Feature",
  "properties": {
    "addr:full":"Carrer de Verdi, 138 Barcelona Barcelona 08012",
    "addr:housenumber":"138",
    "addr:postcode":"08012",
    "addr:street":"Carrer De Verdi",
    "iso:country":"ES",
    "sg:address":"Carrer de Verdi, 138",
    "sg:city":"Barcelona",
    "sg:orig_category":"Restaurantes",
    "sg:phone":"+34 934 15 39 96",
    "sg:postcode":"08012",
    "sg:province":"Barcelona",
    "wof:name":"Martin Lopez Ramon",
    "wof:placetype":"venue"
},
  "geometry": {"coordinates":[2.1535460949,41.4073753357],"type":"Point"}
}