{
  "type": "Feature",
  "properties": {
    "addr:full":"Calle de Mendizabal, 3 Oviedo Asturias 33003",
    "addr:housenumber":"3",
    "addr:postcode":"33003",
    "addr:street":"Calle De Mendizabal",
    "iso:country":"ES",
    "sg:address":"Calle de Mendizabal, 3",
    "sg:city":"Oviedo",
    "sg:orig_category":"Asociaciones, Organismos Culturales Y Socioeducativos",
    "sg:phone":"+34 985 21 22 37",
    "sg:postcode":"33003",
    "sg:province":"Asturias",
    "wof:name":"Sociedad Filarmonica",
    "wof:placetype":"venue"
},
  "geometry": {"coordinates":[-5.8460350037,43.3628692627],"type":"Point"}
}