{
  "type": "Feature",
  "properties": {
    "iso:country":"ES",
    "sg:address":"Calle de Real, 154",
    "sg:city":"Pesquera Duero",
    "sg:orig_category":"Productores Recolectores, Venta Directa De Vinos",
    "sg:phone":"+34 983 87 01 05",
    "sg:postcode":"47315",
    "sg:province":"Valladolid",
    "wof:name":"Bodegas Federico S.l.",
    "wof:placetype":"venue"
},
  "geometry": {"coordinates":[-4.153678894,41.6420097351],"type":"Point"}
}