{
  "type": "Feature",
  "properties": {
    "addr:full":"Carrer de Joan Guell, 44 Barcelona Barcelona 08028",
    "addr:housenumber":"44",
    "addr:postcode":"08028",
    "addr:street":"Carrer De Joan Guell",
    "iso:country":"ES",
    "sg:address":"Carrer de Joan Guell, 44",
    "sg:city":"Barcelona",
    "sg:orig_category":"Reposter\u00cdas",
    "sg:phone":"+34 934 90 85 61",
    "sg:postcode":"08028",
    "sg:province":"Barcelona",
    "wof:name":"Tellez Pujol Almudena",
    "wof:placetype":"venue"
},
  "geometry": {"coordinates":[2.1337380409,41.3783187866],"type":"Point"}
}