{
  "type": "Feature",
  "properties": {
    "addr:full":"Calle de Emilio Tuya, 60 Gijon Asturias 33203",
    "addr:housenumber":"60",
    "addr:postcode":"33203",
    "addr:street":"Calle De Emilio Tuya",
    "iso:country":"ES",
    "sg:address":"Calle de Emilio Tuya, 60",
    "sg:city":"Gijon",
    "sg:orig_category":"Pescader\u00cdas (al Por Menor)",
    "sg:phone":"+34 985 33 39 21",
    "sg:postcode":"33203",
    "sg:province":"Asturias",
    "wof:name":"Trigo Sanz Segismundo",
    "wof:placetype":"venue"
},
  "geometry": {"coordinates":[-5.6469316483,43.5379066467],"type":"Point"}
}