{
  "type": "Feature",
  "properties": {
    "addr:full":"Calle de Mayor, S/n Vera Almer\u00eda 04620",
    "addr:housenumber":"s / n;almeri\u0301a",
    "addr:postcode":"04620",
    "addr:street":"Calle De Mayor",
    "iso:country":"ES",
    "sg:address":"Calle de Mayor, S/n",
    "sg:city":"Vera",
    "sg:orig_category":"Peluquer\u00cdas",
    "sg:phone":"+34 950 39 17 60",
    "sg:postcode":"04620",
    "sg:province":"Almer\u00eda",
    "wof:name":"Alonso Lopez Damiana",
    "wof:placetype":"venue"
},
  "geometry": {"coordinates":[-1.8639945984,37.245300293],"type":"Point"}
}