{
  "type": "Feature",
  "properties": {
    "addr:full":"Carrer de Francesc Moragas, 64 Santa Coloma De Gramenet Barcelona 08922",
    "addr:housenumber":"64",
    "addr:postcode":"08922",
    "addr:street":"Carrer De Francesc Moragas",
    "iso:country":"ES",
    "sg:address":"Carrer de Francesc Moragas, 64",
    "sg:city":"Santa Coloma De Gramenet",
    "sg:orig_category":"Juegos Y Juguetes (al Por Menor)",
    "sg:phone":"+34 933 86 60 19",
    "sg:postcode":"08922",
    "sg:province":"Barcelona",
    "wof:name":"Carneado Ferreri Carlos",
    "wof:placetype":"venue"
},
  "geometry": {"coordinates":[2.2071020603,41.4486732483],"type":"Point"}
}