{
  "type": "Feature",
  "properties": {
    "iso:country":"ES",
    "sg:address":"Calle de Doctor Fco. Vazquez Limon, 4",
    "sg:city":"Huelva",
    "sg:orig_category":"Abogados",
    "sg:phone":"+34 959 24 41 94",
    "sg:postcode":"21002",
    "sg:province":"Huelva",
    "wof:name":"Azcarate Prieto Jose",
    "wof:placetype":"venue"
},
  "geometry": {"coordinates":[-6.9521670341,37.2611503601],"type":"Point"}
}