{
  "type": "Feature",
  "properties": {
    "iso:country":"ES",
    "sg:address":"Calle de Pozo Dulce, 3",
    "sg:city":"Arahal",
    "sg:orig_category":"Cooperativas Agr\u00cdcolas",
    "sg:phone":"+34 954 84 07 20",
    "sg:postcode":"41600",
    "sg:province":"Sevilla",
    "wof:name":"Union De Agricultores Y Ganaderos De Sev",
    "wof:placetype":"venue"
},
  "geometry": {"coordinates":[-5.5445199013,37.2658996582],"type":"Point"}
}