{
  "type": "Feature",
  "properties": {
    "iso:country":"ES",
    "sg:address":"Calle de Colon De Larreategui, 38",
    "sg:city":"Bilbao",
    "sg:orig_category":"Fabricaci\u00d3n, Importaci\u00d3n, Venta De Material De Telefon\u00cda, Peritelefon\u00cda",
    "sg:phone":"+34 944 23 81 04",
    "sg:postcode":"48009",
    "sg:province":"Vizcaya",
    "wof:name":"Telefonica Data Espa\u00f1a S.a.",
    "wof:placetype":"venue"
},
  "geometry": {"coordinates":[-2.9347689152,43.2641830444],"type":"Point"}
}