{
  "type": "Feature",
  "properties": {
    "addr:full":"Calle de Mirador De La Sierra, 5 Madrid Madrid 28035",
    "addr:housenumber":"5",
    "addr:postcode":"28035",
    "addr:street":"Calle De Mirador De La Sierra",
    "iso:country":"ES",
    "sg:address":"Calle de Mirador De La Sierra, 5",
    "sg:city":"Madrid",
    "sg:orig_category":"Ingenier\u00cda, Centros De Estudios (diversos)",
    "sg:phone":"+34 913 86 59 67",
    "sg:postcode":"28035",
    "sg:province":"Madrid",
    "wof:name":"Anita Tecnica S.l.",
    "wof:placetype":"venue"
},
  "geometry": {"coordinates":[-3.7225990295,40.46352005],"type":"Point"}
}