{
  "type": "Feature",
  "properties": {
    "addr:full":"Paredilla, 5 Vecindario Las Palmas 35110",
    "addr:housenumber":"5",
    "addr:postcode":"35110",
    "addr:street":"Paredilla;Palmas",
    "iso:country":"ES",
    "sg:address":"Paredilla, 5",
    "sg:city":"Vecindario",
    "sg:orig_category":"Tapicer\u00cdas",
    "sg:phone":"+34 928 75 46 32",
    "sg:postcode":"35110",
    "sg:province":"Las Palmas",
    "wof:name":"Cazorla Armas Jose Valentin",
    "wof:placetype":"venue"
},
  "geometry": {"coordinates":[-15.4483470917,27.8407039642],"type":"Point"}
}