{
  "type": "Feature",
  "properties": {
    "addr:full":"Calle de Patricio Arabolaza, 4 Irun Guip\u00f9zcoa 20304",
    "addr:housenumber":"4",
    "addr:postcode":"20304",
    "addr:street":"Calle De Patricio Arabolaza;Guipu\u0300Zcoa",
    "iso:country":"ES",
    "sg:address":"Calle de Patricio Arabolaza, 4",
    "sg:city":"Irun",
    "sg:orig_category":"Asociaciones Y Clubs Deportivos",
    "sg:phone":"+34 943 63 20 56",
    "sg:postcode":"20304",
    "sg:province":"Guip\u00f9zcoa",
    "wof:name":"Sociedad Deportiva Santiagotarrak",
    "wof:placetype":"venue"
},
  "geometry": {"coordinates":[-1.7863260508,43.3458557129],"type":"Point"}
}