{
  "type": "Feature",
  "properties": {
    "iso:country":"ES",
    "sg:address":"Av Antilla, S/n",
    "sg:city":"La Antilla",
    "sg:orig_category":"Transporte En General",
    "sg:phone":"+34 959 48 10 02",
    "sg:postcode":"21449",
    "sg:province":"Huelva",
    "wof:name":"Bermejo Mora Antonio",
    "wof:placetype":"venue"
},
  "geometry": {"coordinates":[-7.2179589272,37.2067184448],"type":"Point"}
}