{
  "type": "Feature",
  "properties": {
    "addr:full":"Pintor Ribera, 3 Almu\u00f1ecar Granada 18690",
    "addr:housenumber":"3",
    "addr:postcode":"18690",
    "addr:street":"Pintor Ribera",
    "iso:country":"ES",
    "sg:address":"Pintor Ribera, 3",
    "sg:city":"Almu\u00f1ecar",
    "sg:orig_category":"Institutos De Belleza",
    "sg:phone":"+34 958 88 08 92",
    "sg:postcode":"18690",
    "sg:province":"Granada",
    "wof:name":"Carrascosa Garcia Yolanda",
    "wof:placetype":"venue"
},
  "geometry": {"coordinates":[-3.6635279655,36.7483711243],"type":"Point"}
}