{
  "type": "Feature",
  "properties": {
    "iso:country":"ES",
    "sg:address":"Av Madrid, 8",
    "sg:city":"Barcelona",
    "sg:orig_category":"Farmacias",
    "sg:phone":"+34 934 40 51 52",
    "sg:postcode":"08028",
    "sg:province":"Barcelona",
    "wof:name":"Miquel Carbo Francisco Javier",
    "wof:placetype":"venue"
},
  "geometry": {"coordinates":[2.1236550808,41.3760528564],"type":"Point"}
}