{
  "type": "Feature",
  "properties": {
    "addr:full":"Avda Mari\u00d1a (da), 8 Vilagarcia Pontevedra 36600",
    "addr:postcode":"36600",
    "addr:street":"Avda Marin\u0303A Da 8",
    "iso:country":"ES",
    "sg:address":"Avda Mari\u00d1a (da), 8",
    "sg:city":"Vilagarcia",
    "sg:orig_category":"Barcos",
    "sg:phone":"+34 986 50 13 74",
    "sg:postcode":"36600",
    "sg:province":"Pontevedra",
    "wof:name":"Perez Alvarez Jose",
    "wof:placetype":"venue"
},
  "geometry": {"coordinates":[-8.7668628693,42.5963172913],"type":"Point"}
}