{
  "type": "Feature",
  "properties": {
    "addr:full":"Carrer de Torrent Santa Anna, 33 Premia Mar Barcelona 08330",
    "addr:housenumber":"33",
    "addr:postcode":"08330",
    "addr:street":"Carrer De Torrent Santa Anna",
    "iso:country":"ES",
    "sg:address":"Carrer de Torrent Santa Anna, 33",
    "sg:city":"Premia Mar",
    "sg:orig_category":"Alquiler De V\u00cddeo",
    "sg:phone":"+34 937 52 26 62",
    "sg:postcode":"08330",
    "sg:province":"Barcelona",
    "wof:name":"Gomez Alvarez Francisco",
    "wof:placetype":"venue"
},
  "geometry": {"coordinates":[2.353110075,41.4906196594],"type":"Point"}
}