{
  "type": "Feature",
  "properties": {
    "iso:country":"ES",
    "sg:address":"Carrer de Pescadors, 11",
    "sg:city":"Roses",
    "sg:orig_category":"Tapicer\u00cdas",
    "sg:phone":"+34 972 25 54 03",
    "sg:postcode":"17480",
    "sg:province":"Girona",
    "wof:name":"Montoro Rodriguez Francisco",
    "wof:placetype":"venue"
},
  "geometry": {"coordinates":[3.1800999641,42.2600402832],"type":"Point"}
}