{
  "type": "Feature",
  "properties": {
    "iso:country":"ES",
    "sg:address":"Avda Consejero Montaner, 9",
    "sg:city":"Bonares",
    "sg:orig_category":"Comercio, Reparaci\u00d3n De Motocicletas, Bicicletas Y Piezas Sueltas",
    "sg:phone":"+34 959 36 64 16",
    "sg:postcode":"21830",
    "sg:province":"Huelva",
    "wof:name":"Molin Riquel Juan Jose",
    "wof:placetype":"venue"
},
  "geometry": {"coordinates":[-6.6843018532,37.3246040344],"type":"Point"}
}