{
  "type": "Feature",
  "properties": {
    "iso:country":"ES",
    "sg:address":"Calle de Virgen De La Paz, 14",
    "sg:city":"Manzanares",
    "sg:orig_category":"Abogados",
    "sg:phone":"+34 926 61 17 95",
    "sg:postcode":"13200",
    "sg:province":"Ciudad Real",
    "wof:name":"Garcia De Dionisio Montemayor Jose",
    "wof:placetype":"venue"
},
  "geometry": {"coordinates":[-3.3721790314,39.0001411438],"type":"Point"}
}