{
  "type": "Feature",
  "properties": {
    "addr:full":"C/ Mare De Deu, 16 Cerdanyola Valles Barcelona 08290",
    "addr:housenumber":"16",
    "addr:postcode":"08290",
    "addr:street":"C / Mare De Deu;Valles Barcelona",
    "iso:country":"ES",
    "sg:address":"C/ Mare De Deu, 16",
    "sg:city":"Cerdanyola Valles",
    "sg:orig_category":"Guarder\u00cdas",
    "sg:phone":"+34 936 92 01 04",
    "sg:postcode":"08290",
    "sg:province":"Barcelona",
    "wof:name":"Escola Bressol Bambi Sccl",
    "wof:placetype":"venue"
},
  "geometry": {"coordinates":[2.1323618889,41.4923362732],"type":"Point"}
}