{
  "type": "Feature",
  "properties": {
    "addr:full":"Pl Sol, 11 Barcelona Barcelona 08012",
    "addr:housenumber":"11",
    "addr:postcode":"08012",
    "addr:street":"Pl Sol",
    "iso:country":"ES",
    "sg:address":"Pl Sol, 11",
    "sg:city":"Barcelona",
    "sg:orig_category":"Tintorer\u00cdas, Limpieza En Seco",
    "sg:phone":"+34 934 15 03 61",
    "sg:postcode":"08012",
    "sg:province":"Barcelona",
    "sg:website":"www.oranmgevending.com",
    "wof:name":"Orange Wash & Vending S.l.",
    "wof:placetype":"venue"
},
  "geometry": {"coordinates":[2.1560618877,41.402053833],"type":"Point"}
}