{
  "type": "Feature",
  "properties": {
    "addr:full":"Calle de Iglesia, 52 Villanueva Tapia M\u00e1laga 29315",
    "addr:housenumber":"52",
    "addr:postcode":"29315",
    "addr:street":"Calle De Iglesia",
    "iso:country":"ES",
    "sg:address":"Calle de Iglesia, 52",
    "sg:city":"Villanueva Tapia",
    "sg:orig_category":"Aceites Y Grasas Alimentarias (fabricaci\u00d3n, Al Por Mayor)",
    "sg:phone":"+34 952 75 00 08",
    "sg:postcode":"29315",
    "sg:province":"M\u00e1laga",
    "wof:name":"Sociedad Cooperativa Olivarera Del Campo De Santa Rita",
    "wof:placetype":"venue"
},
  "geometry": {"coordinates":[-4.3344841003,37.1855392456],"type":"Point"}
}