{
  "type": "Feature",
  "properties": {
    "iso:country":"ES",
    "sg:address":"Carr Bas, 6",
    "sg:city":"Juneda",
    "sg:orig_category":"Peluqueros: De Se\u00d1oras",
    "sg:phone":"+34 973 15 00 78",
    "sg:postcode":"25430",
    "sg:province":"Lleida",
    "wof:name":"Olivart Melis Maria Pilar",
    "wof:placetype":"venue"
},
  "geometry": {"coordinates":[0.8210999966,41.5490760803],"type":"Point"}
}