{
  "type": "Feature",
  "properties": {
    "addr:full":"Concejo De Sagaseta, 17 Iru\u00f1a Navarra 31016",
    "addr:housenumber":"17",
    "addr:postcode":"31016",
    "addr:street":"Irun\u0303A Navarra",
    "iso:country":"ES",
    "sg:address":"Concejo De Sagaseta, 17",
    "sg:city":"Iru\u00f1a",
    "sg:orig_category":"Centros De Adelgazamiento Y De Est\u00c9tica",
    "sg:phone":"+34 948 16 30 99",
    "sg:postcode":"31016",
    "sg:province":"Navarra",
    "wof:name":"Vitorica Leoz Maria Natividad",
    "wof:placetype":"venue"
},
  "geometry": {"coordinates":[-1.6142754555,42.8079528809],"type":"Point"}
}