{
  "type": "Feature",
  "properties": {
    "iso:country":"ES",
    "sg:address":"Calle de Ponzano, 37",
    "sg:city":"Madrid",
    "sg:orig_category":"M\u00c9dicos: Pediatr\u00cda. Enfermedades De Los Ni\u00d1os",
    "sg:phone":"+34 914 41 47 75",
    "sg:postcode":"28003",
    "sg:province":"Madrid",
    "wof:name":"Mora Duran Jose Luis",
    "wof:placetype":"venue"
},
  "geometry": {"coordinates":[-3.6994099617,40.4398956299],"type":"Point"}
}