{
  "type": "Feature",
  "properties": {
    "iso:country":"ES",
    "sg:address":"Carr Lluis Companys, 18",
    "sg:city":"Blanes",
    "sg:orig_category":"Panader\u00cdas, Panader\u00cdas",
    "sg:phone":"+34 972 35 22 80",
    "sg:postcode":"17300",
    "sg:province":"Girona",
    "wof:name":"Crospasa S.l.",
    "wof:placetype":"venue"
},
  "geometry": {"coordinates":[2.7829949856,41.6669197083],"type":"Point"}
}