{
  "type": "Feature",
  "properties": {
    "iso:country":"ES",
    "sg:address":"Calle de Doctor Romagosa, 3",
    "sg:city":"Valencia",
    "sg:orig_category":"Asesor\u00cda Fiscal Y Jur\u00cddica",
    "sg:phone":"+34 963 51 65 95",
    "sg:postcode":"46002",
    "sg:province":"Valencia",
    "sg:website":"www.leopoldopons.com",
    "wof:name":"Leopoldo Pons S.l.",
    "wof:placetype":"venue"
},
  "geometry": {"coordinates":[-0.3725090921,39.4710273743],"type":"Point"}
}