{
  "type": "Feature",
  "properties": {
    "addr:full":"Calle de Real Vieja, 22 Alcobendas Madrid 28100",
    "addr:housenumber":"22",
    "addr:postcode":"28100",
    "addr:street":"Calle De Real Vieja",
    "iso:country":"ES",
    "sg:address":"Calle de Real Vieja, 22",
    "sg:city":"Alcobendas",
    "sg:orig_category":"Arreglo, Reparaci\u00d3n, Piezas Sueltas De Televisi\u00d3n, V\u00cddeo, Hi",
    "sg:phone":"+34 916 51 67 75",
    "sg:postcode":"28100",
    "sg:province":"Madrid",
    "wof:name":"Grunsat S.l.",
    "wof:placetype":"venue"
},
  "geometry": {"coordinates":[-3.6346158981,40.5390930176],"type":"Point"}
}