{
  "type": "Feature",
  "properties": {
    "iso:country":"ES",
    "sg:address":"Barr Aita Mari Auzategia, 44",
    "sg:city":"Zumaia",
    "sg:orig_category":"Centros De Educaci\u00d3n Especial",
    "sg:phone":"+34 943 86 10 37",
    "sg:postcode":"20750",
    "sg:province":"Guip\u00f9zcoa",
    "wof:name":"Ayuntamiento De Zumaya",
    "wof:placetype":"venue"
},
  "geometry": {"coordinates":[-2.2583589554,43.2942314148],"type":"Point"}
}