{
  "type": "Feature",
  "properties": {
    "iso:country":"ES",
    "sg:address":"Carrer de Josep Sabater I Sust, 52",
    "sg:city":"Mataro",
    "sg:orig_category":"Vallados Y Barreras",
    "sg:phone":"+34 937 55 60 40",
    "sg:postcode":"08301",
    "sg:province":"Barcelona",
    "wof:name":"Secom Cercados Y Automatismos",
    "wof:placetype":"venue"
},
  "geometry": {"coordinates":[2.4492070675,41.5452613831],"type":"Point"}
}