{
  "type": "Feature",
  "properties": {
    "iso:country":"ES",
    "sg:address":"Calle de Cardenal Monescillo, 9",
    "sg:city":"Campo Criptana",
    "sg:orig_category":"Sociedades, Compa\u00d1\u00cdas Aseguradoras",
    "sg:phone":"+34 926 56 03 74",
    "sg:postcode":"13610",
    "sg:province":"Ciudad Real",
    "wof:name":"Sanchez-manjavacas Panadero Maria Angeles",
    "wof:placetype":"venue"
},
  "geometry": {"coordinates":[-3.1270914078,39.4050827026],"type":"Point"}
}