{
  "type": "Feature",
  "properties": {
    "iso:country":"ES",
    "sg:address":"Calle de Antonio Cabezon, S/n",
    "sg:city":"Alcala Henares",
    "sg:orig_category":"Ense\u00d1anza: Comercio, Gesti\u00d3n, Inform\u00c1tica",
    "sg:phone":"+34 918 82 46 32",
    "sg:postcode":"28806",
    "sg:province":"Madrid",
    "wof:name":"Perales Figueroa Marcos",
    "wof:placetype":"venue"
},
  "geometry": {"coordinates":[-3.3766562939,40.4901504517],"type":"Point"}
}