{
  "type": "Feature",
  "properties": {
    "iso:country":"ES",
    "sg:address":"Carrer de Sant Antoni, 36",
    "sg:city":"Busot",
    "sg:orig_category":"Animales (al Por Menor)",
    "sg:phone":"+34 965 69 81 88",
    "sg:postcode":"03111",
    "sg:province":"Alicante",
    "wof:name":"Varon Naharro C.b.",
    "wof:placetype":"venue"
},
  "geometry": {"coordinates":[-0.4195089936,38.4827041626],"type":"Point"}
}