{
  "type": "Feature",
  "properties": {
    "addr:full":"Calle de Juan Capo, 27 Vall D'uixo Castell\u00f3n 12600",
    "addr:housenumber":"27",
    "addr:postcode":"12600",
    "addr:street":"Calle De Juan Capo",
    "iso:country":"ES",
    "sg:address":"Calle de Juan Capo, 27",
    "sg:city":"Vall D'uixo",
    "sg:orig_category":"Ense\u00d1anza Variada",
    "sg:phone":"+34 964 69 00 49",
    "sg:postcode":"12600",
    "sg:province":"Castell\u00f3n",
    "wof:name":"Centro De Estudios Informaster S.l.",
    "wof:placetype":"venue"
},
  "geometry": {"coordinates":[-0.0482099988,39.992477417],"type":"Point"}
}