{
  "type": "Feature",
  "properties": {
    "addr:full":"Calle de Guillem De Anglesola, 5 Valencia Valencia 46022",
    "addr:housenumber":"5",
    "addr:postcode":"46022",
    "addr:street":"Calle De Guillem De Anglesola",
    "iso:country":"ES",
    "sg:address":"Calle de Guillem De Anglesola, 5",
    "sg:city":"Valencia",
    "sg:orig_category":"Ingeniero",
    "sg:phone":"+34 963 30 27 66",
    "sg:postcode":"46022",
    "sg:province":"Valencia",
    "sg:website":"www.scatter-radio.com",
    "wof:name":"Scatter Radio S.l.",
    "wof:placetype":"venue"
},
  "geometry": {"coordinates":[-0.3463369906,39.4644584656],"type":"Point"}
}