{
  "type": "Feature",
  "properties": {
    "iso:country":"ES",
    "sg:address":"Carrer de S Joan De La Creu, 65",
    "sg:city":"Son Ferriol",
    "sg:orig_category":"Mec\u00c1nico Del Autom\u00d3vil",
    "sg:phone":"+34 971 42 75 86",
    "sg:postcode":"07198",
    "sg:province":"Islas Baleares",
    "wof:name":"Jose Vallespir Gost S.l.",
    "wof:placetype":"venue"
},
  "geometry": {"coordinates":[2.7178099155,39.5789794922],"type":"Point"}
}