{
  "type": "Feature",
  "properties": {
    "iso:country":"ES",
    "sg:address":"Carrer de Muntaner, 95",
    "sg:city":"Barcelona",
    "sg:orig_category":"Motocicletas (agentes, Concesionarios)",
    "sg:phone":"+34 933 62 08 80",
    "sg:postcode":"08036",
    "sg:province":"Barcelona",
    "sg:website":"www.nivelmoto.com",
    "wof:name":"C.s.nivel Moto S.l.",
    "wof:placetype":"venue"
},
  "geometry": {"coordinates":[2.1565880775,41.3885650635],"type":"Point"}
}