{
  "type": "Feature",
  "properties": {
    "addr:full":"Calle de Teniente Coronel Valenzuela, 2 Zaragoza Zaragoza 50004",
    "addr:housenumber":"2",
    "addr:postcode":"50004",
    "addr:street":"Calle De Teniente Coronel Valenzuela",
    "iso:country":"ES",
    "sg:address":"Calle de Teniente Coronel Valenzuela, 2",
    "sg:city":"Zaragoza",
    "sg:orig_category":"Farmacias",
    "sg:phone":"+34 976 23 60 20",
    "sg:postcode":"50004",
    "sg:province":"Zaragoza",
    "wof:name":"Faci Lerida Margarita",
    "wof:placetype":"venue"
},
  "geometry": {"coordinates":[-0.8937289715,41.6567459106],"type":"Point"}
}