{
  "type": "Feature",
  "properties": {
    "iso:country":"ES",
    "sg:address":"Calle de Susana Benitez, 14",
    "sg:city":"Puente-genil",
    "sg:orig_category":"Alimentaci\u00d3n General (al Por Menor)",
    "sg:phone":"+34 957 60 71 87",
    "sg:postcode":"14500",
    "sg:province":"C\u00f3rdoba",
    "wof:name":"Gonzalez Bernal Jose",
    "wof:placetype":"venue"
},
  "geometry": {"coordinates":[-4.7695231438,37.390537262],"type":"Point"}
}