{
  "type": "Feature",
  "properties": {
    "iso:country":"ES",
    "sg:address":"Calle de Mayor, 16",
    "sg:city":"Fuentes Ebro",
    "sg:orig_category":"Juegos Y Juguetes (al Por Menor)",
    "sg:phone":"+34 976 16 06 48",
    "sg:postcode":"50740",
    "sg:province":"Zaragoza",
    "wof:name":"Bowling Center Fuentes S.c.",
    "wof:placetype":"venue"
},
  "geometry": {"coordinates":[-0.6294289827,41.5119094849],"type":"Point"}
}