{
  "type": "Feature",
  "properties": {
    "addr:full":"Avda Lepanto, 11 Aduanas Alicante 03730",
    "addr:housenumber":"11",
    "addr:postcode":"03730",
    "addr:street":"Avda Lepanto",
    "iso:country":"ES",
    "sg:address":"Avda Lepanto, 11",
    "sg:city":"Aduanas",
    "sg:orig_category":"Asociaciones Y Clubs Deportivos",
    "sg:phone":"+34 966 46 26 70",
    "sg:postcode":"03730",
    "sg:province":"Alicante",
    "wof:name":"No Limit S.c.",
    "wof:placetype":"venue"
},
  "geometry": {"coordinates":[0.1787530035,38.7944259644],"type":"Point"}
}