{
  "type": "Feature",
  "properties": {
    "iso:country":"ES",
    "sg:address":"Carrer de Rocafort, 252",
    "sg:city":"Barcelona",
    "sg:orig_category":"Renovaci\u00d3n Inmobiliaria",
    "sg:phone":"+34 934 10 98 89",
    "sg:postcode":"08029",
    "sg:province":"Barcelona",
    "wof:name":"Luis Montero S.l.",
    "wof:placetype":"venue"
},
  "geometry": {"coordinates":[2.1436738968,41.386756897],"type":"Point"}
}