{
  "type": "Feature",
  "properties": {
    "iso:country":"ES",
    "sg:address":"Calle de Yesera, 2",
    "sg:city":"Lerin",
    "sg:orig_category":"Maquinaria Para Industrias Diversas",
    "sg:phone":"+34 948 53 00 59",
    "sg:postcode":"31260",
    "sg:province":"Navarra",
    "wof:name":"Aramandia Villanueva Pilar",
    "wof:placetype":"venue"
},
  "geometry": {"coordinates":[-1.9671545029,42.4837913513],"type":"Point"}
}