{
  "type": "Feature",
  "properties": {
    "addr:full":"Avda Andalucia (de), 26 Estacion M\u00e1laga 29580",
    "addr:housenumber":"26 estacion",
    "addr:postcode":"29580",
    "addr:street":"Avda Andalucia De;Ma\u0301Laga",
    "iso:country":"ES",
    "sg:address":"Avda Andalucia (de), 26",
    "sg:city":"Estacion",
    "sg:orig_category":"Cajas Para Embalar",
    "sg:phone":"+34 952 42 01 00",
    "sg:postcode":"29580",
    "sg:province":"M\u00e1laga",
    "wof:name":"Cajamar",
    "wof:placetype":"venue"
},
  "geometry": {"coordinates":[-4.6095371246,36.7366523743],"type":"Point"}
}