{
  "type": "Feature",
  "properties": {
    "addr:full":"Ctra. Monovar, Km. 0013,0 Elda Alicante 03600",
    "addr:postcode":"03600",
    "addr:street":"Ctra. Monovar Km. 0013,0",
    "iso:country":"ES",
    "sg:address":"Ctra. Monovar, Km. 0013,0",
    "sg:city":"Elda",
    "sg:orig_category":"Distribuci\u00d3n De Petr\u00d3leo Y Derivados",
    "sg:phone":"+34 965 39 73 08",
    "sg:postcode":"03600",
    "sg:province":"Alicante",
    "wof:name":"Galpgest Petrogal Estaciones De Servicio S.l.u.",
    "wof:placetype":"venue"
},
  "geometry": {"coordinates":[-0.7961040139,38.475315094],"type":"Point"}
}