{
  "type": "Feature",
  "properties": {
    "addr:full":"Barr Solrivero, 5 Colunga Asturias 33320",
    "addr:housenumber":"5",
    "addr:postcode":"33320",
    "addr:street":"Solrivero",
    "iso:country":"ES",
    "sg:address":"Barr Solrivero, 5",
    "sg:city":"Colunga",
    "sg:orig_category":"Molduras, Junquillos, Listones Y Molduras Perforadas",
    "sg:phone":"+34 985 85 61 86",
    "sg:postcode":"33320",
    "sg:province":"Asturias",
    "wof:name":"Vega Marina Maria Luisa Evangelina",
    "wof:placetype":"venue"
},
  "geometry": {"coordinates":[-5.2751731873,43.485458374],"type":"Point"}
}