{
  "type": "Feature",
  "properties": {
    "iso:country":"ES",
    "sg:address":"Carrer de Sant Jaume, 34",
    "sg:city":"Calaf",
    "sg:orig_category":"Mataderos De Poller\u00cda",
    "sg:phone":"+34 938 69 85 32",
    "sg:postcode":"08280",
    "sg:province":"Barcelona",
    "wof:name":"Escorxador Industrial De Conills J.grau S.l.",
    "wof:placetype":"venue"
},
  "geometry": {"coordinates":[1.5121699572,41.7332496643],"type":"Point"}
}