{
  "type": "Feature",
  "properties": {
    "addr:full":"Calle de Anastasio Oliva, 1 Puebla Montalban Toledo 45516",
    "addr:housenumber":"1",
    "addr:postcode":"45516",
    "addr:street":"Calle De Anastasio Oliva",
    "iso:country":"ES",
    "sg:address":"Calle de Anastasio Oliva, 1",
    "sg:city":"Puebla Montalban",
    "sg:orig_category":"Carnicer\u00cdas, Carnicer\u00cdas",
    "sg:phone":"+34 925 75 00 15",
    "sg:postcode":"45516",
    "sg:province":"Toledo",
    "wof:name":"De La Fuente Garcia Marin",
    "wof:placetype":"venue"
},
  "geometry": {"coordinates":[-4.3618388176,39.8662376404],"type":"Point"}
}