{
  "type": "Feature",
  "properties": {
    "iso:country":"ES",
    "sg:address":"Calle de Cordovilla, S/n",
    "sg:city":"Pedraza",
    "sg:orig_category":"Iglesia Cat\u00d3lica",
    "sg:phone":"+34 921 50 98 28",
    "sg:postcode":"40172",
    "sg:province":"Segovia",
    "wof:name":"Obispado Segovia",
    "wof:placetype":"venue"
},
  "geometry": {"coordinates":[-3.8107306957,41.1306877136],"type":"Point"}
}