{
  "type": "Feature",
  "properties": {
    "iso:country":"ES",
    "sg:address":"Calle de Breton Los Herreros, 10",
    "sg:city":"Puertollano",
    "sg:orig_category":"Comercio De Piezas De Recambio Y De Accesorios De Veh\u00cdculos, Veh\u00cdculos Industriales",
    "sg:phone":"+34 926 44 19 04",
    "sg:postcode":"13500",
    "sg:province":"Ciudad Real",
    "wof:name":"Repuestos Y Talleres Electricos Sanikar S.l.",
    "wof:placetype":"venue"
},
  "geometry": {"coordinates":[-4.1094193459,38.6958503723],"type":"Point"}
}