{
  "type": "Feature",
  "properties": {
    "iso:country":"ES",
    "sg:address":"Carr Domenec Cardenal, 59",
    "sg:city":"Bellvis",
    "sg:orig_category":"Ingenier\u00cda, Centros De Estudios (diversos)",
    "sg:phone":"+34 973 71 60 65",
    "sg:postcode":"25142",
    "sg:province":"Lleida",
    "wof:name":"Copra 2005 S.l.",
    "wof:placetype":"venue"
},
  "geometry": {"coordinates":[0.8176680207,41.6722335815],"type":"Point"}
}