{
  "type": "Feature",
  "properties": {
    "iso:country":"ES",
    "sg:address":"Avda Alcalde Jose Fernandin, 22",
    "sg:city":"Piedras Blancas",
    "sg:orig_category":"Mercer\u00cda, Lencer\u00cda (al Por Menor)",
    "sg:phone":"+34 985 50 74 54",
    "sg:postcode":"33450",
    "sg:province":"Asturias",
    "wof:name":"Alba Fernandez Josefina",
    "wof:placetype":"venue"
},
  "geometry": {"coordinates":[-5.9747633934,43.5619888306],"type":"Point"}
}