{
  "type": "Feature",
  "properties": {
    "iso:country":"ES",
    "sg:address":"Calle de Jose Lopez Rodriguez, 11",
    "sg:city":"S. Fernando",
    "sg:orig_category":"Arquitectos",
    "sg:phone":"+34 956 88 36 70",
    "sg:postcode":"11100",
    "sg:province":"C\u00e1diz",
    "wof:name":"Sura\u00f1a Fernandez Isabel",
    "wof:placetype":"venue"
},
  "geometry": {"coordinates":[-6.1991147995,36.4651145935],"type":"Point"}
}