{
  "type": "Feature",
  "properties": {
    "addr:full":"Calle de Pez Espada, 14 Sevilla Sevilla 41015",
    "addr:housenumber":"14",
    "addr:postcode":"41015",
    "addr:street":"Calle De Pez Espada",
    "iso:country":"ES",
    "sg:address":"Calle de Pez Espada, 14",
    "sg:city":"Sevilla",
    "sg:orig_category":"Agencias Y Agentes Comerciales, Representantes",
    "sg:phone":"+34 954 90 24 62",
    "sg:postcode":"41015",
    "sg:province":"Sevilla",
    "wof:name":"Fernandez Gonzalez Jacinto",
    "wof:placetype":"venue"
},
  "geometry": {"coordinates":[-5.9825630188,37.4319877625],"type":"Point"}
}