{
  "type": "Feature",
  "properties": {
    "iso:country":"ES",
    "sg:address":"Avda Generalisimo, 86",
    "sg:city":"Mi\u00f1o",
    "sg:orig_category":"Bisuter\u00cda, Joyer\u00cda, Relojer\u00cda (al Por Menor)",
    "sg:phone":"+34 981 78 26 60",
    "sg:postcode":"15630",
    "sg:province":"La Coru\u00f1a",
    "wof:name":"Pousada Cubeiro Jose",
    "wof:placetype":"venue"
},
  "geometry": {"coordinates":[-8.2014837265,43.3393096924],"type":"Point"}
}