{
  "type": "Feature",
  "properties": {
    "iso:country":"ES",
    "sg:address":"Carrer de Severo Ochoa, 4",
    "sg:city":"Crevillent",
    "sg:orig_category":"Sociedades, Compa\u00d1\u00cdas Aseguradoras",
    "sg:phone":"+34 966 68 10 95",
    "sg:postcode":"03330",
    "sg:province":"Alicante",
    "wof:name":"Correduria De Seguros Lloret D'mas S.l.",
    "wof:placetype":"venue"
},
  "geometry": {"coordinates":[-0.8128020167,38.2426490784],"type":"Point"}
}