{
  "type": "Feature",
  "properties": {
    "iso:country":"ES",
    "sg:address":"Carrer de Jacint Verdaguer, 10",
    "sg:city":"Olost",
    "sg:orig_category":"Puertas Y Portales",
    "sg:phone":"+34 938 88 02 27",
    "sg:postcode":"08516",
    "sg:province":"Barcelona",
    "wof:name":"Casellas Pons Albert",
    "wof:placetype":"venue"
},
  "geometry": {"coordinates":[-97.78224945069999,45.7040786743],"type":"Point"}
}