{
  "type": "Feature",
  "properties": {
    "addr:full":"Av Granvia, 23 Hospitalet Llobregat Barcelona 08908",
    "addr:housenumber":"23",
    "addr:postcode":"08908",
    "addr:street":"Av Granvia",
    "iso:country":"ES",
    "sg:address":"Av Granvia, 23",
    "sg:city":"Hospitalet Llobregat",
    "sg:orig_category":"Controles De Edificaci\u00d3n (construcci\u00d3n, Seguridad)",
    "sg:phone":"+34 932 98 86 40",
    "sg:postcode":"08908",
    "sg:province":"Barcelona",
    "wof:name":"Antares Catalunya S. A.",
    "wof:placetype":"venue"
},
  "geometry": {"coordinates":[2.1155488491,41.3495864868],"type":"Point"}
}