{
  "type": "Feature",
  "properties": {
    "addr:full":"Plaz Mayor, 4 Puebla Montalban Toledo 45516",
    "addr:housenumber":"4",
    "addr:postcode":"45516",
    "addr:street":"Plaz Mayor",
    "iso:country":"ES",
    "sg:address":"Plaz Mayor, 4",
    "sg:city":"Puebla Montalban",
    "sg:orig_category":"Molduras, Junquillos, Listones Y Molduras Perforadas",
    "sg:phone":"+34 925 75 04 39",
    "sg:postcode":"45516",
    "sg:province":"Toledo",
    "wof:name":"Lopez Sanchez De Pedro Jose-antonio",
    "wof:placetype":"venue"
},
  "geometry": {"coordinates":[-4.3588690758,39.8725013733],"type":"Point"}
}