{
  "type": "Feature",
  "properties": {
    "iso:country":"ES",
    "sg:address":"Calle de Andalucia, 21",
    "sg:city":"Vitoria-gasteiz",
    "sg:orig_category":"Peluqueros: De Se\u00d1oras",
    "sg:phone":"+34 945 25 07 47",
    "sg:postcode":"01003",
    "sg:province":"\u00c1lava",
    "wof:name":"Stylos, S.c.",
    "wof:placetype":"venue"
},
  "geometry": {"coordinates":[-2.6586389542,42.8502311707],"type":"Point"}
}