{
  "type": "Feature",
  "properties": {
    "iso:country":"ES",
    "sg:address":"Ctra Aldaia-xirivella, 38",
    "sg:city":"Aldaia",
    "sg:orig_category":"Trabajos De Soldaduras",
    "sg:phone":"+34 961 51 33 82",
    "sg:postcode":"46960",
    "sg:province":"Valencia",
    "wof:name":"Automecanica Hermanos Pellicer Belenguer S.l.",
    "wof:placetype":"venue"
},
  "geometry": {"coordinates":[-0.4502579868,39.4636154175],"type":"Point"}
}