{
  "type": "Feature",
  "properties": {
    "addr:full":"Calle de Pintora (la), 1 Toscal Santa Cruz De Tenerife 38418",
    "addr:housenumber":"1",
    "addr:postcode":"38418",
    "addr:street":"Calle De Pintora La",
    "iso:country":"ES",
    "sg:address":"Calle de Pintora (la), 1",
    "sg:city":"Toscal",
    "sg:orig_category":"Asesor\u00cda Sobre Comunicaci\u00d3n De Empresas",
    "sg:phone":"+34 922 36 30 40",
    "sg:postcode":"38418",
    "sg:province":"Santa Cruz De Tenerife",
    "wof:name":"Asesores Gonzamen 2004 S.l.u",
    "wof:placetype":"venue"
},
  "geometry": {"coordinates":[-16.5755519867,28.399061203],"type":"Point"}
}