{
  "type": "Feature",
  "properties": {
    "addr:full":"El Pavo, S/n Colmenar M\u00e1laga 29170",
    "addr:postcode":"29170",
    "addr:street":"El Pavo S / N",
    "iso:country":"ES",
    "sg:address":"El Pavo, S/n",
    "sg:city":"Colmenar",
    "sg:orig_category":"Centros Empresariales",
    "sg:phone":"+34 952 73 00 88",
    "sg:postcode":"29170",
    "sg:province":"M\u00e1laga",
    "wof:name":"Asociacion De Empresarios Y Profesionales La Colmena",
    "wof:placetype":"venue"
},
  "geometry": {"coordinates":[-4.3362865448,36.9058418274],"type":"Point"}
}