{
  "type": "Feature",
  "properties": {
    "addr:full":"Calle de Libertad, 54 Pola De Laviana Asturias 33980",
    "addr:housenumber":"54",
    "addr:postcode":"33980",
    "addr:street":"Calle De Libertad",
    "iso:country":"ES",
    "sg:address":"Calle de Libertad, 54",
    "sg:city":"Pola De Laviana",
    "sg:orig_category":"Perfumer\u00cda, Art\u00cdculos De Ba\u00d1o (fabricaci\u00d3n, Al Por Mayor)",
    "sg:phone":"+34 985 61 12 84",
    "sg:postcode":"33980",
    "sg:province":"Asturias",
    "wof:name":"Perfumeria Estilo S.l.",
    "wof:placetype":"venue"
},
  "geometry": {"coordinates":[-5.560983181,43.2430381775],"type":"Point"}
}