{
  "type": "Feature",
  "properties": {
    "iso:country":"ES",
    "sg:address":"Calle de Cesar Arbasia, 7",
    "sg:city":"Malaga",
    "sg:orig_category":"Peluqueros: De Se\u00d1oras",
    "sg:phone":"+34 952 28 62 47",
    "sg:postcode":"29010",
    "sg:province":"M\u00e1laga",
    "wof:name":"Cabrera Fernandez Maximiliana",
    "wof:placetype":"venue"
},
  "geometry": {"coordinates":[-4.4419541359,36.7279663086],"type":"Point"}
}