{
  "type": "Feature",
  "properties": {
    "iso:country":"ES",
    "sg:address":"Carrer de Montflorit, 162",
    "sg:city":"Gava",
    "sg:orig_category":"Enfermeras: Consultas, Atenci\u00d3n A Domicilio",
    "sg:phone":"+34 936 62 15 89",
    "sg:postcode":"08850",
    "sg:province":"Barcelona",
    "wof:name":"Sero Bernat Teresa",
    "wof:placetype":"venue"
},
  "geometry": {"coordinates":[1.9982279539,41.3079414368],"type":"Point"}
}