{
  "type": "Feature",
  "properties": {
    "iso:country":"ES",
    "sg:address":"Calle de Yunque, 9",
    "sg:city":"San Vicente Del Raspeig-sant Vicent Del Raspeig",
    "sg:orig_category":"Guarda",
    "sg:phone":"+34 965 67 16 24",
    "sg:postcode":"03690",
    "sg:province":"Alicante",
    "wof:name":"Albarracin Segui Lidia",
    "wof:placetype":"venue"
},
  "geometry": {"coordinates":[-0.5362781286,38.4031143188],"type":"Point"}
}