{
  "type": "Feature",
  "properties": {
    "iso:country":"ES",
    "sg:address":"Carrer de Comer\u00c7, 31",
    "sg:city":"Barcelona",
    "sg:orig_category":"Agencias De Relaciones P\u00dablicas",
    "sg:phone":"+34 932 68 01 97",
    "sg:postcode":"08003",
    "sg:province":"Barcelona",
    "wof:name":"Color Naranja S.l.",
    "wof:placetype":"venue"
},
  "geometry": {"coordinates":[2.1846849918,41.3847694397],"type":"Point"}
}