{
  "type": "Feature",
  "properties": {
    "iso:country":"ES",
    "sg:address":"Carrer de Flor I Cel, 2",
    "sg:city":"Santa Coloma De Gramenet",
    "sg:orig_category":"Extinci\u00d3n De Incendios: Material Y Suministros (fabricaci\u00d3n, Al Por Mayor)",
    "sg:phone":"+34 933 92 57 10",
    "sg:postcode":"08923",
    "sg:province":"Barcelona",
    "wof:name":"Extintores G.m.c.s.l.",
    "wof:placetype":"venue"
},
  "geometry": {"coordinates":[2.2169120312,41.4464035034],"type":"Point"}
}