{
  "type": "Feature",
  "properties": {
    "addr:full":"Calle de Ruperto Chapi (de), 57 Alcobendas Madrid 28100",
    "addr:housenumber":"57",
    "addr:postcode":"28100",
    "addr:street":"Calle De Ruperto Chapi De",
    "iso:country":"ES",
    "sg:address":"Calle de Ruperto Chapi (de), 57",
    "sg:city":"Alcobendas",
    "sg:orig_category":"Laboratorios Farmac\u00c9uticos",
    "sg:phone":"+34 916 52 00 68",
    "sg:postcode":"28100",
    "sg:province":"Madrid",
    "wof:name":"Paramo Aguado Antonia",
    "wof:placetype":"venue"
},
  "geometry": {"coordinates":[-3.6404020786,40.548625946],"type":"Point"}
}