{
  "type": "Feature",
  "properties": {
    "iso:country":"ES",
    "sg:address":"Calle de Granada, 5",
    "sg:city":"Albacete",
    "sg:orig_category":"Reposter\u00cdas",
    "sg:phone":"+34 967 22 08 29",
    "sg:postcode":"02005",
    "sg:province":"Albacete",
    "wof:name":"V.palacios Pan Y Dulces Caseros S.l.",
    "wof:placetype":"venue"
},
  "geometry": {"coordinates":[-1.8670165539,38.9980125427],"type":"Point"}
}