{
  "type": "Feature",
  "properties": {
    "addr:full":"Av Corts Catalanes, 3 S. Adria Besos Barcelona 08930",
    "addr:housenumber":"3",
    "addr:postcode":"08930",
    "addr:street":"Av Corts Catalanes;Barcelona",
    "iso:country":"ES",
    "sg:address":"Av Corts Catalanes, 3",
    "sg:city":"S. Adria Besos",
    "sg:orig_category":"Molduras, Junquillos, Listones Y Molduras Perforadas",
    "sg:phone":"+34 934 62 00 24",
    "sg:postcode":"08930",
    "sg:province":"Barcelona",
    "wof:name":"Sanz Castro Francisco",
    "wof:placetype":"venue"
},
  "geometry": {"coordinates":[2.2116599083,41.4223899841],"type":"Point"}
}