{
  "type": "Feature",
  "properties": {
    "iso:country":"ES",
    "sg:address":"Calle de Acueducto, 26",
    "sg:city":"Fuente Del Rey",
    "sg:classifiers":[
        {
            "category":"Manufacturing",
            "subcategory":"Building Materials",
            "type":"Manufacturing & Wholesale Goods"
        }
    ],
    "sg:phone":"+34 954 93 02 59",
    "sg:postcode":"41700",
    "sg:province":"Sevilla",
    "sg:tags":[
        "cemento",
        "y",
        "de",
        "fabricaci\u00d3n",
        "cal"
    ],
    "wof:name":"Cementos Barrero S.a.",
    "wof:placetype":"venue"
},
  "geometry": {"coordinates":[-5.9924249649,37.2735176086],"type":"Point"}
}