{
  "type": "Feature",
  "properties": {
    "iso:country":"ES",
    "sg:address":"Los Toros, 6",
    "sg:city":"Duruelo Sierra",
    "sg:orig_category":"Quincaller\u00cda (al Por Menor)",
    "sg:phone":"+34 975 37 12 25",
    "sg:postcode":"42158",
    "sg:province":"Soria",
    "wof:name":"Garcia Martin Javier",
    "wof:placetype":"venue"
},
  "geometry": {"coordinates":[-2.9326441288,41.9536132812],"type":"Point"}
}