{
  "type": "Feature",
  "properties": {
    "iso:country":"ES",
    "sg:address":"Calle de Ba\u00d1ales, 7",
    "sg:city":"Coria Rio",
    "sg:orig_category":"Ense\u00d1ante, Direcci\u00d3n",
    "sg:phone":"+34 954 77 91 76",
    "sg:postcode":"41100",
    "sg:province":"Sevilla",
    "wof:name":"Sosa Mu\u00f1oz Carmen Maria",
    "wof:placetype":"venue"
},
  "geometry": {"coordinates":[-6.0552787781,37.2866783142],"type":"Point"}
}