{
  "type": "Feature",
  "properties": {
    "addr:full":"Avda Domingo Lopez Ortega, 2 Borox Toledo 45222",
    "addr:housenumber":"2",
    "addr:postcode":"45222",
    "addr:street":"Avda Domingo Lopez Ortega",
    "iso:country":"ES",
    "sg:address":"Avda Domingo Lopez Ortega, 2",
    "sg:city":"Borox",
    "sg:orig_category":"Centros De Educaci\u00d3n Especial",
    "sg:phone":"+34 925 52 80 27",
    "sg:postcode":"45222",
    "sg:province":"Toledo",
    "wof:name":"Colegio Nacional Mixto Nuestra Se\u00f1ora De La Salud",
    "wof:placetype":"venue"
},
  "geometry": {"coordinates":[-3.6806640625,40.0350456238],"type":"Point"}
}