{
  "type": "Feature",
  "properties": {
    "addr:full":"Carrer de Major, 40 Mora Nova Tarragona 43770",
    "addr:housenumber":"40",
    "addr:postcode":"43770",
    "addr:street":"Carrer De Major",
    "iso:country":"ES",
    "sg:address":"Carrer de Major, 40",
    "sg:city":"Mora Nova",
    "sg:orig_category":"Panader\u00cdas, Panader\u00cdas",
    "sg:phone":"+34 977 40 30 09",
    "sg:postcode":"43770",
    "sg:province":"Tarragona",
    "wof:name":"Faura Plane Pedro",
    "wof:placetype":"venue"
},
  "geometry": {"coordinates":[0.6500210166,41.0990715027],"type":"Point"}
}