{
  "type": "Feature",
  "properties": {
    "iso:country":"ES",
    "sg:address":"Avda Europa, 19",
    "sg:city":"Pozuelo De Alarcon",
    "sg:orig_category":"Venta, Alquiler De V\u00cddeo",
    "sg:phone":"+34 913 51 97 12",
    "sg:postcode":"28224",
    "sg:province":"Madrid",
    "sg:website":"www.thq.com",
    "wof:name":"Thq Interactive Entertainment S.l.",
    "wof:placetype":"venue"
},
  "geometry": {"coordinates":[-3.7874910831,40.4409637451],"type":"Point"}
}