{
  "type": "Feature",
  "properties": {
    "addr:full":"Pedra Queimada, S/n Malpica Berganti\u00f1os La Coru\u00f1a 15113",
    "addr:housenumber":"s",
    "addr:postcode":"15113",
    "addr:street":"Pedra Queimada;/ N;Corun\u0303A",
    "iso:country":"ES",
    "sg:address":"Pedra Queimada, S/n",
    "sg:city":"Malpica Berganti\u00f1os",
    "sg:orig_category":"Electricidad: Instalaciones Industriales",
    "sg:phone":"+34 902 15 22 04",
    "sg:postcode":"15113",
    "sg:province":"La Coru\u00f1a",
    "sg:website":"www.garaysa.com",
    "wof:name":"Garaysa Montajes Electricos S.l.",
    "wof:placetype":"venue"
},
  "geometry": {"coordinates":[-8.8147649765,43.3196563721],"type":"Point"}
}