{
  "type": "Feature",
  "properties": {
    "addr:full":"Carrer de Santa Isabel, 37 Pedreguer Alicante 03750",
    "addr:housenumber":"37",
    "addr:postcode":"03750",
    "addr:street":"Carrer De Santa Isabel",
    "iso:country":"ES",
    "sg:address":"Carrer de Santa Isabel, 37",
    "sg:city":"Pedreguer",
    "sg:orig_category":"Fabricaci\u00d3n De Sobres, Bolsas Y Fundas",
    "sg:phone":"+34 966 45 60 56",
    "sg:postcode":"03750",
    "sg:province":"Alicante",
    "wof:name":"Laipa Paper I Ploma Sl",
    "wof:placetype":"venue"
},
  "geometry": {"coordinates":[0.0373670012,38.7924346924],"type":"Point"}
}