{
  "type": "Feature",
  "properties": {
    "iso:country":"ES",
    "sg:address":"Plaz Santa Maria, 8",
    "sg:city":"Almansa",
    "sg:orig_category":"Caf\u00c9s, Bares, Cervecer\u00cdas",
    "sg:phone":"+34 967 31 31 14",
    "sg:postcode":"02640",
    "sg:province":"Albacete",
    "wof:name":"Chema Y Banovio S.l.",
    "wof:placetype":"venue"
},
  "geometry": {"coordinates":[-1.0936859846,38.8696937561],"type":"Point"}
}