{
  "type": "Feature",
  "properties": {
    "addr:full":"Calle de Madrid, S/n Luisiana Sevilla 41430",
    "addr:housenumber":"s / n",
    "addr:postcode":"41430",
    "addr:street":"Calle De Madrid",
    "iso:country":"ES",
    "sg:address":"Calle de Madrid, S/n",
    "sg:city":"Luisiana",
    "sg:orig_category":"Panader\u00cdas, Panader\u00cdas",
    "sg:phone":"+34 955 90 71 98",
    "sg:postcode":"41430",
    "sg:province":"Sevilla",
    "wof:name":"Picos La Luisiana Sll",
    "wof:placetype":"venue"
},
  "geometry": {"coordinates":[-5.2405891418,37.5285148621],"type":"Point"}
}