{
  "type": "Feature",
  "properties": {
    "iso:country":"ES",
    "sg:address":"Calle de Real, 17",
    "sg:city":"Horcajo Santiago",
    "sg:orig_category":"Asesor\u00cda Fiscal Y Jur\u00cddica",
    "sg:phone":"+34 969 12 70 14",
    "sg:postcode":"16410",
    "sg:province":"Cuenca",
    "wof:name":"Sicuendes S.l.",
    "wof:placetype":"venue"
},
  "geometry": {"coordinates":[-3.0003340244,39.8414802551],"type":"Point"}
}