{
  "type": "Feature",
  "properties": {
    "addr:full":"Carrer de Unio (de La), 17 Tarragona Tarragona 43001",
    "addr:housenumber":"17",
    "addr:postcode":"43001",
    "addr:street":"Carrer De Unio De La",
    "iso:country":"ES",
    "sg:address":"Carrer de Unio (de La), 17",
    "sg:city":"Tarragona",
    "sg:orig_category":"Fotocopias, Reprograf\u00cda",
    "sg:phone":"+34 977 23 26 28",
    "sg:postcode":"43001",
    "sg:province":"Tarragona",
    "wof:name":"Iglesias Espa\u00f1ol Jose",
    "wof:placetype":"venue"
},
  "geometry": {"coordinates":[1.2519379854,41.1149978638],"type":"Point"}
}