{
  "type": "Feature",
  "properties": {
    "addr:full":"Av Cornella, 128 Esplugues Llobregat Barcelona 08950",
    "addr:housenumber":"128",
    "addr:postcode":"08950",
    "addr:street":"Av Cornella",
    "iso:country":"ES",
    "sg:address":"Av Cornella, 128",
    "sg:city":"Esplugues Llobregat",
    "sg:orig_category":"Rectificaci\u00d3n, Mecanizado, Fresado",
    "sg:phone":"+34 933 71 67 96",
    "sg:postcode":"08950",
    "sg:province":"Barcelona",
    "wof:name":"Gonz\u00c1lez Col\u00d3n Oscar",
    "wof:placetype":"venue"
},
  "geometry": {"coordinates":[2.0810570717,41.3700408936],"type":"Point"}
}