{
  "type": "Feature",
  "properties": {
    "addr:full":"Calle de Roman Alonso, 19 Madrid Madrid 28039",
    "addr:housenumber":"19",
    "addr:postcode":"madrid;28039",
    "addr:street":"Calle De Roman Alonso",
    "iso:country":"ES",
    "sg:address":"Calle de Roman Alonso, 19",
    "sg:city":"Madrid",
    "sg:orig_category":"Asesor\u00cda Fiscal Y Jur\u00cddica",
    "sg:phone":"+34 914 50 00 25",
    "sg:postcode":"28039",
    "sg:province":"Madrid",
    "wof:name":"Royalpatents; S.l",
    "wof:placetype":"venue"
},
  "geometry": {"coordinates":[-3.7053470612,40.4594230652],"type":"Point"}
}