{
  "type": "Feature",
  "properties": {
    "addr:full":"Calle de Escultura (de La), 2 Loranca Madrid 28942",
    "addr:postcode":"28942",
    "addr:street":"Calle De Escultura De La 2 Loranca",
    "iso:country":"ES",
    "sg:address":"Calle de Escultura (de La), 2",
    "sg:city":"Loranca",
    "sg:orig_category":"Estancos",
    "sg:phone":"+34 916 89 22 68",
    "sg:postcode":"28942",
    "sg:province":"Madrid",
    "wof:name":"Sanchez Marquez Angel",
    "wof:placetype":"venue"
},
  "geometry": {"coordinates":[-3.8374240398,40.2973709106],"type":"Point"}
}