{
  "type": "Feature",
  "properties": {
    "addr:full":"Calle de Periodista Antonio Rodriguez Mesa, 5 Cordoba C\u00f3rdoba 14010",
    "addr:housenumber":"5",
    "addr:postcode":"14010",
    "addr:street":"Calle De Periodista Antonio Rodriguez Mesa;Co\u0301Rdoba",
    "iso:country":"ES",
    "sg:address":"Calle de Periodista Antonio Rodriguez Mesa, 5",
    "sg:city":"Cordoba",
    "sg:orig_category":"Agentes, Concesionarios Y Sucursales De Veh\u00cdculos",
    "sg:phone":"+34 957 75 06 78",
    "sg:postcode":"14010",
    "sg:province":"C\u00f3rdoba",
    "sg:website":"www.elmundodelauto.com",
    "wof:name":"Francisco Zamora Mu\u00f1oz S.l.",
    "wof:placetype":"venue"
},
  "geometry": {"coordinates":[-4.7644782066,37.8758392334],"type":"Point"}
}