{
  "type": "Feature",
  "properties": {
    "addr:full":"Avda Marineros (de Los), 3 Torrevieja Alicante 03180",
    "addr:postcode":"03180",
    "addr:street":"Avda Marineros De Los",
    "iso:country":"ES",
    "sg:address":"Avda Marineros (de Los), 3",
    "sg:city":"Torrevieja",
    "sg:orig_category":"Supermercados Y Hipermercados",
    "sg:phone":"+34 965 70 58 37",
    "sg:postcode":"03180",
    "sg:province":"Alicante",
    "wof:name":"Union Bops S.a.",
    "wof:placetype":"venue"
},
  "geometry": {"coordinates":[-0.6536790133,38.0173606873],"type":"Point"}
}