{
  "type": "Feature",
  "properties": {
    "addr:full":"Pol Ind Usila, S/n Ugao-miraballes Vizcaya 48490",
    "addr:housenumber":"s / n",
    "addr:postcode":"48490",
    "iso:country":"ES",
    "sg:address":"Pol Ind Usila, S/n",
    "sg:city":"Ugao-miraballes",
    "sg:orig_category":"Trabajos De Soldaduras",
    "sg:phone":"+34 946 48 15 93",
    "sg:postcode":"48490",
    "sg:province":"Vizcaya",
    "wof:name":"Suministros Tasol S.l.",
    "wof:placetype":"venue"
},
  "geometry": {"coordinates":[-2.9049639702,43.1779060364],"type":"Point"}
}