{
  "type": "Feature",
  "properties": {
    "iso:country":"ES",
    "sg:address":"Ctra Vila, 16",
    "sg:city":"Viladecans",
    "sg:orig_category":"Tapicer\u00cdas",
    "sg:phone":"+34 936 37 32 99",
    "sg:postcode":"08840",
    "sg:province":"Barcelona",
    "sg:website":"www.joquer.com",
    "wof:name":"Joquer Tapicerias S.a.",
    "wof:placetype":"venue"
},
  "geometry": {"coordinates":[2.0216200352,41.3136367798],"type":"Point"}
}