{
  "type": "Feature",
  "properties": {
    "iso:country":"ES",
    "sg:address":"Calle de Virgen Del Carmen, 23",
    "sg:city":"Donostia-san Sebastian",
    "sg:orig_category":"Herboristas (al Por Menor)",
    "sg:phone":"+34 943 27 76 02",
    "sg:postcode":"20012",
    "sg:province":"Guip\u00f9zcoa",
    "wof:name":"Herbodietetica Loratu",
    "wof:placetype":"venue"
},
  "geometry": {"coordinates":[-1.9705109596,43.3172225952],"type":"Point"}
}