{
  "type": "Feature",
  "properties": {
    "iso:country":"ES",
    "sg:address":"Calle de Motril, 11",
    "sg:city":"Cordoba",
    "sg:orig_category":"Marketing Directo",
    "sg:phone":"+34 957 29 48 45",
    "sg:postcode":"14013",
    "sg:province":"C\u00f3rdoba",
    "wof:name":"Francisco Jose Arenas Alias S.l.",
    "wof:placetype":"venue"
},
  "geometry": {"coordinates":[-4.776968956,37.8627166748],"type":"Point"}
}