{
  "type": "Feature",
  "properties": {
    "addr:full":"Calle de Zaragoza, 6 Calamocha Teruel 44200",
    "addr:housenumber":"6",
    "addr:postcode":"44200",
    "addr:street":"Calle De Zaragoza",
    "iso:country":"ES",
    "sg:address":"Calle de Zaragoza, 6",
    "sg:city":"Calamocha",
    "sg:orig_category":"Carnicer\u00cdas, Carnicer\u00cdas",
    "sg:phone":"+34 978 73 14 01",
    "sg:postcode":"44200",
    "sg:province":"Teruel",
    "wof:name":"Polo Catalan Maria Rosa",
    "wof:placetype":"venue"
},
  "geometry": {"coordinates":[-1.2965730429,40.9208374023],"type":"Point"}
}