{
  "type": "Feature",
  "properties": {
    "iso:country":"ES",
    "sg:address":"Luama, S/n",
    "sg:city":"Ortigueira",
    "sg:orig_category":"Arreglo, Reparaci\u00d3n, Piezas Sueltas De Televisi\u00d3n, V\u00cddeo, Hi",
    "sg:phone":"+34 981 42 24 11",
    "sg:postcode":"15330",
    "sg:province":"La Coru\u00f1a",
    "wof:name":"Aguiar Giz Jose Vicente",
    "wof:placetype":"venue"
},
  "geometry": {"coordinates":[-7.8177599907,43.6668701172],"type":"Point"}
}