{
  "type": "Feature",
  "properties": {
    "iso:country":"ES",
    "sg:address":"Calle de Requena, 1",
    "sg:city":"Casas-iba\u00e7ez",
    "sg:orig_category":"Reposter\u00cdas",
    "sg:phone":"+34 967 46 01 16",
    "sg:postcode":"02200",
    "sg:province":"Albacete",
    "wof:name":"Carrion Ballestero Juan",
    "wof:placetype":"venue"
},
  "geometry": {"coordinates":[-1.4703429937,39.2890396118],"type":"Point"}
}