{
  "type": "Feature",
  "properties": {
    "iso:country":"ES",
    "sg:address":"Rua Condesa Casa Barcena, 8",
    "sg:city":"Vigo",
    "sg:orig_category":"Venta, Instalaci\u00d3n, Reparaci\u00d3n De Antenas Para Televisi\u00d3n",
    "sg:phone":"+34 986 41 84 54",
    "sg:postcode":"36204",
    "sg:province":"Pontevedra",
    "wof:name":"Antesat S. L.",
    "wof:placetype":"venue"
},
  "geometry": {"coordinates":[-8.7178354263,42.2218933105],"type":"Point"}
}