{
  "type": "Feature",
  "properties": {
    "addr:full":"Avda Cehegin (de), 51 Bullas Murcia 30180",
    "addr:housenumber":"51",
    "addr:postcode":"30180",
    "addr:street":"Avda Cehegin De",
    "iso:country":"ES",
    "sg:address":"Avda Cehegin (de), 51",
    "sg:city":"Bullas",
    "sg:orig_category":"Fabricaci\u00d3n De Productos L\u00c1cteos Y Derivados",
    "sg:phone":"+34 968 65 48 69",
    "sg:postcode":"30180",
    "sg:province":"Murcia",
    "wof:name":"Sanchez Garcia Salvador",
    "wof:placetype":"venue"
},
  "geometry": {"coordinates":[-1.6731230021,38.0475578308],"type":"Point"}
}