{
  "type": "Feature",
  "properties": {
    "addr:full":"Calle de Urgel, 7 Madrid Madrid 28019",
    "addr:housenumber":"7",
    "addr:postcode":"madrid;28019",
    "addr:street":"Calle De Urgel",
    "iso:country":"ES",
    "sg:address":"Calle de Urgel, 7",
    "sg:city":"Madrid",
    "sg:orig_category":"Persianas Interiores, Exteriores",
    "sg:phone":"+34 914 71 39 80",
    "sg:postcode":"28019",
    "sg:province":"Madrid",
    "wof:name":"Manzano Sanchez Victoriano",
    "wof:placetype":"venue"
},
  "geometry": {"coordinates":[-3.7256290913,40.3930664062],"type":"Point"}
}