{
  "type": "Feature",
  "properties": {
    "addr:full":"Carrer de Arago, 236 Barcelona Barcelona 08007",
    "addr:housenumber":"236",
    "addr:postcode":"08007",
    "addr:street":"Carrer De Arago",
    "iso:country":"ES",
    "sg:address":"Carrer de Arago, 236",
    "sg:city":"Barcelona",
    "sg:orig_category":"Molduras, Junquillos, Listones Y Molduras Perforadas",
    "sg:phone":"+34 934 87 61 56",
    "sg:postcode":"08007",
    "sg:province":"Barcelona",
    "wof:name":"Sambola Puebla Adela",
    "wof:placetype":"venue"
},
  "geometry": {"coordinates":[2.1620810032,41.389919281],"type":"Point"}
}