{
  "type": "Feature",
  "properties": {
    "iso:country":"ES",
    "sg:address":"Carrer de Cecili Metel, 4",
    "sg:city":"Palma",
    "sg:orig_category":"Centros Empresariales",
    "sg:phone":"+34 971 21 46 49",
    "sg:postcode":"07003",
    "sg:province":"Islas Baleares",
    "wof:name":"A.e.l.i.b.",
    "wof:placetype":"venue"
},
  "geometry": {"coordinates":[2.6520214081,39.5768241882],"type":"Point"}
}