{
  "type": "Feature",
  "properties": {
    "addr:full":"Carrer de Sant Ramon, 79 Campello Alicante 03560",
    "addr:housenumber":"79",
    "addr:postcode":"03560",
    "addr:street":"Carrer De Sant Ramon",
    "iso:country":"ES",
    "sg:address":"Carrer de Sant Ramon, 79",
    "sg:city":"Campello",
    "sg:orig_category":"Postigos, Persianas Y Celos\u00cdas",
    "sg:phone":"+34 965 63 40 51",
    "sg:postcode":"03560",
    "sg:province":"Alicante",
    "wof:name":"Caler Rubio Antonio",
    "wof:placetype":"venue"
},
  "geometry": {"coordinates":[-0.4010069966,38.4289131165],"type":"Point"}
}