{
  "type": "Feature",
  "properties": {
    "addr:full":"Ctra. Posadas, S/n Fuente Palmera C\u00f3rdoba 14120",
    "addr:housenumber":"s / n",
    "addr:postcode":"14120",
    "addr:street":"Ctra. Posadas",
    "iso:country":"ES",
    "sg:address":"Ctra. Posadas, S/n",
    "sg:city":"Fuente Palmera",
    "sg:orig_category":"Charcuter\u00cdas (al Por Mayor)",
    "sg:phone":"+34 957 71 27 89",
    "sg:postcode":"14120",
    "sg:province":"C\u00f3rdoba",
    "wof:name":"Martinez Barragan S.a.",
    "wof:placetype":"venue"
},
  "geometry": {"coordinates":[-5.1065440178,37.7317390442],"type":"Point"}
}