{
  "type": "Feature",
  "properties": {
    "iso:country":"ES",
    "sg:address":"Calle de Araba, 12",
    "sg:city":"Legizamon",
    "sg:orig_category":"Calefacci\u00d3n Central: Material (fabricaci\u00d3n, Al Por Mayor)",
    "sg:phone":"+34 944 26 10 27",
    "sg:postcode":"48450",
    "sg:province":"Vizcaya",
    "wof:name":"Faust Y Kammann Norte S.a.",
    "wof:placetype":"venue"
},
  "geometry": {"coordinates":[-2.8970928192,43.2486495972],"type":"Point"}
}