{
  "type": "Feature",
  "properties": {
    "iso:country":"ES",
    "sg:address":"Avda Ciudad De Barcelona, 63",
    "sg:city":"Madrid",
    "sg:orig_category":"Pintura Y Barniz (al Por Menor)",
    "sg:phone":"+34 915 51 46 28",
    "sg:postcode":"28007",
    "sg:province":"Madrid",
    "wof:name":"Garbajosa Monge Hilaria Genoveva",
    "wof:placetype":"venue"
},
  "geometry": {"coordinates":[-3.6760001183,40.4020271301],"type":"Point"}
}