{
  "type": "Feature",
  "properties": {
    "addr:full":"Calle de Jesus, 16 Palma Islas Baleares 07003",
    "addr:housenumber":"16",
    "addr:postcode":"07003",
    "addr:street":"Calle De Jesus",
    "iso:country":"ES",
    "sg:address":"Calle de Jesus, 16",
    "sg:city":"Palma",
    "sg:orig_category":"Molduras, Junquillos, Listones Y Molduras Perforadas",
    "sg:phone":"+34 971 20 65 53",
    "sg:postcode":"07003",
    "sg:province":"Islas Baleares",
    "wof:name":"Riera Jorda Serafin",
    "wof:placetype":"venue"
},
  "geometry": {"coordinates":[2.6465361118,39.5795593262],"type":"Point"}
}