{
  "type": "Feature",
  "properties": {
    "iso:country":"ES",
    "sg:address":"Eduardo Gonzalez Pastrana, 30",
    "sg:city":"Trobajo Camino",
    "sg:orig_category":"Centros De Educaci\u00d3n Especial",
    "sg:phone":"+34 987 80 02 78",
    "sg:postcode":"24010",
    "sg:province":"Le\u00f3n",
    "wof:name":"Colegio Publico Comarcal Trepalio",
    "wof:placetype":"venue"
},
  "geometry": {"coordinates":[-5.5716600418,42.5981292725],"type":"Point"}
}