{
  "type": "Feature",
  "properties": {
    "addr:full":"Carrer de Llonch, 14 Sabadell Barcelona 08201",
    "addr:housenumber":"14",
    "addr:postcode":"08201",
    "addr:street":"Carrer De Llonch",
    "iso:country":"ES",
    "sg:address":"Carrer de Llonch, 14",
    "sg:city":"Sabadell",
    "sg:orig_category":"Administradores De Bienes Y Delegados De Comunidades De Propietarios",
    "sg:phone":"+34 937 26 48 48",
    "sg:postcode":"08201",
    "sg:province":"Barcelona",
    "wof:name":"Fincas Riana S. A.",
    "wof:placetype":"venue"
},
  "geometry": {"coordinates":[2.1090788841,41.5387611389],"type":"Point"}
}