{
  "type": "Feature",
  "properties": {
    "iso:country":"ES",
    "sg:address":"Rua Curros Enriquez, 2",
    "sg:city":"Sarria",
    "sg:orig_category":"Hormig\u00d3n (m\u00c1quinas E Instalaci\u00d3n)",
    "sg:phone":"+34 982 53 19 06",
    "sg:postcode":"27600",
    "sg:province":"Lugo",
    "wof:name":"Arias Balboa Jose Luis",
    "wof:placetype":"venue"
},
  "geometry": {"coordinates":[-7.413939476,42.7736320496],"type":"Point"}
}