{
  "type": "Feature",
  "properties": {
    "addr:full":"Bijuters, 2 Ciutadella Menorca Islas Baleares 07760",
    "addr:housenumber":"2",
    "addr:postcode":"07760",
    "addr:street":"Bijuters",
    "iso:country":"ES",
    "sg:address":"Bijuters, 2",
    "sg:city":"Ciutadella Menorca",
    "sg:orig_category":"Mec\u00c1nico Del Autom\u00d3vil",
    "sg:phone":"+34 971 48 28 55",
    "sg:postcode":"07760",
    "sg:province":"Islas Baleares",
    "wof:name":"Autos Alayor S.a.",
    "wof:placetype":"venue"
},
  "geometry": {"coordinates":[3.8544538021,40.0101356506],"type":"Point"}
}