{
  "type": "Feature",
  "properties": {
    "iso:country":"ES",
    "sg:address":"Pque Erreniega Parkea, 14",
    "sg:city":"Zizur Mayor",
    "sg:orig_category":"Tintes (fabricaci\u00d3n, Al Por Mayor)",
    "sg:phone":"+34 948 18 65 45",
    "sg:postcode":"31180",
    "sg:province":"Navarra",
    "wof:name":"Tintorerias Navarras S.l.",
    "wof:placetype":"venue"
},
  "geometry": {"coordinates":[-1.6927130222,42.7866821289],"type":"Point"}
}