{
  "type": "Feature",
  "properties": {
    "addr:full":"Calle de Huerta, 9 Santovenia Pisuerga Valladolid 47155",
    "addr:housenumber":"9",
    "addr:postcode":"47155",
    "addr:street":"Calle De Huerta",
    "iso:country":"ES",
    "sg:address":"Calle de Huerta, 9",
    "sg:city":"Santovenia Pisuerga",
    "sg:orig_category":"Delegados, Agentes De Tr\u00c1nsito, Auxiliares De Transporte Internacional",
    "sg:phone":"+34 983 40 05 75",
    "sg:postcode":"47155",
    "sg:province":"Valladolid",
    "wof:name":"Romero Romero Jose Luis",
    "wof:placetype":"venue"
},
  "geometry": {"coordinates":[-4.6894488335,41.6954994202],"type":"Point"}
}