{
  "type": "Feature",
  "properties": {
    "addr:full":"Calle de Jaime I, 3 Alaquas Valencia 46970",
    "addr:housenumber":"3",
    "addr:postcode":"46970",
    "addr:street":"Calle De Jaime I",
    "iso:country":"ES",
    "sg:address":"Calle de Jaime I, 3",
    "sg:city":"Alaquas",
    "sg:orig_category":"Madera Para Chapado",
    "sg:phone":"+34 961 50 09 84",
    "sg:postcode":"46970",
    "sg:province":"Valencia",
    "wof:name":"Chapas Y Maderas Luis Peris S.l",
    "wof:placetype":"venue"
},
  "geometry": {"coordinates":[-0.4677369893,39.4522285461],"type":"Point"}
}