{
  "type": "Feature",
  "properties": {
    "addr:full":"Carr Espronceda, 32 Villanueva De Castellon Valencia 46270",
    "addr:housenumber":"32",
    "addr:postcode":"46270",
    "addr:street":"Carr Espronceda",
    "iso:country":"ES",
    "sg:address":"Carr Espronceda, 32",
    "sg:city":"Villanueva De Castellon",
    "sg:orig_category":"Ebanister\u00cda",
    "sg:phone":"+34 962 45 11 83",
    "sg:postcode":"46270",
    "sg:province":"Valencia",
    "wof:name":"Pardo Sanchis Jose Luis",
    "wof:placetype":"venue"
},
  "geometry": {"coordinates":[-0.5139170289,39.0746841431],"type":"Point"}
}