{
  "type": "Feature",
  "properties": {
    "addr:full":"Pg Maragall, 23 Barcelona Barcelona 08026",
    "addr:housenumber":"23",
    "addr:postcode":"08026",
    "addr:street":"Pg Maragall",
    "iso:country":"ES",
    "sg:address":"Pg Maragall, 23",
    "sg:city":"Barcelona",
    "sg:orig_category":"Molduras, Junquillos, Listones Y Molduras Perforadas",
    "sg:phone":"+34 934 56 31 59",
    "sg:postcode":"08026",
    "sg:province":"Barcelona",
    "wof:name":"Grandio Exposito Lauro",
    "wof:placetype":"venue"
},
  "geometry": {"coordinates":[2.1808493137,41.4145050049],"type":"Point"}
}