{
  "type": "Feature",
  "properties": {
    "iso:country":"ES",
    "sg:address":"Calle de Alzola Pablo De, 3",
    "sg:city":"Bilbao",
    "sg:orig_category":"Empresarios Y Productoras De Espect\u00c1culos",
    "sg:phone":"+34 944 41 43 70",
    "sg:postcode":"48012",
    "sg:province":"Vizcaya",
    "sg:website":"www.paginasamarillas.es",
    "wof:name":"Garcia Valle Yolanda",
    "wof:placetype":"venue"
},
  "geometry": {"coordinates":[-2.9466602802,43.2574195862],"type":"Point"}
}