{
  "type": "Feature",
  "properties": {
    "iso:country":"ES",
    "sg:address":"Carrer de Colom, 312",
    "sg:city":"Terrassa",
    "sg:orig_category":"Art\u00cdculos De Aluminio",
    "sg:phone":"+34 937 85 24 54",
    "sg:postcode":"08223",
    "sg:province":"Barcelona",
    "sg:website":"www.crismetal.com",
    "wof:name":"Crismetal Ibars S.l.",
    "wof:placetype":"venue"
},
  "geometry": {"coordinates":[2.0253651142,41.5537643433],"type":"Point"}
}