{
  "type": "Feature",
  "properties": {
    "addr:full":"Calle de Estoril, 3 Mostoles Madrid 28936",
    "addr:housenumber":"3",
    "addr:postcode":"28936",
    "addr:street":"Calle De Estoril",
    "iso:country":"ES",
    "sg:address":"Calle de Estoril, 3",
    "sg:city":"Mostoles",
    "sg:orig_category":"Electrodom\u00c9sticos (al Por Menor)",
    "sg:phone":"+34 916 46 21 94",
    "sg:postcode":"28936",
    "sg:province":"Madrid",
    "wof:name":"Sanchez Blazquez Fernando",
    "wof:placetype":"venue"
},
  "geometry": {"coordinates":[-3.8490190506,40.325553894],"type":"Point"}
}