{
  "type": "Feature",
  "properties": {
    "iso:country":"ES",
    "sg:address":"Av Ramon I Cajal, 37",
    "sg:city":"Tarragona",
    "sg:orig_category":"Farmacias",
    "sg:phone":"+34 977 21 22 86",
    "sg:postcode":"43001",
    "sg:province":"Tarragona",
    "wof:name":"Cabrito Serra Maria Teresa",
    "wof:placetype":"venue"
},
  "geometry": {"coordinates":[1.2452230453,41.1161308289],"type":"Point"}
}