{
  "type": "Feature",
  "properties": {
    "iso:country":"ES",
    "sg:address":"Atva. Zaragoza-logro\u00f1o, 5",
    "sg:city":"Casetas",
    "sg:orig_category":"Art\u00cdculos Funerarios (al Por Menor)",
    "sg:phone":"+34 976 77 52 77",
    "sg:postcode":"50620",
    "sg:province":"Zaragoza",
    "wof:name":"Pompas Funebres Aragon S.l.",
    "wof:placetype":"venue"
},
  "geometry": {"coordinates":[-1.0303390026,41.7199440002],"type":"Point"}
}