{
  "type": "Feature",
  "properties": {
    "iso:country":"ES",
    "sg:address":"Calle de Isidro Diaz, 1",
    "sg:city":"Tarajalejo",
    "sg:orig_category":"Promotores Constructores",
    "sg:phone":"+34 928 87 21 64",
    "sg:postcode":"35627",
    "sg:province":"Las Palmas",
    "wof:name":"Abaco Gesfiscont S.l.",
    "wof:placetype":"venue"
},
  "geometry": {"coordinates":[-14.11628,28.191994],"type":"Point"}
}