{
  "type": "Feature",
  "properties": {
    "iso:country":"ES",
    "sg:address":"Carrer de Cala Blanca, 7",
    "sg:city":"Palma",
    "sg:orig_category":"Abrasivos Y Superabrasivos (fabricaci\u00d3n, Al Por Mayor)",
    "sg:phone":"+34 971 47 68 22",
    "sg:postcode":"07009",
    "sg:province":"Islas Baleares",
    "wof:name":"Coll Tomas Lorenzo",
    "wof:placetype":"venue"
},
  "geometry": {"coordinates":[2.6766169071,39.5970153809],"type":"Point"}
}