{
  "type": "Feature",
  "properties": {
    "addr:full":"Carrer de Misser Rufet, 3 Vilafranca Penedes Barcelona 08720",
    "addr:housenumber":"3",
    "addr:postcode":"08720",
    "addr:street":"Carrer De Misser Rufet;Penedes Barcelona",
    "iso:country":"ES",
    "sg:address":"Carrer de Misser Rufet, 3",
    "sg:city":"Vilafranca Penedes",
    "sg:orig_category":"Peluquer\u00cdas, Peluquer\u00cda Mixta",
    "sg:phone":"+34 938 17 52 44",
    "sg:postcode":"08720",
    "sg:province":"Barcelona",
    "wof:name":"Bruna  Natalia Laura",
    "wof:placetype":"venue"
},
  "geometry": {"coordinates":[1.7028729916,41.3458404541],"type":"Point"}
}