{
  "type": "Feature",
  "properties": {
    "addr:full":"Praj Canteras, S/n Molina Segura Murcia 30500",
    "addr:housenumber":"s",
    "addr:postcode":"30500",
    "addr:street":"/ N Molina",
    "iso:country":"ES",
    "sg:address":"Praj Canteras, S/n",
    "sg:city":"Molina Segura",
    "sg:orig_category":"Alimentaci\u00d3n General (al Por Mayor)",
    "sg:phone":"+34 968 38 97 19",
    "sg:postcode":"30500",
    "sg:province":"Murcia",
    "wof:name":"Agrovic Alimentacion S.a.",
    "wof:placetype":"venue"
},
  "geometry": {"coordinates":[-1.2075797319,38.0452728271],"type":"Point"}
}