{
  "type": "Feature",
  "properties": {
    "addr:full":"Cra. Nacional Ii, Km. 0065,0 S. Andreu Llavaneres Barcelona 08392",
    "addr:postcode":"08392",
    "addr:street":"Km. 0065,0 S. Andreu Llavaneres Barcelona",
    "iso:country":"ES",
    "sg:address":"Cra. Nacional Ii, Km. 0065,0",
    "sg:city":"S. Andreu Llavaneres",
    "sg:orig_category":"Grabados",
    "sg:phone":"+34 937 95 28 40",
    "sg:postcode":"08392",
    "sg:province":"Barcelona",
    "wof:name":"Montero Espinazo Antonio",
    "wof:placetype":"venue"
},
  "geometry": {"coordinates":[2.4849700928,41.5697517395],"type":"Point"}
}