{
  "type": "Feature",
  "properties": {
    "addr:full":"Calle de Rascon, 26 Huelva Huelva 21001",
    "addr:housenumber":"26",
    "addr:postcode":"21001",
    "addr:street":"Calle De Rascon",
    "iso:country":"ES",
    "sg:address":"Calle de Rascon, 26",
    "sg:city":"Huelva",
    "sg:orig_category":"Arquitectos",
    "sg:phone":"+34 959 28 03 41",
    "sg:postcode":"21001",
    "sg:province":"Huelva",
    "wof:name":"Mu\u00f1oz Martinez Jose",
    "wof:placetype":"venue"
},
  "geometry": {"coordinates":[-6.9534358978,37.2560958862],"type":"Point"}
}