{
  "type": "Feature",
  "properties": {
    "addr:full":"Raval De Sant Jaume, 34 Calaf Barcelona 08280",
    "addr:housenumber":"34",
    "addr:postcode":"08280",
    "addr:street":"Raval De Sant Jaume",
    "iso:country":"ES",
    "sg:address":"Raval De Sant Jaume, 34",
    "sg:city":"Calaf",
    "sg:orig_category":"Refiner\u00cdas De Petr\u00d3leo",
    "sg:phone":"+34 938 68 10 58",
    "sg:postcode":"08280",
    "sg:province":"Barcelona",
    "wof:name":"Calaf Oleum S.l.",
    "wof:placetype":"venue"
},
  "geometry": {"coordinates":[1.5121699572,41.7332496643],"type":"Point"}
}