{
  "type": "Feature",
  "properties": {
    "addr:full":"Pl Creu, 4 Berga-ciudad Barcelona 08600",
    "addr:housenumber":"4",
    "addr:postcode":"08600",
    "addr:street":"Pl Creu;Barcelona",
    "iso:country":"ES",
    "sg:address":"Pl Creu, 4",
    "sg:city":"Berga-ciudad",
    "sg:orig_category":"Agencias De Viajes",
    "sg:phone":"+34 938 22 09 14",
    "sg:postcode":"08600",
    "sg:province":"Barcelona",
    "sg:website":"www.halconviajes.com",
    "wof:name":"Viajes Halcon S.a.",
    "wof:placetype":"venue"
},
  "geometry": {"coordinates":[1.8441770077,42.1015510559],"type":"Point"}
}