{
  "type": "Feature",
  "properties": {
    "iso:country":"ES",
    "sg:address":"Calle de Espa\u00d1a, 43",
    "sg:city":"Yecla",
    "sg:orig_category":"Supermercados Y Hipermercados",
    "sg:phone":"+34 968 79 52 50",
    "sg:postcode":"30510",
    "sg:province":"Murcia",
    "wof:name":"Gil Marco Maria",
    "wof:placetype":"venue"
},
  "geometry": {"coordinates":[-1.1129000187,38.6120872498],"type":"Point"}
}