{
  "type": "Feature",
  "properties": {
    "iso:country":"ES",
    "sg:address":"Calle de Modesto Lafuente, 8",
    "sg:city":"Le\u00f3n",
    "sg:orig_category":"Abogados",
    "sg:phone":"+34 987 20 69 10",
    "sg:postcode":"24004",
    "sg:province":"Le\u00f3n",
    "wof:name":"Despacho Merino Y Asociados S.l",
    "wof:placetype":"venue"
},
  "geometry": {"coordinates":[-5.5770740509,42.5949440002],"type":"Point"}
}