{
  "type": "Feature",
  "properties": {
    "iso:country":"ES",
    "sg:address":"Calle de Mayor, 2",
    "sg:city":"Puertomingalvo",
    "sg:classifiers":[
        {
            "category":"Taxi",
            "type":"Transportation"
        }
    ],
    "sg:phone":"+34 978 80 22 91",
    "sg:postcode":"44411",
    "sg:province":"Teruel",
    "wof:name":"Garces Solsona Nicolas",
    "wof:placetype":"venue"
},
  "geometry": {"coordinates":[-0.4599440098,40.2645874023],"type":"Point"}
}