{
  "type": "Feature",
  "properties": {
    "iso:country":"ES",
    "sg:address":"Calle de Virgen Del Amparo, 4",
    "sg:city":"Marbella",
    "sg:orig_category":"Carnicer\u00cdas, Carnicer\u00cdas",
    "sg:phone":"+34 952 77 77 97",
    "sg:postcode":"29600",
    "sg:province":"M\u00e1laga",
    "wof:name":"Aro Gil Salvador De",
    "wof:placetype":"venue"
},
  "geometry": {"coordinates":[-4.8818764687,36.5107879639],"type":"Point"}
}