{
  "type": "Feature",
  "properties": {
    "iso:country":"ES",
    "sg:address":"G.v. Germanias, 25",
    "sg:city":"Valencia",
    "sg:orig_category":"Asilos De Ancianos. Centros Privados",
    "sg:phone":"+34 963 41 30 00",
    "sg:postcode":"46006",
    "sg:province":"Valencia",
    "wof:name":"Asociacion De Prejubilados De Telefonica Valencia",
    "wof:placetype":"venue"
},
  "geometry": {"coordinates":[-0.3756884933,39.464050293],"type":"Point"}
}