{
  "type": "Feature",
  "properties": {
    "addr:full":"Carrer de Cami Reial, 118 Palau-solita I Plegamans Barcelona 08184",
    "addr:housenumber":"118",
    "addr:postcode":"08184",
    "addr:street":"Carrer De;Reial",
    "iso:country":"ES",
    "sg:address":"Carrer de Cami Reial, 118",
    "sg:city":"Palau-solita I Plegamans",
    "sg:orig_category":"Agencias Y Agentes Comerciales, Representantes",
    "sg:phone":"+34 938 64 33 04",
    "sg:postcode":"08184",
    "sg:province":"Barcelona",
    "wof:name":"Castillo Lopez Patricia",
    "wof:placetype":"venue"
},
  "geometry": {"coordinates":[2.181032896,41.5802307129],"type":"Point"}
}