{
  "type": "Feature",
  "properties": {
    "iso:country":"ES",
    "sg:address":"Calle de Tejar, 8",
    "sg:city":"Boecillo",
    "sg:orig_category":"Farmacias",
    "sg:phone":"+34 983 55 21 92",
    "sg:postcode":"47151",
    "sg:province":"Valladolid",
    "wof:name":"Garcia Garcia Jesus Manuel",
    "wof:placetype":"venue"
},
  "geometry": {"coordinates":[-4.7008738518,41.5422897339],"type":"Point"}
}