{
  "type": "Feature",
  "properties": {
    "iso:country":"ES",
    "sg:address":"Ondarreta Kalea, 4",
    "sg:city":"Andoain",
    "sg:orig_category":"Pescader\u00cdas (al Por Menor)",
    "sg:phone":"+34 943 30 02 45",
    "sg:postcode":"20140",
    "sg:province":"Guip\u00f9zcoa",
    "wof:name":"Gorrochategui Iraola Bego\u00f1a",
    "wof:placetype":"venue"
},
  "geometry": {"coordinates":[-2.0217511654,43.2180404663],"type":"Point"}
}