{
  "type": "Feature",
  "properties": {
    "addr:full":"Calle de Calvario-la Orotava (el), 6 Orotava Santa Cruz De Tenerife 38300",
    "addr:postcode":"38300",
    "addr:street":"Calle De Calvario-La;El;Orotava",
    "iso:country":"ES",
    "sg:address":"Calle de Calvario-la Orotava (el), 6",
    "sg:city":"Orotava",
    "sg:orig_category":"Abogados",
    "sg:phone":"+34 922 33 50 14",
    "sg:postcode":"38300",
    "sg:province":"Santa Cruz De Tenerife",
    "wof:name":"Gonzalez Alonso Andrea",
    "wof:placetype":"venue"
},
  "geometry": {"coordinates":[-16.5226840973,28.3915653229],"type":"Point"}
}