{
  "type": "Feature",
  "properties": {
    "iso:country":"ES",
    "sg:address":"Carr Adolfo Saez, 24",
    "sg:city":"Aldaia",
    "sg:orig_category":"Asesor\u00cda De Formaci\u00d3n Y Gesti\u00d3n De Personal",
    "sg:phone":"+34 961 51 80 87",
    "sg:postcode":"46960",
    "sg:province":"Valencia",
    "wof:name":"Folgado I Asuncion Asesores S.l.",
    "wof:placetype":"venue"
},
  "geometry": {"coordinates":[-0.4649150074,39.4630661011],"type":"Point"}
}