{
  "type": "Feature",
  "properties": {
    "addr:full":"Calle de Hermanos Garcia Noblejas, 196 Madrid Madrid 28037",
    "addr:housenumber":"196",
    "addr:postcode":"28037",
    "addr:street":"Calle De Hermanos Garcia Noblejas",
    "iso:country":"ES",
    "sg:address":"Calle de Hermanos Garcia Noblejas, 196",
    "sg:city":"Madrid",
    "sg:orig_category":"Cervecer\u00cdas",
    "sg:phone":"+34 913 06 26 65",
    "sg:postcode":"28037",
    "sg:province":"Madrid",
    "wof:name":"Telemensaje S.a.",
    "wof:placetype":"venue"
},
  "geometry": {"coordinates":[-3.6241130829,40.4182357788],"type":"Point"}
}