{
  "type": "Feature",
  "properties": {
    "addr:full":"Calle de Idiakez, 9 Donostia-san Sebastian Guip\u00f9zcoa 20004",
    "addr:housenumber":"9",
    "addr:postcode":"20004",
    "addr:street":"Calle De Idiakez",
    "iso:country":"ES",
    "sg:address":"Calle de Idiakez, 9",
    "sg:city":"Donostia-san Sebastian",
    "sg:orig_category":"Navegaci\u00d3n (equipos Fluviales)",
    "sg:phone":"+34 943 44 06 52",
    "sg:postcode":"20004",
    "sg:province":"Guip\u00f9zcoa",
    "wof:name":"Pesquera Echalar S.a.",
    "wof:placetype":"venue"
},
  "geometry": {"coordinates":[-1.980995059,43.3203773499],"type":"Point"}
}