{
  "type": "Feature",
  "properties": {
    "addr:full":"Carretera, S/n Oteo Burgos 09512",
    "addr:postcode":"09512",
    "addr:street":"Carretera S / N Oteo",
    "iso:country":"ES",
    "sg:address":"Carretera, S/n",
    "sg:city":"Oteo",
    "sg:orig_category":"M\u00c9dicos: Cardiolog\u00cda Y Afecciones Cardiovasculares",
    "sg:phone":"+34 947 19 50 74",
    "sg:postcode":"09512",
    "sg:province":"Burgos",
    "wof:name":"Junta Administrativa De Oteo De Losa",
    "wof:placetype":"venue"
},
  "geometry": {"coordinates":[-3.3156592846,43.0003852844],"type":"Point"}
}