{
  "type": "Feature",
  "properties": {
    "addr:full":"Pla\u00c7 Gran, 5 Centre Urba Girona 17500",
    "addr:housenumber":"5;urba",
    "addr:postcode":"17500",
    "addr:street":"Gran",
    "iso:country":"ES",
    "sg:address":"Pla\u00c7 Gran, 5",
    "sg:city":"Centre Urba",
    "sg:orig_category":"Inmobiliaria (agencias)",
    "sg:phone":"+34 972 70 34 69",
    "sg:postcode":"17500",
    "sg:province":"Girona",
    "sg:website":"www.ferlam.net",
    "wof:name":"Sereveis Immobiliaris Maribel-margarita S.l.",
    "wof:placetype":"venue"
},
  "geometry": {"coordinates":[2.1959049702,42.1965866089],"type":"Point"}
}