{
  "type": "Feature",
  "properties": {
    "iso:country":"ES",
    "sg:address":"Carrer de Major, 56",
    "sg:city":"Salou",
    "sg:orig_category":"Art\u00cdculos De Regalo (al Por Menor)",
    "sg:phone":"+34 977 38 19 91",
    "sg:postcode":"43840",
    "sg:province":"Tarragona",
    "wof:name":"Gonzalez Rodriguez Clara",
    "wof:placetype":"venue"
},
  "geometry": {"coordinates":[1.1427019835,41.0756034851],"type":"Point"}
}