{
  "type": "Feature",
  "properties": {
    "iso:country":"ES",
    "sg:address":"Calle de Comercio, 15",
    "sg:city":"Legutiano",
    "sg:orig_category":"Farmacias",
    "sg:phone":"+34 945 45 51 89",
    "sg:postcode":"01170",
    "sg:province":"\u00c1lava",
    "wof:name":"Lopez De Ocariz Lopez De Munain Milagros",
    "wof:placetype":"venue"
},
  "geometry": {"coordinates":[-2.6424798965,42.9788970947],"type":"Point"}
}