{
  "type": "Feature",
  "properties": {
    "addr:full":"Calle de Juan De Herrera, 5 Santander Cantabria 39002",
    "addr:housenumber":"5",
    "addr:postcode":"39002",
    "addr:street":"Calle De Juan De Herrera",
    "iso:country":"ES",
    "sg:address":"Calle de Juan De Herrera, 5",
    "sg:city":"Santander",
    "sg:orig_category":"Centros P\u00dablicos De Formaci\u00d3n Profesional Y T\u00c9cnica",
    "sg:phone":"+34 942 31 82 62",
    "sg:postcode":"39002",
    "sg:province":"Cantabria",
    "wof:name":"Colegio Oficial Agentes Comerciales",
    "wof:placetype":"venue"
},
  "geometry": {"coordinates":[-3.8086500168,43.4622268677],"type":"Point"}
}