{
  "type": "Feature",
  "properties": {
    "addr:full":"D (pol Ind Brenes), S/n Carmona Sevilla 41410",
    "addr:housenumber":"s / n",
    "addr:postcode":"41410",
    "iso:country":"ES",
    "sg:address":"D (pol Ind Brenes), S/n",
    "sg:city":"Carmona",
    "sg:orig_category":"Material Y Herramientas Agr\u00cdcolas",
    "sg:phone":"+34 954 14 19 04",
    "sg:postcode":"41410",
    "sg:province":"Sevilla",
    "wof:name":"Talleres Francisco Sobera S.l.",
    "wof:placetype":"venue"
},
  "geometry": {"coordinates":[-5.644464016,37.4767036438],"type":"Point"}
}