{
  "type": "Feature",
  "properties": {
    "addr:full":"Calle de Jesus, 19 Mazarron Murcia 30870",
    "addr:housenumber":"19",
    "addr:postcode":"30870",
    "addr:street":"Calle De Jesus",
    "iso:country":"ES",
    "sg:address":"Calle de Jesus, 19",
    "sg:city":"Mazarron",
    "sg:orig_category":"Empresas De Desmonte",
    "sg:phone":"+34 968 59 16 62",
    "sg:postcode":"30870",
    "sg:province":"Murcia",
    "wof:name":"Treimsur Sl",
    "wof:placetype":"venue"
},
  "geometry": {"coordinates":[-1.3123589754,37.5996627808],"type":"Point"}
}