{
  "type": "Feature",
  "properties": {
    "iso:country":"ES",
    "sg:address":"Rbla Pau, 65",
    "sg:city":"Vilanova I La Geltru",
    "sg:orig_category":"Inmobiliaria (agencias)",
    "sg:phone":"+34 938 15 62 35",
    "sg:postcode":"08800",
    "sg:province":"Barcelona",
    "wof:name":"Martin Perez Concepcion",
    "wof:placetype":"venue"
},
  "geometry": {"coordinates":[1.7283090353,41.2183418274],"type":"Point"}
}