{
  "type": "Feature",
  "properties": {
    "addr:full":"Rua Garcia Alvarez, 16 Barrantes Pontevedra 36636",
    "addr:housenumber":"16",
    "addr:postcode":"36636",
    "addr:street":"Rua Garcia Alvarez",
    "iso:country":"ES",
    "sg:address":"Rua Garcia Alvarez, 16",
    "sg:city":"Barrantes",
    "sg:orig_category":"Centros De Educaci\u00d3n Especial",
    "sg:phone":"+34 986 71 00 21",
    "sg:postcode":"36636",
    "sg:province":"Pontevedra",
    "wof:name":"Colexio Publico Julia Becerra Malvar",
    "wof:placetype":"venue"
},
  "geometry": {"coordinates":[-8.7683343887,42.5012207031],"type":"Point"}
}