{
  "type": "Feature",
  "properties": {
    "addr:full":"Calle de Alamos, 17 Jaen Ja\u00e9n 23003",
    "addr:housenumber":"17;jae\u0301n",
    "addr:postcode":"23003",
    "addr:street":"Calle De Alamos",
    "iso:country":"ES",
    "sg:address":"Calle de Alamos, 17",
    "sg:city":"Jaen",
    "sg:orig_category":"Muebles, Minoristas",
    "sg:phone":"+34 953 23 73 37",
    "sg:postcode":"23003",
    "sg:province":"Ja\u00e9n",
    "wof:name":"Condestable Iranzo S.a.",
    "wof:placetype":"venue"
},
  "geometry": {"coordinates":[-3.7907156944,37.7672309875],"type":"Point"}
}