{
  "type": "Feature",
  "properties": {
    "addr:full":"Pl Mercadal, 10 Barcelona Barcelona 08030",
    "addr:housenumber":"10",
    "addr:postcode":"08030",
    "addr:street":"Pl Mercadal",
    "iso:country":"ES",
    "sg:address":"Pl Mercadal, 10",
    "sg:city":"Barcelona",
    "sg:orig_category":"Transportes Por Carretera: Lotes Completos, Mercanc\u00cdas Diversas",
    "sg:phone":"+34 933 45 00 55",
    "sg:postcode":"08030",
    "sg:province":"Barcelona",
    "wof:name":"Perello Mestres Emilio",
    "wof:placetype":"venue"
},
  "geometry": {"coordinates":[2.1883490086,41.4345054626],"type":"Point"}
}