{
  "type": "Feature",
  "properties": {
    "iso:country":"ES",
    "sg:address":"Cta. M. Badajoz, Km. 0368,0",
    "sg:city":"Lobon",
    "sg:orig_category":"Transporte En General",
    "sg:phone":"+34 924 14 06 26",
    "sg:postcode":"06498",
    "sg:province":"Badajoz",
    "wof:name":"Dulmedi Extremadura S.c.l.",
    "wof:placetype":"venue"
},
  "geometry": {"coordinates":[-6.6271691322,38.8500518799],"type":"Point"}
}