{
  "type": "Feature",
  "properties": {
    "addr:full":"Calle de Pedro Velasco, 26 Vitigudino Salamanca 37210",
    "addr:housenumber":"26",
    "addr:postcode":"37210",
    "addr:street":"Calle De Pedro Velasco",
    "iso:country":"ES",
    "sg:address":"Calle de Pedro Velasco, 26",
    "sg:city":"Vitigudino",
    "sg:orig_category":"Farmacias",
    "sg:phone":"+34 923 50 00 06",
    "sg:postcode":"37210",
    "sg:province":"Salamanca",
    "wof:name":"Delgado De U\u00f1a Juan",
    "wof:placetype":"venue"
},
  "geometry": {"coordinates":[-6.4338140488,41.0085601807],"type":"Point"}
}