{
  "type": "Feature",
  "properties": {
    "iso:country":"ES",
    "sg:address":"O Rio Da Ucha, Km. 0001,0",
    "sg:city":"Rio Da Ucha",
    "sg:orig_category":"Agentes, Concesionarios Y Sucursales De Veh\u00cdculos",
    "sg:phone":"+34 986 54 30 44",
    "sg:postcode":"36634",
    "sg:province":"Pontevedra",
    "wof:name":"Talleres Manuel Mosteiro E Hijos S.l.",
    "wof:placetype":"venue"
},
  "geometry": {"coordinates":[-8.811788559,42.52526474],"type":"Point"}
}