{
  "type": "Feature",
  "properties": {
    "addr:full":"Calle de Matadero, 3 Hellin Albacete 02400",
    "addr:housenumber":"3",
    "addr:postcode":"02400",
    "addr:street":"Calle De Matadero",
    "iso:country":"ES",
    "sg:address":"Calle de Matadero, 3",
    "sg:city":"Hellin",
    "sg:orig_category":"Cueros Y Pieles (al Por Mayor)",
    "sg:phone":"+34 967 30 03 05",
    "sg:postcode":"02400",
    "sg:province":"Albacete",
    "wof:name":"Sanchez Merenciano S. A.",
    "wof:placetype":"venue"
},
  "geometry": {"coordinates":[-1.7061150074,38.5191650391],"type":"Point"}
}