{
  "type": "Feature",
  "properties": {
    "iso:country":"ES",
    "sg:address":"C/ Antoni Fluxa, 52",
    "sg:city":"Inca",
    "sg:classifiers":[
        {
            "category":"Personal",
            "subcategory":"Barber",
            "type":"Services"
        }
    ],
    "sg:phone":"+34 971 50 52 74",
    "sg:postcode":"07300",
    "sg:province":"Islas Baleares",
    "sg:tags":[
        "caballeros",
        "de",
        "peluqueros"
    ],
    "wof:name":"Navarro Gonzalez Miguel",
    "wof:placetype":"venue"
},
  "geometry": {"coordinates":[2.9084620476,39.7200088501],"type":"Point"}
}