{
  "type": "Feature",
  "properties": {
    "addr:full":"Rbla Onze De Setembre, S/n Cassa Selva Girona 17244",
    "addr:housenumber":"s / n",
    "addr:postcode":"17244",
    "addr:street":"Rbla Onze De Setembre",
    "iso:country":"ES",
    "sg:address":"Rbla Onze De Setembre, S/n",
    "sg:city":"Cassa Selva",
    "sg:orig_category":"Ense\u00d1anza, Formaci\u00d3n Profesional: Aprendizaje",
    "sg:phone":"+34 972 46 00 05",
    "sg:postcode":"17244",
    "sg:province":"Girona",
    "wof:name":"Ajuntament De Cassa De La Selva",
    "wof:placetype":"venue"
},
  "geometry": {"coordinates":[2.880222559,41.8836784363],"type":"Point"}
}