{
  "type": "Feature",
  "properties": {
    "iso:country":"ES",
    "sg:address":"Carr Canonigo Cebrian, 4",
    "sg:city":"Xativa",
    "sg:orig_category":"Asilos De Ancianos. Centros Privados",
    "sg:phone":"+34 962 27 64 25",
    "sg:postcode":"46800",
    "sg:province":"Valencia",
    "wof:name":"Hogar De San Jose",
    "wof:placetype":"venue"
},
  "geometry": {"coordinates":[-0.5228790045,38.9883613586],"type":"Point"}
}