{
  "type": "Feature",
  "properties": {
    "iso:country":"ES",
    "sg:address":"Dr Lopez Torruellas, 9",
    "sg:city":"Tomares",
    "sg:orig_category":"Cristaler\u00cdas",
    "sg:phone":"+34 954 15 63 45",
    "sg:postcode":"41940",
    "sg:province":"Sevilla",
    "wof:name":"Lobo Garcia Maria Remedios",
    "wof:placetype":"venue"
},
  "geometry": {"coordinates":[-6.0477590561,37.3773002625],"type":"Point"}
}