{
  "type": "Feature",
  "properties": {
    "addr:full":"Pase Regino Sainz De La Maza, 9 Burgos Burgos 09004",
    "addr:housenumber":"9",
    "addr:postcode":"09004",
    "addr:street":"Regino;De La Maza",
    "iso:country":"ES",
    "sg:address":"Pase Regino Sainz De La Maza, 9",
    "sg:city":"Burgos",
    "sg:orig_category":"Fabricaci\u00d3n, Distribuci\u00d3n De Discos, V\u00cddeodiscos Y Musicassettes",
    "sg:phone":"+34 947 20 07 57",
    "sg:postcode":"09004",
    "sg:province":"Burgos",
    "wof:name":"Discos Burgos S.l.",
    "wof:placetype":"venue"
},
  "geometry": {"coordinates":[-3.6899778843,42.3436164856],"type":"Point"}
}