{
  "type": "Feature",
  "properties": {
    "iso:country":"ES",
    "sg:address":"Poligono Industrial, 32",
    "sg:city":"Castro Riberas",
    "sg:orig_category":"Mec\u00c1nico Del Autom\u00d3vil",
    "sg:phone":"+34 982 31 01 29",
    "sg:postcode":"27260",
    "sg:province":"Lugo",
    "wof:name":"Sancosmed Blanco Antonio",
    "wof:placetype":"venue"
},
  "geometry": {"coordinates":[-7.5693798065,43.0095100403],"type":"Point"}
}