{
  "type": "Feature",
  "properties": {
    "addr:full":"Carr Via Emporitana, 21 Figueres Girona 17600",
    "addr:housenumber":"21",
    "addr:postcode":"17600",
    "addr:street":"Carr Via Emporitana",
    "iso:country":"ES",
    "sg:address":"Carr Via Emporitana, 21",
    "sg:city":"Figueres",
    "sg:orig_category":"Agencias Y Agentes Comerciales, Representantes",
    "sg:phone":"+34 972 50 52 89",
    "sg:postcode":"17600",
    "sg:province":"Girona",
    "wof:name":"Valenti Romero Jose Maria",
    "wof:placetype":"venue"
},
  "geometry": {"coordinates":[2.9573171139,42.2625923157],"type":"Point"}
}