{
  "type": "Feature",
  "properties": {
    "addr:full":"Calle de Jesus, 18 Oviedo Asturias 33009",
    "addr:housenumber":"18",
    "addr:postcode":"33009",
    "addr:street":"Calle De Jesus",
    "iso:country":"ES",
    "sg:address":"Calle de Jesus, 18",
    "sg:city":"Oviedo",
    "sg:orig_category":"Administradores De Bienes Y Delegados De Comunidades De Propietarios",
    "sg:phone":"+34 985 22 30 55",
    "sg:postcode":"33009",
    "sg:province":"Asturias",
    "wof:name":"Iglesias Garcia Jesus",
    "wof:placetype":"venue"
},
  "geometry": {"coordinates":[-5.8450889587,43.3605384827],"type":"Point"}
}