{
  "type": "Feature",
  "properties": {
    "iso:country":"ES",
    "sg:address":"Calle de Calvo Sotelo, 27",
    "sg:city":"Padron",
    "sg:orig_category":"Bisuter\u00cda, Joyer\u00cda, Relojer\u00cda (al Por Menor)",
    "sg:phone":"+34 981 81 18 99",
    "sg:postcode":"15900",
    "sg:province":"La Coru\u00f1a",
    "wof:name":"Fernandez Camoiras Antonio",
    "wof:placetype":"venue"
},
  "geometry": {"coordinates":[-8.659822464,42.7377471924],"type":"Point"}
}