{
  "type": "Feature",
  "properties": {
    "iso:country":"ES",
    "sg:address":"Calle de Drago, 48",
    "sg:city":"Galdar",
    "sg:orig_category":"Promotores Constructores",
    "sg:phone":"+34 928 55 11 53",
    "sg:postcode":"35460",
    "sg:province":"Las Palmas",
    "wof:name":"Vega Castellano Y Suarez Castellano E Hijos S.l.",
    "wof:placetype":"venue"
},
  "geometry": {"coordinates":[-15.6512537003,28.1460514069],"type":"Point"}
}