{
  "type": "Feature",
  "properties": {
    "iso:country":"ES",
    "sg:address":"Calle de Mendez Nu\u00d1ez, 24",
    "sg:city":"Valencia Ventoso",
    "sg:orig_category":"Ortopedia General",
    "sg:phone":"+34 924 56 24 50",
    "sg:postcode":"06330",
    "sg:province":"Badajoz",
    "wof:name":"Barrial Centeno Emilio Jose",
    "wof:placetype":"venue"
},
  "geometry": {"coordinates":[-6.4718489647,38.2648391724],"type":"Point"}
}