{
  "type": "Feature",
  "properties": {
    "iso:country":"ES",
    "sg:address":"Calle de Angel, 4",
    "sg:city":"Albacete",
    "sg:orig_category":"Cooperativas Agr\u00cdcolas",
    "sg:phone":"+34 967 24 87 05",
    "sg:postcode":"02006",
    "sg:province":"Albacete",
    "wof:name":"Manuses S.cooperativa",
    "wof:placetype":"venue"
},
  "geometry": {"coordinates":[-1.8468346596,38.9868202209],"type":"Point"}
}