{
  "type": "Feature",
  "properties": {
    "iso:country":"ES",
    "sg:address":"Calle de Calvario-la Orotava (el), 5",
    "sg:city":"Orotava",
    "sg:orig_category":"Contables",
    "sg:phone":"+34 922 33 21 06",
    "sg:postcode":"38300",
    "sg:province":"Santa Cruz De Tenerife",
    "wof:name":"Cedatos S.l.",
    "wof:placetype":"venue"
},
  "geometry": {"coordinates":[-16.5220966339,28.3926258087],"type":"Point"}
}