{
  "type": "Feature",
  "properties": {
    "addr:full":"Calle de A, 8 Mutiloabeiti Navarra 31192",
    "addr:housenumber":"8",
    "addr:postcode":"31192",
    "addr:street":"Calle De A",
    "iso:country":"ES",
    "sg:address":"Calle de A, 8",
    "sg:city":"Mutiloabeiti",
    "sg:orig_category":"Carros Elevadores, Carros De Operaciones Portuarias",
    "sg:phone":"+34 948 24 16 99",
    "sg:postcode":"31192",
    "sg:province":"Navarra",
    "wof:name":"Lapurbide Manutencion S.a.",
    "wof:placetype":"venue"
},
  "geometry": {"coordinates":[-1.6344386339,42.8068733215],"type":"Point"}
}