{
  "type": "Feature",
  "properties": {
    "iso:country":"ES",
    "sg:address":"Cra. De Gualba, Km. 0238,0",
    "sg:city":"Gualba",
    "sg:orig_category":"Filtros Y Elementos Filtradores",
    "sg:phone":"+34 938 47 00 99",
    "sg:postcode":"08474",
    "sg:province":"Barcelona",
    "wof:name":"Ms Clever S. L.",
    "wof:placetype":"venue"
},
  "geometry": {"coordinates":[2.5234498978,41.7172317505],"type":"Point"}
}