{
  "type": "Feature",
  "properties": {
    "iso:country":"ES",
    "sg:address":"Calle de Miguel Hernandez, 46",
    "sg:city":"Bollullos Mitacion",
    "sg:orig_category":"Construcciones Met\u00c1licas",
    "sg:phone":"+34 955 76 60 27",
    "sg:postcode":"41110",
    "sg:province":"Sevilla",
    "wof:name":"Herrera Rodriguez Rosario",
    "wof:placetype":"venue"
},
  "geometry": {"coordinates":[-6.141119957,37.3434944153],"type":"Point"}
}