{
  "type": "Feature",
  "properties": {
    "iso:country":"ES",
    "sg:address":"Arriaga Kalea, 5",
    "sg:city":"Elgoibar",
    "sg:orig_category":"Metalurgia",
    "sg:phone":"+34 943 74 42 27",
    "sg:postcode":"20870",
    "sg:province":"Guip\u00f9zcoa",
    "wof:name":"Industrias Traterh S.a.",
    "wof:placetype":"venue"
},
  "geometry": {"coordinates":[-2.4138290882,43.2163581848],"type":"Point"}
}