{
  "type": "Feature",
  "properties": {
    "iso:country":"ES",
    "sg:address":"Calle de Ancha, 2",
    "sg:city":"Aranjuez",
    "sg:orig_category":"Carnicer\u00cdas, Carnicer\u00cdas",
    "sg:phone":"+34 918 75 41 30",
    "sg:postcode":"28300",
    "sg:province":"Madrid",
    "wof:name":"Gutierrez Paredes Yowanny Francisco",
    "wof:placetype":"venue"
},
  "geometry": {"coordinates":[-3.5948102474,40.0360984802],"type":"Point"}
}