{
  "type": "Feature",
  "properties": {
    "iso:country":"ES",
    "sg:address":"Plaz Santa Maria, S/n",
    "sg:city":"Olivenza",
    "sg:orig_category":"Museos",
    "sg:phone":"+34 924 49 02 22",
    "sg:postcode":"06100",
    "sg:province":"Badajoz",
    "wof:name":"Consorcio Museo Etnografico Extreme\u00f1o Gonzalez Santana",
    "wof:placetype":"venue"
},
  "geometry": {"coordinates":[-7.0996689796,38.6855392456],"type":"Point"}
}