{
  "type": "Feature",
  "properties": {
    "addr:full":"Calle de Velazquez, 4 Torres Cotillas Murcia 30565",
    "addr:housenumber":"4",
    "addr:postcode":"30565",
    "addr:street":"Calle De Velazquez",
    "iso:country":"ES",
    "sg:address":"Calle de Velazquez, 4",
    "sg:city":"Torres Cotillas",
    "sg:orig_category":"Muebles",
    "sg:phone":"+34 968 62 37 59",
    "sg:postcode":"30565",
    "sg:province":"Murcia",
    "wof:name":"Salda\u00f1a Martin Carlos",
    "wof:placetype":"venue"
},
  "geometry": {"coordinates":[-1.2388550043,38.0237197876],"type":"Point"}
}