{
  "type": "Feature",
  "properties": {
    "addr:full":"Estacion, S/n Vallejo Burgos 09568",
    "addr:housenumber":"s / n",
    "addr:postcode":"09568",
    "iso:country":"ES",
    "sg:address":"Estacion, S/n",
    "sg:city":"Vallejo",
    "sg:orig_category":"Negocio De Madera",
    "sg:phone":"+34 947 13 87 26",
    "sg:postcode":"09568",
    "sg:province":"Burgos",
    "wof:name":"Sainz Iturriaga Fernando",
    "wof:placetype":"venue"
},
  "geometry": {"coordinates":[-3.6394879818,43.0316963196],"type":"Point"}
}