{
  "type": "Feature",
  "properties": {
    "iso:country":"ES",
    "sg:address":"Plaz Mariana Pineda (de), 1",
    "sg:city":"Granada",
    "sg:orig_category":"Peluqueros: De Se\u00d1oras",
    "sg:phone":"+34 958 22 16 35",
    "sg:postcode":"18009",
    "sg:province":"Granada",
    "wof:name":"Macias Amador Ruben",
    "wof:placetype":"venue"
},
  "geometry": {"coordinates":[-3.5981988907,37.1751174927],"type":"Point"}
}