{
  "type": "Feature",
  "properties": {
    "iso:country":"ES",
    "sg:address":"Calle de Prado, 79",
    "sg:city":"Ibros",
    "sg:orig_category":"Empresas De Carpinter\u00cda De Madera",
    "sg:phone":"+34 953 76 70 70",
    "sg:postcode":"23450",
    "sg:province":"Ja\u00e9n",
    "wof:name":"Suarez Mendoza Rafael",
    "wof:placetype":"venue"
},
  "geometry": {"coordinates":[-3.5042850971,38.0218429565],"type":"Point"}
}