{
  "type": "Feature",
  "properties": {
    "iso:country":"ES",
    "sg:address":"Calle de Silleria, 10",
    "sg:city":"Toledo",
    "sg:orig_category":"Abogados",
    "sg:phone":"+34 925 22 10 65",
    "sg:postcode":"45001",
    "sg:province":"Toledo",
    "wof:name":"Riesco Alonso Daniel",
    "wof:placetype":"venue"
},
  "geometry": {"coordinates":[-4.0220780373,39.8598823547],"type":"Point"}
}