{
  "type": "Feature",
  "properties": {
    "addr:full":"Carretera, 1 La Ventilla C\u00f3rdoba 14112",
    "addr:housenumber":"1",
    "addr:postcode":"14112",
    "addr:street":"Carretera;La Ventilla Co\u0301Rdoba",
    "iso:country":"ES",
    "sg:address":"Carretera, 1",
    "sg:city":"La Ventilla",
    "sg:orig_category":"Aceites Y Grasas Alimentarias (fabricaci\u00d3n, Al Por Mayor)",
    "sg:phone":"+34 957 63 80 70",
    "sg:postcode":"14112",
    "sg:province":"C\u00f3rdoba",
    "wof:name":"Aceites Fuenteoliva S.l.",
    "wof:placetype":"venue"
},
  "geometry": {"coordinates":[-5.0971984863,37.7343826294],"type":"Point"}
}