{
  "type": "Feature",
  "properties": {
    "addr:full":"Socorra, 8 Fataga Las Palmas 35108",
    "addr:housenumber":"8",
    "addr:postcode":"35108",
    "addr:street":"Socorra",
    "iso:country":"ES",
    "sg:address":"Socorra, 8",
    "sg:city":"Fataga",
    "sg:orig_category":"Creaci\u00d3n De Sitios, Hosting Internet",
    "sg:phone":"+34 928 79 85 88",
    "sg:postcode":"35108",
    "sg:province":"Las Palmas",
    "sg:website":"www.sainteca.com",
    "wof:name":"Betancort Santana Narciso",
    "wof:placetype":"venue"
},
  "geometry": {"coordinates":[-15.5638666153,27.8875045776],"type":"Point"}
}