{
  "type": "Feature",
  "properties": {
    "iso:country":"ES",
    "sg:address":"Calle de Ramon Y Cajal, 46",
    "sg:city":"Cadrete",
    "sg:orig_category":"Trabajos De Soldaduras",
    "sg:phone":"+34 976 12 61 43",
    "sg:postcode":"50420",
    "sg:province":"Zaragoza",
    "wof:name":"Ebro Sol Instalaciones Y Reparaciones S.l.",
    "wof:placetype":"venue"
},
  "geometry": {"coordinates":[-0.9651759863,41.552444458],"type":"Point"}
}