{
  "type": "Feature",
  "properties": {
    "addr:full":"Avgd De L'alt Urgell, 9 Oliana Lleida 25790",
    "addr:housenumber":"9",
    "addr:postcode":"25790",
    "addr:street":"Urgell",
    "iso:country":"ES",
    "sg:address":"Avgd De L'alt Urgell, 9",
    "sg:city":"Oliana",
    "sg:orig_category":"Bancos",
    "sg:phone":"+34 973 47 06 18",
    "sg:postcode":"25790",
    "sg:province":"Lleida",
    "wof:name":"Finques Marpla",
    "wof:placetype":"venue"
},
  "geometry": {"coordinates":[1.3136110306,42.0670890808],"type":"Point"}
}