{
  "type": "Feature",
  "properties": {
    "iso:country":"ES",
    "sg:address":"Calle de Antonio Ferrandis 'chanquete', 16",
    "sg:city":"Nerja",
    "sg:orig_category":"Empresas De Carpinter\u00cda Met\u00c1lica",
    "sg:phone":"+34 952 96 61 24",
    "sg:postcode":"29780",
    "sg:province":"M\u00e1laga",
    "wof:name":"Cmc Villena S.l.",
    "wof:placetype":"venue"
},
  "geometry": {"coordinates":[-3.8853590488,36.7441635132],"type":"Point"}
}