{
  "type": "Feature",
  "properties": {
    "iso:country":"ES",
    "sg:address":"Avda Ejercito (del), 57",
    "sg:city":"Arganda",
    "sg:orig_category":"Venta, Montaje De Neum\u00c1ticos",
    "sg:phone":"+34 918 71 20 28",
    "sg:postcode":"28500",
    "sg:province":"Madrid",
    "wof:name":"Sepulveda Esteban Gregoria",
    "wof:placetype":"venue"
},
  "geometry": {"coordinates":[-3.4503650665,40.303527832],"type":"Point"}
}