{
  "type": "Feature",
  "properties": {
    "addr:full":"Calle de Florida, S/n Barca De La Florida C\u00e1diz 11570",
    "addr:postcode":"11570",
    "addr:street":"Calle De Florida S / N Barca De La;Ca\u0301Diz",
    "iso:country":"ES",
    "sg:address":"Calle de Florida, S/n",
    "sg:city":"Barca De La Florida",
    "sg:orig_category":"Patatas (al Por Mayor)",
    "sg:phone":"+34 956 39 01 08",
    "sg:postcode":"11570",
    "sg:province":"C\u00e1diz",
    "wof:name":"Expat Andalucia S.a.",
    "wof:placetype":"venue"
},
  "geometry": {"coordinates":[-5.9383087158,36.6469802856],"type":"Point"}
}