{
  "type": "Feature",
  "properties": {
    "iso:country":"ES",
    "sg:address":"Amaya-amaia, 6",
    "sg:city":"Iru\u00f1a",
    "sg:orig_category":"Zapatos (al Por Menor)",
    "sg:phone":"+34 948 22 34 57",
    "sg:postcode":"31002",
    "sg:province":"Navarra",
    "wof:name":"Clavijo Lavilla Andres Jose",
    "wof:placetype":"venue"
},
  "geometry": {"coordinates":[-1.6388920546,42.8138542175],"type":"Point"}
}