{
  "type": "Feature",
  "properties": {
    "addr:full":"Calle de Zamora (de), 6 Fuenlabrada Madrid 28941",
    "addr:housenumber":"6",
    "addr:postcode":"28941",
    "addr:street":"Calle De Zamora De",
    "iso:country":"ES",
    "sg:address":"Calle de Zamora (de), 6",
    "sg:city":"Fuenlabrada",
    "sg:orig_category":"Inmobiliaria (alquileres Por Temporada Y Temporales)",
    "sg:phone":"+34 916 15 62 18",
    "sg:postcode":"28941",
    "sg:province":"Madrid",
    "wof:name":"Encisil S.l.",
    "wof:placetype":"venue"
},
  "geometry": {"coordinates":[-3.8019299507,40.2938346863],"type":"Point"}
}