{
  "type": "Feature",
  "properties": {
    "addr:full":"Calle de San Juan De La Cruz, 11 Zaragoza Zaragoza 50006",
    "addr:housenumber":"11",
    "addr:postcode":"50006",
    "addr:street":"Calle De San Juan;La Cruz",
    "iso:country":"ES",
    "sg:address":"Calle de San Juan De La Cruz, 11",
    "sg:city":"Zaragoza",
    "sg:orig_category":"Perfumer\u00cda Y Cosm\u00c9tica (fabricaci\u00d3n, Al Por Mayor)",
    "sg:phone":"+34 976 55 04 62",
    "sg:postcode":"50006",
    "sg:province":"Zaragoza",
    "wof:name":"Lafuente Estallo Eduardo Secundino",
    "wof:placetype":"venue"
},
  "geometry": {"coordinates":[-0.8927180171,41.6414146423],"type":"Point"}
}