{
  "type": "Feature",
  "properties": {
    "iso:country":"ES",
    "sg:address":"Calle de Infanta Mercedes, 13",
    "sg:city":"Madrid",
    "sg:orig_category":"Agencias Y Asesores De Publicidad",
    "sg:phone":"+34 915 71 93 75",
    "sg:postcode":"28020",
    "sg:province":"Madrid",
    "sg:website":"www.seinpre.com",
    "wof:name":"Seguimiento De Informacion En Prensa S. L.",
    "wof:placetype":"venue"
},
  "geometry": {"coordinates":[-3.6993970871,40.453453064],"type":"Point"}
}