{
  "type": "Feature",
  "properties": {
    "addr:full":"Ctra Lora Rio, Km. 0132,0 Algaba Sevilla 41980",
    "addr:postcode":"41980",
    "addr:street":"Ctra Lora Rio Km. 0132,0",
    "iso:country":"ES",
    "sg:address":"Ctra Lora Rio, Km. 0132,0",
    "sg:city":"Algaba",
    "sg:orig_category":"Molduras, Junquillos, Listones Y Molduras Perforadas",
    "sg:phone":"+34 955 78 77 51",
    "sg:postcode":"41980",
    "sg:province":"Sevilla",
    "wof:name":"Perez Reyes Fernando",
    "wof:placetype":"venue"
},
  "geometry": {"coordinates":[-6.0153942108,37.4607162476],"type":"Point"}
}