{
  "type": "Feature",
  "properties": {
    "iso:country":"ES",
    "sg:address":"Avda Diputacion (de La), S/n",
    "sg:city":"Chiclana De La Frontera",
    "sg:orig_category":"Televisi\u00d3n, V\u00cddeo: Aparatos Y Accesorios (venta)",
    "sg:phone":"+34 956 53 41 76",
    "sg:postcode":"11130",
    "sg:province":"C\u00e1diz",
    "wof:name":"Jaime Zafra S.l.",
    "wof:placetype":"venue"
},
  "geometry": {"coordinates":[-6.1544790268,36.422618866],"type":"Point"}
}