{
  "type": "Feature",
  "properties": {
    "addr:full":"Av Peguera, 20 Peguera Islas Baleares 07160",
    "addr:housenumber":"20",
    "addr:postcode":"07160",
    "addr:street":"Av Peguera",
    "iso:country":"ES",
    "sg:address":"Av Peguera, 20",
    "sg:city":"Peguera",
    "sg:orig_category":"Albergues",
    "sg:phone":"+34 971 68 70 21",
    "sg:postcode":"07160",
    "sg:province":"Islas Baleares",
    "wof:name":"Bruc Regals I Decoracio S.l.",
    "wof:placetype":"venue"
},
  "geometry": {"coordinates":[2.4432940483,39.5372657776],"type":"Point"}
}