{
  "type": "Feature",
  "properties": {
    "iso:country":"ES",
    "sg:address":"Rier Blanca, 137",
    "sg:city":"Barcelona",
    "sg:orig_category":"Inform\u00c1tica (estudios, Servicios, Asesor\u00cda, Formaci\u00d3n)",
    "sg:phone":"+34 934 31 52 65",
    "sg:postcode":"08028",
    "sg:province":"Barcelona",
    "sg:website":"www.c2puntos.com",
    "wof:name":"C Informatica S.l.",
    "wof:placetype":"venue"
},
  "geometry": {"coordinates":[2.1289720535,41.3710136414],"type":"Point"}
}