{
  "type": "Feature",
  "properties": {
    "addr:full":"Calle de Maestro Serrano, 8 Algeciras C\u00e1diz 11204",
    "addr:housenumber":"8;ca\u0301diz",
    "addr:postcode":"11204",
    "addr:street":"Calle De Maestro Serrano",
    "iso:country":"ES",
    "sg:address":"Calle de Maestro Serrano, 8",
    "sg:city":"Algeciras",
    "sg:orig_category":"Empresas De Carpinter\u00cda",
    "sg:phone":"+34 956 65 09 51",
    "sg:postcode":"11204",
    "sg:province":"C\u00e1diz",
    "wof:name":"Martinez Y Jurado S.l",
    "wof:placetype":"venue"
},
  "geometry": {"coordinates":[-5.4486598969,36.1412773132],"type":"Point"}
}