{
  "type": "Feature",
  "properties": {
    "iso:country":"ES",
    "sg:address":"Calle de Profesor Waksman, 8",
    "sg:city":"Madrid",
    "sg:orig_category":"M\u00c9dicos: Estomatolog\u00cda",
    "sg:phone":"+34 914 57 00 62",
    "sg:postcode":"28036",
    "sg:province":"Madrid",
    "wof:name":"Itza Santos Fernando",
    "wof:placetype":"venue"
},
  "geometry": {"coordinates":[-3.6886560917,40.4559135437],"type":"Point"}
}