{
  "type": "Feature",
  "properties": {
    "addr:full":"Calle de Pintor Velazquez (del), 33 Mostoles Madrid 28933",
    "addr:housenumber":"33",
    "addr:postcode":"28933",
    "addr:street":"Calle De Pintor Velazquez Del",
    "iso:country":"ES",
    "sg:address":"Calle de Pintor Velazquez (del), 33",
    "sg:city":"Mostoles",
    "sg:orig_category":"Electricidad: Instaladores",
    "sg:phone":"+34 916 17 05 46",
    "sg:postcode":"28933",
    "sg:province":"Madrid",
    "wof:name":"Juan Vigo S.l.",
    "wof:placetype":"venue"
},
  "geometry": {"coordinates":[-3.8757929802,40.3301925659],"type":"Point"}
}