{
  "type": "Feature",
  "properties": {
    "iso:country":"ES",
    "sg:address":"Plaz Alcalde Horacio Hermoso, 6",
    "sg:city":"Sevilla",
    "sg:orig_category":"Asociaciones Y Clubs Deportivos",
    "sg:phone":"+34 954 61 85 99",
    "sg:postcode":"41013",
    "sg:province":"Sevilla",
    "wof:name":"Pe\u00f1a Cultural Sevillista Nuestra Se\u00f1ora De Las Mercedes",
    "wof:placetype":"venue"
},
  "geometry": {"coordinates":[-5.9757490158,37.3708114624],"type":"Point"}
}