{
  "type": "Feature",
  "properties": {
    "addr:full":"Carrer de Llacuna, 104 Barcelona Barcelona 08018",
    "addr:housenumber":"104",
    "addr:postcode":"08018",
    "addr:street":"Carrer De Llacuna",
    "iso:country":"ES",
    "sg:address":"Carrer de Llacuna, 104",
    "sg:city":"Barcelona",
    "sg:orig_category":"Mec\u00c1nico Del Autom\u00d3vil",
    "sg:phone":"+34 933 09 26 18",
    "sg:postcode":"08018",
    "sg:province":"Barcelona",
    "wof:name":"Riera Rovira Luis",
    "wof:placetype":"venue"
},
  "geometry": {"coordinates":[2.1963970661,41.4032516479],"type":"Point"}
}