{
  "type": "Feature",
  "properties": {
    "iso:country":"ES",
    "sg:address":"Ezozia, Barrio, 8",
    "sg:city":"Soraluze-placencia Armas",
    "sg:orig_category":"Sindicatos De Trabajadores",
    "sg:phone":"+34 943 75 22 04",
    "sg:postcode":"20590",
    "sg:province":"Guip\u00f9zcoa",
    "wof:name":"Langile Abertzaleen Batzordeak",
    "wof:placetype":"venue"
},
  "geometry": {"coordinates":[-2.419989109,43.1778755188],"type":"Point"}
}