{
  "type": "Feature",
  "properties": {
    "iso:country":"ES",
    "sg:address":"Calle de Dolores, 11",
    "sg:city":"Cox",
    "sg:orig_category":"Muebles, Minoristas",
    "sg:phone":"+34 966 75 02 61",
    "sg:postcode":"03350",
    "sg:province":"Alicante",
    "wof:name":"Molera Manresa Jose",
    "wof:placetype":"venue"
},
  "geometry": {"coordinates":[-0.8906695247,38.1464309692],"type":"Point"}
}