{
  "type": "Feature",
  "properties": {
    "iso:country":"ES",
    "sg:address":"Calle de Arrayan, 28",
    "sg:city":"Santa Fe",
    "sg:orig_category":"Abogados",
    "sg:phone":"+34 958 51 01 09",
    "sg:postcode":"18320",
    "sg:province":"Granada",
    "wof:name":"Casas Martinez Pilar",
    "wof:placetype":"venue"
},
  "geometry": {"coordinates":[-3.7217760086,37.1918716431],"type":"Point"}
}