{
  "type": "Feature",
  "properties": {
    "iso:country":"ES",
    "sg:address":"Sierra De Telar, 40",
    "sg:city":"Viator",
    "sg:orig_category":"Electricidad, Electr\u00d3nica: Material Y Suministros (al Por Mayor)",
    "sg:phone":"+34 950 30 61 94",
    "sg:postcode":"04240",
    "sg:province":"Almer\u00eda",
    "sg:website":"www.cirsa.com",
    "wof:name":"Juegomatic S. A.",
    "wof:placetype":"venue"
},
  "geometry": {"coordinates":[-2.4208340645,36.8807601929],"type":"Point"}
}