{
  "type": "Feature",
  "properties": {
    "iso:country":"ES",
    "sg:address":"Calle de Luis Santangel, 30",
    "sg:city":"Valencia",
    "sg:orig_category":"Caf\u00c9s Teatro",
    "sg:phone":"+34 963 73 50 56",
    "sg:postcode":"46005",
    "sg:province":"Valencia",
    "wof:name":"Noche De Ronda S.l.",
    "wof:placetype":"venue"
},
  "geometry": {"coordinates":[-0.3664386868,39.4610748291],"type":"Point"}
}