{
  "type": "Feature",
  "properties": {
    "iso:country":"ES",
    "sg:address":"Calle de Alfonso De Castro, 6",
    "sg:city":"Rute",
    "sg:orig_category":"Agencias Y Asesores De Publicidad",
    "sg:phone":"+34 957 53 30 02",
    "sg:postcode":"14960",
    "sg:province":"C\u00f3rdoba",
    "wof:name":"Gines Ortu\u00f1o Francisco",
    "wof:placetype":"venue"
},
  "geometry": {"coordinates":[-4.3707170486,37.3254241943],"type":"Point"}
}