{
  "type": "Feature",
  "properties": {
    "iso:country":"ES",
    "sg:address":"Calle de Granjilla, 7",
    "sg:city":"Madrid",
    "sg:orig_category":"Empresarios Y Productoras De Espect\u00c1culos",
    "sg:phone":"+34 913 55 11 57",
    "sg:postcode":"28028",
    "sg:province":"Madrid",
    "wof:name":"Management Producciones Midu S.l.",
    "wof:placetype":"venue"
},
  "geometry": {"coordinates":[-3.6732499599,40.4376831055],"type":"Point"}
}