{
  "type": "Feature",
  "properties": {
    "iso:country":"ES",
    "sg:address":"Calle de Serrano, 218",
    "sg:city":"Madrid",
    "sg:orig_category":"Importaci\u00d3n",
    "sg:phone":"+34 915 63 67 93",
    "sg:postcode":"28016",
    "sg:province":"Madrid",
    "wof:name":"Merilainen  Timo",
    "wof:placetype":"venue"
},
  "geometry": {"coordinates":[-3.6811766624,40.4520149231],"type":"Point"}
}