{
  "type": "Feature",
  "properties": {
    "addr:full":"Barrio De Las Escuelas, S/n Torres Cantabria 39300",
    "addr:housenumber":"s / n",
    "addr:postcode":"39300",
    "addr:street":"Barrio;Las Escuelas",
    "iso:country":"ES",
    "sg:address":"Barrio De Las Escuelas, S/n",
    "sg:city":"Torres",
    "sg:orig_category":"Iglesia Cat\u00d3lica",
    "sg:phone":"+34 942 80 10 27",
    "sg:postcode":"39300",
    "sg:province":"Cantabria",
    "wof:name":"Parroquia De Torres",
    "wof:placetype":"venue"
},
  "geometry": {"coordinates":[-4.0520391464,43.34897995],"type":"Point"}
}