{
  "type": "Feature",
  "properties": {
    "addr:full":"Avda Calasancio (del), 22 Cordoba C\u00f3rdoba 14012",
    "addr:housenumber":"22",
    "addr:postcode":"14012",
    "addr:street":"Avda Calasancio Del;Co\u0301Rdoba",
    "iso:country":"ES",
    "sg:address":"Avda Calasancio (del), 22",
    "sg:city":"Cordoba",
    "sg:orig_category":"Ingeniero",
    "sg:phone":"+34 957 76 12 13",
    "sg:postcode":"14012",
    "sg:province":"C\u00f3rdoba",
    "sg:website":"www.ecointegral.com",
    "wof:name":"Ecointegral Ingenieria S.l.",
    "wof:placetype":"venue"
},
  "geometry": {"coordinates":[-4.7880530357,37.9061164856],"type":"Point"}
}