{
  "type": "Feature",
  "properties": {
    "iso:country":"ES",
    "sg:address":"Plaz Mayor, 16",
    "sg:city":"Briviesca",
    "sg:orig_category":"Institutos De Belleza",
    "sg:phone":"+34 947 59 14 99",
    "sg:postcode":"09240",
    "sg:province":"Burgos",
    "wof:name":"Val Rasines Mari Angeles Del",
    "wof:placetype":"venue"
},
  "geometry": {"coordinates":[-3.3246610165,42.5496292114],"type":"Point"}
}