{
  "type": "Feature",
  "properties": {
    "addr:full":"Carrer de Pinar Del Rio, 39 Barcelona Barcelona 08027",
    "addr:housenumber":"39",
    "addr:postcode":"08027",
    "addr:street":"Carrer De Pinar Del Rio",
    "iso:country":"ES",
    "sg:address":"Carrer de Pinar Del Rio, 39",
    "sg:city":"Barcelona",
    "sg:orig_category":"Empresas De Demolici\u00d3n",
    "sg:phone":"+34 934 08 35 07",
    "sg:postcode":"08027",
    "sg:province":"Barcelona",
    "wof:name":"Demoliciones Tarragona",
    "wof:placetype":"venue"
},
  "geometry": {"coordinates":[2.1810050011,41.4224395752],"type":"Point"}
}