{
  "type": "Feature",
  "properties": {
    "iso:country":"ES",
    "sg:address":"Calle de Antonio Pascual, 42",
    "sg:city":"Aljorra",
    "sg:orig_category":"Transportes Por Carretera: Lotes Completos, Mercanc\u00cdas Diversas",
    "sg:phone":"+34 968 55 81 59",
    "sg:postcode":"30390",
    "sg:province":"Murcia",
    "wof:name":"Mateo Requena Francisco Javier",
    "wof:placetype":"venue"
},
  "geometry": {"coordinates":[-1.0704388618,37.6906318665],"type":"Point"}
}