{
  "type": "Feature",
  "properties": {
    "addr:full":"Ctra Prejano, S/n Arnedo La Rioja 26580",
    "addr:housenumber":"s / n",
    "addr:postcode":"26580",
    "addr:street":"Ctra Prejano;Rioja",
    "iso:country":"ES",
    "sg:address":"Ctra Prejano, S/n",
    "sg:city":"Arnedo",
    "sg:orig_category":"Zapater\u00cdas",
    "sg:phone":"+34 941 38 20 45",
    "sg:postcode":"26580",
    "sg:province":"La Rioja",
    "wof:name":"Cordon Muro Jose Ramon",
    "wof:placetype":"venue"
},
  "geometry": {"coordinates":[-2.098361969,42.2173881531],"type":"Point"}
}