{
  "type": "Feature",
  "properties": {
    "iso:country":"ES",
    "sg:address":"Carrer de Francesc Pi I Margall, 126",
    "sg:city":"S. Boi Llobregat",
    "sg:orig_category":"Doctores En Medicina",
    "sg:phone":"+34 936 40 18 18",
    "sg:postcode":"08830",
    "sg:province":"Barcelona",
    "wof:name":"Llobregat Informedic S.l.",
    "wof:placetype":"venue"
},
  "geometry": {"coordinates":[2.0338830948,41.3470153809],"type":"Point"}
}