{
  "type": "Feature",
  "properties": {
    "addr:full":"Barr Lantzarte Auzoa, 16 Berango Vizcaya 48640",
    "addr:housenumber":"16",
    "addr:postcode":"48640",
    "addr:street":"Lantzarte Auzoa",
    "iso:country":"ES",
    "sg:address":"Barr Lantzarte Auzoa, 16",
    "sg:city":"Berango",
    "sg:orig_category":"Molduras, Junquillos, Listones Y Molduras Perforadas",
    "sg:phone":"+34 946 68 11 26",
    "sg:postcode":"48640",
    "sg:province":"Vizcaya",
    "wof:name":"Hernandez Garcia Josune",
    "wof:placetype":"venue"
},
  "geometry": {"coordinates":[-2.9955940247,43.3641815186],"type":"Point"}
}