{
  "type": "Feature",
  "properties": {
    "addr:full":"Poligono Jessica, 5 Gerindote Toledo 45518",
    "addr:housenumber":"5",
    "addr:postcode":"45518",
    "addr:street":"Poligono Jessica",
    "iso:country":"ES",
    "sg:address":"Poligono Jessica, 5",
    "sg:city":"Gerindote",
    "sg:orig_category":"Ebanister\u00cda",
    "sg:phone":"+34 925 76 07 47",
    "sg:postcode":"45518",
    "sg:province":"Toledo",
    "wof:name":"Torneados Torrijos S.l.l.",
    "wof:placetype":"venue"
},
  "geometry": {"coordinates":[-4.3021659851,39.9683151245],"type":"Point"}
}