{
  "type": "Feature",
  "properties": {
    "iso:country":"ES",
    "sg:address":"Calle de Ministro Luis Mayans, 8",
    "sg:city":"Valencia",
    "sg:orig_category":"Maquinaria Para Industrias Diversas",
    "sg:phone":"+34 963 66 94 55",
    "sg:postcode":"46009",
    "sg:province":"Valencia",
    "wof:name":"Perea Juan Jesus",
    "wof:placetype":"venue"
},
  "geometry": {"coordinates":[-0.3721800148,39.484752655],"type":"Point"}
}