{
  "type": "Feature",
  "properties": {
    "addr:full":"Calle de Cristo De Los Milagros, 12 Salamanca Salamanca 37001",
    "addr:housenumber":"12",
    "addr:postcode":"37001",
    "addr:street":"Calle De Cristo De Los Milagros",
    "iso:country":"ES",
    "sg:address":"Calle de Cristo De Los Milagros, 12",
    "sg:city":"Salamanca",
    "sg:orig_category":"Zapatos (al Por Menor)",
    "sg:phone":"+34 923 21 94 06",
    "sg:postcode":"37001",
    "sg:province":"Salamanca",
    "wof:name":"Sanchez Mendez Antonio",
    "wof:placetype":"venue"
},
  "geometry": {"coordinates":[-5.6596097946,40.9685058594],"type":"Point"}
}