{
  "type": "Feature",
  "properties": {
    "iso:country":"ES",
    "sg:address":"Calle de Peque, 6",
    "sg:city":"Molezuelas Carballeda",
    "sg:orig_category":"Cr\u00cda De Animales",
    "sg:phone":"+34 980 64 29 95",
    "sg:postcode":"49327",
    "sg:province":"Zamora",
    "wof:name":"Lopez Martinez Pedro",
    "wof:placetype":"venue"
},
  "geometry": {"coordinates":[-6.1858825684,42.0820198059],"type":"Point"}
}