{
  "type": "Feature",
  "properties": {
    "iso:country":"ES",
    "sg:address":"Calle de Leon Y Castillo, 132",
    "sg:city":"Palmas De Gran Canaria",
    "sg:orig_category":"Electricidad, Electr\u00d3nica: Suministros (al Por Menor)",
    "sg:phone":"+34 928 24 26 19",
    "sg:postcode":"35004",
    "sg:province":"Las Palmas",
    "wof:name":"Suarez Betts Carlos",
    "wof:placetype":"venue"
},
  "geometry": {"coordinates":[-15.4221534729,28.1161556244],"type":"Point"}
}