{
  "type": "Feature",
  "properties": {
    "iso:country":"ES",
    "sg:address":"Carr General Brito, 5",
    "sg:city":"Lleida",
    "sg:orig_category":"Reposter\u00cdas",
    "sg:phone":"+34 973 23 77 28",
    "sg:postcode":"25007",
    "sg:province":"Lleida",
    "wof:name":"Casals Ribalta Vicente",
    "wof:placetype":"venue"
},
  "geometry": {"coordinates":[0.6320359707,41.6184005737],"type":"Point"}
}