{
  "type": "Feature",
  "properties": {
    "addr:full":"Calle de San Francisco, 6 Castellon Castell\u00f3n 12002",
    "addr:housenumber":"6",
    "addr:postcode":"12002",
    "addr:street":"Calle De San Francisco;Castello\u0301N",
    "iso:country":"ES",
    "sg:address":"Calle de San Francisco, 6",
    "sg:city":"Castellon",
    "sg:orig_category":"Zapatos (al Por Menor)",
    "sg:phone":"+34 964 24 27 39",
    "sg:postcode":"12002",
    "sg:province":"Castell\u00f3n",
    "wof:name":"Arias Vizcaya Jose",
    "wof:placetype":"venue"
},
  "geometry": {"coordinates":[-0.0413269997,39.9841499329],"type":"Point"}
}