{
  "type": "Feature",
  "properties": {
    "iso:country":"ES",
    "sg:address":"Avda Extremadura, 145",
    "sg:city":"Santa Marta",
    "sg:orig_category":"Electrodom\u00c9sticos (al Por Menor)",
    "sg:phone":"+34 924 69 00 19",
    "sg:postcode":"06150",
    "sg:province":"Badajoz",
    "wof:name":"Corrales Garcia Justo",
    "wof:placetype":"venue"
},
  "geometry": {"coordinates":[-6.6212978363,38.6202507019],"type":"Point"}
}