{
  "type": "Feature",
  "properties": {
    "iso:country":"ES",
    "sg:address":"Carrer de Marques De Campo, 43",
    "sg:city":"Denia",
    "sg:orig_category":"Maquinaria Para Industrias Diversas",
    "sg:phone":"+34 965 78 93 13",
    "sg:postcode":"03700",
    "sg:province":"Alicante",
    "wof:name":"Borrell Collado Jose",
    "wof:placetype":"venue"
},
  "geometry": {"coordinates":[0.1107579991,38.841178894],"type":"Point"}
}