{
  "type": "Feature",
  "properties": {
    "iso:country":"ES",
    "sg:address":"Sect Islas, 3",
    "sg:city":"Tres Cantos",
    "sg:orig_category":"Contenedores Para Transporte De Mercanc\u00cdas",
    "sg:phone":"+34 918 03 83 63",
    "sg:postcode":"28760",
    "sg:province":"Madrid",
    "sg:website":"www.j-pedraza.com",
    "wof:name":"Transportes Y Contenedores J.pedraza S.l.",
    "wof:placetype":"venue"
},
  "geometry": {"coordinates":[-3.7012178898,40.5929832458],"type":"Point"}
}