{
  "type": "Feature",
  "properties": {
    "addr:full":"Calle de Carranza, 25 Madrid Madrid 28004",
    "addr:housenumber":"25",
    "addr:postcode":"madrid;28004",
    "addr:street":"Calle De Carranza",
    "iso:country":"ES",
    "sg:address":"Calle de Carranza, 25",
    "sg:city":"Madrid",
    "sg:orig_category":"Agencias De Viajes",
    "sg:phone":"+34 914 45 40 06",
    "sg:postcode":"28004",
    "sg:province":"Madrid",
    "wof:name":"Viajes Hanshin S.a.",
    "wof:placetype":"venue"
},
  "geometry": {"coordinates":[-3.7049610615,40.4293327332],"type":"Point"}
}