{
  "type": "Feature",
  "properties": {
    "iso:country":"ES",
    "sg:address":"Calle de San Agustin, 6",
    "sg:city":"Jerez De La Frontera",
    "sg:orig_category":"Electricidad: Equipos Industriales, Componentes (fabricaci\u00d3n)",
    "sg:phone":"+34 956 32 50 13",
    "sg:postcode":"11401",
    "sg:province":"C\u00e1diz",
    "wof:name":"Triano Sanchez Fernando",
    "wof:placetype":"venue"
},
  "geometry": {"coordinates":[-5.936852932,36.6455764771],"type":"Point"}
}