{
  "type": "Feature",
  "properties": {
    "addr:full":"Calle de Colon, 14 Segorbe Castell\u00f3n 12400",
    "addr:housenumber":"14",
    "addr:postcode":"12400",
    "addr:street":"Calle De Colon",
    "iso:country":"ES",
    "sg:address":"Calle de Colon, 14",
    "sg:city":"Segorbe",
    "sg:orig_category":"Fabricaci\u00d3n De Art\u00cdculos Para Papeler\u00cdas",
    "sg:phone":"+34 964 71 10 70",
    "sg:postcode":"12400",
    "sg:province":"Castell\u00f3n",
    "wof:name":"Fleta Gil Jose Manuel",
    "wof:placetype":"venue"
},
  "geometry": {"coordinates":[-0.4877935946,39.8518180847],"type":"Point"}
}