{
  "type": "Feature",
  "properties": {
    "iso:country":"ES",
    "sg:address":"Pg Riera (la), 42",
    "sg:city":"Cardedeu",
    "sg:orig_category":"Aparatos, Sistemas De Tele",
    "sg:phone":"+34 938 71 14 98",
    "sg:postcode":"08440",
    "sg:province":"Barcelona",
    "wof:name":"Bcn Irealb Serveis S.l.",
    "wof:placetype":"venue"
},
  "geometry": {"coordinates":[2.352864027,41.6377410889],"type":"Point"}
}