{
  "type": "Feature",
  "properties": {
    "addr:full":"Errekatxo Emparantza, 6 Astigarraga Guip\u00f9zcoa 20115",
    "addr:housenumber":"6",
    "addr:postcode":"20115",
    "addr:street":"Emparantza;Guipu\u0300Zcoa",
    "iso:country":"ES",
    "sg:address":"Errekatxo Emparantza, 6",
    "sg:city":"Astigarraga",
    "sg:orig_category":"Plomeros",
    "sg:phone":"+34 943 55 62 66",
    "sg:postcode":"20115",
    "sg:province":"Guip\u00f9zcoa",
    "wof:name":"Ivan Ortiz De Guinea Garcia",
    "wof:placetype":"venue"
},
  "geometry": {"coordinates":[-1.9507540464,43.2802085876],"type":"Point"}
}