{
  "type": "Feature",
  "properties": {
    "addr:full":"Isaac Albeniz, 82 Tarragona Tarragona 43007",
    "addr:housenumber":"82",
    "addr:postcode":"43007",
    "addr:street":"Isaac Albeniz",
    "iso:country":"ES",
    "sg:address":"Isaac Albeniz, 82",
    "sg:city":"Tarragona",
    "sg:orig_category":"Empresas Portuarias",
    "sg:phone":"+34 977 20 85 94",
    "sg:postcode":"43007",
    "sg:province":"Tarragona",
    "wof:name":"Euromarco S.l.",
    "wof:placetype":"venue"
},
  "geometry": {"coordinates":[1.3018540144,41.1378898621],"type":"Point"}
}