{
  "type": "Feature",
  "properties": {
    "addr:full":"Exconvento, 2 Monovar Alicante 03640",
    "addr:housenumber":"2",
    "addr:postcode":"03640",
    "addr:street":"Exconvento;Alicante",
    "iso:country":"ES",
    "sg:address":"Exconvento, 2",
    "sg:city":"Monovar",
    "sg:orig_category":"Mercados De Productos Alimenticios",
    "sg:phone":"+34 966 96 08 72",
    "sg:postcode":"03640",
    "sg:province":"Alicante",
    "wof:name":"Ayuntamiento De Monovar",
    "wof:placetype":"venue"
},
  "geometry": {"coordinates":[-0.8427320123,38.4374084473],"type":"Point"}
}