{
  "type": "Feature",
  "properties": {
    "addr:full":"Carrer de Comte D'urgell, 268 Barcelona Barcelona 08036",
    "addr:housenumber":"268",
    "addr:postcode":"08036",
    "addr:street":"Carrer De Comte D'Urgell",
    "iso:country":"ES",
    "sg:address":"Carrer de Comte D'urgell, 268",
    "sg:city":"Barcelona",
    "sg:orig_category":"Ingenier\u00cda, Centros De Estudios (diversos)",
    "sg:phone":"+34 933 21 12 90",
    "sg:postcode":"08036",
    "sg:province":"Barcelona",
    "wof:name":"Dalmau Porta Javier",
    "wof:placetype":"venue"
},
  "geometry": {"coordinates":[2.1467483044,41.3910675049],"type":"Point"}
}