{
  "type": "Feature",
  "properties": {
    "addr:full":"Pol Ind Sector Iv, 7 Villanueva Gallego Zaragoza 50830",
    "addr:postcode":"50830",
    "iso:country":"ES",
    "sg:address":"Pol Ind Sector Iv, 7",
    "sg:city":"Villanueva Gallego",
    "sg:orig_category":"Chapister\u00cda",
    "sg:phone":"+34 976 18 00 04",
    "sg:postcode":"50830",
    "sg:province":"Zaragoza",
    "wof:name":"Chapas Parga S.l.",
    "wof:placetype":"venue"
},
  "geometry": {"coordinates":[-0.8222020268,41.7705192566],"type":"Point"}
}