{
  "type": "Feature",
  "properties": {
    "addr:full":"Calle de Sagasta, 10 Linares Ja\u00e9n 23700",
    "addr:housenumber":"10",
    "addr:postcode":"23700",
    "addr:street":"Calle De Sagasta;Jae\u0301N",
    "iso:country":"ES",
    "sg:address":"Calle de Sagasta, 10",
    "sg:city":"Linares",
    "sg:orig_category":"Bisuter\u00cda, Joyer\u00cda, Relojer\u00cda (al Por Menor)",
    "sg:phone":"+34 953 60 71 39",
    "sg:postcode":"23700",
    "sg:province":"Ja\u00e9n",
    "wof:name":"Chamorro Perez Isaac",
    "wof:placetype":"venue"
},
  "geometry": {"coordinates":[-3.6329410076,38.0953330994],"type":"Point"}
}