{
  "type": "Feature",
  "properties": {
    "iso:country":"ES",
    "sg:address":"Calle de Luis Taboada, 55",
    "sg:city":"Malaga",
    "sg:orig_category":"Arquitectos",
    "sg:phone":"+34 952 29 26 20",
    "sg:postcode":"29017",
    "sg:province":"M\u00e1laga",
    "wof:name":"Tosina Tosina Antonio",
    "wof:placetype":"venue"
},
  "geometry": {"coordinates":[-4.3609280586,36.7255249023],"type":"Point"}
}