{
  "type": "Feature",
  "properties": {
    "addr:full":"Calle de Sederia, S/n Poligono Industrial El Palmar C\u00e1diz 11500",
    "addr:housenumber":"s / n",
    "addr:postcode":"11500",
    "addr:street":"Calle De Sederia;Poligono Industrial",
    "iso:country":"ES",
    "sg:address":"Calle de Sederia, S/n",
    "sg:city":"Poligono Industrial El Palmar",
    "sg:orig_category":"Deportes Y Ocio: Art\u00cdculos Y Ropas (al Por Menor Y Accesorios)",
    "sg:phone":"+34 956 87 04 57",
    "sg:postcode":"11500",
    "sg:province":"C\u00e1diz",
    "sg:website":"www.golftaller.com",
    "wof:name":"Taller De Golf Cuarto De Palos",
    "wof:placetype":"venue"
},
  "geometry": {"coordinates":[-6.2197542191,36.6056632996],"type":"Point"}
}