{
  "type": "Feature",
  "properties": {
    "iso:country":"ES",
    "sg:address":"Calle de Castrobarto, S/n",
    "sg:city":"Madrid",
    "sg:orig_category":"Alquiler De Veh\u00cdculos: Turismos Y Utilitarios",
    "sg:phone":"+34 913 29 16 09",
    "sg:postcode":"28042",
    "sg:province":"Madrid",
    "sg:website":"www.atesa.es",
    "wof:name":"Atesa",
    "wof:placetype":"venue"
},
  "geometry": {"coordinates":[-3.5814557076,40.4519920349],"type":"Point"}
}