{
  "type": "Feature",
  "properties": {
    "iso:country":"ES",
    "sg:address":"Pase Fernando El Catolico, 19",
    "sg:city":"Zaragoza",
    "sg:orig_category":"Abogados",
    "sg:phone":"+34 976 35 85 81",
    "sg:postcode":"50006",
    "sg:province":"Zaragoza",
    "wof:name":"Novel Peruga Jose Maria",
    "wof:placetype":"venue"
},
  "geometry": {"coordinates":[-0.8929960132,41.6425743103],"type":"Point"}
}