{
  "type": "Feature",
  "properties": {
    "addr:full":"Calle de Manuel Junquera, 5 Gijon Asturias 33204",
    "addr:housenumber":"5",
    "addr:postcode":"33204",
    "addr:street":"Calle De Manuel Junquera",
    "iso:country":"ES",
    "sg:address":"Calle de Manuel Junquera, 5",
    "sg:city":"Gijon",
    "sg:orig_category":"Peluqueros: De Se\u00d1oras",
    "sg:phone":"+34 985 33 02 27",
    "sg:postcode":"33204",
    "sg:province":"Asturias",
    "wof:name":"Llera Estevez Maria Del Carmen",
    "wof:placetype":"venue"
},
  "geometry": {"coordinates":[-5.6541671753,43.5303573608],"type":"Point"}
}