{
  "type": "Feature",
  "properties": {
    "iso:country":"ES",
    "sg:address":"Calle de Telleria, 7",
    "sg:city":"Barakaldo",
    "sg:orig_category":"Librer\u00cdas",
    "sg:phone":"+34 944 99 02 15",
    "sg:postcode":"48903",
    "sg:province":"Vizcaya",
    "wof:name":"Limbreria Pampin",
    "wof:placetype":"venue"
},
  "geometry": {"coordinates":[-2.9821815491,43.282749176],"type":"Point"}
}