{
  "type": "Feature",
  "properties": {
    "addr:full":"Avgd Santa Margalida, 43 Muro Islas Baleares 07440",
    "addr:housenumber":"43",
    "addr:postcode":"07440",
    "addr:street":"Margalida",
    "iso:country":"ES",
    "sg:address":"Avgd Santa Margalida, 43",
    "sg:city":"Muro",
    "sg:orig_category":"Caf\u00c9s, Bares, Cervecer\u00cdas",
    "sg:phone":"+34 971 53 74 71",
    "sg:postcode":"07440",
    "sg:province":"Islas Baleares",
    "wof:name":"Le Cheval C.b.",
    "wof:placetype":"venue"
},
  "geometry": {"coordinates":[3.0596179962,39.7293052673],"type":"Point"}
}