{
  "type": "Feature",
  "properties": {
    "addr:full":"Rio Ega, 34 Iru\u00f1a Navarra 31005",
    "addr:housenumber":"34",
    "addr:postcode":"31005",
    "addr:street":"Rio Ega",
    "iso:country":"ES",
    "sg:address":"Rio Ega, 34",
    "sg:city":"Iru\u00f1a",
    "sg:orig_category":"Pintura, Barniz, Productos Asimilables (fabricaci\u00d3n, Al Por Mayor)",
    "sg:phone":"+34 948 23 85 52",
    "sg:postcode":"31005",
    "sg:province":"Navarra",
    "wof:name":"Navarro Iribarren Jose Luis",
    "wof:placetype":"venue"
},
  "geometry": {"coordinates":[-1.6462939978,42.8044929504],"type":"Point"}
}