{
  "type": "Feature",
  "properties": {
    "iso:country":"ES",
    "sg:address":"Calle de Francisco A\u00d1on, 39",
    "sg:city":"Coru\u00d1a",
    "sg:orig_category":"Fabricaci\u00d3n, Importaci\u00d3n, Venta De Material De Telefon\u00cda, Peritelefon\u00cda",
    "sg:phone":"+34 981 25 25 50",
    "sg:postcode":"15010",
    "sg:province":"La Coru\u00f1a",
    "wof:name":"Golmar Sistemas De Comunicacion S. A.",
    "wof:placetype":"venue"
},
  "geometry": {"coordinates":[-8.4193964005,43.3645210266],"type":"Point"}
}