{
  "type": "Feature",
  "properties": {
    "addr:full":"Avda Maisonnave, 45 Alacant Alicante 03003",
    "addr:housenumber":"45",
    "addr:postcode":"03003",
    "addr:street":"Avda Maisonnave",
    "iso:country":"ES",
    "sg:address":"Avda Maisonnave, 45",
    "sg:city":"Alacant",
    "sg:orig_category":"Fabricaci\u00d3n, Venta De Productos Base Farmac\u00c9uticos",
    "sg:phone":"+34 965 92 96 06",
    "sg:postcode":"03003",
    "sg:province":"Alicante",
    "wof:name":"Orts Llinares Maria De Los Angeles",
    "wof:placetype":"venue"
},
  "geometry": {"coordinates":[-0.4925270081,38.3432731628],"type":"Point"}
}