{
  "type": "Feature",
  "properties": {
    "addr:full":"Avgd Germanies, De Les, 19 Casco Urbano Valencia 46760",
    "addr:postcode":"46760",
    "addr:street":"Avgd",
    "iso:country":"ES",
    "sg:address":"Avgd Germanies, De Les, 19",
    "sg:city":"Casco Urbano",
    "sg:orig_category":"\u00d3ptica: Instrumentos (fabricaci\u00d3n)",
    "sg:phone":"+34 962 83 64 80",
    "sg:postcode":"46760",
    "sg:province":"Valencia",
    "wof:name":"Vercher Clemente Jose Luis",
    "wof:placetype":"venue"
},
  "geometry": {"coordinates":[-0.2594090104,39.0749702454],"type":"Point"}
}