{
  "type": "Feature",
  "properties": {
    "addr:full":"Calle de Margaritas, 2 Madrid Madrid 28039",
    "addr:housenumber":"2",
    "addr:postcode":"28039",
    "addr:street":"Calle De Margaritas",
    "iso:country":"ES",
    "sg:address":"Calle de Margaritas, 2",
    "sg:city":"Madrid",
    "sg:orig_category":"Cl\u00cdnicas M\u00c9dicas",
    "sg:phone":"+34 914 59 19 16",
    "sg:postcode":"28039",
    "sg:province":"Madrid",
    "wof:name":"Policlinica San Fermin S.l.",
    "wof:placetype":"venue"
},
  "geometry": {"coordinates":[-3.7063150406,40.4567909241],"type":"Point"}
}