{
  "type": "Feature",
  "properties": {
    "addr:full":"Calle de Arturo Almazan, S/n Roales Zamora 49192",
    "addr:housenumber":"s / n",
    "addr:postcode":"49192",
    "addr:street":"Calle De Arturo Almazan",
    "iso:country":"ES",
    "sg:address":"Calle de Arturo Almazan, S/n",
    "sg:city":"Roales",
    "sg:orig_category":"Mec\u00c1nico Del Autom\u00d3vil",
    "sg:phone":"+34 980 53 86 52",
    "sg:postcode":"49192",
    "sg:province":"Zamora",
    "wof:name":"Centeno Agricola, S.l.",
    "wof:placetype":"venue"
},
  "geometry": {"coordinates":[-5.7722911835,41.5519828796],"type":"Point"}
}