{
  "type": "Feature",
  "properties": {
    "iso:country":"ES",
    "sg:address":"Trva Canteras, 3",
    "sg:city":"Carrizosa",
    "sg:orig_category":"Hilaturas, Hilos Y Actividades Relacionadas",
    "sg:phone":"+34 926 36 80 75",
    "sg:postcode":"13329",
    "sg:province":"Ciudad Real",
    "wof:name":"Induman Carrizosa S.l.",
    "wof:placetype":"venue"
},
  "geometry": {"coordinates":[-2.9902379513,38.8417472839],"type":"Point"}
}