{
  "type": "Feature",
  "properties": {
    "addr:full":"Calle de Lilas, 5 Valladolid Valladolid 47012",
    "addr:housenumber":"5",
    "addr:postcode":"47012",
    "addr:street":"Calle De Lilas",
    "iso:country":"ES",
    "sg:address":"Calle de Lilas, 5",
    "sg:city":"Valladolid",
    "sg:orig_category":"Acero: Productos Sider\u00dargicos Y Transformados (fabricaci\u00d3n, Negocio)",
    "sg:phone":"+34 983 30 97 35",
    "sg:postcode":"47012",
    "sg:province":"Valladolid",
    "wof:name":"Alusa S.l.",
    "wof:placetype":"venue"
},
  "geometry": {"coordinates":[-4.6909394264,41.6426124573],"type":"Point"}
}