{
  "type": "Feature",
  "properties": {
    "addr:full":"Calle de Iglesia, 9 Villamayor Salamanca 37185",
    "addr:housenumber":"9",
    "addr:postcode":"37185",
    "addr:street":"Calle De Iglesia",
    "iso:country":"ES",
    "sg:address":"Calle de Iglesia, 9",
    "sg:city":"Villamayor",
    "sg:orig_category":"Iglesia Cat\u00d3lica",
    "sg:phone":"+34 923 28 95 95",
    "sg:postcode":"37185",
    "sg:province":"Salamanca",
    "wof:name":"Obispado De Salamanca",
    "wof:placetype":"venue"
},
  "geometry": {"coordinates":[-5.6965179443,40.9982414246],"type":"Point"}
}