{
  "type": "Feature",
  "properties": {
    "addr:full":"Calle de Conserva, 16 Valencia Valencia 46022",
    "addr:housenumber":"16",
    "addr:postcode":"46022",
    "addr:street":"Calle De Conserva",
    "iso:country":"ES",
    "sg:address":"Calle de Conserva, 16",
    "sg:city":"Valencia",
    "sg:orig_category":"Peluqueros: De Se\u00d1oras",
    "sg:phone":"+34 963 30 42 21",
    "sg:postcode":"46022",
    "sg:province":"Valencia",
    "wof:name":"Benita Garcia Piedad",
    "wof:placetype":"venue"
},
  "geometry": {"coordinates":[-0.3443419933,39.4652786255],"type":"Point"}
}