{
  "type": "Feature",
  "properties": {
    "addr:full":"Carrer de Castell, 31 Rubi Barcelona 08191",
    "addr:housenumber":"31",
    "addr:postcode":"08191",
    "addr:street":"Carrer De Castell",
    "iso:country":"ES",
    "sg:address":"Carrer de Castell, 31",
    "sg:city":"Rubi",
    "sg:orig_category":"Promotores Constructores",
    "sg:phone":"+34 935 88 47 06",
    "sg:postcode":"08191",
    "sg:province":"Barcelona",
    "wof:name":"Perforaciones Fiel S.l.",
    "wof:placetype":"venue"
},
  "geometry": {"coordinates":[2.0267341137,41.4939956665],"type":"Point"}
}