{
  "type": "Feature",
  "properties": {
    "iso:country":"ES",
    "sg:address":"Castell Milmanda, S/n",
    "sg:city":"Vimbodi",
    "sg:orig_category":"Productores Recolectores, Venta Directa De Vinos",
    "sg:phone":"+34 977 87 80 77",
    "sg:postcode":"43430",
    "sg:province":"Tarragona",
    "wof:name":"Torres Riera Miquel",
    "wof:placetype":"venue"
},
  "geometry": {"coordinates":[1.0504649878,41.4003601074],"type":"Point"}
}