{
  "type": "Feature",
  "properties": {
    "iso:country":"ES",
    "sg:address":"Calle de Darro, 22",
    "sg:city":"Madrid",
    "sg:orig_category":"Centros Empresariales",
    "sg:phone":"+34 915 64 52 20",
    "sg:postcode":"28002",
    "sg:province":"Madrid",
    "wof:name":"Aldan Gestion S.l.",
    "wof:placetype":"venue"
},
  "geometry": {"coordinates":[-3.6858379841,40.4502220154],"type":"Point"}
}