{
  "type": "Feature",
  "properties": {
    "iso:country":"ES",
    "sg:address":"Ctra Borja-el Buste, S/n",
    "sg:city":"Borja",
    "sg:orig_category":"Arquitectos",
    "sg:phone":"+34 976 86 78 81",
    "sg:postcode":"50540",
    "sg:province":"Zaragoza",
    "wof:name":"Garcia Lazaro Jose Antonio",
    "wof:placetype":"venue"
},
  "geometry": {"coordinates":[-1.5289520025,41.8329086304],"type":"Point"}
}