{
  "type": "Feature",
  "properties": {
    "addr:full":"Calle de Oliver, S/n Catedral Murcia 30001",
    "addr:housenumber":"s",
    "addr:postcode":"30001",
    "addr:street":"Calle De Oliver;/ N",
    "iso:country":"ES",
    "sg:address":"Calle de Oliver, S/n",
    "sg:city":"Catedral",
    "sg:orig_category":"Iglesia Cat\u00d3lica",
    "sg:phone":"+34 968 21 63 44",
    "sg:postcode":"30001",
    "sg:province":"Murcia",
    "wof:name":"Obispado De Cartagena",
    "wof:placetype":"venue"
},
  "geometry": {"coordinates":[-1.1280620098,37.9844360352],"type":"Point"}
}