{
  "type": "Feature",
  "properties": {
    "iso:country":"ES",
    "sg:address":"Avda Olivo, 7",
    "sg:city":"Mora",
    "sg:classifiers":[
        {
            "category":"Taxi",
            "type":"Transportation"
        }
    ],
    "sg:phone":"+34 925 30 00 09",
    "sg:postcode":"45400",
    "sg:province":"Toledo",
    "wof:name":"Cervantes Garcia Marcos",
    "wof:placetype":"venue"
},
  "geometry": {"coordinates":[-3.7722260952,39.686832428],"type":"Point"}
}