{
  "type": "Feature",
  "properties": {
    "addr:full":"Unic, S/n For\u00e7a Lleida 25749",
    "addr:housenumber":"s / n",
    "addr:postcode":"25749",
    "addr:street":"Unic",
    "iso:country":"ES",
    "sg:address":"Unic, S/n",
    "sg:city":"For\u00e7a",
    "sg:orig_category":"Cr\u00cda De Animales",
    "sg:phone":"+34 973 46 03 52",
    "sg:postcode":"25749",
    "sg:province":"Lleida",
    "wof:name":"Mitjaneta-canes S.c.p.",
    "wof:placetype":"venue"
},
  "geometry": {"coordinates":[1.2525399923,41.9118309021],"type":"Point"}
}