{
  "type": "Feature",
  "properties": {
    "addr:full":"Avda Txorierriko Etorbidea, 6 Arteaga Vizcaya 48170",
    "addr:housenumber":"6",
    "addr:postcode":"48170",
    "addr:street":"Avda Txorierriko Etorbidea",
    "iso:country":"ES",
    "sg:address":"Avda Txorierriko Etorbidea, 6",
    "sg:city":"Arteaga",
    "sg:orig_category":"Electrodom\u00c9sticos (al Por Menor)",
    "sg:phone":"+34 944 52 09 03",
    "sg:postcode":"48170",
    "sg:province":"Vizcaya",
    "wof:name":"Alloza Ruiz Santiago Ricardo",
    "wof:placetype":"venue"
},
  "geometry": {"coordinates":[-2.8838644028,43.2901039124],"type":"Point"}
}