{
  "type": "Feature",
  "properties": {
    "iso:country":"ES",
    "sg:address":"Carr Emili Grahit, 59",
    "sg:city":"Girona",
    "sg:orig_category":"Arquitectos",
    "sg:phone":"+34 972 20 19 04",
    "sg:postcode":"17002",
    "sg:province":"Girona",
    "wof:name":"Sagrera Busquets Emilio",
    "wof:placetype":"venue"
},
  "geometry": {"coordinates":[2.821698904,41.9747505188],"type":"Point"}
}