{
  "type": "Feature",
  "properties": {
    "addr:full":"Av. Ayala, 4 Amurrio \u00c1lava 01470",
    "addr:housenumber":"4",
    "addr:postcode":"01470",
    "addr:street":"Av. Ayala",
    "iso:country":"ES",
    "sg:address":"Av. Ayala, 4",
    "sg:city":"Amurrio",
    "sg:orig_category":"Radiocomunicaciones, Telefon\u00cda M\u00d3vil, Radiomensajer\u00cda: Servicios, Comercializaci\u00d3n",
    "sg:phone":"+34 945 89 16 52",
    "sg:postcode":"01470",
    "sg:province":"\u00c1lava",
    "wof:name":"Nefertel S.l.",
    "wof:placetype":"venue"
},
  "geometry": {"coordinates":[-3.0022740364,43.0514984131],"type":"Point"}
}