{
  "type": "Feature",
  "properties": {
    "addr:full":"Calle de Del Agujero De San Andres, 3 Benavente Zamora 49600",
    "addr:housenumber":"3",
    "addr:postcode":"49600",
    "addr:street":"Calle De Del Agujero De San Andres",
    "iso:country":"ES",
    "sg:address":"Calle de Del Agujero De San Andres, 3",
    "sg:city":"Benavente",
    "sg:orig_category":"Venta, Instalaci\u00d3n De Calefacci\u00d3n",
    "sg:phone":"+34 980 63 38 64",
    "sg:postcode":"49600",
    "sg:province":"Zamora",
    "wof:name":"Calefaccion Hernando S.l.",
    "wof:placetype":"venue"
},
  "geometry": {"coordinates":[-5.6784591675,41.9984016418],"type":"Point"}
}