{
  "type": "Feature",
  "properties": {
    "addr:full":"Trav De Gracia, 33 Barcelona Barcelona 08021",
    "addr:housenumber":"33",
    "addr:postcode":"08021",
    "addr:street":"Trav De Gracia",
    "iso:country":"ES",
    "sg:address":"Trav De Gracia, 33",
    "sg:city":"Barcelona",
    "sg:orig_category":"Agentes, Concesionarios Y Sucursales De Veh\u00cdculos",
    "sg:phone":"+34 934 14 13 46",
    "sg:postcode":"08021",
    "sg:province":"Barcelona",
    "sg:website":"www.motorllavina.com",
    "wof:name":"Automoviles Llanord S.a.",
    "wof:placetype":"venue"
},
  "geometry": {"coordinates":[2.1471860409,41.394744873],"type":"Point"}
}