{
  "type": "Feature",
  "properties": {
    "addr:full":"Carrer de Rosello, S/n Gava Barcelona 08850",
    "addr:housenumber":"s / n",
    "addr:postcode":"08850",
    "addr:street":"Carrer De Rosello",
    "iso:country":"ES",
    "sg:address":"Carrer de Rosello, S/n",
    "sg:city":"Gava",
    "sg:orig_category":"Pintura, Barniz, Productos Asimilables (fabricaci\u00d3n, Al Por Mayor)",
    "sg:phone":"+34 936 38 33 05",
    "sg:postcode":"08850",
    "sg:province":"Barcelona",
    "wof:name":"Oca\u00f1a Vilchez Jose",
    "wof:placetype":"venue"
},
  "geometry": {"coordinates":[2.011480093,41.3061218262],"type":"Point"}
}