{
  "type": "Feature",
  "properties": {
    "addr:full":"Calle de Mayor, 8 Puerto Mazarron Murcia 30860",
    "addr:housenumber":"8",
    "addr:postcode":"30860",
    "addr:street":"Calle De Mayor",
    "iso:country":"ES",
    "sg:address":"Calle de Mayor, 8",
    "sg:city":"Puerto Mazarron",
    "sg:orig_category":"Lencer\u00cda Femenina, Corseter\u00cda, Trajes De Ba\u00d1o (al Por Menor)",
    "sg:phone":"+34 968 59 57 04",
    "sg:postcode":"30860",
    "sg:province":"Murcia",
    "wof:name":"Sanchez De Las Matas Garcia Isabel",
    "wof:placetype":"venue"
},
  "geometry": {"coordinates":[-1.2589199543,37.5650978088],"type":"Point"}
}