{
  "type": "Feature",
  "properties": {
    "addr:full":"Plaz Mayor, 1 Villaconejos Madrid 28360",
    "addr:housenumber":"1",
    "addr:postcode":"28360",
    "addr:street":"Plaz Mayor",
    "iso:country":"ES",
    "sg:address":"Plaz Mayor, 1",
    "sg:city":"Villaconejos",
    "sg:orig_category":"Administraciones Regionales, Departamentales Y Locales",
    "sg:phone":"+34 918 93 82 14",
    "sg:postcode":"28360",
    "sg:province":"Madrid",
    "wof:name":"Ayuntamiento De Villaconejos",
    "wof:placetype":"venue"
},
  "geometry": {"coordinates":[-3.4848365784,40.1041488647],"type":"Point"}
}