{
  "type": "Feature",
  "properties": {
    "addr:full":"Calle de Jose Antonio Primo De Rivera, 108 Arrecife Las Palmas 35500",
    "addr:housenumber":"108",
    "addr:postcode":"35500",
    "addr:street":"Calle De Jose Antonio Primo De Rivera",
    "iso:country":"ES",
    "sg:address":"Calle de Jose Antonio Primo De Rivera, 108",
    "sg:city":"Arrecife",
    "sg:orig_category":"Inform\u00c1tica, Ofim\u00c1tica (estudios, Asesor\u00cda, Ingenier\u00cda, Formaci\u00d3n)",
    "sg:phone":"+34 928 80 49 33",
    "sg:postcode":"35500",
    "sg:province":"Las Palmas",
    "wof:name":"Ossorio Informatica S.l.",
    "wof:placetype":"venue"
},
  "geometry": {"coordinates":[-13.5575027466,28.9593048096],"type":"Point"}
}