{
  "type": "Feature",
  "properties": {
    "addr:full":"Plaz Victorias, De Las, 11 Melilla Melilla 52005",
    "addr:housenumber":"11",
    "addr:postcode":"52005",
    "addr:street":"Plaz Victorias De Las",
    "iso:country":"ES",
    "sg:address":"Plaz Victorias, De Las, 11",
    "sg:city":"Melilla",
    "sg:orig_category":"Farmacias",
    "sg:phone":"+34 952 67 37 35",
    "sg:postcode":"52005",
    "sg:province":"Melilla",
    "wof:name":"Patricio Cuenca Isabel",
    "wof:placetype":"venue"
},
  "geometry": {"coordinates":[-2.9556701183,35.2835693359],"type":"Point"}
}