{
  "type": "Feature",
  "properties": {
    "iso:country":"ES",
    "sg:address":"Calle de Langileria, 106",
    "sg:city":"Lamiako",
    "sg:orig_category":"Teatro, Ballet, Danza (agrupaciones, Compa\u00d1\u00cdas)",
    "sg:phone":"+34 944 63 05 89",
    "sg:postcode":"48940",
    "sg:province":"Vizcaya",
    "wof:name":"Txikiak-txiki",
    "wof:placetype":"venue"
},
  "geometry": {"coordinates":[-2.9860789776,43.3275489807],"type":"Point"}
}