{
  "type": "Feature",
  "properties": {
    "addr:full":"Calle de Jose Antonio (de), 19 Boadilla Del Monte Madrid 28660",
    "addr:housenumber":"19",
    "addr:postcode":"28660",
    "addr:street":"Calle De Jose Antonio De",
    "iso:country":"ES",
    "sg:address":"Calle de Jose Antonio (de), 19",
    "sg:city":"Boadilla Del Monte",
    "sg:orig_category":"Muebles, Minoristas",
    "sg:phone":"+34 916 33 08 93",
    "sg:postcode":"28660",
    "sg:province":"Madrid",
    "wof:name":"Labian Gonzalez-roman Domingo",
    "wof:placetype":"venue"
},
  "geometry": {"coordinates":[-3.8773810863,40.4053230286],"type":"Point"}
}