{
  "type": "Feature",
  "properties": {
    "addr:full":"Pg Torres, 84 Rubi Barcelona 08191",
    "addr:housenumber":"84",
    "addr:postcode":"08191",
    "addr:street":"Pg Torres",
    "iso:country":"ES",
    "sg:address":"Pg Torres, 84",
    "sg:city":"Rubi",
    "sg:orig_category":"Inmobiliaria (agencias)",
    "sg:phone":"+34 935 86 17 49",
    "sg:postcode":"08191",
    "sg:province":"Barcelona",
    "wof:name":"Servicios Inmobiliarios Hannover S.l.",
    "wof:placetype":"venue"
},
  "geometry": {"coordinates":[2.0341908932,41.479221344],"type":"Point"}
}