{
  "type": "Feature",
  "properties": {
    "iso:country":"ES",
    "sg:address":"Avda Corazon De Jesus, 24",
    "sg:city":"Vall D'uixo",
    "sg:orig_category":"Bancos",
    "sg:phone":"+34 964 66 67 98",
    "sg:postcode":"12600",
    "sg:province":"Castell\u00f3n",
    "sg:website":"www.bancsabadell.es",
    "wof:name":"Banc Sabadell S.a.",
    "wof:placetype":"venue"
},
  "geometry": {"coordinates":[-0.0482099988,39.992477417],"type":"Point"}
}