{
  "type": "Feature",
  "properties": {
    "iso:country":"ES",
    "sg:address":"Calle de Comandante Santa Pau, 17",
    "sg:city":"Zaragoza",
    "sg:orig_category":"Peluqueros: De Se\u00d1oras",
    "sg:phone":"+34 976 22 27 63",
    "sg:postcode":"50008",
    "sg:province":"Zaragoza",
    "wof:name":"Polo Cuenca Emilia Teresa",
    "wof:placetype":"venue"
},
  "geometry": {"coordinates":[-0.8848412037,41.6418685913],"type":"Point"}
}