{
  "type": "Feature",
  "properties": {
    "addr:full":"Cendona, 16 Cendona Pontevedra 36099",
    "addr:housenumber":"16",
    "addr:postcode":"36099",
    "addr:street":"Cendona",
    "iso:country":"ES",
    "sg:address":"Cendona, 16",
    "sg:city":"Cendona",
    "sg:orig_category":"Motocicletas (agentes, Concesionarios)",
    "sg:phone":"+34 986 87 06 78",
    "sg:postcode":"36099",
    "sg:province":"Pontevedra",
    "wof:name":"Automotogas S.l.",
    "wof:placetype":"venue"
},
  "geometry": {"coordinates":[-8.6428003311,42.4304618835],"type":"Point"}
}