{
  "type": "Feature",
  "properties": {
    "addr:full":"Calle de Martinez Campos, 7 Melilla Melilla 52002",
    "addr:housenumber":"7",
    "addr:postcode":"52002",
    "addr:street":"Calle De Martinez Campos",
    "iso:country":"ES",
    "sg:address":"Calle de Martinez Campos, 7",
    "sg:city":"Melilla",
    "sg:orig_category":"Bazares, Art\u00cdculos De Limpieza Y De Cocina (al Por Menor)",
    "sg:phone":"+34 952 67 21 13",
    "sg:postcode":"52002",
    "sg:province":"Melilla",
    "wof:name":"Tieb Mohamed Mulut",
    "wof:placetype":"venue"
},
  "geometry": {"coordinates":[-2.9456830025,35.2968978882],"type":"Point"}
}