{
  "type": "Feature",
  "properties": {
    "addr:full":"Calle de Aurora, 11 Puerto De Santa Maria C\u00e1diz 11500",
    "addr:housenumber":"11",
    "addr:postcode":"11500",
    "addr:street":"Calle De Aurora;Ca\u0301Diz",
    "iso:country":"ES",
    "sg:address":"Calle de Aurora, 11",
    "sg:city":"Puerto De Santa Maria",
    "sg:classifiers":[
        {
            "category":"Professional",
            "subcategory":"Research",
            "type":"Services"
        }
    ],
    "sg:phone":"+34 956 87 22 37",
    "sg:postcode":"11500",
    "sg:province":"C\u00e1diz",
    "sg:tags":[
        "mercado",
        "de",
        "estudios"
    ],
    "wof:name":"Kersmaecker  Matilde",
    "wof:placetype":"venue"
},
  "geometry": {"coordinates":[-6.2284545898,36.5932922363],"type":"Point"}
}