{
  "type": "Feature",
  "properties": {
    "iso:country":"ES",
    "sg:address":"Avda Juan Carlos I, 10",
    "sg:city":"Alhama Murcia",
    "sg:orig_category":"Veh\u00cdculos De Ocasi\u00d3n",
    "sg:phone":"+34 968 63 02 17",
    "sg:postcode":"30840",
    "sg:province":"Murcia",
    "wof:name":"Torralba Ferragut Antonio",
    "wof:placetype":"venue"
},
  "geometry": {"coordinates":[-1.4226789474,37.8512268066],"type":"Point"}
}