{
  "type": "Feature",
  "properties": {
    "addr:full":"Calle de Jaen, 8 Peligros Granada 18210",
    "addr:housenumber":"8",
    "addr:postcode":"18210",
    "addr:street":"Calle De Jaen",
    "iso:country":"ES",
    "sg:address":"Calle de Jaen, 8",
    "sg:city":"Peligros",
    "sg:orig_category":"Empresas De Vigilancia, Guardia Y Protecci\u00d3n",
    "sg:phone":"+34 958 26 77 04",
    "sg:postcode":"18210",
    "sg:province":"Granada",
    "sg:website":"www.esabe.es",
    "wof:name":"Esabe Vigilancia S.a.",
    "wof:placetype":"venue"
},
  "geometry": {"coordinates":[-3.6298270226,37.2311706543],"type":"Point"}
}