{
  "type": "Feature",
  "properties": {
    "addr:full":"Carrer de Patronat Obrer, 30 Palma Islas Baleares 07006",
    "addr:housenumber":"30",
    "addr:postcode":"07006",
    "addr:street":"Carrer De Patronat Obrer",
    "iso:country":"ES",
    "sg:address":"Carrer de Patronat Obrer, 30",
    "sg:city":"Palma",
    "sg:orig_category":"Ense\u00d1anza, Formaci\u00d3n Profesional: Aprendizaje",
    "sg:phone":"+34 971 77 48 11",
    "sg:postcode":"07006",
    "sg:province":"Islas Baleares",
    "wof:name":"Instituto Social De Las Fuerzas Armadas",
    "wof:placetype":"venue"
},
  "geometry": {"coordinates":[2.658853054,39.5742301941],"type":"Point"}
}