{
  "type": "Feature",
  "properties": {
    "addr:full":"Carrer de Verntallat, 25 Barcelona Barcelona 08024",
    "addr:housenumber":"25",
    "addr:postcode":"08024",
    "addr:street":"Carrer De Verntallat",
    "iso:country":"ES",
    "sg:address":"Carrer de Verntallat, 25",
    "sg:city":"Barcelona",
    "sg:orig_category":"Audiovisuales (producci\u00d3n, Edici\u00d3n, Realizaci\u00d3n)",
    "sg:phone":"+34 932 17 40 38",
    "sg:postcode":"08024",
    "sg:province":"Barcelona",
    "sg:website":"www.frame25online.com",
    "wof:name":"Frame 25 S.l",
    "wof:placetype":"venue"
},
  "geometry": {"coordinates":[2.155328989,41.40650177],"type":"Point"}
}