{
  "type": "Feature",
  "properties": {
    "iso:country":"ES",
    "sg:address":"Calle de Honorio Lozano, 2",
    "sg:city":"Estacion",
    "sg:orig_category":"Ense\u00d1anza Variada",
    "sg:phone":"+34 918 50 57 95",
    "sg:postcode":"28400",
    "sg:province":"Madrid",
    "wof:name":"Garcia Gutierrez Mariano",
    "wof:placetype":"venue"
},
  "geometry": {"coordinates":[-3.9919650555,40.6455612183],"type":"Point"}
}