{
  "type": "Feature",
  "properties": {
    "iso:country":"ES",
    "sg:address":"Avda Habana (de La), 57",
    "sg:city":"Ourense",
    "sg:orig_category":"Abogados",
    "sg:phone":"+34 988 25 50 55",
    "sg:postcode":"32004",
    "sg:province":"Ourense",
    "wof:name":"Valles Urriza Rafael",
    "wof:placetype":"venue"
},
  "geometry": {"coordinates":[-7.8622689247,42.3423309326],"type":"Point"}
}