{
  "type": "Feature",
  "properties": {
    "iso:country":"ES",
    "sg:address":"Barro Iurre Auzunea, 11",
    "sg:city":"Tolosa",
    "sg:orig_category":"Fisioterapia",
    "sg:phone":"+34 943 67 39 10",
    "sg:postcode":"20400",
    "sg:province":"Guip\u00f9zcoa",
    "wof:name":"Josu Diez Catalina Y Otra C.b.",
    "wof:placetype":"venue"
},
  "geometry": {"coordinates":[-2.0820438862,43.1321983337],"type":"Point"}
}