{
  "type": "Feature",
  "properties": {
    "addr:full":"Calle de Paseo Del Estatuto, 35 Carmona Sevilla 41410",
    "addr:housenumber":"35",
    "addr:postcode":"41410",
    "addr:street":"Calle De Paseo Del Estatuto",
    "iso:country":"ES",
    "sg:address":"Calle de Paseo Del Estatuto, 35",
    "sg:city":"Carmona",
    "sg:orig_category":"Asesor\u00cda Fiscal Y Jur\u00cddica",
    "sg:phone":"+34 954 19 18 88",
    "sg:postcode":"41410",
    "sg:province":"Sevilla",
    "wof:name":"Elias Castejon S.l.",
    "wof:placetype":"venue"
},
  "geometry": {"coordinates":[-5.6433792114,37.4708709717],"type":"Point"}
}