{
  "type": "Feature",
  "properties": {
    "iso:country":"ES",
    "sg:address":"Calle de Medieras, 3",
    "sg:city":"Cartagena",
    "sg:orig_category":"Panader\u00cdas, Panader\u00cdas",
    "sg:phone":"+34 968 50 31 73",
    "sg:postcode":"30201",
    "sg:province":"Murcia",
    "wof:name":"Sanchez Conesa Fulgencio",
    "wof:placetype":"venue"
},
  "geometry": {"coordinates":[-0.9854519963,37.6006317139],"type":"Point"}
}