{
  "type": "Feature",
  "properties": {
    "iso:country":"ES",
    "sg:address":"Carrer de Reig I Bonet, 22",
    "sg:city":"Barcelona",
    "sg:orig_category":"Bisuter\u00cda, Joyer\u00cda, Relojer\u00cda (al Por Menor)",
    "sg:phone":"+34 932 84 99 72",
    "sg:postcode":"08024",
    "sg:province":"Barcelona",
    "wof:name":"Aullo Monte Andres",
    "wof:placetype":"venue"
},
  "geometry": {"coordinates":[2.1606490612,41.4075279236],"type":"Point"}
}