{
  "type": "Feature",
  "properties": {
    "addr:full":"Avda Marinero (el), 39 Caleta De Famara Las Palmas 35558",
    "addr:housenumber":"39",
    "addr:postcode":"35558",
    "addr:street":"Avda Marinero El;Palmas",
    "iso:country":"ES",
    "sg:address":"Avda Marinero (el), 39",
    "sg:city":"Caleta De Famara",
    "sg:orig_category":"Asociaciones Y Clubs Deportivos",
    "sg:phone":"+34 928 52 86 76",
    "sg:postcode":"35558",
    "sg:province":"Las Palmas",
    "wof:name":"Urrestarazu Montesdeoca Pedro",
    "wof:placetype":"venue"
},
  "geometry": {"coordinates":[-13.5640792847,29.1168136597],"type":"Point"}
}