{
  "type": "Feature",
  "properties": {
    "iso:country":"ES",
    "sg:address":"Calle de Teodoro Llorente, 163",
    "sg:city":"Puerto",
    "sg:orig_category":"Asociaciones, Organismos Culturales Y Socioeducativos",
    "sg:phone":"+34 962 69 10 94",
    "sg:postcode":"46520",
    "sg:province":"Valencia",
    "wof:name":"La Columna Teatro De Sagunto",
    "wof:placetype":"venue"
},
  "geometry": {"coordinates":[-0.2025949955,39.7040786743],"type":"Point"}
}