{
  "type": "Feature",
  "properties": {
    "iso:country":"ES",
    "sg:address":"Carr Mostasaff (el), 7",
    "sg:city":"Alboraya",
    "sg:orig_category":"Creaci\u00d3n De Sitios, Hosting Internet",
    "sg:phone":"+34 961 86 04 57",
    "sg:postcode":"46120",
    "sg:province":"Valencia",
    "sg:website":"www.virtualis-ebs.com",
    "wof:name":"Virtualis Ebs S.l.",
    "wof:placetype":"venue"
},
  "geometry": {"coordinates":[-0.3505490124,39.4936752319],"type":"Point"}
}