{
  "type": "Feature",
  "properties": {
    "addr:full":"Avda Virgen De Lidon, 16 Castellon Castell\u00f3n 12003",
    "addr:housenumber":"16",
    "addr:postcode":"12003",
    "addr:street":"Avda Virgen De Lidon",
    "iso:country":"ES",
    "sg:address":"Avda Virgen De Lidon, 16",
    "sg:city":"Castellon",
    "sg:orig_category":"Aparatos E Instalaci\u00d3n De Regad\u00cdos",
    "sg:phone":"+34 964 22 00 39",
    "sg:postcode":"12003",
    "sg:province":"Castell\u00f3n",
    "wof:name":"Sindicato De Riegos De Castellon De La Plana",
    "wof:placetype":"venue"
},
  "geometry": {"coordinates":[-0.0077,39.9836883545],"type":"Point"}
}