{
  "type": "Feature",
  "properties": {
    "addr:full":"G.v. Corts Catalanes, 541 Barcelona Barcelona 08011",
    "addr:housenumber":"541",
    "addr:postcode":"08011",
    "addr:street":"Catalanes",
    "iso:country":"ES",
    "sg:address":"G.v. Corts Catalanes, 541",
    "sg:city":"Barcelona",
    "sg:orig_category":"Asesor\u00cda Fiscal Y Jur\u00cddica",
    "sg:phone":"+34 933 23 54 04",
    "sg:postcode":"08011",
    "sg:province":"Barcelona",
    "wof:name":"Puig Pulido Jose Maria",
    "wof:placetype":"venue"
},
  "geometry": {"coordinates":[2.1596930027,41.3834114075],"type":"Point"}
}