{
  "type": "Feature",
  "properties": {
    "addr:full":"Calle de Lealtad, S/n Villaviciosa Asturias 33300",
    "addr:housenumber":"s / n",
    "addr:postcode":"33300",
    "addr:street":"Calle De Lealtad",
    "iso:country":"ES",
    "sg:address":"Calle de Lealtad, S/n",
    "sg:city":"Villaviciosa",
    "sg:orig_category":"Psic\u00d3logos",
    "sg:phone":"+34 985 89 21 41",
    "sg:postcode":"33300",
    "sg:province":"Asturias",
    "wof:name":"Gonzalez Santos Obdulia",
    "wof:placetype":"venue"
},
  "geometry": {"coordinates":[-5.4341239929,43.482673645],"type":"Point"}
}