{
  "type": "Feature",
  "properties": {
    "iso:country":"ES",
    "sg:address":"Calle de Ribera La, S/n",
    "sg:city":"Cudillero",
    "sg:orig_category":"Empresas Portuarias",
    "sg:phone":"+34 985 59 01 15",
    "sg:postcode":"33150",
    "sg:province":"Asturias",
    "wof:name":"Autoridad Portuaria De Aviles",
    "wof:placetype":"venue"
},
  "geometry": {"coordinates":[-6.1456646919,43.563419342],"type":"Point"}
}