{
  "type": "Feature",
  "properties": {
    "addr:full":"Calle de San Antonio, 7 Montijo Badajoz 06480",
    "addr:housenumber":"7",
    "addr:postcode":"06480",
    "addr:street":"Calle De San Antonio",
    "iso:country":"ES",
    "sg:address":"Calle de San Antonio, 7",
    "sg:city":"Montijo",
    "sg:orig_category":"Perfumer\u00cda (al Por Menor)",
    "sg:phone":"+34 924 45 72 04",
    "sg:postcode":"06480",
    "sg:province":"Badajoz",
    "wof:name":"Rodriguez Pedreira Maria Esperanza",
    "wof:placetype":"venue"
},
  "geometry": {"coordinates":[-6.6158590317,38.9077835083],"type":"Point"}
}