{
  "type": "Feature",
  "properties": {
    "iso:country":"ES",
    "sg:address":"Calle de Mayor, 105",
    "sg:city":"Union",
    "sg:orig_category":"Ropa Y Art\u00cdculos Pre",
    "sg:phone":"+34 968 56 10 57",
    "sg:postcode":"30360",
    "sg:province":"Murcia",
    "wof:name":"Gonzalez Pagan Jose Angel",
    "wof:placetype":"venue"
},
  "geometry": {"coordinates":[-0.8753709793,37.617603302],"type":"Point"}
}