{
  "type": "Feature",
  "properties": {
    "iso:country":"ES",
    "sg:address":"Luga Hacienda San Eugenio, S/n",
    "sg:city":"Campanillas",
    "sg:orig_category":"Producci\u00d3n De Huevos",
    "sg:phone":"+34 952 43 41 46",
    "sg:postcode":"29590",
    "sg:province":"M\u00e1laga",
    "wof:name":"Granja Jurado S.l",
    "wof:placetype":"venue"
},
  "geometry": {"coordinates":[-4.5338149071,36.7264175415],"type":"Point"}
}