{
  "type": "Feature",
  "properties": {
    "addr:full":"Calle de Manuel Caso De La Villa, 24 Ribadesella Asturias 33560",
    "addr:housenumber":"24",
    "addr:postcode":"33560",
    "addr:street":"Calle De Manuel Caso De La Villa",
    "iso:country":"ES",
    "sg:address":"Calle de Manuel Caso De La Villa, 24",
    "sg:city":"Ribadesella",
    "sg:orig_category":"Mec\u00c1nico Del Autom\u00d3vil",
    "sg:phone":"+34 985 85 80 91",
    "sg:postcode":"33560",
    "sg:province":"Asturias",
    "wof:name":"Gonzalez Gutierrez Maria Isabel",
    "wof:placetype":"venue"
},
  "geometry": {"coordinates":[-5.0592489243,43.4654998779],"type":"Point"}
}