{
  "type": "Feature",
  "properties": {
    "addr:full":"Pase Canal (del), 145 Zaragoza Zaragoza 50007",
    "addr:housenumber":"145",
    "addr:postcode":"50007",
    "addr:street":"Canal Del",
    "iso:country":"ES",
    "sg:address":"Pase Canal (del), 145",
    "sg:city":"Zaragoza",
    "sg:orig_category":"Promotores Constructores",
    "sg:phone":"+34 976 38 22 12",
    "sg:postcode":"50007",
    "sg:province":"Zaragoza",
    "wof:name":"Seyga S.l.",
    "wof:placetype":"venue"
},
  "geometry": {"coordinates":[-0.8893640041,41.6115264893],"type":"Point"}
}