{
  "type": "Feature",
  "properties": {
    "iso:country":"ES",
    "sg:address":"Calle de Patricio Ferrandiz, 35",
    "sg:city":"Denia",
    "sg:orig_category":"Psic\u00d3logos",
    "sg:phone":"+34 965 78 14 50",
    "sg:postcode":"03700",
    "sg:province":"Alicante",
    "wof:name":"Ahuir Rosello Maria Teresa",
    "wof:placetype":"venue"
},
  "geometry": {"coordinates":[0.1079393029,38.8383026123],"type":"Point"}
}