{
  "type": "Feature",
  "properties": {
    "addr:full":"Calle de Gran Via, 18 Sax Alicante 03630",
    "addr:housenumber":"18",
    "addr:postcode":"03630",
    "addr:street":"Calle De Gran Via",
    "iso:country":"ES",
    "sg:address":"Calle de Gran Via, 18",
    "sg:city":"Sax",
    "sg:orig_category":"Inmobiliaria (agencias)",
    "sg:phone":"+34 966 96 74 96",
    "sg:postcode":"03630",
    "sg:province":"Alicante",
    "wof:name":"Blesa Villaplana Venancio",
    "wof:placetype":"venue"
},
  "geometry": {"coordinates":[-0.8188570142,38.5362968445],"type":"Point"}
}