{
  "type": "Feature",
  "properties": {
    "iso:country":"ES",
    "sg:address":"Calle de Narciso Serra, 11",
    "sg:city":"Madrid",
    "sg:orig_category":"Inform\u00c1tica, Ofim\u00c1tica (estudios, Asesor\u00cda, Ingenier\u00cda, Formaci\u00d3n)",
    "sg:phone":"+34 915 01 98 86",
    "sg:postcode":"28007",
    "sg:province":"Madrid",
    "wof:name":"Federico Cuellar S.a.",
    "wof:placetype":"venue"
},
  "geometry": {"coordinates":[-3.6789569855,40.4051208496],"type":"Point"}
}