{
  "type": "Feature",
  "properties": {
    "addr:full":"Calle de Feria, 16 Constantina Sevilla 41450",
    "addr:housenumber":"16",
    "addr:postcode":"41450",
    "addr:street":"Calle De Feria",
    "iso:country":"ES",
    "sg:address":"Calle de Feria, 16",
    "sg:city":"Constantina",
    "sg:orig_category":"Asociaciones Y Clubs Deportivos",
    "sg:phone":"+34 955 88 18 87",
    "sg:postcode":"41450",
    "sg:province":"Sevilla",
    "wof:name":"Arroyo Omenat Marcos Antonio",
    "wof:placetype":"venue"
},
  "geometry": {"coordinates":[-5.6208491325,37.8766937256],"type":"Point"}
}