{
  "type": "Feature",
  "properties": {
    "iso:country":"ES",
    "sg:address":"Calle de Edison, 44",
    "sg:city":"Getafe",
    "sg:orig_category":"Ingenier\u00cda, Centros De Estudios (diversos)",
    "sg:phone":"+34 916 01 01 01",
    "sg:postcode":"28906",
    "sg:province":"Madrid",
    "wof:name":"General De Ingenieria Inhiset S.a.",
    "wof:placetype":"venue"
},
  "geometry": {"coordinates":[-3.6943583488,40.3022956848],"type":"Point"}
}