{
  "type": "Feature",
  "properties": {
    "iso:country":"ES",
    "sg:address":"Calle de Arribes Del Duero, 75",
    "sg:city":"Salamanca",
    "sg:orig_category":"Perfumer\u00cda Y Cosm\u00c9tica (fabricaci\u00d3n, Al Por Mayor)",
    "sg:phone":"+34 923 19 00 40",
    "sg:postcode":"37008",
    "sg:province":"Salamanca",
    "sg:website":"www.alcantaracosmetica.com",
    "wof:name":"Alcantara Espa\u00f1a S. A.",
    "wof:placetype":"venue"
},
  "geometry": {"coordinates":[-5.6646709442,40.9372520447],"type":"Point"}
}