{
  "type": "Feature",
  "properties": {
    "addr:full":"Calle de Etreros, S/n Sangarcia Segovia 40134",
    "addr:housenumber":"s",
    "addr:postcode":"40134",
    "addr:street":"Calle De Etreros;/ N Sangarcia Segovia",
    "iso:country":"ES",
    "sg:address":"Calle de Etreros, S/n",
    "sg:city":"Sangarcia",
    "sg:orig_category":"Ba\u00d1os Y Duchas P\u00dablicos",
    "sg:phone":"+34 921 17 80 40",
    "sg:postcode":"40134",
    "sg:province":"Segovia",
    "wof:name":"Ayuntamiento De Sangarcia",
    "wof:placetype":"venue"
},
  "geometry": {"coordinates":[-4.417529583,40.9475326538],"type":"Point"}
}