{
  "type": "Feature",
  "properties": {
    "iso:country":"ES",
    "sg:address":"Calle de Melendez Valdes, 59",
    "sg:city":"Madrid",
    "sg:orig_category":"Ropa Para Se\u00d1oras Y Caballeros (al Por Menor)",
    "sg:phone":"+34 915 43 91 36",
    "sg:postcode":"28015",
    "sg:province":"Madrid",
    "wof:name":"Salgado Garcia Carmen",
    "wof:placetype":"venue"
},
  "geometry": {"coordinates":[-3.7162148952,40.4329605103],"type":"Point"}
}