{
  "type": "Feature",
  "properties": {
    "iso:country":"ES",
    "sg:address":"Pol Ind El Brosquil, S/n",
    "sg:city":"Oliva",
    "sg:orig_category":"Limpieza Con Chorro De Arena Y Con Granalla, Pulido",
    "sg:phone":"+34 962 96 32 27",
    "sg:postcode":"46780",
    "sg:province":"Valencia",
    "wof:name":"Lacados Serrano Y Ma\u00f1o S.l.",
    "wof:placetype":"venue"
},
  "geometry": {"coordinates":[-0.1179220006,38.9189491272],"type":"Point"}
}