{
  "type": "Feature",
  "properties": {
    "addr:full":"Carrer de L'hospital, 83 Barcelona Barcelona 08001",
    "addr:housenumber":"83",
    "addr:postcode":"08001",
    "addr:street":"Carrer De L'Hospital",
    "iso:country":"ES",
    "sg:address":"Carrer de L'hospital, 83",
    "sg:city":"Barcelona",
    "sg:orig_category":"Estancos",
    "sg:phone":"+34 934 41 78 88",
    "sg:postcode":"08001",
    "sg:province":"Barcelona",
    "wof:name":"Morera Salvat Jordi",
    "wof:placetype":"venue"
},
  "geometry": {"coordinates":[2.1700882912,41.380355835],"type":"Point"}
}