{
  "type": "Feature",
  "properties": {
    "iso:country":"ES",
    "sg:address":"Avda Constitucion, 112",
    "sg:city":"Cistierna",
    "sg:orig_category":"Restaurantes: Restauraci\u00d3n R\u00c1pida Y Autoservicio",
    "sg:phone":"+34 987 70 01 78",
    "sg:postcode":"24800",
    "sg:province":"Le\u00f3n",
    "wof:name":"Diez Valbuena Daniel",
    "wof:placetype":"venue"
},
  "geometry": {"coordinates":[-5.1286349297,42.8044586182],"type":"Point"}
}