{
  "type": "Feature",
  "properties": {
    "iso:country":"ES",
    "sg:address":"Calle de Poesia (de La), 2",
    "sg:city":"Loranca",
    "sg:orig_category":"Trabajos De Perforaciones, Sondeos, Construcci\u00d3n De Pozos",
    "sg:phone":"+34 914 86 88 99",
    "sg:postcode":"28942",
    "sg:province":"Madrid",
    "wof:name":"Patino Galan Jose Andres",
    "wof:placetype":"venue"
},
  "geometry": {"coordinates":[-3.8380270004,40.2979202271],"type":"Point"}
}