{
  "type": "Feature",
  "properties": {
    "iso:country":"ES",
    "sg:address":"Avda Reyes Catolicos, S/n",
    "sg:city":"Alcala Henares",
    "sg:orig_category":"Aguas (distribuci\u00d3n, Servicios)",
    "sg:phone":"+34 918 89 46 32",
    "sg:postcode":"28802",
    "sg:province":"Madrid",
    "wof:name":"Cadagua S.a.",
    "wof:placetype":"venue"
},
  "geometry": {"coordinates":[-3.3731091022,40.4779014587],"type":"Point"}
}