{
  "type": "Feature",
  "properties": {
    "iso:country":"ES",
    "sg:address":"Calle de Laser (el), S/n",
    "sg:city":"Azuqueca Henares",
    "sg:orig_category":"Promotores Constructores",
    "sg:phone":"+34 949 27 73 67",
    "sg:postcode":"19200",
    "sg:province":"Guadalajara",
    "wof:name":"Azalia Grupo Inmobiliario S.l.",
    "wof:placetype":"venue"
},
  "geometry": {"coordinates":[-3.2621743679,40.5581932068],"type":"Point"}
}