{
  "type": "Feature",
  "properties": {
    "addr:full":"Av. Passeig Mar, 5 Palamos Girona 17230",
    "addr:housenumber":"5",
    "addr:postcode":"17230",
    "addr:street":"Av. Passeig Mar",
    "iso:country":"ES",
    "sg:address":"Av. Passeig Mar, 5",
    "sg:city":"Palamos",
    "sg:orig_category":"Asesor\u00cda Fiscal Y Jur\u00cddica",
    "sg:phone":"+34 972 31 69 54",
    "sg:postcode":"17230",
    "sg:province":"Girona",
    "wof:name":"B.i.b. Assesors Associats S.l.",
    "wof:placetype":"venue"
},
  "geometry": {"coordinates":[3.1279499531,41.8473548889],"type":"Point"}
}