{
  "type": "Feature",
  "properties": {
    "addr:full":"Calle de Ayora, 14 Valencia Valencia 46018",
    "addr:housenumber":"14",
    "addr:postcode":"46018",
    "addr:street":"Calle De Ayora",
    "iso:country":"ES",
    "sg:address":"Calle de Ayora, 14",
    "sg:city":"Valencia",
    "sg:orig_category":"Bisuter\u00cda, Joyer\u00cda, Relojer\u00cda (al Por Menor)",
    "sg:phone":"+34 963 85 21 32",
    "sg:postcode":"46018",
    "sg:province":"Valencia",
    "wof:name":"Pagan Vera Javier",
    "wof:placetype":"venue"
},
  "geometry": {"coordinates":[-0.3919236958,39.4667129517],"type":"Point"}
}