{
  "type": "Feature",
  "properties": {
    "iso:country":"ES",
    "sg:address":"Parque Agroalimentario La Alcudia, 1",
    "sg:city":"Elche",
    "sg:orig_category":"Comercio De Piezas De Recambio Y De Accesorios De Veh\u00cdculos, Veh\u00cdculos Industriales",
    "sg:phone":"+34 965 42 71 31",
    "sg:postcode":"03290",
    "sg:province":"Alicante",
    "wof:name":"Autocentro Elektra S.l.",
    "wof:placetype":"venue"
},
  "geometry": {"coordinates":[-0.6915392876,38.2354507446],"type":"Point"}
}