{
  "type": "Feature",
  "properties": {
    "iso:country":"ES",
    "sg:address":"Calle de Maldonado Ocampo, 6",
    "sg:city":"Salamanca",
    "sg:orig_category":"Abogados",
    "sg:phone":"+34 923 23 97 26",
    "sg:postcode":"37005",
    "sg:province":"Salamanca",
    "wof:name":"Lucas Cuesta Juan Antonio",
    "wof:placetype":"venue"
},
  "geometry": {"coordinates":[-5.661239624,40.9698448181],"type":"Point"}
}