{
  "type": "Feature",
  "properties": {
    "addr:full":"Pla\u00c7 Esglesia (de L'), 7 Agramunt Lleida 25310",
    "addr:housenumber":"7",
    "addr:postcode":"25310",
    "addr:street":"Plac\u0327;'",
    "iso:country":"ES",
    "sg:address":"Pla\u00c7 Esglesia (de L'), 7",
    "sg:city":"Agramunt",
    "sg:orig_category":"Ropa Para Se\u00d1oras Y Caballeros (al Por Menor)",
    "sg:phone":"+34 973 39 06 56",
    "sg:postcode":"25310",
    "sg:province":"Lleida",
    "wof:name":"Pedraza Puig Olga",
    "wof:placetype":"venue"
},
  "geometry": {"coordinates":[1.0799080133,41.8081474304],"type":"Point"}
}