{
  "type": "Feature",
  "properties": {
    "addr:full":"Calle de Real De Malaga, 20 Gabia Grande Granada 18110",
    "addr:housenumber":"20",
    "addr:postcode":"18110",
    "addr:street":"Calle De Real De Malaga",
    "iso:country":"ES",
    "sg:address":"Calle de Real De Malaga, 20",
    "sg:city":"Gabia Grande",
    "sg:orig_category":"Prot\u00c9sicos Dentales",
    "sg:phone":"+34 958 58 00 05",
    "sg:postcode":"18110",
    "sg:province":"Granada",
    "wof:name":"Salvador Alonso Jimenez Y Otros Cdad.",
    "wof:placetype":"venue"
},
  "geometry": {"coordinates":[-3.6684379578,37.1355476379],"type":"Point"}
}