{
  "type": "Feature",
  "properties": {
    "addr:full":"Conj. Nuevo Chapin, 6 Jerez C\u00e1diz 11405",
    "addr:postcode":"11405",
    "iso:country":"ES",
    "sg:address":"Conj. Nuevo Chapin, 6",
    "sg:city":"Jerez",
    "sg:orig_category":"Molduras, Junquillos, Listones Y Molduras Perforadas",
    "sg:phone":"+34 956 32 49 17",
    "sg:postcode":"11405",
    "sg:province":"C\u00e1diz",
    "wof:name":"Sistelcom-telemensaje S.a.",
    "wof:placetype":"venue"
},
  "geometry": {"coordinates":[-6.1005191803,36.7067260742],"type":"Point"}
}