{
  "type": "Feature",
  "properties": {
    "iso:country":"ES",
    "sg:address":"La Fabrica, S/n",
    "sg:city":"Huetor-tajar",
    "sg:orig_category":"Caf\u00c9s, Bares, Cervecer\u00cdas",
    "sg:phone":"+34 958 33 33 07",
    "sg:postcode":"18360",
    "sg:province":"Granada",
    "wof:name":"Urbano Fernandez Jose",
    "wof:placetype":"venue"
},
  "geometry": {"coordinates":[-4.046749115,37.1978111267],"type":"Point"}
}