{
  "type": "Feature",
  "properties": {
    "iso:country":"ES",
    "sg:address":"Pg Bisbe Guillamet, 10",
    "sg:city":"Olot",
    "sg:orig_category":"Ense\u00d1anza, Formaci\u00d3n Profesional: Aprendizaje",
    "sg:phone":"+34 972 27 91 00",
    "sg:postcode":"17800",
    "sg:province":"Girona",
    "wof:name":"Ajuntament D'olot",
    "wof:placetype":"venue"
},
  "geometry": {"coordinates":[2.4844088554,42.1831283569],"type":"Point"}
}