{
  "type": "Feature",
  "properties": {
    "addr:full":"Calle de Espinos, 17 Aranjuez Madrid 28300",
    "addr:housenumber":"17",
    "addr:postcode":"28300",
    "addr:street":"Calle De Espinos",
    "iso:country":"ES",
    "sg:address":"Calle de Espinos, 17",
    "sg:city":"Aranjuez",
    "sg:orig_category":"Comercio De Hierro",
    "sg:phone":"+34 918 91 02 44",
    "sg:postcode":"28300",
    "sg:province":"Madrid",
    "wof:name":"Mafe Manufacturas Ferricas S.l.",
    "wof:placetype":"venue"
},
  "geometry": {"coordinates":[-3.6223609447,40.0232505798],"type":"Point"}
}