{
  "type": "Feature",
  "properties": {
    "iso:country":"ES",
    "sg:address":"Calle de Zamora, 9",
    "sg:city":"Salamanca",
    "sg:orig_category":"Fabricaci\u00d3n De Sobres, Bolsas Y Fundas",
    "sg:phone":"+34 923 21 21 46",
    "sg:postcode":"37002",
    "sg:province":"Salamanca",
    "wof:name":"Bernus Marrama Amparo",
    "wof:placetype":"venue"
},
  "geometry": {"coordinates":[-5.664162159,40.965763092],"type":"Point"}
}