{
  "type": "Feature",
  "properties": {
    "iso:country":"ES",
    "sg:address":"Ctra Casillas, 10",
    "sg:city":"Sotillo Adrada",
    "sg:orig_category":"Fabricaci\u00d3n De Papel Pintado",
    "sg:phone":"+34 918 60 12 69",
    "sg:postcode":"05420",
    "sg:province":"\u00c1vila",
    "wof:name":"Suministros Santa Teresa S.l.",
    "wof:placetype":"venue"
},
  "geometry": {"coordinates":[-4.5801072121,40.2944526672],"type":"Point"}
}