{
  "type": "Feature",
  "properties": {
    "addr:full":"Calle de Cobre, 2 Salamanca Salamanca 37008",
    "addr:housenumber":"2",
    "addr:postcode":"37008",
    "addr:street":"Calle De Cobre",
    "iso:country":"ES",
    "sg:address":"Calle de Cobre, 2",
    "sg:city":"Salamanca",
    "sg:orig_category":"Empresas De Limpieza",
    "sg:phone":"+34 923 19 29 27",
    "sg:postcode":"37008",
    "sg:province":"Salamanca",
    "wof:name":"Cuadrado Ramos Francisco",
    "wof:placetype":"venue"
},
  "geometry": {"coordinates":[-5.6849241257,40.9504928589],"type":"Point"}
}