{
  "type": "Feature",
  "properties": {
    "iso:country":"ES",
    "sg:address":"Calle de San Pedro De Carde\u00d1a, 100",
    "sg:city":"Burgos",
    "sg:orig_category":"Molduras, Junquillos, Listones Y Molduras Perforadas",
    "sg:phone":"+34 947 26 97 77",
    "sg:postcode":"09002",
    "sg:province":"Burgos",
    "wof:name":"Perez Zu\u00f1eda Benigno",
    "wof:placetype":"venue"
},
  "geometry": {"coordinates":[-3.6858789921,42.3399467468],"type":"Point"}
}