{
  "type": "Feature",
  "properties": {
    "addr:full":"Avda Constitucion, 148 Valencia Valencia 46009",
    "addr:housenumber":"148",
    "addr:postcode":"46009",
    "addr:street":"Avda Constitucion",
    "iso:country":"ES",
    "sg:address":"Avda Constitucion, 148",
    "sg:city":"Valencia",
    "sg:orig_category":"Inform\u00c1tica, Ofim\u00c1tica (estudios, Asesor\u00cda, Ingenier\u00cda, Formaci\u00d3n)",
    "sg:phone":"+34 963 65 03 42",
    "sg:postcode":"46009",
    "sg:province":"Valencia",
    "sg:website":"www.lambdainformatica.es",
    "wof:name":"Lambda Informatica Y Comunicaciones S.l.",
    "wof:placetype":"venue"
},
  "geometry": {"coordinates":[-0.3743340075,39.4913024902],"type":"Point"}
}