{
  "type": "Feature",
  "properties": {
    "addr:full":"Avda Constitucion (de La), 33 Granada Granada 18014",
    "addr:housenumber":"33",
    "addr:postcode":"18014",
    "addr:street":"Avda Constitucion De La",
    "iso:country":"ES",
    "sg:address":"Avda Constitucion (de La), 33",
    "sg:city":"Granada",
    "sg:orig_category":"Electricidad, Electr\u00d3nica: Material Y Suministros (al Por Mayor)",
    "sg:phone":"+34 958 20 74 05",
    "sg:postcode":"18014",
    "sg:province":"Granada",
    "wof:name":"Bufer Electronica S.l.",
    "wof:placetype":"venue"
},
  "geometry": {"coordinates":[-3.608864069,37.186050415],"type":"Point"}
}