{
  "type": "Feature",
  "properties": {
    "iso:country":"ES",
    "sg:address":"Calle de Triste Condesa, 38",
    "sg:city":"Arenas San Pedro",
    "sg:orig_category":"Abogados",
    "sg:phone":"+34 920 37 04 29",
    "sg:postcode":"05400",
    "sg:province":"\u00c1vila",
    "wof:name":"Asesoria Juridica Milagros Torres",
    "wof:placetype":"venue"
},
  "geometry": {"coordinates":[-5.0875487328,40.2102661133],"type":"Point"}
}