{
  "type": "Feature",
  "properties": {
    "iso:country":"ES",
    "sg:address":"Pase Estacion, 19",
    "sg:city":"Torredelcampo",
    "sg:orig_category":"Imprenta",
    "sg:phone":"+34 953 56 89 73",
    "sg:postcode":"23640",
    "sg:province":"Ja\u00e9n",
    "wof:name":"Didot Impresion Digital S.l.",
    "wof:placetype":"venue"
},
  "geometry": {"coordinates":[-3.8992650509,37.7720832825],"type":"Point"}
}