{
  "type": "Feature",
  "properties": {
    "iso:country":"ES",
    "sg:address":"Calle de Pabellon, S/n",
    "sg:city":"Roda",
    "sg:orig_category":"Granos Y Semillas (producci\u00d3n, Al Por Mayor)",
    "sg:phone":"+34 967 44 08 48",
    "sg:postcode":"02630",
    "sg:province":"Albacete",
    "wof:name":"Diego Cortijo S.l.",
    "wof:placetype":"venue"
},
  "geometry": {"coordinates":[-2.1637969017,39.1990661621],"type":"Point"}
}