{
  "type": "Feature",
  "properties": {
    "addr:full":"Pl Palau Ausit (de), 5 Ripollet Barcelona 08291",
    "addr:postcode":"08291",
    "addr:street":"Pl",
    "iso:country":"ES",
    "sg:address":"Pl Palau Ausit (de), 5",
    "sg:city":"Ripollet",
    "sg:orig_category":"Promotores Constructores",
    "sg:phone":"+34 935 80 45 55",
    "sg:postcode":"08291",
    "sg:province":"Barcelona",
    "wof:name":"Construcciones Dineva S.l.",
    "wof:placetype":"venue"
},
  "geometry": {"coordinates":[2.159719944,41.5019645691],"type":"Point"}
}