{
  "type": "Feature",
  "properties": {
    "addr:full":"Avda Gabriel Miro, 17 Calpe Alicante 03710",
    "addr:housenumber":"17",
    "addr:postcode":"03710",
    "addr:street":"Avda Gabriel Miro",
    "iso:country":"ES",
    "sg:address":"Avda Gabriel Miro, 17",
    "sg:city":"Calpe",
    "sg:orig_category":"Art\u00cdculos De Regalo (al Por Menor)",
    "sg:phone":"+34 965 83 86 00",
    "sg:postcode":"03710",
    "sg:province":"Alicante",
    "wof:name":"Syre  Carmen",
    "wof:placetype":"venue"
},
  "geometry": {"coordinates":[0.0486910008,38.643283844],"type":"Point"}
}