{
  "type": "Feature",
  "properties": {
    "iso:country":"ES",
    "sg:address":"Carr Peru, 29",
    "sg:city":"Gandia",
    "sg:orig_category":"Molduras, Junquillos, Listones Y Molduras Perforadas",
    "sg:phone":"+34 962 96 09 07",
    "sg:postcode":"46700",
    "sg:province":"Valencia",
    "wof:name":"Sistelcom-telemensaje S.a.",
    "wof:placetype":"venue"
},
  "geometry": {"coordinates":[-0.1913339943,38.960735321],"type":"Point"}
}