{
  "type": "Feature",
  "properties": {
    "addr:full":"Calle de Concepcion Arenal, 13 Pardilla Las Palmas 35200",
    "addr:housenumber":"13",
    "addr:postcode":"35200",
    "addr:street":"Calle De Concepcion Arenal;Palmas",
    "iso:country":"ES",
    "sg:address":"Calle de Concepcion Arenal, 13",
    "sg:city":"Pardilla",
    "sg:orig_category":"Fabricaci\u00d3n, Distribuci\u00d3n De Material Para La Climatizaci\u00d3n, Aireaci\u00d3n Y Ventilaci\u00d3n",
    "sg:phone":"+34 928 69 22 62",
    "sg:postcode":"35200",
    "sg:province":"Las Palmas",
    "wof:name":"Rodriguez Blanco Bernardo",
    "wof:placetype":"venue"
},
  "geometry": {"coordinates":[-15.3908967972,28.0105724335],"type":"Point"}
}