{
  "type": "Feature",
  "properties": {
    "iso:country":"ES",
    "sg:address":"Calle de Huertas, 21",
    "sg:city":"Madrid",
    "sg:orig_category":"Librer\u00cdas",
    "sg:phone":"+34 914 29 00 15",
    "sg:postcode":"28014",
    "sg:province":"Madrid",
    "wof:name":"Gil Gil Vicente",
    "wof:placetype":"venue"
},
  "geometry": {"coordinates":[-3.6992900372,40.4138221741],"type":"Point"}
}