{
  "type": "Feature",
  "properties": {
    "addr:full":"Avda Gran Capitan (del), 46 Cordoba C\u00f3rdoba 14006",
    "addr:housenumber":"46",
    "addr:postcode":"14006",
    "addr:street":"Avda Gran Capitan Del;Co\u0301Rdoba",
    "iso:country":"ES",
    "sg:address":"Avda Gran Capitan (del), 46",
    "sg:city":"Cordoba",
    "sg:orig_category":"Sociedades, Compa\u00d1\u00cdas Aseguradoras",
    "sg:phone":"+34 957 49 81 15",
    "sg:postcode":"14006",
    "sg:province":"C\u00f3rdoba",
    "wof:name":"France Telecom Espa\u00d1a S.a.",
    "wof:placetype":"venue"
},
  "geometry": {"coordinates":[-4.7832012177,37.8930664062],"type":"Point"}
}