{
  "type": "Feature",
  "properties": {
    "addr:full":"Avda Burgos (de) (muriedas), 56 Muriedas Cantabria 39600",
    "addr:housenumber":"56",
    "addr:postcode":"39600",
    "addr:street":"Avda Burgos;Muriedas",
    "iso:country":"ES",
    "sg:address":"Avda Burgos (de) (muriedas), 56",
    "sg:city":"Muriedas",
    "sg:orig_category":"Distribuci\u00d3n De Petr\u00d3leo Y Derivados",
    "sg:phone":"+34 942 25 49 65",
    "sg:postcode":"39600",
    "sg:province":"Cantabria",
    "wof:name":"Estacion De Hidrocarburos Muriedas Sl",
    "wof:placetype":"venue"
},
  "geometry": {"coordinates":[-3.8571200371,43.4241294861],"type":"Point"}
}