{
  "type": "Feature",
  "properties": {
    "iso:country":"ES",
    "sg:address":"Calle de Moreras (de Las), 5",
    "sg:city":"Aranjuez",
    "sg:orig_category":"Ortopedia General",
    "sg:phone":"+34 918 91 19 51",
    "sg:postcode":"28300",
    "sg:province":"Madrid",
    "wof:name":"Ortopedico Crispe S.l.",
    "wof:placetype":"venue"
},
  "geometry": {"coordinates":[-3.5971679688,40.0356521606],"type":"Point"}
}