{
  "type": "Feature",
  "properties": {
    "addr:full":"Calle de Cuenca, 13 Santa Pola Alicante 03130",
    "addr:housenumber":"13",
    "addr:postcode":"03130",
    "addr:street":"Calle De Cuenca",
    "iso:country":"ES",
    "sg:address":"Calle de Cuenca, 13",
    "sg:city":"Santa Pola",
    "sg:orig_category":"Alimentaci\u00d3n General (al Por Menor)",
    "sg:phone":"+34 965 41 44 55",
    "sg:postcode":"03130",
    "sg:province":"Alicante",
    "wof:name":"Galindo Clement Jesus Manuel",
    "wof:placetype":"venue"
},
  "geometry": {"coordinates":[-0.5760849118,38.1929244995],"type":"Point"}
}