{
  "type": "Feature",
  "properties": {
    "iso:country":"ES",
    "sg:address":"Calle de Colon, 14",
    "sg:city":"Castellon",
    "sg:orig_category":"Zapatos (al Por Menor)",
    "sg:phone":"+34 964 23 01 28",
    "sg:postcode":"12001",
    "sg:province":"Castell\u00f3n",
    "wof:name":"Amples S.c.",
    "wof:placetype":"venue"
},
  "geometry": {"coordinates":[-0.0369938985,39.9863739014],"type":"Point"}
}