{
  "type": "Feature",
  "properties": {
    "addr:full":"Cami Font Canyes, 48 Terrassa Barcelona 08227",
    "addr:housenumber":"48",
    "addr:postcode":"08227",
    "iso:country":"ES",
    "sg:address":"Cami Font Canyes, 48",
    "sg:city":"Terrassa",
    "sg:orig_category":"Postigos, Persianas Y Celos\u00cdas",
    "sg:phone":"+34 937 83 20 11",
    "sg:postcode":"08227",
    "sg:province":"Barcelona",
    "wof:name":"Percoter S. L.",
    "wof:placetype":"venue"
},
  "geometry": {"coordinates":[2.0512850285,41.5623893738],"type":"Point"}
}