{
  "type": "Feature",
  "properties": {
    "addr:full":"Vte. Portoles, 2 Lliria Valencia 46160",
    "addr:housenumber":"2",
    "addr:postcode":"46160",
    "addr:street":"Portoles",
    "iso:country":"ES",
    "sg:address":"Vte. Portoles, 2",
    "sg:city":"Lliria",
    "sg:orig_category":"Ingeniero",
    "sg:phone":"+34 962 79 31 57",
    "sg:postcode":"46160",
    "sg:province":"Valencia",
    "wof:name":"Proin-proyectos De Ingenieria C.b.",
    "wof:placetype":"venue"
},
  "geometry": {"coordinates":[-0.59542799,39.6267623901],"type":"Point"}
}