{
  "type": "Feature",
  "properties": {
    "iso:country":"ES",
    "sg:address":"Calle de Calvari, 71",
    "sg:city":"Benaguasil",
    "sg:orig_category":"Peluqueros: De Se\u00d1oras",
    "sg:phone":"+34 962 73 04 21",
    "sg:postcode":"46180",
    "sg:province":"Valencia",
    "wof:name":"Gramuntell Gimeno Concepcion",
    "wof:placetype":"venue"
},
  "geometry": {"coordinates":[-0.5881046057,39.5982437134],"type":"Point"}
}