{
  "type": "Feature",
  "properties": {
    "addr:full":"Avda Alcalde Miguel Casta\u00d1o, S/n Le\u00f3n Le\u00f3n 24005",
    "addr:housenumber":"s",
    "addr:postcode":"24005",
    "addr:street":"Avda Alcalde Miguel Castan\u0303O;/ N Leo\u0301N Leo\u0301N",
    "iso:country":"ES",
    "sg:address":"Avda Alcalde Miguel Casta\u00d1o, S/n",
    "sg:city":"Le\u00f3n",
    "sg:orig_category":"Lavado, Limpieza De Veh\u00cdculos",
    "sg:phone":"+34 987 26 19 09",
    "sg:postcode":"24005",
    "sg:province":"Le\u00f3n",
    "wof:name":"Urbaser S.a.",
    "wof:placetype":"venue"
},
  "geometry": {"coordinates":[-5.5675988197,42.5927467346],"type":"Point"}
}