{
  "type": "Feature",
  "properties": {
    "iso:country":"ES",
    "sg:address":"Calle de Jaime Segarra, 67",
    "sg:city":"Alacant",
    "sg:orig_category":"Reposter\u00cdas",
    "sg:phone":"+34 965 24 46 89",
    "sg:postcode":"03012",
    "sg:province":"Alicante",
    "wof:name":"Sucesores De Manuel Torregrosa S.l.",
    "wof:placetype":"venue"
},
  "geometry": {"coordinates":[-0.4808265865,38.3563919067],"type":"Point"}
}