{
  "type": "Feature",
  "properties": {
    "addr:full":"Calle de Cadenas, 19 Cieza Murcia 30530",
    "addr:housenumber":"19",
    "addr:postcode":"30530",
    "addr:street":"Calle De Cadenas",
    "iso:country":"ES",
    "sg:address":"Calle de Cadenas, 19",
    "sg:city":"Cieza",
    "sg:orig_category":"Farmacias",
    "sg:phone":"+34 968 76 03 83",
    "sg:postcode":"30530",
    "sg:province":"Murcia",
    "wof:name":"Garcia Gomez Francisco",
    "wof:placetype":"venue"
},
  "geometry": {"coordinates":[-1.425973773,38.2382888794],"type":"Point"}
}