{
  "type": "Feature",
  "properties": {
    "addr:full":"Carrer de Jordi Camp, 43 Granollers Barcelona 08403",
    "addr:housenumber":"43",
    "addr:postcode":"08403",
    "addr:street":"Carrer De Jordi Camp",
    "iso:country":"ES",
    "sg:address":"Carrer de Jordi Camp, 43",
    "sg:city":"Granollers",
    "sg:orig_category":"Mec\u00c1nico Del Autom\u00d3vil",
    "sg:phone":"+34 938 49 68 23",
    "sg:postcode":"08403",
    "sg:province":"Barcelona",
    "wof:name":"Martinez Membrive Justo",
    "wof:placetype":"venue"
},
  "geometry": {"coordinates":[2.2773931026,41.605304718],"type":"Point"}
}