{
  "type": "Feature",
  "properties": {
    "addr:full":"Calle de Horno, S/n Vega De Ruiponce Valladolid 47609",
    "addr:housenumber":"s / n",
    "addr:postcode":"47609",
    "addr:street":"Calle De Horno",
    "iso:country":"ES",
    "sg:address":"Calle de Horno, S/n",
    "sg:city":"Vega De Ruiponce",
    "sg:orig_category":"Producci\u00d3n, Comercio De Cereales",
    "sg:phone":"+34 983 48 70 05",
    "sg:postcode":"47609",
    "sg:province":"Valladolid",
    "wof:name":"Blanco Antolin S.l.",
    "wof:placetype":"venue"
},
  "geometry": {"coordinates":[-5.1149587631,42.1894607544],"type":"Point"}
}