{
  "type": "Feature",
  "properties": {
    "addr:full":"Avda Doctor Fleming, 7 Do\u00e7a Mencia C\u00f3rdoba 14860",
    "addr:housenumber":"7",
    "addr:postcode":"14860",
    "addr:street":"Avda Doctor Fleming;Co\u0301Rdoba",
    "iso:country":"ES",
    "sg:address":"Avda Doctor Fleming, 7",
    "sg:city":"Do\u00e7a Mencia",
    "sg:orig_category":"Molduras, Junquillos, Listones Y Molduras Perforadas",
    "sg:phone":"+34 957 67 61 10",
    "sg:postcode":"14860",
    "sg:province":"C\u00f3rdoba",
    "wof:name":"Ubeda Gomez Maria Del Rosario",
    "wof:placetype":"venue"
},
  "geometry": {"coordinates":[-4.354929924,37.5529174805],"type":"Point"}
}