{
  "type": "Feature",
  "properties": {
    "iso:country":"ES",
    "sg:address":"Avenida Acceso A Las Americas, S/n",
    "sg:city":"Los Cristianos",
    "sg:orig_category":"Bazares, Art\u00cdculos De Limpieza Y De Cocina (al Por Menor)",
    "sg:phone":"+34 922 75 02 47",
    "sg:postcode":"38650",
    "sg:province":"Santa Cruz De Tenerife",
    "wof:name":"Rinaldi  Mirta Ofelia",
    "wof:placetype":"venue"
},
  "geometry": {"coordinates":[-16.7313289642,28.0631198883],"type":"Point"}
}