{
  "type": "Feature",
  "properties": {
    "addr:full":"Cmno Moncada, 63 Valencia Valencia 46025",
    "addr:housenumber":"63",
    "addr:postcode":"46025",
    "addr:street":"Cmno Moncada",
    "iso:country":"ES",
    "sg:address":"Cmno Moncada, 63",
    "sg:city":"Valencia",
    "sg:orig_category":"Institutos De Belleza",
    "sg:phone":"+34 963 49 80 68",
    "sg:postcode":"46025",
    "sg:province":"Valencia",
    "wof:name":"Casa Reig Maria Dolores",
    "wof:placetype":"venue"
},
  "geometry": {"coordinates":[-0.3791570067,39.4919395447],"type":"Point"}
}