{
  "type": "Feature",
  "properties": {
    "iso:country":"ES",
    "sg:address":"Calle de Moraleja, S/n",
    "sg:city":"Arroyomolinos",
    "sg:orig_category":"Peluquer\u00cdas, Peluquer\u00cda Mixta",
    "sg:phone":"+34 916 09 58 11",
    "sg:postcode":"28939",
    "sg:province":"Madrid",
    "wof:name":"Reflejos Coronado",
    "wof:placetype":"venue"
},
  "geometry": {"coordinates":[-3.9201169014,40.2696990967],"type":"Point"}
}