{
  "type": "Feature",
  "properties": {
    "iso:country":"ES",
    "sg:address":"Av Eduard Toldra, 59",
    "sg:city":"Vilanova I La Geltru",
    "sg:orig_category":"Comercio De Piezas De Recambio Y De Accesorios De Veh\u00cdculos, Veh\u00cdculos Industriales",
    "sg:phone":"+34 938 93 37 61",
    "sg:postcode":"08800",
    "sg:province":"Barcelona",
    "wof:name":"Rueda Aguilera Antonio",
    "wof:placetype":"venue"
},
  "geometry": {"coordinates":[1.734850049,41.2270088196],"type":"Point"}
}