{
  "type": "Feature",
  "properties": {
    "addr:full":"Calle de Bravo Murillo, 39 Madrid Madrid 28015",
    "addr:housenumber":"39",
    "addr:postcode":"madrid;28015",
    "addr:street":"Calle De Bravo Murillo",
    "iso:country":"ES",
    "sg:address":"Calle de Bravo Murillo, 39",
    "sg:city":"Madrid",
    "sg:orig_category":"Iglesia Cat\u00d3lica",
    "sg:phone":"+34 914 46 73 66",
    "sg:postcode":"28015",
    "sg:province":"Madrid",
    "wof:name":"Parroquia De San Cristobal Y San Rafael",
    "wof:placetype":"venue"
},
  "geometry": {"coordinates":[-3.7043251991,40.4372825623],"type":"Point"}
}