{
  "type": "Feature",
  "properties": {
    "addr:full":"Joaquim Agut, 51 Canet De Fals Barcelona 08259",
    "addr:housenumber":"51",
    "addr:postcode":"08259",
    "addr:street":"Agut;Barcelona",
    "iso:country":"ES",
    "sg:address":"Joaquim Agut, 51",
    "sg:city":"Canet De Fals",
    "sg:orig_category":"Transportes De Autom\u00d3viles Y Otros Veh\u00cdculos",
    "sg:phone":"+34 938 36 90 68",
    "sg:postcode":"08259",
    "sg:province":"Barcelona",
    "wof:name":"Oviols Pallares Ester",
    "wof:placetype":"venue"
},
  "geometry": {"coordinates":[1.744977951,41.7602119446],"type":"Point"}
}