{
  "type": "Feature",
  "properties": {
    "iso:country":"ES",
    "sg:address":"Carrer de Major, 67",
    "sg:city":"Sabadell",
    "sg:orig_category":"Reposter\u00cdas",
    "sg:phone":"+34 937 16 17 13",
    "sg:postcode":"08208",
    "sg:province":"Barcelona",
    "wof:name":"Forn De Pa J.armengol S.l.",
    "wof:placetype":"venue"
},
  "geometry": {"coordinates":[2.1002919674,41.5559272766],"type":"Point"}
}