{
  "type": "Feature",
  "properties": {
    "iso:country":"ES",
    "sg:address":"Calle de La Rioja, 7",
    "sg:city":"Madrid",
    "sg:orig_category":"Art\u00cdculos De Decoraci\u00d3n",
    "sg:phone":"+34 917 42 67 35",
    "sg:postcode":"28042",
    "sg:province":"Madrid",
    "wof:name":"Abey Decoracion Comunidad",
    "wof:placetype":"venue"
},
  "geometry": {"coordinates":[-3.589889,40.456436],"type":"Point"}
}