{
  "type": "Feature",
  "properties": {
    "iso:country":"ES",
    "sg:address":"Calle de Trafalgar, 20",
    "sg:city":"Grao",
    "sg:classifiers":[
        {
            "category":"Autos & Motor Vehicles",
            "subcategory":"Automobile Sales",
            "type":"Retail Goods"
        }
    ],
    "sg:phone":"+34 964 28 48 31",
    "sg:postcode":"12100",
    "sg:province":"Castell\u00f3n",
    "wof:name":"Fernandez Tamayo Jose Manuel",
    "wof:placetype":"venue"
},
  "geometry": {"coordinates":[0.0176999997,39.9888801575],"type":"Point"}
}