{
  "type": "Feature",
  "properties": {
    "iso:country":"ES",
    "sg:address":"Carr Calvari, 2",
    "sg:city":"Corbins",
    "sg:orig_category":"Supermercados Y Hipermercados",
    "sg:phone":"+34 973 19 01 69",
    "sg:postcode":"25137",
    "sg:province":"Lleida",
    "wof:name":"Fernandez More Pedro",
    "wof:placetype":"venue"
},
  "geometry": {"coordinates":[0.695825994,41.6915435791],"type":"Point"}
}