{
  "type": "Feature",
  "properties": {
    "iso:country":"ES",
    "sg:address":"Calle de Julian Sanz Iba\u00d1ez, 2",
    "sg:city":"Zaragoza",
    "sg:orig_category":"Peluqueros: De Se\u00d1oras",
    "sg:phone":"+34 976 32 37 11",
    "sg:postcode":"50017",
    "sg:province":"Zaragoza",
    "wof:name":"Valera Molina Antonio",
    "wof:placetype":"venue"
},
  "geometry": {"coordinates":[-0.9153490067,41.6517791748],"type":"Point"}
}