{
  "type": "Feature",
  "properties": {
    "addr:full":"Calle de Villafranca Del Bierzo, 10 Ribadeo Lugo 27700",
    "addr:housenumber":"10",
    "addr:postcode":"27700",
    "addr:street":"Calle De Villafranca Del Bierzo",
    "iso:country":"ES",
    "sg:address":"Calle de Villafranca Del Bierzo, 10",
    "sg:city":"Ribadeo",
    "sg:orig_category":"Arquitectos",
    "sg:phone":"+34 982 13 08 52",
    "sg:postcode":"27700",
    "sg:province":"Lugo",
    "wof:name":"Ernesto Cruzado, Aquitecto, Sl",
    "wof:placetype":"venue"
},
  "geometry": {"coordinates":[-7.0410790443,43.5367698669],"type":"Point"}
}