{
  "type": "Feature",
  "properties": {
    "addr:full":"Av Cubelles, 60 Vilanova I La Geltru Barcelona 08800",
    "addr:housenumber":"60",
    "addr:postcode":"08800",
    "addr:street":"Av Cubelles",
    "iso:country":"ES",
    "sg:address":"Av Cubelles, 60",
    "sg:city":"Vilanova I La Geltru",
    "sg:orig_category":"Agencias Y Agentes Comerciales, Representantes",
    "sg:phone":"+34 938 15 53 76",
    "sg:postcode":"08800",
    "sg:province":"Barcelona",
    "wof:name":"Bosch Abad Carlos",
    "wof:placetype":"venue"
},
  "geometry": {"coordinates":[1.7196099758,41.219909668],"type":"Point"}
}