{
  "type": "Feature",
  "properties": {
    "iso:country":"ES",
    "sg:address":"Av Prat De La Riba, 20",
    "sg:city":"Tarragona",
    "sg:orig_category":"Ropa Para Se\u00d1oras (al Por Menor)",
    "sg:phone":"+34 977 24 36 39",
    "sg:postcode":"43001",
    "sg:province":"Tarragona",
    "wof:name":"Osella Panza Rosa Ramona",
    "wof:placetype":"venue"
},
  "geometry": {"coordinates":[1.2463239431,41.1166038513],"type":"Point"}
}