{
  "type": "Feature",
  "properties": {
    "addr:full":"Calle de Argentina, 22 Coslada Madrid 28820",
    "addr:housenumber":"22",
    "addr:postcode":"28820",
    "addr:street":"Calle De Argentina",
    "iso:country":"ES",
    "sg:address":"Calle de Argentina, 22",
    "sg:city":"Coslada",
    "sg:orig_category":"Lavado, Limpieza De Veh\u00cdculos",
    "sg:phone":"+34 916 72 08 09",
    "sg:postcode":"28820",
    "sg:province":"Madrid",
    "wof:name":"Miranda Abeja Francisco",
    "wof:placetype":"venue"
},
  "geometry": {"coordinates":[-3.54144454,40.4267845154],"type":"Point"}
}