{
  "type": "Feature",
  "properties": {
    "iso:country":"ES",
    "sg:address":"Calle de Linares, 2",
    "sg:city":"Valencia",
    "sg:classifiers":[
        {
            "category":"Personal",
            "subcategory":"Barber",
            "type":"Services"
        }
    ],
    "sg:phone":"+34 963 84 14 60",
    "sg:postcode":"46018",
    "sg:province":"Valencia",
    "sg:tags":[
        "caballeros",
        "de",
        "peluqueros"
    ],
    "wof:name":"Brusel Carrion Jose Julio",
    "wof:placetype":"venue"
},
  "geometry": {"coordinates":[-0.3929530084,39.4685897827],"type":"Point"}
}