{
  "type": "Feature",
  "properties": {
    "iso:country":"ES",
    "sg:address":"Capitan Ramonell Boix, S/n",
    "sg:city":"Palma",
    "sg:orig_category":"Cajas De Ahorro",
    "sg:phone":"+34 971 24 24 53",
    "sg:postcode":"07007",
    "sg:province":"Islas Baleares",
    "wof:name":"Caixa D'estalvis I Pensions De Barcelona",
    "wof:placetype":"venue"
},
  "geometry": {"coordinates":[2.6912350655,39.5560188293],"type":"Point"}
}