{
  "type": "Feature",
  "properties": {
    "iso:country":"ES",
    "sg:address":"Avda Ourense (de), 12",
    "sg:city":"Chantada",
    "sg:orig_category":"Ropa Para Ni\u00d1os (al Por Menor)",
    "sg:phone":"+34 982 46 20 62",
    "sg:postcode":"27500",
    "sg:province":"Lugo",
    "wof:name":"Vazquez Rodriguez Maria Del Mar",
    "wof:placetype":"venue"
},
  "geometry": {"coordinates":[-7.7724027634,42.608341217],"type":"Point"}
}