{
  "type": "Feature",
  "properties": {
    "addr:full":"Carr Duc De Lliria (del), 79 Lliria Valencia 46160",
    "addr:housenumber":"79",
    "addr:postcode":"46160",
    "addr:street":"Carr Duc De Lliria Del",
    "iso:country":"ES",
    "sg:address":"Carr Duc De Lliria (del), 79",
    "sg:city":"Lliria",
    "sg:orig_category":"Comercio De Piezas De Recambio Y De Accesorios De Veh\u00cdculos, Veh\u00cdculos Industriales",
    "sg:phone":"+34 962 78 02 63",
    "sg:postcode":"46160",
    "sg:province":"Valencia",
    "wof:name":"Civera Marquino Salvador",
    "wof:placetype":"venue"
},
  "geometry": {"coordinates":[-0.5952839851,39.6247406006],"type":"Point"}
}