{
  "type": "Feature",
  "properties": {
    "iso:country":"ES",
    "sg:address":"Ptda Benadresa, 39",
    "sg:city":"Castellon De La Plana",
    "sg:orig_category":"Fabricaci\u00d3n De Enlosados, Soler\u00cdas",
    "sg:phone":"+34 964 24 22 48",
    "sg:postcode":"12006",
    "sg:province":"Castell\u00f3n",
    "wof:name":"Garcia Nebot Emilio",
    "wof:placetype":"venue"
},
  "geometry": {"coordinates":[-0.1404139996,40.0213813782],"type":"Point"}
}