{
  "type": "Feature",
  "properties": {
    "addr:full":"Avda Andalucia (de), 33 Fuente Alamo Murcia 30320",
    "addr:housenumber":"33",
    "addr:postcode":"30320",
    "addr:street":"Avda Andalucia De",
    "iso:country":"ES",
    "sg:address":"Avda Andalucia (de), 33",
    "sg:city":"Fuente Alamo",
    "sg:orig_category":"Promotores Constructores",
    "sg:phone":"+34 968 59 71 85",
    "sg:postcode":"30320",
    "sg:province":"Murcia",
    "wof:name":"Proinmo Zamora Pagan S.l.",
    "wof:placetype":"venue"
},
  "geometry": {"coordinates":[-1.1771639585,37.7239685059],"type":"Point"}
}