{
  "type": "Feature",
  "properties": {
    "iso:country":"ES",
    "sg:address":"Carr De Vinar S, 3",
    "sg:city":"Benicarlo",
    "sg:orig_category":"Telas Y Sedas (al Por Menor)",
    "sg:phone":"+34 964 47 07 93",
    "sg:postcode":"12580",
    "sg:province":"Castell\u00f3n",
    "wof:name":"Lores Larrosa Joaquin",
    "wof:placetype":"venue"
},
  "geometry": {"coordinates":[0.4030939937,40.4407463074],"type":"Point"}
}