{
  "type": "Feature",
  "properties": {
    "addr:full":"Calle de Rafaela De Antonio, 2 Avila \u00c1vila 05002",
    "addr:housenumber":"2",
    "addr:postcode":"05002",
    "addr:street":"Calle De Rafaela De Antonio;A\u0301Vila",
    "iso:country":"ES",
    "sg:address":"Calle de Rafaela De Antonio, 2",
    "sg:city":"Avila",
    "sg:orig_category":"Asesor\u00cda Sobre Comunicaci\u00d3n De Empresas",
    "sg:phone":"+34 920 22 13 00",
    "sg:postcode":"05002",
    "sg:province":"\u00c1vila",
    "wof:name":"Orgaz Jimenez Carlos",
    "wof:placetype":"venue"
},
  "geometry": {"coordinates":[-4.7002577782,40.6487350464],"type":"Point"}
}