{
  "type": "Feature",
  "properties": {
    "iso:country":"ES",
    "sg:address":"Josep M. Pi I Sunyer, 20",
    "sg:city":"S. Joan Despi",
    "sg:orig_category":"Ropa Para Se\u00d1oras (al Por Menor)",
    "sg:phone":"+34 933 73 61 73",
    "sg:postcode":"08970",
    "sg:province":"Barcelona",
    "wof:name":"Molina Costa Alfredo",
    "wof:placetype":"venue"
},
  "geometry": {"coordinates":[2.073554039,41.3669166565],"type":"Point"}
}