{
  "type": "Feature",
  "properties": {
    "iso:country":"ES",
    "sg:address":"Calle de Elizkale, 11",
    "sg:city":"Zumarraga",
    "sg:classifiers":[
        {
            "category":"Autos & Motor Vehicles",
            "subcategory":"Automobile Sales",
            "type":"Retail Goods"
        }
    ],
    "sg:phone":"+34 943 72 04 52",
    "sg:postcode":"20700",
    "sg:province":"Guip\u00f9zcoa",
    "wof:name":"Gipuzkoarena Heziketa S.l.l.",
    "wof:placetype":"venue"
},
  "geometry": {"coordinates":[-2.3128829002,43.0885505676],"type":"Point"}
}