{
  "type": "Feature",
  "properties": {
    "addr:full":"Calle de Corregidor Francisco De Molina, 18 Malaga M\u00e1laga 29006",
    "addr:housenumber":"18",
    "addr:postcode":"29006",
    "addr:street":"Calle De Corregidor Francisco De Molina;Ma\u0301Laga",
    "iso:country":"ES",
    "sg:address":"Calle de Corregidor Francisco De Molina, 18",
    "sg:city":"Malaga",
    "sg:classifiers":[
        {
            "category":"Autos & Motor Vehicles",
            "subcategory":"Automobile Sales",
            "type":"Retail Goods"
        }
    ],
    "sg:phone":"+34 952 34 54 84",
    "sg:postcode":"29006",
    "sg:province":"M\u00e1laga",
    "sg:website":"www.torcal.es",
    "wof:name":"Autoescuelas Torcal S.l.",
    "wof:placetype":"venue"
},
  "geometry": {"coordinates":[-4.4521389008,36.7129631042],"type":"Point"}
}