{
  "type": "Feature",
  "properties": {
    "addr:full":"Calle de Gaminiz Kalea, 3 Plentzia Vizcaya 48620",
    "addr:housenumber":"3",
    "addr:postcode":"48620",
    "addr:street":"Calle De Gaminiz Kalea",
    "iso:country":"ES",
    "sg:address":"Calle de Gaminiz Kalea, 3",
    "sg:city":"Plentzia",
    "sg:orig_category":"Plomeros",
    "sg:phone":"+34 946 77 05 98",
    "sg:postcode":"48620",
    "sg:province":"Vizcaya",
    "wof:name":"Fontaneria Plentzia S.l.",
    "wof:placetype":"venue"
},
  "geometry": {"coordinates":[-2.9459908009,43.40442276],"type":"Point"}
}