{
  "type": "Feature",
  "properties": {
    "addr:full":"Avda Luis Espada, 60 Verin Ourense 32600",
    "addr:housenumber":"60",
    "addr:postcode":"32600",
    "addr:street":"Avda Luis Espada",
    "iso:country":"ES",
    "sg:address":"Avda Luis Espada, 60",
    "sg:city":"Verin",
    "sg:orig_category":"Ropa Para Se\u00d1oras Y Caballeros (al Por Menor)",
    "sg:phone":"+34 988 41 07 81",
    "sg:postcode":"32600",
    "sg:province":"Ourense",
    "wof:name":"Mario Cid Verin S.l.",
    "wof:placetype":"venue"
},
  "geometry": {"coordinates":[-7.4384818077,41.940322876],"type":"Point"}
}