{
  "type": "Feature",
  "properties": {
    "addr:full":"Ctra. Galapagar-las Rozas, Km. 0018,8 Galapagar Madrid 28260",
    "addr:postcode":"28260",
    "addr:street":"Ctra. Galapagar-Las Rozas Km. 0018,8",
    "iso:country":"ES",
    "sg:address":"Ctra. Galapagar-las Rozas, Km. 0018,8",
    "sg:city":"Galapagar",
    "sg:orig_category":"Producci\u00d3n, Venta De Productos De Agricultura Biol\u00d3gica",
    "sg:phone":"+34 918 58 33 22",
    "sg:postcode":"28260",
    "sg:province":"Madrid",
    "wof:name":"Arroyo Torero S.l.",
    "wof:placetype":"venue"
},
  "geometry": {"coordinates":[-3.9575195312,40.5764389038],"type":"Point"}
}