{
  "type": "Feature",
  "properties": {
    "addr:full":"Calle de Zamora, 3 Puerto Cruz Santa Cruz De Tenerife 38400",
    "addr:housenumber":"3",
    "addr:postcode":"38400",
    "addr:street":"Calle De Zamora;Cruz",
    "iso:country":"ES",
    "sg:address":"Calle de Zamora, 3",
    "sg:city":"Puerto Cruz",
    "sg:orig_category":"M\u00c9dicos: Ginecolog\u00cda Y Obstetricia",
    "sg:phone":"+34 922 38 04 02",
    "sg:postcode":"38400",
    "sg:province":"Santa Cruz De Tenerife",
    "wof:name":"Delgado Gomez Luis",
    "wof:placetype":"venue"
},
  "geometry": {"coordinates":[-16.5475521088,28.4165916443],"type":"Point"}
}