{
  "type": "Feature",
  "properties": {
    "addr:full":"Carrer de Tarragona, 43 Senia Tarragona 43560",
    "addr:housenumber":"43",
    "addr:postcode":"43560",
    "addr:street":"Carrer De Tarragona",
    "iso:country":"ES",
    "sg:address":"Carrer de Tarragona, 43",
    "sg:city":"Senia",
    "sg:orig_category":"Bancos",
    "sg:phone":"+34 977 57 54 58",
    "sg:postcode":"43560",
    "sg:province":"Tarragona",
    "wof:name":"Banco Popular Espa\u00f1ol S.a.",
    "wof:placetype":"venue"
},
  "geometry": {"coordinates":[0.2846480012,40.6340408325],"type":"Point"}
}