{
  "type": "Feature",
  "properties": {
    "addr:full":"Calle de Conde De Pe\u00d1alver, 82 Madrid Madrid 28006",
    "addr:housenumber":"82",
    "addr:postcode":"madrid;28006",
    "addr:street":"Calle De Conde De Pen\u0303Alver",
    "iso:country":"ES",
    "sg:address":"Calle de Conde De Pe\u00d1alver, 82",
    "sg:city":"Madrid",
    "sg:orig_category":"Restaurantes",
    "sg:phone":"+34 914 02 30 20",
    "sg:postcode":"28006",
    "sg:province":"Madrid",
    "wof:name":"Jocqgenma S.l.",
    "wof:placetype":"venue"
},
  "geometry": {"coordinates":[-3.6750504971,40.432975769],"type":"Point"}
}