{
  "type": "Feature",
  "properties": {
    "addr:full":"Plaz Baco, S/n Selaya Cantabria 39696",
    "addr:housenumber":"s / n",
    "addr:postcode":"39696",
    "addr:street":"Baco",
    "iso:country":"ES",
    "sg:address":"Plaz Baco, S/n",
    "sg:city":"Selaya",
    "sg:orig_category":"Molduras, Junquillos, Listones Y Molduras Perforadas",
    "sg:phone":"+34 942 59 02 92",
    "sg:postcode":"39696",
    "sg:province":"Cantabria",
    "wof:name":"Piculin C.b.",
    "wof:placetype":"venue"
},
  "geometry": {"coordinates":[-3.8065640926,43.2147674561],"type":"Point"}
}