{
  "type": "Feature",
  "properties": {
    "addr:full":"Tor. Tortuguer (els Pinetons), 47 Ripollet Barcelona 08291",
    "addr:housenumber":"47",
    "addr:postcode":"08291",
    "addr:street":"Pinetons",
    "iso:country":"ES",
    "sg:address":"Tor. Tortuguer (els Pinetons), 47",
    "sg:city":"Ripollet",
    "sg:orig_category":"Fabricaci\u00d3n De Moldes Y Modelos",
    "sg:phone":"+34 936 92 77 77",
    "sg:postcode":"08291",
    "sg:province":"Barcelona",
    "wof:name":"Moldes Calibres Y Prototipos S.a.",
    "wof:placetype":"venue"
},
  "geometry": {"coordinates":[2.1489770412,41.5094833374],"type":"Point"}
}