{
  "type": "Feature",
  "properties": {
    "addr:full":"Calle de Celeste, 15 Madrid Madrid 28043",
    "addr:housenumber":"15",
    "addr:postcode":"madrid;28043",
    "addr:street":"Calle De Celeste",
    "iso:country":"ES",
    "sg:address":"Calle de Celeste, 15",
    "sg:city":"Madrid",
    "sg:orig_category":"Asesor\u00cdas Y Estudios Financieros",
    "sg:phone":"+34 914 15 15 55",
    "sg:postcode":"28043",
    "sg:province":"Madrid",
    "wof:name":"Mu\u00f1iz Arg\u00fcelles Vicente",
    "wof:placetype":"venue"
},
  "geometry": {"coordinates":[-3.6577365398,40.4562759399],"type":"Point"}
}