{
  "type": "Feature",
  "properties": {
    "addr:full":"Calle de San Jose, 54 Atarfe Granada 18230",
    "addr:housenumber":"54",
    "addr:postcode":"18230",
    "addr:street":"Calle De San",
    "iso:country":"ES",
    "sg:address":"Calle de San Jose, 54",
    "sg:city":"Atarfe",
    "sg:orig_category":"Mec\u00c1nico Del Autom\u00d3vil",
    "sg:phone":"+34 958 43 83 07",
    "sg:postcode":"18230",
    "sg:province":"Granada",
    "wof:name":"Talleres Palma Barea S.l.",
    "wof:placetype":"venue"
},
  "geometry": {"coordinates":[-3.6598525047,37.2059326172],"type":"Point"}
}