{
  "type": "Feature",
  "properties": {
    "addr:full":"Calle de Sevilla, 22 Fuengirola M\u00e1laga 29640",
    "addr:housenumber":"22",
    "addr:postcode":"29640",
    "addr:street":"Calle De Sevilla;Ma\u0301Laga",
    "iso:country":"ES",
    "sg:address":"Calle de Sevilla, 22",
    "sg:city":"Fuengirola",
    "sg:orig_category":"Muebles",
    "sg:phone":"+34 952 47 02 98",
    "sg:postcode":"29640",
    "sg:province":"M\u00e1laga",
    "wof:name":"Lopez Vera Juan",
    "wof:placetype":"venue"
},
  "geometry": {"coordinates":[-4.6285238266,36.5411529541],"type":"Point"}
}