{
  "type": "Feature",
  "properties": {
    "addr:full":"Calle de Hermosilla, 48 Madrid Madrid 28001",
    "addr:housenumber":"48",
    "addr:postcode":"madrid;28001",
    "addr:street":"Calle De Hermosilla",
    "iso:country":"ES",
    "sg:address":"Calle de Hermosilla, 48",
    "sg:city":"Madrid",
    "sg:orig_category":"Asesor\u00cda Sobre Comunicaci\u00d3n De Empresas",
    "sg:phone":"+34 915 77 40 14",
    "sg:postcode":"28001",
    "sg:province":"Madrid",
    "sg:website":"www.idetra.es",
    "wof:name":"Innovacion Desarrollo Y Transferencia De Tecnologia S.a.",
    "wof:placetype":"venue"
},
  "geometry": {"coordinates":[-3.6818749905,40.4260978699],"type":"Point"}
}