{
  "type": "Feature",
  "properties": {
    "iso:country":"ES",
    "sg:address":"Avda Lope De Figueroa, 45",
    "sg:city":"Alcala Henares",
    "sg:orig_category":"Guarder\u00cdas",
    "sg:phone":"+34 918 81 06 54",
    "sg:postcode":"28804",
    "sg:province":"Madrid",
    "wof:name":"Ruiz De La Hermosa Valdepe\u00f1as Maria Del Pilar",
    "wof:placetype":"venue"
},
  "geometry": {"coordinates":[-3.348995924,40.4883308411],"type":"Point"}
}