{
  "type": "Feature",
  "properties": {
    "addr:full":"Avda Nuestra Se\u00d1ora De Atocha, 16 Vista Alegre Murcia 30007",
    "addr:housenumber":"16",
    "addr:postcode":"30007",
    "addr:street":"Avda Nuestra Sen\u0303Ora De Atocha",
    "iso:country":"ES",
    "sg:address":"Avda Nuestra Se\u00d1ora De Atocha, 16",
    "sg:city":"Vista Alegre",
    "sg:orig_category":"Cajas De Ahorro",
    "sg:phone":"+34 968 27 21 62",
    "sg:postcode":"30007",
    "sg:province":"Murcia",
    "sg:website":"www.cam.es",
    "wof:name":"Caja De Ahorros Del Mediterraneo",
    "wof:placetype":"venue"
},
  "geometry": {"coordinates":[-1.1142389774,37.9970092773],"type":"Point"}
}