{
  "type": "Feature",
  "properties": {
    "iso:country":"ES",
    "sg:address":"Ctra. Valencia-pedralba, S/n",
    "sg:city":"Pedralba",
    "sg:orig_category":"Agricultura: Abastecimiento Y Cosechado (negocio)",
    "sg:phone":"+34 962 70 77 72",
    "sg:postcode":"46164",
    "sg:province":"Valencia",
    "wof:name":"Productos Agricolas Andres Y Diago S.l.",
    "wof:placetype":"venue"
},
  "geometry": {"coordinates":[-0.7244750261,39.604801178],"type":"Point"}
}