{
  "type": "Feature",
  "properties": {
    "iso:country":"ES",
    "sg:address":"Ctra N-152, Km. 0021,2",
    "sg:city":"Can Gosc",
    "sg:orig_category":"Agentes, Concesionarios Y Sucursales De Camiones Y Veh\u00cdculos Industriales",
    "sg:phone":"+34 935 62 45 02",
    "sg:postcode":"08150",
    "sg:province":"Barcelona",
    "sg:website":"www.man-v-i.es",
    "wof:name":"Man Vehiculos Industriales (espa\u00d1a",
    "wof:placetype":"venue"
},
  "geometry": {"coordinates":[2.2319469452,41.5694198608],"type":"Point"}
}