{
  "type": "Feature",
  "properties": {
    "addr:full":"Calle de Via Taurina, 1 Barbastro Huesca 22300",
    "addr:housenumber":"1",
    "addr:postcode":"22300",
    "addr:street":"Calle De Via Taurina",
    "iso:country":"ES",
    "sg:address":"Calle de Via Taurina, 1",
    "sg:city":"Barbastro",
    "sg:orig_category":"Muebles, Minoristas",
    "sg:phone":"+34 974 31 40 94",
    "sg:postcode":"22300",
    "sg:province":"Huesca",
    "sg:website":"www.barbastro.com/armi2",
    "wof:name":"Muebles Armi 2 S.l.",
    "wof:placetype":"venue"
},
  "geometry": {"coordinates":[0.1208214983,42.0347251892],"type":"Point"}
}