{
  "type": "Feature",
  "properties": {
    "addr:full":"Ctra Nacional 601, Km. 0086,6 Tabanera Luenga Segovia 40291",
    "addr:postcode":"40291",
    "addr:street":"Ctra Nacional 601 Km. 0086,6 Tabanera Luenga Segovia",
    "iso:country":"ES",
    "sg:address":"Ctra Nacional 601, Km. 0086,6",
    "sg:city":"Tabanera Luenga",
    "sg:orig_category":"Charcuter\u00cdas (al Por Menor)",
    "sg:phone":"+34 921 56 19 06",
    "sg:postcode":"40291",
    "sg:province":"Segovia",
    "wof:name":"Hecaber S.a.l.",
    "wof:placetype":"venue"
},
  "geometry": {"coordinates":[-4.2393989563,41.0971755981],"type":"Point"}
}