{
  "type": "Feature",
  "properties": {
    "iso:country":"ES",
    "sg:address":"Pase Extremadura, 225",
    "sg:city":"Monesterio",
    "sg:orig_category":"Empresas De Electricidad En General",
    "sg:phone":"+34 924 51 71 53",
    "sg:postcode":"06260",
    "sg:province":"Badajoz",
    "wof:name":"Electrica Monesterio S. A.",
    "wof:placetype":"venue"
},
  "geometry": {"coordinates":[-6.2714591026,38.0864181519],"type":"Point"}
}