{
  "type": "Feature",
  "properties": {
    "addr:full":"Urbz. Bahia De Pedre\u00f1a, 3 Pedre\u00f1a Cantabria 39130",
    "addr:housenumber":"3",
    "addr:postcode":"39130",
    "addr:street":"Bahia;Pedren\u0303A",
    "iso:country":"ES",
    "sg:address":"Urbz. Bahia De Pedre\u00f1a, 3",
    "sg:city":"Pedre\u00f1a",
    "sg:orig_category":"Centros Empresariales",
    "sg:phone":"+34 942 50 06 15",
    "sg:postcode":"39130",
    "sg:province":"Cantabria",
    "wof:name":"Qualo S.l.",
    "wof:placetype":"venue"
},
  "geometry": {"coordinates":[-3.774107933,43.436794281],"type":"Point"}
}