{
  "type": "Feature",
  "properties": {
    "iso:country":"ES",
    "sg:address":"Comp Puerto Deportivo Aguadulce, 1",
    "sg:city":"Aguadulce",
    "sg:orig_category":"Bares, Piano",
    "sg:phone":"+34 950 34 93 93",
    "sg:postcode":"04720",
    "sg:province":"Almer\u00eda",
    "wof:name":"Peninsula Del Puerto S.l.",
    "wof:placetype":"venue"
},
  "geometry": {"coordinates":[-2.5974500179,36.801410675],"type":"Point"}
}