{
  "type": "Feature",
  "properties": {
    "iso:country":"ES",
    "sg:address":"Calle de Luis Chamizo, 35",
    "sg:city":"Don Benito",
    "sg:orig_category":"Telas Y Sedas (al Por Menor)",
    "sg:phone":"+34 924 80 35 72",
    "sg:postcode":"06400",
    "sg:province":"Badajoz",
    "wof:name":"Martin-mora Quiros Maria Victoria",
    "wof:placetype":"venue"
},
  "geometry": {"coordinates":[-5.8595290184,38.9615783691],"type":"Point"}
}