{
  "type": "Feature",
  "properties": {
    "iso:country":"ES",
    "sg:address":"Carr Bernat De Santa Eugenia, 78",
    "sg:city":"Santa Maria Del Cami",
    "sg:orig_category":"Electrodom\u00c9sticos (fabricaci\u00d3n, Al Por Mayor)",
    "sg:phone":"+34 971 62 11 12",
    "sg:postcode":"07320",
    "sg:province":"Islas Baleares",
    "wof:name":"Germans Verdera Oliver S.l.",
    "wof:placetype":"venue"
},
  "geometry": {"coordinates":[2.7695550919,39.6493873596],"type":"Point"}
}