{
  "type": "Feature",
  "properties": {
    "iso:country":"ES",
    "sg:address":"Pl Amadeu Borras, 6",
    "sg:city":"Cardedeu",
    "sg:orig_category":"Art\u00cdculos De Decoraci\u00d3n",
    "sg:phone":"+34 938 45 44 38",
    "sg:postcode":"08440",
    "sg:province":"Barcelona",
    "sg:website":"www.mobelsistem.com",
    "wof:name":"Representaciones Mobel Systems S.l.",
    "wof:placetype":"venue"
},
  "geometry": {"coordinates":[2.3591001034,41.6405105591],"type":"Point"}
}