{
  "type": "Feature",
  "properties": {
    "iso:country":"ES",
    "sg:address":"Calle de Olmo, 21",
    "sg:city":"Villamalea",
    "sg:orig_category":"Herboristas (al Por Menor)",
    "sg:phone":"+34 967 48 34 12",
    "sg:postcode":"02270",
    "sg:province":"Albacete",
    "wof:name":"Verde Rubio Maria Francisca",
    "wof:placetype":"venue"
},
  "geometry": {"coordinates":[-1.5990680456,39.3602142334],"type":"Point"}
}