{
  "type": "Feature",
  "properties": {
    "iso:country":"ES",
    "sg:address":"Carrer de Lluis Sagnier, 64",
    "sg:city":"Barcelona",
    "sg:orig_category":"Aparatos De Medida, Control, Regulaci\u00d3n Y Detecci\u00d3n",
    "sg:phone":"+34 934 55 16 96",
    "sg:postcode":"08032",
    "sg:province":"Barcelona",
    "wof:name":"Proyectos Y Regulacion S.l.",
    "wof:placetype":"venue"
},
  "geometry": {"coordinates":[2.1737399101,41.4252586365],"type":"Point"}
}