{
  "type": "Feature",
  "properties": {
    "addr:full":"Calle de Villalba, 5 Luque C\u00f3rdoba 14880",
    "addr:housenumber":"5",
    "addr:postcode":"14880",
    "addr:street":"Calle De Villalba;Co\u0301Rdoba",
    "iso:country":"ES",
    "sg:address":"Calle de Villalba, 5",
    "sg:city":"Luque",
    "sg:classifiers":[
        {
            "category":"Taxi",
            "type":"Transportation"
        }
    ],
    "sg:phone":"+34 957 66 70 33",
    "sg:postcode":"14880",
    "sg:province":"C\u00f3rdoba",
    "wof:name":"Blanco Cardenas Fernanda",
    "wof:placetype":"venue"
},
  "geometry": {"coordinates":[-4.278067112,37.5577888489],"type":"Point"}
}