{
  "type": "Feature",
  "properties": {
    "addr:full":"Plaz Catedral, S/n Huesca Huesca 22002",
    "addr:housenumber":"s / n",
    "addr:postcode":"22002",
    "iso:country":"ES",
    "sg:address":"Plaz Catedral, S/n",
    "sg:city":"Huesca",
    "sg:orig_category":"Museos",
    "sg:phone":"+34 974 23 10 99",
    "sg:postcode":"22002",
    "sg:province":"Huesca",
    "wof:name":"Obispado De Huesca",
    "wof:placetype":"venue"
},
  "geometry": {"coordinates":[-0.4087690115,42.1403007507],"type":"Point"}
}