{
  "type": "Feature",
  "properties": {
    "addr:full":"Poli Cantabria, 62 Logro\u00f1o La Rioja 26006",
    "addr:housenumber":"62",
    "addr:postcode":"26006",
    "addr:street":"Cantabria;Rioja",
    "iso:country":"ES",
    "sg:address":"Poli Cantabria, 62",
    "sg:city":"Logro\u00f1o",
    "sg:orig_category":"Comercio De Piezas De Recambio Y De Accesorios De Veh\u00cdculos, Veh\u00cdculos Industriales",
    "sg:phone":"+34 941 27 05 31",
    "sg:postcode":"26006",
    "sg:province":"La Rioja",
    "wof:name":"Regenauto S.a.",
    "wof:placetype":"venue"
},
  "geometry": {"coordinates":[-2.4036989212,42.46043396],"type":"Point"}
}