{
  "type": "Feature",
  "properties": {
    "iso:country":"ES",
    "sg:address":"Calle de Roma, 1",
    "sg:city":"Valdemoro",
    "sg:orig_category":"Agentes, Concesionarios Y Sucursales De Veh\u00cdculos",
    "sg:phone":"+34 918 09 40 44",
    "sg:postcode":"28340",
    "sg:province":"Madrid",
    "wof:name":"J M Moral Sl",
    "wof:placetype":"venue"
},
  "geometry": {"coordinates":[-3.6836791039,40.2108001709],"type":"Point"}
}