{
  "type": "Feature",
  "properties": {
    "addr:full":"Calle de San Silvestre, 8 Salamanca Salamanca 37007",
    "addr:housenumber":"8",
    "addr:postcode":"37007",
    "addr:street":"Calle De San Silvestre",
    "iso:country":"ES",
    "sg:address":"Calle de San Silvestre, 8",
    "sg:city":"Salamanca",
    "sg:orig_category":"Alimentaci\u00d3n General (al Por Menor)",
    "sg:phone":"+34 923 21 44 82",
    "sg:postcode":"37007",
    "sg:province":"Salamanca",
    "wof:name":"Mateos Gonzalez Isabel",
    "wof:placetype":"venue"
},
  "geometry": {"coordinates":[-5.6716098785,40.9632263184],"type":"Point"}
}