{
  "type": "Feature",
  "properties": {
    "iso:country":"ES",
    "sg:address":"Elena Fortun, -",
    "sg:city":"Abades",
    "sg:orig_category":"Iglesia Cat\u00d3lica",
    "sg:phone":"+34 921 49 52 18",
    "sg:postcode":"40141",
    "sg:province":"Segovia",
    "wof:name":"C. Pablo Gonzalez Caro",
    "wof:placetype":"venue"
},
  "geometry": {"coordinates":[-4.2702608109,40.9153938293],"type":"Point"}
}