{
  "type": "Feature",
  "properties": {
    "iso:country":"ES",
    "sg:address":"Pase Castellana, 153",
    "sg:city":"Madrid",
    "sg:orig_category":"Abogados",
    "sg:phone":"+34 915 72 09 02",
    "sg:postcode":"28046",
    "sg:province":"Madrid",
    "wof:name":"Chillon Loarte Pablo",
    "wof:placetype":"venue"
},
  "geometry": {"coordinates":[-3.6904349327,40.4609375],"type":"Point"}
}