{
  "type": "Feature",
  "properties": {
    "addr:full":"Carrer de Felip Ii, 143 Barcelona Barcelona 08027",
    "addr:housenumber":"143",
    "addr:postcode":"08027",
    "addr:street":"Carrer De Felip Ii",
    "iso:country":"ES",
    "sg:address":"Carrer de Felip Ii, 143",
    "sg:city":"Barcelona",
    "sg:orig_category":"Bisuteros (fabricaci\u00d3n, Al Por Mayor)",
    "sg:phone":"+34 933 52 74 56",
    "sg:postcode":"08027",
    "sg:province":"Barcelona",
    "wof:name":"Comercial Japsa S. A.",
    "wof:placetype":"venue"
},
  "geometry": {"coordinates":[2.1834430695,41.4228782654],"type":"Point"}
}