{
  "type": "Feature",
  "properties": {
    "addr:full":"Labeaga Kalea, 60 Urretxu Guip\u00f9zcoa 20700",
    "addr:housenumber":"60",
    "addr:postcode":"20700",
    "addr:street":"Labeaga Kalea;Guipu\u0300Zcoa",
    "iso:country":"ES",
    "sg:address":"Labeaga Kalea, 60",
    "sg:city":"Urretxu",
    "sg:orig_category":"Farmacias",
    "sg:phone":"+34 943 72 05 21",
    "sg:postcode":"20700",
    "sg:province":"Guip\u00f9zcoa",
    "wof:name":"Arcelus Arbulu Maria Del Carmen",
    "wof:placetype":"venue"
},
  "geometry": {"coordinates":[-2.3195879459,43.0893821716],"type":"Point"}
}