{
  "type": "Feature",
  "properties": {
    "iso:country":"ES",
    "sg:address":"Calle de Jose Zorrilla, 7",
    "sg:city":"Palencia",
    "sg:orig_category":"Abogados",
    "sg:phone":"+34 979 70 18 47",
    "sg:postcode":"34001",
    "sg:province":"Palencia",
    "wof:name":"Vargas Torres Maria Isabel",
    "wof:placetype":"venue"
},
  "geometry": {"coordinates":[-4.5312161446,42.0114517212],"type":"Point"}
}