{
  "type": "Feature",
  "properties": {
    "addr:full":"Av Ramon Folch, 3 Girona Girona 17001",
    "addr:housenumber":"3",
    "addr:postcode":"17001",
    "addr:street":"Av Ramon Folch",
    "iso:country":"ES",
    "sg:address":"Av Ramon Folch, 3",
    "sg:city":"Girona",
    "sg:orig_category":"Caf\u00c9s, Bares, Cervecer\u00cdas",
    "sg:phone":"+34 872 08 01 72",
    "sg:postcode":"17001",
    "sg:province":"Girona",
    "wof:name":"Girona Oci S. L.",
    "wof:placetype":"venue"
},
  "geometry": {"coordinates":[2.8231539726,41.9859886169],"type":"Point"}
}