{
  "type": "Feature",
  "properties": {
    "iso:country":"ES",
    "sg:address":"Afores, S/n",
    "sg:city":"Fontcoberta",
    "sg:orig_category":"Empresas De Carpinter\u00cda",
    "sg:phone":"+34 972 19 04 02",
    "sg:postcode":"17833",
    "sg:province":"Girona",
    "wof:name":"Ponsi Sabate Joaquim",
    "wof:placetype":"venue"
},
  "geometry": {"coordinates":[2.7903430462,42.142791748],"type":"Point"}
}