{
  "type": "Feature",
  "properties": {
    "iso:country":"ES",
    "sg:address":"Avda Chapi, 32",
    "sg:city":"Elda",
    "sg:orig_category":"Inform\u00c1tica, Ofim\u00c1tica (estudios, Asesor\u00cda, Ingenier\u00cda, Formaci\u00d3n)",
    "sg:phone":"+34 966 98 13 14",
    "sg:postcode":"03600",
    "sg:province":"Alicante",
    "wof:name":"Fundacion Ficia",
    "wof:placetype":"venue"
},
  "geometry": {"coordinates":[-0.794254005,38.4734573364],"type":"Point"}
}