{
  "type": "Feature",
  "properties": {
    "iso:country":"ES",
    "sg:address":"Plaz Corredera, 13",
    "sg:city":"Calasparra",
    "sg:orig_category":"Reposter\u00cdas",
    "sg:phone":"+34 968 74 51 82",
    "sg:postcode":"30420",
    "sg:province":"Murcia",
    "wof:name":"Intertecno S.c.",
    "wof:placetype":"venue"
},
  "geometry": {"coordinates":[-1.697846055,38.2309913635],"type":"Point"}
}