{
  "type": "Feature",
  "properties": {
    "addr:full":"Pasaje Pio X, 3 Javea Alicante 03730",
    "addr:housenumber":"3",
    "addr:postcode":"03730",
    "addr:street":"Pasaje Pio X",
    "iso:country":"ES",
    "sg:address":"Pasaje Pio X, 3",
    "sg:city":"Javea",
    "sg:orig_category":"Heladeros",
    "sg:phone":"+34 965 79 07 96",
    "sg:postcode":"03730",
    "sg:province":"Alicante",
    "wof:name":"Espi Cremades Eliseo",
    "wof:placetype":"venue"
},
  "geometry": {"coordinates":[0.1819150001,38.7957572937],"type":"Point"}
}