{
  "type": "Feature",
  "properties": {
    "iso:country":"ES",
    "sg:address":"Calle de Medico Rodriguez, 24",
    "sg:city":"Montemayor",
    "sg:orig_category":"Formaci\u00d3n Continuada (variada)",
    "sg:phone":"+34 957 38 42 28",
    "sg:postcode":"14530",
    "sg:province":"C\u00f3rdoba",
    "wof:name":"Alferez Povedano Ana",
    "wof:placetype":"venue"
},
  "geometry": {"coordinates":[-4.7009496689,37.6487770081],"type":"Point"}
}