{
  "type": "Feature",
  "properties": {
    "iso:country":"ES",
    "sg:address":"Rua Castro, 17",
    "sg:city":"Betanzos",
    "sg:orig_category":"Arquitectos",
    "sg:phone":"+34 981 77 16 25",
    "sg:postcode":"15300",
    "sg:province":"La Coru\u00f1a",
    "wof:name":"Erias Estudio Tecnico S.l",
    "wof:placetype":"venue"
},
  "geometry": {"coordinates":[-8.2105913162,43.2806167603],"type":"Point"}
}