{
  "type": "Feature",
  "properties": {
    "iso:country":"ES",
    "sg:address":"Calle de San Francisco, 37",
    "sg:city":"Teruel",
    "sg:orig_category":"Promotores Constructores",
    "sg:phone":"+34 978 61 85 40",
    "sg:postcode":"44001",
    "sg:province":"Teruel",
    "wof:name":"Construcciones Vicente Perez S.a.",
    "wof:placetype":"venue"
},
  "geometry": {"coordinates":[-1.1095169783,40.3429641724],"type":"Point"}
}