{
  "type": "Feature",
  "properties": {
    "iso:country":"ES",
    "sg:address":"Plaz Espa\u00d1a, 3",
    "sg:city":"Linares Riofrio",
    "sg:orig_category":"Molduras, Junquillos, Listones Y Molduras Perforadas",
    "sg:phone":"+34 923 41 60 90",
    "sg:postcode":"37760",
    "sg:province":"Salamanca",
    "wof:name":"Hernandez Gomez Carolina",
    "wof:placetype":"venue"
},
  "geometry": {"coordinates":[-5.9210190773,40.5825767517],"type":"Point"}
}