{
  "type": "Feature",
  "properties": {
    "addr:full":"Carrer de Esteve Terradas, 1 Manresa Barcelona 08243",
    "addr:housenumber":"1",
    "addr:postcode":"08243",
    "addr:street":"Carrer De Esteve Terradas",
    "iso:country":"ES",
    "sg:address":"Carrer de Esteve Terradas, 1",
    "sg:city":"Manresa",
    "sg:orig_category":"Fabricaci\u00d3n De Distribuidores Autom\u00c1ticos",
    "sg:phone":"+34 938 73 18 58",
    "sg:postcode":"08243",
    "sg:province":"Barcelona",
    "wof:name":"Supermatic 2000 S.l.",
    "wof:placetype":"venue"
},
  "geometry": {"coordinates":[1.8454389572,41.7147216797],"type":"Point"}
}