{
  "type": "Feature",
  "properties": {
    "addr:full":"Ermitaga\u00f1a, 48 Iru\u00f1a Navarra 31008",
    "addr:housenumber":"48",
    "addr:postcode":"31008",
    "addr:street":"Ermitagan\u0303A",
    "iso:country":"ES",
    "sg:address":"Ermitaga\u00f1a, 48",
    "sg:city":"Iru\u00f1a",
    "sg:orig_category":"Caf\u00c9s, Bares, Cervecer\u00cdas",
    "sg:phone":"+34 948 27 95 95",
    "sg:postcode":"31008",
    "sg:province":"Navarra",
    "wof:name":"Chica Lopez Bartolome",
    "wof:placetype":"venue"
},
  "geometry": {"coordinates":[-1.6733180285,42.8091621399],"type":"Point"}
}