{
  "type": "Feature",
  "properties": {
    "addr:full":"Carr Comte Borrell, 29 Igualada Barcelona 08700",
    "addr:housenumber":"29",
    "addr:postcode":"08700",
    "addr:street":"Carr Comte Borrell",
    "iso:country":"ES",
    "sg:address":"Carr Comte Borrell, 29",
    "sg:city":"Igualada",
    "sg:orig_category":"Cerrajer\u00cda, Ferrallista",
    "sg:phone":"+34 938 05 23 55",
    "sg:postcode":"08700",
    "sg:province":"Barcelona",
    "wof:name":"Terron Prieto Cristobal",
    "wof:placetype":"venue"
},
  "geometry": {"coordinates":[1.6237390041,41.5940132141],"type":"Point"}
}