{
  "type": "Feature",
  "properties": {
    "addr:full":"Calle de Santiago, 2 Santa Cruz De Tenerife Santa Cruz De Tenerife 38002",
    "addr:housenumber":"2",
    "addr:postcode":"38002",
    "addr:street":"Calle De Santiago",
    "iso:country":"ES",
    "sg:address":"Calle de Santiago, 2",
    "sg:city":"Santa Cruz De Tenerife",
    "sg:orig_category":"Ropa Para Se\u00d1oras (al Por Menor)",
    "sg:phone":"+34 922 28 47 95",
    "sg:postcode":"38002",
    "sg:province":"Santa Cruz De Tenerife",
    "wof:name":"Trujillo Brito Eduardo",
    "wof:placetype":"venue"
},
  "geometry": {"coordinates":[-16.2508049011,28.4705524445],"type":"Point"}
}