{
  "type": "Feature",
  "properties": {
    "iso:country":"ES",
    "sg:address":"Pla\u00c7 Mercat, 6",
    "sg:city":"S. Feliu Guixols",
    "sg:orig_category":"Ense\u00d1anza, Formaci\u00d3n Profesional: Aprendizaje",
    "sg:phone":"+34 972 32 70 00",
    "sg:postcode":"17220",
    "sg:province":"Girona",
    "wof:name":"Ajuntament De Sant Feliu De Guixols",
    "wof:placetype":"venue"
},
  "geometry": {"coordinates":[2.8236999512,41.9817962646],"type":"Point"}
}