{
  "type": "Feature",
  "properties": {
    "iso:country":"ES",
    "sg:address":"Carrer de Bassegoda, 39",
    "sg:city":"Barcelona",
    "sg:orig_category":"Peluquer\u00cdas, Peluquer\u00cda Mixta",
    "sg:phone":"+34 934 49 81 01",
    "sg:postcode":"08028",
    "sg:province":"Barcelona",
    "wof:name":"Alba Gomez Francisco Manuel",
    "wof:placetype":"venue"
},
  "geometry": {"coordinates":[2.1247799397,41.3746490479],"type":"Point"}
}