{
  "type": "Feature",
  "properties": {
    "addr:full":"Calle de Valenzuela, 7 Rambla C\u00f3rdoba 14540",
    "addr:housenumber":"7",
    "addr:postcode":"14540",
    "addr:street":"Calle De Valenzuela;Co\u0301Rdoba",
    "iso:country":"ES",
    "sg:address":"Calle de Valenzuela, 7",
    "sg:city":"Rambla",
    "sg:orig_category":"Electrodom\u00c9sticos (al Por Menor)",
    "sg:phone":"+34 957 68 44 46",
    "sg:postcode":"14540",
    "sg:province":"C\u00f3rdoba",
    "wof:name":"Estepa Casado Rafael",
    "wof:placetype":"venue"
},
  "geometry": {"coordinates":[-4.7392258644,37.607837677],"type":"Point"}
}