{
  "type": "Feature",
  "properties": {
    "addr:full":"Carrer de Madrazo, 51 Barcelona Barcelona 08006",
    "addr:housenumber":"51",
    "addr:postcode":"08006",
    "addr:street":"Carrer De Madrazo",
    "iso:country":"ES",
    "sg:address":"Carrer de Madrazo, 51",
    "sg:city":"Barcelona",
    "sg:orig_category":"Peluquer\u00cdas, Peluquer\u00cda Mixta",
    "sg:phone":"+34 932 17 13 97",
    "sg:postcode":"08006",
    "sg:province":"Barcelona",
    "wof:name":"Gracia Bernal Miguela",
    "wof:placetype":"venue"
},
  "geometry": {"coordinates":[2.1485009193,41.3997116089],"type":"Point"}
}