{
  "type": "Feature",
  "properties": {
    "iso:country":"ES",
    "sg:address":"Calle de Albareda, 8",
    "sg:city":"Zaragoza",
    "sg:orig_category":"Doctores En Medicina",
    "sg:phone":"+34 976 21 59 93",
    "sg:postcode":"50004",
    "sg:province":"Zaragoza",
    "wof:name":"Fernandez Fernandez Fidel",
    "wof:placetype":"venue"
},
  "geometry": {"coordinates":[-0.8860660791,41.6500053406],"type":"Point"}
}