{
  "type": "Feature",
  "properties": {
    "addr:full":"Avda Ausias March, S/n Valencia Valencia 46026",
    "addr:housenumber":"s / n",
    "addr:postcode":"46026",
    "addr:street":"Avda Ausias March",
    "iso:country":"ES",
    "sg:address":"Avda Ausias March, S/n",
    "sg:city":"Valencia",
    "sg:orig_category":"Muebles, Minoristas",
    "sg:phone":"+34 963 33 00 32",
    "sg:postcode":"46026",
    "sg:province":"Valencia",
    "sg:website":"www.alvarez-mobiliario.com",
    "wof:name":"Alvarez Mobiliario S. L.",
    "wof:placetype":"venue"
},
  "geometry": {"coordinates":[-0.3702963889,39.436214447],"type":"Point"}
}