{
  "type": "Feature",
  "properties": {
    "iso:country":"ES",
    "sg:address":"Ctra. Benasque, S/n",
    "sg:city":"El Poblado",
    "sg:orig_category":"Ense\u00d1anza Agr\u00cdcola",
    "sg:phone":"+34 974 30 40 79",
    "sg:postcode":"22390",
    "sg:province":"Huesca",
    "wof:name":"Federacion De Centros De Promocion Rural Escuelas Familiares Agra",
    "wof:placetype":"venue"
},
  "geometry": {"coordinates":[0.2227389961,42.1511497498],"type":"Point"}
}