{
  "type": "Feature",
  "properties": {
    "iso:country":"ES",
    "sg:address":"Carrer de Prat De La Riba, 73",
    "sg:city":"Mataro",
    "sg:orig_category":"Centros De Educaci\u00d3n Especial",
    "sg:phone":"+34 937 90 83 32",
    "sg:postcode":"08301",
    "sg:province":"Barcelona",
    "wof:name":"Fundacio El Maresme",
    "wof:placetype":"venue"
},
  "geometry": {"coordinates":[2.4507529736,41.5441741943],"type":"Point"}
}