{
  "type": "Feature",
  "properties": {
    "addr:full":"Avda Costa Blanca, 102 Alacant Alicante 03540",
    "addr:housenumber":"102",
    "addr:postcode":"03540",
    "addr:street":"Avda Costa Blanca",
    "iso:country":"ES",
    "sg:address":"Avda Costa Blanca, 102",
    "sg:city":"Alacant",
    "sg:orig_category":"Arquitectos",
    "sg:phone":"+34 965 26 22 41",
    "sg:postcode":"03540",
    "sg:province":"Alicante",
    "wof:name":"Alamo Triana Manuel Del",
    "wof:placetype":"venue"
},
  "geometry": {"coordinates":[-0.4151566923,38.3625106812],"type":"Point"}
}