{
  "type": "Feature",
  "properties": {
    "iso:country":"ES",
    "sg:address":"Calle de Quevedo, 23",
    "sg:city":"Carrizo Ribera",
    "sg:orig_category":"M\u00c9dicos: Estomatolog\u00cda",
    "sg:phone":"+34 987 35 76 29",
    "sg:postcode":"24270",
    "sg:province":"Le\u00f3n",
    "wof:name":"Acosta Fa\u00f1a Austria Miguelina",
    "wof:placetype":"venue"
},
  "geometry": {"coordinates":[-5.8315563202,42.5866165161],"type":"Point"}
}