{
  "type": "Feature",
  "properties": {
    "iso:country":"ES",
    "sg:address":"Cami Riu, S/n",
    "sg:city":"Albesa",
    "sg:orig_category":"Cooperativas Agr\u00cdcolas",
    "sg:phone":"+34 973 18 60 00",
    "sg:postcode":"25135",
    "sg:province":"Lleida",
    "wof:name":"Agraria Sant Roc D'albesa Sccl.",
    "wof:placetype":"venue"
},
  "geometry": {"coordinates":[0.6574411988,41.7486343384],"type":"Point"}
}