{
  "type": "Feature",
  "properties": {
    "iso:country":"ES",
    "sg:address":"Carrer de Floridablanca, 138",
    "sg:city":"Barcelona",
    "sg:orig_category":"Molduras, Junquillos, Listones Y Molduras Perforadas",
    "sg:phone":"+34 934 24 76 89",
    "sg:postcode":"08011",
    "sg:province":"Barcelona",
    "wof:name":"Villarroya Lagunas Maria Antonia",
    "wof:placetype":"venue"
},
  "geometry": {"coordinates":[2.1623809338,41.3812255859],"type":"Point"}
}