{
  "type": "Feature",
  "properties": {
    "iso:country":"ES",
    "sg:address":"Calle de Santa Ana, 24",
    "sg:city":"Cuarte Huerva",
    "sg:orig_category":"Empresas De Carpinter\u00cda Met\u00c1lica",
    "sg:phone":"+34 976 50 31 64",
    "sg:postcode":"50410",
    "sg:province":"Zaragoza",
    "wof:name":"Cansado Blesa Francisco Jose",
    "wof:placetype":"venue"
},
  "geometry": {"coordinates":[-0.9313349724,41.5957756042],"type":"Point"}
}