{
  "type": "Feature",
  "properties": {
    "addr:full":"Calle de Etxerre(sektorea), 16 Urbi Vizcaya 48970",
    "addr:housenumber":"16",
    "addr:postcode":"48970",
    "addr:street":"Calle De Etxerre Sektorea",
    "iso:country":"ES",
    "sg:address":"Calle de Etxerre(sektorea), 16",
    "sg:city":"Urbi",
    "sg:orig_category":"Asociaciones Humanitarias, De Cooperaci\u00d3n, De Acci\u00d3n Social",
    "sg:phone":"+34 944 40 80 40",
    "sg:postcode":"48970",
    "sg:province":"Vizcaya",
    "wof:name":"Fundacion Eragintza",
    "wof:placetype":"venue"
},
  "geometry": {"coordinates":[-2.8693768978,43.2320594788],"type":"Point"}
}