{
  "type": "Feature",
  "properties": {
    "iso:country":"ES",
    "sg:address":"Calle de Paris, 61",
    "sg:city":"Malaga",
    "sg:orig_category":"Comercio De Piezas De Recambio Y De Accesorios De Veh\u00cdculos, Veh\u00cdculos Industriales",
    "sg:phone":"+34 952 32 71 47",
    "sg:postcode":"29006",
    "sg:province":"M\u00e1laga",
    "wof:name":"Recambios Y Lubricantes Del Sur S.l.",
    "wof:placetype":"venue"
},
  "geometry": {"coordinates":[-4.4729661942,36.703578949],"type":"Point"}
}