{
  "type": "Feature",
  "properties": {
    "iso:country":"ES",
    "sg:address":"Avda Ricardo Soriano, 40",
    "sg:city":"Marbella",
    "sg:orig_category":"M\u00c9dicos: Dermatolog\u00cda Y Venereolog\u00cda",
    "sg:phone":"+34 952 86 86 31",
    "sg:postcode":"29600",
    "sg:province":"M\u00e1laga",
    "wof:name":"Aranzana Gomez Amalia",
    "wof:placetype":"venue"
},
  "geometry": {"coordinates":[-4.8919410706,36.5104827881],"type":"Point"}
}