{
  "type": "Feature",
  "properties": {
    "iso:country":"ES",
    "sg:address":"Calle de Eufrosino Martinez Azorin, 10",
    "sg:city":"Ayora",
    "sg:orig_category":"Serrer\u00cdas De Madera",
    "sg:phone":"+34 961 89 06 80",
    "sg:postcode":"46620",
    "sg:province":"Valencia",
    "wof:name":"Serrano Dominguez Juan",
    "wof:placetype":"venue"
},
  "geometry": {"coordinates":[-1.052718997,39.0567207336],"type":"Point"}
}