{
  "type": "Feature",
  "properties": {
    "iso:country":"ES",
    "sg:address":"Calle de Carrer de (poligono Industrial), 1",
    "sg:city":"Villarrobledo",
    "sg:orig_category":"Papel (al Por Mayor)",
    "sg:phone":"+34 967 13 81 78",
    "sg:postcode":"02600",
    "sg:province":"Albacete",
    "wof:name":"Ortega Y Caro Manipulados De Villarrobledo S.a.l.",
    "wof:placetype":"venue"
},
  "geometry": {"coordinates":[-2.5900740623,39.2765045166],"type":"Point"}
}