{
  "type": "Feature",
  "properties": {
    "addr:full":"Ctra. Extremadura, Km. 0037,5 Calypo Fado Toledo 45950",
    "addr:postcode":"45950",
    "addr:street":"Ctra. Extremadura Km. 0037,5 Calypo",
    "iso:country":"ES",
    "sg:address":"Ctra. Extremadura, Km. 0037,5",
    "sg:city":"Calypo Fado",
    "sg:orig_category":"Promotores Constructores",
    "sg:phone":"+34 918 13 22 64",
    "sg:postcode":"45950",
    "sg:province":"Toledo",
    "wof:name":"Urbanismo Y Contratas S.a.",
    "wof:placetype":"venue"
},
  "geometry": {"coordinates":[-4.0399508476,40.1880645752],"type":"Point"}
}