{
  "type": "Feature",
  "properties": {
    "iso:country":"ES",
    "sg:address":"Calle de Cabo Rufino Lazaro, 18",
    "sg:city":"Rozas De Madrid",
    "sg:orig_category":"Veh\u00cdculos De Ocasi\u00d3n",
    "sg:phone":"+34 916 36 00 06",
    "sg:postcode":"28230",
    "sg:province":"Madrid",
    "wof:name":"Kobe Motoer S.l.",
    "wof:placetype":"venue"
},
  "geometry": {"coordinates":[-3.887339592,40.4974212646],"type":"Point"}
}