{
  "type": "Feature",
  "properties": {
    "iso:country":"ES",
    "sg:address":"Ctra Vallderiolf, Km. 0000,4",
    "sg:city":"Torreta",
    "sg:orig_category":"Laboratorios Farmac\u00c9uticos",
    "sg:phone":"+34 938 79 55 50",
    "sg:postcode":"08430",
    "sg:province":"Barcelona",
    "wof:name":"Fresenius Medical Care Espa\u00d1a S.a.",
    "wof:placetype":"venue"
},
  "geometry": {"coordinates":[2.3271899223,41.5986404419],"type":"Point"}
}