{
  "type": "Feature",
  "properties": {
    "addr:full":"Ctro. Comerc. Cristamar, 43 Nueva Andalucia M\u00e1laga 29660",
    "addr:housenumber":"43",
    "addr:postcode":"29660",
    "addr:street":"Cristamar;Ma\u0301Laga",
    "iso:country":"ES",
    "sg:address":"Ctro. Comerc. Cristamar, 43",
    "sg:city":"Nueva Andalucia",
    "sg:orig_category":"Transporte En General",
    "sg:phone":"+34 952 81 56 48",
    "sg:postcode":"29660",
    "sg:province":"M\u00e1laga",
    "wof:name":"Mail-pack-ship Etc. S.l.",
    "wof:placetype":"venue"
},
  "geometry": {"coordinates":[-4.963350296,36.498714447],"type":"Point"}
}