{
  "type": "Feature",
  "properties": {
    "addr:full":"Calle de Tarbes, 5 Huesca Huesca 22005",
    "addr:housenumber":"5",
    "addr:postcode":"22005",
    "addr:street":"Calle De Tarbes",
    "iso:country":"ES",
    "sg:address":"Calle de Tarbes, 5",
    "sg:city":"Huesca",
    "sg:orig_category":"Partidos Pol\u00cdticos",
    "sg:phone":"+34 974 24 41 69",
    "sg:postcode":"22005",
    "sg:province":"Huesca",
    "wof:name":"Partido Popular",
    "wof:placetype":"venue"
},
  "geometry": {"coordinates":[-0.4078490138,42.1333656311],"type":"Point"}
}