{
  "type": "Feature",
  "properties": {
    "iso:country":"ES",
    "sg:address":"Avda Doctor Garcia Tapia, 122",
    "sg:city":"Madrid",
    "sg:orig_category":"Internados & Ense\u00d1anza Privada",
    "sg:phone":"+34 914 39 06 24",
    "sg:postcode":"28030",
    "sg:province":"Madrid",
    "wof:name":"Colegio San Martin",
    "wof:placetype":"venue"
},
  "geometry": {"coordinates":[-3.6470661163,40.4118232727],"type":"Point"}
}