{
  "type": "Feature",
  "properties": {
    "iso:country":"ES",
    "sg:address":"Carr Ferrer Barbara, 14",
    "sg:city":"Camprodon",
    "sg:orig_category":"Reposter\u00cdas",
    "sg:phone":"+34 972 74 01 32",
    "sg:postcode":"17867",
    "sg:province":"Girona",
    "wof:name":"Sala Surriba Josep",
    "wof:placetype":"venue"
},
  "geometry": {"coordinates":[2.3648760319,42.3141365051],"type":"Point"}
}