{
  "type": "Feature",
  "properties": {
    "addr:full":"Calle de Landako Kalea, 3 Amurrio \u00c1lava 01470",
    "addr:housenumber":"3",
    "addr:postcode":"01470",
    "addr:street":"Calle De Landako Kalea",
    "iso:country":"ES",
    "sg:address":"Calle de Landako Kalea, 3",
    "sg:city":"Amurrio",
    "sg:orig_category":"Estancos",
    "sg:phone":"+34 945 89 00 66",
    "sg:postcode":"01470",
    "sg:province":"\u00c1lava",
    "wof:name":"Zulueta Bordagarai Carmen",
    "wof:placetype":"venue"
},
  "geometry": {"coordinates":[-3.0016999245,43.0513496399],"type":"Point"}
}