{
  "type": "Feature",
  "properties": {
    "addr:full":"Calle de Oriente, 21 Brea De Aragon Zaragoza 50246",
    "addr:housenumber":"21",
    "addr:postcode":"50246",
    "addr:street":"Calle De Oriente",
    "iso:country":"ES",
    "sg:address":"Calle de Oriente, 21",
    "sg:city":"Brea De Aragon",
    "sg:orig_category":"Mec\u00c1nico Del Autom\u00d3vil",
    "sg:phone":"+34 976 82 41 03",
    "sg:postcode":"50246",
    "sg:province":"Zaragoza",
    "wof:name":"Talleres Escolano S.l.",
    "wof:placetype":"venue"
},
  "geometry": {"coordinates":[-1.5995635986,41.5204391479],"type":"Point"}
}