{
  "type": "Feature",
  "properties": {
    "iso:country":"ES",
    "sg:address":"Calle de Salvador Dali (de), 28",
    "sg:city":"Mejorada Campo",
    "sg:orig_category":"Centros Comerciales Y Grandes Tiendas",
    "sg:phone":"+34 916 68 03 38",
    "sg:postcode":"28840",
    "sg:province":"Madrid",
    "wof:name":"Martin Rodriguez Santos",
    "wof:placetype":"venue"
},
  "geometry": {"coordinates":[-3.4823310375,40.3927383423],"type":"Point"}
}