{
  "type": "Feature",
  "properties": {
    "iso:country":"ES",
    "sg:address":"Ptda. Del Pla, S/n",
    "sg:city":"Villanueva De Castellon",
    "sg:orig_category":"Producci\u00d3n De Abonos Y De Fertilizantes",
    "sg:phone":"+34 962 45 01 94",
    "sg:postcode":"46270",
    "sg:province":"Valencia",
    "wof:name":"Hijos De Vicente Climent S.a.",
    "wof:placetype":"venue"
},
  "geometry": {"coordinates":[-0.5113490224,39.0756912231],"type":"Point"}
}