{
  "type": "Feature",
  "properties": {
    "addr:full":"Calle de Monte Perdido, 33 Madrid Madrid 28053",
    "addr:housenumber":"33",
    "addr:postcode":"madrid;28053",
    "addr:street":"Calle De Monte Perdido",
    "iso:country":"ES",
    "sg:address":"Calle de Monte Perdido, 33",
    "sg:city":"Madrid",
    "sg:orig_category":"Mec\u00c1nico Del Autom\u00d3vil",
    "sg:phone":"+34 914 78 25 76",
    "sg:postcode":"28053",
    "sg:province":"Madrid",
    "wof:name":"Carrocerias Ramon S.l.",
    "wof:placetype":"venue"
},
  "geometry": {"coordinates":[-3.6691300869,40.3938369751],"type":"Point"}
}