{
  "type": "Feature",
  "properties": {
    "iso:country":"ES",
    "sg:address":"Calle de Juan De Austria, 16",
    "sg:city":"Mairena Aljarafe",
    "sg:orig_category":"Energ\u00cda Solar Y Nuevas Energ\u00cdas (equipo, Estudios)",
    "sg:phone":"+34 954 17 82 63",
    "sg:postcode":"41927",
    "sg:province":"Sevilla",
    "wof:name":"Enersol Energias Renovables S.l.",
    "wof:placetype":"venue"
},
  "geometry": {"coordinates":[-6.0401368141,37.35546875],"type":"Point"}
}