{
  "type": "Feature",
  "properties": {
    "addr:full":"Ctra Cadiz De, Km. 0227,0 Perla-torremuelle M\u00e1laga 29630",
    "addr:postcode":"29630",
    "addr:street":"Ctra Cadiz De Km. 0227,0 Perla-Torremuelle Ma\u0301Laga",
    "iso:country":"ES",
    "sg:address":"Ctra Cadiz De, Km. 0227,0",
    "sg:city":"Perla-torremuelle",
    "sg:orig_category":"Supermercados Y Hipermercados",
    "sg:phone":"+34 952 44 00 86",
    "sg:postcode":"29630",
    "sg:province":"M\u00e1laga",
    "wof:name":"Harjani Kishinchand Prem",
    "wof:placetype":"venue"
},
  "geometry": {"coordinates":[-4.521381855,36.5971374512],"type":"Point"}
}