{
  "type": "Feature",
  "properties": {
    "addr:full":"Calle de Albacete, 32 Arganda Madrid 28500",
    "addr:housenumber":"32",
    "addr:postcode":"28500",
    "addr:street":"Calle De Albacete",
    "iso:country":"ES",
    "sg:address":"Calle de Albacete, 32",
    "sg:city":"Arganda",
    "sg:orig_category":"Automatizaci\u00d3n De Procesos Industriales Y De Edificaci\u00d3n (estudios, Instalaci\u00d3n)",
    "sg:phone":"+34 918 71 52 80",
    "sg:postcode":"28500",
    "sg:province":"Madrid",
    "wof:name":"Amiac S.a.",
    "wof:placetype":"venue"
},
  "geometry": {"coordinates":[-3.4588561058,40.3085250854],"type":"Point"}
}