{
  "type": "Feature",
  "properties": {
    "iso:country":"ES",
    "sg:address":"Calle de Ronda (la), 30",
    "sg:city":"Castro Urdiales",
    "sg:orig_category":"Ropa Para Ni\u00d1os (al Por Menor)",
    "sg:phone":"+34 942 86 77 54",
    "sg:postcode":"39700",
    "sg:province":"Cantabria",
    "wof:name":"Abascal Urquijo Angeles",
    "wof:placetype":"venue"
},
  "geometry": {"coordinates":[-3.219885,43.380901],"type":"Point"}
}