{
  "type": "Feature",
  "properties": {
    "addr:full":"Zarugalde Kalea, 14 Arrasate Guip\u00f9zcoa 20500",
    "addr:housenumber":"14",
    "addr:postcode":"20500",
    "addr:street":"Zarugalde Kalea;Guipu\u0300Zcoa",
    "iso:country":"ES",
    "sg:address":"Zarugalde Kalea, 14",
    "sg:city":"Arrasate",
    "sg:orig_category":"Zapatos (al Por Menor)",
    "sg:phone":"+34 943 79 49 72",
    "sg:postcode":"20500",
    "sg:province":"Guip\u00f9zcoa",
    "wof:name":"Algaba Sanchez Agustin",
    "wof:placetype":"venue"
},
  "geometry": {"coordinates":[-2.4926660061,43.0658721924],"type":"Point"}
}