{
  "type": "Feature",
  "properties": {
    "iso:country":"ES",
    "sg:address":"Calle de Juan Llorens, 35",
    "sg:city":"Valencia",
    "sg:orig_category":"Inmobiliaria (agencias)",
    "sg:phone":"+34 963 84 84 04",
    "sg:postcode":"46008",
    "sg:province":"Valencia",
    "wof:name":"C. Mariano Ballesteros S.l.",
    "wof:placetype":"venue"
},
  "geometry": {"coordinates":[-0.3898560107,39.4717826843],"type":"Point"}
}