{
  "type": "Feature",
  "properties": {
    "addr:full":"Praj Fuente Vieja, S/n Almonacid Zorita Guadalajara 19118",
    "addr:housenumber":"s",
    "addr:postcode":"19118",
    "addr:street":"Fuente Vieja;/ N",
    "iso:country":"ES",
    "sg:address":"Praj Fuente Vieja, S/n",
    "sg:city":"Almonacid Zorita",
    "sg:orig_category":"Asilos De Ancianos. Centros Privados",
    "sg:phone":"+34 949 37 50 11",
    "sg:postcode":"19118",
    "sg:province":"Guadalajara",
    "wof:name":"Residencia De Ancianos Virgen De La Luz",
    "wof:placetype":"venue"
},
  "geometry": {"coordinates":[-2.8495969772,40.3290367126],"type":"Point"}
}