{
  "type": "Feature",
  "properties": {
    "addr:full":"La Rosa, 12 Sta Cruz Tenerife Santa Cruz De Tenerife 38002",
    "addr:housenumber":"12",
    "addr:postcode":"38002",
    "addr:street":"Rosa;Sta Cruz Tenerife",
    "iso:country":"ES",
    "sg:address":"La Rosa, 12",
    "sg:city":"Sta Cruz Tenerife",
    "sg:orig_category":"Retoques De Vestidos",
    "sg:phone":"+34 922 27 46 65",
    "sg:postcode":"38002",
    "sg:province":"Santa Cruz De Tenerife",
    "sg:website":"www.retoucherie.com",
    "wof:name":"Del Canto Fernandez Maria Rosalia",
    "wof:placetype":"venue"
},
  "geometry": {"coordinates":[-16.250164032,28.4701557159],"type":"Point"}
}