{
  "type": "Feature",
  "properties": {
    "addr:full":"Carrer de L'escultor Llimona, 16 Barcelona Barcelona 08031",
    "addr:housenumber":"16",
    "addr:postcode":"08031",
    "addr:street":"Carrer De L'Escultor Llimona",
    "iso:country":"ES",
    "sg:address":"Carrer de L'escultor Llimona, 16",
    "sg:city":"Barcelona",
    "sg:orig_category":"Promotores Constructores",
    "sg:phone":"+34 933 57 46 00",
    "sg:postcode":"08031",
    "sg:province":"Barcelona",
    "wof:name":"Asprilla S.a.",
    "wof:placetype":"venue"
},
  "geometry": {"coordinates":[2.1695830822,41.427898407],"type":"Point"}
}