{
  "type": "Feature",
  "properties": {
    "addr:full":"Calle de Naves, 16 Madrid Madrid 28005",
    "addr:housenumber":"16",
    "addr:postcode":"madrid;28005",
    "addr:street":"Calle De Naves",
    "iso:country":"ES",
    "sg:address":"Calle de Naves, 16",
    "sg:city":"Madrid",
    "sg:orig_category":"Arquitectos",
    "sg:phone":"+34 915 17 15 71",
    "sg:postcode":"28005",
    "sg:province":"Madrid",
    "wof:name":"Trasdos 04 Proyectos S.l.",
    "wof:placetype":"venue"
},
  "geometry": {"coordinates":[-3.7062280178,40.3979606628],"type":"Point"}
}