{
  "type": "Feature",
  "properties": {
    "addr:full":"Carr Independencia, 251 Badalona Barcelona 08915",
    "addr:housenumber":"251",
    "addr:postcode":"08915",
    "addr:street":"Carr Independencia",
    "iso:country":"ES",
    "sg:address":"Carr Independencia, 251",
    "sg:city":"Badalona",
    "sg:orig_category":"Carnicer\u00cdas, Carnicer\u00cdas",
    "sg:phone":"+34 933 83 04 52",
    "sg:postcode":"08915",
    "sg:province":"Barcelona",
    "wof:name":"Mari Salcedo Purificacion",
    "wof:placetype":"venue"
},
  "geometry": {"coordinates":[2.2410230637,41.4611167908],"type":"Point"}
}