{
  "type": "Feature",
  "properties": {
    "addr:full":"Calle de Soto, 11 Valladolid Valladolid 47010",
    "addr:housenumber":"11",
    "addr:postcode":"47010",
    "addr:street":"Calle De Soto",
    "iso:country":"ES",
    "sg:address":"Calle de Soto, 11",
    "sg:city":"Valladolid",
    "sg:orig_category":"Muebles Y Accesorios Para Cocinas Y Cuartos De Ba\u00d1o (al Por Menor)",
    "sg:phone":"+34 983 25 75 77",
    "sg:postcode":"47010",
    "sg:province":"Valladolid",
    "wof:name":"Garcia Mendez Javier",
    "wof:placetype":"venue"
},
  "geometry": {"coordinates":[-4.7185349464,41.6618461609],"type":"Point"}
}