{
  "type": "Feature",
  "properties": {
    "iso:country":"ES",
    "sg:address":"Calle de Joan Miro, 1",
    "sg:city":"Almansa",
    "sg:orig_category":"Zapatos: Material, Suministros, Accesorios (fabricaci\u00d3n, Al Por Mayor)",
    "sg:phone":"+34 967 34 01 36",
    "sg:postcode":"02640",
    "sg:province":"Albacete",
    "wof:name":"Garcia Garcia Hipolito",
    "wof:placetype":"venue"
},
  "geometry": {"coordinates":[-1.1049729586,38.8746490479],"type":"Point"}
}