{
  "type": "Feature",
  "properties": {
    "iso:country":"ES",
    "sg:address":"Calle de Marques De Celada, 83",
    "sg:city":"San Cristobal De La Laguna",
    "sg:orig_category":"Zapatos (al Por Menor)",
    "sg:phone":"+34 922 26 07 64",
    "sg:postcode":"38202",
    "sg:province":"Santa Cruz De Tenerife",
    "wof:name":"Quintero Lopez Antonio Benito",
    "wof:placetype":"venue"
},
  "geometry": {"coordinates":[-16.3247509003,28.4901657104],"type":"Point"}
}