{
  "type": "Feature",
  "properties": {
    "addr:full":"Avda Portugal, 19 Zamora Zamora 49016",
    "addr:housenumber":"19",
    "addr:postcode":"49016",
    "addr:street":"Avda Portugal",
    "iso:country":"ES",
    "sg:address":"Avda Portugal, 19",
    "sg:city":"Zamora",
    "sg:orig_category":"Promotores Constructores",
    "sg:phone":"+34 980 67 18 85",
    "sg:postcode":"49016",
    "sg:province":"Zamora",
    "wof:name":"S.z.v. Promociones Y Obras S.l.",
    "wof:placetype":"venue"
},
  "geometry": {"coordinates":[-5.7397990227,41.503490448],"type":"Point"}
}