{
  "type": "Feature",
  "properties": {
    "addr:full":"Calle de Villagarcia, 11 Madrid Madrid 28011",
    "addr:housenumber":"11",
    "addr:postcode":"madrid;28011",
    "addr:street":"Calle De Villagarcia",
    "iso:country":"ES",
    "sg:address":"Calle de Villagarcia, 11",
    "sg:city":"Madrid",
    "sg:orig_category":"Delegados, Agentes De Tr\u00c1nsito, Auxiliares De Transporte Internacional",
    "sg:phone":"+34 914 79 18 64",
    "sg:postcode":"28011",
    "sg:province":"Madrid",
    "wof:name":"Hermanos Arnal S.l",
    "wof:placetype":"venue"
},
  "geometry": {"coordinates":[-3.7544999123,40.4047393799],"type":"Point"}
}