{
  "type": "Feature",
  "properties": {
    "addr:full":"Pl Gran, 4 Mataro Barcelona 08301",
    "addr:housenumber":"4",
    "addr:postcode":"08301",
    "addr:street":"Pl Gran",
    "iso:country":"ES",
    "sg:address":"Pl Gran, 4",
    "sg:city":"Mataro",
    "sg:orig_category":"Mercer\u00cda, Lencer\u00cda (al Por Menor)",
    "sg:phone":"+34 937 90 69 39",
    "sg:postcode":"08301",
    "sg:province":"Barcelona",
    "wof:name":"Sires Collado Javier",
    "wof:placetype":"venue"
},
  "geometry": {"coordinates":[2.4470720291,41.5401153564],"type":"Point"}
}