{
  "type": "Feature",
  "properties": {
    "iso:country":"ES",
    "sg:address":"Ctra Vp Mil Treinta Y Seis, S/n",
    "sg:city":"Xativa",
    "sg:orig_category":"Fabricaci\u00d3n, Importaci\u00d3n De L\u00c1mparas Y Bombillas",
    "sg:phone":"+34 962 27 50 11",
    "sg:postcode":"46800",
    "sg:province":"Valencia",
    "sg:website":"w.w.w.lamparasrafaeltormo.com",
    "wof:name":"Lamparas Rafael Tormo S.a.",
    "wof:placetype":"venue"
},
  "geometry": {"coordinates":[-0.5327939987,38.9840393066],"type":"Point"}
}