{
  "type": "Feature",
  "properties": {
    "addr:full":"Calle de Azucena, 30 Ciudad Real Ciudad Real 13002",
    "addr:housenumber":"30",
    "addr:postcode":"13002",
    "addr:street":"Calle De Azucena",
    "iso:country":"ES",
    "sg:address":"Calle de Azucena, 30",
    "sg:city":"Ciudad Real",
    "sg:orig_category":"Empresas De Impermeabilizaci\u00d3n",
    "sg:phone":"+34 926 25 57 94",
    "sg:postcode":"13002",
    "sg:province":"Ciudad Real",
    "wof:name":"Imtexcir S.l.",
    "wof:placetype":"venue"
},
  "geometry": {"coordinates":[-3.9313735962,38.9864768982],"type":"Point"}
}