{
  "type": "Feature",
  "properties": {
    "iso:country":"ES",
    "sg:address":"Plaz Jose Antonio Giron, S/n",
    "sg:city":"Herrera Pisuerga",
    "sg:orig_category":"Molduras, Junquillos, Listones Y Molduras Perforadas",
    "sg:phone":"+34 979 13 00 33",
    "sg:postcode":"34400",
    "sg:province":"Palencia",
    "wof:name":"Sanchez Barcenilla Judith",
    "wof:placetype":"venue"
},
  "geometry": {"coordinates":[-4.3294730186,42.5958480835],"type":"Point"}
}