{
  "type": "Feature",
  "properties": {
    "addr:full":"Calle de General Primo De Rivera, 2 Algeciras C\u00e1diz 11201",
    "addr:housenumber":"2;ca\u0301diz",
    "addr:postcode":"11201",
    "addr:street":"Calle De General Primo De Rivera",
    "iso:country":"ES",
    "sg:address":"Calle de General Primo De Rivera, 2",
    "sg:city":"Algeciras",
    "sg:orig_category":"Notarios",
    "sg:phone":"+34 956 65 38 12",
    "sg:postcode":"11201",
    "sg:province":"C\u00e1diz",
    "wof:name":"Bermudez De Castro Fernandez Pilar",
    "wof:placetype":"venue"
},
  "geometry": {"coordinates":[-5.4476771355,36.1314849854],"type":"Point"}
}