{
  "type": "Feature",
  "properties": {
    "addr:full":"Luga Poligono Industrial De Roces, S/n Gijon Asturias 33211",
    "addr:housenumber":"s",
    "addr:postcode":"33211",
    "addr:street":"Poligono Industrial De Roces;/ N",
    "iso:country":"ES",
    "sg:address":"Luga Poligono Industrial De Roces, S/n",
    "sg:city":"Gijon",
    "sg:orig_category":"Material Y Herramientas Agr\u00cdcolas",
    "sg:phone":"+34 985 16 79 34",
    "sg:postcode":"33211",
    "sg:province":"Asturias",
    "wof:name":"Agricola Costa Verde S.l.",
    "wof:placetype":"venue"
},
  "geometry": {"coordinates":[-5.6852426529,43.5228233337],"type":"Point"}
}