{
  "type": "Feature",
  "properties": {
    "addr:full":"Calle de General Yague, 2 Fuensalida Toledo 45510",
    "addr:housenumber":"2",
    "addr:postcode":"45510",
    "addr:street":"Calle De General Yague",
    "iso:country":"ES",
    "sg:address":"Calle de General Yague, 2",
    "sg:city":"Fuensalida",
    "sg:orig_category":"Asesor\u00cda Fiscal Y Jur\u00cddica",
    "sg:phone":"+34 925 73 12 12",
    "sg:postcode":"45510",
    "sg:province":"Toledo",
    "wof:name":"Inforlex C.b.",
    "wof:placetype":"venue"
},
  "geometry": {"coordinates":[-4.2108111382,40.0493507385],"type":"Point"}
}