{
  "type": "Feature",
  "properties": {
    "iso:country":"ES",
    "sg:address":"Calle de Libertad, 20",
    "sg:city":"Hellin",
    "sg:orig_category":"Alumbrados",
    "sg:phone":"+34 967 30 57 51",
    "sg:postcode":"02400",
    "sg:province":"Albacete",
    "wof:name":"Apex Print S.l.",
    "wof:placetype":"venue"
},
  "geometry": {"coordinates":[-1.6972423792,38.5125694275],"type":"Point"}
}