{
  "type": "Feature",
  "properties": {
    "iso:country":"ES",
    "sg:address":"Carrer de Llanera, 16",
    "sg:city":"Sabadell",
    "sg:orig_category":"Platos Preparados Refrigerados (fabricaci\u00d3n, Al Por Mayor)",
    "sg:phone":"+34 937 17 40 16",
    "sg:postcode":"08207",
    "sg:province":"Barcelona",
    "wof:name":"Rotisseria La Botigueta S.c.p",
    "wof:placetype":"venue"
},
  "geometry": {"coordinates":[2.0891499519,41.567691803],"type":"Point"}
}