{
  "type": "Feature",
  "properties": {
    "iso:country":"ES",
    "sg:address":"Calle de Camara La, 27",
    "sg:city":"Aviles",
    "sg:orig_category":"Parques De Atracciones Y Centros De Esparcimiento",
    "sg:phone":"+34 985 56 04 88",
    "sg:postcode":"33401",
    "sg:province":"Asturias",
    "wof:name":"Sodicarsa.s.a.",
    "wof:placetype":"venue"
},
  "geometry": {"coordinates":[-5.9238557816,43.5568809509],"type":"Point"}
}