{
  "type": "Feature",
  "properties": {
    "addr:full":"Calle de Triana, 71 Palmas De Gran Canaria Las Palmas 35002",
    "addr:housenumber":"71",
    "addr:postcode":"35002",
    "addr:street":"Calle De Triana",
    "iso:country":"ES",
    "sg:address":"Calle de Triana, 71",
    "sg:city":"Palmas De Gran Canaria",
    "sg:orig_category":"Complementos De Vestir (al Por Menor)",
    "sg:phone":"+34 928 38 09 73",
    "sg:postcode":"35002",
    "sg:province":"Las Palmas",
    "sg:website":"www.promod.cr",
    "wof:name":"Promod Espa\u00f1a S.a.",
    "wof:placetype":"venue"
},
  "geometry": {"coordinates":[-15.416434288,28.1061096191],"type":"Point"}
}