{
  "type": "Feature",
  "properties": {
    "addr:full":"Calle de Cardenal Parrado, 3 Granada Granada 18013",
    "addr:housenumber":"3",
    "addr:postcode":"18013",
    "addr:street":"Calle De Cardenal Parrado",
    "iso:country":"ES",
    "sg:address":"Calle de Cardenal Parrado, 3",
    "sg:city":"Granada",
    "sg:orig_category":"Peluqueros: De Se\u00d1oras",
    "sg:phone":"+34 958 16 17 22",
    "sg:postcode":"18013",
    "sg:province":"Granada",
    "wof:name":"Cabello Baena Rosario",
    "wof:placetype":"venue"
},
  "geometry": {"coordinates":[-3.6047744751,37.1896018982],"type":"Point"}
}