{
  "type": "Feature",
  "properties": {
    "addr:full":"Avda Machupichu, 43 Madrid Madrid 28043",
    "addr:housenumber":"43",
    "addr:postcode":"madrid;28043",
    "addr:street":"Avda Machupichu",
    "iso:country":"ES",
    "sg:address":"Avda Machupichu, 43",
    "sg:city":"Madrid",
    "sg:orig_category":"Arquitectos",
    "sg:phone":"+34 913 88 52 23",
    "sg:postcode":"28043",
    "sg:province":"Madrid",
    "wof:name":"Mosso Sayavedra Mariana",
    "wof:placetype":"venue"
},
  "geometry": {"coordinates":[-3.6281321049,40.4598236084],"type":"Point"}
}