{
  "type": "Feature",
  "properties": {
    "addr:full":"Calle de Empecinado (del), 59 Mostoles Madrid 28936",
    "addr:housenumber":"59",
    "addr:postcode":"28936",
    "addr:street":"Calle De Empecinado Del",
    "iso:country":"ES",
    "sg:address":"Calle de Empecinado (del), 59",
    "sg:city":"Mostoles",
    "sg:orig_category":"Cine (distribuci\u00d3n)",
    "sg:phone":"+34 916 46 09 25",
    "sg:postcode":"28936",
    "sg:province":"Madrid",
    "wof:name":"Sanchez Flores Luis",
    "wof:placetype":"venue"
},
  "geometry": {"coordinates":[-3.8527350426,40.3211631775],"type":"Point"}
}