{
  "type": "Feature",
  "properties": {
    "addr:full":"Juventud(los Dolores), 13 Murcia Murcia 30011",
    "addr:housenumber":"13",
    "addr:postcode":"30011",
    "addr:street":"Los Dolores",
    "iso:country":"ES",
    "sg:address":"Juventud(los Dolores), 13",
    "sg:city":"Murcia",
    "sg:orig_category":"Cl\u00cdnicas Dentales",
    "sg:phone":"+34 968 34 70 53",
    "sg:postcode":"30011",
    "sg:province":"Murcia",
    "wof:name":"Kavo Dental S.l.",
    "wof:placetype":"venue"
},
  "geometry": {"coordinates":[-1.1052470207,37.9774665833],"type":"Point"}
}