{
  "type": "Feature",
  "properties": {
    "iso:country":"ES",
    "sg:address":"Carrer de Joan Pallares, 25",
    "sg:city":"Hospitalet Llobregat",
    "sg:orig_category":"Molduras, Junquillos, Listones Y Molduras Perforadas",
    "sg:phone":"+34 933 38 71 90",
    "sg:postcode":"08901",
    "sg:province":"Barcelona",
    "wof:name":"Monfort Serrano Fernando",
    "wof:placetype":"venue"
},
  "geometry": {"coordinates":[2.0980889797,41.3609466553],"type":"Point"}
}