{
  "type": "Feature",
  "properties": {
    "iso:country":"ES",
    "sg:address":"Las Mestas, 3",
    "sg:city":"Mestas",
    "sg:orig_category":"Molduras, Junquillos, Listones Y Molduras Perforadas",
    "sg:phone":"+34 985 89 71 29",
    "sg:postcode":"33315",
    "sg:province":"Asturias",
    "wof:name":"Les Mestes C.b.",
    "wof:placetype":"venue"
},
  "geometry": {"coordinates":[-5.4002161026,43.5276565552],"type":"Point"}
}