{
  "type": "Feature",
  "properties": {
    "iso:country":"ES",
    "sg:address":"Mercat Clot, S/n",
    "sg:city":"Barcelona",
    "sg:orig_category":"Carnicer\u00cdas, Carnicer\u00cdas",
    "sg:phone":"+34 932 31 71 60",
    "sg:postcode":"08005",
    "sg:province":"Barcelona",
    "wof:name":"Ros Castella Francisca",
    "wof:placetype":"venue"
},
  "geometry": {"coordinates":[2.1898999214,41.4121246338],"type":"Point"}
}