{
  "type": "Feature",
  "properties": {
    "addr:full":"Avda Uruguay, 3 Benidorm Alicante 03500",
    "addr:housenumber":"3",
    "addr:postcode":"03500",
    "addr:street":"Avda Uruguay",
    "iso:country":"ES",
    "sg:address":"Avda Uruguay, 3",
    "sg:city":"Benidorm",
    "sg:orig_category":"Inmobiliaria (agencias)",
    "sg:phone":"+34 965 85 68 07",
    "sg:postcode":"03500",
    "sg:province":"Alicante",
    "wof:name":"De La Fuente Villaroel Irene",
    "wof:placetype":"venue"
},
  "geometry": {"coordinates":[-0.1399829984,38.5385513306],"type":"Point"}
}