{
  "type": "Feature",
  "properties": {
    "iso:country":"ES",
    "sg:address":"Ctra Murcia, S/n",
    "sg:city":"Pinoso",
    "sg:orig_category":"Centros Empresariales",
    "sg:phone":"+34 965 47 88 24",
    "sg:postcode":"03650",
    "sg:province":"Alicante",
    "wof:name":"Asociacion De Comerciantes De Pinoso",
    "wof:placetype":"venue"
},
  "geometry": {"coordinates":[-1.044721365,38.3960189819],"type":"Point"}
}