{
  "type": "Feature",
  "properties": {
    "iso:country":"ES",
    "sg:address":"Calle de Pastores, 6",
    "sg:city":"Javea",
    "sg:orig_category":"Peluquer\u00cdas, Peluquer\u00cda Mixta",
    "sg:phone":"+34 965 79 42 34",
    "sg:postcode":"03730",
    "sg:province":"Alicante",
    "wof:name":"Garcia Talaveron Carlos",
    "wof:placetype":"venue"
},
  "geometry": {"coordinates":[0.1622070074,38.7876777649],"type":"Point"}
}