{
  "type": "Feature",
  "properties": {
    "iso:country":"ES",
    "sg:address":"Avda Paz La, 6",
    "sg:city":"Entrego",
    "sg:orig_category":"Bancos",
    "sg:phone":"+34 985 66 08 12",
    "sg:postcode":"33940",
    "sg:province":"Asturias",
    "wof:name":"Banco Espa\u00f1ol De Credito S.a.",
    "wof:placetype":"venue"
},
  "geometry": {"coordinates":[-5.6435742378,43.2864112854],"type":"Point"}
}