{
  "type": "Feature",
  "properties": {
    "addr:full":"Calle de Virgen De La Oliva, 10 Madrid Madrid 28037",
    "addr:housenumber":"10",
    "addr:postcode":"madrid;28037",
    "addr:street":"Calle De Virgen De La Oliva",
    "iso:country":"ES",
    "sg:address":"Calle de Virgen De La Oliva, 10",
    "sg:city":"Madrid",
    "sg:orig_category":"Carnicer\u00cdas, Carnicer\u00cdas",
    "sg:phone":"+34 917 54 58 79",
    "sg:postcode":"28037",
    "sg:province":"Madrid",
    "wof:name":"Manzano Martinez Julian",
    "wof:placetype":"venue"
},
  "geometry": {"coordinates":[-3.6250369549,40.4309082031],"type":"Point"}
}