{
  "type": "Feature",
  "properties": {
    "iso:country":"ES",
    "sg:address":"Calle de Franciscas, 17",
    "sg:city":"Almagro",
    "sg:orig_category":"Fabricaci\u00d3n De Bordados, Encajes Y Tules",
    "sg:phone":"+34 926 86 00 06",
    "sg:postcode":"13270",
    "sg:province":"Ciudad Real",
    "wof:name":"Sanchez-pastor Moreno Maria Nieves",
    "wof:placetype":"venue"
},
  "geometry": {"coordinates":[-3.714509964,38.8876838684],"type":"Point"}
}