{
  "type": "Feature",
  "properties": {
    "iso:country":"ES",
    "sg:address":"Avda Perez Galdos, 59",
    "sg:city":"Logro\u00f1o",
    "sg:orig_category":"Estancos",
    "sg:phone":"+34 941 20 69 95",
    "sg:postcode":"26005",
    "sg:province":"La Rioja",
    "wof:name":"Castillo Ibarreche Elena Valvanera Del",
    "wof:placetype":"venue"
},
  "geometry": {"coordinates":[-2.4543828964,42.462600708],"type":"Point"}
}