{
  "type": "Feature",
  "properties": {
    "addr:full":"Calle de Cirilo Santos, 21 Santa Maria Del Paramo Le\u00f3n 24240",
    "addr:housenumber":"21",
    "addr:postcode":"24240",
    "addr:street":"Calle De Cirilo Santos",
    "iso:country":"ES",
    "sg:address":"Calle de Cirilo Santos, 21",
    "sg:city":"Santa Maria Del Paramo",
    "sg:orig_category":"Bancos",
    "sg:phone":"+34 987 36 01 78",
    "sg:postcode":"24240",
    "sg:province":"Le\u00f3n",
    "wof:name":"Banco De Castilla",
    "wof:placetype":"venue"
},
  "geometry": {"coordinates":[-5.7493438721,42.3546447754],"type":"Point"}
}