{
  "type": "Feature",
  "properties": {
    "addr:full":"Calle de Fray Luis Amigo, 6 Zaragoza Zaragoza 50006",
    "addr:housenumber":"6",
    "addr:postcode":"50006",
    "addr:street":"Calle De Fray Luis Amigo",
    "iso:country":"ES",
    "sg:address":"Calle de Fray Luis Amigo, 6",
    "sg:city":"Zaragoza",
    "sg:orig_category":"Agentes Generales De Seguros",
    "sg:phone":"+34 976 37 86 10",
    "sg:postcode":"50006",
    "sg:province":"Zaragoza",
    "wof:name":"Cauhe Turon Jaime",
    "wof:placetype":"venue"
},
  "geometry": {"coordinates":[-0.8936190009,41.6372299194],"type":"Point"}
}