{
  "type": "Feature",
  "properties": {
    "addr:full":"Calle de Gonzalo De Cordoba, 7 Madrid Madrid 28010",
    "addr:housenumber":"7",
    "addr:postcode":"madrid;28010",
    "addr:street":"Calle De Gonzalo De Cordoba",
    "iso:country":"ES",
    "sg:address":"Calle de Gonzalo De Cordoba, 7",
    "sg:city":"Madrid",
    "sg:orig_category":"Ropa Para Ni\u00d1os (al Por Menor)",
    "sg:phone":"+34 914 44 05 96",
    "sg:postcode":"28010",
    "sg:province":"Madrid",
    "wof:name":"Carreno Belmonte Barbara",
    "wof:placetype":"venue"
},
  "geometry": {"coordinates":[-3.7030301094,40.4324073792],"type":"Point"}
}