{
  "type": "Feature",
  "properties": {
    "addr:full":"Trva Arbolantxa, 1 Bilbao Vizcaya 48004",
    "addr:housenumber":"1",
    "addr:postcode":"48004",
    "addr:street":"Trva Arbolantxa",
    "iso:country":"ES",
    "sg:address":"Trva Arbolantxa, 1",
    "sg:city":"Bilbao",
    "sg:orig_category":"Cervecer\u00cdas",
    "sg:phone":"+34 944 12 41 93",
    "sg:postcode":"48004",
    "sg:province":"Vizcaya",
    "wof:name":"Sardon Carrillo M Isabel",
    "wof:placetype":"venue"
},
  "geometry": {"coordinates":[-2.8979790211,43.2613601685],"type":"Point"}
}