{
  "type": "Feature",
  "properties": {
    "addr:full":"Carrer de Balmes, 15 Bisbal Del Penedes Tarragona 43717",
    "addr:housenumber":"15",
    "addr:postcode":"43717",
    "addr:street":"Carrer De Balmes",
    "iso:country":"ES",
    "sg:address":"Carrer de Balmes, 15",
    "sg:city":"Bisbal Del Penedes",
    "sg:orig_category":"Poller\u00cda Y Caza (al Por Menor)",
    "sg:phone":"+34 977 68 85 53",
    "sg:postcode":"43717",
    "sg:province":"Tarragona",
    "wof:name":"Guasch Papiol Pedro",
    "wof:placetype":"venue"
},
  "geometry": {"coordinates":[1.4875580072,41.2824020386],"type":"Point"}
}