{
  "type": "Feature",
  "properties": {
    "addr:full":"Calle de Cristo (el), 11 Ponferrada Le\u00f3n 24400",
    "addr:housenumber":"11",
    "addr:postcode":"24400",
    "addr:street":"Calle De Cristo El",
    "iso:country":"ES",
    "sg:address":"Calle de Cristo (el), 11",
    "sg:city":"Ponferrada",
    "sg:orig_category":"Sociedades, Compa\u00d1\u00cdas Aseguradoras",
    "sg:phone":"+34 987 42 72 72",
    "sg:postcode":"24400",
    "sg:province":"Le\u00f3n",
    "wof:name":"Tecnicos Abella Correduria De Seguros S.l.",
    "wof:placetype":"venue"
},
  "geometry": {"coordinates":[-6.5974822044,42.5473518372],"type":"Point"}
}