{
  "type": "Feature",
  "properties": {
    "addr:full":"Carrer de Constitucio (de La), 31 Gata Gorgos Alicante 03740",
    "addr:housenumber":"31",
    "addr:postcode":"03740",
    "addr:street":"Carrer De Constitucio De La",
    "iso:country":"ES",
    "sg:address":"Carrer de Constitucio (de La), 31",
    "sg:city":"Gata Gorgos",
    "sg:orig_category":"Perfumer\u00cda (al Por Menor)",
    "sg:phone":"+34 965 75 62 66",
    "sg:postcode":"03740",
    "sg:province":"Alicante",
    "wof:name":"Signes Monfort Magdalena",
    "wof:placetype":"venue"
},
  "geometry": {"coordinates":[0.0838349983,38.7745437622],"type":"Point"}
}