{
  "type": "Feature",
  "properties": {
    "iso:country":"ES",
    "sg:address":"Calle de Antonio Concha, 61",
    "sg:city":"Navalmoral Mata",
    "sg:orig_category":"Abogados",
    "sg:phone":"+34 927 53 46 46",
    "sg:postcode":"10300",
    "sg:province":"C\u00e1ceres",
    "wof:name":"Gomez Esteban Julio",
    "wof:placetype":"venue"
},
  "geometry": {"coordinates":[-5.5375685692,39.8904190063],"type":"Point"}
}