{
  "type": "Feature",
  "properties": {
    "addr:full":"Villarroa\u00f1e, Km. 0003,0 Sta Olaja Ribera Le\u00f3n 24199",
    "addr:postcode":"24199",
    "addr:street":"Villarroan\u0303E Km. 0003,0 Sta Olaja Ribera Leo\u0301N",
    "iso:country":"ES",
    "sg:address":"Villarroa\u00f1e, Km. 0003,0",
    "sg:city":"Sta Olaja Ribera",
    "sg:orig_category":"Rectificaci\u00d3n, Mecanizado, Fresado",
    "sg:phone":"+34 987 26 11 64",
    "sg:postcode":"24199",
    "sg:province":"Le\u00f3n",
    "wof:name":"Arias Gonzalez Juan Manuel",
    "wof:placetype":"venue"
},
  "geometry": {"coordinates":[-5.5717520714,42.5998764038],"type":"Point"}
}