{
  "type": "Feature",
  "properties": {
    "iso:country":"ES",
    "sg:address":"Rbla Marina, 368",
    "sg:city":"Hospitalet Llobregat",
    "sg:orig_category":"Molduras, Junquillos, Listones Y Molduras Perforadas",
    "sg:phone":"+34 933 36 59 16",
    "sg:postcode":"08907",
    "sg:province":"Barcelona",
    "wof:name":"Garcia Bayona Antonia Maria",
    "wof:placetype":"venue"
},
  "geometry": {"coordinates":[2.1106600761,41.3535919189],"type":"Point"}
}