{
  "type": "Feature",
  "properties": {
    "iso:country":"ES",
    "sg:address":"Avda Jose Mesa Y Lopez, 18",
    "sg:city":"Palmas De Gran Canaria",
    "sg:orig_category":"Sociedades, Compa\u00d1\u00cdas Aseguradoras",
    "sg:phone":"+34 928 22 47 76",
    "sg:postcode":"35007",
    "sg:province":"Las Palmas",
    "wof:name":"Centro De Seguros S.a.",
    "wof:placetype":"venue"
},
  "geometry": {"coordinates":[-15.4314022064,28.134979248],"type":"Point"}
}