{
  "type": "Feature",
  "properties": {
    "iso:country":"ES",
    "sg:address":"Avda San Cristobal, S/n",
    "sg:city":"Linares",
    "sg:orig_category":"Tiendas De Grano, Frutas Y Legumbres Secas (al Por Menor)",
    "sg:phone":"+34 953 60 24 37",
    "sg:postcode":"23700",
    "sg:province":"Ja\u00e9n",
    "wof:name":"Productos Alimenticios Belros S.a.",
    "wof:placetype":"venue"
},
  "geometry": {"coordinates":[-3.642234087,38.0896987915],"type":"Point"}
}