{
  "type": "Feature",
  "properties": {
    "iso:country":"ES",
    "sg:address":"Calle de Pedro Domingo, 1",
    "sg:city":"Madrid",
    "sg:orig_category":"Mercer\u00cda, Lencer\u00cda (al Por Menor)",
    "sg:phone":"+34 915 69 51 50",
    "sg:postcode":"28025",
    "sg:province":"Madrid",
    "wof:name":"Centro De Urgencias Odontologicas Anadent S.l.",
    "wof:placetype":"venue"
},
  "geometry": {"coordinates":[-3.7307500839,40.3858642578],"type":"Point"}
}