{
  "type": "Feature",
  "properties": {
    "iso:country":"ES",
    "sg:address":"Calle de Aviacion, 17",
    "sg:city":"San Vicente Del Raspeig-sant Vicent Del Raspeig",
    "sg:orig_category":"Molduras, Junquillos, Listones Y Molduras Perforadas",
    "sg:phone":"+34 965 66 63 25",
    "sg:postcode":"03690",
    "sg:province":"Alicante",
    "wof:name":"Cano Criado Felix",
    "wof:placetype":"venue"
},
  "geometry": {"coordinates":[-0.521196425,38.3945770264],"type":"Point"}
}