{
  "type": "Feature",
  "properties": {
    "iso:country":"ES",
    "sg:address":"Calle de San Andres, 1",
    "sg:city":"Almoradi",
    "sg:orig_category":"Bazares, Art\u00cdculos De Limpieza Y De Cocina (al Por Menor)",
    "sg:phone":"+34 965 70 04 37",
    "sg:postcode":"03160",
    "sg:province":"Alicante",
    "wof:name":"Aldeguer Aldeguer Jose Antonio",
    "wof:placetype":"venue"
},
  "geometry": {"coordinates":[-0.7907997966,38.1089439392],"type":"Point"}
}