{
  "type": "Feature",
  "properties": {
    "addr:full":"Rua Cesar Conti, 28 Bolo Ourense 32373",
    "addr:housenumber":"28",
    "addr:postcode":"32373",
    "addr:street":"Rua Cesar Conti",
    "iso:country":"ES",
    "sg:address":"Rua Cesar Conti, 28",
    "sg:city":"Bolo",
    "sg:orig_category":"Cajas De Ahorro",
    "sg:phone":"+34 988 32 30 78",
    "sg:postcode":"32373",
    "sg:province":"Ourense",
    "wof:name":"Caixa De Aforros De Vigo Ourense E Pontevedra",
    "wof:placetype":"venue"
},
  "geometry": {"coordinates":[-7.0795769691,42.2941207886],"type":"Point"}
}