{
  "type": "Feature",
  "properties": {
    "addr:full":"Calle de Infantas (de Las), 47 Aranjuez Madrid 28300",
    "addr:housenumber":"47",
    "addr:postcode":"28300",
    "addr:street":"Calle De Infantas De Las",
    "iso:country":"ES",
    "sg:address":"Calle de Infantas (de Las), 47",
    "sg:city":"Aranjuez",
    "sg:orig_category":"Bares, Piano",
    "sg:phone":"+34 918 92 42 77",
    "sg:postcode":"28300",
    "sg:province":"Madrid",
    "wof:name":"Jimenez Hernandez Francisco",
    "wof:placetype":"venue"
},
  "geometry": {"coordinates":[-3.6003844738,40.0348434448],"type":"Point"}
}