{
  "type": "Feature",
  "properties": {
    "iso:country":"ES",
    "sg:address":"Poli Industrial Francoli, S/n",
    "sg:city":"Campsa",
    "sg:orig_category":"M\u00c9dicos: Medicina General Orientada A La Homeopat\u00cda",
    "sg:phone":"+34 977 55 05 42",
    "sg:postcode":"43006",
    "sg:province":"Tarragona",
    "sg:website":"www.dhu.es",
    "wof:name":"Deutsche Homoopathie Union Iberica S.a.",
    "wof:placetype":"venue"
},
  "geometry": {"coordinates":[1.2209249735,41.1154441833],"type":"Point"}
}