{
  "type": "Feature",
  "properties": {
    "iso:country":"ES",
    "sg:address":"Calle de Antonio Machado, 12",
    "sg:city":"Calahorra",
    "sg:orig_category":"Aguas (distribuci\u00d3n, Servicios)",
    "sg:phone":"+34 941 13 13 48",
    "sg:postcode":"26500",
    "sg:province":"La Rioja",
    "wof:name":"Aqualia Gestion Integral Del Agua S.a.",
    "wof:placetype":"venue"
},
  "geometry": {"coordinates":[-1.9714338779,42.3055000305],"type":"Point"}
}