{
  "type": "Feature",
  "properties": {
    "addr:full":"Calle de Alcalde Isaac Dominguez, 7 Teror Las Palmas 35330",
    "addr:housenumber":"7",
    "addr:postcode":"35330",
    "addr:street":"Calle De Alcalde Isaac Dominguez",
    "iso:country":"ES",
    "sg:address":"Calle de Alcalde Isaac Dominguez, 7",
    "sg:city":"Teror",
    "sg:orig_category":"Loter\u00cda Y T\u00d3mbola",
    "sg:phone":"+34 928 63 11 67",
    "sg:postcode":"35330",
    "sg:province":"Las Palmas",
    "wof:name":"Marichal Gonzalez Maria Del Carmen",
    "wof:placetype":"venue"
},
  "geometry": {"coordinates":[-15.5469579697,28.0610084534],"type":"Point"}
}