{
  "type": "Feature",
  "properties": {
    "iso:country":"ES",
    "sg:address":"Calle de Huesca, 10",
    "sg:city":"Urrea Gaen",
    "sg:orig_category":"Electrodom\u00c9sticos (al Por Menor)",
    "sg:phone":"+34 978 82 16 18",
    "sg:postcode":"44593",
    "sg:province":"Teruel",
    "wof:name":"Jariod Fandos Jose Luis",
    "wof:placetype":"venue"
},
  "geometry": {"coordinates":[-0.4724450111,41.159614563],"type":"Point"}
}