{
  "type": "Feature",
  "properties": {
    "iso:country":"ES",
    "sg:address":"Calle de Fray Sebastian, 21",
    "sg:city":"Nava Asuncion",
    "sg:orig_category":"Alimentaci\u00d3n General (al Por Menor)",
    "sg:phone":"+34 921 58 07 98",
    "sg:postcode":"40450",
    "sg:province":"Segovia",
    "wof:name":"Briz Castro Jesus",
    "wof:placetype":"venue"
},
  "geometry": {"coordinates":[-4.4884591103,41.1546974182],"type":"Point"}
}