{
  "type": "Feature",
  "properties": {
    "addr:full":"Calle de San Ramon, 41 Yecla Murcia 30510",
    "addr:housenumber":"41",
    "addr:postcode":"30510",
    "addr:street":"Calle De San Ramon",
    "iso:country":"ES",
    "sg:address":"Calle de San Ramon, 41",
    "sg:city":"Yecla",
    "sg:orig_category":"Confecci\u00d3n De Zapatos",
    "sg:phone":"+34 968 79 19 27",
    "sg:postcode":"30510",
    "sg:province":"Murcia",
    "wof:name":"Mu\u00f1oz Gomez Francisco",
    "wof:placetype":"venue"
},
  "geometry": {"coordinates":[-1.1125450134,38.6145629883],"type":"Point"}
}