{
  "type": "Feature",
  "properties": {
    "addr:full":"Avda San Cristobal, 47 Palma De Gandia Valencia 46724",
    "addr:housenumber":"47",
    "addr:postcode":"46724",
    "addr:street":"Avda San Cristobal",
    "iso:country":"ES",
    "sg:address":"Avda San Cristobal, 47",
    "sg:city":"Palma De Gandia",
    "sg:orig_category":"Cooperativas Agr\u00cdcolas",
    "sg:phone":"+34 962 80 90 01",
    "sg:postcode":"46724",
    "sg:province":"Valencia",
    "wof:name":"Cooperativa Agricola San Miguel De Palma De Gandia Coop.v.",
    "wof:placetype":"venue"
},
  "geometry": {"coordinates":[-0.2205529958,38.9255485535],"type":"Point"}
}