{
  "type": "Feature",
  "properties": {
    "iso:country":"ES",
    "sg:address":"Calle de Antonio Perez Montesinos, 4",
    "sg:city":"Landete",
    "sg:orig_category":"Iglesia Cat\u00d3lica",
    "sg:phone":"+34 969 36 11 21",
    "sg:postcode":"16330",
    "sg:province":"Cuenca",
    "wof:name":"Parroquia Nuestra Se\u00f1ora De La Asuncion",
    "wof:placetype":"venue"
},
  "geometry": {"coordinates":[-1.3702863455,39.9104919434],"type":"Point"}
}