{
  "type": "Feature",
  "properties": {
    "addr:full":"Uscarres, 4 Iru\u00f1a Navarra 31014",
    "addr:housenumber":"4",
    "addr:postcode":"31014",
    "addr:street":"Uscarres",
    "iso:country":"ES",
    "sg:address":"Uscarres, 4",
    "sg:city":"Iru\u00f1a",
    "sg:orig_category":"Iglesias Cristianas Diversas",
    "sg:phone":"+34 948 36 32 36",
    "sg:postcode":"31014",
    "sg:province":"Navarra",
    "wof:name":"Testigos Cristianos De Jehova",
    "wof:placetype":"venue"
},
  "geometry": {"coordinates":[-1.6464979649,42.8254966736],"type":"Point"}
}