{
  "type": "Feature",
  "properties": {
    "addr:full":"Calle de Geologicas, 46 Alcorcon Madrid 28925",
    "addr:housenumber":"46",
    "addr:postcode":"28925",
    "addr:street":"Calle De Geologicas",
    "iso:country":"ES",
    "sg:address":"Calle de Geologicas, 46",
    "sg:city":"Alcorcon",
    "sg:orig_category":"Vidrio, Fabricaci\u00d3n Y Comercio",
    "sg:phone":"+34 916 43 87 65",
    "sg:postcode":"28925",
    "sg:province":"Madrid",
    "wof:name":"Lart Vidrio S.l.",
    "wof:placetype":"venue"
},
  "geometry": {"coordinates":[-3.8140120506,40.3367576599],"type":"Point"}
}