{
  "type": "Feature",
  "properties": {
    "addr:full":"Avda Carlos De Haya, 74 Malaga M\u00e1laga 29010",
    "addr:housenumber":"74",
    "addr:postcode":"29010",
    "addr:street":"Avda Carlos De Haya;Ma\u0301Laga",
    "iso:country":"ES",
    "sg:address":"Avda Carlos De Haya, 74",
    "sg:city":"Malaga",
    "sg:orig_category":"Loter\u00cda Y T\u00d3mbola",
    "sg:phone":"+34 952 28 13 95",
    "sg:postcode":"29010",
    "sg:province":"M\u00e1laga",
    "wof:name":"Valdivia Gutierrez Adelina",
    "wof:placetype":"venue"
},
  "geometry": {"coordinates":[-4.447535038,36.7223625183],"type":"Point"}
}