{
  "type": "Feature",
  "properties": {
    "iso:country":"ES",
    "sg:address":"Carr Cervantes Saavedra, 46",
    "sg:city":"Cerdera",
    "sg:orig_category":"Hilaturas, Hilos Y Actividades Relacionadas",
    "sg:phone":"+34 973 73 62 77",
    "sg:postcode":"25110",
    "sg:province":"Lleida",
    "wof:name":"Rosell Solsona Teresa",
    "wof:placetype":"venue"
},
  "geometry": {"coordinates":[0.5569900274,41.6662216187],"type":"Point"}
}