{
  "type": "Feature",
  "properties": {
    "iso:country":"ES",
    "sg:address":"Calvario, 11",
    "sg:city":"Espinardo",
    "sg:orig_category":"Bisuter\u00cda, Joyer\u00cda, Relojer\u00cda (al Por Menor)",
    "sg:phone":"+34 968 30 66 46",
    "sg:postcode":"30100",
    "sg:province":"Murcia",
    "wof:name":"Noguera Pardo Angel",
    "wof:placetype":"venue"
},
  "geometry": {"coordinates":[-1.1530259848,38.0106315613],"type":"Point"}
}