{
  "type": "Feature",
  "properties": {
    "iso:country":"ES",
    "sg:address":"Finca Colichet, 12",
    "sg:city":"Churriana",
    "sg:orig_category":"Internados & Ense\u00d1anza Privada",
    "sg:phone":"+34 952 62 12 96",
    "sg:postcode":"29140",
    "sg:province":"M\u00e1laga",
    "wof:name":"Hijas De La Caridad De San Vicente De Paul",
    "wof:placetype":"venue"
},
  "geometry": {"coordinates":[-4.5023150444,36.6485328674],"type":"Point"}
}