{
  "type": "Feature",
  "properties": {
    "addr:full":"Ctra Santo Domingo, 16 Morales C\u00f3rdoba 14012",
    "addr:housenumber":"16",
    "addr:postcode":"14012",
    "addr:street":"Ctra Santo Domingo;Co\u0301Rdoba",
    "iso:country":"ES",
    "sg:address":"Ctra Santo Domingo, 16",
    "sg:city":"Morales",
    "sg:orig_category":"Asilos De Ancianos. Centros Privados",
    "sg:phone":"+34 957 27 57 62",
    "sg:postcode":"14012",
    "sg:province":"C\u00f3rdoba",
    "wof:name":"Hermanas Hospitalarias De Jesus Nazareno",
    "wof:placetype":"venue"
},
  "geometry": {"coordinates":[-4.7528471947,37.9300079346],"type":"Point"}
}