{
  "type": "Feature",
  "properties": {
    "addr:full":"Calle de Juan Fernandez Suria, 9 Malaga M\u00e1laga 29010",
    "addr:postcode":"29010",
    "addr:street":"Calle De Juan Fernandez Suria 9 Malaga Ma\u0301Laga",
    "iso:country":"ES",
    "sg:address":"Calle de Juan Fernandez Suria, 9",
    "sg:city":"Malaga",
    "sg:orig_category":"Promotores Constructores",
    "sg:phone":"+34 952 61 49 10",
    "sg:postcode":"29010",
    "sg:province":"M\u00e1laga",
    "wof:name":"Gelavian S.l.",
    "wof:placetype":"venue"
},
  "geometry": {"coordinates":[-4.4388837814,36.7221755981],"type":"Point"}
}