{
  "type": "Feature",
  "properties": {
    "iso:country":"ES",
    "sg:address":"Calle de Ana De Austria, 27",
    "sg:city":"Madrid",
    "sg:orig_category":"Promotores Constructores",
    "sg:phone":"+34 917 65 00 91",
    "sg:postcode":"28050",
    "sg:province":"Madrid",
    "sg:website":"www.urpesa.com",
    "wof:name":"Knight Frank Espa\u00d1a S.a.",
    "wof:placetype":"venue"
},
  "geometry": {"coordinates":[-3.6595714092,40.4924163818],"type":"Point"}
}