{
  "type": "Feature",
  "properties": {
    "addr:full":"Monast. Vjo San Pedro, 2 Iru\u00f1a Navarra 31014",
    "addr:housenumber":"2",
    "addr:postcode":"31014",
    "addr:street":"San Pedro",
    "iso:country":"ES",
    "sg:address":"Monast. Vjo San Pedro, 2",
    "sg:city":"Iru\u00f1a",
    "sg:orig_category":"Laboratorios Y Trabajos De Fotograf\u00cda, V\u00cddeo Y Cine",
    "sg:phone":"+34 948 12 68 87",
    "sg:postcode":"31014",
    "sg:province":"Navarra",
    "wof:name":"Leon Espinar Rafael",
    "wof:placetype":"venue"
},
  "geometry": {"coordinates":[-1.6456480026,42.8257102966],"type":"Point"}
}