{
  "type": "Feature",
  "properties": {
    "addr:full":"Calle de Miguel Villanueva, 5 Logro\u00f1o La Rioja 26001",
    "addr:housenumber":"5",
    "addr:postcode":"26001",
    "addr:street":"Calle De Miguel Villanueva;Rioja",
    "iso:country":"ES",
    "sg:address":"Calle de Miguel Villanueva, 5",
    "sg:city":"Logro\u00f1o",
    "sg:orig_category":"Dentistas: Cirujanos Dentistas Cualificados En Ortopedia Odontofacial",
    "sg:phone":"+34 941 26 13 01",
    "sg:postcode":"26001",
    "sg:province":"La Rioja",
    "wof:name":"Ardanza Trevijano Moras Bruno",
    "wof:placetype":"venue"
},
  "geometry": {"coordinates":[-2.4458141327,42.4642219543],"type":"Point"}
}