{
  "type": "Feature",
  "properties": {
    "addr:full":"Carrer de Fontanills, 44 Masnou Barcelona 08320",
    "addr:housenumber":"44",
    "addr:postcode":"08320",
    "addr:street":"Carrer De Fontanills",
    "iso:country":"ES",
    "sg:address":"Carrer de Fontanills, 44",
    "sg:city":"Masnou",
    "sg:orig_category":"Notarios",
    "sg:phone":"+34 935 40 20 11",
    "sg:postcode":"08320",
    "sg:province":"Barcelona",
    "wof:name":"Torrent-esquirol, Notaris Associats,scp",
    "wof:placetype":"venue"
},
  "geometry": {"coordinates":[2.3224229813,41.4818725586],"type":"Point"}
}