{
  "type": "Feature",
  "properties": {
    "addr:full":"Calle de Belostikale, 1 Bilbao Vizcaya 48005",
    "addr:housenumber":"1",
    "addr:postcode":"48005",
    "addr:street":"Calle De Belostikale",
    "iso:country":"ES",
    "sg:address":"Calle de Belostikale, 1",
    "sg:city":"Bilbao",
    "sg:orig_category":"Peluquer\u00cdas, Peluquer\u00cda Mixta",
    "sg:phone":"+34 944 15 55 55",
    "sg:postcode":"48005",
    "sg:province":"Vizcaya",
    "sg:website":"www.anademiguel.com",
    "wof:name":"Marcos Meno Ana Maria",
    "wof:placetype":"venue"
},
  "geometry": {"coordinates":[-2.9245891571,43.2559242249],"type":"Point"}
}