{
  "type": "Feature",
  "properties": {
    "iso:country":"ES",
    "sg:address":"Calle de Narciso Monturiol, S/n",
    "sg:city":"Valmor-rompecubas",
    "sg:orig_category":"Cervezas (negociantes Y Depositarios)",
    "sg:phone":"+34 918 95 51 61",
    "sg:postcode":"28340",
    "sg:province":"Madrid",
    "wof:name":"Distribuciones De Oro S.l.",
    "wof:placetype":"venue"
},
  "geometry": {"coordinates":[-3.6677899361,40.1646308899],"type":"Point"}
}