{
  "type": "Feature",
  "properties": {
    "addr:full":"Calle de Mayor, 94 Alcantarilla Murcia 30820",
    "addr:housenumber":"94",
    "addr:postcode":"30820",
    "addr:street":"Calle De Mayor",
    "iso:country":"ES",
    "sg:address":"Calle de Mayor, 94",
    "sg:city":"Alcantarilla",
    "sg:orig_category":"Zapatos (al Por Menor)",
    "sg:phone":"+34 968 89 18 31",
    "sg:postcode":"30820",
    "sg:province":"Murcia",
    "wof:name":"Rubio Gutierrez Maria Luisa",
    "wof:placetype":"venue"
},
  "geometry": {"coordinates":[-1.2135289907,37.9697532654],"type":"Point"}
}