{
  "type": "Feature",
  "properties": {
    "iso:country":"ES",
    "sg:address":"Calle de Virgen Otero, 5",
    "sg:city":"Pola De Laviana",
    "sg:orig_category":"Escayola Y Productos De Escayola (fabricaci\u00d3n, Al Por Mayor)",
    "sg:phone":"+34 985 61 02 54",
    "sg:postcode":"33980",
    "sg:province":"Asturias",
    "wof:name":"Fernandez Fernandez Gil",
    "wof:placetype":"venue"
},
  "geometry": {"coordinates":[-5.5597968102,43.2432937622],"type":"Point"}
}