{
  "type": "Feature",
  "properties": {
    "iso:country":"ES",
    "sg:address":"Calle de Don Lope De Los Rios, 2",
    "sg:city":"Cordoba",
    "sg:orig_category":"Telas Y Sedas (al Por Menor)",
    "sg:phone":"+34 957 28 25 28",
    "sg:postcode":"14006",
    "sg:province":"C\u00f3rdoba",
    "wof:name":"Fernandez Calzado Miguel",
    "wof:placetype":"venue"
},
  "geometry": {"coordinates":[-4.7773842812,37.8972053528],"type":"Point"}
}