{
  "type": "Feature",
  "properties": {
    "iso:country":"ES",
    "sg:address":"Avda Zaragoza, 13",
    "sg:city":"Borriol",
    "sg:orig_category":"Fabricaci\u00d3n, Comercio De Muebles En Ca\u00d1a, Mimbre",
    "sg:phone":"+34 964 32 10 73",
    "sg:postcode":"12190",
    "sg:province":"Castell\u00f3n",
    "wof:name":"Castello Pallares Joaquin",
    "wof:placetype":"venue"
},
  "geometry": {"coordinates":[-0.0733560026,40.0402526855],"type":"Point"}
}