{
  "type": "Feature",
  "properties": {
    "addr:full":"Calle de Ortega Y Gasset, 11 Elda Alicante 03600",
    "addr:housenumber":"11",
    "addr:postcode":"03600",
    "addr:street":"Calle De Ortega Y Gasset",
    "iso:country":"ES",
    "sg:address":"Calle de Ortega Y Gasset, 11",
    "sg:city":"Elda",
    "sg:orig_category":"Cajas De Ahorro",
    "sg:phone":"+34 965 38 38 34",
    "sg:postcode":"03600",
    "sg:province":"Alicante",
    "wof:name":"Caja De Ahorros Del Mediterraneo",
    "wof:placetype":"venue"
},
  "geometry": {"coordinates":[-0.7948459983,38.4780006409],"type":"Point"}
}