{
  "type": "Feature",
  "properties": {
    "addr:full":"Calle de Mayor, 29 Burlada Navarra 31600",
    "addr:housenumber":"29",
    "addr:postcode":"31600",
    "addr:street":"Calle De Mayor",
    "iso:country":"ES",
    "sg:address":"Calle de Mayor, 29",
    "sg:city":"Burlada",
    "sg:orig_category":"Centros Comerciales Y Grandes Tiendas",
    "sg:phone":"+34 948 13 43 36",
    "sg:postcode":"31600",
    "sg:province":"Navarra",
    "wof:name":"Cien Center S.i.",
    "wof:placetype":"venue"
},
  "geometry": {"coordinates":[-1.6171469688,42.8248901367],"type":"Point"}
}