{
  "type": "Feature",
  "properties": {
    "addr:full":"Calle de Castillo, 6 Perales De Taju\u00e7a Madrid 28540",
    "addr:housenumber":"6",
    "addr:postcode":"28540",
    "addr:street":"Calle De Castillo",
    "iso:country":"ES",
    "sg:address":"Calle de Castillo, 6",
    "sg:city":"Perales De Taju\u00e7a",
    "sg:orig_category":"Pintura Industrial (trabajos De)",
    "sg:phone":"+34 918 74 91 08",
    "sg:postcode":"28540",
    "sg:province":"Madrid",
    "wof:name":"Hermanos Colmenar C.b.",
    "wof:placetype":"venue"
},
  "geometry": {"coordinates":[-3.7003455162,40.4166908264],"type":"Point"}
}