{
  "type": "Feature",
  "properties": {
    "iso:country":"ES",
    "sg:address":"Av Catalunya, 37",
    "sg:city":"S. Adria Besos",
    "sg:orig_category":"Alimentaci\u00d3n General (al Por Menor)",
    "sg:phone":"+34 933 81 17 45",
    "sg:postcode":"08930",
    "sg:province":"Barcelona",
    "wof:name":"Tarrason Redan Leonardo",
    "wof:placetype":"venue"
},
  "geometry": {"coordinates":[2.2172000408,41.431640625],"type":"Point"}
}