{
  "type": "Feature",
  "properties": {
    "addr:full":"Calle de Mortuero, S/n Carreras Vizcaya 48540",
    "addr:housenumber":"s",
    "addr:postcode":"48540",
    "addr:street":"Calle De Mortuero;/ N",
    "iso:country":"ES",
    "sg:address":"Calle de Mortuero, S/n",
    "sg:city":"Carreras",
    "sg:orig_category":"Asociaciones Y Clubs Deportivos",
    "sg:phone":"+34 946 36 86 93",
    "sg:postcode":"48540",
    "sg:province":"Vizcaya",
    "wof:name":"Abanto Club Sociedad Deportiva",
    "wof:placetype":"venue"
},
  "geometry": {"coordinates":[-3.096888,43.319313],"type":"Point"}
}