{
  "type": "Feature",
  "properties": {
    "iso:country":"ES",
    "sg:address":"Barrera, 46",
    "sg:city":"Lucena",
    "sg:orig_category":"Venta, Alquiler De Instrumentos Y Accesorios De M\u00dasica",
    "sg:phone":"+34 957 50 25 17",
    "sg:postcode":"14900",
    "sg:province":"C\u00f3rdoba",
    "wof:name":"Mu\u00f1oz Servian Jesus",
    "wof:placetype":"venue"
},
  "geometry": {"coordinates":[-4.4797391891,37.4077911377],"type":"Point"}
}