{
  "type": "Feature",
  "properties": {
    "iso:country":"ES",
    "sg:address":"Cami Papalus (de), S/n",
    "sg:city":"Papalus",
    "sg:orig_category":"Agencias De Viajes",
    "sg:phone":"+34 972 37 25 16",
    "sg:postcode":"17310",
    "sg:province":"Girona",
    "sg:website":"www.iberoservice.com",
    "wof:name":"Iberoservice S.a.",
    "wof:placetype":"venue"
},
  "geometry": {"coordinates":[2.846834898,41.6981697083],"type":"Point"}
}