{
  "type": "Feature",
  "properties": {
    "iso:country":"ES",
    "sg:address":"Praz Constitucion 1812, 7",
    "sg:city":"Redondela",
    "sg:orig_category":"Inmobiliaria (agencias)",
    "sg:phone":"+34 986 40 99 29",
    "sg:postcode":"36800",
    "sg:province":"Pontevedra",
    "wof:name":"Frerod S.l.",
    "wof:placetype":"venue"
},
  "geometry": {"coordinates":[-8.608669281,42.2839317322],"type":"Point"}
}