{
  "type": "Feature",
  "properties": {
    "iso:country":"ES",
    "sg:address":"Calle de Carolina La, S/n",
    "sg:city":"Churriana",
    "sg:orig_category":"Centros De Educaci\u00d3n Especial",
    "sg:phone":"+34 952 62 16 44",
    "sg:postcode":"29140",
    "sg:province":"M\u00e1laga",
    "wof:name":"Colegio Publico Manuel Fernandez",
    "wof:placetype":"venue"
},
  "geometry": {"coordinates":[-4.5078282356,36.6733894348],"type":"Point"}
}