{
  "type": "Feature",
  "properties": {
    "addr:full":"Pase San Francisco De Sales, 3 Madrid Madrid 28003",
    "addr:housenumber":"3",
    "addr:postcode":"28003",
    "addr:street":"Francisco De Sales",
    "iso:country":"ES",
    "sg:address":"Pase San Francisco De Sales, 3",
    "sg:city":"Madrid",
    "sg:orig_category":"M\u00c9dicos: Cardiolog\u00cda Y Afecciones Cardiovasculares",
    "sg:phone":"+34 915 49 97 28",
    "sg:postcode":"28003",
    "sg:province":"Madrid",
    "wof:name":"Fundacion Medica Para La Investigacion Y Desarrollo Cardiovascular",
    "wof:placetype":"venue"
},
  "geometry": {"coordinates":[-3.7171030045,40.4397468567],"type":"Point"}
}