{
  "type": "Feature",
  "properties": {
    "addr:full":"Carrer de Segura, S/n Barcelona Barcelona 08038",
    "addr:housenumber":"s / n",
    "addr:postcode":"08038",
    "addr:street":"Carrer De Segura",
    "iso:country":"ES",
    "sg:address":"Carrer de Segura, S/n",
    "sg:city":"Barcelona",
    "sg:orig_category":"Restaurantes",
    "sg:phone":"+34 933 32 03 97",
    "sg:postcode":"08038",
    "sg:province":"Barcelona",
    "wof:name":"Tevite S.l.",
    "wof:placetype":"venue"
},
  "geometry": {"coordinates":[2.1409409046,41.3635749817],"type":"Point"}
}