{
  "type": "Feature",
  "properties": {
    "iso:country":"ES",
    "sg:address":"Carr Marques Del Turia, 7",
    "sg:city":"Quart Poblet",
    "sg:orig_category":"Agentes, Concesionarios Y Sucursales De Veh\u00cdculos",
    "sg:phone":"+34 961 53 33 98",
    "sg:postcode":"46930",
    "sg:province":"Valencia",
    "wof:name":"Amigo Motor S.l.",
    "wof:placetype":"venue"
},
  "geometry": {"coordinates":[-0.437946409,39.4822807312],"type":"Point"}
}