{
  "type": "Feature",
  "properties": {
    "iso:country":"ES",
    "sg:address":"Calle de Faisan, 9",
    "sg:city":"Fuenlabrada",
    "sg:orig_category":"Asesor\u00cdas En Comunicaci\u00d3n",
    "sg:phone":"+34 916 42 23 23",
    "sg:postcode":"28...",
    "sg:province":"Madrid",
    "wof:name":"Tsi Ingenieria De Imagen S.a.",
    "wof:placetype":"venue"
},
  "geometry": {"coordinates":[-3.7647299767,40.2609367371],"type":"Point"}
}