{
  "type": "Feature",
  "properties": {
    "iso:country":"ES",
    "sg:address":"Calle de Rubiera, 23",
    "sg:city":"Poligono Industrial Los Villares",
    "sg:orig_category":"Ebanister\u00cda",
    "sg:phone":"+34 923 24 07 12",
    "sg:postcode":"37184",
    "sg:province":"Salamanca",
    "wof:name":"Caballero De La Cruz Francisco Jose",
    "wof:placetype":"venue"
},
  "geometry": {"coordinates":[-5.6465191841,40.9891052246],"type":"Point"}
}