{
  "type": "Feature",
  "properties": {
    "addr:full":"Plaz Mayor, S/n Escalona Prado Segovia 40350",
    "addr:housenumber":"s / n",
    "addr:postcode":"40350",
    "addr:street":"Plaz Mayor",
    "iso:country":"ES",
    "sg:address":"Plaz Mayor, S/n",
    "sg:city":"Escalona Prado",
    "sg:orig_category":"Sanatorios M\u00c9dico",
    "sg:phone":"+34 921 57 02 26",
    "sg:postcode":"40350",
    "sg:province":"Segovia",
    "wof:name":"Ayuntamiento",
    "wof:placetype":"venue"
},
  "geometry": {"coordinates":[-4.1218671799,41.1667861938],"type":"Point"}
}