{
  "type": "Feature",
  "properties": {
    "iso:country":"ES",
    "sg:address":"Calle de San Diego, S/n",
    "sg:city":"Taucho",
    "sg:orig_category":"Inmobiliaria (agencias)",
    "sg:phone":"+34 922 69 11 99",
    "sg:postcode":"38670",
    "sg:province":"Santa Cruz De Tenerife",
    "wof:name":"Wimpen Leisure Management S.a.",
    "wof:placetype":"venue"
},
  "geometry": {"coordinates":[-16.724899292,28.1215400696],"type":"Point"}
}