{
  "type": "Feature",
  "properties": {
    "addr:full":"Carr Galligans, 4 Figueres Girona 17600",
    "addr:housenumber":"4",
    "addr:postcode":"17600",
    "addr:street":"Carr Galligans",
    "iso:country":"ES",
    "sg:address":"Carr Galligans, 4",
    "sg:city":"Figueres",
    "sg:orig_category":"Panader\u00cdas, Panader\u00cdas",
    "sg:phone":"+34 972 50 01 27",
    "sg:postcode":"17600",
    "sg:province":"Girona",
    "wof:name":"Vidal Roura Fortunato",
    "wof:placetype":"venue"
},
  "geometry": {"coordinates":[2.9591789246,42.2660980225],"type":"Point"}
}