{
  "type": "Feature",
  "properties": {
    "addr:full":"Calle de Picasso, 5 Trigueros Huelva 21620",
    "addr:housenumber":"5",
    "addr:postcode":"21620",
    "addr:street":"Calle De Picasso",
    "iso:country":"ES",
    "sg:address":"Calle de Picasso, 5",
    "sg:city":"Trigueros",
    "sg:orig_category":"Papeler\u00cdas, Librer\u00cdas",
    "sg:phone":"+34 959 30 68 00",
    "sg:postcode":"21620",
    "sg:province":"Huelva",
    "wof:name":"Grafipapel Trigueras C.b.",
    "wof:placetype":"venue"
},
  "geometry": {"coordinates":[-6.8304791451,37.3835754395],"type":"Point"}
}