{
  "type": "Feature",
  "properties": {
    "iso:country":"ES",
    "sg:address":"Calle de Amadeo Vives, 31",
    "sg:city":"Matas-pinar-monte Rozas",
    "sg:orig_category":"Iglesia Cat\u00d3lica",
    "sg:phone":"+34 916 30 37 00",
    "sg:postcode":"28290",
    "sg:province":"Madrid",
    "wof:name":"Parroquia De San Jose. Las Matas",
    "wof:placetype":"venue"
},
  "geometry": {"coordinates":[-3.8915719986,40.5526924133],"type":"Point"}
}