{
  "type": "Feature",
  "properties": {
    "addr:full":"Calle de Navas De Tolosa, 3 Carolina Ja\u00e9n 23200",
    "addr:housenumber":"3",
    "addr:postcode":"23200",
    "addr:street":"Calle De Navas De Tolosa;Carolina Jae\u0301N",
    "iso:country":"ES",
    "sg:address":"Calle de Navas De Tolosa, 3",
    "sg:city":"Carolina",
    "sg:orig_category":"Soportes L\u00d3gicos, Programas Integradores De Aplicaciones (progiciels)",
    "sg:phone":"+34 953 66 21 49",
    "sg:postcode":"23200",
    "sg:province":"Ja\u00e9n",
    "sg:website":"www.beep.es",
    "wof:name":"Servicios E Informatica Carolina S.l",
    "wof:placetype":"venue"
},
  "geometry": {"coordinates":[-3.6136529446,38.2755203247],"type":"Point"}
}