{
  "type": "Feature",
  "properties": {
    "addr:full":"Avda Fermin Bouza Brey, 12 Ponteareas Pontevedra 36860",
    "addr:housenumber":"12",
    "addr:postcode":"36860",
    "addr:street":"Avda Fermin Bouza Brey",
    "iso:country":"ES",
    "sg:address":"Avda Fermin Bouza Brey, 12",
    "sg:city":"Ponteareas",
    "sg:orig_category":"Inmobiliaria (agencias)",
    "sg:phone":"+34 986 66 11 78",
    "sg:postcode":"36860",
    "sg:province":"Pontevedra",
    "wof:name":"Inmobiliaria Alen Mi\u00f1o Sl",
    "wof:placetype":"venue"
},
  "geometry": {"coordinates":[-8.5163888931,42.1783599854],"type":"Point"}
}