{
  "type": "Feature",
  "properties": {
    "iso:country":"ES",
    "sg:address":"Avda Independencia, S/n",
    "sg:city":"Marbella",
    "sg:orig_category":"Zapatos (al Por Menor)",
    "sg:phone":"+34 952 77 58 53",
    "sg:postcode":"29600",
    "sg:province":"M\u00e1laga",
    "wof:name":"Fernandez Plaza Francisco",
    "wof:placetype":"venue"
},
  "geometry": {"coordinates":[-4.886223793,36.5162391663],"type":"Point"}
}