{
  "type": "Feature",
  "properties": {
    "addr:full":"Barrenkalea, 21 Bergara Guip\u00f9zcoa 20570",
    "addr:housenumber":"21",
    "addr:postcode":"20570",
    "addr:street":"Barrenkalea;Guipu\u0300Zcoa",
    "iso:country":"ES",
    "sg:address":"Barrenkalea, 21",
    "sg:city":"Bergara",
    "sg:orig_category":"Herboristas (al Por Menor)",
    "sg:phone":"+34 943 76 30 08",
    "sg:postcode":"20570",
    "sg:province":"Guip\u00f9zcoa",
    "wof:name":"Altube Belar Alberto",
    "wof:placetype":"venue"
},
  "geometry": {"coordinates":[-2.4128518105,43.1183586121],"type":"Point"}
}