{
  "type": "Feature",
  "properties": {
    "iso:country":"ES",
    "sg:address":"Carrer de Gravina, 11",
    "sg:city":"S. Adria Besos",
    "sg:orig_category":"Comercio De Cuadros, L\u00c1minas Y Reproducciones De Obras De Arte",
    "sg:phone":"+34 933 81 81 60",
    "sg:postcode":"08930",
    "sg:province":"Barcelona",
    "sg:website":"www.adarveart.com",
    "wof:name":"Adarve Art S.l.",
    "wof:placetype":"venue"
},
  "geometry": {"coordinates":[2.2295145988,41.4295883179],"type":"Point"}
}