{
  "type": "Feature",
  "properties": {
    "iso:country":"ES",
    "sg:address":"Calle de General Kirkpatrick, 33",
    "sg:city":"Madrid",
    "sg:orig_category":"Ingenier\u00cda, Centros De Estudios (diversos)",
    "sg:phone":"+34 914 08 93 67",
    "sg:postcode":"28027",
    "sg:province":"Madrid",
    "wof:name":"Summa Global S.l.",
    "wof:placetype":"venue"
},
  "geometry": {"coordinates":[-3.6478710175,40.4452095032],"type":"Point"}
}