{
  "type": "Feature",
  "properties": {
    "addr:full":"Calle de Mayor, 9 Alcaraz Albacete 02300",
    "addr:housenumber":"9",
    "addr:postcode":"02300",
    "addr:street":"Calle De Mayor",
    "iso:country":"ES",
    "sg:address":"Calle de Mayor, 9",
    "sg:city":"Alcaraz",
    "sg:orig_category":"Zapater\u00cdas",
    "sg:phone":"+34 967 38 01 46",
    "sg:postcode":"02300",
    "sg:province":"Albacete",
    "wof:name":"Tebar Vazquez Antonio",
    "wof:placetype":"venue"
},
  "geometry": {"coordinates":[-2.4913680553,38.6658172607],"type":"Point"}
}