{
  "type": "Feature",
  "properties": {
    "iso:country":"ES",
    "sg:address":"Carr Trobat, 10",
    "sg:city":"Xativa",
    "sg:orig_category":"Promotores Constructores",
    "sg:phone":"+34 962 27 44 21",
    "sg:postcode":"46800",
    "sg:province":"Valencia",
    "wof:name":"Hernandez Perez Eloy Jose",
    "wof:placetype":"venue"
},
  "geometry": {"coordinates":[-0.5222970247,38.9888763428],"type":"Point"}
}