{
  "type": "Feature",
  "properties": {
    "addr:full":"Carrer de Flor De Neu, 14 Barcelona Barcelona 08016",
    "addr:housenumber":"14",
    "addr:postcode":"08016",
    "addr:street":"Carrer De Flor De Neu",
    "iso:country":"ES",
    "sg:address":"Carrer de Flor De Neu, 14",
    "sg:city":"Barcelona",
    "sg:orig_category":"Panader\u00cdas, Panader\u00cdas",
    "sg:phone":"+34 933 53 46 61",
    "sg:postcode":"08016",
    "sg:province":"Barcelona",
    "wof:name":"Pitas Damas C.b.",
    "wof:placetype":"venue"
},
  "geometry": {"coordinates":[2.1856870651,41.4443817139],"type":"Point"}
}