{
  "type": "Feature",
  "properties": {
    "iso:country":"ES",
    "sg:address":"Av Manuel Girona, S/n",
    "sg:city":"Castelldefels",
    "sg:orig_category":"Centros De Educaci\u00d3n Especial",
    "sg:phone":"+34 936 65 40 52",
    "sg:postcode":"08860",
    "sg:province":"Barcelona",
    "wof:name":"Ajuntament De Castelldefels",
    "wof:placetype":"venue"
},
  "geometry": {"coordinates":[1.9802434444,41.2856445312],"type":"Point"}
}