{
  "type": "Feature",
  "properties": {
    "addr:full":"Trav De Gracia, 12 Barcelona Barcelona 08021",
    "addr:housenumber":"12",
    "addr:postcode":"08021",
    "addr:street":"Trav De Gracia",
    "iso:country":"ES",
    "sg:address":"Trav De Gracia, 12",
    "sg:city":"Barcelona",
    "sg:orig_category":"Art\u00cdculos De Decoraci\u00d3n",
    "sg:phone":"+34 932 00 58 02",
    "sg:postcode":"08021",
    "sg:province":"Barcelona",
    "wof:name":"Alterra S.l.",
    "wof:placetype":"venue"
},
  "geometry": {"coordinates":[2.1689713001,41.3890762329],"type":"Point"}
}