{
  "type": "Feature",
  "properties": {
    "addr:full":"De La Peseta, 1 Isla Cristina Huelva 21410",
    "addr:postcode":"21410",
    "iso:country":"ES",
    "sg:address":"De La Peseta, 1",
    "sg:city":"Isla Cristina",
    "sg:orig_category":"Fabricaci\u00d3n, Distribuci\u00d3n De Material Para La Climatizaci\u00d3n, Aireaci\u00d3n Y Ventilaci\u00d3n",
    "sg:phone":"+34 959 34 33 06",
    "sg:postcode":"21410",
    "sg:province":"Huelva",
    "wof:name":"Islaclimanpe",
    "wof:placetype":"venue"
},
  "geometry": {"coordinates":[-7.3212938309,37.2044334412],"type":"Point"}
}