{
  "type": "Feature",
  "properties": {
    "iso:country":"ES",
    "sg:address":"Bard Nuestra Se\u00d1ora De La Oliva, S/n",
    "sg:city":"Sevilla",
    "sg:orig_category":"Reposter\u00cdas",
    "sg:phone":"+34 954 61 43 04",
    "sg:postcode":"41013",
    "sg:province":"Sevilla",
    "wof:name":"Iglesia Pla Maria Felisa",
    "wof:placetype":"venue"
},
  "geometry": {"coordinates":[-5.9674739838,37.3655357361],"type":"Point"}
}