{
  "type": "Feature",
  "properties": {
    "iso:country":"ES",
    "sg:address":"Calle de Santa Fe, 35",
    "sg:city":"Puerto De Santa Maria",
    "sg:orig_category":"Molduras, Junquillos, Listones Y Molduras Perforadas",
    "sg:phone":"+34 956 87 03 02",
    "sg:postcode":"11500",
    "sg:province":"C\u00e1diz",
    "wof:name":"Calvario Perez Jose Manuel",
    "wof:placetype":"venue"
},
  "geometry": {"coordinates":[-6.2311477661,36.602230072],"type":"Point"}
}