{
  "type": "Feature",
  "properties": {
    "addr:full":"Carrer de Riera Roja, 20 S. Boi Llobregat Barcelona 08830",
    "addr:housenumber":"20",
    "addr:postcode":"08830",
    "addr:street":"Carrer De Riera Roja",
    "iso:country":"ES",
    "sg:address":"Carrer de Riera Roja, 20",
    "sg:city":"S. Boi Llobregat",
    "sg:orig_category":"Acero: Productos Sider\u00dargicos Y Transformados (fabricaci\u00d3n, Negocio)",
    "sg:phone":"+34 936 40 18 04",
    "sg:postcode":"08830",
    "sg:province":"Barcelona",
    "wof:name":"Cdc Hiacre S.a.",
    "wof:placetype":"venue"
},
  "geometry": {"coordinates":[2.0453400612,41.3298721313],"type":"Point"}
}