{
  "type": "Feature",
  "properties": {
    "addr:full":"Carrer de Sant Joan, 36 Reus Tarragona 43201",
    "addr:housenumber":"36",
    "addr:postcode":"43201",
    "addr:street":"Carrer De Sant Joan",
    "iso:country":"ES",
    "sg:address":"Carrer de Sant Joan, 36",
    "sg:city":"Reus",
    "sg:orig_category":"Sociedades, Compa\u00d1\u00cdas Aseguradoras",
    "sg:phone":"+34 977 33 33 08",
    "sg:postcode":"43201",
    "sg:province":"Tarragona",
    "sg:website":"www.suarezconsultores.com",
    "wof:name":"Suarez Consultores Correduria De Seguros S.l.",
    "wof:placetype":"venue"
},
  "geometry": {"coordinates":[1.102594018,41.1561088562],"type":"Point"}
}