{
  "type": "Feature",
  "properties": {
    "iso:country":"ES",
    "sg:address":"Calle de Pablo Casals, 19",
    "sg:city":"Burgos",
    "sg:orig_category":"Arreglo, Reparaci\u00d3n, Piezas Sueltas De Televisi\u00d3n, V\u00cddeo, Hi",
    "sg:phone":"+34 947 48 69 96",
    "sg:postcode":"09007",
    "sg:province":"Burgos",
    "wof:name":"Vega Renes Jose Ramon",
    "wof:placetype":"venue"
},
  "geometry": {"coordinates":[-3.6646099091,42.3537063599],"type":"Point"}
}