{
  "type": "Feature",
  "properties": {
    "addr:full":"Carrer de Diputacio, 243 Barcelona Barcelona 08007",
    "addr:housenumber":"243",
    "addr:postcode":"08007",
    "addr:street":"Carrer De Diputacio",
    "iso:country":"ES",
    "sg:address":"Carrer de Diputacio, 243",
    "sg:city":"Barcelona",
    "sg:orig_category":"Aparcamientos (infraestructuras, Accesorios)",
    "sg:phone":"+34 934 87 71 64",
    "sg:postcode":"08007",
    "sg:province":"Barcelona",
    "wof:name":"Cantarell Y Cia S.r.c.",
    "wof:placetype":"venue"
},
  "geometry": {"coordinates":[2.1647529602,41.3888664246],"type":"Point"}
}