{
  "type": "Feature",
  "properties": {
    "iso:country":"ES",
    "sg:address":"Carr 25 D'abril, 2",
    "sg:city":"Cullera",
    "sg:orig_category":"Asociaciones Y Clubs Deportivos",
    "sg:phone":"+34 961 72 35 13",
    "sg:postcode":"46400",
    "sg:province":"Valencia",
    "sg:website":"www.deportesalapont.es",
    "wof:name":"Deportes Alapont S.l.",
    "wof:placetype":"venue"
},
  "geometry": {"coordinates":[-0.2480420023,39.1633262634],"type":"Point"}
}