{
  "type": "Feature",
  "properties": {
    "addr:full":"Carrer de Pau Claris, 89 Barcelona Barcelona 08010",
    "addr:housenumber":"89",
    "addr:postcode":"08010",
    "addr:street":"Carrer De Pau Claris",
    "iso:country":"ES",
    "sg:address":"Carrer de Pau Claris, 89",
    "sg:city":"Barcelona",
    "sg:orig_category":"Agencias De Trabajo Temporal",
    "sg:phone":"+34 933 17 12 11",
    "sg:postcode":"08010",
    "sg:province":"Barcelona",
    "wof:name":"Trabatem E.t.t. S.a.",
    "wof:placetype":"venue"
},
  "geometry": {"coordinates":[2.1702980995,41.3901367188],"type":"Point"}
}