{
  "type": "Feature",
  "properties": {
    "iso:country":"ES",
    "sg:address":"Calle de Eufrosino Martinez Azorin, 1",
    "sg:city":"Ayora",
    "sg:orig_category":"Venta, Montaje De Neum\u00c1ticos",
    "sg:phone":"+34 961 89 03 66",
    "sg:postcode":"46620",
    "sg:province":"Valencia",
    "wof:name":"Talleres Quilez Ayora S.l.",
    "wof:placetype":"venue"
},
  "geometry": {"coordinates":[-1.052718997,39.0567207336],"type":"Point"}
}