{
  "type": "Feature",
  "properties": {
    "iso:country":"ES",
    "sg:address":"Av Verge De Montserrat, 51",
    "sg:city":"Barbera Valles",
    "sg:orig_category":"Institutos De Belleza",
    "sg:phone":"+34 937 18 40 99",
    "sg:postcode":"08210",
    "sg:province":"Barcelona",
    "wof:name":"Ruiz Ruiz Libertad",
    "wof:placetype":"venue"
},
  "geometry": {"coordinates":[2.1235198975,41.5140419006],"type":"Point"}
}