{
  "type": "Feature",
  "properties": {
    "iso:country":"ES",
    "sg:address":"Calle de Potosi, 9",
    "sg:city":"Madrid",
    "sg:orig_category":"Arquitectos",
    "sg:phone":"+34 914 57 00 04",
    "sg:postcode":"28016",
    "sg:province":"Madrid",
    "sg:website":"www.fechevarria.org",
    "wof:name":"Echevarria Sainz Federico",
    "wof:placetype":"venue"
},
  "geometry": {"coordinates":[-3.6794838905,40.4568901062],"type":"Point"}
}