{
  "type": "Feature",
  "properties": {
    "iso:country":"ES",
    "sg:address":"Carrer de Sant Ferran, 5",
    "sg:city":"Mataro",
    "sg:orig_category":"Imprenta",
    "sg:phone":"+34 937 57 39 51",
    "sg:postcode":"08304",
    "sg:province":"Barcelona",
    "sg:website":"www.imaresme.com",
    "wof:name":"Imprenta Maresme S.l.",
    "wof:placetype":"venue"
},
  "geometry": {"coordinates":[2.4346330166,41.5499420166],"type":"Point"}
}