{
  "type": "Feature",
  "properties": {
    "iso:country":"ES",
    "sg:address":"Sar, 16",
    "sg:city":"Beluso",
    "sg:orig_category":"Vinos Y Licores (venta Al Por Menor)",
    "sg:phone":"+34 986 32 07 11",
    "sg:postcode":"36939",
    "sg:province":"Pontevedra",
    "wof:name":"Medra\u00f1o Queiruga Julio",
    "wof:placetype":"venue"
},
  "geometry": {"coordinates":[-8.7823858261,42.3033218384],"type":"Point"}
}