{
  "type": "Feature",
  "properties": {
    "addr:full":"Calle de Morago, 15 Manzanares Ciudad Real 13200",
    "addr:housenumber":"15",
    "addr:postcode":"13200",
    "addr:street":"Calle De Morago",
    "iso:country":"ES",
    "sg:address":"Calle de Morago, 15",
    "sg:city":"Manzanares",
    "sg:orig_category":"Doctores En Medicina",
    "sg:phone":"+34 926 61 02 12",
    "sg:postcode":"13200",
    "sg:province":"Ciudad Real",
    "wof:name":"Calero Bola\u00f1os Pedro",
    "wof:placetype":"venue"
},
  "geometry": {"coordinates":[-3.3703188896,38.9991111755],"type":"Point"}
}