{
  "type": "Feature",
  "properties": {
    "iso:country":"ES",
    "sg:address":"Calle de Santa Teresa, 5",
    "sg:city":"Alcala Henares",
    "sg:orig_category":"Mercer\u00cda, Lencer\u00cda (al Por Menor)",
    "sg:phone":"+34 918 83 30 37",
    "sg:postcode":"28803",
    "sg:province":"Madrid",
    "wof:name":"Carrero Martinez Antonia",
    "wof:placetype":"venue"
},
  "geometry": {"coordinates":[-3.376832962,40.4738464355],"type":"Point"}
}