{
  "type": "Feature",
  "properties": {
    "iso:country":"ES",
    "sg:address":"Calle de Alcalde Marcelino Sanz, 4",
    "sg:city":"Majadahonda",
    "sg:orig_category":"Electricidad: Instaladores",
    "sg:phone":"+34 916 38 19 42",
    "sg:postcode":"28220",
    "sg:province":"Madrid",
    "wof:name":"Carames Montero Ismael",
    "wof:placetype":"venue"
},
  "geometry": {"coordinates":[-3.8751647472,40.4683227539],"type":"Point"}
}