{
  "type": "Feature",
  "properties": {
    "iso:country":"ES",
    "sg:address":"Arbona Colom, 6",
    "sg:city":"Fornalutx",
    "sg:orig_category":"Venta, Instalaci\u00d3n De Cocinas",
    "sg:phone":"+34 971 63 08 08",
    "sg:postcode":"07109",
    "sg:province":"Islas Baleares",
    "wof:name":"Maria Francisca I Bernardo Cabot C.b.",
    "wof:placetype":"venue"
},
  "geometry": {"coordinates":[2.7431418896,39.7839393616],"type":"Point"}
}