{
  "type": "Feature",
  "properties": {
    "iso:country":"ES",
    "sg:address":"Carrer de Catalunya, 62",
    "sg:city":"Prat Llobregat",
    "sg:orig_category":"Laboratorios Y Trabajos De Fotograf\u00cda, V\u00cddeo Y Cine",
    "sg:phone":"+34 933 70 69 03",
    "sg:postcode":"08820",
    "sg:province":"Barcelona",
    "wof:name":"Moreno Carrillo Maria Rosario",
    "wof:placetype":"venue"
},
  "geometry": {"coordinates":[2.097342968,41.324054718],"type":"Point"}
}