{
  "type": "Feature",
  "properties": {
    "addr:full":"Pase San Francisco De Sales, 6 Madrid Madrid 28003",
    "addr:housenumber":"6",
    "addr:postcode":"28003",
    "addr:street":"Francisco De Sales",
    "iso:country":"ES",
    "sg:address":"Pase San Francisco De Sales, 6",
    "sg:city":"Madrid",
    "sg:orig_category":"Agencias Y Agentes Comerciales, Representantes",
    "sg:phone":"+34 914 41 46 08",
    "sg:postcode":"28003",
    "sg:province":"Madrid",
    "wof:name":"Antonio Llorente Blanco S.l.",
    "wof:placetype":"venue"
},
  "geometry": {"coordinates":[-3.9667513371,40.4892883301],"type":"Point"}
}