{
  "type": "Feature",
  "properties": {
    "iso:country":"ES",
    "sg:address":"Calle de Bajada Escuelas, 9",
    "sg:city":"Peralta",
    "sg:orig_category":"Panader\u00cdas, Panader\u00cdas",
    "sg:phone":"+34 948 75 04 28",
    "sg:postcode":"31350",
    "sg:province":"Navarra",
    "wof:name":"Marquez Dominguez Rocio",
    "wof:placetype":"venue"
},
  "geometry": {"coordinates":[-1.7993171215,42.3379821777],"type":"Point"}
}