{
  "type": "Feature",
  "properties": {
    "addr:full":"Calle de Esperantista Enrique Arnau, S/n Cheste Valencia 46380",
    "addr:housenumber":"s / n",
    "addr:postcode":"46380",
    "addr:street":"Calle De Esperantista Enrique Arnau",
    "iso:country":"ES",
    "sg:address":"Calle de Esperantista Enrique Arnau, S/n",
    "sg:city":"Cheste",
    "sg:orig_category":"Sanatorios M\u00c9dico",
    "sg:phone":"+34 962 51 28 80",
    "sg:postcode":"46380",
    "sg:province":"Valencia",
    "wof:name":"Generalitat Valenciana",
    "wof:placetype":"venue"
},
  "geometry": {"coordinates":[-0.6855490208,39.4977149963],"type":"Point"}
}