{
  "type": "Feature",
  "properties": {
    "addr:full":"Ntra Sra De La Asuncion, 8 Jumilla Murcia 30520",
    "addr:housenumber":"8",
    "addr:postcode":"30520",
    "addr:street":"Ntra Sra De La Asuncion",
    "iso:country":"ES",
    "sg:address":"Ntra Sra De La Asuncion, 8",
    "sg:city":"Jumilla",
    "sg:orig_category":"Ense\u00d1anza: Comercio, Gesti\u00d3n, Inform\u00c1tica",
    "sg:phone":"+34 968 75 69 27",
    "sg:postcode":"30520",
    "sg:province":"Murcia",
    "wof:name":"Juminfor S.l.",
    "wof:placetype":"venue"
},
  "geometry": {"coordinates":[-1.3222140074,38.4765434265],"type":"Point"}
}