{
  "type": "Feature",
  "properties": {
    "iso:country":"ES",
    "sg:address":"Rua Curros Enriquez, 64",
    "sg:city":"Celanova",
    "sg:orig_category":"Bebidas",
    "sg:phone":"+34 988 43 16 61",
    "sg:postcode":"32800",
    "sg:province":"Ourense",
    "wof:name":"Montes Perez Nieves",
    "wof:placetype":"venue"
},
  "geometry": {"coordinates":[-7.9598321915,42.1573295593],"type":"Point"}
}