{
  "type": "Feature",
  "properties": {
    "iso:country":"ES",
    "sg:address":"Calle de Bajada A La Playa, 6",
    "sg:city":"Loredo",
    "sg:orig_category":"Mec\u00c1nico Del Autom\u00d3vil",
    "sg:phone":"+34 942 50 41 69",
    "sg:postcode":"39140",
    "sg:province":"Cantabria",
    "wof:name":"Melero San Miguel Jose Francisco",
    "wof:placetype":"venue"
},
  "geometry": {"coordinates":[-3.7227594852,43.4630661011],"type":"Point"}
}