{
  "type": "Feature",
  "properties": {
    "addr:full":"Calle de San Pedro, 6 Almeria Almer\u00eda 04001",
    "addr:housenumber":"6",
    "addr:postcode":"04001",
    "addr:street":"Calle De San Pedro",
    "iso:country":"ES",
    "sg:address":"Calle de San Pedro, 6",
    "sg:city":"Almeria",
    "sg:orig_category":"Bares, Piano",
    "sg:phone":"+34 950 25 10 47",
    "sg:postcode":"04001",
    "sg:province":"Almer\u00eda",
    "wof:name":"Diversion Y Fantasia Almeria S.l.",
    "wof:placetype":"venue"
},
  "geometry": {"coordinates":[-2.4648149014,36.8386611938],"type":"Point"}
}