{
  "type": "Feature",
  "properties": {
    "addr:full":"Via Europa, 125 Mataro Barcelona 08303",
    "addr:housenumber":"125",
    "addr:postcode":"08303",
    "addr:street":"Via Europa",
    "iso:country":"ES",
    "sg:address":"Via Europa, 125",
    "sg:city":"Mataro",
    "sg:orig_category":"Fabricaci\u00d3n, Importaci\u00d3n De L\u00c1mparas Y Bombillas",
    "sg:phone":"+34 937 57 18 63",
    "sg:postcode":"08303",
    "sg:province":"Barcelona",
    "wof:name":"Asensio Fernandez Jose",
    "wof:placetype":"venue"
},
  "geometry": {"coordinates":[2.4318048954,41.5459518433],"type":"Point"}
}