{
  "type": "Feature",
  "properties": {
    "addr:full":"Calle de Luis Doreste Silva, 19 Palmas De Gran Canaria Las Palmas 35004",
    "addr:housenumber":"19",
    "addr:postcode":"35004",
    "addr:street":"Calle De Luis Doreste Silva",
    "iso:country":"ES",
    "sg:address":"Calle de Luis Doreste Silva, 19",
    "sg:city":"Palmas De Gran Canaria",
    "sg:orig_category":"Arquitectos",
    "sg:phone":"+34 928 29 07 16",
    "sg:postcode":"35004",
    "sg:province":"Las Palmas",
    "wof:name":"Navarro Betancor Georgina Yaiza",
    "wof:placetype":"venue"
},
  "geometry": {"coordinates":[-15.421330452,28.1160125732],"type":"Point"}
}