{
  "type": "Feature",
  "properties": {
    "addr:full":"Rua Zeus, 9 Pazo Do Rio La Coru\u00f1a 15172",
    "addr:housenumber":"9",
    "addr:postcode":"15172",
    "addr:street":"Rua Zeus;Corun\u0303A",
    "iso:country":"ES",
    "sg:address":"Rua Zeus, 9",
    "sg:city":"Pazo Do Rio",
    "sg:orig_category":"Imprenta",
    "sg:phone":"+34 981 63 83 99",
    "sg:postcode":"15172",
    "sg:province":"La Coru\u00f1a",
    "wof:name":"Imprenta Argrove,s.l.",
    "wof:placetype":"venue"
},
  "geometry": {"coordinates":[-8.3740053177,43.3324584961],"type":"Point"}
}