{
  "type": "Feature",
  "properties": {
    "iso:country":"ES",
    "sg:address":"As Gandaras, S/n",
    "sg:city":"Porri\u00f1o",
    "sg:orig_category":"M\u00c1rmoles, Granitos Y Piedras Naturales",
    "sg:phone":"+34 986 34 60 08",
    "sg:postcode":"36475",
    "sg:province":"Pontevedra",
    "sg:website":"www.recsa.com",
    "wof:name":"Rocas Europeas De Construccion S.a.",
    "wof:placetype":"venue"
},
  "geometry": {"coordinates":[-8.606926918,42.1053466797],"type":"Point"}
}