{
  "type": "Feature",
  "properties": {
    "iso:country":"ES",
    "sg:address":"Calle de Mallorca, S/n",
    "sg:city":"Fuengirola",
    "sg:orig_category":"Servicios De Higiene Y Peluquer\u00cda Para Perros Y Gatos",
    "sg:phone":"+34 952 66 42 48",
    "sg:postcode":"29640",
    "sg:province":"M\u00e1laga",
    "wof:name":"Perez Mu\u00f1oz Alberto",
    "wof:placetype":"venue"
},
  "geometry": {"coordinates":[-4.6293392181,36.54529953],"type":"Point"}
}