{
  "type": "Feature",
  "properties": {
    "iso:country":"ES",
    "sg:address":"Carrer de Sant Marti, 32",
    "sg:city":"S. Cugat Valles",
    "sg:orig_category":"Laboratorios Y Cl\u00cdnicas Veterinarias",
    "sg:phone":"+34 936 75 37 54",
    "sg:postcode":"08172",
    "sg:province":"Barcelona",
    "wof:name":"Vendrell Campmany Ana",
    "wof:placetype":"venue"
},
  "geometry": {"coordinates":[2.0803439617,41.4750442505],"type":"Point"}
}