{
  "type": "Feature",
  "properties": {
    "iso:country":"ES",
    "sg:address":"Calle de Ermita Vieja, 20",
    "sg:city":"Jodar",
    "sg:orig_category":"Supermercados Y Hipermercados",
    "sg:phone":"+34 953 78 77 97",
    "sg:postcode":"23500",
    "sg:province":"Ja\u00e9n",
    "wof:name":"Hijos De Alejandro S.l.l.",
    "wof:placetype":"venue"
},
  "geometry": {"coordinates":[-3.3550684452,37.8346710205],"type":"Point"}
}