{
  "type": "Feature",
  "properties": {
    "addr:full":"Fonciello, S/n Lugo Asturias 33690",
    "addr:housenumber":"/ n",
    "addr:postcode":"33690",
    "addr:street":"Fonciello S",
    "iso:country":"ES",
    "sg:address":"Fonciello, S/n",
    "sg:city":"Lugo",
    "sg:orig_category":"Empresas De Desmonte",
    "sg:phone":"+34 985 26 25 74",
    "sg:postcode":"33690",
    "sg:province":"Asturias",
    "wof:name":"Tato Tato Manuel",
    "wof:placetype":"venue"
},
  "geometry": {"coordinates":[-5.810836792,43.4387741089],"type":"Point"}
}