{
  "type": "Feature",
  "properties": {
    "iso:country":"ES",
    "sg:address":"Pl Vila (de La), 1",
    "sg:city":"Montbrio Del Camp",
    "sg:orig_category":"Ense\u00d1anza, Formaci\u00d3n Profesional: Aprendizaje",
    "sg:phone":"+34 977 82 60 10",
    "sg:postcode":"43340",
    "sg:province":"Tarragona",
    "wof:name":"Ajuntament De Montbrio Del Camp",
    "wof:placetype":"venue"
},
  "geometry": {"coordinates":[1.0036611557,41.1207351685],"type":"Point"}
}