{
  "type": "Feature",
  "properties": {
    "addr:full":"Pase Aragon, 96 Alboraya Valencia 46120",
    "addr:housenumber":"96",
    "addr:postcode":"46120",
    "addr:street":"Aragon",
    "iso:country":"ES",
    "sg:address":"Pase Aragon, 96",
    "sg:city":"Alboraya",
    "sg:orig_category":"Edici\u00d3n De Diarios, Revistas, Boletines",
    "sg:phone":"+34 963 61 53 71",
    "sg:postcode":"46120",
    "sg:province":"Valencia",
    "wof:name":"Grupo 85 Ediciones S.l.",
    "wof:placetype":"venue"
},
  "geometry": {"coordinates":[-0.3405140042,39.4990692139],"type":"Point"}
}