{
  "type": "Feature",
  "properties": {
    "addr:full":"Rbla Salvador Sama, 25 Vilanova I La Geltru Barcelona 08800",
    "addr:housenumber":"25",
    "addr:postcode":"08800",
    "addr:street":"Rbla Salvador Sama",
    "iso:country":"ES",
    "sg:address":"Rbla Salvador Sama, 25",
    "sg:city":"Vilanova I La Geltru",
    "sg:orig_category":"Material Y Suministros Para Peluquer\u00cda",
    "sg:phone":"+34 938 93 40 18",
    "sg:postcode":"08800",
    "sg:province":"Barcelona",
    "wof:name":"Colucci Hair Products S.c.p.",
    "wof:placetype":"venue"
},
  "geometry": {"coordinates":[1.7227510214,41.2231559753],"type":"Point"}
}