{
  "type": "Feature",
  "properties": {
    "addr:full":"Avda Concepcion Arenal, 4 Praia Pontevedra 36950",
    "addr:housenumber":"4",
    "addr:postcode":"36950",
    "addr:street":"Avda Concepcion Arenal",
    "iso:country":"ES",
    "sg:address":"Avda Concepcion Arenal, 4",
    "sg:city":"Praia",
    "sg:orig_category":"Caf\u00c9s, Bares, Cervecer\u00cdas",
    "sg:phone":"+34 986 31 23 01",
    "sg:postcode":"36950",
    "sg:province":"Pontevedra",
    "wof:name":"Galtelcom",
    "wof:placetype":"venue"
},
  "geometry": {"coordinates":[-8.738442421,42.2772254944],"type":"Point"}
}