{
  "type": "Feature",
  "properties": {
    "addr:full":"Mandabidea, 1 Zarautz Guip\u00f9zcoa 20800",
    "addr:housenumber":"1",
    "addr:postcode":"20800",
    "addr:street":"Mandabidea;Guipu\u0300Zcoa",
    "iso:country":"ES",
    "sg:address":"Mandabidea, 1",
    "sg:city":"Zarautz",
    "sg:orig_category":"Agencias Y Agentes Comerciales, Representantes",
    "sg:phone":"+34 943 83 10 45",
    "sg:postcode":"20800",
    "sg:province":"Guip\u00f9zcoa",
    "wof:name":"Pe\u00f1a Unanue Juan",
    "wof:placetype":"venue"
},
  "geometry": {"coordinates":[-2.1670610905,43.2862052917],"type":"Point"}
}