{
  "type": "Feature",
  "properties": {
    "iso:country":"ES",
    "sg:address":"Calle de Mancha La, 29",
    "sg:city":"Gijon",
    "sg:orig_category":"Farmacias",
    "sg:phone":"+34 985 38 91 49",
    "sg:postcode":"33210",
    "sg:province":"Asturias",
    "wof:name":"Vi\u00f1uela Collado Jose Antonio",
    "wof:placetype":"venue"
},
  "geometry": {"coordinates":[-5.67197752,43.5241928101],"type":"Point"}
}