{
  "type": "Feature",
  "properties": {
    "addr:full":"Calle de Agustina De Aragon, 1 Ceuta Ceuta 51001",
    "addr:housenumber":"1",
    "addr:postcode":"51001",
    "addr:street":"Calle De Agustina De Aragon",
    "iso:country":"ES",
    "sg:address":"Calle de Agustina De Aragon, 1",
    "sg:city":"Ceuta",
    "sg:orig_category":"Librer\u00cdas",
    "sg:phone":"+34 956 51 45 38",
    "sg:postcode":"51001",
    "sg:province":"Ceuta",
    "wof:name":"Bentolila Hachuel Jose",
    "wof:placetype":"venue"
},
  "geometry": {"coordinates":[-5.3063883781,35.8879394531],"type":"Point"}
}