{
  "type": "Feature",
  "properties": {
    "iso:country":"ES",
    "sg:address":"Calle de Luciano, 18",
    "sg:city":"Cenes Vega",
    "sg:orig_category":"Filatelia",
    "sg:phone":"+34 958 48 67 04",
    "sg:postcode":"18190",
    "sg:province":"Granada",
    "wof:name":"Cortes Martin Jose Miguel",
    "wof:placetype":"venue"
},
  "geometry": {"coordinates":[-3.5437850952,37.1631126404],"type":"Point"}
}