{
  "type": "Feature",
  "properties": {
    "addr:full":"Plaz Salesas, 11 Madrid Madrid 28004",
    "addr:housenumber":"11",
    "addr:postcode":"madrid;28004",
    "addr:street":"Plaz Salesas",
    "iso:country":"ES",
    "sg:address":"Plaz Salesas, 11",
    "sg:city":"Madrid",
    "sg:orig_category":"Alimentaci\u00d3n General (al Por Menor)",
    "sg:phone":"+34 913 19 54 60",
    "sg:postcode":"28004",
    "sg:province":"Madrid",
    "wof:name":"Hernando Paul Evelio",
    "wof:placetype":"venue"
},
  "geometry": {"coordinates":[-3.6950929165,40.4240684509],"type":"Point"}
}