{
  "type": "Feature",
  "properties": {
    "iso:country":"ES",
    "sg:address":"San Marcos, 41",
    "sg:city":"San Marcos",
    "sg:orig_category":"Alimentaci\u00d3n General (al Por Menor)",
    "sg:phone":"+34 981 56 43 61",
    "sg:postcode":"15820",
    "sg:province":"La Coru\u00f1a",
    "wof:name":"Otero Barral Francisca",
    "wof:placetype":"venue"
},
  "geometry": {"coordinates":[-8.4883518219,42.892490387],"type":"Point"}
}