{
  "type": "Feature",
  "properties": {
    "iso:country":"ES",
    "sg:address":"Calle de Marroquina, 26",
    "sg:city":"Madrid",
    "sg:orig_category":"Laboratorios Y Cl\u00cdnicas Veterinarias",
    "sg:phone":"+34 914 39 86 30",
    "sg:postcode":"28030",
    "sg:province":"Madrid",
    "wof:name":"Clinica Veterinaria Madrid S.l.",
    "wof:placetype":"venue"
},
  "geometry": {"coordinates":[-3.6490058899,40.4074363708],"type":"Point"}
}