{
  "type": "Feature",
  "properties": {
    "iso:country":"ES",
    "sg:address":"Trva Villaescusa, 2",
    "sg:city":"Madrid",
    "sg:orig_category":"Centros Empresariales",
    "sg:phone":"+34 913 04 20 13",
    "sg:postcode":"28017",
    "sg:province":"Madrid",
    "wof:name":"Kishar Code Sl",
    "wof:placetype":"venue"
},
  "geometry": {"coordinates":[-3.631016016,40.4202461243],"type":"Point"}
}