{
  "type": "Feature",
  "properties": {
    "iso:country":"ES",
    "sg:address":"Outeiro Xavi\u00f1a, S/n",
    "sg:city":"Outeiro Xavi\u00e7a",
    "sg:orig_category":"Guarder\u00cdas",
    "sg:phone":"+34 981 73 42 23",
    "sg:postcode":"15147",
    "sg:province":"La Coru\u00f1a",
    "wof:name":"Sanchez Seoane Aurelio",
    "wof:placetype":"venue"
},
  "geometry": {"coordinates":[-8.7346086502,43.1884384155],"type":"Point"}
}