{
  "type": "Feature",
  "properties": {
    "iso:country":"ES",
    "sg:address":"Av Furs (dels), S/n",
    "sg:city":"Lliria",
    "sg:orig_category":"Iglesia Cat\u00d3lica",
    "sg:phone":"+34 962 78 06 94",
    "sg:postcode":"46160",
    "sg:province":"Valencia",
    "wof:name":"Parroquia Maria Madre De La Iglesia",
    "wof:placetype":"venue"
},
  "geometry": {"coordinates":[-0.5956739783,39.6306915283],"type":"Point"}
}