{
  "type": "Feature",
  "properties": {
    "iso:country":"ES",
    "sg:address":"Plaz Aragon, 7",
    "sg:city":"Burgos",
    "sg:orig_category":"Transportes Por V\u00cdas Navegables",
    "sg:phone":"+34 947 20 48 37",
    "sg:postcode":"09001",
    "sg:province":"Burgos",
    "wof:name":"Rubio Puente Segundo",
    "wof:placetype":"venue"
},
  "geometry": {"coordinates":[-3.7074921131,42.3295326233],"type":"Point"}
}