{
  "type": "Feature",
  "properties": {
    "iso:country":"ES",
    "sg:address":"Maquina, 36",
    "sg:city":"Gava",
    "sg:orig_category":"Chapister\u00cda",
    "sg:phone":"+34 936 62 92 66",
    "sg:postcode":"08850",
    "sg:province":"Barcelona",
    "wof:name":"Autocreacion Gava S.l.",
    "wof:placetype":"venue"
},
  "geometry": {"coordinates":[2.0098409653,41.2956161499],"type":"Point"}
}