{
  "type": "Feature",
  "properties": {
    "iso:country":"ES",
    "sg:address":"Plaz Pintor Velazquez, 1",
    "sg:city":"Santa Fe",
    "sg:orig_category":"Peluquer\u00cdas, Peluquer\u00cda Mixta",
    "sg:phone":"+34 958 44 12 44",
    "sg:postcode":"18320",
    "sg:province":"Granada",
    "wof:name":"Agenjo Rueda Jose Antonio",
    "wof:placetype":"venue"
},
  "geometry": {"coordinates":[-3.7179663181,37.1874656677],"type":"Point"}
}