{
  "type": "Feature",
  "properties": {
    "addr:full":"Covadonga, 8 Infiesto Asturias 33530",
    "addr:housenumber":"8",
    "addr:postcode":"33530",
    "addr:street":"Covadonga",
    "iso:country":"ES",
    "sg:address":"Covadonga, 8",
    "sg:city":"Infiesto",
    "sg:orig_category":"Sociedades, Compa\u00d1\u00cdas Aseguradoras",
    "sg:phone":"+34 985 71 00 30",
    "sg:postcode":"33530",
    "sg:province":"Asturias",
    "wof:name":"Mapfre Servicios De Informatica",
    "wof:placetype":"venue"
},
  "geometry": {"coordinates":[-5.3612360954,43.3455467224],"type":"Point"}
}