{
  "type": "Feature",
  "properties": {
    "iso:country":"ES",
    "sg:address":"Poligon Baix Ebre, S/n",
    "sg:city":"Camp-redo",
    "sg:orig_category":"Barnizadores",
    "sg:phone":"+34 977 59 76 36",
    "sg:postcode":"43897",
    "sg:province":"Tarragona",
    "wof:name":"Lacats I Envernissats Aguilera C.b.",
    "wof:placetype":"venue"
},
  "geometry": {"coordinates":[0.5545499921,40.7676849365],"type":"Point"}
}