{
  "type": "Feature",
  "properties": {
    "addr:full":"Ctra Port, Del, 13 Porto Cristo Islas Baleares 07680",
    "addr:housenumber":"13",
    "addr:postcode":"07680",
    "addr:street":"Ctra Port Del;Islas Baleares",
    "iso:country":"ES",
    "sg:address":"Ctra Port, Del, 13",
    "sg:city":"Porto Cristo",
    "sg:classifiers":[
        {
            "category":"Autos & Motor Vehicles",
            "subcategory":"Automobile Sales",
            "type":"Retail Goods"
        }
    ],
    "sg:phone":"+34 971 82 20 86",
    "sg:postcode":"07680",
    "sg:province":"Islas Baleares",
    "wof:name":"Riera Bauza Andres",
    "wof:placetype":"venue"
},
  "geometry": {"coordinates":[3.3337659836,39.5413703918],"type":"Point"}
}