{
  "type": "Feature",
  "properties": {
    "iso:country":"ES",
    "sg:address":"Avgd Joan Xxiii, De, 7",
    "sg:city":"Carcaixent",
    "sg:orig_category":"Caf\u00c9s, Bares, Cervecer\u00cdas",
    "sg:phone":"+34 962 46 05 55",
    "sg:postcode":"46740",
    "sg:province":"Valencia",
    "wof:name":"Alcina Caudet Manuel",
    "wof:placetype":"venue"
},
  "geometry": {"coordinates":[-0.4484950006,39.1259880066],"type":"Point"}
}