{
  "type": "Feature",
  "properties": {
    "addr:full":"C/ Pio Baroja, 11 Cerdanyola Valles Barcelona 08290",
    "addr:housenumber":"11",
    "addr:postcode":"08290",
    "addr:street":"C / Pio Baroja;Valles Barcelona",
    "iso:country":"ES",
    "sg:address":"C/ Pio Baroja, 11",
    "sg:city":"Cerdanyola Valles",
    "sg:orig_category":"M\u00c9dicos: Naturistas",
    "sg:phone":"+34 936 92 72 53",
    "sg:postcode":"08290",
    "sg:province":"Barcelona",
    "wof:name":"Garcia Pescador Felix",
    "wof:placetype":"venue"
},
  "geometry": {"coordinates":[2.1470150948,41.4924812317],"type":"Point"}
}