{
  "type": "Feature",
  "properties": {
    "iso:country":"ES",
    "sg:address":"Avda Castellon, 54",
    "sg:city":"Almazora",
    "sg:orig_category":"Suministros Para Hoteles",
    "sg:phone":"+34 964 56 41 39",
    "sg:postcode":"12550",
    "sg:province":"Castell\u00f3n",
    "wof:name":"Fogues Traver Antonio",
    "wof:placetype":"venue"
},
  "geometry": {"coordinates":[-0.0604390018,39.9470405579],"type":"Point"}
}