{
  "type": "Feature",
  "properties": {
    "iso:country":"ES",
    "sg:address":"Cmno Cementerio Vello, S/n",
    "sg:city":"Carballo",
    "sg:orig_category":"Plomeros",
    "sg:phone":"+34 981 75 59 62",
    "sg:postcode":"15100",
    "sg:province":"La Coru\u00f1a",
    "wof:name":"J.vazquez J.eiris S.c.",
    "wof:placetype":"venue"
},
  "geometry": {"coordinates":[-8.6875286102,43.2075386047],"type":"Point"}
}