{
  "type": "Feature",
  "properties": {
    "iso:country":"ES",
    "sg:address":"Carr Nord, 6",
    "sg:city":"Girona",
    "sg:orig_category":"Peluquer\u00cdas, Peluquer\u00cda Mixta",
    "sg:phone":"+34 972 41 10 29",
    "sg:postcode":"17001",
    "sg:province":"Girona",
    "wof:name":"Lopez Campa\u00f1a Eva",
    "wof:placetype":"venue"
},
  "geometry": {"coordinates":[2.8187448978,41.9808616638],"type":"Point"}
}