{
  "type": "Feature",
  "properties": {
    "addr:full":"Calle de E, S/n Pol. Malpica Zaragoza 50057",
    "addr:housenumber":"s / n",
    "addr:postcode":"50057",
    "addr:street":"Calle De E;Pol. Malpica",
    "iso:country":"ES",
    "sg:address":"Calle de E, S/n",
    "sg:city":"Pol. Malpica",
    "sg:orig_category":"Tapicer\u00cdas",
    "sg:phone":"+34 976 57 27 31",
    "sg:postcode":"50057",
    "sg:province":"Zaragoza",
    "wof:name":"Manuel Larraga S.l.",
    "wof:placetype":"venue"
},
  "geometry": {"coordinates":[-0.8765661716,41.6563491821],"type":"Point"}
}