{
  "type": "Feature",
  "properties": {
    "addr:full":"Carr Garriga, 2 Palafrugell Girona 17200",
    "addr:housenumber":"2",
    "addr:postcode":"17200",
    "addr:street":"Carr Garriga",
    "iso:country":"ES",
    "sg:address":"Carr Garriga, 2",
    "sg:city":"Palafrugell",
    "sg:orig_category":"Instalaci\u00d3n, Reparaci\u00d3n De Calefacci\u00d3n Por Gas",
    "sg:phone":"+34 972 30 02 21",
    "sg:postcode":"17200",
    "sg:province":"Girona",
    "wof:name":"Benet Pibernat S.l.",
    "wof:placetype":"venue"
},
  "geometry": {"coordinates":[3.1664280891,41.9173774719],"type":"Point"}
}