{
  "type": "Feature",
  "properties": {
    "addr:full":"Calle de Hiedra, 14 Villarrobledo Albacete 02600",
    "addr:housenumber":"14",
    "addr:postcode":"02600",
    "addr:street":"Calle De Hiedra",
    "iso:country":"ES",
    "sg:address":"Calle de Hiedra, 14",
    "sg:city":"Villarrobledo",
    "sg:orig_category":"Producci\u00d3n, Venta De Productos De Agricultura Biol\u00d3gica",
    "sg:phone":"+34 967 14 61 36",
    "sg:postcode":"02600",
    "sg:province":"Albacete",
    "wof:name":"Martinez Sanchez Antonio",
    "wof:placetype":"venue"
},
  "geometry": {"coordinates":[-2.6076979637,39.2642097473],"type":"Point"}
}