{
  "type": "Feature",
  "properties": {
    "iso:country":"ES",
    "sg:address":"Calle de Fortuny, 6",
    "sg:city":"Melilla",
    "sg:orig_category":"Alimentaci\u00d3n General (al Por Menor)",
    "sg:phone":"+34 952 67 30 01",
    "sg:postcode":"52004",
    "sg:province":"Melilla",
    "wof:name":"Jimenez Filloy Miguel Fernando",
    "wof:placetype":"venue"
},
  "geometry": {"coordinates":[-2.9424700737,35.2899398804],"type":"Point"}
}