{
  "type": "Feature",
  "properties": {
    "addr:full":"Calle de Rio Tajo, 12 Malpartida Caceres C\u00e1ceres 10910",
    "addr:housenumber":"12",
    "addr:postcode":"10910",
    "addr:street":"Calle De Rio Tajo;Ca\u0301Ceres",
    "iso:country":"ES",
    "sg:address":"Calle de Rio Tajo, 12",
    "sg:city":"Malpartida Caceres",
    "sg:orig_category":"Inform\u00c1tica Equipo Y Programas (al Por Mayor)",
    "sg:phone":"+34 927 27 67 51",
    "sg:postcode":"10910",
    "sg:province":"C\u00e1ceres",
    "wof:name":"De La Osa Barriga Antonio Jesus",
    "wof:placetype":"venue"
},
  "geometry": {"coordinates":[-6.5082287788,39.4438285828],"type":"Point"}
}