{
  "type": "Feature",
  "properties": {
    "addr:full":"Calle de Estrella De Elola, 32 Valdemoro Madrid 28340",
    "addr:housenumber":"32",
    "addr:postcode":"28340",
    "addr:street":"Calle De Estrella De Elola",
    "iso:country":"ES",
    "sg:address":"Calle de Estrella De Elola, 32",
    "sg:city":"Valdemoro",
    "sg:orig_category":"Construcciones Met\u00c1licas",
    "sg:phone":"+34 918 09 52 84",
    "sg:postcode":"28340",
    "sg:province":"Madrid",
    "wof:name":"Calculotecnia S.l.",
    "wof:placetype":"venue"
},
  "geometry": {"coordinates":[-3.6762449741,40.1918411255],"type":"Point"}
}