{
  "type": "Feature",
  "properties": {
    "iso:country":"ES",
    "sg:address":"Barr Estacion, S/n",
    "sg:city":"Estacion",
    "sg:orig_category":"Fabricaci\u00d3n De Moldes Y Modelos",
    "sg:phone":"+34 918 09 82 00",
    "sg:postcode":"45...",
    "sg:province":"Toledo",
    "sg:website":"www.mecaplastiberica.com",
    "wof:name":"Mecaplast Iberica S.a.",
    "wof:placetype":"venue"
},
  "geometry": {"coordinates":[-4.4871239662,39.949054718],"type":"Point"}
}