{
  "type": "Feature",
  "properties": {
    "addr:full":"Calle de Mayor, 1 Siscar Murcia 30149",
    "addr:housenumber":"1",
    "addr:postcode":"30149",
    "addr:street":"Calle De Mayor",
    "iso:country":"ES",
    "sg:address":"Calle de Mayor, 1",
    "sg:city":"Siscar",
    "sg:orig_category":"Asociaciones Ecologistas",
    "sg:phone":"+34 968 86 56 67",
    "sg:postcode":"30149",
    "sg:province":"Murcia",
    "wof:name":"Comunidad De Regantes Los Angeles",
    "wof:placetype":"venue"
},
  "geometry": {"coordinates":[-1.0298500061,38.0684127808],"type":"Point"}
}