{
  "type": "Feature",
  "properties": {
    "iso:country":"ES",
    "sg:address":"Carrer de Eduard Alcoy, 32",
    "sg:city":"Mataro",
    "sg:orig_category":"Fabricaci\u00d3n De Su\u00c9ters Y Chalecos De Punto",
    "sg:phone":"+34 937 96 28 15",
    "sg:postcode":"08304",
    "sg:province":"Barcelona",
    "wof:name":"Marquez Merchan Catalina",
    "wof:placetype":"venue"
},
  "geometry": {"coordinates":[2.4470961094,41.5536956787],"type":"Point"}
}