{
  "type": "Feature",
  "properties": {
    "addr:full":"Carrer de Antonio Machado, 29 Barcelona Barcelona 08042",
    "addr:housenumber":"29",
    "addr:postcode":"08042",
    "addr:street":"Carrer De Antonio Machado",
    "iso:country":"ES",
    "sg:address":"Carrer de Antonio Machado, 29",
    "sg:city":"Barcelona",
    "sg:orig_category":"Electrodom\u00c9sticos (al Por Menor)",
    "sg:phone":"+34 934 27 14 99",
    "sg:postcode":"08042",
    "sg:province":"Barcelona",
    "wof:name":"Martin Tobar Pilar",
    "wof:placetype":"venue"
},
  "geometry": {"coordinates":[2.1689651012,41.4439811707],"type":"Point"}
}