{
  "type": "Feature",
  "properties": {
    "addr:full":"Calle de Hernan Cortes, 49 Santander Cantabria 39003",
    "addr:housenumber":"49",
    "addr:postcode":"39003",
    "addr:street":"Calle De Hernan Cortes",
    "iso:country":"ES",
    "sg:address":"Calle de Hernan Cortes, 49",
    "sg:city":"Santander",
    "sg:orig_category":"Muebles",
    "sg:phone":"+34 942 31 20 13",
    "sg:postcode":"39003",
    "sg:province":"Cantabria",
    "sg:website":"www.artespana-santander.com",
    "wof:name":"Confort Cantabria S. A.",
    "wof:placetype":"venue"
},
  "geometry": {"coordinates":[-3.7986190319,43.4631881714],"type":"Point"}
}