{
  "type": "Feature",
  "properties": {
    "iso:country":"ES",
    "sg:address":"Carrer de Penedes, 67",
    "sg:city":"S. Quirze Valles",
    "sg:orig_category":"Electrolisis, Depurado Del Aluminio Y De Aleaciones",
    "sg:phone":"+34 937 21 40 97",
    "sg:postcode":"08192",
    "sg:province":"Barcelona",
    "wof:name":"Sodeve S.l.",
    "wof:placetype":"venue"
},
  "geometry": {"coordinates":[2.0734500885,41.5405387878],"type":"Point"}
}