{
  "type": "Feature",
  "properties": {
    "iso:country":"ES",
    "sg:address":"Avda Aragon De, 132",
    "sg:city":"Fraga",
    "sg:orig_category":"M\u00c1quinas De Coser Y De Hacer Punto (al Por Mayor)",
    "sg:phone":"+34 974 45 41 72",
    "sg:postcode":"22520",
    "sg:province":"Huesca",
    "wof:name":"Punto 2001 S.l.l.",
    "wof:placetype":"venue"
},
  "geometry": {"coordinates":[0.3337309957,41.5199699402],"type":"Point"}
}