{
  "type": "Feature",
  "properties": {
    "iso:country":"ES",
    "sg:address":"Calle de Porto Cristo, 7",
    "sg:city":"Alcorcon",
    "sg:orig_category":"Empresarios Y Productoras De Espect\u00c1culos",
    "sg:phone":"+34 916 19 50 73",
    "sg:postcode":"28924",
    "sg:province":"Madrid",
    "sg:website":"www.chacena.es",
    "wof:name":"Servicios Produccion Distribucion Y Propuestas Escenicas S.l.",
    "wof:placetype":"venue"
},
  "geometry": {"coordinates":[-3.8181400299,40.3518409729],"type":"Point"}
}