{
  "type": "Feature",
  "properties": {
    "iso:country":"ES",
    "sg:address":"Carrer de Frederic Soler, 96",
    "sg:city":"Cornella Llobregat",
    "sg:orig_category":"Peluqueros: De Se\u00d1oras",
    "sg:phone":"+34 933 76 28 80",
    "sg:postcode":"08940",
    "sg:province":"Barcelona",
    "wof:name":"Martin Sanchez Aurora",
    "wof:placetype":"venue"
},
  "geometry": {"coordinates":[2.0781428814,41.3647422791],"type":"Point"}
}