{
  "type": "Feature",
  "properties": {
    "iso:country":"ES",
    "sg:address":"Calle de Errekatxulo, 4",
    "sg:city":"Donostia-san Sebastian",
    "sg:orig_category":"Mec\u00c1nico Del Autom\u00d3vil",
    "sg:phone":"+34 943 37 68 43",
    "sg:postcode":"20018",
    "sg:province":"Guip\u00f9zcoa",
    "wof:name":"Talleres Urrestarazu S. L.",
    "wof:placetype":"venue"
},
  "geometry": {"coordinates":[-2.0107710361,43.2816848755],"type":"Point"}
}