{
  "type": "Feature",
  "properties": {
    "iso:country":"ES",
    "sg:address":"Avda Elda (de), 6",
    "sg:city":"Petrer",
    "sg:orig_category":"Negocio De Materiales De Construcci\u00d3n",
    "sg:phone":"+34 965 37 06 94",
    "sg:postcode":"03610",
    "sg:province":"Alicante",
    "wof:name":"Construcciones Y Fontaneria Morote S.l.",
    "wof:placetype":"venue"
},
  "geometry": {"coordinates":[-0.7858989835,38.4819984436],"type":"Point"}
}