{
  "type": "Feature",
  "properties": {
    "iso:country":"ES",
    "sg:address":"Avda Laza (de), 4",
    "sg:city":"Verin",
    "sg:orig_category":"Comercio, Reparaci\u00d3n De Bicicletas, De Motocicletas, De Accesorios",
    "sg:phone":"+34 988 41 18 76",
    "sg:postcode":"32600",
    "sg:province":"Ourense",
    "wof:name":"Estevez Ca\u00f1izo Javier",
    "wof:placetype":"venue"
},
  "geometry": {"coordinates":[-7.4333648682,41.9474754333],"type":"Point"}
}