{
  "type": "Feature",
  "properties": {
    "iso:country":"ES",
    "sg:address":"Calle de Profesor Armas Fernandez, S/n",
    "sg:city":"S. Sebastian Gomera",
    "sg:orig_category":"Ingeniero",
    "sg:phone":"+34 922 87 15 56",
    "sg:postcode":"38800",
    "sg:province":"Santa Cruz De Tenerife",
    "wof:name":"Pascual Pujada Jaime",
    "wof:placetype":"venue"
},
  "geometry": {"coordinates":[-17.1136703491,28.0930137634],"type":"Point"}
}