{
  "type": "Feature",
  "properties": {
    "iso:country":"ES",
    "sg:address":"Plaz Santisima Trinidad, 14",
    "sg:city":"Trujillanos",
    "sg:orig_category":"Estancos",
    "sg:phone":"+34 924 32 71 90",
    "sg:postcode":"06892",
    "sg:province":"Badajoz",
    "wof:name":"Gomez Chamizo Maria Jose",
    "wof:placetype":"venue"
},
  "geometry": {"coordinates":[-6.2628531456,38.9497528076],"type":"Point"}
}