{
  "type": "Feature",
  "properties": {
    "iso:country":"ES",
    "sg:address":"Calle de Pablo Espinel, 18",
    "sg:city":"Pto. Rosario",
    "sg:orig_category":"Escayola Y Productos De Escayola (fabricaci\u00d3n, Al Por Mayor)",
    "sg:phone":"+34 928 85 17 01",
    "sg:postcode":"35600",
    "sg:province":"Las Palmas",
    "wof:name":"Escayolas Y Decoraciones Lanzarote S.l.",
    "wof:placetype":"venue"
},
  "geometry": {"coordinates":[-13.8524141312,28.5063686371],"type":"Point"}
}