{
  "type": "Feature",
  "properties": {
    "addr:full":"Barr Anto\u00d1an, 89 Cobreces Cantabria 39320",
    "addr:housenumber":"89",
    "addr:postcode":"39320",
    "addr:street":"Anton\u0303An",
    "iso:country":"ES",
    "sg:address":"Barr Anto\u00d1an, 89",
    "sg:city":"Cobreces",
    "sg:orig_category":"Iglesia Cat\u00d3lica",
    "sg:phone":"+34 942 72 50 16",
    "sg:postcode":"39320",
    "sg:province":"Cantabria",
    "wof:name":"Casa Parroquial",
    "wof:placetype":"venue"
},
  "geometry": {"coordinates":[-4.2107009888,43.3850250244],"type":"Point"}
}