{
  "type": "Feature",
  "properties": {
    "addr:full":"Avda. Barcelona, S/n Oropesa Mar Castell\u00f3n 12594",
    "addr:housenumber":"/ n",
    "addr:postcode":"12594",
    "addr:street":"Avda. Barcelona S",
    "iso:country":"ES",
    "sg:address":"Avda. Barcelona, S/n",
    "sg:city":"Oropesa Mar",
    "sg:orig_category":"Equitaci\u00d3n Y Centros De H\u00cdpica",
    "sg:phone":"+34 964 31 00 65",
    "sg:postcode":"12594",
    "sg:province":"Castell\u00f3n",
    "wof:name":"Club Hipico Oropesa",
    "wof:placetype":"venue"
},
  "geometry": {"coordinates":[0.145754993,40.0984306335],"type":"Point"}
}