{
  "type": "Feature",
  "properties": {
    "addr:full":"Plaz Posadas (las), 3 Jadraque Guadalajara 19240",
    "addr:housenumber":"3",
    "addr:postcode":"19240",
    "addr:street":"Las",
    "iso:country":"ES",
    "sg:address":"Plaz Posadas (las), 3",
    "sg:city":"Jadraque",
    "sg:orig_category":"Cajas De Ahorro",
    "sg:phone":"+34 949 89 01 32",
    "sg:postcode":"19240",
    "sg:province":"Guadalajara",
    "wof:name":"Caja De Ahorros Y Monte De Piedad De Zaragoza Aragon Y Rioja",
    "wof:placetype":"venue"
},
  "geometry": {"coordinates":[-2.9276280403,40.9257965088],"type":"Point"}
}