{
  "type": "Feature",
  "properties": {
    "addr:full":"Calle de Andres Cortina, 2 Algorta Vizcaya 48993",
    "addr:housenumber":"2",
    "addr:postcode":"48993",
    "addr:street":"Calle De Andres Cortina",
    "iso:country":"ES",
    "sg:address":"Calle de Andres Cortina, 2",
    "sg:city":"Algorta",
    "sg:orig_category":"Molduras, Junquillos, Listones Y Molduras Perforadas",
    "sg:phone":"+34 944 91 14 47",
    "sg:postcode":"48993",
    "sg:province":"Vizcaya",
    "wof:name":"Sociedad Regional De Informatica S.a.",
    "wof:placetype":"venue"
},
  "geometry": {"coordinates":[-3.0135684013,43.3525047302],"type":"Point"}
}