{
  "type": "Feature",
  "properties": {
    "addr:full":"Avda Manuel Salmeron, 13 Berja Almer\u00eda 04760",
    "addr:housenumber":"13",
    "addr:postcode":"04760",
    "addr:street":"Avda Manuel Salmeron",
    "iso:country":"ES",
    "sg:address":"Avda Manuel Salmeron, 13",
    "sg:city":"Berja",
    "sg:orig_category":"Abogados",
    "sg:phone":"+34 950 49 27 44",
    "sg:postcode":"04760",
    "sg:province":"Almer\u00eda",
    "wof:name":"Miguel Ortiz Jose Javier",
    "wof:placetype":"venue"
},
  "geometry": {"coordinates":[-2.9484550953,36.8461227417],"type":"Point"}
}