{
  "type": "Feature",
  "properties": {
    "addr:full":"Vereda Real, Km. 0000,5 Argamasilla Alba Ciudad Real 13710",
    "addr:postcode":"13710",
    "addr:street":"Vereda Real Km. 0000,5 Argamasilla Alba",
    "iso:country":"ES",
    "sg:address":"Vereda Real, Km. 0000,5",
    "sg:city":"Argamasilla Alba",
    "sg:orig_category":"Transportes Internacionales",
    "sg:phone":"+34 926 52 18 64",
    "sg:postcode":"13710",
    "sg:province":"Ciudad Real",
    "wof:name":"Traco-arga Sociedad Cooperativa Limitada",
    "wof:placetype":"venue"
},
  "geometry": {"coordinates":[-3.0829439163,39.1299705505],"type":"Point"}
}