{
  "type": "Feature",
  "properties": {
    "addr:full":"Avda Santiago Melo Pison, 8 Barco Ourense 32300",
    "addr:housenumber":"8",
    "addr:postcode":"32300",
    "addr:street":"Avda Santiago Melo Pison",
    "iso:country":"ES",
    "sg:address":"Avda Santiago Melo Pison, 8",
    "sg:city":"Barco",
    "sg:orig_category":"Centros M\u00c9dicos Y Sociales, Dispensarios",
    "sg:phone":"+34 988 32 24 14",
    "sg:postcode":"32300",
    "sg:province":"Ourense",
    "wof:name":"Centro Medico As Regas S.l.",
    "wof:placetype":"venue"
},
  "geometry": {"coordinates":[-6.9819378853,42.4178237915],"type":"Point"}
}