{
  "type": "Feature",
  "properties": {
    "iso:country":"ES",
    "sg:address":"Pase Echegaray Y Caballero, 152",
    "sg:city":"Zaragoza",
    "sg:orig_category":"Montaje (empresas De)",
    "sg:phone":"+34 976 39 13 37",
    "sg:postcode":"50001",
    "sg:province":"Zaragoza",
    "wof:name":"Montajes Marin Zaragoza S.l.",
    "wof:placetype":"venue"
},
  "geometry": {"coordinates":[-0.8722590208,41.654750824],"type":"Point"}
}