{
  "type": "Feature",
  "properties": {
    "addr:full":"Plaz Europa (de), 18 Ecija Sevilla 41400",
    "addr:postcode":"41400",
    "iso:country":"ES",
    "sg:address":"Plaz Europa (de), 18",
    "sg:city":"Ecija",
    "sg:orig_category":"Artes Gr\u00c1ficas, Artes Pl\u00c1sticas: Material Y Suministros (al Por Menor)",
    "sg:phone":"+34 955 90 51 77",
    "sg:postcode":"41400",
    "sg:province":"Sevilla",
    "wof:name":"Agua Campi\u00d1a S.a",
    "wof:placetype":"venue"
},
  "geometry": {"coordinates":[-5.0753765106,37.5370826721],"type":"Point"}
}