{
  "type": "Feature",
  "properties": {
    "iso:country":"ES",
    "sg:address":"Carrer de Camelies, 15",
    "sg:city":"Barcelona",
    "sg:orig_category":"Hospitales",
    "sg:phone":"+34 932 85 99 55",
    "sg:postcode":"08024",
    "sg:province":"Barcelona",
    "wof:name":"Enfermeria Evangelica Fundacion Privada",
    "wof:placetype":"venue"
},
  "geometry": {"coordinates":[2.1589009762,41.411151886],"type":"Point"}
}