{
  "type": "Feature",
  "properties": {
    "iso:country":"ES",
    "sg:address":"Calle de General Franco, 34",
    "sg:city":"Cristianos",
    "sg:orig_category":"Telefon\u00cda M\u00d3vil, Radiomensajer\u00cda, Radiocomunicaciones (servicios, Comercializaci\u00d3n)",
    "sg:phone":"+34 922 79 05 47",
    "sg:postcode":"38650",
    "sg:province":"Santa Cruz De Tenerife",
    "wof:name":"Rodriguez Leon Manuel",
    "wof:placetype":"venue"
},
  "geometry": {"coordinates":[-16.7176189423,28.0517501831],"type":"Point"}
}