{
  "type": "Feature",
  "properties": {
    "iso:country":"ES",
    "sg:address":"Calle de Jovellanos, 1",
    "sg:city":"Ibi",
    "sg:orig_category":"Mec\u00c1nico Del Autom\u00d3vil",
    "sg:phone":"+34 965 55 18 31",
    "sg:postcode":"03440",
    "sg:province":"Alicante",
    "wof:name":"Automocion 2000 C.b.",
    "wof:placetype":"venue"
},
  "geometry": {"coordinates":[-0.5773360133,38.6195487976],"type":"Point"}
}