{
  "type": "Feature",
  "properties": {
    "iso:country":"ES",
    "sg:address":"Calle de Ramon Y Cajal, 3",
    "sg:city":"Coru\u00d1a",
    "sg:orig_category":"Agencias Y Agentes Comerciales, Representantes",
    "sg:phone":"+34 981 13 17 31",
    "sg:postcode":"15006",
    "sg:province":"La Coru\u00f1a",
    "wof:name":"Cusi Martinez Manuel",
    "wof:placetype":"venue"
},
  "geometry": {"coordinates":[-8.4000930786,43.3572731018],"type":"Point"}
}