{
  "type": "Feature",
  "properties": {
    "addr:full":"Calle de Francisco De Medina Y Mendoza, S/n Cabanillas Campo Guadalajara 19171",
    "addr:housenumber":"s",
    "addr:postcode":"19171",
    "addr:street":"Calle De Francisco De Medina Y Mendoza;/ N",
    "iso:country":"ES",
    "sg:address":"Calle de Francisco De Medina Y Mendoza, S/n",
    "sg:city":"Cabanillas Campo",
    "sg:orig_category":"Panader\u00cdas, Pasteler\u00cdas, Boller\u00cda Industriale (fabricaci\u00d3n, Al Por Mayor)",
    "sg:phone":"+34 949 20 02 66",
    "sg:postcode":"19171",
    "sg:province":"Guadalajara",
    "wof:name":"Rosa Xamirada S.l.",
    "wof:placetype":"venue"
},
  "geometry": {"coordinates":[-3.2051389217,40.6177062988],"type":"Point"}
}