{
  "type": "Feature",
  "properties": {
    "iso:country":"ES",
    "sg:address":"Calle de Cristobal Bordiu, 57",
    "sg:city":"Madrid",
    "sg:orig_category":"Peluqueros: De Se\u00d1oras",
    "sg:phone":"+34 915 53 05 98",
    "sg:postcode":"28003",
    "sg:province":"Madrid",
    "wof:name":"Gil Cubillo Maria De Los Angeles",
    "wof:placetype":"venue"
},
  "geometry": {"coordinates":[-3.6961429119,40.4430236816],"type":"Point"}
}