{
  "type": "Feature",
  "properties": {
    "addr:full":"Avda Alcalde Miguel Casta\u00d1o, 91 Le\u00f3n Le\u00f3n 24005",
    "addr:housenumber":"91",
    "addr:postcode":"24005",
    "addr:street":"Avda Alcalde Miguel Castan\u0303O;Leo\u0301N",
    "iso:country":"ES",
    "sg:address":"Avda Alcalde Miguel Casta\u00d1o, 91",
    "sg:city":"Le\u00f3n",
    "sg:orig_category":"Fabricaci\u00d3n De Juguetes Autom\u00c1ticos",
    "sg:phone":"+34 987 25 51 48",
    "sg:postcode":"24005",
    "sg:province":"Le\u00f3n",
    "wof:name":"Inverexpan",
    "wof:placetype":"venue"
},
  "geometry": {"coordinates":[-5.5598831177,42.5867843628],"type":"Point"}
}