{
  "type": "Feature",
  "properties": {
    "iso:country":"ES",
    "sg:address":"Calle de Almansa, 22",
    "sg:city":"Madrid",
    "sg:orig_category":"Pintores",
    "sg:phone":"+34 915 34 63 22",
    "sg:postcode":"28039",
    "sg:province":"Madrid",
    "wof:name":"Ramirez Rios Antonio",
    "wof:placetype":"venue"
},
  "geometry": {"coordinates":[-3.7051057816,40.4487571716],"type":"Point"}
}