{
  "type": "Feature",
  "properties": {
    "addr:full":"Calle de Arzobispo Domenech, 2 Zaragoza Zaragoza 50006",
    "addr:housenumber":"2",
    "addr:postcode":"50006",
    "addr:street":"Calle De Arzobispo Domenech",
    "iso:country":"ES",
    "sg:address":"Calle de Arzobispo Domenech, 2",
    "sg:city":"Zaragoza",
    "sg:orig_category":"Inform\u00c1tica (estudios, Servicios, Asesor\u00cda, Formaci\u00d3n)",
    "sg:phone":"+34 976 23 69 71",
    "sg:postcode":"50006",
    "sg:province":"Zaragoza",
    "wof:name":"Sermalogic S.l.",
    "wof:placetype":"venue"
},
  "geometry": {"coordinates":[-0.8879460096,41.6458702087],"type":"Point"}
}