{
  "type": "Feature",
  "properties": {
    "addr:full":"Avda Andalucia, S/n Carrion De Los Cespedes Sevilla 41820",
    "addr:postcode":"41820",
    "addr:street":"Avda Andalucia S / N",
    "iso:country":"ES",
    "sg:address":"Avda Andalucia, S/n",
    "sg:city":"Carrion De Los Cespedes",
    "sg:orig_category":"Institutos M\u00c9dicos",
    "sg:phone":"+34 954 75 49 15",
    "sg:postcode":"41820",
    "sg:province":"Sevilla",
    "wof:name":"Servicio Andaluz De Salud",
    "wof:placetype":"venue"
},
  "geometry": {"coordinates":[-6.3282809258,37.3669967651],"type":"Point"}
}