{
  "type": "Feature",
  "properties": {
    "iso:country":"ES",
    "sg:address":"Poli Industrial Espiritu Santo, S/n",
    "sg:city":"Colloto",
    "sg:orig_category":"Comercio De Hierro",
    "sg:phone":"+34 985 79 20 14",
    "sg:postcode":"33010",
    "sg:province":"Asturias",
    "wof:name":"Tubos Y Hierros Industriales S.a.",
    "wof:placetype":"venue"
},
  "geometry": {"coordinates":[-5.8078641891,43.3804016113],"type":"Point"}
}