{
  "type": "Feature",
  "properties": {
    "iso:country":"ES",
    "sg:address":"Calle de Albareda, 64",
    "sg:city":"Palmas De Gran Canaria",
    "sg:orig_category":"Telas Y Sedas (al Por Menor)",
    "sg:phone":"+34 928 26 40 34",
    "sg:postcode":"35008",
    "sg:province":"Las Palmas",
    "wof:name":"Habid Hafez Jorge",
    "wof:placetype":"venue"
},
  "geometry": {"coordinates":[-15.429567337,28.1469802856],"type":"Point"}
}