{
  "type": "Feature",
  "properties": {
    "iso:country":"ES",
    "sg:address":"Cmno San Martin De La Vega, 1",
    "sg:city":"Arganda",
    "sg:orig_category":"Materias Pl\u00c1sticas: Productos De Consumo Masivo (fabricaci\u00d3n, Al Por Mayor)",
    "sg:phone":"+34 918 71 67 65",
    "sg:postcode":"28500",
    "sg:province":"Madrid",
    "wof:name":"Cmv Plasticos S.a.",
    "wof:placetype":"venue"
},
  "geometry": {"coordinates":[-3.4531629086,40.3032836914],"type":"Point"}
}