{
  "type": "Feature",
  "properties": {
    "addr:full":"Pl. C. Sotelo, 6 Salas Asturias 33860",
    "addr:housenumber":"6",
    "addr:postcode":"33860",
    "addr:street":"C. Sotelo",
    "iso:country":"ES",
    "sg:address":"Pl. C. Sotelo, 6",
    "sg:city":"Salas",
    "sg:orig_category":"Mercer\u00cda, Lencer\u00cda (al Por Menor)",
    "sg:phone":"+34 985 83 08 13",
    "sg:postcode":"33860",
    "sg:province":"Asturias",
    "wof:name":"Fernandez Alvarez Maria Paz",
    "wof:placetype":"venue"
},
  "geometry": {"coordinates":[-6.2606191635,43.4088745117],"type":"Point"}
}