{
  "type": "Feature",
  "properties": {
    "iso:country":"ES",
    "sg:address":"Calle de Domingo Beltran De Otazu, 1",
    "sg:city":"Vitoria-gasteiz",
    "sg:orig_category":"Muebles, Minoristas",
    "sg:phone":"+34 945 24 42 45",
    "sg:postcode":"01012",
    "sg:province":"\u00c1lava",
    "wof:name":"Millan Arnadillo Antonio",
    "wof:placetype":"venue"
},
  "geometry": {"coordinates":[-2.6781401634,42.8496742249],"type":"Point"}
}