{
  "type": "Feature",
  "properties": {
    "addr:full":"Pla\u00c7 Orient, 36 Inca Islas Baleares 07300",
    "addr:housenumber":"36",
    "addr:postcode":"07300",
    "iso:country":"ES",
    "sg:address":"Pla\u00c7 Orient, 36",
    "sg:city":"Inca",
    "sg:orig_category":"Iglesia Cat\u00d3lica",
    "sg:phone":"+34 971 50 01 47",
    "sg:postcode":"07300",
    "sg:province":"Islas Baleares",
    "wof:name":"Obispado De Mallorca",
    "wof:placetype":"venue"
},
  "geometry": {"coordinates":[2.9091899395,39.7197418213],"type":"Point"}
}