{
  "type": "Feature",
  "properties": {
    "iso:country":"ES",
    "sg:address":"Calle de Castilla La Nueva (de), 23",
    "sg:city":"Fuenlabrada",
    "sg:orig_category":"Ense\u00d1anza Variada",
    "sg:phone":"+34 916 15 45 20",
    "sg:postcode":"28941",
    "sg:province":"Madrid",
    "wof:name":"Flores Garcia Miguel",
    "wof:placetype":"venue"
},
  "geometry": {"coordinates":[-3.7973020077,40.2938117981],"type":"Point"}
}