{
  "type": "Feature",
  "properties": {
    "addr:full":"Calle de Madre De Dios, 16 Puente-genil C\u00f3rdoba 14500",
    "addr:housenumber":"16",
    "addr:postcode":"14500",
    "addr:street":"Calle De Madre;Dios;Co\u0301Rdoba",
    "iso:country":"ES",
    "sg:address":"Calle de Madre De Dios, 16",
    "sg:city":"Puente-genil",
    "sg:orig_category":"Imprenta",
    "sg:phone":"+34 957 60 07 81",
    "sg:postcode":"14500",
    "sg:province":"C\u00f3rdoba",
    "wof:name":"Hidalgo Gonzalez Antonio Jesus",
    "wof:placetype":"venue"
},
  "geometry": {"coordinates":[-4.7766270638,37.3889961243],"type":"Point"}
}