{
  "type": "Feature",
  "properties": {
    "addr:full":"Ctra De La Fuente, Km. 0002,5 Estepa Sevilla 41560",
    "addr:postcode":"41560",
    "addr:street":"Ctra De La Fuente Km. 0002,5;Sevilla",
    "iso:country":"ES",
    "sg:address":"Ctra De La Fuente, Km. 0002,5",
    "sg:city":"Estepa",
    "sg:orig_category":"Empresas De Carpinter\u00cda De Madera",
    "sg:phone":"+34 955 95 82 19",
    "sg:postcode":"41560",
    "sg:province":"Sevilla",
    "wof:name":"Perez Gimenez Jose Antonio",
    "wof:placetype":"venue"
},
  "geometry": {"coordinates":[-4.871740818,37.2891731262],"type":"Point"}
}