{
  "type": "Feature",
  "properties": {
    "addr:full":"Calle de Jaen, 10 Mostoles Madrid 28935",
    "addr:housenumber":"10",
    "addr:postcode":"28935",
    "addr:street":"Calle De Jaen",
    "iso:country":"ES",
    "sg:address":"Calle de Jaen, 10",
    "sg:city":"Mostoles",
    "sg:orig_category":"Papel, Reciclaje",
    "sg:phone":"+34 916 65 98 49",
    "sg:postcode":"28935",
    "sg:province":"Madrid",
    "wof:name":"Yugi S.l.",
    "wof:placetype":"venue"
},
  "geometry": {"coordinates":[-3.8752670288,40.3270759583],"type":"Point"}
}