{
  "type": "Feature",
  "properties": {
    "iso:country":"ES",
    "sg:address":"Manuel Prado-mallon, 25",
    "sg:city":"A Ramallosa",
    "sg:orig_category":"Molduras, Junquillos, Listones Y Molduras Perforadas",
    "sg:phone":"+34 986 35 47 36",
    "sg:postcode":"36379",
    "sg:province":"Pontevedra",
    "wof:name":"Rodriguez Mini\u00f1o Francisco",
    "wof:placetype":"venue"
},
  "geometry": {"coordinates":[-8.8134374619,42.1331443787],"type":"Point"}
}