{
  "type": "Feature",
  "properties": {
    "addr:full":"Santa Marta, 4 Iru\u00f1a Navarra 31003",
    "addr:housenumber":"4",
    "addr:postcode":"31003",
    "addr:street":"Santa Marta",
    "iso:country":"ES",
    "sg:address":"Santa Marta, 4",
    "sg:city":"Iru\u00f1a",
    "sg:orig_category":"Ortopedia General",
    "sg:phone":"+34 948 23 34 50",
    "sg:postcode":"31003",
    "sg:province":"Navarra",
    "wof:name":"Servicios Sanitarios A Domicilio S.l.",
    "wof:placetype":"venue"
},
  "geometry": {"coordinates":[-1.636417985,42.8073234558],"type":"Point"}
}