{
  "type": "Feature",
  "properties": {
    "iso:country":"ES",
    "sg:address":"Ctra Avila Mu\u00d1ico, S/n",
    "sg:city":"Martiherrero",
    "sg:orig_category":"Centros De Educaci\u00d3n Especial",
    "sg:phone":"+34 920 26 94 54",
    "sg:postcode":"05140",
    "sg:province":"\u00c1vila",
    "wof:name":"Centro De Educacion Especial Santa Teresa",
    "wof:placetype":"venue"
},
  "geometry": {"coordinates":[-4.7839479446,40.6717224121],"type":"Point"}
}