{
  "type": "Feature",
  "properties": {
    "addr:full":"Carrer de Lola Anglada, S/n Castelldefels Barcelona 08860",
    "addr:housenumber":"s / n",
    "addr:postcode":"08860",
    "addr:street":"Carrer De Lola Anglada",
    "iso:country":"ES",
    "sg:address":"Carrer de Lola Anglada, S/n",
    "sg:city":"Castelldefels",
    "sg:orig_category":"Centros De Educaci\u00d3n Especial",
    "sg:phone":"+34 936 36 30 67",
    "sg:postcode":"08860",
    "sg:province":"Barcelona",
    "wof:name":"Ceip Margallo",
    "wof:placetype":"venue"
},
  "geometry": {"coordinates":[1.9743779898,41.2898597717],"type":"Point"}
}