{
  "type": "Feature",
  "properties": {
    "addr:full":"Ctra. N. 340, Km. 0415,4 Santa Maria Aguila Almer\u00eda 04710",
    "addr:postcode":"04710",
    "addr:street":"Ctra. N. 340 Km. 0415,4;Almeri\u0301A",
    "iso:country":"ES",
    "sg:address":"Ctra. N. 340, Km. 0415,4",
    "sg:city":"Santa Maria Aguila",
    "sg:orig_category":"Goma: Materias Primas (producci\u00d3n, Distribuci\u00d3n)",
    "sg:phone":"+34 950 58 31 13",
    "sg:postcode":"04710",
    "sg:province":"Almer\u00eda",
    "sg:website":"www.sotrafa.com",
    "wof:name":"Sotrafa S.a.",
    "wof:placetype":"venue"
},
  "geometry": {"coordinates":[-2.7759139538,36.7795753479],"type":"Point"}
}