{
  "type": "Feature",
  "properties": {
    "addr:full":"Av Torre Roja, 15 Viladecans Barcelona 08840",
    "addr:housenumber":"15",
    "addr:postcode":"08840",
    "addr:street":"Av Torre Roja",
    "iso:country":"ES",
    "sg:address":"Av Torre Roja, 15",
    "sg:city":"Viladecans",
    "sg:orig_category":"Fabricaci\u00d3n De Distribuidores Autom\u00c1ticos",
    "sg:phone":"+34 936 58 84 91",
    "sg:postcode":"08840",
    "sg:province":"Barcelona",
    "wof:name":"Llamacafe S.l.",
    "wof:placetype":"venue"
},
  "geometry": {"coordinates":[2.0084159374,41.3226318359],"type":"Point"}
}