{
  "type": "Feature",
  "properties": {
    "addr:full":"Calle de Paloma, 39 Burgos Burgos 09003",
    "addr:housenumber":"39",
    "addr:postcode":"09003",
    "addr:street":"Calle De Paloma",
    "iso:country":"ES",
    "sg:address":"Calle de Paloma, 39",
    "sg:city":"Burgos",
    "sg:orig_category":"Bisuter\u00cda, Joyer\u00cda, Relojer\u00cda (al Por Menor)",
    "sg:phone":"+34 947 27 01 40",
    "sg:postcode":"09003",
    "sg:province":"Burgos",
    "wof:name":"Pedrosa Vivar Florentina",
    "wof:placetype":"venue"
},
  "geometry": {"coordinates":[-3.7034010887,42.340473175],"type":"Point"}
}