{
  "type": "Feature",
  "properties": {
    "iso:country":"ES",
    "sg:address":"Carrer de Sant Pere, 11",
    "sg:city":"Vic",
    "sg:orig_category":"Alimentaci\u00d3n General (al Por Mayor)",
    "sg:phone":"+34 938 85 02 15",
    "sg:postcode":"08500",
    "sg:province":"Barcelona",
    "wof:name":"Pujol Costa Jaume",
    "wof:placetype":"venue"
},
  "geometry": {"coordinates":[2.2519390583,41.9272613525],"type":"Point"}
}