{
  "type": "Feature",
  "properties": {
    "addr:full":"Calle de Fuentes, 100 Lepe Huelva 21440",
    "addr:housenumber":"100",
    "addr:postcode":"21440",
    "addr:street":"Calle De Fuentes",
    "iso:country":"ES",
    "sg:address":"Calle de Fuentes, 100",
    "sg:city":"Lepe",
    "sg:orig_category":"Molduras, Junquillos, Listones Y Molduras Perforadas",
    "sg:phone":"+34 959 38 20 24",
    "sg:postcode":"21440",
    "sg:province":"Huelva",
    "wof:name":"Pereira Palma Manuel",
    "wof:placetype":"venue"
},
  "geometry": {"coordinates":[-7.202038765,37.2512702942],"type":"Point"}
}