{
  "type": "Feature",
  "properties": {
    "iso:country":"ES",
    "sg:address":"Calle de Salamanca, S/n",
    "sg:city":"Benidorm",
    "sg:orig_category":"Centros Empresariales",
    "sg:phone":"+34 965 86 71 06",
    "sg:postcode":"03500",
    "sg:province":"Alicante",
    "wof:name":"Helafrin S.l.",
    "wof:placetype":"venue"
},
  "geometry": {"coordinates":[-0.1336439997,38.5437698364],"type":"Point"}
}