{
  "type": "Feature",
  "properties": {
    "addr:full":"Carretera Fontanillas, S/n Gualta Girona 17257",
    "addr:housenumber":"s",
    "addr:postcode":"17257",
    "addr:street":"Carretera Fontanillas;/ N Gualta",
    "iso:country":"ES",
    "sg:address":"Carretera Fontanillas, S/n",
    "sg:city":"Gualta",
    "sg:orig_category":"\u00c1reas De Especies Protegidas, Parques Zool\u00d3gicos",
    "sg:phone":"+34 972 76 19 85",
    "sg:postcode":"17257",
    "sg:province":"Girona",
    "wof:name":"Blay Tamarit S.l.",
    "wof:placetype":"venue"
},
  "geometry": {"coordinates":[3.1037321091,42.0280914307],"type":"Point"}
}