{
  "type": "Feature",
  "properties": {
    "iso:country":"ES",
    "sg:address":"C/ Barracar, 101",
    "sg:city":"Manacor",
    "sg:orig_category":"Empresas De Carpinter\u00cda De Madera",
    "sg:phone":"+34 971 55 96 80",
    "sg:postcode":"07500",
    "sg:province":"Islas Baleares",
    "wof:name":"Fusteria Copega S.l.",
    "wof:placetype":"venue"
},
  "geometry": {"coordinates":[3.2140591145,39.5738449097],"type":"Point"}
}