{
  "type": "Feature",
  "properties": {
    "addr:full":"Calle de Miracruz, 12 Donostia-san Sebastian Guip\u00f9zcoa 20001",
    "addr:housenumber":"12",
    "addr:postcode":"20001",
    "addr:street":"Calle De Miracruz",
    "iso:country":"ES",
    "sg:address":"Calle de Miracruz, 12",
    "sg:city":"Donostia-san Sebastian",
    "sg:orig_category":"Farmacias",
    "sg:phone":"+34 943 29 70 27",
    "sg:postcode":"20001",
    "sg:province":"Guip\u00f9zcoa",
    "wof:name":"Garcia De Alzuru Teresa Maria",
    "wof:placetype":"venue"
},
  "geometry": {"coordinates":[-1.9751759768,43.3217964172],"type":"Point"}
}