{
  "type": "Feature",
  "properties": {
    "addr:full":"Carrer de Llatzeret, 15 Barcelona Barcelona 08005",
    "addr:housenumber":"15",
    "addr:postcode":"08005",
    "addr:street":"Carrer De Llatzeret",
    "iso:country":"ES",
    "sg:address":"Carrer de Llatzeret, 15",
    "sg:city":"Barcelona",
    "sg:orig_category":"Artes Gr\u00c1ficas, Artes Pl\u00c1sticas (curso)",
    "sg:phone":"+34 933 07 47 36",
    "sg:postcode":"08005",
    "sg:province":"Barcelona",
    "wof:name":"Lourenco  Fulvio Carlos",
    "wof:placetype":"venue"
},
  "geometry": {"coordinates":[2.2015628815,41.4032096863],"type":"Point"}
}