{
  "type": "Feature",
  "properties": {
    "iso:country":"ES",
    "sg:address":"Ptge Nogues, 66",
    "sg:city":"Barcelona",
    "sg:orig_category":"Cerrajer\u00cda, Ferrallista",
    "sg:phone":"+34 932 19 75 66",
    "sg:postcode":"08025",
    "sg:province":"Barcelona",
    "wof:name":"Maires Alsina Juan",
    "wof:placetype":"venue"
},
  "geometry": {"coordinates":[2.165211916,41.4091644287],"type":"Point"}
}