{
  "type": "Feature",
  "properties": {
    "addr:full":"Plaz Plaza Espa\u00d1a, 22 Alcubierre Huesca 22251",
    "addr:housenumber":"22",
    "addr:postcode":"22251",
    "addr:street":"Espan\u0303A",
    "iso:country":"ES",
    "sg:address":"Plaz Plaza Espa\u00d1a, 22",
    "sg:city":"Alcubierre",
    "sg:orig_category":"Confiter\u00cdas, Chocolater\u00cdas (al Por Menor)",
    "sg:phone":"+34 974 57 48 82",
    "sg:postcode":"22251",
    "sg:province":"Huesca",
    "wof:name":"Hermanos Berdun S.l.",
    "wof:placetype":"venue"
},
  "geometry": {"coordinates":[-0.4524981081,41.8081207275],"type":"Point"}
}