{
  "type": "Feature",
  "properties": {
    "addr:full":"Rua Alfredo Nan, 37 Allariz Ourense 32660",
    "addr:housenumber":"37",
    "addr:postcode":"32660",
    "addr:street":"Rua Alfredo Nan",
    "iso:country":"ES",
    "sg:address":"Rua Alfredo Nan, 37",
    "sg:city":"Allariz",
    "sg:orig_category":"Venta, Instalaci\u00d3n De Calefacci\u00d3n",
    "sg:phone":"+34 988 44 03 90",
    "sg:postcode":"32660",
    "sg:province":"Ourense",
    "wof:name":"Bola\u00f1o Carnero Manuel",
    "wof:placetype":"venue"
},
  "geometry": {"coordinates":[-7.8035750389,42.1881752014],"type":"Point"}
}