{
  "type": "Feature",
  "properties": {
    "addr:full":"Carr Progres, 6 Lleida Lleida 25005",
    "addr:housenumber":"6",
    "addr:postcode":"25005",
    "addr:street":"Carr Progres",
    "iso:country":"ES",
    "sg:address":"Carr Progres, 6",
    "sg:city":"Lleida",
    "sg:orig_category":"Restaurantes",
    "sg:phone":"+34 973 24 53 86",
    "sg:postcode":"25005",
    "sg:province":"Lleida",
    "wof:name":"Porta Campabadal Juan",
    "wof:placetype":"venue"
},
  "geometry": {"coordinates":[0.6285539865,41.6363868713],"type":"Point"}
}