{
  "type": "Feature",
  "properties": {
    "iso:country":"ES",
    "sg:address":"Calle de Real, 120",
    "sg:city":"San Sebastian De Los Reyes",
    "sg:orig_category":"Distribuci\u00d3n De Petr\u00d3leo Y Derivados",
    "sg:phone":"+34 916 63 77 50",
    "sg:postcode":"28700",
    "sg:province":"Madrid",
    "wof:name":"Repsol Ypf S.a.",
    "wof:placetype":"venue"
},
  "geometry": {"coordinates":[-3.6203041077,40.5518035889],"type":"Point"}
}