{
  "type": "Feature",
  "properties": {
    "addr:full":"Calle de Alcalde Pedro Uceda, S/n Hinojales Huelva 21389",
    "addr:housenumber":"s",
    "addr:postcode":"21389",
    "addr:street":"Calle De Alcalde Pedro Uceda;/ N Hinojales",
    "iso:country":"ES",
    "sg:address":"Calle de Alcalde Pedro Uceda, S/n",
    "sg:city":"Hinojales",
    "sg:orig_category":"Centros De Educaci\u00d3n Especial",
    "sg:phone":"+34 959 72 26 22",
    "sg:postcode":"21389",
    "sg:province":"Huelva",
    "wof:name":"Junta De Andalucia",
    "wof:placetype":"venue"
},
  "geometry": {"coordinates":[-6.5905528069,38.0087127686],"type":"Point"}
}