{
  "type": "Feature",
  "properties": {
    "addr:full":"Carrer de Balmes, 376 Barcelona Barcelona 08022",
    "addr:housenumber":"376",
    "addr:postcode":"08022",
    "addr:street":"Carrer De Balmes",
    "iso:country":"ES",
    "sg:address":"Carrer de Balmes, 376",
    "sg:city":"Barcelona",
    "sg:orig_category":"Agencias De Prensa E Informaci\u00d3n",
    "sg:phone":"+34 932 07 09 84",
    "sg:postcode":"08022",
    "sg:province":"Barcelona",
    "sg:website":"www.cordonpress.com",
    "wof:name":"Cordon Press S. L.",
    "wof:placetype":"venue"
},
  "geometry": {"coordinates":[2.140417099,41.4047813416],"type":"Point"}
}