{
  "type": "Feature",
  "properties": {
    "addr:full":"Ptge Lleteries, 11 Seu D'urgell Lleida 25700",
    "addr:housenumber":"11",
    "addr:postcode":"25700",
    "addr:street":"Ptge Lleteries",
    "iso:country":"ES",
    "sg:address":"Ptge Lleteries, 11",
    "sg:city":"Seu D'urgell",
    "sg:orig_category":"Ingeniero",
    "sg:phone":"+34 973 35 02 36",
    "sg:postcode":"25700",
    "sg:province":"Lleida",
    "wof:name":"Martin Garcia Pedro Jose",
    "wof:placetype":"venue"
},
  "geometry": {"coordinates":[0.6457189918,41.6027946472],"type":"Point"}
}