{
  "type": "Feature",
  "properties": {
    "iso:country":"ES",
    "sg:address":"Sara Karrika, 11",
    "sg:city":"Bera",
    "sg:orig_category":"Peluquer\u00cdas, Peluquer\u00cda Mixta",
    "sg:phone":"+34 948 63 10 55",
    "sg:postcode":"31780",
    "sg:province":"Navarra",
    "wof:name":"Picabea Etxebeste Bego\u00f1a",
    "wof:placetype":"venue"
},
  "geometry": {"coordinates":[-1.6860439777,43.2754211426],"type":"Point"}
}