{
  "type": "Feature",
  "properties": {
    "iso:country":"ES",
    "sg:address":"Virgen Del Puy, 13",
    "sg:city":"Iru\u00f1a",
    "sg:orig_category":"Iglesia Cat\u00d3lica",
    "sg:phone":"+34 948 25 21 83",
    "sg:postcode":"31011",
    "sg:province":"Navarra",
    "wof:name":"Parroquia San Vicente De Paul",
    "wof:placetype":"venue"
},
  "geometry": {"coordinates":[-1.6594330072,42.81640625],"type":"Point"}
}