{
  "type": "Feature",
  "properties": {
    "iso:country":"ES",
    "sg:address":"Avda Quinto Centenario, 8",
    "sg:city":"Sanlucar De Barrameda",
    "sg:orig_category":"Promotores Constructores",
    "sg:phone":"+34 956 36 94 12",
    "sg:postcode":"11540",
    "sg:province":"C\u00e1diz",
    "wof:name":"Promotora Constructora Herederos De Jose Luis Morales Lopez",
    "wof:placetype":"venue"
},
  "geometry": {"coordinates":[-6.3585891724,36.7747955322],"type":"Point"}
}