{
  "type": "Feature",
  "properties": {
    "iso:country":"ES",
    "sg:address":"Calle de Borderas, 3",
    "sg:city":"Zaragoza",
    "sg:orig_category":"Centros Empresariales",
    "sg:phone":"+34 976 37 10 20",
    "sg:postcode":"50007",
    "sg:province":"Zaragoza",
    "wof:name":"Villagrasa Corral Pedro Luis",
    "wof:placetype":"venue"
},
  "geometry": {"coordinates":[-0.878805995,41.636932373],"type":"Point"}
}