{
  "type": "Feature",
  "properties": {
    "iso:country":"ES",
    "sg:address":"Avda Hellin, S/n",
    "sg:city":"Madrid",
    "sg:orig_category":"Alimentaci\u00d3n General (al Por Menor)",
    "sg:phone":"+34 917 75 97 12",
    "sg:postcode":"28037",
    "sg:province":"Madrid",
    "wof:name":"Moreno Berrio Maria Del Carmen",
    "wof:placetype":"venue"
},
  "geometry": {"coordinates":[-3.6162190437,40.432800293],"type":"Point"}
}