{
  "type": "Feature",
  "properties": {
    "addr:full":"Carrer de Jardi, 11 Sabadell Barcelona 08202",
    "addr:housenumber":"11",
    "addr:postcode":"08202",
    "addr:street":"Carrer De Jardi",
    "iso:country":"ES",
    "sg:address":"Carrer de Jardi, 11",
    "sg:city":"Sabadell",
    "sg:orig_category":"M\u00c9dicos: Gastroenterolog\u00cda Y Hepatolog\u00cda (aparato Digestivo)",
    "sg:phone":"+34 937 26 31 77",
    "sg:postcode":"08202",
    "sg:province":"Barcelona",
    "wof:name":"Pinos Desplat Tomas",
    "wof:placetype":"venue"
},
  "geometry": {"coordinates":[2.1103420258,41.5452423096],"type":"Point"}
}