{
  "type": "Feature",
  "properties": {
    "addr:full":"La Iglesia, 3 Ponferrada Le\u00f3n 24400",
    "addr:housenumber":"3",
    "addr:postcode":"24400",
    "addr:street":"Iglesia",
    "iso:country":"ES",
    "sg:address":"La Iglesia, 3",
    "sg:city":"Ponferrada",
    "sg:orig_category":"Peluqueros: De Se\u00d1oras",
    "sg:phone":"+34 987 41 04 19",
    "sg:postcode":"24400",
    "sg:province":"Le\u00f3n",
    "wof:name":"Blanco Garnelo Maria Josefa",
    "wof:placetype":"venue"
},
  "geometry": {"coordinates":[-6.6254000664,42.5469093323],"type":"Point"}
}