{
  "type": "Feature",
  "properties": {
    "iso:country":"ES",
    "sg:address":"Carrer de Pau Casals, 25",
    "sg:city":"S. Celoni",
    "sg:orig_category":"Molduras, Junquillos, Listones Y Molduras Perforadas",
    "sg:phone":"+34 938 67 48 34",
    "sg:postcode":"08470",
    "sg:province":"Barcelona",
    "wof:name":"Giro Gudiol Alberto",
    "wof:placetype":"venue"
},
  "geometry": {"coordinates":[2.4922180176,41.6874847412],"type":"Point"}
}