{
  "type": "Feature",
  "properties": {
    "iso:country":"ES",
    "sg:address":"Calle de Doctor Jesus Galan, 25",
    "sg:city":"Avila",
    "sg:orig_category":"Reposter\u00cdas",
    "sg:phone":"+34 920 21 22 79",
    "sg:postcode":"05003",
    "sg:province":"\u00c1vila",
    "wof:name":"Jose Maria De La Iglesia Martin Y Maria Del Mar Nieves Jimenez Cdad.",
    "wof:placetype":"venue"
},
  "geometry": {"coordinates":[-4.69343853,40.6521835327],"type":"Point"}
}