{
  "type": "Feature",
  "properties": {
    "iso:country":"ES",
    "sg:address":"Carr Caba\u00d1al, 3",
    "sg:city":"Cullera",
    "sg:orig_category":"Inmobiliaria (agencias)",
    "sg:phone":"+34 961 72 05 56",
    "sg:postcode":"46400",
    "sg:province":"Valencia",
    "sg:website":"www.inmocrespo.com",
    "wof:name":"Crespo Escobedo Jose Luis",
    "wof:placetype":"venue"
},
  "geometry": {"coordinates":[-0.245667994,39.1642837524],"type":"Point"}
}