{
  "type": "Feature",
  "properties": {
    "iso:country":"ES",
    "sg:address":"Calle de Monasterio, S/n",
    "sg:city":"Yepes",
    "sg:orig_category":"Quincaller\u00cda (al Por Menor)",
    "sg:phone":"+34 925 15 42 50",
    "sg:postcode":"45313",
    "sg:province":"Toledo",
    "wof:name":"Fontaneria Y Calefaccion Mora Monedero S.l.",
    "wof:placetype":"venue"
},
  "geometry": {"coordinates":[-3.6232039928,39.9013290405],"type":"Point"}
}