{
  "type": "Feature",
  "properties": {
    "addr:full":"Calle de Fernando De Lesseps, 5 Malaga M\u00e1laga 29005",
    "addr:housenumber":"5",
    "addr:postcode":"29005",
    "addr:street":"Calle De Fernando De Lesseps;Ma\u0301Laga",
    "iso:country":"ES",
    "sg:address":"Calle de Fernando De Lesseps, 5",
    "sg:city":"Malaga",
    "sg:orig_category":"Grafistas",
    "sg:phone":"+34 952 22 64 53",
    "sg:postcode":"29005",
    "sg:province":"M\u00e1laga",
    "sg:website":"www.visitasvirtuales.com",
    "wof:name":"Cantero Tellez Raquel",
    "wof:placetype":"venue"
},
  "geometry": {"coordinates":[-4.4228549004,36.7206077576],"type":"Point"}
}