{
  "type": "Feature",
  "properties": {
    "iso:country":"ES",
    "sg:address":"Avgd Seminario, 50",
    "sg:city":"Moncada",
    "sg:orig_category":"Molduras, Junquillos, Listones Y Molduras Perforadas",
    "sg:phone":"+34 961 39 08 55",
    "sg:postcode":"46113",
    "sg:province":"Valencia",
    "wof:name":"Conchilla Fornosa Jose Angel",
    "wof:placetype":"venue"
},
  "geometry": {"coordinates":[-0.3982529938,39.5452728271],"type":"Point"}
}