{
  "type": "Feature",
  "properties": {
    "addr:full":"Calle de Olite, 3 Peralta Navarra 31350",
    "addr:housenumber":"3",
    "addr:postcode":"31350",
    "addr:street":"Calle De Olite",
    "iso:country":"ES",
    "sg:address":"Calle de Olite, 3",
    "sg:city":"Peralta",
    "sg:orig_category":"Chapister\u00cda",
    "sg:phone":"+34 948 71 30 11",
    "sg:postcode":"31350",
    "sg:province":"Navarra",
    "wof:name":"Rodriguez Ezquerro Antonio",
    "wof:placetype":"venue"
},
  "geometry": {"coordinates":[-1.8042570353,42.3395729065],"type":"Point"}
}