{
  "type": "Feature",
  "properties": {
    "addr:full":"Carrer de Ramon Batlle, 12 Barcelona Barcelona 08030",
    "addr:housenumber":"12",
    "addr:postcode":"08030",
    "addr:street":"Carrer De Ramon Batlle",
    "iso:country":"ES",
    "sg:address":"Carrer de Ramon Batlle, 12",
    "sg:city":"Barcelona",
    "sg:orig_category":"Electromec\u00c1nica",
    "sg:phone":"+34 933 11 58 26",
    "sg:postcode":"08030",
    "sg:province":"Barcelona",
    "wof:name":"Duque Jimenez Jose",
    "wof:placetype":"venue"
},
  "geometry": {"coordinates":[2.1900138855,41.4318161011],"type":"Point"}
}