{
  "type": "Feature",
  "properties": {
    "iso:country":"ES",
    "sg:address":"Carrer de Casanova, 52",
    "sg:city":"Barcelona",
    "sg:orig_category":"Material De Ocasi\u00d3n (compra, Reventa)",
    "sg:phone":"+34 902 36 61 76",
    "sg:postcode":"08011",
    "sg:province":"Barcelona",
    "sg:website":"www.ofertaspc.com",
    "wof:name":"Ofertas Pc S.l.",
    "wof:placetype":"venue"
},
  "geometry": {"coordinates":[2.1599900723,41.3847007751],"type":"Point"}
}