{
  "type": "Feature",
  "properties": {
    "iso:country":"ES",
    "sg:address":"Calle de Sevilla, 54",
    "sg:city":"Mairena Alcor",
    "sg:orig_category":"Supermercados Y Hipermercados",
    "sg:phone":"+34 955 94 33 03",
    "sg:postcode":"41510",
    "sg:province":"Sevilla",
    "wof:name":"Marin Bustos Isabel",
    "wof:placetype":"venue"
},
  "geometry": {"coordinates":[-5.7510399818,37.3699493408],"type":"Point"}
}