{
  "type": "Feature",
  "properties": {
    "addr:full":"Avda Divina Pastora, 1 Granada Granada 18012",
    "addr:housenumber":"1",
    "addr:postcode":"18012",
    "addr:street":"Avda Divina Pastora",
    "iso:country":"ES",
    "sg:address":"Avda Divina Pastora, 1",
    "sg:city":"Granada",
    "sg:orig_category":"M\u00c9dicos: Cardiolog\u00cda Y Afecciones Cardiovasculares",
    "sg:phone":"+34 958 27 10 22",
    "sg:postcode":"18012",
    "sg:province":"Granada",
    "wof:name":"Prieto Granda Jesus Angel",
    "wof:placetype":"venue"
},
  "geometry": {"coordinates":[-3.6030590534,37.1838989258],"type":"Point"}
}