{
  "type": "Feature",
  "properties": {
    "iso:country":"ES",
    "sg:address":"Calle de Bailen, 19",
    "sg:city":"Alacant",
    "sg:orig_category":"Ense\u00d1anza Variada",
    "sg:phone":"+34 965 21 28 43",
    "sg:postcode":"03001",
    "sg:province":"Alicante",
    "sg:website":"www.intervertice.com",
    "wof:name":"Centro Estudios Profesionales Inter-vertice Alicante S.l.",
    "wof:placetype":"venue"
},
  "geometry": {"coordinates":[-0.4845370948,38.3451919556],"type":"Point"}
}