{
  "type": "Feature",
  "properties": {
    "iso:country":"ES",
    "sg:address":"Calle de Zaragoza, 28",
    "sg:city":"Soria",
    "sg:classifiers":[
        {
            "category":"Taxi",
            "type":"Transportation"
        }
    ],
    "sg:phone":"+34 975 23 16 99",
    "sg:postcode":"42004",
    "sg:province":"Soria",
    "wof:name":"Valero Garcia Isidro",
    "wof:placetype":"venue"
},
  "geometry": {"coordinates":[-2.4791219234,41.7687492371],"type":"Point"}
}