{
  "type": "Feature",
  "properties": {
    "addr:full":"Calle de Bolivia, S/n Iscar Valladolid 47420",
    "addr:housenumber":"s / n",
    "addr:postcode":"47420",
    "addr:street":"Calle De Bolivia",
    "iso:country":"ES",
    "sg:address":"Calle de Bolivia, S/n",
    "sg:city":"Iscar",
    "sg:orig_category":"Maquinaria Para Industrias Diversas",
    "sg:phone":"+34 983 61 22 22",
    "sg:postcode":"47420",
    "sg:province":"Valladolid",
    "wof:name":"Mecanizados Martin Merlo S.l.",
    "wof:placetype":"venue"
},
  "geometry": {"coordinates":[-4.5474801064,41.3552131653],"type":"Point"}
}