{
  "type": "Feature",
  "properties": {
    "addr:full":"Calle de San Isidro Labrador, 1 Pedroso Sevilla 41360",
    "addr:housenumber":"1",
    "addr:postcode":"41360",
    "addr:street":"Calle De San Isidro Labrador",
    "iso:country":"ES",
    "sg:address":"Calle de San Isidro Labrador, 1",
    "sg:city":"Pedroso",
    "sg:orig_category":"Cajas Para Embalar",
    "sg:phone":"+34 954 88 91 17",
    "sg:postcode":"41360",
    "sg:province":"Sevilla",
    "wof:name":"Caja Rural Del Sur Sociedad Cooperativa",
    "wof:placetype":"venue"
},
  "geometry": {"coordinates":[-5.7650637627,37.8378601074],"type":"Point"}
}