{
  "type": "Feature",
  "properties": {
    "iso:country":"ES",
    "sg:address":"Pinada, 2",
    "sg:city":"Palmanova",
    "sg:orig_category":"Alquiler De Bicicletas Y Motocicletas",
    "sg:phone":"+34 971 68 27 38",
    "sg:postcode":"07181",
    "sg:province":"Islas Baleares",
    "wof:name":"Rodriguez Ruiz Juan Bautista",
    "wof:placetype":"venue"
},
  "geometry": {"coordinates":[2.5352098942,39.5245780945],"type":"Point"}
}