{
  "type": "Feature",
  "properties": {
    "iso:country":"ES",
    "sg:address":"Calle de Fuencarral, 138",
    "sg:city":"Madrid",
    "sg:orig_category":"Asesor\u00cda Sobre Comunicaci\u00d3n De Empresas",
    "sg:phone":"+34 914 45 85 99",
    "sg:postcode":"28010",
    "sg:province":"Madrid",
    "sg:website":"www.lam-asesoria.com",
    "wof:name":"Controlmadrid Consulting S.l.u.",
    "wof:placetype":"venue"
},
  "geometry": {"coordinates":[-3.7034039497,40.4318618774],"type":"Point"}
}