{
  "type": "Feature",
  "properties": {
    "iso:country":"ES",
    "sg:address":"Calle de Antonio Chacon, 5",
    "sg:city":"Malaga",
    "sg:orig_category":"Asesor\u00cda De Formaci\u00d3n Y Gesti\u00d3n De Personal",
    "sg:phone":"+34 952 04 07 89",
    "sg:postcode":"29003",
    "sg:province":"M\u00e1laga",
    "wof:name":"Ramos Rueda Teresa",
    "wof:placetype":"venue"
},
  "geometry": {"coordinates":[-4.4478216171,36.6992454529],"type":"Point"}
}