{
  "type": "Feature",
  "properties": {
    "iso:country":"ES",
    "sg:address":"Calle de Ejido De La Alcantarilla, 28",
    "sg:city":"Jaen",
    "sg:orig_category":"Producci\u00d3n De Huevos",
    "sg:phone":"+34 953 23 37 15",
    "sg:postcode":"23001",
    "sg:province":"Ja\u00e9n",
    "wof:name":"Barragan Martinez Rosa Maria",
    "wof:placetype":"venue"
},
  "geometry": {"coordinates":[-3.7885410786,37.7638168335],"type":"Point"}
}