{
  "type": "Feature",
  "properties": {
    "iso:country":"ES",
    "sg:address":"Randin, S/n",
    "sg:city":"Randin",
    "sg:classifiers":[
        {
            "category":"Taxi",
            "type":"Transportation"
        }
    ],
    "sg:phone":"+34 988 30 25 81",
    "sg:postcode":"32646",
    "sg:province":"Ourense",
    "wof:name":"Rodriguez Docampo David",
    "wof:placetype":"venue"
},
  "geometry": {"coordinates":[-7.8745241165,41.9077987671],"type":"Point"}
}