{
  "type": "Feature",
  "properties": {
    "iso:country":"ES",
    "sg:address":"Avda Guadalajara, 11",
    "sg:city":"Alcala Henares",
    "sg:orig_category":"Bisuter\u00cda, Joyer\u00cda, Relojer\u00cda (al Por Menor)",
    "sg:phone":"+34 918 81 24 18",
    "sg:postcode":"28805",
    "sg:province":"Madrid",
    "wof:name":"Garcia Meco Inmaculada",
    "wof:placetype":"venue"
},
  "geometry": {"coordinates":[-3.3595399857,40.4865264893],"type":"Point"}
}