{
  "type": "Feature",
  "properties": {
    "addr:full":"Calle de Virgen Del Sagrario, 30 Madrid Madrid 28027",
    "addr:housenumber":"30",
    "addr:postcode":"madrid;28027",
    "addr:street":"Calle De Virgen Del Sagrario",
    "iso:country":"ES",
    "sg:address":"Calle de Virgen Del Sagrario, 30",
    "sg:city":"Madrid",
    "sg:orig_category":"Molduras, Junquillos, Listones Y Molduras Perforadas",
    "sg:phone":"+34 914 03 89 31",
    "sg:postcode":"28027",
    "sg:province":"Madrid",
    "wof:name":"Uamil Duran Jorge",
    "wof:placetype":"venue"
},
  "geometry": {"coordinates":[-3.6507070065,40.4379463196],"type":"Point"}
}