{
  "type": "Feature",
  "properties": {
    "iso:country":"ES",
    "sg:address":"Calle de Eladio Bustamante, 26",
    "sg:city":"Villasana Mena",
    "sg:orig_category":"Restaurantes",
    "sg:phone":"+34 947 14 10 47",
    "sg:postcode":"09580",
    "sg:province":"Burgos",
    "wof:name":"Erostarbe Novales Eva",
    "wof:placetype":"venue"
},
  "geometry": {"coordinates":[-3.2799839973,43.1019859314],"type":"Point"}
}