{
  "type": "Feature",
  "properties": {
    "iso:country":"ES",
    "sg:address":"Calle de Aben Humeya, 6",
    "sg:city":"Granada",
    "sg:orig_category":"Arquitectos",
    "sg:phone":"+34 958 25 18 30",
    "sg:postcode":"18005",
    "sg:province":"Granada",
    "wof:name":"Egopri Xxi S.l.",
    "wof:placetype":"venue"
},
  "geometry": {"coordinates":[-3.6003568172,37.1703033447],"type":"Point"}
}