{
  "type": "Feature",
  "properties": {
    "addr:full":"Ctra Carretera, S/n Malanquilla Zaragoza 50315",
    "addr:postcode":"50315",
    "addr:street":"Ctra Carretera S / N Malanquilla",
    "iso:country":"ES",
    "sg:address":"Ctra Carretera, S/n",
    "sg:city":"Malanquilla",
    "sg:orig_category":"Albergues",
    "sg:phone":"+34 976 54 60 33",
    "sg:postcode":"50315",
    "sg:province":"Zaragoza",
    "wof:name":"Serrano Pelegrin Carlos",
    "wof:placetype":"venue"
},
  "geometry": {"coordinates":[-1.8762290478,41.5698890686],"type":"Point"}
}