{
  "type": "Feature",
  "properties": {
    "iso:country":"ES",
    "sg:address":"C/ Gavarres, 12",
    "sg:city":"Salt",
    "sg:orig_category":"Promotores Constructores",
    "sg:phone":"+34 972 23 62 78",
    "sg:postcode":"17190",
    "sg:province":"Girona",
    "wof:name":"Construccions J.j. Valenti",
    "wof:placetype":"venue"
},
  "geometry": {"coordinates":[2.7873120308,41.9695587158],"type":"Point"}
}