{
  "type": "Feature",
  "properties": {
    "iso:country":"ES",
    "sg:address":"Poligono Alijares, S/n",
    "sg:city":"Jumilla",
    "sg:orig_category":"Maquinaria Para Industrias Diversas",
    "sg:phone":"+34 968 75 79 40",
    "sg:postcode":"30520",
    "sg:province":"Murcia",
    "wof:name":"Gonzalez Cutillas Jose Antonio",
    "wof:placetype":"venue"
},
  "geometry": {"coordinates":[-1.3276422024,38.4354362488],"type":"Point"}
}