{
  "type": "Feature",
  "properties": {
    "iso:country":"ES",
    "sg:address":"Carrer de Severo Ochoa, S/n",
    "sg:city":"Granollers",
    "sg:orig_category":"Pintura Industrial (trabajos De)",
    "sg:phone":"+34 938 40 20 23",
    "sg:postcode":"08403",
    "sg:province":"Barcelona",
    "wof:name":"Xavi Disseny S.l.",
    "wof:placetype":"venue"
},
  "geometry": {"coordinates":[2.2699067593,41.6003494263],"type":"Point"}
}