{
  "type": "Feature",
  "properties": {
    "iso:country":"ES",
    "sg:address":"Calle de San Miguel, 42",
    "sg:city":"Cortes",
    "sg:orig_category":"Lencer\u00cda Femenina, Corseter\u00cda, Trajes De Ba\u00d1o (al Por Menor)",
    "sg:phone":"+34 948 80 00 47",
    "sg:postcode":"31530",
    "sg:province":"Navarra",
    "wof:name":"Coloma Llorca Agustina",
    "wof:placetype":"venue"
},
  "geometry": {"coordinates":[-1.42129004,41.9221916199],"type":"Point"}
}