{
  "type": "Feature",
  "properties": {
    "addr:full":"Calle de San Luis, 57 Coru\u00d1a A Coru\u00f1a 15007",
    "addr:housenumber":"57",
    "addr:postcode":"15007",
    "addr:street":"Calle De San Luis;Corun\u0303A",
    "iso:country":"ES",
    "sg:address":"Calle de San Luis, 57",
    "sg:city":"Coru\u00d1a",
    "sg:orig_category":"Alimentaci\u00d3n General (al Por Menor)",
    "sg:phone":"+34 981 15 09 06",
    "sg:postcode":"15007",
    "sg:province":"A Coru\u00f1a",
    "wof:name":"Varela Cotelo Herminio",
    "wof:placetype":"venue"
},
  "geometry": {"coordinates":[-8.4116764069,43.3538856506],"type":"Point"}
}