{
  "type": "Feature",
  "properties": {
    "iso:country":"ES",
    "sg:address":"Av Roma, 97",
    "sg:city":"Manlleu",
    "sg:orig_category":"Venta, Instalaci\u00d3n De Calefacci\u00d3n",
    "sg:phone":"+34 938 50 69 29",
    "sg:postcode":"08560",
    "sg:province":"Barcelona",
    "wof:name":"Calefaccio Triola S.c.p.",
    "wof:placetype":"venue"
},
  "geometry": {"coordinates":[2.2857089043,42.0042610168],"type":"Point"}
}