{
  "type": "Feature",
  "properties": {
    "addr:full":"Rua Alcalde Ramiro Rueda Fernandez, 16 Lugo Lugo 27003",
    "addr:housenumber":"16",
    "addr:postcode":"27003",
    "addr:street":"Rua Alcalde Ramiro Rueda Fernandez",
    "iso:country":"ES",
    "sg:address":"Rua Alcalde Ramiro Rueda Fernandez, 16",
    "sg:city":"Lugo",
    "sg:orig_category":"Abogados",
    "sg:phone":"+34 982 24 19 06",
    "sg:postcode":"27003",
    "sg:province":"Lugo",
    "wof:name":"Diaz Pardeiro Celestino",
    "wof:placetype":"venue"
},
  "geometry": {"coordinates":[-7.5607028008,43.0185661316],"type":"Point"}
}