{
  "type": "Feature",
  "properties": {
    "iso:country":"ES",
    "sg:address":"Carrer de Enamorats, 117",
    "sg:city":"Barcelona",
    "sg:orig_category":"Peluquer\u00cdas, Peluquer\u00cda Mixta",
    "sg:phone":"+34 932 65 49 97",
    "sg:postcode":"08026",
    "sg:province":"Barcelona",
    "wof:name":"Izquierdo Ayarza Maria Soledad",
    "wof:placetype":"venue"
},
  "geometry": {"coordinates":[2.1836960316,41.4072647095],"type":"Point"}
}