{
  "type": "Feature",
  "properties": {
    "iso:country":"ES",
    "sg:address":"Plaz Fueros, 2",
    "sg:city":"Errenteria",
    "sg:orig_category":"Ropa Para Ni\u00d1os (al Por Menor)",
    "sg:phone":"+34 943 52 60 62",
    "sg:postcode":"20100",
    "sg:province":"Guip\u00f9zcoa",
    "wof:name":"Alayo Lorente Mercedes",
    "wof:placetype":"venue"
},
  "geometry": {"coordinates":[-1.8996850252,43.314365387],"type":"Point"}
}