{
  "type": "Feature",
  "properties": {
    "iso:country":"ES",
    "sg:address":"Calle de Jesus, 3",
    "sg:city":"Pedro Abad",
    "sg:orig_category":"Electrodom\u00c9sticos (al Por Menor)",
    "sg:phone":"+34 957 18 62 61",
    "sg:postcode":"14630",
    "sg:province":"C\u00f3rdoba",
    "wof:name":"Ruiz Roman Francisco",
    "wof:placetype":"venue"
},
  "geometry": {"coordinates":[-4.4550452232,37.9659729004],"type":"Point"}
}