{
  "type": "Feature",
  "properties": {
    "iso:country":"ES",
    "sg:address":"Barreiros, S/n",
    "sg:city":"Rante",
    "sg:orig_category":"Centros Empresariales",
    "sg:phone":"+34 988 36 40 30",
    "sg:postcode":"32910",
    "sg:province":"Ourense",
    "wof:name":"Asociacion De Propietarios Zona Comercial Barreiros",
    "wof:placetype":"venue"
},
  "geometry": {"coordinates":[-7.8716039658,42.2960510254],"type":"Point"}
}