{
  "type": "Feature",
  "properties": {
    "addr:full":"Calle de Simon Aranda, 2 Carpio Valladolid 47470",
    "addr:housenumber":"2",
    "addr:postcode":"47470",
    "addr:street":"Calle De Simon Aranda",
    "iso:country":"ES",
    "sg:address":"Calle de Simon Aranda, 2",
    "sg:city":"Carpio",
    "sg:orig_category":"Cajas Para Embalar",
    "sg:phone":"+34 983 86 37 35",
    "sg:postcode":"47470",
    "sg:province":"Valladolid",
    "sg:website":"www.crduero.com",
    "wof:name":"Caja Rural Del Duero",
    "wof:placetype":"venue"
},
  "geometry": {"coordinates":[-5.1114068031,41.2139930725],"type":"Point"}
}