{
  "type": "Feature",
  "properties": {
    "addr:full":"Carr Guetaria, 13 Eliana Valencia 46183",
    "addr:housenumber":"13",
    "addr:postcode":"46183",
    "addr:street":"Carr Guetaria",
    "iso:country":"ES",
    "sg:address":"Carr Guetaria, 13",
    "sg:city":"Eliana",
    "sg:orig_category":"Edici\u00d3n De Diarios, Revistas, Boletines",
    "sg:phone":"+34 962 74 08 96",
    "sg:postcode":"46183",
    "sg:province":"Valencia",
    "wof:name":"Obrador Bravo Marta",
    "wof:placetype":"venue"
},
  "geometry": {"coordinates":[-0.528208971,39.5667457581],"type":"Point"}
}