{
  "type": "Feature",
  "properties": {
    "iso:country":"ES",
    "sg:address":"Avda Madrid, 113",
    "sg:city":"Zaragoza",
    "sg:orig_category":"Frutas Y Legumbres Secas (al Por Mayor)",
    "sg:phone":"+34 976 34 94 58",
    "sg:postcode":"50010",
    "sg:province":"Zaragoza",
    "wof:name":"Frutos Secos El Rincon S.l.",
    "wof:placetype":"venue"
},
  "geometry": {"coordinates":[-0.9082840085,41.6526832581],"type":"Point"}
}