{
  "type": "Feature",
  "properties": {
    "iso:country":"ES",
    "sg:address":"Carr Vicent Serra I Orvay, 47",
    "sg:city":"Eivissa",
    "sg:orig_category":"Alquiler De V\u00cddeo",
    "sg:phone":"+34 971 19 09 58",
    "sg:postcode":"07800",
    "sg:province":"Islas Baleares",
    "wof:name":"Pareja Aguilar Emilio",
    "wof:placetype":"venue"
},
  "geometry": {"coordinates":[1.4240900278,38.9106216431],"type":"Point"}
}