{
  "type": "Feature",
  "properties": {
    "addr:full":"M. Ynca, S/n Torremolinos M\u00e1laga 29620",
    "addr:housenumber":"s / n",
    "addr:postcode":"29620",
    "addr:street":"Ma\u0301Laga",
    "iso:country":"ES",
    "sg:address":"M. Ynca, S/n",
    "sg:city":"Torremolinos",
    "sg:orig_category":"Aguas (distribuci\u00d3n, Servicios)",
    "sg:phone":"+34 952 38 02 37",
    "sg:postcode":"29620",
    "sg:province":"M\u00e1laga",
    "wof:name":"Aguas Y Saneamiento Torremolinos S.a.m.",
    "wof:placetype":"venue"
},
  "geometry": {"coordinates":[-4.5160393715,36.6265563965],"type":"Point"}
}