{
  "type": "Feature",
  "properties": {
    "iso:country":"ES",
    "sg:address":"Avda Guardia Civil, 14",
    "sg:city":"Albacete",
    "sg:orig_category":"Promotores Constructores",
    "sg:phone":"+34 967 52 09 21",
    "sg:postcode":"02005",
    "sg:province":"Albacete",
    "wof:name":"Trazados Y Cimientos S.l.",
    "wof:placetype":"venue"
},
  "geometry": {"coordinates":[-1.8579109907,38.9992713928],"type":"Point"}
}