{
  "type": "Feature",
  "properties": {
    "addr:full":"Rier Toda, 18 Barcelona Barcelona 08024",
    "addr:housenumber":"18",
    "addr:postcode":"08024",
    "addr:street":"Toda",
    "iso:country":"ES",
    "sg:address":"Rier Toda, 18",
    "sg:city":"Barcelona",
    "sg:orig_category":"Material Y Equipo Para Panader\u00cdas Y Pasteler\u00cdas",
    "sg:phone":"+34 932 10 64 06",
    "sg:postcode":"08024",
    "sg:province":"Barcelona",
    "wof:name":"Vinielles Mata Enrique",
    "wof:placetype":"venue"
},
  "geometry": {"coordinates":[2.1583330631,41.4137535095],"type":"Point"}
}