{
  "type": "Feature",
  "properties": {
    "addr:full":"Calle de Arditurri, 11 Errenteria Guip\u00f9zcoa 20100",
    "addr:housenumber":"11",
    "addr:postcode":"20100",
    "addr:street":"Calle De Arditurri;Guipu\u0300Zcoa",
    "iso:country":"ES",
    "sg:address":"Calle de Arditurri, 11",
    "sg:city":"Errenteria",
    "sg:orig_category":"Molduras, Junquillos, Listones Y Molduras Perforadas",
    "sg:phone":"+34 943 52 25 36",
    "sg:postcode":"20100",
    "sg:province":"Guip\u00f9zcoa",
    "wof:name":"Miguel Ibarguren Jauregui",
    "wof:placetype":"venue"
},
  "geometry": {"coordinates":[-1.90480268,43.3100814819],"type":"Point"}
}