{
  "type": "Feature",
  "properties": {
    "iso:country":"ES",
    "sg:address":"Calle de Alhondiga, 12",
    "sg:city":"Bormujos",
    "sg:orig_category":"Contenedores (mercanc\u00cdas)",
    "sg:phone":"+34 954 78 96 50",
    "sg:postcode":"41930",
    "sg:province":"Sevilla",
    "wof:name":"Escaleras Rios Isidro",
    "wof:placetype":"venue"
},
  "geometry": {"coordinates":[-6.0749497414,37.3642578125],"type":"Point"}
}