{
  "type": "Feature",
  "properties": {
    "addr:full":"Iliada, 8 Villabalter Le\u00f3n 24010",
    "addr:housenumber":"8",
    "addr:postcode":"24010",
    "addr:street":"Iliada;Leo\u0301N",
    "iso:country":"ES",
    "sg:address":"Iliada, 8",
    "sg:city":"Villabalter",
    "sg:orig_category":"Ebanister\u00cda",
    "sg:phone":"+34 987 23 80 28",
    "sg:postcode":"24010",
    "sg:province":"Le\u00f3n",
    "wof:name":"Martinez Diaz Nerea",
    "wof:placetype":"venue"
},
  "geometry": {"coordinates":[-5.5932598114,42.6119194031],"type":"Point"}
}