{
  "type": "Feature",
  "properties": {
    "iso:country":"ES",
    "sg:address":"Calle de Claudio Moyano, 4",
    "sg:city":"Valladolid",
    "sg:orig_category":"Asistencia Y Consejos",
    "sg:phone":"+34 983 39 76 44",
    "sg:postcode":"47001",
    "sg:province":"Valladolid",
    "wof:name":"Miguel Esteban Silvia Alejandra",
    "wof:placetype":"venue"
},
  "geometry": {"coordinates":[-4.7290606499,41.6488990784],"type":"Point"}
}