{
  "type": "Feature",
  "properties": {
    "addr:full":"Plaz Venus, 15 Jerez De La Frontera C\u00e1diz 11407",
    "addr:housenumber":"15",
    "addr:postcode":"11407",
    "addr:street":"Venus",
    "iso:country":"ES",
    "sg:address":"Plaz Venus, 15",
    "sg:city":"Jerez De La Frontera",
    "sg:orig_category":"Carnes De Carnicer\u00cda (al Por Mayor)",
    "sg:phone":"+34 956 30 69 97",
    "sg:postcode":"11407",
    "sg:province":"C\u00e1diz",
    "wof:name":"Sanchez Romero Perdigones S. A.",
    "wof:placetype":"venue"
},
  "geometry": {"coordinates":[-6.0982751846,36.7228431702],"type":"Point"}
}