{
  "type": "Feature",
  "properties": {
    "iso:country":"ES",
    "sg:address":"Calle de Juan Padilla, 5",
    "sg:city":"Aranda Duero",
    "sg:orig_category":"Ingenier\u00cda, Centros De Estudios (diversos)",
    "sg:phone":"+34 947 50 33 66",
    "sg:postcode":"09400",
    "sg:province":"Burgos",
    "wof:name":"Felesan S.l.",
    "wof:placetype":"venue"
},
  "geometry": {"coordinates":[-3.6838889122,41.6741409302],"type":"Point"}
}