{
  "type": "Feature",
  "properties": {
    "addr:full":"Calle de Ana Maria, 29 Madrid Madrid 28039",
    "addr:housenumber":"29",
    "addr:postcode":"madrid;28039",
    "addr:street":"Calle De Ana Maria",
    "iso:country":"ES",
    "sg:address":"Calle de Ana Maria, 29",
    "sg:city":"Madrid",
    "sg:orig_category":"Pintores",
    "sg:phone":"+34 915 71 44 81",
    "sg:postcode":"28039",
    "sg:province":"Madrid",
    "wof:name":"Segovia Esquirol Juan Carlos",
    "wof:placetype":"venue"
},
  "geometry": {"coordinates":[-3.7019228935,40.4640922546],"type":"Point"}
}