{
  "type": "Feature",
  "properties": {
    "iso:country":"ES",
    "sg:address":"Avda Madrid (de), 3",
    "sg:city":"San Fernando De Henares",
    "sg:orig_category":"Asesor\u00cda Fiscal Y Jur\u00cddica",
    "sg:phone":"+34 916 73 72 01",
    "sg:postcode":"28830",
    "sg:province":"Madrid",
    "wof:name":"Ca\u00d1ada Asesores S.coop.mad",
    "wof:placetype":"venue"
},
  "geometry": {"coordinates":[-3.5337018967,40.4277038574],"type":"Point"}
}