{
  "type": "Feature",
  "properties": {
    "addr:full":"Carrer de Socrates, 37 Barcelona Barcelona 08030",
    "addr:housenumber":"37",
    "addr:postcode":"08030",
    "addr:street":"Carrer De Socrates",
    "iso:country":"ES",
    "sg:address":"Carrer de Socrates, 37",
    "sg:city":"Barcelona",
    "sg:orig_category":"Fabricaci\u00d3n De Motores El\u00c9ctricos",
    "sg:phone":"+34 933 11 84 04",
    "sg:postcode":"08030",
    "sg:province":"Barcelona",
    "wof:name":"Electrica Sant Andreu S.a.",
    "wof:placetype":"venue"
},
  "geometry": {"coordinates":[2.187928915,41.4316825867],"type":"Point"}
}