{
  "type": "Feature",
  "properties": {
    "iso:country":"ES",
    "sg:address":"Ctra Nal 340, Km. 0233,0",
    "sg:city":"Beniparrell",
    "sg:orig_category":"Aluminio Y Aleaciones (producci\u00d3n, Transformaci\u00d3n, Negocio)",
    "sg:phone":"+34 961 21 09 96",
    "sg:postcode":"46469",
    "sg:province":"Valencia",
    "wof:name":"Aluminios Torralba S. A.",
    "wof:placetype":"venue"
},
  "geometry": {"coordinates":[-0.4148744047,39.3847122192],"type":"Point"}
}