{
  "type": "Feature",
  "properties": {
    "addr:full":"C/ Sant Marti, 94 Riudarenes Girona 17421",
    "addr:housenumber":"94",
    "addr:postcode":"17421",
    "addr:street":"C / Sant Marti",
    "iso:country":"ES",
    "sg:address":"C/ Sant Marti, 94",
    "sg:city":"Riudarenes",
    "sg:orig_category":"Fabricaci\u00d3n De Telas Y Sedas",
    "sg:phone":"+34 972 85 60 09",
    "sg:postcode":"17421",
    "sg:province":"Girona",
    "sg:website":"www.mompio.com",
    "wof:name":"Textiles M.mompio S.a.",
    "wof:placetype":"venue"
},
  "geometry": {"coordinates":[2.7155199051,41.8246688843],"type":"Point"}
}