{
  "type": "Feature",
  "properties": {
    "addr:full":"Avda Cid, 25 Sangonera La Verde O Ermita Nueva Murcia 30833",
    "addr:housenumber":"25",
    "addr:postcode":"30833",
    "addr:street":"Avda Cid",
    "iso:country":"ES",
    "sg:address":"Avda Cid, 25",
    "sg:city":"Sangonera La Verde O Ermita Nueva",
    "sg:orig_category":"Promotores Constructores",
    "sg:phone":"+34 968 86 82 62",
    "sg:postcode":"30833",
    "sg:province":"Murcia",
    "wof:name":"Herguimur 2002 S.l.",
    "wof:placetype":"venue"
},
  "geometry": {"coordinates":[-1.2034956217,37.9333381653],"type":"Point"}
}