{
  "type": "Feature",
  "properties": {
    "addr:full":"Camino Viejo Simancas, 42 Valladolid Valladolid 47008",
    "addr:housenumber":"42",
    "addr:postcode":"47008",
    "addr:street":"Camino Viejo Simancas",
    "iso:country":"ES",
    "sg:address":"Camino Viejo Simancas, 42",
    "sg:city":"Valladolid",
    "sg:orig_category":"Bricolaje, Herramientas (al Por Menor)",
    "sg:phone":"+34 983 22 18 22",
    "sg:postcode":"47008",
    "sg:province":"Valladolid",
    "wof:name":"Maryan Decoracion S.a.",
    "wof:placetype":"venue"
},
  "geometry": {"coordinates":[-4.7500419617,41.6250495911],"type":"Point"}
}