{
  "type": "Feature",
  "properties": {
    "addr:full":"Carrer de Rector Ubach, 11 Barcelona Barcelona 08021",
    "addr:housenumber":"11",
    "addr:postcode":"08021",
    "addr:street":"Carrer De Rector Ubach",
    "iso:country":"ES",
    "sg:address":"Carrer de Rector Ubach, 11",
    "sg:city":"Barcelona",
    "sg:orig_category":"Art\u00cdculos De Regalo (al Por Menor)",
    "sg:phone":"+34 934 14 57 98",
    "sg:postcode":"08021",
    "sg:province":"Barcelona",
    "wof:name":"Dijous 3 C.b.",
    "wof:placetype":"venue"
},
  "geometry": {"coordinates":[2.1447110176,41.3988342285],"type":"Point"}
}