{
  "type": "Feature",
  "properties": {
    "iso:country":"ES",
    "sg:address":"Avda Trece De Octubre, 17",
    "sg:city":"Alcazares",
    "sg:orig_category":"Aud\u00cdfonos",
    "sg:phone":"+34 968 17 05 20",
    "sg:postcode":"30710",
    "sg:province":"Murcia",
    "wof:name":"Albaladejo Villaescusa Maria Belen",
    "wof:placetype":"venue"
},
  "geometry": {"coordinates":[-0.8513467908,37.7382774353],"type":"Point"}
}