{
  "type": "Feature",
  "properties": {
    "iso:country":"ES",
    "sg:address":"Calle de Merida, 91",
    "sg:city":"Santos De Maimona",
    "sg:orig_category":"Molinos",
    "sg:phone":"+34 924 57 18 22",
    "sg:postcode":"06230",
    "sg:province":"Badajoz",
    "wof:name":"Cardenas Viseda Manuel",
    "wof:placetype":"venue"
},
  "geometry": {"coordinates":[-6.3729300499,38.4487571716],"type":"Point"}
}