{
  "type": "Feature",
  "properties": {
    "addr:full":"Avda Fraga Iribarne, 10 Betanzos La Coru\u00f1a 15300",
    "addr:housenumber":"10",
    "addr:postcode":"15300",
    "addr:street":"Avda Fraga Iribarne;La",
    "iso:country":"ES",
    "sg:address":"Avda Fraga Iribarne, 10",
    "sg:city":"Betanzos",
    "sg:orig_category":"Material Y Herramientas Agr\u00cdcolas",
    "sg:phone":"+34 981 77 14 03",
    "sg:postcode":"15300",
    "sg:province":"La Coru\u00f1a",
    "wof:name":"Comercial Marti Vazquez S. A.",
    "wof:placetype":"venue"
},
  "geometry": {"coordinates":[-8.2119092941,43.279914856],"type":"Point"}
}