{
  "type": "Feature",
  "properties": {
    "addr:full":"Calle de Electricistas, 51 Poligono Industrial Alicante 03130",
    "addr:housenumber":"51",
    "addr:postcode":"03130",
    "addr:street":"Calle De Electricistas;Industrial Alicante",
    "iso:country":"ES",
    "sg:address":"Calle de Electricistas, 51",
    "sg:city":"Poligono Industrial",
    "sg:orig_category":"Cerrajer\u00cda, Ferrallista",
    "sg:phone":"+34 966 69 42 57",
    "sg:postcode":"03130",
    "sg:province":"Alicante",
    "wof:name":"Cerrajeria Hedacar S.l.",
    "wof:placetype":"venue"
},
  "geometry": {"coordinates":[-0.5565090179,38.190448761],"type":"Point"}
}