{
  "type": "Feature",
  "properties": {
    "addr:full":"Calle de Lagos, 70 Navas Del Marques \u00c1vila 05230",
    "addr:housenumber":"70",
    "addr:postcode":"05230",
    "addr:street":"Calle De Lagos;A\u0301Vila",
    "iso:country":"ES",
    "sg:address":"Calle de Lagos, 70",
    "sg:city":"Navas Del Marques",
    "sg:orig_category":"Plomeros",
    "sg:phone":"+34 918 97 06 14",
    "sg:postcode":"05230",
    "sg:province":"\u00c1vila",
    "wof:name":"Rodriguez Herranz Maria Dolores",
    "wof:placetype":"venue"
},
  "geometry": {"coordinates":[-4.337872982,40.6034889221],"type":"Point"}
}