{
  "type": "Feature",
  "properties": {
    "addr:full":"Ctra Tarragona, 58 Lleida Lleida 25005",
    "addr:housenumber":"58",
    "addr:postcode":"25005",
    "addr:street":"Ctra Tarragona",
    "iso:country":"ES",
    "sg:address":"Ctra Tarragona, 58",
    "sg:city":"Lleida",
    "sg:orig_category":"Molduras, Junquillos, Listones Y Molduras Perforadas",
    "sg:phone":"+34 973 23 08 21",
    "sg:postcode":"25005",
    "sg:province":"Lleida",
    "wof:name":"Ripoll Torres Dionisio",
    "wof:placetype":"venue"
},
  "geometry": {"coordinates":[0.6365299821,41.6256103516],"type":"Point"}
}