{
  "type": "Feature",
  "properties": {
    "addr:full":"Calle de Castilla (de), 12 Pinto Madrid 28320",
    "addr:housenumber":"12",
    "addr:postcode":"28320",
    "addr:street":"Calle De Castilla De",
    "iso:country":"ES",
    "sg:address":"Calle de Castilla (de), 12",
    "sg:city":"Pinto",
    "sg:orig_category":"Postigos, Persianas Y Celos\u00cdas",
    "sg:phone":"+34 916 91 36 22",
    "sg:postcode":"28320",
    "sg:province":"Madrid",
    "wof:name":"Villamil Verdasco Mariano",
    "wof:placetype":"venue"
},
  "geometry": {"coordinates":[-3.6971569061,40.2470054626],"type":"Point"}
}