{
  "type": "Feature",
  "properties": {
    "iso:country":"ES",
    "sg:address":"Calle de Europa, 5",
    "sg:city":"Segorbe",
    "sg:orig_category":"Empresas De Carpinter\u00cda De Madera",
    "sg:phone":"+34 964 71 14 19",
    "sg:postcode":"12400",
    "sg:province":"Castell\u00f3n",
    "wof:name":"Moles Morro Eduardo",
    "wof:placetype":"venue"
},
  "geometry": {"coordinates":[-0.4846189916,39.8481941223],"type":"Point"}
}