{
  "type": "Feature",
  "properties": {
    "iso:country":"ES",
    "sg:address":"Carrer de Peru, 156",
    "sg:city":"Barcelona",
    "sg:orig_category":"Servicio De Salud",
    "sg:phone":"+34 933 07 27 08",
    "sg:postcode":"08020",
    "sg:province":"Barcelona",
    "wof:name":"Tubos Y Hierros Industriales S. A.",
    "wof:placetype":"venue"
},
  "geometry": {"coordinates":[2.2002449036,41.4113769531],"type":"Point"}
}