{
  "type": "Feature",
  "properties": {
    "addr:full":"Calle de Sol, 2 Churriana Vega Granada 18194",
    "addr:housenumber":"2",
    "addr:postcode":"18194",
    "addr:street":"Calle De Sol",
    "iso:country":"ES",
    "sg:address":"Calle de Sol, 2",
    "sg:city":"Churriana Vega",
    "sg:orig_category":"Plomeros",
    "sg:phone":"+34 958 57 32 91",
    "sg:postcode":"18194",
    "sg:province":"Granada",
    "wof:name":"Campos Rodriguez Guillermo",
    "wof:placetype":"venue"
},
  "geometry": {"coordinates":[-3.6476740837,37.1475715637],"type":"Point"}
}