{
  "type": "Feature",
  "properties": {
    "addr:full":"Calle de San Roque, 5 Salas Asturias 33860",
    "addr:housenumber":"5",
    "addr:postcode":"33860",
    "addr:street":"Calle De San Roque",
    "iso:country":"ES",
    "sg:address":"Calle de San Roque, 5",
    "sg:city":"Salas",
    "sg:orig_category":"Deportes Y Ocio: Art\u00cdculos Y Ropas (al Por Menor Y Accesorios)",
    "sg:phone":"+34 985 83 20 29",
    "sg:postcode":"33860",
    "sg:province":"Asturias",
    "wof:name":"Villar Cauz Jorge",
    "wof:placetype":"venue"
},
  "geometry": {"coordinates":[-6.2587599754,43.4082145691],"type":"Point"}
}