{
  "type": "Feature",
  "properties": {
    "iso:country":"ES",
    "sg:address":"Ctra. Mercadal-es Migjorn, S/n",
    "sg:city":"Mercadal",
    "sg:orig_category":"Agricultores, Agricultores",
    "sg:phone":"+34 971 35 91 54",
    "sg:postcode":"07740",
    "sg:province":"Islas Baleares",
    "wof:name":"Santa Margarita S.r.m.",
    "wof:placetype":"venue"
},
  "geometry": {"coordinates":[4.0921797752,39.9863700867],"type":"Point"}
}