{
  "type": "Feature",
  "properties": {
    "addr:full":"Ctra Medinya(ravos) (de), 8 Ravos Terri Girona 17845",
    "addr:postcode":"17845",
    "addr:street":"Ctra Medinya Ravos De 8 Ravos",
    "iso:country":"ES",
    "sg:address":"Ctra Medinya(ravos) (de), 8",
    "sg:city":"Ravos Terri",
    "sg:orig_category":"Cr\u00cda De Animales",
    "sg:phone":"+34 972 59 42 43",
    "sg:postcode":"17845",
    "sg:province":"Girona",
    "wof:name":"Jose Y Jose M.oliveras S.cv.",
    "wof:placetype":"venue"
},
  "geometry": {"coordinates":[2.838506937,42.0705718994],"type":"Point"}
}