{
  "type": "Feature",
  "properties": {
    "iso:country":"ES",
    "sg:address":"Calle de Urki, 9",
    "sg:city":"Galdakao",
    "sg:orig_category":"Peluquer\u00cdas, Peluquer\u00cda Mixta",
    "sg:phone":"+34 944 56 50 58",
    "sg:postcode":"48960",
    "sg:province":"Vizcaya",
    "wof:name":"Mariano Asensio Gonzalez",
    "wof:placetype":"venue"
},
  "geometry": {"coordinates":[-2.8435080051,43.2307434082],"type":"Point"}
}