{
  "type": "Feature",
  "properties": {
    "iso:country":"ES",
    "sg:address":"Calle de Concertista Gil Orozco, 32",
    "sg:city":"Requena",
    "sg:orig_category":"Reposter\u00cdas",
    "sg:phone":"+34 962 30 20 16",
    "sg:postcode":"46340",
    "sg:province":"Valencia",
    "wof:name":"Panaderia Hermanos Cardonas S.l.",
    "wof:placetype":"venue"
},
  "geometry": {"coordinates":[-1.1042126417,39.4854736328],"type":"Point"}
}