{
  "type": "Feature",
  "properties": {
    "iso:country":"ES",
    "sg:address":"Calle de Julio Romero, 15",
    "sg:city":"Cabra",
    "sg:orig_category":"Servidores Y Editores De Bases De Datos",
    "sg:phone":"+34 957 52 49 96",
    "sg:postcode":"14940",
    "sg:province":"C\u00f3rdoba",
    "wof:name":"Informes Y Datos Por Internet S.l.",
    "wof:placetype":"venue"
},
  "geometry": {"coordinates":[-4.4438037872,37.4707336426],"type":"Point"}
}