{
  "type": "Feature",
  "properties": {
    "addr:full":"Calle de Fuente El Sol, 18 Valladolid Valladolid 47009",
    "addr:housenumber":"18",
    "addr:postcode":"47009",
    "addr:street":"Calle De Fuente El Sol",
    "iso:country":"ES",
    "sg:address":"Calle de Fuente El Sol, 18",
    "sg:city":"Valladolid",
    "sg:orig_category":"Zapatos (al Por Menor)",
    "sg:phone":"+34 983 37 21 03",
    "sg:postcode":"47009",
    "sg:province":"Valladolid",
    "wof:name":"De La Calle Cabero Eva Maria",
    "wof:placetype":"venue"
},
  "geometry": {"coordinates":[-4.7338218689,41.6628303528],"type":"Point"}
}