{
  "type": "Feature",
  "properties": {
    "addr:full":"Calle de Conde De Altea, 35 Altea Alicante 03590",
    "addr:housenumber":"35",
    "addr:postcode":"03590",
    "addr:street":"Calle De Conde De Altea",
    "iso:country":"ES",
    "sg:address":"Calle de Conde De Altea, 35",
    "sg:city":"Altea",
    "sg:orig_category":"M\u00c9dicos: Pediatr\u00cda. Enfermedades De Los Ni\u00d1os",
    "sg:phone":"+34 965 84 32 86",
    "sg:postcode":"03590",
    "sg:province":"Alicante",
    "wof:name":"Manche\u00f1o Segarra Mariano",
    "wof:placetype":"venue"
},
  "geometry": {"coordinates":[-0.0462425984,38.6017951965],"type":"Point"}
}