{
  "type": "Feature",
  "properties": {
    "iso:country":"ES",
    "sg:address":"Carrer de Blavets De Lluc, 2",
    "sg:city":"Secar De La Real",
    "sg:orig_category":"Empresas De Pintura Y Revestimientos",
    "sg:phone":"+34 971 72 34 38",
    "sg:postcode":"07010",
    "sg:province":"Islas Baleares",
    "wof:name":"Apuntadores 15 S.l.",
    "wof:placetype":"venue"
},
  "geometry": {"coordinates":[2.6334886551,39.6072235107],"type":"Point"}
}