{
  "type": "Feature",
  "properties": {
    "addr:full":"Carretera De Suances, Km. 6316,0 Viveda Cantabria 39314",
    "addr:postcode":"39314",
    "addr:street":"Carretera De Suances Km. 6316,0",
    "iso:country":"ES",
    "sg:address":"Carretera De Suances, Km. 6316,0",
    "sg:city":"Viveda",
    "sg:orig_category":"Distribuci\u00d3n De Petr\u00d3leo Y Derivados",
    "sg:phone":"+34 942 80 59 33",
    "sg:postcode":"39314",
    "sg:province":"Cantabria",
    "wof:name":"Garcia Rodriguez Carmen",
    "wof:placetype":"venue"
},
  "geometry": {"coordinates":[-4.0517559052,43.3763237],"type":"Point"}
}