{
  "type": "Feature",
  "properties": {
    "iso:country":"ES",
    "sg:address":"Carrer de Sant Pere Mitja, 9",
    "sg:city":"Barcelona",
    "sg:orig_category":"Estilistas Y Estudios De Estilo De Corte Y Confecci\u00d3n",
    "sg:phone":"+34 933 10 04 43",
    "sg:postcode":"08003",
    "sg:province":"Barcelona",
    "wof:name":"Confecciones Mode Scp",
    "wof:placetype":"venue"
},
  "geometry": {"coordinates":[2.1764640808,41.3871498108],"type":"Point"}
}