{
  "type": "Feature",
  "properties": {
    "iso:country":"ES",
    "sg:address":"Avda De Europa, S/n",
    "sg:city":"Mondujar",
    "sg:orig_category":"Imprenta",
    "sg:phone":"+34 958 79 53 49",
    "sg:postcode":"18656",
    "sg:province":"Granada",
    "wof:name":"Legraf S.l.",
    "wof:placetype":"venue"
},
  "geometry": {"coordinates":[-3.5461320877,36.951915741],"type":"Point"}
}