{
  "type": "Feature",
  "properties": {
    "addr:full":"Carr Eres De Patxuga, 35 Villarreal Castell\u00f3n 12540",
    "addr:housenumber":"35",
    "addr:postcode":"12540",
    "addr:street":"Carr Eres De Patxuga",
    "iso:country":"ES",
    "sg:address":"Carr Eres De Patxuga, 35",
    "sg:city":"Villarreal",
    "sg:orig_category":"Molduras, Junquillos, Listones Y Molduras Perforadas",
    "sg:phone":"+34 964 52 57 61",
    "sg:postcode":"12540",
    "sg:province":"Castell\u00f3n",
    "wof:name":"Escamilla Gomez Domingo",
    "wof:placetype":"venue"
},
  "geometry": {"coordinates":[-0.0952939987,39.9453048706],"type":"Point"}
}