{
  "type": "Feature",
  "properties": {
    "addr:full":"Calle de Jose Vasconcelos, S/n Madrid Madrid 28046",
    "addr:postcode":"28046",
    "addr:street":"Calle De Jose Vasconcelos S / N Madrid",
    "iso:country":"ES",
    "sg:address":"Calle de Jose Vasconcelos, S/n",
    "sg:city":"Madrid",
    "sg:orig_category":"Alquiler De Veh\u00cdculos: Turismos Y Utilitarios",
    "sg:phone":"+34 913 14 69 31",
    "sg:postcode":"28046",
    "sg:province":"Madrid",
    "sg:website":"www.atesa.es",
    "wof:name":"Atesa",
    "wof:placetype":"venue"
},
  "geometry": {"coordinates":[-3.6863601208,40.4710464478],"type":"Point"}
}