{
  "type": "Feature",
  "properties": {
    "iso:country":"ES",
    "sg:address":"Avda 1 De Mayo, S/n",
    "sg:city":"Albacete",
    "sg:orig_category":"Mec\u00c1nico Del Autom\u00d3vil",
    "sg:phone":"+34 967 22 61 84",
    "sg:postcode":"02006",
    "sg:province":"Albacete",
    "wof:name":"Sabeldai S.l.",
    "wof:placetype":"venue"
},
  "geometry": {"coordinates":[-1.8691840172,38.9862785339],"type":"Point"}
}