{
  "type": "Feature",
  "properties": {
    "addr:full":"Calle de Cristo De La Yedra, 34 Granada Granada 18012",
    "addr:housenumber":"34",
    "addr:postcode":"18012",
    "addr:street":"Calle De Cristo De La Yedra",
    "iso:country":"ES",
    "sg:address":"Calle de Cristo De La Yedra, 34",
    "sg:city":"Granada",
    "sg:orig_category":"Internados & Ense\u00d1anza Privada",
    "sg:phone":"+34 958 20 33 21",
    "sg:postcode":"18012",
    "sg:province":"Granada",
    "wof:name":"Jimenez Calisalvo Jose Eduardo",
    "wof:placetype":"venue"
},
  "geometry": {"coordinates":[-3.6012160778,37.187122345],"type":"Point"}
}