{
  "type": "Feature",
  "properties": {
    "addr:full":"Avda Blasco Iba\u00d1ez, 196 Valencia Valencia 46022",
    "addr:housenumber":"196",
    "addr:postcode":"46022",
    "addr:street":"Avda Blasco Iban\u0303Ez",
    "iso:country":"ES",
    "sg:address":"Avda Blasco Iba\u00d1ez, 196",
    "sg:city":"Valencia",
    "sg:orig_category":"Arquitectos",
    "sg:phone":"+34 963 56 23 44",
    "sg:postcode":"46022",
    "sg:province":"Valencia",
    "wof:name":"Hornero Chornet Victor",
    "wof:placetype":"venue"
},
  "geometry": {"coordinates":[-0.3360440135,39.4700431824],"type":"Point"}
}