{
  "type": "Feature",
  "properties": {
    "iso:country":"ES",
    "sg:address":"Carrer de Luarca, 12",
    "sg:city":"Hospitalet Llobregat",
    "sg:orig_category":"Telas Y Sedas (al Por Menor)",
    "sg:phone":"+34 934 37 84 74",
    "sg:postcode":"08906",
    "sg:province":"Barcelona",
    "wof:name":"Ortega Lara Manuel",
    "wof:placetype":"venue"
},
  "geometry": {"coordinates":[2.1034290791,41.371421814],"type":"Point"}
}