{
  "type": "Feature",
  "properties": {
    "addr:full":"Carrer de Tamarits, 8 Hospitalet De L'infant Tarragona 43890",
    "addr:housenumber":"8",
    "addr:postcode":"43890",
    "addr:street":"Carrer De Tamarits",
    "iso:country":"ES",
    "sg:address":"Carrer de Tamarits, 8",
    "sg:city":"Hospitalet De L'infant",
    "sg:orig_category":"Ingeniero",
    "sg:phone":"+34 977 82 00 55",
    "sg:postcode":"43890",
    "sg:province":"Tarragona",
    "wof:name":"Lopera Rodriguez Francisco",
    "wof:placetype":"venue"
},
  "geometry": {"coordinates":[1.2569299936,41.1178817749],"type":"Point"}
}