{
  "type": "Feature",
  "properties": {
    "addr:full":"Avda Carolina Coronado, 7 Badajoz Badajoz 06007",
    "addr:housenumber":"7",
    "addr:postcode":"06007",
    "addr:street":"Avda Carolina Coronado",
    "iso:country":"ES",
    "sg:address":"Avda Carolina Coronado, 7",
    "sg:city":"Badajoz",
    "sg:orig_category":"Importaci\u00d3n, Exportaci\u00d3n Y Comercios De Productos Textiles",
    "sg:phone":"+34 924 27 51 78",
    "sg:postcode":"06007",
    "sg:province":"Badajoz",
    "wof:name":"Nogales Dominguez C.b.",
    "wof:placetype":"venue"
},
  "geometry": {"coordinates":[-6.9822878838,38.8903388977],"type":"Point"}
}