{
  "type": "Feature",
  "properties": {
    "addr:full":"Calle de Capitan Luna, 25 Caceres C\u00e1ceres 10004",
    "addr:housenumber":"25",
    "addr:postcode":"10004",
    "addr:street":"Calle De Capitan Luna;Ca\u0301Ceres",
    "iso:country":"ES",
    "sg:address":"Calle de Capitan Luna, 25",
    "sg:city":"Caceres",
    "sg:orig_category":"Promotores Constructores",
    "sg:phone":"+34 927 24 49 91",
    "sg:postcode":"10004",
    "sg:province":"C\u00e1ceres",
    "wof:name":"Constructora Virgen De La Monta\u00f1a S.l.",
    "wof:placetype":"venue"
},
  "geometry": {"coordinates":[-6.3713850975,39.4794616699],"type":"Point"}
}