{
  "type": "Feature",
  "properties": {
    "iso:country":"ES",
    "sg:address":"Plaza, S/n",
    "sg:city":"Torrefrades",
    "sg:orig_category":"Venta, Instalaci\u00d3n De Cocinas",
    "sg:phone":"+34 980 61 90 22",
    "sg:postcode":"49216",
    "sg:province":"Zamora",
    "wof:name":"Fernandez Manzano Alonso",
    "wof:placetype":"venue"
},
  "geometry": {"coordinates":[-5.9719839096,41.3188056946],"type":"Point"}
}