{
  "type": "Feature",
  "properties": {
    "addr:full":"Cmno Gojar, 50 Zubia Granada 18140",
    "addr:housenumber":"50",
    "addr:postcode":"18140",
    "addr:street":"Cmno Gojar",
    "iso:country":"ES",
    "sg:address":"Cmno Gojar, 50",
    "sg:city":"Zubia",
    "sg:orig_category":"Panader\u00cdas, Panader\u00cdas",
    "sg:phone":"+34 958 59 17 24",
    "sg:postcode":"18140",
    "sg:province":"Granada",
    "wof:name":"Fernandez-reinoso Dona Gema Maria",
    "wof:placetype":"venue"
},
  "geometry": {"coordinates":[-3.5853440762,37.1218338013],"type":"Point"}
}