{
  "type": "Feature",
  "properties": {
    "addr:full":"Avda Atenas, 75 Matas-pinar-monte Rozas Madrid 28290",
    "addr:housenumber":"75",
    "addr:postcode":"28290",
    "addr:street":"Avda Atenas",
    "iso:country":"ES",
    "sg:address":"Avda Atenas, 75",
    "sg:city":"Matas-pinar-monte Rozas",
    "sg:orig_category":"Fotocopias, Reprograf\u00cda",
    "sg:phone":"+34 916 31 91 49",
    "sg:postcode":"28290",
    "sg:province":"Madrid",
    "sg:website":"www.laguiapymes.com/ayd75",
    "wof:name":"Holgado Perez Juan Felipe",
    "wof:placetype":"venue"
},
  "geometry": {"coordinates":[-3.9113090038,40.5303611755],"type":"Point"}
}