{
  "type": "Feature",
  "properties": {
    "iso:country":"ES",
    "sg:address":"Plaz Moraza, 4",
    "sg:city":"Bilbao",
    "sg:orig_category":"Inform\u00c1tica (estudios, Servicios, Asesor\u00cda, Formaci\u00d3n)",
    "sg:phone":"+34 944 23 64 32",
    "sg:postcode":"48007",
    "sg:province":"Vizcaya",
    "wof:name":"Bilbania, S.a.",
    "wof:placetype":"venue"
},
  "geometry": {"coordinates":[-2.925303936,43.268081665],"type":"Point"}
}