{
  "type": "Feature",
  "properties": {
    "addr:full":"Calle de Cuba, 3 Parla Madrid 28980",
    "addr:housenumber":"3",
    "addr:postcode":"28980",
    "addr:street":"Calle De Cuba",
    "iso:country":"ES",
    "sg:address":"Calle de Cuba, 3",
    "sg:city":"Parla",
    "sg:orig_category":"Farmacias",
    "sg:phone":"+34 916 05 37 68",
    "sg:postcode":"28980",
    "sg:province":"Madrid",
    "wof:name":"Quiralte Carre\u00f1o Luis",
    "wof:placetype":"venue"
},
  "geometry": {"coordinates":[-3.7659285069,40.2297058105],"type":"Point"}
}