{
  "type": "Feature",
  "properties": {
    "iso:country":"ES",
    "sg:address":"Rua Fernando Vi, 48",
    "sg:city":"Ferrol",
    "sg:orig_category":"Asesor\u00cda Sobre Comunicaci\u00d3n De Empresas",
    "sg:phone":"+34 981 35 32 08",
    "sg:postcode":"15403",
    "sg:province":"La Coru\u00f1a",
    "wof:name":"Juanmaher S.l.",
    "wof:placetype":"venue"
},
  "geometry": {"coordinates":[-8.2265014648,43.4819793701],"type":"Point"}
}