{
  "type": "Feature",
  "properties": {
    "addr:full":"Avda Almendros, 34 Benidorm Alicante 03500",
    "addr:housenumber":"34",
    "addr:postcode":"03500",
    "addr:street":"Avda Almendros",
    "iso:country":"ES",
    "sg:address":"Avda Almendros, 34",
    "sg:city":"Benidorm",
    "sg:orig_category":"Peluquer\u00cdas, Peluquer\u00cda Mixta",
    "sg:phone":"+34 965 86 50 72",
    "sg:postcode":"03500",
    "sg:province":"Alicante",
    "wof:name":"Garcia Fernandez Fernando",
    "wof:placetype":"venue"
},
  "geometry": {"coordinates":[-0.1739459932,38.5365180969],"type":"Point"}
}