{
  "type": "Feature",
  "properties": {
    "iso:country":"ES",
    "sg:address":"Calle de Lope De Rueda, 17",
    "sg:city":"Madrid",
    "sg:orig_category":"Centros De Coordinaci\u00d3n",
    "sg:phone":"+34 914 35 49 71",
    "sg:postcode":"28009",
    "sg:province":"Madrid",
    "wof:name":"Calvo Antoraz Pilar",
    "wof:placetype":"venue"
},
  "geometry": {"coordinates":[-3.6772789955,40.4221687317],"type":"Point"}
}