{
  "type": "Feature",
  "properties": {
    "addr:full":"Carrer de Lluis Carulla, 34 Espluga Francoli Tarragona 43440",
    "addr:housenumber":"34",
    "addr:postcode":"43440",
    "addr:street":"Carrer De Lluis Carulla",
    "iso:country":"ES",
    "sg:address":"Carrer de Lluis Carulla, 34",
    "sg:city":"Espluga Francoli",
    "sg:orig_category":"Molduras, Junquillos, Listones Y Molduras Perforadas",
    "sg:phone":"+34 977 87 13 57",
    "sg:postcode":"43440",
    "sg:province":"Tarragona",
    "wof:name":"Roca Armengol Javier",
    "wof:placetype":"venue"
},
  "geometry": {"coordinates":[1.0992749929,41.3950653076],"type":"Point"}
}