{
  "type": "Feature",
  "properties": {
    "iso:country":"ES",
    "sg:address":"Carrer de Alcalde Josep Abril, 9",
    "sg:city":"Mataro",
    "sg:orig_category":"Promotores Constructores",
    "sg:phone":"+34 937 99 98 83",
    "sg:postcode":"08302",
    "sg:province":"Barcelona",
    "wof:name":"Cabot Recto Juana Maria",
    "wof:placetype":"venue"
},
  "geometry": {"coordinates":[2.4401600361,41.5331382751],"type":"Point"}
}