{
  "type": "Feature",
  "properties": {
    "addr:full":"Carrer de Cervera, 79 Terrassa Barcelona 08227",
    "addr:housenumber":"79",
    "addr:postcode":"08227",
    "addr:street":"Carrer De Cervera",
    "iso:country":"ES",
    "sg:address":"Carrer de Cervera, 79",
    "sg:city":"Terrassa",
    "sg:orig_category":"Empresas De Carpinter\u00cda",
    "sg:phone":"+34 937 31 49 05",
    "sg:postcode":"08227",
    "sg:province":"Barcelona",
    "wof:name":"Duran Especialistas En Aluminio S.l.",
    "wof:placetype":"venue"
},
  "geometry": {"coordinates":[2.0353169441,41.5737571716],"type":"Point"}
}