{
  "type": "Feature",
  "properties": {
    "iso:country":"ES",
    "sg:address":"Avda Puerta Del Sur, S/n",
    "sg:city":"Jerez De La Frontera",
    "sg:orig_category":"Loter\u00cda Y T\u00d3mbola",
    "sg:phone":"+34 956 14 52 02",
    "sg:postcode":"11408",
    "sg:province":"C\u00e1diz",
    "wof:name":"Merello Luna Luis Gonzaga",
    "wof:placetype":"venue"
},
  "geometry": {"coordinates":[-6.1407923698,36.6689376831],"type":"Point"}
}