{
  "type": "Feature",
  "properties": {
    "iso:country":"ES",
    "sg:address":"Calle de Gomez Ferrer, 43",
    "sg:city":"Torrent",
    "sg:orig_category":"Fabricaci\u00d3n De Muebles",
    "sg:phone":"+34 961 56 25 62",
    "sg:postcode":"46900",
    "sg:province":"Valencia",
    "wof:name":"Aparisio Navarro Juan Mauro",
    "wof:placetype":"venue"
},
  "geometry": {"coordinates":[-0.443601191,39.370098114],"type":"Point"}
}