{
  "type": "Feature",
  "properties": {
    "addr:full":"San Pedro De Alcantara, S/n Navatrasierra C\u00e1ceres 10331",
    "addr:housenumber":"s / n",
    "addr:postcode":"10331",
    "addr:street":"Alcantara;Ca\u0301Ceres",
    "iso:country":"ES",
    "sg:address":"San Pedro De Alcantara, S/n",
    "sg:city":"Navatrasierra",
    "sg:orig_category":"Asociaciones, Organismos Culturales Y Socioeducativos",
    "sg:phone":"+34 927 55 65 06",
    "sg:postcode":"10331",
    "sg:province":"C\u00e1ceres",
    "wof:name":"Ayuntamiento",
    "wof:placetype":"venue"
},
  "geometry": {"coordinates":[-5.2157888412,39.6454238892],"type":"Point"}
}