{
  "type": "Feature",
  "properties": {
    "addr:full":"Cra. De Sant Hipolit De Voltrega, S/n Gurb Barcelona 08518",
    "addr:housenumber":"s / n",
    "addr:postcode":"08518",
    "iso:country":"ES",
    "sg:address":"Cra. De Sant Hipolit De Voltrega, S/n",
    "sg:city":"Gurb",
    "sg:orig_category":"Cr\u00cda De Cerdos",
    "sg:phone":"+34 938 86 06 70",
    "sg:postcode":"08518",
    "sg:province":"Barcelona",
    "wof:name":"Sat El Vilar De Palau 748",
    "wof:placetype":"venue"
},
  "geometry": {"coordinates":[2.0596010685,41.9344711304],"type":"Point"}
}