{
  "type": "Feature",
  "properties": {
    "addr:full":"Carr Marti Rubi-secretari, 29 Cabaneta Islas Baleares 07141",
    "addr:housenumber":"29",
    "addr:postcode":"07141",
    "addr:street":"Carr Marti Rubi-Secretari;Islas",
    "iso:country":"ES",
    "sg:address":"Carr Marti Rubi-secretari, 29",
    "sg:city":"Cabaneta",
    "sg:orig_category":"Promotores Constructores",
    "sg:phone":"+34 971 79 70 36",
    "sg:postcode":"07141",
    "sg:province":"Islas Baleares",
    "wof:name":"Garcico De Construcciones S.l.",
    "wof:placetype":"venue"
},
  "geometry": {"coordinates":[2.7493097782,39.6213951111],"type":"Point"}
}