{
  "type": "Feature",
  "properties": {
    "addr:full":"Carrer de Maracaibo, 16 Barcelona Barcelona 08030",
    "addr:housenumber":"16",
    "addr:postcode":"08030",
    "addr:street":"Carrer De Maracaibo",
    "iso:country":"ES",
    "sg:address":"Carrer de Maracaibo, 16",
    "sg:city":"Barcelona",
    "sg:orig_category":"Calderer\u00cda",
    "sg:phone":"+34 933 46 25 65",
    "sg:postcode":"08030",
    "sg:province":"Barcelona",
    "wof:name":"Ofitecmo S.l.",
    "wof:placetype":"venue"
},
  "geometry": {"coordinates":[2.2046310902,41.4419975281],"type":"Point"}
}