{
  "type": "Feature",
  "properties": {
    "iso:country":"ES",
    "sg:address":"Calle de Barcas, 7",
    "sg:city":"Ciudad Rodrigo",
    "sg:orig_category":"Asesor\u00cda Sobre Comunicaci\u00d3n De Empresas",
    "sg:phone":"+34 923 46 21 83",
    "sg:postcode":"37500",
    "sg:province":"Salamanca",
    "wof:name":"Agudo Gomez Angel",
    "wof:placetype":"venue"
},
  "geometry": {"coordinates":[-6.5288305283,40.5956001282],"type":"Point"}
}