{
  "type": "Feature",
  "properties": {
    "iso:country":"ES",
    "sg:address":"Carr Comte De Vinatesa, 6",
    "sg:city":"Lleida",
    "sg:orig_category":"Alimentaci\u00d3n General (al Por Menor)",
    "sg:phone":"+34 973 20 26 06",
    "sg:postcode":"25001",
    "sg:province":"Lleida",
    "wof:name":"Buira Comella Vicenta Yolanda",
    "wof:placetype":"venue"
},
  "geometry": {"coordinates":[0.6330040097,41.6112136841],"type":"Point"}
}