{
  "type": "Feature",
  "properties": {
    "addr:full":"Ezkaba, S/n Iru\u00f1a Navarra 31015",
    "addr:postcode":"31015",
    "addr:street":"Ezkaba S / N Irun\u0303A Navarra",
    "iso:country":"ES",
    "sg:address":"Ezkaba, S/n",
    "sg:city":"Iru\u00f1a",
    "sg:orig_category":"Molduras, Junquillos, Listones Y Molduras Perforadas",
    "sg:phone":"+34 948 36 25 93",
    "sg:postcode":"31015",
    "sg:province":"Navarra",
    "wof:name":"Bar Ezkaba S.l.",
    "wof:placetype":"venue"
},
  "geometry": {"coordinates":[-1.6265089512,42.8312034607],"type":"Point"}
}