{
  "type": "Feature",
  "properties": {
    "addr:full":"Calle de Extremadura, 21 Torres Cotillas Murcia 30565",
    "addr:housenumber":"21",
    "addr:postcode":"30565",
    "addr:street":"Calle De Extremadura",
    "iso:country":"ES",
    "sg:address":"Calle de Extremadura, 21",
    "sg:city":"Torres Cotillas",
    "sg:orig_category":"Electricidad, Electr\u00d3nica: Material Y Suministros (al Por Mayor)",
    "sg:phone":"+34 968 62 32 19",
    "sg:postcode":"30565",
    "sg:province":"Murcia",
    "wof:name":"Garcia Martinez Pedro",
    "wof:placetype":"venue"
},
  "geometry": {"coordinates":[-1.2410550117,38.0190391541],"type":"Point"}
}