{
  "type": "Feature",
  "properties": {
    "iso:country":"ES",
    "sg:address":"Carrer de Pere Grau, 18",
    "sg:city":"Masnou",
    "sg:orig_category":"Art\u00cdculos De Decoraci\u00d3n",
    "sg:phone":"+34 935 55 45 31",
    "sg:postcode":"08320",
    "sg:province":"Barcelona",
    "wof:name":"Kalima S.c.p.",
    "wof:placetype":"venue"
},
  "geometry": {"coordinates":[2.3244180679,41.4809761047],"type":"Point"}
}