{
  "type": "Feature",
  "properties": {
    "iso:country":"ES",
    "sg:address":"Av. Zaragoza, 45",
    "sg:city":"Iru\u00f1a",
    "sg:orig_category":"Centros Comerciales Y Grandes Tiendas",
    "sg:phone":"+34 948 15 32 58",
    "sg:postcode":"31005",
    "sg:province":"Navarra",
    "wof:name":"Zhang  Xufeng",
    "wof:placetype":"venue"
},
  "geometry": {"coordinates":[-1.64422822,42.8057098389],"type":"Point"}
}