{
  "type": "Feature",
  "properties": {
    "addr:full":"Calle de Juan Bautista Zabala, 12 Algorta Vizcaya 48991",
    "addr:housenumber":"12",
    "addr:postcode":"48991",
    "addr:street":"Calle De Juan Bautista Zabala",
    "iso:country":"ES",
    "sg:address":"Calle de Juan Bautista Zabala, 12",
    "sg:city":"Algorta",
    "sg:orig_category":"Sociedades, Compa\u00d1\u00cdas Aseguradoras",
    "sg:phone":"+34 944 80 53 55",
    "sg:postcode":"48991",
    "sg:province":"Vizcaya",
    "wof:name":"Abaiasa S.l.",
    "wof:placetype":"venue"
},
  "geometry": {"coordinates":[-3.010218,43.350872],"type":"Point"}
}