{
  "type": "Feature",
  "properties": {
    "addr:full":"Calle de Acosta, 17 Burgo Osma Soria 42300",
    "addr:housenumber":"17",
    "addr:postcode":"42300",
    "addr:street":"Calle De Acosta",
    "iso:country":"ES",
    "sg:address":"Calle de Acosta, 17",
    "sg:city":"Burgo Osma",
    "sg:orig_category":"Medicamentos",
    "sg:phone":"+34 975 34 00 52",
    "sg:postcode":"42300",
    "sg:province":"Soria",
    "wof:name":"Marques De Bonifaz Almudena",
    "wof:placetype":"venue"
},
  "geometry": {"coordinates":[-3.0644555092,41.5892410278],"type":"Point"}
}