{
  "type": "Feature",
  "properties": {
    "iso:country":"ES",
    "sg:address":"Calle de Llobregat, 12",
    "sg:city":"Malaga",
    "sg:orig_category":"Revestimientos Diversos",
    "sg:phone":"+34 952 24 70 30",
    "sg:postcode":"29014",
    "sg:province":"M\u00e1laga",
    "wof:name":"Pavitec Multiservicios S.l.",
    "wof:placetype":"venue"
},
  "geometry": {"coordinates":[-4.4163079262,36.7487754822],"type":"Point"}
}