{
  "type": "Feature",
  "properties": {
    "addr:full":"Calle de Florida, 1 Benidorm Alicante 03500",
    "addr:housenumber":"1",
    "addr:postcode":"03500",
    "addr:street":"Calle De Florida",
    "iso:country":"ES",
    "sg:address":"Calle de Florida, 1",
    "sg:city":"Benidorm",
    "sg:orig_category":"Distribuci\u00d3n De Petr\u00d3leo Y Derivados",
    "sg:phone":"+34 965 85 32 35",
    "sg:postcode":"03500",
    "sg:province":"Alicante",
    "wof:name":"Cerda Garrido Bernardino Jose",
    "wof:placetype":"venue"
},
  "geometry": {"coordinates":[-0.1345749944,38.5421218872],"type":"Point"}
}