{
  "type": "Feature",
  "properties": {
    "iso:country":"ES",
    "sg:address":"Av Reis Catolics, 16",
    "sg:city":"Olot",
    "sg:orig_category":"Cajas De Ahorro",
    "sg:phone":"+34 972 26 17 66",
    "sg:postcode":"17800",
    "sg:province":"Girona",
    "sg:website":"www.lacaixa.es",
    "wof:name":"Caixa D'estalvis I Pensions De Barcelona",
    "wof:placetype":"venue"
},
  "geometry": {"coordinates":[2.4824221134,42.1821594238],"type":"Point"}
}