{
  "type": "Feature",
  "properties": {
    "addr:full":"Calle de Catedratic Juan Ferrando Badia, 18 Foios Valencia 46134",
    "addr:housenumber":"18",
    "addr:postcode":"46134",
    "addr:street":"Calle De Catedratic Juan Ferrando Badia",
    "iso:country":"ES",
    "sg:address":"Calle de Catedratic Juan Ferrando Badia, 18",
    "sg:city":"Foios",
    "sg:orig_category":"Fabricaci\u00d3n Y Venta De Volquetes Y Remolques",
    "sg:phone":"+34 961 49 26 98",
    "sg:postcode":"46134",
    "sg:province":"Valencia",
    "sg:website":"www.remolquestudela.com",
    "wof:name":"Remolques Tudela S.l.",
    "wof:placetype":"venue"
},
  "geometry": {"coordinates":[-0.352321893,39.5345497131],"type":"Point"}
}