{
  "type": "Feature",
  "properties": {
    "addr:full":"Calle de Larga, 12 Olivares Sevilla 41804",
    "addr:housenumber":"12",
    "addr:postcode":"41804",
    "addr:street":"Calle De Larga;Sevilla",
    "iso:country":"ES",
    "sg:address":"Calle de Larga, 12",
    "sg:city":"Olivares",
    "sg:orig_category":"Mercer\u00cda, Lencer\u00cda (al Por Menor)",
    "sg:phone":"+34 954 11 02 79",
    "sg:postcode":"41804",
    "sg:province":"Sevilla",
    "wof:name":"Delgado Zambruno Manuela",
    "wof:placetype":"venue"
},
  "geometry": {"coordinates":[-6.1573419571,37.4182624817],"type":"Point"}
}