{
  "type": "Feature",
  "properties": {
    "iso:country":"ES",
    "sg:address":"Calle de Angel Gonzalez Tejedor, 18",
    "sg:city":"Madrid",
    "sg:orig_category":"Marroquiner\u00cda (confecci\u00d3n)",
    "sg:phone":"+34 917 25 83 79",
    "sg:postcode":"28017",
    "sg:province":"Madrid",
    "wof:name":"Casarrubios Estebanez Antonio",
    "wof:placetype":"venue"
},
  "geometry": {"coordinates":[-3.6565012932,40.430809021],"type":"Point"}
}