{
  "type": "Feature",
  "properties": {
    "iso:country":"ES",
    "sg:address":"Cuesta De La Higera, S/n",
    "sg:city":"Valseca",
    "sg:orig_category":"Agricultores, Agricultores",
    "sg:phone":"+34 921 12 00 29",
    "sg:postcode":"40390",
    "sg:province":"Segovia",
    "wof:name":"S.a.t.el Abanico",
    "wof:placetype":"venue"
},
  "geometry": {"coordinates":[-4.1745610237,40.9992713928],"type":"Point"}
}