{
  "type": "Feature",
  "properties": {
    "iso:country":"ES",
    "sg:address":"Maestro Pareja Lopez, 3",
    "sg:city":"Monda",
    "sg:orig_category":"Panader\u00cdas, Panader\u00cdas",
    "sg:phone":"+34 952 45 72 86",
    "sg:postcode":"29110",
    "sg:province":"M\u00e1laga",
    "wof:name":"Framancha Sociedad Cooperativa Andaluza",
    "wof:placetype":"venue"
},
  "geometry": {"coordinates":[-4.8280038834,36.6316719055],"type":"Point"}
}