{
  "type": "Feature",
  "properties": {
    "addr:full":"Calle de Cantos Negros, 14 Madrid Madrid 28023",
    "addr:housenumber":"14",
    "addr:postcode":"madrid;28023",
    "addr:street":"Calle De Cantos Negros",
    "iso:country":"ES",
    "sg:address":"Calle de Cantos Negros, 14",
    "sg:city":"Madrid",
    "sg:orig_category":"Centros Empresariales",
    "sg:phone":"+34 913 07 78 88",
    "sg:postcode":"28023",
    "sg:province":"Madrid",
    "wof:name":"Macedonia Bussines Art S.l.",
    "wof:placetype":"venue"
},
  "geometry": {"coordinates":[-3.8349757195,40.4762115479],"type":"Point"}
}