{
  "type": "Feature",
  "properties": {
    "addr:full":"Calle de Cuenca, 29 Ibi Alicante 03440",
    "addr:housenumber":"29",
    "addr:postcode":"03440",
    "addr:street":"Calle De Cuenca",
    "iso:country":"ES",
    "sg:address":"Calle de Cuenca, 29",
    "sg:city":"Ibi",
    "sg:orig_category":"Juegos Y Juguetes (al Por Menor)",
    "sg:phone":"+34 966 55 34 27",
    "sg:postcode":"03440",
    "sg:province":"Alicante",
    "wof:name":"Demare Toys S.l.",
    "wof:placetype":"venue"
},
  "geometry": {"coordinates":[-0.5966339111,38.6128196716],"type":"Point"}
}