{
  "type": "Feature",
  "properties": {
    "iso:country":"ES",
    "sg:address":"Carrer de Vinyals, 28",
    "sg:city":"Barcelona",
    "sg:orig_category":"Empresas De Carpinter\u00cda Met\u00c1lica",
    "sg:phone":"+34 934 33 03 90",
    "sg:postcode":"08041",
    "sg:province":"Barcelona",
    "wof:name":"Martinez Martinez Ernesto",
    "wof:placetype":"venue"
},
  "geometry": {"coordinates":[2.175442934,41.4199485779],"type":"Point"}
}