{
  "type": "Feature",
  "properties": {
    "addr:full":"Calle de Juan Ramon Jimenez, 3 Tiemblo \u00c1vila 05270",
    "addr:housenumber":"3",
    "addr:postcode":"05270",
    "addr:street":"Calle De Juan Ramon Jimenez;A\u0301Vila",
    "iso:country":"ES",
    "sg:address":"Calle de Juan Ramon Jimenez, 3",
    "sg:city":"Tiemblo",
    "sg:orig_category":"Bares, Piano",
    "sg:phone":"+34 918 62 53 31",
    "sg:postcode":"05270",
    "sg:province":"\u00c1vila",
    "wof:name":"Garcia Reviejo Maria Del Carmen",
    "wof:placetype":"venue"
},
  "geometry": {"coordinates":[-4.4869670868,40.4095344543],"type":"Point"}
}