{
  "type": "Feature",
  "properties": {
    "iso:country":"ES",
    "sg:address":"Ptge Marti Rossell, 2",
    "sg:city":"Premia Mar",
    "sg:orig_category":"Persianas Interiores, Exteriores",
    "sg:phone":"+34 937 52 32 21",
    "sg:postcode":"08330",
    "sg:province":"Barcelona",
    "wof:name":"Ruiz Diaz Romualdo",
    "wof:placetype":"venue"
},
  "geometry": {"coordinates":[2.3584089279,41.495059967],"type":"Point"}
}