{
  "type": "Feature",
  "properties": {
    "iso:country":"ES",
    "sg:address":"Calle de Calzada, 2",
    "sg:city":"Puertollano",
    "sg:orig_category":"Aguas (distribuci\u00d3n, Servicios)",
    "sg:phone":"+34 926 42 60 59",
    "sg:postcode":"13500",
    "sg:province":"Ciudad Real",
    "wof:name":"Aquagest S.a.",
    "wof:placetype":"venue"
},
  "geometry": {"coordinates":[-4.1097817421,38.687877655],"type":"Point"}
}