{
  "type": "Feature",
  "properties": {
    "addr:full":"Carrer de Palaudaries, S/n Serra Barcelona 08185",
    "addr:housenumber":"s",
    "addr:postcode":"08185",
    "addr:street":"Carrer De Palaudaries;/ N",
    "iso:country":"ES",
    "sg:address":"Carrer de Palaudaries, S/n",
    "sg:city":"Serra",
    "sg:orig_category":"Molduras, Junquillos, Listones Y Molduras Perforadas",
    "sg:phone":"+34 938 43 93 98",
    "sg:postcode":"08185",
    "sg:province":"Barcelona",
    "wof:name":"Esteban Marin Juan",
    "wof:placetype":"venue"
},
  "geometry": {"coordinates":[2.2406799793,41.5862312317],"type":"Point"}
}