{
  "type": "Feature",
  "properties": {
    "iso:country":"ES",
    "sg:address":"Calle de Nogal (del), 18",
    "sg:city":"Nogal",
    "sg:orig_category":"Rectificaci\u00d3n, Mecanizado, Fresado",
    "sg:phone":"+34 916 28 21 59",
    "sg:postcode":"28110",
    "sg:province":"Madrid",
    "wof:name":"Gonzalez Martin Amancio",
    "wof:placetype":"venue"
},
  "geometry": {"coordinates":[-3.4999940395,40.5979003906],"type":"Point"}
}