{
  "type": "Feature",
  "properties": {
    "iso:country":"ES",
    "sg:address":"Trv. Ria De Betanzos, 2",
    "sg:city":"Arteixo",
    "sg:orig_category":"Productos Qu\u00cdmicos (fabricaci\u00d3n, Al Por Mayor)",
    "sg:phone":"+34 981 63 30 44",
    "sg:postcode":"15142",
    "sg:province":"La Coru\u00f1a",
    "wof:name":"Laboratio Punin",
    "wof:placetype":"venue"
},
  "geometry": {"coordinates":[-8.5082969666,43.3048820496],"type":"Point"}
}