{
  "type": "Feature",
  "properties": {
    "addr:full":"Pase Farola, S/n Malaga M\u00e1laga 29016",
    "addr:housenumber":"s / n",
    "addr:postcode":"29016",
    "addr:street":"Ma\u0301Laga",
    "iso:country":"ES",
    "sg:address":"Pase Farola, S/n",
    "sg:city":"Malaga",
    "sg:orig_category":"Organizaciones Internacionales",
    "sg:phone":"+34 952 22 22 22",
    "sg:postcode":"29016",
    "sg:province":"M\u00e1laga",
    "wof:name":"Cruz Roja Espa\u00f1ola Asamblea Provincial",
    "wof:placetype":"venue"
},
  "geometry": {"coordinates":[-4.4147658348,36.713634491],"type":"Point"}
}