{
  "type": "Feature",
  "properties": {
    "iso:country":"ES",
    "sg:address":"Calle de Duque, S/n",
    "sg:city":"Arahal",
    "sg:orig_category":"Bancos",
    "sg:phone":"+34 954 84 05 12",
    "sg:postcode":"41600",
    "sg:province":"Sevilla",
    "wof:name":"Banco De Andalucia",
    "wof:placetype":"venue"
},
  "geometry": {"coordinates":[-5.5445590019,37.2616653442],"type":"Point"}
}