{
  "type": "Feature",
  "properties": {
    "addr:full":"Calle de General Margallo, 8 Madrid Madrid 28020",
    "addr:housenumber":"8",
    "addr:postcode":"madrid;28020",
    "addr:street":"Calle De General Margallo",
    "iso:country":"ES",
    "sg:address":"Calle de General Margallo, 8",
    "sg:city":"Madrid",
    "sg:orig_category":"Mortero Y Material Para Jardines",
    "sg:phone":"+34 915 79 68 73",
    "sg:postcode":"28020",
    "sg:province":"Madrid",
    "wof:name":"Ferreteria Margallo S.l.",
    "wof:placetype":"venue"
},
  "geometry": {"coordinates":[-3.6971521378,40.4610061646],"type":"Point"}
}