{
  "type": "Feature",
  "properties": {
    "iso:country":"ES",
    "sg:address":"Calle de Serna Occina, 9",
    "sg:city":"Santo\u00f1a",
    "sg:orig_category":"Confecci\u00d3n (fabricaci\u00d3n, Al Por Mayor)",
    "sg:phone":"+34 942 67 19 54",
    "sg:postcode":"39740",
    "sg:province":"Cantabria",
    "wof:name":"Martin Lopez S. Cv",
    "wof:placetype":"venue"
},
  "geometry": {"coordinates":[-3.4565899372,43.4425773621],"type":"Point"}
}