{
  "type": "Feature",
  "properties": {
    "iso:country":"ES",
    "sg:address":"Calle de Olof Palme, 36",
    "sg:city":"Palmas De Gran Canaria",
    "sg:orig_category":"Asesor\u00cda De Formaci\u00d3n Y Gesti\u00d3n De Personal",
    "sg:phone":"+34 928 22 79 02",
    "sg:postcode":"35010",
    "sg:province":"Las Palmas",
    "wof:name":"Mabriba S.l.",
    "wof:placetype":"venue"
},
  "geometry": {"coordinates":[-15.4361715317,28.1340179443],"type":"Point"}
}