{
  "type": "Feature",
  "properties": {
    "addr:full":"Carr Metge En Joan Garces, 39 Cullera Valencia 46400",
    "addr:housenumber":"39",
    "addr:postcode":"46400",
    "addr:street":"Carr Metge;Joan Garces",
    "iso:country":"ES",
    "sg:address":"Carr Metge En Joan Garces, 39",
    "sg:city":"Cullera",
    "sg:orig_category":"Reposter\u00cdas",
    "sg:phone":"+34 961 72 10 51",
    "sg:postcode":"46400",
    "sg:province":"Valencia",
    "wof:name":"Signes Ruiz Manuel",
    "wof:placetype":"venue"
},
  "geometry": {"coordinates":[-0.2532660067,39.1617469788],"type":"Point"}
}