{
  "type": "Feature",
  "properties": {
    "addr:full":"Calle de San Marcos, 9 Priego Cordoba C\u00f3rdoba 14800",
    "addr:housenumber":"9",
    "addr:postcode":"14800",
    "addr:street":"Calle De San Marcos;Cordoba Co\u0301Rdoba",
    "iso:country":"ES",
    "sg:address":"Calle de San Marcos, 9",
    "sg:city":"Priego Cordoba",
    "sg:orig_category":"Pescader\u00cdas (al Por Menor)",
    "sg:phone":"+34 957 70 10 94",
    "sg:postcode":"14800",
    "sg:province":"C\u00f3rdoba",
    "wof:name":"Perez Serrano Jose",
    "wof:placetype":"venue"
},
  "geometry": {"coordinates":[-4.1993298531,37.4374885559],"type":"Point"}
}