{
  "type": "Feature",
  "properties": {
    "iso:country":"ES",
    "sg:address":"Av Pirineus, 83",
    "sg:city":"Puigcerda",
    "sg:orig_category":"Cristaler\u00cdas",
    "sg:phone":"+34 972 14 11 54",
    "sg:postcode":"17520",
    "sg:province":"Girona",
    "wof:name":"Cristalls I Aluminis El Llac S. L.",
    "wof:placetype":"venue"
},
  "geometry": {"coordinates":[1.9253900051,42.4297904968],"type":"Point"}
}