{
  "type": "Feature",
  "properties": {
    "iso:country":"ES",
    "sg:address":"Calle de Corredera Del Espolon, 1",
    "sg:city":"Roa",
    "sg:orig_category":"Asilos De Ancianos. Centros Privados",
    "sg:phone":"+34 947 54 11 76",
    "sg:postcode":"09300",
    "sg:province":"Burgos",
    "wof:name":"Asociacion De Jubilados Y Pensionistas Rauda",
    "wof:placetype":"venue"
},
  "geometry": {"coordinates":[-3.926053524,41.696182251],"type":"Point"}
}