{
  "type": "Feature",
  "properties": {
    "iso:country":"ES",
    "sg:address":"Pl Sant Jaume, 13",
    "sg:city":"Manacor",
    "sg:orig_category":"Estancos",
    "sg:phone":"+34 971 55 55 67",
    "sg:postcode":"07500",
    "sg:province":"Islas Baleares",
    "wof:name":"Rossello Homar Sebastian",
    "wof:placetype":"venue"
},
  "geometry": {"coordinates":[3.2061970234,39.5718650818],"type":"Point"}
}