{
  "type": "Feature",
  "properties": {
    "iso:country":"ES",
    "sg:address":"Calle de Alejandro Volta, 2",
    "sg:city":"Zaragoza",
    "sg:orig_category":"Contenedores (mercanc\u00cdas)",
    "sg:phone":"+34 976 47 31 06",
    "sg:postcode":"50014",
    "sg:province":"Zaragoza",
    "wof:name":"Agencia De Transportes Sancho S.l.",
    "wof:placetype":"venue"
},
  "geometry": {"coordinates":[-0.861066103,41.6671905518],"type":"Point"}
}