{
  "type": "Feature",
  "properties": {
    "iso:country":"ES",
    "sg:address":"Calle de Iznatoraf, 12",
    "sg:city":"Jaen",
    "sg:orig_category":"Suministros Para Hoteles",
    "sg:phone":"+34 953 28 01 93",
    "sg:postcode":"23009",
    "sg:province":"Ja\u00e9n",
    "wof:name":"Fermin Martinez Mata",
    "wof:placetype":"venue"
},
  "geometry": {"coordinates":[-3.7809939384,37.8030204773],"type":"Point"}
}