{
  "type": "Feature",
  "properties": {
    "addr:full":"Calle de Mayor, 1 Lerma Burgos 09340",
    "addr:housenumber":"1",
    "addr:postcode":"09340",
    "addr:street":"Calle De Mayor",
    "iso:country":"ES",
    "sg:address":"Calle de Mayor, 1",
    "sg:city":"Lerma",
    "sg:orig_category":"Sales (al Por Mayor)",
    "sg:phone":"+34 947 17 04 08",
    "sg:postcode":"09340",
    "sg:province":"Burgos",
    "wof:name":"Perez Arrroyo Maria Del Carmen",
    "wof:placetype":"venue"
},
  "geometry": {"coordinates":[-3.7600119114,42.0261802673],"type":"Point"}
}