{
  "type": "Feature",
  "properties": {
    "addr:full":"La Paz, 5 Mi\u00f1ambres Valduerna Le\u00f3n 24765",
    "addr:housenumber":"5",
    "addr:postcode":"24765",
    "addr:street":"La Paz;Leo\u0301N",
    "iso:country":"ES",
    "sg:address":"La Paz, 5",
    "sg:city":"Mi\u00f1ambres Valduerna",
    "sg:orig_category":"Delegados, Agentes De Tr\u00c1nsito, Auxiliares De Transporte Internacional",
    "sg:phone":"+34 987 65 56 94",
    "sg:postcode":"24765",
    "sg:province":"Le\u00f3n",
    "wof:name":"Transportes Marques Rubio S.l.",
    "wof:placetype":"venue"
},
  "geometry": {"coordinates":[-5.9938941002,42.3284187317],"type":"Point"}
}