{
  "type": "Feature",
  "properties": {
    "iso:country":"ES",
    "sg:address":"Calle de San Salvador, 15",
    "sg:city":"Huelva",
    "sg:orig_category":"Abogados",
    "sg:phone":"+34 959 28 37 66",
    "sg:postcode":"21003",
    "sg:province":"Huelva",
    "wof:name":"Campos Horta Jose Manuel",
    "wof:placetype":"venue"
},
  "geometry": {"coordinates":[-6.9478621483,37.2566337585],"type":"Point"}
}