{
  "type": "Feature",
  "properties": {
    "addr:full":"Carr Ciutat De Valencia, 13 Cullera Valencia 46400",
    "addr:housenumber":"13",
    "addr:postcode":"46400",
    "addr:street":"Carr Ciutat De Valencia",
    "iso:country":"ES",
    "sg:address":"Carr Ciutat De Valencia, 13",
    "sg:city":"Cullera",
    "sg:orig_category":"Tapicer\u00cdas",
    "sg:phone":"+34 961 72 16 51",
    "sg:postcode":"46400",
    "sg:province":"Valencia",
    "wof:name":"Belmonte Frigola Roberto",
    "wof:placetype":"venue"
},
  "geometry": {"coordinates":[-0.2585690022,39.1682815552],"type":"Point"}
}