{
  "type": "Feature",
  "properties": {
    "iso:country":"ES",
    "sg:address":"Calle de Canalejas, 10",
    "sg:city":"Velez-malaga",
    "sg:orig_category":"\u00d3ptica: Instrumentos (fabricaci\u00d3n)",
    "sg:phone":"+34 952 50 00 49",
    "sg:postcode":"29700",
    "sg:province":"M\u00e1laga",
    "wof:name":"Martin Delgado Francisco",
    "wof:placetype":"venue"
},
  "geometry": {"coordinates":[-4.1056857109,36.7819366455],"type":"Point"}
}