{
  "type": "Feature",
  "properties": {
    "iso:country":"ES",
    "sg:address":"Calle de Simon De Anda, 27",
    "sg:city":"Vitoria-gasteiz",
    "sg:orig_category":"Garajes De Veh\u00cdculos",
    "sg:phone":"+34 945 20 04 82",
    "sg:postcode":"01012",
    "sg:province":"\u00c1lava",
    "wof:name":"G Y P S.c.",
    "wof:placetype":"venue"
},
  "geometry": {"coordinates":[-2.6737370491,42.8553314209],"type":"Point"}
}