{
  "type": "Feature",
  "properties": {
    "addr:full":"Avda Toreros (de Los), 28 Puerto De Santa Maria C\u00e1diz 11500",
    "addr:housenumber":"28",
    "addr:postcode":"11500",
    "addr:street":"Avda Toreros De Los;Ca\u0301Diz",
    "iso:country":"ES",
    "sg:address":"Avda Toreros (de Los), 28",
    "sg:city":"Puerto De Santa Maria",
    "sg:orig_category":"Empresas De Carpinter\u00cda De Madera",
    "sg:phone":"+34 956 87 09 85",
    "sg:postcode":"11500",
    "sg:province":"C\u00e1diz",
    "wof:name":"Marroquin Gomez Francisco",
    "wof:placetype":"venue"
},
  "geometry": {"coordinates":[-6.2376141548,36.5966873169],"type":"Point"}
}