{
  "type": "Feature",
  "properties": {
    "addr:full":"Avgda. Bisbe Campins, 6 Porreres Islas Baleares 07260",
    "addr:housenumber":"6",
    "addr:postcode":"07260",
    "addr:street":"Campins",
    "iso:country":"ES",
    "sg:address":"Avgda. Bisbe Campins, 6",
    "sg:city":"Porreres",
    "sg:orig_category":"Molduras, Junquillos, Listones Y Molduras Perforadas",
    "sg:phone":"+34 971 64 73 16",
    "sg:postcode":"07260",
    "sg:province":"Islas Baleares",
    "wof:name":"Barcelo Janer Joaquim",
    "wof:placetype":"venue"
},
  "geometry": {"coordinates":[3.0230870247,39.516998291],"type":"Point"}
}