{
  "type": "Feature",
  "properties": {
    "iso:country":"ES",
    "sg:address":"Calle de Pegaso, 37",
    "sg:city":"Alacant",
    "sg:orig_category":"Transporte En General",
    "sg:phone":"+34 965 10 41 35",
    "sg:postcode":"03007",
    "sg:province":"Alicante",
    "wof:name":"Ortega Sanchez Alfonso",
    "wof:placetype":"venue"
},
  "geometry": {"coordinates":[-0.515707016,38.3435935974],"type":"Point"}
}