{
  "type": "Feature",
  "properties": {
    "addr:full":"Avda Mahia, 79 Bertamirans La Coru\u00f1a 15220",
    "addr:housenumber":"79",
    "addr:postcode":"15220",
    "addr:street":"Avda Mahia;La Corun\u0303A",
    "iso:country":"ES",
    "sg:address":"Avda Mahia, 79",
    "sg:city":"Bertamirans",
    "sg:orig_category":"Laboratorios Farmac\u00c9uticos",
    "sg:phone":"+34 981 89 03 18",
    "sg:postcode":"15220",
    "sg:province":"La Coru\u00f1a",
    "wof:name":"Laboratorios Ordesa S.l.",
    "wof:placetype":"venue"
},
  "geometry": {"coordinates":[-8.6529855728,42.859249115],"type":"Point"}
}