{
  "type": "Feature",
  "properties": {
    "addr:full":"Carrer de Bailen, 92 Barcelona Barcelona 08009",
    "addr:housenumber":"92",
    "addr:postcode":"08009",
    "addr:street":"Carrer De Bailen",
    "iso:country":"ES",
    "sg:address":"Carrer de Bailen, 92",
    "sg:city":"Barcelona",
    "sg:orig_category":"Perfumer\u00cda (al Por Menor)",
    "sg:phone":"+34 932 65 60 52",
    "sg:postcode":"08009",
    "sg:province":"Barcelona",
    "wof:name":"Centelles Alemany Ana",
    "wof:placetype":"venue"
},
  "geometry": {"coordinates":[2.1713140011,41.3966026306],"type":"Point"}
}