{
  "type": "Feature",
  "properties": {
    "addr:full":"Carr Vilafant, 7 Figueres Girona 17600",
    "addr:housenumber":"7",
    "addr:postcode":"17600",
    "addr:street":"Carr Vilafant",
    "iso:country":"ES",
    "sg:address":"Carr Vilafant, 7",
    "sg:city":"Figueres",
    "sg:orig_category":"Ropa Para Se\u00d1oras (al Por Menor)",
    "sg:phone":"+34 972 67 42 10",
    "sg:postcode":"17600",
    "sg:province":"Girona",
    "wof:name":"Zona Digital S.c",
    "wof:placetype":"venue"
},
  "geometry": {"coordinates":[2.959829092,42.265663147],"type":"Point"}
}