{
  "type": "Feature",
  "properties": {
    "addr:full":"Pl. Constituci\u00f3, 8 Ultramort Girona 17133",
    "addr:housenumber":"8",
    "addr:postcode":"17133",
    "addr:street":"Pl. Constitucio\u0301",
    "iso:country":"ES",
    "sg:address":"Pl. Constituci\u00f3, 8",
    "sg:city":"Ultramort",
    "sg:orig_category":"Cr\u00cda De Cerdos",
    "sg:phone":"+34 972 76 91 58",
    "sg:postcode":"17133",
    "sg:province":"Girona",
    "wof:name":"Granjes Palmiro Sl",
    "wof:placetype":"venue"
},
  "geometry": {"coordinates":[3.0344831944,42.0369033813],"type":"Point"}
}