{
  "type": "Feature",
  "properties": {
    "addr:full":"Santakurtz Kalea, 25 Aretxabaleta Guip\u00f9zcoa 20550",
    "addr:housenumber":"25",
    "addr:postcode":"20550",
    "addr:street":"Santakurtz Kalea;Guipu\u0300Zcoa",
    "iso:country":"ES",
    "sg:address":"Santakurtz Kalea, 25",
    "sg:city":"Aretxabaleta",
    "sg:orig_category":"Suministros Y Materiales Industriales",
    "sg:phone":"+34 943 71 24 11",
    "sg:postcode":"20550",
    "sg:province":"Guip\u00f9zcoa",
    "wof:name":"Sein Batu S.l.",
    "wof:placetype":"venue"
},
  "geometry": {"coordinates":[-2.5027968884,43.0345153809],"type":"Point"}
}