{
  "type": "Feature",
  "properties": {
    "iso:country":"ES",
    "sg:address":"Ctra Mairena-brenes, S/n",
    "sg:city":"Mairena Alcor",
    "sg:orig_category":"Agricultura: Abastecimiento Y Cosechado (negocio)",
    "sg:phone":"+34 955 74 61 11",
    "sg:postcode":"41510",
    "sg:province":"Sevilla",
    "wof:name":"Masverde S.l.",
    "wof:placetype":"venue"
},
  "geometry": {"coordinates":[-5.7439141273,37.377117157],"type":"Point"}
}