{
  "type": "Feature",
  "properties": {
    "iso:country":"ES",
    "sg:address":"Calle de Churruca, 18",
    "sg:city":"Alacant",
    "sg:orig_category":"Gas: Botellas Y Contenedores",
    "sg:phone":"+34 965 12 13 91",
    "sg:postcode":"03003",
    "sg:province":"Alicante",
    "wof:name":"La Degustacion S.c",
    "wof:placetype":"venue"
},
  "geometry": {"coordinates":[-0.4919903874,38.3402175903],"type":"Point"}
}