{
  "type": "Feature",
  "properties": {
    "iso:country":"ES",
    "sg:address":"Calle de Cochera (la), 2",
    "sg:city":"Moriles",
    "sg:orig_category":"Asesor\u00cda Sobre Comunicaci\u00d3n De Empresas",
    "sg:phone":"+34 957 53 60 38",
    "sg:postcode":"14510",
    "sg:province":"C\u00f3rdoba",
    "wof:name":"Alfa 88 Consultores Fiscales S.l.",
    "wof:placetype":"venue"
},
  "geometry": {"coordinates":[-4.6077165604,37.4350395203],"type":"Point"}
}