{
  "type": "Feature",
  "properties": {
    "iso:country":"ES",
    "sg:address":"Trva Arteixo, 246",
    "sg:city":"Arteixo",
    "sg:orig_category":"Pescader\u00cdas (al Por Menor)",
    "sg:phone":"+34 981 60 03 58",
    "sg:postcode":"15142",
    "sg:province":"La Coru\u00f1a",
    "wof:name":"Martinez Campos Josefa",
    "wof:placetype":"venue"
},
  "geometry": {"coordinates":[-8.5051193237,43.3018226624],"type":"Point"}
}