{
  "type": "Feature",
  "properties": {
    "iso:country":"ES",
    "sg:address":"Ctra Madrid-cartagena (antigua N-301), Km. 0302,0",
    "sg:city":"Hellin",
    "sg:orig_category":"Construcciones Met\u00c1licas",
    "sg:phone":"+34 967 30 08 63",
    "sg:postcode":"02400",
    "sg:province":"Albacete",
    "wof:name":"Garcia Beteta Isidro",
    "wof:placetype":"venue"
},
  "geometry": {"coordinates":[-1.6971139908,38.511756897],"type":"Point"}
}