{
  "type": "Feature",
  "properties": {
    "addr:full":"Calle de Calzada, S/n Campanario Badajoz 06460",
    "addr:postcode":"06460",
    "addr:street":"Calle De Calzada S / N Campanario",
    "iso:country":"ES",
    "sg:address":"Calle de Calzada, S/n",
    "sg:city":"Campanario",
    "sg:orig_category":"Cooperativas Agr\u00cdcolas",
    "sg:phone":"+34 924 83 11 95",
    "sg:postcode":"06460",
    "sg:province":"Badajoz",
    "wof:name":"Cooperativa Comarcal De Consumo La Serena",
    "wof:placetype":"venue"
},
  "geometry": {"coordinates":[-5.615901947,38.8675575256],"type":"Point"}
}