{
  "type": "Feature",
  "properties": {
    "addr:full":"Calle de Fuente (la), 9 Leganes Madrid 28911",
    "addr:housenumber":"9",
    "addr:postcode":"28911",
    "addr:street":"Calle De Fuente La",
    "iso:country":"ES",
    "sg:address":"Calle de Fuente (la), 9",
    "sg:city":"Leganes",
    "sg:classifiers":[
        {
            "category":"Autos & Motor Vehicles",
            "subcategory":"Automobile Sales",
            "type":"Retail Goods"
        }
    ],
    "sg:phone":"+34 916 93 00 08",
    "sg:postcode":"28911",
    "sg:province":"Madrid",
    "wof:name":"Autoescuela Leganes S.l.",
    "wof:placetype":"venue"
},
  "geometry": {"coordinates":[-3.7641174793,40.3282966614],"type":"Point"}
}