{
  "type": "Feature",
  "properties": {
    "addr:full":"Pase Alfonso Xiii, 14 Cartagena Murcia 30201",
    "addr:housenumber":"14",
    "addr:postcode":"30201",
    "addr:street":"Alfonso Xiii",
    "iso:country":"ES",
    "sg:address":"Pase Alfonso Xiii, 14",
    "sg:city":"Cartagena",
    "sg:orig_category":"Psic\u00d3logos",
    "sg:phone":"+34 968 12 15 59",
    "sg:postcode":"30201",
    "sg:province":"Murcia",
    "wof:name":"Mi\u00f1arro Garrido Maria Angeles",
    "wof:placetype":"venue"
},
  "geometry": {"coordinates":[-0.9862040281,37.6066856384],"type":"Point"}
}