{
  "type": "Feature",
  "properties": {
    "iso:country":"ES",
    "sg:address":"Calle de Jorge Juan, 2",
    "sg:city":"San Vicente Del Raspeig-sant Vicent Del Raspeig",
    "sg:orig_category":"Cajas De Ahorro",
    "sg:phone":"+34 965 67 31 42",
    "sg:postcode":"03690",
    "sg:province":"Alicante",
    "wof:name":"Caixa D'estalvis I Pensions De Barcelona",
    "wof:placetype":"venue"
},
  "geometry": {"coordinates":[-0.5198569894,38.3942718506],"type":"Point"}
}