{
  "type": "Feature",
  "properties": {
    "iso:country":"ES",
    "sg:address":"Pl. Cristo, S/n",
    "sg:city":"Las Navas Marques",
    "sg:orig_category":"Molduras, Junquillos, Listones Y Molduras Perforadas",
    "sg:phone":"+34 918 97 09 15",
    "sg:postcode":"05230",
    "sg:province":"\u00c1vila",
    "wof:name":"Quiros Martin Felipe",
    "wof:placetype":"venue"
},
  "geometry": {"coordinates":[-4.3334889412,40.6027450562],"type":"Point"}
}