{
  "type": "Feature",
  "properties": {
    "iso:country":"ES",
    "sg:address":"Calle de Modesto Lafuente, 52",
    "sg:city":"Madrid",
    "sg:orig_category":"Institutos De Belleza",
    "sg:phone":"+34 915 53 92 04",
    "sg:postcode":"28003",
    "sg:province":"Madrid",
    "wof:name":"Pe\u00f1a Gijon Maria Teresa",
    "wof:placetype":"venue"
},
  "geometry": {"coordinates":[-3.6958220005,40.4429626465],"type":"Point"}
}