{
  "type": "Feature",
  "properties": {
    "iso:country":"ES",
    "sg:address":"Calle de Rueda Lopez, 19",
    "sg:city":"Almeria",
    "sg:orig_category":"Abogados",
    "sg:phone":"+34 950 23 01 92",
    "sg:postcode":"04004",
    "sg:province":"Almer\u00eda",
    "wof:name":"Peralta Y Peralta Eugenio",
    "wof:placetype":"venue"
},
  "geometry": {"coordinates":[-2.4617919922,36.8378372192],"type":"Point"}
}