{
  "type": "Feature",
  "properties": {
    "iso:country":"ES",
    "sg:address":"Av. Bayona, 26",
    "sg:city":"Iru\u00f1a",
    "sg:orig_category":"Iglesia Cat\u00d3lica",
    "sg:phone":"+34 948 19 82 98",
    "sg:postcode":"31011",
    "sg:province":"Navarra",
    "wof:name":"Prelatura Del Opus Dei Delegacion De Pamplona",
    "wof:placetype":"venue"
},
  "geometry": {"coordinates":[-1.6583570242,42.814868927],"type":"Point"}
}