{
  "type": "Feature",
  "properties": {
    "addr:full":"Avda Tenor Fleta, 1 Zaragoza Zaragoza 50008",
    "addr:housenumber":"1",
    "addr:postcode":"50008",
    "addr:street":"Avda Tenor Fleta",
    "iso:country":"ES",
    "sg:address":"Avda Tenor Fleta, 1",
    "sg:city":"Zaragoza",
    "sg:orig_category":"Tiendas De Grano, Frutas Y Legumbres Secas (al Por Menor)",
    "sg:phone":"+34 976 23 03 66",
    "sg:postcode":"50008",
    "sg:province":"Zaragoza",
    "wof:name":"Ibertele Moviles S.l",
    "wof:placetype":"venue"
},
  "geometry": {"coordinates":[-0.8858190179,41.6422157288],"type":"Point"}
}