{
  "type": "Feature",
  "properties": {
    "addr:full":"Calle de Pagel, 7 Alacant Alicante 03540",
    "addr:housenumber":"7",
    "addr:postcode":"03540",
    "addr:street":"Calle De Pagel",
    "iso:country":"ES",
    "sg:address":"Calle de Pagel, 7",
    "sg:city":"Alacant",
    "sg:orig_category":"Promotores Constructores",
    "sg:phone":"+34 965 16 37 56",
    "sg:postcode":"03540",
    "sg:province":"Alicante",
    "wof:name":"Construcciones Villarejo S.a.",
    "wof:placetype":"venue"
},
  "geometry": {"coordinates":[-0.4190709889,38.3608474731],"type":"Point"}
}