{
  "type": "Feature",
  "properties": {
    "iso:country":"ES",
    "sg:address":"Calle de Mar, 39",
    "sg:city":"Valencia",
    "sg:orig_category":"Asesor\u00cda Fiscal Y Jur\u00cddica",
    "sg:phone":"+34 963 91 77 77",
    "sg:postcode":"46003",
    "sg:province":"Valencia",
    "wof:name":"Moll Mengual Francisco",
    "wof:placetype":"venue"
},
  "geometry": {"coordinates":[-0.3715598881,39.4735107422],"type":"Point"}
}