{
  "type": "Feature",
  "properties": {
    "addr:full":"Calle de Carretas, 20 Villaviciosa Odon Madrid 28670",
    "addr:housenumber":"20",
    "addr:postcode":"28670",
    "addr:street":"Calle De Carretas;Odon",
    "iso:country":"ES",
    "sg:address":"Calle de Carretas, 20",
    "sg:city":"Villaviciosa Odon",
    "sg:orig_category":"Inmobiliaria (agencias)",
    "sg:phone":"+34 916 16 47 06",
    "sg:postcode":"28670",
    "sg:province":"Madrid",
    "wof:name":"Tormo Climent Nieves",
    "wof:placetype":"venue"
},
  "geometry": {"coordinates":[-3.9021925926,40.3580207825],"type":"Point"}
}