{
  "type": "Feature",
  "properties": {
    "addr:full":"Av. Scho Fuerte, 7 Iru\u00f1a Navarra 31007",
    "addr:housenumber":"7",
    "addr:postcode":"31007",
    "addr:street":"Av. Scho Fuerte",
    "iso:country":"ES",
    "sg:address":"Av. Scho Fuerte, 7",
    "sg:city":"Iru\u00f1a",
    "sg:orig_category":"Aparcamientos (infraestructuras, Accesorios)",
    "sg:phone":"+34 948 27 19 05",
    "sg:postcode":"31007",
    "sg:province":"Navarra",
    "wof:name":"Garaje Sancho El Fuerte S. L.",
    "wof:placetype":"venue"
},
  "geometry": {"coordinates":[-1.650567174,42.8092765808],"type":"Point"}
}