{
  "type": "Feature",
  "properties": {
    "addr:full":"Calle de Huesa, S/n Jaen Ja\u00e9n 23009",
    "addr:housenumber":"s / n;jae\u0301n",
    "addr:postcode":"23009",
    "addr:street":"Calle De Huesa",
    "iso:country":"ES",
    "sg:address":"Calle de Huesa, S/n",
    "sg:city":"Jaen",
    "sg:orig_category":"Frutas Y Legumbres Frescas (al Por Mayor)",
    "sg:phone":"+34 953 28 17 47",
    "sg:postcode":"23009",
    "sg:province":"Ja\u00e9n",
    "wof:name":"Frutas Los Amigos De Jaen S.l.",
    "wof:placetype":"venue"
},
  "geometry": {"coordinates":[-3.7822189331,37.8033752441],"type":"Point"}
}