{
  "type": "Feature",
  "properties": {
    "iso:country":"ES",
    "sg:address":"Calle de Valle De La Ballestera, 59",
    "sg:city":"Valencia",
    "sg:orig_category":"M\u00c9dicos: Neurolog\u00cda",
    "sg:phone":"+34 963 49 73 76",
    "sg:postcode":"46015",
    "sg:province":"Valencia",
    "wof:name":"Clinica Tatay S.l.",
    "wof:placetype":"venue"
},
  "geometry": {"coordinates":[-0.4019689858,39.4783821106],"type":"Point"}
}