{
  "type": "Feature",
  "properties": {
    "iso:country":"ES",
    "sg:address":"Carrer de Arago, 114",
    "sg:city":"Barcelona",
    "sg:orig_category":"M\u00c9dicos: Estomatolog\u00cda",
    "sg:phone":"+34 933 23 11 27",
    "sg:postcode":"08015",
    "sg:province":"Barcelona",
    "wof:name":"Font Rosinach Antonio",
    "wof:placetype":"venue"
},
  "geometry": {"coordinates":[2.1545860767,41.3842315674],"type":"Point"}
}