{
  "type": "Feature",
  "properties": {
    "iso:country":"ES",
    "sg:address":"Av Bertomeu, 4",
    "sg:city":"Cerdanyola Valles",
    "sg:orig_category":"Autob\u00das (explotaci\u00d3n Y Servicios De)",
    "sg:phone":"+34 935 80 24 56",
    "sg:postcode":"08193",
    "sg:province":"Barcelona",
    "wof:name":"Marfina S.l.",
    "wof:placetype":"venue"
},
  "geometry": {"coordinates":[2.0911829472,41.50182724],"type":"Point"}
}