{
  "type": "Feature",
  "properties": {
    "iso:country":"ES",
    "sg:address":"Calle de Industria, S/n",
    "sg:city":"Ajalvir",
    "sg:orig_category":"Limpieza Y Vaciado De Fosas",
    "sg:phone":"+34 918 84 45 16",
    "sg:postcode":"28864",
    "sg:province":"Madrid",
    "wof:name":"Conservacion Integral De Poceria S.l.",
    "wof:placetype":"venue"
},
  "geometry": {"coordinates":[-3.4829359055,40.5310707092],"type":"Point"}
}