{
  "type": "Feature",
  "properties": {
    "addr:full":"Calle de Do\u00d1a Urraca, 15 Madrid Madrid 28011",
    "addr:housenumber":"15",
    "addr:postcode":"madrid;28011",
    "addr:street":"Calle De Don\u0303A Urraca",
    "iso:country":"ES",
    "sg:address":"Calle de Do\u00d1a Urraca, 15",
    "sg:city":"Madrid",
    "sg:orig_category":"Pescader\u00cdas (al Por Menor)",
    "sg:phone":"+34 914 64 28 90",
    "sg:postcode":"28011",
    "sg:province":"Madrid",
    "wof:name":"Escribano Jimenez Ricardo",
    "wof:placetype":"venue"
},
  "geometry": {"coordinates":[-3.7255280018,40.412940979],"type":"Point"}
}