{
  "type": "Feature",
  "properties": {
    "addr:full":"Carr Sang De Crist, 2 Villarreal Castell\u00f3n 12540",
    "addr:housenumber":"2",
    "addr:postcode":"12540",
    "addr:street":"Carr Sang De Crist",
    "iso:country":"ES",
    "sg:address":"Carr Sang De Crist, 2",
    "sg:city":"Villarreal",
    "sg:orig_category":"Zapatos (al Por Menor)",
    "sg:phone":"+34 964 52 05 35",
    "sg:postcode":"12540",
    "sg:province":"Castell\u00f3n",
    "wof:name":"Calzados Peques Cdad.",
    "wof:placetype":"venue"
},
  "geometry": {"coordinates":[-0.0952939987,39.9453048706],"type":"Point"}
}