{
  "type": "Feature",
  "properties": {
    "iso:country":"ES",
    "sg:address":"Calle de Navarro Ledesma, 101",
    "sg:city":"Malaga",
    "sg:classifiers":[
        {
            "category":"Autos & Motor Vehicles",
            "subcategory":"Automobile Sales",
            "type":"Retail Goods"
        }
    ],
    "sg:phone":"+34 952 61 44 10",
    "sg:postcode":"29010",
    "sg:province":"M\u00e1laga",
    "wof:name":"Rio Escobar Jose Del",
    "wof:placetype":"venue"
},
  "geometry": {"coordinates":[-4.4651861191,36.7251701355],"type":"Point"}
}