{
  "type": "Feature",
  "properties": {
    "iso:country":"ES",
    "sg:address":"Calle de San Pedro, S/n",
    "sg:city":"Pitillas",
    "sg:orig_category":"Estudios De Cine Y Televisi\u00d3n",
    "sg:phone":"+34 948 74 54 19",
    "sg:postcode":"31392",
    "sg:province":"Navarra",
    "wof:name":"Sargardoy Alli Pedro Jose",
    "wof:placetype":"venue"
},
  "geometry": {"coordinates":[-1.6229939461,42.4214515686],"type":"Point"}
}