{
  "type": "Feature",
  "properties": {
    "iso:country":"ES",
    "sg:address":"Gta Lebon, 1",
    "sg:city":"Cadiz",
    "sg:orig_category":"Encuadernaci\u00d3n E Impresi\u00d3n De Folletos",
    "sg:phone":"+34 956 27 83 48",
    "sg:postcode":"11007",
    "sg:province":"C\u00e1diz",
    "wof:name":"Galvan Encuadernaciones De Arte S.cv.",
    "wof:placetype":"venue"
},
  "geometry": {"coordinates":[-6.2902388573,36.5298614502],"type":"Point"}
}