{
  "type": "Feature",
  "properties": {
    "iso:country":"ES",
    "sg:address":"Carr Major, 148",
    "sg:city":"Lliria",
    "sg:orig_category":"Prot\u00c9sicos Dentales",
    "sg:phone":"+34 962 79 12 72",
    "sg:postcode":"46160",
    "sg:province":"Valencia",
    "wof:name":"Acevedo Martinez Pedro",
    "wof:placetype":"venue"
},
  "geometry": {"coordinates":[-0.5999965072,39.6273841858],"type":"Point"}
}