{
  "type": "Feature",
  "properties": {
    "addr:full":"Calle de Soraluze, 1 Donostia-san Sebastian Guip\u00f9zcoa 20003",
    "addr:housenumber":"1",
    "addr:postcode":"20003",
    "addr:street":"Calle De Soraluze",
    "iso:country":"ES",
    "sg:address":"Calle de Soraluze, 1",
    "sg:city":"Donostia-san Sebastian",
    "sg:orig_category":"Papel (al Por Mayor)",
    "sg:phone":"+34 943 42 84 43",
    "sg:postcode":"20003",
    "sg:province":"Guip\u00f9zcoa",
    "wof:name":"Repap S.l.",
    "wof:placetype":"venue"
},
  "geometry": {"coordinates":[-1.9838190079,43.3249473572],"type":"Point"}
}