{
  "type": "Feature",
  "properties": {
    "addr:full":"Calle de Hungria, 18 Ejido Almer\u00eda 04700",
    "addr:housenumber":"18 ejido",
    "addr:postcode":"04700",
    "addr:street":"Calle De Hungria;Almeri\u0301A",
    "iso:country":"ES",
    "sg:address":"Calle de Hungria, 18",
    "sg:city":"Ejido",
    "sg:orig_category":"Mec\u00c1nico Del Autom\u00d3vil",
    "sg:phone":"+34 950 48 48 90",
    "sg:postcode":"04700",
    "sg:province":"Almer\u00eda",
    "wof:name":"Jimenez Jimenez Francisco",
    "wof:placetype":"venue"
},
  "geometry": {"coordinates":[-2.7997350693,36.7743492126],"type":"Point"}
}