{
  "type": "Feature",
  "properties": {
    "addr:full":"Avda Espa\u00d1a, 5 Ceuta Ceuta 51001",
    "addr:housenumber":"5",
    "addr:postcode":"51001",
    "addr:street":"Avda Espan\u0303A",
    "iso:country":"ES",
    "sg:address":"Avda Espa\u00d1a, 5",
    "sg:city":"Ceuta",
    "sg:classifiers":[
        {
            "category":"Autos & Motor Vehicles",
            "subcategory":"Automobile Sales",
            "type":"Retail Goods"
        }
    ],
    "sg:phone":"+34 956 52 23 55",
    "sg:postcode":"51001",
    "sg:province":"Ceuta",
    "wof:name":"Academia De Conductores Y Servicios De Ceuta",
    "wof:placetype":"venue"
},
  "geometry": {"coordinates":[-5.316561,35.891712],"type":"Point"}
}