{
  "type": "Feature",
  "properties": {
    "addr:full":"Calle de Triana, 50 Madrid Madrid 28016",
    "addr:housenumber":"50",
    "addr:postcode":"madrid;28016",
    "addr:street":"Calle De Triana",
    "iso:country":"ES",
    "sg:address":"Calle de Triana, 50",
    "sg:city":"Madrid",
    "sg:orig_category":"Artes Gr\u00c1ficas, Artes Pl\u00c1sticas: Material Y Suministros (al Por Menor)",
    "sg:phone":"+34 913 50 73 96",
    "sg:postcode":"28016",
    "sg:province":"Madrid",
    "wof:name":"Sqanchez Teran Fernando",
    "wof:placetype":"venue"
},
  "geometry": {"coordinates":[-3.6762213707,40.4650802612],"type":"Point"}
}