{
  "type": "Feature",
  "properties": {
    "addr:full":"Ctra. Madrid(poligono), Km. 0320,0 Arcahueja Le\u00f3n 24227",
    "addr:postcode":"24227",
    "addr:street":"Ctra. Madrid Poligono Km. 0320,0;Leo\u0301N",
    "iso:country":"ES",
    "sg:address":"Ctra. Madrid(poligono), Km. 0320,0",
    "sg:city":"Arcahueja",
    "sg:orig_category":"Bazares, Art\u00cdculos De Limpieza Y De Cocina (al Por Menor)",
    "sg:phone":"+34 987 26 90 93",
    "sg:postcode":"24227",
    "sg:province":"Le\u00f3n",
    "wof:name":"Mipabel S.ll",
    "wof:placetype":"venue"
},
  "geometry": {"coordinates":[-5.4982323647,42.5662117004],"type":"Point"}
}