{
  "type": "Feature",
  "properties": {
    "addr:full":"Av Baix Penedes, 6 Vendrell Tarragona 43700",
    "addr:housenumber":"6",
    "addr:postcode":"43700",
    "addr:street":"Av Baix Penedes",
    "iso:country":"ES",
    "sg:address":"Av Baix Penedes, 6",
    "sg:city":"Vendrell",
    "sg:orig_category":"Promotores Constructores",
    "sg:phone":"+34 977 66 86 88",
    "sg:postcode":"43700",
    "sg:province":"Tarragona",
    "wof:name":"Construcciones Abema Bp S.l.",
    "wof:placetype":"venue"
},
  "geometry": {"coordinates":[1.5291149616,41.2162055969],"type":"Point"}
}