{
  "type": "Feature",
  "properties": {
    "iso:country":"ES",
    "sg:address":"Luga Centro Comercial Las Arenas, S/n",
    "sg:city":"Palmas De Gran Canaria",
    "sg:orig_category":"Florister\u00cdas",
    "sg:phone":"+34 928 22 70 80",
    "sg:postcode":"35010",
    "sg:province":"Las Palmas",
    "wof:name":"Martin Fernandez Julio",
    "wof:placetype":"venue"
},
  "geometry": {"coordinates":[-15.4397087097,28.1302242279],"type":"Point"}
}