{
  "type": "Feature",
  "properties": {
    "iso:country":"ES",
    "sg:address":"Carrer de Era D'esquerra, 2",
    "sg:city":"Manresa",
    "sg:orig_category":"Carnicer\u00cdas, Carnicer\u00cdas",
    "sg:phone":"+34 938 72 49 80",
    "sg:postcode":"08242",
    "sg:province":"Barcelona",
    "wof:name":"Xarcuteries Soler S.l.",
    "wof:placetype":"venue"
},
  "geometry": {"coordinates":[1.8172068596,41.7413520813],"type":"Point"}
}