{
  "type": "Feature",
  "properties": {
    "addr:full":"Casa Monegal, S/n Olius Lleida 25286",
    "addr:housenumber":"s / n",
    "addr:postcode":"25286",
    "iso:country":"ES",
    "sg:address":"Casa Monegal, S/n",
    "sg:city":"Olius",
    "sg:orig_category":"Cr\u00cda De Animales",
    "sg:phone":"+34 973 29 91 24",
    "sg:postcode":"25286",
    "sg:province":"Lleida",
    "wof:name":"Sat Num 1041 Cat Taure",
    "wof:placetype":"venue"
},
  "geometry": {"coordinates":[1.4181050062,41.9509010315],"type":"Point"}
}