{
  "type": "Feature",
  "properties": {
    "addr:full":"Calle de Cimadevila, 14 Boiro La Coru\u00f1a 15930",
    "addr:housenumber":"14",
    "addr:postcode":"15930",
    "addr:street":"Calle De Cimadevila;La Corun\u0303A",
    "iso:country":"ES",
    "sg:address":"Calle de Cimadevila, 14",
    "sg:city":"Boiro",
    "sg:orig_category":"Molduras, Junquillos, Listones Y Molduras Perforadas",
    "sg:phone":"+34 981 84 69 80",
    "sg:postcode":"15930",
    "sg:province":"La Coru\u00f1a",
    "sg:website":"www.cepsa.es",
    "wof:name":"Garlou S.l.",
    "wof:placetype":"venue"
},
  "geometry": {"coordinates":[-8.8747062683,42.6569137573],"type":"Point"}
}