{
  "type": "Feature",
  "properties": {
    "addr:full":"Avda Fernando El Catolico, 20 Ejea De Los Caballeros Zaragoza 50600",
    "addr:housenumber":"20",
    "addr:postcode":"50600",
    "addr:street":"Avda Fernando El Catolico",
    "iso:country":"ES",
    "sg:address":"Avda Fernando El Catolico, 20",
    "sg:city":"Ejea De Los Caballeros",
    "sg:orig_category":"Productos Alimentarios",
    "sg:phone":"+34 976 67 70 99",
    "sg:postcode":"50600",
    "sg:province":"Zaragoza",
    "wof:name":"Producciones Pecuarias S. L.",
    "wof:placetype":"venue"
},
  "geometry": {"coordinates":[-1.1352119446,42.1239318848],"type":"Point"}
}