{
  "type": "Feature",
  "properties": {
    "addr:full":"Calle de Cantos, 2 Santa Croya De Tera Zamora 49626",
    "addr:housenumber":"2",
    "addr:postcode":"49626",
    "addr:street":"Calle De Cantos",
    "iso:country":"ES",
    "sg:address":"Calle de Cantos, 2",
    "sg:city":"Santa Croya De Tera",
    "sg:orig_category":"Carnicer\u00cdas, Carnicer\u00cdas",
    "sg:phone":"+34 980 64 52 35",
    "sg:postcode":"49626",
    "sg:province":"Zamora",
    "wof:name":"Santiago Alvarez Francisca",
    "wof:placetype":"venue"
},
  "geometry": {"coordinates":[-5.9765219688,41.9841575623],"type":"Point"}
}