{
  "type": "Feature",
  "properties": {
    "addr:full":"Calle de Julio Antonio, 20 Valencia Valencia 46007",
    "addr:housenumber":"20",
    "addr:postcode":"46007",
    "addr:street":"Calle De Julio Antonio",
    "iso:country":"ES",
    "sg:address":"Calle de Julio Antonio, 20",
    "sg:city":"Valencia",
    "sg:orig_category":"Fabricaci\u00d3n De Peines Y De Accesorios De Peluquer\u00cda",
    "sg:phone":"+34 963 41 69 71",
    "sg:postcode":"46007",
    "sg:province":"Valencia",
    "wof:name":"Cerdan Carpio Jose",
    "wof:placetype":"venue"
},
  "geometry": {"coordinates":[-0.3795340061,39.465549469],"type":"Point"}
}