{
  "type": "Feature",
  "properties": {
    "addr:full":"Calle de Tubal, 39 Tafalla Navarra 31300",
    "addr:housenumber":"39",
    "addr:postcode":"31300",
    "addr:street":"Calle De Tubal",
    "iso:country":"ES",
    "sg:address":"Calle de Tubal, 39",
    "sg:city":"Tafalla",
    "sg:orig_category":"Promotores Constructores",
    "sg:phone":"+34 948 70 30 39",
    "sg:postcode":"31300",
    "sg:province":"Navarra",
    "wof:name":"Conteyo S.a.",
    "wof:placetype":"venue"
},
  "geometry": {"coordinates":[-1.678820014,42.5267715454],"type":"Point"}
}