{
  "type": "Feature",
  "properties": {
    "iso:country":"ES",
    "sg:address":"Mercat Sant Josep, 15",
    "sg:city":"Barcelona",
    "sg:orig_category":"Molduras, Junquillos, Listones Y Molduras Perforadas",
    "sg:phone":"+34 933 17 25 40",
    "sg:postcode":"08002",
    "sg:province":"Barcelona",
    "wof:name":"Oliva Roig Jaime",
    "wof:placetype":"venue"
},
  "geometry": {"coordinates":[2.1723499298,41.3820495605],"type":"Point"}
}