{
  "type": "Feature",
  "properties": {
    "iso:country":"ES",
    "sg:address":"Calle de Clodoaldo Naranjo, 4",
    "sg:city":"Trujillo",
    "sg:orig_category":"Florister\u00cdas",
    "sg:phone":"+34 927 32 07 98",
    "sg:postcode":"10200",
    "sg:province":"C\u00e1ceres",
    "wof:name":"Acero Garcia Concepcion",
    "wof:placetype":"venue"
},
  "geometry": {"coordinates":[-5.9621105194,39.561050415],"type":"Point"}
}