{
  "type": "Feature",
  "properties": {
    "iso:country":"ES",
    "sg:address":"Plaz Padre Lasa, 5",
    "sg:city":"Tudela",
    "sg:orig_category":"Ropa Para Se\u00d1oras (al Por Menor)",
    "sg:phone":"+34 948 82 79 13",
    "sg:postcode":"31500",
    "sg:province":"Navarra",
    "wof:name":"Lavilla Moneo Miguel Angel",
    "wof:placetype":"venue"
},
  "geometry": {"coordinates":[-1.6025749445,42.054901123],"type":"Point"}
}