{
  "type": "Feature",
  "properties": {
    "iso:country":"ES",
    "sg:address":"Calle de Santa Rosa, 10",
    "sg:city":"Valencia",
    "sg:orig_category":"Organismos De Reclutamiento",
    "sg:phone":"+34 963 37 56 87",
    "sg:postcode":"46021",
    "sg:province":"Valencia",
    "wof:name":"Gesfinocio S.l.",
    "wof:placetype":"venue"
},
  "geometry": {"coordinates":[-0.3580560088,39.4683151245],"type":"Point"}
}