{
  "type": "Feature",
  "properties": {
    "addr:full":"Avda Ortigueira, 50 Pontes Garcia Rodriguez La Coru\u00f1a 15320",
    "addr:housenumber":"50",
    "addr:postcode":"15320",
    "addr:street":"Avda Ortigueira;Corun\u0303A",
    "iso:country":"ES",
    "sg:address":"Avda Ortigueira, 50",
    "sg:city":"Pontes Garcia Rodriguez",
    "sg:orig_category":"T\u00c9cnicos Veterinarios",
    "sg:phone":"+34 981 44 07 13",
    "sg:postcode":"15320",
    "sg:province":"La Coru\u00f1a",
    "wof:name":"Bote Rodriguez Maria Belen",
    "wof:placetype":"venue"
},
  "geometry": {"coordinates":[-7.8522920609,43.4518661499],"type":"Point"}
}