{
  "type": "Feature",
  "properties": {
    "iso:country":"ES",
    "sg:address":"Ctra Barcelona, 577",
    "sg:city":"Sabadell",
    "sg:orig_category":"Bisuter\u00cda, Joyer\u00cda, Relojer\u00cda (al Por Menor)",
    "sg:phone":"+34 937 11 67 02",
    "sg:postcode":"08204",
    "sg:province":"Barcelona",
    "wof:name":"Bajona Cortes Pedro",
    "wof:placetype":"venue"
},
  "geometry": {"coordinates":[2.1166620255,41.529499054],"type":"Point"}
}