{
  "type": "Feature",
  "properties": {
    "addr:full":"Carr Cargol De Mar, 10 Blanes Girona 17300",
    "addr:housenumber":"10",
    "addr:postcode":"17300",
    "addr:street":"Carr Cargol De Mar",
    "iso:country":"ES",
    "sg:address":"Carr Cargol De Mar, 10",
    "sg:city":"Blanes",
    "sg:orig_category":"Inmobiliaria (agencias)",
    "sg:phone":"+34 972 33 62 16",
    "sg:postcode":"17300",
    "sg:province":"Girona",
    "wof:name":"Grup Tarradellas S.l.",
    "wof:placetype":"venue"
},
  "geometry": {"coordinates":[2.7868340015,41.6682777405],"type":"Point"}
}