{
  "type": "Feature",
  "properties": {
    "addr:full":"Carr Mestre Martinez, (del), 1 Carlet Valencia 46240",
    "addr:housenumber":"1",
    "addr:postcode":"46240",
    "addr:street":"Carr Mestre Martinez Del",
    "iso:country":"ES",
    "sg:address":"Carr Mestre Martinez, (del), 1",
    "sg:city":"Carlet",
    "sg:orig_category":"Iglesia Cat\u00d3lica",
    "sg:phone":"+34 962 53 11 29",
    "sg:postcode":"46240",
    "sg:province":"Valencia",
    "wof:name":"Parroquia De La Asuncion",
    "wof:placetype":"venue"
},
  "geometry": {"coordinates":[-0.5196300149,39.2262916565],"type":"Point"}
}