{
  "type": "Feature",
  "properties": {
    "addr:full":"Calle de Leon Xiii, 23 Sevilla Sevilla 41009",
    "addr:housenumber":"23",
    "addr:postcode":"41009",
    "addr:street":"Calle De Leon Xiii",
    "iso:country":"ES",
    "sg:address":"Calle de Leon Xiii, 23",
    "sg:city":"Sevilla",
    "sg:orig_category":"Ropa Para Se\u00d1oras (al Por Menor)",
    "sg:phone":"+34 954 37 09 52",
    "sg:postcode":"41009",
    "sg:province":"Sevilla",
    "wof:name":"Fernandez Dominguez Joaquina",
    "wof:placetype":"venue"
},
  "geometry": {"coordinates":[-5.9836192131,37.4029159546],"type":"Point"}
}