{
  "type": "Feature",
  "properties": {
    "addr:full":"Pla\u00c7 Major, 7 Sant Joan Les Fonts Girona 17857",
    "addr:postcode":"17857",
    "iso:country":"ES",
    "sg:address":"Pla\u00c7 Major, 7",
    "sg:city":"Sant Joan Les Fonts",
    "sg:orig_category":"Frutas, Legumbres Frescas Y Tempranas (al Por Menor)",
    "sg:phone":"+34 972 29 05 05",
    "sg:postcode":"17857",
    "sg:province":"Girona",
    "wof:name":"Delgado Lopez Jose",
    "wof:placetype":"venue"
},
  "geometry": {"coordinates":[2.5107150078,42.2121162415],"type":"Point"}
}