{
  "type": "Feature",
  "properties": {
    "addr:full":"Calle de Rosario, 35 Albacete Albacete 02001",
    "addr:housenumber":"35",
    "addr:postcode":"02001",
    "addr:street":"Calle De Rosario",
    "iso:country":"ES",
    "sg:address":"Calle de Rosario, 35",
    "sg:city":"Albacete",
    "sg:orig_category":"Electrodom\u00c9sticos (al Por Menor)",
    "sg:phone":"+34 967 24 81 36",
    "sg:postcode":"02001",
    "sg:province":"Albacete",
    "wof:name":"Rosario 35 S.l.",
    "wof:placetype":"venue"
},
  "geometry": {"coordinates":[-1.8566880226,38.9933547974],"type":"Point"}
}