{
  "type": "Feature",
  "properties": {
    "addr:full":"Rua Terra, 1 Ferrol La Coru\u00f1a 15402",
    "addr:housenumber":"1",
    "addr:postcode":"15402",
    "addr:street":"Rua Terra;La Corun\u0303A",
    "iso:country":"ES",
    "sg:address":"Rua Terra, 1",
    "sg:city":"Ferrol",
    "sg:orig_category":"Farmacias",
    "sg:phone":"+34 981 36 96 85",
    "sg:postcode":"15402",
    "sg:province":"La Coru\u00f1a",
    "wof:name":"Rodriguez-tenreiro Romero-mella Carlos",
    "wof:placetype":"venue"
},
  "geometry": {"coordinates":[-8.2327327728,43.4833259583],"type":"Point"}
}