{
  "type": "Feature",
  "properties": {
    "iso:country":"ES",
    "sg:address":"Cerdedelo, S/n",
    "sg:city":"Cerdedelo",
    "sg:orig_category":"Agencias Y Agentes Comerciales, Representantes",
    "sg:phone":"+34 986 33 33 81",
    "sg:postcode":"36417",
    "sg:province":"Pontevedra",
    "wof:name":"Gra\u00f1a Barciela Arsenio",
    "wof:placetype":"venue"
},
  "geometry": {"coordinates":[-8.6178617477,42.2033996582],"type":"Point"}
}