{
  "type": "Feature",
  "properties": {
    "addr:full":"Calle de Santuario, 3 Valladolid Valladolid 47002",
    "addr:housenumber":"3",
    "addr:postcode":"47002",
    "addr:street":"Calle De Santuario",
    "iso:country":"ES",
    "sg:address":"Calle de Santuario, 3",
    "sg:city":"Valladolid",
    "sg:orig_category":"C\u00c1maras De Comercio E Industria, Oficios, Agricultura",
    "sg:phone":"+34 983 30 29 49",
    "sg:postcode":"47002",
    "sg:province":"Valladolid",
    "wof:name":"Camara Agraria Local De Valladolid",
    "wof:placetype":"venue"
},
  "geometry": {"coordinates":[-4.7233772278,41.6501922607],"type":"Point"}
}