{
  "type": "Feature",
  "properties": {
    "addr:full":"Calle de Benito Perez Galdos, 21 Ca\u00e7ete De Las Torres C\u00f3rdoba 14660",
    "addr:housenumber":"21",
    "addr:postcode":"14660",
    "addr:street":"Calle De Benito Perez Galdos;Co\u0301Rdoba",
    "iso:country":"ES",
    "sg:address":"Calle de Benito Perez Galdos, 21",
    "sg:city":"Ca\u00e7ete De Las Torres",
    "sg:orig_category":"Plomeros",
    "sg:phone":"+34 957 18 36 18",
    "sg:postcode":"14660",
    "sg:province":"C\u00f3rdoba",
    "wof:name":"Sanchez Garrido Manuel",
    "wof:placetype":"venue"
},
  "geometry": {"coordinates":[-4.3197612762,37.8698272705],"type":"Point"}
}