{
  "type": "Feature",
  "properties": {
    "iso:country":"ES",
    "sg:address":"Calle de Jose Miguel Barandiaran, 37",
    "sg:city":"Santurtzi",
    "sg:orig_category":"Florister\u00cdas",
    "sg:phone":"+34 944 62 42 34",
    "sg:postcode":"48980",
    "sg:province":"Vizcaya",
    "wof:name":"Floristeria Maria Luz",
    "wof:placetype":"venue"
},
  "geometry": {"coordinates":[-3.0366339684,43.3228378296],"type":"Point"}
}