{
  "type": "Feature",
  "properties": {
    "addr:full":"Barr Calle de (la), S/n Parbayon Cantabria 39612",
    "addr:postcode":"39612",
    "addr:street":"Calle De La S / N",
    "iso:country":"ES",
    "sg:address":"Barr Calle de (la), S/n",
    "sg:city":"Parbayon",
    "sg:orig_category":"Fotograf\u00cda Art\u00cdstica Y Retratos",
    "sg:phone":"+34 942 58 66 12",
    "sg:postcode":"39612",
    "sg:province":"Cantabria",
    "wof:name":"Gandara Due\u00f1as Agustin",
    "wof:placetype":"venue"
},
  "geometry": {"coordinates":[-3.8936638832,43.3754005432],"type":"Point"}
}