{
  "type": "Feature",
  "properties": {
    "addr:full":"Ctra. Estella, 12 Acedo Navarra 31282",
    "addr:housenumber":"12",
    "addr:postcode":"31282",
    "addr:street":"Ctra. Estella",
    "iso:country":"ES",
    "sg:address":"Ctra. Estella, 12",
    "sg:city":"Acedo",
    "sg:orig_category":"Ebanistas Y Talladores De Muebles Y Objetos De Arte",
    "sg:phone":"+34 948 52 10 08",
    "sg:postcode":"31282",
    "sg:province":"Navarra",
    "wof:name":"Manufacturas Alde S. L.",
    "wof:placetype":"venue"
},
  "geometry": {"coordinates":[-2.2494468689,42.6669921875],"type":"Point"}
}