{
  "type": "Feature",
  "properties": {
    "addr:full":"Calle de San Isidro, 14 Azagra Navarra 31560",
    "addr:housenumber":"14",
    "addr:postcode":"31560",
    "addr:street":"Calle De San Isidro",
    "iso:country":"ES",
    "sg:address":"Calle de San Isidro, 14",
    "sg:city":"Azagra",
    "sg:orig_category":"M\u00c1quinas Para Recortar Y Pegar",
    "sg:phone":"+34 948 69 22 15",
    "sg:postcode":"31560",
    "sg:province":"Navarra",
    "wof:name":"Gracia Gimenez David",
    "wof:placetype":"venue"
},
  "geometry": {"coordinates":[-1.8944790363,42.3061485291],"type":"Point"}
}