{
  "type": "Feature",
  "properties": {
    "addr:full":"Ctra Blanca (de), 14 Abaran Murcia 30550",
    "addr:housenumber":"14",
    "addr:postcode":"30550",
    "addr:street":"Ctra Blanca De",
    "iso:country":"ES",
    "sg:address":"Ctra Blanca (de), 14",
    "sg:city":"Abaran",
    "sg:orig_category":"Comercio, Reparaci\u00d3n De Motocicletas, Bicicletas Y Piezas Sueltas",
    "sg:phone":"+34 968 77 09 48",
    "sg:postcode":"30550",
    "sg:province":"Murcia",
    "wof:name":"Carrasco Laveda Joaquin",
    "wof:placetype":"venue"
},
  "geometry": {"coordinates":[-1.3941969872,38.206401825],"type":"Point"}
}