{
  "type": "Feature",
  "properties": {
    "addr:full":"Calle de Gran Canaria, 64 Pto. Rosario Las Palmas 35600",
    "addr:housenumber":"64",
    "addr:postcode":"35600",
    "addr:street":"Calle De Gran Canaria;Pto. Rosario Las",
    "iso:country":"ES",
    "sg:address":"Calle de Gran Canaria, 64",
    "sg:city":"Pto. Rosario",
    "sg:orig_category":"Promotores Constructores",
    "sg:phone":"+34 928 85 01 12",
    "sg:postcode":"35600",
    "sg:province":"Las Palmas",
    "wof:name":"Sulemipa S.l.",
    "wof:placetype":"venue"
},
  "geometry": {"coordinates":[-13.8716440201,28.507938385],"type":"Point"}
}