{
  "type": "Feature",
  "properties": {
    "iso:country":"ES",
    "sg:address":"Carretera De Granada-motril, Km. 0151,0",
    "sg:city":"Padul",
    "sg:orig_category":"Comercio De Muebles De Estilo Y Contempor\u00c1neos",
    "sg:phone":"+34 958 77 35 71",
    "sg:postcode":"18640",
    "sg:province":"Granada",
    "wof:name":"Casa De Campo C.b.",
    "wof:placetype":"venue"
},
  "geometry": {"coordinates":[-3.6279389858,37.0232009888],"type":"Point"}
}