{
  "type": "Feature",
  "properties": {
    "iso:country":"ES",
    "sg:address":"Calle de Castillo De San Felipe, S/n",
    "sg:city":"Nijar",
    "sg:orig_category":"Caf\u00c9s, Bares, Cervecer\u00cdas",
    "sg:phone":"+34 950 36 04 11",
    "sg:postcode":"04100",
    "sg:province":"Almer\u00eda",
    "wof:name":"Segura Garcia Juan Antonio",
    "wof:placetype":"venue"
},
  "geometry": {"coordinates":[-2.2052540779,36.961139679],"type":"Point"}
}