{
  "type": "Feature",
  "properties": {
    "addr:full":"Carrer de Valles, 96 S. Cugat Valles Barcelona 08172",
    "addr:housenumber":"96",
    "addr:postcode":"08172",
    "addr:street":"Carrer De Valles;S. Cugat Valles Barcelona",
    "iso:country":"ES",
    "sg:address":"Carrer de Valles, 96",
    "sg:city":"S. Cugat Valles",
    "sg:orig_category":"Centros Empresariales",
    "sg:phone":"+34 935 90 14 70",
    "sg:postcode":"08172",
    "sg:province":"Barcelona",
    "wof:name":"Lead Molecular Design S.l.",
    "wof:placetype":"venue"
},
  "geometry": {"coordinates":[2.0909740925,41.4729728699],"type":"Point"}
}