{
  "type": "Feature",
  "properties": {
    "addr:full":"Calle de San Ciriaco, 7 Madrid Madrid 28032",
    "addr:housenumber":"7",
    "addr:postcode":"28032",
    "addr:street":"Calle De San;Madrid",
    "iso:country":"ES",
    "sg:address":"Calle de San Ciriaco, 7",
    "sg:city":"Madrid",
    "sg:orig_category":"Inmobiliaria (agencias)",
    "sg:phone":"+34 913 71 92 35",
    "sg:postcode":"28032",
    "sg:province":"Madrid",
    "wof:name":"Agencia De Gestion Inmobiliaria Toribio S.l.",
    "wof:placetype":"venue"
},
  "geometry": {"coordinates":[-3.6043469906,40.4057350159],"type":"Point"}
}