{
  "type": "Feature",
  "properties": {
    "iso:country":"ES",
    "sg:address":"Calle de Carabelos, 21",
    "sg:city":"Madrid",
    "sg:orig_category":"Cl\u00cdnicas Dentales",
    "sg:phone":"+34 915 00 04 22",
    "sg:postcode":"28041",
    "sg:province":"Madrid",
    "wof:name":"Noemident S L",
    "wof:placetype":"venue"
},
  "geometry": {"coordinates":[-3.6922829151,40.3747024536],"type":"Point"}
}