{
  "type": "Feature",
  "properties": {
    "iso:country":"ES",
    "sg:address":"Avda Real De Madrid, 129",
    "sg:city":"Valencia",
    "sg:orig_category":"Mec\u00c1nico Del Autom\u00d3vil",
    "sg:phone":"+34 963 18 21 91",
    "sg:postcode":"46017",
    "sg:province":"Valencia",
    "wof:name":"Devesa Motors S.l.",
    "wof:placetype":"venue"
},
  "geometry": {"coordinates":[-0.3933570087,39.4283027649],"type":"Point"}
}