{
  "type": "Feature",
  "properties": {
    "iso:country":"ES",
    "sg:address":"Calle de Hermanos Moroy, 22",
    "sg:city":"Logro\u00f1o",
    "sg:orig_category":"Promotores Constructores",
    "sg:phone":"+34 941 27 50 57",
    "sg:postcode":"26001",
    "sg:province":"La Rioja",
    "sg:website":"www.ortiz-construcciones.com",
    "wof:name":"Ortiz Construcciones Y Proyectos S.a.",
    "wof:placetype":"venue"
},
  "geometry": {"coordinates":[-2.4470911026,42.4660186768],"type":"Point"}
}