{
  "type": "Feature",
  "properties": {
    "iso:country":"ES",
    "sg:address":"Carrer de Barcelona, 291",
    "sg:city":"Sant Vicen\u00c7 Dels Horts",
    "sg:orig_category":"Molduras, Junquillos, Listones Y Molduras Perforadas",
    "sg:phone":"+34 936 56 31 51",
    "sg:postcode":"08620",
    "sg:province":"Barcelona",
    "wof:name":"Fernandez Bermudez Alberto",
    "wof:placetype":"venue"
},
  "geometry": {"coordinates":[2.0068171024,41.399974823],"type":"Point"}
}