{
  "type": "Feature",
  "properties": {
    "addr:full":"Calle de San Pancracio, 29 Valencia Valencia 46009",
    "addr:housenumber":"29",
    "addr:postcode":"46009",
    "addr:street":"Calle De San Pancracio",
    "iso:country":"ES",
    "sg:address":"Calle de San Pancracio, 29",
    "sg:city":"Valencia",
    "sg:orig_category":"Abogados",
    "sg:phone":"+34 963 49 44 01",
    "sg:postcode":"46009",
    "sg:province":"Valencia",
    "wof:name":"Hernandiz Abogados S.c.",
    "wof:placetype":"venue"
},
  "geometry": {"coordinates":[-0.3843420148,39.4883613586],"type":"Point"}
}