{
  "type": "Feature",
  "properties": {
    "addr:full":"Pla\u00c7 Ajuntament, 1 Serinya Girona 17852",
    "addr:housenumber":"1",
    "addr:postcode":"17852",
    "addr:street":"Serinya Girona",
    "iso:country":"ES",
    "sg:address":"Pla\u00c7 Ajuntament, 1",
    "sg:city":"Serinya",
    "sg:orig_category":"Guarder\u00cdas",
    "sg:phone":"+34 972 59 33 49",
    "sg:postcode":"17852",
    "sg:province":"Girona",
    "wof:name":"Daus De Colors",
    "wof:placetype":"venue"
},
  "geometry": {"coordinates":[2.744343996,42.169128418],"type":"Point"}
}