{
  "type": "Feature",
  "properties": {
    "addr:full":"Avda Libertad De La, 25 Donostia-san Sebastian Guip\u00f9zcoa 20004",
    "addr:housenumber":"25",
    "addr:postcode":"20004",
    "addr:street":"Avda Libertad De La",
    "iso:country":"ES",
    "sg:address":"Avda Libertad De La, 25",
    "sg:city":"Donostia-san Sebastian",
    "sg:orig_category":"Agencias De Trabajo Temporal",
    "sg:phone":"+34 943 43 34 93",
    "sg:postcode":"20004",
    "sg:province":"Guip\u00f9zcoa",
    "sg:website":"www.creyfs.es",
    "wof:name":"Creyf's Trabajo Temporal Ett S.a.",
    "wof:placetype":"venue"
},
  "geometry": {"coordinates":[-1.9827469587,43.3191413879],"type":"Point"}
}