{
  "type": "Feature",
  "properties": {
    "iso:country":"ES",
    "sg:address":"Calle de Fama, 1",
    "sg:city":"Coru\u00d1a",
    "sg:orig_category":"Asesor\u00cda Sobre Comunicaci\u00d3n De Empresas",
    "sg:phone":"+34 981 20 02 03",
    "sg:postcode":"15001",
    "sg:province":"La Coru\u00f1a",
    "sg:website":"www.kpmg.es",
    "wof:name":"Kpmg Recursos S.a.",
    "wof:placetype":"venue"
},
  "geometry": {"coordinates":[-8.3969831467,43.3706436157],"type":"Point"}
}