{
  "type": "Feature",
  "properties": {
    "addr:full":"Calle de Francisco De Diego, 2 Madrid Madrid 28040",
    "addr:housenumber":"2",
    "addr:postcode":"28040",
    "addr:street":"Calle De Francisco De Diego",
    "iso:country":"ES",
    "sg:address":"Calle de Francisco De Diego, 2",
    "sg:city":"Madrid",
    "sg:orig_category":"Pintura Y Barniz (al Por Menor)",
    "sg:phone":"+34 914 50 45 51",
    "sg:postcode":"28040",
    "sg:province":"Madrid",
    "wof:name":"Borreguero Martinez Felix",
    "wof:placetype":"venue"
},
  "geometry": {"coordinates":[-3.714525938,40.4551239014],"type":"Point"}
}