{
  "type": "Feature",
  "properties": {
    "addr:full":"Ctra Torrejon (de), Km. 0003,2 Ajalvir Madrid 28864",
    "addr:postcode":"28864",
    "addr:street":"Ctra Torrejon De Km. 0003,2",
    "iso:country":"ES",
    "sg:address":"Ctra Torrejon (de), Km. 0003,2",
    "sg:city":"Ajalvir",
    "sg:orig_category":"Venta, Localizaci\u00d3n, Reparaci\u00d3n De Material E Instrumental M\u00c9dico",
    "sg:phone":"+34 918 84 31 75",
    "sg:postcode":"28864",
    "sg:province":"Madrid",
    "wof:name":"Americo Govantes Burguete S.l.",
    "wof:placetype":"venue"
},
  "geometry": {"coordinates":[-3.4808473587,40.5143165588],"type":"Point"}
}