{
  "type": "Feature",
  "properties": {
    "iso:country":"ES",
    "sg:address":"Psaj Union Jaquesa, 3",
    "sg:city":"Jaca",
    "sg:orig_category":"Deportes Y Ocio: Art\u00cdculos Y Ropas (al Por Menor Y Accesorios)",
    "sg:phone":"+34 974 36 24 83",
    "sg:postcode":"22700",
    "sg:province":"Huesca",
    "wof:name":"Sport System Chuss S.l.",
    "wof:placetype":"venue"
},
  "geometry": {"coordinates":[-0.5506039858,42.5692863464],"type":"Point"}
}