{
  "type": "Feature",
  "properties": {
    "iso:country":"ES",
    "sg:address":"Calle de Rafalafena, 21",
    "sg:city":"Castellon",
    "sg:orig_category":"Doctores En Medicina",
    "sg:phone":"+34 964 26 11 91",
    "sg:postcode":"12003",
    "sg:province":"Castell\u00f3n",
    "wof:name":"Baldo Vives Francisco",
    "wof:placetype":"venue"
},
  "geometry": {"coordinates":[-0.0319700018,39.9885482788],"type":"Point"}
}