{
  "type": "Feature",
  "properties": {
    "addr:full":"Calle de Porches De Galicia, 5 Huesca Huesca 22002",
    "addr:housenumber":"5",
    "addr:postcode":"22002",
    "addr:street":"Calle De Porches De Galicia",
    "iso:country":"ES",
    "sg:address":"Calle de Porches De Galicia, 5",
    "sg:city":"Huesca",
    "sg:orig_category":"Librer\u00cdas",
    "sg:phone":"+34 974 22 64 79",
    "sg:postcode":"22002",
    "sg:province":"Huesca",
    "wof:name":"Papeleria Santiago S.l.",
    "wof:placetype":"venue"
},
  "geometry": {"coordinates":[-0.4081360102,42.1365432739],"type":"Point"}
}