{
  "type": "Feature",
  "properties": {
    "addr:full":"Calle de Molina De Segura, S/n Paz Murcia 30007",
    "addr:housenumber":"s / n",
    "addr:postcode":"30007",
    "addr:street":"Calle De Molina;Segura",
    "iso:country":"ES",
    "sg:address":"Calle de Molina De Segura, S/n",
    "sg:city":"Paz",
    "sg:orig_category":"Cajas De Ahorro",
    "sg:phone":"+34 968 24 82 52",
    "sg:postcode":"30007",
    "sg:province":"Murcia",
    "wof:name":"Caja De Ahorros De Murcia",
    "wof:placetype":"venue"
},
  "geometry": {"coordinates":[-1.1142389774,37.9970092773],"type":"Point"}
}