{
  "type": "Feature",
  "properties": {
    "addr:full":"Calle de Dimas Madariaga, 34 Salamanca Salamanca 37005",
    "addr:housenumber":"34",
    "addr:postcode":"37005",
    "addr:street":"Calle De Dimas Madariaga",
    "iso:country":"ES",
    "sg:address":"Calle de Dimas Madariaga, 34",
    "sg:city":"Salamanca",
    "sg:orig_category":"Ropa Para Ni\u00d1os (al Por Menor)",
    "sg:phone":"+34 923 25 55 54",
    "sg:postcode":"37005",
    "sg:province":"Salamanca",
    "wof:name":"Gomez Gomez Maria Elena",
    "wof:placetype":"venue"
},
  "geometry": {"coordinates":[-5.6596956253,40.9711303711],"type":"Point"}
}