{
  "type": "Feature",
  "properties": {
    "iso:country":"ES",
    "sg:address":"Calle de Disvaron, 65",
    "sg:city":"Villanueva De Los Infantes",
    "sg:orig_category":"Reposter\u00cdas",
    "sg:phone":"+34 926 36 02 72",
    "sg:postcode":"13320",
    "sg:province":"Ciudad Real",
    "wof:name":"Pacheco Riaza Jose Luis",
    "wof:placetype":"venue"
},
  "geometry": {"coordinates":[-3.0104293823,38.7394332886],"type":"Point"}
}