{
  "type": "Feature",
  "properties": {
    "iso:country":"ES",
    "sg:address":"Carr Bega, 3",
    "sg:city":"Cullera",
    "sg:orig_category":"Supermercados Y Hipermercados",
    "sg:phone":"+34 961 72 21 92",
    "sg:postcode":"46400",
    "sg:province":"Valencia",
    "sg:website":"www.mercadona.es",
    "wof:name":"Mercadona S.a.",
    "wof:placetype":"venue"
},
  "geometry": {"coordinates":[-0.2562240064,39.1653251648],"type":"Point"}
}