{
  "type": "Feature",
  "properties": {
    "addr:full":"Calle de Leon, 32 Madrid Madrid 28014",
    "addr:housenumber":"32",
    "addr:postcode":"madrid;28014",
    "addr:street":"Calle De Leon",
    "iso:country":"ES",
    "sg:address":"Calle de Leon, 32",
    "sg:city":"Madrid",
    "sg:orig_category":"Librer\u00cdas",
    "sg:phone":"+34 914 29 99 98",
    "sg:postcode":"28014",
    "sg:province":"Madrid",
    "sg:website":"www.librosgulliver.com",
    "wof:name":"Dominguez Cascajero Manuel Francisco",
    "wof:placetype":"venue"
},
  "geometry": {"coordinates":[-3.6995229721,40.4127235413],"type":"Point"}
}