{
  "type": "Feature",
  "properties": {
    "iso:country":"ES",
    "sg:address":"Calle de Nuestra Se\u00d1ora De Bego\u00d1a, 5",
    "sg:city":"Santurtzi",
    "sg:orig_category":"Peluqueros: De Se\u00d1oras",
    "sg:phone":"+34 944 61 99 01",
    "sg:postcode":"48980",
    "sg:province":"Vizcaya",
    "wof:name":"Martin San Miguel Maria Del Mar",
    "wof:placetype":"venue"
},
  "geometry": {"coordinates":[-3.0356490612,43.3274726868],"type":"Point"}
}