{
  "type": "Feature",
  "properties": {
    "addr:full":"C/ Marques D'asprella, 69 Elche Alicante 03201",
    "addr:housenumber":"69",
    "addr:postcode":"03201",
    "addr:street":"C / Marques D'Asprella",
    "iso:country":"ES",
    "sg:address":"C/ Marques D'asprella, 69",
    "sg:city":"Elche",
    "sg:orig_category":"Estudios, Instalaci\u00d3n De Climatizaci\u00d3n",
    "sg:phone":"+34 965 44 75 62",
    "sg:postcode":"03201",
    "sg:province":"Alicante",
    "wof:name":"Climatizacion Y Fontaneria Ilicitana S.l",
    "wof:placetype":"venue"
},
  "geometry": {"coordinates":[-0.7026060224,38.2696647644],"type":"Point"}
}