{
  "type": "Feature",
  "properties": {
    "addr:full":"Calle de San Vicente, 18 San Vicente De Barakaldo Vizcaya 48902",
    "addr:housenumber":"18",
    "addr:postcode":"48902",
    "addr:street":"Calle De San Vicente",
    "iso:country":"ES",
    "sg:address":"Calle de San Vicente, 18",
    "sg:city":"San Vicente De Barakaldo",
    "sg:orig_category":"Molduras, Junquillos, Listones Y Molduras Perforadas",
    "sg:phone":"+34 944 37 12 47",
    "sg:postcode":"48902",
    "sg:province":"Vizcaya",
    "wof:name":"Gijo Jimenez Dolores",
    "wof:placetype":"venue"
},
  "geometry": {"coordinates":[-2.9928040504,43.2953338623],"type":"Point"}
}