{
  "type": "Feature",
  "properties": {
    "iso:country":"ES",
    "sg:address":"Calle de San Juan Bosco, 99",
    "sg:city":"Almeria",
    "sg:orig_category":"Administradores De Bienes Y Delegados De Comunidades De Propietarios",
    "sg:phone":"+34 950 23 44 55",
    "sg:postcode":"04005",
    "sg:province":"Almer\u00eda",
    "wof:name":"Oyonarte Inmobiliaria S.l.",
    "wof:placetype":"venue"
},
  "geometry": {"coordinates":[-2.4532799721,36.842918396],"type":"Point"}
}