{
  "type": "Feature",
  "properties": {
    "iso:country":"ES",
    "sg:address":"Calle de Archer Marino, S/n",
    "sg:city":"Bilbao",
    "sg:orig_category":"Carnes De Carnicer\u00cda (al Por Mayor)",
    "sg:phone":"+34 944 85 08 35",
    "sg:postcode":"48013",
    "sg:province":"Vizcaya",
    "wof:name":"Industrial Tripera Del Norte S.a.",
    "wof:placetype":"venue"
},
  "geometry": {"coordinates":[-2.9700567722,43.2499694824],"type":"Point"}
}