{
  "type": "Feature",
  "properties": {
    "addr:full":"Alvarez, Km. 0350,0 Cieza Murcia 30530",
    "addr:postcode":"30530",
    "addr:street":"Alvarez Km. 0350,0",
    "iso:country":"ES",
    "sg:address":"Alvarez, Km. 0350,0",
    "sg:city":"Cieza",
    "sg:orig_category":"Mec\u00c1nico Del Autom\u00d3vil",
    "sg:phone":"+34 968 76 41 76",
    "sg:postcode":"30530",
    "sg:province":"Murcia",
    "wof:name":"Moreno Vazquez Juan Carlos",
    "wof:placetype":"venue"
},
  "geometry": {"coordinates":[-1.4241739511,38.2379302979],"type":"Point"}
}