{
  "type": "Feature",
  "properties": {
    "addr:full":"Arkotz Kalea (pol Lanbarren), 7 Oiartzun Guip\u00f9zcoa 20180",
    "addr:housenumber":"7",
    "addr:postcode":"20180",
    "addr:street":"Arkotz Kalea;Lanbarren;Guipu\u0300Zcoa",
    "iso:country":"ES",
    "sg:address":"Arkotz Kalea (pol Lanbarren), 7",
    "sg:city":"Oiartzun",
    "sg:orig_category":"Delineantes",
    "sg:phone":"+34 943 26 00 43",
    "sg:postcode":"20180",
    "sg:province":"Guip\u00f9zcoa",
    "wof:name":"Dimp S.a.",
    "wof:placetype":"venue"
},
  "geometry": {"coordinates":[-1.865694046,43.3177757263],"type":"Point"}
}