{
  "type": "Feature",
  "properties": {
    "iso:country":"ES",
    "sg:address":"Carrer de Viladecans, 22",
    "sg:city":"S. Boi Llobregat",
    "sg:orig_category":"Molduras, Junquillos, Listones Y Molduras Perforadas",
    "sg:phone":"+34 936 52 01 13",
    "sg:postcode":"08830",
    "sg:province":"Barcelona",
    "wof:name":"Diaz San Miguel Gregorio",
    "wof:placetype":"venue"
},
  "geometry": {"coordinates":[2.0408670902,41.3324623108],"type":"Point"}
}