{
  "type": "Feature",
  "properties": {
    "addr:full":"Calle de Valle (el), 20 San Pedro Arroyo \u00c1vila 05350",
    "addr:housenumber":"20",
    "addr:postcode":"05350",
    "addr:street":"Calle De Valle El",
    "iso:country":"ES",
    "sg:address":"Calle de Valle (el), 20",
    "sg:city":"San Pedro Arroyo",
    "sg:orig_category":"Carnicer\u00cdas, Carnicer\u00cdas",
    "sg:phone":"+34 920 24 00 39",
    "sg:postcode":"05350",
    "sg:province":"\u00c1vila",
    "wof:name":"Velayos Martin Fidel",
    "wof:placetype":"venue"
},
  "geometry": {"coordinates":[-4.8760547638,40.8029022217],"type":"Point"}
}