{
  "type": "Feature",
  "properties": {
    "iso:country":"ES",
    "sg:address":"Ctra Frailes, S/n",
    "sg:city":"Santa Ana",
    "sg:orig_category":"Fabricaci\u00d3n De Telas Y Sedas",
    "sg:phone":"+34 953 59 72 58",
    "sg:postcode":"23692",
    "sg:province":"Ja\u00e9n",
    "wof:name":"Escribano Aceituno Aurora",
    "wof:placetype":"venue"
},
  "geometry": {"coordinates":[-3.8862950802,37.4635848999],"type":"Point"}
}