{
  "type": "Feature",
  "properties": {
    "iso:country":"ES",
    "sg:address":"Carrer de Sant Carles, 2",
    "sg:city":"Roquetes",
    "sg:orig_category":"Arquitectos",
    "sg:phone":"+34 977 50 18 22",
    "sg:postcode":"43520",
    "sg:province":"Tarragona",
    "wof:name":"Ferre Capellades Ramon",
    "wof:placetype":"venue"
},
  "geometry": {"coordinates":[0.5014560223,40.8192443848],"type":"Point"}
}