{
  "type": "Feature",
  "properties": {
    "addr:full":"Carrer de Miguel De Cervantes (de), 1 Tortosa Tarragona 43500",
    "addr:postcode":"43500",
    "addr:street":"Carrer De Miguel De Cervantes De",
    "iso:country":"ES",
    "sg:address":"Carrer de Miguel De Cervantes (de), 1",
    "sg:city":"Tortosa",
    "sg:orig_category":"Caf\u00c9s, Bares, Cervecer\u00cdas",
    "sg:phone":"+34 977 44 10 33",
    "sg:postcode":"43500",
    "sg:province":"Tarragona",
    "wof:name":"Camacho Tevas Jose",
    "wof:placetype":"venue"
},
  "geometry": {"coordinates":[0.5220950246,40.8103675842],"type":"Point"}
}