{
  "type": "Feature",
  "properties": {
    "iso:country":"ES",
    "sg:address":"Ctra. General, 36",
    "sg:city":"Trevias",
    "sg:orig_category":"Transportes Por Carretera: Lotes Completos, Mercanc\u00cdas Diversas",
    "sg:phone":"+34 985 64 70 77",
    "sg:postcode":"33780",
    "sg:province":"Asturias",
    "wof:name":"Almacenes Garaot S.l.",
    "wof:placetype":"venue"
},
  "geometry": {"coordinates":[-6.4339017868,43.5014915466],"type":"Point"}
}