{
  "type": "Feature",
  "properties": {
    "iso:country":"ES",
    "sg:address":"Ctra. Jerez-los Barrios, Km. 0001,0",
    "sg:city":"Jerez",
    "sg:orig_category":"Comercio De Piezas De Recambio Y De Accesorios De Veh\u00cdculos, Veh\u00cdculos Industriales",
    "sg:phone":"+34 956 34 08 60",
    "sg:postcode":"11406",
    "sg:province":"C\u00e1diz",
    "wof:name":"Ramos Hermanos Talleres Especializados S.l",
    "wof:placetype":"venue"
},
  "geometry": {"coordinates":[-6.1010842323,36.6589164734],"type":"Point"}
}