{
  "type": "Feature",
  "properties": {
    "addr:full":"Carr Cerdanya, 24 Caldes Malavella Girona 17455",
    "addr:housenumber":"24",
    "addr:postcode":"17455",
    "addr:street":"Carr Cerdanya",
    "iso:country":"ES",
    "sg:address":"Carr Cerdanya, 24",
    "sg:city":"Caldes Malavella",
    "sg:orig_category":"Traductores",
    "sg:phone":"+34 972 47 07 80",
    "sg:postcode":"17455",
    "sg:province":"Girona",
    "wof:name":"Escuain Sanz Santiago",
    "wof:placetype":"venue"
},
  "geometry": {"coordinates":[2.8256690502,41.8730735779],"type":"Point"}
}