{
  "type": "Feature",
  "properties": {
    "iso:country":"ES",
    "sg:address":"Calle de Azeta, 17",
    "sg:city":"Portugalete",
    "sg:orig_category":"Ebanister\u00cda",
    "sg:phone":"+34 944 95 42 32",
    "sg:postcode":"48920",
    "sg:province":"Vizcaya",
    "wof:name":"Vera Vera Rafael",
    "wof:placetype":"venue"
},
  "geometry": {"coordinates":[-3.0122818947,43.3141326904],"type":"Point"}
}