{
  "type": "Feature",
  "properties": {
    "addr:full":"Calle de Altamira, 42 Almeria Almer\u00eda 04005",
    "addr:housenumber":"42",
    "addr:postcode":"04005",
    "addr:street":"Calle De Altamira",
    "iso:country":"ES",
    "sg:address":"Calle de Altamira, 42",
    "sg:city":"Almeria",
    "sg:orig_category":"Inmobiliaria (agencias)",
    "sg:phone":"+34 950 25 00 12",
    "sg:postcode":"04005",
    "sg:province":"Almer\u00eda",
    "wof:name":"Cibergestion Hipotecaria S.l.",
    "wof:placetype":"venue"
},
  "geometry": {"coordinates":[-2.4571022987,36.8401794434],"type":"Point"}
}