{
  "type": "Feature",
  "properties": {
    "iso:country":"ES",
    "sg:address":"Calle de Olivos (de Los), 1",
    "sg:city":"Algete",
    "sg:orig_category":"Administradores De Bienes Y Delegados De Comunidades De Propietarios",
    "sg:phone":"+34 916 29 30 76",
    "sg:postcode":"28110",
    "sg:province":"Madrid",
    "wof:name":"San Jose Martin Julio",
    "wof:placetype":"venue"
},
  "geometry": {"coordinates":[-3.5018188953,40.5974235535],"type":"Point"}
}