{
  "type": "Feature",
  "properties": {
    "iso:country":"ES",
    "sg:address":"Carr Doctor Fleming, S/n",
    "sg:city":"Ciutadella Menorca",
    "sg:orig_category":"Centros De Educaci\u00d3n Especial",
    "sg:phone":"+34 971 38 26 08",
    "sg:postcode":"07760",
    "sg:province":"Islas Baleares",
    "wof:name":"Colegio Publico Mare De Deu Del Toro",
    "wof:placetype":"venue"
},
  "geometry": {"coordinates":[3.8407099247,39.9962844849],"type":"Point"}
}