{
  "type": "Feature",
  "properties": {
    "iso:country":"ES",
    "sg:address":"Calle de Murillo, 7",
    "sg:city":"Linares",
    "sg:orig_category":"Comercio, Reparaci\u00d3n De Motocicletas, Bicicletas Y Piezas Sueltas",
    "sg:phone":"+34 953 65 18 28",
    "sg:postcode":"23700",
    "sg:province":"Ja\u00e9n",
    "wof:name":"Soler Linares Juan Antonio",
    "wof:placetype":"venue"
},
  "geometry": {"coordinates":[-3.630810976,38.0968284607],"type":"Point"}
}