{
  "type": "Feature",
  "properties": {
    "iso:country":"ES",
    "sg:address":"Avda Carlota Alessandri, 131",
    "sg:city":"Torremolinos",
    "sg:orig_category":"Alquiler De Material Y De Programas Audiovisuales",
    "sg:phone":"+34 952 38 87 10",
    "sg:postcode":"29620",
    "sg:province":"M\u00e1laga",
    "wof:name":"Electronica J.r. S.l.",
    "wof:placetype":"venue"
},
  "geometry": {"coordinates":[-4.5136590004,36.602645874],"type":"Point"}
}