{
  "type": "Feature",
  "properties": {
    "iso:country":"ES",
    "sg:address":"Calle de Aita Gotzon, 2",
    "sg:city":"Elortza",
    "sg:orig_category":"Restaurantes",
    "sg:phone":"+34 946 76 58 56",
    "sg:postcode":"48610",
    "sg:province":"Vizcaya",
    "wof:name":"Somarriba Carriles Vitoriano",
    "wof:placetype":"venue"
},
  "geometry": {"coordinates":[-2.6983869076,43.2204284668],"type":"Point"}
}