{
  "type": "Feature",
  "properties": {
    "iso:country":"ES",
    "sg:address":"Calle de Nueva, 40",
    "sg:city":"Cuellar",
    "sg:orig_category":"Molduras, Junquillos, Listones Y Molduras Perforadas",
    "sg:phone":"+34 921 14 02 56",
    "sg:postcode":"40200",
    "sg:province":"Segovia",
    "wof:name":"Martin Gonzalo Leonor",
    "wof:placetype":"venue"
},
  "geometry": {"coordinates":[-4.3142991066,41.4025382996],"type":"Point"}
}