{
  "type": "Feature",
  "properties": {
    "iso:country":"ES",
    "sg:address":"Plaz Navarro Rodrigo, 11",
    "sg:city":"Alacant",
    "sg:orig_category":"Abogados",
    "sg:phone":"+34 965 12 24 29",
    "sg:postcode":"03007",
    "sg:province":"Alicante",
    "wof:name":"Parra Parra Ana Maria",
    "wof:placetype":"venue"
},
  "geometry": {"coordinates":[-0.4979180098,38.3406600952],"type":"Point"}
}