{
  "type": "Feature",
  "properties": {
    "iso:country":"ES",
    "sg:address":"Calle de San Ignacio, 63",
    "sg:city":"Pto Real",
    "sg:orig_category":"Cl\u00cdnicas Dentales",
    "sg:phone":"+34 956 83 46 57",
    "sg:postcode":"11510",
    "sg:province":"C\u00e1diz",
    "wof:name":"Cardent S.c.",
    "wof:placetype":"venue"
},
  "geometry": {"coordinates":[-6.1895179749,36.5307769775],"type":"Point"}
}