{
  "type": "Feature",
  "properties": {
    "addr:full":"Calle de Severo Ochoa, S/n Burgos Burgos 09007",
    "addr:housenumber":"s / n",
    "addr:postcode":"09007",
    "addr:street":"Calle De Severo Ochoa",
    "iso:country":"ES",
    "sg:address":"Calle de Severo Ochoa, S/n",
    "sg:city":"Burgos",
    "sg:orig_category":"Ense\u00d1anza Secundaria: Colegios Y Escuelas Privadas",
    "sg:phone":"+34 947 23 82 19",
    "sg:postcode":"09007",
    "sg:province":"Burgos",
    "wof:name":"I.e.s. Pintor Luis Saez",
    "wof:placetype":"venue"
},
  "geometry": {"coordinates":[-3.6753690243,42.3531455994],"type":"Point"}
}