{
  "type": "Feature",
  "properties": {
    "iso:country":"ES",
    "sg:address":"Barr Elguero, 13",
    "sg:city":"Elguero",
    "sg:orig_category":"Empresas De Carpinter\u00cda Met\u00c1lica",
    "sg:phone":"+34 944 95 33 37",
    "sg:postcode":"48510",
    "sg:province":"Vizcaya",
    "wof:name":"Martin Casado Lucas",
    "wof:placetype":"venue"
},
  "geometry": {"coordinates":[-3.0369338989,43.3047294617],"type":"Point"}
}