{
  "type": "Feature",
  "properties": {
    "iso:country":"ES",
    "sg:address":"Calle de San Melchor De Quiros, 12",
    "sg:city":"Gijon",
    "sg:orig_category":"Acero: Productos Sider\u00dargicos Y Transformados (fabricaci\u00d3n, Negocio)",
    "sg:phone":"+34 985 31 93 03",
    "sg:postcode":"33201",
    "sg:province":"Asturias",
    "wof:name":"Oruro Analisis E Inversiones S.a.",
    "wof:placetype":"venue"
},
  "geometry": {"coordinates":[-5.6635565758,43.5441055298],"type":"Point"}
}