{
  "type": "Feature",
  "properties": {
    "iso:country":"ES",
    "sg:address":"Calle de Cruz, 29",
    "sg:city":"Torrejon Ardoz",
    "sg:orig_category":"Centros Empresariales",
    "sg:phone":"+34 916 78 04 77",
    "sg:postcode":"28850",
    "sg:province":"Madrid",
    "wof:name":"Representaciones Electromena 2 S.l.",
    "wof:placetype":"venue"
},
  "geometry": {"coordinates":[-3.4812376499,40.4613265991],"type":"Point"}
}