{
  "type": "Feature",
  "properties": {
    "iso:country":"ES",
    "sg:address":"Calle de Alhamar, 8",
    "sg:city":"Granada",
    "sg:orig_category":"Cajas De Ahorro",
    "sg:phone":"+34 958 25 45 00",
    "sg:postcode":"18005",
    "sg:province":"Granada",
    "sg:website":"www.caja-granada.es",
    "wof:name":"Cajagranada",
    "wof:placetype":"venue"
},
  "geometry": {"coordinates":[-3.6004526615,37.1690139771],"type":"Point"}
}