{
  "type": "Feature",
  "properties": {
    "iso:country":"ES",
    "sg:address":"Calle de Regimiento Argel, 43",
    "sg:city":"Alcantara",
    "sg:orig_category":"Asociaciones, Organismos Culturales Y Socioeducativos",
    "sg:phone":"+34 927 39 00 80",
    "sg:postcode":"10980",
    "sg:province":"C\u00e1ceres",
    "wof:name":"Fundacion San Benito De Alcantara",
    "wof:placetype":"venue"
},
  "geometry": {"coordinates":[-6.8848991394,39.7201004028],"type":"Point"}
}