{
  "type": "Feature",
  "properties": {
    "addr:full":"Ctra De Segovia (pol. Industrial), Km. 0013,7 Aldeamayor S. Martin Valladolid 47162",
    "addr:postcode":"47162",
    "addr:street":"Ctra De Segovia Pol. Industrial Km. 0013,7 Aldeamayor S. Martin",
    "iso:country":"ES",
    "sg:address":"Ctra De Segovia (pol. Industrial), Km. 0013,7",
    "sg:city":"Aldeamayor S. Martin",
    "sg:classifiers":[
        {
            "category":"Shopping",
            "subcategory":"Crafts & Fabrics",
            "type":"Retail Goods"
        }
    ],
    "sg:phone":"+34 983 52 85 92",
    "sg:postcode":"47162",
    "sg:province":"Valladolid",
    "sg:tags":[
        "manta",
        "de",
        "fabricaci\u00d3n"
    ],
    "wof:name":"Manufacturas Textiles Nicolas S.l.",
    "wof:placetype":"venue"
},
  "geometry": {"coordinates":[-4.6361689568,41.515625],"type":"Point"}
}