{
  "type": "Feature",
  "properties": {
    "addr:full":"G. Boyvia, 20 Callosa Segura Alicante 03360",
    "addr:housenumber":"20",
    "addr:postcode":"03360",
    "addr:street":"Boyvia",
    "iso:country":"ES",
    "sg:address":"G. Boyvia, 20",
    "sg:city":"Callosa Segura",
    "sg:orig_category":"Fabricaci\u00d3n, Venta, Instalaci\u00d3n De R\u00d3tulos, De R\u00d3tulos Luminosos",
    "sg:phone":"+34 966 75 70 47",
    "sg:postcode":"03360",
    "sg:province":"Alicante",
    "wof:name":"Matsuki Sanchez Miguel Angel",
    "wof:placetype":"venue"
},
  "geometry": {"coordinates":[-0.8776689768,38.1256752014],"type":"Point"}
}