{
  "type": "Feature",
  "properties": {
    "iso:country":"ES",
    "sg:address":"Carrer de Arquimedes, 33",
    "sg:city":"Barbera Valles",
    "sg:orig_category":"Fabricaci\u00d3n De Moldes Y Modelos",
    "sg:phone":"+34 937 18 75 12",
    "sg:postcode":"08210",
    "sg:province":"Barcelona",
    "wof:name":"Imatric S. A.",
    "wof:placetype":"venue"
},
  "geometry": {"coordinates":[2.1313750744,41.5104141235],"type":"Point"}
}