{
  "type": "Feature",
  "properties": {
    "iso:country":"ES",
    "sg:address":"Calle de Lanberri, 4",
    "sg:city":"Donostia-san Sebastian",
    "sg:orig_category":"Maquinaria Para Industrias Diversas",
    "sg:phone":"+34 943 31 33 19",
    "sg:postcode":"20009",
    "sg:province":"Guip\u00f9zcoa",
    "wof:name":"Ekicontrol S.l.",
    "wof:placetype":"venue"
},
  "geometry": {"coordinates":[-1.981030941,43.3007240295],"type":"Point"}
}