{
  "type": "Feature",
  "properties": {
    "addr:full":"Avda Madrigueras, S/n Tarazona Mancha Albacete 02100",
    "addr:housenumber":"s / n",
    "addr:postcode":"02100",
    "addr:street":"Avda Madrigueras",
    "iso:country":"ES",
    "sg:address":"Avda Madrigueras, S/n",
    "sg:city":"Tarazona Mancha",
    "sg:orig_category":"Empresas De Carpinter\u00cda Met\u00c1lica",
    "sg:phone":"+34 967 48 13 46",
    "sg:postcode":"02100",
    "sg:province":"Albacete",
    "wof:name":"Martinez Morales Isidro",
    "wof:placetype":"venue"
},
  "geometry": {"coordinates":[-1.9072569609,39.2594718933],"type":"Point"}
}