{
  "type": "Feature",
  "properties": {
    "addr:full":"Carrer de Aribau, 176 Barcelona Barcelona 08036",
    "addr:housenumber":"176",
    "addr:postcode":"08036",
    "addr:street":"Carrer De Aribau",
    "iso:country":"ES",
    "sg:address":"Carrer de Aribau, 176",
    "sg:city":"Barcelona",
    "sg:orig_category":"Supermercados Y Hipermercados",
    "sg:phone":"+34 932 18 38 87",
    "sg:postcode":"08036",
    "sg:province":"Barcelona",
    "sg:website":"www.capraboacasa.com",
    "wof:name":"Caprabo S.a.",
    "wof:placetype":"venue"
},
  "geometry": {"coordinates":[2.1530768871,41.3932037354],"type":"Point"}
}