{
  "type": "Feature",
  "properties": {
    "addr:full":"Av Velero, 190 La Zenia Alicante 03189",
    "addr:housenumber":"190",
    "addr:postcode":"03189",
    "addr:street":"Av Velero",
    "iso:country":"ES",
    "sg:address":"Av Velero, 190",
    "sg:city":"La Zenia",
    "sg:orig_category":"Inmobiliaria (agencias)",
    "sg:phone":"+34 966 76 07 87",
    "sg:postcode":"03189",
    "sg:province":"Alicante",
    "wof:name":"Costa Blanca Logistic Company S.l.",
    "wof:placetype":"venue"
},
  "geometry": {"coordinates":[-0.7534540296,37.9003753662],"type":"Point"}
}