{
  "type": "Feature",
  "properties": {
    "iso:country":"ES",
    "sg:address":"Calle de Valencia, 19",
    "sg:city":"Villalonga",
    "sg:orig_category":"Marmolistas Funerarios",
    "sg:phone":"+34 962 81 71 61",
    "sg:postcode":"46720",
    "sg:province":"Valencia",
    "wof:name":"Pompas Funebres La Safor S.l.",
    "wof:placetype":"venue"
},
  "geometry": {"coordinates":[-0.2075690031,38.8871498108],"type":"Point"}
}