{
  "type": "Feature",
  "properties": {
    "iso:country":"ES",
    "sg:address":"Rbla Catalunya, 87",
    "sg:city":"Barcelona",
    "sg:orig_category":"M\u00c9dicos: Cirug\u00cda Ortop\u00c9dica Y Traumatolog\u00cda",
    "sg:phone":"+34 932 15 79 46",
    "sg:postcode":"08008",
    "sg:province":"Barcelona",
    "wof:name":"Lafuente Rodes Fernando",
    "wof:placetype":"venue"
},
  "geometry": {"coordinates":[2.1611340046,41.3924636841],"type":"Point"}
}