{
  "type": "Feature",
  "properties": {
    "iso:country":"ES",
    "sg:address":"Telers, 48",
    "sg:city":"Ontinyent",
    "sg:orig_category":"Telas (al Por Mayor)",
    "sg:phone":"+34 962 91 17 58",
    "sg:postcode":"46870",
    "sg:province":"Valencia",
    "sg:website":"www.textil.org/revertasociados",
    "wof:name":"Revert Asociados S.l.",
    "wof:placetype":"venue"
},
  "geometry": {"coordinates":[-0.5755249858,38.8320846558],"type":"Point"}
}