{
  "type": "Feature",
  "properties": {
    "addr:full":"Calle de Rio G\u00fce\u00d1a-el Censo, 1 Cangas Onis Asturias 33550",
    "addr:housenumber":"1",
    "addr:postcode":"33550",
    "addr:street":"Calle De Rio Gueen\u0303A-El Censo;Onis Asturias",
    "iso:country":"ES",
    "sg:address":"Calle de Rio G\u00fce\u00d1a-el Censo, 1",
    "sg:city":"Cangas Onis",
    "sg:orig_category":"Notarios",
    "sg:phone":"+34 985 94 70 07",
    "sg:postcode":"33550",
    "sg:province":"Asturias",
    "wof:name":"Notaria De Cangas De Onis",
    "wof:placetype":"venue"
},
  "geometry": {"coordinates":[-5.1302790642,43.3507957458],"type":"Point"}
}