{
  "type": "Feature",
  "properties": {
    "iso:country":"ES",
    "sg:address":"Carrer de Osona, 3",
    "sg:city":"Barcelona",
    "sg:orig_category":"M\u00c9dicos: Ginecolog\u00cda Y Obstetricia",
    "sg:phone":"+34 932 11 79 21",
    "sg:postcode":"08023",
    "sg:province":"Barcelona",
    "wof:name":"Honrado Eguren Manuel",
    "wof:placetype":"venue"
},
  "geometry": {"coordinates":[2.1443750858,41.4078712463],"type":"Point"}
}