{
  "type": "Feature",
  "properties": {
    "addr:full":"Calle de Luis Rodriguez Arango, 1 Burgos Burgos 09001",
    "addr:housenumber":"1",
    "addr:postcode":"09001",
    "addr:street":"Calle De Luis Rodriguez Arango",
    "iso:country":"ES",
    "sg:address":"Calle de Luis Rodriguez Arango, 1",
    "sg:city":"Burgos",
    "sg:orig_category":"Minerales (al Por Mayor)",
    "sg:phone":"+34 947 20 44 79",
    "sg:postcode":"09001",
    "sg:province":"Burgos",
    "wof:name":"Alonso Garcia Eliseo",
    "wof:placetype":"venue"
},
  "geometry": {"coordinates":[-3.7122352123,42.3352661133],"type":"Point"}
}