{
  "type": "Feature",
  "properties": {
    "addr:full":"Calle de Severo Ochoa, 24 Villaviciosa Odon Madrid 28670",
    "addr:housenumber":"24",
    "addr:postcode":"28670",
    "addr:street":"Calle De Severo Ochoa;Odon",
    "iso:country":"ES",
    "sg:address":"Calle de Severo Ochoa, 24",
    "sg:city":"Villaviciosa Odon",
    "sg:orig_category":"Importaci\u00d3n",
    "sg:phone":"+34 916 85 50 64",
    "sg:postcode":"28670",
    "sg:province":"Madrid",
    "wof:name":"Juan Godino Internacional S.l.",
    "wof:placetype":"venue"
},
  "geometry": {"coordinates":[-3.9140861034,40.3584747314],"type":"Point"}
}