{
  "type": "Feature",
  "properties": {
    "iso:country":"ES",
    "sg:address":"Turiaso, 28",
    "sg:city":"Garrapinillos",
    "sg:orig_category":"Rectificaci\u00d3n, Mecanizado, Fresado",
    "sg:phone":"+34 976 77 07 55",
    "sg:postcode":"50197",
    "sg:province":"Zaragoza",
    "wof:name":"Mecanizados El Aguila S.l.",
    "wof:placetype":"venue"
},
  "geometry": {"coordinates":[-1.0269140005,41.6842803955],"type":"Point"}
}