{
  "type": "Feature",
  "properties": {
    "addr:full":"Calle de Brihuega, 2 Alcala Henares Madrid 28805",
    "addr:housenumber":"2",
    "addr:postcode":"28805",
    "addr:street":"Calle De Brihuega",
    "iso:country":"ES",
    "sg:address":"Calle de Brihuega, 2",
    "sg:city":"Alcala Henares",
    "sg:orig_category":"Sociedades, Compa\u00d1\u00cdas Aseguradoras",
    "sg:phone":"+34 918 77 09 25",
    "sg:postcode":"28805",
    "sg:province":"Madrid",
    "wof:name":"Seguros El Corte Ingles Vida Pensiones Y Reaseguros S.a.",
    "wof:placetype":"venue"
},
  "geometry": {"coordinates":[-3.3599879742,40.4864425659],"type":"Point"}
}