{
  "type": "Feature",
  "properties": {
    "iso:country":"ES",
    "sg:address":"Pg Born, 17",
    "sg:city":"Palma",
    "sg:orig_category":"Bancos",
    "sg:phone":"+34 971 72 51 46",
    "sg:postcode":"07012",
    "sg:province":"Islas Baleares",
    "wof:name":"Bt Espa\u00d1a Compa\u00d1ia De Servicios Globales De Telecomunicaciones S.a.u.",
    "wof:placetype":"venue"
},
  "geometry": {"coordinates":[2.646253109,39.5696868896],"type":"Point"}
}