{
  "type": "Feature",
  "properties": {
    "addr:full":"Calle de Arrabal Del Coso, S/n Pedro\u00d1eras Cuenca 16660",
    "addr:housenumber":"s / n",
    "addr:postcode":"16660",
    "addr:street":"Calle De Arrabal Del Coso",
    "iso:country":"ES",
    "sg:address":"Calle de Arrabal Del Coso, S/n",
    "sg:city":"Pedro\u00d1eras",
    "sg:orig_category":"Aguas (distribuci\u00d3n, Servicios)",
    "sg:phone":"+34 967 16 22 10",
    "sg:postcode":"16660",
    "sg:province":"Cuenca",
    "wof:name":"Aquagest S.a.",
    "wof:placetype":"venue"
},
  "geometry": {"coordinates":[-2.6713466644,39.4483947754],"type":"Point"}
}