{
  "type": "Feature",
  "properties": {
    "iso:country":"ES",
    "sg:address":"Crta. Eivissa Portinatx, Km. 0004,0",
    "sg:city":"Puig D'en Valls",
    "sg:orig_category":"Persianas Interiores, Exteriores",
    "sg:phone":"+34 971 31 36 53",
    "sg:postcode":"07819",
    "sg:province":"Islas Baleares",
    "wof:name":"Sanchez Gomez Claudio",
    "wof:placetype":"venue"
},
  "geometry": {"coordinates":[2.9117100239,39.6136398315],"type":"Point"}
}