{
  "type": "Feature",
  "properties": {
    "iso:country":"ES",
    "sg:address":"Avda I Argentina, S/n",
    "sg:city":"Malaga",
    "sg:orig_category":"Promotores Constructores",
    "sg:phone":"+34 952 24 70 66",
    "sg:postcode":"29004",
    "sg:province":"M\u00e1laga",
    "wof:name":"Piscis Constructora Promotora S.a.",
    "wof:placetype":"venue"
},
  "geometry": {"coordinates":[-4.4557738304,36.6829948425],"type":"Point"}
}