{
  "type": "Feature",
  "properties": {
    "addr:full":"Av Abat Marcet, 315 Terrassa Barcelona 08225",
    "addr:housenumber":"315",
    "addr:postcode":"08225",
    "addr:street":"Av Abat Marcet",
    "iso:country":"ES",
    "sg:address":"Av Abat Marcet, 315",
    "sg:city":"Terrassa",
    "sg:orig_category":"Asociaciones Y Clubs Deportivos",
    "sg:phone":"+34 937 88 59 28",
    "sg:postcode":"08225",
    "sg:province":"Barcelona",
    "sg:website":"www.intersports.es",
    "wof:name":"Egara Esports J.g. S.l.",
    "wof:placetype":"venue"
},
  "geometry": {"coordinates":[2.0054199696,41.574420929],"type":"Point"}
}