{
  "type": "Feature",
  "properties": {
    "addr:full":"Carrer de Creu, 39 S. Just Desvern Barcelona 08960",
    "addr:housenumber":"39",
    "addr:postcode":"08960",
    "addr:street":"Carrer De Creu",
    "iso:country":"ES",
    "sg:address":"Carrer de Creu, 39",
    "sg:city":"S. Just Desvern",
    "sg:orig_category":"Ropa Para Se\u00d1oras (al Por Menor)",
    "sg:phone":"+34 933 72 42 52",
    "sg:postcode":"08960",
    "sg:province":"Barcelona",
    "wof:name":"Bel Ciuret Maria Antonia",
    "wof:placetype":"venue"
},
  "geometry": {"coordinates":[2.0784931183,41.3830718994],"type":"Point"}
}