{
  "type": "Feature",
  "properties": {
    "addr:full":"Calle de Veracruz, 47 Puebla Almoradiel Toledo 45840",
    "addr:housenumber":"47",
    "addr:postcode":"45840",
    "addr:street":"Calle De Veracruz;Almoradiel",
    "iso:country":"ES",
    "sg:address":"Calle de Veracruz, 47",
    "sg:city":"Puebla Almoradiel",
    "sg:classifiers":[
        {
            "category":"Taxi",
            "type":"Transportation"
        }
    ],
    "sg:phone":"+34 925 20 54 33",
    "sg:postcode":"45840",
    "sg:province":"Toledo",
    "wof:name":"Rodriguez Angulo Miguel",
    "wof:placetype":"venue"
},
  "geometry": {"coordinates":[-3.1219029427,39.6003723145],"type":"Point"}
}