{
  "type": "Feature",
  "properties": {
    "addr:full":"Carrer de Sant Gervasi De Cassoles, 101 Barcelona Barcelona 08022",
    "addr:housenumber":"101",
    "addr:postcode":"08022",
    "addr:street":"Carrer De Sant Gervasi De Cassoles",
    "iso:country":"ES",
    "sg:address":"Carrer de Sant Gervasi De Cassoles, 101",
    "sg:city":"Barcelona",
    "sg:orig_category":"Complementos De Vestir (al Por Menor)",
    "sg:phone":"+34 932 11 21 64",
    "sg:postcode":"08022",
    "sg:province":"Barcelona",
    "wof:name":"First Level Shops S. L.",
    "wof:placetype":"venue"
},
  "geometry": {"coordinates":[2.1351110935,41.4061012268],"type":"Point"}
}