{
  "type": "Feature",
  "properties": {
    "iso:country":"ES",
    "sg:address":"Carrer de Sant Pere Mes Baix, 50",
    "sg:city":"Barcelona",
    "sg:orig_category":"Ropa Para Se\u00d1oras (al Por Menor)",
    "sg:phone":"+34 933 19 03 27",
    "sg:postcode":"08003",
    "sg:province":"Barcelona",
    "wof:name":"Lopez Colombo Pilar",
    "wof:placetype":"venue"
},
  "geometry": {"coordinates":[2.1781640053,41.3876724243],"type":"Point"}
}