{
  "type": "Feature",
  "properties": {
    "iso:country":"ES",
    "sg:address":"Calle de Villanueva, 13",
    "sg:city":"Valladolid",
    "sg:orig_category":"Peluqueros: De Se\u00d1oras",
    "sg:phone":"+34 983 27 36 55",
    "sg:postcode":"47013",
    "sg:province":"Valladolid",
    "wof:name":"Arguello Rodriguez Clara Esperanza",
    "wof:placetype":"venue"
},
  "geometry": {"coordinates":[-4.720864296,41.6379203796],"type":"Point"}
}