{
  "type": "Feature",
  "properties": {
    "addr:full":"Psaj Espronceda, 9 Linea De La Concepcion C\u00e1diz 11300",
    "addr:housenumber":"9",
    "addr:postcode":"11300",
    "addr:street":"Psaj Espronceda;Ca\u0301Diz",
    "iso:country":"ES",
    "sg:address":"Psaj Espronceda, 9",
    "sg:city":"Linea De La Concepcion",
    "sg:orig_category":"Electrodom\u00c9sticos (fabricaci\u00d3n, Al Por Mayor)",
    "sg:phone":"+34 956 17 09 59",
    "sg:postcode":"11300",
    "sg:province":"C\u00e1diz",
    "wof:name":"Calzada Gil Juan Manuel",
    "wof:placetype":"venue"
},
  "geometry": {"coordinates":[-5.3437790871,36.1630630493],"type":"Point"}
}