{
  "type": "Feature",
  "properties": {
    "iso:country":"ES",
    "sg:address":"Calle de Pinar (el), 56",
    "sg:city":"Santo Domingo De La Calzada",
    "sg:orig_category":"Ropa Para Se\u00d1oras Y Caballeros (al Por Menor)",
    "sg:phone":"+34 941 34 33 40",
    "sg:postcode":"26250",
    "sg:province":"La Rioja",
    "wof:name":"Sacristan Olmos Luis",
    "wof:placetype":"venue"
},
  "geometry": {"coordinates":[-2.9542388916,42.4401397705],"type":"Point"}
}