{
  "type": "Feature",
  "properties": {
    "addr:full":"Calle de Calderon De La Barca, 53 Nules Castell\u00f3n 12520",
    "addr:housenumber":"53",
    "addr:postcode":"12520",
    "addr:street":"Calle De Calderon De La Barca",
    "iso:country":"ES",
    "sg:address":"Calle de Calderon De La Barca, 53",
    "sg:city":"Nules",
    "sg:orig_category":"Transportes Por V\u00cdas Navegables",
    "sg:phone":"+34 964 67 03 61",
    "sg:postcode":"12520",
    "sg:province":"Castell\u00f3n",
    "wof:name":"Canos Casaus Francisco",
    "wof:placetype":"venue"
},
  "geometry": {"coordinates":[-0.157258004,39.8562278748],"type":"Point"}
}