{
  "type": "Feature",
  "properties": {
    "addr:full":"Trva Rubia (la), 6 Segovia Segovia 40001",
    "addr:housenumber":"6",
    "addr:postcode":"40001",
    "addr:street":"Trva Rubia La",
    "iso:country":"ES",
    "sg:address":"Trva Rubia (la), 6",
    "sg:city":"Segovia",
    "sg:orig_category":"Tapicer\u00cdas",
    "sg:phone":"+34 921 46 02 23",
    "sg:postcode":"40001",
    "sg:province":"Segovia",
    "wof:name":"Dominguez Moreno Jose Antonio",
    "wof:placetype":"venue"
},
  "geometry": {"coordinates":[-4.1221628189,40.9505653381],"type":"Point"}
}