{
  "type": "Feature",
  "properties": {
    "addr:full":"Rbla Catalunya, 47 Barcelona Barcelona 08007",
    "addr:housenumber":"47",
    "addr:postcode":"08007",
    "addr:street":"Rbla Catalunya",
    "iso:country":"ES",
    "sg:address":"Rbla Catalunya, 47",
    "sg:city":"Barcelona",
    "sg:orig_category":"Asociaciones, Organismos Culturales Y Socioeducativos",
    "sg:phone":"+34 932 15 58 48",
    "sg:postcode":"08007",
    "sg:province":"Barcelona",
    "wof:name":"Fundacio Ramon Trias Fargas",
    "wof:placetype":"venue"
},
  "geometry": {"coordinates":[2.1641049385,41.3902931213],"type":"Point"}
}