{
  "type": "Feature",
  "properties": {
    "addr:full":"Calle de Alvarez De Lugo, 51 Santa Cruz De Tenerife Santa Cruz De Tenerife 38004",
    "addr:housenumber":"51",
    "addr:postcode":"38004",
    "addr:street":"Calle De Alvarez De Lugo",
    "iso:country":"ES",
    "sg:address":"Calle de Alvarez De Lugo, 51",
    "sg:city":"Santa Cruz De Tenerife",
    "sg:orig_category":"Frutas, Legumbres Frescas Y Tempranas (al Por Menor)",
    "sg:phone":"+34 922 24 96 76",
    "sg:postcode":"38004",
    "sg:province":"Santa Cruz De Tenerife",
    "wof:name":"Morales Suarez Francisco Pedro",
    "wof:placetype":"venue"
},
  "geometry": {"coordinates":[-16.258140564,28.4668159485],"type":"Point"}
}