{
  "type": "Feature",
  "properties": {
    "iso:country":"ES",
    "sg:address":"Plaz Espa\u00d1a, 4",
    "sg:city":"Onda",
    "sg:orig_category":"Asesor\u00cda Fiscal Y Jur\u00cddica",
    "sg:phone":"+34 964 60 29 52",
    "sg:postcode":"12200",
    "sg:province":"Castell\u00f3n",
    "wof:name":"Asesoria Fiscal Y Contable Ondense S.l.",
    "wof:placetype":"venue"
},
  "geometry": {"coordinates":[-0.2432307005,39.9604454041],"type":"Point"}
}