{
  "type": "Feature",
  "properties": {
    "iso:country":"ES",
    "sg:address":"Pl Pio Xii, 1",
    "sg:city":"Pu\u00e7ol",
    "sg:orig_category":"Electricidad: Instaladores",
    "sg:phone":"+34 961 42 09 82",
    "sg:postcode":"46530",
    "sg:province":"Valencia",
    "wof:name":"Fontestad Ruiz Julian",
    "wof:placetype":"venue"
},
  "geometry": {"coordinates":[-0.3000389934,39.6155700684],"type":"Point"}
}