{
  "type": "Feature",
  "properties": {
    "iso:country":"ES",
    "sg:address":"Calle de Isaac Peral, 6",
    "sg:city":"Linares",
    "sg:orig_category":"Tintes (fabricaci\u00d3n, Al Por Mayor)",
    "sg:phone":"+34 953 60 22 33",
    "sg:postcode":"23700",
    "sg:province":"Ja\u00e9n",
    "wof:name":"Sevilla Vera Jose Manuel",
    "wof:placetype":"venue"
},
  "geometry": {"coordinates":[-3.6336131096,38.0961112976],"type":"Point"}
}