{
  "type": "Feature",
  "properties": {
    "addr:full":"Carrer de Moli Dels Frares, 45 Sant Vicen\u00c7 Dels Horts Barcelona 08620",
    "addr:housenumber":"45",
    "addr:postcode":"08620",
    "addr:street":"Carrer De Moli Dels Frares",
    "iso:country":"ES",
    "sg:address":"Carrer de Moli Dels Frares, 45",
    "sg:city":"Sant Vicen\u00c7 Dels Horts",
    "sg:orig_category":"Electricidad: Instaladores",
    "sg:phone":"+34 936 56 81 67",
    "sg:postcode":"08620",
    "sg:province":"Barcelona",
    "wof:name":"Basor Electric S.a.",
    "wof:placetype":"venue"
},
  "geometry": {"coordinates":[1.9983990192,41.4034576416],"type":"Point"}
}