{
  "type": "Feature",
  "properties": {
    "iso:country":"ES",
    "sg:address":"Calle de Sol, 35",
    "sg:city":"Orihuela",
    "sg:orig_category":"Tapicer\u00cdas",
    "sg:phone":"+34 966 73 67 50",
    "sg:postcode":"03300",
    "sg:province":"Alicante",
    "wof:name":"Comersan S.a.",
    "wof:placetype":"venue"
},
  "geometry": {"coordinates":[-0.9512640238,38.0833473206],"type":"Point"}
}