{
  "type": "Feature",
  "properties": {
    "addr:full":"Calle de Vicerrector Javier Herrera, 14 Osuna Sevilla 41640",
    "addr:housenumber":"14",
    "addr:postcode":"41640",
    "addr:street":"Calle De Vicerrector Javier Herrera",
    "iso:country":"ES",
    "sg:address":"Calle de Vicerrector Javier Herrera, 14",
    "sg:city":"Osuna",
    "sg:orig_category":"Empresas De Portes Y Mensajer\u00cda",
    "sg:phone":"+34 955 82 05 76",
    "sg:postcode":"41640",
    "sg:province":"Sevilla",
    "wof:name":"Zamora Alvarez Manuel",
    "wof:placetype":"venue"
},
  "geometry": {"coordinates":[-5.0958347321,37.2341308594],"type":"Point"}
}