{
  "type": "Feature",
  "properties": {
    "addr:full":"Calle de Extramuros, S/n Ca\u00f1amares Cuenca 16890",
    "addr:postcode":"16890",
    "addr:street":"Calle De Extramuros S / N Can\u0303Amares",
    "iso:country":"ES",
    "sg:address":"Calle de Extramuros, S/n",
    "sg:city":"Ca\u00f1amares",
    "sg:orig_category":"Cester\u00cda (fabricaci\u00d3n)",
    "sg:phone":"+34 969 31 00 86",
    "sg:postcode":"16890",
    "sg:province":"Cuenca",
    "wof:name":"Canomim S.l.",
    "wof:placetype":"venue"
},
  "geometry": {"coordinates":[-2.1762690544,40.475440979],"type":"Point"}
}