{
  "type": "Feature",
  "properties": {
    "addr:full":"Calle de Andres Piquer, 2 Zaragoza Zaragoza 50006",
    "addr:housenumber":"2",
    "addr:postcode":"50006",
    "addr:street":"Calle De Andres Piquer",
    "iso:country":"ES",
    "sg:address":"Calle de Andres Piquer, 2",
    "sg:city":"Zaragoza",
    "sg:orig_category":"Molduras, Junquillos, Listones Y Molduras Perforadas",
    "sg:phone":"+34 976 35 82 65",
    "sg:postcode":"50006",
    "sg:province":"Zaragoza",
    "wof:name":"Bar Sybaris S.c.",
    "wof:placetype":"venue"
},
  "geometry": {"coordinates":[-0.8947539926,41.6401176453],"type":"Point"}
}