{
  "type": "Feature",
  "properties": {
    "iso:country":"ES",
    "sg:address":"Pl Pati Del Castell, 9",
    "sg:city":"Valls",
    "sg:orig_category":"Quincaller\u00cda (al Por Menor)",
    "sg:phone":"+34 977 60 10 76",
    "sg:postcode":"43800",
    "sg:province":"Tarragona",
    "wof:name":"Serra Sabate Jose",
    "wof:placetype":"venue"
},
  "geometry": {"coordinates":[1.2506849766,41.2858657837],"type":"Point"}
}