{
  "type": "Feature",
  "properties": {
    "iso:country":"ES",
    "sg:address":"Carrer de Mossen Camil Rosell, 8",
    "sg:city":"Santa Perpetua De Mogoda",
    "sg:orig_category":"Mercer\u00cda, Lencer\u00cda (al Por Menor)",
    "sg:phone":"+34 935 60 15 04",
    "sg:postcode":"08130",
    "sg:province":"Barcelona",
    "wof:name":"Payes Jarque Maria",
    "wof:placetype":"venue"
},
  "geometry": {"coordinates":[2.1797719002,41.5353240967],"type":"Point"}
}