{
  "type": "Feature",
  "properties": {
    "addr:full":"Avda Albufera, 139 Madrid Madrid 28038",
    "addr:housenumber":"139",
    "addr:postcode":"28038",
    "addr:street":"Avda Albufera",
    "iso:country":"ES",
    "sg:address":"Avda Albufera, 139",
    "sg:city":"Madrid",
    "sg:orig_category":"Mec\u00c1nico Del Autom\u00d3vil",
    "sg:phone":"+34 914 78 13 74",
    "sg:postcode":"28038",
    "sg:province":"Madrid",
    "wof:name":"Alcalde Martinez Arturo",
    "wof:placetype":"venue"
},
  "geometry": {"coordinates":[-3.658134222,40.3924179077],"type":"Point"}
}