{
  "type": "Feature",
  "properties": {
    "addr:full":"Calle de Padilla, S/n Palencia Palencia 34003",
    "addr:housenumber":"s / n",
    "addr:postcode":"34003",
    "addr:street":"Calle De Padilla",
    "iso:country":"ES",
    "sg:address":"Calle de Padilla, S/n",
    "sg:city":"Palencia",
    "sg:orig_category":"Centros De Educaci\u00d3n Especial",
    "sg:phone":"+34 979 72 05 63",
    "sg:postcode":"34003",
    "sg:province":"Palencia",
    "wof:name":"Colegio Nacional Ciudad De Buenos Aires",
    "wof:placetype":"venue"
},
  "geometry": {"coordinates":[-4.5235691071,42.0097846985],"type":"Point"}
}