{
  "type": "Feature",
  "properties": {
    "iso:country":"ES",
    "sg:address":"Carr Afores, S/n",
    "sg:city":"Marza",
    "sg:orig_category":"Reciclaje Y Tratamiento De Desechos Varios",
    "sg:phone":"+34 972 19 31 47",
    "sg:postcode":"17493",
    "sg:province":"Girona",
    "wof:name":"Gbi Serveis S.a.",
    "wof:placetype":"venue"
},
  "geometry": {"coordinates":[3.0930049419,42.3256111145],"type":"Point"}
}