{
  "type": "Feature",
  "properties": {
    "addr:full":"Calle de Outeiro Grande, S/n Maside Ourense 32570",
    "addr:housenumber":"s / n",
    "addr:postcode":"32570",
    "addr:street":"Calle De Outeiro Grande",
    "iso:country":"ES",
    "sg:address":"Calle de Outeiro Grande, S/n",
    "sg:city":"Maside",
    "sg:orig_category":"Molduras, Junquillos, Listones Y Molduras Perforadas",
    "sg:phone":"+34 988 28 85 17",
    "sg:postcode":"32570",
    "sg:province":"Ourense",
    "wof:name":"Alvarez Gonzalez Jose",
    "wof:placetype":"venue"
},
  "geometry": {"coordinates":[-8.0303440094,42.4181518555],"type":"Point"}
}