{
  "type": "Feature",
  "properties": {
    "addr:full":"Calle de Serrablo (de), 37 Sabi\u00f1anigo Huesca 22600",
    "addr:housenumber":"37",
    "addr:postcode":"22600",
    "addr:street":"Calle De Serrablo De",
    "iso:country":"ES",
    "sg:address":"Calle de Serrablo (de), 37",
    "sg:city":"Sabi\u00f1anigo",
    "sg:orig_category":"Electricidad: Instaladores",
    "sg:phone":"+34 974 48 28 91",
    "sg:postcode":"22600",
    "sg:province":"Huesca",
    "wof:name":"Eleca Pirineos C.b.",
    "wof:placetype":"venue"
},
  "geometry": {"coordinates":[-0.3686169982,42.5185966492],"type":"Point"}
}