{
  "type": "Feature",
  "properties": {
    "iso:country":"ES",
    "sg:address":"Calle de Jacinto Benavente, S/n",
    "sg:city":"Jamilena",
    "sg:orig_category":"Electricidad: Instalaciones Industriales",
    "sg:phone":"+34 953 41 70 50",
    "sg:postcode":"23658",
    "sg:province":"Ja\u00e9n",
    "wof:name":"Barranco Jimenez Jose",
    "wof:placetype":"venue"
},
  "geometry": {"coordinates":[-3.9078888893,37.7475357056],"type":"Point"}
}