{
  "type": "Feature",
  "properties": {
    "iso:country":"ES",
    "sg:address":"Carrer de Roger De Flor, 149",
    "sg:city":"Barcelona",
    "sg:orig_category":"Fabricaci\u00d3n De Telas Y Sedas",
    "sg:phone":"+34 932 32 12 66",
    "sg:postcode":"08013",
    "sg:province":"Barcelona",
    "wof:name":"Re\u00f1e Bordes Jose Maria",
    "wof:placetype":"venue"
},
  "geometry": {"coordinates":[2.1738770008,41.3976478577],"type":"Point"}
}