{
  "type": "Feature",
  "properties": {
    "addr:full":"Calle de Daban, 31 Peralta Navarra 31350",
    "addr:housenumber":"31",
    "addr:postcode":"31350",
    "addr:street":"Calle De Daban",
    "iso:country":"ES",
    "sg:address":"Calle de Daban, 31",
    "sg:city":"Peralta",
    "sg:orig_category":"Peluquer\u00cdas, Peluquer\u00cda Mixta",
    "sg:phone":"+34 948 75 11 26",
    "sg:postcode":"31350",
    "sg:province":"Navarra",
    "wof:name":"Ordu\u00f1a Castillo Angel",
    "wof:placetype":"venue"
},
  "geometry": {"coordinates":[-1.7961915731,42.3384094238],"type":"Point"}
}