{
  "type": "Feature",
  "properties": {
    "addr:full":"Carr Marian Aguilo, 15 Felanitx Islas Baleares 07200",
    "addr:housenumber":"15",
    "addr:postcode":"07200",
    "addr:street":"Carr Marian Aguilo",
    "iso:country":"ES",
    "sg:address":"Carr Marian Aguilo, 15",
    "sg:city":"Felanitx",
    "sg:orig_category":"Abogados",
    "sg:phone":"+34 971 58 00 87",
    "sg:postcode":"07200",
    "sg:province":"Islas Baleares",
    "wof:name":"Julia Barcelo Antonio",
    "wof:placetype":"venue"
},
  "geometry": {"coordinates":[3.1461510658,39.4695892334],"type":"Point"}
}