{
  "type": "Feature",
  "properties": {
    "addr:full":"Calle de Rafael Del Riego, 14 Veguina Asturias 33610",
    "addr:housenumber":"14",
    "addr:postcode":"33610",
    "addr:street":"Calle De Rafael Del Riego;Asturias",
    "iso:country":"ES",
    "sg:address":"Calle de Rafael Del Riego, 14",
    "sg:city":"Veguina",
    "sg:orig_category":"Sociedades, Compa\u00d1\u00cdas Aseguradoras",
    "sg:phone":"+34 985 43 14 24",
    "sg:postcode":"33610",
    "sg:province":"Asturias",
    "wof:name":"Mapfre Servicios De Informatica",
    "wof:placetype":"venue"
},
  "geometry": {"coordinates":[-5.6699900627,43.2162284851],"type":"Point"}
}