{
  "type": "Feature",
  "properties": {
    "iso:country":"ES",
    "sg:address":"Calle de Mesones, 8",
    "sg:city":"San Esteban Del Valle",
    "sg:classifiers":[
        {
            "category":"Taxi",
            "type":"Transportation"
        }
    ],
    "sg:phone":"+34 920 38 33 27",
    "sg:postcode":"05412",
    "sg:province":"\u00c1vila",
    "wof:name":"Gonzalez Degano Leopoldo",
    "wof:placetype":"venue"
},
  "geometry": {"coordinates":[-4.982779026,40.2744674683],"type":"Point"}
}