{
  "type": "Feature",
  "properties": {
    "iso:country":"ES",
    "sg:address":"Calle de Calahorra, 17",
    "sg:city":"Madrid",
    "sg:orig_category":"\u00d3ptica: Instrumentos (fabricaci\u00d3n)",
    "sg:phone":"+34 917 76 02 49",
    "sg:postcode":"28032",
    "sg:province":"Madrid",
    "wof:name":"Centro Auditivo Sotone S.l.",
    "wof:placetype":"venue"
},
  "geometry": {"coordinates":[-3.6130411625,40.4071540833],"type":"Point"}
}