{
  "type": "Feature",
  "properties": {
    "iso:country":"ES",
    "sg:address":"Carrer de L'escultor Ordo\u00d1ez, 12",
    "sg:city":"Barcelona",
    "sg:orig_category":"Droguer\u00cdas (al Por Menor)",
    "sg:phone":"+34 933 52 49 56",
    "sg:postcode":"08016",
    "sg:province":"Barcelona",
    "wof:name":"Alvarez Encinas Carmen",
    "wof:placetype":"venue"
},
  "geometry": {"coordinates":[2.1741893291,41.4325561523],"type":"Point"}
}