{
  "type": "Feature",
  "properties": {
    "iso:country":"ES",
    "sg:address":"Pase Florida, 10",
    "sg:city":"Madrid",
    "sg:orig_category":"Arquitectos",
    "sg:phone":"+34 915 48 50 75",
    "sg:postcode":"28008",
    "sg:province":"Madrid",
    "wof:name":"Gallego Carvajal Miguel Angel",
    "wof:placetype":"venue"
},
  "geometry": {"coordinates":[-3.7224009037,40.4224891663],"type":"Point"}
}