{
  "type": "Feature",
  "properties": {
    "addr:full":"Calle de Francisco Juan Follana, 57 Albatera Alicante 03340",
    "addr:housenumber":"57",
    "addr:postcode":"03340",
    "addr:street":"Calle De Francisco Juan Follana",
    "iso:country":"ES",
    "sg:address":"Calle de Francisco Juan Follana, 57",
    "sg:city":"Albatera",
    "sg:orig_category":"Art\u00cdculos De Regalo (al Por Menor)",
    "sg:phone":"+34 965 48 59 26",
    "sg:postcode":"03340",
    "sg:province":"Alicante",
    "wof:name":"Minguez Cordoba Jose Manuel",
    "wof:placetype":"venue"
},
  "geometry": {"coordinates":[-0.8716989756,38.1786193848],"type":"Point"}
}