{
  "type": "Feature",
  "properties": {
    "addr:full":"Carr Pu\u00c7ol, 7 Puig Valencia 46540",
    "addr:housenumber":"7",
    "addr:postcode":"46540",
    "addr:street":"Carr Puc\u0327Ol",
    "iso:country":"ES",
    "sg:address":"Carr Pu\u00c7ol, 7",
    "sg:city":"Puig",
    "sg:orig_category":"Confecci\u00d3n De Trajes Para Se\u00d1oras",
    "sg:phone":"+34 961 47 08 86",
    "sg:postcode":"46540",
    "sg:province":"Valencia",
    "wof:name":"Romero Gargallo Clara",
    "wof:placetype":"venue"
},
  "geometry": {"coordinates":[-0.3027769923,39.5904808044],"type":"Point"}
}