{
  "type": "Feature",
  "properties": {
    "addr:full":"Ctra Ugena, S/n Illescas Toledo 45200",
    "addr:housenumber":"s / n",
    "addr:postcode":"45200",
    "addr:street":"Ctra Ugena",
    "iso:country":"ES",
    "sg:address":"Ctra Ugena, S/n",
    "sg:city":"Illescas",
    "sg:orig_category":"Ense\u00d1anza Secundaria: Colegios Y Escuelas Privadas",
    "sg:phone":"+34 925 54 00 51",
    "sg:postcode":"45200",
    "sg:province":"Toledo",
    "wof:name":"Instituto De Ense\u00d1anza Secundaria Ii De Illescas",
    "wof:placetype":"venue"
},
  "geometry": {"coordinates":[-3.8492290974,40.1332359314],"type":"Point"}
}