{
  "type": "Feature",
  "properties": {
    "iso:country":"ES",
    "sg:address":"Luga Barranca, S/n",
    "sg:city":"Corcos",
    "sg:orig_category":"Cr\u00cda De Animales",
    "sg:phone":"+34 983 58 03 88",
    "sg:postcode":"47280",
    "sg:province":"Valladolid",
    "wof:name":"Agropecuaria De La Barranca S. A.",
    "wof:placetype":"venue"
},
  "geometry": {"coordinates":[-4.681209,41.79969],"type":"Point"}
}