{
  "type": "Feature",
  "properties": {
    "iso:country":"ES",
    "sg:address":"Calle de Acera Recoletos, 11",
    "sg:city":"Valladolid",
    "sg:orig_category":"Inmobiliaria (agencias)",
    "sg:phone":"+34 983 29 22 88",
    "sg:postcode":"47004",
    "sg:province":"Valladolid",
    "wof:name":"Agc Asesoramiento Y Gestion De Comunidades De Viviendas Sociales S.l.",
    "wof:placetype":"venue"
},
  "geometry": {"coordinates":[-4.7279658318,41.6462173462],"type":"Point"}
}