{
  "type": "Feature",
  "properties": {
    "addr:full":"Calle de Puerta Del Mar, 18 Malaga M\u00e1laga 29005",
    "addr:housenumber":"18",
    "addr:postcode":"29005",
    "addr:street":"Calle De Puerta Del Mar;Ma\u0301Laga",
    "iso:country":"ES",
    "sg:address":"Calle de Puerta Del Mar, 18",
    "sg:city":"Malaga",
    "sg:orig_category":"Centros De Coordinaci\u00d3n",
    "sg:phone":"+34 952 22 30 41",
    "sg:postcode":"29005",
    "sg:province":"M\u00e1laga",
    "wof:name":"Rodriguez Ayala Juan",
    "wof:placetype":"venue"
},
  "geometry": {"coordinates":[-4.4229741096,36.718296051],"type":"Point"}
}