{
  "type": "Feature",
  "properties": {
    "iso:country":"ES",
    "sg:address":"Calle de Ferrocarril, 33",
    "sg:city":"Madrid",
    "sg:orig_category":"Plomeros",
    "sg:phone":"+34 915 28 18 66",
    "sg:postcode":"28045",
    "sg:province":"Madrid",
    "wof:name":"Metidieri Carde\u00f1osa Eulalio",
    "wof:placetype":"venue"
},
  "geometry": {"coordinates":[-3.6982018948,40.4008674622],"type":"Point"}
}