{
  "type": "Feature",
  "properties": {
    "addr:full":"Calle de Fernando El Catolico, 7 Alcala Real Ja\u00e9n 23680",
    "addr:housenumber":"7",
    "addr:postcode":"23680",
    "addr:street":"Calle De Fernando El Catolico;Jae\u0301N",
    "iso:country":"ES",
    "sg:address":"Calle de Fernando El Catolico, 7",
    "sg:city":"Alcala Real",
    "sg:orig_category":"Confecci\u00d3n De Trajes Para Se\u00d1oras",
    "sg:phone":"+34 953 58 33 22",
    "sg:postcode":"23680",
    "sg:province":"Ja\u00e9n",
    "wof:name":"Perez Gonzalez Maximo",
    "wof:placetype":"venue"
},
  "geometry": {"coordinates":[-3.9218790531,37.4599685669],"type":"Point"}
}