{
  "type": "Feature",
  "properties": {
    "addr:full":"La Dama De Noche, S/n Nueva Andalucia M\u00e1laga 29660",
    "addr:housenumber":"s / n",
    "addr:postcode":"29660",
    "addr:street":"Ma\u0301Laga",
    "iso:country":"ES",
    "sg:address":"La Dama De Noche, S/n",
    "sg:city":"Nueva Andalucia",
    "sg:orig_category":"Limpieza Con Chorro De Arena Y Con Granalla, Pulido",
    "sg:phone":"+34 952 81 26 16",
    "sg:postcode":"29660",
    "sg:province":"M\u00e1laga",
    "wof:name":"Zia Ebrahimi  Lahle",
    "wof:placetype":"venue"
},
  "geometry": {"coordinates":[-4.963350296,36.498714447],"type":"Point"}
}