{
  "type": "Feature",
  "properties": {
    "iso:country":"ES",
    "sg:address":"Carrer de Tavern, 17",
    "sg:city":"Barcelona",
    "sg:orig_category":"Peleter\u00cdas",
    "sg:phone":"+34 932 09 52 07",
    "sg:postcode":"08006",
    "sg:province":"Barcelona",
    "wof:name":"Jimenez Camarero Teresa",
    "wof:placetype":"venue"
},
  "geometry": {"coordinates":[2.1435821056,41.3994178772],"type":"Point"}
}