{
  "type": "Feature",
  "properties": {
    "iso:country":"ES",
    "sg:address":"Avda Sevilla, 48",
    "sg:city":"Don Benito",
    "sg:orig_category":"Material Y Herramientas Agr\u00cdcolas",
    "sg:phone":"+34 924 80 48 01",
    "sg:postcode":"06400",
    "sg:province":"Badajoz",
    "wof:name":"Capilla Martin Casimiro",
    "wof:placetype":"venue"
},
  "geometry": {"coordinates":[-5.8753938675,38.953956604],"type":"Point"}
}