{
  "type": "Feature",
  "properties": {
    "addr:full":"Calle de Gran Via, 43 Majadahonda Madrid 28220",
    "addr:housenumber":"43",
    "addr:postcode":"28220",
    "addr:street":"Calle De Gran Via",
    "iso:country":"ES",
    "sg:address":"Calle de Gran Via, 43",
    "sg:city":"Majadahonda",
    "sg:orig_category":"Centros Empresariales",
    "sg:phone":"+34 916 34 35 97",
    "sg:postcode":"28220",
    "sg:province":"Madrid",
    "wof:name":"Suan Asociados Consultores, S.l.",
    "wof:placetype":"venue"
},
  "geometry": {"coordinates":[-3.8713328838,40.4706802368],"type":"Point"}
}