{
  "type": "Feature",
  "properties": {
    "addr:full":"Avda Sinforiano Madro\u00d1ero, 18 Badajoz Badajoz 06011",
    "addr:housenumber":"18",
    "addr:postcode":"06011",
    "addr:street":"Avda Sinforiano Madron\u0303Ero",
    "iso:country":"ES",
    "sg:address":"Avda Sinforiano Madro\u00d1ero, 18",
    "sg:city":"Badajoz",
    "sg:orig_category":"Alquiler De V\u00cddeo",
    "sg:phone":"+34 924 23 67 06",
    "sg:postcode":"06011",
    "sg:province":"Badajoz",
    "wof:name":"Alsu Vision S.l.",
    "wof:placetype":"venue"
},
  "geometry": {"coordinates":[-6.9865069389,38.867565155],"type":"Point"}
}