{
  "type": "Feature",
  "properties": {
    "addr:full":"Avda Arboleda (de La), 17 Escorial Madrid 28280",
    "addr:housenumber":"17",
    "addr:postcode":"28280",
    "addr:street":"Avda Arboleda De La",
    "iso:country":"ES",
    "sg:address":"Avda Arboleda (de La), 17",
    "sg:city":"Escorial",
    "sg:orig_category":"Reposter\u00cdas",
    "sg:phone":"+34 918 90 01 02",
    "sg:postcode":"28280",
    "sg:province":"Madrid",
    "wof:name":"Iglesias Bernaldo De Quiros Jose",
    "wof:placetype":"venue"
},
  "geometry": {"coordinates":[-4.1300368309,40.5833930969],"type":"Point"}
}