{
  "type": "Feature",
  "properties": {
    "addr:full":"Calle de Canalejas, 8 Logro\u00f1o La Rioja 26005",
    "addr:housenumber":"8",
    "addr:postcode":"26005",
    "addr:street":"Calle De Canalejas;Rioja",
    "iso:country":"ES",
    "sg:address":"Calle de Canalejas, 8",
    "sg:city":"Logro\u00f1o",
    "sg:orig_category":"Organizaci\u00d3n De Actos, Seminarios Y Congresos",
    "sg:phone":"+34 941 21 46 33",
    "sg:postcode":"26005",
    "sg:province":"La Rioja",
    "wof:name":"Planner Organizacion De Congresos S.l.",
    "wof:placetype":"venue"
},
  "geometry": {"coordinates":[-2.453548193,42.4665374756],"type":"Point"}
}