{
  "type": "Feature",
  "properties": {
    "iso:country":"ES",
    "sg:address":"Calle de Gascos (los), 18",
    "sg:city":"Segovia",
    "sg:orig_category":"Sindicatos Y Colegios Profesionales",
    "sg:phone":"+34 921 42 54 63",
    "sg:postcode":"40003",
    "sg:province":"Segovia",
    "wof:name":"Asociacion Autonoma De Instaladores Fontaneros De Segovia Y Provincia",
    "wof:placetype":"venue"
},
  "geometry": {"coordinates":[-4.1157865524,40.9492263794],"type":"Point"}
}