{
  "type": "Feature",
  "properties": {
    "addr:full":"Av Ramon I Cajal, 23 Tarragona Tarragona 43001",
    "addr:housenumber":"23",
    "addr:postcode":"43001",
    "addr:street":"Av Ramon I Cajal",
    "iso:country":"ES",
    "sg:address":"Av Ramon I Cajal, 23",
    "sg:city":"Tarragona",
    "sg:orig_category":"Fabricaci\u00d3n De Peines Y De Accesorios De Peluquer\u00cda",
    "sg:phone":"+34 977 24 56 94",
    "sg:postcode":"43001",
    "sg:province":"Tarragona",
    "wof:name":"Repollo Santiago Cristobal",
    "wof:placetype":"venue"
},
  "geometry": {"coordinates":[1.2474060059,41.1164932251],"type":"Point"}
}