{
  "type": "Feature",
  "properties": {
    "addr:full":"Avda Calvo Sotelo, 4 Belchite Zaragoza 50130",
    "addr:housenumber":"4",
    "addr:postcode":"50130",
    "addr:street":"Avda Calvo Sotelo",
    "iso:country":"ES",
    "sg:address":"Avda Calvo Sotelo, 4",
    "sg:city":"Belchite",
    "sg:orig_category":"Electricidad Veh\u00cdculo",
    "sg:phone":"+34 976 83 04 32",
    "sg:postcode":"50130",
    "sg:province":"Zaragoza",
    "wof:name":"Ganados Los Pajareros S.l.",
    "wof:placetype":"venue"
},
  "geometry": {"coordinates":[-0.7540720105,41.3040313721],"type":"Point"}
}