{
  "type": "Feature",
  "properties": {
    "addr:full":"Carrer de Ateneu (l'), 28 Vilafranca Penedes Barcelona 08720",
    "addr:housenumber":"28",
    "addr:postcode":"08720",
    "addr:street":"Carrer De Ateneu L ';Penedes Barcelona",
    "iso:country":"ES",
    "sg:address":"Carrer de Ateneu (l'), 28",
    "sg:city":"Vilafranca Penedes",
    "sg:classifiers":[
        {
            "category":"Personal",
            "subcategory":"Barber",
            "type":"Services"
        }
    ],
    "sg:phone":"+34 938 90 03 96",
    "sg:postcode":"08720",
    "sg:province":"Barcelona",
    "sg:tags":[
        "caballeros",
        "de",
        "peluqueros"
    ],
    "wof:name":"Jimenez Diaz Francisco",
    "wof:placetype":"venue"
},
  "geometry": {"coordinates":[1.6992499828,41.3423614502],"type":"Point"}
}