{
  "type": "Feature",
  "properties": {
    "iso:country":"ES",
    "sg:address":"Plaz Mayor, 1",
    "sg:city":"Estadilla",
    "sg:orig_category":"Ense\u00d1anza, Formaci\u00d3n Profesional: Aprendizaje",
    "sg:phone":"+34 974 30 50 00",
    "sg:postcode":"22423",
    "sg:province":"Huesca",
    "wof:name":"Ayuntamiento De Estadilla",
    "wof:placetype":"venue"
},
  "geometry": {"coordinates":[0.2439990044,42.056224823],"type":"Point"}
}