{
  "type": "Feature",
  "properties": {
    "iso:country":"ES",
    "sg:address":"Calle de Grande, 16",
    "sg:city":"Guare\u00f1a",
    "sg:orig_category":"\u00d3ptica: Instrumentos (fabricaci\u00d3n)",
    "sg:phone":"+34 924 35 14 00",
    "sg:postcode":"06470",
    "sg:province":"Badajoz",
    "wof:name":"Centro Optico Guare\u00f1a",
    "wof:placetype":"venue"
},
  "geometry": {"coordinates":[-6.1017289162,38.8589477539],"type":"Point"}
}