{
  "type": "Feature",
  "properties": {
    "iso:country":"ES",
    "sg:address":"Calle de Via Complutense, 21",
    "sg:city":"Alcala Henares",
    "sg:orig_category":"Muebles Y Accesorios Para Cocinas Y Cuartos De Ba\u00d1o (al Por Menor)",
    "sg:phone":"+34 918 83 64 64",
    "sg:postcode":"28807",
    "sg:province":"Madrid",
    "wof:name":"Azahar Cocina Y Ba\u00f1o S.l.",
    "wof:placetype":"venue"
},
  "geometry": {"coordinates":[-3.3668758869,40.4846076965],"type":"Point"}
}