{
  "type": "Feature",
  "properties": {
    "iso:country":"ES",
    "sg:address":"Avda Calvo Sotelo (de), 12",
    "sg:city":"Carballi\u00f1o",
    "sg:orig_category":"Molduras, Junquillos, Listones Y Molduras Perforadas",
    "sg:phone":"+34 988 27 00 18",
    "sg:postcode":"32500",
    "sg:province":"Ourense",
    "wof:name":"Telefourense S.l.",
    "wof:placetype":"venue"
},
  "geometry": {"coordinates":[-8.0803747177,42.4276580811],"type":"Point"}
}