{
  "type": "Feature",
  "properties": {
    "iso:country":"ES",
    "sg:address":"Rbla Onze De Setembre, 62",
    "sg:city":"Barcelona",
    "sg:orig_category":"Peluquer\u00cdas, Peluquer\u00cda Mixta",
    "sg:phone":"+34 933 46 88 55",
    "sg:postcode":"08030",
    "sg:province":"Barcelona",
    "wof:name":"M.i. Roca Perruquers S.l.",
    "wof:placetype":"venue"
},
  "geometry": {"coordinates":[2.1919209957,41.4303016663],"type":"Point"}
}