{
  "type": "Feature",
  "properties": {
    "iso:country":"ES",
    "sg:address":"Calle de Martin Alonso Pinzon, 10",
    "sg:city":"Sevilla",
    "sg:orig_category":"M\u00c9dicos: Endocrinolog\u00cda Y Metabolismo",
    "sg:phone":"+34 954 51 15 69",
    "sg:postcode":"41007",
    "sg:province":"Sevilla",
    "wof:name":"Leal Cerro Alfonso",
    "wof:placetype":"venue"
},
  "geometry": {"coordinates":[-5.9544639587,37.4015884399],"type":"Point"}
}