{
  "type": "Feature",
  "properties": {
    "addr:full":"Desvio Distante, S/n Inca Islas Baleares 07300",
    "addr:housenumber":"s / n",
    "addr:postcode":"07300",
    "iso:country":"ES",
    "sg:address":"Desvio Distante, S/n",
    "sg:city":"Inca",
    "sg:orig_category":"Agentes, Concesionarios Y Sucursales De Veh\u00cdculos",
    "sg:phone":"+34 971 88 32 07",
    "sg:postcode":"07300",
    "sg:province":"Islas Baleares",
    "wof:name":"Auto Freno Oliver S.a.",
    "wof:placetype":"venue"
},
  "geometry": {"coordinates":[2.9091899395,39.7197418213],"type":"Point"}
}