{
  "type": "Feature",
  "properties": {
    "iso:country":"ES",
    "sg:address":"Calle de San Martin, 46",
    "sg:city":"Donostia-san Sebastian",
    "sg:orig_category":"Inmobiliaria (agencias)",
    "sg:phone":"+34 943 46 82 66",
    "sg:postcode":"20005",
    "sg:province":"Guip\u00f9zcoa",
    "wof:name":"Loinorte S.l.",
    "wof:placetype":"venue"
},
  "geometry": {"coordinates":[-1.9837390184,43.3167495728],"type":"Point"}
}