{
  "type": "Feature",
  "properties": {
    "iso:country":"ES",
    "sg:address":"Calle de Portuetxe, 39",
    "sg:city":"Donostia-san Sebastian",
    "sg:orig_category":"Asesor\u00cdas Y Estudios Financieros",
    "sg:phone":"+34 943 22 48 19",
    "sg:postcode":"20018",
    "sg:province":"Guip\u00f9zcoa",
    "wof:name":"Novoa Redondo Arantza",
    "wof:placetype":"venue"
},
  "geometry": {"coordinates":[-2.0123400688,43.3020324707],"type":"Point"}
}