{
  "type": "Feature",
  "properties": {
    "iso:country":"ES",
    "sg:address":"Calle de Rio Taju\u00d1a, S/n",
    "sg:city":"Alcala Henares",
    "sg:orig_category":"Limpieza Industrial",
    "sg:phone":"+34 918 82 47 74",
    "sg:postcode":"28803",
    "sg:province":"Madrid",
    "wof:name":"Carrasco Giron Sebastian",
    "wof:placetype":"venue"
},
  "geometry": {"coordinates":[-3.3627688885,40.4691963196],"type":"Point"}
}