{
  "type": "Feature",
  "properties": {
    "iso:country":"ES",
    "sg:address":"Cmno Aurin (de), 10",
    "sg:city":"Sabi\u00f1anigo",
    "sg:orig_category":"Maquinaria Para Industrias Diversas",
    "sg:phone":"+34 974 48 08 30",
    "sg:postcode":"22600",
    "sg:province":"Huesca",
    "wof:name":"Mecanizados Y Ajuste Pirineo S.a.l.",
    "wof:placetype":"venue"
},
  "geometry": {"coordinates":[-0.3513957858,42.521812439],"type":"Point"}
}