{
  "type": "Feature",
  "properties": {
    "iso:country":"ES",
    "sg:address":"Carrer de Alzina, 35",
    "sg:city":"Palma",
    "sg:orig_category":"Empresas De Carpinter\u00cda",
    "sg:phone":"+34 971 73 74 12",
    "sg:postcode":"07014",
    "sg:province":"Islas Baleares",
    "wof:name":"Lluch Llull Pedro",
    "wof:placetype":"venue"
},
  "geometry": {"coordinates":[2.6296160221,39.5762367249],"type":"Point"}
}