{
  "type": "Feature",
  "properties": {
    "addr:full":"Libertad, S/n Tuineje Las Palmas 35628",
    "addr:housenumber":"s / n",
    "addr:postcode":"35628",
    "addr:street":"Libertad",
    "iso:country":"ES",
    "sg:address":"Libertad, S/n",
    "sg:city":"Tuineje",
    "sg:orig_category":"Producci\u00d3n, Venta De Productos De Agricultura Biol\u00d3gica",
    "sg:phone":"+34 928 16 41 29",
    "sg:postcode":"35628",
    "sg:province":"Las Palmas",
    "wof:name":"Sociedad Agraria De Transformacion Salinas S.a.",
    "wof:placetype":"venue"
},
  "geometry": {"coordinates":[-14.0489139557,28.3267745972],"type":"Point"}
}