{
  "type": "Feature",
  "properties": {
    "iso:country":"ES",
    "sg:address":"Calle de Libertad, 32",
    "sg:city":"Pola De Laviana",
    "sg:orig_category":"Armas Y Municiones (fabricaci\u00d3n, Al Por Mayor)",
    "sg:phone":"+34 985 60 09 83",
    "sg:postcode":"33980",
    "sg:province":"Asturias",
    "wof:name":"Trelles Blanco Moises",
    "wof:placetype":"venue"
},
  "geometry": {"coordinates":[-5.5624489784,43.2470397949],"type":"Point"}
}