{
  "type": "Feature",
  "properties": {
    "iso:country":"ES",
    "sg:address":"Avda Constitucion, 62",
    "sg:city":"Villena",
    "sg:orig_category":"Ropa Para Ni\u00d1os (al Por Menor)",
    "sg:phone":"+34 965 80 82 41",
    "sg:postcode":"03400",
    "sg:province":"Alicante",
    "wof:name":"Sanjuan Ribera Cecilia",
    "wof:placetype":"venue"
},
  "geometry": {"coordinates":[-0.8651319742,38.6346511841],"type":"Point"}
}