{
  "type": "Feature",
  "properties": {
    "addr:full":"Plaz Fuensanta, 2 San Miguel Murcia 30008",
    "addr:postcode":"30008",
    "addr:street":"Fuensanta",
    "iso:country":"ES",
    "sg:address":"Plaz Fuensanta, 2",
    "sg:city":"San Miguel",
    "sg:orig_category":"Inmobiliaria (agencias)",
    "sg:phone":"+34 968 20 21 91",
    "sg:postcode":"30008",
    "sg:province":"Murcia",
    "sg:website":"www.grupohispania.com",
    "wof:name":"Grupo Inversor Hispania S.a.",
    "wof:placetype":"venue"
},
  "geometry": {"coordinates":[-1.1225090027,37.9928436279],"type":"Point"}
}