{
  "type": "Feature",
  "properties": {
    "iso:country":"ES",
    "sg:address":"Calle de Alfonso I, 4",
    "sg:city":"Piedras Blancas",
    "sg:orig_category":"Asociaciones Y Clubs Deportivos",
    "sg:phone":"+34 985 53 03 34",
    "sg:postcode":"33450",
    "sg:province":"Asturias",
    "wof:name":"Nuevo Azpiri I\u00f1igo",
    "wof:placetype":"venue"
},
  "geometry": {"coordinates":[-5.9733605385,43.5603141785],"type":"Point"}
}