{
  "type": "Feature",
  "properties": {
    "iso:country":"ES",
    "sg:address":"Calle de Lapuyade, 3",
    "sg:city":"Zaragoza",
    "sg:orig_category":"Comerciantes Al Por Mayor De Vinos, Licores Y Alcoholes",
    "sg:phone":"+34 976 27 69 24",
    "sg:postcode":"50007",
    "sg:province":"Zaragoza",
    "wof:name":"Vicente Corbaton Mariano",
    "wof:placetype":"venue"
},
  "geometry": {"coordinates":[-0.8839280009,41.6362609863],"type":"Point"}
}