{
  "type": "Feature",
  "properties": {
    "iso:country":"ES",
    "sg:address":"Trva San Ignacio, 45",
    "sg:city":"Marchena",
    "sg:orig_category":"Mec\u00c1nico Del Autom\u00d3vil",
    "sg:phone":"+34 954 84 31 75",
    "sg:postcode":"41620",
    "sg:province":"Sevilla",
    "wof:name":"Talleres Baranco Diaz S.l.",
    "wof:placetype":"venue"
},
  "geometry": {"coordinates":[-5.4159379005,37.3229827881],"type":"Point"}
}