{
  "type": "Feature",
  "properties": {
    "iso:country":"ES",
    "sg:address":"Calle de Madrilas, 2",
    "sg:city":"Ciudad Real",
    "sg:orig_category":"Peluquer\u00cdas, Peluquer\u00cda Mixta",
    "sg:phone":"+34 926 25 58 80",
    "sg:postcode":"13004",
    "sg:province":"Ciudad Real",
    "wof:name":"Evangelina Nieto Martinez Y Bego\u00f1a Nieto Martinez Cdad",
    "wof:placetype":"venue"
},
  "geometry": {"coordinates":[-3.924339056,38.9847984314],"type":"Point"}
}