{
  "type": "Feature",
  "properties": {
    "addr:full":"Carrer de Tres Creus, 115 Sabadell Barcelona 08202",
    "addr:housenumber":"115",
    "addr:postcode":"08202",
    "addr:street":"Carrer De Tres Creus",
    "iso:country":"ES",
    "sg:address":"Carrer de Tres Creus, 115",
    "sg:city":"Sabadell",
    "sg:orig_category":"Caf\u00c9s, Bares, Cervecer\u00cdas",
    "sg:phone":"+34 937 26 60 12",
    "sg:postcode":"08202",
    "sg:province":"Barcelona",
    "wof:name":"Saura Alcarazo Ricardo",
    "wof:placetype":"venue"
},
  "geometry": {"coordinates":[2.1139578819,41.5463256836],"type":"Point"}
}