{
  "type": "Feature",
  "properties": {
    "iso:country":"ES",
    "sg:address":"Calle de San Pedro, 25",
    "sg:city":"Medina Rioseco",
    "sg:orig_category":"Empresas De Pintura Y Revestimientos",
    "sg:phone":"+34 983 70 03 40",
    "sg:postcode":"47800",
    "sg:province":"Valladolid",
    "wof:name":"Alonso Sanchez Antonio",
    "wof:placetype":"venue"
},
  "geometry": {"coordinates":[-5.048058033,41.8846969604],"type":"Point"}
}