{
  "type": "Feature",
  "properties": {
    "iso:country":"ES",
    "sg:address":"Calle de Manteria, 26",
    "sg:city":"Valladolid",
    "sg:orig_category":"Ropa Para Se\u00d1oras (al Por Menor)",
    "sg:phone":"+34 983 39 03 31",
    "sg:postcode":"47004",
    "sg:province":"Valladolid",
    "wof:name":"Martin Fernandez Maria Teresa",
    "wof:placetype":"venue"
},
  "geometry": {"coordinates":[-4.7222328186,41.6485023499],"type":"Point"}
}