{
  "type": "Feature",
  "properties": {
    "iso:country":"ES",
    "sg:address":"Calle de G(san Rafael), 27",
    "sg:city":"Hellin",
    "sg:orig_category":"Aspiradoras Industriales",
    "sg:phone":"+34 967 54 30 49",
    "sg:postcode":"02400",
    "sg:province":"Albacete",
    "wof:name":"Aspiraciones Valen S.l.",
    "wof:placetype":"venue"
},
  "geometry": {"coordinates":[-1.7024521828,38.5132217407],"type":"Point"}
}