{
  "type": "Feature",
  "properties": {
    "iso:country":"ES",
    "sg:address":"Calle de Fuenterrabia, 1",
    "sg:city":"Donostia-san Sebastian",
    "sg:orig_category":"\u00d3ptica: Instrumentos (fabricaci\u00d3n)",
    "sg:phone":"+34 943 42 86 91",
    "sg:postcode":"20005",
    "sg:province":"Guip\u00f9zcoa",
    "wof:name":"Ignacio Garmendia Uribarri Y Otro Cdad",
    "wof:placetype":"venue"
},
  "geometry": {"coordinates":[-1.9821439981,43.3190994263],"type":"Point"}
}