{
  "type": "Feature",
  "properties": {
    "addr:full":"Carr S Magi, 41 Igualada Barcelona 08700",
    "addr:housenumber":"41",
    "addr:postcode":"08700",
    "addr:street":"Carr S Magi",
    "iso:country":"ES",
    "sg:address":"Carr S Magi, 41",
    "sg:city":"Igualada",
    "sg:orig_category":"Cr\u00cda De Animales",
    "sg:phone":"+34 938 03 64 15",
    "sg:postcode":"08700",
    "sg:province":"Barcelona",
    "wof:name":"Mas Llopart Sandra",
    "wof:placetype":"venue"
},
  "geometry": {"coordinates":[1.6163909435,41.5809211731],"type":"Point"}
}