{
  "type": "Feature",
  "properties": {
    "addr:full":"Avda Vicente Aleixandre, 3 Segovia Segovia 40006",
    "addr:housenumber":"3",
    "addr:postcode":"40006",
    "addr:street":"Avda Vicente Aleixandre",
    "iso:country":"ES",
    "sg:address":"Avda Vicente Aleixandre, 3",
    "sg:city":"Segovia",
    "sg:orig_category":"Molduras, Junquillos, Listones Y Molduras Perforadas",
    "sg:phone":"+34 921 43 29 08",
    "sg:postcode":"40006",
    "sg:province":"Segovia",
    "wof:name":"Gil Martin Eduardo",
    "wof:placetype":"venue"
},
  "geometry": {"coordinates":[-4.1026854515,40.9322662354],"type":"Point"}
}