{
  "type": "Feature",
  "properties": {
    "addr:full":"Rua San Roque, 17 Celanova Ourense 32800",
    "addr:housenumber":"17",
    "addr:postcode":"32800",
    "addr:street":"Rua San Roque",
    "iso:country":"ES",
    "sg:address":"Rua San Roque, 17",
    "sg:city":"Celanova",
    "sg:orig_category":"Charcuter\u00cdas (al Por Mayor)",
    "sg:phone":"+34 988 43 11 09",
    "sg:postcode":"32800",
    "sg:province":"Ourense",
    "wof:name":"Azpilcueta Seijo Camilo",
    "wof:placetype":"venue"
},
  "geometry": {"coordinates":[-7.958591938,42.1530570984],"type":"Point"}
}