{
  "type": "Feature",
  "properties": {
    "addr:full":"Calle de Acera De La Marina, 2 Marbella M\u00e1laga 29600",
    "addr:housenumber":"2",
    "addr:postcode":"29600",
    "addr:street":"Calle De Acera De La Marina;Ma\u0301Laga",
    "iso:country":"ES",
    "sg:address":"Calle de Acera De La Marina, 2",
    "sg:city":"Marbella",
    "sg:orig_category":"Importaci\u00d3n",
    "sg:phone":"+34 952 86 56 68",
    "sg:postcode":"29600",
    "sg:province":"M\u00e1laga",
    "wof:name":"Vexco S.l.",
    "wof:placetype":"venue"
},
  "geometry": {"coordinates":[-4.8871741295,36.5074386597],"type":"Point"}
}