{
  "type": "Feature",
  "properties": {
    "iso:country":"ES",
    "sg:address":"Carrer de Dalmau, 26",
    "sg:city":"Santa Coloma De Gramenet",
    "sg:orig_category":"Colchones (fabricaci\u00d3n, Al Por Mayor, Al Por Menor)",
    "sg:phone":"+34 933 92 63 06",
    "sg:postcode":"08922",
    "sg:province":"Barcelona",
    "wof:name":"Gonzalez Cabeza Francisca",
    "wof:placetype":"venue"
},
  "geometry": {"coordinates":[2.2179660797,41.450088501],"type":"Point"}
}