{
  "type": "Feature",
  "properties": {
    "iso:country":"ES",
    "sg:address":"Calle de Mayor, 391",
    "sg:city":"Raal",
    "sg:orig_category":"Inform\u00c1tica (estudios, Servicios, Asesor\u00cda, Formaci\u00d3n)",
    "sg:phone":"+34 968 87 09 70",
    "sg:postcode":"30139",
    "sg:province":"Murcia",
    "sg:website":"www.inforlistin.com",
    "wof:name":"Marin Munuera Antonio Cesar",
    "wof:placetype":"venue"
},
  "geometry": {"coordinates":[-1.025028944,38.0419311523],"type":"Point"}
}