{
  "type": "Feature",
  "properties": {
    "addr:full":"Avda Blasco Iba\u00d1ez, 28 Valencia Valencia 46010",
    "addr:housenumber":"28",
    "addr:postcode":"46010",
    "addr:street":"Avda Blasco Iban\u0303Ez",
    "iso:country":"ES",
    "sg:address":"Avda Blasco Iba\u00d1ez, 28",
    "sg:city":"Valencia",
    "sg:orig_category":"Caf\u00c9s, Bares, Cervecer\u00cdas",
    "sg:phone":"+34 963 89 18 62",
    "sg:postcode":"46010",
    "sg:province":"Valencia",
    "wof:name":"Valero Y Perez S.l.",
    "wof:placetype":"venue"
},
  "geometry": {"coordinates":[-0.3614490032,39.4775161743],"type":"Point"}
}