{
  "type": "Feature",
  "properties": {
    "addr:full":"Carrer de Barcelona, 2 Hospitalet Llobregat Barcelona 08901",
    "addr:housenumber":"2",
    "addr:postcode":"08901",
    "addr:street":"Carrer De Barcelona",
    "iso:country":"ES",
    "sg:address":"Carrer de Barcelona, 2",
    "sg:city":"Hospitalet Llobregat",
    "sg:orig_category":"Tintorer\u00cdas, Limpieza En Seco",
    "sg:phone":"+34 932 61 07 85",
    "sg:postcode":"08901",
    "sg:province":"Barcelona",
    "wof:name":"Minit Spain S. A.",
    "wof:placetype":"venue"
},
  "geometry": {"coordinates":[2.1044960022,41.3615684509],"type":"Point"}
}