{
  "type": "Feature",
  "properties": {
    "addr:full":"Calle de Farmaceutico Miguel Padilla, S/n Palmas De Gran Canaria Las Palmas 35012",
    "addr:housenumber":"s",
    "addr:postcode":"35012",
    "addr:street":"Calle De Farmaceutico Miguel Padilla;/ N",
    "iso:country":"ES",
    "sg:address":"Calle de Farmaceutico Miguel Padilla, S/n",
    "sg:city":"Palmas De Gran Canaria",
    "sg:orig_category":"Bazares, Art\u00cdculos De Limpieza Y De Cocina (al Por Menor)",
    "sg:phone":"+34 928 20 91 53",
    "sg:postcode":"35012",
    "sg:province":"Las Palmas",
    "wof:name":"Perez Ribero Francisco",
    "wof:placetype":"venue"
},
  "geometry": {"coordinates":[-15.4403820038,28.1040325165],"type":"Point"}
}