{
  "type": "Feature",
  "properties": {
    "addr:full":"Carrer de Cala Crancs (de La), 13 Cap De Salou-nostra Senyora De Nuria Tarragona 43840",
    "addr:housenumber":"13",
    "addr:postcode":"43840",
    "addr:street":"Carrer De Cala Crancs De La",
    "iso:country":"ES",
    "sg:address":"Carrer de Cala Crancs (de La), 13",
    "sg:city":"Cap De Salou-nostra Senyora De Nuria",
    "sg:orig_category":"Centros Empresariales",
    "sg:phone":"+34 977 37 12 36",
    "sg:postcode":"43840",
    "sg:province":"Tarragona",
    "wof:name":"Integra S.c.",
    "wof:placetype":"venue"
},
  "geometry": {"coordinates":[1.1675900221,41.0587463379],"type":"Point"}
}