{
  "type": "Feature",
  "properties": {
    "addr:full":"Pl Narcis Oller, 6 Barcelona Barcelona 08006",
    "addr:housenumber":"6",
    "addr:postcode":"08006",
    "addr:street":"Narcis Oller",
    "iso:country":"ES",
    "sg:address":"Pl Narcis Oller, 6",
    "sg:city":"Barcelona",
    "sg:orig_category":"Inform\u00c1tica (estudios, Servicios, Asesor\u00cda, Formaci\u00d3n)",
    "sg:phone":"+34 932 92 22 12",
    "sg:postcode":"08006",
    "sg:province":"Barcelona",
    "sg:website":"www.tecman.es",
    "wof:name":"Tecman Serveis Informatics S.l.",
    "wof:placetype":"venue"
},
  "geometry": {"coordinates":[2.1555469036,41.3972091675],"type":"Point"}
}