{
  "type": "Feature",
  "properties": {
    "addr:full":"Rua Elduayen, 16 Vigo Pontevedra 36202",
    "addr:housenumber":"16",
    "addr:postcode":"36202",
    "addr:street":"Rua Elduayen",
    "iso:country":"ES",
    "sg:address":"Rua Elduayen, 16",
    "sg:city":"Vigo",
    "sg:orig_category":"Lencer\u00cda Femenina, Corseter\u00cda, Trajes De Ba\u00d1o (al Por Menor)",
    "sg:phone":"+34 986 43 96 78",
    "sg:postcode":"36202",
    "sg:province":"Pontevedra",
    "wof:name":"Feijoo Martinez Gerardo",
    "wof:placetype":"venue"
},
  "geometry": {"coordinates":[-8.7271280289,42.2381362915],"type":"Point"}
}