{
  "type": "Feature",
  "properties": {
    "addr:full":"Calle de Principal, 60 Boiro La Coru\u00f1a 15930",
    "addr:housenumber":"60",
    "addr:postcode":"15930",
    "addr:street":"Calle De Principal;La Corun\u0303A",
    "iso:country":"ES",
    "sg:address":"Calle de Principal, 60",
    "sg:city":"Boiro",
    "sg:orig_category":"Cajas De Ahorro",
    "sg:phone":"+34 981 84 27 50",
    "sg:postcode":"15930",
    "sg:province":"La Coru\u00f1a",
    "wof:name":"Caixa De Aforros De Vigo Ourense E Pontevedra",
    "wof:placetype":"venue"
},
  "geometry": {"coordinates":[-8.8816537857,42.6479148865],"type":"Point"}
}