{
  "type": "Feature",
  "properties": {
    "iso:country":"ES",
    "sg:address":"Carr Portal, 4",
    "sg:city":"Igualada",
    "sg:orig_category":"Agricultura: Abastecimiento Y Cosechado (negocio)",
    "sg:phone":"+34 938 03 09 17",
    "sg:postcode":"08700",
    "sg:province":"Barcelona",
    "wof:name":"Comarcal Agropecuaria De Igualada",
    "wof:placetype":"venue"
},
  "geometry": {"coordinates":[1.6323850155,41.5766448975],"type":"Point"}
}