{
  "type": "Feature",
  "properties": {
    "iso:country":"ES",
    "sg:address":"Carretera Blanes-lloret, S/n",
    "sg:city":"Lloret Mar",
    "sg:orig_category":"Paisajistas Asesor\u00cda",
    "sg:phone":"+34 972 36 32 18",
    "sg:postcode":"17310",
    "sg:province":"Girona",
    "wof:name":"Pisci Jardi Construccions S.l.",
    "wof:placetype":"venue"
},
  "geometry": {"coordinates":[2.846834898,41.6981697083],"type":"Point"}
}