{
  "type": "Feature",
  "properties": {
    "addr:full":"Avda Isabel Ii De, 25 Donostia-san Sebastian Guip\u00f9zcoa 20011",
    "addr:housenumber":"25",
    "addr:postcode":"20011",
    "addr:street":"Avda Isabel Ii De",
    "iso:country":"ES",
    "sg:address":"Avda Isabel Ii De, 25",
    "sg:city":"Donostia-san Sebastian",
    "sg:orig_category":"Farmacias",
    "sg:phone":"+34 943 45 83 40",
    "sg:postcode":"20011",
    "sg:province":"Guip\u00f9zcoa",
    "wof:name":"Santamaria Aguirre Maria Pilar",
    "wof:placetype":"venue"
},
  "geometry": {"coordinates":[-1.9774659872,43.3035697937],"type":"Point"}
}