{
  "type": "Feature",
  "properties": {
    "addr:full":"Av Espanya, S/n Palafrugell Girona 17200",
    "addr:housenumber":"s / n",
    "addr:postcode":"17200",
    "addr:street":"Av Espanya",
    "iso:country":"ES",
    "sg:address":"Av Espanya, S/n",
    "sg:city":"Palafrugell",
    "sg:orig_category":"Flores Y Plantas Naturales (al Por Mayor)",
    "sg:phone":"+34 972 30 62 34",
    "sg:postcode":"17200",
    "sg:province":"Girona",
    "wof:name":"Clavaguera Carbo Josep",
    "wof:placetype":"venue"
},
  "geometry": {"coordinates":[3.1621220112,41.9098243713],"type":"Point"}
}