{
  "type": "Feature",
  "properties": {
    "addr:full":"Bajo El Otero, 1 Guardo Palencia 34880",
    "addr:housenumber":"1",
    "addr:postcode":"34880",
    "addr:street":"El Otero",
    "iso:country":"ES",
    "sg:address":"Bajo El Otero, 1",
    "sg:city":"Guardo",
    "sg:orig_category":"Peluquer\u00cdas, Peluquer\u00cda Mixta",
    "sg:phone":"+34 979 85 28 54",
    "sg:postcode":"34880",
    "sg:province":"Palencia",
    "sg:website":"www.paginasamarillas.es",
    "wof:name":"Estetica Matices S.l.",
    "wof:placetype":"venue"
},
  "geometry": {"coordinates":[-4.8420028687,42.7900505066],"type":"Point"}
}