{
  "type": "Feature",
  "properties": {
    "iso:country":"ES",
    "sg:address":"Calle de Creu (la), 47",
    "sg:city":"Banyeres Mariola",
    "sg:orig_category":"Electromec\u00c1nica",
    "sg:phone":"+34 966 56 76 37",
    "sg:postcode":"03450",
    "sg:province":"Alicante",
    "wof:name":"Jorda Reig Angel",
    "wof:placetype":"venue"
},
  "geometry": {"coordinates":[-0.656175375,38.7181777954],"type":"Point"}
}