{
  "type": "Feature",
  "properties": {
    "addr:full":"Calle de Egido, 38 Villanueva Cordoba C\u00f3rdoba 14440",
    "addr:housenumber":"38;cordoba co\u0301rdoba",
    "addr:postcode":"14440",
    "addr:street":"Calle De Egido",
    "iso:country":"ES",
    "sg:address":"Calle de Egido, 38",
    "sg:city":"Villanueva Cordoba",
    "sg:orig_category":"Molduras, Junquillos, Listones Y Molduras Perforadas",
    "sg:phone":"+34 957 12 13 12",
    "sg:postcode":"14440",
    "sg:province":"C\u00f3rdoba",
    "wof:name":"Gomez Silva Sebastian",
    "wof:placetype":"venue"
},
  "geometry": {"coordinates":[-4.7791519165,37.884727478],"type":"Point"}
}