{
  "type": "Feature",
  "properties": {
    "addr:full":"Av Flora Cadena, 10 Rialp Lleida 25594",
    "addr:housenumber":"10",
    "addr:postcode":"25594",
    "addr:street":"Av Flora Cadena",
    "iso:country":"ES",
    "sg:address":"Av Flora Cadena, 10",
    "sg:city":"Rialp",
    "sg:orig_category":"Armas Y Municiones (fabricaci\u00d3n, Al Por Mayor)",
    "sg:phone":"+34 973 62 03 26",
    "sg:postcode":"25594",
    "sg:province":"Lleida",
    "wof:name":"Sabarich Roset Jose",
    "wof:placetype":"venue"
},
  "geometry": {"coordinates":[1.1351100206,42.4431343079],"type":"Point"}
}