{
  "type": "Feature",
  "properties": {
    "iso:country":"ES",
    "sg:address":"Calle de Pizarro, 21",
    "sg:city":"Alcantarilla",
    "sg:orig_category":"Guarder\u00cdas",
    "sg:phone":"+34 968 89 05 36",
    "sg:postcode":"30820",
    "sg:province":"Murcia",
    "wof:name":"Maria Dolores Y Esperanza Martinez Garcia C.b.",
    "wof:placetype":"venue"
},
  "geometry": {"coordinates":[-1.2207030058,37.9637870789],"type":"Point"}
}