{
  "type": "Feature",
  "properties": {
    "addr:full":"Avda Almirante Loaysa, 17 Flota Murcia 30007",
    "addr:housenumber":"17",
    "addr:postcode":"30007",
    "addr:street":"Avda Almirante Loaysa",
    "iso:country":"ES",
    "sg:address":"Avda Almirante Loaysa, 17",
    "sg:city":"Flota",
    "sg:orig_category":"Sociedades, Compa\u00d1\u00cdas Aseguradoras",
    "sg:phone":"+34 968 23 33 62",
    "sg:postcode":"30007",
    "sg:province":"Murcia",
    "wof:name":"Luis A.forca S.l.",
    "wof:placetype":"venue"
},
  "geometry": {"coordinates":[-1.1142389774,37.9970092773],"type":"Point"}
}