{
  "type": "Feature",
  "properties": {
    "addr:full":"Ptda Carrus, S/n Elche Alicante 03205",
    "addr:housenumber":"s / n",
    "addr:postcode":"03205",
    "addr:street":"Ptda Carrus",
    "iso:country":"ES",
    "sg:address":"Ptda Carrus, S/n",
    "sg:city":"Elche",
    "sg:orig_category":"Herramientas Y Suministros Para Plomeros",
    "sg:phone":"+34 965 46 12 05",
    "sg:postcode":"03205",
    "sg:province":"Alicante",
    "wof:name":"Aigues I Sanejament Elx",
    "wof:placetype":"venue"
},
  "geometry": {"coordinates":[-0.743776083,38.2826004028],"type":"Point"}
}