{
  "type": "Feature",
  "properties": {
    "addr:full":"Av Icaria, 138 Barcelona Barcelona 08005",
    "addr:housenumber":"138",
    "addr:postcode":"08005",
    "addr:street":"Av Icaria",
    "iso:country":"ES",
    "sg:address":"Av Icaria, 138",
    "sg:city":"Barcelona",
    "sg:orig_category":"Bancos",
    "sg:phone":"+34 932 21 11 00",
    "sg:postcode":"08005",
    "sg:province":"Barcelona",
    "wof:name":"Banco Bilbao Vizcaya Argentaria S.a.",
    "wof:placetype":"venue"
},
  "geometry": {"coordinates":[2.1956140995,41.3897399902],"type":"Point"}
}