{
  "type": "Feature",
  "properties": {
    "iso:country":"ES",
    "sg:address":"Calle de Acoran, S/n",
    "sg:city":"Acoran",
    "sg:orig_category":"Inmobiliaria (agencias)",
    "sg:phone":"+34 922 68 58 99",
    "sg:postcode":"38109",
    "sg:province":"Santa Cruz De Tenerife",
    "wof:name":"Canariense De Urbanizacion S.a.",
    "wof:placetype":"venue"
},
  "geometry": {"coordinates":[-16.2548561096,28.4698104858],"type":"Point"}
}