{
  "type": "Feature",
  "properties": {
    "iso:country":"ES",
    "sg:address":"Calle de Pe\u00d1a Trevinca, 16",
    "sg:city":"Zamora",
    "sg:orig_category":"Fabricaci\u00d3n De Juguetes Autom\u00c1ticos",
    "sg:phone":"+34 980 51 03 71",
    "sg:postcode":"49024",
    "sg:province":"Zamora",
    "wof:name":"Operadora Castilla Sociedad Anonima",
    "wof:placetype":"venue"
},
  "geometry": {"coordinates":[-5.7498707771,41.5147705078],"type":"Point"}
}