{
  "type": "Feature",
  "properties": {
    "iso:country":"ES",
    "sg:address":"Calle de Cervantes, 12",
    "sg:city":"Anchuras",
    "sg:orig_category":"Cajas Para Embalar",
    "sg:phone":"+34 926 77 30 16",
    "sg:postcode":"13117",
    "sg:province":"Ciudad Real",
    "wof:name":"Caja Rural De Ciudad Real",
    "wof:placetype":"venue"
},
  "geometry": {"coordinates":[-4.8364458084,39.479839325],"type":"Point"}
}