{
  "type": "Feature",
  "properties": {
    "addr:full":"Plaz Manuel Gomez-moreno, S/n Madrid Madrid 28020",
    "addr:housenumber":"s / n",
    "addr:postcode":"28020",
    "iso:country":"ES",
    "sg:address":"Plaz Manuel Gomez-moreno, S/n",
    "sg:city":"Madrid",
    "sg:orig_category":"Empresarios",
    "sg:phone":"+34 915 55 04 30",
    "sg:postcode":"28020",
    "sg:province":"Madrid",
    "wof:name":"Fundetec",
    "wof:placetype":"venue"
},
  "geometry": {"coordinates":[-3.6950740814,40.4479103088],"type":"Point"}
}