{
  "type": "Feature",
  "properties": {
    "iso:country":"ES",
    "sg:address":"Calle de Ingeniero Martin Gil, 26",
    "sg:city":"Cantalejo",
    "sg:orig_category":"Fabricaci\u00d3n, Venta De Cuadros, Accesorios Para Enmarcar",
    "sg:phone":"+34 921 52 01 43",
    "sg:postcode":"40320",
    "sg:province":"Segovia",
    "wof:name":"Anton Velasco Pedro",
    "wof:placetype":"venue"
},
  "geometry": {"coordinates":[-3.9281828403,41.2576217651],"type":"Point"}
}