{
  "type": "Feature",
  "properties": {
    "addr:full":"Carrer de Granio, 23 Terrassa Barcelona 08224",
    "addr:housenumber":"23",
    "addr:postcode":"08224",
    "addr:street":"Carrer De Granio",
    "iso:country":"ES",
    "sg:address":"Carrer de Granio, 23",
    "sg:city":"Terrassa",
    "sg:orig_category":"Aceites Y Grasas Alimentarias (fabricaci\u00d3n, Al Por Mayor)",
    "sg:phone":"+34 937 89 53 53",
    "sg:postcode":"08224",
    "sg:province":"Barcelona",
    "wof:name":"Rubio Ros Enrique",
    "wof:placetype":"venue"
},
  "geometry": {"coordinates":[2.0069899559,41.5629310608],"type":"Point"}
}