{
  "type": "Feature",
  "properties": {
    "iso:country":"ES",
    "sg:address":"Avda Reyes Catolicos, 124",
    "sg:city":"Villarrobledo",
    "sg:orig_category":"Agentes, Concesionarios Y Sucursales De Veh\u00cdculos",
    "sg:phone":"+34 967 14 07 29",
    "sg:postcode":"02600",
    "sg:province":"Albacete",
    "wof:name":"Martinez Ya\u00d1ez E Hijos S.l.",
    "wof:placetype":"venue"
},
  "geometry": {"coordinates":[-2.5916728973,39.2760658264],"type":"Point"}
}