{
  "type": "Feature",
  "properties": {
    "iso:country":"ES",
    "sg:address":"Gustey, 12",
    "sg:city":"Gustei",
    "sg:orig_category":"Reposter\u00cdas",
    "sg:phone":"+34 988 20 40 69",
    "sg:postcode":"32100",
    "sg:province":"Ourense",
    "wof:name":"Novoa Corral Rosario",
    "wof:placetype":"venue"
},
  "geometry": {"coordinates":[-7.852959156,42.3917961121],"type":"Point"}
}