{
  "type": "Feature",
  "properties": {
    "iso:country":"ES",
    "sg:address":"Praj Vadillo, 4",
    "sg:city":"Tobarra",
    "sg:orig_category":"Ense\u00d1anza Agr\u00cdcola",
    "sg:phone":"+34 967 32 54 86",
    "sg:postcode":"02500",
    "sg:province":"Albacete",
    "wof:name":"Polope S.l.",
    "wof:placetype":"venue"
},
  "geometry": {"coordinates":[-1.689489007,38.5949516296],"type":"Point"}
}