{
  "type": "Feature",
  "properties": {
    "addr:full":"Calle de Alonso Nu\u00d1ez, 1 Sanlucar De Barrameda C\u00e1diz 11540",
    "addr:housenumber":"1",
    "addr:postcode":"11540",
    "addr:street":"Calle De Alonso Nun\u0303Ez;Ca\u0301Diz",
    "iso:country":"ES",
    "sg:address":"Calle de Alonso Nu\u00d1ez, 1",
    "sg:city":"Sanlucar De Barrameda",
    "sg:orig_category":"M\u00c9dicos: Estomatolog\u00cda",
    "sg:phone":"+34 956 36 75 09",
    "sg:postcode":"11540",
    "sg:province":"C\u00e1diz",
    "wof:name":"Mera Velasco Alejandro",
    "wof:placetype":"venue"
},
  "geometry": {"coordinates":[-6.3543815613,36.7797050476],"type":"Point"}
}