{
  "type": "Feature",
  "properties": {
    "addr:full":"Pase Canalejas, 11 Santander Cantabria 39004",
    "addr:housenumber":"11",
    "addr:postcode":"39004",
    "addr:street":"Canalejas",
    "iso:country":"ES",
    "sg:address":"Pase Canalejas, 11",
    "sg:city":"Santander",
    "sg:orig_category":"Iglesia Cat\u00d3lica",
    "sg:phone":"+34 942 21 80 10",
    "sg:postcode":"39004",
    "sg:province":"Cantabria",
    "wof:name":"Obispado De Santander",
    "wof:placetype":"venue"
},
  "geometry": {"coordinates":[-3.7955760956,43.4644317627],"type":"Point"}
}