{
  "type": "Feature",
  "properties": {
    "iso:country":"ES",
    "sg:address":"Calle de San Francisco, 49",
    "sg:city":"Bilbao",
    "sg:orig_category":"Bisuter\u00cda, Joyer\u00cda, Relojer\u00cda (al Por Menor)",
    "sg:phone":"+34 944 15 35 90",
    "sg:postcode":"48003",
    "sg:province":"Vizcaya",
    "wof:name":"Herrero Pascual Manuel Antonio",
    "wof:placetype":"venue"
},
  "geometry": {"coordinates":[-2.9293279648,43.2561073303],"type":"Point"}
}