{
  "type": "Feature",
  "properties": {
    "addr:full":"Rua Jose Gomez Posada-curros, 10 Vigo Pontevedra 36203",
    "addr:housenumber":"10",
    "addr:postcode":"36203",
    "addr:street":"Rua Jose Gomez Posada-Curros",
    "iso:country":"ES",
    "sg:address":"Rua Jose Gomez Posada-curros, 10",
    "sg:city":"Vigo",
    "sg:orig_category":"Farmacias",
    "sg:phone":"+34 986 48 45 45",
    "sg:postcode":"36203",
    "sg:province":"Pontevedra",
    "wof:name":"Sande Llovo Patricia",
    "wof:placetype":"venue"
},
  "geometry": {"coordinates":[-8.7256879807,42.2271575928],"type":"Point"}
}