{
  "type": "Feature",
  "properties": {
    "addr:full":"Rbla Principal, 60 Vilanova I La Geltru Barcelona 08800",
    "addr:housenumber":"60",
    "addr:postcode":"08800",
    "addr:street":"Rbla Principal",
    "iso:country":"ES",
    "sg:address":"Rbla Principal, 60",
    "sg:city":"Vilanova I La Geltru",
    "sg:orig_category":"\u00d3ptica: Instrumentos (fabricaci\u00d3n)",
    "sg:phone":"+34 938 93 89 03",
    "sg:postcode":"08800",
    "sg:province":"Barcelona",
    "wof:name":"Reunion Optica S.l.",
    "wof:placetype":"venue"
},
  "geometry": {"coordinates":[1.724848032,41.2237014771],"type":"Point"}
}