{
  "type": "Feature",
  "properties": {
    "addr:full":"Avda Andalucia, 45 Jaen Ja\u00e9n 23006",
    "addr:housenumber":"45;jae\u0301n",
    "addr:postcode":"23006",
    "addr:street":"Avda Andalucia",
    "iso:country":"ES",
    "sg:address":"Avda Andalucia, 45",
    "sg:city":"Jaen",
    "sg:orig_category":"M\u00c9dicos: Oftalmolog\u00cda",
    "sg:phone":"+34 953 25 63 88",
    "sg:postcode":"23006",
    "sg:province":"Ja\u00e9n",
    "wof:name":"Francar Laser S.l.",
    "wof:placetype":"venue"
},
  "geometry": {"coordinates":[-3.8113589287,37.7791099548],"type":"Point"}
}