{
  "type": "Feature",
  "properties": {
    "iso:country":"ES",
    "sg:address":"C/ Sant Antoni, 47",
    "sg:city":"Salt",
    "sg:orig_category":"Panader\u00cdas, Panader\u00cdas",
    "sg:phone":"+34 972 23 18 05",
    "sg:postcode":"17190",
    "sg:province":"Girona",
    "wof:name":"Sant Antoni Pastissers S.l.",
    "wof:placetype":"venue"
},
  "geometry": {"coordinates":[2.798582077,41.9777336121],"type":"Point"}
}