{
  "type": "Feature",
  "properties": {
    "iso:country":"ES",
    "sg:address":"Calle de Real, 29",
    "sg:city":"Villamiel De Mu\u00e7o",
    "sg:orig_category":"Cr\u00cda De Animales",
    "sg:phone":"+34 947 41 20 79",
    "sg:postcode":"09239",
    "sg:province":"Burgos",
    "wof:name":"Florencio Hortiguela Perez Y Otros S.cv.",
    "wof:placetype":"venue"
},
  "geometry": {"coordinates":[-3.8316578865,42.2584991455],"type":"Point"}
}