{
  "type": "Feature",
  "properties": {
    "addr:full":"Autovia Logro\u00f1o P El Olivar, Km. 0008,4 Zaragoza Zaragoza 50011",
    "addr:postcode":"50011",
    "addr:street":"Autovia Logron\u0303O P El Olivar Km. 0008,4",
    "iso:country":"ES",
    "sg:address":"Autovia Logro\u00f1o P El Olivar, Km. 0008,4",
    "sg:city":"Zaragoza",
    "sg:orig_category":"Aceros Inoxidables",
    "sg:phone":"+34 976 46 27 60",
    "sg:postcode":"50011",
    "sg:province":"Zaragoza",
    "wof:name":"Inoxmetal S.a.",
    "wof:placetype":"venue"
},
  "geometry": {"coordinates":[-0.9672325253,41.6833457947],"type":"Point"}
}