{
  "type": "Feature",
  "properties": {
    "iso:country":"ES",
    "sg:address":"Calle de Jose Antonio, 6",
    "sg:city":"Astudillo",
    "sg:orig_category":"Alimentaci\u00d3n General (al Por Menor)",
    "sg:phone":"+34 979 82 23 14",
    "sg:postcode":"34450",
    "sg:province":"Palencia",
    "wof:name":"Aparicio Tejido Esperanza",
    "wof:placetype":"venue"
},
  "geometry": {"coordinates":[-4.2913546562,42.1935310364],"type":"Point"}
}