{
  "type": "Feature",
  "properties": {
    "addr:full":"Calle de Fuenterrabia, 20 Donostia-san Sebastian Guip\u00f9zcoa 20005",
    "addr:housenumber":"20",
    "addr:postcode":"20005",
    "addr:street":"Calle De Fuenterrabia",
    "iso:country":"ES",
    "sg:address":"Calle de Fuenterrabia, 20",
    "sg:city":"Donostia-san Sebastian",
    "sg:orig_category":"Bisuteros (fabricaci\u00d3n, Al Por Mayor)",
    "sg:phone":"+34 943 43 10 09",
    "sg:postcode":"20005",
    "sg:province":"Guip\u00f9zcoa",
    "wof:name":"Alejandro Vallejo C.b",
    "wof:placetype":"venue"
},
  "geometry": {"coordinates":[-1.9816198349,43.3179779053],"type":"Point"}
}