{
  "type": "Feature",
  "properties": {
    "iso:country":"ES",
    "sg:address":"Avda Pilas, 7",
    "sg:city":"Bollullos Mitacion",
    "sg:orig_category":"Electricidad: Instaladores",
    "sg:phone":"+34 955 77 66 52",
    "sg:postcode":"41110",
    "sg:province":"Sevilla",
    "wof:name":"Lopez Mateos Eduardo",
    "wof:placetype":"venue"
},
  "geometry": {"coordinates":[-6.1414737701,37.3562393188],"type":"Point"}
}