{
  "type": "Feature",
  "properties": {
    "iso:country":"ES",
    "sg:address":"Carrer de Nou, 29",
    "sg:city":"Vendrell",
    "sg:orig_category":"Mec\u00c1nico Del Autom\u00d3vil",
    "sg:phone":"+34 977 66 04 83",
    "sg:postcode":"43700",
    "sg:province":"Tarragona",
    "wof:name":"Fernandez Martinez Antonio",
    "wof:placetype":"venue"
},
  "geometry": {"coordinates":[1.5340080261,41.2187080383],"type":"Point"}
}