{
  "type": "Feature",
  "properties": {
    "iso:country":"ES",
    "sg:address":"C/ Mestre Obrador, 9",
    "sg:city":"Ferreries",
    "sg:orig_category":"Transportes Por Carretera: Lotes Completos, Mercanc\u00cdas Diversas",
    "sg:phone":"+34 971 37 41 27",
    "sg:postcode":"07750",
    "sg:province":"Islas Baleares",
    "wof:name":"Distribucions Mercat S.a.",
    "wof:placetype":"venue"
},
  "geometry": {"coordinates":[4.0130028725,39.9844398499],"type":"Point"}
}