{
  "type": "Feature",
  "properties": {
    "addr:full":"Plaz Euskadi, 2 Irun Guip\u00f9zcoa 20305",
    "addr:housenumber":"2",
    "addr:postcode":"20305",
    "addr:street":"Plaz Euskadi;Guipu\u0300Zcoa",
    "iso:country":"ES",
    "sg:address":"Plaz Euskadi, 2",
    "sg:city":"Irun",
    "sg:orig_category":"Telefon\u00cda: Instaladores Varios",
    "sg:phone":"+34 943 63 53 78",
    "sg:postcode":"20305",
    "sg:province":"Guip\u00f9zcoa",
    "wof:name":"Telecomunicaciones Moviles Zaisa S.l.",
    "wof:placetype":"venue"
},
  "geometry": {"coordinates":[-1.7590839863,43.3432312012],"type":"Point"}
}