{
  "type": "Feature",
  "properties": {
    "iso:country":"ES",
    "sg:address":"Carrer de Jaume Pinent, 27",
    "sg:city":"Barcelona",
    "sg:orig_category":"Loter\u00cda Y T\u00d3mbola",
    "sg:phone":"+34 933 50 08 91",
    "sg:postcode":"08042",
    "sg:province":"Barcelona",
    "wof:name":"Lindo Junior Maria Angeles",
    "wof:placetype":"venue"
},
  "geometry": {"coordinates":[2.175786972,41.4464912415],"type":"Point"}
}