{
  "type": "Feature",
  "properties": {
    "iso:country":"ES",
    "sg:address":"Carrer de Llac Quatre Canton, 19",
    "sg:city":"Vileta -son Rapinya",
    "sg:orig_category":"Fabricaci\u00d3n, Instalaci\u00d3n Y Reparaci\u00d3n De Bombas",
    "sg:phone":"+34 971 79 25 09",
    "sg:postcode":"07013",
    "sg:province":"Islas Baleares",
    "wof:name":"Electro Tecno Hidraulica S.l.",
    "wof:placetype":"venue"
},
  "geometry": {"coordinates":[2.6142339706,39.5896873474],"type":"Point"}
}