{
  "type": "Feature",
  "properties": {
    "iso:country":"ES",
    "sg:address":"Plaz Plateria De Martinez, 1",
    "sg:city":"Madrid",
    "sg:orig_category":"Embajadas, Consulados Y Otras Representaciones Diplom\u00c1ticas",
    "sg:phone":"+34 914 20 16 02",
    "sg:postcode":"28014",
    "sg:province":"Madrid",
    "wof:name":"Embajada De La Republica Arabe Siria",
    "wof:placetype":"venue"
},
  "geometry": {"coordinates":[-3.6937150955,40.4128189087],"type":"Point"}
}