{
  "type": "Feature",
  "properties": {
    "iso:country":"ES",
    "sg:address":"Avda Coru\u00d1a (la), 31",
    "sg:city":"Puente Valga",
    "sg:orig_category":"Droguer\u00cdas (al Por Menor)",
    "sg:phone":"+34 986 55 97 39",
    "sg:postcode":"36645",
    "sg:province":"Pontevedra",
    "wof:name":"Devesa Manteiga Amancia",
    "wof:placetype":"venue"
},
  "geometry": {"coordinates":[-8.6393947601,42.6959877014],"type":"Point"}
}