{
  "type": "Feature",
  "properties": {
    "iso:country":"ES",
    "sg:address":"Calle de Platino (pol. Ind. ), 8",
    "sg:city":"Marbella",
    "sg:orig_category":"Artesan\u00cda",
    "sg:phone":"+34 952 77 54 98",
    "sg:postcode":"29600",
    "sg:province":"M\u00e1laga",
    "wof:name":"Policromia Restauracion Creativa S.c.",
    "wof:placetype":"venue"
},
  "geometry": {"coordinates":[-4.8705768585,36.5128364563],"type":"Point"}
}