{
  "type": "Feature",
  "properties": {
    "addr:full":"Carrer de Galileu, 325 Terrassa Barcelona 08224",
    "addr:housenumber":"325",
    "addr:postcode":"08224",
    "addr:street":"Carrer De Galileu",
    "iso:country":"ES",
    "sg:address":"Carrer de Galileu, 325",
    "sg:city":"Terrassa",
    "sg:orig_category":"M\u00c9dicos: An\u00c1lisis Cl\u00cdnicos",
    "sg:phone":"+34 937 33 38 47",
    "sg:postcode":"08224",
    "sg:province":"Barcelona",
    "sg:website":"www.echevarne.com",
    "wof:name":"Laboratorio Dr. F. Echevarne Analisis S.a.",
    "wof:placetype":"venue"
},
  "geometry": {"coordinates":[2.0054628849,41.5659370422],"type":"Point"}
}