{
  "type": "Feature",
  "properties": {
    "iso:country":"ES",
    "sg:address":"Calle de Iv(romica), 12",
    "sg:city":"Albacete",
    "sg:orig_category":"Molduras, Junquillos, Listones Y Molduras Perforadas",
    "sg:phone":"+34 967 25 40 48",
    "sg:postcode":"02006",
    "sg:province":"Albacete",
    "wof:name":"Garcia Castillo Manuel",
    "wof:placetype":"venue"
},
  "geometry": {"coordinates":[-1.8730750084,38.9823379517],"type":"Point"}
}