{
  "type": "Feature",
  "properties": {
    "addr:full":"Av Jaume I, 54 Mollet Valles Barcelona 08100",
    "addr:housenumber":"54",
    "addr:postcode":"08100",
    "addr:street":"Av Jaume I",
    "iso:country":"ES",
    "sg:address":"Av Jaume I, 54",
    "sg:city":"Mollet Valles",
    "sg:orig_category":"Ense\u00d1anza: Idiomas",
    "sg:phone":"+34 935 70 71 19",
    "sg:postcode":"08100",
    "sg:province":"Barcelona",
    "wof:name":"Icart Riguillo Neus",
    "wof:placetype":"venue"
},
  "geometry": {"coordinates":[2.2132160664,41.5400161743],"type":"Point"}
}