{
  "type": "Feature",
  "properties": {
    "addr:full":"Calle de Serafin Escalante, 3 Torrelavega Cantabria 39300",
    "addr:housenumber":"3",
    "addr:postcode":"39300",
    "addr:street":"Calle De Serafin Escalante",
    "iso:country":"ES",
    "sg:address":"Calle de Serafin Escalante, 3",
    "sg:city":"Torrelavega",
    "sg:orig_category":"Ense\u00d1anza, Formaci\u00d3n Profesional: Aprendizaje",
    "sg:phone":"+34 942 80 20 64",
    "sg:postcode":"39300",
    "sg:province":"Cantabria",
    "wof:name":"Ayuntamiento De Torrelavega Servicio De Limpieza",
    "wof:placetype":"venue"
},
  "geometry": {"coordinates":[-4.0491266251,43.3490753174],"type":"Point"}
}