{
  "type": "Feature",
  "properties": {
    "iso:country":"ES",
    "sg:address":"Carrer de Agusti Blanch I Clausell, 4",
    "sg:city":"Lloret Mar",
    "sg:orig_category":"Fabricaci\u00d3n, Venta, Instalaci\u00d3n De R\u00d3tulos, De R\u00d3tulos Luminosos",
    "sg:phone":"+34 972 37 26 03",
    "sg:postcode":"17310",
    "sg:province":"Girona",
    "wof:name":"Costa Fernandez Francesc",
    "wof:placetype":"venue"
},
  "geometry": {"coordinates":[2.8421690464,41.7076454163],"type":"Point"}
}