{
  "type": "Feature",
  "properties": {
    "iso:country":"ES",
    "sg:address":"Rbla Girada (la), 45",
    "sg:city":"Vilafranca Penedes",
    "sg:orig_category":"Inmobiliaria (agencias)",
    "sg:phone":"+34 938 19 99 00",
    "sg:postcode":"08720",
    "sg:province":"Barcelona",
    "sg:website":"www.fincasvilafranca.com",
    "wof:name":"Fincas Urbanas Vilafranca",
    "wof:placetype":"venue"
},
  "geometry": {"coordinates":[1.7020299435,41.3395004272],"type":"Point"}
}