{
  "type": "Feature",
  "properties": {
    "addr:full":"Rua Soto, 9 Ferrol La Coru\u00f1a 15403",
    "addr:housenumber":"9",
    "addr:postcode":"15403",
    "addr:street":"Rua Soto;La Corun\u0303A",
    "iso:country":"ES",
    "sg:address":"Rua Soto, 9",
    "sg:city":"Ferrol",
    "sg:orig_category":"Asociaciones, Organismos Culturales Y Socioeducativos",
    "sg:phone":"+34 981 37 27 98",
    "sg:postcode":"15403",
    "sg:province":"La Coru\u00f1a",
    "sg:website":"http://circulogacela.convierta.com/index.htm",
    "wof:name":"Circulo Gacela",
    "wof:placetype":"venue"
},
  "geometry": {"coordinates":[-8.2267856598,43.4838905334],"type":"Point"}
}