{
  "type": "Feature",
  "properties": {
    "iso:country":"ES",
    "sg:address":"Calle de David Vazquez Martinez, 4",
    "sg:city":"Langreo",
    "sg:orig_category":"Ense\u00d1anza Secundaria: Colegios Y Escuelas Privadas",
    "sg:phone":"+34 985 69 51 01",
    "sg:postcode":"33930",
    "sg:province":"Asturias",
    "wof:name":"Instituto Nacional De Bachillerato Mixto De La Felguera",
    "wof:placetype":"venue"
},
  "geometry": {"coordinates":[-5.6918201447,43.3098716736],"type":"Point"}
}