{
  "type": "Feature",
  "properties": {
    "iso:country":"ES",
    "sg:address":"Vereda Pino, S/n",
    "sg:city":"Olvera",
    "sg:orig_category":"Ense\u00d1anza, Formaci\u00d3n Profesional: Aprendizaje",
    "sg:phone":"+34 956 13 04 75",
    "sg:postcode":"11690",
    "sg:province":"C\u00e1diz",
    "wof:name":"Ayuntamiento De Olvera",
    "wof:placetype":"venue"
},
  "geometry": {"coordinates":[-5.2500925064,36.9319038391],"type":"Point"}
}