{
  "type": "Feature",
  "properties": {
    "addr:full":"Carrer de Llull, 52 Barcelona Barcelona 08005",
    "addr:housenumber":"52",
    "addr:postcode":"08005",
    "addr:street":"Carrer De Llull",
    "iso:country":"ES",
    "sg:address":"Carrer de Llull, 52",
    "sg:city":"Barcelona",
    "sg:orig_category":"Artes Gr\u00c1ficas, Artes Pl\u00c1sticas (curso)",
    "sg:phone":"+34 933 09 52 83",
    "sg:postcode":"08005",
    "sg:province":"Barcelona",
    "wof:name":"Manipulados Imca S.l.",
    "wof:placetype":"venue"
},
  "geometry": {"coordinates":[2.1922309399,41.3935852051],"type":"Point"}
}