{
  "type": "Feature",
  "properties": {
    "addr:full":"Rua Aureliano Ferreiro, S/n Maceda Ourense 32700",
    "addr:housenumber":"s / n",
    "addr:postcode":"32700",
    "addr:street":"Rua Aureliano Ferreiro",
    "iso:country":"ES",
    "sg:address":"Rua Aureliano Ferreiro, S/n",
    "sg:city":"Maceda",
    "sg:orig_category":"Asilos De Ancianos. Centros Privados",
    "sg:phone":"+34 988 46 33 85",
    "sg:postcode":"32700",
    "sg:province":"Ourense",
    "wof:name":"Compania De Las Hijas De La Caridad De S Vicente De Paul Provincia De Gijon",
    "wof:placetype":"venue"
},
  "geometry": {"coordinates":[-7.6513810158,42.2663917542],"type":"Point"}
}