{
  "type": "Feature",
  "properties": {
    "iso:country":"ES",
    "sg:address":"Ctra Hospitalet, 147",
    "sg:city":"Almeda Mercader",
    "sg:orig_category":"Centros Empresariales",
    "sg:phone":"+34 934 54 41 49",
    "sg:postcode":"08940",
    "sg:province":"Barcelona",
    "wof:name":"Machtmind S.l.",
    "wof:placetype":"venue"
},
  "geometry": {"coordinates":[2.0708940029,41.3559417725],"type":"Point"}
}