{
  "type": "Feature",
  "properties": {
    "iso:country":"ES",
    "sg:address":"Calle de Lopez De Hoyos, 104",
    "sg:city":"Madrid",
    "sg:orig_category":"Zapatos (al Por Menor)",
    "sg:phone":"+34 915 61 64 53",
    "sg:postcode":"28002",
    "sg:province":"Madrid",
    "wof:name":"Garcia Sebastian Carlos",
    "wof:placetype":"venue"
},
  "geometry": {"coordinates":[-3.6748280525,40.4434547424],"type":"Point"}
}