{
  "type": "Feature",
  "properties": {
    "iso:country":"ES",
    "sg:address":"Calle de Lizarre, 4",
    "sg:city":"Moreaga",
    "sg:orig_category":"Pescader\u00cdas (al Por Menor)",
    "sg:phone":"+34 946 76 14 56",
    "sg:postcode":"48600",
    "sg:province":"Vizcaya",
    "wof:name":"Rodriguez Portabales Jose Luis",
    "wof:placetype":"venue"
},
  "geometry": {"coordinates":[-2.9804880619,43.378528595],"type":"Point"}
}