{
  "type": "Feature",
  "properties": {
    "addr:full":"Calle de Tino Casal, 41 Tudela Veguin Asturias 33910",
    "addr:housenumber":"41",
    "addr:postcode":"33910",
    "addr:street":"Calle De Tino Casal;Veguin Asturias",
    "iso:country":"ES",
    "sg:address":"Calle de Tino Casal, 41",
    "sg:city":"Tudela Veguin",
    "sg:orig_category":"Fabricaci\u00d3n, Venta De Cuadros, Accesorios Para Enmarcar",
    "sg:phone":"+34 985 78 90 78",
    "sg:postcode":"33910",
    "sg:province":"Asturias",
    "wof:name":"Pinto Marqueteria S.l.",
    "wof:placetype":"venue"
},
  "geometry": {"coordinates":[-5.7765288353,43.331161499],"type":"Point"}
}