{
  "type": "Feature",
  "properties": {
    "iso:country":"ES",
    "sg:address":"Calle de Bravo, 17",
    "sg:city":"Medina Campo",
    "sg:orig_category":"Molduras, Junquillos, Listones Y Molduras Perforadas",
    "sg:phone":"+34 983 81 08 31",
    "sg:postcode":"47400",
    "sg:province":"Valladolid",
    "wof:name":"Capa Calvo Andres",
    "wof:placetype":"venue"
},
  "geometry": {"coordinates":[-4.9152870178,41.3072547913],"type":"Point"}
}