{
  "type": "Feature",
  "properties": {
    "addr:full":"Plaz Glorieta (de La), 1 Jumilla Murcia 30520",
    "addr:housenumber":"1",
    "addr:postcode":"30520",
    "addr:street":"Glorieta;La",
    "iso:country":"ES",
    "sg:address":"Plaz Glorieta (de La), 1",
    "sg:city":"Jumilla",
    "sg:orig_category":"Escayola Y Productos De Escayola (fabricaci\u00d3n, Al Por Mayor)",
    "sg:phone":"+34 968 78 20 18",
    "sg:postcode":"30520",
    "sg:province":"Murcia",
    "wof:name":"Perez Ruiz Antonio",
    "wof:placetype":"venue"
},
  "geometry": {"coordinates":[-1.3255720139,38.4749794006],"type":"Point"}
}