{
  "type": "Feature",
  "properties": {
    "iso:country":"ES",
    "sg:address":"Barr Murtatza, S/n",
    "sg:city":"Murtatza",
    "sg:orig_category":"Forjas Y Altos Hornos",
    "sg:phone":"+34 946 31 46 06",
    "sg:postcode":"48390",
    "sg:province":"Vizcaya",
    "wof:name":"Forjas Unidas Vascas S.a.",
    "wof:placetype":"venue"
},
  "geometry": {"coordinates":[-2.8070700169,43.2098846436],"type":"Point"}
}