{
  "type": "Feature",
  "properties": {
    "iso:country":"ES",
    "sg:address":"Avda Vilar, 16",
    "sg:city":"Vilar",
    "sg:orig_category":"Ense\u00d1anza: Profesiones Art\u00cdsticas",
    "sg:phone":"+34 986 74 51 51",
    "sg:postcode":"36990",
    "sg:province":"Pontevedra",
    "wof:name":"Mini\u00f1o Fernandez Jose",
    "wof:placetype":"venue"
},
  "geometry": {"coordinates":[-8.8619022369,42.4462432861],"type":"Point"}
}