{
  "type": "Feature",
  "properties": {
    "iso:country":"ES",
    "sg:address":"Calle de Virgen De Los Dolores, 14",
    "sg:city":"Puerto",
    "sg:orig_category":"Asociaciones Y Clubs Deportivos",
    "sg:phone":"+34 962 67 52 80",
    "sg:postcode":"46520",
    "sg:province":"Valencia",
    "wof:name":"Monis Viega Maria Jose",
    "wof:placetype":"venue"
},
  "geometry": {"coordinates":[-0.222935006,39.6608314514],"type":"Point"}
}