{
  "type": "Feature",
  "properties": {
    "addr:full":"Na Taconera, S/n Font Sa Cala Islas Baleares 07589",
    "addr:housenumber":"s / n",
    "addr:postcode":"07589",
    "addr:street":"Taconera;Islas",
    "iso:country":"ES",
    "sg:address":"Na Taconera, S/n",
    "sg:city":"Font Sa Cala",
    "sg:orig_category":"Bebidas",
    "sg:phone":"+34 971 56 35 93",
    "sg:postcode":"07589",
    "sg:province":"Islas Baleares",
    "wof:name":"Pascual Amoros Juan",
    "wof:placetype":"venue"
},
  "geometry": {"coordinates":[3.4302499294,39.7453918457],"type":"Point"}
}