{
  "type": "Feature",
  "properties": {
    "iso:country":"ES",
    "sg:address":"Carretera Figueres-portbou, S/n",
    "sg:city":"Garriguella",
    "sg:orig_category":"Bares, Piano",
    "sg:phone":"+34 972 55 20 00",
    "sg:postcode":"17780",
    "sg:province":"Girona",
    "wof:name":"Distribucions Figueres S.l.",
    "wof:placetype":"venue"
},
  "geometry": {"coordinates":[3.0643210411,42.3423805237],"type":"Point"}
}