{
  "type": "Feature",
  "properties": {
    "iso:country":"ES",
    "sg:address":"Cmno Cementerio, S/n",
    "sg:city":"Rus",
    "sg:orig_category":"Aceites Y Grasas Alimentarias (fabricaci\u00d3n, Al Por Mayor)",
    "sg:phone":"+34 953 77 00 09",
    "sg:postcode":"23430",
    "sg:province":"Ja\u00e9n",
    "wof:name":"Cooperativa Del Campo Nuestra Se\u00f1ora Del Rosario Y San Blas",
    "wof:placetype":"venue"
},
  "geometry": {"coordinates":[-3.4641931057,38.0461196899],"type":"Point"}
}