{
  "type": "Feature",
  "properties": {
    "iso:country":"ES",
    "sg:address":"Poligono Industrial, S/n",
    "sg:city":"Albalat De La Ribera",
    "sg:orig_category":"Limpieza Con Chorro De Arena Y Con Granalla, Pulido",
    "sg:phone":"+34 962 49 21 39",
    "sg:postcode":"46687",
    "sg:province":"Valencia",
    "wof:name":"Pulial Cooperativa Valenciana",
    "wof:placetype":"venue"
},
  "geometry": {"coordinates":[-0.388639003,39.2029685974],"type":"Point"}
}