{
  "type": "Feature",
  "properties": {
    "addr:full":"Calle de Montes De Oca, 13 Villalonquejar Burgos 09001",
    "addr:housenumber":"13",
    "addr:postcode":"09001",
    "addr:street":"Calle De Montes De Oca",
    "iso:country":"ES",
    "sg:address":"Calle de Montes De Oca, 13",
    "sg:city":"Villalonquejar",
    "sg:orig_category":"Textil",
    "sg:phone":"+34 947 29 82 83",
    "sg:postcode":"09001",
    "sg:province":"Burgos",
    "wof:name":"Castellana De Lanas, S. A.",
    "wof:placetype":"venue"
},
  "geometry": {"coordinates":[-3.756362915,42.3614349365],"type":"Point"}
}