{
  "type": "Feature",
  "properties": {
    "addr:full":"Carr General Alberti, Del, 74 Mercadal Islas Baleares 07740",
    "addr:housenumber":"74",
    "addr:postcode":"07740",
    "addr:street":"Carr General Alberti Del",
    "iso:country":"ES",
    "sg:address":"Carr General Alberti, Del, 74",
    "sg:city":"Mercadal",
    "sg:orig_category":"Inmobiliaria (agencias)",
    "sg:phone":"+34 971 37 50 99",
    "sg:postcode":"07740",
    "sg:province":"Islas Baleares",
    "sg:website":"www.etica-menorca.com",
    "wof:name":"Etica Servicios Inmobiliarios S.l.",
    "wof:placetype":"venue"
},
  "geometry": {"coordinates":[4.1529397964,40.00730896],"type":"Point"}
}