{
  "type": "Feature",
  "properties": {
    "addr:full":"Calle de Virgen De La Asuncion, 1 Cabanillas Campo Guadalajara 19171",
    "addr:housenumber":"1",
    "addr:postcode":"19171",
    "addr:street":"Calle De Virgen De La Asuncion",
    "iso:country":"ES",
    "sg:address":"Calle de Virgen De La Asuncion, 1",
    "sg:city":"Cabanillas Campo",
    "sg:orig_category":"Inmobiliaria (agencias)",
    "sg:phone":"+34 949 32 47 35",
    "sg:postcode":"19171",
    "sg:province":"Guadalajara",
    "wof:name":"Promotora Montallegro S.r.l.",
    "wof:placetype":"venue"
},
  "geometry": {"coordinates":[-3.2268190384,40.6436882019],"type":"Point"}
}