{
  "type": "Feature",
  "properties": {
    "iso:country":"ES",
    "sg:address":"Calle de Victor Moya, 5",
    "sg:city":"Valencia",
    "sg:orig_category":"Extinci\u00d3n De Incendios: Material Y Suministros (fabricaci\u00d3n, Al Por Mayor)",
    "sg:phone":"+34 963 56 40 85",
    "sg:postcode":"46022",
    "sg:province":"Valencia",
    "wof:name":"Noe Comercial De Extintores S.l.",
    "wof:placetype":"venue"
},
  "geometry": {"coordinates":[-0.3414320052,39.4666061401],"type":"Point"}
}