{
  "type": "Feature",
  "properties": {
    "iso:country":"ES",
    "sg:address":"Muel Santa Catalina, S/n",
    "sg:city":"Palmas De Gran Canaria",
    "sg:orig_category":"Transporte En General",
    "sg:phone":"+34 928 26 37 84",
    "sg:postcode":"35008",
    "sg:province":"Las Palmas",
    "sg:website":"www.grupoboluda.com",
    "wof:name":"Remoladores Don Quijote S.l.",
    "wof:placetype":"venue"
},
  "geometry": {"coordinates":[-15.4279222488,28.1409034729],"type":"Point"}
}