{
  "type": "Feature",
  "properties": {
    "iso:country":"ES",
    "sg:address":"Calle de Manuel Caso De La Villa, 1",
    "sg:city":"Ribadesella",
    "sg:orig_category":"Telas (al Por Mayor)",
    "sg:phone":"+34 985 86 14 76",
    "sg:postcode":"33560",
    "sg:province":"Asturias",
    "wof:name":"Gonzalez Cuevas Covadonga",
    "wof:placetype":"venue"
},
  "geometry": {"coordinates":[-5.0568509102,43.4630432129],"type":"Point"}
}