{
  "type": "Feature",
  "properties": {
    "iso:country":"ES",
    "sg:address":"Avda Corts Valencianes, 36",
    "sg:city":"Burriana",
    "sg:orig_category":"Agentes Generales De Seguros",
    "sg:phone":"+34 964 51 00 95",
    "sg:postcode":"12530",
    "sg:province":"Castell\u00f3n",
    "wof:name":"Mingarro Fortea Vicente",
    "wof:placetype":"venue"
},
  "geometry": {"coordinates":[-0.0805549994,39.8864250183],"type":"Point"}
}