{
  "type": "Feature",
  "properties": {
    "iso:country":"ES",
    "sg:address":"Calle de Santo Domingo De Guzman, S/n",
    "sg:city":"Mislata",
    "sg:orig_category":"Venta, Colocaci\u00d3n, Reparaci\u00d3n De Radiadores Para Veh\u00cdculos",
    "sg:phone":"+34 963 70 70 04",
    "sg:postcode":"46920",
    "sg:province":"Valencia",
    "wof:name":"Radiadores Xirivella S.l.",
    "wof:placetype":"venue"
},
  "geometry": {"coordinates":[-0.4261740148,39.4694824219],"type":"Point"}
}