{
  "type": "Feature",
  "properties": {
    "addr:full":"Carrer de Topazi, 11 Barcelona Barcelona 08012",
    "addr:housenumber":"11",
    "addr:postcode":"08012",
    "addr:street":"Carrer De Topazi",
    "iso:country":"ES",
    "sg:address":"Carrer de Topazi, 11",
    "sg:city":"Barcelona",
    "sg:orig_category":"Molduras, Junquillos, Listones Y Molduras Perforadas",
    "sg:phone":"+34 932 18 10 87",
    "sg:postcode":"08012",
    "sg:province":"Barcelona",
    "wof:name":"Jimenez Fernandez David",
    "wof:placetype":"venue"
},
  "geometry": {"coordinates":[2.1549921036,41.4046592712],"type":"Point"}
}