{
  "type": "Feature",
  "properties": {
    "addr:full":"Calle de Pastor Y Landero, 13 Sevilla Sevilla 41001",
    "addr:housenumber":"13",
    "addr:postcode":"41001",
    "addr:street":"Calle De Pastor Y Landero",
    "iso:country":"ES",
    "sg:address":"Calle de Pastor Y Landero, 13",
    "sg:city":"Sevilla",
    "sg:orig_category":"Centros M\u00c9dicos Y Sociales, Dispensarios",
    "sg:phone":"+34 954 29 33 38",
    "sg:postcode":"41001",
    "sg:province":"Sevilla",
    "wof:name":"Nazarena De Salud, S.l.",
    "wof:placetype":"venue"
},
  "geometry": {"coordinates":[-5.9995679855,37.3879394531],"type":"Point"}
}