{
  "type": "Feature",
  "properties": {
    "iso:country":"ES",
    "sg:address":"Calle de Marcos Zapata, 35",
    "sg:city":"Zaragoza",
    "sg:orig_category":"Centros Empresariales",
    "sg:phone":"+34 976 32 37 76",
    "sg:postcode":"50010",
    "sg:province":"Zaragoza",
    "wof:name":"Aragonesa De Contratas Y Reformas Sl",
    "wof:placetype":"venue"
},
  "geometry": {"coordinates":[-0.9074788094,41.6531639099],"type":"Point"}
}