{
  "type": "Feature",
  "properties": {
    "iso:country":"ES",
    "sg:address":"Calle de Cartagena, 136",
    "sg:city":"Madrid",
    "sg:orig_category":"Colchones (fabricaci\u00d3n, Al Por Mayor, Al Por Menor)",
    "sg:phone":"+34 915 62 24 70",
    "sg:postcode":"28002",
    "sg:province":"Madrid",
    "sg:website":"www.lasguias.com/colchoneriajavier",
    "wof:name":"Guzman Nu\u00f1ez Francisco Javier",
    "wof:placetype":"venue"
},
  "geometry": {"coordinates":[-3.6754302979,40.4421157837],"type":"Point"}
}