{
  "type": "Feature",
  "properties": {
    "addr:full":"Carrer de Galicia, 103 Terrassa Barcelona 08223",
    "addr:housenumber":"103",
    "addr:postcode":"08223",
    "addr:street":"Carrer De Galicia",
    "iso:country":"ES",
    "sg:address":"Carrer de Galicia, 103",
    "sg:city":"Terrassa",
    "sg:orig_category":"Productos Qu\u00cdmicos (fabricaci\u00d3n, Al Por Mayor)",
    "sg:phone":"+34 937 84 26 47",
    "sg:postcode":"08223",
    "sg:province":"Barcelona",
    "wof:name":"Envatel S.l.",
    "wof:placetype":"venue"
},
  "geometry": {"coordinates":[2.0117371082,41.550655365],"type":"Point"}
}