{
  "type": "Feature",
  "properties": {
    "iso:country":"ES",
    "sg:address":"Calle de Vencejos, 4",
    "sg:city":"Puerto De Santa Maria",
    "sg:orig_category":"Institutos De Belleza",
    "sg:phone":"+34 956 05 48 31",
    "sg:postcode":"11500",
    "sg:province":"C\u00e1diz",
    "wof:name":"Cristobal Rodriguez Ana",
    "wof:placetype":"venue"
},
  "geometry": {"coordinates":[-6.2337222099,36.5955505371],"type":"Point"}
}