{
  "type": "Feature",
  "properties": {
    "iso:country":"ES",
    "sg:address":"Calle de Estrella De Elola, 11",
    "sg:city":"Valdemoro",
    "sg:orig_category":"Frutas Y Legumbres Secas (al Por Mayor)",
    "sg:phone":"+34 918 95 29 02",
    "sg:postcode":"28340",
    "sg:province":"Madrid",
    "wof:name":"Lacasa Pa\u00f1os Salvador",
    "wof:placetype":"venue"
},
  "geometry": {"coordinates":[-3.6783568859,40.1918983459],"type":"Point"}
}