{
  "type": "Feature",
  "properties": {
    "addr:full":"Almendros, 8 Logro\u00f1o La Rioja 26006",
    "addr:housenumber":"8",
    "addr:postcode":"26006",
    "addr:street":"Almendros;Rioja",
    "iso:country":"ES",
    "sg:address":"Almendros, 8",
    "sg:city":"Logro\u00f1o",
    "sg:orig_category":"Materias Pl\u00c1sticas: Art\u00cdculos Para La Industria",
    "sg:phone":"+34 941 25 02 71",
    "sg:postcode":"26006",
    "sg:province":"La Rioja",
    "sg:website":"www.envaplaster.com",
    "wof:name":"Envaplaster S.a.",
    "wof:placetype":"venue"
},
  "geometry": {"coordinates":[-2.4147729874,42.4738998413],"type":"Point"}
}