{
  "type": "Feature",
  "properties": {
    "addr:full":"Calle de Fenelon, 4 Madrid Madrid 28022",
    "addr:housenumber":"4",
    "addr:postcode":"28022",
    "addr:street":"Calle De Fenelon",
    "iso:country":"ES",
    "sg:address":"Calle de Fenelon, 4",
    "sg:city":"Madrid",
    "sg:orig_category":"Agencias Y Agentes Comerciales, Representantes",
    "sg:phone":"+34 913 20 45 64",
    "sg:postcode":"28022",
    "sg:province":"Madrid",
    "wof:name":"Doceco Trading S.l.",
    "wof:placetype":"venue"
},
  "geometry": {"coordinates":[-3.6116929054,40.4372901917],"type":"Point"}
}