{
  "type": "Feature",
  "properties": {
    "iso:country":"ES",
    "sg:address":"Carrer de Torello, 9",
    "sg:city":"Vic",
    "sg:orig_category":"Pintura Y Barniz (al Por Menor)",
    "sg:phone":"+34 938 86 90 47",
    "sg:postcode":"08500",
    "sg:province":"Barcelona",
    "wof:name":"Pinturas Vic S.a.",
    "wof:placetype":"venue"
},
  "geometry": {"coordinates":[2.2653019428,41.9288825989],"type":"Point"}
}