{
  "type": "Feature",
  "properties": {
    "addr:full":"Avda Pilar, S/n Torrijos Toledo 45500",
    "addr:housenumber":"s / n",
    "addr:postcode":"45500",
    "addr:street":"Avda Pilar",
    "iso:country":"ES",
    "sg:address":"Avda Pilar, S/n",
    "sg:city":"Torrijos",
    "sg:orig_category":"Abogados",
    "sg:phone":"+34 925 77 04 30",
    "sg:postcode":"45500",
    "sg:province":"Toledo",
    "wof:name":"Administracion De Justicia",
    "wof:placetype":"venue"
},
  "geometry": {"coordinates":[-4.2790427208,39.9807052612],"type":"Point"}
}