{
  "type": "Feature",
  "properties": {
    "addr:full":"Calle de Reykjavik, 47 Jardines Del Duque Santa Cruz De Tenerife 38660",
    "addr:housenumber":"47",
    "addr:postcode":"38660",
    "addr:street":"Calle De Reykjavik",
    "iso:country":"ES",
    "sg:address":"Calle de Reykjavik, 47",
    "sg:city":"Jardines Del Duque",
    "sg:orig_category":"Administradores De Bienes Y Delegados De Comunidades De Propietarios",
    "sg:phone":"+34 922 71 93 70",
    "sg:postcode":"38660",
    "sg:province":"Santa Cruz De Tenerife",
    "wof:name":"Mimi Millenium S.l.",
    "wof:placetype":"venue"
},
  "geometry": {"coordinates":[-16.7317714691,28.0760765076],"type":"Point"}
}