{
  "type": "Feature",
  "properties": {
    "addr:full":"Calle de Sagunto, 14 Soria Soria 42001",
    "addr:housenumber":"14",
    "addr:postcode":"42001",
    "addr:street":"Calle De Sagunto",
    "iso:country":"ES",
    "sg:address":"Calle de Sagunto, 14",
    "sg:city":"Soria",
    "sg:orig_category":"Empleado Administrativo",
    "sg:phone":"+34 975 22 78 11",
    "sg:postcode":"42001",
    "sg:province":"Soria",
    "wof:name":"Milla Romera Esther",
    "wof:placetype":"venue"
},
  "geometry": {"coordinates":[-2.4716620445,41.7655220032],"type":"Point"}
}