{
  "type": "Feature",
  "properties": {
    "addr:full":"Avda Ferrandis Salvador, 138 Mas Dels Frares Castell\u00f3n 12560",
    "addr:housenumber":"138",
    "addr:postcode":"12560",
    "addr:street":"Avda Ferrandis Salvador;Castello\u0301N",
    "iso:country":"ES",
    "sg:address":"Avda Ferrandis Salvador, 138",
    "sg:city":"Mas Dels Frares",
    "sg:orig_category":"Telefon\u00cda: Instaladores Varios",
    "sg:phone":"+34 964 39 21 14",
    "sg:postcode":"12560",
    "sg:province":"Castell\u00f3n",
    "wof:name":"Locutorio Telefonico Benicasim S.l.",
    "wof:placetype":"venue"
},
  "geometry": {"coordinates":[0.0505715013,40.0370368958],"type":"Point"}
}