{
  "type": "Feature",
  "properties": {
    "addr:full":"Calle de Iglesia, 2 Moreruela De Los Infanzones Zamora 49731",
    "addr:housenumber":"2",
    "addr:postcode":"49731",
    "addr:street":"Calle De Iglesia",
    "iso:country":"ES",
    "sg:address":"Calle de Iglesia, 2",
    "sg:city":"Moreruela De Los Infanzones",
    "sg:orig_category":"Contenedores (mercanc\u00cdas)",
    "sg:phone":"+34 980 50 45 64",
    "sg:postcode":"49731",
    "sg:province":"Zamora",
    "wof:name":"Calles Gullon David",
    "wof:placetype":"venue"
},
  "geometry": {"coordinates":[-5.7089729309,41.6316871643],"type":"Point"}
}