{
  "type": "Feature",
  "properties": {
    "iso:country":"ES",
    "sg:address":"Carrer de Lope De Vega, 71",
    "sg:city":"Barcelona",
    "sg:orig_category":"Ebanister\u00cda",
    "sg:phone":"+34 934 85 59 69",
    "sg:postcode":"08005",
    "sg:province":"Barcelona",
    "wof:name":"Castro Marti Isaac",
    "wof:placetype":"venue"
},
  "geometry": {"coordinates":[2.2044289112,41.4037513733],"type":"Point"}
}