{
  "type": "Feature",
  "properties": {
    "addr:full":"Avda San Juan, 1 Miranda Arga Navarra 31253",
    "addr:housenumber":"1",
    "addr:postcode":"31253",
    "addr:street":"Avda San Juan",
    "iso:country":"ES",
    "sg:address":"Avda San Juan, 1",
    "sg:city":"Miranda Arga",
    "sg:orig_category":"Venta, Instalaci\u00d3n De Cocinas",
    "sg:phone":"+34 948 73 70 41",
    "sg:postcode":"31253",
    "sg:province":"Navarra",
    "wof:name":"Rio Aoiz Ignacio Del",
    "wof:placetype":"venue"
},
  "geometry": {"coordinates":[-1.826892972,42.4831466675],"type":"Point"}
}