{
  "type": "Feature",
  "properties": {
    "iso:country":"ES",
    "sg:address":"Calle de Cantera (la), 18",
    "sg:city":"Cantera",
    "sg:orig_category":"Pirotecnia (espect\u00c1culos)",
    "sg:phone":"+34 928 57 07 38",
    "sg:postcode":"35217",
    "sg:province":"Las Palmas",
    "wof:name":"Martel Davila Juan Ramon",
    "wof:placetype":"venue"
},
  "geometry": {"coordinates":[-15.482378006,27.9995822906],"type":"Point"}
}