{
  "type": "Feature",
  "properties": {
    "addr:full":"Calle de Zabalbide, 75 Bilbao Vizcaya 48007",
    "addr:housenumber":"75",
    "addr:postcode":"48007",
    "addr:street":"Calle De Zabalbide",
    "iso:country":"ES",
    "sg:address":"Calle de Zabalbide, 75",
    "sg:city":"Bilbao",
    "sg:orig_category":"Edici\u00d3n De Diarios, Revistas, Boletines",
    "sg:phone":"+34 944 13 22 94",
    "sg:postcode":"48007",
    "sg:province":"Vizcaya",
    "wof:name":"Ediciones Aupper S.l.",
    "wof:placetype":"venue"
},
  "geometry": {"coordinates":[-2.9115200043,43.2609825134],"type":"Point"}
}