{
  "type": "Feature",
  "properties": {
    "addr:full":"Ctra Madrid Toledo (1-3), S/n Illescas Toledo 45200",
    "addr:housenumber":"1-3 s / n",
    "addr:postcode":"45200",
    "addr:street":"Ctra Madrid Toledo",
    "iso:country":"ES",
    "sg:address":"Ctra Madrid Toledo (1-3), S/n",
    "sg:city":"Illescas",
    "sg:orig_category":"Muebles Y Accesorios Para Cocinas Y Cuartos De Ba\u00d1o (al Por Menor)",
    "sg:phone":"+34 925 51 42 22",
    "sg:postcode":"45200",
    "sg:province":"Toledo",
    "sg:website":"www.almirezcocina.com",
    "wof:name":"Almirez Cocinas S.l.",
    "wof:placetype":"venue"
},
  "geometry": {"coordinates":[-3.8801996708,40.0446395874],"type":"Point"}
}