{
  "type": "Feature",
  "properties": {
    "addr:full":"Andalucia, S/n Utrillas Teruel 44760",
    "addr:postcode":"44760",
    "addr:street":"Andalucia S / N",
    "iso:country":"ES",
    "sg:address":"Andalucia, S/n",
    "sg:city":"Utrillas",
    "sg:orig_category":"Alquiler De Veh\u00cdculos: Turismos Y Utilitarios",
    "sg:phone":"+34 978 75 81 91",
    "sg:postcode":"44760",
    "sg:province":"Teruel",
    "wof:name":"Hijos De Ignacio Garcia Edo S.l.",
    "wof:placetype":"venue"
},
  "geometry": {"coordinates":[-0.8411239982,40.8033256531],"type":"Point"}
}