{
  "type": "Feature",
  "properties": {
    "addr:full":"Avda Florida, 24 Vigo Pontevedra 36210",
    "addr:housenumber":"24",
    "addr:postcode":"36210",
    "addr:street":"Avda Florida",
    "iso:country":"ES",
    "sg:address":"Avda Florida, 24",
    "sg:city":"Vigo",
    "sg:orig_category":"Almacenes Para Venta: Muebles Y Varios",
    "sg:phone":"+34 986 29 29 98",
    "sg:postcode":"36210",
    "sg:province":"Pontevedra",
    "wof:name":"Cerdeira Vazquez Albina",
    "wof:placetype":"venue"
},
  "geometry": {"coordinates":[-8.7476491928,42.2103309631],"type":"Point"}
}