{
  "type": "Feature",
  "properties": {
    "iso:country":"ES",
    "sg:address":"C/ Merce, 6",
    "sg:city":"Ripollet",
    "sg:orig_category":"Delegados, Agentes De Tr\u00c1nsito, Auxiliares De Transporte Internacional",
    "sg:phone":"+34 935 80 58 53",
    "sg:postcode":"08291",
    "sg:province":"Barcelona",
    "wof:name":"Transportes Aragal S.c.p.",
    "wof:placetype":"venue"
},
  "geometry": {"coordinates":[2.1682701111,41.4941902161],"type":"Point"}
}