{
  "type": "Feature",
  "properties": {
    "iso:country":"ES",
    "sg:address":"Calle de Mayor Antigua, 51",
    "sg:city":"Palencia",
    "sg:orig_category":"M\u00c9dicos: Medicina Manual",
    "sg:phone":"+34 979 17 02 80",
    "sg:postcode":"34005",
    "sg:province":"Palencia",
    "wof:name":"Rubio Cadierno Domingo",
    "wof:placetype":"venue"
},
  "geometry": {"coordinates":[-4.5353088379,42.0084381104],"type":"Point"}
}