{
  "type": "Feature",
  "properties": {
    "iso:country":"ES",
    "sg:address":"Barreras, 19",
    "sg:city":"Baeza",
    "sg:orig_category":"Caf\u00c9s, Bares, Cervecer\u00cdas",
    "sg:phone":"+34 953 74 43 55",
    "sg:postcode":"23440",
    "sg:province":"Ja\u00e9n",
    "wof:name":"Garcia Godino Rafael",
    "wof:placetype":"venue"
},
  "geometry": {"coordinates":[-3.4671545029,37.9926185608],"type":"Point"}
}