{
  "type": "Feature",
  "properties": {
    "addr:full":"Calle de Esteban De Arteaga, 3 Madrid Madrid 28019",
    "addr:housenumber":"3",
    "addr:postcode":"28019",
    "addr:street":"Calle De Esteban De Arteaga",
    "iso:country":"ES",
    "sg:address":"Calle de Esteban De Arteaga, 3",
    "sg:city":"Madrid",
    "sg:orig_category":"Tapicer\u00cdas",
    "sg:phone":"+34 914 60 13 11",
    "sg:postcode":"28019",
    "sg:province":"Madrid",
    "wof:name":"Moya Roman Elisa",
    "wof:placetype":"venue"
},
  "geometry": {"coordinates":[-3.7093040943,40.3953742981],"type":"Point"}
}