{
  "type": "Feature",
  "properties": {
    "addr:full":"Avda Castilla, 14 Guadalajara Guadalajara 19002",
    "addr:housenumber":"14",
    "addr:postcode":"19002",
    "addr:street":"Avda Castilla",
    "iso:country":"ES",
    "sg:address":"Avda Castilla, 14",
    "sg:city":"Guadalajara",
    "sg:orig_category":"Molduras, Junquillos, Listones Y Molduras Perforadas",
    "sg:phone":"+34 949 21 68 31",
    "sg:postcode":"19002",
    "sg:province":"Guadalajara",
    "wof:name":"La Botellita Guadalajara S.l.",
    "wof:placetype":"venue"
},
  "geometry": {"coordinates":[-3.1663908958,40.6257400513],"type":"Point"}
}