{
  "type": "Feature",
  "properties": {
    "iso:country":"ES",
    "sg:address":"Calle de Gutemberg, 48",
    "sg:city":"Badajoz",
    "sg:orig_category":"Decoraci\u00d3n: Instalaci\u00d3n Y Talleres",
    "sg:phone":"+34 924 25 13 75",
    "sg:postcode":"06011",
    "sg:province":"Badajoz",
    "wof:name":"Gutierrez Sanchez Martin",
    "wof:placetype":"venue"
},
  "geometry": {"coordinates":[-6.989803791,38.8555297852],"type":"Point"}
}