{
  "type": "Feature",
  "properties": {
    "addr:full":"Carrer de Aitana, 2 Muro Alcoy Alicante 03830",
    "addr:housenumber":"2",
    "addr:postcode":"03830",
    "addr:street":"Carrer De Aitana",
    "iso:country":"ES",
    "sg:address":"Carrer de Aitana, 2",
    "sg:city":"Muro Alcoy",
    "sg:orig_category":"Locales Y Clases De Danza",
    "sg:phone":"+34 965 53 19 78",
    "sg:postcode":"03830",
    "sg:province":"Alicante",
    "wof:name":"Tudela Cerver Elena",
    "wof:placetype":"venue"
},
  "geometry": {"coordinates":[-0.4414289892,38.7812538147],"type":"Point"}
}