{
  "type": "Feature",
  "properties": {
    "addr:full":"Calle de Hiendelaencina, 3 Madrid Madrid 28023",
    "addr:housenumber":"3",
    "addr:postcode":"28023",
    "addr:street":"Calle De Hiendelaencina",
    "iso:country":"ES",
    "sg:address":"Calle de Hiendelaencina, 3",
    "sg:city":"Madrid",
    "sg:orig_category":"Centros De Coordinaci\u00d3n",
    "sg:phone":"+34 913 07 83 14",
    "sg:postcode":"28023",
    "sg:province":"Madrid",
    "wof:name":"Maura Inversiones S.l.",
    "wof:placetype":"venue"
},
  "geometry": {"coordinates":[-3.766890049,40.4594535828],"type":"Point"}
}