{
  "type": "Feature",
  "properties": {
    "iso:country":"ES",
    "sg:address":"Calle de Isidoro Salas, 47",
    "sg:city":"Santo Domingo De La Calzada",
    "sg:orig_category":"Pescader\u00cdas (al Por Menor)",
    "sg:phone":"+34 941 34 22 77",
    "sg:postcode":"26250",
    "sg:province":"La Rioja",
    "wof:name":"Oca\u00f1a Sanchez Jose Antonio",
    "wof:placetype":"venue"
},
  "geometry": {"coordinates":[-2.9541809559,42.4401893616],"type":"Point"}
}