{
  "type": "Feature",
  "properties": {
    "addr:full":"Carrer de Ferrer I Clariana, 2 Mataro Barcelona 08304",
    "addr:housenumber":"2",
    "addr:postcode":"08304",
    "addr:street":"Carrer De Ferrer I Clariana",
    "iso:country":"ES",
    "sg:address":"Carrer de Ferrer I Clariana, 2",
    "sg:city":"Mataro",
    "sg:orig_category":"Rectificaci\u00d3n, Mecanizado, Fresado",
    "sg:phone":"+34 937 99 57 00",
    "sg:postcode":"08304",
    "sg:province":"Barcelona",
    "wof:name":"Sanchez Martinez Gines",
    "wof:placetype":"venue"
},
  "geometry": {"coordinates":[2.4445869923,41.5494995117],"type":"Point"}
}