{
  "type": "Feature",
  "properties": {
    "addr:full":"Av Diputacio, 175 Cambrils Tarragona 43850",
    "addr:housenumber":"175",
    "addr:postcode":"43850",
    "addr:street":"Av Diputacio",
    "iso:country":"ES",
    "sg:address":"Av Diputacio, 175",
    "sg:city":"Cambrils",
    "sg:orig_category":"Inmobiliaria (agencias)",
    "sg:phone":"+34 977 38 40 67",
    "sg:postcode":"43850",
    "sg:province":"Tarragona",
    "sg:website":"www.interfinques.com",
    "wof:name":"Inver Vilafortuny S.l.",
    "wof:placetype":"venue"
},
  "geometry": {"coordinates":[1.1097800732,41.0730400085],"type":"Point"}
}