{
  "type": "Feature",
  "properties": {
    "addr:full":"Pol Ind Pla Rasca\u00f1a, S/n Lliria Valencia 46160",
    "addr:housenumber":"s / n",
    "addr:postcode":"46160",
    "addr:street":"Ind Pla Rascan\u0303A",
    "iso:country":"ES",
    "sg:address":"Pol Ind Pla Rasca\u00f1a, S/n",
    "sg:city":"Lliria",
    "sg:orig_category":"Empresas De Carpinter\u00cda Met\u00c1lica",
    "sg:phone":"+34 962 79 04 29",
    "sg:postcode":"46160",
    "sg:province":"Valencia",
    "wof:name":"Taller Moreno Y Ferrer S.l.",
    "wof:placetype":"venue"
},
  "geometry": {"coordinates":[-0.5887290239,39.6367645264],"type":"Point"}
}