{
  "type": "Feature",
  "properties": {
    "addr:full":"Calle de Callejo, 46 Madrid Madrid 28053",
    "addr:housenumber":"46",
    "addr:postcode":"madrid;28053",
    "addr:street":"Calle De Callejo",
    "iso:country":"ES",
    "sg:address":"Calle de Callejo, 46",
    "sg:city":"Madrid",
    "sg:orig_category":"Centros Empresariales",
    "sg:phone":"+34 914 78 10 76",
    "sg:postcode":"28053",
    "sg:province":"Madrid",
    "wof:name":"Gonzalez Fernandez Francisco Fermin",
    "wof:placetype":"venue"
},
  "geometry": {"coordinates":[-3.6689996719,40.3886299133],"type":"Point"}
}