{
  "type": "Feature",
  "properties": {
    "iso:country":"ES",
    "sg:address":"Calle de Zarza, 30",
    "sg:city":"Alcorcon",
    "sg:orig_category":"M\u00c9dicos: Estomatolog\u00cda",
    "sg:phone":"+34 916 42 57 48",
    "sg:postcode":"28921",
    "sg:province":"Madrid",
    "wof:name":"Instituto Bucodental Integral S.l.",
    "wof:placetype":"venue"
},
  "geometry": {"coordinates":[-3.8260691166,40.3492469788],"type":"Point"}
}