{
  "type": "Feature",
  "properties": {
    "addr:full":"Carrer de Nord, 19 Vendrell Tarragona 43700",
    "addr:housenumber":"19",
    "addr:postcode":"43700",
    "addr:street":"Carrer De Nord",
    "iso:country":"ES",
    "sg:address":"Carrer de Nord, 19",
    "sg:city":"Vendrell",
    "sg:orig_category":"Confecci\u00d3n (fabricaci\u00d3n, Al Por Mayor)",
    "sg:phone":"+34 977 66 74 67",
    "sg:postcode":"43700",
    "sg:province":"Tarragona",
    "wof:name":"Cabaex S.l.",
    "wof:placetype":"venue"
},
  "geometry": {"coordinates":[1.5364370346,41.2215957642],"type":"Point"}
}