{
  "type": "Feature",
  "properties": {
    "iso:country":"ES",
    "sg:address":"Rio Pisuerga, S/n",
    "sg:city":"San Miguel",
    "sg:orig_category":"Acero: Productos Sider\u00dargicos Y Transformados (fabricaci\u00d3n, Negocio)",
    "sg:phone":"+34 961 98 18 44",
    "sg:postcode":"46370",
    "sg:province":"Valencia",
    "wof:name":"Sociedad Siderurgica Siglo 21 S.l",
    "wof:placetype":"venue"
},
  "geometry": {"coordinates":[-0.5709310174,39.4352073669],"type":"Point"}
}