{
  "type": "Feature",
  "properties": {
    "addr:full":"Calle de San Ramon, 2 Sabi\u00d1an Zaragoza 50299",
    "addr:housenumber":"2",
    "addr:postcode":"50299",
    "addr:street":"Calle De San Ramon",
    "iso:country":"ES",
    "sg:address":"Calle de San Ramon, 2",
    "sg:city":"Sabi\u00d1an",
    "sg:orig_category":"Panader\u00cdas, Panader\u00cdas",
    "sg:phone":"+34 976 82 61 14",
    "sg:postcode":"50299",
    "sg:province":"Zaragoza",
    "wof:name":"Salda\u00f1a Villalba Carlos",
    "wof:placetype":"venue"
},
  "geometry": {"coordinates":[-1.5671190023,41.4425582886],"type":"Point"}
}