{
  "type": "Feature",
  "properties": {
    "addr:full":"Calle de Greco (el), 5 Socuellamos Ciudad Real 13630",
    "addr:housenumber":"5",
    "addr:postcode":"13630",
    "addr:street":"Calle De Greco El",
    "iso:country":"ES",
    "sg:address":"Calle de Greco (el), 5",
    "sg:city":"Socuellamos",
    "sg:orig_category":"Ropa Y Accesorios",
    "sg:phone":"+34 926 53 23 77",
    "sg:postcode":"13630",
    "sg:province":"Ciudad Real",
    "wof:name":"Confecciones Loreto S.l.",
    "wof:placetype":"venue"
},
  "geometry": {"coordinates":[-2.7990190983,39.2781410217],"type":"Point"}
}