{
  "type": "Feature",
  "properties": {
    "iso:country":"ES",
    "sg:address":"Avda Andalucia, 17",
    "sg:city":"Santisteban Puerto",
    "sg:orig_category":"Lavado, Limpieza De Veh\u00cdculos",
    "sg:phone":"+34 953 40 13 90",
    "sg:postcode":"23250",
    "sg:province":"Ja\u00e9n",
    "wof:name":"Soriano Alamo Marcos",
    "wof:placetype":"venue"
},
  "geometry": {"coordinates":[-3.2012410164,38.250705719],"type":"Point"}
}