{
  "type": "Feature",
  "properties": {
    "iso:country":"ES",
    "sg:address":"Avda Andalucia (de), 26",
    "sg:city":"Estepa",
    "sg:orig_category":"Aceites Y Grasas Alimentarias (fabricaci\u00d3n, Al Por Mayor)",
    "sg:phone":"+34 955 91 35 29",
    "sg:postcode":"41560",
    "sg:province":"Sevilla",
    "wof:name":"Olivarera Sor Angela De La Cruz S.coop.andaluza",
    "wof:placetype":"venue"
},
  "geometry": {"coordinates":[-4.8842759132,37.291179657],"type":"Point"}
}