{
  "type": "Feature",
  "properties": {
    "iso:country":"ES",
    "sg:address":"Calle de Villa De Plentzia, 28",
    "sg:city":"Arenas -areeta",
    "sg:orig_category":"Organizaciones Internacionales",
    "sg:phone":"+34 944 80 32 41",
    "sg:postcode":"48930",
    "sg:province":"Vizcaya",
    "wof:name":"Asociacion Euskadiko Pku Elkartea-asociacion Pku De Euskadi",
    "wof:placetype":"venue"
},
  "geometry": {"coordinates":[-2.6983869076,43.2204284668],"type":"Point"}
}