{
  "type": "Feature",
  "properties": {
    "iso:country":"ES",
    "sg:address":"Calle de Alcalde Romero Raggio, 15",
    "sg:city":"Malaga",
    "sg:orig_category":"Centros De Educaci\u00d3n Especial",
    "sg:phone":"+34 952 36 34 02",
    "sg:postcode":"29003",
    "sg:province":"M\u00e1laga",
    "wof:name":"Fundacion Diocesana De Ense\u00f1anza Santa Maria De La Victoria",
    "wof:placetype":"venue"
},
  "geometry": {"coordinates":[-4.4494175911,36.7029953003],"type":"Point"}
}