{
  "type": "Feature",
  "properties": {
    "addr:full":"Sagrat Cor (raval De Crist), 14 Roquetes Tarragona 43520",
    "addr:housenumber":"14",
    "addr:postcode":"43520",
    "addr:street":"Raval De Crist",
    "iso:country":"ES",
    "sg:address":"Sagrat Cor (raval De Crist), 14",
    "sg:city":"Roquetes",
    "sg:orig_category":"Laboratorios Farmac\u00c9uticos",
    "sg:phone":"+34 977 50 40 56",
    "sg:postcode":"43520",
    "sg:province":"Tarragona",
    "wof:name":"Farmacia Gamundi C.b.",
    "wof:placetype":"venue"
},
  "geometry": {"coordinates":[0.4970969856,40.8088302612],"type":"Point"}
}