{
  "type": "Feature",
  "properties": {
    "addr:full":"Carrer de Horts, 46 Fonts Barcelona 08194",
    "addr:housenumber":"46",
    "addr:postcode":"08194",
    "addr:street":"Carrer De Horts",
    "iso:country":"ES",
    "sg:address":"Carrer de Horts, 46",
    "sg:city":"Fonts",
    "sg:orig_category":"Empresarios",
    "sg:phone":"+34 937 84 16 74",
    "sg:postcode":"08194",
    "sg:province":"Barcelona",
    "wof:name":"Martin Pelaez Antonio",
    "wof:placetype":"venue"
},
  "geometry": {"coordinates":[2.0374999046,41.5248565674],"type":"Point"}
}