{
  "type": "Feature",
  "properties": {
    "iso:country":"ES",
    "sg:address":"Calle de Regacho, 10",
    "sg:city":"Mislata",
    "sg:orig_category":"Colocaci\u00d3n, Mantenimiento De Canalizaciones",
    "sg:phone":"+34 963 83 44 50",
    "sg:postcode":"46920",
    "sg:province":"Valencia",
    "wof:name":"Leon Pareja Domingo",
    "wof:placetype":"venue"
},
  "geometry": {"coordinates":[-0.4195876122,39.4779243469],"type":"Point"}
}