{
  "type": "Feature",
  "properties": {
    "addr:full":"Calle de Santisima Trinidad, 15 Antequera M\u00e1laga 29200",
    "addr:housenumber":"15",
    "addr:postcode":"29200",
    "addr:street":"Calle De Santisima Trinidad",
    "iso:country":"ES",
    "sg:address":"Calle de Santisima Trinidad, 15",
    "sg:city":"Antequera",
    "sg:orig_category":"Promotores Constructores",
    "sg:phone":"+34 952 70 00 70",
    "sg:postcode":"29200",
    "sg:province":"M\u00e1laga",
    "wof:name":"Construcciones Cebrian Y Tortosa, S.l.",
    "wof:placetype":"venue"
},
  "geometry": {"coordinates":[-4.563519001,37.0185317993],"type":"Point"}
}