{
  "type": "Feature",
  "properties": {
    "addr:full":"Calle de Santiago Dulong, 12 Zaragoza Zaragoza 50003",
    "addr:housenumber":"12",
    "addr:postcode":"50003",
    "addr:street":"Calle De Santiago Dulong",
    "iso:country":"ES",
    "sg:address":"Calle de Santiago Dulong, 12",
    "sg:city":"Zaragoza",
    "sg:orig_category":"Muebles Y Accesorios Para Cocinas Y Cuartos De Ba\u00d1o (al Por Menor)",
    "sg:phone":"+34 976 43 02 57",
    "sg:postcode":"50003",
    "sg:province":"Zaragoza",
    "wof:name":"Luis Escalante S.l.",
    "wof:placetype":"venue"
},
  "geometry": {"coordinates":[-0.9025959969,41.6594200134],"type":"Point"}
}