{
  "type": "Feature",
  "properties": {
    "addr:full":"Calle de Doctor Horno Alcorta, 5 Zaragoza Zaragoza 50004",
    "addr:housenumber":"5",
    "addr:postcode":"50004",
    "addr:street":"Calle De Doctor Horno Alcorta",
    "iso:country":"ES",
    "sg:address":"Calle de Doctor Horno Alcorta, 5",
    "sg:city":"Zaragoza",
    "sg:orig_category":"Inmobiliaria (agencias)",
    "sg:phone":"+34 976 21 08 09",
    "sg:postcode":"50004",
    "sg:province":"Zaragoza",
    "wof:name":"Ebrhogar Gestion Inmobiliaria Sl",
    "wof:placetype":"venue"
},
  "geometry": {"coordinates":[-0.8895949721,41.6505622864],"type":"Point"}
}