{
  "type": "Feature",
  "properties": {
    "addr:full":"Carrer de Pau Casals, 22 Mas Rampinyo Barcelona 08110",
    "addr:housenumber":"22",
    "addr:postcode":"08110",
    "addr:street":"Carrer De Pau Casals",
    "iso:country":"ES",
    "sg:address":"Carrer de Pau Casals, 22",
    "sg:city":"Mas Rampinyo",
    "sg:orig_category":"Embalajes",
    "sg:phone":"+34 935 64 46 92",
    "sg:postcode":"08110",
    "sg:province":"Barcelona",
    "wof:name":"Hesa Embal S.l.",
    "wof:placetype":"venue"
},
  "geometry": {"coordinates":[2.1793539524,41.4938545227],"type":"Point"}
}