{
  "type": "Feature",
  "properties": {
    "addr:full":"Munts, 9 Torredembarra Tarragona 43830",
    "addr:housenumber":"9",
    "addr:postcode":"43830",
    "addr:street":"Munts",
    "iso:country":"ES",
    "sg:address":"Munts, 9",
    "sg:city":"Torredembarra",
    "sg:orig_category":"Empresarios",
    "sg:phone":"+34 977 64 15 11",
    "sg:postcode":"43830",
    "sg:province":"Tarragona",
    "wof:name":"Delgado Garcia Carina",
    "wof:placetype":"venue"
},
  "geometry": {"coordinates":[1.3935389519,41.1439437866],"type":"Point"}
}