{
  "type": "Feature",
  "properties": {
    "iso:country":"ES",
    "sg:address":"Calle de Macedonia, 2",
    "sg:city":"Sevilla",
    "sg:orig_category":"Aparcamientos (infraestructuras, Accesorios)",
    "sg:phone":"+34 954 25 10 54",
    "sg:postcode":"41007",
    "sg:province":"Sevilla",
    "wof:name":"Oropesa Galan Jose",
    "wof:placetype":"venue"
},
  "geometry": {"coordinates":[-5.9569177628,37.4022979736],"type":"Point"}
}