{
  "type": "Feature",
  "properties": {
    "iso:country":"ES",
    "sg:address":"Calle de Sevilla, 132",
    "sg:city":"Bailen",
    "sg:orig_category":"Bares, Piano",
    "sg:phone":"+34 953 67 26 87",
    "sg:postcode":"23710",
    "sg:province":"Ja\u00e9n",
    "wof:name":"Rodriguez Lendinez Antonio",
    "wof:placetype":"venue"
},
  "geometry": {"coordinates":[-3.7808890343,38.0945091248],"type":"Point"}
}