{
  "type": "Feature",
  "properties": {
    "addr:full":"Ctra Fuerte Del Rey, 5 Jaen Ja\u00e9n 23006",
    "addr:housenumber":"5;jae\u0301n",
    "addr:postcode":"23006",
    "addr:street":"Ctra Fuerte Del Rey",
    "iso:country":"ES",
    "sg:address":"Ctra Fuerte Del Rey, 5",
    "sg:city":"Jaen",
    "sg:orig_category":"Maquinaria Para Industrias Diversas",
    "sg:phone":"+34 953 26 60 38",
    "sg:postcode":"23006",
    "sg:province":"Ja\u00e9n",
    "wof:name":"Remancer Jaen S.l",
    "wof:placetype":"venue"
},
  "geometry": {"coordinates":[-3.7975718975,37.7809104919],"type":"Point"}
}