{
  "type": "Feature",
  "properties": {
    "iso:country":"ES",
    "sg:address":"Calle de Azafranal, 17",
    "sg:city":"Salamanca",
    "sg:orig_category":"Bisuter\u00cda, Joyer\u00cda, Relojer\u00cda (al Por Menor)",
    "sg:phone":"+34 923 21 58 79",
    "sg:postcode":"37001",
    "sg:province":"Salamanca",
    "wof:name":"Fernandez Prior Jeremias",
    "wof:placetype":"venue"
},
  "geometry": {"coordinates":[-5.6614284515,40.9669265747],"type":"Point"}
}