{
  "type": "Feature",
  "properties": {
    "addr:full":"Calle de Parroco Antonio Gomez Villalobos, 2 Sevilla Sevilla 41006",
    "addr:housenumber":"2",
    "addr:postcode":"41006",
    "addr:street":"Calle De Parroco Antonio Gomez Villalobos",
    "iso:country":"ES",
    "sg:address":"Calle de Parroco Antonio Gomez Villalobos, 2",
    "sg:city":"Sevilla",
    "sg:orig_category":"Electricidad: Equipos Industriales, Componentes (fabricaci\u00d3n)",
    "sg:phone":"+34 954 63 02 15",
    "sg:postcode":"41006",
    "sg:province":"Sevilla",
    "wof:name":"Cecub Materiales Electricos S.l.",
    "wof:placetype":"venue"
},
  "geometry": {"coordinates":[-5.9519062042,37.3706550598],"type":"Point"}
}