{
  "type": "Feature",
  "properties": {
    "addr:full":"Carrer de Doctor Pi I Sunyer, 31 Roses Girona 17480",
    "addr:housenumber":"31",
    "addr:postcode":"17480",
    "addr:street":"Carrer De Doctor Pi I Sunyer",
    "iso:country":"ES",
    "sg:address":"Carrer de Doctor Pi I Sunyer, 31",
    "sg:city":"Roses",
    "sg:orig_category":"Art\u00cdculos De Regalo (al Por Menor)",
    "sg:phone":"+34 972 15 23 95",
    "sg:postcode":"17480",
    "sg:province":"Girona",
    "wof:name":"Forton Farres Rosa",
    "wof:placetype":"venue"
},
  "geometry": {"coordinates":[3.1757600307,42.2619400024],"type":"Point"}
}