{
  "type": "Feature",
  "properties": {
    "addr:full":"Calle de Octavio Cuartero, 30 Albacete Albacete 02003",
    "addr:housenumber":"30",
    "addr:postcode":"02003",
    "addr:street":"Calle De Octavio Cuartero",
    "iso:country":"ES",
    "sg:address":"Calle de Octavio Cuartero, 30",
    "sg:city":"Albacete",
    "sg:orig_category":"Clases De M\u00dasica Y Canto",
    "sg:phone":"+34 967 50 25 90",
    "sg:postcode":"02003",
    "sg:province":"Albacete",
    "wof:name":"Molina Gomez Maria De Los Llanos",
    "wof:placetype":"venue"
},
  "geometry": {"coordinates":[-1.8592549562,38.9913406372],"type":"Point"}
}