{
  "type": "Feature",
  "properties": {
    "addr:full":"Calle de Postrera, 21 Cordoba C\u00f3rdoba 14004",
    "addr:housenumber":"21",
    "addr:postcode":"14004",
    "addr:street":"Calle De Postrera;Co\u0301Rdoba",
    "iso:country":"ES",
    "sg:address":"Calle de Postrera, 21",
    "sg:city":"Cordoba",
    "sg:orig_category":"Agencias Y Asesores De Publicidad",
    "sg:phone":"+34 957 76 04 01",
    "sg:postcode":"14004",
    "sg:province":"C\u00f3rdoba",
    "sg:website":"www.almargen.com",
    "wof:name":"Al Margen S.coop.andaluza",
    "wof:placetype":"venue"
},
  "geometry": {"coordinates":[-4.7842822075,37.875213623],"type":"Point"}
}