{
  "type": "Feature",
  "properties": {
    "iso:country":"ES",
    "sg:address":"Estd De Mondariz, S/n",
    "sg:city":"Cachadas",
    "sg:orig_category":"Inmobiliaria (agencias)",
    "sg:phone":"+34 986 64 28 76",
    "sg:postcode":"36860",
    "sg:province":"Pontevedra",
    "wof:name":"Espiga Salceda S.l.",
    "wof:placetype":"venue"
},
  "geometry": {"coordinates":[-8.5163888931,42.1783599854],"type":"Point"}
}