{
  "type": "Feature",
  "properties": {
    "iso:country":"ES",
    "sg:address":"Avda Paskual Abaroa Etorbidea, 11",
    "sg:city":"Lekeitio",
    "sg:orig_category":"Art\u00cdculos De Regalo (al Por Menor)",
    "sg:phone":"+34 946 24 31 34",
    "sg:postcode":"48280",
    "sg:province":"Vizcaya",
    "wof:name":"Flores Urreisti Angel",
    "wof:placetype":"venue"
},
  "geometry": {"coordinates":[-2.5055499077,43.3629341125],"type":"Point"}
}