{
  "type": "Feature",
  "properties": {
    "addr:full":"Calle de Galeon, 3 Madrid Madrid 28042",
    "addr:housenumber":"3",
    "addr:postcode":"28042",
    "addr:street":"Calle De Galeon",
    "iso:country":"ES",
    "sg:address":"Calle de Galeon, 3",
    "sg:city":"Madrid",
    "sg:orig_category":"Inform\u00c1tica (estudios, Servicios, Asesor\u00cda, Formaci\u00d3n)",
    "sg:phone":"+34 917 47 26 32",
    "sg:postcode":"28042",
    "sg:province":"Madrid",
    "wof:name":"Gonzalez Baron Jose Luis",
    "wof:placetype":"venue"
},
  "geometry": {"coordinates":[-3.5857889652,40.4557533264],"type":"Point"}
}