{
  "type": "Feature",
  "properties": {
    "addr:full":"Calle de Canillas, 11 Madrid Madrid 28002",
    "addr:housenumber":"11",
    "addr:postcode":"madrid;28002",
    "addr:street":"Calle De Canillas",
    "iso:country":"ES",
    "sg:address":"Calle de Canillas, 11",
    "sg:city":"Madrid",
    "sg:classifiers":[
        {
            "category":"Communications",
            "subcategory":"Film & Video Production",
            "type":"Services"
        }
    ],
    "sg:phone":"+34 915 61 81 01",
    "sg:postcode":"28002",
    "sg:province":"Madrid",
    "sg:tags":[
        "de",
        "material",
        "fotocomposici\u00d3n"
    ],
    "wof:name":"Foto-porst Imagen Audio S. A.",
    "wof:placetype":"venue"
},
  "geometry": {"coordinates":[-3.676715374,40.4409255981],"type":"Point"}
}