{
  "type": "Feature",
  "properties": {
    "addr:full":"Calle de Zu\u00d1iga Rodriguez, 5 Bejar Salamanca 37700",
    "addr:housenumber":"5",
    "addr:postcode":"37700",
    "addr:street":"Calle De Zun\u0303Iga Rodriguez",
    "iso:country":"ES",
    "sg:address":"Calle de Zu\u00d1iga Rodriguez, 5",
    "sg:city":"Bejar",
    "sg:orig_category":"Radiocomunicaciones, Telefon\u00cda M\u00d3vil, Radiomensajer\u00cda: Servicios, Comercializaci\u00d3n",
    "sg:phone":"+34 923 40 27 06",
    "sg:postcode":"37700",
    "sg:province":"Salamanca",
    "sg:website":"www.electrosan.net",
    "wof:name":"Electrosan Telecomunicaciones S.l.",
    "wof:placetype":"venue"
},
  "geometry": {"coordinates":[-5.7626190186,40.3851509094],"type":"Point"}
}