{
  "type": "Feature",
  "properties": {
    "iso:country":"ES",
    "sg:address":"Calle de Obispo Rabadan, 29",
    "sg:city":"Palmas De Gran Canaria",
    "sg:orig_category":"M\u00c1quinas De Coser Y De Hacer Punto (al Por Mayor)",
    "sg:phone":"+34 928 37 23 30",
    "sg:postcode":"35003",
    "sg:province":"Las Palmas",
    "wof:name":"Sigma Canarias S.a.",
    "wof:placetype":"venue"
},
  "geometry": {"coordinates":[-15.4202070236,28.1123046875],"type":"Point"}
}