{
  "type": "Feature",
  "properties": {
    "addr:full":"Ctra Franca, S/n Mollo Girona 17868",
    "addr:housenumber":"s",
    "addr:postcode":"17868",
    "addr:street":"Ctra Franca;/ N",
    "iso:country":"ES",
    "sg:address":"Ctra Franca, S/n",
    "sg:city":"Mollo",
    "sg:orig_category":"Charcuter\u00cdas (al Por Menor)",
    "sg:phone":"+34 972 74 03 84",
    "sg:postcode":"17868",
    "sg:province":"Girona",
    "wof:name":"Aspar Ricart Francisco",
    "wof:placetype":"venue"
},
  "geometry": {"coordinates":[2.4814145565,42.3207473755],"type":"Point"}
}