{
  "type": "Feature",
  "properties": {
    "iso:country":"ES",
    "sg:address":"Calle de Algeciras, 77",
    "sg:city":"Tomares",
    "sg:orig_category":"Animales (al Por Menor)",
    "sg:phone":"+34 954 15 43 26",
    "sg:postcode":"41940",
    "sg:province":"Sevilla",
    "wof:name":"Martinez Garcia Juan",
    "wof:placetype":"venue"
},
  "geometry": {"coordinates":[-6.030040741,37.3754768372],"type":"Point"}
}