{
  "type": "Feature",
  "properties": {
    "addr:full":"Carr Gran Bretanya, 54 Badalona Barcelona 08917",
    "addr:housenumber":"54",
    "addr:postcode":"08917",
    "addr:street":"Carr Gran Bretanya",
    "iso:country":"ES",
    "sg:address":"Carr Gran Bretanya, 54",
    "sg:city":"Badalona",
    "sg:orig_category":"Vestidos De Se\u00d1ora (tallas Grandes)",
    "sg:phone":"+34 933 95 65 53",
    "sg:postcode":"08917",
    "sg:province":"Barcelona",
    "wof:name":"Trios Bdn Montigala S.l.",
    "wof:placetype":"venue"
},
  "geometry": {"coordinates":[2.2222900391,41.4602088928],"type":"Point"}
}