{
  "type": "Feature",
  "properties": {
    "addr:full":"Calle de Maqueda, 22 Madrid Madrid 28024",
    "addr:housenumber":"22",
    "addr:postcode":"madrid;28024",
    "addr:street":"Calle De Maqueda",
    "iso:country":"ES",
    "sg:address":"Calle de Maqueda, 22",
    "sg:city":"Madrid",
    "sg:orig_category":"Fabricaci\u00d3n Y Distribuci\u00d3n De Colas, Masillas Y Encoladoras",
    "sg:phone":"+34 915 18 22 01",
    "sg:postcode":"28024",
    "sg:province":"Madrid",
    "wof:name":"Forbo Adhesives Spain S.l. Unipersonal",
    "wof:placetype":"venue"
},
  "geometry": {"coordinates":[-3.7664840221,40.3938217163],"type":"Point"}
}