{
  "type": "Feature",
  "properties": {
    "iso:country":"ES",
    "sg:address":"Calle de Puente, 34",
    "sg:city":"Miajadas",
    "sg:orig_category":"Inmobiliaria (agencias)",
    "sg:phone":"+34 927 34 50 36",
    "sg:postcode":"10100",
    "sg:province":"C\u00e1ceres",
    "wof:name":"Parras Puerto Juan",
    "wof:placetype":"venue"
},
  "geometry": {"coordinates":[-5.9074292183,39.1479797363],"type":"Point"}
}