{
  "type": "Feature",
  "properties": {
    "addr:full":"Calle de Gobernador Fernandez Jimenez (del), 10 Segovia Segovia 40002",
    "addr:housenumber":"10",
    "addr:postcode":"40002",
    "addr:street":"Calle De Gobernador Fernandez Jimenez Del",
    "iso:country":"ES",
    "sg:address":"Calle de Gobernador Fernandez Jimenez (del), 10",
    "sg:city":"Segovia",
    "sg:orig_category":"Ropa Para Se\u00d1oras (al Por Menor)",
    "sg:phone":"+34 921 42 65 50",
    "sg:postcode":"40002",
    "sg:province":"Segovia",
    "wof:name":"Castro Perez Sonia Francisca",
    "wof:placetype":"venue"
},
  "geometry": {"coordinates":[-4.1187791824,40.9455986023],"type":"Point"}
}