{
  "type": "Feature",
  "properties": {
    "iso:country":"ES",
    "sg:address":"C/ Benito Perez Galdos, 2",
    "sg:city":"Elche",
    "sg:orig_category":"Edici\u00d3n De Diarios, Revistas, Boletines",
    "sg:phone":"+34 965 43 45 88",
    "sg:postcode":"03201",
    "sg:province":"Alicante",
    "wof:name":"Prensa Y Noticias S.l.",
    "wof:placetype":"venue"
},
  "geometry": {"coordinates":[-0.7041019797,38.2663459778],"type":"Point"}
}