{
  "type": "Feature",
  "properties": {
    "addr:full":"Avda Lugo (de), 1 Barrela Lugo 27520",
    "addr:postcode":"27520",
    "addr:street":"Avda Lugo De 1 Barrela",
    "iso:country":"ES",
    "sg:address":"Avda Lugo (de), 1",
    "sg:city":"Barrela",
    "sg:orig_category":"Electricidad: Instaladores",
    "sg:phone":"+34 982 46 64 10",
    "sg:postcode":"27520",
    "sg:province":"Lugo",
    "wof:name":"Couso Gonzalez Jose",
    "wof:placetype":"venue"
},
  "geometry": {"coordinates":[-7.8145589828,42.5395202637],"type":"Point"}
}