{
  "type": "Feature",
  "properties": {
    "iso:country":"ES",
    "sg:address":"Carr Grecia, 3",
    "sg:city":"Igualada",
    "sg:orig_category":"Artes Gr\u00c1ficas, Artes Pl\u00c1sticas (curso)",
    "sg:phone":"+34 938 05 10 00",
    "sg:postcode":"08700",
    "sg:province":"Barcelona",
    "sg:website":"www.unigraf.es",
    "wof:name":"Unigraf Anoia S.a.",
    "wof:placetype":"venue"
},
  "geometry": {"coordinates":[1.6279139519,41.5977210999],"type":"Point"}
}