{
  "type": "Feature",
  "properties": {
    "iso:country":"ES",
    "sg:address":"Calle de Hilarion Eslava, 13",
    "sg:city":"Madrid",
    "sg:orig_category":"Zapatos (al Por Menor)",
    "sg:phone":"+34 915 49 86 67",
    "sg:postcode":"28015",
    "sg:province":"Madrid",
    "wof:name":"Tres Precios S.c.v.",
    "wof:placetype":"venue"
},
  "geometry": {"coordinates":[-3.7169780731,40.4329414368],"type":"Point"}
}