{
  "type": "Feature",
  "properties": {
    "iso:country":"ES",
    "sg:address":"Calle de Pelota, 1",
    "sg:city":"Cadiz",
    "sg:orig_category":"T\u00c9cnicos Veterinarios",
    "sg:phone":"+34 956 28 25 04",
    "sg:postcode":"11005",
    "sg:province":"C\u00e1diz",
    "wof:name":"Saenz Rodriguez Juan Jesus",
    "wof:placetype":"venue"
},
  "geometry": {"coordinates":[-6.2942690849,36.5295562744],"type":"Point"}
}