{
  "type": "Feature",
  "properties": {
    "addr:full":"Ctra Alicante-cartagena, Km. 0074,0 S. Fulgencio Alicante 03177",
    "addr:postcode":"03177",
    "addr:street":"Ctra Alicante-Cartagena Km. 0074,0 S. Fulgencio Alicante",
    "iso:country":"ES",
    "sg:address":"Ctra Alicante-cartagena, Km. 0074,0",
    "sg:city":"S. Fulgencio",
    "sg:orig_category":"Karting",
    "sg:phone":"+34 965 72 75 03",
    "sg:postcode":"03177",
    "sg:province":"Alicante",
    "wof:name":"Go Karts San Fulgencio S.l.",
    "wof:placetype":"venue"
},
  "geometry": {"coordinates":[-0.7383440137,38.1049537659],"type":"Point"}
}