{
  "type": "Feature",
  "properties": {
    "addr:full":"Calle de San Juan De Dios, 14 Sevilla Sevilla 41005",
    "addr:housenumber":"14",
    "addr:postcode":"41005",
    "addr:street":"Calle De San Juan;Dios",
    "iso:country":"ES",
    "sg:address":"Calle de San Juan De Dios, 14",
    "sg:city":"Sevilla",
    "sg:orig_category":"M\u00c9dicos: Cirug\u00cda Urol\u00d3gica",
    "sg:phone":"+34 954 63 73 78",
    "sg:postcode":"41005",
    "sg:province":"Sevilla",
    "wof:name":"Monta\u00f1es Medina Pedro",
    "wof:placetype":"venue"
},
  "geometry": {"coordinates":[-5.9669079781,37.3807144165],"type":"Point"}
}