{
  "type": "Feature",
  "properties": {
    "iso:country":"ES",
    "sg:address":"Cra Sant Boi, 110",
    "sg:city":"Sant Vicen\u00c7 Dels Horts",
    "sg:orig_category":"Instalaci\u00d3n De Aspiraci\u00d3n De Gases Y Humos",
    "sg:phone":"+34 936 56 81 00",
    "sg:postcode":"08620",
    "sg:province":"Barcelona",
    "wof:name":"Gesco Serveis Bcn S.l.",
    "wof:placetype":"venue"
},
  "geometry": {"coordinates":[2.0100400448,41.3932189941],"type":"Point"}
}