{
  "type": "Feature",
  "properties": {
    "iso:country":"ES",
    "sg:address":"Avda Gran Via, 161",
    "sg:city":"Vigo",
    "sg:orig_category":"Venta, Montaje De Neum\u00c1ticos",
    "sg:phone":"+34 986 48 06 27",
    "sg:postcode":"36210",
    "sg:province":"Pontevedra",
    "wof:name":"Rodasco S.a.",
    "wof:placetype":"venue"
},
  "geometry": {"coordinates":[-8.7263765335,42.2219848633],"type":"Point"}
}