{
  "type": "Feature",
  "properties": {
    "iso:country":"ES",
    "sg:address":"Calle de Ugarte, 17",
    "sg:city":"Bilbao",
    "sg:orig_category":"Carnicer\u00cdas, Carnicer\u00cdas",
    "sg:phone":"+34 944 12 03 39",
    "sg:postcode":"48004",
    "sg:province":"Vizcaya",
    "wof:name":"Ramirez Polo Francisco",
    "wof:placetype":"venue"
},
  "geometry": {"coordinates":[-2.90178895,43.2599029541],"type":"Point"}
}