{
  "type": "Feature",
  "properties": {
    "iso:country":"ES",
    "sg:address":"Luz Serena, Km. 0005,0",
    "sg:city":"Casas Rio",
    "sg:orig_category":"Cultos Diversos",
    "sg:phone":"+34 962 30 10 55",
    "sg:postcode":"46356",
    "sg:province":"Valencia",
    "wof:name":"Comunidad Budista Soto Zen",
    "wof:placetype":"venue"
},
  "geometry": {"coordinates":[-1.1428769827,39.2991485596],"type":"Point"}
}