{
  "type": "Feature",
  "properties": {
    "iso:country":"ES",
    "sg:address":"Calle de Juderia Vieja (la), 12",
    "sg:city":"Segovia",
    "sg:orig_category":"Empresarios",
    "sg:phone":"+34 921 46 22 49",
    "sg:postcode":"40001",
    "sg:province":"Segovia",
    "wof:name":"Fundacion Don Juan De Borbon",
    "wof:placetype":"venue"
},
  "geometry": {"coordinates":[-4.1248149872,40.9496459961],"type":"Point"}
}