{
  "type": "Feature",
  "properties": {
    "addr:full":"Calle de Romeu, 6 Sagunt Valencia 46500",
    "addr:housenumber":"6",
    "addr:postcode":"46500",
    "addr:street":"Calle De Romeu",
    "iso:country":"ES",
    "sg:address":"Calle de Romeu, 6",
    "sg:city":"Sagunt",
    "sg:orig_category":"Abogados",
    "sg:phone":"+34 962 65 05 51",
    "sg:postcode":"46500",
    "sg:province":"Valencia",
    "wof:name":"Chabret Bahilo Juan",
    "wof:placetype":"venue"
},
  "geometry": {"coordinates":[-0.2770499885,39.6802406311],"type":"Point"}
}