{
  "type": "Feature",
  "properties": {
    "addr:full":"Calle de Neptuno, 2 Granada Granada 18004",
    "addr:housenumber":"2",
    "addr:postcode":"18004",
    "addr:street":"Calle De Neptuno",
    "iso:country":"ES",
    "sg:address":"Calle de Neptuno, 2",
    "sg:city":"Granada",
    "sg:orig_category":"Asesor\u00cda Fiscal Y Jur\u00cddica",
    "sg:phone":"+34 958 25 85 22",
    "sg:postcode":"18004",
    "sg:province":"Granada",
    "wof:name":"Gavilan Dionisio Miguel Angel",
    "wof:placetype":"venue"
},
  "geometry": {"coordinates":[-3.606153965,37.1701087952],"type":"Point"}
}