{
  "type": "Feature",
  "properties": {
    "addr:full":"Bjd. De La Iglesia, 1 Caracenilla Cuenca 16540",
    "addr:housenumber":"1",
    "addr:postcode":"16540",
    "addr:street":"Iglesia",
    "iso:country":"ES",
    "sg:address":"Bjd. De La Iglesia, 1",
    "sg:city":"Caracenilla",
    "sg:orig_category":"Fabricaci\u00d3n De Quesos",
    "sg:phone":"+34 969 27 26 69",
    "sg:postcode":"16540",
    "sg:province":"Cuenca",
    "wof:name":"S.a.t. Rio Mayor",
    "wof:placetype":"venue"
},
  "geometry": {"coordinates":[-2.5502479076,40.1932678223],"type":"Point"}
}