{
  "type": "Feature",
  "properties": {
    "iso:country":"ES",
    "sg:address":"Calle de Porvenir De Productor, 59",
    "sg:city":"Alacant",
    "sg:orig_category":"Quincaller\u00cda (al Por Menor)",
    "sg:phone":"+34 965 11 70 78",
    "sg:postcode":"03008",
    "sg:province":"Alicante",
    "wof:name":"Lorenzo Astilleros Lucia",
    "wof:placetype":"venue"
},
  "geometry": {"coordinates":[-0.5151363015,38.3293685913],"type":"Point"}
}