{
  "type": "Feature",
  "properties": {
    "iso:country":"ES",
    "sg:address":"Calle de Camas, 28",
    "sg:city":"Sevilla",
    "sg:orig_category":"Librer\u00cdas",
    "sg:phone":"+34 954 67 54 73",
    "sg:postcode":"41016",
    "sg:province":"Sevilla",
    "wof:name":"Real Fernandez Josefa",
    "wof:placetype":"venue"
},
  "geometry": {"coordinates":[-5.9111604691,37.3869247437],"type":"Point"}
}