{
  "type": "Feature",
  "properties": {
    "addr:full":"Calle de Fari\u00d1a (la), 7 Orotava Santa Cruz De Tenerife 38300",
    "addr:housenumber":"7",
    "addr:postcode":"38300",
    "addr:street":"Calle De Farin\u0303A La",
    "iso:country":"ES",
    "sg:address":"Calle de Fari\u00d1a (la), 7",
    "sg:city":"Orotava",
    "sg:orig_category":"Empresas De Carpinter\u00cda De Madera",
    "sg:phone":"+34 922 33 52 04",
    "sg:postcode":"38300",
    "sg:province":"Santa Cruz De Tenerife",
    "wof:name":"Gonzalez Diaz Juan",
    "wof:placetype":"venue"
},
  "geometry": {"coordinates":[-16.5253238678,28.3842773438],"type":"Point"}
}