{
  "type": "Feature",
  "properties": {
    "addr:full":"Pase Heriz De, 3 Donostia-san Sebastian Guip\u00f9zcoa 20008",
    "addr:postcode":"20008",
    "iso:country":"ES",
    "sg:address":"Pase Heriz De, 3",
    "sg:city":"Donostia-san Sebastian",
    "sg:orig_category":"Molduras, Junquillos, Listones Y Molduras Perforadas",
    "sg:phone":"+34 943 21 12 81",
    "sg:postcode":"20008",
    "sg:province":"Guip\u00f9zcoa",
    "wof:name":"Gonzalez Quinto Alfonso",
    "wof:placetype":"venue"
},
  "geometry": {"coordinates":[-2.0392899513,43.3088798523],"type":"Point"}
}