{
  "type": "Feature",
  "properties": {
    "addr:full":"Calle de Milan, 3 Arenal Islas Baleares 07600",
    "addr:housenumber":"3",
    "addr:postcode":"07600",
    "addr:street":"Calle De Milan",
    "iso:country":"ES",
    "sg:address":"Calle de Milan, 3",
    "sg:city":"Arenal",
    "sg:orig_category":"Loter\u00cda Y T\u00d3mbola",
    "sg:phone":"+34 971 26 58 17",
    "sg:postcode":"07600",
    "sg:province":"Islas Baleares",
    "sg:website":"www.asgsa.es/palma28",
    "wof:name":"Fajula Quiroga Maria Dolores",
    "wof:placetype":"venue"
},
  "geometry": {"coordinates":[2.7524049282,39.5043296814],"type":"Point"}
}