{
  "type": "Feature",
  "properties": {
    "addr:full":"Calle de Manuel Aleixandre, 12 Madrid Madrid 28045",
    "addr:housenumber":"12",
    "addr:postcode":"madrid;28045",
    "addr:street":"Calle De Manuel Aleixandre",
    "iso:country":"ES",
    "sg:address":"Calle de Manuel Aleixandre, 12",
    "sg:city":"Madrid",
    "sg:orig_category":"Cervecer\u00cdas",
    "sg:phone":"+34 915 27 90 15",
    "sg:postcode":"28045",
    "sg:province":"Madrid",
    "wof:name":"Ortega Alvia Angel",
    "wof:placetype":"venue"
},
  "geometry": {"coordinates":[-3.6935229301,40.391166687],"type":"Point"}
}