{
  "type": "Feature",
  "properties": {
    "iso:country":"ES",
    "sg:address":"Deba Kalea, 2",
    "sg:city":"Elgoibar",
    "sg:orig_category":"Rectificaci\u00d3n, Mecanizado, Fresado",
    "sg:phone":"+34 943 74 26 28",
    "sg:postcode":"20870",
    "sg:province":"Guip\u00f9zcoa",
    "wof:name":"Betetxe S.l.",
    "wof:placetype":"venue"
},
  "geometry": {"coordinates":[-2.4114789963,43.2172584534],"type":"Point"}
}