{
  "type": "Feature",
  "properties": {
    "addr:full":"Calle de Jesus Nazareno, 19 Santa Cruz De Tenerife Santa Cruz De Tenerife 38003",
    "addr:housenumber":"19",
    "addr:postcode":"38003",
    "addr:street":"Calle De Jesus Nazareno",
    "iso:country":"ES",
    "sg:address":"Calle de Jesus Nazareno, 19",
    "sg:city":"Santa Cruz De Tenerife",
    "sg:orig_category":"Abogados",
    "sg:phone":"+34 922 24 26 84",
    "sg:postcode":"38003",
    "sg:province":"Santa Cruz De Tenerife",
    "wof:name":"Grupo Migrantess.l..l.",
    "wof:placetype":"venue"
},
  "geometry": {"coordinates":[-16.2544116974,28.4682407379],"type":"Point"}
}