{
  "type": "Feature",
  "properties": {
    "addr:full":"Calle de Anunciadora, 22 Pozuelo De Alarcon Madrid 28224",
    "addr:housenumber":"22",
    "addr:postcode":"28224",
    "addr:street":"Calle De Anunciadora",
    "iso:country":"ES",
    "sg:address":"Calle de Anunciadora, 22",
    "sg:city":"Pozuelo De Alarcon",
    "sg:orig_category":"Maquinaria Para Industrias Diversas",
    "sg:phone":"+34 917 15 58 45",
    "sg:postcode":"28224",
    "sg:province":"Madrid",
    "wof:name":"Irati Systems S.a.",
    "wof:placetype":"venue"
},
  "geometry": {"coordinates":[-3.7937266827,40.4440917969],"type":"Point"}
}