{
  "type": "Feature",
  "properties": {
    "addr:full":"Pl Sierra De Aralar, 7 Estella Navarra 31200",
    "addr:housenumber":"7",
    "addr:postcode":"31200",
    "addr:street":"Pl Sierra De Aralar",
    "iso:country":"ES",
    "sg:address":"Pl Sierra De Aralar, 7",
    "sg:city":"Estella",
    "sg:orig_category":"Droguer\u00cdas (al Por Menor)",
    "sg:phone":"+34 948 55 24 60",
    "sg:postcode":"31200",
    "sg:province":"Navarra",
    "wof:name":"Albizu Droguerias S.l.",
    "wof:placetype":"venue"
},
  "geometry": {"coordinates":[-2.0342307091,42.6712684631],"type":"Point"}
}