{
  "type": "Feature",
  "properties": {
    "iso:country":"ES",
    "sg:address":"Calle de Igeltzera, 3",
    "sg:city":"Landa",
    "sg:orig_category":"Negocio De Materiales De Construcci\u00d3n",
    "sg:phone":"+34 946 76 27 03",
    "sg:postcode":"48610",
    "sg:province":"Vizcaya",
    "wof:name":"Yanguas Carrascal Jose Ramon",
    "wof:placetype":"venue"
},
  "geometry": {"coordinates":[-2.6983869076,43.2204284668],"type":"Point"}
}