{
  "type": "Feature",
  "properties": {
    "addr:full":"Calle de Ponzano, 4 Zaragoza Zaragoza 50004",
    "addr:housenumber":"4",
    "addr:postcode":"50004",
    "addr:street":"Calle De Ponzano",
    "iso:country":"ES",
    "sg:address":"Calle de Ponzano, 4",
    "sg:city":"Zaragoza",
    "sg:orig_category":"Droguer\u00cdas (al Por Menor)",
    "sg:phone":"+34 976 22 13 78",
    "sg:postcode":"50004",
    "sg:province":"Zaragoza",
    "wof:name":"Lapuente Gil Daniel",
    "wof:placetype":"venue"
},
  "geometry": {"coordinates":[-0.8851550221,41.6492614746],"type":"Point"}
}