{
  "type": "Feature",
  "properties": {
    "addr:full":"Avda Manuel Rodriguez, 11 Malaga M\u00e1laga 29190",
    "addr:housenumber":"11",
    "addr:postcode":"29190",
    "addr:street":"Avda Manuel Rodriguez;Ma\u0301Laga",
    "iso:country":"ES",
    "sg:address":"Avda Manuel Rodriguez, 11",
    "sg:city":"Malaga",
    "sg:orig_category":"Agencias Y Agentes Comerciales, Representantes",
    "sg:phone":"+34 952 43 15 94",
    "sg:postcode":"29190",
    "sg:province":"M\u00e1laga",
    "wof:name":"Comercial Distribuciones Y Representaciones Cortes S.l.",
    "wof:placetype":"venue"
},
  "geometry": {"coordinates":[-4.479195118,36.7341995239],"type":"Point"}
}