{
  "type": "Feature",
  "properties": {
    "iso:country":"ES",
    "sg:address":"Musa(pol Ind Labradorcico), S/n",
    "sg:city":"Aguilas",
    "sg:orig_category":"Mec\u00c1nico Del Autom\u00d3vil",
    "sg:phone":"+34 968 41 20 77",
    "sg:postcode":"30880",
    "sg:province":"Murcia",
    "wof:name":"Tamesur Scl",
    "wof:placetype":"venue"
},
  "geometry": {"coordinates":[-1.5839740038,37.4077987671],"type":"Point"}
}