{
  "type": "Feature",
  "properties": {
    "iso:country":"ES",
    "sg:address":"Calle de Real, 1",
    "sg:city":"Piedrabuena",
    "sg:orig_category":"Farmacias",
    "sg:phone":"+34 926 76 03 60",
    "sg:postcode":"13100",
    "sg:province":"Ciudad Real",
    "wof:name":"Alvarez Ballesteros Maria Pilar",
    "wof:placetype":"venue"
},
  "geometry": {"coordinates":[-4.1737604141,39.0353851318],"type":"Point"}
}