{
  "type": "Feature",
  "properties": {
    "iso:country":"ES",
    "sg:address":"Afores, 41",
    "sg:city":"Vila-seca",
    "sg:orig_category":"Contenedores (mercanc\u00cdas)",
    "sg:phone":"+34 977 39 14 28",
    "sg:postcode":"43480",
    "sg:province":"Tarragona",
    "wof:name":"Sanchez Marti Salvador",
    "wof:placetype":"venue"
},
  "geometry": {"coordinates":[1.1441899538,41.1080245972],"type":"Point"}
}