{
  "type": "Feature",
  "properties": {
    "addr:full":"Avda Limonar (del), 8 Jerez De La Frontera C\u00e1diz 11407",
    "addr:postcode":"11407",
    "addr:street":"Avda Limonar Del",
    "iso:country":"ES",
    "sg:address":"Avda Limonar (del), 8",
    "sg:city":"Jerez De La Frontera",
    "sg:orig_category":"Escuelas De Maternidad P\u00dablicas",
    "sg:phone":"+34 956 31 17 55",
    "sg:postcode":"11407",
    "sg:province":"C\u00e1diz",
    "wof:name":"Guarderias Jerezanas S. A.",
    "wof:placetype":"venue"
},
  "geometry": {"coordinates":[-6.1349639893,36.7040481567],"type":"Point"}
}