{
  "type": "Feature",
  "properties": {
    "iso:country":"ES",
    "sg:address":"Carrer de Sant Hipolit, 4",
    "sg:city":"Barcelona",
    "sg:orig_category":"Agencias Y Agentes Comerciales, Representantes",
    "sg:phone":"+34 933 45 68 13",
    "sg:postcode":"08030",
    "sg:province":"Barcelona",
    "wof:name":"Mora Campon Hector",
    "wof:placetype":"venue"
},
  "geometry": {"coordinates":[2.187885046,41.4376525879],"type":"Point"}
}