{
  "type": "Feature",
  "properties": {
    "iso:country":"ES",
    "sg:address":"Calle de J, 27",
    "sg:city":"Mutiloabeiti",
    "sg:orig_category":"Fotograf\u00cda Publicitaria E Industrial",
    "sg:phone":"+34 948 23 50 25",
    "sg:postcode":"31192",
    "sg:province":"Navarra",
    "wof:name":"Ederra Sancho Francisco Javier",
    "wof:placetype":"venue"
},
  "geometry": {"coordinates":[-1.6213389635,42.7853355408],"type":"Point"}
}