{
  "type": "Feature",
  "properties": {
    "iso:country":"ES",
    "sg:address":"Carrer de Floridablanca, 28",
    "sg:city":"Hospitalet Llobregat",
    "sg:orig_category":"Arreglo, Reparaci\u00d3n, Piezas Sueltas De Televisi\u00d3n, V\u00cddeo, Hi",
    "sg:phone":"+34 934 38 74 53",
    "sg:postcode":"08906",
    "sg:province":"Barcelona",
    "wof:name":"Alvarez Fernandez Jose",
    "wof:placetype":"venue"
},
  "geometry": {"coordinates":[2.1026332378,41.3749809265],"type":"Point"}
}