{
  "type": "Feature",
  "properties": {
    "iso:country":"ES",
    "sg:address":"Calle de Nueva, 48",
    "sg:city":"Cieza",
    "sg:orig_category":"Reposter\u00cdas",
    "sg:phone":"+34 968 76 01 29",
    "sg:postcode":"30530",
    "sg:province":"Murcia",
    "wof:name":"Angosto Guirao Juan Jose",
    "wof:placetype":"venue"
},
  "geometry": {"coordinates":[-1.4278763533,38.2356719971],"type":"Point"}
}