{
  "type": "Feature",
  "properties": {
    "addr:full":"Calle de Timoteo Domingo, 39 Madrid Madrid 28017",
    "addr:housenumber":"39",
    "addr:postcode":"madrid;28017",
    "addr:street":"Calle De Timoteo Domingo",
    "iso:country":"ES",
    "sg:address":"Calle de Timoteo Domingo, 39",
    "sg:city":"Madrid",
    "sg:orig_category":"Ense\u00d1anza Variada",
    "sg:phone":"+34 902 44 46 66",
    "sg:postcode":"28017",
    "sg:province":"Madrid",
    "wof:name":"Centro De Estudios Academicos S.a.",
    "wof:placetype":"venue"
},
  "geometry": {"coordinates":[-3.644053936,40.4324302673],"type":"Point"}
}