{
  "type": "Feature",
  "properties": {
    "addr:full":"Carr Bisbe Iglesias Navarri, 42 Seu D'urgell Lleida 25700",
    "addr:housenumber":"42",
    "addr:postcode":"25700",
    "addr:street":"Carr Bisbe Iglesias Navarri",
    "iso:country":"ES",
    "sg:address":"Carr Bisbe Iglesias Navarri, 42",
    "sg:city":"Seu D'urgell",
    "sg:orig_category":"Venta, Instalaci\u00d3n De Calefacci\u00d3n",
    "sg:phone":"+34 973 36 00 85",
    "sg:postcode":"25700",
    "sg:province":"Lleida",
    "wof:name":"Miquel Bigorda Montserrat",
    "wof:placetype":"venue"
},
  "geometry": {"coordinates":[0.6457189918,41.6027946472],"type":"Point"}
}