{
  "type": "Feature",
  "properties": {
    "addr:full":"Calle de Fuente, 5 Madrid Madrid 28021",
    "addr:housenumber":"5",
    "addr:postcode":"28021",
    "addr:street":"Calle De Fuente",
    "iso:country":"ES",
    "sg:address":"Calle de Fuente, 5",
    "sg:city":"Madrid",
    "sg:orig_category":"Molduras, Junquillos, Listones Y Molduras Perforadas",
    "sg:phone":"+34 917 97 10 18",
    "sg:postcode":"28021",
    "sg:province":"Madrid",
    "wof:name":"Rodrigo Villena Mariano",
    "wof:placetype":"venue"
},
  "geometry": {"coordinates":[-3.7084751129,40.3460845947],"type":"Point"}
}