{
  "type": "Feature",
  "properties": {
    "addr:full":"Lili Alvarez, S/n Valdemoro Madrid 28340",
    "addr:postcode":"28340",
    "addr:street":"Lili Alvarez S / N Valdemoro",
    "iso:country":"ES",
    "sg:address":"Lili Alvarez, S/n",
    "sg:city":"Valdemoro",
    "sg:orig_category":"Promotores Constructores",
    "sg:phone":"+34 918 94 94 50",
    "sg:postcode":"28340",
    "sg:province":"Madrid",
    "wof:name":"Dragados S.a.",
    "wof:placetype":"venue"
},
  "geometry": {"coordinates":[-3.6902189255,40.2069587708],"type":"Point"}
}