{
  "type": "Feature",
  "properties": {
    "addr:full":"Calle de Cura Gonzalez, 33 Novelda Alicante 03660",
    "addr:housenumber":"33",
    "addr:postcode":"03660",
    "addr:street":"Calle De Cura Gonzalez",
    "iso:country":"ES",
    "sg:address":"Calle de Cura Gonzalez, 33",
    "sg:city":"Novelda",
    "sg:orig_category":"Contenedores (mercanc\u00cdas)",
    "sg:phone":"+34 965 60 31 33",
    "sg:postcode":"03660",
    "sg:province":"Alicante",
    "wof:name":"Parras Marcos Francisco",
    "wof:placetype":"venue"
},
  "geometry": {"coordinates":[-0.7748118043,38.381603241],"type":"Point"}
}