{
  "type": "Feature",
  "properties": {
    "iso:country":"ES",
    "sg:address":"Calle de Iru\u00d1alde, 11",
    "sg:city":"Berriozar",
    "sg:orig_category":"Ropa Para Se\u00d1oras (al Por Menor)",
    "sg:phone":"+34 948 30 01 57",
    "sg:postcode":"31013",
    "sg:province":"Navarra",
    "wof:name":"Alonso Moda Joven S.l.",
    "wof:placetype":"venue"
},
  "geometry": {"coordinates":[-1.6754404306,42.8364639282],"type":"Point"}
}