{
  "type": "Feature",
  "properties": {
    "addr:full":"Calle de Dean Castor Robledo, 16 Avila \u00c1vila 05003",
    "addr:housenumber":"16",
    "addr:postcode":"05003",
    "addr:street":"Calle De Dean Castor Robledo;A\u0301Vila",
    "iso:country":"ES",
    "sg:address":"Calle de Dean Castor Robledo, 16",
    "sg:city":"Avila",
    "sg:orig_category":"Mec\u00c1nico Del Autom\u00d3vil",
    "sg:phone":"+34 920 22 10 23",
    "sg:postcode":"05003",
    "sg:province":"\u00c1vila",
    "wof:name":"Jimenez Garcia Jose Manuel",
    "wof:placetype":"venue"
},
  "geometry": {"coordinates":[-4.6949954033,40.6530075073],"type":"Point"}
}