{
  "type": "Feature",
  "properties": {
    "iso:country":"ES",
    "sg:address":"Calle de Gabriel Lobo, 26",
    "sg:city":"Madrid",
    "sg:orig_category":"Tapicer\u00cdas",
    "sg:phone":"+34 914 11 13 98",
    "sg:postcode":"28002",
    "sg:province":"Madrid",
    "wof:name":"Antes Y Despues De La Cierva Y Cruzado C.b.",
    "wof:placetype":"venue"
},
  "geometry": {"coordinates":[-3.6794891357,40.4438476562],"type":"Point"}
}