{
  "type": "Feature",
  "properties": {
    "iso:country":"ES",
    "sg:address":"Avda Tombatossals, 73",
    "sg:city":"Castellon",
    "sg:orig_category":"Reposter\u00cdas",
    "sg:phone":"+34 964 21 61 89",
    "sg:postcode":"12004",
    "sg:province":"Castell\u00f3n",
    "wof:name":"Valls Miquel Juan Antonio",
    "wof:placetype":"venue"
},
  "geometry": {"coordinates":[-0.0438689999,39.9977912903],"type":"Point"}
}