{
  "type": "Feature",
  "properties": {
    "iso:country":"ES",
    "sg:address":"Poligono 2 (bunyola), Km. 0006,2",
    "sg:city":"Es Garrovers",
    "sg:orig_category":"Deportes Diversos",
    "sg:phone":"+34 971 79 66 07",
    "sg:postcode":"07141",
    "sg:province":"Islas Baleares",
    "wof:name":"Club De Tiro Olimpico Mallorca",
    "wof:placetype":"venue"
},
  "geometry": {"coordinates":[2.7445349693,39.6195487976],"type":"Point"}
}