{
  "type": "Feature",
  "properties": {
    "iso:country":"ES",
    "sg:address":"Calle de Sagrario, 2",
    "sg:city":"Alfafar",
    "sg:orig_category":"Inmobiliaria (agencias)",
    "sg:phone":"+34 963 75 31 81",
    "sg:postcode":"46910",
    "sg:province":"Valencia",
    "wof:name":"Mendoza Ca\u00f1avate S.l.",
    "wof:placetype":"venue"
},
  "geometry": {"coordinates":[-0.3895339966,39.4232254028],"type":"Point"}
}