{
  "type": "Feature",
  "properties": {
    "iso:country":"ES",
    "sg:address":"Calle de Ciudad De San Roque, S/n",
    "sg:city":"Cadiz",
    "sg:orig_category":"Bater\u00cdas",
    "sg:phone":"+34 956 27 11 16",
    "sg:postcode":"11011",
    "sg:province":"C\u00e1diz",
    "wof:name":"Reparacion Y Distribucion De Baterias S.a.l.",
    "wof:placetype":"venue"
},
  "geometry": {"coordinates":[-6.267373085,36.4982452393],"type":"Point"}
}