{
  "type": "Feature",
  "properties": {
    "addr:full":"Avda Pintor Xavier Soler, 7 Alacant Alicante 03015",
    "addr:housenumber":"7",
    "addr:postcode":"03015",
    "addr:street":"Avda Pintor Xavier Soler",
    "iso:country":"ES",
    "sg:address":"Avda Pintor Xavier Soler, 7",
    "sg:city":"Alacant",
    "sg:orig_category":"Cajas De Ahorro",
    "sg:phone":"+34 965 91 65 40",
    "sg:postcode":"03015",
    "sg:province":"Alicante",
    "wof:name":"Caja De Ahorros De Valencia Castellon Y Alicante",
    "wof:placetype":"venue"
},
  "geometry": {"coordinates":[-0.4703339934,38.3656768799],"type":"Point"}
}