{
  "type": "Feature",
  "properties": {
    "iso:country":"ES",
    "sg:address":"Carrer de Narcis De Monturiol, 116",
    "sg:city":"Hospitalet Llobregat",
    "sg:orig_category":"Maquinaria Para Industrias Diversas",
    "sg:phone":"+34 934 32 00 26",
    "sg:postcode":"08902",
    "sg:province":"Barcelona",
    "wof:name":"Fijaciones Norma S.a.",
    "wof:placetype":"venue"
},
  "geometry": {"coordinates":[2.1217000484,41.3632202148],"type":"Point"}
}