{
  "type": "Feature",
  "properties": {
    "addr:full":"Pg Carretera, 52 Benidorm Alicante 03500",
    "addr:housenumber":"52",
    "addr:postcode":"03500",
    "addr:street":"Carretera",
    "iso:country":"ES",
    "sg:address":"Pg Carretera, 52",
    "sg:city":"Benidorm",
    "sg:orig_category":"Sociedades, Compa\u00d1\u00cdas Aseguradoras",
    "sg:phone":"+34 966 81 11 06",
    "sg:postcode":"03500",
    "sg:province":"Alicante",
    "wof:name":"Saez Medina Miguel",
    "wof:placetype":"venue"
},
  "geometry": {"coordinates":[-0.1323889941,38.5365257263],"type":"Point"}
}