{
  "type": "Feature",
  "properties": {
    "iso:country":"ES",
    "sg:address":"Avda San Francisco Javier, S/n",
    "sg:city":"Sevilla",
    "sg:orig_category":"Ense\u00d1anza Variada",
    "sg:phone":"+34 954 66 10 33",
    "sg:postcode":"41005",
    "sg:province":"Sevilla",
    "sg:website":"www.cede.es",
    "wof:name":"Centro Documentacion De Estudios Y Oposiciones S.l.",
    "wof:placetype":"venue"
},
  "geometry": {"coordinates":[-5.9732937813,37.3819160461],"type":"Point"}
}