{
  "type": "Feature",
  "properties": {
    "iso:country":"ES",
    "sg:address":"Avda Americas (las), 8",
    "sg:city":"Mairena Aljarafe",
    "sg:orig_category":"Inmobiliaria (agencias)",
    "sg:phone":"+34 954 18 16 64",
    "sg:postcode":"41927",
    "sg:province":"Sevilla",
    "sg:website":"www.inmobiliarias-almagado.com",
    "wof:name":"Desarrollo E Intermediacion Urbanistica S.l.",
    "wof:placetype":"venue"
},
  "geometry": {"coordinates":[-6.0495390892,37.3502044678],"type":"Point"}
}