{
  "type": "Feature",
  "properties": {
    "iso:country":"ES",
    "sg:address":"Carrer de Josep Anselm Clave, 6",
    "sg:city":"Barcelona",
    "sg:orig_category":"Obras Y Organismos Sociales",
    "sg:phone":"+34 934 12 72 17",
    "sg:postcode":"08002",
    "sg:province":"Barcelona",
    "wof:name":"Educacio Sense Fronteres",
    "wof:placetype":"venue"
},
  "geometry": {"coordinates":[2.1784739494,41.3779602051],"type":"Point"}
}