{
  "type": "Feature",
  "properties": {
    "iso:country":"ES",
    "sg:address":"Calle de Peruyal La, 1",
    "sg:city":"Arriondas",
    "sg:orig_category":"Ropa Para Caballeros (al Por Menor)",
    "sg:phone":"+34 985 84 08 38",
    "sg:postcode":"33540",
    "sg:province":"Asturias",
    "wof:name":"Garcia Larrea Manuel Fidel",
    "wof:placetype":"venue"
},
  "geometry": {"coordinates":[-5.1852741241,43.3902168274],"type":"Point"}
}