{
  "type": "Feature",
  "properties": {
    "iso:country":"ES",
    "sg:address":"Carrer de Sants, 91",
    "sg:city":"Barcelona",
    "sg:orig_category":"M\u00c9dicos: Estomatolog\u00cda",
    "sg:phone":"+34 933 32 46 13",
    "sg:postcode":"08014",
    "sg:province":"Barcelona",
    "wof:name":"Robledano Vicente Loreto",
    "wof:placetype":"venue"
},
  "geometry": {"coordinates":[2.1360480785,41.3753356934],"type":"Point"}
}