{
  "type": "Feature",
  "properties": {
    "addr:full":"Calle de Muguru, 8 Kurtzea Vizcaya 48960",
    "addr:housenumber":"8",
    "addr:postcode":"48960",
    "addr:street":"Calle De Muguru",
    "iso:country":"ES",
    "sg:address":"Calle de Muguru, 8",
    "sg:city":"Kurtzea",
    "sg:orig_category":"Diarios, Revistas Y Boletines (suscripciones)",
    "sg:phone":"+34 944 57 03 29",
    "sg:postcode":"48960",
    "sg:province":"Vizcaya",
    "wof:name":"Puente Cagigas Pilar",
    "wof:placetype":"venue"
},
  "geometry": {"coordinates":[-2.8413510323,43.2321739197],"type":"Point"}
}