{
  "type": "Feature",
  "properties": {
    "addr:full":"Calle de Camoens, 2 Ceuta Ceuta 51001",
    "addr:housenumber":"2",
    "addr:postcode":"51001",
    "addr:street":"Calle De Camoens",
    "iso:country":"ES",
    "sg:address":"Calle de Camoens, 2",
    "sg:city":"Ceuta",
    "sg:orig_category":"Laboratorios Y Trabajos De Fotograf\u00cda, V\u00cddeo Y Cine",
    "sg:phone":"+34 956 51 38 52",
    "sg:postcode":"51001",
    "sg:province":"Ceuta",
    "wof:name":"Casa Ros S. A.",
    "wof:placetype":"venue"
},
  "geometry": {"coordinates":[-5.3100190163,35.8872871399],"type":"Point"}
}