{
  "type": "Feature",
  "properties": {
    "addr:full":"Calle de Real, 13 Iscar Valladolid 47420",
    "addr:housenumber":"13",
    "addr:postcode":"47420",
    "addr:street":"Calle De Real",
    "iso:country":"ES",
    "sg:address":"Calle de Real, 13",
    "sg:city":"Iscar",
    "sg:orig_category":"Electrodom\u00c9sticos (al Por Menor)",
    "sg:phone":"+34 983 61 16 44",
    "sg:postcode":"47420",
    "sg:province":"Valladolid",
    "wof:name":"Ca\u00f1o Sanz Gaspar Del",
    "wof:placetype":"venue"
},
  "geometry": {"coordinates":[-4.5307540894,41.3635215759],"type":"Point"}
}