{
  "type": "Feature",
  "properties": {
    "iso:country":"ES",
    "sg:address":"Calle de Asuncion, 3",
    "sg:city":"Sevilla",
    "sg:classifiers":[
        {
            "category":"Casinos & Gambling",
            "type":"Entertainment"
        }
    ],
    "sg:phone":"+34 954 28 07 11",
    "sg:postcode":"41011",
    "sg:province":"Sevilla",
    "sg:tags":[
        "locale",
        "de",
        "juego"
    ],
    "wof:name":"Bingos Andaluces S.a.",
    "wof:placetype":"venue"
},
  "geometry": {"coordinates":[-5.9974718094,37.3792114258],"type":"Point"}
}