{
  "type": "Feature",
  "properties": {
    "iso:country":"ES",
    "sg:address":"Calle de Italia, 10",
    "sg:city":"Carrizal",
    "sg:orig_category":"Centros Empresariales",
    "sg:phone":"+34 928 78 62 79",
    "sg:postcode":"35240",
    "sg:province":"Las Palmas",
    "wof:name":"Ramirez Galvan Jose",
    "wof:placetype":"venue"
},
  "geometry": {"coordinates":[-15.4053573608,27.9128952026],"type":"Point"}
}