{
  "type": "Feature",
  "properties": {
    "iso:country":"ES",
    "sg:address":"Mossen Felix, 1",
    "sg:city":"Sitges",
    "sg:orig_category":"Ropa Para Caballeros (al Por Menor)",
    "sg:phone":"+34 938 11 01 50",
    "sg:postcode":"08870",
    "sg:province":"Barcelona",
    "wof:name":"Alvest  Jean Claude",
    "wof:placetype":"venue"
},
  "geometry": {"coordinates":[1.810002923,41.2362213135],"type":"Point"}
}