{
  "type": "Feature",
  "properties": {
    "addr:full":"Calle de Miguel De Unamuno, 10 Chiclana De La Frontera C\u00e1diz 11130",
    "addr:housenumber":"10",
    "addr:postcode":"11130",
    "addr:street":"Calle De Miguel De Unamuno",
    "iso:country":"ES",
    "sg:address":"Calle de Miguel De Unamuno, 10",
    "sg:city":"Chiclana De La Frontera",
    "sg:orig_category":"Escritores",
    "sg:phone":"+34 956 53 36 72",
    "sg:postcode":"11130",
    "sg:province":"C\u00e1diz",
    "wof:name":"Rosa Martin Antonio",
    "wof:placetype":"venue"
},
  "geometry": {"coordinates":[-6.1412611008,36.4239349365],"type":"Point"}
}