{
  "type": "Feature",
  "properties": {
    "iso:country":"ES",
    "sg:address":"Calle de General Pardi\u00d1as, 22",
    "sg:city":"Madrid",
    "sg:orig_category":"Trajes Y Adornos De Boda (confecci\u00d3n, Al Por Menor)",
    "sg:phone":"+34 915 77 12 51",
    "sg:postcode":"28001",
    "sg:province":"Madrid",
    "wof:name":"Lozano Jimenez Maria Luisa",
    "wof:placetype":"venue"
},
  "geometry": {"coordinates":[-3.6784319878,40.4254112244],"type":"Point"}
}