{
  "type": "Feature",
  "properties": {
    "iso:country":"ES",
    "sg:address":"Calle de San Andres, 54",
    "sg:city":"Coru\u00d1a",
    "sg:orig_category":"Bisuter\u00cda, Joyer\u00cda, Relojer\u00cda (al Por Menor)",
    "sg:phone":"+34 981 22 31 28",
    "sg:postcode":"15003",
    "sg:province":"La Coru\u00f1a",
    "wof:name":"Juan Lopez Seoane S. L.",
    "wof:placetype":"venue"
},
  "geometry": {"coordinates":[-8.4029111862,43.3702430725],"type":"Point"}
}