{
  "type": "Feature",
  "properties": {
    "addr:full":"Cra. Sant Esteban A Montseny, 169 S. Esteve Palautordera Barcelona 08461",
    "addr:housenumber":"169",
    "addr:postcode":"08461",
    "addr:street":"Esteban A Montseny;S. Esteve Palautordera Barcelona",
    "iso:country":"ES",
    "sg:address":"Cra. Sant Esteban A Montseny, 169",
    "sg:city":"S. Esteve Palautordera",
    "sg:classifiers":[
        {
            "category":"Arts & Performance",
            "subcategory":"Art Gallery",
            "type":"Entertainment"
        }
    ],
    "sg:phone":"+34 938 48 20 63",
    "sg:postcode":"08461",
    "sg:province":"Barcelona",
    "sg:tags":[
        "obras",
        "de",
        "coleccionismo",
        "compraventa",
        "arte",
        "y"
    ],
    "wof:name":"Broncano Atencia Maria Jose",
    "wof:placetype":"venue"
},
  "geometry": {"coordinates":[2.4317650795,41.706451416],"type":"Point"}
}