{
  "type": "Feature",
  "properties": {
    "addr:full":"El Cobo, 26 Mi\u00f1o La Coru\u00f1a 15630",
    "addr:housenumber":"26",
    "addr:postcode":"15630",
    "addr:street":"El Cobo;La Corun\u0303A",
    "iso:country":"ES",
    "sg:address":"El Cobo, 26",
    "sg:city":"Mi\u00f1o",
    "sg:orig_category":"Dibujos Animados",
    "sg:phone":"+34 981 78 30 32",
    "sg:postcode":"15630",
    "sg:province":"La Coru\u00f1a",
    "wof:name":"Pilar Libreria Papeleria S.l.",
    "wof:placetype":"venue"
},
  "geometry": {"coordinates":[-8.2091083527,43.3502922058],"type":"Point"}
}