{
  "type": "Feature",
  "properties": {
    "iso:country":"ES",
    "sg:address":"Calle de Malaga, 5",
    "sg:city":"Granada",
    "sg:orig_category":"Colchones (fabricaci\u00d3n, Al Por Mayor, Al Por Menor)",
    "sg:phone":"+34 958 27 93 26",
    "sg:postcode":"18001",
    "sg:province":"Granada",
    "wof:name":"Gonzalez Israel Francisco",
    "wof:placetype":"venue"
},
  "geometry": {"coordinates":[-3.6017889977,37.1773986816],"type":"Point"}
}