{
  "type": "Feature",
  "properties": {
    "addr:full":"Calle de Uria, 3 Oviedo Asturias 33003",
    "addr:housenumber":"3",
    "addr:postcode":"33003",
    "addr:street":"Calle De Uria",
    "iso:country":"ES",
    "sg:address":"Calle de Uria, 3",
    "sg:city":"Oviedo",
    "sg:orig_category":"Fabricaci\u00d3n De Bolsos Y Bolsos De Tela",
    "sg:phone":"+34 985 25 15 13",
    "sg:postcode":"33003",
    "sg:province":"Asturias",
    "sg:website":"www.blancoint.com",
    "wof:name":"Vagtex S.l.",
    "wof:placetype":"venue"
},
  "geometry": {"coordinates":[-5.8506350517,43.3634262085],"type":"Point"}
}