{
  "type": "Feature",
  "properties": {
    "addr:full":"Edif Helios, S/n Sevilla Sevilla 41020",
    "addr:housenumber":"s / n",
    "addr:postcode":"41020",
    "iso:country":"ES",
    "sg:address":"Edif Helios, S/n",
    "sg:city":"Sevilla",
    "sg:orig_category":"Inform\u00c1tica Equipo Y Programas (al Por Mayor)",
    "sg:phone":"+34 954 25 63 54",
    "sg:postcode":"41020",
    "sg:province":"Sevilla",
    "sg:website":"www.bizerba.com",
    "wof:name":"Balanzas Y Sistemas Bizerba S. A.",
    "wof:placetype":"venue"
},
  "geometry": {"coordinates":[-5.9356870651,37.4206848145],"type":"Point"}
}