{
  "type": "Feature",
  "properties": {
    "addr:full":"Carrer de Pere Catala I Pic, 1 Valls Tarragona 43800",
    "addr:housenumber":"1",
    "addr:postcode":"43800",
    "addr:street":"Carrer De Pere Catala I Pic",
    "iso:country":"ES",
    "sg:address":"Carrer de Pere Catala I Pic, 1",
    "sg:city":"Valls",
    "sg:orig_category":"Agencias Y Agentes Comerciales, Representantes",
    "sg:phone":"+34 977 60 17 87",
    "sg:postcode":"43800",
    "sg:province":"Tarragona",
    "wof:name":"Pares Miralles Francisco",
    "wof:placetype":"venue"
},
  "geometry": {"coordinates":[1.2470170259,41.2893333435],"type":"Point"}
}