{
  "type": "Feature",
  "properties": {
    "addr:full":"Avda Valencia, 11 Zaragoza Zaragoza 50005",
    "addr:housenumber":"11",
    "addr:postcode":"50005",
    "addr:street":"Avda Valencia",
    "iso:country":"ES",
    "sg:address":"Avda Valencia, 11",
    "sg:city":"Zaragoza",
    "sg:orig_category":"Frutas Y Legumbres Secas (al Por Mayor)",
    "sg:phone":"+34 976 55 52 36",
    "sg:postcode":"50005",
    "sg:province":"Zaragoza",
    "wof:name":"Ruiz Franco Mercedes",
    "wof:placetype":"venue"
},
  "geometry": {"coordinates":[-0.8948029876,41.6470222473],"type":"Point"}
}