{
  "type": "Feature",
  "properties": {
    "iso:country":"ES",
    "sg:address":"Pl. Mayor, S/n",
    "sg:city":"Tubilla Lago",
    "sg:orig_category":"Centros De Educaci\u00d3n Especial",
    "sg:phone":"+34 947 55 70 27",
    "sg:postcode":"09453",
    "sg:province":"Burgos",
    "wof:name":"C.r.a. Diego Marin",
    "wof:placetype":"venue"
},
  "geometry": {"coordinates":[-3.591119051,41.8138618469],"type":"Point"}
}