{
  "type": "Feature",
  "properties": {
    "iso:country":"ES",
    "sg:address":"Calle de Progreso, 40",
    "sg:city":"Rua De Valdeorras",
    "sg:orig_category":"Reposter\u00cdas",
    "sg:phone":"+34 988 31 06 20",
    "sg:postcode":"32350",
    "sg:province":"Ourense",
    "wof:name":"Rodriguez Rodil Manuel Jesus",
    "wof:placetype":"venue"
},
  "geometry": {"coordinates":[-7.1205739975,42.392490387],"type":"Point"}
}