{
  "type": "Feature",
  "properties": {
    "iso:country":"ES",
    "sg:address":"Dism Estacada Espino, S/n",
    "sg:city":"Pedroso",
    "sg:orig_category":"Poller\u00cda Y Caza (al Por Menor)",
    "sg:phone":"+34 954 88 91 09",
    "sg:postcode":"41360",
    "sg:province":"Sevilla",
    "wof:name":"Naranjo Garcia Jose",
    "wof:placetype":"venue"
},
  "geometry": {"coordinates":[-5.7650637627,37.8378601074],"type":"Point"}
}