{
  "type": "Feature",
  "properties": {
    "addr:full":"Calle de Andres Torrejon, 24 Madrid Madrid 28014",
    "addr:housenumber":"24",
    "addr:postcode":"madrid;28014",
    "addr:street":"Calle De Andres Torrejon",
    "iso:country":"ES",
    "sg:address":"Calle de Andres Torrejon, 24",
    "sg:city":"Madrid",
    "sg:orig_category":"Peluqueros: De Se\u00d1oras",
    "sg:phone":"+34 914 33 94 40",
    "sg:postcode":"28014",
    "sg:province":"Madrid",
    "wof:name":"Santos Fernandez Laura",
    "wof:placetype":"venue"
},
  "geometry": {"coordinates":[-3.6823310852,40.4083824158],"type":"Point"}
}