{
  "type": "Feature",
  "properties": {
    "addr:full":"Calle de Diego Mu\u00d1oz Torrero, 4 Merida Badajoz 06800",
    "addr:housenumber":"4",
    "addr:postcode":"06800",
    "addr:street":"Calle De Diego Mun\u0303Oz Torrero",
    "iso:country":"ES",
    "sg:address":"Calle de Diego Mu\u00d1oz Torrero, 4",
    "sg:city":"Merida",
    "sg:orig_category":"Peluqueros: De Se\u00d1oras",
    "sg:phone":"+34 924 30 49 30",
    "sg:postcode":"06800",
    "sg:province":"Badajoz",
    "wof:name":"Lozano Sanchez Milagros",
    "wof:placetype":"venue"
},
  "geometry": {"coordinates":[-6.3651571274,38.9394264221],"type":"Point"}
}