{
  "type": "Feature",
  "properties": {
    "iso:country":"ES",
    "sg:address":"Pauet, S/n",
    "sg:city":"S. Joan Funat",
    "sg:orig_category":"Venta, Instalaci\u00d3n De Cocinas",
    "sg:phone":"+34 973 35 34 84",
    "sg:postcode":"25799",
    "sg:province":"Lleida",
    "wof:name":"Fabrega Isanta Joana",
    "wof:placetype":"venue"
},
  "geometry": {"coordinates":[1.4720100164,42.4348068237],"type":"Point"}
}