{
  "type": "Feature",
  "properties": {
    "addr:full":"Calle de Gran Breta\u00d1a, 7 Caceres C\u00e1ceres 10005",
    "addr:housenumber":"7",
    "addr:postcode":"10005",
    "addr:street":"Calle De Gran Bretan\u0303A;Ca\u0301Ceres",
    "iso:country":"ES",
    "sg:address":"Calle de Gran Breta\u00d1a, 7",
    "sg:city":"Caceres",
    "sg:orig_category":"Alquiler De Casas Y Habitaciones Amuebladas",
    "sg:phone":"+34 927 23 78 65",
    "sg:postcode":"10005",
    "sg:province":"C\u00e1ceres",
    "wof:name":"Instituto Secular De Derecho Diocesano Cruzados De Santa Maria",
    "wof:placetype":"venue"
},
  "geometry": {"coordinates":[-6.3808226585,39.4653320312],"type":"Point"}
}