{
  "type": "Feature",
  "properties": {
    "addr:full":"Calle de Rollo, 7 Madrid Madrid 28005",
    "addr:housenumber":"7",
    "addr:postcode":"madrid;28005",
    "addr:street":"Calle De Rollo",
    "iso:country":"ES",
    "sg:address":"Calle de Rollo, 7",
    "sg:city":"Madrid",
    "sg:orig_category":"Empresarios Y Productoras De Espect\u00c1culos",
    "sg:phone":"+34 915 41 72 95",
    "sg:postcode":"28005",
    "sg:province":"Madrid",
    "sg:website":"www.armachina.com",
    "wof:name":"Ars Machina S.l.",
    "wof:placetype":"venue"
},
  "geometry": {"coordinates":[-3.7111997604,40.4139633179],"type":"Point"}
}