{
  "type": "Feature",
  "properties": {
    "iso:country":"ES",
    "sg:address":"Calle de Mayor, 136",
    "sg:city":"Garres",
    "sg:orig_category":"Farmacias",
    "sg:phone":"+34 968 82 04 04",
    "sg:postcode":"30158",
    "sg:province":"Murcia",
    "wof:name":"Orenes Barcelo Maria",
    "wof:placetype":"venue"
},
  "geometry": {"coordinates":[-1.0905519724,37.9586448669],"type":"Point"}
}