{
  "type": "Feature",
  "properties": {
    "iso:country":"ES",
    "sg:address":"Carr Valencia, 158",
    "sg:city":"Algemesi",
    "sg:orig_category":"Sociedades, Compa\u00d1\u00cdas Aseguradoras",
    "sg:phone":"+34 962 48 12 16",
    "sg:postcode":"46680",
    "sg:province":"Valencia",
    "sg:website":"www.fremap.es",
    "wof:name":"Fremap-mutua De Accidentes De Trabajo Y Enfermedades Profesionales De La Seguridad Social",
    "wof:placetype":"venue"
},
  "geometry": {"coordinates":[-0.4342089891,39.1948165894],"type":"Point"}
}