{
  "type": "Feature",
  "properties": {
    "addr:full":"Avda Extremadura, 122 Talavera Real Badajoz 06140",
    "addr:housenumber":"122",
    "addr:postcode":"06140",
    "addr:street":"Avda Extremadura",
    "iso:country":"ES",
    "sg:address":"Avda Extremadura, 122",
    "sg:city":"Talavera Real",
    "sg:orig_category":"Radiocomunicaciones, Telefon\u00cda M\u00d3vil, Radiomensajer\u00cda: Servicios, Comercializaci\u00d3n",
    "sg:phone":"+34 924 44 03 97",
    "sg:postcode":"06140",
    "sg:province":"Badajoz",
    "wof:name":"Centro Moviles Badajoz S.l.",
    "wof:placetype":"venue"
},
  "geometry": {"coordinates":[-6.7664089203,38.87474823],"type":"Point"}
}