{
  "type": "Feature",
  "properties": {
    "addr:full":"Calle de Francisco De Orellana, S/n Utrera Sevilla 41710",
    "addr:housenumber":"s / n",
    "addr:postcode":"41710",
    "addr:street":"Calle De Francisco De Orellana",
    "iso:country":"ES",
    "sg:address":"Calle de Francisco De Orellana, S/n",
    "sg:city":"Utrera",
    "sg:orig_category":"Supermercados Y Hipermercados",
    "sg:phone":"+34 954 86 24 12",
    "sg:postcode":"41710",
    "sg:province":"Sevilla",
    "sg:website":"www.mercadona.es",
    "wof:name":"Mercadona S.a.",
    "wof:placetype":"venue"
},
  "geometry": {"coordinates":[-5.775788784,37.1827316284],"type":"Point"}
}