{
  "type": "Feature",
  "properties": {
    "addr:full":"Calle de Beato Tomas De Zumarraga, 1 Vitoria-gasteiz \u00c1lava 01008",
    "addr:housenumber":"1",
    "addr:postcode":"01008",
    "addr:street":"Calle De Beato Tomas De Zumarraga",
    "iso:country":"ES",
    "sg:address":"Calle de Beato Tomas De Zumarraga, 1",
    "sg:city":"Vitoria-gasteiz",
    "sg:orig_category":"Centros De Coordinaci\u00d3n",
    "sg:phone":"+34 945 23 15 20",
    "sg:postcode":"01008",
    "sg:province":"\u00c1lava",
    "sg:website":"www.isurkide.com",
    "wof:name":"Isurkide Consultores Y Gestores S.l.",
    "wof:placetype":"venue"
},
  "geometry": {"coordinates":[-2.6764476299,42.8493461609],"type":"Point"}
}