{
  "type": "Feature",
  "properties": {
    "iso:country":"ES",
    "sg:address":"Avda Balsicas, 28",
    "sg:city":"Roldan",
    "sg:orig_category":"Promotores Constructores",
    "sg:phone":"+34 968 58 94 04",
    "sg:postcode":"30709",
    "sg:province":"Murcia",
    "wof:name":"S.b.m. Servicios Integrados S.l.",
    "wof:placetype":"venue"
},
  "geometry": {"coordinates":[-1.000535965,37.8011932373],"type":"Point"}
}