{
  "type": "Feature",
  "properties": {
    "addr:full":"Pase Ezequiel Gonzalez, 20 Segovia Segovia 40002",
    "addr:housenumber":"20",
    "addr:postcode":"40002",
    "addr:street":"Gonzalez",
    "iso:country":"ES",
    "sg:address":"Pase Ezequiel Gonzalez, 20",
    "sg:city":"Segovia",
    "sg:orig_category":"Abogados",
    "sg:phone":"+34 921 44 37 75",
    "sg:postcode":"40002",
    "sg:province":"Segovia",
    "wof:name":"Gonzalez Aguado Jose Ignacio",
    "wof:placetype":"venue"
},
  "geometry": {"coordinates":[-4.1213312149,40.9448547363],"type":"Point"}
}