{
  "type": "Feature",
  "properties": {
    "iso:country":"ES",
    "sg:address":"Calle de Compas De Santo Domingo, 15",
    "sg:city":"Ciudad Real",
    "sg:orig_category":"Encuadernaci\u00d3n E Impresi\u00d3n De Folletos",
    "sg:phone":"+34 926 22 20 79",
    "sg:postcode":"13004",
    "sg:province":"Ciudad Real",
    "wof:name":"Orejudo Murillo Jose",
    "wof:placetype":"venue"
},
  "geometry": {"coordinates":[-3.9240705967,38.9860458374],"type":"Point"}
}