{
  "type": "Feature",
  "properties": {
    "iso:country":"ES",
    "sg:address":"Geltoki Kalea-calle Estacion, 14",
    "sg:city":"Lasarte",
    "sg:orig_category":"Centros Comerciales Y Grandes Tiendas",
    "sg:phone":"+34 943 37 79 83",
    "sg:postcode":"20160",
    "sg:province":"Guip\u00f9zcoa",
    "wof:name":"Jianliang  Feng",
    "wof:placetype":"venue"
},
  "geometry": {"coordinates":[-2.020414114,43.2698173523],"type":"Point"}
}