{
  "type": "Feature",
  "properties": {
    "iso:country":"ES",
    "sg:address":"Calle de Padre Arintero, 5",
    "sg:city":"Le\u00f3n",
    "sg:orig_category":"Peleter\u00cdas",
    "sg:phone":"+34 987 22 22 26",
    "sg:postcode":"24001",
    "sg:province":"Le\u00f3n",
    "wof:name":"Alvarez Sevilla Natividad",
    "wof:placetype":"venue"
},
  "geometry": {"coordinates":[-5.5769414902,42.5990982056],"type":"Point"}
}