{
  "type": "Feature",
  "properties": {
    "iso:country":"ES",
    "sg:address":"Av Puerto Rico, 26",
    "sg:city":"Tossa",
    "sg:orig_category":"Panader\u00cdas, Panader\u00cdas",
    "sg:phone":"+34 972 34 02 71",
    "sg:postcode":"17320",
    "sg:province":"Girona",
    "wof:name":"Panificadora De Tossa S.l.",
    "wof:placetype":"venue"
},
  "geometry": {"coordinates":[2.9273300171,41.7238693237],"type":"Point"}
}