{
  "type": "Feature",
  "properties": {
    "addr:full":"Prag Mas D'en Cisa, S/n Sentmenat Barcelona 08181",
    "addr:housenumber":"s / n",
    "addr:postcode":"08181",
    "iso:country":"ES",
    "sg:address":"Prag Mas D'en Cisa, S/n",
    "sg:city":"Sentmenat",
    "sg:orig_category":"F\u00c1bricas De Ladrillo Y Tejas",
    "sg:phone":"+34 937 15 06 73",
    "sg:postcode":"08181",
    "sg:province":"Barcelona",
    "wof:name":"Gali Rajolers S.l.",
    "wof:placetype":"venue"
},
  "geometry": {"coordinates":[2.1389029026,41.6162223816],"type":"Point"}
}