{
  "type": "Feature",
  "properties": {
    "addr:full":"Carrer de Anselm Clave, 2 Eixample Barcelona 08150",
    "addr:housenumber":"2",
    "addr:postcode":"08150",
    "addr:street":"Carrer De Anselm Clave",
    "iso:country":"ES",
    "sg:address":"Carrer de Anselm Clave, 2",
    "sg:city":"Eixample",
    "sg:orig_category":"Reposter\u00cdas",
    "sg:phone":"+34 935 62 25 54",
    "sg:postcode":"08150",
    "sg:province":"Barcelona",
    "wof:name":"Lozano Gallardo Candido",
    "wof:placetype":"venue"
},
  "geometry": {"coordinates":[2.2319469452,41.5694198608],"type":"Point"}
}