{
  "type": "Feature",
  "properties": {
    "addr:full":"Calle de Fernan Gonzalez, 16 Madrid Madrid 28009",
    "addr:housenumber":"16",
    "addr:postcode":"madrid;28009",
    "addr:street":"Calle De Fernan Gonzalez",
    "iso:country":"ES",
    "sg:address":"Calle de Fernan Gonzalez, 16",
    "sg:city":"Madrid",
    "sg:orig_category":"Colchones (fabricaci\u00d3n, Al Por Mayor, Al Por Menor)",
    "sg:phone":"+34 915 76 60 76",
    "sg:postcode":"28009",
    "sg:province":"Madrid",
    "wof:name":"Cuesta De Oro Maria Pilar",
    "wof:placetype":"venue"
},
  "geometry": {"coordinates":[-3.6744399071,40.4231414795],"type":"Point"}
}