{
  "type": "Feature",
  "properties": {
    "addr:full":"Calle de Iglesia (la), 13 Caldas De Reis Pontevedra 36650",
    "addr:housenumber":"13",
    "addr:postcode":"36650",
    "addr:street":"Calle De Iglesia La",
    "iso:country":"ES",
    "sg:address":"Calle de Iglesia (la), 13",
    "sg:city":"Caldas De Reis",
    "sg:orig_category":"Institutos De Belleza",
    "sg:phone":"+34 986 54 02 28",
    "sg:postcode":"36650",
    "sg:province":"Pontevedra",
    "wof:name":"Pi\u00f1eiro Martinez Jose",
    "wof:placetype":"venue"
},
  "geometry": {"coordinates":[-8.6430425644,42.6041069031],"type":"Point"}
}