{
  "type": "Feature",
  "properties": {
    "iso:country":"ES",
    "sg:address":"Avda Mateo Bosch, 6",
    "sg:city":"Port D'andratx",
    "sg:orig_category":"Restaurantes",
    "sg:phone":"+34 971 67 41 64",
    "sg:postcode":"07157",
    "sg:province":"Islas Baleares",
    "wof:name":"Romero Garcia Francisco",
    "wof:placetype":"venue"
},
  "geometry": {"coordinates":[2.3900249004,39.5450210571],"type":"Point"}
}