{
  "type": "Feature",
  "properties": {
    "iso:country":"ES",
    "sg:address":"Calle de Alzada, 15",
    "sg:city":"Villafranca De Los Barros",
    "sg:orig_category":"Contenedores (mercanc\u00cdas)",
    "sg:phone":"+34 924 52 44 27",
    "sg:postcode":"06220",
    "sg:province":"Badajoz",
    "wof:name":"Claro Mancera Juan Gabriel",
    "wof:placetype":"venue"
},
  "geometry": {"coordinates":[-6.3393259048,38.5624313354],"type":"Point"}
}