{
  "type": "Feature",
  "properties": {
    "addr:full":"Cmno Abejar, S/n Garrapinillos Zaragoza 50190",
    "addr:housenumber":"s / n",
    "addr:postcode":"50190",
    "addr:street":"Cmno Abejar;Garrapinillos",
    "iso:country":"ES",
    "sg:address":"Cmno Abejar, S/n",
    "sg:city":"Garrapinillos",
    "sg:orig_category":"Teatros Y Salas De Espect\u00c1culos",
    "sg:phone":"+34 976 77 42 78",
    "sg:postcode":"50190",
    "sg:province":"Zaragoza",
    "wof:name":"Zaragoza Hng S.l.",
    "wof:placetype":"venue"
},
  "geometry": {"coordinates":[-0.9857519269,41.6770553589],"type":"Point"}
}