{
  "type": "Feature",
  "properties": {
    "addr:full":"Avda Li\u00d1os (los), S/n Jerez De La Frontera C\u00e1diz 11404",
    "addr:postcode":"11404",
    "addr:street":"Avda Lin\u0303Os Los S / N",
    "iso:country":"ES",
    "sg:address":"Avda Li\u00d1os (los), S/n",
    "sg:city":"Jerez De La Frontera",
    "sg:orig_category":"Librer\u00cdas",
    "sg:phone":"+34 956 31 33 43",
    "sg:postcode":"11404",
    "sg:province":"C\u00e1diz",
    "wof:name":"Lopez Calbellido Fernando",
    "wof:placetype":"venue"
},
  "geometry": {"coordinates":[-6.1442289352,36.6956939697],"type":"Point"}
}