{
  "type": "Feature",
  "properties": {
    "iso:country":"ES",
    "sg:address":"Cmno Moncofar, S/n",
    "sg:city":"Chilches",
    "sg:orig_category":"Arboricultura Y Producci\u00d3n De Frutas",
    "sg:phone":"+34 964 59 01 69",
    "sg:postcode":"12592",
    "sg:province":"Castell\u00f3n",
    "wof:name":"Fyffes Citrus S.l.",
    "wof:placetype":"venue"
},
  "geometry": {"coordinates":[-0.1846590042,39.7813034058],"type":"Point"}
}