{
  "type": "Feature",
  "properties": {
    "iso:country":"ES",
    "sg:address":"Carr Arminyana I Canut, D', 5",
    "sg:city":"Carcaixent",
    "sg:orig_category":"Pompas F\u00danebres, Inhumaciones Y Cremaciones",
    "sg:phone":"+34 962 43 51 86",
    "sg:postcode":"46740",
    "sg:province":"Valencia",
    "wof:name":"Tanatorio Virgen De Aguas Vivas S.l.",
    "wof:placetype":"venue"
},
  "geometry": {"coordinates":[-0.453204006,39.118888855],"type":"Point"}
}