{
  "type": "Feature",
  "properties": {
    "addr:full":"Calle de Eustasio Amilibia, 4 Donostia-san Sebastian Guip\u00f9zcoa 20011",
    "addr:housenumber":"4",
    "addr:postcode":"20011",
    "addr:street":"Calle De Eustasio Amilibia",
    "iso:country":"ES",
    "sg:address":"Calle de Eustasio Amilibia, 4",
    "sg:city":"Donostia-san Sebastian",
    "sg:orig_category":"Electricidad: Instaladores",
    "sg:phone":"+34 943 45 08 47",
    "sg:postcode":"20011",
    "sg:province":"Guip\u00f9zcoa",
    "wof:name":"Crespo Ruiz Miguel Angel",
    "wof:placetype":"venue"
},
  "geometry": {"coordinates":[-1.9759589434,43.3062858582],"type":"Point"}
}