{
  "type": "Feature",
  "properties": {
    "iso:country":"ES",
    "sg:address":"Calle de Egidazu Kaia, 15",
    "sg:city":"Ondarroa",
    "sg:orig_category":"Hielo Para Enfriar",
    "sg:phone":"+34 946 83 07 85",
    "sg:postcode":"48700",
    "sg:province":"Vizcaya",
    "wof:name":"Frigorifica Santa Clara S. A.",
    "wof:placetype":"venue"
},
  "geometry": {"coordinates":[-2.4197461605,43.3257026672],"type":"Point"}
}