{
  "type": "Feature",
  "properties": {
    "addr:full":"Calle de Ramon Y Cajal, 1 Coru\u00d1a La Coru\u00f1a 15006",
    "addr:housenumber":"1",
    "addr:postcode":"15006",
    "addr:street":"Calle De Ramon Y Cajal;La Corun\u0303A",
    "iso:country":"ES",
    "sg:address":"Calle de Ramon Y Cajal, 1",
    "sg:city":"Coru\u00d1a",
    "sg:orig_category":"Bisuter\u00cda, Joyer\u00cda, Relojer\u00cda (al Por Menor)",
    "sg:phone":"+34 981 24 95 22",
    "sg:postcode":"15006",
    "sg:province":"La Coru\u00f1a",
    "wof:name":"Joya 36 S. A.",
    "wof:placetype":"venue"
},
  "geometry": {"coordinates":[-8.4000263214,43.3573646545],"type":"Point"}
}