{
  "type": "Feature",
  "properties": {
    "addr:full":"Calle de San Isidro Labrador, 10 Santa Maria Del Paramo Le\u00f3n 24240",
    "addr:housenumber":"10",
    "addr:postcode":"24240",
    "addr:street":"Calle De San Isidro Labrador",
    "iso:country":"ES",
    "sg:address":"Calle de San Isidro Labrador, 10",
    "sg:city":"Santa Maria Del Paramo",
    "sg:orig_category":"Institutos De Belleza",
    "sg:phone":"+34 987 35 09 75",
    "sg:postcode":"24240",
    "sg:province":"Le\u00f3n",
    "wof:name":"Pozo Aparicio Maria Soraya",
    "wof:placetype":"venue"
},
  "geometry": {"coordinates":[-5.7497410774,42.3561668396],"type":"Point"}
}