{
  "type": "Feature",
  "properties": {
    "addr:full":"Barr Leizotz Auzoa, S/n Leizotz Guip\u00f9zcoa 20140",
    "addr:housenumber":"s / n",
    "addr:postcode":"20140",
    "addr:street":"Leizotz Auzoa;Leizotz Guipu\u0300Zcoa",
    "iso:country":"ES",
    "sg:address":"Barr Leizotz Auzoa, S/n",
    "sg:city":"Leizotz",
    "sg:orig_category":"Estudios Y Construcci\u00d3n De Acuarios Y Viveros",
    "sg:phone":"+34 943 59 23 65",
    "sg:postcode":"20140",
    "sg:province":"Guip\u00f9zcoa",
    "wof:name":"Truchas Erreka S.a.",
    "wof:placetype":"venue"
},
  "geometry": {"coordinates":[-2.0200839043,43.2191047668],"type":"Point"}
}