{
  "type": "Feature",
  "properties": {
    "addr:full":"Calle de Colon, 11 Almansa Albacete 02640",
    "addr:housenumber":"11",
    "addr:postcode":"02640",
    "addr:street":"Calle De Colon",
    "iso:country":"ES",
    "sg:address":"Calle de Colon, 11",
    "sg:city":"Almansa",
    "sg:orig_category":"Pescader\u00cdas (al Por Menor)",
    "sg:phone":"+34 967 31 14 19",
    "sg:postcode":"02640",
    "sg:province":"Albacete",
    "wof:name":"Gonzalez Martinez Juan Santiago",
    "wof:placetype":"venue"
},
  "geometry": {"coordinates":[-1.0955045223,38.8680725098],"type":"Point"}
}