{
  "type": "Feature",
  "properties": {
    "iso:country":"ES",
    "sg:address":"Ctra Alcazaren, 20",
    "sg:city":"Pedrajas S. Esteban",
    "sg:orig_category":"Sales (al Por Mayor)",
    "sg:phone":"+34 983 60 52 16",
    "sg:postcode":"47430",
    "sg:province":"Valladolid",
    "wof:name":"Sociedad Cooperativa Pi\u00f1onsol Castilla Y Leon",
    "wof:placetype":"venue"
},
  "geometry": {"coordinates":[-4.580698967,41.3408317566],"type":"Point"}
}