{
  "type": "Feature",
  "properties": {
    "iso:country":"ES",
    "sg:address":"Avda Andalucia, 50",
    "sg:city":"Torre Mar",
    "sg:orig_category":"Caf\u00c9s, Bares, Cervecer\u00cdas",
    "sg:phone":"+34 952 54 55 84",
    "sg:postcode":"29740",
    "sg:province":"M\u00e1laga",
    "wof:name":"Cafe Bar Las Yucas S.l.",
    "wof:placetype":"venue"
},
  "geometry": {"coordinates":[-4.441660881,36.7164268494],"type":"Point"}
}