{
  "type": "Feature",
  "properties": {
    "iso:country":"ES",
    "sg:address":"Carr D'en Lluis Vives, 11",
    "sg:city":"Benicarlo",
    "sg:orig_category":"Inform\u00c1tica, Ofim\u00c1tica (estudios, Asesor\u00cda, Ingenier\u00cda, Formaci\u00d3n)",
    "sg:phone":"+34 964 47 01 12",
    "sg:postcode":"12580",
    "sg:province":"Castell\u00f3n",
    "wof:name":"Ofimat Benicarlo S.l.",
    "wof:placetype":"venue"
},
  "geometry": {"coordinates":[0.4274570048,40.4203186035],"type":"Point"}
}