{
  "type": "Feature",
  "properties": {
    "iso:country":"ES",
    "sg:address":"Plaz Lauaxeta, 10",
    "sg:city":"Bilbao",
    "sg:orig_category":"Comerciantes Al Por Mayor De Vinos, Licores Y Alcoholes",
    "sg:phone":"+34 944 11 47 93",
    "sg:postcode":"48004",
    "sg:province":"Vizcaya",
    "sg:website":"www.bodega-alcanadre.com",
    "wof:name":"Bodegas Alcanadre-unai Etxebarrieta",
    "wof:placetype":"venue"
},
  "geometry": {"coordinates":[-2.9095129967,43.2506980896],"type":"Point"}
}