{
  "type": "Feature",
  "properties": {
    "addr:full":"Calle de San Vicente Martir, 78 Valencia Valencia 46002",
    "addr:housenumber":"78",
    "addr:postcode":"46002",
    "addr:street":"Calle De San Vicente Martir",
    "iso:country":"ES",
    "sg:address":"Calle de San Vicente Martir, 78",
    "sg:city":"Valencia",
    "sg:orig_category":"Perfumer\u00cda (al Por Menor)",
    "sg:phone":"+34 963 52 17 56",
    "sg:postcode":"46002",
    "sg:province":"Valencia",
    "wof:name":"Larza Belda Emilia",
    "wof:placetype":"venue"
},
  "geometry": {"coordinates":[-0.3791790009,39.469367981],"type":"Point"}
}