{
  "type": "Feature",
  "properties": {
    "iso:country":"ES",
    "sg:address":"Calle de Ruiz Hernandez, 10",
    "sg:city":"Valladolid",
    "sg:orig_category":"Edici\u00d3n De Diarios, Revistas, Boletines",
    "sg:phone":"+34 983 29 32 38",
    "sg:postcode":"47002",
    "sg:province":"Valladolid",
    "wof:name":"Editorial Sal Terrae Compa\u00f1ia De Jesus",
    "wof:placetype":"venue"
},
  "geometry": {"coordinates":[-4.7199840546,41.6526794434],"type":"Point"}
}