{
  "type": "Feature",
  "properties": {
    "iso:country":"ES",
    "sg:address":"Carrer de Balmes, 320",
    "sg:city":"Barcelona",
    "sg:orig_category":"M\u00c9dicos: Dermatolog\u00cda Y Venereolog\u00cda",
    "sg:phone":"+34 932 01 89 23",
    "sg:postcode":"08006",
    "sg:province":"Barcelona",
    "wof:name":"Mascaro Ballester Josep Maria",
    "wof:placetype":"venue"
},
  "geometry": {"coordinates":[2.1445670128,41.402885437],"type":"Point"}
}