{
  "type": "Feature",
  "properties": {
    "addr:full":"Avda Vicente Mortes, 6 Valladolid Valladolid 47014",
    "addr:housenumber":"6",
    "addr:postcode":"47014",
    "addr:street":"Avda Vicente Mortes",
    "iso:country":"ES",
    "sg:address":"Avda Vicente Mortes, 6",
    "sg:city":"Valladolid",
    "sg:orig_category":"Papeler\u00cdas, Librer\u00cdas",
    "sg:phone":"+34 983 34 55 04",
    "sg:postcode":"47014",
    "sg:province":"Valladolid",
    "wof:name":"Serrano  Maria Dolores",
    "wof:placetype":"venue"
},
  "geometry": {"coordinates":[-4.7366352081,41.6536178589],"type":"Point"}
}