{
  "type": "Feature",
  "properties": {
    "iso:country":"ES",
    "sg:address":"C/ Major, 14",
    "sg:city":"Inca",
    "sg:orig_category":"Estancos",
    "sg:phone":"+34 971 50 27 97",
    "sg:postcode":"07300",
    "sg:province":"Islas Baleares",
    "wof:name":"Melia Crespi Maria Magdalena",
    "wof:placetype":"venue"
},
  "geometry": {"coordinates":[2.9105296135,39.7212181091],"type":"Point"}
}