{
  "type": "Feature",
  "properties": {
    "addr:full":"C/ Teniente Ruiz, 13 Elche Alicante 03203",
    "addr:housenumber":"13",
    "addr:postcode":"03203",
    "addr:street":"C / Teniente Ruiz",
    "iso:country":"ES",
    "sg:address":"C/ Teniente Ruiz, 13",
    "sg:city":"Elche",
    "sg:orig_category":"Promotores Constructores",
    "sg:phone":"+34 965 42 56 15",
    "sg:postcode":"03203",
    "sg:province":"Alicante",
    "wof:name":"Construcciones Olican S.l.",
    "wof:placetype":"venue"
},
  "geometry": {"coordinates":[-0.6939229965,38.2660713196],"type":"Point"}
}