{
  "type": "Feature",
  "properties": {
    "addr:full":"Pg Valldaura, 172 Barcelona Barcelona 08042",
    "addr:housenumber":"172",
    "addr:postcode":"08042",
    "addr:street":"Pg Valldaura",
    "iso:country":"ES",
    "sg:address":"Pg Valldaura, 172",
    "sg:city":"Barcelona",
    "sg:orig_category":"Distribuci\u00d3n De Petr\u00d3leo Y Derivados",
    "sg:phone":"+34 933 53 09 28",
    "sg:postcode":"08042",
    "sg:province":"Barcelona",
    "wof:name":"Consum Sociedad Cooperativa Limitada",
    "wof:placetype":"venue"
},
  "geometry": {"coordinates":[2.1682479382,41.4389419556],"type":"Point"}
}