{
  "type": "Feature",
  "properties": {
    "iso:country":"ES",
    "sg:address":"Calle de Division Azul, 4",
    "sg:city":"Oviedo",
    "sg:orig_category":"Abogados",
    "sg:phone":"+34 985 23 11 66",
    "sg:postcode":"33013",
    "sg:province":"Asturias",
    "wof:name":"Martinez Barrial Jesus",
    "wof:placetype":"venue"
},
  "geometry": {"coordinates":[-5.8587965965,43.3624687195],"type":"Point"}
}