{
  "type": "Feature",
  "properties": {
    "addr:full":"Calle de Larga, 7 Molina Guadalajara 19300",
    "addr:housenumber":"7",
    "addr:postcode":"19300",
    "addr:street":"Calle De Larga",
    "iso:country":"ES",
    "sg:address":"Calle de Larga, 7",
    "sg:city":"Molina",
    "sg:orig_category":"Empresas De Carpinter\u00cda De Madera",
    "sg:phone":"+34 949 83 27 08",
    "sg:postcode":"19300",
    "sg:province":"Guadalajara",
    "wof:name":"Fernandez Garcia Jesus",
    "wof:placetype":"venue"
},
  "geometry": {"coordinates":[-1.8916330338,40.8456840515],"type":"Point"}
}