{
  "type": "Feature",
  "properties": {
    "iso:country":"ES",
    "sg:address":"Carr Plus Ultra, 11",
    "sg:city":"Faura",
    "sg:orig_category":"Bazares, Art\u00cdculos De Limpieza Y De Cocina (al Por Menor)",
    "sg:phone":"+34 962 60 28 13",
    "sg:postcode":"46512",
    "sg:province":"Valencia",
    "wof:name":"Navarro Segarra Maira Isabel",
    "wof:placetype":"venue"
},
  "geometry": {"coordinates":[-0.2669549882,39.7263031006],"type":"Point"}
}