{
  "type": "Feature",
  "properties": {
    "iso:country":"ES",
    "sg:address":"Grup Arrizar, 11",
    "sg:city":"Donostia-san Sebastian",
    "sg:orig_category":"Panader\u00cdas, Panader\u00cdas",
    "sg:phone":"+34 943 35 33 13",
    "sg:postcode":"20017",
    "sg:province":"Guip\u00f9zcoa",
    "wof:name":"Maria Carmen Alberdi Sagasti Y Otra C.b (pasteleria Gofy)",
    "wof:placetype":"venue"
},
  "geometry": {"coordinates":[-1.9294450283,43.3188705444],"type":"Point"}
}