{
  "type": "Feature",
  "properties": {
    "addr:full":"Plaz Constitucion (de La), 23 Linea De La Concepcion C\u00e1diz 11300",
    "addr:postcode":"11300",
    "addr:street":"Linea;La;Ca\u0301Diz",
    "iso:country":"ES",
    "sg:address":"Plaz Constitucion (de La), 23",
    "sg:city":"Linea De La Concepcion",
    "sg:orig_category":"Promotores Constructores",
    "sg:phone":"+34 956 76 24 69",
    "sg:postcode":"11300",
    "sg:province":"C\u00e1diz",
    "wof:name":"Dravo S.a.",
    "wof:placetype":"venue"
},
  "geometry": {"coordinates":[-5.340939045,36.1683044434],"type":"Point"}
}