{
  "type": "Feature",
  "properties": {
    "iso:country":"ES",
    "sg:address":"Carrer de Arago, 182",
    "sg:city":"Barcelona",
    "sg:orig_category":"Ense\u00d1anza, Formaci\u00d3n Profesional: Aprendizaje",
    "sg:phone":"+34 934 54 39 04",
    "sg:postcode":"08011",
    "sg:province":"Barcelona",
    "wof:name":"Centre De Telecomunicaciones De Catalunya",
    "wof:placetype":"venue"
},
  "geometry": {"coordinates":[2.1579890251,41.3867988586],"type":"Point"}
}