{
  "type": "Feature",
  "properties": {
    "iso:country":"ES",
    "sg:address":"Calle de Benavente, 16",
    "sg:city":"San Cristobal De Entrevi\u00e7as",
    "sg:orig_category":"Molduras, Junquillos, Listones Y Molduras Perforadas",
    "sg:phone":"+34 980 64 40 28",
    "sg:postcode":"49690",
    "sg:province":"Zamora",
    "wof:name":"Ferreras Ma\u00f1anes Sigerico",
    "wof:placetype":"venue"
},
  "geometry": {"coordinates":[-5.7462787628,41.5033454895],"type":"Point"}
}