{
  "type": "Feature",
  "properties": {
    "addr:full":"C/ Gregori Casasempere Juan, 3 Alcoi Alicante 03802",
    "addr:housenumber":"3",
    "addr:postcode":"03802",
    "addr:street":"C / Gregori Casasempere Juan",
    "iso:country":"ES",
    "sg:address":"C/ Gregori Casasempere Juan, 3",
    "sg:city":"Alcoi",
    "sg:orig_category":"Escayola Y Productos De Escayola (fabricaci\u00d3n, Al Por Mayor)",
    "sg:phone":"+34 965 33 15 81",
    "sg:postcode":"03802",
    "sg:province":"Alicante",
    "wof:name":"Valls Bernabeu Luis",
    "wof:placetype":"venue"
},
  "geometry": {"coordinates":[-0.4852269888,38.6923141479],"type":"Point"}
}