{
  "type": "Feature",
  "properties": {
    "addr:full":"Calle de Cebreros, 88 Madrid Madrid 28011",
    "addr:housenumber":"88",
    "addr:postcode":"madrid;28011",
    "addr:street":"Calle De Cebreros",
    "iso:country":"ES",
    "sg:address":"Calle de Cebreros, 88",
    "sg:city":"Madrid",
    "sg:classifiers":[
        {
            "category":"Personal",
            "subcategory":"Barber",
            "type":"Services"
        }
    ],
    "sg:phone":"+34 914 79 24 34",
    "sg:postcode":"28011",
    "sg:province":"Madrid",
    "sg:tags":[
        "caballeros",
        "de",
        "peluqueros"
    ],
    "wof:name":"Fuentes Fernandez Jose",
    "wof:placetype":"venue"
},
  "geometry": {"coordinates":[-3.7494158745,40.4042396545],"type":"Point"}
}