{
  "type": "Feature",
  "properties": {
    "addr:full":"Carrer de Acacia, 7 Cornella Llobregat Barcelona 08940",
    "addr:housenumber":"7",
    "addr:postcode":"08940",
    "addr:street":"Carrer De Acacia",
    "iso:country":"ES",
    "sg:address":"Carrer de Acacia, 7",
    "sg:city":"Cornella Llobregat",
    "sg:orig_category":"Abogados",
    "sg:phone":"+34 934 71 17 03",
    "sg:postcode":"08940",
    "sg:province":"Barcelona",
    "wof:name":"Garcia Castilla Manuel",
    "wof:placetype":"venue"
},
  "geometry": {"coordinates":[2.0817549229,41.3637008667],"type":"Point"}
}