{
  "type": "Feature",
  "properties": {
    "iso:country":"ES",
    "sg:address":"Calle de Portalada (la), 48",
    "sg:city":"Logro\u00f1o",
    "sg:orig_category":"Empresas De Vigilancia, Guardia Y Protecci\u00d3n",
    "sg:phone":"+34 941 26 33 66",
    "sg:postcode":"26006",
    "sg:province":"La Rioja",
    "wof:name":"Prosegur Cia De Seguridad",
    "wof:placetype":"venue"
},
  "geometry": {"coordinates":[-2.4042050838,42.4592475891],"type":"Point"}
}