{
  "type": "Feature",
  "properties": {
    "addr:full":"Blas Infante, 1 Tomares Sevilla 41940",
    "addr:housenumber":"1",
    "addr:postcode":"41940",
    "addr:street":"Blas Infante",
    "iso:country":"ES",
    "sg:address":"Blas Infante, 1",
    "sg:city":"Tomares",
    "sg:orig_category":"Artes Gr\u00c1ficas, Artes Pl\u00c1sticas: Material Y Suministros (al Por Menor)",
    "sg:phone":"+34 954 15 67 62",
    "sg:postcode":"41940",
    "sg:province":"Sevilla",
    "wof:name":"Hermandad Sacramental De Tomares",
    "wof:placetype":"venue"
},
  "geometry": {"coordinates":[-6.0466790199,37.3741836548],"type":"Point"}
}