{
  "type": "Feature",
  "properties": {
    "addr:full":"Rua Dolores, 23 Ferrol La Coru\u00f1a 15402",
    "addr:housenumber":"23",
    "addr:postcode":"15402",
    "addr:street":"Rua Dolores;La Corun\u0303A",
    "iso:country":"ES",
    "sg:address":"Rua Dolores, 23",
    "sg:city":"Ferrol",
    "sg:orig_category":"Notarios",
    "sg:phone":"+34 981 35 21 99",
    "sg:postcode":"15402",
    "sg:province":"La Coru\u00f1a",
    "wof:name":"Aceituno Perez Manuel",
    "wof:placetype":"venue"
},
  "geometry": {"coordinates":[-8.2354755402,43.4833564758],"type":"Point"}
}