{
  "type": "Feature",
  "properties": {
    "addr:full":"Plaz Mayor, 16 Altorricon Huesca 22540",
    "addr:housenumber":"16",
    "addr:postcode":"22540",
    "addr:street":"Plaz Mayor",
    "iso:country":"ES",
    "sg:address":"Plaz Mayor, 16",
    "sg:city":"Altorricon",
    "sg:orig_category":"Restaurantes",
    "sg:phone":"+34 974 42 50 28",
    "sg:postcode":"22540",
    "sg:province":"Huesca",
    "wof:name":"Ari\u00f1o Aldabo Antonio Javier",
    "wof:placetype":"venue"
},
  "geometry": {"coordinates":[0.4140174985,41.8021469116],"type":"Point"}
}