{
  "type": "Feature",
  "properties": {
    "addr:full":"Rond Alfons Xii, 75 Mataro Barcelona 08302",
    "addr:postcode":"08302",
    "iso:country":"ES",
    "sg:address":"Rond Alfons Xii, 75",
    "sg:city":"Mataro",
    "sg:orig_category":"Caf\u00c9s, Bares, Cervecer\u00cdas",
    "sg:phone":"+34 937 41 55 99",
    "sg:postcode":"08302",
    "sg:province":"Barcelona",
    "wof:name":"Bbbeli Cups S L",
    "wof:placetype":"venue"
},
  "geometry": {"coordinates":[2.4380569458,41.5359382629],"type":"Point"}
}