{
  "type": "Feature",
  "properties": {
    "iso:country":"ES",
    "sg:address":"Fraiskozuri Plaza, 3",
    "sg:city":"Bergara",
    "sg:orig_category":"Barbacoas Y Accesorios",
    "sg:phone":"+34 943 76 38 51",
    "sg:postcode":"20570",
    "sg:province":"Guip\u00f9zcoa",
    "wof:name":"Echaniz Zugasti Ignacio (asador Erreki)",
    "wof:placetype":"venue"
},
  "geometry": {"coordinates":[-2.4142100811,43.1186408997],"type":"Point"}
}