{
  "type": "Feature",
  "properties": {
    "addr:full":"Calle de 9 De Octubre, 35 Riba-roja Turia Valencia 46190",
    "addr:housenumber":"35",
    "addr:postcode":"46190",
    "addr:street":"Calle De 9 De Octubre",
    "iso:country":"ES",
    "sg:address":"Calle de 9 De Octubre, 35",
    "sg:city":"Riba-roja Turia",
    "sg:orig_category":"Marroquiner\u00cda (confecci\u00d3n)",
    "sg:phone":"+34 962 77 22 60",
    "sg:postcode":"46190",
    "sg:province":"Valencia",
    "wof:name":"Ribapell C.b.",
    "wof:placetype":"venue"
},
  "geometry": {"coordinates":[-0.6096935868,39.4714736938],"type":"Point"}
}