{
  "type": "Feature",
  "properties": {
    "iso:country":"ES",
    "sg:address":"Calle de Postas, 10",
    "sg:city":"Vitoria-gasteiz",
    "sg:orig_category":"M\u00c9dicos: Estomatolog\u00cda",
    "sg:phone":"+34 945 14 70 50",
    "sg:postcode":"01001",
    "sg:province":"\u00c1lava",
    "wof:name":"Martinez Villamor Raimundo Antonio",
    "wof:placetype":"venue"
},
  "geometry": {"coordinates":[-2.6733310223,42.8460006714],"type":"Point"}
}