{
  "type": "Feature",
  "properties": {
    "addr:full":"Calle de Herrero, 64 Castellon Castell\u00f3n 12005",
    "addr:housenumber":"64",
    "addr:postcode":"12005",
    "addr:street":"Calle De Herrero",
    "iso:country":"ES",
    "sg:address":"Calle de Herrero, 64",
    "sg:city":"Castellon",
    "sg:orig_category":"Agencias Y Agentes Comerciales, Representantes",
    "sg:phone":"+34 964 20 84 85",
    "sg:postcode":"12005",
    "sg:province":"Castell\u00f3n",
    "wof:name":"Escorihuela Grau Juan Julian",
    "wof:placetype":"venue"
},
  "geometry": {"coordinates":[-0.0419210009,39.9783668518],"type":"Point"}
}