{
  "type": "Feature",
  "properties": {
    "iso:country":"ES",
    "sg:address":"Lazkaomendi Auzoa, S/n",
    "sg:city":"Lazkaomendi",
    "sg:orig_category":"Molduras, Junquillos, Listones Y Molduras Perforadas",
    "sg:phone":"+34 943 88 08 05",
    "sg:postcode":"20210",
    "sg:province":"Guip\u00f9zcoa",
    "wof:name":"Arruabarrena Sukia Simon",
    "wof:placetype":"venue"
},
  "geometry": {"coordinates":[-2.1701691151,43.0341110229],"type":"Point"}
}