{
  "type": "Feature",
  "properties": {
    "addr:full":"Ctra Logro\u00d1o, 9 Soria Soria 42004",
    "addr:housenumber":"9",
    "addr:postcode":"42004",
    "addr:street":"Ctra Logron\u0303O",
    "iso:country":"ES",
    "sg:address":"Ctra Logro\u00d1o, 9",
    "sg:city":"Soria",
    "sg:orig_category":"Barnizadores",
    "sg:phone":"+34 975 22 45 34",
    "sg:postcode":"42004",
    "sg:province":"Soria",
    "wof:name":"Gomollon Escribano Santiago",
    "wof:placetype":"venue"
},
  "geometry": {"coordinates":[-2.4651689529,41.7683067322],"type":"Point"}
}