{
  "type": "Feature",
  "properties": {
    "iso:country":"ES",
    "sg:address":"Carrer de Olorda, 46",
    "sg:city":"Mira-sol",
    "sg:orig_category":"Asesor\u00cda De Comercio Exterior",
    "sg:phone":"+34 935 75 39 40",
    "sg:postcode":"08195",
    "sg:province":"Barcelona",
    "wof:name":"Am-lican Ray Sl",
    "wof:placetype":"venue"
},
  "geometry": {"coordinates":[2.0543341637,41.4699287415],"type":"Point"}
}