{
  "type": "Feature",
  "properties": {
    "iso:country":"ES",
    "sg:address":"Calle de Carlos Iii, 4",
    "sg:city":"San Miguel",
    "sg:orig_category":"Asociaciones Humanitarias, De Cooperaci\u00d3n, De Acci\u00d3n Social",
    "sg:phone":"+34 968 20 50 96",
    "sg:postcode":"30008",
    "sg:province":"Murcia",
    "wof:name":"Asociacion Orientacion Familiar Alquibla",
    "wof:placetype":"venue"
},
  "geometry": {"coordinates":[-1.1309714317,37.9888687134],"type":"Point"}
}