{
  "type": "Feature",
  "properties": {
    "addr:full":"P. Maritimo, S/n Pe\u00f1iscola Castell\u00f3n 12598",
    "addr:housenumber":"s",
    "addr:postcode":"12598",
    "addr:street":"P. Maritimo;/ N Pen\u0303Iscola Castello\u0301N",
    "iso:country":"ES",
    "sg:address":"P. Maritimo, S/n",
    "sg:city":"Pe\u00f1iscola",
    "sg:orig_category":"Ense\u00d1anza, Formaci\u00d3n Profesional: Aprendizaje",
    "sg:phone":"+34 964 48 02 08",
    "sg:postcode":"12598",
    "sg:province":"Castell\u00f3n",
    "wof:name":"Ayuntamiento De Pe\u00f1iscola",
    "wof:placetype":"venue"
},
  "geometry": {"coordinates":[0.2863911092,40.2507781982],"type":"Point"}
}