{
  "type": "Feature",
  "properties": {
    "iso:country":"ES",
    "sg:address":"Calle de San Vicente, 51",
    "sg:city":"Villar Arzobispo",
    "sg:orig_category":"Bebidas",
    "sg:phone":"+34 962 72 00 29",
    "sg:postcode":"46170",
    "sg:province":"Valencia",
    "wof:name":"Lopez Sebastian Jesus",
    "wof:placetype":"venue"
},
  "geometry": {"coordinates":[-0.8273460269,39.730266571],"type":"Point"}
}