{
  "type": "Feature",
  "properties": {
    "addr:full":"Santa Marina Kalea, 3 Zarautz Guip\u00f9zcoa 20800",
    "addr:housenumber":"3",
    "addr:postcode":"20800",
    "addr:street":"Santa Marina Kalea;Guipu\u0300Zcoa",
    "iso:country":"ES",
    "sg:address":"Santa Marina Kalea, 3",
    "sg:city":"Zarautz",
    "sg:orig_category":"Ropa De Ocasi\u00d3n (al Por Mayor)",
    "sg:phone":"+34 943 89 43 98",
    "sg:postcode":"20800",
    "sg:province":"Guip\u00f9zcoa",
    "wof:name":"Parroquia De Santa Maria La Real",
    "wof:placetype":"venue"
},
  "geometry": {"coordinates":[-2.1769979,43.2855262756],"type":"Point"}
}