{
  "type": "Feature",
  "properties": {
    "addr:full":"Calle de Parque De Las Ca\u00d1adas, 35 Vaguadas Badajoz 06010",
    "addr:housenumber":"35",
    "addr:postcode":"06010",
    "addr:street":"Calle De Parque De Las Can\u0303Adas",
    "iso:country":"ES",
    "sg:address":"Calle de Parque De Las Ca\u00d1adas, 35",
    "sg:city":"Vaguadas",
    "sg:orig_category":"Arquitectos",
    "sg:phone":"+34 924 26 83 13",
    "sg:postcode":"06010",
    "sg:province":"Badajoz",
    "wof:name":"Luna Martinez Carlos",
    "wof:placetype":"venue"
},
  "geometry": {"coordinates":[-6.9808192253,38.8422317505],"type":"Point"}
}