{
  "type": "Feature",
  "properties": {
    "iso:country":"ES",
    "sg:address":"Calle de Berna, 2",
    "sg:city":"Toledo",
    "sg:orig_category":"Asesor\u00cda Sobre Comunicaci\u00d3n De Empresas",
    "sg:phone":"+34 925 21 04 61",
    "sg:postcode":"45005",
    "sg:province":"Toledo",
    "sg:website":"www.ayceautditores.com",
    "wof:name":"Ayce Auditores Y Consultores S.l.",
    "wof:placetype":"venue"
},
  "geometry": {"coordinates":[-4.05473423,39.8932037354],"type":"Point"}
}