{
  "type": "Feature",
  "properties": {
    "addr:full":"Rio Ebro, 6 Najera La Rioja 26300",
    "addr:housenumber":"6",
    "addr:postcode":"26300",
    "addr:street":"Rio Ebro;Rioja",
    "iso:country":"ES",
    "sg:address":"Rio Ebro, 6",
    "sg:city":"Najera",
    "sg:orig_category":"Escuelas De Maternidad P\u00dablicas",
    "sg:phone":"+34 941 36 17 08",
    "sg:postcode":"26300",
    "sg:province":"La Rioja",
    "wof:name":"Aladin S.c.",
    "wof:placetype":"venue"
},
  "geometry": {"coordinates":[-2.7286441326,42.4201622009],"type":"Point"}
}