{
  "type": "Feature",
  "properties": {
    "addr:full":"Calle de Nu\u00d1ez De Arce, 1 Santiago Murcia 30800",
    "addr:housenumber":"1",
    "addr:postcode":"30800",
    "addr:street":"Calle De Nun\u0303Ez De Arce",
    "iso:country":"ES",
    "sg:address":"Calle de Nu\u00d1ez De Arce, 1",
    "sg:city":"Santiago",
    "sg:orig_category":"Electricidad: Material Y Suministros De Instalaci\u00d3n (fabricaci\u00d3n)",
    "sg:phone":"+34 968 46 88 70",
    "sg:postcode":"30800",
    "sg:province":"Murcia",
    "wof:name":"Joruca S.l.",
    "wof:placetype":"venue"
},
  "geometry": {"coordinates":[-1.6905640364,37.680557251],"type":"Point"}
}