{
  "type": "Feature",
  "properties": {
    "addr:full":"Calle de Lope De Rueda, 33 Madrid Madrid 28009",
    "addr:housenumber":"33",
    "addr:postcode":"madrid;28009",
    "addr:street":"Calle De Lope De Rueda",
    "iso:country":"ES",
    "sg:address":"Calle de Lope De Rueda, 33",
    "sg:city":"Madrid",
    "sg:orig_category":"Abogados",
    "sg:phone":"+34 915 75 73 65",
    "sg:postcode":"28009",
    "sg:province":"Madrid",
    "wof:name":"Algar Jimenez Carmen",
    "wof:placetype":"venue"
},
  "geometry": {"coordinates":[-3.6776101589,40.4205551147],"type":"Point"}
}