{
  "type": "Feature",
  "properties": {
    "addr:full":"Calle de Galicia, 5 Madrid Madrid 28024",
    "addr:housenumber":"5",
    "addr:postcode":"28024",
    "addr:street":"Calle De Galicia",
    "iso:country":"ES",
    "sg:address":"Calle de Galicia, 5",
    "sg:city":"Madrid",
    "sg:orig_category":"Producci\u00d3n, Distribuci\u00d3n De Electricidad",
    "sg:phone":"+34 917 11 14 64",
    "sg:postcode":"28024",
    "sg:province":"Madrid",
    "wof:name":"Lopez Garcia Alicia",
    "wof:placetype":"venue"
},
  "geometry": {"coordinates":[-3.7713339329,40.3975982666],"type":"Point"}
}