{
  "type": "Feature",
  "properties": {
    "iso:country":"ES",
    "sg:address":"Calle de Iglesia, 19",
    "sg:city":"Pozuelo De Alarcon",
    "sg:orig_category":"Farmacias",
    "sg:phone":"+34 917 15 34 07",
    "sg:postcode":"28223",
    "sg:province":"Madrid",
    "wof:name":"Espinosa De Los Monteros Gamboa Maria Bego\u00f1a",
    "wof:placetype":"venue"
},
  "geometry": {"coordinates":[-3.7849929333,40.4289131165],"type":"Point"}
}