{
  "type": "Feature",
  "properties": {
    "iso:country":"ES",
    "sg:address":"Calle de Amistad (la), 4",
    "sg:city":"Santander",
    "sg:orig_category":"Alimentaci\u00d3n General (al Por Menor)",
    "sg:phone":"+34 942 37 12 20",
    "sg:postcode":"39006",
    "sg:province":"Cantabria",
    "wof:name":"Iglesias Santamaria Maria De Los Angales",
    "wof:placetype":"venue"
},
  "geometry": {"coordinates":[-3.8161344528,43.4633255005],"type":"Point"}
}