{
  "type": "Feature",
  "properties": {
    "iso:country":"ES",
    "sg:address":"Av. Pio Xii, 34",
    "sg:city":"Iru\u00f1a",
    "sg:orig_category":"Caf\u00c9s, Bares, Cervecer\u00cdas",
    "sg:phone":"+34 948 17 10 18",
    "sg:postcode":"31008",
    "sg:province":"Navarra",
    "wof:name":"Montar Hostelera-4 S.l.",
    "wof:placetype":"venue"
},
  "geometry": {"coordinates":[-1.6621123552,42.8059692383],"type":"Point"}
}