{
  "type": "Feature",
  "properties": {
    "iso:country":"ES",
    "sg:address":"Carr Sant Lluc, 53",
    "sg:city":"Badalona",
    "sg:orig_category":"M\u00c1rmoles, Granitos Y Piedras Naturales",
    "sg:phone":"+34 933 99 16 30",
    "sg:postcode":"08918",
    "sg:province":"Barcelona",
    "wof:name":"Todevi-fil S.l.",
    "wof:placetype":"venue"
},
  "geometry": {"coordinates":[2.2346959114,41.4355163574],"type":"Point"}
}