{
  "type": "Feature",
  "properties": {
    "addr:full":"Pol Ind Fuente Dos, S/n Fuente Obejuna C\u00f3rdoba 14290",
    "addr:postcode":"14290",
    "addr:street":"S / N",
    "iso:country":"ES",
    "sg:address":"Pol Ind Fuente Dos, S/n",
    "sg:city":"Fuente Obejuna",
    "sg:orig_category":"Cr\u00cda De Animales",
    "sg:phone":"+34 957 58 42 42",
    "sg:postcode":"14290",
    "sg:province":"C\u00f3rdoba",
    "wof:name":"Agroganadera Perea Escribano S.l.",
    "wof:placetype":"venue"
},
  "geometry": {"coordinates":[-5.4149003029,38.2551231384],"type":"Point"}
}