{
  "type": "Feature",
  "properties": {
    "iso:country":"ES",
    "sg:address":"Avda Pintor Portela, 34",
    "sg:city":"Cartagena",
    "sg:orig_category":"Asesor\u00cda Sobre Comunicaci\u00d3n De Empresas",
    "sg:phone":"+34 968 52 22 49",
    "sg:postcode":"30203",
    "sg:province":"Murcia",
    "wof:name":"Eulen S.a.",
    "wof:placetype":"venue"
},
  "geometry": {"coordinates":[-0.9726629853,37.6093406677],"type":"Point"}
}