{
  "type": "Feature",
  "properties": {
    "addr:full":"Calle de Juanelo, 18 Madrid Madrid 28012",
    "addr:housenumber":"18",
    "addr:postcode":"madrid;28012",
    "addr:street":"Calle De Juanelo",
    "iso:country":"ES",
    "sg:address":"Calle de Juanelo, 18",
    "sg:city":"Madrid",
    "sg:orig_category":"Molduras, Junquillos, Listones Y Molduras Perforadas",
    "sg:phone":"+34 913 69 07 80",
    "sg:postcode":"28012",
    "sg:province":"Madrid",
    "wof:name":"Hernandez Sanchez Maximino",
    "wof:placetype":"venue"
},
  "geometry": {"coordinates":[-3.7062420845,40.4112968445],"type":"Point"}
}