{
  "type": "Feature",
  "properties": {
    "addr:full":"Carrer de Floridablanca, 36 Barcelona Barcelona 08015",
    "addr:housenumber":"36",
    "addr:postcode":"08015",
    "addr:street":"Carrer De Floridablanca",
    "iso:country":"ES",
    "sg:address":"Carrer de Floridablanca, 36",
    "sg:city":"Barcelona",
    "sg:orig_category":"Organismos De Reclutamiento",
    "sg:phone":"+34 934 24 71 23",
    "sg:postcode":"08015",
    "sg:province":"Barcelona",
    "wof:name":"Inicia Tres S.l.",
    "wof:placetype":"venue"
},
  "geometry": {"coordinates":[2.1568861008,41.3770904541],"type":"Point"}
}