{
  "type": "Feature",
  "properties": {
    "iso:country":"ES",
    "sg:address":"Avda Denia, 32",
    "sg:city":"Alacant",
    "sg:orig_category":"Librer\u00cdas",
    "sg:phone":"+34 965 22 01 39",
    "sg:postcode":"03016",
    "sg:province":"Alicante",
    "wof:name":"Bego\u00d1a Ba\u00d1o Alonso Sl",
    "wof:placetype":"venue"
},
  "geometry": {"coordinates":[-0.4705969989,38.3565597534],"type":"Point"}
}