{
  "type": "Feature",
  "properties": {
    "addr:full":"Calle de San Jose, 42 Ibi Alicante 03440",
    "addr:housenumber":"42",
    "addr:postcode":"03440",
    "addr:street":"Calle De San",
    "iso:country":"ES",
    "sg:address":"Calle de San Jose, 42",
    "sg:city":"Ibi",
    "sg:orig_category":"Reposter\u00cdas",
    "sg:phone":"+34 965 55 46 71",
    "sg:postcode":"03440",
    "sg:province":"Alicante",
    "wof:name":"Lape\u00f1a Valero Moises",
    "wof:placetype":"venue"
},
  "geometry": {"coordinates":[-0.5754389763,38.6289176941],"type":"Point"}
}