{
  "type": "Feature",
  "properties": {
    "iso:country":"ES",
    "sg:address":"Av Constitucio, 137",
    "sg:city":"Castelldefels",
    "sg:orig_category":"Confiter\u00cdas, Chocolater\u00cdas (al Por Menor)",
    "sg:phone":"+34 936 65 12 89",
    "sg:postcode":"08860",
    "sg:province":"Barcelona",
    "wof:name":"Vives De Castelldefels S.l.",
    "wof:placetype":"venue"
},
  "geometry": {"coordinates":[1.9778654575,41.2785987854],"type":"Point"}
}