{
  "type": "Feature",
  "properties": {
    "addr:full":"Carrer de Valeta, 28 Hospitalet Llobregat Barcelona 08906",
    "addr:housenumber":"28",
    "addr:postcode":"08906",
    "addr:street":"Carrer De Valeta",
    "iso:country":"ES",
    "sg:address":"Carrer de Valeta, 28",
    "sg:city":"Hospitalet Llobregat",
    "sg:orig_category":"Empresas De Carpinter\u00cda De Madera",
    "sg:phone":"+34 933 37 37 18",
    "sg:postcode":"08906",
    "sg:province":"Barcelona",
    "wof:name":"Garcia Rouco Jesus",
    "wof:placetype":"venue"
},
  "geometry": {"coordinates":[2.0877420902,41.3673057556],"type":"Point"}
}