{
  "type": "Feature",
  "properties": {
    "addr:full":"Avda Inmaculada, 4 Barrios C\u00e1diz 11370",
    "addr:housenumber":"4",
    "addr:postcode":"11370",
    "addr:street":"Avda Inmaculada;Ca\u0301Diz",
    "iso:country":"ES",
    "sg:address":"Avda Inmaculada, 4",
    "sg:city":"Barrios",
    "sg:orig_category":"Bricolaje, Herramientas (al Por Menor)",
    "sg:phone":"+34 956 62 03 04",
    "sg:postcode":"11370",
    "sg:province":"C\u00e1diz",
    "wof:name":"Salguero Duarte Maria Del Carmen",
    "wof:placetype":"venue"
},
  "geometry": {"coordinates":[-5.4933671951,36.1822929382],"type":"Point"}
}