{
  "type": "Feature",
  "properties": {
    "addr:full":"Carrer de Violant Hongria R Arago, 71 Barcelona Barcelona 08028",
    "addr:housenumber":"hongria;71",
    "addr:postcode":"08028",
    "addr:street":"Carrer De Violant;R Arago",
    "iso:country":"ES",
    "sg:address":"Carrer de Violant Hongria R Arago, 71",
    "sg:city":"Barcelona",
    "sg:orig_category":"Ingenier\u00cda, Centros De Estudios (diversos)",
    "sg:phone":"+34 934 09 03 58",
    "sg:postcode":"08028",
    "sg:province":"Barcelona",
    "sg:website":"www.espaciosolar.com",
    "wof:name":"Espacio Constructivo Ingenieros S.l.",
    "wof:placetype":"venue"
},
  "geometry": {"coordinates":[2.1300759315,41.378818512],"type":"Point"}
}