{
  "type": "Feature",
  "properties": {
    "iso:country":"ES",
    "sg:address":"Rond Segovia, 75",
    "sg:city":"Madrid",
    "sg:orig_category":"Agencias Y Agentes Comerciales, Representantes",
    "sg:phone":"+34 913 65 84 21",
    "sg:postcode":"28005",
    "sg:province":"Madrid",
    "wof:name":"De Quiterio Mahugo Jose",
    "wof:placetype":"venue"
},
  "geometry": {"coordinates":[-3.7205889225,40.4138908386],"type":"Point"}
}