{
  "type": "Feature",
  "properties": {
    "iso:country":"ES",
    "sg:address":"Pase Alameda, 49",
    "sg:city":"Valencia",
    "sg:orig_category":"Promotores Constructores",
    "sg:phone":"+34 963 30 62 12",
    "sg:postcode":"46023",
    "sg:province":"Valencia",
    "wof:name":"Raga S. Xxii S.l.",
    "wof:placetype":"venue"
},
  "geometry": {"coordinates":[-0.3602719903,39.4677505493],"type":"Point"}
}