{
  "type": "Feature",
  "properties": {
    "iso:country":"ES",
    "sg:address":"Calle de Serrano, 91",
    "sg:city":"Madrid",
    "sg:orig_category":"Notarios",
    "sg:phone":"+34 915 61 94 92",
    "sg:postcode":"28006",
    "sg:province":"Madrid",
    "wof:name":"Sanchez Gonzalez Jose Carlos",
    "wof:placetype":"venue"
},
  "geometry": {"coordinates":[-3.6865079403,40.4369163513],"type":"Point"}
}