{
  "type": "Feature",
  "properties": {
    "addr:full":"Calle de Cueva De Menga, 12 Sevilla Sevilla 41020",
    "addr:housenumber":"12",
    "addr:postcode":"41020",
    "addr:street":"Calle De Cueva De Menga",
    "iso:country":"ES",
    "sg:address":"Calle de Cueva De Menga, 12",
    "sg:city":"Sevilla",
    "sg:orig_category":"Bisuter\u00cda, Joyer\u00cda, Relojer\u00cda (al Por Menor)",
    "sg:phone":"+34 954 25 89 71",
    "sg:postcode":"41020",
    "sg:province":"Sevilla",
    "wof:name":"Palomo Mallen S.l.",
    "wof:placetype":"venue"
},
  "geometry": {"coordinates":[-5.9371528625,37.4022254944],"type":"Point"}
}