{
  "type": "Feature",
  "properties": {
    "addr:full":"Calle de Alfonso Xiii, 22 Alcazar S. Juan Ciudad Real 13600",
    "addr:housenumber":"22",
    "addr:postcode":"13600",
    "addr:street":"Calle De Alfonso Xiii;Alcazar S. Juan Ciudad Real",
    "iso:country":"ES",
    "sg:address":"Calle de Alfonso Xiii, 22",
    "sg:city":"Alcazar S. Juan",
    "sg:orig_category":"Desinfecci\u00d3n, Desinsectaci\u00d3n, Desratizaci\u00d3n",
    "sg:phone":"+34 926 54 78 04",
    "sg:postcode":"13600",
    "sg:province":"Ciudad Real",
    "wof:name":"Desinfecciones Rubio S.l.",
    "wof:placetype":"venue"
},
  "geometry": {"coordinates":[-3.2131948471,39.3974838257],"type":"Point"}
}