{
  "type": "Feature",
  "properties": {
    "addr:full":"F (urb. Las Dunas), 12 Cabrerizos Salamanca 37193",
    "addr:housenumber":"12",
    "addr:postcode":"37193",
    "addr:street":"Las Dunas",
    "iso:country":"ES",
    "sg:address":"F (urb. Las Dunas), 12",
    "sg:city":"Cabrerizos",
    "sg:orig_category":"Ense\u00d1anza P\u00dablica Primaria",
    "sg:phone":"+34 923 18 21 57",
    "sg:postcode":"37193",
    "sg:province":"Salamanca",
    "sg:website":"www.escuelainfantil-losrosales.com",
    "wof:name":"Marquez Garcia Maria Del Carmen",
    "wof:placetype":"venue"
},
  "geometry": {"coordinates":[-5.6286168098,40.9666404724],"type":"Point"}
}