{
  "type": "Feature",
  "properties": {
    "addr:full":"Calle de Pablo Picasso (de), 5 San Fernando De Henares Madrid 28830",
    "addr:postcode":"28830",
    "addr:street":"Calle De Pablo Picasso De 5",
    "iso:country":"ES",
    "sg:address":"Calle de Pablo Picasso (de), 5",
    "sg:city":"San Fernando De Henares",
    "sg:orig_category":"Cajas De Ahorro",
    "sg:phone":"+34 916 69 56 00",
    "sg:postcode":"28830",
    "sg:province":"Madrid",
    "wof:name":"Caja De Ahorros De Castilla La Mancha",
    "wof:placetype":"venue"
},
  "geometry": {"coordinates":[-3.5326681137,40.4259681702],"type":"Point"}
}