{
  "type": "Feature",
  "properties": {
    "addr:full":"Calle de Forjadores, 23 Utrera Sevilla 41710",
    "addr:housenumber":"23",
    "addr:postcode":"41710",
    "addr:street":"Calle De Forjadores",
    "iso:country":"ES",
    "sg:address":"Calle de Forjadores, 23",
    "sg:city":"Utrera",
    "sg:orig_category":"Panader\u00cdas, Panader\u00cdas",
    "sg:phone":"+34 954 86 15 86",
    "sg:postcode":"41710",
    "sg:province":"Sevilla",
    "wof:name":"Pariente Jimenez Antonio",
    "wof:placetype":"venue"
},
  "geometry": {"coordinates":[-5.794567585,37.1998634338],"type":"Point"}
}