{
  "type": "Feature",
  "properties": {
    "addr:full":"Cmno Bellavista, 68 Alquian Almer\u00eda 04130",
    "addr:housenumber":"68",
    "addr:postcode":"04130",
    "addr:street":"Cmno Bellavista;Almeri\u0301A",
    "iso:country":"ES",
    "sg:address":"Cmno Bellavista, 68",
    "sg:city":"Alquian",
    "sg:orig_category":"Servicios De Telecomunicaciones",
    "sg:phone":"+34 950 60 03 00",
    "sg:postcode":"04130",
    "sg:province":"Almer\u00eda",
    "wof:name":"Servem Telecomunicaciones S.l.",
    "wof:placetype":"venue"
},
  "geometry": {"coordinates":[-2.3529150486,36.8523406982],"type":"Point"}
}