{
  "type": "Feature",
  "properties": {
    "addr:full":"Carrer de Valladolid, 6 Barcelona Barcelona 08014",
    "addr:housenumber":"6",
    "addr:postcode":"08014",
    "addr:street":"Carrer De Valladolid",
    "iso:country":"ES",
    "sg:address":"Carrer de Valladolid, 6",
    "sg:city":"Barcelona",
    "sg:orig_category":"M\u00c9dicos: Medicina General Orientada A La Acupuntura",
    "sg:phone":"+34 934 91 49 28",
    "sg:postcode":"08014",
    "sg:province":"Barcelona",
    "wof:name":"Fengtai S.cp.",
    "wof:placetype":"venue"
},
  "geometry": {"coordinates":[2.1358060837,41.3773727417],"type":"Point"}
}