{
  "type": "Feature",
  "properties": {
    "iso:country":"ES",
    "sg:address":"Carrer de Roger De Lluria, 90",
    "sg:city":"Barcelona",
    "sg:orig_category":"Grafistas",
    "sg:phone":"+34 934 59 23 98",
    "sg:postcode":"08009",
    "sg:province":"Barcelona",
    "sg:website":"www.ambientgrafic.com",
    "wof:name":"Diaz Pina Juan",
    "wof:placetype":"venue"
},
  "geometry": {"coordinates":[2.1659779549,41.3955001831],"type":"Point"}
}