{
  "type": "Feature",
  "properties": {
    "addr:full":"Gta Primero De Mayo (del), 1 Coslada Madrid 28820",
    "addr:housenumber":"1",
    "addr:postcode":"28820",
    "addr:street":"Gta Primero;Mayo Del",
    "iso:country":"ES",
    "sg:address":"Gta Primero De Mayo (del), 1",
    "sg:city":"Coslada",
    "sg:orig_category":"Abogados",
    "sg:phone":"+34 916 73 37 16",
    "sg:postcode":"28820",
    "sg:province":"Madrid",
    "wof:name":"Bendicho Gonzalez Guillermo",
    "wof:placetype":"venue"
},
  "geometry": {"coordinates":[-3.5645070076,40.4260902405],"type":"Point"}
}