{
  "type": "Feature",
  "properties": {
    "addr:full":"Bandarma, 1 Cala Moral M\u00e1laga 29720",
    "addr:housenumber":"1",
    "addr:postcode":"29720",
    "addr:street":"Bandarma;Ma\u0301Laga",
    "iso:country":"ES",
    "sg:address":"Bandarma, 1",
    "sg:city":"Cala Moral",
    "sg:orig_category":"Inmobiliaria (agencias)",
    "sg:phone":"+34 952 42 57 73",
    "sg:postcode":"29720",
    "sg:province":"M\u00e1laga",
    "wof:name":"Inserhogar S.l.",
    "wof:placetype":"venue"
},
  "geometry": {"coordinates":[-4.325949192,36.7128982544],"type":"Point"}
}