{
  "type": "Feature",
  "properties": {
    "addr:full":"Ctra Coronada, Km. 0004,0 Villanueva Serena Badajoz 06700",
    "addr:postcode":"06700",
    "addr:street":"Ctra Coronada Km. 0004,0",
    "iso:country":"ES",
    "sg:address":"Ctra Coronada, Km. 0004,0",
    "sg:city":"Villanueva Serena",
    "sg:orig_category":"Mataderos Y Talleres De Despiezado",
    "sg:phone":"+34 924 84 79 53",
    "sg:postcode":"06700",
    "sg:province":"Badajoz",
    "wof:name":"Ovino Del Suroeste S.c.l.",
    "wof:placetype":"venue"
},
  "geometry": {"coordinates":[-5.7927408218,38.9731750488],"type":"Point"}
}