{
  "type": "Feature",
  "properties": {
    "iso:country":"ES",
    "sg:address":"Calle de Sebastian Elcano, 12",
    "sg:city":"Sevilla",
    "sg:orig_category":"Ingeniero",
    "sg:phone":"+34 954 28 18 00",
    "sg:postcode":"41011",
    "sg:province":"Sevilla",
    "wof:name":"Perez Monreal Jose Ramon",
    "wof:placetype":"venue"
},
  "geometry": {"coordinates":[-5.9962329865,37.378074646],"type":"Point"}
}