{
  "type": "Feature",
  "properties": {
    "addr:full":"Carrer de Sant Pere, 50 Calella Barcelona 08370",
    "addr:housenumber":"50",
    "addr:postcode":"08370",
    "addr:street":"Carrer De Sant Pere",
    "iso:country":"ES",
    "sg:address":"Carrer de Sant Pere, 50",
    "sg:city":"Calella",
    "sg:orig_category":"Bancos",
    "sg:phone":"+34 937 69 04 62",
    "sg:postcode":"08370",
    "sg:province":"Barcelona",
    "wof:name":"Bt Espa\u00d1a Compa\u00d1ia De Servicios Globales De Telecomunicaciones S.a.u.",
    "wof:placetype":"venue"
},
  "geometry": {"coordinates":[2.6626799107,41.6150360107],"type":"Point"}
}