{
  "type": "Feature",
  "properties": {
    "addr:full":"Ovedo, 15 Melide La Coru\u00f1a 15800",
    "addr:housenumber":"15",
    "addr:postcode":"15800",
    "addr:street":"Ovedo;La Corun\u0303A",
    "iso:country":"ES",
    "sg:address":"Ovedo, 15",
    "sg:city":"Melide",
    "sg:orig_category":"Herboristas (al Por Menor)",
    "sg:phone":"+34 981 50 56 24",
    "sg:postcode":"15800",
    "sg:province":"La Coru\u00f1a",
    "wof:name":"Prado Pintor Armando",
    "wof:placetype":"venue"
},
  "geometry": {"coordinates":[-8.0163373947,42.914730072],"type":"Point"}
}