{
  "type": "Feature",
  "properties": {
    "addr:full":"Calle de Azahar, 18 Mairena Alcor Sevilla 41510",
    "addr:housenumber":"18",
    "addr:postcode":"41510",
    "addr:street":"Calle De Azahar",
    "iso:country":"ES",
    "sg:address":"Calle de Azahar, 18",
    "sg:city":"Mairena Alcor",
    "sg:orig_category":"Agencias De Viajes",
    "sg:phone":"+34 955 94 39 00",
    "sg:postcode":"41510",
    "sg:province":"Sevilla",
    "sg:website":"www.viajesmarchena.com",
    "wof:name":"Viajes Marchena S.l.",
    "wof:placetype":"venue"
},
  "geometry": {"coordinates":[-5.7439141273,37.377117157],"type":"Point"}
}