{
  "type": "Feature",
  "properties": {
    "iso:country":"ES",
    "sg:address":"Calle de Mayor, 51",
    "sg:city":"Tobarra",
    "sg:orig_category":"Ingenier\u00cda, Centros De Estudios (industria)",
    "sg:phone":"+34 967 32 80 17",
    "sg:postcode":"02500",
    "sg:province":"Albacete",
    "sg:website":"www.pce-iberica.es",
    "wof:name":"Pce Group Iberica S.l.",
    "wof:placetype":"venue"
},
  "geometry": {"coordinates":[-1.6895090342,38.5892715454],"type":"Point"}
}