{
  "type": "Feature",
  "properties": {
    "iso:country":"ES",
    "sg:address":"Fca. Rueda Tornijas, S/n",
    "sg:city":"Lumbrales",
    "sg:orig_category":"Charcuter\u00cdas (al Por Mayor)",
    "sg:phone":"+34 923 16 92 78",
    "sg:postcode":"37240",
    "sg:province":"Salamanca",
    "wof:name":"Embutidos Herrero C.b.",
    "wof:placetype":"venue"
},
  "geometry": {"coordinates":[-6.7207489014,40.9344139099],"type":"Point"}
}