{
  "type": "Feature",
  "properties": {
    "addr:full":"Ctra Abanilla (de), Km. 0005,3 Santomera Murcia 30140",
    "addr:postcode":"30140",
    "addr:street":"Ctra Abanilla De Km. 0005,3",
    "iso:country":"ES",
    "sg:address":"Ctra Abanilla (de), Km. 0005,3",
    "sg:city":"Santomera",
    "sg:orig_category":"Aparatos E Instalaci\u00d3n De Regad\u00cdos",
    "sg:phone":"+34 968 86 41 31",
    "sg:postcode":"30140",
    "sg:province":"Murcia",
    "wof:name":"Ceice Canovas Ingienerias Y Obras S.a.",
    "wof:placetype":"venue"
},
  "geometry": {"coordinates":[-1.0556559563,38.0687408447],"type":"Point"}
}