{
  "type": "Feature",
  "properties": {
    "iso:country":"ES",
    "sg:address":"Calle de Federico Tapia, 65",
    "sg:city":"Coru\u00d1a",
    "sg:orig_category":"Filatelia",
    "sg:phone":"+34 981 23 44 55",
    "sg:postcode":"15005",
    "sg:province":"A Coru\u00f1a",
    "wof:name":"Sociedad Filatelica De La Coru\u00f1a",
    "wof:placetype":"venue"
},
  "geometry": {"coordinates":[-8.4061613083,43.3607597351],"type":"Point"}
}