{
  "type": "Feature",
  "properties": {
    "iso:country":"ES",
    "sg:address":"Carrer de Ramon Y Cajal, 74",
    "sg:city":"Alcanar",
    "sg:orig_category":"Desinfecci\u00d3n, Desinsectaci\u00d3n, Desratizaci\u00d3n",
    "sg:phone":"+34 977 73 10 01",
    "sg:postcode":"43530",
    "sg:province":"Tarragona",
    "wof:name":"Juan Bort Queralt S.l.",
    "wof:placetype":"venue"
},
  "geometry": {"coordinates":[0.4814899862,40.5393791199],"type":"Point"}
}