{
  "type": "Feature",
  "properties": {
    "iso:country":"ES",
    "sg:address":"Avda Virgen De Argeme, 25",
    "sg:city":"Coria",
    "sg:orig_category":"Supermercados Y Hipermercados",
    "sg:phone":"+34 927 50 09 90",
    "sg:postcode":"10800",
    "sg:province":"C\u00e1ceres",
    "wof:name":"Vaquero Mateos Benito",
    "wof:placetype":"venue"
},
  "geometry": {"coordinates":[-6.5415291786,39.9918403625],"type":"Point"}
}