{
  "type": "Feature",
  "properties": {
    "addr:full":"Donibane Kalea, 16 Lezo Guip\u00f9zcoa 20100",
    "addr:housenumber":"16",
    "addr:postcode":"20100",
    "addr:street":"Donibane Kalea;Guipu\u0300Zcoa",
    "iso:country":"ES",
    "sg:address":"Donibane Kalea, 16",
    "sg:city":"Lezo",
    "sg:orig_category":"Bancos",
    "sg:phone":"+34 943 34 40 24",
    "sg:postcode":"20100",
    "sg:province":"Guip\u00f9zcoa",
    "wof:name":"Banco Guipuzcoano S.a.",
    "wof:placetype":"venue"
},
  "geometry": {"coordinates":[-1.9008280039,43.3205223083],"type":"Point"}
}