{
  "type": "Feature",
  "properties": {
    "addr:full":"Calle de Gran Via, 13 Mula Murcia 30170",
    "addr:housenumber":"13",
    "addr:postcode":"30170",
    "addr:street":"Calle De Gran Via",
    "iso:country":"ES",
    "sg:address":"Calle de Gran Via, 13",
    "sg:city":"Mula",
    "sg:orig_category":"Sociedades, Compa\u00d1\u00cdas Aseguradoras",
    "sg:phone":"+34 968 66 08 62",
    "sg:postcode":"30170",
    "sg:province":"Murcia",
    "wof:name":"Correduria De Seguros Huesgon S.l.",
    "wof:placetype":"venue"
},
  "geometry": {"coordinates":[-1.4893250465,38.0386199951],"type":"Point"}
}