{
  "type": "Feature",
  "properties": {
    "iso:country":"ES",
    "sg:address":"Carrer de Felip Ii, 21",
    "sg:city":"Palma",
    "sg:orig_category":"Ense\u00d1anza: Profesiones Art\u00cdsticas",
    "sg:phone":"+34 971 20 52 39",
    "sg:postcode":"07010",
    "sg:province":"Islas Baleares",
    "wof:name":"Video Fotografia Llofriu S.l.",
    "wof:placetype":"venue"
},
  "geometry": {"coordinates":[2.6478409767,39.5903358459],"type":"Point"}
}