{
  "type": "Feature",
  "properties": {
    "iso:country":"ES",
    "sg:address":"Calle de Marques De Comillas, 13",
    "sg:city":"Laredo",
    "sg:orig_category":"Formaci\u00d3n Continuada (variada)",
    "sg:phone":"+34 942 61 31 28",
    "sg:postcode":"39770",
    "sg:province":"Cantabria",
    "wof:name":"Ortiz Alvarez Benito",
    "wof:placetype":"venue"
},
  "geometry": {"coordinates":[-3.4171309471,43.4098739624],"type":"Point"}
}