{
  "type": "Feature",
  "properties": {
    "addr:full":"Calle de Juan Rodriguez, 16 San Vicente Alcantara Badajoz 06500",
    "addr:housenumber":"16",
    "addr:postcode":"06500",
    "addr:street":"Calle De Juan Rodriguez",
    "iso:country":"ES",
    "sg:address":"Calle de Juan Rodriguez, 16",
    "sg:city":"San Vicente Alcantara",
    "sg:orig_category":"Supermercados Y Hipermercados",
    "sg:phone":"+34 924 41 30 14",
    "sg:postcode":"06500",
    "sg:province":"Badajoz",
    "wof:name":"Supermercados Garcias La Posada S.l.",
    "wof:placetype":"venue"
},
  "geometry": {"coordinates":[-7.136302948,39.3609085083],"type":"Point"}
}