{
  "type": "Feature",
  "properties": {
    "addr:full":"Calle de Arlanza, 14 Madrid Madrid 28019",
    "addr:housenumber":"14",
    "addr:postcode":"madrid;28019",
    "addr:street":"Calle De Arlanza",
    "iso:country":"ES",
    "sg:address":"Calle de Arlanza, 14",
    "sg:city":"Madrid",
    "sg:orig_category":"Aparcamientos (infraestructuras, Accesorios)",
    "sg:phone":"+34 914 76 35 19",
    "sg:postcode":"28019",
    "sg:province":"Madrid",
    "wof:name":"Hafa S. L.",
    "wof:placetype":"venue"
},
  "geometry": {"coordinates":[-3.715767622,40.3876533508],"type":"Point"}
}