{
  "type": "Feature",
  "properties": {
    "addr:full":"Las Cruces, 3 Guillena Sevilla 41210",
    "addr:housenumber":"3",
    "addr:postcode":"41210",
    "addr:street":"Las Cruces",
    "iso:country":"ES",
    "sg:address":"Las Cruces, 3",
    "sg:city":"Guillena",
    "sg:orig_category":"Zapatos (al Por Menor)",
    "sg:phone":"+34 955 78 50 42",
    "sg:postcode":"41210",
    "sg:province":"Sevilla",
    "wof:name":"Malmo Calzados S.l.",
    "wof:placetype":"venue"
},
  "geometry": {"coordinates":[-6.0524868965,37.5390892029],"type":"Point"}
}