{
  "type": "Feature",
  "properties": {
    "iso:country":"ES",
    "sg:address":"Calle de Godofredo Ortega Y Mu\u00d1oz, 38",
    "sg:city":"Badajoz",
    "sg:orig_category":"\u00d3ptica: Instrumentos (fabricaci\u00d3n)",
    "sg:phone":"+34 924 22 38 95",
    "sg:postcode":"06011",
    "sg:province":"Badajoz",
    "wof:name":"Cano Caro Juan Antonio",
    "wof:placetype":"venue"
},
  "geometry": {"coordinates":[-6.9857192039,38.8671607971],"type":"Point"}
}