{
  "type": "Feature",
  "properties": {
    "iso:country":"ES",
    "sg:address":"Avda Principe De Asturias, S/n",
    "sg:city":"Anguciana",
    "sg:orig_category":"Poller\u00cda Y Caza (al Por Menor)",
    "sg:phone":"+34 941 32 02 32",
    "sg:postcode":"26210",
    "sg:province":"La Rioja",
    "wof:name":"Ruiz Perez Basilio Jose",
    "wof:placetype":"venue"
},
  "geometry": {"coordinates":[-2.8984489441,42.5735092163],"type":"Point"}
}