{
  "type": "Feature",
  "properties": {
    "addr:full":"Parc Ausias March (d'), 10 Tortosa Tarragona 43500",
    "addr:postcode":"43500",
    "iso:country":"ES",
    "sg:address":"Parc Ausias March (d'), 10",
    "sg:city":"Tortosa",
    "sg:orig_category":"Peluquer\u00cdas",
    "sg:phone":"+34 977 50 06 66",
    "sg:postcode":"43500",
    "sg:province":"Tarragona",
    "wof:name":"Perruqueria Perfils Unisex C.b.",
    "wof:placetype":"venue"
},
  "geometry": {"coordinates":[0.5209109783,40.8127632141],"type":"Point"}
}