{
  "type": "Feature",
  "properties": {
    "iso:country":"ES",
    "sg:address":"Calle de Mar De Aral, 13",
    "sg:city":"Caceres",
    "sg:orig_category":"Empresas De Carpinter\u00cda Met\u00c1lica",
    "sg:phone":"+34 927 22 21 06",
    "sg:postcode":"10005",
    "sg:province":"C\u00e1ceres",
    "wof:name":"Pacheco Rebollo Julian",
    "wof:placetype":"venue"
},
  "geometry": {"coordinates":[-6.3686218262,39.4505119324],"type":"Point"}
}