{
  "type": "Feature",
  "properties": {
    "addr:full":"Calle de Blanca, 1 S. Pedro Pinatar Murcia 30740",
    "addr:housenumber":"1",
    "addr:postcode":"30740",
    "addr:street":"Calle De Blanca",
    "iso:country":"ES",
    "sg:address":"Calle de Blanca, 1",
    "sg:city":"S. Pedro Pinatar",
    "sg:orig_category":"Servicio De Salud",
    "sg:phone":"+34 968 18 09 53",
    "sg:postcode":"30740",
    "sg:province":"Murcia",
    "wof:name":"Torreaguas S.a.",
    "wof:placetype":"venue"
},
  "geometry": {"coordinates":[-0.785417974,37.833770752],"type":"Point"}
}