{
  "type": "Feature",
  "properties": {
    "addr:full":"G.v. Marques Del Turia, 45 Valencia Valencia 46005",
    "addr:housenumber":"45",
    "addr:postcode":"46005",
    "addr:street":"Turia",
    "iso:country":"ES",
    "sg:address":"G.v. Marques Del Turia, 45",
    "sg:city":"Valencia",
    "sg:orig_category":"Zapatos (al Por Menor)",
    "sg:phone":"+34 963 51 13 71",
    "sg:postcode":"46005",
    "sg:province":"Valencia",
    "wof:name":"Ese De Ese C.b",
    "wof:placetype":"venue"
},
  "geometry": {"coordinates":[-0.3695940077,39.4669799805],"type":"Point"}
}