{
  "type": "Feature",
  "properties": {
    "addr:full":"Calle de Espiolla, S/n Borja Zaragoza 50540",
    "addr:housenumber":"s",
    "addr:postcode":"50540",
    "addr:street":"Calle De Espiolla;/ N Borja",
    "iso:country":"ES",
    "sg:address":"Calle de Espiolla, S/n",
    "sg:city":"Borja",
    "sg:orig_category":"Venta, Instalaci\u00d3n De Cocinas",
    "sg:phone":"+34 976 85 28 79",
    "sg:postcode":"50540",
    "sg:province":"Zaragoza",
    "wof:name":"Laguardia Banzo Maria Natalia",
    "wof:placetype":"venue"
},
  "geometry": {"coordinates":[-1.53272295,41.8310203552],"type":"Point"}
}