{
  "type": "Feature",
  "properties": {
    "addr:full":"Calle de Cuarteles, 28 Malaga M\u00e1laga 29002",
    "addr:housenumber":"28",
    "addr:postcode":"29002",
    "addr:street":"Calle De Cuarteles;Ma\u0301Laga",
    "iso:country":"ES",
    "sg:address":"Calle de Cuarteles, 28",
    "sg:city":"Malaga",
    "sg:orig_category":"Loter\u00cda Y T\u00d3mbola",
    "sg:phone":"+34 952 31 40 47",
    "sg:postcode":"29002",
    "sg:province":"M\u00e1laga",
    "sg:website":"www.loterias6malaga.com",
    "wof:name":"Guerrero Garcia Rosalia",
    "wof:placetype":"venue"
},
  "geometry": {"coordinates":[-4.4281611443,36.7137565613],"type":"Point"}
}