{
  "type": "Feature",
  "properties": {
    "iso:country":"ES",
    "sg:address":"Plaz Campo De La Feria, S/n",
    "sg:city":"Pobra Parga",
    "sg:orig_category":"Supermercados Y Hipermercados",
    "sg:phone":"+34 982 37 30 65",
    "sg:postcode":"27380",
    "sg:province":"Lugo",
    "wof:name":"Ayuntamiento De Guitiriz-consultorio Medico",
    "wof:placetype":"venue"
},
  "geometry": {"coordinates":[-7.8389353752,43.1624069214],"type":"Point"}
}