{
  "type": "Feature",
  "properties": {
    "iso:country":"ES",
    "sg:address":"Las Partidas, 25",
    "sg:city":"Mairena Aljarafe",
    "sg:orig_category":"T\u00c9cnicos Veterinarios",
    "sg:phone":"+34 954 18 18 00",
    "sg:postcode":"41927",
    "sg:province":"Sevilla",
    "wof:name":"Garcia De Los Santos Luisa",
    "wof:placetype":"venue"
},
  "geometry": {"coordinates":[-6.0603790283,37.3457298279],"type":"Point"}
}