{
  "type": "Feature",
  "properties": {
    "iso:country":"ES",
    "sg:address":"Av Carrilet, 230",
    "sg:city":"Hospitalet Llobregat",
    "sg:orig_category":"Asesor\u00cda Fiscal Y Jur\u00cddica",
    "sg:phone":"+34 932 61 05 47",
    "sg:postcode":"08901",
    "sg:province":"Barcelona",
    "wof:name":"Segura Melero Pedro",
    "wof:placetype":"venue"
},
  "geometry": {"coordinates":[2.1094119549,41.3606414795],"type":"Point"}
}