{
  "type": "Feature",
  "properties": {
    "iso:country":"ES",
    "sg:address":"Calle de Joaquin Arroyo, 9",
    "sg:city":"Madrid",
    "sg:orig_category":"Ingeniero",
    "sg:phone":"+34 917 66 07 06",
    "sg:postcode":"28033",
    "sg:province":"Madrid",
    "wof:name":"Adicora Servicios Ingenieria S.l.",
    "wof:placetype":"venue"
},
  "geometry": {"coordinates":[-3.6639740467,40.4683227539],"type":"Point"}
}