{
  "type": "Feature",
  "properties": {
    "iso:country":"ES",
    "sg:address":"Carrer de Beat Almato, 37",
    "sg:city":"Barcelona",
    "sg:orig_category":"Fabricaci\u00d3n De Moldes Y Modelos",
    "sg:phone":"+34 932 13 83 36",
    "sg:postcode":"08023",
    "sg:province":"Barcelona",
    "wof:name":"Belmonte Alcaraz Julian",
    "wof:placetype":"venue"
},
  "geometry": {"coordinates":[2.1480150223,41.4175567627],"type":"Point"}
}