{
  "type": "Feature",
  "properties": {
    "addr:full":"C/ Castell, 17 Paterna Valencia 46980",
    "addr:housenumber":"17",
    "addr:postcode":"46980",
    "addr:street":"C / Castell",
    "iso:country":"ES",
    "sg:address":"C/ Castell, 17",
    "sg:city":"Paterna",
    "sg:orig_category":"Pod\u00d3logos: Pedicuros",
    "sg:phone":"+34 961 36 57 57",
    "sg:postcode":"46980",
    "sg:province":"Valencia",
    "wof:name":"Macian Romero Cecilio",
    "wof:placetype":"venue"
},
  "geometry": {"coordinates":[-0.4395389855,39.500629425],"type":"Point"}
}