{
  "type": "Feature",
  "properties": {
    "addr:full":"Av Penedes, 6 Vilanova I La Geltru Barcelona 08800",
    "addr:housenumber":"6",
    "addr:postcode":"08800",
    "addr:street":"Av Penedes",
    "iso:country":"ES",
    "sg:address":"Av Penedes, 6",
    "sg:city":"Vilanova I La Geltru",
    "sg:orig_category":"Fabricaci\u00d3n De Juguetes Autom\u00c1ticos",
    "sg:phone":"+34 938 93 63 01",
    "sg:postcode":"08800",
    "sg:province":"Barcelona",
    "wof:name":"Lopez Piquer Alberto",
    "wof:placetype":"venue"
},
  "geometry": {"coordinates":[1.7308440208,41.2250137329],"type":"Point"}
}