{
  "type": "Feature",
  "properties": {
    "addr:full":"Calle de Capitan Haya, 6 Madrid Madrid 28020",
    "addr:housenumber":"6",
    "addr:postcode":"28020",
    "addr:street":"Calle De Capitan Haya",
    "iso:country":"ES",
    "sg:address":"Calle de Capitan Haya, 6",
    "sg:city":"Madrid",
    "sg:orig_category":"Importaci\u00d3n",
    "sg:phone":"+34 915 56 98 59",
    "sg:postcode":"28020",
    "sg:province":"Madrid",
    "wof:name":"Grupo Escada Espa\u00d1a S.a.u.",
    "wof:placetype":"venue"
},
  "geometry": {"coordinates":[-3.6923875809,40.4547576904],"type":"Point"}
}