{
  "type": "Feature",
  "properties": {
    "iso:country":"ES",
    "sg:address":"Avda Alcalde Alvaro Domecq, 11",
    "sg:city":"Jerez De La Frontera",
    "sg:orig_category":"Cr\u00cda De Animales",
    "sg:phone":"+34 956 30 56 31",
    "sg:postcode":"11405",
    "sg:province":"C\u00e1diz",
    "wof:name":"Alzor S.a.",
    "wof:placetype":"venue"
},
  "geometry": {"coordinates":[-6.1331181526,36.6919975281],"type":"Point"}
}