{
  "type": "Feature",
  "properties": {
    "addr:full":"Avda D. Ricardo Ruiz De Azcarraga, 42 Cenicero La Rioja 26350",
    "addr:housenumber":"42",
    "addr:postcode":"26350",
    "addr:street":"Avda D. Ricardo Ruiz De Azcarraga;Rioja",
    "iso:country":"ES",
    "sg:address":"Avda D. Ricardo Ruiz De Azcarraga, 42",
    "sg:city":"Cenicero",
    "sg:orig_category":"Empresas De Pintura Y Revestimientos",
    "sg:phone":"+34 941 45 43 56",
    "sg:postcode":"26350",
    "sg:province":"La Rioja",
    "wof:name":"Dieguez Lopez Julio",
    "wof:placetype":"venue"
},
  "geometry": {"coordinates":[-2.637018919,42.483291626],"type":"Point"}
}