{
  "type": "Feature",
  "properties": {
    "addr:full":"Calle de Pedro De Axular, S/n Elizondo Navarra 31700",
    "addr:postcode":"31700",
    "addr:street":"Calle De Pedro De Axular S / N;Navarra",
    "iso:country":"ES",
    "sg:address":"Calle de Pedro De Axular, S/n",
    "sg:city":"Elizondo",
    "sg:orig_category":"Restaurantes",
    "sg:phone":"+34 948 58 02 97",
    "sg:postcode":"31700",
    "sg:province":"Navarra",
    "wof:name":"Lopez Tranche Fernando",
    "wof:placetype":"venue"
},
  "geometry": {"coordinates":[-1.5181502104,43.1471595764],"type":"Point"}
}