{
  "type": "Feature",
  "properties": {
    "iso:country":"ES",
    "sg:address":"Calle de Ronda De Poniente, 14",
    "sg:city":"Chiclana De La Frontera",
    "sg:orig_category":"Ingenieros Asesor\u00cda",
    "sg:phone":"+34 956 53 84 97",
    "sg:postcode":"11130",
    "sg:province":"C\u00e1diz",
    "wof:name":"Control De Calidad Tedecon S.l.",
    "wof:placetype":"venue"
},
  "geometry": {"coordinates":[-6.1447038651,36.4212188721],"type":"Point"}
}