{
  "type": "Feature",
  "properties": {
    "addr:full":"Calle de Nu\u00d1ez Arenas, 15 Villaviciosa Odon Madrid 28670",
    "addr:housenumber":"15",
    "addr:postcode":"28670",
    "addr:street":"Calle De Nun\u0303Ez Arenas;Odon",
    "iso:country":"ES",
    "sg:address":"Calle de Nu\u00d1ez Arenas, 15",
    "sg:city":"Villaviciosa Odon",
    "sg:orig_category":"Deportes Diversos",
    "sg:phone":"+34 916 16 08 75",
    "sg:postcode":"28670",
    "sg:province":"Madrid",
    "wof:name":"Setien Acebo Alvaro",
    "wof:placetype":"venue"
},
  "geometry": {"coordinates":[-3.9022419453,40.3571548462],"type":"Point"}
}