{
  "type": "Feature",
  "properties": {
    "addr:full":"Calle de Yeles, 63 Yuncos Toledo 45210",
    "addr:housenumber":"63",
    "addr:postcode":"45210",
    "addr:street":"Calle De Yeles",
    "iso:country":"ES",
    "sg:address":"Calle de Yeles, 63",
    "sg:city":"Yuncos",
    "sg:orig_category":"Escayola Y Productos De Escayola (fabricaci\u00d3n, Al Por Mayor)",
    "sg:phone":"+34 925 55 76 84",
    "sg:postcode":"45210",
    "sg:province":"Toledo",
    "wof:name":"Escayolas Tiburon S.l.",
    "wof:placetype":"venue"
},
  "geometry": {"coordinates":[-3.8711190224,40.088470459],"type":"Point"}
}