{
  "type": "Feature",
  "properties": {
    "iso:country":"ES",
    "sg:address":"Calle de Clavel (el), 9",
    "sg:city":"Santa Cruz De Tenerife",
    "sg:orig_category":"Arquitectos",
    "sg:phone":"+34 922 24 78 66",
    "sg:postcode":"38003",
    "sg:province":"Santa Cruz De Tenerife",
    "wof:name":"Santos Martin Luis Carlos",
    "wof:placetype":"venue"
},
  "geometry": {"coordinates":[-16.3326644897,28.4846744537],"type":"Point"}
}