{
  "type": "Feature",
  "properties": {
    "addr:full":"Pase Florida, 8 Madrid Madrid 28008",
    "addr:housenumber":"8",
    "addr:postcode":"madrid;28008",
    "addr:street":"Florida",
    "iso:country":"ES",
    "sg:address":"Pase Florida, 8",
    "sg:city":"Madrid",
    "sg:orig_category":"Farmacias",
    "sg:phone":"+34 915 47 79 33",
    "sg:postcode":"28008",
    "sg:province":"Madrid",
    "wof:name":"Suarez Aparicio Aurora",
    "wof:placetype":"venue"
},
  "geometry": {"coordinates":[-3.7219600677,40.4221305847],"type":"Point"}
}