{
  "type": "Feature",
  "properties": {
    "addr:full":"Romani, 3 Olius Lleida 25286",
    "addr:housenumber":"3",
    "addr:postcode":"25286",
    "addr:street":"Romani",
    "iso:country":"ES",
    "sg:address":"Romani, 3",
    "sg:city":"Olius",
    "sg:orig_category":"Montaje (empresas De)",
    "sg:phone":"+34 973 48 31 79",
    "sg:postcode":"25286",
    "sg:province":"Lleida",
    "wof:name":"Muntatges Tecnics Auxiliars S.l.",
    "wof:placetype":"venue"
},
  "geometry": {"coordinates":[1.4181050062,41.9509010315],"type":"Point"}
}