{
  "type": "Feature",
  "properties": {
    "addr:full":"Carr Mendez Nu\u00d1ez, 30 Badalona Barcelona 08911",
    "addr:housenumber":"30",
    "addr:postcode":"08911",
    "addr:street":"Carr Mendez Nun\u0303Ez",
    "iso:country":"ES",
    "sg:address":"Carr Mendez Nu\u00d1ez, 30",
    "sg:city":"Badalona",
    "sg:orig_category":"Equipo De Refrigeraci\u00d3n Industrial",
    "sg:phone":"+34 933 84 09 14",
    "sg:postcode":"08911",
    "sg:province":"Barcelona",
    "wof:name":"Frio Industrial De Badalona Sociedad Cooperativa Catalana Limitada",
    "wof:placetype":"venue"
},
  "geometry": {"coordinates":[2.2508249283,41.4538154602],"type":"Point"}
}