{
  "type": "Feature",
  "properties": {
    "iso:country":"ES",
    "sg:address":"Pol. Ind. Torrefarrera, S/n",
    "sg:city":"Torrefarrera",
    "sg:orig_category":"Suministros Y Materiales Industriales",
    "sg:phone":"+34 973 75 19 10",
    "sg:postcode":"25123",
    "sg:province":"Lleida",
    "wof:name":"Suma Agroindustrial S.l.",
    "wof:placetype":"venue"
},
  "geometry": {"coordinates":[0.5995969772,41.6718292236],"type":"Point"}
}