{
  "type": "Feature",
  "properties": {
    "addr:full":"Estd Santiago (estrada Vella De), 64 Lugo Lugo 27004",
    "addr:housenumber":"64",
    "addr:postcode":"27004",
    "addr:street":"Estrada Vella De",
    "iso:country":"ES",
    "sg:address":"Estd Santiago (estrada Vella De), 64",
    "sg:city":"Lugo",
    "sg:orig_category":"Radiocomunicaciones, Telefon\u00cda M\u00d3vil, Radiomensajer\u00cda: Servicios, Comercializaci\u00d3n",
    "sg:phone":"+34 982 25 33 33",
    "sg:postcode":"27004",
    "sg:province":"Lugo",
    "wof:name":"Raul Rey S.l.",
    "wof:placetype":"venue"
},
  "geometry": {"coordinates":[-7.5643548965,42.9992637634],"type":"Point"}
}