{
  "type": "Feature",
  "properties": {
    "iso:country":"ES",
    "sg:address":"Carrer de Dos De Maig, 234",
    "sg:city":"Barcelona",
    "sg:orig_category":"Agencias Y Agentes Comerciales, Representantes",
    "sg:phone":"+34 932 46 37 82",
    "sg:postcode":"08013",
    "sg:province":"Barcelona",
    "wof:name":"Balaguer Guinart Joaquin",
    "wof:placetype":"venue"
},
  "geometry": {"coordinates":[2.1818590164,41.4072227478],"type":"Point"}
}