{
  "type": "Feature",
  "properties": {
    "iso:country":"ES",
    "sg:address":"Calle de Cervantes, 6",
    "sg:city":"Santander",
    "sg:orig_category":"Procuradores",
    "sg:phone":"+34 942 22 69 33",
    "sg:postcode":"39001",
    "sg:province":"Cantabria",
    "wof:name":"Alvarez Sastre Cesar",
    "wof:placetype":"venue"
},
  "geometry": {"coordinates":[-3.8115406036,43.462310791],"type":"Point"}
}