{
  "type": "Feature",
  "properties": {
    "addr:full":"Pol Ind Sta Ana, 38 Guardamar Segura Alicante 03140",
    "addr:housenumber":"38",
    "addr:postcode":"03140",
    "addr:street":"Sta Ana",
    "iso:country":"ES",
    "sg:address":"Pol Ind Sta Ana, 38",
    "sg:city":"Guardamar Segura",
    "sg:orig_category":"Negocio De Materiales De Construcci\u00d3n",
    "sg:phone":"+34 965 72 98 52",
    "sg:postcode":"03140",
    "sg:province":"Alicante",
    "wof:name":"Quiles S.a.",
    "wof:placetype":"venue"
},
  "geometry": {"coordinates":[-0.6540290117,38.086681366],"type":"Point"}
}