{
  "type": "Feature",
  "properties": {
    "iso:country":"ES",
    "sg:address":"Calle de Duque De Alba, 15",
    "sg:city":"Madrid",
    "sg:orig_category":"Zapatos (al Por Menor)",
    "sg:phone":"+34 914 29 47 17",
    "sg:postcode":"28012",
    "sg:province":"Madrid",
    "wof:name":"Hong Wang Li",
    "wof:placetype":"venue"
},
  "geometry": {"coordinates":[-3.707005024,40.4115638733],"type":"Point"}
}