{
  "type": "Feature",
  "properties": {
    "addr:full":"Calle de Fausto Herrero, 2 Iscar Valladolid 47420",
    "addr:housenumber":"2",
    "addr:postcode":"47420",
    "addr:street":"Calle De Fausto Herrero",
    "iso:country":"ES",
    "sg:address":"Calle de Fausto Herrero, 2",
    "sg:city":"Iscar",
    "sg:orig_category":"Electrodom\u00c9sticos (al Por Menor)",
    "sg:phone":"+34 983 61 17 60",
    "sg:postcode":"47420",
    "sg:province":"Valladolid",
    "wof:name":"Garcia Gomez Angel",
    "wof:placetype":"venue"
},
  "geometry": {"coordinates":[-4.5268640518,41.364818573],"type":"Point"}
}