{
  "type": "Feature",
  "properties": {
    "iso:country":"ES",
    "sg:address":"Avda Schulz, 176",
    "sg:city":"Gijon",
    "sg:orig_category":"Bazares, Art\u00cdculos De Limpieza Y De Cocina (al Por Menor)",
    "sg:phone":"+34 985 39 30 62",
    "sg:postcode":"33210",
    "sg:province":"Asturias",
    "wof:name":"Manuel Otero Gonzalez Y Otros Cdad.",
    "wof:placetype":"venue"
},
  "geometry": {"coordinates":[-5.6673388481,43.5258407593],"type":"Point"}
}