{
  "type": "Feature",
  "properties": {
    "iso:country":"ES",
    "sg:address":"Calle de Ximenez Sandoval, 3",
    "sg:city":"Venta De Ba\u00e7os",
    "sg:orig_category":"Pescader\u00cdas (al Por Menor)",
    "sg:phone":"+34 979 77 08 77",
    "sg:postcode":"34200",
    "sg:province":"Palencia",
    "wof:name":"Puertas Sanz Juan Antonio",
    "wof:placetype":"venue"
},
  "geometry": {"coordinates":[-4.4890079498,41.9196929932],"type":"Point"}
}