{
  "type": "Feature",
  "properties": {
    "addr:full":"Urb Puerto Jose Banus, S/n Nueva Andalucia M\u00e1laga 29660",
    "addr:housenumber":"s / n",
    "addr:postcode":"29660",
    "addr:street":"Urb Puerto Jose Banus;Ma\u0301Laga",
    "iso:country":"ES",
    "sg:address":"Urb Puerto Jose Banus, S/n",
    "sg:city":"Nueva Andalucia",
    "sg:orig_category":"Zapatos (al Por Mayor)",
    "sg:phone":"+34 952 81 20 34",
    "sg:postcode":"29660",
    "sg:province":"M\u00e1laga",
    "wof:name":"Corcia Belilty Moises",
    "wof:placetype":"venue"
},
  "geometry": {"coordinates":[-4.9572491646,36.4902381897],"type":"Point"}
}