{
  "type": "Feature",
  "properties": {
    "iso:country":"ES",
    "sg:address":"Rua Justo Martinez, 20",
    "sg:city":"Estrada",
    "sg:orig_category":"Fabricaci\u00d3n De Acumuladores Y De Pilas El\u00c9ctricas",
    "sg:phone":"+34 986 57 36 17",
    "sg:postcode":"36680",
    "sg:province":"Pontevedra",
    "wof:name":"Decocasasl",
    "wof:placetype":"venue"
},
  "geometry": {"coordinates":[-8.4893693924,42.6889801025],"type":"Point"}
}