{
  "type": "Feature",
  "properties": {
    "addr:full":"Alam Areilza Doctor, 54 Bilbao Vizcaya 48010",
    "addr:housenumber":"54",
    "addr:postcode":"48010",
    "addr:street":"Alam;Doctor",
    "iso:country":"ES",
    "sg:address":"Alam Areilza Doctor, 54",
    "sg:city":"Bilbao",
    "sg:orig_category":"Mercer\u00cda, Lencer\u00cda (al Por Menor)",
    "sg:phone":"+34 944 21 89 17",
    "sg:postcode":"48010",
    "sg:province":"Vizcaya",
    "wof:name":"I\u00f1aki Gomez Murua Y Maria Milagros Gomez Murua Cdad",
    "wof:placetype":"venue"
},
  "geometry": {"coordinates":[-2.9437849522,43.2583732605],"type":"Point"}
}