{
  "type": "Feature",
  "properties": {
    "iso:country":"ES",
    "sg:address":"Calle de Palafox, 8",
    "sg:city":"Villanueva Gallego",
    "sg:orig_category":"Asesor\u00cda Sobre Comunicaci\u00d3n De Empresas",
    "sg:phone":"+34 976 18 07 43",
    "sg:postcode":"50830",
    "sg:province":"Zaragoza",
    "wof:name":"Obras Y Construcciones Carbu",
    "wof:placetype":"venue"
},
  "geometry": {"coordinates":[-0.8260449767,41.7678451538],"type":"Point"}
}