{
  "type": "Feature",
  "properties": {
    "addr:full":"Carrer de Europa, 7 Sitges Barcelona 08870",
    "addr:housenumber":"7",
    "addr:postcode":"08870",
    "addr:street":"Carrer De Europa",
    "iso:country":"ES",
    "sg:address":"Carrer de Europa, 7",
    "sg:city":"Sitges",
    "sg:orig_category":"Sociedades, Compa\u00d1\u00cdas Aseguradoras",
    "sg:phone":"+34 938 11 33 63",
    "sg:postcode":"08870",
    "sg:province":"Barcelona",
    "wof:name":"Grossmann Alpresa Jorge",
    "wof:placetype":"venue"
},
  "geometry": {"coordinates":[1.8058689833,41.2375259399],"type":"Point"}
}