{
  "type": "Feature",
  "properties": {
    "iso:country":"ES",
    "sg:address":"Carrer de Lluis Companys, 48",
    "sg:city":"Granollers",
    "sg:orig_category":"Moquetas, Alfombras (al Por Menor)",
    "sg:phone":"+34 938 60 01 69",
    "sg:postcode":"08401",
    "sg:province":"Barcelona",
    "wof:name":"David Albareda S.l.",
    "wof:placetype":"venue"
},
  "geometry": {"coordinates":[2.282075882,41.5980453491],"type":"Point"}
}