{
  "type": "Feature",
  "properties": {
    "addr:full":"B. La Manresana, S/n Prats Rei Barcelona 08281",
    "addr:housenumber":"s / n",
    "addr:postcode":"08281",
    "addr:street":"B.;Barcelona",
    "iso:country":"ES",
    "sg:address":"B. La Manresana, S/n",
    "sg:city":"Prats Rei",
    "sg:orig_category":"Dibujantes (diversos)",
    "sg:phone":"+34 938 68 07 31",
    "sg:postcode":"08281",
    "sg:province":"Barcelona",
    "wof:name":"Carlton Studio Sl",
    "wof:placetype":"venue"
},
  "geometry": {"coordinates":[1.5294400454,41.7358589172],"type":"Point"}
}