{
  "type": "Feature",
  "properties": {
    "iso:country":"ES",
    "sg:address":"Pol Goardia, 11",
    "sg:city":"Idiazabal",
    "sg:orig_category":"Rectificaci\u00d3n, Mecanizado, Fresado",
    "sg:phone":"+34 943 18 77 15",
    "sg:postcode":"20213",
    "sg:province":"Guip\u00f9zcoa",
    "wof:name":"Faver Lazkao S.l.",
    "wof:placetype":"venue"
},
  "geometry": {"coordinates":[-2.1205339432,43.0957565308],"type":"Point"}
}