{
  "type": "Feature",
  "properties": {
    "iso:country":"ES",
    "sg:address":"Avda Porteli\u00d1a, 7",
    "sg:city":"Porteli\u00d1a",
    "sg:orig_category":"Caf\u00c9s, Bares, Cervecer\u00cdas",
    "sg:phone":"+34 986 87 05 53",
    "sg:postcode":"36163",
    "sg:province":"Pontevedra",
    "wof:name":"Tele Renta S.l.",
    "wof:placetype":"venue"
},
  "geometry": {"coordinates":[-8.6367549896,42.1933135986],"type":"Point"}
}