{
  "type": "Feature",
  "properties": {
    "addr:full":"Pg Espronceda, 25 Sabadell Barcelona 08204",
    "addr:housenumber":"25",
    "addr:postcode":"08204",
    "addr:street":"Pg Espronceda",
    "iso:country":"ES",
    "sg:address":"Pg Espronceda, 25",
    "sg:city":"Sabadell",
    "sg:orig_category":"Agencias De Viajes",
    "sg:phone":"+34 937 11 25 11",
    "sg:postcode":"08204",
    "sg:province":"Barcelona",
    "wof:name":"Viatges Iberplan S.a.",
    "wof:placetype":"venue"
},
  "geometry": {"coordinates":[2.1161549091,41.5286216736],"type":"Point"}
}