{
  "type": "Feature",
  "properties": {
    "iso:country":"ES",
    "sg:address":"Poli Poliviso, S/n",
    "sg:city":"Viso Del Alcor",
    "sg:orig_category":"Protecci\u00d3n Contra Incendios: Material, Instalaci\u00d3n, Mantenimiento",
    "sg:phone":"+34 955 74 21 59",
    "sg:postcode":"41520",
    "sg:province":"Sevilla",
    "wof:name":"Albert Ziegler Espa\u00f1a S.l.",
    "wof:placetype":"venue"
},
  "geometry": {"coordinates":[-5.7141880989,37.3890113831],"type":"Point"}
}