{
  "type": "Feature",
  "properties": {
    "addr:full":"Avda Fragata Almansa, 35 Real Pontevedra 36950",
    "addr:housenumber":"35",
    "addr:postcode":"36950",
    "addr:street":"Avda Fragata Almansa",
    "iso:country":"ES",
    "sg:address":"Avda Fragata Almansa, 35",
    "sg:city":"Real",
    "sg:orig_category":"Empresas De Pintura Y Revestimientos",
    "sg:phone":"+34 986 31 54 79",
    "sg:postcode":"36950",
    "sg:province":"Pontevedra",
    "wof:name":"Fernandez Pintura Y Decoracion S.l.",
    "wof:placetype":"venue"
},
  "geometry": {"coordinates":[-8.738442421,42.2772254944],"type":"Point"}
}