{
  "type": "Feature",
  "properties": {
    "addr:full":"Ptda Almafra Baixa, S/n Almafra Alicante 03610",
    "addr:housenumber":"s / n",
    "addr:postcode":"03610",
    "addr:street":"Ptda Almafra Baixa",
    "iso:country":"ES",
    "sg:address":"Ptda Almafra Baixa, S/n",
    "sg:city":"Almafra",
    "sg:orig_category":"Venta, Montaje De Neum\u00c1ticos",
    "sg:phone":"+34 965 37 39 78",
    "sg:postcode":"03610",
    "sg:province":"Alicante",
    "wof:name":"Santa Diaz Pedro",
    "wof:placetype":"venue"
},
  "geometry": {"coordinates":[-0.7731289864,38.4793281555],"type":"Point"}
}