{
  "type": "Feature",
  "properties": {
    "addr:full":"Calle de Modesto Lafuente, 63 Madrid Madrid 28003",
    "addr:housenumber":"63",
    "addr:postcode":"madrid;28003",
    "addr:street":"Calle De Modesto Lafuente",
    "iso:country":"ES",
    "sg:address":"Calle de Modesto Lafuente, 63",
    "sg:city":"Madrid",
    "sg:orig_category":"Clubes, Asociaciones De Ocio",
    "sg:phone":"+34 915 33 48 51",
    "sg:postcode":"28003",
    "sg:province":"Madrid",
    "wof:name":"Silvo Fernandez Anselmo",
    "wof:placetype":"venue"
},
  "geometry": {"coordinates":[-3.6959269047,40.4446868896],"type":"Point"}
}