{
  "type": "Feature",
  "properties": {
    "addr:full":"Pg Florida, 33 Santa Perpetua De Mogoda Barcelona 08130",
    "addr:housenumber":"33",
    "addr:postcode":"08130",
    "addr:street":"Pg Florida",
    "iso:country":"ES",
    "sg:address":"Pg Florida, 33",
    "sg:city":"Santa Perpetua De Mogoda",
    "sg:orig_category":"Cajas De Ahorro",
    "sg:phone":"+34 935 44 83 94",
    "sg:postcode":"08130",
    "sg:province":"Barcelona",
    "sg:website":"www.caixasabadell.es",
    "wof:name":"Caixa D'estalvis Sabadell",
    "wof:placetype":"venue"
},
  "geometry": {"coordinates":[2.1844100952,41.531879425],"type":"Point"}
}