{
  "type": "Feature",
  "properties": {
    "addr:full":"Calle de Industria, 58 Valencia Valencia 46022",
    "addr:housenumber":"58",
    "addr:postcode":"46022",
    "addr:street":"Calle De Industria",
    "iso:country":"ES",
    "sg:address":"Calle de Industria, 58",
    "sg:city":"Valencia",
    "sg:orig_category":"Confecci\u00d3n (fabricaci\u00d3n, Al Por Mayor)",
    "sg:phone":"+34 963 56 46 08",
    "sg:postcode":"46022",
    "sg:province":"Valencia",
    "wof:name":"Llorens Candela Elisa",
    "wof:placetype":"venue"
},
  "geometry": {"coordinates":[-0.3415670097,39.4683227539],"type":"Point"}
}