{
  "type": "Feature",
  "properties": {
    "addr:full":"Calle de Cervantes, 49 Calzada Calatrava Ciudad Real 13370",
    "addr:housenumber":"49",
    "addr:postcode":"13370",
    "addr:street":"Calle De Cervantes",
    "iso:country":"ES",
    "sg:address":"Calle de Cervantes, 49",
    "sg:city":"Calzada Calatrava",
    "sg:orig_category":"Confecci\u00d3n (fabricaci\u00d3n, Al Por Mayor)",
    "sg:phone":"+34 926 87 51 93",
    "sg:postcode":"13370",
    "sg:province":"Ciudad Real",
    "wof:name":"Ruiz Ciudad Juan Francisco",
    "wof:placetype":"venue"
},
  "geometry": {"coordinates":[-3.7747175694,38.7030830383],"type":"Point"}
}