{
  "type": "Feature",
  "properties": {
    "addr:full":"Gurmendi Kalea, 9 Zarautz Guip\u00f9zcoa 20800",
    "addr:housenumber":"9",
    "addr:postcode":"20800",
    "addr:street":"Gurmendi Kalea;Guipu\u0300Zcoa",
    "iso:country":"ES",
    "sg:address":"Gurmendi Kalea, 9",
    "sg:city":"Zarautz",
    "sg:orig_category":"Explotaci\u00d3n De Aparcamientos",
    "sg:phone":"+34 943 83 46 67",
    "sg:postcode":"20800",
    "sg:province":"Guip\u00f9zcoa",
    "wof:name":"Arteche Iceta I\u00f1aki",
    "wof:placetype":"venue"
},
  "geometry": {"coordinates":[-2.1728720665,43.2816772461],"type":"Point"}
}