{
  "type": "Feature",
  "properties": {
    "iso:country":"ES",
    "sg:address":"Plaz Txurruka, 2",
    "sg:city":"Mutriku",
    "sg:orig_category":"Molduras, Junquillos, Listones Y Molduras Perforadas",
    "sg:phone":"+34 943 60 37 49",
    "sg:postcode":"20830",
    "sg:province":"Guip\u00f9zcoa",
    "wof:name":"Miren Zubizarreta Aguirre",
    "wof:placetype":"venue"
},
  "geometry": {"coordinates":[-2.3862249851,43.3065185547],"type":"Point"}
}