{
  "type": "Feature",
  "properties": {
    "iso:country":"ES",
    "sg:address":"Calle de Enrique Granados (de), 33",
    "sg:city":"Partija-santa Monica",
    "sg:orig_category":"Ingeniero",
    "sg:phone":"+34 916 66 93 26",
    "sg:postcode":"28529",
    "sg:province":"Madrid",
    "sg:website":"www.sick.es",
    "wof:name":"Sick Optic Electronic S.a.",
    "wof:placetype":"venue"
},
  "geometry": {"coordinates":[-3.5102670193,40.314289093],"type":"Point"}
}