{
  "type": "Feature",
  "properties": {
    "iso:country":"ES",
    "sg:address":"Calle de Jabonerias, S/n",
    "sg:city":"Cartagena",
    "sg:classifiers":[
        {
            "category":"Cinema",
            "subcategory":"Movie Theater",
            "type":"Entertainment"
        }
    ],
    "sg:phone":"+34 968 50 16 15",
    "sg:postcode":"30201",
    "sg:province":"Murcia",
    "sg:tags":[
        "salas",
        "de",
        "cine"
    ],
    "sg:website":"www.murciaregion.es",
    "wof:name":"Sonora Producciones S.l.",
    "wof:placetype":"venue"
},
  "geometry": {"coordinates":[-0.9899638891,37.6037445068],"type":"Point"}
}