{
  "type": "Feature",
  "properties": {
    "iso:country":"ES",
    "sg:address":"Ctra Nal 340, Km. 0226,0",
    "sg:city":"Picassent",
    "sg:orig_category":"Sales (al Por Mayor)",
    "sg:phone":"+34 961 24 01 38",
    "sg:postcode":"46220",
    "sg:province":"Valencia",
    "wof:name":"Chelardo S.l.",
    "wof:placetype":"venue"
},
  "geometry": {"coordinates":[-0.4595290124,39.3631401062],"type":"Point"}
}