{
  "type": "Feature",
  "properties": {
    "iso:country":"ES",
    "sg:address":"Carrer de Valencia, 18",
    "sg:city":"Roquetes",
    "sg:orig_category":"Gafas (fabricaci\u00d3n)",
    "sg:phone":"+34 977 50 47 50",
    "sg:postcode":"43520",
    "sg:province":"Tarragona",
    "wof:name":"Emocop S.l.",
    "wof:placetype":"venue"
},
  "geometry": {"coordinates":[0.5007299781,40.8220787048],"type":"Point"}
}