{
  "type": "Feature",
  "properties": {
    "iso:country":"ES",
    "sg:address":"Ctra De Jesus, S/n",
    "sg:city":"Tortosa",
    "sg:orig_category":"Alimentaci\u00d3n General (al Por Mayor)",
    "sg:phone":"+34 977 58 11 43",
    "sg:postcode":"43500",
    "sg:province":"Tarragona",
    "wof:name":"Gossos S.l.",
    "wof:placetype":"venue"
},
  "geometry": {"coordinates":[0.5132960081,40.82188797],"type":"Point"}
}