{
  "type": "Feature",
  "properties": {
    "addr:full":"Redonda De Marconi, 53 Porcuna Ja\u00e9n 23790",
    "addr:housenumber":"53",
    "addr:postcode":"23790",
    "addr:street":"Marconi",
    "iso:country":"ES",
    "sg:address":"Redonda De Marconi, 53",
    "sg:city":"Porcuna",
    "sg:orig_category":"Empresas De Carpinter\u00cda Met\u00c1lica",
    "sg:phone":"+34 953 54 48 92",
    "sg:postcode":"23790",
    "sg:province":"Ja\u00e9n",
    "wof:name":"Gaston Del Pino Sacramento",
    "wof:placetype":"venue"
},
  "geometry": {"coordinates":[-4.2128338814,37.8397483826],"type":"Point"}
}