{
  "type": "Feature",
  "properties": {
    "addr:full":"Calle de Caballeros, 4 Coru\u00d1a La Coru\u00f1a 15009",
    "addr:housenumber":"4",
    "addr:postcode":"15009",
    "addr:street":"Calle De Caballeros;La Corun\u0303A",
    "iso:country":"ES",
    "sg:address":"Calle de Caballeros, 4",
    "sg:city":"Coru\u00d1a",
    "sg:orig_category":"Agencias Y Asesores De Publicidad",
    "sg:phone":"+34 981 15 35 58",
    "sg:postcode":"15009",
    "sg:province":"La Coru\u00f1a",
    "wof:name":"Recreativos Seyer S.l.",
    "wof:placetype":"venue"
},
  "geometry": {"coordinates":[-8.4051084518,43.3512382507],"type":"Point"}
}