{
  "type": "Feature",
  "properties": {
    "iso:country":"ES",
    "sg:address":"Carrer de Avinyo, 13",
    "sg:city":"Terrassa",
    "sg:orig_category":"Alimentaci\u00d3n General (al Por Menor)",
    "sg:phone":"+34 937 83 73 20",
    "sg:postcode":"08223",
    "sg:province":"Barcelona",
    "wof:name":"Fito Ventura Jose",
    "wof:placetype":"venue"
},
  "geometry": {"coordinates":[2.0117950439,41.556640625],"type":"Point"}
}