{
  "type": "Feature",
  "properties": {
    "iso:country":"ES",
    "sg:address":"Carr Comte D'empuries, 7",
    "sg:city":"Maria De La Salut",
    "sg:orig_category":"Chapister\u00cda",
    "sg:phone":"+34 971 52 50 64",
    "sg:postcode":"07519",
    "sg:province":"Islas Baleares",
    "wof:name":"Colombram Font Martin",
    "wof:placetype":"venue"
},
  "geometry": {"coordinates":[3.0760140419,39.6655158997],"type":"Point"}
}