{
  "type": "Feature",
  "properties": {
    "iso:country":"ES",
    "sg:address":"Calle de Jazmines, 2",
    "sg:city":"Malaga",
    "sg:orig_category":"Cerrajer\u00cda, Ferrallista",
    "sg:phone":"+34 952 27 93 01",
    "sg:postcode":"29010",
    "sg:province":"M\u00e1laga",
    "wof:name":"Gomez Ruiz Emilio",
    "wof:placetype":"venue"
},
  "geometry": {"coordinates":[-4.4372930527,36.7264862061],"type":"Point"}
}