{
  "type": "Feature",
  "properties": {
    "iso:country":"ES",
    "sg:address":"Plaz Espa\u00d1a, 7",
    "sg:city":"Sada",
    "sg:orig_category":"Bancos",
    "sg:phone":"+34 981 62 03 24",
    "sg:postcode":"15160",
    "sg:province":"La Coru\u00f1a",
    "wof:name":"Banco Etcheverria",
    "wof:placetype":"venue"
},
  "geometry": {"coordinates":[-8.2539548874,43.3508605957],"type":"Point"}
}