{
  "type": "Feature",
  "properties": {
    "addr:full":"San Lorenzo, 13 Iru\u00f1a Navarra 31001",
    "addr:housenumber":"13",
    "addr:postcode":"31001",
    "addr:street":"San Lorenzo",
    "iso:country":"ES",
    "sg:address":"San Lorenzo, 13",
    "sg:city":"Iru\u00f1a",
    "sg:orig_category":"Fiesta: Art\u00cdculos De (al Por Menor)",
    "sg:phone":"+34 948 21 08 79",
    "sg:postcode":"31001",
    "sg:province":"Navarra",
    "wof:name":"Jodar Cartujo Maria Jesus",
    "wof:placetype":"venue"
},
  "geometry": {"coordinates":[-1.6489659548,42.8174705505],"type":"Point"}
}