{
  "type": "Feature",
  "properties": {
    "addr:full":"Plaz Julio De La Calle, S/n Piedrahita \u00c1vila 05500",
    "addr:housenumber":"/ n",
    "addr:postcode":"05500",
    "addr:street":"Calle S",
    "iso:country":"ES",
    "sg:address":"Plaz Julio De La Calle, S/n",
    "sg:city":"Piedrahita",
    "sg:orig_category":"Sanatorios M\u00c9dico",
    "sg:phone":"+34 920 36 05 00",
    "sg:postcode":"05500",
    "sg:province":"\u00c1vila",
    "wof:name":"Gerencia De Atencion Primaria De Avila",
    "wof:placetype":"venue"
},
  "geometry": {"coordinates":[-5.3263239861,40.4657211304],"type":"Point"}
}