{
  "type": "Feature",
  "properties": {
    "iso:country":"ES",
    "sg:address":"Carrer de Ferro, 12",
    "sg:city":"Palma",
    "sg:orig_category":"Asociaciones, Organismos Culturales Y Socioeducativos",
    "sg:phone":"+34 971 45 78 27",
    "sg:postcode":"07013",
    "sg:province":"Islas Baleares",
    "wof:name":"Asociacion De Amigos De La Tercera Edad Bona Gent.",
    "wof:placetype":"venue"
},
  "geometry": {"coordinates":[2.6350820065,39.5757751465],"type":"Point"}
}