{
  "type": "Feature",
  "properties": {
    "addr:full":"Carr Pintor Jacomart, 2 Xativa Valencia 46800",
    "addr:housenumber":"2",
    "addr:postcode":"46800",
    "addr:street":"Carr Pintor Jacomart",
    "iso:country":"ES",
    "sg:address":"Carr Pintor Jacomart, 2",
    "sg:city":"Xativa",
    "sg:orig_category":"Caf\u00c9s, Bares, Cervecer\u00cdas",
    "sg:phone":"+34 962 28 13 17",
    "sg:postcode":"46800",
    "sg:province":"Valencia",
    "wof:name":"Asociacion Local De Cazadores El Orion",
    "wof:placetype":"venue"
},
  "geometry": {"coordinates":[-0.5237323046,38.9870071411],"type":"Point"}
}