{
  "type": "Feature",
  "properties": {
    "addr:full":"Carrer de Sant Gervasi De Cassoles, 70 Barcelona Barcelona 08022",
    "addr:housenumber":"70",
    "addr:postcode":"08022",
    "addr:street":"Carrer De Sant Gervasi De Cassoles",
    "iso:country":"ES",
    "sg:address":"Carrer de Sant Gervasi De Cassoles, 70",
    "sg:city":"Barcelona",
    "sg:orig_category":"Productos Qu\u00cdmicos (fabricaci\u00d3n, Al Por Mayor)",
    "sg:phone":"+34 932 12 74 00",
    "sg:postcode":"08022",
    "sg:province":"Barcelona",
    "wof:name":"Francis S. A.",
    "wof:placetype":"venue"
},
  "geometry": {"coordinates":[2.1367878914,41.4057731628],"type":"Point"}
}