{
  "type": "Feature",
  "properties": {
    "addr:full":"Calle de Bolivia, 3 Toledo Toledo 45004",
    "addr:housenumber":"3",
    "addr:postcode":"45004",
    "addr:street":"Calle De Bolivia",
    "iso:country":"ES",
    "sg:address":"Calle de Bolivia, 3",
    "sg:city":"Toledo",
    "sg:orig_category":"Bisuter\u00cda, Joyer\u00cda, Relojer\u00cda (al Por Menor)",
    "sg:phone":"+34 925 22 15 65",
    "sg:postcode":"45004",
    "sg:province":"Toledo",
    "wof:name":"Lude\u00f1a Miguel Juan",
    "wof:placetype":"venue"
},
  "geometry": {"coordinates":[-4.0299730301,39.866569519],"type":"Point"}
}