{
  "type": "Feature",
  "properties": {
    "addr:full":"Avda Pais Valencia (del), 33 Onda Castell\u00f3n 12200",
    "addr:postcode":"12200",
    "addr:street":"Avda Pais;Del;Castello\u0301N",
    "iso:country":"ES",
    "sg:address":"Avda Pais Valencia (del), 33",
    "sg:city":"Onda",
    "sg:orig_category":"Platos Preparados Refrigerados (fabricaci\u00d3n, Al Por Mayor)",
    "sg:phone":"+34 964 77 01 82",
    "sg:postcode":"12200",
    "sg:province":"Castell\u00f3n",
    "wof:name":"Manuel Martin Bienvenido Salvador",
    "wof:placetype":"venue"
},
  "geometry": {"coordinates":[-0.2614625096,39.9651870728],"type":"Point"}
}