{
  "type": "Feature",
  "properties": {
    "addr:full":"Calle de Negrillos, S/n Benavente Zamora 49600",
    "addr:housenumber":"s / n",
    "addr:postcode":"49600",
    "addr:street":"Calle De Negrillos",
    "iso:country":"ES",
    "sg:address":"Calle de Negrillos, S/n",
    "sg:city":"Benavente",
    "sg:orig_category":"Empresas De Portes Y Mensajer\u00cda",
    "sg:phone":"+34 980 63 63 24",
    "sg:postcode":"49600",
    "sg:province":"Zamora",
    "wof:name":"Gonzalez Guillen Maria Jose",
    "wof:placetype":"venue"
},
  "geometry": {"coordinates":[-5.6740942001,42.0135498047],"type":"Point"}
}