{
  "type": "Feature",
  "properties": {
    "iso:country":"ES",
    "sg:address":"Carrer de Havana (l'), 59",
    "sg:city":"Deltebre",
    "sg:orig_category":"Florister\u00cdas",
    "sg:phone":"+34 977 48 01 30",
    "sg:postcode":"43580",
    "sg:province":"Tarragona",
    "wof:name":"Panisello Bayo Facundo",
    "wof:placetype":"venue"
},
  "geometry": {"coordinates":[0.7353969812,40.7157402039],"type":"Point"}
}