{
  "type": "Feature",
  "properties": {
    "iso:country":"ES",
    "sg:address":"Avgd Valencia, 3",
    "sg:city":"Lleida",
    "sg:orig_category":"Empresas De Carpinter\u00cda Met\u00c1lica",
    "sg:phone":"+34 973 20 16 54",
    "sg:postcode":"25001",
    "sg:province":"Lleida",
    "wof:name":"Rodriguez Rodriguez Bautista",
    "wof:placetype":"venue"
},
  "geometry": {"coordinates":[0.6310049891,41.612121582],"type":"Point"}
}