{
  "type": "Feature",
  "properties": {
    "iso:country":"ES",
    "sg:address":"Av Rei En Jaume, 261",
    "sg:city":"Cardedeu",
    "sg:orig_category":"M\u00c9dicos: Estomatolog\u00cda",
    "sg:phone":"+34 938 46 09 15",
    "sg:postcode":"08440",
    "sg:province":"Barcelona",
    "wof:name":"Hernandez Garcia Aida Victoria",
    "wof:placetype":"venue"
},
  "geometry": {"coordinates":[2.3638300896,41.6374015808],"type":"Point"}
}