{
  "type": "Feature",
  "properties": {
    "addr:full":"Pedro Gcia. Mochales, 9 Cortijo S. Isidro Madrid 28300",
    "addr:housenumber":"9",
    "addr:postcode":"28300",
    "addr:street":"Pedro Gcia. Mochales;Cortijo S. Isidro",
    "iso:country":"ES",
    "sg:address":"Pedro Gcia. Mochales, 9",
    "sg:city":"Cortijo S. Isidro",
    "sg:orig_category":"Asesor\u00cda, Estudio Y Control Medioambiental",
    "sg:phone":"+34 918 01 16 83",
    "sg:postcode":"28300",
    "sg:province":"Madrid",
    "wof:name":"Ecomanchega De Consulting S.l.",
    "wof:placetype":"venue"
},
  "geometry": {"coordinates":[-3.6042790413,40.0360946655],"type":"Point"}
}