{
  "type": "Feature",
  "properties": {
    "addr:full":"Ctra N-232, Km. 0083,0 Castejon Navarra 31590",
    "addr:postcode":"31590",
    "addr:street":"Ctra N-232 Km. 0083,0",
    "iso:country":"ES",
    "sg:address":"Ctra N-232, Km. 0083,0",
    "sg:city":"Castejon",
    "sg:orig_category":"Ense\u00d1anza Variada",
    "sg:phone":"+34 948 84 20 28",
    "sg:postcode":"31590",
    "sg:province":"Navarra",
    "wof:name":"Iglesias Rubio Jeronimo",
    "wof:placetype":"venue"
},
  "geometry": {"coordinates":[-1.69807899,42.1733131409],"type":"Point"}
}