{
  "type": "Feature",
  "properties": {
    "iso:country":"ES",
    "sg:address":"Carrer de Amilcar, 7",
    "sg:city":"Barcelona",
    "sg:orig_category":"Muebles Y Accesorios Para Cocinas Y Cuartos De Ba\u00d1o (al Por Menor)",
    "sg:phone":"+34 933 57 31 95",
    "sg:postcode":"08031",
    "sg:province":"Barcelona",
    "wof:name":"Martinez Ruiz Manuela",
    "wof:placetype":"venue"
},
  "geometry": {"coordinates":[2.1721429825,41.4299163818],"type":"Point"}
}