{
  "type": "Feature",
  "properties": {
    "iso:country":"ES",
    "sg:address":"Calle de Escuelas (de Las), S/n",
    "sg:city":"Barco De Avila",
    "sg:orig_category":"Empresas De Carpinter\u00cda Met\u00c1lica",
    "sg:phone":"+34 920 34 01 67",
    "sg:postcode":"05600",
    "sg:province":"\u00c1vila",
    "wof:name":"Pascual Flores Luis",
    "wof:placetype":"venue"
},
  "geometry": {"coordinates":[-5.5231695175,40.355632782],"type":"Point"}
}