{
  "type": "Feature",
  "properties": {
    "addr:full":"Alam Principal, 44 Malaga M\u00e1laga 29005",
    "addr:housenumber":"44",
    "addr:postcode":"29005",
    "addr:street":"Alam Principal;Ma\u0301Laga",
    "iso:country":"ES",
    "sg:address":"Alam Principal, 44",
    "sg:city":"Malaga",
    "sg:orig_category":"Centros Empresariales",
    "sg:phone":"+34 952 60 25 85",
    "sg:postcode":"29005",
    "sg:province":"M\u00e1laga",
    "wof:name":"Escudero Administraciones S.l.",
    "wof:placetype":"venue"
},
  "geometry": {"coordinates":[-4.4515972137,36.7294387817],"type":"Point"}
}