{
  "type": "Feature",
  "properties": {
    "addr:full":"Calle de Santiago, 52 Casar Caceres C\u00e1ceres 10190",
    "addr:housenumber":"52",
    "addr:postcode":"10190",
    "addr:street":"Calle De Santiago;Ca\u0301Ceres",
    "iso:country":"ES",
    "sg:address":"Calle de Santiago, 52",
    "sg:city":"Casar Caceres",
    "sg:orig_category":"Limpieza Con Chorro De Arena Y Con Granalla, Pulido",
    "sg:phone":"+34 927 29 06 05",
    "sg:postcode":"10190",
    "sg:province":"C\u00e1ceres",
    "wof:name":"Royo Dionisio Juan",
    "wof:placetype":"venue"
},
  "geometry": {"coordinates":[-6.4180822372,39.563495636],"type":"Point"}
}