{
  "type": "Feature",
  "properties": {
    "iso:country":"ES",
    "sg:address":"Avgd Colon, 70",
    "sg:city":"Alcasser",
    "sg:orig_category":"Agencias Y Agentes Comerciales, Representantes",
    "sg:phone":"+34 961 23 32 08",
    "sg:postcode":"46290",
    "sg:province":"Valencia",
    "wof:name":"Lerma Duart Amador",
    "wof:placetype":"venue"
},
  "geometry": {"coordinates":[-0.4425030053,39.3660202026],"type":"Point"}
}