{
  "type": "Feature",
  "properties": {
    "iso:country":"ES",
    "sg:address":"Poligono Industrial Litutxipi, S/n",
    "sg:city":"Salvatierra Agurain",
    "sg:orig_category":"Embalajes",
    "sg:phone":"+34 945 31 22 32",
    "sg:postcode":"01200",
    "sg:province":"\u00c1lava",
    "wof:name":"Maderas Agurain S.l.",
    "wof:placetype":"venue"
},
  "geometry": {"coordinates":[-2.3517525196,42.8104705811],"type":"Point"}
}