{
  "type": "Feature",
  "properties": {
    "addr:full":"Carrer de Sant Pere, 4 Cambrils Tarragona 43850",
    "addr:housenumber":"4",
    "addr:postcode":"43850",
    "addr:street":"Carrer De Sant Pere",
    "iso:country":"ES",
    "sg:address":"Carrer de Sant Pere, 4",
    "sg:city":"Cambrils",
    "sg:orig_category":"Alimentaci\u00d3n General (al Por Menor)",
    "sg:phone":"+34 977 79 20 83",
    "sg:postcode":"43850",
    "sg:province":"Tarragona",
    "wof:name":"Alfaro Chimuris Petrona Isabel",
    "wof:placetype":"venue"
},
  "geometry": {"coordinates":[1.0623041391,41.0659561157],"type":"Point"}
}