{
  "type": "Feature",
  "properties": {
    "iso:country":"ES",
    "sg:address":"Avda Oporto, 30",
    "sg:city":"Madrid",
    "sg:orig_category":"Zapatos (al Por Menor)",
    "sg:phone":"+34 915 60 70 40",
    "sg:postcode":"28019",
    "sg:province":"Madrid",
    "wof:name":"Perez Gonzalez Tomas",
    "wof:placetype":"venue"
},
  "geometry": {"coordinates":[-3.7230329514,40.385471344],"type":"Point"}
}