{
  "type": "Feature",
  "properties": {
    "addr:full":"Calle de Placido Martinez, 8 Nava Asturias 33520",
    "addr:housenumber":"8",
    "addr:postcode":"33520",
    "addr:street":"Calle De Placido Martinez",
    "iso:country":"ES",
    "sg:address":"Calle de Placido Martinez, 8",
    "sg:city":"Nava",
    "sg:orig_category":"Agentes Generales De Seguros",
    "sg:phone":"+34 985 71 66 98",
    "sg:postcode":"33520",
    "sg:province":"Asturias",
    "wof:name":"Manuel Nava S.l.",
    "wof:placetype":"venue"
},
  "geometry": {"coordinates":[-5.508810997,43.3584327698],"type":"Point"}
}