{
  "type": "Feature",
  "properties": {
    "addr:full":"Calle de Melilla (de), 24 Alcobendas Madrid 28100",
    "addr:housenumber":"24",
    "addr:postcode":"28100",
    "addr:street":"Calle De Melilla De",
    "iso:country":"ES",
    "sg:address":"Calle de Melilla (de), 24",
    "sg:city":"Alcobendas",
    "sg:orig_category":"Empresas De Pintura Y Revestimientos",
    "sg:phone":"+34 916 61 99 42",
    "sg:postcode":"28100",
    "sg:province":"Madrid",
    "wof:name":"Gil Blanco Macario",
    "wof:placetype":"venue"
},
  "geometry": {"coordinates":[-3.6378440857,40.5390625],"type":"Point"}
}