{
  "type": "Feature",
  "properties": {
    "iso:country":"ES",
    "sg:address":"Maestro Don Joaquin, 25",
    "sg:city":"Monovar",
    "sg:orig_category":"Laboratorios Y Cl\u00cdnicas Veterinarias",
    "sg:phone":"+34 966 96 10 59",
    "sg:postcode":"03640",
    "sg:province":"Alicante",
    "wof:name":"Hospital Veterinario Menescal S.l.",
    "wof:placetype":"venue"
},
  "geometry": {"coordinates":[-0.837477982,38.4364852905],"type":"Point"}
}