{
  "type": "Feature",
  "properties": {
    "iso:country":"ES",
    "sg:address":"Avda Alcalde J.elosegi, 128",
    "sg:city":"Donostia-san Sebastian",
    "sg:orig_category":"Asociaciones Y Clubs Deportivos",
    "sg:phone":"+34 943 39 11 74",
    "sg:postcode":"20017",
    "sg:province":"Guip\u00f9zcoa",
    "wof:name":"Sociedad De Monta\u00f1a Mendi-zaleak",
    "wof:placetype":"venue"
},
  "geometry": {"coordinates":[-1.9251650572,43.3212585449],"type":"Point"}
}