{
  "type": "Feature",
  "properties": {
    "iso:country":"ES",
    "sg:address":"Urradi Karrika, S/n",
    "sg:city":"Labaien",
    "sg:orig_category":"Cr\u00cda De Animales",
    "sg:phone":"+34 948 39 31 38",
    "sg:postcode":"31753",
    "sg:province":"Navarra",
    "wof:name":"Fernandez Cureses Isabel",
    "wof:placetype":"venue"
},
  "geometry": {"coordinates":[-1.7507660389,43.0846061707],"type":"Point"}
}