{
  "type": "Feature",
  "properties": {
    "addr:full":"Carrer de Pintor Fortuny, 21 Viladecans Barcelona 08840",
    "addr:housenumber":"21",
    "addr:postcode":"08840",
    "addr:street":"Carrer De Pintor Fortuny",
    "iso:country":"ES",
    "sg:address":"Carrer de Pintor Fortuny, 21",
    "sg:city":"Viladecans",
    "sg:orig_category":"Postigos, Persianas Y Celos\u00cdas",
    "sg:phone":"+34 936 37 19 60",
    "sg:postcode":"08840",
    "sg:province":"Barcelona",
    "wof:name":"Jimenez Garcia Ernesto",
    "wof:placetype":"venue"
},
  "geometry": {"coordinates":[2.0253300667,41.3211517334],"type":"Point"}
}