{
  "type": "Feature",
  "properties": {
    "iso:country":"ES",
    "sg:address":"Parc Bit, S/n",
    "sg:city":"Son Sardina",
    "sg:orig_category":"Inform\u00c1tica (estudios, Servicios, Asesor\u00cda, Formaci\u00d3n)",
    "sg:phone":"+34 971 22 00 63",
    "sg:postcode":"07120",
    "sg:province":"Islas Baleares",
    "wof:name":"Sistemas De Gestion De Baleares S.a.",
    "wof:placetype":"venue"
},
  "geometry": {"coordinates":[2.655944109,39.6189918518],"type":"Point"}
}