{
  "type": "Feature",
  "properties": {
    "iso:country":"ES",
    "sg:address":"Avda Pio Xii, S/n",
    "sg:city":"Valencia",
    "sg:orig_category":"Peluquer\u00cdas, Peluquer\u00cda Mixta",
    "sg:phone":"+34 963 49 52 95",
    "sg:postcode":"46015",
    "sg:province":"Valencia",
    "sg:website":"www.peluqueriaspascual.com",
    "wof:name":"Segura Martinez Pascual",
    "wof:placetype":"venue"
},
  "geometry": {"coordinates":[-0.3958959877,39.4850387573],"type":"Point"}
}