{
  "type": "Feature",
  "properties": {
    "iso:country":"ES",
    "sg:address":"Avda Albufera, 25",
    "sg:city":"Madrid",
    "sg:orig_category":"Ropa Para Ni\u00d1os (al Por Menor)",
    "sg:phone":"+34 915 01 20 83",
    "sg:postcode":"28038",
    "sg:province":"Madrid",
    "sg:website":"www.bershka.com",
    "wof:name":"Bershka Bsr Espa\u00f1a S.a.",
    "wof:placetype":"venue"
},
  "geometry": {"coordinates":[-3.6669418812,40.3972129822],"type":"Point"}
}