{
  "type": "Feature",
  "properties": {
    "addr:full":"Calle de Julio Saez De La Hoya, 3 Burgos Burgos 09005",
    "addr:housenumber":"3",
    "addr:postcode":"09005",
    "addr:street":"Calle De Julio Saez De La Hoya",
    "iso:country":"ES",
    "sg:address":"Calle de Julio Saez De La Hoya, 3",
    "sg:city":"Burgos",
    "sg:orig_category":"Fotocopias, Reprograf\u00cda",
    "sg:phone":"+34 947 22 50 21",
    "sg:postcode":"09005",
    "sg:province":"Burgos",
    "wof:name":"Quintana Ortiz Alfredo",
    "wof:placetype":"venue"
},
  "geometry": {"coordinates":[-3.6975390911,42.3453102112],"type":"Point"}
}