{
  "type": "Feature",
  "properties": {
    "addr:full":"Calle de Valle Aureliano, 3 Bilbao Vizcaya 48010",
    "addr:housenumber":"3",
    "addr:postcode":"48010",
    "addr:street":"Calle De Valle Aureliano",
    "iso:country":"ES",
    "sg:address":"Calle de Valle Aureliano, 3",
    "sg:city":"Bilbao",
    "sg:orig_category":"Peluqueros: De Se\u00d1oras",
    "sg:phone":"+34 944 43 51 43",
    "sg:postcode":"48010",
    "sg:province":"Vizcaya",
    "wof:name":"Fernandez Pe\u00f1a Isabel",
    "wof:placetype":"venue"
},
  "geometry": {"coordinates":[-2.9400770664,43.2593421936],"type":"Point"}
}