{
  "type": "Feature",
  "properties": {
    "iso:country":"ES",
    "sg:address":"Avda Santa Ana, 22",
    "sg:city":"Tudela",
    "sg:orig_category":"Asesor\u00cda Fiscal Y Jur\u00cddica",
    "sg:phone":"+34 948 82 09 46",
    "sg:postcode":"31500",
    "sg:province":"Navarra",
    "wof:name":"Pascual Ramirez Mercedes",
    "wof:placetype":"venue"
},
  "geometry": {"coordinates":[-1.6024620533,42.0558242798],"type":"Point"}
}