{
  "type": "Feature",
  "properties": {
    "addr:full":"Trva Soleta, 1 Ezcaray La Rioja 26280",
    "addr:housenumber":"1",
    "addr:postcode":"26280",
    "addr:street":"Trva Soleta;Rioja",
    "iso:country":"ES",
    "sg:address":"Trva Soleta, 1",
    "sg:city":"Ezcaray",
    "sg:orig_category":"T\u00c9cnicos Veterinarios",
    "sg:phone":"+34 941 35 43 66",
    "sg:postcode":"26280",
    "sg:province":"La Rioja",
    "wof:name":"Arana Beorlegui Antonio",
    "wof:placetype":"venue"
},
  "geometry": {"coordinates":[-3.0165169239,42.3237457275],"type":"Point"}
}