{
  "type": "Feature",
  "properties": {
    "iso:country":"ES",
    "sg:address":"Avda Ramon Y Cajal, 41",
    "sg:city":"Sevilla",
    "sg:orig_category":"Ingenier\u00cda, Centros De Estudios (diversos)",
    "sg:phone":"+34 954 66 20 79",
    "sg:postcode":"41005",
    "sg:province":"Sevilla",
    "wof:name":"Mascort Giraldez Carlos Miguel",
    "wof:placetype":"venue"
},
  "geometry": {"coordinates":[-5.9689450264,37.3754501343],"type":"Point"}
}