{
  "type": "Feature",
  "properties": {
    "iso:country":"ES",
    "sg:address":"Beko Kalea, 4",
    "sg:city":"Usurbil",
    "sg:orig_category":"Carnicer\u00cdas, Carnicer\u00cdas",
    "sg:phone":"+34 943 36 57 42",
    "sg:postcode":"20170",
    "sg:province":"Guip\u00f9zcoa",
    "wof:name":"Alcorta Echeverria Jose Joaquin",
    "wof:placetype":"venue"
},
  "geometry": {"coordinates":[-2.018683672,43.2669525146],"type":"Point"}
}