{
  "type": "Feature",
  "properties": {
    "iso:country":"ES",
    "sg:address":"Calle de Blasco Iba\u00d1ez, 58",
    "sg:city":"Palmas De Gran Canaria",
    "sg:orig_category":"Chapister\u00cda",
    "sg:phone":"+34 928 24 22 73",
    "sg:postcode":"35006",
    "sg:province":"Las Palmas",
    "wof:name":"Garcia Cabrera Matilde",
    "wof:placetype":"venue"
},
  "geometry": {"coordinates":[-15.4322061539,28.1315631866],"type":"Point"}
}