{
  "type": "Feature",
  "properties": {
    "iso:country":"ES",
    "sg:address":"Carr Juan Xxiii, 68",
    "sg:city":"Puerto De Pollen\u00c7a",
    "sg:orig_category":"Molduras, Junquillos, Listones Y Molduras Perforadas",
    "sg:phone":"+34 971 86 50 05",
    "sg:postcode":"07470",
    "sg:province":"Islas Baleares",
    "wof:name":"Torres Luquec.b.",
    "wof:placetype":"venue"
},
  "geometry": {"coordinates":[3.0826599598,39.9063415527],"type":"Point"}
}