{
  "type": "Feature",
  "properties": {
    "iso:country":"ES",
    "sg:address":"Avda Democracia, 11",
    "sg:city":"Madrid",
    "sg:orig_category":"Transportes Frigor\u00cdficos",
    "sg:phone":"+34 913 32 71 81",
    "sg:postcode":"28031",
    "sg:province":"Madrid",
    "wof:name":"Transportes Yague S.a.",
    "wof:placetype":"venue"
},
  "geometry": {"coordinates":[-3.6250369549,40.3839263916],"type":"Point"}
}