{
  "type": "Feature",
  "properties": {
    "iso:country":"ES",
    "sg:address":"Calle de Aller, 4",
    "sg:city":"Mieres",
    "sg:orig_category":"Cristaler\u00cdas",
    "sg:phone":"+34 985 46 57 29",
    "sg:postcode":"33600",
    "sg:province":"Asturias",
    "wof:name":"Vidrios La Nueva S.l.",
    "wof:placetype":"venue"
},
  "geometry": {"coordinates":[-5.776556015,43.2528381348],"type":"Point"}
}