{
  "type": "Feature",
  "properties": {
    "addr:full":"Carrer de Alfons Amic, 2 Hostalets Balenya Barcelona 08550",
    "addr:housenumber":"2",
    "addr:postcode":"08550",
    "addr:street":"Carrer De Alfons Amic",
    "iso:country":"ES",
    "sg:address":"Carrer de Alfons Amic, 2",
    "sg:city":"Hostalets Balenya",
    "sg:orig_category":"Carnicer\u00cdas, Carnicer\u00cdas",
    "sg:phone":"+34 938 89 83 51",
    "sg:postcode":"08550",
    "sg:province":"Barcelona",
    "wof:name":"Jamonificio Subirats S.l.",
    "wof:placetype":"venue"
},
  "geometry": {"coordinates":[2.2346220016,41.8132362366],"type":"Point"}
}