{
  "type": "Feature",
  "properties": {
    "iso:country":"ES",
    "sg:address":"Carrer de Carme, 1",
    "sg:city":"Manresa",
    "sg:orig_category":"Molduras, Junquillos, Listones Y Molduras Perforadas",
    "sg:phone":"+34 938 72 53 86",
    "sg:postcode":"08241",
    "sg:province":"Barcelona",
    "wof:name":"Diaz Sanchez Consuelo",
    "wof:placetype":"venue"
},
  "geometry": {"coordinates":[1.8268419504,41.7240753174],"type":"Point"}
}