{
  "type": "Feature",
  "properties": {
    "addr:full":"Calle de Flor De Azalea, 4 Sevilla Sevilla 41020",
    "addr:housenumber":"4",
    "addr:postcode":"41020",
    "addr:street":"Calle De Flor De Azalea",
    "iso:country":"ES",
    "sg:address":"Calle de Flor De Azalea, 4",
    "sg:city":"Sevilla",
    "sg:orig_category":"Bisuter\u00cda, Joyer\u00cda, Relojer\u00cda (al Por Menor)",
    "sg:phone":"+34 954 40 28 33",
    "sg:postcode":"41020",
    "sg:province":"Sevilla",
    "wof:name":"Pino Garcia Manuel",
    "wof:placetype":"venue"
},
  "geometry": {"coordinates":[-5.9188528061,37.3921394348],"type":"Point"}
}