{
  "type": "Feature",
  "properties": {
    "iso:country":"ES",
    "sg:address":"Calle de Valencia, 18",
    "sg:city":"Huesca",
    "sg:orig_category":"Carnicer\u00cdas, Carnicer\u00cdas",
    "sg:phone":"+34 974 22 33 68",
    "sg:postcode":"22006",
    "sg:province":"Huesca",
    "wof:name":"Lloro Santolaria Marino",
    "wof:placetype":"venue"
},
  "geometry": {"coordinates":[-0.3958329856,42.1413803101],"type":"Point"}
}