{
  "type": "Feature",
  "properties": {
    "addr:full":"Carrer de Mallorca, 594 Barcelona Barcelona 08026",
    "addr:housenumber":"594",
    "addr:postcode":"08026",
    "addr:street":"Carrer De Mallorca",
    "iso:country":"ES",
    "sg:address":"Carrer de Mallorca, 594",
    "sg:city":"Barcelona",
    "sg:orig_category":"Reposter\u00cdas",
    "sg:phone":"+34 932 32 31 83",
    "sg:postcode":"08026",
    "sg:province":"Barcelona",
    "wof:name":"Elitepan S.l.",
    "wof:placetype":"venue"
},
  "geometry": {"coordinates":[2.18501091,41.4105033875],"type":"Point"}
}