{
  "type": "Feature",
  "properties": {
    "addr:full":"Calle de Jesus Sanchez Martin, 3 Repilado Huelva 21360",
    "addr:housenumber":"3",
    "addr:postcode":"21360",
    "addr:street":"Calle De Jesus Sanchez Martin",
    "iso:country":"ES",
    "sg:address":"Calle de Jesus Sanchez Martin, 3",
    "sg:city":"Repilado",
    "sg:orig_category":"Contenedores (mercanc\u00cdas)",
    "sg:phone":"+34 959 12 27 34",
    "sg:postcode":"21360",
    "sg:province":"Huelva",
    "wof:name":"Vazquez Ramos Sebastian",
    "wof:placetype":"venue"
},
  "geometry": {"coordinates":[-6.7708749771,37.9265136719],"type":"Point"}
}