{
  "type": "Feature",
  "properties": {
    "addr:full":"Calle de Severo Ochoa (de), S/n Leganes Madrid 28914",
    "addr:postcode":"28914",
    "addr:street":"Calle De Severo Ochoa De S / N",
    "iso:country":"ES",
    "sg:address":"Calle de Severo Ochoa (de), S/n",
    "sg:city":"Leganes",
    "sg:orig_category":"Alimentaci\u00d3n General (al Por Mayor)",
    "sg:phone":"+34 916 88 43 33",
    "sg:postcode":"28914",
    "sg:province":"Madrid",
    "sg:website":"www.makro.es",
    "wof:name":"Makro Autoservicio Mayoristas S. A.",
    "wof:placetype":"venue"
},
  "geometry": {"coordinates":[-3.7468540668,40.3192558289],"type":"Point"}
}