{
  "type": "Feature",
  "properties": {
    "iso:country":"ES",
    "sg:address":"Calle de Colon, 33",
    "sg:city":"Almazora",
    "sg:orig_category":"Institutos De Belleza",
    "sg:phone":"+34 964 56 35 07",
    "sg:postcode":"12550",
    "sg:province":"Castell\u00f3n",
    "wof:name":"Esteve Romero Rosario",
    "wof:placetype":"venue"
},
  "geometry": {"coordinates":[-0.0639650002,39.9426040649],"type":"Point"}
}