{
  "type": "Feature",
  "properties": {
    "addr:full":"Calle de Galizia, 5 Basauri Vizcaya 48970",
    "addr:housenumber":"5",
    "addr:postcode":"48970",
    "addr:street":"Calle De Galizia",
    "iso:country":"ES",
    "sg:address":"Calle de Galizia, 5",
    "sg:city":"Basauri",
    "sg:orig_category":"Molduras, Junquillos, Listones Y Molduras Perforadas",
    "sg:phone":"+34 944 26 02 31",
    "sg:postcode":"48970",
    "sg:province":"Vizcaya",
    "wof:name":"Pablo Barbadillo Nu\u00f1ez",
    "wof:placetype":"venue"
},
  "geometry": {"coordinates":[-2.8822000027,43.2354049683],"type":"Point"}
}