{
  "type": "Feature",
  "properties": {
    "iso:country":"ES",
    "sg:address":"Ctra Estacio (de L'), 20",
    "sg:city":"Ripollet",
    "sg:orig_category":"Molduras, Junquillos, Listones Y Molduras Perforadas",
    "sg:phone":"+34 936 92 77 03",
    "sg:postcode":"08291",
    "sg:province":"Barcelona",
    "wof:name":"Vergara Monterde Juan Antonio",
    "wof:placetype":"venue"
},
  "geometry": {"coordinates":[2.1530649662,41.4968643188],"type":"Point"}
}