{
  "type": "Feature",
  "properties": {
    "iso:country":"ES",
    "sg:address":"Calle de Sol, S/n",
    "sg:city":"Coru\u00d1a",
    "sg:orig_category":"Cajas De Ahorro",
    "sg:phone":"+34 981 20 83 78",
    "sg:postcode":"15003",
    "sg:province":"La Coru\u00f1a",
    "sg:website":"www.obrasocialcaixagalicia.org",
    "wof:name":"Bt Espa\u00d1a Compa\u00d1ia De Servicios Globales De Telecomunicaciones S.a.u.",
    "wof:placetype":"venue"
},
  "geometry": {"coordinates":[-8.4024543762,43.372253418],"type":"Point"}
}