{
  "type": "Feature",
  "properties": {
    "addr:full":"Calle de Urbieta, 11 Donostia-san Sebastian Guip\u00f9zcoa 20006",
    "addr:housenumber":"11",
    "addr:postcode":"20006",
    "addr:street":"Calle De Urbieta",
    "iso:country":"ES",
    "sg:address":"Calle de Urbieta, 11",
    "sg:city":"Donostia-san Sebastian",
    "sg:orig_category":"Agencias Y Agentes Comerciales, Representantes",
    "sg:phone":"+34 943 43 18 35",
    "sg:postcode":"20006",
    "sg:province":"Guip\u00f9zcoa",
    "wof:name":"De Diego Echeverria Maria Teresa",
    "wof:placetype":"venue"
},
  "geometry": {"coordinates":[-1.982951045,43.3175239563],"type":"Point"}
}