{
  "type": "Feature",
  "properties": {
    "addr:full":"Plaz Constitucion (la), 1 Chercos Nuevo Almer\u00eda 04859",
    "addr:housenumber":"1",
    "addr:postcode":"04859",
    "addr:street":"Constitucion La;Almeri\u0301A",
    "iso:country":"ES",
    "sg:address":"Plaz Constitucion (la), 1",
    "sg:city":"Chercos Nuevo",
    "sg:orig_category":"Molduras, Junquillos, Listones Y Molduras Perforadas",
    "sg:phone":"+34 950 12 25 41",
    "sg:postcode":"04859",
    "sg:province":"Almer\u00eda",
    "wof:name":"Torres Saez Carmen",
    "wof:placetype":"venue"
},
  "geometry": {"coordinates":[-2.2297298908,37.2589683533],"type":"Point"}
}