{
  "type": "Feature",
  "properties": {
    "iso:country":"ES",
    "sg:address":"Rua Pablo Iglesias, 8",
    "sg:city":"Grove",
    "sg:orig_category":"Ropa Y Art\u00cdculos Pre",
    "sg:phone":"+34 986 73 06 57",
    "sg:postcode":"36980",
    "sg:province":"Pontevedra",
    "wof:name":"Meis Otero Maria Del Carmen",
    "wof:placetype":"venue"
},
  "geometry": {"coordinates":[-8.8653116226,42.4953956604],"type":"Point"}
}