{
  "type": "Feature",
  "properties": {
    "iso:country":"ES",
    "sg:address":"Pg Conca De Tremp, 10",
    "sg:city":"Tremp",
    "sg:orig_category":"Transportes Por V\u00cdas Navegables",
    "sg:phone":"+34 973 65 07 18",
    "sg:postcode":"25620",
    "sg:province":"Lleida",
    "wof:name":"Fustes I Transports Roca S.l.",
    "wof:placetype":"venue"
},
  "geometry": {"coordinates":[0.8894950151,42.1651382446],"type":"Point"}
}