{
  "type": "Feature",
  "properties": {
    "iso:country":"ES",
    "sg:address":"C/ Reina Victoria, 75",
    "sg:city":"Elche",
    "sg:orig_category":"Peluqueros: De Se\u00d1oras",
    "sg:phone":"+34 965 46 05 67",
    "sg:postcode":"03201",
    "sg:province":"Alicante",
    "wof:name":"Gonzalvez Mas Angeles",
    "wof:placetype":"venue"
},
  "geometry": {"coordinates":[-0.7060520053,38.2654190063],"type":"Point"}
}