{
  "type": "Feature",
  "properties": {
    "addr:full":"Calle de Nueva, 34 Valdeganga Albacete 02150",
    "addr:housenumber":"34",
    "addr:postcode":"02150",
    "addr:street":"Calle De Nueva",
    "iso:country":"ES",
    "sg:address":"Calle de Nueva, 34",
    "sg:city":"Valdeganga",
    "sg:orig_category":"Electrodom\u00c9sticos (al Por Menor)",
    "sg:phone":"+34 967 40 02 03",
    "sg:postcode":"02150",
    "sg:province":"Albacete",
    "wof:name":"Belmonte Calero Celestino",
    "wof:placetype":"venue"
},
  "geometry": {"coordinates":[-1.6756089926,39.1335716248],"type":"Point"}
}