{
  "type": "Feature",
  "properties": {
    "addr:full":"Avda R. Juan Carlos I, S/n Castilleja Cuesta Sevilla 41950",
    "addr:housenumber":"s / n",
    "addr:postcode":"41950",
    "addr:street":"Avda R. Juan Carlos I;Castilleja Cuesta Sevilla",
    "iso:country":"ES",
    "sg:address":"Avda R. Juan Carlos I, S/n",
    "sg:city":"Castilleja Cuesta",
    "sg:classifiers":[
        {
            "category":"Taxi",
            "type":"Transportation"
        }
    ],
    "sg:phone":"+34 954 16 09 08",
    "sg:postcode":"41950",
    "sg:province":"Sevilla",
    "wof:name":"Union Local Sindical De Autonomos Del Taxi",
    "wof:placetype":"venue"
},
  "geometry": {"coordinates":[-6.0566887856,37.3854942322],"type":"Point"}
}