{
  "type": "Feature",
  "properties": {
    "iso:country":"ES",
    "sg:address":"Rua Progreso (do), 89",
    "sg:city":"Ourense",
    "sg:orig_category":"Fabricaci\u00d3n, Venta De Cuadros, Accesorios Para Enmarcar",
    "sg:phone":"+34 988 25 25 86",
    "sg:postcode":"32003",
    "sg:province":"Ourense",
    "wof:name":"Fernandez Sueiro Maria Isabel",
    "wof:placetype":"venue"
},
  "geometry": {"coordinates":[-7.8661937714,42.3387184143],"type":"Point"}
}