{
  "type": "Feature",
  "properties": {
    "iso:country":"ES",
    "sg:address":"Calle de Francisco Grandmontagne, 3",
    "sg:city":"Burgos",
    "sg:orig_category":"Pescader\u00cdas (al Por Menor)",
    "sg:phone":"+34 947 21 04 90",
    "sg:postcode":"09007",
    "sg:province":"Burgos",
    "wof:name":"Barriuso Gonzalez Francisco Javier",
    "wof:placetype":"venue"
},
  "geometry": {"coordinates":[-3.6704380512,42.3518867493],"type":"Point"}
}