{
  "type": "Feature",
  "properties": {
    "iso:country":"ES",
    "sg:address":"Carrer de Indalecio Prieto, S/n",
    "sg:city":"Palma",
    "sg:orig_category":"Centros De Educaci\u00d3n Especial",
    "sg:phone":"+34 971 24 07 81",
    "sg:postcode":"07008",
    "sg:province":"Islas Baleares",
    "wof:name":"Colegio Publico Es Pont",
    "wof:placetype":"venue"
},
  "geometry": {"coordinates":[2.6749498844,39.5794487],"type":"Point"}
}