{
  "type": "Feature",
  "properties": {
    "iso:country":"ES",
    "sg:address":"Avda Rosalia De Castro (de), 18",
    "sg:city":"Santiago De Compostela",
    "sg:orig_category":"Alimentaci\u00d3n General (al Por Menor)",
    "sg:phone":"+34 981 58 59 38",
    "sg:postcode":"15706",
    "sg:province":"La Coru\u00f1a",
    "wof:name":"Mari\u00f1o Mari\u00f1o Dolores",
    "wof:placetype":"venue"
},
  "geometry": {"coordinates":[-8.5499191284,42.8757858276],"type":"Point"}
}