{
  "type": "Feature",
  "properties": {
    "addr:full":"Calle de Crucero, 9 Luarca Asturias 33700",
    "addr:housenumber":"9",
    "addr:postcode":"33700",
    "addr:street":"Calle De Crucero",
    "iso:country":"ES",
    "sg:address":"Calle de Crucero, 9",
    "sg:city":"Luarca",
    "sg:orig_category":"Ropa Para Se\u00d1oras (al Por Menor)",
    "sg:phone":"+34 985 64 08 07",
    "sg:postcode":"33700",
    "sg:province":"Asturias",
    "wof:name":"Menendez Fernandez Maria Isabel",
    "wof:placetype":"venue"
},
  "geometry": {"coordinates":[-6.4823179245,43.5019721985],"type":"Point"}
}