{
  "type": "Feature",
  "properties": {
    "addr:full":"Avda Valladolid, S/n Soria Soria 42004",
    "addr:postcode":"42004",
    "addr:street":"Avda Valladolid S / N",
    "iso:country":"ES",
    "sg:address":"Avda Valladolid, S/n",
    "sg:city":"Soria",
    "sg:orig_category":"Agentes, Concesionarios Y Sucursales De Veh\u00cdculos",
    "sg:phone":"+34 975 22 07 48",
    "sg:postcode":"42004",
    "sg:province":"Soria",
    "wof:name":"Jemoya S. A.",
    "wof:placetype":"venue"
},
  "geometry": {"coordinates":[-2.4828391075,41.7677268982],"type":"Point"}
}