{
  "type": "Feature",
  "properties": {
    "iso:country":"ES",
    "sg:address":"Calle de Polonia, 37",
    "sg:city":"Utebo",
    "sg:orig_category":"Fabricaci\u00d3n, Distribuci\u00d3n De Material Para La Climatizaci\u00d3n, Aireaci\u00d3n Y Ventilaci\u00d3n",
    "sg:phone":"+34 976 78 57 93",
    "sg:postcode":"50180",
    "sg:province":"Zaragoza",
    "wof:name":"Arven Sociedad Cooperativa",
    "wof:placetype":"venue"
},
  "geometry": {"coordinates":[-1.009442687,41.7101593018],"type":"Point"}
}