{
  "type": "Feature",
  "properties": {
    "addr:full":"Carrer de Montserrat, 101 Terrassa Barcelona 08221",
    "addr:housenumber":"101",
    "addr:postcode":"08221",
    "addr:street":"Carrer De Montserrat",
    "iso:country":"ES",
    "sg:address":"Carrer de Montserrat, 101",
    "sg:city":"Terrassa",
    "sg:orig_category":"Empresarios Y Productoras De Espect\u00c1culos",
    "sg:phone":"+34 937 88 02 36",
    "sg:postcode":"08221",
    "sg:province":"Barcelona",
    "wof:name":"Epica Scp",
    "wof:placetype":"venue"
},
  "geometry": {"coordinates":[2.0100069046,41.5676765442],"type":"Point"}
}