{
  "type": "Feature",
  "properties": {
    "iso:country":"ES",
    "sg:address":"Carr Lluna, De Sa, 29",
    "sg:city":"Soller",
    "sg:orig_category":"Confecci\u00d3n (fabricaci\u00d3n, Al Por Mayor)",
    "sg:phone":"+34 971 63 28 25",
    "sg:postcode":"07100",
    "sg:province":"Islas Baleares",
    "wof:name":"Vida\u00f1a Triola Juan",
    "wof:placetype":"venue"
},
  "geometry": {"coordinates":[2.7147779465,39.7659072876],"type":"Point"}
}