{
  "type": "Feature",
  "properties": {
    "addr:full":"Avda Libertad (de La), 24 Colmenar Viejo Madrid 28770",
    "addr:postcode":"28770",
    "addr:street":"Avda Libertad De La",
    "iso:country":"ES",
    "sg:address":"Avda Libertad (de La), 24",
    "sg:city":"Colmenar Viejo",
    "sg:orig_category":"Arquitectos",
    "sg:phone":"+34 918 45 62 09",
    "sg:postcode":"28770",
    "sg:province":"Madrid",
    "wof:name":"De Andres Santos Fernando",
    "wof:placetype":"venue"
},
  "geometry": {"coordinates":[-3.7645699978,40.6608123779],"type":"Point"}
}