{
  "type": "Feature",
  "properties": {
    "iso:country":"ES",
    "sg:address":"Calle de Harineros, S/n",
    "sg:city":"Daimiel",
    "sg:orig_category":"Electricidad: Equipos Industriales, Componentes (fabricaci\u00d3n)",
    "sg:phone":"+34 926 85 54 50",
    "sg:postcode":"13250",
    "sg:province":"Ciudad Real",
    "wof:name":"Cocemfe Oretania S.l",
    "wof:placetype":"venue"
},
  "geometry": {"coordinates":[-3.5911800861,39.0772895813],"type":"Point"}
}