{
  "type": "Feature",
  "properties": {
    "iso:country":"ES",
    "sg:address":"Via Augusta, 83",
    "sg:city":"Tarragona",
    "sg:orig_category":"Seguridad Social",
    "sg:phone":"+34 977 29 20 16",
    "sg:postcode":"43003",
    "sg:province":"Tarragona",
    "sg:website":"www.fremap.es",
    "wof:name":"Fremap Mutua De Accidentes De Trabajo Y Enferm.profes.",
    "wof:placetype":"venue"
},
  "geometry": {"coordinates":[1.2641099691,41.1169929504],"type":"Point"}
}