{
  "type": "Feature",
  "properties": {
    "iso:country":"ES",
    "sg:address":"Crt. La Vi\u00f1uela, Km. 0006,3",
    "sg:city":"Brazatortas",
    "sg:orig_category":"Producci\u00d3n, Venta De Productos De Agricultura Biol\u00d3gica",
    "sg:phone":"+34 926 69 82 12",
    "sg:postcode":"13450",
    "sg:province":"Ciudad Real",
    "wof:name":"Navalcuerno S.l.",
    "wof:placetype":"venue"
},
  "geometry": {"coordinates":[-4.2914190292,38.6598701477],"type":"Point"}
}