{
  "type": "Feature",
  "properties": {
    "addr:full":"Calle de Noria, S/n Aldeadavila Ribera Salamanca 37250",
    "addr:housenumber":"s",
    "addr:postcode":"37250",
    "addr:street":"Calle De Noria;/ N Aldeadavila Ribera",
    "iso:country":"ES",
    "sg:address":"Calle de Noria, S/n",
    "sg:city":"Aldeadavila Ribera",
    "sg:orig_category":"Empresas De Carpinter\u00cda Met\u00c1lica",
    "sg:phone":"+34 923 50 54 00",
    "sg:postcode":"37250",
    "sg:province":"Salamanca",
    "wof:name":"Carpinteria Metalica Ribera S.l.",
    "wof:placetype":"venue"
},
  "geometry": {"coordinates":[-6.6141238213,41.2177467346],"type":"Point"}
}