{
  "type": "Feature",
  "properties": {
    "addr:full":"Carr Colon, 185 Vila Joiosa Alicante 03570",
    "addr:housenumber":"185",
    "addr:postcode":"03570",
    "addr:street":"Carr Colon",
    "iso:country":"ES",
    "sg:address":"Carr Colon, 185",
    "sg:city":"Vila Joiosa",
    "sg:orig_category":"Venta, Montaje De Neum\u00c1ticos",
    "sg:phone":"+34 965 89 36 12",
    "sg:postcode":"03570",
    "sg:province":"Alicante",
    "wof:name":"Estudillo Mora Cristobal",
    "wof:placetype":"venue"
},
  "geometry": {"coordinates":[-0.2327190042,38.505821228],"type":"Point"}
}