{
  "type": "Feature",
  "properties": {
    "iso:country":"ES",
    "sg:address":"Plaz Maria Pita, 12",
    "sg:city":"Coru\u00d1a",
    "sg:orig_category":"Loter\u00cda Y T\u00d3mbola",
    "sg:phone":"+34 981 21 06 10",
    "sg:postcode":"15001",
    "sg:province":"La Coru\u00f1a",
    "wof:name":"Paramo Sureda Maria",
    "wof:placetype":"venue"
},
  "geometry": {"coordinates":[-8.3967437744,43.3701553345],"type":"Point"}
}