{
  "type": "Feature",
  "properties": {
    "iso:country":"ES",
    "sg:address":"Avda Lugo (de), 221",
    "sg:city":"Santiago De Compostela",
    "sg:orig_category":"Comercio, Reparaci\u00d3n De Bicicletas, De Motocicletas, De Accesorios",
    "sg:phone":"+34 981 56 45 62",
    "sg:postcode":"15703",
    "sg:province":"La Coru\u00f1a",
    "wof:name":"Chao Import S.l.",
    "wof:placetype":"venue"
},
  "geometry": {"coordinates":[-8.533493042,42.8815841675],"type":"Point"}
}