{
  "type": "Feature",
  "properties": {
    "addr:full":"Calle de Serrablo (de), 116 Sabi\u00f1anigo Huesca 22600",
    "addr:housenumber":"116",
    "addr:postcode":"22600",
    "addr:street":"Calle De Serrablo De",
    "iso:country":"ES",
    "sg:address":"Calle de Serrablo (de), 116",
    "sg:city":"Sabi\u00f1anigo",
    "sg:orig_category":"Distribuci\u00d3n De Petr\u00d3leo Y Derivados",
    "sg:phone":"+34 974 48 03 22",
    "sg:postcode":"22600",
    "sg:province":"Huesca",
    "wof:name":"Cebollero S.l.",
    "wof:placetype":"venue"
},
  "geometry": {"coordinates":[-0.3617359996,42.519657135],"type":"Point"}
}