{
  "type": "Feature",
  "properties": {
    "iso:country":"ES",
    "sg:address":"Rbra De Deustu, 74",
    "sg:city":"Bilbao",
    "sg:orig_category":"M\u00c1rmoles, Granitos Y Piedras Naturales",
    "sg:phone":"+34 944 75 59 84",
    "sg:postcode":"48014",
    "sg:province":"Vizcaya",
    "wof:name":"Pavimentos Y Aplacados Urbanos",
    "wof:placetype":"venue"
},
  "geometry": {"coordinates":[-2.9614489079,43.2679405212],"type":"Point"}
}