{
  "type": "Feature",
  "properties": {
    "addr:full":"Carrer de Justicia, 25 Pineda Mar Barcelona 08397",
    "addr:housenumber":"25",
    "addr:postcode":"08397",
    "addr:street":"Carrer De Justicia;Barcelona",
    "iso:country":"ES",
    "sg:address":"Carrer de Justicia, 25",
    "sg:city":"Pineda Mar",
    "sg:classifiers":[
        {
            "category":"Communications",
            "type":"Services"
        }
    ],
    "sg:phone":"+34 937 67 19 19",
    "sg:postcode":"08397",
    "sg:province":"Barcelona",
    "sg:tags":[
        "televisiones",
        "y",
        "radio"
    ],
    "sg:website":"www.radiopineda.com",
    "wof:name":"Ajuntament De Pineda De Mar",
    "wof:placetype":"venue"
},
  "geometry": {"coordinates":[2.6884455681,41.6231575012],"type":"Point"}
}