{
  "type": "Feature",
  "properties": {
    "addr:full":"Calle de Mercedes (las), 25 Arenas -areeta Vizcaya 48930",
    "addr:housenumber":"25;areeta",
    "addr:postcode":"48930",
    "addr:street":"Calle De Mercedes Las",
    "iso:country":"ES",
    "sg:address":"Calle de Mercedes (las), 25",
    "sg:city":"Arenas -areeta",
    "sg:orig_category":"Ropa Para Ni\u00d1os (al Por Menor)",
    "sg:phone":"+34 944 63 19 30",
    "sg:postcode":"48930",
    "sg:province":"Vizcaya",
    "wof:name":"Kiddys's Class S A",
    "wof:placetype":"venue"
},
  "geometry": {"coordinates":[-3.0131719112,43.3271179199],"type":"Point"}
}