{
  "type": "Feature",
  "properties": {
    "iso:country":"ES",
    "sg:address":"Calle de Feria, 3",
    "sg:city":"Alora",
    "sg:orig_category":"Empresas De Carpinter\u00cda Met\u00c1lica",
    "sg:phone":"+34 952 49 80 60",
    "sg:postcode":"29500",
    "sg:province":"M\u00e1laga",
    "wof:name":"Sanchez Gonsalez Miguel",
    "wof:placetype":"venue"
},
  "geometry": {"coordinates":[-4.7036380768,36.8298950195],"type":"Point"}
}