{
  "type": "Feature",
  "properties": {
    "addr:full":"Carr Bisbe Comes, 22 Ciutadella Menorca Islas Baleares 07760",
    "addr:housenumber":"22",
    "addr:postcode":"07760",
    "addr:street":"Carr Bisbe Comes",
    "iso:country":"ES",
    "sg:address":"Carr Bisbe Comes, 22",
    "sg:city":"Ciutadella Menorca",
    "sg:orig_category":"Promotores Constructores",
    "sg:phone":"+34 971 48 25 70",
    "sg:postcode":"07760",
    "sg:province":"Islas Baleares",
    "wof:name":"Anperrat Construcciones S.l.",
    "wof:placetype":"venue"
},
  "geometry": {"coordinates":[3.8369390965,39.9972572327],"type":"Point"}
}