{
  "type": "Feature",
  "properties": {
    "iso:country":"ES",
    "sg:address":"Cra. Carrer de Disset, S/n",
    "sg:city":"Lli\u00e7a Vall",
    "sg:orig_category":"Fabricaci\u00d3n De Distribuidores Autom\u00c1ticos",
    "sg:phone":"+34 900 35 43 33",
    "sg:postcode":"08185",
    "sg:province":"Barcelona",
    "wof:name":"Cafegra S.l.",
    "wof:placetype":"venue"
},
  "geometry": {"coordinates":[2.2325119972,41.5866622925],"type":"Point"}
}