{
  "type": "Feature",
  "properties": {
    "addr:full":"Ctra Matadepera, 2 Pla Del Bon Aire Barcelona 08225",
    "addr:housenumber":"2",
    "addr:postcode":"08225",
    "addr:street":"Ctra Matadepera",
    "iso:country":"ES",
    "sg:address":"Ctra Matadepera, 2",
    "sg:city":"Pla Del Bon Aire",
    "sg:orig_category":"Maquinaria Para Industrias Diversas",
    "sg:phone":"+34 937 34 90 54",
    "sg:postcode":"08225",
    "sg:province":"Barcelona",
    "wof:name":"Flexer Packaging S.l.",
    "wof:placetype":"venue"
},
  "geometry": {"coordinates":[1.9797079563,41.5738563538],"type":"Point"}
}