{
  "type": "Feature",
  "properties": {
    "addr:full":"Calle de Rosa, S/n Puertollano Ciudad Real 13500",
    "addr:housenumber":"s / n",
    "addr:postcode":"13500",
    "addr:street":"Calle De Rosa",
    "iso:country":"ES",
    "sg:address":"Calle de Rosa, S/n",
    "sg:city":"Puertollano",
    "sg:orig_category":"Centros De Educaci\u00d3n Especial",
    "sg:phone":"+34 926 44 00 69",
    "sg:postcode":"13500",
    "sg:province":"Ciudad Real",
    "wof:name":"Colegio Publico Doctor Limon",
    "wof:placetype":"venue"
},
  "geometry": {"coordinates":[-4.1162338257,38.6865539551],"type":"Point"}
}