{
  "type": "Feature",
  "properties": {
    "iso:country":"ES",
    "sg:address":"Calle de Apolo, 60",
    "sg:city":"Torrevieja",
    "sg:orig_category":"Molduras, Junquillos, Listones Y Molduras Perforadas",
    "sg:phone":"+34 965 70 46 98",
    "sg:postcode":"03180",
    "sg:province":"Alicante",
    "wof:name":"Cutillas Cerdan David",
    "wof:placetype":"venue"
},
  "geometry": {"coordinates":[-0.6788653731,37.9799575806],"type":"Point"}
}