{
  "type": "Feature",
  "properties": {
    "iso:country":"ES",
    "sg:address":"Carrer de Consell De Cent, 227",
    "sg:city":"Barcelona",
    "sg:orig_category":"Agencias De Modelos",
    "sg:phone":"+34 934 51 62 55",
    "sg:postcode":"08011",
    "sg:province":"Barcelona",
    "wof:name":"Doble Punto S.a.",
    "wof:placetype":"venue"
},
  "geometry": {"coordinates":[2.1580209732,41.3855056763],"type":"Point"}
}