{
  "type": "Feature",
  "properties": {
    "iso:country":"ES",
    "sg:address":"Calle de Carlo Goldoni, 60",
    "sg:city":"Malaga",
    "sg:orig_category":"Fabricaci\u00d3n, Alquiler, Venta De Encofrados",
    "sg:phone":"+34 952 24 00 01",
    "sg:postcode":"29004",
    "sg:province":"M\u00e1laga",
    "wof:name":"Sistemas Tecnicos De Encofrados",
    "wof:placetype":"venue"
},
  "geometry": {"coordinates":[-4.488904953,36.6976547241],"type":"Point"}
}