{
  "type": "Feature",
  "properties": {
    "addr:full":"Ibargarai Hiribidea, S/n Bergara Guip\u00f9zcoa 20570",
    "addr:housenumber":"s / n",
    "addr:postcode":"20570",
    "addr:street":"Ibargarai Hiribidea;Guipu\u0300Zcoa",
    "iso:country":"ES",
    "sg:address":"Ibargarai Hiribidea, S/n",
    "sg:city":"Bergara",
    "sg:orig_category":"Guarder\u00cdas",
    "sg:phone":"+34 943 76 20 44",
    "sg:postcode":"20570",
    "sg:province":"Guip\u00f9zcoa",
    "wof:name":"Haurtxoa",
    "wof:placetype":"venue"
},
  "geometry": {"coordinates":[-2.4157474041,43.1153450012],"type":"Point"}
}