{
  "type": "Feature",
  "properties": {
    "iso:country":"ES",
    "sg:address":"Plaz Colon (de), 1",
    "sg:city":"Galapagar",
    "sg:orig_category":"Peluquer\u00cdas, Peluquer\u00cda Mixta",
    "sg:phone":"+34 918 58 40 89",
    "sg:postcode":"28260",
    "sg:province":"Madrid",
    "wof:name":"Guada\u00f1o Cuesta Beatriz",
    "wof:placetype":"venue"
},
  "geometry": {"coordinates":[-4.0020170212,40.5765609741],"type":"Point"}
}