{
  "type": "Feature",
  "properties": {
    "iso:country":"ES",
    "sg:address":"Calle de Miguel De Cervantes, 1",
    "sg:city":"Bullas",
    "sg:orig_category":"Molduras, Junquillos, Listones Y Molduras Perforadas",
    "sg:phone":"+34 968 65 42 50",
    "sg:postcode":"30180",
    "sg:province":"Murcia",
    "wof:name":"Fernandez Lopez Manuel",
    "wof:placetype":"venue"
},
  "geometry": {"coordinates":[-1.6724890471,38.043800354],"type":"Point"}
}