{
  "type": "Feature",
  "properties": {
    "addr:full":"Calle de Florentino Cuevillas, 4 Ourense Ourense 32003",
    "addr:housenumber":"4",
    "addr:postcode":"32003",
    "addr:street":"Calle De Florentino Cuevillas",
    "iso:country":"ES",
    "sg:address":"Calle de Florentino Cuevillas, 4",
    "sg:city":"Ourense",
    "sg:orig_category":"Ingeniero",
    "sg:phone":"+34 988 21 00 71",
    "sg:postcode":"32003",
    "sg:province":"Ourense",
    "wof:name":"Lopez Camacho Jose Blas",
    "wof:placetype":"venue"
},
  "geometry": {"coordinates":[-7.8654069901,42.3431129456],"type":"Point"}
}