{
  "type": "Feature",
  "properties": {
    "addr:full":"Andres Segovia, 18 Xirivella Valencia 46950",
    "addr:housenumber":"18",
    "addr:postcode":"46950",
    "addr:street":"Segovia",
    "iso:country":"ES",
    "sg:address":"Andres Segovia, 18",
    "sg:city":"Xirivella",
    "sg:orig_category":"Peluquer\u00cdas, Peluquer\u00cda Mixta",
    "sg:phone":"+34 963 83 47 82",
    "sg:postcode":"46950",
    "sg:province":"Valencia",
    "wof:name":"Amores Garfella Elvira",
    "wof:placetype":"venue"
},
  "geometry": {"coordinates":[-0.4153028131,39.4661865234],"type":"Point"}
}