{
  "type": "Feature",
  "properties": {
    "iso:country":"ES",
    "sg:address":"Calle de Mota Del Cuervo, 9",
    "sg:city":"Madrid",
    "sg:orig_category":"M\u00dasicos Int\u00c9rpretes",
    "sg:phone":"+34 917 59 87 84",
    "sg:postcode":"28043",
    "sg:province":"Madrid",
    "wof:name":"Producciones Charleston S.l.",
    "wof:placetype":"venue"
},
  "geometry": {"coordinates":[-3.6325409412,40.4648361206],"type":"Point"}
}