{
  "type": "Feature",
  "properties": {
    "addr:full":"Calle de Sevilla, 8 Cordoba C\u00f3rdoba 14003",
    "addr:housenumber":"8",
    "addr:postcode":"14003",
    "addr:street":"Calle De Sevilla;Co\u0301Rdoba",
    "iso:country":"ES",
    "sg:address":"Calle de Sevilla, 8",
    "sg:city":"Cordoba",
    "sg:orig_category":"Inmobiliaria (agencias)",
    "sg:phone":"+34 957 48 01 52",
    "sg:postcode":"14003",
    "sg:province":"C\u00f3rdoba",
    "wof:name":"Proconcor S.l.",
    "wof:placetype":"venue"
},
  "geometry": {"coordinates":[-4.7814860344,37.8831443787],"type":"Point"}
}