{
  "type": "Feature",
  "properties": {
    "iso:country":"ES",
    "sg:address":"Carr Bonastruc De Porta, 18",
    "sg:city":"Girona",
    "sg:orig_category":"Guarder\u00cdas",
    "sg:phone":"+34 972 20 05 55",
    "sg:postcode":"17001",
    "sg:province":"Girona",
    "sg:website":"www.grn.es/lamassana/",
    "wof:name":"Escola Bressol Querubi S.l.",
    "wof:placetype":"venue"
},
  "geometry": {"coordinates":[2.8189179897,41.9843673706],"type":"Point"}
}