{
  "type": "Feature",
  "properties": {
    "iso:country":"ES",
    "sg:address":"Avda Veinticinco De Abril, 24",
    "sg:city":"Icod De Los Vinos",
    "sg:orig_category":"Farmacias",
    "sg:phone":"+34 922 81 02 35",
    "sg:postcode":"38430",
    "sg:province":"Santa Cruz De Tenerife",
    "wof:name":"Martin Lorenzo-caceres Tomas",
    "wof:placetype":"venue"
},
  "geometry": {"coordinates":[-16.7204761505,28.3677654266],"type":"Point"}
}