{
  "type": "Feature",
  "properties": {
    "addr:full":"Avda Segovia, 19 Valladolid Valladolid 47013",
    "addr:housenumber":"19",
    "addr:postcode":"47013",
    "addr:street":"Avda Segovia",
    "iso:country":"ES",
    "sg:address":"Avda Segovia, 19",
    "sg:city":"Valladolid",
    "sg:orig_category":"Ropa Y Accesorios",
    "sg:phone":"+34 983 29 67 90",
    "sg:postcode":"47013",
    "sg:province":"Valladolid",
    "wof:name":"Martin Martin Maximo",
    "wof:placetype":"venue"
},
  "geometry": {"coordinates":[-4.7208991051,41.6429634094],"type":"Point"}
}