{
  "type": "Feature",
  "properties": {
    "iso:country":"ES",
    "sg:address":"Calle de Londres, S/n",
    "sg:city":"Playas De Fa\u00e7abe",
    "sg:orig_category":"Inmobiliaria (agencias)",
    "sg:phone":"+34 922 71 20 16",
    "sg:postcode":"38660",
    "sg:province":"Santa Cruz De Tenerife",
    "wof:name":"Fanal Trading, Lda",
    "wof:placetype":"venue"
},
  "geometry": {"coordinates":[-16.7317714691,28.0760765076],"type":"Point"}
}