{
  "type": "Feature",
  "properties": {
    "iso:country":"ES",
    "sg:address":"Calle de Lepanto, 7",
    "sg:city":"Valencia",
    "sg:orig_category":"M\u00c1rmoles, Granitos Y Piedras Naturales",
    "sg:phone":"+34 963 91 36 29",
    "sg:postcode":"46008",
    "sg:province":"Valencia",
    "wof:name":"Costa Galvez Manuel",
    "wof:placetype":"venue"
},
  "geometry": {"coordinates":[-0.3845359981,39.4737243652],"type":"Point"}
}