{
  "type": "Feature",
  "properties": {
    "addr:full":"Calle de Pintor Velazquez (del), 67 Mostoles Madrid 28935",
    "addr:housenumber":"67",
    "addr:postcode":"28935",
    "addr:street":"Calle De Pintor Velazquez Del",
    "iso:country":"ES",
    "sg:address":"Calle de Pintor Velazquez (del), 67",
    "sg:city":"Mostoles",
    "sg:orig_category":"Barbacoas Y Accesorios",
    "sg:phone":"+34 916 18 81 01",
    "sg:postcode":"28935",
    "sg:province":"Madrid",
    "wof:name":"Calzada Sanz Cb",
    "wof:placetype":"venue"
},
  "geometry": {"coordinates":[-3.8807599545,40.3211975098],"type":"Point"}
}