{
  "type": "Feature",
  "properties": {
    "addr:full":"Calle de Francos, 3 Sevilla Sevilla 41004",
    "addr:housenumber":"3",
    "addr:postcode":"41004",
    "addr:street":"Calle De Francos",
    "iso:country":"ES",
    "sg:address":"Calle de Francos, 3",
    "sg:city":"Sevilla",
    "sg:orig_category":"Ropa Para Se\u00d1oras (al Por Menor)",
    "sg:phone":"+34 954 21 57 80",
    "sg:postcode":"41004",
    "sg:province":"Sevilla",
    "wof:name":"Palacios Bancalero Maria Cruz",
    "wof:placetype":"venue"
},
  "geometry": {"coordinates":[-5.9924688339,37.3878059387],"type":"Point"}
}