{
  "type": "Feature",
  "properties": {
    "addr:full":"Calle de Alcala, 9 Montefrio Granada 18270",
    "addr:housenumber":"9",
    "addr:postcode":"18270",
    "addr:street":"Calle De Alcala",
    "iso:country":"ES",
    "sg:address":"Calle de Alcala, 9",
    "sg:city":"Montefrio",
    "sg:orig_category":"Supermercados Y Hipermercados",
    "sg:phone":"+34 958 31 03 12",
    "sg:postcode":"18270",
    "sg:province":"Granada",
    "wof:name":"Supermercados Arenas Guzman S.l.",
    "wof:placetype":"venue"
},
  "geometry": {"coordinates":[-4.0102200508,37.3216514587],"type":"Point"}
}