{
  "type": "Feature",
  "properties": {
    "iso:country":"ES",
    "sg:address":"Calle de Eusebio Navarro, 20",
    "sg:city":"Palmas De Gran Canaria",
    "sg:orig_category":"Centros Empresariales",
    "sg:phone":"+34 928 43 17 09",
    "sg:postcode":"35003",
    "sg:province":"Las Palmas",
    "wof:name":"Gestion Fiscal De Gran Canaria",
    "wof:placetype":"venue"
},
  "geometry": {"coordinates":[-15.4207897186,28.1099185944],"type":"Point"}
}