{
  "type": "Feature",
  "properties": {
    "addr:full":"Carrer de Sant Joan De Ribera, 34 Muro Alcoy Alicante 03830",
    "addr:housenumber":"34",
    "addr:postcode":"03830",
    "addr:street":"Carrer De Sant Joan De Ribera",
    "iso:country":"ES",
    "sg:address":"Carrer de Sant Joan De Ribera, 34",
    "sg:city":"Muro Alcoy",
    "sg:orig_category":"Reposter\u00cdas",
    "sg:phone":"+34 965 53 17 31",
    "sg:postcode":"03830",
    "sg:province":"Alicante",
    "wof:name":"Silvestre Mora Luis Manuel",
    "wof:placetype":"venue"
},
  "geometry": {"coordinates":[-0.4397999942,38.7828674316],"type":"Point"}
}