{
  "type": "Feature",
  "properties": {
    "addr:full":"Calle de Padilla, 60 Madrid Madrid 28006",
    "addr:housenumber":"60",
    "addr:postcode":"madrid;28006",
    "addr:street":"Calle De Padilla",
    "iso:country":"ES",
    "sg:address":"Calle de Padilla, 60",
    "sg:city":"Madrid",
    "sg:orig_category":"Papeler\u00cdas, Librer\u00cdas",
    "sg:phone":"+34 914 02 57 98",
    "sg:postcode":"28006",
    "sg:province":"Madrid",
    "wof:name":"Ruano Mesa Francisco",
    "wof:placetype":"venue"
},
  "geometry": {"coordinates":[-3.6769371033,40.4310951233],"type":"Point"}
}