{
  "type": "Feature",
  "properties": {
    "iso:country":"ES",
    "sg:address":"Pase San Francisco De Sales, 26",
    "sg:city":"Madrid",
    "sg:orig_category":"Sociedades, Compa\u00d1\u00cdas Aseguradoras",
    "sg:phone":"+34 914 41 96 71",
    "sg:postcode":"28003",
    "sg:province":"Madrid",
    "wof:name":"Velasco Viejo Juan",
    "wof:placetype":"venue"
},
  "geometry": {"coordinates":[-3.7147469521,40.4410400391],"type":"Point"}
}