{
  "type": "Feature",
  "properties": {
    "iso:country":"ES",
    "sg:address":"Calle de Cruz, 22",
    "sg:city":"Cabeza Buey",
    "sg:orig_category":"Molduras, Junquillos, Listones Y Molduras Perforadas",
    "sg:phone":"+34 924 60 00 59",
    "sg:postcode":"06600",
    "sg:province":"Badajoz",
    "wof:name":"Lax Calvo-fernandez Juan Antonio",
    "wof:placetype":"venue"
},
  "geometry": {"coordinates":[-5.2206330299,38.7209205627],"type":"Point"}
}