{
  "type": "Feature",
  "properties": {
    "addr:full":"Calle de Francisco Vales Villamarin, 34 Coru\u00d1a A Coru\u00f1a 15006",
    "addr:housenumber":"34",
    "addr:postcode":"15006",
    "addr:street":"Calle De Francisco Vales Villamarin;Corun\u0303A",
    "iso:country":"ES",
    "sg:address":"Calle de Francisco Vales Villamarin, 34",
    "sg:city":"Coru\u00d1a",
    "sg:orig_category":"Chapister\u00cda",
    "sg:phone":"+34 981 28 64 94",
    "sg:postcode":"15006",
    "sg:province":"A Coru\u00f1a",
    "wof:name":"Valcarcel Lancina Eladio",
    "wof:placetype":"venue"
},
  "geometry": {"coordinates":[-8.3886327744,43.3531265259],"type":"Point"}
}