{
  "type": "Feature",
  "properties": {
    "addr:full":"C/ Enmig, 6 Moncofa Castell\u00f3n 12593",
    "addr:housenumber":"6",
    "addr:postcode":"12593",
    "addr:street":"C / Enmig;Castello\u0301N",
    "iso:country":"ES",
    "sg:address":"C/ Enmig, 6",
    "sg:city":"Moncofa",
    "sg:orig_category":"Cooperativas Agr\u00cdcolas",
    "sg:phone":"+34 964 57 78 07",
    "sg:postcode":"12593",
    "sg:province":"Castell\u00f3n",
    "wof:name":"Coop.agraria La Prosperidad Coop.v.",
    "wof:placetype":"venue"
},
  "geometry": {"coordinates":[-0.1429889947,39.8067741394],"type":"Point"}
}