{
  "type": "Feature",
  "properties": {
    "addr:full":"Calle de Gutenberg, 63 Poligono Industrial Los Villares Salamanca 37184",
    "addr:housenumber":"63",
    "addr:postcode":"37184",
    "addr:street":"Calle De Gutenberg;Industrial",
    "iso:country":"ES",
    "sg:address":"Calle de Gutenberg, 63",
    "sg:city":"Poligono Industrial Los Villares",
    "sg:orig_category":"Herramientas Manuales (fabricaci\u00d3n, Al Por Mayor)",
    "sg:phone":"+34 923 20 43 54",
    "sg:postcode":"37184",
    "sg:province":"Salamanca",
    "wof:name":"Tools Salamanca S.l.",
    "wof:placetype":"venue"
},
  "geometry": {"coordinates":[-5.6396670341,40.9890823364],"type":"Point"}
}