{
  "type": "Feature",
  "properties": {
    "addr:full":"O Sisto, S/n Sixto La Coru\u00f1a 15142",
    "addr:housenumber":"s / n",
    "addr:postcode":"15142",
    "addr:street":"Sixto La Corun\u0303A",
    "iso:country":"ES",
    "sg:address":"O Sisto, S/n",
    "sg:city":"Sixto",
    "sg:orig_category":"Iglesia Cat\u00d3lica",
    "sg:phone":"+34 981 60 00 42",
    "sg:postcode":"15142",
    "sg:province":"La Coru\u00f1a",
    "wof:name":"Arzobispado De Santiago",
    "wof:placetype":"venue"
},
  "geometry": {"coordinates":[-9.1545495987,43.146697998],"type":"Point"}
}