{
  "type": "Feature",
  "properties": {
    "iso:country":"ES",
    "sg:address":"Salgueiros, S/n",
    "sg:city":"Salgueiros",
    "sg:orig_category":"Empresas De Carpinter\u00cda De Madera",
    "sg:phone":"+34 981 67 23 61",
    "sg:postcode":"15175",
    "sg:province":"A Coru\u00f1a",
    "wof:name":"Varela Ca\u00f1as Manuel",
    "wof:placetype":"venue"
},
  "geometry": {"coordinates":[-8.3558893204,43.2278442383],"type":"Point"}
}