{
  "type": "Feature",
  "properties": {
    "iso:country":"ES",
    "sg:address":"Calle de San Pol De Mar, 11",
    "sg:city":"Madrid",
    "sg:orig_category":"Peluqueros: De Se\u00d1oras",
    "sg:phone":"+34 915 41 91 98",
    "sg:postcode":"28008",
    "sg:province":"Madrid",
    "wof:name":"Lopez Campos Modesta",
    "wof:placetype":"venue"
},
  "geometry": {"coordinates":[-3.7274227142,40.4236335754],"type":"Point"}
}