{
  "type": "Feature",
  "properties": {
    "iso:country":"ES",
    "sg:address":"Pase San Francisco De Sales, 13",
    "sg:city":"Madrid",
    "sg:orig_category":"Ense\u00d1anza Superior Privada",
    "sg:phone":"+34 915 49 50 22",
    "sg:postcode":"28003",
    "sg:province":"Madrid",
    "wof:name":"Dominicas Misioneras De La Sagrada Famil",
    "wof:placetype":"venue"
},
  "geometry": {"coordinates":[-3.7159440517,40.4405136108],"type":"Point"}
}