{
  "type": "Feature",
  "properties": {
    "addr:full":"Calle de Virgen Milagrosa, S/n Cordoba C\u00f3rdoba 14010",
    "addr:housenumber":"s / n",
    "addr:postcode":"14010",
    "addr:street":"Calle De Virgen Milagrosa;Co\u0301Rdoba",
    "iso:country":"ES",
    "sg:address":"Calle de Virgen Milagrosa, S/n",
    "sg:city":"Cordoba",
    "sg:orig_category":"Carnicer\u00cdas, Carnicer\u00cdas",
    "sg:phone":"+34 957 25 10 50",
    "sg:postcode":"14010",
    "sg:province":"C\u00f3rdoba",
    "wof:name":"Torrecilla Aguilera Cecilia",
    "wof:placetype":"venue"
},
  "geometry": {"coordinates":[-4.7580590248,37.8856315613],"type":"Point"}
}