{
  "type": "Feature",
  "properties": {
    "iso:country":"ES",
    "sg:address":"Avda Goya, 43",
    "sg:city":"Zaragoza",
    "sg:orig_category":"Muebles, Minoristas",
    "sg:phone":"+34 976 37 76 65",
    "sg:postcode":"50006",
    "sg:province":"Zaragoza",
    "sg:website":"www.sillaszaragoza.com",
    "wof:name":"Sillas Zaragoza S. A.",
    "wof:placetype":"venue"
},
  "geometry": {"coordinates":[-0.8813189864,41.6517295837],"type":"Point"}
}