{
  "type": "Feature",
  "properties": {
    "addr:full":"Calle de Luis Armi\u00d1an, 21 Nava Asturias 33529",
    "addr:housenumber":"21",
    "addr:postcode":"33529",
    "addr:street":"Calle De Luis Armin\u0303An",
    "iso:country":"ES",
    "sg:address":"Calle de Luis Armi\u00d1an, 21",
    "sg:city":"Nava",
    "sg:orig_category":"Laboratorios Y Cl\u00cdnicas Veterinarias",
    "sg:phone":"+34 985 71 66 36",
    "sg:postcode":"33529",
    "sg:province":"Asturias",
    "wof:name":"Agustin Martin S.a.",
    "wof:placetype":"venue"
},
  "geometry": {"coordinates":[-5.5076956749,43.3584289551],"type":"Point"}
}