{
  "type": "Feature",
  "properties": {
    "iso:country":"ES",
    "sg:address":"Calle de Sierra Donesteve, 2",
    "sg:city":"Astillero",
    "sg:orig_category":"Prot\u00c9sicos Dentales",
    "sg:phone":"+34 942 54 00 44",
    "sg:postcode":"39610",
    "sg:province":"Cantabria",
    "wof:name":"Ulloa Gonzalez Higinio Angel",
    "wof:placetype":"venue"
},
  "geometry": {"coordinates":[-3.8196649551,43.4002685547],"type":"Point"}
}