{
  "type": "Feature",
  "properties": {
    "addr:full":"Calle de Artes Graficas, 44 Valencia Valencia 46010",
    "addr:housenumber":"44",
    "addr:postcode":"46010",
    "addr:street":"Calle De;Graficas",
    "iso:country":"ES",
    "sg:address":"Calle de Artes Graficas, 44",
    "sg:city":"Valencia",
    "sg:orig_category":"Arquitectos",
    "sg:phone":"+34 963 60 75 33",
    "sg:postcode":"46010",
    "sg:province":"Valencia",
    "wof:name":"Soler Cruz Maria Pilar",
    "wof:placetype":"venue"
},
  "geometry": {"coordinates":[-0.3588537872,39.4757652283],"type":"Point"}
}