{
  "type": "Feature",
  "properties": {
    "iso:country":"ES",
    "sg:address":"Calle de Padre Ajates, S/n",
    "sg:city":"Papatrigo",
    "sg:orig_category":"Empresas De Carpinter\u00cda De Madera",
    "sg:phone":"+34 920 24 13 47",
    "sg:postcode":"05359",
    "sg:province":"\u00c1vila",
    "wof:name":"Carpinteria Hermanos Jimenez Andres S.l.",
    "wof:placetype":"venue"
},
  "geometry": {"coordinates":[-4.833999157,40.8673782349],"type":"Point"}
}