{
  "type": "Feature",
  "properties": {
    "addr:full":"Calle de Rico, 27 Huelva Huelva 21001",
    "addr:housenumber":"27",
    "addr:postcode":"21001",
    "addr:street":"Calle De Rico",
    "iso:country":"ES",
    "sg:address":"Calle de Rico, 27",
    "sg:city":"Huelva",
    "sg:orig_category":"Abogados",
    "sg:phone":"+34 959 24 68 16",
    "sg:postcode":"21001",
    "sg:province":"Huelva",
    "wof:name":"Sanz Escalera Emiliano Jesus",
    "wof:placetype":"venue"
},
  "geometry": {"coordinates":[-6.9524531364,37.2554740906],"type":"Point"}
}