{
  "type": "Feature",
  "properties": {
    "iso:country":"ES",
    "sg:address":"Calle de Mendez Nu\u00d1ez, 12",
    "sg:city":"Huelva",
    "sg:orig_category":"M\u00c9dicos: Oftalmolog\u00cda",
    "sg:phone":"+34 959 25 99 97",
    "sg:postcode":"21001",
    "sg:province":"Huelva",
    "wof:name":"Ardila Dominguez Fausto",
    "wof:placetype":"venue"
},
  "geometry": {"coordinates":[-6.9523630142,37.258014679],"type":"Point"}
}