{
  "type": "Feature",
  "properties": {
    "iso:country":"ES",
    "sg:address":"Carrer de Vista Alegre, 39",
    "sg:city":"Mataro",
    "sg:orig_category":"Sindicatos De Trabajadores",
    "sg:phone":"+34 937 99 14 14",
    "sg:postcode":"08304",
    "sg:province":"Barcelona",
    "wof:name":"Sindicato De Trabajadores Autonomos Del Taxi De Catalu\u00d1a.",
    "wof:placetype":"venue"
},
  "geometry": {"coordinates":[2.4448370934,41.5542831421],"type":"Point"}
}