{
  "type": "Feature",
  "properties": {
    "addr:full":"Calle de Capitan Cortes, 2 Corrales Cantabria 39400",
    "addr:housenumber":"2",
    "addr:postcode":"39400",
    "addr:street":"Calle De Capitan Cortes",
    "iso:country":"ES",
    "sg:address":"Calle de Capitan Cortes, 2",
    "sg:city":"Corrales",
    "sg:orig_category":"Arquitectos",
    "sg:phone":"+34 942 83 07 55",
    "sg:postcode":"39400",
    "sg:province":"Cantabria",
    "wof:name":"Fernandez Fernandez Luis",
    "wof:placetype":"venue"
},
  "geometry": {"coordinates":[-4.0666298866,43.2547988892],"type":"Point"}
}