{
  "type": "Feature",
  "properties": {
    "addr:full":"Calle de Veracruz, 18 Galapagar Madrid 28260",
    "addr:housenumber":"18",
    "addr:postcode":"28260",
    "addr:street":"Calle De Veracruz",
    "iso:country":"ES",
    "sg:address":"Calle de Veracruz, 18",
    "sg:city":"Galapagar",
    "sg:orig_category":"Zapatos (al Por Menor)",
    "sg:phone":"+34 918 58 10 99",
    "sg:postcode":"28260",
    "sg:province":"Madrid",
    "wof:name":"Martin De La Cruz Isabel",
    "wof:placetype":"venue"
},
  "geometry": {"coordinates":[-4.0027070045,40.574760437],"type":"Point"}
}