{
  "type": "Feature",
  "properties": {
    "addr:full":"Calle de Santa Cruz De Tenerife, 10 Cadiz C\u00e1diz 11007",
    "addr:housenumber":"10",
    "addr:postcode":"11007",
    "addr:street":"Calle De Santa Cruz;Tenerife",
    "iso:country":"ES",
    "sg:address":"Calle de Santa Cruz De Tenerife, 10",
    "sg:city":"Cadiz",
    "sg:orig_category":"Carnicer\u00cdas, Carnicer\u00cdas",
    "sg:phone":"+34 956 26 48 64",
    "sg:postcode":"11007",
    "sg:province":"C\u00e1diz",
    "wof:name":"Moreno Dianez Juan Antonio",
    "wof:placetype":"venue"
},
  "geometry": {"coordinates":[-6.2842621803,36.5241851807],"type":"Point"}
}