{
  "type": "Feature",
  "properties": {
    "addr:full":"Calle de Correo, 8 Motril Granada 18600",
    "addr:housenumber":"8",
    "addr:postcode":"18600",
    "addr:street":"Calle De Correo",
    "iso:country":"ES",
    "sg:address":"Calle de Correo, 8",
    "sg:city":"Motril",
    "sg:orig_category":"Perreras, Pensiones Para Perros, Gatos Y Otros Animales",
    "sg:phone":"+34 958 82 19 69",
    "sg:postcode":"18600",
    "sg:province":"Granada",
    "wof:name":"Manrubia & Prados Cb",
    "wof:placetype":"venue"
},
  "geometry": {"coordinates":[-3.5191457272,36.74584198],"type":"Point"}
}