{
  "type": "Feature",
  "properties": {
    "iso:country":"ES",
    "sg:address":"Carr Coves, 36",
    "sg:city":"Capdepera",
    "sg:orig_category":"Alquiler De Veh\u00cdculos: Turismos Y Utilitarios",
    "sg:phone":"+34 971 56 56 10",
    "sg:postcode":"07580",
    "sg:province":"Islas Baleares",
    "wof:name":"Autocares Levante S. A.",
    "wof:placetype":"venue"
},
  "geometry": {"coordinates":[3.4293928146,39.7007904053],"type":"Point"}
}