{
  "type": "Feature",
  "properties": {
    "iso:country":"ES",
    "sg:address":"Ctra. S. Clemente, S/n",
    "sg:city":"Villanueva Jara",
    "sg:orig_category":"Forjas Y Altos Hornos",
    "sg:phone":"+34 967 49 81 12",
    "sg:postcode":"16230",
    "sg:province":"Cuenca",
    "wof:name":"Jose Maria Romero Cb",
    "wof:placetype":"venue"
},
  "geometry": {"coordinates":[-1.9584540129,39.4430656433],"type":"Point"}
}