{
  "type": "Feature",
  "properties": {
    "iso:country":"ES",
    "sg:address":"Carr Aurora, 5",
    "sg:city":"Torres Segre",
    "sg:orig_category":"Transportes Por V\u00cdas Navegables",
    "sg:phone":"+34 973 79 60 62",
    "sg:postcode":"25170",
    "sg:province":"Lleida",
    "wof:name":"Florensa Biosca Jaime",
    "wof:placetype":"venue"
},
  "geometry": {"coordinates":[0.5142099857,41.5340461731],"type":"Point"}
}