{
  "type": "Feature",
  "properties": {
    "addr:full":"Calle de Juan De La Cruz, 2 Irun Guip\u00f9zcoa 20301",
    "addr:housenumber":"2",
    "addr:postcode":"20301",
    "addr:street":"Calle De Juan De La Cruz;Guipu\u0300Zcoa",
    "iso:country":"ES",
    "sg:address":"Calle de Juan De La Cruz, 2",
    "sg:city":"Irun",
    "sg:orig_category":"M\u00c9dicos: Oftalmolog\u00cda",
    "sg:phone":"+34 943 61 34 08",
    "sg:postcode":"20301",
    "sg:province":"Guip\u00f9zcoa",
    "wof:name":"Fornieles Navarrete Pedro",
    "wof:placetype":"venue"
},
  "geometry": {"coordinates":[-1.7934579849,43.3411903381],"type":"Point"}
}