{
  "type": "Feature",
  "properties": {
    "iso:country":"ES",
    "sg:address":"Avgd Pau (de La), 27",
    "sg:city":"Grau I Platja",
    "sg:orig_category":"Zapatos (al Por Menor)",
    "sg:phone":"+34 962 84 73 23",
    "sg:postcode":"46730",
    "sg:province":"Valencia",
    "wof:name":"Sempere Esparza C.b.",
    "wof:placetype":"venue"
},
  "geometry": {"coordinates":[-0.1664949954,38.9994888306],"type":"Point"}
}