{
  "type": "Feature",
  "properties": {
    "addr:full":"Calle de Victor De La Serna, 37 Madrid Madrid 28016",
    "addr:housenumber":"37",
    "addr:postcode":"madrid;28016",
    "addr:street":"Calle De Victor De La Serna",
    "iso:country":"ES",
    "sg:address":"Calle de Victor De La Serna, 37",
    "sg:city":"Madrid",
    "sg:orig_category":"Cajas De Ahorro",
    "sg:phone":"+34 913 59 97 08",
    "sg:postcode":"28016",
    "sg:province":"Madrid",
    "sg:website":"www.lacaixa.es",
    "wof:name":"Caixa D'estalvis I Pensions De Barcelona",
    "wof:placetype":"venue"
},
  "geometry": {"coordinates":[-3.6720600128,40.4566192627],"type":"Point"}
}