{
  "type": "Feature",
  "properties": {
    "addr:full":"Calle de Juan Xxiii (de), 10 Parla Madrid 28980",
    "addr:housenumber":"10",
    "addr:postcode":"28980",
    "addr:street":"Calle De Juan Xxiii De",
    "iso:country":"ES",
    "sg:address":"Calle de Juan Xxiii (de), 10",
    "sg:city":"Parla",
    "sg:orig_category":"Molduras, Junquillos, Listones Y Molduras Perforadas",
    "sg:phone":"+34 916 99 44 57",
    "sg:postcode":"28980",
    "sg:province":"Madrid",
    "wof:name":"Jimenez Luque Miguel",
    "wof:placetype":"venue"
},
  "geometry": {"coordinates":[-3.7628850937,40.2404251099],"type":"Point"}
}