{
  "type": "Feature",
  "properties": {
    "addr:full":"Calle de Ramon Y Cajal, 4 Cortijos Nuevos Ja\u00e9n 23293",
    "addr:housenumber":"4",
    "addr:postcode":"23293",
    "addr:street":"Calle De Ramon Y Cajal",
    "iso:country":"ES",
    "sg:address":"Calle de Ramon Y Cajal, 4",
    "sg:city":"Cortijos Nuevos",
    "sg:classifiers":[
        {
            "category":"Taxi",
            "type":"Transportation"
        }
    ],
    "sg:phone":"+34 953 49 64 17",
    "sg:postcode":"23293",
    "sg:province":"Ja\u00e9n",
    "wof:name":"Mu\u00f1oz Pretel Manuel",
    "wof:placetype":"venue"
},
  "geometry": {"coordinates":[-2.6999690533,38.2573356628],"type":"Point"}
}