{
  "type": "Feature",
  "properties": {
    "iso:country":"ES",
    "sg:address":"Calle de San Juan, 2",
    "sg:city":"Daimiel",
    "sg:orig_category":"Electricidad, Electr\u00d3nica: Material Y Suministros (al Por Mayor)",
    "sg:phone":"+34 926 85 20 06",
    "sg:postcode":"13250",
    "sg:province":"Ciudad Real",
    "wof:name":"Sanchez-camacho Reguillos Miguel Angel",
    "wof:placetype":"venue"
},
  "geometry": {"coordinates":[-3.6160569191,39.0695648193],"type":"Point"}
}