{
  "type": "Feature",
  "properties": {
    "addr:full":"Calle de Miranda, 20 Burgos Burgos 09002",
    "addr:housenumber":"20",
    "addr:postcode":"09002",
    "addr:street":"Calle De Miranda",
    "iso:country":"ES",
    "sg:address":"Calle de Miranda, 20",
    "sg:city":"Burgos",
    "sg:orig_category":"Florister\u00cdas",
    "sg:phone":"+34 947 26 87 34",
    "sg:postcode":"09002",
    "sg:province":"Burgos",
    "wof:name":"Jimenez Bascones Pedro",
    "wof:placetype":"venue"
},
  "geometry": {"coordinates":[-3.6986420155,42.3380584717],"type":"Point"}
}