{
  "type": "Feature",
  "properties": {
    "iso:country":"ES",
    "sg:address":"Calle de Correos, S/n",
    "sg:city":"Puente Tocinos",
    "sg:orig_category":"Quincaller\u00cda (al Por Menor)",
    "sg:phone":"+34 968 30 46 62",
    "sg:postcode":"30006",
    "sg:province":"Murcia",
    "wof:name":"Molina Lopez Pedro",
    "wof:placetype":"venue"
},
  "geometry": {"coordinates":[-1.1028074026,37.9938201904],"type":"Point"}
}