{
  "type": "Feature",
  "properties": {
    "iso:country":"ES",
    "sg:address":"Calle de Larragana, 3",
    "sg:city":"Vitoria-gasteiz",
    "sg:orig_category":"Abrasivos Y Superabrasivos (fabricaci\u00d3n, Al Por Mayor)",
    "sg:phone":"+34 945 27 75 17",
    "sg:postcode":"01013",
    "sg:province":"\u00c1lava",
    "sg:website":"www.abrasivoflexton.com",
    "wof:name":"Abrasivos Flexston, S.l.",
    "wof:placetype":"venue"
},
  "geometry": {"coordinates":[-2.649728,42.867283],"type":"Point"}
}