{
  "type": "Feature",
  "properties": {
    "iso:country":"ES",
    "sg:address":"Ctr Porzuna, S/n",
    "sg:city":"Piedrabuena",
    "sg:orig_category":"Promotores Constructores",
    "sg:phone":"+34 926 69 73 39",
    "sg:postcode":"13100",
    "sg:province":"Ciudad Real",
    "wof:name":"Agricola Industrial Santa Oliva S.l",
    "wof:placetype":"venue"
},
  "geometry": {"coordinates":[-4.0764627457,39.0822067261],"type":"Point"}
}