{
  "type": "Feature",
  "properties": {
    "iso:country":"ES",
    "sg:address":"Ctra. Nacional 340, Km. 0137,6",
    "sg:city":"Benicarlo",
    "sg:orig_category":"Contenedores (mercanc\u00cdas)",
    "sg:phone":"+34 964 46 51 00",
    "sg:postcode":"12580",
    "sg:province":"Castell\u00f3n",
    "wof:name":"Transportes Marzal S.a.",
    "wof:placetype":"venue"
},
  "geometry": {"coordinates":[0.4042100012,40.4457893372],"type":"Point"}
}