{
  "type": "Feature",
  "properties": {
    "addr:full":"Calle de Gonzalez Besada, 10 Oviedo Asturias 33007",
    "addr:housenumber":"10",
    "addr:postcode":"33007",
    "addr:street":"Calle De Gonzalez Besada",
    "iso:country":"ES",
    "sg:address":"Calle de Gonzalez Besada, 10",
    "sg:city":"Oviedo",
    "sg:orig_category":"M\u00c9dicos: Estomatolog\u00cda",
    "sg:phone":"+34 985 24 47 05",
    "sg:postcode":"33007",
    "sg:province":"Asturias",
    "wof:name":"Medicina Y Cirugia Oral Y Maxilofacial S.l.",
    "wof:placetype":"venue"
},
  "geometry": {"coordinates":[-5.8492870331,43.3569335938],"type":"Point"}
}