{
  "type": "Feature",
  "properties": {
    "iso:country":"ES",
    "sg:address":"Carrer de Villarroel, 45",
    "sg:city":"Barcelona",
    "sg:orig_category":"Aparcamientos (infraestructuras, Accesorios)",
    "sg:phone":"+34 933 23 37 63",
    "sg:postcode":"08011",
    "sg:province":"Barcelona",
    "wof:name":"Villur S. A.",
    "wof:placetype":"venue"
},
  "geometry": {"coordinates":[2.1602809429,41.3823661804],"type":"Point"}
}