{
  "type": "Feature",
  "properties": {
    "iso:country":"ES",
    "sg:address":"C/ Ciutat De Sevilla, 42",
    "sg:city":"Paterna",
    "sg:orig_category":"Artes Gr\u00c1ficas, Artes Pl\u00c1sticas (curso)",
    "sg:phone":"+34 961 32 30 88",
    "sg:postcode":"46988",
    "sg:province":"Valencia",
    "wof:name":"Peliculados Levante S. L.",
    "wof:placetype":"venue"
},
  "geometry": {"coordinates":[-0.4649890065,39.5210990906],"type":"Point"}
}