{
  "type": "Feature",
  "properties": {
    "addr:full":"Calle de Gaztambide, 68 Madrid Madrid 28003",
    "addr:housenumber":"68",
    "addr:postcode":"madrid;28003",
    "addr:street":"Calle De Gaztambide",
    "iso:country":"ES",
    "sg:address":"Calle de Gaztambide, 68",
    "sg:city":"Madrid",
    "sg:orig_category":"Carnicer\u00cdas, Carnicer\u00cdas",
    "sg:phone":"+34 914 41 01 74",
    "sg:postcode":"28003",
    "sg:province":"Madrid",
    "wof:name":"Jimenez Salgueiro Jose",
    "wof:placetype":"venue"
},
  "geometry": {"coordinates":[-3.7152013779,40.4395179749],"type":"Point"}
}