{
  "type": "Feature",
  "properties": {
    "iso:country":"ES",
    "sg:address":"Calle de Aragoneses (de Los), 2",
    "sg:city":"Alcobendas",
    "sg:orig_category":"Centros De Reservas Hoteleras",
    "sg:phone":"+34 916 61 16 88",
    "sg:postcode":"28108",
    "sg:province":"Madrid",
    "sg:website":"www.pinocchio.es",
    "wof:name":"Monaco Alimentaria S.a.",
    "wof:placetype":"venue"
},
  "geometry": {"coordinates":[-3.6599686146,40.5241699219],"type":"Point"}
}