{
  "type": "Feature",
  "properties": {
    "iso:country":"ES",
    "sg:address":"Urb. Porto Avieira(gandara), 19",
    "sg:city":"Sigueiro",
    "sg:orig_category":"Audiovisuales (producci\u00d3n, Edici\u00d3n, Realizaci\u00d3n)",
    "sg:phone":"+34 981 68 89 20",
    "sg:postcode":"15888",
    "sg:province":"La Coru\u00f1a",
    "wof:name":"Portico De Comunicaciones S.l.",
    "wof:placetype":"venue"
},
  "geometry": {"coordinates":[-8.4441986084,42.966709137],"type":"Point"}
}