{
  "type": "Feature",
  "properties": {
    "iso:country":"ES",
    "sg:address":"Cia Navegacion Paquet (pto Luz), S/n",
    "sg:city":"Las Palmas",
    "sg:classifiers":[
        {
            "category":"Recreation",
            "type":"Entertainment"
        }
    ],
    "sg:phone":"+34 928 46 42 66",
    "sg:postcode":"35008",
    "sg:province":"Las Palmas",
    "sg:tags":[
        "caza",
        "pr\u00c1ctica",
        "la",
        "de",
        "pesca",
        "y"
    ],
    "wof:name":"Maruha Kabushiki Kaisha",
    "wof:placetype":"venue"
},
  "geometry": {"coordinates":[-15.4216136932,28.1481399536],"type":"Point"}
}