{
  "type": "Feature",
  "properties": {
    "addr:full":"Barria, 5 Urdu\u00f1a-ordu\u00f1a Vizcaya 48460",
    "addr:housenumber":"5",
    "addr:postcode":"48460",
    "addr:street":"Barria",
    "iso:country":"ES",
    "sg:address":"Barria, 5",
    "sg:city":"Urdu\u00f1a-ordu\u00f1a",
    "sg:orig_category":"\u00d3ptica: Instrumentos (fabricaci\u00d3n)",
    "sg:phone":"+34 945 38 44 99",
    "sg:postcode":"48460",
    "sg:province":"Vizcaya",
    "sg:website":"www.luyandoopticos.com",
    "wof:name":"Luyando Opticos S.l.",
    "wof:placetype":"venue"
},
  "geometry": {"coordinates":[-3.0096225739,42.9944496155],"type":"Point"}
}