{
  "type": "Feature",
  "properties": {
    "iso:country":"ES",
    "sg:address":"Carrer de Minetes, 9",
    "sg:city":"Granollers",
    "sg:orig_category":"Frutas, Legumbres Frescas Y Tempranas (al Por Menor)",
    "sg:phone":"+34 938 40 24 04",
    "sg:postcode":"08402",
    "sg:province":"Barcelona",
    "wof:name":"Pont Portet Salvador",
    "wof:placetype":"venue"
},
  "geometry": {"coordinates":[2.2914700508,41.6122894287],"type":"Point"}
}