{
  "type": "Feature",
  "properties": {
    "addr:full":"Pla\u00c7 Major, 33 Betxi Castell\u00f3n 12549",
    "addr:housenumber":"33",
    "addr:postcode":"12549",
    "addr:street":"Betxi Castello\u0301N",
    "iso:country":"ES",
    "sg:address":"Pla\u00c7 Major, 33",
    "sg:city":"Betxi",
    "sg:orig_category":"Cajas De Ahorro",
    "sg:phone":"+34 964 62 00 30",
    "sg:postcode":"12549",
    "sg:province":"Castell\u00f3n",
    "wof:name":"Caja De Ahorros De Valencia Castellon Y Alicante",
    "wof:placetype":"venue"
},
  "geometry": {"coordinates":[-0.1963589936,39.9285507202],"type":"Point"}
}