{
  "type": "Feature",
  "properties": {
    "iso:country":"ES",
    "sg:address":"Carr Industria, 26",
    "sg:city":"Palamos",
    "sg:orig_category":"M\u00c1quinas De Escribir, M\u00c1quinas De Oficina (al Por Menor, Reparaci\u00d3n)",
    "sg:phone":"+34 972 60 14 50",
    "sg:postcode":"17230",
    "sg:province":"Girona",
    "sg:website":"www.jorpa.net",
    "wof:name":"Jorpa Sistemes Informatics S.l.",
    "wof:placetype":"venue"
},
  "geometry": {"coordinates":[3.1274039745,41.8500671387],"type":"Point"}
}