{
  "type": "Feature",
  "properties": {
    "addr:full":"B, S/n Alcoi Alicante 03800",
    "addr:housenumber":"s / n",
    "addr:postcode":"03800",
    "iso:country":"ES",
    "sg:address":"B, S/n",
    "sg:city":"Alcoi",
    "sg:orig_category":"Plomeros",
    "sg:phone":"+34 965 33 37 12",
    "sg:postcode":"03800",
    "sg:province":"Alicante",
    "wof:name":"Comercial Fontanera S.l.",
    "wof:placetype":"venue"
},
  "geometry": {"coordinates":[-0.4631600082,38.7107849121],"type":"Point"}
}