{
  "type": "Feature",
  "properties": {
    "addr:full":"Carr Pere Amoros, De, S/n Arta Islas Baleares 07570",
    "addr:postcode":"07570",
    "addr:street":"Carr Pere Amoros De S / N Arta Islas Baleares",
    "iso:country":"ES",
    "sg:address":"Carr Pere Amoros, De, S/n",
    "sg:city":"Arta",
    "sg:orig_category":"Centros De Educaci\u00d3n Especial",
    "sg:phone":"+34 971 83 50 56",
    "sg:postcode":"07570",
    "sg:province":"Islas Baleares",
    "wof:name":"Cooperativa Aixa",
    "wof:placetype":"venue"
},
  "geometry": {"coordinates":[3.3463900089,39.6962509155],"type":"Point"}
}