{
  "type": "Feature",
  "properties": {
    "iso:country":"ES",
    "sg:address":"Carr Tosqueres (les), 7",
    "sg:city":"Moraira",
    "sg:orig_category":"Reposter\u00cdas",
    "sg:phone":"+34 966 49 17 17",
    "sg:postcode":"03724",
    "sg:province":"Alicante",
    "wof:name":"Sanchez Fernandez Francisco",
    "wof:placetype":"venue"
},
  "geometry": {"coordinates":[0.1334089935,38.6877479553],"type":"Point"}
}