{
  "type": "Feature",
  "properties": {
    "iso:country":"ES",
    "sg:address":"Elorriagazar Kalea, 6",
    "sg:city":"Tra\u00f1a-matiena",
    "sg:orig_category":"Servicio De Salud",
    "sg:phone":"+34 946 21 41 27",
    "sg:postcode":"48220",
    "sg:province":"Vizcaya",
    "wof:name":"Plusba\u00d1o S.l.",
    "wof:placetype":"venue"
},
  "geometry": {"coordinates":[-2.6079039574,43.1692581177],"type":"Point"}
}