{
  "type": "Feature",
  "properties": {
    "addr:full":"Avda Astorga, 80 Virgen Camino Le\u00f3n 24198",
    "addr:housenumber":"80",
    "addr:postcode":"24198",
    "addr:street":"Avda Astorga;Camino Leo\u0301N",
    "iso:country":"ES",
    "sg:address":"Avda Astorga, 80",
    "sg:city":"Virgen Camino",
    "sg:orig_category":"Quincaller\u00cda (al Por Menor)",
    "sg:phone":"+34 987 30 00 04",
    "sg:postcode":"24198",
    "sg:province":"Le\u00f3n",
    "wof:name":"Molero Garcia Ramon",
    "wof:placetype":"venue"
},
  "geometry": {"coordinates":[-5.6407938004,42.5803794861],"type":"Point"}
}