{
  "type": "Feature",
  "properties": {
    "addr:full":"Avda Aragon, 36 Montalban Teruel 44700",
    "addr:housenumber":"36",
    "addr:postcode":"44700",
    "addr:street":"Avda Aragon",
    "iso:country":"ES",
    "sg:address":"Avda Aragon, 36",
    "sg:city":"Montalban",
    "sg:orig_category":"Supermercados Y Hipermercados",
    "sg:phone":"+34 978 75 05 07",
    "sg:postcode":"44700",
    "sg:province":"Teruel",
    "wof:name":"Julian Marzo S. L.",
    "wof:placetype":"venue"
},
  "geometry": {"coordinates":[-0.7980690002,40.8313903809],"type":"Point"}
}