{
  "type": "Feature",
  "properties": {
    "iso:country":"ES",
    "sg:address":"Calle de Alcoba, 73",
    "sg:city":"Dos Hermanas",
    "sg:orig_category":"Tapicer\u00cdas",
    "sg:phone":"+34 954 72 86 77",
    "sg:postcode":"41700",
    "sg:province":"Sevilla",
    "wof:name":"Vargas Gomez Braulio",
    "wof:placetype":"venue"
},
  "geometry": {"coordinates":[-5.9252791405,37.2867279053],"type":"Point"}
}