{
  "type": "Feature",
  "properties": {
    "iso:country":"ES",
    "sg:address":"Plaz Casilla, 1",
    "sg:city":"Bilbao",
    "sg:orig_category":"Art\u00cdculos De Regalo (al Por Menor)",
    "sg:phone":"+34 944 10 30 06",
    "sg:postcode":"48012",
    "sg:province":"Vizcaya",
    "wof:name":"Ruiz Escudero Maria Del Carmen",
    "wof:placetype":"venue"
},
  "geometry": {"coordinates":[-2.9442179203,43.2574806213],"type":"Point"}
}