{
  "type": "Feature",
  "properties": {
    "addr:full":"Pol Ind La Algaida, Km. 0003,0 Roquetas Mar Almer\u00eda 04740",
    "addr:postcode":"04740",
    "addr:street":"0003,0",
    "iso:country":"ES",
    "sg:address":"Pol Ind La Algaida, Km. 0003,0",
    "sg:city":"Roquetas Mar",
    "sg:orig_category":"Alquiler De Veh\u00cdculos: Turismos Y Utilitarios",
    "sg:phone":"+34 950 32 25 04",
    "sg:postcode":"04740",
    "sg:province":"Almer\u00eda",
    "wof:name":"Raguse Motor S.l.",
    "wof:placetype":"venue"
},
  "geometry": {"coordinates":[-2.6124989986,36.7638435364],"type":"Point"}
}