{
  "type": "Feature",
  "properties": {
    "addr:full":"Ctra. Losar De La Vera, S/n Losar Vera C\u00e1ceres 10460",
    "addr:housenumber":"s / n",
    "addr:postcode":"10460",
    "addr:street":"Ctra. Losar De La Vera",
    "iso:country":"ES",
    "sg:address":"Ctra. Losar De La Vera, S/n",
    "sg:city":"Losar Vera",
    "sg:orig_category":"Aparatos E Instalaci\u00d3n De Regad\u00cdos",
    "sg:phone":"+34 927 56 90 18",
    "sg:postcode":"10460",
    "sg:province":"C\u00e1ceres",
    "wof:name":"Indofer S.l.",
    "wof:placetype":"venue"
},
  "geometry": {"coordinates":[-5.6001491547,40.1184997559],"type":"Point"}
}