{
  "type": "Feature",
  "properties": {
    "addr:full":"Calle de Dolores Ibarruri, La Pasionaria, 14 Puerto Valencia 46520",
    "addr:housenumber":"14",
    "addr:postcode":"46520",
    "addr:street":"Calle De Dolores Ibarruri La Pasionaria",
    "iso:country":"ES",
    "sg:address":"Calle de Dolores Ibarruri, La Pasionaria, 14",
    "sg:city":"Puerto",
    "sg:orig_category":"Agencias De Trabajo Temporal",
    "sg:phone":"+34 962 68 34 50",
    "sg:postcode":"46520",
    "sg:province":"Valencia",
    "sg:website":"www.adecco.es",
    "wof:name":"Adecco E.t.t. S.a.",
    "wof:placetype":"venue"
},
  "geometry": {"coordinates":[-0.3768048882,39.4702377319],"type":"Point"}
}