{
  "type": "Feature",
  "properties": {
    "iso:country":"ES",
    "sg:address":"Carrer de Guillem Forteza, 6",
    "sg:city":"Palma",
    "sg:orig_category":"M\u00c9dicos: Estomatolog\u00cda",
    "sg:phone":"+34 971 20 02 62",
    "sg:postcode":"07010",
    "sg:province":"Islas Baleares",
    "wof:name":"Guillem Obanos Concepcion",
    "wof:placetype":"venue"
},
  "geometry": {"coordinates":[2.646337986,39.5874176025],"type":"Point"}
}