{
  "type": "Feature",
  "properties": {
    "addr:full":"Calle de Jupiter, S/n Puebla Almoradiel Toledo 45840",
    "addr:housenumber":"s / n",
    "addr:postcode":"45840",
    "addr:street":"Calle De Jupiter;Almoradiel",
    "iso:country":"ES",
    "sg:address":"Calle de Jupiter, S/n",
    "sg:city":"Puebla Almoradiel",
    "sg:orig_category":"Promotores Constructores",
    "sg:phone":"+34 925 20 56 37",
    "sg:postcode":"45840",
    "sg:province":"Toledo",
    "wof:name":"Obras Micar S.l.",
    "wof:placetype":"venue"
},
  "geometry": {"coordinates":[-3.1157441139,39.5946846008],"type":"Point"}
}