{
  "type": "Feature",
  "properties": {
    "addr:full":"Calle de Prado, 3 Prado Del Rey C\u00e1diz 11660",
    "addr:housenumber":"3",
    "addr:postcode":"11660",
    "addr:street":"Calle De Prado",
    "iso:country":"ES",
    "sg:address":"Calle de Prado, 3",
    "sg:city":"Prado Del Rey",
    "sg:orig_category":"Estancos",
    "sg:phone":"+34 956 72 46 07",
    "sg:postcode":"11660",
    "sg:province":"C\u00e1diz",
    "wof:name":"Gomez Gutierrez Maria Inmaculada",
    "wof:placetype":"venue"
},
  "geometry": {"coordinates":[-5.5575790405,36.7871627808],"type":"Point"}
}