{
  "type": "Feature",
  "properties": {
    "iso:country":"ES",
    "sg:address":"Calle de Alfar (del), 2",
    "sg:city":"Tres Cantos",
    "sg:orig_category":"Productos Qu\u00cdmicos (fabricaci\u00d3n, Al Por Mayor)",
    "sg:phone":"+34 918 07 48 09",
    "sg:postcode":"28760",
    "sg:province":"Madrid",
    "wof:name":"Centro Espa\u00d1ol De Metrologia",
    "wof:placetype":"venue"
},
  "geometry": {"coordinates":[-3.6968297958,40.5957832336],"type":"Point"}
}