{
  "type": "Feature",
  "properties": {
    "iso:country":"ES",
    "sg:address":"Calle de Maestro Lara, 40",
    "sg:city":"Cozar",
    "sg:orig_category":"Panader\u00cdas, Panader\u00cdas",
    "sg:phone":"+34 926 36 51 48",
    "sg:postcode":"13345",
    "sg:province":"Ciudad Real",
    "wof:name":"Romero Castilla Francisco",
    "wof:placetype":"venue"
},
  "geometry": {"coordinates":[-3.0700941086,38.6614837646],"type":"Point"}
}