{
  "type": "Feature",
  "properties": {
    "iso:country":"ES",
    "sg:address":"Pol Ind Collet, 213",
    "sg:city":"Benicarlo",
    "sg:orig_category":"Transportes Por Carretera: Lotes Completos, Mercanc\u00cdas Diversas",
    "sg:phone":"+34 964 47 44 65",
    "sg:postcode":"12580",
    "sg:province":"Castell\u00f3n",
    "wof:name":"Miguel Y Miguel C.b.",
    "wof:placetype":"venue"
},
  "geometry": {"coordinates":[0.4042100012,40.4457893372],"type":"Point"}
}