{
  "type": "Feature",
  "properties": {
    "addr:full":"Atvia De Logro\u00f1o, Km. 0009,0 Zaragoza Zaragoza 50011",
    "addr:postcode":"50011",
    "addr:street":"Logron\u0303O Km. 0009,0",
    "iso:country":"ES",
    "sg:address":"Atvia De Logro\u00f1o, Km. 0009,0",
    "sg:city":"Zaragoza",
    "sg:orig_category":"Agencias Y Agentes Comerciales, Representantes",
    "sg:phone":"+34 976 77 01 91",
    "sg:postcode":"50011",
    "sg:province":"Zaragoza",
    "wof:name":"Balboa Social Club S. L.",
    "wof:placetype":"venue"
},
  "geometry": {"coordinates":[-1.0011901855,41.6566925049],"type":"Point"}
}