{
  "type": "Feature",
  "properties": {
    "addr:full":"Calle de Rosal, S/n Rincon Victoria M\u00e1laga 29730",
    "addr:housenumber":"/ n",
    "addr:postcode":"29730",
    "addr:street":"Calle De Rosal S;Ma\u0301Laga",
    "iso:country":"ES",
    "sg:address":"Calle de Rosal, S/n",
    "sg:city":"Rincon Victoria",
    "sg:orig_category":"Electricidad Veh\u00cdculo",
    "sg:phone":"+34 952 40 43 86",
    "sg:postcode":"29730",
    "sg:province":"M\u00e1laga",
    "wof:name":"Palomo Benitez Francisco",
    "wof:placetype":"venue"
},
  "geometry": {"coordinates":[-4.2710089684,36.7168388367],"type":"Point"}
}