{
  "type": "Feature",
  "properties": {
    "iso:country":"ES",
    "sg:address":"Calle de Jonay, 6",
    "sg:city":"S. Sebastian Gomera",
    "sg:orig_category":"Alimentaci\u00d3n General (al Por Menor)",
    "sg:phone":"+34 922 87 14 03",
    "sg:postcode":"38800",
    "sg:province":"Santa Cruz De Tenerife",
    "wof:name":"Distribuciones Jonay Santos S.l.",
    "wof:placetype":"venue"
},
  "geometry": {"coordinates":[-17.1105136871,28.0907344818],"type":"Point"}
}