{
  "type": "Feature",
  "properties": {
    "iso:country":"ES",
    "sg:address":"Ctro Cial Alcampo, S/n",
    "sg:city":"Son Ramonell Nou",
    "sg:orig_category":"Ropa Para Se\u00d1oras (al Por Menor)",
    "sg:phone":"+34 971 60 40 81",
    "sg:postcode":"07141",
    "sg:province":"Islas Baleares",
    "wof:name":"Promod Espa\u00f1a S.a.",
    "wof:placetype":"venue"
},
  "geometry": {"coordinates":[2.7445349693,39.6195487976],"type":"Point"}
}