{
  "type": "Feature",
  "properties": {
    "iso:country":"ES",
    "sg:address":"Calle de Charcos (los), 6",
    "sg:city":"Taco",
    "sg:orig_category":"Cl\u00cdnicas Dentales",
    "sg:phone":"+34 922 61 12 57",
    "sg:postcode":"38108",
    "sg:province":"Santa Cruz De Tenerife",
    "wof:name":"Clinica Dental Manuel Marin S.l.",
    "wof:placetype":"venue"
},
  "geometry": {"coordinates":[-16.2976093292,28.4458198547],"type":"Point"}
}