{
  "type": "Feature",
  "properties": {
    "addr:full":"Nus Trinitat, S/n Barcelona Barcelona 08033",
    "addr:housenumber":"s / n",
    "addr:postcode":"08033",
    "iso:country":"ES",
    "sg:address":"Nus Trinitat, S/n",
    "sg:city":"Barcelona",
    "sg:orig_category":"Distribuci\u00d3n De Petr\u00d3leo Y Derivados",
    "sg:phone":"+34 933 46 10 75",
    "sg:postcode":"08033",
    "sg:province":"Barcelona",
    "wof:name":"Gespevesa S.a.",
    "wof:placetype":"venue"
},
  "geometry": {"coordinates":[2.1937050819,41.4489212036],"type":"Point"}
}