{
  "type": "Feature",
  "properties": {
    "iso:country":"ES",
    "sg:address":"Calle de Juan Bautista Uriarte, 49",
    "sg:city":"Galdakao",
    "sg:orig_category":"Material Y Suministros Para Imprenta E Industrias Gr\u00c1ficas",
    "sg:phone":"+34 944 57 23 32",
    "sg:postcode":"48960",
    "sg:province":"Vizcaya",
    "wof:name":"Gemma Maguregui De Miguel",
    "wof:placetype":"venue"
},
  "geometry": {"coordinates":[-2.8416690826,43.2307701111],"type":"Point"}
}