{
  "type": "Feature",
  "properties": {
    "iso:country":"ES",
    "sg:address":"Magdalena, 33",
    "sg:city":"Villaviciosa",
    "sg:orig_category":"Supermercados Y Hipermercados",
    "sg:phone":"+34 985 89 32 04",
    "sg:postcode":"33300",
    "sg:province":"Asturias",
    "wof:name":"Trebol Center S. A.",
    "wof:placetype":"venue"
},
  "geometry": {"coordinates":[-5.4345989227,43.4814491272],"type":"Point"}
}