{
  "type": "Feature",
  "properties": {
    "iso:country":"ES",
    "sg:address":"Calle de Nueva, 8",
    "sg:city":"Campillo Salvatierra",
    "sg:orig_category":"Fabrica De Charcuter\u00cda",
    "sg:phone":"+34 923 58 10 51",
    "sg:postcode":"37778",
    "sg:province":"Salamanca",
    "wof:name":"Benito Puente Jose",
    "wof:placetype":"venue"
},
  "geometry": {"coordinates":[-5.6778941154,40.5667457581],"type":"Point"}
}