{
  "type": "Feature",
  "properties": {
    "iso:country":"ES",
    "sg:address":"Calle de Andalucia (de), 3",
    "sg:city":"Mejorada Campo",
    "sg:orig_category":"Trabajos De Fotocomposici\u00d3n",
    "sg:phone":"+34 916 68 04 40",
    "sg:postcode":"28840",
    "sg:province":"Madrid",
    "wof:name":"Excatres S.a.",
    "wof:placetype":"venue"
},
  "geometry": {"coordinates":[-3.4842293262,40.3968353271],"type":"Point"}
}