{
  "type": "Feature",
  "properties": {
    "addr:full":"Ctra Alfara A Tortosa (d'), S/n Reguers Tarragona 43527",
    "addr:postcode":"43527",
    "addr:street":"Ctra Alfara A Tortosa D ' S / N Reguers",
    "iso:country":"ES",
    "sg:address":"Ctra Alfara A Tortosa (d'), S/n",
    "sg:city":"Reguers",
    "sg:orig_category":"Poller\u00cda Y Caza (al Por Menor)",
    "sg:phone":"+34 977 47 41 56",
    "sg:postcode":"43527",
    "sg:province":"Tarragona",
    "wof:name":"Pavo Y Derivados S.a.",
    "wof:placetype":"venue"
},
  "geometry": {"coordinates":[0.4487150013,40.8387298584],"type":"Point"}
}