{
  "type": "Feature",
  "properties": {
    "addr:full":"Ctra. Alcorcon-plasencia, 83 Piedralaves \u00c1vila 05440",
    "addr:housenumber":"83",
    "addr:postcode":"05440",
    "addr:street":"Ctra. Alcorcon-Plasencia",
    "iso:country":"ES",
    "sg:address":"Ctra. Alcorcon-plasencia, 83",
    "sg:city":"Piedralaves",
    "sg:orig_category":"Ebanister\u00cda",
    "sg:phone":"+34 918 66 62 86",
    "sg:postcode":"05440",
    "sg:province":"\u00c1vila",
    "sg:website":"www.arraigo.net",
    "wof:name":"Arraigo S.l.",
    "wof:placetype":"venue"
},
  "geometry": {"coordinates":[-4.7070617676,40.3153572083],"type":"Point"}
}