{
  "type": "Feature",
  "properties": {
    "iso:country":"ES",
    "sg:address":"Carr Santa Clara, 41",
    "sg:city":"Girona",
    "sg:orig_category":"Zapatos (al Por Menor)",
    "sg:phone":"+34 972 21 48 48",
    "sg:postcode":"17001",
    "sg:province":"Girona",
    "wof:name":"Cal\u00c7ats Freixas S.l.",
    "wof:placetype":"venue"
},
  "geometry": {"coordinates":[2.8232839108,41.9846000671],"type":"Point"}
}