{
  "type": "Feature",
  "properties": {
    "addr:full":"Calle de Emilio Ortu\u00d1o, 13 Madrid Madrid 28038",
    "addr:housenumber":"13",
    "addr:postcode":"madrid;28038",
    "addr:street":"Calle De Emilio Ortun\u0303O",
    "iso:country":"ES",
    "sg:address":"Calle de Emilio Ortu\u00d1o, 13",
    "sg:city":"Madrid",
    "sg:orig_category":"Internados & Ense\u00d1anza Privada",
    "sg:phone":"+34 914 33 11 50",
    "sg:postcode":"28038",
    "sg:province":"Madrid",
    "wof:name":"Colegio Divina Pastora",
    "wof:placetype":"venue"
},
  "geometry": {"coordinates":[-3.6663489342,40.3989715576],"type":"Point"}
}