{
  "type": "Feature",
  "properties": {
    "addr:full":"Calle de Benedictinas De San Jose, 23 Burgos Burgos 09003",
    "addr:housenumber":"23",
    "addr:postcode":"09003",
    "addr:street":"Calle De Benedictinas De San",
    "iso:country":"ES",
    "sg:address":"Calle de Benedictinas De San Jose, 23",
    "sg:city":"Burgos",
    "sg:orig_category":"Arquitectos",
    "sg:phone":"+34 947 27 86 57",
    "sg:postcode":"09003",
    "sg:province":"Burgos",
    "wof:name":"Adrian Dossio Oscar",
    "wof:placetype":"venue"
},
  "geometry": {"coordinates":[-3.7134981155,42.3411178589],"type":"Point"}
}