{
  "type": "Feature",
  "properties": {
    "addr:full":"Avda Del Mediterrani, 34 Onda Castell\u00f3n 12200",
    "addr:housenumber":"34",
    "addr:postcode":"12200",
    "addr:street":"Avda Del Mediterrani;Castello\u0301N",
    "iso:country":"ES",
    "sg:address":"Avda Del Mediterrani, 34",
    "sg:city":"Onda",
    "sg:orig_category":"Distribuci\u00d3n De Petr\u00d3leo Y Derivados",
    "sg:phone":"+34 964 60 00 15",
    "sg:postcode":"12200",
    "sg:province":"Castell\u00f3n",
    "sg:website":"www.cepsa.es",
    "wof:name":"Cedipsa Compa\u00d1ia Espa\u00d1ola Distribuidora De Petroleos S.a.",
    "wof:placetype":"venue"
},
  "geometry": {"coordinates":[-0.2475789934,39.9642982483],"type":"Point"}
}