{
  "type": "Feature",
  "properties": {
    "iso:country":"ES",
    "sg:address":"Calle de Guadalajara, 1",
    "sg:city":"Chozas Canales",
    "sg:orig_category":"Art\u00cdculos De Decoraci\u00d3n",
    "sg:phone":"+34 918 17 68 86",
    "sg:postcode":"45960",
    "sg:province":"Toledo",
    "wof:name":"Siscar Sanchez Isabel Rosario",
    "wof:placetype":"venue"
},
  "geometry": {"coordinates":[-4.0433659554,40.0983924866],"type":"Point"}
}