{
  "type": "Feature",
  "properties": {
    "addr:full":"Poli Industrial San Valero, S/n Cartuja Baja Zaragoza 50720",
    "addr:housenumber":"s / n",
    "addr:postcode":"50720",
    "addr:street":"San Valero;Baja",
    "iso:country":"ES",
    "sg:address":"Poli Industrial San Valero, S/n",
    "sg:city":"Cartuja Baja",
    "sg:orig_category":"Fabricaci\u00d3n De Taburetes, Sillas Y Sillones",
    "sg:phone":"+34 976 50 09 90",
    "sg:postcode":"50720",
    "sg:province":"Zaragoza",
    "wof:name":"Silleria Aragonesa Javier Yuste S.l.",
    "wof:placetype":"venue"
},
  "geometry": {"coordinates":[-0.8236089945,41.602935791],"type":"Point"}
}