{
  "type": "Feature",
  "properties": {
    "iso:country":"ES",
    "sg:address":"Avda Iparragirre, 35",
    "sg:city":"Santurtzi",
    "sg:orig_category":"Cristaler\u00cdas",
    "sg:phone":"+34 944 83 66 55",
    "sg:postcode":"48980",
    "sg:province":"Vizcaya",
    "wof:name":"Fernando Lacoma San Martin",
    "wof:placetype":"venue"
},
  "geometry": {"coordinates":[-3.0374760628,43.332950592],"type":"Point"}
}