{
  "type": "Feature",
  "properties": {
    "iso:country":"ES",
    "sg:address":"Calle de Puentezuelas, 28",
    "sg:city":"Granada",
    "sg:orig_category":"Art\u00cdculos De Decoraci\u00d3n",
    "sg:phone":"+34 958 25 57 02",
    "sg:postcode":"18002",
    "sg:province":"Granada",
    "wof:name":"Huertas Rueda Encarnacion",
    "wof:placetype":"venue"
},
  "geometry": {"coordinates":[-3.6023108959,37.174331665],"type":"Point"}
}