{
  "type": "Feature",
  "properties": {
    "iso:country":"ES",
    "sg:address":"Avda Niza, 50",
    "sg:city":"Madrid",
    "sg:orig_category":"Bazares, Art\u00cdculos De Limpieza Y De Cocina (al Por Menor)",
    "sg:phone":"+34 913 24 23 44",
    "sg:postcode":"28022",
    "sg:province":"Madrid",
    "wof:name":"Zhang  Zhongbiao",
    "wof:placetype":"venue"
},
  "geometry": {"coordinates":[-3.6079986095,40.4345092773],"type":"Point"}
}