{
  "type": "Feature",
  "properties": {
    "iso:country":"ES",
    "sg:address":"Confianza (p I Pizarra), S/n",
    "sg:city":"Pizarra",
    "sg:orig_category":"Promotores Constructores",
    "sg:phone":"+34 952 48 41 53",
    "sg:postcode":"29560",
    "sg:province":"M\u00e1laga",
    "wof:name":"Construcciones Pachema 2002 Sll",
    "wof:placetype":"venue"
},
  "geometry": {"coordinates":[-4.707526207,36.7672538757],"type":"Point"}
}