{
  "type": "Feature",
  "properties": {
    "iso:country":"ES",
    "sg:address":"Calle de Leoncio Rodriguez, 1",
    "sg:city":"Santa Ursula",
    "sg:orig_category":"Bazares, Art\u00cdculos De Limpieza Y De Cocina (al Por Menor)",
    "sg:phone":"+34 922 30 14 15",
    "sg:postcode":"38390",
    "sg:province":"Santa Cruz De Tenerife",
    "wof:name":"Mendoza Aguilar Florencio",
    "wof:placetype":"venue"
},
  "geometry": {"coordinates":[-16.488904953,28.4257984161],"type":"Point"}
}