{
  "type": "Feature",
  "properties": {
    "addr:full":"Calle de Leganitos, 27 Madrid Madrid 28013",
    "addr:housenumber":"27",
    "addr:postcode":"madrid;28013",
    "addr:street":"Calle De Leganitos",
    "iso:country":"ES",
    "sg:address":"Calle de Leganitos, 27",
    "sg:city":"Madrid",
    "sg:orig_category":"Inform\u00c1tica (estudios, Servicios, Asesor\u00cda, Formaci\u00d3n)",
    "sg:phone":"+34 915 47 11 83",
    "sg:postcode":"28013",
    "sg:province":"Madrid",
    "sg:website":"www.financialtech-mag.com",
    "wof:name":"Goldfryd  Oscar Enrique",
    "wof:placetype":"venue"
},
  "geometry": {"coordinates":[-3.710408926,40.421787262],"type":"Point"}
}