{
  "type": "Feature",
  "properties": {
    "addr:full":"Carrer de Merce Amell, 6 Vallpineda Barcelona 08810",
    "addr:housenumber":"6",
    "addr:postcode":"08810",
    "addr:street":"Carrer De Merce Amell;Barcelona",
    "iso:country":"ES",
    "sg:address":"Carrer de Merce Amell, 6",
    "sg:city":"Vallpineda",
    "sg:orig_category":"Aeropuertos Y Servicios Aeroportuarios",
    "sg:phone":"+34 938 94 14 95",
    "sg:postcode":"08810",
    "sg:province":"Barcelona",
    "wof:name":"Wolf, Compa\u00f1ia De Servicios Y Automocion S.l.",
    "wof:placetype":"venue"
},
  "geometry": {"coordinates":[1.7909742594,41.2461242676],"type":"Point"}
}