{
  "type": "Feature",
  "properties": {
    "iso:country":"ES",
    "sg:address":"Carrer de Sant Antoni Maria Claret, 26",
    "sg:city":"Manresa",
    "sg:orig_category":"M\u00c9dicos: An\u00c1lisis Cl\u00cdnicos",
    "sg:phone":"+34 938 73 33 00",
    "sg:postcode":"08243",
    "sg:province":"Barcelona",
    "wof:name":"Laboratorio De Analisis Clinicos Dr. Badal S. A.",
    "wof:placetype":"venue"
},
  "geometry": {"coordinates":[1.8334519863,41.7312164307],"type":"Point"}
}