{
  "type": "Feature",
  "properties": {
    "iso:country":"ES",
    "sg:address":"Calle de San Roque, 5",
    "sg:city":"Salas De Los Infantes",
    "sg:orig_category":"Bancos",
    "sg:phone":"+34 947 38 00 00",
    "sg:postcode":"09600",
    "sg:province":"Burgos",
    "wof:name":"Banco De Castilla",
    "wof:placetype":"venue"
},
  "geometry": {"coordinates":[-3.2898170948,42.0208816528],"type":"Point"}
}