{
  "type": "Feature",
  "properties": {
    "iso:country":"ES",
    "sg:address":"Ctra. Pedro Mu\u00f1oz, 8",
    "sg:city":"Mota Cuervo",
    "sg:orig_category":"Fabricaci\u00d3n De Enlosados, Soler\u00cdas",
    "sg:phone":"+34 967 18 05 34",
    "sg:postcode":"16630",
    "sg:province":"Cuenca",
    "wof:name":"Hermanos Lopez S. A.",
    "wof:placetype":"venue"
},
  "geometry": {"coordinates":[-2.8739209175,39.5004196167],"type":"Point"}
}