{
  "type": "Feature",
  "properties": {
    "iso:country":"ES",
    "sg:address":"Touro, 62",
    "sg:city":"Touro",
    "sg:orig_category":"Frutas Y Legumbres Frescas (al Por Mayor)",
    "sg:phone":"+34 981 87 16 04",
    "sg:postcode":"15960",
    "sg:province":"La Coru\u00f1a",
    "wof:name":"Parada Fernandez Jose Antonio",
    "wof:placetype":"venue"
},
  "geometry": {"coordinates":[-8.9908485413,42.5553665161],"type":"Point"}
}