{
  "type": "Feature",
  "properties": {
    "iso:country":"ES",
    "sg:address":"Calle de Canal, 56",
    "sg:city":"Sevilla",
    "sg:orig_category":"Lavado, Limpieza De Veh\u00cdculos",
    "sg:phone":"+34 954 92 08 42",
    "sg:postcode":"41006",
    "sg:province":"Sevilla",
    "wof:name":"Engrase Y Lavado Cabezuelo S.l.",
    "wof:placetype":"venue"
},
  "geometry": {"coordinates":[-5.9615898132,37.3759040833],"type":"Point"}
}