{
  "type": "Feature",
  "properties": {
    "iso:country":"ES",
    "sg:address":"Calle de San Sebastian, 20",
    "sg:city":"Marmolejo",
    "sg:orig_category":"Productos Qu\u00cdmicos (fabricaci\u00d3n, Al Por Mayor)",
    "sg:phone":"+34 953 51 78 64",
    "sg:postcode":"23770",
    "sg:province":"Ja\u00e9n",
    "wof:name":"Agroquimicos Santiago Flores S.l.",
    "wof:placetype":"venue"
},
  "geometry": {"coordinates":[-4.1666593552,38.0438613892],"type":"Point"}
}