{
  "type": "Feature",
  "properties": {
    "iso:country":"ES",
    "sg:address":"Mayor, 15",
    "sg:city":"Ortells",
    "sg:orig_category":"Restaurantes",
    "sg:phone":"+34 964 17 12 82",
    "sg:postcode":"12311",
    "sg:province":"Castell\u00f3n",
    "wof:name":"Domenech Marti Ramon",
    "wof:placetype":"venue"
},
  "geometry": {"coordinates":[-0.166159004,40.7288360596],"type":"Point"}
}