{
  "type": "Feature",
  "properties": {
    "addr:full":"Calle de Gutenberg, 26 Madrid Madrid 28014",
    "addr:housenumber":"26",
    "addr:postcode":"madrid;28014",
    "addr:street":"Calle De Gutenberg",
    "iso:country":"ES",
    "sg:address":"Calle de Gutenberg, 26",
    "sg:city":"Madrid",
    "sg:orig_category":"Imprenta",
    "sg:phone":"+34 915 51 20 20",
    "sg:postcode":"28014",
    "sg:province":"Madrid",
    "wof:name":"Rubio Vizcaino Manuel",
    "wof:placetype":"venue"
},
  "geometry": {"coordinates":[-3.680136919,40.4068717957],"type":"Point"}
}