{
  "type": "Feature",
  "properties": {
    "addr:full":"Avda Arcos De La Frontera, 3 Jerez De La Frontera C\u00e1diz 11405",
    "addr:housenumber":"3",
    "addr:postcode":"11405",
    "addr:street":"Avda Arcos De La Frontera",
    "iso:country":"ES",
    "sg:address":"Avda Arcos De La Frontera, 3",
    "sg:city":"Jerez De La Frontera",
    "sg:orig_category":"Caf\u00c9s, Bares, Cervecer\u00cdas",
    "sg:phone":"+34 956 32 53 88",
    "sg:postcode":"11405",
    "sg:province":"C\u00e1diz",
    "wof:name":"Cano Diaz Angeles",
    "wof:placetype":"venue"
},
  "geometry": {"coordinates":[-6.0988402367,36.6960334778],"type":"Point"}
}