{
  "type": "Feature",
  "properties": {
    "addr:full":"Carneceria, S/n Medinaceli Soria 42240",
    "addr:postcode":"42240",
    "addr:street":"Carneceria S / N",
    "iso:country":"ES",
    "sg:address":"Carneceria, S/n",
    "sg:city":"Medinaceli",
    "sg:orig_category":"Reposter\u00cdas",
    "sg:phone":"+34 975 32 61 03",
    "sg:postcode":"42240",
    "sg:province":"Soria",
    "wof:name":"Panaderia De Diego C.b.",
    "wof:placetype":"venue"
},
  "geometry": {"coordinates":[-2.4339120388,41.170627594],"type":"Point"}
}