{
  "type": "Feature",
  "properties": {
    "iso:country":"ES",
    "sg:address":"Calle de Fueros De Aragon, 3",
    "sg:city":"Zaragoza",
    "sg:orig_category":"Dibujos Animados",
    "sg:phone":"+34 976 56 02 34",
    "sg:postcode":"50005",
    "sg:province":"Zaragoza",
    "wof:name":"Nostromo Comics S.l.l.",
    "wof:placetype":"venue"
},
  "geometry": {"coordinates":[-0.8940370083,41.6461906433],"type":"Point"}
}