{
  "type": "Feature",
  "properties": {
    "addr:full":"Av Paral.lel, 114 Barcelona Barcelona 08015",
    "addr:housenumber":"114",
    "addr:postcode":"08015",
    "addr:street":"Av Paral.Lel",
    "iso:country":"ES",
    "sg:address":"Av Paral.lel, 114",
    "sg:city":"Barcelona",
    "sg:orig_category":"Ense\u00d1anza Secundaria: Colegios Y Escuelas Privadas",
    "sg:phone":"+34 933 29 12 91",
    "sg:postcode":"08015",
    "sg:province":"Barcelona",
    "wof:name":"Fundacion Ies Barcelona",
    "wof:placetype":"venue"
},
  "geometry": {"coordinates":[2.1640200615,41.3749694824],"type":"Point"}
}