{
  "type": "Feature",
  "properties": {
    "addr:full":"Carr Canonge Brugulat, 16 Lleida Lleida 25003",
    "addr:housenumber":"16",
    "addr:postcode":"25003",
    "addr:street":"Carr Canonge Brugulat",
    "iso:country":"ES",
    "sg:address":"Carr Canonge Brugulat, 16",
    "sg:city":"Lleida",
    "sg:orig_category":"Clases De M\u00dasica Y Canto",
    "sg:phone":"+34 973 28 09 07",
    "sg:postcode":"25003",
    "sg:province":"Lleida",
    "sg:website":"www.lleida.net/creativity",
    "wof:name":"Musica Pons-rosello S.c.p.",
    "wof:placetype":"venue"
},
  "geometry": {"coordinates":[0.6182379723,41.6135177612],"type":"Point"}
}