{
  "type": "Feature",
  "properties": {
    "addr:full":"Carrer de Enric Granados, 15 S. Cugat Valles Barcelona 08172",
    "addr:housenumber":"15",
    "addr:postcode":"08172",
    "addr:street":"Carrer De Enric Granados;S. Cugat Valles Barcelona",
    "iso:country":"ES",
    "sg:address":"Carrer de Enric Granados, 15",
    "sg:city":"S. Cugat Valles",
    "sg:orig_category":"Contenedores (mercanc\u00cdas)",
    "sg:phone":"+34 936 74 73 18",
    "sg:postcode":"08172",
    "sg:province":"Barcelona",
    "wof:name":"Ruiz Mila Transports I Logistics S.l.",
    "wof:placetype":"venue"
},
  "geometry": {"coordinates":[2.0816690922,41.4728889465],"type":"Point"}
}