{
  "type": "Feature",
  "properties": {
    "iso:country":"ES",
    "sg:address":"Calle de Rosas, 8",
    "sg:city":"Fuengirola",
    "sg:orig_category":"Guarder\u00cdas",
    "sg:phone":"+34 952 46 98 76",
    "sg:postcode":"29640",
    "sg:province":"M\u00e1laga",
    "wof:name":"Moreno Casas Maria Teresa",
    "wof:placetype":"venue"
},
  "geometry": {"coordinates":[-4.6239790916,36.5414886475],"type":"Point"}
}