{
  "type": "Feature",
  "properties": {
    "addr:full":"Vial Industrial, 4 Ihurre Guip\u00f9zcoa 20212",
    "addr:postcode":"20212",
    "addr:street":"Guipu\u0300Zcoa",
    "iso:country":"ES",
    "sg:address":"Vial Industrial, 4",
    "sg:city":"Ihurre",
    "sg:orig_category":"Suministros Para Carrocer\u00cdas",
    "sg:phone":"+34 943 88 05 65",
    "sg:postcode":"20212",
    "sg:province":"Guip\u00f9zcoa",
    "wof:name":"Garage Moderno Pablo Irizar S.l.",
    "wof:placetype":"venue"
},
  "geometry": {"coordinates":[-2.2013700008,43.0282554626],"type":"Point"}
}