{
  "type": "Feature",
  "properties": {
    "iso:country":"ES",
    "sg:address":"Avda Touroperador Kuoni, 17",
    "sg:city":"Campo Internacional",
    "sg:orig_category":"Charcuter\u00cdas (al Por Mayor)",
    "sg:phone":"+34 928 76 89 24",
    "sg:postcode":"35100",
    "sg:province":"Las Palmas",
    "wof:name":"Embutidos Arinaga S.l",
    "wof:placetype":"venue"
},
  "geometry": {"coordinates":[-15.4397096634,28.1302204132],"type":"Point"}
}