{
  "type": "Feature",
  "properties": {
    "iso:country":"ES",
    "sg:address":"Carr Font De Sant Josep, 6",
    "sg:city":"Benicasim",
    "sg:orig_category":"Negocio De Materiales De Construcci\u00d3n",
    "sg:phone":"+34 964 30 10 86",
    "sg:postcode":"12560",
    "sg:province":"Castell\u00f3n",
    "wof:name":"Materiales Tarrega S.l.",
    "wof:placetype":"venue"
},
  "geometry": {"coordinates":[0.0457400009,40.0510292053],"type":"Point"}
}