{
  "type": "Feature",
  "properties": {
    "iso:country":"ES",
    "sg:address":"Avda. Mar, 18",
    "sg:city":"Puente Mayorga",
    "sg:orig_category":"Alquiler De V\u00cddeo",
    "sg:phone":"+34 956 69 94 00",
    "sg:postcode":"11313",
    "sg:province":"C\u00e1diz",
    "wof:name":"Gomez Ruiz Maria Esther",
    "wof:placetype":"venue"
},
  "geometry": {"coordinates":[-5.3862771988,36.180644989],"type":"Point"}
}