{
  "type": "Feature",
  "properties": {
    "iso:country":"ES",
    "sg:address":"Calle de Leopoldo Alas Clarin, 41",
    "sg:city":"Madrid",
    "sg:orig_category":"Frutas Y Legumbres Secas (al Por Mayor)",
    "sg:phone":"+34 913 73 30 93",
    "sg:postcode":"28035",
    "sg:province":"Madrid",
    "wof:name":"Pena Mui\u00f1os Oscar",
    "wof:placetype":"venue"
},
  "geometry": {"coordinates":[-3.7331926823,40.4811210632],"type":"Point"}
}