{
  "type": "Feature",
  "properties": {
    "iso:country":"ES",
    "sg:address":"Pase Castellana, 95",
    "sg:city":"Madrid",
    "sg:orig_category":"Sociedades, Compa\u00d1\u00cdas Aseguradoras",
    "sg:phone":"+34 913 10 40 96",
    "sg:postcode":"28046",
    "sg:province":"Madrid",
    "sg:website":"www.cofaceiberica.com",
    "wof:name":"Coface Iberica",
    "wof:placetype":"venue"
},
  "geometry": {"coordinates":[-3.6913490295,40.4513130188],"type":"Point"}
}