{
  "type": "Feature",
  "properties": {
    "addr:full":"Ctra Coru\u00f1a-santiago, Km. 0017,0 Carral A Coru\u00f1a 15175",
    "addr:postcode":"15175",
    "addr:street":"Ctra Corun\u0303A-Santiago Km. 0017,0;Corun\u0303A",
    "iso:country":"ES",
    "sg:address":"Ctra Coru\u00f1a-santiago, Km. 0017,0",
    "sg:city":"Carral",
    "sg:orig_category":"Mec\u00c1nico Del Autom\u00d3vil",
    "sg:phone":"+34 981 67 00 81",
    "sg:postcode":"15175",
    "sg:province":"A Coru\u00f1a",
    "wof:name":"Talleres Luis Trigo S.l.",
    "wof:placetype":"venue"
},
  "geometry": {"coordinates":[-8.3558893204,43.2278442383],"type":"Point"}
}