{
  "type": "Feature",
  "properties": {
    "addr:full":"Ctra Pe\u00d1aranda, 20 Alba Tormes Salamanca 37800",
    "addr:housenumber":"20",
    "addr:postcode":"37800",
    "addr:street":"Ctra Pen\u0303Aranda",
    "iso:country":"ES",
    "sg:address":"Ctra Pe\u00d1aranda, 20",
    "sg:city":"Alba Tormes",
    "sg:orig_category":"Electrodom\u00c9sticos (al Por Menor)",
    "sg:phone":"+34 923 37 02 35",
    "sg:postcode":"37800",
    "sg:province":"Salamanca",
    "wof:name":"Rollan Malmierca Juan",
    "wof:placetype":"venue"
},
  "geometry": {"coordinates":[-5.5071167946,40.8273429871],"type":"Point"}
}