{
  "type": "Feature",
  "properties": {
    "addr:full":"Calle de Briviesca, 1 Almeria Almer\u00eda 04007",
    "addr:housenumber":"1",
    "addr:postcode":"04007",
    "addr:street":"Calle De Briviesca",
    "iso:country":"ES",
    "sg:address":"Calle de Briviesca, 1",
    "sg:city":"Almeria",
    "sg:orig_category":"Internados & Ense\u00d1anza Privada",
    "sg:phone":"+34 950 24 42 58",
    "sg:postcode":"04007",
    "sg:province":"Almer\u00eda",
    "wof:name":"Colegio Nuestra Se\u00f1ora De Fatima",
    "wof:placetype":"venue"
},
  "geometry": {"coordinates":[-2.4502470493,36.8311576843],"type":"Point"}
}