{
  "type": "Feature",
  "properties": {
    "addr:full":"Calle de Morera, 6 Coria Rio Sevilla 41100",
    "addr:housenumber":"6",
    "addr:postcode":"41100",
    "addr:street":"Calle De Morera;Rio Sevilla",
    "iso:country":"ES",
    "sg:address":"Calle de Morera, 6",
    "sg:city":"Coria Rio",
    "sg:orig_category":"Pintura Y Barniz (al Por Menor)",
    "sg:phone":"+34 954 77 59 69",
    "sg:postcode":"41100",
    "sg:province":"Sevilla",
    "wof:name":"Pinturas Caura S.l.",
    "wof:placetype":"venue"
},
  "geometry": {"coordinates":[-6.0569958687,37.2929344177],"type":"Point"}
}