{
  "type": "Feature",
  "properties": {
    "iso:country":"ES",
    "sg:address":"S. De Madariaga, S/n",
    "sg:city":"Albox",
    "sg:orig_category":"Ingeniero",
    "sg:phone":"+34 950 12 03 42",
    "sg:postcode":"04800",
    "sg:province":"Almer\u00eda",
    "wof:name":"Del Aguila Lopez Jose",
    "wof:placetype":"venue"
},
  "geometry": {"coordinates":[-2.1466989517,37.3857002258],"type":"Point"}
}