{
  "type": "Feature",
  "properties": {
    "addr:full":"Calle de Asta, 8 Jerez De La Frontera C\u00e1diz 11404",
    "addr:housenumber":"8",
    "addr:postcode":"11404",
    "addr:street":"Calle De Asta",
    "iso:country":"ES",
    "sg:address":"Calle de Asta, 8",
    "sg:city":"Jerez De La Frontera",
    "sg:orig_category":"Mec\u00c1nico Del Autom\u00d3vil",
    "sg:phone":"+34 956 18 59 74",
    "sg:postcode":"11404",
    "sg:province":"C\u00e1diz",
    "wof:name":"Gonzalez Rendon Luis Gonzaga",
    "wof:placetype":"venue"
},
  "geometry": {"coordinates":[-6.1435232162,36.6904602051],"type":"Point"}
}