{
  "type": "Feature",
  "properties": {
    "addr:full":"Calle de Autonomia, 15 Donostia-san Sebastian Guip\u00f9zcoa 20006",
    "addr:housenumber":"15",
    "addr:postcode":"20006",
    "addr:street":"Calle De Autonomia",
    "iso:country":"ES",
    "sg:address":"Calle de Autonomia, 15",
    "sg:city":"Donostia-san Sebastian",
    "sg:orig_category":"Agencias De Viajes",
    "sg:phone":"+34 943 44 41 86",
    "sg:postcode":"20006",
    "sg:province":"Guip\u00f9zcoa",
    "wof:name":"Viajes Gantour, S.a.",
    "wof:placetype":"venue"
},
  "geometry": {"coordinates":[-1.9818789959,43.3120422363],"type":"Point"}
}