{
  "type": "Feature",
  "properties": {
    "addr:full":"Calle de San Antonio, 7 Cedillo Condado Toledo 45214",
    "addr:housenumber":"7",
    "addr:postcode":"45214",
    "addr:street":"Calle De San Antonio",
    "iso:country":"ES",
    "sg:address":"Calle de San Antonio, 7",
    "sg:city":"Cedillo Condado",
    "sg:orig_category":"Muebles",
    "sg:phone":"+34 925 50 88 46",
    "sg:postcode":"45214",
    "sg:province":"Toledo",
    "wof:name":"Inox Talavera S.l.",
    "wof:placetype":"venue"
},
  "geometry": {"coordinates":[-3.9261898994,40.1136817932],"type":"Point"}
}