{
  "type": "Feature",
  "properties": {
    "addr:full":"Calle de Ayala, 10 Madrid Madrid 28001",
    "addr:housenumber":"10",
    "addr:postcode":"madrid;28001",
    "addr:street":"Calle De Ayala",
    "iso:country":"ES",
    "sg:address":"Calle de Ayala, 10",
    "sg:city":"Madrid",
    "sg:orig_category":"Ingenier\u00cda, Centros De Estudios (diversos)",
    "sg:phone":"+34 914 36 09 40",
    "sg:postcode":"28001",
    "sg:province":"Madrid",
    "wof:name":"Cavosa Obras Y Proyectos Sa.",
    "wof:placetype":"venue"
},
  "geometry": {"coordinates":[-3.6885175705,40.427947998],"type":"Point"}
}