{
  "type": "Feature",
  "properties": {
    "iso:country":"ES",
    "sg:address":"Calle de Jose Miguel Guridi, 3",
    "sg:city":"Madrid",
    "sg:orig_category":"Ingeniero",
    "sg:phone":"+34 913 00 42 37",
    "sg:postcode":"28043",
    "sg:province":"Madrid",
    "wof:name":"Anton Jornet Jose Maria",
    "wof:placetype":"venue"
},
  "geometry": {"coordinates":[-3.6349737644,40.4602737427],"type":"Point"}
}