{
  "type": "Feature",
  "properties": {
    "addr:full":"Calle de Rafael Lucenqui, 5 Badajoz Badajoz 06004",
    "addr:housenumber":"5",
    "addr:postcode":"06004",
    "addr:street":"Calle De Rafael Lucenqui",
    "iso:country":"ES",
    "sg:address":"Calle de Rafael Lucenqui, 5",
    "sg:city":"Badajoz",
    "sg:orig_category":"M\u00c9dicos: Otorrinolaringolog\u00cda",
    "sg:phone":"+34 924 23 59 85",
    "sg:postcode":"06004",
    "sg:province":"Badajoz",
    "wof:name":"Trinidad Ramos German Tomas",
    "wof:placetype":"venue"
},
  "geometry": {"coordinates":[-6.9766378403,38.8705825806],"type":"Point"}
}