{
  "type": "Feature",
  "properties": {
    "addr:full":"Poligono Industrial El Berrocal, Km. 0118,0 Valladolid Valladolid 47009",
    "addr:postcode":"47009",
    "addr:street":"0118,0",
    "iso:country":"ES",
    "sg:address":"Poligono Industrial El Berrocal, Km. 0118,0",
    "sg:city":"Valladolid",
    "sg:orig_category":"Montaje (empresas De)",
    "sg:phone":"+34 983 35 41 22",
    "sg:postcode":"47009",
    "sg:province":"Valladolid",
    "wof:name":"Montajes Vallejo Cim S.a.",
    "wof:placetype":"venue"
},
  "geometry": {"coordinates":[-4.7070288658,41.6909103394],"type":"Point"}
}