{
  "type": "Feature",
  "properties": {
    "iso:country":"ES",
    "sg:address":"Calle de Secunda Romana, 46",
    "sg:city":"Cordoba",
    "sg:orig_category":"Construcci\u00d3n De Edificios Residenciales Y No Residenciales",
    "sg:phone":"+34 957 29 15 29",
    "sg:postcode":"14009",
    "sg:province":"C\u00f3rdoba",
    "wof:name":"Rodriguez Luque Antonio",
    "wof:placetype":"venue"
},
  "geometry": {"coordinates":[-4.7720341682,37.8695907593],"type":"Point"}
}