{
  "type": "Feature",
  "properties": {
    "iso:country":"ES",
    "sg:address":"Otalora Lizentziaduna Kalea, 9",
    "sg:city":"Arrasate",
    "sg:orig_category":"Peluqueros: De Se\u00d1oras",
    "sg:phone":"+34 943 79 18 14",
    "sg:postcode":"20500",
    "sg:province":"Guip\u00f9zcoa",
    "wof:name":"Larra\u00f1aga Ceciaga Maria Pilar",
    "wof:placetype":"venue"
},
  "geometry": {"coordinates":[-2.487128973,43.066318512],"type":"Point"}
}