{
  "type": "Feature",
  "properties": {
    "addr:full":"Calle de Albacete, 36 Castellon Castell\u00f3n 12004",
    "addr:housenumber":"36",
    "addr:postcode":"12004",
    "addr:street":"Calle De Albacete",
    "iso:country":"ES",
    "sg:address":"Calle de Albacete, 36",
    "sg:city":"Castellon",
    "sg:orig_category":"Cajas De Ahorro",
    "sg:phone":"+34 964 20 90 96",
    "sg:postcode":"12004",
    "sg:province":"Castell\u00f3n",
    "wof:name":"Caja De Ahorros De Valencia Castellon Y Alicante",
    "wof:placetype":"venue"
},
  "geometry": {"coordinates":[-0.0479195006,40.0005607605],"type":"Point"}
}