{
  "type": "Feature",
  "properties": {
    "addr:full":"Calle de Santiago Ramon Y Cajal, 15 Algaba Sevilla 41980",
    "addr:housenumber":"15",
    "addr:postcode":"41980",
    "addr:street":"Calle De Santiago Ramon Y Cajal",
    "iso:country":"ES",
    "sg:address":"Calle de Santiago Ramon Y Cajal, 15",
    "sg:city":"Algaba",
    "sg:orig_category":"Reposter\u00cdas",
    "sg:phone":"+34 955 78 84 25",
    "sg:postcode":"41980",
    "sg:province":"Sevilla",
    "wof:name":"Marquez Flores Manuel",
    "wof:placetype":"venue"
},
  "geometry": {"coordinates":[-6.0144309998,37.4621658325],"type":"Point"}
}