{
  "type": "Feature",
  "properties": {
    "addr:full":"Calle de Castilla La Mancha, 17 Carranque Toledo 45216",
    "addr:housenumber":"17",
    "addr:postcode":"45216",
    "addr:street":"Calle De Castilla La Mancha",
    "iso:country":"ES",
    "sg:address":"Calle de Castilla La Mancha, 17",
    "sg:city":"Carranque",
    "sg:orig_category":"Cajas Y Embalajes De Madera",
    "sg:phone":"+34 925 52 99 12",
    "sg:postcode":"45216",
    "sg:province":"Toledo",
    "sg:website":"www.estucheriatabaglo.com",
    "wof:name":"Estucheria Tabaglo S.l.",
    "wof:placetype":"venue"
},
  "geometry": {"coordinates":[-3.8974189758,40.1712684631],"type":"Point"}
}