{
  "type": "Feature",
  "properties": {
    "addr:full":"Calle de Granja San Ildefonso, 5 Cadiz C\u00e1diz 11007",
    "addr:housenumber":"5",
    "addr:postcode":"11007",
    "addr:street":"Calle De Granja San Ildefonso",
    "iso:country":"ES",
    "sg:address":"Calle de Granja San Ildefonso, 5",
    "sg:city":"Cadiz",
    "sg:orig_category":"Peluqueros: De Se\u00d1oras",
    "sg:phone":"+34 956 26 40 14",
    "sg:postcode":"11007",
    "sg:province":"C\u00e1diz",
    "wof:name":"Aragon Chilia Francisco Jose",
    "wof:placetype":"venue"
},
  "geometry": {"coordinates":[-6.2844204903,36.5218048096],"type":"Point"}
}