{
  "type": "Feature",
  "properties": {
    "iso:country":"ES",
    "sg:address":"Carrer de Poeta Cabanyes, 67",
    "sg:city":"Barcelona",
    "sg:orig_category":"Farmacias",
    "sg:phone":"+34 934 41 18 12",
    "sg:postcode":"08004",
    "sg:province":"Barcelona",
    "wof:name":"Aran Simon Rosa Maria",
    "wof:placetype":"venue"
},
  "geometry": {"coordinates":[2.1646387577,41.3725852966],"type":"Point"}
}