{
  "type": "Feature",
  "properties": {
    "iso:country":"ES",
    "sg:address":"Calle de Granada (de), 3",
    "sg:city":"Humanes De Madrid",
    "sg:orig_category":"Papel (al Por Mayor)",
    "sg:phone":"+34 916 97 10 30",
    "sg:postcode":"28970",
    "sg:province":"Madrid",
    "wof:name":"Manipulados Siglo Xxi S.l.",
    "wof:placetype":"venue"
},
  "geometry": {"coordinates":[-3.8228979111,40.2761726379],"type":"Point"}
}