{
  "type": "Feature",
  "properties": {
    "iso:country":"ES",
    "sg:address":"Calle de Bureba, 26",
    "sg:city":"Leganes",
    "sg:orig_category":"Centros M\u00c9dicos Y Sociales, Dispensarios",
    "sg:phone":"+34 916 80 43 33",
    "sg:postcode":"28915",
    "sg:province":"Madrid",
    "wof:name":"Intermedic Centros Medicos S.l.",
    "wof:placetype":"venue"
},
  "geometry": {"coordinates":[-3.7502839565,40.3315544128],"type":"Point"}
}