{
  "type": "Feature",
  "properties": {
    "addr:full":"Calle de Navarro Rodrigo, 9 Almeria Almer\u00eda 04001",
    "addr:housenumber":"9",
    "addr:postcode":"04001",
    "addr:street":"Calle De Navarro Rodrigo",
    "iso:country":"ES",
    "sg:address":"Calle de Navarro Rodrigo, 9",
    "sg:city":"Almeria",
    "sg:orig_category":"Promotores Constructores",
    "sg:phone":"+34 950 23 14 88",
    "sg:postcode":"04001",
    "sg:province":"Almer\u00eda",
    "wof:name":"Protecho S.l.",
    "wof:placetype":"venue"
},
  "geometry": {"coordinates":[-2.4627940655,36.8397674561],"type":"Point"}
}