{
  "type": "Feature",
  "properties": {
    "iso:country":"ES",
    "sg:address":"Carrer de Pau Sans, 24",
    "sg:city":"Hospitalet Llobregat",
    "sg:orig_category":"Construcciones Met\u00c1licas",
    "sg:phone":"+34 933 37 72 55",
    "sg:postcode":"08901",
    "sg:province":"Barcelona",
    "wof:name":"Talleres Campellas S.l.",
    "wof:placetype":"venue"
},
  "geometry": {"coordinates":[2.1118218899,41.3624534607],"type":"Point"}
}