{
  "type": "Feature",
  "properties": {
    "iso:country":"ES",
    "sg:address":"Carr Del Dos De Maig, 193",
    "sg:city":"Ontinyent",
    "sg:orig_category":"Materias Pl\u00c1sticas: Productos De Consumo Masivo (fabricaci\u00d3n, Al Por Mayor)",
    "sg:phone":"+34 962 91 31 57",
    "sg:postcode":"46870",
    "sg:province":"Valencia",
    "wof:name":"Juan Mico Vicente Ramon",
    "wof:placetype":"venue"
},
  "geometry": {"coordinates":[-0.6042240262,38.8194389343],"type":"Point"}
}