{
  "type": "Feature",
  "properties": {
    "iso:country":"ES",
    "sg:address":"Calle de Nido, S/n",
    "sg:city":"Narros De Saldue\u00e7a",
    "sg:orig_category":"Empresarios",
    "sg:phone":"+34 920 24 10 92",
    "sg:postcode":"05358",
    "sg:province":"\u00c1vila",
    "wof:name":"Lopez Lopez Pedro",
    "wof:placetype":"venue"
},
  "geometry": {"coordinates":[-4.8676319122,40.8731536865],"type":"Point"}
}