{
  "type": "Feature",
  "properties": {
    "iso:country":"ES",
    "sg:address":"Calle de Ramon Y Cajal, 1",
    "sg:city":"Ciudad Real",
    "sg:orig_category":"Asesor\u00cda De Formaci\u00d3n Y Gesti\u00d3n De Personal",
    "sg:phone":"+34 926 27 11 13",
    "sg:postcode":"13001",
    "sg:province":"Ciudad Real",
    "wof:name":"Centro Manchego De Asesoramiento S.l.",
    "wof:placetype":"venue"
},
  "geometry": {"coordinates":[-3.9269480705,38.9841384888],"type":"Point"}
}