{
  "type": "Feature",
  "properties": {
    "iso:country":"ES",
    "sg:address":"Calle de Valparaiso (de), 2",
    "sg:city":"Fuenlabrada",
    "sg:orig_category":"Empresas De Portes Y Mensajer\u00cda",
    "sg:phone":"+34 914 92 12 23",
    "sg:postcode":"28944",
    "sg:province":"Madrid",
    "wof:name":"Euro Courier Urgente Sl",
    "wof:placetype":"venue"
},
  "geometry": {"coordinates":[-3.7842459679,40.2847099304],"type":"Point"}
}