{
  "type": "Feature",
  "properties": {
    "addr:full":"Cmno Vereda De La Basca, S/n Basca Murcia 30130",
    "addr:housenumber":"s / n",
    "addr:postcode":"30130",
    "addr:street":"Cmno Vereda De La",
    "iso:country":"ES",
    "sg:address":"Cmno Vereda De La Basca, S/n",
    "sg:city":"Basca",
    "sg:orig_category":"Embalajes",
    "sg:phone":"+34 968 60 15 50",
    "sg:postcode":"30130",
    "sg:province":"Murcia",
    "wof:name":"Nomo Pack S.l",
    "wof:placetype":"venue"
},
  "geometry": {"coordinates":[-1.0019739866,38.045753479],"type":"Point"}
}