{
  "type": "Feature",
  "properties": {
    "iso:country":"ES",
    "sg:address":"Av. Del Coure(pol. Ind. Argenteria), 4",
    "sg:city":"Selva Del Camp",
    "sg:orig_category":"Vidrio, Fabricaci\u00d3n Y Comercio",
    "sg:phone":"+34 977 76 61 97",
    "sg:postcode":"43470",
    "sg:province":"Tarragona",
    "wof:name":"Tecnocat 21 S.l.",
    "wof:placetype":"venue"
},
  "geometry": {"coordinates":[1.1409749985,41.2144813538],"type":"Point"}
}