{
  "type": "Feature",
  "properties": {
    "addr:full":"Calle de Compa\u00d1ia, 20 Salamanca Salamanca 37002",
    "addr:housenumber":"20",
    "addr:postcode":"37002",
    "addr:street":"Calle De Compan\u0303Ia",
    "iso:country":"ES",
    "sg:address":"Calle de Compa\u00d1ia, 20",
    "sg:city":"Salamanca",
    "sg:orig_category":"Regalos, Souvenires (fabricaci\u00d3n, Al Por Mayor)",
    "sg:phone":"+34 923 26 49 40",
    "sg:postcode":"37002",
    "sg:province":"Salamanca",
    "wof:name":"Shamhaaghaaiin S.l.",
    "wof:placetype":"venue"
},
  "geometry": {"coordinates":[-5.6661481857,40.9632415771],"type":"Point"}
}