{
  "type": "Feature",
  "properties": {
    "iso:country":"ES",
    "sg:address":"Calle de Carretera, S/n",
    "sg:city":"Villar De Rena",
    "sg:orig_category":"Frutas Y Legumbres Frescas (al Por Mayor)",
    "sg:phone":"+34 924 83 50 11",
    "sg:postcode":"06716",
    "sg:province":"Badajoz",
    "wof:name":"Alfonso Cruz S.a.",
    "wof:placetype":"venue"
},
  "geometry": {"coordinates":[-5.7918992043,39.0326271057],"type":"Point"}
}