{
  "type": "Feature",
  "properties": {
    "addr:full":"Av Ferrocarril, 9 S. Adria Besos Barcelona 08930",
    "addr:housenumber":"9",
    "addr:postcode":"08930",
    "addr:street":"Av Ferrocarril;Barcelona",
    "iso:country":"ES",
    "sg:address":"Av Ferrocarril, 9",
    "sg:city":"S. Adria Besos",
    "sg:orig_category":"Agencias Y Agentes Comerciales, Representantes",
    "sg:phone":"+34 933 81 26 78",
    "sg:postcode":"08930",
    "sg:province":"Barcelona",
    "wof:name":"Stil-gonza S.l.",
    "wof:placetype":"venue"
},
  "geometry": {"coordinates":[2.208509922,41.4273948669],"type":"Point"}
}