{
  "type": "Feature",
  "properties": {
    "addr:full":"Av L'hospital Militar, 180 Barcelona Barcelona 08023",
    "addr:housenumber":"180",
    "addr:postcode":"08023",
    "addr:street":"Av L'Hospital Militar",
    "iso:country":"ES",
    "sg:address":"Av L'hospital Militar, 180",
    "sg:city":"Barcelona",
    "sg:orig_category":"Establecimientos De Cura, Prevenci\u00d3n Y Readaptaci\u00d3n",
    "sg:phone":"+34 932 10 38 54",
    "sg:postcode":"08023",
    "sg:province":"Barcelona",
    "wof:name":"Sociedad Cientifica Espa\u00f1ola De Estudios Sobre El Alcohol El Alcoholismo Y Las Otras Toxicomanias",
    "wof:placetype":"venue"
},
  "geometry": {"coordinates":[2.1406440735,41.4200019836],"type":"Point"}
}