{
  "type": "Feature",
  "properties": {
    "addr:full":"Calle de Zorrilla, 29 Madrid Madrid 28014",
    "addr:housenumber":"29",
    "addr:postcode":"madrid;28014",
    "addr:street":"Calle De Zorrilla",
    "iso:country":"ES",
    "sg:address":"Calle de Zorrilla, 29",
    "sg:city":"Madrid",
    "sg:orig_category":"Sociedades, Compa\u00d1\u00cdas Aseguradoras",
    "sg:phone":"+34 915 23 86 44",
    "sg:postcode":"28014",
    "sg:province":"Madrid",
    "wof:name":"Servicios Tecnicos Aseguramiento Integral S.a.",
    "wof:placetype":"venue"
},
  "geometry": {"coordinates":[-3.6946280003,40.4168624878],"type":"Point"}
}