{
  "type": "Feature",
  "properties": {
    "iso:country":"ES",
    "sg:address":"Calle de Bembibre, 7",
    "sg:city":"Fuenlabrada",
    "sg:orig_category":"Importaci\u00d3n",
    "sg:phone":"+34 916 21 42 85",
    "sg:postcode":"28947",
    "sg:province":"Madrid",
    "wof:name":"Importacion Zhan S.l.",
    "wof:placetype":"venue"
},
  "geometry": {"coordinates":[-3.7462005615,40.267490387],"type":"Point"}
}