{
  "type": "Feature",
  "properties": {
    "iso:country":"ES",
    "sg:address":"Bronze(pol Ind Guixeres), 21",
    "sg:city":"Badalona",
    "sg:classifiers":[
        {
            "category":"Professional",
            "subcategory":"Management & Consulting",
            "type":"Services"
        }
    ],
    "sg:phone":"+34 933 98 72 06",
    "sg:postcode":"08912",
    "sg:province":"Barcelona",
    "sg:tags":[
        "asesor\u00cda",
        "en",
        "marketing"
    ],
    "sg:website":"www.lidair.es",
    "wof:name":"Lidair S.a.",
    "wof:placetype":"venue"
},
  "geometry": {"coordinates":[2.2543799877,41.460483551],"type":"Point"}
}