{
  "type": "Feature",
  "properties": {
    "iso:country":"ES",
    "sg:address":"Crta Motril Cruce Padul(p I La Paloma), S/n",
    "sg:city":"Padul",
    "sg:orig_category":"Bares, Piano",
    "sg:phone":"+34 958 79 00 76",
    "sg:postcode":"18640",
    "sg:province":"Granada",
    "wof:name":"Supercach Manuel Martin Morales S.l.",
    "wof:placetype":"venue"
},
  "geometry": {"coordinates":[-3.6279389858,37.0232009888],"type":"Point"}
}