{
  "type": "Feature",
  "properties": {
    "iso:country":"ES",
    "sg:address":"Calle de Alvarez De Abreu, S/n",
    "sg:city":"Santa Cruz Palma",
    "sg:orig_category":"Colchones (fabricaci\u00d3n, Al Por Mayor, Al Por Menor)",
    "sg:phone":"+34 922 41 14 23",
    "sg:postcode":"38700",
    "sg:province":"Santa Cruz De Tenerife",
    "wof:name":"Matos Bravo Maria Teresa",
    "wof:placetype":"venue"
},
  "geometry": {"coordinates":[-17.7645530701,28.6830120087],"type":"Point"}
}