{
  "type": "Feature",
  "properties": {
    "addr:full":"Calle de Meseguer, 93 Alcazares Murcia 30710",
    "addr:housenumber":"93",
    "addr:postcode":"30710",
    "addr:street":"Calle De Meseguer",
    "iso:country":"ES",
    "sg:address":"Calle de Meseguer, 93",
    "sg:city":"Alcazares",
    "sg:orig_category":"Comercio, Reparaci\u00d3n De Motocicletas, Bicicletas Y Piezas Sueltas",
    "sg:phone":"+34 968 17 02 51",
    "sg:postcode":"30710",
    "sg:province":"Murcia",
    "wof:name":"Hernandez Pe\u00f1alver Gines",
    "wof:placetype":"venue"
},
  "geometry": {"coordinates":[-0.852241993,37.7404441833],"type":"Point"}
}