{
  "type": "Feature",
  "properties": {
    "iso:country":"ES",
    "sg:address":"Pg Bastareny, S/n",
    "sg:city":"Baga",
    "sg:orig_category":"Empresas De Electricidad En General",
    "sg:phone":"+34 938 24 45 78",
    "sg:postcode":"08695",
    "sg:province":"Barcelona",
    "wof:name":"Hidrodata S.a.",
    "wof:placetype":"venue"
},
  "geometry": {"coordinates":[1.8621250391,42.2517356873],"type":"Point"}
}