{
  "type": "Feature",
  "properties": {
    "iso:country":"ES",
    "sg:address":"Calle de Duraznero, 40",
    "sg:city":"Poligono Industrial De Arinaga",
    "sg:orig_category":"Quincaller\u00cda (al Por Mayor)",
    "sg:phone":"+34 928 79 36 23",
    "sg:postcode":"35118",
    "sg:province":"Las Palmas",
    "sg:website":"www.anfrabar.com",
    "wof:name":"Comercial Anfrabar S. L.",
    "wof:placetype":"venue"
},
  "geometry": {"coordinates":[-15.3927698135,27.8557987213],"type":"Point"}
}