{
  "type": "Feature",
  "properties": {
    "addr:full":"Calle de Juan Bravo, 4 Puertollano Ciudad Real 13500",
    "addr:housenumber":"4",
    "addr:postcode":"13500",
    "addr:street":"Calle De Juan Bravo",
    "iso:country":"ES",
    "sg:address":"Calle de Juan Bravo, 4",
    "sg:city":"Puertollano",
    "sg:orig_category":"Sindicatos De Trabajadores",
    "sg:phone":"+34 926 42 28 52",
    "sg:postcode":"13500",
    "sg:province":"Ciudad Real",
    "wof:name":"Federacion Regional De Ense\u00f1anza De Comisiones Obreras",
    "wof:placetype":"venue"
},
  "geometry": {"coordinates":[-4.1069412231,38.6863822937],"type":"Point"}
}