{
  "type": "Feature",
  "properties": {
    "addr:full":"Calle de Goienkalea, 2 Durango Vizcaya 48200",
    "addr:housenumber":"2",
    "addr:postcode":"48200",
    "addr:street":"Calle De Goienkalea",
    "iso:country":"ES",
    "sg:address":"Calle de Goienkalea, 2",
    "sg:city":"Durango",
    "sg:orig_category":"Complementos De Vestir (al Por Menor)",
    "sg:phone":"+34 946 81 88 75",
    "sg:postcode":"48200",
    "sg:province":"Vizcaya",
    "wof:name":"Mari Carmen Iriondo Asategui (marina Boutique)",
    "wof:placetype":"venue"
},
  "geometry": {"coordinates":[-2.6309885979,43.1674728394],"type":"Point"}
}