{
  "type": "Feature",
  "properties": {
    "iso:country":"ES",
    "sg:address":"Calle de Jaudenes, 15",
    "sg:city":"Ceuta",
    "sg:orig_category":"Abogados",
    "sg:phone":"+34 956 51 94 05",
    "sg:postcode":"51001",
    "sg:province":"Ceuta",
    "wof:name":"Martinez Miguel Guillermo",
    "wof:placetype":"venue"
},
  "geometry": {"coordinates":[-5.3144931793,35.8876304626],"type":"Point"}
}