{
  "type": "Feature",
  "properties": {
    "addr:full":"Calle de Padre Santalla, 2 Ponferrada Le\u00f3n 24400",
    "addr:housenumber":"2",
    "addr:postcode":"24400",
    "addr:street":"Calle De Padre Santalla",
    "iso:country":"ES",
    "sg:address":"Calle de Padre Santalla, 2",
    "sg:city":"Ponferrada",
    "sg:orig_category":"Electricidad: Equipos Industriales, Componentes (fabricaci\u00d3n)",
    "sg:phone":"+34 987 41 31 68",
    "sg:postcode":"24400",
    "sg:province":"Le\u00f3n",
    "wof:name":"Euregasa S.l.",
    "wof:placetype":"venue"
},
  "geometry": {"coordinates":[-6.6023759842,42.5480728149],"type":"Point"}
}