{
  "type": "Feature",
  "properties": {
    "addr:full":"Plaz Constitucion, 2 Casar Guadalajara 19170",
    "addr:housenumber":"2",
    "addr:postcode":"19170",
    "addr:street":"Constitucion",
    "iso:country":"ES",
    "sg:address":"Plaz Constitucion, 2",
    "sg:city":"Casar",
    "sg:orig_category":"Asistencia Social",
    "sg:phone":"+34 949 33 40 01",
    "sg:postcode":"19170",
    "sg:province":"Guadalajara",
    "wof:name":"Ayuntamiento De El Casar De Talamanca",
    "wof:placetype":"venue"
},
  "geometry": {"coordinates":[-3.4308691025,40.7028961182],"type":"Point"}
}