{
  "type": "Feature",
  "properties": {
    "addr:full":"Calle de Hermosilla, 75 Madrid Madrid 28001",
    "addr:housenumber":"75",
    "addr:postcode":"madrid;28001",
    "addr:street":"Calle De Hermosilla",
    "iso:country":"ES",
    "sg:address":"Calle de Hermosilla, 75",
    "sg:city":"Madrid",
    "sg:orig_category":"M\u00c9dicos: Oftalmolog\u00cda",
    "sg:phone":"+34 915 76 32 48",
    "sg:postcode":"28001",
    "sg:province":"Madrid",
    "wof:name":"Montes Vicente Manuel",
    "wof:placetype":"venue"
},
  "geometry": {"coordinates":[-3.678303957,40.4261856079],"type":"Point"}
}