{
  "type": "Feature",
  "properties": {
    "iso:country":"ES",
    "sg:address":"Calle de Foso (del), 52",
    "sg:city":"Aranjuez",
    "sg:orig_category":"Bares, Piano",
    "sg:phone":"+34 918 92 13 32",
    "sg:postcode":"28300",
    "sg:province":"Madrid",
    "wof:name":"Pub Cotton C.b.",
    "wof:placetype":"venue"
},
  "geometry": {"coordinates":[-3.5979859829,40.034362793],"type":"Point"}
}