{
  "type": "Feature",
  "properties": {
    "addr:full":"Avda Carabancheles (de Los), 16 Alcorcon Madrid 28921",
    "addr:housenumber":"16",
    "addr:postcode":"28921",
    "addr:street":"Avda Carabancheles De Los",
    "iso:country":"ES",
    "sg:address":"Avda Carabancheles (de Los), 16",
    "sg:city":"Alcorcon",
    "sg:orig_category":"Promotores Constructores",
    "sg:phone":"+34 916 19 04 09",
    "sg:postcode":"28921",
    "sg:province":"Madrid",
    "wof:name":"Esteban Mu\u00f1oz Y Hermanos S.a.",
    "wof:placetype":"venue"
},
  "geometry": {"coordinates":[-3.826967001,40.3505058289],"type":"Point"}
}