{
  "type": "Feature",
  "properties": {
    "addr:full":"Carrer de Puerto Rico, 18 Palma Islas Baleares 07007",
    "addr:housenumber":"18",
    "addr:postcode":"07007",
    "addr:street":"Carrer De Puerto Rico",
    "iso:country":"ES",
    "sg:address":"Carrer de Puerto Rico, 18",
    "sg:city":"Palma",
    "sg:orig_category":"Sanatorios M\u00c9dico",
    "sg:phone":"+34 971 42 01 61",
    "sg:postcode":"07007",
    "sg:province":"Islas Baleares",
    "wof:name":"Ib Salut",
    "wof:placetype":"venue"
},
  "geometry": {"coordinates":[2.668076992,39.5647544861],"type":"Point"}
}