{
  "type": "Feature",
  "properties": {
    "iso:country":"ES",
    "sg:address":"Calle de Grande Covian, 3",
    "sg:city":"Pola De Lena",
    "sg:orig_category":"Inform\u00c1tica, Ofim\u00c1tica (estudios, Asesor\u00cda, Ingenier\u00cda, Formaci\u00d3n)",
    "sg:phone":"+34 985 49 39 11",
    "sg:postcode":"33630",
    "sg:province":"Asturias",
    "wof:name":"Servicios Integrales Ascii S.l.",
    "wof:placetype":"venue"
},
  "geometry": {"coordinates":[-5.8289198875,43.1574020386],"type":"Point"}
}