{
  "type": "Feature",
  "properties": {
    "iso:country":"ES",
    "sg:address":"Calle de Conde De Altea, 58",
    "sg:city":"Altea",
    "sg:orig_category":"Ropa Para Ni\u00d1os (al Por Menor)",
    "sg:phone":"+34 965 84 51 61",
    "sg:postcode":"03590",
    "sg:province":"Alicante",
    "wof:name":"Blazquez Parra Ricardo",
    "wof:placetype":"venue"
},
  "geometry": {"coordinates":[-0.0450970009,38.6026573181],"type":"Point"}
}