{
  "type": "Feature",
  "properties": {
    "addr:full":"Av Catalunya, 10 Puigcerda Girona 17520",
    "addr:housenumber":"10",
    "addr:postcode":"17520",
    "addr:street":"Av Catalunya",
    "iso:country":"ES",
    "sg:address":"Av Catalunya, 10",
    "sg:city":"Puigcerda",
    "sg:orig_category":"Compraventa De Antig\u00dcedades",
    "sg:phone":"+34 972 14 10 85",
    "sg:postcode":"17520",
    "sg:province":"Girona",
    "wof:name":"Llombart Padros Juan",
    "wof:placetype":"venue"
},
  "geometry": {"coordinates":[1.9271199703,42.4292411804],"type":"Point"}
}