{
  "type": "Feature",
  "properties": {
    "iso:country":"ES",
    "sg:address":"Calle de Lope De Vega, 18",
    "sg:city":"Castalla",
    "sg:orig_category":"Fabricaci\u00d3n De Moldes Y Modelos",
    "sg:phone":"+34 965 56 18 81",
    "sg:postcode":"03420",
    "sg:province":"Alicante",
    "wof:name":"Sanchez Martinez Antonio",
    "wof:placetype":"venue"
},
  "geometry": {"coordinates":[-0.6763290167,38.5946578979],"type":"Point"}
}