{
  "type": "Feature",
  "properties": {
    "iso:country":"ES",
    "sg:address":"Calle de Antolin Lopez Pelaez, 17",
    "sg:city":"Ponferrada",
    "sg:orig_category":"Librer\u00cdas",
    "sg:phone":"+34 987 42 32 26",
    "sg:postcode":"24400",
    "sg:province":"Le\u00f3n",
    "wof:name":"Lopez Blanco Maria Olimpia",
    "wof:placetype":"venue"
},
  "geometry": {"coordinates":[-6.6000127792,42.5471878052],"type":"Point"}
}