{
  "type": "Feature",
  "properties": {
    "iso:country":"ES",
    "sg:address":"Sandua, 42",
    "sg:city":"Iru\u00f1a",
    "sg:orig_category":"Farmacias",
    "sg:phone":"+34 948 13 21 80",
    "sg:postcode":"31012",
    "sg:province":"Navarra",
    "wof:name":"Gogorza Moreno Maria Gloria",
    "wof:placetype":"venue"
},
  "geometry": {"coordinates":[-1.6646840572,42.8227653503],"type":"Point"}
}