{
  "type": "Feature",
  "properties": {
    "iso:country":"ES",
    "sg:address":"Av Barcelona, 64",
    "sg:city":"S. Joan Despi",
    "sg:classifiers":[
        {
            "category":"Communications",
            "type":"Services"
        }
    ],
    "sg:phone":"+34 933 73 43 40",
    "sg:postcode":"08970",
    "sg:province":"Barcelona",
    "sg:tags":[
        "televisiones",
        "y",
        "radio"
    ],
    "wof:name":"Radio Despi A.j.a.r. Sant Joan D'espi",
    "wof:placetype":"venue"
},
  "geometry": {"coordinates":[2.0700800419,41.3683586121],"type":"Point"}
}