{
  "type": "Feature",
  "properties": {
    "addr:full":"Urb Holiday Club, 8 Barranc Fondo Alicante 03530",
    "addr:housenumber":"8",
    "addr:postcode":"03530",
    "addr:street":"Barranc Fondo",
    "iso:country":"ES",
    "sg:address":"Urb Holiday Club, 8",
    "sg:city":"Barranc Fondo",
    "sg:orig_category":"Inmobiliaria (agencias)",
    "sg:phone":"+34 966 87 70 11",
    "sg:postcode":"03530",
    "sg:province":"Alicante",
    "wof:name":"Lamprecht  Alexandra",
    "wof:placetype":"venue"
},
  "geometry": {"coordinates":[-0.1213990003,38.594619751],"type":"Point"}
}