{
  "type": "Feature",
  "properties": {
    "iso:country":"ES",
    "sg:address":"Calle de Vinca, S/n",
    "sg:city":"Poligono Industrial De Arinaga",
    "sg:orig_category":"Suministros Para Hoteles",
    "sg:phone":"+34 928 14 26 72",
    "sg:postcode":"35118",
    "sg:province":"Las Palmas",
    "wof:name":"Comercial Faustino Diaz S.l.",
    "wof:placetype":"venue"
},
  "geometry": {"coordinates":[-15.4319887161,27.8808555603],"type":"Point"}
}