{
  "type": "Feature",
  "properties": {
    "addr:full":"Avda Alcaldesa Maria Regla Jimenez, 82 Espartinas Sevilla 41807",
    "addr:housenumber":"82",
    "addr:postcode":"41807",
    "addr:street":"Avda Alcaldesa Maria Regla Jimenez",
    "iso:country":"ES",
    "sg:address":"Avda Alcaldesa Maria Regla Jimenez, 82",
    "sg:city":"Espartinas",
    "sg:orig_category":"Restaurantes",
    "sg:phone":"+34 954 11 37 36",
    "sg:postcode":"41807",
    "sg:province":"Sevilla",
    "wof:name":"Hermanos Gavi\u00f1o Ruiz C.b.",
    "wof:placetype":"venue"
},
  "geometry": {"coordinates":[-6.1277508736,37.3822021484],"type":"Point"}
}