{
  "type": "Feature",
  "properties": {
    "addr:full":"Calle de Santiago, 2 Madrid Madrid 28013",
    "addr:housenumber":"2",
    "addr:postcode":"28013",
    "addr:street":"Calle De Santiago",
    "iso:country":"ES",
    "sg:address":"Calle de Santiago, 2",
    "sg:city":"Madrid",
    "sg:orig_category":"Centros Empresariales",
    "sg:phone":"+34 915 59 68 57",
    "sg:postcode":"28013",
    "sg:province":"Madrid",
    "wof:name":"Habitat Siglo Xxis.a.",
    "wof:placetype":"venue"
},
  "geometry": {"coordinates":[-3.7096469402,40.4161872864],"type":"Point"}
}