{
  "type": "Feature",
  "properties": {
    "addr:full":"Calle de Asturias, 6 Bilbao Vizcaya 48015",
    "addr:housenumber":"6",
    "addr:postcode":"48015",
    "addr:street":"Calle De Asturias",
    "iso:country":"ES",
    "sg:address":"Calle de Asturias, 6",
    "sg:city":"Bilbao",
    "sg:orig_category":"Molduras, Junquillos, Listones Y Molduras Perforadas",
    "sg:phone":"+34 944 76 17 61",
    "sg:postcode":"48015",
    "sg:province":"Vizcaya",
    "wof:name":"Juan Jose Castrillo Perez",
    "wof:placetype":"venue"
},
  "geometry": {"coordinates":[-2.9629354477,43.2816696167],"type":"Point"}
}