{
  "type": "Feature",
  "properties": {
    "addr:full":"Calle de Barrio Nuevo, 49 Alcala Guadaira Sevilla 41500",
    "addr:housenumber":"49",
    "addr:postcode":"41500",
    "addr:street":"Calle De Barrio Nuevo",
    "iso:country":"ES",
    "sg:address":"Calle de Barrio Nuevo, 49",
    "sg:city":"Alcala Guadaira",
    "sg:classifiers":[
        {
            "category":"Autos & Motor Vehicles",
            "subcategory":"Automobile Sales",
            "type":"Retail Goods"
        }
    ],
    "sg:phone":"+34 955 68 37 44",
    "sg:postcode":"41500",
    "sg:province":"Sevilla",
    "wof:name":"Sebastian Y Lumi S.l.",
    "wof:placetype":"venue"
},
  "geometry": {"coordinates":[-5.8459811211,37.341129303],"type":"Point"}
}