{
  "type": "Feature",
  "properties": {
    "addr:full":"Calle de Marcos Redondo, 20 San Javier Murcia 30730",
    "addr:housenumber":"20",
    "addr:postcode":"30730",
    "addr:street":"Calle De Marcos Redondo",
    "iso:country":"ES",
    "sg:address":"Calle de Marcos Redondo, 20",
    "sg:city":"San Javier",
    "sg:orig_category":"Delegados, Agentes De Tr\u00c1nsito, Auxiliares De Transporte Internacional",
    "sg:phone":"+34 968 57 07 51",
    "sg:postcode":"30730",
    "sg:province":"Murcia",
    "wof:name":"Fructuoso Gutierrez Salvador",
    "wof:placetype":"venue"
},
  "geometry": {"coordinates":[-0.832728982,37.8003387451],"type":"Point"}
}