{
  "type": "Feature",
  "properties": {
    "iso:country":"ES",
    "sg:address":"Carrer de Mallorca, 474",
    "sg:city":"Barcelona",
    "sg:orig_category":"Prot\u00c9sicos Dentales",
    "sg:phone":"+34 932 32 89 25",
    "sg:postcode":"08013",
    "sg:province":"Barcelona",
    "wof:name":"The End Tes S.l.",
    "wof:placetype":"venue"
},
  "geometry": {"coordinates":[2.1788549423,41.4059791565],"type":"Point"}
}