{
  "type": "Feature",
  "properties": {
    "addr:full":"Redondo, 12 Moa\u00f1a Pontevedra 36959",
    "addr:housenumber":"12",
    "addr:postcode":"36959",
    "addr:street":"Redondo",
    "iso:country":"ES",
    "sg:address":"Redondo, 12",
    "sg:city":"Moa\u00f1a",
    "sg:orig_category":"Abogados",
    "sg:phone":"+34 986 31 39 29",
    "sg:postcode":"36959",
    "sg:province":"Pontevedra",
    "wof:name":"Rosales Garcia Alba",
    "wof:placetype":"venue"
},
  "geometry": {"coordinates":[-8.7357263565,42.3101577759],"type":"Point"}
}