{
  "type": "Feature",
  "properties": {
    "addr:full":"Luga Poblado Del Porti\u00d1o, 2 Porti\u00d1o La Coru\u00f1a 15011",
    "addr:housenumber":"2",
    "addr:postcode":"15011",
    "addr:street":"Portin\u0303O;La Corun\u0303A",
    "iso:country":"ES",
    "sg:address":"Luga Poblado Del Porti\u00d1o, 2",
    "sg:city":"Porti\u00d1o",
    "sg:orig_category":"Empresas De Carpinter\u00cda De Madera",
    "sg:phone":"+34 981 27 41 03",
    "sg:postcode":"15011",
    "sg:province":"La Coru\u00f1a",
    "wof:name":"Manti\u00f1an Candal Carlos",
    "wof:placetype":"venue"
},
  "geometry": {"coordinates":[-8.3964595795,43.3701095581],"type":"Point"}
}