{
  "type": "Feature",
  "properties": {
    "addr:full":"Rava Fora, 8 Sabadell Barcelona 08202",
    "addr:housenumber":"8",
    "addr:postcode":"08202",
    "addr:street":"Fora",
    "iso:country":"ES",
    "sg:address":"Rava Fora, 8",
    "sg:city":"Sabadell",
    "sg:orig_category":"M\u00c9dicos: Cirug\u00cda Urol\u00d3gica",
    "sg:phone":"+34 937 26 48 38",
    "sg:postcode":"08202",
    "sg:province":"Barcelona",
    "wof:name":"Orriols Moix Anna Maria",
    "wof:placetype":"venue"
},
  "geometry": {"coordinates":[2.125674963,41.5481300354],"type":"Point"}
}