{
  "type": "Feature",
  "properties": {
    "addr:full":"Avgd Pais Valencia, 120 Algemesi Valencia 46680",
    "addr:housenumber":"120",
    "addr:postcode":"46680",
    "addr:street":"Valencia",
    "iso:country":"ES",
    "sg:address":"Avgd Pais Valencia, 120",
    "sg:city":"Algemesi",
    "sg:orig_category":"Agencias Y Agentes Comerciales, Representantes",
    "sg:phone":"+34 962 42 18 04",
    "sg:postcode":"46680",
    "sg:province":"Valencia",
    "wof:name":"Rojas Gomariz Vicente",
    "wof:placetype":"venue"
},
  "geometry": {"coordinates":[-0.431396991,39.1934394836],"type":"Point"}
}