{
  "type": "Feature",
  "properties": {
    "iso:country":"ES",
    "sg:address":"Paseo Costureras-p I La Piel, 17",
    "sg:city":"Ubrique",
    "sg:orig_category":"Marroquiner\u00cda (confecci\u00d3n)",
    "sg:phone":"+34 956 46 42 83",
    "sg:postcode":"11600",
    "sg:province":"C\u00e1diz",
    "wof:name":"Marroquineria Pi\u00f1ero S.l.",
    "wof:placetype":"venue"
},
  "geometry": {"coordinates":[-5.4475698471,36.6776618958],"type":"Point"}
}