{
  "type": "Feature",
  "properties": {
    "addr:full":"Avda Camilo Jose Cela, 19 Cuellar Segovia 40200",
    "addr:housenumber":"19",
    "addr:postcode":"40200",
    "addr:street":"Avda Camilo Jose Cela",
    "iso:country":"ES",
    "sg:address":"Avda Camilo Jose Cela, 19",
    "sg:city":"Cuellar",
    "sg:orig_category":"Venta, Alquiler, Mantenimiento De Calderas",
    "sg:phone":"+34 921 14 24 30",
    "sg:postcode":"40200",
    "sg:province":"Segovia",
    "wof:name":"Saneamientos Cuellar S.r.l.",
    "wof:placetype":"venue"
},
  "geometry": {"coordinates":[-4.3069338799,41.3962402344],"type":"Point"}
}