{
  "type": "Feature",
  "properties": {
    "addr:full":"Calle de Sancho Iv El Bravo, 9 Tarifa C\u00e1diz 11380",
    "addr:housenumber":"9",
    "addr:postcode":"11380",
    "addr:street":"Calle De Sancho Iv El Bravo;Ca\u0301Diz",
    "iso:country":"ES",
    "sg:address":"Calle de Sancho Iv El Bravo, 9",
    "sg:city":"Tarifa",
    "sg:orig_category":"Telas Y Sedas (al Por Menor)",
    "sg:phone":"+34 956 68 00 88",
    "sg:postcode":"11380",
    "sg:province":"C\u00e1diz",
    "wof:name":"Trujillo Perez Juan",
    "wof:placetype":"venue"
},
  "geometry": {"coordinates":[-5.6030640602,36.0127944946],"type":"Point"}
}