{
  "type": "Feature",
  "properties": {
    "iso:country":"ES",
    "sg:address":"Carrer de Gambus, 42",
    "sg:city":"Sabadell",
    "sg:orig_category":"Veh\u00cdculos De Ocasi\u00d3n",
    "sg:phone":"+34 937 24 70 51",
    "sg:postcode":"08208",
    "sg:province":"Barcelona",
    "sg:website":"www.automovilsconrad.com",
    "wof:name":"Automovils Conrad Sl",
    "wof:placetype":"venue"
},
  "geometry": {"coordinates":[2.0998210907,41.5577201843],"type":"Point"}
}