{
  "type": "Feature",
  "properties": {
    "addr:full":"Carrer de Pere Martell (de), 18 Tarragona Tarragona 43001",
    "addr:housenumber":"18",
    "addr:postcode":"43001",
    "addr:street":"Carrer De Pere Martell De",
    "iso:country":"ES",
    "sg:address":"Carrer de Pere Martell (de), 18",
    "sg:city":"Tarragona",
    "sg:orig_category":"Chapister\u00cda",
    "sg:phone":"+34 977 21 37 17",
    "sg:postcode":"43001",
    "sg:province":"Tarragona",
    "wof:name":"Talleres Gua Car C.b.",
    "wof:placetype":"venue"
},
  "geometry": {"coordinates":[1.2445789576,41.1165962219],"type":"Point"}
}