{
  "type": "Feature",
  "properties": {
    "addr:full":"Avda Madrid (de), 116 Molina Segura Murcia 30500",
    "addr:housenumber":"116",
    "addr:postcode":"30500",
    "addr:street":"Avda Madrid De",
    "iso:country":"ES",
    "sg:address":"Avda Madrid (de), 116",
    "sg:city":"Molina Segura",
    "sg:orig_category":"Mortero Y Material Para Jardines",
    "sg:phone":"+34 968 64 45 29",
    "sg:postcode":"30500",
    "sg:province":"Murcia",
    "wof:name":"Soleras Y Recrecidos Autonivelantes S.l.",
    "wof:placetype":"venue"
},
  "geometry": {"coordinates":[-1.2170009613,38.0592956543],"type":"Point"}
}