{
  "type": "Feature",
  "properties": {
    "addr:full":"Cm\u00d1o Barciela, 5 Vigo Pontevedra 36208",
    "addr:housenumber":"5",
    "addr:postcode":"36208",
    "addr:street":"Barciela",
    "iso:country":"ES",
    "sg:address":"Cm\u00d1o Barciela, 5",
    "sg:city":"Vigo",
    "sg:orig_category":"Molduras, Junquillos, Listones Y Molduras Perforadas",
    "sg:phone":"+34 986 23 31 26",
    "sg:postcode":"36208",
    "sg:province":"Pontevedra",
    "wof:name":"Carpintero Alberte Jose Ramon",
    "wof:placetype":"venue"
},
  "geometry": {"coordinates":[-8.740650177,42.2234687805],"type":"Point"}
}