{
  "type": "Feature",
  "properties": {
    "addr:full":"C/ 110, 2 Ca\u00d1ada Valencia 46182",
    "addr:housenumber":"2",
    "addr:postcode":"46182",
    "addr:street":"C / 110",
    "iso:country":"ES",
    "sg:address":"C/ 110, 2",
    "sg:city":"Ca\u00d1ada",
    "sg:orig_category":"Perfumer\u00cda Y Cosm\u00c9tica (fabricaci\u00d3n, Al Por Mayor)",
    "sg:phone":"+34 961 32 24 79",
    "sg:postcode":"46182",
    "sg:province":"Valencia",
    "wof:name":"Aura Riaza Maria Carmen",
    "wof:placetype":"venue"
},
  "geometry": {"coordinates":[-0.4824869037,39.5298156738],"type":"Point"}
}