{
  "type": "Feature",
  "properties": {
    "iso:country":"ES",
    "sg:address":"Jose Migel Iturriotz Kalea, 12",
    "sg:city":"Beasain",
    "sg:orig_category":"Relojer\u00cda (al Por Menor, Reparaci\u00d3n)",
    "sg:phone":"+34 943 88 40 63",
    "sg:postcode":"20200",
    "sg:province":"Guip\u00f9zcoa",
    "wof:name":"Imaz Ibarbia Jose Antonio",
    "wof:placetype":"venue"
},
  "geometry": {"coordinates":[-2.1934010983,43.0476875305],"type":"Point"}
}