{
  "type": "Feature",
  "properties": {
    "addr:full":"Calle de Luz Arriero, 2 Sevilla Sevilla 41010",
    "addr:housenumber":"2",
    "addr:postcode":"41010",
    "addr:street":"Calle De Luz Arriero",
    "iso:country":"ES",
    "sg:address":"Calle de Luz Arriero, 2",
    "sg:city":"Sevilla",
    "sg:orig_category":"Fisioterapia",
    "sg:phone":"+34 954 33 27 88",
    "sg:postcode":"41010",
    "sg:province":"Sevilla",
    "wof:name":"Escribano Contreras Carmen",
    "wof:placetype":"venue"
},
  "geometry": {"coordinates":[-6.0021829605,37.3808937073],"type":"Point"}
}