{
  "type": "Feature",
  "properties": {
    "addr:full":"Cust Caldereros, 32 Antequera M\u00e1laga 29200",
    "addr:housenumber":"32",
    "addr:postcode":"29200",
    "addr:street":"Caldereros",
    "iso:country":"ES",
    "sg:address":"Cust Caldereros, 32",
    "sg:city":"Antequera",
    "sg:orig_category":"Alimentaci\u00d3n General (al Por Menor)",
    "sg:phone":"+34 952 70 48 65",
    "sg:postcode":"29200",
    "sg:province":"M\u00e1laga",
    "wof:name":"Hermanos Acedo Sanchez S.l.",
    "wof:placetype":"venue"
},
  "geometry": {"coordinates":[-4.5597438812,37.0140838623],"type":"Point"}
}