{
  "type": "Feature",
  "properties": {
    "addr:full":"Ctra. M-lisboa, Km. 0328,5 San Pedro Merida Badajoz 06893",
    "addr:postcode":"06893",
    "addr:street":"Ctra. M-Lisboa Km. 0328,5",
    "iso:country":"ES",
    "sg:address":"Ctra. M-lisboa, Km. 0328,5",
    "sg:city":"San Pedro Merida",
    "sg:orig_category":"Poller\u00cda Y Caza (al Por Menor)",
    "sg:phone":"+34 924 12 30 19",
    "sg:postcode":"06893",
    "sg:province":"Badajoz",
    "wof:name":"Granjas Cantos Blancos Sur S.l.",
    "wof:placetype":"venue"
},
  "geometry": {"coordinates":[-6.1862578392,38.9473075867],"type":"Point"}
}