{
  "type": "Feature",
  "properties": {
    "addr:full":"B (p I Llanos Del Valle), S/n Jaen Ja\u00e9n 23009",
    "addr:housenumber":"s / n;jae\u0301n",
    "addr:postcode":"23009",
    "iso:country":"ES",
    "sg:address":"B (p I Llanos Del Valle), S/n",
    "sg:city":"Jaen",
    "sg:orig_category":"Empresas De Limpieza",
    "sg:phone":"+34 953 28 40 25",
    "sg:postcode":"23009",
    "sg:province":"Ja\u00e9n",
    "wof:name":"Eulen S.a.",
    "wof:placetype":"venue"
},
  "geometry": {"coordinates":[-3.7581489086,37.779209137],"type":"Point"}
}