{
  "type": "Feature",
  "properties": {
    "addr:full":"Calle de Gran Via, 50 Hellin Albacete 02400",
    "addr:housenumber":"50",
    "addr:postcode":"02400",
    "addr:street":"Calle De Gran Via",
    "iso:country":"ES",
    "sg:address":"Calle de Gran Via, 50",
    "sg:city":"Hellin",
    "sg:orig_category":"Librer\u00cdas",
    "sg:phone":"+34 967 17 61 11",
    "sg:postcode":"02400",
    "sg:province":"Albacete",
    "wof:name":"Garcia Caballero Rosario",
    "wof:placetype":"venue"
},
  "geometry": {"coordinates":[-1.695325017,38.50831604],"type":"Point"}
}