{
  "type": "Feature",
  "properties": {
    "iso:country":"ES",
    "sg:address":"Calle de Clavel (del), 4",
    "sg:city":"Pozuelo De Alarcon",
    "sg:orig_category":"Electricidad: Instaladores",
    "sg:phone":"+34 917 99 03 00",
    "sg:postcode":"28223",
    "sg:province":"Madrid",
    "wof:name":"Elecoeste S.l.",
    "wof:placetype":"venue"
},
  "geometry": {"coordinates":[-3.8136210442,40.4375190735],"type":"Point"}
}