{
  "type": "Feature",
  "properties": {
    "iso:country":"ES",
    "sg:address":"Av Fco Salzillo(pol Ind Oeste), S/n",
    "sg:city":"S. Gines",
    "sg:orig_category":"Serigraf\u00cda (material Y Suministros)",
    "sg:phone":"+34 968 88 11 27",
    "sg:postcode":"30169",
    "sg:province":"Murcia",
    "wof:name":"Printimur S.a.l.",
    "wof:placetype":"venue"
},
  "geometry": {"coordinates":[-1.177366972,37.9589958191],"type":"Point"}
}