{
  "type": "Feature",
  "properties": {
    "addr:full":"Pelotari Kalea, 6 Astigarraga Guip\u00f9zcoa 20115",
    "addr:housenumber":"6",
    "addr:postcode":"20115",
    "addr:street":"Pelotari Kalea;Guipu\u0300Zcoa",
    "iso:country":"ES",
    "sg:address":"Pelotari Kalea, 6",
    "sg:city":"Astigarraga",
    "sg:classifiers":[
        {
            "category":"Autos & Motor Vehicles",
            "subcategory":"Automobile Sales",
            "type":"Retail Goods"
        }
    ],
    "sg:phone":"+34 943 33 22 11",
    "sg:postcode":"20115",
    "sg:province":"Guip\u00f9zcoa",
    "wof:name":"Otamendi Anaiak S.l.",
    "wof:placetype":"venue"
},
  "geometry": {"coordinates":[-1.9484319687,43.2820472717],"type":"Point"}
}