{
  "type": "Feature",
  "properties": {
    "iso:country":"ES",
    "sg:address":"Prje Tiesas, S/n",
    "sg:city":"Villena",
    "sg:orig_category":"Semiller\u00cdas",
    "sg:phone":"+34 965 80 68 55",
    "sg:postcode":"03400",
    "sg:province":"Alicante",
    "wof:name":"Viveros Bernabeu S.l.",
    "wof:placetype":"venue"
},
  "geometry": {"coordinates":[-0.8865833879,38.6286621094],"type":"Point"}
}