{
  "type": "Feature",
  "properties": {
    "iso:country":"ES",
    "sg:address":"Portu Kalea, 2",
    "sg:city":"O\u00f1ati",
    "sg:orig_category":"Carnicer\u00cdas, Carnicer\u00cdas",
    "sg:phone":"+34 943 78 31 04",
    "sg:postcode":"20560",
    "sg:province":"Guip\u00f9zcoa",
    "wof:name":"Oses Otxandorena Isidro Tarsicio",
    "wof:placetype":"venue"
},
  "geometry": {"coordinates":[-2.4125061035,43.0333099365],"type":"Point"}
}