{
  "type": "Feature",
  "properties": {
    "iso:country":"ES",
    "sg:address":"Calle de Puerta De Lorca, S/n",
    "sg:city":"Baza",
    "sg:orig_category":"M\u00c1rmoles, Granitos Y Piedras Naturales",
    "sg:phone":"+34 958 70 03 42",
    "sg:postcode":"18800",
    "sg:province":"Granada",
    "wof:name":"Valdes Pastor Juan",
    "wof:placetype":"venue"
},
  "geometry": {"coordinates":[-2.7695889473,37.4909744263],"type":"Point"}
}