{
  "type": "Feature",
  "properties": {
    "iso:country":"ES",
    "sg:address":"Calle de Velazquez, 70",
    "sg:city":"Madrid",
    "sg:orig_category":"Peluqueros: De Se\u00d1oras",
    "sg:phone":"+34 915 78 17 54",
    "sg:postcode":"28001",
    "sg:province":"Madrid",
    "wof:name":"Gonzalez Alcaraz Mercedes",
    "wof:placetype":"venue"
},
  "geometry": {"coordinates":[-3.6836500168,40.4287605286],"type":"Point"}
}