{
  "type": "Feature",
  "properties": {
    "addr:full":"Calle de Juan Carlos I, 10 Pe\u00e7arroya-pueblonuevo C\u00f3rdoba 14200",
    "addr:housenumber":"10",
    "addr:postcode":"14200",
    "addr:street":"Calle De Juan Carlos I;Co\u0301Rdoba",
    "iso:country":"ES",
    "sg:address":"Calle de Juan Carlos I, 10",
    "sg:city":"Pe\u00e7arroya-pueblonuevo",
    "sg:orig_category":"Florister\u00cdas",
    "sg:phone":"+34 957 56 01 86",
    "sg:postcode":"14200",
    "sg:province":"C\u00f3rdoba",
    "wof:name":"Cabellero Gea Carlos",
    "wof:placetype":"venue"
},
  "geometry": {"coordinates":[-5.2654738426,38.2985687256],"type":"Point"}
}