{
  "type": "Feature",
  "properties": {
    "iso:country":"ES",
    "sg:address":"Calle de San Antonio, 1",
    "sg:city":"Xirivella",
    "sg:orig_category":"Abogados",
    "sg:phone":"+34 963 70 11 50",
    "sg:postcode":"46950",
    "sg:province":"Valencia",
    "wof:name":"Garcia Alix Juan Jose",
    "wof:placetype":"venue"
},
  "geometry": {"coordinates":[-0.4253520072,39.4653625488],"type":"Point"}
}