{
  "type": "Feature",
  "properties": {
    "iso:country":"ES",
    "sg:address":"Calle de Mar Caspio, 10",
    "sg:city":"Madrid",
    "sg:orig_category":"Empresas De Limpieza",
    "sg:phone":"+34 913 81 85 64",
    "sg:postcode":"28033",
    "sg:province":"Madrid",
    "wof:name":"Pilar Herrero Poza S.l.",
    "wof:placetype":"venue"
},
  "geometry": {"coordinates":[-3.6437959671,40.4732704163],"type":"Point"}
}