{
  "type": "Feature",
  "properties": {
    "addr:full":"Calle de Gudari, 9 Amorebieta Vizcaya 48340",
    "addr:housenumber":"9",
    "addr:postcode":"48340",
    "addr:street":"Calle De Gudari",
    "iso:country":"ES",
    "sg:address":"Calle de Gudari, 9",
    "sg:city":"Amorebieta",
    "sg:orig_category":"Agencias De Viajes",
    "sg:phone":"+34 946 73 19 76",
    "sg:postcode":"48340",
    "sg:province":"Vizcaya",
    "wof:name":"Viajes Azkorri S.l.",
    "wof:placetype":"venue"
},
  "geometry": {"coordinates":[-2.7350170612,43.2201194763],"type":"Point"}
}