{
  "type": "Feature",
  "properties": {
    "addr:full":"Calle de Virgen, 5 Zarza Badajoz 06830",
    "addr:housenumber":"5",
    "addr:postcode":"06830",
    "addr:street":"Calle De Virgen",
    "iso:country":"ES",
    "sg:address":"Calle de Virgen, 5",
    "sg:city":"Zarza",
    "sg:orig_category":"Electrodom\u00c9sticos (al Por Menor)",
    "sg:phone":"+34 924 36 61 07",
    "sg:postcode":"06830",
    "sg:province":"Badajoz",
    "sg:website":"www.empresasyservicios.com",
    "wof:name":"Electricidad Y Fontaneria Casa Gutierrez C.b.",
    "wof:placetype":"venue"
},
  "geometry": {"coordinates":[-6.2205381393,38.8173179626],"type":"Point"}
}