{
  "type": "Feature",
  "properties": {
    "addr:full":"Calle de Bolivia (de), 3 Fuenlabrada Madrid 28945",
    "addr:housenumber":"3",
    "addr:postcode":"28945",
    "addr:street":"Calle De Bolivia De",
    "iso:country":"ES",
    "sg:address":"Calle de Bolivia (de), 3",
    "sg:city":"Fuenlabrada",
    "sg:orig_category":"Empresarios",
    "sg:phone":"+34 916 06 99 42",
    "sg:postcode":"28945",
    "sg:province":"Madrid",
    "wof:name":"Dapema Construcciones S.l.",
    "wof:placetype":"venue"
},
  "geometry": {"coordinates":[-3.7846770287,40.2861404419],"type":"Point"}
}