{
  "type": "Feature",
  "properties": {
    "addr:full":"Carrer de Riera Blanca, 14 Hospitalet Llobregat Barcelona 08903",
    "addr:housenumber":"14",
    "addr:postcode":"08903",
    "addr:street":"Carrer De Riera Blanca",
    "iso:country":"ES",
    "sg:address":"Carrer de Riera Blanca, 14",
    "sg:city":"Hospitalet Llobregat",
    "sg:orig_category":"M\u00c9dicos: An\u00c1lisis Cl\u00cdnicos",
    "sg:phone":"+34 934 40 71 51",
    "sg:postcode":"08903",
    "sg:province":"Barcelona",
    "wof:name":"Gonzalez Castro Urba",
    "wof:placetype":"venue"
},
  "geometry": {"coordinates":[2.1215031147,41.3764648438],"type":"Point"}
}