{
  "type": "Feature",
  "properties": {
    "iso:country":"ES",
    "sg:address":"Carrer de Ferrer De Pallares, 10",
    "sg:city":"Palma",
    "sg:orig_category":"Guarder\u00cdas",
    "sg:phone":"+34 971 27 16 53",
    "sg:postcode":"07007",
    "sg:province":"Islas Baleares",
    "wof:name":"Scubidu C.b.",
    "wof:placetype":"venue"
},
  "geometry": {"coordinates":[2.6700189114,39.572429657],"type":"Point"}
}