{
  "type": "Feature",
  "properties": {
    "addr:full":"Agrupacion Viv San Miguel, 3 Agoitz Navarra 31430",
    "addr:housenumber":"3",
    "addr:postcode":"31430",
    "addr:street":"San Miguel",
    "iso:country":"ES",
    "sg:address":"Agrupacion Viv San Miguel, 3",
    "sg:city":"Agoitz",
    "sg:orig_category":"Sociedades, Compa\u00d1\u00cdas Aseguradoras",
    "sg:phone":"+34 948 33 41 98",
    "sg:postcode":"31430",
    "sg:province":"Navarra",
    "wof:name":"Mapfre Servicios De Informatica",
    "wof:placetype":"venue"
},
  "geometry": {"coordinates":[-1.3729139566,42.7836151123],"type":"Point"}
}