{
  "type": "Feature",
  "properties": {
    "addr:full":"Martires Castillo Olite, 6 Fuente Alamo Murcia 30320",
    "addr:housenumber":"6",
    "addr:postcode":"30320",
    "addr:street":"Castillo Olite",
    "iso:country":"ES",
    "sg:address":"Martires Castillo Olite, 6",
    "sg:city":"Fuente Alamo",
    "sg:orig_category":"Cl\u00cdnicas Dentales",
    "sg:phone":"+34 968 59 75 80",
    "sg:postcode":"30320",
    "sg:province":"Murcia",
    "wof:name":"Batista Matos Esperanza",
    "wof:placetype":"venue"
},
  "geometry": {"coordinates":[-1.1687190533,37.7235946655],"type":"Point"}
}