{
  "type": "Feature",
  "properties": {
    "iso:country":"ES",
    "sg:address":"Baoto, S/n",
    "sg:city":"Tudela-veguin-box",
    "sg:orig_category":"Hormigonados",
    "sg:phone":"+34 985 78 81 24",
    "sg:postcode":"33910",
    "sg:province":"Asturias",
    "wof:name":"Hanson Hispania S.a.",
    "wof:placetype":"venue"
},
  "geometry": {"coordinates":[-5.7506370544,43.3397521973],"type":"Point"}
}