{
  "type": "Feature",
  "properties": {
    "addr:full":"Av Granvia, 144 Hospitalet Llobregat Barcelona 08902",
    "addr:housenumber":"144",
    "addr:postcode":"08902",
    "addr:street":"Av Granvia",
    "iso:country":"ES",
    "sg:address":"Av Granvia, 144",
    "sg:city":"Hospitalet Llobregat",
    "sg:orig_category":"Distribuci\u00d3n De Petr\u00d3leo Y Derivados",
    "sg:phone":"+34 933 36 01 52",
    "sg:postcode":"08902",
    "sg:province":"Barcelona",
    "wof:name":"Galpgest Petrogal Estaciones De Servicio S.l.u.",
    "wof:placetype":"venue"
},
  "geometry": {"coordinates":[2.1175599098,41.3517913818],"type":"Point"}
}