{
  "type": "Feature",
  "properties": {
    "iso:country":"ES",
    "sg:address":"Ctra Llano Quart, 58",
    "sg:city":"Aldaia",
    "sg:orig_category":"Muebles",
    "sg:phone":"+34 961 50 99 27",
    "sg:postcode":"46960",
    "sg:province":"Valencia",
    "wof:name":"Mesas Dumar S.l.",
    "wof:placetype":"venue"
},
  "geometry": {"coordinates":[-0.460878998,39.4649238586],"type":"Point"}
}