{
  "type": "Feature",
  "properties": {
    "iso:country":"ES",
    "sg:address":"Calle de Pio Baroja, 1",
    "sg:city":"Granada",
    "sg:orig_category":"Molduras, Junquillos, Listones Y Molduras Perforadas",
    "sg:phone":"+34 958 27 45 03",
    "sg:postcode":"18003",
    "sg:province":"Granada",
    "wof:name":"Trujillo Caravaca Juan Jesus",
    "wof:placetype":"venue"
},
  "geometry": {"coordinates":[-3.6112775803,37.1797294617],"type":"Point"}
}