{
  "type": "Feature",
  "properties": {
    "addr:full":"Calle de D. Roque Gorriz, 4 Puebla Valverde Teruel 44450",
    "addr:housenumber":"4",
    "addr:postcode":"44450",
    "addr:street":"Calle De D. Roque Gorriz",
    "iso:country":"ES",
    "sg:address":"Calle de D. Roque Gorriz, 4",
    "sg:city":"Puebla Valverde",
    "sg:classifiers":[
        {
            "category":"Taxi",
            "type":"Transportation"
        }
    ],
    "sg:phone":"+34 978 67 01 61",
    "sg:postcode":"44450",
    "sg:province":"Teruel",
    "wof:name":"Cercos Barea Alejandro",
    "wof:placetype":"venue"
},
  "geometry": {"coordinates":[-0.929713428,40.2251243591],"type":"Point"}
}