{
  "type": "Feature",
  "properties": {
    "addr:full":"Calle de Sol, 25 Plasencia C\u00e1ceres 10600",
    "addr:housenumber":"25",
    "addr:postcode":"10600",
    "addr:street":"Calle De Sol;Ca\u0301Ceres",
    "iso:country":"ES",
    "sg:address":"Calle de Sol, 25",
    "sg:city":"Plasencia",
    "sg:orig_category":"\u00d3ptica: Instrumentos (fabricaci\u00d3n)",
    "sg:phone":"+34 927 41 11 73",
    "sg:postcode":"10600",
    "sg:province":"C\u00e1ceres",
    "wof:name":"Alegre Lopez Manuel",
    "wof:placetype":"venue"
},
  "geometry": {"coordinates":[-6.088326931,40.0301628113],"type":"Point"}
}