{
  "type": "Feature",
  "properties": {
    "iso:country":"ES",
    "sg:address":"Calle de Arturo Campion, 30",
    "sg:city":"Donostia-san Sebastian",
    "sg:orig_category":"Garajes De Veh\u00cdculos",
    "sg:phone":"+34 943 31 01 37",
    "sg:postcode":"20018",
    "sg:province":"Guip\u00f9zcoa",
    "wof:name":"Beraza Jaunsaras Juan Jose",
    "wof:placetype":"venue"
},
  "geometry": {"coordinates":[-2.0149729252,43.3024787903],"type":"Point"}
}