{
  "type": "Feature",
  "properties": {
    "addr:full":"Calle de Doctor Pe\u00d1a, 4 San Martin Del Casta\u00e7ar Salamanca 37659",
    "addr:housenumber":"4",
    "addr:postcode":"37659",
    "addr:street":"Calle De Doctor Pen\u0303A;Martin",
    "iso:country":"ES",
    "sg:address":"Calle de Doctor Pe\u00d1a, 4",
    "sg:city":"San Martin Del Casta\u00e7ar",
    "sg:orig_category":"Carnicer\u00cdas, Carnicer\u00cdas",
    "sg:phone":"+34 923 43 73 26",
    "sg:postcode":"37659",
    "sg:province":"Salamanca",
    "wof:name":"Calvo Sanchez Ventura",
    "wof:placetype":"venue"
},
  "geometry": {"coordinates":[-6.0638837814,40.5211029053],"type":"Point"}
}