{
  "type": "Feature",
  "properties": {
    "iso:country":"ES",
    "sg:address":"Avda Condesa Sagasta, 30",
    "sg:city":"Le\u00f3n",
    "sg:orig_category":"Ortopedia General",
    "sg:phone":"+34 987 08 36 51",
    "sg:postcode":"24001",
    "sg:province":"Le\u00f3n",
    "wof:name":"Orto-gaudi S.l.",
    "wof:placetype":"venue"
},
  "geometry": {"coordinates":[-5.5800681114,42.5992584229],"type":"Point"}
}