{
  "type": "Feature",
  "properties": {
    "iso:country":"ES",
    "sg:address":"Pase Rollo, 75",
    "sg:city":"Salamanca",
    "sg:orig_category":"Peluqueros: De Se\u00d1oras",
    "sg:phone":"+34 923 18 54 54",
    "sg:postcode":"37003",
    "sg:province":"Salamanca",
    "wof:name":"Blanco Gonzalez Manuel",
    "wof:placetype":"venue"
},
  "geometry": {"coordinates":[-5.6496448517,40.9673118591],"type":"Point"}
}