{
  "type": "Feature",
  "properties": {
    "addr:full":"Calle de Federico De Mendizabal, 5 Jaen Ja\u00e9n 23001",
    "addr:housenumber":"5;jae\u0301n",
    "addr:postcode":"23001",
    "addr:street":"Calle De Federico De Mendizabal",
    "iso:country":"ES",
    "sg:address":"Calle de Federico De Mendizabal, 5",
    "sg:city":"Jaen",
    "sg:orig_category":"Cooperativas Agr\u00cdcolas",
    "sg:phone":"+34 953 24 50 91",
    "sg:postcode":"23001",
    "sg:province":"Ja\u00e9n",
    "wof:name":"Oleoxa Aceites De Jaen S.c.a.",
    "wof:placetype":"venue"
},
  "geometry": {"coordinates":[-3.7883520126,37.7683143616],"type":"Point"}
}