{
  "type": "Feature",
  "properties": {
    "iso:country":"ES",
    "sg:address":"Calle de Doctores Castroviejo, 10",
    "sg:city":"Calahorra",
    "sg:orig_category":"Sociedades, Compa\u00d1\u00cdas Aseguradoras",
    "sg:phone":"+34 941 14 74 27",
    "sg:postcode":"26500",
    "sg:province":"La Rioja",
    "wof:name":"Sarasa Lapuerta Jose Maria",
    "wof:placetype":"venue"
},
  "geometry": {"coordinates":[-1.9718199968,42.3080596924],"type":"Point"}
}