{
  "type": "Feature",
  "properties": {
    "iso:country":"ES",
    "sg:address":"Avda Ausias March, 46",
    "sg:city":"Alaquas",
    "sg:orig_category":"Molduras, Junquillos, Listones Y Molduras Perforadas",
    "sg:phone":"+34 961 51 77 98",
    "sg:postcode":"46970",
    "sg:province":"Valencia",
    "wof:name":"Molina Canis Pedro",
    "wof:placetype":"venue"
},
  "geometry": {"coordinates":[-0.4580059946,39.4546852112],"type":"Point"}
}