{
  "type": "Feature",
  "properties": {
    "addr:full":"Avda Estacion, 32 Santiago Ribera Murcia 30720",
    "addr:housenumber":"32",
    "addr:postcode":"30720",
    "addr:street":"Avda Estacion",
    "iso:country":"ES",
    "sg:address":"Avda Estacion, 32",
    "sg:city":"Santiago Ribera",
    "sg:orig_category":"Empresas De Carpinter\u00cda",
    "sg:phone":"+34 968 57 14 99",
    "sg:postcode":"30720",
    "sg:province":"Murcia",
    "sg:website":"www.jacema.com",
    "wof:name":"Jacema S. L.",
    "wof:placetype":"venue"
},
  "geometry": {"coordinates":[-0.8069189787,37.8014183044],"type":"Point"}
}