{
  "type": "Feature",
  "properties": {
    "addr:full":"Carrer de Muntaner, 260 Barcelona Barcelona 08021",
    "addr:housenumber":"260",
    "addr:postcode":"08021",
    "addr:street":"Carrer De Muntaner",
    "iso:country":"ES",
    "sg:address":"Carrer de Muntaner, 260",
    "sg:city":"Barcelona",
    "sg:orig_category":"Zapatos (al Por Menor)",
    "sg:phone":"+34 932 00 74 54",
    "sg:postcode":"08021",
    "sg:province":"Barcelona",
    "wof:name":"Fernandez Santos Luis",
    "wof:placetype":"venue"
},
  "geometry": {"coordinates":[2.1480679512,41.3954048157],"type":"Point"}
}