{
  "type": "Feature",
  "properties": {
    "addr:full":"Carrer de Santa Cristina, 8 Lloret Mar Girona 17310",
    "addr:housenumber":"8",
    "addr:postcode":"17310",
    "addr:street":"Carrer De Santa Cristina",
    "iso:country":"ES",
    "sg:address":"Carrer de Santa Cristina, 8",
    "sg:city":"Lloret Mar",
    "sg:orig_category":"Discotecas Y Salas De Baile",
    "sg:phone":"+34 972 36 49 48",
    "sg:postcode":"17310",
    "sg:province":"Girona",
    "wof:name":"Young  Graham Leslie",
    "wof:placetype":"venue"
},
  "geometry": {"coordinates":[2.846834898,41.6981697083],"type":"Point"}
}