{
  "type": "Feature",
  "properties": {
    "addr:full":"Poli Industrial San Valero, Km. 0004,8 Cartuja Baja Zaragoza 50720",
    "addr:postcode":"50720",
    "addr:street":"San Valero Km. 0004,8 Cartuja Baja",
    "iso:country":"ES",
    "sg:address":"Poli Industrial San Valero, Km. 0004,8",
    "sg:city":"Cartuja Baja",
    "sg:orig_category":"Persianas Interiores, Exteriores",
    "sg:phone":"+34 976 50 10 54",
    "sg:postcode":"50720",
    "sg:province":"Zaragoza",
    "sg:website":"www.toldospastor.com",
    "wof:name":"Carmelo Pastor Pina S.l.",
    "wof:placetype":"venue"
},
  "geometry": {"coordinates":[-0.8236089945,41.602935791],"type":"Point"}
}