{
  "type": "Feature",
  "properties": {
    "iso:country":"ES",
    "sg:address":"Po Enamorados, 43",
    "sg:city":"Iru\u00f1a",
    "sg:orig_category":"Electricidad Veh\u00cdculo",
    "sg:phone":"+34 948 14 76 60",
    "sg:postcode":"31014",
    "sg:province":"Navarra",
    "wof:name":"Ayarra Elia Agustin",
    "wof:placetype":"venue"
},
  "geometry": {"coordinates":[-1.6467219591,42.8252182007],"type":"Point"}
}