{
  "type": "Feature",
  "properties": {
    "iso:country":"ES",
    "sg:address":"Avda Perez Galdos, 16",
    "sg:city":"Logro\u00f1o",
    "sg:orig_category":"Ense\u00d1anza: Comercio, Gesti\u00d3n, Inform\u00c1tica",
    "sg:phone":"+34 941 24 78 91",
    "sg:postcode":"26002",
    "sg:province":"La Rioja",
    "wof:name":"Opc Informatica S.l.",
    "wof:placetype":"venue"
},
  "geometry": {"coordinates":[-2.4479510784,42.461391449],"type":"Point"}
}