{
  "type": "Feature",
  "properties": {
    "iso:country":"ES",
    "sg:address":"Pol Ind, 1",
    "sg:city":"Puerto Lumbreras",
    "sg:orig_category":"Persianas Interiores, Exteriores",
    "sg:phone":"+34 968 40 04 40",
    "sg:postcode":"30890",
    "sg:province":"Murcia",
    "wof:name":"Toldos Garcia S.l.",
    "wof:placetype":"venue"
},
  "geometry": {"coordinates":[-1.8125690222,37.5551490784],"type":"Point"}
}