{
  "type": "Feature",
  "properties": {
    "addr:full":"Av Can Fontanals, S/n Mira-sol Barcelona 08195",
    "addr:housenumber":"s / n",
    "addr:postcode":"08195",
    "addr:street":"Av Can Fontanals",
    "iso:country":"ES",
    "sg:address":"Av Can Fontanals, S/n",
    "sg:city":"Mira-sol",
    "sg:orig_category":"Maquinaria Para Industrias Diversas",
    "sg:phone":"+34 936 75 41 11",
    "sg:postcode":"08195",
    "sg:province":"Barcelona",
    "sg:website":"www.tma.es",
    "wof:name":"Tecnologia Medio Ambiente Grupo F.sanchez S.l.",
    "wof:placetype":"venue"
},
  "geometry": {"coordinates":[2.0623049736,41.4687767029],"type":"Point"}
}