{
  "type": "Feature",
  "properties": {
    "iso:country":"ES",
    "sg:address":"Calle de San Simon, 10",
    "sg:city":"Santander",
    "sg:orig_category":"Farmacias",
    "sg:phone":"+34 942 22 48 13",
    "sg:postcode":"39003",
    "sg:province":"Cantabria",
    "wof:name":"Azcona Sanchez Pedro Manuel",
    "wof:placetype":"venue"
},
  "geometry": {"coordinates":[-3.8024919033,43.4646606445],"type":"Point"}
}