{
  "type": "Feature",
  "properties": {
    "iso:country":"ES",
    "sg:address":"Plaz Constitucion, 4",
    "sg:city":"Higuera Real",
    "sg:orig_category":"Bancos",
    "sg:phone":"+34 924 72 33 29",
    "sg:postcode":"06350",
    "sg:province":"Badajoz",
    "sg:website":"www.gruposantander.es",
    "wof:name":"Bt Espa\u00d1a Compa\u00d1ia De Servicios Globales De Telecomunicaciones S.a.u.",
    "wof:placetype":"venue"
},
  "geometry": {"coordinates":[-6.6923351288,38.1417617798],"type":"Point"}
}