{
  "type": "Feature",
  "properties": {
    "addr:full":"Calle de Estacion, 24 Rozas De Madrid Madrid 28230",
    "addr:housenumber":"24",
    "addr:postcode":"28230",
    "addr:street":"Calle De Estacion",
    "iso:country":"ES",
    "sg:address":"Calle de Estacion, 24",
    "sg:city":"Rozas De Madrid",
    "sg:orig_category":"Desinfecci\u00d3n, Desinsectaci\u00d3n, Desratizaci\u00d3n",
    "sg:phone":"+34 916 37 58 87",
    "sg:postcode":"28230",
    "sg:province":"Madrid",
    "wof:name":"Sanimad Sanidad Ambiental S.l.",
    "wof:placetype":"venue"
},
  "geometry": {"coordinates":[-3.8692860603,40.4949684143],"type":"Point"}
}