{
  "type": "Feature",
  "properties": {
    "iso:country":"ES",
    "sg:address":"Calle de Mayor Principal, 8",
    "sg:city":"Palencia",
    "sg:orig_category":"Cajas De Ahorro",
    "sg:phone":"+34 979 70 64 73",
    "sg:postcode":"34001",
    "sg:province":"Palencia",
    "sg:website":"www.caixacatalunya.es",
    "wof:name":"Caixa D'estalvis De Catalunya",
    "wof:placetype":"venue"
},
  "geometry": {"coordinates":[-4.5392618179,42.010433197],"type":"Point"}
}