{
  "type": "Feature",
  "properties": {
    "iso:country":"ES",
    "sg:address":"Calle de Uruguay, S/n",
    "sg:city":"Alcantarilla",
    "sg:orig_category":"Delegados, Agentes De Tr\u00c1nsito, Auxiliares De Transporte Internacional",
    "sg:phone":"+34 968 83 60 30",
    "sg:postcode":"30820",
    "sg:province":"Murcia",
    "wof:name":"Tdn Murcia S.a.",
    "wof:placetype":"venue"
},
  "geometry": {"coordinates":[-1.1980240345,37.9597854614],"type":"Point"}
}