{
  "type": "Feature",
  "properties": {
    "iso:country":"ES",
    "sg:address":"Ctra San Vicente, 31",
    "sg:city":"Valle Trapaga",
    "sg:orig_category":"Impuestos, Tesoro P\u00dablico",
    "sg:phone":"+34 944 72 48 12",
    "sg:postcode":"48510",
    "sg:province":"Vizcaya",
    "wof:name":"L.r.peritos Tasadores S.l.",
    "wof:placetype":"venue"
},
  "geometry": {"coordinates":[-3.0191290379,43.2994880676],"type":"Point"}
}