{
  "type": "Feature",
  "properties": {
    "iso:country":"ES",
    "sg:address":"Calle de San Anton, 8",
    "sg:city":"Logro\u00f1o",
    "sg:orig_category":"Peleter\u00cdas",
    "sg:phone":"+34 941 24 29 97",
    "sg:postcode":"26002",
    "sg:province":"La Rioja",
    "wof:name":"Najarro Bartolome Maria Del Carmen",
    "wof:placetype":"venue"
},
  "geometry": {"coordinates":[-2.4470179081,42.4623565674],"type":"Point"}
}