{
  "type": "Feature",
  "properties": {
    "iso:country":"ES",
    "sg:address":"Calle de Atalfa, 2",
    "sg:city":"Puebla Montalban",
    "sg:orig_category":"Farmacias",
    "sg:phone":"+34 925 74 50 60",
    "sg:postcode":"45516",
    "sg:province":"Toledo",
    "wof:name":"Del Valle Perez Francisco Javier",
    "wof:placetype":"venue"
},
  "geometry": {"coordinates":[-4.3518972397,39.8687400818],"type":"Point"}
}