{
  "type": "Feature",
  "properties": {
    "addr:full":"Montenegro, 9 Lucena C\u00f3rdoba 14900",
    "addr:housenumber":"9",
    "addr:postcode":"14900",
    "addr:street":"Montenegro",
    "iso:country":"ES",
    "sg:address":"Montenegro, 9",
    "sg:city":"Lucena",
    "sg:orig_category":"Promotores Constructores",
    "sg:phone":"+34 957 50 12 13",
    "sg:postcode":"14900",
    "sg:province":"C\u00f3rdoba",
    "wof:name":"Proluc S.l.",
    "wof:placetype":"venue"
},
  "geometry": {"coordinates":[-4.4867172241,37.4092597961],"type":"Point"}
}