{
  "type": "Feature",
  "properties": {
    "addr:full":"Trva Carretera Villanueva, 26 Jerez De Los Caballeros Badajoz 06380",
    "addr:housenumber":"26",
    "addr:postcode":"06380",
    "addr:street":"Trva Carretera Villanueva",
    "iso:country":"ES",
    "sg:address":"Trva Carretera Villanueva, 26",
    "sg:city":"Jerez De Los Caballeros",
    "sg:orig_category":"Chapister\u00cda",
    "sg:phone":"+34 924 73 02 53",
    "sg:postcode":"06380",
    "sg:province":"Badajoz",
    "wof:name":"Barrio Labrador Manuel",
    "wof:placetype":"venue"
},
  "geometry": {"coordinates":[-6.7662930489,38.3218612671],"type":"Point"}
}