{
  "type": "Feature",
  "properties": {
    "addr:full":"Avda Jose Maria Alcaraz Y Alenda, S/n Badajoz Badajoz 06011",
    "addr:housenumber":"s / n",
    "addr:postcode":"06011",
    "addr:street":"Avda Jose Maria Alcaraz Y Alenda",
    "iso:country":"ES",
    "sg:address":"Avda Jose Maria Alcaraz Y Alenda, S/n",
    "sg:city":"Badajoz",
    "sg:orig_category":"Asociaciones Humanitarias, De Cooperaci\u00d3n, De Acci\u00d3n Social",
    "sg:phone":"+34 924 24 14 14",
    "sg:postcode":"06011",
    "sg:province":"Badajoz",
    "wof:name":"Aexpainba S.c.",
    "wof:placetype":"venue"
},
  "geometry": {"coordinates":[-6.9886050224,38.8688049316],"type":"Point"}
}