{
  "type": "Feature",
  "properties": {
    "addr:full":"Calle de Cruz (la), 9 Olivos-la Postura Santa Cruz De Tenerife 38670",
    "addr:housenumber":"9",
    "addr:postcode":"38670",
    "addr:street":"Calle De Cruz La",
    "iso:country":"ES",
    "sg:address":"Calle de Cruz (la), 9",
    "sg:city":"Olivos-la Postura",
    "sg:classifiers":[
        {
            "category":"Taxi",
            "type":"Transportation"
        }
    ],
    "sg:phone":"+34 922 78 08 76",
    "sg:postcode":"38670",
    "sg:province":"Santa Cruz De Tenerife",
    "wof:name":"Rodriguez Morales Jose",
    "wof:placetype":"venue"
},
  "geometry": {"coordinates":[-16.2548561096,28.4698104858],"type":"Point"}
}