{
  "type": "Feature",
  "properties": {
    "iso:country":"ES",
    "sg:address":"Calle de Saenz Laguna, 22",
    "sg:city":"Algeciras",
    "sg:orig_category":"Abogados",
    "sg:phone":"+34 956 63 48 26",
    "sg:postcode":"11201",
    "sg:province":"C\u00e1diz",
    "wof:name":"Polonio Pedraza Rosa Maria",
    "wof:placetype":"venue"
},
  "geometry": {"coordinates":[-5.4474921227,36.1328430176],"type":"Point"}
}