{
  "type": "Feature",
  "properties": {
    "iso:country":"ES",
    "sg:address":"Calle de Rio Algar, 14",
    "sg:city":"Fanadix",
    "sg:orig_category":"Agencias Y Agentes Comerciales, Representantes",
    "sg:phone":"+34 965 74 83 01",
    "sg:postcode":"03725",
    "sg:province":"Alicante",
    "wof:name":"Matthews  Stephen Anthony",
    "wof:placetype":"venue"
},
  "geometry": {"coordinates":[0.1124000996,38.6876983643],"type":"Point"}
}