{
  "type": "Feature",
  "properties": {
    "iso:country":"ES",
    "sg:address":"C/ Cami Dels Magros, 85",
    "sg:city":"Elche",
    "sg:orig_category":"Caf\u00c9s, Bares, Cervecer\u00cdas",
    "sg:phone":"+34 966 66 06 70",
    "sg:postcode":"03206",
    "sg:province":"Alicante",
    "wof:name":"Rada Business S.l.",
    "wof:placetype":"venue"
},
  "geometry": {"coordinates":[-0.7047759891,38.2742538452],"type":"Point"}
}