{
  "type": "Feature",
  "properties": {
    "iso:country":"ES",
    "sg:address":"Calle de Martin Cansado, 5",
    "sg:city":"Badajoz",
    "sg:orig_category":"Panader\u00cdas, Panader\u00cdas",
    "sg:phone":"+34 924 22 12 54",
    "sg:postcode":"06002",
    "sg:province":"Badajoz",
    "wof:name":"Perez Rodriguez Alvaro",
    "wof:placetype":"venue"
},
  "geometry": {"coordinates":[-6.9701228142,38.8770446777],"type":"Point"}
}