{
  "type": "Feature",
  "properties": {
    "addr:full":"Calle de Manuel Lasala, 44 Zaragoza Zaragoza 50006",
    "addr:housenumber":"44",
    "addr:postcode":"50006",
    "addr:street":"Calle De Manuel Lasala",
    "iso:country":"ES",
    "sg:address":"Calle de Manuel Lasala, 44",
    "sg:city":"Zaragoza",
    "sg:orig_category":"Arquitectos",
    "sg:phone":"+34 976 46 73 17",
    "sg:postcode":"50006",
    "sg:province":"Zaragoza",
    "wof:name":"B.pestana & Asociados S.l.",
    "wof:placetype":"venue"
},
  "geometry": {"coordinates":[-0.8974320292,41.6376838684],"type":"Point"}
}