{
  "type": "Feature",
  "properties": {
    "addr:full":"Ctra. Herrera, 10 Puente-genil C\u00f3rdoba 14500",
    "addr:housenumber":"10",
    "addr:postcode":"14500",
    "addr:street":"Ctra. Herrera;Co\u0301Rdoba",
    "iso:country":"ES",
    "sg:address":"Ctra. Herrera, 10",
    "sg:city":"Puente-genil",
    "sg:orig_category":"Fabricaci\u00d3n De Peines Y De Accesorios De Peluquer\u00cda",
    "sg:phone":"+34 957 60 55 47",
    "sg:postcode":"14500",
    "sg:province":"C\u00f3rdoba",
    "wof:name":"Almacenes Lince S.l.",
    "wof:placetype":"venue"
},
  "geometry": {"coordinates":[-4.781607151,37.3792953491],"type":"Point"}
}