{
  "type": "Feature",
  "properties": {
    "addr:full":"Avda Europa, S/n Benidorm Alicante 03500",
    "addr:housenumber":"s / n",
    "addr:postcode":"03500",
    "addr:street":"Avda Europa",
    "iso:country":"ES",
    "sg:address":"Avda Europa, S/n",
    "sg:city":"Benidorm",
    "sg:orig_category":"Cr\u00cda De Animales",
    "sg:phone":"+34 965 85 32 96",
    "sg:postcode":"03500",
    "sg:province":"Alicante",
    "wof:name":"Jaen Gallego Fernando",
    "wof:placetype":"venue"
},
  "geometry": {"coordinates":[-0.1202159971,38.5427055359],"type":"Point"}
}