{
  "type": "Feature",
  "properties": {
    "addr:full":"Pla\u00c7 Catalunya, 8 Girona Girona 17002",
    "addr:housenumber":"8",
    "addr:postcode":"17002",
    "iso:country":"ES",
    "sg:address":"Pla\u00c7 Catalunya, 8",
    "sg:city":"Girona",
    "sg:orig_category":"\u00d3ptica: Instrumentos (fabricaci\u00d3n)",
    "sg:phone":"+34 972 20 42 28",
    "sg:postcode":"17002",
    "sg:province":"Girona",
    "wof:name":"Carrer Barcelona Vintidos S.l.",
    "wof:placetype":"venue"
},
  "geometry": {"coordinates":[2.8187448978,41.9808616638],"type":"Point"}
}