{
  "type": "Feature",
  "properties": {
    "iso:country":"ES",
    "sg:address":"Calle de Campo, 37",
    "sg:city":"Tomelloso",
    "sg:orig_category":"Distribuci\u00d3n De Petr\u00d3leo Y Derivados",
    "sg:phone":"+34 926 50 50 44",
    "sg:postcode":"13700",
    "sg:province":"Ciudad Real",
    "wof:name":"Gasoleos Sanchez Y Murcia S.l.",
    "wof:placetype":"venue"
},
  "geometry": {"coordinates":[-3.0222806931,39.1602630615],"type":"Point"}
}