{
  "type": "Feature",
  "properties": {
    "addr:full":"Plaz Carballo, 9 Madrid Madrid 28029",
    "addr:housenumber":"9",
    "addr:postcode":"madrid;28029",
    "addr:street":"Plaz Carballo",
    "iso:country":"ES",
    "sg:address":"Plaz Carballo, 9",
    "sg:city":"Madrid",
    "sg:orig_category":"Negocio De Materiales De Construcci\u00d3n",
    "sg:phone":"+34 917 30 39 38",
    "sg:postcode":"28029",
    "sg:province":"Madrid",
    "wof:name":"Portela Martin Epifanio",
    "wof:placetype":"venue"
},
  "geometry": {"coordinates":[-3.7049229145,40.4770088196],"type":"Point"}
}