{
  "type": "Feature",
  "properties": {
    "addr:full":"Poli Poligon Industrial, S/n Picassent Valencia 46220",
    "addr:postcode":"46220",
    "addr:street":"Industrial S / N",
    "iso:country":"ES",
    "sg:address":"Poli Poligon Industrial, S/n",
    "sg:city":"Picassent",
    "sg:orig_category":"Confecci\u00d3n De Trajes Para Se\u00d1oras",
    "sg:phone":"+34 961 22 16 40",
    "sg:postcode":"46220",
    "sg:province":"Valencia",
    "wof:name":"Bluei Blouze S.l.",
    "wof:placetype":"venue"
},
  "geometry": {"coordinates":[-0.4524689913,39.3585700989],"type":"Point"}
}