{
  "type": "Feature",
  "properties": {
    "addr:full":"Calle de San Juan (de), 22 Fuenlabrada Madrid 28946",
    "addr:housenumber":"22",
    "addr:postcode":"28946",
    "addr:street":"Calle De San Juan De",
    "iso:country":"ES",
    "sg:address":"Calle de San Juan (de), 22",
    "sg:city":"Fuenlabrada",
    "sg:orig_category":"Artes Gr\u00c1ficas, Artes Pl\u00c1sticas (curso)",
    "sg:phone":"+34 916 15 37 74",
    "sg:postcode":"28946",
    "sg:province":"Madrid",
    "wof:name":"Iberica Grafic S.a.",
    "wof:placetype":"venue"
},
  "geometry": {"coordinates":[-3.7752048969,40.281452179],"type":"Point"}
}