{
  "type": "Feature",
  "properties": {
    "addr:full":"Carr Volta, S/n Palamos Girona 17230",
    "addr:housenumber":"s / n",
    "addr:postcode":"17230",
    "addr:street":"Carr Volta",
    "iso:country":"ES",
    "sg:address":"Carr Volta, S/n",
    "sg:city":"Palamos",
    "sg:orig_category":"Institutos De Belleza",
    "sg:phone":"+34 972 60 03 16",
    "sg:postcode":"17230",
    "sg:province":"Girona",
    "wof:name":"Baeza Duque Josefina",
    "wof:placetype":"venue"
},
  "geometry": {"coordinates":[3.130095005,41.8461685181],"type":"Point"}
}