{
  "type": "Feature",
  "properties": {
    "iso:country":"ES",
    "sg:address":"Carrer de Jacint Verdaguer, 24",
    "sg:city":"Vic",
    "sg:orig_category":"Cl\u00cdnicas Dentales",
    "sg:phone":"+34 938 89 42 02",
    "sg:postcode":"08500",
    "sg:province":"Barcelona",
    "wof:name":"Costa Palau Santiago",
    "wof:placetype":"venue"
},
  "geometry": {"coordinates":[2.2513120174,41.9308242798],"type":"Point"}
}