{
  "type": "Feature",
  "properties": {
    "iso:country":"ES",
    "sg:address":"Ctra Menarguens (de), S/n",
    "sg:city":"Balaguer",
    "sg:orig_category":"Agricultura: Abastecimiento Y Cosechado (negocio)",
    "sg:phone":"+34 973 44 61 17",
    "sg:postcode":"25600",
    "sg:province":"Lleida",
    "wof:name":"Espar Tico Josep",
    "wof:placetype":"venue"
},
  "geometry": {"coordinates":[0.8020899892,41.7799301147],"type":"Point"}
}