{
  "type": "Feature",
  "properties": {
    "iso:country":"ES",
    "sg:address":"Carr Sor Elena Bouzas, 5",
    "sg:city":"Betera",
    "sg:orig_category":"Pod\u00d3logos: Pedicuros",
    "sg:phone":"+34 961 69 20 43",
    "sg:postcode":"46117",
    "sg:province":"Valencia",
    "wof:name":"Gimenez Lopez Rosana",
    "wof:placetype":"venue"
},
  "geometry": {"coordinates":[-0.4646939933,39.5906906128],"type":"Point"}
}