{
  "type": "Feature",
  "properties": {
    "addr:full":"Calle de Zaragoza, S/n Garrapinillos Zaragoza 50190",
    "addr:postcode":"50190",
    "addr:street":"Calle De Zaragoza S / N Garrapinillos",
    "iso:country":"ES",
    "sg:address":"Calle de Zaragoza, S/n",
    "sg:city":"Garrapinillos",
    "sg:orig_category":"Mec\u00c1nico Del Autom\u00d3vil",
    "sg:phone":"+34 976 78 03 68",
    "sg:postcode":"50190",
    "sg:province":"Zaragoza",
    "wof:name":"Escribano Miranda Antonio",
    "wof:placetype":"venue"
},
  "geometry": {"coordinates":[-1.0262379646,41.6826438904],"type":"Point"}
}