{
  "type": "Feature",
  "properties": {
    "iso:country":"ES",
    "sg:address":"Avda Do\u00d1a Urraca, 25",
    "sg:city":"Salamanca",
    "sg:orig_category":"Institutos De Belleza",
    "sg:phone":"+34 923 12 14 94",
    "sg:postcode":"37005",
    "sg:province":"Salamanca",
    "wof:name":"Santos Plaza Mercedes",
    "wof:placetype":"venue"
},
  "geometry": {"coordinates":[-5.6578388214,40.9752655029],"type":"Point"}
}