{
  "type": "Feature",
  "properties": {
    "iso:country":"ES",
    "sg:address":"Calle de Mayor, 256",
    "sg:city":"Alcantarilla",
    "sg:orig_category":"Transporte En General",
    "sg:phone":"+34 968 80 11 46",
    "sg:postcode":"30820",
    "sg:province":"Murcia",
    "wof:name":"Belmonte Alarcos Agustin",
    "wof:placetype":"venue"
},
  "geometry": {"coordinates":[-1.2216180563,37.9646263123],"type":"Point"}
}