{
  "type": "Feature",
  "properties": {
    "addr:full":"Carrer de Josep Maria Prous I Vila, 34 Reus Tarragona 43205",
    "addr:housenumber":"34",
    "addr:postcode":"43205",
    "addr:street":"Carrer De Josep Maria Prous;Vila",
    "iso:country":"ES",
    "sg:address":"Carrer de Josep Maria Prous I Vila, 34",
    "sg:city":"Reus",
    "sg:orig_category":"Chapister\u00cda",
    "sg:phone":"+34 977 75 03 08",
    "sg:postcode":"43205",
    "sg:province":"Tarragona",
    "wof:name":"Planchisteria Reus S.c.p.",
    "wof:placetype":"venue"
},
  "geometry": {"coordinates":[1.1088080406,41.1491775513],"type":"Point"}
}