{
  "type": "Feature",
  "properties": {
    "addr:full":"Ctr. Puertollano, 5 Aldea Rey Ciudad Real 13380",
    "addr:housenumber":"5",
    "addr:postcode":"13380",
    "addr:street":"Puertollano;Real",
    "iso:country":"ES",
    "sg:address":"Ctr. Puertollano, 5",
    "sg:city":"Aldea Rey",
    "sg:orig_category":"Cr\u00cda De Cerdos",
    "sg:phone":"+34 926 86 56 83",
    "sg:postcode":"13380",
    "sg:province":"Ciudad Real",
    "wof:name":"Villalon Benitez Valentin",
    "wof:placetype":"venue"
},
  "geometry": {"coordinates":[-3.8383390903,38.7374916077],"type":"Point"}
}