{
  "type": "Feature",
  "properties": {
    "iso:country":"ES",
    "sg:address":"Calle de Caballeros, 3",
    "sg:city":"Valencia",
    "sg:orig_category":"Trajes Y Adornos De Boda (confecci\u00d3n, Al Por Menor)",
    "sg:phone":"+34 963 91 29 05",
    "sg:postcode":"46001",
    "sg:province":"Valencia",
    "wof:name":"Cabrera Tormo Jose",
    "wof:placetype":"venue"
},
  "geometry": {"coordinates":[-0.3767490089,39.4765815735],"type":"Point"}
}