{
  "type": "Feature",
  "properties": {
    "iso:country":"ES",
    "sg:address":"Avda Madrid (de), 18",
    "sg:city":"Valdemoro",
    "sg:orig_category":"Empresas De Pintura Y Revestimientos",
    "sg:phone":"+34 918 08 25 63",
    "sg:postcode":"28340",
    "sg:province":"Madrid",
    "wof:name":"Santos Lopez Pedro Alfonso",
    "wof:placetype":"venue"
},
  "geometry": {"coordinates":[-3.6842870712,40.2111625671],"type":"Point"}
}