{
  "type": "Feature",
  "properties": {
    "iso:country":"ES",
    "sg:address":"Calle de Gran Via, 51",
    "sg:city":"Madrid",
    "sg:orig_category":"Ropa Para Ni\u00d1os (al Por Menor)",
    "sg:phone":"+34 915 59 75 42",
    "sg:postcode":"28013",
    "sg:province":"Madrid",
    "sg:website":"www.kwaleon.com",
    "wof:name":"Kwaleon S.l.",
    "wof:placetype":"venue"
},
  "geometry": {"coordinates":[-3.7079091072,40.4213218689],"type":"Point"}
}