{
  "type": "Feature",
  "properties": {
    "addr:full":"Calle de Calera, 42 Talavera Reina Toledo 45600",
    "addr:housenumber":"42",
    "addr:postcode":"45600",
    "addr:street":"Calle De Calera",
    "iso:country":"ES",
    "sg:address":"Calle de Calera, 42",
    "sg:city":"Talavera Reina",
    "sg:orig_category":"Mec\u00c1nico Del Autom\u00d3vil",
    "sg:phone":"+34 925 80 72 65",
    "sg:postcode":"45600",
    "sg:province":"Toledo",
    "wof:name":"Talleres Pierre Y Andres S.l.",
    "wof:placetype":"venue"
},
  "geometry": {"coordinates":[-4.8429160118,39.9564704895],"type":"Point"}
}