{
  "type": "Feature",
  "properties": {
    "addr:full":"Carretera Cuenca, S/n Valdeca\u00d1as Cuenca 16846",
    "addr:housenumber":"s",
    "addr:postcode":"16846",
    "addr:street":"Carretera Cuenca;/ N Valdecan\u0303As",
    "iso:country":"ES",
    "sg:address":"Carretera Cuenca, S/n",
    "sg:city":"Valdeca\u00d1as",
    "sg:orig_category":"Restaurantes",
    "sg:phone":"+34 969 27 00 64",
    "sg:postcode":"16846",
    "sg:province":"Cuenca",
    "wof:name":"Asociacion Para El Desarrollo De Pueblos En Extincion,s.a.",
    "wof:placetype":"venue"
},
  "geometry": {"coordinates":[-2.3343355656,40.2270126343],"type":"Point"}
}