{
  "type": "Feature",
  "properties": {
    "iso:country":"ES",
    "sg:address":"Av Alacant, 22",
    "sg:city":"Elche",
    "sg:orig_category":"Inmobiliaria (agencias)",
    "sg:phone":"+34 966 61 30 43",
    "sg:postcode":"03203",
    "sg:province":"Alicante",
    "sg:website":"www.habitel.com",
    "wof:name":"Habitel Inmobiliarios S.l.",
    "wof:placetype":"venue"
},
  "geometry": {"coordinates":[-0.6859980226,38.2686386108],"type":"Point"}
}