{
  "type": "Feature",
  "properties": {
    "iso:country":"ES",
    "sg:address":"Calle de Pilar (el), 2",
    "sg:city":"Molar",
    "sg:orig_category":"Bricolaje, Herramientas (al Por Menor)",
    "sg:phone":"+34 918 41 21 58",
    "sg:postcode":"28710",
    "sg:province":"Madrid",
    "wof:name":"Escarate Martino Jose Benito",
    "wof:placetype":"venue"
},
  "geometry": {"coordinates":[-3.581056118,40.7363166809],"type":"Point"}
}