{
  "type": "Feature",
  "properties": {
    "iso:country":"ES",
    "sg:address":"Avda Doctor Rodriguez Mi\u00d1on, 15",
    "sg:city":"Sotillo Adrada",
    "sg:orig_category":"Fabricaci\u00d3n De Muebles",
    "sg:phone":"+34 918 66 80 24",
    "sg:postcode":"05420",
    "sg:province":"\u00c1vila",
    "wof:name":"Muebles Jugar 2001 C.b.",
    "wof:placetype":"venue"
},
  "geometry": {"coordinates":[-4.5896468163,40.2908287048],"type":"Point"}
}