{
  "type": "Feature",
  "properties": {
    "iso:country":"ES",
    "sg:address":"Calle de Merced, 34",
    "sg:city":"Jerez De La Frontera",
    "sg:orig_category":"Asociaciones, Organismos Culturales Y Socioeducativos",
    "sg:phone":"+34 956 33 51 32",
    "sg:postcode":"11404",
    "sg:province":"C\u00e1diz",
    "wof:name":"Hermandad De Transportes",
    "wof:placetype":"venue"
},
  "geometry": {"coordinates":[-6.1455421448,36.6870536804],"type":"Point"}
}