{
  "type": "Feature",
  "properties": {
    "addr:full":"Ptda Cachapet, S/n Crevillente Alicante 03330",
    "addr:housenumber":"s / n",
    "addr:postcode":"03330",
    "addr:street":"Ptda Cachapet",
    "iso:country":"ES",
    "sg:address":"Ptda Cachapet, S/n",
    "sg:city":"Crevillente",
    "sg:orig_category":"Fabricaci\u00d3n De Sobres, Bolsas Y Fundas",
    "sg:phone":"+34 965 40 26 52",
    "sg:postcode":"03330",
    "sg:province":"Alicante",
    "wof:name":"Inillopir S.l.",
    "wof:placetype":"venue"
},
  "geometry": {"coordinates":[-0.8163840175,38.2342567444],"type":"Point"}
}