{
  "type": "Feature",
  "properties": {
    "iso:country":"ES",
    "sg:address":"Carretera De Espeluy, S/n",
    "sg:city":"Mengibar",
    "sg:orig_category":"Fabrica De Charcuter\u00cda",
    "sg:phone":"+34 953 37 07 50",
    "sg:postcode":"23620",
    "sg:province":"Ja\u00e9n",
    "wof:name":"Hijos De Reyes Perez S.l.",
    "wof:placetype":"venue"
},
  "geometry": {"coordinates":[-3.812792778,37.9714012146],"type":"Point"}
}