{
  "type": "Feature",
  "properties": {
    "addr:full":"Avda Castellon, Km. 0007,6 Almazora Castell\u00f3n 12550",
    "addr:postcode":"12550",
    "addr:street":"Avda Castellon Km. 0007,6;Castello\u0301N",
    "iso:country":"ES",
    "sg:address":"Avda Castellon, Km. 0007,6",
    "sg:city":"Almazora",
    "sg:orig_category":"Arboricultura Y Producci\u00d3n De Frutas",
    "sg:phone":"+34 964 56 25 55",
    "sg:postcode":"12550",
    "sg:province":"Castell\u00f3n",
    "wof:name":"Peris Agost Hermanos S. L.",
    "wof:placetype":"venue"
},
  "geometry": {"coordinates":[-0.0631740019,39.9439582825],"type":"Point"}
}