{
  "type": "Feature",
  "properties": {
    "addr:full":"Avgd Prat De La Riba, 16 Lleida Lleida 25004",
    "addr:housenumber":"16",
    "addr:postcode":"25004",
    "addr:street":"La Riba",
    "iso:country":"ES",
    "sg:address":"Avgd Prat De La Riba, 16",
    "sg:city":"Lleida",
    "sg:orig_category":"Perfumer\u00cda (al Por Menor)",
    "sg:phone":"+34 973 23 23 65",
    "sg:postcode":"25004",
    "sg:province":"Lleida",
    "wof:name":"Comercial Caus S. A.",
    "wof:placetype":"venue"
},
  "geometry": {"coordinates":[0.6203650236,41.6195259094],"type":"Point"}
}