{
  "type": "Feature",
  "properties": {
    "iso:country":"ES",
    "sg:address":"Calle de Alamillos, 16",
    "sg:city":"Montilla",
    "sg:orig_category":"Heladeros",
    "sg:phone":"+34 957 65 11 99",
    "sg:postcode":"14550",
    "sg:province":"C\u00f3rdoba",
    "wof:name":"Cabello Garcia Antonio",
    "wof:placetype":"venue"
},
  "geometry": {"coordinates":[-4.640712738,37.5903396606],"type":"Point"}
}