{
  "type": "Feature",
  "properties": {
    "iso:country":"ES",
    "sg:address":"Calle de Comercio, 5",
    "sg:city":"Madrid",
    "sg:classifiers":[
        {
            "category":"Arts & Performance",
            "subcategory":"Art Gallery",
            "type":"Entertainment"
        }
    ],
    "sg:phone":"+34 915 01 86 43",
    "sg:postcode":"28007",
    "sg:province":"Madrid",
    "sg:tags":[
        "obras",
        "de",
        "coleccionismo",
        "compraventa",
        "arte",
        "y"
    ],
    "sg:website":"www.picassomio.com",
    "wof:name":"Picassomio Gallery S.l.",
    "wof:placetype":"venue"
},
  "geometry": {"coordinates":[-3.6817502975,40.4029006958],"type":"Point"}
}