{
  "type": "Feature",
  "properties": {
    "addr:full":"Calle de Duque De Sevilla, 3 Madrid Madrid 28...",
    "addr:housenumber":"3;28 ...",
    "addr:street":"Calle De Duque De Sevilla;Madrid",
    "iso:country":"ES",
    "sg:address":"Calle de Duque De Sevilla, 3",
    "sg:city":"Madrid",
    "sg:orig_category":"Agencias Y Asesores De Publicidad",
    "sg:phone":"+34 915 90 50 00",
    "sg:postcode":"28...",
    "sg:province":"Madrid",
    "wof:name":"Vitrubio Leo Burnett S.a.",
    "wof:placetype":"venue"
},
  "geometry": {"coordinates":[-3.6795840263,40.4419937134],"type":"Point"}
}