{
  "type": "Feature",
  "properties": {
    "iso:country":"ES",
    "sg:address":"Urb. Los Brezos, 22",
    "sg:city":"La Alcaidesa",
    "sg:orig_category":"Art\u00cdculos De Limpieza Y De Cocina (fabricaci\u00d3n, Al Por Mayor)",
    "sg:phone":"+34 956 79 13 38",
    "sg:postcode":"11311",
    "sg:province":"C\u00e1diz",
    "wof:name":"Absorbentes Espa\u00d1oles S.l.",
    "wof:placetype":"venue"
},
  "geometry": {"coordinates":[-5.319337,36.234371],"type":"Point"}
}