{
  "type": "Feature",
  "properties": {
    "addr:full":"Calle de Periodistas Cepeda, 4 Oviedo Asturias 33013",
    "addr:housenumber":"4",
    "addr:postcode":"33013",
    "addr:street":"Calle De Periodistas Cepeda",
    "iso:country":"ES",
    "sg:address":"Calle de Periodistas Cepeda, 4",
    "sg:city":"Oviedo",
    "sg:orig_category":"Empresas De Carpinter\u00cda De Madera",
    "sg:phone":"+34 985 24 39 37",
    "sg:postcode":"33013",
    "sg:province":"Asturias",
    "wof:name":"Fernandez Tain Armando",
    "wof:placetype":"venue"
},
  "geometry": {"coordinates":[-5.873939991,43.3644447327],"type":"Point"}
}