{
  "type": "Feature",
  "properties": {
    "addr:full":"Cpjo S. Enrique, S/n Torremolinos M\u00e1laga 29620",
    "addr:housenumber":"/ n",
    "addr:postcode":"29620",
    "addr:street":"Cpjo;Enrique S;Ma\u0301Laga",
    "iso:country":"ES",
    "sg:address":"Cpjo S. Enrique, S/n",
    "sg:city":"Torremolinos",
    "sg:orig_category":"Reciclaje Y Tratamiento De Desechos Varios",
    "sg:phone":"+34 952 37 18 73",
    "sg:postcode":"29620",
    "sg:province":"M\u00e1laga",
    "wof:name":"Melwani  Anup Ramchand",
    "wof:placetype":"venue"
},
  "geometry": {"coordinates":[-4.4998540878,36.6244087219],"type":"Point"}
}