{
  "type": "Feature",
  "properties": {
    "addr:full":"Pg Espronceda, 36 Sabadell Barcelona 08204",
    "addr:housenumber":"36",
    "addr:postcode":"08204",
    "addr:street":"Pg Espronceda",
    "iso:country":"ES",
    "sg:address":"Pg Espronceda, 36",
    "sg:city":"Sabadell",
    "sg:orig_category":"Loter\u00cda Y T\u00d3mbola",
    "sg:phone":"+34 937 10 00 84",
    "sg:postcode":"08204",
    "sg:province":"Barcelona",
    "wof:name":"Montalvo Aguilera Hermogenes",
    "wof:placetype":"venue"
},
  "geometry": {"coordinates":[2.1159830093,41.5288467407],"type":"Point"}
}