{
  "type": "Feature",
  "properties": {
    "iso:country":"ES",
    "sg:address":"Carr Vicente Cuervo, 19",
    "sg:city":"Eivissa",
    "sg:orig_category":"Electrodom\u00c9sticos (al Por Menor)",
    "sg:phone":"+34 971 31 19 67",
    "sg:postcode":"07800",
    "sg:province":"Islas Baleares",
    "wof:name":"Ferrer Guasch Pedro",
    "wof:placetype":"venue"
},
  "geometry": {"coordinates":[1.4337899685,38.9086494446],"type":"Point"}
}