{
  "type": "Feature",
  "properties": {
    "addr:full":"Carr Vicari Pastor, De, 7 Soller Islas Baleares 07100",
    "addr:housenumber":"7",
    "addr:postcode":"07100",
    "addr:street":"Carr Vicari Pastor De",
    "iso:country":"ES",
    "sg:address":"Carr Vicari Pastor, De, 7",
    "sg:city":"Soller",
    "sg:orig_category":"Confiter\u00cdas, Chocolater\u00cdas (al Por Menor)",
    "sg:phone":"+34 971 63 19 73",
    "sg:postcode":"07100",
    "sg:province":"Islas Baleares",
    "wof:name":"Marroig Bennassar Maria Magdalena",
    "wof:placetype":"venue"
},
  "geometry": {"coordinates":[2.7145121098,39.7660636902],"type":"Point"}
}