{
  "type": "Feature",
  "properties": {
    "iso:country":"ES",
    "sg:address":"Calle de Mayor, 33",
    "sg:city":"Almaden",
    "sg:orig_category":"Muebles",
    "sg:phone":"+34 926 71 02 85",
    "sg:postcode":"13400",
    "sg:province":"Ciudad Real",
    "wof:name":"Muebles Medina",
    "wof:placetype":"venue"
},
  "geometry": {"coordinates":[-4.8351559639,38.7758483887],"type":"Point"}
}