{
  "type": "Feature",
  "properties": {
    "addr:full":"Calle de Ramon De La Sagra, 14 Coru\u00d1a La Coru\u00f1a 15005",
    "addr:housenumber":"14",
    "addr:postcode":"15005",
    "addr:street":"Calle De Ramon De La Sagra;La Corun\u0303A",
    "iso:country":"ES",
    "sg:address":"Calle de Ramon De La Sagra, 14",
    "sg:city":"Coru\u00d1a",
    "sg:orig_category":"Institutos De Belleza",
    "sg:phone":"+34 981 23 79 03",
    "sg:postcode":"15005",
    "sg:province":"La Coru\u00f1a",
    "wof:name":"Blanco Chao Ana Maria",
    "wof:placetype":"venue"
},
  "geometry": {"coordinates":[-8.4061880112,43.3610229492],"type":"Point"}
}