{
  "type": "Feature",
  "properties": {
    "addr:full":"Calle de Gazaperas (de), 10 Fuenlabrada Madrid 28944",
    "addr:housenumber":"10",
    "addr:postcode":"28944",
    "addr:street":"Calle De Gazaperas De",
    "iso:country":"ES",
    "sg:address":"Calle de Gazaperas (de), 10",
    "sg:city":"Fuenlabrada",
    "sg:orig_category":"Inmobiliaria (agencias)",
    "sg:phone":"+34 916 90 69 44",
    "sg:postcode":"28944",
    "sg:province":"Madrid",
    "wof:name":"Desarrollo Inmobiliario De Fuenlabrada S.l.",
    "wof:placetype":"venue"
},
  "geometry": {"coordinates":[-3.8025159836,40.2750778198],"type":"Point"}
}