{
  "type": "Feature",
  "properties": {
    "iso:country":"ES",
    "sg:address":"Plaz Lonja (la), 5",
    "sg:city":"Gerena",
    "sg:orig_category":"Servicios Gsm",
    "sg:phone":"+34 955 78 28 30",
    "sg:postcode":"41860",
    "sg:province":"Sevilla",
    "wof:name":"Marin Leal Miguel Angel",
    "wof:placetype":"venue"
},
  "geometry": {"coordinates":[-6.1572999954,37.5256385803],"type":"Point"}
}