{
  "type": "Feature",
  "properties": {
    "addr:full":"Calle de Lisboa, S/n Malaga M\u00e1laga 29006",
    "addr:housenumber":"s",
    "addr:postcode":"29006",
    "addr:street":"Calle De Lisboa;/ N;Ma\u0301Laga",
    "iso:country":"ES",
    "sg:address":"Calle de Lisboa, S/n",
    "sg:city":"Malaga",
    "sg:orig_category":"Carnes De Carnicer\u00cda (al Por Mayor)",
    "sg:phone":"+34 952 34 97 50",
    "sg:postcode":"29006",
    "sg:province":"M\u00e1laga",
    "wof:name":"Frimancha Industrias Carnicas S.a.",
    "wof:placetype":"venue"
},
  "geometry": {"coordinates":[-4.4738388062,36.7026405334],"type":"Point"}
}