{
  "type": "Feature",
  "properties": {
    "addr:full":"Calle de San Juan De Dios, 28 Granada Granada 18001",
    "addr:housenumber":"28",
    "addr:postcode":"18001",
    "addr:street":"Calle De San Juan;Dios",
    "iso:country":"ES",
    "sg:address":"Calle de San Juan De Dios, 28",
    "sg:city":"Granada",
    "sg:orig_category":"Transportes Por Carretera: Lotes Completos, Mercanc\u00cdas Diversas",
    "sg:phone":"+34 958 20 03 83",
    "sg:postcode":"18001",
    "sg:province":"Granada",
    "wof:name":"Divercapricho Distribuciones S.l.",
    "wof:placetype":"venue"
},
  "geometry": {"coordinates":[-3.6024560928,37.1809654236],"type":"Point"}
}