{
  "type": "Feature",
  "properties": {
    "iso:country":"ES",
    "sg:address":"Av Arana G Sabin, 8",
    "sg:city":"Sukarrieta",
    "sg:orig_category":"Inform\u00c1tica Equipo Y Programas (al Por Mayor)",
    "sg:phone":"+34 946 17 12 44",
    "sg:postcode":"48395",
    "sg:province":"Vizcaya",
    "wof:name":"Gomagui Informatica S.l.",
    "wof:placetype":"venue"
},
  "geometry": {"coordinates":[-2.6973750591,43.3936691284],"type":"Point"}
}