{
  "type": "Feature",
  "properties": {
    "addr:full":"Pla\u00c7 Major, 6 Paterna Valencia 46980",
    "addr:postcode":"46980",
    "iso:country":"ES",
    "sg:address":"Pla\u00c7 Major, 6",
    "sg:city":"Paterna",
    "sg:orig_category":"Asesor\u00cda Fiscal Y Jur\u00cddica",
    "sg:phone":"+34 961 37 06 18",
    "sg:postcode":"46980",
    "sg:province":"Valencia",
    "wof:name":"Asesoria Herrera 98 S.l.",
    "wof:placetype":"venue"
},
  "geometry": {"coordinates":[-0.4405986071,39.5020637512],"type":"Point"}
}