{
  "type": "Feature",
  "properties": {
    "addr:full":"Rua Dolores, 23 Ferrol La Coru\u00f1a 15402",
    "addr:housenumber":"23",
    "addr:postcode":"15402",
    "addr:street":"Rua Dolores;La Corun\u0303A",
    "iso:country":"ES",
    "sg:address":"Rua Dolores, 23",
    "sg:city":"Ferrol",
    "sg:orig_category":"Asesor\u00cda Fiscal Y Jur\u00cddica",
    "sg:phone":"+34 981 35 46 18",
    "sg:postcode":"15402",
    "sg:province":"La Coru\u00f1a",
    "wof:name":"Lawtax S.l.",
    "wof:placetype":"venue"
},
  "geometry": {"coordinates":[-8.234380722,43.4836807251],"type":"Point"}
}