{
  "type": "Feature",
  "properties": {
    "addr:full":"Calle de Camarena, 88 Madrid Madrid 28047",
    "addr:housenumber":"88",
    "addr:postcode":"madrid;28047",
    "addr:street":"Calle De Camarena",
    "iso:country":"ES",
    "sg:address":"Calle de Camarena, 88",
    "sg:city":"Madrid",
    "sg:orig_category":"Papeler\u00cdas, Librer\u00cdas",
    "sg:phone":"+34 917 17 07 49",
    "sg:postcode":"28047",
    "sg:province":"Madrid",
    "wof:name":"Osuna Garrido Purificacion",
    "wof:placetype":"venue"
},
  "geometry": {"coordinates":[-3.7571117878,40.3936767578],"type":"Point"}
}