{
  "type": "Feature",
  "properties": {
    "iso:country":"ES",
    "sg:address":"Rua Calvo Sotelo, 80",
    "sg:city":"Sarria",
    "sg:orig_category":"Negocio De Materiales De Construcci\u00d3n",
    "sg:phone":"+34 982 53 01 09",
    "sg:postcode":"27600",
    "sg:province":"Lugo",
    "wof:name":"Vazquez Fernandez Guillermo",
    "wof:placetype":"venue"
},
  "geometry": {"coordinates":[-7.4125890732,42.7799110413],"type":"Point"}
}