{
  "type": "Feature",
  "properties": {
    "iso:country":"ES",
    "sg:address":"Concejo De Egues, 13",
    "sg:city":"Iru\u00f1a",
    "sg:orig_category":"Carnicer\u00cdas, Carnicer\u00cdas",
    "sg:phone":"+34 948 16 10 38",
    "sg:postcode":"31016",
    "sg:province":"Navarra",
    "wof:name":"Satur Y Jose S.l.l.",
    "wof:placetype":"venue"
},
  "geometry": {"coordinates":[-1.6122809649,42.8130683899],"type":"Point"}
}