{
  "type": "Feature",
  "properties": {
    "iso:country":"ES",
    "sg:address":"Calle de Flor De Retama, 6",
    "sg:city":"Sevilla",
    "sg:orig_category":"Empresas De Pintura Y Revestimientos",
    "sg:phone":"+34 954 44 24 03",
    "sg:postcode":"41020",
    "sg:province":"Sevilla",
    "wof:name":"Vizcaino Hidalgo Andres",
    "wof:placetype":"venue"
},
  "geometry": {"coordinates":[-5.9190201759,37.3981628418],"type":"Point"}
}