{
  "type": "Feature",
  "properties": {
    "addr:full":"Calle de Mariano Jose De Larra, 44 Merida Badajoz 06800",
    "addr:housenumber":"44",
    "addr:postcode":"06800",
    "addr:street":"Calle De Mariano Jose De Larra",
    "iso:country":"ES",
    "sg:address":"Calle de Mariano Jose De Larra, 44",
    "sg:city":"Merida",
    "sg:orig_category":"M\u00c9dicos: Ginecolog\u00cda Y Obstetricia",
    "sg:phone":"+34 924 30 09 34",
    "sg:postcode":"06800",
    "sg:province":"Badajoz",
    "wof:name":"Blanco Coronado Francisco Ramon",
    "wof:placetype":"venue"
},
  "geometry": {"coordinates":[-6.3382239342,38.9175338745],"type":"Point"}
}