{
  "type": "Feature",
  "properties": {
    "addr:full":"Carrer de Roca I Roca, 37 Terrassa Barcelona 08226",
    "addr:housenumber":"37",
    "addr:postcode":"08226",
    "addr:street":"Carrer De Roca I Roca",
    "iso:country":"ES",
    "sg:address":"Carrer de Roca I Roca, 37",
    "sg:city":"Terrassa",
    "sg:orig_category":"Promotores Constructores",
    "sg:phone":"+34 937 35 49 54",
    "sg:postcode":"08226",
    "sg:province":"Barcelona",
    "wof:name":"Ingenec Medi Ambient S.l.",
    "wof:placetype":"venue"
},
  "geometry": {"coordinates":[2.0187520981,41.5739250183],"type":"Point"}
}