{
  "type": "Feature",
  "properties": {
    "iso:country":"ES",
    "sg:address":"Avda Valdelasfuentes (de), 9",
    "sg:city":"San Sebastian De Los Reyes",
    "sg:orig_category":"Bancos",
    "sg:phone":"+34 916 63 78 39",
    "sg:postcode":"28700",
    "sg:province":"Madrid",
    "wof:name":"Banco Espa\u00f1ol De Credito S.a.",
    "wof:placetype":"venue"
},
  "geometry": {"coordinates":[-3.6326611042,40.551525116],"type":"Point"}
}