{
  "type": "Feature",
  "properties": {
    "addr:full":"A Pena Parda(s. Xiao), S/n Pena Parda La Coru\u00f1a 15578",
    "addr:housenumber":"s / n",
    "addr:postcode":"15578",
    "addr:street":"Parda;Corun\u0303A",
    "iso:country":"ES",
    "sg:address":"A Pena Parda(s. Xiao), S/n",
    "sg:city":"Pena Parda",
    "sg:orig_category":"Ense\u00d1anza, Formaci\u00d3n Profesional: Aprendizaje",
    "sg:phone":"+34 981 38 88 38",
    "sg:postcode":"15578",
    "sg:province":"La Coru\u00f1a",
    "wof:name":"Asociacion Provincial De Talleres De Reparacion De Vehiculos De La Coru\u00d1a",
    "wof:placetype":"venue"
},
  "geometry": {"coordinates":[-8.1559448242,43.5172233582],"type":"Point"}
}