{
  "type": "Feature",
  "properties": {
    "addr:full":"Carr Sor Rita Mercader, 7 Igualada Barcelona 08700",
    "addr:housenumber":"7",
    "addr:postcode":"08700",
    "addr:street":"Carr Sor Rita Mercader",
    "iso:country":"ES",
    "sg:address":"Carr Sor Rita Mercader, 7",
    "sg:city":"Igualada",
    "sg:orig_category":"Ense\u00d1anza: Profesiones Art\u00cdsticas",
    "sg:phone":"+34 938 04 48 03",
    "sg:postcode":"08700",
    "sg:province":"Barcelona",
    "sg:website":"www.rosebudfilms.net",
    "wof:name":"Rosebud Films Publimedia S.c.p.",
    "wof:placetype":"venue"
},
  "geometry": {"coordinates":[1.6098510027,41.5813484192],"type":"Point"}
}