{
  "type": "Feature",
  "properties": {
    "addr:full":"Obpo. Tabera, 5 Villoruela Salamanca 37339",
    "addr:housenumber":"5",
    "addr:postcode":"37339",
    "addr:street":"Obpo. Tabera",
    "iso:country":"ES",
    "sg:address":"Obpo. Tabera, 5",
    "sg:city":"Villoruela",
    "sg:orig_category":"Fabricaci\u00d3n, Comercio De Muebles En Ca\u00d1a, Mimbre",
    "sg:phone":"+34 923 35 63 82",
    "sg:postcode":"37339",
    "sg:province":"Salamanca",
    "wof:name":"Lazaro Sanchez Juan Manuel",
    "wof:placetype":"venue"
},
  "geometry": {"coordinates":[-5.3757038116,40.9952888489],"type":"Point"}
}