{
  "type": "Feature",
  "properties": {
    "addr:full":"Ctra Ronda (de), 82 Almeria Almer\u00eda 04004",
    "addr:housenumber":"82",
    "addr:postcode":"04004",
    "addr:street":"Ctra Ronda De",
    "iso:country":"ES",
    "sg:address":"Ctra Ronda (de), 82",
    "sg:city":"Almeria",
    "sg:orig_category":"Mec\u00c1nico Del Autom\u00d3vil",
    "sg:phone":"+34 950 25 22 73",
    "sg:postcode":"04004",
    "sg:province":"Almer\u00eda",
    "wof:name":"Morales Rubio Jose",
    "wof:placetype":"venue"
},
  "geometry": {"coordinates":[-2.4564709663,36.8360519409],"type":"Point"}
}