{
  "type": "Feature",
  "properties": {
    "addr:full":"Calle de Canovas Del Castillo, 53 Linares Ja\u00e9n 23700",
    "addr:housenumber":"53",
    "addr:postcode":"23700",
    "addr:street":"Calle De Canovas Del Castillo;Jae\u0301N",
    "iso:country":"ES",
    "sg:address":"Calle de Canovas Del Castillo, 53",
    "sg:city":"Linares",
    "sg:orig_category":"Agricultura: Abastecimiento Y Cosechado (negocio)",
    "sg:phone":"+34 953 69 42 63",
    "sg:postcode":"23700",
    "sg:province":"Ja\u00e9n",
    "wof:name":"Santiago Santiago Jesus",
    "wof:placetype":"venue"
},
  "geometry": {"coordinates":[-3.632281065,38.0930252075],"type":"Point"}
}