{
  "type": "Feature",
  "properties": {
    "addr:full":"Carrer de Rafalet, D'es, 1 Santanyi Islas Baleares 07650",
    "addr:housenumber":"1",
    "addr:postcode":"07650",
    "addr:street":"Carrer De Rafalet D'Es",
    "iso:country":"ES",
    "sg:address":"Carrer de Rafalet, D'es, 1",
    "sg:city":"Santanyi",
    "sg:orig_category":"Peluquer\u00cdas, Peluquer\u00cda Mixta",
    "sg:phone":"+34 971 65 32 93",
    "sg:postcode":"07650",
    "sg:province":"Islas Baleares",
    "wof:name":"Gaya Vidal Maria Del Mar",
    "wof:placetype":"venue"
},
  "geometry": {"coordinates":[3.1299529076,39.3502616882],"type":"Point"}
}