{
  "type": "Feature",
  "properties": {
    "addr:full":"Avda Camelias, 86 Vigo Pontevedra 36211",
    "addr:housenumber":"86",
    "addr:postcode":"36211",
    "addr:street":"Avda Camelias",
    "iso:country":"ES",
    "sg:address":"Avda Camelias, 86",
    "sg:city":"Vigo",
    "sg:orig_category":"Agencias De Trabajo Temporal",
    "sg:phone":"+34 986 20 47 62",
    "sg:postcode":"36211",
    "sg:province":"Pontevedra",
    "wof:name":"Manpower Team Empresas De Trabajo Temporal",
    "wof:placetype":"venue"
},
  "geometry": {"coordinates":[-8.7299613953,42.2271690369],"type":"Point"}
}