{
  "type": "Feature",
  "properties": {
    "iso:country":"ES",
    "sg:address":"Calle de Pelayo Moreno Sanchez, 4",
    "sg:city":"Merida",
    "sg:orig_category":"Electricidad: Instaladores",
    "sg:phone":"+34 924 37 32 11",
    "sg:postcode":"06800",
    "sg:province":"Badajoz",
    "wof:name":"Cidoncha Parejo Miguel",
    "wof:placetype":"venue"
},
  "geometry": {"coordinates":[-6.3591837883,38.9119758606],"type":"Point"}
}