{
  "type": "Feature",
  "properties": {
    "iso:country":"ES",
    "sg:address":"Avda Jose De Mora, 14",
    "sg:city":"Baza",
    "sg:orig_category":"Ropa Para Ni\u00d1os (al Por Menor)",
    "sg:phone":"+34 958 70 15 74",
    "sg:postcode":"18800",
    "sg:province":"Granada",
    "wof:name":"Garrido Ruiz Juan Carlos",
    "wof:placetype":"venue"
},
  "geometry": {"coordinates":[-2.7705180645,37.4861831665],"type":"Point"}
}