{
  "type": "Feature",
  "properties": {
    "addr:full":"Calle de Ondarroa, 2 Bilbao Vizcaya 48004",
    "addr:housenumber":"2",
    "addr:postcode":"48004",
    "addr:street":"Calle De Ondarroa",
    "iso:country":"ES",
    "sg:address":"Calle de Ondarroa, 2",
    "sg:city":"Bilbao",
    "sg:orig_category":"Laboratorios Farmac\u00c9uticos",
    "sg:phone":"+34 944 59 70 05",
    "sg:postcode":"48004",
    "sg:province":"Vizcaya",
    "wof:name":"Lundbeck Espa\u00d1a S.a.",
    "wof:placetype":"venue"
},
  "geometry": {"coordinates":[-2.9057309628,43.2513237],"type":"Point"}
}