{
  "type": "Feature",
  "properties": {
    "addr:full":"Calle de Padre Marin, 10 Logro\u00f1o La Rioja 26004",
    "addr:housenumber":"10",
    "addr:postcode":"26004",
    "addr:street":"Calle De Padre Marin;Rioja",
    "iso:country":"ES",
    "sg:address":"Calle de Padre Marin, 10",
    "sg:city":"Logro\u00f1o",
    "sg:orig_category":"Agencias Y Agentes Comerciales, Representantes",
    "sg:phone":"+34 941 25 44 26",
    "sg:postcode":"26004",
    "sg:province":"La Rioja",
    "wof:name":"Rubio Martinez Esteban",
    "wof:placetype":"venue"
},
  "geometry": {"coordinates":[-2.4306380749,42.46434021],"type":"Point"}
}