{
  "type": "Feature",
  "properties": {
    "addr:full":"Calle de Toledo, 1 Mostoles Madrid 28938",
    "addr:housenumber":"1",
    "addr:postcode":"28938",
    "addr:street":"Calle De Toledo",
    "iso:country":"ES",
    "sg:address":"Calle de Toledo, 1",
    "sg:city":"Mostoles",
    "sg:orig_category":"Fabricaci\u00d3n, Venta De Cuadros, Accesorios Para Enmarcar",
    "sg:phone":"+34 916 14 96 43",
    "sg:postcode":"28938",
    "sg:province":"Madrid",
    "wof:name":"Benito Rodriguez Juan",
    "wof:placetype":"venue"
},
  "geometry": {"coordinates":[-3.86226511,40.3193206787],"type":"Point"}
}