{
  "type": "Feature",
  "properties": {
    "iso:country":"ES",
    "sg:address":"Calle de Herramientas, 36",
    "sg:city":"Leganes",
    "sg:orig_category":"Artes Gr\u00c1ficas, Artes Pl\u00c1sticas: Material Y Suministros (al Por Menor)",
    "sg:phone":"+34 916 41 67 70",
    "sg:postcode":"28918",
    "sg:province":"Madrid",
    "wof:name":"Etirol S.l.",
    "wof:placetype":"venue"
},
  "geometry": {"coordinates":[-3.8022470474,40.3452453613],"type":"Point"}
}