{
  "type": "Feature",
  "properties": {
    "addr:full":"Plaz Canovas Del Castillo, 4 Algar Murcia 30366",
    "addr:housenumber":"4",
    "addr:postcode":"30366",
    "addr:street":"Plaz Canovas Del Castillo",
    "iso:country":"ES",
    "sg:address":"Plaz Canovas Del Castillo, 4",
    "sg:city":"Algar",
    "sg:orig_category":"Chapister\u00cda",
    "sg:phone":"+34 968 13 50 38",
    "sg:postcode":"30366",
    "sg:province":"Murcia",
    "wof:name":"Pedro Ros Fernandez S.l.",
    "wof:placetype":"venue"
},
  "geometry": {"coordinates":[-0.8678010106,37.6480293274],"type":"Point"}
}