{
  "type": "Feature",
  "properties": {
    "iso:country":"ES",
    "sg:address":"Avda Padre Isla, 87",
    "sg:city":"Le\u00f3n",
    "sg:orig_category":"Mercer\u00cda, Lencer\u00cda (al Por Menor)",
    "sg:phone":"+34 987 23 43 10",
    "sg:postcode":"24008",
    "sg:province":"Le\u00f3n",
    "sg:website":"www.paginasamarillas.es",
    "wof:name":"Riera Cervantes Miguel",
    "wof:placetype":"venue"
},
  "geometry": {"coordinates":[-5.5787172318,42.6057624817],"type":"Point"}
}