{
  "type": "Feature",
  "properties": {
    "addr:full":"Calle de Palo, 10 Urda Toledo 45480",
    "addr:housenumber":"10",
    "addr:postcode":"45480",
    "addr:street":"Calle De Palo",
    "iso:country":"ES",
    "sg:address":"Calle de Palo, 10",
    "sg:city":"Urda",
    "sg:orig_category":"Cajas De Ahorro",
    "sg:phone":"+34 925 47 22 10",
    "sg:postcode":"45480",
    "sg:province":"Toledo",
    "sg:website":"www.ccm.es",
    "wof:name":"Caja De Ahorros De Castilla La Mancha",
    "wof:placetype":"venue"
},
  "geometry": {"coordinates":[-3.7161691189,39.4127883911],"type":"Point"}
}