{
  "type": "Feature",
  "properties": {
    "iso:country":"ES",
    "sg:address":"Calle de Obispo Herrera Oria, 1",
    "sg:city":"Arroyo De La Miel-benalmadena Costa",
    "sg:orig_category":"T\u00c9cnicos Veterinarios",
    "sg:phone":"+34 952 44 77 83",
    "sg:postcode":"29631",
    "sg:province":"M\u00e1laga",
    "wof:name":"Buendia Diaz Edmundo",
    "wof:placetype":"venue"
},
  "geometry": {"coordinates":[-4.5371189117,36.5974197388],"type":"Point"}
}