{
  "type": "Feature",
  "properties": {
    "addr:full":"Calle de Capulino Jauregui, 8 Malaga M\u00e1laga 29002",
    "addr:housenumber":"8",
    "addr:postcode":"29002",
    "addr:street":"Calle De Capulino Jauregui;Ma\u0301Laga",
    "iso:country":"ES",
    "sg:address":"Calle de Capulino Jauregui, 8",
    "sg:city":"Malaga",
    "sg:orig_category":"Carnicer\u00cdas, Carnicer\u00cdas",
    "sg:phone":"+34 952 35 60 24",
    "sg:postcode":"29002",
    "sg:province":"M\u00e1laga",
    "wof:name":"Diaz Blanco Rafael",
    "wof:placetype":"venue"
},
  "geometry": {"coordinates":[-4.4351949692,36.7050666809],"type":"Point"}
}