{
  "type": "Feature",
  "properties": {
    "addr:full":"Carr Sant Cristofol, 6 Eivissa Islas Baleares 07800",
    "addr:housenumber":"6",
    "addr:postcode":"07800",
    "addr:street":"Carr Sant Cristofol",
    "iso:country":"ES",
    "sg:address":"Carr Sant Cristofol, 6",
    "sg:city":"Eivissa",
    "sg:orig_category":"Procuradores",
    "sg:phone":"+34 971 19 14 63",
    "sg:postcode":"07800",
    "sg:province":"Islas Baleares",
    "wof:name":"Tur Pereyro Magdalena",
    "wof:placetype":"venue"
},
  "geometry": {"coordinates":[1.4291679859,38.9127006531],"type":"Point"}
}