{
  "type": "Feature",
  "properties": {
    "addr:full":"Plaz Luis De Zu\u00d1iga, 37 Plasencia C\u00e1ceres 10600",
    "addr:housenumber":"37",
    "addr:postcode":"10600",
    "addr:street":"Plaz Luis De Zun\u0303Iga;Ca\u0301Ceres",
    "iso:country":"ES",
    "sg:address":"Plaz Luis De Zu\u00d1iga, 37",
    "sg:city":"Plasencia",
    "sg:orig_category":"Cristaler\u00cdas",
    "sg:phone":"+34 927 42 00 70",
    "sg:postcode":"10600",
    "sg:province":"C\u00e1ceres",
    "wof:name":"Cristaleria Mayorga S.l.",
    "wof:placetype":"venue"
},
  "geometry": {"coordinates":[-6.0828690529,40.0327110291],"type":"Point"}
}