{
  "type": "Feature",
  "properties": {
    "addr:full":"Calle de Polvoranca, 74 Alcorcon Madrid 28923",
    "addr:housenumber":"74",
    "addr:postcode":"28923",
    "addr:street":"Calle De Polvoranca",
    "iso:country":"ES",
    "sg:address":"Calle de Polvoranca, 74",
    "sg:city":"Alcorcon",
    "sg:orig_category":"M\u00c9dicos: Estomatolog\u00cda",
    "sg:phone":"+34 916 41 02 25",
    "sg:postcode":"28923",
    "sg:province":"Madrid",
    "wof:name":"Gonzalez Abad Antonio",
    "wof:placetype":"venue"
},
  "geometry": {"coordinates":[-3.8173429966,40.3410377502],"type":"Point"}
}