{
  "type": "Feature",
  "properties": {
    "iso:country":"ES",
    "sg:address":"Calle de Mayor, 82",
    "sg:city":"Castellon",
    "sg:orig_category":"Ingeniero",
    "sg:phone":"+34 964 23 21 83",
    "sg:postcode":"12001",
    "sg:province":"Castell\u00f3n",
    "wof:name":"Zaera Tena Fidel",
    "wof:placetype":"venue"
},
  "geometry": {"coordinates":[-0.0390900001,39.9866714478],"type":"Point"}
}