{
  "type": "Feature",
  "properties": {
    "addr:full":"Carr Sipells, Des, 3 Cala Millor Islas Baleares 07560",
    "addr:postcode":"07560",
    "addr:street":"Carr Sipells",
    "iso:country":"ES",
    "sg:address":"Carr Sipells, Des, 3",
    "sg:city":"Cala Millor",
    "sg:orig_category":"Abogados",
    "sg:phone":"+34 971 58 57 65",
    "sg:postcode":"07560",
    "sg:province":"Islas Baleares",
    "wof:name":"Ruiz Llorente Maria Teresa",
    "wof:placetype":"venue"
},
  "geometry": {"coordinates":[3.3860778809,39.603553772],"type":"Point"}
}