{
  "type": "Feature",
  "properties": {
    "addr:full":"Calle de Antonio Machado, 74 Albacete Albacete 02004",
    "addr:housenumber":"74",
    "addr:postcode":"02004",
    "addr:street":"Calle De Antonio Machado",
    "iso:country":"ES",
    "sg:address":"Calle de Antonio Machado, 74",
    "sg:city":"Albacete",
    "sg:orig_category":"Asistencia Social",
    "sg:phone":"+34 967 23 86 16",
    "sg:postcode":"02004",
    "sg:province":"Albacete",
    "wof:name":"Desarrollo Social A.i.e.",
    "wof:placetype":"venue"
},
  "geometry": {"coordinates":[-1.8647371531,38.991809845],"type":"Point"}
}