{
  "type": "Feature",
  "properties": {
    "addr:full":"Calle de Poza Licenciado, 6 Bilbao Vizcaya 48008",
    "addr:housenumber":"6",
    "addr:postcode":"48008",
    "addr:street":"Calle De Poza Licenciado",
    "iso:country":"ES",
    "sg:address":"Calle de Poza Licenciado, 6",
    "sg:city":"Bilbao",
    "sg:orig_category":"Promotores Constructores",
    "sg:phone":"+34 944 42 40 17",
    "sg:postcode":"48008",
    "sg:province":"Vizcaya",
    "sg:website":"www.keymare.com",
    "wof:name":"Key Mare Promotores S.l.",
    "wof:placetype":"venue"
},
  "geometry": {"coordinates":[-2.9341619015,43.2607841492],"type":"Point"}
}