{
  "type": "Feature",
  "properties": {
    "iso:country":"ES",
    "sg:address":"Carrer de Polop, 6",
    "sg:city":"Benidorm",
    "sg:orig_category":"Molduras, Junquillos, Listones Y Molduras Perforadas",
    "sg:phone":"+34 966 80 32 94",
    "sg:postcode":"03500",
    "sg:province":"Alicante",
    "wof:name":"Beteta Botella Simon",
    "wof:placetype":"venue"
},
  "geometry": {"coordinates":[-0.1336649954,38.5475158691],"type":"Point"}
}