{
  "type": "Feature",
  "properties": {
    "iso:country":"ES",
    "sg:address":"Calle de Castillo De Arevalo, 1",
    "sg:city":"Rozas De Madrid",
    "sg:orig_category":"Agencias Y Asesores De Publicidad",
    "sg:phone":"+34 916 30 97 88",
    "sg:postcode":"28230",
    "sg:province":"Madrid",
    "wof:name":"Martin Centeno Encarnacion",
    "wof:placetype":"venue"
},
  "geometry": {"coordinates":[-3.8937637806,40.5062675476],"type":"Point"}
}