{
  "type": "Feature",
  "properties": {
    "iso:country":"ES",
    "sg:address":"Cami Font (la), 37",
    "sg:city":"Sabadell",
    "sg:orig_category":"Zapater\u00cdas",
    "sg:phone":"+34 937 25 77 70",
    "sg:postcode":"08201",
    "sg:province":"Barcelona",
    "wof:name":"Cal\u00c7ats Moix S.l.",
    "wof:placetype":"venue"
},
  "geometry": {"coordinates":[2.105825901,41.5463867188],"type":"Point"}
}