{
  "type": "Feature",
  "properties": {
    "iso:country":"ES",
    "sg:address":"Calle de Zabalbide, 68",
    "sg:city":"Bilbao",
    "sg:orig_category":"Poller\u00cda Y Caza (al Por Menor)",
    "sg:phone":"+34 944 12 21 21",
    "sg:postcode":"48006",
    "sg:province":"Vizcaya",
    "wof:name":"Martinez Saez Jose Luis",
    "wof:placetype":"venue"
},
  "geometry": {"coordinates":[-2.9134140015,43.2551078796],"type":"Point"}
}