{
  "type": "Feature",
  "properties": {
    "iso:country":"ES",
    "sg:address":"Luga Mercalaspalmas, S/n",
    "sg:city":"Mercalaspalmas",
    "sg:orig_category":"Frutas Y Legumbres Frescas (al Por Mayor)",
    "sg:phone":"+34 928 71 11 41",
    "sg:postcode":"35229",
    "sg:province":"Las Palmas",
    "wof:name":"Armas Moreno Manuel",
    "wof:placetype":"venue"
},
  "geometry": {"coordinates":[-15.4300060272,28.1248226166],"type":"Point"}
}