{
  "type": "Feature",
  "properties": {
    "addr:full":"Calle de Doce De Octubre, 6 Mieres Asturias 33600",
    "addr:housenumber":"6",
    "addr:postcode":"33600",
    "addr:street":"Calle De Doce De Octubre",
    "iso:country":"ES",
    "sg:address":"Calle de Doce De Octubre, 6",
    "sg:city":"Mieres",
    "sg:orig_category":"Centros De Coordinaci\u00d3n",
    "sg:phone":"+34 984 18 07 03",
    "sg:postcode":"33600",
    "sg:province":"Asturias",
    "wof:name":"Fematite S.l",
    "wof:placetype":"venue"
},
  "geometry": {"coordinates":[-5.7739243507,43.2503623962],"type":"Point"}
}