{
  "type": "Feature",
  "properties": {
    "iso:country":"ES",
    "sg:address":"Avda Principes De Espa\u00d1a, 27",
    "sg:city":"Rota",
    "sg:orig_category":"Agentes Generales De Seguros",
    "sg:phone":"+34 956 81 08 42",
    "sg:postcode":"11520",
    "sg:province":"C\u00e1diz",
    "wof:name":"Asmedisan S.l.",
    "wof:placetype":"venue"
},
  "geometry": {"coordinates":[-6.3871073723,36.6367835999],"type":"Point"}
}