{
  "type": "Feature",
  "properties": {
    "iso:country":"ES",
    "sg:address":"Plaz Maestro Mateo Hernandez, 2",
    "sg:city":"Portugalete",
    "sg:orig_category":"Molduras, Junquillos, Listones Y Molduras Perforadas",
    "sg:phone":"+34 944 95 52 49",
    "sg:postcode":"48920",
    "sg:province":"Vizcaya",
    "wof:name":"Diaz Romero Francisco",
    "wof:placetype":"venue"
},
  "geometry": {"coordinates":[-3.0167689323,43.3158721924],"type":"Point"}
}