{
  "type": "Feature",
  "properties": {
    "addr:full":"Calle de Ega\u00d1a, 8 Bilbao Vizcaya 48010",
    "addr:housenumber":"8",
    "addr:postcode":"48010",
    "addr:street":"Calle De Egan\u0303A",
    "iso:country":"ES",
    "sg:address":"Calle de Ega\u00d1a, 8",
    "sg:city":"Bilbao",
    "sg:orig_category":"Fabricaci\u00d3n De Instrumentos Y Accesorios Musicales",
    "sg:phone":"+34 944 10 07 11",
    "sg:postcode":"48010",
    "sg:province":"Vizcaya",
    "wof:name":"Berohi, S.coop.",
    "wof:placetype":"venue"
},
  "geometry": {"coordinates":[-2.9372909069,43.2582855225],"type":"Point"}
}