{
  "type": "Feature",
  "properties": {
    "addr:full":"Ctra Caldes, Km. 5878,0 Pineda Feu Barcelona 08186",
    "addr:postcode":"08186",
    "addr:street":"Ctra Caldes Km. 5878,0 Pineda;Barcelona",
    "iso:country":"ES",
    "sg:address":"Ctra Caldes, Km. 5878,0",
    "sg:city":"Pineda Feu",
    "sg:orig_category":"Jardiner\u00cdas, Vegetales, Art\u00cdculos De Jardiner\u00cda (al Por Menor)",
    "sg:phone":"+34 938 41 44 82",
    "sg:postcode":"08186",
    "sg:province":"Barcelona",
    "wof:name":"Vivers Ernest S.l.",
    "wof:placetype":"venue"
},
  "geometry": {"coordinates":[2.2318193913,41.6288833618],"type":"Point"}
}