{
  "type": "Feature",
  "properties": {
    "addr:full":"Calle de Magdalena (la), S/n Treviana La Rioja 26215",
    "addr:postcode":"26215",
    "addr:street":"Calle De Magdalena La S / N Treviana;Rioja",
    "iso:country":"ES",
    "sg:address":"Calle de Magdalena (la), S/n",
    "sg:city":"Treviana",
    "sg:orig_category":"Empresarios",
    "sg:phone":"+34 941 32 60 89",
    "sg:postcode":"26215",
    "sg:province":"La Rioja",
    "wof:name":"Ruiz-olalla Alonso Jose Antonio",
    "wof:placetype":"venue"
},
  "geometry": {"coordinates":[-3.0491330624,42.5590133667],"type":"Point"}
}