{
  "type": "Feature",
  "properties": {
    "addr:full":"Rua Avelino Montero Villegas, 41 Vilanova Lugo 27760",
    "addr:housenumber":"41",
    "addr:postcode":"27760",
    "addr:street":"Rua Avelino Montero Villegas",
    "iso:country":"ES",
    "sg:address":"Rua Avelino Montero Villegas, 41",
    "sg:city":"Vilanova",
    "sg:orig_category":"Reposter\u00cdas",
    "sg:phone":"+34 982 12 10 33",
    "sg:postcode":"27760",
    "sg:province":"Lugo",
    "wof:name":"Panaderia Neli Lourenza S.l.u.",
    "wof:placetype":"venue"
},
  "geometry": {"coordinates":[-7.2977337837,43.4696350098],"type":"Point"}
}