{
  "type": "Feature",
  "properties": {
    "addr:full":"Trva Beatriz Galindo, 2 Alcala Henares Madrid 28803",
    "addr:housenumber":"2",
    "addr:postcode":"28803",
    "addr:street":"Trva Beatriz Galindo",
    "iso:country":"ES",
    "sg:address":"Trva Beatriz Galindo, 2",
    "sg:city":"Alcala Henares",
    "sg:orig_category":"Molduras, Junquillos, Listones Y Molduras Perforadas",
    "sg:phone":"+34 918 82 39 78",
    "sg:postcode":"28803",
    "sg:province":"Madrid",
    "wof:name":"Garcia Varas Paula",
    "wof:placetype":"venue"
},
  "geometry": {"coordinates":[-3.3694078922,40.4765014648],"type":"Point"}
}