{
  "type": "Feature",
  "properties": {
    "addr:full":"Calle de Ba\u00d1os, 16 Sevilla Sevilla 41002",
    "addr:housenumber":"16",
    "addr:postcode":"41002",
    "addr:street":"Calle De Ban\u0303Os",
    "iso:country":"ES",
    "sg:address":"Calle de Ba\u00d1os, 16",
    "sg:city":"Sevilla",
    "sg:orig_category":"Caf\u00c9s, Bares, Cervecer\u00cdas",
    "sg:phone":"+34 954 38 20 57",
    "sg:postcode":"41002",
    "sg:province":"Sevilla",
    "wof:name":"Miranda Labrador Julio",
    "wof:placetype":"venue"
},
  "geometry": {"coordinates":[-5.9981117249,37.3952407837],"type":"Point"}
}