{
  "type": "Feature",
  "properties": {
    "iso:country":"ES",
    "sg:address":"Rua Cruz (da), 16",
    "sg:city":"Lugo",
    "sg:orig_category":"Estancos",
    "sg:phone":"+34 982 25 01 08",
    "sg:postcode":"27001",
    "sg:province":"Lugo",
    "wof:name":"Armesto Mauriz Jesus Fernando",
    "wof:placetype":"venue"
},
  "geometry": {"coordinates":[-7.5579190254,43.01014328],"type":"Point"}
}