{
  "type": "Feature",
  "properties": {
    "addr:full":"Calle de Comercio, S/n Mairena Aljarafe Sevilla 41927",
    "addr:housenumber":"s / n",
    "addr:postcode":"41927",
    "addr:street":"Calle De Comercio",
    "iso:country":"ES",
    "sg:address":"Calle de Comercio, S/n",
    "sg:city":"Mairena Aljarafe",
    "sg:orig_category":"Venta, Instalaci\u00d3n De Sistemas De Alarmas Y Vigilancia",
    "sg:phone":"+34 955 60 12 34",
    "sg:postcode":"41927",
    "sg:province":"Sevilla",
    "sg:website":"www.notifier.es",
    "wof:name":"Honeywell Life Safety Iberia S.l.",
    "wof:placetype":"venue"
},
  "geometry": {"coordinates":[-6.0579571724,37.3542289734],"type":"Point"}
}