{
  "type": "Feature",
  "properties": {
    "iso:country":"ES",
    "sg:address":"Carrer de Gambo, 6",
    "sg:city":"Benidorm",
    "sg:orig_category":"Abogados",
    "sg:phone":"+34 965 85 21 67",
    "sg:postcode":"03500",
    "sg:province":"Alicante",
    "wof:name":"Sancho Mestre Pilar",
    "wof:placetype":"venue"
},
  "geometry": {"coordinates":[-0.1279319972,38.5369796753],"type":"Point"}
}