{
  "type": "Feature",
  "properties": {
    "iso:country":"ES",
    "sg:address":"G.v. Corts Catalanes, 562",
    "sg:city":"Barcelona",
    "sg:orig_category":"Discapacitados",
    "sg:phone":"+34 934 51 55 50",
    "sg:postcode":"08011",
    "sg:province":"Barcelona",
    "wof:name":"Federacion Ecom",
    "wof:placetype":"venue"
},
  "geometry": {"coordinates":[2.1613059044,41.3837585449],"type":"Point"}
}