{
  "type": "Feature",
  "properties": {
    "iso:country":"ES",
    "sg:address":"Yucas Las, 8",
    "sg:city":"Cabo Palos",
    "sg:orig_category":"Ingenier\u00cda, Centros De Estudios (diversos)",
    "sg:phone":"+34 968 56 36 10",
    "sg:postcode":"30370",
    "sg:province":"Murcia",
    "wof:name":"Alvargonzalez Juliana Victoriano",
    "wof:placetype":"venue"
},
  "geometry": {"coordinates":[-0.7055284977,37.6263618469],"type":"Point"}
}