{
  "type": "Feature",
  "properties": {
    "addr:full":"Pl Sant Pere, 3 Berga-ciudad Barcelona 08600",
    "addr:housenumber":"3",
    "addr:postcode":"08600",
    "addr:street":"Pl Sant Pere;Barcelona",
    "iso:country":"ES",
    "sg:address":"Pl Sant Pere, 3",
    "sg:city":"Berga-ciudad",
    "sg:orig_category":"Electrodom\u00c9sticos (al Por Menor)",
    "sg:phone":"+34 938 21 18 97",
    "sg:postcode":"08600",
    "sg:province":"Barcelona",
    "wof:name":"Romero Costa Yolanda",
    "wof:placetype":"venue"
},
  "geometry": {"coordinates":[1.846009016,42.1041412354],"type":"Point"}
}