{
  "type": "Feature",
  "properties": {
    "iso:country":"ES",
    "sg:address":"Carrer de Germans Farguell, 45",
    "sg:city":"Sabadell",
    "sg:orig_category":"Goma: Productos De Uso Industrial (fabricaci\u00d3n, Al Por Mayor)",
    "sg:phone":"+34 937 27 53 58",
    "sg:postcode":"08205",
    "sg:province":"Barcelona",
    "sg:website":"www.gumroller.com",
    "wof:name":"Gumroller S.l.",
    "wof:placetype":"venue"
},
  "geometry": {"coordinates":[2.0964980125,41.5436706543],"type":"Point"}
}