{
  "type": "Feature",
  "properties": {
    "addr:full":"O. Redondo, 2 Cordoba C\u00f3rdoba 14010",
    "addr:housenumber":"2",
    "addr:postcode":"14010",
    "addr:street":"Cordoba Co\u0301Rdoba",
    "iso:country":"ES",
    "sg:address":"O. Redondo, 2",
    "sg:city":"Cordoba",
    "sg:orig_category":"Internados & Ense\u00d1anza Privada",
    "sg:phone":"+34 957 25 49 01",
    "sg:postcode":"14010",
    "sg:province":"C\u00f3rdoba",
    "wof:name":"Hijas De Maria Religiosas De Las Escuelas Pias Provincia De Castilla Curia Provincial",
    "wof:placetype":"venue"
},
  "geometry": {"coordinates":[-4.7584738731,37.8859214783],"type":"Point"}
}