{
  "type": "Feature",
  "properties": {
    "iso:country":"ES",
    "sg:address":"Calle de Carlos Aurioles, 27",
    "sg:city":"Madrid",
    "sg:orig_category":"Electricidad: Instaladores",
    "sg:phone":"+34 915 07 92 00",
    "sg:postcode":"28018",
    "sg:province":"Madrid",
    "sg:website":"www.irmadirect.apiem.fenie.es",
    "wof:name":"I.r.m.a. Direct S.l.",
    "wof:placetype":"venue"
},
  "geometry": {"coordinates":[-3.6668510437,40.3821754456],"type":"Point"}
}