{
  "type": "Feature",
  "properties": {
    "addr:full":"Carrer de Lleida, 92 Prat Llobregat Barcelona 08820",
    "addr:housenumber":"92",
    "addr:postcode":"08820",
    "addr:street":"Carrer De Lleida;Llobregat",
    "iso:country":"ES",
    "sg:address":"Carrer de Lleida, 92",
    "sg:city":"Prat Llobregat",
    "sg:orig_category":"Electricidad: Instaladores",
    "sg:phone":"+34 933 79 03 29",
    "sg:postcode":"08820",
    "sg:province":"Barcelona",
    "wof:name":"Pareda Pascual Juan",
    "wof:placetype":"venue"
},
  "geometry": {"coordinates":[2.0966339111,41.3225898743],"type":"Point"}
}