{
  "type": "Feature",
  "properties": {
    "iso:country":"ES",
    "sg:address":"Calle de San Miguel Alta, 15",
    "sg:city":"Granada",
    "sg:orig_category":"Procuradores",
    "sg:phone":"+34 958 52 21 46",
    "sg:postcode":"18002",
    "sg:province":"Granada",
    "wof:name":"Molina Ca\u00f1avate Maria",
    "wof:placetype":"venue"
},
  "geometry": {"coordinates":[-3.6039149761,37.1735954285],"type":"Point"}
}