{
  "type": "Feature",
  "properties": {
    "iso:country":"ES",
    "sg:address":"Pl. Fc\u00ba Ruiz Jarabo, 1",
    "sg:city":"Villarejo-periesteban",
    "sg:orig_category":"Bibliotecas, Mediatecas",
    "sg:phone":"+34 969 19 65 01",
    "sg:postcode":"16443",
    "sg:province":"Cuenca",
    "wof:name":"Ayuntamiento De Villarejo-periesteban",
    "wof:placetype":"venue"
},
  "geometry": {"coordinates":[-2.4411098957,39.8714408875],"type":"Point"}
}