{
  "type": "Feature",
  "properties": {
    "addr:full":"Calle de Rosario, 30 Ribaforada Navarra 31550",
    "addr:housenumber":"30",
    "addr:postcode":"31550",
    "addr:street":"Calle De Rosario",
    "iso:country":"ES",
    "sg:address":"Calle de Rosario, 30",
    "sg:city":"Ribaforada",
    "sg:orig_category":"Ingenier\u00cda, Centros De Estudios (diversos)",
    "sg:phone":"+34 948 86 40 96",
    "sg:postcode":"31550",
    "sg:province":"Navarra",
    "wof:name":"Zardoya Y Huete Ingenieria S.l.l.",
    "wof:placetype":"venue"
},
  "geometry": {"coordinates":[-1.5086679459,41.9964370728],"type":"Point"}
}