{
  "type": "Feature",
  "properties": {
    "addr:full":"Avda Estacion, S/n Barbastro Huesca 22300",
    "addr:postcode":"22300",
    "addr:street":"Avda Estacion S / N",
    "iso:country":"ES",
    "sg:address":"Avda Estacion, S/n",
    "sg:city":"Barbastro",
    "sg:orig_category":"Comit\u00c9s De Organizaci\u00d3n De Exposiciones, Ferias, Salones",
    "sg:phone":"+34 974 31 19 19",
    "sg:postcode":"22300",
    "sg:province":"Huesca",
    "wof:name":"Institucion Ferial De Barbastro",
    "wof:placetype":"venue"
},
  "geometry": {"coordinates":[0.1314049959,42.0275688171],"type":"Point"}
}