{
  "type": "Feature",
  "properties": {
    "iso:country":"ES",
    "sg:address":"Ctra Valencia, S/n",
    "sg:city":"Cheste",
    "sg:orig_category":"Transporte En General",
    "sg:phone":"+34 962 51 17 51",
    "sg:postcode":"46380",
    "sg:province":"Valencia",
    "wof:name":"Levantina De Almacenamientos Y Distribucion S.l.",
    "wof:placetype":"venue"
},
  "geometry": {"coordinates":[-0.6810290217,39.4970283508],"type":"Point"}
}