{
  "type": "Feature",
  "properties": {
    "addr:full":"Calle de Cuadrillos (los), 23 Noja Cantabria 39180",
    "addr:housenumber":"23",
    "addr:postcode":"39180",
    "addr:street":"Calle De Cuadrillos Los",
    "iso:country":"ES",
    "sg:address":"Calle de Cuadrillos (los), 23",
    "sg:city":"Noja",
    "sg:orig_category":"Locales Deportivos",
    "sg:phone":"+34 942 63 11 53",
    "sg:postcode":"39180",
    "sg:province":"Cantabria",
    "wof:name":"De Isla Pereira Jose",
    "wof:placetype":"venue"
},
  "geometry": {"coordinates":[-3.5246195793,43.4784698486],"type":"Point"}
}