{
  "type": "Feature",
  "properties": {
    "addr:full":"Carr Joan Miro, S/n Albatarrec Lleida 25171",
    "addr:housenumber":"s / n",
    "addr:postcode":"25171",
    "addr:street":"Carr Joan Miro",
    "iso:country":"ES",
    "sg:address":"Carr Joan Miro, S/n",
    "sg:city":"Albatarrec",
    "sg:orig_category":"Guarder\u00cdas",
    "sg:phone":"+34 973 72 07 10",
    "sg:postcode":"25171",
    "sg:province":"Lleida",
    "wof:name":"Ayuntamiento De Albatarrec",
    "wof:placetype":"venue"
},
  "geometry": {"coordinates":[0.6026195288,41.5724716187],"type":"Point"}
}