{
  "type": "Feature",
  "properties": {
    "iso:country":"ES",
    "sg:address":"Pla\u00c7 Beato Carmelo, 9",
    "sg:city":"Real Gandia",
    "sg:orig_category":"Fotograf\u00cda Art\u00cdstica Y Retratos",
    "sg:phone":"+34 962 87 61 62",
    "sg:postcode":"46727",
    "sg:province":"Valencia",
    "wof:name":"Cucart Simo Victor",
    "wof:placetype":"venue"
},
  "geometry": {"coordinates":[-0.1924739927,38.9537200928],"type":"Point"}
}