{
  "type": "Feature",
  "properties": {
    "iso:country":"ES",
    "sg:address":"Calle de San Sebastian, 14",
    "sg:city":"S. Clemente",
    "sg:orig_category":"Farmacias",
    "sg:phone":"+34 969 30 07 06",
    "sg:postcode":"16600",
    "sg:province":"Cuenca",
    "wof:name":"Garcia-sacristan Fernandez Maria Pilar",
    "wof:placetype":"venue"
},
  "geometry": {"coordinates":[-2.433027029,39.4020576477],"type":"Point"}
}