{
  "type": "Feature",
  "properties": {
    "iso:country":"ES",
    "sg:address":"Calle de Habana La, 12",
    "sg:city":"Marpeque\u00d1a",
    "sg:orig_category":"Alquiler De V\u00cddeo",
    "sg:phone":"+34 928 13 30 19",
    "sg:postcode":"35214",
    "sg:province":"Las Palmas",
    "wof:name":"Marrero Suarez Javier",
    "wof:placetype":"venue"
},
  "geometry": {"coordinates":[-15.3887634277,27.9937648773],"type":"Point"}
}