{
  "type": "Feature",
  "properties": {
    "addr:full":"Avda Emilio Arrieta, 5 San Sebastian De Los Reyes Madrid 28700",
    "addr:housenumber":"5",
    "addr:postcode":"28700",
    "addr:street":"Avda Emilio Arrieta",
    "iso:country":"ES",
    "sg:address":"Avda Emilio Arrieta, 5",
    "sg:city":"San Sebastian De Los Reyes",
    "sg:orig_category":"Empresarios Y Productoras De Espect\u00c1culos",
    "sg:phone":"+34 916 59 54 33",
    "sg:postcode":"28700",
    "sg:province":"Madrid",
    "wof:name":"Sostec,proyectos Y Eventos,s.l",
    "wof:placetype":"venue"
},
  "geometry": {"coordinates":[-3.582349062,40.6092414856],"type":"Point"}
}