{
  "type": "Feature",
  "properties": {
    "iso:country":"ES",
    "sg:address":"Pl Orient, S/n",
    "sg:city":"Vendrell",
    "sg:orig_category":"Pescader\u00cdas (al Por Menor)",
    "sg:phone":"+34 977 66 60 51",
    "sg:postcode":"43700",
    "sg:province":"Tarragona",
    "wof:name":"Mas Jansa Juan",
    "wof:placetype":"venue"
},
  "geometry": {"coordinates":[1.5362499952,41.2197761536],"type":"Point"}
}