{
  "type": "Feature",
  "properties": {
    "iso:country":"ES",
    "sg:address":"Av. Pio Xii, 21",
    "sg:city":"Iru\u00f1a",
    "sg:orig_category":"M\u00c9dicos: Estomatolog\u00cda",
    "sg:phone":"+34 948 12 25 86",
    "sg:postcode":"31008",
    "sg:province":"Navarra",
    "wof:name":"Bautista Lasprilla Hernando",
    "wof:placetype":"venue"
},
  "geometry": {"coordinates":[-1.6579500437,42.8094596863],"type":"Point"}
}