{
  "type": "Feature",
  "properties": {
    "addr:full":"Calle de Fueros, 6 Bilbao Vizcaya 48005",
    "addr:housenumber":"6",
    "addr:postcode":"48005",
    "addr:street":"Calle De Fueros",
    "iso:country":"ES",
    "sg:address":"Calle de Fueros, 6",
    "sg:city":"Bilbao",
    "sg:orig_category":"Confiter\u00cdas, Chocolater\u00cdas (al Por Menor)",
    "sg:phone":"+34 944 15 38 50",
    "sg:postcode":"48005",
    "sg:province":"Vizcaya",
    "wof:name":"Ceberino Alcantara Maria Jose",
    "wof:placetype":"venue"
},
  "geometry": {"coordinates":[-2.9231069088,43.2595596313],"type":"Point"}
}