{
  "type": "Feature",
  "properties": {
    "iso:country":"ES",
    "sg:address":"Calle de Ramon Y Cajal, 8",
    "sg:city":"Madridejos",
    "sg:orig_category":"Carnicer\u00cdas, Carnicer\u00cdas",
    "sg:phone":"+34 925 46 00 88",
    "sg:postcode":"45710",
    "sg:province":"Toledo",
    "wof:name":"Sevilla Dorado Francisco",
    "wof:placetype":"venue"
},
  "geometry": {"coordinates":[-3.5352039337,39.4682006836],"type":"Point"}
}