{
  "type": "Feature",
  "properties": {
    "addr:full":"Calle de Santander, 1 Alcorcon Madrid 28922",
    "addr:housenumber":"1",
    "addr:postcode":"28922",
    "addr:street":"Calle De Santander",
    "iso:country":"ES",
    "sg:address":"Calle de Santander, 1",
    "sg:city":"Alcorcon",
    "sg:orig_category":"Organizaciones Internacionales",
    "sg:phone":"+34 916 43 37 16",
    "sg:postcode":"28922",
    "sg:province":"Madrid",
    "wof:name":"Caritas Diocesana De Getafe",
    "wof:placetype":"venue"
},
  "geometry": {"coordinates":[-3.8304069042,40.3440093994],"type":"Point"}
}