{
  "type": "Feature",
  "properties": {
    "addr:full":"Ameas, 54 Abrigosa La Coru\u00f1a 15175",
    "addr:housenumber":"54",
    "addr:postcode":"15175",
    "addr:street":"Ameas;La Corun\u0303A",
    "iso:country":"ES",
    "sg:address":"Ameas, 54",
    "sg:city":"Abrigosa",
    "sg:orig_category":"Venta, Alquiler De Instrumentos Y Accesorios De M\u00dasica",
    "sg:phone":"+34 981 61 34 15",
    "sg:postcode":"15175",
    "sg:province":"La Coru\u00f1a",
    "wof:name":"Artinso S.c.",
    "wof:placetype":"venue"
},
  "geometry": {"coordinates":[-8.3076906204,43.2499084473],"type":"Point"}
}