{
  "type": "Feature",
  "properties": {
    "addr:full":"Calle de Geltoki Kalea, 7 Berriz-olakueta Vizcaya 48240",
    "addr:housenumber":"7",
    "addr:postcode":"48240",
    "addr:street":"Calle De Geltoki Kalea",
    "iso:country":"ES",
    "sg:address":"Calle de Geltoki Kalea, 7",
    "sg:city":"Berriz-olakueta",
    "sg:orig_category":"Promotores Constructores",
    "sg:phone":"+34 946 82 76 03",
    "sg:postcode":"48240",
    "sg:province":"Vizcaya",
    "wof:name":"Construcciones Astarloa S.a.",
    "wof:placetype":"venue"
},
  "geometry": {"coordinates":[-2.5734739304,43.1681594849],"type":"Point"}
}