{
  "type": "Feature",
  "properties": {
    "iso:country":"ES",
    "sg:address":"Calle de Carretas, 11",
    "sg:city":"Villaviciosa Odon",
    "sg:orig_category":"Peluquer\u00cdas, Peluquer\u00cda Mixta",
    "sg:phone":"+34 916 16 64 30",
    "sg:postcode":"28670",
    "sg:province":"Madrid",
    "wof:name":"Centro Especial De Manipulados Cesma S.l.",
    "wof:placetype":"venue"
},
  "geometry": {"coordinates":[-3.9025802612,40.3581962585],"type":"Point"}
}