{
  "type": "Feature",
  "properties": {
    "addr:full":"Carrer de Buenaventura Mu\u00d1oz, 56 Barcelona Barcelona 08018",
    "addr:housenumber":"56",
    "addr:postcode":"08018",
    "addr:street":"Carrer De Buenaventura Mun\u0303Oz",
    "iso:country":"ES",
    "sg:address":"Carrer de Buenaventura Mu\u00d1oz, 56",
    "sg:city":"Barcelona",
    "sg:orig_category":"Cerrajer\u00cda, Ferrallista",
    "sg:phone":"+34 933 00 03 49",
    "sg:postcode":"08018",
    "sg:province":"Barcelona",
    "wof:name":"Fores Marti Gabriel",
    "wof:placetype":"venue"
},
  "geometry": {"coordinates":[2.1875340939,41.393447876],"type":"Point"}
}