{
  "type": "Feature",
  "properties": {
    "addr:full":"Cami Mina De Madro, 9 Pobla Mafumet Tarragona 43140",
    "addr:housenumber":"9",
    "addr:postcode":"43140",
    "addr:street":"Mina;Madro",
    "iso:country":"ES",
    "sg:address":"Cami Mina De Madro, 9",
    "sg:city":"Pobla Mafumet",
    "sg:orig_category":"Molduras, Junquillos, Listones Y Molduras Perforadas",
    "sg:phone":"+34 977 84 20 78",
    "sg:postcode":"43140",
    "sg:province":"Tarragona",
    "wof:name":"Moya Lopez Maria Josefa",
    "wof:placetype":"venue"
},
  "geometry": {"coordinates":[1.2092289925,41.1888885498],"type":"Point"}
}