{
  "type": "Feature",
  "properties": {
    "iso:country":"ES",
    "sg:address":"Calle de Medio (el), 8",
    "sg:city":"Laredo",
    "sg:orig_category":"Abogados",
    "sg:phone":"+34 942 60 55 76",
    "sg:postcode":"39770",
    "sg:province":"Cantabria",
    "wof:name":"Alonso Fernandez Felix",
    "wof:placetype":"venue"
},
  "geometry": {"coordinates":[-3.4117913246,43.4119758606],"type":"Point"}
}