{
  "type": "Feature",
  "properties": {
    "iso:country":"ES",
    "sg:address":"Plaz Merced, 5",
    "sg:city":"Malaga",
    "sg:orig_category":"Peluquer\u00cdas, Peluquer\u00cda Mixta",
    "sg:phone":"+34 952 60 88 30",
    "sg:postcode":"29012",
    "sg:province":"M\u00e1laga",
    "wof:name":"Grupo Figueroa & Ordo\u00f1ez S.l.",
    "wof:placetype":"venue"
},
  "geometry": {"coordinates":[-4.4179739952,36.7229042053],"type":"Point"}
}