{
  "type": "Feature",
  "properties": {
    "iso:country":"ES",
    "sg:address":"Calle de Txurruka, 12",
    "sg:city":"Donostia-san Sebastian",
    "sg:orig_category":"Reposter\u00cdas",
    "sg:phone":"+34 943 42 02 07",
    "sg:postcode":"20004",
    "sg:province":"Guip\u00f9zcoa",
    "wof:name":"Panificadora Rich, S.l.l.",
    "wof:placetype":"venue"
},
  "geometry": {"coordinates":[-1.9820430279,43.3198623657],"type":"Point"}
}