{
  "type": "Feature",
  "properties": {
    "iso:country":"ES",
    "sg:address":"Carr Reina De La, 11",
    "sg:city":"Xativa",
    "sg:orig_category":"Venta, Montaje De Neum\u00c1ticos",
    "sg:phone":"+34 962 27 44 28",
    "sg:postcode":"46800",
    "sg:province":"Valencia",
    "wof:name":"Aybar Moscardo Adela",
    "wof:placetype":"venue"
},
  "geometry": {"coordinates":[-0.5280368924,38.9870948792],"type":"Point"}
}