{
  "type": "Feature",
  "properties": {
    "iso:country":"ES",
    "sg:address":"Rua Roma\u00d1o (do), S/n",
    "sg:city":"Santiago De Compostela",
    "sg:orig_category":"Ropa Para Caballeros (al Por Menor)",
    "sg:phone":"+34 981 58 65 00",
    "sg:postcode":"15700",
    "sg:province":"La Coru\u00f1a",
    "wof:name":"Confecciones Barmez S.l.",
    "wof:placetype":"venue"
},
  "geometry": {"coordinates":[-8.5445709229,42.9047012329],"type":"Point"}
}