{
  "type": "Feature",
  "properties": {
    "iso:country":"ES",
    "sg:address":"Avda Fuente Del Moral, 23",
    "sg:city":"Moralzarzal",
    "sg:orig_category":"Venta, Alquiler De Instrumentos Y Accesorios De M\u00dasica",
    "sg:phone":"+34 918 42 11 69",
    "sg:postcode":"28411",
    "sg:province":"Madrid",
    "wof:name":"Open Brainstorm, S.l.",
    "wof:placetype":"venue"
},
  "geometry": {"coordinates":[-3.9570059776,40.6774406433],"type":"Point"}
}