{
  "type": "Feature",
  "properties": {
    "addr:full":"Calle de Ca\u00d1ada Real, 4 Estacion Madrid 28400",
    "addr:housenumber":"4 estacion",
    "addr:postcode":"28400",
    "addr:street":"Calle De Can\u0303Ada Real",
    "iso:country":"ES",
    "sg:address":"Calle de Ca\u00d1ada Real, 4",
    "sg:city":"Estacion",
    "sg:orig_category":"Edici\u00d3n De Diarios, Revistas, Boletines",
    "sg:phone":"+34 918 40 62 89",
    "sg:postcode":"28400",
    "sg:province":"Madrid",
    "sg:website":"www.eltelegrafo.org",
    "wof:name":"Villalba Ediciones S.l.",
    "wof:placetype":"venue"
},
  "geometry": {"coordinates":[-4.0184102058,40.6317253113],"type":"Point"}
}