{
  "type": "Feature",
  "properties": {
    "iso:country":"ES",
    "sg:address":"Avda Lugo (de), 4",
    "sg:city":"Taboada",
    "sg:orig_category":"Lavado, Limpieza De Veh\u00cdculos",
    "sg:phone":"+34 982 46 53 75",
    "sg:postcode":"27550",
    "sg:province":"Lugo",
    "wof:name":"Fuentes Morales Jose Luis",
    "wof:placetype":"venue"
},
  "geometry": {"coordinates":[-7.7629389763,42.7198104858],"type":"Point"}
}