{
  "type": "Feature",
  "properties": {
    "addr:full":"Calle de Orotava La, 121 Malaga M\u00e1laga 29006",
    "addr:housenumber":"121",
    "addr:postcode":"29006",
    "addr:street":"Calle De Orotava La;Ma\u0301Laga",
    "iso:country":"ES",
    "sg:address":"Calle de Orotava La, 121",
    "sg:city":"Malaga",
    "sg:orig_category":"Equipo De Refrigeraci\u00d3n Industrial",
    "sg:phone":"+34 952 34 71 15",
    "sg:postcode":"29006",
    "sg:province":"M\u00e1laga",
    "wof:name":"Tienda Sur S.a.",
    "wof:placetype":"venue"
},
  "geometry": {"coordinates":[-4.4699840546,36.7015228271],"type":"Point"}
}