{
  "type": "Feature",
  "properties": {
    "addr:full":"Calle de Carretera, Km. 0272,8 Valcabado Zamora 49192",
    "addr:postcode":"49192",
    "addr:street":"Calle De Carretera Km. 0272,8",
    "iso:country":"ES",
    "sg:address":"Calle de Carretera, Km. 0272,8",
    "sg:city":"Valcabado",
    "sg:orig_category":"Alimentaci\u00d3n General (al Por Mayor)",
    "sg:phone":"+34 980 53 87 27",
    "sg:postcode":"49192",
    "sg:province":"Zamora",
    "wof:name":"Diagro S.l.",
    "wof:placetype":"venue"
},
  "geometry": {"coordinates":[-5.8029990196,41.550819397],"type":"Point"}
}