{
  "type": "Feature",
  "properties": {
    "addr:full":"Calle de Lorenzo Pardo, 4 Zaragoza Zaragoza 50008",
    "addr:housenumber":"4",
    "addr:postcode":"50008",
    "addr:street":"Calle De Lorenzo Pardo",
    "iso:country":"ES",
    "sg:address":"Calle de Lorenzo Pardo, 4",
    "sg:city":"Zaragoza",
    "sg:orig_category":"Panader\u00cdas, Panader\u00cdas",
    "sg:phone":"+34 976 59 76 68",
    "sg:postcode":"50008",
    "sg:province":"Zaragoza",
    "wof:name":"Ramos Leon Ramon",
    "wof:placetype":"venue"
},
  "geometry": {"coordinates":[-0.8742759824,41.6425476074],"type":"Point"}
}