{
  "type": "Feature",
  "properties": {
    "addr:full":"Calle de Felipe Ramirez, 4 Arahal Sevilla 41600",
    "addr:housenumber":"4",
    "addr:postcode":"41600",
    "addr:street":"Calle De Felipe Ramirez",
    "iso:country":"ES",
    "sg:address":"Calle de Felipe Ramirez, 4",
    "sg:city":"Arahal",
    "sg:orig_category":"Abogados",
    "sg:phone":"+34 955 84 12 72",
    "sg:postcode":"41600",
    "sg:province":"Sevilla",
    "wof:name":"Fernandez Garcia Mara Del Valle",
    "wof:placetype":"venue"
},
  "geometry": {"coordinates":[-5.545665741,37.2621917725],"type":"Point"}
}