{
  "type": "Feature",
  "properties": {
    "iso:country":"ES",
    "sg:address":"Calle de Eric Lionel Fox, 3",
    "sg:city":"Santa Cruz De Tenerife",
    "sg:orig_category":"M\u00c9dicos: Estomatolog\u00cda",
    "sg:phone":"+34 922 22 96 04",
    "sg:postcode":"38005",
    "sg:province":"Santa Cruz De Tenerife",
    "wof:name":"Abuelo Vazquez Manuel Jesus",
    "wof:placetype":"venue"
},
  "geometry": {"coordinates":[-16.263079,28.460072],"type":"Point"}
}