{
  "type": "Feature",
  "properties": {
    "addr:full":"Avda Fernandez Ladreda, 11 Pontevedra Pontevedra 36003",
    "addr:housenumber":"11",
    "addr:postcode":"36003",
    "addr:street":"Avda Fernandez Ladreda",
    "iso:country":"ES",
    "sg:address":"Avda Fernandez Ladreda, 11",
    "sg:city":"Pontevedra",
    "sg:orig_category":"Institutos De Belleza",
    "sg:phone":"+34 986 86 09 44",
    "sg:postcode":"36003",
    "sg:province":"Pontevedra",
    "wof:name":"Rodriguez Valverde Andrea",
    "wof:placetype":"venue"
},
  "geometry": {"coordinates":[-8.6522274017,42.4269256592],"type":"Point"}
}