{
  "type": "Feature",
  "properties": {
    "addr:full":"Escala Esplai, S/n Escala Girona 17130",
    "addr:housenumber":"s / n",
    "addr:postcode":"17130",
    "iso:country":"ES",
    "sg:address":"Escala Esplai, S/n",
    "sg:city":"Escala",
    "sg:orig_category":"Empresas De Carpinter\u00cda",
    "sg:phone":"+34 972 77 05 16",
    "sg:postcode":"17130",
    "sg:province":"Girona",
    "wof:name":"Clemente Suazo Vicente",
    "wof:placetype":"venue"
},
  "geometry": {"coordinates":[3.1321649551,42.1229934692],"type":"Point"}
}