{
  "type": "Feature",
  "properties": {
    "addr:full":"Pl Jaume I, 4 Vilafranca Penedes Barcelona 08720",
    "addr:postcode":"08720",
    "addr:street":"Pl;Vilafranca Penedes Barcelona",
    "iso:country":"ES",
    "sg:address":"Pl Jaume I, 4",
    "sg:city":"Vilafranca Penedes",
    "sg:orig_category":"Caf\u00c9s, Bares, Cervecer\u00cdas",
    "sg:phone":"+34 938 17 47 11",
    "sg:postcode":"08720",
    "sg:province":"Barcelona",
    "wof:name":"Anfi Vilafranca S.l.",
    "wof:placetype":"venue"
},
  "geometry": {"coordinates":[1.6986479759,41.348777771],"type":"Point"}
}