{
  "type": "Feature",
  "properties": {
    "iso:country":"ES",
    "sg:address":"Carr Cami De Marimunt, 46",
    "sg:city":"Lleida",
    "sg:orig_category":"Empresarios Y Productoras De Espect\u00c1culos",
    "sg:phone":"+34 973 24 33 21",
    "sg:postcode":"25005",
    "sg:province":"Lleida",
    "sg:website":"www.xipxap.com",
    "wof:name":"Xip-xap S.l.",
    "wof:placetype":"venue"
},
  "geometry": {"coordinates":[0.6263669133,41.6385612488],"type":"Point"}
}