{
  "type": "Feature",
  "properties": {
    "addr:full":"Ctra Villanueva Rio-s Traviesa, S/n Villanueva Rio Y Minas Sevilla 41350",
    "addr:housenumber":"s",
    "addr:postcode":"41350",
    "addr:street":"Ctra Villanueva Rio-S;/ N",
    "iso:country":"ES",
    "sg:address":"Ctra Villanueva Rio-s Traviesa, S/n",
    "sg:city":"Villanueva Rio Y Minas",
    "sg:orig_category":"Agricultores, Agricultores",
    "sg:phone":"+34 955 95 30 09",
    "sg:postcode":"41350",
    "sg:province":"Sevilla",
    "wof:name":"Promociones B-4 S.a.",
    "wof:placetype":"venue"
},
  "geometry": {"coordinates":[-5.7183542252,37.6519584656],"type":"Point"}
}