{
  "type": "Feature",
  "properties": {
    "addr:full":"Carrer de Balmes, 184 Barcelona Barcelona 08006",
    "addr:housenumber":"184",
    "addr:postcode":"08006",
    "addr:street":"Carrer De Balmes",
    "iso:country":"ES",
    "sg:address":"Carrer de Balmes, 184",
    "sg:city":"Barcelona",
    "sg:orig_category":"Inform\u00c1tica (estudios, Servicios, Asesor\u00cda, Formaci\u00d3n)",
    "sg:phone":"+34 933 42 72 72",
    "sg:postcode":"08006",
    "sg:province":"Barcelona",
    "sg:website":"www.signiatech.net",
    "wof:name":"Signia Tecnologies S.l.",
    "wof:placetype":"venue"
},
  "geometry": {"coordinates":[2.1533150673,41.3965988159],"type":"Point"}
}