{
  "type": "Feature",
  "properties": {
    "iso:country":"ES",
    "sg:address":"Lug. Tordable, S/n",
    "sg:city":"Villalmanzo",
    "sg:orig_category":"Producci\u00d3n, Venta De Productos De Agricultura Biol\u00d3gica",
    "sg:phone":"+34 947 17 01 49",
    "sg:postcode":"09390",
    "sg:province":"Burgos",
    "wof:name":"Tordable",
    "wof:placetype":"venue"
},
  "geometry": {"coordinates":[-3.7047789097,42.0872116089],"type":"Point"}
}