{
  "type": "Feature",
  "properties": {
    "addr:full":"Avda Portugal (de), 18 San Jose Murcia 30800",
    "addr:housenumber":"18",
    "addr:postcode":"30800",
    "addr:street":"Avda Portugal De",
    "iso:country":"ES",
    "sg:address":"Avda Portugal (de), 18",
    "sg:city":"San Jose",
    "sg:orig_category":"Lencer\u00cda Femenina, Corseter\u00cda, Trajes De Ba\u00d1o (al Por Menor)",
    "sg:phone":"+34 968 46 00 04",
    "sg:postcode":"30800",
    "sg:province":"Murcia",
    "wof:name":"Ruiz Lopez Juana",
    "wof:placetype":"venue"
},
  "geometry": {"coordinates":[-1.6905640364,37.680557251],"type":"Point"}
}