{
  "type": "Feature",
  "properties": {
    "addr:full":"Avda San Jose De La Monta\u00d1a, 15 Valencia Valencia 46008",
    "addr:housenumber":"15",
    "addr:postcode":"46008",
    "addr:street":"Avda San Jose De La Montan\u0303A",
    "iso:country":"ES",
    "sg:address":"Avda San Jose De La Monta\u00d1a, 15",
    "sg:city":"Valencia",
    "sg:orig_category":"Obras Y Organismos Sociales",
    "sg:phone":"+34 963 84 35 01",
    "sg:postcode":"46008",
    "sg:province":"Valencia",
    "sg:website":"www.resagradocorazon.e.telefonica.net",
    "wof:name":"Congregacion De Madres Desamparados Y S.",
    "wof:placetype":"venue"
},
  "geometry": {"coordinates":[-0.3941330016,39.4742279053],"type":"Point"}
}