{
  "type": "Feature",
  "properties": {
    "addr:full":"San Xulian De Abaixo, S/n Hospital Lugo 27320",
    "addr:housenumber":"s / n",
    "addr:postcode":"27320",
    "iso:country":"ES",
    "sg:address":"San Xulian De Abaixo, S/n",
    "sg:city":"Hospital",
    "sg:orig_category":"Empresarios",
    "sg:phone":"+34 982 42 88 22",
    "sg:postcode":"27320",
    "sg:province":"Lugo",
    "wof:name":"Gonzalez Rodriguez Antonio",
    "wof:placetype":"venue"
},
  "geometry": {"coordinates":[-7.2701539993,42.4753761292],"type":"Point"}
}