{
  "type": "Feature",
  "properties": {
    "addr:full":"Ptda El Collao, 16 Enguera Valencia 46810",
    "addr:housenumber":"16",
    "addr:postcode":"46810",
    "addr:street":"Ptda El Collao",
    "iso:country":"ES",
    "sg:address":"Ptda El Collao, 16",
    "sg:city":"Enguera",
    "sg:orig_category":"Granos Y Semillas (producci\u00d3n, Al Por Mayor)",
    "sg:phone":"+34 962 22 53 70",
    "sg:postcode":"46810",
    "sg:province":"Valencia",
    "wof:name":"Esteve Rivera Jose",
    "wof:placetype":"venue"
},
  "geometry": {"coordinates":[-0.6887639761,38.9810943604],"type":"Point"}
}