{
  "type": "Feature",
  "properties": {
    "addr:full":"Carr Doctor Fleming, S/n Torregrossa Lleida 25141",
    "addr:housenumber":"s",
    "addr:postcode":"25141",
    "addr:street":"Carr Doctor Fleming;/ N",
    "iso:country":"ES",
    "sg:address":"Carr Doctor Fleming, S/n",
    "sg:city":"Torregrossa",
    "sg:orig_category":"Comercio, Reparaci\u00d3n De Bicicletas, De Motocicletas, De Accesorios",
    "sg:phone":"+34 973 17 00 00",
    "sg:postcode":"25141",
    "sg:province":"Lleida",
    "wof:name":"Pelegri Solsona Jaime",
    "wof:placetype":"venue"
},
  "geometry": {"coordinates":[0.8324049711,41.5803718567],"type":"Point"}
}