{
  "type": "Feature",
  "properties": {
    "addr:full":"Calle de Catedratico Jimenez De Gregorio, 4 San Javier Murcia 30730",
    "addr:housenumber":"4",
    "addr:postcode":"30730",
    "addr:street":"Calle De Catedratico Jimenez De Gregorio",
    "iso:country":"ES",
    "sg:address":"Calle de Catedratico Jimenez De Gregorio, 4",
    "sg:city":"San Javier",
    "sg:orig_category":"Abogados",
    "sg:phone":"+34 968 19 03 03",
    "sg:postcode":"30730",
    "sg:province":"Murcia",
    "wof:name":"Garcia Garcia Juan",
    "wof:placetype":"venue"
},
  "geometry": {"coordinates":[-0.8389251828,37.8164138794],"type":"Point"}
}