{
  "type": "Feature",
  "properties": {
    "iso:country":"ES",
    "sg:address":"Av Josep Gramunt I Subiela (de), 46",
    "sg:city":"Tarragona",
    "sg:orig_category":"Arquitectos",
    "sg:phone":"+34 977 21 85 46",
    "sg:postcode":"43007",
    "sg:province":"Tarragona",
    "wof:name":"Magre Cardona Juan",
    "wof:placetype":"venue"
},
  "geometry": {"coordinates":[1.2497149706,41.1251678467],"type":"Point"}
}