{
  "type": "Feature",
  "properties": {
    "addr:full":"Avda Industria (de La), 32 Alcobendas Madrid 28108",
    "addr:housenumber":"32",
    "addr:postcode":"28108",
    "addr:street":"Avda Industria De La",
    "iso:country":"ES",
    "sg:address":"Avda Industria (de La), 32",
    "sg:city":"Alcobendas",
    "sg:orig_category":"Cajas De Ahorro",
    "sg:phone":"+34 914 90 15 40",
    "sg:postcode":"28108",
    "sg:province":"Madrid",
    "wof:name":"Caixa D'estalvis Del Penedes",
    "wof:placetype":"venue"
},
  "geometry": {"coordinates":[-3.6505000591,40.5345573425],"type":"Point"}
}