{
  "type": "Feature",
  "properties": {
    "addr:full":"Cjto Golf Garden, 2 Calahonda M\u00e1laga 29647",
    "addr:housenumber":"2",
    "addr:postcode":"29647",
    "addr:street":"Calahonda Ma\u0301Laga",
    "iso:country":"ES",
    "sg:address":"Cjto Golf Garden, 2",
    "sg:city":"Calahonda",
    "sg:orig_category":"Inmobiliaria (agencias)",
    "sg:phone":"+34 952 93 54 95",
    "sg:postcode":"29647",
    "sg:province":"M\u00e1laga",
    "wof:name":"Por Y House Y Par S.l.",
    "wof:placetype":"venue"
},
  "geometry": {"coordinates":[-4.7157039642,36.4931945801],"type":"Point"}
}