{
  "type": "Feature",
  "properties": {
    "addr:full":"Calle de Raquel Meller, 8 Zaragoza Zaragoza 50008",
    "addr:housenumber":"8",
    "addr:postcode":"50008",
    "addr:street":"Calle De Raquel Meller",
    "iso:country":"ES",
    "sg:address":"Calle de Raquel Meller, 8",
    "sg:city":"Zaragoza",
    "sg:orig_category":"Peluqueros: De Se\u00d1oras",
    "sg:phone":"+34 976 59 17 57",
    "sg:postcode":"50008",
    "sg:province":"Zaragoza",
    "wof:name":"Sicilia Sicilia Maria Pilar",
    "wof:placetype":"venue"
},
  "geometry": {"coordinates":[-0.8732209802,41.637462616],"type":"Point"}
}