{
  "type": "Feature",
  "properties": {
    "addr:full":"Calle de Nueva, 6 Montalban Teruel 44700",
    "addr:housenumber":"6",
    "addr:postcode":"44700",
    "addr:street":"Calle De Nueva",
    "iso:country":"ES",
    "sg:address":"Calle de Nueva, 6",
    "sg:city":"Montalban",
    "sg:orig_category":"Estancos",
    "sg:phone":"+34 978 75 01 84",
    "sg:postcode":"44700",
    "sg:province":"Teruel",
    "wof:name":"Lancis Monzon Maria Del Carmen",
    "wof:placetype":"venue"
},
  "geometry": {"coordinates":[-0.7987400293,40.8321266174],"type":"Point"}
}