{
  "type": "Feature",
  "properties": {
    "addr:full":"Plaz San Julian Del Mercado, 15 Zamora Zamora 49002",
    "addr:housenumber":"15",
    "addr:postcode":"49002",
    "addr:street":"Plaz San Julian Del Mercado",
    "iso:country":"ES",
    "sg:address":"Plaz San Julian Del Mercado, 15",
    "sg:city":"Zamora",
    "sg:orig_category":"Iglesia Cat\u00d3lica",
    "sg:phone":"+34 980 53 32 58",
    "sg:postcode":"49002",
    "sg:province":"Zamora",
    "wof:name":"Obispado De Zamora",
    "wof:placetype":"venue"
},
  "geometry": {"coordinates":[-5.7457151413,41.5006408691],"type":"Point"}
}