{
  "type": "Feature",
  "properties": {
    "iso:country":"ES",
    "sg:address":"Calle de H(poligono Industrial), 1",
    "sg:city":"Villarrobledo",
    "sg:orig_category":"Adaptaciones, Acondicionamientos Especiales Para Veh\u00cdculos, Veh\u00cdculos Industriales",
    "sg:phone":"+34 967 14 57 82",
    "sg:postcode":"02600",
    "sg:province":"Albacete",
    "wof:name":"Agromecanica Villarobledo Sl",
    "wof:placetype":"venue"
},
  "geometry": {"coordinates":[-2.590074,39.276505],"type":"Point"}
}