{
  "type": "Feature",
  "properties": {
    "iso:country":"ES",
    "sg:address":"Calle de Valle De Ordesa, S/n",
    "sg:city":"Monzon",
    "sg:orig_category":"Empresas De Carpinter\u00cda",
    "sg:phone":"+34 974 41 51 16",
    "sg:postcode":"22400",
    "sg:province":"Huesca",
    "wof:name":"Aluminios Catedra S.l.",
    "wof:placetype":"venue"
},
  "geometry": {"coordinates":[0.1682271063,41.8996734619],"type":"Point"}
}