{
  "type": "Feature",
  "properties": {
    "addr:full":"Calle de Tharsis, S/n Sevilla Sevilla 41008",
    "addr:housenumber":"s / n",
    "addr:postcode":"41008",
    "addr:street":"Calle De Tharsis",
    "iso:country":"ES",
    "sg:address":"Calle de Tharsis, S/n",
    "sg:city":"Sevilla",
    "sg:orig_category":"Mec\u00c1nico Del Autom\u00d3vil",
    "sg:phone":"+34 954 41 51 57",
    "sg:postcode":"41008",
    "sg:province":"Sevilla",
    "wof:name":"Gomez Chia Enrique",
    "wof:placetype":"venue"
},
  "geometry": {"coordinates":[-5.9729189873,37.3987617493],"type":"Point"}
}