{
  "type": "Feature",
  "properties": {
    "iso:country":"ES",
    "sg:address":"Calle de Juan De Austria, 4",
    "sg:city":"Parla",
    "sg:orig_category":"Comercio De Piezas De Recambio Y De Accesorios De Veh\u00cdculos, Veh\u00cdculos Industriales",
    "sg:phone":"+34 916 05 17 89",
    "sg:postcode":"28980",
    "sg:province":"Madrid",
    "wof:name":"Diez Lopez Jesus Antonio",
    "wof:placetype":"venue"
},
  "geometry": {"coordinates":[-3.7700619698,40.2355308533],"type":"Point"}
}