{
  "type": "Feature",
  "properties": {
    "iso:country":"ES",
    "sg:address":"Cno. Palomeque, S/n",
    "sg:city":"Cedillo Condado",
    "sg:orig_category":"Hornos Industriales",
    "sg:phone":"+34 925 50 83 50",
    "sg:postcode":"45214",
    "sg:province":"Toledo",
    "wof:name":"Eustaquio Pasero Gonzalez Y Otro C.b.",
    "wof:placetype":"venue"
},
  "geometry": {"coordinates":[-3.9259839058,40.1141433716],"type":"Point"}
}