{
  "type": "Feature",
  "properties": {
    "iso:country":"ES",
    "sg:address":"Calle de Larga, 27",
    "sg:city":"Godelleta",
    "sg:orig_category":"Distribuci\u00d3n De Petr\u00d3leo Y Derivados",
    "sg:phone":"+34 961 80 00 62",
    "sg:postcode":"46388",
    "sg:province":"Valencia",
    "wof:name":"Pescados Y Mariscos V. Boluda S.l.",
    "wof:placetype":"venue"
},
  "geometry": {"coordinates":[-0.6867619753,39.4229354858],"type":"Point"}
}