{
  "type": "Feature",
  "properties": {
    "iso:country":"ES",
    "sg:address":"Calle de San Mames, 2",
    "sg:city":"Santa Maria Del Paramo",
    "sg:classifiers":[
        {
            "category":"Taxi",
            "type":"Transportation"
        }
    ],
    "sg:phone":"+34 987 35 16 26",
    "sg:postcode":"24240",
    "sg:province":"Le\u00f3n",
    "wof:name":"Pozo Llamera Aquilino Del",
    "wof:placetype":"venue"
},
  "geometry": {"coordinates":[-5.7555441856,42.3532295227],"type":"Point"}
}