{
  "type": "Feature",
  "properties": {
    "addr:full":"Avda Val Mi\u00d1or, 12 Vilamean Pontevedra 36350",
    "addr:housenumber":"12",
    "addr:postcode":"36350",
    "addr:street":"Avda Val Min\u0303Or",
    "iso:country":"ES",
    "sg:address":"Avda Val Mi\u00d1or, 12",
    "sg:city":"Vilamean",
    "sg:orig_category":"Carnicer\u00cdas, Carnicer\u00cdas",
    "sg:phone":"+34 986 36 86 80",
    "sg:postcode":"36350",
    "sg:province":"Pontevedra",
    "wof:name":"Giraldez Garcia Pablo",
    "wof:placetype":"venue"
},
  "geometry": {"coordinates":[-8.8063592911,42.1425476074],"type":"Point"}
}