{
  "type": "Feature",
  "properties": {
    "iso:country":"ES",
    "sg:address":"Calle de Fronton (el), 3",
    "sg:city":"Cadreita",
    "sg:orig_category":"Art\u00cdculos Funerarios (al Por Menor)",
    "sg:phone":"+34 948 84 48 91",
    "sg:postcode":"31515",
    "sg:province":"Navarra",
    "wof:name":"La Rivera Gestiones Funebres S.l.",
    "wof:placetype":"venue"
},
  "geometry": {"coordinates":[-1.6958600283,42.2171096802],"type":"Point"}
}