{
  "type": "Feature",
  "properties": {
    "iso:country":"ES",
    "sg:address":"Luga Carrus Poligono Industrial, 26",
    "sg:city":"Elche",
    "sg:orig_category":"Confecci\u00d3n De Zapatos",
    "sg:phone":"+34 965 46 92 12",
    "sg:postcode":"03291",
    "sg:province":"Alicante",
    "wof:name":"Advenced Logic Shoes Sl",
    "wof:placetype":"venue"
},
  "geometry": {"coordinates":[-0.7449640036,38.2628173828],"type":"Point"}
}