{
  "type": "Feature",
  "properties": {
    "addr:full":"Ctra Estacio, 23 Anglesola Lleida 25320",
    "addr:housenumber":"23",
    "addr:postcode":"25320",
    "addr:street":"Ctra Estacio",
    "iso:country":"ES",
    "sg:address":"Ctra Estacio, 23",
    "sg:city":"Anglesola",
    "sg:orig_category":"Maquinaria Para Industrias Diversas",
    "sg:phone":"+34 973 30 81 11",
    "sg:postcode":"25320",
    "sg:province":"Lleida",
    "wof:name":"Auctions Second Hand S.l",
    "wof:placetype":"venue"
},
  "geometry": {"coordinates":[1.0811289549,41.6523475647],"type":"Point"}
}