{
  "type": "Feature",
  "properties": {
    "addr:full":"Calle de Juan Manuel Duran Gonzalez, 28 Palmas De Gran Canaria Las Palmas 35007",
    "addr:housenumber":"28",
    "addr:postcode":"35007",
    "addr:street":"Calle De Juan Manuel Duran Gonzalez",
    "iso:country":"ES",
    "sg:address":"Calle de Juan Manuel Duran Gonzalez, 28",
    "sg:city":"Palmas De Gran Canaria",
    "sg:orig_category":"Electrodom\u00c9sticos (al Por Menor)",
    "sg:phone":"+34 928 22 56 45",
    "sg:postcode":"35007",
    "sg:province":"Las Palmas",
    "wof:name":"Gonzalez Mayor Ignacio",
    "wof:placetype":"venue"
},
  "geometry": {"coordinates":[-15.4335870743,28.135477066],"type":"Point"}
}