{
  "type": "Feature",
  "properties": {
    "iso:country":"ES",
    "sg:address":"Calle de Agua (el), 1",
    "sg:city":"Lucena",
    "sg:orig_category":"Art\u00cdculos De Regalo (al Por Menor)",
    "sg:phone":"+34 957 50 06 17",
    "sg:postcode":"14900",
    "sg:province":"C\u00f3rdoba",
    "wof:name":"Sanchez Gonzalez Miguel",
    "wof:placetype":"venue"
},
  "geometry": {"coordinates":[-4.4874815941,37.4086723328],"type":"Point"}
}