{
  "type": "Feature",
  "properties": {
    "iso:country":"ES",
    "sg:address":"Carrer de Girona, 173",
    "sg:city":"Barcelona",
    "sg:orig_category":"Fabricaci\u00d3n, Importaci\u00d3n De L\u00c1mparas Y Bombillas",
    "sg:phone":"+34 934 57 19 18",
    "sg:postcode":"08037",
    "sg:province":"Barcelona",
    "wof:name":"Instalaciones Electricas Ifmar S. A.",
    "wof:placetype":"venue"
},
  "geometry": {"coordinates":[2.1646499634,41.3995285034],"type":"Point"}
}