{
  "type": "Feature",
  "properties": {
    "iso:country":"ES",
    "sg:address":"Carretas, 12",
    "sg:city":"El Rocio",
    "sg:orig_category":"Ropa Y Accesorios",
    "sg:phone":"+34 959 44 20 90",
    "sg:postcode":"21750",
    "sg:province":"Huelva",
    "wof:name":"Martinez Perez Manuel",
    "wof:placetype":"venue"
},
  "geometry": {"coordinates":[-6.4851679802,37.1313781738],"type":"Point"}
}