{
  "type": "Feature",
  "properties": {
    "addr:full":"Ctra Balsa, 30 Ribas Pontevedra 36213",
    "addr:housenumber":"30",
    "addr:postcode":"36213",
    "addr:street":"Ctra Balsa",
    "iso:country":"ES",
    "sg:address":"Ctra Balsa, 30",
    "sg:city":"Ribas",
    "sg:orig_category":"Chapister\u00cda",
    "sg:phone":"+34 986 29 61 63",
    "sg:postcode":"36213",
    "sg:province":"Pontevedra",
    "wof:name":"Alonso Novoa Jacobo",
    "wof:placetype":"venue"
},
  "geometry": {"coordinates":[-8.6480531693,42.4336204529],"type":"Point"}
}