{
  "type": "Feature",
  "properties": {
    "addr:full":"Avda Antonio Mairena, 66 Alcala Guadaira Sevilla 41500",
    "addr:housenumber":"66",
    "addr:postcode":"41500",
    "addr:street":"Avda Antonio Mairena",
    "iso:country":"ES",
    "sg:address":"Avda Antonio Mairena, 66",
    "sg:city":"Alcala Guadaira",
    "sg:orig_category":"Molduras, Junquillos, Listones Y Molduras Perforadas",
    "sg:phone":"+34 955 61 44 34",
    "sg:postcode":"41500",
    "sg:province":"Sevilla",
    "wof:name":"Casares Lamu\u00f1o Maria Antonia",
    "wof:placetype":"venue"
},
  "geometry": {"coordinates":[-5.8365950584,37.33934021],"type":"Point"}
}