{
  "type": "Feature",
  "properties": {
    "addr:full":"Avda Valencia, 1 Calamocha Teruel 44200",
    "addr:housenumber":"1",
    "addr:postcode":"44200",
    "addr:street":"Avda Valencia",
    "iso:country":"ES",
    "sg:address":"Avda Valencia, 1",
    "sg:city":"Calamocha",
    "sg:orig_category":"Molduras, Junquillos, Listones Y Molduras Perforadas",
    "sg:phone":"+34 978 73 01 02",
    "sg:postcode":"44200",
    "sg:province":"Teruel",
    "wof:name":"Asociacion Tercera Edad Jubilados Y Pensionistas",
    "wof:placetype":"venue"
},
  "geometry": {"coordinates":[-1.2980606556,40.9215240479],"type":"Point"}
}