{
  "type": "Feature",
  "properties": {
    "addr:full":"Rond Sancti Spiritus, 18 Salamanca Salamanca 37001",
    "addr:housenumber":"18",
    "addr:postcode":"37001",
    "addr:street":"Rond Sancti Spiritus",
    "iso:country":"ES",
    "sg:address":"Rond Sancti Spiritus, 18",
    "sg:city":"Salamanca",
    "sg:classifiers":[
        {
            "category":"Banks & Credit Unions",
            "subcategory":"Bureau De Change",
            "type":"Services"
        }
    ],
    "sg:phone":"+34 923 26 68 87",
    "sg:postcode":"37001",
    "sg:province":"Salamanca",
    "sg:tags":[
        "organismos",
        "control"
    ],
    "wof:name":"Eurocontrol S.a.",
    "wof:placetype":"venue"
},
  "geometry": {"coordinates":[-5.6592769623,40.9649124146],"type":"Point"}
}