{
  "type": "Feature",
  "properties": {
    "addr:full":"Plaz Carlos Trias Bertran, 4 Madrid Madrid 28020",
    "addr:housenumber":"4",
    "addr:postcode":"28020",
    "addr:street":"Bertran",
    "iso:country":"ES",
    "sg:address":"Plaz Carlos Trias Bertran, 4",
    "sg:city":"Madrid",
    "sg:orig_category":"Financiaci\u00d3n Y Cr\u00c9ditos",
    "sg:phone":"+34 915 98 03 69",
    "sg:postcode":"28020",
    "sg:province":"Madrid",
    "wof:name":"Centro De Asesoria Hipotecaria S.l.",
    "wof:placetype":"venue"
},
  "geometry": {"coordinates":[-3.6936919689,40.4509353638],"type":"Point"}
}