{
  "type": "Feature",
  "properties": {
    "iso:country":"ES",
    "sg:address":"Calle de Predicadores, 13",
    "sg:city":"Zaragoza",
    "sg:orig_category":"Alimentaci\u00d3n General (al Por Menor)",
    "sg:phone":"+34 976 43 04 23",
    "sg:postcode":"50003",
    "sg:province":"Zaragoza",
    "wof:name":"Francisco Diez S. L.",
    "wof:placetype":"venue"
},
  "geometry": {"coordinates":[-0.8831980228,41.6569328308],"type":"Point"}
}