{
  "type": "Feature",
  "properties": {
    "iso:country":"ES",
    "sg:address":"Calle de San Carlos Borromeo, 23",
    "sg:city":"Cieza",
    "sg:orig_category":"Aguas (distribuci\u00d3n, Servicios)",
    "sg:phone":"+34 968 45 64 34",
    "sg:postcode":"30530",
    "sg:province":"Murcia",
    "wof:name":"Garcia Lopez Maria Pilar",
    "wof:placetype":"venue"
},
  "geometry": {"coordinates":[-1.4150890112,38.2360305786],"type":"Point"}
}