{
  "type": "Feature",
  "properties": {
    "addr:full":"Poligon C, S/n Xativa Valencia 46800",
    "addr:housenumber":"/ n",
    "addr:postcode":"46800",
    "addr:street":"C S",
    "iso:country":"ES",
    "sg:address":"Poligon C, S/n",
    "sg:city":"Xativa",
    "sg:orig_category":"Lavado, Limpieza De Veh\u00cdculos",
    "sg:phone":"+34 962 27 42 09",
    "sg:postcode":"46800",
    "sg:province":"Valencia",
    "wof:name":"Garcia Perez Jose",
    "wof:placetype":"venue"
},
  "geometry": {"coordinates":[-0.5427367091,38.9142379761],"type":"Point"}
}