{
  "type": "Feature",
  "properties": {
    "iso:country":"ES",
    "sg:address":"Avda Tierra Llana, 56",
    "sg:city":"Vilalba",
    "sg:orig_category":"Electrodom\u00c9sticos (al Por Menor)",
    "sg:phone":"+34 982 51 21 49",
    "sg:postcode":"27800",
    "sg:province":"Lugo",
    "wof:name":"Seoane Trastoy Florentino",
    "wof:placetype":"venue"
},
  "geometry": {"coordinates":[-7.6766757965,43.2959022522],"type":"Point"}
}