{
  "type": "Feature",
  "properties": {
    "addr:full":"Calle de Hernan Cortes, 11 Santander Cantabria 39003",
    "addr:housenumber":"11",
    "addr:postcode":"39003",
    "addr:street":"Calle De Hernan Cortes",
    "iso:country":"ES",
    "sg:address":"Calle de Hernan Cortes, 11",
    "sg:city":"Santander",
    "sg:orig_category":"Bancos",
    "sg:phone":"+34 942 36 70 08",
    "sg:postcode":"39003",
    "sg:province":"Cantabria",
    "wof:name":"Banco Espa\u00f1ol De Credito S.a.",
    "wof:placetype":"venue"
},
  "geometry": {"coordinates":[-3.8037760258,43.4627037048],"type":"Point"}
}