{
  "type": "Feature",
  "properties": {
    "addr:full":"Carrer de Escultor Modest Gene, 23 Reus Tarragona 43204",
    "addr:housenumber":"23",
    "addr:postcode":"43204",
    "addr:street":"Carrer De Escultor Modest Gene",
    "iso:country":"ES",
    "sg:address":"Carrer de Escultor Modest Gene, 23",
    "sg:city":"Reus",
    "sg:orig_category":"Librer\u00cdas",
    "sg:phone":"+34 977 75 34 35",
    "sg:postcode":"43204",
    "sg:province":"Tarragona",
    "wof:name":"Llibreria Sobrerroca S.a.",
    "wof:placetype":"venue"
},
  "geometry": {"coordinates":[1.1146090031,41.154838562],"type":"Point"}
}