{
  "type": "Feature",
  "properties": {
    "iso:country":"ES",
    "sg:address":"Ctra Herville, 60",
    "sg:city":"Cidans",
    "sg:orig_category":"Casas Con Estructura De Madera",
    "sg:phone":"+34 986 46 71 24",
    "sg:postcode":"36310",
    "sg:province":"Pontevedra",
    "wof:name":"Primer Argentino S.l.",
    "wof:placetype":"venue"
},
  "geometry": {"coordinates":[-8.6795969009,42.1573181152],"type":"Point"}
}