{
  "type": "Feature",
  "properties": {
    "addr:full":"Calle de Mercurio (pol. Ind.), 15 Marbella M\u00e1laga 29600",
    "addr:housenumber":"15",
    "addr:postcode":"29600",
    "addr:street":"Calle De Mercurio Pol. Ind.;Ma\u0301Laga",
    "iso:country":"ES",
    "sg:address":"Calle de Mercurio (pol. Ind.), 15",
    "sg:city":"Marbella",
    "sg:orig_category":"Transporte En General",
    "sg:phone":"+34 952 89 80 72",
    "sg:postcode":"29600",
    "sg:province":"M\u00e1laga",
    "wof:name":"Servicios Especiales S. A.",
    "wof:placetype":"venue"
},
  "geometry": {"coordinates":[-4.8678708076,36.5120277405],"type":"Point"}
}