{
  "type": "Feature",
  "properties": {
    "addr:full":"Carr Carles Rahola, 30 Girona Girona 17003",
    "addr:housenumber":"30",
    "addr:postcode":"17003",
    "addr:street":"Carr Carles Rahola",
    "iso:country":"ES",
    "sg:address":"Carr Carles Rahola, 30",
    "sg:city":"Girona",
    "sg:orig_category":"Promotores Constructores",
    "sg:phone":"+34 972 20 65 27",
    "sg:postcode":"17003",
    "sg:province":"Girona",
    "wof:name":"Construcciones Enrique Carmona S.l.",
    "wof:placetype":"venue"
},
  "geometry": {"coordinates":[2.8161458969,41.9699363708],"type":"Point"}
}