{
  "type": "Feature",
  "properties": {
    "addr:full":"Carrer de Marques De Comillas, 139 Sabadell Barcelona 08202",
    "addr:housenumber":"139",
    "addr:postcode":"08202",
    "addr:street":"Carrer De Marques De Comillas",
    "iso:country":"ES",
    "sg:address":"Carrer de Marques De Comillas, 139",
    "sg:city":"Sabadell",
    "sg:orig_category":"Peluquer\u00cdas, Peluquer\u00cda Mixta",
    "sg:phone":"+34 937 45 90 18",
    "sg:postcode":"08202",
    "sg:province":"Barcelona",
    "wof:name":"Centro Tecnico Miralles Martinez S L",
    "wof:placetype":"venue"
},
  "geometry": {"coordinates":[2.116410017,41.5451889038],"type":"Point"}
}