{
  "type": "Feature",
  "properties": {
    "iso:country":"ES",
    "sg:address":"Calle de Riscos Altos, 11",
    "sg:city":"Sevilla",
    "sg:orig_category":"Aparatos, Sistemas De Tele",
    "sg:phone":"+34 954 62 96 62",
    "sg:postcode":"41013",
    "sg:province":"Sevilla",
    "wof:name":"Sistemax S.l.",
    "wof:placetype":"venue"
},
  "geometry": {"coordinates":[-5.9734091759,37.3675460815],"type":"Point"}
}