{
  "type": "Feature",
  "properties": {
    "iso:country":"ES",
    "sg:address":"Pol Ind El Rubial, S/n",
    "sg:city":"Villena",
    "sg:orig_category":"Producci\u00d3n, Venta De Productos De Agricultura Biol\u00d3gica",
    "sg:phone":"+34 965 34 03 25",
    "sg:postcode":"03400",
    "sg:province":"Alicante",
    "wof:name":"Atlantica Agricola S.a.",
    "wof:placetype":"venue"
},
  "geometry": {"coordinates":[-0.8865833879,38.6286621094],"type":"Point"}
}