{
  "type": "Feature",
  "properties": {
    "iso:country":"ES",
    "sg:address":"Carr San Vicente Martir, 3",
    "sg:city":"Faro",
    "sg:orig_category":"Inmobiliaria (agencias)",
    "sg:phone":"+34 961 74 66 02",
    "sg:postcode":"46408",
    "sg:province":"Valencia",
    "wof:name":"Futuro Servicios Inmobiliarios S.l.",
    "wof:placetype":"venue"
},
  "geometry": {"coordinates":[-0.2200939953,39.1828956604],"type":"Point"}
}