{
  "type": "Feature",
  "properties": {
    "addr:full":"Rua Travesia De Vigo, 219 Roris Pontevedra 36207",
    "addr:housenumber":"219",
    "addr:postcode":"36207",
    "addr:street":"Rua Travesia De Vigo",
    "iso:country":"ES",
    "sg:address":"Rua Travesia De Vigo, 219",
    "sg:city":"Roris",
    "sg:orig_category":"Centros Empresariales",
    "sg:phone":"+34 986 27 57 34",
    "sg:postcode":"36207",
    "sg:province":"Pontevedra",
    "wof:name":"Herbolarios Asociados De Pontevedra",
    "wof:placetype":"venue"
},
  "geometry": {"coordinates":[-8.6667003632,42.25],"type":"Point"}
}