{
  "type": "Feature",
  "properties": {
    "iso:country":"ES",
    "sg:address":"Rbla Rei En Jaume, 5",
    "sg:city":"Manacor",
    "sg:classifiers":[
        {
            "category":"Autos & Motor Vehicles",
            "subcategory":"Automobile Sales",
            "type":"Retail Goods"
        }
    ],
    "sg:phone":"+34 971 84 43 82",
    "sg:postcode":"07500",
    "sg:province":"Islas Baleares",
    "wof:name":"Campins Ayuso Matias",
    "wof:placetype":"venue"
},
  "geometry": {"coordinates":[3.2127900124,39.5662498474],"type":"Point"}
}