{
  "type": "Feature",
  "properties": {
    "addr:full":"Plaz Espa\u00d1a (paseo Del Coso), 11 Lucena C\u00f3rdoba 14900",
    "addr:housenumber":"11",
    "addr:postcode":"14900",
    "addr:street":"Plaz;Paseo Del Coso",
    "iso:country":"ES",
    "sg:address":"Plaz Espa\u00d1a (paseo Del Coso), 11",
    "sg:city":"Lucena",
    "sg:orig_category":"M\u00c9dicos: Gastroenterolog\u00cda Y Hepatolog\u00cda (aparato Digestivo)",
    "sg:phone":"+34 957 50 08 90",
    "sg:postcode":"14900",
    "sg:province":"C\u00f3rdoba",
    "wof:name":"Arjona Varo Manuel",
    "wof:placetype":"venue"
},
  "geometry": {"coordinates":[-4.4840459824,37.4076118469],"type":"Point"}
}