{
  "type": "Feature",
  "properties": {
    "addr:full":"C/ Canonge Quetglas, 21 Inca Islas Baleares 07300",
    "addr:housenumber":"21",
    "addr:postcode":"07300",
    "addr:street":"C / Canonge Quetglas",
    "iso:country":"ES",
    "sg:address":"C/ Canonge Quetglas, 21",
    "sg:city":"Inca",
    "sg:orig_category":"Agencias Y Agentes Comerciales, Representantes",
    "sg:phone":"+34 971 50 22 39",
    "sg:postcode":"07300",
    "sg:province":"Islas Baleares",
    "wof:name":"Amengual Ferragut Pablo",
    "wof:placetype":"venue"
},
  "geometry": {"coordinates":[2.9035377502,39.7221450806],"type":"Point"}
}