{
  "type": "Feature",
  "properties": {
    "addr:full":"Calle de Almendro, 10 Madrid Madrid 28005",
    "addr:housenumber":"10",
    "addr:postcode":"madrid;28005",
    "addr:street":"Calle De Almendro",
    "iso:country":"ES",
    "sg:address":"Calle de Almendro, 10",
    "sg:city":"Madrid",
    "sg:orig_category":"Bisuter\u00cda, Joyer\u00cda, Relojer\u00cda (al Por Menor)",
    "sg:phone":"+34 913 65 96 20",
    "sg:postcode":"28005",
    "sg:province":"Madrid",
    "wof:name":"Rujas Maroto Lucia",
    "wof:placetype":"venue"
},
  "geometry": {"coordinates":[-3.7096760273,40.4127540588],"type":"Point"}
}