{
  "type": "Feature",
  "properties": {
    "iso:country":"ES",
    "sg:address":"Calle de Alonso Cano, 46",
    "sg:city":"Madrid",
    "sg:orig_category":"M\u00c9dicos: Cardiolog\u00cda Y Afecciones Cardiovasculares",
    "sg:phone":"+34 915 54 46 65",
    "sg:postcode":"28003",
    "sg:province":"Madrid",
    "wof:name":"Hellin Zaragoza Juan Jose",
    "wof:placetype":"venue"
},
  "geometry": {"coordinates":[-3.6975293159,40.441368103],"type":"Point"}
}