{
  "type": "Feature",
  "properties": {
    "addr:full":"Carrer de Llu\u00c7a, 15 Barcelona Barcelona 08028",
    "addr:housenumber":"15",
    "addr:postcode":"08028",
    "addr:street":"Carrer De Lluc\u0327A",
    "iso:country":"ES",
    "sg:address":"Carrer de Llu\u00c7a, 15",
    "sg:city":"Barcelona",
    "sg:orig_category":"Maquinaria Para Industrias Diversas",
    "sg:phone":"+34 934 90 40 90",
    "sg:postcode":"08028",
    "sg:province":"Barcelona",
    "wof:name":"Italmaquinaria Del Curtido S.l.",
    "wof:placetype":"venue"
},
  "geometry": {"coordinates":[2.1305520535,41.3817176819],"type":"Point"}
}