{
  "type": "Feature",
  "properties": {
    "addr:full":"Via Laietana, 40 Barcelona Barcelona 08003",
    "addr:housenumber":"40",
    "addr:postcode":"08003",
    "addr:street":"Via Laietana",
    "iso:country":"ES",
    "sg:address":"Via Laietana, 40",
    "sg:city":"Barcelona",
    "sg:orig_category":"Agencias Y Asesores De Publicidad",
    "sg:phone":"+34 933 10 38 22",
    "sg:postcode":"08003",
    "sg:province":"Barcelona",
    "wof:name":"Pol & Partners S.l.",
    "wof:placetype":"venue"
},
  "geometry": {"coordinates":[2.1763710976,41.385925293],"type":"Point"}
}