{
  "type": "Feature",
  "properties": {
    "addr:full":"Calle de Fontanilla, 14 Zafra Badajoz 06300",
    "addr:housenumber":"14",
    "addr:postcode":"06300",
    "addr:street":"Calle De Fontanilla",
    "iso:country":"ES",
    "sg:address":"Calle de Fontanilla, 14",
    "sg:city":"Zafra",
    "sg:orig_category":"Inform\u00c1tica, Ofim\u00c1tica (estudios, Asesor\u00cda, Ingenier\u00cda, Formaci\u00d3n)",
    "sg:phone":"+34 924 55 41 21",
    "sg:postcode":"06300",
    "sg:province":"Badajoz",
    "sg:website":"www.cinex-informatica.com",
    "wof:name":"Jimenez Lopez Ezequiel",
    "wof:placetype":"venue"
},
  "geometry": {"coordinates":[-6.4178872108,38.4216423035],"type":"Point"}
}