{
  "type": "Feature",
  "properties": {
    "addr:full":"Carrer de Doctor Marti I Julia, 150 Hospitalet Llobregat Barcelona 08903",
    "addr:housenumber":"150",
    "addr:postcode":"08903",
    "addr:street":"Carrer De Doctor Marti I Julia",
    "iso:country":"ES",
    "sg:address":"Carrer de Doctor Marti I Julia, 150",
    "sg:city":"Hospitalet Llobregat",
    "sg:orig_category":"Peluquer\u00cdas, Peluquer\u00cda Mixta",
    "sg:phone":"+34 933 31 20 41",
    "sg:postcode":"08903",
    "sg:province":"Barcelona",
    "wof:name":"Medina Castro Fernando",
    "wof:placetype":"venue"
},
  "geometry": {"coordinates":[2.1254570484,41.370716095],"type":"Point"}
}