{
  "type": "Feature",
  "properties": {
    "iso:country":"ES",
    "sg:address":"Calle de Teruel, 66",
    "sg:city":"Tomelloso",
    "sg:orig_category":"Alcoholes Y Aguardientes (fabricaci\u00d3n, Al Por Mayor)",
    "sg:phone":"+34 926 51 35 62",
    "sg:postcode":"13700",
    "sg:province":"Ciudad Real",
    "wof:name":"Alcoholera De La Mancha S.a.",
    "wof:placetype":"venue"
},
  "geometry": {"coordinates":[-3.0315744877,39.1504821777],"type":"Point"}
}