{
  "type": "Feature",
  "properties": {
    "iso:country":"ES",
    "sg:address":"Calle de Antonio Royo Villanova, 2",
    "sg:city":"Valladolid",
    "sg:orig_category":"Contenedores (mercanc\u00cdas)",
    "sg:phone":"+34 983 33 25 92",
    "sg:postcode":"47014",
    "sg:province":"Valladolid",
    "wof:name":"Morro Mora Antonio",
    "wof:placetype":"venue"
},
  "geometry": {"coordinates":[-4.7348875999,41.6507911682],"type":"Point"}
}