{
  "type": "Feature",
  "properties": {
    "addr:full":"Calle de Galiana, 28 Madrid Madrid 28011",
    "addr:housenumber":"28",
    "addr:postcode":"madrid;28011",
    "addr:street":"Calle De Galiana",
    "iso:country":"ES",
    "sg:address":"Calle de Galiana, 28",
    "sg:city":"Madrid",
    "sg:orig_category":"Alimentaci\u00d3n General (al Por Menor)",
    "sg:phone":"+34 914 63 61 21",
    "sg:postcode":"28011",
    "sg:province":"Madrid",
    "wof:name":"Lopez Mendez Concepcion",
    "wof:placetype":"venue"
},
  "geometry": {"coordinates":[-3.7327170372,40.4090805054],"type":"Point"}
}