{
  "type": "Feature",
  "properties": {
    "addr:full":"Calle de Pico De Mulhacen, 5 San Sebastian De Los Reyes Madrid 28700",
    "addr:housenumber":"5",
    "addr:postcode":"28700",
    "addr:street":"Calle De Pico De Mulhacen",
    "iso:country":"ES",
    "sg:address":"Calle de Pico De Mulhacen, 5",
    "sg:city":"San Sebastian De Los Reyes",
    "sg:orig_category":"Asesor\u00cda Sobre Comunicaci\u00d3n De Empresas",
    "sg:phone":"+34 916 63 86 88",
    "sg:postcode":"28700",
    "sg:province":"Madrid",
    "wof:name":"Gesconlab S.l.",
    "wof:placetype":"venue"
},
  "geometry": {"coordinates":[-3.6364850998,40.5499458313],"type":"Point"}
}