{
  "type": "Feature",
  "properties": {
    "addr:full":"Plaz Espa\u00d1a, 23 Quintana Serena Badajoz 06450",
    "addr:housenumber":"23",
    "addr:postcode":"06450",
    "addr:street":"Plaz Espan\u0303A",
    "iso:country":"ES",
    "sg:address":"Plaz Espa\u00d1a, 23",
    "sg:city":"Quintana Serena",
    "sg:orig_category":"Relojer\u00cda (al Por Menor, Reparaci\u00d3n)",
    "sg:phone":"+34 924 78 60 84",
    "sg:postcode":"06450",
    "sg:province":"Badajoz",
    "wof:name":"Mariano Reinoso Jose",
    "wof:placetype":"venue"
},
  "geometry": {"coordinates":[-5.6712579727,38.743019104],"type":"Point"}
}