{
  "type": "Feature",
  "properties": {
    "iso:country":"ES",
    "sg:address":"Los Rufines, 2",
    "sg:city":"Pilar Horadada",
    "sg:orig_category":"Poli\u00c9ster",
    "sg:phone":"+34 966 76 60 46",
    "sg:postcode":"03190",
    "sg:province":"Alicante",
    "sg:website":"www.mundopol.com",
    "wof:name":"Mundo-pol S.l.",
    "wof:placetype":"venue"
},
  "geometry": {"coordinates":[-0.7898390293,37.8640213013],"type":"Point"}
}