{
  "type": "Feature",
  "properties": {
    "iso:country":"ES",
    "sg:address":"Pl Hospital, 3",
    "sg:city":"Sitges",
    "sg:orig_category":"Partidos Pol\u00cdticos",
    "sg:phone":"+34 938 94 36 58",
    "sg:postcode":"08870",
    "sg:province":"Barcelona",
    "wof:name":"Partit Dels Socialistas De Catalunya",
    "wof:placetype":"venue"
},
  "geometry": {"coordinates":[1.8117049932,41.2392539978],"type":"Point"}
}