{
  "type": "Feature",
  "properties": {
    "addr:full":"Avda Los Llanos, 5 Portugalete Vizcaya 48920",
    "addr:housenumber":"5",
    "addr:postcode":"48920",
    "addr:street":"Avda Los Llanos",
    "iso:country":"ES",
    "sg:address":"Avda Los Llanos, 5",
    "sg:city":"Portugalete",
    "sg:orig_category":"Electricidad: Instaladores",
    "sg:phone":"+34 944 62 97 37",
    "sg:postcode":"48920",
    "sg:province":"Vizcaya",
    "wof:name":"Electricidad Benaiz S.l.",
    "wof:placetype":"venue"
},
  "geometry": {"coordinates":[-3.0176839828,43.3219337463],"type":"Point"}
}