{
  "type": "Feature",
  "properties": {
    "iso:country":"ES",
    "sg:address":"Cmno Solana, S/n",
    "sg:city":"Villamediana Iregua",
    "sg:orig_category":"Cerrajer\u00cda, Ferrallista",
    "sg:phone":"+34 941 43 53 88",
    "sg:postcode":"26142",
    "sg:province":"La Rioja",
    "wof:name":"Martinez Soler Jose",
    "wof:placetype":"venue"
},
  "geometry": {"coordinates":[-2.417953968,42.4283485413],"type":"Point"}
}