{
  "type": "Feature",
  "properties": {
    "addr:full":"Calle de Santuario, 12 Montijo Badajoz 06480",
    "addr:housenumber":"12",
    "addr:postcode":"06480",
    "addr:street":"Calle De Santuario",
    "iso:country":"ES",
    "sg:address":"Calle de Santuario, 12",
    "sg:city":"Montijo",
    "sg:orig_category":"Chapister\u00cda",
    "sg:phone":"+34 924 45 33 27",
    "sg:postcode":"06480",
    "sg:province":"Badajoz",
    "wof:name":"Taller De Chapa Y Pintura Montero E Hijos S.l.",
    "wof:placetype":"venue"
},
  "geometry": {"coordinates":[-6.6065511703,38.9049034119],"type":"Point"}
}