{
  "type": "Feature",
  "properties": {
    "iso:country":"ES",
    "sg:address":"Carr Major, 22",
    "sg:city":"Benetusser",
    "sg:orig_category":"Asilos De Ancianos. Centros Privados",
    "sg:phone":"+34 963 76 15 31",
    "sg:postcode":"46910",
    "sg:province":"Valencia",
    "wof:name":"Asociacion Democratica Provincial De Jubilados Y Pensionistas De Valencia",
    "wof:placetype":"venue"
},
  "geometry": {"coordinates":[-0.3970994055,39.4227561951],"type":"Point"}
}