{
  "type": "Feature",
  "properties": {
    "addr:full":"Calle de Gonzalo De Cordoba (de), 18 San Fernando De Henares Madrid 28830",
    "addr:housenumber":"18",
    "addr:postcode":"28830",
    "addr:street":"Calle De Gonzalo De Cordoba De",
    "iso:country":"ES",
    "sg:address":"Calle de Gonzalo De Cordoba (de), 18",
    "sg:city":"San Fernando De Henares",
    "sg:orig_category":"Bares, Piano",
    "sg:phone":"+34 916 74 14 83",
    "sg:postcode":"28830",
    "sg:province":"Madrid",
    "wof:name":"Albarral S.a.",
    "wof:placetype":"venue"
},
  "geometry": {"coordinates":[-3.5343072414,40.4241676331],"type":"Point"}
}