{
  "type": "Feature",
  "properties": {
    "iso:country":"ES",
    "sg:address":"Rua Republica Arxentina (da), 23",
    "sg:city":"Santiago De Compostela",
    "sg:orig_category":"Iglesia Cat\u00d3lica",
    "sg:phone":"+34 981 59 11 72",
    "sg:postcode":"15701",
    "sg:province":"La Coru\u00f1a",
    "wof:name":"Parroquia De San Fernando",
    "wof:placetype":"venue"
},
  "geometry": {"coordinates":[-8.5487194061,42.8724861145],"type":"Point"}
}