{
  "type": "Feature",
  "properties": {
    "addr:full":"Calle de Miguel Servet, 37 Zaragoza Zaragoza 50013",
    "addr:housenumber":"37",
    "addr:postcode":"50013",
    "addr:street":"Calle De Miguel Servet",
    "iso:country":"ES",
    "sg:address":"Calle de Miguel Servet, 37",
    "sg:city":"Zaragoza",
    "sg:orig_category":"Escotaduras, Torneados",
    "sg:phone":"+34 976 42 55 27",
    "sg:postcode":"50013",
    "sg:province":"Zaragoza",
    "wof:name":"Lon Lon Valero",
    "wof:placetype":"venue"
},
  "geometry": {"coordinates":[-0.8719729781,41.6461410522],"type":"Point"}
}