{
  "type": "Feature",
  "properties": {
    "iso:country":"ES",
    "sg:address":"Carrer de Josep Pons, 5",
    "sg:city":"S. Adria Besos",
    "sg:orig_category":"Inform\u00c1tica, Ofim\u00c1tica (estudios, Asesor\u00cda, Ingenier\u00cda, Formaci\u00d3n)",
    "sg:phone":"+34 933 81 49 23",
    "sg:postcode":"08930",
    "sg:province":"Barcelona",
    "wof:name":"New Home Pc System S.l",
    "wof:placetype":"venue"
},
  "geometry": {"coordinates":[2.2153689861,41.4305000305],"type":"Point"}
}