{
  "type": "Feature",
  "properties": {
    "iso:country":"ES",
    "sg:address":"Avda Santa Marina, 13",
    "sg:city":"Badajoz",
    "sg:orig_category":"M\u00c9dicos: Estomatolog\u00cda",
    "sg:phone":"+34 924 20 73 24",
    "sg:postcode":"06005",
    "sg:province":"Badajoz",
    "wof:name":"Bernardo Muriel Francisco Javier",
    "wof:placetype":"venue"
},
  "geometry": {"coordinates":[-6.9770407677,38.8740005493],"type":"Point"}
}