{
  "type": "Feature",
  "properties": {
    "iso:country":"ES",
    "sg:address":"Calle de Carrilejos (de Los), 67",
    "sg:city":"Colmenar Viejo",
    "sg:orig_category":"Inmobiliaria (agencias)",
    "sg:phone":"+34 918 46 77 00",
    "sg:postcode":"28770",
    "sg:province":"Madrid",
    "wof:name":"Fincasa Real S.l",
    "wof:placetype":"venue"
},
  "geometry": {"coordinates":[-3.7716434002,40.6657600403],"type":"Point"}
}