{
  "type": "Feature",
  "properties": {
    "iso:country":"ES",
    "sg:address":"Calle de Virgen De Iciar, 12",
    "sg:city":"Alcorcon",
    "sg:orig_category":"Zapatos (al Por Menor)",
    "sg:phone":"+34 916 43 28 45",
    "sg:postcode":"28921",
    "sg:province":"Madrid",
    "wof:name":"Cambero Maillo Ismael",
    "wof:placetype":"venue"
},
  "geometry": {"coordinates":[-3.8281769753,40.3452415466],"type":"Point"}
}