{
  "type": "Feature",
  "properties": {
    "addr:full":"Calle de San Bartolome, 75 Torredelcampo Ja\u00e9n 23640",
    "addr:housenumber":"75",
    "addr:postcode":"23640",
    "addr:street":"Calle De San Bartolome;Jae\u0301N",
    "iso:country":"ES",
    "sg:address":"Calle de San Bartolome, 75",
    "sg:city":"Torredelcampo",
    "sg:orig_category":"Ense\u00d1anza Variada",
    "sg:phone":"+34 953 41 50 68",
    "sg:postcode":"23640",
    "sg:province":"Ja\u00e9n",
    "wof:name":"Rodriguez Rodriguez Ana",
    "wof:placetype":"venue"
},
  "geometry": {"coordinates":[-3.9016358852,37.7717285156],"type":"Point"}
}