{
  "type": "Feature",
  "properties": {
    "addr:full":"Pg Germanies (de Les), 3 Gandia Valencia 46700",
    "addr:postcode":"46700",
    "addr:street":"Pg Germanies De Les",
    "iso:country":"ES",
    "sg:address":"Pg Germanies (de Les), 3",
    "sg:city":"Gandia",
    "sg:orig_category":"Inform\u00c1tica (estudios, Servicios, Asesor\u00cda, Formaci\u00d3n)",
    "sg:phone":"+34 962 96 19 77",
    "sg:postcode":"46700",
    "sg:province":"Valencia",
    "wof:name":"I.g.b.informatica S.l.",
    "wof:placetype":"venue"
},
  "geometry": {"coordinates":[-0.1806840003,38.9649963379],"type":"Point"}
}