{
  "type": "Feature",
  "properties": {
    "addr:full":"Calle de Estepona, 1 Castillo Bajo-conejito M\u00e1laga 29793",
    "addr:housenumber":"1",
    "addr:postcode":"29793",
    "addr:street":"Calle De Estepona;Castillo Bajo-Conejito Ma\u0301Laga",
    "iso:country":"ES",
    "sg:address":"Calle de Estepona, 1",
    "sg:city":"Castillo Bajo-conejito",
    "sg:orig_category":"Inmobiliaria (agencias)",
    "sg:phone":"+34 952 53 14 86",
    "sg:postcode":"29793",
    "sg:province":"M\u00e1laga",
    "wof:name":"Torrox Costa Real Estate Congress Center S.l.",
    "wof:placetype":"venue"
},
  "geometry": {"coordinates":[-4.4201598167,36.7183189392],"type":"Point"}
}