{
  "type": "Feature",
  "properties": {
    "addr:full":"Serra Mariola, 7 Barrio Cristo Valencia 46960",
    "addr:housenumber":"7",
    "addr:postcode":"46960",
    "addr:street":"Barrio Cristo",
    "iso:country":"ES",
    "sg:address":"Serra Mariola, 7",
    "sg:city":"Barrio Cristo",
    "sg:orig_category":"Molduras, Junquillos, Listones Y Molduras Perforadas",
    "sg:phone":"+34 961 50 04 24",
    "sg:postcode":"46960",
    "sg:province":"Valencia",
    "wof:name":"Public Phone Vending S L",
    "wof:placetype":"venue"
},
  "geometry": {"coordinates":[-0.460878998,39.4649238586],"type":"Point"}
}