{
  "type": "Feature",
  "properties": {
    "iso:country":"ES",
    "sg:address":"Carrer de Pujades, 309",
    "sg:city":"Barcelona",
    "sg:orig_category":"Distribuci\u00d3n De Petr\u00d3leo Y Derivados",
    "sg:phone":"+34 933 07 33 11",
    "sg:postcode":"08019",
    "sg:province":"Barcelona",
    "wof:name":"Gescarburants 2m S.l.",
    "wof:placetype":"venue"
},
  "geometry": {"coordinates":[2.2070870399,41.4067192078],"type":"Point"}
}