{
  "type": "Feature",
  "properties": {
    "iso:country":"ES",
    "sg:address":"C/ Pi, 12",
    "sg:city":"Bayas",
    "sg:orig_category":"Electricidad Veh\u00cdculo",
    "sg:phone":"+34 966 63 74 50",
    "sg:postcode":"03292",
    "sg:province":"Alicante",
    "wof:name":"Lopez Huescar Domingo",
    "wof:placetype":"venue"
},
  "geometry": {"coordinates":[-0.6416826248,38.2199058533],"type":"Point"}
}