{
  "type": "Feature",
  "properties": {
    "iso:country":"ES",
    "sg:address":"Calle de Capitan Gomez Pinto (del), 11",
    "sg:city":"Colmenar Viejo",
    "sg:orig_category":"Papel Pintado (al Por Menor)",
    "sg:phone":"+34 918 45 11 06",
    "sg:postcode":"28770",
    "sg:province":"Madrid",
    "wof:name":"Barriales Martin Jose",
    "wof:placetype":"venue"
},
  "geometry": {"coordinates":[-3.7670650482,40.6586608887],"type":"Point"}
}