{
  "type": "Feature",
  "properties": {
    "iso:country":"ES",
    "sg:address":"Avda Pais Valencia, 104",
    "sg:city":"Torrent",
    "sg:orig_category":"Agencias Y Agentes Comerciales, Representantes",
    "sg:phone":"+34 961 57 06 79",
    "sg:postcode":"46900",
    "sg:province":"Valencia",
    "wof:name":"Representaciones Lopez & Haro S.l.",
    "wof:placetype":"venue"
},
  "geometry": {"coordinates":[-0.4741190076,39.4309883118],"type":"Point"}
}