{
  "type": "Feature",
  "properties": {
    "iso:country":"ES",
    "sg:address":"Calle de Primero De Mayo, 6",
    "sg:city":"Alhama Murcia",
    "sg:orig_category":"Carnicer\u00cdas, Carnicer\u00cdas",
    "sg:phone":"+34 968 63 95 55",
    "sg:postcode":"30840",
    "sg:province":"Murcia",
    "wof:name":"Gambin Vicente Jose Javier",
    "wof:placetype":"venue"
},
  "geometry": {"coordinates":[-1.4241490364,37.8507995605],"type":"Point"}
}