{
  "type": "Feature",
  "properties": {
    "iso:country":"ES",
    "sg:address":"Avda Condes De San Isidro, 36",
    "sg:city":"Fuengirola",
    "sg:orig_category":"Ense\u00d1anza: Peluquer\u00cda Est\u00c9tica",
    "sg:phone":"+34 952 46 12 19",
    "sg:postcode":"29640",
    "sg:province":"M\u00e1laga",
    "wof:name":"Can Ruiz Manuel Del",
    "wof:placetype":"venue"
},
  "geometry": {"coordinates":[-4.6263790131,36.5349006653],"type":"Point"}
}