{
  "type": "Feature",
  "properties": {
    "iso:country":"ES",
    "sg:address":"Calle de Baron De Patraix, 3",
    "sg:city":"Valencia",
    "sg:orig_category":"Peluquer\u00cdas, Peluquer\u00cda Mixta",
    "sg:phone":"+34 963 42 15 83",
    "sg:postcode":"46018",
    "sg:province":"Valencia",
    "wof:name":"Beas Moratalla Pilar",
    "wof:placetype":"venue"
},
  "geometry": {"coordinates":[-0.3904210031,39.4623985291],"type":"Point"}
}