{
  "type": "Feature",
  "properties": {
    "addr:full":"Carrer de Holanda, 44 P.o.pla Llerona Barcelona 08520",
    "addr:housenumber":"44",
    "addr:postcode":"08520",
    "addr:street":"Carrer De Holanda",
    "iso:country":"ES",
    "sg:address":"Carrer de Holanda, 44",
    "sg:city":"P.o.pla Llerona",
    "sg:orig_category":"Cables Y Hilos El\u00c9ctricos (fabricaci\u00d3n, Al Por Mayor)",
    "sg:phone":"+34 938 46 77 20",
    "sg:postcode":"08520",
    "sg:province":"Barcelona",
    "wof:name":"Cadillac Industria S.l.",
    "wof:placetype":"venue"
},
  "geometry": {"coordinates":[2.2953050137,41.6295814514],"type":"Point"}
}