{
  "type": "Feature",
  "properties": {
    "iso:country":"ES",
    "sg:address":"Calle de Sextante, 12",
    "sg:city":"Madrid",
    "sg:orig_category":"Arquitectos",
    "sg:phone":"+34 913 57 49 08",
    "sg:postcode":"28023",
    "sg:province":"Madrid",
    "wof:name":"Del Campo Arquitectos S.l.",
    "wof:placetype":"venue"
},
  "geometry": {"coordinates":[-3.7886610031,40.4574623108],"type":"Point"}
}