{
  "type": "Feature",
  "properties": {
    "addr:full":"Calle de San Delfin, 5 Madrid Madrid 28019",
    "addr:housenumber":"5",
    "addr:postcode":"28019",
    "addr:street":"Calle De San Delfin",
    "iso:country":"ES",
    "sg:address":"Calle de San Delfin, 5",
    "sg:city":"Madrid",
    "sg:orig_category":"Pod\u00d3logos: Pedicuros",
    "sg:phone":"+34 914 60 16 78",
    "sg:postcode":"28019",
    "sg:province":"Madrid",
    "wof:name":"Fuentes Alvarez Remedios",
    "wof:placetype":"venue"
},
  "geometry": {"coordinates":[-3.7079670429,40.3950195312],"type":"Point"}
}