{
  "type": "Feature",
  "properties": {
    "iso:country":"ES",
    "sg:address":"Rbla Egara, 213",
    "sg:city":"Terrassa",
    "sg:orig_category":"Zapatos (al Por Menor)",
    "sg:phone":"+34 937 88 04 98",
    "sg:postcode":"08224",
    "sg:province":"Barcelona",
    "wof:name":"Rodriguez Jornet David",
    "wof:placetype":"venue"
},
  "geometry": {"coordinates":[2.0076169968,41.5632286072],"type":"Point"}
}