{
  "type": "Feature",
  "properties": {
    "addr:full":"Calle de Emilio Serra Fernandez De Moratin, 10 Santa Cruz De Tenerife Santa Cruz De Tenerife 38006",
    "addr:housenumber":"10",
    "addr:postcode":"38006",
    "addr:street":"Calle De Emilio Serra Fernandez De Moratin",
    "iso:country":"ES",
    "sg:address":"Calle de Emilio Serra Fernandez De Moratin, 10",
    "sg:city":"Santa Cruz De Tenerife",
    "sg:orig_category":"Transporte En General",
    "sg:phone":"+34 922 15 12 18",
    "sg:postcode":"38006",
    "sg:province":"Santa Cruz De Tenerife",
    "sg:website":"www.riromel.com",
    "wof:name":"Riromel S.l.",
    "wof:placetype":"venue"
},
  "geometry": {"coordinates":[-16.2595691681,28.4719696045],"type":"Point"}
}