{
  "type": "Feature",
  "properties": {
    "iso:country":"ES",
    "sg:address":"Calle de Canalejas, 5",
    "sg:city":"Tarazona Mancha",
    "sg:orig_category":"Molduras, Junquillos, Listones Y Molduras Perforadas",
    "sg:phone":"+34 967 48 06 07",
    "sg:postcode":"02100",
    "sg:province":"Albacete",
    "wof:name":"Simarro Lopez Pedro",
    "wof:placetype":"venue"
},
  "geometry": {"coordinates":[-1.9131280184,39.2648391724],"type":"Point"}
}