{
  "type": "Feature",
  "properties": {
    "iso:country":"ES",
    "sg:address":"Avda Ral (el), 56",
    "sg:city":"Castejon Sos",
    "sg:orig_category":"Peluquer\u00cdas, Peluquer\u00cda Mixta",
    "sg:phone":"+34 974 55 30 10",
    "sg:postcode":"22466",
    "sg:province":"Huesca",
    "wof:name":"Ortega Gracia Anastasia",
    "wof:placetype":"venue"
},
  "geometry": {"coordinates":[0.4904699922,42.512336731],"type":"Point"}
}