{
  "type": "Feature",
  "properties": {
    "addr:full":"Calle de Actriz Encarna Ma\u00d1ez, 3 Valencia Valencia 46022",
    "addr:housenumber":"3",
    "addr:postcode":"46022",
    "addr:street":"Calle De Actriz;Man\u0303Ez",
    "iso:country":"ES",
    "sg:address":"Calle de Actriz Encarna Ma\u00d1ez, 3",
    "sg:city":"Valencia",
    "sg:orig_category":"Psic\u00d3logos",
    "sg:phone":"+34 963 55 34 23",
    "sg:postcode":"46022",
    "sg:province":"Valencia",
    "wof:name":"Catalan Borja Amelia",
    "wof:placetype":"venue"
},
  "geometry": {"coordinates":[-0.3462322056,39.472454071],"type":"Point"}
}