{
  "type": "Feature",
  "properties": {
    "iso:country":"ES",
    "sg:address":"Avda Aviacion, 83",
    "sg:city":"Madrid",
    "sg:orig_category":"Farmacias",
    "sg:phone":"+34 917 05 03 91",
    "sg:postcode":"28044",
    "sg:province":"Madrid",
    "wof:name":"Marivela Rivas Fernando",
    "wof:placetype":"venue"
},
  "geometry": {"coordinates":[-3.781388998,40.3756484985],"type":"Point"}
}