{
  "type": "Feature",
  "properties": {
    "addr:full":"Calle de Flores, 4 Rozas De Madrid Madrid 28230",
    "addr:housenumber":"4",
    "addr:postcode":"28230",
    "addr:street":"Calle De Flores",
    "iso:country":"ES",
    "sg:address":"Calle de Flores, 4",
    "sg:city":"Rozas De Madrid",
    "sg:orig_category":"Ropa Para Se\u00d1oras (al Por Menor)",
    "sg:phone":"+34 916 37 19 41",
    "sg:postcode":"28230",
    "sg:province":"Madrid",
    "wof:name":"Blasco Cordero Jose Javier",
    "wof:placetype":"venue"
},
  "geometry": {"coordinates":[-3.8723320961,40.4913215637],"type":"Point"}
}