{
  "type": "Feature",
  "properties": {
    "iso:country":"ES",
    "sg:address":"Carrer de Miquel Moragas, 1",
    "sg:city":"Premia Mar",
    "sg:orig_category":"Carnicer\u00cdas, Carnicer\u00cdas",
    "sg:phone":"+34 937 51 66 63",
    "sg:postcode":"08330",
    "sg:province":"Barcelona",
    "wof:name":"Izquierdo Mendoza Jose Manuel",
    "wof:placetype":"venue"
},
  "geometry": {"coordinates":[2.3569691181,41.4901161194],"type":"Point"}
}