{
  "type": "Feature",
  "properties": {
    "addr:full":"Cami Ral, 387 Mataro Barcelona 08301",
    "addr:housenumber":"387",
    "addr:postcode":"08301",
    "addr:street":"Ral",
    "iso:country":"ES",
    "sg:address":"Cami Ral, 387",
    "sg:city":"Mataro",
    "sg:classifiers":[
        {
            "category":"Personal",
            "subcategory":"Barber",
            "type":"Services"
        }
    ],
    "sg:phone":"+34 937 90 20 96",
    "sg:postcode":"08301",
    "sg:province":"Barcelona",
    "sg:tags":[
        "caballeros",
        "de",
        "peluqueros"
    ],
    "wof:name":"Claramunt Trivo Manuel",
    "wof:placetype":"venue"
},
  "geometry": {"coordinates":[2.4443280697,41.53698349],"type":"Point"}
}