{
  "type": "Feature",
  "properties": {
    "addr:full":"Avda Li\u00d1os (los), 8 Jerez De La Frontera C\u00e1diz 11404",
    "addr:postcode":"11404",
    "addr:street":"Avda Lin\u0303Os Los",
    "iso:country":"ES",
    "sg:address":"Avda Li\u00d1os (los), 8",
    "sg:city":"Jerez De La Frontera",
    "sg:orig_category":"Inmobiliaria (agencias)",
    "sg:phone":"+34 956 31 07 38",
    "sg:postcode":"11404",
    "sg:province":"C\u00e1diz",
    "wof:name":"Almcreditfinanzas2006 Sl",
    "wof:placetype":"venue"
},
  "geometry": {"coordinates":[-6.1553497314,36.7065124512],"type":"Point"}
}