{
  "type": "Feature",
  "properties": {
    "addr:full":"Avda Principe De Asturias, 24 Zamora Zamora 49012",
    "addr:housenumber":"24",
    "addr:postcode":"49012",
    "addr:street":"Avda Principe De Asturias",
    "iso:country":"ES",
    "sg:address":"Avda Principe De Asturias, 24",
    "sg:city":"Zamora",
    "sg:orig_category":"Electrodom\u00c9sticos (al Por Menor)",
    "sg:phone":"+34 980 51 71 76",
    "sg:postcode":"49012",
    "sg:province":"Zamora",
    "wof:name":"Calvo Calvo Florentino",
    "wof:placetype":"venue"
},
  "geometry": {"coordinates":[-5.7370271683,41.5110778809],"type":"Point"}
}