{
  "type": "Feature",
  "properties": {
    "addr:full":"Calle de Salamanca, 21 Valencia Valencia 46005",
    "addr:housenumber":"21",
    "addr:postcode":"46005",
    "addr:street":"Calle De Salamanca",
    "iso:country":"ES",
    "sg:address":"Calle de Salamanca, 21",
    "sg:city":"Valencia",
    "sg:orig_category":"Abogados",
    "sg:phone":"+34 963 34 64 27",
    "sg:postcode":"46005",
    "sg:province":"Valencia",
    "wof:name":"David Castillo Y Asociados S.l.abogados Economistas",
    "wof:placetype":"venue"
},
  "geometry": {"coordinates":[-0.3643729985,39.4666633606],"type":"Point"}
}