{
  "type": "Feature",
  "properties": {
    "addr:full":"Ctra San Javier, Km. 0004,8 Secano Murcia 30579",
    "addr:postcode":"30579",
    "addr:street":"Ctra San Javier Km. 0004,8",
    "iso:country":"ES",
    "sg:address":"Ctra San Javier, Km. 0004,8",
    "sg:city":"Secano",
    "sg:orig_category":"Inmobiliaria (agencias)",
    "sg:phone":"+34 968 82 42 09",
    "sg:postcode":"30579",
    "sg:province":"Murcia",
    "wof:name":"Gestibensa S.l.",
    "wof:placetype":"venue"
},
  "geometry": {"coordinates":[-1.0529290438,37.9830245972],"type":"Point"}
}