{
  "type": "Feature",
  "properties": {
    "iso:country":"ES",
    "sg:address":"Pg Maritim, 90",
    "sg:city":"Sitges",
    "sg:orig_category":"Inversiones",
    "sg:phone":"+34 938 11 20 57",
    "sg:postcode":"08870",
    "sg:province":"Barcelona",
    "wof:name":"Inversiones Caribe\u00f1as Saturno S.a.",
    "wof:placetype":"venue"
},
  "geometry": {"coordinates":[1.7934972048,41.2293434143],"type":"Point"}
}