{
  "type": "Feature",
  "properties": {
    "iso:country":"ES",
    "sg:address":"Avda Fuenlabrada, 37",
    "sg:city":"Leganes",
    "sg:orig_category":"Poller\u00cda Y Caza (al Por Menor)",
    "sg:phone":"+34 916 86 77 31",
    "sg:postcode":"28911",
    "sg:province":"Madrid",
    "wof:name":"Fernandez Madrigal Alfredo",
    "wof:placetype":"venue"
},
  "geometry": {"coordinates":[-3.7626340389,40.3296813965],"type":"Point"}
}