{
  "type": "Feature",
  "properties": {
    "addr:full":"Carrer de Freser, 16 Vic Barcelona 08500",
    "addr:housenumber":"16",
    "addr:postcode":"08500",
    "addr:street":"Carrer De Freser",
    "iso:country":"ES",
    "sg:address":"Carrer de Freser, 16",
    "sg:city":"Vic",
    "sg:orig_category":"Piscinas, Accesorios, Suministros (fabricaci\u00d3n, Al Por Mayor)",
    "sg:phone":"+34 938 85 12 98",
    "sg:postcode":"08500",
    "sg:province":"Barcelona",
    "wof:name":"Aqubiologic S.l.",
    "wof:placetype":"venue"
},
  "geometry": {"coordinates":[2.2573196888,41.9131011963],"type":"Point"}
}