{
  "type": "Feature",
  "properties": {
    "addr:full":"Calle de Jardin De Medina, 5 Almeria Almer\u00eda 04006",
    "addr:housenumber":"5",
    "addr:postcode":"04006",
    "addr:street":"Calle De Jardin De Medina",
    "iso:country":"ES",
    "sg:address":"Calle de Jardin De Medina, 5",
    "sg:city":"Almeria",
    "sg:orig_category":"Servicios Gsm",
    "sg:phone":"+34 950 24 50 68",
    "sg:postcode":"04006",
    "sg:province":"Almer\u00eda",
    "wof:name":"Vodafone Espa\u00d1a S.a.",
    "wof:placetype":"venue"
},
  "geometry": {"coordinates":[-2.4551980495,36.8364601135],"type":"Point"}
}