{
  "type": "Feature",
  "properties": {
    "addr:full":"Avda Pio Xii, 2 Valencia Valencia 46009",
    "addr:housenumber":"2",
    "addr:postcode":"46009",
    "addr:street":"Avda Pio Xii",
    "iso:country":"ES",
    "sg:address":"Avda Pio Xii, 2",
    "sg:city":"Valencia",
    "sg:orig_category":"Servicios Gsm",
    "sg:phone":"+34 963 45 90 74",
    "sg:postcode":"46009",
    "sg:province":"Valencia",
    "wof:name":"Phone Warehouse S.l.",
    "wof:placetype":"venue"
},
  "geometry": {"coordinates":[-0.3910419941,39.4790344238],"type":"Point"}
}