{
  "type": "Feature",
  "properties": {
    "addr:full":"Calle de Siena, 8 Santa Marta De Tormes Salamanca 37900",
    "addr:housenumber":"8",
    "addr:postcode":"37900",
    "addr:street":"Calle De Siena",
    "iso:country":"ES",
    "sg:address":"Calle de Siena, 8",
    "sg:city":"Santa Marta De Tormes",
    "sg:orig_category":"Promotores Constructores",
    "sg:phone":"+34 923 20 10 14",
    "sg:postcode":"37900",
    "sg:province":"Salamanca",
    "wof:name":"Puente De La Serna Ute",
    "wof:placetype":"venue"
},
  "geometry": {"coordinates":[-5.644384861,40.9557228088],"type":"Point"}
}