{
  "type": "Feature",
  "properties": {
    "iso:country":"ES",
    "sg:address":"Calle de San Vicente De Paul, 20",
    "sg:city":"Sevilla",
    "sg:orig_category":"Panader\u00cdas, Panader\u00cdas",
    "sg:phone":"+34 954 34 06 85",
    "sg:postcode":"41010",
    "sg:province":"Sevilla",
    "wof:name":"Confiteria Heladeria De Moguer S.l.",
    "wof:placetype":"venue"
},
  "geometry": {"coordinates":[-6.0100898743,37.3838500977],"type":"Point"}
}