{
  "type": "Feature",
  "properties": {
    "addr:full":"Avda Gabriel Y Galan, 32 Brozas C\u00e1ceres 10950",
    "addr:housenumber":"32",
    "addr:postcode":"10950",
    "addr:street":"Avda Gabriel Y Galan;Ca\u0301Ceres",
    "iso:country":"ES",
    "sg:address":"Avda Gabriel Y Galan, 32",
    "sg:city":"Brozas",
    "sg:orig_category":"Doctores En Medicina",
    "sg:phone":"+34 927 39 51 66",
    "sg:postcode":"10950",
    "sg:province":"C\u00e1ceres",
    "wof:name":"Marcos Fernandez Ramon",
    "wof:placetype":"venue"
},
  "geometry": {"coordinates":[-6.776031971,39.6152648926],"type":"Point"}
}