{
  "type": "Feature",
  "properties": {
    "iso:country":"ES",
    "sg:address":"Calle de Medellin, 3",
    "sg:city":"Talavera Reina",
    "sg:orig_category":"Inmobiliaria (agencias)",
    "sg:phone":"+34 925 81 52 38",
    "sg:postcode":"45600",
    "sg:province":"Toledo",
    "wof:name":"Promocion Y Venta De Solares De Edificios",
    "wof:placetype":"venue"
},
  "geometry": {"coordinates":[-4.8351521492,39.9649505615],"type":"Point"}
}