{
  "type": "Feature",
  "properties": {
    "addr:full":"Carrer de Almeria, 31 Barcelona Barcelona 08014",
    "addr:housenumber":"31",
    "addr:postcode":"08014",
    "addr:street":"Carrer De Almeria",
    "iso:country":"ES",
    "sg:address":"Carrer de Almeria, 31",
    "sg:city":"Barcelona",
    "sg:orig_category":"Molduras, Junquillos, Listones Y Molduras Perforadas",
    "sg:phone":"+34 933 32 62 84",
    "sg:postcode":"08014",
    "sg:province":"Barcelona",
    "wof:name":"Lacalle Trujillo Francisco",
    "wof:placetype":"venue"
},
  "geometry": {"coordinates":[2.138753891,41.3728408813],"type":"Point"}
}