{
  "type": "Feature",
  "properties": {
    "iso:country":"ES",
    "sg:address":"Avda Orovilla, 42",
    "sg:city":"Madrid",
    "sg:orig_category":"Molduras, Junquillos, Listones Y Molduras Perforadas",
    "sg:phone":"+34 913 69 92 48",
    "sg:postcode":"28041",
    "sg:province":"Madrid",
    "wof:name":"Leon Hernandez Maria Belen",
    "wof:placetype":"venue"
},
  "geometry": {"coordinates":[-3.6899631023,40.3607635498],"type":"Point"}
}