{
  "type": "Feature",
  "properties": {
    "iso:country":"ES",
    "sg:address":"Plaz Aragon, 13",
    "sg:city":"Albalate Arzobispo",
    "sg:orig_category":"Florister\u00cdas",
    "sg:phone":"+34 978 81 30 58",
    "sg:postcode":"44540",
    "sg:province":"Teruel",
    "wof:name":"Gasco Paris Isabel",
    "wof:placetype":"venue"
},
  "geometry": {"coordinates":[-0.5113179088,41.1221733093],"type":"Point"}
}