{
  "type": "Feature",
  "properties": {
    "addr:full":"Calle de Juan Ramon Jimenez, 9 Carlota C\u00f3rdoba 14100",
    "addr:housenumber":"9",
    "addr:postcode":"14100",
    "addr:street":"Calle De Juan Ramon Jimenez;Co\u0301Rdoba",
    "iso:country":"ES",
    "sg:address":"Calle de Juan Ramon Jimenez, 9",
    "sg:city":"Carlota",
    "sg:orig_category":"Empresas De Desmonte",
    "sg:phone":"+34 957 30 01 56",
    "sg:postcode":"14100",
    "sg:province":"C\u00f3rdoba",
    "wof:name":"Vasco Sayago Jose",
    "wof:placetype":"venue"
},
  "geometry": {"coordinates":[-4.9374890327,37.6685142517],"type":"Point"}
}