{
  "type": "Feature",
  "properties": {
    "iso:country":"ES",
    "sg:address":"Calle de Ramiro De Maeztu, 42",
    "sg:city":"Valencia",
    "sg:orig_category":"Abogados",
    "sg:phone":"+34 963 30 15 54",
    "sg:postcode":"46022",
    "sg:province":"Valencia",
    "wof:name":"Valero Melero Francisco Adrian",
    "wof:placetype":"venue"
},
  "geometry": {"coordinates":[-0.3459782004,39.4667472839],"type":"Point"}
}