{
  "type": "Feature",
  "properties": {
    "iso:country":"ES",
    "sg:address":"Calle de Tajamar, 11",
    "sg:city":"Malaga",
    "sg:orig_category":"Alimentaci\u00d3n General (al Por Menor)",
    "sg:phone":"+34 952 34 48 30",
    "sg:postcode":"29006",
    "sg:province":"M\u00e1laga",
    "wof:name":"Alimentacion Pema S.l.",
    "wof:placetype":"venue"
},
  "geometry": {"coordinates":[-4.4800834656,36.712978363],"type":"Point"}
}