{
  "type": "Feature",
  "properties": {
    "addr:full":"Avda Cristo De Confalon, 29 Ecija Sevilla 41400",
    "addr:housenumber":"29",
    "addr:postcode":"41400",
    "addr:street":"Avda Cristo De Confalon",
    "iso:country":"ES",
    "sg:address":"Avda Cristo De Confalon, 29",
    "sg:city":"Ecija",
    "sg:orig_category":"Sociedades, Compa\u00d1\u00cdas Aseguradoras",
    "sg:phone":"+34 954 83 44 44",
    "sg:postcode":"41400",
    "sg:province":"Sevilla",
    "wof:name":"Seguros Catalana Occidente S.a. De Seguros Y Reaseguros",
    "wof:placetype":"venue"
},
  "geometry": {"coordinates":[-5.0806398392,37.5351104736],"type":"Point"}
}