{
  "type": "Feature",
  "properties": {
    "addr:full":"Avda Nazaret (de), S/n Jerez De La Frontera C\u00e1diz 11406",
    "addr:postcode":"11406",
    "addr:street":"Avda Nazaret De S / N",
    "iso:country":"ES",
    "sg:address":"Avda Nazaret (de), S/n",
    "sg:city":"Jerez De La Frontera",
    "sg:orig_category":"Ense\u00d1anza Secundaria: Colegios Y Escuelas Privadas",
    "sg:phone":"+34 956 33 02 01",
    "sg:postcode":"11406",
    "sg:province":"C\u00e1diz",
    "wof:name":"Junta De Andalucia",
    "wof:placetype":"venue"
},
  "geometry": {"coordinates":[-6.1135911942,36.6772918701],"type":"Point"}
}