{
  "type": "Feature",
  "properties": {
    "addr:full":"Pg Maritim, 1 Estartit Girona 17258",
    "addr:housenumber":"1",
    "addr:postcode":"17258",
    "addr:street":"Pg Maritim",
    "iso:country":"ES",
    "sg:address":"Pg Maritim, 1",
    "sg:city":"Estartit",
    "sg:orig_category":"Deportes N\u00c1uticos, Acu\u00c1ticos Y Subacu\u00c1ticos: Art\u00cdculos Y Equipo (al Por Menor)",
    "sg:phone":"+34 972 75 07 92",
    "sg:postcode":"17258",
    "sg:province":"Girona",
    "wof:name":"Nautica Borrat S.l.",
    "wof:placetype":"venue"
},
  "geometry": {"coordinates":[3.2068030834,42.0542106628],"type":"Point"}
}