{
  "type": "Feature",
  "properties": {
    "addr:full":"Avda Moratalaz, 189 Madrid Madrid 28030",
    "addr:housenumber":"189",
    "addr:postcode":"28030",
    "addr:street":"Avda Moratalaz",
    "iso:country":"ES",
    "sg:address":"Avda Moratalaz, 189",
    "sg:city":"Madrid",
    "sg:orig_category":"Molduras, Junquillos, Listones Y Molduras Perforadas",
    "sg:phone":"+34 914 39 80 57",
    "sg:postcode":"28030",
    "sg:province":"Madrid",
    "wof:name":"Del Valle Fernandez Carolina Olga",
    "wof:placetype":"venue"
},
  "geometry": {"coordinates":[-3.6432170868,40.408996582],"type":"Point"}
}