{
  "type": "Feature",
  "properties": {
    "addr:full":"Calle de Magallanes, 9 Merida Badajoz 06800",
    "addr:housenumber":"9",
    "addr:postcode":"06800",
    "addr:street":"Calle De Magallanes",
    "iso:country":"ES",
    "sg:address":"Calle de Magallanes, 9",
    "sg:city":"Merida",
    "sg:orig_category":"Centros Empresariales",
    "sg:phone":"+34 924 37 03 26",
    "sg:postcode":"06800",
    "sg:province":"Badajoz",
    "wof:name":"Garcia Gama Jose Antonio",
    "wof:placetype":"venue"
},
  "geometry": {"coordinates":[-6.3626928329,38.9071617126],"type":"Point"}
}