{
  "type": "Feature",
  "properties": {
    "iso:country":"ES",
    "sg:address":"Calle de San Pedro De Alcantara, 10",
    "sg:city":"Valverde Fresno",
    "sg:orig_category":"Quincaller\u00cda (al Por Menor)",
    "sg:phone":"+34 927 51 04 56",
    "sg:postcode":"10890",
    "sg:province":"C\u00e1ceres",
    "wof:name":"Manuel Fernandez Y Santiago Pereira C.b.",
    "wof:placetype":"venue"
},
  "geometry": {"coordinates":[-6.8782739639,40.2250328064],"type":"Point"}
}