{
  "type": "Feature",
  "properties": {
    "addr:full":"Carrer de Arago, 616 Barcelona Barcelona 08018",
    "addr:housenumber":"616",
    "addr:postcode":"08018",
    "addr:street":"Carrer De Arago",
    "iso:country":"ES",
    "sg:address":"Carrer de Arago, 616",
    "sg:city":"Barcelona",
    "sg:orig_category":"Centros De Educaci\u00d3n Especial",
    "sg:phone":"+34 932 45 42 43",
    "sg:postcode":"08018",
    "sg:province":"Barcelona",
    "wof:name":"Ajuntament De Barcelona",
    "wof:placetype":"venue"
},
  "geometry": {"coordinates":[2.189237833,41.4102554321],"type":"Point"}
}