{
  "type": "Feature",
  "properties": {
    "iso:country":"ES",
    "sg:address":"C/ Picassent, 36",
    "sg:city":"Elche",
    "sg:orig_category":"Centros M\u00c9dicos Y Sociales, Dispensarios",
    "sg:phone":"+34 966 67 46 67",
    "sg:postcode":"03203",
    "sg:province":"Alicante",
    "wof:name":"Servicios De Medicina Preventiva S.a.",
    "wof:placetype":"venue"
},
  "geometry": {"coordinates":[-0.6717889905,38.2676811218],"type":"Point"}
}