{
  "type": "Feature",
  "properties": {
    "addr:full":"Pase Fabrica (la), 22 Brihuega Guadalajara 19400",
    "addr:postcode":"19400",
    "addr:street":"Brihuega",
    "iso:country":"ES",
    "sg:address":"Pase Fabrica (la), 22",
    "sg:city":"Brihuega",
    "sg:orig_category":"Promotores Constructores",
    "sg:phone":"+34 949 28 10 32",
    "sg:postcode":"19400",
    "sg:province":"Guadalajara",
    "wof:name":"Cepu S.a.",
    "wof:placetype":"venue"
},
  "geometry": {"coordinates":[-2.8703289032,40.7592315674],"type":"Point"}
}