{
  "type": "Feature",
  "properties": {
    "addr:full":"Avda Andalucia, 67 Santisteban Puerto Ja\u00e9n 23250",
    "addr:housenumber":"67",
    "addr:postcode":"23250",
    "addr:street":"Avda Andalucia;Jae\u0301N",
    "iso:country":"ES",
    "sg:address":"Avda Andalucia, 67",
    "sg:city":"Santisteban Puerto",
    "sg:orig_category":"Arquitectos",
    "sg:phone":"+34 953 40 16 91",
    "sg:postcode":"23250",
    "sg:province":"Ja\u00e9n",
    "wof:name":"Arquishem S.l.",
    "wof:placetype":"venue"
},
  "geometry": {"coordinates":[-3.2050631046,38.250541687],"type":"Point"}
}