{
  "type": "Feature",
  "properties": {
    "iso:country":"ES",
    "sg:address":"Calle de Fruta De La, 4",
    "sg:city":"Aviles",
    "sg:orig_category":"Asesor\u00cda Fiscal Y Jur\u00cddica",
    "sg:phone":"+34 985 51 04 55",
    "sg:postcode":"33402",
    "sg:province":"Asturias",
    "wof:name":"Asesoria Gonzalez Valdes S.l.",
    "wof:placetype":"venue"
},
  "geometry": {"coordinates":[-5.9223189354,43.5558357239],"type":"Point"}
}