{
  "type": "Feature",
  "properties": {
    "iso:country":"ES",
    "sg:address":"Calle de Saturno, 16",
    "sg:city":"Valladolid",
    "sg:orig_category":"Asociaciones Y Clubs Deportivos",
    "sg:phone":"+34 983 13 19 98",
    "sg:postcode":"47009",
    "sg:province":"Valladolid",
    "wof:name":"Planet Gym S.l.",
    "wof:placetype":"venue"
},
  "geometry": {"coordinates":[-4.7366499901,41.6649742126],"type":"Point"}
}