{
  "type": "Feature",
  "properties": {
    "iso:country":"ES",
    "sg:address":"Calle de Blas De Lezo, 13",
    "sg:city":"Malaga",
    "sg:orig_category":"Reposter\u00cdas",
    "sg:phone":"+34 952 61 18 81",
    "sg:postcode":"29011",
    "sg:province":"M\u00e1laga",
    "wof:name":"Fabrica Y Distribucion De Pan Malaga S.l.",
    "wof:placetype":"venue"
},
  "geometry": {"coordinates":[-4.4346342087,36.7283172607],"type":"Point"}
}