{
  "type": "Feature",
  "properties": {
    "iso:country":"ES",
    "sg:address":"Calle de Martires, 14",
    "sg:city":"Almendralejo",
    "sg:orig_category":"Librer\u00cdas",
    "sg:phone":"+34 924 66 55 78",
    "sg:postcode":"06200",
    "sg:province":"Badajoz",
    "wof:name":"Garcia-moreno Villar Maria Dolores",
    "wof:placetype":"venue"
},
  "geometry": {"coordinates":[-6.4088959694,38.6810951233],"type":"Point"}
}