{
  "type": "Feature",
  "properties": {
    "addr:full":"Carrer de Jaume Balmes, 36 Vilafranca Penedes Barcelona 08720",
    "addr:housenumber":"36",
    "addr:postcode":"08720",
    "addr:street":"Carrer De Jaume Balmes",
    "iso:country":"ES",
    "sg:address":"Carrer de Jaume Balmes, 36",
    "sg:city":"Vilafranca Penedes",
    "sg:orig_category":"Empresas De Carpinter\u00cda",
    "sg:phone":"+34 938 17 11 70",
    "sg:postcode":"08720",
    "sg:province":"Barcelona",
    "wof:name":"Reformas-2000 S.l.",
    "wof:placetype":"venue"
},
  "geometry": {"coordinates":[1.6992199421,41.3447799683],"type":"Point"}
}