{
  "type": "Feature",
  "properties": {
    "addr:full":"Calle de Sant Jaume, S/n Santa Eulalia Islas Baleares 07840",
    "addr:housenumber":"s / n",
    "addr:postcode":"07840",
    "addr:street":"Calle De Sant Jaume",
    "iso:country":"ES",
    "sg:address":"Calle de Sant Jaume, S/n",
    "sg:city":"Santa Eulalia",
    "sg:orig_category":"Farmacias",
    "sg:phone":"+34 971 33 27 21",
    "sg:postcode":"07840",
    "sg:province":"Islas Baleares",
    "wof:name":"Noguera Vera Maria Luisa",
    "wof:placetype":"venue"
},
  "geometry": {"coordinates":[2.9117100239,39.6136398315],"type":"Point"}
}