{
  "type": "Feature",
  "properties": {
    "iso:country":"ES",
    "sg:address":"Calle de Melchor Fernandez Almagro, 17",
    "sg:city":"Madrid",
    "sg:orig_category":"Centros Empresariales",
    "sg:phone":"+34 913 14 43 97",
    "sg:postcode":"28029",
    "sg:province":"Madrid",
    "wof:name":"Fernandez Leblic Beatriz",
    "wof:placetype":"venue"
},
  "geometry": {"coordinates":[-3.6964631081,40.4775733948],"type":"Point"}
}