{
  "type": "Feature",
  "properties": {
    "addr:full":"Marie Curie, 2 Mi\u00f1ano Menor \u00c1lava 01510",
    "addr:housenumber":"2",
    "addr:postcode":"01510",
    "addr:street":"Marie Curie",
    "iso:country":"ES",
    "sg:address":"Marie Curie, 2",
    "sg:city":"Mi\u00f1ano Menor",
    "sg:orig_category":"Construcciones Navales Y Fluviales",
    "sg:phone":"+34 945 29 72 20",
    "sg:postcode":"01510",
    "sg:province":"\u00c1lava",
    "wof:name":"Sk 2024 S.l.",
    "wof:placetype":"venue"
},
  "geometry": {"coordinates":[-2.6422491074,42.9813613892],"type":"Point"}
}