{
  "type": "Feature",
  "properties": {
    "addr:full":"Calle de Ramon Gorge, 11 Elda Alicante 03600",
    "addr:housenumber":"11",
    "addr:postcode":"03600",
    "addr:street":"Calle De Ramon Gorge",
    "iso:country":"ES",
    "sg:address":"Calle de Ramon Gorge, 11",
    "sg:city":"Elda",
    "sg:orig_category":"Electricidad: Instaladores",
    "sg:phone":"+34 965 39 44 41",
    "sg:postcode":"03600",
    "sg:province":"Alicante",
    "wof:name":"Ricardo Rico S.l.",
    "wof:placetype":"venue"
},
  "geometry": {"coordinates":[-0.7925940156,38.4768676758],"type":"Point"}
}