{
  "type": "Feature",
  "properties": {
    "addr:full":"Carrer de Ali Bei, 11 Barcelona Barcelona 08010",
    "addr:housenumber":"11",
    "addr:postcode":"08010",
    "addr:street":"Carrer De Ali Bei",
    "iso:country":"ES",
    "sg:address":"Carrer de Ali Bei, 11",
    "sg:city":"Barcelona",
    "sg:orig_category":"Centros Empresariales",
    "sg:phone":"+34 932 45 04 48",
    "sg:postcode":"08010",
    "sg:province":"Barcelona",
    "wof:name":"Meredith Romero, S.l.",
    "wof:placetype":"venue"
},
  "geometry": {"coordinates":[2.1774110794,41.3911857605],"type":"Point"}
}