{
  "type": "Feature",
  "properties": {
    "addr:full":"Avda Ramon Nieto, 65 Penis Pontevedra 36205",
    "addr:housenumber":"65",
    "addr:postcode":"36205",
    "addr:street":"Avda Ramon Nieto",
    "iso:country":"ES",
    "sg:address":"Avda Ramon Nieto, 65",
    "sg:city":"Penis",
    "sg:orig_category":"Farmacias",
    "sg:phone":"+34 986 27 14 94",
    "sg:postcode":"36205",
    "sg:province":"Pontevedra",
    "wof:name":"De Prado Orban Maria Del Carmen",
    "wof:placetype":"venue"
},
  "geometry": {"coordinates":[-8.70246315,42.2290763855],"type":"Point"}
}