{
  "type": "Feature",
  "properties": {
    "iso:country":"ES",
    "sg:address":"Calle de Albino Perez Ayestarain (de), 52",
    "sg:city":"San Fernando De Henares",
    "sg:orig_category":"Molduras, Junquillos, Listones Y Molduras Perforadas",
    "sg:phone":"+34 916 69 22 67",
    "sg:postcode":"28830",
    "sg:province":"Madrid",
    "wof:name":"Mota Urbanos Domingo",
    "wof:placetype":"venue"
},
  "geometry": {"coordinates":[-3.5372869968,40.4281349182],"type":"Point"}
}