{
  "type": "Feature",
  "properties": {
    "addr:full":"Ctra. Logro\u00f1o, S/n Nalda La Rioja 26190",
    "addr:housenumber":"s / n",
    "addr:postcode":"26190",
    "addr:street":"Ctra. Logron\u0303O;Rioja",
    "iso:country":"ES",
    "sg:address":"Ctra. Logro\u00f1o, S/n",
    "sg:city":"Nalda",
    "sg:orig_category":"Conservas De Legumbres (fabricaci\u00d3n, Al Por Mayor)",
    "sg:phone":"+34 941 44 73 24",
    "sg:postcode":"26190",
    "sg:province":"La Rioja",
    "wof:name":"Conservas V.jalon S.a.",
    "wof:placetype":"venue"
},
  "geometry": {"coordinates":[-2.4869959354,42.3356437683],"type":"Point"}
}