{
  "type": "Feature",
  "properties": {
    "iso:country":"ES",
    "sg:address":"Calle de Extramuros Sur, 8",
    "sg:city":"Elciego",
    "sg:orig_category":"Conservas De Carnes (fabricaci\u00d3n, Al Por Mayor)",
    "sg:phone":"+34 945 60 60 44",
    "sg:postcode":"01340",
    "sg:province":"\u00c1lava",
    "wof:name":"Murua Perez Ignacio",
    "wof:placetype":"venue"
},
  "geometry": {"coordinates":[-2.6288523674,42.511100769],"type":"Point"}
}