{
  "type": "Feature",
  "properties": {
    "addr:full":"Calle de Iglesia, S/n Sotoserrano Salamanca 37657",
    "addr:housenumber":"s / n",
    "addr:postcode":"37657",
    "addr:street":"Calle De Iglesia",
    "iso:country":"ES",
    "sg:address":"Calle de Iglesia, S/n",
    "sg:city":"Sotoserrano",
    "sg:orig_category":"Iglesia Cat\u00d3lica",
    "sg:phone":"+34 923 42 21 39",
    "sg:postcode":"37657",
    "sg:province":"Salamanca",
    "wof:name":"Obispado De Salamanca",
    "wof:placetype":"venue"
},
  "geometry": {"coordinates":[-6.0338435173,40.4386634827],"type":"Point"}
}