{
  "type": "Feature",
  "properties": {
    "iso:country":"ES",
    "sg:address":"Calle de La Purisima, 24",
    "sg:city":"Almoradi",
    "sg:orig_category":"Abogados",
    "sg:phone":"+34 966 78 11 78",
    "sg:postcode":"03160",
    "sg:province":"Alicante",
    "wof:name":"Rodriguez Perez Hermenegildo",
    "wof:placetype":"venue"
},
  "geometry": {"coordinates":[-0.790489018,38.1074905396],"type":"Point"}
}