{
  "type": "Feature",
  "properties": {
    "addr:full":"Av Tres(pol Ind Base Dos Mil), S/n Lorqui Murcia 30564",
    "addr:housenumber":"s",
    "addr:postcode":"30564",
    "addr:street":"Av Tres Pol;/ N",
    "iso:country":"ES",
    "sg:address":"Av Tres(pol Ind Base Dos Mil), S/n",
    "sg:city":"Lorqui",
    "sg:classifiers":[
        {
            "category":"Manufacturing",
            "subcategory":"Building Materials",
            "type":"Manufacturing & Wholesale Goods"
        }
    ],
    "sg:phone":"+34 968 67 63 70",
    "sg:postcode":"30564",
    "sg:province":"Murcia",
    "sg:tags":[
        "cemento",
        "y",
        "de",
        "fabricaci\u00d3n",
        "cal"
    ],
    "sg:website":"www.cementospuma.es",
    "wof:name":"Cementos Puma Murcia S.l.",
    "wof:placetype":"venue"
},
  "geometry": {"coordinates":[-1.227799058,38.1053009033],"type":"Point"}
}