{
  "type": "Feature",
  "properties": {
    "addr:full":"Calle de Mondragon, 11 Vitoria-gasteiz \u00c1lava 01013",
    "addr:housenumber":"11",
    "addr:postcode":"01013",
    "addr:street":"Calle De Mondragon",
    "iso:country":"ES",
    "sg:address":"Calle de Mondragon, 11",
    "sg:city":"Vitoria-gasteiz",
    "sg:orig_category":"Organizaci\u00d3n De Actos, Seminarios Y Congresos",
    "sg:phone":"+34 902 25 35 00",
    "sg:postcode":"01013",
    "sg:province":"\u00c1lava",
    "wof:name":"Xabide S. Coop. Ldta.",
    "wof:placetype":"venue"
},
  "geometry": {"coordinates":[-2.6840889454,42.8761367798],"type":"Point"}
}