{
  "type": "Feature",
  "properties": {
    "addr:full":"Carrer de Miquel Biada, 115 Mataro Barcelona 08302",
    "addr:housenumber":"115",
    "addr:postcode":"08302",
    "addr:street":"Carrer De Miquel Biada",
    "iso:country":"ES",
    "sg:address":"Carrer de Miquel Biada, 115",
    "sg:city":"Mataro",
    "sg:orig_category":"Reposter\u00cdas",
    "sg:phone":"+34 937 98 19 61",
    "sg:postcode":"08302",
    "sg:province":"Barcelona",
    "wof:name":"Diaz Carpena Cesar",
    "wof:placetype":"venue"
},
  "geometry": {"coordinates":[2.4339129925,41.5371322632],"type":"Point"}
}