{
  "type": "Feature",
  "properties": {
    "addr:full":"Calle de Hospital, S/n Puertollano Ciudad Real 13500",
    "addr:housenumber":"s / n",
    "addr:postcode":"13500",
    "addr:street":"Calle De Hospital",
    "iso:country":"ES",
    "sg:address":"Calle de Hospital, S/n",
    "sg:city":"Puertollano",
    "sg:orig_category":"Iglesia Cat\u00d3lica",
    "sg:phone":"+34 926 42 50 22",
    "sg:postcode":"13500",
    "sg:province":"Ciudad Real",
    "wof:name":"Parroquia De Nuestra Se\u00f1ora De La Asuncion",
    "wof:placetype":"venue"
},
  "geometry": {"coordinates":[-4.1119270325,38.6869735718],"type":"Point"}
}