{
  "type": "Feature",
  "properties": {
    "addr:full":"Calle de Santiago Cuadrado, 25 Santa Cruz De Tenerife Santa Cruz De Tenerife 38006",
    "addr:housenumber":"25",
    "addr:postcode":"38006",
    "addr:street":"Calle De Santiago Cuadrado",
    "iso:country":"ES",
    "sg:address":"Calle de Santiago Cuadrado, 25",
    "sg:city":"Santa Cruz De Tenerife",
    "sg:orig_category":"Doctores En Medicina",
    "sg:phone":"+34 922 27 88 26",
    "sg:postcode":"38006",
    "sg:province":"Santa Cruz De Tenerife",
    "wof:name":"Galera Davidson Felix",
    "wof:placetype":"venue"
},
  "geometry": {"coordinates":[-16.2627506256,28.4683475494],"type":"Point"}
}