{
  "type": "Feature",
  "properties": {
    "addr:full":"Av Bejar, 399 Terrassa Barcelona 08226",
    "addr:housenumber":"399",
    "addr:postcode":"08226",
    "addr:street":"Av Bejar",
    "iso:country":"ES",
    "sg:address":"Av Bejar, 399",
    "sg:city":"Terrassa",
    "sg:orig_category":"Ferreter\u00cda (diversos)",
    "sg:phone":"+34 937 35 60 20",
    "sg:postcode":"08226",
    "sg:province":"Barcelona",
    "wof:name":"Alonso Aguirre Luis",
    "wof:placetype":"venue"
},
  "geometry": {"coordinates":[2.0249760151,41.5804672241],"type":"Point"}
}