{
  "type": "Feature",
  "properties": {
    "addr:full":"Avda Reyes Catolicos, 11 Almazan Soria 42200",
    "addr:housenumber":"11",
    "addr:postcode":"42200",
    "addr:street":"Avda Reyes Catolicos",
    "iso:country":"ES",
    "sg:address":"Avda Reyes Catolicos, 11",
    "sg:city":"Almazan",
    "sg:orig_category":"Peluquer\u00cdas, Peluquer\u00cda Mixta",
    "sg:phone":"+34 975 30 02 46",
    "sg:postcode":"42200",
    "sg:province":"Soria",
    "wof:name":"Perez Mayoral Pilar",
    "wof:placetype":"venue"
},
  "geometry": {"coordinates":[-2.527230978,41.487197876],"type":"Point"}
}