{
  "type": "Feature",
  "properties": {
    "addr:full":"Calle de Pe\u00d1on Elias, 1 Ubrique C\u00e1diz 11600",
    "addr:housenumber":"1",
    "addr:postcode":"11600",
    "addr:street":"Calle De Pen\u0303On Elias;Ca\u0301Diz",
    "iso:country":"ES",
    "sg:address":"Calle de Pe\u00d1on Elias, 1",
    "sg:city":"Ubrique",
    "sg:orig_category":"Marroquiner\u00cda (confecci\u00d3n)",
    "sg:phone":"+34 956 46 30 72",
    "sg:postcode":"11600",
    "sg:province":"C\u00e1diz",
    "wof:name":"Fresno Cb",
    "wof:placetype":"venue"
},
  "geometry": {"coordinates":[-5.4475698471,36.6776618958],"type":"Point"}
}