{
  "type": "Feature",
  "properties": {
    "iso:country":"ES",
    "sg:address":"Cristofol Colon, 5",
    "sg:city":"Ametlla Mar",
    "sg:orig_category":"Turismo: Lugares, Circuitos Y Curiosidades",
    "sg:phone":"+34 977 45 73 13",
    "sg:postcode":"43860",
    "sg:province":"Tarragona",
    "sg:website":"www.lacovadelllopmari.com",
    "wof:name":"Creuers La Cova Del Llop Mari S.l.",
    "wof:placetype":"venue"
},
  "geometry": {"coordinates":[0.8011879921,40.8830223083],"type":"Point"}
}