{
  "type": "Feature",
  "properties": {
    "iso:country":"ES",
    "sg:address":"Calle de Huerto Manu, 5",
    "sg:city":"San Anton",
    "sg:orig_category":"Asesor\u00cda Sobre Comunicaci\u00d3n De Empresas",
    "sg:phone":"+34 968 28 14 05",
    "sg:postcode":"30009",
    "sg:province":"Murcia",
    "wof:name":"Meseguer Ortin Maria Cruz",
    "wof:placetype":"venue"
},
  "geometry": {"coordinates":[-1.1399279833,37.9907112122],"type":"Point"}
}