{
  "type": "Feature",
  "properties": {
    "addr:full":"Ctra. N. 340, Km. 0001,0 Balanegra Almer\u00eda 04713",
    "addr:postcode":"04713",
    "addr:street":"Ctra. N. 340 Km. 0001,0;Almeri\u0301A",
    "iso:country":"ES",
    "sg:address":"Ctra. N. 340, Km. 0001,0",
    "sg:city":"Balanegra",
    "sg:orig_category":"Motocicletas (agentes, Concesionarios)",
    "sg:phone":"+34 950 40 62 40",
    "sg:postcode":"04713",
    "sg:province":"Almer\u00eda",
    "wof:name":"Dean Cc Moto Racing S.l.",
    "wof:placetype":"venue"
},
  "geometry": {"coordinates":[-2.9070239067,36.7499694824],"type":"Point"}
}