{
  "type": "Feature",
  "properties": {
    "addr:full":"Carrer de Aribau, 24 Barcelona Barcelona 08011",
    "addr:housenumber":"24",
    "addr:postcode":"08011",
    "addr:street":"Carrer De Aribau",
    "iso:country":"ES",
    "sg:address":"Carrer de Aribau, 24",
    "sg:city":"Barcelona",
    "sg:orig_category":"Doctores En Medicina",
    "sg:phone":"+34 934 51 22 02",
    "sg:postcode":"08011",
    "sg:province":"Barcelona",
    "wof:name":"Perez Ballestero Maria Del Carmen",
    "wof:placetype":"venue"
},
  "geometry": {"coordinates":[2.1616389751,41.3868789673],"type":"Point"}
}