{
  "type": "Feature",
  "properties": {
    "iso:country":"ES",
    "sg:address":"Rua Parque Infantil, 19",
    "sg:city":"Porri\u00f1o",
    "sg:orig_category":"T\u00c9cnicos Veterinarios",
    "sg:phone":"+34 986 33 66 38",
    "sg:postcode":"36400",
    "sg:province":"Pontevedra",
    "wof:name":"Tea Servicios Veterinarios S.l.",
    "wof:placetype":"venue"
},
  "geometry": {"coordinates":[-8.6193037033,42.1581916809],"type":"Point"}
}