{
  "type": "Feature",
  "properties": {
    "addr:full":"Calle de Alava, 3 Armilla Granada 18100",
    "addr:housenumber":"3",
    "addr:postcode":"18100",
    "addr:street":"Calle De Alava",
    "iso:country":"ES",
    "sg:address":"Calle de Alava, 3",
    "sg:city":"Armilla",
    "sg:orig_category":"Zapatos (al Por Menor)",
    "sg:phone":"+34 958 57 23 45",
    "sg:postcode":"18100",
    "sg:province":"Granada",
    "wof:name":"Santiago Raya Fausto",
    "wof:placetype":"venue"
},
  "geometry": {"coordinates":[-3.6270289421,37.1427841187],"type":"Point"}
}