{
  "type": "Feature",
  "properties": {
    "iso:country":"ES",
    "sg:address":"Avda Libia (de), 31",
    "sg:city":"Cordoba",
    "sg:orig_category":"Hoteles",
    "sg:phone":"+34 957 43 47 36",
    "sg:postcode":"14010",
    "sg:province":"C\u00f3rdoba",
    "wof:name":"Abadi C.b.",
    "wof:placetype":"venue"
},
  "geometry": {"coordinates":[-4.758455,37.890842],"type":"Point"}
}