{
  "type": "Feature",
  "properties": {
    "iso:country":"ES",
    "sg:address":"Av Barcelona, 99",
    "sg:city":"Molins Rei",
    "sg:orig_category":"Mec\u00c1nico Del Autom\u00d3vil",
    "sg:phone":"+34 936 68 05 96",
    "sg:postcode":"08750",
    "sg:province":"Barcelona",
    "wof:name":"Autodiesel Mohedano S.l.",
    "wof:placetype":"venue"
},
  "geometry": {"coordinates":[2.0227100849,41.4072113037],"type":"Point"}
}