{
  "type": "Feature",
  "properties": {
    "addr:full":"Carrer de Passio (la), 6 Manlleu Barcelona 08560",
    "addr:housenumber":"6",
    "addr:postcode":"08560",
    "addr:street":"Carrer De Passio La",
    "iso:country":"ES",
    "sg:address":"Carrer de Passio (la), 6",
    "sg:city":"Manlleu",
    "sg:orig_category":"Comidas Por Encargo Para Colectivos",
    "sg:phone":"+34 938 51 01 78",
    "sg:postcode":"08560",
    "sg:province":"Barcelona",
    "wof:name":"Rostisseria Ca La Montse Vins Cullell S.c.p.",
    "wof:placetype":"venue"
},
  "geometry": {"coordinates":[2.2863380909,41.9998703003],"type":"Point"}
}