{
  "type": "Feature",
  "properties": {
    "iso:country":"ES",
    "sg:address":"Calle de Rodrigo Rebolledo, 32",
    "sg:city":"Zaragoza",
    "sg:orig_category":"Ropa Para Caballeros (al Por Menor)",
    "sg:phone":"+34 976 49 73 74",
    "sg:postcode":"50002",
    "sg:province":"Zaragoza",
    "wof:name":"Llop Alcuten Jose Luis",
    "wof:placetype":"venue"
},
  "geometry": {"coordinates":[-0.8624849916,41.6458473206],"type":"Point"}
}