{
  "type": "Feature",
  "properties": {
    "addr:full":"Carrer de Marne, 2 Barcelona Barcelona 08042",
    "addr:housenumber":"2",
    "addr:postcode":"08042",
    "addr:street":"Carrer De Marne",
    "iso:country":"ES",
    "sg:address":"Carrer de Marne, 2",
    "sg:city":"Barcelona",
    "sg:orig_category":"Centros De Educaci\u00d3n Especial",
    "sg:phone":"+34 933 59 62 80",
    "sg:postcode":"08042",
    "sg:province":"Barcelona",
    "wof:name":"Ajuntament De Barcelona",
    "wof:placetype":"venue"
},
  "geometry": {"coordinates":[2.1678438187,41.4373703003],"type":"Point"}
}