{
  "type": "Feature",
  "properties": {
    "iso:country":"ES",
    "sg:address":"Calle de Doctor Castelo, 34",
    "sg:city":"Madrid",
    "sg:orig_category":"Tintes (fabricaci\u00d3n, Al Por Mayor)",
    "sg:phone":"+34 915 73 11 81",
    "sg:postcode":"28009",
    "sg:province":"Madrid",
    "wof:name":"Cajigas Olazabal Jose Manuel",
    "wof:placetype":"venue"
},
  "geometry": {"coordinates":[-3.6747870445,40.4201583862],"type":"Point"}
}