{
  "type": "Feature",
  "properties": {
    "iso:country":"ES",
    "sg:address":"Carrer de Joan Maragall, 34",
    "sg:city":"S. Pere Ribes",
    "sg:orig_category":"Empresas De Carpinter\u00cda Met\u00c1lica",
    "sg:phone":"+34 938 10 21 84",
    "sg:postcode":"08810",
    "sg:province":"Barcelona",
    "sg:website":"www.al\u00f1uminiosperez.com",
    "wof:name":"Pascual Miret Pedro",
    "wof:placetype":"venue"
},
  "geometry": {"coordinates":[1.7677789927,41.260307312],"type":"Point"}
}