{
  "type": "Feature",
  "properties": {
    "addr:full":"Carrer de Alt Emporda, 39 Mora Tarragona 43008",
    "addr:housenumber":"39",
    "addr:postcode":"43008",
    "addr:street":"Carrer De Alt Emporda",
    "iso:country":"ES",
    "sg:address":"Carrer de Alt Emporda, 39",
    "sg:city":"Mora",
    "sg:orig_category":"Financiaci\u00d3n Y Cr\u00c9ditos",
    "sg:phone":"+34 977 65 25 71",
    "sg:postcode":"43008",
    "sg:province":"Tarragona",
    "wof:name":"Financial Brokers S.a.",
    "wof:placetype":"venue"
},
  "geometry": {"coordinates":[1.3460949659,41.1375007629],"type":"Point"}
}