{
  "type": "Feature",
  "properties": {
    "iso:country":"ES",
    "sg:address":"Carrer de Proven\u00c7a, 552",
    "sg:city":"Barcelona",
    "sg:orig_category":"Peluqueros: De Se\u00d1oras",
    "sg:phone":"+34 933 47 50 58",
    "sg:postcode":"08026",
    "sg:province":"Barcelona",
    "wof:name":"Millaruelo Bosch Antonia",
    "wof:placetype":"venue"
},
  "geometry": {"coordinates":[2.1803970337,41.4086914062],"type":"Point"}
}