{
  "type": "Feature",
  "properties": {
    "iso:country":"ES",
    "sg:address":"Av Tudela, 40",
    "sg:city":"Manresa",
    "sg:orig_category":"Supermercados Y Hipermercados",
    "sg:phone":"+34 938 73 37 43",
    "sg:postcode":"08242",
    "sg:province":"Barcelona",
    "wof:name":"Beltran Estrada Nuria",
    "wof:placetype":"venue"
},
  "geometry": {"coordinates":[1.8172489405,41.7312088013],"type":"Point"}
}