{
  "type": "Feature",
  "properties": {
    "iso:country":"ES",
    "sg:address":"Calle de Cercados (de Los), 37",
    "sg:city":"Manzanares El Real",
    "sg:orig_category":"Fabricaci\u00d3n Y Refinado De Az\u00dacares",
    "sg:phone":"+34 918 53 96 99",
    "sg:postcode":"28410",
    "sg:province":"Madrid",
    "wof:name":"Acedo Arias Montserrat 000173788n S.l.n.e.",
    "wof:placetype":"venue"
},
  "geometry": {"coordinates":[-3.8574864864,40.7315444946],"type":"Point"}
}