{
  "type": "Feature",
  "properties": {
    "addr:full":"Pg Carme, 40 Vilanova I La Geltru Barcelona 08800",
    "addr:housenumber":"40",
    "addr:postcode":"08800",
    "addr:street":"Pg Carme",
    "iso:country":"ES",
    "sg:address":"Pg Carme, 40",
    "sg:city":"Vilanova I La Geltru",
    "sg:orig_category":"Restaurantes",
    "sg:phone":"+34 938 15 54 79",
    "sg:postcode":"08800",
    "sg:province":"Barcelona",
    "wof:name":"Can Trasses S.c.c.l.",
    "wof:placetype":"venue"
},
  "geometry": {"coordinates":[1.7280869484,41.2154884338],"type":"Point"}
}