{
  "type": "Feature",
  "properties": {
    "addr:full":"Calle de Cronos, 63 Madrid Madrid 28037",
    "addr:housenumber":"63",
    "addr:postcode":"madrid;28037",
    "addr:street":"Calle De Cronos",
    "iso:country":"ES",
    "sg:address":"Calle de Cronos, 63",
    "sg:city":"Madrid",
    "sg:orig_category":"Inform\u00c1tica (estudios, Servicios, Asesor\u00cda, Formaci\u00d3n)",
    "sg:phone":"+34 917 54 06 58",
    "sg:postcode":"28037",
    "sg:province":"Madrid",
    "sg:website":"www.inextrama.com",
    "wof:name":"Inextrama Soluciones Informaticas Para El Sector Grafico S.l.",
    "wof:placetype":"venue"
},
  "geometry": {"coordinates":[-3.6182465553,40.4409446716],"type":"Point"}
}