{
  "type": "Feature",
  "properties": {
    "addr:full":"Plaz Santa Isabel, 2 Santa Catalina Murcia 30004",
    "addr:housenumber":"2",
    "addr:postcode":"30004",
    "addr:street":"Santa Isabel",
    "iso:country":"ES",
    "sg:address":"Plaz Santa Isabel, 2",
    "sg:city":"Santa Catalina",
    "sg:orig_category":"Cajas De Ahorro",
    "sg:phone":"+34 968 22 28 22",
    "sg:postcode":"30004",
    "sg:province":"Murcia",
    "wof:name":"Caja De Badajoz",
    "wof:placetype":"venue"
},
  "geometry": {"coordinates":[-1.1326060295,37.9855232239],"type":"Point"}
}