{
  "type": "Feature",
  "properties": {
    "iso:country":"ES",
    "sg:address":"Calle de San Jose Artesano, 2",
    "sg:city":"Fuencaliente",
    "sg:orig_category":"Electrodom\u00c9sticos (al Por Menor)",
    "sg:phone":"+34 926 47 02 83",
    "sg:postcode":"13130",
    "sg:province":"Ciudad Real",
    "wof:name":"Casado Santos Basilisa",
    "wof:placetype":"venue"
},
  "geometry": {"coordinates":[-4.3054389954,38.4061660767],"type":"Point"}
}