{
  "type": "Feature",
  "properties": {
    "addr:full":"Carrer de Marcelino Menendez Pelayo, 12 Cornella Llobregat Barcelona 08940",
    "addr:housenumber":"12",
    "addr:postcode":"08940",
    "addr:street":"Carrer De Marcelino Menendez Pelayo",
    "iso:country":"ES",
    "sg:address":"Carrer de Marcelino Menendez Pelayo, 12",
    "sg:city":"Cornella Llobregat",
    "sg:orig_category":"Panader\u00cdas, Panader\u00cdas",
    "sg:phone":"+34 933 77 85 88",
    "sg:postcode":"08940",
    "sg:province":"Barcelona",
    "wof:name":"La Pastisseria S.l",
    "wof:placetype":"venue"
},
  "geometry": {"coordinates":[2.0724339485,41.3538742065],"type":"Point"}
}