{
  "type": "Feature",
  "properties": {
    "iso:country":"ES",
    "sg:address":"Calle de Antonio Trueba Kalea, 13",
    "sg:city":"Erandio",
    "sg:orig_category":"Molduras, Junquillos, Listones Y Molduras Perforadas",
    "sg:phone":"+34 944 67 35 03",
    "sg:postcode":"48950",
    "sg:province":"Vizcaya",
    "wof:name":"Jesus Rodriguez Manjon, Bar Beiti",
    "wof:placetype":"venue"
},
  "geometry": {"coordinates":[-2.9754214287,43.3019180298],"type":"Point"}
}