{
  "type": "Feature",
  "properties": {
    "iso:country":"ES",
    "sg:address":"Ebanista, 13",
    "sg:city":"Aspe",
    "sg:orig_category":"Serigraf\u00cda (material Y Suministros)",
    "sg:phone":"+34 965 49 40 67",
    "sg:postcode":"03680",
    "sg:province":"Alicante",
    "wof:name":"Serigrabat S.l.",
    "wof:placetype":"venue"
},
  "geometry": {"coordinates":[-0.7597950101,38.3260421753],"type":"Point"}
}