{
  "type": "Feature",
  "properties": {
    "addr:full":"Calle de Villaharta, 12 Cordoba C\u00f3rdoba 14007",
    "addr:housenumber":"12",
    "addr:postcode":"14007",
    "addr:street":"Calle De Villaharta;Co\u0301Rdoba",
    "iso:country":"ES",
    "sg:address":"Calle de Villaharta, 12",
    "sg:city":"Cordoba",
    "sg:orig_category":"Molduras, Junquillos, Listones Y Molduras Perforadas",
    "sg:phone":"+34 957 43 27 47",
    "sg:postcode":"14007",
    "sg:province":"C\u00f3rdoba",
    "wof:name":"Bracero Mostazo Juan",
    "wof:placetype":"venue"
},
  "geometry": {"coordinates":[-4.7695059776,37.8959197998],"type":"Point"}
}