{
  "type": "Feature",
  "properties": {
    "iso:country":"ES",
    "sg:address":"Calle de Julian Duro, 1",
    "sg:city":"Langreo",
    "sg:orig_category":"Asociaciones, Organismos Culturales Y Socioeducativos",
    "sg:phone":"+34 985 69 21 91",
    "sg:postcode":"33930",
    "sg:province":"Asturias",
    "wof:name":"Asociacion Antiguos Alumnos De La Salle",
    "wof:placetype":"venue"
},
  "geometry": {"coordinates":[-5.688996315,43.3079566956],"type":"Point"}
}