{
  "type": "Feature",
  "properties": {
    "addr:full":"Gta. Comarcal E. Diaz Teran, 2 Zafra Badajoz 06300",
    "addr:housenumber":"2",
    "addr:postcode":"06300",
    "addr:street":"Teran",
    "iso:country":"ES",
    "sg:address":"Gta. Comarcal E. Diaz Teran, 2",
    "sg:city":"Zafra",
    "sg:orig_category":"Servicios Gsm",
    "sg:phone":"+34 924 56 31 58",
    "sg:postcode":"06300",
    "sg:province":"Badajoz",
    "wof:name":"Niza Moviles Sl",
    "wof:placetype":"venue"
},
  "geometry": {"coordinates":[-6.4164791107,38.4230194092],"type":"Point"}
}