{
  "type": "Feature",
  "properties": {
    "addr:full":"Calle de Canada, 23 Malaga M\u00e1laga 29006",
    "addr:housenumber":"23",
    "addr:postcode":"29006",
    "addr:street":"Calle De Canada;Ma\u0301Laga",
    "iso:country":"ES",
    "sg:address":"Calle de Canada, 23",
    "sg:city":"Malaga",
    "sg:orig_category":"Promotores Constructores",
    "sg:phone":"+34 952 32 28 14",
    "sg:postcode":"29006",
    "sg:province":"M\u00e1laga",
    "wof:name":"Cosuran S.l.",
    "wof:placetype":"venue"
},
  "geometry": {"coordinates":[-4.4735560417,36.7110443115],"type":"Point"}
}