{
  "type": "Feature",
  "properties": {
    "addr:full":"Calle de Atalaya, 2 Ubeda Ja\u00e9n 23400",
    "addr:housenumber":"2",
    "addr:postcode":"23400",
    "addr:street":"Calle De Atalaya;Jae\u0301N",
    "iso:country":"ES",
    "sg:address":"Calle de Atalaya, 2",
    "sg:city":"Ubeda",
    "sg:orig_category":"Contenedores (mercanc\u00cdas)",
    "sg:phone":"+34 953 75 58 45",
    "sg:postcode":"23400",
    "sg:province":"Ja\u00e9n",
    "wof:name":"Olmedilla Millan Francisco",
    "wof:placetype":"venue"
},
  "geometry": {"coordinates":[-3.3792436123,38.017791748],"type":"Point"}
}