{
  "type": "Feature",
  "properties": {
    "addr:full":"Carr Girona, 25 Angles Girona 17160",
    "addr:housenumber":"25",
    "addr:postcode":"17160",
    "addr:street":"Carr Girona",
    "iso:country":"ES",
    "sg:address":"Carr Girona, 25",
    "sg:city":"Angles",
    "sg:orig_category":"Mec\u00c1nico Del Autom\u00d3vil",
    "sg:phone":"+34 972 42 05 56",
    "sg:postcode":"17160",
    "sg:province":"Girona",
    "wof:name":"Parramon Fauchs Josep",
    "wof:placetype":"venue"
},
  "geometry": {"coordinates":[2.6347820759,41.9582252502],"type":"Point"}
}