{
  "type": "Feature",
  "properties": {
    "iso:country":"ES",
    "sg:address":"Calle de Paco Leon, 2",
    "sg:city":"Cordoba",
    "sg:orig_category":"Arquitectos",
    "sg:phone":"+34 957 25 61 91",
    "sg:postcode":"14014",
    "sg:province":"C\u00f3rdoba",
    "wof:name":"Mesa Lopez Antonio Javier",
    "wof:placetype":"venue"
},
  "geometry": {"coordinates":[-4.7565689087,37.8909988403],"type":"Point"}
}