{
  "type": "Feature",
  "properties": {
    "iso:country":"ES",
    "sg:address":"Carr Sant Joan Baptista La Salle, 35",
    "sg:city":"Girona",
    "sg:classifiers":[
        {
            "category":"Government",
            "subcategory":"Post Office",
            "type":"Public Place"
        }
    ],
    "sg:phone":"+34 972 21 53 28",
    "sg:postcode":"17002",
    "sg:province":"Girona",
    "sg:tags":[
        "de",
        "yoga",
        "clases"
    ],
    "wof:name":"Martinez Calvo Saul",
    "wof:placetype":"venue"
},
  "geometry": {"coordinates":[2.8189439774,41.9777412415],"type":"Point"}
}