{
  "type": "Feature",
  "properties": {
    "iso:country":"ES",
    "sg:address":"Calle de Jose Bastos, 75",
    "sg:city":"Madrid",
    "sg:orig_category":"Centros Empresariales",
    "sg:phone":"+34 913 57 46 94",
    "sg:postcode":"28023",
    "sg:province":"Madrid",
    "wof:name":"Mendez-vigo Vega De Seoane Jose Maria",
    "wof:placetype":"venue"
},
  "geometry": {"coordinates":[-3.7913401127,40.4710617065],"type":"Point"}
}