{
  "type": "Feature",
  "properties": {
    "addr:full":"Calle de Andalucia, 32 Malaga M\u00e1laga 29009",
    "addr:housenumber":"32",
    "addr:postcode":"29009",
    "addr:street":"Calle De Andalucia;Ma\u0301Laga",
    "iso:country":"ES",
    "sg:address":"Calle de Andalucia, 32",
    "sg:city":"Malaga",
    "sg:orig_category":"Abogados",
    "sg:phone":"+34 952 61 39 14",
    "sg:postcode":"29009",
    "sg:province":"M\u00e1laga",
    "wof:name":"Carre\u00f1o Borrego Cristobal",
    "wof:placetype":"venue"
},
  "geometry": {"coordinates":[-4.4354381561,36.7238769531],"type":"Point"}
}