{
  "type": "Feature",
  "properties": {
    "iso:country":"ES",
    "sg:address":"Calle de Rodriguez Del Valle, 1",
    "sg:city":"Le\u00f3n",
    "sg:orig_category":"Empresarios",
    "sg:phone":"+34 987 22 72 61",
    "sg:postcode":"24002",
    "sg:province":"Le\u00f3n",
    "wof:name":"Mayoral Bartolome S.l.",
    "wof:placetype":"venue"
},
  "geometry": {"coordinates":[-5.5767889023,42.600479126],"type":"Point"}
}