{
  "type": "Feature",
  "properties": {
    "iso:country":"ES",
    "sg:address":"Calle de General Franco, S/n",
    "sg:city":"Cristianos",
    "sg:orig_category":"Agencias De Trabajo Temporal",
    "sg:phone":"+34 922 77 76 00",
    "sg:postcode":"38650",
    "sg:province":"Santa Cruz De Tenerife",
    "wof:name":"Horecca Staffing Services E.t.t. S.a.",
    "wof:placetype":"venue"
},
  "geometry": {"coordinates":[-16.7186546326,28.0511054993],"type":"Point"}
}