{
  "type": "Feature",
  "properties": {
    "addr:full":"Carr Republica Portuguesa, 19 Badalona Barcelona 08912",
    "addr:housenumber":"19",
    "addr:postcode":"08912",
    "addr:street":"Carr Republica Portuguesa",
    "iso:country":"ES",
    "sg:address":"Carr Republica Portuguesa, 19",
    "sg:city":"Badalona",
    "sg:orig_category":"Empresas De Carpinter\u00cda Met\u00c1lica",
    "sg:phone":"+34 933 88 25 02",
    "sg:postcode":"08912",
    "sg:province":"Barcelona",
    "wof:name":"Themistanjioglus Chaler David",
    "wof:placetype":"venue"
},
  "geometry": {"coordinates":[2.2385408878,41.4478569031],"type":"Point"}
}