{
  "type": "Feature",
  "properties": {
    "iso:country":"ES",
    "sg:address":"Calle de Cuenca, 11",
    "sg:city":"Malaga",
    "sg:orig_category":"Quincaller\u00cda (al Por Menor)",
    "sg:phone":"+34 952 26 23 46",
    "sg:postcode":"29014",
    "sg:province":"M\u00e1laga",
    "wof:name":"Moraleda Martinez Maria Dolores",
    "wof:placetype":"venue"
},
  "geometry": {"coordinates":[-4.4208211899,36.7506370544],"type":"Point"}
}