{
  "type": "Feature",
  "properties": {
    "iso:country":"ES",
    "sg:address":"Plaz Mayor, 8",
    "sg:city":"S. Miguel Arroyo",
    "sg:orig_category":"Pescader\u00cdas (al Por Menor)",
    "sg:phone":"+34 983 69 72 62",
    "sg:postcode":"47164",
    "sg:province":"Valladolid",
    "wof:name":"Barco Martin Patrocinio Del",
    "wof:placetype":"venue"
},
  "geometry": {"coordinates":[-4.4605717659,41.441696167],"type":"Point"}
}