{
  "type": "Feature",
  "properties": {
    "addr:full":"Avda Madrid (de), 74 Avila \u00c1vila 05001",
    "addr:housenumber":"74",
    "addr:postcode":"05001",
    "addr:street":"Avda Madrid De;A\u0301Vila",
    "iso:country":"ES",
    "sg:address":"Avda Madrid (de), 74",
    "sg:city":"Avila",
    "sg:orig_category":"Electricidad Veh\u00cdculo",
    "sg:phone":"+34 920 22 44 60",
    "sg:postcode":"05001",
    "sg:province":"\u00c1vila",
    "wof:name":"Longinos Martin E Hijos S.l.",
    "wof:placetype":"venue"
},
  "geometry": {"coordinates":[-4.7032828331,40.6597862244],"type":"Point"}
}