{
  "type": "Feature",
  "properties": {
    "addr:full":"Calle de Clavijo Y Fajardo, 1 Arguineguin Las Palmas 35120",
    "addr:housenumber":"1",
    "addr:postcode":"35120",
    "addr:street":"Calle De Clavijo Y Fajardo;Palmas",
    "iso:country":"ES",
    "sg:address":"Calle de Clavijo Y Fajardo, 1",
    "sg:city":"Arguineguin",
    "sg:orig_category":"Inmobiliaria (agencias)",
    "sg:phone":"+34 928 18 50 57",
    "sg:postcode":"35120",
    "sg:province":"Las Palmas",
    "wof:name":"Blue Atlantic Management S.l.",
    "wof:placetype":"venue"
},
  "geometry": {"coordinates":[-15.6831970215,27.7615470886],"type":"Point"}
}