{
  "type": "Feature",
  "properties": {
    "addr:full":"Calle de Nueva, S/n Alhendin Granada 18620",
    "addr:housenumber":"s",
    "addr:postcode":"18620",
    "addr:street":"Calle De Nueva;/ N Alhendin",
    "iso:country":"ES",
    "sg:address":"Calle de Nueva, S/n",
    "sg:city":"Alhendin",
    "sg:orig_category":"Iglesia Cat\u00d3lica",
    "sg:phone":"+34 958 57 60 09",
    "sg:postcode":"18620",
    "sg:province":"Granada",
    "wof:name":"Parroquia De La Concepcion",
    "wof:placetype":"venue"
},
  "geometry": {"coordinates":[-3.6468031406,37.1086997986],"type":"Point"}
}