{
  "type": "Feature",
  "properties": {
    "addr:full":"Calle de Navas De Tolosa, 6 Malaga M\u00e1laga 29016",
    "addr:housenumber":"6",
    "addr:postcode":"29016",
    "addr:street":"Calle De Navas De Tolosa;Ma\u0301Laga",
    "iso:country":"ES",
    "sg:address":"Calle de Navas De Tolosa, 6",
    "sg:city":"Malaga",
    "sg:orig_category":"Procuradores",
    "sg:phone":"+34 952 21 41 46",
    "sg:postcode":"29016",
    "sg:province":"M\u00e1laga",
    "wof:name":"Domingo Corpas Jose",
    "wof:placetype":"venue"
},
  "geometry": {"coordinates":[-4.406288147,36.7207527161],"type":"Point"}
}