{
  "type": "Feature",
  "properties": {
    "addr:full":"Avda Agirre Lehendakaria, 55 Urbi Vizcaya 48970",
    "addr:housenumber":"55",
    "addr:postcode":"48970",
    "addr:street":"Avda Agirre Lehendakaria",
    "iso:country":"ES",
    "sg:address":"Avda Agirre Lehendakaria, 55",
    "sg:city":"Urbi",
    "sg:orig_category":"Deportes Y Programas De Aventura",
    "sg:phone":"+34 944 26 03 35",
    "sg:postcode":"48970",
    "sg:province":"Vizcaya",
    "wof:name":"San Real Surf S.l.",
    "wof:placetype":"venue"
},
  "geometry": {"coordinates":[-2.8794789314,43.2355804443],"type":"Point"}
}