{
  "type": "Feature",
  "properties": {
    "addr:full":"Calle de Mayor, 15 Borja Zaragoza 50540",
    "addr:housenumber":"15",
    "addr:postcode":"50540",
    "addr:street":"Calle De Mayor",
    "iso:country":"ES",
    "sg:address":"Calle de Mayor, 15",
    "sg:city":"Borja",
    "sg:orig_category":"Plomeros",
    "sg:phone":"+34 976 86 71 55",
    "sg:postcode":"50540",
    "sg:province":"Zaragoza",
    "wof:name":"Juan Burguete Jose",
    "wof:placetype":"venue"
},
  "geometry": {"coordinates":[-1.5328769684,41.833480835],"type":"Point"}
}