{
  "type": "Feature",
  "properties": {
    "addr:full":"Calle de Independencia (de La), 27 Manzanares Ciudad Real 13200",
    "addr:housenumber":"27",
    "addr:postcode":"13200",
    "addr:street":"Calle De Independencia De La",
    "iso:country":"ES",
    "sg:address":"Calle de Independencia (de La), 27",
    "sg:city":"Manzanares",
    "sg:orig_category":"Empresas De Carpinter\u00cda Met\u00c1lica",
    "sg:phone":"+34 926 61 11 26",
    "sg:postcode":"13200",
    "sg:province":"Ciudad Real",
    "wof:name":"Borja Martin Juan Jose",
    "wof:placetype":"venue"
},
  "geometry": {"coordinates":[-3.361358881,38.9951515198],"type":"Point"}
}