{
  "type": "Feature",
  "properties": {
    "iso:country":"ES",
    "sg:address":"Avda Generalisimo, S/n",
    "sg:city":"Barbate",
    "sg:orig_category":"Quincaller\u00cda (al Por Menor)",
    "sg:phone":"+34 956 43 07 38",
    "sg:postcode":"11160",
    "sg:province":"C\u00e1diz",
    "wof:name":"Perez Llorca Y Cia",
    "wof:placetype":"venue"
},
  "geometry": {"coordinates":[-5.9205489159,36.1911468506],"type":"Point"}
}