{
  "type": "Feature",
  "properties": {
    "iso:country":"ES",
    "sg:address":"Rua Castelao, 14",
    "sg:city":"Negreira",
    "sg:orig_category":"Ense\u00d1anza, Formaci\u00d3n Profesional: Aprendizaje",
    "sg:phone":"+34 981 88 62 20",
    "sg:postcode":"15830",
    "sg:province":"La Coru\u00f1a",
    "wof:name":"Instituto Nacional De La Seguridad Social",
    "wof:placetype":"venue"
},
  "geometry": {"coordinates":[-8.7344770432,42.9109954834],"type":"Point"}
}