{
  "type": "Feature",
  "properties": {
    "addr:full":"Ctra Montoro-puente Genil, S/n Aguilar De La Frontera C\u00f3rdoba 14920",
    "addr:housenumber":"s / n",
    "addr:postcode":"14920",
    "addr:street":"Ctra Montoro-Puente Genil",
    "iso:country":"ES",
    "sg:address":"Ctra Montoro-puente Genil, S/n",
    "sg:city":"Aguilar De La Frontera",
    "sg:orig_category":"Asesor\u00cda De Formaci\u00d3n Y Gesti\u00d3n De Personal",
    "sg:phone":"+34 957 66 12 34",
    "sg:postcode":"14920",
    "sg:province":"C\u00f3rdoba",
    "wof:name":"Ipagro Asesores S.l.l.",
    "wof:placetype":"venue"
},
  "geometry": {"coordinates":[-4.6616902351,37.5073776245],"type":"Point"}
}