{
  "type": "Feature",
  "properties": {
    "iso:country":"ES",
    "sg:address":"Carr Industria, De La, 13",
    "sg:city":"Barri De Porta",
    "sg:orig_category":"Delegados, Agentes De Tr\u00c1nsito, Auxiliares De Transporte Internacional",
    "sg:phone":"+34 961 52 18 86",
    "sg:postcode":"46930",
    "sg:province":"Valencia",
    "wof:name":"Grupo Transaher S.l.",
    "wof:placetype":"venue"
},
  "geometry": {"coordinates":[-0.4601689875,39.47706604],"type":"Point"}
}