{
  "type": "Feature",
  "properties": {
    "iso:country":"ES",
    "sg:address":"Carrer de Farigola, 24",
    "sg:city":"Barcelona",
    "sg:orig_category":"Mec\u00c1nico Del Autom\u00d3vil",
    "sg:phone":"+34 932 85 64 69",
    "sg:postcode":"08023",
    "sg:province":"Barcelona",
    "wof:name":"Ramos Rodriguez Manuela",
    "wof:placetype":"venue"
},
  "geometry": {"coordinates":[2.146394968,41.4123191833],"type":"Point"}
}