{
  "type": "Feature",
  "properties": {
    "addr:full":"Calle de Obispo Arenzana, 19 Calahorra La Rioja 26500",
    "addr:housenumber":"19",
    "addr:postcode":"26500",
    "addr:street":"Calle De Obispo Arenzana",
    "iso:country":"ES",
    "sg:address":"Calle de Obispo Arenzana, 19",
    "sg:city":"Calahorra",
    "sg:orig_category":"Semiller\u00cdas",
    "sg:phone":"+34 941 13 02 23",
    "sg:postcode":"26500",
    "sg:province":"La Rioja",
    "wof:name":"Vitoria Gil Santiago",
    "wof:placetype":"venue"
},
  "geometry": {"coordinates":[-1.9708718061,42.3046035767],"type":"Point"}
}