{
  "type": "Feature",
  "properties": {
    "addr:full":"Calle de Principe De Vergara, 270 Madrid Madrid 28016",
    "addr:housenumber":"270",
    "addr:postcode":"28016",
    "addr:street":"Calle De Principe De Vergara",
    "iso:country":"ES",
    "sg:address":"Calle de Principe De Vergara, 270",
    "sg:city":"Madrid",
    "sg:orig_category":"Librer\u00cdas",
    "sg:phone":"+34 914 57 31 29",
    "sg:postcode":"28016",
    "sg:province":"Madrid",
    "wof:name":"Ortega Miranda Jose",
    "wof:placetype":"venue"
},
  "geometry": {"coordinates":[-3.6770849228,40.4577674866],"type":"Point"}
}