{
  "type": "Feature",
  "properties": {
    "addr:full":"Calle de Juan Alvargonzalez, 15 Gijon Asturias 33208",
    "addr:housenumber":"15",
    "addr:postcode":"33208",
    "addr:street":"Calle De Juan Alvargonzalez",
    "iso:country":"ES",
    "sg:address":"Calle de Juan Alvargonzalez, 15",
    "sg:city":"Gijon",
    "sg:orig_category":"Mercer\u00cda, Lencer\u00cda (al Por Menor)",
    "sg:phone":"+34 985 14 42 12",
    "sg:postcode":"33208",
    "sg:province":"Asturias",
    "wof:name":"Blanco Iglesias Maria Jose",
    "wof:placetype":"venue"
},
  "geometry": {"coordinates":[-5.6706857681,43.5306243896],"type":"Point"}
}