{
  "type": "Feature",
  "properties": {
    "addr:full":"Rbla Independencia, 99 Silla Valencia 46460",
    "addr:housenumber":"99",
    "addr:postcode":"46460",
    "addr:street":"Rbla Independencia",
    "iso:country":"ES",
    "sg:address":"Rbla Independencia, 99",
    "sg:city":"Silla",
    "sg:orig_category":"Cristaler\u00cdas",
    "sg:phone":"+34 961 21 14 90",
    "sg:postcode":"46460",
    "sg:province":"Valencia",
    "wof:name":"Salvador Chafer Xavier",
    "wof:placetype":"venue"
},
  "geometry": {"coordinates":[-0.4110139906,39.3590507507],"type":"Point"}
}