{
  "type": "Feature",
  "properties": {
    "iso:country":"ES",
    "sg:address":"Plaz Luis Lopez Allue, 4",
    "sg:city":"Huesca",
    "sg:orig_category":"Conservas De Carnes (fabricaci\u00d3n, Al Por Mayor)",
    "sg:phone":"+34 974 22 63 50",
    "sg:postcode":"22001",
    "sg:province":"Huesca",
    "wof:name":"Agrupacion Provincial De Carniceros Y Salchicheros",
    "wof:placetype":"venue"
},
  "geometry": {"coordinates":[-0.4042719007,42.1405067444],"type":"Point"}
}