{
  "type": "Feature",
  "properties": {
    "addr:full":"Calle de San Isidro, S/n Majadahonda Madrid 28220",
    "addr:housenumber":"s / n",
    "addr:postcode":"28220",
    "addr:street":"Calle De San Isidro",
    "iso:country":"ES",
    "sg:address":"Calle de San Isidro, S/n",
    "sg:city":"Majadahonda",
    "sg:orig_category":"Peluqueros: De Se\u00d1oras",
    "sg:phone":"+34 916 38 75 87",
    "sg:postcode":"28220",
    "sg:province":"Madrid",
    "wof:name":"Rivua S.l.",
    "wof:placetype":"venue"
},
  "geometry": {"coordinates":[-3.8702089787,40.4731559753],"type":"Point"}
}