{
  "type": "Feature",
  "properties": {
    "iso:country":"ES",
    "sg:address":"Avda Europa, 30",
    "sg:city":"Arriondas",
    "sg:orig_category":"Quincaller\u00cda (al Por Menor)",
    "sg:phone":"+34 985 84 01 32",
    "sg:postcode":"33540",
    "sg:province":"Asturias",
    "wof:name":"Raul Nava Meana Y Otro C.b.",
    "wof:placetype":"venue"
},
  "geometry": {"coordinates":[-5.1821389198,43.3912849426],"type":"Point"}
}