{
  "type": "Feature",
  "properties": {
    "addr:full":"Ctra Pont De Vilomara, 1 Manresa Barcelona 08241",
    "addr:housenumber":"1",
    "addr:postcode":"08241",
    "addr:street":"Ctra Pont De Vilomara",
    "iso:country":"ES",
    "sg:address":"Ctra Pont De Vilomara, 1",
    "sg:city":"Manresa",
    "sg:orig_category":"Agentes Generales De Seguros",
    "sg:phone":"+34 938 72 21 96",
    "sg:postcode":"08241",
    "sg:province":"Barcelona",
    "wof:name":"Mayordomo Arpa Jaime",
    "wof:placetype":"venue"
},
  "geometry": {"coordinates":[1.8320080042,41.7292289734],"type":"Point"}
}