{
  "type": "Feature",
  "properties": {
    "addr:full":"Calle de Montera, 39 Madrid Madrid 28013",
    "addr:housenumber":"39",
    "addr:postcode":"madrid;28013",
    "addr:street":"Calle De Montera",
    "iso:country":"ES",
    "sg:address":"Calle de Montera, 39",
    "sg:city":"Madrid",
    "sg:orig_category":"Grabados",
    "sg:phone":"+34 915 21 42 52",
    "sg:postcode":"28013",
    "sg:province":"Madrid",
    "wof:name":"Guiseris Estevanez Maria Teresa",
    "wof:placetype":"venue"
},
  "geometry": {"coordinates":[-3.7021040916,40.4193916321],"type":"Point"}
}