{
  "type": "Feature",
  "properties": {
    "addr:full":"Poligono Industrial Congost, 4 Martorell Barcelona 08760",
    "addr:housenumber":"4",
    "addr:postcode":"08760",
    "iso:country":"ES",
    "sg:address":"Poligono Industrial Congost, 4",
    "sg:city":"Martorell",
    "sg:orig_category":"Contenedores (mercanc\u00cdas)",
    "sg:phone":"+34 937 75 20 30",
    "sg:postcode":"08760",
    "sg:province":"Barcelona",
    "wof:name":"S.j.trans-castillo S.l.",
    "wof:placetype":"venue"
},
  "geometry": {"coordinates":[1.9265979528,41.474105835],"type":"Point"}
}