{
  "type": "Feature",
  "properties": {
    "addr:full":"Calle de Valencia, 31 Getafe Madrid 28903",
    "addr:housenumber":"31",
    "addr:postcode":"28903",
    "addr:street":"Calle De Valencia",
    "iso:country":"ES",
    "sg:address":"Calle de Valencia, 31",
    "sg:city":"Getafe",
    "sg:orig_category":"Confecci\u00d3n De Trajes Para Se\u00d1oras",
    "sg:phone":"+34 916 95 70 37",
    "sg:postcode":"28903",
    "sg:province":"Madrid",
    "wof:name":"Maria Luz Galvez Aguilo Y German Garcia Mora Cdad.",
    "wof:placetype":"venue"
},
  "geometry": {"coordinates":[-3.7207655907,40.3121795654],"type":"Point"}
}