{
  "type": "Feature",
  "properties": {
    "addr:full":"Carr Riu Brugent, 9 Girona Girona 17003",
    "addr:housenumber":"9",
    "addr:postcode":"17003",
    "addr:street":"Carr Riu Brugent",
    "iso:country":"ES",
    "sg:address":"Carr Riu Brugent, 9",
    "sg:city":"Girona",
    "sg:orig_category":"Agencias Y Agentes Comerciales, Representantes",
    "sg:phone":"+34 972 22 72 19",
    "sg:postcode":"17003",
    "sg:province":"Girona",
    "wof:name":"Marco Peleja Carlos",
    "wof:placetype":"venue"
},
  "geometry": {"coordinates":[2.8123810291,41.961681366],"type":"Point"}
}