{
  "type": "Feature",
  "properties": {
    "iso:country":"ES",
    "sg:address":"B. Tirapu, 67",
    "sg:city":"Iru\u00f1a",
    "sg:orig_category":"Clubes Y Asociaciones Deportivas Y De Actividades Invernales Y De Monta\u00d1a",
    "sg:phone":"+34 948 16 40 80",
    "sg:postcode":"31014",
    "sg:province":"Navarra",
    "wof:name":"Federacion Internacional De Pelota Vasca",
    "wof:placetype":"venue"
},
  "geometry": {"coordinates":[-1.6508990526,42.8241882324],"type":"Point"}
}