{
  "type": "Feature",
  "properties": {
    "addr:full":"Calle de San Cayetano, 4 Potes Cantabria 39570",
    "addr:housenumber":"4",
    "addr:postcode":"39570",
    "addr:street":"Calle De San Cayetano",
    "iso:country":"ES",
    "sg:address":"Calle de San Cayetano, 4",
    "sg:city":"Potes",
    "sg:orig_category":"Empresas De Carpinter\u00cda De Madera",
    "sg:phone":"+34 942 73 01 83",
    "sg:postcode":"39570",
    "sg:province":"Cantabria",
    "wof:name":"Otero Gutierrez Jose Antonio",
    "wof:placetype":"venue"
},
  "geometry": {"coordinates":[-4.6245989799,43.1531906128],"type":"Point"}
}