{
  "type": "Feature",
  "properties": {
    "iso:country":"ES",
    "sg:address":"Psaj Josep M De Pereda, 10",
    "sg:city":"Badalona",
    "sg:orig_category":"Metalurgia",
    "sg:phone":"+34 934 60 35 60",
    "sg:postcode":"08918",
    "sg:province":"Barcelona",
    "wof:name":"Feloaga Villalba Jose Alberto",
    "wof:placetype":"venue"
},
  "geometry": {"coordinates":[2.2354440689,41.4362182617],"type":"Point"}
}