{
  "type": "Feature",
  "properties": {
    "addr:full":"Avda Leitariegos, S/n Cangas Narcea Asturias 33800",
    "addr:housenumber":"s / n",
    "addr:postcode":"33800",
    "addr:street":"Avda Leitariegos",
    "iso:country":"ES",
    "sg:address":"Avda Leitariegos, S/n",
    "sg:city":"Cangas Narcea",
    "sg:orig_category":"Sanatorios M\u00c9dico",
    "sg:phone":"+34 985 81 31 71",
    "sg:postcode":"33800",
    "sg:province":"Asturias",
    "wof:name":"Insalud-atencion Primaria Area Ii-hospital Carmen Y Severo Ochoa",
    "wof:placetype":"venue"
},
  "geometry": {"coordinates":[-6.5450277328,43.1703147888],"type":"Point"}
}