{
  "type": "Feature",
  "properties": {
    "iso:country":"ES",
    "sg:address":"Avda Asturias, 2",
    "sg:city":"Ribadeo",
    "sg:orig_category":"Promotores Constructores",
    "sg:phone":"+34 982 13 01 27",
    "sg:postcode":"27700",
    "sg:province":"Lugo",
    "wof:name":"Gayba S.l.",
    "wof:placetype":"venue"
},
  "geometry": {"coordinates":[-7.0408210754,43.5341796875],"type":"Point"}
}