{
  "type": "Feature",
  "properties": {
    "addr:full":"Calle de Iglesia, 4 Baeza Ja\u00e9n 23440",
    "addr:housenumber":"4",
    "addr:postcode":"23440",
    "addr:street":"Calle De Iglesia",
    "iso:country":"ES",
    "sg:address":"Calle de Iglesia, 4",
    "sg:city":"Baeza",
    "sg:orig_category":"Iglesia Cat\u00d3lica",
    "sg:phone":"+34 953 74 04 30",
    "sg:postcode":"23440",
    "sg:province":"Ja\u00e9n",
    "wof:name":"Parroquia Del Salvador",
    "wof:placetype":"venue"
},
  "geometry": {"coordinates":[-3.4715640545,37.9933853149],"type":"Point"}
}