{
  "type": "Feature",
  "properties": {
    "iso:country":"ES",
    "sg:address":"Calle de Peru, 9",
    "sg:city":"Almendralejo",
    "sg:orig_category":"Empresarios",
    "sg:phone":"+34 924 66 24 21",
    "sg:postcode":"06200",
    "sg:province":"Badajoz",
    "wof:name":"Diaz Benitez Francisco",
    "wof:placetype":"venue"
},
  "geometry": {"coordinates":[-6.4162740707,38.6780586243],"type":"Point"}
}