{
  "type": "Feature",
  "properties": {
    "iso:country":"ES",
    "sg:address":"C\u00aa Sant Feliu, Km. 0027,7",
    "sg:city":"Sta. Cristina Aro",
    "sg:orig_category":"Pintura, Barniz, Productos Asimilables (fabricaci\u00d3n, Al Por Mayor)",
    "sg:phone":"+34 972 83 77 61",
    "sg:postcode":"17246",
    "sg:province":"Girona",
    "sg:website":"www.gespaint.com",
    "wof:name":"Gespaint S.l.",
    "wof:placetype":"venue"
},
  "geometry": {"coordinates":[2.9987950325,41.8115959167],"type":"Point"}
}