{
  "type": "Feature",
  "properties": {
    "iso:country":"ES",
    "sg:address":"Ctra. Son Servera, S/n",
    "sg:city":"Cala Millor",
    "sg:orig_category":"Empresas De Limpieza",
    "sg:phone":"+34 971 58 77 97",
    "sg:postcode":"07560",
    "sg:province":"Islas Baleares",
    "wof:name":"Limpiezas M.ruiz S.l.",
    "wof:placetype":"venue"
},
  "geometry": {"coordinates":[3.3819820881,39.6054573059],"type":"Point"}
}