{
  "type": "Feature",
  "properties": {
    "iso:country":"ES",
    "sg:address":"P. Industrial, 3",
    "sg:city":"Rota",
    "sg:orig_category":"Electricidad: Instaladores",
    "sg:phone":"+34 956 84 05 15",
    "sg:postcode":"11520",
    "sg:province":"C\u00e1diz",
    "wof:name":"Rota Electricidad Y Montajes S.l.l.",
    "wof:placetype":"venue"
},
  "geometry": {"coordinates":[-6.3688821793,36.6247940063],"type":"Point"}
}