{
  "type": "Feature",
  "properties": {
    "iso:country":"ES",
    "sg:address":"Calle de Padre Vidal, 20",
    "sg:city":"Alca\u00f1iz",
    "sg:orig_category":"Peluquer\u00cdas, Peluquer\u00cda Mixta",
    "sg:phone":"+34 978 83 17 65",
    "sg:postcode":"44600",
    "sg:province":"Teruel",
    "wof:name":"Peluqueria R.c.juste S.l.",
    "wof:placetype":"venue"
},
  "geometry": {"coordinates":[-0.1315699965,41.046131134],"type":"Point"}
}