{
  "type": "Feature",
  "properties": {
    "iso:country":"ES",
    "sg:address":"Carrer de Roger De Flor, 96",
    "sg:city":"Barcelona",
    "sg:orig_category":"Carnicer\u00cdas, Carnicer\u00cdas",
    "sg:phone":"+34 932 45 75 38",
    "sg:postcode":"08013",
    "sg:province":"Barcelona",
    "wof:name":"Mor Sinobas Vicente",
    "wof:placetype":"venue"
},
  "geometry": {"coordinates":[2.1788499355,41.3943214417],"type":"Point"}
}