{
  "type": "Feature",
  "properties": {
    "addr:full":"Avda Juan Carlos I, 14 Tobarra Albacete 02500",
    "addr:housenumber":"14",
    "addr:postcode":"02500",
    "addr:street":"Avda Juan Carlos I",
    "iso:country":"ES",
    "sg:address":"Avda Juan Carlos I, 14",
    "sg:city":"Tobarra",
    "sg:orig_category":"Asociaciones, Organismos Culturales Y Socioeducativos",
    "sg:phone":"+34 967 32 81 62",
    "sg:postcode":"02500",
    "sg:province":"Albacete",
    "wof:name":"Ayuntamiento De Tobarra",
    "wof:placetype":"venue"
},
  "geometry": {"coordinates":[-1.6884915829,38.5907363892],"type":"Point"}
}