{
  "type": "Feature",
  "properties": {
    "iso:country":"ES",
    "sg:address":"Calle de Cuadrilla De Laguardia-rioja Alavesa, 60",
    "sg:city":"Vitoria-gasteiz",
    "sg:orig_category":"Asociaciones, Organismos Culturales Y Socioeducativos",
    "sg:phone":"+34 945 25 95 72",
    "sg:postcode":"01013",
    "sg:province":"\u00c1lava",
    "wof:name":"Asociacion Cultural Deportiva Club De Pesca El Oso",
    "wof:placetype":"venue"
},
  "geometry": {"coordinates":[-2.6643743515,42.8586578369],"type":"Point"}
}