{
  "type": "Feature",
  "properties": {
    "iso:country":"ES",
    "sg:address":"Calle de Fresno, 32",
    "sg:city":"Gormaig",
    "sg:orig_category":"Centros Empresariales",
    "sg:phone":"+34 965 59 27 23",
    "sg:postcode":"03820",
    "sg:province":"Alicante",
    "wof:name":"Hermanos Santamaria Cortes S.l.",
    "wof:placetype":"venue"
},
  "geometry": {"coordinates":[-0.4608376026,38.7186050415],"type":"Point"}
}