{
  "type": "Feature",
  "properties": {
    "addr:full":"Calle de Granada, 52 Osuna Sevilla 41640",
    "addr:housenumber":"52",
    "addr:postcode":"41640",
    "addr:street":"Calle De Granada",
    "iso:country":"ES",
    "sg:address":"Calle de Granada, 52",
    "sg:city":"Osuna",
    "sg:orig_category":"Carnicer\u00cdas, Carnicer\u00cdas",
    "sg:phone":"+34 954 81 24 56",
    "sg:postcode":"41640",
    "sg:province":"Sevilla",
    "wof:name":"Carnicerias Moya Nu\u00f1ez S.c. Andaluza",
    "wof:placetype":"venue"
},
  "geometry": {"coordinates":[-5.1031608582,37.2400817871],"type":"Point"}
}