{
  "type": "Feature",
  "properties": {
    "iso:country":"ES",
    "sg:address":"Ctra. Vja. Salvatierra, Km. 0001,9",
    "sg:city":"Aldeavieja De Tormes",
    "sg:orig_category":"Carnicer\u00cdas, Carnicer\u00cdas",
    "sg:phone":"+34 923 58 06 54",
    "sg:postcode":"37779",
    "sg:province":"Salamanca",
    "wof:name":"Victor Gomez S.a.",
    "wof:placetype":"venue"
},
  "geometry": {"coordinates":[-5.6143941879,40.5835647583],"type":"Point"}
}