{
  "type": "Feature",
  "properties": {
    "iso:country":"ES",
    "sg:address":"Calle de Panama, 1",
    "sg:city":"Majadahonda",
    "sg:orig_category":"Inmobiliaria (agencias)",
    "sg:phone":"+34 916 34 12 88",
    "sg:postcode":"28220",
    "sg:province":"Madrid",
    "wof:name":"Alfonso Ruiz Lopez S.l",
    "wof:placetype":"venue"
},
  "geometry": {"coordinates":[-3.8714947701,40.4768028259],"type":"Point"}
}