{
  "type": "Feature",
  "properties": {
    "addr:full":"Calle de San Miguel, 21 Amorebieta Vizcaya 48340",
    "addr:housenumber":"21",
    "addr:postcode":"48340",
    "addr:street":"Calle De San Miguel",
    "iso:country":"ES",
    "sg:address":"Calle de San Miguel, 21",
    "sg:city":"Amorebieta",
    "sg:orig_category":"T\u00c9cnicos Veterinarios",
    "sg:phone":"+34 946 73 21 02",
    "sg:postcode":"48340",
    "sg:province":"Vizcaya",
    "wof:name":"Kaitana C.b.",
    "wof:placetype":"venue"
},
  "geometry": {"coordinates":[-2.7321588993,43.2210960388],"type":"Point"}
}