{
  "type": "Feature",
  "properties": {
    "iso:country":"ES",
    "sg:address":"Carrer de Pau Piferrer, 17",
    "sg:city":"Palma",
    "sg:orig_category":"Plomeros",
    "sg:phone":"+34 971 73 49 53",
    "sg:postcode":"07011",
    "sg:province":"Islas Baleares",
    "wof:name":"Fontaneria Estadio S.l",
    "wof:placetype":"venue"
},
  "geometry": {"coordinates":[2.6424779892,39.578125],"type":"Point"}
}