{
  "type": "Feature",
  "properties": {
    "addr:full":"Avda De La Libertad, 4 Vinaros Castell\u00f3n 12500",
    "addr:housenumber":"4",
    "addr:postcode":"12500",
    "addr:street":"Avda De La Libertad",
    "iso:country":"ES",
    "sg:address":"Avda De La Libertad, 4",
    "sg:city":"Vinaros",
    "sg:orig_category":"Cer\u00c1micas: Material Y Suministros",
    "sg:phone":"+34 964 45 17 46",
    "sg:postcode":"12500",
    "sg:province":"Castell\u00f3n",
    "wof:name":"Sebastian Quixal S.l.",
    "wof:placetype":"venue"
},
  "geometry": {"coordinates":[0.4749450088,40.4711990356],"type":"Point"}
}