{
  "type": "Feature",
  "properties": {
    "iso:country":"ES",
    "sg:address":"Cmno Boleo, 4",
    "sg:city":"Quintanar Orden",
    "sg:orig_category":"M\u00c1rmoles, Granitos Y Piedras Naturales",
    "sg:phone":"+34 925 18 16 77",
    "sg:postcode":"45800",
    "sg:province":"Toledo",
    "wof:name":"Pintado Mu\u00f1oz Tomas Ramon",
    "wof:placetype":"venue"
},
  "geometry": {"coordinates":[-3.047492981,39.5965499878],"type":"Point"}
}