{
  "type": "Feature",
  "properties": {
    "addr:full":"Calle de Jose Chust, 12 Catarroja Valencia 46470",
    "addr:housenumber":"12",
    "addr:postcode":"46470",
    "addr:street":"Calle De Jose Chust",
    "iso:country":"ES",
    "sg:address":"Calle de Jose Chust, 12",
    "sg:city":"Catarroja",
    "sg:orig_category":"Comadronas",
    "sg:phone":"+34 961 26 11 08",
    "sg:postcode":"46470",
    "sg:province":"Valencia",
    "wof:name":"Raga Gamon Carmen",
    "wof:placetype":"venue"
},
  "geometry": {"coordinates":[-0.4031859934,39.4005699158],"type":"Point"}
}