{
  "type": "Feature",
  "properties": {
    "addr:full":"Carr Ricardo Benavent, 8 Benissa Alicante 03720",
    "addr:housenumber":"8",
    "addr:postcode":"03720",
    "addr:street":"Carr Ricardo Benavent",
    "iso:country":"ES",
    "sg:address":"Carr Ricardo Benavent, 8",
    "sg:city":"Benissa",
    "sg:orig_category":"Promotores Constructores",
    "sg:phone":"+34 965 73 07 91",
    "sg:postcode":"03720",
    "sg:province":"Alicante",
    "wof:name":"Arlandis Cardona Pascual",
    "wof:placetype":"venue"
},
  "geometry": {"coordinates":[0.0524898991,38.714225769],"type":"Point"}
}