{
  "type": "Feature",
  "properties": {
    "iso:country":"ES",
    "sg:address":"Calle de Obispo Rey Redondo, 37",
    "sg:city":"San Cristobal De La Laguna",
    "sg:orig_category":"Inmobiliaria (agencias)",
    "sg:phone":"+34 922 26 55 10",
    "sg:postcode":"38201",
    "sg:province":"Santa Cruz De Tenerife",
    "wof:name":"Perez Caceres Juam Manuel",
    "wof:placetype":"venue"
},
  "geometry": {"coordinates":[-16.3172187805,28.4888324738],"type":"Point"}
}