{
  "type": "Feature",
  "properties": {
    "addr:full":"Calle de Julio Romero De Torres, S/n Villanueva Cordoba C\u00f3rdoba 14440",
    "addr:postcode":"14440",
    "addr:street":"Calle De Julio Romero De Torres S / N;Cordoba Co\u0301Rdoba",
    "iso:country":"ES",
    "sg:address":"Calle de Julio Romero De Torres, S/n",
    "sg:city":"Villanueva Cordoba",
    "sg:orig_category":"Guarder\u00cdas",
    "sg:phone":"+34 957 12 21 99",
    "sg:postcode":"14440",
    "sg:province":"C\u00f3rdoba",
    "wof:name":"Jarotines Jarotines S.coop. Andaluza",
    "wof:placetype":"venue"
},
  "geometry": {"coordinates":[-4.6307640076,38.3280944824],"type":"Point"}
}