{
  "type": "Feature",
  "properties": {
    "iso:country":"ES",
    "sg:address":"Calle de Jose Maria Pereda, 1",
    "sg:city":"Alcala Henares",
    "sg:orig_category":"Quincaller\u00cda (al Por Menor)",
    "sg:phone":"+34 918 02 72 31",
    "sg:postcode":"28806",
    "sg:province":"Madrid",
    "wof:name":"Rubio Garrido Maria Teresa",
    "wof:placetype":"venue"
},
  "geometry": {"coordinates":[-3.3633260727,40.4962463379],"type":"Point"}
}