{
  "type": "Feature",
  "properties": {
    "addr:full":"Afueras, S/n Villalba Alcores Valladolid 47639",
    "addr:postcode":"47639",
    "addr:street":"Afueras S / N",
    "iso:country":"ES",
    "sg:address":"Afueras, S/n",
    "sg:city":"Villalba Alcores",
    "sg:orig_category":"Cr\u00cda De Animales",
    "sg:phone":"+34 983 72 15 98",
    "sg:postcode":"47639",
    "sg:province":"Valladolid",
    "wof:name":"Cacesa",
    "wof:placetype":"venue"
},
  "geometry": {"coordinates":[-4.8577241898,41.8624038696],"type":"Point"}
}