{
  "type": "Feature",
  "properties": {
    "addr:full":"Rua Exercito Espa\u00d1ol, 62 Ferrol La Coru\u00f1a 15406",
    "addr:housenumber":"62",
    "addr:postcode":"15406",
    "addr:street":"Rua Exercito Espan\u0303Ol;La Corun\u0303A",
    "iso:country":"ES",
    "sg:address":"Rua Exercito Espa\u00d1ol, 62",
    "sg:city":"Ferrol",
    "sg:orig_category":"Panader\u00cdas, Panader\u00cdas",
    "sg:phone":"+34 981 31 56 78",
    "sg:postcode":"15406",
    "sg:province":"La Coru\u00f1a",
    "wof:name":"Industriales Panaderos Agrupados S.a.",
    "wof:placetype":"venue"
},
  "geometry": {"coordinates":[-8.2011079788,43.4837760925],"type":"Point"}
}