{
  "type": "Feature",
  "properties": {
    "addr:full":"Plaz Lopez Almagro, S/n Ubeda Ja\u00e9n 23400",
    "addr:housenumber":"s / n",
    "addr:postcode":"23400",
    "addr:street":"Almagro;Ubeda Jae\u0301N",
    "iso:country":"ES",
    "sg:address":"Plaz Lopez Almagro, S/n",
    "sg:city":"Ubeda",
    "sg:orig_category":"Molduras, Junquillos, Listones Y Molduras Perforadas",
    "sg:phone":"+34 953 79 30 81",
    "sg:postcode":"23400",
    "sg:province":"Ja\u00e9n",
    "wof:name":"Eurotel Sur",
    "wof:placetype":"venue"
},
  "geometry": {"coordinates":[-3.367538929,38.0083732605],"type":"Point"}
}