{
  "type": "Feature",
  "properties": {
    "iso:country":"ES",
    "sg:address":"Carrer de Petritxol, 1",
    "sg:city":"Barcelona",
    "sg:orig_category":"Ropa Para Se\u00d1oras Y Caballeros (al Por Menor)",
    "sg:phone":"+34 933 18 72 31",
    "sg:postcode":"08002",
    "sg:province":"Barcelona",
    "wof:name":"Dragfly S.l.",
    "wof:placetype":"venue"
},
  "geometry": {"coordinates":[2.1731729507,41.3824386597],"type":"Point"}
}