{
  "type": "Feature",
  "properties": {
    "iso:country":"ES",
    "sg:address":"Avda Constitucion (de La), 20",
    "sg:city":"Pedro Mu\u00e7oz",
    "sg:orig_category":"Aparatos E Instalaci\u00d3n De Regad\u00cdos",
    "sg:phone":"+34 926 58 62 79",
    "sg:postcode":"13620",
    "sg:province":"Ciudad Real",
    "wof:name":"Riegos Cano Jimenez S.l.",
    "wof:placetype":"venue"
},
  "geometry": {"coordinates":[-2.955878973,39.4055213928],"type":"Point"}
}