{
  "type": "Feature",
  "properties": {
    "iso:country":"ES",
    "sg:address":"Calle de Martires, 11",
    "sg:city":"Torrelavega",
    "sg:orig_category":"Abogados",
    "sg:phone":"+34 942 89 21 43",
    "sg:postcode":"39300",
    "sg:province":"Cantabria",
    "wof:name":"Manrique Quintana Carmen Mercedes",
    "wof:placetype":"venue"
},
  "geometry": {"coordinates":[-4.0484142303,43.3520622253],"type":"Point"}
}