{
  "type": "Feature",
  "properties": {
    "addr:full":"Ctra Sevilla-merida, Km. 0805,0 Valencina Concepcion Sevilla 41907",
    "addr:postcode":"41907",
    "addr:street":"Ctra Sevilla-Merida Km. 0805,0",
    "iso:country":"ES",
    "sg:address":"Ctra Sevilla-merida, Km. 0805,0",
    "sg:city":"Valencina Concepcion",
    "sg:orig_category":"Artesan\u00cda De Mesa: Cristaler\u00cda, Vajilla, Orfebrer\u00cda (fabricaci\u00d3n, Al Por Mayor)",
    "sg:phone":"+34 955 99 74 12",
    "sg:postcode":"41907",
    "sg:province":"Sevilla",
    "wof:name":"Pickman S.a.",
    "wof:placetype":"venue"
},
  "geometry": {"coordinates":[-6.0776147842,37.4170455933],"type":"Point"}
}