{
  "type": "Feature",
  "properties": {
    "addr:full":"Rua Praza (da), 24 Grove Pontevedra 36980",
    "addr:housenumber":"24",
    "addr:postcode":"36980",
    "addr:street":"Rua Praza Da;Grove Pontevedra",
    "iso:country":"ES",
    "sg:address":"Rua Praza (da), 24",
    "sg:city":"Grove",
    "sg:orig_category":"Artesan\u00cda Y Trabajos Manuales: Suministros (al Por Menor)",
    "sg:phone":"+34 986 73 12 42",
    "sg:postcode":"36980",
    "sg:province":"Pontevedra",
    "wof:name":"Otras Latitudes C.b.",
    "wof:placetype":"venue"
},
  "geometry": {"coordinates":[-8.8647975922,42.4955062866],"type":"Point"}
}