{
  "type": "Feature",
  "properties": {
    "addr:full":"Carrer de Tamarit, 156 Barcelona Barcelona 08011",
    "addr:housenumber":"156",
    "addr:postcode":"08011",
    "addr:street":"Carrer De Tamarit",
    "iso:country":"ES",
    "sg:address":"Carrer de Tamarit, 156",
    "sg:city":"Barcelona",
    "sg:orig_category":"Peluquer\u00cdas, Peluquer\u00cda Mixta",
    "sg:phone":"+34 934 43 24 28",
    "sg:postcode":"08011",
    "sg:province":"Barcelona",
    "wof:name":"Shine Look Scp",
    "wof:placetype":"venue"
},
  "geometry": {"coordinates":[2.1624031067,41.3795318604],"type":"Point"}
}