{
  "type": "Feature",
  "properties": {
    "iso:country":"ES",
    "sg:address":"Avda Andres Segovia, 12",
    "sg:city":"Linares",
    "sg:orig_category":"Agentes Generales De Seguros",
    "sg:phone":"+34 953 60 21 46",
    "sg:postcode":"23700",
    "sg:province":"Ja\u00e9n",
    "wof:name":"Perez Sueza Pilar",
    "wof:placetype":"venue"
},
  "geometry": {"coordinates":[-3.6395230293,38.0982894897],"type":"Point"}
}