{
  "type": "Feature",
  "properties": {
    "iso:country":"ES",
    "sg:address":"Manuel W Guimbarda, 22",
    "sg:city":"Cartagena",
    "sg:orig_category":"Agencias De Trabajo Temporal",
    "sg:phone":"+34 968 52 99 98",
    "sg:postcode":"30204",
    "sg:province":"Murcia",
    "sg:website":"www.humangroup.es",
    "wof:name":"Alta Gestion S.a.",
    "wof:placetype":"venue"
},
  "geometry": {"coordinates":[-0.9863820076,37.6082115173],"type":"Point"}
}