{
  "type": "Feature",
  "properties": {
    "iso:country":"ES",
    "sg:address":"Aurrera Manzana 2, 16",
    "sg:city":"Valle Trapaga",
    "sg:orig_category":"Hormig\u00d3n (m\u00c1quinas E Instalaci\u00d3n)",
    "sg:phone":"+34 944 72 07 04",
    "sg:postcode":"48510",
    "sg:province":"Vizcaya",
    "wof:name":"Hormigoneras Reunidas, S.l.",
    "wof:placetype":"venue"
},
  "geometry": {"coordinates":[-3.0369338989,43.3047294617],"type":"Point"}
}