{
  "type": "Feature",
  "properties": {
    "iso:country":"ES",
    "sg:address":"Plaz Buen Pastor Del, S/n",
    "sg:city":"Donostia-san Sebastian",
    "sg:orig_category":"Iglesia Cat\u00d3lica",
    "sg:phone":"+34 943 46 45 16",
    "sg:postcode":"20005",
    "sg:province":"Guip\u00f9zcoa",
    "wof:name":"Parroquia Del Buen Pastor",
    "wof:placetype":"venue"
},
  "geometry": {"coordinates":[-1.9812940359,43.3169250488],"type":"Point"}
}