{
  "type": "Feature",
  "properties": {
    "addr:full":"Calle de Antonio Martinez De Pinillos, 7 Almendralejo Badajoz 06200",
    "addr:housenumber":"7",
    "addr:postcode":"06200",
    "addr:street":"Calle De Antonio Martinez De Pinillos",
    "iso:country":"ES",
    "sg:address":"Calle de Antonio Martinez De Pinillos, 7",
    "sg:city":"Almendralejo",
    "sg:orig_category":"Inform\u00c1tica: Material Y Suministros",
    "sg:phone":"+34 924 66 31 78",
    "sg:postcode":"06200",
    "sg:province":"Badajoz",
    "sg:website":"www.jump.es",
    "wof:name":"Jump Ordenadores S.l.",
    "wof:placetype":"venue"
},
  "geometry": {"coordinates":[-6.4026918411,38.6827163696],"type":"Point"}
}