{
  "type": "Feature",
  "properties": {
    "iso:country":"ES",
    "sg:address":"Calle de Justiniano, 8",
    "sg:city":"Madrid",
    "sg:orig_category":"Tapiceros Y Tapiceros",
    "sg:phone":"+34 913 19 89 81",
    "sg:postcode":"28004",
    "sg:province":"Madrid",
    "wof:name":"Valero Artola Fernando",
    "wof:placetype":"venue"
},
  "geometry": {"coordinates":[-3.6949870586,40.425868988],"type":"Point"}
}