{
  "type": "Feature",
  "properties": {
    "iso:country":"ES",
    "sg:address":"Paseo Maritim De Neptu",
    "sg:city":"Grao Gandia",
    "sg:orig_category":"Reposter\u00cdas",
    "sg:phone":"+34 962 84 20 84",
    "sg:postcode":"46730",
    "sg:province":"Valencia",
    "wof:name":"Allegra Y Vecchia S.l.",
    "wof:placetype":"venue"
},
  "geometry": {"coordinates":[-0.1660270989,39.0085029602],"type":"Point"}
}