{
  "type": "Feature",
  "properties": {
    "iso:country":"ES",
    "sg:address":"Plaz Gabriel Y Galan, 6",
    "sg:city":"Salamanca",
    "sg:orig_category":"Abogados",
    "sg:phone":"+34 923 25 87 50",
    "sg:postcode":"37005",
    "sg:province":"Salamanca",
    "wof:name":"Benavente Cuesta Manuel",
    "wof:placetype":"venue"
},
  "geometry": {"coordinates":[-5.6616292,40.9703369141],"type":"Point"}
}