{
  "type": "Feature",
  "properties": {
    "iso:country":"ES",
    "sg:address":"Barr San Juan, 22",
    "sg:city":"Boo",
    "sg:orig_category":"Internados & Ense\u00d1anza Privada",
    "sg:phone":"+34 942 58 62 60",
    "sg:postcode":"39478",
    "sg:province":"Cantabria",
    "wof:name":"Parroquia De Boo",
    "wof:placetype":"venue"
},
  "geometry": {"coordinates":[-3.9400789738,43.4105300903],"type":"Point"}
}