{
  "type": "Feature",
  "properties": {
    "addr:full":"Calle de Ezequiel Lopez, S/n Cedeira La Coru\u00f1a 15350",
    "addr:housenumber":"s / n",
    "addr:postcode":"15350",
    "addr:street":"Calle De Ezequiel Lopez;La Corun\u0303A",
    "iso:country":"ES",
    "sg:address":"Calle de Ezequiel Lopez, S/n",
    "sg:city":"Cedeira",
    "sg:orig_category":"Electricidad: Instaladores",
    "sg:phone":"+34 981 48 01 96",
    "sg:postcode":"15350",
    "sg:province":"La Coru\u00f1a",
    "wof:name":"Mayserel S.l.",
    "wof:placetype":"venue"
},
  "geometry": {"coordinates":[-8.056098938,43.660736084],"type":"Point"}
}