{
  "type": "Feature",
  "properties": {
    "iso:country":"ES",
    "sg:address":"Plaz Constitucion, 1",
    "sg:city":"Carcelen",
    "sg:orig_category":"Bibliotecas, Mediatecas",
    "sg:phone":"+34 967 40 30 22",
    "sg:postcode":"02153",
    "sg:province":"Albacete",
    "wof:name":"Ayuntamiento De Carcelen",
    "wof:placetype":"venue"
},
  "geometry": {"coordinates":[-1.3084770441,39.1018562317],"type":"Point"}
}