{
  "type": "Feature",
  "properties": {
    "iso:country":"ES",
    "sg:address":"Carr Roscada, 20",
    "sg:city":"Cassa Selva",
    "sg:orig_category":"Panader\u00cdas, Panader\u00cdas",
    "sg:phone":"+34 972 46 04 86",
    "sg:postcode":"17244",
    "sg:province":"Girona",
    "wof:name":"Uransel S.l.",
    "wof:placetype":"venue"
},
  "geometry": {"coordinates":[2.8780760765,41.8896598816],"type":"Point"}
}