{
  "type": "Feature",
  "properties": {
    "addr:full":"Calle de Virgen Del Prado, 47 Higuera Sierra Huelva 21220",
    "addr:housenumber":"47",
    "addr:postcode":"21220",
    "addr:street":"Calle De Virgen Del Prado",
    "iso:country":"ES",
    "sg:address":"Calle de Virgen Del Prado, 47",
    "sg:city":"Higuera Sierra",
    "sg:orig_category":"Mataderos Y Talleres De Despiezado",
    "sg:phone":"+34 959 19 60 92",
    "sg:postcode":"21220",
    "sg:province":"Huelva",
    "wof:name":"Ramos Gonzalez S.l.",
    "wof:placetype":"venue"
},
  "geometry": {"coordinates":[-6.445748806,37.8351402283],"type":"Point"}
}