{
  "type": "Feature",
  "properties": {
    "addr:full":"Carrer de Rectoria, 1 Gava Barcelona 08850",
    "addr:housenumber":"1",
    "addr:postcode":"08850",
    "addr:street":"Carrer De Rectoria",
    "iso:country":"ES",
    "sg:address":"Carrer de Rectoria, 1",
    "sg:city":"Gava",
    "sg:orig_category":"Peluquer\u00cdas, Peluquer\u00cda Mixta",
    "sg:phone":"+34 936 62 39 01",
    "sg:postcode":"08850",
    "sg:province":"Barcelona",
    "wof:name":"Molero Gomez Eulogia",
    "wof:placetype":"venue"
},
  "geometry": {"coordinates":[2.0034220219,41.3039474487],"type":"Point"}
}