{
  "type": "Feature",
  "properties": {
    "iso:country":"ES",
    "sg:address":"Calle de Cardenal Cisneros, 5",
    "sg:city":"Madrid",
    "sg:orig_category":"Deportes N\u00c1uticos, Acu\u00c1ticos Y Subacu\u00c1ticos: Art\u00cdculos Y Equipo (al Por Menor)",
    "sg:phone":"+34 915 91 96 91",
    "sg:postcode":"28010",
    "sg:province":"Madrid",
    "sg:website":"www.marsans.es",
    "wof:name":"Lucas Dive S.l.",
    "wof:placetype":"venue"
},
  "geometry": {"coordinates":[-3.701592207,40.4297218323],"type":"Point"}
}