{
  "type": "Feature",
  "properties": {
    "iso:country":"ES",
    "sg:address":"Calle de Gallega (la), 27",
    "sg:city":"Gallega",
    "sg:orig_category":"Imprenta",
    "sg:phone":"+34 922 62 04 88",
    "sg:postcode":"38108",
    "sg:province":"Santa Cruz De Tenerife",
    "wof:name":"Graficas Ansay S.l.",
    "wof:placetype":"venue"
},
  "geometry": {"coordinates":[-16.31939888,28.430727005],"type":"Point"}
}