{
  "type": "Feature",
  "properties": {
    "addr:full":"Calle de Sevilla, 16 Gines Sevilla 41960",
    "addr:housenumber":"16",
    "addr:postcode":"41960",
    "addr:street":"Calle De Sevilla;Sevilla",
    "iso:country":"ES",
    "sg:address":"Calle de Sevilla, 16",
    "sg:city":"Gines",
    "sg:orig_category":"Agencias Y Agentes Comerciales, Representantes",
    "sg:phone":"+34 954 71 32 15",
    "sg:postcode":"41960",
    "sg:province":"Sevilla",
    "wof:name":"Ceballos Sport S.l.",
    "wof:placetype":"venue"
},
  "geometry": {"coordinates":[-6.0721259117,37.3857154846],"type":"Point"}
}