{
  "type": "Feature",
  "properties": {
    "addr:full":"Calle de Garcia Alix, 2 San Antolin Murcia 30005",
    "addr:housenumber":"2",
    "addr:postcode":"30005",
    "addr:street":"Calle De Garcia Alix;San Antolin",
    "iso:country":"ES",
    "sg:address":"Calle de Garcia Alix, 2",
    "sg:city":"San Antolin",
    "sg:orig_category":"Puertas Y Portales",
    "sg:phone":"+34 968 29 19 06",
    "sg:postcode":"30005",
    "sg:province":"Murcia",
    "wof:name":"Aleman Sainz Luis",
    "wof:placetype":"venue"
},
  "geometry": {"coordinates":[-1.1375941038,37.9848709106],"type":"Point"}
}