{
  "type": "Feature",
  "properties": {
    "addr:full":"Carrer de Cartagena, 178 Barcelona Barcelona 08013",
    "addr:housenumber":"178",
    "addr:postcode":"08013",
    "addr:street":"Carrer De Cartagena",
    "iso:country":"ES",
    "sg:address":"Carrer de Cartagena, 178",
    "sg:city":"Barcelona",
    "sg:orig_category":"Marroquiner\u00cda (confecci\u00d3n)",
    "sg:phone":"+34 932 45 75 85",
    "sg:postcode":"08013",
    "sg:province":"Barcelona",
    "wof:name":"Bolsos Roca S.l.",
    "wof:placetype":"venue"
},
  "geometry": {"coordinates":[2.1823270321,41.4051933289],"type":"Point"}
}