{
  "type": "Feature",
  "properties": {
    "iso:country":"ES",
    "sg:address":"Calle de Alcalde Pedro Gonzalez Gonzalez, 15",
    "sg:city":"Leganes",
    "sg:orig_category":"Molduras, Junquillos, Listones Y Molduras Perforadas",
    "sg:phone":"+34 916 48 51 00",
    "sg:postcode":"28914",
    "sg:province":"Madrid",
    "wof:name":"Cytasa Comunicaciones S.l.",
    "wof:placetype":"venue"
},
  "geometry": {"coordinates":[-3.7863240242,40.3174552917],"type":"Point"}
}