{
  "type": "Feature",
  "properties": {
    "addr:full":"Calle de San Vicente Martir, 50 Valencia Valencia 46002",
    "addr:housenumber":"50",
    "addr:postcode":"46002",
    "addr:street":"Calle De San Vicente Martir",
    "iso:country":"ES",
    "sg:address":"Calle de San Vicente Martir, 50",
    "sg:city":"Valencia",
    "sg:orig_category":"Relojer\u00cda (al Por Menor, Reparaci\u00d3n)",
    "sg:phone":"+34 963 52 56 09",
    "sg:postcode":"46002",
    "sg:province":"Valencia",
    "wof:name":"Sanchez Montesinos Maria Veronica",
    "wof:placetype":"venue"
},
  "geometry": {"coordinates":[-0.3783529997,39.4704399109],"type":"Point"}
}