{
  "type": "Feature",
  "properties": {
    "iso:country":"ES",
    "sg:address":"Plaz Corredera (de La), S/n",
    "sg:city":"Cordoba",
    "sg:orig_category":"Congelados: Productos Alimentarios (al Por Menor)",
    "sg:phone":"+34 957 47 18 48",
    "sg:postcode":"14002",
    "sg:province":"C\u00f3rdoba",
    "wof:name":"Valero Garcia Manuel",
    "wof:placetype":"venue"
},
  "geometry": {"coordinates":[-4.7750291824,37.8835906982],"type":"Point"}
}