{
  "type": "Feature",
  "properties": {
    "addr:full":"Ctra. B-granada, 112 Llerena Badajoz 06900",
    "addr:housenumber":"112",
    "addr:postcode":"06900",
    "addr:street":"Ctra. B-Granada",
    "iso:country":"ES",
    "sg:address":"Ctra. B-granada, 112",
    "sg:city":"Llerena",
    "sg:orig_category":"Mataderos Y Talleres De Despiezado",
    "sg:phone":"+34 924 87 38 37",
    "sg:postcode":"06900",
    "sg:province":"Badajoz",
    "wof:name":"Jamon Y Salud S.a.",
    "wof:placetype":"venue"
},
  "geometry": {"coordinates":[-6.0153741837,38.2413711548],"type":"Point"}
}