{
  "type": "Feature",
  "properties": {
    "addr:full":"Calle de Rafaela, 27 Malaga M\u00e1laga 29009",
    "addr:housenumber":"27",
    "addr:postcode":"29009",
    "addr:street":"Calle De Rafaela;Ma\u0301Laga",
    "iso:country":"ES",
    "sg:address":"Calle de Rafaela, 27",
    "sg:city":"Malaga",
    "sg:orig_category":"Asociaciones, Organismos Culturales Y Socioeducativos",
    "sg:phone":"+34 952 27 00 25",
    "sg:postcode":"29009",
    "sg:province":"M\u00e1laga",
    "wof:name":"Pe\u00f1a El Parral",
    "wof:placetype":"venue"
},
  "geometry": {"coordinates":[-4.4346461296,36.7241439819],"type":"Point"}
}