{
  "type": "Feature",
  "properties": {
    "iso:country":"ES",
    "sg:address":"Calle de San Jose, 7",
    "sg:city":"Alcorcon",
    "sg:orig_category":"Librer\u00cdas",
    "sg:phone":"+34 916 42 56 41",
    "sg:postcode":"28921",
    "sg:province":"Madrid",
    "wof:name":"Navarro Lanzadera Pilar",
    "wof:placetype":"venue"
},
  "geometry": {"coordinates":[-3.8247220516,40.3506126404],"type":"Point"}
}