{
  "type": "Feature",
  "properties": {
    "addr:full":"Calle de Lope De Vega, 7 Santander Cantabria 39003",
    "addr:housenumber":"7",
    "addr:postcode":"39003",
    "addr:street":"Calle De Lope De Vega",
    "iso:country":"ES",
    "sg:address":"Calle de Lope De Vega, 7",
    "sg:city":"Santander",
    "sg:orig_category":"Farmacias",
    "sg:phone":"+34 942 21 59 60",
    "sg:postcode":"39003",
    "sg:province":"Cantabria",
    "wof:name":"Palacios Esteban Gloria",
    "wof:placetype":"venue"
},
  "geometry": {"coordinates":[-3.7996881008,43.4627494812],"type":"Point"}
}