{
  "type": "Feature",
  "properties": {
    "addr:full":"Av Amadeus Mozart, 130 Tarragona Tarragona 43007",
    "addr:housenumber":"130",
    "addr:postcode":"43007",
    "addr:street":"Av Amadeus Mozart",
    "iso:country":"ES",
    "sg:address":"Av Amadeus Mozart, 130",
    "sg:city":"Tarragona",
    "sg:orig_category":"Delegados, Agentes De Tr\u00c1nsito, Auxiliares De Transporte Internacional",
    "sg:phone":"+34 977 29 24 20",
    "sg:postcode":"43007",
    "sg:province":"Tarragona",
    "sg:website":"www.telerepartos.com",
    "wof:name":"Alier Cortes Ramon",
    "wof:placetype":"venue"
},
  "geometry": {"coordinates":[1.2637747526,41.1224517822],"type":"Point"}
}