{
  "type": "Feature",
  "properties": {
    "iso:country":"ES",
    "sg:address":"Calle de Yanguas Messias, 8",
    "sg:city":"Linares",
    "sg:orig_category":"Internados & Ense\u00d1anza Privada",
    "sg:phone":"+34 953 60 71 14",
    "sg:postcode":"23700",
    "sg:province":"Ja\u00e9n",
    "wof:name":"Sociedad Cooperativa De Ense\u00f1anza Colegio San Joaquin",
    "wof:placetype":"venue"
},
  "geometry": {"coordinates":[-3.6331880093,38.0938987732],"type":"Point"}
}