{
  "type": "Feature",
  "properties": {
    "addr:full":"Pase Virgen De Linarejos, 2 Linares Ja\u00e9n 23700",
    "addr:housenumber":"2",
    "addr:postcode":"23700",
    "addr:street":"Jae\u0301N",
    "iso:country":"ES",
    "sg:address":"Pase Virgen De Linarejos, 2",
    "sg:city":"Linares",
    "sg:orig_category":"Promotores Constructores",
    "sg:phone":"+34 953 69 54 02",
    "sg:postcode":"23700",
    "sg:province":"Ja\u00e9n",
    "wof:name":"Audogo S.l.",
    "wof:placetype":"venue"
},
  "geometry": {"coordinates":[-3.6420478821,38.1125907898],"type":"Point"}
}