{
  "type": "Feature",
  "properties": {
    "addr:full":"Calle de Juan Mambrilla, 7 Valladolid Valladolid 47003",
    "addr:housenumber":"7",
    "addr:postcode":"47003",
    "addr:street":"Calle De Juan Mambrilla",
    "iso:country":"ES",
    "sg:address":"Calle de Juan Mambrilla, 7",
    "sg:city":"Valladolid",
    "sg:orig_category":"M\u00c9dicos: Psiquiatr\u00cda",
    "sg:phone":"+34 983 29 84 87",
    "sg:postcode":"47003",
    "sg:province":"Valladolid",
    "wof:name":"Minguez Rodriguez Mariano",
    "wof:placetype":"venue"
},
  "geometry": {"coordinates":[-4.7208538055,41.6539154053],"type":"Point"}
}