{
  "type": "Feature",
  "properties": {
    "iso:country":"ES",
    "sg:address":"Calle de Coru\u00d1a (la), 82",
    "sg:city":"Zaragoza",
    "sg:orig_category":"M\u00c1rmoles, Granitos Y Piedras Naturales",
    "sg:phone":"+34 976 27 12 63",
    "sg:postcode":"50007",
    "sg:province":"Zaragoza",
    "wof:name":"Salas Berdala Maria Del Mar",
    "wof:placetype":"venue"
},
  "geometry": {"coordinates":[-0.8811883926,41.6272888184],"type":"Point"}
}