{
  "type": "Feature",
  "properties": {
    "iso:country":"ES",
    "sg:address":"Carrer de Bac De Roda, 64",
    "sg:city":"Barcelona",
    "sg:orig_category":"Promotores Constructores",
    "sg:phone":"+34 932 07 76 13",
    "sg:postcode":"08019",
    "sg:province":"Barcelona",
    "wof:name":"Constructora San Jose S.a.",
    "wof:placetype":"venue"
},
  "geometry": {"coordinates":[2.2073609829,41.405128479],"type":"Point"}
}