{
  "type": "Feature",
  "properties": {
    "iso:country":"ES",
    "sg:address":"Avda Prensa (la), 25",
    "sg:city":"Sevilla",
    "sg:orig_category":"Goma: Productos De Uso Industrial (fabricaci\u00d3n, Al Por Mayor)",
    "sg:phone":"+34 954 25 71 76",
    "sg:postcode":"41007",
    "sg:province":"Sevilla",
    "wof:name":"Agro-gomas S.l.",
    "wof:placetype":"venue"
},
  "geometry": {"coordinates":[-5.9521150589,37.3896713257],"type":"Point"}
}