{
  "type": "Feature",
  "properties": {
    "addr:full":"Calle de Parra, 7 Valencia Valencia 46015",
    "addr:housenumber":"7",
    "addr:postcode":"46015",
    "addr:street":"Calle De Parra",
    "iso:country":"ES",
    "sg:address":"Calle de Parra, 7",
    "sg:city":"Valencia",
    "sg:orig_category":"\u00d3ptica: Instrumentos (fabricaci\u00d3n)",
    "sg:phone":"+34 963 40 15 01",
    "sg:postcode":"46015",
    "sg:province":"Valencia",
    "wof:name":"Opvin S.l.",
    "wof:placetype":"venue"
},
  "geometry": {"coordinates":[-0.3967519999,39.4832572937],"type":"Point"}
}