{
  "type": "Feature",
  "properties": {
    "iso:country":"ES",
    "sg:address":"Pl Regomir, 4",
    "sg:city":"Barcelona",
    "sg:orig_category":"Molduras, Junquillos, Listones Y Molduras Perforadas",
    "sg:phone":"+34 933 02 48 40",
    "sg:postcode":"08002",
    "sg:province":"Barcelona",
    "wof:name":"Valderas Cabrera Santiago",
    "wof:placetype":"venue"
},
  "geometry": {"coordinates":[2.1787190437,41.3815612793],"type":"Point"}
}