{
  "type": "Feature",
  "properties": {
    "addr:full":"Avda De Niebla, 86 Bonares Huelva 21830",
    "addr:housenumber":"86",
    "addr:postcode":"21830",
    "addr:street":"Avda De Niebla",
    "iso:country":"ES",
    "sg:address":"Avda De Niebla, 86",
    "sg:city":"Bonares",
    "sg:orig_category":"Chapister\u00cda",
    "sg:phone":"+34 959 36 61 77",
    "sg:postcode":"21830",
    "sg:province":"Huelva",
    "wof:name":"Talleres Martin Ponce S.l.",
    "wof:placetype":"venue"
},
  "geometry": {"coordinates":[-6.6785230637,37.3265342712],"type":"Point"}
}