{
  "type": "Feature",
  "properties": {
    "addr:full":"Calle de Gloria (la), 2 Roquetas Mar Almer\u00eda 04740",
    "addr:housenumber":"2",
    "addr:postcode":"04740",
    "addr:street":"Calle De Gloria La",
    "iso:country":"ES",
    "sg:address":"Calle de Gloria (la), 2",
    "sg:city":"Roquetas Mar",
    "sg:orig_category":"Peluquer\u00cdas, Peluquer\u00cda Mixta",
    "sg:phone":"+34 950 32 14 84",
    "sg:postcode":"04740",
    "sg:province":"Almer\u00eda",
    "wof:name":"Gallardo Rodriguez Rosalia",
    "wof:placetype":"venue"
},
  "geometry": {"coordinates":[-2.6085762978,36.7583351135],"type":"Point"}
}