{
  "type": "Feature",
  "properties": {
    "addr:full":"Avda Gran Via Tarrega Monteblanco, 254 Castellon Castell\u00f3n 12006",
    "addr:housenumber":"254",
    "addr:postcode":"12006",
    "addr:street":"Avda Gran Via Tarrega Monteblanco;Castello\u0301N",
    "iso:country":"ES",
    "sg:address":"Avda Gran Via Tarrega Monteblanco, 254",
    "sg:city":"Castellon",
    "sg:orig_category":"Electricidad: Instaladores",
    "sg:phone":"+34 964 20 97 83",
    "sg:postcode":"12006",
    "sg:province":"Castell\u00f3n",
    "wof:name":"Electricidad Ricmon S.l.",
    "wof:placetype":"venue"
},
  "geometry": {"coordinates":[-0.1292939931,40.0168533325],"type":"Point"}
}