{
  "type": "Feature",
  "properties": {
    "iso:country":"ES",
    "sg:address":"Calle de Argensola, 4",
    "sg:city":"Madrid",
    "sg:orig_category":"Colchones (fabricaci\u00d3n, Al Por Mayor, Al Por Menor)",
    "sg:phone":"+34 913 19 21 19",
    "sg:postcode":"28004",
    "sg:province":"Madrid",
    "sg:website":"www.futon.es",
    "wof:name":"Futon Nature Company S.l.",
    "wof:placetype":"venue"
},
  "geometry": {"coordinates":[-3.6952650547,40.4247779846],"type":"Point"}
}