{
  "type": "Feature",
  "properties": {
    "addr:full":"Calle de San Roque, S/n Valdelosa Salamanca 37799",
    "addr:housenumber":"s",
    "addr:postcode":"37799",
    "addr:street":"Calle De San Roque;/ N",
    "iso:country":"ES",
    "sg:address":"Calle de San Roque, S/n",
    "sg:city":"Valdelosa",
    "sg:orig_category":"Cr\u00cda De Animales",
    "sg:phone":"+34 923 31 42 83",
    "sg:postcode":"37799",
    "sg:province":"Salamanca",
    "wof:name":"Casaseca Ramos Antonio",
    "wof:placetype":"venue"
},
  "geometry": {"coordinates":[-5.7833337784,41.1729164124],"type":"Point"}
}