{
  "type": "Feature",
  "properties": {
    "addr:full":"Calle de Agricultura, 1 Novales Huesca 22113",
    "addr:housenumber":"1",
    "addr:postcode":"22113",
    "addr:street":"Calle De Agricultura",
    "iso:country":"ES",
    "sg:address":"Calle de Agricultura, 1",
    "sg:city":"Novales",
    "sg:orig_category":"Electricidad: Instaladores",
    "sg:phone":"+34 974 28 03 51",
    "sg:postcode":"22113",
    "sg:province":"Huesca",
    "wof:name":"Ferrer Lera Jose Luis",
    "wof:placetype":"venue"
},
  "geometry": {"coordinates":[-0.2713944018,42.0283699036],"type":"Point"}
}