{
  "type": "Feature",
  "properties": {
    "iso:country":"ES",
    "sg:address":"Calle de Cuenca, 48",
    "sg:city":"Tui",
    "sg:orig_category":"Procuradores",
    "sg:phone":"+34 986 60 17 22",
    "sg:postcode":"36700",
    "sg:province":"Pontevedra",
    "wof:name":"Casti\u00f1eira Gonzalez Xose Carlos",
    "wof:placetype":"venue"
},
  "geometry": {"coordinates":[-8.6432342529,42.0455207825],"type":"Point"}
}