{
  "type": "Feature",
  "properties": {
    "iso:country":"ES",
    "sg:address":"Calle de Paraguay, S/n",
    "sg:city":"Alcantarilla",
    "sg:orig_category":"Metalurgia",
    "sg:phone":"+34 968 89 21 57",
    "sg:postcode":"30820",
    "sg:province":"Murcia",
    "wof:name":"Lopez Garcia Miguel Angel",
    "wof:placetype":"venue"
},
  "geometry": {"coordinates":[-1.197584033,37.9587364197],"type":"Point"}
}