{
  "type": "Feature",
  "properties": {
    "addr:full":"Av Catalunya, 26 S. Feliu Guixols Girona 17220",
    "addr:housenumber":"26",
    "addr:postcode":"17220",
    "addr:street":"Av Catalunya;S. Feliu Guixols",
    "iso:country":"ES",
    "sg:address":"Av Catalunya, 26",
    "sg:city":"S. Feliu Guixols",
    "sg:orig_category":"Mercer\u00cda, Lencer\u00cda (al Por Menor)",
    "sg:phone":"+34 972 82 06 84",
    "sg:postcode":"17220",
    "sg:province":"Girona",
    "wof:name":"Arnau Genesca Rosa Maria",
    "wof:placetype":"venue"
},
  "geometry": {"coordinates":[3.0244896412,41.7897262573],"type":"Point"}
}