{
  "type": "Feature",
  "properties": {
    "addr:full":"Plaz Emigrante, S/n Navalvillar Pela Badajoz 06760",
    "addr:housenumber":"s / n",
    "addr:postcode":"06760",
    "iso:country":"ES",
    "sg:address":"Plaz Emigrante, S/n",
    "sg:city":"Navalvillar Pela",
    "sg:orig_category":"Cajas Para Embalar",
    "sg:phone":"+34 924 86 13 00",
    "sg:postcode":"06760",
    "sg:province":"Badajoz",
    "wof:name":"Caja Rural De Extremadura",
    "wof:placetype":"venue"
},
  "geometry": {"coordinates":[-5.4656438828,39.0907363892],"type":"Point"}
}