{
  "type": "Feature",
  "properties": {
    "addr:full":"Ctra. Valencia-alicante, Km. 0246,0 Cullera Valencia 46400",
    "addr:postcode":"46400",
    "addr:street":"Ctra. Valencia-Alicante Km. 0246,0",
    "iso:country":"ES",
    "sg:address":"Ctra. Valencia-alicante, Km. 0246,0",
    "sg:city":"Cullera",
    "sg:orig_category":"Distribuci\u00d3n De Petr\u00d3leo Y Derivados",
    "sg:phone":"+34 961 73 05 16",
    "sg:postcode":"46400",
    "sg:province":"Valencia",
    "wof:name":"Galpgest Petrogal Estaciones De Servicio S.l.u.",
    "wof:placetype":"venue"
},
  "geometry": {"coordinates":[-0.2562240064,39.1653251648],"type":"Point"}
}