{
  "type": "Feature",
  "properties": {
    "addr:full":"Calle de Alamo, El, 6 Valencia Valencia 46025",
    "addr:housenumber":"6",
    "addr:postcode":"46025",
    "addr:street":"Calle De Alamo El",
    "iso:country":"ES",
    "sg:address":"Calle de Alamo, El, 6",
    "sg:city":"Valencia",
    "sg:orig_category":"Plomeros",
    "sg:phone":"+34 963 45 92 17",
    "sg:postcode":"46025",
    "sg:province":"Valencia",
    "wof:name":"Santiago Lopez Manzaneda S.l.",
    "wof:placetype":"venue"
},
  "geometry": {"coordinates":[-0.3903059959,39.4925384521],"type":"Point"}
}