{
  "type": "Feature",
  "properties": {
    "addr:full":"Pase Salamanca, 45 Le\u00f3n Le\u00f3n 24010",
    "addr:housenumber":"45",
    "addr:postcode":"24010",
    "addr:street":"Salamanca;Leo\u0301N",
    "iso:country":"ES",
    "sg:address":"Pase Salamanca, 45",
    "sg:city":"Le\u00f3n",
    "sg:orig_category":"Venta, Montaje De Neum\u00c1ticos",
    "sg:phone":"+34 987 87 52 62",
    "sg:postcode":"24010",
    "sg:province":"Le\u00f3n",
    "wof:name":"Neumaticos Suarez S.l.",
    "wof:placetype":"venue"
},
  "geometry": {"coordinates":[-5.5861229897,42.6035385132],"type":"Point"}
}