{
  "type": "Feature",
  "properties": {
    "iso:country":"ES",
    "sg:address":"Calle de Medico Sorapan, 1",
    "sg:city":"Caceres",
    "sg:orig_category":"Fabricaci\u00d3n De Acumuladores Y De Pilas El\u00c9ctricas",
    "sg:phone":"+34 927 22 15 27",
    "sg:postcode":"10002",
    "sg:province":"C\u00e1ceres",
    "wof:name":"Jmr Ingenieria Y Montajes S.l.",
    "wof:placetype":"venue"
},
  "geometry": {"coordinates":[-6.3732681274,39.4679832458],"type":"Point"}
}