{
  "type": "Feature",
  "properties": {
    "iso:country":"ES",
    "sg:address":"Rua Lamas Carvajal, 8",
    "sg:city":"Barco",
    "sg:orig_category":"Reposter\u00cdas",
    "sg:phone":"+34 988 32 02 59",
    "sg:postcode":"32300",
    "sg:province":"Ourense",
    "wof:name":"Nuevo Arias Faustino",
    "wof:placetype":"venue"
},
  "geometry": {"coordinates":[-6.9818887711,42.4165420532],"type":"Point"}
}