{
  "type": "Feature",
  "properties": {
    "addr:full":"Carrer de Felip Ii, 158 Barcelona Barcelona 08027",
    "addr:housenumber":"158",
    "addr:postcode":"08027",
    "addr:street":"Carrer De Felip Ii",
    "iso:country":"ES",
    "sg:address":"Carrer de Felip Ii, 158",
    "sg:city":"Barcelona",
    "sg:orig_category":"Droguer\u00cdas (al Por Menor)",
    "sg:phone":"+34 933 52 48 01",
    "sg:postcode":"08027",
    "sg:province":"Barcelona",
    "wof:name":"Serrano Gonzalez Francisco",
    "wof:placetype":"venue"
},
  "geometry": {"coordinates":[2.1821250916,41.4242019653],"type":"Point"}
}