{
  "type": "Feature",
  "properties": {
    "addr:full":"Calle de San Francisco, 59 Valverde Santa Cruz De Tenerife 38910",
    "addr:housenumber":"59",
    "addr:postcode":"38910",
    "addr:street":"Calle De San Francisco",
    "iso:country":"ES",
    "sg:address":"Calle de San Francisco, 59",
    "sg:city":"Valverde",
    "sg:orig_category":"Organismos De Turismo",
    "sg:phone":"+34 922 55 18 40",
    "sg:postcode":"38910",
    "sg:province":"Santa Cruz De Tenerife",
    "sg:website":"www.lasanjora.com",
    "wof:name":"Leon Quintero Maria Aranzazu",
    "wof:placetype":"venue"
},
  "geometry": {"coordinates":[-17.8970718384,27.8238143921],"type":"Point"}
}