{
  "type": "Feature",
  "properties": {
    "addr:full":"Carrer de Torrent De L'olla, 81 Barcelona Barcelona 08012",
    "addr:housenumber":"81",
    "addr:postcode":"08012",
    "addr:street":"Carrer De Torrent De L'Olla",
    "iso:country":"ES",
    "sg:address":"Carrer de Torrent De L'olla, 81",
    "sg:city":"Barcelona",
    "sg:orig_category":"Panader\u00cdas, Panader\u00cdas",
    "sg:phone":"+34 932 18 47 43",
    "sg:postcode":"08012",
    "sg:province":"Barcelona",
    "wof:name":"Torremade Roig Martin",
    "wof:placetype":"venue"
},
  "geometry": {"coordinates":[2.1580667496,41.4014396667],"type":"Point"}
}