{
  "type": "Feature",
  "properties": {
    "iso:country":"ES",
    "sg:address":"Telleria, 4",
    "sg:city":"Arrasate Edo Mondragon",
    "sg:orig_category":"Electromec\u00c1nica",
    "sg:phone":"+34 943 79 13 34",
    "sg:postcode":"20500",
    "sg:province":"Guip\u00f9zcoa",
    "wof:name":"Rj Utiles Electromecanicos S.l.",
    "wof:placetype":"venue"
},
  "geometry": {"coordinates":[-2.4945991039,43.060295105],"type":"Point"}
}