{
  "type": "Feature",
  "properties": {
    "addr:full":"Calle de Regino Martinez, 23 Algeciras C\u00e1diz 11201",
    "addr:housenumber":"23;ca\u0301diz",
    "addr:postcode":"11201",
    "addr:street":"Calle De Regino Martinez",
    "iso:country":"ES",
    "sg:address":"Calle de Regino Martinez, 23",
    "sg:city":"Algeciras",
    "sg:orig_category":"Fabricaci\u00d3n, Venta De Productos Base Farmac\u00c9uticos",
    "sg:phone":"+34 956 66 15 56",
    "sg:postcode":"11201",
    "sg:province":"C\u00e1diz",
    "wof:name":"Corrales Garcia Eduardo",
    "wof:placetype":"venue"
},
  "geometry": {"coordinates":[-5.4484949112,36.1319885254],"type":"Point"}
}