{
  "type": "Feature",
  "properties": {
    "addr:full":"Transversal Del Monte, 9 Megeces Valladolid 47440",
    "addr:housenumber":"9",
    "addr:postcode":"47440",
    "addr:street":"Transversal Del Monte",
    "iso:country":"ES",
    "sg:address":"Transversal Del Monte, 9",
    "sg:city":"Megeces",
    "sg:orig_category":"Chapister\u00cda",
    "sg:phone":"+34 983 60 42 25",
    "sg:postcode":"47440",
    "sg:province":"Valladolid",
    "wof:name":"Manso Gonzalez David",
    "wof:placetype":"venue"
},
  "geometry": {"coordinates":[-4.5637259483,41.4070014954],"type":"Point"}
}