{
  "type": "Feature",
  "properties": {
    "addr:full":"Calle de San Miguel, 23 Catarroja Valencia 46470",
    "addr:housenumber":"23",
    "addr:postcode":"46470",
    "addr:street":"Calle De San Miguel",
    "iso:country":"ES",
    "sg:address":"Calle de San Miguel, 23",
    "sg:city":"Catarroja",
    "sg:orig_category":"Compresores",
    "sg:phone":"+34 961 26 75 93",
    "sg:postcode":"46470",
    "sg:province":"Valencia",
    "wof:name":"Extintores Comercial Garcia S.l.",
    "wof:placetype":"venue"
},
  "geometry": {"coordinates":[-0.4025090039,39.3984718323],"type":"Point"}
}