{
  "type": "Feature",
  "properties": {
    "iso:country":"ES",
    "sg:address":"Calle de Veinte De Noviembre, 48",
    "sg:city":"Carrion Calatrava",
    "sg:orig_category":"Empresas De Carpinter\u00cda",
    "sg:phone":"+34 926 81 43 34",
    "sg:postcode":"13150",
    "sg:province":"Ciudad Real",
    "wof:name":"Carpinteria-ebanisteria Marvi C.b",
    "wof:placetype":"venue"
},
  "geometry": {"coordinates":[-3.814743042,39.0208091736],"type":"Point"}
}