{
  "type": "Feature",
  "properties": {
    "addr:full":"Calle de Maestro Palau, 8 Mislata Valencia 46920",
    "addr:housenumber":"8",
    "addr:postcode":"46920",
    "addr:street":"Calle De Maestro Palau",
    "iso:country":"ES",
    "sg:address":"Calle de Maestro Palau, 8",
    "sg:city":"Mislata",
    "sg:orig_category":"Electricidad Veh\u00cdculo",
    "sg:phone":"+34 963 59 07 59",
    "sg:postcode":"46920",
    "sg:province":"Valencia",
    "wof:name":"Soto Montoro Juan Maria",
    "wof:placetype":"venue"
},
  "geometry": {"coordinates":[-0.4206767082,39.4729728699],"type":"Point"}
}