{
  "type": "Feature",
  "properties": {
    "addr:full":"Avda Vidrio (del), 18 Azuqueca Henares Guadalajara 19200",
    "addr:housenumber":"18",
    "addr:postcode":"19200",
    "addr:street":"Avda Vidrio Del",
    "iso:country":"ES",
    "sg:address":"Avda Vidrio (del), 18",
    "sg:city":"Azuqueca Henares",
    "sg:orig_category":"Transportes Urbanos Y Regionales Para Personas",
    "sg:phone":"+34 949 26 78 10",
    "sg:postcode":"19200",
    "sg:province":"Guadalajara",
    "wof:name":"Mai Tours S. L.",
    "wof:placetype":"venue"
},
  "geometry": {"coordinates":[-3.2621030807,40.5603904724],"type":"Point"}
}