{
  "type": "Feature",
  "properties": {
    "iso:country":"ES",
    "sg:address":"Urb. Alcor, 115",
    "sg:city":"Mazagon",
    "sg:orig_category":"Centros Empresariales",
    "sg:phone":"+34 959 37 72 60",
    "sg:postcode":"21130",
    "sg:province":"Huelva",
    "wof:name":"Sanchez Vazquez Pedro",
    "wof:placetype":"venue"
},
  "geometry": {"coordinates":[-6.8279538155,37.1366615295],"type":"Point"}
}