{
  "type": "Feature",
  "properties": {
    "iso:country":"ES",
    "sg:address":"Tamon, 1",
    "sg:city":"Tamon",
    "sg:orig_category":"Comercio De Hierro",
    "sg:phone":"+34 985 57 89 03",
    "sg:postcode":"33469",
    "sg:province":"Asturias",
    "wof:name":"Hierros De Tamon S. A.",
    "wof:placetype":"venue"
},
  "geometry": {"coordinates":[-5.8119959831,43.5127182007],"type":"Point"}
}