{
  "type": "Feature",
  "properties": {
    "iso:country":"ES",
    "sg:address":"Calle de San Esteban, 9",
    "sg:city":"Guadalajara",
    "sg:orig_category":"Abogados",
    "sg:phone":"+34 949 21 26 60",
    "sg:postcode":"19001",
    "sg:province":"Guadalajara",
    "wof:name":"Muelas Mazario Maria Teresa",
    "wof:placetype":"venue"
},
  "geometry": {"coordinates":[-3.1640090942,40.6337471008],"type":"Point"}
}