{
  "type": "Feature",
  "properties": {
    "iso:country":"ES",
    "sg:address":"Fragoso, 5",
    "sg:city":"Vinseiro",
    "sg:orig_category":"Materias Pl\u00c1sticas: Productos De Consumo Masivo (fabricaci\u00d3n, Al Por Mayor)",
    "sg:phone":"+34 986 57 38 54",
    "sg:postcode":"36687",
    "sg:province":"Pontevedra",
    "wof:name":"Jose Carracedo S.l.",
    "wof:placetype":"venue"
},
  "geometry": {"coordinates":[-8.4347791672,42.6690101624],"type":"Point"}
}