{
  "type": "Feature",
  "properties": {
    "iso:country":"ES",
    "sg:address":"Ctra Zaragoza, Km. 0053,7",
    "sg:city":"Calahorra",
    "sg:orig_category":"Distribuci\u00d3n De Petr\u00d3leo Y Derivados",
    "sg:phone":"+34 941 14 63 46",
    "sg:postcode":"26500",
    "sg:province":"La Rioja",
    "wof:name":"Area De Servicio De Calahorra S.a.",
    "wof:placetype":"venue"
},
  "geometry": {"coordinates":[-1.9538147449,42.2948112488],"type":"Point"}
}