{
  "type": "Feature",
  "properties": {
    "addr:full":"Plaz Cortes Espa\u00d1olas, 3 Cieza Murcia 30530",
    "addr:housenumber":"3",
    "addr:postcode":"30530",
    "addr:street":"Plaz;Espan\u0303Olas",
    "iso:country":"ES",
    "sg:address":"Plaz Cortes Espa\u00d1olas, 3",
    "sg:city":"Cieza",
    "sg:orig_category":"Bancos",
    "sg:phone":"+34 968 76 15 12",
    "sg:postcode":"30530",
    "sg:province":"Murcia",
    "wof:name":"Banco Popular Espa\u00f1ol S.a.",
    "wof:placetype":"venue"
},
  "geometry": {"coordinates":[-1.4187070131,38.2392654419],"type":"Point"}
}