{
  "type": "Feature",
  "properties": {
    "addr:full":"Carrer de Rocafort, 60 Sabadell Barcelona 08205",
    "addr:housenumber":"60",
    "addr:postcode":"08205",
    "addr:street":"Carrer De Rocafort",
    "iso:country":"ES",
    "sg:address":"Carrer de Rocafort, 60",
    "sg:city":"Sabadell",
    "sg:orig_category":"Fabricaci\u00d3n De Productos L\u00c1cteos Y Derivados",
    "sg:phone":"+34 937 12 21 14",
    "sg:postcode":"08205",
    "sg:province":"Barcelona",
    "wof:name":"Parmalat S.a.",
    "wof:placetype":"venue"
},
  "geometry": {"coordinates":[2.0982899666,41.5359764099],"type":"Point"}
}