{
  "type": "Feature",
  "properties": {
    "addr:full":"Calle de Campelo, 29 Umbrete Sevilla 41806",
    "addr:housenumber":"29",
    "addr:postcode":"41806",
    "addr:street":"Calle De Campelo",
    "iso:country":"ES",
    "sg:address":"Calle de Campelo, 29",
    "sg:city":"Umbrete",
    "sg:orig_category":"Agricultores, Agricultores",
    "sg:phone":"+34 955 71 54 89",
    "sg:postcode":"41806",
    "sg:province":"Sevilla",
    "wof:name":"Explotaciones Agricolas El Noventa Y Uno S.l.",
    "wof:placetype":"venue"
},
  "geometry": {"coordinates":[-6.1597943306,37.3700752258],"type":"Point"}
}