{
  "type": "Feature",
  "properties": {
    "addr:full":"Calle de Juan Alvargonzalez, 51 Gijon Asturias 33208",
    "addr:housenumber":"51",
    "addr:postcode":"33208",
    "addr:street":"Calle De Juan Alvargonzalez",
    "iso:country":"ES",
    "sg:address":"Calle de Juan Alvargonzalez, 51",
    "sg:city":"Gijon",
    "sg:orig_category":"Comercio De Piezas De Recambio Y De Accesorios De Veh\u00cdculos, Veh\u00cdculos Industriales",
    "sg:phone":"+34 985 39 86 11",
    "sg:postcode":"33208",
    "sg:province":"Asturias",
    "wof:name":"Recambios Asturias S.l.",
    "wof:placetype":"venue"
},
  "geometry": {"coordinates":[-5.6670761108,43.5301704407],"type":"Point"}
}