{
  "type": "Feature",
  "properties": {
    "addr:full":"Calle de Pintor Fernando Fenoll, 6 Orihuela Alicante 03300",
    "addr:housenumber":"6",
    "addr:postcode":"03300",
    "addr:street":"Calle De Pintor Fernando Fenoll",
    "iso:country":"ES",
    "sg:address":"Calle de Pintor Fernando Fenoll, 6",
    "sg:city":"Orihuela",
    "sg:orig_category":"Agencias Y Asesores De Publicidad",
    "sg:phone":"+34 966 74 09 76",
    "sg:postcode":"03300",
    "sg:province":"Alicante",
    "wof:name":"Onda-0 Productora De Publicidad S. L.",
    "wof:placetype":"venue"
},
  "geometry": {"coordinates":[-0.9485020041,38.0790557861],"type":"Point"}
}