{
  "type": "Feature",
  "properties": {
    "addr:full":"Gral. Franco, 19 Gomara Soria 42120",
    "addr:housenumber":"19",
    "addr:postcode":"42120",
    "addr:street":"Gral. Franco",
    "iso:country":"ES",
    "sg:address":"Gral. Franco, 19",
    "sg:city":"Gomara",
    "sg:orig_category":"Maquinaria Para Industrias Diversas",
    "sg:phone":"+34 975 38 00 10",
    "sg:postcode":"42120",
    "sg:province":"Soria",
    "wof:name":"Martinez Lafuente Jesus",
    "wof:placetype":"venue"
},
  "geometry": {"coordinates":[-2.2247591019,41.6239356995],"type":"Point"}
}