{
  "type": "Feature",
  "properties": {
    "addr:full":"Calle de Avila, 20 Burgohondo \u00c1vila 05113",
    "addr:housenumber":"20",
    "addr:postcode":"05113",
    "addr:street":"Calle De Avila;A\u0301Vila",
    "iso:country":"ES",
    "sg:address":"Calle de Avila, 20",
    "sg:city":"Burgohondo",
    "sg:orig_category":"Administradores De Bienes Y Delegados De Comunidades De Propietarios",
    "sg:phone":"+34 920 28 44 04",
    "sg:postcode":"05113",
    "sg:province":"\u00c1vila",
    "wof:name":"Morales Ruiz Jose Luis",
    "wof:placetype":"venue"
},
  "geometry": {"coordinates":[-4.7868466377,40.4143333435],"type":"Point"}
}