{
  "type": "Feature",
  "properties": {
    "iso:country":"ES",
    "sg:address":"Castellon, 12",
    "sg:city":"Finestrat",
    "sg:orig_category":"Agencias Y Agentes Comerciales, Representantes",
    "sg:phone":"+34 965 85 37 16",
    "sg:postcode":"03509",
    "sg:province":"Alicante",
    "wof:name":"Valero Gomez Francisco",
    "wof:placetype":"venue"
},
  "geometry": {"coordinates":[-0.2110220045,38.5676612854],"type":"Point"}
}