{
  "type": "Feature",
  "properties": {
    "addr:full":"Calle de Gerona, 13 Benidorm Alicante 03500",
    "addr:housenumber":"13",
    "addr:postcode":"03500",
    "addr:street":"Calle De Gerona",
    "iso:country":"ES",
    "sg:address":"Calle de Gerona, 13",
    "sg:city":"Benidorm",
    "sg:orig_category":"Art\u00cdculos De Regalo (al Por Menor)",
    "sg:phone":"+34 965 86 54 61",
    "sg:postcode":"03500",
    "sg:province":"Alicante",
    "wof:name":"Van Beek Garcia Esperanza",
    "wof:placetype":"venue"
},
  "geometry": {"coordinates":[-0.1160816997,38.5373306274],"type":"Point"}
}