{
  "type": "Feature",
  "properties": {
    "iso:country":"ES",
    "sg:address":"Calle de Conde Duque, 12",
    "sg:city":"Madrid",
    "sg:orig_category":"Alimentaci\u00d3n General (al Por Menor)",
    "sg:phone":"+34 915 47 31 87",
    "sg:postcode":"28015",
    "sg:province":"Madrid",
    "wof:name":"Asenjo Provencio Primitivo",
    "wof:placetype":"venue"
},
  "geometry": {"coordinates":[-3.7112021446,40.4262924194],"type":"Point"}
}