{
  "type": "Feature",
  "properties": {
    "addr:full":"Moll Llevant, S/n Barcelona Barcelona 08039",
    "addr:housenumber":"s / n",
    "addr:postcode":"08039",
    "addr:street":"Moll Llevant",
    "iso:country":"ES",
    "sg:address":"Moll Llevant, S/n",
    "sg:city":"Barcelona",
    "sg:orig_category":"Electricidad: Instaladores",
    "sg:phone":"+34 932 21 95 15",
    "sg:postcode":"08039",
    "sg:province":"Barcelona",
    "wof:name":"Fm 2 Insta%acions S.a.",
    "wof:placetype":"venue"
},
  "geometry": {"coordinates":[2.1573033333,41.3334465027],"type":"Point"}
}