{
  "type": "Feature",
  "properties": {
    "addr:full":"Carrer de Colon, 149 Olesa Montserrat Barcelona 08640",
    "addr:housenumber":"149",
    "addr:postcode":"08640",
    "addr:street":"Carrer De Colon;Barcelona",
    "iso:country":"ES",
    "sg:address":"Carrer de Colon, 149",
    "sg:city":"Olesa Montserrat",
    "sg:orig_category":"Asilos De Ancianos. Centros Privados",
    "sg:phone":"+34 937 78 38 61",
    "sg:postcode":"08640",
    "sg:province":"Barcelona",
    "wof:name":"Residencia D'avis Nuestra Se\u00f1ora De Montserrat",
    "wof:placetype":"venue"
},
  "geometry": {"coordinates":[1.8907580376,41.542011261],"type":"Point"}
}