{
  "type": "Feature",
  "properties": {
    "addr:full":"Calle de Real De Arriba, 109 Valverde Camino Huelva 21600",
    "addr:housenumber":"109",
    "addr:postcode":"21600",
    "addr:street":"Calle De Real De Arriba;Camino Huelva",
    "iso:country":"ES",
    "sg:address":"Calle de Real De Arriba, 109",
    "sg:city":"Valverde Camino",
    "sg:orig_category":"Venta, Montaje De Neum\u00c1ticos",
    "sg:phone":"+34 959 55 12 33",
    "sg:postcode":"21600",
    "sg:province":"Huelva",
    "wof:name":"Alfaro Lorca Jose Martin",
    "wof:placetype":"venue"
},
  "geometry": {"coordinates":[-6.7520546913,37.577381134],"type":"Point"}
}