{
  "type": "Feature",
  "properties": {
    "addr:full":"Carr Campet, Des, 8 Cala Ratjada Islas Baleares 07590",
    "addr:postcode":"07590",
    "addr:street":"Carr Campet Des 8",
    "iso:country":"ES",
    "sg:address":"Carr Campet, Des, 8",
    "sg:city":"Cala Ratjada",
    "sg:orig_category":"Comercio, Reparaci\u00d3n De Motocicletas, Bicicletas Y Piezas Sueltas",
    "sg:phone":"+34 971 56 52 19",
    "sg:postcode":"07590",
    "sg:province":"Islas Baleares",
    "wof:name":"Sard Flaquer Juan Jose",
    "wof:placetype":"venue"
},
  "geometry": {"coordinates":[3.4606449604,39.7145996094],"type":"Point"}
}