{
  "type": "Feature",
  "properties": {
    "addr:full":"Calle de Fuente, S/n Villanueva Del Campillo \u00c1vila 05591",
    "addr:housenumber":"s",
    "addr:postcode":"05591",
    "addr:street":"Calle De Fuente;/ N",
    "iso:country":"ES",
    "sg:address":"Calle de Fuente, S/n",
    "sg:city":"Villanueva Del Campillo",
    "sg:orig_category":"Transportes Por Carretera: Lotes Completos, Mercanc\u00cdas Diversas",
    "sg:phone":"+34 920 23 53 88",
    "sg:postcode":"05591",
    "sg:province":"\u00c1vila",
    "wof:name":"Sanchez Gomez Francisco Javier",
    "wof:placetype":"venue"
},
  "geometry": {"coordinates":[-5.1795101166,40.5754623413],"type":"Point"}
}