{
  "type": "Feature",
  "properties": {
    "addr:full":"Carr Sagunto, 29 Silla Valencia 46460",
    "addr:housenumber":"29",
    "addr:postcode":"46460",
    "addr:street":"Carr Sagunto",
    "iso:country":"ES",
    "sg:address":"Carr Sagunto, 29",
    "sg:city":"Silla",
    "sg:orig_category":"Complementos De Vestir (al Por Menor)",
    "sg:phone":"+34 961 21 11 75",
    "sg:postcode":"46460",
    "sg:province":"Valencia",
    "wof:name":"Construcciones Vibecons S.l.",
    "wof:placetype":"venue"
},
  "geometry": {"coordinates":[-0.4125399888,39.3581428528],"type":"Point"}
}