{
  "type": "Feature",
  "properties": {
    "iso:country":"ES",
    "sg:address":"Calle de Camarena, 153",
    "sg:city":"Madrid",
    "sg:orig_category":"Bancos",
    "sg:phone":"+34 917 19 41 11",
    "sg:postcode":"28047",
    "sg:province":"Madrid",
    "wof:name":"Banco Popular Espa\u00f1ol S.a.",
    "wof:placetype":"venue"
},
  "geometry": {"coordinates":[-3.7554950714,40.3924713135],"type":"Point"}
}