{
  "type": "Feature",
  "properties": {
    "iso:country":"ES",
    "sg:address":"Ctra. Coru\u00f1a, Km. 0046,4",
    "sg:city":"Guadarrama",
    "sg:orig_category":"Cr\u00cda De Animales",
    "sg:phone":"+34 918 54 00 65",
    "sg:postcode":"28440",
    "sg:province":"Madrid",
    "wof:name":"Agropecuaria La Cumbre S.l.",
    "wof:placetype":"venue"
},
  "geometry": {"coordinates":[-4.0841560364,40.6688690186],"type":"Point"}
}