{
  "type": "Feature",
  "properties": {
    "addr:full":"Calle de Galoponte, 5 Medano Santa Cruz De Tenerife 38612",
    "addr:housenumber":"5",
    "addr:postcode":"38612",
    "addr:street":"Calle De Galoponte",
    "iso:country":"ES",
    "sg:address":"Calle de Galoponte, 5",
    "sg:city":"Medano",
    "sg:orig_category":"Herboristas (al Por Menor)",
    "sg:phone":"+34 922 17 63 62",
    "sg:postcode":"38612",
    "sg:province":"Santa Cruz De Tenerife",
    "wof:name":"Schewe  Kornelia",
    "wof:placetype":"venue"
},
  "geometry": {"coordinates":[-16.5262241364,28.0532035828],"type":"Point"}
}