{
  "type": "Feature",
  "properties": {
    "iso:country":"ES",
    "sg:address":"Calle de Levante, 7",
    "sg:city":"Alcazar S. Juan",
    "sg:orig_category":"Abogados",
    "sg:phone":"+34 926 55 00 96",
    "sg:postcode":"13600",
    "sg:province":"Ciudad Real",
    "wof:name":"Bueno Castillo Carmen",
    "wof:placetype":"venue"
},
  "geometry": {"coordinates":[-3.2120521069,39.3890266418],"type":"Point"}
}