{
  "type": "Feature",
  "properties": {
    "addr:full":"Avda Constitucion, 99 Mazarron Murcia 30870",
    "addr:housenumber":"99",
    "addr:postcode":"30870",
    "addr:street":"Avda Constitucion",
    "iso:country":"ES",
    "sg:address":"Avda Constitucion, 99",
    "sg:city":"Mazarron",
    "sg:orig_category":"Bancos",
    "sg:phone":"+34 968 59 28 11",
    "sg:postcode":"30870",
    "sg:province":"Murcia",
    "wof:name":"Banco Bilbao Vizcaya Argentaria S.a.",
    "wof:placetype":"venue"
},
  "geometry": {"coordinates":[-1.3137489557,37.5989875793],"type":"Point"}
}