{
  "type": "Feature",
  "properties": {
    "addr:full":"Ctra Estacion De La-san Claudio, 21 San Claudio Asturias 33191",
    "addr:housenumber":"21",
    "addr:postcode":"33191",
    "addr:street":"Ctra Estacion De La-San Claudio",
    "iso:country":"ES",
    "sg:address":"Ctra Estacion De La-san Claudio, 21",
    "sg:city":"San Claudio",
    "sg:orig_category":"Prot\u00c9sicos Dentales",
    "sg:phone":"+34 985 78 18 66",
    "sg:postcode":"33191",
    "sg:province":"Asturias",
    "wof:name":"Garcia Alvarez Marcos",
    "wof:placetype":"venue"
},
  "geometry": {"coordinates":[-5.9176192284,43.3596382141],"type":"Point"}
}