{
  "type": "Feature",
  "properties": {
    "iso:country":"ES",
    "sg:address":"Carrer de Font (la), 14",
    "sg:city":"Vilafranca Penedes",
    "sg:orig_category":"Laboratorios Y Trabajos De Fotograf\u00cda, V\u00cddeo Y Cine",
    "sg:phone":"+34 938 92 28 93",
    "sg:postcode":"08720",
    "sg:province":"Barcelona",
    "wof:name":"Paretas Biarnes Jose Maria",
    "wof:placetype":"venue"
},
  "geometry": {"coordinates":[1.699416995,41.3473205566],"type":"Point"}
}