{
  "type": "Feature",
  "properties": {
    "addr:full":"Calle de Vicente Berdusan, 4 Zaragoza Zaragoza 50010",
    "addr:housenumber":"4",
    "addr:postcode":"50010",
    "addr:street":"Calle De Vicente Berdusan",
    "iso:country":"ES",
    "sg:address":"Calle de Vicente Berdusan, 4",
    "sg:city":"Zaragoza",
    "sg:orig_category":"Maquinaria Y Herramientas Para Madera, Pvc, Aluminio Y Aperos (fabricaci\u00d3n, Comercio)",
    "sg:phone":"+34 976 34 31 96",
    "sg:postcode":"50010",
    "sg:province":"Zaragoza",
    "wof:name":"Espinosa Maquinaria S.l.",
    "wof:placetype":"venue"
},
  "geometry": {"coordinates":[-0.8980389833,41.6519393921],"type":"Point"}
}