{
  "type": "Feature",
  "properties": {
    "addr:full":"Praj Carretera De Caudete, Km. 0001,5 Campo Abajo Murcia 30510",
    "addr:postcode":"30510",
    "addr:street":"Carretera De Caudete Km. 0001,5",
    "iso:country":"ES",
    "sg:address":"Praj Carretera De Caudete, Km. 0001,5",
    "sg:city":"Campo Abajo",
    "sg:orig_category":"Tapicer\u00cdas",
    "sg:phone":"+34 968 79 04 16",
    "sg:postcode":"30510",
    "sg:province":"Murcia",
    "wof:name":"Iba\u00f1ez Asensio Antonio",
    "wof:placetype":"venue"
},
  "geometry": {"coordinates":[-1.1298867464,37.9834747314],"type":"Point"}
}