{
  "type": "Feature",
  "properties": {
    "addr:full":"Calle de Pique\u00d1as, 20 Madrid Madrid 28044",
    "addr:housenumber":"20",
    "addr:postcode":"madrid;28044",
    "addr:street":"Calle De Piquen\u0303As",
    "iso:country":"ES",
    "sg:address":"Calle de Pique\u00d1as, 20",
    "sg:city":"Madrid",
    "sg:orig_category":"Molduras, Junquillos, Listones Y Molduras Perforadas",
    "sg:phone":"+34 915 08 03 91",
    "sg:postcode":"28044",
    "sg:province":"Madrid",
    "wof:name":"Nieto Cempellin Antonio",
    "wof:placetype":"venue"
},
  "geometry": {"coordinates":[-3.7603359222,40.3674926758],"type":"Point"}
}