{
  "type": "Feature",
  "properties": {
    "iso:country":"ES",
    "sg:address":"Carrer de Ramon Par, 1",
    "sg:city":"Argentona",
    "sg:orig_category":"Ense\u00d1anza, Formaci\u00d3n Profesional: Aprendizaje",
    "sg:phone":"+34 937 97 49 00",
    "sg:postcode":"08310",
    "sg:province":"Barcelona",
    "wof:name":"Ajuntament D'argentona",
    "wof:placetype":"venue"
},
  "geometry": {"coordinates":[2.4004890919,41.5555381775],"type":"Point"}
}