{
  "type": "Feature",
  "properties": {
    "addr:full":"Avda Arrabal, 62 Requena Valencia 46340",
    "addr:housenumber":"62",
    "addr:postcode":"46340",
    "addr:street":"Avda Arrabal",
    "iso:country":"ES",
    "sg:address":"Avda Arrabal, 62",
    "sg:city":"Requena",
    "sg:orig_category":"Fabricaci\u00d3n De Muebles",
    "sg:phone":"+34 962 30 60 16",
    "sg:postcode":"46340",
    "sg:province":"Valencia",
    "wof:name":"Moreno Picazo Encarnacion",
    "wof:placetype":"venue"
},
  "geometry": {"coordinates":[-1.1082309484,39.4888954163],"type":"Point"}
}