{
  "type": "Feature",
  "properties": {
    "iso:country":"ES",
    "sg:address":"Calle de Goya, 14",
    "sg:city":"Puertollano",
    "sg:orig_category":"Tiendas De Grano, Frutas Y Legumbres Secas (al Por Menor)",
    "sg:phone":"+34 926 41 40 83",
    "sg:postcode":"13500",
    "sg:province":"Ciudad Real",
    "wof:name":"Navarro Murillo Jose Luis",
    "wof:placetype":"venue"
},
  "geometry": {"coordinates":[-4.1048388481,38.6852607727],"type":"Point"}
}