{
  "type": "Feature",
  "properties": {
    "iso:country":"ES",
    "sg:address":"Carr Canal Xuquer Turia, 1",
    "sg:city":"Pai I Capellans",
    "sg:orig_category":"Cristaler\u00cdas",
    "sg:phone":"+34 961 57 90 27",
    "sg:postcode":"46930",
    "sg:province":"Valencia",
    "wof:name":"Querubin Industria Del Vidrio S. L.",
    "wof:placetype":"venue"
},
  "geometry": {"coordinates":[-0.4419890046,39.482711792],"type":"Point"}
}