{
  "type": "Feature",
  "properties": {
    "iso:country":"ES",
    "sg:address":"Calle de Fueros, 2",
    "sg:city":"Salvatierra O Agurain",
    "sg:orig_category":"Venta, Instalaci\u00d3n De Calefacci\u00d3n",
    "sg:phone":"+34 945 31 23 51",
    "sg:postcode":"01200",
    "sg:province":"\u00c1lava",
    "wof:name":"Instalaciones Y Mantenimientos Campo S.cv.",
    "wof:placetype":"venue"
},
  "geometry": {"coordinates":[-2.3982276917,42.8485107422],"type":"Point"}
}