{
  "type": "Feature",
  "properties": {
    "addr:full":"Calle de Cronista Alvarez Rixo, S/n Palmas De Gran Canaria Las Palmas 35011",
    "addr:housenumber":"s",
    "addr:postcode":"35011",
    "addr:street":"Calle De Cronista Alvarez Rixo;/ N",
    "iso:country":"ES",
    "sg:address":"Calle de Cronista Alvarez Rixo, S/n",
    "sg:city":"Palmas De Gran Canaria",
    "sg:orig_category":"Inmobiliaria (agencias)",
    "sg:phone":"+34 928 28 02 41",
    "sg:postcode":"35011",
    "sg:province":"Las Palmas",
    "wof:name":"Hermanos Santana Cazorla S.l.",
    "wof:placetype":"venue"
},
  "geometry": {"coordinates":[-15.4354429245,28.1244335175],"type":"Point"}
}