{
  "type": "Feature",
  "properties": {
    "iso:country":"ES",
    "sg:address":"Avda Perez Galdos, 7",
    "sg:city":"Castellon",
    "sg:orig_category":"Centros De Coordinaci\u00d3n",
    "sg:phone":"+34 964 21 28 61",
    "sg:postcode":"12002",
    "sg:province":"Castell\u00f3n",
    "wof:name":"Escorihuela Centelles Maria Del Pilar",
    "wof:placetype":"venue"
},
  "geometry": {"coordinates":[-0.0436520018,39.9861030579],"type":"Point"}
}