{
  "type": "Feature",
  "properties": {
    "addr:full":"Calle de Miravalles, 12 Vitoria-gasteiz \u00c1lava 01013",
    "addr:housenumber":"12",
    "addr:postcode":"01013",
    "addr:street":"Calle De Miravalles",
    "iso:country":"ES",
    "sg:address":"Calle de Miravalles, 12",
    "sg:city":"Vitoria-gasteiz",
    "sg:orig_category":"Mec\u00c1nico Del Autom\u00d3vil",
    "sg:phone":"+34 945 28 74 33",
    "sg:postcode":"01013",
    "sg:province":"\u00c1lava",
    "wof:name":"Cooperativa Industrial Carrocera Alavesa",
    "wof:placetype":"venue"
},
  "geometry": {"coordinates":[-2.641297102,42.8687171936],"type":"Point"}
}