{
  "type": "Feature",
  "properties": {
    "addr:full":"Luga El Coso, 1 Ribera Fresno Badajoz 06225",
    "addr:housenumber":"1",
    "addr:postcode":"06225",
    "addr:street":"Coso",
    "iso:country":"ES",
    "sg:address":"Luga El Coso, 1",
    "sg:city":"Ribera Fresno",
    "sg:orig_category":"Carnicer\u00cdas, Carnicer\u00cdas",
    "sg:phone":"+34 924 53 72 54",
    "sg:postcode":"06225",
    "sg:province":"Badajoz",
    "wof:name":"Rosa Vazquez Pilar",
    "wof:placetype":"venue"
},
  "geometry": {"coordinates":[-6.2413439751,38.5495986938],"type":"Point"}
}