{
  "type": "Feature",
  "properties": {
    "iso:country":"ES",
    "sg:address":"Avda Reino De Leon, 1",
    "sg:city":"Santa Maria Del Paramo",
    "sg:orig_category":"Supermercados Y Hipermercados",
    "sg:phone":"+34 987 35 08 54",
    "sg:postcode":"24240",
    "sg:province":"Le\u00f3n",
    "wof:name":"Rebollanes S.l.",
    "wof:placetype":"venue"
},
  "geometry": {"coordinates":[-5.7469739914,42.3569259644],"type":"Point"}
}