{
  "type": "Feature",
  "properties": {
    "addr:full":"Pl Ajuntament, 7 Premia Mar Barcelona 08330",
    "addr:housenumber":"7",
    "addr:postcode":"08330",
    "addr:street":"Pl Ajuntament",
    "iso:country":"ES",
    "sg:address":"Pl Ajuntament, 7",
    "sg:city":"Premia Mar",
    "sg:orig_category":"Estancos",
    "sg:phone":"+34 937 52 38 78",
    "sg:postcode":"08330",
    "sg:province":"Barcelona",
    "wof:name":"Llonch Catala Juan",
    "wof:placetype":"venue"
},
  "geometry": {"coordinates":[2.3568599224,41.4897575378],"type":"Point"}
}