{
  "type": "Feature",
  "properties": {
    "iso:country":"ES",
    "sg:address":"Carrer de Robert Gerhard, 3",
    "sg:city":"Tarragona",
    "sg:orig_category":"Electricidad: Instaladores",
    "sg:phone":"+34 977 23 04 54",
    "sg:postcode":"43005",
    "sg:province":"Tarragona",
    "wof:name":"Verge Gomez Daniel",
    "wof:placetype":"venue"
},
  "geometry": {"coordinates":[1.2419079542,41.1152610779],"type":"Point"}
}