{
  "type": "Feature",
  "properties": {
    "addr:full":"Calle de Florentino Cueto Felgueroso, S/n Langreo Asturias 33930",
    "addr:housenumber":"s / n",
    "addr:postcode":"33930",
    "addr:street":"Calle De Florentino;Felgueroso",
    "iso:country":"ES",
    "sg:address":"Calle de Florentino Cueto Felgueroso, S/n",
    "sg:city":"Langreo",
    "sg:orig_category":"Farmacias",
    "sg:phone":"+34 985 69 07 01",
    "sg:postcode":"33930",
    "sg:province":"Asturias",
    "wof:name":"Farmacia Palencia C B",
    "wof:placetype":"venue"
},
  "geometry": {"coordinates":[-5.6923308372,43.3076591492],"type":"Point"}
}