{
  "type": "Feature",
  "properties": {
    "iso:country":"ES",
    "sg:address":"Labradores, 24",
    "sg:city":"Boadilla",
    "sg:orig_category":"Ense\u00d1anza: Profesiones Art\u00cdsticas",
    "sg:phone":"+34 916 32 68 07",
    "sg:postcode":"28660",
    "sg:province":"Madrid",
    "sg:website":"www.pixelin.com",
    "wof:name":"Pixelin Fotografia S.l.",
    "wof:placetype":"venue"
},
  "geometry": {"coordinates":[-3.8441109657,40.3948326111],"type":"Point"}
}