{
  "type": "Feature",
  "properties": {
    "addr:full":"Calle de Secundino Alonso, 96 Pto. Rosario Las Palmas 35600",
    "addr:housenumber":"96",
    "addr:postcode":"35600",
    "addr:street":"Calle De Secundino Alonso;Pto. Rosario Las",
    "iso:country":"ES",
    "sg:address":"Calle de Secundino Alonso, 96",
    "sg:city":"Pto. Rosario",
    "sg:orig_category":"Pr\u00c9stamos Personales E Hipotecarios",
    "sg:phone":"+34 928 86 10 83",
    "sg:postcode":"35600",
    "sg:province":"Las Palmas",
    "wof:name":"Mu\u00f1oz Roncero Jose Manuel",
    "wof:placetype":"venue"
},
  "geometry": {"coordinates":[-13.8638477325,28.4934978485],"type":"Point"}
}