{
  "type": "Feature",
  "properties": {
    "iso:country":"ES",
    "sg:address":"Avda Porteli\u00d1a, 10",
    "sg:city":"Porteli\u00d1a",
    "sg:orig_category":"Loter\u00cda Y T\u00d3mbola",
    "sg:phone":"+34 986 87 33 84",
    "sg:postcode":"36163",
    "sg:province":"Pontevedra",
    "wof:name":"Martinez Moreira Manuel",
    "wof:placetype":"venue"
},
  "geometry": {"coordinates":[-8.6362781525,42.1934928894],"type":"Point"}
}