{
  "type": "Feature",
  "properties": {
    "addr:full":"Carretera Leon, Km. 0210,0 S. Cristobal Entrevi\u00f1as Zamora 49690",
    "addr:postcode":"49690",
    "addr:street":"Carretera Leon Km. 0210,0 S. Cristobal Entrevin\u0303As Zamora",
    "iso:country":"ES",
    "sg:address":"Carretera Leon, Km. 0210,0",
    "sg:city":"S. Cristobal Entrevi\u00f1as",
    "sg:orig_category":"Cueros Y Pieles (al Por Mayor)",
    "sg:phone":"+34 980 64 37 06",
    "sg:postcode":"49690",
    "sg:province":"Zamora",
    "wof:name":"Cueros Y Curtidos Pavon S.a.",
    "wof:placetype":"venue"
},
  "geometry": {"coordinates":[-5.6349887848,42.0465202332],"type":"Point"}
}