{
  "type": "Feature",
  "properties": {
    "iso:country":"ES",
    "sg:address":"Urb Coveta Fuma, 6",
    "sg:city":"Coveta Fuma",
    "sg:orig_category":"Edici\u00d3n, Venta De Partituras Musicales",
    "sg:phone":"+34 965 63 83 75",
    "sg:postcode":"03560",
    "sg:province":"Alicante",
    "wof:name":"Compa\u00f1ia De Canciones S.l.",
    "wof:placetype":"venue"
},
  "geometry": {"coordinates":[-0.3906340003,38.4271888733],"type":"Point"}
}