{
  "type": "Feature",
  "properties": {
    "addr:full":"Calle de Sevilla, 75 Carmona Sevilla 41410",
    "addr:housenumber":"75",
    "addr:postcode":"41410",
    "addr:street":"Calle De Sevilla",
    "iso:country":"ES",
    "sg:address":"Calle de Sevilla, 75",
    "sg:city":"Carmona",
    "sg:orig_category":"Material Y Suministros Para Veterinarios",
    "sg:phone":"+34 954 19 17 99",
    "sg:postcode":"41410",
    "sg:province":"Sevilla",
    "wof:name":"Roman Perez Antonio Javier",
    "wof:placetype":"venue"
},
  "geometry": {"coordinates":[-5.6482791901,37.4681091309],"type":"Point"}
}