{
  "type": "Feature",
  "properties": {
    "addr:full":"Calle de La Alegria De La Huerta, 20 Madrid Madrid 28041",
    "addr:housenumber":"20",
    "addr:postcode":"madrid;28041",
    "addr:street":"Calle De La Alegria De La Huerta",
    "iso:country":"ES",
    "sg:address":"Calle de La Alegria De La Huerta, 20",
    "sg:city":"Madrid",
    "sg:orig_category":"Reposter\u00cdas",
    "sg:phone":"+34 917 96 12 95",
    "sg:postcode":"28041",
    "sg:province":"Madrid",
    "wof:name":"Alvarez Quintero Rosa Maria",
    "wof:placetype":"venue"
},
  "geometry": {"coordinates":[-3.6952950954,40.3541564941],"type":"Point"}
}