{
  "type": "Feature",
  "properties": {
    "iso:country":"ES",
    "sg:address":"Calle de Merced La, 33",
    "sg:city":"Gijon",
    "sg:orig_category":"Imprenta",
    "sg:phone":"+34 985 34 23 31",
    "sg:postcode":"33201",
    "sg:province":"Asturias",
    "wof:name":"Imprenta La Versal S.l.",
    "wof:placetype":"venue"
},
  "geometry": {"coordinates":[-5.6621088982,43.5421791077],"type":"Point"}
}