{
  "type": "Feature",
  "properties": {
    "iso:country":"ES",
    "sg:address":"Lesakako Bidea, 22",
    "sg:city":"Arditurri",
    "sg:orig_category":"Ense\u00d1anza, Formaci\u00d3n Profesional: Aprendizaje",
    "sg:phone":"+34 943 58 00 10",
    "sg:postcode":"20180",
    "sg:province":"Guip\u00f9zcoa",
    "wof:name":"P.p.g. Eta Besteak C.b.",
    "wof:placetype":"venue"
},
  "geometry": {"coordinates":[-1.8629590273,43.2992401123],"type":"Point"}
}