{
  "type": "Feature",
  "properties": {
    "addr:full":"Carrer de Sant Miquel, 4 Molins Rei Barcelona 08750",
    "addr:housenumber":"4",
    "addr:postcode":"08750",
    "addr:street":"Carrer De Sant Miquel;Barcelona",
    "iso:country":"ES",
    "sg:address":"Carrer de Sant Miquel, 4",
    "sg:city":"Molins Rei",
    "sg:orig_category":"Peluquer\u00cdas, Peluquer\u00cda Mixta",
    "sg:phone":"+34 936 68 58 68",
    "sg:postcode":"08750",
    "sg:province":"Barcelona",
    "wof:name":"Cuenca Guas Nuria",
    "wof:placetype":"venue"
},
  "geometry": {"coordinates":[2.0176479816,41.4129333496],"type":"Point"}
}