{
  "type": "Feature",
  "properties": {
    "addr:full":"Calle de Lapurdi, 41 Kurtzea Vizcaya 48960",
    "addr:housenumber":"41",
    "addr:postcode":"48960",
    "addr:street":"Calle De Lapurdi",
    "iso:country":"ES",
    "sg:address":"Calle de Lapurdi, 41",
    "sg:city":"Kurtzea",
    "sg:orig_category":"Fisioterapia",
    "sg:phone":"+34 944 56 52 35",
    "sg:postcode":"48960",
    "sg:province":"Vizcaya",
    "wof:name":"1002 Body Conninchigua S.l.",
    "wof:placetype":"venue"
},
  "geometry": {"coordinates":[-2.698387,43.220428],"type":"Point"}
}