{
  "type": "Feature",
  "properties": {
    "iso:country":"ES",
    "sg:address":"Calle de Tarraco, 7",
    "sg:city":"Merida",
    "sg:orig_category":"Venta, Colocaci\u00d3n, Reparaci\u00d3n De Radiadores Para Veh\u00cdculos",
    "sg:phone":"+34 924 37 20 66",
    "sg:postcode":"06800",
    "sg:province":"Badajoz",
    "wof:name":"Radiadores Sanchez S.l.",
    "wof:placetype":"venue"
},
  "geometry": {"coordinates":[-6.3532919884,38.9113044739],"type":"Point"}
}