{
  "type": "Feature",
  "properties": {
    "addr:full":"Carrer de Gallecs, 62 Mollet Valles Barcelona 08100",
    "addr:housenumber":"62",
    "addr:postcode":"08100",
    "addr:street":"Carrer De Gallecs",
    "iso:country":"ES",
    "sg:address":"Carrer de Gallecs, 62",
    "sg:city":"Mollet Valles",
    "sg:orig_category":"Cajas De Ahorro",
    "sg:phone":"+34 935 79 01 52",
    "sg:postcode":"08100",
    "sg:province":"Barcelona",
    "sg:website":"www.lacaixa.es",
    "wof:name":"Caixa D'estalvis I Pensions De Barcelona",
    "wof:placetype":"venue"
},
  "geometry": {"coordinates":[2.2078011036,41.5483665466],"type":"Point"}
}