{
  "type": "Feature",
  "properties": {
    "addr:full":"Calle de Alfareros (los), 14 Alcorcon Madrid 28925",
    "addr:housenumber":"14",
    "addr:postcode":"28925",
    "addr:street":"Calle De Alfareros Los",
    "iso:country":"ES",
    "sg:address":"Calle de Alfareros (los), 14",
    "sg:city":"Alcorcon",
    "sg:orig_category":"Muebles Y Accesorios Para Cocinas Y Cuartos De Ba\u00d1o (al Por Menor)",
    "sg:phone":"+34 916 43 38 22",
    "sg:postcode":"28925",
    "sg:province":"Madrid",
    "wof:name":"Cociarco S.a.",
    "wof:placetype":"venue"
},
  "geometry": {"coordinates":[-3.8048079014,40.3416290283],"type":"Point"}
}