{
  "type": "Feature",
  "properties": {
    "addr:full":"Calle de Gracia, 20 Granada Granada 18002",
    "addr:housenumber":"20",
    "addr:postcode":"18002",
    "addr:street":"Calle De Gracia",
    "iso:country":"ES",
    "sg:address":"Calle de Gracia, 20",
    "sg:city":"Granada",
    "sg:orig_category":"Telas Y Sedas (al Por Menor)",
    "sg:phone":"+34 958 26 45 12",
    "sg:postcode":"18002",
    "sg:province":"Granada",
    "wof:name":"Tejidos Buenos Aires S. A.",
    "wof:placetype":"venue"
},
  "geometry": {"coordinates":[-3.6024901867,37.1741828918],"type":"Point"}
}