{
  "type": "Feature",
  "properties": {
    "iso:country":"ES",
    "sg:address":"Calle de Mayor, 41",
    "sg:city":"Ari\u00f1o",
    "sg:orig_category":"Cajas Para Embalar",
    "sg:phone":"+34 978 81 74 93",
    "sg:postcode":"44547",
    "sg:province":"Teruel",
    "wof:name":"Caja Rural De Teruel",
    "wof:placetype":"venue"
},
  "geometry": {"coordinates":[-0.5921900272,41.030670166],"type":"Point"}
}