{
  "type": "Feature",
  "properties": {
    "addr:full":"Carr Vicen\u00c7 Buades, 39 Puerto De Pollen\u00c7a Islas Baleares 07470",
    "addr:housenumber":"39",
    "addr:postcode":"07470",
    "addr:street":"Carr Vicenc\u0327 Buades",
    "iso:country":"ES",
    "sg:address":"Carr Vicen\u00c7 Buades, 39",
    "sg:city":"Puerto De Pollen\u00c7a",
    "sg:orig_category":"Florister\u00cdas",
    "sg:phone":"+34 971 86 42 09",
    "sg:postcode":"07470",
    "sg:province":"Islas Baleares",
    "wof:name":"Coll Coll Catalina",
    "wof:placetype":"venue"
},
  "geometry": {"coordinates":[3.0821900368,39.9063034058],"type":"Point"}
}