{
  "type": "Feature",
  "properties": {
    "iso:country":"ES",
    "sg:address":"Av Viena, 10",
    "sg:city":"Miami Playa",
    "sg:orig_category":"Inmobiliaria (agencias)",
    "sg:phone":"+34 977 17 25 06",
    "sg:postcode":"43892",
    "sg:province":"Tarragona",
    "wof:name":"Bola\u00f1os & Cano Servicios S.l.",
    "wof:placetype":"venue"
},
  "geometry": {"coordinates":[0.9573349953,41.0249786377],"type":"Point"}
}