{
  "type": "Feature",
  "properties": {
    "iso:country":"ES",
    "sg:address":"Calle de Joaquin Chapaprieta, 48",
    "sg:city":"Torrevieja",
    "sg:orig_category":"Carnicer\u00cdas, Carnicer\u00cdas",
    "sg:phone":"+34 965 71 29 24",
    "sg:postcode":"03180",
    "sg:province":"Alicante",
    "wof:name":"Dolon Esteve Eduardo",
    "wof:placetype":"venue"
},
  "geometry": {"coordinates":[-0.6810740232,37.9792976379],"type":"Point"}
}