{
  "type": "Feature",
  "properties": {
    "iso:country":"ES",
    "sg:address":"C/ Pou Florit, 33",
    "sg:city":"Porreres",
    "sg:orig_category":"Ense\u00d1anza: Profesiones Art\u00cdsticas",
    "sg:phone":"+34 971 64 76 81",
    "sg:postcode":"07260",
    "sg:province":"Islas Baleares",
    "wof:name":"Cerda Bonnin Gabriel",
    "wof:placetype":"venue"
},
  "geometry": {"coordinates":[3.0247321129,39.5151481628],"type":"Point"}
}