{
  "type": "Feature",
  "properties": {
    "addr:full":"Carrer de Balmes, 66 Sant Vicen\u00c7 Dels Horts Barcelona 08620",
    "addr:housenumber":"66",
    "addr:postcode":"08620",
    "addr:street":"Carrer De Balmes",
    "iso:country":"ES",
    "sg:address":"Carrer de Balmes, 66",
    "sg:city":"Sant Vicen\u00c7 Dels Horts",
    "sg:orig_category":"Alquiler De V\u00cddeo",
    "sg:phone":"+34 936 56 50 83",
    "sg:postcode":"08620",
    "sg:province":"Barcelona",
    "wof:name":"S.vicen\u00c7 Video Digital, S.l.",
    "wof:placetype":"venue"
},
  "geometry": {"coordinates":[2.0062000751,41.3991127014],"type":"Point"}
}