{
  "type": "Feature",
  "properties": {
    "addr:full":"Calle de San Felipe, 11 Tomelloso Ciudad Real 13700",
    "addr:housenumber":"11",
    "addr:postcode":"13700",
    "addr:street":"Calle De San Felipe",
    "iso:country":"ES",
    "sg:address":"Calle de San Felipe, 11",
    "sg:city":"Tomelloso",
    "sg:orig_category":"Electricidad: Instaladores",
    "sg:phone":"+34 926 50 45 59",
    "sg:postcode":"13700",
    "sg:province":"Ciudad Real",
    "wof:name":"Inelclim S.l.",
    "wof:placetype":"venue"
},
  "geometry": {"coordinates":[-3.0260360241,39.1516456604],"type":"Point"}
}