{
  "type": "Feature",
  "properties": {
    "addr:full":"Av Ciutat De L'hospitalet, 87 Esplugues Llobregat Barcelona 08950",
    "addr:housenumber":"87",
    "addr:postcode":"08950",
    "addr:street":"Av Ciutat De L'Hospitalet",
    "iso:country":"ES",
    "sg:address":"Av Ciutat De L'hospitalet, 87",
    "sg:city":"Esplugues Llobregat",
    "sg:orig_category":"Contenedores (mercanc\u00cdas)",
    "sg:phone":"+34 934 73 31 49",
    "sg:postcode":"08950",
    "sg:province":"Barcelona",
    "wof:name":"Transdetagare S.l",
    "wof:placetype":"venue"
},
  "geometry": {"coordinates":[2.0969913006,41.3701972961],"type":"Point"}
}