{
  "type": "Feature",
  "properties": {
    "addr:full":"Carrer de Santander, 26 Barcelona Barcelona 08020",
    "addr:housenumber":"26",
    "addr:postcode":"08020",
    "addr:street":"Carrer De Santander",
    "iso:country":"ES",
    "sg:address":"Carrer de Santander, 26",
    "sg:city":"Barcelona",
    "sg:orig_category":"Molduras, Junquillos, Listones Y Molduras Perforadas",
    "sg:phone":"+34 933 05 25 61",
    "sg:postcode":"08020",
    "sg:province":"Barcelona",
    "wof:name":"Fernandez Cardona Marina",
    "wof:placetype":"venue"
},
  "geometry": {"coordinates":[2.2007710934,41.4258003235],"type":"Point"}
}