{
  "type": "Feature",
  "properties": {
    "addr:full":"Calle de Auso Y Monzo, 16 Alacant Alicante 03006",
    "addr:housenumber":"16",
    "addr:postcode":"03006",
    "addr:street":"Calle De Auso Y Monzo",
    "iso:country":"ES",
    "sg:address":"Calle de Auso Y Monzo, 16",
    "sg:city":"Alacant",
    "sg:orig_category":"Promotores Constructores",
    "sg:phone":"+34 965 11 55 51",
    "sg:postcode":"03006",
    "sg:province":"Alicante",
    "sg:website":"www.aldesacontrucciones.es",
    "wof:name":"Aldesa Construcciones S.a.",
    "wof:placetype":"venue"
},
  "geometry": {"coordinates":[-0.5067557096,38.3449363708],"type":"Point"}
}