{
  "type": "Feature",
  "properties": {
    "addr:full":"Pase Sherry (del), S/n Costa Oeste C\u00e1diz 11500",
    "addr:housenumber":"s / n",
    "addr:postcode":"11500",
    "addr:street":"Costa Oeste Ca\u0301Diz",
    "iso:country":"ES",
    "sg:address":"Pase Sherry (del), S/n",
    "sg:city":"Costa Oeste",
    "sg:orig_category":"Deportes N\u00c1uticos, Acu\u00c1ticos Y Subacu\u00c1ticos: Art\u00cdculos Y Equipo (al Por Menor)",
    "sg:phone":"+34 956 87 03 92",
    "sg:postcode":"11500",
    "sg:province":"C\u00e1diz",
    "wof:name":"Julio Romero Nautica S.l.l.",
    "wof:placetype":"venue"
},
  "geometry": {"coordinates":[-6.2197542191,36.6056632996],"type":"Point"}
}