{
  "type": "Feature",
  "properties": {
    "addr:full":"Av Can Serra, 44 Hospitalet Llobregat Barcelona 08906",
    "addr:housenumber":"44",
    "addr:postcode":"08906",
    "addr:street":"Av Can Serra",
    "iso:country":"ES",
    "sg:address":"Av Can Serra, 44",
    "sg:city":"Hospitalet Llobregat",
    "sg:orig_category":"Empresas De Limpieza",
    "sg:phone":"+34 934 38 40 86",
    "sg:postcode":"08906",
    "sg:province":"Barcelona",
    "wof:name":"Salimeni Monsalve Horacio Abel",
    "wof:placetype":"venue"
},
  "geometry": {"coordinates":[2.100425005,41.3660049438],"type":"Point"}
}