{
  "type": "Feature",
  "properties": {
    "addr:full":"La Campana, 35 Luisiana Sevilla 41430",
    "addr:housenumber":"35",
    "addr:postcode":"41430",
    "addr:street":"La Campana",
    "iso:country":"ES",
    "sg:address":"La Campana, 35",
    "sg:city":"Luisiana",
    "sg:classifiers":[
        {
            "category":"Taxi",
            "type":"Transportation"
        }
    ],
    "sg:phone":"+34 955 90 73 65",
    "sg:postcode":"41430",
    "sg:province":"Sevilla",
    "wof:name":"Dominguez Mu\u00f1oz Sebastian",
    "wof:placetype":"venue"
},
  "geometry": {"coordinates":[-5.2505440712,37.5272445679],"type":"Point"}
}