{
  "type": "Feature",
  "properties": {
    "iso:country":"ES",
    "sg:address":"Barrio San Roque, S/n",
    "sg:city":"Torres",
    "sg:orig_category":"Distribuci\u00d3n De Petr\u00d3leo Y Derivados",
    "sg:phone":"+34 942 88 10 66",
    "sg:postcode":"39300",
    "sg:province":"Cantabria",
    "wof:name":"Cedipsa Compa\u00d1ia Espa\u00d1ola Distribuidora De Petroleos S.a.",
    "wof:placetype":"venue"
},
  "geometry": {"coordinates":[-4.0520391464,43.34897995],"type":"Point"}
}