{
  "type": "Feature",
  "properties": {
    "addr:full":"Barr Luz (la), 1 Santander Cantabria 39008",
    "addr:housenumber":"1",
    "addr:postcode":"39008",
    "addr:street":"Luz La",
    "iso:country":"ES",
    "sg:address":"Barr Luz (la), 1",
    "sg:city":"Santander",
    "sg:orig_category":"Imprenta",
    "sg:phone":"+34 942 23 16 10",
    "sg:postcode":"39008",
    "sg:province":"Cantabria",
    "wof:name":"Jaurena Del Pozo Miguel Angel",
    "wof:placetype":"venue"
},
  "geometry": {"coordinates":[-3.8100090027,43.4614982605],"type":"Point"}
}