{
  "type": "Feature",
  "properties": {
    "iso:country":"ES",
    "sg:address":"Calle de Santa Virgilia, 5",
    "sg:city":"Madrid",
    "sg:orig_category":"Abogados",
    "sg:phone":"+34 913 81 84 33",
    "sg:postcode":"28033",
    "sg:province":"Madrid",
    "wof:name":"Abalos Culebras Luis",
    "wof:placetype":"venue"
},
  "geometry": {"coordinates":[-3.643847,40.478077],"type":"Point"}
}