{
  "type": "Feature",
  "properties": {
    "addr:full":"Calle de San Bernardo, 126 Madrid Madrid 28015",
    "addr:housenumber":"126",
    "addr:postcode":"28015",
    "addr:street":"Calle De San Bernardo",
    "iso:country":"ES",
    "sg:address":"Calle de San Bernardo, 126",
    "sg:city":"Madrid",
    "sg:orig_category":"Agencias De Viajes",
    "sg:phone":"+34 914 45 59 01",
    "sg:postcode":"28015",
    "sg:province":"Madrid",
    "wof:name":"Viajes Trenamar S. A.",
    "wof:placetype":"venue"
},
  "geometry": {"coordinates":[-3.7049100399,40.4317588806],"type":"Point"}
}