{
  "type": "Feature",
  "properties": {
    "addr:full":"Calle de Jesus Rincon Jimenez, 84 Badajoz Badajoz 06010",
    "addr:housenumber":"84",
    "addr:postcode":"06010",
    "addr:street":"Calle De Jesus Rincon Jimenez",
    "iso:country":"ES",
    "sg:address":"Calle de Jesus Rincon Jimenez, 84",
    "sg:city":"Badajoz",
    "sg:orig_category":"Arquitectos",
    "sg:phone":"+34 924 24 84 33",
    "sg:postcode":"06010",
    "sg:province":"Badajoz",
    "wof:name":"Rius Direccion De Proyectos Sl",
    "wof:placetype":"venue"
},
  "geometry": {"coordinates":[-6.9794988632,38.8668899536],"type":"Point"}
}