{
  "type": "Feature",
  "properties": {
    "iso:country":"ES",
    "sg:address":"Carrer de Floridablanca, 54",
    "sg:city":"Barcelona",
    "sg:orig_category":"Comidas Por Encargo, Organizaci\u00d3n De Recepciones",
    "sg:phone":"+34 933 25 84 51",
    "sg:postcode":"08015",
    "sg:province":"Barcelona",
    "wof:name":"Sauri Pardo De Atin Maria Cristina",
    "wof:placetype":"venue"
},
  "geometry": {"coordinates":[2.157337904,41.3774299622],"type":"Point"}
}