{
  "type": "Feature",
  "properties": {
    "iso:country":"ES",
    "sg:address":"Avda Ordo\u00d1o Ii, 28",
    "sg:city":"Le\u00f3n",
    "sg:orig_category":"M\u00c9dicos: Estomatolog\u00cda",
    "sg:phone":"+34 987 24 03 13",
    "sg:postcode":"24001",
    "sg:province":"Le\u00f3n",
    "wof:name":"Rodriguez Perez Jose Manuel",
    "wof:placetype":"venue"
},
  "geometry": {"coordinates":[-5.5768551826,42.596698761],"type":"Point"}
}