{
  "type": "Feature",
  "properties": {
    "addr:full":"Urb Aguadulce, S/n Aguadulce Almer\u00eda 04720",
    "addr:housenumber":"s / n",
    "addr:postcode":"04720",
    "addr:street":"Urb Aguadulce;Almeri\u0301A",
    "iso:country":"ES",
    "sg:address":"Urb Aguadulce, S/n",
    "sg:city":"Aguadulce",
    "sg:orig_category":"Arquitectos",
    "sg:phone":"+34 950 34 00 88",
    "sg:postcode":"04720",
    "sg:province":"Almer\u00eda",
    "wof:name":"Pfeifer De Formica-corsi Carlos",
    "wof:placetype":"venue"
},
  "geometry": {"coordinates":[-2.5749289989,36.8141555786],"type":"Point"}
}