{
  "type": "Feature",
  "properties": {
    "addr:full":"Calle de Don Juan Campos, 4 Guadalcanal Sevilla 41390",
    "addr:housenumber":"4",
    "addr:postcode":"41390",
    "addr:street":"Calle De Don Juan Campos",
    "iso:country":"ES",
    "sg:address":"Calle de Don Juan Campos, 4",
    "sg:city":"Guadalcanal",
    "sg:orig_category":"Agricultores, Agricultores",
    "sg:phone":"+34 954 88 67 95",
    "sg:postcode":"41390",
    "sg:province":"Sevilla",
    "wof:name":"Agriculturas Diversas S.l.",
    "wof:placetype":"venue"
},
  "geometry": {"coordinates":[-5.8202190399,38.092502594],"type":"Point"}
}