{
  "type": "Feature",
  "properties": {
    "iso:country":"ES",
    "sg:address":"Carrer de Sant Cosme, 166",
    "sg:city":"Terrassa",
    "sg:orig_category":"Centros Comerciales Y Grandes Tiendas",
    "sg:phone":"+34 937 31 71 35",
    "sg:postcode":"08222",
    "sg:province":"Barcelona",
    "wof:name":"Torrades Salaet Maria Carme",
    "wof:placetype":"venue"
},
  "geometry": {"coordinates":[2.0292100906,41.5659866333],"type":"Point"}
}