{
  "type": "Feature",
  "properties": {
    "addr:full":"Avda Mancha, 5 Villaca\u00f1as Toledo 45860",
    "addr:housenumber":"5",
    "addr:postcode":"45860",
    "addr:street":"Avda Mancha",
    "iso:country":"ES",
    "sg:address":"Avda Mancha, 5",
    "sg:city":"Villaca\u00f1as",
    "sg:orig_category":"Negocio De Materiales De Construcci\u00d3n",
    "sg:phone":"+34 925 16 00 85",
    "sg:postcode":"45860",
    "sg:province":"Toledo",
    "wof:name":"Suministros Villaca\u00f1as S. L.",
    "wof:placetype":"venue"
},
  "geometry": {"coordinates":[-3.3311240673,39.6321792603],"type":"Point"}
}