{
  "type": "Feature",
  "properties": {
    "addr:full":"Calle de Santo Domingo, 12 Jerez De La Frontera C\u00e1diz 11402",
    "addr:housenumber":"12",
    "addr:postcode":"11402",
    "addr:street":"Calle De Santo Domingo",
    "iso:country":"ES",
    "sg:address":"Calle de Santo Domingo, 12",
    "sg:city":"Jerez De La Frontera",
    "sg:orig_category":"Inmobiliaria (agencias)",
    "sg:phone":"+34 956 32 61 93",
    "sg:postcode":"11402",
    "sg:province":"C\u00e1diz",
    "wof:name":"Sanchez Ojeda Joaquin",
    "wof:placetype":"venue"
},
  "geometry": {"coordinates":[-6.1342830658,36.6891136169],"type":"Point"}
}