{
  "type": "Feature",
  "properties": {
    "iso:country":"ES",
    "sg:address":"Calle de Ramon De Campoamor, 13",
    "sg:city":"Navia",
    "sg:orig_category":"Farmacias",
    "sg:phone":"+34 985 63 01 97",
    "sg:postcode":"33710",
    "sg:province":"Asturias",
    "wof:name":"Sela Perez Maria Cruz",
    "wof:placetype":"venue"
},
  "geometry": {"coordinates":[-6.7213191986,43.53931427],"type":"Point"}
}