{
  "type": "Feature",
  "properties": {
    "iso:country":"ES",
    "sg:address":"Moldes, 33",
    "sg:city":"Moldes",
    "sg:orig_category":"Empresas De Pintura Y Revestimientos",
    "sg:phone":"+34 986 87 71 00",
    "sg:postcode":"36157",
    "sg:province":"Pontevedra",
    "wof:name":"Casas Moldes Angel",
    "wof:placetype":"venue"
},
  "geometry": {"coordinates":[-8.6582126617,42.4889144897],"type":"Point"}
}