{
  "type": "Feature",
  "properties": {
    "iso:country":"ES",
    "sg:address":"Calle de Fundadora De Las Siervas De Jesus, 31",
    "sg:city":"Vitoria-gasteiz",
    "sg:orig_category":"M\u00c9dicos: Psiquiatr\u00cda",
    "sg:phone":"+34 945 28 39 72",
    "sg:postcode":"01001",
    "sg:province":"\u00c1lava",
    "wof:name":"Garcia Gonzalo Dictinio Amador",
    "wof:placetype":"venue"
},
  "geometry": {"coordinates":[-2.6750330925,42.8495903015],"type":"Point"}
}