{
  "type": "Feature",
  "properties": {
    "addr:full":"C/ Ciutat De Mataro, 13 Tarrega Lleida 25300",
    "addr:housenumber":"13",
    "addr:postcode":"25300",
    "addr:street":"C / Ciutat De Mataro",
    "iso:country":"ES",
    "sg:address":"C/ Ciutat De Mataro, 13",
    "sg:city":"Tarrega",
    "sg:orig_category":"Promotores Constructores",
    "sg:phone":"+34 973 50 10 59",
    "sg:postcode":"25300",
    "sg:province":"Lleida",
    "wof:name":"Construccions Balcells-cucurull S.l.",
    "wof:placetype":"venue"
},
  "geometry": {"coordinates":[1.1410850286,41.6482696533],"type":"Point"}
}