{
  "type": "Feature",
  "properties": {
    "addr:full":"Calle de Quemadero De San Francisco, 1 Carmona Sevilla 41410",
    "addr:housenumber":"1",
    "addr:postcode":"41410",
    "addr:street":"Calle De Quemadero De San Francisco",
    "iso:country":"ES",
    "sg:address":"Calle de Quemadero De San Francisco, 1",
    "sg:city":"Carmona",
    "sg:orig_category":"Quincaller\u00cda (al Por Menor)",
    "sg:phone":"+34 954 14 27 29",
    "sg:postcode":"41410",
    "sg:province":"Sevilla",
    "wof:name":"Roldan Villalba David",
    "wof:placetype":"venue"
},
  "geometry": {"coordinates":[-5.6499037743,37.4703559875],"type":"Point"}
}