{
  "type": "Feature",
  "properties": {
    "iso:country":"ES",
    "sg:address":"Dique Sur, S/n",
    "sg:city":"Melilla",
    "sg:orig_category":"Venta, Montaje De Neum\u00c1ticos",
    "sg:phone":"+34 952 67 83 12",
    "sg:postcode":"52006",
    "sg:province":"Melilla",
    "wof:name":"Dris Maanan Benaisa",
    "wof:placetype":"venue"
},
  "geometry": {"coordinates":[-2.9383699894,35.2764587402],"type":"Point"}
}