{
  "type": "Feature",
  "properties": {
    "addr:full":"Carrer de Diputacio, 282 Barcelona Barcelona 08009",
    "addr:housenumber":"282",
    "addr:postcode":"08009",
    "addr:street":"Carrer De Diputacio",
    "iso:country":"ES",
    "sg:address":"Carrer de Diputacio, 282",
    "sg:city":"Barcelona",
    "sg:orig_category":"\u00d3ptica: Instrumentos (fabricaci\u00d3n)",
    "sg:phone":"+34 933 01 61 66",
    "sg:postcode":"08009",
    "sg:province":"Barcelona",
    "wof:name":"Kukos Opticas S.l.",
    "wof:placetype":"venue"
},
  "geometry": {"coordinates":[2.1695699692,41.3921127319],"type":"Point"}
}