{
  "type": "Feature",
  "properties": {
    "iso:country":"ES",
    "sg:address":"B Magdalena, 34",
    "sg:city":"Iru\u00f1a",
    "sg:orig_category":"Frutas Y Legumbres Frescas (al Por Mayor)",
    "sg:phone":"+34 948 12 93 92",
    "sg:postcode":"31015",
    "sg:province":"Navarra",
    "wof:name":"Echaide Gomez Jesus Maria",
    "wof:placetype":"venue"
},
  "geometry": {"coordinates":[-1.632349968,42.8258132935],"type":"Point"}
}