{
  "type": "Feature",
  "properties": {
    "addr:full":"Calle de Diego Perez Mila, 26 Isla Cristina Huelva 21410",
    "addr:housenumber":"26",
    "addr:postcode":"21410",
    "addr:street":"Calle De Diego Perez Mila",
    "iso:country":"ES",
    "sg:address":"Calle de Diego Perez Mila, 26",
    "sg:city":"Isla Cristina",
    "sg:orig_category":"Distribuci\u00d3n De Petr\u00d3leo Y Derivados",
    "sg:phone":"+34 959 33 19 06",
    "sg:postcode":"21410",
    "sg:province":"Huelva",
    "wof:name":"Benito Alonso S. L.",
    "wof:placetype":"venue"
},
  "geometry": {"coordinates":[-7.3289451599,37.2046737671],"type":"Point"}
}