{
  "type": "Feature",
  "properties": {
    "addr:full":"Carrer de Montserrat, 2 Esparreguera Barcelona 08292",
    "addr:housenumber":"2",
    "addr:postcode":"08292",
    "addr:street":"Carrer De Montserrat",
    "iso:country":"ES",
    "sg:address":"Carrer de Montserrat, 2",
    "sg:city":"Esparreguera",
    "sg:orig_category":"Cl\u00cdnicas Dentales",
    "sg:phone":"+34 937 77 73 74",
    "sg:postcode":"08292",
    "sg:province":"Barcelona",
    "wof:name":"Consultorio Dental Doctora Vela S.c.p.",
    "wof:placetype":"venue"
},
  "geometry": {"coordinates":[1.8670150042,41.5418968201],"type":"Point"}
}