{
  "type": "Feature",
  "properties": {
    "addr:full":"Calle de Alonso Alvarado, 10 Palmas De Gran Canaria Las Palmas 35003",
    "addr:housenumber":"10",
    "addr:postcode":"35003",
    "addr:street":"Calle De Alonso Alvarado",
    "iso:country":"ES",
    "sg:address":"Calle de Alonso Alvarado, 10",
    "sg:city":"Palmas De Gran Canaria",
    "sg:orig_category":"Asesor\u00cda De Formaci\u00d3n Y Gesti\u00d3n De Personal",
    "sg:phone":"+34 928 38 44 29",
    "sg:postcode":"35003",
    "sg:province":"Las Palmas",
    "wof:name":"Penichet Penichet Jose",
    "wof:placetype":"venue"
},
  "geometry": {"coordinates":[-15.417555809,28.1099510193],"type":"Point"}
}