{
  "type": "Feature",
  "properties": {
    "addr:full":"Plaz Eguzki, 8 Mutiloagoiti Navarra 31192",
    "addr:housenumber":"8",
    "addr:postcode":"31192",
    "addr:street":"Eguzki",
    "iso:country":"ES",
    "sg:address":"Plaz Eguzki, 8",
    "sg:city":"Mutiloagoiti",
    "sg:orig_category":"Inform\u00c1tica (estudios, Servicios, Asesor\u00cda, Formaci\u00d3n)",
    "sg:phone":"+34 948 29 02 02",
    "sg:postcode":"31192",
    "sg:province":"Navarra",
    "sg:website":"www.cyc.es",
    "wof:name":"Consultoria Y Comunicaciones De Navarra S.l.",
    "wof:placetype":"venue"
},
  "geometry": {"coordinates":[-1.6151809692,42.7892303467],"type":"Point"}
}