{
  "type": "Feature",
  "properties": {
    "iso:country":"ES",
    "sg:address":"Carrer de Joan Maura,bisbe, 45",
    "sg:city":"Palma",
    "sg:orig_category":"Centros Empresariales",
    "sg:phone":"+34 971 46 11 60",
    "sg:postcode":"07005",
    "sg:province":"Islas Baleares",
    "wof:name":"Bb Servicios De Bienestar De Palma De Mallorca S.l.",
    "wof:placetype":"venue"
},
  "geometry": {"coordinates":[2.659029007,39.5772361755],"type":"Point"}
}