{
  "type": "Feature",
  "properties": {
    "addr:full":"O Rego, 4 Cambre La Coru\u00f1a 15181",
    "addr:housenumber":"4",
    "addr:postcode":"15181",
    "addr:street":"La Corun\u0303A",
    "iso:country":"ES",
    "sg:address":"O Rego, 4",
    "sg:city":"Cambre",
    "sg:classifiers":[
        {
            "category":"Taxi",
            "type":"Transportation"
        }
    ],
    "sg:phone":"+34 981 67 69 07",
    "sg:postcode":"15181",
    "sg:province":"La Coru\u00f1a",
    "wof:name":"Li\u00f1ares Li\u00f1ares Jesus",
    "wof:placetype":"venue"
},
  "geometry": {"coordinates":[-8.3443889618,43.291721344],"type":"Point"}
}