{
  "type": "Feature",
  "properties": {
    "addr:full":"Cra. Olot, 149 Manlleu Barcelona 08560",
    "addr:housenumber":"149",
    "addr:postcode":"08560",
    "addr:street":"Cra. Olot",
    "iso:country":"ES",
    "sg:address":"Cra. Olot, 149",
    "sg:city":"Manlleu",
    "sg:orig_category":"Supermercados Y Hipermercados",
    "sg:phone":"+34 938 51 05 99",
    "sg:postcode":"08560",
    "sg:province":"Barcelona",
    "wof:name":"Superficies De Alimentacion S. A.",
    "wof:placetype":"venue"
},
  "geometry": {"coordinates":[2.2844099998,42.0036239624],"type":"Point"}
}