{
  "type": "Feature",
  "properties": {
    "iso:country":"ES",
    "sg:address":"Desvio Distante, S/n",
    "sg:city":"Toledo",
    "sg:orig_category":"Empresas De Limpieza",
    "sg:phone":"+34 925 25 03 26",
    "sg:postcode":"45001",
    "sg:province":"Toledo",
    "wof:name":"Gabinete Tecnico De Sanidad Ambiental S.l.",
    "wof:placetype":"venue"
},
  "geometry": {"coordinates":[-4.025138855,39.8618774414],"type":"Point"}
}