{
  "type": "Feature",
  "properties": {
    "addr:full":"Avda Pablo Iglesias, 41 Gijon Asturias 33205",
    "addr:housenumber":"41",
    "addr:postcode":"33205",
    "addr:street":"Avda Pablo Iglesias",
    "iso:country":"ES",
    "sg:address":"Avda Pablo Iglesias, 41",
    "sg:city":"Gijon",
    "sg:classifiers":[
        {
            "category":"Autos & Motor Vehicles",
            "subcategory":"Automobile Sales",
            "type":"Retail Goods"
        }
    ],
    "sg:phone":"+34 985 33 62 85",
    "sg:postcode":"33205",
    "sg:province":"Asturias",
    "wof:name":"Autoescuela Seguridad S.l.",
    "wof:placetype":"venue"
},
  "geometry": {"coordinates":[-5.6551699638,43.5357475281],"type":"Point"}
}