{
  "type": "Feature",
  "properties": {
    "iso:country":"ES",
    "sg:address":"Carrer de Vicari Joaquim Fus, 37",
    "sg:city":"Palma",
    "sg:orig_category":"Inmobiliaria (agencias)",
    "sg:phone":"+34 971 79 63 96",
    "sg:postcode":"07006",
    "sg:province":"Islas Baleares",
    "wof:name":"Mallorca Mietborse S.l.",
    "wof:placetype":"venue"
},
  "geometry": {"coordinates":[2.6727190018,39.5603103638],"type":"Point"}
}