{
  "type": "Feature",
  "properties": {
    "iso:country":"ES",
    "sg:address":"Ctra Valencia-alicante, Km. 0087,0",
    "sg:city":"S. Juan Alicante",
    "sg:orig_category":"Caf\u00c9s, Bares, Cervecer\u00cdas",
    "sg:phone":"+34 965 65 22 90",
    "sg:postcode":"03550",
    "sg:province":"Alicante",
    "wof:name":"Fernandez Vazquez Francisco",
    "wof:placetype":"venue"
},
  "geometry": {"coordinates":[-0.4289290011,38.400390625],"type":"Point"}
}