{
  "type": "Feature",
  "properties": {
    "addr:full":"Calle de Suertes (las), 134 Estacion Madrid 28400",
    "addr:housenumber":"134 estacion",
    "addr:postcode":"28400",
    "addr:street":"Calle De Suertes Las",
    "iso:country":"ES",
    "sg:address":"Calle de Suertes (las), 134",
    "sg:city":"Estacion",
    "sg:orig_category":"Agencias Y Agentes Comerciales, Representantes",
    "sg:phone":"+34 918 51 96 65",
    "sg:postcode":"28400",
    "sg:province":"Madrid",
    "wof:name":"Bortolotti Lopez Roberto Eduardo",
    "wof:placetype":"venue"
},
  "geometry": {"coordinates":[-4.0053691864,40.6207618713],"type":"Point"}
}