{
  "type": "Feature",
  "properties": {
    "addr:full":"Ptda Carrus, 251 Elche Alicante 03205",
    "addr:housenumber":"251",
    "addr:postcode":"03205",
    "addr:street":"Ptda Carrus",
    "iso:country":"ES",
    "sg:address":"Ptda Carrus, 251",
    "sg:city":"Elche",
    "sg:orig_category":"Zapatos: Material, Suministros, Accesorios (fabricaci\u00d3n, Al Por Mayor)",
    "sg:phone":"+34 965 46 27 46",
    "sg:postcode":"03205",
    "sg:province":"Alicante",
    "wof:name":"Maquinaria Y Vias Automaticas Para Calzado S.l.",
    "wof:placetype":"venue"
},
  "geometry": {"coordinates":[-0.6995239854,38.2634811401],"type":"Point"}
}