{
  "type": "Feature",
  "properties": {
    "addr:full":"Calle de Cerca, 1 Aranzueque Guadalajara 19141",
    "addr:housenumber":"1",
    "addr:postcode":"19141",
    "addr:street":"Calle De Cerca",
    "iso:country":"ES",
    "sg:address":"Calle de Cerca, 1",
    "sg:city":"Aranzueque",
    "sg:orig_category":"Empresas De Electricidad En General",
    "sg:phone":"+34 949 29 20 25",
    "sg:postcode":"19141",
    "sg:province":"Guadalajara",
    "wof:name":"Hidroelectrica El Carmen S.l.",
    "wof:placetype":"venue"
},
  "geometry": {"coordinates":[-3.0757913589,40.4920196533],"type":"Point"}
}