{
  "type": "Feature",
  "properties": {
    "addr:full":"Carrer de Riu Ebre, S/n Prat Llobregat Barcelona 08820",
    "addr:housenumber":"s / n",
    "addr:postcode":"08820",
    "addr:street":"Carrer De Riu Ebre;Llobregat",
    "iso:country":"ES",
    "sg:address":"Carrer de Riu Ebre, S/n",
    "sg:city":"Prat Llobregat",
    "sg:orig_category":"Asociaciones, Organismos Culturales Y Socioeducativos",
    "sg:phone":"+34 933 70 19 17",
    "sg:postcode":"08820",
    "sg:province":"Barcelona",
    "wof:name":"Grup Infantil Sant Cosme",
    "wof:placetype":"venue"
},
  "geometry": {"coordinates":[2.0894129276,41.3181838989],"type":"Point"}
}