{
  "type": "Feature",
  "properties": {
    "addr:full":"Lavacolla, 1 Lavacolla La Coru\u00f1a 15820",
    "addr:housenumber":"1",
    "addr:postcode":"15820",
    "addr:street":"Lavacolla;La Corun\u0303A",
    "iso:country":"ES",
    "sg:address":"Lavacolla, 1",
    "sg:city":"Lavacolla",
    "sg:orig_category":"Promotores Constructores",
    "sg:phone":"+34 981 50 95 44",
    "sg:postcode":"15820",
    "sg:province":"La Coru\u00f1a",
    "wof:name":"Dragados S.a.",
    "wof:placetype":"venue"
},
  "geometry": {"coordinates":[-8.4459133148,42.8992347717],"type":"Point"}
}