{
  "type": "Feature",
  "properties": {
    "iso:country":"ES",
    "sg:address":"Avda Constitucion, 112",
    "sg:city":"Torrejon Ardoz",
    "sg:orig_category":"Alumbrados",
    "sg:phone":"+34 916 56 35 52",
    "sg:postcode":"28850",
    "sg:province":"Madrid",
    "wof:name":"Iluminacion Y Decoracion Garcia S.l.",
    "wof:placetype":"venue"
},
  "geometry": {"coordinates":[-3.465681076,40.458732605],"type":"Point"}
}