{
  "type": "Feature",
  "properties": {
    "iso:country":"ES",
    "sg:address":"Calle de Puentezuelas, 35",
    "sg:city":"Granada",
    "sg:orig_category":"Peluqueros: De Se\u00d1oras",
    "sg:phone":"+34 958 52 34 31",
    "sg:postcode":"18002",
    "sg:province":"Granada",
    "wof:name":"Zabaleta Cortaberria Pedro",
    "wof:placetype":"venue"
},
  "geometry": {"coordinates":[-3.6022400856,37.1740074158],"type":"Point"}
}