{
  "type": "Feature",
  "properties": {
    "addr:full":"Calle de Fuente Juliana, S/n Pozuelo De Zarzon C\u00e1ceres 10813",
    "addr:housenumber":"s / n",
    "addr:postcode":"10813",
    "addr:street":"Calle De Fuente Juliana;Ca\u0301Ceres",
    "iso:country":"ES",
    "sg:address":"Calle de Fuente Juliana, S/n",
    "sg:city":"Pozuelo De Zarzon",
    "sg:orig_category":"Cajas De Ahorro",
    "sg:phone":"+34 927 44 80 48",
    "sg:postcode":"10813",
    "sg:province":"C\u00e1ceres",
    "sg:website":"www.cajaextremadura.es",
    "wof:name":"Caja De Ahorros Y Monte De Piedad De Extremadura",
    "wof:placetype":"venue"
},
  "geometry": {"coordinates":[-6.4136738777,40.1478462219],"type":"Point"}
}