{
  "type": "Feature",
  "properties": {
    "iso:country":"ES",
    "sg:address":"Calle de Asociacion, S/n",
    "sg:city":"Molina Segura",
    "sg:orig_category":"Hospitales",
    "sg:phone":"+34 968 64 42 72",
    "sg:postcode":"30500",
    "sg:province":"Murcia",
    "wof:name":"Terapias Medicas Domiciliarias",
    "wof:placetype":"venue"
},
  "geometry": {"coordinates":[-1.2132557631,38.0607643127],"type":"Point"}
}