{
  "type": "Feature",
  "properties": {
    "iso:country":"ES",
    "sg:address":"Calle de Illas Cies, 15",
    "sg:city":"Loureiral",
    "sg:orig_category":"Distribuci\u00d3n De Petr\u00d3leo Y Derivados",
    "sg:phone":"+34 986 35 82 67",
    "sg:postcode":"36300",
    "sg:province":"Pontevedra",
    "wof:name":"Figueroa Mijon Jose Maria",
    "wof:placetype":"venue"
},
  "geometry": {"coordinates":[-8.8501644135,42.1211166382],"type":"Point"}
}