{
  "type": "Feature",
  "properties": {
    "iso:country":"ES",
    "sg:address":"Calle de Diego Ponce, 2",
    "sg:city":"Antequera",
    "sg:orig_category":"Sociedades, Compa\u00d1\u00cdas Aseguradoras",
    "sg:phone":"+34 952 84 27 58",
    "sg:postcode":"29200",
    "sg:province":"M\u00e1laga",
    "wof:name":"Leon Burgos Rafael",
    "wof:placetype":"venue"
},
  "geometry": {"coordinates":[-4.5599122047,37.0193519592],"type":"Point"}
}