{
  "type": "Feature",
  "properties": {
    "addr:full":"Pla\u00c7 Constitucio, De Sa, 3 Soller Islas Baleares 07100",
    "addr:housenumber":"3",
    "addr:postcode":"07100",
    "addr:street":"Plac\u0327 Constitucio De Sa",
    "iso:country":"ES",
    "sg:address":"Pla\u00c7 Constitucio, De Sa, 3",
    "sg:city":"Soller",
    "sg:orig_category":"Molduras, Junquillos, Listones Y Molduras Perforadas",
    "sg:phone":"+34 971 63 45 70",
    "sg:postcode":"07100",
    "sg:province":"Islas Baleares",
    "wof:name":"Valls Alberti C.b.",
    "wof:placetype":"venue"
},
  "geometry": {"coordinates":[2.7146658897,39.7662811279],"type":"Point"}
}