{
  "type": "Feature",
  "properties": {
    "iso:country":"ES",
    "sg:address":"Calle de Rufino Torres Manuel, 2",
    "sg:city":"Torrelodones",
    "sg:orig_category":"Edici\u00d3n De Diarios, Revistas, Boletines",
    "sg:phone":"+34 918 59 12 37",
    "sg:postcode":"28250",
    "sg:province":"Madrid",
    "wof:name":"Conbuenaletra Tareas Editoriales S.c.p.",
    "wof:placetype":"venue"
},
  "geometry": {"coordinates":[-3.92988801,40.5754585266],"type":"Point"}
}