{
  "type": "Feature",
  "properties": {
    "addr:full":"Carrer de Turisme, 12 Calella Barcelona 08370",
    "addr:housenumber":"12",
    "addr:postcode":"08370",
    "addr:street":"Carrer De Turisme",
    "iso:country":"ES",
    "sg:address":"Carrer de Turisme, 12",
    "sg:city":"Calella",
    "sg:orig_category":"Molduras, Junquillos, Listones Y Molduras Perforadas",
    "sg:phone":"+34 937 69 19 99",
    "sg:postcode":"08370",
    "sg:province":"Barcelona",
    "wof:name":"Jorbax S.c.p.",
    "wof:placetype":"venue"
},
  "geometry": {"coordinates":[2.6532669067,41.612247467],"type":"Point"}
}