{
  "type": "Feature",
  "properties": {
    "addr:full":"Los Robles-berron, 2 La Carrera Asturias 33186",
    "addr:housenumber":"2",
    "addr:postcode":"33186",
    "addr:street":"Robles-Berron",
    "iso:country":"ES",
    "sg:address":"Los Robles-berron, 2",
    "sg:city":"La Carrera",
    "sg:orig_category":"Electricidad, Electr\u00d3nica: Material Y Suministros (al Por Mayor)",
    "sg:phone":"+34 985 74 25 21",
    "sg:postcode":"33186",
    "sg:province":"Asturias",
    "wof:name":"Dimetronic S.a.",
    "wof:placetype":"venue"
},
  "geometry": {"coordinates":[-5.7012858391,43.3833732605],"type":"Point"}
}