{
  "type": "Feature",
  "properties": {
    "addr:full":"Carr Mar, 55 Alboraya Valencia 46120",
    "addr:housenumber":"55",
    "addr:postcode":"46120",
    "addr:street":"Carr Mar",
    "iso:country":"ES",
    "sg:address":"Carr Mar, 55",
    "sg:city":"Alboraya",
    "sg:orig_category":"Art\u00cdculos De Limpieza Y De Cocina (fabricaci\u00d3n, Al Por Mayor)",
    "sg:phone":"+34 961 85 79 23",
    "sg:postcode":"46120",
    "sg:province":"Valencia",
    "wof:name":"Exclusivas Comerciales Marcelino S. L.",
    "wof:placetype":"venue"
},
  "geometry": {"coordinates":[-0.3405140042,39.4990692139],"type":"Point"}
}