{
  "type": "Feature",
  "properties": {
    "iso:country":"ES",
    "sg:address":"Calle de Mayor, 35",
    "sg:city":"Almaden",
    "sg:orig_category":"Loter\u00cda Y T\u00d3mbola",
    "sg:phone":"+34 926 71 12 29",
    "sg:postcode":"13400",
    "sg:province":"Ciudad Real",
    "wof:name":"Yun Quintana Jose",
    "wof:placetype":"venue"
},
  "geometry": {"coordinates":[-4.8351068497,38.7758483887],"type":"Point"}
}