{
  "type": "Feature",
  "properties": {
    "addr:full":"Calle de Ruiz Mu\u00d1iz, 62 Ejido Las Palmas 35200",
    "addr:housenumber":"62 ejido",
    "addr:postcode":"35200",
    "addr:street":"Calle De Ruiz Mun\u0303Iz;Las Palmas",
    "iso:country":"ES",
    "sg:address":"Calle de Ruiz Mu\u00d1iz, 62",
    "sg:city":"Ejido",
    "sg:orig_category":"Frutas Y Legumbres Frescas (al Por Mayor)",
    "sg:phone":"+34 928 69 16 47",
    "sg:postcode":"35200",
    "sg:province":"Las Palmas",
    "wof:name":"Mu\u00f1oz Rodriguez Juan",
    "wof:placetype":"venue"
},
  "geometry": {"coordinates":[-15.4264154434,27.990732193],"type":"Point"}
}