{
  "type": "Feature",
  "properties": {
    "iso:country":"ES",
    "sg:address":"Plaz Luca De Tena, 3",
    "sg:city":"Madrid",
    "sg:orig_category":"Venta, Instalaci\u00d3n, Reparaci\u00d3n De Antenas Para Televisi\u00d3n",
    "sg:phone":"+34 915 39 03 21",
    "sg:postcode":"28045",
    "sg:province":"Madrid",
    "wof:name":"Rufino Lusilla Instalaciones Electricas S.l.",
    "wof:placetype":"venue"
},
  "geometry": {"coordinates":[-3.6930499077,40.4021911621],"type":"Point"}
}