{
  "type": "Feature",
  "properties": {
    "addr:full":"Calle de Francisco Pacheco, 40 Sevilla Sevilla 41005",
    "addr:housenumber":"40",
    "addr:postcode":"41005",
    "addr:street":"Calle De Francisco Pacheco",
    "iso:country":"ES",
    "sg:address":"Calle de Francisco Pacheco, 40",
    "sg:city":"Sevilla",
    "sg:orig_category":"Centros Empresariales",
    "sg:phone":"+34 954 57 40 81",
    "sg:postcode":"41005",
    "sg:province":"Sevilla",
    "wof:name":"Perez Rubio Oscar",
    "wof:placetype":"venue"
},
  "geometry": {"coordinates":[-5.9634046555,37.3829193115],"type":"Point"}
}