{
  "type": "Feature",
  "properties": {
    "iso:country":"ES",
    "sg:address":"Rua Conchido, S/n",
    "sg:city":"Serra De Outes",
    "sg:classifiers":[
        {
            "category":"Autos & Motor Vehicles",
            "subcategory":"Automobile Sales",
            "type":"Retail Goods"
        }
    ],
    "sg:phone":"+34 981 85 00 18",
    "sg:postcode":"15230",
    "sg:province":"La Coru\u00f1a",
    "wof:name":"Calo Outon Francisco",
    "wof:placetype":"venue"
},
  "geometry": {"coordinates":[-8.9030036926,42.8408432007],"type":"Point"}
}