{
  "type": "Feature",
  "properties": {
    "addr:full":"Calle de San Vicente, 6 Ayora Valencia 46620",
    "addr:housenumber":"6",
    "addr:postcode":"46620",
    "addr:street":"Calle De San Vicente",
    "iso:country":"ES",
    "sg:address":"Calle de San Vicente, 6",
    "sg:city":"Ayora",
    "sg:orig_category":"Art\u00cdculos Funerarios (al Por Menor)",
    "sg:phone":"+34 961 89 02 44",
    "sg:postcode":"46620",
    "sg:province":"Valencia",
    "wof:name":"Martinez Teruel Francisco",
    "wof:placetype":"venue"
},
  "geometry": {"coordinates":[-1.0542910099,39.0598068237],"type":"Point"}
}