{
  "type": "Feature",
  "properties": {
    "iso:country":"ES",
    "sg:address":"Pl Abastos, S/n",
    "sg:city":"Rojales",
    "sg:orig_category":"Caf\u00c9s, Bares, Cervecer\u00cdas",
    "sg:phone":"+34 966 71 30 46",
    "sg:postcode":"03170",
    "sg:province":"Alicante",
    "wof:name":"Senent Zaragoza Francisca",
    "wof:placetype":"venue"
},
  "geometry": {"coordinates":[-0.7155489922,38.0730285645],"type":"Point"}
}