{
  "type": "Feature",
  "properties": {
    "iso:country":"ES",
    "sg:address":"Calle de Norte, 2",
    "sg:city":"Cabra",
    "sg:orig_category":"Muebles, Minoristas",
    "sg:phone":"+34 957 52 14 93",
    "sg:postcode":"14940",
    "sg:province":"C\u00f3rdoba",
    "wof:name":"Mesa Carnerero Isabel",
    "wof:placetype":"venue"
},
  "geometry": {"coordinates":[-4.4447789192,37.4740715027],"type":"Point"}
}