{
  "type": "Feature",
  "properties": {
    "iso:country":"ES",
    "sg:address":"Calle de Carlos Martinez-barbeito Moras, 14",
    "sg:city":"Coru\u00d1a",
    "sg:orig_category":"Andamiajes Y Escaleras De Mano (fabricaci\u00d3n, Al Por Mayor)",
    "sg:phone":"+34 981 17 00 80",
    "sg:postcode":"15009",
    "sg:province":"La Coru\u00f1a",
    "wof:name":"Rmd Kwikform Iberica S.a.",
    "wof:placetype":"venue"
},
  "geometry": {"coordinates":[-8.4049472809,43.3422851562],"type":"Point"}
}