{
  "type": "Feature",
  "properties": {
    "addr:full":"Calle de Ibiza, S/n Estepona M\u00e1laga 29680",
    "addr:housenumber":"s",
    "addr:postcode":"29680",
    "addr:street":"Calle De Ibiza;/ N;Ma\u0301Laga",
    "iso:country":"ES",
    "sg:address":"Calle de Ibiza, S/n",
    "sg:city":"Estepona",
    "sg:orig_category":"Estudios, Instalaci\u00d3n De Climatizaci\u00d3n",
    "sg:phone":"+34 952 80 40 64",
    "sg:postcode":"29680",
    "sg:province":"M\u00e1laga",
    "wof:name":"Miguel Campano S.l.",
    "wof:placetype":"venue"
},
  "geometry": {"coordinates":[-5.1450138092,36.4305038452],"type":"Point"}
}