{
  "type": "Feature",
  "properties": {
    "iso:country":"ES",
    "sg:address":"Calle de Camelias Las, 30",
    "sg:city":"Nueva Andalucia",
    "sg:orig_category":"Agencias Y Agentes Comerciales, Representantes",
    "sg:phone":"+34 951 31 92 23",
    "sg:postcode":"29660",
    "sg:province":"M\u00e1laga",
    "wof:name":"Vivo Carrasco Pedro",
    "wof:placetype":"venue"
},
  "geometry": {"coordinates":[-4.9660391808,36.4936408997],"type":"Point"}
}