{
  "type": "Feature",
  "properties": {
    "iso:country":"ES",
    "sg:address":"Calle de Relatores, 4",
    "sg:city":"Madrid",
    "sg:orig_category":"Grafistas",
    "sg:phone":"+34 913 69 40 21",
    "sg:postcode":"28012",
    "sg:province":"Madrid",
    "sg:website":"www.cuartalinea.es",
    "wof:name":"Reprograficas Cuarta Linea S.l.",
    "wof:placetype":"venue"
},
  "geometry": {"coordinates":[-3.7031490803,40.4136772156],"type":"Point"}
}