{
  "type": "Feature",
  "properties": {
    "iso:country":"ES",
    "sg:address":"Carrer de Progres, 69",
    "sg:city":"Gava",
    "sg:orig_category":"Molduras, Junquillos, Listones Y Molduras Perforadas",
    "sg:phone":"+34 936 38 22 52",
    "sg:postcode":"08850",
    "sg:province":"Barcelona",
    "wof:name":"Laorden Primero S.l.",
    "wof:placetype":"venue"
},
  "geometry": {"coordinates":[2.0115170479,41.2989578247],"type":"Point"}
}