{
  "type": "Feature",
  "properties": {
    "iso:country":"ES",
    "sg:address":"Av Esplugues, 74",
    "sg:city":"Barcelona",
    "sg:orig_category":"Florister\u00cdas",
    "sg:phone":"+34 932 03 52 22",
    "sg:postcode":"08034",
    "sg:province":"Barcelona",
    "sg:website":"www.conillas.com",
    "wof:name":"Conillas Garden Center S.l.",
    "wof:placetype":"venue"
},
  "geometry": {"coordinates":[2.109513998,41.3900413513],"type":"Point"}
}