{
  "type": "Feature",
  "properties": {
    "iso:country":"ES",
    "sg:address":"Carrer de Bolero, 20",
    "sg:city":"Palma",
    "sg:orig_category":"Perfumer\u00cda Y Cosm\u00c9tica (fabricaci\u00d3n, Al Por Mayor)",
    "sg:phone":"+34 971 75 94 43",
    "sg:postcode":"07010",
    "sg:province":"Islas Baleares",
    "wof:name":"J. C. Prolimper S.l.",
    "wof:placetype":"venue"
},
  "geometry": {"coordinates":[2.6462380886,39.5923271179],"type":"Point"}
}