{
  "type": "Feature",
  "properties": {
    "iso:country":"ES",
    "sg:address":"Avda Gomez Laguna, 6",
    "sg:city":"Zaragoza",
    "sg:orig_category":"Electricidad: Instaladores",
    "sg:phone":"+34 976 35 27 61",
    "sg:postcode":"50009",
    "sg:province":"Zaragoza",
    "wof:name":"Delgado Lalinde Jose Alberto",
    "wof:placetype":"venue"
},
  "geometry": {"coordinates":[-0.907671988,41.6433486938],"type":"Point"}
}