{
  "type": "Feature",
  "properties": {
    "iso:country":"ES",
    "sg:address":"Carrer de Garbi, 4",
    "sg:city":"Can Volart",
    "sg:orig_category":"Maquinaria Para Industrias Diversas",
    "sg:phone":"+34 935 62 10 54",
    "sg:postcode":"08150",
    "sg:province":"Barcelona",
    "wof:name":"Artemain S.l.",
    "wof:placetype":"venue"
},
  "geometry": {"coordinates":[2.2930374146,41.6836967468],"type":"Point"}
}