{
  "type": "Feature",
  "properties": {
    "addr:full":"Cmn. Ca\u00f1adillas, 3 Daimiel Ciudad Real 13250",
    "addr:housenumber":"3",
    "addr:postcode":"13250",
    "addr:street":"Can\u0303Adillas",
    "iso:country":"ES",
    "sg:address":"Cmn. Ca\u00f1adillas, 3",
    "sg:city":"Daimiel",
    "sg:orig_category":"Aparatos E Instalaci\u00d3n De Regad\u00cdos",
    "sg:phone":"+34 926 85 36 99",
    "sg:postcode":"13250",
    "sg:province":"Ciudad Real",
    "wof:name":"Vazquez De Aguedos Aguirre Victor",
    "wof:placetype":"venue"
},
  "geometry": {"coordinates":[-3.6021900177,39.0659408569],"type":"Point"}
}