{
  "type": "Feature",
  "properties": {
    "addr:full":"Avda Lisboa (de), 9 Coslada Madrid 28820",
    "addr:housenumber":"9",
    "addr:postcode":"28820",
    "addr:street":"Avda Lisboa De",
    "iso:country":"ES",
    "sg:address":"Avda Lisboa (de), 9",
    "sg:city":"Coslada",
    "sg:orig_category":"Centros De Educaci\u00d3n Especial",
    "sg:phone":"+34 916 73 80 21",
    "sg:postcode":"28820",
    "sg:province":"Madrid",
    "wof:name":"Colegio Publico Virgen Del Amor Hermoso",
    "wof:placetype":"venue"
},
  "geometry": {"coordinates":[-3.542140007,40.4172554016],"type":"Point"}
}