{
  "type": "Feature",
  "properties": {
    "iso:country":"ES",
    "sg:address":"Calle de General Moscardo, 3",
    "sg:city":"Talavera Reina",
    "sg:orig_category":"Equipo De Refrigeraci\u00d3n Industrial",
    "sg:phone":"+34 925 82 46 57",
    "sg:postcode":"45600",
    "sg:province":"Toledo",
    "wof:name":"Diaz Vaquerizo Constantino",
    "wof:placetype":"venue"
},
  "geometry": {"coordinates":[-4.8208098412,39.9626808167],"type":"Point"}
}