{
  "type": "Feature",
  "properties": {
    "addr:full":"Poligono 3, S/n Algaida Islas Baleares 07210",
    "addr:housenumber":"s / n",
    "addr:postcode":"07210",
    "addr:street":"Poligono 3",
    "iso:country":"ES",
    "sg:address":"Poligono 3, S/n",
    "sg:city":"Algaida",
    "sg:orig_category":"Agricultura: Abastecimiento Y Cosechado (negocio)",
    "sg:phone":"+34 971 18 04 94",
    "sg:postcode":"07210",
    "sg:province":"Islas Baleares",
    "wof:name":"Son Pujol Vell S.l.",
    "wof:placetype":"venue"
},
  "geometry": {"coordinates":[2.8951790333,39.5589103699],"type":"Point"}
}