{
  "type": "Feature",
  "properties": {
    "addr:full":"Ctra Picanya, 18 Paiporta Valencia 46200",
    "addr:housenumber":"18",
    "addr:postcode":"46200",
    "addr:street":"Ctra Picanya",
    "iso:country":"ES",
    "sg:address":"Ctra Picanya, 18",
    "sg:city":"Paiporta",
    "sg:orig_category":"Plomeros",
    "sg:phone":"+34 963 97 20 64",
    "sg:postcode":"46200",
    "sg:province":"Valencia",
    "wof:name":"Ribes Instalaciones Y Suministros S.l.",
    "wof:placetype":"venue"
},
  "geometry": {"coordinates":[-0.422807008,39.4295387268],"type":"Point"}
}