{
  "type": "Feature",
  "properties": {
    "addr:full":"Carrer de Mare De Deu Del Carme, 122 S. Adria Besos Barcelona 08930",
    "addr:housenumber":"122",
    "addr:postcode":"08930",
    "addr:street":"Carrer De Mare De Deu Del Carme;S. Adria Besos Barcelona",
    "iso:country":"ES",
    "sg:address":"Carrer de Mare De Deu Del Carme, 122",
    "sg:city":"S. Adria Besos",
    "sg:orig_category":"Alimentaci\u00d3n General (al Por Menor)",
    "sg:phone":"+34 934 62 03 68",
    "sg:postcode":"08930",
    "sg:province":"Barcelona",
    "wof:name":"Jimenez Zea Ana",
    "wof:placetype":"venue"
},
  "geometry": {"coordinates":[2.2294745445,41.423789978],"type":"Point"}
}