{
  "type": "Feature",
  "properties": {
    "iso:country":"ES",
    "sg:address":"Calle de Muro Prolongacion, 8",
    "sg:city":"Ejea De Los Caballeros",
    "sg:orig_category":"Tapicer\u00cdas",
    "sg:phone":"+34 976 66 01 57",
    "sg:postcode":"50600",
    "sg:province":"Zaragoza",
    "wof:name":"Angles Rofes Juan",
    "wof:placetype":"venue"
},
  "geometry": {"coordinates":[-1.1331256628,42.1274681091],"type":"Point"}
}