{
  "type": "Feature",
  "properties": {
    "addr:full":"Avda Habana (de La), 87 Ourense Ourense 32004",
    "addr:housenumber":"87",
    "addr:postcode":"32004",
    "addr:street":"Avda Habana De La",
    "iso:country":"ES",
    "sg:address":"Avda Habana (de La), 87",
    "sg:city":"Ourense",
    "sg:orig_category":"Ense\u00d1anza Variada",
    "sg:phone":"+34 988 23 23 53",
    "sg:postcode":"32004",
    "sg:province":"Ourense",
    "wof:name":"Academia San Roque S. L.",
    "wof:placetype":"venue"
},
  "geometry": {"coordinates":[-7.8615951538,42.3418083191],"type":"Point"}
}