{
  "type": "Feature",
  "properties": {
    "addr:full":"Carrer de Cementiri Nou, 11 Sentmenat Barcelona 08181",
    "addr:housenumber":"11",
    "addr:postcode":"08181",
    "addr:street":"Carrer De Cementiri Nou",
    "iso:country":"ES",
    "sg:address":"Carrer de Cementiri Nou, 11",
    "sg:city":"Sentmenat",
    "sg:orig_category":"Abrasivos Y Superabrasivos (fabricaci\u00d3n, Al Por Mayor)",
    "sg:phone":"+34 937 15 13 42",
    "sg:postcode":"08181",
    "sg:province":"Barcelona",
    "wof:name":"Iberabrasivos Sll",
    "wof:placetype":"venue"
},
  "geometry": {"coordinates":[2.1432650089,41.6143264771],"type":"Point"}
}