{
  "type": "Feature",
  "properties": {
    "addr:full":"Calle de Heros, 22 Bilbao Vizcaya 48009",
    "addr:housenumber":"22",
    "addr:postcode":"48009",
    "addr:street":"Calle De Heros",
    "iso:country":"ES",
    "sg:address":"Calle de Heros, 22",
    "sg:city":"Bilbao",
    "sg:orig_category":"Cl\u00cdnicas M\u00c9dicas",
    "sg:phone":"+34 944 23 52 14",
    "sg:postcode":"48009",
    "sg:province":"Vizcaya",
    "wof:name":"Mencia Martinez Luis",
    "wof:placetype":"venue"
},
  "geometry": {"coordinates":[-2.9327340126,43.264995575],"type":"Point"}
}