{
  "type": "Feature",
  "properties": {
    "iso:country":"ES",
    "sg:address":"Calle de Puerto De La Cruz Verde, 11",
    "sg:city":"Madrid",
    "sg:orig_category":"Guarder\u00cdas",
    "sg:phone":"+34 914 68 57 83",
    "sg:postcode":"28045",
    "sg:province":"Madrid",
    "wof:name":"Escuela Infantil Cosquillas S.l.",
    "wof:placetype":"venue"
},
  "geometry": {"coordinates":[-3.6867580414,40.3871574402],"type":"Point"}
}