{
  "type": "Feature",
  "properties": {
    "addr:full":"Calle de Aldamiz Etxebarria Kalea, 4 Lekeitio Vizcaya 48280",
    "addr:housenumber":"4",
    "addr:postcode":"48280",
    "addr:street":"Calle De Aldamiz Etxebarria Kalea",
    "iso:country":"ES",
    "sg:address":"Calle de Aldamiz Etxebarria Kalea, 4",
    "sg:city":"Lekeitio",
    "sg:orig_category":"Mec\u00c1nico Del Autom\u00d3vil",
    "sg:phone":"+34 944 65 31 84",
    "sg:postcode":"48280",
    "sg:province":"Vizcaya",
    "wof:name":"I\u00f1igo Badiola Osoro (talleres Arbaza)",
    "wof:placetype":"venue"
},
  "geometry": {"coordinates":[-2.5086004734,43.3624420166],"type":"Point"}
}