{
  "type": "Feature",
  "properties": {
    "iso:country":"ES",
    "sg:address":"Plaz Ayuntamiento, 2",
    "sg:city":"Viso Del Alcor",
    "sg:orig_category":"Producci\u00d3n, Venta De Productos De Agricultura Biol\u00d3gica",
    "sg:phone":"+34 955 94 50 05",
    "sg:postcode":"41520",
    "sg:province":"Sevilla",
    "wof:name":"Leon Cuesta Mercedes",
    "wof:placetype":"venue"
},
  "geometry": {"coordinates":[-5.7201328278,37.3874588013],"type":"Point"}
}