{
  "type": "Feature",
  "properties": {
    "addr:full":"Ctra. Nijar, 26 Almeria Almer\u00eda 04006",
    "addr:housenumber":"26",
    "addr:postcode":"04006",
    "addr:street":"Ctra. Nijar",
    "iso:country":"ES",
    "sg:address":"Ctra. Nijar, 26",
    "sg:city":"Almeria",
    "sg:orig_category":"Abogados",
    "sg:phone":"+34 950 22 48 92",
    "sg:postcode":"04006",
    "sg:province":"Almer\u00eda",
    "wof:name":"Ruano Ferron Francisco",
    "wof:placetype":"venue"
},
  "geometry": {"coordinates":[-2.4514141083,36.84532547],"type":"Point"}
}