{
  "type": "Feature",
  "properties": {
    "iso:country":"ES",
    "sg:address":"Rond Muralla (da), 108",
    "sg:city":"Lugo",
    "sg:orig_category":"Comercio De Piezas De Recambio Y De Accesorios De Veh\u00cdculos, Veh\u00cdculos Industriales",
    "sg:phone":"+34 982 25 06 38",
    "sg:postcode":"27004",
    "sg:province":"Lugo",
    "wof:name":"Comercial Auto Vazquez S. L.",
    "wof:placetype":"venue"
},
  "geometry": {"coordinates":[-7.569381237,43.0095176697],"type":"Point"}
}