{
  "type": "Feature",
  "properties": {
    "iso:country":"ES",
    "sg:address":"Calle de Benisaet, 11",
    "sg:city":"Torrent",
    "sg:orig_category":"Plomeros",
    "sg:phone":"+34 961 55 39 25",
    "sg:postcode":"46900",
    "sg:province":"Valencia",
    "wof:name":"Picazo Serrano Diego",
    "wof:placetype":"venue"
},
  "geometry": {"coordinates":[-0.461006999,39.441986084],"type":"Point"}
}