{
  "type": "Feature",
  "properties": {
    "iso:country":"ES",
    "sg:address":"Rua Rosalia De Castro, 24",
    "sg:city":"Burela",
    "sg:orig_category":"Ropa Para Se\u00d1oras Y Caballeros (al Por Menor)",
    "sg:phone":"+34 982 58 62 81",
    "sg:postcode":"27880",
    "sg:province":"Lugo",
    "wof:name":"Veiga Rego Maria Socorro",
    "wof:placetype":"venue"
},
  "geometry": {"coordinates":[-7.3609890938,43.6615982056],"type":"Point"}
}