{
  "type": "Feature",
  "properties": {
    "addr:full":"Ctra Almarcha, 29 S. Clemente Cuenca 16600",
    "addr:housenumber":"29",
    "addr:postcode":"16600",
    "addr:street":"Ctra Almarcha;S. Clemente Cuenca",
    "iso:country":"ES",
    "sg:address":"Ctra Almarcha, 29",
    "sg:city":"S. Clemente",
    "sg:orig_category":"Extinci\u00d3n De Incendios: Material Y Suministros (fabricaci\u00d3n, Al Por Mayor)",
    "sg:phone":"+34 969 30 10 29",
    "sg:postcode":"16600",
    "sg:province":"Cuenca",
    "wof:name":"Inema Exatel S.l.",
    "wof:placetype":"venue"
},
  "geometry": {"coordinates":[-2.4270188808,39.3993186951],"type":"Point"}
}