{
  "type": "Feature",
  "properties": {
    "addr:full":"La Cosa Plaza, 25 S. Pedro Manrique Soria 42174",
    "addr:postcode":"42174",
    "addr:street":"25 S. Pedro Manrique",
    "iso:country":"ES",
    "sg:address":"La Cosa Plaza, 25",
    "sg:city":"S. Pedro Manrique",
    "sg:orig_category":"Peluquer\u00cdas, Peluquer\u00cda Mixta",
    "sg:phone":"+34 975 38 10 30",
    "sg:postcode":"42174",
    "sg:province":"Soria",
    "wof:name":"Miguel Garcia Laura",
    "wof:placetype":"venue"
},
  "geometry": {"coordinates":[-2.2307789326,42.029209137],"type":"Point"}
}