{
  "type": "Feature",
  "properties": {
    "addr:full":"Calle de Cardenal Vera, 48 Alzira Valencia 46600",
    "addr:housenumber":"48",
    "addr:postcode":"46600",
    "addr:street":"Calle De Cardenal Vera",
    "iso:country":"ES",
    "sg:address":"Calle de Cardenal Vera, 48",
    "sg:city":"Alzira",
    "sg:orig_category":"Molduras, Junquillos, Listones Y Molduras Perforadas",
    "sg:phone":"+34 962 41 00 42",
    "sg:postcode":"46600",
    "sg:province":"Valencia",
    "wof:name":"Cabrerizo Cerdillo Francisco",
    "wof:placetype":"venue"
},
  "geometry": {"coordinates":[-0.4341003895,39.1469116211],"type":"Point"}
}