{
  "type": "Feature",
  "properties": {
    "iso:country":"ES",
    "sg:address":"Avda Portugal (de), 17",
    "sg:city":"Avila",
    "sg:orig_category":"Art\u00cdculos De Regalo (al Por Menor)",
    "sg:phone":"+34 920 25 17 96",
    "sg:postcode":"05001",
    "sg:province":"\u00c1vila",
    "wof:name":"Gonzalez Perez Maria Del Carmen",
    "wof:placetype":"venue"
},
  "geometry": {"coordinates":[-4.6931099892,40.6576347351],"type":"Point"}
}