{
  "type": "Feature",
  "properties": {
    "addr:full":"Calle de Cuarzo, 4 Alacant Alicante 03014",
    "addr:housenumber":"4",
    "addr:postcode":"03014",
    "addr:street":"Calle De Cuarzo",
    "iso:country":"ES",
    "sg:address":"Calle de Cuarzo, 4",
    "sg:city":"Alacant",
    "sg:orig_category":"Iglesia Cat\u00d3lica",
    "sg:phone":"+34 965 17 71 91",
    "sg:postcode":"03014",
    "sg:province":"Alicante",
    "wof:name":"Parroquia Nuestra Se\u00d1ora De Los Desamparados",
    "wof:placetype":"venue"
},
  "geometry": {"coordinates":[-0.4860362113,38.3731613159],"type":"Point"}
}