{
  "type": "Feature",
  "properties": {
    "iso:country":"ES",
    "sg:address":"Calle de Grande, 2",
    "sg:city":"Quintanar Orden",
    "sg:orig_category":"Abogados",
    "sg:phone":"+34 925 18 10 70",
    "sg:postcode":"45800",
    "sg:province":"Toledo",
    "wof:name":"Benitez Jimenez Jose Luis",
    "wof:placetype":"venue"
},
  "geometry": {"coordinates":[-3.0434610844,39.5911483765],"type":"Point"}
}