{
  "type": "Feature",
  "properties": {
    "iso:country":"ES",
    "sg:address":"Avgd Ermita (la), 11",
    "sg:city":"Canals",
    "sg:orig_category":"Ense\u00d1anza: Profesiones Art\u00cdsticas",
    "sg:phone":"+34 962 24 61 16",
    "sg:postcode":"46650",
    "sg:province":"Valencia",
    "wof:name":"Sanchis Barbera Jose",
    "wof:placetype":"venue"
},
  "geometry": {"coordinates":[-0.5790200233,38.9646186829],"type":"Point"}
}