{
  "type": "Feature",
  "properties": {
    "addr:full":"San Gregorio, 10 Iru\u00f1a Navarra 31001",
    "addr:housenumber":"10",
    "addr:postcode":"31001",
    "addr:street":"San Gregorio",
    "iso:country":"ES",
    "sg:address":"San Gregorio, 10",
    "sg:city":"Iru\u00f1a",
    "sg:orig_category":"Equitaci\u00d3n: Guarnicioner\u00cda, Equipo (al Por Menor)",
    "sg:phone":"+34 948 22 25 24",
    "sg:postcode":"31001",
    "sg:province":"Navarra",
    "wof:name":"Fernandez Sola Jesus Antonio",
    "wof:placetype":"venue"
},
  "geometry": {"coordinates":[-1.6460649967,42.815788269],"type":"Point"}
}