{
  "type": "Feature",
  "properties": {
    "addr:full":"Calle de Arnao, 3 S.gregorio Las Palmas 35200",
    "addr:housenumber":"3",
    "addr:postcode":"35200",
    "addr:street":"Calle De Arnao;Las Palmas",
    "iso:country":"ES",
    "sg:address":"Calle de Arnao, 3",
    "sg:city":"S.gregorio",
    "sg:orig_category":"Fotocopias, Reprograf\u00cda",
    "sg:phone":"+34 928 68 42 97",
    "sg:postcode":"35200",
    "sg:province":"Las Palmas",
    "wof:name":"Copy Telde S.l.",
    "wof:placetype":"venue"
},
  "geometry": {"coordinates":[-15.4300060272,28.1248226166],"type":"Point"}
}