{
  "type": "Feature",
  "properties": {
    "iso:country":"ES",
    "sg:address":"Plaz Pio Xii De, 5",
    "sg:city":"Donostia-san Sebastian",
    "sg:orig_category":"Abogados",
    "sg:phone":"+34 943 47 08 48",
    "sg:postcode":"20010",
    "sg:province":"Guip\u00f9zcoa",
    "wof:name":"Calvo Serrulla Maria Mercedes",
    "wof:placetype":"venue"
},
  "geometry": {"coordinates":[-1.9798990488,43.3073768616],"type":"Point"}
}