{
  "type": "Feature",
  "properties": {
    "iso:country":"ES",
    "sg:address":"Reboredo, S/n",
    "sg:city":"Sillobre",
    "sg:orig_category":"Explotaci\u00d3n De Canteras",
    "sg:phone":"+34 981 34 04 26",
    "sg:postcode":"15509",
    "sg:province":"La Coru\u00f1a",
    "wof:name":"Aridos De Reboredo Sociedad Anonima",
    "wof:placetype":"venue"
},
  "geometry": {"coordinates":[-8.3959693909,43.3714904785],"type":"Point"}
}