{
  "type": "Feature",
  "properties": {
    "addr:full":"Calle de Vereda De Los Chopos (de La), 18 Alcobendas Madrid 28109",
    "addr:housenumber":"18",
    "addr:postcode":"28109",
    "addr:street":"Calle De Vereda De Los Chopos De La",
    "iso:country":"ES",
    "sg:address":"Calle de Vereda De Los Chopos (de La), 18",
    "sg:city":"Alcobendas",
    "sg:orig_category":"M\u00c9dicos: Pediatr\u00cda. Enfermedades De Los Ni\u00d1os",
    "sg:phone":"+34 916 50 00 36",
    "sg:postcode":"28109",
    "sg:province":"Madrid",
    "wof:name":"Garrido-lestache Cabrera Antonio",
    "wof:placetype":"venue"
},
  "geometry": {"coordinates":[-3.6288280487,40.5096664429],"type":"Point"}
}