{
  "type": "Feature",
  "properties": {
    "addr:full":"Calle de Padre Arnau, S/n Biar Alicante 03410",
    "addr:housenumber":"s / n",
    "addr:postcode":"03410",
    "addr:street":"Calle De Padre Arnau",
    "iso:country":"ES",
    "sg:address":"Calle de Padre Arnau, S/n",
    "sg:city":"Biar",
    "sg:orig_category":"Reposter\u00cdas",
    "sg:phone":"+34 965 81 06 70",
    "sg:postcode":"03410",
    "sg:province":"Alicante",
    "wof:name":"Panaderia Vr S.l.",
    "wof:placetype":"venue"
},
  "geometry": {"coordinates":[-0.7638139725,38.6286659241],"type":"Point"}
}