{
  "type": "Feature",
  "properties": {
    "addr:full":"Cami Cinc Senies (de Les), 88 Mataro Barcelona 08301",
    "addr:postcode":"08301",
    "addr:street":"Cinc",
    "iso:country":"ES",
    "sg:address":"Cami Cinc Senies (de Les), 88",
    "sg:city":"Mataro",
    "sg:orig_category":"Alquiler De Gr\u00daas",
    "sg:phone":"+34 937 55 15 00",
    "sg:postcode":"08301",
    "sg:province":"Barcelona",
    "wof:name":"Gruas Serrat S. A.",
    "wof:placetype":"venue"
},
  "geometry": {"coordinates":[2.4587700367,41.5489845276],"type":"Point"}
}