{
  "type": "Feature",
  "properties": {
    "addr:full":"Afueras, S/n Cala D'or Islas Baleares 07660",
    "addr:postcode":"07660",
    "addr:street":"Afueras S / N",
    "iso:country":"ES",
    "sg:address":"Afueras, S/n",
    "sg:city":"Cala D'or",
    "sg:orig_category":"Aguas (distribuci\u00d3n, Servicios)",
    "sg:phone":"+34 971 64 83 56",
    "sg:postcode":"07660",
    "sg:province":"Islas Baleares",
    "wof:name":"U.t.e. Moncobra-socamex",
    "wof:placetype":"venue"
},
  "geometry": {"coordinates":[2.9117100239,39.6136398315],"type":"Point"}
}