{
  "type": "Feature",
  "properties": {
    "iso:country":"ES",
    "sg:address":"Carr Sant Pere, 9",
    "sg:city":"Algemesi",
    "sg:orig_category":"Carnicer\u00cdas, Carnicer\u00cdas",
    "sg:phone":"+34 962 42 09 65",
    "sg:postcode":"46680",
    "sg:province":"Valencia",
    "wof:name":"Canet Soler Sonia",
    "wof:placetype":"venue"
},
  "geometry": {"coordinates":[-0.4335309863,39.1941337585],"type":"Point"}
}