{
  "type": "Feature",
  "properties": {
    "addr:full":"Calle de Gabriel Aresti, 11 Santurtzi Vizcaya 48980",
    "addr:housenumber":"11",
    "addr:postcode":"48980",
    "addr:street":"Calle De Gabriel Aresti",
    "iso:country":"ES",
    "sg:address":"Calle de Gabriel Aresti, 11",
    "sg:city":"Santurtzi",
    "sg:orig_category":"Lencer\u00cda Femenina, Corseter\u00cda, Trajes De Ba\u00d1o (al Por Menor)",
    "sg:phone":"+34 944 01 30 82",
    "sg:postcode":"48980",
    "sg:province":"Vizcaya",
    "wof:name":"Taraska",
    "wof:placetype":"venue"
},
  "geometry": {"coordinates":[-3.0326490402,43.3266181946],"type":"Point"}
}