{
  "type": "Feature",
  "properties": {
    "addr:full":"Calle de Mercurio, 15 Humanes De Madrid Madrid 28970",
    "addr:housenumber":"15",
    "addr:postcode":"28970",
    "addr:street":"Calle De Mercurio",
    "iso:country":"ES",
    "sg:address":"Calle de Mercurio, 15",
    "sg:city":"Humanes De Madrid",
    "sg:orig_category":"Vidrio, Fabricaci\u00d3n Y Comercio",
    "sg:phone":"+34 916 15 41 28",
    "sg:postcode":"28970",
    "sg:province":"Madrid",
    "wof:name":"Vidriforma S.l",
    "wof:placetype":"venue"
},
  "geometry": {"coordinates":[-3.8235359192,40.2697601318],"type":"Point"}
}