{
  "type": "Feature",
  "properties": {
    "addr:full":"Avda Parque, 3 Viso C\u00f3rdoba 14470",
    "addr:housenumber":"3",
    "addr:postcode":"14470",
    "addr:street":"Avda Parque;Co\u0301Rdoba",
    "iso:country":"ES",
    "sg:address":"Avda Parque, 3",
    "sg:city":"Viso",
    "sg:orig_category":"Guarder\u00cdas",
    "sg:phone":"+34 957 12 72 16",
    "sg:postcode":"14470",
    "sg:province":"C\u00f3rdoba",
    "wof:name":"Ayuntamiento De El Viso",
    "wof:placetype":"venue"
},
  "geometry": {"coordinates":[-4.9518370628,38.4823265076],"type":"Point"}
}