{
  "type": "Feature",
  "properties": {
    "addr:full":"Avda Caballeria Espa\u00d1ola, 3 Alcala Henares Madrid 28805",
    "addr:housenumber":"3",
    "addr:postcode":"28805",
    "addr:street":"Avda Caballeria Espan\u0303Ola",
    "iso:country":"ES",
    "sg:address":"Avda Caballeria Espa\u00d1ola, 3",
    "sg:city":"Alcala Henares",
    "sg:orig_category":"Asociaciones Y Clubs Deportivos",
    "sg:phone":"+34 918 89 56 51",
    "sg:postcode":"28805",
    "sg:province":"Madrid",
    "wof:name":"Lee  Suk-jae",
    "wof:placetype":"venue"
},
  "geometry": {"coordinates":[-3.3594040871,40.487575531],"type":"Point"}
}