{
  "type": "Feature",
  "properties": {
    "addr:full":"Calle de Fuente Redonda, S/n Mengibar Ja\u00e9n 23620",
    "addr:housenumber":"/ n",
    "addr:postcode":"23620",
    "addr:street":"Calle De Fuente Redonda S;Mengibar Jae\u0301N",
    "iso:country":"ES",
    "sg:address":"Calle de Fuente Redonda, S/n",
    "sg:city":"Mengibar",
    "sg:orig_category":"Cooperativas Agr\u00cdcolas",
    "sg:phone":"+34 953 37 08 80",
    "sg:postcode":"23620",
    "sg:province":"Ja\u00e9n",
    "wof:name":"Sociedad Cooperat Andaluza San Pedro Apostol",
    "wof:placetype":"venue"
},
  "geometry": {"coordinates":[-3.8137218952,37.9724693298],"type":"Point"}
}