{
  "type": "Feature",
  "properties": {
    "iso:country":"ES",
    "sg:address":"Calle de Descalzos (de Los), 65",
    "sg:city":"Arevalo",
    "sg:orig_category":"Panader\u00cdas, Panader\u00cdas",
    "sg:phone":"+34 920 30 05 33",
    "sg:postcode":"05200",
    "sg:province":"\u00c1vila",
    "wof:name":"Lopez Serrano Florentino",
    "wof:placetype":"venue"
},
  "geometry": {"coordinates":[-4.7159566879,41.0586357117],"type":"Point"}
}