{
  "type": "Feature",
  "properties": {
    "iso:country":"ES",
    "sg:address":"Cm Vell Onda Castello, 12",
    "sg:city":"Vila-real",
    "sg:orig_category":"Cer\u00c1micas: Material Y Suministros",
    "sg:phone":"+34 964 53 83 89",
    "sg:postcode":"12540",
    "sg:province":"Castell\u00f3n",
    "wof:name":"Talleres Almela S.l.",
    "wof:placetype":"venue"
},
  "geometry": {"coordinates":[-0.0934460014,39.9502639771],"type":"Point"}
}