{
  "type": "Feature",
  "properties": {
    "addr:full":"Calle de Luis Doreste Silva, 5 Palmas De Gran Canaria Las Palmas 35004",
    "addr:housenumber":"5",
    "addr:postcode":"35004",
    "addr:street":"Calle De Luis Doreste Silva",
    "iso:country":"ES",
    "sg:address":"Calle de Luis Doreste Silva, 5",
    "sg:city":"Palmas De Gran Canaria",
    "sg:orig_category":"Institutos De Belleza",
    "sg:phone":"+34 928 29 53 36",
    "sg:postcode":"35004",
    "sg:province":"Las Palmas",
    "wof:name":"Martin Cabrera Judith",
    "wof:placetype":"venue"
},
  "geometry": {"coordinates":[-15.4199991226,28.1148738861],"type":"Point"}
}