{
  "type": "Feature",
  "properties": {
    "addr:full":"Praz Fernando Buesa, 1 Temple La Coru\u00f1a 15679",
    "addr:housenumber":"1",
    "addr:postcode":"15679",
    "addr:street":"Praz Fernando Buesa;La Corun\u0303A",
    "iso:country":"ES",
    "sg:address":"Praz Fernando Buesa, 1",
    "sg:city":"Temple",
    "sg:orig_category":"Centros De Adelgazamiento Y De Est\u00c9tica",
    "sg:phone":"+34 981 65 21 36",
    "sg:postcode":"15679",
    "sg:province":"La Coru\u00f1a",
    "wof:name":"Salas Santa Maria Damaso Emilio",
    "wof:placetype":"venue"
},
  "geometry": {"coordinates":[-8.3685693741,43.3172721863],"type":"Point"}
}