{
  "type": "Feature",
  "properties": {
    "addr:full":"Avda Inventor Pedro Cawley, 14 Poligono Industrial Salinas De San Jose C\u00e1diz 11500",
    "addr:housenumber":"14",
    "addr:postcode":"11500",
    "addr:street":"Avda Inventor Pedro Cawley;Industrial;Ca\u0301Diz",
    "iso:country":"ES",
    "sg:address":"Avda Inventor Pedro Cawley, 14",
    "sg:city":"Poligono Industrial Salinas De San Jose",
    "sg:orig_category":"Electricidad: Instaladores",
    "sg:phone":"+34 956 87 52 33",
    "sg:postcode":"11500",
    "sg:province":"C\u00e1diz",
    "wof:name":"Andaluza De Montajes Electricos Y Telefo",
    "wof:placetype":"venue"
},
  "geometry": {"coordinates":[-6.1977591515,36.6144371033],"type":"Point"}
}