{
  "type": "Feature",
  "properties": {
    "addr:full":"Calle de Borrull, 3 Valencia Valencia 46008",
    "addr:housenumber":"3",
    "addr:postcode":"46008",
    "addr:street":"Calle De Borrull",
    "iso:country":"ES",
    "sg:address":"Calle de Borrull, 3",
    "sg:city":"Valencia",
    "sg:orig_category":"Platos Preparados Refrigerados (fabricaci\u00d3n, Al Por Mayor)",
    "sg:phone":"+34 963 91 56 79",
    "sg:postcode":"46008",
    "sg:province":"Valencia",
    "wof:name":"Gomez Hernandez Eduardo",
    "wof:placetype":"venue"
},
  "geometry": {"coordinates":[-0.3843185008,39.4746513367],"type":"Point"}
}