{
  "type": "Feature",
  "properties": {
    "addr:full":"Calle de Virgen De La Estrella, 13 Sabiote Ja\u00e9n 23410",
    "addr:housenumber":"13",
    "addr:postcode":"23410",
    "addr:street":"Calle De Virgen De La Estrella;Jae\u0301N",
    "iso:country":"ES",
    "sg:address":"Calle de Virgen De La Estrella, 13",
    "sg:city":"Sabiote",
    "sg:orig_category":"Empresas De Carpinter\u00cda De Madera",
    "sg:phone":"+34 953 77 30 20",
    "sg:postcode":"23410",
    "sg:province":"Ja\u00e9n",
    "wof:name":"Hermanos Martinez Sanchez C.b.",
    "wof:placetype":"venue"
},
  "geometry": {"coordinates":[-3.3115210533,38.0673789978],"type":"Point"}
}