{
  "type": "Feature",
  "properties": {
    "iso:country":"ES",
    "sg:address":"Calle de Mestikabaso Kalea, 21",
    "sg:city":"Gernika-lumo",
    "sg:orig_category":"Peluquer\u00cdas, Peluquer\u00cda Mixta",
    "sg:phone":"+34 946 25 55 05",
    "sg:postcode":"48300",
    "sg:province":"Vizcaya",
    "wof:name":"Iratxe Garikaetxebarria Galan",
    "wof:placetype":"venue"
},
  "geometry": {"coordinates":[-2.6816699505,43.3085479736],"type":"Point"}
}