{
  "type": "Feature",
  "properties": {
    "iso:country":"ES",
    "sg:address":"Carrer de Ferrocarril, 22",
    "sg:city":"Mollet Valles",
    "sg:orig_category":"Transportes Por V\u00cdas Navegables",
    "sg:phone":"+34 935 93 07 79",
    "sg:postcode":"08100",
    "sg:province":"Barcelona",
    "wof:name":"Transportes Gordi S.a.",
    "wof:placetype":"venue"
},
  "geometry": {"coordinates":[2.2119879723,41.5438423157],"type":"Point"}
}