{
  "type": "Feature",
  "properties": {
    "iso:country":"ES",
    "sg:address":"Avda El Ferrol, 18",
    "sg:city":"Madrid",
    "sg:orig_category":"Cl\u00cdnicas Dentales",
    "sg:phone":"+34 913 23 33 80",
    "sg:postcode":"28029",
    "sg:province":"Madrid",
    "wof:name":"Bratos Morillo M. Cilinica Dental S.l.",
    "wof:placetype":"venue"
},
  "geometry": {"coordinates":[-3.7041769028,40.4746131897],"type":"Point"}
}