{
  "type": "Feature",
  "properties": {
    "addr:full":"Calle de Ramon Gallud, 85 Torrevieja Alicante 03180",
    "addr:housenumber":"85",
    "addr:postcode":"03180",
    "addr:street":"Calle De Ramon Gallud",
    "iso:country":"ES",
    "sg:address":"Calle de Ramon Gallud, 85",
    "sg:city":"Torrevieja",
    "sg:orig_category":"Cajas De Ahorro",
    "sg:phone":"+34 965 70 62 23",
    "sg:postcode":"03180",
    "sg:province":"Alicante",
    "wof:name":"Caixa D'estalvis De Catalunya",
    "wof:placetype":"venue"
},
  "geometry": {"coordinates":[-0.6786450148,37.9775352478],"type":"Point"}
}