{
  "type": "Feature",
  "properties": {
    "addr:full":"Calle de Andra Maria, S/n Gernika-lumo Vizcaya 48300",
    "addr:housenumber":"/ n",
    "addr:postcode":"48300",
    "addr:street":"Calle De Andra Maria S",
    "iso:country":"ES",
    "sg:address":"Calle de Andra Maria, S/n",
    "sg:city":"Gernika-lumo",
    "sg:orig_category":"Ense\u00d1anza: Idiomas",
    "sg:phone":"+34 946 25 35 96",
    "sg:postcode":"48300",
    "sg:province":"Vizcaya",
    "wof:name":"Euskaraz Koop. E.",
    "wof:placetype":"venue"
},
  "geometry": {"coordinates":[-2.6777374744,43.3155326843],"type":"Point"}
}