{
  "type": "Feature",
  "properties": {
    "iso:country":"ES",
    "sg:address":"Calle de Mexico, 53",
    "sg:city":"Arrecife",
    "sg:orig_category":"Platos Preparados Refrigerados (fabricaci\u00d3n, Al Por Mayor)",
    "sg:phone":"+34 928 81 33 87",
    "sg:postcode":"35500",
    "sg:province":"Las Palmas",
    "wof:name":"Anolke Lanzarote S.l",
    "wof:placetype":"venue"
},
  "geometry": {"coordinates":[-13.561044693,28.9756126404],"type":"Point"}
}