{
  "type": "Feature",
  "properties": {
    "addr:full":"Pase Marques De Zafra, 38 Madrid Madrid 28028",
    "addr:housenumber":"38",
    "addr:postcode":"madrid;28028",
    "addr:street":"Marques;Zafra",
    "iso:country":"ES",
    "sg:address":"Pase Marques De Zafra, 38",
    "sg:city":"Madrid",
    "sg:classifiers":[
        {
            "category":"Professional",
            "subcategory":"Management & Consulting",
            "type":"Services"
        }
    ],
    "sg:phone":"+34 913 55 71 60",
    "sg:postcode":"28028",
    "sg:province":"Madrid",
    "sg:tags":[
        "asesor\u00cda",
        "en",
        "marketing"
    ],
    "sg:website":"www.01consulting.com",
    "wof:name":"01 Consulting S.l.",
    "wof:placetype":"venue"
},
  "geometry": {"coordinates":[-3.663519,40.425488],"type":"Point"}
}