{
  "type": "Feature",
  "properties": {
    "addr:full":"Calle de Jabega, 59 Malaga M\u00e1laga 29017",
    "addr:housenumber":"59",
    "addr:postcode":"29017",
    "addr:street":"Calle De Jabega;Ma\u0301Laga",
    "iso:country":"ES",
    "sg:address":"Calle de Jabega, 59",
    "sg:city":"Malaga",
    "sg:orig_category":"Alimentaci\u00d3n General (al Por Menor)",
    "sg:phone":"+34 952 29 93 80",
    "sg:postcode":"29017",
    "sg:province":"M\u00e1laga",
    "wof:name":"Romero Arcas Dolores",
    "wof:placetype":"venue"
},
  "geometry": {"coordinates":[-4.3724088669,36.7210655212],"type":"Point"}
}