{
  "type": "Feature",
  "properties": {
    "addr:full":"Independentzia, 70 Elexalde Vizcaya 48940",
    "addr:housenumber":"70",
    "addr:postcode":"48940",
    "addr:street":"Independentzia",
    "iso:country":"ES",
    "sg:address":"Independentzia, 70",
    "sg:city":"Elexalde",
    "sg:orig_category":"Electricidad, Electr\u00d3nica: Material Y Suministros (al Por Mayor)",
    "sg:phone":"+34 944 31 58 43",
    "sg:postcode":"48940",
    "sg:province":"Vizcaya",
    "wof:name":"Ziv Aplicaciones Y Tecnologia S.a.",
    "wof:placetype":"venue"
},
  "geometry": {"coordinates":[-2.8873260021,43.2208213806],"type":"Point"}
}