{
  "type": "Feature",
  "properties": {
    "iso:country":"ES",
    "sg:address":"R. Oliva, 13",
    "sg:city":"Malaga",
    "sg:orig_category":"Audiovisuales (producci\u00d3n, Edici\u00d3n, Realizaci\u00d3n)",
    "sg:phone":"+34 952 17 31 86",
    "sg:postcode":"29004",
    "sg:province":"M\u00e1laga",
    "wof:name":"Producciones Malaga 2000 S.l.",
    "wof:placetype":"venue"
},
  "geometry": {"coordinates":[-4.4609279633,36.6641159058],"type":"Point"}
}