{
  "type": "Feature",
  "properties": {
    "iso:country":"ES",
    "sg:address":"Carrer de Gran De Gracia, 221",
    "sg:city":"Barcelona",
    "sg:orig_category":"Alimentaci\u00d3n General (al Por Menor)",
    "sg:phone":"+34 932 37 95 79",
    "sg:postcode":"08012",
    "sg:province":"Barcelona",
    "wof:name":"Torrella Mauri Mercedes",
    "wof:placetype":"venue"
},
  "geometry": {"coordinates":[2.1511209011,41.4046821594],"type":"Point"}
}