{
  "type": "Feature",
  "properties": {
    "addr:full":"Calle de Caleros, 4 Salamanca Salamanca 37001",
    "addr:housenumber":"4",
    "addr:postcode":"37001",
    "addr:street":"Calle De Caleros",
    "iso:country":"ES",
    "sg:address":"Calle de Caleros, 4",
    "sg:city":"Salamanca",
    "sg:orig_category":"Arquitectos",
    "sg:phone":"+34 923 26 22 47",
    "sg:postcode":"37001",
    "sg:province":"Salamanca",
    "wof:name":"De La Mano Moran Antonio",
    "wof:placetype":"venue"
},
  "geometry": {"coordinates":[-5.6617736816,40.9657859802],"type":"Point"}
}