{
  "type": "Feature",
  "properties": {
    "iso:country":"ES",
    "sg:address":"Calle de Federico Garcia Lorca, S/n",
    "sg:city":"Algeciras",
    "sg:orig_category":"Carnicer\u00cdas, Carnicer\u00cdas",
    "sg:phone":"+34 956 57 09 43",
    "sg:postcode":"11207",
    "sg:province":"C\u00e1diz",
    "wof:name":"Santos Perez Antonio",
    "wof:placetype":"venue"
},
  "geometry": {"coordinates":[-5.4530940056,36.1144485474],"type":"Point"}
}