{
  "type": "Feature",
  "properties": {
    "addr:full":"Calle de Cerro (del), S/n Navas Del Marques \u00c1vila 05230",
    "addr:housenumber":"/ n",
    "addr:postcode":"05230",
    "addr:street":"Calle De Cerro Del S;A\u0301Vila",
    "iso:country":"ES",
    "sg:address":"Calle de Cerro (del), S/n",
    "sg:city":"Navas Del Marques",
    "sg:orig_category":"Escayola Y Productos De Escayola (fabricaci\u00d3n, Al Por Mayor)",
    "sg:phone":"+34 918 97 90 40",
    "sg:postcode":"05230",
    "sg:province":"\u00c1vila",
    "wof:name":"Ismael Y Samuel S.l.",
    "wof:placetype":"venue"
},
  "geometry": {"coordinates":[-4.3314566612,40.5951652527],"type":"Point"}
}