{
  "type": "Feature",
  "properties": {
    "addr:full":"Carr Pau Casals, 14 Girona Girona 17001",
    "addr:housenumber":"14",
    "addr:postcode":"17001",
    "addr:street":"Carr Pau Casals",
    "iso:country":"ES",
    "sg:address":"Carr Pau Casals, 14",
    "sg:city":"Girona",
    "sg:orig_category":"Alimentaci\u00d3n General (al Por Menor)",
    "sg:phone":"+34 972 20 36 70",
    "sg:postcode":"17001",
    "sg:province":"Girona",
    "wof:name":"Girones Reig Maria Clara",
    "wof:placetype":"venue"
},
  "geometry": {"coordinates":[2.8144960403,41.9836921692],"type":"Point"}
}