{
  "type": "Feature",
  "properties": {
    "addr:full":"Calle de Antonio Jorge, 26 Pto. Rosario Las Palmas 35600",
    "addr:housenumber":"26",
    "addr:postcode":"35600",
    "addr:street":"Calle De Antonio Jorge;Pto. Rosario Las",
    "iso:country":"ES",
    "sg:address":"Calle de Antonio Jorge, 26",
    "sg:city":"Pto. Rosario",
    "sg:classifiers":[
        {
            "category":"Personal",
            "subcategory":"Barber",
            "type":"Services"
        }
    ],
    "sg:phone":"+34 928 53 16 57",
    "sg:postcode":"35600",
    "sg:province":"Las Palmas",
    "sg:tags":[
        "caballeros",
        "de",
        "peluqueros"
    ],
    "wof:name":"Perdomo Rodriguez Emiliano Jose",
    "wof:placetype":"venue"
},
  "geometry": {"coordinates":[-13.8721981049,28.5042743683],"type":"Point"}
}