{
  "type": "Feature",
  "properties": {
    "iso:country":"ES",
    "sg:address":"Avda Extremadura, 84",
    "sg:city":"Talavera Real",
    "sg:orig_category":"Bazares, Art\u00cdculos De Limpieza Y De Cocina (al Por Menor)",
    "sg:phone":"+34 924 44 00 83",
    "sg:postcode":"06140",
    "sg:province":"Badajoz",
    "wof:name":"Villalobos Y Moran S.l.",
    "wof:placetype":"venue"
},
  "geometry": {"coordinates":[-6.7681651115,38.8766860962],"type":"Point"}
}