{
  "type": "Feature",
  "properties": {
    "addr:full":"Cruz De Barkazio, 23 Iru\u00f1a Navarra 31014",
    "addr:housenumber":"23",
    "addr:postcode":"31014",
    "addr:street":"Cruz;Barkazio",
    "iso:country":"ES",
    "sg:address":"Cruz De Barkazio, 23",
    "sg:city":"Iru\u00f1a",
    "sg:orig_category":"Muebles, Minoristas",
    "sg:phone":"+34 948 38 26 59",
    "sg:postcode":"31014",
    "sg:province":"Navarra",
    "sg:website":"www.gbmobiliario.com",
    "wof:name":"G. B. Mobiliario S. L.",
    "wof:placetype":"venue"
},
  "geometry": {"coordinates":[-1.6494560242,42.8272628784],"type":"Point"}
}