{
  "type": "Feature",
  "properties": {
    "iso:country":"ES",
    "sg:address":"Plaz Solidaridad De La, 7",
    "sg:city":"Malaga",
    "sg:orig_category":"Promotores Constructores",
    "sg:phone":"+34 952 36 80 93",
    "sg:postcode":"29006",
    "sg:province":"M\u00e1laga",
    "wof:name":"Aruges S.l.",
    "wof:placetype":"venue"
},
  "geometry": {"coordinates":[-4.4980049133,36.7106819153],"type":"Point"}
}