{
  "type": "Feature",
  "properties": {
    "iso:country":"ES",
    "sg:address":"Av Espanya, 6",
    "sg:city":"Eivissa",
    "sg:orig_category":"Ropa Para Se\u00d1oras (al Por Menor)",
    "sg:phone":"+34 971 30 14 90",
    "sg:postcode":"07800",
    "sg:province":"Islas Baleares",
    "wof:name":"Fuster Bonet Margarita",
    "wof:placetype":"venue"
},
  "geometry": {"coordinates":[1.4319449663,38.9089050293],"type":"Point"}
}