{
  "type": "Feature",
  "properties": {
    "iso:country":"ES",
    "sg:address":"Avda Jose Maria Alcaraz Y Alenda, 25",
    "sg:city":"Badajoz",
    "sg:orig_category":"Ingeniero",
    "sg:phone":"+34 924 22 34 64",
    "sg:postcode":"06011",
    "sg:province":"Badajoz",
    "wof:name":"Pinilla Jimenez Isidoro",
    "wof:placetype":"venue"
},
  "geometry": {"coordinates":[-6.9947738647,38.8652305603],"type":"Point"}
}