{
  "type": "Feature",
  "properties": {
    "iso:country":"ES",
    "sg:address":"Carrer de Font (la), 26",
    "sg:city":"Vilafranca Penedes",
    "sg:orig_category":"Asesor\u00cda Fiscal Y Jur\u00cddica",
    "sg:phone":"+34 938 92 36 01",
    "sg:postcode":"08720",
    "sg:province":"Barcelona",
    "wof:name":"Carrillo Sanchez Carmelo",
    "wof:placetype":"venue"
},
  "geometry": {"coordinates":[1.699936986,41.347694397],"type":"Point"}
}