{
  "type": "Feature",
  "properties": {
    "iso:country":"ES",
    "sg:address":"Calle de Fray Luis Amigo, 8",
    "sg:city":"Zaragoza",
    "sg:orig_category":"Seguridad Social",
    "sg:phone":"+34 976 25 94 00",
    "sg:postcode":"50006",
    "sg:province":"Zaragoza",
    "wof:name":"Mutua Universal Mugenat-matepss Numero 10",
    "wof:placetype":"venue"
},
  "geometry": {"coordinates":[-0.8936190009,41.6372299194],"type":"Point"}
}