{
  "type": "Feature",
  "properties": {
    "addr:full":"Calle de Atalaya, 4 Ubeda Ja\u00e9n 23400",
    "addr:housenumber":"4",
    "addr:postcode":"23400",
    "addr:street":"Calle De Atalaya;Jae\u0301N",
    "iso:country":"ES",
    "sg:address":"Calle de Atalaya, 4",
    "sg:city":"Ubeda",
    "sg:orig_category":"M\u00c9dicos: Estomatolog\u00cda",
    "sg:phone":"+34 953 79 21 42",
    "sg:postcode":"23400",
    "sg:province":"Ja\u00e9n",
    "wof:name":"Palma Gutierrez Sergio",
    "wof:placetype":"venue"
},
  "geometry": {"coordinates":[-3.3789510727,38.0178184509],"type":"Point"}
}