{
  "type": "Feature",
  "properties": {
    "iso:country":"ES",
    "sg:address":"Calle de Mayor, 40",
    "sg:city":"Jarque",
    "sg:orig_category":"Carnes De Carnicer\u00cda (al Por Mayor)",
    "sg:phone":"+34 976 82 16 14",
    "sg:postcode":"50258",
    "sg:province":"Zaragoza",
    "wof:name":"Embid Martinez Angel",
    "wof:placetype":"venue"
},
  "geometry": {"coordinates":[-1.6745519638,41.5554847717],"type":"Point"}
}