{
  "type": "Feature",
  "properties": {
    "addr:full":"Avda Alcalde Cantos Ropero, 43 Jerez De La Frontera C\u00e1diz 11408",
    "addr:housenumber":"43",
    "addr:postcode":"11408",
    "addr:street":"Avda Alcalde Cantos Ropero",
    "iso:country":"ES",
    "sg:address":"Avda Alcalde Cantos Ropero, 43",
    "sg:city":"Jerez De La Frontera",
    "sg:orig_category":"Agencias Y Asesores De Publicidad",
    "sg:phone":"+34 956 14 13 64",
    "sg:postcode":"11408",
    "sg:province":"C\u00e1diz",
    "wof:name":"Atiber Marketing Y Publicidad S.l.",
    "wof:placetype":"venue"
},
  "geometry": {"coordinates":[-6.1315279007,36.66223526],"type":"Point"}
}