{
  "type": "Feature",
  "properties": {
    "iso:country":"ES",
    "sg:address":"Carr Elcano, 21",
    "sg:city":"Puerto De Pollen\u00c7a",
    "sg:orig_category":"Peritos En C\u00c1lculo Inmobiliario, Industrial Y De Fondos De Comercio",
    "sg:phone":"+34 971 86 46 61",
    "sg:postcode":"07470",
    "sg:province":"Islas Baleares",
    "sg:website":"www.exclusivasxisca.com",
    "wof:name":"Exclusivas Xisca S.l.",
    "wof:placetype":"venue"
},
  "geometry": {"coordinates":[3.0821900368,39.9063034058],"type":"Point"}
}