{
  "type": "Feature",
  "properties": {
    "addr:full":"Estd Conde Do Grove, 7 Grove Pontevedra 36980",
    "addr:housenumber":"7",
    "addr:postcode":"36980",
    "addr:street":"Grove Pontevedra",
    "iso:country":"ES",
    "sg:address":"Estd Conde Do Grove, 7",
    "sg:city":"Grove",
    "sg:orig_category":"Sales (al Por Mayor)",
    "sg:phone":"+34 986 73 03 95",
    "sg:postcode":"36980",
    "sg:province":"Pontevedra",
    "wof:name":"Castro Iglesias Manuel",
    "wof:placetype":"venue"
},
  "geometry": {"coordinates":[-8.86282444,42.4956588745],"type":"Point"}
}