{
  "type": "Feature",
  "properties": {
    "iso:country":"ES",
    "sg:address":"Calle de Zaragoza, 6",
    "sg:city":"Huesca",
    "sg:orig_category":"Ropa Para Se\u00d1oras Y Caballeros (al Por Menor)",
    "sg:phone":"+34 974 21 57 16",
    "sg:postcode":"22002",
    "sg:province":"Huesca",
    "sg:website":"www.adolfo-dominguez.com",
    "wof:name":"Canudo Cancer S.l.",
    "wof:placetype":"venue"
},
  "geometry": {"coordinates":[-0.4088059962,42.1354293823],"type":"Point"}
}