{
  "type": "Feature",
  "properties": {
    "iso:country":"ES",
    "sg:address":"Rua Xeneral Pardi\u00d1as (do), 9",
    "sg:city":"Santiago De Compostela",
    "sg:orig_category":"Obras Y Organismos Sociales",
    "sg:phone":"+34 981 56 28 98",
    "sg:postcode":"15701",
    "sg:province":"A Coru\u00f1a",
    "wof:name":"Union De Artesanos",
    "wof:placetype":"venue"
},
  "geometry": {"coordinates":[-8.5459623337,42.8754882812],"type":"Point"}
}