{
  "type": "Feature",
  "properties": {
    "iso:country":"ES",
    "sg:address":"Carrer de Lepant, 246",
    "sg:city":"Barcelona",
    "sg:orig_category":"Impermeabilizantes",
    "sg:phone":"+34 932 65 12 24",
    "sg:postcode":"08013",
    "sg:province":"Barcelona",
    "wof:name":"Materiales De Reparacion Y Refuerzo S.l.",
    "wof:placetype":"venue"
},
  "geometry": {"coordinates":[2.1788730621,41.4030036926],"type":"Point"}
}