{
  "type": "Feature",
  "properties": {
    "addr:full":"Av Conqueridor, 79 Ciutadella Menorca Islas Baleares 07760",
    "addr:housenumber":"79",
    "addr:postcode":"07760",
    "addr:street":"Av Conqueridor",
    "iso:country":"ES",
    "sg:address":"Av Conqueridor, 79",
    "sg:city":"Ciutadella Menorca",
    "sg:orig_category":"Agencias De Viajes",
    "sg:phone":"+34 971 38 62 23",
    "sg:postcode":"07760",
    "sg:province":"Islas Baleares",
    "wof:name":"Viajes Iberia S.a:",
    "wof:placetype":"venue"
},
  "geometry": {"coordinates":[3.839867115,40.0002784729],"type":"Point"}
}