{
  "type": "Feature",
  "properties": {
    "iso:country":"ES",
    "sg:address":"Calle de Restoy, 79",
    "sg:city":"Almeria",
    "sg:orig_category":"Alquiler De V\u00cddeo",
    "sg:phone":"+34 950 23 66 89",
    "sg:postcode":"04003",
    "sg:province":"Almer\u00eda",
    "wof:name":"Rubira Reina Jose",
    "wof:placetype":"venue"
},
  "geometry": {"coordinates":[-2.4635989666,36.8466873169],"type":"Point"}
}