{
  "type": "Feature",
  "properties": {
    "iso:country":"ES",
    "sg:address":"Calle de Jacinto, 20",
    "sg:city":"Ciudad Real",
    "sg:orig_category":"Clubes, Asociaciones De Ocio",
    "sg:phone":"+34 926 22 08 72",
    "sg:postcode":"13003",
    "sg:province":"Ciudad Real",
    "wof:name":"Lopez Gascon Virgilio",
    "wof:placetype":"venue"
},
  "geometry": {"coordinates":[-3.926418066,38.9890480042],"type":"Point"}
}