{
  "type": "Feature",
  "properties": {
    "iso:country":"ES",
    "sg:address":"Calle de Agricultores, S/n",
    "sg:city":"Olivenza",
    "sg:orig_category":"Electricidad: Instaladores",
    "sg:phone":"+34 924 49 23 51",
    "sg:postcode":"06100",
    "sg:province":"Badajoz",
    "sg:website":"www.tecyca.com",
    "wof:name":"Tec Y Ca.olivenza S.l.",
    "wof:placetype":"venue"
},
  "geometry": {"coordinates":[-7.0893921852,38.6941719055],"type":"Point"}
}