{
  "type": "Feature",
  "properties": {
    "addr:full":"Avda Machupichu, 50 Madrid Madrid 28043",
    "addr:housenumber":"50",
    "addr:postcode":"madrid;28043",
    "addr:street":"Avda Machupichu",
    "iso:country":"ES",
    "sg:address":"Avda Machupichu, 50",
    "sg:city":"Madrid",
    "sg:orig_category":"Iglesia Cat\u00d3lica",
    "sg:phone":"+34 913 88 23 41",
    "sg:postcode":"28043",
    "sg:province":"Madrid",
    "wof:name":"Parroquia Maria Virgen Madre",
    "wof:placetype":"venue"
},
  "geometry": {"coordinates":[-3.6322278976,40.4609794617],"type":"Point"}
}