{
  "type": "Feature",
  "properties": {
    "addr:full":"Calle de Nueva, S/n Montemayor Pililla Valladolid 47320",
    "addr:housenumber":"s / n",
    "addr:postcode":"47320",
    "addr:street":"Calle De Nueva",
    "iso:country":"ES",
    "sg:address":"Calle de Nueva, S/n",
    "sg:city":"Montemayor Pililla",
    "sg:orig_category":"Supermercados Y Hipermercados",
    "sg:phone":"+34 983 69 44 00",
    "sg:postcode":"47320",
    "sg:province":"Valladolid",
    "wof:name":"Supermercados La Salve S.l.",
    "wof:placetype":"venue"
},
  "geometry": {"coordinates":[-4.4563326836,41.5094604492],"type":"Point"}
}