{
  "type": "Feature",
  "properties": {
    "addr:full":"Calle de Cristobal Colon, 1 Alcala Guadaira Sevilla 41500",
    "addr:housenumber":"1",
    "addr:postcode":"41500",
    "addr:street":"Calle De Cristobal Colon",
    "iso:country":"ES",
    "sg:address":"Calle de Cristobal Colon, 1",
    "sg:city":"Alcala Guadaira",
    "sg:orig_category":"M\u00c9dicos: Estomatolog\u00cda",
    "sg:phone":"+34 954 10 19 81",
    "sg:postcode":"41500",
    "sg:province":"Sevilla",
    "wof:name":"Gonzalez Acebo Lidia",
    "wof:placetype":"venue"
},
  "geometry": {"coordinates":[-5.7515850067,37.3742370605],"type":"Point"}
}