{
  "type": "Feature",
  "properties": {
    "iso:country":"ES",
    "sg:address":"Carr Miquel Bordoy, 10",
    "sg:city":"Felanitx",
    "sg:orig_category":"Art\u00cdculos De Regalo (al Por Menor)",
    "sg:phone":"+34 971 58 03 84",
    "sg:postcode":"07200",
    "sg:province":"Islas Baleares",
    "wof:name":"Bimbolles I Nones",
    "wof:placetype":"venue"
},
  "geometry": {"coordinates":[3.1502590179,39.4691810608],"type":"Point"}
}