{
  "type": "Feature",
  "properties": {
    "addr:full":"Avda Juan Carlos I, 26 Espinardo Murcia 30008",
    "addr:housenumber":"26",
    "addr:postcode":"30008",
    "addr:street":"Avda Juan Carlos I",
    "iso:country":"ES",
    "sg:address":"Avda Juan Carlos I, 26",
    "sg:city":"Espinardo",
    "sg:orig_category":"Inmobiliaria (agencias)",
    "sg:phone":"+34 968 20 30 70",
    "sg:postcode":"30008",
    "sg:province":"Murcia",
    "sg:website":"www.gesinar.es",
    "wof:name":"Gesinar Servicios Inmobiliarios S.l.u.",
    "wof:placetype":"venue"
},
  "geometry": {"coordinates":[-1.133259058,37.9954223633],"type":"Point"}
}