{
  "type": "Feature",
  "properties": {
    "iso:country":"ES",
    "sg:address":"Calle de Principado De Asturias, 4",
    "sg:city":"Rozas De Madrid",
    "sg:orig_category":"Perfumer\u00cda (al Por Menor)",
    "sg:phone":"+34 916 37 74 76",
    "sg:postcode":"28230",
    "sg:province":"Madrid",
    "wof:name":"Miguel Ordu\u00f1a Nieves",
    "wof:placetype":"venue"
},
  "geometry": {"coordinates":[-3.8750619888,40.4878616333],"type":"Point"}
}