{
  "type": "Feature",
  "properties": {
    "iso:country":"ES",
    "sg:address":"Carrer de Jaume Balmes, 55",
    "sg:city":"Palma",
    "sg:orig_category":"Laboratorios Y Cl\u00cdnicas Veterinarias",
    "sg:phone":"+34 971 29 52 45",
    "sg:postcode":"07004",
    "sg:province":"Islas Baleares",
    "wof:name":"Clinica Veterinaria Balmes C.b.",
    "wof:placetype":"venue"
},
  "geometry": {"coordinates":[2.6571819782,39.5805473328],"type":"Point"}
}