{
  "type": "Feature",
  "properties": {
    "addr:full":"Ctra. S. Franc. La Savina, S/n S. Francesc Formentera Islas Baleares 07860",
    "addr:housenumber":"s",
    "addr:postcode":"07860",
    "addr:street":"Ctra. S. Franc. La Savina;/ N S. Francesc",
    "iso:country":"ES",
    "sg:address":"Ctra. S. Franc. La Savina, S/n",
    "sg:city":"S. Francesc Formentera",
    "sg:orig_category":"Turismo",
    "sg:phone":"+34 971 32 20 57",
    "sg:postcode":"07860",
    "sg:province":"Islas Baleares",
    "sg:website":"www.visitformentera.com",
    "wof:name":"Patronat Municipal De Turisme",
    "wof:placetype":"venue"
},
  "geometry": {"coordinates":[1.4309200048,38.7072410583],"type":"Point"}
}