{
  "type": "Feature",
  "properties": {
    "addr:full":"Calle de Generalisimo, S/n Amatos Salamanca 37181",
    "addr:housenumber":"s",
    "addr:postcode":"37181",
    "addr:street":"Calle De Generalisimo;/ N",
    "iso:country":"ES",
    "sg:address":"Calle de Generalisimo, S/n",
    "sg:city":"Amatos",
    "sg:orig_category":"Centros De Educaci\u00d3n Especial",
    "sg:phone":"+34 923 30 63 18",
    "sg:postcode":"37181",
    "sg:province":"Salamanca",
    "wof:name":"Cra Los Girasoles",
    "wof:placetype":"venue"
},
  "geometry": {"coordinates":[-5.504778862,40.9649505615],"type":"Point"}
}