{
  "type": "Feature",
  "properties": {
    "iso:country":"ES",
    "sg:address":"Calle de Real, 35",
    "sg:city":"Estacion",
    "sg:orig_category":"Cajas De Ahorro",
    "sg:phone":"+34 918 40 60 26",
    "sg:postcode":"28400",
    "sg:province":"Madrid",
    "sg:website":"www.cajasegovia.es",
    "wof:name":"Caja De Ahorros Y Monte De Piedad De Segovia",
    "wof:placetype":"venue"
},
  "geometry": {"coordinates":[-3.9919650555,40.6455612183],"type":"Point"}
}