{
  "type": "Feature",
  "properties": {
    "iso:country":"ES",
    "sg:address":"Calle de Mayor, 15",
    "sg:city":"Mijares",
    "sg:orig_category":"Muebles, Minoristas",
    "sg:phone":"+34 920 38 54 05",
    "sg:postcode":"05461",
    "sg:province":"\u00c1vila",
    "wof:name":"Sanchez Maqueda Luis",
    "wof:placetype":"venue"
},
  "geometry": {"coordinates":[-4.8376808167,40.2980461121],"type":"Point"}
}