{
  "type": "Feature",
  "properties": {
    "iso:country":"ES",
    "sg:address":"Calle de Cracovia, 4",
    "sg:city":"Madrid",
    "sg:orig_category":"Centros Empresariales",
    "sg:phone":"+34 917 75 71 95",
    "sg:postcode":"28022",
    "sg:province":"Madrid",
    "wof:name":"Pareja De Sebastian Maria Angeles",
    "wof:placetype":"venue"
},
  "geometry": {"coordinates":[-3.6056025028,40.4235725403],"type":"Point"}
}