{
  "type": "Feature",
  "properties": {
    "addr:full":"Carrer de Roger, 25 Barcelona Barcelona 08028",
    "addr:housenumber":"25",
    "addr:postcode":"08028",
    "addr:street":"Carrer De Roger",
    "iso:country":"ES",
    "sg:address":"Carrer de Roger, 25",
    "sg:city":"Barcelona",
    "sg:orig_category":"Contenedores (mercanc\u00cdas)",
    "sg:phone":"+34 933 30 40 70",
    "sg:postcode":"08028",
    "sg:province":"Barcelona",
    "wof:name":"Global Dispath Service S.l.",
    "wof:placetype":"venue"
},
  "geometry": {"coordinates":[2.1271569729,41.3770942688],"type":"Point"}
}