{
  "type": "Feature",
  "properties": {
    "addr:full":"Calle de Doctor Romagosa, 9 Valencia Valencia 46002",
    "addr:housenumber":"9",
    "addr:postcode":"46002",
    "addr:street":"Calle De Doctor Romagosa",
    "iso:country":"ES",
    "sg:address":"Calle de Doctor Romagosa, 9",
    "sg:city":"Valencia",
    "sg:orig_category":"Peluqueros: De Se\u00d1oras",
    "sg:phone":"+34 963 51 05 32",
    "sg:postcode":"46002",
    "sg:province":"Valencia",
    "wof:name":"Ruiz Navarro Daniel",
    "wof:placetype":"venue"
},
  "geometry": {"coordinates":[-0.3724707067,39.4705696106],"type":"Point"}
}