{
  "type": "Feature",
  "properties": {
    "iso:country":"ES",
    "sg:address":"Carrer de Industria, S/n",
    "sg:city":"Gurb",
    "sg:orig_category":"Papel, Reciclaje",
    "sg:phone":"+34 938 86 06 40",
    "sg:postcode":"08518",
    "sg:province":"Barcelona",
    "wof:name":"Recuperacions Muntada Sl",
    "wof:placetype":"venue"
},
  "geometry": {"coordinates":[2.2384250164,41.9416999817],"type":"Point"}
}