{
  "type": "Feature",
  "properties": {
    "addr:full":"Gabarres, 9 S. Antoni Calonge Girona 17252",
    "addr:housenumber":"9",
    "addr:postcode":"17252",
    "addr:street":"Gabarres",
    "iso:country":"ES",
    "sg:address":"Gabarres, 9",
    "sg:city":"S. Antoni Calonge",
    "sg:orig_category":"Carnicer\u00cdas, Carnicer\u00cdas",
    "sg:phone":"+34 972 65 12 34",
    "sg:postcode":"17252",
    "sg:province":"Girona",
    "wof:name":"Pruja Illa Jose",
    "wof:placetype":"venue"
},
  "geometry": {"coordinates":[3.1094601154,41.8569297791],"type":"Point"}
}