{
  "type": "Feature",
  "properties": {
    "addr:full":"Calle de Cronista Cervero, 38 Riba-roja Turia Valencia 46190",
    "addr:housenumber":"38",
    "addr:postcode":"46190",
    "addr:street":"Calle De Cronista Cervero",
    "iso:country":"ES",
    "sg:address":"Calle de Cronista Cervero, 38",
    "sg:city":"Riba-roja Turia",
    "sg:orig_category":"Frutas Y Legumbres Frescas (al Por Mayor)",
    "sg:phone":"+34 962 77 92 62",
    "sg:postcode":"46190",
    "sg:province":"Valencia",
    "wof:name":"Frutomas Export S.l.",
    "wof:placetype":"venue"
},
  "geometry": {"coordinates":[-0.5723358989,39.5469894409],"type":"Point"}
}