{
  "type": "Feature",
  "properties": {
    "iso:country":"ES",
    "sg:address":"Las Costureras, 11",
    "sg:city":"La Solana",
    "sg:orig_category":"T\u00c9cnicos Veterinarios",
    "sg:phone":"+34 926 63 44 91",
    "sg:postcode":"13240",
    "sg:province":"Ciudad Real",
    "wof:name":"Perez Corrales Rafael",
    "wof:placetype":"venue"
},
  "geometry": {"coordinates":[-3.2383489609,38.9393005371],"type":"Point"}
}