{
  "type": "Feature",
  "properties": {
    "iso:country":"ES",
    "sg:address":"Calle de Zamacola, 11",
    "sg:city":"Bilbao",
    "sg:orig_category":"Peluqueros: De Se\u00d1oras",
    "sg:phone":"+34 944 15 96 09",
    "sg:postcode":"48003",
    "sg:province":"Vizcaya",
    "wof:name":"Pliego-valdes Lopez Maria De Las Mercedes",
    "wof:placetype":"venue"
},
  "geometry": {"coordinates":[-2.9216859341,43.2497024536],"type":"Point"}
}