{
  "type": "Feature",
  "properties": {
    "addr:full":"Calle de Isla, 5 Zafarraya Granada 18128",
    "addr:housenumber":"5",
    "addr:postcode":"18128",
    "addr:street":"Calle De Isla",
    "iso:country":"ES",
    "sg:address":"Calle de Isla, 5",
    "sg:city":"Zafarraya",
    "sg:orig_category":"Arboricultura Y Producci\u00d3n De Frutas",
    "sg:phone":"+34 958 36 80 21",
    "sg:postcode":"18128",
    "sg:province":"Granada",
    "wof:name":"Domingo Peula S.l.",
    "wof:placetype":"venue"
},
  "geometry": {"coordinates":[-4.141933918,36.9743881226],"type":"Point"}
}