{
  "type": "Feature",
  "properties": {
    "addr:full":"Calle de Ferrandiz, 17 Malaga M\u00e1laga 29012",
    "addr:housenumber":"17",
    "addr:postcode":"29012",
    "addr:street":"Calle De Ferrandiz;Ma\u0301Laga",
    "iso:country":"ES",
    "sg:address":"Calle de Ferrandiz, 17",
    "sg:city":"Malaga",
    "sg:orig_category":"Peluquer\u00cdas, Peluquer\u00cda Mixta",
    "sg:phone":"+34 952 25 34 34",
    "sg:postcode":"29012",
    "sg:province":"M\u00e1laga",
    "wof:name":"Zurita Gomez Alberto",
    "wof:placetype":"venue"
},
  "geometry": {"coordinates":[-4.4122462273,36.7273826599],"type":"Point"}
}