{
  "type": "Feature",
  "properties": {
    "addr:full":"Calle de Maria Juncal Labandibar, 7 Irun Guip\u00f9zcoa 20305",
    "addr:housenumber":"7",
    "addr:postcode":"20305",
    "addr:street":"Calle De Maria Juncal Labandibar;Guipu\u0300Zcoa",
    "iso:country":"ES",
    "sg:address":"Calle de Maria Juncal Labandibar, 7",
    "sg:city":"Irun",
    "sg:orig_category":"Comercio De Minerales, F\u00d3siles Y Conchas",
    "sg:phone":"+34 943 62 44 77",
    "sg:postcode":"20305",
    "sg:province":"Guip\u00f9zcoa",
    "wof:name":"Aristieta Bengoechea Miren Arantza",
    "wof:placetype":"venue"
},
  "geometry": {"coordinates":[-1.7617176771,43.3433418274],"type":"Point"}
}