{
  "type": "Feature",
  "properties": {
    "addr:full":"Calle de Jerez Perchet, 2 Malaga M\u00e1laga 29014",
    "addr:housenumber":"2",
    "addr:postcode":"29014",
    "addr:street":"Calle De Jerez Perchet;Ma\u0301Laga",
    "iso:country":"ES",
    "sg:address":"Calle de Jerez Perchet, 2",
    "sg:city":"Malaga",
    "sg:orig_category":"Reposter\u00cdas",
    "sg:phone":"+34 952 26 07 86",
    "sg:postcode":"29014",
    "sg:province":"M\u00e1laga",
    "wof:name":"Panificadora Platero S.l.",
    "wof:placetype":"venue"
},
  "geometry": {"coordinates":[-4.4215488434,36.7458724976],"type":"Point"}
}