{
  "type": "Feature",
  "properties": {
    "iso:country":"ES",
    "sg:address":"Calle de Rio Llobregat, 11",
    "sg:city":"Mostoles",
    "sg:orig_category":"Mec\u00c1nico Del Autom\u00d3vil",
    "sg:phone":"+34 916 47 15 52",
    "sg:postcode":"28935",
    "sg:province":"Madrid",
    "wof:name":"Garcia Rodriguez Jose Antonio",
    "wof:placetype":"venue"
},
  "geometry": {"coordinates":[-3.8752720356,40.3168487549],"type":"Point"}
}