{
  "type": "Feature",
  "properties": {
    "iso:country":"ES",
    "sg:address":"Calle de Postigo, 8",
    "sg:city":"Puerto De Santa Maria",
    "sg:orig_category":"Fabricaci\u00d3n De Harinas, S\u00c9molas, Productos De Elaboraci\u00d3n Del Grano",
    "sg:phone":"+34 956 85 03 13",
    "sg:postcode":"11500",
    "sg:province":"C\u00e1diz",
    "wof:name":"Esteban Fernandez Rosado S. A.",
    "wof:placetype":"venue"
},
  "geometry": {"coordinates":[-6.2292509079,36.6004104614],"type":"Point"}
}