{
  "type": "Feature",
  "properties": {
    "addr:full":"Pol. Ind. Seis, S/n Silla Valencia 46460",
    "addr:housenumber":"s / n",
    "addr:postcode":"46460",
    "iso:country":"ES",
    "sg:address":"Pol. Ind. Seis, S/n",
    "sg:city":"Silla",
    "sg:orig_category":"Limpieza Con Chorro De Arena Y Con Granalla, Pulido",
    "sg:phone":"+34 961 21 18 61",
    "sg:postcode":"46460",
    "sg:province":"Valencia",
    "sg:website":"www.blanch-house.com",
    "wof:name":"Blanch's House S.a.",
    "wof:placetype":"venue"
},
  "geometry": {"coordinates":[-0.417858988,39.3685531616],"type":"Point"}
}