{
  "type": "Feature",
  "properties": {
    "iso:country":"ES",
    "sg:address":"Pg Ronda, 7",
    "sg:city":"Lourdes",
    "sg:orig_category":"Caf\u00c9s, Bares, Cervecer\u00cdas",
    "sg:phone":"+34 935 62 22 22",
    "sg:postcode":"08100",
    "sg:province":"Barcelona",
    "wof:name":"Guerra Galan Vanessa",
    "wof:placetype":"venue"
},
  "geometry": {"coordinates":[2.1699187756,41.3879165649],"type":"Point"}
}