{
  "type": "Feature",
  "properties": {
    "addr:full":"Carr Sant Antoni Abat, 11 Sueca Valencia 46410",
    "addr:housenumber":"11",
    "addr:postcode":"46410",
    "addr:street":"Carr Sant Antoni Abat",
    "iso:country":"ES",
    "sg:address":"Carr Sant Antoni Abat, 11",
    "sg:city":"Sueca",
    "sg:orig_category":"Droguer\u00cdas (al Por Menor)",
    "sg:phone":"+34 961 71 02 59",
    "sg:postcode":"46410",
    "sg:province":"Valencia",
    "wof:name":"A\u00f1oz Perez Manuela Francisca",
    "wof:placetype":"venue"
},
  "geometry": {"coordinates":[-0.3115560114,39.1998558044],"type":"Point"}
}