{
  "type": "Feature",
  "properties": {
    "iso:country":"ES",
    "sg:address":"Calle de Toribio Alzaga, 11",
    "sg:city":"Donostia-san Sebastian",
    "sg:orig_category":"Arreglo, Reparaci\u00d3n, Piezas Sueltas De Televisi\u00d3n, V\u00cddeo, Hi",
    "sg:phone":"+34 943 47 00 51",
    "sg:postcode":"20011",
    "sg:province":"Guip\u00f9zcoa",
    "wof:name":"Moreiro Caballero Jesus",
    "wof:placetype":"venue"
},
  "geometry": {"coordinates":[-1.9725589752,43.3046836853],"type":"Point"}
}