{
  "type": "Feature",
  "properties": {
    "iso:country":"ES",
    "sg:address":"Carr Major, 11",
    "sg:city":"Gandia",
    "sg:orig_category":"Televisi\u00d3n, V\u00cddeo: Aparatos Y Accesorios (venta)",
    "sg:phone":"+34 962 87 21 52",
    "sg:postcode":"46700",
    "sg:province":"Valencia",
    "wof:name":"Audio Video J.perez S.l.",
    "wof:placetype":"venue"
},
  "geometry": {"coordinates":[-0.1811736971,38.9680595398],"type":"Point"}
}