{
  "type": "Feature",
  "properties": {
    "addr:full":"Rua Calvo Sotelo, 140 Sarria Lugo 27600",
    "addr:housenumber":"140",
    "addr:postcode":"27600",
    "addr:street":"Rua Calvo Sotelo",
    "iso:country":"ES",
    "sg:address":"Rua Calvo Sotelo, 140",
    "sg:city":"Sarria",
    "sg:orig_category":"Caf\u00c9s, Bares, Cervecer\u00cdas",
    "sg:phone":"+34 982 53 36 64",
    "sg:postcode":"27600",
    "sg:province":"Lugo",
    "wof:name":"Diaz Lopez Carmen",
    "wof:placetype":"venue"
},
  "geometry": {"coordinates":[-7.4092030525,42.7774810791],"type":"Point"}
}