{
  "type": "Feature",
  "properties": {
    "iso:country":"ES",
    "sg:address":"Calle de Principe, 11",
    "sg:city":"Granada",
    "sg:classifiers":[
        {
            "category":"Bars & Pubs",
            "subcategory":"Wine Bar",
            "type":"Food & Drink"
        }
    ],
    "sg:phone":"+34 958 26 32 02",
    "sg:postcode":"18001",
    "sg:province":"Granada",
    "sg:tags":[
        "cd"
    ],
    "wof:name":"Con Pintor Jose Manuel",
    "wof:placetype":"venue"
},
  "geometry": {"coordinates":[-3.5994720459,37.1745681763],"type":"Point"}
}