{
  "type": "Feature",
  "properties": {
    "addr:full":"Plaz Mayor, 15 Casar Palomero C\u00e1ceres 10640",
    "addr:housenumber":"15",
    "addr:postcode":"10640",
    "addr:street":"Plaz Mayor;Ca\u0301Ceres",
    "iso:country":"ES",
    "sg:address":"Plaz Mayor, 15",
    "sg:city":"Casar Palomero",
    "sg:orig_category":"Asesor\u00cda, Estudio Y Control Medioambiental",
    "sg:phone":"+34 927 43 63 75",
    "sg:postcode":"10640",
    "sg:province":"C\u00e1ceres",
    "wof:name":"Jihemse S.l.",
    "wof:placetype":"venue"
},
  "geometry": {"coordinates":[-6.2764458656,40.2459831238],"type":"Point"}
}