{
  "type": "Feature",
  "properties": {
    "addr:full":"Carrer de Valencia, 266 Barcelona Barcelona 08007",
    "addr:housenumber":"266",
    "addr:postcode":"08007",
    "addr:street":"Carrer De Valencia",
    "iso:country":"ES",
    "sg:address":"Carrer de Valencia, 266",
    "sg:city":"Barcelona",
    "sg:orig_category":"Art\u00cdculos De Decoraci\u00d3n",
    "sg:phone":"+34 934 87 26 54",
    "sg:postcode":"08007",
    "sg:province":"Barcelona",
    "wof:name":"Taberdis S.l.",
    "wof:placetype":"venue"
},
  "geometry": {"coordinates":[2.1629359722,41.3922843933],"type":"Point"}
}