{
  "type": "Feature",
  "properties": {
    "addr:full":"Ctra Nacional V (polig Soto), S/n Cazalegas Toledo 45553",
    "addr:housenumber":"s / n",
    "addr:postcode":"45553",
    "addr:street":"Ctra Nacional V Polig Soto",
    "iso:country":"ES",
    "sg:address":"Ctra Nacional V (polig Soto), S/n",
    "sg:city":"Cazalegas",
    "sg:orig_category":"Agricultura: Abastecimiento Y Cosechado (negocio)",
    "sg:phone":"+34 925 86 91 64",
    "sg:postcode":"45553",
    "sg:province":"Toledo",
    "wof:name":"Corralejo 3923 S.l.",
    "wof:placetype":"venue"
},
  "geometry": {"coordinates":[-4.7320308685,39.9928665161],"type":"Point"}
}