{
  "type": "Feature",
  "properties": {
    "iso:country":"ES",
    "sg:address":"Calle de Mendez Nu\u00d1ez, 8",
    "sg:city":"Granada",
    "sg:classifiers":[
        {
            "category":"Casinos & Gambling",
            "type":"Entertainment"
        }
    ],
    "sg:phone":"+34 958 28 37 51",
    "sg:postcode":"18003",
    "sg:province":"Granada",
    "sg:tags":[
        "locale",
        "de",
        "juego"
    ],
    "wof:name":"Juegos Andaca S.a.",
    "wof:placetype":"venue"
},
  "geometry": {"coordinates":[-3.6108939648,37.1778564453],"type":"Point"}
}