{
  "type": "Feature",
  "properties": {
    "iso:country":"ES",
    "sg:address":"Plaz Constitucion, 10",
    "sg:city":"Villacarrillo",
    "sg:orig_category":"\u00d3ptica: Instrumentos (fabricaci\u00d3n)",
    "sg:phone":"+34 953 44 21 93",
    "sg:postcode":"23300",
    "sg:province":"Ja\u00e9n",
    "wof:name":"Ortega Estero Mari Paz",
    "wof:placetype":"venue"
},
  "geometry": {"coordinates":[-3.0878789425,38.1153488159],"type":"Point"}
}