{
  "type": "Feature",
  "properties": {
    "iso:country":"ES",
    "sg:address":"Calle de Ana Belen, 2",
    "sg:city":"Arroyo De La Miel-benalmadena Costa",
    "sg:orig_category":"Inform\u00c1tica, Ofim\u00c1tica (estudios, Asesor\u00cda, Ingenier\u00cda, Formaci\u00d3n)",
    "sg:phone":"+34 952 57 55 18",
    "sg:postcode":"29631",
    "sg:province":"M\u00e1laga",
    "sg:website":"www.pccable.es",
    "wof:name":"Pccable S.l.",
    "wof:placetype":"venue"
},
  "geometry": {"coordinates":[-4.5328426361,36.5984382629],"type":"Point"}
}