{
  "type": "Feature",
  "properties": {
    "iso:country":"ES",
    "sg:address":"Carr Jaume I, 78",
    "sg:city":"Girona",
    "sg:orig_category":"M\u00c9dicos: Ginecolog\u00cda Y Obstetricia",
    "sg:phone":"+34 972 20 78 82",
    "sg:postcode":"17001",
    "sg:province":"Girona",
    "wof:name":"Oliveras Bague Joan",
    "wof:placetype":"venue"
},
  "geometry": {"coordinates":[2.8201799393,41.9814186096],"type":"Point"}
}