{
  "type": "Feature",
  "properties": {
    "addr:full":"Avda Remedios (los), 26 Realejo Alto Santa Cruz De Tenerife 38410",
    "addr:housenumber":"26",
    "addr:postcode":"38410",
    "addr:street":"Avda Remedios Los",
    "iso:country":"ES",
    "sg:address":"Avda Remedios (los), 26",
    "sg:city":"Realejo Alto",
    "sg:orig_category":"Supermercados Y Hipermercados",
    "sg:phone":"+34 922 34 03 61",
    "sg:postcode":"38410",
    "sg:province":"Santa Cruz De Tenerife",
    "wof:name":"Barroso Molina Miguel",
    "wof:placetype":"venue"
},
  "geometry": {"coordinates":[-16.5806484222,28.3678607941],"type":"Point"}
}