{
  "type": "Feature",
  "properties": {
    "addr:full":"Pase Canalejas, 188 Salamanca Salamanca 37008",
    "addr:housenumber":"188",
    "addr:postcode":"37008",
    "addr:street":"Canalejas",
    "iso:country":"ES",
    "sg:address":"Pase Canalejas, 188",
    "sg:city":"Salamanca",
    "sg:orig_category":"Lavado, Limpieza De Veh\u00cdculos",
    "sg:phone":"+34 923 26 64 18",
    "sg:postcode":"37008",
    "sg:province":"Salamanca",
    "wof:name":"Autodisco S. A.",
    "wof:placetype":"venue"
},
  "geometry": {"coordinates":[-5.6600623131,40.9595756531],"type":"Point"}
}