{
  "type": "Feature",
  "properties": {
    "iso:country":"ES",
    "sg:address":"Carrer de Selva De Mar, 44",
    "sg:city":"Barcelona",
    "sg:orig_category":"Molduras, Junquillos, Listones Y Molduras Perforadas",
    "sg:phone":"+34 932 66 04 63",
    "sg:postcode":"08019",
    "sg:province":"Barcelona",
    "wof:name":"Capdevila Compta Maria",
    "wof:placetype":"venue"
},
  "geometry": {"coordinates":[2.2107601166,41.4075813293],"type":"Point"}
}