{
  "type": "Feature",
  "properties": {
    "iso:country":"ES",
    "sg:address":"Atvia De Logro\u00f1o, Km. 0001,5",
    "sg:city":"Zaragoza",
    "sg:orig_category":"Maquinaria Para Industrias Diversas",
    "sg:phone":"+34 976 34 12 26",
    "sg:postcode":"50011",
    "sg:province":"Zaragoza",
    "wof:name":"Figuerola Mateo Miguel Angel",
    "wof:placetype":"venue"
},
  "geometry": {"coordinates":[-1.0011901855,41.6566925049],"type":"Point"}
}