{
  "type": "Feature",
  "properties": {
    "addr:full":"Calle de Juan De Toledo, 7 Lagartera Toledo 45567",
    "addr:housenumber":"7",
    "addr:postcode":"45567",
    "addr:street":"Calle De Juan De Toledo",
    "iso:country":"ES",
    "sg:address":"Calle de Juan De Toledo, 7",
    "sg:city":"Lagartera",
    "sg:orig_category":"Telas Y Sedas (al Por Menor)",
    "sg:phone":"+34 925 43 09 19",
    "sg:postcode":"45567",
    "sg:province":"Toledo",
    "wof:name":"Bravo Igual Jose",
    "wof:placetype":"venue"
},
  "geometry": {"coordinates":[-5.2017021179,39.9065742493],"type":"Point"}
}