{
  "type": "Feature",
  "properties": {
    "addr:full":"Calle de Don Teodomiro, 51 Cordoba C\u00f3rdoba 14014",
    "addr:housenumber":"51",
    "addr:postcode":"14014",
    "addr:street":"Calle De Don Teodomiro;Co\u0301Rdoba",
    "iso:country":"ES",
    "sg:address":"Calle de Don Teodomiro, 51",
    "sg:city":"Cordoba",
    "sg:orig_category":"Empresas De Carpinter\u00cda Met\u00c1lica",
    "sg:phone":"+34 957 43 75 36",
    "sg:postcode":"14014",
    "sg:province":"C\u00f3rdoba",
    "wof:name":"Perficor S.l.",
    "wof:placetype":"venue"
},
  "geometry": {"coordinates":[-4.7515516281,37.8887176514],"type":"Point"}
}