{
  "type": "Feature",
  "properties": {
    "addr:full":"Carrer de Proven\u00c7a, 110 Barcelona Barcelona 08029",
    "addr:housenumber":"110",
    "addr:postcode":"08029",
    "addr:street":"Carrer De Provenc\u0327A",
    "iso:country":"ES",
    "sg:address":"Carrer de Proven\u00c7a, 110",
    "sg:city":"Barcelona",
    "sg:orig_category":"Chapister\u00cda",
    "sg:phone":"+34 934 39 23 67",
    "sg:postcode":"08029",
    "sg:province":"Barcelona",
    "wof:name":"Tallers Travessera 80 S.l.",
    "wof:placetype":"venue"
},
  "geometry": {"coordinates":[2.1491909027,41.3852844238],"type":"Point"}
}