{
  "type": "Feature",
  "properties": {
    "iso:country":"ES",
    "sg:address":"Ctra Granada (de), 61",
    "sg:city":"San Jose",
    "sg:orig_category":"Quincaller\u00cda (al Por Menor)",
    "sg:phone":"+34 968 44 15 16",
    "sg:postcode":"30800",
    "sg:province":"Murcia",
    "sg:website":"www.suministrosbeyma.com",
    "wof:name":"Suministros Beyma S.l.",
    "wof:placetype":"venue"
},
  "geometry": {"coordinates":[-1.6905640364,37.680557251],"type":"Point"}
}