{
  "type": "Feature",
  "properties": {
    "iso:country":"ES",
    "sg:address":"Calle de Marquesa De Almarza, 1",
    "sg:city":"Salamanca",
    "sg:orig_category":"Internados & Ense\u00d1anza Privada",
    "sg:phone":"+34 923 27 00 11",
    "sg:postcode":"37001",
    "sg:province":"Salamanca",
    "wof:name":"Colegio Siervas De San Jose",
    "wof:placetype":"venue"
},
  "geometry": {"coordinates":[-5.6619210243,40.9618797302],"type":"Point"}
}