{
  "type": "Feature",
  "properties": {
    "iso:country":"ES",
    "sg:address":"Almachar, 8",
    "sg:city":"Mijas Costa",
    "sg:orig_category":"Laboratorios",
    "sg:phone":"+34 952 19 92 09",
    "sg:postcode":"29649",
    "sg:province":"M\u00e1laga",
    "wof:name":"Inmunoclic A.i.e.",
    "wof:placetype":"venue"
},
  "geometry": {"coordinates":[-4.6310629845,36.5238952637],"type":"Point"}
}