{
  "type": "Feature",
  "properties": {
    "addr:full":"Onsares De Abajo, S/n Onsares Ja\u00e9n 23393",
    "addr:housenumber":"s",
    "addr:postcode":"23393",
    "addr:street":"Abajo;/ N Onsares Jae\u0301N",
    "iso:country":"ES",
    "sg:address":"Onsares De Abajo, S/n",
    "sg:city":"Onsares",
    "sg:orig_category":"Centros De Educaci\u00d3n Especial",
    "sg:phone":"+34 953 48 30 49",
    "sg:postcode":"23393",
    "sg:province":"Ja\u00e9n",
    "wof:name":"Junta De Andalucia",
    "wof:placetype":"venue"
},
  "geometry": {"coordinates":[-2.6358571053,38.4886817932],"type":"Point"}
}