{
  "type": "Feature",
  "properties": {
    "addr:full":"Calle de Emilio Ostale Tudela, 5 Zaragoza Zaragoza 50011",
    "addr:housenumber":"5",
    "addr:postcode":"50011",
    "addr:street":"Calle De Emilio Ostale Tudela",
    "iso:country":"ES",
    "sg:address":"Calle de Emilio Ostale Tudela, 5",
    "sg:city":"Zaragoza",
    "sg:orig_category":"Plomeros",
    "sg:phone":"+34 976 31 49 58",
    "sg:postcode":"50011",
    "sg:province":"Zaragoza",
    "wof:name":"Saneamientos Oliver S.l.",
    "wof:placetype":"venue"
},
  "geometry": {"coordinates":[-0.9214140177,41.6524353027],"type":"Point"}
}