{
  "type": "Feature",
  "properties": {
    "iso:country":"ES",
    "sg:address":"Grup San Lorenzo, 10",
    "sg:city":"Castellon",
    "sg:orig_category":"Empresas De Carpinter\u00cda",
    "sg:phone":"+34 964 20 02 94",
    "sg:postcode":"12006",
    "sg:province":"Castell\u00f3n",
    "wof:name":"Talleres Masfont S.l",
    "wof:placetype":"venue"
},
  "geometry": {"coordinates":[-0.1292939931,40.0168533325],"type":"Point"}
}