{
  "type": "Feature",
  "properties": {
    "iso:country":"ES",
    "sg:address":"Plaz Iglesia, 11",
    "sg:city":"Lominchar",
    "sg:orig_category":"Iglesia Cat\u00d3lica",
    "sg:phone":"+34 925 55 81 35",
    "sg:postcode":"45212",
    "sg:province":"Toledo",
    "wof:name":"Parroquia San Esteban",
    "wof:placetype":"venue"
},
  "geometry": {"coordinates":[-3.962829113,40.0889167786],"type":"Point"}
}