{
  "type": "Feature",
  "properties": {
    "addr:full":"Av Estrella(pol Ind Estrella), 19 Torre-pacheco Murcia 30700",
    "addr:housenumber":"19",
    "addr:postcode":"30700",
    "addr:street":"Av Estrella Pol;Estrella",
    "iso:country":"ES",
    "sg:address":"Av Estrella(pol Ind Estrella), 19",
    "sg:city":"Torre-pacheco",
    "sg:orig_category":"Mec\u00c1nico Del Autom\u00d3vil",
    "sg:phone":"+34 968 58 74 15",
    "sg:postcode":"30700",
    "sg:province":"Murcia",
    "wof:name":"Talleres Salvador Ris Leon S.l.",
    "wof:placetype":"venue"
},
  "geometry": {"coordinates":[-1.1514149904,38.0151138306],"type":"Point"}
}