{
  "type": "Feature",
  "properties": {
    "addr:full":"Avia Puente Colgante, 33 Valladolid Valladolid 47014",
    "addr:housenumber":"33",
    "addr:postcode":"47014",
    "addr:street":"Puente Colgante",
    "iso:country":"ES",
    "sg:address":"Avia Puente Colgante, 33",
    "sg:city":"Valladolid",
    "sg:orig_category":"Supermercados Y Hipermercados",
    "sg:phone":"+34 983 22 85 60",
    "sg:postcode":"47014",
    "sg:province":"Valladolid",
    "wof:name":"Supercor S.a.",
    "wof:placetype":"venue"
},
  "geometry": {"coordinates":[-4.7439498901,41.6410293579],"type":"Point"}
}