{
  "type": "Feature",
  "properties": {
    "addr:full":"Alam San Mames, 37 Bilbao Vizcaya 48010",
    "addr:housenumber":"37",
    "addr:postcode":"48010",
    "addr:street":"Alam San Mames",
    "iso:country":"ES",
    "sg:address":"Alam San Mames, 37",
    "sg:city":"Bilbao",
    "sg:orig_category":"Seguridad En El Trabajo Y Prevenci\u00d3n De Riesgos Laborales",
    "sg:phone":"+34 944 21 30 82",
    "sg:postcode":"48010",
    "sg:province":"Vizcaya",
    "wof:name":"Segycal S.l.",
    "wof:placetype":"venue"
},
  "geometry": {"coordinates":[-2.9382989407,43.2593727112],"type":"Point"}
}