{
  "type": "Feature",
  "properties": {
    "addr:full":"Pase Cauce, 30 Valladolid Valladolid 47010",
    "addr:housenumber":"30",
    "addr:postcode":"47010",
    "addr:street":"Cauce",
    "iso:country":"ES",
    "sg:address":"Pase Cauce, 30",
    "sg:city":"Valladolid",
    "sg:orig_category":"Plomeros",
    "sg:phone":"+34 983 25 60 62",
    "sg:postcode":"47010",
    "sg:province":"Valladolid",
    "wof:name":"Blanco Esteban Mariano",
    "wof:placetype":"venue"
},
  "geometry": {"coordinates":[-4.7160859108,41.6638221741],"type":"Point"}
}