{
  "type": "Feature",
  "properties": {
    "addr:full":"Avda Andalucia, 124 Estepona M\u00e1laga 29680",
    "addr:housenumber":"124",
    "addr:postcode":"29680",
    "addr:street":"Avda Andalucia",
    "iso:country":"ES",
    "sg:address":"Avda Andalucia, 124",
    "sg:city":"Estepona",
    "sg:orig_category":"Estudios, Instalaci\u00d3n De Climatizaci\u00d3n",
    "sg:phone":"+34 952 79 45 70",
    "sg:postcode":"29680",
    "sg:province":"M\u00e1laga",
    "wof:name":"Fradejas Lorenzo Isabel",
    "wof:placetype":"venue"
},
  "geometry": {"coordinates":[-5.1459650993,36.4313163757],"type":"Point"}
}