{
  "type": "Feature",
  "properties": {
    "iso:country":"ES",
    "sg:address":"Calle de Segovia, 59",
    "sg:city":"Madrid",
    "sg:orig_category":"Venta, Montaje De Neum\u00c1ticos",
    "sg:phone":"+34 913 65 87 15",
    "sg:postcode":"28005",
    "sg:province":"Madrid",
    "wof:name":"Autodisco S.a.",
    "wof:placetype":"venue"
},
  "geometry": {"coordinates":[-3.7186973095,40.4137611389],"type":"Point"}
}