{
  "type": "Feature",
  "properties": {
    "iso:country":"ES",
    "sg:address":"Plaz Espa\u00d1a, 2",
    "sg:city":"Tobarra",
    "sg:orig_category":"Electricidad: Instaladores",
    "sg:phone":"+34 967 32 82 00",
    "sg:postcode":"02500",
    "sg:province":"Albacete",
    "wof:name":"Electrotobarra S.l.",
    "wof:placetype":"venue"
},
  "geometry": {"coordinates":[-1.6922299862,38.5883102417],"type":"Point"}
}