{
  "type": "Feature",
  "properties": {
    "iso:country":"ES",
    "sg:address":"Avda Luis Casais, 10",
    "sg:city":"Grove",
    "sg:orig_category":"Lencer\u00cda Femenina, Corseter\u00cda, Trajes De Ba\u00d1o (al Por Menor)",
    "sg:phone":"+34 986 73 28 09",
    "sg:postcode":"36980",
    "sg:province":"Pontevedra",
    "wof:name":"Costal Cameselle Maria Jesus",
    "wof:placetype":"venue"
},
  "geometry": {"coordinates":[-8.8615665436,42.4951515198],"type":"Point"}
}