{
  "type": "Feature",
  "properties": {
    "addr:full":"Plaz Estacion, 5 Toral De Los Vados Le\u00f3n 24560",
    "addr:housenumber":"5",
    "addr:postcode":"24560",
    "addr:street":"Estacion",
    "iso:country":"ES",
    "sg:address":"Plaz Estacion, 5",
    "sg:city":"Toral De Los Vados",
    "sg:orig_category":"Telas Y Sedas (al Por Menor)",
    "sg:phone":"+34 987 54 46 24",
    "sg:postcode":"24560",
    "sg:province":"Le\u00f3n",
    "wof:name":"Guibelalde Regueiro Pedro",
    "wof:placetype":"venue"
},
  "geometry": {"coordinates":[-6.7822341919,42.5436286926],"type":"Point"}
}