{
  "type": "Feature",
  "properties": {
    "addr:full":"Calle de Isaac Peral, 3 Palencia Palencia 34004",
    "addr:housenumber":"3",
    "addr:postcode":"34004",
    "addr:street":"Calle De Isaac Peral",
    "iso:country":"ES",
    "sg:address":"Calle de Isaac Peral, 3",
    "sg:city":"Palencia",
    "sg:orig_category":"Fabricaci\u00d3n, Venta De Cuadros, Accesorios Para Enmarcar",
    "sg:phone":"+34 979 72 84 99",
    "sg:postcode":"34004",
    "sg:province":"Palencia",
    "wof:name":"Nieto Citores Lourdes De Los Angeles",
    "wof:placetype":"venue"
},
  "geometry": {"coordinates":[-4.5246372223,42.0035095215],"type":"Point"}
}