{
  "type": "Feature",
  "properties": {
    "iso:country":"ES",
    "sg:address":"Carrer de Cabrera, 12",
    "sg:city":"S. Quirze Valles",
    "sg:orig_category":"Electricidad, Electr\u00d3nica: Suministros (al Por Menor)",
    "sg:phone":"+34 937 21 35 54",
    "sg:postcode":"08192",
    "sg:province":"Barcelona",
    "wof:name":"Omikron Barcelona S.l.",
    "wof:placetype":"venue"
},
  "geometry": {"coordinates":[2.0936560631,41.5220870972],"type":"Point"}
}