{
  "type": "Feature",
  "properties": {
    "iso:country":"ES",
    "sg:address":"Pg Colom, S/n",
    "sg:city":"Barcelona",
    "sg:orig_category":"Ense\u00d1anza, Formaci\u00d3n Profesional: Aprendizaje",
    "sg:phone":"+34 933 01 54 68",
    "sg:postcode":"08002",
    "sg:province":"Barcelona",
    "wof:name":"Jefatura De Artilleria De La 4\u00aa Region Militar",
    "wof:placetype":"venue"
},
  "geometry": {"coordinates":[2.1804099083,41.3793067932],"type":"Point"}
}