{
  "type": "Feature",
  "properties": {
    "addr:full":"Avda Castellon, 162 Almazora Castell\u00f3n 12550",
    "addr:housenumber":"162",
    "addr:postcode":"12550",
    "addr:street":"Avda Castellon",
    "iso:country":"ES",
    "sg:address":"Avda Castellon, 162",
    "sg:city":"Almazora",
    "sg:orig_category":"Empresas De Pintura Y Revestimientos",
    "sg:phone":"+34 964 56 10 05",
    "sg:postcode":"12550",
    "sg:province":"Castell\u00f3n",
    "wof:name":"Tena Barrachina Juan",
    "wof:placetype":"venue"
},
  "geometry": {"coordinates":[-0.0604390018,39.9470405579],"type":"Point"}
}