{
  "type": "Feature",
  "properties": {
    "addr:full":"Carrer de Proven\u00c7a, 539 Barcelona Barcelona 08025",
    "addr:housenumber":"539",
    "addr:postcode":"08025",
    "addr:street":"Carrer De Provenc\u0327A",
    "iso:country":"ES",
    "sg:address":"Carrer de Proven\u00c7a, 539",
    "sg:city":"Barcelona",
    "sg:orig_category":"T\u00c9cnicos Veterinarios",
    "sg:phone":"+34 934 56 58 59",
    "sg:postcode":"08025",
    "sg:province":"Barcelona",
    "wof:name":"Nuri Salles Ramon",
    "wof:placetype":"venue"
},
  "geometry": {"coordinates":[2.179721117,41.4085884094],"type":"Point"}
}