{
  "type": "Feature",
  "properties": {
    "addr:full":"Calle de Ruiz, 7 Madrid Madrid 28004",
    "addr:housenumber":"7",
    "addr:postcode":"madrid;28004",
    "addr:street":"Calle De Ruiz",
    "iso:country":"ES",
    "sg:address":"Calle de Ruiz, 7",
    "sg:city":"Madrid",
    "sg:orig_category":"Caf\u00c9s, Bares, Cervecer\u00cdas",
    "sg:phone":"+34 914 45 91 33",
    "sg:postcode":"28004",
    "sg:province":"Madrid",
    "wof:name":"Buquerin Catalina Francisco Javier",
    "wof:placetype":"venue"
},
  "geometry": {"coordinates":[-3.7040739059,40.4278831482],"type":"Point"}
}