{
  "type": "Feature",
  "properties": {
    "addr:full":"Calle de Alfonso Xii, 48 Madrid Madrid 28014",
    "addr:housenumber":"48",
    "addr:postcode":"madrid;28014",
    "addr:street":"Calle De Alfonso Xii",
    "iso:country":"ES",
    "sg:address":"Calle de Alfonso Xii, 48",
    "sg:city":"Madrid",
    "sg:orig_category":"Abogados",
    "sg:phone":"+34 913 69 14 14",
    "sg:postcode":"28014",
    "sg:province":"Madrid",
    "sg:website":"www.gcv-abogados.com",
    "wof:name":"Gomez-casero Valcarcel Y Asociados S.l.",
    "wof:placetype":"venue"
},
  "geometry": {"coordinates":[-3.688929081,40.4123077393],"type":"Point"}
}