{
  "type": "Feature",
  "properties": {
    "addr:full":"Rbla Pompeu Fabra, 144 Gava Barcelona 08850",
    "addr:housenumber":"144",
    "addr:postcode":"08850",
    "addr:street":"Rbla Pompeu Fabra",
    "iso:country":"ES",
    "sg:address":"Rbla Pompeu Fabra, 144",
    "sg:city":"Gava",
    "sg:orig_category":"Deportes Y Programas De Aventura",
    "sg:phone":"+34 936 62 46 91",
    "sg:postcode":"08850",
    "sg:province":"Barcelona",
    "wof:name":"Club Basket Gava",
    "wof:placetype":"venue"
},
  "geometry": {"coordinates":[2.0029499531,41.3097381592],"type":"Point"}
}