{
  "type": "Feature",
  "properties": {
    "addr:full":"Avda Valle, 59 Plasencia C\u00e1ceres 10600",
    "addr:housenumber":"59",
    "addr:postcode":"10600",
    "addr:street":"Avda Valle;Ca\u0301Ceres",
    "iso:country":"ES",
    "sg:address":"Avda Valle, 59",
    "sg:city":"Plasencia",
    "sg:orig_category":"Promotores Constructores",
    "sg:phone":"+34 927 42 64 93",
    "sg:postcode":"10600",
    "sg:province":"C\u00e1ceres",
    "wof:name":"Alicatadores Romu, S.l.",
    "wof:placetype":"venue"
},
  "geometry": {"coordinates":[-6.0833296776,40.0308265686],"type":"Point"}
}