{
  "type": "Feature",
  "properties": {
    "addr:full":"Calle de Serrano, 4 Villarta S. Juan Ciudad Real 13210",
    "addr:housenumber":"4",
    "addr:postcode":"13210",
    "addr:street":"Calle De Serrano;Villarta S. Juan Ciudad Real",
    "iso:country":"ES",
    "sg:address":"Calle de Serrano, 4",
    "sg:city":"Villarta S. Juan",
    "sg:orig_category":"Empresarios",
    "sg:phone":"+34 926 64 01 48",
    "sg:postcode":"13210",
    "sg:province":"Ciudad Real",
    "wof:name":"Rojo Garcia Leandro",
    "wof:placetype":"venue"
},
  "geometry": {"coordinates":[-3.4233880043,39.2358589172],"type":"Point"}
}