{
  "type": "Feature",
  "properties": {
    "iso:country":"ES",
    "sg:address":"Pase Maria Agustin, 38",
    "sg:city":"Zaragoza",
    "sg:orig_category":"Pe\u00d1as Y Asociaciones Varias",
    "sg:phone":"+34 976 28 56 19",
    "sg:postcode":"50004",
    "sg:province":"Zaragoza",
    "wof:name":"Ascomaex",
    "wof:placetype":"venue"
},
  "geometry": {"coordinates":[-0.8922770023,41.6531143188],"type":"Point"}
}