{
  "type": "Feature",
  "properties": {
    "addr:full":"Carr Sant Joan Baptista De La Salle, 24 Seu D'urgell Lleida 25700",
    "addr:housenumber":"24",
    "addr:postcode":"25700",
    "addr:street":"Carr Sant Joan Baptista De La Salle",
    "iso:country":"ES",
    "sg:address":"Carr Sant Joan Baptista De La Salle, 24",
    "sg:city":"Seu D'urgell",
    "sg:orig_category":"Agencias De Viajes",
    "sg:phone":"+34 973 35 48 51",
    "sg:postcode":"25700",
    "sg:province":"Lleida",
    "wof:name":"Tarres Viatges S.l.",
    "wof:placetype":"venue"
},
  "geometry": {"coordinates":[0.646551013,41.6026687622],"type":"Point"}
}