{
  "type": "Feature",
  "properties": {
    "iso:country":"ES",
    "sg:address":"Avda Lopez Ballesteros, 2",
    "sg:city":"Vilagarcia",
    "sg:orig_category":"Ense\u00d1anza: Costura",
    "sg:phone":"+34 986 51 08 27",
    "sg:postcode":"36600",
    "sg:province":"Pontevedra",
    "wof:name":"Hernandez Castillo Luis",
    "wof:placetype":"venue"
},
  "geometry": {"coordinates":[-8.7633886337,42.597820282],"type":"Point"}
}