{
  "type": "Feature",
  "properties": {
    "addr:full":"Carr Conde De Rodezno, 19 Quart Poblet Valencia 46930",
    "addr:housenumber":"19",
    "addr:postcode":"46930",
    "addr:street":"Carr Conde De Rodezno;Poblet",
    "iso:country":"ES",
    "sg:address":"Carr Conde De Rodezno, 19",
    "sg:city":"Quart Poblet",
    "sg:orig_category":"Distribuci\u00d3n De Petr\u00d3leo Y Derivados",
    "sg:phone":"+34 961 53 42 52",
    "sg:postcode":"46930",
    "sg:province":"Valencia",
    "sg:website":"www.cepsa.es",
    "wof:name":"Lagaso Inversiones S.l.",
    "wof:placetype":"venue"
},
  "geometry": {"coordinates":[-0.4480220079,39.4805030823],"type":"Point"}
}