{
  "type": "Feature",
  "properties": {
    "iso:country":"ES",
    "sg:address":"Carrer de Pau Claris, 103",
    "sg:city":"Barcelona",
    "sg:orig_category":"Alquiler De V\u00cddeo",
    "sg:phone":"+34 933 18 18 35",
    "sg:postcode":"08009",
    "sg:province":"Barcelona",
    "wof:name":"Fundi-dos S.l.",
    "wof:placetype":"venue"
},
  "geometry": {"coordinates":[2.1687860489,41.3912734985],"type":"Point"}
}