{
  "type": "Feature",
  "properties": {
    "addr:full":"Carr Colomi, S/n Platja D'alcudia Islas Baleares 07408",
    "addr:housenumber":"s / n",
    "addr:postcode":"07408",
    "addr:street":"Carr Colomi;D'Alcudia",
    "iso:country":"ES",
    "sg:address":"Carr Colomi, S/n",
    "sg:city":"Platja D'alcudia",
    "sg:orig_category":"Caf\u00c9s, Bares, Cervecer\u00cdas",
    "sg:phone":"+34 971 89 10 95",
    "sg:postcode":"07408",
    "sg:province":"Islas Baleares",
    "wof:name":"Dubalva S.l.",
    "wof:placetype":"venue"
},
  "geometry": {"coordinates":[3.1220939159,39.8534736633],"type":"Point"}
}