{
  "type": "Feature",
  "properties": {
    "iso:country":"ES",
    "sg:address":"Calle de Caleta Del Jurado, 1",
    "sg:city":"Puerto Santiago",
    "sg:orig_category":"Abogados",
    "sg:phone":"+34 922 86 24 27",
    "sg:postcode":"38683",
    "sg:province":"Santa Cruz De Tenerife",
    "wof:name":"Cantillon  Patrick",
    "wof:placetype":"venue"
},
  "geometry": {"coordinates":[-16.8411998749,28.2355442047],"type":"Point"}
}