{
  "type": "Feature",
  "properties": {
    "addr:full":"Trva Industria De La, 4 Aviles Asturias 33401",
    "addr:housenumber":"4",
    "addr:postcode":"33401",
    "addr:street":"Trva Industria De La",
    "iso:country":"ES",
    "sg:address":"Trva Industria De La, 4",
    "sg:city":"Aviles",
    "sg:orig_category":"Venta, Montaje De Neum\u00c1ticos",
    "sg:phone":"+34 985 56 25 71",
    "sg:postcode":"33401",
    "sg:province":"Asturias",
    "wof:name":"Casero Suarez Maria Mercedes",
    "wof:placetype":"venue"
},
  "geometry": {"coordinates":[-5.9253520966,43.5651817322],"type":"Point"}
}