{
  "type": "Feature",
  "properties": {
    "iso:country":"ES",
    "sg:address":"Plaz Ejercito, 1",
    "sg:city":"Valladolid",
    "sg:orig_category":"Farmacias",
    "sg:phone":"+34 983 23 27 71",
    "sg:postcode":"47007",
    "sg:province":"Valladolid",
    "wof:name":"Ureta Ruiz De Clavijo Maria Teresa",
    "wof:placetype":"venue"
},
  "geometry": {"coordinates":[-4.6675691605,41.5873718262],"type":"Point"}
}