{
  "type": "Feature",
  "properties": {
    "addr:full":"Cmno Molinos (de Los), 79 Zaragoza Zaragoza 50015",
    "addr:housenumber":"79",
    "addr:postcode":"50015",
    "addr:street":"Cmno Molinos De Los",
    "iso:country":"ES",
    "sg:address":"Cmno Molinos (de Los), 79",
    "sg:city":"Zaragoza",
    "sg:orig_category":"Pintura: M\u00c1quinas (instalaci\u00d3n)",
    "sg:phone":"+34 976 73 66 90",
    "sg:postcode":"50015",
    "sg:province":"Zaragoza",
    "sg:website":"www.spraymaq.es",
    "wof:name":"Spraymaq S. A.",
    "wof:placetype":"venue"
},
  "geometry": {"coordinates":[-0.8681709766,41.6785011292],"type":"Point"}
}