{
  "type": "Feature",
  "properties": {
    "addr:full":"Carrer de Pi I Margall, 23 Molins Rei Barcelona 08750",
    "addr:housenumber":"23",
    "addr:postcode":"08750",
    "addr:street":"Carrer De Pi I Margall;Barcelona",
    "iso:country":"ES",
    "sg:address":"Carrer de Pi I Margall, 23",
    "sg:city":"Molins Rei",
    "sg:orig_category":"Agentes Generales De Seguros",
    "sg:phone":"+34 936 68 41 26",
    "sg:postcode":"08750",
    "sg:province":"Barcelona",
    "wof:name":"Galimany Pubill Jose",
    "wof:placetype":"venue"
},
  "geometry": {"coordinates":[2.0191130638,41.4095039368],"type":"Point"}
}