{
  "type": "Feature",
  "properties": {
    "iso:country":"ES",
    "sg:address":"Calle de Ugijar, 29",
    "sg:city":"Peligros",
    "sg:orig_category":"Art\u00cdculos De Regalo (al Por Menor)",
    "sg:phone":"+34 958 46 78 08",
    "sg:postcode":"18210",
    "sg:province":"Granada",
    "wof:name":"Taljou  Ghalib",
    "wof:placetype":"venue"
},
  "geometry": {"coordinates":[-3.6360590458,37.2232666016],"type":"Point"}
}