{
  "type": "Feature",
  "properties": {
    "addr:full":"Carrer de Salvador Espriu, 65 Barcelona Barcelona 08005",
    "addr:housenumber":"65",
    "addr:postcode":"08005",
    "addr:street":"Carrer De Salvador Espriu",
    "iso:country":"ES",
    "sg:address":"Carrer de Salvador Espriu, 65",
    "sg:city":"Barcelona",
    "sg:orig_category":"Ceras Y Encaustos (fabricaci\u00d3n, Al Por Mayor)",
    "sg:phone":"+34 932 21 36 48",
    "sg:postcode":"08005",
    "sg:province":"Barcelona",
    "wof:name":"Mediterrania 94 S.a.",
    "wof:placetype":"venue"
},
  "geometry": {"coordinates":[2.1989970207,41.3904800415],"type":"Point"}
}