{
  "type": "Feature",
  "properties": {
    "addr:full":"Drago, 42 San Cristobal De La Laguna Santa Cruz De Tenerife 38205",
    "addr:housenumber":"42",
    "addr:postcode":"38205",
    "addr:street":"Drago",
    "iso:country":"ES",
    "sg:address":"Drago, 42",
    "sg:city":"San Cristobal De La Laguna",
    "sg:orig_category":"Frutas, Legumbres Frescas Y Tempranas (al Por Menor)",
    "sg:phone":"+34 922 25 42 27",
    "sg:postcode":"38205",
    "sg:province":"Santa Cruz De Tenerife",
    "wof:name":"Hernandez Hernandez Siro Julian",
    "wof:placetype":"venue"
},
  "geometry": {"coordinates":[-16.298746109,28.4750785828],"type":"Point"}
}