{
  "type": "Feature",
  "properties": {
    "addr:full":"Calle de Andalucia, 20 Trigueros Huelva 21620",
    "addr:housenumber":"20",
    "addr:postcode":"21620",
    "addr:street":"Calle De Andalucia",
    "iso:country":"ES",
    "sg:address":"Calle de Andalucia, 20",
    "sg:city":"Trigueros",
    "sg:orig_category":"Cajas De Ahorro",
    "sg:phone":"+34 959 30 56 79",
    "sg:postcode":"21620",
    "sg:province":"Huelva",
    "sg:website":"www.lacaixa.es",
    "wof:name":"Caixa D'estalvis I Pensions De Barcelona",
    "wof:placetype":"venue"
},
  "geometry": {"coordinates":[-6.8351435661,37.3830718994],"type":"Point"}
}