{
  "type": "Feature",
  "properties": {
    "addr:full":"San Miguel Auzoa, 9 Legorreta Guip\u00f9zcoa 20250",
    "addr:housenumber":"9",
    "addr:postcode":"20250",
    "addr:street":"San Miguel Auzoa;Guipu\u0300Zcoa",
    "iso:country":"ES",
    "sg:address":"San Miguel Auzoa, 9",
    "sg:city":"Legorreta",
    "sg:orig_category":"Paneles De Madera: Contrachapados, Fibras, Particulados, Estratificados (fabricaci\u00d3n, Venta)",
    "sg:phone":"+34 943 80 70 00",
    "sg:postcode":"20250",
    "sg:province":"Guip\u00f9zcoa",
    "sg:website":"www.prodema.com",
    "wof:name":"Prodema S. A.",
    "wof:placetype":"venue"
},
  "geometry": {"coordinates":[-2.1403119564,43.0859947205],"type":"Point"}
}