{
  "type": "Feature",
  "properties": {
    "iso:country":"ES",
    "sg:address":"Rua Padre Luis Maria Fernandez, 3",
    "sg:city":"Pontevedra",
    "sg:orig_category":"Promotores Constructores",
    "sg:phone":"+34 986 86 44 66",
    "sg:postcode":"36002",
    "sg:province":"Pontevedra",
    "wof:name":"Elias Prado Casas S.l.",
    "wof:placetype":"venue"
},
  "geometry": {"coordinates":[-8.6424474716,42.4324188232],"type":"Point"}
}