{
  "type": "Feature",
  "properties": {
    "iso:country":"ES",
    "sg:address":"Calle de Pardo Jimeno, 8",
    "sg:city":"Alacant",
    "sg:orig_category":"Agentes Generales De Seguros",
    "sg:phone":"+34 965 92 08 07",
    "sg:postcode":"03007",
    "sg:province":"Alicante",
    "wof:name":"Pomares Esteve Ana",
    "wof:placetype":"venue"
},
  "geometry": {"coordinates":[-0.4963369071,38.3418159485],"type":"Point"}
}