{
  "type": "Feature",
  "properties": {
    "iso:country":"ES",
    "sg:address":"Av Reis Catolics, 117",
    "sg:city":"Inca",
    "sg:orig_category":"Molduras, Junquillos, Listones Y Molduras Perforadas",
    "sg:phone":"+34 971 50 21 36",
    "sg:postcode":"07300",
    "sg:province":"Islas Baleares",
    "wof:name":"Maquinas De Internet S.l.",
    "wof:placetype":"venue"
},
  "geometry": {"coordinates":[2.9172599316,39.7203292847],"type":"Point"}
}