{
  "type": "Feature",
  "properties": {
    "iso:country":"ES",
    "sg:address":"Calle de Encartaciones, 7",
    "sg:city":"Bilbao",
    "sg:orig_category":"Peluqueros: De Se\u00d1oras",
    "sg:phone":"+34 944 47 28 74",
    "sg:postcode":"48015",
    "sg:province":"Vizcaya",
    "wof:name":"Oteo Alvarez Maria Luisa",
    "wof:placetype":"venue"
},
  "geometry": {"coordinates":[-2.9597620964,43.2778930664],"type":"Point"}
}