{
  "type": "Feature",
  "properties": {
    "iso:country":"ES",
    "sg:address":"Calle de Zabaleta, 47",
    "sg:city":"Donostia-san Sebastian",
    "sg:orig_category":"Molduras, Junquillos, Listones Y Molduras Perforadas",
    "sg:phone":"+34 943 27 38 27",
    "sg:postcode":"20002",
    "sg:province":"Guip\u00f9zcoa",
    "wof:name":"Rosa Atalaya Maria Encarnacion",
    "wof:placetype":"venue"
},
  "geometry": {"coordinates":[-1.9737930298,43.3249320984],"type":"Point"}
}