{
  "type": "Feature",
  "properties": {
    "addr:full":"Calle de Guardia Civil, 10 Santa Maria De Guia Las Palmas 35450",
    "addr:housenumber":"10",
    "addr:postcode":"35450",
    "addr:street":"Calle De Guardia Civil",
    "iso:country":"ES",
    "sg:address":"Calle de Guardia Civil, 10",
    "sg:city":"Santa Maria De Guia",
    "sg:orig_category":"C\u00c1maras De Comercio E Industria, Oficios, Agricultura",
    "sg:phone":"+34 928 88 09 69",
    "sg:postcode":"35450",
    "sg:province":"Las Palmas",
    "wof:name":"Camara Oficial De Comercio Industria Y Navegacion De Las Palmas",
    "wof:placetype":"venue"
},
  "geometry": {"coordinates":[-15.6350135803,28.1420059204],"type":"Point"}
}