{
  "type": "Feature",
  "properties": {
    "iso:country":"ES",
    "sg:address":"Carrer de Montcada, 26",
    "sg:city":"Castellar Valles",
    "sg:orig_category":"Reposter\u00cdas",
    "sg:phone":"+34 937 14 82 01",
    "sg:postcode":"08211",
    "sg:province":"Barcelona",
    "wof:name":"Joan Grane Sellares I Cia S.c.p.",
    "wof:placetype":"venue"
},
  "geometry": {"coordinates":[2.0892999172,41.6148757935],"type":"Point"}
}