{
  "type": "Feature",
  "properties": {
    "iso:country":"ES",
    "sg:address":"Carrer de Puig Rom, 128",
    "sg:city":"Roses",
    "sg:orig_category":"Ense\u00d1anza, Formaci\u00d3n Profesional: Aprendizaje",
    "sg:phone":"+34 972 15 27 57",
    "sg:postcode":"17480",
    "sg:province":"Girona",
    "wof:name":"Forma I Colors",
    "wof:placetype":"venue"
},
  "geometry": {"coordinates":[3.1895680428,42.254737854],"type":"Point"}
}