{
  "type": "Feature",
  "properties": {
    "addr:full":"Calle de Martinez De La Rosa, 16 San Isidro Las Palmas 35200",
    "addr:housenumber":"16",
    "addr:postcode":"35200",
    "addr:street":"Calle De Martinez De La Rosa",
    "iso:country":"ES",
    "sg:address":"Calle de Martinez De La Rosa, 16",
    "sg:city":"San Isidro",
    "sg:orig_category":"Alquiler De Gr\u00daas",
    "sg:phone":"+34 928 69 10 54",
    "sg:postcode":"35200",
    "sg:province":"Las Palmas",
    "wof:name":"Rodriguez Silva Carmen",
    "wof:placetype":"venue"
},
  "geometry": {"coordinates":[-15.4144220352,28.0029888153],"type":"Point"}
}