{
  "type": "Feature",
  "properties": {
    "iso:country":"ES",
    "sg:address":"Carrer de Pilar, 21",
    "sg:city":"Premia Mar",
    "sg:orig_category":"Guarder\u00cdas",
    "sg:phone":"+34 937 51 15 87",
    "sg:postcode":"08330",
    "sg:province":"Barcelona",
    "wof:name":"Gomez Serrano Nuria",
    "wof:placetype":"venue"
},
  "geometry": {"coordinates":[2.3553469181,41.4935531616],"type":"Point"}
}