{
  "type": "Feature",
  "properties": {
    "addr:full":"Pase Alberto Palacios, 27 Madrid Madrid 28021",
    "addr:housenumber":"27",
    "addr:postcode":"madrid;28021",
    "addr:street":"Alberto Palacios",
    "iso:country":"ES",
    "sg:address":"Pase Alberto Palacios, 27",
    "sg:city":"Madrid",
    "sg:orig_category":"Farmacias",
    "sg:phone":"+34 917 97 17 73",
    "sg:postcode":"28021",
    "sg:province":"Madrid",
    "wof:name":"Martinez Marcos Maria Del Carmen",
    "wof:placetype":"venue"
},
  "geometry": {"coordinates":[-3.7122039795,40.3427696228],"type":"Point"}
}