{
  "type": "Feature",
  "properties": {
    "iso:country":"ES",
    "sg:address":"Av Ramon Espinet, 32",
    "sg:city":"Alguaire",
    "sg:orig_category":"Agricultores, Agricultores",
    "sg:phone":"+34 973 75 61 31",
    "sg:postcode":"25125",
    "sg:province":"Lleida",
    "wof:name":"Agropecuaria Roig C. B.",
    "wof:placetype":"venue"
},
  "geometry": {"coordinates":[0.5883560777,41.7388496399],"type":"Point"}
}