{
  "type": "Feature",
  "properties": {
    "iso:country":"ES",
    "sg:address":"Calle de Toledo, 20",
    "sg:city":"Villa Don Fadrique",
    "sg:orig_category":"Droguer\u00cdas (al Por Menor)",
    "sg:phone":"+34 925 19 53 65",
    "sg:postcode":"45850",
    "sg:province":"Toledo",
    "wof:name":"Manzanero Izquierda Maria Cruz",
    "wof:placetype":"venue"
},
  "geometry": {"coordinates":[-3.2199089527,39.6170196533],"type":"Point"}
}