{
  "type": "Feature",
  "properties": {
    "addr:full":"Calle de Plegarias, 14 Le\u00f3n Le\u00f3n 24003",
    "addr:housenumber":"14",
    "addr:postcode":"24003",
    "addr:street":"Calle De Plegarias;Leo\u0301N",
    "iso:country":"ES",
    "sg:address":"Calle de Plegarias, 14",
    "sg:city":"Le\u00f3n",
    "sg:orig_category":"Fabricaci\u00d3n De Mantequilla (al Por Mayor)",
    "sg:phone":"+34 987 25 50 18",
    "sg:postcode":"24003",
    "sg:province":"Le\u00f3n",
    "wof:name":"Carro Sanz Manuel",
    "wof:placetype":"venue"
},
  "geometry": {"coordinates":[-5.5677042007,42.5970802307],"type":"Point"}
}