{
  "type": "Feature",
  "properties": {
    "iso:country":"ES",
    "sg:address":"Carrer de Mallorca, 4",
    "sg:city":"Olesa Montserrat",
    "sg:orig_category":"Organizaciones Internacionales",
    "sg:phone":"+34 937 78 59 38",
    "sg:postcode":"08640",
    "sg:province":"Barcelona",
    "wof:name":"Dones I Progres S.cv.",
    "wof:placetype":"venue"
},
  "geometry": {"coordinates":[1.8926030397,41.5441627502],"type":"Point"}
}