{
  "type": "Feature",
  "properties": {
    "addr:full":"Carr Major (cas Concos), 34 Cas Concos Des Cavaller Islas Baleares 07208",
    "addr:housenumber":"34",
    "addr:postcode":"07208",
    "addr:street":"Carr Major Cas Concos;Islas",
    "iso:country":"ES",
    "sg:address":"Carr Major (cas Concos), 34",
    "sg:city":"Cas Concos Des Cavaller",
    "sg:orig_category":"M\u00c9dicos: Medicina General Orientada A La Homeopat\u00cda",
    "sg:phone":"+34 971 84 22 32",
    "sg:postcode":"07208",
    "sg:province":"Islas Baleares",
    "wof:name":"Adrover Tirado Andreu",
    "wof:placetype":"venue"
},
  "geometry": {"coordinates":[3.1367135048,39.4184455872],"type":"Point"}
}