{
  "type": "Feature",
  "properties": {
    "addr:full":"Avda Novelda, 148 Alacant Alicante 03011",
    "addr:housenumber":"148",
    "addr:postcode":"03011",
    "addr:street":"Avda Novelda",
    "iso:country":"ES",
    "sg:address":"Avda Novelda, 148",
    "sg:city":"Alacant",
    "sg:orig_category":"Lavado, Limpieza De Veh\u00cdculos",
    "sg:phone":"+34 965 17 22 36",
    "sg:postcode":"03011",
    "sg:province":"Alicante",
    "wof:name":"Bobrubor S.l.",
    "wof:placetype":"venue"
},
  "geometry": {"coordinates":[-0.4984689951,38.373840332],"type":"Point"}
}