{
  "type": "Feature",
  "properties": {
    "addr:full":"Avda Calzada Del Ejercito, 3 Sanlucar De Barrameda C\u00e1diz 11540",
    "addr:housenumber":"3",
    "addr:postcode":"11540",
    "addr:street":"Avda Calzada Del Ejercito;Ca\u0301Diz",
    "iso:country":"ES",
    "sg:address":"Avda Calzada Del Ejercito, 3",
    "sg:city":"Sanlucar De Barrameda",
    "sg:orig_category":"Molduras, Junquillos, Listones Y Molduras Perforadas",
    "sg:phone":"+34 956 36 18 02",
    "sg:postcode":"11540",
    "sg:province":"C\u00e1diz",
    "wof:name":"Monta\u00f1o Rodriguez Manuel",
    "wof:placetype":"venue"
},
  "geometry": {"coordinates":[-6.3545899391,36.7807044983],"type":"Point"}
}