{
  "type": "Feature",
  "properties": {
    "iso:country":"ES",
    "sg:address":"Calle de Jose Payan Garrido, 20",
    "sg:city":"San Juan De Aznalfarache",
    "sg:orig_category":"Estancos",
    "sg:phone":"+34 954 76 18 31",
    "sg:postcode":"41920",
    "sg:province":"Sevilla",
    "wof:name":"Martin Leal Adela",
    "wof:placetype":"venue"
},
  "geometry": {"coordinates":[-6.0358772278,37.3592224121],"type":"Point"}
}