{
  "type": "Feature",
  "properties": {
    "addr:full":"Cmno Azkarate, S/n Erratzu Navarra 31714",
    "addr:housenumber":"s / n",
    "addr:postcode":"31714",
    "addr:street":"Cmno Azkarate",
    "iso:country":"ES",
    "sg:address":"Cmno Azkarate, S/n",
    "sg:city":"Erratzu",
    "sg:orig_category":"Cr\u00cda De Bovinos",
    "sg:phone":"+34 948 45 30 70",
    "sg:postcode":"31714",
    "sg:province":"Navarra",
    "wof:name":"Sociedad Bengoetxea S.c",
    "wof:placetype":"venue"
},
  "geometry": {"coordinates":[-1.4558990002,43.1828804016],"type":"Point"}
}