{
  "type": "Feature",
  "properties": {
    "iso:country":"ES",
    "sg:address":"Calle de Venezuela, 1",
    "sg:city":"Alcantarilla",
    "sg:orig_category":"Suministros Y Materiales Industriales",
    "sg:phone":"+34 968 89 15 16",
    "sg:postcode":"30820",
    "sg:province":"Murcia",
    "sg:website":"www.erreka.com",
    "wof:name":"Talleres Matz-erreka S.c.i.",
    "wof:placetype":"venue"
},
  "geometry": {"coordinates":[-1.199097991,37.9515190125],"type":"Point"}
}