{
  "type": "Feature",
  "properties": {
    "iso:country":"ES",
    "sg:address":"Calle de Melchor Cano, 54",
    "sg:city":"Fuente El Fresno",
    "sg:orig_category":"Farmacias",
    "sg:phone":"+34 926 80 60 67",
    "sg:postcode":"13680",
    "sg:province":"Ciudad Real",
    "wof:name":"Martin Ruiz Juana",
    "wof:placetype":"venue"
},
  "geometry": {"coordinates":[-3.7757806778,39.2280349731],"type":"Point"}
}