{
  "type": "Feature",
  "properties": {
    "iso:country":"ES",
    "sg:address":"Plaz Constitucion De (la), 2",
    "sg:city":"Calahorra",
    "sg:orig_category":"Ropa Y Accesorios",
    "sg:phone":"+34 941 13 27 15",
    "sg:postcode":"26500",
    "sg:province":"La Rioja",
    "wof:name":"Pinilla Arpon Gloria",
    "wof:placetype":"venue"
},
  "geometry": {"coordinates":[-1.9670690298,42.3058128357],"type":"Point"}
}