{
  "type": "Feature",
  "properties": {
    "iso:country":"ES",
    "sg:address":"Calle de Francia, 44",
    "sg:city":"Zuera",
    "sg:orig_category":"Construcciones Met\u00c1licas",
    "sg:phone":"+34 976 68 07 54",
    "sg:postcode":"50800",
    "sg:province":"Zaragoza",
    "sg:website":"ww.tesyc.es",
    "wof:name":"Talleres Tesyc S.l.",
    "wof:placetype":"venue"
},
  "geometry": {"coordinates":[-0.7876061797,41.8926696777],"type":"Point"}
}