{
  "type": "Feature",
  "properties": {
    "addr:full":"Crrd San Fernando, 44 Ubeda Ja\u00e9n 23400",
    "addr:housenumber":"44",
    "addr:postcode":"23400",
    "addr:street":"San Fernando;Jae\u0301N",
    "iso:country":"ES",
    "sg:address":"Crrd San Fernando, 44",
    "sg:city":"Ubeda",
    "sg:orig_category":"Institutos De Belleza (productos Y Aparatos)",
    "sg:phone":"+34 953 79 00 39",
    "sg:postcode":"23400",
    "sg:province":"Ja\u00e9n",
    "wof:name":"Real Martin Mari Cielo",
    "wof:placetype":"venue"
},
  "geometry": {"coordinates":[-3.3708279133,38.0113449097],"type":"Point"}
}