{
  "type": "Feature",
  "properties": {
    "addr:full":"Calle de San Roque, 2 Torralba De Los Sisones Teruel 44359",
    "addr:housenumber":"2",
    "addr:postcode":"44359",
    "addr:street":"Calle De San Roque",
    "iso:country":"ES",
    "sg:address":"Calle de San Roque, 2",
    "sg:city":"Torralba De Los Sisones",
    "sg:orig_category":"Asesor\u00cda, Estudio Y Control Medioambiental",
    "sg:phone":"+34 978 86 21 19",
    "sg:postcode":"44359",
    "sg:province":"Teruel",
    "wof:name":"Trastorre Medioambiental S.l.",
    "wof:placetype":"venue"
},
  "geometry": {"coordinates":[-1.4571213722,40.8914794922],"type":"Point"}
}