{
  "type": "Feature",
  "properties": {
    "addr:full":"Av Reis Catolics, 10 Olot Girona 17800",
    "addr:housenumber":"10",
    "addr:postcode":"17800",
    "addr:street":"Av Reis Catolics",
    "iso:country":"ES",
    "sg:address":"Av Reis Catolics, 10",
    "sg:city":"Olot",
    "sg:orig_category":"Florister\u00cdas",
    "sg:phone":"+34 972 27 26 56",
    "sg:postcode":"17800",
    "sg:province":"Girona",
    "wof:name":"Mancebo Fuentes Consuelo",
    "wof:placetype":"venue"
},
  "geometry": {"coordinates":[2.4829089642,42.1812400818],"type":"Point"}
}