{
  "type": "Feature",
  "properties": {
    "addr:full":"Calle de Albacete, 48 Requena Valencia 46340",
    "addr:housenumber":"48",
    "addr:postcode":"46340",
    "addr:street":"Calle De Albacete",
    "iso:country":"ES",
    "sg:address":"Calle de Albacete, 48",
    "sg:city":"Requena",
    "sg:orig_category":"Ense\u00d1anza: Comercio, Gesti\u00d3n, Inform\u00c1tica",
    "sg:phone":"+34 962 30 07 58",
    "sg:postcode":"46340",
    "sg:province":"Valencia",
    "wof:name":"Iranzo Garcia Rafael",
    "wof:placetype":"venue"
},
  "geometry": {"coordinates":[-1.1060580015,39.4858207703],"type":"Point"}
}