{
  "type": "Feature",
  "properties": {
    "addr:full":"Rua Travesia De Vigo, 92 Roris Pontevedra 36206",
    "addr:housenumber":"92",
    "addr:postcode":"36206",
    "addr:street":"Rua Travesia De Vigo",
    "iso:country":"ES",
    "sg:address":"Rua Travesia De Vigo, 92",
    "sg:city":"Roris",
    "sg:orig_category":"Farmacias",
    "sg:phone":"+34 986 27 92 52",
    "sg:postcode":"36206",
    "sg:province":"Pontevedra",
    "wof:name":"Palacian Urdillo Adoracion",
    "wof:placetype":"venue"
},
  "geometry": {"coordinates":[-8.7025899887,42.2368202209],"type":"Point"}
}