{
  "type": "Feature",
  "properties": {
    "iso:country":"ES",
    "sg:address":"Avda Martin Palomino, 48",
    "sg:city":"Plasencia",
    "sg:orig_category":"Molduras, Junquillos, Listones Y Molduras Perforadas",
    "sg:phone":"+34 927 41 47 46",
    "sg:postcode":"10600",
    "sg:province":"C\u00e1ceres",
    "wof:name":"Cafe Bar Restaurante Alba Plata C.b.",
    "wof:placetype":"venue"
},
  "geometry": {"coordinates":[-6.1041688919,40.0150947571],"type":"Point"}
}