{
  "type": "Feature",
  "properties": {
    "iso:country":"ES",
    "sg:address":"Calle de Tietar, 4",
    "sg:city":"Sotillo Adrada",
    "sg:orig_category":"Muebles Y Accesorios Para Cocinas Y Cuartos De Ba\u00d1o (al Por Menor)",
    "sg:phone":"+34 918 66 11 82",
    "sg:postcode":"05420",
    "sg:province":"\u00c1vila",
    "wof:name":"Gabriel Garcia Jose Luis",
    "wof:placetype":"venue"
},
  "geometry": {"coordinates":[-4.5819787979,40.2912368774],"type":"Point"}
}