{
  "type": "Feature",
  "properties": {
    "iso:country":"ES",
    "sg:address":"Calle de Jaime Casasus, 42",
    "sg:city":"Pina De Ebro",
    "sg:orig_category":"Carnicer\u00cdas, Carnicer\u00cdas",
    "sg:phone":"+34 976 16 50 31",
    "sg:postcode":"50750",
    "sg:province":"Zaragoza",
    "wof:name":"Fanlo Gonzalvo Juan Antonio",
    "wof:placetype":"venue"
},
  "geometry": {"coordinates":[-0.5311689973,41.4894981384],"type":"Point"}
}