{
  "type": "Feature",
  "properties": {
    "addr:full":"Calle de Innovacion, S/n Sevilla Sevilla 41020",
    "addr:housenumber":"s / n",
    "addr:postcode":"41020",
    "addr:street":"Calle De Innovacion",
    "iso:country":"ES",
    "sg:address":"Calle de Innovacion, S/n",
    "sg:city":"Sevilla",
    "sg:orig_category":"Edici\u00d3n De Mapas, Gu\u00cdas Y Planos",
    "sg:phone":"+34 954 25 83 52",
    "sg:postcode":"41020",
    "sg:province":"Sevilla",
    "sg:website":"www.navteq.com",
    "wof:name":"Navteq Technologies S.l.",
    "wof:placetype":"venue"
},
  "geometry": {"coordinates":[-5.9318771362,37.4069862366],"type":"Point"}
}