{
  "type": "Feature",
  "properties": {
    "addr:full":"Pase Sagasta, 16 Zaragoza Zaragoza 50006",
    "addr:housenumber":"16",
    "addr:postcode":"50006",
    "iso:country":"ES",
    "sg:address":"Pase Sagasta, 16",
    "sg:city":"Zaragoza",
    "sg:orig_category":"Procuradores",
    "sg:phone":"+34 976 23 11 75",
    "sg:postcode":"50006",
    "sg:province":"Zaragoza",
    "wof:name":"Serrano Mendez Maria Del Pilar",
    "wof:placetype":"venue"
},
  "geometry": {"coordinates":[-0.8860219717,41.6451530457],"type":"Point"}
}