{
  "type": "Feature",
  "properties": {
    "iso:country":"ES",
    "sg:address":"Calle de Navarra, 67",
    "sg:city":"Castellon",
    "sg:orig_category":"Restaurantes De Empresas Y Colectivos",
    "sg:phone":"+34 964 24 06 48",
    "sg:postcode":"12002",
    "sg:province":"Castell\u00f3n",
    "wof:name":"La Dinada S.l.",
    "wof:placetype":"venue"
},
  "geometry": {"coordinates":[-0.0410979986,39.9844055176],"type":"Point"}
}