{
  "type": "Feature",
  "properties": {
    "iso:country":"ES",
    "sg:address":"Florida, S/n",
    "sg:city":"Aguilas",
    "sg:orig_category":"Material Y Herramientas Agr\u00cdcolas",
    "sg:phone":"+34 968 44 84 61",
    "sg:postcode":"30880",
    "sg:province":"Murcia",
    "wof:name":"Pacheco Aguilas S.l.",
    "wof:placetype":"venue"
},
  "geometry": {"coordinates":[-1.5911439657,37.4093818665],"type":"Point"}
}