{
  "type": "Feature",
  "properties": {
    "iso:country":"ES",
    "sg:address":"Calle de Armenia, 3",
    "sg:city":"Ejido",
    "sg:orig_category":"Bares, Piano",
    "sg:phone":"+34 950 48 67 78",
    "sg:postcode":"04700",
    "sg:province":"Almer\u00eda",
    "wof:name":"Nunes Gonsalves Jose",
    "wof:placetype":"venue"
},
  "geometry": {"coordinates":[-2.7997674942,36.7727012634],"type":"Point"}
}