{
  "type": "Feature",
  "properties": {
    "addr:full":"Avgd Vicente Ferri, 1 Canals Valencia 46650",
    "addr:housenumber":"1",
    "addr:postcode":"46650",
    "addr:street":"Ferri",
    "iso:country":"ES",
    "sg:address":"Avgd Vicente Ferri, 1",
    "sg:city":"Canals",
    "sg:orig_category":"Electrodom\u00c9sticos (fabricaci\u00d3n, Al Por Mayor)",
    "sg:phone":"+34 962 24 02 70",
    "sg:postcode":"46650",
    "sg:province":"Valencia",
    "wof:name":"Garvi Hogar S.l.",
    "wof:placetype":"venue"
},
  "geometry": {"coordinates":[-0.5852789879,38.9629402161],"type":"Point"}
}