{
  "type": "Feature",
  "properties": {
    "addr:full":"Carr Major, 118 Jonquera Girona 17700",
    "addr:housenumber":"118",
    "addr:postcode":"17700",
    "addr:street":"Carr Major",
    "iso:country":"ES",
    "sg:address":"Carr Major, 118",
    "sg:city":"Jonquera",
    "sg:orig_category":"Centros Empresariales",
    "sg:phone":"+34 972 55 54 83",
    "sg:postcode":"17700",
    "sg:province":"Girona",
    "wof:name":"Martinez Guayaquil Alexandra Mirella",
    "wof:placetype":"venue"
},
  "geometry": {"coordinates":[2.8718750477,42.4159698486],"type":"Point"}
}