{
  "type": "Feature",
  "properties": {
    "addr:full":"Calle de Calixto Iii, 7 Valencia Valencia 46008",
    "addr:housenumber":"7",
    "addr:postcode":"46008",
    "addr:street":"Calle De Calixto Iii",
    "iso:country":"ES",
    "sg:address":"Calle de Calixto Iii, 7",
    "sg:city":"Valencia",
    "sg:orig_category":"Agencias Y Agentes Comerciales, Representantes",
    "sg:phone":"+34 963 84 62 78",
    "sg:postcode":"46008",
    "sg:province":"Valencia",
    "wof:name":"Llorens Ramon Miguel",
    "wof:placetype":"venue"
},
  "geometry": {"coordinates":[-0.3872798085,39.471988678],"type":"Point"}
}