{
  "type": "Feature",
  "properties": {
    "iso:country":"ES",
    "sg:address":"Pintor Murillo, 14",
    "sg:city":"Olivares",
    "sg:orig_category":"Supermercados Y Hipermercados",
    "sg:phone":"+34 955 71 90 31",
    "sg:postcode":"41804",
    "sg:province":"Sevilla",
    "wof:name":"Supermercados El Prado S.l.",
    "wof:placetype":"venue"
},
  "geometry": {"coordinates":[-6.1503419876,37.4187316895],"type":"Point"}
}