{
  "type": "Feature",
  "properties": {
    "addr:full":"Urb Coral Beach, S/n Marbella M\u00e1laga 29600",
    "addr:housenumber":"s / n",
    "addr:postcode":"29600",
    "addr:street":"Urb Coral Beach;Ma\u0301Laga",
    "iso:country":"ES",
    "sg:address":"Urb Coral Beach, S/n",
    "sg:city":"Marbella",
    "sg:orig_category":"Museos",
    "sg:phone":"+34 952 85 79 23",
    "sg:postcode":"29600",
    "sg:province":"M\u00e1laga",
    "wof:name":"Museo Ralli S.l.",
    "wof:placetype":"venue"
},
  "geometry": {"coordinates":[-4.9421358109,36.4979705811],"type":"Point"}
}