{
  "type": "Feature",
  "properties": {
    "iso:country":"ES",
    "sg:address":"Carrer de Jota, 63",
    "sg:city":"Barcelona",
    "sg:orig_category":"Mec\u00c1nico Del Autom\u00d3vil",
    "sg:phone":"+34 933 51 22 50",
    "sg:postcode":"08016",
    "sg:province":"Barcelona",
    "wof:name":"Repris J.g.s.cv.",
    "wof:placetype":"venue"
},
  "geometry": {"coordinates":[2.1795809269,41.4293403625],"type":"Point"}
}