{
  "type": "Feature",
  "properties": {
    "addr:full":"Ctra San Javier, S/n Secano Murcia 30579",
    "addr:postcode":"30579",
    "addr:street":"Ctra San Javier S / N",
    "iso:country":"ES",
    "sg:address":"Ctra San Javier, S/n",
    "sg:city":"Secano",
    "sg:orig_category":"Cristaler\u00cdas",
    "sg:phone":"+34 968 87 33 66",
    "sg:postcode":"30579",
    "sg:province":"Murcia",
    "wof:name":"Carmona Tomas Angel",
    "wof:placetype":"venue"
},
  "geometry": {"coordinates":[-1.0529290438,37.9830245972],"type":"Point"}
}