{
  "type": "Feature",
  "properties": {
    "addr:full":"Carrer de Tisso, 5 Barcelona Barcelona 08016",
    "addr:housenumber":"5",
    "addr:postcode":"08016",
    "addr:street":"Carrer De Tisso",
    "iso:country":"ES",
    "sg:address":"Carrer de Tisso, 5",
    "sg:city":"Barcelona",
    "sg:orig_category":"Inmobiliaria (agencias)",
    "sg:phone":"+34 932 76 05 96",
    "sg:postcode":"08016",
    "sg:province":"Barcelona",
    "wof:name":"Castellgrup Inmobiliaris S.c.t.",
    "wof:placetype":"venue"
},
  "geometry": {"coordinates":[2.1847920418,41.4426727295],"type":"Point"}
}