{
  "type": "Feature",
  "properties": {
    "addr:full":"Avda Presidente Carmona, 8 Madrid Madrid 28020",
    "addr:housenumber":"8",
    "addr:postcode":"madrid;28020",
    "addr:street":"Avda Presidente Carmona",
    "iso:country":"ES",
    "sg:address":"Avda Presidente Carmona, 8",
    "sg:city":"Madrid",
    "sg:orig_category":"Inform\u00c1tica: Material Y Suministros",
    "sg:phone":"+34 915 97 15 43",
    "sg:postcode":"28020",
    "sg:province":"Madrid",
    "wof:name":"Ingenieria De Software Aplicada S.l.",
    "wof:placetype":"venue"
},
  "geometry": {"coordinates":[-3.6968889236,40.4539413452],"type":"Point"}
}