{
  "type": "Feature",
  "properties": {
    "iso:country":"ES",
    "sg:address":"Avda San Ignacio, 18",
    "sg:city":"Le\u00f3n",
    "sg:orig_category":"Pescader\u00cdas (al Por Menor)",
    "sg:phone":"+34 987 22 29 44",
    "sg:postcode":"24010",
    "sg:province":"Le\u00f3n",
    "wof:name":"Fernandez Alvarez Miguel",
    "wof:placetype":"venue"
},
  "geometry": {"coordinates":[-5.5896339417,42.6042251587],"type":"Point"}
}