{
  "type": "Feature",
  "properties": {
    "addr:full":"Calle de Jeronimo Zurita, 15 Pina De Ebro Zaragoza 50750",
    "addr:housenumber":"15",
    "addr:postcode":"50750",
    "addr:street":"Calle De Jeronimo Zurita",
    "iso:country":"ES",
    "sg:address":"Calle de Jeronimo Zurita, 15",
    "sg:city":"Pina De Ebro",
    "sg:orig_category":"Cr\u00cda De Animales",
    "sg:phone":"+34 976 16 54 47",
    "sg:postcode":"50750",
    "sg:province":"Zaragoza",
    "wof:name":"Fanlo Lechon Javier",
    "wof:placetype":"venue"
},
  "geometry": {"coordinates":[-0.5273090005,41.4905014038],"type":"Point"}
}