{
  "type": "Feature",
  "properties": {
    "iso:country":"ES",
    "sg:address":"Calle de Alcalde Sainz De Baranda, 28",
    "sg:city":"Madrid",
    "sg:orig_category":"Librer\u00cdas",
    "sg:phone":"+34 914 00 84 35",
    "sg:postcode":"28009",
    "sg:province":"Madrid",
    "wof:name":"Lopez Escobar Marta Cristina",
    "wof:placetype":"venue"
},
  "geometry": {"coordinates":[-3.6749122143,40.4167709351],"type":"Point"}
}