{
  "type": "Feature",
  "properties": {
    "iso:country":"ES",
    "sg:address":"Calle de Nueva De San Anton, 20",
    "sg:city":"Granada",
    "sg:orig_category":"Bisuter\u00cda, Joyer\u00cda, Relojer\u00cda (al Por Menor)",
    "sg:phone":"+34 958 26 32 57",
    "sg:postcode":"18005",
    "sg:province":"Granada",
    "wof:name":"Torres Vilchez Manuel",
    "wof:placetype":"venue"
},
  "geometry": {"coordinates":[-3.6014690399,37.1710357666],"type":"Point"}
}