{
  "type": "Feature",
  "properties": {
    "iso:country":"ES",
    "sg:address":"Calle de Juan De Austria, 6",
    "sg:city":"Parla",
    "sg:orig_category":"Empresarios",
    "sg:phone":"+34 916 05 11 62",
    "sg:postcode":"28980",
    "sg:province":"Madrid",
    "wof:name":"Danser Instalaciones S.l.",
    "wof:placetype":"venue"
},
  "geometry": {"coordinates":[-3.7697269917,40.2358093262],"type":"Point"}
}