{
  "type": "Feature",
  "properties": {
    "iso:country":"ES",
    "sg:address":"Pl Esglesia, 25",
    "sg:city":"Creixell",
    "sg:orig_category":"Iglesia Cat\u00d3lica",
    "sg:phone":"+34 977 80 02 08",
    "sg:postcode":"43839",
    "sg:province":"Tarragona",
    "wof:name":"Arquebisbat De Tarragona",
    "wof:placetype":"venue"
},
  "geometry": {"coordinates":[1.4415794611,41.1677856445],"type":"Point"}
}