{
  "type": "Feature",
  "properties": {
    "iso:country":"ES",
    "sg:address":"Calle de Andres Alvarez Caballero (de), 5",
    "sg:city":"Humanes De Madrid",
    "sg:orig_category":"Empresas De Carpinter\u00cda De Madera",
    "sg:phone":"+34 916 06 98 28",
    "sg:postcode":"28970",
    "sg:province":"Madrid",
    "wof:name":"Carpinteria Linares Decoracion E Interiorismo S.l.",
    "wof:placetype":"venue"
},
  "geometry": {"coordinates":[-3.814483881,40.2752838135],"type":"Point"}
}