{
  "type": "Feature",
  "properties": {
    "iso:country":"ES",
    "sg:address":"Calle de Alejandro Rodriguez De Valcarcel, 7",
    "sg:city":"Villarcayo",
    "sg:orig_category":"Organismos De Turismo",
    "sg:phone":"+34 947 13 13 37",
    "sg:postcode":"09550",
    "sg:province":"Burgos",
    "sg:website":"www.arcay.org",
    "wof:name":"Arcay Proyectos Turisticos S.c.",
    "wof:placetype":"venue"
},
  "geometry": {"coordinates":[-3.5753192902,42.937702179],"type":"Point"}
}