{
  "type": "Feature",
  "properties": {
    "addr:full":"Calle de Valle De Laguar, 14 Valencia Valencia 46009",
    "addr:housenumber":"14",
    "addr:postcode":"46009",
    "addr:street":"Calle De Valle De Laguar",
    "iso:country":"ES",
    "sg:address":"Calle de Valle De Laguar, 14",
    "sg:city":"Valencia",
    "sg:orig_category":"Plomeros",
    "sg:phone":"+34 963 47 81 85",
    "sg:postcode":"46009",
    "sg:province":"Valencia",
    "wof:name":"Garcia Marti Vicente",
    "wof:placetype":"venue"
},
  "geometry": {"coordinates":[-0.3840009868,39.4826431274],"type":"Point"}
}