{
  "type": "Feature",
  "properties": {
    "addr:full":"Calle de Reinante, 18 Ribadeo Lugo 27700",
    "addr:housenumber":"18",
    "addr:postcode":"27700",
    "addr:street":"Calle De Reinante",
    "iso:country":"ES",
    "sg:address":"Calle de Reinante, 18",
    "sg:city":"Ribadeo",
    "sg:orig_category":"Mercer\u00cda, Lencer\u00cda (al Por Menor)",
    "sg:phone":"+34 982 12 81 42",
    "sg:postcode":"27700",
    "sg:province":"Lugo",
    "wof:name":"Innovaciones Artesanas Del Eo S.l.l",
    "wof:placetype":"venue"
},
  "geometry": {"coordinates":[-7.0414390564,43.5364685059],"type":"Point"}
}