{
  "type": "Feature",
  "properties": {
    "addr:full":"Carrer de Marina, 135 Barcelona Barcelona 08013",
    "addr:housenumber":"135",
    "addr:postcode":"08013",
    "addr:street":"Carrer De Marina",
    "iso:country":"ES",
    "sg:address":"Carrer de Marina, 135",
    "sg:city":"Barcelona",
    "sg:orig_category":"Negocio De Materiales De Construcci\u00d3n",
    "sg:phone":"+34 932 46 67 58",
    "sg:postcode":"08013",
    "sg:province":"Barcelona",
    "wof:name":"Suministros Tecnicos Anoia S.l.",
    "wof:placetype":"venue"
},
  "geometry": {"coordinates":[2.1835548878,41.3971595764],"type":"Point"}
}