{
  "type": "Feature",
  "properties": {
    "iso:country":"ES",
    "sg:address":"Ctra. Juia, S/n",
    "sg:city":"Juia",
    "sg:orig_category":"Carnes De Carnicer\u00cda (al Por Mayor)",
    "sg:phone":"+34 972 49 05 11",
    "sg:postcode":"17462",
    "sg:province":"Girona",
    "wof:name":"Girosona S.l.",
    "wof:placetype":"venue"
},
  "geometry": {"coordinates":[2.9117949009,42.0443763733],"type":"Point"}
}