{
  "type": "Feature",
  "properties": {
    "iso:country":"ES",
    "sg:address":"Calle de Gamonal, 29",
    "sg:city":"Madrid",
    "sg:orig_category":"Electricidad: Instaladores",
    "sg:phone":"+34 913 31 30 80",
    "sg:postcode":"28031",
    "sg:province":"Madrid",
    "wof:name":"Elecnor S.a.",
    "wof:placetype":"venue"
},
  "geometry": {"coordinates":[-3.6432430744,40.373260498],"type":"Point"}
}