{
  "type": "Feature",
  "properties": {
    "addr:full":"Rtda Riu Cardener, S/n Girona Girona 17003",
    "addr:housenumber":"s / n",
    "addr:postcode":"17003",
    "addr:street":"Cardener",
    "iso:country":"ES",
    "sg:address":"Rtda Riu Cardener, S/n",
    "sg:city":"Girona",
    "sg:orig_category":"Asociaciones, Organismos Culturales Y Socioeducativos",
    "sg:phone":"+34 972 21 44 04",
    "sg:postcode":"17003",
    "sg:province":"Girona",
    "wof:name":"Fundacio Astres",
    "wof:placetype":"venue"
},
  "geometry": {"coordinates":[2.8187100887,41.9630203247],"type":"Point"}
}