{
  "type": "Feature",
  "properties": {
    "iso:country":"ES",
    "sg:address":"Calle de Canonigo, 106",
    "sg:city":"Dos Hermanas",
    "sg:orig_category":"Agencias Y Agentes Comerciales, Representantes",
    "sg:phone":"+34 954 72 25 81",
    "sg:postcode":"41700",
    "sg:province":"Sevilla",
    "wof:name":"Mora Carazo Antonio",
    "wof:placetype":"venue"
},
  "geometry": {"coordinates":[-5.9221029282,37.2822113037],"type":"Point"}
}