{
  "type": "Feature",
  "properties": {
    "addr:full":"Calle de Astillero, 5 Bilbao Vizcaya 48013",
    "addr:housenumber":"5",
    "addr:postcode":"48013",
    "addr:street":"Calle De Astillero",
    "iso:country":"ES",
    "sg:address":"Calle de Astillero, 5",
    "sg:city":"Bilbao",
    "sg:orig_category":"Peluquer\u00cdas, Peluquer\u00cda Mixta",
    "sg:phone":"+34 944 27 02 07",
    "sg:postcode":"48013",
    "sg:province":"Vizcaya",
    "wof:name":"Hillera Malmonje Monica",
    "wof:placetype":"venue"
},
  "geometry": {"coordinates":[-2.9814510345,43.303604126],"type":"Point"}
}