{
  "type": "Feature",
  "properties": {
    "addr:full":"Carrer de Miguel De Cervantes, 9 Mollet Valles Barcelona 08100",
    "addr:housenumber":"9",
    "addr:postcode":"08100",
    "addr:street":"Carrer De Miguel De Cervantes",
    "iso:country":"ES",
    "sg:address":"Carrer de Miguel De Cervantes, 9",
    "sg:city":"Mollet Valles",
    "sg:classifiers":[
        {
            "category":"Professional",
            "subcategory":"Management & Consulting",
            "type":"Services"
        }
    ],
    "sg:phone":"+34 935 70 63 06",
    "sg:postcode":"08100",
    "sg:province":"Barcelona",
    "sg:tags":[
        "asesor\u00cda",
        "en",
        "marketing"
    ],
    "wof:name":"Rios Vega Gabriela Ines",
    "wof:placetype":"venue"
},
  "geometry": {"coordinates":[2.2103190422,41.5436782837],"type":"Point"}
}