{
  "type": "Feature",
  "properties": {
    "addr:full":"Calle de Beraqueta, 13 Irun Guip\u00f9zcoa 20302",
    "addr:housenumber":"13",
    "addr:postcode":"20302",
    "addr:street":"Calle De Beraqueta;Guipu\u0300Zcoa",
    "iso:country":"ES",
    "sg:address":"Calle de Beraqueta, 13",
    "sg:city":"Irun",
    "sg:orig_category":"Arquitectos",
    "sg:phone":"+34 943 63 55 55",
    "sg:postcode":"20302",
    "sg:province":"Guip\u00f9zcoa",
    "wof:name":"Guezuraga Manterola Javier",
    "wof:placetype":"venue"
},
  "geometry": {"coordinates":[-1.7897750139,43.3400535583],"type":"Point"}
}