{
  "type": "Feature",
  "properties": {
    "iso:country":"ES",
    "sg:address":"Carr Juli Garreta, 7",
    "sg:city":"Girona",
    "sg:orig_category":"Ropa Para Ni\u00d1os (al Por Menor)",
    "sg:phone":"+34 872 08 17 46",
    "sg:postcode":"17002",
    "sg:province":"Girona",
    "wof:name":"Kiddys's Class S.a.",
    "wof:placetype":"venue"
},
  "geometry": {"coordinates":[2.8196771145,41.9796295166],"type":"Point"}
}