{
  "type": "Feature",
  "properties": {
    "iso:country":"ES",
    "sg:address":"Carrer de Mila I Fontanals, 78",
    "sg:city":"Sabadell",
    "sg:orig_category":"Fabricaci\u00d3n De Telas Y Sedas",
    "sg:phone":"+34 937 20 63 00",
    "sg:postcode":"08205",
    "sg:province":"Barcelona",
    "sg:website":"www.pazrorras.com",
    "wof:name":"Confecciones Paz Torras S.a.",
    "wof:placetype":"venue"
},
  "geometry": {"coordinates":[2.1024119854,41.5358200073],"type":"Point"}
}