{
  "type": "Feature",
  "properties": {
    "addr:full":"Calle de San Antonio, 14 Monzon Huesca 22400",
    "addr:housenumber":"14",
    "addr:postcode":"22400",
    "addr:street":"Calle De San Antonio",
    "iso:country":"ES",
    "sg:address":"Calle de San Antonio, 14",
    "sg:city":"Monzon",
    "sg:orig_category":"Carnicer\u00cdas, Carnicer\u00cdas",
    "sg:phone":"+34 974 40 02 39",
    "sg:postcode":"22400",
    "sg:province":"Huesca",
    "wof:name":"Beltran Bestue Eusebio",
    "wof:placetype":"venue"
},
  "geometry": {"coordinates":[0.1935939938,41.9107322693],"type":"Point"}
}