{
  "type": "Feature",
  "properties": {
    "addr:full":"Calle de Marcelo Usera, 86 Madrid Madrid 28026",
    "addr:housenumber":"86",
    "addr:postcode":"madrid;28026",
    "addr:street":"Calle De Marcelo Usera",
    "iso:country":"ES",
    "sg:address":"Calle de Marcelo Usera, 86",
    "sg:city":"Madrid",
    "sg:orig_category":"Institutos De Belleza",
    "sg:phone":"+34 915 00 15 08",
    "sg:postcode":"28026",
    "sg:province":"Madrid",
    "wof:name":"Laura Y Tamara S.l.",
    "wof:placetype":"venue"
},
  "geometry": {"coordinates":[-3.7067708969,40.3858528137],"type":"Point"}
}