{
  "type": "Feature",
  "properties": {
    "addr:full":"Calle de Encomienda, 19 Alange Badajoz 06840",
    "addr:housenumber":"19",
    "addr:postcode":"06840",
    "addr:street":"Calle De Encomienda",
    "iso:country":"ES",
    "sg:address":"Calle de Encomienda, 19",
    "sg:city":"Alange",
    "sg:orig_category":"Cajas De Ahorro",
    "sg:phone":"+34 924 36 50 36",
    "sg:postcode":"06840",
    "sg:province":"Badajoz",
    "wof:name":"Caja De Ahorros Y Monte De Piedad De Extremadura",
    "wof:placetype":"venue"
},
  "geometry": {"coordinates":[-6.2491159439,38.7854385376],"type":"Point"}
}