{
  "type": "Feature",
  "properties": {
    "iso:country":"ES",
    "sg:address":"Calle de Rio Genil, 4",
    "sg:city":"Santa Fe",
    "sg:orig_category":"Cerrajer\u00cda, Ferrallista",
    "sg:phone":"+34 958 44 04 86",
    "sg:postcode":"18320",
    "sg:province":"Granada",
    "wof:name":"Talleres Rodriguez S.c.",
    "wof:placetype":"venue"
},
  "geometry": {"coordinates":[-3.7220025063,37.1851768494],"type":"Point"}
}