{
  "type": "Feature",
  "properties": {
    "iso:country":"ES",
    "sg:address":"Calle de Santo Tomas, 4",
    "sg:city":"Aspe",
    "sg:orig_category":"Dietistas",
    "sg:phone":"+34 965 49 42 66",
    "sg:postcode":"03680",
    "sg:province":"Alicante",
    "wof:name":"San Roque Botella Antonia Rosa",
    "wof:placetype":"venue"
},
  "geometry": {"coordinates":[-0.7678400278,38.3460769653],"type":"Point"}
}