{
  "type": "Feature",
  "properties": {
    "iso:country":"ES",
    "sg:address":"Calle de Santiago, 24",
    "sg:city":"Alburquerque",
    "sg:orig_category":"Alimentaci\u00d3n General (al Por Menor)",
    "sg:phone":"+34 924 40 13 00",
    "sg:postcode":"06510",
    "sg:province":"Badajoz",
    "wof:name":"Marquez Cabrera Jose Manuel",
    "wof:placetype":"venue"
},
  "geometry": {"coordinates":[-6.9959588051,39.2207984924],"type":"Point"}
}