{
  "type": "Feature",
  "properties": {
    "addr:full":"Calle de San Carlos Rapita, 22 Calaceite Teruel 44610",
    "addr:housenumber":"22",
    "addr:postcode":"44610",
    "addr:street":"Calle De San;Rapita",
    "iso:country":"ES",
    "sg:address":"Calle de San Carlos Rapita, 22",
    "sg:city":"Calaceite",
    "sg:orig_category":"Transportes Por V\u00cdas Navegables",
    "sg:phone":"+34 978 85 11 29",
    "sg:postcode":"44610",
    "sg:province":"Teruel",
    "wof:name":"Peris Vicente Pablo",
    "wof:placetype":"venue"
},
  "geometry": {"coordinates":[0.1909599006,41.0162391663],"type":"Point"}
}