{
  "type": "Feature",
  "properties": {
    "addr:full":"Cmno. Trancal, S/n Morales Vino Zamora 49190",
    "addr:postcode":"49190",
    "addr:street":"Trancal S / N Morales Vino Zamora",
    "iso:country":"ES",
    "sg:address":"Cmno. Trancal, S/n",
    "sg:city":"Morales Vino",
    "sg:orig_category":"Carnes De Carnicer\u00cda (al Por Mayor)",
    "sg:phone":"+34 980 57 03 20",
    "sg:postcode":"49190",
    "sg:province":"Zamora",
    "sg:website":"www.magnus.es",
    "wof:name":"Grupo Carnico Magnus S.a.",
    "wof:placetype":"venue"
},
  "geometry": {"coordinates":[-5.7349591255,41.445602417],"type":"Point"}
}