{
  "type": "Feature",
  "properties": {
    "iso:country":"ES",
    "sg:address":"Calle de Inmaculada Concepcion, 10",
    "sg:city":"Ciudad Real",
    "sg:orig_category":"Inform\u00c1tica (estudios, Servicios, Asesor\u00cda, Formaci\u00d3n)",
    "sg:phone":"+34 926 23 29 97",
    "sg:postcode":"13003",
    "sg:province":"Ciudad Real",
    "wof:name":"A.d.m.informatica S.c.c.m.",
    "wof:placetype":"venue"
},
  "geometry": {"coordinates":[-3.9220883846,38.9897079468],"type":"Point"}
}