{
  "type": "Feature",
  "properties": {
    "addr:full":"Calle de Santa Cruz, S/n Almanzora Almer\u00eda 04815",
    "addr:housenumber":"s / n",
    "addr:postcode":"04815",
    "addr:street":"Calle De Santa Cruz;Almanzora Almeri\u0301A",
    "iso:country":"ES",
    "sg:address":"Calle de Santa Cruz, S/n",
    "sg:city":"Almanzora",
    "sg:orig_category":"Arboricultura Y Producci\u00d3n De Frutas",
    "sg:phone":"+34 950 43 14 05",
    "sg:postcode":"04815",
    "sg:province":"Almer\u00eda",
    "wof:name":"Merca Bio Sociedad Coop.andaluza",
    "wof:placetype":"venue"
},
  "geometry": {"coordinates":[-2.136259079,37.3484458923],"type":"Point"}
}