{
  "type": "Feature",
  "properties": {
    "addr:full":"San Ignazio Kalea, 1 Elgoibar Guip\u00f9zcoa 20870",
    "addr:housenumber":"1",
    "addr:postcode":"20870",
    "addr:street":"San Ignazio Kalea;Guipu\u0300Zcoa",
    "iso:country":"ES",
    "sg:address":"San Ignazio Kalea, 1",
    "sg:city":"Elgoibar",
    "sg:orig_category":"Sindicatos De Trabajadores",
    "sg:phone":"+34 943 74 10 28",
    "sg:postcode":"20870",
    "sg:province":"Guip\u00f9zcoa",
    "wof:name":"Comisiones Obreras De Euskadi",
    "wof:placetype":"venue"
},
  "geometry": {"coordinates":[-2.4172070026,43.2139778137],"type":"Point"}
}