{
  "type": "Feature",
  "properties": {
    "iso:country":"ES",
    "sg:address":"Loredo, S/n",
    "sg:city":"Loredo",
    "sg:orig_category":"Supermercados Y Hipermercados",
    "sg:phone":"+34 942 50 91 30",
    "sg:postcode":"39140",
    "sg:province":"Cantabria",
    "wof:name":"Lastra Revuelta Jose Antonio",
    "wof:placetype":"venue"
},
  "geometry": {"coordinates":[-3.7208049297,43.4618911743],"type":"Point"}
}