{
  "type": "Feature",
  "properties": {
    "iso:country":"ES",
    "sg:address":"Calle de Sierra De Aracena, 17",
    "sg:city":"Lora Rio",
    "sg:orig_category":"Asesor\u00cda Sobre Comunicaci\u00d3n De Empresas",
    "sg:phone":"+34 955 80 23 53",
    "sg:postcode":"41440",
    "sg:province":"Sevilla",
    "wof:name":"Garcia Nu\u00f1ez Rosario",
    "wof:placetype":"venue"
},
  "geometry": {"coordinates":[-5.5226302147,37.6577224731],"type":"Point"}
}