{
  "type": "Feature",
  "properties": {
    "iso:country":"ES",
    "sg:address":"Via Mallorca, 4",
    "sg:city":"Cala Ratjada",
    "sg:orig_category":"Asesor\u00cda Fiscal Y Jur\u00cddica",
    "sg:phone":"+34 971 81 83 87",
    "sg:postcode":"07590",
    "sg:province":"Islas Baleares",
    "wof:name":"Ferrer Garau Jeronimo",
    "wof:placetype":"venue"
},
  "geometry": {"coordinates":[3.4608900547,39.7104988098],"type":"Point"}
}