{
  "type": "Feature",
  "properties": {
    "addr:full":"Trasona, S/n Aviles Asturias 33468",
    "addr:housenumber":"/ n",
    "addr:postcode":"33468",
    "addr:street":"Trasona S",
    "iso:country":"ES",
    "sg:address":"Trasona, S/n",
    "sg:city":"Aviles",
    "sg:orig_category":"Promotores Constructores",
    "sg:phone":"+34 985 54 99 43",
    "sg:postcode":"33468",
    "sg:province":"Asturias",
    "wof:name":"Dragados S A",
    "wof:placetype":"venue"
},
  "geometry": {"coordinates":[-5.8703289032,43.563129425],"type":"Point"}
}