{
  "type": "Feature",
  "properties": {
    "iso:country":"ES",
    "sg:address":"Carrer de Canigo, 2",
    "sg:city":"Barbera Valles",
    "sg:orig_category":"M\u00c9dicos: Cirug\u00cda Pl\u00c1stica, Reconstructiva Y Est\u00c9tica",
    "sg:phone":"+34 937 19 08 04",
    "sg:postcode":"08210",
    "sg:province":"Barcelona",
    "wof:name":"Guillen Sanchez Mercedes",
    "wof:placetype":"venue"
},
  "geometry": {"coordinates":[2.1269729137,41.5155067444],"type":"Point"}
}