{
  "type": "Feature",
  "properties": {
    "iso:country":"ES",
    "sg:address":"Calle de Terrero, 31",
    "sg:city":"Daimiel",
    "sg:orig_category":"Mudanzas",
    "sg:phone":"+34 926 85 29 39",
    "sg:postcode":"13250",
    "sg:province":"Ciudad Real",
    "wof:name":"Oviedo Sesma Miguel",
    "wof:placetype":"venue"
},
  "geometry": {"coordinates":[-3.614839077,39.0740432739],"type":"Point"}
}