{
  "type": "Feature",
  "properties": {
    "addr:full":"Avda Pintor Baeza, 11 Alacant Alicante 03010",
    "addr:housenumber":"11",
    "addr:postcode":"03010",
    "addr:street":"Avda Pintor Baeza",
    "iso:country":"ES",
    "sg:address":"Avda Pintor Baeza, 11",
    "sg:city":"Alacant",
    "sg:orig_category":"Servicios De Telecomunicaciones",
    "sg:phone":"+34 965 24 87 61",
    "sg:postcode":"03010",
    "sg:province":"Alicante",
    "wof:name":"Respuesta Directa En Telecomunicaciones S.l.",
    "wof:placetype":"venue"
},
  "geometry": {"coordinates":[-0.4874860048,38.3625221252],"type":"Point"}
}