{
  "type": "Feature",
  "properties": {
    "addr:full":"Calle de San Jaime, 28 Onil Alicante 03430",
    "addr:housenumber":"28",
    "addr:postcode":"03430",
    "addr:street":"Calle De San Jaime",
    "iso:country":"ES",
    "sg:address":"Calle de San Jaime, 28",
    "sg:city":"Onil",
    "sg:orig_category":"Sindicatos De Trabajadores",
    "sg:phone":"+34 965 56 51 06",
    "sg:postcode":"03430",
    "sg:province":"Alicante",
    "wof:name":"Union General De Trabajadores",
    "wof:placetype":"venue"
},
  "geometry": {"coordinates":[-0.6720603108,38.6309013367],"type":"Point"}
}