{
  "type": "Feature",
  "properties": {
    "iso:country":"ES",
    "sg:address":"Calle de Arzobispo Blanco, 5",
    "sg:city":"Pola De Lena",
    "sg:orig_category":"Abogados",
    "sg:phone":"+34 985 49 31 11",
    "sg:postcode":"33630",
    "sg:province":"Asturias",
    "wof:name":"Prieto Arg\u00fcelles Cristina Sonia",
    "wof:placetype":"venue"
},
  "geometry": {"coordinates":[-5.8292150497,43.1567802429],"type":"Point"}
}