{
  "type": "Feature",
  "properties": {
    "addr:full":"Avda General Mola, 10 Pozuelo De Alarcon Madrid 28224",
    "addr:housenumber":"10",
    "addr:postcode":"28224",
    "addr:street":"Avda General Mola",
    "iso:country":"ES",
    "sg:address":"Avda General Mola, 10",
    "sg:city":"Pozuelo De Alarcon",
    "sg:orig_category":"Inform\u00c1tica (estudios, Servicios, Asesor\u00cda, Formaci\u00d3n)",
    "sg:phone":"+34 913 51 38 98",
    "sg:postcode":"28224",
    "sg:province":"Madrid",
    "sg:website":"www.qualitysa.com",
    "wof:name":"Quality Information Systems S.a.",
    "wof:placetype":"venue"
},
  "geometry": {"coordinates":[-3.797066927,40.4507293701],"type":"Point"}
}