{
  "type": "Feature",
  "properties": {
    "iso:country":"ES",
    "sg:address":"Avda Montendre, 10",
    "sg:city":"Onda",
    "sg:orig_category":"Zapatos (al Por Menor)",
    "sg:phone":"+34 964 60 35 92",
    "sg:postcode":"12200",
    "sg:province":"Castell\u00f3n",
    "wof:name":"Talamantes Marin Jose Ernesto",
    "wof:placetype":"venue"
},
  "geometry": {"coordinates":[-0.262609005,39.9651603699],"type":"Point"}
}