{
  "type": "Feature",
  "properties": {
    "iso:country":"ES",
    "sg:address":"Calle de Cerro De La Alcazaba, 8",
    "sg:city":"Madrid",
    "sg:orig_category":"Electricidad: Instaladores",
    "sg:phone":"+34 914 77 84 43",
    "sg:postcode":"28053",
    "sg:province":"Madrid",
    "wof:name":"Montajes Arquero S.l",
    "wof:placetype":"venue"
},
  "geometry": {"coordinates":[-3.6713452339,40.3848686218],"type":"Point"}
}