{
  "type": "Feature",
  "properties": {
    "iso:country":"ES",
    "sg:address":"Carr Santa Catalina Tomas, 21",
    "sg:city":"Santa Maria Del Cami",
    "sg:orig_category":"Supermercados Y Hipermercados",
    "sg:phone":"+34 971 62 07 55",
    "sg:postcode":"07320",
    "sg:province":"Islas Baleares",
    "wof:name":"Insular General Alimentaria S. A.",
    "wof:placetype":"venue"
},
  "geometry": {"coordinates":[2.7718789577,39.6521682739],"type":"Point"}
}