{
  "type": "Feature",
  "properties": {
    "addr:full":"Plaz Constitucio, S/n Cullera Valencia 46400",
    "addr:housenumber":"s / n",
    "addr:postcode":"46400",
    "addr:street":"Plaz Constitucio",
    "iso:country":"ES",
    "sg:address":"Plaz Constitucio, S/n",
    "sg:city":"Cullera",
    "sg:orig_category":"Ense\u00d1anza, Formaci\u00d3n Profesional: Aprendizaje",
    "sg:phone":"+34 961 73 15 86",
    "sg:postcode":"46400",
    "sg:province":"Valencia",
    "wof:name":"Ayuntamiento De Cullera",
    "wof:placetype":"venue"
},
  "geometry": {"coordinates":[-0.241711393,39.1651802063],"type":"Point"}
}