{
  "type": "Feature",
  "properties": {
    "iso:country":"ES",
    "sg:address":"Calle de Concepcion Arenal, 16",
    "sg:city":"Chauchina",
    "sg:orig_category":"Plomeros",
    "sg:phone":"+34 958 44 68 34",
    "sg:postcode":"18330",
    "sg:province":"Granada",
    "wof:name":"Garcia Roldan Eduardo",
    "wof:placetype":"venue"
},
  "geometry": {"coordinates":[-3.7722680569,37.1958503723],"type":"Point"}
}