{
  "type": "Feature",
  "properties": {
    "iso:country":"ES",
    "sg:address":"Calle de Factoria Matagorda, 50",
    "sg:city":"Pto Real",
    "sg:orig_category":"Supermercados Y Hipermercados",
    "sg:phone":"+34 956 83 50 62",
    "sg:postcode":"11510",
    "sg:province":"C\u00e1diz",
    "wof:name":"Dinosol Supermercados S.l.",
    "wof:placetype":"venue"
},
  "geometry": {"coordinates":[-6.1960492134,36.5291900635],"type":"Point"}
}