{
  "type": "Feature",
  "properties": {
    "iso:country":"ES",
    "sg:address":"Calle de Cristobal Colon, 17",
    "sg:city":"Carpio",
    "sg:orig_category":"Contenedores (mercanc\u00cdas)",
    "sg:phone":"+34 957 18 05 17",
    "sg:postcode":"14620",
    "sg:province":"C\u00f3rdoba",
    "wof:name":"Fernandez Gavilan Antonio",
    "wof:placetype":"venue"
},
  "geometry": {"coordinates":[-4.4991765022,37.9420623779],"type":"Point"}
}