{
  "type": "Feature",
  "properties": {
    "addr:full":"Carrer de Comte Borrell, 89 Barcelona Barcelona 08015",
    "addr:housenumber":"89",
    "addr:postcode":"08015",
    "addr:street":"Carrer De Comte Borrell",
    "iso:country":"ES",
    "sg:address":"Carrer de Comte Borrell, 89",
    "sg:city":"Barcelona",
    "sg:orig_category":"Administradores De Bienes Y Delegados De Comunidades De Propietarios",
    "sg:phone":"+34 934 25 46 14",
    "sg:postcode":"08015",
    "sg:province":"Barcelona",
    "wof:name":"Ghuad S.l.",
    "wof:placetype":"venue"
},
  "geometry": {"coordinates":[2.1603479385,41.3789710999],"type":"Point"}
}