{
  "type": "Feature",
  "properties": {
    "addr:full":"Carrer de Sebel.li, 3 Peguera Islas Baleares 07160",
    "addr:housenumber":"3",
    "addr:postcode":"07160",
    "addr:street":"Carrer De Sebel.Li",
    "iso:country":"ES",
    "sg:address":"Carrer de Sebel.li, 3",
    "sg:city":"Peguera",
    "sg:orig_category":"Alimentaci\u00d3n General (al Por Menor)",
    "sg:phone":"+34 971 68 54 22",
    "sg:postcode":"07160",
    "sg:province":"Islas Baleares",
    "wof:name":"Garcia Criado Maria Del Carmen",
    "wof:placetype":"venue"
},
  "geometry": {"coordinates":[2.4557859898,39.5362586975],"type":"Point"}
}