{
  "type": "Feature",
  "properties": {
    "iso:country":"ES",
    "sg:address":"Plaz Poniente, S/n",
    "sg:city":"Armilla",
    "sg:orig_category":"Ropa Para Ni\u00d1os (al Por Menor)",
    "sg:phone":"+34 958 57 22 57",
    "sg:postcode":"18100",
    "sg:province":"Granada",
    "wof:name":"Essadi  Beboubker",
    "wof:placetype":"venue"
},
  "geometry": {"coordinates":[-3.6292641163,37.1432952881],"type":"Point"}
}