{
  "type": "Feature",
  "properties": {
    "addr:full":"Calle de Joaquin Costa, 41 Gra\u00f1en Huesca 22260",
    "addr:housenumber":"41",
    "addr:postcode":"22260",
    "addr:street":"Calle De Joaquin Costa",
    "iso:country":"ES",
    "sg:address":"Calle de Joaquin Costa, 41",
    "sg:city":"Gra\u00f1en",
    "sg:orig_category":"Maquinaria Para Industrias Diversas",
    "sg:phone":"+34 974 39 01 03",
    "sg:postcode":"22260",
    "sg:province":"Huesca",
    "wof:name":"Pamplona Perez Alejandro",
    "wof:placetype":"venue"
},
  "geometry": {"coordinates":[-0.3667179942,41.9412994385],"type":"Point"}
}