{
  "type": "Feature",
  "properties": {
    "addr:full":"Calle de Vicente Rey, 78 Lopera Ja\u00e9n 23780",
    "addr:housenumber":"78",
    "addr:postcode":"23780",
    "addr:street":"Calle De Vicente Rey",
    "iso:country":"ES",
    "sg:address":"Calle de Vicente Rey, 78",
    "sg:city":"Lopera",
    "sg:orig_category":"Promotores Constructores",
    "sg:phone":"+34 953 51 67 34",
    "sg:postcode":"23780",
    "sg:province":"Ja\u00e9n",
    "wof:name":"Construcciones Sanchez A Y Jm S.l.",
    "wof:placetype":"venue"
},
  "geometry": {"coordinates":[-4.2108941078,37.9467926025],"type":"Point"}
}