{
  "type": "Feature",
  "properties": {
    "addr:full":"Carr Biscaia, 46 Andratx Islas Baleares 07150",
    "addr:housenumber":"46",
    "addr:postcode":"07150",
    "addr:street":"Carr Biscaia",
    "iso:country":"ES",
    "sg:address":"Carr Biscaia, 46",
    "sg:city":"Andratx",
    "sg:orig_category":"Notarios",
    "sg:phone":"+34 971 13 62 70",
    "sg:postcode":"07150",
    "sg:province":"Islas Baleares",
    "wof:name":"Nu\u00f1ez Caballero Miguel",
    "wof:placetype":"venue"
},
  "geometry": {"coordinates":[2.4228799343,39.5626411438],"type":"Point"}
}