{
  "type": "Feature",
  "properties": {
    "iso:country":"ES",
    "sg:address":"Plaz Pueblo (del), 12",
    "sg:city":"Colmenar Viejo",
    "sg:orig_category":"Cajas De Ahorro",
    "sg:phone":"+34 918 45 67 24",
    "sg:postcode":"28770",
    "sg:province":"Madrid",
    "wof:name":"Caixa D'estalvis De Catalunya",
    "wof:placetype":"venue"
},
  "geometry": {"coordinates":[-3.7655479908,40.6590423584],"type":"Point"}
}