{
  "type": "Feature",
  "properties": {
    "iso:country":"ES",
    "sg:address":"Calle de Alondra, 9",
    "sg:city":"Madrid",
    "sg:orig_category":"Radiocomunicaciones, Telefon\u00cda M\u00d3vil, Radiomensajer\u00cda: Servicios, Comercializaci\u00d3n",
    "sg:phone":"+34 914 62 11 36",
    "sg:postcode":"28025",
    "sg:province":"Madrid",
    "wof:name":"Naranjo Viteri Yessenia Elisabet",
    "wof:placetype":"venue"
},
  "geometry": {"coordinates":[-3.7348837852,40.387462616],"type":"Point"}
}