{
  "type": "Feature",
  "properties": {
    "iso:country":"ES",
    "sg:address":"Arcades, S/n",
    "sg:city":"Montblanc",
    "sg:classifiers":[
        {
            "category":"Recreation",
            "type":"Entertainment"
        }
    ],
    "sg:phone":"+34 977 86 08 57",
    "sg:postcode":"43400",
    "sg:province":"Tarragona",
    "sg:tags":[
        "caza",
        "pr\u00c1ctica",
        "la",
        "de",
        "pesca",
        "y"
    ],
    "wof:name":"Societat De Ca\u00e7adors La Codorniu",
    "wof:placetype":"venue"
},
  "geometry": {"coordinates":[1.1643300056,41.3753395081],"type":"Point"}
}