{
  "type": "Feature",
  "properties": {
    "iso:country":"ES",
    "sg:address":"Pg Ter, 34",
    "sg:city":"Manlleu",
    "sg:orig_category":"Material Did\u00c1ctico",
    "sg:phone":"+34 938 51 27 25",
    "sg:postcode":"08560",
    "sg:province":"Barcelona",
    "sg:website":"www.xango.biz",
    "wof:name":"Xango Societat Limitada",
    "wof:placetype":"venue"
},
  "geometry": {"coordinates":[2.2842071056,41.9974937439],"type":"Point"}
}