{
  "type": "Feature",
  "properties": {
    "addr:full":"Calle de Lepanto, 6 Malaga M\u00e1laga 29003",
    "addr:housenumber":"6",
    "addr:postcode":"29003",
    "addr:street":"Calle De Lepanto;Ma\u0301Laga",
    "iso:country":"ES",
    "sg:address":"Calle de Lepanto, 6",
    "sg:city":"Malaga",
    "sg:orig_category":"Panader\u00cdas, Panader\u00cdas",
    "sg:phone":"+34 952 34 17 12",
    "sg:postcode":"29003",
    "sg:province":"M\u00e1laga",
    "wof:name":"Beltran Galindo Guillermina",
    "wof:placetype":"venue"
},
  "geometry": {"coordinates":[-4.4441208839,36.6977577209],"type":"Point"}
}