{
  "type": "Feature",
  "properties": {
    "addr:full":"Carrer de Taquigraf Garriga, 72 Barcelona Barcelona 08029",
    "addr:housenumber":"72",
    "addr:postcode":"08029",
    "addr:street":"Carrer De Taquigraf Garriga",
    "iso:country":"ES",
    "sg:address":"Carrer de Taquigraf Garriga, 72",
    "sg:city":"Barcelona",
    "sg:orig_category":"Reposter\u00cdas",
    "sg:phone":"+34 934 39 36 29",
    "sg:postcode":"08029",
    "sg:province":"Barcelona",
    "wof:name":"Forn Les Corts S.l.",
    "wof:placetype":"venue"
},
  "geometry": {"coordinates":[2.1352629662,41.3877449036],"type":"Point"}
}