{
  "type": "Feature",
  "properties": {
    "addr:full":"Playa Del Arenal, 80 Javea Alicante 03730",
    "addr:housenumber":"80",
    "addr:postcode":"03730",
    "addr:street":"Playa Del Arenal",
    "iso:country":"ES",
    "sg:address":"Playa Del Arenal, 80",
    "sg:city":"Javea",
    "sg:orig_category":"Controles De Edificaci\u00d3n (construcci\u00d3n, Seguridad)",
    "sg:phone":"+34 965 77 10 03",
    "sg:postcode":"03730",
    "sg:province":"Alicante",
    "wof:name":"Almerinta,s.l.",
    "wof:placetype":"venue"
},
  "geometry": {"coordinates":[0.1635441929,38.773349762],"type":"Point"}
}