{
  "type": "Feature",
  "properties": {
    "iso:country":"ES",
    "sg:address":"Barr Matanza (la), 101",
    "sg:city":"Matanza",
    "sg:orig_category":"Chapister\u00cda",
    "sg:phone":"+34 946 80 92 22",
    "sg:postcode":"39880",
    "sg:province":"Cantabria",
    "wof:name":"Herrandorena Gil Jose Luis",
    "wof:placetype":"venue"
},
  "geometry": {"coordinates":[-3.2616589069,43.2439994812],"type":"Point"}
}