{
  "type": "Feature",
  "properties": {
    "addr:full":"Bo. Irabien, 23 Irabien \u00c1lava 01409",
    "addr:housenumber":"23",
    "addr:postcode":"01409",
    "addr:street":"Bo. Irabien;A\u0301Lava",
    "iso:country":"ES",
    "sg:address":"Bo. Irabien, 23",
    "sg:city":"Irabien",
    "sg:orig_category":"Supermercados Y Hipermercados",
    "sg:phone":"+34 945 89 82 48",
    "sg:postcode":"01409",
    "sg:province":"\u00c1lava",
    "wof:name":"Gonzaga Abiega Maria Del Carmen",
    "wof:placetype":"venue"
},
  "geometry": {"coordinates":[-3.0286810398,43.1525382996],"type":"Point"}
}