{
  "type": "Feature",
  "properties": {
    "iso:country":"ES",
    "sg:address":"Carr Catalunya, 24",
    "sg:city":"Bellver Cerdanya",
    "sg:orig_category":"Florister\u00cdas",
    "sg:phone":"+34 973 51 05 46",
    "sg:postcode":"25720",
    "sg:province":"Lleida",
    "wof:name":"Magatzem Guerrero S.l.",
    "wof:placetype":"venue"
},
  "geometry": {"coordinates":[1.7763129473,42.371257782],"type":"Point"}
}