{
  "type": "Feature",
  "properties": {
    "addr:full":"Calle de Troncon, 15 Fuengirola M\u00e1laga 29640",
    "addr:housenumber":"15",
    "addr:postcode":"29640",
    "addr:street":"Calle De Troncon;Ma\u0301Laga",
    "iso:country":"ES",
    "sg:address":"Calle de Troncon, 15",
    "sg:city":"Fuengirola",
    "sg:orig_category":"Molduras, Junquillos, Listones Y Molduras Perforadas",
    "sg:phone":"+34 952 58 83 91",
    "sg:postcode":"29640",
    "sg:province":"M\u00e1laga",
    "wof:name":"Dominguez Haro Francisca",
    "wof:placetype":"venue"
},
  "geometry": {"coordinates":[-4.6257100105,36.5366897583],"type":"Point"}
}