{
  "type": "Feature",
  "properties": {
    "addr:full":"Pol Ind El Pino, S/n Sevilla Sevilla 41016",
    "addr:housenumber":"/ n",
    "addr:postcode":"41016",
    "addr:street":"Pino S",
    "iso:country":"ES",
    "sg:address":"Pol Ind El Pino, S/n",
    "sg:city":"Sevilla",
    "sg:orig_category":"Papel, Reciclaje",
    "sg:phone":"+34 954 67 44 98",
    "sg:postcode":"41016",
    "sg:province":"Sevilla",
    "wof:name":"Reguesa S.l.",
    "wof:placetype":"venue"
},
  "geometry": {"coordinates":[-5.9262089729,37.3770637512],"type":"Point"}
}