{
  "type": "Feature",
  "properties": {
    "addr:full":"Prolongacion Sierra Ascoy, 24 Cieza Murcia 30530",
    "addr:housenumber":"24",
    "addr:postcode":"30530",
    "addr:street":"Prolongacion Sierra Ascoy",
    "iso:country":"ES",
    "sg:address":"Prolongacion Sierra Ascoy, 24",
    "sg:city":"Cieza",
    "sg:orig_category":"Confecci\u00d3n (fabricaci\u00d3n, Al Por Mayor)",
    "sg:phone":"+34 968 45 64 91",
    "sg:postcode":"30530",
    "sg:province":"Murcia",
    "wof:name":"Textil 2006 S.l.l.",
    "wof:placetype":"venue"
},
  "geometry": {"coordinates":[-1.4207789898,38.2454605103],"type":"Point"}
}