{
  "type": "Feature",
  "properties": {
    "iso:country":"ES",
    "sg:address":"Carrer de Vent (del), 11",
    "sg:city":"Montbrio Del Camp",
    "sg:orig_category":"Promotores Constructores",
    "sg:phone":"+34 977 82 62 29",
    "sg:postcode":"43340",
    "sg:province":"Tarragona",
    "wof:name":"Construcciones Josep Maria Baiges Sl",
    "wof:placetype":"venue"
},
  "geometry": {"coordinates":[1.005053997,41.1225852966],"type":"Point"}
}