{
  "type": "Feature",
  "properties": {
    "iso:country":"ES",
    "sg:address":"Carrer de Sau, 3",
    "sg:city":"Vic",
    "sg:orig_category":"Cueros Y Pieles (al Por Mayor)",
    "sg:phone":"+34 938 89 19 79",
    "sg:postcode":"08500",
    "sg:province":"Barcelona",
    "wof:name":"Boix Capdevila Esteban",
    "wof:placetype":"venue"
},
  "geometry": {"coordinates":[2.2830460072,41.9465522766],"type":"Point"}
}