{
  "type": "Feature",
  "properties": {
    "iso:country":"ES",
    "sg:address":"Av Gaspar Bennazar, 4",
    "sg:city":"Palma",
    "sg:orig_category":"Edici\u00d3n De Diarios, Revistas, Boletines",
    "sg:phone":"+34 971 20 84 88",
    "sg:postcode":"07004",
    "sg:province":"Islas Baleares",
    "wof:name":"Ediciones Rueda J.m.",
    "wof:placetype":"venue"
},
  "geometry": {"coordinates":[2.661864996,39.5818710327],"type":"Point"}
}