{
  "type": "Feature",
  "properties": {
    "addr:full":"M. Comercial L. De Pesc (p I Guadalete), 12 Pto Sta Maria C\u00e1diz 11500",
    "addr:housenumber":"12",
    "addr:postcode":"11500",
    "addr:street":"Guadalete;Ca\u0301Diz",
    "iso:country":"ES",
    "sg:address":"M. Comercial L. De Pesc (p I Guadalete), 12",
    "sg:city":"Pto Sta Maria",
    "sg:orig_category":"Electrodom\u00c9sticos (fabricaci\u00d3n, Al Por Mayor)",
    "sg:phone":"+34 956 56 21 16",
    "sg:postcode":"11500",
    "sg:province":"C\u00e1diz",
    "wof:name":"Pe\u00f1a Nu\u00f1ez Jose",
    "wof:placetype":"venue"
},
  "geometry": {"coordinates":[-6.2902097702,36.5298614502],"type":"Point"}
}