{
  "type": "Feature",
  "properties": {
    "iso:country":"ES",
    "sg:address":"Calle de Castillete, 9",
    "sg:city":"Union",
    "sg:orig_category":"Expositores",
    "sg:phone":"+34 968 56 05 28",
    "sg:postcode":"30360",
    "sg:province":"Murcia",
    "wof:name":"Pagan Lopez Antonio",
    "wof:placetype":"venue"
},
  "geometry": {"coordinates":[-0.875700891,37.6255645752],"type":"Point"}
}