{
  "type": "Feature",
  "properties": {
    "iso:country":"ES",
    "sg:address":"Calle de Rio, 9",
    "sg:city":"Uharte-arakil",
    "sg:orig_category":"Supermercados Y Hipermercados",
    "sg:phone":"+34 948 46 40 05",
    "sg:postcode":"31840",
    "sg:province":"Navarra",
    "wof:name":"Garro Loidi Jose Luis",
    "wof:placetype":"venue"
},
  "geometry": {"coordinates":[-1.9683259726,42.9221076965],"type":"Point"}
}