{
  "type": "Feature",
  "properties": {
    "iso:country":"ES",
    "sg:address":"Avda Virgen De Fatima (de), 38",
    "sg:city":"Cordoba",
    "sg:orig_category":"M\u00c9dicos: Pediatr\u00cda. Enfermedades De Los Ni\u00d1os",
    "sg:phone":"+34 957 25 45 80",
    "sg:postcode":"14014",
    "sg:province":"C\u00f3rdoba",
    "wof:name":"Rios Garcia Rafael",
    "wof:placetype":"venue"
},
  "geometry": {"coordinates":[-4.7562007904,37.8977355957],"type":"Point"}
}