{
  "type": "Feature",
  "properties": {
    "iso:country":"ES",
    "sg:address":"Calle de Guadalquivir, 24",
    "sg:city":"Mairena Alcor",
    "sg:orig_category":"Zapatos (al Por Menor)",
    "sg:phone":"+34 955 74 61 76",
    "sg:postcode":"41510",
    "sg:province":"Sevilla",
    "wof:name":"Cordero Gonzalez Juan Antonio",
    "wof:placetype":"venue"
},
  "geometry": {"coordinates":[-5.7454891205,37.3764801025],"type":"Point"}
}