{
  "type": "Feature",
  "properties": {
    "iso:country":"ES",
    "sg:address":"Ctra Rubi, 88",
    "sg:city":"Mira-sol",
    "sg:orig_category":"Cintas, Balduques Y Cierres De Tela (fabricaci\u00d3n, Al Por Mayor)",
    "sg:phone":"+34 935 90 03 82",
    "sg:postcode":"08173",
    "sg:province":"Barcelona",
    "sg:website":"www.binder-iberica.com",
    "wof:name":"Sistemas De Cierre Binder S.l.",
    "wof:placetype":"venue"
},
  "geometry": {"coordinates":[2.0622999668,41.4687690735],"type":"Point"}
}