{
  "type": "Feature",
  "properties": {
    "iso:country":"ES",
    "sg:address":"Calle de Valderribas, 26",
    "sg:city":"Madrid",
    "sg:orig_category":"M\u00c9dicos: Estomatolog\u00cda",
    "sg:phone":"+34 915 01 34 48",
    "sg:postcode":"28007",
    "sg:province":"Madrid",
    "wof:name":"Galindo Victorio Lucia",
    "wof:placetype":"venue"
},
  "geometry": {"coordinates":[-3.6763999462,40.4047050476],"type":"Point"}
}