{
  "type": "Feature",
  "properties": {
    "addr:full":"Calle de Herrenes, 29 Fresneda Toledo 45651",
    "addr:housenumber":"29",
    "addr:postcode":"45651",
    "addr:street":"Calle De Herrenes",
    "iso:country":"ES",
    "sg:address":"Calle de Herrenes, 29",
    "sg:city":"Fresneda",
    "sg:orig_category":"Transportes Por Carretera: Lotes Completos, Mercanc\u00cdas Diversas",
    "sg:phone":"+34 925 70 47 13",
    "sg:postcode":"45651",
    "sg:province":"Toledo",
    "wof:name":"Lopez Fernandez Angela",
    "wof:placetype":"venue"
},
  "geometry": {"coordinates":[-4.7743239403,39.7032966614],"type":"Point"}
}