{
  "type": "Feature",
  "properties": {
    "iso:country":"ES",
    "sg:address":"Carrer de Mandri, 3",
    "sg:city":"Barcelona",
    "sg:orig_category":"M\u00c9dicos: Pediatr\u00cda. Enfermedades De Los Ni\u00d1os",
    "sg:phone":"+34 934 18 17 92",
    "sg:postcode":"08022",
    "sg:province":"Barcelona",
    "wof:name":"Bargu\u00f1o Bassols Jose Maria",
    "wof:placetype":"venue"
},
  "geometry": {"coordinates":[2.1354711056,41.4016342163],"type":"Point"}
}