{
  "type": "Feature",
  "properties": {
    "iso:country":"ES",
    "sg:address":"Avda Espa\u00d1a, 1",
    "sg:city":"Ceuta",
    "sg:orig_category":"Mercer\u00cda, Lencer\u00cda (al Por Menor)",
    "sg:phone":"+34 956 50 73 10",
    "sg:postcode":"51001",
    "sg:province":"Ceuta",
    "wof:name":"Lopez Paris Maria",
    "wof:placetype":"venue"
},
  "geometry": {"coordinates":[-5.3210959435,35.8895339966],"type":"Point"}
}