{
  "type": "Feature",
  "properties": {
    "iso:country":"ES",
    "sg:address":"Calle de Lopez De Hoyos, 39",
    "sg:city":"Madrid",
    "sg:orig_category":"Iglesia Cat\u00d3lica",
    "sg:phone":"+34 915 63 53 33",
    "sg:postcode":"28002",
    "sg:province":"Madrid",
    "wof:name":"Parroquia San Miguel De Los Santos",
    "wof:placetype":"venue"
},
  "geometry": {"coordinates":[-3.6791069508,40.4413261414],"type":"Point"}
}