{
  "type": "Feature",
  "properties": {
    "addr:full":"Rua Comunidad De Madrid, 5 Carballi\u00f1o Ourense 32500",
    "addr:housenumber":"5",
    "addr:postcode":"32500",
    "addr:street":"Rua Comunidad;Madrid",
    "iso:country":"ES",
    "sg:address":"Rua Comunidad De Madrid, 5",
    "sg:city":"Carballi\u00f1o",
    "sg:orig_category":"Muebles, Minoristas",
    "sg:phone":"+34 988 27 44 43",
    "sg:postcode":"32500",
    "sg:province":"Ourense",
    "wof:name":"Cibeira Mato Camilo",
    "wof:placetype":"venue"
},
  "geometry": {"coordinates":[-8.087430954,42.4260902405],"type":"Point"}
}