{
  "type": "Feature",
  "properties": {
    "iso:country":"ES",
    "sg:address":"Cruceiros, S/n",
    "sg:city":"Barra Mi\u00f1o",
    "sg:orig_category":"Chapister\u00cda",
    "sg:phone":"+34 988 20 60 93",
    "sg:postcode":"32950",
    "sg:province":"Ourense",
    "wof:name":"Sotelo Dosouto Camilo",
    "wof:placetype":"venue"
},
  "geometry": {"coordinates":[-7.8384737968,42.3799209595],"type":"Point"}
}