{
  "type": "Feature",
  "properties": {
    "iso:country":"ES",
    "sg:address":"Calle de Madrid (de), 18",
    "sg:city":"Fuenlabrada",
    "sg:orig_category":"Asociaciones Y Clubs Deportivos",
    "sg:phone":"+34 916 09 83 91",
    "sg:postcode":"28944",
    "sg:province":"Madrid",
    "wof:name":"Abanades Peralta Silvia",
    "wof:placetype":"venue"
},
  "geometry": {"coordinates":[-3.797212,40.280392],"type":"Point"}
}