{
  "type": "Feature",
  "properties": {
    "addr:full":"Sa Placa, 11 Sa Pobla Islas Baleares 07420",
    "addr:housenumber":"11",
    "addr:postcode":"07420",
    "addr:street":"Placa",
    "iso:country":"ES",
    "sg:address":"Sa Placa, 11",
    "sg:city":"Sa Pobla",
    "sg:orig_category":"M\u00c9dicos: Gastroenterolog\u00cda Y Hepatolog\u00cda (aparato Digestivo)",
    "sg:phone":"+34 971 54 17 56",
    "sg:postcode":"07420",
    "sg:province":"Islas Baleares",
    "wof:name":"Gaya Prohens S.l.",
    "wof:placetype":"venue"
},
  "geometry": {"coordinates":[3.0255138874,39.7686805725],"type":"Point"}
}