{
  "type": "Feature",
  "properties": {
    "iso:country":"ES",
    "sg:address":"Calle de Toledo, 141",
    "sg:city":"Madrid",
    "sg:orig_category":"Ropa Y Accesorios",
    "sg:phone":"+34 914 73 82 38",
    "sg:postcode":"28005",
    "sg:province":"Madrid",
    "wof:name":"Unifor's Line S.l.",
    "wof:placetype":"venue"
},
  "geometry": {"coordinates":[-3.7124760151,40.4046058655],"type":"Point"}
}