{
  "type": "Feature",
  "properties": {
    "addr:full":"Calle de Secundino Esnaola, 5 Donostia-san Sebastian Guip\u00f9zcoa 20001",
    "addr:housenumber":"5",
    "addr:postcode":"20001",
    "addr:street":"Calle De Secundino Esnaola",
    "iso:country":"ES",
    "sg:address":"Calle de Secundino Esnaola, 5",
    "sg:city":"Donostia-san Sebastian",
    "sg:orig_category":"Psic\u00d3logos",
    "sg:phone":"+34 943 32 04 36",
    "sg:postcode":"20001",
    "sg:province":"Guip\u00f9zcoa",
    "wof:name":"Bengoechea Nerecan Alicia Maria Enriqueta",
    "wof:placetype":"venue"
},
  "geometry": {"coordinates":[-1.9750930071,43.3223800659],"type":"Point"}
}