{
  "type": "Feature",
  "properties": {
    "iso:country":"ES",
    "sg:address":"Pase Cuellar, 47",
    "sg:city":"Zaragoza",
    "sg:orig_category":"M\u00c9dicos: Ginecolog\u00cda Y Obstetricia",
    "sg:phone":"+34 976 37 29 23",
    "sg:postcode":"50007",
    "sg:province":"Zaragoza",
    "wof:name":"Tello Galindo Agustin Angel",
    "wof:placetype":"venue"
},
  "geometry": {"coordinates":[-0.8843269944,41.6361122131],"type":"Point"}
}