{
  "type": "Feature",
  "properties": {
    "iso:country":"ES",
    "sg:address":"Rua Cotelma (da), 13",
    "sg:city":"Valenza",
    "sg:orig_category":"Maquinaria Para Industrias Diversas",
    "sg:phone":"+34 988 37 23 02",
    "sg:postcode":"32002",
    "sg:province":"Ourense",
    "wof:name":"Barreras De Seguridad S.l.",
    "wof:placetype":"venue"
},
  "geometry": {"coordinates":[-7.8811202049,42.3190994263],"type":"Point"}
}