{
  "type": "Feature",
  "properties": {
    "iso:country":"ES",
    "sg:address":"Carrer de Jeroni Alemany, 5",
    "sg:city":"Palma",
    "sg:orig_category":"Transportes Por Carretera: Lotes Completos, Mercanc\u00cdas Diversas",
    "sg:phone":"+34 971 28 38 55",
    "sg:postcode":"07011",
    "sg:province":"Islas Baleares",
    "wof:name":"Distribuciones Salleras Vidal S.l.",
    "wof:placetype":"venue"
},
  "geometry": {"coordinates":[2.6377139091,39.5798072815],"type":"Point"}
}