{
  "type": "Feature",
  "properties": {
    "iso:country":"ES",
    "sg:address":"Calle de Ramon Y Cajal, 12",
    "sg:city":"Laguna Duero",
    "sg:orig_category":"Servicio De Salud",
    "sg:phone":"+34 983 54 15 03",
    "sg:postcode":"47140",
    "sg:province":"Valladolid",
    "wof:name":"Colado Lopez Eva Maria",
    "wof:placetype":"venue"
},
  "geometry": {"coordinates":[-4.724419117,41.580581665],"type":"Point"}
}