{
  "type": "Feature",
  "properties": {
    "addr:full":"Ctra Murillo, S/n Calahorra La Rioja 26500",
    "addr:housenumber":"s / n",
    "addr:postcode":"26500",
    "addr:street":"Ctra Murillo",
    "iso:country":"ES",
    "sg:address":"Ctra Murillo, S/n",
    "sg:city":"Calahorra",
    "sg:orig_category":"Reciclaje, Desguace De Veh\u00cdculos",
    "sg:phone":"+34 941 74 30 33",
    "sg:postcode":"26500",
    "sg:province":"La Rioja",
    "sg:website":"www.desguacecalahorra.com",
    "wof:name":"Desguace Calahorra S.c.",
    "wof:placetype":"venue"
},
  "geometry": {"coordinates":[-1.9731140137,42.3031311035],"type":"Point"}
}