{
  "type": "Feature",
  "properties": {
    "addr:full":"Calle de Iglesia, 40 Navaluenga \u00c1vila 05100",
    "addr:housenumber":"40",
    "addr:postcode":"05100",
    "addr:street":"Calle De Iglesia",
    "iso:country":"ES",
    "sg:address":"Calle de Iglesia, 40",
    "sg:city":"Navaluenga",
    "sg:orig_category":"Plomeros",
    "sg:phone":"+34 920 28 64 66",
    "sg:postcode":"05100",
    "sg:province":"\u00c1vila",
    "wof:name":"Rueda Corralejo Juan",
    "wof:placetype":"venue"
},
  "geometry": {"coordinates":[-4.7080287933,40.4113082886],"type":"Point"}
}