{
  "type": "Feature",
  "properties": {
    "iso:country":"ES",
    "sg:address":"Calle de Francos, S/n",
    "sg:city":"Olmedo",
    "sg:orig_category":"Asociaciones Y Clubs Deportivos",
    "sg:phone":"+34 983 60 11 52",
    "sg:postcode":"47410",
    "sg:province":"Valladolid",
    "wof:name":"Minguela Ortega Henar",
    "wof:placetype":"venue"
},
  "geometry": {"coordinates":[-4.686398983,41.2874755859],"type":"Point"}
}