{
  "type": "Feature",
  "properties": {
    "addr:full":"Calle de Javier (don), 62 Socuellamos Ciudad Real 13630",
    "addr:housenumber":"62",
    "addr:postcode":"13630",
    "addr:street":"Calle De Javier Don",
    "iso:country":"ES",
    "sg:address":"Calle de Javier (don), 62",
    "sg:city":"Socuellamos",
    "sg:orig_category":"Papeler\u00cdas: Art\u00cdculos (al Por Mayor)",
    "sg:phone":"+34 926 53 27 15",
    "sg:postcode":"13630",
    "sg:province":"Ciudad Real",
    "wof:name":"Distribuciones Alcolea Ballesteros S.l.",
    "wof:placetype":"venue"
},
  "geometry": {"coordinates":[-2.7924890518,39.2827682495],"type":"Point"}
}