{
  "type": "Feature",
  "properties": {
    "addr:full":"Calle de Echegaray, S/n Roda Albacete 02630",
    "addr:housenumber":"s / n",
    "addr:postcode":"02630",
    "addr:street":"Calle De Echegaray",
    "iso:country":"ES",
    "sg:address":"Calle de Echegaray, S/n",
    "sg:city":"Roda",
    "sg:orig_category":"Centros De Educaci\u00d3n Especial",
    "sg:phone":"+34 967 44 16 85",
    "sg:postcode":"02630",
    "sg:province":"Albacete",
    "wof:name":"Ministerio De Educacion Y Ciencia-colegio Publico Miguel Hernandez",
    "wof:placetype":"venue"
},
  "geometry": {"coordinates":[-2.1593031883,39.2107543945],"type":"Point"}
}