{
  "type": "Feature",
  "properties": {
    "iso:country":"ES",
    "sg:address":"Calle de Norias, 165",
    "sg:city":"Majadahonda",
    "sg:orig_category":"Inmobiliaria (agencias)",
    "sg:phone":"+34 916 02 95 46",
    "sg:postcode":"28220",
    "sg:province":"Madrid",
    "wof:name":"Merinacasa Asesoria Integral S.l",
    "wof:placetype":"venue"
},
  "geometry": {"coordinates":[-3.8688089848,40.4712905884],"type":"Point"}
}