{
  "type": "Feature",
  "properties": {
    "iso:country":"ES",
    "sg:address":"Pol. Ind., S/n",
    "sg:city":"Azuaga",
    "sg:orig_category":"Lacadores",
    "sg:phone":"+34 924 89 13 65",
    "sg:postcode":"06920",
    "sg:province":"Badajoz",
    "wof:name":"Castillo Prieto Manuel",
    "wof:placetype":"venue"
},
  "geometry": {"coordinates":[-5.6808290482,38.2573204041],"type":"Point"}
}