{
  "type": "Feature",
  "properties": {
    "addr:full":"Carrer de Andrade, 156 Barcelona Barcelona 08020",
    "addr:housenumber":"156",
    "addr:postcode":"08020",
    "addr:street":"Carrer De Andrade",
    "iso:country":"ES",
    "sg:address":"Carrer de Andrade, 156",
    "sg:city":"Barcelona",
    "sg:orig_category":"Poller\u00cda Y Caza (al Por Menor)",
    "sg:phone":"+34 933 13 33 99",
    "sg:postcode":"08020",
    "sg:province":"Barcelona",
    "wof:name":"Hernandez Almecija Rosa",
    "wof:placetype":"venue"
},
  "geometry": {"coordinates":[2.2016680241,41.4162826538],"type":"Point"}
}