{
  "type": "Feature",
  "properties": {
    "iso:country":"ES",
    "sg:address":"C/ Ciutat De Gibraltar, 10",
    "sg:city":"Paterna",
    "sg:orig_category":"Fabricaci\u00d3n De Telas Y Sedas",
    "sg:phone":"+34 961 34 40 75",
    "sg:postcode":"46988",
    "sg:province":"Valencia",
    "wof:name":"Distribuidora De Tejidos S.a.",
    "wof:placetype":"venue"
},
  "geometry": {"coordinates":[-0.4724059999,39.5111808777],"type":"Point"}
}