{
  "type": "Feature",
  "properties": {
    "addr:full":"Calle de Mesena, 22 Madrid Madrid 28033",
    "addr:housenumber":"22",
    "addr:postcode":"madrid;28033",
    "addr:street":"Calle De Mesena",
    "iso:country":"ES",
    "sg:address":"Calle de Mesena, 22",
    "sg:city":"Madrid",
    "sg:orig_category":"Inmobiliaria (agencias)",
    "sg:phone":"+34 917 59 24 67",
    "sg:postcode":"28033",
    "sg:province":"Madrid",
    "wof:name":"Torre Rioja-madrid S.a.",
    "wof:placetype":"venue"
},
  "geometry": {"coordinates":[-3.6618418694,40.4632720947],"type":"Point"}
}