{
  "type": "Feature",
  "properties": {
    "addr:full":"Calle de Doctor Navarro, 21 Alfara Patriarca Valencia 46115",
    "addr:housenumber":"21",
    "addr:postcode":"46115",
    "addr:street":"Calle De Doctor Navarro",
    "iso:country":"ES",
    "sg:address":"Calle de Doctor Navarro, 21",
    "sg:city":"Alfara Patriarca",
    "sg:orig_category":"Empresas De Pintura Y Revestimientos",
    "sg:phone":"+34 961 39 03 13",
    "sg:postcode":"46115",
    "sg:province":"Valencia",
    "wof:name":"Perez Quilis Francisco",
    "wof:placetype":"venue"
},
  "geometry": {"coordinates":[-0.3858411908,39.5446472168],"type":"Point"}
}