{
  "type": "Feature",
  "properties": {
    "addr:full":"Calle de San Jose (de), 43 Navalcarnero Madrid 28600",
    "addr:postcode":"28600",
    "addr:street":"Calle De San",
    "iso:country":"ES",
    "sg:address":"Calle de San Jose (de), 43",
    "sg:city":"Navalcarnero",
    "sg:orig_category":"Escultores, Estatuarios E Imagineros",
    "sg:phone":"+34 918 11 04 06",
    "sg:postcode":"28600",
    "sg:province":"Madrid",
    "wof:name":"Hernandez Sanchez Feliciano",
    "wof:placetype":"venue"
},
  "geometry": {"coordinates":[-4.0101752281,40.2900505066],"type":"Point"}
}