{
  "type": "Feature",
  "properties": {
    "iso:country":"ES",
    "sg:address":"Carrer de Priorat, 30",
    "sg:city":"Residencial",
    "sg:orig_category":"Molduras, Junquillos, Listones Y Molduras Perforadas",
    "sg:phone":"+34 977 69 45 27",
    "sg:postcode":"43820",
    "sg:province":"Tarragona",
    "wof:name":"Stephenson  Jacqueline Avril",
    "wof:placetype":"venue"
},
  "geometry": {"coordinates":[1.5684100389,41.1977844238],"type":"Point"}
}