{
  "type": "Feature",
  "properties": {
    "iso:country":"ES",
    "sg:address":"Calle de Jose Marcos De Segovia, S/n",
    "sg:city":"Ba\u00d1eza",
    "sg:orig_category":"Transportes Por V\u00cdas Navegables",
    "sg:phone":"+34 987 64 18 29",
    "sg:postcode":"24750",
    "sg:province":"Le\u00f3n",
    "wof:name":"Fernandez Lopez Manuel",
    "wof:placetype":"venue"
},
  "geometry": {"coordinates":[-5.9264888763,42.3065757751],"type":"Point"}
}