{
  "type": "Feature",
  "properties": {
    "iso:country":"ES",
    "sg:address":"Calle de Padre Balbino Velasco, 13",
    "sg:city":"Cuellar",
    "sg:orig_category":"Electrodom\u00c9sticos (al Por Menor)",
    "sg:phone":"+34 921 14 19 75",
    "sg:postcode":"40200",
    "sg:province":"Segovia",
    "wof:name":"Martin Garcia Pedro Luis",
    "wof:placetype":"venue"
},
  "geometry": {"coordinates":[-4.3103890419,41.400428772],"type":"Point"}
}