{
  "type": "Feature",
  "properties": {
    "addr:full":"Avda Ruiz Jarabo, 4 Teruel Teruel 44002",
    "addr:housenumber":"4",
    "addr:postcode":"44002",
    "addr:street":"Avda Ruiz Jarabo",
    "iso:country":"ES",
    "sg:address":"Avda Ruiz Jarabo, 4",
    "sg:city":"Teruel",
    "sg:orig_category":"Internados & Ense\u00d1anza Privada",
    "sg:phone":"+34 978 62 01 31",
    "sg:postcode":"44002",
    "sg:province":"Teruel",
    "wof:name":"Institucion Teresiana Asociacion Civil",
    "wof:placetype":"venue"
},
  "geometry": {"coordinates":[-1.1076220274,40.3340072632],"type":"Point"}
}