{
  "type": "Feature",
  "properties": {
    "addr:full":"Calle de Vinader, 8 Santa Catalina Murcia 30004",
    "addr:housenumber":"8",
    "addr:postcode":"30004",
    "addr:street":"Calle De Vinader",
    "iso:country":"ES",
    "sg:address":"Calle de Vinader, 8",
    "sg:city":"Santa Catalina",
    "sg:orig_category":"Agencias De Trabajo Temporal",
    "sg:phone":"+34 968 21 96 66",
    "sg:postcode":"30004",
    "sg:province":"Murcia",
    "wof:name":"Creyf's Trabajo Temporal S.a.",
    "wof:placetype":"venue"
},
  "geometry": {"coordinates":[-1.1334539652,37.9863891602],"type":"Point"}
}