{
  "type": "Feature",
  "properties": {
    "iso:country":"ES",
    "sg:address":"Calle de Francisco Guzman, 42",
    "sg:city":"Illescas",
    "sg:orig_category":"Promotores Constructores",
    "sg:phone":"+34 925 51 35 54",
    "sg:postcode":"45200",
    "sg:province":"Toledo",
    "wof:name":"Medran Caballero Rafael",
    "wof:placetype":"venue"
},
  "geometry": {"coordinates":[-3.8465490341,40.1244697571],"type":"Point"}
}