{
  "type": "Feature",
  "properties": {
    "addr:full":"Ctra. Sagunto-burgos, Km. 0125,0 Teruel Teruel 44002",
    "addr:postcode":"44002",
    "addr:street":"Ctra. Sagunto-Burgos Km. 0125,0;Teruel",
    "iso:country":"ES",
    "sg:address":"Ctra. Sagunto-burgos, Km. 0125,0",
    "sg:city":"Teruel",
    "sg:orig_category":"Transportes Urbanos Y Regionales Para Personas",
    "sg:phone":"+34 978 60 28 28",
    "sg:postcode":"44002",
    "sg:province":"Teruel",
    "wof:name":"Autobuses Teruel Zaragoza S.a.",
    "wof:placetype":"venue"
},
  "geometry": {"coordinates":[-1.1203912497,40.3458175659],"type":"Point"}
}