{
  "type": "Feature",
  "properties": {
    "addr:full":"Calle de Regidor Caballero Villamediana, 1 Fuente Obejuna C\u00f3rdoba 14290",
    "addr:housenumber":"1",
    "addr:postcode":"14290",
    "addr:street":"Calle De Regidor Caballero Villamediana",
    "iso:country":"ES",
    "sg:address":"Calle de Regidor Caballero Villamediana, 1",
    "sg:city":"Fuente Obejuna",
    "sg:orig_category":"Cajas De Ahorro",
    "sg:phone":"+34 957 58 40 64",
    "sg:postcode":"14290",
    "sg:province":"C\u00f3rdoba",
    "wof:name":"Caja De Ahorros Y Monte De Piedad De Cordoba",
    "wof:placetype":"venue"
},
  "geometry": {"coordinates":[-5.4189591408,38.2661209106],"type":"Point"}
}