{
  "type": "Feature",
  "properties": {
    "addr:full":"Avda Palencia, S/n Aguilar Campoo Palencia 34800",
    "addr:housenumber":"s / n",
    "addr:postcode":"34800",
    "addr:street":"Avda Palencia",
    "iso:country":"ES",
    "sg:address":"Avda Palencia, S/n",
    "sg:city":"Aguilar Campoo",
    "sg:orig_category":"Electricidad Veh\u00cdculo",
    "sg:phone":"+34 979 12 22 75",
    "sg:postcode":"34800",
    "sg:province":"Palencia",
    "wof:name":"Perez Catalina Jose Luis",
    "wof:placetype":"venue"
},
  "geometry": {"coordinates":[-4.2655792236,42.7925987244],"type":"Point"}
}