{
  "type": "Feature",
  "properties": {
    "addr:full":"Avda Colon, 15 Logro\u00f1o La Rioja 26003",
    "addr:housenumber":"15",
    "addr:postcode":"26003",
    "addr:street":"Avda Colon;Rioja",
    "iso:country":"ES",
    "sg:address":"Avda Colon, 15",
    "sg:city":"Logro\u00f1o",
    "sg:orig_category":"Institutos De Belleza",
    "sg:phone":"+34 941 24 59 51",
    "sg:postcode":"26003",
    "sg:province":"La Rioja",
    "wof:name":"Deanma Siglo Xxi S.l.",
    "wof:placetype":"venue"
},
  "geometry": {"coordinates":[-2.4393129349,42.4636077881],"type":"Point"}
}