{
  "type": "Feature",
  "properties": {
    "addr:full":"Rua Alcalde Lorenzo (del), 16 Bertamirans La Coru\u00f1a 15220",
    "addr:housenumber":"16",
    "addr:postcode":"15220",
    "addr:street":"Rua Alcalde Lorenzo Del;La Corun\u0303A",
    "iso:country":"ES",
    "sg:address":"Rua Alcalde Lorenzo (del), 16",
    "sg:city":"Bertamirans",
    "sg:orig_category":"Alimentaci\u00d3n General (al Por Mayor)",
    "sg:phone":"+34 981 89 16 74",
    "sg:postcode":"15220",
    "sg:province":"La Coru\u00f1a",
    "wof:name":"Paz Paz Ricardo",
    "wof:placetype":"venue"
},
  "geometry": {"coordinates":[-8.6529092789,42.8592033386],"type":"Point"}
}