{
  "type": "Feature",
  "properties": {
    "iso:country":"ES",
    "sg:address":"Calvo Sotelo, 26",
    "sg:city":"Casas Monte",
    "sg:orig_category":"Supermercados Y Hipermercados",
    "sg:phone":"+34 927 17 90 76",
    "sg:postcode":"10730",
    "sg:province":"C\u00e1ceres",
    "wof:name":"Rojo Leo Fernando",
    "wof:placetype":"venue"
},
  "geometry": {"coordinates":[-5.9633669853,40.2041282654],"type":"Point"}
}