{
  "type": "Feature",
  "properties": {
    "iso:country":"ES",
    "sg:address":"Calle de Burgao, 4",
    "sg:city":"Puerto Del Carmen",
    "sg:orig_category":"Cl\u00cdnicas M\u00c9dicas",
    "sg:phone":"+34 928 51 28 67",
    "sg:postcode":"35510",
    "sg:province":"Las Palmas",
    "wof:name":"Montmeda S.a",
    "wof:placetype":"venue"
},
  "geometry": {"coordinates":[-13.6330308914,28.930021286],"type":"Point"}
}