{
  "type": "Feature",
  "properties": {
    "iso:country":"ES",
    "sg:address":"Calle de Numancia, 22",
    "sg:city":"Soria",
    "sg:orig_category":"Pescader\u00cdas (al Por Menor)",
    "sg:phone":"+34 975 21 11 45",
    "sg:postcode":"42001",
    "sg:province":"Soria",
    "wof:name":"Moreno Garcia Jose Luis",
    "wof:placetype":"venue"
},
  "geometry": {"coordinates":[-2.4691669941,41.7646598816],"type":"Point"}
}