{
  "type": "Feature",
  "properties": {
    "addr:full":"Calle de Pellicer, 14 Caspe Zaragoza 50700",
    "addr:housenumber":"14",
    "addr:postcode":"50700",
    "addr:street":"Calle De Pellicer",
    "iso:country":"ES",
    "sg:address":"Calle de Pellicer, 14",
    "sg:city":"Caspe",
    "sg:orig_category":"Carnicer\u00cdas, Carnicer\u00cdas",
    "sg:phone":"+34 976 63 65 01",
    "sg:postcode":"50700",
    "sg:province":"Zaragoza",
    "wof:name":"Aceites Aborigenes Sl",
    "wof:placetype":"venue"
},
  "geometry": {"coordinates":[-0.0381992012,41.2356262207],"type":"Point"}
}