{
  "type": "Feature",
  "properties": {
    "iso:country":"ES",
    "sg:address":"Calle de Cantalejo, 3",
    "sg:city":"Madrid",
    "sg:orig_category":"Supermercados Y Hipermercados",
    "sg:phone":"+34 917 36 50 01",
    "sg:postcode":"28035",
    "sg:province":"Madrid",
    "wof:name":"Comercial Superma S.a.",
    "wof:placetype":"venue"
},
  "geometry": {"coordinates":[-3.7414205074,40.4755935669],"type":"Point"}
}