{
  "type": "Feature",
  "properties": {
    "addr:full":"Calle de Tosca La, S/n San Lorenzo Las Palmas 35018",
    "addr:housenumber":"/ n",
    "addr:postcode":"35018",
    "addr:street":"Calle De Tosca La S;Lorenzo Las",
    "iso:country":"ES",
    "sg:address":"Calle de Tosca La, S/n",
    "sg:city":"San Lorenzo",
    "sg:orig_category":"Poller\u00cda Y Caza (al Por Menor)",
    "sg:phone":"+34 928 67 55 48",
    "sg:postcode":"35018",
    "sg:province":"Las Palmas",
    "wof:name":"Quintana Ramos Manuel",
    "wof:placetype":"venue"
},
  "geometry": {"coordinates":[-15.4784650803,28.0919818878],"type":"Point"}
}