{
  "type": "Feature",
  "properties": {
    "iso:country":"ES",
    "sg:address":"Carrer de Sardenya, 508",
    "sg:city":"Barcelona",
    "sg:orig_category":"Reposter\u00cdas",
    "sg:phone":"+34 932 84 26 70",
    "sg:postcode":"08024",
    "sg:province":"Barcelona",
    "wof:name":"Rosines Pa S.l.",
    "wof:placetype":"venue"
},
  "geometry": {"coordinates":[2.1634719372,41.411190033],"type":"Point"}
}