{
  "type": "Feature",
  "properties": {
    "iso:country":"ES",
    "sg:address":"Carr Esglesia, 14",
    "sg:city":"Anglesola",
    "sg:orig_category":"Iglesia Cat\u00d3lica",
    "sg:phone":"+34 973 30 80 08",
    "sg:postcode":"25320",
    "sg:province":"Lleida",
    "wof:name":"Bisbat De Solsona",
    "wof:placetype":"venue"
},
  "geometry": {"coordinates":[1.0846190453,41.6594657898],"type":"Point"}
}