{
  "type": "Feature",
  "properties": {
    "addr:full":"Calle de Cigue\u00d1a, 18 Valladolid Valladolid 47012",
    "addr:housenumber":"18",
    "addr:postcode":"47012",
    "addr:street":"Calle De Ciguen\u0303A",
    "iso:country":"ES",
    "sg:address":"Calle de Cigue\u00d1a, 18",
    "sg:city":"Valladolid",
    "sg:orig_category":"Ense\u00d1anza Variada",
    "sg:phone":"+34 983 20 06 92",
    "sg:postcode":"47012",
    "sg:province":"Valladolid",
    "wof:name":"Gomez Benito Maximino",
    "wof:placetype":"venue"
},
  "geometry": {"coordinates":[-4.7102723122,41.6462860107],"type":"Point"}
}