{
  "type": "Feature",
  "properties": {
    "iso:country":"ES",
    "sg:address":"Carrer de Roger De Flor, 33",
    "sg:city":"Manresa",
    "sg:orig_category":"Agencias Y Agentes Comerciales, Representantes",
    "sg:phone":"+34 938 73 00 54",
    "sg:postcode":"08241",
    "sg:province":"Barcelona",
    "wof:name":"Ruiz Pe\u00f1a Angel",
    "wof:placetype":"venue"
},
  "geometry": {"coordinates":[1.8363200426,41.7248535156],"type":"Point"}
}