{
  "type": "Feature",
  "properties": {
    "addr:full":"Calle de Camino De Santiago, 27 Ponferrada Le\u00f3n 24400",
    "addr:housenumber":"27",
    "addr:postcode":"24400",
    "addr:street":"Calle De Camino De Santiago",
    "iso:country":"ES",
    "sg:address":"Calle de Camino De Santiago, 27",
    "sg:city":"Ponferrada",
    "sg:orig_category":"Bazares, Art\u00cdculos De Limpieza Y De Cocina (al Por Menor)",
    "sg:phone":"+34 987 40 97 19",
    "sg:postcode":"24400",
    "sg:province":"Le\u00f3n",
    "wof:name":"Zf Trading Aftermarket Iberica S.a.",
    "wof:placetype":"venue"
},
  "geometry": {"coordinates":[-6.5901231766,42.5396995544],"type":"Point"}
}