{
  "type": "Feature",
  "properties": {
    "iso:country":"ES",
    "sg:address":"Avgd Doctor Fleming, 9",
    "sg:city":"Lleida",
    "sg:orig_category":"M\u00c9dicos: Dermatolog\u00cda Y Venereolog\u00cda",
    "sg:phone":"+34 973 23 32 14",
    "sg:postcode":"25006",
    "sg:province":"Lleida",
    "wof:name":"Porqueras Mayo Jose Maria",
    "wof:placetype":"venue"
},
  "geometry": {"coordinates":[0.6176609993,41.618888855],"type":"Point"}
}