{
  "type": "Feature",
  "properties": {
    "iso:country":"ES",
    "sg:address":"Carrer de Bisbe Vilanova, 5",
    "sg:city":"Olot",
    "sg:orig_category":"M\u00c9dicos: Estomatolog\u00cda",
    "sg:phone":"+34 972 27 10 66",
    "sg:postcode":"17800",
    "sg:province":"Girona",
    "wof:name":"Perea Rodriguez Ignacio",
    "wof:placetype":"venue"
},
  "geometry": {"coordinates":[2.4860069752,42.1795349121],"type":"Point"}
}