{
  "type": "Feature",
  "properties": {
    "iso:country":"ES",
    "sg:address":"Calle de Logro\u00d1o, 29",
    "sg:city":"Miranda Ebro",
    "sg:orig_category":"Papeler\u00cdas, Librer\u00cdas",
    "sg:phone":"+34 947 33 05 91",
    "sg:postcode":"09200",
    "sg:province":"Burgos",
    "wof:name":"Mipapel S.c.",
    "wof:placetype":"venue"
},
  "geometry": {"coordinates":[-2.9387040138,42.6880226135],"type":"Point"}
}