{
  "type": "Feature",
  "properties": {
    "iso:country":"ES",
    "sg:address":"Calle de Periodista Leopoldo Ayuso, 7",
    "sg:city":"San Basilio",
    "sg:orig_category":"Agencias Y Asesores De Publicidad",
    "sg:phone":"+34 968 28 20 00",
    "sg:postcode":"30009",
    "sg:province":"Murcia",
    "wof:name":"Publicidad Liquida De Murcia S.l.",
    "wof:placetype":"venue"
},
  "geometry": {"coordinates":[-1.1483709812,37.9956207275],"type":"Point"}
}