{
  "type": "Feature",
  "properties": {
    "iso:country":"ES",
    "sg:address":"Calle de Martin De Los Heros, 17",
    "sg:city":"Madrid",
    "sg:orig_category":"Venta, Alquiler De Instrumentos Y Accesorios De M\u00dasica",
    "sg:phone":"+34 915 41 15 95",
    "sg:postcode":"28008",
    "sg:province":"Madrid",
    "sg:website":"www.musicalprincesa.com",
    "wof:name":"Musical Princesa S.l.",
    "wof:placetype":"venue"
},
  "geometry": {"coordinates":[-3.7143731117,40.4251556396],"type":"Point"}
}