{
  "type": "Feature",
  "properties": {
    "iso:country":"ES",
    "sg:address":"Calle de Ricardo De Los Rios, 1",
    "sg:city":"Laguna Duero",
    "sg:orig_category":"Peluquer\u00cdas, Peluquer\u00cda Mixta",
    "sg:phone":"+34 983 54 28 85",
    "sg:postcode":"47140",
    "sg:province":"Valladolid",
    "wof:name":"Torbado Sandoval Marina",
    "wof:placetype":"venue"
},
  "geometry": {"coordinates":[-4.7189879417,41.582118988],"type":"Point"}
}