{
  "type": "Feature",
  "properties": {
    "addr:full":"Avda Estacion, 23 Azuaga Badajoz 06920",
    "addr:housenumber":"23",
    "addr:postcode":"06920",
    "addr:street":"Avda Estacion",
    "iso:country":"ES",
    "sg:address":"Avda Estacion, 23",
    "sg:city":"Azuaga",
    "sg:orig_category":"Peluquer\u00cdas, Peluquer\u00cda Mixta",
    "sg:phone":"+34 924 89 18 21",
    "sg:postcode":"06920",
    "sg:province":"Badajoz",
    "wof:name":"Ruiz Gomez Raquel",
    "wof:placetype":"venue"
},
  "geometry": {"coordinates":[-5.6780581474,38.2620506287],"type":"Point"}
}