{
  "type": "Feature",
  "properties": {
    "iso:country":"ES",
    "sg:address":"Calle de Pantoja, 16",
    "sg:city":"Madrid",
    "sg:orig_category":"Chapister\u00cda",
    "sg:phone":"+34 914 15 86 73",
    "sg:postcode":"28002",
    "sg:province":"Madrid",
    "wof:name":"Talleres Villauto S.l.",
    "wof:placetype":"venue"
},
  "geometry": {"coordinates":[-3.6714947224,40.4482383728],"type":"Point"}
}