{
  "type": "Feature",
  "properties": {
    "addr:full":"Rond Sant Antoni Maria Claret, 31 Girona Girona 17001",
    "addr:housenumber":"31",
    "addr:postcode":"17001",
    "addr:street":"Sant Antoni Maria Claret",
    "iso:country":"ES",
    "sg:address":"Rond Sant Antoni Maria Claret, 31",
    "sg:city":"Girona",
    "sg:orig_category":"Electrodom\u00c9sticos (al Por Menor)",
    "sg:phone":"+34 972 20 35 73",
    "sg:postcode":"17001",
    "sg:province":"Girona",
    "wof:name":"Ball-llosera Llagostera Joan",
    "wof:placetype":"venue"
},
  "geometry": {"coordinates":[2.8210148811,41.9795875549],"type":"Point"}
}