{
  "type": "Feature",
  "properties": {
    "addr:full":"Cant Peque\u00d1o, 5 Coru\u00d1a La Coru\u00f1a 15003",
    "addr:housenumber":"5",
    "addr:postcode":"15003",
    "addr:street":"Pequen\u0303O;La Corun\u0303A",
    "iso:country":"ES",
    "sg:address":"Cant Peque\u00d1o, 5",
    "sg:city":"Coru\u00d1a",
    "sg:orig_category":"Inmobiliaria (agencias)",
    "sg:phone":"+34 981 21 63 67",
    "sg:postcode":"15003",
    "sg:province":"La Coru\u00f1a",
    "wof:name":"Arcilla Y Cobian Asesores S.l.",
    "wof:placetype":"venue"
},
  "geometry": {"coordinates":[-8.4033460617,43.370677948],"type":"Point"}
}