{
  "type": "Feature",
  "properties": {
    "iso:country":"ES",
    "sg:address":"Calle de Juan Florez, 80",
    "sg:city":"Coru\u00d1a",
    "sg:orig_category":"Marketing Directo",
    "sg:phone":"+34 981 25 42 66",
    "sg:postcode":"15005",
    "sg:province":"La Coru\u00f1a",
    "wof:name":"Estratel",
    "wof:placetype":"venue"
},
  "geometry": {"coordinates":[-8.4081897736,43.362449646],"type":"Point"}
}