{
  "type": "Feature",
  "properties": {
    "addr:full":"Calle de Ruzafa, 30 Valencia Valencia 46006",
    "addr:housenumber":"30",
    "addr:postcode":"46006",
    "addr:street":"Calle De Ruzafa",
    "iso:country":"ES",
    "sg:address":"Calle de Ruzafa, 30",
    "sg:city":"Valencia",
    "sg:orig_category":"Centros Empresariales",
    "sg:phone":"+34 963 69 67 22",
    "sg:postcode":"46006",
    "sg:province":"Valencia",
    "sg:website":"www.gestionc.es",
    "wof:name":"Gestion Integral De Contratos Y Centros De Trabajo S.l.",
    "wof:placetype":"venue"
},
  "geometry": {"coordinates":[-0.3737030029,39.4645805359],"type":"Point"}
}