{
  "type": "Feature",
  "properties": {
    "addr:full":"Calle de Rioja, 23 Leganes Madrid 28915",
    "addr:housenumber":"23",
    "addr:postcode":"28915",
    "addr:street":"Calle De Rioja",
    "iso:country":"ES",
    "sg:address":"Calle de Rioja, 23",
    "sg:city":"Leganes",
    "sg:orig_category":"Bisuter\u00cda, Joyer\u00cda, Relojer\u00cda (al Por Menor)",
    "sg:phone":"+34 916 80 50 12",
    "sg:postcode":"28915",
    "sg:province":"Madrid",
    "wof:name":"Zinnia 04 S.l.",
    "wof:placetype":"venue"
},
  "geometry": {"coordinates":[-3.7554249763,40.3310775757],"type":"Point"}
}