{
  "type": "Feature",
  "properties": {
    "iso:country":"ES",
    "sg:address":"Ctra Madrid, Km. 0301,0",
    "sg:city":"Ba\u00d1eza",
    "sg:orig_category":"Material Y Herramientas Agr\u00cdcolas",
    "sg:phone":"+34 987 65 62 38",
    "sg:postcode":"24750",
    "sg:province":"Le\u00f3n",
    "sg:website":"www.depuentegeijo.com",
    "wof:name":"De Puente Geijo S.l.",
    "wof:placetype":"venue"
},
  "geometry": {"coordinates":[-5.9242091179,42.3069114685],"type":"Point"}
}