{
  "type": "Feature",
  "properties": {
    "iso:country":"ES",
    "sg:address":"Carrer de Ocells, 33",
    "sg:city":"Palma",
    "sg:orig_category":"Art\u00cdculos De Regalo (al Por Menor)",
    "sg:phone":"+34 971 45 55 09",
    "sg:postcode":"07011",
    "sg:province":"Islas Baleares",
    "wof:name":"Margarita Sastre Capo",
    "wof:placetype":"venue"
},
  "geometry": {"coordinates":[2.6336460114,39.5831832886],"type":"Point"}
}