{
  "type": "Feature",
  "properties": {
    "iso:country":"ES",
    "sg:address":"Calle de Santa Clara, 89",
    "sg:city":"Sevilla",
    "sg:orig_category":"Dorados, Plater\u00cda (orfebrer\u00cda)",
    "sg:phone":"+34 954 38 85 84",
    "sg:postcode":"41002",
    "sg:province":"Sevilla",
    "wof:name":"Taller Orfebreria Jesus Dominguez S.l.",
    "wof:placetype":"venue"
},
  "geometry": {"coordinates":[-5.9960799217,37.4019775391],"type":"Point"}
}