{
  "type": "Feature",
  "properties": {
    "iso:country":"ES",
    "sg:address":"Cmno Suarez, 10",
    "sg:city":"Malaga",
    "sg:orig_category":"Ropa Para Ni\u00d1os (al Por Menor)",
    "sg:phone":"+34 952 39 09 99",
    "sg:postcode":"29010",
    "sg:province":"M\u00e1laga",
    "wof:name":"Grupo Proyecto Moda Joven S.l.",
    "wof:placetype":"venue"
},
  "geometry": {"coordinates":[-4.4369711876,36.7272872925],"type":"Point"}
}