{
  "type": "Feature",
  "properties": {
    "iso:country":"ES",
    "sg:address":"Carretera De Capuchinos, S/n",
    "sg:city":"Antequera",
    "sg:orig_category":"Negocio De Materiales De Construcci\u00d3n",
    "sg:phone":"+34 952 84 15 38",
    "sg:postcode":"29200",
    "sg:province":"M\u00e1laga",
    "wof:name":"Materiales De Construccion Rosal Perez S.l.",
    "wof:placetype":"venue"
},
  "geometry": {"coordinates":[-4.5653891563,37.0188293457],"type":"Point"}
}