{
  "type": "Feature",
  "properties": {
    "iso:country":"ES",
    "sg:address":"Carrer de Sant Esteve, 23",
    "sg:city":"Olot",
    "sg:orig_category":"Platos Preparados Refrigerados (fabricaci\u00d3n, Al Por Mayor)",
    "sg:phone":"+34 972 26 07 28",
    "sg:postcode":"17800",
    "sg:province":"Girona",
    "wof:name":"Primer Plat S.l.",
    "wof:placetype":"venue"
},
  "geometry": {"coordinates":[2.4882979393,42.1819763184],"type":"Point"}
}