{
  "type": "Feature",
  "properties": {
    "iso:country":"ES",
    "sg:address":"Pase Martutene De, 65",
    "sg:city":"Donostia-san Sebastian",
    "sg:orig_category":"Mec\u00c1nico Del Autom\u00d3vil",
    "sg:phone":"+34 943 46 36 19",
    "sg:postcode":"20014",
    "sg:province":"Guip\u00f9zcoa",
    "wof:name":"Arruabarrena Mendizabal Jose",
    "wof:placetype":"venue"
},
  "geometry": {"coordinates":[-1.9009970427,43.2548027039],"type":"Point"}
}