{
  "type": "Feature",
  "properties": {
    "addr:full":"Calle de Angel Ganivet, 5 Chauchina Granada 18330",
    "addr:housenumber":"5",
    "addr:postcode":"18330",
    "addr:street":"Calle De Angel Ganivet",
    "iso:country":"ES",
    "sg:address":"Calle de Angel Ganivet, 5",
    "sg:city":"Chauchina",
    "sg:orig_category":"Producci\u00d3n De Abonos Y De Fertilizantes",
    "sg:phone":"+34 958 44 60 02",
    "sg:postcode":"18330",
    "sg:province":"Granada",
    "wof:name":"Agroquimicos Chica Y Moreno C.b.",
    "wof:placetype":"venue"
},
  "geometry": {"coordinates":[-3.7677323818,37.2027702332],"type":"Point"}
}