{
  "type": "Feature",
  "properties": {
    "addr:full":"Carrer de Torrent (del), 8 Roda De Bara Tarragona 43883",
    "addr:housenumber":"8",
    "addr:postcode":"43883",
    "addr:street":"Carrer De Torrent Del",
    "iso:country":"ES",
    "sg:address":"Carrer de Torrent (del), 8",
    "sg:city":"Roda De Bara",
    "sg:orig_category":"Empresas De Carpinter\u00cda Met\u00c1lica",
    "sg:phone":"+34 977 80 90 47",
    "sg:postcode":"43883",
    "sg:province":"Tarragona",
    "wof:name":"Torres Sanroma Alejandro",
    "wof:placetype":"venue"
},
  "geometry": {"coordinates":[1.4545600414,41.1849632263],"type":"Point"}
}