{
  "type": "Feature",
  "properties": {
    "addr:full":"Gral. Mola, 35 Garcibuey Salamanca 37658",
    "addr:housenumber":"35",
    "addr:postcode":"37658",
    "addr:street":"Gral. Mola",
    "iso:country":"ES",
    "sg:address":"Gral. Mola, 35",
    "sg:city":"Garcibuey",
    "sg:orig_category":"Delegados, Agentes De Tr\u00c1nsito, Auxiliares De Transporte Internacional",
    "sg:phone":"+34 923 43 70 73",
    "sg:postcode":"37658",
    "sg:province":"Salamanca",
    "wof:name":"Andres Alba Flores",
    "wof:placetype":"venue"
},
  "geometry": {"coordinates":[-5.994351387,40.5159301758],"type":"Point"}
}