{
  "type": "Feature",
  "properties": {
    "addr:full":"Calle de Rio Eo, 14 Gijon Asturias 33210",
    "addr:housenumber":"14",
    "addr:postcode":"33210",
    "addr:street":"Calle De Rio Eo",
    "iso:country":"ES",
    "sg:address":"Calle de Rio Eo, 14",
    "sg:city":"Gijon",
    "sg:orig_category":"Caf\u00c9s, Bares, Cervecer\u00cdas",
    "sg:phone":"+34 985 38 54 15",
    "sg:postcode":"33210",
    "sg:province":"Asturias",
    "wof:name":"Montes Canteli Eladio",
    "wof:placetype":"venue"
},
  "geometry": {"coordinates":[-5.6667289734,43.5168304443],"type":"Point"}
}