{
  "type": "Feature",
  "properties": {
    "iso:country":"ES",
    "sg:address":"Urb Cane Pujuleta, S/n",
    "sg:city":"Sta Gertrudis Fruitera",
    "sg:orig_category":"Piscinas, Accesorios, Suministros (fabricaci\u00d3n, Al Por Mayor)",
    "sg:phone":"+34 971 19 72 54",
    "sg:postcode":"07814",
    "sg:province":"Islas Baleares",
    "wof:name":"Piscinas Pitiusas S.l.",
    "wof:placetype":"venue"
},
  "geometry": {"coordinates":[1.4285869598,38.9992485046],"type":"Point"}
}