{
  "type": "Feature",
  "properties": {
    "iso:country":"ES",
    "sg:address":"Avda Ordesa, 5",
    "sg:city":"Ainsa",
    "sg:orig_category":"Muebles, Minoristas",
    "sg:phone":"+34 974 50 00 19",
    "sg:postcode":"22330",
    "sg:province":"Huesca",
    "wof:name":"Sabas Sanchez Mauricio",
    "wof:placetype":"venue"
},
  "geometry": {"coordinates":[0.1399099976,42.4146957397],"type":"Point"}
}