{
  "type": "Feature",
  "properties": {
    "iso:country":"ES",
    "sg:address":"Fumarell, 11",
    "sg:city":"S. Antonio Benageber",
    "sg:orig_category":"M\u00c1quinas De Escribir, M\u00c1quinas De Oficina (al Por Menor, Reparaci\u00d3n)",
    "sg:phone":"+34 961 35 00 32",
    "sg:postcode":"46184",
    "sg:province":"Valencia",
    "wof:name":"Dastis Ferrer Alfons",
    "wof:placetype":"venue"
},
  "geometry": {"coordinates":[-0.4905569851,39.5499916077],"type":"Point"}
}