{
  "type": "Feature",
  "properties": {
    "iso:country":"ES",
    "sg:address":"Rbla Hospital, 11",
    "sg:city":"Vic",
    "sg:orig_category":"Cajas De Ahorro",
    "sg:phone":"+34 938 83 23 20",
    "sg:postcode":"08500",
    "sg:province":"Barcelona",
    "sg:website":"www.caixamanlleu.es",
    "wof:name":"Caixa De Manlleu",
    "wof:placetype":"venue"
},
  "geometry": {"coordinates":[2.2526879311,41.9292793274],"type":"Point"}
}