{
  "type": "Feature",
  "properties": {
    "addr:full":"Calle de Huesca, 1 Jaca Huesca 22700",
    "addr:housenumber":"1",
    "addr:postcode":"22700",
    "addr:street":"Calle De Huesca",
    "iso:country":"ES",
    "sg:address":"Calle de Huesca, 1",
    "sg:city":"Jaca",
    "sg:orig_category":"Peluqueros: De Se\u00d1oras",
    "sg:phone":"+34 974 36 30 01",
    "sg:postcode":"22700",
    "sg:province":"Huesca",
    "wof:name":"Ara Martinez Diana Rosa",
    "wof:placetype":"venue"
},
  "geometry": {"coordinates":[-0.5494757295,42.5723762512],"type":"Point"}
}