{
  "type": "Feature",
  "properties": {
    "iso:country":"ES",
    "sg:address":"Avda Londres (de), 1",
    "sg:city":"Andujar",
    "sg:orig_category":"Inmobiliaria (agencias)",
    "sg:phone":"+34 953 50 37 53",
    "sg:postcode":"23740",
    "sg:province":"Ja\u00e9n",
    "wof:name":"Requero Promociones Inmobiliarias S.a.",
    "wof:placetype":"venue"
},
  "geometry": {"coordinates":[-4.057518959,38.0386962891],"type":"Point"}
}