{
  "type": "Feature",
  "properties": {
    "addr:full":"Luga Diseminado El Palmital, 5 Palmital Las Palmas 35458",
    "addr:housenumber":"5",
    "addr:postcode":"35458",
    "addr:street":"Luga Diseminado El Palmital",
    "iso:country":"ES",
    "sg:address":"Luga Diseminado El Palmital, 5",
    "sg:city":"Palmital",
    "sg:orig_category":"Transportes Por V\u00cdas Navegables",
    "sg:phone":"+34 928 55 90 64",
    "sg:postcode":"35458",
    "sg:province":"Las Palmas",
    "wof:name":"Navarro Gonzalez Maria Lourdes",
    "wof:placetype":"venue"
},
  "geometry": {"coordinates":[-15.6107625961,28.1050014496],"type":"Point"}
}