{
  "type": "Feature",
  "properties": {
    "iso:country":"ES",
    "sg:address":"Ctra Alqueria Blanca, Km. 0001,5",
    "sg:city":"Santanyi",
    "sg:orig_category":"Deportes N\u00c1uticos, Acu\u00c1ticos Y Subacu\u00c1ticos: Art\u00cdculos Y Equipo (al Por Menor)",
    "sg:phone":"+34 971 65 43 53",
    "sg:postcode":"07650",
    "sg:province":"Islas Baleares",
    "wof:name":"Amengual Contesti Miguel",
    "wof:placetype":"venue"
},
  "geometry": {"coordinates":[3.2047247887,39.3520202637],"type":"Point"}
}