{
  "type": "Feature",
  "properties": {
    "addr:full":"Calle de Zubieta, 9 Donostia-san Sebastian Guip\u00f9zcoa 20007",
    "addr:housenumber":"9",
    "addr:postcode":"20007",
    "addr:street":"Calle De Zubieta",
    "iso:country":"ES",
    "sg:address":"Calle de Zubieta, 9",
    "sg:city":"Donostia-san Sebastian",
    "sg:orig_category":"M\u00c9dicos: Medicina Manual",
    "sg:phone":"+34 943 45 16 13",
    "sg:postcode":"20007",
    "sg:province":"Guip\u00f9zcoa",
    "wof:name":"Ortega Cuesta Carlos",
    "wof:placetype":"venue"
},
  "geometry": {"coordinates":[-1.9865490198,43.3160858154],"type":"Point"}
}