{
  "type": "Feature",
  "properties": {
    "addr:full":"Plaz Ezkabazabal, 10 Burlada Navarra 31600",
    "addr:housenumber":"10",
    "addr:postcode":"31600",
    "addr:street":"Plaz Ezkabazabal",
    "iso:country":"ES",
    "sg:address":"Plaz Ezkabazabal, 10",
    "sg:city":"Burlada",
    "sg:orig_category":"Ense\u00d1anza, Formaci\u00d3n Profesional: Aprendizaje",
    "sg:phone":"+34 948 35 58 34",
    "sg:postcode":"31600",
    "sg:province":"Navarra",
    "wof:name":"Ayuntamiento De Burlada",
    "wof:placetype":"venue"
},
  "geometry": {"coordinates":[-1.6152689457,42.8264541626],"type":"Point"}
}