{
  "type": "Feature",
  "properties": {
    "iso:country":"ES",
    "sg:address":"El Romeral, 5",
    "sg:city":"Monachil",
    "sg:orig_category":"Prot\u00c9sicos Dentales",
    "sg:phone":"+34 958 30 33 75",
    "sg:postcode":"18193",
    "sg:province":"Granada",
    "wof:name":"Bosch Zafra Francisco Jose",
    "wof:placetype":"venue"
},
  "geometry": {"coordinates":[-3.5582458973,37.1356697083],"type":"Point"}
}