{
  "type": "Feature",
  "properties": {
    "addr:full":"Ctra N-152, S/n Can Gosc Barcelona 08150",
    "addr:housenumber":"s",
    "addr:postcode":"08150",
    "addr:street":"Ctra N-152;/ N",
    "iso:country":"ES",
    "sg:address":"Ctra N-152, S/n",
    "sg:city":"Can Gosc",
    "sg:orig_category":"Filtros Y Elementos Filtradores",
    "sg:phone":"+34 935 65 62 00",
    "sg:postcode":"08150",
    "sg:province":"Barcelona",
    "sg:website":"www.freudenberg.es/telas",
    "wof:name":"Freudenberg Espa\u00d1a S.a. Telas Sin Tejer Sociedad En Comandita",
    "wof:placetype":"venue"
},
  "geometry": {"coordinates":[2.2293000221,41.5678787231],"type":"Point"}
}