{
  "type": "Feature",
  "properties": {
    "addr:full":"Calle de Santa Eugenia, 17 Getxo Vizcaya 48930",
    "addr:housenumber":"17",
    "addr:postcode":"48930",
    "addr:street":"Calle De Santa Eugenia",
    "iso:country":"ES",
    "sg:address":"Calle de Santa Eugenia, 17",
    "sg:city":"Getxo",
    "sg:orig_category":"Peluqueros: De Se\u00d1oras",
    "sg:phone":"+34 944 64 55 17",
    "sg:postcode":"48930",
    "sg:province":"Vizcaya",
    "wof:name":"Laura Garcia Carron",
    "wof:placetype":"venue"
},
  "geometry": {"coordinates":[-3.0087356567,43.3262252808],"type":"Point"}
}