{
  "type": "Feature",
  "properties": {
    "addr:full":"C/ Aurons, 3 Paterna Valencia 46980",
    "addr:housenumber":"3",
    "addr:postcode":"46980",
    "addr:street":"C / Aurons",
    "iso:country":"ES",
    "sg:address":"C/ Aurons, 3",
    "sg:city":"Paterna",
    "sg:orig_category":"Bazares, Art\u00cdculos De Limpieza Y De Cocina (al Por Menor)",
    "sg:phone":"+34 961 36 52 86",
    "sg:postcode":"46980",
    "sg:province":"Valencia",
    "wof:name":"Pinel Manjon Maria",
    "wof:placetype":"venue"
},
  "geometry": {"coordinates":[-0.4395389855,39.500629425],"type":"Point"}
}