{
  "type": "Feature",
  "properties": {
    "addr:full":"Calle de Carlos Haya, 19 Sevilla Sevilla 41011",
    "addr:housenumber":"19",
    "addr:postcode":"41011",
    "addr:street":"Calle De Carlos Haya",
    "iso:country":"ES",
    "sg:address":"Calle de Carlos Haya, 19",
    "sg:city":"Sevilla",
    "sg:orig_category":"Contenedores (mercanc\u00cdas)",
    "sg:phone":"+34 954 45 05 05",
    "sg:postcode":"41011",
    "sg:province":"Sevilla",
    "wof:name":"Soriano Aranda Miguel",
    "wof:placetype":"venue"
},
  "geometry": {"coordinates":[-6.0060329437,37.368522644],"type":"Point"}
}