{
  "type": "Feature",
  "properties": {
    "addr:full":"Carrer de Gomis, 33 Martorell Barcelona 08760",
    "addr:housenumber":"33",
    "addr:postcode":"08760",
    "addr:street":"Carrer De Gomis",
    "iso:country":"ES",
    "sg:address":"Carrer de Gomis, 33",
    "sg:city":"Martorell",
    "sg:orig_category":"M\u00c1rmoles, Granitos Y Piedras Naturales",
    "sg:phone":"+34 937 75 41 09",
    "sg:postcode":"08760",
    "sg:province":"Barcelona",
    "wof:name":"Marmoles Luna S.c.p.",
    "wof:placetype":"venue"
},
  "geometry": {"coordinates":[1.9280400276,41.4779701233],"type":"Point"}
}