{
  "type": "Feature",
  "properties": {
    "iso:country":"ES",
    "sg:address":"Carr Ca S'hereu (cm), De, 14",
    "sg:city":"Cala Millor",
    "sg:orig_category":"Caf\u00c9s, Bares, Cervecer\u00cdas",
    "sg:phone":"+34 971 58 54 16",
    "sg:postcode":"07560",
    "sg:province":"Islas Baleares",
    "wof:name":"Marin Sansegundo Vicente",
    "wof:placetype":"venue"
},
  "geometry": {"coordinates":[3.38478899,39.6016807556],"type":"Point"}
}