{
  "type": "Feature",
  "properties": {
    "iso:country":"ES",
    "sg:address":"Vega Molinos, S/n",
    "sg:city":"Vega Molinos",
    "sg:orig_category":"Transportes De Material De Construcci\u00d3n",
    "sg:phone":"+34 956 72 65 00",
    "sg:postcode":"11620",
    "sg:province":"C\u00e1diz",
    "wof:name":"Derribos Arcenses S.l.",
    "wof:placetype":"venue"
},
  "geometry": {"coordinates":[-5.9306740761,36.7245635986],"type":"Point"}
}