{
  "type": "Feature",
  "properties": {
    "iso:country":"ES",
    "sg:address":"Avda Cristo De Las Cadenas, 12",
    "sg:city":"Oviedo",
    "sg:orig_category":"Comit\u00c9s De Organizaci\u00d3n De Exposiciones, Ferias, Salones",
    "sg:phone":"+34 985 96 61 19",
    "sg:postcode":"33006",
    "sg:province":"Asturias",
    "sg:website":"www.congresosasturias.com",
    "wof:name":"Congresos Principado De Asturias Sl",
    "wof:placetype":"venue"
},
  "geometry": {"coordinates":[-5.8582282066,43.3565330505],"type":"Point"}
}