{
  "type": "Feature",
  "properties": {
    "iso:country":"ES",
    "sg:address":"Calle de Capuchinos, 2",
    "sg:city":"Tudela",
    "sg:orig_category":"Electricidad: Instaladores",
    "sg:phone":"+34 948 82 01 27",
    "sg:postcode":"31500",
    "sg:province":"Navarra",
    "wof:name":"Casado Abadia Jesus Y Martinez Arrondo Jose S.cv.",
    "wof:placetype":"venue"
},
  "geometry": {"coordinates":[-1.6018348932,42.0604782104],"type":"Point"}
}