{
  "type": "Feature",
  "properties": {
    "addr:full":"Calle de Obispo Jaime Perez, 17 Valencia Valencia 46006",
    "addr:housenumber":"17",
    "addr:postcode":"46006",
    "addr:street":"Calle De Obispo Jaime Perez",
    "iso:country":"ES",
    "sg:address":"Calle de Obispo Jaime Perez, 17",
    "sg:city":"Valencia",
    "sg:orig_category":"Droguer\u00cdas (al Por Menor)",
    "sg:phone":"+34 963 73 10 32",
    "sg:postcode":"46006",
    "sg:province":"Valencia",
    "wof:name":"Vilanova Pradas Salvador",
    "wof:placetype":"venue"
},
  "geometry": {"coordinates":[-0.3657880127,39.4587173462],"type":"Point"}
}