{
  "type": "Feature",
  "properties": {
    "addr:full":"Calle de Gines Martin, 23 Huelva Huelva 21002",
    "addr:housenumber":"23",
    "addr:postcode":"21002",
    "addr:street":"Calle De Gines Martin",
    "iso:country":"ES",
    "sg:address":"Calle de Gines Martin, 23",
    "sg:city":"Huelva",
    "sg:orig_category":"Agencias De Trabajo Temporal",
    "sg:phone":"+34 959 26 23 99",
    "sg:postcode":"21002",
    "sg:province":"Huelva",
    "wof:name":"Laborman Trabajo Temporal Ett S.a.",
    "wof:placetype":"venue"
},
  "geometry": {"coordinates":[-6.9523501396,37.2605018616],"type":"Point"}
}