{
  "type": "Feature",
  "properties": {
    "iso:country":"ES",
    "sg:address":"Escuelas Vjas., S/n",
    "sg:city":"Museros",
    "sg:orig_category":"Arquitectos",
    "sg:phone":"+34 961 45 23 11",
    "sg:postcode":"46136",
    "sg:province":"Valencia",
    "wof:name":"Miguel Angel Gimeno Torres 000777818g S.l.n.e",
    "wof:placetype":"venue"
},
  "geometry": {"coordinates":[-0.3403970003,39.5639953613],"type":"Point"}
}