{
  "type": "Feature",
  "properties": {
    "iso:country":"ES",
    "sg:address":"Calle de Tesoro, 18",
    "sg:city":"Madrid",
    "sg:orig_category":"Transportes Por Carretera: Lotes Completos, Mercanc\u00cdas Diversas",
    "sg:phone":"+34 915 22 13 56",
    "sg:postcode":"28004",
    "sg:province":"Madrid",
    "wof:name":"Catem Alimentacion Especializada S.l.",
    "wof:placetype":"venue"
},
  "geometry": {"coordinates":[-3.7055110931,40.4250984192],"type":"Point"}
}