{
  "type": "Feature",
  "properties": {
    "addr:full":"Elosegi Kalea, 11 Lazkao Guip\u00f9zcoa 20210",
    "addr:housenumber":"11",
    "addr:postcode":"20210",
    "addr:street":"Elosegi Kalea;Guipu\u0300Zcoa",
    "iso:country":"ES",
    "sg:address":"Elosegi Kalea, 11",
    "sg:city":"Lazkao",
    "sg:orig_category":"Alimentaci\u00d3n General (al Por Menor)",
    "sg:phone":"+34 943 16 00 00",
    "sg:postcode":"20210",
    "sg:province":"Guip\u00f9zcoa",
    "wof:name":"Aracama Mugica Maria Milagros",
    "wof:placetype":"venue"
},
  "geometry": {"coordinates":[-2.1862959862,43.0348739624],"type":"Point"}
}