{
  "type": "Feature",
  "properties": {
    "addr:full":"Carr Guifre, 759 Badalona Barcelona 08918",
    "addr:housenumber":"759",
    "addr:postcode":"08918",
    "addr:street":"Carr Guifre",
    "iso:country":"ES",
    "sg:address":"Carr Guifre, 759",
    "sg:city":"Badalona",
    "sg:orig_category":"Artes Gr\u00c1ficas, Artes Pl\u00c1sticas: Material Y Suministros (al Por Menor)",
    "sg:phone":"+34 934 60 13 52",
    "sg:postcode":"08918",
    "sg:province":"Barcelona",
    "sg:website":"www.imer-centralsa.com",
    "wof:name":"Imer S. A.",
    "wof:placetype":"venue"
},
  "geometry": {"coordinates":[2.227969408,41.4322547913],"type":"Point"}
}