{
  "type": "Feature",
  "properties": {
    "iso:country":"ES",
    "sg:address":"Avda Concepcion Arenal, 4",
    "sg:city":"Porto De Santa Cruz",
    "sg:orig_category":"Promotores Constructores",
    "sg:phone":"+34 981 61 40 53",
    "sg:postcode":"15179",
    "sg:province":"La Coru\u00f1a",
    "wof:name":"Nobrega Chicharo Jose",
    "wof:placetype":"venue"
},
  "geometry": {"coordinates":[-8.3444890976,43.3433189392],"type":"Point"}
}