{
  "type": "Feature",
  "properties": {
    "addr:full":"Calle de Arrabal, 22 Alegria-dulantzi \u00c1lava 01240",
    "addr:housenumber":"22",
    "addr:postcode":"01240",
    "addr:street":"Calle De Arrabal;A\u0301Lava",
    "iso:country":"ES",
    "sg:address":"Calle de Arrabal, 22",
    "sg:city":"Alegria-dulantzi",
    "sg:orig_category":"Hoteles",
    "sg:phone":"+34 945 42 00 39",
    "sg:postcode":"01240",
    "sg:province":"\u00c1lava",
    "wof:name":"Ruiz Vidan Rosa",
    "wof:placetype":"venue"
},
  "geometry": {"coordinates":[-2.5109465122,42.8408851624],"type":"Point"}
}