{
  "type": "Feature",
  "properties": {
    "addr:full":"Calle de Tirire, S/n Benalua Guadix Granada 18510",
    "addr:housenumber":"s",
    "addr:postcode":"18510",
    "addr:street":"Calle De Tirire;/ N Benalua",
    "iso:country":"ES",
    "sg:address":"Calle de Tirire, S/n",
    "sg:city":"Benalua Guadix",
    "sg:orig_category":"Laboratorios Farmac\u00c9uticos",
    "sg:phone":"+34 958 67 63 74",
    "sg:postcode":"18510",
    "sg:province":"Granada",
    "wof:name":"Aguila Hernandez Laura Del",
    "wof:placetype":"venue"
},
  "geometry": {"coordinates":[-3.1345832348,37.3003959656],"type":"Point"}
}