{
  "type": "Feature",
  "properties": {
    "iso:country":"ES",
    "sg:address":"Avda Real De Madrid, 13",
    "sg:city":"Valencia",
    "sg:orig_category":"Centros De Salud",
    "sg:phone":"+34 963 75 90 37",
    "sg:postcode":"46017",
    "sg:province":"Valencia",
    "wof:name":"Asociacion De Padres De Minusvalidos Psiquicos",
    "wof:placetype":"venue"
},
  "geometry": {"coordinates":[-0.3914526105,39.433555603],"type":"Point"}
}