{
  "type": "Feature",
  "properties": {
    "addr:full":"Campo De La Feria, S/n Peroxa Ourense 32150",
    "addr:housenumber":"s / n",
    "addr:postcode":"32150",
    "addr:street":"Feria",
    "iso:country":"ES",
    "sg:address":"Campo De La Feria, S/n",
    "sg:city":"Peroxa",
    "sg:orig_category":"Reposter\u00cdas",
    "sg:phone":"+34 988 20 66 34",
    "sg:postcode":"32150",
    "sg:province":"Ourense",
    "wof:name":"Seoane Novoa Juan",
    "wof:placetype":"venue"
},
  "geometry": {"coordinates":[-7.7943491936,42.439704895],"type":"Point"}
}