{
  "type": "Feature",
  "properties": {
    "addr:full":"Calle de Serrano, 61 Madrid Madrid 28006",
    "addr:housenumber":"61",
    "addr:postcode":"madrid;28006",
    "addr:street":"Calle De Serrano",
    "iso:country":"ES",
    "sg:address":"Calle de Serrano, 61",
    "sg:city":"Madrid",
    "sg:orig_category":"Gafas (fabricaci\u00d3n)",
    "sg:phone":"+34 915 76 91 58",
    "sg:postcode":"28006",
    "sg:province":"Madrid",
    "sg:website":"www.sunplanet.com",
    "wof:name":"Sun Planet S.a.",
    "wof:placetype":"venue"
},
  "geometry": {"coordinates":[-3.6868038177,40.4321937561],"type":"Point"}
}