{
  "type": "Feature",
  "properties": {
    "addr:full":"Calle de Jose Macias, 4 Madrid Madrid 28047",
    "addr:housenumber":"4",
    "addr:postcode":"28047",
    "addr:street":"Calle De Jose Macias",
    "iso:country":"ES",
    "sg:address":"Calle de Jose Macias, 4",
    "sg:city":"Madrid",
    "sg:orig_category":"Chapister\u00cda",
    "sg:phone":"+34 914 62 95 77",
    "sg:postcode":"28047",
    "sg:province":"Madrid",
    "wof:name":"Talleres Mu\u00f1oz Lopez C.b.",
    "wof:placetype":"venue"
},
  "geometry": {"coordinates":[-3.7456839085,40.3872146606],"type":"Point"}
}