{
  "type": "Feature",
  "properties": {
    "iso:country":"ES",
    "sg:address":"Carrer de Angel (de L'), 8",
    "sg:city":"Tortosa",
    "sg:orig_category":"Librer\u00cdas",
    "sg:phone":"+34 977 44 14 45",
    "sg:postcode":"43500",
    "sg:province":"Tarragona",
    "wof:name":"Domingo Valls Lluis Javier",
    "wof:placetype":"venue"
},
  "geometry": {"coordinates":[0.5215950012,40.8120651245],"type":"Point"}
}