{
  "type": "Feature",
  "properties": {
    "iso:country":"ES",
    "sg:address":"Calle de Picasso, 16",
    "sg:city":"Ubeda",
    "sg:orig_category":"Internados & Ense\u00d1anza Privada",
    "sg:phone":"+34 953 75 04 49",
    "sg:postcode":"23400",
    "sg:province":"Ja\u00e9n",
    "wof:name":"Colegio De La Milagrosa",
    "wof:placetype":"venue"
},
  "geometry": {"coordinates":[-3.3746678829,38.0157356262],"type":"Point"}
}