{
  "type": "Feature",
  "properties": {
    "iso:country":"ES",
    "sg:address":"Avda Portugal, 136",
    "sg:city":"Salamanca",
    "sg:orig_category":"Frutas, Legumbres Frescas Y Tempranas (al Por Menor)",
    "sg:phone":"+34 923 12 37 60",
    "sg:postcode":"37006",
    "sg:province":"Salamanca",
    "wof:name":"Matias Targaguila Jose Eugenio",
    "wof:placetype":"venue"
},
  "geometry": {"coordinates":[-5.6645932198,40.9728775024],"type":"Point"}
}