{
  "type": "Feature",
  "properties": {
    "addr:full":"Avda Salvador De Madariaga, 56 Coru\u00d1a La Coru\u00f1a 15008",
    "addr:housenumber":"56",
    "addr:postcode":"15008",
    "addr:street":"Avda Salvador De Madariaga;Corun\u0303A",
    "iso:country":"ES",
    "sg:address":"Avda Salvador De Madariaga, 56",
    "sg:city":"Coru\u00d1a",
    "sg:orig_category":"Molduras, Junquillos, Listones Y Molduras Perforadas",
    "sg:phone":"+34 981 13 25 76",
    "sg:postcode":"15008",
    "sg:province":"La Coru\u00f1a",
    "wof:name":"Reyes Fari\u00f1as Mercedes",
    "wof:placetype":"venue"
},
  "geometry": {"coordinates":[-8.4069318771,43.3454284668],"type":"Point"}
}