{
  "type": "Feature",
  "properties": {
    "iso:country":"ES",
    "sg:address":"Calle de Estacion, 1",
    "sg:city":"Miranda Ebro",
    "sg:orig_category":"Agencias Y Asesores De Publicidad",
    "sg:phone":"+34 947 34 78 85",
    "sg:postcode":"09200",
    "sg:province":"Burgos",
    "wof:name":"Gestion Interpublicitaria S.l.",
    "wof:placetype":"venue"
},
  "geometry": {"coordinates":[-2.9476790428,42.6856498718],"type":"Point"}
}