{
  "type": "Feature",
  "properties": {
    "iso:country":"ES",
    "sg:address":"Calle de Constancia, 37",
    "sg:city":"Madrid",
    "sg:orig_category":"Asesor\u00cdas Y Estudios Financieros",
    "sg:phone":"+34 914 13 26 30",
    "sg:postcode":"28002",
    "sg:province":"Madrid",
    "wof:name":"Lopez De Vicu\u00f1a Arcauz Fernando",
    "wof:placetype":"venue"
},
  "geometry": {"coordinates":[-3.6722066402,40.4426078796],"type":"Point"}
}