{
  "type": "Feature",
  "properties": {
    "iso:country":"ES",
    "sg:address":"Porti\u00f1o, 6",
    "sg:city":"Sigueiro",
    "sg:orig_category":"Laboratorios Y Trabajos De Fotograf\u00cda, V\u00cddeo Y Cine",
    "sg:phone":"+34 981 68 89 11",
    "sg:postcode":"15888",
    "sg:province":"La Coru\u00f1a",
    "wof:name":"Foto Video Antonio S.l.",
    "wof:placetype":"venue"
},
  "geometry": {"coordinates":[-8.4441976547,42.9674835205],"type":"Point"}
}