{
  "type": "Feature",
  "properties": {
    "iso:country":"ES",
    "sg:address":"Calle de Alfonso Fernandez, 4",
    "sg:city":"Madrid",
    "sg:orig_category":"Art\u00cdculos De Limpieza Y De Cocina (fabricaci\u00d3n, Al Por Mayor)",
    "sg:phone":"+34 915 08 80 77",
    "sg:postcode":"28044",
    "sg:province":"Madrid",
    "wof:name":"Celimp Cemelimp S.a.",
    "wof:placetype":"venue"
},
  "geometry": {"coordinates":[-3.7558355331,40.3680496216],"type":"Point"}
}