{
  "type": "Feature",
  "properties": {
    "addr:full":"Calle de Cervera, 5 Talavera Reina Toledo 45600",
    "addr:housenumber":"5",
    "addr:postcode":"45600",
    "addr:street":"Calle De Cervera",
    "iso:country":"ES",
    "sg:address":"Calle de Cervera, 5",
    "sg:city":"Talavera Reina",
    "sg:orig_category":"Masajistas Kinesiterapeutas",
    "sg:phone":"+34 925 82 57 84",
    "sg:postcode":"45600",
    "sg:province":"Toledo",
    "wof:name":"Bodas Pinero Eugenio",
    "wof:placetype":"venue"
},
  "geometry": {"coordinates":[-4.8324599266,39.9657936096],"type":"Point"}
}