{
  "type": "Feature",
  "properties": {
    "addr:full":"Calle de Jose Gutierrez Abascal, 2 Madrid Madrid 28006",
    "addr:housenumber":"2",
    "addr:postcode":"28006",
    "addr:street":"Calle De Jose Gutierrez Abascal",
    "iso:country":"ES",
    "sg:address":"Calle de Jose Gutierrez Abascal, 2",
    "sg:city":"Madrid",
    "sg:orig_category":"Librer\u00cdas",
    "sg:phone":"+34 914 11 04 70",
    "sg:postcode":"28006",
    "sg:province":"Madrid",
    "sg:website":"www.mncn.cesic.es",
    "wof:name":"Tienda Museo De Ciencias S.l.",
    "wof:placetype":"venue"
},
  "geometry": {"coordinates":[-3.6902143955,40.4408874512],"type":"Point"}
}