{
  "type": "Feature",
  "properties": {
    "iso:country":"ES",
    "sg:address":"Plaz Pilar Redondo, 3",
    "sg:city":"Zafra",
    "sg:orig_category":"Inform\u00c1tica: Material Y Suministros",
    "sg:phone":"+34 924 55 30 04",
    "sg:postcode":"06300",
    "sg:province":"Badajoz",
    "wof:name":"Hernandez Pons Francisco",
    "wof:placetype":"venue"
},
  "geometry": {"coordinates":[-6.417869091,38.426612854],"type":"Point"}
}