{
  "type": "Feature",
  "properties": {
    "addr:full":"Calle de Angel Nieto, 9 Santomera Murcia 30140",
    "addr:housenumber":"9",
    "addr:postcode":"30140",
    "addr:street":"Calle De Angel Nieto",
    "iso:country":"ES",
    "sg:address":"Calle de Angel Nieto, 9",
    "sg:city":"Santomera",
    "sg:orig_category":"Animales (al Por Menor)",
    "sg:phone":"+34 968 86 50 95",
    "sg:postcode":"30140",
    "sg:province":"Murcia",
    "wof:name":"Gonzalez Menarguez Gerardo",
    "wof:placetype":"venue"
},
  "geometry": {"coordinates":[-1.0485409498,38.0584602356],"type":"Point"}
}