{
  "type": "Feature",
  "properties": {
    "addr:full":"Calle de Sanz Raso, 33 Madrid Madrid 28038",
    "addr:housenumber":"33",
    "addr:postcode":"madrid;28038",
    "addr:street":"Calle De Sanz Raso",
    "iso:country":"ES",
    "sg:address":"Calle de Sanz Raso, 33",
    "sg:city":"Madrid",
    "sg:orig_category":"Agencias De Trabajo Temporal",
    "sg:phone":"+34 913 28 73 50",
    "sg:postcode":"28038",
    "sg:province":"Madrid",
    "sg:website":"www.adecco.es",
    "wof:name":"Adecco E.t.t. S.a.",
    "wof:placetype":"venue"
},
  "geometry": {"coordinates":[-3.6602060795,40.3943786621],"type":"Point"}
}