{
  "type": "Feature",
  "properties": {
    "iso:country":"ES",
    "sg:address":"Carrer de Saragossa, 1",
    "sg:city":"Castelldefels",
    "sg:orig_category":"Inmobiliaria (agencias)",
    "sg:phone":"+34 936 36 64 78",
    "sg:postcode":"08860",
    "sg:province":"Barcelona",
    "wof:name":"Carso Grupo Inmobiliario S.a.",
    "wof:placetype":"venue"
},
  "geometry": {"coordinates":[1.980224967,41.2700920105],"type":"Point"}
}