{
  "type": "Feature",
  "properties": {
    "iso:country":"ES",
    "sg:address":"Plaz Cueva Santa, 19",
    "sg:city":"Segorbe",
    "sg:orig_category":"Aguas (distribuci\u00d3n, Servicios)",
    "sg:phone":"+34 964 71 37 05",
    "sg:postcode":"12400",
    "sg:province":"Castell\u00f3n",
    "wof:name":"Sociedad De Fomento Agricola Castellonense S.a.",
    "wof:placetype":"venue"
},
  "geometry": {"coordinates":[-0.4885739982,39.8518714905],"type":"Point"}
}