{
  "type": "Feature",
  "properties": {
    "iso:country":"ES",
    "sg:address":"Carrer de Urgell, 10",
    "sg:city":"Espluga Francoli",
    "sg:orig_category":"Promotores Constructores",
    "sg:phone":"+34 977 87 01 03",
    "sg:postcode":"43440",
    "sg:province":"Tarragona",
    "wof:name":"Teixido Rosell Trinidad",
    "wof:placetype":"venue"
},
  "geometry": {"coordinates":[1.1045479774,41.3942222595],"type":"Point"}
}