{
  "type": "Feature",
  "properties": {
    "addr:full":"Plaz Ayuntamiento, 14 Valencia Valencia 46002",
    "addr:housenumber":"14",
    "addr:postcode":"46002",
    "addr:street":"Valencia",
    "iso:country":"ES",
    "sg:address":"Plaz Ayuntamiento, 14",
    "sg:city":"Valencia",
    "sg:orig_category":"Agencias De Viajes",
    "sg:phone":"+34 963 51 04 77",
    "sg:postcode":"46002",
    "sg:province":"Valencia",
    "sg:website":"www.viajesturia.com",
    "wof:name":"Viajes Turia S. A.",
    "wof:placetype":"venue"
},
  "geometry": {"coordinates":[-0.3766550124,39.4710006714],"type":"Point"}
}