{
  "type": "Feature",
  "properties": {
    "addr:full":"Avda Pio Xii, 7 Talavera Reina Toledo 45600",
    "addr:housenumber":"7",
    "addr:postcode":"45600",
    "addr:street":"Avda Pio Xii",
    "iso:country":"ES",
    "sg:address":"Avda Pio Xii, 7",
    "sg:city":"Talavera Reina",
    "sg:orig_category":"Inmobiliaria (agencias)",
    "sg:phone":"+34 925 82 82 45",
    "sg:postcode":"45600",
    "sg:province":"Toledo",
    "wof:name":"Torres Vega Maria Del Pilar",
    "wof:placetype":"venue"
},
  "geometry": {"coordinates":[-4.8203411102,39.9639053345],"type":"Point"}
}