{
  "type": "Feature",
  "properties": {
    "addr:full":"Calle de Pe\u00d1uelas, 54 Madrid Madrid 28005",
    "addr:housenumber":"54",
    "addr:postcode":"madrid;28005",
    "addr:street":"Calle De Pen\u0303Uelas",
    "iso:country":"ES",
    "sg:address":"Calle de Pe\u00d1uelas, 54",
    "sg:city":"Madrid",
    "sg:orig_category":"Mec\u00c1nico Del Autom\u00d3vil",
    "sg:phone":"+34 914 73 50 85",
    "sg:postcode":"28005",
    "sg:province":"Madrid",
    "wof:name":"Velez Sanchez Francisco",
    "wof:placetype":"venue"
},
  "geometry": {"coordinates":[-3.7016689777,40.3996047974],"type":"Point"}
}