{
  "type": "Feature",
  "properties": {
    "addr:full":"Calle de Manuel Lekuona, 2 Donostia-san Sebastian Guip\u00f9zcoa 20018",
    "addr:housenumber":"2",
    "addr:postcode":"20018",
    "addr:street":"Calle De Manuel Lekuona",
    "iso:country":"ES",
    "sg:address":"Calle de Manuel Lekuona, 2",
    "sg:city":"Donostia-san Sebastian",
    "sg:orig_category":"Ingenier\u00cda, Centros De Estudios (diversos)",
    "sg:phone":"+34 943 21 30 33",
    "sg:postcode":"20018",
    "sg:province":"Guip\u00f9zcoa",
    "wof:name":"Sistemas Y Servicios En Siderurgia, S.l.",
    "wof:placetype":"venue"
},
  "geometry": {"coordinates":[-2.0091910362,43.3106384277],"type":"Point"}
}