{
  "type": "Feature",
  "properties": {
    "iso:country":"ES",
    "sg:address":"Carrer de Garbi, 144",
    "sg:city":"Pineda Mar",
    "sg:classifiers":[
        {
            "category":"Casinos & Gambling",
            "type":"Entertainment"
        }
    ],
    "sg:phone":"+34 937 67 17 62",
    "sg:postcode":"08397",
    "sg:province":"Barcelona",
    "sg:tags":[
        "locale",
        "de",
        "juego"
    ],
    "wof:name":"Planeta Magic Pineda S.c.p.",
    "wof:placetype":"venue"
},
  "geometry": {"coordinates":[2.6739709377,41.6236953735],"type":"Point"}
}