{
  "type": "Feature",
  "properties": {
    "addr:full":"Calle de Portalada (la), 2 Logro\u00f1o La Rioja 26006",
    "addr:housenumber":"2",
    "addr:postcode":"26006",
    "addr:street":"Calle De Portalada La;Rioja",
    "iso:country":"ES",
    "sg:address":"Calle de Portalada (la), 2",
    "sg:city":"Logro\u00f1o",
    "sg:orig_category":"Contenedores (mercanc\u00cdas)",
    "sg:phone":"+34 941 44 53 87",
    "sg:postcode":"26006",
    "sg:province":"La Rioja",
    "wof:name":"Vehiculos Trigar S.l.",
    "wof:placetype":"venue"
},
  "geometry": {"coordinates":[-2.4137508869,42.457862854],"type":"Point"}
}