{
  "type": "Feature",
  "properties": {
    "addr:full":"Calle de Sol, 51 Plasencia C\u00e1ceres 10600",
    "addr:housenumber":"51",
    "addr:postcode":"10600",
    "addr:street":"Calle De Sol;Ca\u0301Ceres",
    "iso:country":"ES",
    "sg:address":"Calle de Sol, 51",
    "sg:city":"Plasencia",
    "sg:orig_category":"Ense\u00d1anza Variada",
    "sg:phone":"+34 927 42 54 60",
    "sg:postcode":"10600",
    "sg:province":"C\u00e1ceres",
    "wof:name":"Moriano Matias Raul",
    "wof:placetype":"venue"
},
  "geometry": {"coordinates":[-6.0869288445,40.0306396484],"type":"Point"}
}