{
  "type": "Feature",
  "properties": {
    "addr:full":"Ptge Pere Serra, 8 Sabadell Barcelona 08205",
    "addr:housenumber":"8",
    "addr:postcode":"08205",
    "addr:street":"Ptge Pere Serra",
    "iso:country":"ES",
    "sg:address":"Ptge Pere Serra, 8",
    "sg:city":"Sabadell",
    "sg:orig_category":"Confecci\u00d3n De Trajes Para Se\u00d1oras",
    "sg:phone":"+34 937 25 19 44",
    "sg:postcode":"08205",
    "sg:province":"Barcelona",
    "wof:name":"Gorina Y Sauquet S. A.",
    "wof:placetype":"venue"
},
  "geometry": {"coordinates":[2.0951859951,41.5408287048],"type":"Point"}
}