{
  "type": "Feature",
  "properties": {
    "iso:country":"ES",
    "sg:address":"Calle de Cristobal Colon, 9",
    "sg:city":"Burgos",
    "sg:orig_category":"Mercer\u00cda, Lencer\u00cda (al Por Menor)",
    "sg:phone":"+34 947 21 77 79",
    "sg:postcode":"09005",
    "sg:province":"Burgos",
    "wof:name":"Merceria Pilar",
    "wof:placetype":"venue"
},
  "geometry": {"coordinates":[-3.6950297356,42.3483123779],"type":"Point"}
}