{
  "type": "Feature",
  "properties": {
    "addr:full":"Calle de Mayor, 11 Espinosa Henares Guadalajara 19292",
    "addr:housenumber":"11",
    "addr:postcode":"19292",
    "addr:street":"Calle De Mayor",
    "iso:country":"ES",
    "sg:address":"Calle de Mayor, 11",
    "sg:city":"Espinosa Henares",
    "sg:orig_category":"Iglesia Cat\u00d3lica",
    "sg:phone":"+34 949 85 88 12",
    "sg:postcode":"19292",
    "sg:province":"Guadalajara",
    "wof:name":"Obispado De Siguenza-guadalajara",
    "wof:placetype":"venue"
},
  "geometry": {"coordinates":[-3.0717039108,40.9046096802],"type":"Point"}
}