{
  "type": "Feature",
  "properties": {
    "addr:full":"Calle de Juan De Quesada, 31 Arrecife Las Palmas 35500",
    "addr:housenumber":"31",
    "addr:postcode":"35500",
    "addr:street":"Calle De Juan De Quesada",
    "iso:country":"ES",
    "sg:address":"Calle de Juan De Quesada, 31",
    "sg:city":"Arrecife",
    "sg:orig_category":"Florister\u00cdas",
    "sg:phone":"+34 928 81 48 39",
    "sg:postcode":"35500",
    "sg:province":"Las Palmas",
    "wof:name":"Cartelanz S.l.",
    "wof:placetype":"venue"
},
  "geometry": {"coordinates":[-13.5431833267,28.9628505707],"type":"Point"}
}