{
  "type": "Feature",
  "properties": {
    "addr:full":"Calle de Moreras, S/n Carcelen Albacete 02153",
    "addr:housenumber":"s / n",
    "addr:postcode":"02153",
    "addr:street":"Calle De Moreras",
    "iso:country":"ES",
    "sg:address":"Calle de Moreras, S/n",
    "sg:city":"Carcelen",
    "sg:classifiers":[
        {
            "category":"Manufacturing",
            "subcategory":"Building Materials",
            "type":"Manufacturing & Wholesale Goods"
        }
    ],
    "sg:phone":"+34 967 40 32 79",
    "sg:postcode":"02153",
    "sg:province":"Albacete",
    "sg:tags":[
        "de",
        "industrial",
        "alquiler"
    ],
    "wof:name":"Los Martos Carcelen C.b.",
    "wof:placetype":"venue"
},
  "geometry": {"coordinates":[-1.3081840277,39.1028633118],"type":"Point"}
}