{
  "type": "Feature",
  "properties": {
    "addr:full":"Calle de San Juan Bosco, 3 Pozoblanco C\u00f3rdoba 14400",
    "addr:housenumber":"3",
    "addr:postcode":"14400",
    "addr:street":"Calle De San Juan Bosco",
    "iso:country":"ES",
    "sg:address":"Calle de San Juan Bosco, 3",
    "sg:city":"Pozoblanco",
    "sg:orig_category":"Carnicer\u00cdas, Carnicer\u00cdas",
    "sg:phone":"+34 957 13 09 75",
    "sg:postcode":"14400",
    "sg:province":"C\u00f3rdoba",
    "wof:name":"Garcia Garcia Pedro",
    "wof:placetype":"venue"
},
  "geometry": {"coordinates":[-4.8472771645,38.3792266846],"type":"Point"}
}