{
  "type": "Feature",
  "properties": {
    "iso:country":"ES",
    "sg:address":"Calle de Alhambra, 5",
    "sg:city":"Cartagena",
    "sg:orig_category":"Supermercados Y Hipermercados",
    "sg:phone":"+34 968 31 46 64",
    "sg:postcode":"30204",
    "sg:province":"Murcia",
    "wof:name":"Urama Pastori Jose Diego",
    "wof:placetype":"venue"
},
  "geometry": {"coordinates":[-0.9873110056,37.6122932434],"type":"Point"}
}