{
  "type": "Feature",
  "properties": {
    "iso:country":"ES",
    "sg:address":"Ctra Tordesillas, 3",
    "sg:city":"Toro",
    "sg:orig_category":"Construcciones Met\u00c1licas",
    "sg:phone":"+34 980 69 26 69",
    "sg:postcode":"49800",
    "sg:province":"Zamora",
    "wof:name":"Industrias Ernumi S.l",
    "wof:placetype":"venue"
},
  "geometry": {"coordinates":[-5.3850340843,41.5232315063],"type":"Point"}
}