{
  "type": "Feature",
  "properties": {
    "iso:country":"ES",
    "sg:address":"Calle de Tarragona, 14",
    "sg:city":"Leganes",
    "sg:orig_category":"Peluquer\u00cdas, Peluquer\u00cda Mixta",
    "sg:phone":"+34 916 93 55 63",
    "sg:postcode":"28914",
    "sg:province":"Madrid",
    "wof:name":"Moreno Feito Sonia Maria",
    "wof:placetype":"venue"
},
  "geometry": {"coordinates":[-3.7553079128,40.3210449219],"type":"Point"}
}