{
  "type": "Feature",
  "properties": {
    "addr:full":"Calle de La Del Manojo De Rosas, 44 Madrid Madrid 28041",
    "addr:housenumber":"44",
    "addr:postcode":"madrid;28041",
    "addr:street":"Calle De La Del Manojo De Rosas",
    "iso:country":"ES",
    "sg:address":"Calle de La Del Manojo De Rosas, 44",
    "sg:city":"Madrid",
    "sg:orig_category":"Estilistas Y Estudios De Estilo De Corte Y Confecci\u00d3n",
    "sg:phone":"+34 913 17 34 46",
    "sg:postcode":"28041",
    "sg:province":"Madrid",
    "wof:name":"Cantandor Diaz Jose",
    "wof:placetype":"venue"
},
  "geometry": {"coordinates":[-3.6974520683,40.3584022522],"type":"Point"}
}