{
  "type": "Feature",
  "properties": {
    "iso:country":"ES",
    "sg:address":"Carrer de Santa Anna, 86",
    "sg:city":"Vendrell",
    "sg:orig_category":"Carnicer\u00cdas, Carnicer\u00cdas",
    "sg:phone":"+34 977 66 04 40",
    "sg:postcode":"43700",
    "sg:province":"Tarragona",
    "wof:name":"Rovira Planas Jose",
    "wof:placetype":"venue"
},
  "geometry": {"coordinates":[1.5331319571,41.2242279053],"type":"Point"}
}