{
  "type": "Feature",
  "properties": {
    "addr:full":"Calle de Arrieros (de Los), 7 Barco De Avila \u00c1vila 05600",
    "addr:housenumber":"7",
    "addr:postcode":"05600",
    "addr:street":"Calle De Arrieros De Los;A\u0301Vila",
    "iso:country":"ES",
    "sg:address":"Calle de Arrieros (de Los), 7",
    "sg:city":"Barco De Avila",
    "sg:orig_category":"Cerrajer\u00cda, Ferrallista",
    "sg:phone":"+34 920 34 05 02",
    "sg:postcode":"05600",
    "sg:province":"\u00c1vila",
    "wof:name":"Pascual Flores Jose Antonio",
    "wof:placetype":"venue"
},
  "geometry": {"coordinates":[-5.5254631042,40.3579368591],"type":"Point"}
}