{
  "type": "Feature",
  "properties": {
    "iso:country":"ES",
    "sg:address":"Barr Campas Las, S/n",
    "sg:city":"Grandas",
    "sg:orig_category":"Delegados, Agentes De Tr\u00c1nsito, Auxiliares De Transporte Internacional",
    "sg:phone":"+34 985 62 73 06",
    "sg:postcode":"33730",
    "sg:province":"Asturias",
    "wof:name":"Transportes Diaz Ranca\u00f1o S.l.",
    "wof:placetype":"venue"
},
  "geometry": {"coordinates":[-6.8758378029,43.2181434631],"type":"Point"}
}