{
  "type": "Feature",
  "properties": {
    "iso:country":"ES",
    "sg:address":"Sant Andreu, 64",
    "sg:city":"Porqueres",
    "sg:orig_category":"Agencias Y Agentes Comerciales, Representantes",
    "sg:phone":"+34 972 57 54 34",
    "sg:postcode":"17834",
    "sg:province":"Girona",
    "wof:name":"Arbues Pin Josep Maria",
    "wof:placetype":"venue"
},
  "geometry": {"coordinates":[2.7819714546,42.1065597534],"type":"Point"}
}