{
  "type": "Feature",
  "properties": {
    "iso:country":"ES",
    "sg:address":"Nogal, S/n",
    "sg:city":"Ciempozuelos",
    "sg:orig_category":"Instalaci\u00d3n, Preparaci\u00d3n De Exposiciones, Ferias, Salones",
    "sg:phone":"+34 918 01 53 56",
    "sg:postcode":"28350",
    "sg:province":"Madrid",
    "wof:name":"Argeron S.c.",
    "wof:placetype":"venue"
},
  "geometry": {"coordinates":[-3.6312365532,40.1671295166],"type":"Point"}
}