{
  "type": "Feature",
  "properties": {
    "addr:full":"Calle de Gustavo Adolfo Becquer, 17 Arme\u00d1ime Santa Cruz De Tenerife 38678",
    "addr:housenumber":"17",
    "addr:postcode":"38678",
    "addr:street":"Calle De Gustavo Adolfo Becquer",
    "iso:country":"ES",
    "sg:address":"Calle de Gustavo Adolfo Becquer, 17",
    "sg:city":"Arme\u00d1ime",
    "sg:orig_category":"Tapicer\u00cdas",
    "sg:phone":"+34 922 74 10 51",
    "sg:postcode":"38678",
    "sg:province":"Santa Cruz De Tenerife",
    "wof:name":"Duran Martin Jose Juan",
    "wof:placetype":"venue"
},
  "geometry": {"coordinates":[-16.7568416595,28.1286678314],"type":"Point"}
}