{
  "type": "Feature",
  "properties": {
    "iso:country":"ES",
    "sg:address":"Avda Madrid (de), 12",
    "sg:city":"Granada",
    "sg:orig_category":"Fabricaci\u00d3n De Juegos Y Juguetes",
    "sg:phone":"+34 958 27 26 07",
    "sg:postcode":"18012",
    "sg:province":"Granada",
    "wof:name":"Net Cyber S.l",
    "wof:placetype":"venue"
},
  "geometry": {"coordinates":[-3.6037390232,37.1855735779],"type":"Point"}
}