{
  "type": "Feature",
  "properties": {
    "addr:full":"Calle de Oropendola, 56 Salamanca Salamanca 37006",
    "addr:housenumber":"56",
    "addr:postcode":"37006",
    "addr:street":"Calle De Oropendola",
    "iso:country":"ES",
    "sg:address":"Calle de Oropendola, 56",
    "sg:city":"Salamanca",
    "sg:orig_category":"Promotores Constructores",
    "sg:phone":"+34 923 25 86 78",
    "sg:postcode":"37006",
    "sg:province":"Salamanca",
    "wof:name":"Calle Oropendola 54 C.p.",
    "wof:placetype":"venue"
},
  "geometry": {"coordinates":[-5.6720199585,40.979927063],"type":"Point"}
}