{
  "type": "Feature",
  "properties": {
    "addr:full":"C/ Illes Canaries, 27 Paterna Valencia 46988",
    "addr:housenumber":"27",
    "addr:postcode":"46988",
    "addr:street":"C / Illes Canaries",
    "iso:country":"ES",
    "sg:address":"C/ Illes Canaries, 27",
    "sg:city":"Paterna",
    "sg:orig_category":"Cerrajer\u00cda, Ferrallista",
    "sg:phone":"+34 961 32 53 95",
    "sg:postcode":"46988",
    "sg:province":"Valencia",
    "wof:name":"Cerrajera Valenciana S.a.",
    "wof:placetype":"venue"
},
  "geometry": {"coordinates":[-0.4395389855,39.500629425],"type":"Point"}
}