{
  "type": "Feature",
  "properties": {
    "addr:full":"Calle de Gaudi, 52 Estepona M\u00e1laga 29680",
    "addr:housenumber":"52",
    "addr:postcode":"29680",
    "addr:street":"Calle De Gaudi",
    "iso:country":"ES",
    "sg:address":"Calle de Gaudi, 52",
    "sg:city":"Estepona",
    "sg:orig_category":"Chapister\u00cda",
    "sg:phone":"+34 952 80 21 02",
    "sg:postcode":"29680",
    "sg:province":"M\u00e1laga",
    "wof:name":"Talleres Arcoiris S.l.",
    "wof:placetype":"venue"
},
  "geometry": {"coordinates":[-5.1675901413,36.4276237488],"type":"Point"}
}