{
  "type": "Feature",
  "properties": {
    "addr:full":"Plaz Aransotegi Enparantza, 3 Zabaloetxe Vizcaya 48180",
    "addr:housenumber":"3",
    "addr:postcode":"48180",
    "addr:street":"Plaz Aransotegi Enparantza",
    "iso:country":"ES",
    "sg:address":"Plaz Aransotegi Enparantza, 3",
    "sg:city":"Zabaloetxe",
    "sg:orig_category":"Asociaciones, Organismos Culturales Y Socioeducativos",
    "sg:phone":"+34 944 53 00 01",
    "sg:postcode":"48180",
    "sg:province":"Vizcaya",
    "wof:name":"Asociacion De Jubilados Y Pensionistas Gure Etxea De Loiu",
    "wof:placetype":"venue"
},
  "geometry": {"coordinates":[-2.9396224022,43.314163208],"type":"Point"}
}