{
  "type": "Feature",
  "properties": {
    "addr:full":"Ctra Aguilas (de), 142 Campillo Murcia 30813",
    "addr:housenumber":"142",
    "addr:postcode":"30813",
    "addr:street":"Ctra Aguilas De",
    "iso:country":"ES",
    "sg:address":"Ctra Aguilas (de), 142",
    "sg:city":"Campillo",
    "sg:orig_category":"Camiones",
    "sg:phone":"+34 968 46 77 63",
    "sg:postcode":"30813",
    "sg:province":"Murcia",
    "wof:name":"Hermanos Heredia Y Mulero S.l.",
    "wof:placetype":"venue"
},
  "geometry": {"coordinates":[-1.7215889692,37.491394043],"type":"Point"}
}