{
  "type": "Feature",
  "properties": {
    "addr:full":"Psaj Molinillo, 3 Ubeda Ja\u00e9n 23400",
    "addr:housenumber":"3",
    "addr:postcode":"23400",
    "addr:street":"Molinillo;Jae\u0301N",
    "iso:country":"ES",
    "sg:address":"Psaj Molinillo, 3",
    "sg:city":"Ubeda",
    "sg:orig_category":"Centros Empresariales",
    "sg:phone":"+34 953 75 81 91",
    "sg:postcode":"23400",
    "sg:province":"Ja\u00e9n",
    "wof:name":"Asociacion De Defensa Sanitaria De Ganado La Loma Sierra Magina Norte Condado",
    "wof:placetype":"venue"
},
  "geometry": {"coordinates":[-3.3590445518,37.994178772],"type":"Point"}
}