{
  "type": "Feature",
  "properties": {
    "iso:country":"ES",
    "sg:address":"Carrer de Barcelona (de), 59",
    "sg:city":"Salou",
    "sg:orig_category":"Juegos Y Juguetes (al Por Menor)",
    "sg:phone":"+34 977 35 03 64",
    "sg:postcode":"43840",
    "sg:province":"Tarragona",
    "wof:name":"Chacon Vilanova Magatzems S.l.",
    "wof:placetype":"venue"
},
  "geometry": {"coordinates":[1.1317709684,41.0821609497],"type":"Point"}
}