{
  "type": "Feature",
  "properties": {
    "iso:country":"ES",
    "sg:address":"Ctra Pinilla, Km. 0001,2",
    "sg:city":"Mazarron",
    "sg:orig_category":"Transportes Internacionales",
    "sg:phone":"+34 968 59 27 24",
    "sg:postcode":"30870",
    "sg:province":"Murcia",
    "wof:name":"Cervera Rojo Pedro Clemente",
    "wof:placetype":"venue"
},
  "geometry": {"coordinates":[-1.31378901,37.598865509],"type":"Point"}
}