{
  "type": "Feature",
  "properties": {
    "addr:full":"Calle de Fuenlabrada, 13 Alcorcon Madrid 28921",
    "addr:housenumber":"13",
    "addr:postcode":"28921",
    "addr:street":"Calle De Fuenlabrada",
    "iso:country":"ES",
    "sg:address":"Calle de Fuenlabrada, 13",
    "sg:city":"Alcorcon",
    "sg:orig_category":"Reposter\u00cdas",
    "sg:phone":"+34 916 43 79 70",
    "sg:postcode":"28921",
    "sg:province":"Madrid",
    "wof:name":"Sotomayor Gomez Brigida",
    "wof:placetype":"venue"
},
  "geometry": {"coordinates":[-3.8267071247,40.3453903198],"type":"Point"}
}