{
  "type": "Feature",
  "properties": {
    "iso:country":"ES",
    "sg:address":"Avda General, 21",
    "sg:city":"Madrid",
    "sg:orig_category":"Perfumer\u00cda (al Por Menor)",
    "sg:phone":"+34 917 47 84 27",
    "sg:postcode":"28042",
    "sg:province":"Madrid",
    "wof:name":"Arranz Martinez Emilio",
    "wof:placetype":"venue"
},
  "geometry": {"coordinates":[-3.5785517693,40.4727134705],"type":"Point"}
}