{
  "type": "Feature",
  "properties": {
    "iso:country":"ES",
    "sg:address":"Rua Doutor Teixeiro (do), 9",
    "sg:city":"Santiago De Compostela",
    "sg:orig_category":"M\u00c9dicos: An\u00c1lisis Cl\u00cdnicos",
    "sg:phone":"+34 981 56 25 48",
    "sg:postcode":"15701",
    "sg:province":"La Coru\u00f1a",
    "wof:name":"Salceda Diaz-munio Fernando",
    "wof:placetype":"venue"
},
  "geometry": {"coordinates":[-8.5448169708,42.8754577637],"type":"Point"}
}