{
  "type": "Feature",
  "properties": {
    "iso:country":"ES",
    "sg:address":"Calle de Estacion, 2",
    "sg:city":"Alagon",
    "sg:orig_category":"Agencias Y Agentes Comerciales, Representantes",
    "sg:phone":"+34 976 61 02 44",
    "sg:postcode":"50630",
    "sg:province":"Zaragoza",
    "wof:name":"Martinez Esteban Alberto",
    "wof:placetype":"venue"
},
  "geometry": {"coordinates":[-1.1172549725,41.7711715698],"type":"Point"}
}