{
  "type": "Feature",
  "properties": {
    "addr:full":"Gacela, 2 Algar Murcia 30366",
    "addr:housenumber":"2",
    "addr:postcode":"30366",
    "addr:street":"Gacela",
    "iso:country":"ES",
    "sg:address":"Gacela, 2",
    "sg:city":"Algar",
    "sg:orig_category":"Reposter\u00cdas",
    "sg:phone":"+34 968 13 63 24",
    "sg:postcode":"30366",
    "sg:province":"Murcia",
    "wof:name":"Panaderia Y Bolleria Adrymar S.l.l",
    "wof:placetype":"venue"
},
  "geometry": {"coordinates":[-0.8688459992,37.6484107971],"type":"Point"}
}