{
  "type": "Feature",
  "properties": {
    "addr:full":"Calle de Conde Aranda, 130 Zaragoza Zaragoza 50003",
    "addr:housenumber":"130",
    "addr:postcode":"50003",
    "addr:street":"Calle De Conde Aranda",
    "iso:country":"ES",
    "sg:address":"Calle de Conde Aranda, 130",
    "sg:city":"Zaragoza",
    "sg:orig_category":"Bancos",
    "sg:phone":"+34 976 28 12 27",
    "sg:postcode":"50003",
    "sg:province":"Zaragoza",
    "sg:website":"www.bancozaragozano.es",
    "wof:name":"Barclays Bank S.a.e.",
    "wof:placetype":"venue"
},
  "geometry": {"coordinates":[-0.8922920227,41.656124115],"type":"Point"}
}