{
  "type": "Feature",
  "properties": {
    "addr:full":"Calle de Amadeo De Saboya, 24 Valencia Valencia 46010",
    "addr:housenumber":"24",
    "addr:postcode":"46010",
    "addr:street":"Calle De Amadeo De Saboya",
    "iso:country":"ES",
    "sg:address":"Calle de Amadeo De Saboya, 24",
    "sg:city":"Valencia",
    "sg:orig_category":"Cajas De Ahorro",
    "sg:phone":"+34 963 62 45 53",
    "sg:postcode":"46010",
    "sg:province":"Valencia",
    "sg:website":"www.bancaja.es",
    "wof:name":"Caja De Ahorros De Valencia Castellon Y Alicante",
    "wof:placetype":"venue"
},
  "geometry": {"coordinates":[-0.3593961895,39.4729194641],"type":"Point"}
}