{
  "type": "Feature",
  "properties": {
    "iso:country":"ES",
    "sg:address":"Calle de Obieta, 29",
    "sg:city":"Altzaga",
    "sg:orig_category":"Quincaller\u00cda (al Por Menor)",
    "sg:phone":"+34 944 67 00 99",
    "sg:postcode":"48950",
    "sg:province":"Vizcaya",
    "wof:name":"Jose Ignacio Y Agustin Prada Miguel C.b.",
    "wof:placetype":"venue"
},
  "geometry": {"coordinates":[-2.9729468822,43.3039360046],"type":"Point"}
}