{
  "type": "Feature",
  "properties": {
    "iso:country":"ES",
    "sg:address":"Pl Emili Sala, 1",
    "sg:city":"Alcoi",
    "sg:orig_category":"Goma: Materias Primas (producci\u00d3n, Distribuci\u00d3n)",
    "sg:phone":"+34 965 54 09 27",
    "sg:postcode":"03801",
    "sg:province":"Alicante",
    "sg:website":"www.carbongen.net",
    "wof:name":"Carbongen Sa",
    "wof:placetype":"venue"
},
  "geometry": {"coordinates":[-0.4769090116,38.6973648071],"type":"Point"}
}