{
  "type": "Feature",
  "properties": {
    "iso:country":"ES",
    "sg:address":"C/ Sant Joan, 15",
    "sg:city":"Tarrega",
    "sg:orig_category":"Loter\u00cda Y T\u00d3mbola",
    "sg:phone":"+34 973 31 04 25",
    "sg:postcode":"25300",
    "sg:province":"Lleida",
    "wof:name":"Carrasquer Vidal Alba",
    "wof:placetype":"venue"
},
  "geometry": {"coordinates":[1.13854599,41.6478691101],"type":"Point"}
}