{
  "type": "Feature",
  "properties": {
    "addr:full":"Calle de Garcia Morato, 21 Valladolid Valladolid 47007",
    "addr:housenumber":"21",
    "addr:postcode":"47007",
    "addr:street":"Calle De Garcia Morato",
    "iso:country":"ES",
    "sg:address":"Calle de Garcia Morato, 21",
    "sg:city":"Valladolid",
    "sg:orig_category":"Peluquer\u00cdas, Peluquer\u00cda Mixta",
    "sg:phone":"+34 983 47 64 32",
    "sg:postcode":"47007",
    "sg:province":"Valladolid",
    "wof:name":"Lerma Velasco Cristina",
    "wof:placetype":"venue"
},
  "geometry": {"coordinates":[-4.7328424454,41.6429634094],"type":"Point"}
}