{
  "type": "Feature",
  "properties": {
    "addr:full":"Pg Gran Passeig Ronda, 107 Lleida Lleida 25006",
    "addr:housenumber":"107",
    "addr:postcode":"25006",
    "addr:street":"Pg Gran Passeig Ronda",
    "iso:country":"ES",
    "sg:address":"Pg Gran Passeig Ronda, 107",
    "sg:city":"Lleida",
    "sg:orig_category":"Escuelas De Maternidad P\u00dablicas",
    "sg:phone":"+34 973 23 45 51",
    "sg:postcode":"25006",
    "sg:province":"Lleida",
    "wof:name":"Llar Doinfants Peterpam S.c.l",
    "wof:placetype":"venue"
},
  "geometry": {"coordinates":[0.6158609986,41.620300293],"type":"Point"}
}