{
  "type": "Feature",
  "properties": {
    "iso:country":"ES",
    "sg:address":"Avda Playas (las), 53",
    "sg:city":"Puerto Del Carmen",
    "sg:orig_category":"Ropa Para Se\u00d1oras Y Caballeros (al Por Menor)",
    "sg:phone":"+34 928 51 11 07",
    "sg:postcode":"35510",
    "sg:province":"Las Palmas",
    "wof:name":"Novedades Vashi S.l.",
    "wof:placetype":"venue"
},
  "geometry": {"coordinates":[-13.6543092728,28.9192905426],"type":"Point"}
}