{
  "type": "Feature",
  "properties": {
    "iso:country":"ES",
    "sg:address":"Calle de Placido Martinez, 7",
    "sg:city":"Nava",
    "sg:orig_category":"Material Y Suministros Para Veterinarios",
    "sg:phone":"+34 985 71 61 05",
    "sg:postcode":"33520",
    "sg:province":"Asturias",
    "wof:name":"Maria Marta Suarez Zapatero S.l.",
    "wof:placetype":"venue"
},
  "geometry": {"coordinates":[-5.5089564323,43.3581504822],"type":"Point"}
}