{
  "type": "Feature",
  "properties": {
    "iso:country":"ES",
    "sg:address":"Cmno Gojar, 5",
    "sg:city":"Zubia",
    "sg:orig_category":"Frutas, Legumbres Frescas Y Tempranas (al Por Menor)",
    "sg:phone":"+34 958 89 12 09",
    "sg:postcode":"18140",
    "sg:province":"Granada",
    "wof:name":"Ruiz Martin Diego",
    "wof:placetype":"venue"
},
  "geometry": {"coordinates":[-3.5853440762,37.1218338013],"type":"Point"}
}