{
  "type": "Feature",
  "properties": {
    "iso:country":"ES",
    "sg:address":"Calle de Santa Isabel, 22",
    "sg:city":"Alcazares",
    "sg:orig_category":"Papeler\u00cdas, Librer\u00cdas",
    "sg:phone":"+34 968 17 12 73",
    "sg:postcode":"30710",
    "sg:province":"Murcia",
    "wof:name":"Saura Olmos Caridad",
    "wof:placetype":"venue"
},
  "geometry": {"coordinates":[-0.8500279784,37.7394714355],"type":"Point"}
}