{
  "type": "Feature",
  "properties": {
    "iso:country":"ES",
    "sg:address":"Finca De Los Canedos, S/n",
    "sg:city":"Simancas",
    "sg:orig_category":"Abogados",
    "sg:phone":"+34 983 59 13 30",
    "sg:postcode":"47130",
    "sg:province":"Valladolid",
    "wof:name":"Recio Cordova Gonzalo",
    "wof:placetype":"venue"
},
  "geometry": {"coordinates":[-4.8235812187,41.5907974243],"type":"Point"}
}