{
  "type": "Feature",
  "properties": {
    "addr:full":"Plaz Mayor, 10 Elda Alicante 03600",
    "addr:housenumber":"10",
    "addr:postcode":"03600",
    "addr:street":"Plaz Mayor",
    "iso:country":"ES",
    "sg:address":"Plaz Mayor, 10",
    "sg:city":"Elda",
    "sg:orig_category":"Caf\u00c9s, Bares, Cervecer\u00cdas",
    "sg:phone":"+34 965 39 33 12",
    "sg:postcode":"03600",
    "sg:province":"Alicante",
    "wof:name":"Cafetria Sayago S.l.u",
    "wof:placetype":"venue"
},
  "geometry": {"coordinates":[-0.7941759825,38.4786491394],"type":"Point"}
}