{
  "type": "Feature",
  "properties": {
    "iso:country":"ES",
    "sg:address":"Calle de Ubeda, 7",
    "sg:city":"Martos",
    "sg:orig_category":"Electricidad (montaje, Ensamblaje De Componentes)",
    "sg:phone":"+34 953 55 28 21",
    "sg:postcode":"23600",
    "sg:province":"Ja\u00e9n",
    "wof:name":"Ramirez Garcia Francisco",
    "wof:placetype":"venue"
},
  "geometry": {"coordinates":[-3.9689340591,37.7091827393],"type":"Point"}
}