{
  "type": "Feature",
  "properties": {
    "addr:full":"Rua Real, 138 Ferrol La Coru\u00f1a 15402",
    "addr:housenumber":"138",
    "addr:postcode":"15402",
    "addr:street":"Rua Real;La Corun\u0303A",
    "iso:country":"ES",
    "sg:address":"Rua Real, 138",
    "sg:city":"Ferrol",
    "sg:orig_category":"Ropa Para Caballeros (al Por Menor)",
    "sg:phone":"+34 981 35 67 11",
    "sg:postcode":"15402",
    "sg:province":"La Coru\u00f1a",
    "sg:website":"www.spf.com",
    "wof:name":"Cortefiel S.a.",
    "wof:placetype":"venue"
},
  "geometry": {"coordinates":[-8.236328125,43.4826965332],"type":"Point"}
}