{
  "type": "Feature",
  "properties": {
    "iso:country":"ES",
    "sg:address":"Calle de Rosas, 10",
    "sg:city":"Coru\u00d1a",
    "sg:orig_category":"Transportes Por V\u00cdas Navegables",
    "sg:phone":"+34 981 28 49 02",
    "sg:postcode":"15008",
    "sg:province":"La Coru\u00f1a",
    "wof:name":"Penas Folgar Jose Evaristo",
    "wof:placetype":"venue"
},
  "geometry": {"coordinates":[-8.4512443542,43.3434753418],"type":"Point"}
}