{
  "type": "Feature",
  "properties": {
    "iso:country":"ES",
    "sg:address":"Calle de Musico Gines, 9",
    "sg:city":"Valencia",
    "sg:orig_category":"Promotores Constructores",
    "sg:phone":"+34 963 55 37 68",
    "sg:postcode":"46022",
    "sg:province":"Valencia",
    "wof:name":"Sociedad Constructora Familia Mauric",
    "wof:placetype":"venue"
},
  "geometry": {"coordinates":[-0.3434300125,39.4702758789],"type":"Point"}
}