{
  "type": "Feature",
  "properties": {
    "iso:country":"ES",
    "sg:address":"Avda Guadarrama (de), 17",
    "sg:city":"San Sebastian De Los Reyes",
    "sg:orig_category":"Molduras, Junquillos, Listones Y Molduras Perforadas",
    "sg:phone":"+34 916 54 65 55",
    "sg:postcode":"28700",
    "sg:province":"Madrid",
    "wof:name":"Gomez Acedo Jose Antonio",
    "wof:placetype":"venue"
},
  "geometry": {"coordinates":[-3.6348779202,40.5492973328],"type":"Point"}
}