{
  "type": "Feature",
  "properties": {
    "addr:full":"Carrer de Paris, 196 Barcelona Barcelona 08036",
    "addr:housenumber":"196",
    "addr:postcode":"08036",
    "addr:street":"Carrer De Paris",
    "iso:country":"ES",
    "sg:address":"Carrer de Paris, 196",
    "sg:city":"Barcelona",
    "sg:classifiers":[
        {
            "category":"Personal",
            "subcategory":"Barber",
            "type":"Services"
        }
    ],
    "sg:phone":"+34 932 18 26 76",
    "sg:postcode":"08036",
    "sg:province":"Barcelona",
    "sg:tags":[
        "caballeros",
        "de",
        "peluqueros"
    ],
    "wof:name":"Rosales Guijarro C.b.",
    "wof:placetype":"venue"
},
  "geometry": {"coordinates":[2.1538369656,41.3939056396],"type":"Point"}
}