{
  "type": "Feature",
  "properties": {
    "addr:full":"Calle de Doctor Fleming, 2 Andujar Ja\u00e9n 23740",
    "addr:housenumber":"2",
    "addr:postcode":"23740",
    "addr:street":"Calle De Doctor Fleming",
    "iso:country":"ES",
    "sg:address":"Calle de Doctor Fleming, 2",
    "sg:city":"Andujar",
    "sg:orig_category":"Cervezas (negociantes Y Depositarios)",
    "sg:phone":"+34 953 50 48 67",
    "sg:postcode":"23740",
    "sg:province":"Ja\u00e9n",
    "wof:name":"Martinez Pontiveros Jose",
    "wof:placetype":"venue"
},
  "geometry": {"coordinates":[-4.0572714806,38.0386314392],"type":"Point"}
}