{
  "type": "Feature",
  "properties": {
    "addr:full":"Carrer de Jacint Verdaguer, 4 Vic Barcelona 08500",
    "addr:housenumber":"4",
    "addr:postcode":"08500",
    "addr:street":"Carrer De Jacint Verdaguer",
    "iso:country":"ES",
    "sg:address":"Carrer de Jacint Verdaguer, 4",
    "sg:city":"Vic",
    "sg:orig_category":"Arquitectos",
    "sg:phone":"+34 938 85 23 58",
    "sg:postcode":"08500",
    "sg:province":"Barcelona",
    "wof:name":"Llobet Llobet Lluis",
    "wof:placetype":"venue"
},
  "geometry": {"coordinates":[2.2528319359,41.9305953979],"type":"Point"}
}