{
  "type": "Feature",
  "properties": {
    "iso:country":"ES",
    "sg:address":"Calle de Jaraba, 15",
    "sg:city":"Guadalajara",
    "sg:orig_category":"Promotores Constructores",
    "sg:phone":"+34 949 20 70 33",
    "sg:postcode":"19004",
    "sg:province":"Guadalajara",
    "wof:name":"Del Rio Diaz Jose Fermin",
    "wof:placetype":"venue"
},
  "geometry": {"coordinates":[-3.1922221184,40.6310462952],"type":"Point"}
}