{
  "type": "Feature",
  "properties": {
    "addr:full":"Calle de Rosal, 25 Puebla De Don Rodrigo Ciudad Real 13109",
    "addr:housenumber":"25",
    "addr:postcode":"13109",
    "addr:street":"Calle De Rosal",
    "iso:country":"ES",
    "sg:address":"Calle de Rosal, 25",
    "sg:city":"Puebla De Don Rodrigo",
    "sg:orig_category":"Material Y Suministros Para Perforaciones, Sondeos",
    "sg:phone":"+34 926 77 73 05",
    "sg:postcode":"13109",
    "sg:province":"Ciudad Real",
    "wof:name":"Rivero Fernandez Victoriano",
    "wof:placetype":"venue"
},
  "geometry": {"coordinates":[-4.6175990105,39.082447052],"type":"Point"}
}