{
  "type": "Feature",
  "properties": {
    "addr:full":"Calle de San Pablo, 13 Baeza Ja\u00e9n 23440",
    "addr:housenumber":"13",
    "addr:postcode":"23440",
    "addr:street":"Calle De San Pablo",
    "iso:country":"ES",
    "sg:address":"Calle de San Pablo, 13",
    "sg:city":"Baeza",
    "sg:orig_category":"Ropa Para Ni\u00d1os (al Por Menor)",
    "sg:phone":"+34 953 74 40 28",
    "sg:postcode":"23440",
    "sg:province":"Ja\u00e9n",
    "wof:name":"Garcia Najera Bartolome",
    "wof:placetype":"venue"
},
  "geometry": {"coordinates":[-3.4676690102,37.9936141968],"type":"Point"}
}