{
  "type": "Feature",
  "properties": {
    "iso:country":"ES",
    "sg:address":"Calle de Escritor Mercado Solis, 7",
    "sg:city":"Cordoba",
    "sg:orig_category":"Abogados",
    "sg:phone":"+34 957 27 66 68",
    "sg:postcode":"14011",
    "sg:province":"C\u00f3rdoba",
    "wof:name":"Cano Ballesta Juan",
    "wof:placetype":"venue"
},
  "geometry": {"coordinates":[-4.7934360504,37.8889312744],"type":"Point"}
}