{
  "type": "Feature",
  "properties": {
    "addr:full":"Carr Abat Sola, 34 Gandia Valencia 46700",
    "addr:housenumber":"34",
    "addr:postcode":"46700",
    "addr:street":"Carr Abat Sola;Valencia",
    "iso:country":"ES",
    "sg:address":"Carr Abat Sola, 34",
    "sg:city":"Gandia",
    "sg:orig_category":"Electricidad, Electr\u00d3nica: Material Y Suministros (al Por Mayor)",
    "sg:phone":"+34 962 86 34 62",
    "sg:postcode":"46700",
    "sg:province":"Valencia",
    "wof:name":"Safor Componentes Electronicos S. L.",
    "wof:placetype":"venue"
},
  "geometry": {"coordinates":[-0.1913339943,38.960735321],"type":"Point"}
}