{
  "type": "Feature",
  "properties": {
    "addr:full":"Urtaki, 34 Aduna Guip\u00f9zcoa 20150",
    "addr:housenumber":"34",
    "addr:postcode":"20150",
    "addr:street":"Urtaki;Guipu\u0300Zcoa",
    "iso:country":"ES",
    "sg:address":"Urtaki, 34",
    "sg:city":"Aduna",
    "sg:orig_category":"Rectificaci\u00d3n, Mecanizado, Fresado",
    "sg:phone":"+34 943 69 31 71",
    "sg:postcode":"20150",
    "sg:province":"Guip\u00f9zcoa",
    "wof:name":"Eutxi S.l.",
    "wof:placetype":"venue"
},
  "geometry": {"coordinates":[-2.0415990353,43.2008552551],"type":"Point"}
}