{
  "type": "Feature",
  "properties": {
    "addr:full":"Carr Creu, 7 Palamos Girona 17230",
    "addr:housenumber":"7",
    "addr:postcode":"17230",
    "addr:street":"Carr Creu",
    "iso:country":"ES",
    "sg:address":"Carr Creu, 7",
    "sg:city":"Palamos",
    "sg:orig_category":"Agencias Y Agentes Comerciales, Representantes",
    "sg:phone":"+34 972 60 02 08",
    "sg:postcode":"17230",
    "sg:province":"Girona",
    "wof:name":"Padro Rovira Juan",
    "wof:placetype":"venue"
},
  "geometry": {"coordinates":[3.1279499531,41.8473548889],"type":"Point"}
}