{
  "type": "Feature",
  "properties": {
    "iso:country":"ES",
    "sg:address":"Calle de Villa Benavente, 8",
    "sg:city":"Le\u00f3n",
    "sg:orig_category":"Abogados",
    "sg:phone":"+34 987 20 56 00",
    "sg:postcode":"24004",
    "sg:province":"Le\u00f3n",
    "sg:website":"www.paginasamarillas.es",
    "wof:name":"Mallo Lorenzo Andres",
    "wof:placetype":"venue"
},
  "geometry": {"coordinates":[-5.5734190941,42.5948600769],"type":"Point"}
}