{
  "type": "Feature",
  "properties": {
    "addr:full":"Calle de Corredera, 39 Miajadas C\u00e1ceres 10100",
    "addr:housenumber":"39",
    "addr:postcode":"10100",
    "addr:street":"Calle De Corredera;Ca\u0301Ceres",
    "iso:country":"ES",
    "sg:address":"Calle de Corredera, 39",
    "sg:city":"Miajadas",
    "sg:orig_category":"Venta, Instalaci\u00d3n De Calefacci\u00d3n",
    "sg:phone":"+34 927 34 77 64",
    "sg:postcode":"10100",
    "sg:province":"C\u00e1ceres",
    "wof:name":"Gutierro Sanchez Antonio",
    "wof:placetype":"venue"
},
  "geometry": {"coordinates":[-5.9056563377,39.1536102295],"type":"Point"}
}