{
  "type": "Feature",
  "properties": {
    "addr:full":"Calle de Pola De Siero, 11 Gijon Asturias 33207",
    "addr:housenumber":"11",
    "addr:postcode":"33207",
    "addr:street":"Calle De Pola;Siero",
    "iso:country":"ES",
    "sg:address":"Calle de Pola De Siero, 11",
    "sg:city":"Gijon",
    "sg:orig_category":"Venta, Instalaci\u00d3n De Calefacci\u00d3n",
    "sg:phone":"+34 985 35 90 02",
    "sg:postcode":"33207",
    "sg:province":"Asturias",
    "wof:name":"Requena Amigo Jose Angel",
    "wof:placetype":"venue"
},
  "geometry": {"coordinates":[-5.6696472168,43.5392036438],"type":"Point"}
}