{
  "type": "Feature",
  "properties": {
    "addr:full":"Av Mare De Deu De Bellvitge, 86 Hospitalet Llobregat Barcelona 08907",
    "addr:housenumber":"86",
    "addr:postcode":"08907",
    "addr:street":"Av Mare De Deu De Bellvitge",
    "iso:country":"ES",
    "sg:address":"Av Mare De Deu De Bellvitge, 86",
    "sg:city":"Hospitalet Llobregat",
    "sg:orig_category":"Cajas De Ahorro",
    "sg:phone":"+34 933 36 21 02",
    "sg:postcode":"08907",
    "sg:province":"Barcelona",
    "sg:website":"www.caixacatalunya.com",
    "wof:name":"Caixa D'estalvis De Catalunya",
    "wof:placetype":"venue"
},
  "geometry": {"coordinates":[2.1058499813,41.349521637],"type":"Point"}
}