{
  "type": "Feature",
  "properties": {
    "iso:country":"ES",
    "sg:address":"Pg Generalitat, 62",
    "sg:city":"Vic",
    "sg:orig_category":"Electrodom\u00c9sticos (al Por Menor)",
    "sg:phone":"+34 938 85 19 16",
    "sg:postcode":"08500",
    "sg:province":"Barcelona",
    "wof:name":"L'endoll S. A.",
    "wof:placetype":"venue"
},
  "geometry": {"coordinates":[2.2520298958,41.9195098877],"type":"Point"}
}