{
  "type": "Feature",
  "properties": {
    "iso:country":"ES",
    "sg:address":"Carrer de Eusebi Estada, 55",
    "sg:city":"Palma",
    "sg:orig_category":"Cristaler\u00cdas",
    "sg:phone":"+34 971 20 04 19",
    "sg:postcode":"07004",
    "sg:province":"Islas Baleares",
    "wof:name":"Cristaleria Estada S.l.",
    "wof:placetype":"venue"
},
  "geometry": {"coordinates":[2.6585280895,39.5801239014],"type":"Point"}
}