{
  "type": "Feature",
  "properties": {
    "iso:country":"ES",
    "sg:address":"Ctra. Tabernas A Uleila, Km. 0043,0",
    "sg:city":"Uleila Del Campo",
    "sg:orig_category":"Cooperativas Agr\u00cdcolas",
    "sg:phone":"+34 950 36 32 65",
    "sg:postcode":"04279",
    "sg:province":"Almer\u00eda",
    "wof:name":"Agroma\u00d1an S.c.l.",
    "wof:placetype":"venue"
},
  "geometry": {"coordinates":[-2.2038011551,37.1854820251],"type":"Point"}
}