{
  "type": "Feature",
  "properties": {
    "addr:full":"L. Pesquera, 8 Castello Plana Castell\u00f3n 12100",
    "addr:housenumber":"8",
    "addr:postcode":"12100",
    "addr:street":"Pesquera;Castello\u0301N",
    "iso:country":"ES",
    "sg:address":"L. Pesquera, 8",
    "sg:city":"Castello Plana",
    "sg:orig_category":"Distribuci\u00d3n De Petr\u00d3leo Y Derivados",
    "sg:phone":"+34 964 28 53 68",
    "sg:postcode":"12100",
    "sg:province":"Castell\u00f3n",
    "wof:name":"Falomir Martinez Jose",
    "wof:placetype":"venue"
},
  "geometry": {"coordinates":[0.0176999997,39.9888801575],"type":"Point"}
}