{
  "type": "Feature",
  "properties": {
    "addr:full":"Carrer de Tallers, 65 Barcelona Barcelona 08001",
    "addr:housenumber":"65",
    "addr:postcode":"08001",
    "addr:street":"Carrer De Tallers",
    "iso:country":"ES",
    "sg:address":"Carrer de Tallers, 65",
    "sg:city":"Barcelona",
    "sg:orig_category":"Pesca Y Caza: Art\u00cdculos (al Por Menor)",
    "sg:phone":"+34 933 01 88 80",
    "sg:postcode":"08001",
    "sg:province":"Barcelona",
    "wof:name":"Trevin S.a.",
    "wof:placetype":"venue"
},
  "geometry": {"coordinates":[2.1671140194,41.3847808838],"type":"Point"}
}