{
  "type": "Feature",
  "properties": {
    "iso:country":"ES",
    "sg:address":"Ptda Canastel-a, 5",
    "sg:city":"San Vicente Del Raspeig-sant Vicent Del Raspeig",
    "sg:orig_category":"Fabricaci\u00d3n De Postres Y Desayunos Preparados",
    "sg:phone":"+34 965 66 55 30",
    "sg:postcode":"03690",
    "sg:province":"Alicante",
    "wof:name":"Cobela Puig Manuel Odilo",
    "wof:placetype":"venue"
},
  "geometry": {"coordinates":[-0.5231339931,38.3981590271],"type":"Point"}
}