{
  "type": "Feature",
  "properties": {
    "addr:full":"Calle de Gobernador (del), S/n Aranjuez Madrid 28300",
    "addr:housenumber":"/ n",
    "addr:postcode":"28300",
    "addr:street":"Calle De Gobernador Del S",
    "iso:country":"ES",
    "sg:address":"Calle de Gobernador (del), S/n",
    "sg:city":"Aranjuez",
    "sg:orig_category":"Carnicer\u00cdas, Carnicer\u00cdas",
    "sg:phone":"+34 918 92 00 19",
    "sg:postcode":"28300",
    "sg:province":"Madrid",
    "wof:name":"Gonzalez Sanchez-rios Jose Luis",
    "wof:placetype":"venue"
},
  "geometry": {"coordinates":[-3.6040546894,40.0324630737],"type":"Point"}
}