{
  "type": "Feature",
  "properties": {
    "addr:full":"Calle de Naranjo De Bulnes, 2 Gijon Asturias 33211",
    "addr:housenumber":"2",
    "addr:postcode":"33211",
    "addr:street":"Calle De Naranjo De Bulnes",
    "iso:country":"ES",
    "sg:address":"Calle de Naranjo De Bulnes, 2",
    "sg:city":"Gijon",
    "sg:orig_category":"Cajas De Ahorro",
    "sg:phone":"+34 985 14 21 91",
    "sg:postcode":"33211",
    "sg:province":"Asturias",
    "wof:name":"Caja De Ahorros De Asturias",
    "wof:placetype":"venue"
},
  "geometry": {"coordinates":[-5.6796498299,43.5257606506],"type":"Point"}
}