{
  "type": "Feature",
  "properties": {
    "addr:full":"Sojoguti, 3 Sojoguti \u00c1lava 01474",
    "addr:housenumber":"3",
    "addr:postcode":"01474",
    "addr:street":"Sojoguti;A\u0301Lava",
    "iso:country":"ES",
    "sg:address":"Sojoguti, 3",
    "sg:city":"Sojoguti",
    "sg:orig_category":"Encuadernaci\u00d3n E Impresi\u00d3n De Folletos",
    "sg:phone":"+34 945 39 60 41",
    "sg:postcode":"01474",
    "sg:province":"\u00c1lava",
    "wof:name":"Gil Quintero Jose Angel",
    "wof:placetype":"venue"
},
  "geometry": {"coordinates":[-3.1292920113,43.122543335],"type":"Point"}
}