{
  "type": "Feature",
  "properties": {
    "addr:full":"Trav De Gracia, 51 Barcelona Barcelona 08006",
    "addr:housenumber":"51",
    "addr:postcode":"08006",
    "addr:street":"Trav De Gracia",
    "iso:country":"ES",
    "sg:address":"Trav De Gracia, 51",
    "sg:city":"Barcelona",
    "sg:orig_category":"Ropa Para Ni\u00d1os (al Por Menor)",
    "sg:phone":"+34 932 01 27 07",
    "sg:postcode":"08006",
    "sg:province":"Barcelona",
    "wof:name":"Umbert Hortal Margarita",
    "wof:placetype":"venue"
},
  "geometry": {"coordinates":[2.1494059563,41.3961677551],"type":"Point"}
}