{
  "type": "Feature",
  "properties": {
    "addr:full":"Afueras, Km. 0009,0 Valencia Alcantara C\u00e1ceres 10500",
    "addr:postcode":"10500",
    "addr:street":"Afueras Km. 0009,0;Alcantara Ca\u0301Ceres",
    "iso:country":"ES",
    "sg:address":"Afueras, Km. 0009,0",
    "sg:city":"Valencia Alcantara",
    "sg:orig_category":"Cr\u00cda De Animales",
    "sg:phone":"+34 927 58 02 26",
    "sg:postcode":"10500",
    "sg:province":"C\u00e1ceres",
    "wof:name":"Sociedad Agraria De Transformacion 2817 Heriher",
    "wof:placetype":"venue"
},
  "geometry": {"coordinates":[-7.2451472282,39.4101142883],"type":"Point"}
}