{
  "type": "Feature",
  "properties": {
    "iso:country":"ES",
    "sg:address":"Barr Axpe, 144",
    "sg:city":"Axpe-san Bartolome",
    "sg:orig_category":"Inversiones",
    "sg:phone":"+34 946 87 07 26",
    "sg:postcode":"48350",
    "sg:province":"Vizcaya",
    "wof:name":"Jacob Rox S.l.",
    "wof:placetype":"venue"
},
  "geometry": {"coordinates":[-2.6975340843,43.3843383789],"type":"Point"}
}