{
  "type": "Feature",
  "properties": {
    "addr:full":"Calle de Virgen De Los Remedios, S/n Oca\u00f1a Toledo 45300",
    "addr:housenumber":"s",
    "addr:postcode":"45300",
    "addr:street":"Calle De Virgen De Los;/ N Ocan\u0303A",
    "iso:country":"ES",
    "sg:address":"Calle de Virgen De Los Remedios, S/n",
    "sg:city":"Oca\u00f1a",
    "sg:orig_category":"Material Y Suministros Para Imprenta E Industrias Gr\u00c1ficas",
    "sg:phone":"+34 925 13 15 01",
    "sg:postcode":"45300",
    "sg:province":"Toledo",
    "wof:name":"Imprenta Rubiales S.l.",
    "wof:placetype":"venue"
},
  "geometry": {"coordinates":[-3.4924190044,39.9584541321],"type":"Point"}
}