{
  "type": "Feature",
  "properties": {
    "addr:full":"Carr Dr Fleming, 2 Almenar Lleida 25126",
    "addr:housenumber":"2",
    "addr:postcode":"25126",
    "addr:street":"Carr Dr Fleming",
    "iso:country":"ES",
    "sg:address":"Carr Dr Fleming, 2",
    "sg:city":"Almenar",
    "sg:orig_category":"Promotores Constructores",
    "sg:phone":"+34 973 77 02 85",
    "sg:postcode":"25126",
    "sg:province":"Lleida",
    "wof:name":"Vitoba Sl",
    "wof:placetype":"venue"
},
  "geometry": {"coordinates":[0.5709884167,41.7938919067],"type":"Point"}
}