{
  "type": "Feature",
  "properties": {
    "addr:full":"Calle de Calixto Fernandez De La Torre, 8 Valladolid Valladolid 47001",
    "addr:housenumber":"8",
    "addr:postcode":"47001",
    "addr:street":"Calle De Calixto Fernandez De La Torre",
    "iso:country":"ES",
    "sg:address":"Calle de Calixto Fernandez De La Torre, 8",
    "sg:city":"Valladolid",
    "sg:orig_category":"Muebles",
    "sg:phone":"+34 983 33 08 44",
    "sg:postcode":"47001",
    "sg:province":"Valladolid",
    "sg:website":"www.bonsaidecoracion.com",
    "wof:name":"Bonsai S. A.",
    "wof:placetype":"venue"
},
  "geometry": {"coordinates":[-4.7298140526,41.6518363953],"type":"Point"}
}