{
  "type": "Feature",
  "properties": {
    "addr:full":"Calle de Cardenal Cisneros, S/n Villalpardo Cuenca 16270",
    "addr:postcode":"16270",
    "addr:street":"Calle De Cardenal Cisneros S / N Villalpardo",
    "iso:country":"ES",
    "sg:address":"Calle de Cardenal Cisneros, S/n",
    "sg:city":"Villalpardo",
    "sg:orig_category":"Frutas Y Legumbres Secas (al Por Mayor)",
    "sg:phone":"+34 962 31 10 31",
    "sg:postcode":"16270",
    "sg:province":"Cuenca",
    "wof:name":"E.pedro Y Librado Carrasco C.b.",
    "wof:placetype":"venue"
},
  "geometry": {"coordinates":[-1.6244239807,39.4710884094],"type":"Point"}
}