{
  "type": "Feature",
  "properties": {
    "iso:country":"ES",
    "sg:address":"Avda Carolina Coronado, 29",
    "sg:city":"Badajoz",
    "sg:orig_category":"Instalaci\u00d3n De Sanitarios",
    "sg:phone":"+34 924 27 49 96",
    "sg:postcode":"06007",
    "sg:province":"Badajoz",
    "wof:name":"Aprosuba 3 Badajoz",
    "wof:placetype":"venue"
},
  "geometry": {"coordinates":[-6.981798172,38.8877334595],"type":"Point"}
}