{
  "type": "Feature",
  "properties": {
    "addr:full":"Calle de Major, 1 Javea Alicante 03730",
    "addr:housenumber":"1",
    "addr:postcode":"03730",
    "addr:street":"Calle De Major",
    "iso:country":"ES",
    "sg:address":"Calle de Major, 1",
    "sg:city":"Javea",
    "sg:orig_category":"Bisuter\u00cda, Joyer\u00cda, Relojer\u00cda (al Por Menor)",
    "sg:phone":"+34 965 79 68 65",
    "sg:postcode":"03730",
    "sg:province":"Alicante",
    "wof:name":"Joyeria Puigcerver Serra S.l.",
    "wof:placetype":"venue"
},
  "geometry": {"coordinates":[0.1634836048,38.7888145447],"type":"Point"}
}