{
  "type": "Feature",
  "properties": {
    "addr:full":"Pza. San Rogelio, S/n Illora Granada 18260",
    "addr:housenumber":"s / n",
    "addr:postcode":"18260",
    "addr:street":"Pza. San Rogelio",
    "iso:country":"ES",
    "sg:address":"Pza. San Rogelio, S/n",
    "sg:city":"Illora",
    "sg:orig_category":"Cajas De Ahorro",
    "sg:phone":"+34 958 46 33 00",
    "sg:postcode":"18260",
    "sg:province":"Granada",
    "wof:name":"Cajagranada",
    "wof:placetype":"venue"
},
  "geometry": {"coordinates":[-3.8815441132,37.2860450745],"type":"Point"}
}