{
  "type": "Feature",
  "properties": {
    "iso:country":"ES",
    "sg:address":"Calle de Prolongacion Virgen Del Carmen, 21",
    "sg:city":"Argamasilla Calatrava",
    "sg:orig_category":"Centros Empresariales",
    "sg:phone":"+34 926 47 70 19",
    "sg:postcode":"13440",
    "sg:province":"Ciudad Real",
    "wof:name":"Espinosa Garcia-moreno Juan Antonio",
    "wof:placetype":"venue"
},
  "geometry": {"coordinates":[-4.0764231682,38.7312202454],"type":"Point"}
}