{
  "type": "Feature",
  "properties": {
    "addr:full":"Calle de Italia, 2 Rota C\u00e1diz 11520",
    "addr:housenumber":"2",
    "addr:postcode":"11520",
    "addr:street":"Calle De Italia;Ca\u0301Diz",
    "iso:country":"ES",
    "sg:address":"Calle de Italia, 2",
    "sg:city":"Rota",
    "sg:orig_category":"Molduras, Junquillos, Listones Y Molduras Perforadas",
    "sg:phone":"+34 956 81 62 73",
    "sg:postcode":"11520",
    "sg:province":"C\u00e1diz",
    "wof:name":"Barba Benitez Jose Manuel",
    "wof:placetype":"venue"
},
  "geometry": {"coordinates":[-6.3581838608,36.6180419922],"type":"Point"}
}