{
  "type": "Feature",
  "properties": {
    "iso:country":"ES",
    "sg:address":"Avda Novelda, 273",
    "sg:city":"Alacant",
    "sg:orig_category":"Muebles, Minoristas",
    "sg:phone":"+34 965 17 28 20",
    "sg:postcode":"03009",
    "sg:province":"Alicante",
    "sg:website":"www.lamuebleriademicasa.es",
    "wof:name":"La Muebleria De Mi Casa S.l.",
    "wof:placetype":"venue"
},
  "geometry": {"coordinates":[-0.5013499856,38.3791847229],"type":"Point"}
}