{
  "type": "Feature",
  "properties": {
    "addr:full":"Praz Mestre Jose Dapena, 1 Betanzos La Coru\u00f1a 15300",
    "addr:housenumber":"1",
    "addr:postcode":"15300",
    "addr:street":"Jose Dapena;La",
    "iso:country":"ES",
    "sg:address":"Praz Mestre Jose Dapena, 1",
    "sg:city":"Betanzos",
    "sg:orig_category":"Aguas (distribuci\u00d3n, Servicios)",
    "sg:phone":"+34 981 77 21 12",
    "sg:postcode":"15300",
    "sg:province":"La Coru\u00f1a",
    "wof:name":"Aquagest S.a.",
    "wof:placetype":"venue"
},
  "geometry": {"coordinates":[-8.2267665863,43.2696266174],"type":"Point"}
}