{
  "type": "Feature",
  "properties": {
    "iso:country":"ES",
    "sg:address":"C/ Hospital, 16",
    "sg:city":"Elche",
    "sg:orig_category":"Lencer\u00cda Femenina, Corseter\u00cda, Trajes De Ba\u00d1o (al Por Menor)",
    "sg:phone":"+34 966 61 13 01",
    "sg:postcode":"03203",
    "sg:province":"Alicante",
    "wof:name":"Garcia Martinez Virginia",
    "wof:placetype":"venue"
},
  "geometry": {"coordinates":[-0.6964989901,38.2654685974],"type":"Point"}
}