{
  "type": "Feature",
  "properties": {
    "addr:full":"Avda Santa Cruz (la), 38 Santa Cruz De Bezana Cantabria 39100",
    "addr:housenumber":"38",
    "addr:postcode":"39100",
    "addr:street":"Avda Santa Cruz La",
    "iso:country":"ES",
    "sg:address":"Avda Santa Cruz (la), 38",
    "sg:city":"Santa Cruz De Bezana",
    "sg:orig_category":"Restaurantes",
    "sg:phone":"+34 942 58 00 09",
    "sg:postcode":"39100",
    "sg:province":"Cantabria",
    "wof:name":"Pomposo Ocejo Jose Luis",
    "wof:placetype":"venue"
},
  "geometry": {"coordinates":[-3.9104630947,43.4343833923],"type":"Point"}
}