{
  "type": "Feature",
  "properties": {
    "addr:full":"Rua Barcelona, 34 Vigo Pontevedra 36203",
    "addr:housenumber":"34",
    "addr:postcode":"36203",
    "addr:street":"Rua Barcelona",
    "iso:country":"ES",
    "sg:address":"Rua Barcelona, 34",
    "sg:city":"Vigo",
    "sg:orig_category":"Dietistas",
    "sg:phone":"+34 986 48 23 11",
    "sg:postcode":"36203",
    "sg:province":"Pontevedra",
    "sg:website":"www.naturhouse.com",
    "wof:name":"Housediet S.l. Sociedad Unipersonal",
    "wof:placetype":"venue"
},
  "geometry": {"coordinates":[-8.723531723,42.2259483337],"type":"Point"}
}