{
  "type": "Feature",
  "properties": {
    "addr:full":"Calle de Alamillos, 7 Palma Rio C\u00f3rdoba 14700",
    "addr:housenumber":"7",
    "addr:postcode":"14700",
    "addr:street":"Calle De Alamillos;Rio Co\u0301Rdoba",
    "iso:country":"ES",
    "sg:address":"Calle de Alamillos, 7",
    "sg:city":"Palma Rio",
    "sg:orig_category":"Producci\u00d3n, Venta De Productos De Agricultura Biol\u00d3gica",
    "sg:phone":"+34 957 71 02 80",
    "sg:postcode":"14700",
    "sg:province":"C\u00f3rdoba",
    "wof:name":"Ortega Ceballos,c.b.",
    "wof:placetype":"venue"
},
  "geometry": {"coordinates":[-5.2815284729,37.6970787048],"type":"Point"}
}