{
  "type": "Feature",
  "properties": {
    "iso:country":"ES",
    "sg:address":"Carrer de Doctor Marti I Julia, 77",
    "sg:city":"Hospitalet Llobregat",
    "sg:orig_category":"Frutas, Legumbres Frescas Y Tempranas (al Por Menor)",
    "sg:phone":"+34 933 33 62 51",
    "sg:postcode":"08903",
    "sg:province":"Barcelona",
    "wof:name":"Marcos Fernandez Jaime",
    "wof:placetype":"venue"
},
  "geometry": {"coordinates":[2.1229970455,41.3733024597],"type":"Point"}
}