{
  "type": "Feature",
  "properties": {
    "iso:country":"ES",
    "sg:address":"Carr Gavarres, 15",
    "sg:city":"Blanes",
    "sg:orig_category":"Chapister\u00cda",
    "sg:phone":"+34 972 33 22 00",
    "sg:postcode":"17300",
    "sg:province":"Girona",
    "wof:name":"Planchisteria Y Mecanica Quatre Vents S.l.",
    "wof:placetype":"venue"
},
  "geometry": {"coordinates":[2.781265974,41.6732063293],"type":"Point"}
}