{
  "type": "Feature",
  "properties": {
    "iso:country":"ES",
    "sg:address":"Calle de Rio Alberche, 130",
    "sg:city":"Poligono Sta M. De Benquerencia",
    "sg:orig_category":"Zapatos (al Por Menor)",
    "sg:phone":"+34 925 23 31 17",
    "sg:postcode":"45007",
    "sg:province":"Toledo",
    "wof:name":"Ballesteros Escobar Fermin",
    "wof:placetype":"venue"
},
  "geometry": {"coordinates":[-3.9422769547,39.8685455322],"type":"Point"}
}