{
  "type": "Feature",
  "properties": {
    "iso:country":"ES",
    "sg:address":"Calle de Marva, 5",
    "sg:city":"Valencia",
    "sg:classifiers":[
        {
            "category":"Arts & Performance",
            "subcategory":"Art Gallery",
            "type":"Entertainment"
        }
    ],
    "sg:phone":"+34 963 41 20 94",
    "sg:postcode":"46007",
    "sg:province":"Valencia",
    "sg:tags":[
        "arte",
        "de",
        "galer\u00cdas"
    ],
    "wof:name":"Jean-pierre Motte Y Stephane Quintiliano Cdad.",
    "wof:placetype":"venue"
},
  "geometry": {"coordinates":[-0.3826420009,39.4631767273],"type":"Point"}
}