{
  "type": "Feature",
  "properties": {
    "iso:country":"ES",
    "sg:address":"Carrer de Alt De Sant Salvador, 12",
    "sg:city":"Reus",
    "sg:orig_category":"Explotaci\u00d3n De Aparcamientos",
    "sg:phone":"+34 977 31 29 08",
    "sg:postcode":"43201",
    "sg:province":"Tarragona",
    "wof:name":"Conticin S.l.",
    "wof:placetype":"venue"
},
  "geometry": {"coordinates":[1.1065579653,41.1544036865],"type":"Point"}
}