{
  "type": "Feature",
  "properties": {
    "addr:full":"Rond O'donnell, 29 Mataro Barcelona 08303",
    "addr:housenumber":"29",
    "addr:postcode":"08303",
    "addr:street":"O'Donnell",
    "iso:country":"ES",
    "sg:address":"Rond O'donnell, 29",
    "sg:city":"Mataro",
    "sg:orig_category":"Fabricaci\u00d3n De Su\u00c9ters Y Chalecos De Punto",
    "sg:phone":"+34 937 98 52 93",
    "sg:postcode":"08303",
    "sg:province":"Barcelona",
    "wof:name":"Mida's Barcelona S.l.",
    "wof:placetype":"venue"
},
  "geometry": {"coordinates":[2.4321320057,41.5380477905],"type":"Point"}
}