{
  "type": "Feature",
  "properties": {
    "iso:country":"ES",
    "sg:address":"Avda El Ferial, 94",
    "sg:city":"Benavente",
    "sg:orig_category":"Maquinaria Para Industrias Diversas",
    "sg:phone":"+34 980 63 11 11",
    "sg:postcode":"49600",
    "sg:province":"Zamora",
    "wof:name":"Alcalser 2000 S.l.",
    "wof:placetype":"venue"
},
  "geometry": {"coordinates":[-5.6773509979,42.0072517395],"type":"Point"}
}