{
  "type": "Feature",
  "properties": {
    "addr:full":"Pl Granados, 20 Sabadell Barcelona 08201",
    "addr:housenumber":"20",
    "addr:postcode":"08201",
    "addr:street":"Pl Granados",
    "iso:country":"ES",
    "sg:address":"Pl Granados, 20",
    "sg:city":"Sabadell",
    "sg:orig_category":"Carnicer\u00cdas, Carnicer\u00cdas",
    "sg:phone":"+34 937 26 23 78",
    "sg:postcode":"08201",
    "sg:province":"Barcelona",
    "wof:name":"Lourdes & Marta Charcuteria Qualitat S.l.",
    "wof:placetype":"venue"
},
  "geometry": {"coordinates":[2.1036849022,41.5509338379],"type":"Point"}
}