{
  "type": "Feature",
  "properties": {
    "addr:full":"Pe\u00f1a Santa, S/n Lugo Asturias 33192",
    "addr:housenumber":"/ n",
    "addr:postcode":"33192",
    "addr:street":"Santa S",
    "iso:country":"ES",
    "sg:address":"Pe\u00f1a Santa, S/n",
    "sg:city":"Lugo",
    "sg:orig_category":"Frutas Y Legumbres Frescas (al Por Mayor)",
    "sg:phone":"+34 985 26 72 87",
    "sg:postcode":"33192",
    "sg:province":"Asturias",
    "sg:website":"www.dole.com",
    "wof:name":"Dole Food Espa\u00d1a S.a.",
    "wof:placetype":"venue"
},
  "geometry": {"coordinates":[-5.7745718956,43.4596939087],"type":"Point"}
}