{
  "type": "Feature",
  "properties": {
    "addr:full":"Calle de Llano Ponte, 29 Oviedo Asturias 33011",
    "addr:housenumber":"29",
    "addr:postcode":"33011",
    "addr:street":"Calle De Llano Ponte",
    "iso:country":"ES",
    "sg:address":"Calle de Llano Ponte, 29",
    "sg:city":"Oviedo",
    "sg:orig_category":"Mec\u00c1nico Del Autom\u00d3vil",
    "sg:phone":"+34 985 28 09 65",
    "sg:postcode":"33011",
    "sg:province":"Asturias",
    "wof:name":"Norastur S.a.",
    "wof:placetype":"venue"
},
  "geometry": {"coordinates":[-5.8503851891,43.3686523438],"type":"Point"}
}