{
  "type": "Feature",
  "properties": {
    "iso:country":"ES",
    "sg:address":"Calle de Fernando El Catolico, 47",
    "sg:city":"Riba-roja Turia",
    "sg:orig_category":"Electrodom\u00c9sticos (al Por Menor)",
    "sg:phone":"+34 962 77 11 57",
    "sg:postcode":"46190",
    "sg:province":"Valencia",
    "wof:name":"Gimeno Zorrilla Jose Ramon",
    "wof:placetype":"venue"
},
  "geometry": {"coordinates":[-0.5698940158,39.5458450317],"type":"Point"}
}