{
  "type": "Feature",
  "properties": {
    "addr:full":"Ramirez La Sala, 53 Sta. Cruz Mudela Ciudad Real 13730",
    "addr:housenumber":"53",
    "addr:postcode":"13730",
    "addr:street":"La Sala;Cruz Mudela",
    "iso:country":"ES",
    "sg:address":"Ramirez La Sala, 53",
    "sg:city":"Sta. Cruz Mudela",
    "sg:orig_category":"Tintes (fabricaci\u00d3n, Al Por Mayor)",
    "sg:phone":"+34 926 34 21 02",
    "sg:postcode":"13730",
    "sg:province":"Ciudad Real",
    "wof:name":"Trujillo Nu\u00f1ez Luis Victoriano",
    "wof:placetype":"venue"
},
  "geometry": {"coordinates":[-3.4659380913,38.6414527893],"type":"Point"}
}