{
  "type": "Feature",
  "properties": {
    "iso:country":"ES",
    "sg:address":"Calle de Fuente Nueva, 4",
    "sg:city":"Poyales Del Hoyo",
    "sg:orig_category":"Contenedores (mercanc\u00cdas)",
    "sg:phone":"+34 920 39 02 88",
    "sg:postcode":"05492",
    "sg:province":"\u00c1vila",
    "wof:name":"Blazquez Fraile Jose Maria",
    "wof:placetype":"venue"
},
  "geometry": {"coordinates":[-5.1665167809,40.1719856262],"type":"Point"}
}