{
  "type": "Feature",
  "properties": {
    "iso:country":"ES",
    "sg:address":"Av Diagonal, 656",
    "sg:city":"Barcelona",
    "sg:orig_category":"Freidur\u00cdas: Equipos Y Suministros",
    "sg:phone":"+34 932 80 35 32",
    "sg:postcode":"08034",
    "sg:province":"Barcelona",
    "wof:name":"Unichips Espa\u00f1a S.a.",
    "wof:placetype":"venue"
},
  "geometry": {"coordinates":[2.1303560734,41.3896141052],"type":"Point"}
}