{
  "type": "Feature",
  "properties": {
    "iso:country":"ES",
    "sg:address":"Avda Alcalde Alvaro Domecq, 31",
    "sg:city":"Jerez De La Frontera",
    "sg:orig_category":"Promotores Constructores",
    "sg:phone":"+34 956 30 84 50",
    "sg:postcode":"11405",
    "sg:province":"C\u00e1diz",
    "wof:name":"Gonzalez Pinto Antonio",
    "wof:placetype":"venue"
},
  "geometry": {"coordinates":[-6.1281862259,36.6960525513],"type":"Point"}
}