{
  "type": "Feature",
  "properties": {
    "iso:country":"ES",
    "sg:address":"Calle de Mairena, 24",
    "sg:city":"Alcala Guadaira",
    "sg:orig_category":"Ropa Para Se\u00d1oras (al Por Menor)",
    "sg:phone":"+34 955 68 35 04",
    "sg:postcode":"41500",
    "sg:province":"Sevilla",
    "wof:name":"Britvi S.l.",
    "wof:placetype":"venue"
},
  "geometry": {"coordinates":[-5.842479229,37.3378944397],"type":"Point"}
}