{
  "type": "Feature",
  "properties": {
    "iso:country":"ES",
    "sg:address":"Rua Damas Apostolicas, 17",
    "sg:city":"Ramallosa",
    "sg:orig_category":"Mercer\u00cda, Lencer\u00cda (al Por Menor)",
    "sg:phone":"+34 986 35 09 55",
    "sg:postcode":"36379",
    "sg:province":"Pontevedra",
    "wof:name":"De Catro Ramallosa S.l.",
    "wof:placetype":"venue"
},
  "geometry": {"coordinates":[-8.810918808,42.1176185608],"type":"Point"}
}