{
  "type": "Feature",
  "properties": {
    "addr:full":"Rua Via Norte, 50 Vigo Pontevedra 36204",
    "addr:housenumber":"50",
    "addr:postcode":"36204",
    "addr:street":"Rua Via Norte",
    "iso:country":"ES",
    "sg:address":"Rua Via Norte, 50",
    "sg:city":"Vigo",
    "sg:orig_category":"Doctores En Medicina",
    "sg:phone":"+34 986 47 00 88",
    "sg:postcode":"36204",
    "sg:province":"Pontevedra",
    "wof:name":"Lopez Boado Oscar",
    "wof:placetype":"venue"
},
  "geometry": {"coordinates":[-8.708278656,42.2345085144],"type":"Point"}
}