{
  "type": "Feature",
  "properties": {
    "addr:full":"Pol. Industrial, S/n Agramunt Lleida 25310",
    "addr:housenumber":"/ n",
    "addr:postcode":"25310",
    "addr:street":"Pol. Industrial S",
    "iso:country":"ES",
    "sg:address":"Pol. Industrial, S/n",
    "sg:city":"Agramunt",
    "sg:orig_category":"Construcci\u00d3n Mec\u00c1nica",
    "sg:phone":"+34 973 39 16 33",
    "sg:postcode":"25310",
    "sg:province":"Lleida",
    "sg:website":"www.rosroca.com",
    "wof:name":"Primeros Transformados",
    "wof:placetype":"venue"
},
  "geometry": {"coordinates":[1.1030299664,41.7803268433],"type":"Point"}
}