{
  "type": "Feature",
  "properties": {
    "addr:full":"Calle de Iglesia, S/n Malpartida Caceres C\u00e1ceres 10910",
    "addr:housenumber":"s / n",
    "addr:postcode":"10910",
    "addr:street":"Calle De Iglesia;Ca\u0301Ceres",
    "iso:country":"ES",
    "sg:address":"Calle de Iglesia, S/n",
    "sg:city":"Malpartida Caceres",
    "sg:orig_category":"Iglesia Cat\u00d3lica",
    "sg:phone":"+34 927 27 50 31",
    "sg:postcode":"10910",
    "sg:province":"C\u00e1ceres",
    "wof:name":"Parroquia Nuestra Se\u00f1ora De La Asuncion",
    "wof:placetype":"venue"
},
  "geometry": {"coordinates":[-6.5064339638,39.4458351135],"type":"Point"}
}