{
  "type": "Feature",
  "properties": {
    "iso:country":"ES",
    "sg:address":"Rua Progreso, 34",
    "sg:city":"Sanxenxo",
    "sg:orig_category":"T\u00c9cnicos Veterinarios",
    "sg:phone":"+34 986 69 18 45",
    "sg:postcode":"36960",
    "sg:province":"Pontevedra",
    "wof:name":"Vetxenxo S.l",
    "wof:placetype":"venue"
},
  "geometry": {"coordinates":[-8.799908638,42.4011306763],"type":"Point"}
}