{
  "type": "Feature",
  "properties": {
    "addr:full":"Calle de Rutilo, 17 Madrid Madrid 28041",
    "addr:housenumber":"17",
    "addr:postcode":"madrid;28041",
    "addr:street":"Calle De Rutilo",
    "iso:country":"ES",
    "sg:address":"Calle de Rutilo, 17",
    "sg:city":"Madrid",
    "sg:orig_category":"Agencias Y Agentes Comerciales, Representantes",
    "sg:phone":"+34 913 92 02 19",
    "sg:postcode":"28041",
    "sg:province":"Madrid",
    "wof:name":"Ortiz Cano Roger Antonio",
    "wof:placetype":"venue"
},
  "geometry": {"coordinates":[-3.6864900589,40.3660049438],"type":"Point"}
}