{
  "type": "Feature",
  "properties": {
    "iso:country":"ES",
    "sg:address":"Avda Americas (das), 30",
    "sg:city":"Lugo",
    "sg:orig_category":"Transporte En General",
    "sg:phone":"+34 982 21 81 52",
    "sg:postcode":"27004",
    "sg:province":"Lugo",
    "wof:name":"Postal Lugo C.b",
    "wof:placetype":"venue"
},
  "geometry": {"coordinates":[-7.5682148933,43.0102348328],"type":"Point"}
}