{
  "type": "Feature",
  "properties": {
    "iso:country":"ES",
    "sg:address":"Calle de Duquesa Villahermosa, 4",
    "sg:city":"Zaragoza",
    "sg:orig_category":"Fotograf\u00cda Y Cine: Aparatos, Pel\u00cdculas Y Accesorios (fabricaci\u00d3n, Al Por Mayor)",
    "sg:phone":"+34 976 33 66 25",
    "sg:postcode":"50010",
    "sg:province":"Zaragoza",
    "wof:name":"Varea Legorburo Ana Maria",
    "wof:placetype":"venue"
},
  "geometry": {"coordinates":[-0.8995299935,41.649307251],"type":"Point"}
}