{
  "type": "Feature",
  "properties": {
    "addr:full":"Carr Gran Bretanya, 45 Igualada Barcelona 08700",
    "addr:housenumber":"45",
    "addr:postcode":"08700",
    "addr:street":"Carr Gran Bretanya",
    "iso:country":"ES",
    "sg:address":"Carr Gran Bretanya, 45",
    "sg:city":"Igualada",
    "sg:orig_category":"M\u00c1rmoles, Granitos Y Piedras Naturales",
    "sg:phone":"+34 938 03 68 15",
    "sg:postcode":"08700",
    "sg:province":"Barcelona",
    "wof:name":"Marbres Pedres Y Granits Iva\u00f1ez S.c.p.",
    "wof:placetype":"venue"
},
  "geometry": {"coordinates":[1.6338759661,41.5870132446],"type":"Point"}
}