{
  "type": "Feature",
  "properties": {
    "iso:country":"ES",
    "sg:address":"Calle de Gabriel Usera, 72",
    "sg:city":"Madrid",
    "sg:orig_category":"Chapister\u00cda",
    "sg:phone":"+34 914 75 10 95",
    "sg:postcode":"28026",
    "sg:province":"Madrid",
    "wof:name":"Montesano Llorente Maria Teresa",
    "wof:placetype":"venue"
},
  "geometry": {"coordinates":[-3.7084810734,40.3827476501],"type":"Point"}
}