{
  "type": "Feature",
  "properties": {
    "addr:full":"Avda Granada, 6 Jaen Ja\u00e9n 23001",
    "addr:housenumber":"6;jae\u0301n",
    "addr:postcode":"23001",
    "addr:street":"Avda Granada",
    "iso:country":"ES",
    "sg:address":"Avda Granada, 6",
    "sg:city":"Jaen",
    "sg:orig_category":"Promotores Constructores",
    "sg:phone":"+34 953 19 03 07",
    "sg:postcode":"23001",
    "sg:province":"Ja\u00e9n",
    "wof:name":"Covalmon S. C. A",
    "wof:placetype":"venue"
},
  "geometry": {"coordinates":[-3.7858440876,37.7689247131],"type":"Point"}
}