{
  "type": "Feature",
  "properties": {
    "iso:country":"ES",
    "sg:address":"Calle de Colon, 2",
    "sg:city":"Nerva",
    "sg:orig_category":"Quincaller\u00cda (al Por Menor)",
    "sg:phone":"+34 959 58 00 37",
    "sg:postcode":"21670",
    "sg:province":"Huelva",
    "wof:name":"Escobar Garcia Miguel Angel",
    "wof:placetype":"venue"
},
  "geometry": {"coordinates":[-6.5504927635,37.6966819763],"type":"Point"}
}