{
  "type": "Feature",
  "properties": {
    "iso:country":"ES",
    "sg:address":"Cmno Pobladura, 2",
    "sg:city":"Santa Maria Del Paramo",
    "sg:orig_category":"Bebidas",
    "sg:phone":"+34 987 35 02 40",
    "sg:postcode":"24240",
    "sg:province":"Le\u00f3n",
    "wof:name":"Gaseosas Polo C.b.",
    "wof:placetype":"venue"
},
  "geometry": {"coordinates":[-5.7451381683,42.3512687683],"type":"Point"}
}