{
  "type": "Feature",
  "properties": {
    "addr:full":"De La Cruz, 15 Montellano Sevilla 41770",
    "addr:housenumber":"15",
    "addr:postcode":"41770",
    "addr:street":"La Cruz",
    "iso:country":"ES",
    "sg:address":"De La Cruz, 15",
    "sg:city":"Montellano",
    "sg:orig_category":"Heladeros",
    "sg:phone":"+34 954 87 56 16",
    "sg:postcode":"41770",
    "sg:province":"Sevilla",
    "wof:name":"Roman Lopez Inmaculada",
    "wof:placetype":"venue"
},
  "geometry": {"coordinates":[-5.5723938942,36.9944152832],"type":"Point"}
}