{
  "type": "Feature",
  "properties": {
    "addr:full":"Calle de Honorato Juan, 9 Valencia Valencia 46007",
    "addr:housenumber":"9",
    "addr:postcode":"46007",
    "addr:street":"Calle De Honorato Juan",
    "iso:country":"ES",
    "sg:address":"Calle de Honorato Juan, 9",
    "sg:city":"Valencia",
    "sg:classifiers":[
        {
            "category":"Autos & Motor Vehicles",
            "subcategory":"Automobile Sales",
            "type":"Retail Goods"
        }
    ],
    "sg:phone":"+34 963 80 96 63",
    "sg:postcode":"46007",
    "sg:province":"Valencia",
    "wof:name":"Auto Escuela Blay Climent S.l.",
    "wof:placetype":"venue"
},
  "geometry": {"coordinates":[-0.3866162002,39.4645462036],"type":"Point"}
}