{
  "type": "Feature",
  "properties": {
    "iso:country":"ES",
    "sg:address":"Carr Pep Ventura, 23",
    "sg:city":"Figueres",
    "sg:orig_category":"Psic\u00d3logos",
    "sg:phone":"+34 972 50 30 03",
    "sg:postcode":"17600",
    "sg:province":"Girona",
    "wof:name":"Serra Rosa Blanca",
    "wof:placetype":"venue"
},
  "geometry": {"coordinates":[2.9585359097,42.2666702271],"type":"Point"}
}