{
  "type": "Feature",
  "properties": {
    "iso:country":"ES",
    "sg:address":"Rua Oliva (la), 18",
    "sg:city":"Pontevedra",
    "sg:orig_category":"Arquitectos",
    "sg:phone":"+34 986 85 83 28",
    "sg:postcode":"36001",
    "sg:province":"Pontevedra",
    "wof:name":"Diaz Grande Alfredo",
    "wof:placetype":"venue"
},
  "geometry": {"coordinates":[-8.6449346542,42.4301757812],"type":"Point"}
}