{
  "type": "Feature",
  "properties": {
    "addr:full":"Carr Sol Naixent, 24 Son Moro Islas Baleares 07560",
    "addr:housenumber":"24",
    "addr:postcode":"07560",
    "addr:street":"Carr Sol Naixent",
    "iso:country":"ES",
    "sg:address":"Carr Sol Naixent, 24",
    "sg:city":"Son Moro",
    "sg:orig_category":"Perfumer\u00cda (al Por Menor)",
    "sg:phone":"+34 971 58 53 65",
    "sg:postcode":"07560",
    "sg:province":"Islas Baleares",
    "wof:name":"Perfums Sirer S. A.",
    "wof:placetype":"venue"
},
  "geometry": {"coordinates":[3.3764801025,39.5764541626],"type":"Point"}
}