{
  "type": "Feature",
  "properties": {
    "iso:country":"ES",
    "sg:address":"Calle de Rabida, 22",
    "sg:city":"Palos Frontera",
    "sg:orig_category":"Farmacias",
    "sg:phone":"+34 959 35 00 64",
    "sg:postcode":"21810",
    "sg:province":"Huelva",
    "wof:name":"Arjonilla Romero Manuel Jesus",
    "wof:placetype":"venue"
},
  "geometry": {"coordinates":[-6.894244194,37.2280540466],"type":"Point"}
}