{
  "type": "Feature",
  "properties": {
    "addr:full":"Calle de Enrique Segura Ota\u00d1o, 8 Badajoz Badajoz 06004",
    "addr:housenumber":"8",
    "addr:postcode":"06004",
    "addr:street":"Calle De Enrique Segura Otan\u0303O",
    "iso:country":"ES",
    "sg:address":"Calle de Enrique Segura Ota\u00d1o, 8",
    "sg:city":"Badajoz",
    "sg:orig_category":"Psic\u00d3logos",
    "sg:phone":"+34 924 24 66 54",
    "sg:postcode":"06004",
    "sg:province":"Badajoz",
    "wof:name":"Atanet Paniagua Francisco",
    "wof:placetype":"venue"
},
  "geometry": {"coordinates":[-6.9734578133,38.8731384277],"type":"Point"}
}