{
  "type": "Feature",
  "properties": {
    "addr:full":"Carrer de Dos De Maig, 50 Viladecans Barcelona 08840",
    "addr:housenumber":"50",
    "addr:postcode":"08840",
    "addr:street":"Carrer De Dos De Maig",
    "iso:country":"ES",
    "sg:address":"Carrer de Dos De Maig, 50",
    "sg:city":"Viladecans",
    "sg:orig_category":"Supermercados Y Hipermercados",
    "sg:phone":"+34 936 59 17 47",
    "sg:postcode":"08840",
    "sg:province":"Barcelona",
    "wof:name":"Cs Establiments De Proximitat S.l.",
    "wof:placetype":"venue"
},
  "geometry": {"coordinates":[2.0117819309,41.3186531067],"type":"Point"}
}