{
  "type": "Feature",
  "properties": {
    "addr:full":"Avda Mediterraneo, 15 Benidorm Alicante 03500",
    "addr:housenumber":"15",
    "addr:postcode":"03500",
    "addr:street":"Avda Mediterraneo",
    "iso:country":"ES",
    "sg:address":"Avda Mediterraneo, 15",
    "sg:city":"Benidorm",
    "sg:orig_category":"Estancos",
    "sg:phone":"+34 965 85 60 41",
    "sg:postcode":"03500",
    "sg:province":"Alicante",
    "wof:name":"Algado Llinares Maria Carmen",
    "wof:placetype":"venue"
},
  "geometry": {"coordinates":[-0.1196201965,38.5368728638],"type":"Point"}
}