{
  "type": "Feature",
  "properties": {
    "iso:country":"ES",
    "sg:address":"Guadalpark Ii, 18",
    "sg:city":"Marbella",
    "sg:orig_category":"Seguridad En El Trabajo Y Prevenci\u00d3n De Riesgos Laborales",
    "sg:phone":"+34 952 77 00 41",
    "sg:postcode":"29600",
    "sg:province":"M\u00e1laga",
    "wof:name":"Global Control S.c.",
    "wof:placetype":"venue"
},
  "geometry": {"coordinates":[-4.7588043213,36.5039405823],"type":"Point"}
}