{
  "type": "Feature",
  "properties": {
    "addr:full":"Calle de Bravo Murillo, 12 Madrid Madrid 28015",
    "addr:housenumber":"12",
    "addr:postcode":"madrid;28015",
    "addr:street":"Calle De Bravo Murillo",
    "iso:country":"ES",
    "sg:address":"Calle de Bravo Murillo, 12",
    "sg:city":"Madrid",
    "sg:orig_category":"Quincaller\u00cda (al Por Menor)",
    "sg:phone":"+34 914 45 70 14",
    "sg:postcode":"28015",
    "sg:province":"Madrid",
    "wof:name":"Garcia Santander Jorge",
    "wof:placetype":"venue"
},
  "geometry": {"coordinates":[-3.704328537,40.4347915649],"type":"Point"}
}