{
  "type": "Feature",
  "properties": {
    "iso:country":"ES",
    "sg:address":"Avda Akra Leuka, S/n",
    "sg:city":"Pe\u00f1iscola",
    "sg:orig_category":"Organizaciones Internacionales",
    "sg:phone":"+34 964 48 99 02",
    "sg:postcode":"12598",
    "sg:province":"Castell\u00f3n",
    "wof:name":"Cruz Roja Espa\u00f1ola",
    "wof:placetype":"venue"
},
  "geometry": {"coordinates":[0.4009099901,40.3586883545],"type":"Point"}
}