{
  "type": "Feature",
  "properties": {
    "addr:full":"Carr Major, 9 Arbucies Girona 17401",
    "addr:housenumber":"9",
    "addr:postcode":"17401",
    "addr:street":"Carr Major",
    "iso:country":"ES",
    "sg:address":"Carr Major, 9",
    "sg:city":"Arbucies",
    "sg:orig_category":"Zapatos (al Por Menor)",
    "sg:phone":"+34 972 86 08 02",
    "sg:postcode":"17401",
    "sg:province":"Girona",
    "wof:name":"Vilamala Comajuan Josep",
    "wof:placetype":"venue"
},
  "geometry": {"coordinates":[2.518239975,41.8144645691],"type":"Point"}
}