{
  "type": "Feature",
  "properties": {
    "addr:full":"Comercio, 23 Monforte De Lemos Lugo 27400",
    "addr:housenumber":"23",
    "addr:postcode":"27400",
    "addr:street":"Comercio",
    "iso:country":"ES",
    "sg:address":"Comercio, 23",
    "sg:city":"Monforte De Lemos",
    "sg:orig_category":"Farmacias",
    "sg:phone":"+34 982 40 49 55",
    "sg:postcode":"27400",
    "sg:province":"Lugo",
    "wof:name":"Pazo Rocha Berta",
    "wof:placetype":"venue"
},
  "geometry": {"coordinates":[-7.5138111115,42.5224609375],"type":"Point"}
}