{
  "type": "Feature",
  "properties": {
    "addr:full":"Calle de Siervo De Dios, 19 Icod De Los Vinos Santa Cruz De Tenerife 38430",
    "addr:housenumber":"19",
    "addr:postcode":"38430",
    "addr:street":"Calle De Siervo;Dios",
    "iso:country":"ES",
    "sg:address":"Calle de Siervo De Dios, 19",
    "sg:city":"Icod De Los Vinos",
    "sg:orig_category":"Asociaciones Y Clubs Deportivos",
    "sg:phone":"+34 922 81 30 63",
    "sg:postcode":"38430",
    "sg:province":"Santa Cruz De Tenerife",
    "wof:name":"Delgado Herrera Maria Del Rosario",
    "wof:placetype":"venue"
},
  "geometry": {"coordinates":[-16.7176208496,28.3677482605],"type":"Point"}
}