{
  "type": "Feature",
  "properties": {
    "iso:country":"ES",
    "sg:address":"Calle de Alcalde Eduardo Carvajal, 4",
    "sg:city":"Malaga",
    "sg:orig_category":"Agencias Y Asesores De Publicidad",
    "sg:phone":"+34 952 25 87 63",
    "sg:postcode":"29014",
    "sg:province":"M\u00e1laga",
    "wof:name":"Sotorcam Promociones S.l.",
    "wof:placetype":"venue"
},
  "geometry": {"coordinates":[-4.4220061302,36.7382621765],"type":"Point"}
}