{
  "type": "Feature",
  "properties": {
    "addr:full":"Avda Democracia De La, 93 Mesas Las Palmas 35018",
    "addr:housenumber":"93",
    "addr:postcode":"35018",
    "addr:street":"Avda Democracia De La",
    "iso:country":"ES",
    "sg:address":"Avda Democracia De La, 93",
    "sg:city":"Mesas",
    "sg:orig_category":"Artes Gr\u00c1ficas, Artes Pl\u00c1sticas (curso)",
    "sg:phone":"+34 928 67 35 19",
    "sg:postcode":"35018",
    "sg:province":"Las Palmas",
    "wof:name":"Graficas 2000 Las Palmas S.l.",
    "wof:placetype":"venue"
},
  "geometry": {"coordinates":[-15.5027666092,28.0957775116],"type":"Point"}
}