{
  "type": "Feature",
  "properties": {
    "addr:full":"Calle de Sal (de La), 50 Parla Madrid 28980",
    "addr:postcode":"28980",
    "addr:street":"Calle De",
    "iso:country":"ES",
    "sg:address":"Calle de Sal (de La), 50",
    "sg:city":"Parla",
    "sg:orig_category":"Carnicer\u00cdas, Carnicer\u00cdas",
    "sg:phone":"+34 916 05 76 15",
    "sg:postcode":"28980",
    "sg:province":"Madrid",
    "wof:name":"Hermano Gil C.b.",
    "wof:placetype":"venue"
},
  "geometry": {"coordinates":[-3.7699849606,40.2404289246],"type":"Point"}
}