{
  "type": "Feature",
  "properties": {
    "addr:full":"Pg Gracia, 100 Barcelona Barcelona 08008",
    "addr:housenumber":"100",
    "addr:postcode":"08008",
    "addr:street":"Pg Gracia",
    "iso:country":"ES",
    "sg:address":"Pg Gracia, 100",
    "sg:city":"Barcelona",
    "sg:orig_category":"Cl\u00cdnicas Dentales",
    "sg:phone":"+34 932 15 20 78",
    "sg:postcode":"08008",
    "sg:province":"Barcelona",
    "wof:name":"Centre Medic Dental Sant Jordi S.l.",
    "wof:placetype":"venue"
},
  "geometry": {"coordinates":[2.1611158848,41.3956565857],"type":"Point"}
}