{
  "type": "Feature",
  "properties": {
    "iso:country":"ES",
    "sg:address":"Av Republica Argentina, 190",
    "sg:city":"Barcelona",
    "sg:orig_category":"Dorados, Plater\u00cda (orfebrer\u00cda)",
    "sg:phone":"+34 932 12 21 76",
    "sg:postcode":"08023",
    "sg:province":"Barcelona",
    "wof:name":"Razzauti Escoda Luis Jose",
    "wof:placetype":"venue"
},
  "geometry": {"coordinates":[2.1412549019,41.4118232727],"type":"Point"}
}