{
  "type": "Feature",
  "properties": {
    "iso:country":"ES",
    "sg:address":"Carrer de Gurrea, 127",
    "sg:city":"Sabadell",
    "sg:orig_category":"Imprenta",
    "sg:phone":"+34 937 25 07 03",
    "sg:postcode":"08202",
    "sg:province":"Barcelona",
    "wof:name":"Sdio Espau S.l.",
    "wof:placetype":"venue"
},
  "geometry": {"coordinates":[2.115434885,41.5439033508],"type":"Point"}
}