{
  "type": "Feature",
  "properties": {
    "addr:full":"Carrer de Sant Antoni Maria Claret, 506 Barcelona Barcelona 08027",
    "addr:housenumber":"506",
    "addr:postcode":"08027",
    "addr:street":"Carrer De Sant Antoni Maria Claret",
    "iso:country":"ES",
    "sg:address":"Carrer de Sant Antoni Maria Claret, 506",
    "sg:city":"Barcelona",
    "sg:orig_category":"Galvanizaci\u00d3n, Esta\u00d1ado, Emplomado",
    "sg:phone":"+34 933 49 06 31",
    "sg:postcode":"08027",
    "sg:province":"Barcelona",
    "wof:name":"Auxiliares De Galvanotecnia S. L.",
    "wof:placetype":"venue"
},
  "geometry": {"coordinates":[2.1885459423,41.4215354919],"type":"Point"}
}