{
  "type": "Feature",
  "properties": {
    "iso:country":"ES",
    "sg:address":"Rua Benito Corbal, 26",
    "sg:city":"Pontevedra",
    "sg:classifiers":[
        {
            "category":"Taxi",
            "type":"Transportation"
        }
    ],
    "sg:phone":"+34 986 85 12 00",
    "sg:postcode":"36001",
    "sg:province":"Pontevedra",
    "wof:name":"Taxis Asociacion De Autopatronos Pontevedra Y Municipios De La Provincia",
    "wof:placetype":"venue"
},
  "geometry": {"coordinates":[-8.6410493851,42.4304161072],"type":"Point"}
}