{
  "type": "Feature",
  "properties": {
    "addr:full":"Calle de Sebastian Elcano, 4 Petrer Alicante 03610",
    "addr:housenumber":"4",
    "addr:postcode":"03610",
    "addr:street":"Calle De Sebastian Elcano",
    "iso:country":"ES",
    "sg:address":"Calle de Sebastian Elcano, 4",
    "sg:city":"Petrer",
    "sg:orig_category":"Cl\u00cdnicas M\u00c9dicas",
    "sg:phone":"+34 965 37 20 67",
    "sg:postcode":"03610",
    "sg:province":"Alicante",
    "wof:name":"Iba\u00f1ez Hernandez Miguel Angel",
    "wof:placetype":"venue"
},
  "geometry": {"coordinates":[-0.7857300043,38.4804496765],"type":"Point"}
}