{
  "type": "Feature",
  "properties": {
    "addr:full":"Arriero El, S/n Baeza Ja\u00e9n 23440",
    "addr:postcode":"23440",
    "addr:street":"El S / N;Jae\u0301N",
    "iso:country":"ES",
    "sg:address":"Arriero El, S/n",
    "sg:city":"Baeza",
    "sg:orig_category":"Venta, Instalaci\u00d3n De Calefacci\u00d3n",
    "sg:phone":"+34 953 74 82 01",
    "sg:postcode":"23440",
    "sg:province":"Ja\u00e9n",
    "wof:name":"Garrido Contreras Gines",
    "wof:placetype":"venue"
},
  "geometry": {"coordinates":[-3.4596045017,38.0012245178],"type":"Point"}
}