{
  "type": "Feature",
  "properties": {
    "iso:country":"ES",
    "sg:address":"Rua Nova, 46",
    "sg:city":"Lugo",
    "sg:orig_category":"Electrodom\u00c9sticos (al Por Menor)",
    "sg:phone":"+34 982 24 10 39",
    "sg:postcode":"27001",
    "sg:province":"Lugo",
    "wof:name":"Rodriguez Lopez Consuelo",
    "wof:placetype":"venue"
},
  "geometry": {"coordinates":[-7.5592341423,43.0117683411],"type":"Point"}
}