{
  "type": "Feature",
  "properties": {
    "iso:country":"ES",
    "sg:address":"Calle de Alvaro Gil, 4",
    "sg:city":"Salamanca",
    "sg:orig_category":"Agencias De Viajes",
    "sg:phone":"+34 923 12 12 63",
    "sg:postcode":"37007",
    "sg:province":"Salamanca",
    "wof:name":"Viajes Y Excursiones Nautilus S.l.",
    "wof:placetype":"venue"
},
  "geometry": {"coordinates":[-5.6644473076,40.9700698853],"type":"Point"}
}