{
  "type": "Feature",
  "properties": {
    "addr:full":"Avda Jose Izquierdo, 98 Alquerias Del Ni\u00e7o Perdido Castell\u00f3n 12539",
    "addr:housenumber":"98",
    "addr:postcode":"12539",
    "addr:street":"Avda Jose Izquierdo;Castello\u0301N",
    "iso:country":"ES",
    "sg:address":"Avda Jose Izquierdo, 98",
    "sg:city":"Alquerias Del Ni\u00e7o Perdido",
    "sg:orig_category":"Alimentaci\u00d3n General (al Por Menor)",
    "sg:phone":"+34 964 51 26 97",
    "sg:postcode":"12539",
    "sg:province":"Castell\u00f3n",
    "wof:name":"Martin Gomez Adolfo",
    "wof:placetype":"venue"
},
  "geometry": {"coordinates":[-0.1214139983,39.8971862793],"type":"Point"}
}