{
  "type": "Feature",
  "properties": {
    "addr:full":"Calle de Rodriguez Acosta, 14 Nerja M\u00e1laga 29780",
    "addr:housenumber":"14",
    "addr:postcode":"29780",
    "addr:street":"Calle De Rodriguez Acosta",
    "iso:country":"ES",
    "sg:address":"Calle de Rodriguez Acosta, 14",
    "sg:city":"Nerja",
    "sg:orig_category":"Promotores Constructores",
    "sg:phone":"+34 952 52 17 21",
    "sg:postcode":"29780",
    "sg:province":"M\u00e1laga",
    "wof:name":"Almijara Del Sur S.l.",
    "wof:placetype":"venue"
},
  "geometry": {"coordinates":[-3.873295784,36.7513237],"type":"Point"}
}