{
  "type": "Feature",
  "properties": {
    "iso:country":"ES",
    "sg:address":"Carrer de Retama, 81",
    "sg:city":"Viladecans",
    "sg:orig_category":"Artes Gr\u00c1ficas, Artes Pl\u00c1sticas (curso)",
    "sg:phone":"+34 936 58 70 68",
    "sg:postcode":"08840",
    "sg:province":"Barcelona",
    "wof:name":"Matimpres S.l.",
    "wof:placetype":"venue"
},
  "geometry": {"coordinates":[2.0074698925,41.3203697205],"type":"Point"}
}