{
  "type": "Feature",
  "properties": {
    "iso:country":"ES",
    "sg:address":"Ctra N Ii, Km. 0454,0",
    "sg:city":"Alcarras",
    "sg:orig_category":"Transportes Por V\u00cdas Navegables",
    "sg:phone":"+34 973 79 05 86",
    "sg:postcode":"25180",
    "sg:province":"Lleida",
    "wof:name":"Traler S.l",
    "wof:placetype":"venue"
},
  "geometry": {"coordinates":[0.5282099843,41.5634155273],"type":"Point"}
}