{
  "type": "Feature",
  "properties": {
    "addr:full":"Carrer de Moli, S/n Godall Tarragona 43516",
    "addr:housenumber":"s / n",
    "addr:postcode":"43516",
    "addr:street":"Carrer De Moli",
    "iso:country":"ES",
    "sg:address":"Carrer de Moli, S/n",
    "sg:city":"Godall",
    "sg:orig_category":"Centros De Educaci\u00d3n Especial",
    "sg:phone":"+34 977 73 80 54",
    "sg:postcode":"43516",
    "sg:province":"Tarragona",
    "wof:name":"Ajuntament De Godall",
    "wof:placetype":"venue"
},
  "geometry": {"coordinates":[0.4707373977,40.6564750671],"type":"Point"}
}