{
  "type": "Feature",
  "properties": {
    "iso:country":"ES",
    "sg:address":"Rond Guinardo, 233",
    "sg:city":"Barcelona",
    "sg:orig_category":"Arquitectos",
    "sg:phone":"+34 934 46 11 22",
    "sg:postcode":"08041",
    "sg:province":"Barcelona",
    "wof:name":"Salgado Rajo Juan Manuel",
    "wof:placetype":"venue"
},
  "geometry": {"coordinates":[2.1770989895,41.4224624634],"type":"Point"}
}