{
  "type": "Feature",
  "properties": {
    "addr:full":"Rua Pintor Arximiro Suarez, 2 Noia La Coru\u00f1a 15200",
    "addr:housenumber":"2",
    "addr:postcode":"15200",
    "addr:street":"Rua Pintor Arximiro Suarez;La Corun\u0303A",
    "iso:country":"ES",
    "sg:address":"Rua Pintor Arximiro Suarez, 2",
    "sg:city":"Noia",
    "sg:orig_category":"M\u00c9dicos: Fisioterapia Y Rehabilitaci\u00d3n",
    "sg:phone":"+34 981 82 09 92",
    "sg:postcode":"15200",
    "sg:province":"La Coru\u00f1a",
    "wof:name":"Centro Gallego De Rehabilitacion",
    "wof:placetype":"venue"
},
  "geometry": {"coordinates":[-8.8889379501,42.7879524231],"type":"Point"}
}