{
  "type": "Feature",
  "properties": {
    "addr:full":"Carr Romani, 2 Almussafes Valencia 46440",
    "addr:housenumber":"2",
    "addr:postcode":"46440",
    "addr:street":"Carr Romani",
    "iso:country":"ES",
    "sg:address":"Carr Romani, 2",
    "sg:city":"Almussafes",
    "sg:orig_category":"Frutas Y Legumbres Secas (al Por Mayor)",
    "sg:phone":"+34 961 78 29 14",
    "sg:postcode":"46440",
    "sg:province":"Valencia",
    "wof:name":"Escriba S.l.",
    "wof:placetype":"venue"
},
  "geometry": {"coordinates":[-0.4110679924,39.2963638306],"type":"Point"}
}