{
  "type": "Feature",
  "properties": {
    "addr:full":"Carrer de Font Del Cargol, 48 Torreta Barcelona 08430",
    "addr:housenumber":"48",
    "addr:postcode":"08430",
    "addr:street":"Carrer De Font Del Cargol",
    "iso:country":"ES",
    "sg:address":"Carrer de Font Del Cargol, 48",
    "sg:city":"Torreta",
    "sg:orig_category":"Peluquer\u00cdas, Peluquer\u00cda Mixta",
    "sg:phone":"+34 938 60 62 03",
    "sg:postcode":"08430",
    "sg:province":"Barcelona",
    "wof:name":"Solvez Vega Carmen",
    "wof:placetype":"venue"
},
  "geometry": {"coordinates":[2.301019907,41.6021537781],"type":"Point"}
}