{
  "type": "Feature",
  "properties": {
    "iso:country":"ES",
    "sg:address":"Pase Coso (del), 24",
    "sg:city":"Barbastro",
    "sg:orig_category":"Arquitectos",
    "sg:phone":"+34 974 31 03 19",
    "sg:postcode":"22300",
    "sg:province":"Huesca",
    "sg:website":"www.2carq.com",
    "wof:name":"2c Arquitectos S.c.",
    "wof:placetype":"venue"
},
  "geometry": {"coordinates":[0.13078,42.018711],"type":"Point"}
}