{
  "type": "Feature",
  "properties": {
    "addr:full":"Calle de Santa Lucia, 4 Aranda Duero Burgos 09400",
    "addr:housenumber":"4",
    "addr:postcode":"09400",
    "addr:street":"Calle De Santa Lucia",
    "iso:country":"ES",
    "sg:address":"Calle de Santa Lucia, 4",
    "sg:city":"Aranda Duero",
    "sg:orig_category":"Zapater\u00cdas",
    "sg:phone":"+34 947 51 29 80",
    "sg:postcode":"09400",
    "sg:province":"Burgos",
    "wof:name":"Andarines",
    "wof:placetype":"venue"
},
  "geometry": {"coordinates":[-3.6879608631,41.6702537537],"type":"Point"}
}