{
  "type": "Feature",
  "properties": {
    "iso:country":"ES",
    "sg:address":"Calle de Iparraguirre, 33",
    "sg:city":"Bilbao",
    "sg:orig_category":"Peleter\u00cdas",
    "sg:phone":"+34 944 15 46 11",
    "sg:postcode":"48011",
    "sg:province":"Vizcaya",
    "wof:name":"Gonzalez Arrieta Maria De Los Desamparados",
    "wof:placetype":"venue"
},
  "geometry": {"coordinates":[-2.9368889332,43.2621116638],"type":"Point"}
}