{
  "type": "Feature",
  "properties": {
    "iso:country":"ES",
    "sg:address":"Calle de Garcia De Paredes, 80",
    "sg:city":"Madrid",
    "sg:orig_category":"Ingenier\u00cda, Centros De Estudios (diversos)",
    "sg:phone":"+34 913 19 32 70",
    "sg:postcode":"28010",
    "sg:province":"Madrid",
    "sg:website":"www.tdt-e.com",
    "wof:name":"Td & T Transferencia Y Desarrollo De Tecnologia S.l.",
    "wof:placetype":"venue"
},
  "geometry": {"coordinates":[-3.6933400631,40.4365005493],"type":"Point"}
}