{
  "type": "Feature",
  "properties": {
    "iso:country":"ES",
    "sg:address":"Carr Rutlla, 29",
    "sg:city":"Girona",
    "sg:orig_category":"Molduras, Junquillos, Listones Y Molduras Perforadas",
    "sg:phone":"+34 972 20 02 07",
    "sg:postcode":"17002",
    "sg:province":"Girona",
    "wof:name":"Garcia Tudela Francisco",
    "wof:placetype":"venue"
},
  "geometry": {"coordinates":[2.8231158257,41.9773216248],"type":"Point"}
}