{
  "type": "Feature",
  "properties": {
    "iso:country":"ES",
    "sg:address":"Carrer de Major, 22",
    "sg:city":"Caldes Montbui",
    "sg:orig_category":"M\u00c9dicos: Pediatr\u00cda. Enfermedades De Los Ni\u00d1os",
    "sg:phone":"+34 938 65 03 88",
    "sg:postcode":"08140",
    "sg:province":"Barcelona",
    "wof:name":"Xalabarder Miramanda Eduardo",
    "wof:placetype":"venue"
},
  "geometry": {"coordinates":[2.1636118889,41.632900238],"type":"Point"}
}