{
  "type": "Feature",
  "properties": {
    "addr:full":"Calle de Padre Mendez, 166 Torrent Valencia 46900",
    "addr:housenumber":"166",
    "addr:postcode":"46900",
    "addr:street":"Calle De Padre Mendez;Valencia",
    "iso:country":"ES",
    "sg:address":"Calle de Padre Mendez, 166",
    "sg:city":"Torrent",
    "sg:orig_category":"Farmacias",
    "sg:phone":"+34 961 55 59 71",
    "sg:postcode":"46900",
    "sg:province":"Valencia",
    "wof:name":"Carbonell Fornet Isabel",
    "wof:placetype":"venue"
},
  "geometry": {"coordinates":[-0.477079004,39.4272994995],"type":"Point"}
}