{
  "type": "Feature",
  "properties": {
    "iso:country":"ES",
    "sg:address":"Calle de Arenas, 64",
    "sg:city":"Daimiel",
    "sg:orig_category":"Ense\u00d1anza, Formaci\u00d3n Profesional: Aprendizaje",
    "sg:phone":"+34 926 85 29 99",
    "sg:postcode":"13250",
    "sg:province":"Ciudad Real",
    "wof:name":"Asamblea Suprema De La Cruz Roja Espa\u00d1ola",
    "wof:placetype":"venue"
},
  "geometry": {"coordinates":[-3.6106567383,39.0711898804],"type":"Point"}
}