{
  "type": "Feature",
  "properties": {
    "iso:country":"ES",
    "sg:address":"Calle de Mazarron, Km. 0004,5",
    "sg:city":"Ensanche-almarjal",
    "sg:orig_category":"Mec\u00c1nico Del Autom\u00d3vil",
    "sg:phone":"+34 968 53 57 14",
    "sg:postcode":"30203",
    "sg:province":"Murcia",
    "wof:name":"El Rastro De La Frenada S.l.l.",
    "wof:placetype":"venue"
},
  "geometry": {"coordinates":[-0.9793279767,37.6137199402],"type":"Point"}
}