{
  "type": "Feature",
  "properties": {
    "iso:country":"ES",
    "sg:address":"Ctra. Coru\u00f1a, 18",
    "sg:city":"Collado Villalba",
    "sg:orig_category":"Reposter\u00cdas",
    "sg:phone":"+34 918 50 02 79",
    "sg:postcode":"28400",
    "sg:province":"Madrid",
    "wof:name":"Burguillo Balandin Pablo Ignacio",
    "wof:placetype":"venue"
},
  "geometry": {"coordinates":[-4.0064492226,40.6153297424],"type":"Point"}
}