{
  "type": "Feature",
  "properties": {
    "iso:country":"ES",
    "sg:address":"Carrer de Marques De Cornella, 94",
    "sg:city":"Cornella Llobregat",
    "sg:orig_category":"Adhesivos (fabricaci\u00d3n, Al Por Mayor)",
    "sg:phone":"+34 933 77 01 28",
    "sg:postcode":"08940",
    "sg:province":"Barcelona",
    "sg:website":"www.cintamalla.es",
    "wof:name":"Cintamalla S. A.",
    "wof:placetype":"venue"
},
  "geometry": {"coordinates":[2.0691459179,41.3522529602],"type":"Point"}
}