{
  "type": "Feature",
  "properties": {
    "addr:full":"Carrer de Vendrell, 25 Terrassa Barcelona 08227",
    "addr:housenumber":"25",
    "addr:postcode":"08227",
    "addr:street":"Carrer De Vendrell",
    "iso:country":"ES",
    "sg:address":"Carrer de Vendrell, 25",
    "sg:city":"Terrassa",
    "sg:orig_category":"Reposter\u00cdas",
    "sg:phone":"+34 937 85 32 50",
    "sg:postcode":"08227",
    "sg:province":"Barcelona",
    "wof:name":"Egea Leiva Isabel",
    "wof:placetype":"venue"
},
  "geometry": {"coordinates":[2.0343599319,41.5733184814],"type":"Point"}
}