{
  "type": "Feature",
  "properties": {
    "iso:country":"ES",
    "sg:address":"Mayor, 65",
    "sg:city":"Estella",
    "sg:orig_category":"Estancos",
    "sg:phone":"+34 948 55 03 42",
    "sg:postcode":"31200",
    "sg:province":"Navarra",
    "wof:name":"Garin Caballero Jose Ignacio",
    "wof:placetype":"venue"
},
  "geometry": {"coordinates":[-2.0304999352,42.6710929871],"type":"Point"}
}