{
  "type": "Feature",
  "properties": {
    "addr:full":"Calle de Marques De Albaida, 1 Palencia Palencia 34005",
    "addr:housenumber":"1",
    "addr:postcode":"34005",
    "addr:street":"Calle De Marques De Albaida",
    "iso:country":"ES",
    "sg:address":"Calle de Marques De Albaida, 1",
    "sg:city":"Palencia",
    "sg:orig_category":"M\u00c9dicos: Dermatolog\u00cda Y Venereolog\u00cda",
    "sg:phone":"+34 979 70 16 89",
    "sg:postcode":"34005",
    "sg:province":"Palencia",
    "wof:name":"De Pedro Herrero Maria Teresa",
    "wof:placetype":"venue"
},
  "geometry": {"coordinates":[-4.5327467918,42.0076599121],"type":"Point"}
}