{
  "type": "Feature",
  "properties": {
    "iso:country":"ES",
    "sg:address":"Calle de Moguer, 17",
    "sg:city":"Alcala Guadaira",
    "sg:orig_category":"Ropa Para Se\u00d1oras Y Caballeros (al Por Menor)",
    "sg:phone":"+34 955 68 26 91",
    "sg:postcode":"41500",
    "sg:province":"Sevilla",
    "wof:name":"Bejarano Alcaide Josefa",
    "wof:placetype":"venue"
},
  "geometry": {"coordinates":[-5.8342208862,37.3328285217],"type":"Point"}
}