{
  "type": "Feature",
  "properties": {
    "addr:full":"Calle de Acacia (de La), 4 Cercedilla Madrid 28470",
    "addr:housenumber":"4",
    "addr:postcode":"28470",
    "addr:street":"Calle De Acacia De La",
    "iso:country":"ES",
    "sg:address":"Calle de Acacia (de La), 4",
    "sg:city":"Cercedilla",
    "sg:orig_category":"Fabricaci\u00d3n De Material Y Sistemas De Se\u00d1alizaci\u00d3n De Carreteras, Urbanos Y De Obras",
    "sg:phone":"+34 918 52 23 54",
    "sg:postcode":"28470",
    "sg:province":"Madrid",
    "sg:website":"www.pgbsl.com",
    "wof:name":"P.g.b. Se\u00f1alizacion Urbana S.l.",
    "wof:placetype":"venue"
},
  "geometry": {"coordinates":[-4.0808405876,40.7216873169],"type":"Point"}
}