{
  "type": "Feature",
  "properties": {
    "addr:full":"Calle de Principal De Provincias, S/n Madrid Madrid 28011",
    "addr:housenumber":"s / n",
    "addr:postcode":"28011",
    "addr:street":"Calle De Principal De Provincias",
    "iso:country":"ES",
    "sg:address":"Calle de Principal De Provincias, S/n",
    "sg:city":"Madrid",
    "sg:orig_category":"Bodas Y Casamientos, Organizaci\u00d3n",
    "sg:phone":"+34 914 64 56 56",
    "sg:postcode":"28011",
    "sg:province":"Madrid",
    "wof:name":"Palacio De Mision S.l.",
    "wof:placetype":"venue"
},
  "geometry": {"coordinates":[-3.735503912,40.4138412476],"type":"Point"}
}