{
  "type": "Feature",
  "properties": {
    "iso:country":"ES",
    "sg:address":"Urb Nueva Estebbuna, 73",
    "sg:city":"Estepona",
    "sg:orig_category":"Fabricaci\u00d3n De Ventanas",
    "sg:phone":"+34 952 93 65 26",
    "sg:postcode":"29680",
    "sg:province":"M\u00e1laga",
    "wof:name":"Gomez Guillen Jose Manuel",
    "wof:placetype":"venue"
},
  "geometry": {"coordinates":[-5.1574540138,36.4287147522],"type":"Point"}
}