{
  "type": "Feature",
  "properties": {
    "addr:full":"Calle de Condesa De La Oliva, 8 Almendralejo Badajoz 06200",
    "addr:housenumber":"8",
    "addr:postcode":"06200",
    "addr:street":"Calle De Condesa De La Oliva",
    "iso:country":"ES",
    "sg:address":"Calle de Condesa De La Oliva, 8",
    "sg:city":"Almendralejo",
    "sg:classifiers":[
        {
            "category":"Cinema",
            "subcategory":"Movie Theater",
            "type":"Entertainment"
        }
    ],
    "sg:phone":"+34 924 66 14 97",
    "sg:postcode":"06200",
    "sg:province":"Badajoz",
    "sg:tags":[
        "salas",
        "de",
        "cine"
    ],
    "wof:name":"Villegas Puerto S.l.",
    "wof:placetype":"venue"
},
  "geometry": {"coordinates":[-6.4053268433,38.6760864258],"type":"Point"}
}