{
  "type": "Feature",
  "properties": {
    "iso:country":"ES",
    "sg:address":"Calle de Carmona, 40",
    "sg:city":"Campana",
    "sg:orig_category":"Panader\u00cdas, Panader\u00cdas",
    "sg:phone":"+34 954 19 98 25",
    "sg:postcode":"41429",
    "sg:province":"Sevilla",
    "wof:name":"Haza Romero Antonio De La",
    "wof:placetype":"venue"
},
  "geometry": {"coordinates":[-5.4282107353,37.5692596436],"type":"Point"}
}