{
  "type": "Feature",
  "properties": {
    "addr:full":"Carr Constitucio, 29 Benetusser Valencia 46910",
    "addr:housenumber":"29",
    "addr:postcode":"46910",
    "addr:street":"Carr Constitucio",
    "iso:country":"ES",
    "sg:address":"Carr Constitucio, 29",
    "sg:city":"Benetusser",
    "sg:orig_category":"Productos Qu\u00cdmicos (fabricaci\u00d3n, Al Por Mayor)",
    "sg:phone":"+34 963 96 53 82",
    "sg:postcode":"46910",
    "sg:province":"Valencia",
    "wof:name":"Iberia Ashland Chemical S.a.",
    "wof:placetype":"venue"
},
  "geometry": {"coordinates":[-0.3936280012,39.4223709106],"type":"Point"}
}