{
  "type": "Feature",
  "properties": {
    "addr:full":"Rua Nova, 12 San Luis Pontevedra 36640",
    "addr:housenumber":"12",
    "addr:postcode":"36640",
    "addr:street":"Rua Nova",
    "iso:country":"ES",
    "sg:address":"Rua Nova, 12",
    "sg:city":"San Luis",
    "sg:classifiers":[
        {
            "category":"Taxi",
            "type":"Transportation"
        }
    ],
    "sg:phone":"+34 986 55 74 53",
    "sg:postcode":"36640",
    "sg:province":"Pontevedra",
    "wof:name":"Fontenla Barreiro Maria",
    "wof:placetype":"venue"
},
  "geometry": {"coordinates":[-8.6507349014,42.7232513428],"type":"Point"}
}