{
  "type": "Feature",
  "properties": {
    "addr:full":"Ctra Hospitalet, 370 Almeda Mercader Barcelona 08940",
    "addr:housenumber":"370",
    "addr:postcode":"08940",
    "addr:street":"Ctra Hospitalet;Mercader Barcelona",
    "iso:country":"ES",
    "sg:address":"Ctra Hospitalet, 370",
    "sg:city":"Almeda Mercader",
    "sg:orig_category":"Bancos",
    "sg:phone":"+34 933 77 39 56",
    "sg:postcode":"08940",
    "sg:province":"Barcelona",
    "sg:website":"www.gruposantander.es",
    "wof:name":"Bt Espa\u00d1a Compa\u00d1ia De Servicios Globales De Telecomunicaciones S.a.u.",
    "wof:placetype":"venue"
},
  "geometry": {"coordinates":[2.0708940029,41.3559417725],"type":"Point"}
}