{
  "type": "Feature",
  "properties": {
    "iso:country":"ES",
    "sg:address":"Ptda Llano San Jose, 170",
    "sg:city":"Elche",
    "sg:orig_category":"Agentes, Concesionarios Y Sucursales De Veh\u00cdculos",
    "sg:phone":"+34 965 43 96 00",
    "sg:postcode":"03293",
    "sg:province":"Alicante",
    "wof:name":"Vehiculos Hernandez S.l.",
    "wof:placetype":"venue"
},
  "geometry": {"coordinates":[-0.6995239854,38.2634811401],"type":"Point"}
}