{
  "type": "Feature",
  "properties": {
    "iso:country":"ES",
    "sg:address":"Ma\u00d1e I Flaquer Plaza, 5",
    "sg:city":"Hernani",
    "sg:orig_category":"Molduras, Junquillos, Listones Y Molduras Perforadas",
    "sg:phone":"+34 943 55 59 53",
    "sg:postcode":"20120",
    "sg:province":"Guip\u00f9zcoa",
    "wof:name":"Bar Aldapa",
    "wof:placetype":"venue"
},
  "geometry": {"coordinates":[-1.9728809595,43.2703018188],"type":"Point"}
}