{
  "type": "Feature",
  "properties": {
    "iso:country":"ES",
    "sg:address":"Avda Kansas City, 1",
    "sg:city":"Sevilla",
    "sg:orig_category":"Confecci\u00d3n De Corbatas",
    "sg:phone":"+34 954 53 82 15",
    "sg:postcode":"41018",
    "sg:province":"Sevilla",
    "wof:name":"The Tie Gallery Espa\u00f1a S.a.",
    "wof:placetype":"venue"
},
  "geometry": {"coordinates":[-5.9744081497,37.3893890381],"type":"Point"}
}