{
  "type": "Feature",
  "properties": {
    "iso:country":"ES",
    "sg:address":"Avda Monta\u00d1ana, 678",
    "sg:city":"Monta\u00d1ana",
    "sg:orig_category":"Motores De Gasolina",
    "sg:phone":"+34 976 57 57 67",
    "sg:postcode":"50059",
    "sg:province":"Zaragoza",
    "wof:name":"Loma E Hijos S.l.",
    "wof:placetype":"venue"
},
  "geometry": {"coordinates":[-0.821129024,41.6935806274],"type":"Point"}
}