{
  "type": "Feature",
  "properties": {
    "addr:full":"Calle de Carlos Picabea, 2 Torrelodones Madrid 28250",
    "addr:housenumber":"2",
    "addr:postcode":"28250",
    "addr:street":"Calle De Carlos Picabea",
    "iso:country":"ES",
    "sg:address":"Calle de Carlos Picabea, 2",
    "sg:city":"Torrelodones",
    "sg:orig_category":"Ropa Y Art\u00cdculos Pre",
    "sg:phone":"+34 918 59 22 48",
    "sg:postcode":"28250",
    "sg:province":"Madrid",
    "wof:name":"Servus Bebes S.l.",
    "wof:placetype":"venue"
},
  "geometry": {"coordinates":[-3.9296770096,40.5765647888],"type":"Point"}
}