{
  "type": "Feature",
  "properties": {
    "addr:full":"Apeadeiro, 1 Cambre La Coru\u00f1a 15650",
    "addr:housenumber":"1",
    "addr:postcode":"15650",
    "addr:street":"Apeadeiro;La Corun\u0303A",
    "iso:country":"ES",
    "sg:address":"Apeadeiro, 1",
    "sg:city":"Cambre",
    "sg:orig_category":"Molduras, Junquillos, Listones Y Molduras Perforadas",
    "sg:phone":"+34 981 67 60 41",
    "sg:postcode":"15650",
    "sg:province":"La Coru\u00f1a",
    "wof:name":"Sanchez Gomez Jose",
    "wof:placetype":"venue"
},
  "geometry": {"coordinates":[-8.3069343567,43.2885551453],"type":"Point"}
}