{
  "type": "Feature",
  "properties": {
    "iso:country":"ES",
    "sg:address":"Carrer de Nuno San\u00c7, 11",
    "sg:city":"Palma",
    "sg:orig_category":"Reparaci\u00d3n Y Restauraci\u00d3n De Objetos Diversos",
    "sg:phone":"+34 971 24 14 95",
    "sg:postcode":"07005",
    "sg:province":"Islas Baleares",
    "wof:name":"Rubi Riera Miguel",
    "wof:placetype":"venue"
},
  "geometry": {"coordinates":[2.6603999138,39.5791244507],"type":"Point"}
}