{
  "type": "Feature",
  "properties": {
    "iso:country":"ES",
    "sg:address":"Calle de Muela (la), S/n",
    "sg:city":"Seron Nagima",
    "sg:orig_category":"Cr\u00cda De Animales",
    "sg:phone":"+34 975 30 70 65",
    "sg:postcode":"42127",
    "sg:province":"Soria",
    "wof:name":"Mu\u00f1oz Remacha Hermanos S.l.",
    "wof:placetype":"venue"
},
  "geometry": {"coordinates":[-2.2036440372,41.49609375],"type":"Point"}
}