{
  "type": "Feature",
  "properties": {
    "iso:country":"ES",
    "sg:address":"Carrer de Ramon Llull, 19",
    "sg:city":"Granollers",
    "sg:orig_category":"Muebles, Minoristas",
    "sg:phone":"+34 938 40 22 09",
    "sg:postcode":"08401",
    "sg:province":"Barcelona",
    "wof:name":"Azul Mobiliario Actual S.l.",
    "wof:placetype":"venue"
},
  "geometry": {"coordinates":[2.2883501053,41.6137466431],"type":"Point"}
}