{
  "type": "Feature",
  "properties": {
    "iso:country":"ES",
    "sg:address":"Calle de Fuente (la), 4",
    "sg:city":"Olabarri",
    "sg:orig_category":"Agricultores, Agricultores",
    "sg:phone":"+34 945 37 10 58",
    "sg:postcode":"01428",
    "sg:province":"\u00c1lava",
    "wof:name":"Ribatxentxa S.l.",
    "wof:placetype":"venue"
},
  "geometry": {"coordinates":[-2.8369209766,42.8172035217],"type":"Point"}
}