{
  "type": "Feature",
  "properties": {
    "addr:full":"Av Catalunya, 38 S. Antoni Vilamajor Barcelona 08459",
    "addr:housenumber":"38",
    "addr:postcode":"08459",
    "addr:street":"Av Catalunya",
    "iso:country":"ES",
    "sg:address":"Av Catalunya, 38",
    "sg:city":"S. Antoni Vilamajor",
    "sg:orig_category":"\u00d3ptica: Instrumentos (fabricaci\u00d3n)",
    "sg:phone":"+34 938 45 19 24",
    "sg:postcode":"08459",
    "sg:province":"Barcelona",
    "wof:name":"Look Uno S.l.",
    "wof:placetype":"venue"
},
  "geometry": {"coordinates":[2.3954401016,41.6741600037],"type":"Point"}
}