{
  "type": "Feature",
  "properties": {
    "addr:full":"Calle de Escuelas (las), 25 Rincon De Olivedo O Las Casas La Rioja 26527",
    "addr:housenumber":"25",
    "addr:postcode":"26527",
    "addr:street":"Calle De Escuelas Las;Casas;Rioja",
    "iso:country":"ES",
    "sg:address":"Calle de Escuelas (las), 25",
    "sg:city":"Rincon De Olivedo O Las Casas",
    "sg:orig_category":"Institutos De Belleza",
    "sg:phone":"+34 941 17 56 40",
    "sg:postcode":"26527",
    "sg:province":"La Rioja",
    "wof:name":"Gil De Gomez Diez Esther",
    "wof:placetype":"venue"
},
  "geometry": {"coordinates":[-1.9673190117,42.0512390137],"type":"Point"}
}