{
  "type": "Feature",
  "properties": {
    "iso:country":"ES",
    "sg:address":"Calle de Augusto Figueroa, 1",
    "sg:city":"Madrid",
    "sg:orig_category":"Ropa Para Caballeros (al Por Menor)",
    "sg:phone":"+34 915 22 73 27",
    "sg:postcode":"28004",
    "sg:province":"Madrid",
    "wof:name":"Puglisi  Roberto",
    "wof:placetype":"venue"
},
  "geometry": {"coordinates":[-3.700605154,40.4230651855],"type":"Point"}
}