{
  "type": "Feature",
  "properties": {
    "iso:country":"ES",
    "sg:address":"Avda Europa, 43",
    "sg:city":"Vigo",
    "sg:orig_category":"Restaurantes",
    "sg:phone":"+34 986 24 12 96",
    "sg:postcode":"36209",
    "sg:province":"Pontevedra",
    "wof:name":"Restaurante Avenida De Samil S.l.",
    "wof:placetype":"venue"
},
  "geometry": {"coordinates":[-8.7644453049,42.2130470276],"type":"Point"}
}