{
  "type": "Feature",
  "properties": {
    "addr:full":"Calle de Sanchidrian, 8 Pozuelo De Alarcon Madrid 28224",
    "addr:housenumber":"8",
    "addr:postcode":"28224",
    "addr:street":"Calle De Sanchidrian",
    "iso:country":"ES",
    "sg:address":"Calle de Sanchidrian, 8",
    "sg:city":"Pozuelo De Alarcon",
    "sg:orig_category":"Ingeniero",
    "sg:phone":"+34 913 52 63 68",
    "sg:postcode":"28224",
    "sg:province":"Madrid",
    "wof:name":"Antolin Baigorri Jose Maria",
    "wof:placetype":"venue"
},
  "geometry": {"coordinates":[-3.8052697182,40.4509048462],"type":"Point"}
}