{
  "type": "Feature",
  "properties": {
    "iso:country":"ES",
    "sg:address":"Ctra Mahamud, S/n",
    "sg:city":"Villahoz",
    "sg:orig_category":"Cr\u00cda De Animales",
    "sg:phone":"+34 947 18 64 05",
    "sg:postcode":"09343",
    "sg:province":"Burgos",
    "wof:name":"Ganados Villahoz S.l.",
    "wof:placetype":"venue"
},
  "geometry": {"coordinates":[-3.9125440121,42.0762443542],"type":"Point"}
}