{
  "type": "Feature",
  "properties": {
    "addr:full":"Calle de Dean Campos Moro, 4 Cumbres Mayores Huelva 21380",
    "addr:housenumber":"4",
    "addr:postcode":"21380",
    "addr:street":"Calle De Dean Campos Moro",
    "iso:country":"ES",
    "sg:address":"Calle de Dean Campos Moro, 4",
    "sg:city":"Cumbres Mayores",
    "sg:orig_category":"Electrodom\u00c9sticos (fabricaci\u00d3n, Al Por Mayor)",
    "sg:phone":"+34 959 71 00 54",
    "sg:postcode":"21380",
    "sg:province":"Huelva",
    "wof:name":"Nuevo Rio De Oro S.l.",
    "wof:placetype":"venue"
},
  "geometry": {"coordinates":[-6.6446709633,38.0629425049],"type":"Point"}
}