{
  "type": "Feature",
  "properties": {
    "addr:full":"Calle de Alberto Aguilera, 7 Madrid Madrid 28015",
    "addr:housenumber":"7",
    "addr:postcode":"madrid;28015",
    "addr:street":"Calle De Alberto Aguilera",
    "iso:country":"ES",
    "sg:address":"Calle de Alberto Aguilera, 7",
    "sg:city":"Madrid",
    "sg:orig_category":"Inform\u00c1tica (estudios, Servicios, Asesor\u00cda, Formaci\u00d3n)",
    "sg:phone":"+34 915 91 27 21",
    "sg:postcode":"28015",
    "sg:province":"Madrid",
    "sg:website":"www.spoc.com",
    "wof:name":"Soluciones Y Plataformas Orientadas Al Conocimiento S.l.",
    "wof:placetype":"venue"
},
  "geometry": {"coordinates":[-3.7082593441,40.429775238],"type":"Point"}
}