{
  "type": "Feature",
  "properties": {
    "addr:full":"Calle de Torrecilla, 5 Valdepe\u00f1as Ciudad Real 13300",
    "addr:housenumber":"5",
    "addr:postcode":"13300",
    "addr:street":"Calle De Torrecilla",
    "iso:country":"ES",
    "sg:address":"Calle de Torrecilla, 5",
    "sg:city":"Valdepe\u00f1as",
    "sg:orig_category":"Artes Gr\u00c1ficas, Artes Pl\u00c1sticas (curso)",
    "sg:phone":"+34 926 32 45 08",
    "sg:postcode":"13300",
    "sg:province":"Ciudad Real",
    "wof:name":"Graficos C.b.",
    "wof:placetype":"venue"
},
  "geometry": {"coordinates":[-3.3838889599,38.7621574402],"type":"Point"}
}