{
  "type": "Feature",
  "properties": {
    "addr:full":"Rua Estrada, 1 Vigo Pontevedra 36209",
    "addr:housenumber":"1",
    "addr:postcode":"36209",
    "addr:street":"Rua Estrada",
    "iso:country":"ES",
    "sg:address":"Rua Estrada, 1",
    "sg:city":"Vigo",
    "sg:orig_category":"Peluqueros: De Se\u00d1oras",
    "sg:phone":"+34 986 20 51 69",
    "sg:postcode":"36209",
    "sg:province":"Pontevedra",
    "wof:name":"Guillan Gonzalez Carmen",
    "wof:placetype":"venue"
},
  "geometry": {"coordinates":[-8.7391691208,42.2205314636],"type":"Point"}
}