{
  "type": "Feature",
  "properties": {
    "iso:country":"ES",
    "sg:address":"Calle de Juan Florez, 30",
    "sg:city":"Coru\u00d1a",
    "sg:orig_category":"Librer\u00cdas",
    "sg:phone":"+34 981 26 14 44",
    "sg:postcode":"15004",
    "sg:province":"A Coru\u00f1a",
    "wof:name":"Sociedad Anonima De Distribucion Edicion Y Librerias",
    "wof:placetype":"venue"
},
  "geometry": {"coordinates":[-8.4085016251,43.3653411865],"type":"Point"}
}