{
  "type": "Feature",
  "properties": {
    "iso:country":"ES",
    "sg:address":"Carrer de Sant Antoni, 3",
    "sg:city":"Cardedeu",
    "sg:orig_category":"Confiter\u00cdas, Chocolater\u00cdas (al Por Menor)",
    "sg:phone":"+34 938 45 45 93",
    "sg:postcode":"08440",
    "sg:province":"Barcelona",
    "wof:name":"Rojas Dupin Flavio Blas",
    "wof:placetype":"venue"
},
  "geometry": {"coordinates":[2.3558270931,41.6378707886],"type":"Point"}
}