{
  "type": "Feature",
  "properties": {
    "iso:country":"ES",
    "sg:address":"Calle de San Bartolome, 128",
    "sg:city":"Torredelcampo",
    "sg:orig_category":"Negocio De Materiales De Construcci\u00d3n",
    "sg:phone":"+34 953 41 59 10",
    "sg:postcode":"23640",
    "sg:province":"Ja\u00e9n",
    "wof:name":"La Catalana Derivados Del Cemento S.l.",
    "wof:placetype":"venue"
},
  "geometry": {"coordinates":[-3.9027280807,37.7714309692],"type":"Point"}
}