{
  "type": "Feature",
  "properties": {
    "addr:full":"Calle de San Ildefonso, 49 Utiel Valencia 46300",
    "addr:housenumber":"49",
    "addr:postcode":"46300",
    "addr:street":"Calle De San Ildefonso",
    "iso:country":"ES",
    "sg:address":"Calle de San Ildefonso, 49",
    "sg:city":"Utiel",
    "sg:orig_category":"Comercio, Reparaci\u00d3n De Motocicletas, Bicicletas Y Piezas Sueltas",
    "sg:phone":"+34 962 17 02 63",
    "sg:postcode":"46300",
    "sg:province":"Valencia",
    "wof:name":"Viana Andres Jose",
    "wof:placetype":"venue"
},
  "geometry": {"coordinates":[-1.2002780437,39.5657691956],"type":"Point"}
}