{
  "type": "Feature",
  "properties": {
    "addr:full":"Avda Navarra, 45 Zaragoza Zaragoza 50010",
    "addr:housenumber":"45",
    "addr:postcode":"50010",
    "addr:street":"Avda Navarra",
    "iso:country":"ES",
    "sg:address":"Avda Navarra, 45",
    "sg:city":"Zaragoza",
    "sg:orig_category":"Carnicer\u00cdas, Carnicer\u00cdas",
    "sg:phone":"+34 976 33 31 66",
    "sg:postcode":"50010",
    "sg:province":"Zaragoza",
    "wof:name":"Martin Gay Serafin",
    "wof:placetype":"venue"
},
  "geometry": {"coordinates":[-0.9050220251,41.6549797058],"type":"Point"}
}