{
  "type": "Feature",
  "properties": {
    "iso:country":"ES",
    "sg:address":"Calle de Virgen De Los Dolores, 39",
    "sg:city":"Umbrete",
    "sg:orig_category":"T\u00c9cnicos Veterinarios",
    "sg:phone":"+34 955 71 57 06",
    "sg:postcode":"41806",
    "sg:province":"Sevilla",
    "wof:name":"Jimenez Lopez Manuel",
    "wof:placetype":"venue"
},
  "geometry": {"coordinates":[-6.1528091431,37.3684654236],"type":"Point"}
}