{
  "type": "Feature",
  "properties": {
    "iso:country":"ES",
    "sg:address":"Calle de San Lorenzo, 5",
    "sg:city":"Valladolid",
    "sg:orig_category":"Molduras, Junquillos, Listones Y Molduras Perforadas",
    "sg:phone":"+34 983 33 07 58",
    "sg:postcode":"47001",
    "sg:province":"Valladolid",
    "wof:name":"Garcia Francisco Francisca",
    "wof:placetype":"venue"
},
  "geometry": {"coordinates":[-4.7314190865,41.6522331238],"type":"Point"}
}