{
  "type": "Feature",
  "properties": {
    "addr:full":"Plaz Espa\u00d1a, 45 Fuente-alamo Albacete 02651",
    "addr:housenumber":"45",
    "addr:postcode":"02651",
    "addr:street":"Plaz Espan\u0303A",
    "iso:country":"ES",
    "sg:address":"Plaz Espa\u00d1a, 45",
    "sg:city":"Fuente-alamo",
    "sg:orig_category":"Cajas Para Embalar",
    "sg:phone":"+34 967 32 12 90",
    "sg:postcode":"02651",
    "sg:province":"Albacete",
    "wof:name":"Caja Rural De Albacete",
    "wof:placetype":"venue"
},
  "geometry": {"coordinates":[-1.4333479404,38.6902923584],"type":"Point"}
}