{
  "type": "Feature",
  "properties": {
    "iso:country":"ES",
    "sg:address":"Calle de Apodaca, 4",
    "sg:city":"Madrid",
    "sg:orig_category":"Art\u00cdculos De Regalo (al Por Menor)",
    "sg:phone":"+34 915 22 83 43",
    "sg:postcode":"28004",
    "sg:province":"Madrid",
    "wof:name":"La Tienda Del Peregil S.l.l.",
    "wof:placetype":"venue"
},
  "geometry": {"coordinates":[-3.7013664246,40.4272460938],"type":"Point"}
}