{
  "type": "Feature",
  "properties": {
    "addr:full":"Calle de Antonio Torrero, 1 Alcala Guadaira Sevilla 41500",
    "addr:housenumber":"1",
    "addr:postcode":"41500",
    "addr:street":"Calle De Antonio Torrero",
    "iso:country":"ES",
    "sg:address":"Calle de Antonio Torrero, 1",
    "sg:city":"Alcala Guadaira",
    "sg:orig_category":"Notarios",
    "sg:phone":"+34 955 68 19 68",
    "sg:postcode":"41500",
    "sg:province":"Sevilla",
    "wof:name":"Morales Lozano Rafael",
    "wof:placetype":"venue"
},
  "geometry": {"coordinates":[-5.8419604301,37.3383712769],"type":"Point"}
}