{
  "type": "Feature",
  "properties": {
    "addr:full":"Av Ramon I Cajal, 57 Tarragona Tarragona 43005",
    "addr:housenumber":"57",
    "addr:postcode":"43005",
    "addr:street":"Av Ramon I Cajal",
    "iso:country":"ES",
    "sg:address":"Av Ramon I Cajal, 57",
    "sg:city":"Tarragona",
    "sg:orig_category":"Partidos Pol\u00cdticos",
    "sg:phone":"+34 977 23 64 16",
    "sg:postcode":"43005",
    "sg:province":"Tarragona",
    "wof:name":"Partit Dels Socialistes De Catalunya",
    "wof:placetype":"venue"
},
  "geometry": {"coordinates":[1.2420749664,41.116230011],"type":"Point"}
}