{
  "type": "Feature",
  "properties": {
    "iso:country":"ES",
    "sg:address":"Labeaga Kalea, 14",
    "sg:city":"Urretxu",
    "sg:orig_category":"Carnicer\u00cdas, Carnicer\u00cdas",
    "sg:phone":"+34 943 03 65 08",
    "sg:postcode":"20700",
    "sg:province":"Guip\u00f9zcoa",
    "wof:name":"Jose Esteban Insausti Irastorza",
    "wof:placetype":"venue"
},
  "geometry": {"coordinates":[-2.3156120777,43.0913352966],"type":"Point"}
}