{
  "type": "Feature",
  "properties": {
    "iso:country":"ES",
    "sg:address":"Calle de Lopez Urraca, 17",
    "sg:city":"Almunia De Do\u00e7a Godina",
    "sg:orig_category":"Farmacias",
    "sg:phone":"+34 976 81 30 48",
    "sg:postcode":"50100",
    "sg:province":"Zaragoza",
    "wof:name":"Farmacia Alvarez-ugena Vicente C.b.",
    "wof:placetype":"venue"
},
  "geometry": {"coordinates":[-1.3740489483,41.4770965576],"type":"Point"}
}