{
  "type": "Feature",
  "properties": {
    "addr:full":"Ctra Madrid-lisboa, Km. 0169,6 Navalmoral Mata C\u00e1ceres 10300",
    "addr:postcode":"10300",
    "addr:street":"Ctra Madrid-Lisboa Km. 0169,6;Ca\u0301Ceres",
    "iso:country":"ES",
    "sg:address":"Ctra Madrid-lisboa, Km. 0169,6",
    "sg:city":"Navalmoral Mata",
    "sg:orig_category":"Persianas Interiores, Exteriores",
    "sg:phone":"+34 927 53 54 83",
    "sg:postcode":"10300",
    "sg:province":"C\u00e1ceres",
    "wof:name":"Toldos Blazquez S.l.",
    "wof:placetype":"venue"
},
  "geometry": {"coordinates":[-5.5375142097,39.8904418945],"type":"Point"}
}