{
  "type": "Feature",
  "properties": {
    "addr:full":"Avda Doctor Artero Guirao, 124 S. Pedro Pinatar Murcia 30740",
    "addr:housenumber":"124",
    "addr:postcode":"30740",
    "addr:street":"Avda Doctor Artero Guirao",
    "iso:country":"ES",
    "sg:address":"Avda Doctor Artero Guirao, 124",
    "sg:city":"S. Pedro Pinatar",
    "sg:orig_category":"Tiendas De Grano, Frutas Y Legumbres Secas (al Por Menor)",
    "sg:phone":"+34 968 18 09 13",
    "sg:postcode":"30740",
    "sg:province":"Murcia",
    "wof:name":"Ferrer Saez Maria Carmen",
    "wof:placetype":"venue"
},
  "geometry": {"coordinates":[-0.7921950221,37.8349876404],"type":"Point"}
}