{
  "type": "Feature",
  "properties": {
    "addr:full":"Pase Santo Tomas (de), 10 Avila \u00c1vila 05003",
    "addr:postcode":"05003",
    "addr:street":"A\u0301Vila",
    "iso:country":"ES",
    "sg:address":"Pase Santo Tomas (de), 10",
    "sg:city":"Avila",
    "sg:orig_category":"Promotores Constructores",
    "sg:phone":"+34 920 25 64 33",
    "sg:postcode":"05003",
    "sg:province":"\u00c1vila",
    "wof:name":"Construcciones Faustino Esteban S.a.",
    "wof:placetype":"venue"
},
  "geometry": {"coordinates":[-4.6925787926,40.6530342102],"type":"Point"}
}