{
  "type": "Feature",
  "properties": {
    "addr:full":"Rua Tinde, 11 Tinde Pontevedra 36379",
    "addr:housenumber":"11",
    "addr:postcode":"36379",
    "addr:street":"Rua Tinde",
    "iso:country":"ES",
    "sg:address":"Rua Tinde, 11",
    "sg:city":"Tinde",
    "sg:orig_category":"Quincaller\u00cda (al Por Menor)",
    "sg:phone":"+34 986 35 11 51",
    "sg:postcode":"36379",
    "sg:province":"Pontevedra",
    "wof:name":"Ca\u00f1as Y Gomez S.l",
    "wof:placetype":"venue"
},
  "geometry": {"coordinates":[-8.8124990463,42.1194648743],"type":"Point"}
}