{
  "type": "Feature",
  "properties": {
    "addr:full":"Rua Ensino (do), S/n Ourense Ourense 32002",
    "addr:housenumber":"s",
    "addr:postcode":"32002",
    "addr:street":"Rua Ensino;/ N",
    "iso:country":"ES",
    "sg:address":"Rua Ensino (do), S/n",
    "sg:city":"Ourense",
    "sg:orig_category":"Maquinaria Para Industrias Diversas",
    "sg:phone":"+34 988 23 43 88",
    "sg:postcode":"32002",
    "sg:province":"Ourense",
    "wof:name":"Carracedo Asfaltico S.l.",
    "wof:placetype":"venue"
},
  "geometry": {"coordinates":[-7.8703041077,42.3408355713],"type":"Point"}
}