{
  "type": "Feature",
  "properties": {
    "iso:country":"ES",
    "sg:address":"Rua Ramon Pi\u00d1eiro (de), 10",
    "sg:city":"Santiago De Compostela",
    "sg:orig_category":"Centros P\u00dablicos De Formaci\u00d3n Profesional Y T\u00c9cnica",
    "sg:phone":"+34 981 59 58 98",
    "sg:postcode":"15702",
    "sg:province":"La Coru\u00f1a",
    "sg:website":"www.coag.es",
    "wof:name":"Colegio Oficial De Arquitectos De Galicia",
    "wof:placetype":"venue"
},
  "geometry": {"coordinates":[-8.5423612595,42.8736343384],"type":"Point"}
}