{
  "type": "Feature",
  "properties": {
    "addr:full":"Tran Merce (da), 1 Santiago De Compostela La Coru\u00f1a 15703",
    "addr:postcode":"15703",
    "addr:street":"Corun\u0303A",
    "iso:country":"ES",
    "sg:address":"Tran Merce (da), 1",
    "sg:city":"Santiago De Compostela",
    "sg:orig_category":"Comunidades Religiosas",
    "sg:phone":"+34 981 56 44 10",
    "sg:postcode":"15703",
    "sg:province":"La Coru\u00f1a",
    "wof:name":"Arzobispado De Santiago",
    "wof:placetype":"venue"
},
  "geometry": {"coordinates":[-8.5240430832,42.8899269104],"type":"Point"}
}