{
  "type": "Feature",
  "properties": {
    "iso:country":"ES",
    "sg:address":"Calle de Baja, 10",
    "sg:city":"Montillana",
    "sg:orig_category":"Carnicer\u00cdas, Carnicer\u00cdas",
    "sg:phone":"+34 958 39 21 81",
    "sg:postcode":"18566",
    "sg:province":"Granada",
    "wof:name":"Ruano Camara Juan",
    "wof:placetype":"venue"
},
  "geometry": {"coordinates":[-3.6723332405,37.50233078],"type":"Point"}
}