{
  "type": "Feature",
  "properties": {
    "addr:full":"Carrer de Sant Ramon, 41 Campello Alicante 03560",
    "addr:housenumber":"41",
    "addr:postcode":"03560",
    "addr:street":"Carrer De Sant Ramon",
    "iso:country":"ES",
    "sg:address":"Carrer de Sant Ramon, 41",
    "sg:city":"Campello",
    "sg:orig_category":"Alimentaci\u00d3n Animal (fabricaci\u00d3n, Al Por Mayor)",
    "sg:phone":"+34 965 63 34 11",
    "sg:postcode":"03560",
    "sg:province":"Alicante",
    "wof:name":"Espla Giner Adriana",
    "wof:placetype":"venue"
},
  "geometry": {"coordinates":[-0.4032639861,38.4274406433],"type":"Point"}
}