{
  "type": "Feature",
  "properties": {
    "iso:country":"ES",
    "sg:address":"Carr Mallorquines, 70",
    "sg:city":"Urbanitzacio Mallorquines",
    "sg:classifiers":[
        {
            "category":"Personal",
            "subcategory":"Barber",
            "type":"Services"
        }
    ],
    "sg:phone":"+34 972 85 31 19",
    "sg:postcode":"17410",
    "sg:province":"Girona",
    "sg:tags":[
        "caballeros",
        "de",
        "peluqueros"
    ],
    "wof:name":"Call Morell Emilio",
    "wof:placetype":"venue"
},
  "geometry": {"coordinates":[2.745290041,41.8085403442],"type":"Point"}
}