{
  "type": "Feature",
  "properties": {
    "addr:full":"Avda Iparraguirre(ed Cantabrico), 59 Santurtzi Vizcaya 48980",
    "addr:housenumber":"59",
    "addr:postcode":"48980",
    "addr:street":"Avda Iparraguirre Ed Cantabrico",
    "iso:country":"ES",
    "sg:address":"Avda Iparraguirre(ed Cantabrico), 59",
    "sg:city":"Santurtzi",
    "sg:orig_category":"Asesor\u00cda Para La Organizaci\u00d3n Y Gesti\u00d3n Del Transporte",
    "sg:phone":"+34 944 83 91 50",
    "sg:postcode":"48980",
    "sg:province":"Vizcaya",
    "wof:name":"Bizkaitrans S.l.",
    "wof:placetype":"venue"
},
  "geometry": {"coordinates":[-3.0402920246,43.3344573975],"type":"Point"}
}