{
  "type": "Feature",
  "properties": {
    "addr:full":"Av Josep Tarradellas, 19 Barcelona Barcelona 08029",
    "addr:housenumber":"19",
    "addr:postcode":"08029",
    "addr:street":"Av Josep Tarradellas",
    "iso:country":"ES",
    "sg:address":"Av Josep Tarradellas, 19",
    "sg:city":"Barcelona",
    "sg:orig_category":"M\u00c9dicos: Cardiolog\u00cda Y Afecciones Cardiovasculares",
    "sg:phone":"+34 934 39 02 38",
    "sg:postcode":"08029",
    "sg:province":"Barcelona",
    "wof:name":"Torres Torres Enrique",
    "wof:placetype":"venue"
},
  "geometry": {"coordinates":[2.1420409679,41.3821411133],"type":"Point"}
}