{
  "type": "Feature",
  "properties": {
    "addr:full":"C.n. Paterna, 126 Benimamet-beniferri Valencia 46035",
    "addr:housenumber":"126",
    "addr:postcode":"46035",
    "addr:street":"Paterna",
    "iso:country":"ES",
    "sg:address":"C.n. Paterna, 126",
    "sg:city":"Benimamet-beniferri",
    "sg:orig_category":"Alumbrados",
    "sg:phone":"+34 963 90 06 01",
    "sg:postcode":"46035",
    "sg:province":"Valencia",
    "wof:name":"Iluminaciones Folgado S.l.",
    "wof:placetype":"venue"
},
  "geometry": {"coordinates":[-0.4190289974,39.5016059875],"type":"Point"}
}