{
  "type": "Feature",
  "properties": {
    "iso:country":"ES",
    "sg:address":"Av. Franca, 115",
    "sg:city":"Sarria Ter",
    "sg:orig_category":"Muebles, Minoristas",
    "sg:phone":"+34 972 17 13 09",
    "sg:postcode":"17840",
    "sg:province":"Girona",
    "sg:website":"www.marcmagenti.com",
    "wof:name":"M. Magenti S.l.",
    "wof:placetype":"venue"
},
  "geometry": {"coordinates":[2.8208498955,42.0173606873],"type":"Point"}
}