{
  "type": "Feature",
  "properties": {
    "addr:full":"Primera Trva Dtor Zunzunegui, 14 Salceda Caselas Pontevedra 36470",
    "addr:housenumber":"14",
    "addr:postcode":"36470",
    "addr:street":"Trva Dtor Zunzunegui",
    "iso:country":"ES",
    "sg:address":"Primera Trva Dtor Zunzunegui, 14",
    "sg:city":"Salceda Caselas",
    "sg:orig_category":"Caf\u00c9s, Bares, Cervecer\u00cdas",
    "sg:phone":"+34 986 34 91 44",
    "sg:postcode":"36470",
    "sg:province":"Pontevedra",
    "wof:name":"Cafeteria Tips S.l.",
    "wof:placetype":"venue"
},
  "geometry": {"coordinates":[-8.5589160919,42.101108551],"type":"Point"}
}