{
  "type": "Feature",
  "properties": {
    "addr:full":"Pumari\u00f1o, 4 Pumari\u00d1o Pontevedra 36158",
    "addr:housenumber":"4",
    "addr:postcode":"36158",
    "addr:street":"Pumarin\u0303O",
    "iso:country":"ES",
    "sg:address":"Pumari\u00f1o, 4",
    "sg:city":"Pumari\u00d1o",
    "sg:orig_category":"M\u00c1quinas Y Herramientas Para Trabajar La Piedra",
    "sg:phone":"+34 986 84 76 07",
    "sg:postcode":"36158",
    "sg:province":"Pontevedra",
    "wof:name":"Canteiros J. Garcia Gonzalez S.l.",
    "wof:placetype":"venue"
},
  "geometry": {"coordinates":[-8.601433754,42.4093666077],"type":"Point"}
}