{
  "type": "Feature",
  "properties": {
    "addr:full":"Plaz San Antonio, 1 Villasana Mena Burgos 09580",
    "addr:housenumber":"1",
    "addr:postcode":"09580",
    "addr:street":"Plaz San Antonio;Villasana Mena",
    "iso:country":"ES",
    "sg:address":"Plaz San Antonio, 1",
    "sg:city":"Villasana Mena",
    "sg:orig_category":"Peluquer\u00cdas, Peluquer\u00cda Mixta",
    "sg:phone":"+34 947 14 12 11",
    "sg:postcode":"09580",
    "sg:province":"Burgos",
    "wof:name":"Gutierrez Villa Marta",
    "wof:placetype":"venue"
},
  "geometry": {"coordinates":[-3.2866690159,43.0996284485],"type":"Point"}
}