{
  "type": "Feature",
  "properties": {
    "addr:full":"Calle de Valencia De Don Juan, 4 Fuenlabrada Madrid 28947",
    "addr:housenumber":"4",
    "addr:postcode":"28947",
    "addr:street":"Calle De Valencia De Don Juan",
    "iso:country":"ES",
    "sg:address":"Calle de Valencia De Don Juan, 4",
    "sg:city":"Fuenlabrada",
    "sg:orig_category":"Transportes Por Carretera: Lotes Completos, Mercanc\u00cdas Diversas",
    "sg:phone":"+34 916 42 16 97",
    "sg:postcode":"28947",
    "sg:province":"Madrid",
    "wof:name":"Distribuciones Esteso S.a.",
    "wof:placetype":"venue"
},
  "geometry": {"coordinates":[-3.7489058971,40.2525978088],"type":"Point"}
}