{
  "type": "Feature",
  "properties": {
    "iso:country":"ES",
    "sg:address":"Calle de Pardo Bazan, 50",
    "sg:city":"Madrid",
    "sg:orig_category":"Inmobiliaria (agencias)",
    "sg:phone":"+34 914 13 85 63",
    "sg:postcode":"28016",
    "sg:province":"Madrid",
    "wof:name":"Boj Promociones Inmobiliarias G.u. S.l.",
    "wof:placetype":"venue"
},
  "geometry": {"coordinates":[-3.6699299812,40.4527740479],"type":"Point"}
}