{
  "type": "Feature",
  "properties": {
    "addr:full":"Calle de Josep Maria Llopico, 36 Alzira Valencia 46600",
    "addr:housenumber":"36",
    "addr:postcode":"46600",
    "addr:street":"Calle De Josep Maria Llopico",
    "iso:country":"ES",
    "sg:address":"Calle de Josep Maria Llopico, 36",
    "sg:city":"Alzira",
    "sg:orig_category":"Persianas Interiores, Exteriores",
    "sg:phone":"+34 962 41 06 03",
    "sg:postcode":"46600",
    "sg:province":"Valencia",
    "wof:name":"Bernardo Calatayud Castera Y Otro Cdad",
    "wof:placetype":"venue"
},
  "geometry": {"coordinates":[-0.4338029921,39.1469039917],"type":"Point"}
}