{
  "type": "Feature",
  "properties": {
    "addr:full":"Ctra Iznalloz, 2 Santa Ana Ja\u00e9n 23692",
    "addr:housenumber":"2",
    "addr:postcode":"23692",
    "addr:street":"Ctra Iznalloz",
    "iso:country":"ES",
    "sg:address":"Ctra Iznalloz, 2",
    "sg:city":"Santa Ana",
    "sg:orig_category":"Muebles Y Accesorios Para Cocinas Y Cuartos De Ba\u00d1o (al Por Menor)",
    "sg:phone":"+34 953 59 71 05",
    "sg:postcode":"23692",
    "sg:province":"Ja\u00e9n",
    "sg:website":"www.muesco.com",
    "wof:name":"Muescodecoracion S.l.",
    "wof:placetype":"venue"
},
  "geometry": {"coordinates":[-3.8913030624,37.4607162476],"type":"Point"}
}