{
  "type": "Feature",
  "properties": {
    "addr:full":"Calle de Cruz De La, 3 Torremolinos M\u00e1laga 29620",
    "addr:housenumber":"3",
    "addr:postcode":"29620",
    "addr:street":"Calle De Cruz De La;Ma\u0301Laga",
    "iso:country":"ES",
    "sg:address":"Calle de Cruz De La, 3",
    "sg:city":"Torremolinos",
    "sg:orig_category":"Agencias De Viajes",
    "sg:phone":"+34 952 37 71 99",
    "sg:postcode":"29620",
    "sg:province":"M\u00e1laga",
    "sg:website":"www.diaslibres.es",
    "wof:name":"Comunitel Global S.a.",
    "wof:placetype":"venue"
},
  "geometry": {"coordinates":[-4.4998540878,36.6244087219],"type":"Point"}
}