{
  "type": "Feature",
  "properties": {
    "iso:country":"ES",
    "sg:address":"Catra. Alcubillas, S/n",
    "sg:city":"Sta Maria Vega",
    "sg:orig_category":"Cooperativas Agr\u00cdcolas",
    "sg:phone":"+34 980 65 15 80",
    "sg:postcode":"49696",
    "sg:province":"Zamora",
    "wof:name":"Cooperativa Tera-esla-orbigo",
    "wof:placetype":"venue"
},
  "geometry": {"coordinates":[-5.8954339027,42.1077232361],"type":"Point"}
}