{
  "type": "Feature",
  "properties": {
    "addr:full":"Carrer de Mallorca, 314 Barcelona Barcelona 08037",
    "addr:housenumber":"314",
    "addr:postcode":"08037",
    "addr:street":"Carrer De Mallorca",
    "iso:country":"ES",
    "sg:address":"Carrer de Mallorca, 314",
    "sg:city":"Barcelona",
    "sg:orig_category":"Confecci\u00d3n (fabricaci\u00d3n, Al Por Mayor)",
    "sg:phone":"+34 934 59 41 04",
    "sg:postcode":"08037",
    "sg:province":"Barcelona",
    "wof:name":"Carrador Fares Carmen",
    "wof:placetype":"venue"
},
  "geometry": {"coordinates":[2.1677849293,41.3975868225],"type":"Point"}
}