{
  "type": "Feature",
  "properties": {
    "iso:country":"ES",
    "sg:address":"Calle de Espadan, 20",
    "sg:city":"Valencia",
    "sg:orig_category":"Pintores",
    "sg:phone":"+34 963 72 07 95",
    "sg:postcode":"46011",
    "sg:province":"Valencia",
    "wof:name":"Naranjo Reymondez Pilar",
    "wof:placetype":"venue"
},
  "geometry": {"coordinates":[-0.3296189904,39.4715919495],"type":"Point"}
}