{
  "type": "Feature",
  "properties": {
    "iso:country":"ES",
    "sg:address":"Ctra. Mojacar Playa, 39",
    "sg:city":"Mojacar",
    "sg:orig_category":"Centros De Coordinaci\u00d3n",
    "sg:phone":"+34 950 47 84 20",
    "sg:postcode":"04638",
    "sg:province":"Almer\u00eda",
    "wof:name":"Soria Bonilla Diego Maria",
    "wof:placetype":"venue"
},
  "geometry": {"coordinates":[-1.8467450142,37.1402359009],"type":"Point"}
}