{
  "type": "Feature",
  "properties": {
    "addr:full":"Barr Iurre Auzunea, 17 San Blas Guip\u00f9zcoa 20400",
    "addr:housenumber":"17",
    "addr:postcode":"20400",
    "addr:street":"Iurre Auzunea",
    "iso:country":"ES",
    "sg:address":"Barr Iurre Auzunea, 17",
    "sg:city":"San Blas",
    "sg:orig_category":"Alimentaci\u00d3n General (al Por Menor)",
    "sg:phone":"+34 943 67 09 00",
    "sg:postcode":"20400",
    "sg:province":"Guip\u00f9zcoa",
    "sg:website":"www.grupoeroski.es",
    "wof:name":"Eroski Sociedad Cooperativa",
    "wof:placetype":"venue"
},
  "geometry": {"coordinates":[-2.0789339542,43.1339912415],"type":"Point"}
}