{
  "type": "Feature",
  "properties": {
    "addr:full":"Calle de Leon Y Escosura, 6 Oviedo Asturias 33013",
    "addr:housenumber":"6",
    "addr:postcode":"33013",
    "addr:street":"Calle De Leon Y Escosura",
    "iso:country":"ES",
    "sg:address":"Calle de Leon Y Escosura, 6",
    "sg:city":"Oviedo",
    "sg:orig_category":"Agencias Y Agentes Comerciales, Representantes",
    "sg:phone":"+34 985 24 40 93",
    "sg:postcode":"33013",
    "sg:province":"Asturias",
    "wof:name":"Garcia Fuente Luis Fernando",
    "wof:placetype":"venue"
},
  "geometry": {"coordinates":[-5.8612160683,43.3623924255],"type":"Point"}
}