{
  "type": "Feature",
  "properties": {
    "iso:country":"ES",
    "sg:address":"Calle de Manuel Luna Rivera, 2",
    "sg:city":"Pozoblanco",
    "sg:orig_category":"Mercer\u00cda, Lencer\u00cda (al Por Menor)",
    "sg:phone":"+34 957 13 22 34",
    "sg:postcode":"14400",
    "sg:province":"C\u00f3rdoba",
    "wof:name":"Moreno Caballero Maria Luisa",
    "wof:placetype":"venue"
},
  "geometry": {"coordinates":[-4.8515911102,38.3824424744],"type":"Point"}
}