{
  "type": "Feature",
  "properties": {
    "iso:country":"ES",
    "sg:address":"Av Diagonal, 503",
    "sg:city":"Barcelona",
    "sg:orig_category":"Inmobiliaria (agencias)",
    "sg:phone":"+34 934 04 79 00",
    "sg:postcode":"08...",
    "sg:province":"Barcelona",
    "wof:name":"Inmobiliaria Colonial S.a.",
    "wof:placetype":"venue"
},
  "geometry": {"coordinates":[2.1419620514,41.3916358948],"type":"Point"}
}