{
  "type": "Feature",
  "properties": {
    "iso:country":"ES",
    "sg:address":"Calle de Begonia (de), 98",
    "sg:city":"Alcobendas",
    "sg:orig_category":"Agencias Y Agentes Comerciales, Representantes",
    "sg:phone":"+34 916 50 04 52",
    "sg:postcode":"28109",
    "sg:province":"Madrid",
    "wof:name":"Tu Trastero Tu Otro Espacio S.l.",
    "wof:placetype":"venue"
},
  "geometry": {"coordinates":[-3.6451787949,40.521232605],"type":"Point"}
}