{
  "type": "Feature",
  "properties": {
    "iso:country":"ES",
    "sg:address":"Carr Pollentia, 6",
    "sg:city":"Alcudia",
    "sg:orig_category":"Molduras, Junquillos, Listones Y Molduras Perforadas",
    "sg:phone":"+34 971 54 77 25",
    "sg:postcode":"07400",
    "sg:province":"Islas Baleares",
    "wof:name":"Vives Massanet Pedro",
    "wof:placetype":"venue"
},
  "geometry": {"coordinates":[3.1244540215,39.8526153564],"type":"Point"}
}