{
  "type": "Feature",
  "properties": {
    "iso:country":"ES",
    "sg:address":"Calle de Mayor, 35",
    "sg:city":"Burlada",
    "sg:orig_category":"Comerciantes Al Por Mayor De Vinos, Licores Y Alcoholes",
    "sg:phone":"+34 948 12 78 11",
    "sg:postcode":"31600",
    "sg:province":"Navarra",
    "wof:name":"Bastida Corera Carlos",
    "wof:placetype":"venue"
},
  "geometry": {"coordinates":[-1.6166820526,42.8253211975],"type":"Point"}
}