{
  "type": "Feature",
  "properties": {
    "addr:full":"Calle de Concha Espina, 1 Granada Granada 18007",
    "addr:housenumber":"1",
    "addr:postcode":"18007",
    "addr:street":"Calle De Concha Espina",
    "iso:country":"ES",
    "sg:address":"Calle de Concha Espina, 1",
    "sg:city":"Granada",
    "sg:orig_category":"Abogados",
    "sg:phone":"+34 958 13 28 38",
    "sg:postcode":"18007",
    "sg:province":"Granada",
    "wof:name":"Gamega C.b.",
    "wof:placetype":"venue"
},
  "geometry": {"coordinates":[-3.6003146172,37.1570205688],"type":"Point"}
}