{
  "type": "Feature",
  "properties": {
    "addr:full":"Trva Francisca Fernandez Miranda, 1 Grado Asturias 33820",
    "addr:housenumber":"1",
    "addr:postcode":"33820",
    "addr:street":"Trva Francisca Fernandez Miranda",
    "iso:country":"ES",
    "sg:address":"Trva Francisca Fernandez Miranda, 1",
    "sg:city":"Grado",
    "sg:orig_category":"Asesor\u00cda Fiscal Y Jur\u00cddica",
    "sg:phone":"+34 985 75 24 79",
    "sg:postcode":"33820",
    "sg:province":"Asturias",
    "wof:name":"Asesores Asociados C.b.",
    "wof:placetype":"venue"
},
  "geometry": {"coordinates":[-6.0573301315,43.3139686584],"type":"Point"}
}