{
  "type": "Feature",
  "properties": {
    "iso:country":"ES",
    "sg:address":"Los Pobres, 119",
    "sg:city":"Tegueste",
    "sg:orig_category":"T\u00c9cnicos Veterinarios",
    "sg:phone":"+34 922 54 23 00",
    "sg:postcode":"38280",
    "sg:province":"Santa Cruz De Tenerife",
    "wof:name":"Clinica Veterinaria Tegueste S.l.",
    "wof:placetype":"venue"
},
  "geometry": {"coordinates":[-16.3384094238,28.5215549469],"type":"Point"}
}