{
  "type": "Feature",
  "properties": {
    "addr:full":"Av Principal, 15 Sentmenat Barcelona 08181",
    "addr:housenumber":"15",
    "addr:postcode":"08181",
    "addr:street":"Av Principal",
    "iso:country":"ES",
    "sg:address":"Av Principal, 15",
    "sg:city":"Sentmenat",
    "sg:orig_category":"Artes Gr\u00c1ficas, Artes Pl\u00c1sticas: Material Y Suministros (al Por Menor)",
    "sg:phone":"+34 937 15 13 15",
    "sg:postcode":"08181",
    "sg:province":"Barcelona",
    "wof:name":"Albaladejo Alonso Vicente",
    "wof:placetype":"venue"
},
  "geometry": {"coordinates":[2.1408133507,41.6125831604],"type":"Point"}
}