{
  "type": "Feature",
  "properties": {
    "iso:country":"ES",
    "sg:address":"Calle de Doctor Zamenhof, 27",
    "sg:city":"Valencia",
    "sg:orig_category":"Confecci\u00d3n De Uniformes",
    "sg:phone":"+34 963 85 09 72",
    "sg:postcode":"46008",
    "sg:province":"Valencia",
    "wof:name":"Levantina De Servicios Generales S.l.",
    "wof:placetype":"venue"
},
  "geometry": {"coordinates":[-0.3927434981,39.4753990173],"type":"Point"}
}