{
  "type": "Feature",
  "properties": {
    "iso:country":"ES",
    "sg:address":"Calle de General Vives, 94",
    "sg:city":"Palmas De Gran Canaria",
    "sg:orig_category":"Importaci\u00d3n",
    "sg:phone":"+34 928 22 05 58",
    "sg:postcode":"35007",
    "sg:province":"Las Palmas",
    "wof:name":"Bangalore S. A.",
    "wof:placetype":"venue"
},
  "geometry": {"coordinates":[-15.4316072464,28.1406116486],"type":"Point"}
}