{
  "type": "Feature",
  "properties": {
    "addr:full":"Pase Victoria (de La), 11 Cordoba C\u00f3rdoba 14008",
    "addr:postcode":"14008",
    "addr:street":"Co\u0301Rdoba",
    "iso:country":"ES",
    "sg:address":"Pase Victoria (de La), 11",
    "sg:city":"Cordoba",
    "sg:orig_category":"Centros P\u00dablicos De Formaci\u00d3n Profesional Y T\u00c9cnica",
    "sg:phone":"+34 957 48 41 59",
    "sg:postcode":"14008",
    "sg:province":"C\u00f3rdoba",
    "wof:name":"Colegio Oficial De Peritos Industriales",
    "wof:placetype":"venue"
},
  "geometry": {"coordinates":[-4.784318924,37.8856124878],"type":"Point"}
}