{
  "type": "Feature",
  "properties": {
    "iso:country":"ES",
    "sg:address":"Ctra. Pelayos Presa, Km. 0009,0",
    "sg:city":"Cadalso",
    "sg:orig_category":"Explotaci\u00d3n De Canteras",
    "sg:phone":"+34 918 64 03 27",
    "sg:postcode":"28640",
    "sg:province":"Madrid",
    "wof:name":"Talle De Canteria Heliodoro Y Ruben S.l.",
    "wof:placetype":"venue"
},
  "geometry": {"coordinates":[-4.4287958145,40.3056488037],"type":"Point"}
}