{
  "type": "Feature",
  "properties": {
    "addr:full":"Pol Ind Rematacaudales, S/n Sanlucar C\u00e1diz 11540",
    "addr:housenumber":"s / n",
    "addr:postcode":"11540",
    "iso:country":"ES",
    "sg:address":"Pol Ind Rematacaudales, S/n",
    "sg:city":"Sanlucar",
    "sg:orig_category":"Empresas De Carpinter\u00cda",
    "sg:phone":"+34 956 36 73 98",
    "sg:postcode":"11540",
    "sg:province":"C\u00e1diz",
    "wof:name":"Galan Silva Jose Manuel",
    "wof:placetype":"venue"
},
  "geometry": {"coordinates":[-6.3119745255,36.7976112366],"type":"Point"}
}