{
  "type": "Feature",
  "properties": {
    "iso:country":"ES",
    "sg:address":"Carr Luis Vives, 4",
    "sg:city":"Benissa",
    "sg:orig_category":"Inmobiliaria (agencias)",
    "sg:phone":"+34 965 73 14 73",
    "sg:postcode":"03720",
    "sg:province":"Alicante",
    "wof:name":"Casa Mar Hahn Y Moor House S.l.",
    "wof:placetype":"venue"
},
  "geometry": {"coordinates":[0.0465539992,38.7119026184],"type":"Point"}
}