{
  "type": "Feature",
  "properties": {
    "iso:country":"ES",
    "sg:address":"Calle de Capitan Angosto Gomez Castrillon (del), 23",
    "sg:city":"Aranjuez",
    "sg:orig_category":"Art\u00cdculos De Decoraci\u00d3n (fabricaci\u00d3n Y Al Por Mayor)",
    "sg:phone":"+34 918 91 63 42",
    "sg:postcode":"28300",
    "sg:province":"Madrid",
    "wof:name":"Intordi S.l.",
    "wof:placetype":"venue"
},
  "geometry": {"coordinates":[-3.6016197205,40.0342102051],"type":"Point"}
}