{
  "type": "Feature",
  "properties": {
    "addr:full":"Carrer de Senia Del Rabich, 7 Lloret Mar Girona 17310",
    "addr:housenumber":"7",
    "addr:postcode":"17310",
    "addr:street":"Carrer De Senia Del Rabich",
    "iso:country":"ES",
    "sg:address":"Carrer de Senia Del Rabich, 7",
    "sg:city":"Lloret Mar",
    "sg:orig_category":"Inmobiliaria (agencias)",
    "sg:phone":"+34 972 37 08 95",
    "sg:postcode":"17310",
    "sg:province":"Girona",
    "wof:name":"Claro Sayago Yolanda",
    "wof:placetype":"venue"
},
  "geometry": {"coordinates":[2.846834898,41.6981697083],"type":"Point"}
}