{
  "type": "Feature",
  "properties": {
    "iso:country":"ES",
    "sg:address":"Calle de Tajo, 4",
    "sg:city":"Ajalvir",
    "sg:orig_category":"Ferreter\u00cda (diversos)",
    "sg:phone":"+34 918 84 36 28",
    "sg:postcode":"28864",
    "sg:province":"Madrid",
    "wof:name":"Urbaline S.l.",
    "wof:placetype":"venue"
},
  "geometry": {"coordinates":[-3.4809091091,40.5009422302],"type":"Point"}
}