{
  "type": "Feature",
  "properties": {
    "addr:full":"Pase San Julian, 1 Najera La Rioja 26300",
    "addr:postcode":"26300",
    "addr:street":"Julian;Najera;Rioja",
    "iso:country":"ES",
    "sg:address":"Pase San Julian, 1",
    "sg:city":"Najera",
    "sg:orig_category":"Laboratorios Y Trabajos De Fotograf\u00cda, V\u00cddeo Y Cine",
    "sg:phone":"+34 941 36 07 72",
    "sg:postcode":"26300",
    "sg:province":"La Rioja",
    "wof:name":"Perez Rubin Jose Luis",
    "wof:placetype":"venue"
},
  "geometry": {"coordinates":[-2.7250440121,42.4189338684],"type":"Point"}
}