{
  "type": "Feature",
  "properties": {
    "addr:full":"Pont Del Princep, S/n Vilamalla Girona 17469",
    "addr:housenumber":"s / n",
    "addr:postcode":"17469",
    "addr:street":"Princep",
    "iso:country":"ES",
    "sg:address":"Pont Del Princep, S/n",
    "sg:city":"Vilamalla",
    "sg:orig_category":"Deportes N\u00c1uticos, Acu\u00c1ticos Y Subacu\u00c1ticos: Art\u00cdculos Y Equipo (al Por Menor)",
    "sg:phone":"+34 972 52 58 48",
    "sg:postcode":"17469",
    "sg:province":"Girona",
    "wof:name":"Gordillo Martinez Isabel",
    "wof:placetype":"venue"
},
  "geometry": {"coordinates":[3.0403180122,42.2426719666],"type":"Point"}
}