{
  "type": "Feature",
  "properties": {
    "iso:country":"ES",
    "sg:address":"Ctra Logro\u00d1o, S/n",
    "sg:city":"Tricio",
    "sg:orig_category":"Art\u00cdculos De Madera (fabricaci\u00d3n Y Al Por Mayor)",
    "sg:phone":"+34 941 36 16 81",
    "sg:postcode":"26312",
    "sg:province":"La Rioja",
    "wof:name":"Industria Najerina Del Mueble Artesano S.a.",
    "wof:placetype":"venue"
},
  "geometry": {"coordinates":[-2.7043788433,42.4123306274],"type":"Point"}
}