{
  "type": "Feature",
  "properties": {
    "addr:full":"Calle de Lechuga (de La), S/n Fuenlabrada Madrid 28944",
    "addr:postcode":"28944",
    "addr:street":"Calle De Lechuga De La S / N",
    "iso:country":"ES",
    "sg:address":"Calle de Lechuga (de La), S/n",
    "sg:city":"Fuenlabrada",
    "sg:orig_category":"Estudios Y Construcci\u00d3n De Acuarios Y Viveros",
    "sg:phone":"+34 916 15 26 29",
    "sg:postcode":"28944",
    "sg:province":"Madrid",
    "wof:name":"Sanchez Garcia Elena",
    "wof:placetype":"venue"
},
  "geometry": {"coordinates":[-3.7946391106,40.2838592529],"type":"Point"}
}