{
  "type": "Feature",
  "properties": {
    "addr:full":"Carrer de Diputacio, 204 Barcelona Barcelona 08011",
    "addr:housenumber":"204",
    "addr:postcode":"08011",
    "addr:street":"Carrer De Diputacio",
    "iso:country":"ES",
    "sg:address":"Carrer de Diputacio, 204",
    "sg:city":"Barcelona",
    "sg:orig_category":"Abogados",
    "sg:phone":"+34 934 51 82 78",
    "sg:postcode":"08011",
    "sg:province":"Barcelona",
    "wof:name":"Pages Cortes Maria Asuncion",
    "wof:placetype":"venue"
},
  "geometry": {"coordinates":[2.1612389088,41.3858413696],"type":"Point"}
}