{
  "type": "Feature",
  "properties": {
    "addr:full":"Calle de Intxausti, 18 Bermeo Vizcaya 48370",
    "addr:housenumber":"18",
    "addr:postcode":"48370",
    "addr:street":"Calle De Intxausti",
    "iso:country":"ES",
    "sg:address":"Calle de Intxausti, 18",
    "sg:city":"Bermeo",
    "sg:orig_category":"Servicios Diversos",
    "sg:phone":"+34 946 18 72 94",
    "sg:postcode":"48370",
    "sg:province":"Vizcaya",
    "wof:name":"Funeraria Zulueta, S.l",
    "wof:placetype":"venue"
},
  "geometry": {"coordinates":[-2.7240509987,43.42029953],"type":"Point"}
}