{
  "type": "Feature",
  "properties": {
    "addr:full":"Avda Salamanca, Km. 0125,0 Valladolid Valladolid 47014",
    "addr:housenumber":"km.",
    "addr:postcode":"47014",
    "addr:street":"Avda Salamanca;0125,0",
    "iso:country":"ES",
    "sg:address":"Avda Salamanca, Km. 0125,0",
    "sg:city":"Valladolid",
    "sg:orig_category":"Herramientas Y Suministros Para Plomeros",
    "sg:phone":"+34 983 40 82 45",
    "sg:postcode":"47014",
    "sg:province":"Valladolid",
    "wof:name":"Sane Riego S. A.",
    "wof:placetype":"venue"
},
  "geometry": {"coordinates":[-4.7448167801,41.6402320862],"type":"Point"}
}