{
  "type": "Feature",
  "properties": {
    "iso:country":"ES",
    "sg:address":"Avda Cristobal Colon, 1",
    "sg:city":"Bu\u00f1uel",
    "sg:orig_category":"Peluqueros: De Se\u00d1oras",
    "sg:phone":"+34 948 83 33 04",
    "sg:postcode":"31540",
    "sg:province":"Navarra",
    "wof:name":"Yoldi Chueca Rita",
    "wof:placetype":"venue"
},
  "geometry": {"coordinates":[-1.4464205503,41.9808883667],"type":"Point"}
}