{
  "type": "Feature",
  "properties": {
    "addr:full":"Calle de Castillejos, 16 Madrid Madrid 28039",
    "addr:housenumber":"16",
    "addr:postcode":"madrid;28039",
    "addr:street":"Calle De Castillejos",
    "iso:country":"ES",
    "sg:address":"Calle de Castillejos, 16",
    "sg:city":"Madrid",
    "sg:orig_category":"Comercio De Piezas De Recambio Y De Accesorios De Veh\u00cdculos, Veh\u00cdculos Industriales",
    "sg:phone":"+34 913 11 25 40",
    "sg:postcode":"28039",
    "sg:province":"Madrid",
    "wof:name":"Garcia Martinez Antonio",
    "wof:placetype":"venue"
},
  "geometry": {"coordinates":[-3.7062687874,40.4561004639],"type":"Point"}
}