{
  "type": "Feature",
  "properties": {
    "iso:country":"ES",
    "sg:address":"Vilari\u00f1o, 41",
    "sg:city":"Vilari\u00f1o",
    "sg:orig_category":"Delegados, Agentes De Tr\u00c1nsito, Auxiliares De Transporte Internacional",
    "sg:phone":"+34 986 74 76 65",
    "sg:postcode":"36969",
    "sg:province":"Pontevedra",
    "wof:name":"Bouzada Ucha Luis",
    "wof:placetype":"venue"
},
  "geometry": {"coordinates":[-8.8211641312,42.4239959717],"type":"Point"}
}