{
  "type": "Feature",
  "properties": {
    "addr:full":"Calle de Juan De Salazar, S/n Medina Pomar Burgos 09500",
    "addr:housenumber":"s / n",
    "addr:postcode":"09500",
    "addr:street":"Calle De Juan De Salazar",
    "iso:country":"ES",
    "sg:address":"Calle de Juan De Salazar, S/n",
    "sg:city":"Medina Pomar",
    "sg:orig_category":"Estancos",
    "sg:phone":"+34 947 19 13 64",
    "sg:postcode":"09500",
    "sg:province":"Burgos",
    "wof:name":"Rasines Saez Alberto",
    "wof:placetype":"venue"
},
  "geometry": {"coordinates":[-3.4887235165,42.9322471619],"type":"Point"}
}