{
  "type": "Feature",
  "properties": {
    "addr:full":"Calle de Mariano Vergara, 18 Santa Eulalia Murcia 30003",
    "addr:housenumber":"18",
    "addr:postcode":"30003",
    "addr:street":"Calle De Mariano Vergara",
    "iso:country":"ES",
    "sg:address":"Calle de Mariano Vergara, 18",
    "sg:city":"Santa Eulalia",
    "sg:orig_category":"Bisuter\u00cda, Joyer\u00cda, Relojer\u00cda (al Por Menor)",
    "sg:phone":"+34 968 23 20 97",
    "sg:postcode":"30003",
    "sg:province":"Murcia",
    "wof:name":"Blesa Serrano Jose",
    "wof:placetype":"venue"
},
  "geometry": {"coordinates":[-1.1234680414,37.9866294861],"type":"Point"}
}