{
  "type": "Feature",
  "properties": {
    "iso:country":"ES",
    "sg:address":"Calle de Espa\u00d1oleto, 6",
    "sg:city":"Madrid",
    "sg:orig_category":"Tapicer\u00cdas",
    "sg:phone":"+34 914 47 59 24",
    "sg:postcode":"28010",
    "sg:province":"Madrid",
    "wof:name":"Calvente Bomati Eduardo",
    "wof:placetype":"venue"
},
  "geometry": {"coordinates":[-3.6963460445,40.4310379028],"type":"Point"}
}