{
  "type": "Feature",
  "properties": {
    "addr:full":"Calle de Torneros, 12 Getafe Madrid 28906",
    "addr:housenumber":"12",
    "addr:postcode":"28906",
    "addr:street":"Calle De Torneros",
    "iso:country":"ES",
    "sg:address":"Calle de Torneros, 12",
    "sg:city":"Getafe",
    "sg:orig_category":"Perfumer\u00cda (al Por Menor)",
    "sg:phone":"+34 916 82 10 11",
    "sg:postcode":"28906",
    "sg:province":"Madrid",
    "sg:website":"www.perfumeriasborque.com",
    "wof:name":"Perfumerias Borque C.b.",
    "wof:placetype":"venue"
},
  "geometry": {"coordinates":[-3.6983220577,40.305606842],"type":"Point"}
}