{
  "type": "Feature",
  "properties": {
    "addr:full":"Carrer de Sor Lluisa Estivill, 8 Reus Tarragona 43202",
    "addr:housenumber":"8",
    "addr:postcode":"43202",
    "addr:street":"Carrer De Sor Lluisa Estivill",
    "iso:country":"ES",
    "sg:address":"Carrer de Sor Lluisa Estivill, 8",
    "sg:city":"Reus",
    "sg:orig_category":"Empresas De Limpieza",
    "sg:phone":"+34 977 33 01 85",
    "sg:postcode":"43202",
    "sg:province":"Tarragona",
    "wof:name":"Neteges Ribas's S.l.",
    "wof:placetype":"venue"
},
  "geometry": {"coordinates":[1.1007230282,41.1508712769],"type":"Point"}
}