{
  "type": "Feature",
  "properties": {
    "addr:full":"Avda Aragon, 40 Alca\u00f1iz Teruel 44600",
    "addr:housenumber":"40",
    "addr:postcode":"44600",
    "addr:street":"Avda Aragon",
    "iso:country":"ES",
    "sg:address":"Avda Aragon, 40",
    "sg:city":"Alca\u00f1iz",
    "sg:orig_category":"\u00d3ptica: Instrumentos (fabricaci\u00d3n)",
    "sg:phone":"+34 978 83 04 95",
    "sg:postcode":"44600",
    "sg:province":"Teruel",
    "wof:name":"Godoy Collados Ana",
    "wof:placetype":"venue"
},
  "geometry": {"coordinates":[-0.1291120052,41.0457458496],"type":"Point"}
}