{
  "type": "Feature",
  "properties": {
    "addr:full":"Calle de Juan Aranda, S/n Martos Ja\u00e9n 23600",
    "addr:housenumber":"s / n",
    "addr:postcode":"23600",
    "addr:street":"Calle De Juan Aranda;Jae\u0301N",
    "iso:country":"ES",
    "sg:address":"Calle de Juan Aranda, S/n",
    "sg:city":"Martos",
    "sg:orig_category":"Aceites Y Grasas Alimentarias (fabricaci\u00d3n, Al Por Mayor)",
    "sg:phone":"+34 953 70 47 75",
    "sg:postcode":"23600",
    "sg:province":"Ja\u00e9n",
    "sg:website":"www.aceitestuccitanos.com",
    "wof:name":"Aceites Tuccitanos S.l.",
    "wof:placetype":"venue"
},
  "geometry": {"coordinates":[-3.9729845524,37.7184410095],"type":"Point"}
}