{
  "type": "Feature",
  "properties": {
    "iso:country":"ES",
    "sg:address":"Calle de Gran Via, 23",
    "sg:city":"Isla Cristina",
    "sg:orig_category":"Inmobiliaria (agencias)",
    "sg:phone":"+34 959 34 37 61",
    "sg:postcode":"21410",
    "sg:province":"Huelva",
    "wof:name":"Mar-antilla Inmobiliaria",
    "wof:placetype":"venue"
},
  "geometry": {"coordinates":[-7.3256669044,37.2013664246],"type":"Point"}
}