{
  "type": "Feature",
  "properties": {
    "addr:full":"Carrer de Sant Francesc Xavier, 10 Esplugues Llobregat Barcelona 08950",
    "addr:housenumber":"10",
    "addr:postcode":"08950",
    "addr:street":"Carrer De Sant Francesc Xavier",
    "iso:country":"ES",
    "sg:address":"Carrer de Sant Francesc Xavier, 10",
    "sg:city":"Esplugues Llobregat",
    "sg:orig_category":"Decoraci\u00d3n: Instalaci\u00d3n Y Talleres",
    "sg:phone":"+34 933 71 73 28",
    "sg:postcode":"08950",
    "sg:province":"Barcelona",
    "wof:name":"Borrego Gonzalez Roman",
    "wof:placetype":"venue"
},
  "geometry": {"coordinates":[2.0854699612,41.3750038147],"type":"Point"}
}