{
  "type": "Feature",
  "properties": {
    "addr:full":"Avda Federico Leal Casta\u00d1o, S/n Espartinas Sevilla 41807",
    "addr:housenumber":"s / n",
    "addr:postcode":"41807",
    "addr:street":"Avda Federico Leal Castan\u0303O",
    "iso:country":"ES",
    "sg:address":"Avda Federico Leal Casta\u00d1o, S/n",
    "sg:city":"Espartinas",
    "sg:orig_category":"Artes Gr\u00c1ficas, Artes Pl\u00c1sticas (curso)",
    "sg:phone":"+34 954 11 30 26",
    "sg:postcode":"41807",
    "sg:province":"Sevilla",
    "wof:name":"Nouveau/,s.c.",
    "wof:placetype":"venue"
},
  "geometry": {"coordinates":[-6.1224789619,37.3823661804],"type":"Point"}
}