{
  "type": "Feature",
  "properties": {
    "iso:country":"ES",
    "sg:address":"Calle de Serapio Mugica, 20",
    "sg:city":"Irun",
    "sg:orig_category":"Fachadas",
    "sg:phone":"+34 943 61 44 01",
    "sg:postcode":"20302",
    "sg:province":"Guip\u00f9zcoa",
    "wof:name":"Pino Gil Alba\u00f1ileria,s.l.",
    "wof:placetype":"venue"
},
  "geometry": {"coordinates":[-1.7964570522,43.3378486633],"type":"Point"}
}