{
  "type": "Feature",
  "properties": {
    "addr:full":"Ctra Tomares, Km. 0001,0 San J. Aznalfarache Sevilla 41920",
    "addr:postcode":"41920",
    "addr:street":"Ctra Tomares Km. 0001,0 San J. Aznalfarache",
    "iso:country":"ES",
    "sg:address":"Ctra Tomares, Km. 0001,0",
    "sg:city":"San J. Aznalfarache",
    "sg:orig_category":"Droguer\u00cdas (al Por Menor)",
    "sg:phone":"+34 954 17 82 23",
    "sg:postcode":"41920",
    "sg:province":"Sevilla",
    "sg:website":"www.bodybell.com",
    "wof:name":"Iberica De Drogueria Y Perfumeria S.a.",
    "wof:placetype":"venue"
},
  "geometry": {"coordinates":[-6.0277690887,37.359916687],"type":"Point"}
}