{
  "type": "Feature",
  "properties": {
    "iso:country":"ES",
    "sg:address":"Calle de San Agustin, 90",
    "sg:city":"Icod De Los Vinos",
    "sg:orig_category":"Supermercados Y Hipermercados",
    "sg:phone":"+34 922 81 00 66",
    "sg:postcode":"38430",
    "sg:province":"Santa Cruz De Tenerife",
    "wof:name":"Marrero Gonzalez Juan",
    "wof:placetype":"venue"
},
  "geometry": {"coordinates":[-16.7149295807,28.369184494],"type":"Point"}
}