{
  "type": "Feature",
  "properties": {
    "addr:full":"Golf Del Sur, 65 Golf Sur Santa Cruz De Tenerife 38639",
    "addr:postcode":"38639",
    "iso:country":"ES",
    "sg:address":"Golf Del Sur, 65",
    "sg:city":"Golf Sur",
    "sg:orig_category":"Inmobiliaria (agencias)",
    "sg:phone":"+34 922 73 86 13",
    "sg:postcode":"38639",
    "sg:province":"Santa Cruz De Tenerife",
    "wof:name":"Francis  Christine Marilyn",
    "wof:placetype":"venue"
},
  "geometry": {"coordinates":[-16.6115474701,28.0350246429],"type":"Point"}
}