{
  "type": "Feature",
  "properties": {
    "iso:country":"ES",
    "sg:address":"Calle de Vereda De Las Pe\u00d1as (de La), 41",
    "sg:city":"Alcobendas",
    "sg:orig_category":"Tratamientos De Conversi\u00d3n Qu\u00cdmica O Electrol\u00cdtica De Metales",
    "sg:phone":"+34 916 50 74 95",
    "sg:postcode":"28109",
    "sg:province":"Madrid",
    "wof:name":"Stemcor Steel S.l.",
    "wof:placetype":"venue"
},
  "geometry": {"coordinates":[-3.6160919666,40.5303268433],"type":"Point"}
}