{
  "type": "Feature",
  "properties": {
    "iso:country":"ES",
    "sg:address":"Calle de Pintor Aurelio Vera-fajardo, 6",
    "sg:city":"Vitoria-gasteiz",
    "sg:orig_category":"Carnicer\u00cdas, Carnicer\u00cdas",
    "sg:phone":"+34 945 01 03 33",
    "sg:postcode":"01008",
    "sg:province":"\u00c1lava",
    "wof:name":"Oscar Onetxa Verganza",
    "wof:placetype":"venue"
},
  "geometry": {"coordinates":[-2.6829140186,42.8487358093],"type":"Point"}
}