{
  "type": "Feature",
  "properties": {
    "addr:full":"Calle de Acera Fuente De La Salud, 9 Cordoba C\u00f3rdoba 14006",
    "addr:housenumber":"9",
    "addr:postcode":"14006",
    "addr:street":"Calle De Acera Fuente De La Salud;Co\u0301Rdoba",
    "iso:country":"ES",
    "sg:address":"Calle de Acera Fuente De La Salud, 9",
    "sg:city":"Cordoba",
    "sg:orig_category":"Mec\u00c1nico Del Autom\u00d3vil",
    "sg:phone":"+34 957 27 43 56",
    "sg:postcode":"14006",
    "sg:province":"C\u00f3rdoba",
    "wof:name":"Tecnicentro Cordoba S.l.",
    "wof:placetype":"venue"
},
  "geometry": {"coordinates":[-4.773499012,37.8974494934],"type":"Point"}
}