{
  "type": "Feature",
  "properties": {
    "addr:full":"Calle de Ramon Menendez Pidal, 3 Roda Albacete 02630",
    "addr:housenumber":"3",
    "addr:postcode":"02630",
    "addr:street":"Calle De Ramon Menendez Pidal",
    "iso:country":"ES",
    "sg:address":"Calle de Ramon Menendez Pidal, 3",
    "sg:city":"Roda",
    "sg:orig_category":"\u00d3ptica: Instrumentos (fabricaci\u00d3n)",
    "sg:phone":"+34 967 44 28 54",
    "sg:postcode":"02630",
    "sg:province":"Albacete",
    "wof:name":"Rabadan Morales Maria Cristina",
    "wof:placetype":"venue"
},
  "geometry": {"coordinates":[-2.1573829651,39.2025032043],"type":"Point"}
}