{
  "type": "Feature",
  "properties": {
    "iso:country":"ES",
    "sg:address":"Calle de Karmelo Etxegarai, 6",
    "sg:city":"Gernika-lumo",
    "sg:orig_category":"Abogados",
    "sg:phone":"+34 946 25 47 00",
    "sg:postcode":"48300",
    "sg:province":"Vizcaya",
    "wof:name":"Hiritek, S.l.",
    "wof:placetype":"venue"
},
  "geometry": {"coordinates":[-2.6792171001,43.3126602173],"type":"Point"}
}