{
  "type": "Feature",
  "properties": {
    "iso:country":"ES",
    "sg:address":"C/ Corco, S/n",
    "sg:city":"Tarrega",
    "sg:orig_category":"M\u00c1rmoles, Granitos Y Piedras Naturales",
    "sg:phone":"+34 973 50 05 66",
    "sg:postcode":"25300",
    "sg:province":"Lleida",
    "wof:name":"Marbres Gracia S.l",
    "wof:placetype":"venue"
},
  "geometry": {"coordinates":[1.1511900425,41.6495361328],"type":"Point"}
}