{
  "type": "Feature",
  "properties": {
    "iso:country":"ES",
    "sg:address":"Calle de Hacienda De Pavones, 174",
    "sg:city":"Madrid",
    "sg:orig_category":"Molduras, Junquillos, Listones Y Molduras Perforadas",
    "sg:phone":"+34 917 73 00 38",
    "sg:postcode":"28030",
    "sg:province":"Madrid",
    "wof:name":"Blazquez Casillas Pedro",
    "wof:placetype":"venue"
},
  "geometry": {"coordinates":[-3.6406350136,40.402431488],"type":"Point"}
}