{
  "type": "Feature",
  "properties": {
    "addr:full":"Calle de Torre (la), 4 Le\u00f3n Le\u00f3n 24002",
    "addr:housenumber":"4",
    "addr:postcode":"24002",
    "addr:street":"Calle De Torre La;Leo\u0301N",
    "iso:country":"ES",
    "sg:address":"Calle de Torre (la), 4",
    "sg:city":"Le\u00f3n",
    "sg:orig_category":"Carnicer\u00cdas, Carnicer\u00cdas",
    "sg:phone":"+34 987 24 30 65",
    "sg:postcode":"24002",
    "sg:province":"Le\u00f3n",
    "wof:name":"Rodriguez Madrid Elisa Isabel",
    "wof:placetype":"venue"
},
  "geometry": {"coordinates":[-5.5716609955,42.5981369019],"type":"Point"}
}