{
  "type": "Feature",
  "properties": {
    "addr:full":"Calle de Republica Argentina, 19 Castellon Castell\u00f3n 12002",
    "addr:housenumber":"19",
    "addr:postcode":"12002",
    "addr:street":"Calle De Republica Argentina",
    "iso:country":"ES",
    "sg:address":"Calle de Republica Argentina, 19",
    "sg:city":"Castellon",
    "sg:orig_category":"M\u00c9dicos: Nefrolog\u00cda",
    "sg:phone":"+34 964 21 99 32",
    "sg:postcode":"12002",
    "sg:province":"Castell\u00f3n",
    "wof:name":"Gambro Healthcare Valencia S.l.u.",
    "wof:placetype":"venue"
},
  "geometry": {"coordinates":[-0.0446580015,39.9839668274],"type":"Point"}
}