{
  "type": "Feature",
  "properties": {
    "iso:country":"ES",
    "sg:address":"Cmno Olagitxieta Bidea, 13",
    "sg:city":"Baserri-santa Ana",
    "sg:orig_category":"Cerrajer\u00cda, Ferrallista",
    "sg:phone":"+34 946 68 12 93",
    "sg:postcode":"48640",
    "sg:province":"Vizcaya",
    "wof:name":"Bilbao Barrientos Gaizca",
    "wof:placetype":"venue"
},
  "geometry": {"coordinates":[-2.9955940247,43.3641815186],"type":"Point"}
}