{
  "type": "Feature",
  "properties": {
    "iso:country":"ES",
    "sg:address":"Calle de Reyes, 25",
    "sg:city":"Ciudad Real",
    "sg:orig_category":"Molduras, Junquillos, Listones Y Molduras Perforadas",
    "sg:phone":"+34 926 23 01 82",
    "sg:postcode":"13002",
    "sg:province":"Ciudad Real",
    "wof:name":"Cespedes Herrera Valerio",
    "wof:placetype":"venue"
},
  "geometry": {"coordinates":[-3.932737112,38.9871482849],"type":"Point"}
}