{
  "type": "Feature",
  "properties": {
    "addr:full":"Moll Contradic, S/n Barcelona Barcelona 08039",
    "addr:housenumber":"s",
    "addr:postcode":"08039",
    "addr:street":"/ N",
    "iso:country":"ES",
    "sg:address":"Moll Contradic, S/n",
    "sg:city":"Barcelona",
    "sg:orig_category":"Fabricaci\u00d3n Y Refinado De Az\u00dacares",
    "sg:phone":"+34 934 43 10 60",
    "sg:postcode":"08039",
    "sg:province":"Barcelona",
    "wof:name":"Loiret Haentjens Espa\u00f1a S.a.",
    "wof:placetype":"venue"
},
  "geometry": {"coordinates":[2.1666629314,41.3592224121],"type":"Point"}
}