{
  "type": "Feature",
  "properties": {
    "iso:country":"ES",
    "sg:address":"Poligono Los Jarales, S/n",
    "sg:city":"Tobaruela-la Tortilla",
    "sg:orig_category":"Cojinetes De Bolas, Agujas Y Rodillos (fabricaci\u00d3n, Al Por Mayor)",
    "sg:phone":"+34 953 60 67 82",
    "sg:postcode":"23700",
    "sg:province":"Ja\u00e9n",
    "sg:website":"www.rodamientos.net",
    "wof:name":"Rodamientos Y Servicios S.l.",
    "wof:placetype":"venue"
},
  "geometry": {"coordinates":[-3.6356039047,38.093914032],"type":"Point"}
}