{
  "type": "Feature",
  "properties": {
    "iso:country":"ES",
    "sg:address":"Marin Lopez, 8",
    "sg:city":"Molina Segura",
    "sg:orig_category":"Importaci\u00d3n",
    "sg:phone":"+34 968 61 07 83",
    "sg:postcode":"30500",
    "sg:province":"Murcia",
    "wof:name":"Productos Siderurgicos Del Segura S.a.",
    "wof:placetype":"venue"
},
  "geometry": {"coordinates":[-1.2082190514,38.0629577637],"type":"Point"}
}