{
  "type": "Feature",
  "properties": {
    "iso:country":"ES",
    "sg:address":"Calle de Fray Luis De Leon, 21",
    "sg:city":"Le\u00f3n",
    "sg:orig_category":"Centros Comerciales Y Grandes Tiendas",
    "sg:phone":"+34 987 26 31 00",
    "sg:postcode":"24...",
    "sg:province":"Le\u00f3n",
    "sg:website":"www.elcorteingles.es",
    "wof:name":"El Corte Ingles S.a.",
    "wof:placetype":"venue"
},
  "geometry": {"coordinates":[-5.5685048103,42.5894317627],"type":"Point"}
}