{
  "type": "Feature",
  "properties": {
    "addr:full":"Calle de Andres Larrazabal, 3 Arenas -areeta Vizcaya 48930",
    "addr:housenumber":"3;areeta",
    "addr:postcode":"48930",
    "addr:street":"Calle De Andres Larrazabal",
    "iso:country":"ES",
    "sg:address":"Calle de Andres Larrazabal, 3",
    "sg:city":"Arenas -areeta",
    "sg:orig_category":"Peluquer\u00cdas, Peluquer\u00cda Mixta",
    "sg:phone":"+34 944 63 62 49",
    "sg:postcode":"48930",
    "sg:province":"Vizcaya",
    "wof:name":"Imanol Uriarte Mijangos Y Otro Cdad",
    "wof:placetype":"venue"
},
  "geometry": {"coordinates":[-3.0136384964,43.3259048462],"type":"Point"}
}