{
  "type": "Feature",
  "properties": {
    "addr:full":"Calle de General Aguilera, 5 Ciudad Real Ciudad Real 13001",
    "addr:housenumber":"5",
    "addr:postcode":"13001",
    "addr:street":"Calle De General Aguilera",
    "iso:country":"ES",
    "sg:address":"Calle de General Aguilera, 5",
    "sg:city":"Ciudad Real",
    "sg:orig_category":"Energ\u00cda Solar Y Nuevas Energ\u00cdas (equipo, Estudios)",
    "sg:phone":"+34 926 23 21 20",
    "sg:postcode":"13001",
    "sg:province":"Ciudad Real",
    "sg:website":"www.era-sl.com",
    "wof:name":"Energias Renovables Aplicadas S.l.",
    "wof:placetype":"venue"
},
  "geometry": {"coordinates":[-3.9280428886,38.9849014282],"type":"Point"}
}