{
  "type": "Feature",
  "properties": {
    "iso:country":"ES",
    "sg:address":"Fouco, 12",
    "sg:city":"Fouco",
    "sg:orig_category":"M\u00c1quinas De Jardiner\u00cda",
    "sg:phone":"+34 986 36 00 22",
    "sg:postcode":"36389",
    "sg:province":"Pontevedra",
    "wof:name":"Garcia Correa Manuel",
    "wof:placetype":"venue"
},
  "geometry": {"coordinates":[-8.7404689789,42.1420402527],"type":"Point"}
}