{
  "type": "Feature",
  "properties": {
    "addr:full":"Abejeras, 8 Iru\u00f1a Navarra 31007",
    "addr:housenumber":"8",
    "addr:postcode":"31007",
    "addr:street":"Abejeras",
    "iso:country":"ES",
    "sg:address":"Abejeras, 8",
    "sg:city":"Iru\u00f1a",
    "sg:orig_category":"Ense\u00d1anza, Formaci\u00d3n Profesional: Aprendizaje",
    "sg:phone":"+34 948 17 23 11",
    "sg:postcode":"31007",
    "sg:province":"Navarra",
    "wof:name":"Sabate Baruque Teresa",
    "wof:placetype":"venue"
},
  "geometry": {"coordinates":[-1.6453789473,42.8072433472],"type":"Point"}
}