{
  "type": "Feature",
  "properties": {
    "addr:full":"Calle de Piles, 4 Gijon Asturias 33203",
    "addr:housenumber":"4",
    "addr:postcode":"33203",
    "addr:street":"Calle De Piles",
    "iso:country":"ES",
    "sg:address":"Calle de Piles, 4",
    "sg:city":"Gijon",
    "sg:orig_category":"Asilos De Ancianos. Centros Privados",
    "sg:phone":"+34 985 36 21 10",
    "sg:postcode":"33203",
    "sg:province":"Asturias",
    "sg:website":"www.residencialescastillo.com",
    "wof:name":"Residencial El Castillo C.b.",
    "wof:placetype":"venue"
},
  "geometry": {"coordinates":[-5.6485600471,43.5371856689],"type":"Point"}
}