{
  "type": "Feature",
  "properties": {
    "addr:full":"Carrer de Barcelona, 1 S. Celoni Barcelona 08470",
    "addr:housenumber":"1",
    "addr:postcode":"08470",
    "addr:street":"Carrer De Barcelona",
    "iso:country":"ES",
    "sg:address":"Carrer de Barcelona, 1",
    "sg:city":"S. Celoni",
    "sg:orig_category":"Peluqueros: De Se\u00d1oras",
    "sg:phone":"+34 938 67 20 50",
    "sg:postcode":"08470",
    "sg:province":"Barcelona",
    "wof:name":"Miralls Perruqueria S.c.p.",
    "wof:placetype":"venue"
},
  "geometry": {"coordinates":[2.4916100502,41.691078186],"type":"Point"}
}