{
  "type": "Feature",
  "properties": {
    "addr:full":"A, 35 Mostoles Madrid 28938",
    "addr:housenumber":"35",
    "addr:postcode":"28938",
    "addr:street":"A",
    "iso:country":"ES",
    "sg:address":"A, 35",
    "sg:city":"Mostoles",
    "sg:orig_category":"Agentes, Concesionarios Y Sucursales De Veh\u00cdculos",
    "sg:phone":"+34 916 45 65 06",
    "sg:postcode":"28938",
    "sg:province":"Madrid",
    "wof:name":"Fergoauto S.a.",
    "wof:placetype":"venue"
},
  "geometry": {"coordinates":[-3.8633348942,40.3433532715],"type":"Point"}
}