{
  "type": "Feature",
  "properties": {
    "addr:full":"Ctra. Circunvalacion, S/n Corrales Zamora 49700",
    "addr:postcode":"49700",
    "addr:street":"Ctra. Circunvalacion S / N",
    "iso:country":"ES",
    "sg:address":"Ctra. Circunvalacion, S/n",
    "sg:city":"Corrales",
    "sg:orig_category":"C\u00c1maras De Comercio E Industria, Oficios, Agricultura",
    "sg:phone":"+34 980 56 00 18",
    "sg:postcode":"49700",
    "sg:province":"Zamora",
    "wof:name":"Asociacion De Agricultores Y Ganaderos De Corrales",
    "wof:placetype":"venue"
},
  "geometry": {"coordinates":[-5.7237353325,41.3599853516],"type":"Point"}
}