{
  "type": "Feature",
  "properties": {
    "iso:country":"ES",
    "sg:address":"Carr Palauet, 52",
    "sg:city":"Lleida",
    "sg:orig_category":"Suministros Para Hoteles",
    "sg:phone":"+34 973 20 18 99",
    "sg:postcode":"25001",
    "sg:province":"Lleida",
    "wof:name":"Ilervending S.l.",
    "wof:placetype":"venue"
},
  "geometry": {"coordinates":[0.6445310116,41.6069831848],"type":"Point"}
}