{
  "type": "Feature",
  "properties": {
    "iso:country":"ES",
    "sg:address":"Calle de Jesus Del Gran Poder, 30",
    "sg:city":"Madrid",
    "sg:orig_category":"Fabricaci\u00d3n E Instalaci\u00d3n De Cajas Fuertes",
    "sg:phone":"+34 914 76 17 24",
    "sg:postcode":"28026",
    "sg:province":"Madrid",
    "wof:name":"Sanchez Romo Luis Fernando",
    "wof:placetype":"venue"
},
  "geometry": {"coordinates":[-3.7020089626,40.3871116638],"type":"Point"}
}