{
  "type": "Feature",
  "properties": {
    "iso:country":"ES",
    "sg:address":"Ptge. N. Monturiol, 1",
    "sg:city":"Cabrera Mar",
    "sg:orig_category":"Fabricaci\u00d3n De Moldes Y Modelos",
    "sg:phone":"+34 937 59 49 19",
    "sg:postcode":"08349",
    "sg:province":"Barcelona",
    "wof:name":"Taumol Moldes S.l.",
    "wof:placetype":"venue"
},
  "geometry": {"coordinates":[2.3933050632,41.5273513794],"type":"Point"}
}