{
  "type": "Feature",
  "properties": {
    "iso:country":"ES",
    "sg:address":"Calle de Guzman El Bueno, 15",
    "sg:city":"Madrid",
    "sg:orig_category":"Inform\u00c1tica (estudios, Servicios, Asesor\u00cda, Formaci\u00d3n)",
    "sg:phone":"+34 915 49 17 30",
    "sg:postcode":"28015",
    "sg:province":"Madrid",
    "wof:name":"Le Intelapli S.a.",
    "wof:placetype":"venue"
},
  "geometry": {"coordinates":[-3.7135779858,40.4316635132],"type":"Point"}
}