{
  "type": "Feature",
  "properties": {
    "iso:country":"ES",
    "sg:address":"Calle de Zarzuela, 20",
    "sg:city":"Benamocarra",
    "sg:classifiers":[
        {
            "category":"Taxi",
            "type":"Transportation"
        }
    ],
    "sg:phone":"+34 952 50 95 28",
    "sg:postcode":"29719",
    "sg:province":"M\u00e1laga",
    "wof:name":"Tellez Sarmiento Antonio",
    "wof:placetype":"venue"
},
  "geometry": {"coordinates":[-4.160738945,36.7914772034],"type":"Point"}
}