{
  "type": "Feature",
  "properties": {
    "addr:full":"C/ Ciutat De Barcelona, 18 Paterna Valencia 46988",
    "addr:housenumber":"18",
    "addr:postcode":"46988",
    "addr:street":"C / Ciutat De Barcelona",
    "iso:country":"ES",
    "sg:address":"C/ Ciutat De Barcelona, 18",
    "sg:city":"Paterna",
    "sg:orig_category":"Materiales De Construcci\u00d3n (en General)",
    "sg:phone":"+34 961 34 30 80",
    "sg:postcode":"46988",
    "sg:province":"Valencia",
    "wof:name":"Hofman S.l.",
    "wof:placetype":"venue"
},
  "geometry": {"coordinates":[-0.4629589915,39.5087623596],"type":"Point"}
}