{
  "type": "Feature",
  "properties": {
    "addr:full":"Pol Ind Jaraiz Vera, Km. 0003,3 Jaraiz Vera C\u00e1ceres 10400",
    "addr:postcode":"10400",
    "addr:street":"Km. 0003,3",
    "iso:country":"ES",
    "sg:address":"Pol Ind Jaraiz Vera, Km. 0003,3",
    "sg:city":"Jaraiz Vera",
    "sg:orig_category":"Importaci\u00d3n",
    "sg:phone":"+34 927 46 12 77",
    "sg:postcode":"10400",
    "sg:province":"C\u00e1ceres",
    "wof:name":"Pentaflex S.a.",
    "wof:placetype":"venue"
},
  "geometry": {"coordinates":[-5.7516927719,40.0606231689],"type":"Point"}
}