{
  "type": "Feature",
  "properties": {
    "addr:full":"Avda Alpujarras De (las), 200 Dalias Almer\u00eda 04750",
    "addr:housenumber":"200",
    "addr:postcode":"04750",
    "addr:street":"Avda Alpujarras De Las;Almeri\u0301A",
    "iso:country":"ES",
    "sg:address":"Avda Alpujarras De (las), 200",
    "sg:city":"Dalias",
    "sg:orig_category":"Negocio De Materiales De Construcci\u00d3n",
    "sg:phone":"+34 950 49 43 91",
    "sg:postcode":"04750",
    "sg:province":"Almer\u00eda",
    "wof:name":"Cara Martin Salvador",
    "wof:placetype":"venue"
},
  "geometry": {"coordinates":[-2.8725988865,36.82447052],"type":"Point"}
}