{
  "type": "Feature",
  "properties": {
    "iso:country":"ES",
    "sg:address":"Fermin Calbeton Kalea, 14",
    "sg:city":"Eibar",
    "sg:orig_category":"Electrodom\u00c9sticos (al Por Menor)",
    "sg:phone":"+34 943 20 08 65",
    "sg:postcode":"20600",
    "sg:province":"Guip\u00f9zcoa",
    "wof:name":"Ramon Ega\u00f1a S.l.",
    "wof:placetype":"venue"
},
  "geometry": {"coordinates":[-2.4725339413,43.1840133667],"type":"Point"}
}