{
  "type": "Feature",
  "properties": {
    "iso:country":"ES",
    "sg:address":"Calle de Madre De Dios, 12",
    "sg:city":"Baeza",
    "sg:orig_category":"Cr\u00cda De Animales",
    "sg:phone":"+34 953 74 21 26",
    "sg:postcode":"23440",
    "sg:province":"Ja\u00e9n",
    "wof:name":"Robles Herrera Juan Luis",
    "wof:placetype":"venue"
},
  "geometry": {"coordinates":[-3.46134305,37.9972610474],"type":"Point"}
}