{
  "type": "Feature",
  "properties": {
    "iso:country":"ES",
    "sg:address":"Calle de Rey Fernando Iii, S/n",
    "sg:city":"Petrer",
    "sg:orig_category":"Zapater\u00cdas",
    "sg:phone":"+34 965 37 04 95",
    "sg:postcode":"03610",
    "sg:province":"Alicante",
    "wof:name":"Plantas Motilla S.l.",
    "wof:placetype":"venue"
},
  "geometry": {"coordinates":[-0.787974,38.4902687073],"type":"Point"}
}