{
  "type": "Feature",
  "properties": {
    "addr:full":"Barr San Cristobal, 2 Burgos Burgos 09007",
    "addr:housenumber":"2",
    "addr:postcode":"09007",
    "addr:street":"San Cristobal",
    "iso:country":"ES",
    "sg:address":"Barr San Cristobal, 2",
    "sg:city":"Burgos",
    "sg:orig_category":"Panader\u00cdas, Panader\u00cdas",
    "sg:phone":"+34 947 48 58 59",
    "sg:postcode":"09007",
    "sg:province":"Burgos",
    "wof:name":"Panaderia Ricardo Y Jaime Camara S. L.",
    "wof:placetype":"venue"
},
  "geometry": {"coordinates":[-3.6520240307,42.3627700806],"type":"Point"}
}