{
  "type": "Feature",
  "properties": {
    "iso:country":"ES",
    "sg:address":"Estda. De Vigo, 46",
    "sg:city":"Ourense",
    "sg:orig_category":"Mec\u00c1nico Del Autom\u00d3vil",
    "sg:phone":"+34 988 37 30 92",
    "sg:postcode":"32001",
    "sg:province":"Ourense",
    "wof:name":"Automecanica Deza-car S.l.cc",
    "wof:placetype":"venue"
},
  "geometry": {"coordinates":[-7.8814702034,42.3738327026],"type":"Point"}
}