{
  "type": "Feature",
  "properties": {
    "addr:full":"Pg Blay, 55 Olot Girona 17800",
    "addr:housenumber":"55",
    "addr:postcode":"17800",
    "addr:street":"Pg Blay",
    "iso:country":"ES",
    "sg:address":"Pg Blay, 55",
    "sg:city":"Olot",
    "sg:orig_category":"Farmacias",
    "sg:phone":"+34 972 26 11 20",
    "sg:postcode":"17800",
    "sg:province":"Girona",
    "wof:name":"Olot Analisi S.l.",
    "wof:placetype":"venue"
},
  "geometry": {"coordinates":[2.4877610207,42.1828536987],"type":"Point"}
}