{
  "type": "Feature",
  "properties": {
    "addr:full":"Av Generalitat (de La), S/n Tortosa Tarragona 43500",
    "addr:postcode":"43500",
    "addr:street":"Av Generalitat De La S / N",
    "iso:country":"ES",
    "sg:address":"Av Generalitat (de La), S/n",
    "sg:city":"Tortosa",
    "sg:orig_category":"Ense\u00d1anza, Formaci\u00d3n Profesional: Aprendizaje",
    "sg:phone":"+34 977 51 07 51",
    "sg:postcode":"43500",
    "sg:province":"Tarragona",
    "wof:name":"Centre De Telecomunicaciones De Catalunya",
    "wof:placetype":"venue"
},
  "geometry": {"coordinates":[0.5203400254,40.8029403687],"type":"Point"}
}