{
  "type": "Feature",
  "properties": {
    "addr:full":"Plaz Puerta De Zamora, 9 Salamanca Salamanca 37005",
    "addr:housenumber":"9",
    "addr:postcode":"37005",
    "addr:street":"Puerta;Zamora",
    "iso:country":"ES",
    "sg:address":"Plaz Puerta De Zamora, 9",
    "sg:city":"Salamanca",
    "sg:orig_category":"Promotores Constructores",
    "sg:phone":"+34 923 26 15 71",
    "sg:postcode":"37005",
    "sg:province":"Salamanca",
    "wof:name":"Riosbau S.l.",
    "wof:placetype":"venue"
},
  "geometry": {"coordinates":[-5.6583042145,40.9937133789],"type":"Point"}
}