{
  "type": "Feature",
  "properties": {
    "iso:country":"ES",
    "sg:address":"Ctra. C. 231, S/n",
    "sg:city":"Los Barrios",
    "sg:orig_category":"Carnicer\u00cdas, Carnicer\u00cdas",
    "sg:phone":"+34 956 23 62 49",
    "sg:postcode":"11370",
    "sg:province":"C\u00e1diz",
    "wof:name":"Tiurba S.l.",
    "wof:placetype":"venue"
},
  "geometry": {"coordinates":[-5.4946498871,36.1863174438],"type":"Point"}
}