{
  "type": "Feature",
  "properties": {
    "addr:full":"Calle de Linneo, 25 Madrid Madrid 28005",
    "addr:housenumber":"25",
    "addr:postcode":"madrid;28005",
    "addr:street":"Calle De Linneo",
    "iso:country":"ES",
    "sg:address":"Calle de Linneo, 25",
    "sg:city":"Madrid",
    "sg:orig_category":"Art\u00cdculos De Regalo (al Por Menor)",
    "sg:phone":"+34 913 66 90 28",
    "sg:postcode":"28005",
    "sg:province":"Madrid",
    "wof:name":"Ortu\u00f1o Vida Maria Dolores",
    "wof:placetype":"venue"
},
  "geometry": {"coordinates":[-3.7205379009,40.411365509],"type":"Point"}
}