{
  "type": "Feature",
  "properties": {
    "iso:country":"ES",
    "sg:address":"Goiko Kalea, 8",
    "sg:city":"Azpeitia",
    "sg:orig_category":"Bares, Piano",
    "sg:phone":"+34 943 81 20 26",
    "sg:postcode":"20730",
    "sg:province":"Guip\u00f9zcoa",
    "wof:name":"Call Phone S.l.",
    "wof:placetype":"venue"
},
  "geometry": {"coordinates":[-2.2663080692,43.1833953857],"type":"Point"}
}