{
  "type": "Feature",
  "properties": {
    "iso:country":"ES",
    "sg:address":"Avda Galicia, 36",
    "sg:city":"Zamora",
    "sg:orig_category":"Caf\u00c9s, Bares, Cervecer\u00cdas",
    "sg:phone":"+34 980 51 54 84",
    "sg:postcode":"49024",
    "sg:province":"Zamora",
    "wof:name":"Cafe Bar Rossi Sll",
    "wof:placetype":"venue"
},
  "geometry": {"coordinates":[-5.7579388618,41.5273628235],"type":"Point"}
}