{
  "type": "Feature",
  "properties": {
    "addr:full":"Ctra Alicante, 62 Puente Tocinos Murcia 30007",
    "addr:housenumber":"62",
    "addr:postcode":"30007",
    "addr:street":"Ctra Alicante",
    "iso:country":"ES",
    "sg:address":"Ctra Alicante, 62",
    "sg:city":"Puente Tocinos",
    "sg:orig_category":"Veh\u00cdculos De Ocasi\u00d3n",
    "sg:phone":"+34 968 20 46 11",
    "sg:postcode":"30007",
    "sg:province":"Murcia",
    "wof:name":"Rafael Torrecillas Murcia S.l.",
    "wof:placetype":"venue"
},
  "geometry": {"coordinates":[-1.1175760031,37.9925994873],"type":"Point"}
}