{
  "type": "Feature",
  "properties": {
    "iso:country":"ES",
    "sg:address":"Ptge Nuria, 22",
    "sg:city":"Barcelona",
    "sg:orig_category":"Bisuter\u00cda, Joyer\u00cda, Relojer\u00cda (al Por Menor)",
    "sg:phone":"+34 934 36 40 14",
    "sg:postcode":"08025",
    "sg:province":"Barcelona",
    "wof:name":"Ysalgue Ciso Xavier",
    "wof:placetype":"venue"
},
  "geometry": {"coordinates":[2.1755578518,41.4110908508],"type":"Point"}
}