{
  "type": "Feature",
  "properties": {
    "iso:country":"ES",
    "sg:address":"Cipres, 1",
    "sg:city":"Torrelamata",
    "sg:orig_category":"Promotores Constructores",
    "sg:phone":"+34 966 92 07 07",
    "sg:postcode":"03188",
    "sg:province":"Alicante",
    "wof:name":"Torrevi\u00f1as S.l.",
    "wof:placetype":"venue"
},
  "geometry": {"coordinates":[-0.6580709815,38.0311698914],"type":"Point"}
}