{
  "type": "Feature",
  "properties": {
    "iso:country":"ES",
    "sg:address":"Avda Miranda, 15",
    "sg:city":"Barakaldo",
    "sg:orig_category":"Comercio De Piezas De Recambio Y De Accesorios De Veh\u00cdculos, Veh\u00cdculos Industriales",
    "sg:phone":"+34 944 00 95 90",
    "sg:postcode":"48902",
    "sg:province":"Vizcaya",
    "wof:name":"Igor Rodriguez San Juan",
    "wof:placetype":"venue"
},
  "geometry": {"coordinates":[-2.9948070049,43.2953109741],"type":"Point"}
}