{
  "type": "Feature",
  "properties": {
    "iso:country":"ES",
    "sg:address":"Manuel Rodriguez Manolete, 3",
    "sg:city":"Montilla",
    "sg:orig_category":"Electricidad: Instaladores",
    "sg:phone":"+34 957 65 33 03",
    "sg:postcode":"14550",
    "sg:province":"C\u00f3rdoba",
    "wof:name":"Electro Zo\u00f1ar S.l.",
    "wof:placetype":"venue"
},
  "geometry": {"coordinates":[-4.647356987,37.5804595947],"type":"Point"}
}