{
  "type": "Feature",
  "properties": {
    "addr:full":"Rua Real, 66 Ferrol A Coru\u00f1a 15402",
    "addr:housenumber":"66",
    "addr:postcode":"15402",
    "addr:street":"Rua Real;A Corun\u0303A",
    "iso:country":"ES",
    "sg:address":"Rua Real, 66",
    "sg:city":"Ferrol",
    "sg:orig_category":"Abogados",
    "sg:phone":"+34 981 35 37 60",
    "sg:postcode":"15402",
    "sg:province":"A Coru\u00f1a",
    "wof:name":"Seoane Iglesias Jose",
    "wof:placetype":"venue"
},
  "geometry": {"coordinates":[-8.2316856384,43.4846534729],"type":"Point"}
}