{
  "type": "Feature",
  "properties": {
    "iso:country":"ES",
    "sg:address":"Carr Bellavista, 34",
    "sg:city":"Lleida",
    "sg:orig_category":"Suministros Y Materiales Industriales",
    "sg:phone":"+34 973 20 00 85",
    "sg:postcode":"25001",
    "sg:province":"Lleida",
    "wof:name":"Suministros Lleida S.c.p.",
    "wof:placetype":"venue"
},
  "geometry": {"coordinates":[0.6391749978,41.6049690247],"type":"Point"}
}