{
  "type": "Feature",
  "properties": {
    "addr:full":"Calle de Alcazar, 16 Yebenes Toledo 45470",
    "addr:housenumber":"16",
    "addr:postcode":"45470",
    "addr:street":"Calle De Alcazar",
    "iso:country":"ES",
    "sg:address":"Calle de Alcazar, 16",
    "sg:city":"Yebenes",
    "sg:orig_category":"Empresarios",
    "sg:phone":"+34 925 32 02 00",
    "sg:postcode":"45470",
    "sg:province":"Toledo",
    "wof:name":"Diaz Jimenez Valentin",
    "wof:placetype":"venue"
},
  "geometry": {"coordinates":[-3.8718636036,39.5830726624],"type":"Point"}
}