{
  "type": "Feature",
  "properties": {
    "iso:country":"ES",
    "sg:address":"Taibilla, 25",
    "sg:city":"Roldan",
    "sg:orig_category":"Rotulistas",
    "sg:phone":"+34 968 58 82 52",
    "sg:postcode":"30709",
    "sg:province":"Murcia",
    "wof:name":"Sanchez Martinez Salvador",
    "wof:placetype":"venue"
},
  "geometry": {"coordinates":[-1.00712502,37.7947006226],"type":"Point"}
}