{
  "type": "Feature",
  "properties": {
    "iso:country":"ES",
    "sg:address":"Via Massague, 25",
    "sg:city":"Sabadell",
    "sg:orig_category":"Art\u00cdculos De Regalo (al Por Menor)",
    "sg:phone":"+34 937 26 97 54",
    "sg:postcode":"08201",
    "sg:province":"Barcelona",
    "wof:name":"Canals Gracia Joaquina",
    "wof:placetype":"venue"
},
  "geometry": {"coordinates":[2.1075561047,41.5499992371],"type":"Point"}
}