{
  "type": "Feature",
  "properties": {
    "addr:full":"Calle de Moscatel, S/n Malaga M\u00e1laga 29014",
    "addr:housenumber":"s",
    "addr:postcode":"29014",
    "addr:street":"Calle De Moscatel;/ N;Ma\u0301Laga",
    "iso:country":"ES",
    "sg:address":"Calle de Moscatel, S/n",
    "sg:city":"Malaga",
    "sg:orig_category":"Cerrajer\u00cda, Ferrallista",
    "sg:phone":"+34 952 25 00 90",
    "sg:postcode":"29014",
    "sg:province":"M\u00e1laga",
    "wof:name":"Sanchez Guerrero Antonio",
    "wof:placetype":"venue"
},
  "geometry": {"coordinates":[-4.4160618782,36.7449035645],"type":"Point"}
}