{
  "type": "Feature",
  "properties": {
    "addr:full":"Calle de Madrid, 1 Playa Del Ingles Las Palmas 35100",
    "addr:housenumber":"1",
    "addr:postcode":"35100",
    "addr:street":"Calle De Madrid",
    "iso:country":"ES",
    "sg:address":"Calle de Madrid, 1",
    "sg:city":"Playa Del Ingles",
    "sg:orig_category":"Bisuter\u00cda, Joyer\u00cda, Relojer\u00cda (al Por Menor)",
    "sg:phone":"+34 928 76 88 54",
    "sg:postcode":"35100",
    "sg:province":"Las Palmas",
    "wof:name":"Ponce Loscalzo Griselda Vivian",
    "wof:placetype":"venue"
},
  "geometry": {"coordinates":[-15.5756196976,27.759519577],"type":"Point"}
}