{
  "type": "Feature",
  "properties": {
    "iso:country":"ES",
    "sg:address":"La Rioja, 1",
    "sg:city":"Iru\u00f1a",
    "sg:orig_category":"Institutos De Belleza",
    "sg:phone":"+34 948 25 15 32",
    "sg:postcode":"31008",
    "sg:province":"Navarra",
    "wof:name":"Casares Iglesias Miguel",
    "wof:placetype":"venue"
},
  "geometry": {"coordinates":[-1.6600350142,42.8090896606],"type":"Point"}
}