{
  "type": "Feature",
  "properties": {
    "addr:full":"Calle de Sagunto, 138 Valencia Valencia 46009",
    "addr:housenumber":"138",
    "addr:postcode":"46009",
    "addr:street":"Calle De Sagunto",
    "iso:country":"ES",
    "sg:address":"Calle de Sagunto, 138",
    "sg:city":"Valencia",
    "sg:orig_category":"Pescader\u00cdas (al Por Menor)",
    "sg:phone":"+34 963 65 69 67",
    "sg:postcode":"46009",
    "sg:province":"Valencia",
    "wof:name":"Peixcateria Valencia S.l.",
    "wof:placetype":"venue"
},
  "geometry": {"coordinates":[-0.3751150072,39.4876556396],"type":"Point"}
}