{
  "type": "Feature",
  "properties": {
    "iso:country":"ES",
    "sg:address":"Ctra Nova, 63",
    "sg:city":"Alcanar",
    "sg:orig_category":"Mec\u00c1nico Del Autom\u00d3vil",
    "sg:phone":"+34 977 73 01 86",
    "sg:postcode":"43530",
    "sg:province":"Tarragona",
    "wof:name":"Ramon Sancho Alfredo",
    "wof:placetype":"venue"
},
  "geometry": {"coordinates":[0.4777849913,40.5415725708],"type":"Point"}
}