{
  "type": "Feature",
  "properties": {
    "iso:country":"ES",
    "sg:address":"Calle de Pego (el), S/n",
    "sg:city":"Villabuena Puente",
    "sg:orig_category":"Serrer\u00cdas De Madera",
    "sg:phone":"+34 980 60 66 96",
    "sg:postcode":"49820",
    "sg:province":"Zamora",
    "wof:name":"Manso Manzanera Roberto",
    "wof:placetype":"venue"
},
  "geometry": {"coordinates":[-5.4120926857,41.3770866394],"type":"Point"}
}