{
  "type": "Feature",
  "properties": {
    "iso:country":"ES",
    "sg:address":"Carr Prim, 1",
    "sg:city":"Caldes Malavella",
    "sg:orig_category":"Cajas De Ahorro",
    "sg:phone":"+34 972 47 05 61",
    "sg:postcode":"17455",
    "sg:province":"Girona",
    "sg:website":"www.caixagirona.es",
    "wof:name":"Caixa De Girona",
    "wof:placetype":"venue"
},
  "geometry": {"coordinates":[2.8018240929,41.8385505676],"type":"Point"}
}