{
  "type": "Feature",
  "properties": {
    "addr:full":"Calle de Sambara, 128 Madrid Madrid 28027",
    "addr:housenumber":"128",
    "addr:postcode":"28027",
    "addr:street":"Calle De Sambara",
    "iso:country":"ES",
    "sg:address":"Calle de Sambara, 128",
    "sg:city":"Madrid",
    "sg:orig_category":"Inform\u00c1tica (estudios, Servicios, Asesor\u00cda, Formaci\u00d3n)",
    "sg:phone":"+34 914 06 11 17",
    "sg:postcode":"28027",
    "sg:province":"Madrid",
    "sg:website":"www.asomed",
    "wof:name":"Asociacion Madrile\u00f1a De Empresarios De Servicios Deportivos",
    "wof:placetype":"venue"
},
  "geometry": {"coordinates":[-3.6436564922,40.4372215271],"type":"Point"}
}