{
  "type": "Feature",
  "properties": {
    "iso:country":"ES",
    "sg:address":"Calle de Calero Pita, 4",
    "sg:city":"Madrid",
    "sg:orig_category":"Serigraf\u00cda (material Y Suministros)",
    "sg:phone":"+34 914 77 90 88",
    "sg:postcode":"28053",
    "sg:province":"Madrid",
    "wof:name":"Garcia Recuero Andres",
    "wof:placetype":"venue"
},
  "geometry": {"coordinates":[-3.6701292992,40.3831787109],"type":"Point"}
}