{
  "type": "Feature",
  "properties": {
    "addr:full":"Calle de Santo Domingo, 4 San Cristobal De La Laguna Santa Cruz De Tenerife 38201",
    "addr:housenumber":"4",
    "addr:postcode":"38201",
    "addr:street":"Calle De Santo Domingo",
    "iso:country":"ES",
    "sg:address":"Calle de Santo Domingo, 4",
    "sg:city":"San Cristobal De La Laguna",
    "sg:orig_category":"Ropa Para Se\u00d1oras Y Caballeros (al Por Menor)",
    "sg:phone":"+34 922 26 15 94",
    "sg:postcode":"38201",
    "sg:province":"Santa Cruz De Tenerife",
    "wof:name":"Atoche Rodriguez Maria Del Pilar",
    "wof:placetype":"venue"
},
  "geometry": {"coordinates":[-16.3135070801,28.4869098663],"type":"Point"}
}