{
  "type": "Feature",
  "properties": {
    "addr:full":"Calle de Banderas De Castilla, S/n Torrijos Toledo 45500",
    "addr:housenumber":"s / n",
    "addr:postcode":"45500",
    "addr:street":"Calle De Banderas De Castilla",
    "iso:country":"ES",
    "sg:address":"Calle de Banderas De Castilla, S/n",
    "sg:city":"Torrijos",
    "sg:orig_category":"Venta, Instalaci\u00d3n De Calefacci\u00d3n",
    "sg:phone":"+34 925 76 08 64",
    "sg:postcode":"45500",
    "sg:province":"Toledo",
    "wof:name":"Jurado Gonzalez Jose",
    "wof:placetype":"venue"
},
  "geometry": {"coordinates":[-4.2861809731,39.9767684937],"type":"Point"}
}