{
  "type": "Feature",
  "properties": {
    "addr:full":"Calle de Egido, 23 U\u00d1a Cuenca 16152",
    "addr:housenumber":"23",
    "addr:postcode":"16152",
    "addr:street":"Calle De Egido",
    "iso:country":"ES",
    "sg:address":"Calle de Egido, 23",
    "sg:city":"U\u00d1a",
    "sg:orig_category":"Hoteles",
    "sg:phone":"+34 969 28 28 52",
    "sg:postcode":"16152",
    "sg:province":"Cuenca",
    "wof:name":"Agua-riscas S. A.",
    "wof:placetype":"venue"
},
  "geometry": {"coordinates":[-1.9772433043,40.2237014771],"type":"Point"}
}