{
  "type": "Feature",
  "properties": {
    "addr:full":"Carrer de Barcelona, 5 Palau-solita I Plegamans Barcelona 08184",
    "addr:housenumber":"5",
    "addr:postcode":"08184",
    "addr:street":"Carrer De Barcelona",
    "iso:country":"ES",
    "sg:address":"Carrer de Barcelona, 5",
    "sg:city":"Palau-solita I Plegamans",
    "sg:orig_category":"Fisioterapia",
    "sg:phone":"+34 938 64 46 94",
    "sg:postcode":"08184",
    "sg:province":"Barcelona",
    "wof:name":"Garriga Artigas Susana",
    "wof:placetype":"venue"
},
  "geometry": {"coordinates":[2.1788089275,41.5881652832],"type":"Point"}
}