{
  "type": "Feature",
  "properties": {
    "addr:full":"Calle de B(campollano), 4 Albacete Albacete 02006",
    "addr:housenumber":"4",
    "addr:postcode":"02006",
    "addr:street":"Calle De;Campollano",
    "iso:country":"ES",
    "sg:address":"Calle de B(campollano), 4",
    "sg:city":"Albacete",
    "sg:orig_category":"Electricidad: Equipos Industriales, Componentes (fabricaci\u00d3n)",
    "sg:phone":"+34 967 52 30 86",
    "sg:postcode":"02006",
    "sg:province":"Albacete",
    "wof:name":"Dielectro Manchego S.a.",
    "wof:placetype":"venue"
},
  "geometry": {"coordinates":[-1.9490209818,39.013168335],"type":"Point"}
}