{
  "type": "Feature",
  "properties": {
    "iso:country":"ES",
    "sg:address":"Calle de Santa Clara, 12",
    "sg:city":"Le\u00f3n",
    "sg:orig_category":"Herboristas (al Por Menor)",
    "sg:phone":"+34 987 23 04 04",
    "sg:postcode":"24002",
    "sg:province":"Le\u00f3n",
    "wof:name":"Verde Santa Clara S L Dietetica",
    "wof:placetype":"venue"
},
  "geometry": {"coordinates":[-5.5761408806,42.5999221802],"type":"Point"}
}