{
  "type": "Feature",
  "properties": {
    "addr:full":"Carrer de Bruc, 68 Barcelona Barcelona 08009",
    "addr:housenumber":"68",
    "addr:postcode":"08009",
    "addr:street":"Carrer De Bruc",
    "iso:country":"ES",
    "sg:address":"Carrer de Bruc, 68",
    "sg:city":"Barcelona",
    "sg:orig_category":"Colchones (fabricaci\u00d3n, Al Por Mayor, Al Por Menor)",
    "sg:phone":"+34 934 88 13 12",
    "sg:postcode":"08009",
    "sg:province":"Barcelona",
    "wof:name":"Capell Pou Marc",
    "wof:placetype":"venue"
},
  "geometry": {"coordinates":[2.1707680225,41.3935928345],"type":"Point"}
}