{
  "type": "Feature",
  "properties": {
    "addr:full":"Ctra Andalucia (de), 126 Aranjuez Madrid 28300",
    "addr:housenumber":"126",
    "addr:postcode":"28300",
    "addr:street":"Ctra Andalucia De",
    "iso:country":"ES",
    "sg:address":"Ctra Andalucia (de), 126",
    "sg:city":"Aranjuez",
    "sg:orig_category":"Colocaci\u00d3n, Mantenimiento, Vitrificaci\u00d3n De Parquets",
    "sg:phone":"+34 918 91 49 23",
    "sg:postcode":"28300",
    "sg:province":"Madrid",
    "wof:name":"Torres Fernandez Maria Jesus",
    "wof:placetype":"venue"
},
  "geometry": {"coordinates":[-3.6057519913,40.0281028748],"type":"Point"}
}