{
  "type": "Feature",
  "properties": {
    "iso:country":"ES",
    "sg:address":"Carrer de Espartero, 9",
    "sg:city":"Palma",
    "sg:orig_category":"Iglesia Cat\u00d3lica",
    "sg:phone":"+34 971 73 07 08",
    "sg:postcode":"07014",
    "sg:province":"Islas Baleares",
    "wof:name":"Parroquia I.concepcion Sant Magi",
    "wof:placetype":"venue"
},
  "geometry": {"coordinates":[2.6347630024,39.5710372925],"type":"Point"}
}