{
  "type": "Feature",
  "properties": {
    "iso:country":"ES",
    "sg:address":"Calle de Empedrada, 18",
    "sg:city":"Manzanares",
    "sg:orig_category":"Agencias De Viajes",
    "sg:phone":"+34 926 61 49 10",
    "sg:postcode":"13200",
    "sg:province":"Ciudad Real",
    "sg:website":"www.halconviajes.com",
    "wof:name":"Viajes Halcon S.a.",
    "wof:placetype":"venue"
},
  "geometry": {"coordinates":[-3.3720190525,38.9964790344],"type":"Point"}
}