{
  "type": "Feature",
  "properties": {
    "iso:country":"ES",
    "sg:address":"Calle de Toledo, 20",
    "sg:city":"Madrid",
    "sg:orig_category":"Zapatos (al Por Menor)",
    "sg:phone":"+34 913 66 54 71",
    "sg:postcode":"28005",
    "sg:province":"Madrid",
    "wof:name":"Castellanos Cordobes Rafael",
    "wof:placetype":"venue"
},
  "geometry": {"coordinates":[-3.7068390846,40.4056091309],"type":"Point"}
}