{
  "type": "Feature",
  "properties": {
    "iso:country":"ES",
    "sg:address":"Calle de Juan Martin El Empecinado, 4",
    "sg:city":"Madrid",
    "sg:orig_category":"Caf\u00c9s, Bares, Cervecer\u00cdas",
    "sg:phone":"+34 915 28 81 48",
    "sg:postcode":"28045",
    "sg:province":"Madrid",
    "wof:name":"Provencio Martin Pedro",
    "wof:placetype":"venue"
},
  "geometry": {"coordinates":[-3.6881361008,40.4020881653],"type":"Point"}
}