{
  "type": "Feature",
  "properties": {
    "iso:country":"ES",
    "sg:address":"Carrer de Francoli, 1",
    "sg:city":"Constanti",
    "sg:orig_category":"Cl\u00cdnicas Dentales",
    "sg:phone":"+34 977 52 26 80",
    "sg:postcode":"43120",
    "sg:province":"Tarragona",
    "wof:name":"Causape Fontanet Esperanza",
    "wof:placetype":"venue"
},
  "geometry": {"coordinates":[1.2167329788,41.1516456604],"type":"Point"}
}