{
  "type": "Feature",
  "properties": {
    "addr:full":"Avda Constitucion, 83 Cari\u00f1o La Coru\u00f1a 15360",
    "addr:housenumber":"83",
    "addr:postcode":"15360",
    "addr:street":"Avda Constitucion;Corun\u0303A",
    "iso:country":"ES",
    "sg:address":"Avda Constitucion, 83",
    "sg:city":"Cari\u00f1o",
    "sg:orig_category":"Doctores En Medicina",
    "sg:phone":"+34 981 40 60 51",
    "sg:postcode":"15360",
    "sg:province":"La Coru\u00f1a",
    "wof:name":"Iglesias Fernandez Federico",
    "wof:placetype":"venue"
},
  "geometry": {"coordinates":[-7.8745212555,43.7368850708],"type":"Point"}
}