{
  "type": "Feature",
  "properties": {
    "addr:full":"Parada, 25 Parada La Coru\u00f1a 15380",
    "addr:postcode":"15380",
    "addr:street":"Parada;Corun\u0303A",
    "iso:country":"ES",
    "sg:address":"Parada, 25",
    "sg:city":"Parada",
    "sg:orig_category":"Estancos",
    "sg:phone":"+34 981 79 21 44",
    "sg:postcode":"15380",
    "sg:province":"La Coru\u00f1a",
    "wof:name":"Rodriguez Seoane Roberto",
    "wof:placetype":"venue"
},
  "geometry": {"coordinates":[-8.1878890991,43.2155342102],"type":"Point"}
}