{
  "type": "Feature",
  "properties": {
    "iso:country":"ES",
    "sg:address":"Avda Almazora, 58",
    "sg:city":"Castellon",
    "sg:orig_category":"Loter\u00cda Y T\u00d3mbola",
    "sg:phone":"+34 964 24 49 87",
    "sg:postcode":"12005",
    "sg:province":"Castell\u00f3n",
    "wof:name":"Cerrudo Beltran Rosalia",
    "wof:placetype":"venue"
},
  "geometry": {"coordinates":[-0.0297400001,39.9624290466],"type":"Point"}
}