{
  "type": "Feature",
  "properties": {
    "addr:full":"Plaz Escuelas (las), 1 Alcorcon Madrid 28921",
    "addr:housenumber":"1",
    "addr:postcode":"28921",
    "addr:street":"Plaz;Las",
    "iso:country":"ES",
    "sg:address":"Plaz Escuelas (las), 1",
    "sg:city":"Alcorcon",
    "sg:orig_category":"Guarder\u00cdas",
    "sg:phone":"+34 916 11 33 53",
    "sg:postcode":"28921",
    "sg:province":"Madrid",
    "wof:name":"Escuela Infantlil Ponpitas S.l.",
    "wof:placetype":"venue"
},
  "geometry": {"coordinates":[-3.8297860622,40.3489646912],"type":"Point"}
}