{
  "type": "Feature",
  "properties": {
    "addr:full":"Calle de Madrid, 115 Getafe Madrid 28903",
    "addr:housenumber":"115",
    "addr:postcode":"28903",
    "addr:street":"Calle De Madrid",
    "iso:country":"ES",
    "sg:address":"Calle de Madrid, 115",
    "sg:city":"Getafe",
    "sg:orig_category":"Ropa Para Se\u00d1oras (al Por Menor)",
    "sg:phone":"+34 916 95 78 88",
    "sg:postcode":"28903",
    "sg:province":"Madrid",
    "wof:name":"Diaz Fargas Antonio",
    "wof:placetype":"venue"
},
  "geometry": {"coordinates":[-3.7266089916,40.3201408386],"type":"Point"}
}