{
  "type": "Feature",
  "properties": {
    "addr:full":"Union, S/n Vecindario Las Palmas 35110",
    "addr:housenumber":"s",
    "addr:postcode":"35110",
    "addr:street":"/ N Vecindario Las Palmas",
    "iso:country":"ES",
    "sg:address":"Union, S/n",
    "sg:city":"Vecindario",
    "sg:orig_category":"Ense\u00d1anza Secundaria: Colegios Y Escuelas Privadas",
    "sg:phone":"+34 928 75 02 75",
    "sg:postcode":"35110",
    "sg:province":"Las Palmas",
    "wof:name":"Gobierno De Canarias",
    "wof:placetype":"venue"
},
  "geometry": {"coordinates":[-15.4464740753,27.8485298157],"type":"Point"}
}