{
  "type": "Feature",
  "properties": {
    "addr:full":"Carr Emili Grahit, 17 Girona Girona 17002",
    "addr:housenumber":"17",
    "addr:postcode":"17002",
    "addr:street":"Carr Emili Grahit",
    "iso:country":"ES",
    "sg:address":"Carr Emili Grahit, 17",
    "sg:city":"Girona",
    "sg:orig_category":"Inmobiliaria (agencias)",
    "sg:phone":"+34 972 21 80 86",
    "sg:postcode":"17002",
    "sg:province":"Girona",
    "wof:name":"Fincas Corral Occitania S.l.",
    "wof:placetype":"venue"
},
  "geometry": {"coordinates":[2.8187699318,41.975315094],"type":"Point"}
}