{
  "type": "Feature",
  "properties": {
    "addr:full":"Calle de Joaquin Costa, 15 Salamanca Salamanca 37007",
    "addr:housenumber":"15",
    "addr:postcode":"37007",
    "addr:street":"Calle De Joaquin Costa",
    "iso:country":"ES",
    "sg:address":"Calle de Joaquin Costa, 15",
    "sg:city":"Salamanca",
    "sg:orig_category":"Artes Gr\u00c1ficas, Artes Pl\u00c1sticas: Productos Y Suministros (al Por Mayor)",
    "sg:phone":"+34 923 25 74 39",
    "sg:postcode":"37007",
    "sg:province":"Salamanca",
    "wof:name":"Hernandez Hernandez Alfredo",
    "wof:placetype":"venue"
},
  "geometry": {"coordinates":[-5.6663951874,40.9706535339],"type":"Point"}
}