{
  "type": "Feature",
  "properties": {
    "addr:full":"Avda Segunda Aguada, S/n Cadiz C\u00e1diz 11012",
    "addr:housenumber":"s / n",
    "addr:postcode":"11012",
    "addr:street":"Avda Segunda Aguada",
    "iso:country":"ES",
    "sg:address":"Avda Segunda Aguada, S/n",
    "sg:city":"Cadiz",
    "sg:orig_category":"Electrodom\u00c9sticos (fabricaci\u00d3n, Al Por Mayor)",
    "sg:phone":"+34 956 27 01 54",
    "sg:postcode":"11012",
    "sg:province":"C\u00e1diz",
    "wof:name":"Carmona Perez Luis",
    "wof:placetype":"venue"
},
  "geometry": {"coordinates":[-6.2759170532,36.5127334595],"type":"Point"}
}