{
  "type": "Feature",
  "properties": {
    "iso:country":"ES",
    "sg:address":"Avda Juan Xxiii, S/n",
    "sg:city":"Sevilla",
    "sg:orig_category":"Mec\u00c1nico Del Autom\u00d3vil",
    "sg:phone":"+34 954 65 66 54",
    "sg:postcode":"41006",
    "sg:province":"Sevilla",
    "wof:name":"Aznar Alonso Domingo",
    "wof:placetype":"venue"
},
  "geometry": {"coordinates":[-5.9536094666,37.3796424866],"type":"Point"}
}