{
  "type": "Feature",
  "properties": {
    "addr:full":"Calle de Maestro Varela, 8 Albacete Albacete 02005",
    "addr:housenumber":"8",
    "addr:postcode":"02005",
    "addr:street":"Calle De Maestro Varela",
    "iso:country":"ES",
    "sg:address":"Calle de Maestro Varela, 8",
    "sg:city":"Albacete",
    "sg:orig_category":"Congelados: Productos Alimentarios (al Por Menor)",
    "sg:phone":"+34 967 52 41 25",
    "sg:postcode":"02005",
    "sg:province":"Albacete",
    "wof:name":"Gonzalez Flores Jose Luis",
    "wof:placetype":"venue"
},
  "geometry": {"coordinates":[-1.8647010326,39.0017127991],"type":"Point"}
}