{
  "type": "Feature",
  "properties": {
    "addr:full":"Poligon Industrial De Girona, S/n Riudellots Selva Girona 17457",
    "addr:housenumber":"s / n",
    "addr:postcode":"17457",
    "iso:country":"ES",
    "sg:address":"Poligon Industrial De Girona, S/n",
    "sg:city":"Riudellots Selva",
    "sg:orig_category":"Transportes Por V\u00cdas Navegables",
    "sg:phone":"+34 972 47 81 80",
    "sg:postcode":"17457",
    "sg:province":"Girona",
    "wof:name":"Julvetrans S.l.",
    "wof:placetype":"venue"
},
  "geometry": {"coordinates":[2.8304951191,41.8967056274],"type":"Point"}
}