{
  "type": "Feature",
  "properties": {
    "addr:full":"Calle de Iglesia, S/n Caba\u00e7as De La Sagra Toledo 45592",
    "addr:housenumber":"s / n",
    "addr:postcode":"45592",
    "addr:street":"Calle De Iglesia",
    "iso:country":"ES",
    "sg:address":"Calle de Iglesia, S/n",
    "sg:city":"Caba\u00e7as De La Sagra",
    "sg:orig_category":"Iglesia Cat\u00d3lica",
    "sg:phone":"+34 925 35 50 26",
    "sg:postcode":"45592",
    "sg:province":"Toledo",
    "wof:name":"Parroquia De La Asuncion",
    "wof:placetype":"venue"
},
  "geometry": {"coordinates":[-3.9469740391,40.006690979],"type":"Point"}
}