{
  "type": "Feature",
  "properties": {
    "addr:full":"Calle de Murcia, 9 Madrid Madrid 28045",
    "addr:housenumber":"9",
    "addr:postcode":"madrid;28045",
    "addr:street":"Calle De Murcia",
    "iso:country":"ES",
    "sg:address":"Calle de Murcia, 9",
    "sg:city":"Madrid",
    "sg:orig_category":"Estancos",
    "sg:phone":"+34 915 30 41 50",
    "sg:postcode":"28045",
    "sg:province":"Madrid",
    "wof:name":"Lopez Cortes Isabel",
    "wof:placetype":"venue"
},
  "geometry": {"coordinates":[-3.6939539909,40.4053993225],"type":"Point"}
}