{
  "type": "Feature",
  "properties": {
    "addr:full":"Pg Bonanova, 54 Barcelona Barcelona 08017",
    "addr:housenumber":"54",
    "addr:postcode":"08017",
    "addr:street":"Pg Bonanova",
    "iso:country":"ES",
    "sg:address":"Pg Bonanova, 54",
    "sg:city":"Barcelona",
    "sg:orig_category":"Sociedades, Compa\u00d1\u00cdas Aseguradoras",
    "sg:phone":"+34 934 18 48 28",
    "sg:postcode":"08017",
    "sg:province":"Barcelona",
    "wof:name":"Prevision Sanitaria Nacional-mutua De Seguros Y Reaseguros",
    "wof:placetype":"venue"
},
  "geometry": {"coordinates":[2.127612114,41.4035491943],"type":"Point"}
}