{
  "type": "Feature",
  "properties": {
    "addr:full":"Calle de Amberes, 1 Jerez De La Frontera C\u00e1diz 11405",
    "addr:housenumber":"1",
    "addr:postcode":"11405",
    "addr:street":"Calle De Amberes",
    "iso:country":"ES",
    "sg:address":"Calle de Amberes, 1",
    "sg:city":"Jerez De La Frontera",
    "sg:orig_category":"Institutos De Belleza",
    "sg:phone":"+34 956 39 78 76",
    "sg:postcode":"11405",
    "sg:province":"C\u00e1diz",
    "wof:name":"Suarez Guerrero Manuela",
    "wof:placetype":"venue"
},
  "geometry": {"coordinates":[-6.108604908,36.6915550232],"type":"Point"}
}