{
  "type": "Feature",
  "properties": {
    "iso:country":"ES",
    "sg:address":"Ctra. Fte. Saz, Km. 0002,8",
    "sg:city":"Belvis De Jarama",
    "sg:orig_category":"Confecciones De Art\u00cdculos De Punto",
    "sg:phone":"+34 916 58 22 14",
    "sg:postcode":"28862",
    "sg:province":"Madrid",
    "wof:name":"Tejidos Getexma 2000 S.l.",
    "wof:placetype":"venue"
},
  "geometry": {"coordinates":[-3.5449800491,40.5565299988],"type":"Point"}
}