{
  "type": "Feature",
  "properties": {
    "iso:country":"ES",
    "sg:address":"Calle de Conde Vallellano, 5",
    "sg:city":"Palencia",
    "sg:orig_category":"M\u00c9dicos: Estomatolog\u00cda",
    "sg:phone":"+34 979 71 36 33",
    "sg:postcode":"34002",
    "sg:province":"Palencia",
    "wof:name":"Lobete Martin Maria Soledad",
    "wof:placetype":"venue"
},
  "geometry": {"coordinates":[-4.5301918983,42.0083808899],"type":"Point"}
}