{
  "type": "Feature",
  "properties": {
    "addr:full":"Avda Compa\u00d1ia De Mar (de La), S/n Ceuta Ceuta 51001",
    "addr:postcode":"51001",
    "addr:street":"Avda Compan\u0303Ia De Mar De La S / N",
    "iso:country":"ES",
    "sg:address":"Avda Compa\u00d1ia De Mar (de La), S/n",
    "sg:city":"Ceuta",
    "sg:orig_category":"Deportes Diversos",
    "sg:phone":"+34 956 51 74 87",
    "sg:postcode":"51001",
    "sg:province":"Ceuta",
    "wof:name":"Federacion De Vela De Ceuta",
    "wof:placetype":"venue"
},
  "geometry": {"coordinates":[-5.3302302361,35.8947601318],"type":"Point"}
}