{
  "type": "Feature",
  "properties": {
    "addr:full":"Calle de Sierra Nevada (de La), 26 Humanes De Madrid Madrid 28970",
    "addr:housenumber":"26",
    "addr:postcode":"28970",
    "addr:street":"Calle De Sierra Nevada De La",
    "iso:country":"ES",
    "sg:address":"Calle de Sierra Nevada (de La), 26",
    "sg:city":"Humanes De Madrid",
    "sg:orig_category":"Empresas De Desmonte",
    "sg:phone":"+34 914 92 09 47",
    "sg:postcode":"28970",
    "sg:province":"Madrid",
    "wof:name":"Cateljuma S.l.",
    "wof:placetype":"venue"
},
  "geometry": {"coordinates":[-3.8170089722,40.2712631226],"type":"Point"}
}