{
  "type": "Feature",
  "properties": {
    "iso:country":"ES",
    "sg:address":"Calle de Arganda, 26",
    "sg:city":"Madrid",
    "sg:orig_category":"Plomeros",
    "sg:phone":"+34 914 74 50 40",
    "sg:postcode":"28005",
    "sg:province":"Madrid",
    "wof:name":"Requena Mendoza Francisco",
    "wof:placetype":"venue"
},
  "geometry": {"coordinates":[-3.7065644264,40.4008369446],"type":"Point"}
}