{
  "type": "Feature",
  "properties": {
    "iso:country":"ES",
    "sg:address":"Calle de Pablo Iglesias, 111",
    "sg:city":"Elda",
    "sg:orig_category":"Agencias Y Asesores De Publicidad",
    "sg:phone":"+34 965 38 35 62",
    "sg:postcode":"03600",
    "sg:province":"Alicante",
    "wof:name":"Zeus Dise\u00f1o Y Publicidad S.l.u.",
    "wof:placetype":"venue"
},
  "geometry": {"coordinates":[-0.7879354954,38.4760017395],"type":"Point"}
}