{
  "type": "Feature",
  "properties": {
    "iso:country":"ES",
    "sg:address":"Rua Ramon Aller, 27",
    "sg:city":"Lalin",
    "sg:orig_category":"Museos",
    "sg:phone":"+34 986 78 40 04",
    "sg:postcode":"36500",
    "sg:province":"Pontevedra",
    "wof:name":"Concello De Lalin",
    "wof:placetype":"venue"
},
  "geometry": {"coordinates":[-8.1155147552,42.659324646],"type":"Point"}
}