{
  "type": "Feature",
  "properties": {
    "addr:full":"Calle de Puerta Nueva, 8 San Lorenzo Murcia 30001",
    "addr:housenumber":"8",
    "addr:postcode":"30001",
    "addr:street":"Calle De Puerta Nueva",
    "iso:country":"ES",
    "sg:address":"Calle de Puerta Nueva, 8",
    "sg:city":"San Lorenzo",
    "sg:orig_category":"Comercio, Reparaci\u00d3n De Bicicletas, De Motocicletas, De Accesorios",
    "sg:phone":"+34 968 24 66 42",
    "sg:postcode":"30001",
    "sg:province":"Murcia",
    "wof:name":"Marin Baeza Jose",
    "wof:placetype":"venue"
},
  "geometry": {"coordinates":[-1.1269539595,37.988910675],"type":"Point"}
}