{
  "type": "Feature",
  "properties": {
    "addr:full":"Calle de Vicario, 11 Iniesta Cuenca 16235",
    "addr:housenumber":"11",
    "addr:postcode":"16235",
    "addr:street":"Calle De Vicario",
    "iso:country":"ES",
    "sg:address":"Calle de Vicario, 11",
    "sg:city":"Iniesta",
    "sg:orig_category":"Asesor\u00cdas Y Estudios Financieros",
    "sg:phone":"+34 967 57 90 03",
    "sg:postcode":"16235",
    "sg:province":"Cuenca",
    "wof:name":"Plaza Tebar Antonio",
    "wof:placetype":"venue"
},
  "geometry": {"coordinates":[-1.7488889694,39.4430007935],"type":"Point"}
}