{
  "type": "Feature",
  "properties": {
    "iso:country":"ES",
    "sg:address":"Pase Estacion, 18",
    "sg:city":"Caravaca Cruz",
    "sg:orig_category":"Marroquiner\u00cda (confecci\u00d3n)",
    "sg:phone":"+34 968 70 36 66",
    "sg:postcode":"30400",
    "sg:province":"Murcia",
    "wof:name":"Anna Y Robert S.l.",
    "wof:placetype":"venue"
},
  "geometry": {"coordinates":[-1.8538861275,38.1034812927],"type":"Point"}
}