{
  "type": "Feature",
  "properties": {
    "addr:full":"Pol Ind Can Massaguer, 4 Sta. Agnes Malanyanes Barcelona 08430",
    "addr:housenumber":"4",
    "addr:postcode":"08430",
    "addr:street":"Ind;Massaguer",
    "iso:country":"ES",
    "sg:address":"Pol Ind Can Massaguer, 4",
    "sg:city":"Sta. Agnes Malanyanes",
    "sg:orig_category":"Ropa Para Se\u00d1oras Y Caballeros (al Por Menor)",
    "sg:phone":"+34 938 42 30 71",
    "sg:postcode":"08430",
    "sg:province":"Barcelona",
    "wof:name":"Bienfundamentada S.l.",
    "wof:placetype":"venue"
},
  "geometry": {"coordinates":[2.3271899223,41.5986404419],"type":"Point"}
}