{
  "type": "Feature",
  "properties": {
    "iso:country":"ES",
    "sg:address":"Avda Campana (la), 3",
    "sg:city":"Lora Rio",
    "sg:orig_category":"Ropa Y Accesorios",
    "sg:phone":"+34 955 80 37 14",
    "sg:postcode":"41440",
    "sg:province":"Sevilla",
    "wof:name":"Ortiz Blazquez Francisco",
    "wof:placetype":"venue"
},
  "geometry": {"coordinates":[-5.5245900154,37.6563262939],"type":"Point"}
}