{
  "type": "Feature",
  "properties": {
    "iso:country":"ES",
    "sg:address":"Calle de Tesos, 49",
    "sg:city":"Sancti-spiritus",
    "sg:orig_category":"Empresas De Carpinter\u00cda Met\u00c1lica",
    "sg:phone":"+34 923 48 40 28",
    "sg:postcode":"37470",
    "sg:province":"Salamanca",
    "wof:name":"Garzon Lazaro Jose Franciso",
    "wof:placetype":"venue"
},
  "geometry": {"coordinates":[-6.4177241325,40.6967506409],"type":"Point"}
}