{
  "type": "Feature",
  "properties": {
    "iso:country":"ES",
    "sg:address":"Calle de Mayor, 56",
    "sg:city":"Vera",
    "sg:orig_category":"Transporte En General",
    "sg:phone":"+34 950 39 33 42",
    "sg:postcode":"04620",
    "sg:province":"Almer\u00eda",
    "wof:name":"Gallardo Parra Francisco",
    "wof:placetype":"venue"
},
  "geometry": {"coordinates":[-1.8652260303,37.245716095],"type":"Point"}
}