{
  "type": "Feature",
  "properties": {
    "iso:country":"ES",
    "sg:address":"Bo Borroto, S/n",
    "sg:city":"Escalante",
    "sg:orig_category":"Empresarios",
    "sg:phone":"+34 942 74 36 29",
    "sg:postcode":"39795",
    "sg:province":"Cantabria",
    "wof:name":"Moreno Herrero Jose Felix",
    "wof:placetype":"venue"
},
  "geometry": {"coordinates":[-3.5204238892,43.4464454651],"type":"Point"}
}