{
  "type": "Feature",
  "properties": {
    "iso:country":"ES",
    "sg:address":"Calle de Alfonso X El Sabio, 27",
    "sg:city":"Parla",
    "sg:orig_category":"Electrodom\u00c9sticos (al Por Menor)",
    "sg:phone":"+34 916 05 45 10",
    "sg:postcode":"28980",
    "sg:province":"Madrid",
    "wof:name":"Super As De Oros S.l.",
    "wof:placetype":"venue"
},
  "geometry": {"coordinates":[-3.7676167488,40.2338600159],"type":"Point"}
}