{
  "type": "Feature",
  "properties": {
    "iso:country":"ES",
    "sg:address":"Vrda Escorredor, 3",
    "sg:city":"Dolores",
    "sg:orig_category":"Puertas Y Portales",
    "sg:phone":"+34 966 71 02 44",
    "sg:postcode":"03150",
    "sg:province":"Alicante",
    "wof:name":"Perez Rodriguez Fernando",
    "wof:placetype":"venue"
},
  "geometry": {"coordinates":[-0.7677869797,38.137386322],"type":"Point"}
}