{
  "type": "Feature",
  "properties": {
    "iso:country":"ES",
    "sg:address":"Calle de Cristo, 61",
    "sg:city":"Velez-malaga",
    "sg:orig_category":"Porcelanas, Azulejos (fabricaci\u00d3n, Al Por Mayor)",
    "sg:phone":"+34 952 50 11 33",
    "sg:postcode":"29700",
    "sg:province":"M\u00e1laga",
    "wof:name":"Alba Espejo Antonio",
    "wof:placetype":"venue"
},
  "geometry": {"coordinates":[-4.1021575928,36.7790527344],"type":"Point"}
}