{
  "type": "Feature",
  "properties": {
    "iso:country":"ES",
    "sg:address":"Avda Carlos Iii, 238",
    "sg:city":"Campillo Del Moro",
    "sg:orig_category":"Herboristas (al Por Menor)",
    "sg:phone":"+34 950 55 03 34",
    "sg:postcode":"04720",
    "sg:province":"Almer\u00eda",
    "wof:name":"Soriano Sanchez Encarna",
    "wof:placetype":"venue"
},
  "geometry": {"coordinates":[-2.5974500179,36.801410675],"type":"Point"}
}