{
  "type": "Feature",
  "properties": {
    "iso:country":"ES",
    "sg:address":"Calle de Cronista Carreres, 9",
    "sg:city":"Valencia",
    "sg:orig_category":"Asesor\u00cda Fiscal Y Jur\u00cddica",
    "sg:phone":"+34 963 52 45 11",
    "sg:postcode":"46003",
    "sg:province":"Valencia",
    "wof:name":"Agustin Arnal Vicente",
    "wof:placetype":"venue"
},
  "geometry": {"coordinates":[-0.3677935004,39.4729576111],"type":"Point"}
}