{
  "type": "Feature",
  "properties": {
    "addr:full":"Calle de Miguel De Legazpi, 9 Aljorra Murcia 30390",
    "addr:housenumber":"9",
    "addr:postcode":"30390",
    "addr:street":"Calle De Miguel De Legazpi",
    "iso:country":"ES",
    "sg:address":"Calle de Miguel De Legazpi, 9",
    "sg:city":"Aljorra",
    "sg:orig_category":"Mec\u00c1nico Del Autom\u00d3vil",
    "sg:phone":"+34 968 55 86 23",
    "sg:postcode":"30390",
    "sg:province":"Murcia",
    "wof:name":"Garcia Sanchez Diego",
    "wof:placetype":"venue"
},
  "geometry": {"coordinates":[-1.0707390308,37.6909942627],"type":"Point"}
}