{
  "type": "Feature",
  "properties": {
    "iso:country":"ES",
    "sg:address":"Barr Quintana (la), S/n",
    "sg:city":"Quintana",
    "sg:orig_category":"Agricultores, Agricultores",
    "sg:phone":"+34 942 77 03 90",
    "sg:postcode":"39418",
    "sg:province":"Cantabria",
    "wof:name":"Hoyos Gomez Bernardino",
    "wof:placetype":"venue"
},
  "geometry": {"coordinates":[-4.1527471542,42.9326438904],"type":"Point"}
}