{
  "type": "Feature",
  "properties": {
    "addr:full":"Calle de Palencia, 23 Granada Granada 18007",
    "addr:housenumber":"23",
    "addr:postcode":"18007",
    "addr:street":"Calle De Palencia",
    "iso:country":"ES",
    "sg:address":"Calle de Palencia, 23",
    "sg:city":"Granada",
    "sg:orig_category":"Autob\u00das (explotaci\u00d3n Y Servicios De)",
    "sg:phone":"+34 958 81 60 64",
    "sg:postcode":"18007",
    "sg:province":"Granada",
    "wof:name":"Valmebus S.l.",
    "wof:placetype":"venue"
},
  "geometry": {"coordinates":[-3.5954380035,37.1597442627],"type":"Point"}
}