{
  "type": "Feature",
  "properties": {
    "addr:full":"Calle de Rio Borines (del), 66 Alcazares Murcia 30710",
    "addr:housenumber":"66",
    "addr:postcode":"30710",
    "addr:street":"Calle De Rio Borines Del",
    "iso:country":"ES",
    "sg:address":"Calle de Rio Borines (del), 66",
    "sg:city":"Alcazares",
    "sg:orig_category":"Bancos",
    "sg:phone":"+34 968 58 31 50",
    "sg:postcode":"30710",
    "sg:province":"Murcia",
    "wof:name":"R Cable Y Telecomunicaciones Galicia S.a.",
    "wof:placetype":"venue"
},
  "geometry": {"coordinates":[-0.8950669765,37.7512741089],"type":"Point"}
}