{
  "type": "Feature",
  "properties": {
    "iso:country":"ES",
    "sg:address":"Calle de Lopez Allue, 2",
    "sg:city":"Zaragoza",
    "sg:orig_category":"Molduras, Junquillos, Listones Y Molduras Perforadas",
    "sg:phone":"+34 976 35 97 68",
    "sg:postcode":"50005",
    "sg:province":"Zaragoza",
    "wof:name":"Arhuaco S.c",
    "wof:placetype":"venue"
},
  "geometry": {"coordinates":[-0.8935732245,41.6443481445],"type":"Point"}
}