{
  "type": "Feature",
  "properties": {
    "iso:country":"ES",
    "sg:address":"C/ Sebastian El Cano, 20",
    "sg:city":"Grao",
    "sg:orig_category":"Agencias Y Agentes Comerciales, Representantes",
    "sg:phone":"+34 964 58 85 77",
    "sg:postcode":"12593",
    "sg:province":"Castell\u00f3n",
    "wof:name":"Sanchez Benito Angel",
    "wof:placetype":"venue"
},
  "geometry": {"coordinates":[-0.1429889947,39.8067741394],"type":"Point"}
}