{
  "type": "Feature",
  "properties": {
    "iso:country":"ES",
    "sg:address":"Calle de Palomares (de Los), 22",
    "sg:city":"Algete",
    "sg:orig_category":"Alumbrados",
    "sg:phone":"+34 916 29 03 01",
    "sg:postcode":"28110",
    "sg:province":"Madrid",
    "wof:name":"Maestre Mu\u00f1oz Enrique",
    "wof:placetype":"venue"
},
  "geometry": {"coordinates":[-3.5007939339,40.5975532532],"type":"Point"}
}