{
  "type": "Feature",
  "properties": {
    "iso:country":"ES",
    "sg:address":"Calle de Juan De Dios Diaz, 41",
    "sg:city":"Real S. Vicente",
    "sg:classifiers":[
        {
            "category":"Taxi",
            "type":"Transportation"
        }
    ],
    "sg:phone":"+34 925 87 93 51",
    "sg:postcode":"45640",
    "sg:province":"Toledo",
    "wof:name":"Ruiz Garrido Jesus",
    "wof:placetype":"venue"
},
  "geometry": {"coordinates":[-4.6925091743,40.1328697205],"type":"Point"}
}