{
  "type": "Feature",
  "properties": {
    "addr:full":"Carr Sant Llatzer, 24 Figueres Girona 17600",
    "addr:housenumber":"24",
    "addr:postcode":"17600",
    "addr:street":"Carr Sant Llatzer",
    "iso:country":"ES",
    "sg:address":"Carr Sant Llatzer, 24",
    "sg:city":"Figueres",
    "sg:orig_category":"Ense\u00d1anza: Profesiones Art\u00cdsticas",
    "sg:phone":"+34 972 67 37 56",
    "sg:postcode":"17600",
    "sg:province":"Girona",
    "wof:name":"Hierro Codina Pedro",
    "wof:placetype":"venue"
},
  "geometry": {"coordinates":[2.9646070004,42.2646446228],"type":"Point"}
}