{
  "type": "Feature",
  "properties": {
    "iso:country":"ES",
    "sg:address":"Calle de Kurene, 6",
    "sg:city":"Moreaga",
    "sg:orig_category":"Florister\u00cdas",
    "sg:phone":"+34 946 76 45 27",
    "sg:postcode":"48600",
    "sg:province":"Vizcaya",
    "wof:name":"Blanco Pomposo Igone",
    "wof:placetype":"venue"
},
  "geometry": {"coordinates":[-2.9802730083,43.3807220459],"type":"Point"}
}