{
  "type": "Feature",
  "properties": {
    "addr:full":"Carrer de Porvenir, S/n Casco Urbano Barcelona 08450",
    "addr:housenumber":"s / n",
    "addr:postcode":"08450",
    "addr:street":"Carrer De Porvenir",
    "iso:country":"ES",
    "sg:address":"Carrer de Porvenir, S/n",
    "sg:city":"Casco Urbano",
    "sg:orig_category":"Cerrajer\u00cda, Ferrallista",
    "sg:phone":"+34 938 41 25 63",
    "sg:postcode":"08450",
    "sg:province":"Barcelona",
    "sg:website":"www.soler-seguridad.com",
    "wof:name":"Seguridad Fisica S.l.",
    "wof:placetype":"venue"
},
  "geometry": {"coordinates":[2.4019749165,41.6397705078],"type":"Point"}
}