{
  "type": "Feature",
  "properties": {
    "iso:country":"ES",
    "sg:address":"Pintor Sabater, 4",
    "sg:city":"Sedavi",
    "sg:orig_category":"Artes Gr\u00c1ficas, Artes Pl\u00c1sticas (curso)",
    "sg:phone":"+34 963 96 38 19",
    "sg:postcode":"46910",
    "sg:province":"Valencia",
    "wof:name":"Sistemas Y Formas Perez Company S.l.",
    "wof:placetype":"venue"
},
  "geometry": {"coordinates":[-0.3765799999,39.4254379272],"type":"Point"}
}