{
  "type": "Feature",
  "properties": {
    "iso:country":"ES",
    "sg:address":"Carrer de L'alcalde De Mostoles, 49",
    "sg:city":"Barcelona",
    "sg:orig_category":"Agentes Generales De Seguros",
    "sg:phone":"+34 934 35 84 48",
    "sg:postcode":"08025",
    "sg:province":"Barcelona",
    "wof:name":"Assessorament Gestio C.coronel S.l.",
    "wof:placetype":"venue"
},
  "geometry": {"coordinates":[2.1651875973,41.4115447998],"type":"Point"}
}