{
  "type": "Feature",
  "properties": {
    "addr:full":"Carrer de Sant Lloren\u00c7, 23 Cambrils Badia Tarragona 43850",
    "addr:housenumber":"23",
    "addr:postcode":"43850",
    "addr:street":"Carrer De Sant Llorenc\u0327",
    "iso:country":"ES",
    "sg:address":"Carrer de Sant Lloren\u00c7, 23",
    "sg:city":"Cambrils Badia",
    "sg:orig_category":"Importaci\u00d3n",
    "sg:phone":"+34 977 79 22 49",
    "sg:postcode":"43850",
    "sg:province":"Tarragona",
    "wof:name":"Sodemin S. L.",
    "wof:placetype":"venue"
},
  "geometry": {"coordinates":[1.0756649971,41.0697822571],"type":"Point"}
}