{
  "type": "Feature",
  "properties": {
    "iso:country":"ES",
    "sg:address":"Carrer de Serafi Julia, 26",
    "sg:city":"S. Esteve Sesrovires",
    "sg:orig_category":"Peluqueros: De Se\u00d1oras",
    "sg:phone":"+34 937 71 32 34",
    "sg:postcode":"08635",
    "sg:province":"Barcelona",
    "wof:name":"Martinez Molina Isabel",
    "wof:placetype":"venue"
},
  "geometry": {"coordinates":[1.8730169535,41.4941482544],"type":"Point"}
}