{
  "type": "Feature",
  "properties": {
    "addr:full":"Polig Arrayanes, S/n Linares Ja\u00e9n 23700",
    "addr:housenumber":"s / n",
    "addr:postcode":"23700",
    "addr:street":"Polig Arrayanes;Jae\u0301N",
    "iso:country":"ES",
    "sg:address":"Polig Arrayanes, S/n",
    "sg:city":"Linares",
    "sg:orig_category":"Cajas Para Embalar",
    "sg:phone":"+34 953 69 91 60",
    "sg:postcode":"23700",
    "sg:province":"Ja\u00e9n",
    "wof:name":"Caja Rural De Jaen",
    "wof:placetype":"venue"
},
  "geometry": {"coordinates":[-3.6279289722,38.1343536377],"type":"Point"}
}