{
  "type": "Feature",
  "properties": {
    "iso:country":"ES",
    "sg:address":"Carrer de Volta De La Merce, 3",
    "sg:city":"Palma",
    "sg:orig_category":"Asociaciones, Organismos Culturales Y Socioeducativos",
    "sg:phone":"+34 971 72 05 74",
    "sg:postcode":"07002",
    "sg:province":"Islas Baleares",
    "wof:name":"Federacion Balear De Bandas De Musica Y Asociaciones Musicales",
    "wof:placetype":"venue"
},
  "geometry": {"coordinates":[2.6543951035,39.5728530884],"type":"Point"}
}