{
  "type": "Feature",
  "properties": {
    "iso:country":"ES",
    "sg:address":"Carrer de Sant Jordi, 1",
    "sg:city":"Cambrils",
    "sg:orig_category":"Art\u00cdculos De Regalo (al Por Menor)",
    "sg:phone":"+34 977 79 41 53",
    "sg:postcode":"43850",
    "sg:province":"Tarragona",
    "wof:name":"Mata Llutart Jose Maria",
    "wof:placetype":"venue"
},
  "geometry": {"coordinates":[1.0589649677,41.0656509399],"type":"Point"}
}