{
  "type": "Feature",
  "properties": {
    "iso:country":"ES",
    "sg:address":"Bo. Estacion, 34",
    "sg:city":"Pobes",
    "sg:orig_category":"Contenedores (mercanc\u00cdas)",
    "sg:phone":"+34 945 36 20 23",
    "sg:postcode":"01420",
    "sg:province":"\u00c1lava",
    "wof:name":"Sainz De Aja Perez De Carcamo Esther",
    "wof:placetype":"venue"
},
  "geometry": {"coordinates":[-2.9096889496,42.8032951355],"type":"Point"}
}