{
  "type": "Feature",
  "properties": {
    "iso:country":"ES",
    "sg:address":"Ctra. Andratx, 147",
    "sg:city":"Port Andratx",
    "sg:orig_category":"Peluqueros: De Se\u00d1oras",
    "sg:phone":"+34 971 67 17 52",
    "sg:postcode":"07157",
    "sg:province":"Islas Baleares",
    "wof:name":"Tur Ense\u00f1at Miguel",
    "wof:placetype":"venue"
},
  "geometry": {"coordinates":[2.3837299347,39.5477485657],"type":"Point"}
}