{
  "type": "Feature",
  "properties": {
    "addr:full":"Avda Nuestra Se\u00d1ora De Fatima, 75 Madrid Madrid 28047",
    "addr:housenumber":"75",
    "addr:postcode":"madrid;28047",
    "addr:street":"Avda Nuestra Sen\u0303Ora De Fatima",
    "iso:country":"ES",
    "sg:address":"Avda Nuestra Se\u00d1ora De Fatima, 75",
    "sg:city":"Madrid",
    "sg:orig_category":"Laboratorios Y Cl\u00cdnicas Veterinarias",
    "sg:phone":"+34 915 25 10 07",
    "sg:postcode":"28047",
    "sg:province":"Madrid",
    "wof:name":"Clinica Veterinaria Sirkan C.b.",
    "wof:placetype":"venue"
},
  "geometry": {"coordinates":[-3.7487370968,40.3791007996],"type":"Point"}
}