{
  "type": "Feature",
  "properties": {
    "iso:country":"ES",
    "sg:address":"La Palma, 2",
    "sg:city":"Coin",
    "sg:orig_category":"Agencias Y Agentes Comerciales, Representantes",
    "sg:phone":"+34 952 45 42 35",
    "sg:postcode":"29100",
    "sg:province":"M\u00e1laga",
    "wof:name":"Valdivia Berroca Andres",
    "wof:placetype":"venue"
},
  "geometry": {"coordinates":[-4.7516088486,36.6633148193],"type":"Point"}
}