{
  "type": "Feature",
  "properties": {
    "addr:full":"Calle de Canonigo Torres, 3 Torrevieja Alicante 03180",
    "addr:housenumber":"3",
    "addr:postcode":"03180",
    "addr:street":"Calle De Canonigo Torres",
    "iso:country":"ES",
    "sg:address":"Calle de Canonigo Torres, 3",
    "sg:city":"Torrevieja",
    "sg:orig_category":"Ropa Para Se\u00d1oras Y Caballeros (al Por Menor)",
    "sg:phone":"+34 966 70 15 95",
    "sg:postcode":"03180",
    "sg:province":"Alicante",
    "wof:name":"Vegas Gutierrez Felicidad",
    "wof:placetype":"venue"
},
  "geometry": {"coordinates":[-0.6834545732,37.9761657715],"type":"Point"}
}