{
  "type": "Feature",
  "properties": {
    "iso:country":"ES",
    "sg:address":"Calle de General Moscardo, 6",
    "sg:city":"Toledo",
    "sg:orig_category":"Asociaciones Humanitarias, De Cooperaci\u00d3n, De Acci\u00d3n Social",
    "sg:phone":"+34 925 25 06 93",
    "sg:postcode":"45001",
    "sg:province":"Toledo",
    "wof:name":"Asociacion De Diabeticos De Toledo",
    "wof:placetype":"venue"
},
  "geometry": {"coordinates":[-4.0202822685,39.8574066162],"type":"Point"}
}