{
  "type": "Feature",
  "properties": {
    "iso:country":"ES",
    "sg:address":"Carr Roca Labrador, 25",
    "sg:city":"Lleida",
    "sg:orig_category":"Cristaler\u00cdas",
    "sg:phone":"+34 973 26 49 01",
    "sg:postcode":"25003",
    "sg:province":"Lleida",
    "wof:name":"Inoxvidre S.l.",
    "wof:placetype":"venue"
},
  "geometry": {"coordinates":[0.615218997,41.6141395569],"type":"Point"}
}