{
  "type": "Feature",
  "properties": {
    "addr:full":"Carrer de Sobrerroca, 40 Manresa Barcelona 08241",
    "addr:housenumber":"40",
    "addr:postcode":"08241",
    "addr:street":"Carrer De Sobrerroca",
    "iso:country":"ES",
    "sg:address":"Carrer de Sobrerroca, 40",
    "sg:city":"Manresa",
    "sg:orig_category":"Farmacias",
    "sg:phone":"+34 938 72 21 80",
    "sg:postcode":"08241",
    "sg:province":"Barcelona",
    "wof:name":"Trape Pujol Josep",
    "wof:placetype":"venue"
},
  "geometry": {"coordinates":[1.8281129599,41.7247428894],"type":"Point"}
}