{
  "type": "Feature",
  "properties": {
    "addr:full":"Carr Verge De Montserrat, 6 Mollerussa Lleida 25230",
    "addr:housenumber":"6",
    "addr:postcode":"25230",
    "addr:street":"Carr Verge De Montserrat",
    "iso:country":"ES",
    "sg:address":"Carr Verge De Montserrat, 6",
    "sg:city":"Mollerussa",
    "sg:orig_category":"Cerrajer\u00cda, Ferrallista",
    "sg:phone":"+34 973 60 12 03",
    "sg:postcode":"25230",
    "sg:province":"Lleida",
    "wof:name":"Cuchilleria Delgado S.c.c.l.",
    "wof:placetype":"venue"
},
  "geometry": {"coordinates":[0.894611001,41.6281814575],"type":"Point"}
}