{
  "type": "Feature",
  "properties": {
    "iso:country":"ES",
    "sg:address":"Carrer de L'escultor Canet, 7",
    "sg:city":"Barcelona",
    "sg:orig_category":"Promotores Constructores",
    "sg:phone":"+34 932 96 48 52",
    "sg:postcode":"08028",
    "sg:province":"Barcelona",
    "wof:name":"Toledano Mu\u00f1oz Jose",
    "wof:placetype":"venue"
},
  "geometry": {"coordinates":[2.1278009415,41.374042511],"type":"Point"}
}