{
  "type": "Feature",
  "properties": {
    "iso:country":"ES",
    "sg:address":"Carrer de Sant Jaume, 129",
    "sg:city":"Eixample",
    "sg:orig_category":"Alimentaci\u00d3n General (al Por Menor)",
    "sg:phone":"+34 935 73 04 95",
    "sg:postcode":"08150",
    "sg:province":"Barcelona",
    "wof:name":"Martorell Roura Maria Antonia",
    "wof:placetype":"venue"
},
  "geometry": {"coordinates":[2.2293000221,41.5678787231],"type":"Point"}
}