{
  "type": "Feature",
  "properties": {
    "iso:country":"ES",
    "sg:address":"Carrer de Portugal, 13",
    "sg:city":"Hospitalet Llobregat",
    "sg:orig_category":"Empresas De Limpieza",
    "sg:phone":"+34 933 36 53 98",
    "sg:postcode":"08907",
    "sg:province":"Barcelona",
    "wof:name":"Portugal 13 S.l.",
    "wof:placetype":"venue"
},
  "geometry": {"coordinates":[2.110558033,41.3550796509],"type":"Point"}
}