{
  "type": "Feature",
  "properties": {
    "addr:full":"Calle de Carlos Iii, 3 San Miguel Murcia 30008",
    "addr:housenumber":"3",
    "addr:postcode":"30008",
    "addr:street":"Calle De Carlos Iii",
    "iso:country":"ES",
    "sg:address":"Calle de Carlos Iii, 3",
    "sg:city":"San Miguel",
    "sg:orig_category":"Mercer\u00cda (fabricaci\u00d3n, Al Por Mayor)",
    "sg:phone":"+34 968 23 98 55",
    "sg:postcode":"30008",
    "sg:province":"Murcia",
    "wof:name":"Alarcon Lopez Maria Teresa",
    "wof:placetype":"venue"
},
  "geometry": {"coordinates":[-1.1309378147,37.989112854],"type":"Point"}
}