{
  "type": "Feature",
  "properties": {
    "iso:country":"ES",
    "sg:address":"Carrer de Arimon, 54",
    "sg:city":"Barcelona",
    "sg:orig_category":"Pescader\u00cdas (al Por Menor)",
    "sg:phone":"+34 934 18 02 14",
    "sg:postcode":"08022",
    "sg:province":"Barcelona",
    "wof:name":"Espinosa Cabetas Manuel",
    "wof:placetype":"venue"
},
  "geometry": {"coordinates":[2.1355159283,41.4029884338],"type":"Point"}
}