{
  "type": "Feature",
  "properties": {
    "iso:country":"ES",
    "sg:address":"Plaz Cuatro Ca\u00d1os, 4",
    "sg:city":"Collado Villalba",
    "sg:orig_category":"Mec\u00c1nico Del Autom\u00d3vil",
    "sg:phone":"+34 918 50 35 75",
    "sg:postcode":"28400",
    "sg:province":"Madrid",
    "wof:name":"Enrique Tejera S.l.",
    "wof:placetype":"venue"
},
  "geometry": {"coordinates":[-4.0064492226,40.6153297424],"type":"Point"}
}