{
  "type": "Feature",
  "properties": {
    "addr:full":"Carrer de Espartero, 21 Caldes Montbui Barcelona 08140",
    "addr:housenumber":"21",
    "addr:postcode":"08140",
    "addr:street":"Carrer De Espartero;Montbui Barcelona",
    "iso:country":"ES",
    "sg:address":"Carrer de Espartero, 21",
    "sg:city":"Caldes Montbui",
    "sg:orig_category":"Cerrajer\u00cda, Ferrallista",
    "sg:phone":"+34 938 65 10 19",
    "sg:postcode":"08140",
    "sg:province":"Barcelona",
    "wof:name":"Tallers Boluda Iba\u00f1ez C.b.",
    "wof:placetype":"venue"
},
  "geometry": {"coordinates":[2.1651480198,41.6322937012],"type":"Point"}
}