{
  "type": "Feature",
  "properties": {
    "iso:country":"ES",
    "sg:address":"Calle de Ayala, 5",
    "sg:city":"Don Benito",
    "sg:orig_category":"Ropa Para Ni\u00d1os (al Por Menor)",
    "sg:phone":"+34 924 80 82 40",
    "sg:postcode":"06400",
    "sg:province":"Badajoz",
    "wof:name":"Parquecillos S.l.",
    "wof:placetype":"venue"
},
  "geometry": {"coordinates":[-5.8600420952,38.9616508484],"type":"Point"}
}