{
  "type": "Feature",
  "properties": {
    "addr:full":"Ctra Carrion, 7 Almagro Ciudad Real 13270",
    "addr:housenumber":"7",
    "addr:postcode":"13270",
    "addr:street":"Ctra Carrion",
    "iso:country":"ES",
    "sg:address":"Ctra Carrion, 7",
    "sg:city":"Almagro",
    "sg:orig_category":"Art\u00cdculos De Madera (fabricaci\u00d3n Y Al Por Mayor)",
    "sg:phone":"+34 926 86 05 60",
    "sg:postcode":"13270",
    "sg:province":"Ciudad Real",
    "sg:website":"www.josico.com",
    "wof:name":"Carpinteria Josico S.l.",
    "wof:placetype":"venue"
},
  "geometry": {"coordinates":[-3.7164590359,38.8968544006],"type":"Point"}
}