{
  "type": "Feature",
  "properties": {
    "addr:full":"Carrer de Noruega, 2 Sant Agusti Islas Baleares 07015",
    "addr:housenumber":"2",
    "addr:postcode":"07015",
    "addr:street":"Carrer De Noruega",
    "iso:country":"ES",
    "sg:address":"Carrer de Noruega, 2",
    "sg:city":"Sant Agusti",
    "sg:orig_category":"Embajadas, Consulados Y Otras Representaciones Diplom\u00c1ticas",
    "sg:phone":"+34 971 40 33 07",
    "sg:postcode":"07015",
    "sg:province":"Islas Baleares",
    "wof:name":"Miralles Celant Juan Carlos",
    "wof:placetype":"venue"
},
  "geometry": {"coordinates":[2.5930919647,39.5524673462],"type":"Point"}
}