{
  "type": "Feature",
  "properties": {
    "iso:country":"ES",
    "sg:address":"Carrer de Pare Bartomeu Pou, 11",
    "sg:city":"Palma",
    "sg:orig_category":"Trabajos De Topograf\u00cda",
    "sg:phone":"+34 971 20 01 19",
    "sg:postcode":"07003",
    "sg:province":"Islas Baleares",
    "wof:name":"Lougedo Calderon Alfonso",
    "wof:placetype":"venue"
},
  "geometry": {"coordinates":[2.651747942,39.5813179016],"type":"Point"}
}