{
  "type": "Feature",
  "properties": {
    "iso:country":"ES",
    "sg:address":"Calle de Cuesta Del Matadero, 6",
    "sg:city":"Chiclana De La Frontera",
    "sg:orig_category":"M\u00c1quinas De Coser Y De Hacer Punto (al Por Mayor)",
    "sg:phone":"+34 956 53 33 97",
    "sg:postcode":"11130",
    "sg:province":"C\u00e1diz",
    "wof:name":"Riquet Bejarano Manuel",
    "wof:placetype":"venue"
},
  "geometry": {"coordinates":[-6.1457400322,36.41639328],"type":"Point"}
}