{
  "type": "Feature",
  "properties": {
    "iso:country":"ES",
    "sg:address":"Plaz Grande, 7",
    "sg:city":"Zafra",
    "sg:orig_category":"Pintura, Barniz, Productos Asimilables (fabricaci\u00d3n, Al Por Mayor)",
    "sg:phone":"+34 924 55 09 93",
    "sg:postcode":"06300",
    "sg:province":"Badajoz",
    "wof:name":"Centro De Pinturas Decoral S.l.",
    "wof:placetype":"venue"
},
  "geometry": {"coordinates":[-6.4194259644,38.4255065918],"type":"Point"}
}