{
  "type": "Feature",
  "properties": {
    "addr:full":"Ctra Gomara, Km. 0192,0 Almazan Soria 42200",
    "addr:postcode":"42200",
    "addr:street":"Ctra Gomara Km. 0192,0",
    "iso:country":"ES",
    "sg:address":"Ctra Gomara, Km. 0192,0",
    "sg:city":"Almazan",
    "sg:orig_category":"Distribuci\u00d3n De Petr\u00d3leo Y Derivados",
    "sg:phone":"+34 975 31 01 63",
    "sg:postcode":"42200",
    "sg:province":"Soria",
    "wof:name":"Repsol Ypf S.a.",
    "wof:placetype":"venue"
},
  "geometry": {"coordinates":[-2.5245800018,41.4865493774],"type":"Point"}
}