{
  "type": "Feature",
  "properties": {
    "iso:country":"ES",
    "sg:address":"Rua Revolta, 9",
    "sg:city":"Revolta",
    "sg:orig_category":"Alimentaci\u00d3n General (al Por Menor)",
    "sg:phone":"+34 986 71 01 95",
    "sg:postcode":"36636",
    "sg:province":"Pontevedra",
    "wof:name":"Noya Cons Manuel",
    "wof:placetype":"venue"
},
  "geometry": {"coordinates":[-8.7683343887,42.5012207031],"type":"Point"}
}