{
  "type": "Feature",
  "properties": {
    "iso:country":"ES",
    "sg:address":"Avda Virgen De La Monta\u00d1a, 28",
    "sg:city":"Caceres",
    "sg:orig_category":"Molduras, Junquillos, Listones Y Molduras Perforadas",
    "sg:phone":"+34 927 24 32 66",
    "sg:postcode":"10004",
    "sg:province":"C\u00e1ceres",
    "wof:name":"Falque Salbide Miren Itziar",
    "wof:placetype":"venue"
},
  "geometry": {"coordinates":[-6.3583831787,39.5027656555],"type":"Point"}
}