{
  "type": "Feature",
  "properties": {
    "addr:full":"Poligono San Lazaro, S/n Sto. Domingo Calzada La Rioja 26250",
    "addr:postcode":"26250",
    "addr:street":"San Lazaro S / N Sto. Domingo Calzada;Rioja",
    "iso:country":"ES",
    "sg:address":"Poligono San Lazaro, S/n",
    "sg:city":"Sto. Domingo Calzada",
    "sg:orig_category":"Mantenimiento Industrial",
    "sg:phone":"+34 941 34 16 90",
    "sg:postcode":"26250",
    "sg:province":"La Rioja",
    "wof:name":"Ca\u00f1as Cardenas Martin",
    "wof:placetype":"venue"
},
  "geometry": {"coordinates":[-2.9541339874,42.4394760132],"type":"Point"}
}