{
  "type": "Feature",
  "properties": {
    "iso:country":"ES",
    "sg:address":"Carrer de Gran De Sant Andreu, 36",
    "sg:city":"Barcelona",
    "sg:orig_category":"Supermercados Y Hipermercados",
    "sg:phone":"+34 933 11 80 01",
    "sg:postcode":"08030",
    "sg:province":"Barcelona",
    "wof:name":"Bon-preu S.a.",
    "wof:placetype":"venue"
},
  "geometry": {"coordinates":[2.1906449795,41.4286613464],"type":"Point"}
}