{
  "type": "Feature",
  "properties": {
    "iso:country":"ES",
    "sg:address":"Ctra. Es Canar, 9",
    "sg:city":"Sta. Eularia Riu",
    "sg:orig_category":"M\u00c9dicos: Naturistas",
    "sg:phone":"+34 971 33 16 79",
    "sg:postcode":"07840",
    "sg:province":"Islas Baleares",
    "wof:name":"Mar Estar 2005 S.l.",
    "wof:placetype":"venue"
},
  "geometry": {"coordinates":[1.547279954,38.9919815063],"type":"Point"}
}