{
  "type": "Feature",
  "properties": {
    "addr:full":"Ctra Cortijo, Km. 0001,5 Logro\u00f1o La Rioja 26006",
    "addr:postcode":"26006",
    "addr:street":"Ctra Cortijo Km. 0001,5 Logron\u0303O;Rioja",
    "iso:country":"ES",
    "sg:address":"Ctra Cortijo, Km. 0001,5",
    "sg:city":"Logro\u00f1o",
    "sg:orig_category":"Maquinaria Y Herramientas Para Madera, Pvc, Aluminio Y Aperos (fabricaci\u00d3n, Comercio)",
    "sg:phone":"+34 941 22 32 79",
    "sg:postcode":"26006",
    "sg:province":"La Rioja",
    "wof:name":"Barrasa S.l.",
    "wof:placetype":"venue"
},
  "geometry": {"coordinates":[-2.4036989212,42.46043396],"type":"Point"}
}