{
  "type": "Feature",
  "properties": {
    "iso:country":"ES",
    "sg:address":"C/ Poeta Miguel Hernandez, 69",
    "sg:city":"Elche",
    "sg:orig_category":"Fabricaci\u00d3n, Importaci\u00d3n De Material Y Sistemas De Telecomunicaciones",
    "sg:phone":"+34 965 44 47 74",
    "sg:postcode":"03201",
    "sg:province":"Alicante",
    "wof:name":"Tecnitelex S. L.",
    "wof:placetype":"venue"
},
  "geometry": {"coordinates":[-0.7074990273,38.2644348145],"type":"Point"}
}