{
  "type": "Feature",
  "properties": {
    "iso:country":"ES",
    "sg:address":"Calle de Zenit, 8",
    "sg:city":"Madrid",
    "sg:orig_category":"Panader\u00cdas, Panader\u00cdas",
    "sg:phone":"+34 913 57 49 49",
    "sg:postcode":"28023",
    "sg:province":"Madrid",
    "wof:name":"Garcia Dominguez Francisco Jose",
    "wof:placetype":"venue"
},
  "geometry": {"coordinates":[-3.7892251015,40.4635429382],"type":"Point"}
}