{
  "type": "Feature",
  "properties": {
    "iso:country":"ES",
    "sg:address":"Calle de Bidasoa Kalea, 4",
    "sg:city":"Irun",
    "sg:orig_category":"Molduras, Junquillos, Listones Y Molduras Perforadas",
    "sg:phone":"+34 943 62 11 91",
    "sg:postcode":"20304",
    "sg:province":"Guip\u00f9zcoa",
    "wof:name":"Call Phone S.l.",
    "wof:placetype":"venue"
},
  "geometry": {"coordinates":[-1.7863889933,43.3429870605],"type":"Point"}
}