{
  "type": "Feature",
  "properties": {
    "addr:full":"Carrer de Nord, 24 Vilafranca Penedes Barcelona 08720",
    "addr:housenumber":"24",
    "addr:postcode":"08720",
    "addr:street":"Carrer De Nord;Penedes Barcelona",
    "iso:country":"ES",
    "sg:address":"Carrer de Nord, 24",
    "sg:city":"Vilafranca Penedes",
    "sg:orig_category":"Suministros Y Materiales Industriales",
    "sg:phone":"+34 938 92 42 51",
    "sg:postcode":"08720",
    "sg:province":"Barcelona",
    "wof:name":"Automatizacion Industrial Kasmar S.l.",
    "wof:placetype":"venue"
},
  "geometry": {"coordinates":[1.7021809816,41.3509750366],"type":"Point"}
}