{
  "type": "Feature",
  "properties": {
    "addr:full":"Carrer de Violant Hongria R Arago, 64 Barcelona Barcelona 08028",
    "addr:housenumber":"hongria;64",
    "addr:postcode":"08028",
    "addr:street":"Carrer De Violant;R Arago",
    "iso:country":"ES",
    "sg:address":"Carrer de Violant Hongria R Arago, 64",
    "sg:city":"Barcelona",
    "sg:orig_category":"Asesor\u00cda Fiscal Y Jur\u00cddica",
    "sg:phone":"+34 934 90 08 40",
    "sg:postcode":"08028",
    "sg:province":"Barcelona",
    "wof:name":"64 Vh Assessors S.l.",
    "wof:placetype":"venue"
},
  "geometry": {"coordinates":[2.129868,41.378597],"type":"Point"}
}