{
  "type": "Feature",
  "properties": {
    "iso:country":"ES",
    "sg:address":"Calle de Barratxi, 41",
    "sg:city":"Vitoria-gasteiz",
    "sg:orig_category":"Aguas (distribuci\u00d3n, Servicios)",
    "sg:phone":"+34 945 25 09 92",
    "sg:postcode":"01013",
    "sg:province":"\u00c1lava",
    "wof:name":"Uriarte Pagalday S.l.",
    "wof:placetype":"venue"
},
  "geometry": {"coordinates":[-2.6840889454,42.8761367798],"type":"Point"}
}