{
  "type": "Feature",
  "properties": {
    "addr:full":"Calle de Severo Ochoa, 58 Ciudad Rodrigo Salamanca 37500",
    "addr:housenumber":"58",
    "addr:postcode":"37500",
    "addr:street":"Calle De Severo Ochoa",
    "iso:country":"ES",
    "sg:address":"Calle de Severo Ochoa, 58",
    "sg:city":"Ciudad Rodrigo",
    "sg:orig_category":"Promotores Constructores",
    "sg:phone":"+34 923 48 12 16",
    "sg:postcode":"37500",
    "sg:province":"Salamanca",
    "wof:name":"Fandi\u00f1o Molinero Angel",
    "wof:placetype":"venue"
},
  "geometry": {"coordinates":[-6.5222678185,40.5979003906],"type":"Point"}
}