{
  "type": "Feature",
  "properties": {
    "addr:full":"Avda Andalucia, 24 Cadiz C\u00e1diz 11008",
    "addr:housenumber":"24",
    "addr:postcode":"11008",
    "addr:street":"Avda Andalucia",
    "iso:country":"ES",
    "sg:address":"Avda Andalucia, 24",
    "sg:city":"Cadiz",
    "sg:orig_category":"Centros P\u00dablicos De Formaci\u00d3n Profesional Y T\u00c9cnica",
    "sg:phone":"+34 956 27 25 03",
    "sg:postcode":"11008",
    "sg:province":"C\u00e1diz",
    "wof:name":"Colegio Oficial De Graduados Sociales De Cadiz",
    "wof:placetype":"venue"
},
  "geometry": {"coordinates":[-6.2858791351,36.5217857361],"type":"Point"}
}