{
  "type": "Feature",
  "properties": {
    "iso:country":"ES",
    "sg:address":"Carretera Carbayo, 43",
    "sg:city":"Ferreras Abajo",
    "sg:orig_category":"Florister\u00cdas",
    "sg:phone":"+34 980 59 20 07",
    "sg:postcode":"49135",
    "sg:province":"Zamora",
    "wof:name":"Zamodie S.a.",
    "wof:placetype":"venue"
},
  "geometry": {"coordinates":[-6.0706572533,41.8993797302],"type":"Point"}
}