{
  "type": "Feature",
  "properties": {
    "addr:full":"Ctra General Del Sur, Km. 0006,5 Tincer Santa Cruz De Tenerife 38108",
    "addr:postcode":"38108",
    "addr:street":"Ctra General Del Sur Km. 0006,5 Tincer",
    "iso:country":"ES",
    "sg:address":"Ctra General Del Sur, Km. 0006,5",
    "sg:city":"Tincer",
    "sg:orig_category":"Venta, Colocaci\u00d3n, Reparaci\u00d3n De Radiadores Para Veh\u00cdculos",
    "sg:phone":"+34 922 61 48 05",
    "sg:postcode":"38108",
    "sg:province":"Santa Cruz De Tenerife",
    "wof:name":"Ramos Bermudez Jose",
    "wof:placetype":"venue"
},
  "geometry": {"coordinates":[-16.2957706451,28.4491081238],"type":"Point"}
}