{
  "type": "Feature",
  "properties": {
    "addr:full":"Calle de Albacete, 4 Valladolid Valladolid 47012",
    "addr:housenumber":"4",
    "addr:postcode":"47012",
    "addr:street":"Calle De Albacete",
    "iso:country":"ES",
    "sg:address":"Calle de Albacete, 4",
    "sg:city":"Valladolid",
    "sg:orig_category":"Promotores Constructores",
    "sg:phone":"+34 983 21 18 03",
    "sg:postcode":"47012",
    "sg:province":"Valladolid",
    "wof:name":"Urbanizaciones Y Topografias 2004 Sl",
    "wof:placetype":"venue"
},
  "geometry": {"coordinates":[-4.7150549889,41.6422042847],"type":"Point"}
}