{
  "type": "Feature",
  "properties": {
    "addr:full":"Calle de Heroes Alcazar De Toledo, 1 Valladolid Valladolid 47001",
    "addr:housenumber":"1",
    "addr:postcode":"47001",
    "addr:street":"Calle De Heroes Alcazar De Toledo",
    "iso:country":"ES",
    "sg:address":"Calle de Heroes Alcazar De Toledo, 1",
    "sg:city":"Valladolid",
    "sg:orig_category":"Bisuter\u00cda, Joyer\u00cda, Relojer\u00cda (al Por Menor)",
    "sg:phone":"+34 983 34 23 40",
    "sg:postcode":"47001",
    "sg:province":"Valladolid",
    "wof:name":"Sanchez San Miguel Angel",
    "wof:placetype":"venue"
},
  "geometry": {"coordinates":[-4.7294788361,41.65051651],"type":"Point"}
}