{
  "type": "Feature",
  "properties": {
    "addr:full":"Barr Maza (la), S/n San Miguel De Meruelo Cantabria 39192",
    "addr:housenumber":"/ n",
    "addr:postcode":"39192",
    "addr:street":"La S",
    "iso:country":"ES",
    "sg:address":"Barr Maza (la), S/n",
    "sg:city":"San Miguel De Meruelo",
    "sg:orig_category":"Cajas De Ahorro",
    "sg:phone":"+34 942 63 70 13",
    "sg:postcode":"39192",
    "sg:province":"Cantabria",
    "sg:website":"www.cajacantabria.es",
    "wof:name":"Cableuropa",
    "wof:placetype":"venue"
},
  "geometry": {"coordinates":[-3.5817580223,43.4589347839],"type":"Point"}
}