{
  "type": "Feature",
  "properties": {
    "addr:full":"Calle de Santa Isabel, 39 Santa Pola Alicante 03130",
    "addr:housenumber":"39",
    "addr:postcode":"03130",
    "addr:street":"Calle De Santa Isabel",
    "iso:country":"ES",
    "sg:address":"Calle de Santa Isabel, 39",
    "sg:city":"Santa Pola",
    "sg:orig_category":"Promotores Constructores",
    "sg:phone":"+34 966 69 46 75",
    "sg:postcode":"03130",
    "sg:province":"Alicante",
    "wof:name":"Construcciones Noray S.c.",
    "wof:placetype":"venue"
},
  "geometry": {"coordinates":[-0.5568140149,38.1930961609],"type":"Point"}
}