{
  "type": "Feature",
  "properties": {
    "iso:country":"ES",
    "sg:address":"Av Madrid-valencia, 8",
    "sg:city":"Saelices",
    "sg:orig_category":"Farmacias",
    "sg:phone":"+34 969 13 20 41",
    "sg:postcode":"16430",
    "sg:province":"Cuenca",
    "wof:name":"Olmedo Lopez Sagrario",
    "wof:placetype":"venue"
},
  "geometry": {"coordinates":[-2.8077409267,39.9192581177],"type":"Point"}
}