{
  "type": "Feature",
  "properties": {
    "iso:country":"ES",
    "sg:address":"Calle de Vereda De Los Barros, 18",
    "sg:city":"Ventorro Del Cano",
    "sg:orig_category":"Venta, Instalaci\u00d3n De Calefacci\u00d3n",
    "sg:phone":"+34 916 33 06 12",
    "sg:postcode":"28925",
    "sg:province":"Madrid",
    "wof:name":"Jofeg S.a.",
    "wof:placetype":"venue"
},
  "geometry": {"coordinates":[-3.8397541046,40.3913192749],"type":"Point"}
}