{
  "type": "Feature",
  "properties": {
    "iso:country":"ES",
    "sg:address":"Calle de Benigafull, 28",
    "sg:city":"Vall D'uixo",
    "sg:orig_category":"Institutos De Belleza",
    "sg:phone":"+34 964 69 66 35",
    "sg:postcode":"12600",
    "sg:province":"Castell\u00f3n",
    "wof:name":"Arenos Forner Milagros",
    "wof:placetype":"venue"
},
  "geometry": {"coordinates":[-0.2341724038,39.8229751587],"type":"Point"}
}