{
  "type": "Feature",
  "properties": {
    "iso:country":"ES",
    "sg:address":"Calle de Viacampo, S/n",
    "sg:city":"Calahorra",
    "sg:orig_category":"Inmobiliaria (agencias)",
    "sg:phone":"+34 941 13 01 07",
    "sg:postcode":"26500",
    "sg:province":"La Rioja",
    "wof:name":"Materializacion De Ideas S.l.",
    "wof:placetype":"venue"
},
  "geometry": {"coordinates":[-1.9588303566,42.3105964661],"type":"Point"}
}