{
  "type": "Feature",
  "properties": {
    "addr:full":"Cami Sant Crist (del), 58 Mataro Barcelona 08302",
    "addr:postcode":"08302",
    "addr:street":"Sant;Del 58",
    "iso:country":"ES",
    "sg:address":"Cami Sant Crist (del), 58",
    "sg:city":"Mataro",
    "sg:orig_category":"Alquiler De Gr\u00daas",
    "sg:phone":"+34 937 50 10 71",
    "sg:postcode":"08302",
    "sg:province":"Barcelona",
    "wof:name":"Grues De Mataro S.c.c.l.",
    "wof:placetype":"venue"
},
  "geometry": {"coordinates":[2.4288070202,41.5304489136],"type":"Point"}
}