{
  "type": "Feature",
  "properties": {
    "addr:full":"Calle de Delicias, 10 Madrid Madrid 28045",
    "addr:housenumber":"10",
    "addr:postcode":"madrid;28045",
    "addr:street":"Calle De Delicias",
    "iso:country":"ES",
    "sg:address":"Calle de Delicias, 10",
    "sg:city":"Madrid",
    "sg:orig_category":"Servicio De Salud",
    "sg:phone":"+34 914 68 44 80",
    "sg:postcode":"28045",
    "sg:province":"Madrid",
    "wof:name":"Gomez Garcia-vaquero Emilio",
    "wof:placetype":"venue"
},
  "geometry": {"coordinates":[-3.6945483685,40.4041633606],"type":"Point"}
}