{
  "type": "Feature",
  "properties": {
    "iso:country":"ES",
    "sg:address":"Cra Espinel, 20",
    "sg:city":"Ronda",
    "sg:orig_category":"Bisuter\u00cda, Joyer\u00cda, Relojer\u00cda (al Por Menor)",
    "sg:phone":"+34 952 87 17 11",
    "sg:postcode":"29400",
    "sg:province":"M\u00e1laga",
    "wof:name":"Granados Sede\u00f1o Miguel",
    "wof:placetype":"venue"
},
  "geometry": {"coordinates":[-5.165517807,36.7423858643],"type":"Point"}
}