{
  "type": "Feature",
  "properties": {
    "addr:full":"Calle de Isaac Garcia De Quiros, 32 Valencia De Don Juan Le\u00f3n 24200",
    "addr:housenumber":"32",
    "addr:postcode":"24200",
    "addr:street":"Calle De Isaac Garcia De Quiros",
    "iso:country":"ES",
    "sg:address":"Calle de Isaac Garcia De Quiros, 32",
    "sg:city":"Valencia De Don Juan",
    "sg:orig_category":"Quincaller\u00cda (al Por Menor)",
    "sg:phone":"+34 987 75 01 91",
    "sg:postcode":"24200",
    "sg:province":"Le\u00f3n",
    "wof:name":"Fernandez Martinez Maria Ines",
    "wof:placetype":"venue"
},
  "geometry": {"coordinates":[-5.5195999146,42.2927093506],"type":"Point"}
}