{
  "type": "Feature",
  "properties": {
    "addr:full":"Calle de Arzobispo Fuenmayor, 4 Soria Soria 42001",
    "addr:housenumber":"4",
    "addr:postcode":"42001",
    "addr:street":"Calle De Arzobispo Fuenmayor",
    "iso:country":"ES",
    "sg:address":"Calle de Arzobispo Fuenmayor, 4",
    "sg:city":"Soria",
    "sg:orig_category":"Arreglo, Reparaci\u00d3n, Piezas Sueltas De Televisi\u00d3n, V\u00cddeo, Hi",
    "sg:phone":"+34 975 22 96 41",
    "sg:postcode":"42001",
    "sg:province":"Soria",
    "wof:name":"Electronica Nikam S.c",
    "wof:placetype":"venue"
},
  "geometry": {"coordinates":[-2.4712982178,41.7679824829],"type":"Point"}
}