{
  "type": "Feature",
  "properties": {
    "addr:full":"Murtra, 1 S. Jordi Salines Islas Baleares 07817",
    "addr:housenumber":"1",
    "addr:postcode":"07817",
    "addr:street":"Murtra",
    "iso:country":"ES",
    "sg:address":"Murtra, 1",
    "sg:city":"S. Jordi Salines",
    "sg:orig_category":"Art\u00cdculos De Regalo (al Por Menor)",
    "sg:phone":"+34 971 30 03 70",
    "sg:postcode":"07817",
    "sg:province":"Islas Baleares",
    "wof:name":"Zeff Lebedinsky Alberto Eduardo",
    "wof:placetype":"venue"
},
  "geometry": {"coordinates":[2.8577105999,39.5341796875],"type":"Point"}
}