{
  "type": "Feature",
  "properties": {
    "addr:full":"Carrer de Frederica Montseny, 21 Sant Feliu Llobregat Barcelona 08980",
    "addr:housenumber":"21",
    "addr:postcode":"08980",
    "addr:street":"Carrer De Frederica Montseny",
    "iso:country":"ES",
    "sg:address":"Carrer de Frederica Montseny, 21",
    "sg:city":"Sant Feliu Llobregat",
    "sg:orig_category":"Alquiler De V\u00cddeo",
    "sg:phone":"+34 936 32 58 65",
    "sg:postcode":"08980",
    "sg:province":"Barcelona",
    "wof:name":"Tudela Hernandez Xavier",
    "wof:placetype":"venue"
},
  "geometry": {"coordinates":[2.0564119816,41.3860321045],"type":"Point"}
}