{
  "type": "Feature",
  "properties": {
    "addr:full":"Rua Presi\u00d1a (da), 15 Cuntis Pontevedra 36670",
    "addr:housenumber":"15",
    "addr:postcode":"36670",
    "addr:street":"Rua Presin\u0303A Da",
    "iso:country":"ES",
    "sg:address":"Rua Presi\u00d1a (da), 15",
    "sg:city":"Cuntis",
    "sg:orig_category":"Confecci\u00d3n De Zapatos",
    "sg:phone":"+34 986 54 81 68",
    "sg:postcode":"36670",
    "sg:province":"Pontevedra",
    "wof:name":"Cascallar Torres Antonio",
    "wof:placetype":"venue"
},
  "geometry": {"coordinates":[-8.5611791611,42.6424484253],"type":"Point"}
}