{
  "type": "Feature",
  "properties": {
    "iso:country":"ES",
    "sg:address":"Calle de Ferial, 80",
    "sg:city":"Guadalajara",
    "sg:orig_category":"Autob\u00das (explotaci\u00d3n Y Servicios De)",
    "sg:phone":"+34 949 22 33 42",
    "sg:postcode":"19002",
    "sg:province":"Guadalajara",
    "sg:website":"www.autocaresmarin.com",
    "wof:name":"Marin Colmenero Gerardo",
    "wof:placetype":"venue"
},
  "geometry": {"coordinates":[-3.157957077,40.6229095459],"type":"Point"}
}