{
  "type": "Feature",
  "properties": {
    "iso:country":"ES",
    "sg:address":"Calle de Juan Barrau, 12",
    "sg:city":"Tabernas",
    "sg:orig_category":"Marmolistas Funerarios",
    "sg:phone":"+34 950 36 52 64",
    "sg:postcode":"04200",
    "sg:province":"Almer\u00eda",
    "wof:name":"Guerrero Martinez Juan",
    "wof:placetype":"venue"
},
  "geometry": {"coordinates":[-2.3908319473,37.0510177612],"type":"Point"}
}