{
  "type": "Feature",
  "properties": {
    "iso:country":"ES",
    "sg:address":"Joaq. Costa, 2",
    "sg:city":"Loja",
    "sg:orig_category":"Molduras, Junquillos, Listones Y Molduras Perforadas",
    "sg:phone":"+34 958 32 08 17",
    "sg:postcode":"18300",
    "sg:province":"Granada",
    "wof:name":"Lopez Castillo Agustin Y Juan C.b.",
    "wof:placetype":"venue"
},
  "geometry": {"coordinates":[-4.150302887,37.1667861938],"type":"Point"}
}