{
  "type": "Feature",
  "properties": {
    "iso:country":"ES",
    "sg:address":"Ctra. N. 340, S/n",
    "sg:city":"Huercal-overa",
    "sg:orig_category":"Arquitectos",
    "sg:phone":"+34 950 47 10 19",
    "sg:postcode":"04600",
    "sg:province":"Almer\u00eda",
    "wof:name":"Acebo Rodriguez Benjamin",
    "wof:placetype":"venue"
},
  "geometry": {"coordinates":[-1.9436843395,37.390625],"type":"Point"}
}