{
  "type": "Feature",
  "properties": {
    "addr:full":"C/ 126, 3 Ca\u00d1ada Valencia 46182",
    "addr:housenumber":"3",
    "addr:postcode":"46182",
    "addr:street":"C / 126",
    "iso:country":"ES",
    "sg:address":"C/ 126, 3",
    "sg:city":"Ca\u00d1ada",
    "sg:orig_category":"Negocio De Metales No Ferrosos",
    "sg:phone":"+34 961 32 12 31",
    "sg:postcode":"46182",
    "sg:province":"Valencia",
    "wof:name":"Berbegal Rico Jose",
    "wof:placetype":"venue"
},
  "geometry": {"coordinates":[-0.4852339923,39.5221443176],"type":"Point"}
}