{
  "type": "Feature",
  "properties": {
    "addr:full":"Calle de General Palanca, 34 Madrid Madrid 28045",
    "addr:housenumber":"34",
    "addr:postcode":"madrid;28045",
    "addr:street":"Calle De General Palanca",
    "iso:country":"ES",
    "sg:address":"Calle de General Palanca, 34",
    "sg:city":"Madrid",
    "sg:orig_category":"Estudios, Instalaci\u00d3n De Climatizaci\u00d3n",
    "sg:phone":"+34 914 67 41 66",
    "sg:postcode":"28045",
    "sg:province":"Madrid",
    "wof:name":"Limpiezas Crespo S. A.",
    "wof:placetype":"venue"
},
  "geometry": {"coordinates":[-3.6959710121,40.3991317749],"type":"Point"}
}