{
  "type": "Feature",
  "properties": {
    "iso:country":"ES",
    "sg:address":"Calle de Jenaro Oraa, 36",
    "sg:city":"Santurtzi",
    "sg:orig_category":"Panader\u00cdas, Panader\u00cdas",
    "sg:phone":"+34 944 61 51 95",
    "sg:postcode":"48980",
    "sg:province":"Vizcaya",
    "wof:name":"Hijos De Cosme Elguezabal S. A.",
    "wof:placetype":"venue"
},
  "geometry": {"coordinates":[-3.0292010307,43.3265953064],"type":"Point"}
}