{
  "type": "Feature",
  "properties": {
    "iso:country":"ES",
    "sg:address":"Sastres, 3",
    "sg:city":"Ciutadella Menorca",
    "sg:orig_category":"Confecci\u00d3n De Zapatos",
    "sg:phone":"+34 971 38 25 28",
    "sg:postcode":"07760",
    "sg:province":"Islas Baleares",
    "sg:website":"www.patricia.es",
    "wof:name":"Mesquida Y Garcia S. A.",
    "wof:placetype":"venue"
},
  "geometry": {"coordinates":[3.8595910072,40.0074157715],"type":"Point"}
}