{
  "type": "Feature",
  "properties": {
    "iso:country":"ES",
    "sg:address":"Plaza Educador Hermano Benjamin, 1",
    "sg:city":"Erandio",
    "sg:orig_category":"M\u00c9dicos: Estomatolog\u00cda",
    "sg:phone":"+34 944 67 12 08",
    "sg:postcode":"48950",
    "sg:province":"Vizcaya",
    "wof:name":"Raquel Berasategui - Clinica Dental",
    "wof:placetype":"venue"
},
  "geometry": {"coordinates":[-2.971378088,43.3043441772],"type":"Point"}
}