{
  "type": "Feature",
  "properties": {
    "iso:country":"ES",
    "sg:address":"El Fonduxu, S/n",
    "sg:city":"Arroes",
    "sg:orig_category":"Farmacias (repartici\u00d3n Y Al Por Mayor)",
    "sg:phone":"+34 985 89 90 32",
    "sg:postcode":"33314",
    "sg:province":"Asturias",
    "wof:name":"Asle Distribuciones Medicas S.l",
    "wof:placetype":"venue"
},
  "geometry": {"coordinates":[-5.5315785408,43.5102996826],"type":"Point"}
}