{
  "type": "Feature",
  "properties": {
    "addr:full":"Avda Zaragoza, 6 Calatayud Zaragoza 50300",
    "addr:housenumber":"6",
    "addr:postcode":"50300",
    "addr:street":"Avda Zaragoza",
    "iso:country":"ES",
    "sg:address":"Avda Zaragoza, 6",
    "sg:city":"Calatayud",
    "sg:orig_category":"Cristaler\u00cdas",
    "sg:phone":"+34 976 88 19 84",
    "sg:postcode":"50300",
    "sg:province":"Zaragoza",
    "wof:name":"Gracia Garcia Jesus",
    "wof:placetype":"venue"
},
  "geometry": {"coordinates":[-1.6366189718,41.3521003723],"type":"Point"}
}