{
  "type": "Feature",
  "properties": {
    "addr:full":"Alam Revilla Gregorio De La, 22 Bilbao Vizcaya 48011",
    "addr:postcode":"48011",
    "addr:street":"Alam Revilla",
    "iso:country":"ES",
    "sg:address":"Alam Revilla Gregorio De La, 22",
    "sg:city":"Bilbao",
    "sg:orig_category":"Deportes Diversos",
    "sg:phone":"+34 944 42 50 28",
    "sg:postcode":"48011",
    "sg:province":"Vizcaya",
    "wof:name":"Gracia Zu\u00f1iga Josefina",
    "wof:placetype":"venue"
},
  "geometry": {"coordinates":[-2.9404459,43.2612533569],"type":"Point"}
}