{
  "type": "Feature",
  "properties": {
    "iso:country":"ES",
    "sg:address":"Calle de Juan Xxiii (de), 6",
    "sg:city":"Totana",
    "sg:orig_category":"Complementos De Vestir (al Por Menor)",
    "sg:phone":"+34 968 42 36 27",
    "sg:postcode":"30850",
    "sg:province":"Murcia",
    "wof:name":"Status-94 S.l.",
    "wof:placetype":"venue"
},
  "geometry": {"coordinates":[-1.4994926453,37.771270752],"type":"Point"}
}