{
  "type": "Feature",
  "properties": {
    "iso:country":"ES",
    "sg:address":"Cmno Barreros (los), S/n",
    "sg:city":"Sanlucar Mayor",
    "sg:orig_category":"Empresas De Carpinter\u00cda Met\u00c1lica",
    "sg:phone":"+34 955 70 34 78",
    "sg:postcode":"41800",
    "sg:province":"Sevilla",
    "wof:name":"Guirado Moreno Eustaquio",
    "wof:placetype":"venue"
},
  "geometry": {"coordinates":[-6.1956338882,37.3855361938],"type":"Point"}
}