{
  "type": "Feature",
  "properties": {
    "iso:country":"ES",
    "sg:address":"Carr De Ferreres Breto, 21",
    "sg:city":"Benicarlo",
    "sg:orig_category":"Doctores En Medicina",
    "sg:phone":"+34 964 46 72 59",
    "sg:postcode":"12580",
    "sg:province":"Castell\u00f3n",
    "wof:name":"Sanmartin Urchaga Pedro",
    "wof:placetype":"venue"
},
  "geometry": {"coordinates":[0.4042100012,40.4457893372],"type":"Point"}
}