{
  "type": "Feature",
  "properties": {
    "addr:full":"Calle de Marchales, 14 Almeria Almer\u00eda 04008",
    "addr:housenumber":"14",
    "addr:postcode":"04008",
    "addr:street":"Calle De Marchales",
    "iso:country":"ES",
    "sg:address":"Calle de Marchales, 14",
    "sg:city":"Almeria",
    "sg:classifiers":[
        {
            "category":"Taxi",
            "type":"Transportation"
        }
    ],
    "sg:phone":"+34 950 26 76 52",
    "sg:postcode":"04008",
    "sg:province":"Almer\u00eda",
    "wof:name":"Collado Torres Jose",
    "wof:placetype":"venue"
},
  "geometry": {"coordinates":[-2.4574129581,36.848526001],"type":"Point"}
}