{
  "type": "Feature",
  "properties": {
    "iso:country":"ES",
    "sg:address":"Calle de Maria Zambrano, 35",
    "sg:city":"Zaragoza",
    "sg:orig_category":"Ropa Para Ni\u00d1os (al Por Menor)",
    "sg:phone":"+34 976 51 71 81",
    "sg:postcode":"50018",
    "sg:province":"Zaragoza",
    "sg:website":"www.orchestra.es",
    "wof:name":"Opi Prendas Infantiles Orchestra S.l.",
    "wof:placetype":"venue"
},
  "geometry": {"coordinates":[-0.8894900084,41.6705093384],"type":"Point"}
}