{
  "type": "Feature",
  "properties": {
    "iso:country":"ES",
    "sg:address":"Calle de Badaia, 23",
    "sg:city":"Vitoria-gasteiz",
    "sg:orig_category":"Imprenta",
    "sg:phone":"+34 945 20 09 26",
    "sg:postcode":"01012",
    "sg:province":"\u00c1lava",
    "wof:name":"Graficas Badaya S.c.",
    "wof:placetype":"venue"
},
  "geometry": {"coordinates":[-2.6776559353,42.8507957458],"type":"Point"}
}