{
  "type": "Feature",
  "properties": {
    "addr:full":"Calle de Mayor, 28 Pozoblanco C\u00f3rdoba 14400",
    "addr:housenumber":"28",
    "addr:postcode":"14400",
    "addr:street":"Calle De Mayor",
    "iso:country":"ES",
    "sg:address":"Calle de Mayor, 28",
    "sg:city":"Pozoblanco",
    "sg:orig_category":"Electrodom\u00c9sticos (al Por Menor)",
    "sg:phone":"+34 957 77 07 61",
    "sg:postcode":"14400",
    "sg:province":"C\u00f3rdoba",
    "wof:name":"Marquez Lillo Pedro",
    "wof:placetype":"venue"
},
  "geometry": {"coordinates":[-4.8489351273,38.3790969849],"type":"Point"}
}