{
  "type": "Feature",
  "properties": {
    "addr:full":"Carrer de Enten\u00c7a, 324 Barcelona Barcelona 08029",
    "addr:housenumber":"324",
    "addr:postcode":"08029",
    "addr:street":"Carrer De Entenc\u0327A",
    "iso:country":"ES",
    "sg:address":"Carrer de Enten\u00c7a, 324",
    "sg:city":"Barcelona",
    "sg:orig_category":"Ense\u00d1ante, Direcci\u00d3n",
    "sg:phone":"+34 934 30 51 55",
    "sg:postcode":"08029",
    "sg:province":"Barcelona",
    "wof:name":"Solans Soteras Miguel",
    "wof:placetype":"venue"
},
  "geometry": {"coordinates":[2.1381430626,41.3900146484],"type":"Point"}
}