{
  "type": "Feature",
  "properties": {
    "addr:full":"Calle de Marques De San Esteban, 56 Gijon Asturias 33206",
    "addr:housenumber":"56",
    "addr:postcode":"33206",
    "addr:street":"Calle De Marques De San Esteban",
    "iso:country":"ES",
    "sg:address":"Calle de Marques De San Esteban, 56",
    "sg:city":"Gijon",
    "sg:orig_category":"Industria Qu\u00cdmica",
    "sg:phone":"+34 985 34 92 77",
    "sg:postcode":"33206",
    "sg:province":"Asturias",
    "wof:name":"Trivi\u00f1o Vazquez Fernando",
    "wof:placetype":"venue"
},
  "geometry": {"coordinates":[-5.6701521873,43.5413856506],"type":"Point"}
}