{
  "type": "Feature",
  "properties": {
    "addr:full":"Calle de Hamarretxeta, 26 Pasai Antxo Guip\u00f9zcoa 20110",
    "addr:housenumber":"26",
    "addr:postcode":"20110",
    "addr:street":"Calle De Hamarretxeta;Guipu\u0300Zcoa",
    "iso:country":"ES",
    "sg:address":"Calle de Hamarretxeta, 26",
    "sg:city":"Pasai Antxo",
    "sg:orig_category":"Plomeros",
    "sg:phone":"+34 943 34 01 08",
    "sg:postcode":"20110",
    "sg:province":"Guip\u00f9zcoa",
    "wof:name":"Olaciregui Odriozola Jose Martin",
    "wof:placetype":"venue"
},
  "geometry": {"coordinates":[-1.9183189869,43.3161430359],"type":"Point"}
}