{
  "type": "Feature",
  "properties": {
    "iso:country":"ES",
    "sg:address":"Rbla Prat, 7",
    "sg:city":"Barcelona",
    "sg:orig_category":"Panader\u00cdas, Panader\u00cdas",
    "sg:phone":"+34 934 15 03 07",
    "sg:postcode":"08012",
    "sg:province":"Barcelona",
    "wof:name":"Anton Varas Antonio",
    "wof:placetype":"venue"
},
  "geometry": {"coordinates":[2.1524333954,41.4017105103],"type":"Point"}
}