{
  "type": "Feature",
  "properties": {
    "iso:country":"ES",
    "sg:address":"Calle de Sevilla, S/n",
    "sg:city":"Jaen",
    "sg:orig_category":"Carnicer\u00cdas, Carnicer\u00cdas",
    "sg:phone":"+34 953 27 58 14",
    "sg:postcode":"23006",
    "sg:province":"Ja\u00e9n",
    "wof:name":"De La Torre Serrano Juan Carlos",
    "wof:placetype":"venue"
},
  "geometry": {"coordinates":[-3.7999539375,37.7785987854],"type":"Point"}
}