{
  "type": "Feature",
  "properties": {
    "addr:full":"Ctra. Almeria, 18 Malaga M\u00e1laga 29018",
    "addr:housenumber":"18",
    "addr:postcode":"29018",
    "addr:street":"Ctra. Almeria;Ma\u0301Laga",
    "iso:country":"ES",
    "sg:address":"Ctra. Almeria, 18",
    "sg:city":"Malaga",
    "sg:orig_category":"Comercio De Piezas De Recambio Y De Accesorios De Veh\u00cdculos, Veh\u00cdculos Industriales",
    "sg:phone":"+34 952 20 25 88",
    "sg:postcode":"29018",
    "sg:province":"M\u00e1laga",
    "wof:name":"Gil Marquez Gerardo",
    "wof:placetype":"venue"
},
  "geometry": {"coordinates":[-4.3507418633,36.7191543579],"type":"Point"}
}