{
  "type": "Feature",
  "properties": {
    "addr:full":"Calle de Hernando De Zafra, 7 Zafra Badajoz 06300",
    "addr:housenumber":"7",
    "addr:postcode":"06300",
    "addr:street":"Calle De Hernando De Zafra",
    "iso:country":"ES",
    "sg:address":"Calle de Hernando De Zafra, 7",
    "sg:city":"Zafra",
    "sg:orig_category":"Cl\u00cdnicas M\u00c9dicas",
    "sg:phone":"+34 924 55 29 51",
    "sg:postcode":"06300",
    "sg:province":"Badajoz",
    "wof:name":"Cerse S. A.",
    "wof:placetype":"venue"
},
  "geometry": {"coordinates":[-6.4157328606,38.4264793396],"type":"Point"}
}