{
  "type": "Feature",
  "properties": {
    "iso:country":"ES",
    "sg:address":"Calle de Cap Martinet, Des, S/n",
    "sg:city":"Nuestra Se\u00e7ora De Jesus",
    "sg:orig_category":"Cer\u00c1mica Art\u00cdstica Y Decorativa",
    "sg:phone":"+34 971 31 84 91",
    "sg:postcode":"07819",
    "sg:province":"Islas Baleares",
    "wof:name":"Moreno Garrido Alejandro",
    "wof:placetype":"venue"
},
  "geometry": {"coordinates":[2.8577105999,39.5341796875],"type":"Point"}
}