{
  "type": "Feature",
  "properties": {
    "iso:country":"ES",
    "sg:address":"Calle de Bermejeros, 18",
    "sg:city":"Salamanca",
    "sg:orig_category":"Abogados",
    "sg:phone":"+34 923 26 47 93",
    "sg:postcode":"37001",
    "sg:province":"Salamanca",
    "wof:name":"Aguilar Garcia Maria Del Carmen",
    "wof:placetype":"venue"
},
  "geometry": {"coordinates":[-5.6610999107,40.9658126831],"type":"Point"}
}