{
  "type": "Feature",
  "properties": {
    "iso:country":"ES",
    "sg:address":"Calle de Latina, 1",
    "sg:city":"Malaga",
    "sg:orig_category":"Plomeros",
    "sg:phone":"+34 952 32 99 12",
    "sg:postcode":"29006",
    "sg:province":"M\u00e1laga",
    "wof:name":"Padilla Barrueso Luis",
    "wof:placetype":"venue"
},
  "geometry": {"coordinates":[-4.4776549339,36.7108230591],"type":"Point"}
}