{
  "type": "Feature",
  "properties": {
    "iso:country":"ES",
    "sg:address":"Carrer de Valencia, 459",
    "sg:city":"Barcelona",
    "sg:orig_category":"Perfumer\u00cda (al Por Menor)",
    "sg:phone":"+34 932 65 33 85",
    "sg:postcode":"08013",
    "sg:province":"Barcelona",
    "wof:name":"Hermanos Martin Carbo S.l.",
    "wof:placetype":"venue"
},
  "geometry": {"coordinates":[2.1773951054,41.4034576416],"type":"Point"}
}