{
  "type": "Feature",
  "properties": {
    "addr:full":"Calle de Ba\u00d1os, 54 Sevilla Sevilla 41002",
    "addr:housenumber":"54",
    "addr:postcode":"41002",
    "addr:street":"Calle De Ban\u0303Os",
    "iso:country":"ES",
    "sg:address":"Calle de Ba\u00d1os, 54",
    "sg:city":"Sevilla",
    "sg:orig_category":"Organismos De Reclutamiento",
    "sg:phone":"+34 954 91 52 55",
    "sg:postcode":"41002",
    "sg:province":"Sevilla",
    "wof:name":"Rosado Dominguez Fernando",
    "wof:placetype":"venue"
},
  "geometry": {"coordinates":[-6.0006594658,37.3955497742],"type":"Point"}
}