{
  "type": "Feature",
  "properties": {
    "iso:country":"ES",
    "sg:address":"Calle de Angel Guerra, 4",
    "sg:city":"Palmas De Gran Canaria",
    "sg:orig_category":"M\u00c9dicos: Medicina General",
    "sg:phone":"+34 928 36 21 42",
    "sg:postcode":"35003",
    "sg:province":"Las Palmas",
    "wof:name":"Leon Fernandez Armando",
    "wof:placetype":"venue"
},
  "geometry": {"coordinates":[-15.4212589264,28.1086673737],"type":"Point"}
}