{
  "type": "Feature",
  "properties": {
    "addr:full":"Rond Sant Antoni, 29 Barcelona Barcelona 08011",
    "addr:housenumber":"29",
    "addr:postcode":"08011",
    "addr:street":"Sant Antoni",
    "iso:country":"ES",
    "sg:address":"Rond Sant Antoni, 29",
    "sg:city":"Barcelona",
    "sg:orig_category":"Deportes Y Ocio: Art\u00cdculos Y Ropas (al Por Menor Y Accesorios)",
    "sg:phone":"+34 934 23 94 09",
    "sg:postcode":"08011",
    "sg:province":"Barcelona",
    "wof:name":"Ramells Cros Ricardo",
    "wof:placetype":"venue"
},
  "geometry": {"coordinates":[2.163394928,41.3814468384],"type":"Point"}
}