{
  "type": "Feature",
  "properties": {
    "addr:full":"Plaz Paseito Ramiro, S/n Alacant Alicante 03002",
    "addr:housenumber":"/ n",
    "addr:postcode":"03002",
    "addr:street":"Plaz;Ramiro S",
    "iso:country":"ES",
    "sg:address":"Plaz Paseito Ramiro, S/n",
    "sg:city":"Alacant",
    "sg:orig_category":"Promotores Constructores",
    "sg:phone":"+34 965 20 16 77",
    "sg:postcode":"03002",
    "sg:province":"Alicante",
    "wof:name":"Dragados S A",
    "wof:placetype":"venue"
},
  "geometry": {"coordinates":[-0.4789139926,38.3459892273],"type":"Point"}
}