{
  "type": "Feature",
  "properties": {
    "iso:country":"ES",
    "sg:address":"Carrer de Fra Romeu Burguera, 24",
    "sg:city":"Santanyi",
    "sg:orig_category":"Controles De Edificaci\u00d3n (construcci\u00d3n, Seguridad)",
    "sg:phone":"+34 971 65 38 04",
    "sg:postcode":"07650",
    "sg:province":"Islas Baleares",
    "wof:name":"Perello Vidal Lorenzo",
    "wof:placetype":"venue"
},
  "geometry": {"coordinates":[3.1277780533,39.3518066406],"type":"Point"}
}