{
  "type": "Feature",
  "properties": {
    "addr:full":"Conqueridor, 50 Banyeres Mariola Alicante 03450",
    "addr:housenumber":"50",
    "addr:postcode":"03450",
    "addr:street":"Conqueridor",
    "iso:country":"ES",
    "sg:address":"Conqueridor, 50",
    "sg:city":"Banyeres Mariola",
    "sg:orig_category":"Quincaller\u00cda (al Por Menor)",
    "sg:phone":"+34 966 56 72 60",
    "sg:postcode":"03450",
    "sg:province":"Alicante",
    "wof:name":"Puerto Molla Vicenta",
    "wof:placetype":"venue"
},
  "geometry": {"coordinates":[-0.660359025,38.7114982605],"type":"Point"}
}