{
  "type": "Feature",
  "properties": {
    "iso:country":"ES",
    "sg:address":"Calle de Doctor Mas, 22",
    "sg:city":"Moratalla",
    "sg:orig_category":"Reposter\u00cdas",
    "sg:phone":"+34 968 70 68 03",
    "sg:postcode":"30440",
    "sg:province":"Murcia",
    "wof:name":"Navarro Martinez Manuel Jesus",
    "wof:placetype":"venue"
},
  "geometry": {"coordinates":[-1.893291235,38.189201355],"type":"Point"}
}