{
  "type": "Feature",
  "properties": {
    "iso:country":"ES",
    "sg:address":"Carrer de Xipreret, 81",
    "sg:city":"Hospitalet Llobregat",
    "sg:orig_category":"Danza, Cursos, Asociaciones Y M\u00dasicos",
    "sg:phone":"+34 932 61 27 89",
    "sg:postcode":"08901",
    "sg:province":"Barcelona",
    "wof:name":"Mestres Huguet Laura",
    "wof:placetype":"venue"
},
  "geometry": {"coordinates":[2.0972390175,41.3608207703],"type":"Point"}
}