{
  "type": "Feature",
  "properties": {
    "iso:country":"ES",
    "sg:address":"Calle de General Casta\u00d1os, 109",
    "sg:city":"Portugalete",
    "sg:orig_category":"Librer\u00cdas",
    "sg:phone":"+34 944 83 18 98",
    "sg:postcode":"48920",
    "sg:province":"Vizcaya",
    "wof:name":"Angulo Azpiolea Maria Victoria",
    "wof:placetype":"venue"
},
  "geometry": {"coordinates":[-3.0299899578,43.3245544434],"type":"Point"}
}