{
  "type": "Feature",
  "properties": {
    "addr:full":"Carr Ferran Rambla, 32 Lleida Lleida 25007",
    "addr:housenumber":"32",
    "addr:postcode":"25007",
    "addr:street":"Carr Ferran Rambla",
    "iso:country":"ES",
    "sg:address":"Carr Ferran Rambla, 32",
    "sg:city":"Lleida",
    "sg:orig_category":"Empleados",
    "sg:phone":"+34 973 24 59 00",
    "sg:postcode":"25007",
    "sg:province":"Lleida",
    "wof:name":"Mont Consultores S.l.",
    "wof:placetype":"venue"
},
  "geometry": {"coordinates":[0.627129972,41.6145210266],"type":"Point"}
}