{
  "type": "Feature",
  "properties": {
    "iso:country":"ES",
    "sg:address":"Empalme, 11",
    "sg:city":"Empalme",
    "sg:orig_category":"Estancos",
    "sg:phone":"+34 981 71 11 63",
    "sg:postcode":"15111",
    "sg:province":"La Coru\u00f1a",
    "wof:name":"Cean Lopez Maria Del Carmen",
    "wof:placetype":"venue"
},
  "geometry": {"coordinates":[-8.7833986282,43.2669487],"type":"Point"}
}