{
  "type": "Feature",
  "properties": {
    "addr:full":"Calle de Marcos De Obregon, 13 Malaga M\u00e1laga 29016",
    "addr:postcode":"29016",
    "addr:street":"Calle De Marcos De Obregon 13 Malaga Ma\u0301Laga",
    "iso:country":"ES",
    "sg:address":"Calle de Marcos De Obregon, 13",
    "sg:city":"Malaga",
    "sg:orig_category":"Contenedores (mercanc\u00cdas)",
    "sg:phone":"+34 952 12 13 41",
    "sg:postcode":"29016",
    "sg:province":"M\u00e1laga",
    "wof:name":"Leybor S.l.",
    "wof:placetype":"venue"
},
  "geometry": {"coordinates":[-4.3918809891,36.7241096497],"type":"Point"}
}