{
  "type": "Feature",
  "properties": {
    "iso:country":"ES",
    "sg:address":"Calle de Alcala, 11",
    "sg:city":"Ajalvir",
    "sg:orig_category":"Guarder\u00cdas",
    "sg:phone":"+34 918 84 41 98",
    "sg:postcode":"28864",
    "sg:province":"Madrid",
    "wof:name":"Actividades Infantiles Mi Casita Jardin S.l.",
    "wof:placetype":"venue"
},
  "geometry": {"coordinates":[-3.4775998592,40.5329704285],"type":"Point"}
}