{
  "type": "Feature",
  "properties": {
    "addr:full":"Calle de Montreal (de), 18 Humanes De Madrid Madrid 28970",
    "addr:housenumber":"18",
    "addr:postcode":"28970",
    "addr:street":"Calle De Montreal De",
    "iso:country":"ES",
    "sg:address":"Calle de Montreal (de), 18",
    "sg:city":"Humanes De Madrid",
    "sg:orig_category":"Cerrajer\u00cda, Ferrallista",
    "sg:phone":"+34 916 04 16 65",
    "sg:postcode":"28970",
    "sg:province":"Madrid",
    "wof:name":"Metalicos Trameg S.l.",
    "wof:placetype":"venue"
},
  "geometry": {"coordinates":[-3.8111884594,40.2693519592],"type":"Point"}
}