{
  "type": "Feature",
  "properties": {
    "iso:country":"ES",
    "sg:address":"Calle de Marineras, 33",
    "sg:city":"Ajalvir",
    "sg:classifiers":[
        {
            "category":"Manufacturing",
            "subcategory":"Metals",
            "type":"Manufacturing & Wholesale Goods"
        }
    ],
    "sg:phone":"+34 918 84 37 40",
    "sg:postcode":"28864",
    "sg:province":"Madrid",
    "sg:tags":[
        "en",
        "fundiciones"
    ],
    "wof:name":"Fundiarc S.l.l.",
    "wof:placetype":"venue"
},
  "geometry": {"coordinates":[-3.4778790474,40.5161247253],"type":"Point"}
}