{
  "type": "Feature",
  "properties": {
    "addr:full":"Plaz Zarzuela (de La), 5 Abaran Murcia 30550",
    "addr:housenumber":"5",
    "addr:postcode":"30550",
    "iso:country":"ES",
    "sg:address":"Plaz Zarzuela (de La), 5",
    "sg:city":"Abaran",
    "sg:orig_category":"Ropa Para Se\u00d1oras Y Caballeros (al Por Menor)",
    "sg:phone":"+34 968 77 05 43",
    "sg:postcode":"30550",
    "sg:province":"Murcia",
    "wof:name":"Tornero Ramos Jaime",
    "wof:placetype":"venue"
},
  "geometry": {"coordinates":[-1.3965599537,38.2063827515],"type":"Point"}
}