{
  "type": "Feature",
  "properties": {
    "addr:full":"Carrer de Llorens I Barba, 37 Barcelona Barcelona 08025",
    "addr:housenumber":"37",
    "addr:postcode":"08025",
    "addr:street":"Carrer De Llorens I Barba",
    "iso:country":"ES",
    "sg:address":"Carrer de Llorens I Barba, 37",
    "sg:city":"Barcelona",
    "sg:orig_category":"Comercio Y Bancos",
    "sg:phone":"+34 934 36 83 19",
    "sg:postcode":"08025",
    "sg:province":"Barcelona",
    "sg:website":"www.intentvitrines.es",
    "wof:name":"Intent De Disseny S.a.",
    "wof:placetype":"venue"
},
  "geometry": {"coordinates":[2.1700921059,41.4119720459],"type":"Point"}
}