{
  "type": "Feature",
  "properties": {
    "addr:full":"Calle de Via Carpetana, 83 Madrid Madrid 28047",
    "addr:housenumber":"83",
    "addr:postcode":"madrid;28047",
    "addr:street":"Calle De Via Carpetana",
    "iso:country":"ES",
    "sg:address":"Calle de Via Carpetana, 83",
    "sg:city":"Madrid",
    "sg:orig_category":"\u00d3ptica: Instrumentos (fabricaci\u00d3n)",
    "sg:phone":"+34 914 66 27 41",
    "sg:postcode":"28047",
    "sg:province":"Madrid",
    "sg:website":"www.sanganinoopticas.com",
    "wof:name":"Opticas San Gabino 2025 S.l.",
    "wof:placetype":"venue"
},
  "geometry": {"coordinates":[-3.7353520393,40.3979148865],"type":"Point"}
}