{
  "type": "Feature",
  "properties": {
    "addr:full":"Calle de Escultor Daniel, 3 Logro\u00f1o La Rioja 26006",
    "addr:housenumber":"3",
    "addr:postcode":"26006",
    "addr:street":"Calle De Escultor Daniel;Rioja",
    "iso:country":"ES",
    "sg:address":"Calle de Escultor Daniel, 3",
    "sg:city":"Logro\u00f1o",
    "sg:orig_category":"Fisioterapia",
    "sg:phone":"+34 941 22 67 69",
    "sg:postcode":"26006",
    "sg:province":"La Rioja",
    "wof:name":"Perez-espa\u00f1a Matarranz Manuel",
    "wof:placetype":"venue"
},
  "geometry": {"coordinates":[-2.3912363052,42.4574165344],"type":"Point"}
}