{
  "type": "Feature",
  "properties": {
    "addr:full":"Calle de Union, 29 Malaga M\u00e1laga 29006",
    "addr:housenumber":"29",
    "addr:postcode":"29006",
    "addr:street":"Calle De;Malaga Ma\u0301Laga",
    "iso:country":"ES",
    "sg:address":"Calle de Union, 29",
    "sg:city":"Malaga",
    "sg:orig_category":"Fabricaci\u00d3n De Camas",
    "sg:phone":"+34 952 31 46 44",
    "sg:postcode":"29006",
    "sg:province":"M\u00e1laga",
    "wof:name":"Mesefor S. A.",
    "wof:placetype":"venue"
},
  "geometry": {"coordinates":[-4.4372029305,36.7114105225],"type":"Point"}
}