{
  "type": "Feature",
  "properties": {
    "addr:full":"Cra Laurea Miro, 222 Sant Feliu Llobregat Barcelona 08980",
    "addr:housenumber":"222",
    "addr:postcode":"08980",
    "iso:country":"ES",
    "sg:address":"Cra Laurea Miro, 222",
    "sg:city":"Sant Feliu Llobregat",
    "sg:orig_category":"Ropa Para Se\u00d1oras (al Por Menor)",
    "sg:phone":"+34 936 66 53 01",
    "sg:postcode":"08980",
    "sg:province":"Barcelona",
    "wof:name":"Alamo Cuadri Antonio",
    "wof:placetype":"venue"
},
  "geometry": {"coordinates":[2.0398833752,41.3869171143],"type":"Point"}
}