{
  "type": "Feature",
  "properties": {
    "addr:full":"Avda Salobre\u00d1a, 30 Motril Granada 18600",
    "addr:housenumber":"30",
    "addr:postcode":"18600",
    "addr:street":"Avda Salobren\u0303A",
    "iso:country":"ES",
    "sg:address":"Avda Salobre\u00d1a, 30",
    "sg:city":"Motril",
    "sg:orig_category":"Alquiler De V\u00cddeo",
    "sg:phone":"+34 958 82 57 67",
    "sg:postcode":"18600",
    "sg:province":"Granada",
    "wof:name":"Moreno Rodriguez Alicia",
    "wof:placetype":"venue"
},
  "geometry": {"coordinates":[-3.5188140869,36.7434043884],"type":"Point"}
}