{
  "type": "Feature",
  "properties": {
    "iso:country":"ES",
    "sg:address":"El Castillo, 13",
    "sg:city":"Cervera Pisuerga",
    "sg:orig_category":"Estaciones De Servicio",
    "sg:phone":"+34 979 87 02 21",
    "sg:postcode":"34840",
    "sg:province":"Palencia",
    "wof:name":"Jl Sardina S.l.",
    "wof:placetype":"venue"
},
  "geometry": {"coordinates":[-4.4991950989,42.8648071289],"type":"Point"}
}