{
  "type": "Feature",
  "properties": {
    "addr:full":"Carrer de Ramon Y Cajal, 10 Palma Islas Baleares 07011",
    "addr:housenumber":"10",
    "addr:postcode":"07011",
    "addr:street":"Carrer De Ramon Y Cajal",
    "iso:country":"ES",
    "sg:address":"Carrer de Ramon Y Cajal, 10",
    "sg:city":"Palma",
    "sg:orig_category":"Venta, Alquiler De Instrumentos Y Accesorios De M\u00dasica",
    "sg:phone":"+34 971 28 48 85",
    "sg:postcode":"07011",
    "sg:province":"Islas Baleares",
    "sg:website":"www.musicasa.com",
    "wof:name":"Salom Y Pomar S.l.",
    "wof:placetype":"venue"
},
  "geometry": {"coordinates":[2.6423919201,39.575843811],"type":"Point"}
}