{
  "type": "Feature",
  "properties": {
    "addr:full":"La Utrera, 3 Veguellina De Fondo Le\u00f3n 24359",
    "addr:housenumber":"3",
    "addr:postcode":"24359",
    "addr:street":"Veguellina De Fondo Leo\u0301N",
    "iso:country":"ES",
    "sg:address":"La Utrera, 3",
    "sg:city":"Veguellina De Fondo",
    "sg:orig_category":"Empresas De Carpinter\u00cda Met\u00c1lica",
    "sg:phone":"+34 987 66 22 67",
    "sg:postcode":"24359",
    "sg:province":"Le\u00f3n",
    "wof:name":"Moran Castro Manuel",
    "wof:placetype":"venue"
},
  "geometry": {"coordinates":[-5.8740510941,42.3709030151],"type":"Point"}
}