{
  "type": "Feature",
  "properties": {
    "addr:full":"Calle de Rodriguez Arias, 43 Bilbao Vizcaya 48011",
    "addr:housenumber":"43",
    "addr:postcode":"48011",
    "addr:street":"Calle De Rodriguez Arias",
    "iso:country":"ES",
    "sg:address":"Calle de Rodriguez Arias, 43",
    "sg:city":"Bilbao",
    "sg:orig_category":"Farmacias",
    "sg:phone":"+34 944 41 10 26",
    "sg:postcode":"48011",
    "sg:province":"Vizcaya",
    "wof:name":"Perez Garcia Olga Isabel",
    "wof:placetype":"venue"
},
  "geometry": {"coordinates":[-2.9402890205,43.2628555298],"type":"Point"}
}