{
  "type": "Feature",
  "properties": {
    "addr:full":"Pg Verdum, 8 Barcelona Barcelona 08016",
    "addr:housenumber":"8",
    "addr:postcode":"08016",
    "addr:street":"Pg Verdum",
    "iso:country":"ES",
    "sg:address":"Pg Verdum, 8",
    "sg:city":"Barcelona",
    "sg:orig_category":"Inform\u00c1tica, Ofim\u00c1tica (estudios, Asesor\u00cda, Ingenier\u00cda, Formaci\u00d3n)",
    "sg:phone":"+34 932 76 15 25",
    "sg:postcode":"08016",
    "sg:province":"Barcelona",
    "wof:name":"Infortecnic S.c.p.",
    "wof:placetype":"venue"
},
  "geometry": {"coordinates":[2.1728041172,41.4360046387],"type":"Point"}
}