{
  "type": "Feature",
  "properties": {
    "iso:country":"ES",
    "sg:address":"Carrer de Higini Angles, 8",
    "sg:city":"Tarragona",
    "sg:orig_category":"Psic\u00d3logos",
    "sg:phone":"+34 977 21 58 63",
    "sg:postcode":"43001",
    "sg:province":"Tarragona",
    "wof:name":"Oliveras Aixut Pilar",
    "wof:placetype":"venue"
},
  "geometry": {"coordinates":[1.2452059984,41.1174545288],"type":"Point"}
}