{
  "type": "Feature",
  "properties": {
    "addr:full":"Calle de Rivera, 11 Ogijares Granada 18151",
    "addr:housenumber":"11",
    "addr:postcode":"18151",
    "addr:street":"Calle De Rivera",
    "iso:country":"ES",
    "sg:address":"Calle de Rivera, 11",
    "sg:city":"Ogijares",
    "sg:orig_category":"Psic\u00d3logos",
    "sg:phone":"+34 958 50 75 78",
    "sg:postcode":"18151",
    "sg:province":"Granada",
    "wof:name":"Perez Torres Antonio",
    "wof:placetype":"venue"
},
  "geometry": {"coordinates":[-3.6077663898,37.1147003174],"type":"Point"}
}