{
  "type": "Feature",
  "properties": {
    "addr:full":"Calle de Poniente, S/n Cubillas De Santa Marta Valladolid 47290",
    "addr:housenumber":"s / n",
    "addr:postcode":"47290",
    "addr:street":"Calle De Poniente",
    "iso:country":"ES",
    "sg:address":"Calle de Poniente, S/n",
    "sg:city":"Cubillas De Santa Marta",
    "sg:orig_category":"Alcoholes Y Aguardientes (fabricaci\u00d3n, Al Por Mayor)",
    "sg:phone":"+34 983 58 50 06",
    "sg:postcode":"47290",
    "sg:province":"Valladolid",
    "wof:name":"Alfredo Santamaria Arias, S.l.",
    "wof:placetype":"venue"
},
  "geometry": {"coordinates":[-4.6161341667,41.8336334229],"type":"Point"}
}