{
  "type": "Feature",
  "properties": {
    "iso:country":"ES",
    "sg:address":"Calle de Recogidas, 8",
    "sg:city":"Granada",
    "sg:orig_category":"Abogados",
    "sg:phone":"+34 958 53 60 45",
    "sg:postcode":"18002",
    "sg:province":"Granada",
    "wof:name":"Luna Rodrigo Alfonso",
    "wof:placetype":"venue"
},
  "geometry": {"coordinates":[-3.6008970737,37.1730270386],"type":"Point"}
}