{
  "type": "Feature",
  "properties": {
    "addr:full":"Calle de Villa De Plentzia, 32 Arenas -areeta Vizcaya 48930",
    "addr:housenumber":"32;areeta",
    "addr:postcode":"48930",
    "addr:street":"Calle De Villa De Plentzia",
    "iso:country":"ES",
    "sg:address":"Calle de Villa De Plentzia, 32",
    "sg:city":"Arenas -areeta",
    "sg:orig_category":"Edici\u00d3n De Diarios, Revistas, Boletines",
    "sg:phone":"+34 944 42 25 66",
    "sg:postcode":"48930",
    "sg:province":"Vizcaya",
    "wof:name":"Susaeta Ediciones S.a.",
    "wof:placetype":"venue"
},
  "geometry": {"coordinates":[-2.6983869076,43.2204284668],"type":"Point"}
}