{
  "type": "Feature",
  "properties": {
    "iso:country":"ES",
    "sg:address":"Calle de Lope De Vega, 6",
    "sg:city":"Santa Cruz De La Zarza",
    "sg:orig_category":"Transporte En General",
    "sg:phone":"+34 925 14 30 79",
    "sg:postcode":"45370",
    "sg:province":"Toledo",
    "wof:name":"Garcia Valle Jose Antonio",
    "wof:placetype":"venue"
},
  "geometry": {"coordinates":[-3.185477972,39.9792556763],"type":"Point"}
}