{
  "type": "Feature",
  "properties": {
    "addr:full":"Calle de Calvario, 6 S. Miguel Arroyo Valladolid 47164",
    "addr:housenumber":"6",
    "addr:postcode":"47164",
    "addr:street":"Calle De Calvario;S. Miguel Arroyo",
    "iso:country":"ES",
    "sg:address":"Calle de Calvario, 6",
    "sg:city":"S. Miguel Arroyo",
    "sg:orig_category":"Empresarios",
    "sg:phone":"+34 983 69 70 58",
    "sg:postcode":"47164",
    "sg:province":"Valladolid",
    "wof:name":"Gomez Frutos Adrian",
    "wof:placetype":"venue"
},
  "geometry": {"coordinates":[-4.4607949257,41.4448280334],"type":"Point"}
}