{
  "type": "Feature",
  "properties": {
    "addr:full":"Avda Andalucia, S/n Pinos De Alhaurin M\u00e1laga 29130",
    "addr:postcode":"29130",
    "addr:street":"Avda Andalucia S / N",
    "iso:country":"ES",
    "sg:address":"Avda Andalucia, S/n",
    "sg:city":"Pinos De Alhaurin",
    "sg:orig_category":"Cajas De Ahorro",
    "sg:phone":"+34 952 96 05 47",
    "sg:postcode":"29130",
    "sg:province":"M\u00e1laga",
    "wof:name":"Caja De Ahorros Y Monte De Piedad De Cordoba",
    "wof:placetype":"venue"
},
  "geometry": {"coordinates":[-4.5846838951,36.6520118713],"type":"Point"}
}