{
  "type": "Feature",
  "properties": {
    "iso:country":"ES",
    "sg:address":"Calle de San Vicente, 8",
    "sg:city":"Bilbao",
    "sg:orig_category":"Carb\u00d3n, Carb\u00d3n De Madera (al Por Mayor)",
    "sg:phone":"+34 944 25 26 00",
    "sg:postcode":"48...",
    "sg:province":"Vizcaya",
    "sg:website":"www.torobe.com",
    "wof:name":"Consignaciones Toro Y Betolaza S.a.",
    "wof:placetype":"venue"
},
  "geometry": {"coordinates":[-2.9277210236,43.2642745972],"type":"Point"}
}