{
  "type": "Feature",
  "properties": {
    "addr:full":"Avda Dionisio Roman Zaldo, 15 Pradoluengo Burgos 09260",
    "addr:housenumber":"15",
    "addr:postcode":"09260",
    "addr:street":"Avda Dionisio Roman Zaldo",
    "iso:country":"ES",
    "sg:address":"Avda Dionisio Roman Zaldo, 15",
    "sg:city":"Pradoluengo",
    "sg:orig_category":"Asociaciones, Organismos Culturales Y Socioeducativos",
    "sg:phone":"+34 947 58 60 74",
    "sg:postcode":"09260",
    "sg:province":"Burgos",
    "sg:website":"www.socialdea.com",
    "wof:name":"Ayuntamiento De Pradoluengo",
    "wof:placetype":"venue"
},
  "geometry": {"coordinates":[-3.1930301189,42.3150863647],"type":"Point"}
}