{
  "type": "Feature",
  "properties": {
    "iso:country":"ES",
    "sg:address":"Calle de Hermano Lorenzo, S/n",
    "sg:city":"Ag\u00fcimes",
    "sg:orig_category":"Internados & Ense\u00d1anza Privada",
    "sg:phone":"+34 928 12 49 13",
    "sg:postcode":"35260",
    "sg:province":"Las Palmas",
    "wof:name":"Instituto Piadoso Eclesiastico Jesus Sacramentado",
    "wof:placetype":"venue"
},
  "geometry": {"coordinates":[-15.4443426132,27.9040908813],"type":"Point"}
}