{
  "type": "Feature",
  "properties": {
    "iso:country":"ES",
    "sg:address":"Carr Julia Ribera, De, 14",
    "sg:city":"Carcaixent",
    "sg:orig_category":"Bancos",
    "sg:phone":"+34 962 43 10 61",
    "sg:postcode":"46740",
    "sg:province":"Valencia",
    "sg:website":"www.bancodevalencia.es",
    "wof:name":"Banco De Valencia S.a.",
    "wof:placetype":"venue"
},
  "geometry": {"coordinates":[-0.450387001,39.1219406128],"type":"Point"}
}