{
  "type": "Feature",
  "properties": {
    "addr:full":"Avda Albufera, 22 Madrid Madrid 28038",
    "addr:housenumber":"22",
    "addr:postcode":"madrid;28038",
    "addr:street":"Avda Albufera",
    "iso:country":"ES",
    "sg:address":"Avda Albufera, 22",
    "sg:city":"Madrid",
    "sg:orig_category":"Zapatos (al Por Menor)",
    "sg:phone":"+34 915 01 01 22",
    "sg:postcode":"28038",
    "sg:province":"Madrid",
    "wof:name":"Calzados Lomas S.l.",
    "wof:placetype":"venue"
},
  "geometry": {"coordinates":[-3.6676781178,40.3973846436],"type":"Point"}
}