{
  "type": "Feature",
  "properties": {
    "addr:full":"Carrer de Tous I Maroto, 5 Palma Islas Baleares 07001",
    "addr:housenumber":"5",
    "addr:postcode":"07001",
    "addr:street":"Carrer De Tous I Maroto",
    "iso:country":"ES",
    "sg:address":"Carrer de Tous I Maroto, 5",
    "sg:city":"Palma",
    "sg:orig_category":"Centros Comerciales Y Grandes Tiendas",
    "sg:phone":"+34 971 72 73 68",
    "sg:postcode":"07001",
    "sg:province":"Islas Baleares",
    "wof:name":"Buades Blanco Francisca",
    "wof:placetype":"venue"
},
  "geometry": {"coordinates":[2.6476581097,39.5699234009],"type":"Point"}
}