{
  "type": "Feature",
  "properties": {
    "addr:full":"Carr Menendez Y Pelayo, 15 Vilanova I La Geltru Barcelona 08800",
    "addr:housenumber":"15",
    "addr:postcode":"08800",
    "addr:street":"Carr Menendez Y Pelayo",
    "iso:country":"ES",
    "sg:address":"Carr Menendez Y Pelayo, 15",
    "sg:city":"Vilanova I La Geltru",
    "sg:orig_category":"Bibliotecas, Mediatecas",
    "sg:phone":"+34 938 15 91 21",
    "sg:postcode":"08800",
    "sg:province":"Barcelona",
    "wof:name":"Ajuntament De Vilanova I La Geltru",
    "wof:placetype":"venue"
},
  "geometry": {"coordinates":[1.7145974636,41.2217178345],"type":"Point"}
}