{
  "type": "Feature",
  "properties": {
    "addr:full":"Ctra Artica, 12 Ansoain Navarra 31013",
    "addr:housenumber":"12",
    "addr:postcode":"31013",
    "addr:street":"Ctra Artica",
    "iso:country":"ES",
    "sg:address":"Ctra Artica, 12",
    "sg:city":"Ansoain",
    "sg:orig_category":"Fabricaci\u00d3n De Moldes Y Modelos",
    "sg:phone":"+34 948 12 47 51",
    "sg:postcode":"31013",
    "sg:province":"Navarra",
    "wof:name":"Industrias Ladan S. L.",
    "wof:placetype":"venue"
},
  "geometry": {"coordinates":[-1.6492389441,42.8298492432],"type":"Point"}
}