{
  "type": "Feature",
  "properties": {
    "addr:full":"Calle de Sagrado Corazon De Jesus, 52 Rota C\u00e1diz 11520",
    "addr:housenumber":"52",
    "addr:postcode":"11520",
    "addr:street":"Calle De Sagrado Corazon;Jesus;Ca\u0301Diz",
    "iso:country":"ES",
    "sg:address":"Calle de Sagrado Corazon De Jesus, 52",
    "sg:city":"Rota",
    "sg:orig_category":"Farmacias",
    "sg:phone":"+34 956 81 19 50",
    "sg:postcode":"11520",
    "sg:province":"C\u00e1diz",
    "wof:name":"Rodriguez Santos Jose Javier",
    "wof:placetype":"venue"
},
  "geometry": {"coordinates":[-6.3546938896,36.6243286133],"type":"Point"}
}