{
  "type": "Feature",
  "properties": {
    "addr:full":"Rua Salamanca, 13 Vigo Pontevedra 36211",
    "addr:housenumber":"13",
    "addr:postcode":"36211",
    "addr:street":"Rua Salamanca",
    "iso:country":"ES",
    "sg:address":"Rua Salamanca, 13",
    "sg:city":"Vigo",
    "sg:orig_category":"Agencias De Viajes",
    "sg:phone":"+34 986 49 32 00",
    "sg:postcode":"36211",
    "sg:province":"Pontevedra",
    "wof:name":"Lecertour Viaxes S.l.l.",
    "wof:placetype":"venue"
},
  "geometry": {"coordinates":[-8.7269058228,42.2225608826],"type":"Point"}
}