{
  "type": "Feature",
  "properties": {
    "addr:full":"Carrer de Antoni Frontera, 22 Palma Islas Baleares 07004",
    "addr:housenumber":"22",
    "addr:postcode":"07004",
    "addr:street":"Carrer De Antoni Frontera",
    "iso:country":"ES",
    "sg:address":"Carrer de Antoni Frontera, 22",
    "sg:city":"Palma",
    "sg:orig_category":"Madera Para Construcci\u00d3n E Industria",
    "sg:phone":"+34 971 20 10 02",
    "sg:postcode":"07004",
    "sg:province":"Islas Baleares",
    "wof:name":"Herrera Mite Bartolome",
    "wof:placetype":"venue"
},
  "geometry": {"coordinates":[2.6531300545,39.5815162659],"type":"Point"}
}