{
  "type": "Feature",
  "properties": {
    "iso:country":"ES",
    "sg:address":"Avda Aragon, 34",
    "sg:city":"Sang\u00fcesa",
    "sg:orig_category":"Electricidad Veh\u00cdculo",
    "sg:phone":"+34 948 87 05 52",
    "sg:postcode":"31400",
    "sg:province":"Navarra",
    "wof:name":"Arenaz Iba\u00f1ez Luis Pascual",
    "wof:placetype":"venue"
},
  "geometry": {"coordinates":[-1.280654788,42.5736312866],"type":"Point"}
}