{
  "type": "Feature",
  "properties": {
    "addr:full":"Rbla Roma Barnes, 3 Lloret Mar Girona 17310",
    "addr:housenumber":"3",
    "addr:postcode":"17310",
    "addr:street":"Rbla Roma Barnes",
    "iso:country":"ES",
    "sg:address":"Rbla Roma Barnes, 3",
    "sg:city":"Lloret Mar",
    "sg:orig_category":"Artesan\u00cda De Mesa: Cristaler\u00cda, Vajilla, Orfebrer\u00cda (fabricaci\u00d3n, Al Por Mayor)",
    "sg:phone":"+34 972 36 42 39",
    "sg:postcode":"17310",
    "sg:province":"Girona",
    "wof:name":"Fonrodona Su\u00f1e Emilio",
    "wof:placetype":"venue"
},
  "geometry": {"coordinates":[2.8460969925,41.6983718872],"type":"Point"}
}