{
  "type": "Feature",
  "properties": {
    "iso:country":"ES",
    "sg:address":"Avda Valencia, 91",
    "sg:city":"Gangosa",
    "sg:orig_category":"Aparatos E Instalaci\u00d3n De Regad\u00cdos",
    "sg:phone":"+34 950 34 19 47",
    "sg:postcode":"04738",
    "sg:province":"Almer\u00eda",
    "wof:name":"Novedades Agricolas S. A.",
    "wof:placetype":"venue"
},
  "geometry": {"coordinates":[-2.6150989532,36.8059387207],"type":"Point"}
}