{
  "type": "Feature",
  "properties": {
    "addr:full":"Calle de Padre Anchieta, 12 San Isidro Santa Cruz De Tenerife 38611",
    "addr:housenumber":"12",
    "addr:postcode":"38611",
    "addr:street":"Calle De Padre Anchieta",
    "iso:country":"ES",
    "sg:address":"Calle de Padre Anchieta, 12",
    "sg:city":"San Isidro",
    "sg:orig_category":"Supermercados Y Hipermercados",
    "sg:phone":"+34 922 39 37 51",
    "sg:postcode":"38611",
    "sg:province":"Santa Cruz De Tenerife",
    "wof:name":"Martin Tarilonte Jose Maria",
    "wof:placetype":"venue"
},
  "geometry": {"coordinates":[-16.5605049133,28.0771751404],"type":"Point"}
}