{
  "type": "Feature",
  "properties": {
    "iso:country":"ES",
    "sg:address":"Carrer de Alexandre Gali, 29",
    "sg:city":"Barcelona",
    "sg:orig_category":"Empresas De Pintura Y Revestimientos",
    "sg:phone":"+34 933 52 27 54",
    "sg:postcode":"08027",
    "sg:province":"Barcelona",
    "wof:name":"Construcciones Y Estudios Toison S. A.",
    "wof:placetype":"venue"
},
  "geometry": {"coordinates":[2.1783630848,41.4262275696],"type":"Point"}
}