{
  "type": "Feature",
  "properties": {
    "addr:full":"Calle de Joaquin Bau, 7 Madrid Madrid 28036",
    "addr:housenumber":"7",
    "addr:postcode":"madrid;28036",
    "addr:street":"Calle De Joaquin Bau",
    "iso:country":"ES",
    "sg:address":"Calle de Joaquin Bau, 7",
    "sg:city":"Madrid",
    "sg:orig_category":"Abogados",
    "sg:phone":"+34 913 59 00 62",
    "sg:postcode":"28036",
    "sg:province":"Madrid",
    "wof:name":"Vandano S.l.",
    "wof:placetype":"venue"
},
  "geometry": {"coordinates":[-3.6855990887,40.4639778137],"type":"Point"}
}