{
  "type": "Feature",
  "properties": {
    "addr:full":"Calle de Division Azul, 6 Coru\u00d1a La Coru\u00f1a 15005",
    "addr:housenumber":"6",
    "addr:postcode":"15005",
    "addr:street":"Calle De Division Azul;La Corun\u0303A",
    "iso:country":"ES",
    "sg:address":"Calle de Division Azul, 6",
    "sg:city":"Coru\u00d1a",
    "sg:orig_category":"Molduras, Junquillos, Listones Y Molduras Perforadas",
    "sg:phone":"+34 981 25 39 00",
    "sg:postcode":"15005",
    "sg:province":"La Coru\u00f1a",
    "wof:name":"Antelo Martinez Maria",
    "wof:placetype":"venue"
},
  "geometry": {"coordinates":[-8.4076385498,43.3603057861],"type":"Point"}
}