{
  "type": "Feature",
  "properties": {
    "addr:full":"Cachons, S/n Cachons La Coru\u00f1a 15886",
    "addr:postcode":"15886",
    "addr:street":"Cachons S / N Cachons La Corun\u0303A",
    "iso:country":"ES",
    "sg:address":"Cachons, S/n",
    "sg:city":"Cachons",
    "sg:orig_category":"Ingeniero",
    "sg:phone":"+34 981 80 95 61",
    "sg:postcode":"15886",
    "sg:province":"La Coru\u00f1a",
    "wof:name":"Naveira Pequeno Jesus",
    "wof:placetype":"venue"
},
  "geometry": {"coordinates":[-8.5489406586,42.79429245],"type":"Point"}
}