{
  "type": "Feature",
  "properties": {
    "iso:country":"ES",
    "sg:address":"Barri Brugarol, 71",
    "sg:city":"Palafrugell",
    "sg:orig_category":"Agentes, Concesionarios Y Sucursales De Veh\u00cdculos",
    "sg:phone":"+34 972 30 24 51",
    "sg:postcode":"17200",
    "sg:province":"Girona",
    "wof:name":"Auto Taller Cane S.l.",
    "wof:placetype":"venue"
},
  "geometry": {"coordinates":[3.1629064083,41.9109420776],"type":"Point"}
}