{
  "type": "Feature",
  "properties": {
    "iso:country":"ES",
    "sg:address":"Calle de Constitucion, S/n",
    "sg:city":"Guadalajara",
    "sg:orig_category":"Carnicer\u00cdas, Carnicer\u00cdas",
    "sg:phone":"+34 949 22 55 03",
    "sg:postcode":"19003",
    "sg:province":"Guadalajara",
    "wof:name":"Ruiz Valderas Fernando",
    "wof:placetype":"venue"
},
  "geometry": {"coordinates":[-3.1753799915,40.628692627],"type":"Point"}
}