{
  "type": "Feature",
  "properties": {
    "addr:full":"Plaz Constitucion, 1 Villardompardo Ja\u00e9n 23659",
    "addr:housenumber":"1",
    "addr:postcode":"23659",
    "addr:street":"Constitucion;Jae\u0301N",
    "iso:country":"ES",
    "sg:address":"Plaz Constitucion, 1",
    "sg:city":"Villardompardo",
    "sg:orig_category":"Administraciones Regionales, Departamentales Y Locales",
    "sg:phone":"+34 953 57 60 07",
    "sg:postcode":"23659",
    "sg:province":"Ja\u00e9n",
    "wof:name":"Ayuntamiento De Villadompardo",
    "wof:placetype":"venue"
},
  "geometry": {"coordinates":[-4.0043787956,37.8422012329],"type":"Point"}
}