{
  "type": "Feature",
  "properties": {
    "iso:country":"ES",
    "sg:address":"Avda Espa\u00d1a, 3",
    "sg:city":"Ponferrada",
    "sg:orig_category":"Abogados",
    "sg:phone":"+34 987 41 06 86",
    "sg:postcode":"24400",
    "sg:province":"Le\u00f3n",
    "wof:name":"Velasco Arias Adolfo",
    "wof:placetype":"venue"
},
  "geometry": {"coordinates":[-6.598528862,42.5477752686],"type":"Point"}
}