{
  "type": "Feature",
  "properties": {
    "iso:country":"ES",
    "sg:address":"Carrer de Major, 21",
    "sg:city":"Castellbisbal",
    "sg:orig_category":"Tintes (fabricaci\u00d3n, Al Por Mayor)",
    "sg:phone":"+34 937 72 02 86",
    "sg:postcode":"08755",
    "sg:province":"Barcelona",
    "wof:name":"Tintorerias Playa S.l.",
    "wof:placetype":"venue"
},
  "geometry": {"coordinates":[1.9805510044,41.4761009216],"type":"Point"}
}