{
  "type": "Feature",
  "properties": {
    "addr:full":"Sect Pueblos, 1 Tres Cantos Madrid 28760",
    "addr:housenumber":"1",
    "addr:postcode":"28760",
    "addr:street":"Pueblos",
    "iso:country":"ES",
    "sg:address":"Sect Pueblos, 1",
    "sg:city":"Tres Cantos",
    "sg:orig_category":"Alimentaci\u00d3n General (al Por Menor)",
    "sg:phone":"+34 918 03 29 25",
    "sg:postcode":"28760",
    "sg:province":"Madrid",
    "wof:name":"Alcalde Martinez Francisco",
    "wof:placetype":"venue"
},
  "geometry": {"coordinates":[-3.7129912376,40.6115608215],"type":"Point"}
}