{
  "type": "Feature",
  "properties": {
    "iso:country":"ES",
    "sg:address":"Avda San Mames, 87",
    "sg:city":"Le\u00f3n",
    "sg:orig_category":"Fabricaci\u00d3n, Importaci\u00d3n, Venta De Material De Telefon\u00cda, Peritelefon\u00cda",
    "sg:phone":"+34 987 27 27 69",
    "sg:postcode":"24007",
    "sg:province":"Le\u00f3n",
    "wof:name":"Alfayete Alvarez Roberto",
    "wof:placetype":"venue"
},
  "geometry": {"coordinates":[-5.5712041855,42.6083641052],"type":"Point"}
}