{
  "type": "Feature",
  "properties": {
    "addr:full":"Calle de Santa Brigida, 22 Majadahonda Madrid 28220",
    "addr:housenumber":"22",
    "addr:postcode":"28220",
    "addr:street":"Calle De Santa Brigida",
    "iso:country":"ES",
    "sg:address":"Calle de Santa Brigida, 22",
    "sg:city":"Majadahonda",
    "sg:orig_category":"Centros Empresariales",
    "sg:phone":"+34 916 38 67 05",
    "sg:postcode":"28220",
    "sg:province":"Madrid",
    "wof:name":"Ept Consulting S.l.",
    "wof:placetype":"venue"
},
  "geometry": {"coordinates":[-3.866202116,40.4700431824],"type":"Point"}
}