{
  "type": "Feature",
  "properties": {
    "iso:country":"ES",
    "sg:address":"Calle de Bilbao, 26",
    "sg:city":"Albacete",
    "sg:orig_category":"Carnicer\u00cdas, Carnicer\u00cdas",
    "sg:phone":"+34 967 23 82 56",
    "sg:postcode":"02005",
    "sg:province":"Albacete",
    "wof:name":"Gonzalez Argando\u00f1a Felix",
    "wof:placetype":"venue"
},
  "geometry": {"coordinates":[-1.8674205542,39.0009002686],"type":"Point"}
}