{
  "type": "Feature",
  "properties": {
    "addr:full":"Calle de Rabadanes, 69 Cabezas S. Juan Sevilla 41730",
    "addr:housenumber":"69",
    "addr:postcode":"41730",
    "addr:street":"Calle De Rabadanes;S.",
    "iso:country":"ES",
    "sg:address":"Calle de Rabadanes, 69",
    "sg:city":"Cabezas S. Juan",
    "sg:orig_category":"Quincaller\u00cda (al Por Menor)",
    "sg:phone":"+34 955 87 01 29",
    "sg:postcode":"41730",
    "sg:province":"Sevilla",
    "wof:name":"Gonzalez Alonso Domingo",
    "wof:placetype":"venue"
},
  "geometry": {"coordinates":[-5.9394001961,36.9844551086],"type":"Point"}
}