{
  "type": "Feature",
  "properties": {
    "addr:full":"Carr Torre De Sant Narcis, 9 Girona Girona 17007",
    "addr:housenumber":"9",
    "addr:postcode":"17007",
    "addr:street":"Carr Torre De Sant Narcis",
    "iso:country":"ES",
    "sg:address":"Carr Torre De Sant Narcis, 9",
    "sg:city":"Girona",
    "sg:orig_category":"Perreras, Pensiones Para Perros, Gatos Y Otros Animales",
    "sg:phone":"+34 972 20 55 84",
    "sg:postcode":"17007",
    "sg:province":"Girona",
    "wof:name":"Barba Parera Carles",
    "wof:placetype":"venue"
},
  "geometry": {"coordinates":[2.8035190105,41.9965400696],"type":"Point"}
}