{
  "type": "Feature",
  "properties": {
    "iso:country":"ES",
    "sg:address":"Carrer de Doctor Buxo, 17",
    "sg:city":"Montcada Centre",
    "sg:orig_category":"Peluquer\u00cdas, Peluquer\u00cda Mixta",
    "sg:phone":"+34 935 75 12 99",
    "sg:postcode":"08110",
    "sg:province":"Barcelona",
    "wof:name":"Berzosa Cervantes Angeles",
    "wof:placetype":"venue"
},
  "geometry": {"coordinates":[2.1893389225,41.4859848022],"type":"Point"}
}