{
  "type": "Feature",
  "properties": {
    "addr:full":"Carrer de Verge De La Merce, 23 Esplugues Llobregat Barcelona 08950",
    "addr:housenumber":"23",
    "addr:postcode":"08950",
    "addr:street":"Carrer De Verge De La Merce",
    "iso:country":"ES",
    "sg:address":"Carrer de Verge De La Merce, 23",
    "sg:city":"Esplugues Llobregat",
    "sg:orig_category":"Ropa Para Se\u00d1oras Y Caballeros (al Por Menor)",
    "sg:phone":"+34 933 71 25 44",
    "sg:postcode":"08950",
    "sg:province":"Barcelona",
    "wof:name":"Lin  Lifeng",
    "wof:placetype":"venue"
},
  "geometry": {"coordinates":[2.0842609406,41.3737335205],"type":"Point"}
}