{
  "type": "Feature",
  "properties": {
    "iso:country":"ES",
    "sg:address":"Barr Caviedes, S/n",
    "sg:city":"Caviedes",
    "sg:orig_category":"Distribuci\u00d3n De Petr\u00d3leo Y Derivados",
    "sg:phone":"+34 942 70 93 20",
    "sg:postcode":"39593",
    "sg:province":"Cantabria",
    "wof:name":"Repsol Ypf S.a.",
    "wof:placetype":"venue"
},
  "geometry": {"coordinates":[-4.3266730309,43.3378829956],"type":"Point"}
}