{
  "type": "Feature",
  "properties": {
    "iso:country":"ES",
    "sg:address":"Cra Navarcles, Km. 0003,5",
    "sg:city":"Santpedor",
    "sg:orig_category":"Fabricaci\u00d3n Y Venta De Volquetes Y Remolques",
    "sg:phone":"+34 938 27 20 06",
    "sg:postcode":"08251",
    "sg:province":"Barcelona",
    "sg:website":"www.sefes.es/inducast",
    "wof:name":"Inducast S.l.",
    "wof:placetype":"venue"
},
  "geometry": {"coordinates":[1.8371499777,41.8343658447],"type":"Point"}
}