{
  "type": "Feature",
  "properties": {
    "addr:full":"Calle de Vargas, 7 Jaraiz Vera C\u00e1ceres 10400",
    "addr:housenumber":"7",
    "addr:postcode":"10400",
    "addr:street":"Calle De Vargas",
    "iso:country":"ES",
    "sg:address":"Calle de Vargas, 7",
    "sg:city":"Jaraiz Vera",
    "sg:orig_category":"Zapatos (al Por Menor)",
    "sg:phone":"+34 927 46 01 91",
    "sg:postcode":"10400",
    "sg:province":"C\u00e1ceres",
    "wof:name":"Sanchez Gil Teodoro",
    "wof:placetype":"venue"
},
  "geometry": {"coordinates":[-5.7546701431,40.0592384338],"type":"Point"}
}