{
  "type": "Feature",
  "properties": {
    "addr:full":"Carrer de Navarra, 39 Masnou Barcelona 08320",
    "addr:housenumber":"39",
    "addr:postcode":"08320",
    "addr:street":"Carrer De Navarra",
    "iso:country":"ES",
    "sg:address":"Carrer de Navarra, 39",
    "sg:city":"Masnou",
    "sg:orig_category":"Psic\u00d3logos",
    "sg:phone":"+34 935 55 66 10",
    "sg:postcode":"08320",
    "sg:province":"Barcelona",
    "sg:website":"www.maxilon.net/psico",
    "wof:name":"Ripol Millet Beatriz",
    "wof:placetype":"venue"
},
  "geometry": {"coordinates":[2.3166871071,41.4811325073],"type":"Point"}
}