{
  "type": "Feature",
  "properties": {
    "addr:full":"Carrer de Major, 175 Ulldecona Tarragona 43550",
    "addr:postcode":"43550",
    "addr:street":"Carrer De Major 175",
    "iso:country":"ES",
    "sg:address":"Carrer de Major, 175",
    "sg:city":"Ulldecona",
    "sg:orig_category":"Sindicatos Y Colegios Profesionales",
    "sg:phone":"+34 977 72 01 54",
    "sg:postcode":"43550",
    "sg:province":"Tarragona",
    "wof:name":"Comunidad De Regantes De Ulldecona",
    "wof:placetype":"venue"
},
  "geometry": {"coordinates":[0.444137007,40.5941963196],"type":"Point"}
}