{
  "type": "Feature",
  "properties": {
    "iso:country":"ES",
    "sg:address":"Avda Francisco Afonso Carrillo, S/n",
    "sg:city":"Dehesas",
    "sg:orig_category":"Alquiler De Veh\u00cdculos: Turismos Y Utilitarios",
    "sg:phone":"+34 922 37 14 90",
    "sg:postcode":"38400",
    "sg:province":"Santa Cruz De Tenerife",
    "wof:name":"Autos 3000 S.l.",
    "wof:placetype":"venue"
},
  "geometry": {"coordinates":[-16.560798645,28.4110889435],"type":"Point"}
}