{
  "type": "Feature",
  "properties": {
    "addr:full":"Carrer de Aprestadora, 96 Hospitalet Llobregat Barcelona 08902",
    "addr:housenumber":"96",
    "addr:postcode":"08902",
    "addr:street":"Carrer De Aprestadora",
    "iso:country":"ES",
    "sg:address":"Carrer de Aprestadora, 96",
    "sg:city":"Hospitalet Llobregat",
    "sg:classifiers":[
        {
            "category":"Autos & Motor Vehicles",
            "subcategory":"Automobile Sales",
            "type":"Retail Goods"
        }
    ],
    "sg:phone":"+34 934 22 16 40",
    "sg:postcode":"08902",
    "sg:province":"Barcelona",
    "wof:name":"Delgado Machio Francisco",
    "wof:placetype":"venue"
},
  "geometry": {"coordinates":[2.1256549358,41.3620758057],"type":"Point"}
}