{
  "type": "Feature",
  "properties": {
    "addr:full":"Calle de Nuestra Se\u00d1ora De Las Nieves, 8 Puerto De Las Nieves Las Palmas 35489",
    "addr:housenumber":"8",
    "addr:postcode":"35489",
    "addr:street":"Calle De Nuestra Sen\u0303Ora De Las Nieves",
    "iso:country":"ES",
    "sg:address":"Calle de Nuestra Se\u00d1ora De Las Nieves, 8",
    "sg:city":"Puerto De Las Nieves",
    "sg:orig_category":"Centros Comerciales Y Grandes Tiendas",
    "sg:phone":"+34 928 89 85 40",
    "sg:postcode":"35489",
    "sg:province":"Las Palmas",
    "wof:name":"Medina Vega Dolores",
    "wof:placetype":"venue"
},
  "geometry": {"coordinates":[-15.7107448578,28.1012477875],"type":"Point"}
}