{
  "type": "Feature",
  "properties": {
    "addr:full":"Po. Ind Corts, 8 Cabrera Mar Barcelona 08349",
    "addr:housenumber":"8",
    "addr:postcode":"08349",
    "addr:street":"Corts",
    "iso:country":"ES",
    "sg:address":"Po. Ind Corts, 8",
    "sg:city":"Cabrera Mar",
    "sg:orig_category":"Ropa Y Accesorios",
    "sg:phone":"+34 937 56 62 32",
    "sg:postcode":"08349",
    "sg:province":"Barcelona",
    "wof:name":"World Complements S.l.",
    "wof:placetype":"venue"
},
  "geometry": {"coordinates":[2.1699187756,41.3879165649],"type":"Point"}
}