{
  "type": "Feature",
  "properties": {
    "addr:full":"Av La Paz, 18 Onil Alicante 03430",
    "addr:housenumber":"18",
    "addr:postcode":"03430",
    "addr:street":"Av La Paz",
    "iso:country":"ES",
    "sg:address":"Av La Paz, 18",
    "sg:city":"Onil",
    "sg:orig_category":"Supermercados Y Hipermercados",
    "sg:phone":"+34 966 55 71 13",
    "sg:postcode":"03430",
    "sg:province":"Alicante",
    "wof:name":"Dialsur S.a.",
    "wof:placetype":"venue"
},
  "geometry": {"coordinates":[-0.6775159836,38.6278038025],"type":"Point"}
}