{
  "type": "Feature",
  "properties": {
    "addr:full":"Rua General Rubin, 26 Redondela Pontevedra 36800",
    "addr:housenumber":"26",
    "addr:postcode":"36800",
    "addr:street":"Rua General Rubin",
    "iso:country":"ES",
    "sg:address":"Rua General Rubin, 26",
    "sg:city":"Redondela",
    "sg:orig_category":"Loter\u00cda Y T\u00d3mbola",
    "sg:phone":"+34 986 40 13 09",
    "sg:postcode":"36800",
    "sg:province":"Pontevedra",
    "wof:name":"Rodriguez Brea Maria Rita",
    "wof:placetype":"venue"
},
  "geometry": {"coordinates":[-8.6090641022,42.2820243835],"type":"Point"}
}