{
  "type": "Feature",
  "properties": {
    "addr:full":"Finc Silos, S/n Calera Y Chozas Toledo 45595",
    "addr:housenumber":"s / n",
    "addr:postcode":"45595",
    "iso:country":"ES",
    "sg:address":"Finc Silos, S/n",
    "sg:city":"Calera Y Chozas",
    "sg:orig_category":"Producci\u00d3n, Venta De Productos De Agricultura Biol\u00d3gica",
    "sg:phone":"+34 925 59 90 03",
    "sg:postcode":"45595",
    "sg:province":"Toledo",
    "wof:name":"Silos Del Tajo S.l.",
    "wof:placetype":"venue"
},
  "geometry": {"coordinates":[-5.0072097778,39.8687896729],"type":"Point"}
}