{
  "type": "Feature",
  "properties": {
    "addr:full":"C/ Canaries, 103 Cerdanyola Valles Barcelona 08290",
    "addr:housenumber":"103",
    "addr:postcode":"08290",
    "addr:street":"C / Canaries;Valles Barcelona",
    "iso:country":"ES",
    "sg:address":"C/ Canaries, 103",
    "sg:city":"Cerdanyola Valles",
    "sg:orig_category":"Sociedades, Compa\u00d1\u00cdas Aseguradoras",
    "sg:phone":"+34 935 86 46 40",
    "sg:postcode":"08290",
    "sg:province":"Barcelona",
    "sg:website":"www.seguradit.com",
    "wof:name":"Segur Audit Correduria De Seguros S.l.",
    "wof:placetype":"venue"
},
  "geometry": {"coordinates":[2.1212480068,41.5004386902],"type":"Point"}
}