{
  "type": "Feature",
  "properties": {
    "iso:country":"ES",
    "sg:address":"Calle de Monterregado, 3",
    "sg:city":"Zaragoza",
    "sg:orig_category":"Mec\u00c1nico Del Autom\u00d3vil",
    "sg:phone":"+34 976 38 48 06",
    "sg:postcode":"50007",
    "sg:province":"Zaragoza",
    "wof:name":"Segrezauto S.cv.",
    "wof:placetype":"venue"
},
  "geometry": {"coordinates":[-0.8870990276,41.6319198608],"type":"Point"}
}