{
  "type": "Feature",
  "properties": {
    "addr:full":"Tor. Tortuguer (els Pinetons), 41 Ripollet Barcelona 08291",
    "addr:housenumber":"41",
    "addr:postcode":"08291",
    "addr:street":"Pinetons",
    "iso:country":"ES",
    "sg:address":"Tor. Tortuguer (els Pinetons), 41",
    "sg:city":"Ripollet",
    "sg:orig_category":"Promotores Constructores",
    "sg:phone":"+34 935 80 08 47",
    "sg:postcode":"08291",
    "sg:province":"Barcelona",
    "wof:name":"Stonegru S.l.",
    "wof:placetype":"venue"
},
  "geometry": {"coordinates":[2.1489770412,41.5094833374],"type":"Point"}
}