{
  "type": "Feature",
  "properties": {
    "iso:country":"ES",
    "sg:address":"Av Sant Julia, S/n",
    "sg:city":"Granollers",
    "sg:orig_category":"Perfumer\u00cda Y Cosm\u00c9tica (fabricaci\u00d3n, Al Por Mayor)",
    "sg:phone":"+34 938 49 38 55",
    "sg:postcode":"08403",
    "sg:province":"Barcelona",
    "wof:name":"Capel Cosmetics S.a.",
    "wof:placetype":"venue"
},
  "geometry": {"coordinates":[2.2729549408,41.576335907],"type":"Point"}
}