{
  "type": "Feature",
  "properties": {
    "iso:country":"ES",
    "sg:address":"Calle de Torrevieja, 29",
    "sg:city":"Pola De Siero",
    "sg:orig_category":"Asociaciones Y Clubs Deportivos",
    "sg:phone":"+34 985 72 26 31",
    "sg:postcode":"33510",
    "sg:province":"Asturias",
    "wof:name":"Club Siero",
    "wof:placetype":"venue"
},
  "geometry": {"coordinates":[-5.6548819542,43.3961982727],"type":"Point"}
}