{
  "type": "Feature",
  "properties": {
    "addr:full":"Pg Estacio De L', 12 Valls Tarragona 43800",
    "addr:housenumber":"12",
    "addr:postcode":"43800",
    "addr:street":"Pg Estacio De L '",
    "iso:country":"ES",
    "sg:address":"Pg Estacio De L', 12",
    "sg:city":"Valls",
    "sg:orig_category":"Sociedades, Compa\u00d1\u00cdas Aseguradoras",
    "sg:phone":"+34 977 60 81 14",
    "sg:postcode":"43800",
    "sg:province":"Tarragona",
    "sg:website":"www.mapfre.com",
    "wof:name":"Mapfre Servicios De Informatica S.a.",
    "wof:placetype":"venue"
},
  "geometry": {"coordinates":[1.2525299788,41.2871513367],"type":"Point"}
}