{
  "type": "Feature",
  "properties": {
    "iso:country":"ES",
    "sg:address":"Calle de Torrelaguna, 67",
    "sg:city":"Madrid",
    "sg:orig_category":"Abogados",
    "sg:phone":"+34 914 04 41 23",
    "sg:postcode":"28027",
    "sg:province":"Madrid",
    "wof:name":"Solana & Marquet Asociados S.l.",
    "wof:placetype":"venue"
},
  "geometry": {"coordinates":[-3.6545202732,40.4439468384],"type":"Point"}
}