{
  "type": "Feature",
  "properties": {
    "addr:full":"Carrer de Mare De Deu De La Cisa, 73 Mataro Barcelona 08303",
    "addr:housenumber":"73",
    "addr:postcode":"08303",
    "addr:street":"Carrer De Mare De Deu De La Cisa",
    "iso:country":"ES",
    "sg:address":"Carrer de Mare De Deu De La Cisa, 73",
    "sg:city":"Mataro",
    "sg:orig_category":"Peluqueros: De Se\u00d1oras",
    "sg:phone":"+34 937 99 45 33",
    "sg:postcode":"08303",
    "sg:province":"Barcelona",
    "wof:name":"Emilio Serrano Victoria",
    "wof:placetype":"venue"
},
  "geometry": {"coordinates":[2.4252889156,41.5362014771],"type":"Point"}
}