{
  "type": "Feature",
  "properties": {
    "addr:full":"Poli Cortijo Real - Plg.indust., S/n Algeciras C\u00e1diz 11206",
    "addr:housenumber":"s / n;ca\u0301diz",
    "addr:postcode":"11206",
    "iso:country":"ES",
    "sg:address":"Poli Cortijo Real - Plg.indust., S/n",
    "sg:city":"Algeciras",
    "sg:orig_category":"Mec\u00c1nico Del Autom\u00d3vil",
    "sg:phone":"+34 956 60 24 37",
    "sg:postcode":"11206",
    "sg:province":"C\u00e1diz",
    "wof:name":"Talleres Sola Y Valdivia S.l.",
    "wof:placetype":"venue"
},
  "geometry": {"coordinates":[-5.5359191895,36.1193008423],"type":"Point"}
}