{
  "type": "Feature",
  "properties": {
    "addr:full":"Carr Dr. Enrique Gargallo Lopez, 13 Manises Valencia 46940",
    "addr:housenumber":"13",
    "addr:postcode":"46940",
    "addr:street":"Carr Dr. Enrique Gargallo Lopez",
    "iso:country":"ES",
    "sg:address":"Carr Dr. Enrique Gargallo Lopez, 13",
    "sg:city":"Manises",
    "sg:orig_category":"Laboratorios Y Trabajos De Fotograf\u00cda, V\u00cddeo Y Cine",
    "sg:phone":"+34 961 54 53 87",
    "sg:postcode":"46940",
    "sg:province":"Valencia",
    "wof:name":"Estudios Sanchis S.l.c.",
    "wof:placetype":"venue"
},
  "geometry": {"coordinates":[-0.4587340057,39.4921302795],"type":"Point"}
}