{
  "type": "Feature",
  "properties": {
    "addr:full":"Torre, 6 Trebaluger Islas Baleares 07713",
    "addr:postcode":"07713",
    "addr:street":"Islas",
    "iso:country":"ES",
    "sg:address":"Torre, 6",
    "sg:city":"Trebaluger",
    "sg:orig_category":"Inmobiliaria (agencias)",
    "sg:phone":"+34 971 15 06 76",
    "sg:postcode":"07713",
    "sg:province":"Islas Baleares",
    "wof:name":"Niemand S. A.",
    "wof:placetype":"venue"
},
  "geometry": {"coordinates":[4.2635698318,39.8131599426],"type":"Point"}
}