{
  "type": "Feature",
  "properties": {
    "addr:full":"Pase Chopera (de La), S/n Partija-santa Monica Madrid 28529",
    "addr:housenumber":"s",
    "addr:postcode":"28529",
    "addr:street":"/ N Partija-Santa",
    "iso:country":"ES",
    "sg:address":"Pase Chopera (de La), S/n",
    "sg:city":"Partija-santa Monica",
    "sg:orig_category":"M\u00c9dicos: Estomatolog\u00cda",
    "sg:phone":"+34 916 66 56 77",
    "sg:postcode":"28529",
    "sg:province":"Madrid",
    "wof:name":"Ameghino  Oscar Bernardo",
    "wof:placetype":"venue"
},
  "geometry": {"coordinates":[-3.7003455162,40.4166908264],"type":"Point"}
}