{
  "type": "Feature",
  "properties": {
    "iso:country":"ES",
    "sg:address":"Calle de Jose Molina, 7",
    "sg:city":"Arrecife",
    "sg:orig_category":"\u00d3ptica: Instrumentos (fabricaci\u00d3n)",
    "sg:phone":"+34 928 81 65 47",
    "sg:postcode":"35500",
    "sg:province":"Las Palmas",
    "wof:name":"Opticos Lanzarote S.l.",
    "wof:placetype":"venue"
},
  "geometry": {"coordinates":[-13.5492181778,28.9591331482],"type":"Point"}
}