{
  "type": "Feature",
  "properties": {
    "addr:full":"Calle de Constitucion, 61 Balazote Albacete 02320",
    "addr:housenumber":"61",
    "addr:postcode":"02320",
    "addr:street":"Calle De Constitucion",
    "iso:country":"ES",
    "sg:address":"Calle de Constitucion, 61",
    "sg:city":"Balazote",
    "sg:orig_category":"Centros Empresariales",
    "sg:phone":"+34 967 36 10 39",
    "sg:postcode":"02320",
    "sg:province":"Albacete",
    "wof:name":"Ferro-alba S.c.l",
    "wof:placetype":"venue"
},
  "geometry": {"coordinates":[-2.1551020145,38.8862457275],"type":"Point"}
}