{
  "type": "Feature",
  "properties": {
    "iso:country":"ES",
    "sg:address":"Avda. Espa\u00f1a, 11",
    "sg:city":"Elviria",
    "sg:orig_category":"Agencias Y Agentes Comerciales, Representantes",
    "sg:phone":"+34 952 83 61 83",
    "sg:postcode":"29604",
    "sg:province":"M\u00e1laga",
    "wof:name":"Hanack  Johann",
    "wof:placetype":"venue"
},
  "geometry": {"coordinates":[-4.7715616226,36.5040855408],"type":"Point"}
}