{
  "type": "Feature",
  "properties": {
    "addr:full":"Calle de Guardacostas, 3 Valencia Valencia 46009",
    "addr:housenumber":"3",
    "addr:postcode":"46009",
    "addr:street":"Calle De Guardacostas",
    "iso:country":"ES",
    "sg:address":"Calle de Guardacostas, 3",
    "sg:city":"Valencia",
    "sg:orig_category":"Molduras, Junquillos, Listones Y Molduras Perforadas",
    "sg:phone":"+34 963 40 65 88",
    "sg:postcode":"46009",
    "sg:province":"Valencia",
    "wof:name":"Torresano Torresano Maria Rosario",
    "wof:placetype":"venue"
},
  "geometry": {"coordinates":[-0.3824569881,39.4897155762],"type":"Point"}
}