{
  "type": "Feature",
  "properties": {
    "iso:country":"ES",
    "sg:address":"Granada, 5",
    "sg:city":"Orgiva",
    "sg:orig_category":"Farmacias",
    "sg:phone":"+34 958 78 44 05",
    "sg:postcode":"18400",
    "sg:province":"Granada",
    "wof:name":"Martin Salvago Maria Angeles",
    "wof:placetype":"venue"
},
  "geometry": {"coordinates":[-3.4233849049,36.9028091431],"type":"Point"}
}