{
  "type": "Feature",
  "properties": {
    "addr:full":"Calle de Do\u00d1a Urraca, 1 Palencia Palencia 34001",
    "addr:housenumber":"1",
    "addr:postcode":"34001",
    "addr:street":"Calle De Don\u0303A Urraca",
    "iso:country":"ES",
    "sg:address":"Calle de Do\u00d1a Urraca, 1",
    "sg:city":"Palencia",
    "sg:orig_category":"Psic\u00d3logos",
    "sg:phone":"+34 979 75 06 84",
    "sg:postcode":"34001",
    "sg:province":"Palencia",
    "wof:name":"Martin Aduriz Fernando",
    "wof:placetype":"venue"
},
  "geometry": {"coordinates":[-4.534763813,42.0124053955],"type":"Point"}
}