{
  "type": "Feature",
  "properties": {
    "addr:full":"Cust Atalaya, 27 Santander Cantabria 39001",
    "addr:housenumber":"27",
    "addr:postcode":"39001",
    "iso:country":"ES",
    "sg:address":"Cust Atalaya, 27",
    "sg:city":"Santander",
    "sg:orig_category":"Empresas De Electricidad En General",
    "sg:phone":"+34 942 21 66 36",
    "sg:postcode":"39001",
    "sg:province":"Cantabria",
    "wof:name":"Garcia Briz Claudio",
    "wof:placetype":"venue"
},
  "geometry": {"coordinates":[-3.8078649044,43.4651184082],"type":"Point"}
}