{
  "type": "Feature",
  "properties": {
    "addr:full":"Calle de Ebro, 11 Villamartin C\u00e1diz 11650",
    "addr:housenumber":"11",
    "addr:postcode":"11650",
    "addr:street":"Calle De Ebro;Ca\u0301Diz",
    "iso:country":"ES",
    "sg:address":"Calle de Ebro, 11",
    "sg:city":"Villamartin",
    "sg:orig_category":"Imprenta",
    "sg:phone":"+34 956 73 05 03",
    "sg:postcode":"11650",
    "sg:province":"C\u00e1diz",
    "wof:name":"Camacho Holgado Jose Luis",
    "wof:placetype":"venue"
},
  "geometry": {"coordinates":[-5.6477952003,36.8586387634],"type":"Point"}
}