{
  "type": "Feature",
  "properties": {
    "addr:full":"Calle de Ballerias, 12 San Lorenzo Del Flumen Huesca 22212",
    "addr:housenumber":"12",
    "addr:postcode":"22212",
    "addr:street":"Calle De Ballerias",
    "iso:country":"ES",
    "sg:address":"Calle de Ballerias, 12",
    "sg:city":"San Lorenzo Del Flumen",
    "sg:orig_category":"Cajas Para Embalar",
    "sg:phone":"+34 974 39 51 28",
    "sg:postcode":"22212",
    "sg:province":"Huesca",
    "wof:name":"Caja Rural Aragonesa Y De Los Pirineos",
    "wof:placetype":"venue"
},
  "geometry": {"coordinates":[-0.1995370984,41.8735809326],"type":"Point"}
}