{
  "type": "Feature",
  "properties": {
    "addr:full":"Calle de Orense, 25 Zaragoza Zaragoza 50007",
    "addr:housenumber":"25",
    "addr:postcode":"50007",
    "addr:street":"Calle De Orense",
    "iso:country":"ES",
    "sg:address":"Calle de Orense, 25",
    "sg:city":"Zaragoza",
    "sg:orig_category":"Electricidad: Instaladores",
    "sg:phone":"+34 976 37 65 56",
    "sg:postcode":"50007",
    "sg:province":"Zaragoza",
    "wof:name":"Fosber S.l.",
    "wof:placetype":"venue"
},
  "geometry": {"coordinates":[-0.8850979805,41.6274375916],"type":"Point"}
}