{
  "type": "Feature",
  "properties": {
    "addr:full":"Calle de Rodriguez San Pedro, 61 Madrid Madrid 28015",
    "addr:housenumber":"61",
    "addr:postcode":"madrid;28015",
    "addr:street":"Calle De Rodriguez San Pedro",
    "iso:country":"ES",
    "sg:address":"Calle de Rodriguez San Pedro, 61",
    "sg:city":"Madrid",
    "sg:orig_category":"Bazares, Art\u00cdculos De Limpieza Y De Cocina (al Por Menor)",
    "sg:phone":"+34 915 44 48 86",
    "sg:postcode":"28015",
    "sg:province":"Madrid",
    "wof:name":"Gutierrez Martinez Julio",
    "wof:placetype":"venue"
},
  "geometry": {"coordinates":[-3.7150290012,40.4317169189],"type":"Point"}
}