{
  "type": "Feature",
  "properties": {
    "iso:country":"ES",
    "sg:address":"Avda Valentin Andres, 8",
    "sg:city":"Grado",
    "sg:orig_category":"Doctores En Medicina",
    "sg:phone":"+34 985 75 03 06",
    "sg:postcode":"33820",
    "sg:province":"Asturias",
    "wof:name":"Crego Marcos Francisco",
    "wof:placetype":"venue"
},
  "geometry": {"coordinates":[-6.0673890114,43.3921089172],"type":"Point"}
}