{
  "type": "Feature",
  "properties": {
    "addr:full":"Calle de Ramon J, 5 Huesca Huesca 22005",
    "addr:postcode":"22005",
    "addr:street":"Calle De Ramon",
    "iso:country":"ES",
    "sg:address":"Calle de Ramon J, 5",
    "sg:city":"Huesca",
    "sg:orig_category":"Peluquer\u00cdas, Peluquer\u00cda Mixta",
    "sg:phone":"+34 974 24 67 37",
    "sg:postcode":"22005",
    "sg:province":"Huesca",
    "wof:name":"Badules Martinez Eva",
    "wof:placetype":"venue"
},
  "geometry": {"coordinates":[-0.403255403,42.1356811523],"type":"Point"}
}