{
  "type": "Feature",
  "properties": {
    "addr:full":"Carrer de L'argenteria, 33 Barcelona Barcelona 08003",
    "addr:housenumber":"33",
    "addr:postcode":"08003",
    "addr:street":"Carrer De L'Argenteria",
    "iso:country":"ES",
    "sg:address":"Carrer de L'argenteria, 33",
    "sg:city":"Barcelona",
    "sg:orig_category":"Electricidad: Instaladores",
    "sg:phone":"+34 933 10 32 46",
    "sg:postcode":"08003",
    "sg:province":"Barcelona",
    "wof:name":"Vila Martinez Jose Antonio",
    "wof:placetype":"venue"
},
  "geometry": {"coordinates":[2.1798856258,41.3837585449],"type":"Point"}
}