{
  "type": "Feature",
  "properties": {
    "addr:full":"Calle de Cordoba, 28 Villanueva Cordoba C\u00f3rdoba 14440",
    "addr:housenumber":"28;cordoba co\u0301rdoba",
    "addr:postcode":"14440",
    "addr:street":"Calle De Cordoba",
    "iso:country":"ES",
    "sg:address":"Calle de Cordoba, 28",
    "sg:city":"Villanueva Cordoba",
    "sg:orig_category":"Promotores Constructores",
    "sg:phone":"+34 957 12 08 90",
    "sg:postcode":"14440",
    "sg:province":"C\u00f3rdoba",
    "wof:name":"Cubiertas Y Contratas Industriales S. A.",
    "wof:placetype":"venue"
},
  "geometry": {"coordinates":[-4.6263208389,38.3184738159],"type":"Point"}
}