{
  "type": "Feature",
  "properties": {
    "iso:country":"ES",
    "sg:address":"C/ Ausias Marc, 4",
    "sg:city":"Bellreguard",
    "sg:orig_category":"Restaurantes",
    "sg:phone":"+34 962 81 57 07",
    "sg:postcode":"46713",
    "sg:province":"Valencia",
    "wof:name":"Pastisseria Salva S.l.",
    "wof:placetype":"venue"
},
  "geometry": {"coordinates":[-0.161797002,38.9471206665],"type":"Point"}
}