{
  "type": "Feature",
  "properties": {
    "iso:country":"ES",
    "sg:address":"Calle de Jose Maria Moreno, 24",
    "sg:city":"Torrelodones",
    "sg:orig_category":"Agencias Y Agentes Comerciales, Representantes",
    "sg:phone":"+34 918 59 33 37",
    "sg:postcode":"28250",
    "sg:province":"Madrid",
    "wof:name":"Bas Vall Ana",
    "wof:placetype":"venue"
},
  "geometry": {"coordinates":[-3.9287350178,40.5783996582],"type":"Point"}
}