{
  "type": "Feature",
  "properties": {
    "addr:full":"Carnicerias, 1 Montealegre Castillo Albacete 02650",
    "addr:housenumber":"1",
    "addr:postcode":"02650",
    "addr:street":"Carnicerias",
    "iso:country":"ES",
    "sg:address":"Carnicerias, 1",
    "sg:city":"Montealegre Castillo",
    "sg:orig_category":"Asesor\u00cda Sobre Comunicaci\u00d3n De Empresas",
    "sg:phone":"+34 967 33 63 20",
    "sg:postcode":"02650",
    "sg:province":"Albacete",
    "wof:name":"Saez Jimenez Ezequiel",
    "wof:placetype":"venue"
},
  "geometry": {"coordinates":[-1.3244249821,38.787021637],"type":"Point"}
}