{
  "type": "Feature",
  "properties": {
    "iso:country":"ES",
    "sg:address":"Calle de Cid El, 4",
    "sg:city":"Blimea",
    "sg:orig_category":"Bebidas",
    "sg:phone":"+34 985 67 12 05",
    "sg:postcode":"33960",
    "sg:province":"Asturias",
    "wof:name":"Carcedo Garcia Vanesa",
    "wof:placetype":"venue"
},
  "geometry": {"coordinates":[-5.5899987221,43.2751121521],"type":"Point"}
}