{
  "type": "Feature",
  "properties": {
    "iso:country":"ES",
    "sg:address":"Carrer de Major, 17",
    "sg:city":"Ametlla Mar",
    "sg:orig_category":"Restaurantes",
    "sg:phone":"+34 977 49 36 49",
    "sg:postcode":"43860",
    "sg:province":"Tarragona",
    "wof:name":"Garbo C.b.",
    "wof:placetype":"venue"
},
  "geometry": {"coordinates":[0.801789999,40.8830604553],"type":"Point"}
}