{
  "type": "Feature",
  "properties": {
    "iso:country":"ES",
    "sg:address":"Afores, S/n",
    "sg:city":"Tivissa",
    "sg:orig_category":"Producci\u00d3n, Venta De Productos De Agricultura Biol\u00d3gica",
    "sg:phone":"+34 977 26 50 31",
    "sg:postcode":"43746",
    "sg:province":"Tarragona",
    "wof:name":"Greenklima Iberica S.l.",
    "wof:placetype":"venue"
},
  "geometry": {"coordinates":[0.6014583707,41.002696991],"type":"Point"}
}