{
  "type": "Feature",
  "properties": {
    "addr:full":"Po. Del Mar, 5 Palmanova Islas Baleares 07181",
    "addr:housenumber":"5",
    "addr:postcode":"07181",
    "addr:street":"Po. Del Mar",
    "iso:country":"ES",
    "sg:address":"Po. Del Mar, 5",
    "sg:city":"Palmanova",
    "sg:orig_category":"Agencias De Viajes",
    "sg:phone":"+34 971 68 15 52",
    "sg:postcode":"07181",
    "sg:province":"Islas Baleares",
    "sg:website":"www.worldservicesmallorca.com",
    "wof:name":"World Spedkins Services S. A.",
    "wof:placetype":"venue"
},
  "geometry": {"coordinates":[2.5401310921,39.5258560181],"type":"Point"}
}