{
  "type": "Feature",
  "properties": {
    "addr:full":"Carrer de Padilla, 167 Barcelona Barcelona 08013",
    "addr:housenumber":"167",
    "addr:postcode":"08013",
    "addr:street":"Carrer De Padilla",
    "iso:country":"ES",
    "sg:address":"Carrer de Padilla, 167",
    "sg:city":"Barcelona",
    "sg:orig_category":"Abogados",
    "sg:phone":"+34 932 45 69 95",
    "sg:postcode":"08013",
    "sg:province":"Barcelona",
    "wof:name":"Trill Gauthronet Yago",
    "wof:placetype":"venue"
},
  "geometry": {"coordinates":[2.1827759743,41.4016304016],"type":"Point"}
}