{
  "type": "Feature",
  "properties": {
    "iso:country":"ES",
    "sg:address":"Calle de Nueva, 1",
    "sg:city":"Motril",
    "sg:orig_category":"Cajas De Ahorro",
    "sg:phone":"+34 958 82 00 60",
    "sg:postcode":"18600",
    "sg:province":"Granada",
    "sg:website":"www.lacaixa.es",
    "wof:name":"Caixa D'estalvis I Pensions De Barcelona",
    "wof:placetype":"venue"
},
  "geometry": {"coordinates":[-3.5186460018,36.748752594],"type":"Point"}
}