{
  "type": "Feature",
  "properties": {
    "iso:country":"ES",
    "sg:address":"Rua Coru\u00d1a, 11",
    "sg:city":"Carballo",
    "sg:orig_category":"Abogados",
    "sg:phone":"+34 981 70 10 16",
    "sg:postcode":"15100",
    "sg:province":"La Coru\u00f1a",
    "wof:name":"Angeriz Varela Jose",
    "wof:placetype":"venue"
},
  "geometry": {"coordinates":[-8.6900072098,43.2122612],"type":"Point"}
}