{
  "type": "Feature",
  "properties": {
    "addr:full":"Calle de Torremegia, 6 Sevilla Sevilla 41016",
    "addr:housenumber":"6",
    "addr:postcode":"41016",
    "addr:street":"Calle De Torremegia",
    "iso:country":"ES",
    "sg:address":"Calle de Torremegia, 6",
    "sg:city":"Sevilla",
    "sg:orig_category":"Obras Y Organismos Sociales",
    "sg:phone":"+34 954 47 50 78",
    "sg:postcode":"41016",
    "sg:province":"Sevilla",
    "wof:name":"Fundacion Geron",
    "wof:placetype":"venue"
},
  "geometry": {"coordinates":[-5.9040489197,37.3827400208],"type":"Point"}
}