{
  "type": "Feature",
  "properties": {
    "addr:full":"Mayor, 45 Ola Navarra 31809",
    "addr:housenumber":"45",
    "addr:postcode":"31809",
    "addr:street":"Mayor;Navarra",
    "iso:country":"ES",
    "sg:address":"Mayor, 45",
    "sg:city":"Ola",
    "sg:orig_category":"Electrodom\u00c9sticos (al Por Menor)",
    "sg:phone":"+34 948 46 75 04",
    "sg:postcode":"31809",
    "sg:province":"Navarra",
    "wof:name":"Aldaz Osinaga Lara",
    "wof:placetype":"venue"
},
  "geometry": {"coordinates":[-2.1998810768,42.8756637573],"type":"Point"}
}