{
  "type": "Feature",
  "properties": {
    "addr:full":"Av Generalitat (de La), 79 Tarrega Lleida 25300",
    "addr:housenumber":"79",
    "addr:postcode":"25300",
    "addr:street":"Av Generalitat De La",
    "iso:country":"ES",
    "sg:address":"Av Generalitat (de La), 79",
    "sg:city":"Tarrega",
    "sg:orig_category":"Negocio De Madera",
    "sg:phone":"+34 973 31 17 18",
    "sg:postcode":"25300",
    "sg:province":"Lleida",
    "wof:name":"Fes-t'ho Amb Fusta S.l.",
    "wof:placetype":"venue"
},
  "geometry": {"coordinates":[1.1485199928,41.6479492188],"type":"Point"}
}