{
  "type": "Feature",
  "properties": {
    "iso:country":"ES",
    "sg:address":"Carrer de Ramon Cama, 1",
    "sg:city":"Malgrat Mar",
    "sg:orig_category":"Empresas De Limpieza",
    "sg:phone":"+34 937 61 20 45",
    "sg:postcode":"08380",
    "sg:province":"Barcelona",
    "wof:name":"Cubas Malgrat S.l.",
    "wof:placetype":"venue"
},
  "geometry": {"coordinates":[2.7391519547,41.6470222473],"type":"Point"}
}