{
  "type": "Feature",
  "properties": {
    "iso:country":"ES",
    "sg:address":"Avda Garcia Barbon, 47",
    "sg:city":"Vigo",
    "sg:orig_category":"Farmacias",
    "sg:phone":"+34 986 43 02 99",
    "sg:postcode":"36201",
    "sg:province":"Pontevedra",
    "wof:name":"Fernandez Diz Olga",
    "wof:placetype":"venue"
},
  "geometry": {"coordinates":[-8.7163600922,42.2369232178],"type":"Point"}
}