{
  "type": "Feature",
  "properties": {
    "addr:full":"Barr San Lorenzo, S/n Carreras Vizcaya 48540",
    "addr:housenumber":"s / n",
    "addr:postcode":"48540",
    "addr:street":"San Lorenzo",
    "iso:country":"ES",
    "sg:address":"Barr San Lorenzo, S/n",
    "sg:city":"Carreras",
    "sg:orig_category":"Gases Industriales",
    "sg:phone":"+34 946 36 80 39",
    "sg:postcode":"48540",
    "sg:province":"Vizcaya",
    "wof:name":"Carbonorte S.l.",
    "wof:placetype":"venue"
},
  "geometry": {"coordinates":[-3.1058120728,43.3131942749],"type":"Point"}
}