{
  "type": "Feature",
  "properties": {
    "addr:full":"Calle de Comercio (del), 14 Tres Cantos Madrid 28760",
    "addr:postcode":"28760",
    "addr:street":"Calle De;Del",
    "iso:country":"ES",
    "sg:address":"Calle de Comercio (del), 14",
    "sg:city":"Tres Cantos",
    "sg:orig_category":"Fotocopias, Reprograf\u00cda",
    "sg:phone":"+34 918 04 93 61",
    "sg:postcode":"28760",
    "sg:province":"Madrid",
    "wof:name":"Corporacion De Servicios Externos S.l.",
    "wof:placetype":"venue"
},
  "geometry": {"coordinates":[-3.7088651657,40.6006965637],"type":"Point"}
}