{
  "type": "Feature",
  "properties": {
    "addr:full":"Pol Ind Magdalena, S/n Castello Plana Castell\u00f3n 12004",
    "addr:housenumber":"s",
    "addr:postcode":"12004",
    "addr:street":"/ N",
    "iso:country":"ES",
    "sg:address":"Pol Ind Magdalena, S/n",
    "sg:city":"Castello Plana",
    "sg:orig_category":"Comercio De Mobiliario De Oficina",
    "sg:phone":"+34 964 25 37 87",
    "sg:postcode":"12004",
    "sg:province":"Castell\u00f3n",
    "wof:name":"Interdes S.l.",
    "wof:placetype":"venue"
},
  "geometry": {"coordinates":[-0.0441690013,40.0043563843],"type":"Point"}
}