{
  "type": "Feature",
  "properties": {
    "iso:country":"ES",
    "sg:address":"Calle de Guadalajara, 28",
    "sg:city":"Sevilla",
    "sg:orig_category":"Frutas, Legumbres Frescas Y Tempranas (al Por Menor)",
    "sg:phone":"+34 954 69 34 27",
    "sg:postcode":"41014",
    "sg:province":"Sevilla",
    "wof:name":"Romero Ruiz Ignacio",
    "wof:placetype":"venue"
},
  "geometry": {"coordinates":[-5.9673819542,37.3238105774],"type":"Point"}
}