{
  "type": "Feature",
  "properties": {
    "addr:full":"Calle de Estacion, S/n Beniajan Murcia 30570",
    "addr:postcode":"30570",
    "addr:street":"Calle De Estacion S / N",
    "iso:country":"ES",
    "sg:address":"Calle de Estacion, S/n",
    "sg:city":"Beniajan",
    "sg:orig_category":"Arboricultura Y Producci\u00d3n De Frutas",
    "sg:phone":"+34 968 82 02 29",
    "sg:postcode":"30570",
    "sg:province":"Murcia",
    "wof:name":"Andres Lopez E Hijo S. A",
    "wof:placetype":"venue"
},
  "geometry": {"coordinates":[-1.0663211346,37.9794692993],"type":"Point"}
}