{
  "type": "Feature",
  "properties": {
    "addr:full":"Calle de Jorge Juan, 10 Aspe Alicante 03680",
    "addr:housenumber":"10",
    "addr:postcode":"03680",
    "addr:street":"Calle De Jorge Juan",
    "iso:country":"ES",
    "sg:address":"Calle de Jorge Juan, 10",
    "sg:city":"Aspe",
    "sg:orig_category":"Electricidad: Instaladores",
    "sg:phone":"+34 965 49 37 61",
    "sg:postcode":"03680",
    "sg:province":"Alicante",
    "wof:name":"Lopez Barcos Juan Antonio",
    "wof:placetype":"venue"
},
  "geometry": {"coordinates":[-0.7680702209,38.3427696228],"type":"Point"}
}