{
  "type": "Feature",
  "properties": {
    "iso:country":"ES",
    "sg:address":"Carrer de Rosa, 17",
    "sg:city":"Viladecans",
    "sg:orig_category":"Pensiones Familiares",
    "sg:phone":"+34 936 58 14 06",
    "sg:postcode":"08840",
    "sg:province":"Barcelona",
    "wof:name":"Just Do\u00f1ate Joaquin",
    "wof:placetype":"venue"
},
  "geometry": {"coordinates":[2.0041460991,41.3201065063],"type":"Point"}
}