{
  "type": "Feature",
  "properties": {
    "addr:full":"Foro, S/n Foro La Coru\u00f1a 15807",
    "addr:housenumber":"s / n",
    "addr:postcode":"15807",
    "addr:street":"Foro;Foro La Corun\u0303A",
    "iso:country":"ES",
    "sg:address":"Foro, S/n",
    "sg:city":"Foro",
    "sg:orig_category":"Alimentaci\u00d3n General (al Por Mayor)",
    "sg:phone":"+34 981 77 81 40",
    "sg:postcode":"15807",
    "sg:province":"La Coru\u00f1a",
    "wof:name":"Fontambre S.l.",
    "wof:placetype":"venue"
},
  "geometry": {"coordinates":[-8.1210775375,43.0706291199],"type":"Point"}
}