{
  "type": "Feature",
  "properties": {
    "iso:country":"ES",
    "sg:address":"Calle de Collado De Tirobarra, 4",
    "sg:city":"Madrid",
    "sg:orig_category":"Enfermeras: Consultas, Atenci\u00d3n A Domicilio",
    "sg:phone":"+34 917 34 83 81",
    "sg:postcode":"28034",
    "sg:province":"Madrid",
    "wof:name":"Fundacion Nuestra Se\u00d1ora Del Camino",
    "wof:placetype":"venue"
},
  "geometry": {"coordinates":[-3.7155210972,40.4951324463],"type":"Point"}
}