{
  "type": "Feature",
  "properties": {
    "addr:full":"Calle de Vista Alegre, 6 San Vicente De Barakaldo Vizcaya 48903",
    "addr:housenumber":"6",
    "addr:postcode":"48903",
    "addr:street":"Calle De Vista Alegre",
    "iso:country":"ES",
    "sg:address":"Calle de Vista Alegre, 6",
    "sg:city":"San Vicente De Barakaldo",
    "sg:orig_category":"Quincaller\u00cda (al Por Menor)",
    "sg:phone":"+34 944 99 56 17",
    "sg:postcode":"48903",
    "sg:province":"Vizcaya",
    "wof:name":"Gonzalez Gonzalez Julio",
    "wof:placetype":"venue"
},
  "geometry": {"coordinates":[-2.9834029675,43.2800292969],"type":"Point"}
}