{
  "type": "Feature",
  "properties": {
    "addr:full":"Carr S Vicenc, 48 Igualada Barcelona 08700",
    "addr:housenumber":"48",
    "addr:postcode":"08700",
    "addr:street":"Carr S Vicenc",
    "iso:country":"ES",
    "sg:address":"Carr S Vicenc, 48",
    "sg:city":"Igualada",
    "sg:orig_category":"M\u00c9dicos: An\u00c1lisis Cl\u00cdnicos",
    "sg:phone":"+34 938 05 50 27",
    "sg:postcode":"08700",
    "sg:province":"Barcelona",
    "wof:name":"Consorci Del Laboratori Intercomarcal De L'alt Penedes L'anoia I El",
    "wof:placetype":"venue"
},
  "geometry": {"coordinates":[1.6231199503,41.5799293518],"type":"Point"}
}