{
  "type": "Feature",
  "properties": {
    "iso:country":"ES",
    "sg:address":"Pla\u00c7 Josep Irla I Bosch, 21",
    "sg:city":"Girona",
    "sg:orig_category":"Escayola Y Productos De Escayola (fabricaci\u00d3n, Al Por Mayor)",
    "sg:phone":"+34 972 21 83 51",
    "sg:postcode":"17003",
    "sg:province":"Girona",
    "wof:name":"Busquets Serra Luis",
    "wof:placetype":"venue"
},
  "geometry": {"coordinates":[2.8202579021,41.9693756104],"type":"Point"}
}