{
  "type": "Feature",
  "properties": {
    "iso:country":"ES",
    "sg:address":"Pase Damas (las), 11",
    "sg:city":"Zaragoza",
    "sg:orig_category":"Psic\u00d3logos",
    "sg:phone":"+34 976 23 31 72",
    "sg:postcode":"50008",
    "sg:province":"Zaragoza",
    "wof:name":"Sancho Garcia Fernando",
    "wof:placetype":"venue"
},
  "geometry": {"coordinates":[-0.8842329979,41.6453971863],"type":"Point"}
}