{
  "type": "Feature",
  "properties": {
    "addr:full":"Calle de Esperanto, 4 Benidorm Alicante 03500",
    "addr:housenumber":"4",
    "addr:postcode":"03500",
    "addr:street":"Calle De Esperanto",
    "iso:country":"ES",
    "sg:address":"Calle de Esperanto, 4",
    "sg:city":"Benidorm",
    "sg:orig_category":"Bares, Piano",
    "sg:phone":"+34 966 80 49 20",
    "sg:postcode":"03500",
    "sg:province":"Alicante",
    "wof:name":"Guinea Lopez Miguel",
    "wof:placetype":"venue"
},
  "geometry": {"coordinates":[-0.1251198947,38.5378227234],"type":"Point"}
}