{
  "type": "Feature",
  "properties": {
    "iso:country":"ES",
    "sg:address":"Pol Ind Ca\u00f1ada De La Fuente, S/n",
    "sg:city":"Martos",
    "sg:orig_category":"Servicios Diversos",
    "sg:phone":"+34 953 56 91 00",
    "sg:postcode":"23600",
    "sg:province":"Ja\u00e9n",
    "wof:name":"Valeo Iluminacion S.a.",
    "wof:placetype":"venue"
},
  "geometry": {"coordinates":[-3.9491291046,37.601436615],"type":"Point"}
}