{
  "type": "Feature",
  "properties": {
    "iso:country":"ES",
    "sg:address":"Avda Literato Azorin, 42",
    "sg:city":"Yecla",
    "sg:orig_category":"Inform\u00c1tica, Ofim\u00c1tica (estudios, Asesor\u00cda, Ingenier\u00cda, Formaci\u00d3n)",
    "sg:phone":"+34 968 79 64 30",
    "sg:postcode":"30510",
    "sg:province":"Murcia",
    "wof:name":"Ofymat Informatica S.l.",
    "wof:placetype":"venue"
},
  "geometry": {"coordinates":[-1.1075639725,38.6132965088],"type":"Point"}
}