{
  "type": "Feature",
  "properties": {
    "iso:country":"ES",
    "sg:address":"Carrer de L'escorial, 36",
    "sg:city":"Barcelona",
    "sg:orig_category":"Molduras, Junquillos, Listones Y Molduras Perforadas",
    "sg:phone":"+34 932 85 00 96",
    "sg:postcode":"08024",
    "sg:province":"Barcelona",
    "wof:name":"Sentis Garcia Carlos",
    "wof:placetype":"venue"
},
  "geometry": {"coordinates":[2.161608696,41.4070320129],"type":"Point"}
}