{
  "type": "Feature",
  "properties": {
    "iso:country":"ES",
    "sg:address":"Carr Vapor, 22",
    "sg:city":"Vilanova I La Geltru",
    "sg:orig_category":"Asociaciones Y Clubs Deportivos",
    "sg:phone":"+34 938 93 28 53",
    "sg:postcode":"08800",
    "sg:province":"Barcelona",
    "wof:name":"Centre Gimnastic Vilanova S. A.",
    "wof:placetype":"venue"
},
  "geometry": {"coordinates":[1.7238579988,41.2238502502],"type":"Point"}
}