{
  "type": "Feature",
  "properties": {
    "addr:full":"Calle de Mestre Giner, 5 Alzira Valencia 46600",
    "addr:housenumber":"5",
    "addr:postcode":"46600",
    "addr:street":"Calle De Mestre Giner",
    "iso:country":"ES",
    "sg:address":"Calle de Mestre Giner, 5",
    "sg:city":"Alzira",
    "sg:orig_category":"Peluquer\u00cdas, Peluquer\u00cda Mixta",
    "sg:phone":"+34 962 41 11 31",
    "sg:postcode":"46600",
    "sg:province":"Valencia",
    "wof:name":"Perruqueria Nuria Perez S.l.",
    "wof:placetype":"venue"
},
  "geometry": {"coordinates":[-0.4362519979,39.1512947083],"type":"Point"}
}