{
  "type": "Feature",
  "properties": {
    "addr:full":"Calle de Palas, 1 Cartagena Murcia 30202",
    "addr:postcode":"30202",
    "addr:street":"Calle De Palas",
    "iso:country":"ES",
    "sg:address":"Calle de Palas, 1",
    "sg:city":"Cartagena",
    "sg:orig_category":"Carnicer\u00cdas, Carnicer\u00cdas",
    "sg:phone":"+34 968 50 23 70",
    "sg:postcode":"30202",
    "sg:province":"Murcia",
    "wof:name":"Parron Sanchez Pablo",
    "wof:placetype":"venue"
},
  "geometry": {"coordinates":[-0.9837989807,37.601360321],"type":"Point"}
}