{
  "type": "Feature",
  "properties": {
    "iso:country":"ES",
    "sg:address":"Calle de San Juan De Dios, 6",
    "sg:city":"Caceres",
    "sg:orig_category":"Relojer\u00cda Industrial",
    "sg:phone":"+34 927 21 36 83",
    "sg:postcode":"10001",
    "sg:province":"C\u00e1ceres",
    "sg:website":"www.paginasamarillas.es",
    "wof:name":"Sistemas Tecnicos De Cronometria S.l.",
    "wof:placetype":"venue"
},
  "geometry": {"coordinates":[-6.3802189827,39.4721908569],"type":"Point"}
}