{
  "type": "Feature",
  "properties": {
    "iso:country":"ES",
    "sg:address":"Carrer de Dos De Maig, 11",
    "sg:city":"Vilafranca Penedes",
    "sg:orig_category":"Institutos De Belleza",
    "sg:phone":"+34 938 92 02 89",
    "sg:postcode":"08720",
    "sg:province":"Barcelona",
    "wof:name":"Galimany Fabrega Lidia",
    "wof:placetype":"venue"
},
  "geometry": {"coordinates":[1.7011350393,41.3472595215],"type":"Point"}
}