{
  "type": "Feature",
  "properties": {
    "addr:full":"Carrer de Joan Maragall, 3 Martorell Barcelona 08760",
    "addr:housenumber":"3",
    "addr:postcode":"08760",
    "addr:street":"Carrer De Joan Maragall",
    "iso:country":"ES",
    "sg:address":"Carrer de Joan Maragall, 3",
    "sg:city":"Martorell",
    "sg:orig_category":"\u00d3ptica: Instrumentos (fabricaci\u00d3n)",
    "sg:phone":"+34 937 73 52 85",
    "sg:postcode":"08760",
    "sg:province":"Barcelona",
    "wof:name":"Guarino Y Molina Opticas S.l.",
    "wof:placetype":"venue"
},
  "geometry": {"coordinates":[1.9151710272,41.4777412415],"type":"Point"}
}