{
  "type": "Feature",
  "properties": {
    "addr:full":"Calle de Alcalde Francisco Orejas, 8 Aviles Asturias 33401",
    "addr:housenumber":"8",
    "addr:postcode":"33401",
    "addr:street":"Calle De Alcalde Francisco Orejas",
    "iso:country":"ES",
    "sg:address":"Calle de Alcalde Francisco Orejas, 8",
    "sg:city":"Aviles",
    "sg:orig_category":"Asesor\u00cda De Formaci\u00d3n Y Gesti\u00d3n De Personal",
    "sg:phone":"+34 985 52 27 04",
    "sg:postcode":"33401",
    "sg:province":"Asturias",
    "sg:website":"www.arrakis.es/~azcarate",
    "wof:name":"Azcarate Fraile Pablo",
    "wof:placetype":"venue"
},
  "geometry": {"coordinates":[-5.9275689125,43.5562934875],"type":"Point"}
}