{
  "type": "Feature",
  "properties": {
    "addr:full":"Antonio Borrero Chamaco, 6 Huelva Huelva 21001",
    "addr:housenumber":"6",
    "addr:postcode":"21001",
    "addr:street":"Antonio Borrero Chamaco",
    "iso:country":"ES",
    "sg:address":"Antonio Borrero Chamaco, 6",
    "sg:city":"Huelva",
    "sg:orig_category":"Abogados",
    "sg:phone":"+34 959 24 13 07",
    "sg:postcode":"21001",
    "sg:province":"Huelva",
    "wof:name":"Bufete De Letrados Y Asesores C.b.",
    "wof:placetype":"venue"
},
  "geometry": {"coordinates":[-6.9559731483,37.2520980835],"type":"Point"}
}