{
  "type": "Feature",
  "properties": {
    "iso:country":"ES",
    "sg:address":"Carrer de Lepant, 264",
    "sg:city":"Barcelona",
    "sg:orig_category":"Concepci\u00d3n Y Realizaci\u00d3n De Maquetas Profesionales Y Prototipos",
    "sg:phone":"+34 932 31 12 64",
    "sg:postcode":"08013",
    "sg:province":"Barcelona",
    "wof:name":"Flos Rucabado Elisenda",
    "wof:placetype":"venue"
},
  "geometry": {"coordinates":[2.177601099,41.4039764404],"type":"Point"}
}