{
  "type": "Feature",
  "properties": {
    "iso:country":"ES",
    "sg:address":"Carrer de Santa Rosalia, 33",
    "sg:city":"Barcelona",
    "sg:orig_category":"Molduras, Junquillos, Listones Y Molduras Perforadas",
    "sg:phone":"+34 934 29 61 59",
    "sg:postcode":"08035",
    "sg:province":"Barcelona",
    "wof:name":"Martinez Garcia Noemi",
    "wof:placetype":"venue"
},
  "geometry": {"coordinates":[2.1456921101,41.4215774536],"type":"Point"}
}