{
  "type": "Feature",
  "properties": {
    "iso:country":"ES",
    "sg:address":"Calle de Castillo, 12",
    "sg:city":"Cartaya",
    "sg:orig_category":"Reposter\u00cdas",
    "sg:phone":"+34 959 39 01 59",
    "sg:postcode":"21450",
    "sg:province":"Huelva",
    "wof:name":"Panaderia Hermanos Zambrano C.b",
    "wof:placetype":"venue"
},
  "geometry": {"coordinates":[-7.1561818123,37.2836608887],"type":"Point"}
}