{
  "type": "Feature",
  "properties": {
    "addr:full":"Trva Marina (da), 29 Viveiro Lugo 27850",
    "addr:postcode":"27850",
    "addr:street":"Trva Marina Da",
    "iso:country":"ES",
    "sg:address":"Trva Marina (da), 29",
    "sg:city":"Viveiro",
    "sg:classifiers":[
        {
            "category":"Autos & Motor Vehicles",
            "subcategory":"Automobile Sales",
            "type":"Retail Goods"
        }
    ],
    "sg:phone":"+34 982 56 03 34",
    "sg:postcode":"27850",
    "sg:province":"Lugo",
    "wof:name":"Mundial Viveiro-foz S.l.",
    "wof:placetype":"venue"
},
  "geometry": {"coordinates":[-7.5967850685,43.6610298157],"type":"Point"}
}