{
  "type": "Feature",
  "properties": {
    "addr:full":"Carrer de Cerdanya, 42 S. Boi Llobregat Barcelona 08830",
    "addr:housenumber":"42",
    "addr:postcode":"08830",
    "addr:street":"Carrer De Cerdanya",
    "iso:country":"ES",
    "sg:address":"Carrer de Cerdanya, 42",
    "sg:city":"S. Boi Llobregat",
    "sg:orig_category":"Tintes (fabricaci\u00d3n, Al Por Mayor)",
    "sg:phone":"+34 936 40 04 71",
    "sg:postcode":"08830",
    "sg:province":"Barcelona",
    "wof:name":"Tintoreria Casals S.l.",
    "wof:placetype":"venue"
},
  "geometry": {"coordinates":[2.0414938927,41.3420677185],"type":"Point"}
}