{
  "type": "Feature",
  "properties": {
    "iso:country":"ES",
    "sg:address":"Calle de Empedrada, 47",
    "sg:city":"Montalban De Cordoba",
    "sg:orig_category":"Supermercados Y Hipermercados",
    "sg:phone":"+34 957 31 14 73",
    "sg:postcode":"14548",
    "sg:province":"C\u00f3rdoba",
    "wof:name":"Almacenes Yebenes S. A.",
    "wof:placetype":"venue"
},
  "geometry": {"coordinates":[-4.7484850883,37.5826721191],"type":"Point"}
}