{
  "type": "Feature",
  "properties": {
    "iso:country":"ES",
    "sg:address":"Calle de Galicia, 24",
    "sg:city":"Palmas De Gran Canaria",
    "sg:orig_category":"Aparcamientos (infraestructuras, Accesorios)",
    "sg:phone":"+34 928 24 29 10",
    "sg:postcode":"35006",
    "sg:province":"Las Palmas",
    "wof:name":"Aparcamiento Mercado Central S.l",
    "wof:placetype":"venue"
},
  "geometry": {"coordinates":[-15.4331417084,28.1335258484],"type":"Point"}
}