{
  "type": "Feature",
  "properties": {
    "iso:country":"ES",
    "sg:address":"C/ Rambla, 30",
    "sg:city":"Banyoles",
    "sg:orig_category":"Fisioterapia",
    "sg:phone":"+34 972 58 07 28",
    "sg:postcode":"17820",
    "sg:province":"Girona",
    "wof:name":"Global Fisioterapeutes S.c.",
    "wof:placetype":"venue"
},
  "geometry": {"coordinates":[2.7622869015,42.1185913086],"type":"Point"}
}