{
  "type": "Feature",
  "properties": {
    "addr:full":"Paseo Maritimo, 12 O Temple La Coru\u00f1a 15679",
    "addr:housenumber":"12 o",
    "addr:postcode":"15679",
    "addr:street":"Paseo Maritimo;La Corun\u0303A",
    "iso:country":"ES",
    "sg:address":"Paseo Maritimo, 12",
    "sg:city":"O Temple",
    "sg:orig_category":"Confecci\u00d3n De Trajes Para Se\u00d1oras",
    "sg:phone":"+34 981 66 73 33",
    "sg:postcode":"15679",
    "sg:province":"La Coru\u00f1a",
    "wof:name":"Madovar S.l.",
    "wof:placetype":"venue"
},
  "geometry": {"coordinates":[-8.3584518433,43.3199501038],"type":"Point"}
}