{
  "type": "Feature",
  "properties": {
    "addr:full":"Carrer de Ferlandina, 32 Barcelona Barcelona 08001",
    "addr:housenumber":"32",
    "addr:postcode":"08001",
    "addr:street":"Carrer De Ferlandina",
    "iso:country":"ES",
    "sg:address":"Carrer de Ferlandina, 32",
    "sg:city":"Barcelona",
    "sg:orig_category":"Peluquer\u00cdas, Peluquer\u00cda Mixta",
    "sg:phone":"+34 933 18 75 87",
    "sg:postcode":"08001",
    "sg:province":"Barcelona",
    "wof:name":"Vila Ribera Laura",
    "wof:placetype":"venue"
},
  "geometry": {"coordinates":[2.1648299694,41.3817939758],"type":"Point"}
}