{
  "type": "Feature",
  "properties": {
    "addr:full":"Carrer de Pere Puig, 91 Martorell Barcelona 08760",
    "addr:housenumber":"91",
    "addr:postcode":"08760",
    "addr:street":"Carrer De Pere Puig",
    "iso:country":"ES",
    "sg:address":"Carrer de Pere Puig, 91",
    "sg:city":"Martorell",
    "sg:orig_category":"Asesor\u00cda Sobre Comunicaci\u00d3n De Empresas",
    "sg:phone":"+34 937 75 22 52",
    "sg:postcode":"08760",
    "sg:province":"Barcelona",
    "wof:name":"Corral Baron Sergi",
    "wof:placetype":"venue"
},
  "geometry": {"coordinates":[1.9364290237,41.4743156433],"type":"Point"}
}