{
  "type": "Feature",
  "properties": {
    "iso:country":"ES",
    "sg:address":"Calle de Santiago (de), 18",
    "sg:city":"Aranjuez",
    "sg:classifiers":[
        {
            "category":"Casinos & Gambling",
            "type":"Entertainment"
        }
    ],
    "sg:phone":"+34 918 92 17 46",
    "sg:postcode":"28300",
    "sg:province":"Madrid",
    "sg:tags":[
        "locale",
        "de",
        "juego"
    ],
    "sg:website":"www.migabinete.teka",
    "wof:name":"Mi Gabinete C.b.",
    "wof:placetype":"venue"
},
  "geometry": {"coordinates":[-3.5955181122,40.0307197571],"type":"Point"}
}