{
  "type": "Feature",
  "properties": {
    "iso:country":"ES",
    "sg:address":"Carrer de Doctor Marti I Julia, 180",
    "sg:city":"Hospitalet Llobregat",
    "sg:orig_category":"Molduras, Junquillos, Listones Y Molduras Perforadas",
    "sg:phone":"+34 934 21 70 43",
    "sg:postcode":"08903",
    "sg:province":"Barcelona",
    "wof:name":"Gonzalez Tenas Hector",
    "wof:placetype":"venue"
},
  "geometry": {"coordinates":[2.1264529228,41.3698348999],"type":"Point"}
}