{
  "type": "Feature",
  "properties": {
    "addr:full":"Erdikalea, 5 Zestoa Guip\u00f9zcoa 20740",
    "addr:housenumber":"5",
    "addr:postcode":"20740",
    "addr:street":"Erdikalea;Guipu\u0300Zcoa",
    "iso:country":"ES",
    "sg:address":"Erdikalea, 5",
    "sg:city":"Zestoa",
    "sg:orig_category":"Molduras, Junquillos, Listones Y Molduras Perforadas",
    "sg:phone":"+34 943 14 73 22",
    "sg:postcode":"20740",
    "sg:province":"Guip\u00f9zcoa",
    "wof:name":"Ruben Olaizola Odriozola Y Otros C.b.",
    "wof:placetype":"venue"
},
  "geometry": {"coordinates":[-2.2584300041,43.2397994995],"type":"Point"}
}