{
  "type": "Feature",
  "properties": {
    "iso:country":"ES",
    "sg:address":"Carretera Cordoba-valencia, S/n",
    "sg:city":"Villanueva Arzobispo",
    "sg:orig_category":"Carb\u00d3n, Carb\u00d3n De Madera (al Por Mayor)",
    "sg:phone":"+34 953 45 12 47",
    "sg:postcode":"23330",
    "sg:province":"Ja\u00e9n",
    "wof:name":"Fuentes Torres Francisco",
    "wof:placetype":"venue"
},
  "geometry": {"coordinates":[-3.005177021,38.172542572],"type":"Point"}
}