{
  "type": "Feature",
  "properties": {
    "addr:full":"Carrer de Sant Antoni, 50 Calella Barcelona 08370",
    "addr:housenumber":"50",
    "addr:postcode":"08370",
    "addr:street":"Carrer De Sant Antoni",
    "iso:country":"ES",
    "sg:address":"Carrer de Sant Antoni, 50",
    "sg:city":"Calella",
    "sg:orig_category":"Negocio De Materiales De Construcci\u00d3n",
    "sg:phone":"+34 937 66 16 83",
    "sg:postcode":"08370",
    "sg:province":"Barcelona",
    "wof:name":"Ceramicas Faro S.l.",
    "wof:placetype":"venue"
},
  "geometry": {"coordinates":[2.662530899,41.6162796021],"type":"Point"}
}