{
  "type": "Feature",
  "properties": {
    "addr:full":"Via Portugal, 25 Manacor Islas Baleares 07500",
    "addr:housenumber":"25",
    "addr:postcode":"07500",
    "addr:street":"Via Portugal",
    "iso:country":"ES",
    "sg:address":"Via Portugal, 25",
    "sg:city":"Manacor",
    "sg:orig_category":"Producci\u00d3n, Comercio De Cereales",
    "sg:phone":"+34 971 55 05 19",
    "sg:postcode":"07500",
    "sg:province":"Islas Baleares",
    "wof:name":"Ca'n Batliu S. A.",
    "wof:placetype":"venue"
},
  "geometry": {"coordinates":[3.2154960632,39.5669403076],"type":"Point"}
}