{
  "type": "Feature",
  "properties": {
    "iso:country":"ES",
    "sg:address":"Carrer de Riu Ter, 28",
    "sg:city":"Deltebre",
    "sg:orig_category":"Empresas De Carpinter\u00cda De Madera",
    "sg:phone":"+34 977 48 92 36",
    "sg:postcode":"43580",
    "sg:province":"Tarragona",
    "wof:name":"Roman Arques Bertomeu",
    "wof:placetype":"venue"
},
  "geometry": {"coordinates":[0.6972249746,40.7226982117],"type":"Point"}
}