{
  "type": "Feature",
  "properties": {
    "iso:country":"ES",
    "sg:address":"Calle de Ciudad Deportiva Santa Maria, 8",
    "sg:city":"Alca\u00f1iz",
    "sg:orig_category":"Carnicer\u00cdas, Carnicer\u00cdas",
    "sg:phone":"+34 978 83 31 33",
    "sg:postcode":"44600",
    "sg:province":"Teruel",
    "wof:name":"Lope Sanguesa Juan Ignacio",
    "wof:placetype":"venue"
},
  "geometry": {"coordinates":[-0.1277022958,41.0501747131],"type":"Point"}
}