{
  "type": "Feature",
  "properties": {
    "addr:full":"Calle de Pedregales, 14 Logro\u00f1o La Rioja 26006",
    "addr:housenumber":"14",
    "addr:postcode":"26006",
    "addr:street":"Calle De Pedregales;Rioja",
    "iso:country":"ES",
    "sg:address":"Calle de Pedregales, 14",
    "sg:city":"Logro\u00f1o",
    "sg:orig_category":"Entrega Y Recogida (servicios)",
    "sg:phone":"+34 941 50 03 90",
    "sg:postcode":"26006",
    "sg:province":"La Rioja",
    "wof:name":"Distribuciones Pedregales 2004 S.l.",
    "wof:placetype":"venue"
},
  "geometry": {"coordinates":[-2.4352440834,42.4536857605],"type":"Point"}
}