{
  "type": "Feature",
  "properties": {
    "iso:country":"ES",
    "sg:address":"Calle de Prevision Social, 1",
    "sg:city":"Zaragoza",
    "sg:orig_category":"Comercio De Piezas De Recambio Y De Accesorios De Veh\u00cdculos, Veh\u00cdculos Industriales",
    "sg:phone":"+34 976 41 96 80",
    "sg:postcode":"50008",
    "sg:province":"Zaragoza",
    "wof:name":"Comercial Lapuyade S.l.",
    "wof:placetype":"venue"
},
  "geometry": {"coordinates":[-0.8733549714,41.643913269],"type":"Point"}
}