{
  "type": "Feature",
  "properties": {
    "addr:full":"Calle de Recoletas, 22 Tafalla Navarra 31300",
    "addr:housenumber":"22",
    "addr:postcode":"31300",
    "addr:street":"Calle De Recoletas",
    "iso:country":"ES",
    "sg:address":"Calle de Recoletas, 22",
    "sg:city":"Tafalla",
    "sg:orig_category":"Organizaciones Profesionales",
    "sg:phone":"+34 948 75 50 91",
    "sg:postcode":"31300",
    "sg:province":"Navarra",
    "wof:name":"Ainzua De Go\u00f1i Mariasun",
    "wof:placetype":"venue"
},
  "geometry": {"coordinates":[-1.6757494211,42.5260429382],"type":"Point"}
}