{
  "type": "Feature",
  "properties": {
    "addr:full":"Avda Lalin-monforte, Km. 0170,0 Rodeiro Pontevedra 36530",
    "addr:postcode":"36530",
    "addr:street":"Avda Lalin-Monforte Km. 0170,0",
    "iso:country":"ES",
    "sg:address":"Avda Lalin-monforte, Km. 0170,0",
    "sg:city":"Rodeiro",
    "sg:orig_category":"Distribuci\u00d3n De Petr\u00d3leo Y Derivados",
    "sg:phone":"+34 986 79 02 89",
    "sg:postcode":"36530",
    "sg:province":"Pontevedra",
    "wof:name":"Rodoil S.l.",
    "wof:placetype":"venue"
},
  "geometry": {"coordinates":[-7.9422287941,42.6469116211],"type":"Point"}
}