{
  "type": "Feature",
  "properties": {
    "addr:full":"Calle de Iriarte, 23 Madrid Madrid 28028",
    "addr:housenumber":"23",
    "addr:postcode":"madrid;28028",
    "addr:street":"Calle De Iriarte",
    "iso:country":"ES",
    "sg:address":"Calle de Iriarte, 23",
    "sg:city":"Madrid",
    "sg:orig_category":"Importaci\u00d3n",
    "sg:phone":"+34 913 61 53 97",
    "sg:postcode":"28028",
    "sg:province":"Madrid",
    "wof:name":"Oilgas Consulting Internacional S.l.",
    "wof:placetype":"venue"
},
  "geometry": {"coordinates":[-3.6720499992,40.4372215271],"type":"Point"}
}