{
  "type": "Feature",
  "properties": {
    "addr:full":"Carrer de Estrella, 167 Sabadell Barcelona 08201",
    "addr:housenumber":"167",
    "addr:postcode":"08201",
    "addr:street":"Carrer De Estrella",
    "iso:country":"ES",
    "sg:address":"Carrer de Estrella, 167",
    "sg:city":"Sabadell",
    "sg:orig_category":"Fisioterapia",
    "sg:phone":"+34 937 45 95 87",
    "sg:postcode":"08201",
    "sg:province":"Barcelona",
    "wof:name":"Rodriguez Creus Teresa",
    "wof:placetype":"venue"
},
  "geometry": {"coordinates":[2.1018519402,41.5491447449],"type":"Point"}
}