{
  "type": "Feature",
  "properties": {
    "iso:country":"ES",
    "sg:address":"Calle de Pablo Picasso, 39",
    "sg:city":"Laguna Duero",
    "sg:orig_category":"Herboristas (al Por Menor)",
    "sg:phone":"+34 983 54 37 33",
    "sg:postcode":"47140",
    "sg:province":"Valladolid",
    "wof:name":"Pablo Heras Evilasio De",
    "wof:placetype":"venue"
},
  "geometry": {"coordinates":[-4.7225441933,41.5806503296],"type":"Point"}
}