{
  "type": "Feature",
  "properties": {
    "iso:country":"ES",
    "sg:address":"Calle de Artatza, 10",
    "sg:city":"Leioa",
    "sg:orig_category":"Librer\u00cdas",
    "sg:phone":"+34 944 91 23 20",
    "sg:postcode":"48940",
    "sg:province":"Vizcaya",
    "wof:name":"Mercedes Eguren Landeta",
    "wof:placetype":"venue"
},
  "geometry": {"coordinates":[-2.9987297058,43.3329963684],"type":"Point"}
}