{
  "type": "Feature",
  "properties": {
    "iso:country":"ES",
    "sg:address":"Calle de General Diaz Porlier, 37",
    "sg:city":"Madrid",
    "sg:orig_category":"Asociaciones Humanitarias, De Cooperaci\u00d3n, De Acci\u00d3n Social",
    "sg:phone":"+34 913 09 34 54",
    "sg:postcode":"28001",
    "sg:province":"Madrid",
    "wof:name":"Asociacion Contra La Tortura",
    "wof:placetype":"venue"
},
  "geometry": {"coordinates":[-3.6769948006,40.4281730652],"type":"Point"}
}