{
  "type": "Feature",
  "properties": {
    "iso:country":"ES",
    "sg:address":"Carrer de Bonestar, 31",
    "sg:city":"Cornella Llobregat",
    "sg:orig_category":"Ropa Para Se\u00d1oras Y Caballeros (al Por Menor)",
    "sg:phone":"+34 933 75 41 70",
    "sg:postcode":"08940",
    "sg:province":"Barcelona",
    "wof:name":"Acondicionamiento Textil S.l.",
    "wof:placetype":"venue"
},
  "geometry": {"coordinates":[2.0768847466,41.3585166931],"type":"Point"}
}