{
  "type": "Feature",
  "properties": {
    "iso:country":"ES",
    "sg:address":"Avda Club Deportivo, 64",
    "sg:city":"Logro\u00f1o",
    "sg:orig_category":"Fabricaci\u00d3n De Material Y Sistemas De Se\u00d1alizaci\u00d3n De Carreteras, Urbanos Y De Obras",
    "sg:phone":"+34 941 20 38 88",
    "sg:postcode":"26007",
    "sg:province":"La Rioja",
    "wof:name":"Andres Ortuo Cruz",
    "wof:placetype":"venue"
},
  "geometry": {"coordinates":[-2.4595711231,42.4577941895],"type":"Point"}
}