{
  "type": "Feature",
  "properties": {
    "addr:full":"Calle de Gregorio Solabarrieta, 5 Miranda Ebro Burgos 09200",
    "addr:housenumber":"5",
    "addr:postcode":"09200",
    "addr:street":"Calle De Gregorio Solabarrieta",
    "iso:country":"ES",
    "sg:address":"Calle de Gregorio Solabarrieta, 5",
    "sg:city":"Miranda Ebro",
    "sg:orig_category":"Caf\u00c9s, Bares, Cervecer\u00cdas",
    "sg:phone":"+34 947 32 35 03",
    "sg:postcode":"09200",
    "sg:province":"Burgos",
    "wof:name":"Vadillo Martinez De Salinas Enrique",
    "wof:placetype":"venue"
},
  "geometry": {"coordinates":[-2.9493086338,42.6851844788],"type":"Point"}
}