{
  "type": "Feature",
  "properties": {
    "iso:country":"ES",
    "sg:address":"Calle de Coso Bajo, 15",
    "sg:city":"Huesca",
    "sg:orig_category":"Asociaciones Y Clubs Deportivos",
    "sg:phone":"+34 974 23 06 63",
    "sg:postcode":"22001",
    "sg:province":"Huesca",
    "wof:name":"Pe\u00f1a Deportiva Recreativa Oscense Del Real Madrid C.f",
    "wof:placetype":"venue"
},
  "geometry": {"coordinates":[-0.406860292,42.1372909546],"type":"Point"}
}