{
  "type": "Feature",
  "properties": {
    "addr:full":"Martinet, 11 S. Antonio Benageber Valencia 46184",
    "addr:housenumber":"11",
    "addr:postcode":"46184",
    "addr:street":"Martinet;S. Antonio Benageber",
    "iso:country":"ES",
    "sg:address":"Martinet, 11",
    "sg:city":"S. Antonio Benageber",
    "sg:orig_category":"Agencias Y Agentes Comerciales, Representantes",
    "sg:phone":"+34 961 35 10 88",
    "sg:postcode":"46184",
    "sg:province":"Valencia",
    "wof:name":"Andres Y Escribano C.b.",
    "wof:placetype":"venue"
},
  "geometry": {"coordinates":[-0.4883030057,39.55103302],"type":"Point"}
}