{
  "type": "Feature",
  "properties": {
    "iso:country":"ES",
    "sg:address":"Calle-f P I Valdeferrin, 96",
    "sg:city":"Ejea Caballeros",
    "sg:orig_category":"Electricidad: Equipos Industriales, Componentes (fabricaci\u00d3n)",
    "sg:phone":"+34 976 66 02 01",
    "sg:postcode":"50600",
    "sg:province":"Zaragoza",
    "wof:name":"Electroejea S. Coop En Constitucion",
    "wof:placetype":"venue"
},
  "geometry": {"coordinates":[-1.1382750273,42.1269798279],"type":"Point"}
}