{
  "type": "Feature",
  "properties": {
    "iso:country":"ES",
    "sg:address":"Calle de Luis Chamizo, 109",
    "sg:city":"Guare\u00f1a",
    "sg:orig_category":"Droguer\u00cdas (al Por Menor)",
    "sg:phone":"+34 924 35 14 31",
    "sg:postcode":"06470",
    "sg:province":"Badajoz",
    "wof:name":"Carmona Bote S.l.",
    "wof:placetype":"venue"
},
  "geometry": {"coordinates":[-6.0947141647,38.8574905396],"type":"Point"}
}