{
  "type": "Feature",
  "properties": {
    "iso:country":"ES",
    "sg:address":"Calle de Capataz Santiago, 76",
    "sg:city":"Montealegre Castillo",
    "sg:orig_category":"Negocio De Materiales De Construcci\u00d3n",
    "sg:phone":"+34 967 33 60 67",
    "sg:postcode":"02650",
    "sg:province":"Albacete",
    "wof:name":"Martinez Marin Diego",
    "wof:placetype":"venue"
},
  "geometry": {"coordinates":[-1.3281860352,38.7889289856],"type":"Point"}
}