{
  "type": "Feature",
  "properties": {
    "addr:full":"Avda Iberoamerica, 27 Alcala Real Ja\u00e9n 23680",
    "addr:housenumber":"27",
    "addr:postcode":"23680",
    "addr:street":"Avda Iberoamerica;Jae\u0301N",
    "iso:country":"ES",
    "sg:address":"Avda Iberoamerica, 27",
    "sg:city":"Alcala Real",
    "sg:orig_category":"Electricidad: Instaladores",
    "sg:phone":"+34 953 58 53 80",
    "sg:postcode":"23680",
    "sg:province":"Ja\u00e9n",
    "wof:name":"Serrano Serrano Blanca Maria",
    "wof:placetype":"venue"
},
  "geometry": {"coordinates":[-3.9257590771,37.455368042],"type":"Point"}
}