{
  "type": "Feature",
  "properties": {
    "addr:full":"Ctra Alcazares, 101 Torre-pacheco Murcia 30700",
    "addr:housenumber":"101",
    "addr:postcode":"30700",
    "addr:street":"Ctra Alcazares",
    "iso:country":"ES",
    "sg:address":"Ctra Alcazares, 101",
    "sg:city":"Torre-pacheco",
    "sg:orig_category":"Ingeniero",
    "sg:phone":"+34 968 33 63 50",
    "sg:postcode":"30700",
    "sg:province":"Murcia",
    "wof:name":"Abacotech S.l.",
    "wof:placetype":"venue"
},
  "geometry": {"coordinates":[-0.94539,37.73996],"type":"Point"}
}