{
  "type": "Feature",
  "properties": {
    "iso:country":"ES",
    "sg:address":"Calle de Pirineos, 55",
    "sg:city":"Madrid",
    "sg:orig_category":"Ense\u00d1anza, Formaci\u00d3n Profesional: Aprendizaje",
    "sg:phone":"+34 915 43 57 01",
    "sg:postcode":"28040",
    "sg:province":"Madrid",
    "sg:website":"www.ceu.es",
    "wof:name":"Fundacion Universitaria San Pablo",
    "wof:placetype":"venue"
},
  "geometry": {"coordinates":[-3.7182428837,40.4537239075],"type":"Point"}
}