{
  "type": "Feature",
  "properties": {
    "iso:country":"ES",
    "sg:address":"Pla\u00c7 Cardenal Sanz I Fores, 6",
    "sg:city":"Gandia",
    "sg:orig_category":"Pescader\u00cdas (al Por Menor)",
    "sg:phone":"+34 962 86 89 44",
    "sg:postcode":"46700",
    "sg:province":"Valencia",
    "wof:name":"Pescados Juanito Gandia S.l.l.",
    "wof:placetype":"venue"
},
  "geometry": {"coordinates":[-0.1913339943,38.960735321],"type":"Point"}
}