{
  "type": "Feature",
  "properties": {
    "addr:full":"Calle de Cochabamba, 23 Madrid Madrid 28016",
    "addr:housenumber":"23",
    "addr:postcode":"madrid;28016",
    "addr:street":"Calle De Cochabamba",
    "iso:country":"ES",
    "sg:address":"Calle de Cochabamba, 23",
    "sg:city":"Madrid",
    "sg:orig_category":"Comit\u00c9s De Organizaci\u00d3n De Exposiciones, Ferias, Salones",
    "sg:phone":"+34 914 58 71 78",
    "sg:postcode":"28016",
    "sg:province":"Madrid",
    "sg:website":"www.alltime.has.it",
    "wof:name":"Lopez Alvarez Antonio",
    "wof:placetype":"venue"
},
  "geometry": {"coordinates":[-3.6784622669,40.4562187195],"type":"Point"}
}