{
  "type": "Feature",
  "properties": {
    "addr:full":"Rua Colon, 28 Vigo Pontevedra 36201",
    "addr:housenumber":"28",
    "addr:postcode":"36201",
    "addr:street":"Rua Colon",
    "iso:country":"ES",
    "sg:address":"Rua Colon, 28",
    "sg:city":"Vigo",
    "sg:orig_category":"Aparcamientos (infraestructuras, Accesorios)",
    "sg:phone":"+34 986 43 26 95",
    "sg:postcode":"36201",
    "sg:province":"Pontevedra",
    "wof:name":"Soengas Jorge Maria Dolores",
    "wof:placetype":"venue"
},
  "geometry": {"coordinates":[-8.7203550339,42.2369117737],"type":"Point"}
}