{
  "type": "Feature",
  "properties": {
    "iso:country":"ES",
    "sg:address":"Carrer de Foramur, 12",
    "sg:city":"Denia",
    "sg:orig_category":"Muebles, Minoristas",
    "sg:phone":"+34 966 42 68 46",
    "sg:postcode":"03700",
    "sg:province":"Alicante",
    "wof:name":"Tribeca Maderas De Asia S.l.",
    "wof:placetype":"venue"
},
  "geometry": {"coordinates":[0.1092749983,38.8428497314],"type":"Point"}
}