{
  "type": "Feature",
  "properties": {
    "addr:full":"Calle de Fuencarral, 64 Madrid Madrid 28004",
    "addr:housenumber":"64",
    "addr:postcode":"madrid;28004",
    "addr:street":"Calle De Fuencarral",
    "iso:country":"ES",
    "sg:address":"Calle de Fuencarral, 64",
    "sg:city":"Madrid",
    "sg:orig_category":"Dorados, Plater\u00cda (orfebrer\u00cda)",
    "sg:phone":"+34 915 21 37 81",
    "sg:postcode":"28004",
    "sg:province":"Madrid",
    "wof:name":"Varela Rubio Susana",
    "wof:placetype":"venue"
},
  "geometry": {"coordinates":[-3.7006497383,40.4242019653],"type":"Point"}
}