{
  "type": "Feature",
  "properties": {
    "iso:country":"ES",
    "sg:address":"Calle de Guadix, 2",
    "sg:city":"Almu\u00f1ecar",
    "sg:orig_category":"Muebles Y Accesorios Para Cocinas Y Cuartos De Ba\u00d1o (al Por Menor)",
    "sg:phone":"+34 958 63 48 53",
    "sg:postcode":"18690",
    "sg:province":"Granada",
    "wof:name":"Sanchez Rodriguez Jose Antonio",
    "wof:placetype":"venue"
},
  "geometry": {"coordinates":[-3.693253994,36.7356719971],"type":"Point"}
}