{
  "type": "Feature",
  "properties": {
    "addr:full":"Calle de La Revoltosa, 26 Madrid Madrid 28031",
    "addr:housenumber":"26",
    "addr:postcode":"madrid;28031",
    "addr:street":"Calle De La Revoltosa",
    "iso:country":"ES",
    "sg:address":"Calle de La Revoltosa, 26",
    "sg:city":"Madrid",
    "sg:orig_category":"Molduras, Junquillos, Listones Y Molduras Perforadas",
    "sg:phone":"+34 913 31 35 00",
    "sg:postcode":"28031",
    "sg:province":"Madrid",
    "wof:name":"Serrano Huertas Angel",
    "wof:placetype":"venue"
},
  "geometry": {"coordinates":[-3.620454073,40.3754806519],"type":"Point"}
}