{
  "type": "Feature",
  "properties": {
    "addr:full":"Pl Comte De Reus, 5 Reus Tarragona 43205",
    "addr:housenumber":"5",
    "addr:postcode":"43205",
    "addr:street":"Pl Comte De Reus",
    "iso:country":"ES",
    "sg:address":"Pl Comte De Reus, 5",
    "sg:city":"Reus",
    "sg:orig_category":"M\u00c9dicos: Psiquiatr\u00cda",
    "sg:phone":"+34 977 31 68 30",
    "sg:postcode":"43205",
    "sg:province":"Tarragona",
    "wof:name":"Sola Cebrian Joaquin",
    "wof:placetype":"venue"
},
  "geometry": {"coordinates":[1.1050599813,41.1512985229],"type":"Point"}
}