{
  "type": "Feature",
  "properties": {
    "addr:full":"Plaz San Julian, 4 Salamanca Salamanca 37001",
    "addr:housenumber":"4",
    "addr:postcode":"37001",
    "addr:street":"Plaz San Julian",
    "iso:country":"ES",
    "sg:address":"Plaz San Julian, 4",
    "sg:city":"Salamanca",
    "sg:orig_category":"Centros Empresariales",
    "sg:phone":"+34 923 21 24 56",
    "sg:postcode":"37001",
    "sg:province":"Salamanca",
    "wof:name":"Becerro Ruiz Isidora",
    "wof:placetype":"venue"
},
  "geometry": {"coordinates":[-5.6612148285,40.9648132324],"type":"Point"}
}