{
  "type": "Feature",
  "properties": {
    "addr:full":"Calle de Alicante, 94 San Vicente Del Raspeig-sant Vicent Del Raspeig Alicante 03690",
    "addr:housenumber":"94",
    "addr:postcode":"03690",
    "addr:street":"Calle De Alicante",
    "iso:country":"ES",
    "sg:address":"Calle de Alicante, 94",
    "sg:city":"San Vicente Del Raspeig-sant Vicent Del Raspeig",
    "sg:orig_category":"Agencias De Viajes",
    "sg:phone":"+34 965 66 17 79",
    "sg:postcode":"03690",
    "sg:province":"Alicante",
    "wof:name":"Gomez Martinez Lourdes",
    "wof:placetype":"venue"
},
  "geometry": {"coordinates":[-0.5086318254,38.3852844238],"type":"Point"}
}