{
  "type": "Feature",
  "properties": {
    "addr:full":"Ctra De La Rasa, S/n Burgo Osma Soria 42300",
    "addr:housenumber":"s / n",
    "addr:postcode":"42300",
    "addr:street":"Ctra De La Rasa",
    "iso:country":"ES",
    "sg:address":"Ctra De La Rasa, S/n",
    "sg:city":"Burgo Osma",
    "sg:orig_category":"Alimentaci\u00d3n General (al Por Menor)",
    "sg:phone":"+34 975 36 03 43",
    "sg:postcode":"42300",
    "sg:province":"Soria",
    "wof:name":"Ace\u00f1a Motor S.l.",
    "wof:placetype":"venue"
},
  "geometry": {"coordinates":[-3.0761668682,41.582408905],"type":"Point"}
}