{
  "type": "Feature",
  "properties": {
    "iso:country":"ES",
    "sg:address":"San Juan, S/n",
    "sg:city":"Ribera Baja",
    "sg:orig_category":"Florister\u00cdas",
    "sg:phone":"+34 957 60 10 23",
    "sg:postcode":"14512",
    "sg:province":"C\u00f3rdoba",
    "wof:name":"Quero Aro Manuel",
    "wof:placetype":"venue"
},
  "geometry": {"coordinates":[-4.7886390686,37.4040336609],"type":"Point"}
}