{
  "type": "Feature",
  "properties": {
    "addr:full":"Guillermo Reina, 47 Huercal-overa Almer\u00eda 04600",
    "addr:housenumber":"47",
    "addr:postcode":"04600",
    "addr:street":"Guillermo Reina;Almeri\u0301A",
    "iso:country":"ES",
    "sg:address":"Guillermo Reina, 47",
    "sg:city":"Huercal-overa",
    "sg:orig_category":"Alquiler De Veh\u00cdculos: Turismos Y Utilitarios",
    "sg:phone":"+34 950 13 46 29",
    "sg:postcode":"04600",
    "sg:province":"Almer\u00eda",
    "wof:name":"Autocares Y Taxis Rofran S.l.",
    "wof:placetype":"venue"
},
  "geometry": {"coordinates":[-1.9436843395,37.390625],"type":"Point"}
}