{
  "type": "Feature",
  "properties": {
    "addr:full":"Calle de Ginzo De Limia, 53 Madrid Madrid 28034",
    "addr:housenumber":"53",
    "addr:postcode":"madrid;28034",
    "addr:street":"Calle De Ginzo De Limia",
    "iso:country":"ES",
    "sg:address":"Calle de Ginzo De Limia, 53",
    "sg:city":"Madrid",
    "sg:orig_category":"Laboratorios Y Cl\u00cdnicas Veterinarias",
    "sg:phone":"+34 917 30 10 96",
    "sg:postcode":"28034",
    "sg:province":"Madrid",
    "wof:name":"Figueroa Diaz Jose Julio",
    "wof:placetype":"venue"
},
  "geometry": {"coordinates":[-3.7083795071,40.4847221375],"type":"Point"}
}