{
  "type": "Feature",
  "properties": {
    "iso:country":"ES",
    "sg:address":"Calle de Monse\u00d1or Oscar Romero, 26",
    "sg:city":"Madrid",
    "sg:orig_category":"Camiser\u00cda Y Ropa Interior Masculina (al Por Menor)",
    "sg:phone":"+34 914 62 83 28",
    "sg:postcode":"28025",
    "sg:province":"Madrid",
    "wof:name":"Merino Viton Carlos",
    "wof:placetype":"venue"
},
  "geometry": {"coordinates":[-3.7428519726,40.3811683655],"type":"Point"}
}