{
  "type": "Feature",
  "properties": {
    "iso:country":"ES",
    "sg:address":"Carrer de Costa Rica, 17",
    "sg:city":"Terrassa",
    "sg:orig_category":"Empresarios",
    "sg:phone":"+34 937 80 15 16",
    "sg:postcode":"08224",
    "sg:province":"Barcelona",
    "wof:name":"Chimeno Fernandez Moises",
    "wof:placetype":"venue"
},
  "geometry": {"coordinates":[2.0019330978,41.5525283813],"type":"Point"}
}