{
  "type": "Feature",
  "properties": {
    "iso:country":"ES",
    "sg:address":"Calle de Rio Vinalopo, 11",
    "sg:city":"Elda",
    "sg:orig_category":"Zapatos: Material, Suministros, Accesorios (fabricaci\u00d3n, Al Por Mayor)",
    "sg:phone":"+34 966 96 50 60",
    "sg:postcode":"03600",
    "sg:province":"Alicante",
    "wof:name":"Moda Metal S.l.",
    "wof:placetype":"venue"
},
  "geometry": {"coordinates":[-0.7981110215,38.4849586487],"type":"Point"}
}