{
  "type": "Feature",
  "properties": {
    "addr:full":"Calle de Amapola, 8 Mostoles Madrid 28935",
    "addr:housenumber":"8",
    "addr:postcode":"28935",
    "addr:street":"Calle De Amapola",
    "iso:country":"ES",
    "sg:address":"Calle de Amapola, 8",
    "sg:city":"Mostoles",
    "sg:orig_category":"Danza, Cursos, Asociaciones Y M\u00dasicos",
    "sg:phone":"+34 916 18 46 06",
    "sg:postcode":"28935",
    "sg:province":"Madrid",
    "wof:name":"Pomares Rojas Nuria",
    "wof:placetype":"venue"
},
  "geometry": {"coordinates":[-3.867569685,40.3358230591],"type":"Point"}
}