{
  "type": "Feature",
  "properties": {
    "iso:country":"ES",
    "sg:address":"Carrer de Gaudi, 11",
    "sg:city":"Manresa",
    "sg:orig_category":"Centros M\u00c9dicos Y Sociales, Dispensarios",
    "sg:phone":"+34 938 77 39 27",
    "sg:postcode":"08243",
    "sg:province":"Barcelona",
    "sg:website":"www.alergiasmatic.com",
    "wof:name":"Barcelona Parkinson S.l.",
    "wof:placetype":"venue"
},
  "geometry": {"coordinates":[1.8337420225,41.7301101685],"type":"Point"}
}