{
  "type": "Feature",
  "properties": {
    "addr:full":"Avda Paz (la), 1 Arcos Frontera C\u00e1diz 11630",
    "addr:postcode":"11630",
    "addr:street":"Avda Paz La 1 Arcos;Ca\u0301Diz",
    "iso:country":"ES",
    "sg:address":"Avda Paz (la), 1",
    "sg:city":"Arcos Frontera",
    "sg:orig_category":"Cajas De Ahorro",
    "sg:phone":"+34 956 70 03 17",
    "sg:postcode":"11630",
    "sg:province":"C\u00e1diz",
    "sg:website":"www.cajasanfernando.es",
    "wof:name":"Caja San Fernando De Sevilla Y Jerez",
    "wof:placetype":"venue"
},
  "geometry": {"coordinates":[-5.8200149536,36.7541847229],"type":"Point"}
}