{
  "type": "Feature",
  "properties": {
    "addr:full":"Prj. Fuente Nueva, 18 Ejido Almer\u00eda 04700",
    "addr:housenumber":"18 ejido",
    "addr:postcode":"04700",
    "addr:street":"Nueva;Almeri\u0301A",
    "iso:country":"ES",
    "sg:address":"Prj. Fuente Nueva, 18",
    "sg:city":"Ejido",
    "sg:orig_category":"Semiller\u00cdas",
    "sg:phone":"+34 950 48 06 12",
    "sg:postcode":"04700",
    "sg:province":"Almer\u00eda",
    "wof:name":"Palmero Cara Miguel",
    "wof:placetype":"venue"
},
  "geometry": {"coordinates":[-2.8058309555,36.7609977722],"type":"Point"}
}