{
  "type": "Feature",
  "properties": {
    "iso:country":"ES",
    "sg:address":"Carrer de Maresme, 175",
    "sg:city":"Barcelona",
    "sg:orig_category":"Molduras, Junquillos, Listones Y Molduras Perforadas",
    "sg:phone":"+34 933 14 93 20",
    "sg:postcode":"08020",
    "sg:province":"Barcelona",
    "wof:name":"Garcia Maldonado Francisco",
    "wof:placetype":"venue"
},
  "geometry": {"coordinates":[2.2076430321,41.418296814],"type":"Point"}
}