{
  "type": "Feature",
  "properties": {
    "addr:full":"Calle de Pino (del), 7 Arganda Madrid 28500",
    "addr:housenumber":"7",
    "addr:postcode":"28500",
    "addr:street":"Calle De Pino Del",
    "iso:country":"ES",
    "sg:address":"Calle de Pino (del), 7",
    "sg:city":"Arganda",
    "sg:orig_category":"Comercio De Piezas De Recambio Y De Accesorios De Veh\u00cdculos, Veh\u00cdculos Industriales",
    "sg:phone":"+34 918 76 88 80",
    "sg:postcode":"28500",
    "sg:province":"Madrid",
    "sg:website":"www.roadhouse.es",
    "wof:name":"Trw Automotive Espa\u00d1a S.l.",
    "wof:placetype":"venue"
},
  "geometry": {"coordinates":[-3.4640901089,40.3141860962],"type":"Point"}
}