{
  "type": "Feature",
  "properties": {
    "addr:full":"El Apartadeiro, 2 Sotillo De Cabrera Le\u00f3n 24389",
    "addr:housenumber":"2",
    "addr:postcode":"24389",
    "addr:street":"Apartadeiro;Leo\u0301N",
    "iso:country":"ES",
    "sg:address":"El Apartadeiro, 2",
    "sg:city":"Sotillo De Cabrera",
    "sg:orig_category":"Pizzer\u00cdas",
    "sg:phone":"+34 987 69 54 53",
    "sg:postcode":"24389",
    "sg:province":"Le\u00f3n",
    "wof:name":"Pizarras Beta S.a.",
    "wof:placetype":"venue"
},
  "geometry": {"coordinates":[-6.7072958946,42.4021835327],"type":"Point"}
}