{
  "type": "Feature",
  "properties": {
    "addr:full":"Calle de Camino Viejo De Leganes, 177 Madrid Madrid 28025",
    "addr:housenumber":"177",
    "addr:postcode":"28025",
    "addr:street":"Calle De Camino Viejo De Leganes",
    "iso:country":"ES",
    "sg:address":"Calle de Camino Viejo De Leganes, 177",
    "sg:city":"Madrid",
    "sg:orig_category":"Zapater\u00cdas",
    "sg:phone":"+34 914 65 76 10",
    "sg:postcode":"28025",
    "sg:province":"Madrid",
    "wof:name":"Penalva Melero Manuel",
    "wof:placetype":"venue"
},
  "geometry": {"coordinates":[-3.7311840057,40.3810997009],"type":"Point"}
}