{
  "type": "Feature",
  "properties": {
    "iso:country":"ES",
    "sg:address":"Avda Francisco Gonzalez Rey, 2",
    "sg:city":"Celanova",
    "sg:orig_category":"Procuradores",
    "sg:phone":"+34 988 43 18 95",
    "sg:postcode":"32800",
    "sg:province":"Ourense",
    "wof:name":"Taboada Sanchez Jose Ramon",
    "wof:placetype":"venue"
},
  "geometry": {"coordinates":[-7.9564938545,42.1538963318],"type":"Point"}
}