{
  "type": "Feature",
  "properties": {
    "addr:full":"Calle de Camino De San Antonio, S/n Motril Granada 18600",
    "addr:housenumber":"s / n",
    "addr:postcode":"18600",
    "addr:street":"Calle De Camino De San Antonio",
    "iso:country":"ES",
    "sg:address":"Calle de Camino De San Antonio, S/n",
    "sg:city":"Motril",
    "sg:orig_category":"Electrodom\u00c9sticos (al Por Menor)",
    "sg:phone":"+34 958 82 45 54",
    "sg:postcode":"18600",
    "sg:province":"Granada",
    "wof:name":"Rodriguez Puertas Dolores",
    "wof:placetype":"venue"
},
  "geometry": {"coordinates":[-3.5190234184,36.7465934753],"type":"Point"}
}