{
  "type": "Feature",
  "properties": {
    "addr:full":"Calle de Metalurgias (las), 4 Alacant Alicante 03008",
    "addr:housenumber":"4",
    "addr:postcode":"03008",
    "addr:street":"Calle De Metalurgias Las",
    "iso:country":"ES",
    "sg:address":"Calle de Metalurgias (las), 4",
    "sg:city":"Alacant",
    "sg:orig_category":"Electrodom\u00c9sticos (al Por Menor)",
    "sg:phone":"+34 965 11 14 79",
    "sg:postcode":"03008",
    "sg:province":"Alicante",
    "wof:name":"Caypre S.l.",
    "wof:placetype":"venue"
},
  "geometry": {"coordinates":[-0.5131959915,38.3381538391],"type":"Point"}
}