{
  "type": "Feature",
  "properties": {
    "iso:country":"ES",
    "sg:address":"Doctor Demetrio Galan Bergua, 3",
    "sg:city":"Zaragoza",
    "sg:orig_category":"Inmobiliaria (agencias)",
    "sg:phone":"+34 976 33 11 81",
    "sg:postcode":"50017",
    "sg:province":"Zaragoza",
    "wof:name":"Desarrollo Inmohogar 2010 S.l.",
    "wof:placetype":"venue"
},
  "geometry": {"coordinates":[-0.9162570238,41.6505203247],"type":"Point"}
}