{
  "type": "Feature",
  "properties": {
    "iso:country":"ES",
    "sg:address":"Calle de Doctor Castroviejo, 11",
    "sg:city":"Aguilar Del Rio Alhama",
    "sg:orig_category":"Empresas De Desmonte",
    "sg:phone":"+34 941 19 70 08",
    "sg:postcode":"26530",
    "sg:province":"La Rioja",
    "wof:name":"Bomasan S C",
    "wof:placetype":"venue"
},
  "geometry": {"coordinates":[-1.9930289984,41.960811615],"type":"Point"}
}