{
  "type": "Feature",
  "properties": {
    "iso:country":"ES",
    "sg:address":"Ctra. Granada, Km. 0000,7",
    "sg:city":"Castillo Locubin",
    "sg:orig_category":"Frutas, Legumbres Frescas Y Tempranas (al Por Menor)",
    "sg:phone":"+34 953 59 14 58",
    "sg:postcode":"23670",
    "sg:province":"Ja\u00e9n",
    "wof:name":"Fruticola San Pedro S.c.l.",
    "wof:placetype":"venue"
},
  "geometry": {"coordinates":[-3.9412829876,37.5313835144],"type":"Point"}
}