{
  "type": "Feature",
  "properties": {
    "addr:full":"Calle de Doctor Carre\u00d1o, S/n Cari\u00f1o La Coru\u00f1a 15360",
    "addr:housenumber":"s",
    "addr:postcode":"15360",
    "addr:street":"Calle De Doctor Carren\u0303O;/ N Carin\u0303O La Corun\u0303A",
    "iso:country":"ES",
    "sg:address":"Calle de Doctor Carre\u00d1o, S/n",
    "sg:city":"Cari\u00f1o",
    "sg:orig_category":"Hoteles",
    "sg:phone":"+34 981 40 57 27",
    "sg:postcode":"15360",
    "sg:province":"La Coru\u00f1a",
    "wof:name":"Insua Perez Jose",
    "wof:placetype":"venue"
},
  "geometry": {"coordinates":[-7.8765611649,43.7413330078],"type":"Point"}
}