{
  "type": "Feature",
  "properties": {
    "iso:country":"ES",
    "sg:address":"Los Prados, S/n",
    "sg:city":"Carde\u00f1adijo",
    "sg:orig_category":"Armas Y Municiones (fabricaci\u00d3n, Al Por Mayor)",
    "sg:phone":"+34 947 29 00 39",
    "sg:postcode":"09194",
    "sg:province":"Burgos",
    "wof:name":"Serna Vicario Fernando De La",
    "wof:placetype":"venue"
},
  "geometry": {"coordinates":[-3.5908350945,42.2415313721],"type":"Point"}
}