{
  "type": "Feature",
  "properties": {
    "addr:full":"Plce Ortega, 4 Yecla Murcia 30510",
    "addr:postcode":"30510",
    "addr:street":"Ortega",
    "iso:country":"ES",
    "sg:address":"Plce Ortega, 4",
    "sg:city":"Yecla",
    "sg:orig_category":"Cooperativas Agr\u00cdcolas",
    "sg:phone":"+34 968 79 07 59",
    "sg:postcode":"30510",
    "sg:province":"Murcia",
    "wof:name":"Coordinadora De Organizaciones De Agricultores Y Ganaderos Iniciativa Rural De Murcia",
    "wof:placetype":"venue"
},
  "geometry": {"coordinates":[-1.1149940491,38.6145591736],"type":"Point"}
}