{
  "type": "Feature",
  "properties": {
    "addr:full":"Carrer de Maria Sanjuan Cuchi, 25 Viladecans Barcelona 08840",
    "addr:housenumber":"25",
    "addr:postcode":"08840",
    "addr:street":"Carrer De Maria Sanjuan Cuchi",
    "iso:country":"ES",
    "sg:address":"Carrer de Maria Sanjuan Cuchi, 25",
    "sg:city":"Viladecans",
    "sg:orig_category":"Empresas De Carpinter\u00cda De Madera",
    "sg:phone":"+34 936 35 70 19",
    "sg:postcode":"08840",
    "sg:province":"Barcelona",
    "wof:name":"Famudel 50 S.l.",
    "wof:placetype":"venue"
},
  "geometry": {"coordinates":[2.0163009167,41.3253479004],"type":"Point"}
}