{
  "type": "Feature",
  "properties": {
    "addr:full":"Calle de Gordoniz, 53 Bilbao Vizcaya 48002",
    "addr:housenumber":"53",
    "addr:postcode":"48002",
    "addr:street":"Calle De Gordoniz",
    "iso:country":"ES",
    "sg:address":"Calle de Gordoniz, 53",
    "sg:city":"Bilbao",
    "sg:orig_category":"Afiladoras, Pulidoras Y Bru\u00d1idoras",
    "sg:phone":"+34 944 22 02 17",
    "sg:postcode":"48002",
    "sg:province":"Vizcaya",
    "wof:name":"Vela Salgado Juan Manuel",
    "wof:placetype":"venue"
},
  "geometry": {"coordinates":[-2.9454889297,43.2534217834],"type":"Point"}
}