{
  "type": "Feature",
  "properties": {
    "addr:full":"Carrer de Castell, 10 Amposta Tarragona 43870",
    "addr:housenumber":"10",
    "addr:postcode":"43870",
    "addr:street":"Carrer De Castell",
    "iso:country":"ES",
    "sg:address":"Carrer de Castell, 10",
    "sg:city":"Amposta",
    "sg:orig_category":"Promotores Constructores",
    "sg:phone":"+34 977 70 70 38",
    "sg:postcode":"43870",
    "sg:province":"Tarragona",
    "wof:name":"Lloguers Damposta S.l.",
    "wof:placetype":"venue"
},
  "geometry": {"coordinates":[0.5800759792,40.7138442993],"type":"Point"}
}