{
  "type": "Feature",
  "properties": {
    "iso:country":"ES",
    "sg:address":"Calle de Salud (la), 3",
    "sg:city":"Llanos De Aridane",
    "sg:orig_category":"Arquitectos",
    "sg:phone":"+34 922 46 35 99",
    "sg:postcode":"38760",
    "sg:province":"Santa Cruz De Tenerife",
    "wof:name":"Jimenez Pais S.l.u.",
    "wof:placetype":"venue"
},
  "geometry": {"coordinates":[-17.9111652374,28.6579589844],"type":"Point"}
}