{
  "type": "Feature",
  "properties": {
    "addr:full":"Ctra Tacoronte Tejina, 10 Tacoronte Santa Cruz De Tenerife 38350",
    "addr:housenumber":"10",
    "addr:postcode":"38350",
    "addr:street":"Ctra Tacoronte Tejina",
    "iso:country":"ES",
    "sg:address":"Ctra Tacoronte Tejina, 10",
    "sg:city":"Tacoronte",
    "sg:orig_category":"Peluquer\u00cdas, Peluquer\u00cda Mixta",
    "sg:phone":"+34 922 57 20 81",
    "sg:postcode":"38350",
    "sg:province":"Santa Cruz De Tenerife",
    "wof:name":"Gonzalez Perez Andres",
    "wof:placetype":"venue"
},
  "geometry": {"coordinates":[-16.4144248962,28.4774627686],"type":"Point"}
}