{
  "type": "Feature",
  "properties": {
    "addr:full":"Molina, S/n Udrion Asturias 33119",
    "addr:housenumber":"s / n",
    "addr:postcode":"33119",
    "addr:street":"Molina",
    "iso:country":"ES",
    "sg:address":"Molina, S/n",
    "sg:city":"Udrion",
    "sg:orig_category":"Ebanister\u00cda",
    "sg:phone":"+34 985 78 40 00",
    "sg:postcode":"33119",
    "sg:province":"Asturias",
    "wof:name":"Alvarez Garcia Antonio Raul",
    "wof:placetype":"venue"
},
  "geometry": {"coordinates":[-5.9673852921,43.3594436646],"type":"Point"}
}