{
  "type": "Feature",
  "properties": {
    "addr:full":"Calle de Diego Ayllon, 11 Madrid Madrid 28043",
    "addr:housenumber":"11",
    "addr:postcode":"madrid;28043",
    "addr:street":"Calle De Diego Ayllon",
    "iso:country":"ES",
    "sg:address":"Calle de Diego Ayllon, 11",
    "sg:city":"Madrid",
    "sg:orig_category":"Inmobiliaria (agencias)",
    "sg:phone":"+34 913 88 17 17",
    "sg:postcode":"28043",
    "sg:province":"Madrid",
    "wof:name":"Arconar S.a.",
    "wof:placetype":"venue"
},
  "geometry": {"coordinates":[-3.6505262852,40.4518547058],"type":"Point"}
}