{
  "type": "Feature",
  "properties": {
    "iso:country":"ES",
    "sg:address":"Calle de San Francisco, 14",
    "sg:city":"Velez-malaga",
    "sg:orig_category":"Farmacias",
    "sg:phone":"+34 952 50 13 46",
    "sg:postcode":"29700",
    "sg:province":"M\u00e1laga",
    "wof:name":"Seoane Amado Maria De La Sierra",
    "wof:placetype":"venue"
},
  "geometry": {"coordinates":[-4.1013169289,36.7820701599],"type":"Point"}
}