{
  "type": "Feature",
  "properties": {
    "iso:country":"ES",
    "sg:address":"Cami Son Gotleu, 30",
    "sg:city":"Palma",
    "sg:orig_category":"Veh\u00cdculos De Ocasi\u00d3n",
    "sg:phone":"+34 971 27 18 53",
    "sg:postcode":"07008",
    "sg:province":"Islas Baleares",
    "wof:name":"Salamanca Motors S.l.",
    "wof:placetype":"venue"
},
  "geometry": {"coordinates":[2.6707448959,39.5808334351],"type":"Point"}
}