{
  "type": "Feature",
  "properties": {
    "addr:full":"Calle de Emilio Ferrari, 20 Madrid Madrid 28017",
    "addr:housenumber":"20",
    "addr:postcode":"madrid;28017",
    "addr:street":"Calle De Emilio Ferrari",
    "iso:country":"ES",
    "sg:address":"Calle de Emilio Ferrari, 20",
    "sg:city":"Madrid",
    "sg:orig_category":"Frutas Y Legumbres Frescas (al Por Mayor)",
    "sg:phone":"+34 913 67 94 43",
    "sg:postcode":"28017",
    "sg:province":"Madrid",
    "wof:name":"Royco Frutos S.l.",
    "wof:placetype":"venue"
},
  "geometry": {"coordinates":[-3.6432800293,40.4336738586],"type":"Point"}
}