{
  "type": "Feature",
  "properties": {
    "iso:country":"ES",
    "sg:address":"Calle de Comercio, 33",
    "sg:city":"Mairena Aljarafe",
    "sg:orig_category":"Productos Qu\u00cdmicos (fabricaci\u00d3n, Al Por Mayor)",
    "sg:phone":"+34 954 18 66 02",
    "sg:postcode":"41927",
    "sg:province":"Sevilla",
    "wof:name":"Friogas S.a.",
    "wof:placetype":"venue"
},
  "geometry": {"coordinates":[-6.0579571724,37.3542289734],"type":"Point"}
}