{
  "type": "Feature",
  "properties": {
    "iso:country":"ES",
    "sg:address":"Calle de Marques De Monasterio, 4",
    "sg:city":"Madrid",
    "sg:orig_category":"M\u00c9dicos: Medicina Y Biolog\u00cda Del Deporte",
    "sg:phone":"+34 915 31 04 46",
    "sg:postcode":"28004",
    "sg:province":"Madrid",
    "wof:name":"Lauga Henri Michel",
    "wof:placetype":"venue"
},
  "geometry": {"coordinates":[-3.6938183308,40.4230232239],"type":"Point"}
}