{
  "type": "Feature",
  "properties": {
    "iso:country":"ES",
    "sg:address":"Ctra. Malpica, 17",
    "sg:city":"Cebolla",
    "sg:orig_category":"Art\u00cdculos Funerarios (al Por Menor)",
    "sg:phone":"+34 925 87 11 33",
    "sg:postcode":"45550",
    "sg:province":"Toledo",
    "wof:name":"Hermanos Jimenez F.a.c. S.l.",
    "wof:placetype":"venue"
},
  "geometry": {"coordinates":[-4.5692791939,39.9424476624],"type":"Point"}
}