{
  "type": "Feature",
  "properties": {
    "iso:country":"ES",
    "sg:address":"Calle de Fernandez De Los Rios, 98",
    "sg:city":"Madrid",
    "sg:orig_category":"Edici\u00d3n De Diarios, Revistas, Boletines",
    "sg:phone":"+34 915 49 85 23",
    "sg:postcode":"28015",
    "sg:province":"Madrid",
    "wof:name":"Hot English Publishing S.l.",
    "wof:placetype":"venue"
},
  "geometry": {"coordinates":[-3.7162089348,40.4354553223],"type":"Point"}
}