{
  "type": "Feature",
  "properties": {
    "addr:full":"Calle de Felipe Checa, 40 Badajoz Badajoz 06001",
    "addr:housenumber":"40",
    "addr:postcode":"06001",
    "addr:street":"Calle De Felipe Checa",
    "iso:country":"ES",
    "sg:address":"Calle de Felipe Checa, 40",
    "sg:city":"Badajoz",
    "sg:orig_category":"Aguas (distribuci\u00d3n, Servicios)",
    "sg:phone":"+34 924 26 09 45",
    "sg:postcode":"06001",
    "sg:province":"Badajoz",
    "wof:name":"Lusoaguas S.l.",
    "wof:placetype":"venue"
},
  "geometry": {"coordinates":[-6.9708480835,38.8791770935],"type":"Point"}
}