{
  "type": "Feature",
  "properties": {
    "addr:full":"Sarriguren Bidea, S/n Huarte Navarra 31620",
    "addr:housenumber":"s / n",
    "addr:postcode":"31620",
    "addr:street":"Sarriguren Bidea;Navarra",
    "iso:country":"ES",
    "sg:address":"Sarriguren Bidea, S/n",
    "sg:city":"Huarte",
    "sg:orig_category":"Tubos Met\u00c1licos",
    "sg:phone":"+34 948 33 32 89",
    "sg:postcode":"31620",
    "sg:province":"Navarra",
    "wof:name":"Aldaz Echarri S.a.",
    "wof:placetype":"venue"
},
  "geometry": {"coordinates":[-1.6056938171,42.8232345581],"type":"Point"}
}