{
  "type": "Feature",
  "properties": {
    "iso:country":"ES",
    "sg:address":"Avda Estacion (de La), 79",
    "sg:city":"Puente-genil",
    "sg:orig_category":"Molduras, Junquillos, Listones Y Molduras Perforadas",
    "sg:phone":"+34 957 60 23 62",
    "sg:postcode":"14500",
    "sg:province":"C\u00f3rdoba",
    "wof:name":"Ruz Campos Eduardo",
    "wof:placetype":"venue"
},
  "geometry": {"coordinates":[-4.7603387833,37.3938903809],"type":"Point"}
}