{
  "type": "Feature",
  "properties": {
    "addr:full":"Calle de Ponzano, 31 Madrid Madrid 28003",
    "addr:housenumber":"31",
    "addr:postcode":"madrid;28003",
    "addr:street":"Calle De Ponzano",
    "iso:country":"ES",
    "sg:address":"Calle de Ponzano, 31",
    "sg:city":"Madrid",
    "sg:orig_category":"Inmobiliaria (agencias)",
    "sg:phone":"+34 914 42 59 81",
    "sg:postcode":"28003",
    "sg:province":"Madrid",
    "wof:name":"Fopiano  Marco",
    "wof:placetype":"venue"
},
  "geometry": {"coordinates":[-3.6994550228,40.4392929077],"type":"Point"}
}