{
  "type": "Feature",
  "properties": {
    "addr:full":"Calle de Doctor Cerda Marti, 22 Hellin Albacete 02400",
    "addr:housenumber":"22",
    "addr:postcode":"02400",
    "addr:street":"Calle De Doctor Cerda Marti",
    "iso:country":"ES",
    "sg:address":"Calle de Doctor Cerda Marti, 22",
    "sg:city":"Hellin",
    "sg:orig_category":"Hormigonados",
    "sg:phone":"+34 967 30 07 89",
    "sg:postcode":"02400",
    "sg:province":"Albacete",
    "wof:name":"Trihona S.l.",
    "wof:placetype":"venue"
},
  "geometry": {"coordinates":[-1.6972290277,38.5098381042],"type":"Point"}
}