{
  "type": "Feature",
  "properties": {
    "addr:full":"Calle de Gambrinus, 23 Grela La Coru\u00f1a 15008",
    "addr:housenumber":"23",
    "addr:postcode":"15008",
    "addr:street":"Calle De Gambrinus;La Corun\u0303A",
    "iso:country":"ES",
    "sg:address":"Calle de Gambrinus, 23",
    "sg:city":"Grela",
    "sg:orig_category":"Autob\u00das (explotaci\u00d3n Y Servicios De)",
    "sg:phone":"+34 981 27 86 15",
    "sg:postcode":"15008",
    "sg:province":"La Coru\u00f1a",
    "wof:name":"Autocares Cancela S.l.",
    "wof:placetype":"venue"
},
  "geometry": {"coordinates":[-8.4471950531,43.0565299988],"type":"Point"}
}