{
  "type": "Feature",
  "properties": {
    "iso:country":"ES",
    "sg:address":"Pl Donants De Sang, 1",
    "sg:city":"Muro",
    "sg:orig_category":"Abogados",
    "sg:phone":"+34 971 86 06 65",
    "sg:postcode":"07440",
    "sg:province":"Islas Baleares",
    "wof:name":"Vallestir Martorell Jorge",
    "wof:placetype":"venue"
},
  "geometry": {"coordinates":[3.0556950569,39.7377510071],"type":"Point"}
}