{
  "type": "Feature",
  "properties": {
    "addr:full":"Calle de Conde, 4 Ecija Sevilla 41400",
    "addr:housenumber":"4",
    "addr:postcode":"41400",
    "addr:street":"Calle De Conde",
    "iso:country":"ES",
    "sg:address":"Calle de Conde, 4",
    "sg:city":"Ecija",
    "sg:orig_category":"Panader\u00cdas, Panader\u00cdas",
    "sg:phone":"+34 954 83 19 56",
    "sg:postcode":"41400",
    "sg:province":"Sevilla",
    "wof:name":"Alvarez Torres Concepcion",
    "wof:placetype":"venue"
},
  "geometry": {"coordinates":[-5.0803089142,37.5410499573],"type":"Point"}
}