{
  "type": "Feature",
  "properties": {
    "iso:country":"ES",
    "sg:address":"Calle de Val, 2",
    "sg:city":"Valladolid",
    "sg:orig_category":"Laboratorios Y Trabajos De Fotograf\u00cda, V\u00cddeo Y Cine",
    "sg:phone":"+34 983 35 17 63",
    "sg:postcode":"47003",
    "sg:province":"Valladolid",
    "wof:name":"Fragua Gonzalez Raquel",
    "wof:placetype":"venue"
},
  "geometry": {"coordinates":[-4.7274398804,41.652961731],"type":"Point"}
}