{
  "type": "Feature",
  "properties": {
    "addr:full":"Calle de Portillo De San Jeronimo, S/n Jaen Ja\u00e9n 23001",
    "addr:housenumber":"s / n;jae\u0301n",
    "addr:postcode":"23001",
    "addr:street":"Calle De Portillo De San Jeronimo",
    "iso:country":"ES",
    "sg:address":"Calle de Portillo De San Jeronimo, S/n",
    "sg:city":"Jaen",
    "sg:orig_category":"Pescader\u00cdas (al Por Menor)",
    "sg:phone":"+34 953 24 06 75",
    "sg:postcode":"23001",
    "sg:province":"Ja\u00e9n",
    "wof:name":"Hurtado Roldan Francisco",
    "wof:placetype":"venue"
},
  "geometry": {"coordinates":[-3.7844040394,37.7681808472],"type":"Point"}
}