{
  "type": "Feature",
  "properties": {
    "addr:full":"Calle de Pe\u00d1aranda, 16 Villoruela Salamanca 37339",
    "addr:housenumber":"16",
    "addr:postcode":"37339",
    "addr:street":"Calle De Pen\u0303Aranda",
    "iso:country":"ES",
    "sg:address":"Calle de Pe\u00d1aranda, 16",
    "sg:city":"Villoruela",
    "sg:orig_category":"Ense\u00d1anza, Formaci\u00d3n Profesional: Aprendizaje",
    "sg:phone":"+34 923 35 60 18",
    "sg:postcode":"37339",
    "sg:province":"Salamanca",
    "wof:name":"Ayuntamiento De Villoruela",
    "wof:placetype":"venue"
},
  "geometry": {"coordinates":[-5.3731446266,40.9951972961],"type":"Point"}
}