{
  "type": "Feature",
  "properties": {
    "iso:country":"ES",
    "sg:address":"Calle de Cervantes, 1",
    "sg:city":"Martos",
    "sg:orig_category":"Carnicer\u00cdas, Carnicer\u00cdas",
    "sg:phone":"+34 953 55 40 04",
    "sg:postcode":"23600",
    "sg:province":"Ja\u00e9n",
    "wof:name":"Chamorro Delgado Manuel",
    "wof:placetype":"venue"
},
  "geometry": {"coordinates":[-3.9702498913,37.7155456543],"type":"Point"}
}