{
  "type": "Feature",
  "properties": {
    "iso:country":"ES",
    "sg:address":"Carrer de Pere Iv, 354",
    "sg:city":"Barcelona",
    "sg:orig_category":"Molduras, Junquillos, Listones Y Molduras Perforadas",
    "sg:phone":"+34 933 07 10 34",
    "sg:postcode":"08019",
    "sg:province":"Barcelona",
    "wof:name":"Gabarra Seto Jose",
    "wof:placetype":"venue"
},
  "geometry": {"coordinates":[2.2028639317,41.4094161987],"type":"Point"}
}