{
  "type": "Feature",
  "properties": {
    "iso:country":"ES",
    "sg:address":"Avda Espa\u00d1a, 3",
    "sg:city":"Corrales",
    "sg:orig_category":"Lencer\u00cda Femenina, Corseter\u00cda, Trajes De Ba\u00d1o (al Por Menor)",
    "sg:phone":"+34 942 83 28 72",
    "sg:postcode":"39400",
    "sg:province":"Cantabria",
    "wof:name":"Lenceria Corseteria Caprichos S.l.",
    "wof:placetype":"venue"
},
  "geometry": {"coordinates":[-4.0684490204,43.2586174011],"type":"Point"}
}