{
  "type": "Feature",
  "properties": {
    "iso:country":"ES",
    "sg:address":"Carrer de Calders, 8",
    "sg:city":"Barcelona",
    "sg:orig_category":"Ingenier\u00cda, Centros De Estudios (diversos)",
    "sg:phone":"+34 932 68 32 05",
    "sg:postcode":"08003",
    "sg:province":"Barcelona",
    "wof:name":"Enginyeria Reventos S.l.",
    "wof:placetype":"venue"
},
  "geometry": {"coordinates":[2.1833510399,41.3843955994],"type":"Point"}
}