{
  "type": "Feature",
  "properties": {
    "iso:country":"ES",
    "sg:address":"Calle de Ribaza, 50",
    "sg:city":"Puente Madre",
    "sg:orig_category":"Empresas De Carpinter\u00cda De Madera",
    "sg:phone":"+34 941 25 61 06",
    "sg:postcode":"26142",
    "sg:province":"La Rioja",
    "wof:name":"Cordon Mendoza Francisco Jose",
    "wof:placetype":"venue"
},
  "geometry": {"coordinates":[-2.417953968,42.4283485413],"type":"Point"}
}