{
  "type": "Feature",
  "properties": {
    "iso:country":"ES",
    "sg:address":"Carrer de Llibertat, 33",
    "sg:city":"Ametlla Mar",
    "sg:orig_category":"Centros Empresariales",
    "sg:phone":"+34 977 49 36 15",
    "sg:postcode":"43860",
    "sg:province":"Tarragona",
    "wof:name":"Sercon-scp Assessors S.l.",
    "wof:placetype":"venue"
},
  "geometry": {"coordinates":[0.8012760282,40.8846626282],"type":"Point"}
}