{
  "type": "Feature",
  "properties": {
    "addr:full":"Ziku\u00d1aga Bailara, 14 Zikuinaga Guip\u00f9zcoa 20120",
    "addr:housenumber":"14",
    "addr:postcode":"20120",
    "addr:street":"Zikun\u0303Aga Bailara;Guipu\u0300Zcoa",
    "iso:country":"ES",
    "sg:address":"Ziku\u00d1aga Bailara, 14",
    "sg:city":"Zikuinaga",
    "sg:orig_category":"Abrasivos Y Superabrasivos (fabricaci\u00d3n, Al Por Mayor)",
    "sg:phone":"+34 943 55 13 54",
    "sg:postcode":"20120",
    "sg:province":"Guip\u00f9zcoa",
    "sg:website":"www.abrasivosunesa.es",
    "wof:name":"Abrasivos Unesa S.l.",
    "wof:placetype":"venue"
},
  "geometry": {"coordinates":[-1.979829,43.264751],"type":"Point"}
}