{
  "type": "Feature",
  "properties": {
    "addr:full":"Avda Extremadura, 41 Oliva Frontera Badajoz 06120",
    "addr:housenumber":"41",
    "addr:postcode":"06120",
    "addr:street":"Avda Extremadura",
    "iso:country":"ES",
    "sg:address":"Avda Extremadura, 41",
    "sg:city":"Oliva Frontera",
    "sg:orig_category":"Muebles, Minoristas",
    "sg:phone":"+34 924 74 04 02",
    "sg:postcode":"06120",
    "sg:province":"Badajoz",
    "wof:name":"Cami\u00f1a Matamoros Agustin",
    "wof:placetype":"venue"
},
  "geometry": {"coordinates":[-6.9178600311,38.2780036926],"type":"Point"}
}