{
  "type": "Feature",
  "properties": {
    "iso:country":"ES",
    "sg:address":"Avda Cruz Roja (la), 26",
    "sg:city":"Jerez De La Frontera",
    "sg:orig_category":"Ebanister\u00cda",
    "sg:phone":"+34 956 31 03 06",
    "sg:postcode":"11407",
    "sg:province":"C\u00e1diz",
    "wof:name":"Franco Ruiz Jose Maria",
    "wof:placetype":"venue"
},
  "geometry": {"coordinates":[-6.1358089447,36.6981086731],"type":"Point"}
}