{
  "type": "Feature",
  "properties": {
    "iso:country":"ES",
    "sg:address":"Calle de Jerez Perchet, 39",
    "sg:city":"Malaga",
    "sg:orig_category":"Papeler\u00cdas, Librer\u00cdas",
    "sg:phone":"+34 952 26 65 34",
    "sg:postcode":"29014",
    "sg:province":"M\u00e1laga",
    "wof:name":"Rebollo Fernandez Maria Del Carmen",
    "wof:placetype":"venue"
},
  "geometry": {"coordinates":[-4.4175539017,36.7471427917],"type":"Point"}
}