{
  "type": "Feature",
  "properties": {
    "addr:full":"Calle de Zamakoa, 15 Galdakao Vizcaya 48960",
    "addr:housenumber":"15",
    "addr:postcode":"48960",
    "addr:street":"Calle De Zamakoa",
    "iso:country":"ES",
    "sg:address":"Calle de Zamakoa, 15",
    "sg:city":"Galdakao",
    "sg:orig_category":"Fabricaci\u00d3n De Art\u00cdculos Y Equipos Deportivos Y De Ocio",
    "sg:phone":"+34 944 56 10 86",
    "sg:postcode":"48960",
    "sg:province":"Vizcaya",
    "wof:name":"Objetivo Sport, S.l.",
    "wof:placetype":"venue"
},
  "geometry": {"coordinates":[-2.842977047,43.2322807312],"type":"Point"}
}