{
  "type": "Feature",
  "properties": {
    "addr:full":"Pg Montjuic, 66 Barcelona Barcelona 08004",
    "addr:housenumber":"66",
    "addr:postcode":"08004",
    "addr:street":"Pg Montjuic",
    "iso:country":"ES",
    "sg:address":"Pg Montjuic, 66",
    "sg:city":"Barcelona",
    "sg:orig_category":"Agencias Y Agentes Comerciales, Representantes",
    "sg:phone":"+34 934 41 49 20",
    "sg:postcode":"08004",
    "sg:province":"Barcelona",
    "wof:name":"Wakkas  Nazih",
    "wof:placetype":"venue"
},
  "geometry": {"coordinates":[2.167863369,41.3716278076],"type":"Point"}
}