{
  "type": "Feature",
  "properties": {
    "addr:full":"Av. Blasco Iba\u00f1ez, 161 Massanassa Valencia 46470",
    "addr:housenumber":"161",
    "addr:postcode":"46470",
    "addr:street":"Av. Blasco Iban\u0303Ez",
    "iso:country":"ES",
    "sg:address":"Av. Blasco Iba\u00f1ez, 161",
    "sg:city":"Massanassa",
    "sg:orig_category":"Veh\u00cdculos De Ocasi\u00d3n",
    "sg:phone":"+34 961 25 02 69",
    "sg:postcode":"46470",
    "sg:province":"Valencia",
    "wof:name":"Zahonero Del Rio Jose Antonio",
    "wof:placetype":"venue"
},
  "geometry": {"coordinates":[-0.4129641056,39.3978805542],"type":"Point"}
}