{
  "type": "Feature",
  "properties": {
    "iso:country":"ES",
    "sg:address":"Rbla Sant Sebastia, 94",
    "sg:city":"Santa Coloma De Gramenet",
    "sg:orig_category":"Alquiler De V\u00cddeo",
    "sg:phone":"+34 933 92 93 10",
    "sg:postcode":"08922",
    "sg:province":"Barcelona",
    "wof:name":"Silva Hortet David",
    "wof:placetype":"venue"
},
  "geometry": {"coordinates":[2.2153630257,41.4508247375],"type":"Point"}
}