{
  "type": "Feature",
  "properties": {
    "iso:country":"ES",
    "sg:address":"Plaz San Agustin (de), 3",
    "sg:city":"Granada",
    "sg:orig_category":"Mutuas De Seguros",
    "sg:phone":"+34 958 27 58 82",
    "sg:postcode":"18001",
    "sg:province":"Granada",
    "wof:name":"Hermandad Nacional De Arquitectos",
    "wof:placetype":"venue"
},
  "geometry": {"coordinates":[-3.5996730328,37.1780128479],"type":"Point"}
}