{
  "type": "Feature",
  "properties": {
    "iso:country":"ES",
    "sg:address":"Calle de Huertos (los), 34",
    "sg:city":"Camporredondo Alba",
    "sg:orig_category":"Cr\u00cda De Bovinos",
    "sg:phone":"+34 979 86 60 40",
    "sg:postcode":"34887",
    "sg:province":"Palencia",
    "wof:name":"Casado Mancebo Evangelina Araceli",
    "wof:placetype":"venue"
},
  "geometry": {"coordinates":[-4.6683287621,42.9157791138],"type":"Point"}
}