{
  "type": "Feature",
  "properties": {
    "iso:country":"ES",
    "sg:address":"Calle de Doctor Eduardo Evangelista, 13",
    "sg:city":"San Pedro Alcantara",
    "sg:orig_category":"T\u00c9cnicos Veterinarios",
    "sg:phone":"+34 952 78 01 13",
    "sg:postcode":"29670",
    "sg:province":"M\u00e1laga",
    "wof:name":"Hormigo Gil Francisco Angel",
    "wof:placetype":"venue"
},
  "geometry": {"coordinates":[-4.9942789078,36.4860076904],"type":"Point"}
}