{
  "type": "Feature",
  "properties": {
    "addr:full":"Rua Alfonso R Castelao, 5 Estrada Pontevedra 36680",
    "addr:housenumber":"5",
    "addr:postcode":"36680",
    "addr:street":"Rua Alfonso R Castelao;Estrada Pontevedra",
    "iso:country":"ES",
    "sg:address":"Rua Alfonso R Castelao, 5",
    "sg:city":"Estrada",
    "sg:orig_category":"Ropa Para Se\u00d1oras (al Por Menor)",
    "sg:phone":"+34 986 57 10 10",
    "sg:postcode":"36680",
    "sg:province":"Pontevedra",
    "wof:name":"Requeijo Picans Concepcion",
    "wof:placetype":"venue"
},
  "geometry": {"coordinates":[-8.486530304,42.6872253418],"type":"Point"}
}