{
  "type": "Feature",
  "properties": {
    "addr:full":"Avda Romero Donallo (de), 21 Santiago De Compostela A Coru\u00f1a 15706",
    "addr:housenumber":"21",
    "addr:postcode":"15706",
    "addr:street":"Avda Romero Donallo De;Corun\u0303A",
    "iso:country":"ES",
    "sg:address":"Avda Romero Donallo (de), 21",
    "sg:city":"Santiago De Compostela",
    "sg:orig_category":"Supermercados Y Hipermercados",
    "sg:phone":"+34 981 59 99 76",
    "sg:postcode":"15706",
    "sg:province":"A Coru\u00f1a",
    "wof:name":"Santiadesa De Locales S.l.",
    "wof:placetype":"venue"
},
  "geometry": {"coordinates":[-8.5511045456,42.8716659546],"type":"Point"}
}