{
  "type": "Feature",
  "properties": {
    "iso:country":"ES",
    "sg:address":"Ctr. Cuenca-teruel, Km. 0126,0",
    "sg:city":"Carboneras Guadazaon",
    "sg:orig_category":"Empresas De Carpinter\u00cda Met\u00c1lica",
    "sg:phone":"+34 969 34 10 31",
    "sg:postcode":"16350",
    "sg:province":"Cuenca",
    "wof:name":"Herraiz Saiz Julian",
    "wof:placetype":"venue"
},
  "geometry": {"coordinates":[-1.8094300032,39.896030426],"type":"Point"}
}