{
  "type": "Feature",
  "properties": {
    "addr:full":"Calle de Zanja, 7 Villafranca De Los Caballeros Toledo 45730",
    "addr:housenumber":"7",
    "addr:postcode":"45730",
    "addr:street":"Calle De Zanja",
    "iso:country":"ES",
    "sg:address":"Calle de Zanja, 7",
    "sg:city":"Villafranca De Los Caballeros",
    "sg:orig_category":"Confecci\u00d3n De Trajes Para Se\u00d1oras",
    "sg:phone":"+34 926 57 85 01",
    "sg:postcode":"45730",
    "sg:province":"Toledo",
    "wof:name":"Confecciones El Cristo De Santa Ana S.l.",
    "wof:placetype":"venue"
},
  "geometry": {"coordinates":[-3.3610351086,39.4240913391],"type":"Point"}
}