{
  "type": "Feature",
  "properties": {
    "iso:country":"ES",
    "sg:address":"Calle de Jose Ramon Zaragoza, 8",
    "sg:city":"Oviedo",
    "sg:orig_category":"Ingenier\u00cda, Centros De Estudios (diversos)",
    "sg:phone":"+34 985 27 53 33",
    "sg:postcode":"33013",
    "sg:province":"Asturias",
    "wof:name":"Mmf Asesoria Tecnica Sl",
    "wof:placetype":"venue"
},
  "geometry": {"coordinates":[-5.8621487617,43.3610877991],"type":"Point"}
}