{
  "type": "Feature",
  "properties": {
    "addr:full":"Rbla Josep Antoni Vidal, 11 Vilanova I La Geltru Barcelona 08800",
    "addr:housenumber":"11",
    "addr:postcode":"08800",
    "addr:street":"Rbla Josep Antoni Vidal",
    "iso:country":"ES",
    "sg:address":"Rbla Josep Antoni Vidal, 11",
    "sg:city":"Vilanova I La Geltru",
    "sg:orig_category":"Agentes Y Bufetes De Negocio",
    "sg:phone":"+34 938 10 02 70",
    "sg:postcode":"08800",
    "sg:province":"Barcelona",
    "wof:name":"Maez Rodriguez Maria Del Carmen",
    "wof:placetype":"venue"
},
  "geometry": {"coordinates":[1.7256350517,41.2206039429],"type":"Point"}
}