{
  "type": "Feature",
  "properties": {
    "addr:full":"Calle de Cruz De Mayo, 2 Hellin Albacete 02400",
    "addr:housenumber":"2",
    "addr:postcode":"02400",
    "addr:street":"Calle De Cruz De Mayo",
    "iso:country":"ES",
    "sg:address":"Calle de Cruz De Mayo, 2",
    "sg:city":"Hellin",
    "sg:orig_category":"Agencias Y Agentes Comerciales, Representantes",
    "sg:phone":"+34 967 30 08 89",
    "sg:postcode":"02400",
    "sg:province":"Albacete",
    "wof:name":"Hernandez Sanchez Ibrahin",
    "wof:placetype":"venue"
},
  "geometry": {"coordinates":[-1.6981637478,38.510093689],"type":"Point"}
}