{
  "type": "Feature",
  "properties": {
    "addr:full":"Calle de Olivos (los), 15 Mojonera Almer\u00eda 04745",
    "addr:housenumber":"15",
    "addr:postcode":"04745",
    "addr:street":"Calle De Olivos Los",
    "iso:country":"ES",
    "sg:address":"Calle de Olivos (los), 15",
    "sg:city":"Mojonera",
    "sg:orig_category":"Bibliotecas, Mediatecas",
    "sg:phone":"+34 950 33 09 43",
    "sg:postcode":"04745",
    "sg:province":"Almer\u00eda",
    "wof:name":"Ayuntamiento De La Mojonera",
    "wof:placetype":"venue"
},
  "geometry": {"coordinates":[-2.6873002052,36.7517356873],"type":"Point"}
}