{
  "type": "Feature",
  "properties": {
    "addr:full":"Calle de Buen Suceso, 18 Madrid Madrid 28008",
    "addr:housenumber":"18",
    "addr:postcode":"madrid;28008",
    "addr:street":"Calle De Buen Suceso",
    "iso:country":"ES",
    "sg:address":"Calle de Buen Suceso, 18",
    "sg:city":"Madrid",
    "sg:orig_category":"Abogados",
    "sg:phone":"+34 915 59 21 33",
    "sg:postcode":"28008",
    "sg:province":"Madrid",
    "wof:name":"Vilches Ruiz Manuel",
    "wof:placetype":"venue"
},
  "geometry": {"coordinates":[-3.718118906,40.4288406372],"type":"Point"}
}