{
  "type": "Feature",
  "properties": {
    "addr:full":"Av Voltes, 19 Bisbal D'emporda Girona 17100",
    "addr:housenumber":"19",
    "addr:postcode":"17100",
    "addr:street":"Av Voltes",
    "iso:country":"ES",
    "sg:address":"Av Voltes, 19",
    "sg:city":"Bisbal D'emporda",
    "sg:orig_category":"Supermercados Y Hipermercados",
    "sg:phone":"+34 972 64 53 05",
    "sg:postcode":"17100",
    "sg:province":"Girona",
    "wof:name":"Valvi Alimentacio I Serveis S.l.",
    "wof:placetype":"venue"
},
  "geometry": {"coordinates":[2.813131094,41.9749221802],"type":"Point"}
}