{
  "type": "Feature",
  "properties": {
    "addr:full":"Caldereria, 30 Iru\u00f1a Navarra 31001",
    "addr:housenumber":"30",
    "addr:postcode":"31001",
    "addr:street":"Caldereria",
    "iso:country":"ES",
    "sg:address":"Caldereria, 30",
    "sg:city":"Iru\u00f1a",
    "sg:orig_category":"Molduras, Junquillos, Listones Y Molduras Perforadas",
    "sg:phone":"+34 948 22 66 12",
    "sg:postcode":"31001",
    "sg:province":"Navarra",
    "wof:name":"Gonzalez Navascuez Inmaculada",
    "wof:placetype":"venue"
},
  "geometry": {"coordinates":[-1.6418652534,42.8181495667],"type":"Point"}
}