{
  "type": "Feature",
  "properties": {
    "addr:full":"Calle de Fuente Carrantona, 25 Madrid Madrid 28030",
    "addr:housenumber":"25",
    "addr:postcode":"madrid;28030",
    "addr:street":"Calle De Fuente Carrantona",
    "iso:country":"ES",
    "sg:address":"Calle de Fuente Carrantona, 25",
    "sg:city":"Madrid",
    "sg:orig_category":"Muebles Y Accesorios Para Cocinas Y Cuartos De Ba\u00d1o (al Por Menor)",
    "sg:phone":"+34 913 05 01 18",
    "sg:postcode":"28030",
    "sg:province":"Madrid",
    "wof:name":"Muebles Pomar S.l.",
    "wof:placetype":"venue"
},
  "geometry": {"coordinates":[-3.6311810017,40.4083175659],"type":"Point"}
}