{
  "type": "Feature",
  "properties": {
    "iso:country":"ES",
    "sg:address":"Carrer de Comer\u00c7, 74",
    "sg:city":"Hospitalet Llobregat",
    "sg:orig_category":"Peleter\u00cdas",
    "sg:phone":"+34 933 31 96 09",
    "sg:postcode":"08902",
    "sg:province":"Barcelona",
    "wof:name":"Pa\u00f1ella Valles Antonio",
    "wof:placetype":"venue"
},
  "geometry": {"coordinates":[2.1266999245,41.3638877869],"type":"Point"}
}