{
  "type": "Feature",
  "properties": {
    "iso:country":"ES",
    "sg:address":"Carrer de Galicia, 91",
    "sg:city":"Terrassa",
    "sg:orig_category":"Maquinaria Para Industrias Diversas",
    "sg:phone":"+34 937 85 45 70",
    "sg:postcode":"08223",
    "sg:province":"Barcelona",
    "wof:name":"Antonio Hernandez Mendez S.l.",
    "wof:placetype":"venue"
},
  "geometry": {"coordinates":[2.0134167671,41.5510673523],"type":"Point"}
}