{
  "type": "Feature",
  "properties": {
    "iso:country":"ES",
    "sg:address":"Calle de Neptuno, 3",
    "sg:city":"Ejido",
    "sg:orig_category":"Frutas Y Legumbres Frescas (al Por Mayor)",
    "sg:phone":"+34 950 48 19 55",
    "sg:postcode":"04700",
    "sg:province":"Almer\u00eda",
    "wof:name":"Daza Palmero Antonio",
    "wof:placetype":"venue"
},
  "geometry": {"coordinates":[-2.8107988834,36.7732543945],"type":"Point"}
}