{
  "type": "Feature",
  "properties": {
    "addr:full":"Pase Estacion (de La), 27 Arganda Madrid 28500",
    "addr:postcode":"28500",
    "iso:country":"ES",
    "sg:address":"Pase Estacion (de La), 27",
    "sg:city":"Arganda",
    "sg:orig_category":"Veh\u00cdculos De Ocasi\u00d3n",
    "sg:phone":"+34 918 70 01 23",
    "sg:postcode":"28500",
    "sg:province":"Madrid",
    "wof:name":"Maya Losada Miguel",
    "wof:placetype":"venue"
},
  "geometry": {"coordinates":[-3.4406979084,40.2999954224],"type":"Point"}
}