{
  "type": "Feature",
  "properties": {
    "addr:full":"Calle de Eras, S/n Payo Salamanca 37524",
    "addr:housenumber":"s",
    "addr:postcode":"37524",
    "addr:street":"Calle De Eras;/ N Payo",
    "iso:country":"ES",
    "sg:address":"Calle de Eras, S/n",
    "sg:city":"Payo",
    "sg:orig_category":"Centros De Educaci\u00d3n Especial",
    "sg:phone":"+34 923 48 69 04",
    "sg:postcode":"37524",
    "sg:province":"Salamanca",
    "wof:name":"C.r.a. Alto Agueda",
    "wof:placetype":"venue"
},
  "geometry": {"coordinates":[-6.7283592224,40.2857208252],"type":"Point"}
}