{
  "type": "Feature",
  "properties": {
    "addr:full":"Avda Constitucion (la), 25 Sevilla Sevilla 41004",
    "addr:housenumber":"25",
    "addr:postcode":"41004",
    "addr:street":"Avda Constitucion La",
    "iso:country":"ES",
    "sg:address":"Avda Constitucion (la), 25",
    "sg:city":"Sevilla",
    "sg:orig_category":"Sociedades, Compa\u00d1\u00cdas Aseguradoras",
    "sg:phone":"+34 954 22 93 86",
    "sg:postcode":"41004",
    "sg:province":"Sevilla",
    "sg:website":"www.santalucia.es",
    "wof:name":"Santa Lucia S.a.",
    "wof:placetype":"venue"
},
  "geometry": {"coordinates":[-5.9933991432,37.3831863403],"type":"Point"}
}