{
  "type": "Feature",
  "properties": {
    "addr:full":"Calle de Uncastillo, 4 Zaragoza Zaragoza 50008",
    "addr:housenumber":"4",
    "addr:postcode":"50008",
    "addr:street":"Calle De Uncastillo",
    "iso:country":"ES",
    "sg:address":"Calle de Uncastillo, 4",
    "sg:city":"Zaragoza",
    "sg:orig_category":"Laboratorios Y Cl\u00cdnicas Veterinarias",
    "sg:phone":"+34 976 59 86 53",
    "sg:postcode":"50008",
    "sg:province":"Zaragoza",
    "wof:name":"Terren Zaldivar Alfonso",
    "wof:placetype":"venue"
},
  "geometry": {"coordinates":[-0.8787077069,41.6418762207],"type":"Point"}
}