{
  "type": "Feature",
  "properties": {
    "addr:full":"Calle de Via Marciala, 15 Utrera Sevilla 41710",
    "addr:housenumber":"15",
    "addr:postcode":"41710",
    "addr:street":"Calle De Via Marciala",
    "iso:country":"ES",
    "sg:address":"Calle de Via Marciala, 15",
    "sg:city":"Utrera",
    "sg:orig_category":"Asociaciones Humanitarias, De Cooperaci\u00d3n, De Acci\u00d3n Social",
    "sg:phone":"+34 954 86 14 34",
    "sg:postcode":"41710",
    "sg:province":"Sevilla",
    "wof:name":"Asociacion De Familiares Y Amigos De Drogodependientes De Utrera",
    "wof:placetype":"venue"
},
  "geometry": {"coordinates":[-5.7859516144,37.1817092896],"type":"Point"}
}