{
  "type": "Feature",
  "properties": {
    "iso:country":"ES",
    "sg:address":"Crta. Jerez De Los Caballeros, Km. 0089,5",
    "sg:city":"Fregenal Sierra",
    "sg:orig_category":"Cr\u00cda De Cerdos",
    "sg:phone":"+34 924 14 80 09",
    "sg:postcode":"06340",
    "sg:province":"Badajoz",
    "wof:name":"Agropecuaria Dehesa De Pajares S.a.",
    "wof:placetype":"venue"
},
  "geometry": {"coordinates":[-6.970284,38.878597],"type":"Point"}
}