{
  "type": "Feature",
  "properties": {
    "addr:full":"Av Catalunya, 38 Cerdanyola Valles Barcelona 08290",
    "addr:housenumber":"38",
    "addr:postcode":"08290",
    "addr:street":"Av Catalunya;Valles Barcelona",
    "iso:country":"ES",
    "sg:address":"Av Catalunya, 38",
    "sg:city":"Cerdanyola Valles",
    "sg:orig_category":"Bancos",
    "sg:phone":"+34 936 92 02 48",
    "sg:postcode":"08290",
    "sg:province":"Barcelona",
    "wof:name":"Deutsche Bank S.a.e.",
    "wof:placetype":"venue"
},
  "geometry": {"coordinates":[2.1456251144,41.4929504395],"type":"Point"}
}