{
  "type": "Feature",
  "properties": {
    "iso:country":"ES",
    "sg:address":"Calle de Ecuador, 4",
    "sg:city":"Toledo",
    "sg:orig_category":"Cajas De Ahorro",
    "sg:phone":"+34 925 21 63 16",
    "sg:postcode":"45004",
    "sg:province":"Toledo",
    "sg:website":"www.lacaixa.es",
    "wof:name":"Caixa D'estalvis I Pensions De Barcelona",
    "wof:placetype":"venue"
},
  "geometry": {"coordinates":[-4.0296559334,39.8668861389],"type":"Point"}
}