{
  "type": "Feature",
  "properties": {
    "iso:country":"ES",
    "sg:address":"Monjas Altas, 10",
    "sg:city":"Torredonjimeno",
    "sg:orig_category":"Laboratorios Y Trabajos De Fotograf\u00cda, V\u00cddeo Y Cine",
    "sg:phone":"+34 953 57 14 92",
    "sg:postcode":"23650",
    "sg:province":"Ja\u00e9n",
    "wof:name":"Jose Carlos Gonzalez Gonzalez C.b.",
    "wof:placetype":"venue"
},
  "geometry": {"coordinates":[-3.957916975,37.7653999329],"type":"Point"}
}