{
  "type": "Feature",
  "properties": {
    "addr:full":"Calle de Reyes Catolicos, 13 Cordoba C\u00f3rdoba 14001",
    "addr:housenumber":"13",
    "addr:postcode":"14001",
    "addr:street":"Calle De Reyes Catolicos;Co\u0301Rdoba",
    "iso:country":"ES",
    "sg:address":"Calle de Reyes Catolicos, 13",
    "sg:city":"Cordoba",
    "sg:orig_category":"M\u00c9dicos: Cirug\u00cda Ortop\u00c9dica Y Traumatolog\u00cda",
    "sg:phone":"+34 957 47 00 12",
    "sg:postcode":"14001",
    "sg:province":"C\u00f3rdoba",
    "wof:name":"Gala Velasco Manuel",
    "wof:placetype":"venue"
},
  "geometry": {"coordinates":[-4.7811889648,37.8892402649],"type":"Point"}
}