{
  "type": "Feature",
  "properties": {
    "iso:country":"ES",
    "sg:address":"Calle de Preciados, 42",
    "sg:city":"Madrid",
    "sg:orig_category":"Contables",
    "sg:phone":"+34 915 47 37 91",
    "sg:postcode":"28013",
    "sg:province":"Madrid",
    "wof:name":"Hueso Cruz Quintiliano",
    "wof:placetype":"venue"
},
  "geometry": {"coordinates":[-3.7073259354,40.4199066162],"type":"Point"}
}