{
  "type": "Feature",
  "properties": {
    "addr:full":"C/ Formiga, 5 Banyoles Girona 17820",
    "addr:housenumber":"5",
    "addr:postcode":"17820",
    "addr:street":"C / Formiga",
    "iso:country":"ES",
    "sg:address":"C/ Formiga, 5",
    "sg:city":"Banyoles",
    "sg:orig_category":"Producci\u00d3n, Distribuci\u00d3n De Electricidad",
    "sg:phone":"+34 972 57 12 87",
    "sg:postcode":"17820",
    "sg:province":"Girona",
    "wof:name":"Robert Ferrer Miguel",
    "wof:placetype":"venue"
},
  "geometry": {"coordinates":[2.7725100517,42.111541748],"type":"Point"}
}