{
  "type": "Feature",
  "properties": {
    "iso:country":"ES",
    "sg:address":"Rua Castro, 14",
    "sg:city":"Betanzos",
    "sg:orig_category":"Bisuter\u00cda, Joyer\u00cda, Relojer\u00cda (al Por Menor)",
    "sg:phone":"+34 981 77 42 92",
    "sg:postcode":"15300",
    "sg:province":"La Coru\u00f1a",
    "wof:name":"Otero Insua Francisco Javier",
    "wof:placetype":"venue"
},
  "geometry": {"coordinates":[-8.2105913162,43.2806167603],"type":"Point"}
}