{
  "type": "Feature",
  "properties": {
    "iso:country":"ES",
    "sg:address":"Calle de Bodegas, S/n",
    "sg:city":"Quintanilla Del Molar",
    "sg:orig_category":"Mataderos Y Talleres De Despiezado",
    "sg:phone":"+34 980 66 65 12",
    "sg:postcode":"47673",
    "sg:province":"Valladolid",
    "wof:name":"Carnicas Quintanilla S.l",
    "wof:placetype":"venue"
},
  "geometry": {"coordinates":[-5.4481787682,41.9892959595],"type":"Point"}
}