{
  "type": "Feature",
  "properties": {
    "addr:full":"Avda Picos De Europa, S/n Alcayna Murcia 30500",
    "addr:housenumber":"s",
    "addr:postcode":"30500",
    "addr:street":"Avda Picos De Europa;/ N",
    "iso:country":"ES",
    "sg:address":"Avda Picos De Europa, S/n",
    "sg:city":"Alcayna",
    "sg:orig_category":"Doctores En Medicina",
    "sg:phone":"+34 968 61 99 03",
    "sg:postcode":"30500",
    "sg:province":"Murcia",
    "wof:name":"Verdu De La Vieja Gerardo",
    "wof:placetype":"venue"
},
  "geometry": {"coordinates":[-1.2119740248,38.0535736084],"type":"Point"}
}