{
  "type": "Feature",
  "properties": {
    "iso:country":"ES",
    "sg:address":"Calle de San Cayetano, 81",
    "sg:city":"Madrid",
    "sg:orig_category":"Comercio De Cuadros, L\u00c1minas Y Reproducciones De Obras De Arte",
    "sg:phone":"+34 915 39 35 72",
    "sg:postcode":"28005",
    "sg:province":"Madrid",
    "wof:name":"Diez Alonso Beatriz",
    "wof:placetype":"venue"
},
  "geometry": {"coordinates":[-3.7073190212,40.4090995789],"type":"Point"}
}