{
  "type": "Feature",
  "properties": {
    "addr:full":"Calle de Roma, 3 Madrid Madrid 28028",
    "addr:housenumber":"3",
    "addr:postcode":"28028",
    "addr:street":"Calle De Roma",
    "iso:country":"ES",
    "sg:address":"Calle de Roma, 3",
    "sg:city":"Madrid",
    "sg:orig_category":"Institutos De Belleza",
    "sg:phone":"+34 917 25 79 85",
    "sg:postcode":"28028",
    "sg:province":"Madrid",
    "wof:name":"Rodriguez Labrador Catalina",
    "wof:placetype":"venue"
},
  "geometry": {"coordinates":[-3.6666960716,40.4310913086],"type":"Point"}
}