{
  "type": "Feature",
  "properties": {
    "iso:country":"ES",
    "sg:address":"Calle de Fondabos, 17",
    "sg:city":"Jaca",
    "sg:classifiers":[
        {
            "category":"Taxi",
            "type":"Transportation"
        }
    ],
    "sg:phone":"+34 974 36 23 58",
    "sg:postcode":"22700",
    "sg:province":"Huesca",
    "wof:name":"Iguacel Estallo Luis",
    "wof:placetype":"venue"
},
  "geometry": {"coordinates":[-0.5519520044,42.5658493042],"type":"Point"}
}