{
  "type": "Feature",
  "properties": {
    "iso:country":"ES",
    "sg:address":"Calle de Reyes Catolicos, 16",
    "sg:city":"Toledo",
    "sg:orig_category":"Art\u00cdculos De Regalo (al Por Menor)",
    "sg:phone":"+34 925 21 18 09",
    "sg:postcode":"45002",
    "sg:province":"Toledo",
    "wof:name":"Serrano Fernandez Jesus",
    "wof:placetype":"venue"
},
  "geometry": {"coordinates":[-4.0311980247,39.8580818176],"type":"Point"}
}