{
  "type": "Feature",
  "properties": {
    "iso:country":"ES",
    "sg:address":"Avda Guijar (del), 26",
    "sg:city":"Arganda",
    "sg:orig_category":"Metalurgia",
    "sg:phone":"+34 918 71 47 06",
    "sg:postcode":"28500",
    "sg:province":"Madrid",
    "sg:website":"www.leandrocallaba.com",
    "wof:name":"Leandro Callaba S.l.",
    "wof:placetype":"venue"
},
  "geometry": {"coordinates":[-3.460777998,40.3151550293],"type":"Point"}
}