{
  "type": "Feature",
  "properties": {
    "iso:country":"ES",
    "sg:address":"Calle de Rodillo, 18",
    "sg:city":"Salamanca",
    "sg:orig_category":"Mec\u00c1nico Del Autom\u00d3vil",
    "sg:phone":"+34 923 26 16 94",
    "sg:postcode":"37001",
    "sg:province":"Salamanca",
    "wof:name":"Martin Sanchez Juan Carlos",
    "wof:placetype":"venue"
},
  "geometry": {"coordinates":[-5.6600370407,40.9622306824],"type":"Point"}
}