{
  "type": "Feature",
  "properties": {
    "iso:country":"ES",
    "sg:address":"Buenos Aires, 2",
    "sg:city":"Laracha",
    "sg:orig_category":"Molduras, Junquillos, Listones Y Molduras Perforadas",
    "sg:phone":"+34 981 60 51 20",
    "sg:postcode":"15145",
    "sg:province":"La Coru\u00f1a",
    "wof:name":"Rodriguez Marino Jose",
    "wof:placetype":"venue"
},
  "geometry": {"coordinates":[-8.5750217438,43.1730537415],"type":"Point"}
}