{
  "type": "Feature",
  "properties": {
    "iso:country":"ES",
    "sg:address":"Carr Sant Jaume, 2",
    "sg:city":"Blanes",
    "sg:orig_category":"Agencias Y Agentes Comerciales, Representantes",
    "sg:phone":"+34 972 35 35 20",
    "sg:postcode":"17300",
    "sg:province":"Girona",
    "wof:name":"Pastre  Andre",
    "wof:placetype":"venue"
},
  "geometry": {"coordinates":[2.7913379669,41.6730613708],"type":"Point"}
}