{
  "type": "Feature",
  "properties": {
    "addr:full":"Carrer de Pompeu Fabra, S/n Senia Tarragona 43560",
    "addr:housenumber":"s / n",
    "addr:postcode":"43560",
    "addr:street":"Carrer De Pompeu",
    "iso:country":"ES",
    "sg:address":"Carrer de Pompeu Fabra, S/n",
    "sg:city":"Senia",
    "sg:orig_category":"Centros De Educaci\u00d3n Especial",
    "sg:phone":"+34 977 71 32 65",
    "sg:postcode":"43560",
    "sg:province":"Tarragona",
    "wof:name":"Colegio Nacional Mixto Jaime I",
    "wof:placetype":"venue"
},
  "geometry": {"coordinates":[0.2803849876,40.6337738037],"type":"Point"}
}