{
  "type": "Feature",
  "properties": {
    "addr:full":"Calle de Belchite, 6 Logro\u00f1o La Rioja 26003",
    "addr:housenumber":"6",
    "addr:postcode":"26003",
    "addr:street":"Calle De Belchite;Rioja",
    "iso:country":"ES",
    "sg:address":"Calle de Belchite, 6",
    "sg:city":"Logro\u00f1o",
    "sg:orig_category":"Alimentaci\u00d3n General (al Por Menor)",
    "sg:phone":"+34 941 23 78 67",
    "sg:postcode":"26003",
    "sg:province":"La Rioja",
    "wof:name":"Fernandez Gil Valentin",
    "wof:placetype":"venue"
},
  "geometry": {"coordinates":[-2.4434528351,42.4614143372],"type":"Point"}
}