{
  "type": "Feature",
  "properties": {
    "iso:country":"ES",
    "sg:address":"Calle de Villafranca, 8",
    "sg:city":"Le\u00f3n",
    "sg:orig_category":"Charcuter\u00cdas (al Por Mayor)",
    "sg:phone":"+34 987 21 33 41",
    "sg:postcode":"24001",
    "sg:province":"Le\u00f3n",
    "wof:name":"Entrepe\u00f1as S.l.",
    "wof:placetype":"venue"
},
  "geometry": {"coordinates":[-5.5754117966,42.5959854126],"type":"Point"}
}