{
  "type": "Feature",
  "properties": {
    "addr:full":"Pase Cientifico Gabriel Ciscar, 20 Flota Murcia 30007",
    "addr:housenumber":"20",
    "addr:postcode":"30007",
    "addr:street":"Ciscar",
    "iso:country":"ES",
    "sg:address":"Pase Cientifico Gabriel Ciscar, 20",
    "sg:city":"Flota",
    "sg:orig_category":"Centros Empresariales",
    "sg:phone":"+34 968 23 69 50",
    "sg:postcode":"30007",
    "sg:province":"Murcia",
    "wof:name":"Urbaser S.a.",
    "wof:placetype":"venue"
},
  "geometry": {"coordinates":[-1.1142389774,37.9970092773],"type":"Point"}
}