{
  "type": "Feature",
  "properties": {
    "addr:full":"Po. Olmos, S/n Monteprincipe Madrid 28668",
    "addr:housenumber":"s / n",
    "addr:postcode":"28668",
    "addr:street":"Olmos",
    "iso:country":"ES",
    "sg:address":"Po. Olmos, S/n",
    "sg:city":"Monteprincipe",
    "sg:orig_category":"Compraventa De Antig\u00dcedades",
    "sg:phone":"+34 913 52 19 25",
    "sg:postcode":"28668",
    "sg:province":"Madrid",
    "wof:name":"Compras-ventas Agulla Arranz S. A.",
    "wof:placetype":"venue"
},
  "geometry": {"coordinates":[-3.8429419994,40.4011039734],"type":"Point"}
}