{
  "type": "Feature",
  "properties": {
    "addr:full":"Calle de Juan Carlos I, 5 Valverde Leganes Badajoz 06130",
    "addr:housenumber":"5",
    "addr:postcode":"06130",
    "addr:street":"Calle De Juan Carlos I",
    "iso:country":"ES",
    "sg:address":"Calle de Juan Carlos I, 5",
    "sg:city":"Valverde Leganes",
    "sg:orig_category":"Autob\u00das (explotaci\u00d3n Y Servicios De)",
    "sg:phone":"+34 924 49 61 17",
    "sg:postcode":"06130",
    "sg:province":"Badajoz",
    "wof:name":"Lopez Mu\u00f1oz Manuel",
    "wof:placetype":"venue"
},
  "geometry": {"coordinates":[-6.9803109169,38.6700706482],"type":"Point"}
}