{
  "type": "Feature",
  "properties": {
    "iso:country":"ES",
    "sg:address":"Calle de Constanza De Castro, 2",
    "sg:city":"Viveiro",
    "sg:orig_category":"Fabricaci\u00d3n, Venta De Cuadros, Accesorios Para Enmarcar",
    "sg:phone":"+34 982 55 03 85",
    "sg:postcode":"27850",
    "sg:province":"Lugo",
    "wof:name":"Perez Docal Maria Del Carmen",
    "wof:placetype":"venue"
},
  "geometry": {"coordinates":[-7.5941648483,43.6622047424],"type":"Point"}
}