{
  "type": "Feature",
  "properties": {
    "addr:full":"Avda Antonio Ramos Carratala, S/n Alacant Alicante 03015",
    "addr:housenumber":"s / n",
    "addr:postcode":"03015",
    "addr:street":"Avda Antonio Ramos Carratala",
    "iso:country":"ES",
    "sg:address":"Avda Antonio Ramos Carratala, S/n",
    "sg:city":"Alacant",
    "sg:orig_category":"Juegos Y Juguetes (al Por Menor)",
    "sg:phone":"+34 965 15 77 79",
    "sg:postcode":"03015",
    "sg:province":"Alicante",
    "wof:name":"Bowling Sur S.a.",
    "wof:placetype":"venue"
},
  "geometry": {"coordinates":[-0.4619489908,38.369178772],"type":"Point"}
}