{
  "type": "Feature",
  "properties": {
    "addr:full":"Carrer de Miquel Biada, 62 Mataro Barcelona 08302",
    "addr:housenumber":"62",
    "addr:postcode":"08302",
    "addr:street":"Carrer De Miquel Biada",
    "iso:country":"ES",
    "sg:address":"Carrer de Miquel Biada, 62",
    "sg:city":"Mataro",
    "sg:orig_category":"M\u00c9dicos: Estomatolog\u00cda",
    "sg:phone":"+34 937 98 44 39",
    "sg:postcode":"08302",
    "sg:province":"Barcelona",
    "wof:name":"Palacin Feixa Antoni",
    "wof:placetype":"venue"
},
  "geometry": {"coordinates":[2.4349820614,41.537147522],"type":"Point"}
}