{
  "type": "Feature",
  "properties": {
    "addr:full":"Calle de Zenit, 18 Madrid Madrid 28023",
    "addr:housenumber":"18",
    "addr:postcode":"madrid;28023",
    "addr:street":"Calle De Zenit",
    "iso:country":"ES",
    "sg:address":"Calle de Zenit, 18",
    "sg:city":"Madrid",
    "sg:orig_category":"Arquitectos",
    "sg:phone":"+34 913 07 13 23",
    "sg:postcode":"28023",
    "sg:province":"Madrid",
    "wof:name":"Mendoza De Arroquia Aurelio",
    "wof:placetype":"venue"
},
  "geometry": {"coordinates":[-3.7902536392,40.463218689],"type":"Point"}
}