{
  "type": "Feature",
  "properties": {
    "addr:full":"Calle de Siro Alonso De La Huerta, 24 Bembibre Le\u00f3n 24300",
    "addr:housenumber":"24",
    "addr:postcode":"24300",
    "addr:street":"Calle De Siro Alonso De La Huerta;Leo\u0301N",
    "iso:country":"ES",
    "sg:address":"Calle de Siro Alonso De La Huerta, 24",
    "sg:city":"Bembibre",
    "sg:orig_category":"Asilos De Ancianos. Centros Privados",
    "sg:phone":"+34 987 51 11 31",
    "sg:postcode":"24300",
    "sg:province":"Le\u00f3n",
    "wof:name":"Clecer S.a.",
    "wof:placetype":"venue"
},
  "geometry": {"coordinates":[-6.4095439911,42.6139221191],"type":"Point"}
}