{
  "type": "Feature",
  "properties": {
    "addr:full":"Carrer de Ramon Llull, 18 Cardedeu Barcelona 08440",
    "addr:housenumber":"18",
    "addr:postcode":"08440",
    "addr:street":"Carrer De Ramon Llull",
    "iso:country":"ES",
    "sg:address":"Carrer de Ramon Llull, 18",
    "sg:city":"Cardedeu",
    "sg:orig_category":"Empresas De Carpinter\u00cda Met\u00c1lica",
    "sg:phone":"+34 938 46 24 57",
    "sg:postcode":"08440",
    "sg:province":"Barcelona",
    "wof:name":"Rico Cela Tomas",
    "wof:placetype":"venue"
},
  "geometry": {"coordinates":[2.3573009968,41.6390190125],"type":"Point"}
}