{
  "type": "Feature",
  "properties": {
    "addr:full":"Carrer de Repartidor, 29 Barcelona Barcelona 08023",
    "addr:housenumber":"29",
    "addr:postcode":"08023",
    "addr:street":"Carrer De Repartidor",
    "iso:country":"ES",
    "sg:address":"Carrer de Repartidor, 29",
    "sg:city":"Barcelona",
    "sg:orig_category":"Venta, Localizaci\u00d3n, Reparaci\u00d3n De Material E Instrumental M\u00c9dico",
    "sg:phone":"+34 932 84 67 52",
    "sg:postcode":"08023",
    "sg:province":"Barcelona",
    "wof:name":"Gomsoltec S.l.l.",
    "wof:placetype":"venue"
},
  "geometry": {"coordinates":[2.148250103,41.4116020203],"type":"Point"}
}