{
  "type": "Feature",
  "properties": {
    "addr:full":"Poli Poligon 06, S/n Picassent Valencia 46220",
    "addr:housenumber":"06 s / n",
    "addr:postcode":"46220",
    "addr:street":"Poligon",
    "iso:country":"ES",
    "sg:address":"Poli Poligon 06, S/n",
    "sg:city":"Picassent",
    "sg:orig_category":"Cueros Y Pieles (al Por Mayor)",
    "sg:phone":"+34 961 24 01 19",
    "sg:postcode":"46220",
    "sg:province":"Valencia",
    "wof:name":"Teneria Industrial Valenciana S. A.",
    "wof:placetype":"venue"
},
  "geometry": {"coordinates":[-0.4595290124,39.3631401062],"type":"Point"}
}