{
  "type": "Feature",
  "properties": {
    "addr:full":"Calle de Julian Romea, 2 Madrid Madrid 28003",
    "addr:housenumber":"2",
    "addr:postcode":"28003",
    "addr:street":"Calle De Julian Romea",
    "iso:country":"ES",
    "sg:address":"Calle de Julian Romea, 2",
    "sg:city":"Madrid",
    "sg:orig_category":"Juegos Y Juguetes (al Por Menor)",
    "sg:phone":"+34 915 33 50 37",
    "sg:postcode":"28003",
    "sg:province":"Madrid",
    "wof:name":"Sanz Miranda Fernando",
    "wof:placetype":"venue"
},
  "geometry": {"coordinates":[-3.7129240036,40.4427719116],"type":"Point"}
}