{
  "type": "Feature",
  "properties": {
    "addr:full":"Calle de Padre Melchor Prieto, 22 Burgos Burgos 09005",
    "addr:housenumber":"22",
    "addr:postcode":"09005",
    "addr:street":"Calle De Padre Melchor Prieto",
    "iso:country":"ES",
    "sg:address":"Calle de Padre Melchor Prieto, 22",
    "sg:city":"Burgos",
    "sg:orig_category":"Empresas De Desmonte",
    "sg:phone":"+34 947 22 87 10",
    "sg:postcode":"09005",
    "sg:province":"Burgos",
    "wof:name":"Ni\u00f1o Gomez Antonio",
    "wof:placetype":"venue"
},
  "geometry": {"coordinates":[-3.6987309456,42.3481636047],"type":"Point"}
}