{
  "type": "Feature",
  "properties": {
    "iso:country":"ES",
    "sg:address":"Calle de Ciscar, 61",
    "sg:city":"Valencia",
    "sg:orig_category":"Asesor\u00cdas Y Estudios Financieros",
    "sg:phone":"+34 963 34 10 09",
    "sg:postcode":"46005",
    "sg:province":"Valencia",
    "wof:name":"Staff 3 Asesores S.a.",
    "wof:placetype":"venue"
},
  "geometry": {"coordinates":[-0.3637200892,39.4632797241],"type":"Point"}
}