{
  "type": "Feature",
  "properties": {
    "iso:country":"ES",
    "sg:address":"Calle de Pontevedra, 15",
    "sg:city":"Esfarrapada",
    "sg:orig_category":"Institutos De Belleza",
    "sg:phone":"+34 986 34 96 25",
    "sg:postcode":"36470",
    "sg:province":"Pontevedra",
    "wof:name":"Tmt C.b.",
    "wof:placetype":"venue"
},
  "geometry": {"coordinates":[-8.5578489304,42.1026191711],"type":"Point"}
}