{
  "type": "Feature",
  "properties": {
    "iso:country":"ES",
    "sg:address":"Calle de Juan Manuel Duran Gonzalez, 47",
    "sg:city":"Palmas De Gran Canaria",
    "sg:orig_category":"Cl\u00cdnicas Dentales",
    "sg:phone":"+34 928 22 76 19",
    "sg:postcode":"35010",
    "sg:province":"Las Palmas",
    "wof:name":"Garcia Ubierna Jesus",
    "wof:placetype":"venue"
},
  "geometry": {"coordinates":[-15.4350690842,28.1351585388],"type":"Point"}
}