{
  "type": "Feature",
  "properties": {
    "iso:country":"ES",
    "sg:address":"Avda Colon, 2",
    "sg:city":"Gines",
    "sg:orig_category":"Cajas De Ahorro",
    "sg:phone":"+34 954 71 92 17",
    "sg:postcode":"41960",
    "sg:province":"Sevilla",
    "sg:website":"www.unicaja.es",
    "wof:name":"Unicaja",
    "wof:placetype":"venue"
},
  "geometry": {"coordinates":[-6.0804271698,37.3890113831],"type":"Point"}
}