{
  "type": "Feature",
  "properties": {
    "iso:country":"ES",
    "sg:address":"Pla\u00c7 Escorxador, S/n",
    "sg:city":"Figueres",
    "sg:orig_category":"Art\u00cdculos De Regalo (al Por Menor)",
    "sg:phone":"+34 972 50 34 74",
    "sg:postcode":"17600",
    "sg:province":"Girona",
    "wof:name":"Amieva Serra David",
    "wof:placetype":"venue"
},
  "geometry": {"coordinates":[2.9625587463,42.2720336914],"type":"Point"}
}