{
  "type": "Feature",
  "properties": {
    "iso:country":"ES",
    "sg:address":"Carr Enric Granados, 1",
    "sg:city":"Bell-lloc D'urgell",
    "sg:orig_category":"Ferreter\u00cda Artesanal",
    "sg:phone":"+34 973 56 05 25",
    "sg:postcode":"25220",
    "sg:province":"Lleida",
    "wof:name":"Hurtado Marcos Valentin",
    "wof:placetype":"venue"
},
  "geometry": {"coordinates":[0.6213129759,41.6203918457],"type":"Point"}
}