{
  "type": "Feature",
  "properties": {
    "iso:country":"ES",
    "sg:address":"Cmno Villahizan, S/n",
    "sg:city":"Villadiego",
    "sg:orig_category":"Material Y Herramientas Agr\u00cdcolas",
    "sg:phone":"+34 947 36 03 53",
    "sg:postcode":"09120",
    "sg:province":"Burgos",
    "wof:name":"Fuente Bustillo Eduardo De La",
    "wof:placetype":"venue"
},
  "geometry": {"coordinates":[-4.0148591995,42.5139503479],"type":"Point"}
}