{
  "type": "Feature",
  "properties": {
    "addr:full":"Avgd Omet Avda., S/n Picassent Valencia 46220",
    "addr:postcode":"46220",
    "addr:street":"Avda. S / N",
    "iso:country":"ES",
    "sg:address":"Avgd Omet Avda., S/n",
    "sg:city":"Picassent",
    "sg:orig_category":"Aparatos E Instalaci\u00d3n De Regad\u00cdos",
    "sg:phone":"+34 961 23 02 43",
    "sg:postcode":"46220",
    "sg:province":"Valencia",
    "wof:name":"Distribuciones Agricolas Raul Lopez S. L.",
    "wof:placetype":"venue"
},
  "geometry": {"coordinates":[-0.4595290124,39.3631401062],"type":"Point"}
}