{
  "type": "Feature",
  "properties": {
    "addr:full":"C/ Sant Roc, 24 Manacor Islas Baleares 07500",
    "addr:housenumber":"24",
    "addr:postcode":"07500",
    "addr:street":"C / Sant Roc",
    "iso:country":"ES",
    "sg:address":"C/ Sant Roc, 24",
    "sg:city":"Manacor",
    "sg:orig_category":"Art\u00cdculos De Decoraci\u00d3n",
    "sg:phone":"+34 971 55 13 53",
    "sg:postcode":"07500",
    "sg:province":"Islas Baleares",
    "wof:name":"Francisco Bennassar Mesquida-sebastian Riera Gelabert Cdad",
    "wof:placetype":"venue"
},
  "geometry": {"coordinates":[3.2104940414,39.5741462708],"type":"Point"}
}