{
  "type": "Feature",
  "properties": {
    "iso:country":"ES",
    "sg:address":"Carr Muralla, 30",
    "sg:city":"Blanes",
    "sg:orig_category":"Inmobiliaria (agencias)",
    "sg:phone":"+34 972 35 57 44",
    "sg:postcode":"17300",
    "sg:province":"Girona",
    "sg:website":"www.comasserveisimmopliaris",
    "wof:name":"Born Real-estate S.l.",
    "wof:placetype":"venue"
},
  "geometry": {"coordinates":[2.7905459404,41.6737098694],"type":"Point"}
}