{
  "type": "Feature",
  "properties": {
    "iso:country":"ES",
    "sg:address":"Carr Elvis Presley, 31",
    "sg:city":"Badalona",
    "sg:orig_category":"Colorantes, Colores Y Pigmentos (fabricaci\u00d3n, Al Por Mayor)",
    "sg:phone":"+34 934 90 41 09",
    "sg:postcode":"08915",
    "sg:province":"Barcelona",
    "wof:name":"Molto Reig S. A.",
    "wof:placetype":"venue"
},
  "geometry": {"coordinates":[2.2388811111,41.463760376],"type":"Point"}
}