{
  "type": "Feature",
  "properties": {
    "addr:full":"Avda Extremadura, 121 Albuera Badajoz 06170",
    "addr:housenumber":"121",
    "addr:postcode":"06170",
    "addr:street":"Avda Extremadura",
    "iso:country":"ES",
    "sg:address":"Avda Extremadura, 121",
    "sg:city":"Albuera",
    "sg:orig_category":"Producci\u00d3n, Venta De Productos De Agricultura Biol\u00d3gica",
    "sg:phone":"+34 924 48 01 06",
    "sg:postcode":"06170",
    "sg:province":"Badajoz",
    "wof:name":"Industrias Caleyas S.l.",
    "wof:placetype":"venue"
},
  "geometry": {"coordinates":[-6.824037075,38.7159004211],"type":"Point"}
}