{
  "type": "Feature",
  "properties": {
    "iso:country":"ES",
    "sg:address":"Carr Doctor Sarrat, 5",
    "sg:city":"Gimenells",
    "sg:orig_category":"Asociaciones, Organismos Culturales Y Socioeducativos",
    "sg:phone":"+34 973 74 84 10",
    "sg:postcode":"25112",
    "sg:province":"Lleida",
    "wof:name":"Asociacion Local De Jubilados Y Pensionistas San Isidro De Gimenells",
    "wof:placetype":"venue"
},
  "geometry": {"coordinates":[0.3897536099,41.6526832581],"type":"Point"}
}