{
  "type": "Feature",
  "properties": {
    "iso:country":"ES",
    "sg:address":"Carretera De Don Benito-guadalupe, Km. 0003,0",
    "sg:city":"Don Benito",
    "sg:orig_category":"Asociaciones, Organismos Culturales Y Socioeducativos",
    "sg:phone":"+34 924 80 00 13",
    "sg:postcode":"06400",
    "sg:province":"Badajoz",
    "wof:name":"Club Las Arenas",
    "wof:placetype":"venue"
},
  "geometry": {"coordinates":[-5.8639888763,38.9548797607],"type":"Point"}
}