{
  "type": "Feature",
  "properties": {
    "iso:country":"ES",
    "sg:address":"Calle de San Vicente De Paul, 18",
    "sg:city":"Zaragoza",
    "sg:orig_category":"Abogados",
    "sg:phone":"+34 976 20 54 18",
    "sg:postcode":"50001",
    "sg:province":"Zaragoza",
    "wof:name":"Baigorri Rived Virginia",
    "wof:placetype":"venue"
},
  "geometry": {"coordinates":[-0.875698328,41.6524620056],"type":"Point"}
}