{
  "type": "Feature",
  "properties": {
    "iso:country":"ES",
    "sg:address":"Calle de Jalea, 5",
    "sg:city":"Palma",
    "sg:orig_category":"Productos Qu\u00cdmicos (fabricaci\u00d3n, Al Por Mayor)",
    "sg:phone":"+34 968 16 55 49",
    "sg:postcode":"30593",
    "sg:province":"Murcia",
    "wof:name":"Quimicos Marmenor S.l.",
    "wof:placetype":"venue"
},
  "geometry": {"coordinates":[-0.9472910166,37.6822128296],"type":"Point"}
}