{
  "type": "Feature",
  "properties": {
    "addr:full":"Rua Mosteiro De Monfero, 25 Ferrol La Coru\u00f1a 15403",
    "addr:housenumber":"25",
    "addr:postcode":"15403",
    "addr:street":"Rua Mosteiro De Monfero;La Corun\u0303A",
    "iso:country":"ES",
    "sg:address":"Rua Mosteiro De Monfero, 25",
    "sg:city":"Ferrol",
    "sg:orig_category":"Construcci\u00d3n Mec\u00c1nica",
    "sg:phone":"+34 981 32 19 73",
    "sg:postcode":"15403",
    "sg:province":"La Coru\u00f1a",
    "wof:name":"Promociones Porsan Y Fernandez S.l",
    "wof:placetype":"venue"
},
  "geometry": {"coordinates":[-8.2244148254,43.4898223877],"type":"Point"}
}