{
  "type": "Feature",
  "properties": {
    "addr:full":"Avda Alemania (de), 7 Caceres C\u00e1ceres 10001",
    "addr:housenumber":"7",
    "addr:postcode":"10001",
    "addr:street":"Avda Alemania De;Ca\u0301Ceres",
    "iso:country":"ES",
    "sg:address":"Avda Alemania (de), 7",
    "sg:city":"Caceres",
    "sg:orig_category":"Agencias Y Agentes Comerciales, Representantes",
    "sg:phone":"+34 927 23 93 00",
    "sg:postcode":"10001",
    "sg:province":"C\u00e1ceres",
    "wof:name":"Jimenez Grajera Valeriano",
    "wof:placetype":"venue"
},
  "geometry": {"coordinates":[-6.3798289299,39.4673690796],"type":"Point"}
}