{
  "type": "Feature",
  "properties": {
    "addr:full":"Plaz Constitucion (de La), 4 San Martin Del Tesorillo C\u00e1diz 11340",
    "addr:postcode":"11340",
    "addr:street":"San Martin Del Tesorillo Ca\u0301Diz",
    "iso:country":"ES",
    "sg:address":"Plaz Constitucion (de La), 4",
    "sg:city":"San Martin Del Tesorillo",
    "sg:orig_category":"Cajas De Ahorro",
    "sg:phone":"+34 956 61 86 99",
    "sg:postcode":"11340",
    "sg:province":"C\u00e1diz",
    "wof:name":"Caixa D'estalvis I Pensions De Barcelona",
    "wof:placetype":"venue"
},
  "geometry": {"coordinates":[-5.3195900917,36.3414535522],"type":"Point"}
}