{
  "type": "Feature",
  "properties": {
    "iso:country":"ES",
    "sg:address":"Calle de Pedro Jacoste Garde, 8",
    "sg:city":"Tudela",
    "sg:orig_category":"Delegados, Agentes De Tr\u00c1nsito, Auxiliares De Transporte Internacional",
    "sg:phone":"+34 948 82 09 84",
    "sg:postcode":"31500",
    "sg:province":"Navarra",
    "wof:name":"Ochoa Forcada Maria Isabel",
    "wof:placetype":"venue"
},
  "geometry": {"coordinates":[-1.6047970057,42.0519828796],"type":"Point"}
}