{
  "type": "Feature",
  "properties": {
    "iso:country":"ES",
    "sg:address":"Av S'agaro, 148",
    "sg:city":"Platja D'aro",
    "sg:orig_category":"Agencias De Viajes",
    "sg:phone":"+34 972 82 86 40",
    "sg:postcode":"17250",
    "sg:province":"Girona",
    "sg:website":"www.vserhs.com",
    "wof:name":"Viatges Serhs Hotels S.a.",
    "wof:placetype":"venue"
},
  "geometry": {"coordinates":[2.8163490295,41.9701499939],"type":"Point"}
}