{
  "type": "Feature",
  "properties": {
    "addr:full":"Calle de Villa De Foz, 29 Rozas De Madrid Madrid 28230",
    "addr:housenumber":"29",
    "addr:postcode":"28230",
    "addr:street":"Calle De Villa De Foz",
    "iso:country":"ES",
    "sg:address":"Calle de Villa De Foz, 29",
    "sg:city":"Rozas De Madrid",
    "sg:orig_category":"Ingeniero",
    "sg:phone":"+34 916 39 65 74",
    "sg:postcode":"28230",
    "sg:province":"Madrid",
    "wof:name":"Rubio Martinez Tomas",
    "wof:placetype":"venue"
},
  "geometry": {"coordinates":[-3.8854029179,40.4889030457],"type":"Point"}
}