{
  "type": "Feature",
  "properties": {
    "addr:full":"Ctra Madrid, Km. 0381,0 Molina Segura Murcia 30500",
    "addr:postcode":"30500",
    "addr:street":"Ctra Madrid Km. 0381,0 Molina",
    "iso:country":"ES",
    "sg:address":"Ctra Madrid, Km. 0381,0",
    "sg:city":"Molina Segura",
    "sg:orig_category":"Internados & Ense\u00d1anza Privada",
    "sg:phone":"+34 968 61 19 05",
    "sg:postcode":"30500",
    "sg:province":"Murcia",
    "sg:website":"www.ceu.es",
    "wof:name":"Fundacion Universitaria San Pablo",
    "wof:placetype":"venue"
},
  "geometry": {"coordinates":[-1.2119740248,38.0535736084],"type":"Point"}
}