{
  "type": "Feature",
  "properties": {
    "iso:country":"ES",
    "sg:address":"Calle de Fernan Nu\u00d1ez, 16",
    "sg:city":"Malaga",
    "sg:orig_category":"Asesor\u00cdas Y Estudios Financieros",
    "sg:phone":"+34 952 33 95 54",
    "sg:postcode":"29002",
    "sg:province":"M\u00e1laga",
    "wof:name":"Dominguez Jimenez Enrique",
    "wof:placetype":"venue"
},
  "geometry": {"coordinates":[-4.4313211441,36.7087745667],"type":"Point"}
}