{
  "type": "Feature",
  "properties": {
    "addr:full":"Calle de Monte Aldabe, 5 Irun Guip\u00f9zcoa 20305",
    "addr:housenumber":"5",
    "addr:postcode":"20305",
    "addr:street":"Calle De Monte Aldabe;Guipu\u0300Zcoa",
    "iso:country":"ES",
    "sg:address":"Calle de Monte Aldabe, 5",
    "sg:city":"Irun",
    "sg:orig_category":"Ropa De Hogar (al Por Menor)",
    "sg:phone":"+34 943 61 46 98",
    "sg:postcode":"20305",
    "sg:province":"Guip\u00f9zcoa",
    "wof:name":"Etxeberria Velasco Juan Jose",
    "wof:placetype":"venue"
},
  "geometry": {"coordinates":[-1.7637690306,43.3425445557],"type":"Point"}
}