{
  "type": "Feature",
  "properties": {
    "addr:full":"Calle de Don Pio Coronado, 95 Palmas De Gran Canaria Las Palmas 35012",
    "addr:housenumber":"95",
    "addr:postcode":"35012",
    "addr:street":"Calle De Don Pio Coronado",
    "iso:country":"ES",
    "sg:address":"Calle de Don Pio Coronado, 95",
    "sg:city":"Palmas De Gran Canaria",
    "sg:orig_category":"Comercio De Hierro",
    "sg:phone":"+34 928 25 59 96",
    "sg:postcode":"35012",
    "sg:province":"Las Palmas",
    "wof:name":"Ferralla Lubesan S.l.",
    "wof:placetype":"venue"
},
  "geometry": {"coordinates":[-15.43430233,28.1091365814],"type":"Point"}
}