{
  "type": "Feature",
  "properties": {
    "addr:full":"Trva Camino De Pajarillas (del), Km. 0020,8 Mostoles Madrid 28934",
    "addr:postcode":"28934",
    "addr:street":"Trva Camino De Pajarillas Del Km. 0020,8 Mostoles",
    "iso:country":"ES",
    "sg:address":"Trva Camino De Pajarillas (del), Km. 0020,8",
    "sg:city":"Mostoles",
    "sg:orig_category":"Inform\u00c1tica: Material Y Suministros",
    "sg:phone":"+34 916 85 25 90",
    "sg:postcode":"28934",
    "sg:province":"Madrid",
    "wof:name":"Ciagar S.a.",
    "wof:placetype":"venue"
},
  "geometry": {"coordinates":[-3.8649389744,40.3230667114],"type":"Point"}
}