{
  "type": "Feature",
  "properties": {
    "addr:full":"Rua Santa Eulalia, 36 Vilagarcia Pontevedra 36600",
    "addr:housenumber":"36",
    "addr:postcode":"36600",
    "addr:street":"Rua Santa Eulalia",
    "iso:country":"ES",
    "sg:address":"Rua Santa Eulalia, 36",
    "sg:city":"Vilagarcia",
    "sg:orig_category":"Molduras, Junquillos, Listones Y Molduras Perforadas",
    "sg:phone":"+34 986 50 61 25",
    "sg:postcode":"36600",
    "sg:province":"Pontevedra",
    "wof:name":"Souto Garcia Jesus",
    "wof:placetype":"venue"
},
  "geometry": {"coordinates":[-8.763258934,42.59349823],"type":"Point"}
}