{
  "type": "Feature",
  "properties": {
    "addr:full":"Calle de Huerta Nueva, 4 Estepona M\u00e1laga 29680",
    "addr:housenumber":"4",
    "addr:postcode":"29680",
    "addr:street":"Calle De Huerta Nueva",
    "iso:country":"ES",
    "sg:address":"Calle de Huerta Nueva, 4",
    "sg:city":"Estepona",
    "sg:orig_category":"Masajistas Kinesiterapeutas",
    "sg:phone":"+34 952 79 12 14",
    "sg:postcode":"29680",
    "sg:province":"M\u00e1laga",
    "wof:name":"Luque Torrejon Antonia",
    "wof:placetype":"venue"
},
  "geometry": {"coordinates":[-5.1508359909,36.424331665],"type":"Point"}
}