{
  "type": "Feature",
  "properties": {
    "iso:country":"ES",
    "sg:address":"Carrer de Doctor Fleming, 17",
    "sg:city":"Castelldefels",
    "sg:orig_category":"Electricidad: Instaladores",
    "sg:phone":"+34 936 65 16 40",
    "sg:postcode":"08860",
    "sg:province":"Barcelona",
    "wof:name":"Serrano Burillo Macario",
    "wof:placetype":"venue"
},
  "geometry": {"coordinates":[1.9757829905,41.2782363892],"type":"Point"}
}