{
  "type": "Feature",
  "properties": {
    "iso:country":"ES",
    "sg:address":"Calle de Isidoro Melero, 25",
    "sg:city":"Alsasua",
    "sg:orig_category":"Promotores Constructores",
    "sg:phone":"+34 948 46 77 40",
    "sg:postcode":"31800",
    "sg:province":"Navarra",
    "wof:name":"Guerriko Etxea S.l.",
    "wof:placetype":"venue"
},
  "geometry": {"coordinates":[-2.1704590321,42.8968200684],"type":"Point"}
}