{
  "type": "Feature",
  "properties": {
    "iso:country":"ES",
    "sg:address":"Calle de Carrera, 33",
    "sg:city":"Aguilar De La Frontera",
    "sg:orig_category":"\u00d3ptica: Instrumentos (fabricaci\u00d3n)",
    "sg:phone":"+34 957 66 14 77",
    "sg:postcode":"14920",
    "sg:province":"C\u00f3rdoba",
    "wof:name":"Optica Irisol Aguilar C.b.",
    "wof:placetype":"venue"
},
  "geometry": {"coordinates":[-4.6550798416,37.5157546997],"type":"Point"}
}