{
  "type": "Feature",
  "properties": {
    "iso:country":"ES",
    "sg:address":"Carrer de Rossend Arus, 8",
    "sg:city":"Hospitalet Llobregat",
    "sg:orig_category":"Panader\u00cdas, Panader\u00cdas",
    "sg:phone":"+34 933 37 01 65",
    "sg:postcode":"08901",
    "sg:province":"Barcelona",
    "wof:name":"Roca Ricart Ramon",
    "wof:placetype":"venue"
},
  "geometry": {"coordinates":[2.0998079777,41.3585128784],"type":"Point"}
}