{
  "type": "Feature",
  "properties": {
    "iso:country":"ES",
    "sg:address":"Carr Valencia, 30",
    "sg:city":"Burjassot",
    "sg:orig_category":"Farmacias",
    "sg:phone":"+34 963 90 16 34",
    "sg:postcode":"46100",
    "sg:province":"Valencia",
    "wof:name":"Fernandez Palanca Maria Vicenta",
    "wof:placetype":"venue"
},
  "geometry": {"coordinates":[-0.4040969908,39.5029373169],"type":"Point"}
}