{
  "type": "Feature",
  "properties": {
    "iso:country":"ES",
    "sg:address":"Calle de Mayor, 108",
    "sg:city":"Puente Tocinos",
    "sg:orig_category":"Relojer\u00cda (al Por Menor, Reparaci\u00d3n)",
    "sg:phone":"+34 968 30 15 90",
    "sg:postcode":"30006",
    "sg:province":"Murcia",
    "wof:name":"Bunker Inmobiliaria S.l",
    "wof:placetype":"venue"
},
  "geometry": {"coordinates":[-1.1009830236,37.9938926697],"type":"Point"}
}