{
  "type": "Feature",
  "properties": {
    "addr:full":"Carrer de Felix Just Oliveras, 24 Cornella Llobregat Barcelona 08940",
    "addr:housenumber":"24",
    "addr:postcode":"08940",
    "addr:street":"Carrer De Felix Just Oliveras",
    "iso:country":"ES",
    "sg:address":"Carrer de Felix Just Oliveras, 24",
    "sg:city":"Cornella Llobregat",
    "sg:orig_category":"Asesor\u00cda Fiscal Y Jur\u00cddica",
    "sg:phone":"+34 934 71 46 50",
    "sg:postcode":"08940",
    "sg:province":"Barcelona",
    "sg:website":"www.gestoriaromo.com",
    "wof:name":"Gestoria Romo S.l.",
    "wof:placetype":"venue"
},
  "geometry": {"coordinates":[2.079130888,41.3609428406],"type":"Point"}
}