{
  "type": "Feature",
  "properties": {
    "iso:country":"ES",
    "sg:address":"Avda Francisco Montenegro, S/n",
    "sg:city":"Huelva",
    "sg:orig_category":"Productos Qu\u00cdmicos (fabricaci\u00d3n, Al Por Mayor)",
    "sg:phone":"+34 959 24 59 47",
    "sg:postcode":"21001",
    "sg:province":"Huelva",
    "wof:name":"Rhodia Iberia S.a.",
    "wof:placetype":"venue"
},
  "geometry": {"coordinates":[-6.9551591873,37.2447013855],"type":"Point"}
}