{
  "type": "Feature",
  "properties": {
    "iso:country":"ES",
    "sg:address":"Carr Mariola, 31",
    "sg:city":"Lleida",
    "sg:orig_category":"\u00d3ptica: Instrumentos (fabricaci\u00d3n)",
    "sg:phone":"+34 973 26 51 98",
    "sg:postcode":"25003",
    "sg:province":"Lleida",
    "wof:name":"Lleida Optics S.l.",
    "wof:placetype":"venue"
},
  "geometry": {"coordinates":[0.6125059724,41.6121444702],"type":"Point"}
}