{
  "type": "Feature",
  "properties": {
    "addr:full":"Calle de Pe\u00d1a, 32 Malaga M\u00e1laga 29012",
    "addr:housenumber":"32",
    "addr:postcode":"29012",
    "addr:street":"Calle De Pen\u0303A;Ma\u0301Laga",
    "iso:country":"ES",
    "sg:address":"Calle de Pe\u00d1a, 32",
    "sg:city":"Malaga",
    "sg:orig_category":"Frutas, Legumbres Frescas Y Tempranas (al Por Menor)",
    "sg:phone":"+34 952 22 04 95",
    "sg:postcode":"29012",
    "sg:province":"M\u00e1laga",
    "wof:name":"Serrano Madrid Ana",
    "wof:placetype":"venue"
},
  "geometry": {"coordinates":[-4.4187650681,36.7255172729],"type":"Point"}
}