{
  "type": "Feature",
  "properties": {
    "addr:full":"Calle de Botica, 72 Dos Hermanas Sevilla 41700",
    "addr:housenumber":"72",
    "addr:postcode":"41700",
    "addr:street":"Calle De Botica",
    "iso:country":"ES",
    "sg:address":"Calle de Botica, 72",
    "sg:city":"Dos Hermanas",
    "sg:orig_category":"Agencias Y Asesores De Publicidad",
    "sg:phone":"+34 955 67 75 69",
    "sg:postcode":"41700",
    "sg:province":"Sevilla",
    "wof:name":"D.h.p.r.asesores S.l.",
    "wof:placetype":"venue"
},
  "geometry": {"coordinates":[-5.924554348,37.2857017517],"type":"Point"}
}