{
  "type": "Feature",
  "properties": {
    "addr:full":"Carrer de Raval (de), 81 Canonja Tarragona 43110",
    "addr:housenumber":"81",
    "addr:postcode":"43110",
    "addr:street":"Carrer De Raval De",
    "iso:country":"ES",
    "sg:address":"Carrer de Raval (de), 81",
    "sg:city":"Canonja",
    "sg:classifiers":[
        {
            "category":"Autos & Motor Vehicles",
            "subcategory":"Automobile Sales",
            "type":"Retail Goods"
        }
    ],
    "sg:phone":"+34 977 54 76 09",
    "sg:postcode":"43110",
    "sg:province":"Tarragona",
    "wof:name":"Bove Calaf Victor",
    "wof:placetype":"venue"
},
  "geometry": {"coordinates":[1.181030035,41.1210784912],"type":"Point"}
}