{
  "type": "Feature",
  "properties": {
    "iso:country":"ES",
    "sg:address":"Ctra. Jerez, Km. 0002,5",
    "sg:city":"Trebujena",
    "sg:orig_category":"Cooperativas Agr\u00cdcolas",
    "sg:phone":"+34 956 23 72 28",
    "sg:postcode":"11560",
    "sg:province":"C\u00e1diz",
    "wof:name":"Sociedad Cooperativa Andaluza Solidaridad De Cabreros",
    "wof:placetype":"venue"
},
  "geometry": {"coordinates":[-6.1715888977,36.8716392517],"type":"Point"}
}