{
  "type": "Feature",
  "properties": {
    "addr:full":"Calle de Alonso Cano, 103 Madrid Madrid 28003",
    "addr:housenumber":"103",
    "addr:postcode":"28003",
    "addr:street":"Calle De Alonso Cano",
    "iso:country":"ES",
    "sg:address":"Calle de Alonso Cano, 103",
    "sg:city":"Madrid",
    "sg:orig_category":"Muebles Y Accesorios Para Cocinas Y Cuartos De Ba\u00d1o (al Por Menor)",
    "sg:phone":"+34 915 54 90 10",
    "sg:postcode":"28003",
    "sg:province":"Madrid",
    "wof:name":"Ledesma Tamames Manuel",
    "wof:placetype":"venue"
},
  "geometry": {"coordinates":[-3.697157383,40.4462585449],"type":"Point"}
}