{
  "type": "Feature",
  "properties": {
    "iso:country":"ES",
    "sg:address":"Plaz Colonizacion, 18",
    "sg:city":"S. Agustin",
    "sg:orig_category":"Frutas, Legumbres Frescas Y Tempranas (al Por Menor)",
    "sg:phone":"+34 950 53 60 09",
    "sg:postcode":"04700",
    "sg:province":"Almer\u00eda",
    "wof:name":"Jazali  Imane",
    "wof:placetype":"venue"
},
  "geometry": {"coordinates":[-2.8176040649,36.7727012634],"type":"Point"}
}