{
  "type": "Feature",
  "properties": {
    "addr:full":"Av Princep D'asturies, 21 Barcelona Barcelona 08012",
    "addr:housenumber":"21",
    "addr:postcode":"08012",
    "addr:street":"Av Princep D'Asturies",
    "iso:country":"ES",
    "sg:address":"Av Princep D'asturies, 21",
    "sg:city":"Barcelona",
    "sg:orig_category":"Art\u00cdculos De Regalo (al Por Menor)",
    "sg:phone":"+34 932 18 69 80",
    "sg:postcode":"08012",
    "sg:province":"Barcelona",
    "wof:name":"Bardavio Junquera Leon",
    "wof:placetype":"venue"
},
  "geometry": {"coordinates":[2.1502125263,41.4027099609],"type":"Point"}
}