{
  "type": "Feature",
  "properties": {
    "addr:full":"Avda San Mames, S/n Blimea Asturias 33960",
    "addr:housenumber":"s / n",
    "addr:postcode":"33960",
    "addr:street":"Avda San Mames",
    "iso:country":"ES",
    "sg:address":"Avda San Mames, S/n",
    "sg:city":"Blimea",
    "sg:orig_category":"Molduras, Junquillos, Listones Y Molduras Perforadas",
    "sg:phone":"+34 985 65 67 21",
    "sg:postcode":"33960",
    "sg:province":"Asturias",
    "wof:name":"Jove Candanedo Julio Alberto",
    "wof:placetype":"venue"
},
  "geometry": {"coordinates":[-5.5900788307,43.2701644897],"type":"Point"}
}