{
  "type": "Feature",
  "properties": {
    "addr:full":"Avda Fernando Saiz (sancibrian), 6 Sancibrian Cantabria 39110",
    "addr:housenumber":"6",
    "addr:postcode":"39110",
    "addr:street":"Avda Fernando Saiz Sancibrian",
    "iso:country":"ES",
    "sg:address":"Avda Fernando Saiz (sancibrian), 6",
    "sg:city":"Sancibrian",
    "sg:orig_category":"Centros De Educaci\u00d3n Especial",
    "sg:phone":"+34 942 57 96 65",
    "sg:postcode":"39110",
    "sg:province":"Cantabria",
    "wof:name":"Ayuntamiento De Santa Cruz De Bezana",
    "wof:placetype":"venue"
},
  "geometry": {"coordinates":[-3.8968584538,43.4692077637],"type":"Point"}
}