{
  "type": "Feature",
  "properties": {
    "iso:country":"ES",
    "sg:address":"Carr Capsada, 4",
    "sg:city":"Casc Antic",
    "sg:orig_category":"Paletas",
    "sg:phone":"+34 973 71 03 88",
    "sg:postcode":"25241",
    "sg:province":"Lleida",
    "wof:name":"Embalatges Santacreu S.l.",
    "wof:placetype":"venue"
},
  "geometry": {"coordinates":[0.9323819876,41.6301574707],"type":"Point"}
}