{
  "type": "Feature",
  "properties": {
    "addr:full":"Carrer de Llibertat, 3 Palma Islas Baleares 07013",
    "addr:housenumber":"3",
    "addr:postcode":"07013",
    "addr:street":"Carrer De Llibertat",
    "iso:country":"ES",
    "sg:address":"Carrer de Llibertat, 3",
    "sg:city":"Palma",
    "sg:orig_category":"Asesor\u00cda De Formaci\u00d3n Y Gesti\u00d3n De Personal",
    "sg:phone":"+34 971 45 30 49",
    "sg:postcode":"07013",
    "sg:province":"Islas Baleares",
    "wof:name":"De La Poza Moreno Maria Jose",
    "wof:placetype":"venue"
},
  "geometry": {"coordinates":[2.6356270313,39.57654953],"type":"Point"}
}