{
  "type": "Feature",
  "properties": {
    "iso:country":"ES",
    "sg:address":"Calle de Ibarra, 6",
    "sg:city":"San Vicente De Barakaldo",
    "sg:orig_category":"Agencias Y Asesores De Publicidad",
    "sg:phone":"+34 944 18 00 40",
    "sg:postcode":"48901",
    "sg:province":"Vizcaya",
    "wof:name":"Triada Publicidad Y Dise\u00f1o S.l",
    "wof:placetype":"venue"
},
  "geometry": {"coordinates":[-2.9844820499,43.2983818054],"type":"Point"}
}