{
  "type": "Feature",
  "properties": {
    "addr:full":"C/ Cami (el), 40 Alcoi Alicante 03801",
    "addr:postcode":"03801",
    "addr:street":"C /;El",
    "iso:country":"ES",
    "sg:address":"C/ Cami (el), 40",
    "sg:city":"Alcoi",
    "sg:orig_category":"Imprenta",
    "sg:phone":"+34 965 54 13 72",
    "sg:postcode":"03801",
    "sg:province":"Alicante",
    "wof:name":"Borrell Sanz Francisco",
    "wof:placetype":"venue"
},
  "geometry": {"coordinates":[-0.4754709899,38.6928138733],"type":"Point"}
}