{
  "type": "Feature",
  "properties": {
    "iso:country":"ES",
    "sg:address":"Carrer de Banys, 19",
    "sg:city":"Garriga",
    "sg:orig_category":"Frutas Y Legumbres Frescas (al Por Mayor)",
    "sg:phone":"+34 938 71 92 14",
    "sg:postcode":"08530",
    "sg:province":"Barcelona",
    "wof:name":"Bonsuc S.l.",
    "wof:placetype":"venue"
},
  "geometry": {"coordinates":[2.2859430313,41.6838684082],"type":"Point"}
}