{
  "type": "Feature",
  "properties": {
    "iso:country":"ES",
    "sg:address":"San Frantzisko Kalea, 7",
    "sg:city":"Zarautz",
    "sg:orig_category":"Pescader\u00cdas (al Por Menor)",
    "sg:phone":"+34 943 83 31 16",
    "sg:postcode":"20800",
    "sg:province":"Guip\u00f9zcoa",
    "wof:name":"Garmendia Aramendi Felipe",
    "wof:placetype":"venue"
},
  "geometry": {"coordinates":[-2.173801899,43.2859382629],"type":"Point"}
}