{
  "type": "Feature",
  "properties": {
    "iso:country":"ES",
    "sg:address":"Calle de Jorge De Santayana, 13",
    "sg:city":"Avila",
    "sg:orig_category":"Agentes, Concesionarios Y Sucursales De Camiones Y Veh\u00cdculos Industriales",
    "sg:phone":"+34 920 25 01 97",
    "sg:postcode":"05004",
    "sg:province":"\u00c1vila",
    "wof:name":"Industria Tecnica De Automocion Y Repuestos S.a.",
    "wof:placetype":"venue"
},
  "geometry": {"coordinates":[-4.6871089935,40.6682281494],"type":"Point"}
}