{
  "type": "Feature",
  "properties": {
    "iso:country":"ES",
    "sg:address":"G.v. Corts Catalanes, 1176",
    "sg:city":"Barcelona",
    "sg:orig_category":"Metalurgia: Maquinaria Y Equipos",
    "sg:phone":"+34 933 05 34 11",
    "sg:postcode":"08020",
    "sg:province":"Barcelona",
    "wof:name":"Industrial Jogui S. A.",
    "wof:placetype":"venue"
},
  "geometry": {"coordinates":[2.2094969749,41.4196624756],"type":"Point"}
}