{
  "type": "Feature",
  "properties": {
    "addr:full":"Calle de Antonio Trueba, 20 Altzaga Vizcaya 48950",
    "addr:housenumber":"20",
    "addr:postcode":"48950",
    "addr:street":"Calle De Antonio Trueba",
    "iso:country":"ES",
    "sg:address":"Calle de Antonio Trueba, 20",
    "sg:city":"Altzaga",
    "sg:orig_category":"Fabricaci\u00d3n, Distribuci\u00d3n De Material Para La Climatizaci\u00d3n, Aireaci\u00d3n Y Ventilaci\u00d3n",
    "sg:phone":"+34 944 17 00 56",
    "sg:postcode":"48950",
    "sg:province":"Vizcaya",
    "wof:name":"Grupo Berolabe-citech, S.l.",
    "wof:placetype":"venue"
},
  "geometry": {"coordinates":[-2.9751808643,43.3019371033],"type":"Point"}
}