{
  "type": "Feature",
  "properties": {
    "iso:country":"ES",
    "sg:address":"Calle de Vitoria, 35",
    "sg:city":"Burgos",
    "sg:orig_category":"Pod\u00d3logos: Pedicuros",
    "sg:phone":"+34 947 27 15 61",
    "sg:postcode":"09004",
    "sg:province":"Burgos",
    "wof:name":"Pe\u00f1a Alvaro Milagros",
    "wof:placetype":"venue"
},
  "geometry": {"coordinates":[-3.6922411919,42.3426208496],"type":"Point"}
}