{
  "type": "Feature",
  "properties": {
    "iso:country":"ES",
    "sg:address":"Calle de Violeta Parra, 17",
    "sg:city":"Zaragoza",
    "sg:orig_category":"Bazares, Art\u00cdculos De Limpieza Y De Cocina (al Por Menor)",
    "sg:phone":"+34 976 52 89 51",
    "sg:postcode":"50015",
    "sg:province":"Zaragoza",
    "wof:name":"Mir Borraz Maria Elena",
    "wof:placetype":"venue"
},
  "geometry": {"coordinates":[-0.8779860139,41.669719696],"type":"Point"}
}