{
  "type": "Feature",
  "properties": {
    "iso:country":"ES",
    "sg:address":"Barr Pesquera (la), S/n",
    "sg:city":"Villacarriedo",
    "sg:orig_category":"Restaurantes",
    "sg:phone":"+34 942 59 02 14",
    "sg:postcode":"39640",
    "sg:province":"Cantabria",
    "wof:name":"Fernandez Herrero Ildefonso",
    "wof:placetype":"venue"
},
  "geometry": {"coordinates":[-3.8113639355,43.2283859253],"type":"Point"}
}