{
  "type": "Feature",
  "properties": {
    "addr:full":"Carrer de Quintana, 2 Sabadell Barcelona 08205",
    "addr:housenumber":"2",
    "addr:postcode":"08205",
    "addr:street":"Carrer De Quintana",
    "iso:country":"ES",
    "sg:address":"Carrer de Quintana, 2",
    "sg:city":"Sabadell",
    "sg:orig_category":"Inmobiliaria (agencias)",
    "sg:phone":"+34 937 27 62 56",
    "sg:postcode":"08205",
    "sg:province":"Barcelona",
    "wof:name":"Explotaciones Industriales E Inmobiliarias S.l.",
    "wof:placetype":"venue"
},
  "geometry": {"coordinates":[2.0981500149,41.5390090942],"type":"Point"}
}