{
  "type": "Feature",
  "properties": {
    "addr:full":"Carrer de Alta Cortada, 21 Manlleu Barcelona 08560",
    "addr:housenumber":"21",
    "addr:postcode":"08560",
    "addr:street":"Carrer De Alta Cortada",
    "iso:country":"ES",
    "sg:address":"Carrer de Alta Cortada, 21",
    "sg:city":"Manlleu",
    "sg:orig_category":"Cl\u00cdnicas Dentales",
    "sg:phone":"+34 938 51 37 40",
    "sg:postcode":"08560",
    "sg:province":"Barcelona",
    "wof:name":"Clinica Dental Bosch",
    "wof:placetype":"venue"
},
  "geometry": {"coordinates":[2.2819058895,42.0011978149],"type":"Point"}
}