{
  "type": "Feature",
  "properties": {
    "iso:country":"ES",
    "sg:address":"Avda Almeria (de), S/n",
    "sg:city":"Turre",
    "sg:orig_category":"Florister\u00cdas",
    "sg:phone":"+34 950 47 94 96",
    "sg:postcode":"04639",
    "sg:province":"Almer\u00eda",
    "wof:name":"Fernandez Fernandez Lucia",
    "wof:placetype":"venue"
},
  "geometry": {"coordinates":[-1.889703989,37.1529083252],"type":"Point"}
}