{
  "type": "Feature",
  "properties": {
    "iso:country":"ES",
    "sg:address":"Cril Tomason, 47",
    "sg:city":"Murcia",
    "sg:orig_category":"Escultores, Estatuarios E Imagineros",
    "sg:phone":"+34 968 34 05 59",
    "sg:postcode":"30012",
    "sg:province":"Murcia",
    "sg:website":"www.flyppy.com",
    "wof:name":"Cerezo Ramirez Ismael",
    "wof:placetype":"venue"
},
  "geometry": {"coordinates":[-1.1206640005,37.9650650024],"type":"Point"}
}