{
  "type": "Feature",
  "properties": {
    "addr:full":"Calle de Genova, 17 Madrid Madrid 28004",
    "addr:housenumber":"17",
    "addr:postcode":"madrid;28004",
    "addr:street":"Calle De Genova",
    "iso:country":"ES",
    "sg:address":"Calle de Genova, 17",
    "sg:city":"Madrid",
    "sg:orig_category":"Locales Y Clases De Danza",
    "sg:phone":"+34 913 08 16 26",
    "sg:postcode":"28004",
    "sg:province":"Madrid",
    "sg:website":"www.circulodebaile.com",
    "wof:name":"Circulo De Baile S.l.",
    "wof:placetype":"venue"
},
  "geometry": {"coordinates":[-3.6930921078,40.4265098572],"type":"Point"}
}