{
  "type": "Feature",
  "properties": {
    "addr:full":"Av Miraflores, 83 Hospitalet Llobregat Barcelona 08905",
    "addr:housenumber":"83",
    "addr:postcode":"08905",
    "addr:street":"Av Miraflores",
    "iso:country":"ES",
    "sg:address":"Av Miraflores, 83",
    "sg:city":"Hospitalet Llobregat",
    "sg:orig_category":"Ropa De Hogar (al Por Menor)",
    "sg:phone":"+34 934 49 18 73",
    "sg:postcode":"08905",
    "sg:province":"Barcelona",
    "wof:name":"Nieto Alcaraz Rosa",
    "wof:placetype":"venue"
},
  "geometry": {"coordinates":[2.1074640751,41.3721008301],"type":"Point"}
}