{
  "type": "Feature",
  "properties": {
    "addr:full":"Calle de Boleo Nuevo, 20 Valdestillas Valladolid 47240",
    "addr:housenumber":"20",
    "addr:postcode":"47240",
    "addr:street":"Calle De Boleo Nuevo",
    "iso:country":"ES",
    "sg:address":"Calle de Boleo Nuevo, 20",
    "sg:city":"Valdestillas",
    "sg:orig_category":"Pintura, Barniz, Productos Asimilables (fabricaci\u00d3n, Al Por Mayor)",
    "sg:phone":"+34 983 55 14 71",
    "sg:postcode":"47240",
    "sg:province":"Valladolid",
    "wof:name":"Decofa S.l.",
    "wof:placetype":"venue"
},
  "geometry": {"coordinates":[-4.771900177,41.4776268005],"type":"Point"}
}