{
  "type": "Feature",
  "properties": {
    "addr:full":"Juan Bautista Erro Kalea, 8 Andoain Guip\u00f9zcoa 20140",
    "addr:housenumber":"8",
    "addr:postcode":"20140",
    "addr:street":"Juan Bautista Erro Kalea;Guipu\u0300Zcoa",
    "iso:country":"ES",
    "sg:address":"Juan Bautista Erro Kalea, 8",
    "sg:city":"Andoain",
    "sg:orig_category":"Partidos Pol\u00cdticos",
    "sg:phone":"+34 943 30 01 23",
    "sg:postcode":"20140",
    "sg:province":"Guip\u00f9zcoa",
    "wof:name":"Eusko Alkartasuna",
    "wof:placetype":"venue"
},
  "geometry": {"coordinates":[-2.0208981037,43.2170906067],"type":"Point"}
}