{
  "type": "Feature",
  "properties": {
    "iso:country":"ES",
    "sg:address":"Urb Ballena Blanca, 1",
    "sg:city":"Alfas Pi",
    "sg:orig_category":"Aguas (distribuci\u00d3n, Servicios)",
    "sg:phone":"+34 966 86 72 80",
    "sg:postcode":"03580",
    "sg:province":"Alicante",
    "wof:name":"Gomez Martinho Garrido Ana Isabel",
    "wof:placetype":"venue"
},
  "geometry": {"coordinates":[-0.1106439978,38.5881652832],"type":"Point"}
}