{
  "type": "Feature",
  "properties": {
    "addr:full":"Pg Maritim Barceloneta, 25 Barcelona Barcelona 08003",
    "addr:housenumber":"25",
    "addr:postcode":"08003",
    "addr:street":"Pg Maritim Barceloneta",
    "iso:country":"ES",
    "sg:address":"Pg Maritim Barceloneta, 25",
    "sg:city":"Barcelona",
    "sg:orig_category":"Sanatorios M\u00c9dico",
    "sg:phone":"+34 932 21 37 83",
    "sg:postcode":"08003",
    "sg:province":"Barcelona",
    "wof:name":"Institut Mpal.prestacions Assist.med.empleats",
    "wof:placetype":"venue"
},
  "geometry": {"coordinates":[2.1945650578,41.3832969666],"type":"Point"}
}