{
  "type": "Feature",
  "properties": {
    "addr:full":"Pl Casagemas, S/n Badalona Barcelona 08911",
    "addr:housenumber":"s / n",
    "addr:postcode":"08911",
    "addr:street":"Pl Casagemas",
    "iso:country":"ES",
    "sg:address":"Pl Casagemas, S/n",
    "sg:city":"Badalona",
    "sg:orig_category":"Asociaciones Y Clubs Deportivos",
    "sg:phone":"+34 934 64 41 98",
    "sg:postcode":"08911",
    "sg:province":"Barcelona",
    "wof:name":"Associacio Esportiva Minguella",
    "wof:placetype":"venue"
},
  "geometry": {"coordinates":[2.2563905716,41.4537086487],"type":"Point"}
}