{
  "type": "Feature",
  "properties": {
    "iso:country":"ES",
    "sg:address":"Calle de Hermanos Del Moral, 77",
    "sg:city":"Madrid",
    "sg:orig_category":"Fabricaci\u00d3n De Su\u00c9ters Y Chalecos De Punto",
    "sg:phone":"+34 914 69 20 00",
    "sg:postcode":"28019",
    "sg:province":"Madrid",
    "wof:name":"Remanufacturados Vittoline S.l.",
    "wof:placetype":"venue"
},
  "geometry": {"coordinates":[-3.7215590477,40.3902778625],"type":"Point"}
}