{
  "type": "Feature",
  "properties": {
    "addr:full":"Pozo Blanco, 13 Iru\u00f1a Navarra 31001",
    "addr:housenumber":"13",
    "addr:postcode":"31001",
    "addr:street":"Pozo Blanco",
    "iso:country":"ES",
    "sg:address":"Pozo Blanco, 13",
    "sg:city":"Iru\u00f1a",
    "sg:orig_category":"Fabricaci\u00d3n De Telas Y Sedas",
    "sg:phone":"+34 948 22 18 93",
    "sg:postcode":"31001",
    "sg:province":"Navarra",
    "wof:name":"Comercial Orotex S.a.",
    "wof:placetype":"venue"
},
  "geometry": {"coordinates":[-1.6438390017,42.816947937],"type":"Point"}
}