{
  "type": "Feature",
  "properties": {
    "iso:country":"ES",
    "sg:address":"Carrer de Bonaire, 21",
    "sg:city":"Palma",
    "sg:orig_category":"Mercer\u00cda, Lencer\u00cda (al Por Menor)",
    "sg:phone":"+34 971 72 99 68",
    "sg:postcode":"07012",
    "sg:province":"Islas Baleares",
    "wof:name":"Plovins Servera Francisco",
    "wof:placetype":"venue"
},
  "geometry": {"coordinates":[2.645250082,39.5749549866],"type":"Point"}
}