{
  "type": "Feature",
  "properties": {
    "iso:country":"ES",
    "sg:address":"Calle de Pozas (de Las), 9",
    "sg:city":"Alcorcon",
    "sg:orig_category":"Ropa Para Se\u00d1oras Y Caballeros (al Por Menor)",
    "sg:phone":"+34 916 41 27 41",
    "sg:postcode":"28922",
    "sg:province":"Madrid",
    "sg:website":"www.stockfactory.com",
    "wof:name":"Stock-shop S.l.",
    "wof:placetype":"venue"
},
  "geometry": {"coordinates":[-3.8294382095,40.3435745239],"type":"Point"}
}