{
  "type": "Feature",
  "properties": {
    "iso:country":"ES",
    "sg:address":"Calle de Entrebarrios, 7",
    "sg:city":"Berlanas",
    "sg:orig_category":"Delegados, Agentes De Tr\u00c1nsito, Auxiliares De Transporte Internacional",
    "sg:phone":"+34 920 26 91 75",
    "sg:postcode":"05162",
    "sg:province":"\u00c1vila",
    "wof:name":"Pozo Garcinu\u00f1o Jose Manuel Del",
    "wof:placetype":"venue"
},
  "geometry": {"coordinates":[-4.7617092133,40.8013801575],"type":"Point"}
}