{
  "type": "Feature",
  "properties": {
    "addr:full":"Plaz Irlandeses (de Los), 3 Alcala Henares Madrid 28801",
    "addr:postcode":"28801",
    "addr:street":"Plaz",
    "iso:country":"ES",
    "sg:address":"Plaz Irlandeses (de Los), 3",
    "sg:city":"Alcala Henares",
    "sg:orig_category":"Art\u00cdculos De Decoraci\u00d3n",
    "sg:phone":"+34 918 79 64 79",
    "sg:postcode":"28801",
    "sg:province":"Madrid",
    "wof:name":"Florencia Quijada Mignot Tania",
    "wof:placetype":"venue"
},
  "geometry": {"coordinates":[-3.3668460846,40.4812583923],"type":"Point"}
}