{
  "type": "Feature",
  "properties": {
    "iso:country":"ES",
    "sg:address":"Calle de Virgen De Los Milagros, 69",
    "sg:city":"Puerto De Santa Maria",
    "sg:orig_category":"Centros Empresariales",
    "sg:phone":"+34 956 54 04 51",
    "sg:postcode":"11500",
    "sg:province":"C\u00e1diz",
    "wof:name":"Asociacion De Comerciantes De El Puerto",
    "wof:placetype":"venue"
},
  "geometry": {"coordinates":[-6.225063324,36.5995635986],"type":"Point"}
}