{
  "type": "Feature",
  "properties": {
    "addr:full":"Plaz Orense, 7 Coru\u00d1a La Coru\u00f1a 15004",
    "addr:housenumber":"7",
    "addr:postcode":"15004",
    "addr:street":"Plaz Orense;La Corun\u0303A",
    "iso:country":"ES",
    "sg:address":"Plaz Orense, 7",
    "sg:city":"Coru\u00d1a",
    "sg:orig_category":"Promotores Constructores",
    "sg:phone":"+34 981 12 23 96",
    "sg:postcode":"15004",
    "sg:province":"La Coru\u00f1a",
    "wof:name":"Lopez Diaz Carmen",
    "wof:placetype":"venue"
},
  "geometry": {"coordinates":[-8.4115686417,43.3652801514],"type":"Point"}
}