{
  "type": "Feature",
  "properties": {
    "iso:country":"ES",
    "sg:address":"Calle de Conde Duque, 1",
    "sg:city":"Madrid",
    "sg:orig_category":"Procuradores",
    "sg:phone":"+34 915 59 91 11",
    "sg:postcode":"28015",
    "sg:province":"Madrid",
    "wof:name":"Martinez Diez Albito",
    "wof:placetype":"venue"
},
  "geometry": {"coordinates":[-3.7116014957,40.4257774353],"type":"Point"}
}