{
  "type": "Feature",
  "properties": {
    "iso:country":"ES",
    "sg:address":"Calle de Escuelas (las), 4",
    "sg:city":"Alcorcon",
    "sg:orig_category":"Caf\u00c9s, Bares, Cervecer\u00cdas",
    "sg:phone":"+34 916 11 12 86",
    "sg:postcode":"28921",
    "sg:province":"Madrid",
    "wof:name":"Whittle Y Valenciano 2003",
    "wof:placetype":"venue"
},
  "geometry": {"coordinates":[-3.8300664425,40.3493499756],"type":"Point"}
}