{
  "type": "Feature",
  "properties": {
    "iso:country":"ES",
    "sg:address":"Carrer de Volta, 4",
    "sg:city":"Terrassa",
    "sg:orig_category":"Ropa De Hogar (al Por Menor)",
    "sg:phone":"+34 937 33 65 38",
    "sg:postcode":"08224",
    "sg:province":"Barcelona",
    "sg:website":"www.textura-interiors.com",
    "wof:name":"Textil Alea S.l.",
    "wof:placetype":"venue"
},
  "geometry": {"coordinates":[2.0076360703,41.5637779236],"type":"Point"}
}