{
  "type": "Feature",
  "properties": {
    "addr:full":"Camino Cortecillas, S/n Ainzon Zaragoza 50570",
    "addr:housenumber":"s",
    "addr:postcode":"50570",
    "addr:street":"Camino Cortecillas;/ N Ainzon",
    "iso:country":"ES",
    "sg:address":"Camino Cortecillas, S/n",
    "sg:city":"Ainzon",
    "sg:orig_category":"Comercio De Piezas De Recambio Y De Accesorios De Veh\u00cdculos, Veh\u00cdculos Industriales",
    "sg:phone":"+34 976 86 94 89",
    "sg:postcode":"50570",
    "sg:province":"Zaragoza",
    "wof:name":"Accesorios Brun S.l.",
    "wof:placetype":"venue"
},
  "geometry": {"coordinates":[-1.530546546,41.7803382874],"type":"Point"}
}