{
  "type": "Feature",
  "properties": {
    "addr:full":"Plaz San Isidro, S/n Paredes Cuenca 16821",
    "addr:housenumber":"s / n",
    "addr:postcode":"16821",
    "addr:street":"Plaz San Isidro",
    "iso:country":"ES",
    "sg:address":"Plaz San Isidro, S/n",
    "sg:city":"Paredes",
    "sg:orig_category":"Centros De Educaci\u00d3n Especial",
    "sg:phone":"+34 969 12 30 92",
    "sg:postcode":"16821",
    "sg:province":"Cuenca",
    "wof:name":"Colegio Rural Agrupado Segobriga",
    "wof:placetype":"venue"
},
  "geometry": {"coordinates":[-2.853110075,40.1167984009],"type":"Point"}
}