{
  "type": "Feature",
  "properties": {
    "iso:country":"ES",
    "sg:address":"La Corte, 17",
    "sg:city":"Estella",
    "sg:orig_category":"Asociaciones Y Clubs Deportivos",
    "sg:phone":"+34 948 55 07 79",
    "sg:postcode":"31200",
    "sg:province":"Navarra",
    "wof:name":"Sociedad De Cazadores Y Pescadores Estella",
    "wof:placetype":"venue"
},
  "geometry": {"coordinates":[-2.0315849781,42.6733818054],"type":"Point"}
}