{
  "type": "Feature",
  "properties": {
    "iso:country":"ES",
    "sg:address":"Calle de Miguel Zaera, 31",
    "sg:city":"Le\u00f3n",
    "sg:orig_category":"Chapister\u00cda",
    "sg:phone":"+34 987 25 77 62",
    "sg:postcode":"24007",
    "sg:province":"Le\u00f3n",
    "wof:name":"Talleres Orfi S.l.",
    "wof:placetype":"venue"
},
  "geometry": {"coordinates":[-5.559240818,42.6002159119],"type":"Point"}
}