{
  "type": "Feature",
  "properties": {
    "addr:full":"Carrer de Sant Josep, 71 Calella Barcelona 08370",
    "addr:housenumber":"71",
    "addr:postcode":"08370",
    "addr:street":"Carrer De Sant Josep",
    "iso:country":"ES",
    "sg:address":"Carrer de Sant Josep, 71",
    "sg:city":"Calella",
    "sg:orig_category":"Empresas De Carpinter\u00cda De Madera",
    "sg:phone":"+34 937 69 12 88",
    "sg:postcode":"08370",
    "sg:province":"Barcelona",
    "wof:name":"Serras Mir Joan",
    "wof:placetype":"venue"
},
  "geometry": {"coordinates":[2.6599891186,41.6150093079],"type":"Point"}
}