{
  "type": "Feature",
  "properties": {
    "addr:full":"Calle de Mata Linares, S/n S. Vicente Barquera Cantabria 39540",
    "addr:housenumber":"s",
    "addr:postcode":"39540",
    "addr:street":"Calle De Mata Linares;/ N S. Vicente",
    "iso:country":"ES",
    "sg:address":"Calle de Mata Linares, S/n",
    "sg:city":"S. Vicente Barquera",
    "sg:orig_category":"Tintorer\u00cdas, Limpieza En Seco",
    "sg:phone":"+34 942 71 25 75",
    "sg:postcode":"39540",
    "sg:province":"Cantabria",
    "wof:name":"Sanchez Garcia Rosa Maria",
    "wof:placetype":"venue"
},
  "geometry": {"coordinates":[-4.4006319046,43.3824615479],"type":"Point"}
}