{
  "type": "Feature",
  "properties": {
    "iso:country":"ES",
    "sg:address":"Calle de Valentin Madruga, 15",
    "sg:city":"Cigales",
    "sg:orig_category":"Asesor\u00cda Fiscal Y Jur\u00cddica",
    "sg:phone":"+34 983 58 01 70",
    "sg:postcode":"47270",
    "sg:province":"Valladolid",
    "wof:name":"Mu\u00f1oz Ganado Ana Maria",
    "wof:placetype":"venue"
},
  "geometry": {"coordinates":[-4.6983819008,41.7592697144],"type":"Point"}
}