{
  "type": "Feature",
  "properties": {
    "iso:country":"ES",
    "sg:address":"Calle de Castilla La Nueva (de), 38",
    "sg:city":"Fuenlabrada",
    "sg:orig_category":"Supermercados Y Hipermercados",
    "sg:phone":"+34 916 15 03 24",
    "sg:postcode":"28941",
    "sg:province":"Madrid",
    "wof:name":"Madrile\u00f1a De Negocios S.a.",
    "wof:placetype":"venue"
},
  "geometry": {"coordinates":[-3.7968046665,40.2960624695],"type":"Point"}
}