{
  "type": "Feature",
  "properties": {
    "addr:full":"Calle de Sor Felisa Ancin, 2 Baeza Ja\u00e9n 23440",
    "addr:housenumber":"2",
    "addr:postcode":"23440",
    "addr:street":"Calle De Sor Felisa Ancin",
    "iso:country":"ES",
    "sg:address":"Calle de Sor Felisa Ancin, 2",
    "sg:city":"Baeza",
    "sg:orig_category":"Caf\u00c9s, Bares, Cervecer\u00cdas",
    "sg:phone":"+34 953 74 09 50",
    "sg:postcode":"23440",
    "sg:province":"Ja\u00e9n",
    "wof:name":"Cruz Blazquez Bienvenida",
    "wof:placetype":"venue"
},
  "geometry": {"coordinates":[-3.4611589909,37.9959259033],"type":"Point"}
}