{
  "type": "Feature",
  "properties": {
    "iso:country":"ES",
    "sg:address":"Ctra Valencia, 28",
    "sg:city":"Naquera",
    "sg:orig_category":"Material Y Suministros Para Perforaciones, Sondeos",
    "sg:phone":"+34 961 68 13 82",
    "sg:postcode":"46119",
    "sg:province":"Valencia",
    "wof:name":"Fernandez Fernandez Angel",
    "wof:placetype":"venue"
},
  "geometry": {"coordinates":[-0.3922440112,39.6129989624],"type":"Point"}
}