{
  "type": "Feature",
  "properties": {
    "iso:country":"ES",
    "sg:address":"Calle de Jesus Maria Ordo\u00d1o, 1",
    "sg:city":"Burgos",
    "sg:orig_category":"Edici\u00d3n De Diarios, Revistas, Boletines",
    "sg:phone":"+34 947 27 72 45",
    "sg:postcode":"09004",
    "sg:province":"Burgos",
    "wof:name":"Menor Ortega Francisco",
    "wof:placetype":"venue"
},
  "geometry": {"coordinates":[-3.6883609295,42.3441772461],"type":"Point"}
}