{
  "type": "Feature",
  "properties": {
    "iso:country":"ES",
    "sg:address":"Plaz Gabino Diaz Merchan, 3",
    "sg:city":"Oviedo",
    "sg:orig_category":"Promotores Constructores",
    "sg:phone":"+34 985 23 60 52",
    "sg:postcode":"33012",
    "sg:province":"Asturias",
    "wof:name":"More E Hijos S.l.",
    "wof:placetype":"venue"
},
  "geometry": {"coordinates":[-5.8679699898,43.3689155579],"type":"Point"}
}