{
  "type": "Feature",
  "properties": {
    "addr:full":"Calle de San Juan De Dios, 3 Merida Badajoz 06800",
    "addr:housenumber":"3",
    "addr:postcode":"06800",
    "addr:street":"Calle De San Juan;Dios",
    "iso:country":"ES",
    "sg:address":"Calle de San Juan De Dios, 3",
    "sg:city":"Merida",
    "sg:orig_category":"Comit\u00c9s De Organizaci\u00d3n De Exposiciones, Ferias, Salones",
    "sg:phone":"+34 924 30 44 35",
    "sg:postcode":"06800",
    "sg:province":"Badajoz",
    "wof:name":"Escena Congresos S.l.",
    "wof:placetype":"venue"
},
  "geometry": {"coordinates":[-6.3473329544,38.9170303345],"type":"Point"}
}