{
  "type": "Feature",
  "properties": {
    "iso:country":"ES",
    "sg:address":"Av Sta Oliva, 17",
    "sg:city":"Sta. Oliva",
    "sg:orig_category":"Mec\u00c1nico Del Autom\u00d3vil",
    "sg:phone":"+34 977 66 53 31",
    "sg:postcode":"43710",
    "sg:province":"Tarragona",
    "wof:name":"Cordoba Crespo Jose",
    "wof:placetype":"venue"
},
  "geometry": {"coordinates":[1.5496449471,41.2515335083],"type":"Point"}
}