{
  "type": "Feature",
  "properties": {
    "addr:full":"Carrer de Amadeu, 32 Calella Barcelona 08370",
    "addr:housenumber":"32",
    "addr:postcode":"08370",
    "addr:street":"Carrer De Amadeu",
    "iso:country":"ES",
    "sg:address":"Carrer de Amadeu, 32",
    "sg:city":"Calella",
    "sg:orig_category":"M\u00c1quinas De Escribir, M\u00c1quinas De Oficina (al Por Menor, Reparaci\u00d3n)",
    "sg:phone":"+34 937 69 09 95",
    "sg:postcode":"08370",
    "sg:province":"Barcelona",
    "wof:name":"Masvidal Perez Juan",
    "wof:placetype":"venue"
},
  "geometry": {"coordinates":[2.6649820805,41.6154060364],"type":"Point"}
}