{
  "type": "Feature",
  "properties": {
    "addr:full":"Calle de A\u00d1astro, 2 Madrid Madrid 28033",
    "addr:housenumber":"2",
    "addr:postcode":"28033",
    "addr:street":"Calle De An\u0303Astro",
    "iso:country":"ES",
    "sg:address":"Calle de A\u00d1astro, 2",
    "sg:city":"Madrid",
    "sg:classifiers":[
        {
            "category":"Banks & Credit Unions",
            "subcategory":"Bureau De Change",
            "type":"Services"
        }
    ],
    "sg:phone":"+34 917 66 59 08",
    "sg:postcode":"28033",
    "sg:province":"Madrid",
    "sg:tags":[
        "organismos",
        "control"
    ],
    "wof:name":"Bureau Veritas S.a.f.",
    "wof:placetype":"venue"
},
  "geometry": {"coordinates":[-3.6632289886,40.4673576355],"type":"Point"}
}