{
  "type": "Feature",
  "properties": {
    "addr:full":"Calle de Estafeta, 5 San Sebastian De Los Reyes Madrid 28700",
    "addr:housenumber":"5",
    "addr:postcode":"28700",
    "addr:street":"Calle De Estafeta",
    "iso:country":"ES",
    "sg:address":"Calle de Estafeta, 5",
    "sg:city":"San Sebastian De Los Reyes",
    "sg:orig_category":"Cristaler\u00cdas",
    "sg:phone":"+34 916 52 10 10",
    "sg:postcode":"28700",
    "sg:province":"Madrid",
    "wof:name":"Martin Poza Tirso",
    "wof:placetype":"venue"
},
  "geometry": {"coordinates":[-3.6239690781,40.5497741699],"type":"Point"}
}