{
  "type": "Feature",
  "properties": {
    "iso:country":"ES",
    "sg:address":"Reg Maria Cristina, 10",
    "sg:city":"Moral Calatrava",
    "sg:orig_category":"Asociaciones, Organismos Culturales Y Socioeducativos",
    "sg:phone":"+34 926 33 00 15",
    "sg:postcode":"13350",
    "sg:province":"Ciudad Real",
    "wof:name":"Sociedad Circulo Labradores",
    "wof:placetype":"venue"
},
  "geometry": {"coordinates":[-3.5799770355,38.829990387],"type":"Point"}
}