{
  "type": "Feature",
  "properties": {
    "addr:full":"Carrer de Balmes, 24 Barcelona Barcelona 08007",
    "addr:housenumber":"24",
    "addr:postcode":"08007",
    "addr:street":"Carrer De Balmes",
    "iso:country":"ES",
    "sg:address":"Carrer de Balmes, 24",
    "sg:city":"Barcelona",
    "sg:orig_category":"Arquitectos",
    "sg:phone":"+34 933 01 09 45",
    "sg:postcode":"08007",
    "sg:province":"Barcelona",
    "wof:name":"Organizacion Y Estudios Alfatres S. A.",
    "wof:placetype":"venue"
},
  "geometry": {"coordinates":[2.1647040844,41.3878974915],"type":"Point"}
}