{
  "type": "Feature",
  "properties": {
    "iso:country":"ES",
    "sg:address":"Avda Magdalena Sofia De Barat, 84",
    "sg:city":"Mairena Aljarafe",
    "sg:classifiers":[
        {
            "category":"Autos & Motor Vehicles",
            "subcategory":"Automobile Sales",
            "type":"Retail Goods"
        }
    ],
    "sg:phone":"+34 955 60 13 44",
    "sg:postcode":"41927",
    "sg:province":"Sevilla",
    "wof:name":"Martinez Lopez Juan Manuel",
    "wof:placetype":"venue"
},
  "geometry": {"coordinates":[-6.0472707748,37.3511390686],"type":"Point"}
}