{
  "type": "Feature",
  "properties": {
    "iso:country":"ES",
    "sg:address":"Calle de Buen Pastor, 3",
    "sg:city":"Benidorm",
    "sg:orig_category":"Reposter\u00cdas",
    "sg:phone":"+34 965 85 17 87",
    "sg:postcode":"03500",
    "sg:province":"Alicante",
    "wof:name":"Panaderia La Vienesa C.b.",
    "wof:placetype":"venue"
},
  "geometry": {"coordinates":[-0.1318662018,38.5406494141],"type":"Point"}
}