{
  "type": "Feature",
  "properties": {
    "iso:country":"ES",
    "sg:address":"Rua Boan, 8",
    "sg:city":"Vigo",
    "sg:orig_category":"Venta, Alquiler De Toldos",
    "sg:phone":"+34 986 28 36 20",
    "sg:postcode":"36207",
    "sg:province":"Pontevedra",
    "wof:name":"Tecozinc S.l.",
    "wof:placetype":"venue"
},
  "geometry": {"coordinates":[-8.6950883865,42.24842453],"type":"Point"}
}