{
  "type": "Feature",
  "properties": {
    "iso:country":"ES",
    "sg:address":"Araba Kalea, 43",
    "sg:city":"Zarautz",
    "sg:orig_category":"Empresas De Carpinter\u00cda De Madera",
    "sg:phone":"+34 943 83 55 88",
    "sg:postcode":"20800",
    "sg:province":"Guip\u00f9zcoa",
    "wof:name":"Osa Uzcudun Angel",
    "wof:placetype":"venue"
},
  "geometry": {"coordinates":[-2.1632819176,43.2811775208],"type":"Point"}
}