{
  "type": "Feature",
  "properties": {
    "addr:full":"Pol. Monzu, S/n Huesca Huesca 22006",
    "addr:housenumber":"s",
    "addr:postcode":"22006",
    "addr:street":"/ N",
    "iso:country":"ES",
    "sg:address":"Pol. Monzu, S/n",
    "sg:city":"Huesca",
    "sg:orig_category":"Electricidad: Equipos Industriales, Componentes (fabricaci\u00d3n)",
    "sg:phone":"+34 974 24 32 74",
    "sg:postcode":"22006",
    "sg:province":"Huesca",
    "wof:name":"Comercial Material Electrico Huesca S.l.",
    "wof:placetype":"venue"
},
  "geometry": {"coordinates":[-0.4083139896,42.1365661621],"type":"Point"}
}