{
  "type": "Feature",
  "properties": {
    "addr:full":"Carrer de Nil Fabra, 34 Barcelona Barcelona 08012",
    "addr:housenumber":"34",
    "addr:postcode":"08012",
    "addr:street":"Carrer De Nil Fabra",
    "iso:country":"ES",
    "sg:address":"Carrer de Nil Fabra, 34",
    "sg:city":"Barcelona",
    "sg:orig_category":"Venta, Localizaci\u00d3n, Reparaci\u00d3n De Material E Instrumental M\u00c9dico",
    "sg:phone":"+34 934 15 58 35",
    "sg:postcode":"08012",
    "sg:province":"Barcelona",
    "sg:website":"www.prim.es",
    "wof:name":"Prim S.a.",
    "wof:placetype":"venue"
},
  "geometry": {"coordinates":[2.1522469521,41.4061813354],"type":"Point"}
}