{
  "type": "Feature",
  "properties": {
    "iso:country":"ES",
    "sg:address":"Calle de Adela Hernandez, 3",
    "sg:city":"Bajos Y Tagoro",
    "sg:orig_category":"Empresas De Carpinter\u00cda De Madera",
    "sg:phone":"+34 922 58 06 09",
    "sg:postcode":"38380",
    "sg:province":"Santa Cruz De Tenerife",
    "wof:name":"Castilla Gonzalez Roberto",
    "wof:placetype":"venue"
},
  "geometry": {"coordinates":[-16.4786453247,28.4329319],"type":"Point"}
}