{
  "type": "Feature",
  "properties": {
    "addr:full":"Avda General Mola (del), 21 Santa Cruz De Tenerife Santa Cruz De Tenerife 38006",
    "addr:housenumber":"21",
    "addr:postcode":"38006",
    "addr:street":"Avda General Mola Del",
    "iso:country":"ES",
    "sg:address":"Avda General Mola (del), 21",
    "sg:city":"Santa Cruz De Tenerife",
    "sg:orig_category":"Servicios Gsm",
    "sg:phone":"+34 922 24 12 15",
    "sg:postcode":"38006",
    "sg:province":"Santa Cruz De Tenerife",
    "wof:name":"M.movil-ten S.l.",
    "wof:placetype":"venue"
},
  "geometry": {"coordinates":[-16.2628593445,28.4680595398],"type":"Point"}
}