{
  "type": "Feature",
  "properties": {
    "addr:full":"Mas Pujol(pol Ind Congost), 18 Llerona Barcelona 08520",
    "addr:housenumber":"18",
    "addr:postcode":"08520",
    "addr:street":"Congost",
    "iso:country":"ES",
    "sg:address":"Mas Pujol(pol Ind Congost), 18",
    "sg:city":"Llerona",
    "sg:orig_category":"Maquinaria Para Industrias Diversas",
    "sg:phone":"+34 938 46 40 53",
    "sg:postcode":"08520",
    "sg:province":"Barcelona",
    "wof:name":"Amg Tasman S.l.",
    "wof:placetype":"venue"
},
  "geometry": {"coordinates":[2.2982094288,41.6478767395],"type":"Point"}
}