{
  "type": "Feature",
  "properties": {
    "addr:full":"Larraul Diseminado, 30 Larraul Guip\u00f9zcoa 20159",
    "addr:housenumber":"30",
    "addr:postcode":"20159",
    "addr:street":"Larraul Diseminado;Guipu\u0300Zcoa",
    "iso:country":"ES",
    "sg:address":"Larraul Diseminado, 30",
    "sg:city":"Larraul",
    "sg:orig_category":"Promotores Constructores",
    "sg:phone":"+34 943 69 40 29",
    "sg:postcode":"20159",
    "sg:province":"Guip\u00f9zcoa",
    "wof:name":"Iraola Elosegi Jokin",
    "wof:placetype":"venue"
},
  "geometry": {"coordinates":[-2.0742990971,43.1991958618],"type":"Point"}
}