{
  "type": "Feature",
  "properties": {
    "addr:full":"Carr Barcelona, 31 Balaguer Lleida 25600",
    "addr:housenumber":"31",
    "addr:postcode":"25600",
    "addr:street":"Carr Barcelona",
    "iso:country":"ES",
    "sg:address":"Carr Barcelona, 31",
    "sg:city":"Balaguer",
    "sg:orig_category":"Agencias Y Agentes Comerciales, Representantes",
    "sg:phone":"+34 973 44 87 05",
    "sg:postcode":"25600",
    "sg:province":"Lleida",
    "wof:name":"Envanema Slu",
    "wof:placetype":"venue"
},
  "geometry": {"coordinates":[0.8115900159,41.7902603149],"type":"Point"}
}