{
  "type": "Feature",
  "properties": {
    "iso:country":"ES",
    "sg:address":"Calle de Eduardo Nu\u00d1ez, 4",
    "sg:city":"Montijo",
    "sg:orig_category":"Notarios",
    "sg:phone":"+34 924 45 30 00",
    "sg:postcode":"06480",
    "sg:province":"Badajoz",
    "wof:name":"Peralta Esperilla Antonio Francisco",
    "wof:placetype":"venue"
},
  "geometry": {"coordinates":[-6.6142539978,38.9074668884],"type":"Point"}
}