{
  "type": "Feature",
  "properties": {
    "iso:country":"ES",
    "sg:address":"Calle de Trueno (del), 1",
    "sg:city":"Colmenar Viejo",
    "sg:orig_category":"M\u00c9dicos: Endocrinolog\u00cda Y Metabolismo",
    "sg:phone":"+34 918 46 17 51",
    "sg:postcode":"28770",
    "sg:province":"Madrid",
    "wof:name":"Aguirre Tabernero Ana Isabel",
    "wof:placetype":"venue"
},
  "geometry": {"coordinates":[-3.7682797909,40.6596031189],"type":"Point"}
}