{
  "type": "Feature",
  "properties": {
    "iso:country":"ES",
    "sg:address":"Avda Maragatos, 4",
    "sg:city":"Benavente",
    "sg:orig_category":"Electricidad: Instaladores",
    "sg:phone":"+34 980 63 71 69",
    "sg:postcode":"49600",
    "sg:province":"Zamora",
    "wof:name":"Electricidad Merillas S.l.",
    "wof:placetype":"venue"
},
  "geometry": {"coordinates":[-5.6770429611,42.006023407],"type":"Point"}
}