{
  "type": "Feature",
  "properties": {
    "iso:country":"ES",
    "sg:address":"Calle de Victor De La Serna, 6",
    "sg:city":"Madrid",
    "sg:orig_category":"Cl\u00cdnicas M\u00c9dicas",
    "sg:phone":"+34 915 19 79 93",
    "sg:postcode":"28016",
    "sg:province":"Madrid",
    "wof:name":"Gutierrez Montoliu Jose Antonio",
    "wof:placetype":"venue"
},
  "geometry": {"coordinates":[-3.6733388901,40.4523849487],"type":"Point"}
}