{
  "type": "Feature",
  "properties": {
    "iso:country":"ES",
    "sg:address":"Avda Doctor Constantino Cabaneiro, S/n",
    "sg:city":"Pastoriza",
    "sg:orig_category":"Ropa Para Se\u00d1oras Y Caballeros (al Por Menor)",
    "sg:phone":"+34 982 33 21 69",
    "sg:postcode":"27287",
    "sg:province":"Lugo",
    "wof:name":"Luaces Seco Venancio",
    "wof:placetype":"venue"
},
  "geometry": {"coordinates":[-7.3505592346,43.3002243042],"type":"Point"}
}