{
  "type": "Feature",
  "properties": {
    "iso:country":"ES",
    "sg:address":"Calle de Aeronautica, 17",
    "sg:city":"Alcorcon",
    "sg:orig_category":"Centros Empresariales",
    "sg:phone":"+34 915 40 04 22",
    "sg:postcode":"28925",
    "sg:province":"Madrid",
    "wof:name":"Solmad Iluminacion S.l.",
    "wof:placetype":"venue"
},
  "geometry": {"coordinates":[-3.8172461987,40.3345718384],"type":"Point"}
}