{
  "type": "Feature",
  "properties": {
    "addr:full":"Sepes Poligono, 5 Huesca Huesca 22099",
    "addr:housenumber":"5",
    "addr:postcode":"22099",
    "addr:street":"Poligono",
    "iso:country":"ES",
    "sg:address":"Sepes Poligono, 5",
    "sg:city":"Huesca",
    "sg:orig_category":"Ense\u00d1anza, Formaci\u00d3n Profesional: Aprendizaje",
    "sg:phone":"+34 974 22 78 82",
    "sg:postcode":"22099",
    "sg:province":"Huesca",
    "wof:name":"Tesoreria General De La Seguridad Social",
    "wof:placetype":"venue"
},
  "geometry": {"coordinates":[-0.4083139896,42.1365661621],"type":"Point"}
}