{
  "type": "Feature",
  "properties": {
    "addr:full":"Calle de Posito, S/n Atalaya Badajoz 06329",
    "addr:housenumber":"s / n",
    "addr:postcode":"06329",
    "addr:street":"Calle De Posito",
    "iso:country":"ES",
    "sg:address":"Calle de Posito, S/n",
    "sg:city":"Atalaya",
    "sg:orig_category":"Confecci\u00d3n De Trajes Para Se\u00d1oras",
    "sg:phone":"+34 924 56 02 52",
    "sg:postcode":"06329",
    "sg:province":"Badajoz",
    "wof:name":"Fuente Atlaya S.l.l.",
    "wof:placetype":"venue"
},
  "geometry": {"coordinates":[-6.475938797,38.334186554],"type":"Point"}
}