{
  "type": "Feature",
  "properties": {
    "iso:country":"ES",
    "sg:address":"Carretera Baza-lorca, Km. 0072,2",
    "sg:city":"Albox",
    "sg:orig_category":"Muebles, Minoristas",
    "sg:phone":"+34 950 12 09 92",
    "sg:postcode":"04800",
    "sg:province":"Almer\u00eda",
    "wof:name":"Lopez Domene Miguel Angel",
    "wof:placetype":"venue"
},
  "geometry": {"coordinates":[-2.1415529251,37.4031028748],"type":"Point"}
}