{
  "type": "Feature",
  "properties": {
    "iso:country":"ES",
    "sg:address":"Pase San Francisco, 13",
    "sg:city":"Badajoz",
    "sg:orig_category":"Peluqueros: De Se\u00d1oras",
    "sg:phone":"+34 924 22 08 63",
    "sg:postcode":"06001",
    "sg:province":"Badajoz",
    "wof:name":"Fepoma S.l.",
    "wof:placetype":"venue"
},
  "geometry": {"coordinates":[-6.9735498428,38.8770980835],"type":"Point"}
}