{
  "type": "Feature",
  "properties": {
    "iso:country":"ES",
    "sg:address":"Calle de Doctor Moragas, 5",
    "sg:city":"Coru\u00d1a",
    "sg:orig_category":"Navegaci\u00d3n (equipos Fluviales)",
    "sg:phone":"+34 981 29 01 13",
    "sg:postcode":"15006",
    "sg:province":"A Coru\u00f1a",
    "wof:name":"Xeitoso Y Caravel S.l.",
    "wof:placetype":"venue"
},
  "geometry": {"coordinates":[-8.403254509,43.3576774597],"type":"Point"}
}