{
  "type": "Feature",
  "properties": {
    "addr:full":"Calle de Clavellina, 2 Caceres C\u00e1ceres 10003",
    "addr:housenumber":"2",
    "addr:postcode":"10003",
    "addr:street":"Calle De Clavellina;Ca\u0301Ceres",
    "iso:country":"ES",
    "sg:address":"Calle de Clavellina, 2",
    "sg:city":"Caceres",
    "sg:orig_category":"Librer\u00cdas",
    "sg:phone":"+34 927 21 25 54",
    "sg:postcode":"10003",
    "sg:province":"C\u00e1ceres",
    "wof:name":"Gonzalez Macedo Luis Antonio",
    "wof:placetype":"venue"
},
  "geometry": {"coordinates":[-6.2800865173,39.5237045288],"type":"Point"}
}