{
  "type": "Feature",
  "properties": {
    "addr:full":"Calle de Noelia Afonso Cabrera, S/n Playa Americas Santa Cruz De Tenerife 38660",
    "addr:housenumber":"s / n",
    "addr:postcode":"38660",
    "addr:street":"Calle De Noelia Afonso Cabrera;Americas",
    "iso:country":"ES",
    "sg:address":"Calle de Noelia Afonso Cabrera, S/n",
    "sg:city":"Playa Americas",
    "sg:orig_category":"Agencias De Viajes",
    "sg:phone":"+34 922 75 31 52",
    "sg:postcode":"38660",
    "sg:province":"Santa Cruz De Tenerife",
    "wof:name":"Travelplan S.a.",
    "wof:placetype":"venue"
},
  "geometry": {"coordinates":[-16.7317714691,28.0760765076],"type":"Point"}
}