{
  "type": "Feature",
  "properties": {
    "iso:country":"ES",
    "sg:address":"Calle de Real, S/n",
    "sg:city":"Cabezarados",
    "sg:orig_category":"Venta, Instalaci\u00d3n De Cocinas",
    "sg:phone":"+34 926 83 52 14",
    "sg:postcode":"13192",
    "sg:province":"Ciudad Real",
    "wof:name":"Carretero Zamora Miguel Angel",
    "wof:placetype":"venue"
},
  "geometry": {"coordinates":[-4.2984280586,38.8461494446],"type":"Point"}
}