{
  "type": "Feature",
  "properties": {
    "addr:full":"Carr Real (del), 2 Albaida Valencia 46860",
    "addr:housenumber":"2",
    "addr:postcode":"46860",
    "addr:street":"Carr Real Del",
    "iso:country":"ES",
    "sg:address":"Carr Real (del), 2",
    "sg:city":"Albaida",
    "sg:orig_category":"Peluquer\u00cdas, Peluquer\u00cda Mixta",
    "sg:phone":"+34 962 90 06 69",
    "sg:postcode":"46860",
    "sg:province":"Valencia",
    "wof:name":"Peluqueria Raul Y Toni S.l.",
    "wof:placetype":"venue"
},
  "geometry": {"coordinates":[-0.5223839879,38.8395118713],"type":"Point"}
}