{
  "type": "Feature",
  "properties": {
    "addr:full":"Carrer de Roger De Lluria, 8 Terrassa Barcelona 08223",
    "addr:housenumber":"8",
    "addr:postcode":"08223",
    "addr:street":"Carrer De Roger De Lluria",
    "iso:country":"ES",
    "sg:address":"Carrer de Roger De Lluria, 8",
    "sg:city":"Terrassa",
    "sg:orig_category":"Aguas (distribuci\u00d3n, Servicios)",
    "sg:phone":"+34 937 85 02 93",
    "sg:postcode":"08223",
    "sg:province":"Barcelona",
    "wof:name":"Extintors Te-go Csv S.l.",
    "wof:placetype":"venue"
},
  "geometry": {"coordinates":[2.0126860142,41.5569763184],"type":"Point"}
}