{
  "type": "Feature",
  "properties": {
    "addr:full":"Pase Calanda, 45 Zaragoza Zaragoza 50010",
    "addr:housenumber":"45",
    "addr:postcode":"50010",
    "addr:street":"Calanda",
    "iso:country":"ES",
    "sg:address":"Pase Calanda, 45",
    "sg:city":"Zaragoza",
    "sg:orig_category":"Fotograf\u00cda Y Cine: Aparatos, Pel\u00cdculas Y Accesorios (fabricaci\u00d3n, Al Por Mayor)",
    "sg:phone":"+34 976 53 08 13",
    "sg:postcode":"50010",
    "sg:province":"Zaragoza",
    "wof:name":"Moles Espadas Francisco",
    "wof:placetype":"venue"
},
  "geometry": {"coordinates":[-0.9028270245,41.6504211426],"type":"Point"}
}