{
  "type": "Feature",
  "properties": {
    "iso:country":"ES",
    "sg:address":"Carrer de Lluis Muntadas, 11",
    "sg:city":"Barcelona",
    "sg:orig_category":"Inmobiliaria (agencias)",
    "sg:phone":"+34 932 11 28 39",
    "sg:postcode":"08035",
    "sg:province":"Barcelona",
    "wof:name":"Ranufa S.l.",
    "wof:placetype":"venue"
},
  "geometry": {"coordinates":[2.1331810951,41.4159812927],"type":"Point"}
}