{
  "type": "Feature",
  "properties": {
    "iso:country":"ES",
    "sg:address":"Calle de Rafael De La Haba, 3",
    "sg:city":"Bollullos Par Condado",
    "sg:orig_category":"Suministros Para Carrocer\u00cdas",
    "sg:phone":"+34 959 41 04 88",
    "sg:postcode":"21710",
    "sg:province":"Huelva",
    "wof:name":"Gonzalez Diaz Jose Maria",
    "wof:placetype":"venue"
},
  "geometry": {"coordinates":[-6.5423002243,37.3371925354],"type":"Point"}
}