{
  "type": "Feature",
  "properties": {
    "iso:country":"ES",
    "sg:address":"Calle de Toledo, 2",
    "sg:city":"Badajoz",
    "sg:orig_category":"Plomeros",
    "sg:phone":"+34 924 25 36 82",
    "sg:postcode":"06008",
    "sg:province":"Badajoz",
    "wof:name":"Sevilla Silva Bernardino",
    "wof:placetype":"venue"
},
  "geometry": {"coordinates":[-6.9590988159,38.879650116],"type":"Point"}
}