{
  "type": "Feature",
  "properties": {
    "addr:full":"Calle de General Ollero, 1 Sevilla Sevilla 41006",
    "addr:housenumber":"1",
    "addr:postcode":"41006",
    "addr:street":"Calle De General Ollero",
    "iso:country":"ES",
    "sg:address":"Calle de General Ollero, 1",
    "sg:city":"Sevilla",
    "sg:orig_category":"Farmacias",
    "sg:phone":"+34 954 52 07 74",
    "sg:postcode":"41006",
    "sg:province":"Sevilla",
    "wof:name":"Romero Munoz Leopoldo",
    "wof:placetype":"venue"
},
  "geometry": {"coordinates":[-5.9484238625,37.3852462769],"type":"Point"}
}