{
  "type": "Feature",
  "properties": {
    "iso:country":"ES",
    "sg:address":"Calle de Ebanisteria, 3",
    "sg:city":"Torrejon Ardoz",
    "sg:orig_category":"Trabajos De Soldaduras",
    "sg:phone":"+34 916 77 73 99",
    "sg:postcode":"28850",
    "sg:province":"Madrid",
    "wof:name":"Metalurgica Jaraes S.l.l.",
    "wof:placetype":"venue"
},
  "geometry": {"coordinates":[-3.4645609856,40.4440803528],"type":"Point"}
}