{
  "type": "Feature",
  "properties": {
    "addr:full":"Calle de Encimera, 4 Villasana Mena Burgos 09580",
    "addr:housenumber":"4",
    "addr:postcode":"09580",
    "addr:street":"Calle De Encimera;Villasana Mena",
    "iso:country":"ES",
    "sg:address":"Calle de Encimera, 4",
    "sg:city":"Villasana Mena",
    "sg:orig_category":"Caf\u00c9s, Bares, Cervecer\u00cdas",
    "sg:phone":"+34 947 12 63 93",
    "sg:postcode":"09580",
    "sg:province":"Burgos",
    "wof:name":"Fernandez Gil Jose",
    "wof:placetype":"venue"
},
  "geometry": {"coordinates":[-3.2845933437,43.0992050171],"type":"Point"}
}