{
  "type": "Feature",
  "properties": {
    "iso:country":"ES",
    "sg:address":"Calle de Vi\u00d1a, 25",
    "sg:city":"Badajoz",
    "sg:orig_category":"Chapister\u00cda",
    "sg:phone":"+34 924 24 85 28",
    "sg:postcode":"06011",
    "sg:province":"Badajoz",
    "wof:name":"Soto Rodriguez Jorge",
    "wof:placetype":"venue"
},
  "geometry": {"coordinates":[-6.9856290817,38.8575706482],"type":"Point"}
}