{
  "type": "Feature",
  "properties": {
    "iso:country":"ES",
    "sg:address":"Plaz Del Kasko, 2",
    "sg:city":"Sestao",
    "sg:orig_category":"Bancos",
    "sg:phone":"+34 944 72 43 12",
    "sg:postcode":"48910",
    "sg:province":"Vizcaya",
    "wof:name":"Banco Popular Espa\u00d1ol S.a.",
    "wof:placetype":"venue"
},
  "geometry": {"coordinates":[-3.007666111,43.3094024658],"type":"Point"}
}