{
  "type": "Feature",
  "properties": {
    "addr:full":"Calle de Arcipreste De Hita, 14 Motril Granada 18600",
    "addr:housenumber":"14",
    "addr:postcode":"18600",
    "addr:street":"Calle De Arcipreste De Hita",
    "iso:country":"ES",
    "sg:address":"Calle de Arcipreste De Hita, 14",
    "sg:city":"Motril",
    "sg:orig_category":"Delegados, Agentes De Tr\u00c1nsito, Auxiliares De Transporte Internacional",
    "sg:phone":"+34 958 60 08 59",
    "sg:postcode":"18600",
    "sg:province":"Granada",
    "wof:name":"Martin Ruiz Angel",
    "wof:placetype":"venue"
},
  "geometry": {"coordinates":[-3.515131712,36.7551727295],"type":"Point"}
}