{
  "type": "Feature",
  "properties": {
    "iso:country":"ES",
    "sg:address":"Calle de Torres Quevedo, 3",
    "sg:city":"Ponferrada",
    "sg:orig_category":"Fotograf\u00cda Art\u00cdstica Y Retratos",
    "sg:phone":"+34 987 40 09 04",
    "sg:postcode":"24400",
    "sg:province":"Le\u00f3n",
    "wof:name":"Otero Miguelez Blas",
    "wof:placetype":"venue"
},
  "geometry": {"coordinates":[-6.6022210121,42.5505638123],"type":"Point"}
}