{
  "type": "Feature",
  "properties": {
    "addr:full":"Grup Arriberri, 6 Donostia-san Sebastian Guip\u00f9zcoa 20017",
    "addr:housenumber":"6",
    "addr:postcode":"20017",
    "addr:street":"Arriberri",
    "iso:country":"ES",
    "sg:address":"Grup Arriberri, 6",
    "sg:city":"Donostia-san Sebastian",
    "sg:orig_category":"Inform\u00c1tica, Ofim\u00c1tica (estudios, Asesor\u00cda, Ingenier\u00cda, Formaci\u00d3n)",
    "sg:phone":"+34 943 35 00 39",
    "sg:postcode":"20017",
    "sg:province":"Guip\u00f9zcoa",
    "wof:name":"Informatica Y Telecomunicaciones Web S.l.",
    "wof:placetype":"venue"
},
  "geometry": {"coordinates":[-1.9285449982,43.3174858093],"type":"Point"}
}