{
  "type": "Feature",
  "properties": {
    "iso:country":"ES",
    "sg:address":"Carr Gomez Ferrer, 13",
    "sg:city":"Picassent",
    "sg:orig_category":"M\u00c9dicos: Estomatolog\u00cda",
    "sg:phone":"+34 961 23 31 45",
    "sg:postcode":"46220",
    "sg:province":"Valencia",
    "wof:name":"Calatayud Lliso Miguel",
    "wof:placetype":"venue"
},
  "geometry": {"coordinates":[-0.4624040127,39.3619613647],"type":"Point"}
}