{
  "type": "Feature",
  "properties": {
    "addr:full":"Pl Doctor Robert, 4 Terrassa Barcelona 08221",
    "addr:housenumber":"4",
    "addr:postcode":"08221",
    "addr:street":"Pl Doctor Robert",
    "iso:country":"ES",
    "sg:address":"Pl Doctor Robert, 4",
    "sg:city":"Terrassa",
    "sg:orig_category":"Doctores En Medicina",
    "sg:phone":"+34 937 31 56 75",
    "sg:postcode":"08221",
    "sg:province":"Barcelona",
    "wof:name":"Sanahuja Mota Jaume",
    "wof:placetype":"venue"
},
  "geometry": {"coordinates":[2.0164349079,41.5633850098],"type":"Point"}
}