{
  "type": "Feature",
  "properties": {
    "addr:full":"Calle de San Pedro, 1 Burutain Navarra 31798",
    "addr:housenumber":"1",
    "addr:postcode":"31798",
    "addr:street":"Calle De San Pedro",
    "iso:country":"ES",
    "sg:address":"Calle de San Pedro, 1",
    "sg:city":"Burutain",
    "sg:orig_category":"Teatros Y Salas De Espect\u00c1culos",
    "sg:phone":"+34 948 30 71 50",
    "sg:postcode":"31798",
    "sg:province":"Navarra",
    "wof:name":"Trokolo S.i",
    "wof:placetype":"venue"
},
  "geometry": {"coordinates":[-1.6173770428,42.9612770081],"type":"Point"}
}