{
  "type": "Feature",
  "properties": {
    "iso:country":"ES",
    "sg:address":"Carrer de Gravina, 63",
    "sg:city":"Mataro",
    "sg:orig_category":"Doctores En Medicina",
    "sg:phone":"+34 937 98 66 36",
    "sg:postcode":"08301",
    "sg:province":"Barcelona",
    "wof:name":"Juanola Costa Jose",
    "wof:placetype":"venue"
},
  "geometry": {"coordinates":[2.443625927,41.5339050293],"type":"Point"}
}