{
  "type": "Feature",
  "properties": {
    "addr:full":"Av Generalitat (de La), 151 Tortosa Tarragona 43500",
    "addr:housenumber":"151",
    "addr:postcode":"43500",
    "addr:street":"Av Generalitat De La",
    "iso:country":"ES",
    "sg:address":"Av Generalitat (de La), 151",
    "sg:city":"Tortosa",
    "sg:orig_category":"Pescader\u00cdas (al Por Menor)",
    "sg:phone":"+34 977 44 44 41",
    "sg:postcode":"43500",
    "sg:province":"Tarragona",
    "wof:name":"Castejon Marti Maria Cinta",
    "wof:placetype":"venue"
},
  "geometry": {"coordinates":[0.5206819773,40.8046226501],"type":"Point"}
}