{
  "type": "Feature",
  "properties": {
    "addr:full":"Calle de Canovas Del Castillo, 65 Puerto Valencia 46520",
    "addr:housenumber":"65",
    "addr:postcode":"46520",
    "addr:street":"Calle De Canovas Del Castillo",
    "iso:country":"ES",
    "sg:address":"Calle de Canovas Del Castillo, 65",
    "sg:city":"Puerto",
    "sg:orig_category":"Agencias Y Agentes Comerciales, Representantes",
    "sg:phone":"+34 962 67 00 64",
    "sg:postcode":"46520",
    "sg:province":"Valencia",
    "wof:name":"Foved Valenzuela Juan Felix",
    "wof:placetype":"venue"
},
  "geometry": {"coordinates":[-0.2125553936,39.6625900269],"type":"Point"}
}