{
  "type": "Feature",
  "properties": {
    "addr:full":"Avgd Del Cami Nou, 228 Xirivella Valencia 46950",
    "addr:housenumber":"228",
    "addr:postcode":"46950",
    "addr:street":"Nou",
    "iso:country":"ES",
    "sg:address":"Avgd Del Cami Nou, 228",
    "sg:city":"Xirivella",
    "sg:orig_category":"Molduras, Junquillos, Listones Y Molduras Perforadas",
    "sg:phone":"+34 963 50 30 29",
    "sg:postcode":"46950",
    "sg:province":"Valencia",
    "wof:name":"Moreno Fresneda Maria Gabriela",
    "wof:placetype":"venue"
},
  "geometry": {"coordinates":[-0.4380899966,39.4629135132],"type":"Point"}
}