{
  "type": "Feature",
  "properties": {
    "addr:full":"Gesalibar Auzoa, 15 Gesalibar Guip\u00f9zcoa 20509",
    "addr:housenumber":"15",
    "addr:postcode":"20509",
    "addr:street":"Gesalibar Auzoa;Guipu\u0300Zcoa",
    "iso:country":"ES",
    "sg:address":"Gesalibar Auzoa, 15",
    "sg:city":"Gesalibar",
    "sg:orig_category":"Hospitales",
    "sg:phone":"+34 943 79 14 38",
    "sg:postcode":"20509",
    "sg:province":"Guip\u00f9zcoa",
    "wof:name":"Hospital Psiquiatrico Aita Menni",
    "wof:placetype":"venue"
},
  "geometry": {"coordinates":[-2.520637989,43.0691261292],"type":"Point"}
}