{
  "type": "Feature",
  "properties": {
    "addr:full":"Calle de Maestro Nicolas, 8 Le\u00f3n Le\u00f3n 24005",
    "addr:housenumber":"8",
    "addr:postcode":"24005",
    "addr:street":"Calle De Maestro Nicolas;Leo\u0301N",
    "iso:country":"ES",
    "sg:address":"Calle de Maestro Nicolas, 8",
    "sg:city":"Le\u00f3n",
    "sg:orig_category":"Restaurantes",
    "sg:phone":"+34 987 25 79 76",
    "sg:postcode":"24005",
    "sg:province":"Le\u00f3n",
    "wof:name":"Ou  Ling Ling",
    "wof:placetype":"venue"
},
  "geometry": {"coordinates":[-5.5708470345,42.587223053],"type":"Point"}
}