{
  "type": "Feature",
  "properties": {
    "iso:country":"ES",
    "sg:address":"Maunfe, 9",
    "sg:city":"Maunfe",
    "sg:orig_category":"Agencias Y Agentes Comerciales, Representantes",
    "sg:phone":"+34 982 17 67 91",
    "sg:postcode":"27155",
    "sg:province":"Lugo",
    "wof:name":"Varela Y Pastrana C.b.",
    "wof:placetype":"venue"
},
  "geometry": {"coordinates":[-7.6035451889,43.0928039551],"type":"Point"}
}