{
  "type": "Feature",
  "properties": {
    "iso:country":"ES",
    "sg:address":"Av Llibertat, 137",
    "sg:city":"Elche",
    "sg:orig_category":"Mutuas De Seguros",
    "sg:phone":"+34 966 66 00 24",
    "sg:postcode":"03201",
    "sg:province":"Alicante",
    "wof:name":"Mutua Valenciana Automovilista Seguros A Prima Fija",
    "wof:placetype":"venue"
},
  "geometry": {"coordinates":[-0.7137770057,38.263004303],"type":"Point"}
}