{
  "type": "Feature",
  "properties": {
    "iso:country":"ES",
    "sg:address":"Calle de Cuba, 23",
    "sg:city":"Tablero",
    "sg:orig_category":"Electrodom\u00c9sticos (fabricaci\u00d3n, Al Por Mayor)",
    "sg:phone":"+34 928 14 34 26",
    "sg:postcode":"35100",
    "sg:province":"Las Palmas",
    "wof:name":"Suarez Miranda Paulino",
    "wof:placetype":"venue"
},
  "geometry": {"coordinates":[-15.6036195755,27.7702140808],"type":"Point"}
}