{
  "type": "Feature",
  "properties": {
    "iso:country":"ES",
    "sg:address":"Calle de Zoraya, 20",
    "sg:city":"Granada",
    "sg:orig_category":"Ense\u00d1anza, Formaci\u00d3n Profesional: Aprendizaje",
    "sg:phone":"+34 958 12 02 50",
    "sg:postcode":"18008",
    "sg:province":"Granada",
    "wof:name":"Capitan Vallvey Luis Fermin",
    "wof:placetype":"venue"
},
  "geometry": {"coordinates":[-3.5805149078,37.1621208191],"type":"Point"}
}