{
  "type": "Feature",
  "properties": {
    "addr:full":"Calle de Obispo Segura Saez, 8 Caceres C\u00e1ceres 10001",
    "addr:housenumber":"8",
    "addr:postcode":"10001",
    "addr:street":"Calle De Obispo Segura Saez;Ca\u0301Ceres",
    "iso:country":"ES",
    "sg:address":"Calle de Obispo Segura Saez, 8",
    "sg:city":"Caceres",
    "sg:orig_category":"Administraci\u00d3n En Agricultura",
    "sg:phone":"+34 927 62 66 29",
    "sg:postcode":"10001",
    "sg:province":"C\u00e1ceres",
    "wof:name":"Union De Peque\u00f1os Agricultotes De Extremadura",
    "wof:placetype":"venue"
},
  "geometry": {"coordinates":[-6.3786702156,39.4719161987],"type":"Point"}
}