{
  "type": "Feature",
  "properties": {
    "iso:country":"ES",
    "sg:address":"Carr Ribarroja, 43",
    "sg:city":"Manises",
    "sg:orig_category":"Ropa Para Se\u00d1oras (al Por Menor)",
    "sg:phone":"+34 961 52 31 98",
    "sg:postcode":"46940",
    "sg:province":"Valencia",
    "wof:name":"Gonzalez Chico Carmen",
    "wof:placetype":"venue"
},
  "geometry": {"coordinates":[-0.5143820047,39.4729690552],"type":"Point"}
}