{
  "type": "Feature",
  "properties": {
    "iso:country":"ES",
    "sg:address":"Calle de Asensi, 1",
    "sg:city":"Castellon",
    "sg:orig_category":"Administradores De Bienes Y Delegados De Comunidades De Propietarios",
    "sg:phone":"+34 964 24 50 40",
    "sg:postcode":"12002",
    "sg:province":"Castell\u00f3n",
    "wof:name":"Abiplana S.l.",
    "wof:placetype":"venue"
},
  "geometry": {"coordinates":[-0.037967,39.983482],"type":"Point"}
}