{
  "type": "Feature",
  "properties": {
    "addr:full":"Calle de Emilio Thuillier, 84 Malaga M\u00e1laga 29014",
    "addr:housenumber":"84",
    "addr:postcode":"29014",
    "addr:street":"Calle De Emilio Thuillier;Ma\u0301Laga",
    "iso:country":"ES",
    "sg:address":"Calle de Emilio Thuillier, 84",
    "sg:city":"Malaga",
    "sg:orig_category":"Chapister\u00cda",
    "sg:phone":"+34 952 25 84 00",
    "sg:postcode":"29014",
    "sg:province":"M\u00e1laga",
    "wof:name":"Talleres Thuiller S.l.l.",
    "wof:placetype":"venue"
},
  "geometry": {"coordinates":[-4.4216489792,36.7460708618],"type":"Point"}
}