{
  "type": "Feature",
  "properties": {
    "addr:full":"Carrer de Torres I Bages, 2 Sant Vicen\u00c7 Dels Horts Barcelona 08620",
    "addr:housenumber":"2",
    "addr:postcode":"08620",
    "addr:street":"Carrer De Torres I Bages",
    "iso:country":"ES",
    "sg:address":"Carrer de Torres I Bages, 2",
    "sg:city":"Sant Vicen\u00c7 Dels Horts",
    "sg:orig_category":"Comunidades Religiosas",
    "sg:phone":"+34 936 56 16 56",
    "sg:postcode":"08620",
    "sg:province":"Barcelona",
    "wof:name":"Centre Catolic",
    "wof:placetype":"venue"
},
  "geometry": {"coordinates":[2.0087769032,41.3924751282],"type":"Point"}
}