{
  "type": "Feature",
  "properties": {
    "iso:country":"ES",
    "sg:address":"Carrer de Alvar Aalto, S/n",
    "sg:city":"Manresa",
    "sg:orig_category":"Agencias De Viajes",
    "sg:phone":"+34 938 75 74 06",
    "sg:postcode":"08243",
    "sg:province":"Barcelona",
    "sg:website":"www.carrefour.es/viajes",
    "wof:name":"Viajes Carrefour S.l.",
    "wof:placetype":"venue"
},
  "geometry": {"coordinates":[1.8438060284,41.7217254639],"type":"Point"}
}