{
  "type": "Feature",
  "properties": {
    "iso:country":"ES",
    "sg:address":"Calle de Valencia, 20",
    "sg:city":"Madrid",
    "sg:orig_category":"T\u00c9cnicos Veterinarios",
    "sg:phone":"+34 915 39 99 15",
    "sg:postcode":"28012",
    "sg:province":"Madrid",
    "wof:name":"Valmeda Veterinaios S.l.",
    "wof:placetype":"venue"
},
  "geometry": {"coordinates":[-3.7002689838,40.4070739746],"type":"Point"}
}