{
  "type": "Feature",
  "properties": {
    "iso:country":"ES",
    "sg:address":"Carrer de Veguer, 11",
    "sg:city":"Barcelona",
    "sg:orig_category":"Centros Empresariales",
    "sg:phone":"+34 932 68 22 36",
    "sg:postcode":"08002",
    "sg:province":"Barcelona",
    "wof:name":"De La Torre Quesada Pedro",
    "wof:placetype":"venue"
},
  "geometry": {"coordinates":[2.1774890423,41.3838806152],"type":"Point"}
}