{
  "type": "Feature",
  "properties": {
    "iso:country":"ES",
    "sg:address":"Pase Faro Del, 40",
    "sg:city":"Donostia-san Sebastian",
    "sg:orig_category":"Ingeniero",
    "sg:phone":"+34 943 31 07 12",
    "sg:postcode":"20008",
    "sg:province":"Guip\u00f9zcoa",
    "wof:name":"Dubega Ingenieros S.l.",
    "wof:placetype":"venue"
},
  "geometry": {"coordinates":[-2.0392899513,43.3088798523],"type":"Point"}
}