{
  "type": "Feature",
  "properties": {
    "addr:full":"Carrer de Aleixar (cami De L'), 40 Reus Tarragona 43202",
    "addr:housenumber":"40",
    "addr:postcode":"43202",
    "addr:street":"Carrer De Aleixar Cami De L '",
    "iso:country":"ES",
    "sg:address":"Carrer de Aleixar (cami De L'), 40",
    "sg:city":"Reus",
    "sg:orig_category":"M\u00c9dicos: An\u00c1lisis Cl\u00cdnicos",
    "sg:phone":"+34 977 33 17 38",
    "sg:postcode":"43202",
    "sg:province":"Tarragona",
    "wof:name":"Laboratori De Analisis Cliniques Analisis Lab S.l.",
    "wof:placetype":"venue"
},
  "geometry": {"coordinates":[1.1000570059,41.1570053101],"type":"Point"}
}