{
  "type": "Feature",
  "properties": {
    "iso:country":"ES",
    "sg:address":"Avda Rafaela Ybarra, 33",
    "sg:city":"Madrid",
    "sg:orig_category":"Molduras, Junquillos, Listones Y Molduras Perforadas",
    "sg:phone":"+34 914 69 43 77",
    "sg:postcode":"28026",
    "sg:province":"Madrid",
    "wof:name":"Alvarado Dominguez Antonio",
    "wof:placetype":"venue"
},
  "geometry": {"coordinates":[-3.7112603188,40.3832893372],"type":"Point"}
}