{
  "type": "Feature",
  "properties": {
    "addr:full":"Calle de Urbieta, 48 Donostia-san Sebastian Guip\u00f9zcoa 20006",
    "addr:housenumber":"48",
    "addr:postcode":"20006",
    "addr:street":"Calle De Urbieta",
    "iso:country":"ES",
    "sg:address":"Calle de Urbieta, 48",
    "sg:city":"Donostia-san Sebastian",
    "sg:orig_category":"Sociedades, Compa\u00d1\u00cdas Aseguradoras",
    "sg:phone":"+34 943 42 36 39",
    "sg:postcode":"20006",
    "sg:province":"Guip\u00f9zcoa",
    "wof:name":"Correduria De Seguros Esnal & Lacar S.l.",
    "wof:placetype":"venue"
},
  "geometry": {"coordinates":[-1.9813649654,43.3146934509],"type":"Point"}
}