{
  "type": "Feature",
  "properties": {
    "addr:full":"Carrer de Mallorca, 367 Barcelona Barcelona 08013",
    "addr:housenumber":"367",
    "addr:postcode":"08013",
    "addr:street":"Carrer De Mallorca",
    "iso:country":"ES",
    "sg:address":"Carrer de Mallorca, 367",
    "sg:city":"Barcelona",
    "sg:orig_category":"Asesor\u00cda Fiscal Y Jur\u00cddica",
    "sg:phone":"+34 932 07 23 46",
    "sg:postcode":"08013",
    "sg:province":"Barcelona",
    "wof:name":"Garcia-portusach Consultores S.l.",
    "wof:placetype":"venue"
},
  "geometry": {"coordinates":[2.1726620197,41.401599884],"type":"Point"}
}