{
  "type": "Feature",
  "properties": {
    "iso:country":"ES",
    "sg:address":"Calle de Pe\u00d1aflorida, 1",
    "sg:city":"Donostia-san Sebastian",
    "sg:orig_category":"Psic\u00d3logos",
    "sg:phone":"+34 943 42 82 38",
    "sg:postcode":"20004",
    "sg:province":"Guip\u00f9zcoa",
    "wof:name":"Martin Gomez Maria Victoria",
    "wof:placetype":"venue"
},
  "geometry": {"coordinates":[-1.9832129478,43.3211021423],"type":"Point"}
}