{
  "type": "Feature",
  "properties": {
    "addr:full":"Calle de Heroes Alcazar De Toledo, 10 Valladolid Valladolid 47001",
    "addr:housenumber":"10",
    "addr:postcode":"47001",
    "addr:street":"Calle De Heroes Alcazar De Toledo",
    "iso:country":"ES",
    "sg:address":"Calle de Heroes Alcazar De Toledo, 10",
    "sg:city":"Valladolid",
    "sg:orig_category":"Ropa Para Caballeros (al Por Menor)",
    "sg:phone":"+34 983 37 58 18",
    "sg:postcode":"47001",
    "sg:province":"Valladolid",
    "wof:name":"Alonso Braun Antonio",
    "wof:placetype":"venue"
},
  "geometry": {"coordinates":[-4.7296495438,41.6506576538],"type":"Point"}
}