{
  "type": "Feature",
  "properties": {
    "iso:country":"ES",
    "sg:address":"Calle de San Salvador, 24",
    "sg:city":"Merida",
    "sg:orig_category":"Arquitectos",
    "sg:phone":"+34 924 31 80 06",
    "sg:postcode":"06800",
    "sg:province":"Badajoz",
    "wof:name":"Sanchez Castillo Manuel",
    "wof:placetype":"venue"
},
  "geometry": {"coordinates":[-6.3484659195,38.917514801],"type":"Point"}
}