{
  "type": "Feature",
  "properties": {
    "addr:full":"Calle de Duque Y Merino, 4 Reinosa Cantabria 39200",
    "addr:housenumber":"4",
    "addr:postcode":"39200",
    "addr:street":"Calle De Duque Y Merino",
    "iso:country":"ES",
    "sg:address":"Calle de Duque Y Merino, 4",
    "sg:city":"Reinosa",
    "sg:orig_category":"Electrodom\u00c9sticos (al Por Menor)",
    "sg:phone":"+34 942 75 52 24",
    "sg:postcode":"39200",
    "sg:province":"Cantabria",
    "wof:name":"Salido Garcia Bernabe",
    "wof:placetype":"venue"
},
  "geometry": {"coordinates":[-4.1391940117,43.0004043579],"type":"Point"}
}