{
  "type": "Feature",
  "properties": {
    "addr:full":"Carrer de Guerau De Liost, 5 Barcelona Barcelona 08017",
    "addr:housenumber":"5",
    "addr:postcode":"08017",
    "addr:street":"Carrer De Guerau;Liost",
    "iso:country":"ES",
    "sg:address":"Carrer de Guerau De Liost, 5",
    "sg:city":"Barcelona",
    "sg:orig_category":"Molduras, Junquillos, Listones Y Molduras Perforadas",
    "sg:phone":"+34 934 06 81 30",
    "sg:postcode":"08017",
    "sg:province":"Barcelona",
    "wof:name":"Garcia Marsinyach Daniel",
    "wof:placetype":"venue"
},
  "geometry": {"coordinates":[2.1035480499,41.4130516052],"type":"Point"}
}