{
  "type": "Feature",
  "properties": {
    "iso:country":"ES",
    "sg:address":"Pol Ind La Juaida, S/n",
    "sg:city":"Viator",
    "sg:orig_category":"Contenedores (mercanc\u00cdas)",
    "sg:phone":"+34 950 30 61 23",
    "sg:postcode":"04240",
    "sg:province":"Almer\u00eda",
    "wof:name":"Transportes Azkar S.a.",
    "wof:placetype":"venue"
},
  "geometry": {"coordinates":[-2.4223089218,36.884979248],"type":"Point"}
}