{
  "type": "Feature",
  "properties": {
    "addr:full":"Calle de Castillo De Alcala De Guadaira, 13 Sevilla Sevilla 41013",
    "addr:housenumber":"13",
    "addr:postcode":"41013",
    "addr:street":"Calle De Castillo De Alcala;Guadaira",
    "iso:country":"ES",
    "sg:address":"Calle de Castillo De Alcala De Guadaira, 13",
    "sg:city":"Sevilla",
    "sg:orig_category":"Cajas De Ahorro",
    "sg:phone":"+34 954 62 07 96",
    "sg:postcode":"41013",
    "sg:province":"Sevilla",
    "sg:website":"www.lacaixa.es",
    "wof:name":"Caixa D'estalvis I Pensions De Barcelona",
    "wof:placetype":"venue"
},
  "geometry": {"coordinates":[-5.977227211,37.3605270386],"type":"Point"}
}