{
  "type": "Feature",
  "properties": {
    "iso:country":"ES",
    "sg:address":"Pase Ronda, 5",
    "sg:city":"Coru\u00d1a",
    "sg:orig_category":"Delegados, Agentes De Tr\u00c1nsito, Auxiliares De Transporte Internacional",
    "sg:phone":"+34 981 13 84 69",
    "sg:postcode":"15011",
    "sg:province":"A Coru\u00f1a",
    "wof:name":"Transportes Balgoma S.l.",
    "wof:placetype":"venue"
},
  "geometry": {"coordinates":[-8.416478157,43.3702545166],"type":"Point"}
}