{
  "type": "Feature",
  "properties": {
    "iso:country":"ES",
    "sg:address":"Avda San Francisco, 10",
    "sg:city":"Cobeja",
    "sg:orig_category":"Asesor\u00cda Sobre Comunicaci\u00d3n De Empresas",
    "sg:phone":"+34 925 55 14 72",
    "sg:postcode":"45291",
    "sg:province":"Toledo",
    "wof:name":"Garcia Rosado Maria Gema",
    "wof:placetype":"venue"
},
  "geometry": {"coordinates":[-3.8594183922,40.0267562866],"type":"Point"}
}