{
  "type": "Feature",
  "properties": {
    "iso:country":"ES",
    "sg:address":"Calle de Marcelo Usera, 105",
    "sg:city":"Madrid",
    "sg:orig_category":"Bisuter\u00cda, Joyer\u00cda, Relojer\u00cda (al Por Menor)",
    "sg:phone":"+34 914 75 43 44",
    "sg:postcode":"28026",
    "sg:province":"Madrid",
    "wof:name":"M.d.c. Joyeros S.l.",
    "wof:placetype":"venue"
},
  "geometry": {"coordinates":[-3.7079029083,40.3854675293],"type":"Point"}
}