{
  "type": "Feature",
  "properties": {
    "iso:country":"ES",
    "sg:address":"Calle de Sancho Panza, 7",
    "sg:city":"Ciudad Real",
    "sg:orig_category":"Equipo De Refrigeraci\u00d3n Industrial",
    "sg:phone":"+34 926 22 24 45",
    "sg:postcode":"13004",
    "sg:province":"Ciudad Real",
    "wof:name":"Refrigeraciones Electricas Del Amo S.l.",
    "wof:placetype":"venue"
},
  "geometry": {"coordinates":[-3.9233152866,38.9860916138],"type":"Point"}
}