{
  "type": "Feature",
  "properties": {
    "iso:country":"ES",
    "sg:address":"Avda Ordesa, 11",
    "sg:city":"Broto",
    "sg:orig_category":"Fabricaci\u00d3n De Productos Textiles Sin Tejer",
    "sg:phone":"+34 974 48 60 06",
    "sg:postcode":"22370",
    "sg:province":"Huesca",
    "wof:name":"Lopez-belio Lopez Javier",
    "wof:placetype":"venue"
},
  "geometry": {"coordinates":[-0.1234529987,42.6050491333],"type":"Point"}
}