{
  "type": "Feature",
  "properties": {
    "iso:country":"ES",
    "sg:address":"Calle de Arrabal, 7",
    "sg:city":"Moron Almazan",
    "sg:orig_category":"Farmacias",
    "sg:phone":"+34 975 30 60 47",
    "sg:postcode":"42223",
    "sg:province":"Soria",
    "wof:name":"Astobieta Odriozola I\u00f1aki",
    "wof:placetype":"venue"
},
  "geometry": {"coordinates":[-2.4739534855,41.382598877],"type":"Point"}
}