{
  "type": "Feature",
  "properties": {
    "addr:full":"Calle de Puerto, S/n Barbate C\u00e1diz 11160",
    "addr:housenumber":"/ n",
    "addr:postcode":"11160",
    "addr:street":"Calle De Puerto S",
    "iso:country":"ES",
    "sg:address":"Calle de Puerto, S/n",
    "sg:city":"Barbate",
    "sg:orig_category":"Deportes N\u00c1uticos, Acu\u00c1ticos Y Subacu\u00c1ticos: Art\u00cdculos Y Equipo (al Por Menor)",
    "sg:phone":"+34 956 43 42 65",
    "sg:postcode":"11160",
    "sg:province":"C\u00e1diz",
    "wof:name":"Nautica Trafalgar S.l",
    "wof:placetype":"venue"
},
  "geometry": {"coordinates":[-5.9232239723,36.1931915283],"type":"Point"}
}