{
  "type": "Feature",
  "properties": {
    "iso:country":"ES",
    "sg:address":"Calle de Lopez Rubio, 8",
    "sg:city":"Granada",
    "sg:orig_category":"M\u00c9dicos: Ginecolog\u00cda M\u00c9dica, Obstetricia",
    "sg:phone":"+34 958 22 45 17",
    "sg:postcode":"18001",
    "sg:province":"Granada",
    "wof:name":"D.m.geoinvest S.l.",
    "wof:placetype":"venue"
},
  "geometry": {"coordinates":[-3.5985519886,37.1753349304],"type":"Point"}
}