{
  "type": "Feature",
  "properties": {
    "addr:full":"Pase Zarategi De, 75 Donostia-san Sebastian Guip\u00f9zcoa 20015",
    "addr:housenumber":"75",
    "addr:postcode":"20015",
    "iso:country":"ES",
    "sg:address":"Pase Zarategi De, 75",
    "sg:city":"Donostia-san Sebastian",
    "sg:orig_category":"M\u00c9dicos: An\u00c1lisis Cl\u00cdnicos",
    "sg:phone":"+34 943 32 05 09",
    "sg:postcode":"20015",
    "sg:province":"Guip\u00f9zcoa",
    "wof:name":"Reference Laboratory S.a.",
    "wof:placetype":"venue"
},
  "geometry": {"coordinates":[-1.9543859959,43.3154411316],"type":"Point"}
}