{
  "type": "Feature",
  "properties": {
    "addr:full":"Plaz Espa\u00d1a, 7 Atienza Guadalajara 19270",
    "addr:housenumber":"7",
    "addr:postcode":"19270",
    "addr:street":"Plaz Espan\u0303A",
    "iso:country":"ES",
    "sg:address":"Plaz Espa\u00d1a, 7",
    "sg:city":"Atienza",
    "sg:orig_category":"Cajas De Ahorro",
    "sg:phone":"+34 949 39 90 48",
    "sg:postcode":"19270",
    "sg:province":"Guadalajara",
    "sg:website":"www.ibercaja.es",
    "wof:name":"Caja De Ahorros Y Monte De Piedad De Zaragoza Aragon Y Rioja",
    "wof:placetype":"venue"
},
  "geometry": {"coordinates":[-2.8690900803,41.1993293762],"type":"Point"}
}