{
  "type": "Feature",
  "properties": {
    "addr:full":"Carr Teodor Canet, 49 Port D'alcudia Islas Baleares 07410",
    "addr:housenumber":"49",
    "addr:postcode":"07410",
    "addr:street":"Carr Teodor Canet",
    "iso:country":"ES",
    "sg:address":"Carr Teodor Canet, 49",
    "sg:city":"Port D'alcudia",
    "sg:orig_category":"Muebles, Minoristas",
    "sg:phone":"+34 971 54 78 23",
    "sg:postcode":"07410",
    "sg:province":"Islas Baleares",
    "wof:name":"Pons Pons Gabriel",
    "wof:placetype":"venue"
},
  "geometry": {"coordinates":[3.1327590942,39.8442268372],"type":"Point"}
}