{
  "type": "Feature",
  "properties": {
    "addr:full":"Ctra Leon-benavente, S/n Villama\u00f1an Le\u00f3n 24234",
    "addr:housenumber":"s",
    "addr:postcode":"24234",
    "addr:street":"Ctra Leon-Benavente;/ N Villaman\u0303An Leo\u0301N",
    "iso:country":"ES",
    "sg:address":"Ctra Leon-benavente, S/n",
    "sg:city":"Villama\u00f1an",
    "sg:orig_category":"Molduras, Junquillos, Listones Y Molduras Perforadas",
    "sg:phone":"+34 987 76 80 43",
    "sg:postcode":"24234",
    "sg:province":"Le\u00f3n",
    "wof:name":"Santos Rodriguez Maria Concepcion",
    "wof:placetype":"venue"
},
  "geometry": {"coordinates":[-5.5805668831,42.3195075989],"type":"Point"}
}