{
  "type": "Feature",
  "properties": {
    "addr:full":"Dr Bartual, 3 Santo Domingo Valencia 46900",
    "addr:housenumber":"3",
    "addr:postcode":"46900",
    "addr:street":"Dr Bartual",
    "iso:country":"ES",
    "sg:address":"Dr Bartual, 3",
    "sg:city":"Santo Domingo",
    "sg:orig_category":"Venta, Instalaci\u00d3n, Mantenimiento De Chimeneas De Interior Y Accesorios",
    "sg:phone":"+34 961 98 02 85",
    "sg:postcode":"46900",
    "sg:province":"Valencia",
    "wof:name":"Gomez Martinez Jose Maria",
    "wof:placetype":"venue"
},
  "geometry": {"coordinates":[-0.4623290002,39.441619873],"type":"Point"}
}