{
  "type": "Feature",
  "properties": {
    "addr:full":"Aizkoeta Au., 1 Segura Guip\u00f9zcoa 20214",
    "addr:housenumber":"1",
    "addr:postcode":"20214",
    "addr:street":"Au.;Guipu\u0300Zcoa",
    "iso:country":"ES",
    "sg:address":"Aizkoeta Au., 1",
    "sg:city":"Segura",
    "sg:orig_category":"Fabricaci\u00d3n De Papel Para Embalar",
    "sg:phone":"+34 943 88 04 67",
    "sg:postcode":"20214",
    "sg:province":"Guip\u00f9zcoa",
    "wof:name":"Papelera Usurbe S.l.",
    "wof:placetype":"venue"
},
  "geometry": {"coordinates":[-2.2524290085,43.0094947815],"type":"Point"}
}