{
  "type": "Feature",
  "properties": {
    "addr:full":"Calle de Ramon Pelayo, 17 Colindres Cantabria 39750",
    "addr:housenumber":"17",
    "addr:postcode":"39750",
    "addr:street":"Calle De Ramon Pelayo",
    "iso:country":"ES",
    "sg:address":"Calle de Ramon Pelayo, 17",
    "sg:city":"Colindres",
    "sg:orig_category":"Promotores Constructores",
    "sg:phone":"+34 942 65 06 66",
    "sg:postcode":"39750",
    "sg:province":"Cantabria",
    "wof:name":"Promociones De Cantabria Antas S.l.",
    "wof:placetype":"venue"
},
  "geometry": {"coordinates":[-3.446819067,43.3966522217],"type":"Point"}
}