{
  "type": "Feature",
  "properties": {
    "addr:full":"Luga Albina, S/n Rincones C\u00e1diz 11520",
    "addr:housenumber":"s / n",
    "addr:postcode":"11520",
    "addr:street":"Ca\u0301Diz",
    "iso:country":"ES",
    "sg:address":"Luga Albina, S/n",
    "sg:city":"Rincones",
    "sg:orig_category":"Hormigonados",
    "sg:phone":"+34 956 81 48 62",
    "sg:postcode":"11520",
    "sg:province":"C\u00e1diz",
    "wof:name":"Hormigones Y Minas S.a.",
    "wof:placetype":"venue"
},
  "geometry": {"coordinates":[-6.3688821793,36.6247940063],"type":"Point"}
}