{
  "type": "Feature",
  "properties": {
    "iso:country":"ES",
    "sg:address":"Avda Mediterraneo (del), 12",
    "sg:city":"Rincon Victoria",
    "sg:orig_category":"Edici\u00d3n De Diarios, Revistas, Boletines",
    "sg:phone":"+34 952 97 37 62",
    "sg:postcode":"29730",
    "sg:province":"M\u00e1laga",
    "wof:name":"Eichelbaum Guibourg Horacio",
    "wof:placetype":"venue"
},
  "geometry": {"coordinates":[-4.2902889252,36.7160606384],"type":"Point"}
}