{
  "type": "Feature",
  "properties": {
    "addr:full":"Callejon De Malaga, 28 Velez-malaga M\u00e1laga 29700",
    "addr:housenumber":"28",
    "addr:postcode":"29700",
    "addr:street":"Callejon De Malaga",
    "iso:country":"ES",
    "sg:address":"Callejon De Malaga, 28",
    "sg:city":"Velez-malaga",
    "sg:orig_category":"Producci\u00d3n, Distribuci\u00d3n De Gas Butano Y Propano",
    "sg:phone":"+34 952 50 08 94",
    "sg:postcode":"29700",
    "sg:province":"M\u00e1laga",
    "wof:name":"Macias Cervan Francisca",
    "wof:placetype":"venue"
},
  "geometry": {"coordinates":[-4.1035718918,36.7747192383],"type":"Point"}
}