{
  "type": "Feature",
  "properties": {
    "addr:full":"Via Augusta, 185 Barcelona Barcelona 08021",
    "addr:housenumber":"185",
    "addr:postcode":"08021",
    "addr:street":"Via Augusta",
    "iso:country":"ES",
    "sg:address":"Via Augusta, 185",
    "sg:city":"Barcelona",
    "sg:orig_category":"M\u00c9dicos: Fisioterapia Y Rehabilitaci\u00d3n",
    "sg:phone":"+34 932 09 11 52",
    "sg:postcode":"08021",
    "sg:province":"Barcelona",
    "wof:name":"Centro Fisioterapia Rigo Quera Salva S.l.",
    "wof:placetype":"venue"
},
  "geometry": {"coordinates":[2.1412670612,41.3979721069],"type":"Point"}
}