{
  "type": "Feature",
  "properties": {
    "addr:full":"Carr Cases De Capote, 2 Villarreal Castell\u00f3n 12540",
    "addr:housenumber":"2",
    "addr:postcode":"12540",
    "addr:street":"Carr Cases De Capote",
    "iso:country":"ES",
    "sg:address":"Carr Cases De Capote, 2",
    "sg:city":"Villarreal",
    "sg:orig_category":"Fabrica De Cer\u00c1micas",
    "sg:phone":"+34 964 53 46 44",
    "sg:postcode":"12540",
    "sg:province":"Castell\u00f3n",
    "wof:name":"Viama Nou Tall S.l.",
    "wof:placetype":"venue"
},
  "geometry": {"coordinates":[-0.1157760024,39.9449691772],"type":"Point"}
}