{
  "type": "Feature",
  "properties": {
    "addr:full":"Calle de Luis Gonzalez Perez, S/n S.gregorio Las Palmas 35200",
    "addr:postcode":"35200",
    "addr:street":"Calle De Luis Gonzalez Perez S / N S.Gregorio Las Palmas",
    "iso:country":"ES",
    "sg:address":"Calle de Luis Gonzalez Perez, S/n",
    "sg:city":"S.gregorio",
    "sg:orig_category":"Ropa Para Se\u00d1oras Y Caballeros (al Por Menor)",
    "sg:phone":"+34 928 69 13 12",
    "sg:postcode":"35200",
    "sg:province":"Las Palmas",
    "wof:name":"Ramos Dominguez Aida Rosa",
    "wof:placetype":"venue"
},
  "geometry": {"coordinates":[-15.4144220352,28.0029888153],"type":"Point"}
}