{
  "type": "Feature",
  "properties": {
    "iso:country":"ES",
    "sg:address":"Calle de San Pascasio, 4",
    "sg:city":"Salamanca",
    "sg:orig_category":"Promotores Constructores",
    "sg:phone":"+34 923 22 81 54",
    "sg:postcode":"37006",
    "sg:province":"Salamanca",
    "wof:name":"Construcciones Luiger S.l.",
    "wof:placetype":"venue"
},
  "geometry": {"coordinates":[-5.6708841324,40.9761161804],"type":"Point"}
}