{
  "type": "Feature",
  "properties": {
    "iso:country":"ES",
    "sg:address":"Avda Aragon (de), 53",
    "sg:city":"Teruel",
    "sg:orig_category":"Platos Preparados Refrigerados (fabricaci\u00d3n, Al Por Mayor)",
    "sg:phone":"+34 978 60 25 78",
    "sg:postcode":"44002",
    "sg:province":"Teruel",
    "wof:name":"Zuriaga Perruca Jorge",
    "wof:placetype":"venue"
},
  "geometry": {"coordinates":[-1.1069990396,40.3303108215],"type":"Point"}
}