{
  "type": "Feature",
  "properties": {
    "addr:full":"Esglesia, S/n Figols Organya Lleida 25794",
    "addr:housenumber":"s / n",
    "addr:postcode":"25794",
    "iso:country":"ES",
    "sg:address":"Esglesia, S/n",
    "sg:city":"Figols Organya",
    "sg:orig_category":"Centros De Educaci\u00d3n Especial",
    "sg:phone":"+34 973 38 31 00",
    "sg:postcode":"25794",
    "sg:province":"Lleida",
    "wof:name":"Ajuntament De Figols I Alinya",
    "wof:placetype":"venue"
},
  "geometry": {"coordinates":[1.3386619091,42.2023162842],"type":"Point"}
}