{
  "type": "Feature",
  "properties": {
    "iso:country":"ES",
    "sg:address":"Calle de Bra\u00d1uelas, 5",
    "sg:city":"Fuenlabrada",
    "sg:orig_category":"Sindicatos Y Colegios Profesionales",
    "sg:phone":"+34 916 42 09 40",
    "sg:postcode":"28947",
    "sg:province":"Madrid",
    "wof:name":"Sociedad General De Autores Y Editores",
    "wof:placetype":"venue"
},
  "geometry": {"coordinates":[-3.748100996,40.254737854],"type":"Point"}
}