{
  "type": "Feature",
  "properties": {
    "addr:full":"Marti\u00d1ene Plaza, 1 Zarautz Guip\u00f9zcoa 20800",
    "addr:housenumber":"1",
    "addr:postcode":"20800",
    "addr:street":"Guipu\u0300Zcoa",
    "iso:country":"ES",
    "sg:address":"Marti\u00d1ene Plaza, 1",
    "sg:city":"Zarautz",
    "sg:orig_category":"Molduras, Junquillos, Listones Y Molduras Perforadas",
    "sg:phone":"+34 943 13 11 59",
    "sg:postcode":"20800",
    "sg:province":"Guip\u00f9zcoa",
    "wof:name":"Bar Urdaneta",
    "wof:placetype":"venue"
},
  "geometry": {"coordinates":[-2.1737809181,43.2822341919],"type":"Point"}
}