{
  "type": "Feature",
  "properties": {
    "iso:country":"ES",
    "sg:address":"Palomares P I Casablanca, 27",
    "sg:city":"Laguardia-biasteri",
    "sg:orig_category":"Fabricaci\u00d3n De Camas",
    "sg:phone":"+34 945 62 50 49",
    "sg:postcode":"01300",
    "sg:province":"\u00c1lava",
    "wof:name":"Luis Soriano S.a.",
    "wof:placetype":"venue"
},
  "geometry": {"coordinates":[-2.5842370987,42.5542793274],"type":"Point"}
}