{
  "type": "Feature",
  "properties": {
    "addr:full":"Calle de Mendizabal, 28 Valencia Valencia 46011",
    "addr:housenumber":"28",
    "addr:postcode":"46011",
    "addr:street":"Calle De Mendizabal",
    "iso:country":"ES",
    "sg:address":"Calle de Mendizabal, 28",
    "sg:city":"Valencia",
    "sg:orig_category":"Promotores Constructores",
    "sg:phone":"+34 963 71 28 20",
    "sg:postcode":"46011",
    "sg:province":"Valencia",
    "wof:name":"Aplacados Domus S.l.",
    "wof:placetype":"venue"
},
  "geometry": {"coordinates":[-0.330134213,39.473033905],"type":"Point"}
}