{
  "type": "Feature",
  "properties": {
    "addr:full":"Carrer de Basconia, 32 Barcelona Barcelona 08030",
    "addr:housenumber":"32",
    "addr:postcode":"08030",
    "addr:street":"Carrer De Basconia",
    "iso:country":"ES",
    "sg:address":"Carrer de Basconia, 32",
    "sg:city":"Barcelona",
    "sg:orig_category":"Aceites Y Grasas Alimentarias (fabricaci\u00d3n, Al Por Mayor)",
    "sg:phone":"+34 933 12 09 01",
    "sg:postcode":"08030",
    "sg:province":"Barcelona",
    "wof:name":"Markoi S.l.",
    "wof:placetype":"venue"
},
  "geometry": {"coordinates":[2.1871140003,41.4356651306],"type":"Point"}
}