{
  "type": "Feature",
  "properties": {
    "iso:country":"ES",
    "sg:address":"Calle de Pozos, 23",
    "sg:city":"Puebla Montalban",
    "sg:orig_category":"Agricultura: Abastecimiento Y Cosechado (negocio)",
    "sg:phone":"+34 925 74 55 92",
    "sg:postcode":"45516",
    "sg:province":"Toledo",
    "wof:name":"Comercial Macando S.l.",
    "wof:placetype":"venue"
},
  "geometry": {"coordinates":[-4.3634738922,39.8630447388],"type":"Point"}
}