{
  "type": "Feature",
  "properties": {
    "addr:full":"Calle de Mostoles, 19 Gijon Asturias 33212",
    "addr:housenumber":"19",
    "addr:postcode":"33212",
    "addr:street":"Calle De Mostoles",
    "iso:country":"ES",
    "sg:address":"Calle de Mostoles, 19",
    "sg:city":"Gijon",
    "sg:orig_category":"Panader\u00cdas, Panader\u00cdas",
    "sg:phone":"+34 985 30 00 02",
    "sg:postcode":"33212",
    "sg:province":"Asturias",
    "wof:name":"Lomban Diaz Maria De Los Angeles",
    "wof:placetype":"venue"
},
  "geometry": {"coordinates":[-5.6841268539,43.540687561],"type":"Point"}
}