{
  "type": "Feature",
  "properties": {
    "addr:full":"Poli Elegarcu, S/n Cacicedo Cantabria 39608",
    "addr:housenumber":"s / n",
    "addr:postcode":"39608",
    "addr:street":"Poli Elegarcu",
    "iso:country":"ES",
    "sg:address":"Poli Elegarcu, S/n",
    "sg:city":"Cacicedo",
    "sg:orig_category":"Compresores",
    "sg:phone":"+34 942 34 06 99",
    "sg:postcode":"39608",
    "sg:province":"Cantabria",
    "wof:name":"Compresores Vigo S.a.",
    "wof:placetype":"venue"
},
  "geometry": {"coordinates":[-3.8830139637,43.4323272705],"type":"Point"}
}