{
  "type": "Feature",
  "properties": {
    "iso:country":"ES",
    "sg:address":"Avda Cameranos, 5",
    "sg:city":"Zafra",
    "sg:orig_category":"Arquitectos",
    "sg:phone":"+34 924 55 56 32",
    "sg:postcode":"06300",
    "sg:province":"Badajoz",
    "wof:name":"Urribarri Garcia Ernesto",
    "wof:placetype":"venue"
},
  "geometry": {"coordinates":[-6.4112610817,38.4198036194],"type":"Point"}
}