{
  "type": "Feature",
  "properties": {
    "iso:country":"ES",
    "sg:address":"C/ Escorca, 38",
    "sg:city":"Inca",
    "sg:classifiers":[
        {
            "category":"Communications",
            "type":"Services"
        }
    ],
    "sg:phone":"+34 971 88 13 18",
    "sg:postcode":"07300",
    "sg:province":"Islas Baleares",
    "sg:tags":[
        "televisiones",
        "y",
        "radio"
    ],
    "wof:name":"Televisio D'inca Associacio Cultural Falco",
    "wof:placetype":"venue"
},
  "geometry": {"coordinates":[2.9209609032,39.7178268433],"type":"Point"}
}