{
  "type": "Feature",
  "properties": {
    "addr:full":"Plaz Agustin Salido, 9 Ciudad Real Ciudad Real 13003",
    "addr:housenumber":"9",
    "addr:postcode":"13003",
    "addr:street":"Agustin Salido",
    "iso:country":"ES",
    "sg:address":"Plaz Agustin Salido, 9",
    "sg:city":"Ciudad Real",
    "sg:orig_category":"Cristaler\u00cdas",
    "sg:phone":"+34 926 22 34 82",
    "sg:postcode":"13003",
    "sg:province":"Ciudad Real",
    "wof:name":"Peco Rodriguez Antonio",
    "wof:placetype":"venue"
},
  "geometry": {"coordinates":[-3.9301741123,38.9844093323],"type":"Point"}
}