{
  "type": "Feature",
  "properties": {
    "addr:full":"Plaz Pontevedra, 10 Coru\u00d1a La Coru\u00f1a 15003",
    "addr:housenumber":"10",
    "addr:postcode":"15003",
    "addr:street":"Pontevedra;La Corun\u0303A",
    "iso:country":"ES",
    "sg:address":"Plaz Pontevedra, 10",
    "sg:city":"Coru\u00d1a",
    "sg:orig_category":"Bisuter\u00cda, Joyer\u00cda, Relojer\u00cda (al Por Menor)",
    "sg:phone":"+34 981 22 63 92",
    "sg:postcode":"15003",
    "sg:province":"La Coru\u00f1a",
    "sg:website":"www.joyeriacarbe.com",
    "wof:name":"Combery Norte S.l.",
    "wof:placetype":"venue"
},
  "geometry": {"coordinates":[-8.4063863754,43.3679389954],"type":"Point"}
}