{
  "type": "Feature",
  "properties": {
    "iso:country":"ES",
    "sg:address":"Calle de Torrente, 2",
    "sg:city":"Fuenlabrada",
    "sg:orig_category":"Centros Empresariales",
    "sg:phone":"+34 916 08 58 81",
    "sg:postcode":"28942",
    "sg:province":"Madrid",
    "wof:name":"Bricolage 2 S.a.",
    "wof:placetype":"venue"
},
  "geometry": {"coordinates":[-3.8116970062,40.2942428589],"type":"Point"}
}