{
  "type": "Feature",
  "properties": {
    "iso:country":"ES",
    "sg:address":"Carr Barretina (de La), S/n",
    "sg:city":"Agramunt",
    "sg:orig_category":"Fisioterapia",
    "sg:phone":"+34 973 39 21 03",
    "sg:postcode":"25310",
    "sg:province":"Lleida",
    "wof:name":"Centre Medic D'agramunt S.l.",
    "wof:placetype":"venue"
},
  "geometry": {"coordinates":[1.0987299681,41.7856712341],"type":"Point"}
}