{
  "type": "Feature",
  "properties": {
    "addr:full":"Pase Berabera De, 75 Donostia-san Sebastian Guip\u00f9zcoa 20009",
    "addr:housenumber":"75",
    "addr:postcode":"20009",
    "addr:street":"Berabera",
    "iso:country":"ES",
    "sg:address":"Pase Berabera De, 75",
    "sg:city":"Donostia-san Sebastian",
    "sg:orig_category":"Empresas De Pintura Y Revestimientos",
    "sg:phone":"+34 943 31 49 74",
    "sg:postcode":"20009",
    "sg:province":"Guip\u00f9zcoa",
    "wof:name":"Ruesgas Esteban Gilberto",
    "wof:placetype":"venue"
},
  "geometry": {"coordinates":[-1.9972430468,43.3036193848],"type":"Point"}
}