{
  "type": "Feature",
  "properties": {
    "addr:full":"Calle de Zaragoza, 31 Castellon Castell\u00f3n 12001",
    "addr:housenumber":"31",
    "addr:postcode":"12001",
    "addr:street":"Calle De Zaragoza",
    "iso:country":"ES",
    "sg:address":"Calle de Zaragoza, 31",
    "sg:city":"Castellon",
    "sg:orig_category":"Agentes Generales De Seguros",
    "sg:phone":"+34 964 21 08 10",
    "sg:postcode":"12001",
    "sg:province":"Castell\u00f3n",
    "wof:name":"Roca Garcia Fernando",
    "wof:placetype":"venue"
},
  "geometry": {"coordinates":[-0.0418459997,39.9874954224],"type":"Point"}
}