{
  "type": "Feature",
  "properties": {
    "iso:country":"ES",
    "sg:address":"Avda Angeles (de Los), 3",
    "sg:city":"Calahorra",
    "sg:orig_category":"Electrodom\u00c9sticos (al Por Menor)",
    "sg:phone":"+34 941 13 12 54",
    "sg:postcode":"26500",
    "sg:province":"La Rioja",
    "wof:name":"Riobasat S.l.",
    "wof:placetype":"venue"
},
  "geometry": {"coordinates":[-1.9691519737,42.3046035767],"type":"Point"}
}