{
  "type": "Feature",
  "properties": {
    "addr:full":"Rua Manuel Lemos, 34 Ramallosa Pontevedra 36379",
    "addr:housenumber":"34",
    "addr:postcode":"36379",
    "addr:street":"Rua Manuel Lemos",
    "iso:country":"ES",
    "sg:address":"Rua Manuel Lemos, 34",
    "sg:city":"Ramallosa",
    "sg:orig_category":"Inmobiliaria (agencias)",
    "sg:phone":"+34 986 35 05 78",
    "sg:postcode":"36379",
    "sg:province":"Pontevedra",
    "sg:website":"www.agenciabarreras.com",
    "wof:name":"Zulueta De Madariaga Alfonso",
    "wof:placetype":"venue"
},
  "geometry": {"coordinates":[-8.8129825592,42.1181755066],"type":"Point"}
}