{
  "type": "Feature",
  "properties": {
    "addr:full":"Carr Segria, 17 Lleida Lleida 25006",
    "addr:housenumber":"17",
    "addr:postcode":"25006",
    "addr:street":"Carr Segria",
    "iso:country":"ES",
    "sg:address":"Carr Segria, 17",
    "sg:city":"Lleida",
    "sg:orig_category":"Abogados",
    "sg:phone":"+34 973 26 78 35",
    "sg:postcode":"25006",
    "sg:province":"Lleida",
    "wof:name":"Fidalgo Latorre Jose Manuel",
    "wof:placetype":"venue"
},
  "geometry": {"coordinates":[0.6146709919,41.6174812317],"type":"Point"}
}