{
  "type": "Feature",
  "properties": {
    "iso:country":"ES",
    "sg:address":"Calle de Honduras, 4",
    "sg:city":"Coslada",
    "sg:orig_category":"Ropa Para Beb\u00c9s Y Ni\u00d1os (confecci\u00d3n, Al Por Mayor)",
    "sg:phone":"+34 916 74 14 37",
    "sg:postcode":"28820",
    "sg:province":"Madrid",
    "wof:name":"Gonzalo Pidal Luisa",
    "wof:placetype":"venue"
},
  "geometry": {"coordinates":[-3.5456988811,40.4244651794],"type":"Point"}
}