{
  "type": "Feature",
  "properties": {
    "addr:full":"Calle de San Francisco, 22 Lucena C\u00f3rdoba 14900",
    "addr:housenumber":"22",
    "addr:postcode":"14900",
    "addr:street":"Calle De San Francisco",
    "iso:country":"ES",
    "sg:address":"Calle de San Francisco, 22",
    "sg:city":"Lucena",
    "sg:orig_category":"Inmobiliaria (agencias)",
    "sg:phone":"+34 957 50 31 36",
    "sg:postcode":"14900",
    "sg:province":"C\u00f3rdoba",
    "wof:name":"Torralbo Lopez Francisco",
    "wof:placetype":"venue"
},
  "geometry": {"coordinates":[-4.4861440659,37.4118309021],"type":"Point"}
}