{
  "type": "Feature",
  "properties": {
    "iso:country":"ES",
    "sg:address":"Ctra. Toledo, Km. 0030,6",
    "sg:city":"Galvez",
    "sg:orig_category":"Distribuci\u00d3n De Petr\u00d3leo Y Derivados",
    "sg:phone":"+34 925 40 00 29",
    "sg:postcode":"45164",
    "sg:province":"Toledo",
    "wof:name":"Bermudez Guadamillas Jose",
    "wof:placetype":"venue"
},
  "geometry": {"coordinates":[-4.2757091522,39.7027244568],"type":"Point"}
}