{
  "type": "Feature",
  "properties": {
    "addr:full":"Polig. Pocomaco, S/n A Coru\u00f1a A Coru\u00f1a 15190",
    "addr:housenumber":"s / n",
    "addr:postcode":"15190",
    "addr:street":"Polig. Pocomaco;A Corun\u0303A A Corun\u0303A",
    "iso:country":"ES",
    "sg:address":"Polig. Pocomaco, S/n",
    "sg:city":"A Coru\u00f1a",
    "sg:orig_category":"Promotores Constructores",
    "sg:phone":"+34 981 13 93 08",
    "sg:postcode":"15190",
    "sg:province":"A Coru\u00f1a",
    "sg:website":"www.viviendaconfort.es",
    "wof:name":"Vivienda Confort Coru\u00f1a S.a.",
    "wof:placetype":"venue"
},
  "geometry": {"coordinates":[-8.4335021973,43.3301010132],"type":"Point"}
}