{
  "type": "Feature",
  "properties": {
    "iso:country":"ES",
    "sg:address":"Calle de Alto De Leon, 19",
    "sg:city":"Valencia De Don Juan",
    "sg:orig_category":"Agentes, Concesionarios Y Sucursales De Veh\u00cdculos",
    "sg:phone":"+34 987 75 22 44",
    "sg:postcode":"24200",
    "sg:province":"Le\u00f3n",
    "wof:name":"Coyanza Motor S.l.",
    "wof:placetype":"venue"
},
  "geometry": {"coordinates":[-5.5168466568,42.2965354919],"type":"Point"}
}