{
  "type": "Feature",
  "properties": {
    "addr:full":"Ptge Masor, 14 Sant Feliu Llobregat Barcelona 08980",
    "addr:housenumber":"14",
    "addr:postcode":"08980",
    "addr:street":"Ptge Masor",
    "iso:country":"ES",
    "sg:address":"Ptge Masor, 14",
    "sg:city":"Sant Feliu Llobregat",
    "sg:orig_category":"Grafistas",
    "sg:phone":"+34 936 85 50 56",
    "sg:postcode":"08980",
    "sg:province":"Barcelona",
    "wof:name":"Garrido Valle Alejandro",
    "wof:placetype":"venue"
},
  "geometry": {"coordinates":[2.0486500263,41.3884811401],"type":"Point"}
}