{
  "type": "Feature",
  "properties": {
    "addr:full":"Afores, 32 Deltebre Tarragona 43580",
    "addr:housenumber":"32",
    "addr:postcode":"43580",
    "addr:street":"Afores",
    "iso:country":"ES",
    "sg:address":"Afores, 32",
    "sg:city":"Deltebre",
    "sg:orig_category":"Poller\u00cda Y Caza (al Por Menor)",
    "sg:phone":"+34 977 26 79 94",
    "sg:postcode":"43580",
    "sg:province":"Tarragona",
    "wof:name":"Agroavicola Colomines S.c.p.",
    "wof:placetype":"venue"
},
  "geometry": {"coordinates":[0.7342733741,40.7338066101],"type":"Point"}
}