{
  "type": "Feature",
  "properties": {
    "iso:country":"ES",
    "sg:address":"Calle de Anzofe, 72",
    "sg:city":"Palmas De Gran Canaria",
    "sg:orig_category":"Pintura Y Barniz (al Por Menor)",
    "sg:phone":"+34 928 46 65 82",
    "sg:postcode":"35009",
    "sg:province":"Las Palmas",
    "wof:name":"Gil Padron Moises",
    "wof:placetype":"venue"
},
  "geometry": {"coordinates":[-15.4240493774,28.1504039764],"type":"Point"}
}