{
  "type": "Feature",
  "properties": {
    "iso:country":"ES",
    "sg:address":"Bo. Estacion, 11",
    "sg:city":"Calzada Bureba",
    "sg:orig_category":"Producci\u00d3n, Comercio De Cereales",
    "sg:phone":"+34 947 59 50 05",
    "sg:postcode":"09244",
    "sg:province":"Burgos",
    "wof:name":"Alberto Ba\u00f1uelos S.a.",
    "wof:placetype":"venue"
},
  "geometry": {"coordinates":[-3.6457295418,42.3517341614],"type":"Point"}
}