{
  "type": "Feature",
  "properties": {
    "iso:country":"ES",
    "sg:address":"Calle de Margubete, 41",
    "sg:city":"Santo Domingo De La Calzada",
    "sg:orig_category":"Venta, Instalaci\u00d3n De Calefacci\u00d3n",
    "sg:phone":"+34 941 34 14 49",
    "sg:postcode":"26250",
    "sg:province":"La Rioja",
    "wof:name":"Salas Untoria Valentin",
    "wof:placetype":"venue"
},
  "geometry": {"coordinates":[-2.9541339874,42.4394760132],"type":"Point"}
}