{
  "type": "Feature",
  "properties": {
    "iso:country":"ES",
    "sg:address":"Avda Ponferrada, 2",
    "sg:city":"Astorga",
    "sg:orig_category":"Plomeros",
    "sg:phone":"+34 987 61 63 16",
    "sg:postcode":"24700",
    "sg:province":"Le\u00f3n",
    "wof:name":"Campos Gomez Antonio",
    "wof:placetype":"venue"
},
  "geometry": {"coordinates":[-6.0650238991,42.4604034424],"type":"Point"}
}