{
  "type": "Feature",
  "properties": {
    "addr:full":"Carr Alemanya, 73 Badalona Barcelona 08917",
    "addr:housenumber":"73",
    "addr:postcode":"08917",
    "addr:street":"Carr Alemanya",
    "iso:country":"ES",
    "sg:address":"Carr Alemanya, 73",
    "sg:city":"Badalona",
    "sg:orig_category":"Confecci\u00d3n De Trajes Para Se\u00d1oras",
    "sg:phone":"+34 933 95 02 07",
    "sg:postcode":"08917",
    "sg:province":"Barcelona",
    "wof:name":"Valore S.l.",
    "wof:placetype":"venue"
},
  "geometry": {"coordinates":[2.2234721184,41.4606056213],"type":"Point"}
}