{
  "type": "Feature",
  "properties": {
    "addr:full":"Ctra Llobatona, 52 Viladecans Barcelona 08840",
    "addr:housenumber":"52",
    "addr:postcode":"08840",
    "addr:street":"Ctra Llobatona",
    "iso:country":"ES",
    "sg:address":"Ctra Llobatona, 52",
    "sg:city":"Viladecans",
    "sg:orig_category":"Conservas De Pescados Y Salazones Mar\u00cdtimos (fabricaci\u00d3n, Al Por Mayor)",
    "sg:phone":"+34 936 47 31 03",
    "sg:postcode":"08840",
    "sg:province":"Barcelona",
    "wof:name":"Rouremar S.l.",
    "wof:placetype":"venue"
},
  "geometry": {"coordinates":[2.0205199718,41.3077201843],"type":"Point"}
}