{
  "type": "Feature",
  "properties": {
    "addr:full":"Carrer de Guillem De Claramunt (de), 11 Salou Tarragona 43840",
    "addr:housenumber":"11",
    "addr:postcode":"43840",
    "addr:street":"Carrer De Guillem De Claramunt De",
    "iso:country":"ES",
    "sg:address":"Carrer de Guillem De Claramunt (de), 11",
    "sg:city":"Salou",
    "sg:orig_category":"Edici\u00d3n De Diarios, Revistas, Boletines",
    "sg:phone":"+34 977 38 47 06",
    "sg:postcode":"43840",
    "sg:province":"Tarragona",
    "wof:name":"Ediciones Mediterraneo S.c.p.",
    "wof:placetype":"venue"
},
  "geometry": {"coordinates":[1.12479496,41.0771789551],"type":"Point"}
}