{
  "type": "Feature",
  "properties": {
    "iso:country":"ES",
    "sg:address":"Calle de Jose Mara\u00d1on, 3",
    "sg:city":"Madrid",
    "sg:orig_category":"Organizaciones Internacionales",
    "sg:phone":"+34 914 45 40 22",
    "sg:postcode":"28010",
    "sg:province":"Madrid",
    "wof:name":"Comision Episcopal De La Ocasha",
    "wof:placetype":"venue"
},
  "geometry": {"coordinates":[-3.698182106,40.429145813],"type":"Point"}
}