{
  "type": "Feature",
  "properties": {
    "addr:full":"Calle de Jesus (de), 45 Aranjuez Madrid 28300",
    "addr:housenumber":"45",
    "addr:postcode":"28300",
    "addr:street":"Calle De Jesus De",
    "iso:country":"ES",
    "sg:address":"Calle de Jesus (de), 45",
    "sg:city":"Aranjuez",
    "sg:orig_category":"Supermercados Y Hipermercados",
    "sg:phone":"+34 918 91 69 33",
    "sg:postcode":"28300",
    "sg:province":"Madrid",
    "wof:name":"Ahorraprix S.a.",
    "wof:placetype":"venue"
},
  "geometry": {"coordinates":[-3.5923826694,40.0300521851],"type":"Point"}
}