{
  "type": "Feature",
  "properties": {
    "addr:full":"Carrer de Andreu Llambrich, 77 Ametlla Mar Tarragona 43860",
    "addr:housenumber":"77",
    "addr:postcode":"43860",
    "addr:street":"Carrer De Andreu Llambrich",
    "iso:country":"ES",
    "sg:address":"Carrer de Andreu Llambrich, 77",
    "sg:city":"Ametlla Mar",
    "sg:orig_category":"Arquitectos",
    "sg:phone":"+34 977 45 65 67",
    "sg:postcode":"43860",
    "sg:province":"Tarragona",
    "wof:name":"Curto Benet Frances",
    "wof:placetype":"venue"
},
  "geometry": {"coordinates":[0.8036640286,40.8830833435],"type":"Point"}
}