{
  "type": "Feature",
  "properties": {
    "addr:full":"Carrer de Velazquez, 5 Palma Islas Baleares 07002",
    "addr:housenumber":"5",
    "addr:postcode":"07002",
    "addr:street":"Carrer De Velazquez",
    "iso:country":"ES",
    "sg:address":"Carrer de Velazquez, 5",
    "sg:city":"Palma",
    "sg:orig_category":"Sociedades, Compa\u00d1\u00cdas Aseguradoras",
    "sg:phone":"+34 971 21 35 55",
    "sg:postcode":"07002",
    "sg:province":"Islas Baleares",
    "wof:name":"Euroilles 2003 S.l.",
    "wof:placetype":"venue"
},
  "geometry": {"coordinates":[2.6545898914,39.573387146],"type":"Point"}
}