{
  "type": "Feature",
  "properties": {
    "addr:full":"C/ Blas Valero, 27 Elche Alicante 03201",
    "addr:housenumber":"27",
    "addr:postcode":"03201",
    "addr:street":"C / Blas Valero",
    "iso:country":"ES",
    "sg:address":"C/ Blas Valero, 27",
    "sg:city":"Elche",
    "sg:orig_category":"Asesor\u00cda Fiscal Y Jur\u00cddica",
    "sg:phone":"+34 965 44 80 00",
    "sg:postcode":"03201",
    "sg:province":"Alicante",
    "wof:name":"Sempere Macia Jaime",
    "wof:placetype":"venue"
},
  "geometry": {"coordinates":[-0.7016580105,38.2671051025],"type":"Point"}
}