{
  "type": "Feature",
  "properties": {
    "addr:full":"Calle de Doce De Octubre, 8 Valladolid Valladolid 47005",
    "addr:housenumber":"8",
    "addr:postcode":"47005",
    "addr:street":"Calle De Doce De Octubre",
    "iso:country":"ES",
    "sg:address":"Calle de Doce De Octubre, 8",
    "sg:city":"Valladolid",
    "sg:orig_category":"Panader\u00cdas, Panader\u00cdas",
    "sg:phone":"+34 983 39 54 04",
    "sg:postcode":"47005",
    "sg:province":"Valladolid",
    "sg:website":"www.paginasamarillas.es",
    "wof:name":"Hermanos Marban S. A.",
    "wof:placetype":"venue"
},
  "geometry": {"coordinates":[-4.7101764679,41.6536521912],"type":"Point"}
}