{
  "type": "Feature",
  "properties": {
    "iso:country":"ES",
    "sg:address":"Calle de Paredes De Nava, 11",
    "sg:city":"Madrid",
    "sg:orig_category":"Institutos De Belleza",
    "sg:phone":"+34 917 54 38 80",
    "sg:postcode":"28017",
    "sg:province":"Madrid",
    "wof:name":"Jara Esteticista Sl",
    "wof:placetype":"venue"
},
  "geometry": {"coordinates":[-3.6266551018,40.4204826355],"type":"Point"}
}