{
  "type": "Feature",
  "properties": {
    "addr:full":"M.aozaratza Kalea, 14 O\u00f1ati Guip\u00f9zcoa 20560",
    "addr:housenumber":"14",
    "addr:postcode":"20560",
    "addr:street":"M.Aozaratza Kalea;Guipu\u0300Zcoa",
    "iso:country":"ES",
    "sg:address":"M.aozaratza Kalea, 14",
    "sg:city":"O\u00f1ati",
    "sg:orig_category":"Empresas De Carpinter\u00cda De Madera",
    "sg:phone":"+34 943 78 05 03",
    "sg:postcode":"20560",
    "sg:province":"Guip\u00f9zcoa",
    "wof:name":"Francisco Javier Anduaga Yarza",
    "wof:placetype":"venue"
},
  "geometry": {"coordinates":[-2.4114439487,43.0299758911],"type":"Point"}
}