{
  "type": "Feature",
  "properties": {
    "addr:full":"Carrer de Santa Joaquima, 18 S. Cugat Valles Barcelona 08172",
    "addr:housenumber":"18",
    "addr:postcode":"08172",
    "addr:street":"Carrer De Santa Joaquima;S. Cugat Valles Barcelona",
    "iso:country":"ES",
    "sg:address":"Carrer de Santa Joaquima, 18",
    "sg:city":"S. Cugat Valles",
    "sg:orig_category":"Caf\u00c9s, Bares, Cervecer\u00cdas",
    "sg:phone":"+34 935 90 04 01",
    "sg:postcode":"08172",
    "sg:province":"Barcelona",
    "wof:name":"Cot Pastor Montserrat",
    "wof:placetype":"venue"
},
  "geometry": {"coordinates":[2.0806720257,41.4742507935],"type":"Point"}
}