{
  "type": "Feature",
  "properties": {
    "addr:full":"Calle de San Juan Baja, 3 Granada Granada 18005",
    "addr:housenumber":"3",
    "addr:postcode":"18005",
    "addr:street":"Calle De San;Baja",
    "iso:country":"ES",
    "sg:address":"Calle de San Juan Baja, 3",
    "sg:city":"Granada",
    "sg:orig_category":"Sociedades, Compa\u00d1\u00cdas Aseguradoras",
    "sg:phone":"+34 958 52 29 05",
    "sg:postcode":"18005",
    "sg:province":"Granada",
    "sg:website":"www.decasur.es",
    "wof:name":"Martin Linde Enrique",
    "wof:placetype":"venue"
},
  "geometry": {"coordinates":[-3.5976479053,37.1695480347],"type":"Point"}
}