{
  "type": "Feature",
  "properties": {
    "addr:full":"Rua Encarnacion (da), 34 Celanova Ourense 32800",
    "addr:housenumber":"34",
    "addr:postcode":"32800",
    "addr:street":"Rua Encarnacion Da",
    "iso:country":"ES",
    "sg:address":"Rua Encarnacion (da), 34",
    "sg:city":"Celanova",
    "sg:orig_category":"Caf\u00c9s, Bares, Cervecer\u00cdas",
    "sg:phone":"+34 988 43 15 47",
    "sg:postcode":"32800",
    "sg:province":"Ourense",
    "wof:name":"Galtelcom",
    "wof:placetype":"venue"
},
  "geometry": {"coordinates":[-7.9587712288,42.1474876404],"type":"Point"}
}