{
  "type": "Feature",
  "properties": {
    "iso:country":"ES",
    "sg:address":"Calle de Nu\u00d1ez De Balboa, 11",
    "sg:city":"Madrid",
    "sg:orig_category":"Mutuas De Seguros",
    "sg:phone":"+34 914 35 43 05",
    "sg:postcode":"28001",
    "sg:province":"Madrid",
    "wof:name":"Mutualidad Del Cuerpo De Corredores De Comercio Entidad De Prevision Social",
    "wof:placetype":"venue"
},
  "geometry": {"coordinates":[-3.683152914,40.4227790833],"type":"Point"}
}