{
  "type": "Feature",
  "properties": {
    "addr:full":"Sect Pintores, 36 Tres Cantos Madrid 28760",
    "addr:housenumber":"36",
    "addr:postcode":"28760",
    "addr:street":"Sect Pintores",
    "iso:country":"ES",
    "sg:address":"Sect Pintores, 36",
    "sg:city":"Tres Cantos",
    "sg:orig_category":"Estudios De Grabaci\u00d3n Sonora",
    "sg:phone":"+34 918 04 15 09",
    "sg:postcode":"28760",
    "sg:province":"Madrid",
    "wof:name":"Country Music S.l.",
    "wof:placetype":"venue"
},
  "geometry": {"coordinates":[-3.7111880779,40.6095466614],"type":"Point"}
}