{
  "type": "Feature",
  "properties": {
    "iso:country":"ES",
    "sg:address":"Calle de Tinte, S/n",
    "sg:city":"Burgos",
    "sg:orig_category":"Centros De Educaci\u00d3n Especial",
    "sg:phone":"+34 947 27 41 40",
    "sg:postcode":"09002",
    "sg:province":"Burgos",
    "wof:name":"Colegio Publico San Pablo",
    "wof:placetype":"venue"
},
  "geometry": {"coordinates":[-3.6980409622,42.3378944397],"type":"Point"}
}