{
  "type": "Feature",
  "properties": {
    "iso:country":"ES",
    "sg:address":"Avda Pilas, 37",
    "sg:city":"Bollullos Mitacion",
    "sg:orig_category":"Telas Y Sedas (al Por Menor)",
    "sg:phone":"+34 955 77 65 97",
    "sg:postcode":"41110",
    "sg:province":"Sevilla",
    "wof:name":"Overestore S.l.",
    "wof:placetype":"venue"
},
  "geometry": {"coordinates":[-6.1414737701,37.3562393188],"type":"Point"}
}