{
  "type": "Feature",
  "properties": {
    "addr:full":"Lloc Poligon 15, Km. 0042,8 Campos Islas Baleares 07630",
    "addr:postcode":"07630",
    "addr:street":"Poligon 15 Km. 0042,8 Campos",
    "iso:country":"ES",
    "sg:address":"Lloc Poligon 15, Km. 0042,8",
    "sg:city":"Campos",
    "sg:orig_category":"Oficinas Y Gesti\u00d3n De Inmuebles",
    "sg:phone":"+34 971 16 02 90",
    "sg:postcode":"07630",
    "sg:province":"Islas Baleares",
    "wof:name":"Mufti S.l.",
    "wof:placetype":"venue"
},
  "geometry": {"coordinates":[3.0197050571,39.430480957],"type":"Point"}
}