{
  "type": "Feature",
  "properties": {
    "iso:country":"ES",
    "sg:address":"Carr Llibertat, 1",
    "sg:city":"Caldes Malavella",
    "sg:orig_category":"Dorados, Plater\u00cda (orfebrer\u00cda)",
    "sg:phone":"+34 972 48 01 21",
    "sg:postcode":"17455",
    "sg:province":"Girona",
    "wof:name":"Vargas Campoy Jose",
    "wof:placetype":"venue"
},
  "geometry": {"coordinates":[2.8018240929,41.8385505676],"type":"Point"}
}