{
  "type": "Feature",
  "properties": {
    "iso:country":"ES",
    "sg:address":"Ctra. Valencia, Km. 0019,0",
    "sg:city":"Rivas Vaciamadrid",
    "sg:orig_category":"Refiner\u00cdas De Petr\u00d3leo",
    "sg:phone":"+34 916 70 00 04",
    "sg:postcode":"28529",
    "sg:province":"Madrid",
    "wof:name":"Gesa Carburantes S.l.",
    "wof:placetype":"venue"
},
  "geometry": {"coordinates":[-3.5102670193,40.314289093],"type":"Point"}
}