{
  "type": "Feature",
  "properties": {
    "addr:full":"Avda Juan Carlos I, 41 Caravaca Cruz Murcia 30400",
    "addr:housenumber":"41",
    "addr:postcode":"30400",
    "addr:street":"Avda Juan Carlos I",
    "iso:country":"ES",
    "sg:address":"Avda Juan Carlos I, 41",
    "sg:city":"Caravaca Cruz",
    "sg:orig_category":"Restaurantes",
    "sg:phone":"+34 968 70 84 58",
    "sg:postcode":"30400",
    "sg:province":"Murcia",
    "wof:name":"Bar Restaurante Los Vi\u00f1ales S.l.",
    "wof:placetype":"venue"
},
  "geometry": {"coordinates":[-1.8676869869,38.1026382446],"type":"Point"}
}