{
  "type": "Feature",
  "properties": {
    "iso:country":"ES",
    "sg:address":"Calle de Mallorca, 4",
    "sg:city":"Alaquas",
    "sg:orig_category":"Servicio De Salud",
    "sg:phone":"+34 961 50 51 54",
    "sg:postcode":"46970",
    "sg:province":"Valencia",
    "wof:name":"Saneamientos Mallorca S.l.",
    "wof:placetype":"venue"
},
  "geometry": {"coordinates":[-0.4593929946,39.4553451538],"type":"Point"}
}