{
  "type": "Feature",
  "properties": {
    "addr:full":"Carrer de Comte Borrell, 165 Barcelona Barcelona 08015",
    "addr:housenumber":"165",
    "addr:postcode":"08015",
    "addr:street":"Carrer De Comte Borrell",
    "iso:country":"ES",
    "sg:address":"Carrer de Comte Borrell, 165",
    "sg:city":"Barcelona",
    "sg:orig_category":"Carnicer\u00cdas, Carnicer\u00cdas",
    "sg:phone":"+34 934 54 46 63",
    "sg:postcode":"08015",
    "sg:province":"Barcelona",
    "wof:name":"Amoros Nieto Luis",
    "wof:placetype":"venue"
},
  "geometry": {"coordinates":[2.1546628475,41.3833503723],"type":"Point"}
}