{
  "type": "Feature",
  "properties": {
    "iso:country":"ES",
    "sg:address":"Calle de Palenque, 6",
    "sg:city":"Talavera Reina",
    "sg:orig_category":"Farmacias",
    "sg:phone":"+34 925 80 53 77",
    "sg:postcode":"45600",
    "sg:province":"Toledo",
    "wof:name":"Garcia Alcocer Rosa Maria",
    "wof:placetype":"venue"
},
  "geometry": {"coordinates":[-4.8327379227,39.9590339661],"type":"Point"}
}