{
  "type": "Feature",
  "properties": {
    "addr:full":"Rua Paco Maa\u00d1on, 52 Foz Lugo 27780",
    "addr:housenumber":"52",
    "addr:postcode":"27780",
    "addr:street":"Rua Paco Maan\u0303On",
    "iso:country":"ES",
    "sg:address":"Rua Paco Maa\u00d1on, 52",
    "sg:city":"Foz",
    "sg:orig_category":"Art\u00cdculos De Regalo (al Por Menor)",
    "sg:phone":"+34 982 14 00 92",
    "sg:postcode":"27780",
    "sg:province":"Lugo",
    "wof:name":"Vazquez Alvarez Maria Dolores",
    "wof:placetype":"venue"
},
  "geometry": {"coordinates":[-7.2573590279,43.5672683716],"type":"Point"}
}