{
  "type": "Feature",
  "properties": {
    "iso:country":"ES",
    "sg:address":"Calle de Doctor Fleming, 14",
    "sg:city":"Burgos",
    "sg:orig_category":"Peluquer\u00cdas, Peluquer\u00cda Mixta",
    "sg:phone":"+34 947 26 83 01",
    "sg:postcode":"09002",
    "sg:province":"Burgos",
    "wof:name":"Parte Pascual Belen De La",
    "wof:placetype":"venue"
},
  "geometry": {"coordinates":[-3.6963670254,42.3379554749],"type":"Point"}
}