{
  "type": "Feature",
  "properties": {
    "addr:full":"Calle de San Francisco, 26 Santo Domingo De La Calzada La Rioja 26250",
    "addr:housenumber":"26",
    "addr:postcode":"26250",
    "addr:street":"Calle De San Francisco;Rioja",
    "iso:country":"ES",
    "sg:address":"Calle de San Francisco, 26",
    "sg:city":"Santo Domingo De La Calzada",
    "sg:orig_category":"Escayola Y Productos De Escayola (fabricaci\u00d3n, Al Por Mayor)",
    "sg:phone":"+34 941 34 33 49",
    "sg:postcode":"26250",
    "sg:province":"La Rioja",
    "wof:name":"Colmenero E Hijos S.l.",
    "wof:placetype":"venue"
},
  "geometry": {"coordinates":[-2.9587030411,42.4402999878],"type":"Point"}
}