{
  "type": "Feature",
  "properties": {
    "addr:full":"Calle de Ramos Carrion, 4 Zamora Zamora 49001",
    "addr:housenumber":"4",
    "addr:postcode":"49001",
    "addr:street":"Calle De Ramos Carrion",
    "iso:country":"ES",
    "sg:address":"Calle de Ramos Carrion, 4",
    "sg:city":"Zamora",
    "sg:classifiers":[
        {
            "category":"Personal",
            "subcategory":"Barber",
            "type":"Services"
        }
    ],
    "sg:phone":"+34 980 53 43 29",
    "sg:postcode":"49001",
    "sg:province":"Zamora",
    "sg:tags":[
        "caballeros",
        "de",
        "peluqueros"
    ],
    "wof:name":"Fernandez Matilla Sebastian",
    "wof:placetype":"venue"
},
  "geometry": {"coordinates":[-5.7470011711,41.5030441284],"type":"Point"}
}