{
  "type": "Feature",
  "properties": {
    "addr:full":"Ctra Carmona-viso, S/n Carmona Sevilla 41410",
    "addr:housenumber":"s / n",
    "addr:postcode":"41410",
    "addr:street":"Ctra Carmona-Viso",
    "iso:country":"ES",
    "sg:address":"Ctra Carmona-viso, S/n",
    "sg:city":"Carmona",
    "sg:orig_category":"Poller\u00cda Y Caza (al Por Menor)",
    "sg:phone":"+34 954 14 37 72",
    "sg:postcode":"41410",
    "sg:province":"Sevilla",
    "wof:name":"Montero Romero Patrocinio",
    "wof:placetype":"venue"
},
  "geometry": {"coordinates":[-5.6433792114,37.4708709717],"type":"Point"}
}