{
  "type": "Feature",
  "properties": {
    "iso:country":"ES",
    "sg:address":"Calle de Santa Amalia, 11",
    "sg:city":"Madrid",
    "sg:orig_category":"Compraventa De Antig\u00dcedades",
    "sg:phone":"+34 915 01 97 32",
    "sg:postcode":"28038",
    "sg:province":"Madrid",
    "wof:name":"Bullon Gallego Heliodoro",
    "wof:placetype":"venue"
},
  "geometry": {"coordinates":[-3.6635301113,40.4024429321],"type":"Point"}
}