{
  "type": "Feature",
  "properties": {
    "iso:country":"ES",
    "sg:address":"A. Schez Alba, 27",
    "sg:city":"Lebrija",
    "sg:orig_category":"Persianas Interiores, Exteriores",
    "sg:phone":"+34 955 97 32 90",
    "sg:postcode":"41740",
    "sg:province":"Sevilla",
    "wof:name":"Falcon Benitez Jose Luis",
    "wof:placetype":"venue"
},
  "geometry": {"coordinates":[-6.0658698082,36.9205932617],"type":"Point"}
}