{
  "type": "Feature",
  "properties": {
    "addr:full":"Pl Del Mig De Can Clos, 4 Barcelona Barcelona 08038",
    "addr:housenumber":"4",
    "addr:postcode":"08038",
    "addr:street":"Pl;Clos",
    "iso:country":"ES",
    "sg:address":"Pl Del Mig De Can Clos, 4",
    "sg:city":"Barcelona",
    "sg:orig_category":"Centros Empresariales",
    "sg:phone":"+34 934 22 35 30",
    "sg:postcode":"08038",
    "sg:province":"Barcelona",
    "wof:name":"Davani Service S.l.",
    "wof:placetype":"venue"
},
  "geometry": {"coordinates":[2.1475450993,41.3609886169],"type":"Point"}
}