{
  "type": "Feature",
  "properties": {
    "iso:country":"ES",
    "sg:address":"Rua Serafin Pazo, 6",
    "sg:city":"Estrada",
    "sg:orig_category":"Molduras, Junquillos, Listones Y Molduras Perforadas",
    "sg:phone":"+34 986 57 00 61",
    "sg:postcode":"36680",
    "sg:province":"Pontevedra",
    "wof:name":"Sanmartin Fernandez Manuel Angel",
    "wof:placetype":"venue"
},
  "geometry": {"coordinates":[-8.4874696732,42.6870574951],"type":"Point"}
}