{
  "type": "Feature",
  "properties": {
    "addr:full":"Carretera De Macharaviaya, S/n Rincon Victoria M\u00e1laga 29730",
    "addr:housenumber":"s / n",
    "addr:postcode":"29730",
    "addr:street":"Carretera De Macharaviaya;Ma\u0301Laga",
    "iso:country":"ES",
    "sg:address":"Carretera De Macharaviaya, S/n",
    "sg:city":"Rincon Victoria",
    "sg:orig_category":"Promotores Constructores",
    "sg:phone":"+34 952 97 18 97",
    "sg:postcode":"29730",
    "sg:province":"M\u00e1laga",
    "sg:website":"www.aifos.es",
    "wof:name":"Aifos S.a.",
    "wof:placetype":"venue"
},
  "geometry": {"coordinates":[-4.2654309273,36.7136039734],"type":"Point"}
}