{
  "type": "Feature",
  "properties": {
    "addr:full":"Calle de Bailen, 15 Almendralejo Badajoz 06200",
    "addr:housenumber":"15",
    "addr:postcode":"06200",
    "addr:street":"Calle De Bailen",
    "iso:country":"ES",
    "sg:address":"Calle de Bailen, 15",
    "sg:city":"Almendralejo",
    "sg:orig_category":"Ingenier\u00cda, Centros De Estudios (diversos)",
    "sg:phone":"+34 924 66 40 57",
    "sg:postcode":"06200",
    "sg:province":"Badajoz",
    "wof:name":"Guerra Pizarro Jacinto",
    "wof:placetype":"venue"
},
  "geometry": {"coordinates":[-6.4075574875,38.6818809509],"type":"Point"}
}