{
  "type": "Feature",
  "properties": {
    "addr:full":"Calle de Don Quijote, 3 Alcorcon Madrid 28922",
    "addr:housenumber":"3",
    "addr:postcode":"28922",
    "addr:street":"Calle De Don Quijote",
    "iso:country":"ES",
    "sg:address":"Calle de Don Quijote, 3",
    "sg:city":"Alcorcon",
    "sg:orig_category":"Cl\u00cdnicas Dentales",
    "sg:phone":"+34 916 43 35 10",
    "sg:postcode":"28922",
    "sg:province":"Madrid",
    "wof:name":"Centro Odontologico Parque Del Oeste S.l.",
    "wof:placetype":"venue"
},
  "geometry": {"coordinates":[-3.828799963,40.3406639099],"type":"Point"}
}