{
  "type": "Feature",
  "properties": {
    "addr:full":"Tafalla, 13 Iru\u00f1a Navarra 31004",
    "addr:housenumber":"13",
    "addr:postcode":"31004",
    "addr:street":"Tafalla",
    "iso:country":"ES",
    "sg:address":"Tafalla, 13",
    "sg:city":"Iru\u00f1a",
    "sg:orig_category":"Prot\u00c9sicos Dentales",
    "sg:phone":"+34 948 24 73 81",
    "sg:postcode":"31004",
    "sg:province":"Navarra",
    "wof:name":"Estarriaga Ibiricu Julian",
    "wof:placetype":"venue"
},
  "geometry": {"coordinates":[-1.6371289492,42.8121376038],"type":"Point"}
}