{
  "type": "Feature",
  "properties": {
    "iso:country":"ES",
    "sg:address":"Calle de Ganeta, 3",
    "sg:city":"Arenas -areeta",
    "sg:orig_category":"Carnicer\u00cdas, Carnicer\u00cdas",
    "sg:phone":"+34 944 63 76 57",
    "sg:postcode":"48930",
    "sg:province":"Vizcaya",
    "wof:name":"Esteban Rubio Sof\u00efo",
    "wof:placetype":"venue"
},
  "geometry": {"coordinates":[-3.0086240768,43.3289070129],"type":"Point"}
}