{
  "type": "Feature",
  "properties": {
    "addr:full":"Calle de San Pablo, 13 Linea De La Concepcion C\u00e1diz 11300",
    "addr:housenumber":"13",
    "addr:postcode":"11300",
    "addr:street":"Calle De San Pablo;Ca\u0301Diz",
    "iso:country":"ES",
    "sg:address":"Calle de San Pablo, 13",
    "sg:city":"Linea De La Concepcion",
    "sg:orig_category":"Centros P\u00dablicos De Formaci\u00d3n Profesional Y T\u00c9cnica",
    "sg:phone":"+34 956 17 09 50",
    "sg:postcode":"11300",
    "sg:province":"C\u00e1diz",
    "wof:name":"Colegio Provincial De Odontologo Y Estomatologo S.l.",
    "wof:placetype":"venue"
},
  "geometry": {"coordinates":[-5.3495402336,36.1619758606],"type":"Point"}
}