{
  "type": "Feature",
  "properties": {
    "addr:full":"Calle de Navarro Caro, 53 Tomares Sevilla 41940",
    "addr:housenumber":"53",
    "addr:postcode":"41940",
    "addr:street":"Calle De Navarro Caro",
    "iso:country":"ES",
    "sg:address":"Calle de Navarro Caro, 53",
    "sg:city":"Tomares",
    "sg:orig_category":"Carnicer\u00cdas, Carnicer\u00cdas",
    "sg:phone":"+34 954 15 08 20",
    "sg:postcode":"41940",
    "sg:province":"Sevilla",
    "wof:name":"Ramos De Los Reyes Miguel",
    "wof:placetype":"venue"
},
  "geometry": {"coordinates":[-6.0493121147,37.3750152588],"type":"Point"}
}