{
  "type": "Feature",
  "properties": {
    "addr:full":"Calle de Tinte, 11 Albacete Albacete 02001",
    "addr:housenumber":"11",
    "addr:postcode":"02001",
    "addr:street":"Calle De Tinte",
    "iso:country":"ES",
    "sg:address":"Calle de Tinte, 11",
    "sg:city":"Albacete",
    "sg:orig_category":"Bancos",
    "sg:phone":"+34 967 19 34 43",
    "sg:postcode":"02001",
    "sg:province":"Albacete",
    "sg:website":"www.bancopastor.es",
    "wof:name":"R Cable Y Telecomunicaciones Galicia S.a.",
    "wof:placetype":"venue"
},
  "geometry": {"coordinates":[-1.8556884527,38.9928398132],"type":"Point"}
}