{
  "type": "Feature",
  "properties": {
    "addr:full":"Avda Chapi, 27 Elda Alicante 03600",
    "addr:housenumber":"27",
    "addr:postcode":"03600",
    "addr:street":"Avda Chapi",
    "iso:country":"ES",
    "sg:address":"Avda Chapi, 27",
    "sg:city":"Elda",
    "sg:orig_category":"M\u00c9dicos: Estomatolog\u00cda",
    "sg:phone":"+34 965 39 31 11",
    "sg:postcode":"03600",
    "sg:province":"Alicante",
    "wof:name":"Perez Correas Jose Rogelio",
    "wof:placetype":"venue"
},
  "geometry": {"coordinates":[-0.7942759991,38.4738044739],"type":"Point"}
}