{
  "type": "Feature",
  "properties": {
    "addr:full":"Calle de Sanchez Manzano, 5 Caceres C\u00e1ceres 10001",
    "addr:housenumber":"5",
    "addr:postcode":"10001",
    "addr:street":"Calle De Sanchez Manzano;Ca\u0301Ceres",
    "iso:country":"ES",
    "sg:address":"Calle de Sanchez Manzano, 5",
    "sg:city":"Caceres",
    "sg:orig_category":"Prendas Y Chalecos De Punto (al Por Menor)",
    "sg:phone":"+34 927 24 24 28",
    "sg:postcode":"10001",
    "sg:province":"C\u00e1ceres",
    "wof:name":"Jimenez Vazquez Juan Antonio",
    "wof:placetype":"venue"
},
  "geometry": {"coordinates":[-6.3782272339,39.4662780762],"type":"Point"}
}