{
  "type": "Feature",
  "properties": {
    "iso:country":"ES",
    "sg:address":"Trav De Gracia, 415",
    "sg:city":"Barcelona",
    "sg:orig_category":"Laboratorios Farmac\u00c9uticos",
    "sg:phone":"+34 934 56 13 75",
    "sg:postcode":"08025",
    "sg:province":"Barcelona",
    "wof:name":"Laboratorios Farmaceuticos Rovi S.a.",
    "wof:placetype":"venue"
},
  "geometry": {"coordinates":[2.1716530323,41.4102630615],"type":"Point"}
}