{
  "type": "Feature",
  "properties": {
    "addr:full":"Rua Padres Franciscanos, S/n Xesteira Pontevedra 36379",
    "addr:housenumber":"s / n",
    "addr:postcode":"36379",
    "addr:street":"Rua Padres Franciscanos",
    "iso:country":"ES",
    "sg:address":"Rua Padres Franciscanos, S/n",
    "sg:city":"Xesteira",
    "sg:orig_category":"Guarder\u00cdas",
    "sg:phone":"+34 986 35 32 07",
    "sg:postcode":"36379",
    "sg:province":"Pontevedra",
    "wof:name":"Pequerrechos C. B.",
    "wof:placetype":"venue"
},
  "geometry": {"coordinates":[-8.8124990463,42.1194648743],"type":"Point"}
}