{
  "type": "Feature",
  "properties": {
    "iso:country":"ES",
    "sg:address":"Carrer de Mallorca, 279",
    "sg:city":"Barcelona",
    "sg:orig_category":"Institutos De Belleza",
    "sg:phone":"+34 932 15 68 76",
    "sg:postcode":"08037",
    "sg:province":"Barcelona",
    "wof:name":"Pueyo Jove Jordi",
    "wof:placetype":"venue"
},
  "geometry": {"coordinates":[2.1642720699,41.3953094482],"type":"Point"}
}