{
  "type": "Feature",
  "properties": {
    "addr:full":"Rua Corredoira, S/n Monforte De Lemos Lugo 27...",
    "addr:housenumber":"s / n;27 ...",
    "addr:street":"Rua Corredoira;Lugo",
    "iso:country":"ES",
    "sg:address":"Rua Corredoira, S/n",
    "sg:city":"Monforte De Lemos",
    "sg:orig_category":"Hospitales",
    "sg:phone":"+34 982 41 79 00",
    "sg:postcode":"27...",
    "sg:province":"Lugo",
    "wof:name":"Hospital Comarcal De Monforte",
    "wof:placetype":"venue"
},
  "geometry": {"coordinates":[-7.5194401741,42.5259056091],"type":"Point"}
}