{
  "type": "Feature",
  "properties": {
    "iso:country":"ES",
    "sg:address":"Calle de Salzillo, 1",
    "sg:city":"Yecla",
    "sg:orig_category":"Fabricaci\u00d3n De Muebles",
    "sg:phone":"+34 968 79 44 08",
    "sg:postcode":"30510",
    "sg:province":"Murcia",
    "wof:name":"Disla Lorenzo Pedro",
    "wof:placetype":"venue"
},
  "geometry": {"coordinates":[-1.1049089432,38.6077384949],"type":"Point"}
}