{
  "type": "Feature",
  "properties": {
    "addr:full":"Calle de Almendros, 7 Altea Alicante 03590",
    "addr:housenumber":"7",
    "addr:postcode":"03590",
    "addr:street":"Calle De Almendros",
    "iso:country":"ES",
    "sg:address":"Calle de Almendros, 7",
    "sg:city":"Altea",
    "sg:orig_category":"Cristaler\u00cdas",
    "sg:phone":"+34 965 84 42 09",
    "sg:postcode":"03590",
    "sg:province":"Alicante",
    "wof:name":"Cristaleria Negro S.l.",
    "wof:placetype":"venue"
},
  "geometry": {"coordinates":[-0.0536419004,38.6010475159],"type":"Point"}
}