{
  "type": "Feature",
  "properties": {
    "addr:full":"Avda Moliere, 17 Malaga M\u00e1laga 29004",
    "addr:housenumber":"17",
    "addr:postcode":"29004",
    "addr:street":"Avda Moliere;Ma\u0301Laga",
    "iso:country":"ES",
    "sg:address":"Avda Moliere, 17",
    "sg:city":"Malaga",
    "sg:orig_category":"Peluquer\u00cdas, Peluquer\u00cda Mixta",
    "sg:phone":"+34 952 24 09 21",
    "sg:postcode":"29004",
    "sg:province":"M\u00e1laga",
    "sg:website":"www.carrion-peluqueros.com",
    "wof:name":"Carrion Galvez Miguel Angel",
    "wof:placetype":"venue"
},
  "geometry": {"coordinates":[-4.4537911415,36.6881408691],"type":"Point"}
}