{
  "type": "Feature",
  "properties": {
    "iso:country":"ES",
    "sg:address":"Trasera Chozuela, 2",
    "sg:city":"Alora",
    "sg:orig_category":"Inform\u00c1tica, Ofim\u00c1tica (estudios, Asesor\u00cda, Ingenier\u00cda, Formaci\u00d3n)",
    "sg:phone":"+34 952 49 74 75",
    "sg:postcode":"29500",
    "sg:province":"M\u00e1laga",
    "wof:name":"Everbit S.l.",
    "wof:placetype":"venue"
},
  "geometry": {"coordinates":[-4.704264164,36.8287315369],"type":"Point"}
}