{
  "type": "Feature",
  "properties": {
    "iso:country":"ES",
    "sg:address":"Calle de Flores Las, 25",
    "sg:city":"Arroyo De La Miel-benalmadena Costa",
    "sg:orig_category":"Quincaller\u00cda (al Por Menor)",
    "sg:phone":"+34 952 44 48 84",
    "sg:postcode":"29631",
    "sg:province":"M\u00e1laga",
    "wof:name":"Gallego Pino Jose",
    "wof:placetype":"venue"
},
  "geometry": {"coordinates":[-4.5482521057,36.6017608643],"type":"Point"}
}