{
  "type": "Feature",
  "properties": {
    "addr:full":"Czad Oleta De, 9 Donostia-san Sebastian Guip\u00f9zcoa 20017",
    "addr:postcode":"20017",
    "addr:street":"Czad",
    "iso:country":"ES",
    "sg:address":"Czad Oleta De, 9",
    "sg:city":"Donostia-san Sebastian",
    "sg:orig_category":"Suministros Para Carrocer\u00cdas",
    "sg:phone":"+34 943 35 28 72",
    "sg:postcode":"20017",
    "sg:province":"Guip\u00f9zcoa",
    "wof:name":"Gonzalez Martin Bonifacio",
    "wof:placetype":"venue"
},
  "geometry": {"coordinates":[-1.9327039719,43.3204727173],"type":"Point"}
}