{
  "type": "Feature",
  "properties": {
    "addr:full":"Calle de Marques De Estella, 5 San Pedro Alcantara M\u00e1laga 29670",
    "addr:housenumber":"5",
    "addr:postcode":"29670",
    "addr:street":"Calle De Marques De Estella",
    "iso:country":"ES",
    "sg:address":"Calle de Marques De Estella, 5",
    "sg:city":"San Pedro Alcantara",
    "sg:orig_category":"Inmobiliaria (agencias)",
    "sg:phone":"+34 952 78 37 26",
    "sg:postcode":"29670",
    "sg:province":"M\u00e1laga",
    "wof:name":"Medina Bautista Pedro",
    "wof:placetype":"venue"
},
  "geometry": {"coordinates":[-4.9929051399,36.4868011475],"type":"Point"}
}