{
  "type": "Feature",
  "properties": {
    "iso:country":"ES",
    "sg:address":"Calle de Parque San Julian, 2",
    "sg:city":"Cuenca",
    "sg:orig_category":"Sociedades, Compa\u00d1\u00cdas Aseguradoras",
    "sg:phone":"+34 969 23 02 97",
    "sg:postcode":"16002",
    "sg:province":"Cuenca",
    "wof:name":"Asistencia Sanitaria Interprovincial S.a.",
    "wof:placetype":"venue"
},
  "geometry": {"coordinates":[-2.1358375549,40.0735664368],"type":"Point"}
}