{
  "type": "Feature",
  "properties": {
    "addr:full":"Carr Campament, 11 Mao Islas Baleares 07702",
    "addr:housenumber":"11",
    "addr:postcode":"07702",
    "addr:street":"Carr Campament",
    "iso:country":"ES",
    "sg:address":"Carr Campament, 11",
    "sg:city":"Mao",
    "sg:orig_category":"Bisuteros (fabricaci\u00d3n, Al Por Mayor)",
    "sg:phone":"+34 971 36 44 49",
    "sg:postcode":"07702",
    "sg:province":"Islas Baleares",
    "wof:name":"Similart S.l.",
    "wof:placetype":"venue"
},
  "geometry": {"coordinates":[4.2682118416,39.8846511841],"type":"Point"}
}