{
  "type": "Feature",
  "properties": {
    "addr:full":"Calle de Enrique Granados, 6 Pozuelo De Alarcon Madrid 28224",
    "addr:housenumber":"6",
    "addr:postcode":"28224",
    "addr:street":"Calle De Enrique Granados",
    "iso:country":"ES",
    "sg:address":"Calle de Enrique Granados, 6",
    "sg:city":"Pozuelo De Alarcon",
    "sg:orig_category":"Freidur\u00cdas: Equipos Y Suministros",
    "sg:phone":"+34 917 99 08 50",
    "sg:postcode":"28224",
    "sg:province":"Madrid",
    "sg:website":"www.eurofrits.es",
    "wof:name":"Eurofrits S.a.",
    "wof:placetype":"venue"
},
  "geometry": {"coordinates":[-3.8116030693,40.4582138062],"type":"Point"}
}