{
  "type": "Feature",
  "properties": {
    "iso:country":"ES",
    "sg:address":"Avda Alfonso R. Castelao, S/n",
    "sg:city":"Calle",
    "sg:orig_category":"Veh\u00cdculos De Ocasi\u00d3n",
    "sg:phone":"+34 986 70 00 41",
    "sg:postcode":"36690",
    "sg:province":"Pontevedra",
    "wof:name":"Royal Cars Arcade S.l.",
    "wof:placetype":"venue"
},
  "geometry": {"coordinates":[-8.6077241898,42.3371658325],"type":"Point"}
}