{
  "type": "Feature",
  "properties": {
    "iso:country":"ES",
    "sg:address":"Calle de Puerto Rico, 6",
    "sg:city":"Madrid",
    "sg:orig_category":"Audiovisuales (producci\u00d3n, Edici\u00d3n, Realizaci\u00d3n)",
    "sg:phone":"+34 915 19 82 63",
    "sg:postcode":"28016",
    "sg:province":"Madrid",
    "wof:name":"Hiparco S.a.",
    "wof:placetype":"venue"
},
  "geometry": {"coordinates":[-3.6743590832,40.4526062012],"type":"Point"}
}