{
  "type": "Feature",
  "properties": {
    "addr:full":"Calle de Vid (de La), 1 Manzanares Ciudad Real 13200",
    "addr:housenumber":"1",
    "addr:postcode":"13200",
    "addr:street":"Calle De Vid De La",
    "iso:country":"ES",
    "sg:address":"Calle de Vid (de La), 1",
    "sg:city":"Manzanares",
    "sg:orig_category":"Empresas De Pintura Y Revestimientos",
    "sg:phone":"+34 926 61 45 06",
    "sg:postcode":"13200",
    "sg:province":"Ciudad Real",
    "wof:name":"Meneses Martin Eduardo",
    "wof:placetype":"venue"
},
  "geometry": {"coordinates":[-3.363298893,38.9981307983],"type":"Point"}
}