{
  "type": "Feature",
  "properties": {
    "iso:country":"ES",
    "sg:address":"Calle de Hoya (de La), 1",
    "sg:city":"Totana",
    "sg:orig_category":"Empresas De Carpinter\u00cda De Madera",
    "sg:phone":"+34 968 42 02 61",
    "sg:postcode":"30850",
    "sg:province":"Murcia",
    "wof:name":"Martinez Garcia Salvador",
    "wof:placetype":"venue"
},
  "geometry": {"coordinates":[-1.5007920265,37.7673454285],"type":"Point"}
}