{
  "type": "Feature",
  "properties": {
    "addr:full":"Grup El Metal, 6 Portugalete Vizcaya 48920",
    "addr:postcode":"48920",
    "iso:country":"ES",
    "sg:address":"Grup El Metal, 6",
    "sg:city":"Portugalete",
    "sg:orig_category":"Muebles, Minoristas",
    "sg:phone":"+34 944 83 50 22",
    "sg:postcode":"48920",
    "sg:province":"Vizcaya",
    "wof:name":"Jose Oscar Bouso Fernandez",
    "wof:placetype":"venue"
},
  "geometry": {"coordinates":[-3.0286979675,43.3234329224],"type":"Point"}
}