{
  "type": "Feature",
  "properties": {
    "iso:country":"ES",
    "sg:address":"Calle de Miguel Servet, 21",
    "sg:city":"Puertollano",
    "sg:orig_category":"Peluqueros: De Se\u00d1oras",
    "sg:phone":"+34 926 41 07 23",
    "sg:postcode":"13500",
    "sg:province":"Ciudad Real",
    "wof:name":"Fernandez Aragon Antonia",
    "wof:placetype":"venue"
},
  "geometry": {"coordinates":[-4.1016688347,38.6872901917],"type":"Point"}
}