{
  "type": "Feature",
  "properties": {
    "iso:country":"ES",
    "sg:address":"Calle de Clara Campoamor, 41",
    "sg:city":"Madrid",
    "sg:orig_category":"Electricidad Veh\u00cdculo",
    "sg:phone":"+34 914 65 58 75",
    "sg:postcode":"28025",
    "sg:province":"Madrid",
    "wof:name":"Fernandez Herraiz Vicente",
    "wof:placetype":"venue"
},
  "geometry": {"coordinates":[-3.7332155704,40.382686615],"type":"Point"}
}