{
  "type": "Feature",
  "properties": {
    "addr:full":"Calle de San Jacinto, 15 Sevilla Sevilla 41010",
    "addr:housenumber":"15",
    "addr:postcode":"41010",
    "addr:street":"Calle De San Jacinto",
    "iso:country":"ES",
    "sg:address":"Calle de San Jacinto, 15",
    "sg:city":"Sevilla",
    "sg:orig_category":"Confiter\u00cdas, Chocolater\u00cdas (al Por Menor)",
    "sg:phone":"+34 954 33 46 36",
    "sg:postcode":"41010",
    "sg:province":"Sevilla",
    "wof:name":"Nerol S. L.",
    "wof:placetype":"venue"
},
  "geometry": {"coordinates":[-6.0036811829,37.3845367432],"type":"Point"}
}