{
  "type": "Feature",
  "properties": {
    "iso:country":"ES",
    "sg:address":"Calle de Amezti, 10",
    "sg:city":"Algorta",
    "sg:orig_category":"Mercer\u00cda, Lencer\u00cda (al Por Menor)",
    "sg:phone":"+34 944 60 27 51",
    "sg:postcode":"48992",
    "sg:province":"Vizcaya",
    "wof:name":"Fernandez Zapatero Maria Pilar",
    "wof:placetype":"venue"
},
  "geometry": {"coordinates":[-3.010175705,43.3496780396],"type":"Point"}
}