{
  "type": "Feature",
  "properties": {
    "addr:full":"Calle de Manzanos (los), 1 Horche Guadalajara 19140",
    "addr:housenumber":"1",
    "addr:postcode":"19140",
    "addr:street":"Calle De Manzanos Los",
    "iso:country":"ES",
    "sg:address":"Calle de Manzanos (los), 1",
    "sg:city":"Horche",
    "sg:orig_category":"Venta, Alquiler De Toldos",
    "sg:phone":"+34 949 29 05 74",
    "sg:postcode":"19140",
    "sg:province":"Guadalajara",
    "wof:name":"Curbimetal S.a.",
    "wof:placetype":"venue"
},
  "geometry": {"coordinates":[-3.0662961006,40.563369751],"type":"Point"}
}