{
  "type": "Feature",
  "properties": {
    "addr:full":"Rbla Pompeu Fabra, 34 Mollet Valles Barcelona 08100",
    "addr:housenumber":"34",
    "addr:postcode":"08100",
    "addr:street":"Rbla Pompeu Fabra",
    "iso:country":"ES",
    "sg:address":"Rbla Pompeu Fabra, 34",
    "sg:city":"Mollet Valles",
    "sg:orig_category":"Alumbrados",
    "sg:phone":"+34 935 70 88 95",
    "sg:postcode":"08100",
    "sg:province":"Barcelona",
    "wof:name":"Marques Arenas Eva",
    "wof:placetype":"venue"
},
  "geometry": {"coordinates":[2.218930006,41.5403938293],"type":"Point"}
}