{
  "type": "Feature",
  "properties": {
    "addr:full":"Calle de Alloza, 12 Castellon Castell\u00f3n 12001",
    "addr:housenumber":"12",
    "addr:postcode":"12001",
    "addr:street":"Calle De Alloza",
    "iso:country":"ES",
    "sg:address":"Calle de Alloza, 12",
    "sg:city":"Castellon",
    "sg:orig_category":"Abogados",
    "sg:phone":"+34 964 20 18 67",
    "sg:postcode":"12001",
    "sg:province":"Castell\u00f3n",
    "wof:name":"Mata Manzano Juan Antonio",
    "wof:placetype":"venue"
},
  "geometry": {"coordinates":[-0.0398074016,39.985206604],"type":"Point"}
}