{
  "type": "Feature",
  "properties": {
    "iso:country":"ES",
    "sg:address":"Pasaje San Pedro, 1",
    "sg:city":"Tauste",
    "sg:orig_category":"Carnicer\u00cdas, Carnicer\u00cdas",
    "sg:phone":"+34 976 85 45 14",
    "sg:postcode":"50660",
    "sg:province":"Zaragoza",
    "wof:name":"Pola Anso Manuel",
    "wof:placetype":"venue"
},
  "geometry": {"coordinates":[-1.2559020519,41.9210586548],"type":"Point"}
}