{
  "type": "Feature",
  "properties": {
    "iso:country":"ES",
    "sg:address":"Ctra Sevilla-huelva, Km. 0604,0",
    "sg:city":"Villarrasa",
    "sg:orig_category":"Producci\u00d3n, Venta De Productos De Agricultura Biol\u00d3gica",
    "sg:phone":"+34 959 50 60 43",
    "sg:postcode":"21850",
    "sg:province":"Huelva",
    "sg:website":"www.frutaria.com",
    "wof:name":"Agroalimentaria Del Sur S.a.",
    "wof:placetype":"venue"
},
  "geometry": {"coordinates":[-6.5989785194,37.3872375488],"type":"Point"}
}