{
  "type": "Feature",
  "properties": {
    "iso:country":"ES",
    "sg:address":"Ptda Pla De La Vallonga, S/n",
    "sg:city":"Pla De La Vallonga",
    "sg:orig_category":"Aparatos E Instalaci\u00d3n De Regad\u00cdos",
    "sg:phone":"+34 965 11 42 82",
    "sg:postcode":"03113",
    "sg:province":"Alicante",
    "sg:website":"www.hidroten.es",
    "wof:name":"Hidroten S.a.",
    "wof:placetype":"venue"
},
  "geometry": {"coordinates":[-0.5904179811,38.3435401917],"type":"Point"}
}