{
  "type": "Feature",
  "properties": {
    "iso:country":"ES",
    "sg:address":"Calle de Cartaya, S/n",
    "sg:city":"Punta Umbria",
    "sg:orig_category":"Molduras, Junquillos, Listones Y Molduras Perforadas",
    "sg:phone":"+34 959 31 45 69",
    "sg:postcode":"21100",
    "sg:province":"Huelva",
    "wof:name":"Mantenimiento Y Servicios Bernal S.l.",
    "wof:placetype":"venue"
},
  "geometry": {"coordinates":[-6.9655871391,37.1842498779],"type":"Point"}
}