{
  "type": "Feature",
  "properties": {
    "iso:country":"ES",
    "sg:address":"Carrer de Canuda, 35",
    "sg:city":"Barcelona",
    "sg:orig_category":"Librer\u00cdas",
    "sg:phone":"+34 933 01 81 81",
    "sg:postcode":"08002",
    "sg:province":"Barcelona",
    "wof:name":"Arribas Adrian Luis",
    "wof:placetype":"venue"
},
  "geometry": {"coordinates":[2.1726560593,41.3848190308],"type":"Point"}
}