{
  "type": "Feature",
  "properties": {
    "addr:full":"Villafria, S/n Villafria Asturias 33129",
    "addr:postcode":"33129",
    "addr:street":"Villafria S / N Villafria Asturias",
    "iso:country":"ES",
    "sg:address":"Villafria, S/n",
    "sg:city":"Villafria",
    "sg:classifiers":[
        {
            "category":"Taxi",
            "type":"Transportation"
        }
    ],
    "sg:phone":"+34 985 82 08 08",
    "sg:postcode":"33129",
    "sg:province":"Asturias",
    "wof:name":"Radio Taxi Pravia C.b.",
    "wof:placetype":"venue"
},
  "geometry": {"coordinates":[-6.1370148659,43.4517707825],"type":"Point"}
}