{
  "type": "Feature",
  "properties": {
    "iso:country":"ES",
    "sg:address":"Calle de Barraincua, 9",
    "sg:city":"Bilbao",
    "sg:orig_category":"Doctores En Medicina",
    "sg:phone":"+34 944 23 82 24",
    "sg:postcode":"48009",
    "sg:province":"Vizcaya",
    "wof:name":"Lopez Bergareche Ignacio Maria",
    "wof:placetype":"venue"
},
  "geometry": {"coordinates":[-2.9335200787,43.2664031982],"type":"Point"}
}