{
  "type": "Feature",
  "properties": {
    "iso:country":"ES",
    "sg:address":"Calle de Vespasiano, 6",
    "sg:city":"Merida",
    "sg:orig_category":"Electrodom\u00c9sticos (al Por Menor)",
    "sg:phone":"+34 924 30 20 52",
    "sg:postcode":"06800",
    "sg:province":"Badajoz",
    "wof:name":"Nogales Leon Antonio",
    "wof:placetype":"venue"
},
  "geometry": {"coordinates":[-6.3457570076,38.9196014404],"type":"Point"}
}