{
  "type": "Feature",
  "properties": {
    "iso:country":"ES",
    "sg:address":"Ca N'ermengol, 9",
    "sg:city":"Torre-romeu",
    "sg:orig_category":"L\u00c1ser (fabricaci\u00d3n Y Aplicaciones)",
    "sg:phone":"+34 937 18 25 77",
    "sg:postcode":"08202",
    "sg:province":"Barcelona",
    "wof:name":"Laser Roll S.l.",
    "wof:placetype":"venue"
},
  "geometry": {"coordinates":[2.138461113,41.5398635864],"type":"Point"}
}