{
  "type": "Feature",
  "properties": {
    "addr:full":"Calle de Madrid, 6 Ciudad Rodrigo Salamanca 37500",
    "addr:housenumber":"6",
    "addr:postcode":"37500",
    "addr:street":"Calle De Madrid",
    "iso:country":"ES",
    "sg:address":"Calle de Madrid, 6",
    "sg:city":"Ciudad Rodrigo",
    "sg:orig_category":"Edici\u00d3n De Diarios, Revistas, Boletines",
    "sg:phone":"+34 923 46 26 20",
    "sg:postcode":"37500",
    "sg:province":"Salamanca",
    "wof:name":"Casamar Noticias S.l",
    "wof:placetype":"venue"
},
  "geometry": {"coordinates":[-6.5333719254,40.5977859497],"type":"Point"}
}