{
  "type": "Feature",
  "properties": {
    "iso:country":"ES",
    "sg:address":"Rua Baterias, 14",
    "sg:city":"Ferrol",
    "sg:orig_category":"Reposter\u00cdas",
    "sg:phone":"+34 981 35 54 00",
    "sg:postcode":"15401",
    "sg:province":"A Coru\u00f1a",
    "wof:name":"Torres Gijon Angel",
    "wof:placetype":"venue"
},
  "geometry": {"coordinates":[-8.2466192245,43.4808197021],"type":"Point"}
}