{
  "type": "Feature",
  "properties": {
    "addr:full":"Avda Mantecado (del), S/n Estepa Sevilla 41560",
    "addr:housenumber":"/ n",
    "addr:postcode":"41560",
    "addr:street":"Avda Mantecado Del S;Sevilla",
    "iso:country":"ES",
    "sg:address":"Avda Mantecado (del), S/n",
    "sg:city":"Estepa",
    "sg:orig_category":"Aceites Y Grasas Alimentarias (fabricaci\u00d3n, Al Por Mayor)",
    "sg:phone":"+34 955 91 26 30",
    "sg:postcode":"41560",
    "sg:province":"Sevilla",
    "wof:name":"Consejo Regulador De La Donominacion De Origen Estepa",
    "wof:placetype":"venue"
},
  "geometry": {"coordinates":[-4.884390831,37.2940750122],"type":"Point"}
}