{
  "type": "Feature",
  "properties": {
    "iso:country":"ES",
    "sg:address":"Rbla Marina, 241",
    "sg:city":"Hospitalet Llobregat",
    "sg:orig_category":"Partidos Pol\u00cdticos",
    "sg:phone":"+34 933 35 16 50",
    "sg:postcode":"08907",
    "sg:province":"Barcelona",
    "wof:name":"Partit Socialista Unificat De Catalunya",
    "wof:placetype":"venue"
},
  "geometry": {"coordinates":[2.1113939285,41.3507347107],"type":"Point"}
}