{
  "type": "Feature",
  "properties": {
    "iso:country":"ES",
    "sg:address":"Afores, S/n",
    "sg:city":"Lloret Mar",
    "sg:orig_category":"Bebidas",
    "sg:phone":"+34 972 36 83 95",
    "sg:postcode":"17310",
    "sg:province":"Girona",
    "wof:name":"Farre Canudas Jose",
    "wof:placetype":"venue"
},
  "geometry": {"coordinates":[2.846834898,41.6981697083],"type":"Point"}
}