{
  "type": "Feature",
  "properties": {
    "addr:full":"Calle de Feria (de La), 6 Alcazares Murcia 30710",
    "addr:housenumber":"6",
    "addr:postcode":"30710",
    "addr:street":"Calle De",
    "iso:country":"ES",
    "sg:address":"Calle de Feria (de La), 6",
    "sg:city":"Alcazares",
    "sg:orig_category":"Mercer\u00cda, Lencer\u00cda (al Por Menor)",
    "sg:phone":"+34 968 57 50 79",
    "sg:postcode":"30710",
    "sg:province":"Murcia",
    "wof:name":"Zapata Lopez Jose",
    "wof:placetype":"venue"
},
  "geometry": {"coordinates":[-0.8496710062,37.7391586304],"type":"Point"}
}