{
  "type": "Feature",
  "properties": {
    "iso:country":"ES",
    "sg:address":"Calle de Jose Antonio Primo De Rivera, 41",
    "sg:city":"Arrecife",
    "sg:orig_category":"Ropa Para Se\u00d1oras Y Caballeros (al Por Menor)",
    "sg:phone":"+34 928 80 34 78",
    "sg:postcode":"35500",
    "sg:province":"Las Palmas",
    "wof:name":"Carro Hernandez Javier",
    "wof:placetype":"venue"
},
  "geometry": {"coordinates":[-13.5520792007,28.9595317841],"type":"Point"}
}