{
  "type": "Feature",
  "properties": {
    "addr:full":"Ctra Puertollano, S/n Ciudad Real Ciudad Real 13197",
    "addr:housenumber":"s / n",
    "addr:postcode":"13197",
    "addr:street":"Ctra Puertollano",
    "iso:country":"ES",
    "sg:address":"Ctra Puertollano, S/n",
    "sg:city":"Ciudad Real",
    "sg:orig_category":"Asociaciones Y Clubs Deportivos",
    "sg:phone":"+34 926 21 72 34",
    "sg:postcode":"13197",
    "sg:province":"Ciudad Real",
    "wof:name":"Agrupacion Deportiva Cultural Ciudad Real",
    "wof:placetype":"venue"
},
  "geometry": {"coordinates":[-3.9455664158,38.96824646],"type":"Point"}
}