{
  "type": "Feature",
  "properties": {
    "addr:full":"Calle de Manuel Machado, 4 Roquetas Mar Almer\u00eda 04740",
    "addr:housenumber":"4",
    "addr:postcode":"04740",
    "addr:street":"Calle De Manuel Machado",
    "iso:country":"ES",
    "sg:address":"Calle de Manuel Machado, 4",
    "sg:city":"Roquetas Mar",
    "sg:orig_category":"Oficinas: Suministros Para (fabricaci\u00d3n, Al Por Mayor)",
    "sg:phone":"+34 950 33 84 25",
    "sg:postcode":"04740",
    "sg:province":"Almer\u00eda",
    "wof:name":"Roquepack C.b.",
    "wof:placetype":"venue"
},
  "geometry": {"coordinates":[-2.6139690876,36.7647514343],"type":"Point"}
}