{
  "type": "Feature",
  "properties": {
    "iso:country":"ES",
    "sg:address":"Carrer de Francesc Layret, 23",
    "sg:city":"Mollet Valles",
    "sg:orig_category":"Iglesia Cat\u00d3lica",
    "sg:phone":"+34 935 93 81 63",
    "sg:postcode":"08100",
    "sg:province":"Barcelona",
    "wof:name":"Parroquia De San Vicente De Mollet",
    "wof:placetype":"venue"
},
  "geometry": {"coordinates":[2.2045230865,41.5446205139],"type":"Point"}
}