{
  "type": "Feature",
  "properties": {
    "addr:full":"Ctra Huetor Vega (de), 5 Granada Granada 18008",
    "addr:housenumber":"5",
    "addr:postcode":"18008",
    "addr:street":"Ctra Huetor Vega De",
    "iso:country":"ES",
    "sg:address":"Ctra Huetor Vega (de), 5",
    "sg:city":"Granada",
    "sg:orig_category":"Peluqueros: De Se\u00d1oras",
    "sg:phone":"+34 958 12 53 97",
    "sg:postcode":"18008",
    "sg:province":"Granada",
    "wof:name":"Moreno Ruiz Bartolome",
    "wof:placetype":"venue"
},
  "geometry": {"coordinates":[-3.5870330334,37.1625061035],"type":"Point"}
}