{
  "type": "Feature",
  "properties": {
    "iso:country":"ES",
    "sg:address":"Calle de Isidro Pacense, 1",
    "sg:city":"Badajoz",
    "sg:orig_category":"Equipo De Refrigeraci\u00d3n Industrial",
    "sg:phone":"+34 924 24 29 54",
    "sg:postcode":"06008",
    "sg:province":"Badajoz",
    "wof:name":"Alvarez Uria Jesus",
    "wof:placetype":"venue"
},
  "geometry": {"coordinates":[-6.9557433128,38.8787689209],"type":"Point"}
}