{
  "type": "Feature",
  "properties": {
    "addr:full":"Calle de Doctor Esquerdo, 180 Madrid Madrid 28007",
    "addr:housenumber":"180",
    "addr:postcode":"28007",
    "addr:street":"Calle De Doctor Esquerdo",
    "iso:country":"ES",
    "sg:address":"Calle de Doctor Esquerdo, 180",
    "sg:city":"Madrid",
    "sg:orig_category":"Agencias Y Asesores De Publicidad",
    "sg:phone":"+34 913 65 04 54",
    "sg:postcode":"28007",
    "sg:province":"Madrid",
    "wof:name":"Printeo By Lemon S.l.",
    "wof:placetype":"venue"
},
  "geometry": {"coordinates":[-3.6744890213,40.4018363953],"type":"Point"}
}