{
  "type": "Feature",
  "properties": {
    "iso:country":"ES",
    "sg:address":"Av Republica Argentina, 91",
    "sg:city":"Barcelona",
    "sg:orig_category":"Doctores En Medicina",
    "sg:phone":"+34 932 84 58 02",
    "sg:postcode":"08023",
    "sg:province":"Barcelona",
    "wof:name":"Verger Garau Guillem",
    "wof:placetype":"venue"
},
  "geometry": {"coordinates":[2.1454069614,41.410823822],"type":"Point"}
}