{
  "type": "Feature",
  "properties": {
    "addr:full":"Plgno Urtia, S/n Ermua Vizcaya 48260",
    "addr:housenumber":"s",
    "addr:postcode":"48260",
    "addr:street":"/ N",
    "iso:country":"ES",
    "sg:address":"Plgno Urtia, S/n",
    "sg:city":"Ermua",
    "sg:orig_category":"Herramientas Manuales (fabricaci\u00d3n, Al Por Mayor)",
    "sg:phone":"+34 943 17 03 15",
    "sg:postcode":"48260",
    "sg:province":"Vizcaya",
    "wof:name":"Corte Y Suministros S. A.",
    "wof:placetype":"venue"
},
  "geometry": {"coordinates":[-2.4973800182,43.1792488098],"type":"Point"}
}