{
  "type": "Feature",
  "properties": {
    "addr:full":"Calle de Aduana, 13 Puertollano Ciudad Real 13500",
    "addr:housenumber":"13",
    "addr:postcode":"13500",
    "addr:street":"Calle De Aduana",
    "iso:country":"ES",
    "sg:address":"Calle de Aduana, 13",
    "sg:city":"Puertollano",
    "sg:orig_category":"Zapatos (al Por Menor)",
    "sg:phone":"+34 926 41 24 35",
    "sg:postcode":"13500",
    "sg:province":"Ciudad Real",
    "wof:name":"Garcia Rodriguez Dionisia",
    "wof:placetype":"venue"
},
  "geometry": {"coordinates":[-4.1092104912,38.686882019],"type":"Point"}
}