{
  "type": "Feature",
  "properties": {
    "addr:full":"Carrer de Arago, 340 Barcelona Barcelona 08009",
    "addr:housenumber":"340",
    "addr:postcode":"08009",
    "addr:street":"Carrer De Arago",
    "iso:country":"ES",
    "sg:address":"Carrer de Arago, 340",
    "sg:city":"Barcelona",
    "sg:orig_category":"Centros Empresariales",
    "sg:phone":"+34 932 65 35 31",
    "sg:postcode":"08009",
    "sg:province":"Barcelona",
    "wof:name":"A & C Asistecnic S.l.",
    "wof:placetype":"venue"
},
  "geometry": {"coordinates":[2.1701915264,41.3961257935],"type":"Point"}
}