{
  "type": "Feature",
  "properties": {
    "iso:country":"ES",
    "sg:address":"Ctra Badajoz, Km. 0055,5",
    "sg:city":"San Marcos",
    "sg:orig_category":"Electricidad: Instaladores",
    "sg:phone":"+34 924 67 09 01",
    "sg:postcode":"06200",
    "sg:province":"Badajoz",
    "wof:name":"Fraema S.l.",
    "wof:placetype":"venue"
},
  "geometry": {"coordinates":[-6.4068241119,38.6845092773],"type":"Point"}
}