{
  "type": "Feature",
  "properties": {
    "iso:country":"ES",
    "sg:address":"Carrer de Acacies, 34",
    "sg:city":"Barcelona",
    "sg:orig_category":"Molduras, Junquillos, Listones Y Molduras Perforadas",
    "sg:phone":"+34 933 49 73 98",
    "sg:postcode":"08027",
    "sg:province":"Barcelona",
    "wof:name":"Farre Sala Jose Maria",
    "wof:placetype":"venue"
},
  "geometry": {"coordinates":[2.1783750057,41.4250717163],"type":"Point"}
}