{
  "type": "Feature",
  "properties": {
    "iso:country":"ES",
    "sg:address":"Carrer de Sant Antoni Maria Claret, 139",
    "sg:city":"Barcelona",
    "sg:orig_category":"M\u00c9dicos: Cirug\u00cda General",
    "sg:phone":"+34 934 46 11 73",
    "sg:postcode":"08025",
    "sg:province":"Barcelona",
    "wof:name":"Lara Veliz Galo Ismael",
    "wof:placetype":"venue"
},
  "geometry": {"coordinates":[2.1733050346,41.4106292725],"type":"Point"}
}