{
  "type": "Feature",
  "properties": {
    "addr:full":"Carrer de Miquel Vives, 28 Terrassa Barcelona 08222",
    "addr:housenumber":"28",
    "addr:postcode":"08222",
    "addr:street":"Carrer De Miquel Vives",
    "iso:country":"ES",
    "sg:address":"Carrer de Miquel Vives, 28",
    "sg:city":"Terrassa",
    "sg:orig_category":"Papeler\u00cdas, Librer\u00cdas",
    "sg:phone":"+34 937 83 29 92",
    "sg:postcode":"08222",
    "sg:province":"Barcelona",
    "wof:name":"Papereria Es Vedra S.c.p.",
    "wof:placetype":"venue"
},
  "geometry": {"coordinates":[2.0216870308,41.5633087158],"type":"Point"}
}