{
  "type": "Feature",
  "properties": {
    "addr:full":"Calle de Ricardo Soriano, 2 Pe\u00e7aranda De Bracamonte Salamanca 37300",
    "addr:housenumber":"2",
    "addr:postcode":"37300",
    "addr:street":"Calle De Ricardo Soriano",
    "iso:country":"ES",
    "sg:address":"Calle de Ricardo Soriano, 2",
    "sg:city":"Pe\u00e7aranda De Bracamonte",
    "sg:orig_category":"Frutas Y Legumbres Frescas (al Por Mayor)",
    "sg:phone":"+34 923 54 01 37",
    "sg:postcode":"37300",
    "sg:province":"Salamanca",
    "wof:name":"Hernandez Blanco Pablo",
    "wof:placetype":"venue"
},
  "geometry": {"coordinates":[-5.2003350258,40.9021072388],"type":"Point"}
}