{
  "type": "Feature",
  "properties": {
    "addr:full":"Calle de Cartagena, 17 Madrid Madrid 28028",
    "addr:housenumber":"17",
    "addr:postcode":"madrid;28028",
    "addr:street":"Calle De Cartagena",
    "iso:country":"ES",
    "sg:address":"Calle de Cartagena, 17",
    "sg:city":"Madrid",
    "sg:orig_category":"Distribuci\u00d3n De Petr\u00d3leo Y Derivados",
    "sg:phone":"+34 917 26 08 16",
    "sg:postcode":"28028",
    "sg:province":"Madrid",
    "sg:website":"www.cepsa.es",
    "wof:name":"Martinez Unciti C.b.",
    "wof:placetype":"venue"
},
  "geometry": {"coordinates":[-3.6705505848,40.4321556091],"type":"Point"}
}