{
  "type": "Feature",
  "properties": {
    "addr:full":"Carrer de Baldrich, 211 Terrassa Barcelona 08223",
    "addr:housenumber":"211",
    "addr:postcode":"08223",
    "addr:street":"Carrer De Baldrich",
    "iso:country":"ES",
    "sg:address":"Carrer de Baldrich, 211",
    "sg:city":"Terrassa",
    "sg:orig_category":"Fabricaci\u00d3n De Telas Y Sedas",
    "sg:phone":"+34 937 31 70 31",
    "sg:postcode":"08223",
    "sg:province":"Barcelona",
    "wof:name":"Descalzi S.l.",
    "wof:placetype":"venue"
},
  "geometry": {"coordinates":[2.0157809258,41.554851532],"type":"Point"}
}