{
  "type": "Feature",
  "properties": {
    "addr:full":"Calle de Doctor Calero, 26 Majadahonda Madrid 28220",
    "addr:housenumber":"26",
    "addr:postcode":"28220",
    "addr:street":"Calle De Doctor Calero",
    "iso:country":"ES",
    "sg:address":"Calle de Doctor Calero, 26",
    "sg:city":"Majadahonda",
    "sg:orig_category":"Cajas De Ahorro",
    "sg:phone":"+34 916 34 03 93",
    "sg:postcode":"28220",
    "sg:province":"Madrid",
    "sg:website":"www.lacaixa.es",
    "wof:name":"Caixa D'estalvis I Pensions De Barcelona",
    "wof:placetype":"venue"
},
  "geometry": {"coordinates":[-3.8711698055,40.4738578796],"type":"Point"}
}