{
  "type": "Feature",
  "properties": {
    "iso:country":"ES",
    "sg:address":"Joaquin Sorolla, 55",
    "sg:city":"Rivas Vaciamadrid",
    "sg:orig_category":"Estilistas Y Estudios De Estilo De Corte Y Confecci\u00d3n",
    "sg:phone":"+34 916 66 84 12",
    "sg:postcode":"28529",
    "sg:province":"Madrid",
    "wof:name":"Confecciones Arlos S.a.",
    "wof:placetype":"venue"
},
  "geometry": {"coordinates":[-3.5339739323,40.3467216492],"type":"Point"}
}