{
  "type": "Feature",
  "properties": {
    "iso:country":"ES",
    "sg:address":"Carrer de Gran, 33",
    "sg:city":"Esparreguera",
    "sg:orig_category":"Farmacias",
    "sg:phone":"+34 937 77 11 89",
    "sg:postcode":"08292",
    "sg:province":"Barcelona",
    "wof:name":"Florensa Berenguer Mireia",
    "wof:placetype":"venue"
},
  "geometry": {"coordinates":[1.8689899445,41.5402984619],"type":"Point"}
}