{
  "type": "Feature",
  "properties": {
    "addr:full":"Urb Santo Tomas, 7 Sant Tomas Islas Baleares 07749",
    "addr:housenumber":"7",
    "addr:postcode":"07749",
    "addr:street":"Urb Santo Tomas;Sant Tomas Islas",
    "iso:country":"ES",
    "sg:address":"Urb Santo Tomas, 7",
    "sg:city":"Sant Tomas",
    "sg:orig_category":"Cristaler\u00cda: Suministros",
    "sg:phone":"+34 971 37 04 64",
    "sg:postcode":"07749",
    "sg:province":"Islas Baleares",
    "wof:name":"Margarita Arguimbau S.l.",
    "wof:placetype":"venue"
},
  "geometry": {"coordinates":[4.0503702164,39.9455299377],"type":"Point"}
}