{
  "type": "Feature",
  "properties": {
    "addr:full":"Calle de Antonio Lopez, 6 S. Fernando C\u00e1diz 11100",
    "addr:housenumber":"6",
    "addr:postcode":"11100",
    "addr:street":"Calle De Antonio Lopez;S. Fernando Ca\u0301Diz",
    "iso:country":"ES",
    "sg:address":"Calle de Antonio Lopez, 6",
    "sg:city":"S. Fernando",
    "sg:orig_category":"Zapatos (al Por Menor)",
    "sg:phone":"+34 956 88 75 73",
    "sg:postcode":"11100",
    "sg:province":"C\u00e1diz",
    "wof:name":"Aguilar Urri Manuel",
    "wof:placetype":"venue"
},
  "geometry": {"coordinates":[-6.1988577843,36.4658470154],"type":"Point"}
}