{
  "type": "Feature",
  "properties": {
    "addr:full":"Avda Primero De Mayo, 5 Palmas De Gran Canaria Las Palmas 35002",
    "addr:housenumber":"5",
    "addr:postcode":"35002",
    "addr:street":"Avda Primero De Mayo",
    "iso:country":"ES",
    "sg:address":"Avda Primero De Mayo, 5",
    "sg:city":"Palmas De Gran Canaria",
    "sg:orig_category":"Confecci\u00d3n (fabricaci\u00d3n, Al Por Mayor)",
    "sg:phone":"+34 928 37 34 94",
    "sg:postcode":"35002",
    "sg:province":"Las Palmas",
    "wof:name":"Lozano Garcia Rosario",
    "wof:placetype":"venue"
},
  "geometry": {"coordinates":[-15.4178390503,28.1024436951],"type":"Point"}
}