{
  "type": "Feature",
  "properties": {
    "addr:full":"Avda. Carlos Iii, 99 Parador Hortichuelas Almer\u00eda 04720",
    "addr:housenumber":"99",
    "addr:postcode":"04720",
    "addr:street":"Avda. Carlos Iii;Almeri\u0301A",
    "iso:country":"ES",
    "sg:address":"Avda. Carlos Iii, 99",
    "sg:city":"Parador Hortichuelas",
    "sg:orig_category":"Ropa De Trabajo Y Profesionales (fabricaci\u00d3n, Al Por Mayor)",
    "sg:phone":"+34 950 34 53 60",
    "sg:postcode":"04720",
    "sg:province":"Almer\u00eda",
    "wof:name":"Agodis S.l.",
    "wof:placetype":"venue"
},
  "geometry": {"coordinates":[-2.5590658188,36.8166694641],"type":"Point"}
}