{
  "type": "Feature",
  "properties": {
    "iso:country":"ES",
    "sg:address":"Pol Ind Morea, 3",
    "sg:city":"Beriain",
    "sg:orig_category":"Talleres El\u00c9ctricos Para Veh\u00cdculos",
    "sg:phone":"+34 948 31 05 32",
    "sg:postcode":"31191",
    "sg:province":"Navarra",
    "wof:name":"Talleres Anfe S.l.",
    "wof:placetype":"venue"
},
  "geometry": {"coordinates":[-1.6518089771,42.7533912659],"type":"Point"}
}