{
  "type": "Feature",
  "properties": {
    "iso:country":"ES",
    "sg:address":"Av Mare De Deu De Montserrat, 51",
    "sg:city":"S. Joan Despi",
    "sg:orig_category":"Aparatos, Material Y Suministros Para Laboratorios",
    "sg:phone":"+34 934 80 80 47",
    "sg:postcode":"08970",
    "sg:province":"Barcelona",
    "wof:name":"R.a.l.tecnicas Para El Laboratorio S.a.",
    "wof:placetype":"venue"
},
  "geometry": {"coordinates":[2.0652000904,41.3716011047],"type":"Point"}
}