{
  "type": "Feature",
  "properties": {
    "addr:full":"Calle de Floridablanca, 26 Carmen Murcia 30002",
    "addr:housenumber":"26",
    "addr:postcode":"30002",
    "addr:street":"Calle De Floridablanca",
    "iso:country":"ES",
    "sg:address":"Calle de Floridablanca, 26",
    "sg:city":"Carmen",
    "sg:classifiers":[
        {
            "category":"Autos & Motor Vehicles",
            "subcategory":"Automobile Sales",
            "type":"Retail Goods"
        }
    ],
    "sg:phone":"+34 968 34 35 37",
    "sg:postcode":"30002",
    "sg:province":"Murcia",
    "wof:name":"Lorca Gambin Francisco",
    "wof:placetype":"venue"
},
  "geometry": {"coordinates":[-1.1320749521,37.9774742126],"type":"Point"}
}