{
  "type": "Feature",
  "properties": {
    "addr:full":"Carrer de Taulat, 58 Barcelona Barcelona 08005",
    "addr:housenumber":"58",
    "addr:postcode":"08005",
    "addr:street":"Carrer De Taulat",
    "iso:country":"ES",
    "sg:address":"Carrer de Taulat, 58",
    "sg:city":"Barcelona",
    "sg:orig_category":"Materias Pl\u00c1sticas: Productos De Consumo Masivo (fabricaci\u00d3n, Al Por Mayor)",
    "sg:phone":"+34 932 25 38 55",
    "sg:postcode":"08005",
    "sg:province":"Barcelona",
    "wof:name":"Barnaplast S.c.p.",
    "wof:placetype":"venue"
},
  "geometry": {"coordinates":[2.2057108879,41.3992843628],"type":"Point"}
}