{
  "type": "Feature",
  "properties": {
    "addr:full":"Carrer de Concepcion Arenal, 6 Barcelona Barcelona 08027",
    "addr:housenumber":"6",
    "addr:postcode":"08027",
    "addr:street":"Carrer De Concepcion Arenal",
    "iso:country":"ES",
    "sg:address":"Carrer de Concepcion Arenal, 6",
    "sg:city":"Barcelona",
    "sg:orig_category":"Peluqueros: De Se\u00d1oras",
    "sg:phone":"+34 933 40 97 72",
    "sg:postcode":"08027",
    "sg:province":"Barcelona",
    "wof:name":"Asien Arqueros Isabel",
    "wof:placetype":"venue"
},
  "geometry": {"coordinates":[2.1836605072,41.4179267883],"type":"Point"}
}