{
  "type": "Feature",
  "properties": {
    "iso:country":"ES",
    "sg:address":"Pg Pere Iii, 74",
    "sg:city":"Manresa",
    "sg:orig_category":"Pintura Y Barniz (al Por Menor)",
    "sg:phone":"+34 938 77 27 76",
    "sg:postcode":"08242",
    "sg:province":"Barcelona",
    "wof:name":"Pintures Teixidor S.l.",
    "wof:placetype":"venue"
},
  "geometry": {"coordinates":[1.8294509649,41.7300071716],"type":"Point"}
}