{
  "type": "Feature",
  "properties": {
    "addr:full":"Ctra. Valldemossa, Km. 0010,0 S'esgleieta Islas Baleares 07190",
    "addr:housenumber":"km.",
    "addr:postcode":"07190",
    "addr:street":"Ctra. Valldemossa;0010,0 S'Esgleieta",
    "iso:country":"ES",
    "sg:address":"Ctra. Valldemossa, Km. 0010,0",
    "sg:city":"S'esgleieta",
    "sg:orig_category":"Producci\u00d3n, Venta De Productos De Agricultura Biol\u00d3gica",
    "sg:phone":"+34 971 61 02 81",
    "sg:postcode":"07190",
    "sg:province":"Islas Baleares",
    "wof:name":"Agricola De Promociones S.a.",
    "wof:placetype":"venue"
},
  "geometry": {"coordinates":[2.8577105999,39.5341796875],"type":"Point"}
}