{
  "type": "Feature",
  "properties": {
    "iso:country":"ES",
    "sg:address":"Calle de Itrabo, 1",
    "sg:city":"Almu\u00f1ecar",
    "sg:orig_category":"Comercio, Reparaci\u00d3n De Motocicletas, Bicicletas Y Piezas Sueltas",
    "sg:phone":"+34 958 63 34 85",
    "sg:postcode":"18690",
    "sg:province":"Granada",
    "wof:name":"Estevez Rodriguez Francisco",
    "wof:placetype":"venue"
},
  "geometry": {"coordinates":[-3.6899778843,36.7376403809],"type":"Point"}
}