{
  "type": "Feature",
  "properties": {
    "addr:full":"Calle de Zamora, 65 Salamanca Salamanca 37002",
    "addr:housenumber":"65",
    "addr:postcode":"37002",
    "addr:street":"Calle De Zamora",
    "iso:country":"ES",
    "sg:address":"Calle de Zamora, 65",
    "sg:city":"Salamanca",
    "sg:orig_category":"Comercio De Cuadros, L\u00c1minas Y Reproducciones De Obras De Arte",
    "sg:phone":"+34 923 21 68 02",
    "sg:postcode":"37002",
    "sg:province":"Salamanca",
    "wof:name":"Sanchez Bogajo Adolfo",
    "wof:placetype":"venue"
},
  "geometry": {"coordinates":[-5.6638841629,40.9689445496],"type":"Point"}
}