{
  "type": "Feature",
  "properties": {
    "iso:country":"ES",
    "sg:address":"Calle de Canalejas, 90",
    "sg:city":"Palmas De Gran Canaria",
    "sg:orig_category":"Asesor\u00cda Fiscal Y Jur\u00cddica",
    "sg:phone":"+34 928 36 81 73",
    "sg:postcode":"35003",
    "sg:province":"Las Palmas",
    "wof:name":"Gonzalez Ruano Jose Luis",
    "wof:placetype":"venue"
},
  "geometry": {"coordinates":[-15.42141819,28.1127490997],"type":"Point"}
}