{
  "type": "Feature",
  "properties": {
    "iso:country":"ES",
    "sg:address":"Sella, S/n",
    "sg:city":"Pedreguer",
    "sg:orig_category":"Inmobiliaria (agencias)",
    "sg:phone":"+34 966 45 71 04",
    "sg:postcode":"03750",
    "sg:province":"Alicante",
    "wof:name":"Servicios Denia S.l.",
    "wof:placetype":"venue"
},
  "geometry": {"coordinates":[0.0347849987,38.7958145142],"type":"Point"}
}