{
  "type": "Feature",
  "properties": {
    "iso:country":"ES",
    "sg:address":"Cust Gomerez (de), 34",
    "sg:city":"Granada",
    "sg:orig_category":"Artesan\u00cda",
    "sg:phone":"+34 958 22 80 06",
    "sg:postcode":"18009",
    "sg:province":"Granada",
    "sg:website":"www.moebius.es/grnewart",
    "wof:name":"Granada New Art S.l.",
    "wof:placetype":"venue"
},
  "geometry": {"coordinates":[-3.5940890312,37.1759490967],"type":"Point"}
}