{
  "type": "Feature",
  "properties": {
    "iso:country":"ES",
    "sg:address":"Carrer de Pins Roses, S/n",
    "sg:city":"Cardedeu",
    "sg:orig_category":"Fabricaci\u00d3n De Moldes Y Modelos",
    "sg:phone":"+34 938 71 32 20",
    "sg:postcode":"08440",
    "sg:province":"Barcelona",
    "sg:website":"www.laserreta.com",
    "wof:name":"Moldes La Serreta S.l.",
    "wof:placetype":"venue"
},
  "geometry": {"coordinates":[2.3632700443,41.6251335144],"type":"Point"}
}