{
  "type": "Feature",
  "properties": {
    "addr:full":"Av Meridiana, 535 Barcelona Barcelona 08016",
    "addr:housenumber":"535",
    "addr:postcode":"08016",
    "addr:street":"Meridiana",
    "iso:country":"ES",
    "sg:address":"Av Meridiana, 535",
    "sg:city":"Barcelona",
    "sg:orig_category":"M\u00c9dicos: An\u00c1lisis Cl\u00cdnicos",
    "sg:phone":"+34 934 15 94 32",
    "sg:postcode":"08016",
    "sg:province":"Barcelona",
    "wof:name":"Doctor Rabassa S.a.",
    "wof:placetype":"venue"
},
  "geometry": {"coordinates":[2.1861219406,41.4437141418],"type":"Point"}
}