{
  "type": "Feature",
  "properties": {
    "iso:country":"ES",
    "sg:address":"Pase Carrascal, 12",
    "sg:city":"Villacastin",
    "sg:orig_category":"Explotaci\u00d3n De Canteras",
    "sg:phone":"+34 921 19 81 08",
    "sg:postcode":"40150",
    "sg:province":"Segovia",
    "wof:name":"Prados Quemada Angel",
    "wof:placetype":"venue"
},
  "geometry": {"coordinates":[-4.4140291214,40.777961731],"type":"Point"}
}