{
  "type": "Feature",
  "properties": {
    "iso:country":"ES",
    "sg:address":"Carrer de Bisbe Font Andreu, 4",
    "sg:city":"Vic",
    "sg:orig_category":"Asociaciones Humanitarias, De Cooperaci\u00d3n, De Acci\u00d3n Social",
    "sg:phone":"+34 938 89 54 94",
    "sg:postcode":"08500",
    "sg:province":"Barcelona",
    "wof:name":"Asociacion Reto A La Esperanza",
    "wof:placetype":"venue"
},
  "geometry": {"coordinates":[2.2444922924,41.9282951355],"type":"Point"}
}