{
  "type": "Feature",
  "properties": {
    "addr:full":"Eirexa, S/n Callobre Pontevedra 36688",
    "addr:housenumber":"s / n",
    "addr:postcode":"36688",
    "addr:street":"Eirexa",
    "iso:country":"ES",
    "sg:address":"Eirexa, S/n",
    "sg:city":"Callobre",
    "sg:orig_category":"Veh\u00cdculos De Ocasi\u00d3n",
    "sg:phone":"+34 986 57 07 46",
    "sg:postcode":"36688",
    "sg:province":"Pontevedra",
    "wof:name":"Blanco Garea Manuel",
    "wof:placetype":"venue"
},
  "geometry": {"coordinates":[-8.4677591324,42.6931114197],"type":"Point"}
}