{
  "type": "Feature",
  "properties": {
    "iso:country":"ES",
    "sg:address":"Calle de Juliano Bonny Gomez, 23",
    "sg:city":"Ingenio",
    "sg:orig_category":"Herboristas (al Por Menor)",
    "sg:phone":"+34 928 78 74 19",
    "sg:postcode":"35250",
    "sg:province":"Las Palmas",
    "wof:name":"Rodriguez Castellano Natividad",
    "wof:placetype":"venue"
},
  "geometry": {"coordinates":[-15.4320993423,27.9182357788],"type":"Point"}
}