{
  "type": "Feature",
  "properties": {
    "iso:country":"ES",
    "sg:address":"Ctra Valverde, 5",
    "sg:city":"Badajoz",
    "sg:orig_category":"Florister\u00cdas",
    "sg:phone":"+34 924 26 80 88",
    "sg:postcode":"06010",
    "sg:province":"Badajoz",
    "wof:name":"Garden Center Mandiplant S.l.",
    "wof:placetype":"venue"
},
  "geometry": {"coordinates":[-6.9718742371,38.862613678],"type":"Point"}
}