{
  "type": "Feature",
  "properties": {
    "iso:country":"ES",
    "sg:address":"Calle de San Jose Obrero, 50",
    "sg:city":"Molina Segura",
    "sg:orig_category":"Conservas De Legumbres (fabricaci\u00d3n, Al Por Mayor)",
    "sg:phone":"+34 968 64 29 39",
    "sg:postcode":"30500",
    "sg:province":"Murcia",
    "wof:name":"Euroconservas Foods S.l.",
    "wof:placetype":"venue"
},
  "geometry": {"coordinates":[-1.2119740248,38.0535736084],"type":"Point"}
}