{
  "type": "Feature",
  "properties": {
    "addr:full":"Avda O.n.u. (de La), 70 Mostoles Madrid 28936",
    "addr:housenumber":"70",
    "addr:postcode":"28936",
    "addr:street":"Avda O.N.U. De La",
    "iso:country":"ES",
    "sg:address":"Avda O.n.u. (de La), 70",
    "sg:city":"Mostoles",
    "sg:orig_category":"Bancos",
    "sg:phone":"+34 916 46 89 37",
    "sg:postcode":"28936",
    "sg:province":"Madrid",
    "wof:name":"Banco De Valencia S.a.",
    "wof:placetype":"venue"
},
  "geometry": {"coordinates":[-3.8501219749,40.3175888062],"type":"Point"}
}