{
  "type": "Feature",
  "properties": {
    "addr:full":"Av. Pilar Miro, 1 Rivas Vaciamadrid Madrid 28529",
    "addr:housenumber":"1",
    "addr:postcode":"28529",
    "addr:street":"Av. Pilar Miro",
    "iso:country":"ES",
    "sg:address":"Av. Pilar Miro, 1",
    "sg:city":"Rivas Vaciamadrid",
    "sg:orig_category":"Artes Gr\u00c1ficas, Artes Pl\u00c1sticas: Material Y Suministros (al Por Menor)",
    "sg:phone":"+34 914 99 88 03",
    "sg:postcode":"28529",
    "sg:province":"Madrid",
    "wof:name":"Telefonica Publicidad E Informacion S.a.",
    "wof:placetype":"venue"
},
  "geometry": {"coordinates":[-3.5102670193,40.314289093],"type":"Point"}
}