{
  "type": "Feature",
  "properties": {
    "addr:full":"Calle de San Pascual, 8 Nules Castell\u00f3n 12520",
    "addr:housenumber":"8",
    "addr:postcode":"12520",
    "addr:street":"Calle De San Pascual",
    "iso:country":"ES",
    "sg:address":"Calle de San Pascual, 8",
    "sg:city":"Nules",
    "sg:orig_category":"Maquinaria Para Industrias Diversas",
    "sg:phone":"+34 964 67 01 09",
    "sg:postcode":"12520",
    "sg:province":"Castell\u00f3n",
    "wof:name":"Perez Castell Bartolome",
    "wof:placetype":"venue"
},
  "geometry": {"coordinates":[-0.1549800038,39.8551368713],"type":"Point"}
}