{
  "type": "Feature",
  "properties": {
    "addr:full":"Mercat Proven\u00e7als, S/n Barcelona Barcelona 08005",
    "addr:housenumber":"s",
    "addr:postcode":"08005",
    "addr:street":"/ N",
    "iso:country":"ES",
    "sg:address":"Mercat Proven\u00e7als, S/n",
    "sg:city":"Barcelona",
    "sg:orig_category":"Carnicer\u00cdas, Carnicer\u00cdas",
    "sg:phone":"+34 933 13 36 94",
    "sg:postcode":"08005",
    "sg:province":"Barcelona",
    "wof:name":"Naturcarn S.l.",
    "wof:placetype":"venue"
},
  "geometry": {"coordinates":[2.2067101002,41.4088897705],"type":"Point"}
}