{
  "type": "Feature",
  "properties": {
    "addr:full":"Dehesa Del Valle, S/n Fuencaliente Ciudad Real 13130",
    "addr:housenumber":"s / n",
    "addr:postcode":"fuencaliente;13130",
    "iso:country":"ES",
    "sg:address":"Dehesa Del Valle, S/n",
    "sg:city":"Fuencaliente",
    "sg:orig_category":"Asociaciones Y Clubs Deportivos",
    "sg:phone":"+34 926 69 82 95",
    "sg:postcode":"13130",
    "sg:province":"Ciudad Real",
    "wof:name":"Valmayor S.l.",
    "wof:placetype":"venue"
},
  "geometry": {"coordinates":[-4.3045229912,38.4059181213],"type":"Point"}
}