{
  "type": "Feature",
  "properties": {
    "iso:country":"ES",
    "sg:address":"Avda Jose Laguillo, 22",
    "sg:city":"Sevilla",
    "sg:classifiers":[
        {
            "category":"Autos & Motor Vehicles",
            "subcategory":"Automobile Sales",
            "type":"Retail Goods"
        }
    ],
    "sg:phone":"+34 954 53 50 80",
    "sg:postcode":"41003",
    "sg:province":"Sevilla",
    "wof:name":"Laguillo Jimenez Jose Luis",
    "wof:placetype":"venue"
},
  "geometry": {"coordinates":[-5.980175972,37.3925247192],"type":"Point"}
}