{
  "type": "Feature",
  "properties": {
    "iso:country":"ES",
    "sg:address":"Daza Casta\u00f1eda, 54",
    "sg:city":"Santa Maria Aguila",
    "sg:orig_category":"Reposter\u00cdas",
    "sg:phone":"+34 950 58 07 36",
    "sg:postcode":"04710",
    "sg:province":"Almer\u00eda",
    "wof:name":"Pan Rivera S.l.l.",
    "wof:placetype":"venue"
},
  "geometry": {"coordinates":[-2.7759139538,36.7795753479],"type":"Point"}
}