{
  "type": "Feature",
  "properties": {
    "addr:full":"Calle de Arzobispo Barrios, 5 Cordoba C\u00f3rdoba 14009",
    "addr:housenumber":"5",
    "addr:postcode":"14009",
    "addr:street":"Calle De Arzobispo Barrios;Co\u0301Rdoba",
    "iso:country":"ES",
    "sg:address":"Calle de Arzobispo Barrios, 5",
    "sg:city":"Cordoba",
    "sg:orig_category":"Escayola Y Productos De Escayola (fabricaci\u00d3n, Al Por Mayor)",
    "sg:phone":"+34 957 29 68 50",
    "sg:postcode":"14009",
    "sg:province":"C\u00f3rdoba",
    "wof:name":"Luna Alvarez Juan",
    "wof:placetype":"venue"
},
  "geometry": {"coordinates":[-4.7726964951,37.8735198975],"type":"Point"}
}