{
  "type": "Feature",
  "properties": {
    "iso:country":"ES",
    "sg:address":"Carr Verge Dels Dolors, 5",
    "sg:city":"S. Hilari Sacalm",
    "sg:orig_category":"Promotores Constructores",
    "sg:phone":"+34 972 86 87 18",
    "sg:postcode":"17403",
    "sg:province":"Girona",
    "wof:name":"Obres Molist S.l.",
    "wof:placetype":"venue"
},
  "geometry": {"coordinates":[2.5075950623,41.8801231384],"type":"Point"}
}