{
  "type": "Feature",
  "properties": {
    "iso:country":"ES",
    "sg:address":"Plgno. Industrial, S/n",
    "sg:city":"Amurrio",
    "sg:orig_category":"V\u00c1lvulas",
    "sg:phone":"+34 945 89 07 58",
    "sg:postcode":"01470",
    "sg:province":"\u00c1lava",
    "sg:website":"www.tflsa.com",
    "wof:name":"Talleres F. Larrinaga S. A.",
    "wof:placetype":"venue"
},
  "geometry": {"coordinates":[-3.0012290478,43.0519142151],"type":"Point"}
}