{
  "type": "Feature",
  "properties": {
    "iso:country":"ES",
    "sg:address":"Calle de Uria, 51",
    "sg:city":"Cangas Narcea",
    "sg:orig_category":"Sociedades, Compa\u00d1\u00cdas Aseguradoras",
    "sg:phone":"+34 985 81 09 29",
    "sg:postcode":"33800",
    "sg:province":"Asturias",
    "wof:name":"Mapfre Servicios De Informatica",
    "wof:placetype":"venue"
},
  "geometry": {"coordinates":[-6.5468091965,43.1738014221],"type":"Point"}
}