{
  "type": "Feature",
  "properties": {
    "addr:full":"Av Ntra. Sra. De L'assumpcio, 135 Deltebre Tarragona 43580",
    "addr:housenumber":"135",
    "addr:postcode":"43580",
    "addr:street":"Av Ntra. Sra. De L'Assumpcio",
    "iso:country":"ES",
    "sg:address":"Av Ntra. Sra. De L'assumpcio, 135",
    "sg:city":"Deltebre",
    "sg:orig_category":"Bancos",
    "sg:phone":"+34 977 48 91 31",
    "sg:postcode":"43580",
    "sg:province":"Tarragona",
    "sg:website":"www.banesto.es",
    "wof:name":"Banco Espa\u00f1ol De Credito S.a.",
    "wof:placetype":"venue"
},
  "geometry": {"coordinates":[0.7112089992,40.7191085815],"type":"Point"}
}