{
  "type": "Feature",
  "properties": {
    "iso:country":"ES",
    "sg:address":"Calle de Santa Clara, 12",
    "sg:city":"Burgos",
    "sg:orig_category":"Asesor\u00cda, Estudio Y Control Medioambiental",
    "sg:phone":"+34 947 27 96 00",
    "sg:postcode":"09002",
    "sg:province":"Burgos",
    "wof:name":"Hidra Ingenieria Y Gestion Medioambiental S.l.",
    "wof:placetype":"venue"
},
  "geometry": {"coordinates":[-3.6972239017,42.3378105164],"type":"Point"}
}