{
  "type": "Feature",
  "properties": {
    "addr:full":"Calle de Maria Cristina, 18 Nerva Huelva 21670",
    "addr:housenumber":"18",
    "addr:postcode":"21670",
    "addr:street":"Calle De Maria Cristina",
    "iso:country":"ES",
    "sg:address":"Calle de Maria Cristina, 18",
    "sg:city":"Nerva",
    "sg:orig_category":"Electrodom\u00c9sticos (al Por Menor)",
    "sg:phone":"+34 959 58 22 02",
    "sg:postcode":"21670",
    "sg:province":"Huelva",
    "wof:name":"Servicios De Asistencia Tecnica Atalaya S.l.",
    "wof:placetype":"venue"
},
  "geometry": {"coordinates":[-6.5502691269,37.6937026978],"type":"Point"}
}