{
  "type": "Feature",
  "properties": {
    "iso:country":"ES",
    "sg:address":"Plaz Espa\u00d1a (de), S/n",
    "sg:city":"Valdepe\u00f1as",
    "sg:orig_category":"Organizaciones Internacionales",
    "sg:phone":"+34 926 31 02 42",
    "sg:postcode":"13300",
    "sg:province":"Ciudad Real",
    "wof:name":"Asociacion De Mujeres Y Familias De Ambito Rural",
    "wof:placetype":"venue"
},
  "geometry": {"coordinates":[-3.4599325657,38.8113059998],"type":"Point"}
}