{
  "type": "Feature",
  "properties": {
    "iso:country":"ES",
    "sg:address":"Calle de Goya, 1",
    "sg:city":"Membrilla",
    "sg:orig_category":"Caf\u00c9s, Bares, Cervecer\u00cdas",
    "sg:phone":"+34 926 63 72 86",
    "sg:postcode":"13230",
    "sg:province":"Ciudad Real",
    "wof:name":"Cafeteria Mata S.l.",
    "wof:placetype":"venue"
},
  "geometry": {"coordinates":[-3.3370070457,38.9707603455],"type":"Point"}
}