{
  "type": "Feature",
  "properties": {
    "iso:country":"ES",
    "sg:address":"Carrer de Primer De Maig, 53",
    "sg:city":"Amposta",
    "sg:orig_category":"Guarder\u00cdas",
    "sg:phone":"+34 977 70 24 20",
    "sg:postcode":"43870",
    "sg:province":"Tarragona",
    "wof:name":"Maigi Cid Lourdes Alicia",
    "wof:placetype":"venue"
},
  "geometry": {"coordinates":[0.5754609704,40.7134361267],"type":"Point"}
}