{
  "type": "Feature",
  "properties": {
    "iso:country":"ES",
    "sg:address":"Pg Cid Campeador, 31",
    "sg:city":"Roquetes",
    "sg:orig_category":"Inmobiliaria (agencias)",
    "sg:phone":"+34 938 11 59 98",
    "sg:postcode":"08812",
    "sg:province":"Barcelona",
    "wof:name":"Promociones Ormes 2001 S.l",
    "wof:placetype":"venue"
},
  "geometry": {"coordinates":[1.7461849451,41.2285652161],"type":"Point"}
}