{
  "type": "Feature",
  "properties": {
    "iso:country":"ES",
    "sg:address":"Calle de Cardenal Benlloch, 74",
    "sg:city":"Mislata",
    "sg:orig_category":"M\u00c1quinas Y Material Para La Industria De La Alimentaci\u00d3n",
    "sg:phone":"+34 963 70 42 39",
    "sg:postcode":"46920",
    "sg:province":"Valencia",
    "wof:name":"Valvending S.coop.v.",
    "wof:placetype":"venue"
},
  "geometry": {"coordinates":[-0.4223516881,39.4742584229],"type":"Point"}
}