{
  "type": "Feature",
  "properties": {
    "addr:full":"Calle de Vi\u00d1a Vieja, 3 Llodio \u00c1lava 01400",
    "addr:housenumber":"3",
    "addr:postcode":"01400",
    "addr:street":"Calle De Vin\u0303A Vieja",
    "iso:country":"ES",
    "sg:address":"Calle de Vi\u00d1a Vieja, 3",
    "sg:city":"Llodio",
    "sg:orig_category":"Molduras, Junquillos, Listones Y Molduras Perforadas",
    "sg:phone":"+34 946 72 60 77",
    "sg:postcode":"01400",
    "sg:province":"\u00c1lava",
    "wof:name":"Phone Euskadi S. L.",
    "wof:placetype":"venue"
},
  "geometry": {"coordinates":[-2.963064909,43.144443512],"type":"Point"}
}