{
  "type": "Feature",
  "properties": {
    "addr:full":"Carrer de Albert Einstein, 54 Almeda Mercader Barcelona 08940",
    "addr:housenumber":"54",
    "addr:postcode":"08940",
    "addr:street":"Carrer De Albert Einstein;Mercader Barcelona",
    "iso:country":"ES",
    "sg:address":"Carrer de Albert Einstein, 54",
    "sg:city":"Almeda Mercader",
    "sg:orig_category":"Maquinaria Para Industrias Diversas",
    "sg:phone":"+34 933 77 90 01",
    "sg:postcode":"08940",
    "sg:province":"Barcelona",
    "wof:name":"Vera Castillo Antonio",
    "wof:placetype":"venue"
},
  "geometry": {"coordinates":[2.0740599632,41.356880188],"type":"Point"}
}