{
  "type": "Feature",
  "properties": {
    "addr:full":"C/ Monovar, 50 Elche Alicante 03205",
    "addr:housenumber":"50",
    "addr:postcode":"03205",
    "addr:street":"C / Monovar",
    "iso:country":"ES",
    "sg:address":"C/ Monovar, 50",
    "sg:city":"Elche",
    "sg:orig_category":"M\u00c1quinas Para Recortar Y Pegar",
    "sg:phone":"+34 966 67 04 36",
    "sg:postcode":"03205",
    "sg:province":"Alicante",
    "wof:name":"Troquelados Juanito S.l.",
    "wof:placetype":"venue"
},
  "geometry": {"coordinates":[-0.6995239854,38.2634811401],"type":"Point"}
}