{
  "type": "Feature",
  "properties": {
    "addr:full":"Pg. Montserrat, 30 Cabrera Mar Barcelona 08349",
    "addr:housenumber":"30",
    "addr:postcode":"08349",
    "addr:street":"Pg. Montserrat",
    "iso:country":"ES",
    "sg:address":"Pg. Montserrat, 30",
    "sg:city":"Cabrera Mar",
    "sg:orig_category":"Asesor\u00cda Sobre Comunicaci\u00d3n De Empresas",
    "sg:phone":"+34 937 59 84 86",
    "sg:postcode":"08349",
    "sg:province":"Barcelona",
    "wof:name":"Piedra Mazo Rosa",
    "wof:placetype":"venue"
},
  "geometry": {"coordinates":[2.4016799927,41.5094566345],"type":"Point"}
}