{
  "type": "Feature",
  "properties": {
    "addr:full":"Ctra Gral, S/n Rubayo Cantabria 39719",
    "addr:postcode":"39719",
    "addr:street":"Ctra Gral S / N",
    "iso:country":"ES",
    "sg:address":"Ctra Gral, S/n",
    "sg:city":"Rubayo",
    "sg:orig_category":"Centros De Educaci\u00d3n Especial",
    "sg:phone":"+34 942 50 60 68",
    "sg:postcode":"39719",
    "sg:province":"Cantabria",
    "wof:name":"Ayuntamiento De Marina De Cudeyo",
    "wof:placetype":"venue"
},
  "geometry": {"coordinates":[-3.7554419041,43.4218978882],"type":"Point"}
}