{
  "type": "Feature",
  "properties": {
    "addr:full":"Calle de Parque, 9 Coru\u00d1a La Coru\u00f1a 15002",
    "addr:housenumber":"9",
    "addr:postcode":"15002",
    "addr:street":"Calle De Parque;La Corun\u0303A",
    "iso:country":"ES",
    "sg:address":"Calle de Parque, 9",
    "sg:city":"Coru\u00d1a",
    "sg:orig_category":"Arquitectos",
    "sg:phone":"+34 981 20 90 90",
    "sg:postcode":"15002",
    "sg:province":"La Coru\u00f1a",
    "wof:name":"Gonzalez-cebrian Tello Jose Juan",
    "wof:placetype":"venue"
},
  "geometry": {"coordinates":[-8.3988933563,43.3778266907],"type":"Point"}
}