{
  "type": "Feature",
  "properties": {
    "iso:country":"ES",
    "sg:address":"Calle de Rio Valdecarza, 11",
    "sg:city":"Poligono Sta M. De Benquerencia",
    "sg:orig_category":"Frutas Y Legumbres Frescas (al Por Mayor)",
    "sg:phone":"+34 925 23 04 65",
    "sg:postcode":"45007",
    "sg:province":"Toledo",
    "wof:name":"Romero-salazar Fernandez-cabrera Maria Del Pilar",
    "wof:placetype":"venue"
},
  "geometry": {"coordinates":[-3.9474089146,39.8690643311],"type":"Point"}
}