{
  "type": "Feature",
  "properties": {
    "addr:full":"Calle de La Inmaculada, 27 Barakaldo Vizcaya 48903",
    "addr:housenumber":"27",
    "addr:postcode":"48903",
    "addr:street":"Calle De La Inmaculada",
    "iso:country":"ES",
    "sg:address":"Calle de La Inmaculada, 27",
    "sg:city":"Barakaldo",
    "sg:orig_category":"Comerciantes Al Por Mayor De Vinos, Licores Y Alcoholes",
    "sg:phone":"+34 944 99 88 19",
    "sg:postcode":"48903",
    "sg:province":"Vizcaya",
    "wof:name":"Exclusivas Pasafama, S.l.",
    "wof:placetype":"venue"
},
  "geometry": {"coordinates":[-2.9852569103,43.2848815918],"type":"Point"}
}