{
  "type": "Feature",
  "properties": {
    "iso:country":"ES",
    "sg:address":"Torrent (el), 26",
    "sg:city":"Mataro",
    "sg:orig_category":"Inform\u00c1tica (estudios, Servicios, Asesor\u00cda, Formaci\u00d3n)",
    "sg:phone":"+34 937 41 46 63",
    "sg:postcode":"08302",
    "sg:province":"Barcelona",
    "sg:website":"www.abbelion.com",
    "wof:name":"Regas Pacheco Mercedes",
    "wof:placetype":"venue"
},
  "geometry": {"coordinates":[2.4324100018,41.5336990356],"type":"Point"}
}