{
  "type": "Feature",
  "properties": {
    "iso:country":"ES",
    "sg:address":"Pol Ind El Garrotal, 1",
    "sg:city":"Palma Rio",
    "sg:orig_category":"Animales: Material Y Suministros Para (fabricaci\u00d3n, Al Por Mayor)",
    "sg:phone":"+34 957 64 11 37",
    "sg:postcode":"14700",
    "sg:province":"C\u00f3rdoba",
    "sg:website":"imor-sa.com",
    "wof:name":"Manuel Obrero Ruiz S. A.",
    "wof:placetype":"venue"
},
  "geometry": {"coordinates":[-5.2795991898,37.7004241943],"type":"Point"}
}