{
  "type": "Feature",
  "properties": {
    "addr:full":"Cmno Zandardegi De, 47 Donostia-san Sebastian Guip\u00f9zcoa 20015",
    "addr:housenumber":"47",
    "addr:postcode":"20015",
    "addr:street":"Cmno Zandardegi De",
    "iso:country":"ES",
    "sg:address":"Cmno Zandardegi De, 47",
    "sg:city":"Donostia-san Sebastian",
    "sg:orig_category":"Electricidad: Instaladores",
    "sg:phone":"+34 943 32 03 19",
    "sg:postcode":"20015",
    "sg:province":"Guip\u00f9zcoa",
    "wof:name":"Perez Fernandez Jose Miguel",
    "wof:placetype":"venue"
},
  "geometry": {"coordinates":[-1.9446040392,43.3161392212],"type":"Point"}
}