{
  "type": "Feature",
  "properties": {
    "iso:country":"ES",
    "sg:address":"Gazanda Bidea, 1",
    "sg:city":"Mungia",
    "sg:orig_category":"Electricidad: Material Y Suministros De Instalaci\u00d3n (fabricaci\u00d3n)",
    "sg:phone":"+34 946 74 37 41",
    "sg:postcode":"48100",
    "sg:province":"Vizcaya",
    "wof:name":"Jome C.b.",
    "wof:placetype":"venue"
},
  "geometry": {"coordinates":[-2.8228890896,43.3520736694],"type":"Point"}
}