{
  "type": "Feature",
  "properties": {
    "addr:full":"Calle de Lomo Espigon, 78 Ravelo Bajo Santa Cruz De Tenerife 38359",
    "addr:housenumber":"78",
    "addr:postcode":"38359",
    "addr:street":"Calle De Lomo Espigon",
    "iso:country":"ES",
    "sg:address":"Calle de Lomo Espigon, 78",
    "sg:city":"Ravelo Bajo",
    "sg:classifiers":[
        {
            "category":"Taxi",
            "type":"Transportation"
        }
    ],
    "sg:phone":"+34 922 58 45 21",
    "sg:postcode":"38359",
    "sg:province":"Santa Cruz De Tenerife",
    "wof:name":"Perez Perez Cirilo",
    "wof:placetype":"venue"
},
  "geometry": {"coordinates":[-16.2645397186,28.4603843689],"type":"Point"}
}