{
  "type": "Feature",
  "properties": {
    "iso:country":"ES",
    "sg:address":"Carrer de Feixa Llarga, 7",
    "sg:city":"Hospitalet Llobregat",
    "sg:orig_category":"Serigraf\u00cda (material Y Suministros)",
    "sg:phone":"+34 933 36 38 14",
    "sg:postcode":"08907",
    "sg:province":"Barcelona",
    "wof:name":"Walther Dec S.l.",
    "wof:placetype":"venue"
},
  "geometry": {"coordinates":[2.1102375984,41.3364334106],"type":"Point"}
}