{
  "type": "Feature",
  "properties": {
    "addr:full":"Avda Cid Campeador, 96 Burgos Burgos 09005",
    "addr:housenumber":"96",
    "addr:postcode":"09005",
    "addr:street":"Avda Cid Campeador",
    "iso:country":"ES",
    "sg:address":"Avda Cid Campeador, 96",
    "sg:city":"Burgos",
    "sg:orig_category":"Asociaciones, Organismos Culturales Y Socioeducativos",
    "sg:phone":"+34 947 22 44 86",
    "sg:postcode":"09005",
    "sg:province":"Burgos",
    "wof:name":"Fundacion Burgos Por La Investigacion De La Salud",
    "wof:placetype":"venue"
},
  "geometry": {"coordinates":[-3.6951498985,42.3513183594],"type":"Point"}
}