{
  "type": "Feature",
  "properties": {
    "iso:country":"ES",
    "sg:address":"A (p I Navisa), 13",
    "sg:city":"Sevilla",
    "sg:orig_category":"Servicio De Salud",
    "sg:phone":"+34 954 92 13 82",
    "sg:postcode":"41006",
    "sg:province":"Sevilla",
    "sg:website":"www.achaves.com",
    "wof:name":"Antonio Chaves S.a.",
    "wof:placetype":"venue"
},
  "geometry": {"coordinates":[-5.9462552071,37.37758255],"type":"Point"}
}