{
  "type": "Feature",
  "properties": {
    "addr:full":"Calle de Hostieros, 8 Valladolid Valladolid 47004",
    "addr:housenumber":"8",
    "addr:postcode":"47004",
    "addr:street":"Calle De Hostieros",
    "iso:country":"ES",
    "sg:address":"Calle de Hostieros, 8",
    "sg:city":"Valladolid",
    "sg:orig_category":"Ense\u00d1anza Variada",
    "sg:phone":"+34 983 39 25 80",
    "sg:postcode":"47004",
    "sg:province":"Valladolid",
    "sg:website":"www.escueladehosteleria.com",
    "wof:name":"Martinez Antolinez Javier",
    "wof:placetype":"venue"
},
  "geometry": {"coordinates":[-4.7229509354,41.6478538513],"type":"Point"}
}