{
  "type": "Feature",
  "properties": {
    "iso:country":"ES",
    "sg:address":"Calle de Julian Romero, 27",
    "sg:city":"Sanlucar Mayor",
    "sg:orig_category":"Empresas De Carpinter\u00cda De Madera",
    "sg:phone":"+34 955 70 22 97",
    "sg:postcode":"41800",
    "sg:province":"Sevilla",
    "wof:name":"Garcia Y Luque Sociedad Civil",
    "wof:placetype":"venue"
},
  "geometry": {"coordinates":[-6.2034020424,37.3837165833],"type":"Point"}
}