{
  "type": "Feature",
  "properties": {
    "addr:full":"Calle de Luis Zapata (de), 30 Navalcarnero Madrid 28600",
    "addr:housenumber":"30",
    "addr:postcode":"28600",
    "addr:street":"Calle De Luis Zapata De",
    "iso:country":"ES",
    "sg:address":"Calle de Luis Zapata (de), 30",
    "sg:city":"Navalcarnero",
    "sg:orig_category":"Papeler\u00cdas, Librer\u00cdas",
    "sg:phone":"+34 918 11 39 50",
    "sg:postcode":"28600",
    "sg:province":"Madrid",
    "wof:name":"Leiva Escobar Dolores",
    "wof:placetype":"venue"
},
  "geometry": {"coordinates":[-4.0102162361,40.2883605957],"type":"Point"}
}