{
  "type": "Feature",
  "properties": {
    "iso:country":"ES",
    "sg:address":"Carr Sant Mori, 26",
    "sg:city":"Empuriabrava",
    "sg:orig_category":"Peluquer\u00cdas, Peluquer\u00cda Mixta",
    "sg:phone":"+34 972 45 13 69",
    "sg:postcode":"17487",
    "sg:province":"Girona",
    "wof:name":"Rietz  Susana",
    "wof:placetype":"venue"
},
  "geometry": {"coordinates":[3.1236419678,42.2431983948],"type":"Point"}
}