{
  "type": "Feature",
  "properties": {
    "addr:full":"Carr Ecce Homo, 38 Villarreal Castell\u00f3n 12540",
    "addr:housenumber":"38",
    "addr:postcode":"12540",
    "addr:street":"Carr Ecce Homo",
    "iso:country":"ES",
    "sg:address":"Carr Ecce Homo, 38",
    "sg:city":"Villarreal",
    "sg:orig_category":"Peluquer\u00cdas, Peluquer\u00cda Mixta",
    "sg:phone":"+34 964 53 20 17",
    "sg:postcode":"12540",
    "sg:province":"Castell\u00f3n",
    "wof:name":"Gallego Ma\u00f1as Piedad",
    "wof:placetype":"venue"
},
  "geometry": {"coordinates":[-0.1022858992,39.9374389648],"type":"Point"}
}