{
  "type": "Feature",
  "properties": {
    "iso:country":"ES",
    "sg:address":"Av San Jorge, 71",
    "sg:city":"Iru\u00f1a",
    "sg:orig_category":"Supermercados Y Hipermercados",
    "sg:phone":"+34 948 12 85 11",
    "sg:postcode":"31012",
    "sg:province":"Navarra",
    "sg:website":"www.capraboacasa.com",
    "wof:name":"Caprabo S.a.",
    "wof:placetype":"venue"
},
  "geometry": {"coordinates":[-1.6682879925,42.820854187],"type":"Point"}
}