{
  "type": "Feature",
  "properties": {
    "iso:country":"ES",
    "sg:address":"Carrer de Unio, 9",
    "sg:city":"Palma",
    "sg:orig_category":"Centros M\u00c9dicos Y Sociales, Dispensarios",
    "sg:phone":"+34 971 22 80 67",
    "sg:postcode":"07001",
    "sg:province":"Islas Baleares",
    "sg:website":"www.arztehauspalma.de",
    "wof:name":"Weesholler  Johannes",
    "wof:placetype":"venue"
},
  "geometry": {"coordinates":[2.6481990814,39.5715522766],"type":"Point"}
}