{
  "type": "Feature",
  "properties": {
    "addr:full":"Av Josep Tarradellas, 48 Viladecans Barcelona 08840",
    "addr:housenumber":"48",
    "addr:postcode":"08840",
    "addr:street":"Av Josep Tarradellas",
    "iso:country":"ES",
    "sg:address":"Av Josep Tarradellas, 48",
    "sg:city":"Viladecans",
    "sg:orig_category":"Servicios Gsm",
    "sg:phone":"+34 936 37 93 37",
    "sg:postcode":"08840",
    "sg:province":"Barcelona",
    "wof:name":"Informadoric S.l.",
    "wof:placetype":"venue"
},
  "geometry": {"coordinates":[2.0157170296,41.3126907349],"type":"Point"}
}