{
  "type": "Feature",
  "properties": {
    "iso:country":"ES",
    "sg:address":"Carrer de Proven\u00c7a, 483",
    "sg:city":"Barcelona",
    "sg:orig_category":"Sociedades, Compa\u00d1\u00cdas Aseguradoras",
    "sg:phone":"+34 934 35 35 96",
    "sg:postcode":"08025",
    "sg:province":"Barcelona",
    "wof:name":"Cep Correduria De Seguros S A",
    "wof:placetype":"venue"
},
  "geometry": {"coordinates":[2.1767659187,41.4063911438],"type":"Point"}
}