{
  "type": "Feature",
  "properties": {
    "iso:country":"ES",
    "sg:address":"Carrer de Luxemburg, 8",
    "sg:city":"Rubi",
    "sg:orig_category":"Seguridad En El Trabajo Y Prevenci\u00d3n De Riesgos Laborales",
    "sg:phone":"+34 936 99 80 68",
    "sg:postcode":"08191",
    "sg:province":"Barcelona",
    "wof:name":"Potecciones Del Norte S.l.",
    "wof:placetype":"venue"
},
  "geometry": {"coordinates":[2.0274920464,41.4815216064],"type":"Point"}
}