{
  "type": "Feature",
  "properties": {
    "iso:country":"ES",
    "sg:address":"Calle de Mostoles, 78",
    "sg:city":"Sabatera",
    "sg:orig_category":"Inmobiliaria (agencias)",
    "sg:phone":"+34 966 49 17 84",
    "sg:postcode":"03725",
    "sg:province":"Alicante",
    "sg:website":"www.chribento.protopertiesspain.com",
    "wof:name":"Chribento Sociedad Limitada",
    "wof:placetype":"venue"
},
  "geometry": {"coordinates":[0.1012500003,38.7296409607],"type":"Point"}
}