{
  "type": "Feature",
  "properties": {
    "iso:country":"ES",
    "sg:address":"Avda Sancho El Sabio, 27",
    "sg:city":"Donostia-san Sebastian",
    "sg:classifiers":[
        {
            "category":"Personal",
            "subcategory":"Barber",
            "type":"Services"
        }
    ],
    "sg:phone":"+34 943 45 59 97",
    "sg:postcode":"20010",
    "sg:province":"Guip\u00f9zcoa",
    "sg:tags":[
        "caballeros",
        "de",
        "peluqueros"
    ],
    "wof:name":"Sanchez Huerta Enrique",
    "wof:placetype":"venue"
},
  "geometry": {"coordinates":[-1.9796420336,43.3089637756],"type":"Point"}
}