{
  "type": "Feature",
  "properties": {
    "iso:country":"ES",
    "sg:address":"Camino De Santiago, 38",
    "sg:city":"Pte Villarente",
    "sg:orig_category":"Venta, Montaje De Neum\u00c1ticos",
    "sg:phone":"+34 987 31 22 27",
    "sg:postcode":"24226",
    "sg:province":"Le\u00f3n",
    "wof:name":"Carcedo Gutierrez Isidoro",
    "wof:placetype":"venue"
},
  "geometry": {"coordinates":[-5.4851689339,42.5182266235],"type":"Point"}
}