{
  "type": "Feature",
  "properties": {
    "iso:country":"ES",
    "sg:address":"Plaz Espa\u00d1a, 3",
    "sg:city":"Pozuelo De Zarzon",
    "sg:orig_category":"Talleres De Corte Y Confecci\u00d3n",
    "sg:phone":"+34 927 44 81 32",
    "sg:postcode":"10813",
    "sg:province":"C\u00e1ceres",
    "wof:name":"Gil Paule Margarita",
    "wof:placetype":"venue"
},
  "geometry": {"coordinates":[-6.4163150787,40.149646759],"type":"Point"}
}