{
  "type": "Feature",
  "properties": {
    "addr:full":"C/ Sant Lluis, 32 Cerdanyola Valles Barcelona 08290",
    "addr:housenumber":"32",
    "addr:postcode":"08290",
    "addr:street":"C / Sant Lluis;Valles Barcelona",
    "iso:country":"ES",
    "sg:address":"C/ Sant Lluis, 32",
    "sg:city":"Cerdanyola Valles",
    "sg:orig_category":"Inform\u00c1tica: Soportes De Informaci\u00d3n, Suministros & Accesorios",
    "sg:phone":"+34 935 86 55 07",
    "sg:postcode":"08290",
    "sg:province":"Barcelona",
    "wof:name":"Zurzal Reciclajes S.l.",
    "wof:placetype":"venue"
},
  "geometry": {"coordinates":[2.1435468197,41.4954833984],"type":"Point"}
}