{
  "type": "Feature",
  "properties": {
    "iso:country":"ES",
    "sg:address":"Calle de Riquelme, 13",
    "sg:city":"Santa Catalina",
    "sg:orig_category":"Dise\u00d1o Industrial",
    "sg:phone":"+34 968 22 38 05",
    "sg:postcode":"30005",
    "sg:province":"Murcia",
    "sg:website":"www.offdisen.com",
    "wof:name":"Off Dise\u00f1o S.l.",
    "wof:placetype":"venue"
},
  "geometry": {"coordinates":[-1.1337089539,37.9849205017],"type":"Point"}
}