{
  "type": "Feature",
  "properties": {
    "addr:full":"Erletxes I Pltfma A/0, 14 Galdakao Vizcaya 48960",
    "addr:housenumber":"14",
    "addr:postcode":"48960",
    "iso:country":"ES",
    "sg:address":"Erletxes I Pltfma A/0, 14",
    "sg:city":"Galdakao",
    "sg:orig_category":"Fachadas",
    "sg:phone":"+34 946 00 90 70",
    "sg:postcode":"48960",
    "sg:province":"Vizcaya",
    "wof:name":"Fachadas Singulares Abarre, S.a.",
    "wof:placetype":"venue"
},
  "geometry": {"coordinates":[-2.8470389843,43.2298049927],"type":"Point"}
}