{
  "type": "Feature",
  "properties": {
    "iso:country":"ES",
    "sg:address":"Calle de San Fernando, 19",
    "sg:city":"Yecla",
    "sg:orig_category":"Tapicer\u00cdas",
    "sg:phone":"+34 968 71 87 43",
    "sg:postcode":"30510",
    "sg:province":"Murcia",
    "wof:name":"Soriano Martinez Maria Magdalena",
    "wof:placetype":"venue"
},
  "geometry": {"coordinates":[-1.1108754873,38.6096763611],"type":"Point"}
}