{
  "type": "Feature",
  "properties": {
    "addr:full":"C/ Dels Horts, 4 Paterna Valencia 46980",
    "addr:housenumber":"4",
    "addr:postcode":"46980",
    "addr:street":"C / Dels Horts",
    "iso:country":"ES",
    "sg:address":"C/ Dels Horts, 4",
    "sg:city":"Paterna",
    "sg:orig_category":"Abogados",
    "sg:phone":"+34 961 38 54 62",
    "sg:postcode":"46980",
    "sg:province":"Valencia",
    "wof:name":"Guillem Costabella Juan Bautista",
    "wof:placetype":"venue"
},
  "geometry": {"coordinates":[-0.4430339932,39.5009613037],"type":"Point"}
}