{
  "type": "Feature",
  "properties": {
    "iso:country":"ES",
    "sg:address":"Carr Carmesina (de), 3",
    "sg:city":"Gandia",
    "sg:orig_category":"Ropa Para Ni\u00d1os (al Por Menor)",
    "sg:phone":"+34 962 95 41 85",
    "sg:postcode":"46700",
    "sg:province":"Valencia",
    "sg:website":"www.benetton.com",
    "wof:name":"Zerodotze S.l.",
    "wof:placetype":"venue"
},
  "geometry": {"coordinates":[-0.1796112061,38.9672698975],"type":"Point"}
}