{
  "type": "Feature",
  "properties": {
    "addr:full":"Av Puig I Cadafalch, 6 Argentona Barcelona 08310",
    "addr:housenumber":"6",
    "addr:postcode":"08310",
    "addr:street":"Av Puig;Cadafalch",
    "iso:country":"ES",
    "sg:address":"Av Puig I Cadafalch, 6",
    "sg:city":"Argentona",
    "sg:orig_category":"Reposter\u00cdas",
    "sg:phone":"+34 937 97 13 61",
    "sg:postcode":"08310",
    "sg:province":"Barcelona",
    "wof:name":"Fleca Casas S.l.",
    "wof:placetype":"venue"
},
  "geometry": {"coordinates":[2.4025828838,41.5541496277],"type":"Point"}
}