{
  "type": "Feature",
  "properties": {
    "iso:country":"ES",
    "sg:address":"Santa Cristina, S/n",
    "sg:city":"Noia",
    "sg:orig_category":"Serrer\u00cdas De Madera",
    "sg:phone":"+34 981 82 39 02",
    "sg:postcode":"15200",
    "sg:province":"La Coru\u00f1a",
    "wof:name":"Moledo Laranga Jose",
    "wof:placetype":"venue"
},
  "geometry": {"coordinates":[-8.8931541443,42.791469574],"type":"Point"}
}