{
  "type": "Feature",
  "properties": {
    "iso:country":"ES",
    "sg:address":"Avda Burgos, 5",
    "sg:city":"Aranda Duero",
    "sg:orig_category":"Florister\u00cdas",
    "sg:phone":"+34 947 50 32 38",
    "sg:postcode":"09400",
    "sg:province":"Burgos",
    "wof:name":"Terraza Gil Maria Esther",
    "wof:placetype":"venue"
},
  "geometry": {"coordinates":[-3.6787559986,41.6698799133],"type":"Point"}
}