{
  "type": "Feature",
  "properties": {
    "iso:country":"ES",
    "sg:address":"Plaz Colon (de), 19",
    "sg:city":"Cordoba",
    "sg:orig_category":"Asesor\u00cda Sobre Comunicaci\u00d3n De Empresas",
    "sg:phone":"+34 957 47 27 68",
    "sg:postcode":"14001",
    "sg:province":"C\u00f3rdoba",
    "sg:website":"www.jjconsultores.com",
    "wof:name":"Jjf Soluciones De Empresa Sll",
    "wof:placetype":"venue"
},
  "geometry": {"coordinates":[-4.779009819,37.8911705017],"type":"Point"}
}