{
  "type": "Feature",
  "properties": {
    "addr:full":"Plaz Caldas Da Rainha, 38 Badajoz Badajoz 06004",
    "addr:postcode":"38;06004",
    "addr:street":"Plaz",
    "iso:country":"ES",
    "sg:address":"Plaz Caldas Da Rainha, 38",
    "sg:city":"Badajoz",
    "sg:orig_category":"Perreras, Pensiones Para Perros, Gatos Y Otros Animales",
    "sg:phone":"+34 924 26 28 36",
    "sg:postcode":"06004",
    "sg:province":"Badajoz",
    "wof:name":"Ramos Noriega Irene",
    "wof:placetype":"venue"
},
  "geometry": {"coordinates":[-6.9726238251,38.874835968],"type":"Point"}
}