{
  "type": "Feature",
  "properties": {
    "iso:country":"ES",
    "sg:address":"Avda Lugo (de), 9",
    "sg:city":"Chantada",
    "sg:orig_category":"Comercio De Piezas De Recambio Y De Accesorios De Veh\u00cdculos, Veh\u00cdculos Industriales",
    "sg:phone":"+34 982 44 00 23",
    "sg:postcode":"27500",
    "sg:province":"Lugo",
    "wof:name":"Armesto Hermida Jose Luis",
    "wof:placetype":"venue"
},
  "geometry": {"coordinates":[-7.7687158585,42.6167869568],"type":"Point"}
}