{
  "type": "Feature",
  "properties": {
    "addr:full":"Urb. El Palmeral, S/n Mojacar Almer\u00eda 04638",
    "addr:housenumber":"s / n",
    "addr:postcode":"04638",
    "addr:street":"Almeri\u0301A",
    "iso:country":"ES",
    "sg:address":"Urb. El Palmeral, S/n",
    "sg:city":"Mojacar",
    "sg:orig_category":"Promotores Constructores",
    "sg:phone":"+34 950 47 24 24",
    "sg:postcode":"04638",
    "sg:province":"Almer\u00eda",
    "wof:name":"Borja Blanca Promotora De Construcciones S.l.",
    "wof:placetype":"venue"
},
  "geometry": {"coordinates":[-1.8315290213,37.1453361511],"type":"Point"}
}