{
  "type": "Feature",
  "properties": {
    "addr:full":"Carrer de Sant Francesc, 26 Sitges Barcelona 08870",
    "addr:housenumber":"26",
    "addr:postcode":"08870",
    "addr:street":"Carrer De Sant Francesc",
    "iso:country":"ES",
    "sg:address":"Carrer de Sant Francesc, 26",
    "sg:city":"Sitges",
    "sg:orig_category":"Administradores De Bienes Y Delegados De Comunidades De Propietarios",
    "sg:phone":"+34 938 11 13 75",
    "sg:postcode":"08870",
    "sg:province":"Barcelona",
    "sg:website":"www.fincascorral.com",
    "wof:name":"Fincas Corral Mediterraneo S.l.",
    "wof:placetype":"venue"
},
  "geometry": {"coordinates":[1.8083939552,41.2376480103],"type":"Point"}
}