{
  "type": "Feature",
  "properties": {
    "addr:full":"Calle de Morse, 5 Getafe Madrid 28906",
    "addr:housenumber":"5",
    "addr:postcode":"28906",
    "addr:street":"Calle De Morse",
    "iso:country":"ES",
    "sg:address":"Calle de Morse, 5",
    "sg:city":"Getafe",
    "sg:orig_category":"Laboratorios Y Trabajos De Fotograf\u00cda, V\u00cddeo Y Cine",
    "sg:phone":"+34 916 82 69 11",
    "sg:postcode":"28906",
    "sg:province":"Madrid",
    "wof:name":"Gemaher S.a.",
    "wof:placetype":"venue"
},
  "geometry": {"coordinates":[-3.7023348808,40.3020057678],"type":"Point"}
}