{
  "type": "Feature",
  "properties": {
    "iso:country":"ES",
    "sg:address":"Avda. De Vilalba, 69",
    "sg:city":"Pontes Garcia Rodriguez",
    "sg:orig_category":"Pod\u00d3logos: Pedicuros",
    "sg:phone":"+34 981 45 01 81",
    "sg:postcode":"15320",
    "sg:province":"La Coru\u00f1a",
    "wof:name":"Ledo Filgueiras Andrea",
    "wof:placetype":"venue"
},
  "geometry": {"coordinates":[-7.9020018578,43.449848175],"type":"Point"}
}