{
  "type": "Feature",
  "properties": {
    "addr:full":"Calle de Losada Pintor, 19 Bilbao Vizcaya 48004",
    "addr:housenumber":"19",
    "addr:postcode":"48004",
    "addr:street":"Calle De Losada Pintor",
    "iso:country":"ES",
    "sg:address":"Calle de Losada Pintor, 19",
    "sg:city":"Bilbao",
    "sg:classifiers":[
        {
            "category":"Personal",
            "subcategory":"Barber",
            "type":"Services"
        }
    ],
    "sg:phone":"+34 944 11 66 22",
    "sg:postcode":"48004",
    "sg:province":"Vizcaya",
    "sg:tags":[
        "caballeros",
        "de",
        "peluqueros"
    ],
    "wof:name":"Jose Ramon Cerezo Mu\u00f1oz",
    "wof:placetype":"venue"
},
  "geometry": {"coordinates":[-2.9127898216,43.2490844727],"type":"Point"}
}