{
  "type": "Feature",
  "properties": {
    "addr:full":"Calle de Playa Del Sardinero, 11 Matas-pinar-monte Rozas Madrid 28290",
    "addr:housenumber":"11",
    "addr:postcode":"28290",
    "addr:street":"Calle De Playa Del Sardinero",
    "iso:country":"ES",
    "sg:address":"Calle de Playa Del Sardinero, 11",
    "sg:city":"Matas-pinar-monte Rozas",
    "sg:orig_category":"Maquinaria Para Industrias Diversas",
    "sg:phone":"+34 916 30 41 46",
    "sg:postcode":"28290",
    "sg:province":"Madrid",
    "wof:name":"Eusitrade S.l.",
    "wof:placetype":"venue"
},
  "geometry": {"coordinates":[-3.9000749588,40.5392837524],"type":"Point"}
}