{
  "type": "Feature",
  "properties": {
    "addr:full":"Calle de Real, 200 S. Fernando C\u00e1diz 11100",
    "addr:housenumber":"200",
    "addr:postcode":"11100",
    "addr:street":"Calle De Real;S. Fernando Ca\u0301Diz",
    "iso:country":"ES",
    "sg:address":"Calle de Real, 200",
    "sg:city":"S. Fernando",
    "sg:orig_category":"Restaurantes",
    "sg:phone":"+34 956 89 36 02",
    "sg:postcode":"11100",
    "sg:province":"C\u00e1diz",
    "wof:name":"Zhu Yin Qinchao",
    "wof:placetype":"venue"
},
  "geometry": {"coordinates":[-6.2020850182,36.4590988159],"type":"Point"}
}