{
  "type": "Feature",
  "properties": {
    "iso:country":"ES",
    "sg:address":"Sbda San Antonio, 4",
    "sg:city":"Cartagena",
    "sg:orig_category":"Organizaciones Internacionales",
    "sg:phone":"+34 968 12 27 76",
    "sg:postcode":"30202",
    "sg:province":"Murcia",
    "wof:name":"Asociacion Ayuda Mujer Embarazada",
    "wof:placetype":"venue"
},
  "geometry": {"coordinates":[-0.8961216807,37.58203125],"type":"Point"}
}