{
  "type": "Feature",
  "properties": {
    "addr:full":"Avda Felipe Ii (de), S/n Mostoles Madrid 28936",
    "addr:postcode":"28936",
    "addr:street":"Avda Felipe Ii De S / N Mostoles",
    "iso:country":"ES",
    "sg:address":"Avda Felipe Ii (de), S/n",
    "sg:city":"Mostoles",
    "sg:orig_category":"Carnicer\u00cdas, Carnicer\u00cdas",
    "sg:phone":"+34 916 46 93 44",
    "sg:postcode":"28936",
    "sg:province":"Madrid",
    "wof:name":"Prieto Sastre Santiago",
    "wof:placetype":"venue"
},
  "geometry": {"coordinates":[-3.8544650078,40.3199958801],"type":"Point"}
}