{
  "type": "Feature",
  "properties": {
    "addr:full":"Calle de Artabide, 19 Ondarroa Vizcaya 48700",
    "addr:housenumber":"19",
    "addr:postcode":"48700",
    "addr:street":"Calle De Artabide",
    "iso:country":"ES",
    "sg:address":"Calle de Artabide, 19",
    "sg:city":"Ondarroa",
    "sg:orig_category":"Frutas, Legumbres Frescas Y Tempranas (al Por Menor)",
    "sg:phone":"+34 946 83 02 54",
    "sg:postcode":"48700",
    "sg:province":"Vizcaya",
    "wof:name":"Lourdes Lazkano Galdos - Fruteria Bolin",
    "wof:placetype":"venue"
},
  "geometry": {"coordinates":[-2.4227201939,43.3224868774],"type":"Point"}
}