{
  "type": "Feature",
  "properties": {
    "addr:full":"Calle de Portalada (la), 11 Logro\u00f1o La Rioja 26006",
    "addr:housenumber":"11",
    "addr:postcode":"26006",
    "addr:street":"Calle De Portalada La;Rioja",
    "iso:country":"ES",
    "sg:address":"Calle de Portalada (la), 11",
    "sg:city":"Logro\u00f1o",
    "sg:orig_category":"Empresas De Carpinter\u00cda De Madera",
    "sg:phone":"+34 941 25 82 80",
    "sg:postcode":"26006",
    "sg:province":"La Rioja",
    "wof:name":"Gonzalez Carpinteria Mecanica S.l.",
    "wof:placetype":"venue"
},
  "geometry": {"coordinates":[-2.4108641148,42.458026886],"type":"Point"}
}