{
  "type": "Feature",
  "properties": {
    "addr:full":"Rua Ourense, 82 Lugo Lugo 27004",
    "addr:housenumber":"82",
    "addr:postcode":"27004",
    "addr:street":"Rua Ourense",
    "iso:country":"ES",
    "sg:address":"Rua Ourense, 82",
    "sg:city":"Lugo",
    "sg:orig_category":"Electrodom\u00c9sticos (al Por Menor)",
    "sg:phone":"+34 982 21 05 40",
    "sg:postcode":"27004",
    "sg:province":"Lugo",
    "wof:name":"Bao Rodriguez Aurelio",
    "wof:placetype":"venue"
},
  "geometry": {"coordinates":[-7.5654859543,43.0156898499],"type":"Point"}
}