{
  "type": "Feature",
  "properties": {
    "iso:country":"ES",
    "sg:address":"Carrer de Pous, 22",
    "sg:city":"S. Andreu Barca",
    "sg:orig_category":"Producci\u00d3n De Huevos",
    "sg:phone":"+34 936 53 16 93",
    "sg:postcode":"08740",
    "sg:province":"Barcelona",
    "sg:website":"www.granjamenosersmas.com",
    "wof:name":"Avicola Amenos S.l",
    "wof:placetype":"venue"
},
  "geometry": {"coordinates":[1.9729809761,41.4531173706],"type":"Point"}
}