{
  "type": "Feature",
  "properties": {
    "iso:country":"ES",
    "sg:address":"Calle de General Ruiz, 11",
    "sg:city":"Arnedo",
    "sg:orig_category":"Plomeros",
    "sg:phone":"+34 941 38 46 47",
    "sg:postcode":"26580",
    "sg:province":"La Rioja",
    "wof:name":"Breton Ruiz Alejos Enrique",
    "wof:placetype":"venue"
},
  "geometry": {"coordinates":[-2.1015388966,42.2279014587],"type":"Point"}
}