{
  "type": "Feature",
  "properties": {
    "addr:full":"Calle de Gregorio Fernandez, 1 Valladolid Valladolid 47006",
    "addr:housenumber":"1",
    "addr:postcode":"47006",
    "addr:street":"Calle De Gregorio Fernandez",
    "iso:country":"ES",
    "sg:address":"Calle de Gregorio Fernandez, 1",
    "sg:city":"Valladolid",
    "sg:orig_category":"M\u00c9dicos: Dermatolog\u00cda Y Venereolog\u00cda",
    "sg:phone":"+34 983 34 42 82",
    "sg:postcode":"47006",
    "sg:province":"Valladolid",
    "wof:name":"Jo Chu Juan",
    "wof:placetype":"venue"
},
  "geometry": {"coordinates":[-4.7334041595,41.6458892822],"type":"Point"}
}