{
  "type": "Feature",
  "properties": {
    "addr:full":"Carrer de Hierbabuena, 1 Hospitalet Llobregat Barcelona 08906",
    "addr:housenumber":"1",
    "addr:postcode":"08906",
    "addr:street":"Carrer De Hierbabuena",
    "iso:country":"ES",
    "sg:address":"Carrer de Hierbabuena, 1",
    "sg:city":"Hospitalet Llobregat",
    "sg:orig_category":"Alimentaci\u00d3n General (al Por Menor)",
    "sg:phone":"+34 934 38 60 78",
    "sg:postcode":"08906",
    "sg:province":"Barcelona",
    "wof:name":"Alimentacion Ramos Scp",
    "wof:placetype":"venue"
},
  "geometry": {"coordinates":[2.1022987366,41.3691596985],"type":"Point"}
}