{
  "type": "Feature",
  "properties": {
    "iso:country":"ES",
    "sg:address":"Arquimedes, 21",
    "sg:city":"Gijon",
    "sg:orig_category":"Cerrajer\u00cda, Ferrallista",
    "sg:phone":"+34 985 16 83 66",
    "sg:postcode":"33211",
    "sg:province":"Asturias",
    "wof:name":"Vallina Y Quince S.l.",
    "wof:placetype":"venue"
},
  "geometry": {"coordinates":[-5.6933031082,43.5049705505],"type":"Point"}
}