{
  "type": "Feature",
  "properties": {
    "iso:country":"ES",
    "sg:address":"Calle de Puerto, S/n",
    "sg:city":"Almaraz De Duero",
    "sg:orig_category":"Centros De Educaci\u00d3n Especial",
    "sg:phone":"+34 980 55 41 06",
    "sg:postcode":"49180",
    "sg:province":"Zamora",
    "wof:name":"C.e.i.p. De Almaraz De Duero",
    "wof:placetype":"venue"
},
  "geometry": {"coordinates":[-5.9155521393,41.4697341919],"type":"Point"}
}