{
  "type": "Feature",
  "properties": {
    "iso:country":"ES",
    "sg:address":"Av Baro, 14",
    "sg:city":"Barcelona",
    "sg:orig_category":"Promotores Constructores",
    "sg:phone":"+34 932 10 12 50",
    "sg:postcode":"08024",
    "sg:province":"Barcelona",
    "wof:name":"Sopena Fierro Jose Maria",
    "wof:placetype":"venue"
},
  "geometry": {"coordinates":[2.1615200043,41.4154624939],"type":"Point"}
}