{
  "type": "Feature",
  "properties": {
    "iso:country":"ES",
    "sg:address":"Av. Blasco Iba\u00f1ez, 140",
    "sg:city":"Massanassa",
    "sg:orig_category":"Empresas De Limpieza",
    "sg:phone":"+34 961 25 01 57",
    "sg:postcode":"46470",
    "sg:province":"Valencia",
    "wof:name":"Limpiezas Bon Fer C.b.",
    "wof:placetype":"venue"
},
  "geometry": {"coordinates":[-0.3988130093,39.4143753052],"type":"Point"}
}