{
  "type": "Feature",
  "properties": {
    "addr:full":"Calle de Santiago, 25 Valladolid Valladolid 47001",
    "addr:housenumber":"25",
    "addr:postcode":"47001",
    "addr:street":"Calle De Santiago",
    "iso:country":"ES",
    "sg:address":"Calle de Santiago, 25",
    "sg:city":"Valladolid",
    "sg:orig_category":"Arquitectos",
    "sg:phone":"+34 983 33 86 02",
    "sg:postcode":"47001",
    "sg:province":"Valladolid",
    "wof:name":"Hernandez Rodriguez Francisco",
    "wof:placetype":"venue"
},
  "geometry": {"coordinates":[-4.7290391922,41.6491088867],"type":"Point"}
}