{
  "type": "Feature",
  "properties": {
    "addr:full":"Calle de Campos Crespo, 102 Valencia Valencia 46014",
    "addr:housenumber":"102",
    "addr:postcode":"46014",
    "addr:street":"Calle De Campos Crespo",
    "iso:country":"ES",
    "sg:address":"Calle de Campos Crespo, 102",
    "sg:city":"Valencia",
    "sg:orig_category":"Ortopedia General",
    "sg:phone":"+34 963 78 30 89",
    "sg:postcode":"46014",
    "sg:province":"Valencia",
    "wof:name":"Ortomeca S. L.",
    "wof:placetype":"venue"
},
  "geometry": {"coordinates":[-0.4032998085,39.4505500793],"type":"Point"}
}