{
  "type": "Feature",
  "properties": {
    "addr:full":"Calle de San Juanito, 65 Villanueva Fresno Badajoz 06110",
    "addr:housenumber":"65",
    "addr:postcode":"06110",
    "addr:street":"Calle De San Juanito",
    "iso:country":"ES",
    "sg:address":"Calle de San Juanito, 65",
    "sg:city":"Villanueva Fresno",
    "sg:orig_category":"Tiendas De Grano, Frutas Y Legumbres Secas (al Por Menor)",
    "sg:phone":"+34 924 42 76 44",
    "sg:postcode":"06110",
    "sg:province":"Badajoz",
    "wof:name":"Calvino Garcia Jesus",
    "wof:placetype":"venue"
},
  "geometry": {"coordinates":[-7.1665887833,38.3772735596],"type":"Point"}
}