{
  "type": "Feature",
  "properties": {
    "iso:country":"ES",
    "sg:address":"Calle de Cachurra, 11",
    "sg:city":"Negreira",
    "sg:orig_category":"M\u00c9dicos: Estomatolog\u00cda",
    "sg:phone":"+34 981 88 15 11",
    "sg:postcode":"15830",
    "sg:province":"La Coru\u00f1a",
    "wof:name":"Ramos Balboa Jose Domingo",
    "wof:placetype":"venue"
},
  "geometry": {"coordinates":[-8.736951828,42.9107017517],"type":"Point"}
}