{
  "type": "Feature",
  "properties": {
    "iso:country":"ES",
    "sg:address":"Ctra Avila, 102",
    "sg:city":"Piedrahita",
    "sg:orig_category":"Cerrajer\u00cda, Ferrallista",
    "sg:phone":"+34 920 36 07 31",
    "sg:postcode":"05500",
    "sg:province":"\u00c1vila",
    "wof:name":"Bueno De Castro Nicomedes",
    "wof:placetype":"venue"
},
  "geometry": {"coordinates":[-5.3250088692,40.4635314941],"type":"Point"}
}