{
  "type": "Feature",
  "properties": {
    "addr:full":"Calle de Peris Brell, 34 Valencia Valencia 46022",
    "addr:housenumber":"34",
    "addr:postcode":"46022",
    "addr:street":"Calle De Peris Brell",
    "iso:country":"ES",
    "sg:address":"Calle de Peris Brell, 34",
    "sg:city":"Valencia",
    "sg:orig_category":"Peluqueros: De Se\u00d1oras",
    "sg:phone":"+34 963 30 33 33",
    "sg:postcode":"46022",
    "sg:province":"Valencia",
    "wof:name":"Pascual Guillot Maria Elisa",
    "wof:placetype":"venue"
},
  "geometry": {"coordinates":[-0.3469479978,39.4659881592],"type":"Point"}
}