{
  "type": "Feature",
  "properties": {
    "iso:country":"ES",
    "sg:address":"Avgd Alameda Jaume I, 34",
    "sg:city":"Xativa",
    "sg:orig_category":"Confiter\u00cdas, Chocolater\u00cdas (al Por Menor)",
    "sg:phone":"+34 962 27 16 59",
    "sg:postcode":"46800",
    "sg:province":"Valencia",
    "wof:name":"Pafoalte S.l.",
    "wof:placetype":"venue"
},
  "geometry": {"coordinates":[-0.5237929821,38.9893226624],"type":"Point"}
}