{
  "type": "Feature",
  "properties": {
    "iso:country":"ES",
    "sg:address":"Bittor Sarasketa Kalea, 12",
    "sg:city":"Eibar",
    "sg:orig_category":"Molduras, Junquillos, Listones Y Molduras Perforadas",
    "sg:phone":"+34 943 70 15 54",
    "sg:postcode":"20600",
    "sg:province":"Guip\u00f9zcoa",
    "wof:name":"Palomo Gonzalez Amelia",
    "wof:placetype":"venue"
},
  "geometry": {"coordinates":[-2.4644789696,43.1871681213],"type":"Point"}
}