{
  "type": "Feature",
  "properties": {
    "addr:full":"Avda Pinoso, Km. 0018,0 Yecla Murcia 30510",
    "addr:postcode":"30510",
    "addr:street":"Avda Pinoso Km. 0018,0",
    "iso:country":"ES",
    "sg:address":"Avda Pinoso, Km. 0018,0",
    "sg:city":"Yecla",
    "sg:orig_category":"Tapicer\u00cdas",
    "sg:phone":"+34 968 75 38 88",
    "sg:postcode":"30510",
    "sg:province":"Murcia",
    "sg:website":"www.acomodel.net",
    "wof:name":"Tapizados Acomodel Yecla S.l.",
    "wof:placetype":"venue"
},
  "geometry": {"coordinates":[-1.101714015,38.6076087952],"type":"Point"}
}