{
  "type": "Feature",
  "properties": {
    "addr:full":"Carr Obispo Juan Osta, 18 Oliva Valencia 46780",
    "addr:housenumber":"18",
    "addr:postcode":"46780",
    "addr:street":"Carr Obispo Juan Osta",
    "iso:country":"ES",
    "sg:address":"Carr Obispo Juan Osta, 18",
    "sg:city":"Oliva",
    "sg:orig_category":"Bricolaje, Herramientas (al Por Menor)",
    "sg:phone":"+34 962 85 38 00",
    "sg:postcode":"46780",
    "sg:province":"Valencia",
    "wof:name":"Llido Llorca Berta",
    "wof:placetype":"venue"
},
  "geometry": {"coordinates":[-0.1179220006,38.9189491272],"type":"Point"}
}