{
  "type": "Feature",
  "properties": {
    "addr:full":"Calle de Tomas Ibarra, 26 Tomares Sevilla 41940",
    "addr:housenumber":"26",
    "addr:postcode":"41940",
    "addr:street":"Calle De Tomas Ibarra",
    "iso:country":"ES",
    "sg:address":"Calle de Tomas Ibarra, 26",
    "sg:city":"Tomares",
    "sg:orig_category":"Asesor\u00cda Sobre Comunicaci\u00d3n De Empresas",
    "sg:phone":"+34 954 15 31 65",
    "sg:postcode":"41940",
    "sg:province":"Sevilla",
    "wof:name":"Lopez Gomila Antonio",
    "wof:placetype":"venue"
},
  "geometry": {"coordinates":[-6.0455365181,37.37733078],"type":"Point"}
}