{
  "type": "Feature",
  "properties": {
    "addr:full":"Plaz Cristobal Toral, 3 Antequera M\u00e1laga 29200",
    "addr:housenumber":"3",
    "addr:postcode":"29200",
    "addr:street":"Plaz Cristobal Toral",
    "iso:country":"ES",
    "sg:address":"Plaz Cristobal Toral, 3",
    "sg:city":"Antequera",
    "sg:orig_category":"Peluqueros: De Se\u00d1oras",
    "sg:phone":"+34 952 84 58 35",
    "sg:postcode":"29200",
    "sg:province":"M\u00e1laga",
    "wof:name":"Morente Luque Maria",
    "wof:placetype":"venue"
},
  "geometry": {"coordinates":[-4.5695309639,37.0200119019],"type":"Point"}
}