{
  "type": "Feature",
  "properties": {
    "iso:country":"ES",
    "sg:address":"Las Majas De Goya, 13",
    "sg:city":"Zaragoza",
    "sg:orig_category":"Cajas De Ahorro",
    "sg:phone":"+34 976 10 66 33",
    "sg:postcode":"50018",
    "sg:province":"Zaragoza",
    "wof:name":"Caja De Ahorros De La Inmaculada",
    "wof:placetype":"venue"
},
  "geometry": {"coordinates":[-0.8760730028,41.686630249],"type":"Point"}
}