{
  "type": "Feature",
  "properties": {
    "addr:full":"Calle de Cisneros, 23 Alcorcon Madrid 28921",
    "addr:housenumber":"23",
    "addr:postcode":"28921",
    "addr:street":"Calle De Cisneros",
    "iso:country":"ES",
    "sg:address":"Calle de Cisneros, 23",
    "sg:city":"Alcorcon",
    "sg:orig_category":"Alimentaci\u00d3n General (al Por Menor)",
    "sg:phone":"+34 916 44 00 46",
    "sg:postcode":"28921",
    "sg:province":"Madrid",
    "wof:name":"Zhu  Bixan",
    "wof:placetype":"venue"
},
  "geometry": {"coordinates":[-3.8301389217,40.3465194702],"type":"Point"}
}