{
  "type": "Feature",
  "properties": {
    "addr:full":"Calle de Blas Infante, 38 Brenes Sevilla 41310",
    "addr:housenumber":"38",
    "addr:postcode":"41310",
    "addr:street":"Calle De Blas Infante",
    "iso:country":"ES",
    "sg:address":"Calle de Blas Infante, 38",
    "sg:city":"Brenes",
    "sg:orig_category":"Inform\u00c1tica, Ofim\u00c1tica (estudios, Asesor\u00cda, Ingenier\u00cda, Formaci\u00d3n)",
    "sg:phone":"+34 954 79 73 27",
    "sg:postcode":"41310",
    "sg:province":"Sevilla",
    "wof:name":"Sanchez Moreno Jose David",
    "wof:placetype":"venue"
},
  "geometry": {"coordinates":[-5.8705301285,37.5498695374],"type":"Point"}
}