{
  "type": "Feature",
  "properties": {
    "iso:country":"ES",
    "sg:address":"Carrer de Ecija (d'), 2",
    "sg:city":"Campredo",
    "sg:orig_category":"Asesor\u00cda De Formaci\u00d3n Y Gesti\u00d3n De Personal",
    "sg:phone":"+34 977 59 72 85",
    "sg:postcode":"43897",
    "sg:province":"Tarragona",
    "wof:name":"Mulet Gestio S.l.",
    "wof:placetype":"venue"
},
  "geometry": {"coordinates":[0.5529189706,40.760269165],"type":"Point"}
}