{
  "type": "Feature",
  "properties": {
    "iso:country":"ES",
    "sg:address":"Avda Felipe V, 19",
    "sg:city":"Petrer",
    "sg:orig_category":"Frutas, Legumbres Frescas Y Tempranas (al Por Menor)",
    "sg:phone":"+34 966 95 04 66",
    "sg:postcode":"03610",
    "sg:province":"Alicante",
    "wof:name":"Pellifruit S.l.",
    "wof:placetype":"venue"
},
  "geometry": {"coordinates":[-0.7778519988,38.4817581177],"type":"Point"}
}