{
  "type": "Feature",
  "properties": {
    "addr:full":"Pase Anoeta De, 5 Donostia-san Sebastian Guip\u00f9zcoa 20014",
    "addr:postcode":"20014",
    "iso:country":"ES",
    "sg:address":"Pase Anoeta De, 5",
    "sg:city":"Donostia-san Sebastian",
    "sg:orig_category":"Centros Empresariales",
    "sg:phone":"+34 943 45 09 21",
    "sg:postcode":"20014",
    "sg:province":"Guip\u00f9zcoa",
    "wof:name":"Asociacion De La Prensa Deportiva De Gipuzkoa",
    "wof:placetype":"venue"
},
  "geometry": {"coordinates":[-1.9009970427,43.2548027039],"type":"Point"}
}