{
  "type": "Feature",
  "properties": {
    "iso:country":"ES",
    "sg:address":"Avda Lope De Figueroa, 20",
    "sg:city":"Alcala Henares",
    "sg:orig_category":"Inversiones",
    "sg:phone":"+34 918 82 86 43",
    "sg:postcode":"28804",
    "sg:province":"Madrid",
    "wof:name":"Arte Y Naturaleza Gespart S.l.",
    "wof:placetype":"venue"
},
  "geometry": {"coordinates":[-3.3463904858,40.4894790649],"type":"Point"}
}