{
  "type": "Feature",
  "properties": {
    "addr:full":"Calle de Bomba, 11 Badajoz Badajoz 06004",
    "addr:housenumber":"11",
    "addr:postcode":"06004",
    "addr:street":"Calle De Bomba",
    "iso:country":"ES",
    "sg:address":"Calle de Bomba, 11",
    "sg:city":"Badajoz",
    "sg:orig_category":"M\u00c9dicos: Salud P\u00dablica",
    "sg:phone":"+34 924 23 20 08",
    "sg:postcode":"06004",
    "sg:province":"Badajoz",
    "wof:name":"Mu\u00f1oz Sanchez Gregorio",
    "wof:placetype":"venue"
},
  "geometry": {"coordinates":[-6.9718227386,38.8745689392],"type":"Point"}
}