{
  "type": "Feature",
  "properties": {
    "iso:country":"ES",
    "sg:address":"Calle de Ejido (el), 30",
    "sg:city":"Dos Hermanas",
    "sg:orig_category":"M\u00c9dicos: Estomatolog\u00cda",
    "sg:phone":"+34 955 67 55 97",
    "sg:postcode":"41700",
    "sg:province":"Sevilla",
    "wof:name":"Rosado Rivas Sara Eva",
    "wof:placetype":"venue"
},
  "geometry": {"coordinates":[-5.9209990501,37.2803840637],"type":"Point"}
}