{
  "type": "Feature",
  "properties": {
    "iso:country":"ES",
    "sg:address":"Calle de Federico Ozanan, 12",
    "sg:city":"Zaragoza",
    "sg:orig_category":"Caf\u00c9s, Bares, Cervecer\u00cdas",
    "sg:phone":"+34 976 31 93 45",
    "sg:postcode":"50012",
    "sg:province":"Zaragoza",
    "wof:name":"Cafeteria Codigo 12 S.c",
    "wof:placetype":"venue"
},
  "geometry": {"coordinates":[-0.9314309955,41.6400871277],"type":"Point"}
}