{
  "type": "Feature",
  "properties": {
    "addr:full":"Ctra Beniatjar, Km. 0002,0 Rafol Salem Valencia 46843",
    "addr:postcode":"46843",
    "addr:street":"Ctra Beniatjar Km. 0002,0 Rafol",
    "iso:country":"ES",
    "sg:address":"Ctra Beniatjar, Km. 0002,0",
    "sg:city":"Rafol Salem",
    "sg:orig_category":"Paletas",
    "sg:phone":"+34 962 88 35 56",
    "sg:postcode":"46843",
    "sg:province":"Valencia",
    "wof:name":"Jovipal Palets S.l.",
    "wof:placetype":"venue"
},
  "geometry": {"coordinates":[-0.3961670101,38.8641242981],"type":"Point"}
}