{
  "type": "Feature",
  "properties": {
    "addr:full":"Av Dr. Fleming, De, 7 S. Antoni Portmany Islas Baleares 07820",
    "addr:postcode":"07820",
    "addr:street":"Av Dr. Fleming De 7 S. Antoni Portmany",
    "iso:country":"ES",
    "sg:address":"Av Dr. Fleming, De, 7",
    "sg:city":"S. Antoni Portmany",
    "sg:orig_category":"Art\u00cdculos De Regalo (al Por Menor)",
    "sg:phone":"+34 971 34 01 48",
    "sg:postcode":"07820",
    "sg:province":"Islas Baleares",
    "wof:name":"Ribas Mari Juan",
    "wof:placetype":"venue"
},
  "geometry": {"coordinates":[1.3102099895,38.968296051],"type":"Point"}
}