{
  "type": "Feature",
  "properties": {
    "addr:full":"Av. Las Palmeras, 4 Sta.ursula Santa Cruz De Tenerife 38390",
    "addr:housenumber":"4",
    "addr:postcode":"38390",
    "addr:street":"Av. Las Palmeras",
    "iso:country":"ES",
    "sg:address":"Av. Las Palmeras, 4",
    "sg:city":"Sta.ursula",
    "sg:orig_category":"Fabricaci\u00d3n De Peines Y De Accesorios De Peluquer\u00cda",
    "sg:phone":"+34 922 33 76 30",
    "sg:postcode":"38390",
    "sg:province":"Santa Cruz De Tenerife",
    "wof:name":"Dorxi Canarias S.l.",
    "wof:placetype":"venue"
},
  "geometry": {"coordinates":[-16.4886417389,28.4280052185],"type":"Point"}
}