{
  "type": "Feature",
  "properties": {
    "addr:full":"Avda Camino De Santiago (del), 6 Fontanar Guadalajara 19290",
    "addr:housenumber":"6",
    "addr:postcode":"19290",
    "addr:street":"Avda Camino De Santiago Del",
    "iso:country":"ES",
    "sg:address":"Avda Camino De Santiago (del), 6",
    "sg:city":"Fontanar",
    "sg:orig_category":"Instalaci\u00d3n, Reparaci\u00d3n De Calefacci\u00d3n El\u00c9ctrica",
    "sg:phone":"+34 949 32 90 43",
    "sg:postcode":"19290",
    "sg:province":"Guadalajara",
    "wof:name":"Cano Binder Andres",
    "wof:placetype":"venue"
},
  "geometry": {"coordinates":[-3.1724579334,40.7227516174],"type":"Point"}
}