{
  "type": "Feature",
  "properties": {
    "iso:country":"ES",
    "sg:address":"Calle de Librero Esclapes, 2",
    "sg:city":"Valencia",
    "sg:orig_category":"Asesor\u00cda De Formaci\u00d3n Y Gesti\u00d3n De Personal",
    "sg:phone":"+34 963 66 88 49",
    "sg:postcode":"46019",
    "sg:province":"Valencia",
    "wof:name":"Grupo Inversor Azuay S.l.",
    "wof:placetype":"venue"
},
  "geometry": {"coordinates":[-0.3756470084,39.4973144531],"type":"Point"}
}