{
  "type": "Feature",
  "properties": {
    "iso:country":"ES",
    "sg:address":"Carrer de Lluis Pascual Roca, 19",
    "sg:city":"S. Boi Llobregat",
    "sg:orig_category":"Ropa Para Se\u00d1oras Y Caballeros (al Por Menor)",
    "sg:phone":"+34 936 30 85 79",
    "sg:postcode":"08830",
    "sg:province":"Barcelona",
    "wof:name":"Seven You S.l.",
    "wof:placetype":"venue"
},
  "geometry": {"coordinates":[2.0392830372,41.3435935974],"type":"Point"}
}