{
  "type": "Feature",
  "properties": {
    "addr:full":"Mayor, S/n Cretas Teruel 44623",
    "addr:housenumber":"s",
    "addr:postcode":"44623",
    "addr:street":"Mayor;/ N",
    "iso:country":"ES",
    "sg:address":"Mayor, S/n",
    "sg:city":"Cretas",
    "sg:orig_category":"Alimentaci\u00d3n General (al Por Menor)",
    "sg:phone":"+34 978 85 03 16",
    "sg:postcode":"44623",
    "sg:province":"Teruel",
    "wof:name":"Ba\u00f1olas Ciurana Carmen",
    "wof:placetype":"venue"
},
  "geometry": {"coordinates":[0.2130800039,40.929309845],"type":"Point"}
}