{
  "type": "Feature",
  "properties": {
    "addr:full":"Plaz Andalucia (de), 10 Monturque C\u00f3rdoba 14930",
    "addr:housenumber":"10",
    "addr:postcode":"14930",
    "addr:street":"Plaz Andalucia De",
    "iso:country":"ES",
    "sg:address":"Plaz Andalucia (de), 10",
    "sg:city":"Monturque",
    "sg:orig_category":"Droguer\u00cdas (al Por Menor)",
    "sg:phone":"+34 957 51 80 83",
    "sg:postcode":"14930",
    "sg:province":"C\u00f3rdoba",
    "wof:name":"Multiservicios Monturcal S.l.",
    "wof:placetype":"venue"
},
  "geometry": {"coordinates":[-4.5806589127,37.4718437195],"type":"Point"}
}