{
  "type": "Feature",
  "properties": {
    "iso:country":"ES",
    "sg:address":"Av. Fisterra, 55",
    "sg:city":"Laracha",
    "sg:orig_category":"Mec\u00c1nico Del Autom\u00d3vil",
    "sg:phone":"+34 981 60 65 06",
    "sg:postcode":"15145",
    "sg:province":"La Coru\u00f1a",
    "wof:name":"Frayfe Motor S.l.",
    "wof:placetype":"venue"
},
  "geometry": {"coordinates":[-8.5783786774,43.2472114563],"type":"Point"}
}