{
  "type": "Feature",
  "properties": {
    "iso:country":"ES",
    "sg:address":"Avda Venezuela, 17",
    "sg:city":"Guadalajara",
    "sg:orig_category":"Panader\u00cdas, Panader\u00cdas",
    "sg:phone":"+34 949 21 96 19",
    "sg:postcode":"19005",
    "sg:province":"Guadalajara",
    "wof:name":"Damelura S.l",
    "wof:placetype":"venue"
},
  "geometry": {"coordinates":[-3.1523499489,40.6321372986],"type":"Point"}
}