{
  "type": "Feature",
  "properties": {
    "addr:full":"San Cristobal, 5 Cocentaina Alicante 03820",
    "addr:housenumber":"5",
    "addr:postcode":"03820",
    "addr:street":"San Cristobal",
    "iso:country":"ES",
    "sg:address":"San Cristobal, 5",
    "sg:city":"Cocentaina",
    "sg:orig_category":"Postigos, Persianas Y Celos\u00cdas",
    "sg:phone":"+34 965 59 02 42",
    "sg:postcode":"03820",
    "sg:province":"Alicante",
    "wof:name":"Ramos Cano Antonio",
    "wof:placetype":"venue"
},
  "geometry": {"coordinates":[-0.4395990074,38.7440414429],"type":"Point"}
}