{
  "type": "Feature",
  "properties": {
    "iso:country":"ES",
    "sg:address":"Rond Atocha, 5",
    "sg:city":"Madrid",
    "sg:orig_category":"Cervecer\u00cdas",
    "sg:phone":"+34 915 39 80 37",
    "sg:postcode":"28012",
    "sg:province":"Madrid",
    "wof:name":"Lopez Jimenez Julian",
    "wof:placetype":"venue"
},
  "geometry": {"coordinates":[-3.7041509151,40.4144935608],"type":"Point"}
}