{
  "type": "Feature",
  "properties": {
    "iso:country":"ES",
    "sg:address":"Barr Lugar (el) (mu\u00d1orrodero), S/n",
    "sg:city":"Mu\u00f1orrodero",
    "sg:orig_category":"Semiller\u00cdas",
    "sg:phone":"+34 942 71 80 16",
    "sg:postcode":"39594",
    "sg:province":"Cantabria",
    "wof:name":"Villar Lopez Fernando",
    "wof:placetype":"venue"
},
  "geometry": {"coordinates":[-4.4894452095,43.3901939392],"type":"Point"}
}