{
  "type": "Feature",
  "properties": {
    "iso:country":"ES",
    "sg:address":"Plaz Espa\u00d1a (de), 1",
    "sg:city":"Navalagamella",
    "sg:orig_category":"Administraciones Regionales, Departamentales Y Locales",
    "sg:phone":"+34 918 98 80 08",
    "sg:postcode":"28212",
    "sg:province":"Madrid",
    "wof:name":"Ayuntamiento De Navalagamella",
    "wof:placetype":"venue"
},
  "geometry": {"coordinates":[-4.1206746101,40.4496536255],"type":"Point"}
}