{
  "type": "Feature",
  "properties": {
    "addr:full":"Calle de Sevilla, S/n Palencia Palencia 34004",
    "addr:housenumber":"s",
    "addr:postcode":"34004",
    "addr:street":"Calle De Sevilla;/ N",
    "iso:country":"ES",
    "sg:address":"Calle de Sevilla, S/n",
    "sg:city":"Palencia",
    "sg:orig_category":"Perfumer\u00cda, Art\u00cdculos De Ba\u00d1o (fabricaci\u00d3n, Al Por Mayor)",
    "sg:phone":"+34 979 72 98 00",
    "sg:postcode":"34004",
    "sg:province":"Palencia",
    "wof:name":"Natalio De Fuentes S. A.",
    "wof:placetype":"venue"
},
  "geometry": {"coordinates":[-4.5139288902,41.998249054],"type":"Point"}
}