{
  "type": "Feature",
  "properties": {
    "addr:full":"Calle de Marques De La Valdavia, 5 Madrid Madrid 28012",
    "addr:housenumber":"5",
    "addr:postcode":"28012",
    "addr:street":"Calle De Marques De La Valdavia",
    "iso:country":"ES",
    "sg:address":"Calle de Marques De La Valdavia, 5",
    "sg:city":"Madrid",
    "sg:orig_category":"Peluquer\u00cdas, Peluquer\u00cda Mixta",
    "sg:phone":"+34 915 28 79 81",
    "sg:postcode":"28012",
    "sg:province":"Madrid",
    "sg:website":"www.mundoempresas.com/blondy",
    "wof:name":"Pareja Ortiz Jose Manuel",
    "wof:placetype":"venue"
},
  "geometry": {"coordinates":[-3.6958169937,40.4060745239],"type":"Point"}
}