{
  "type": "Feature",
  "properties": {
    "addr:full":"Calle de Jose Maria Carretero, 5 Montilla C\u00f3rdoba 14550",
    "addr:housenumber":"5",
    "addr:postcode":"14550",
    "addr:street":"Calle De Jose Maria Carretero;Co\u0301Rdoba",
    "iso:country":"ES",
    "sg:address":"Calle de Jose Maria Carretero, 5",
    "sg:city":"Montilla",
    "sg:orig_category":"Ingeniero",
    "sg:phone":"+34 957 65 32 93",
    "sg:postcode":"14550",
    "sg:province":"C\u00f3rdoba",
    "wof:name":"Hidalgo Valls Francisco",
    "wof:placetype":"venue"
},
  "geometry": {"coordinates":[-4.6376562119,37.5882110596],"type":"Point"}
}