{
  "type": "Feature",
  "properties": {
    "iso:country":"ES",
    "sg:address":"Calle de Paredes De Nava, 25",
    "sg:city":"Madrid",
    "sg:orig_category":"Pescader\u00cdas (al Por Menor)",
    "sg:phone":"+34 913 24 19 51",
    "sg:postcode":"28017",
    "sg:province":"Madrid",
    "wof:name":"Santos Rodriguez Valentin",
    "wof:placetype":"venue"
},
  "geometry": {"coordinates":[-3.627161026,40.4201393127],"type":"Point"}
}