{
  "type": "Feature",
  "properties": {
    "iso:country":"ES",
    "sg:address":"Barr Cueto Valdenoja, 44",
    "sg:city":"Cueto",
    "sg:orig_category":"Art\u00cdculos De Decoraci\u00d3n",
    "sg:phone":"+34 942 39 31 32",
    "sg:postcode":"39012",
    "sg:province":"Cantabria",
    "wof:name":"Gomez Saiz Gabriel Audelino",
    "wof:placetype":"venue"
},
  "geometry": {"coordinates":[-3.8604888916,43.4665527344],"type":"Point"}
}