{
  "type": "Feature",
  "properties": {
    "iso:country":"ES",
    "sg:address":"Carrer de Cambrils (de), 16",
    "sg:city":"Salou",
    "sg:orig_category":"Empresas De Carpinter\u00cda De Madera",
    "sg:phone":"+34 977 38 34 22",
    "sg:postcode":"43840",
    "sg:province":"Tarragona",
    "wof:name":"Arina Larraz Jose",
    "wof:placetype":"venue"
},
  "geometry": {"coordinates":[1.1257841587,41.0777587891],"type":"Point"}
}