{
  "type": "Feature",
  "properties": {
    "addr:full":"Calle de 31 De Agosto, 15 Donostia-san Sebastian Guip\u00f9zcoa 20003",
    "addr:housenumber":"31;15",
    "addr:postcode":"20003",
    "addr:street":"Calle De;De Agosto",
    "iso:country":"ES",
    "sg:address":"Calle de 31 De Agosto, 15",
    "sg:city":"Donostia-san Sebastian",
    "sg:orig_category":"Asociaciones Y Clubs Deportivos",
    "sg:phone":"+34 943 42 97 83",
    "sg:postcode":"20003",
    "sg:province":"Guip\u00f9zcoa",
    "wof:name":"Club Amaikak Bat",
    "wof:placetype":"venue"
},
  "geometry": {"coordinates":[-1.9852813482,43.3241195679],"type":"Point"}
}