{
  "type": "Feature",
  "properties": {
    "addr:full":"Plaz Andalucia, 1 Ubeda Ja\u00e9n 23400",
    "addr:housenumber":"1",
    "addr:postcode":"23400",
    "addr:street":"Plaz Andalucia;Jae\u0301N",
    "iso:country":"ES",
    "sg:address":"Plaz Andalucia, 1",
    "sg:city":"Ubeda",
    "sg:orig_category":"Zapatos (al Por Menor)",
    "sg:phone":"+34 953 75 05 94",
    "sg:postcode":"23400",
    "sg:province":"Ja\u00e9n",
    "wof:name":"Fernandez Olivares Miguel",
    "wof:placetype":"venue"
},
  "geometry": {"coordinates":[-3.3766860962,38.0135498047],"type":"Point"}
}