{
  "type": "Feature",
  "properties": {
    "addr:full":"Avgd Vicente Blasco Iba\u00d1ez, 31 Aldaia Valencia 46960",
    "addr:housenumber":"31",
    "addr:postcode":"46960",
    "addr:street":"Vicente;Iban\u0303Ez",
    "iso:country":"ES",
    "sg:address":"Avgd Vicente Blasco Iba\u00d1ez, 31",
    "sg:city":"Aldaia",
    "sg:orig_category":"Financiaci\u00d3n Y Cr\u00c9ditos",
    "sg:phone":"+34 961 51 91 52",
    "sg:postcode":"46960",
    "sg:province":"Valencia",
    "wof:name":"Caixa Popular Cooperativa De Credito Valenciana",
    "wof:placetype":"venue"
},
  "geometry": {"coordinates":[-0.4586380124,39.464427948],"type":"Point"}
}