{
  "type": "Feature",
  "properties": {
    "iso:country":"ES",
    "sg:address":"Calle de Modesto Higueras, 10",
    "sg:city":"Santisteban Puerto",
    "sg:orig_category":"Alimentaci\u00d3n General (al Por Menor)",
    "sg:phone":"+34 953 40 24 68",
    "sg:postcode":"23250",
    "sg:province":"Ja\u00e9n",
    "wof:name":"Morante Salido Francisco",
    "wof:placetype":"venue"
},
  "geometry": {"coordinates":[-3.2016999722,38.2514266968],"type":"Point"}
}