{
  "type": "Feature",
  "properties": {
    "iso:country":"ES",
    "sg:address":"Calle de Principal, 29",
    "sg:city":"Castellar-oliveral",
    "sg:orig_category":"Deportes Y Programas De Aventura",
    "sg:phone":"+34 963 96 20 32",
    "sg:postcode":"46026",
    "sg:province":"Valencia",
    "sg:website":"www.deporteasumedida.com",
    "wof:name":"Deporte A Su Medida S. L.",
    "wof:placetype":"venue"
},
  "geometry": {"coordinates":[-0.3626419902,39.4320335388],"type":"Point"}
}