{
  "type": "Feature",
  "properties": {
    "addr:full":"Calle de Rio Tietar, 47 Madrid Madrid 28023",
    "addr:housenumber":"47",
    "addr:postcode":"madrid;28023",
    "addr:street":"Calle De Rio Tietar",
    "iso:country":"ES",
    "sg:address":"Calle de Rio Tietar, 47",
    "sg:city":"Madrid",
    "sg:orig_category":"Procuradores",
    "sg:phone":"+34 913 07 02 87",
    "sg:postcode":"28023",
    "sg:province":"Madrid",
    "wof:name":"Alonso Carbajo Bego\u00f1a",
    "wof:placetype":"venue"
},
  "geometry": {"coordinates":[-3.7862212658,40.451007843],"type":"Point"}
}