{
  "type": "Feature",
  "properties": {
    "addr:full":"Cra Espinel, 66 Ronda M\u00e1laga 29400",
    "addr:postcode":"29400",
    "addr:street":"Ronda Ma\u0301Laga",
    "iso:country":"ES",
    "sg:address":"Cra Espinel, 66",
    "sg:city":"Ronda",
    "sg:orig_category":"Quincaller\u00cda (al Por Menor)",
    "sg:phone":"+34 952 87 16 85",
    "sg:postcode":"29400",
    "sg:province":"M\u00e1laga",
    "wof:name":"Castillo Mu\u00f1oz Jose",
    "wof:placetype":"venue"
},
  "geometry": {"coordinates":[-5.1630859375,36.7438812256],"type":"Point"}
}