{
  "type": "Feature",
  "properties": {
    "addr:full":"Plaz Constitucion (la), 9 Jaen Ja\u00e9n 23001",
    "addr:housenumber":"9;jae\u0301n",
    "addr:postcode":"23001",
    "addr:street":"Constitucion La",
    "iso:country":"ES",
    "sg:address":"Plaz Constitucion (la), 9",
    "sg:city":"Jaen",
    "sg:orig_category":"Zapater\u00cdas",
    "sg:phone":"+34 953 24 29 20",
    "sg:postcode":"23001",
    "sg:province":"Ja\u00e9n",
    "wof:name":"Esteban Gamez Moreno Y Otro Cdad",
    "wof:placetype":"venue"
},
  "geometry": {"coordinates":[-3.7906870842,37.7650947571],"type":"Point"}
}