{
  "type": "Feature",
  "properties": {
    "iso:country":"ES",
    "sg:address":"Calle de Alfonso Vi, S/n",
    "sg:city":"Sepulveda",
    "sg:orig_category":"Ebanister\u00cda",
    "sg:phone":"+34 921 54 01 36",
    "sg:postcode":"40300",
    "sg:province":"Segovia",
    "wof:name":"Garcia Cristobal Ciriaco",
    "wof:placetype":"venue"
},
  "geometry": {"coordinates":[-3.7485799789,41.2977790833],"type":"Point"}
}