{
  "type": "Feature",
  "properties": {
    "addr:full":"Calle de Nueva, 50 Camarzana Tera Zamora 49332",
    "addr:housenumber":"50",
    "addr:postcode":"49332",
    "addr:street":"Calle De Nueva;Zamora",
    "iso:country":"ES",
    "sg:address":"Calle de Nueva, 50",
    "sg:city":"Camarzana Tera",
    "sg:orig_category":"Librer\u00cdas",
    "sg:phone":"+34 980 64 92 95",
    "sg:postcode":"49332",
    "sg:province":"Zamora",
    "wof:name":"Vega Anta Maria Milagros",
    "wof:placetype":"venue"
},
  "geometry": {"coordinates":[-6.0767960548,41.9845962524],"type":"Point"}
}