{
  "type": "Feature",
  "properties": {
    "addr:full":"Calle de Jesus De Monasterio, 17 Santander Cantabria 39008",
    "addr:housenumber":"17",
    "addr:postcode":"39008",
    "addr:street":"Calle De Jesus De Monasterio",
    "iso:country":"ES",
    "sg:address":"Calle de Jesus De Monasterio, 17",
    "sg:city":"Santander",
    "sg:orig_category":"Bisuter\u00cda, Joyer\u00cda, Relojer\u00cda (al Por Menor)",
    "sg:phone":"+34 942 22 53 26",
    "sg:postcode":"39008",
    "sg:province":"Cantabria",
    "wof:name":"Gonzalez Toca Maria Antonia",
    "wof:placetype":"venue"
},
  "geometry": {"coordinates":[-3.8117790222,43.4618110657],"type":"Point"}
}