{
  "type": "Feature",
  "properties": {
    "addr:full":"Calle de Leon Y Castillo, 231 Palmas De Gran Canaria Las Palmas 35005",
    "addr:housenumber":"231",
    "addr:postcode":"35005",
    "addr:street":"Calle De Leon Y Castillo",
    "iso:country":"ES",
    "sg:address":"Calle de Leon Y Castillo, 231",
    "sg:city":"Palmas De Gran Canaria",
    "sg:orig_category":"Organizaciones Internacionales",
    "sg:phone":"+34 928 29 00 00",
    "sg:postcode":"35005",
    "sg:province":"Las Palmas",
    "wof:name":"Cruz Roja Espa\u00f1ola",
    "wof:placetype":"venue"
},
  "geometry": {"coordinates":[-15.427895546,28.1233863831],"type":"Point"}
}