{
  "type": "Feature",
  "properties": {
    "iso:country":"ES",
    "sg:address":"Plaz Espa\u00d1a (de), 23",
    "sg:city":"Barco De Avila",
    "sg:orig_category":"Alquiler De V\u00cddeo",
    "sg:phone":"+34 920 34 05 55",
    "sg:postcode":"05600",
    "sg:province":"\u00c1vila",
    "wof:name":"Sayans Jimenez Jesus Maria",
    "wof:placetype":"venue"
},
  "geometry": {"coordinates":[-5.5218648911,40.3584060669],"type":"Point"}
}