{
  "type": "Feature",
  "properties": {
    "addr:full":"Calle de Ezcurdia, 192 Gijon Asturias 33203",
    "addr:housenumber":"192",
    "addr:postcode":"33203",
    "addr:street":"Calle De Ezcurdia",
    "iso:country":"ES",
    "sg:address":"Calle de Ezcurdia, 192",
    "sg:city":"Gijon",
    "sg:orig_category":"Agencias Y Agentes Comerciales, Representantes",
    "sg:phone":"+34 985 37 47 13",
    "sg:postcode":"33203",
    "sg:province":"Asturias",
    "wof:name":"Sanchez Diaz Jose",
    "wof:placetype":"venue"
},
  "geometry": {"coordinates":[-5.640255928,43.5344772339],"type":"Point"}
}