{
  "type": "Feature",
  "properties": {
    "addr:full":"Calle de San Miguel, 8 Amorebieta Vizcaya 48340",
    "addr:housenumber":"8",
    "addr:postcode":"48340",
    "addr:street":"Calle De San Miguel",
    "iso:country":"ES",
    "sg:address":"Calle de San Miguel, 8",
    "sg:city":"Amorebieta",
    "sg:orig_category":"Electrodom\u00c9sticos (al Por Menor)",
    "sg:phone":"+34 946 73 00 79",
    "sg:postcode":"48340",
    "sg:province":"Vizcaya",
    "wof:name":"Electrodomesticos Berrio C.b.",
    "wof:placetype":"venue"
},
  "geometry": {"coordinates":[-2.7324669361,43.2197341919],"type":"Point"}
}