{
  "type": "Feature",
  "properties": {
    "iso:country":"ES",
    "sg:address":"Calle de Cabo Santa Pola, 20",
    "sg:city":"Algeciras",
    "sg:classifiers":[
        {
            "category":"Autos & Motor Vehicles",
            "subcategory":"Automobile Sales",
            "type":"Retail Goods"
        }
    ],
    "sg:phone":"+34 956 66 32 71",
    "sg:postcode":"11205",
    "sg:province":"C\u00e1diz",
    "wof:name":"Autoescuela Almoraima 2003 S.l.",
    "wof:placetype":"venue"
},
  "geometry": {"coordinates":[-5.449051857,36.1622161865],"type":"Point"}
}