{
  "type": "Feature",
  "properties": {
    "addr:full":"Calle de Londres, 45 Valdemoro Madrid 28340",
    "addr:housenumber":"45",
    "addr:postcode":"28340",
    "addr:street":"Calle De Londres",
    "iso:country":"ES",
    "sg:address":"Calle de Londres, 45",
    "sg:city":"Valdemoro",
    "sg:orig_category":"Publicidad (soportes Y Gesti\u00d3n)",
    "sg:phone":"+34 918 95 66 40",
    "sg:postcode":"28340",
    "sg:province":"Madrid",
    "wof:name":"Ispac S.l.",
    "wof:placetype":"venue"
},
  "geometry": {"coordinates":[-3.6738090515,40.1909751892],"type":"Point"}
}