{
  "type": "Feature",
  "properties": {
    "iso:country":"ES",
    "sg:address":"Calle de Dionisio Barreda, 5",
    "sg:city":"Cervera Pisuerga",
    "sg:orig_category":"Librer\u00cdas",
    "sg:phone":"+34 979 87 05 79",
    "sg:postcode":"34840",
    "sg:province":"Palencia",
    "wof:name":"Ramos Ramos Maria",
    "wof:placetype":"venue"
},
  "geometry": {"coordinates":[-4.4978766441,42.8617897034],"type":"Point"}
}