{
  "type": "Feature",
  "properties": {
    "addr:full":"Girona, 38 Bellavista Barcelona 08521",
    "addr:housenumber":"38",
    "addr:postcode":"08521",
    "addr:street":"Girona",
    "iso:country":"ES",
    "sg:address":"Girona, 38",
    "sg:city":"Bellavista",
    "sg:orig_category":"Mudanzas",
    "sg:phone":"+34 938 46 65 26",
    "sg:postcode":"08521",
    "sg:province":"Barcelona",
    "wof:name":"Transportes Y Mudanzas Mora S.l.",
    "wof:placetype":"venue"
},
  "geometry": {"coordinates":[2.1700499058,41.3857192993],"type":"Point"}
}