{
  "type": "Feature",
  "properties": {
    "addr:full":"Carrer de Sant Xavier, 31 Vendrell Tarragona 43700",
    "addr:housenumber":"31",
    "addr:postcode":"43700",
    "addr:street":"Carrer De Sant Xavier",
    "iso:country":"ES",
    "sg:address":"Carrer de Sant Xavier, 31",
    "sg:city":"Vendrell",
    "sg:orig_category":"Asesor\u00cda Sobre Comunicaci\u00d3n De Empresas",
    "sg:phone":"+34 977 66 15 34",
    "sg:postcode":"43700",
    "sg:province":"Tarragona",
    "wof:name":"Poch Assessors S.c.p.",
    "wof:placetype":"venue"
},
  "geometry": {"coordinates":[1.5311629772,41.2183380127],"type":"Point"}
}