{
  "type": "Feature",
  "properties": {
    "iso:country":"ES",
    "sg:address":"Calle de Donoso Cortes, 60",
    "sg:city":"Madrid",
    "sg:orig_category":"Moda",
    "sg:phone":"+34 915 43 06 57",
    "sg:postcode":"28015",
    "sg:province":"Madrid",
    "wof:name":"Garvia Alvarez Oscar",
    "wof:placetype":"venue"
},
  "geometry": {"coordinates":[-3.7123270035,40.4363822937],"type":"Point"}
}