{
  "type": "Feature",
  "properties": {
    "addr:full":"Avda La Libertad, 27 San Vicente De Barakaldo Vizcaya 48901",
    "addr:housenumber":"27",
    "addr:postcode":"48901",
    "addr:street":"Avda La Libertad",
    "iso:country":"ES",
    "sg:address":"Avda La Libertad, 27",
    "sg:city":"San Vicente De Barakaldo",
    "sg:orig_category":"Asistencia Social",
    "sg:phone":"+34 944 18 80 33",
    "sg:postcode":"48901",
    "sg:province":"Vizcaya",
    "wof:name":"Organizacion Nacional De Ciegos",
    "wof:placetype":"venue"
},
  "geometry": {"coordinates":[-2.9915111065,43.2974472046],"type":"Point"}
}