{
  "type": "Feature",
  "properties": {
    "addr:full":"Calle de Altozano, 8 Niebla Huelva 21840",
    "addr:housenumber":"8",
    "addr:postcode":"21840",
    "addr:street":"Calle De Altozano",
    "iso:country":"ES",
    "sg:address":"Calle de Altozano, 8",
    "sg:city":"Niebla",
    "sg:orig_category":"Farmacias",
    "sg:phone":"+34 959 36 31 84",
    "sg:postcode":"21840",
    "sg:province":"Huelva",
    "wof:name":"Rite Conejo Maria Del Pilar",
    "wof:placetype":"venue"
},
  "geometry": {"coordinates":[-6.6784405708,37.3599967957],"type":"Point"}
}