{
  "type": "Feature",
  "properties": {
    "addr:full":"Calle de Espiritu Santo, 4 Rambla C\u00f3rdoba 14540",
    "addr:housenumber":"4",
    "addr:postcode":"14540",
    "addr:street":"Calle De Espiritu Santo;Rambla Co\u0301Rdoba",
    "iso:country":"ES",
    "sg:address":"Calle de Espiritu Santo, 4",
    "sg:city":"Rambla",
    "sg:orig_category":"Partidos Pol\u00cdticos",
    "sg:phone":"+34 957 68 21 69",
    "sg:postcode":"14540",
    "sg:province":"C\u00f3rdoba",
    "wof:name":"Partido Comunista De Espa\u00f1a",
    "wof:placetype":"venue"
},
  "geometry": {"coordinates":[-4.7734007835,37.8720436096],"type":"Point"}
}