{
  "type": "Feature",
  "properties": {
    "iso:country":"ES",
    "sg:address":"Los Vientos (galeon), 4",
    "sg:city":"Adeje",
    "sg:orig_category":"Centros Empresariales",
    "sg:phone":"+34 922 78 20 30",
    "sg:postcode":"38670",
    "sg:province":"Santa Cruz De Tenerife",
    "wof:name":"Zizzi  Alfredo",
    "wof:placetype":"venue"
},
  "geometry": {"coordinates":[-16.7116699219,28.1336326599],"type":"Point"}
}