{
  "type": "Feature",
  "properties": {
    "addr:full":"Calle de Siguenza, S/n Azuqueca Henares Guadalajara 19200",
    "addr:housenumber":"s / n",
    "addr:postcode":"19200",
    "addr:street":"Calle De Siguenza",
    "iso:country":"ES",
    "sg:address":"Calle de Siguenza, S/n",
    "sg:city":"Azuqueca Henares",
    "sg:orig_category":"Partidos Pol\u00cdticos",
    "sg:phone":"+34 949 26 54 36",
    "sg:postcode":"19200",
    "sg:province":"Guadalajara",
    "wof:name":"Partido Popular",
    "wof:placetype":"venue"
},
  "geometry": {"coordinates":[-3.2666790485,40.5650482178],"type":"Point"}
}