{
  "type": "Feature",
  "properties": {
    "iso:country":"ES",
    "sg:address":"Albitxuri Industrigunea, 22",
    "sg:city":"Elgoibar",
    "sg:classifiers":[
        {
            "category":"Manufacturing",
            "subcategory":"Metals",
            "type":"Manufacturing & Wholesale Goods"
        }
    ],
    "sg:phone":"+34 943 74 11 12",
    "sg:postcode":"20870",
    "sg:province":"Guip\u00f9zcoa",
    "sg:tags":[
        "en",
        "fundiciones"
    ],
    "wof:name":"Spool Sistemas, S.a.",
    "wof:placetype":"venue"
},
  "geometry": {"coordinates":[-2.4138290882,43.2163581848],"type":"Point"}
}