{
  "type": "Feature",
  "properties": {
    "addr:full":"Pla\u00c7 Fonda, 1 Sueca Valencia 46410",
    "addr:postcode":"46410",
    "iso:country":"ES",
    "sg:address":"Pla\u00c7 Fonda, 1",
    "sg:city":"Sueca",
    "sg:orig_category":"Bancos",
    "sg:phone":"+34 961 70 14 36",
    "sg:postcode":"46410",
    "sg:province":"Valencia",
    "sg:website":"www.bancodevalencia.es",
    "wof:name":"Banco De Valencia S.a.",
    "wof:placetype":"venue"
},
  "geometry": {"coordinates":[-0.3076440096,39.2027435303],"type":"Point"}
}