{
  "type": "Feature",
  "properties": {
    "addr:full":"Calle de Reyes Huertas, 2 Badajoz Badajoz 06008",
    "addr:housenumber":"2",
    "addr:postcode":"06008",
    "addr:street":"Calle De Reyes Huertas",
    "iso:country":"ES",
    "sg:address":"Calle de Reyes Huertas, 2",
    "sg:city":"Badajoz",
    "sg:orig_category":"M\u00c9dicos: An\u00c1lisis Cl\u00cdnicos",
    "sg:phone":"+34 924 23 81 81",
    "sg:postcode":"06008",
    "sg:province":"Badajoz",
    "wof:name":"Urgencias Medicas San Roque S.l.",
    "wof:placetype":"venue"
},
  "geometry": {"coordinates":[-6.9592781067,38.8790473938],"type":"Point"}
}