{
  "type": "Feature",
  "properties": {
    "iso:country":"ES",
    "sg:address":"Ctra. Los Barruecos, S/n",
    "sg:city":"Malpartida Caceres",
    "sg:orig_category":"Ense\u00d1anza, Formaci\u00d3n Profesional: Aprendizaje",
    "sg:phone":"+34 927 27 62 36",
    "sg:postcode":"10910",
    "sg:province":"C\u00e1ceres",
    "wof:name":"Ayuntamiento De Malpartida De Caceres",
    "wof:placetype":"venue"
},
  "geometry": {"coordinates":[-6.3707604408,39.4761772156],"type":"Point"}
}