{
  "type": "Feature",
  "properties": {
    "iso:country":"ES",
    "sg:address":"Carrer de Convent, 67",
    "sg:city":"Sabadell",
    "sg:orig_category":"Venta, Instalaci\u00d3n De Calefacci\u00d3n",
    "sg:phone":"+34 937 26 01 33",
    "sg:postcode":"08202",
    "sg:province":"Barcelona",
    "wof:name":"Trullas Clima S.a.",
    "wof:placetype":"venue"
},
  "geometry": {"coordinates":[2.1079349518,41.5514411926],"type":"Point"}
}