{
  "type": "Feature",
  "properties": {
    "iso:country":"ES",
    "sg:address":"Pase Reina Sofia, Km. 0299,0",
    "sg:city":"Muela",
    "sg:orig_category":"Material Y Suministros Para Fotocopiadoras, Reprograf\u00cda",
    "sg:phone":"+34 976 14 43 84",
    "sg:postcode":"50196",
    "sg:province":"Zaragoza",
    "wof:name":"Virtual Formula 1 S.l.",
    "wof:placetype":"venue"
},
  "geometry": {"coordinates":[-1.115334034,41.5763931274],"type":"Point"}
}