{
  "type": "Feature",
  "properties": {
    "iso:country":"ES",
    "sg:address":"Vega Majadales (pol Postuero), 8",
    "sg:city":"Moraleja",
    "sg:orig_category":"Suministros Para Hoteles",
    "sg:phone":"+34 927 51 54 05",
    "sg:postcode":"10840",
    "sg:province":"C\u00e1ceres",
    "sg:website":"www.comercialnavero.es",
    "wof:name":"Navero Elvira Jose",
    "wof:placetype":"venue"
},
  "geometry": {"coordinates":[-6.6580691338,40.0709648132],"type":"Point"}
}