{
  "type": "Feature",
  "properties": {
    "addr:full":"Avda Extremadura, 12 Corte Peleas Badajoz 06196",
    "addr:housenumber":"12",
    "addr:postcode":"06196",
    "addr:street":"Avda Extremadura;Corte Peleas",
    "iso:country":"ES",
    "sg:address":"Avda Extremadura, 12",
    "sg:city":"Corte Peleas",
    "sg:orig_category":"Cajas Para Embalar",
    "sg:phone":"+34 924 69 33 00",
    "sg:postcode":"06196",
    "sg:province":"Badajoz",
    "wof:name":"Caja Rural De Almendralejo",
    "wof:placetype":"venue"
},
  "geometry": {"coordinates":[-6.6680440903,38.7262535095],"type":"Point"}
}