{
  "type": "Feature",
  "properties": {
    "iso:country":"ES",
    "sg:address":"Plaz Clara Campoamor, 7",
    "sg:city":"Granada",
    "sg:orig_category":"Abogados",
    "sg:phone":"+34 958 13 71 94",
    "sg:postcode":"18008",
    "sg:province":"Granada",
    "wof:name":"Motos Galera Jose Manuel",
    "wof:placetype":"venue"
},
  "geometry": {"coordinates":[-3.5888888836,37.1556015015],"type":"Point"}
}