{
  "type": "Feature",
  "properties": {
    "iso:country":"ES",
    "sg:address":"Gta Juan De Austria, 3",
    "sg:city":"Puerto De Santa Maria",
    "sg:orig_category":"Servicio De Salud",
    "sg:phone":"+34 956 54 23 00",
    "sg:postcode":"11500",
    "sg:province":"C\u00e1diz",
    "wof:name":"Saneamientos Y Ferreteria Gocasa S.l.",
    "wof:placetype":"venue"
},
  "geometry": {"coordinates":[-6.2317991257,36.6030082703],"type":"Point"}
}