{
  "type": "Feature",
  "properties": {
    "addr:full":"Urb Sauces (los), 4 Algeciras C\u00e1diz 11202",
    "addr:housenumber":"4;ca\u0301diz",
    "addr:postcode":"11202",
    "addr:street":"Urb;Los",
    "iso:country":"ES",
    "sg:address":"Urb Sauces (los), 4",
    "sg:city":"Algeciras",
    "sg:orig_category":"Cl\u00cdnicas M\u00c9dicas",
    "sg:phone":"+34 956 66 80 14",
    "sg:postcode":"11202",
    "sg:province":"C\u00e1diz",
    "wof:name":"Deux Clinica Medica S.l.",
    "wof:placetype":"venue"
},
  "geometry": {"coordinates":[-5.4556879997,36.1356277466],"type":"Point"}
}