{
  "type": "Feature",
  "properties": {
    "iso:country":"ES",
    "sg:address":"Avda Santa Clara, 16",
    "sg:city":"Santiago",
    "sg:orig_category":"Mec\u00c1nico Del Autom\u00d3vil",
    "sg:phone":"+34 968 46 66 15",
    "sg:postcode":"30800",
    "sg:province":"Murcia",
    "wof:name":"Olcina Fernandez Francisco Luis",
    "wof:placetype":"venue"
},
  "geometry": {"coordinates":[-1.6905640364,37.680557251],"type":"Point"}
}