{
  "type": "Feature",
  "properties": {
    "addr:full":"Calle de Antonio De La Barrera, 5 Priego Cordoba C\u00f3rdoba 14800",
    "addr:housenumber":"5",
    "addr:postcode":"14800",
    "addr:street":"Calle De Antonio De La Barrera;Cordoba Co\u0301Rdoba",
    "iso:country":"ES",
    "sg:address":"Calle de Antonio De La Barrera, 5",
    "sg:city":"Priego Cordoba",
    "sg:orig_category":"Droguer\u00cdas (al Por Menor)",
    "sg:phone":"+34 957 54 01 94",
    "sg:postcode":"14800",
    "sg:province":"C\u00f3rdoba",
    "wof:name":"Morales Cazorla Rafael Pedro",
    "wof:placetype":"venue"
},
  "geometry": {"coordinates":[-4.1958050728,37.4379844666],"type":"Point"}
}