{
  "type": "Feature",
  "properties": {
    "iso:country":"ES",
    "sg:address":"Monaco, 35",
    "sg:city":"Las Rozas",
    "sg:orig_category":"Pintura Y Barniz (al Por Menor)",
    "sg:phone":"+34 916 37 35 11",
    "sg:postcode":"28232",
    "sg:province":"Madrid",
    "wof:name":"Selhogar Comfort S.l.u.",
    "wof:placetype":"venue"
},
  "geometry": {"coordinates":[-3.8927640915,40.5045318604],"type":"Point"}
}