{
  "type": "Feature",
  "properties": {
    "iso:country":"ES",
    "sg:address":"C/ Moli D'en Negre, 19",
    "sg:city":"Porreres",
    "sg:orig_category":"Mec\u00c1nico Del Autom\u00d3vil",
    "sg:phone":"+34 971 64 75 09",
    "sg:postcode":"07260",
    "sg:province":"Islas Baleares",
    "wof:name":"R.gabriel Y Bernardo Castell C.b",
    "wof:placetype":"venue"
},
  "geometry": {"coordinates":[3.0200550556,39.5119171143],"type":"Point"}
}