{
  "type": "Feature",
  "properties": {
    "iso:country":"ES",
    "sg:address":"Avda General Sanjurjo, 24",
    "sg:city":"Coru\u00d1a",
    "sg:orig_category":"Perfumer\u00cda (al Por Menor)",
    "sg:phone":"+34 981 29 40 18",
    "sg:postcode":"15006",
    "sg:province":"La Coru\u00f1a",
    "wof:name":"Citifin S.a.",
    "wof:placetype":"venue"
},
  "geometry": {"coordinates":[-8.4027442932,43.3560676575],"type":"Point"}
}