{
  "type": "Feature",
  "properties": {
    "addr:full":"Carr Major, 1 Mercadal Islas Baleares 07740",
    "addr:housenumber":"1",
    "addr:postcode":"07740",
    "addr:street":"Carr Major",
    "iso:country":"ES",
    "sg:address":"Carr Major, 1",
    "sg:city":"Mercadal",
    "sg:orig_category":"Panader\u00cdas, Panader\u00cdas",
    "sg:phone":"+34 971 37 50 93",
    "sg:postcode":"07740",
    "sg:province":"Islas Baleares",
    "wof:name":"Segui Llull Lucia",
    "wof:placetype":"venue"
},
  "geometry": {"coordinates":[4.1529397964,40.00730896],"type":"Point"}
}