{
  "type": "Feature",
  "properties": {
    "addr:full":"Calle de Conde De Pe\u00d1alver, 90 Madrid Madrid 28006",
    "addr:housenumber":"90",
    "addr:postcode":"madrid;28006",
    "addr:street":"Calle De Conde De Pen\u0303Alver",
    "iso:country":"ES",
    "sg:address":"Calle de Conde De Pe\u00d1alver, 90",
    "sg:city":"Madrid",
    "sg:orig_category":"Caf\u00c9s, Bares, Cervecer\u00cdas",
    "sg:phone":"+34 914 02 10 41",
    "sg:postcode":"28006",
    "sg:province":"Madrid",
    "wof:name":"Rodriguez Mendez Jesus",
    "wof:placetype":"venue"
},
  "geometry": {"coordinates":[-3.6749789715,40.4337234497],"type":"Point"}
}