{
  "type": "Feature",
  "properties": {
    "addr:full":"Avda Bulevar De El Ejido, 342 Ejido Almer\u00eda 04700",
    "addr:postcode":"04700",
    "addr:street":"Bulevar De El Ejido 342 Ejido Almeri\u0301A",
    "iso:country":"ES",
    "sg:address":"Avda Bulevar De El Ejido, 342",
    "sg:city":"Ejido",
    "sg:orig_category":"Centros P\u00dablicos De Formaci\u00d3n Profesional Y T\u00c9cnica",
    "sg:phone":"+34 950 57 13 08",
    "sg:postcode":"04700",
    "sg:province":"Almer\u00eda",
    "wof:name":"Colegio Provincial De Abogados De Almeria",
    "wof:placetype":"venue"
},
  "geometry": {"coordinates":[-2.8058309555,36.7609977722],"type":"Point"}
}