{
  "type": "Feature",
  "properties": {
    "addr:full":"Calle de Alfareria, 108 Sevilla Sevilla 41010",
    "addr:housenumber":"108",
    "addr:postcode":"41010",
    "addr:street":"Calle De Alfareria",
    "iso:country":"ES",
    "sg:address":"Calle de Alfareria, 108",
    "sg:city":"Sevilla",
    "sg:orig_category":"Carnicer\u00cdas, Carnicer\u00cdas",
    "sg:phone":"+34 954 33 17 49",
    "sg:postcode":"41010",
    "sg:province":"Sevilla",
    "wof:name":"Ca\u00f1avate Sastre Bienvenido",
    "wof:placetype":"venue"
},
  "geometry": {"coordinates":[-6.0074858665,37.3878250122],"type":"Point"}
}