{
  "type": "Feature",
  "properties": {
    "iso:country":"ES",
    "sg:address":"C/ Bosch, 2",
    "sg:city":"Manacor",
    "sg:orig_category":"Lanas (al Por Mayor)",
    "sg:phone":"+34 971 55 47 01",
    "sg:postcode":"07500",
    "sg:province":"Islas Baleares",
    "wof:name":"Riera Nadal Antonia",
    "wof:placetype":"venue"
},
  "geometry": {"coordinates":[3.2098228931,39.568939209],"type":"Point"}
}