{
  "type": "Feature",
  "properties": {
    "addr:full":"Calle de Isidoro Salas, 58 Santo Domingo De La Calzada La Rioja 26250",
    "addr:housenumber":"58",
    "addr:postcode":"26250",
    "addr:street":"Calle De Isidoro Salas;Rioja",
    "iso:country":"ES",
    "sg:address":"Calle de Isidoro Salas, 58",
    "sg:city":"Santo Domingo De La Calzada",
    "sg:orig_category":"Carnicer\u00cdas, Carnicer\u00cdas",
    "sg:phone":"+34 941 34 14 52",
    "sg:postcode":"26250",
    "sg:province":"La Rioja",
    "wof:name":"Arenas Martinez Maria Angeles",
    "wof:placetype":"venue"
},
  "geometry": {"coordinates":[-2.9546642303,42.4404373169],"type":"Point"}
}