{
  "type": "Feature",
  "properties": {
    "addr:full":"Calle de Sinceridad, 47 Sevilla Sevilla 41006",
    "addr:housenumber":"47",
    "addr:postcode":"41006",
    "addr:street":"Calle De Sinceridad",
    "iso:country":"ES",
    "sg:address":"Calle de Sinceridad, 47",
    "sg:city":"Sevilla",
    "sg:orig_category":"Cajas De Ahorro",
    "sg:phone":"+34 954 99 96 23",
    "sg:postcode":"41006",
    "sg:province":"Sevilla",
    "wof:name":"Caja Rural Del Sur Sociedad Cooperativa",
    "wof:placetype":"venue"
},
  "geometry": {"coordinates":[-5.9297327995,37.3713798523],"type":"Point"}
}