{
  "type": "Feature",
  "properties": {
    "addr:full":"Avda Hermanos Bou, 173 Castellon Castell\u00f3n 12003",
    "addr:housenumber":"173",
    "addr:postcode":"12003",
    "addr:street":"Avda Hermanos Bou;Castello\u0301N",
    "iso:country":"ES",
    "sg:address":"Avda Hermanos Bou, 173",
    "sg:city":"Castellon",
    "sg:orig_category":"Centros Empresariales",
    "sg:phone":"+34 964 26 03 51",
    "sg:postcode":"12003",
    "sg:province":"Castell\u00f3n",
    "wof:name":"Lavados Nicol S.l.",
    "wof:placetype":"venue"
},
  "geometry": {"coordinates":[-0.0157321002,39.9790267944],"type":"Point"}
}