{
  "type": "Feature",
  "properties": {
    "addr:full":"Calle de Miguel De Cervantes, 8 Teruel Teruel 44002",
    "addr:housenumber":"8",
    "addr:postcode":"44002",
    "addr:street":"Calle De Miguel De Cervantes",
    "iso:country":"ES",
    "sg:address":"Calle de Miguel De Cervantes, 8",
    "sg:city":"Teruel",
    "sg:classifiers":[
        {
            "category":"Taxi",
            "type":"Transportation"
        }
    ],
    "sg:phone":"+34 978 60 56 49",
    "sg:postcode":"44002",
    "sg:province":"Teruel",
    "wof:name":"Sanz Alaman Juan",
    "wof:placetype":"venue"
},
  "geometry": {"coordinates":[-1.1031299829,40.3327102661],"type":"Point"}
}