{
  "type": "Feature",
  "properties": {
    "addr:full":"Calle de Montesa, 4 Ciudad Real Ciudad Real 13001",
    "addr:housenumber":"4",
    "addr:postcode":"13001",
    "addr:street":"Calle De Montesa",
    "iso:country":"ES",
    "sg:address":"Calle de Montesa, 4",
    "sg:city":"Ciudad Real",
    "sg:orig_category":"Trajes Y Adornos De Boda (confecci\u00d3n, Al Por Menor)",
    "sg:phone":"+34 926 23 06 87",
    "sg:postcode":"13001",
    "sg:province":"Ciudad Real",
    "wof:name":"Azahar Novias Cdad",
    "wof:placetype":"venue"
},
  "geometry": {"coordinates":[-3.9281401634,38.9830513],"type":"Point"}
}