{
  "type": "Feature",
  "properties": {
    "iso:country":"ES",
    "sg:address":"Calle de Oberon, 16",
    "sg:city":"Madrid",
    "sg:orig_category":"Arquitectos",
    "sg:phone":"+34 913 71 04 06",
    "sg:postcode":"28030",
    "sg:province":"Madrid",
    "wof:name":"Fernandez-tresguerres Hernandez Gil Jose Maria",
    "wof:placetype":"venue"
},
  "geometry": {"coordinates":[-3.6353740692,40.4048118591],"type":"Point"}
}