{
  "type": "Feature",
  "properties": {
    "iso:country":"ES",
    "sg:address":"Calle de Gibraleon, 37",
    "sg:city":"Ayamonte",
    "sg:orig_category":"Pescader\u00cdas (al Por Menor)",
    "sg:phone":"+34 959 32 13 25",
    "sg:postcode":"21400",
    "sg:province":"Huelva",
    "wof:name":"Distribuciones Ayapesca S.a.",
    "wof:placetype":"venue"
},
  "geometry": {"coordinates":[-7.4045710564,37.2044296265],"type":"Point"}
}