{
  "type": "Feature",
  "properties": {
    "iso:country":"ES",
    "sg:address":"Calle de Volta, 3",
    "sg:city":"Getafe",
    "sg:orig_category":"Construcciones Met\u00c1licas",
    "sg:phone":"+34 916 82 53 63",
    "sg:postcode":"28906",
    "sg:province":"Madrid",
    "wof:name":"Steel Beton Espa\u00f1ola S.a.",
    "wof:placetype":"venue"
},
  "geometry": {"coordinates":[-3.6955347061,40.2996864319],"type":"Point"}
}