{
  "type": "Feature",
  "properties": {
    "iso:country":"ES",
    "sg:address":"Avda Coru\u00d1a (da), 338",
    "sg:city":"Lugo",
    "sg:orig_category":"Agencias Y Agentes Comerciales, Representantes",
    "sg:phone":"+34 982 21 29 17",
    "sg:postcode":"27003",
    "sg:province":"Lugo",
    "wof:name":"Bouza Neira Manuel",
    "wof:placetype":"venue"
},
  "geometry": {"coordinates":[-7.5675821304,43.0262832642],"type":"Point"}
}