{
  "type": "Feature",
  "properties": {
    "iso:country":"ES",
    "sg:address":"Castro, S/n",
    "sg:city":"Castro",
    "sg:orig_category":"Molduras, Junquillos, Listones Y Molduras Perforadas",
    "sg:phone":"+34 981 73 31 09",
    "sg:postcode":"15147",
    "sg:province":"A Coru\u00f1a",
    "wof:name":"Zas Garcia Alcira",
    "wof:placetype":"venue"
},
  "geometry": {"coordinates":[-8.2707662582,43.3364830017],"type":"Point"}
}