{
  "type": "Feature",
  "properties": {
    "addr:full":"Calle de Turia, S/n Villarrubia C\u00f3rdoba 14710",
    "addr:postcode":"14710",
    "addr:street":"Calle De Turia S / N Villarrubia Co\u0301Rdoba",
    "iso:country":"ES",
    "sg:address":"Calle de Turia, S/n",
    "sg:city":"Villarrubia",
    "sg:orig_category":"Ense\u00d1anza, Formaci\u00d3n Profesional: Aprendizaje",
    "sg:phone":"+34 957 32 76 69",
    "sg:postcode":"14710",
    "sg:province":"C\u00f3rdoba",
    "wof:name":"Junta De Andalucia",
    "wof:placetype":"venue"
},
  "geometry": {"coordinates":[-4.9146289825,37.8490753174],"type":"Point"}
}