{
  "type": "Feature",
  "properties": {
    "addr:full":"Calle de Cronista Rocafort, 31 Castellon Castell\u00f3n 12004",
    "addr:housenumber":"31",
    "addr:postcode":"12004",
    "addr:street":"Calle De Cronista Rocafort",
    "iso:country":"ES",
    "sg:address":"Calle de Cronista Rocafort, 31",
    "sg:city":"Castellon",
    "sg:orig_category":"Ingeniero",
    "sg:phone":"+34 964 24 14 80",
    "sg:postcode":"12004",
    "sg:province":"Castell\u00f3n",
    "wof:name":"Cortes Rivero Eduardo Emilio",
    "wof:placetype":"venue"
},
  "geometry": {"coordinates":[-0.0419050008,39.992767334],"type":"Point"}
}