{
  "type": "Feature",
  "properties": {
    "iso:country":"ES",
    "sg:address":"Avda Ebro, 44",
    "sg:city":"Agoncillo",
    "sg:orig_category":"Construcci\u00d3n Mec\u00c1nica",
    "sg:phone":"+34 941 43 12 32",
    "sg:postcode":"26509",
    "sg:province":"La Rioja",
    "wof:name":"Esna Maquinaria Industrial S. A.",
    "wof:placetype":"venue"
},
  "geometry": {"coordinates":[-2.1222639084,42.4031410217],"type":"Point"}
}