{
  "type": "Feature",
  "properties": {
    "iso:country":"ES",
    "sg:address":"Calle de Real, 50",
    "sg:city":"Larouco",
    "sg:orig_category":"Periodistas Profesionales",
    "sg:phone":"+34 988 32 84 64",
    "sg:postcode":"32358",
    "sg:province":"Ourense",
    "wof:name":"Fernandez Vega Dolores",
    "wof:placetype":"venue"
},
  "geometry": {"coordinates":[-7.1599388123,42.3459281921],"type":"Point"}
}