{
  "type": "Feature",
  "properties": {
    "addr:full":"Avda Ca\u00d1ada (de La), 3 Coslada Madrid 28820",
    "addr:housenumber":"3",
    "addr:postcode":"28820",
    "addr:street":"Avda Can\u0303Ada De La",
    "iso:country":"ES",
    "sg:address":"Avda Ca\u00d1ada (de La), 3",
    "sg:city":"Coslada",
    "sg:orig_category":"Art\u00cdculos De Decoraci\u00d3n",
    "sg:phone":"+34 916 71 10 28",
    "sg:postcode":"28820",
    "sg:province":"Madrid",
    "wof:name":"Rodriguez San Juan Pascual",
    "wof:placetype":"venue"
},
  "geometry": {"coordinates":[-3.5373311043,40.4257202148],"type":"Point"}
}