{
  "type": "Feature",
  "properties": {
    "addr:full":"Carrer de Sant Ildefons, 39 Barcelona Barcelona 08030",
    "addr:housenumber":"39",
    "addr:postcode":"08030",
    "addr:street":"Carrer De Sant Ildefons",
    "iso:country":"ES",
    "sg:address":"Carrer de Sant Ildefons, 39",
    "sg:city":"Barcelona",
    "sg:orig_category":"Empresas De Carpinter\u00cda",
    "sg:phone":"+34 932 74 48 24",
    "sg:postcode":"08030",
    "sg:province":"Barcelona",
    "wof:name":"Blazort Aluminis S.l.",
    "wof:placetype":"venue"
},
  "geometry": {"coordinates":[2.1894240379,41.4286270142],"type":"Point"}
}