{
  "type": "Feature",
  "properties": {
    "addr:full":"Calle de Angel Del Castillo, 21 Coru\u00d1a La Coru\u00f1a 15007",
    "addr:housenumber":"21",
    "addr:postcode":"15007",
    "addr:street":"Calle De Angel Del Castillo;La Corun\u0303A",
    "iso:country":"ES",
    "sg:address":"Calle de Angel Del Castillo, 21",
    "sg:city":"Coru\u00d1a",
    "sg:orig_category":"Agencias Y Agentes Comerciales, Representantes",
    "sg:phone":"+34 981 15 35 77",
    "sg:postcode":"15007",
    "sg:province":"La Coru\u00f1a",
    "wof:name":"Representaciones Juan Garcia S.l.",
    "wof:placetype":"venue"
},
  "geometry": {"coordinates":[-8.4087438583,43.353843689],"type":"Point"}
}