{
  "type": "Feature",
  "properties": {
    "iso:country":"ES",
    "sg:address":"Avda Galicia, Km. 0390,0",
    "sg:city":"Fuentes Nuevas",
    "sg:orig_category":"Maquinaria Para Industrias Diversas",
    "sg:phone":"+34 987 45 53 65",
    "sg:postcode":"24411",
    "sg:province":"Le\u00f3n",
    "wof:name":"Tecnicas Mecanicas Del Bierzo S.l.",
    "wof:placetype":"venue"
},
  "geometry": {"coordinates":[-6.6439290047,42.5685310364],"type":"Point"}
}