{
  "type": "Feature",
  "properties": {
    "addr:full":"Avda Ourense (de), 23 Chantada Lugo 27500",
    "addr:housenumber":"23",
    "addr:postcode":"27500",
    "addr:street":"Avda Ourense De",
    "iso:country":"ES",
    "sg:address":"Avda Ourense (de), 23",
    "sg:city":"Chantada",
    "sg:classifiers":[
        {
            "category":"Communications",
            "type":"Services"
        }
    ],
    "sg:phone":"+34 982 44 18 24",
    "sg:postcode":"27500",
    "sg:province":"Lugo",
    "sg:tags":[
        "televisiones",
        "y",
        "radio"
    ],
    "wof:name":"Radio Lugo",
    "wof:placetype":"venue"
},
  "geometry": {"coordinates":[-7.7724709511,42.6081008911],"type":"Point"}
}