{
  "type": "Feature",
  "properties": {
    "addr:full":"Calle de Abastos (de), 201 Aranjuez Madrid 28300",
    "addr:housenumber":"201",
    "addr:postcode":"28300",
    "addr:street":"Calle De",
    "iso:country":"ES",
    "sg:address":"Calle de Abastos (de), 201",
    "sg:city":"Aranjuez",
    "sg:orig_category":"Fabricaci\u00d3n De Juegos Y Juguetes",
    "sg:phone":"+34 918 92 36 21",
    "sg:postcode":"28300",
    "sg:province":"Madrid",
    "wof:name":"Pe\u00f1a Perez Angel",
    "wof:placetype":"venue"
},
  "geometry": {"coordinates":[-3.5926876068,40.0300865173],"type":"Point"}
}