{
  "type": "Feature",
  "properties": {
    "iso:country":"ES",
    "sg:address":"A Pena, S/n",
    "sg:city":"Pena",
    "sg:orig_category":"Art\u00cdculos De Decoraci\u00d3n",
    "sg:phone":"+34 981 79 72 28",
    "sg:postcode":"15314",
    "sg:province":"A Coru\u00f1a",
    "wof:name":"Vazquez Mahia Daniel",
    "wof:placetype":"venue"
},
  "geometry": {"coordinates":[-8.1744441986,43.2855148315],"type":"Point"}
}