{
  "type": "Feature",
  "properties": {
    "iso:country":"ES",
    "sg:address":"Ctra General, Sn00",
    "sg:city":"Quiros",
    "sg:orig_category":"Cajas De Ahorro",
    "sg:phone":"+34 985 76 81 16",
    "sg:postcode":"33117",
    "sg:province":"Asturias",
    "sg:website":"www.cajastur.es",
    "wof:name":"Caja De Ahorros De Asturias",
    "wof:placetype":"venue"
},
  "geometry": {"coordinates":[-5.9834308624,43.1733856201],"type":"Point"}
}