{
  "type": "Feature",
  "properties": {
    "iso:country":"ES",
    "sg:address":"Calle de Miguel Hernandez, 2",
    "sg:city":"Alameda",
    "sg:orig_category":"Molduras, Junquillos, Listones Y Molduras Perforadas",
    "sg:phone":"+34 952 71 10 58",
    "sg:postcode":"29530",
    "sg:province":"M\u00e1laga",
    "wof:name":"Climatizaciones Leiva S.l.",
    "wof:placetype":"venue"
},
  "geometry": {"coordinates":[-4.6554508209,37.2080345154],"type":"Point"}
}