{
  "type": "Feature",
  "properties": {
    "iso:country":"ES",
    "sg:address":"Carrer de Jacquard, 12",
    "sg:city":"Sabadell",
    "sg:orig_category":"Calderer\u00cda",
    "sg:phone":"+34 937 25 83 85",
    "sg:postcode":"08205",
    "sg:province":"Barcelona",
    "wof:name":"Guillem Serveis Metalurgics S.l.",
    "wof:placetype":"venue"
},
  "geometry": {"coordinates":[2.0984809399,41.5433044434],"type":"Point"}
}