{
  "type": "Feature",
  "properties": {
    "iso:country":"ES",
    "sg:address":"Mcdo. Algiros, S/n",
    "sg:city":"Valencia",
    "sg:orig_category":"Poller\u00cda Y Caza (al Por Menor)",
    "sg:phone":"+34 963 60 03 81",
    "sg:postcode":"46021",
    "sg:province":"Valencia",
    "wof:name":"V.r.and B. 99 S.l.",
    "wof:placetype":"venue"
},
  "geometry": {"coordinates":[-0.3536548018,39.4729652405],"type":"Point"}
}