{
  "type": "Feature",
  "properties": {
    "addr:full":"Avda Leganes, 6 Alcorcon Madrid 28921",
    "addr:housenumber":"6",
    "addr:postcode":"28921",
    "addr:street":"Avda Leganes",
    "iso:country":"ES",
    "sg:address":"Avda Leganes, 6",
    "sg:city":"Alcorcon",
    "sg:orig_category":"Psic\u00d3logos",
    "sg:phone":"+34 916 19 66 27",
    "sg:postcode":"28921",
    "sg:province":"Madrid",
    "wof:name":"Dauden Olavide Cristina",
    "wof:placetype":"venue"
},
  "geometry": {"coordinates":[-3.8243319988,40.3512878418],"type":"Point"}
}