{
  "type": "Feature",
  "properties": {
    "addr:full":"Cra Capuchinos, 68 Malaga M\u00e1laga 29014",
    "addr:housenumber":"68",
    "addr:postcode":"29014",
    "addr:street":"Capuchinos;Ma\u0301Laga",
    "iso:country":"ES",
    "sg:address":"Cra Capuchinos, 68",
    "sg:city":"Malaga",
    "sg:orig_category":"Bancos",
    "sg:phone":"+34 952 26 15 71",
    "sg:postcode":"29014",
    "sg:province":"M\u00e1laga",
    "sg:website":"www.banesto.es",
    "wof:name":"Banco Espa\u00f1ol De Credito S.a.",
    "wof:placetype":"venue"
},
  "geometry": {"coordinates":[-4.423210144,36.765007019],"type":"Point"}
}