{
  "type": "Feature",
  "properties": {
    "iso:country":"ES",
    "sg:address":"Agirre Auzunea, 6",
    "sg:city":"Azpeitia",
    "sg:orig_category":"Consultor\u00cdas Diversas",
    "sg:phone":"+34 943 15 00 19",
    "sg:postcode":"20730",
    "sg:province":"Guip\u00f9zcoa",
    "wof:name":"Laboratorios Izadi S.l.",
    "wof:placetype":"venue"
},
  "geometry": {"coordinates":[-2.2644650936,43.180519104],"type":"Point"}
}