{
  "type": "Feature",
  "properties": {
    "addr:full":"Calle de Victoria Balfe, 7 Burgos Burgos 09006",
    "addr:housenumber":"7",
    "addr:postcode":"09006",
    "addr:street":"Calle De Victoria Balfe",
    "iso:country":"ES",
    "sg:address":"Calle de Victoria Balfe, 7",
    "sg:city":"Burgos",
    "sg:classifiers":[
        {
            "category":"Banks & Credit Unions",
            "subcategory":"Bureau De Change",
            "type":"Services"
        }
    ],
    "sg:phone":"+34 947 21 28 03",
    "sg:postcode":"09006",
    "sg:province":"Burgos",
    "sg:tags":[
        "organismos",
        "control"
    ],
    "wof:name":"Arnaiz Gestion S.l.",
    "wof:placetype":"venue"
},
  "geometry": {"coordinates":[-3.6790893078,42.3613433838],"type":"Point"}
}