{
  "type": "Feature",
  "properties": {
    "iso:country":"ES",
    "sg:address":"Carr Castellar, 3",
    "sg:city":"Oliva",
    "sg:orig_category":"Cer\u00c1micas: Material Y Suministros",
    "sg:phone":"+34 962 85 06 41",
    "sg:postcode":"46780",
    "sg:province":"Valencia",
    "sg:website":"www.gresoliva.com",
    "wof:name":"Morell Ortiz Elena",
    "wof:placetype":"venue"
},
  "geometry": {"coordinates":[-0.1137100011,38.9141197205],"type":"Point"}
}