{
  "type": "Feature",
  "properties": {
    "iso:country":"ES",
    "sg:address":"Pase Rollo, 27",
    "sg:city":"Salamanca",
    "sg:orig_category":"Bisuter\u00cda, Joyer\u00cda, Relojer\u00cda (al Por Menor)",
    "sg:phone":"+34 923 28 23 03",
    "sg:postcode":"37003",
    "sg:province":"Salamanca",
    "wof:name":"Lindo S.l.",
    "wof:placetype":"venue"
},
  "geometry": {"coordinates":[-5.6522679329,40.9657821655],"type":"Point"}
}