{
  "type": "Feature",
  "properties": {
    "addr:full":"Sect O, 10 Torre De La Higuera O Matalasca\u00e7as Huelva 21760",
    "addr:housenumber":"10",
    "addr:postcode":"21760",
    "addr:street":"Sect O",
    "iso:country":"ES",
    "sg:address":"Sect O, 10",
    "sg:city":"Torre De La Higuera O Matalasca\u00e7as",
    "sg:orig_category":"Agencias De Trabajo Temporal",
    "sg:phone":"+34 959 44 07 52",
    "sg:postcode":"21760",
    "sg:province":"Huelva",
    "wof:name":"Comunidad De Propietarios Urbanizacion Torre Do\u00f1ana",
    "wof:placetype":"venue"
},
  "geometry": {"coordinates":[-6.9495940208,37.256313324],"type":"Point"}
}