{
  "type": "Feature",
  "properties": {
    "iso:country":"ES",
    "sg:address":"Carr Onyar, 8",
    "sg:city":"Girona",
    "sg:orig_category":"Carb\u00d3n, Carb\u00d3n De Madera (al Por Mayor)",
    "sg:phone":"+34 972 20 43 14",
    "sg:postcode":"17004",
    "sg:province":"Girona",
    "wof:name":"Carreras Palahi Josep",
    "wof:placetype":"venue"
},
  "geometry": {"coordinates":[2.8249809742,41.9758911133],"type":"Point"}
}