{
  "type": "Feature",
  "properties": {
    "addr:full":"Calle de Poeta Altet, 3 Valencia Valencia 46020",
    "addr:housenumber":"3",
    "addr:postcode":"46020",
    "addr:street":"Calle De Poeta Altet",
    "iso:country":"ES",
    "sg:address":"Calle de Poeta Altet, 3",
    "sg:city":"Valencia",
    "sg:orig_category":"Artes Gr\u00c1ficas, Artes Pl\u00c1sticas (curso)",
    "sg:phone":"+34 963 62 03 31",
    "sg:postcode":"46020",
    "sg:province":"Valencia",
    "wof:name":"Imprenthon S.l.",
    "wof:placetype":"venue"
},
  "geometry": {"coordinates":[-0.3651149869,39.4861068726],"type":"Point"}
}