{
  "type": "Feature",
  "properties": {
    "addr:full":"Rua Marcelino Parrondo, 53 Carballi\u00f1o Ourense 32500",
    "addr:housenumber":"53",
    "addr:postcode":"32500",
    "addr:street":"Rua Marcelino Parrondo",
    "iso:country":"ES",
    "sg:address":"Rua Marcelino Parrondo, 53",
    "sg:city":"Carballi\u00f1o",
    "sg:orig_category":"Venta, Montaje De Neum\u00c1ticos",
    "sg:phone":"+34 988 27 00 66",
    "sg:postcode":"32500",
    "sg:province":"Ourense",
    "wof:name":"Garage Nogueira S.l.",
    "wof:placetype":"venue"
},
  "geometry": {"coordinates":[-8.0800561905,42.4331855774],"type":"Point"}
}