{
  "type": "Feature",
  "properties": {
    "iso:country":"ES",
    "sg:address":"Calle de Parroco Antonio Gonzalez Abato, 2",
    "sg:city":"Sevilla",
    "sg:orig_category":"Arquitectos",
    "sg:phone":"+34 954 23 45 80",
    "sg:postcode":"41013",
    "sg:province":"Sevilla",
    "wof:name":"Molinero Cid Francisco",
    "wof:placetype":"venue"
},
  "geometry": {"coordinates":[-5.9752030373,37.3667411804],"type":"Point"}
}