{
  "type": "Feature",
  "properties": {
    "addr:full":"Rua Mercado, S/n Ourense Ourense 32001",
    "addr:postcode":"32001",
    "addr:street":"Rua Mercado S / N",
    "iso:country":"ES",
    "sg:address":"Rua Mercado, S/n",
    "sg:city":"Ourense",
    "sg:orig_category":"M\u00c9dicos: Termomedicina (hidrolog\u00cda Y Climatolog\u00cda M\u00c9dicas)",
    "sg:phone":"+34 988 21 48 21",
    "sg:postcode":"32001",
    "sg:province":"Ourense",
    "wof:name":"Ibernisha S.l.",
    "wof:placetype":"venue"
},
  "geometry": {"coordinates":[-7.8666481972,42.3475952148],"type":"Point"}
}