{
  "type": "Feature",
  "properties": {
    "iso:country":"ES",
    "sg:address":"Calle de Tercia (la), S/n",
    "sg:city":"Aguilar De La Frontera",
    "sg:orig_category":"Frutas, Legumbres Frescas Y Tempranas (al Por Menor)",
    "sg:phone":"+34 957 66 21 50",
    "sg:postcode":"14920",
    "sg:province":"C\u00f3rdoba",
    "wof:name":"Lara Gutierrez Rocio",
    "wof:placetype":"venue"
},
  "geometry": {"coordinates":[-4.6534690857,37.5148925781],"type":"Point"}
}