{
  "type": "Feature",
  "properties": {
    "iso:country":"ES",
    "sg:address":"Cra. Ribes (sector Can Baldic), 108",
    "sg:city":"Llerona",
    "sg:orig_category":"Montaje (empresas De)",
    "sg:phone":"+34 938 49 40 64",
    "sg:postcode":"08520",
    "sg:province":"Barcelona",
    "sg:website":"www.pac04.com",
    "wof:name":"Panell Aillanc S.l.",
    "wof:placetype":"venue"
},
  "geometry": {"coordinates":[2.2953050137,41.6295814514],"type":"Point"}
}