{
  "type": "Feature",
  "properties": {
    "addr:full":"Pase Goya (de), 1 Mostoles Madrid 28931",
    "addr:postcode":"28931",
    "addr:street":"Mostoles",
    "iso:country":"ES",
    "sg:address":"Pase Goya (de), 1",
    "sg:city":"Mostoles",
    "sg:orig_category":"Inmobiliaria (agencias)",
    "sg:phone":"+34 916 17 54 22",
    "sg:postcode":"28931",
    "sg:province":"Madrid",
    "wof:name":"Gesimo Inmobiliaria S. L.",
    "wof:placetype":"venue"
},
  "geometry": {"coordinates":[-3.8649389744,40.3230667114],"type":"Point"}
}