{
  "type": "Feature",
  "properties": {
    "addr:full":"Ctra. Eivissa S. Antoni, Km. 0003,2 Eivissa Islas Baleares 07800",
    "addr:postcode":"07800",
    "addr:street":"Ctra. Eivissa S. Antoni Km. 0003,2",
    "iso:country":"ES",
    "sg:address":"Ctra. Eivissa S. Antoni, Km. 0003,2",
    "sg:city":"Eivissa",
    "sg:orig_category":"Cerrajer\u00cda, Ferrallista",
    "sg:phone":"+34 971 31 44 65",
    "sg:postcode":"07800",
    "sg:province":"Islas Baleares",
    "wof:name":"Cerrajeria Vi\u00f1as Comunidad De Bienes",
    "wof:placetype":"venue"
},
  "geometry": {"coordinates":[1.4188899994,38.9061164856],"type":"Point"}
}