{
  "type": "Feature",
  "properties": {
    "iso:country":"ES",
    "sg:address":"Garcia Lorca, 19",
    "sg:city":"Alora",
    "sg:orig_category":"Panader\u00cdas, Panader\u00cdas",
    "sg:phone":"+34 952 49 70 50",
    "sg:postcode":"29500",
    "sg:province":"M\u00e1laga",
    "wof:name":"Panificadora Hermanos Cabrera S.l.",
    "wof:placetype":"venue"
},
  "geometry": {"coordinates":[-4.6904821396,36.8231163025],"type":"Point"}
}