{
  "type": "Feature",
  "properties": {
    "addr:full":"Calle de Juan Parras, 32 Catarroja Valencia 46470",
    "addr:housenumber":"32",
    "addr:postcode":"46470",
    "addr:street":"Calle De Juan Parras",
    "iso:country":"ES",
    "sg:address":"Calle de Juan Parras, 32",
    "sg:city":"Catarroja",
    "sg:orig_category":"Cristaler\u00cdas",
    "sg:phone":"+34 961 26 88 42",
    "sg:postcode":"46470",
    "sg:province":"Valencia",
    "wof:name":"Almarche Ramon Jose Manuel",
    "wof:placetype":"venue"
},
  "geometry": {"coordinates":[-0.4015350938,39.3975753784],"type":"Point"}
}