{
  "type": "Feature",
  "properties": {
    "addr:full":"Avda Inventor Pedro Cawley, 2 Poligono Industrial Salinas De San Jose C\u00e1diz 11500",
    "addr:housenumber":"2",
    "addr:postcode":"11500",
    "addr:street":"Avda Inventor Pedro Cawley;Poligono Industrial Salinas De;Ca\u0301Diz",
    "iso:country":"ES",
    "sg:address":"Avda Inventor Pedro Cawley, 2",
    "sg:city":"Poligono Industrial Salinas De San Jose",
    "sg:orig_category":"Trabajos De Fotocomposici\u00d3n",
    "sg:phone":"+34 956 85 13 44",
    "sg:postcode":"11500",
    "sg:province":"C\u00e1diz",
    "wof:name":"Fotocromia Lineal S.l.",
    "wof:placetype":"venue"
},
  "geometry": {"coordinates":[-6.2197542191,36.6056632996],"type":"Point"}
}