{
  "type": "Feature",
  "properties": {
    "iso:country":"ES",
    "sg:address":"Calle de Barbecho, 23",
    "sg:city":"Valladolid",
    "sg:orig_category":"Ense\u00d1anza P\u00dablica Primaria",
    "sg:phone":"+34 983 37 96 68",
    "sg:postcode":"47014",
    "sg:province":"Valladolid",
    "wof:name":"Interbaby Estimulacion S.l.",
    "wof:placetype":"venue"
},
  "geometry": {"coordinates":[-4.7460846901,41.6499328613],"type":"Point"}
}