{
  "type": "Feature",
  "properties": {
    "addr:full":"Av Espanya, 26 Eixample Barcelona 08150",
    "addr:housenumber":"26",
    "addr:postcode":"08150",
    "addr:street":"Av Espanya",
    "iso:country":"ES",
    "sg:address":"Av Espanya, 26",
    "sg:city":"Eixample",
    "sg:orig_category":"Peluqueros: De Se\u00d1oras",
    "sg:phone":"+34 935 73 14 82",
    "sg:postcode":"08150",
    "sg:province":"Barcelona",
    "wof:name":"Anglada Frometa Melina",
    "wof:placetype":"venue"
},
  "geometry": {"coordinates":[2.1296372414,41.4952278137],"type":"Point"}
}