{
  "type": "Feature",
  "properties": {
    "addr:full":"Calle de Doce De Octubre, 19 Zaragoza Zaragoza 50007",
    "addr:housenumber":"19",
    "addr:postcode":"50007",
    "addr:street":"Calle De Doce De Octubre",
    "iso:country":"ES",
    "sg:address":"Calle de Doce De Octubre, 19",
    "sg:city":"Zaragoza",
    "sg:orig_category":"Lencer\u00cda Femenina, Corseter\u00cda, Trajes De Ba\u00d1o (al Por Menor)",
    "sg:phone":"+34 976 38 78 52",
    "sg:postcode":"50007",
    "sg:province":"Zaragoza",
    "wof:name":"Super Textil Romeo S.l.",
    "wof:placetype":"venue"
},
  "geometry": {"coordinates":[-0.8780511022,41.6353492737],"type":"Point"}
}