{
  "type": "Feature",
  "properties": {
    "iso:country":"ES",
    "sg:address":"Avda Juan Sebastian Elcano, 192",
    "sg:city":"Malaga",
    "sg:orig_category":"Institutos De Belleza",
    "sg:phone":"+34 952 20 36 64",
    "sg:postcode":"29017",
    "sg:province":"M\u00e1laga",
    "wof:name":"Sanchez Fernandez Maria Jesus",
    "wof:placetype":"venue"
},
  "geometry": {"coordinates":[-4.3596248627,36.7208938599],"type":"Point"}
}