{
  "type": "Feature",
  "properties": {
    "addr:full":"Avda Jose Antonio, 84 Polan Toledo 45161",
    "addr:housenumber":"84",
    "addr:postcode":"45161",
    "addr:street":"Avda Jose Antonio",
    "iso:country":"ES",
    "sg:address":"Avda Jose Antonio, 84",
    "sg:city":"Polan",
    "sg:orig_category":"Agentes, Concesionarios Y Sucursales De Veh\u00cdculos",
    "sg:phone":"+34 925 37 06 25",
    "sg:postcode":"45161",
    "sg:province":"Toledo",
    "wof:name":"Autos Pujirel S. L.",
    "wof:placetype":"venue"
},
  "geometry": {"coordinates":[-4.1654853821,39.7890167236],"type":"Point"}
}