{
  "type": "Feature",
  "properties": {
    "addr:full":"Rond Pintor Garate (del), S/n Albalate Arzobispo Teruel 44540",
    "addr:housenumber":"/ n",
    "addr:postcode":"44540",
    "addr:street":"Rond Pintor Garate Del S;Albalate Arzobispo Teruel",
    "iso:country":"ES",
    "sg:address":"Rond Pintor Garate (del), S/n",
    "sg:city":"Albalate Arzobispo",
    "sg:orig_category":"Centros De Educaci\u00d3n Especial",
    "sg:phone":"+34 978 81 22 31",
    "sg:postcode":"44540",
    "sg:province":"Teruel",
    "wof:name":"Colegio Publico Roman Garcia",
    "wof:placetype":"venue"
},
  "geometry": {"coordinates":[-0.5094739795,41.1234474182],"type":"Point"}
}