{
  "type": "Feature",
  "properties": {
    "addr:full":"Calle de Erreka, 4 Elorrio Vizcaya 48230",
    "addr:housenumber":"4",
    "addr:postcode":"48230",
    "addr:street":"Calle De Erreka",
    "iso:country":"ES",
    "sg:address":"Calle de Erreka, 4",
    "sg:city":"Elorrio",
    "sg:orig_category":"Carnicer\u00cdas, Carnicer\u00cdas",
    "sg:phone":"+34 946 82 00 92",
    "sg:postcode":"48230",
    "sg:province":"Vizcaya",
    "wof:name":"Urizar Amiana Leocadio",
    "wof:placetype":"venue"
},
  "geometry": {"coordinates":[-2.5428104401,43.1308097839],"type":"Point"}
}