{
  "type": "Feature",
  "properties": {
    "iso:country":"ES",
    "sg:address":"Calle de Honduras, 37",
    "sg:city":"Gijon",
    "sg:orig_category":"Venta, Instalaci\u00d3n De Cocinas",
    "sg:phone":"+34 985 31 12 94",
    "sg:postcode":"33212",
    "sg:province":"Asturias",
    "wof:name":"Lojo Suarez Jose Ramon",
    "wof:placetype":"venue"
},
  "geometry": {"coordinates":[-5.6950221062,43.5413398743],"type":"Point"}
}