{
  "type": "Feature",
  "properties": {
    "addr:full":"Calle de Bazan, 24 Gijon Asturias 33211",
    "addr:housenumber":"24",
    "addr:postcode":"33211",
    "addr:street":"Calle De Bazan",
    "iso:country":"ES",
    "sg:address":"Calle de Bazan, 24",
    "sg:city":"Gijon",
    "sg:classifiers":[
        {
            "category":"Manufacturing",
            "subcategory":"Metals",
            "type":"Manufacturing & Wholesale Goods"
        }
    ],
    "sg:phone":"+34 985 32 26 11",
    "sg:postcode":"33211",
    "sg:province":"Asturias",
    "sg:tags":[
        "en",
        "fundiciones"
    ],
    "wof:name":"Fundiciones Inalza S.a.",
    "wof:placetype":"venue"
},
  "geometry": {"coordinates":[-5.6960749626,43.5323028564],"type":"Point"}
}