{
  "type": "Feature",
  "properties": {
    "addr:full":"Calle de Garcia De Paredes, 34 Madrid Madrid 28010",
    "addr:housenumber":"34",
    "addr:postcode":"madrid;28010",
    "addr:street":"Calle De Garcia De Paredes",
    "iso:country":"ES",
    "sg:address":"Calle de Garcia De Paredes, 34",
    "sg:city":"Madrid",
    "sg:orig_category":"Mercer\u00cda, Lencer\u00cda (al Por Menor)",
    "sg:phone":"+34 915 94 29 95",
    "sg:postcode":"28010",
    "sg:province":"Madrid",
    "wof:name":"Dieguez Manzano Oscar",
    "wof:placetype":"venue"
},
  "geometry": {"coordinates":[-3.6990399361,40.4365997314],"type":"Point"}
}