{
  "type": "Feature",
  "properties": {
    "addr:full":"Calle de Santiago Fuentes, 5 Vitigudino Salamanca 37210",
    "addr:housenumber":"5",
    "addr:postcode":"37210",
    "addr:street":"Calle De Santiago Fuentes",
    "iso:country":"ES",
    "sg:address":"Calle de Santiago Fuentes, 5",
    "sg:city":"Vitigudino",
    "sg:orig_category":"Abogados",
    "sg:phone":"+34 923 50 11 28",
    "sg:postcode":"37210",
    "sg:province":"Salamanca",
    "wof:name":"Sanchez Herrero Jesus",
    "wof:placetype":"venue"
},
  "geometry": {"coordinates":[-6.4347600937,41.0079727173],"type":"Point"}
}