{
  "type": "Feature",
  "properties": {
    "iso:country":"ES",
    "sg:address":"Robledo, S/n",
    "sg:city":"Lugo",
    "sg:classifiers":[
        {
            "category":"Taxi",
            "type":"Transportation"
        }
    ],
    "sg:phone":"+34 985 77 01 01",
    "sg:postcode":"33690",
    "sg:province":"Asturias",
    "wof:name":"Jose Luis Fernandez Rodriguez Y Otros Cb",
    "wof:placetype":"venue"
},
  "geometry": {"coordinates":[-5.810836792,43.4387741089],"type":"Point"}
}