{
  "type": "Feature",
  "properties": {
    "addr:full":"Calle de Gaztelu, 8 Donostia-san Sebastian Guip\u00f9zcoa 20013",
    "addr:housenumber":"8",
    "addr:postcode":"20013",
    "addr:street":"Calle De Gaztelu",
    "iso:country":"ES",
    "sg:address":"Calle de Gaztelu, 8",
    "sg:city":"Donostia-san Sebastian",
    "sg:orig_category":"Pescader\u00cdas (al Por Menor)",
    "sg:phone":"+34 943 28 11 48",
    "sg:postcode":"20013",
    "sg:province":"Guip\u00f9zcoa",
    "wof:name":"Urretavizcaya Ayerza Jose",
    "wof:placetype":"venue"
},
  "geometry": {"coordinates":[-1.9566880465,43.3188552856],"type":"Point"}
}