{
  "type": "Feature",
  "properties": {
    "addr:full":"Calle de Sierra De Aralar, 1 Vitoria-gasteiz \u00c1lava 01010",
    "addr:housenumber":"1",
    "addr:postcode":"01010",
    "addr:street":"Calle De Sierra De Aralar",
    "iso:country":"ES",
    "sg:address":"Calle de Sierra De Aralar, 1",
    "sg:city":"Vitoria-gasteiz",
    "sg:orig_category":"Molduras, Junquillos, Listones Y Molduras Perforadas",
    "sg:phone":"+34 945 17 32 67",
    "sg:postcode":"01010",
    "sg:province":"\u00c1lava",
    "wof:name":"C.t.a. Comunicaciones Telefonicas Alavesas",
    "wof:placetype":"venue"
},
  "geometry": {"coordinates":[-2.6941680908,42.8614845276],"type":"Point"}
}