{
  "type": "Feature",
  "properties": {
    "iso:country":"ES",
    "sg:address":"Calle de San Esteban, 35",
    "sg:city":"Sevilla",
    "sg:orig_category":"Importaci\u00d3n, Exportaci\u00d3n Y Comercios De Productos Textiles",
    "sg:phone":"+34 954 41 76 57",
    "sg:postcode":"41003",
    "sg:province":"Sevilla",
    "wof:name":"Ruiz Jimenez Rosario",
    "wof:placetype":"venue"
},
  "geometry": {"coordinates":[-5.9850730896,37.3894615173],"type":"Point"}
}