{
  "type": "Feature",
  "properties": {
    "iso:country":"ES",
    "sg:address":"Carrer de Querol, 41",
    "sg:city":"S. Climent Llobregat",
    "sg:orig_category":"Soldadura, Equipo Y Herramental",
    "sg:phone":"+34 936 37 83 62",
    "sg:postcode":"08849",
    "sg:province":"Barcelona",
    "wof:name":"Districasol S.l.",
    "wof:placetype":"venue"
},
  "geometry": {"coordinates":[1.9956259727,41.3404045105],"type":"Point"}
}