{
  "type": "Feature",
  "properties": {
    "addr:full":"Urb Altavista, 58 La Antilla Huelva 21449",
    "addr:housenumber":"58",
    "addr:postcode":"21449",
    "addr:street":"Urb Altavista",
    "iso:country":"ES",
    "sg:address":"Urb Altavista, 58",
    "sg:city":"La Antilla",
    "sg:orig_category":"Inform\u00c1tica Equipo Y Programas (al Por Mayor)",
    "sg:phone":"+34 959 48 67 93",
    "sg:postcode":"21449",
    "sg:province":"Huelva",
    "wof:name":"Martinez Fernandez Francisco Javier",
    "wof:placetype":"venue"
},
  "geometry": {"coordinates":[-7.2178740501,37.2062454224],"type":"Point"}
}