{
  "type": "Feature",
  "properties": {
    "iso:country":"ES",
    "sg:address":"Urbanizacion Real Orgaz, 5",
    "sg:city":"Orgaz",
    "sg:orig_category":"Molduras, Junquillos, Listones Y Molduras Perforadas",
    "sg:phone":"+34 925 31 73 79",
    "sg:postcode":"45450",
    "sg:province":"Toledo",
    "wof:name":"Sanchez De Castro De La Rica Pedro",
    "wof:placetype":"venue"
},
  "geometry": {"coordinates":[-3.8777449131,39.6468887329],"type":"Point"}
}