{
  "type": "Feature",
  "properties": {
    "addr:full":"Carrer de Paris, 6 Montcada Centre Barcelona 08110",
    "addr:housenumber":"6",
    "addr:postcode":"08110",
    "addr:street":"Carrer De Paris",
    "iso:country":"ES",
    "sg:address":"Carrer de Paris, 6",
    "sg:city":"Montcada Centre",
    "sg:orig_category":"Peluqueros: De Se\u00d1oras",
    "sg:phone":"+34 935 75 08 87",
    "sg:postcode":"08110",
    "sg:province":"Barcelona",
    "wof:name":"Rodriguez Rodriguez Mercedes",
    "wof:placetype":"venue"
},
  "geometry": {"coordinates":[2.1891469955,41.4810371399],"type":"Point"}
}