{
  "type": "Feature",
  "properties": {
    "iso:country":"ES",
    "sg:address":"Calle de Teneria, 28",
    "sg:city":"Galapagar",
    "sg:orig_category":"Pintura Y Barniz (al Por Menor)",
    "sg:phone":"+34 918 58 61 34",
    "sg:postcode":"28260",
    "sg:province":"Madrid",
    "wof:name":"Marpingue S.l.",
    "wof:placetype":"venue"
},
  "geometry": {"coordinates":[-3.9995849133,40.5794944763],"type":"Point"}
}