{
  "type": "Feature",
  "properties": {
    "iso:country":"ES",
    "sg:address":"Pg Joan Borbo Comte Barcelo, 32",
    "sg:city":"Barcelona",
    "sg:orig_category":"Ense\u00d1anza, Formaci\u00d3n Profesional: Aprendizaje",
    "sg:phone":"+34 932 24 06 00",
    "sg:postcode":"08003",
    "sg:province":"Barcelona",
    "wof:name":"Direccion General De La Policia",
    "wof:placetype":"venue"
},
  "geometry": {"coordinates":[2.1879479885,41.3787193298],"type":"Point"}
}