{
  "type": "Feature",
  "properties": {
    "addr:full":"Mcdo Abastos, S/n Logro\u00f1o La Rioja 26001",
    "addr:housenumber":"s / n",
    "addr:postcode":"26001",
    "addr:street":"Rioja",
    "iso:country":"ES",
    "sg:address":"Mcdo Abastos, S/n",
    "sg:city":"Logro\u00f1o",
    "sg:orig_category":"Carnicer\u00cdas, Carnicer\u00cdas",
    "sg:phone":"+34 941 22 91 58",
    "sg:postcode":"26001",
    "sg:province":"La Rioja",
    "wof:name":"Ramirez Perez Victoria",
    "wof:placetype":"venue"
},
  "geometry": {"coordinates":[-2.4461789131,42.4652786255],"type":"Point"}
}