{
  "type": "Feature",
  "properties": {
    "iso:country":"ES",
    "sg:address":"Calle de Hilanderas (de Las), 4",
    "sg:city":"Arganda",
    "sg:orig_category":"Fabricaci\u00d3n, Venta, Instalaci\u00d3n De R\u00d3tulos, De R\u00d3tulos Luminosos",
    "sg:phone":"+34 918 76 06 52",
    "sg:postcode":"28500",
    "sg:province":"Madrid",
    "sg:website":"www.megaplas.com",
    "wof:name":"Megaplas S.a.",
    "wof:placetype":"venue"
},
  "geometry": {"coordinates":[-3.4406979084,40.2999954224],"type":"Point"}
}