{
  "type": "Feature",
  "properties": {
    "iso:country":"ES",
    "sg:address":"Calle de Reyes Catolicos, 15",
    "sg:city":"Toledo",
    "sg:orig_category":"Ense\u00d1anza P\u00dablica Secundaria",
    "sg:phone":"+34 925 22 39 38",
    "sg:postcode":"45002",
    "sg:province":"Toledo",
    "wof:name":"Escuela De Arte",
    "wof:placetype":"venue"
},
  "geometry": {"coordinates":[-4.0310578346,39.8573570251],"type":"Point"}
}