{
  "type": "Feature",
  "properties": {
    "addr:full":"Calle de Vicente Ballester, 38 Valencia Valencia 46011",
    "addr:housenumber":"38",
    "addr:postcode":"46011",
    "addr:street":"Calle De Vicente Ballester",
    "iso:country":"ES",
    "sg:address":"Calle de Vicente Ballester, 38",
    "sg:city":"Valencia",
    "sg:orig_category":"Centros Y Asociaciones De Gesti\u00d3n Homologados",
    "sg:phone":"+34 963 72 22 05",
    "sg:postcode":"46011",
    "sg:province":"Valencia",
    "wof:name":"Catala Carrion S.l.",
    "wof:placetype":"venue"
},
  "geometry": {"coordinates":[-0.33317101,39.4711799622],"type":"Point"}
}