{
  "type": "Feature",
  "properties": {
    "iso:country":"ES",
    "sg:address":"Carrer de Demetrio Poveda, 41",
    "sg:city":"Monovar",
    "sg:orig_category":"Electricidad: Equipos Industriales, Componentes (fabricaci\u00d3n)",
    "sg:phone":"+34 965 47 02 77",
    "sg:postcode":"03640",
    "sg:province":"Alicante",
    "wof:name":"La Tenda De Gori C.b.",
    "wof:placetype":"venue"
},
  "geometry": {"coordinates":[-0.8386489749,38.433921814],"type":"Point"}
}