{
  "type": "Feature",
  "properties": {
    "addr:full":"Calle de Marques Alonso Martinez, 3 Alcala Henares Madrid 28805",
    "addr:housenumber":"3",
    "addr:postcode":"28805",
    "addr:street":"Calle De Marques Alonso Martinez",
    "iso:country":"ES",
    "sg:address":"Calle de Marques Alonso Martinez, 3",
    "sg:city":"Alcala Henares",
    "sg:orig_category":"Farmacias",
    "sg:phone":"+34 918 89 27 55",
    "sg:postcode":"28805",
    "sg:province":"Madrid",
    "wof:name":"Garcia Carrillo Eloisa",
    "wof:placetype":"venue"
},
  "geometry": {"coordinates":[-3.3582549095,40.486618042],"type":"Point"}
}