{
  "type": "Feature",
  "properties": {
    "addr:full":"Bidaburua, 6 Atarrabia Navarra 31610",
    "addr:housenumber":"6",
    "addr:postcode":"31610",
    "addr:street":"Bidaburua",
    "iso:country":"ES",
    "sg:address":"Bidaburua, 6",
    "sg:city":"Atarrabia",
    "sg:orig_category":"Farmacias",
    "sg:phone":"+34 948 33 48 36",
    "sg:postcode":"31610",
    "sg:province":"Navarra",
    "wof:name":"Gonzalez Laborie Maria Teresa",
    "wof:placetype":"venue"
},
  "geometry": {"coordinates":[-1.6098489761,42.8311386108],"type":"Point"}
}