{
  "type": "Feature",
  "properties": {
    "addr:full":"Rua Garcia Lorca, 4 Vigo Pontevedra 36209",
    "addr:housenumber":"4",
    "addr:postcode":"36209",
    "addr:street":"Rua Garcia Lorca",
    "iso:country":"ES",
    "sg:address":"Rua Garcia Lorca, 4",
    "sg:city":"Vigo",
    "sg:orig_category":"Asesor\u00cda Sobre Comunicaci\u00d3n De Empresas",
    "sg:phone":"+34 986 29 85 51",
    "sg:postcode":"36209",
    "sg:province":"Pontevedra",
    "wof:name":"Gonzalez Lias Benjamin",
    "wof:placetype":"venue"
},
  "geometry": {"coordinates":[-8.7352313995,42.2194213867],"type":"Point"}
}