{
  "type": "Feature",
  "properties": {
    "iso:country":"ES",
    "sg:address":"Calle de Carrera, La, 32",
    "sg:city":"Burriana",
    "sg:orig_category":"Importaci\u00d3n",
    "sg:phone":"+34 964 57 03 19",
    "sg:postcode":"12530",
    "sg:province":"Castell\u00f3n",
    "wof:name":"Sancho Arnal Victoriano",
    "wof:placetype":"venue"
},
  "geometry": {"coordinates":[-0.0822552964,39.8886032104],"type":"Point"}
}