{
  "type": "Feature",
  "properties": {
    "addr:full":"Plaz Llano De Las Coronadas, 4 Aguilar De La Frontera C\u00f3rdoba 14920",
    "addr:housenumber":"4",
    "addr:postcode":"14920",
    "addr:street":"Plaz;Coronadas",
    "iso:country":"ES",
    "sg:address":"Plaz Llano De Las Coronadas, 4",
    "sg:city":"Aguilar De La Frontera",
    "sg:orig_category":"Art\u00cdculos De Decoraci\u00d3n",
    "sg:phone":"+34 957 68 80 06",
    "sg:postcode":"14920",
    "sg:province":"C\u00f3rdoba",
    "wof:name":"Lopez Galisteo Angeles",
    "wof:placetype":"venue"
},
  "geometry": {"coordinates":[-4.6657028198,37.4828910828],"type":"Point"}
}