{
  "type": "Feature",
  "properties": {
    "iso:country":"ES",
    "sg:address":"Avda Valencia, 165",
    "sg:city":"Caudete",
    "sg:orig_category":"Empresas De Carpinter\u00cda De Madera",
    "sg:phone":"+34 965 82 76 87",
    "sg:postcode":"02660",
    "sg:province":"Albacete",
    "wof:name":"Serrano Albertos Manuel",
    "wof:placetype":"venue"
},
  "geometry": {"coordinates":[-0.9955589771,38.7054405212],"type":"Point"}
}