{
  "type": "Feature",
  "properties": {
    "addr:full":"Calle de Venecia, 79 Zaragoza Zaragoza 50007",
    "addr:housenumber":"79",
    "addr:postcode":"50007",
    "addr:street":"Calle De Venecia",
    "iso:country":"ES",
    "sg:address":"Calle de Venecia, 79",
    "sg:city":"Zaragoza",
    "sg:orig_category":"Asilos De Ancianos. Centros Privados",
    "sg:phone":"+34 976 38 85 55",
    "sg:postcode":"50007",
    "sg:province":"Zaragoza",
    "wof:name":"Residencia Esteve-lera S.l.",
    "wof:placetype":"venue"
},
  "geometry": {"coordinates":[-0.8901000023,41.6329460144],"type":"Point"}
}