{
  "type": "Feature",
  "properties": {
    "iso:country":"ES",
    "sg:address":"Avda San Miguel, 1",
    "sg:city":"Chinchilla Monte-aragon",
    "sg:orig_category":"Venta, Instalaci\u00d3n, Reparaci\u00d3n De Antenas Para Televisi\u00d3n",
    "sg:phone":"+34 967 26 06 91",
    "sg:postcode":"02520",
    "sg:province":"Albacete",
    "wof:name":"Castellanos Correoso Maria Jose",
    "wof:placetype":"venue"
},
  "geometry": {"coordinates":[-1.7232949734,38.9209251404],"type":"Point"}
}