{
  "type": "Feature",
  "properties": {
    "iso:country":"ES",
    "sg:address":"Calle de Marti Grajales, 9",
    "sg:city":"Valencia",
    "sg:orig_category":"Alimentaci\u00d3n General (al Por Menor)",
    "sg:phone":"+34 963 71 73 27",
    "sg:postcode":"46011",
    "sg:province":"Valencia",
    "wof:name":"Bodega Caba\u00f1al S.l.",
    "wof:placetype":"venue"
},
  "geometry": {"coordinates":[-0.3337259889,39.4687423706],"type":"Point"}
}