{
  "type": "Feature",
  "properties": {
    "iso:country":"ES",
    "sg:address":"Plaz Toros, 1",
    "sg:city":"Ecija",
    "sg:orig_category":"Molduras, Junquillos, Listones Y Molduras Perforadas",
    "sg:phone":"+34 954 83 46 05",
    "sg:postcode":"41400",
    "sg:province":"Sevilla",
    "wof:name":"Lopez Valero Domingo",
    "wof:placetype":"venue"
},
  "geometry": {"coordinates":[-5.0864567757,37.5372161865],"type":"Point"}
}