{
  "type": "Feature",
  "properties": {
    "iso:country":"ES",
    "sg:address":"Carrer de Cala Joanet, 6",
    "sg:city":"Ametlla Mar",
    "sg:orig_category":"Restaurantes",
    "sg:phone":"+34 977 45 65 84",
    "sg:postcode":"43860",
    "sg:province":"Tarragona",
    "wof:name":"Dimarut S.l.",
    "wof:placetype":"venue"
},
  "geometry": {"coordinates":[0.7992730141,40.8853607178],"type":"Point"}
}