{
  "type": "Feature",
  "properties": {
    "iso:country":"ES",
    "sg:address":"Carrer de Palau Reial, 16",
    "sg:city":"Palma",
    "sg:classifiers":[
        {
            "category":"Communications",
            "type":"Services"
        }
    ],
    "sg:phone":"+34 971 22 88 50",
    "sg:postcode":"07001",
    "sg:province":"Islas Baleares",
    "sg:tags":[
        "televisiones",
        "y",
        "radio"
    ],
    "wof:name":"Radio De Les Illes Ballears S.a.",
    "wof:placetype":"venue"
},
  "geometry": {"coordinates":[2.6479949951,39.5687599182],"type":"Point"}
}