{
  "type": "Feature",
  "properties": {
    "iso:country":"ES",
    "sg:address":"Carrer de Barcelona, 8",
    "sg:city":"Castellar Valles",
    "sg:orig_category":"Empresas De Carpinter\u00cda De Madera",
    "sg:phone":"+34 937 14 82 07",
    "sg:postcode":"08211",
    "sg:province":"Barcelona",
    "wof:name":"Morales Merin Alvaro",
    "wof:placetype":"venue"
},
  "geometry": {"coordinates":[2.0867021084,41.6124954224],"type":"Point"}
}