{
  "type": "Feature",
  "properties": {
    "iso:country":"ES",
    "sg:address":"Pda. Arenals, S/n",
    "sg:city":"Ginestar",
    "sg:orig_category":"Poller\u00cda Y Caza (al Por Menor)",
    "sg:phone":"+34 977 40 90 42",
    "sg:postcode":"43748",
    "sg:province":"Tarragona",
    "wof:name":"Agropecuaria Arenals S.l.",
    "wof:placetype":"venue"
},
  "geometry": {"coordinates":[0.634631,41.032619],"type":"Point"}
}