{
  "type": "Feature",
  "properties": {
    "addr:full":"Urb Vallserrat, S/n S. Esteve Sesrovires Barcelona 08635",
    "addr:housenumber":"s",
    "addr:postcode":"08635",
    "addr:street":"Urb Vallserrat;/ N S. Esteve Sesrovires Barcelona",
    "iso:country":"ES",
    "sg:address":"Urb Vallserrat, S/n",
    "sg:city":"S. Esteve Sesrovires",
    "sg:orig_category":"Cine (producci\u00d3n, Realizaci\u00d3n)",
    "sg:phone":"+34 937 71 31 35",
    "sg:postcode":"08635",
    "sg:province":"Barcelona",
    "wof:name":"Bella Bellus Belli S.l.",
    "wof:placetype":"venue"
},
  "geometry": {"coordinates":[1.8731199503,41.4965515137],"type":"Point"}
}