{
  "type": "Feature",
  "properties": {
    "addr:full":"Calle de Sagunto, 127 Valencia Valencia 46009",
    "addr:housenumber":"127",
    "addr:postcode":"46009",
    "addr:street":"Calle De Sagunto",
    "iso:country":"ES",
    "sg:address":"Calle de Sagunto, 127",
    "sg:city":"Valencia",
    "sg:orig_category":"Venta, Alquiler, Mantenimiento De Calderas",
    "sg:phone":"+34 963 68 08 60",
    "sg:postcode":"46009",
    "sg:province":"Valencia",
    "wof:name":"Confi Hogar S.l",
    "wof:placetype":"venue"
},
  "geometry": {"coordinates":[-0.3754720092,39.4882392883],"type":"Point"}
}