{
  "type": "Feature",
  "properties": {
    "addr:full":"Avda Lonjas (de Las), Km. 0401,0 Cordoba C\u00f3rdoba 14010",
    "addr:postcode":"14010",
    "addr:street":"Avda Lonjas De Las Km. 0401,0;Co\u0301Rdoba",
    "iso:country":"ES",
    "sg:address":"Avda Lonjas (de Las), Km. 0401,0",
    "sg:city":"Cordoba",
    "sg:orig_category":"Pescader\u00cdas (al Por Menor)",
    "sg:phone":"+34 957 75 16 84",
    "sg:postcode":"14010",
    "sg:province":"C\u00f3rdoba",
    "wof:name":"Congelados Puerta De Sevilla S.l.",
    "wof:placetype":"venue"
},
  "geometry": {"coordinates":[-4.761826992,37.8765182495],"type":"Point"}
}