{
  "type": "Feature",
  "properties": {
    "iso:country":"ES",
    "sg:address":"Calle de Altozano De Arriba, 2",
    "sg:city":"Guadalupe",
    "sg:orig_category":"Alimentaci\u00d3n General (al Por Menor)",
    "sg:phone":"+34 927 36 73 84",
    "sg:postcode":"10140",
    "sg:province":"C\u00e1ceres",
    "wof:name":"Prieto Reinoso Juan",
    "wof:placetype":"venue"
},
  "geometry": {"coordinates":[-5.3255329132,39.455116272],"type":"Point"}
}