{
  "type": "Feature",
  "properties": {
    "addr:full":"Avda Gonzalez Meneses, 5 Cabra C\u00f3rdoba 14940",
    "addr:housenumber":"5",
    "addr:postcode":"14940",
    "addr:street":"Avda Gonzalez Meneses;Co\u0301Rdoba",
    "iso:country":"ES",
    "sg:address":"Avda Gonzalez Meneses, 5",
    "sg:city":"Cabra",
    "sg:orig_category":"Procuradores",
    "sg:phone":"+34 957 52 92 35",
    "sg:postcode":"14940",
    "sg:province":"C\u00f3rdoba",
    "wof:name":"Espinosa Cubero Juan Francisco",
    "wof:placetype":"venue"
},
  "geometry": {"coordinates":[-4.4379491806,37.4721603394],"type":"Point"}
}