{
  "type": "Feature",
  "properties": {
    "iso:country":"ES",
    "sg:address":"Calle de Actor Francisco Rabal, 10",
    "sg:city":"San Anton",
    "sg:orig_category":"Asesor\u00cdas Y Estudios Financieros",
    "sg:phone":"+34 968 28 19 94",
    "sg:postcode":"30009",
    "sg:province":"Murcia",
    "wof:name":"Briones Perona Carlos",
    "wof:placetype":"venue"
},
  "geometry": {"coordinates":[-1.1298867464,37.9834747314],"type":"Point"}
}