{
  "type": "Feature",
  "properties": {
    "addr:full":"Carr San Jose, 34 Silla Valencia 46460",
    "addr:housenumber":"34",
    "addr:postcode":"46460",
    "addr:street":"Carr San Jose",
    "iso:country":"ES",
    "sg:address":"Carr San Jose, 34",
    "sg:city":"Silla",
    "sg:orig_category":"Centros Empresariales",
    "sg:phone":"+34 961 21 35 43",
    "sg:postcode":"46460",
    "sg:province":"Valencia",
    "sg:website":"www.creyfs.es",
    "wof:name":"Creyf's Trabajo Temporal Ett S.a.",
    "wof:placetype":"venue"
},
  "geometry": {"coordinates":[-0.4105750024,39.3622055054],"type":"Point"}
}