{
  "type": "Feature",
  "properties": {
    "iso:country":"ES",
    "sg:address":"Carrer de Rector Triado, 3",
    "sg:city":"Barcelona",
    "sg:orig_category":"Institutos De Belleza",
    "sg:phone":"+34 934 32 10 47",
    "sg:postcode":"08014",
    "sg:province":"Barcelona",
    "wof:name":"Araez Gil Maria Teresa",
    "wof:placetype":"venue"
},
  "geometry": {"coordinates":[2.145624876,41.3753433228],"type":"Point"}
}