{
  "type": "Feature",
  "properties": {
    "iso:country":"ES",
    "sg:address":"Carr Rutlla, 5",
    "sg:city":"Figueres",
    "sg:orig_category":"\u00d3ptica: Instrumentos (fabricaci\u00d3n)",
    "sg:phone":"+34 972 51 16 50",
    "sg:postcode":"17600",
    "sg:province":"Girona",
    "wof:name":"Opticontrol S.l.",
    "wof:placetype":"venue"
},
  "geometry": {"coordinates":[2.9633119106,42.2662467957],"type":"Point"}
}