{
  "type": "Feature",
  "properties": {
    "iso:country":"ES",
    "sg:address":"Calle de Enrique Fraile, 31",
    "sg:city":"Candelario",
    "sg:orig_category":"Alquiler De Casas Y Habitaciones Amuebladas",
    "sg:phone":"+34 923 41 30 36",
    "sg:postcode":"37710",
    "sg:province":"Salamanca",
    "wof:name":"Naila Hernandez Ana Isabel",
    "wof:placetype":"venue"
},
  "geometry": {"coordinates":[-5.7406277657,40.3655471802],"type":"Point"}
}