{
  "type": "Feature",
  "properties": {
    "addr:full":"Calle de Minero, 8 Almeria Almer\u00eda 04001",
    "addr:housenumber":"8",
    "addr:postcode":"04001",
    "addr:street":"Calle De Minero",
    "iso:country":"ES",
    "sg:address":"Calle de Minero, 8",
    "sg:city":"Almeria",
    "sg:orig_category":"Promotores Constructores",
    "sg:phone":"+34 950 22 08 10",
    "sg:postcode":"04001",
    "sg:province":"Almer\u00eda",
    "wof:name":"Gocal S.a.",
    "wof:placetype":"venue"
},
  "geometry": {"coordinates":[-2.4619259834,36.8389015198],"type":"Point"}
}