{
  "type": "Feature",
  "properties": {
    "iso:country":"ES",
    "sg:address":"Carr Mariners, 20",
    "sg:city":"Port D'alcudia",
    "sg:orig_category":"Molduras, Junquillos, Listones Y Molduras Perforadas",
    "sg:phone":"+34 971 54 74 14",
    "sg:postcode":"07410",
    "sg:province":"Islas Baleares",
    "wof:name":"Rosies Services C.p.",
    "wof:placetype":"venue"
},
  "geometry": {"coordinates":[3.133343935,39.8417510986],"type":"Point"}
}