{
  "type": "Feature",
  "properties": {
    "addr:full":"Kale Nagusia, 14 Usurbil Guip\u00f9zcoa 20170",
    "addr:housenumber":"14",
    "addr:postcode":"20170",
    "addr:street":"Kale Nagusia;Guipu\u0300Zcoa",
    "iso:country":"ES",
    "sg:address":"Kale Nagusia, 14",
    "sg:city":"Usurbil",
    "sg:orig_category":"Restaurantes",
    "sg:phone":"+34 943 36 27 25",
    "sg:postcode":"20170",
    "sg:province":"Guip\u00f9zcoa",
    "wof:name":"Salsamendi Sagardia Javier",
    "wof:placetype":"venue"
},
  "geometry": {"coordinates":[-2.0539140701,43.2733459473],"type":"Point"}
}