{
  "type": "Feature",
  "properties": {
    "addr:full":"Avda Cardenal Benlloch, 107 Valencia Valencia 46021",
    "addr:housenumber":"107",
    "addr:postcode":"46021",
    "addr:street":"Avda Cardenal Benlloch",
    "iso:country":"ES",
    "sg:address":"Avda Cardenal Benlloch, 107",
    "sg:city":"Valencia",
    "sg:orig_category":"Loter\u00cda Y T\u00d3mbola",
    "sg:phone":"+34 963 69 29 15",
    "sg:postcode":"46021",
    "sg:province":"Valencia",
    "wof:name":"Blasco Pons Maria Josefa",
    "wof:placetype":"venue"
},
  "geometry": {"coordinates":[-0.3529660106,39.4747047424],"type":"Point"}
}