{
  "type": "Feature",
  "properties": {
    "addr:full":"Calle de Sagasta, 35 San Pedro Murcia 30005",
    "addr:housenumber":"35",
    "addr:postcode":"30005",
    "addr:street":"Calle De Sagasta",
    "iso:country":"ES",
    "sg:address":"Calle de Sagasta, 35",
    "sg:city":"San Pedro",
    "sg:orig_category":"Materias Pl\u00c1sticas: Productos De Consumo Masivo (fabricaci\u00d3n, Al Por Mayor)",
    "sg:phone":"+34 968 21 18 53",
    "sg:postcode":"30005",
    "sg:province":"Murcia",
    "wof:name":"Manufacturas Murcia S. L.",
    "wof:placetype":"venue"
},
  "geometry": {"coordinates":[-0.7851368189,37.8396339417],"type":"Point"}
}