{
  "type": "Feature",
  "properties": {
    "addr:full":"Cmno Molino, 16 Torre Esteban Hambran Toledo 45920",
    "addr:housenumber":"16",
    "addr:postcode":"45920",
    "addr:street":"Cmno Molino",
    "iso:country":"ES",
    "sg:address":"Cmno Molino, 16",
    "sg:city":"Torre Esteban Hambran",
    "sg:orig_category":"Fabrica De Charcuter\u00cda",
    "sg:phone":"+34 925 79 55 03",
    "sg:postcode":"45920",
    "sg:province":"Toledo",
    "wof:name":"Distribuciones Avicolas La Torre Sl",
    "wof:placetype":"venue"
},
  "geometry": {"coordinates":[-4.025138855,39.8618774414],"type":"Point"}
}