{
  "type": "Feature",
  "properties": {
    "addr:full":"Calle de Fernan Caballero, 10 Malaga M\u00e1laga 29016",
    "addr:housenumber":"10",
    "addr:postcode":"29016",
    "addr:street":"Calle De Fernan Caballero;Ma\u0301Laga",
    "iso:country":"ES",
    "sg:address":"Calle de Fernan Caballero, 10",
    "sg:city":"Malaga",
    "sg:orig_category":"Arquitectos",
    "sg:phone":"+34 952 22 15 86",
    "sg:postcode":"29016",
    "sg:province":"M\u00e1laga",
    "wof:name":"Mu\u00f1oz Gallardo Pablo",
    "wof:placetype":"venue"
},
  "geometry": {"coordinates":[-4.397644043,36.7273674011],"type":"Point"}
}