{
  "type": "Feature",
  "properties": {
    "addr:full":"Calle de Carrera, 52 Solana Ciudad Real 13240",
    "addr:postcode":"13240",
    "addr:street":"Calle De Carrera 52 Solana;Real",
    "iso:country":"ES",
    "sg:address":"Calle de Carrera, 52",
    "sg:city":"Solana",
    "sg:orig_category":"Servicios Gsm",
    "sg:phone":"+34 926 63 33 12",
    "sg:postcode":"13240",
    "sg:province":"Ciudad Real",
    "wof:name":"Trio Comunicaciones S.l.",
    "wof:placetype":"venue"
},
  "geometry": {"coordinates":[-3.2373239994,38.9431343079],"type":"Point"}
}