{
  "type": "Feature",
  "properties": {
    "addr:full":"Calle de Pi\u00f1aga, 13 Getxo Vizcaya 48990",
    "addr:housenumber":"13",
    "addr:postcode":"48990",
    "addr:street":"Calle De Pin\u0303Aga",
    "iso:country":"ES",
    "sg:address":"Calle de Pi\u00f1aga, 13",
    "sg:city":"Getxo",
    "sg:orig_category":"Agentes, Concesionarios Y Sucursales De Veh\u00cdculos",
    "sg:phone":"+34 944 04 27 53",
    "sg:postcode":"48990",
    "sg:province":"Vizcaya",
    "wof:name":"Talleres Arriluce, S.a.",
    "wof:placetype":"venue"
},
  "geometry": {"coordinates":[-3.0095410347,43.3558540344],"type":"Point"}
}