{
  "type": "Feature",
  "properties": {
    "addr:full":"Carrer de Pilar, 10 Premia Mar Barcelona 08330",
    "addr:housenumber":"10",
    "addr:postcode":"08330",
    "addr:street":"Carrer De Pilar",
    "iso:country":"ES",
    "sg:address":"Carrer de Pilar, 10",
    "sg:city":"Premia Mar",
    "sg:classifiers":[
        {
            "category":"Autos & Motor Vehicles",
            "subcategory":"Automobile Sales",
            "type":"Retail Goods"
        }
    ],
    "sg:phone":"+34 937 52 30 83",
    "sg:postcode":"08330",
    "sg:province":"Barcelona",
    "wof:name":"Llamas Fernandez Juan Francisco",
    "wof:placetype":"venue"
},
  "geometry": {"coordinates":[2.3551449776,41.4931488037],"type":"Point"}
}