{
  "type": "Feature",
  "properties": {
    "iso:country":"ES",
    "sg:address":"Carr Jaume I, 41",
    "sg:city":"Girona",
    "sg:orig_category":"Ense\u00d1anza, Formaci\u00d3n Profesional: Aprendizaje",
    "sg:phone":"+34 972 20 29 50",
    "sg:postcode":"17001",
    "sg:province":"Girona",
    "wof:name":"Direccion General De Trafico",
    "wof:placetype":"venue"
},
  "geometry": {"coordinates":[2.8202219009,41.9819221497],"type":"Point"}
}