{
  "type": "Feature",
  "properties": {
    "iso:country":"ES",
    "sg:address":"Koldo Eleizalde Kalea, 8",
    "sg:city":"Bergara",
    "sg:orig_category":"Electricidad: Instaladores",
    "sg:phone":"+34 943 53 25 35",
    "sg:postcode":"20570",
    "sg:province":"Guip\u00f9zcoa",
    "wof:name":"Elkar Elektragintza, C.b.",
    "wof:placetype":"venue"
},
  "geometry": {"coordinates":[-2.4103739262,43.1184692383],"type":"Point"}
}