{
  "type": "Feature",
  "properties": {
    "iso:country":"ES",
    "sg:address":"Calle de Templarios (los), 8",
    "sg:city":"Fabero",
    "sg:orig_category":"Fachadas",
    "sg:phone":"+34 987 55 08 72",
    "sg:postcode":"24420",
    "sg:province":"Le\u00f3n",
    "wof:name":"Perez Alvarez Eladio",
    "wof:placetype":"venue"
},
  "geometry": {"coordinates":[-6.627863884,42.7677383423],"type":"Point"}
}