{
  "type": "Feature",
  "properties": {
    "addr:full":"Avda Pais Valencia, 182 Torrent Valencia 46900",
    "addr:housenumber":"182",
    "addr:postcode":"46900",
    "addr:street":"Avda Pais Valencia;Valencia",
    "iso:country":"ES",
    "sg:address":"Avda Pais Valencia, 182",
    "sg:city":"Torrent",
    "sg:orig_category":"Papeler\u00cdas, Librer\u00cdas",
    "sg:phone":"+34 961 56 44 44",
    "sg:postcode":"46900",
    "sg:province":"Valencia",
    "wof:name":"Dyaservips S.l.",
    "wof:placetype":"venue"
},
  "geometry": {"coordinates":[-0.4811739922,39.4268341064],"type":"Point"}
}