{
  "type": "Feature",
  "properties": {
    "iso:country":"ES",
    "sg:address":"Calle de Joaquin Costa, 21",
    "sg:city":"Teruel",
    "sg:orig_category":"Abogados",
    "sg:phone":"+34 978 61 00 19",
    "sg:postcode":"44001",
    "sg:province":"Teruel",
    "wof:name":"Martin Herrero Alfonso",
    "wof:placetype":"venue"
},
  "geometry": {"coordinates":[-1.1063369513,40.3436508179],"type":"Point"}
}