{
  "type": "Feature",
  "properties": {
    "iso:country":"ES",
    "sg:address":"Calle de Real De Arganda, 29",
    "sg:city":"Madrid",
    "sg:orig_category":"Chapister\u00cda",
    "sg:phone":"+34 913 01 36 60",
    "sg:postcode":"28031",
    "sg:province":"Madrid",
    "wof:name":"Automoviles F.fernandez S.l.",
    "wof:placetype":"venue"
},
  "geometry": {"coordinates":[-3.6181476116,40.3794441223],"type":"Point"}
}