{
  "type": "Feature",
  "properties": {
    "addr:full":"Carrer de Mossen Jacint Verdaguer, 10 Santa Anna-tio Barcelona 08338",
    "addr:housenumber":"10",
    "addr:postcode":"08338",
    "addr:street":"Carrer De Mossen Jacint Verdaguer",
    "iso:country":"ES",
    "sg:address":"Carrer de Mossen Jacint Verdaguer, 10",
    "sg:city":"Santa Anna-tio",
    "sg:classifiers":[
        {
            "category":"Casinos & Gambling",
            "type":"Entertainment"
        }
    ],
    "sg:phone":"+34 937 51 55 90",
    "sg:postcode":"08338",
    "sg:province":"Barcelona",
    "sg:tags":[
        "locale",
        "de",
        "juego"
    ],
    "wof:name":"Ajuntament De Premia De Dalt",
    "wof:placetype":"venue"
},
  "geometry": {"coordinates":[2.1699187756,41.3879165649],"type":"Point"}
}