{
  "type": "Feature",
  "properties": {
    "addr:full":"Calle de Do\u00d1a Perfecta, 73 Palmas De Gran Canaria Las Palmas 35012",
    "addr:housenumber":"73",
    "addr:postcode":"35012",
    "addr:street":"Calle De Don\u0303A Perfecta",
    "iso:country":"ES",
    "sg:address":"Calle de Do\u00d1a Perfecta, 73",
    "sg:city":"Palmas De Gran Canaria",
    "sg:orig_category":"Internados & Ense\u00d1anza Privada",
    "sg:phone":"+34 928 20 36 42",
    "sg:postcode":"35012",
    "sg:province":"Las Palmas",
    "wof:name":"Deniz Martin Josefa Antonia",
    "wof:placetype":"venue"
},
  "geometry": {"coordinates":[-15.4335050583,28.1099433899],"type":"Point"}
}