{
  "type": "Feature",
  "properties": {
    "iso:country":"ES",
    "sg:address":"Calle de Uva (la), S/n",
    "sg:city":"Virgen Camino",
    "sg:orig_category":"Inmobiliaria (agencias)",
    "sg:phone":"+34 987 30 23 34",
    "sg:postcode":"24198",
    "sg:province":"Le\u00f3n",
    "wof:name":"Gomez Gay Jacobo",
    "wof:placetype":"venue"
},
  "geometry": {"coordinates":[-5.6365141869,42.5827865601],"type":"Point"}
}