{
  "type": "Feature",
  "properties": {
    "iso:country":"ES",
    "sg:address":"Rua Blanco Porto, 2",
    "sg:city":"Pontevedra",
    "sg:orig_category":"M\u00c9dicos: Cirug\u00cda Ortop\u00c9dica Y Traumatolog\u00cda",
    "sg:phone":"+34 986 85 89 63",
    "sg:postcode":"36001",
    "sg:province":"Pontevedra",
    "wof:name":"Dominguez Vaz Miguel",
    "wof:placetype":"venue"
},
  "geometry": {"coordinates":[-8.6390790939,42.429069519],"type":"Point"}
}