{
  "type": "Feature",
  "properties": {
    "addr:full":"Barquera(la Barquera), S/n Folgosas La Coru\u00f1a 15563",
    "addr:housenumber":"s / n",
    "addr:postcode":"15563",
    "addr:street":"Barquera;Barquera;La Corun\u0303A",
    "iso:country":"ES",
    "sg:address":"Barquera(la Barquera), S/n",
    "sg:city":"Folgosas",
    "sg:orig_category":"Talleres: Ropa A Medida",
    "sg:phone":"+34 981 41 10 19",
    "sg:postcode":"15563",
    "sg:province":"La Coru\u00f1a",
    "wof:name":"Lopez Pe\u00f1a Manuel",
    "wof:placetype":"venue"
},
  "geometry": {"coordinates":[-8.3964595795,43.3701095581],"type":"Point"}
}