{
  "type": "Feature",
  "properties": {
    "addr:full":"Psaj Virgen De Consolacion, 16 Sevilla Sevilla 41011",
    "addr:housenumber":"16",
    "addr:postcode":"41011",
    "iso:country":"ES",
    "sg:address":"Psaj Virgen De Consolacion, 16",
    "sg:city":"Sevilla",
    "sg:orig_category":"M\u00c9dicos: Medicina Interna",
    "sg:phone":"+34 954 27 73 84",
    "sg:postcode":"41011",
    "sg:province":"Sevilla",
    "wof:name":"Conde Hernandez Jose",
    "wof:placetype":"venue"
},
  "geometry": {"coordinates":[-5.998278141,37.3789329529],"type":"Point"}
}