{
  "type": "Feature",
  "properties": {
    "iso:country":"ES",
    "sg:address":"Avda Carlos Conde, S/n",
    "sg:city":"Castropol",
    "sg:orig_category":"Asesor\u00cda De Formaci\u00d3n Y Gesti\u00d3n De Personal",
    "sg:phone":"+34 985 63 50 25",
    "sg:postcode":"33760",
    "sg:province":"Asturias",
    "wof:name":"Pablos Mu\u00f1oz Maria Jesus",
    "wof:placetype":"venue"
},
  "geometry": {"coordinates":[-7.0278820992,43.5242385864],"type":"Point"}
}