{
  "type": "Feature",
  "properties": {
    "iso:country":"ES",
    "sg:address":"Calle de Paz, S/n",
    "sg:city":"Ares",
    "sg:orig_category":"Asociaciones Y Clubs Deportivos",
    "sg:phone":"+34 981 44 81 21",
    "sg:postcode":"15624",
    "sg:province":"La Coru\u00f1a",
    "wof:name":"Numancia S.d.r.",
    "wof:placetype":"venue"
},
  "geometry": {"coordinates":[-8.2488899231,43.4292793274],"type":"Point"}
}