{
  "type": "Feature",
  "properties": {
    "iso:country":"ES",
    "sg:address":"Calle de Isabel Ii, 19",
    "sg:city":"Santander",
    "sg:orig_category":"Ropa De Hogar (al Por Menor)",
    "sg:phone":"+34 942 21 27 27",
    "sg:postcode":"39002",
    "sg:province":"Cantabria",
    "wof:name":"Gandarillas Celayeta Matilde Amparo",
    "wof:placetype":"venue"
},
  "geometry": {"coordinates":[-3.8088738918,43.4604415894],"type":"Point"}
}