{
  "type": "Feature",
  "properties": {
    "addr:full":"C/ 6, 12 Ca\u00d1ada Valencia 46182",
    "addr:housenumber":"12",
    "addr:postcode":"46182",
    "addr:street":"C / 6",
    "iso:country":"ES",
    "sg:address":"C/ 6, 12",
    "sg:city":"Ca\u00d1ada",
    "sg:orig_category":"Peluquer\u00cdas, Peluquer\u00cda Mixta",
    "sg:phone":"+34 961 32 41 72",
    "sg:postcode":"46182",
    "sg:province":"Valencia",
    "wof:name":"Marti Estilista Vanesa",
    "wof:placetype":"venue"
},
  "geometry": {"coordinates":[-0.4880129099,39.526184082],"type":"Point"}
}