{
  "type": "Feature",
  "properties": {
    "iso:country":"ES",
    "sg:address":"Avda Dilar (de), S/n",
    "sg:city":"Granada",
    "sg:orig_category":"Librer\u00cdas",
    "sg:phone":"+34 958 81 49 67",
    "sg:postcode":"18007",
    "sg:province":"Granada",
    "wof:name":"Lopez Martinez Josefa",
    "wof:placetype":"venue"
},
  "geometry": {"coordinates":[-3.5996789932,37.1599960327],"type":"Point"}
}