{
  "type": "Feature",
  "properties": {
    "addr:full":"Calle de Cruce De Don Manuel, 6 Puente M\u00e1laga 29713",
    "addr:housenumber":"6",
    "addr:postcode":"29713",
    "addr:street":"Calle De Cruce;Don Manuel;Ma\u0301Laga",
    "iso:country":"ES",
    "sg:address":"Calle de Cruce De Don Manuel, 6",
    "sg:city":"Puente",
    "sg:orig_category":"Charcuter\u00cdas (al Por Mayor)",
    "sg:phone":"+34 952 51 09 59",
    "sg:postcode":"29713",
    "sg:province":"M\u00e1laga",
    "wof:name":"Caremaxa S.l.",
    "wof:placetype":"venue"
},
  "geometry": {"coordinates":[-4.1582889557,36.8734664917],"type":"Point"}
}