{
  "type": "Feature",
  "properties": {
    "iso:country":"ES",
    "sg:address":"Avda Rioja De (la), S/n",
    "sg:city":"Aldeanueva Ebro",
    "sg:orig_category":"Frutas Y Legumbres Frescas (al Por Mayor)",
    "sg:phone":"+34 941 16 31 60",
    "sg:postcode":"26559",
    "sg:province":"La Rioja",
    "wof:name":"Frutas Martinez S.a.",
    "wof:placetype":"venue"
},
  "geometry": {"coordinates":[-1.8801590204,42.2278594971],"type":"Point"}
}