{
  "type": "Feature",
  "properties": {
    "addr:full":"Calle de Manuel Caso De La Villa, 1 Ribadesella Asturias 33560",
    "addr:housenumber":"1",
    "addr:postcode":"33560",
    "addr:street":"Calle De Manuel Caso De La Villa",
    "iso:country":"ES",
    "sg:address":"Calle de Manuel Caso De La Villa, 1",
    "sg:city":"Ribadesella",
    "sg:orig_category":"Ropa De Hogar (al Por Menor)",
    "sg:phone":"+34 985 86 04 54",
    "sg:postcode":"33560",
    "sg:province":"Asturias",
    "wof:name":"Blanco Sanchez Maria Teresa",
    "wof:placetype":"venue"
},
  "geometry": {"coordinates":[-5.0568509102,43.4630432129],"type":"Point"}
}