{
  "type": "Feature",
  "properties": {
    "addr:full":"Calle de Puerto Pajares, 5 Lugones Asturias 33420",
    "addr:housenumber":"5",
    "addr:postcode":"33420",
    "addr:street":"Calle De Puerto Pajares",
    "iso:country":"ES",
    "sg:address":"Calle de Puerto Pajares, 5",
    "sg:city":"Lugones",
    "sg:orig_category":"Asociaciones Y Clubs Deportivos",
    "sg:phone":"+34 985 26 75 30",
    "sg:postcode":"33420",
    "sg:province":"Asturias",
    "wof:name":"Prado Rojo Andrea",
    "wof:placetype":"venue"
},
  "geometry": {"coordinates":[-5.8133206367,43.3999137878],"type":"Point"}
}