{
  "type": "Feature",
  "properties": {
    "iso:country":"ES",
    "sg:address":"Calle de Mayor, 21",
    "sg:city":"Santa Cruz De La Zarza",
    "sg:orig_category":"Ropa Para Beb\u00c9s Y Ni\u00d1os (confecci\u00d3n, Al Por Mayor)",
    "sg:phone":"+34 925 14 30 02",
    "sg:postcode":"45370",
    "sg:province":"Toledo",
    "wof:name":"Garcia Garcia Ignacia",
    "wof:placetype":"venue"
},
  "geometry": {"coordinates":[-3.1886920929,39.9817886353],"type":"Point"}
}