{
  "type": "Feature",
  "properties": {
    "iso:country":"ES",
    "sg:address":"Calle de San Juan Grande, 28",
    "sg:city":"Carmona",
    "sg:orig_category":"Formaci\u00d3n Continuada (variada)",
    "sg:phone":"+34 954 14 26 36",
    "sg:postcode":"41410",
    "sg:province":"Sevilla",
    "wof:name":"Aguilar Rodriguez Juan Ramon",
    "wof:placetype":"venue"
},
  "geometry": {"coordinates":[-5.6428375244,37.472694397],"type":"Point"}
}