{
  "type": "Feature",
  "properties": {
    "iso:country":"ES",
    "sg:address":"Calle de Benigafull, 29",
    "sg:city":"Vall D'uixo",
    "sg:orig_category":"Bisuter\u00cda, Joyer\u00cda, Relojer\u00cda (al Por Menor)",
    "sg:phone":"+34 964 66 58 54",
    "sg:postcode":"12600",
    "sg:province":"Castell\u00f3n",
    "wof:name":"Vicente Raul Paulo Aledon",
    "wof:placetype":"venue"
},
  "geometry": {"coordinates":[-0.0482099988,39.992477417],"type":"Point"}
}