{
  "type": "Feature",
  "properties": {
    "iso:country":"ES",
    "sg:address":"Calle de Felipe Ii, 13",
    "sg:city":"Valladolid",
    "sg:orig_category":"Electricidad, Electr\u00d3nica: Suministros (al Por Menor)",
    "sg:phone":"+34 983 33 49 00",
    "sg:postcode":"47003",
    "sg:province":"Valladolid",
    "wof:name":"Castro Frontela Jose Luis",
    "wof:placetype":"venue"
},
  "geometry": {"coordinates":[-4.7252950668,41.65599823],"type":"Point"}
}