{
  "type": "Feature",
  "properties": {
    "addr:full":"Calle de Guabairo, 15 Madrid Madrid 28047",
    "addr:housenumber":"15",
    "addr:postcode":"madrid;28047",
    "addr:street":"Calle De Guabairo",
    "iso:country":"ES",
    "sg:address":"Calle de Guabairo, 15",
    "sg:city":"Madrid",
    "sg:orig_category":"Iglesia Cat\u00d3lica",
    "sg:phone":"+34 914 65 16 98",
    "sg:postcode":"28047",
    "sg:province":"Madrid",
    "wof:name":"Parroquia De La Epifania Del Se\u00d1or. Madrid",
    "wof:placetype":"venue"
},
  "geometry": {"coordinates":[-3.7454640865,40.3860282898],"type":"Point"}
}