{
  "type": "Feature",
  "properties": {
    "iso:country":"ES",
    "sg:address":"Ctra Alicante, 170",
    "sg:city":"Casillas  O Ermita De Buendia",
    "sg:orig_category":"Electricidad, Electr\u00d3nica: Material Y Suministros (al Por Mayor)",
    "sg:phone":"+34 968 20 31 10",
    "sg:postcode":"30007",
    "sg:province":"Murcia",
    "wof:name":"Automaticos Orenes S.l.",
    "wof:placetype":"venue"
},
  "geometry": {"coordinates":[-1.1298867464,37.9834747314],"type":"Point"}
}