{
  "type": "Feature",
  "properties": {
    "iso:country":"ES",
    "sg:address":"Calle de Marques De Ahumada, 1",
    "sg:city":"Zaragoza",
    "sg:orig_category":"Organizaciones Internacionales",
    "sg:phone":"+34 976 25 88 62",
    "sg:postcode":"50007",
    "sg:province":"Zaragoza",
    "wof:name":"Federacion Aragonesa De Familias De Enfermos De Alzeimer",
    "wof:placetype":"venue"
},
  "geometry": {"coordinates":[-0.8833699822,41.6386184692],"type":"Point"}
}