{
  "type": "Feature",
  "properties": {
    "iso:country":"ES",
    "sg:address":"Calle de Intxausti, 7",
    "sg:city":"Bermeo",
    "sg:orig_category":"Relojer\u00cda (al Por Menor, Reparaci\u00d3n)",
    "sg:phone":"+34 946 88 04 14",
    "sg:postcode":"48370",
    "sg:province":"Vizcaya",
    "wof:name":"Atxikallende Asla, Angel",
    "wof:placetype":"venue"
},
  "geometry": {"coordinates":[-2.7234911919,43.4205169678],"type":"Point"}
}