{
  "type": "Feature",
  "properties": {
    "addr:full":"Calle de Martires, 1 Calahorra La Rioja 26500",
    "addr:housenumber":"1",
    "addr:postcode":"26500",
    "addr:street":"Calle De Martires",
    "iso:country":"ES",
    "sg:address":"Calle de Martires, 1",
    "sg:city":"Calahorra",
    "sg:orig_category":"Abogados",
    "sg:phone":"+34 941 13 58 30",
    "sg:postcode":"26500",
    "sg:province":"La Rioja",
    "wof:name":"Gonzalez Losantos Felix Angel",
    "wof:placetype":"venue"
},
  "geometry": {"coordinates":[-1.9630119801,42.3024368286],"type":"Point"}
}