{
  "type": "Feature",
  "properties": {
    "addr:full":"Calle de Jose Sinues, 14 Ejea De Los Caballeros Zaragoza 50600",
    "addr:housenumber":"14",
    "addr:postcode":"50600",
    "addr:street":"Calle De Jose Sinues",
    "iso:country":"ES",
    "sg:address":"Calle de Jose Sinues, 14",
    "sg:city":"Ejea De Los Caballeros",
    "sg:orig_category":"M\u00c9dicos: Oftalmolog\u00cda",
    "sg:phone":"+34 976 66 77 66",
    "sg:postcode":"50600",
    "sg:province":"Zaragoza",
    "wof:name":"Arner Espinosa Jose",
    "wof:placetype":"venue"
},
  "geometry": {"coordinates":[-1.140917778,42.1254615784],"type":"Point"}
}