{
  "type": "Feature",
  "properties": {
    "addr:full":"G.v. Fernando El Catolico, 76 Valencia Valencia 46008",
    "addr:housenumber":"76",
    "addr:postcode":"46008",
    "addr:street":"Fernando El Catolico",
    "iso:country":"ES",
    "sg:address":"G.v. Fernando El Catolico, 76",
    "sg:city":"Valencia",
    "sg:orig_category":"M\u00c9dicos: Estomatolog\u00cda",
    "sg:phone":"+34 963 92 04 39",
    "sg:postcode":"46008",
    "sg:province":"Valencia",
    "wof:name":"Payan  Danny",
    "wof:placetype":"venue"
},
  "geometry": {"coordinates":[-0.3892750144,39.4768180847],"type":"Point"}
}