{
  "type": "Feature",
  "properties": {
    "addr:full":"Barr Palau (el), 8 Palau Barcelona 08740",
    "addr:postcode":"08740",
    "iso:country":"ES",
    "sg:address":"Barr Palau (el), 8",
    "sg:city":"Palau",
    "sg:orig_category":"Servicio De Salud",
    "sg:phone":"+34 936 53 10 54",
    "sg:postcode":"08740",
    "sg:province":"Barcelona",
    "wof:name":"Flector S.l.",
    "wof:placetype":"venue"
},
  "geometry": {"coordinates":[1.968840003,41.4521102905],"type":"Point"}
}