{
  "type": "Feature",
  "properties": {
    "addr:full":"Rua Poligono (a) Industrial De Uceira, S/n Carballi\u00f1o Ourense 32500",
    "addr:housenumber":"s",
    "addr:postcode":"32500",
    "addr:street":"Rua Poligono A Industrial De Uceira;/ N",
    "iso:country":"ES",
    "sg:address":"Rua Poligono (a) Industrial De Uceira, S/n",
    "sg:city":"Carballi\u00f1o",
    "sg:orig_category":"Promotores Constructores",
    "sg:phone":"+34 988 27 32 92",
    "sg:postcode":"32500",
    "sg:province":"Ourense",
    "wof:name":"Agrupconsa S.l.",
    "wof:placetype":"venue"
},
  "geometry": {"coordinates":[-8.065123558,42.4374732971],"type":"Point"}
}