{
  "type": "Feature",
  "properties": {
    "iso:country":"ES",
    "sg:address":"Calle de Poza Licenciado, 23",
    "sg:city":"Bilbao",
    "sg:orig_category":"Importaci\u00d3n",
    "sg:phone":"+34 944 10 47 84",
    "sg:postcode":"48011",
    "sg:province":"Vizcaya",
    "wof:name":"Klasiks Bilbao S.l.",
    "wof:placetype":"venue"
},
  "geometry": {"coordinates":[-2.9385590553,43.2615814209],"type":"Point"}
}