{
  "type": "Feature",
  "properties": {
    "addr:full":"Calle de Sao Paulo, 17 Palmas De Gran Canaria Las Palmas 35008",
    "addr:housenumber":"17",
    "addr:postcode":"35008",
    "addr:street":"Calle De Sao Paulo",
    "iso:country":"ES",
    "sg:address":"Calle de Sao Paulo, 17",
    "sg:city":"Palmas De Gran Canaria",
    "sg:orig_category":"Aparatos, Sistemas De Tele",
    "sg:phone":"+34 928 41 72 20",
    "sg:postcode":"35008",
    "sg:province":"Las Palmas",
    "wof:name":"Casmar Electronica S.a.",
    "wof:placetype":"venue"
},
  "geometry": {"coordinates":[-15.419380188,28.1532001495],"type":"Point"}
}