{
  "type": "Feature",
  "properties": {
    "addr:full":"Carrer de Arnau Rossi\u00d1ol, 20 Palma Islas Baleares 07013",
    "addr:housenumber":"20",
    "addr:postcode":"07013",
    "addr:street":"Carrer De;Rossin\u0303Ol",
    "iso:country":"ES",
    "sg:address":"Carrer de Arnau Rossi\u00d1ol, 20",
    "sg:city":"Palma",
    "sg:orig_category":"Farmacias",
    "sg:phone":"+34 971 73 33 22",
    "sg:postcode":"07013",
    "sg:province":"Islas Baleares",
    "wof:name":"Llull Servera Antonio Maria",
    "wof:placetype":"venue"
},
  "geometry": {"coordinates":[2.6341910362,39.5726356506],"type":"Point"}
}