{
  "type": "Feature",
  "properties": {
    "addr:full":"Calle de Carmen, 30 Cabezo Torres Murcia 30110",
    "addr:housenumber":"30",
    "addr:postcode":"30110",
    "addr:street":"Calle De Carmen",
    "iso:country":"ES",
    "sg:address":"Calle de Carmen, 30",
    "sg:city":"Cabezo Torres",
    "sg:orig_category":"Cajas Para Embalar",
    "sg:phone":"+34 968 85 80 10",
    "sg:postcode":"30110",
    "sg:province":"Murcia",
    "wof:name":"Cajamar",
    "wof:placetype":"venue"
},
  "geometry": {"coordinates":[-1.1250685453,38.0253067017],"type":"Point"}
}