{
  "type": "Feature",
  "properties": {
    "iso:country":"ES",
    "sg:address":"Avda Txorierri Etorbidea, 12",
    "sg:city":"Elotxelerri",
    "sg:orig_category":"Discapacitados",
    "sg:phone":"+34 944 53 59 99",
    "sg:postcode":"48180",
    "sg:province":"Vizcaya",
    "sg:website":"www.lantegi.com",
    "wof:name":"Fundacion Lantegi Batuak",
    "wof:placetype":"venue"
},
  "geometry": {"coordinates":[-2.932158947,43.3143386841],"type":"Point"}
}