{
  "type": "Feature",
  "properties": {
    "iso:country":"ES",
    "sg:address":"Plaz Santa Maria, S/n",
    "sg:city":"Mojados",
    "sg:orig_category":"Reposter\u00cdas",
    "sg:phone":"+34 983 60 70 21",
    "sg:postcode":"47250",
    "sg:province":"Valladolid",
    "wof:name":"Panificadora Cantalapiedra S.l.",
    "wof:placetype":"venue"
},
  "geometry": {"coordinates":[-4.6617069244,41.4333229065],"type":"Point"}
}