{
  "type": "Feature",
  "properties": {
    "addr:full":"Calle de Jose Siurana, 15 Castellar-oliveral Valencia 46026",
    "addr:housenumber":"15",
    "addr:postcode":"46026",
    "addr:street":"Calle De Jose Siurana",
    "iso:country":"ES",
    "sg:address":"Calle de Jose Siurana, 15",
    "sg:city":"Castellar-oliveral",
    "sg:orig_category":"Caf\u00c9s, Bares, Cervecer\u00cdas",
    "sg:phone":"+34 963 75 56 09",
    "sg:postcode":"46026",
    "sg:province":"Valencia",
    "wof:name":"Garcia Perez Pilar",
    "wof:placetype":"venue"
},
  "geometry": {"coordinates":[-0.3619610071,39.4291496277],"type":"Point"}
}