{
  "type": "Feature",
  "properties": {
    "addr:full":"Calle de Chamorro, 14 Lebrija Sevilla 41740",
    "addr:housenumber":"14",
    "addr:postcode":"41740",
    "addr:street":"Calle De Chamorro",
    "iso:country":"ES",
    "sg:address":"Calle de Chamorro, 14",
    "sg:city":"Lebrija",
    "sg:orig_category":"Partidos Pol\u00cdticos",
    "sg:phone":"+34 955 97 42 20",
    "sg:postcode":"41740",
    "sg:province":"Sevilla",
    "wof:name":"Partido Socialista Obrero Espa\u00f1ol",
    "wof:placetype":"venue"
},
  "geometry": {"coordinates":[-6.0745902061,36.9190330505],"type":"Point"}
}