{
  "type": "Feature",
  "properties": {
    "iso:country":"ES",
    "sg:address":"Calle de Leones, 36",
    "sg:city":"Valencia",
    "sg:orig_category":"Congelados: Productos Alimentarios (al Por Menor)",
    "sg:phone":"+34 963 55 10 45",
    "sg:postcode":"46022",
    "sg:province":"Valencia",
    "wof:name":"Congelados Canomar S. L.",
    "wof:placetype":"venue"
},
  "geometry": {"coordinates":[-0.3476369977,39.4675979614],"type":"Point"}
}