{
  "type": "Feature",
  "properties": {
    "iso:country":"ES",
    "sg:address":"Av Fabraquer, 75",
    "sg:city":"Playa Muchavista",
    "sg:orig_category":"Empresas De Carpinter\u00cda Met\u00c1lica",
    "sg:phone":"+34 965 94 38 70",
    "sg:postcode":"03560",
    "sg:province":"Alicante",
    "wof:name":"Molina Galiana Francisco",
    "wof:placetype":"venue"
},
  "geometry": {"coordinates":[-0.4127990007,38.4001235962],"type":"Point"}
}