{
  "type": "Feature",
  "properties": {
    "iso:country":"ES",
    "sg:address":"Dos Hermanas-bi Ahizpe Kalea, 9",
    "sg:city":"Irurtzun",
    "sg:orig_category":"Inform\u00c1tica, Ofim\u00c1tica (estudios, Asesor\u00cda, Ingenier\u00cda, Formaci\u00d3n)",
    "sg:phone":"+34 948 60 06 29",
    "sg:postcode":"31860",
    "sg:province":"Navarra",
    "sg:website":"www.kateinformatica.com",
    "wof:name":"Kate Informatica",
    "wof:placetype":"venue"
},
  "geometry": {"coordinates":[-1.8296530247,42.9196586609],"type":"Point"}
}