{
  "type": "Feature",
  "properties": {
    "iso:country":"ES",
    "sg:address":"Calle de Magisterio, 7",
    "sg:city":"Santa Eulalia",
    "sg:orig_category":"Asociaciones Humanitarias, De Cooperaci\u00d3n, De Acci\u00d3n Social",
    "sg:phone":"+34 978 86 08 22",
    "sg:postcode":"44360",
    "sg:province":"Teruel",
    "wof:name":"Ayuntamiento De Santa Eulalia",
    "wof:placetype":"venue"
},
  "geometry": {"coordinates":[-1.314563036,40.5694732666],"type":"Point"}
}