{
  "type": "Feature",
  "properties": {
    "addr:full":"Calle de General Gomez Nu\u00d1ez, 26 Ponferrada Le\u00f3n 24400",
    "addr:housenumber":"26",
    "addr:postcode":"24400",
    "addr:street":"Calle De General Gomez Nun\u0303Ez",
    "iso:country":"ES",
    "sg:address":"Calle de General Gomez Nu\u00d1ez, 26",
    "sg:city":"Ponferrada",
    "sg:orig_category":"Ense\u00d1anza, Formaci\u00d3n Profesional: Aprendizaje",
    "sg:phone":"+34 987 41 03 92",
    "sg:postcode":"24400",
    "sg:province":"Le\u00f3n",
    "wof:name":"Comunidad De Regantes Canal Bajo Del Bierzo",
    "wof:placetype":"venue"
},
  "geometry": {"coordinates":[-6.599293232,42.5502243042],"type":"Point"}
}