{
  "type": "Feature",
  "properties": {
    "iso:country":"ES",
    "sg:address":"Av Garraf, 28",
    "sg:city":"Vilanova I La Geltru",
    "sg:orig_category":"Bazares, Art\u00cdculos De Limpieza Y De Cocina (al Por Menor)",
    "sg:phone":"+34 938 14 22 99",
    "sg:postcode":"08800",
    "sg:province":"Barcelona",
    "wof:name":"Ying  Shanyan",
    "wof:placetype":"venue"
},
  "geometry": {"coordinates":[1.7296965122,41.2229537964],"type":"Point"}
}