{
  "type": "Feature",
  "properties": {
    "iso:country":"ES",
    "sg:address":"Avda Vi\u00d1uela (de La), 21",
    "sg:city":"Cordoba",
    "sg:orig_category":"Peluquer\u00cdas, Peluquer\u00cda Mixta",
    "sg:phone":"+34 957 26 95 01",
    "sg:postcode":"14010",
    "sg:province":"C\u00f3rdoba",
    "wof:name":"Rujula Redondo Juan",
    "wof:placetype":"venue"
},
  "geometry": {"coordinates":[-4.7626662254,37.8894538879],"type":"Point"}
}