{
  "type": "Feature",
  "properties": {
    "addr:full":"Calle de Doctor Esquerdo, 31 Madrid Madrid 28028",
    "addr:housenumber":"31",
    "addr:postcode":"madrid;28028",
    "addr:street":"Calle De Doctor Esquerdo",
    "iso:country":"ES",
    "sg:address":"Calle de Doctor Esquerdo, 31",
    "sg:city":"Madrid",
    "sg:orig_category":"Aparcamientos (infraestructuras, Accesorios)",
    "sg:phone":"+34 913 55 13 43",
    "sg:postcode":"28028",
    "sg:province":"Madrid",
    "wof:name":"Garaje Dr. Esquerdo S. A.",
    "wof:placetype":"venue"
},
  "geometry": {"coordinates":[-3.6685738564,40.4250411987],"type":"Point"}
}