{
  "type": "Feature",
  "properties": {
    "addr:full":"C/ Joan Segura, 7 Manacor Islas Baleares 07500",
    "addr:housenumber":"7",
    "addr:postcode":"07500",
    "addr:street":"C / Joan Segura",
    "iso:country":"ES",
    "sg:address":"C/ Joan Segura, 7",
    "sg:city":"Manacor",
    "sg:orig_category":"Talleres: Ropa A Medida",
    "sg:phone":"+34 971 55 60 12",
    "sg:postcode":"07500",
    "sg:province":"Islas Baleares",
    "wof:name":"Rafael Llado E Hijos S.l.",
    "wof:placetype":"venue"
},
  "geometry": {"coordinates":[3.2096710205,39.568397522],"type":"Point"}
}