{
  "type": "Feature",
  "properties": {
    "addr:full":"Calle de Ejido De San Juan, 62 Almagro Ciudad Real 13270",
    "addr:housenumber":"62",
    "addr:postcode":"13270",
    "addr:street":"Calle De Ejido De San Juan",
    "iso:country":"ES",
    "sg:address":"Calle de Ejido De San Juan, 62",
    "sg:city":"Almagro",
    "sg:orig_category":"Mec\u00c1nico Del Autom\u00d3vil",
    "sg:phone":"+34 926 86 07 23",
    "sg:postcode":"13270",
    "sg:province":"Ciudad Real",
    "wof:name":"Alvaro Buendia Manuel",
    "wof:placetype":"venue"
},
  "geometry": {"coordinates":[-3.7075695992,38.8856773376],"type":"Point"}
}