{
  "type": "Feature",
  "properties": {
    "addr:full":"Avda Oviedo De, 6 Cangas Narcea Asturias 33800",
    "addr:postcode":"33800",
    "addr:street":"Avda Oviedo De",
    "iso:country":"ES",
    "sg:address":"Avda Oviedo De, 6",
    "sg:city":"Cangas Narcea",
    "sg:orig_category":"Chapister\u00cda",
    "sg:phone":"+34 985 81 21 95",
    "sg:postcode":"33800",
    "sg:province":"Asturias",
    "wof:name":"Fernandez Rodriguez Alfredo",
    "wof:placetype":"venue"
},
  "geometry": {"coordinates":[-6.5502290726,43.1801643372],"type":"Point"}
}