{
  "type": "Feature",
  "properties": {
    "addr:full":"Calle de Alfarerias Bajas, 9 Villarrobledo Albacete 02600",
    "addr:housenumber":"9",
    "addr:postcode":"02600",
    "addr:street":"Calle De Alfarerias Bajas",
    "iso:country":"ES",
    "sg:address":"Calle de Alfarerias Bajas, 9",
    "sg:city":"Villarrobledo",
    "sg:orig_category":"Ropa Para Se\u00d1oras (al Por Menor)",
    "sg:phone":"+34 967 14 11 92",
    "sg:postcode":"02600",
    "sg:province":"Albacete",
    "wof:name":"Rojas Gomez Maria Isabel",
    "wof:placetype":"venue"
},
  "geometry": {"coordinates":[-2.6028199196,39.2677726746],"type":"Point"}
}