{
  "type": "Feature",
  "properties": {
    "addr:full":"Kontzezino Kalea, 2 Arrasate Guip\u00f9zcoa 20500",
    "addr:housenumber":"2",
    "addr:postcode":"20500",
    "addr:street":"Kontzezino Kalea;Guipu\u0300Zcoa",
    "iso:country":"ES",
    "sg:address":"Kontzezino Kalea, 2",
    "sg:city":"Arrasate",
    "sg:orig_category":"Agencias De Viajes",
    "sg:phone":"+34 943 79 14 06",
    "sg:postcode":"20500",
    "sg:province":"Guip\u00f9zcoa",
    "wof:name":"Viajes Ecuador S. A.",
    "wof:placetype":"venue"
},
  "geometry": {"coordinates":[-2.4918580055,43.0629463196],"type":"Point"}
}