{
  "type": "Feature",
  "properties": {
    "addr:full":"Carrer de Alcoi, 5 Xixona Alicante 03100",
    "addr:housenumber":"5",
    "addr:postcode":"03100",
    "addr:street":"Carrer De Alcoi",
    "iso:country":"ES",
    "sg:address":"Carrer de Alcoi, 5",
    "sg:city":"Xixona",
    "sg:orig_category":"Molduras, Junquillos, Listones Y Molduras Perforadas",
    "sg:phone":"+34 965 61 14 74",
    "sg:postcode":"03100",
    "sg:province":"Alicante",
    "wof:name":"Tallon Montoza Manuel",
    "wof:placetype":"venue"
},
  "geometry": {"coordinates":[-0.5068849921,38.539188385],"type":"Point"}
}