{
  "type": "Feature",
  "properties": {
    "iso:country":"ES",
    "sg:address":"Calle de Colon, 7",
    "sg:city":"Torre-pacheco",
    "sg:orig_category":"Servicios De Telecomunicaciones",
    "sg:phone":"+34 968 33 61 02",
    "sg:postcode":"30700",
    "sg:province":"Murcia",
    "wof:name":"Xtra Telecom S.a.",
    "wof:placetype":"venue"
},
  "geometry": {"coordinates":[-1.1613080502,38.0112113953],"type":"Point"}
}