{
  "type": "Feature",
  "properties": {
    "iso:country":"ES",
    "sg:address":"Calle de General Bellod, 4",
    "sg:city":"Villena",
    "sg:orig_category":"Papeler\u00cdas, Librer\u00cdas",
    "sg:phone":"+34 965 80 76 88",
    "sg:postcode":"03400",
    "sg:province":"Alicante",
    "wof:name":"Libreria Itaca C.b.",
    "wof:placetype":"venue"
},
  "geometry": {"coordinates":[-0.8636490107,38.6326675415],"type":"Point"}
}