{
  "type": "Feature",
  "properties": {
    "addr:full":"Calle de Jacinto Benavente, S/n Marbella M\u00e1laga 29600",
    "addr:housenumber":"s / n",
    "addr:postcode":"29600",
    "addr:street":"Calle De Jacinto Benavente;Ma\u0301Laga",
    "iso:country":"ES",
    "sg:address":"Calle de Jacinto Benavente, S/n",
    "sg:city":"Marbella",
    "sg:orig_category":"Agencias De Viajes",
    "sg:phone":"+34 952 77 92 03",
    "sg:postcode":"29600",
    "sg:province":"M\u00e1laga",
    "wof:name":"Lima Y Carrasco S.l.l.",
    "wof:placetype":"venue"
},
  "geometry": {"coordinates":[-4.8888840675,36.511100769],"type":"Point"}
}