{
  "type": "Feature",
  "properties": {
    "addr:full":"Calle de Alfredo Vicenti, 6 Coru\u00d1a A Coru\u00f1a 15004",
    "addr:housenumber":"6",
    "addr:postcode":"15004",
    "addr:street":"Calle De Alfredo Vicenti;Corun\u0303A",
    "iso:country":"ES",
    "sg:address":"Calle de Alfredo Vicenti, 6",
    "sg:city":"Coru\u00d1a",
    "sg:orig_category":"M\u00c9dicos: Oftalmolog\u00cda",
    "sg:phone":"+34 981 14 33 00",
    "sg:postcode":"15004",
    "sg:province":"A Coru\u00f1a",
    "wof:name":"Santos Insua Luis",
    "wof:placetype":"venue"
},
  "geometry": {"coordinates":[-8.410077095,43.3670692444],"type":"Point"}
}