{
  "type": "Feature",
  "properties": {
    "iso:country":"ES",
    "sg:address":"Ctra Hellin, Km. 0004,0",
    "sg:city":"Jumilla",
    "sg:orig_category":"Centro De Estudios",
    "sg:phone":"+34 968 43 50 57",
    "sg:postcode":"30520",
    "sg:province":"Murcia",
    "wof:name":"Compost Reciclables S.a.",
    "wof:placetype":"venue"
},
  "geometry": {"coordinates":[-1.3222140074,38.4765434265],"type":"Point"}
}