{
  "type": "Feature",
  "properties": {
    "iso:country":"ES",
    "sg:address":"Avda Borbolla (la), 53",
    "sg:city":"Sevilla",
    "sg:orig_category":"Administraci\u00d3n En Agricultura",
    "sg:phone":"+34 954 23 14 40",
    "sg:postcode":"41013",
    "sg:province":"Sevilla",
    "wof:name":"Gabinete De Iniciativas Europeas S.a.",
    "wof:placetype":"venue"
},
  "geometry": {"coordinates":[-5.9852900505,37.3727340698],"type":"Point"}
}