{
  "type": "Feature",
  "properties": {
    "iso:country":"ES",
    "sg:address":"Ctra. Santo Tome, 43",
    "sg:city":"Peal Becerro",
    "sg:orig_category":"Empresas De Carpinter\u00cda De Madera",
    "sg:phone":"+34 953 73 01 28",
    "sg:postcode":"23460",
    "sg:province":"Ja\u00e9n",
    "wof:name":"Almansa Perez Manuel Ildefonso",
    "wof:placetype":"venue"
},
  "geometry": {"coordinates":[-3.0070667267,37.9148292542],"type":"Point"}
}