{
  "type": "Feature",
  "properties": {
    "iso:country":"ES",
    "sg:address":"Calle de Acisclo Diaz, 9",
    "sg:city":"San Nicolas",
    "sg:orig_category":"Agencias Y Asesores De Publicidad",
    "sg:phone":"+34 968 29 58 81",
    "sg:postcode":"30005",
    "sg:province":"Murcia",
    "wof:name":"Nical Comunicacion S.l.",
    "wof:placetype":"venue"
},
  "geometry": {"coordinates":[-1.1357518435,37.9878425598],"type":"Point"}
}