{
  "type": "Feature",
  "properties": {
    "iso:country":"ES",
    "sg:address":"Calle de Cipres, 12",
    "sg:city":"Granada",
    "sg:orig_category":"Traductores",
    "sg:phone":"+34 958 20 77 12",
    "sg:postcode":"18010",
    "sg:province":"Granada",
    "wof:name":"Adtrad Traducciones S.c.a.",
    "wof:placetype":"venue"
},
  "geometry": {"coordinates":[-3.5900011063,37.1899719238],"type":"Point"}
}