{
  "type": "Feature",
  "properties": {
    "addr:full":"C/ L'esglesia, 7 Paterna Valencia 46980",
    "addr:housenumber":"7",
    "addr:postcode":"46980",
    "addr:street":"C / L'Esglesia",
    "iso:country":"ES",
    "sg:address":"C/ L'esglesia, 7",
    "sg:city":"Paterna",
    "sg:orig_category":"Abogados",
    "sg:phone":"+34 961 38 56 50",
    "sg:postcode":"46980",
    "sg:province":"Valencia",
    "wof:name":"Lopez Rodado Jesus",
    "wof:placetype":"venue"
},
  "geometry": {"coordinates":[-0.4406276047,39.5005874634],"type":"Point"}
}