{
  "type": "Feature",
  "properties": {
    "iso:country":"ES",
    "sg:address":"Carr Ferran Rambla, 32",
    "sg:city":"Lleida",
    "sg:orig_category":"Centros Empresariales",
    "sg:phone":"+34 973 22 41 62",
    "sg:postcode":"25007",
    "sg:province":"Lleida",
    "wof:name":"Organitzacions Empresarials De Lleida Fundacio Privada",
    "wof:placetype":"venue"
},
  "geometry": {"coordinates":[0.627129972,41.6145210266],"type":"Point"}
}