{
  "type": "Feature",
  "properties": {
    "addr:full":"Calle de Hurtado, 23 Jaen Ja\u00e9n 23001",
    "addr:housenumber":"23;jae\u0301n",
    "addr:postcode":"23001",
    "addr:street":"Calle De Hurtado",
    "iso:country":"ES",
    "sg:address":"Calle de Hurtado, 23",
    "sg:city":"Jaen",
    "sg:orig_category":"Agencias Y Agentes Comerciales, Representantes",
    "sg:phone":"+34 953 24 37 09",
    "sg:postcode":"23001",
    "sg:province":"Ja\u00e9n",
    "wof:name":"Castillo Delgado Angel",
    "wof:placetype":"venue"
},
  "geometry": {"coordinates":[-3.7875139713,37.7665023804],"type":"Point"}
}