{
  "type": "Feature",
  "properties": {
    "iso:country":"ES",
    "sg:address":"Ctra Muel, S/n",
    "sg:city":"Epila",
    "sg:orig_category":"Construcciones Met\u00c1licas",
    "sg:phone":"+34 976 60 38 79",
    "sg:postcode":"50290",
    "sg:province":"Zaragoza",
    "wof:name":"Talleres Osorio S.l.",
    "wof:placetype":"venue"
},
  "geometry": {"coordinates":[-1.2849140167,41.6030502319],"type":"Point"}
}