{
  "type": "Feature",
  "properties": {
    "addr:full":"Calle de Preciados, 13 Madrid Madrid 28013",
    "addr:housenumber":"13",
    "addr:postcode":"madrid;28013",
    "addr:street":"Calle De Preciados",
    "iso:country":"ES",
    "sg:address":"Calle de Preciados, 13",
    "sg:city":"Madrid",
    "sg:orig_category":"Relojer\u00cda (al Por Menor, Reparaci\u00d3n)",
    "sg:phone":"+34 915 22 96 84",
    "sg:postcode":"28013",
    "sg:province":"Madrid",
    "wof:name":"Lopez Perez Manuela",
    "wof:placetype":"venue"
},
  "geometry": {"coordinates":[-3.7051570415,40.4186859131],"type":"Point"}
}