{
  "type": "Feature",
  "properties": {
    "addr:full":"Cmno Torreon (el), S/n Rechazos Santa Cruz De Tenerife 38311",
    "addr:postcode":"38311",
    "addr:street":"Cmno Torreon El S / N Rechazos",
    "iso:country":"ES",
    "sg:address":"Cmno Torreon (el), S/n",
    "sg:city":"Rechazos",
    "sg:orig_category":"Flores Y Plantas Naturales (al Por Mayor)",
    "sg:phone":"+34 922 32 61 65",
    "sg:postcode":"38311",
    "sg:province":"Santa Cruz De Tenerife",
    "sg:website":"www.eldraguito.com",
    "wof:name":"El Draguito S.l.",
    "wof:placetype":"venue"
},
  "geometry": {"coordinates":[-16.4920082092,28.3700504303],"type":"Point"}
}