{
  "type": "Feature",
  "properties": {
    "addr:full":"Avda Espa\u00d1a, S/n Segorbe Castell\u00f3n 12400",
    "addr:housenumber":"s / n",
    "addr:postcode":"12400",
    "addr:street":"Avda Espan\u0303A",
    "iso:country":"ES",
    "sg:address":"Avda Espa\u00d1a, S/n",
    "sg:city":"Segorbe",
    "sg:orig_category":"Supermercados Y Hipermercados",
    "sg:phone":"+34 964 71 21 17",
    "sg:postcode":"12400",
    "sg:province":"Castell\u00f3n",
    "wof:name":"Consum Sociedad Cooperativa Limitada",
    "wof:placetype":"venue"
},
  "geometry": {"coordinates":[-0.4834690094,39.8461456299],"type":"Point"}
}