{
  "type": "Feature",
  "properties": {
    "addr:full":"Avda Alt Rei En Jaume I (l'), 8 Altea Alicante 03590",
    "addr:housenumber":"8",
    "addr:postcode":"03590",
    "addr:street":"Avda Alt Rei En Jaume I L '",
    "iso:country":"ES",
    "sg:address":"Avda Alt Rei En Jaume I (l'), 8",
    "sg:city":"Altea",
    "sg:orig_category":"Droguer\u00cdas (al Por Menor)",
    "sg:phone":"+34 965 84 56 28",
    "sg:postcode":"03590",
    "sg:province":"Alicante",
    "wof:name":"Lloret Vaello Luisa",
    "wof:placetype":"venue"
},
  "geometry": {"coordinates":[-0.0480649993,38.6009597778],"type":"Point"}
}