{
  "type": "Feature",
  "properties": {
    "addr:full":"Los Rosales, 52 Coria C\u00e1ceres 10800",
    "addr:housenumber":"52",
    "addr:postcode":"10800",
    "addr:street":"Los Rosales;Ca\u0301Ceres",
    "iso:country":"ES",
    "sg:address":"Los Rosales, 52",
    "sg:city":"Coria",
    "sg:orig_category":"Chapister\u00cda",
    "sg:phone":"+34 927 50 60 36",
    "sg:postcode":"10800",
    "sg:province":"C\u00e1ceres",
    "wof:name":"Benitez Luis Manuel",
    "wof:placetype":"venue"
},
  "geometry": {"coordinates":[-6.5260438919,39.9898147583],"type":"Point"}
}