{
  "type": "Feature",
  "properties": {
    "iso:country":"ES",
    "sg:address":"Calle de Marcelo Usera, 46",
    "sg:city":"Madrid",
    "sg:orig_category":"Ropa Para Ni\u00d1os (al Por Menor)",
    "sg:phone":"+34 913 92 04 13",
    "sg:postcode":"28026",
    "sg:province":"Madrid",
    "wof:name":"Lopez Leal Ana",
    "wof:placetype":"venue"
},
  "geometry": {"coordinates":[-3.7029912472,40.3860969543],"type":"Point"}
}