{
  "type": "Feature",
  "properties": {
    "iso:country":"ES",
    "sg:address":"Avgd Prat De La Riba, 31",
    "sg:city":"Lleida",
    "sg:orig_category":"Abogados",
    "sg:phone":"+34 973 24 42 26",
    "sg:postcode":"25008",
    "sg:province":"Lleida",
    "wof:name":"Antonijuan Moya Francisco",
    "wof:placetype":"venue"
},
  "geometry": {"coordinates":[0.623178184,41.6207771301],"type":"Point"}
}