{
  "type": "Feature",
  "properties": {
    "iso:country":"ES",
    "sg:address":"Calle de Palencia, 7",
    "sg:city":"Granada",
    "sg:orig_category":"Confecci\u00d3n (fabricaci\u00d3n, Al Por Mayor)",
    "sg:phone":"+34 958 12 51 53",
    "sg:postcode":"18007",
    "sg:province":"Granada",
    "wof:name":"Garcia Torrico Vicente",
    "wof:placetype":"venue"
},
  "geometry": {"coordinates":[-3.5985589027,37.1602172852],"type":"Point"}
}