{
  "type": "Feature",
  "properties": {
    "iso:country":"ES",
    "sg:address":"Carrer de Doctor Reig, 61",
    "sg:city":"Viladecans",
    "sg:orig_category":"Fabricaci\u00d3n De Cortinas Y Visillos",
    "sg:phone":"+34 936 58 10 03",
    "sg:postcode":"08840",
    "sg:province":"Barcelona",
    "wof:name":"Rayo Franco Maria Del Mar",
    "wof:placetype":"venue"
},
  "geometry": {"coordinates":[2.0138919353,41.3185157776],"type":"Point"}
}