{
  "type": "Feature",
  "properties": {
    "iso:country":"ES",
    "sg:address":"Carrer de Alzinar, 71",
    "sg:city":"Alzinar",
    "sg:orig_category":"Jardiner\u00cdas, Vegetales, Art\u00cdculos De Jardiner\u00cda (al Por Menor)",
    "sg:phone":"+34 938 97 94 61",
    "sg:postcode":"08736",
    "sg:province":"Barcelona",
    "wof:name":"Celtics Obert Jardiners S.l",
    "wof:placetype":"venue"
},
  "geometry": {"coordinates":[1.6463429928,41.4202232361],"type":"Point"}
}