{
  "type": "Feature",
  "properties": {
    "iso:country":"ES",
    "sg:address":"Kale Nagusia, 4",
    "sg:city":"Hernani",
    "sg:orig_category":"Molduras, Junquillos, Listones Y Molduras Perforadas",
    "sg:phone":"+34 943 55 00 26",
    "sg:postcode":"20120",
    "sg:province":"Guip\u00f9zcoa",
    "wof:name":"Loran Sarriegui Jose Maria",
    "wof:placetype":"venue"
},
  "geometry": {"coordinates":[-1.9495501518,43.280582428],"type":"Point"}
}