{
  "type": "Feature",
  "properties": {
    "addr:full":"Calle de Alhondiga, 6 Granada Granada 18001",
    "addr:housenumber":"6",
    "addr:postcode":"18001",
    "addr:street":"Calle De Alhondiga",
    "iso:country":"ES",
    "sg:address":"Calle de Alhondiga, 6",
    "sg:city":"Granada",
    "sg:orig_category":"Asesor\u00cda Fiscal Y Jur\u00cddica",
    "sg:phone":"+34 958 26 79 62",
    "sg:postcode":"18001",
    "sg:province":"Granada",
    "wof:name":"Salinas Y Espigares Asesores S.l.",
    "wof:placetype":"venue"
},
  "geometry": {"coordinates":[-3.600748539,37.1738510132],"type":"Point"}
}