{
  "type": "Feature",
  "properties": {
    "iso:country":"ES",
    "sg:address":"Carme Rius(la Torre), 26",
    "sg:city":"S. Gregori",
    "sg:orig_category":"Carnes De Carnicer\u00cda (al Por Mayor)",
    "sg:phone":"+34 972 42 88 34",
    "sg:postcode":"17150",
    "sg:province":"Girona",
    "wof:name":"Agropecuaria San Esteban S.l.",
    "wof:placetype":"venue"
},
  "geometry": {"coordinates":[2.8236999512,41.9817962646],"type":"Point"}
}