{
  "type": "Feature",
  "properties": {
    "iso:country":"ES",
    "sg:address":"Calle de Veinticinco De Diciembre, 9",
    "sg:city":"Sestao",
    "sg:orig_category":"Peluqueros: De Se\u00d1oras",
    "sg:phone":"+34 944 96 37 15",
    "sg:postcode":"48910",
    "sg:province":"Vizcaya",
    "wof:name":"Peluqueria Maria Victoria Carrasco",
    "wof:placetype":"venue"
},
  "geometry": {"coordinates":[-3.0045268536,43.3105812073],"type":"Point"}
}