{
  "type": "Feature",
  "properties": {
    "addr:full":"Co. Apeadero, 7 Moreruela Infanzones Zamora 49731",
    "addr:housenumber":"7",
    "addr:postcode":"49731",
    "addr:street":"Apeadero",
    "iso:country":"ES",
    "sg:address":"Co. Apeadero, 7",
    "sg:city":"Moreruela Infanzones",
    "sg:orig_category":"Cr\u00cda De Animales",
    "sg:phone":"+34 980 50 45 37",
    "sg:postcode":"49731",
    "sg:province":"Zamora",
    "wof:name":"Fariza Aliste Segundo",
    "wof:placetype":"venue"
},
  "geometry": {"coordinates":[-5.7055487633,41.6316719055],"type":"Point"}
}