{
  "type": "Feature",
  "properties": {
    "addr:full":"Carrer de Aleixar (cami De L'), 42 Reus Tarragona 43202",
    "addr:housenumber":"42",
    "addr:postcode":"43202",
    "addr:street":"Carrer De Aleixar Cami De L '",
    "iso:country":"ES",
    "sg:address":"Carrer de Aleixar (cami De L'), 42",
    "sg:city":"Reus",
    "sg:orig_category":"Loter\u00cda Y T\u00d3mbola",
    "sg:phone":"+34 977 31 24 51",
    "sg:postcode":"43202",
    "sg:province":"Tarragona",
    "wof:name":"Vila Mestres Octavio",
    "wof:placetype":"venue"
},
  "geometry": {"coordinates":[1.1000570059,41.1570053101],"type":"Point"}
}