{
  "type": "Feature",
  "properties": {
    "iso:country":"ES",
    "sg:address":"Calle de Castillo, 41",
    "sg:city":"Alcorisa",
    "sg:orig_category":"Pensiones Familiares",
    "sg:phone":"+34 978 88 31 62",
    "sg:postcode":"44550",
    "sg:province":"Teruel",
    "wof:name":"Rebalsal S.l.",
    "wof:placetype":"venue"
},
  "geometry": {"coordinates":[-0.3831565976,40.8907432556],"type":"Point"}
}