{
  "type": "Feature",
  "properties": {
    "addr:full":"Calle de Almeria (de), 3 Humanes De Madrid Madrid 28970",
    "addr:postcode":"28970",
    "addr:street":"Calle De Almeria De 3",
    "iso:country":"ES",
    "sg:address":"Calle de Almeria (de), 3",
    "sg:city":"Humanes De Madrid",
    "sg:orig_category":"Muebles, Minoristas",
    "sg:phone":"+34 916 97 78 01",
    "sg:postcode":"28970",
    "sg:province":"Madrid",
    "wof:name":"Tradismonsa S.l.",
    "wof:placetype":"venue"
},
  "geometry": {"coordinates":[-3.8177239895,40.2746429443],"type":"Point"}
}