{
  "type": "Feature",
  "properties": {
    "iso:country":"ES",
    "sg:address":"Calle de Cottolengo, 17",
    "sg:city":"San Vicente Del Raspeig-sant Vicent Del Raspeig",
    "sg:orig_category":"Alquiler De Casas Y Habitaciones Amuebladas",
    "sg:phone":"+34 965 67 43 48",
    "sg:postcode":"03690",
    "sg:province":"Alicante",
    "wof:name":"Frutas Puche S. L.",
    "wof:placetype":"venue"
},
  "geometry": {"coordinates":[-0.5082728863,38.3876266479],"type":"Point"}
}