{
  "type": "Feature",
  "properties": {
    "addr:full":"Calle de Literato Azorin, 18 Mislata Valencia 46920",
    "addr:housenumber":"18",
    "addr:postcode":"46920",
    "addr:street":"Calle De Literato Azorin",
    "iso:country":"ES",
    "sg:address":"Calle de Literato Azorin, 18",
    "sg:city":"Mislata",
    "sg:orig_category":"Bisuter\u00cda, Joyer\u00cda, Relojer\u00cda (al Por Menor)",
    "sg:phone":"+34 963 83 42 90",
    "sg:postcode":"46920",
    "sg:province":"Valencia",
    "wof:name":"Frias Perez Julian",
    "wof:placetype":"venue"
},
  "geometry": {"coordinates":[-0.4168780148,39.47315979],"type":"Point"}
}