{
  "type": "Feature",
  "properties": {
    "addr:full":"Calle de Escuelas (de Las), 2 Alamo Madrid 28607",
    "addr:housenumber":"2",
    "addr:postcode":"28607",
    "addr:street":"Calle De Escuelas De Las",
    "iso:country":"ES",
    "sg:address":"Calle de Escuelas (de Las), 2",
    "sg:city":"Alamo",
    "sg:orig_category":"Inmobiliaria (agencias)",
    "sg:phone":"+34 918 12 01 57",
    "sg:postcode":"28607",
    "sg:province":"Madrid",
    "wof:name":"Alongar Gestion Inmobiliaria S.l.",
    "wof:placetype":"venue"
},
  "geometry": {"coordinates":[-3.9931342602,40.2295455933],"type":"Point"}
}