{
  "type": "Feature",
  "properties": {
    "addr:full":"Ctra Prats De Llu\u00c7anes, S/n Vic Barcelona 08500",
    "addr:housenumber":"s",
    "addr:postcode":"08500",
    "addr:street":"Ctra Prats De Lluc\u0327Anes;/ N",
    "iso:country":"ES",
    "sg:address":"Ctra Prats De Llu\u00c7anes, S/n",
    "sg:city":"Vic",
    "sg:orig_category":"Productos Qu\u00cdmicos (fabricaci\u00d3n, Al Por Mayor)",
    "sg:phone":"+34 938 89 58 33",
    "sg:postcode":"08500",
    "sg:province":"Barcelona",
    "wof:name":"Diprotel S.a.",
    "wof:placetype":"venue"
},
  "geometry": {"coordinates":[2.2550199032,41.9312210083],"type":"Point"}
}