{
  "type": "Feature",
  "properties": {
    "iso:country":"ES",
    "sg:address":"Calle de Veracruz, 14",
    "sg:city":"Torreperogil",
    "sg:orig_category":"Molduras, Junquillos, Listones Y Molduras Perforadas",
    "sg:phone":"+34 953 77 83 34",
    "sg:postcode":"23320",
    "sg:province":"Ja\u00e9n",
    "wof:name":"Martinez Revert Juan Antonio",
    "wof:placetype":"venue"
},
  "geometry": {"coordinates":[-3.2926659584,38.0340499878],"type":"Point"}
}