{
  "type": "Feature",
  "properties": {
    "addr:full":"Trva Las Minas, 15 Navalmoral Mata C\u00e1ceres 10300",
    "addr:housenumber":"15",
    "addr:postcode":"10300",
    "addr:street":"Trva Las Minas;Ca\u0301Ceres",
    "iso:country":"ES",
    "sg:address":"Trva Las Minas, 15",
    "sg:city":"Navalmoral Mata",
    "sg:orig_category":"Transportes Por V\u00cdas Navegables",
    "sg:phone":"+34 927 53 15 66",
    "sg:postcode":"10300",
    "sg:province":"C\u00e1ceres",
    "wof:name":"Garcia Lopez Santiago",
    "wof:placetype":"venue"
},
  "geometry": {"coordinates":[-5.5365791321,39.8891105652],"type":"Point"}
}