{
  "type": "Feature",
  "properties": {
    "addr:full":"Calle de Pasos, 19 Argamasilla Alba Ciudad Real 13710",
    "addr:housenumber":"19",
    "addr:postcode":"alba;13710",
    "addr:street":"Calle De Pasos",
    "iso:country":"ES",
    "sg:address":"Calle de Pasos, 19",
    "sg:city":"Argamasilla Alba",
    "sg:orig_category":"Electricidad: Instaladores",
    "sg:phone":"+34 926 52 13 15",
    "sg:postcode":"13710",
    "sg:province":"Ciudad Real",
    "wof:name":"Gabaldon Tebar Ricardo",
    "wof:placetype":"venue"
},
  "geometry": {"coordinates":[-3.1016900539,39.125164032],"type":"Point"}
}