{
  "type": "Feature",
  "properties": {
    "addr:full":"Av Masnou, 45 Hospitalet Llobregat Barcelona 08905",
    "addr:housenumber":"45",
    "addr:postcode":"08905",
    "addr:street":"Av Masnou",
    "iso:country":"ES",
    "sg:address":"Av Masnou, 45",
    "sg:city":"Hospitalet Llobregat",
    "sg:orig_category":"Zapatos (al Por Menor)",
    "sg:phone":"+34 933 34 87 42",
    "sg:postcode":"08905",
    "sg:province":"Barcelona",
    "wof:name":"Alfonso Sigalat Norberto",
    "wof:placetype":"venue"
},
  "geometry": {"coordinates":[2.1076383591,41.3697357178],"type":"Point"}
}