{
  "type": "Feature",
  "properties": {
    "iso:country":"ES",
    "sg:address":"Av Catalunya, 26",
    "sg:city":"S. Adria Besos",
    "sg:orig_category":"Zapatos (al Por Menor)",
    "sg:phone":"+34 934 62 01 22",
    "sg:postcode":"08930",
    "sg:province":"Barcelona",
    "wof:name":"Comercial Distribuidora De Calzado S.a.",
    "wof:placetype":"venue"
},
  "geometry": {"coordinates":[2.2167599201,41.4316978455],"type":"Point"}
}