{
  "type": "Feature",
  "properties": {
    "iso:country":"ES",
    "sg:address":"Calle de Botica (la), 7",
    "sg:city":"Rubio",
    "sg:orig_category":"Geolog\u00cda Y Geof\u00cdsica",
    "sg:phone":"+34 955 82 80 21",
    "sg:postcode":"41568",
    "sg:province":"Sevilla",
    "wof:name":"Romero Monta\u00f1o Manuel",
    "wof:placetype":"venue"
},
  "geometry": {"coordinates":[-4.9891295433,37.3558807373],"type":"Point"}
}