{
  "type": "Feature",
  "properties": {
    "addr:full":"Calle de Colon, 9 Alberic Valencia 46260",
    "addr:housenumber":"9",
    "addr:postcode":"46260",
    "addr:street":"Calle De Colon",
    "iso:country":"ES",
    "sg:address":"Calle de Colon, 9",
    "sg:city":"Alberic",
    "sg:orig_category":"Notarios",
    "sg:phone":"+34 962 44 02 03",
    "sg:postcode":"46260",
    "sg:province":"Valencia",
    "wof:name":"Peydro De Moya Amador Esteban",
    "wof:placetype":"venue"
},
  "geometry": {"coordinates":[-0.5199036002,39.1173553467],"type":"Point"}
}