{
  "type": "Feature",
  "properties": {
    "iso:country":"ES",
    "sg:address":"Calle de Doctor Fleming, 26",
    "sg:city":"Arucas",
    "sg:orig_category":"Alumbrados",
    "sg:phone":"+34 928 63 34 75",
    "sg:postcode":"35400",
    "sg:province":"Las Palmas",
    "wof:name":"Show Tecni Canarias S.l.",
    "wof:placetype":"venue"
},
  "geometry": {"coordinates":[-15.5223064423,28.1210021973],"type":"Point"}
}