{
  "type": "Feature",
  "properties": {
    "addr:full":"Avda Miguel Rodriguez Bautista, 22 Santa Uxia De Ribeira La Coru\u00f1a 15960",
    "addr:housenumber":"22",
    "addr:postcode":"15960",
    "addr:street":"Avda Miguel Rodriguez Bautista;Corun\u0303A",
    "iso:country":"ES",
    "sg:address":"Avda Miguel Rodriguez Bautista, 22",
    "sg:city":"Santa Uxia De Ribeira",
    "sg:orig_category":"Ense\u00d1anza, Formaci\u00d3n Profesional: Aprendizaje",
    "sg:phone":"+34 981 87 32 58",
    "sg:postcode":"15960",
    "sg:province":"La Coru\u00f1a",
    "wof:name":"Colexio De Educacion Infantil E Primaria O Grupo",
    "wof:placetype":"venue"
},
  "geometry": {"coordinates":[-8.9943294525,42.5565071106],"type":"Point"}
}