{
  "type": "Feature",
  "properties": {
    "iso:country":"ES",
    "sg:address":"Barr Arechaga, S/n",
    "sg:city":"Mimetiz",
    "sg:orig_category":"Suministros Para Carrocer\u00cdas",
    "sg:phone":"+34 946 39 13 60",
    "sg:postcode":"48860",
    "sg:province":"Vizcaya",
    "wof:name":"Carrocerias Urquizu S.l.",
    "wof:placetype":"venue"
},
  "geometry": {"coordinates":[-3.1296989918,43.2133483887],"type":"Point"}
}