{
  "type": "Feature",
  "properties": {
    "addr:full":"Rua Ramon Farre, 3 Burela Lugo 27880",
    "addr:housenumber":"3",
    "addr:postcode":"27880",
    "addr:street":"Rua Ramon Farre",
    "iso:country":"ES",
    "sg:address":"Rua Ramon Farre, 3",
    "sg:city":"Burela",
    "sg:orig_category":"Electrodom\u00c9sticos (al Por Menor)",
    "sg:phone":"+34 982 58 59 78",
    "sg:postcode":"27880",
    "sg:province":"Lugo",
    "wof:name":"Jose Antonio Burela S. L.",
    "wof:placetype":"venue"
},
  "geometry": {"coordinates":[-7.3571472168,43.6536598206],"type":"Point"}
}