{
  "type": "Feature",
  "properties": {
    "iso:country":"ES",
    "sg:address":"Rda. Del Moli, 2",
    "sg:city":"Vilafant",
    "sg:orig_category":"Centros De Educaci\u00d3n Especial",
    "sg:phone":"+34 972 50 16 76",
    "sg:postcode":"17740",
    "sg:province":"Girona",
    "wof:name":"Centre D'educacio Especial Mare De Deu Del Mont",
    "wof:placetype":"venue"
},
  "geometry": {"coordinates":[2.9652490616,42.2468147278],"type":"Point"}
}