{
  "type": "Feature",
  "properties": {
    "addr:full":"Calle de Cinca, 45 Coria Rio Sevilla 41100",
    "addr:housenumber":"45",
    "addr:postcode":"41100",
    "addr:street":"Calle De Cinca;Rio Sevilla",
    "iso:country":"ES",
    "sg:address":"Calle de Cinca, 45",
    "sg:city":"Coria Rio",
    "sg:orig_category":"Limpieza Con Chorro De Arena Y Con Granalla, Pulido",
    "sg:phone":"+34 954 77 26 39",
    "sg:postcode":"41100",
    "sg:province":"Sevilla",
    "wof:name":"Silva Parra Maria Angeles",
    "wof:placetype":"venue"
},
  "geometry": {"coordinates":[-6.0489578247,37.2927055359],"type":"Point"}
}