{
  "type": "Feature",
  "properties": {
    "addr:full":"Carr Roger De Flor, 127 Badalona Barcelona 08912",
    "addr:housenumber":"127",
    "addr:postcode":"08912",
    "addr:street":"Carr Roger De Flor",
    "iso:country":"ES",
    "sg:address":"Carr Roger De Flor, 127",
    "sg:city":"Badalona",
    "sg:orig_category":"Inmobiliaria (agencias)",
    "sg:phone":"+34 933 87 56 66",
    "sg:postcode":"08912",
    "sg:province":"Barcelona",
    "wof:name":"Fincas Navarro-catalan S.c.p.",
    "wof:placetype":"venue"
},
  "geometry": {"coordinates":[2.2406020164,41.4440841675],"type":"Point"}
}