{
  "type": "Feature",
  "properties": {
    "addr:full":"Maestrat (pol Ind Les Salines), 8 Cubelles Barcelona 08880",
    "addr:housenumber":"8",
    "addr:postcode":"08880",
    "iso:country":"ES",
    "sg:address":"Maestrat (pol Ind Les Salines), 8",
    "sg:city":"Cubelles",
    "sg:orig_category":"Frutas Y Legumbres Frescas (al Por Mayor)",
    "sg:phone":"+34 938 95 36 99",
    "sg:postcode":"08880",
    "sg:province":"Barcelona",
    "wof:name":"Mu\u00f1ido Y Garrido S.l.",
    "wof:placetype":"venue"
},
  "geometry": {"coordinates":[1.6479350328,41.1982955933],"type":"Point"}
}