{
  "type": "Feature",
  "properties": {
    "iso:country":"ES",
    "sg:address":"Calle de Suasbarras, 36",
    "sg:city":"Covas",
    "sg:orig_category":"Reposter\u00cdas",
    "sg:phone":"+34 982 55 01 30",
    "sg:postcode":"27861",
    "sg:province":"Lugo",
    "wof:name":"Paz Rivera Marta",
    "wof:placetype":"venue"
},
  "geometry": {"coordinates":[-7.6583218575,43.691734314],"type":"Point"}
}