{
  "type": "Feature",
  "properties": {
    "iso:country":"ES",
    "sg:address":"Calle de Pico Del Mulhacen, 44",
    "sg:city":"Arganda",
    "sg:orig_category":"Alimentaci\u00d3n Animal (fabricaci\u00d3n, Al Por Mayor)",
    "sg:phone":"+34 918 70 22 91",
    "sg:postcode":"28500",
    "sg:province":"Madrid",
    "wof:name":"Grupo Omega De Nutricion Animal S.l.",
    "wof:placetype":"venue"
},
  "geometry": {"coordinates":[-3.4831209183,40.3063278198],"type":"Point"}
}