{
  "type": "Feature",
  "properties": {
    "addr:full":"Carr Dr Fleming, 1 Balaguer Lleida 25600",
    "addr:housenumber":"1",
    "addr:postcode":"25600",
    "addr:street":"Carr Dr Fleming",
    "iso:country":"ES",
    "sg:address":"Carr Dr Fleming, 1",
    "sg:city":"Balaguer",
    "sg:orig_category":"Estancos",
    "sg:phone":"+34 973 44 53 95",
    "sg:postcode":"25600",
    "sg:province":"Lleida",
    "wof:name":"Espona Talarn Miguel",
    "wof:placetype":"venue"
},
  "geometry": {"coordinates":[0.8102669716,41.7914237976],"type":"Point"}
}