{
  "type": "Feature",
  "properties": {
    "iso:country":"ES",
    "sg:address":"Avda Ejercito Espa\u00d1ol (del), 1",
    "sg:city":"Barbastro",
    "sg:orig_category":"Comerciantes Al Por Mayor De Vinos, Licores Y Alcoholes",
    "sg:phone":"+34 974 31 16 97",
    "sg:postcode":"22300",
    "sg:province":"Huesca",
    "wof:name":"Murillo Cobeta Francisco",
    "wof:placetype":"venue"
},
  "geometry": {"coordinates":[0.1207299978,42.0352287292],"type":"Point"}
}