{
  "type": "Feature",
  "properties": {
    "addr:full":"Pl Generalitat, 13 S. Boi Llobregat Barcelona 08830",
    "addr:housenumber":"13",
    "addr:postcode":"08830",
    "addr:street":"Pl Generalitat",
    "iso:country":"ES",
    "sg:address":"Pl Generalitat, 13",
    "sg:city":"S. Boi Llobregat",
    "sg:orig_category":"Bancos",
    "sg:phone":"+34 936 61 32 00",
    "sg:postcode":"08830",
    "sg:province":"Barcelona",
    "wof:name":"Banc Sabadell S.a.",
    "wof:placetype":"venue"
},
  "geometry": {"coordinates":[2.0314741135,41.3490371704],"type":"Point"}
}