{
  "type": "Feature",
  "properties": {
    "addr:full":"Pla\u00c7 Dau, Del, 2 Quart Poblet Valencia 46930",
    "addr:postcode":"46930",
    "iso:country":"ES",
    "sg:address":"Pla\u00c7 Dau, Del, 2",
    "sg:city":"Quart Poblet",
    "sg:orig_category":"Cajas De Ahorro",
    "sg:phone":"+34 961 52 19 55",
    "sg:postcode":"46930",
    "sg:province":"Valencia",
    "sg:website":"www.bancaja.es",
    "wof:name":"Caja De Ahorros De Valencia Castellon Y Alicante",
    "wof:placetype":"venue"
},
  "geometry": {"coordinates":[-0.4419890046,39.482711792],"type":"Point"}
}