{
  "type": "Feature",
  "properties": {
    "iso:country":"ES",
    "sg:address":"Avda Paz (de La), 1",
    "sg:city":"Huesca",
    "sg:orig_category":"Delegados, Agentes De Tr\u00c1nsito, Auxiliares De Transporte Internacional",
    "sg:phone":"+34 974 22 14 30",
    "sg:postcode":"22004",
    "sg:province":"Huesca",
    "wof:name":"Garces Gimenez Miguel Angel",
    "wof:placetype":"venue"
},
  "geometry": {"coordinates":[-0.4155069888,42.1383514404],"type":"Point"}
}