{
  "type": "Feature",
  "properties": {
    "addr:full":"Calle de Libertad, 20 Gijon Asturias 33206",
    "addr:housenumber":"20",
    "addr:postcode":"33206",
    "addr:street":"Calle De Libertad",
    "iso:country":"ES",
    "sg:address":"Calle de Libertad, 20",
    "sg:city":"Gijon",
    "sg:orig_category":"Asilos De Ancianos. Centros Privados",
    "sg:phone":"+34 985 35 26 99",
    "sg:postcode":"33206",
    "sg:province":"Asturias",
    "wof:name":"Residencia Tercera Edad Virgen Reina S.l.",
    "wof:placetype":"venue"
},
  "geometry": {"coordinates":[-5.6638889313,43.5403327942],"type":"Point"}
}