{
  "type": "Feature",
  "properties": {
    "iso:country":"ES",
    "sg:address":"Carrer de Ricardo, 10",
    "sg:city":"Benidorm",
    "sg:orig_category":"Asociaciones Ecologistas",
    "sg:phone":"+34 965 85 01 33",
    "sg:postcode":"03500",
    "sg:province":"Alicante",
    "wof:name":"Comunidad Regantes Canal Bajo Del Algar",
    "wof:placetype":"venue"
},
  "geometry": {"coordinates":[-0.1295070052,38.5355072021],"type":"Point"}
}