{
  "type": "Feature",
  "properties": {
    "iso:country":"ES",
    "sg:address":"Cllo Cardoso, 17",
    "sg:city":"Cadiz",
    "sg:orig_category":"Peluqueros: De Se\u00d1oras",
    "sg:phone":"+34 956 22 94 05",
    "sg:postcode":"11002",
    "sg:province":"C\u00e1diz",
    "wof:name":"Baena Castillo Remedios Ana",
    "wof:placetype":"venue"
},
  "geometry": {"coordinates":[-6.3046650887,36.530002594],"type":"Point"}
}