{
  "type": "Feature",
  "properties": {
    "addr:full":"Calle de Pinos (de Los), 23 Cabanillas Campo Guadalajara 19171",
    "addr:housenumber":"23",
    "addr:postcode":"19171",
    "addr:street":"Calle De Pinos De Los",
    "iso:country":"ES",
    "sg:address":"Calle de Pinos (de Los), 23",
    "sg:city":"Cabanillas Campo",
    "sg:orig_category":"Laboratorios Farmac\u00c9uticos",
    "sg:phone":"+34 949 33 71 22",
    "sg:postcode":"19171",
    "sg:province":"Guadalajara",
    "sg:website":"www.msd.es",
    "wof:name":"Merck Sharp & Dohme Espa\u00d1ola S.a.",
    "wof:placetype":"venue"
},
  "geometry": {"coordinates":[-3.2330369949,40.6423606873],"type":"Point"}
}