{
  "type": "Feature",
  "properties": {
    "addr:full":"Calle de Akilino Arriola, 1 Moreaga Vizcaya 48600",
    "addr:housenumber":"1",
    "addr:postcode":"48600",
    "addr:street":"Calle De Akilino Arriola",
    "iso:country":"ES",
    "sg:address":"Calle de Akilino Arriola, 1",
    "sg:city":"Moreaga",
    "sg:orig_category":"Inmobiliaria (agencias)",
    "sg:phone":"+34 946 76 30 56",
    "sg:postcode":"48600",
    "sg:province":"Vizcaya",
    "wof:name":"Gomez Ria\u00f1o Valeriano",
    "wof:placetype":"venue"
},
  "geometry": {"coordinates":[-2.9812836647,43.3813781738],"type":"Point"}
}