{
  "type": "Feature",
  "properties": {
    "addr:full":"Carrer de Sant Tomas, 30 Aldea Tarragona 43896",
    "addr:housenumber":"30",
    "addr:postcode":"43896",
    "addr:street":"Carrer De Sant Tomas",
    "iso:country":"ES",
    "sg:address":"Carrer de Sant Tomas, 30",
    "sg:city":"Aldea",
    "sg:orig_category":"Mec\u00c1nico Del Autom\u00d3vil",
    "sg:phone":"+34 977 45 04 25",
    "sg:postcode":"43896",
    "sg:province":"Tarragona",
    "wof:name":"Maquinaria Agricola M.peris S.l.",
    "wof:placetype":"venue"
},
  "geometry": {"coordinates":[0.6085289717,40.7413749695],"type":"Point"}
}