{
  "type": "Feature",
  "properties": {
    "iso:country":"ES",
    "sg:address":"Carrer de Pablo Iglesias, 109",
    "sg:city":"Barcelona",
    "sg:orig_category":"Materias Pl\u00c1sticas: Productos Para Industria Y Agricultura (fabricaci\u00d3n, Al Por Mayor)",
    "sg:phone":"+34 933 59 48 41",
    "sg:postcode":"08016",
    "sg:province":"Barcelona",
    "sg:website":"www.atpsl.com",
    "wof:name":"Asesores Tecnicos Del Plastico S.l.",
    "wof:placetype":"venue"
},
  "geometry": {"coordinates":[2.1830198765,41.4457893372],"type":"Point"}
}