{
  "type": "Feature",
  "properties": {
    "addr:full":"Avda Principal De A\u00d1aza, S/n A\u00d1aza Santa Cruz De Tenerife 38111",
    "addr:housenumber":"s",
    "addr:postcode":"38111",
    "addr:street":"Avda Principal De An\u0303Aza;/ N An\u0303Aza",
    "iso:country":"ES",
    "sg:address":"Avda Principal De A\u00d1aza, S/n",
    "sg:city":"A\u00d1aza",
    "sg:orig_category":"Fabricaci\u00d3n De Peines Y De Accesorios De Peluquer\u00cda",
    "sg:phone":"+34 922 68 83 39",
    "sg:postcode":"38111",
    "sg:province":"Santa Cruz De Tenerife",
    "wof:name":"Javier Armas Distribuciones S.l.",
    "wof:placetype":"venue"
},
  "geometry": {"coordinates":[-16.3033084869,28.4245147705],"type":"Point"}
}