{
  "type": "Feature",
  "properties": {
    "addr:full":"Pol Mun Zafra, 14 Zafra Badajoz 06300",
    "addr:housenumber":"14",
    "addr:postcode":"06300",
    "iso:country":"ES",
    "sg:address":"Pol Mun Zafra, 14",
    "sg:city":"Zafra",
    "sg:orig_category":"Metalurgia",
    "sg:phone":"+34 924 55 09 45",
    "sg:postcode":"06300",
    "sg:province":"Badajoz",
    "sg:website":"www.transesl.com",
    "wof:name":"Transformaciones Segedanas S.l.",
    "wof:placetype":"venue"
},
  "geometry": {"coordinates":[-6.4134092331,38.4236793518],"type":"Point"}
}