{
  "type": "Feature",
  "properties": {
    "addr:full":"Calle de Montecid, 3 Petrer Alicante 03610",
    "addr:housenumber":"3",
    "addr:postcode":"03610",
    "addr:street":"Calle De Montecid",
    "iso:country":"ES",
    "sg:address":"Calle de Montecid, 3",
    "sg:city":"Petrer",
    "sg:orig_category":"Confecci\u00d3n De Zapatos",
    "sg:phone":"+34 965 37 58 19",
    "sg:postcode":"03610",
    "sg:province":"Alicante",
    "wof:name":"Hijos De Juan Montesinos S.l.",
    "wof:placetype":"venue"
},
  "geometry": {"coordinates":[-0.7800340056,38.4884490967],"type":"Point"}
}