{
  "type": "Feature",
  "properties": {
    "addr:full":"Calle de Cervantes, 4 Almoradi Alicante 03160",
    "addr:housenumber":"4",
    "addr:postcode":"03160",
    "addr:street":"Calle De Cervantes",
    "iso:country":"ES",
    "sg:address":"Calle de Cervantes, 4",
    "sg:city":"Almoradi",
    "sg:orig_category":"Lencer\u00cda Femenina, Corseter\u00cda, Trajes De Ba\u00d1o (al Por Menor)",
    "sg:phone":"+34 965 70 26 09",
    "sg:postcode":"03160",
    "sg:province":"Alicante",
    "wof:name":"Montesinos Berenguer Pilar",
    "wof:placetype":"venue"
},
  "geometry": {"coordinates":[-0.7923923135,38.1095161438],"type":"Point"}
}