{
  "type": "Feature",
  "properties": {
    "addr:full":"C/ Sant Marti, 82 Cerdanyola Valles Barcelona 08290",
    "addr:housenumber":"82",
    "addr:postcode":"08290",
    "addr:street":"C / Sant Marti;Valles Barcelona",
    "iso:country":"ES",
    "sg:address":"C/ Sant Marti, 82",
    "sg:city":"Cerdanyola Valles",
    "sg:orig_category":"M\u00c9dicos: Estomatolog\u00cda",
    "sg:phone":"+34 935 86 47 92",
    "sg:postcode":"08290",
    "sg:province":"Barcelona",
    "wof:name":"Trucharte Garcia Gloria",
    "wof:placetype":"venue"
},
  "geometry": {"coordinates":[2.1394479275,41.4912033081],"type":"Point"}
}