{
  "type": "Feature",
  "properties": {
    "iso:country":"ES",
    "sg:address":"Calle de Txurruka, 6",
    "sg:city":"Donostia-san Sebastian",
    "sg:orig_category":"Deportes Y Ocio: Art\u00cdculos Y Ropas (al Por Menor Y Accesorios)",
    "sg:phone":"+34 943 42 02 47",
    "sg:postcode":"20004",
    "sg:province":"Guip\u00f9zcoa",
    "wof:name":"Real Sociedad De Futbol S.a.d.",
    "wof:placetype":"venue"
},
  "geometry": {"coordinates":[-1.982254982,43.3201713562],"type":"Point"}
}