{
  "type": "Feature",
  "properties": {
    "iso:country":"ES",
    "sg:address":"Calle de Actor Llorens, 49",
    "sg:city":"Valencia",
    "sg:orig_category":"Fabricaci\u00d3n, Venta, Instalaci\u00d3n De R\u00d3tulos, De R\u00d3tulos Luminosos",
    "sg:phone":"+34 963 93 10 81",
    "sg:postcode":"46021",
    "sg:province":"Valencia",
    "wof:name":"Serrador Gomez Jose Salvador",
    "wof:placetype":"venue"
},
  "geometry": {"coordinates":[-0.3542059958,39.4696083069],"type":"Point"}
}