{
  "type": "Feature",
  "properties": {
    "iso:country":"ES",
    "sg:address":"Ctra Sagunto-burgos, S/n",
    "sg:city":"Abejar",
    "sg:orig_category":"Hosteler\u00cda, Empleados",
    "sg:phone":"+34 975 37 31 98",
    "sg:postcode":"42146",
    "sg:province":"Soria",
    "wof:name":"Teresa Martin Simon",
    "wof:placetype":"venue"
},
  "geometry": {"coordinates":[-2.8498749733,41.7982330322],"type":"Point"}
}