{
  "type": "Feature",
  "properties": {
    "addr:full":"Calle de Norte Del, 36 Langreo Asturias 33930",
    "addr:housenumber":"36",
    "addr:postcode":"33930",
    "addr:street":"Calle De Norte Del",
    "iso:country":"ES",
    "sg:address":"Calle de Norte Del, 36",
    "sg:city":"Langreo",
    "sg:orig_category":"Ferreter\u00cda (diversos)",
    "sg:phone":"+34 985 69 63 59",
    "sg:postcode":"33930",
    "sg:province":"Asturias",
    "wof:name":"Fraile Iglesias Jose",
    "wof:placetype":"venue"
},
  "geometry": {"coordinates":[-5.7070870399,43.3195877075],"type":"Point"}
}