{
  "type": "Feature",
  "properties": {
    "iso:country":"ES",
    "sg:address":"Cendona, S/n",
    "sg:city":"Cendona",
    "sg:orig_category":"Agentes, Concesionarios Y Sucursales De Camiones Y Veh\u00cdculos Industriales",
    "sg:phone":"+34 986 87 00 32",
    "sg:postcode":"36099",
    "sg:province":"Pontevedra",
    "wof:name":"Talleres Baulo S. L.",
    "wof:placetype":"venue"
},
  "geometry": {"coordinates":[-8.6404018402,42.4590377808],"type":"Point"}
}