{
  "type": "Feature",
  "properties": {
    "iso:country":"ES",
    "sg:address":"Calle de Fray Diego De Cadiz, 153",
    "sg:city":"Moron Frontera",
    "sg:orig_category":"Tapicer\u00cdas",
    "sg:phone":"+34 954 85 07 66",
    "sg:postcode":"41530",
    "sg:province":"Sevilla",
    "wof:name":"Tapizados Roma S.l.",
    "wof:placetype":"venue"
},
  "geometry": {"coordinates":[-5.4584088326,37.1217803955],"type":"Point"}
}