{
  "type": "Feature",
  "properties": {
    "addr:full":"Calle de Atocha, 11 Madrid Madrid 28012",
    "addr:housenumber":"11",
    "addr:postcode":"madrid;28012",
    "addr:street":"Calle De Atocha",
    "iso:country":"ES",
    "sg:address":"Calle de Atocha, 11",
    "sg:city":"Madrid",
    "sg:orig_category":"Ropa Para Se\u00d1oras (al Por Menor)",
    "sg:phone":"+34 917 01 08 97",
    "sg:postcode":"28012",
    "sg:province":"Madrid",
    "wof:name":"Moda Saralba S.l.",
    "wof:placetype":"venue"
},
  "geometry": {"coordinates":[-3.7045354843,40.4145050049],"type":"Point"}
}