{
  "type": "Feature",
  "properties": {
    "addr:full":"Plaz Mayor, 2 Matapozuelos Valladolid 47230",
    "addr:housenumber":"2",
    "addr:postcode":"47230",
    "addr:street":"Plaz Mayor",
    "iso:country":"ES",
    "sg:address":"Plaz Mayor, 2",
    "sg:city":"Matapozuelos",
    "sg:orig_category":"Hoteles",
    "sg:phone":"+34 983 83 29 42",
    "sg:postcode":"47230",
    "sg:province":"Valladolid",
    "wof:name":"De La Cruz Gutierrez Teodoro",
    "wof:placetype":"venue"
},
  "geometry": {"coordinates":[-4.7916398048,41.4142684937],"type":"Point"}
}