{
  "type": "Feature",
  "properties": {
    "iso:country":"ES",
    "sg:address":"Avda Velazquez, 114",
    "sg:city":"Malaga",
    "sg:orig_category":"Agentes, Concesionarios Y Sucursales De Veh\u00cdculos",
    "sg:phone":"+34 952 23 51 46",
    "sg:postcode":"29004",
    "sg:province":"M\u00e1laga",
    "wof:name":"Galvez Motor S.a.",
    "wof:placetype":"venue"
},
  "geometry": {"coordinates":[-4.4582071304,36.6901016235],"type":"Point"}
}