{
  "type": "Feature",
  "properties": {
    "iso:country":"ES",
    "sg:address":"Rua Padron, 5",
    "sg:city":"Estrada",
    "sg:orig_category":"Ropa Para Se\u00d1oras (al Por Menor)",
    "sg:phone":"+34 986 57 24 91",
    "sg:postcode":"36680",
    "sg:province":"Pontevedra",
    "wof:name":"Gonzalez Gonzalez Carmen Otilia",
    "wof:placetype":"venue"
},
  "geometry": {"coordinates":[-8.4932413101,42.6885604858],"type":"Point"}
}