{
  "type": "Feature",
  "properties": {
    "iso:country":"ES",
    "sg:address":"Paladores, 6",
    "sg:city":"Navatejera",
    "sg:orig_category":"Materias Pl\u00c1sticas: Art\u00cdculos Para La Industria",
    "sg:phone":"+34 987 84 72 20",
    "sg:postcode":"24008",
    "sg:province":"Le\u00f3n",
    "wof:name":"Barrioplast S. L.",
    "wof:placetype":"venue"
},
  "geometry": {"coordinates":[-5.5550928116,42.6448745728],"type":"Point"}
}