{
  "type": "Feature",
  "properties": {
    "addr:full":"Calle de Seixo, 56 Cangas Pontevedra 36940",
    "addr:housenumber":"56",
    "addr:postcode":"36940",
    "addr:street":"Calle De Seixo",
    "iso:country":"ES",
    "sg:address":"Calle de Seixo, 56",
    "sg:city":"Cangas",
    "sg:orig_category":"Deportes Diversos",
    "sg:phone":"+34 986 30 66 51",
    "sg:postcode":"36940",
    "sg:province":"Pontevedra",
    "wof:name":"Rederia Y Efectos Vilasmart S.l.u.",
    "wof:placetype":"venue"
},
  "geometry": {"coordinates":[-8.8184690475,42.2742500305],"type":"Point"}
}