{
  "type": "Feature",
  "properties": {
    "addr:full":"Calle de Zarrenebarri, 7 Algorta Vizcaya 48992",
    "addr:housenumber":"7",
    "addr:postcode":"48992",
    "addr:street":"Calle De Zarrenebarri",
    "iso:country":"ES",
    "sg:address":"Calle de Zarrenebarri, 7",
    "sg:city":"Algorta",
    "sg:orig_category":"Asesor\u00cda Sobre Comunicaci\u00d3n De Empresas",
    "sg:phone":"+34 944 60 80 55",
    "sg:postcode":"48992",
    "sg:province":"Vizcaya",
    "wof:name":"Agnever Xxi S.l.",
    "wof:placetype":"venue"
},
  "geometry": {"coordinates":[-3.0038063526,43.34141922],"type":"Point"}
}