{
  "type": "Feature",
  "properties": {
    "iso:country":"ES",
    "sg:address":"San Juan Kalea, 5",
    "sg:city":"Urnieta",
    "sg:orig_category":"Ense\u00d1anza, Formaci\u00d3n Profesional: Aprendizaje",
    "sg:phone":"+34 943 00 80 33",
    "sg:postcode":"20130",
    "sg:province":"Guip\u00f9zcoa",
    "wof:name":"Kulturnieta, S.a.",
    "wof:placetype":"venue"
},
  "geometry": {"coordinates":[-1.9903470278,43.2476539612],"type":"Point"}
}