{
  "type": "Feature",
  "properties": {
    "addr:full":"Calle de Doctor Antonio Bascaran Asunsolo, 1 Oviedo Asturias 33010",
    "addr:housenumber":"1",
    "addr:postcode":"33010",
    "addr:street":"Calle De Doctor Antonio Bascaran Asunsolo",
    "iso:country":"ES",
    "sg:address":"Calle de Doctor Antonio Bascaran Asunsolo, 1",
    "sg:city":"Oviedo",
    "sg:orig_category":"Agencias Y Agentes Comerciales, Representantes",
    "sg:phone":"+34 985 11 65 80",
    "sg:postcode":"33010",
    "sg:province":"Asturias",
    "wof:name":"Gonzalez Alvarez Miguel Angel",
    "wof:placetype":"venue"
},
  "geometry": {"coordinates":[-5.8193836212,43.3688240051],"type":"Point"}
}