{
  "type": "Feature",
  "properties": {
    "addr:full":"Carr Josep R. Batalla, 48 Villarreal Castell\u00f3n 12540",
    "addr:housenumber":"48",
    "addr:postcode":"12540",
    "addr:street":"Carr Josep R. Batalla",
    "iso:country":"ES",
    "sg:address":"Carr Josep R. Batalla, 48",
    "sg:city":"Villarreal",
    "sg:orig_category":"Agencias Y Agentes Comerciales, Representantes",
    "sg:phone":"+34 964 53 85 43",
    "sg:postcode":"12540",
    "sg:province":"Castell\u00f3n",
    "wof:name":"Representaciones Francisco Blasco S.l.",
    "wof:placetype":"venue"
},
  "geometry": {"coordinates":[-0.0952939987,39.9453048706],"type":"Point"}
}