{
  "type": "Feature",
  "properties": {
    "iso:country":"ES",
    "sg:address":"Avda Juan Carlos I, Rey, 3",
    "sg:city":"Melilla",
    "sg:orig_category":"Laboratorios Y Trabajos De Fotograf\u00cda, V\u00cddeo Y Cine",
    "sg:phone":"+34 952 68 17 14",
    "sg:postcode":"52001",
    "sg:province":"Melilla",
    "sg:website":"www.navegalia.com/bch/fotoimperio",
    "wof:name":"Mariscal Fuentes Salvadora",
    "wof:placetype":"venue"
},
  "geometry": {"coordinates":[-2.939909935,35.2935714722],"type":"Point"}
}