{
  "type": "Feature",
  "properties": {
    "addr:full":"Calle de Coso Alto, 57 Huesca Huesca 22003",
    "addr:housenumber":"57",
    "addr:postcode":"22003",
    "addr:street":"Calle De Coso Alto",
    "iso:country":"ES",
    "sg:address":"Calle de Coso Alto, 57",
    "sg:city":"Huesca",
    "sg:orig_category":"Deportes Y Ocio: Art\u00cdculos Y Ropas (al Por Menor Y Accesorios)",
    "sg:phone":"+34 974 24 03 94",
    "sg:postcode":"22003",
    "sg:province":"Huesca",
    "wof:name":"Pesca-c.r.",
    "wof:placetype":"venue"
},
  "geometry": {"coordinates":[-0.4110668898,42.1401062012],"type":"Point"}
}