{
  "type": "Feature",
  "properties": {
    "iso:country":"ES",
    "sg:address":"Calle de Lope Gisbert, 6",
    "sg:city":"Santiago",
    "sg:orig_category":"Ropa Para Ni\u00d1os (al Por Menor)",
    "sg:phone":"+34 968 46 51 23",
    "sg:postcode":"30800",
    "sg:province":"Murcia",
    "wof:name":"Romero Lafont Ana",
    "wof:placetype":"venue"
},
  "geometry": {"coordinates":[-1.6905640364,37.680557251],"type":"Point"}
}