{
  "type": "Feature",
  "properties": {
    "addr:full":"Calle de Artajona, 13 Madrid Madrid 28039",
    "addr:housenumber":"13",
    "addr:postcode":"madrid;28039",
    "addr:street":"Calle De Artajona",
    "iso:country":"ES",
    "sg:address":"Calle de Artajona, 13",
    "sg:city":"Madrid",
    "sg:orig_category":"Estudios, Instalaci\u00d3n De Climatizaci\u00d3n",
    "sg:phone":"+34 914 59 07 10",
    "sg:postcode":"28039",
    "sg:province":"Madrid",
    "wof:name":"Airworks S.l.",
    "wof:placetype":"venue"
},
  "geometry": {"coordinates":[-3.7181479931,40.4632072449],"type":"Point"}
}