{
  "type": "Feature",
  "properties": {
    "addr:full":"Calle de Romero, 23 Cascante Navarra 31520",
    "addr:housenumber":"23",
    "addr:postcode":"31520",
    "addr:street":"Calle De Romero",
    "iso:country":"ES",
    "sg:address":"Calle de Romero, 23",
    "sg:city":"Cascante",
    "sg:orig_category":"Carnicer\u00cdas, Carnicer\u00cdas",
    "sg:phone":"+34 948 85 16 51",
    "sg:postcode":"31520",
    "sg:province":"Navarra",
    "wof:name":"Cunchillos A Y Jimenez Mv Vitas L S.cv.",
    "wof:placetype":"venue"
},
  "geometry": {"coordinates":[-1.6791800261,41.9988937378],"type":"Point"}
}