{
  "type": "Feature",
  "properties": {
    "iso:country":"ES",
    "sg:address":"C/ Padro, 27",
    "sg:city":"Ripollet",
    "sg:orig_category":"Ropa Para Ni\u00d1os (al Por Menor)",
    "sg:phone":"+34 935 80 40 33",
    "sg:postcode":"08291",
    "sg:province":"Barcelona",
    "wof:name":"Montes Gracia Eva",
    "wof:placetype":"venue"
},
  "geometry": {"coordinates":[2.156193018,41.4972496033],"type":"Point"}
}