{
  "type": "Feature",
  "properties": {
    "addr:full":"Calle de Jaime I, 42 Alaquas Valencia 46970",
    "addr:housenumber":"42",
    "addr:postcode":"46970",
    "addr:street":"Calle De Jaime I",
    "iso:country":"ES",
    "sg:address":"Calle de Jaime I, 42",
    "sg:city":"Alaquas",
    "sg:orig_category":"Molduras, Junquillos, Listones Y Molduras Perforadas",
    "sg:phone":"+34 961 51 84 29",
    "sg:postcode":"46970",
    "sg:province":"Valencia",
    "wof:name":"Bar Tutti Sl",
    "wof:placetype":"venue"
},
  "geometry": {"coordinates":[-0.4578439891,39.4546356201],"type":"Point"}
}