{
  "type": "Feature",
  "properties": {
    "addr:full":"C/ Capella Pere Llull, 8 Manacor Islas Baleares 07500",
    "addr:housenumber":"8",
    "addr:postcode":"07500",
    "addr:street":"C / Capella Pere Llull",
    "iso:country":"ES",
    "sg:address":"C/ Capella Pere Llull, 8",
    "sg:city":"Manacor",
    "sg:orig_category":"Ense\u00d1anza: Peluquer\u00cda Est\u00c9tica",
    "sg:phone":"+34 971 55 97 81",
    "sg:postcode":"07500",
    "sg:province":"Islas Baleares",
    "wof:name":"Alfredo Ubiedo S.l.",
    "wof:placetype":"venue"
},
  "geometry": {"coordinates":[3.2104384899,39.5681114197],"type":"Point"}
}