{
  "type": "Feature",
  "properties": {
    "iso:country":"ES",
    "sg:address":"Calle de Maria Santos Colmenar (de), 15",
    "sg:city":"San Sebastian De Los Reyes",
    "sg:orig_category":"Muebles, Minoristas",
    "sg:phone":"+34 916 59 14 61",
    "sg:postcode":"28700",
    "sg:province":"Madrid",
    "wof:name":"Aldar Barakat S.l.",
    "wof:placetype":"venue"
},
  "geometry": {"coordinates":[-3.6245772839,40.5462989807],"type":"Point"}
}