{
  "type": "Feature",
  "properties": {
    "addr:full":"Calle de Urbieta, 17 Donostia-san Sebastian Guip\u00f9zcoa 20006",
    "addr:housenumber":"17",
    "addr:postcode":"20006",
    "addr:street":"Calle De Urbieta",
    "iso:country":"ES",
    "sg:address":"Calle de Urbieta, 17",
    "sg:city":"Donostia-san Sebastian",
    "sg:orig_category":"Ropa Para Se\u00d1oras (al Por Menor)",
    "sg:phone":"+34 943 43 16 60",
    "sg:postcode":"20006",
    "sg:province":"Guip\u00f9zcoa",
    "wof:name":"Telvask S.l.",
    "wof:placetype":"venue"
},
  "geometry": {"coordinates":[-1.982550025,43.3169670105],"type":"Point"}
}