{
  "type": "Feature",
  "properties": {
    "addr:full":"Carrer de Portell, 3 Santanyi Islas Baleares 07650",
    "addr:housenumber":"3",
    "addr:postcode":"07650",
    "addr:street":"Carrer De Portell",
    "iso:country":"ES",
    "sg:address":"Carrer de Portell, 3",
    "sg:city":"Santanyi",
    "sg:orig_category":"Bisuter\u00cda, Joyer\u00cda, Relojer\u00cda (al Por Menor)",
    "sg:phone":"+34 971 65 38 42",
    "sg:postcode":"07650",
    "sg:province":"Islas Baleares",
    "wof:name":"Mulet Rellotgeria I Joieria C.b.",
    "wof:placetype":"venue"
},
  "geometry": {"coordinates":[3.128921032,39.3538856506],"type":"Point"}
}