{
  "type": "Feature",
  "properties": {
    "addr:full":"Fnc Casa Quemada, S/n Minaya Albacete 02620",
    "addr:housenumber":"s / n",
    "addr:postcode":"02620",
    "iso:country":"ES",
    "sg:address":"Fnc Casa Quemada, S/n",
    "sg:city":"Minaya",
    "sg:orig_category":"Producci\u00d3n, Venta De Productos De Agricultura Biol\u00d3gica",
    "sg:phone":"+34 967 57 00 28",
    "sg:postcode":"02620",
    "sg:province":"Albacete",
    "wof:name":"Valentin Cuervas-mons Ciller Y Otros Cdad",
    "wof:placetype":"venue"
},
  "geometry": {"coordinates":[-2.3185939789,39.2175064087],"type":"Point"}
}