{
  "type": "Feature",
  "properties": {
    "iso:country":"ES",
    "sg:address":"Calle de Cadiz, 26",
    "sg:city":"Conil De La Frontera",
    "sg:orig_category":"Mercer\u00cda, Lencer\u00cda (al Por Menor)",
    "sg:phone":"+34 956 44 20 42",
    "sg:postcode":"11140",
    "sg:province":"C\u00e1diz",
    "wof:name":"Ariza Ligero Juana",
    "wof:placetype":"venue"
},
  "geometry": {"coordinates":[-6.0910420418,36.2758293152],"type":"Point"}
}