{
  "type": "Feature",
  "properties": {
    "iso:country":"ES",
    "sg:address":"Calle de Joaquin Costa, 39",
    "sg:city":"Ayerbe",
    "sg:orig_category":"Mec\u00c1nico Del Autom\u00d3vil",
    "sg:phone":"+34 974 38 02 38",
    "sg:postcode":"22800",
    "sg:province":"Huesca",
    "wof:name":"Talleres Morlans S.l",
    "wof:placetype":"venue"
},
  "geometry": {"coordinates":[-0.6835370064,42.2728424072],"type":"Point"}
}