{
  "type": "Feature",
  "properties": {
    "addr:full":"Ctra Murcia-alicante, Km. 0027,1 Orihuela Alicante 03300",
    "addr:postcode":"03300",
    "addr:street":"Ctra Murcia-Alicante Km. 0027,1",
    "iso:country":"ES",
    "sg:address":"Ctra Murcia-alicante, Km. 0027,1",
    "sg:city":"Orihuela",
    "sg:orig_category":"Contenedores (mercanc\u00cdas)",
    "sg:phone":"+34 966 73 92 62",
    "sg:postcode":"03300",
    "sg:province":"Alicante",
    "wof:name":"Gases Grupo Ballesta S.l.",
    "wof:placetype":"venue"
},
  "geometry": {"coordinates":[-0.9448040128,38.0817642212],"type":"Point"}
}