{
  "type": "Feature",
  "properties": {
    "addr:full":"Rbla Badal, 53 Barcelona Barcelona 08014",
    "addr:housenumber":"53",
    "addr:postcode":"08014",
    "addr:street":"Rbla Badal",
    "iso:country":"ES",
    "sg:address":"Rbla Badal, 53",
    "sg:city":"Barcelona",
    "sg:orig_category":"Guarder\u00cdas",
    "sg:phone":"+34 933 31 54 16",
    "sg:postcode":"08014",
    "sg:province":"Barcelona",
    "wof:name":"Tabatha-2 S. L.",
    "wof:placetype":"venue"
},
  "geometry": {"coordinates":[2.1331269741,41.3677444458],"type":"Point"}
}