{
  "type": "Feature",
  "properties": {
    "iso:country":"ES",
    "sg:address":"P. Ori, 6",
    "sg:city":"Iru\u00f1a",
    "sg:orig_category":"Peluqueros: De Se\u00d1oras",
    "sg:phone":"+34 948 24 54 61",
    "sg:postcode":"31006",
    "sg:province":"Navarra",
    "wof:name":"Eraso Andueza Yolanda",
    "wof:placetype":"venue"
},
  "geometry": {"coordinates":[-1.6343519688,42.8048477173],"type":"Point"}
}