{
  "type": "Feature",
  "properties": {
    "addr:full":"Calle de Antonio Viamonte, 2 Fuentes Ebro Zaragoza 50740",
    "addr:housenumber":"2",
    "addr:postcode":"50740",
    "addr:street":"Calle De Antonio Viamonte",
    "iso:country":"ES",
    "sg:address":"Calle de Antonio Viamonte, 2",
    "sg:city":"Fuentes Ebro",
    "sg:orig_category":"Empresas De Pintura Y Revestimientos",
    "sg:phone":"+34 976 16 10 48",
    "sg:postcode":"50740",
    "sg:province":"Zaragoza",
    "wof:name":"Calvo Jareas Enrique",
    "wof:placetype":"venue"
},
  "geometry": {"coordinates":[-0.6324443817,41.5118293762],"type":"Point"}
}