{
  "type": "Feature",
  "properties": {
    "addr:full":"Avda Orense, 26 Palas Rei Lugo 27200",
    "addr:housenumber":"26",
    "addr:postcode":"27200",
    "addr:street":"Avda Orense",
    "iso:country":"ES",
    "sg:address":"Avda Orense, 26",
    "sg:city":"Palas Rei",
    "sg:orig_category":"Carnicer\u00cdas, Carnicer\u00cdas",
    "sg:phone":"+34 982 38 01 87",
    "sg:postcode":"27200",
    "sg:province":"Lugo",
    "wof:name":"Garcia Salgado Jaime",
    "wof:placetype":"venue"
},
  "geometry": {"coordinates":[-7.8686218262,42.8725967407],"type":"Point"}
}