{
  "type": "Feature",
  "properties": {
    "iso:country":"ES",
    "sg:address":"Calle de San Jacinto, 28",
    "sg:city":"Valencia",
    "sg:orig_category":"Partidos Pol\u00cdticos",
    "sg:phone":"+34 963 82 66 06",
    "sg:postcode":"46008",
    "sg:province":"Valencia",
    "wof:name":"Bloc Nacionalista Valencia",
    "wof:placetype":"venue"
},
  "geometry": {"coordinates":[-0.3919160068,39.4751701355],"type":"Point"}
}