{
  "type": "Feature",
  "properties": {
    "addr:full":"Carr Magdalena Miro, 2 Vilanova I La Geltru Barcelona 08800",
    "addr:housenumber":"2",
    "addr:postcode":"08800",
    "addr:street":"Carr Magdalena Miro",
    "iso:country":"ES",
    "sg:address":"Carr Magdalena Miro, 2",
    "sg:city":"Vilanova I La Geltru",
    "sg:orig_category":"Guarder\u00cdas",
    "sg:phone":"+34 938 15 37 46",
    "sg:postcode":"08800",
    "sg:province":"Barcelona",
    "wof:name":"Centre D'educacio Xiu-xiu S.l.",
    "wof:placetype":"venue"
},
  "geometry": {"coordinates":[1.7271009684,41.2210388184],"type":"Point"}
}