{
  "type": "Feature",
  "properties": {
    "iso:country":"ES",
    "sg:address":"Carrer de Numancia, 137",
    "sg:city":"Barcelona",
    "sg:orig_category":"Bancos",
    "sg:phone":"+34 934 30 24 28",
    "sg:postcode":"08029",
    "sg:province":"Barcelona",
    "wof:name":"Bt Espa\u00d1a Compa\u00d1ia De Servicios Globales De Telecomunicaciones S.a.u.",
    "wof:placetype":"venue"
},
  "geometry": {"coordinates":[2.1345329285,41.3874664307],"type":"Point"}
}