{
  "type": "Feature",
  "properties": {
    "iso:country":"ES",
    "sg:address":"Carrer de Valencia, 24",
    "sg:city":"S. Feliu Guixols",
    "sg:orig_category":"Asociaciones Y Clubs Deportivos",
    "sg:phone":"+34 972 82 10 23",
    "sg:postcode":"17220",
    "sg:province":"Girona",
    "sg:website":"www.joismart.com",
    "wof:name":"Fisioterapia Jois Mart S.l.",
    "wof:placetype":"venue"
},
  "geometry": {"coordinates":[3.0238249302,41.7917709351],"type":"Point"}
}