{
  "type": "Feature",
  "properties": {
    "addr:full":"Papabellotas (p I Antequera), 5 Antequera M\u00e1laga 29200",
    "addr:housenumber":"5",
    "addr:postcode":"29200",
    "addr:street":"Papabellotas;Antequera",
    "iso:country":"ES",
    "sg:address":"Papabellotas (p I Antequera), 5",
    "sg:city":"Antequera",
    "sg:orig_category":"Empresas De Carpinter\u00cda",
    "sg:phone":"+34 952 84 55 41",
    "sg:postcode":"29200",
    "sg:province":"M\u00e1laga",
    "wof:name":"Prieto Arjona Juan",
    "wof:placetype":"venue"
},
  "geometry": {"coordinates":[-4.5314850807,37.0313987732],"type":"Point"}
}