{
  "type": "Feature",
  "properties": {
    "addr:full":"Carrer de Oliveres, S/n Mora Nova Tarragona 43770",
    "addr:housenumber":"s / n",
    "addr:postcode":"43770",
    "addr:street":"Carrer De Oliveres",
    "iso:country":"ES",
    "sg:address":"Carrer de Oliveres, S/n",
    "sg:city":"Mora Nova",
    "sg:orig_category":"Empresas De Carpinter\u00cda",
    "sg:phone":"+34 977 40 32 41",
    "sg:postcode":"43770",
    "sg:province":"Tarragona",
    "wof:name":"Compac Mora S L",
    "wof:placetype":"venue"
},
  "geometry": {"coordinates":[0.6463649869,41.1044387817],"type":"Point"}
}