{
  "type": "Feature",
  "properties": {
    "addr:full":"Ctra Almagro, Km. 0017,5 Calzada Calatrava Ciudad Real 13370",
    "addr:postcode":"13370",
    "addr:street":"Ctra Almagro Km. 0017,5 Calzada Calatrava",
    "iso:country":"ES",
    "sg:address":"Ctra Almagro, Km. 0017,5",
    "sg:city":"Calzada Calatrava",
    "sg:orig_category":"Aguas (distribuci\u00d3n, Servicios)",
    "sg:phone":"+34 926 69 31 62",
    "sg:postcode":"13370",
    "sg:province":"Ciudad Real",
    "wof:name":"Aquagest S.a.",
    "wof:placetype":"venue"
},
  "geometry": {"coordinates":[-3.7612674236,38.7727279663],"type":"Point"}
}