{
  "type": "Feature",
  "properties": {
    "addr:full":"Ana De Portugal Y Borja, S/n Sollana Valencia 46430",
    "addr:housenumber":"/ n",
    "addr:postcode":"46430",
    "addr:street":"S",
    "iso:country":"ES",
    "sg:address":"Ana De Portugal Y Borja, S/n",
    "sg:city":"Sollana",
    "sg:orig_category":"Muebles",
    "sg:phone":"+34 961 74 25 22",
    "sg:postcode":"46430",
    "sg:province":"Valencia",
    "wof:name":"Arques Sollana C.b.",
    "wof:placetype":"venue"
},
  "geometry": {"coordinates":[-0.3842526972,39.2888526917],"type":"Point"}
}