{
  "type": "Feature",
  "properties": {
    "iso:country":"ES",
    "sg:address":"Calle de Estribor, 1",
    "sg:city":"Grau I Platja",
    "sg:orig_category":"Empresarios",
    "sg:phone":"+34 962 84 47 52",
    "sg:postcode":"46730",
    "sg:province":"Valencia",
    "wof:name":"Garcia Moya Juan Jose",
    "wof:placetype":"venue"
},
  "geometry": {"coordinates":[-0.3768048882,39.4702377319],"type":"Point"}
}