{
  "type": "Feature",
  "properties": {
    "addr:full":"Calle de Periodista Garcia Prieto, 8 Cordoba C\u00f3rdoba 14010",
    "addr:housenumber":"8",
    "addr:postcode":"14010",
    "addr:street":"Calle De Periodista Garcia Prieto;Co\u0301Rdoba",
    "iso:country":"ES",
    "sg:address":"Calle de Periodista Garcia Prieto, 8",
    "sg:city":"Cordoba",
    "sg:orig_category":"Caf\u00c9s, Bares, Cervecer\u00cdas",
    "sg:phone":"+34 957 25 50 62",
    "sg:postcode":"14010",
    "sg:province":"C\u00f3rdoba",
    "wof:name":"Jimenez Pineda Juan",
    "wof:placetype":"venue"
},
  "geometry": {"coordinates":[-4.7642102242,37.8874092102],"type":"Point"}
}