{
  "type": "Feature",
  "properties": {
    "addr:full":"Calle de San Juan, 13 Aranda Duero Burgos 09400",
    "addr:housenumber":"13",
    "addr:postcode":"09400",
    "addr:street":"Calle De San Juan",
    "iso:country":"ES",
    "sg:address":"Calle de San Juan, 13",
    "sg:city":"Aranda Duero",
    "sg:orig_category":"Laboratorios Y Trabajos De Fotograf\u00cda, V\u00cddeo Y Cine",
    "sg:phone":"+34 947 50 77 73",
    "sg:postcode":"09400",
    "sg:province":"Burgos",
    "wof:name":"Lara Palacios Florentino",
    "wof:placetype":"venue"
},
  "geometry": {"coordinates":[-3.6903181076,41.6718711853],"type":"Point"}
}