{
  "type": "Feature",
  "properties": {
    "iso:country":"ES",
    "sg:address":"Calle de Rosario Pino, 12",
    "sg:city":"Madrid",
    "sg:orig_category":"Ingenier\u00cda, Centros De Estudios (diversos)",
    "sg:phone":"+34 915 71 58 72",
    "sg:postcode":"28020",
    "sg:province":"Madrid",
    "wof:name":"Tecnicas Territoriales Y Urbanas S.l.",
    "wof:placetype":"venue"
},
  "geometry": {"coordinates":[-3.692193985,40.4622612],"type":"Point"}
}