{
  "type": "Feature",
  "properties": {
    "iso:country":"ES",
    "sg:address":"Pase Habana, 40",
    "sg:city":"Madrid",
    "sg:orig_category":"Medicamentos",
    "sg:phone":"+34 915 63 98 61",
    "sg:postcode":"28036",
    "sg:province":"Madrid",
    "sg:website":"www.farmaciamartinmegia.com",
    "wof:name":"Martin Megia Caridad",
    "wof:placetype":"venue"
},
  "geometry": {"coordinates":[-3.6868960857,40.4506111145],"type":"Point"}
}