{
  "type": "Feature",
  "properties": {
    "addr:full":"Pla\u00c7 Sardana, S/n Platja D'aro Girona 17250",
    "addr:housenumber":"s / n",
    "addr:postcode":"17250",
    "iso:country":"ES",
    "sg:address":"Pla\u00c7 Sardana, S/n",
    "sg:city":"Platja D'aro",
    "sg:orig_category":"Abogados",
    "sg:phone":"+34 972 81 83 31",
    "sg:postcode":"17250",
    "sg:province":"Girona",
    "sg:website":"www.drhoehne.com",
    "wof:name":"Hohne  Hans Hellmut",
    "wof:placetype":"venue"
},
  "geometry": {"coordinates":[3.0651328564,41.8168296814],"type":"Point"}
}