{
  "type": "Feature",
  "properties": {
    "iso:country":"ES",
    "sg:address":"Calle de Key Mu\u00d1oz, 26",
    "sg:city":"Icod De Los Vinos",
    "sg:orig_category":"Cerrajer\u00cda, Ferrallista",
    "sg:phone":"+34 922 81 60 00",
    "sg:postcode":"38430",
    "sg:province":"Santa Cruz De Tenerife",
    "wof:name":"La Llave Maestra C.b.",
    "wof:placetype":"venue"
},
  "geometry": {"coordinates":[-16.7173099518,28.3682537079],"type":"Point"}
}