{
  "type": "Feature",
  "properties": {
    "iso:country":"ES",
    "sg:address":"Avda Rey Juan Carlos I, 37",
    "sg:city":"Tarancon",
    "sg:orig_category":"Bebidas",
    "sg:phone":"+34 969 32 54 27",
    "sg:postcode":"16400",
    "sg:province":"Cuenca",
    "wof:name":"Aguas Minerales Aragon S.l.",
    "wof:placetype":"venue"
},
  "geometry": {"coordinates":[-3.0054235458,40.0065536499],"type":"Point"}
}