{
  "type": "Feature",
  "properties": {
    "iso:country":"ES",
    "sg:address":"Calle de Artekalea, 4",
    "sg:city":"Durango",
    "sg:orig_category":"Confecci\u00d3n De Trajes Para Se\u00d1oras",
    "sg:phone":"+34 946 21 80 66",
    "sg:postcode":"48200",
    "sg:province":"Vizcaya",
    "wof:name":"Modas Bardeci S.l.",
    "wof:placetype":"venue"
},
  "geometry": {"coordinates":[-2.6314659119,43.1675720215],"type":"Point"}
}