{
  "type": "Feature",
  "properties": {
    "addr:full":"Plaz Padre Hilario, 4 Palmas De Gran Canaria Las Palmas 35003",
    "addr:housenumber":"4",
    "addr:postcode":"35003",
    "addr:street":"Hilario",
    "iso:country":"ES",
    "sg:address":"Plaz Padre Hilario, 4",
    "sg:city":"Palmas De Gran Canaria",
    "sg:orig_category":"Abogados",
    "sg:phone":"+34 928 38 39 81",
    "sg:postcode":"35003",
    "sg:province":"Las Palmas",
    "wof:name":"Martin Amador Rodolfo",
    "wof:placetype":"venue"
},
  "geometry": {"coordinates":[-15.4201908112,28.1112232208],"type":"Point"}
}