{
  "type": "Feature",
  "properties": {
    "iso:country":"ES",
    "sg:address":"Calle de Arturo Soria, 126",
    "sg:city":"Madrid",
    "sg:orig_category":"Bisuter\u00cda, Joyer\u00cda, Relojer\u00cda (al Por Menor)",
    "sg:phone":"+34 913 88 34 33",
    "sg:postcode":"28043",
    "sg:province":"Madrid",
    "sg:website":"www.accessorize.es",
    "wof:name":"Compleshop S.l.",
    "wof:placetype":"venue"
},
  "geometry": {"coordinates":[-3.6510543823,40.4495353699],"type":"Point"}
}