{
  "type": "Feature",
  "properties": {
    "addr:full":"Carrer de Progres, 116 Hospitalet Llobregat Barcelona 08904",
    "addr:housenumber":"116",
    "addr:postcode":"08904",
    "addr:street":"Carrer De Progres",
    "iso:country":"ES",
    "sg:address":"Carrer de Progres, 116",
    "sg:city":"Hospitalet Llobregat",
    "sg:orig_category":"Colchones (fabricaci\u00d3n, Al Por Mayor, Al Por Menor)",
    "sg:phone":"+34 933 34 87 92",
    "sg:postcode":"08904",
    "sg:province":"Barcelona",
    "wof:name":"Matadasseria La Becaina S.c.p.",
    "wof:placetype":"venue"
},
  "geometry": {"coordinates":[2.1210949421,41.3716049194],"type":"Point"}
}