{
  "type": "Feature",
  "properties": {
    "addr:full":"Carr Comte De Rossello, 8 Eivissa Islas Baleares 07800",
    "addr:housenumber":"8",
    "addr:postcode":"07800",
    "addr:street":"Carr Comte De Rossello",
    "iso:country":"ES",
    "sg:address":"Carr Comte De Rossello, 8",
    "sg:city":"Eivissa",
    "sg:orig_category":"Bisuter\u00cda, Joyer\u00cda, Relojer\u00cda (al Por Menor)",
    "sg:phone":"+34 971 31 04 23",
    "sg:postcode":"07800",
    "sg:province":"Islas Baleares",
    "wof:name":"Afrodisio Bonet Y Otros Cdad",
    "wof:placetype":"venue"
},
  "geometry": {"coordinates":[1.4349648952,38.9094238281],"type":"Point"}
}