{
  "type": "Feature",
  "properties": {
    "iso:country":"ES",
    "sg:address":"Calle de Forja, 92",
    "sg:city":"Valladolid",
    "sg:orig_category":"Molduras, Junquillos, Listones Y Molduras Perforadas",
    "sg:phone":"+34 983 22 60 46",
    "sg:postcode":"47008",
    "sg:province":"Valladolid",
    "wof:name":"J.j.fraile S.l.",
    "wof:placetype":"venue"
},
  "geometry": {"coordinates":[-4.7361397743,41.6250419617],"type":"Point"}
}