{
  "type": "Feature",
  "properties": {
    "addr:full":"Calle de Cortes (las), 4 Sevilla Sevilla 41002",
    "addr:housenumber":"4",
    "addr:postcode":"41002",
    "addr:street":"Calle De Cortes Las",
    "iso:country":"ES",
    "sg:address":"Calle de Cortes (las), 4",
    "sg:city":"Sevilla",
    "sg:orig_category":"Producci\u00d3n, Comercio De Cereales",
    "sg:phone":"+34 954 90 28 28",
    "sg:postcode":"41002",
    "sg:province":"Sevilla",
    "wof:name":"M.lagares S.a.",
    "wof:placetype":"venue"
},
  "geometry": {"coordinates":[-5.996591568,37.3943519592],"type":"Point"}
}