{
  "type": "Feature",
  "properties": {
    "addr:full":"Calle de Donoso Cortes, 7 Gijon Asturias 33204",
    "addr:housenumber":"7",
    "addr:postcode":"33204",
    "addr:street":"Calle De Donoso Cortes",
    "iso:country":"ES",
    "sg:address":"Calle de Donoso Cortes, 7",
    "sg:city":"Gijon",
    "sg:orig_category":"Obras Y Organismos Sociales",
    "sg:phone":"+34 985 36 16 59",
    "sg:postcode":"33204",
    "sg:province":"Asturias",
    "wof:name":"Fundacion Siloe",
    "wof:placetype":"venue"
},
  "geometry": {"coordinates":[-5.6476168633,43.5336532593],"type":"Point"}
}