{
  "type": "Feature",
  "properties": {
    "addr:full":"Carrer de Joaquim Verdaguer, 4 Arenal Islas Baleares 07600",
    "addr:housenumber":"4",
    "addr:postcode":"07600",
    "addr:street":"Carrer De Joaquim Verdaguer",
    "iso:country":"ES",
    "sg:address":"Carrer de Joaquim Verdaguer, 4",
    "sg:city":"Arenal",
    "sg:orig_category":"Molduras, Junquillos, Listones Y Molduras Perforadas",
    "sg:phone":"+34 971 74 45 08",
    "sg:postcode":"07600",
    "sg:province":"Islas Baleares",
    "wof:name":"Pistorius Joannes  Cornelis",
    "wof:placetype":"venue"
},
  "geometry": {"coordinates":[2.750672102,39.5082168579],"type":"Point"}
}