{
  "type": "Feature",
  "properties": {
    "iso:country":"ES",
    "sg:address":"Calle de Almendro, 26",
    "sg:city":"Baza",
    "sg:orig_category":"Venta, Instalaci\u00d3n De Calefacci\u00d3n",
    "sg:phone":"+34 958 70 13 14",
    "sg:postcode":"18800",
    "sg:province":"Granada",
    "wof:name":"Domingo Sabina Manuel",
    "wof:placetype":"venue"
},
  "geometry": {"coordinates":[-2.771831274,37.491027832],"type":"Point"}
}