{
  "type": "Feature",
  "properties": {
    "iso:country":"ES",
    "sg:address":"Calle de Arroyos (los), S/n",
    "sg:city":"Milla Del Rio",
    "sg:orig_category":"Empresas De Desmonte",
    "sg:phone":"+34 987 35 77 62",
    "sg:postcode":"24283",
    "sg:province":"Le\u00f3n",
    "wof:name":"Llamas Martinez Simon",
    "wof:placetype":"venue"
},
  "geometry": {"coordinates":[-5.8479251862,42.5727157593],"type":"Point"}
}