{
  "type": "Feature",
  "properties": {
    "addr:full":"Calle de Clara Del Rey, 59 Madrid Madrid 28002",
    "addr:housenumber":"59",
    "addr:postcode":"madrid;28002",
    "addr:street":"Calle De Clara Del Rey",
    "iso:country":"ES",
    "sg:address":"Calle de Clara Del Rey, 59",
    "sg:city":"Madrid",
    "sg:orig_category":"Papel (al Por Mayor)",
    "sg:phone":"+34 915 19 36 27",
    "sg:postcode":"28002",
    "sg:province":"Madrid",
    "sg:website":"www.fesa-formularios.com",
    "wof:name":"Formularios Europeos S. A.",
    "wof:placetype":"venue"
},
  "geometry": {"coordinates":[-3.668289423,40.4456100464],"type":"Point"}
}