{
  "type": "Feature",
  "properties": {
    "iso:country":"ES",
    "sg:address":"Calle de Pino (del), S/n",
    "sg:city":"Mazarron",
    "sg:orig_category":"Ropa Para Ni\u00d1os (al Por Menor)",
    "sg:phone":"+34 968 59 19 17",
    "sg:postcode":"30870",
    "sg:province":"Murcia",
    "wof:name":"Boutique Peque\u00f1ines S.l.",
    "wof:placetype":"venue"
},
  "geometry": {"coordinates":[-1.3154289722,37.5975608826],"type":"Point"}
}