{
  "type": "Feature",
  "properties": {
    "addr:full":"Carrer de Saclosa, 31 Manresa Barcelona 08241",
    "addr:housenumber":"31",
    "addr:postcode":"08241",
    "addr:street":"Carrer De Saclosa",
    "iso:country":"ES",
    "sg:address":"Carrer de Saclosa, 31",
    "sg:city":"Manresa",
    "sg:orig_category":"M\u00c9dicos: Medicina General Orientada A La Acupuntura",
    "sg:phone":"+34 938 72 39 23",
    "sg:postcode":"08241",
    "sg:province":"Barcelona",
    "wof:name":"Torras Moliner Joan",
    "wof:placetype":"venue"
},
  "geometry": {"coordinates":[1.8196539879,41.7288284302],"type":"Point"}
}