{
  "type": "Feature",
  "properties": {
    "addr:full":"Calle de General Pingarron, S/n Getafe Madrid 28901",
    "addr:housenumber":"s / n",
    "addr:postcode":"28901",
    "addr:street":"Calle De General Pingarron",
    "iso:country":"ES",
    "sg:address":"Calle de General Pingarron, S/n",
    "sg:city":"Getafe",
    "sg:orig_category":"Aparcamientos (infraestructuras, Accesorios)",
    "sg:phone":"+34 916 83 26 58",
    "sg:postcode":"28901",
    "sg:province":"Madrid",
    "wof:name":"Aparcamientos Getafe Sur S.l.",
    "wof:placetype":"venue"
},
  "geometry": {"coordinates":[-3.7329463959,40.3085212708],"type":"Point"}
}