{
  "type": "Feature",
  "properties": {
    "addr:full":"Avda Alicante, 11 Biar Alicante 03410",
    "addr:housenumber":"11",
    "addr:postcode":"03410",
    "addr:street":"Avda Alicante",
    "iso:country":"ES",
    "sg:address":"Avda Alicante, 11",
    "sg:city":"Biar",
    "sg:orig_category":"Reposter\u00cdas",
    "sg:phone":"+34 965 81 10 25",
    "sg:postcode":"03410",
    "sg:province":"Alicante",
    "wof:name":"Panaderia Vilar",
    "wof:placetype":"venue"
},
  "geometry": {"coordinates":[-0.7630950212,38.6278915405],"type":"Point"}
}