{
  "type": "Feature",
  "properties": {
    "addr:full":"Calle de Aurora, 11 Puerto De Santa Maria C\u00e1diz 11500",
    "addr:housenumber":"11",
    "addr:postcode":"11500",
    "addr:street":"Calle De Aurora;Ca\u0301Diz",
    "iso:country":"ES",
    "sg:address":"Calle de Aurora, 11",
    "sg:city":"Puerto De Santa Maria",
    "sg:orig_category":"Centros De Coordinaci\u00d3n",
    "sg:phone":"+34 956 87 03 36",
    "sg:postcode":"11500",
    "sg:province":"C\u00e1diz",
    "wof:name":"Sanchez De Nieva Aguera Rafael",
    "wof:placetype":"venue"
},
  "geometry": {"coordinates":[-6.2284545898,36.5932922363],"type":"Point"}
}