{
  "type": "Feature",
  "properties": {
    "iso:country":"ES",
    "sg:address":"Carrer de General Moragues, 89",
    "sg:city":"Reus",
    "sg:orig_category":"Procuradores",
    "sg:phone":"+34 977 32 61 03",
    "sg:postcode":"43203",
    "sg:province":"Tarragona",
    "wof:name":"Estivill Balsells Francesc Xavier",
    "wof:placetype":"venue"
},
  "geometry": {"coordinates":[1.1058750153,41.1604270935],"type":"Point"}
}