{
  "type": "Feature",
  "properties": {
    "addr:full":"Poli Poligono Industrial, S/n Barros Cantabria 39408",
    "addr:postcode":"39408",
    "addr:street":"Poligono Industrial S / N",
    "iso:country":"ES",
    "sg:address":"Poli Poligono Industrial, S/n",
    "sg:city":"Barros",
    "sg:orig_category":"Carros Elevadores, Carros De Operaciones Portuarias",
    "sg:phone":"+34 942 83 21 16",
    "sg:postcode":"39408",
    "sg:province":"Cantabria",
    "wof:name":"Eleccar Sociedad Cooperativa",
    "wof:placetype":"venue"
},
  "geometry": {"coordinates":[-4.0770049095,43.279712677],"type":"Point"}
}