{
  "type": "Feature",
  "properties": {
    "iso:country":"ES",
    "sg:address":"Carrer de Ramon Y Cajal, 62",
    "sg:city":"Alcanar",
    "sg:orig_category":"Centros Empresariales",
    "sg:phone":"+34 977 73 22 30",
    "sg:postcode":"43530",
    "sg:province":"Tarragona",
    "wof:name":"Af Proafis S.l.",
    "wof:placetype":"venue"
},
  "geometry": {"coordinates":[0.4813925922,40.5401382446],"type":"Point"}
}