{
  "type": "Feature",
  "properties": {
    "addr:full":"Carrer de Pare Sallares, 79 Sabadell Barcelona 08201",
    "addr:housenumber":"79",
    "addr:postcode":"08201",
    "addr:street":"Carrer De Pare Sallares",
    "iso:country":"ES",
    "sg:address":"Carrer de Pare Sallares, 79",
    "sg:city":"Sabadell",
    "sg:orig_category":"El Hogar: Amueblado, Acondicionamiento, Decoraci\u00d3n Y Mantenimiento",
    "sg:phone":"+34 937 25 03 97",
    "sg:postcode":"08201",
    "sg:province":"Barcelona",
    "wof:name":"Melo Valls Jose",
    "wof:placetype":"venue"
},
  "geometry": {"coordinates":[2.1033170223,41.5479698181],"type":"Point"}
}