{
  "type": "Feature",
  "properties": {
    "iso:country":"ES",
    "sg:address":"Carr Camprodon, 66",
    "sg:city":"Arbucies",
    "sg:orig_category":"Panader\u00cdas, Panader\u00cdas",
    "sg:phone":"+34 972 86 07 31",
    "sg:postcode":"17401",
    "sg:province":"Girona",
    "wof:name":"El Hssini  Chemsdoha",
    "wof:placetype":"venue"
},
  "geometry": {"coordinates":[2.5175039768,41.8150215149],"type":"Point"}
}