{
  "type": "Feature",
  "properties": {
    "addr:full":"Calle de Residencia, 52 San Lorenzo De El Escorial Madrid 28200",
    "addr:housenumber":"52",
    "addr:postcode":"28200",
    "addr:street":"Calle De Residencia",
    "iso:country":"ES",
    "sg:address":"Calle de Residencia, 52",
    "sg:city":"San Lorenzo De El Escorial",
    "sg:orig_category":"Agencias Y Agentes Comerciales, Representantes",
    "sg:phone":"+34 918 90 51 00",
    "sg:postcode":"28200",
    "sg:province":"Madrid",
    "wof:name":"Cian Conservando El Arte S.l.",
    "wof:placetype":"venue"
},
  "geometry": {"coordinates":[-4.1422810555,40.5991172791],"type":"Point"}
}