{
  "type": "Feature",
  "properties": {
    "iso:country":"ES",
    "sg:address":"Carrer de Filharmonica (la), 8",
    "sg:city":"Altea",
    "sg:orig_category":"Cr\u00cda De Animales",
    "sg:phone":"+34 965 84 04 20",
    "sg:postcode":"03590",
    "sg:province":"Alicante",
    "wof:name":"Juan Martinez Pedro",
    "wof:placetype":"venue"
},
  "geometry": {"coordinates":[-0.0489519984,38.5993843079],"type":"Point"}
}