{
  "type": "Feature",
  "properties": {
    "addr:full":"C/ Poeta Miguel Hernandez, 38 Elche Alicante 03201",
    "addr:housenumber":"38",
    "addr:postcode":"03201",
    "addr:street":"C / Poeta Miguel Hernandez",
    "iso:country":"ES",
    "sg:address":"C/ Poeta Miguel Hernandez, 38",
    "sg:city":"Elche",
    "sg:orig_category":"Fabricaci\u00d3n De Ventanas",
    "sg:phone":"+34 965 46 30 14",
    "sg:postcode":"03201",
    "sg:province":"Alicante",
    "wof:name":"Amat Torregrosa Ana Teresa",
    "wof:placetype":"venue"
},
  "geometry": {"coordinates":[-0.556838274,38.1914367676],"type":"Point"}
}