{
  "type": "Feature",
  "properties": {
    "iso:country":"ES",
    "sg:address":"Avda Jose Antonio, 154",
    "sg:city":"Polan",
    "sg:orig_category":"Muebles, Minoristas",
    "sg:phone":"+34 925 37 01 39",
    "sg:postcode":"45161",
    "sg:province":"Toledo",
    "wof:name":"Muebles Polan El Fabricante S. A.",
    "wof:placetype":"venue"
},
  "geometry": {"coordinates":[-4.1619591713,39.7910118103],"type":"Point"}
}