{
  "type": "Feature",
  "properties": {
    "addr:full":"Avgd Baixada L'estacio, 19 Xativa Valencia 46800",
    "addr:housenumber":"19",
    "addr:postcode":"46800",
    "addr:street":"Baixada L'Estacio",
    "iso:country":"ES",
    "sg:address":"Avgd Baixada L'estacio, 19",
    "sg:city":"Xativa",
    "sg:orig_category":"Panader\u00cdas, Panader\u00cdas",
    "sg:phone":"+34 962 27 62 83",
    "sg:postcode":"46800",
    "sg:province":"Valencia",
    "wof:name":"Heladeria Pasteleria Sirope S.l.",
    "wof:placetype":"venue"
},
  "geometry": {"coordinates":[-0.5236290097,38.9910926819],"type":"Point"}
}