{
  "type": "Feature",
  "properties": {
    "iso:country":"ES",
    "sg:address":"Calle de Gobernador Garcia Hernandez, 10",
    "sg:city":"Pto. Rosario",
    "sg:classifiers":[
        {
            "category":"Tea Room",
            "subcategory":"None",
            "type":"Food & Drink"
        }
    ],
    "sg:phone":"+34 928 85 92 46",
    "sg:postcode":"35600",
    "sg:province":"Las Palmas",
    "sg:tags":[
        "snack"
    ],
    "wof:name":"De Leon Domingo Juan",
    "wof:placetype":"venue"
},
  "geometry": {"coordinates":[-13.8578596115,28.4993114471],"type":"Point"}
}