{
  "type": "Feature",
  "properties": {
    "iso:country":"ES",
    "sg:address":"Plaz Constitucion, 6",
    "sg:city":"Salamanca",
    "sg:orig_category":"Abogados",
    "sg:phone":"+34 923 21 99 29",
    "sg:postcode":"37001",
    "sg:province":"Salamanca",
    "wof:name":"Arenas Rodriguez Ramon Jose",
    "wof:placetype":"venue"
},
  "geometry": {"coordinates":[-5.6601657867,40.9661102295],"type":"Point"}
}