{
  "type": "Feature",
  "properties": {
    "addr:full":"Carrer de Dante, 9 Manresa Barcelona 08242",
    "addr:housenumber":"9",
    "addr:postcode":"08242",
    "addr:street":"Carrer De Dante",
    "iso:country":"ES",
    "sg:address":"Carrer de Dante, 9",
    "sg:city":"Manresa",
    "sg:orig_category":"Institutos De Belleza",
    "sg:phone":"+34 938 73 43 90",
    "sg:postcode":"08242",
    "sg:province":"Barcelona",
    "wof:name":"Vidal Cervos Josefina",
    "wof:placetype":"venue"
},
  "geometry": {"coordinates":[1.8317079544,41.7354011536],"type":"Point"}
}