{
  "type": "Feature",
  "properties": {
    "addr:full":"Trav De Gracia, 139 Barcelona Barcelona 08012",
    "addr:housenumber":"139",
    "addr:postcode":"08012",
    "addr:street":"Trav De Gracia",
    "iso:country":"ES",
    "sg:address":"Trav De Gracia, 139",
    "sg:city":"Barcelona",
    "sg:orig_category":"Poller\u00cda Y Caza (al Por Menor)",
    "sg:phone":"+34 932 18 26 61",
    "sg:postcode":"08012",
    "sg:province":"Barcelona",
    "wof:name":"Fite Roca Montserrat",
    "wof:placetype":"venue"
},
  "geometry": {"coordinates":[2.156498909,41.4005393982],"type":"Point"}
}