{
  "type": "Feature",
  "properties": {
    "iso:country":"ES",
    "sg:address":"Carrer de Galvany, 17",
    "sg:city":"Hospitalet Llobregat",
    "sg:orig_category":"Molduras, Junquillos, Listones Y Molduras Perforadas",
    "sg:phone":"+34 932 61 15 64",
    "sg:postcode":"08901",
    "sg:province":"Barcelona",
    "wof:name":"Anta Rodriguez Atilano",
    "wof:placetype":"venue"
},
  "geometry": {"coordinates":[2.1087856293,41.3640785217],"type":"Point"}
}