{
  "type": "Feature",
  "properties": {
    "addr:full":"Calle de Joaquin Benlloch, 79 Valencia Valencia 46026",
    "addr:housenumber":"79",
    "addr:postcode":"46026",
    "addr:street":"Calle De Joaquin Benlloch",
    "iso:country":"ES",
    "sg:address":"Calle de Joaquin Benlloch, 79",
    "sg:city":"Valencia",
    "sg:orig_category":"Automatizaci\u00d3n De Procesos Industriales Y De Edificaci\u00d3n (estudios, Instalaci\u00d3n)",
    "sg:phone":"+34 963 33 20 46",
    "sg:postcode":"46026",
    "sg:province":"Valencia",
    "sg:website":"www.erreka.com",
    "wof:name":"Talleres Matz-erreka S.c.i.",
    "wof:placetype":"venue"
},
  "geometry": {"coordinates":[-0.3731229901,39.448551178],"type":"Point"}
}