{
  "type": "Feature",
  "properties": {
    "iso:country":"ES",
    "sg:address":"Carrer de Rossello, 470",
    "sg:city":"Barcelona",
    "sg:orig_category":"Ropa Para Se\u00d1oras (al Por Menor)",
    "sg:phone":"+34 934 36 94 61",
    "sg:postcode":"08025",
    "sg:province":"Barcelona",
    "wof:name":"Gasol Saurina Antonio",
    "wof:placetype":"venue"
},
  "geometry": {"coordinates":[2.1773240566,41.4081573486],"type":"Point"}
}