{
  "type": "Feature",
  "properties": {
    "iso:country":"ES",
    "sg:address":"Carrer de Pont De Can Claveri, 48",
    "sg:city":"Rubi",
    "sg:orig_category":"Artes Gr\u00c1ficas, Artes Pl\u00c1sticas (curso)",
    "sg:phone":"+34 935 88 01 64",
    "sg:postcode":"08191",
    "sg:province":"Barcelona",
    "wof:name":"Realizacion Y Dise\u00f1o Grafico S.a.",
    "wof:placetype":"venue"
},
  "geometry": {"coordinates":[2.0292611122,41.5012245178],"type":"Point"}
}