{
  "type": "Feature",
  "properties": {
    "addr:full":"Calle de Buensuceso, 4 Granada Granada 18002",
    "addr:housenumber":"4",
    "addr:postcode":"18002",
    "addr:street":"Calle De Buensuceso",
    "iso:country":"ES",
    "sg:address":"Calle de Buensuceso, 4",
    "sg:city":"Granada",
    "sg:orig_category":"Abogados",
    "sg:phone":"+34 958 53 52 31",
    "sg:postcode":"18002",
    "sg:province":"Granada",
    "wof:name":"Benitez-alahija Sanchez Matias",
    "wof:placetype":"venue"
},
  "geometry": {"coordinates":[-3.6022310257,37.1756668091],"type":"Point"}
}