{
  "type": "Feature",
  "properties": {
    "iso:country":"ES",
    "sg:address":"Calle de Alcala, 147",
    "sg:city":"Madrid",
    "sg:orig_category":"Sociedades, Compa\u00d1\u00cdas Aseguradoras",
    "sg:phone":"+34 915 78 32 31",
    "sg:postcode":"28009",
    "sg:province":"Madrid",
    "sg:website":"www.paginasamarillas.es",
    "wof:name":"Raquel Alvarez Sanchez Y Otros Cdad.",
    "wof:placetype":"venue"
},
  "geometry": {"coordinates":[-3.6769337654,40.4242668152],"type":"Point"}
}