{
  "type": "Feature",
  "properties": {
    "iso:country":"ES",
    "sg:address":"Cno Bracal El Roncador, S/n",
    "sg:city":"Xativa",
    "sg:orig_category":"Artes Gr\u00c1ficas, Artes Pl\u00c1sticas (curso)",
    "sg:phone":"+34 962 28 40 25",
    "sg:postcode":"46800",
    "sg:province":"Valencia",
    "wof:name":"Coflex S.l.",
    "wof:placetype":"venue"
},
  "geometry": {"coordinates":[-0.524864018,38.9937438965],"type":"Point"}
}