{
  "type": "Feature",
  "properties": {
    "iso:country":"ES",
    "sg:address":"Calle de Tibi, 6",
    "sg:city":"Ibi",
    "sg:orig_category":"Servicios De Telecomunicaciones",
    "sg:phone":"+34 966 55 40 71",
    "sg:postcode":"03440",
    "sg:province":"Alicante",
    "wof:name":"Ibivision S.a",
    "wof:placetype":"venue"
},
  "geometry": {"coordinates":[-0.5765699744,38.6237678528],"type":"Point"}
}