{
  "type": "Feature",
  "properties": {
    "iso:country":"ES",
    "sg:address":"Calle de Magdalena, 8",
    "sg:city":"Madrid",
    "sg:orig_category":"Bazares, Art\u00cdculos De Limpieza Y De Cocina (al Por Menor)",
    "sg:phone":"+34 914 67 20 41",
    "sg:postcode":"28012",
    "sg:province":"Madrid",
    "wof:name":"Caidos De La Division Azul S.a.",
    "wof:placetype":"venue"
},
  "geometry": {"coordinates":[-3.7027161121,40.4123535156],"type":"Point"}
}