{
  "type": "Feature",
  "properties": {
    "iso:country":"ES",
    "sg:address":"Acce Ra\u00d1oa (a), S/n",
    "sg:city":"Maside",
    "sg:orig_category":"Promotores Constructores",
    "sg:phone":"+34 988 28 83 20",
    "sg:postcode":"32570",
    "sg:province":"Ourense",
    "wof:name":"Alvarez Alvarez Benigno",
    "wof:placetype":"venue"
},
  "geometry": {"coordinates":[-8.0192470551,42.4222221375],"type":"Point"}
}