{
  "type": "Feature",
  "properties": {
    "iso:country":"ES",
    "sg:address":"Rua Santo Domingo, 4",
    "sg:city":"Vigo",
    "sg:orig_category":"Peluquer\u00cdas, Peluquer\u00cda Mixta",
    "sg:phone":"+34 986 48 10 75",
    "sg:postcode":"36204",
    "sg:province":"Pontevedra",
    "wof:name":"Fernandez Carballo Francisco Jose",
    "wof:placetype":"venue"
},
  "geometry": {"coordinates":[-8.7128200531,42.2321815491],"type":"Point"}
}