{
  "type": "Feature",
  "properties": {
    "iso:country":"ES",
    "sg:address":"Calle de Astura, 4",
    "sg:city":"Valencia De Don Juan",
    "sg:orig_category":"Peluquer\u00cdas, Peluquer\u00cda Mixta",
    "sg:phone":"+34 987 75 11 85",
    "sg:postcode":"24200",
    "sg:province":"Le\u00f3n",
    "wof:name":"Conade C.b.",
    "wof:placetype":"venue"
},
  "geometry": {"coordinates":[-5.5186910629,42.2928161621],"type":"Point"}
}