{
  "type": "Feature",
  "properties": {
    "iso:country":"ES",
    "sg:address":"Carrer de Valencia, 542",
    "sg:city":"Barcelona",
    "sg:orig_category":"Servicio De Salud",
    "sg:phone":"+34 932 32 67 59",
    "sg:postcode":"08013",
    "sg:province":"Barcelona",
    "wof:name":"Aixetes I Banys Barrachina S. L.",
    "wof:placetype":"venue"
},
  "geometry": {"coordinates":[2.1819424629,41.4066619873],"type":"Point"}
}