{
  "type": "Feature",
  "properties": {
    "addr:full":"Av Costa Brava, 2 Platja D'aro Girona 17250",
    "addr:housenumber":"2",
    "addr:postcode":"17250",
    "addr:street":"Av Costa Brava",
    "iso:country":"ES",
    "sg:address":"Av Costa Brava, 2",
    "sg:city":"Platja D'aro",
    "sg:orig_category":"Farmacias",
    "sg:phone":"+34 972 81 75 64",
    "sg:postcode":"17250",
    "sg:province":"Girona",
    "wof:name":"Sala Calsina Montserrat",
    "wof:placetype":"venue"
},
  "geometry": {"coordinates":[2.8091990948,41.9674415588],"type":"Point"}
}