{
  "type": "Feature",
  "properties": {
    "iso:country":"ES",
    "sg:address":"Calle de Juan Delgado, 4",
    "sg:city":"Sanlucar Mayor",
    "sg:orig_category":"Cajas De Ahorro",
    "sg:phone":"+34 955 70 47 00",
    "sg:postcode":"41800",
    "sg:province":"Sevilla",
    "sg:website":"www.elmonte.es",
    "wof:name":"Monte De Piedad Y Caja De Ahorros De Huelva Y Sevilla",
    "wof:placetype":"venue"
},
  "geometry": {"coordinates":[-6.2015128136,37.3867073059],"type":"Point"}
}