{
  "type": "Feature",
  "properties": {
    "addr:full":"Carr Sant Vicent (de), 2 Lliria Valencia 46160",
    "addr:housenumber":"2",
    "addr:postcode":"46160",
    "addr:street":"Carr Sant Vicent De",
    "iso:country":"ES",
    "sg:address":"Carr Sant Vicent (de), 2",
    "sg:city":"Lliria",
    "sg:orig_category":"Molduras, Junquillos, Listones Y Molduras Perforadas",
    "sg:phone":"+34 962 78 33 34",
    "sg:postcode":"46160",
    "sg:province":"Valencia",
    "wof:name":"Plastic C.b.",
    "wof:placetype":"venue"
},
  "geometry": {"coordinates":[-0.5955740213,39.6270294189],"type":"Point"}
}