{
  "type": "Feature",
  "properties": {
    "addr:full":"Valle Oro, 17 Madrid Madrid 28019",
    "addr:housenumber":"17",
    "addr:postcode":"madrid;28019",
    "iso:country":"ES",
    "sg:address":"Valle Oro, 17",
    "sg:city":"Madrid",
    "sg:orig_category":"Contenedores (mercanc\u00cdas)",
    "sg:phone":"+34 914 71 56 05",
    "sg:postcode":"28019",
    "sg:province":"Madrid",
    "sg:website":"www.rufaro.es",
    "wof:name":"I.rufaro S.l.",
    "wof:placetype":"venue"
},
  "geometry": {"coordinates":[-3.7283139229,40.3880195618],"type":"Point"}
}