{
  "type": "Feature",
  "properties": {
    "iso:country":"ES",
    "sg:address":"Urb Rosales (los), 69",
    "sg:city":"Saron",
    "sg:orig_category":"Laboratorios Y Trabajos De Fotograf\u00cda, V\u00cddeo Y Cine",
    "sg:phone":"+34 942 56 41 58",
    "sg:postcode":"39620",
    "sg:province":"Cantabria",
    "wof:name":"Gutierrez Pelayo Maria Concepcion",
    "wof:placetype":"venue"
},
  "geometry": {"coordinates":[-3.8524339199,43.3249206543],"type":"Point"}
}