{
  "type": "Feature",
  "properties": {
    "addr:full":"Calle de Ibaigane, S/n Arenas -areeta Vizcaya 48930",
    "addr:housenumber":"s / n;areeta",
    "addr:postcode":"48930",
    "addr:street":"Calle De Ibaigane",
    "iso:country":"ES",
    "sg:address":"Calle de Ibaigane, S/n",
    "sg:city":"Arenas -areeta",
    "sg:orig_category":"Centros Empresariales",
    "sg:phone":"+34 944 31 59 66",
    "sg:postcode":"48930",
    "sg:province":"Vizcaya",
    "wof:name":"Mei S.l.",
    "wof:placetype":"venue"
},
  "geometry": {"coordinates":[-3.0084590912,43.3251419067],"type":"Point"}
}