{
  "type": "Feature",
  "properties": {
    "addr:full":"Carrer de Doctor Fleming, 10 Roses Girona 17480",
    "addr:housenumber":"10",
    "addr:postcode":"17480",
    "addr:street":"Carrer De Doctor Fleming",
    "iso:country":"ES",
    "sg:address":"Carrer de Doctor Fleming, 10",
    "sg:city":"Roses",
    "sg:orig_category":"Molduras, Junquillos, Listones Y Molduras Perforadas",
    "sg:phone":"+34 972 15 15 72",
    "sg:postcode":"17480",
    "sg:province":"Girona",
    "wof:name":"Sagitario Futur Sl",
    "wof:placetype":"venue"
},
  "geometry": {"coordinates":[3.1778020859,42.2639656067],"type":"Point"}
}