{
  "type": "Feature",
  "properties": {
    "addr:full":"Calle de Mendez Alvaro, 62 Madrid Madrid 28045",
    "addr:housenumber":"62",
    "addr:postcode":"madrid;28045",
    "addr:street":"Calle De Mendez Alvaro",
    "iso:country":"ES",
    "sg:address":"Calle de Mendez Alvaro, 62",
    "sg:city":"Madrid",
    "sg:orig_category":"Centros Empresariales",
    "sg:phone":"+34 915 06 06 30",
    "sg:postcode":"28045",
    "sg:province":"Madrid",
    "wof:name":"Blanco Martinez Maximo Luis",
    "wof:placetype":"venue"
},
  "geometry": {"coordinates":[-3.6814649105,40.3963546753],"type":"Point"}
}