{
  "type": "Feature",
  "properties": {
    "iso:country":"ES",
    "sg:address":"Calle de Trascastillo, 8",
    "sg:city":"Villalube",
    "sg:orig_category":"Farmacias",
    "sg:phone":"+34 980 50 36 73",
    "sg:postcode":"49539",
    "sg:province":"Zamora",
    "wof:name":"Sanchez Guerra Soledad",
    "wof:placetype":"venue"
},
  "geometry": {"coordinates":[-5.5453691483,41.6093292236],"type":"Point"}
}