{
  "type": "Feature",
  "properties": {
    "addr:full":"Carr Verneda, 14 Angles Girona 17160",
    "addr:housenumber":"14",
    "addr:postcode":"17160",
    "addr:street":"Carr Verneda",
    "iso:country":"ES",
    "sg:address":"Carr Verneda, 14",
    "sg:city":"Angles",
    "sg:orig_category":"Vinos Y Licores (venta Al Por Menor)",
    "sg:phone":"+34 972 42 09 47",
    "sg:postcode":"17160",
    "sg:province":"Girona",
    "wof:name":"Pujolras Oliveras Montserrat",
    "wof:placetype":"venue"
},
  "geometry": {"coordinates":[2.6347820759,41.9582252502],"type":"Point"}
}