{
  "type": "Feature",
  "properties": {
    "addr:full":"Poli Industrial Berriainz, 15 Berriozar Navarra 31013",
    "addr:housenumber":"15",
    "addr:postcode":"31013",
    "addr:street":"Berriainz",
    "iso:country":"ES",
    "sg:address":"Poli Industrial Berriainz, 15",
    "sg:city":"Berriozar",
    "sg:orig_category":"Quincaller\u00cda (al Por Menor)",
    "sg:phone":"+34 948 30 26 92",
    "sg:postcode":"31013",
    "sg:province":"Navarra",
    "wof:name":"Ferreteria Berriainz S.l.l.",
    "wof:placetype":"venue"
},
  "geometry": {"coordinates":[-97.78224945069999,45.7040786743],"type":"Point"}
}