{
  "type": "Feature",
  "properties": {
    "iso:country":"ES",
    "sg:address":"Av Onze De Setembre, 26",
    "sg:city":"S. Boi Llobregat",
    "sg:orig_category":"Organizaciones Internacionales",
    "sg:phone":"+34 936 30 50 11",
    "sg:postcode":"08830",
    "sg:province":"Barcelona",
    "wof:name":"Abella Puges Xavier",
    "wof:placetype":"venue"
},
  "geometry": {"coordinates":[2.041471,41.341106],"type":"Point"}
}