{
  "type": "Feature",
  "properties": {
    "addr:full":"Carrer de Llum, 29 Manresa Barcelona 08241",
    "addr:housenumber":"29",
    "addr:postcode":"08241",
    "addr:street":"Carrer De Llum",
    "iso:country":"ES",
    "sg:address":"Carrer de Llum, 29",
    "sg:city":"Manresa",
    "sg:orig_category":"Inform\u00c1tica (estudios, Servicios, Asesor\u00cda, Formaci\u00d3n)",
    "sg:phone":"+34 938 72 41 73",
    "sg:postcode":"08241",
    "sg:province":"Barcelona",
    "wof:name":"Computerbages",
    "wof:placetype":"venue"
},
  "geometry": {"coordinates":[1.8188819885,41.7236824036],"type":"Point"}
}