{
  "type": "Feature",
  "properties": {
    "addr:full":"Calle de Constitucion, 2 Rojales Alicante 03170",
    "addr:housenumber":"2",
    "addr:postcode":"03170",
    "addr:street":"Calle De Constitucion",
    "iso:country":"ES",
    "sg:address":"Calle de Constitucion, 2",
    "sg:city":"Rojales",
    "sg:orig_category":"Farmacias",
    "sg:phone":"+34 966 71 48 71",
    "sg:postcode":"03170",
    "sg:province":"Alicante",
    "wof:name":"Canales Garcia Manuel",
    "wof:placetype":"venue"
},
  "geometry": {"coordinates":[-0.7307072282,38.0841827393],"type":"Point"}
}