{
  "type": "Feature",
  "properties": {
    "addr:full":"Calle de Chile, 27 Logro\u00f1o La Rioja 26005",
    "addr:housenumber":"27",
    "addr:postcode":"26005",
    "addr:street":"Calle De Chile;Rioja",
    "iso:country":"ES",
    "sg:address":"Calle de Chile, 27",
    "sg:city":"Logro\u00f1o",
    "sg:orig_category":"Asesor\u00cda Sobre Comunicaci\u00d3n De Empresas",
    "sg:phone":"+34 941 21 15 00",
    "sg:postcode":"26005",
    "sg:province":"La Rioja",
    "wof:name":"Coem 90 S.l.",
    "wof:placetype":"venue"
},
  "geometry": {"coordinates":[-2.4548130035,42.460735321],"type":"Point"}
}