{
  "type": "Feature",
  "properties": {
    "iso:country":"ES",
    "sg:address":"Calle de Capellanes, S/n",
    "sg:city":"Magaz De Pisuerga",
    "sg:orig_category":"Empresarios",
    "sg:phone":"+34 979 78 42 16",
    "sg:postcode":"34220",
    "sg:province":"Palencia",
    "wof:name":"Cyrpu S.l.",
    "wof:placetype":"venue"
},
  "geometry": {"coordinates":[-4.428044796,41.9823570251],"type":"Point"}
}