{
  "type": "Feature",
  "properties": {
    "addr:full":"Calle de Teruel, 39 Bu\u00f1ol Valencia 46360",
    "addr:housenumber":"39",
    "addr:postcode":"46360",
    "addr:street":"Calle De Teruel",
    "iso:country":"ES",
    "sg:address":"Calle de Teruel, 39",
    "sg:city":"Bu\u00f1ol",
    "sg:orig_category":"M\u00c1rmoles, Granitos Y Piedras Naturales",
    "sg:phone":"+34 962 50 34 05",
    "sg:postcode":"46360",
    "sg:province":"Valencia",
    "wof:name":"Marmoles Y Granitos Chimo S.c.p.",
    "wof:placetype":"venue"
},
  "geometry": {"coordinates":[-0.7887889743,39.4259986877],"type":"Point"}
}