{
  "type": "Feature",
  "properties": {
    "iso:country":"ES",
    "sg:address":"Calle de Gran Capitan, 50",
    "sg:city":"Molina Segura",
    "sg:orig_category":"Agricultores, Agricultores",
    "sg:phone":"+34 968 64 13 99",
    "sg:postcode":"30500",
    "sg:province":"Murcia",
    "wof:name":"Sociedad Agraria De Transformacion N 4690",
    "wof:placetype":"venue"
},
  "geometry": {"coordinates":[-1.2025589943,38.049659729],"type":"Point"}
}