{
  "type": "Feature",
  "properties": {
    "addr:full":"Pl Tartana, 6 Ibi Alicante 03440",
    "addr:housenumber":"6",
    "addr:postcode":"03440",
    "addr:street":"Pl Tartana",
    "iso:country":"ES",
    "sg:address":"Pl Tartana, 6",
    "sg:city":"Ibi",
    "sg:orig_category":"Cajas De Ahorro",
    "sg:phone":"+34 966 55 37 22",
    "sg:postcode":"03440",
    "sg:province":"Alicante",
    "sg:website":"www.cajamurcia.es",
    "wof:name":"Caja De Ahorros De Murcia",
    "wof:placetype":"venue"
},
  "geometry": {"coordinates":[-0.5754950047,38.6225509644],"type":"Point"}
}