{
  "type": "Feature",
  "properties": {
    "iso:country":"ES",
    "sg:address":"Antzalde Kalea, 6",
    "sg:city":"Lazkao",
    "sg:orig_category":"Sociedades, Compa\u00d1\u00cdas Aseguradoras",
    "sg:phone":"+34 943 16 02 83",
    "sg:postcode":"20210",
    "sg:province":"Guip\u00f9zcoa",
    "wof:name":"Peritaciones Y Tasaciones Valitasa S L.",
    "wof:placetype":"venue"
},
  "geometry": {"coordinates":[-2.1873590946,43.0314903259],"type":"Point"}
}