{
  "type": "Feature",
  "properties": {
    "iso:country":"ES",
    "sg:address":"Calle de Capitan Troncoso, 14",
    "sg:city":"Coru\u00d1a",
    "sg:orig_category":"Restaurantes",
    "sg:phone":"+34 981 20 62 20",
    "sg:postcode":"15001",
    "sg:province":"La Coru\u00f1a",
    "wof:name":"Acevedo Del Cerro Julio Manuel",
    "wof:placetype":"venue"
},
  "geometry": {"coordinates":[-8.394859314,43.3710174561],"type":"Point"}
}