{
  "type": "Feature",
  "properties": {
    "iso:country":"ES",
    "sg:address":"Avda Bueu, 19",
    "sg:city":"Cangas",
    "sg:orig_category":"Reposter\u00cdas",
    "sg:phone":"+34 986 30 36 10",
    "sg:postcode":"36940",
    "sg:province":"Pontevedra",
    "wof:name":"Horno Integral Pandaran S.l.",
    "wof:placetype":"venue"
},
  "geometry": {"coordinates":[-8.7865018845,42.2585449219],"type":"Point"}
}