{
  "type": "Feature",
  "properties": {
    "iso:country":"ES",
    "sg:address":"Calle de Mendez Nu\u00d1ez, 7",
    "sg:city":"Almeria",
    "sg:orig_category":"Confecci\u00d3n De Trajes Para Se\u00d1oras",
    "sg:phone":"+34 950 23 91 84",
    "sg:postcode":"04001",
    "sg:province":"Almer\u00eda",
    "sg:website":"www.puntroma.es",
    "wof:name":"Novel 2000 S.l.",
    "wof:placetype":"venue"
},
  "geometry": {"coordinates":[-2.4629070759,36.8387069702],"type":"Point"}
}