{
  "type": "Feature",
  "properties": {
    "addr:full":"C/ Mare Teresa De Calcuta, 8 Salt Girona 17190",
    "addr:housenumber":"8",
    "addr:postcode":"17190",
    "addr:street":"C / Mare Teresa De Calcuta",
    "iso:country":"ES",
    "sg:address":"C/ Mare Teresa De Calcuta, 8",
    "sg:city":"Salt",
    "sg:orig_category":"Transportes Internacionales",
    "sg:phone":"+34 972 23 30 61",
    "sg:postcode":"17190",
    "sg:province":"Girona",
    "wof:name":"Transports Corominas S.l.",
    "wof:placetype":"venue"
},
  "geometry": {"coordinates":[2.7751300335,41.9678649902],"type":"Point"}
}