{
  "type": "Feature",
  "properties": {
    "addr:full":"Calle de General Eytier, 5 San Mateo Murcia 30800",
    "addr:housenumber":"5",
    "addr:postcode":"30800",
    "addr:street":"Calle De General Eytier",
    "iso:country":"ES",
    "sg:address":"Calle de General Eytier, 5",
    "sg:city":"San Mateo",
    "sg:orig_category":"Frutas Y Legumbres Frescas (al Por Mayor)",
    "sg:phone":"+34 968 44 35 22",
    "sg:postcode":"30800",
    "sg:province":"Murcia",
    "sg:website":"www.mayper.es",
    "wof:name":"Mayper Grupo Alimentario S.r.l.",
    "wof:placetype":"venue"
},
  "geometry": {"coordinates":[-1.6905640364,37.680557251],"type":"Point"}
}