{
  "type": "Feature",
  "properties": {
    "iso:country":"ES",
    "sg:address":"Calle de Tercia, 13",
    "sg:city":"Villares",
    "sg:orig_category":"Farmacias",
    "sg:phone":"+34 953 32 00 18",
    "sg:postcode":"23160",
    "sg:province":"Ja\u00e9n",
    "wof:name":"Medina Perez Encarnacion",
    "wof:placetype":"venue"
},
  "geometry": {"coordinates":[-3.8182940483,37.6881904602],"type":"Point"}
}