{
  "type": "Feature",
  "properties": {
    "addr:full":"Avda Puerto De Santamaria, 25 Calpe Alicante 03710",
    "addr:housenumber":"25",
    "addr:postcode":"03710",
    "addr:street":"Avda Puerto De Santamaria",
    "iso:country":"ES",
    "sg:address":"Avda Puerto De Santamaria, 25",
    "sg:city":"Calpe",
    "sg:orig_category":"Promotores Constructores",
    "sg:phone":"+34 965 83 84 12",
    "sg:postcode":"03710",
    "sg:province":"Alicante",
    "wof:name":"Cp Ed. Quintanes Ii",
    "wof:placetype":"venue"
},
  "geometry": {"coordinates":[0.0535200015,38.6515808105],"type":"Point"}
}