{
  "type": "Feature",
  "properties": {
    "addr:full":"Calle de Cadiz, 25 Conil De La Frontera C\u00e1diz 11140",
    "addr:housenumber":"25",
    "addr:postcode":"11140",
    "addr:street":"Calle De Cadiz",
    "iso:country":"ES",
    "sg:address":"Calle de Cadiz, 25",
    "sg:city":"Conil De La Frontera",
    "sg:orig_category":"Delegados, Agentes De Tr\u00c1nsito, Auxiliares De Transporte Internacional",
    "sg:phone":"+34 956 44 07 03",
    "sg:postcode":"11140",
    "sg:province":"C\u00e1diz",
    "wof:name":"Mu\u00f1oz Pareja Miguel",
    "wof:placetype":"venue"
},
  "geometry": {"coordinates":[-6.0910439491,36.2758483887],"type":"Point"}
}