{
  "type": "Feature",
  "properties": {
    "iso:country":"ES",
    "sg:address":"Pg Fabra I Puig, 330",
    "sg:city":"Barcelona",
    "sg:orig_category":"Inmobiliaria (agencias)",
    "sg:phone":"+34 933 57 33 30",
    "sg:postcode":"08031",
    "sg:province":"Barcelona",
    "wof:name":"Estudi Cartella Ii S.l.",
    "wof:placetype":"venue"
},
  "geometry": {"coordinates":[2.1680700779,41.4305992126],"type":"Point"}
}