{
  "type": "Feature",
  "properties": {
    "addr:full":"Calle de Triste Condesa, 26 Arenas San Pedro \u00c1vila 05400",
    "addr:housenumber":"26",
    "addr:postcode":"05400",
    "addr:street":"Calle De Triste Condesa;A\u0301Vila",
    "iso:country":"ES",
    "sg:address":"Calle de Triste Condesa, 26",
    "sg:city":"Arenas San Pedro",
    "sg:orig_category":"Asociaciones Y Clubs Deportivos",
    "sg:phone":"+34 920 37 25 95",
    "sg:postcode":"05400",
    "sg:province":"\u00c1vila",
    "wof:name":"Meson Salvador Pilar",
    "wof:placetype":"venue"
},
  "geometry": {"coordinates":[-5.0883002281,40.2099990845],"type":"Point"}
}