{
  "type": "Feature",
  "properties": {
    "addr:full":"Ca\u00f1ada Horta, S/n Cieza Murcia 30530",
    "addr:housenumber":"s / n",
    "addr:postcode":"30530",
    "iso:country":"ES",
    "sg:address":"Ca\u00f1ada Horta, S/n",
    "sg:city":"Cieza",
    "sg:orig_category":"Internados & Ense\u00d1anza Privada",
    "sg:phone":"+34 968 76 03 91",
    "sg:postcode":"30530",
    "sg:province":"Murcia",
    "wof:name":"Hermanas Apostolicas De Cristo Crucificado",
    "wof:placetype":"venue"
},
  "geometry": {"coordinates":[-1.4821481705,38.2650794983],"type":"Point"}
}