{
  "type": "Feature",
  "properties": {
    "iso:country":"ES",
    "sg:address":"Calle de Mequinenza (cha), 6",
    "sg:city":"Madrid",
    "sg:orig_category":"Peluquer\u00cdas, Peluquer\u00cda Mixta",
    "sg:phone":"+34 914 44 51 89",
    "sg:postcode":"28004",
    "sg:province":"Madrid",
    "wof:name":"Lopez Quintero Duvan Lizardo",
    "wof:placetype":"venue"
},
  "geometry": {"coordinates":[-3.6056768894,40.4487991333],"type":"Point"}
}