{
  "type": "Feature",
  "properties": {
    "addr:full":"Calle de Albino Hernandez Lazaro, 36 Madrid Madrid 28021",
    "addr:housenumber":"36",
    "addr:postcode":"madrid;28021",
    "addr:street":"Calle De Albino Hernandez Lazaro",
    "iso:country":"ES",
    "sg:address":"Calle de Albino Hernandez Lazaro, 36",
    "sg:city":"Madrid",
    "sg:orig_category":"Ingenier\u00cda, Centros De Estudios (diversos)",
    "sg:phone":"+34 917 23 14 42",
    "sg:postcode":"28021",
    "sg:province":"Madrid",
    "wof:name":"Proyectos Y Obras Los Angeles S.l.",
    "wof:placetype":"venue"
},
  "geometry": {"coordinates":[-3.7072031498,40.3458061218],"type":"Point"}
}