{
  "type": "Feature",
  "properties": {
    "addr:full":"Partida Fajarnes, S/n Binefar Huesca 22500",
    "addr:housenumber":"s",
    "addr:postcode":"22500",
    "addr:street":"Partida Fajarnes;/ N",
    "iso:country":"ES",
    "sg:address":"Partida Fajarnes, S/n",
    "sg:city":"Binefar",
    "sg:orig_category":"Promotores Constructores",
    "sg:phone":"+34 974 42 80 91",
    "sg:postcode":"22500",
    "sg:province":"Huesca",
    "wof:name":"Romeu Amoros Jose",
    "wof:placetype":"venue"
},
  "geometry": {"coordinates":[0.2927800119,41.8499412537],"type":"Point"}
}