{
  "type": "Feature",
  "properties": {
    "addr:full":"Calle de Alferez Cabrera, 1 Constantina Sevilla 41450",
    "addr:housenumber":"1",
    "addr:postcode":"41450",
    "addr:street":"Calle De Alferez Cabrera",
    "iso:country":"ES",
    "sg:address":"Calle de Alferez Cabrera, 1",
    "sg:city":"Constantina",
    "sg:orig_category":"Centros De Coordinaci\u00d3n",
    "sg:phone":"+34 955 88 07 42",
    "sg:postcode":"41450",
    "sg:province":"Sevilla",
    "wof:name":"Lira Avila Asesoramientos S.cv.",
    "wof:placetype":"venue"
},
  "geometry": {"coordinates":[-5.6197242737,37.8726501465],"type":"Point"}
}