{
  "type": "Feature",
  "properties": {
    "addr:full":"Avda Doctor Toledo, 12 Rozas De Madrid Madrid 28230",
    "addr:housenumber":"12",
    "addr:postcode":"28230",
    "addr:street":"Avda Doctor Toledo",
    "iso:country":"ES",
    "sg:address":"Avda Doctor Toledo, 12",
    "sg:city":"Rozas De Madrid",
    "sg:orig_category":"Agencias De Viajes",
    "sg:phone":"+34 916 37 62 13",
    "sg:postcode":"28230",
    "sg:province":"Madrid",
    "sg:website":"www.marsans.es",
    "wof:name":"Viajes Marsans S.a.",
    "wof:placetype":"venue"
},
  "geometry": {"coordinates":[-3.8740289211,40.493434906],"type":"Point"}
}