{
  "type": "Feature",
  "properties": {
    "addr:full":"Ctra. Villaconejos-puente Villarrubia, Km. 0005,0 Colmenar Oreja Madrid 28380",
    "addr:postcode":"28380",
    "addr:street":"Ctra. Villaconejos-Puente Villarrubia Km. 0005,0",
    "iso:country":"ES",
    "sg:address":"Ctra. Villaconejos-puente Villarrubia, Km. 0005,0",
    "sg:city":"Colmenar Oreja",
    "sg:orig_category":"Minerales (al Por Mayor)",
    "sg:phone":"+34 918 93 83 65",
    "sg:postcode":"28380",
    "sg:province":"Madrid",
    "wof:name":"S.a. Sulquisa",
    "wof:placetype":"venue"
},
  "geometry": {"coordinates":[-3.3868250847,40.1092643738],"type":"Point"}
}