{
  "type": "Feature",
  "properties": {
    "iso:country":"ES",
    "sg:address":"Carrer de Marquesa Caldes De Montbui, 48",
    "sg:city":"Barcelona",
    "sg:orig_category":"Electricidad: Instaladores",
    "sg:phone":"+34 934 56 56 72",
    "sg:postcode":"08032",
    "sg:province":"Barcelona",
    "wof:name":"Instalaciones Pardeiro S.l.",
    "wof:placetype":"venue"
},
  "geometry": {"coordinates":[2.1733589172,41.4238777161],"type":"Point"}
}