{
  "type": "Feature",
  "properties": {
    "iso:country":"ES",
    "sg:address":"Avda Monteazahar, 13",
    "sg:city":"Beniajan",
    "sg:classifiers":[
        {
            "category":"Personal",
            "subcategory":"Barber",
            "type":"Services"
        }
    ],
    "sg:phone":"+34 968 82 43 85",
    "sg:postcode":"30570",
    "sg:province":"Murcia",
    "sg:tags":[
        "caballeros",
        "de",
        "peluqueros"
    ],
    "wof:name":"Sanchez Marin Antonio",
    "wof:placetype":"venue"
},
  "geometry": {"coordinates":[-1.0691380501,37.974105835],"type":"Point"}
}