{
  "type": "Feature",
  "properties": {
    "addr:full":"Plaz Poeta Miguel Hernandez, 5 Zaragoza Zaragoza 50007",
    "addr:housenumber":"5",
    "addr:postcode":"50007",
    "addr:street":"Plaz Poeta Miguel Hernandez",
    "iso:country":"ES",
    "sg:address":"Plaz Poeta Miguel Hernandez, 5",
    "sg:city":"Zaragoza",
    "sg:orig_category":"Peluquer\u00cdas, Peluquer\u00cda Mixta",
    "sg:phone":"+34 976 25 35 64",
    "sg:postcode":"50007",
    "sg:province":"Zaragoza",
    "wof:name":"Lopez Lacasta Esperanza",
    "wof:placetype":"venue"
},
  "geometry": {"coordinates":[-0.8827381134,41.6391716003],"type":"Point"}
}