{
  "type": "Feature",
  "properties": {
    "iso:country":"ES",
    "sg:address":"Calle de Petronila Casado, 18",
    "sg:city":"Burgos",
    "sg:orig_category":"Carnicer\u00cdas, Carnicer\u00cdas",
    "sg:phone":"+34 947 21 24 57",
    "sg:postcode":"09005",
    "sg:province":"Burgos",
    "wof:name":"Tobar Hidalgo Juan Jose",
    "wof:placetype":"venue"
},
  "geometry": {"coordinates":[-3.6958105564,42.3486557007],"type":"Point"}
}