{
  "type": "Feature",
  "properties": {
    "iso:country":"ES",
    "sg:address":"Calle de Martinez Tornel, 1",
    "sg:city":"San Javier",
    "sg:classifiers":[
        {
            "category":"Autos & Motor Vehicles",
            "subcategory":"Automobile Sales",
            "type":"Retail Goods"
        }
    ],
    "sg:phone":"+34 968 57 13 80",
    "sg:postcode":"30730",
    "sg:province":"Murcia",
    "wof:name":"Ferre Riquelme Maria",
    "wof:placetype":"venue"
},
  "geometry": {"coordinates":[-0.8344179988,37.8052062988],"type":"Point"}
}