{
  "type": "Feature",
  "properties": {
    "addr:full":"Carrer de Nou De Sant Francesc, 42 Barcelona Barcelona 08002",
    "addr:housenumber":"42",
    "addr:postcode":"08002",
    "addr:street":"Carrer De Nou De Sant Francesc",
    "iso:country":"ES",
    "sg:address":"Carrer de Nou De Sant Francesc, 42",
    "sg:city":"Barcelona",
    "sg:orig_category":"Asociaciones, Organismos Culturales Y Socioeducativos",
    "sg:phone":"+34 933 02 21 25",
    "sg:postcode":"08002",
    "sg:province":"Barcelona",
    "wof:name":"Tecnogestic S.l.",
    "wof:placetype":"venue"
},
  "geometry": {"coordinates":[2.1781749725,41.3783454895],"type":"Point"}
}