{
  "type": "Feature",
  "properties": {
    "addr:full":"Rua Antonio Facorro, Km. 0002,0 Ca\u00f1iza Pontevedra 36880",
    "addr:postcode":"36880",
    "addr:street":"Rua Antonio Facorro Km. 0002,0 Can\u0303Iza",
    "iso:country":"ES",
    "sg:address":"Rua Antonio Facorro, Km. 0002,0",
    "sg:city":"Ca\u00f1iza",
    "sg:orig_category":"Mataderos Y Talleres De Despiezado",
    "sg:phone":"+34 986 65 15 97",
    "sg:postcode":"36880",
    "sg:province":"Pontevedra",
    "wof:name":"Carnicas Anguieiro S.l.",
    "wof:placetype":"venue"
},
  "geometry": {"coordinates":[-8.273182869,42.2129859924],"type":"Point"}
}