{
  "type": "Feature",
  "properties": {
    "iso:country":"ES",
    "sg:address":"Calle de Magallanes, 16",
    "sg:city":"Gijon",
    "sg:orig_category":"Fisioterapia",
    "sg:phone":"+34 984 19 78 20",
    "sg:postcode":"33212",
    "sg:province":"Asturias",
    "wof:name":"Ivan Vazquez Garcia",
    "wof:placetype":"venue"
},
  "geometry": {"coordinates":[-5.7024250031,43.5388221741],"type":"Point"}
}