{
  "type": "Feature",
  "properties": {
    "iso:country":"ES",
    "sg:address":"Del Rincon, 5",
    "sg:city":"Hinojosas De Calatrava",
    "sg:orig_category":"Asociaciones, Organismos Culturales Y Socioeducativos",
    "sg:phone":"+34 926 47 60 04",
    "sg:postcode":"13590",
    "sg:province":"Ciudad Real",
    "wof:name":"Circulo De Labradores",
    "wof:placetype":"venue"
},
  "geometry": {"coordinates":[-4.1398711205,38.6146507263],"type":"Point"}
}