{
  "type": "Feature",
  "properties": {
    "iso:country":"ES",
    "sg:address":"Rua Galicia (de), 5",
    "sg:city":"Vilalba",
    "sg:orig_category":"Farmacias",
    "sg:phone":"+34 982 51 00 03",
    "sg:postcode":"27800",
    "sg:province":"Lugo",
    "wof:name":"Espa\u00f1a Gomez Ana",
    "wof:placetype":"venue"
},
  "geometry": {"coordinates":[-7.6814641953,43.2966461182],"type":"Point"}
}