{
  "type": "Feature",
  "properties": {
    "iso:country":"ES",
    "sg:address":"Plaza De Los Pachorros, 2",
    "sg:city":"Luarca",
    "sg:orig_category":"Florister\u00cdas",
    "sg:phone":"+34 985 64 10 53",
    "sg:postcode":"33700",
    "sg:province":"Asturias",
    "wof:name":"Rubio Alfonso Isabel",
    "wof:placetype":"venue"
},
  "geometry": {"coordinates":[-6.5354027748,43.5428848267],"type":"Point"}
}