{
  "type": "Feature",
  "properties": {
    "addr:full":"Carrer de Bruc, 87 Barcelona Barcelona 08009",
    "addr:housenumber":"87",
    "addr:postcode":"08009",
    "addr:street":"Carrer De Bruc",
    "iso:country":"ES",
    "sg:address":"Carrer de Bruc, 87",
    "sg:city":"Barcelona",
    "sg:orig_category":"Tejidos (al Por Menor)",
    "sg:phone":"+34 932 07 53 85",
    "sg:postcode":"08009",
    "sg:province":"Barcelona",
    "sg:website":"www.militariabcn.com",
    "wof:name":"Andreu Prat Francisco",
    "wof:placetype":"venue"
},
  "geometry": {"coordinates":[2.168469429,41.3951225281],"type":"Point"}
}