{
  "type": "Feature",
  "properties": {
    "iso:country":"ES",
    "sg:address":"Calle de Doctor Oloriz, 1",
    "sg:city":"Valencia",
    "sg:orig_category":"Droguer\u00cdas (al Por Menor)",
    "sg:phone":"+34 963 49 41 39",
    "sg:postcode":"46009",
    "sg:province":"Valencia",
    "wof:name":"Igual Gomez Antonio",
    "wof:placetype":"venue"
},
  "geometry": {"coordinates":[-0.3804487884,39.483089447],"type":"Point"}
}