{
  "type": "Feature",
  "properties": {
    "addr:full":"Calle de Aeronave, 14 Madrid Madrid 28042",
    "addr:housenumber":"14",
    "addr:postcode":"madrid;28042",
    "addr:street":"Calle De Aeronave",
    "iso:country":"ES",
    "sg:address":"Calle de Aeronave, 14",
    "sg:city":"Madrid",
    "sg:orig_category":"Estudios, Instalaci\u00d3n De Climatizaci\u00d3n",
    "sg:phone":"+34 913 12 09 12",
    "sg:postcode":"28042",
    "sg:province":"Madrid",
    "wof:name":"Airvac S.l.",
    "wof:placetype":"venue"
},
  "geometry": {"coordinates":[-3.5863888264,40.4701957703],"type":"Point"}
}