{
  "type": "Feature",
  "properties": {
    "iso:country":"ES",
    "sg:address":"Calle de Luis Felipe Gomez Wanguemert, 12",
    "sg:city":"Llanos De Aridane",
    "sg:orig_category":"Bazares, Art\u00cdculos De Limpieza Y De Cocina (al Por Menor)",
    "sg:phone":"+34 922 40 17 98",
    "sg:postcode":"38760",
    "sg:province":"Santa Cruz De Tenerife",
    "wof:name":"Elena Martin S.l.",
    "wof:placetype":"venue"
},
  "geometry": {"coordinates":[-17.9160194397,28.6604919434],"type":"Point"}
}