{
  "type": "Feature",
  "properties": {
    "iso:country":"ES",
    "sg:address":"Av Valencia, 19",
    "sg:city":"Pu\u00e7ol",
    "sg:orig_category":"Arboricultura Y Producci\u00d3n De Frutas",
    "sg:phone":"+34 961 42 09 17",
    "sg:postcode":"46530",
    "sg:province":"Valencia",
    "wof:name":"Pesudo Casani Manuel",
    "wof:placetype":"venue"
},
  "geometry": {"coordinates":[-0.3065479994,39.6171646118],"type":"Point"}
}