{
  "type": "Feature",
  "properties": {
    "addr:full":"Trva Ramon Y Cajal, 3 Bilbao Vizcaya 48014",
    "addr:housenumber":"3",
    "addr:postcode":"48014",
    "addr:street":"Trva Ramon Y Cajal",
    "iso:country":"ES",
    "sg:address":"Trva Ramon Y Cajal, 3",
    "sg:city":"Bilbao",
    "sg:orig_category":"Administradores De Bienes Y Delegados De Comunidades De Propietarios",
    "sg:phone":"+34 944 75 83 19",
    "sg:postcode":"48014",
    "sg:province":"Vizcaya",
    "wof:name":"Aitziber Robredo Ruiz",
    "wof:placetype":"venue"
},
  "geometry": {"coordinates":[-2.9500646591,43.2698097229],"type":"Point"}
}