{
  "type": "Feature",
  "properties": {
    "iso:country":"ES",
    "sg:address":"Lugar Retiro(s Cristobal), 26",
    "sg:city":"Los Dolores",
    "sg:orig_category":"Mec\u00c1nico Del Autom\u00d3vil",
    "sg:phone":"+34 968 51 88 52",
    "sg:postcode":"30310",
    "sg:province":"Murcia",
    "wof:name":"Contreras Cortes Maria Jose",
    "wof:placetype":"venue"
},
  "geometry": {"coordinates":[-1.0071530342,37.6519165039],"type":"Point"}
}