{
  "type": "Feature",
  "properties": {
    "iso:country":"ES",
    "sg:address":"Trva Redondi\u00d1a, 27",
    "sg:city":"Gandara",
    "sg:orig_category":"Quincaller\u00cda (al Por Menor)",
    "sg:phone":"+34 986 61 37 63",
    "sg:postcode":"36789",
    "sg:province":"Pontevedra",
    "wof:name":"Materiales Do Lago S.l.",
    "wof:placetype":"venue"
},
  "geometry": {"coordinates":[-8.6424407959,42.4478187561],"type":"Point"}
}