{
  "type": "Feature",
  "properties": {
    "iso:country":"ES",
    "sg:address":"Calle de I\u00d1igo Lopez De Haro Kalea, 10",
    "sg:city":"Gernika-lumo",
    "sg:orig_category":"Cristaler\u00cdas",
    "sg:phone":"+34 946 25 16 90",
    "sg:postcode":"48300",
    "sg:province":"Vizcaya",
    "wof:name":"Cristaleria Jose Luis",
    "wof:placetype":"venue"
},
  "geometry": {"coordinates":[-2.6795799732,43.3160858154],"type":"Point"}
}