{
  "type": "Feature",
  "properties": {
    "addr:full":"Estd Catabois, 686 Ferrol La Coru\u00f1a 15405",
    "addr:housenumber":"686",
    "addr:postcode":"15405",
    "addr:street":"Catabois;La Corun\u0303A",
    "iso:country":"ES",
    "sg:address":"Estd Catabois, 686",
    "sg:city":"Ferrol",
    "sg:orig_category":"Distribuci\u00d3n De Petr\u00d3leo Y Derivados",
    "sg:phone":"+34 981 32 62 00",
    "sg:postcode":"15405",
    "sg:province":"La Coru\u00f1a",
    "wof:name":"Javier Martinez Regueira S. L.",
    "wof:placetype":"venue"
},
  "geometry": {"coordinates":[-8.2437515259,43.5037994385],"type":"Point"}
}