{
  "type": "Feature",
  "properties": {
    "iso:country":"ES",
    "sg:address":"Sect Descubridores, 22",
    "sg:city":"Tres Cantos",
    "sg:orig_category":"Polideportivos",
    "sg:phone":"+34 918 04 31 04",
    "sg:postcode":"28760",
    "sg:province":"Madrid",
    "wof:name":"Patronato Deportivo Municipal De Tres Cantos",
    "wof:placetype":"venue"
},
  "geometry": {"coordinates":[-3.7164158821,40.6112098694],"type":"Point"}
}