{
  "type": "Feature",
  "properties": {
    "iso:country":"ES",
    "sg:address":"Calle de Pedro Laborde, 25",
    "sg:city":"Madrid",
    "sg:orig_category":"Zapatos (al Por Menor)",
    "sg:phone":"+34 913 03 23 28",
    "sg:postcode":"28038",
    "sg:province":"Madrid",
    "wof:name":"Moreno Martin Mariano",
    "wof:placetype":"venue"
},
  "geometry": {"coordinates":[-3.6481928825,40.3881187439],"type":"Point"}
}