{
  "type": "Feature",
  "properties": {
    "iso:country":"ES",
    "sg:address":"Calle de Albacete, S/n",
    "sg:city":"Soria",
    "sg:orig_category":"Molduras, Junquillos, Listones Y Molduras Perforadas",
    "sg:phone":"+34 975 22 82 54",
    "sg:postcode":"42004",
    "sg:province":"Soria",
    "wof:name":"La Orden De Blas Miguel Angel",
    "wof:placetype":"venue"
},
  "geometry": {"coordinates":[-2.481991291,41.768119812],"type":"Point"}
}