{
  "type": "Feature",
  "properties": {
    "iso:country":"ES",
    "sg:address":"Avda Portugal, 14",
    "sg:city":"Gijon",
    "sg:orig_category":"Venta, Colocaci\u00d3n, Reparaci\u00d3n De Parabrisas, Techos Descapotables",
    "sg:phone":"+34 985 35 74 46",
    "sg:postcode":"33207",
    "sg:province":"Asturias",
    "wof:name":"Cristamovil S.l.",
    "wof:placetype":"venue"
},
  "geometry": {"coordinates":[-5.6685090065,43.5390167236],"type":"Point"}
}