{
  "type": "Feature",
  "properties": {
    "addr:full":"Calle de Ander Deuna, 17 Usansolo Vizcaya 48960",
    "addr:housenumber":"17",
    "addr:postcode":"48960",
    "addr:street":"Calle De Ander Deuna",
    "iso:country":"ES",
    "sg:address":"Calle de Ander Deuna, 17",
    "sg:city":"Usansolo",
    "sg:orig_category":"Alimentaci\u00d3n General (al Por Menor)",
    "sg:phone":"+34 944 56 06 65",
    "sg:postcode":"48960",
    "sg:province":"Vizcaya",
    "wof:name":"Lecue Uriarte Pascual",
    "wof:placetype":"venue"
},
  "geometry": {"coordinates":[-2.8189804554,43.2190704346],"type":"Point"}
}