{
  "type": "Feature",
  "properties": {
    "addr:full":"Ctra Zaragoza Pol La Laguna, 117 Alca\u00f1iz Teruel 44600",
    "addr:housenumber":"117",
    "addr:postcode":"44600",
    "addr:street":"Ctra Zaragoza Pol La Laguna",
    "iso:country":"ES",
    "sg:address":"Ctra Zaragoza Pol La Laguna, 117",
    "sg:city":"Alca\u00f1iz",
    "sg:orig_category":"Alumbrados",
    "sg:phone":"+34 978 87 05 41",
    "sg:postcode":"44600",
    "sg:province":"Teruel",
    "wof:name":"Lahoz Molinos Maria Teresa",
    "wof:placetype":"venue"
},
  "geometry": {"coordinates":[-0.1331740022,41.0522842407],"type":"Point"}
}