{
  "type": "Feature",
  "properties": {
    "iso:country":"ES",
    "sg:address":"Carrer de Balmes, 450",
    "sg:city":"Barcelona",
    "sg:orig_category":"Inversiones",
    "sg:phone":"+34 934 17 30 00",
    "sg:postcode":"08022",
    "sg:province":"Barcelona",
    "wof:name":"Inversiones Magnum Alfa S.a.",
    "wof:placetype":"venue"
},
  "geometry": {"coordinates":[2.1376779079,41.4090232849],"type":"Point"}
}