{
  "type": "Feature",
  "properties": {
    "addr:full":"Calle de Leonardo Da Vinci, 13 Mi\u00e7ano Menor \u00c1lava 01...",
    "addr:housenumber":"13;01 ...",
    "addr:street":"Calle De Leonardo Da Vinci;A\u0301Lava",
    "iso:country":"ES",
    "sg:address":"Calle de Leonardo Da Vinci, 13",
    "sg:city":"Mi\u00e7ano Menor",
    "sg:orig_category":"Industrias Aeron\u00c1uticas Y Espaciales",
    "sg:phone":"+34 945 18 56 14",
    "sg:postcode":"01...",
    "sg:province":"\u00c1lava",
    "wof:name":"Desarrollos Aeronauticos S.a.",
    "wof:placetype":"venue"
},
  "geometry": {"coordinates":[-2.6687788963,42.9233779907],"type":"Point"}
}