{
  "type": "Feature",
  "properties": {
    "addr:full":"Pase Salvador De Azpiazu, 3 Vitoria-gasteiz \u00c1lava 01008",
    "addr:housenumber":"3",
    "addr:postcode":"01008",
    "addr:street":"Salvador;Azpiazu",
    "iso:country":"ES",
    "sg:address":"Pase Salvador De Azpiazu, 3",
    "sg:city":"Vitoria-gasteiz",
    "sg:orig_category":"Institutos De Belleza",
    "sg:phone":"+34 945 22 05 58",
    "sg:postcode":"01008",
    "sg:province":"\u00c1lava",
    "wof:name":"Centro De Belleza B.g.",
    "wof:placetype":"venue"
},
  "geometry": {"coordinates":[-2.6853740215,42.8451957703],"type":"Point"}
}