{
  "type": "Feature",
  "properties": {
    "addr:full":"Calle de Carreras, 44 Ecija Sevilla 41400",
    "addr:housenumber":"44",
    "addr:postcode":"41400",
    "addr:street":"Calle De Carreras",
    "iso:country":"ES",
    "sg:address":"Calle de Carreras, 44",
    "sg:city":"Ecija",
    "sg:orig_category":"Electricidad: Instaladores",
    "sg:phone":"+34 954 83 21 35",
    "sg:postcode":"41400",
    "sg:province":"Sevilla",
    "wof:name":"Moreno Romero Julian",
    "wof:placetype":"venue"
},
  "geometry": {"coordinates":[-5.0834336281,37.5424804688],"type":"Point"}
}