{
  "type": "Feature",
  "properties": {
    "iso:country":"ES",
    "sg:address":"Pasaje De Fajas, 1",
    "sg:city":"Alcorisa",
    "sg:orig_category":"Plomeros",
    "sg:phone":"+34 978 84 04 04",
    "sg:postcode":"44550",
    "sg:province":"Teruel",
    "wof:name":"Gutierrez Giner Emilio",
    "wof:placetype":"venue"
},
  "geometry": {"coordinates":[-0.3835969865,40.8925437927],"type":"Point"}
}