{
  "type": "Feature",
  "properties": {
    "iso:country":"ES",
    "sg:address":"Cmno Aldapeta, 4",
    "sg:orig_category":"Empresarios",
    "sg:phone":"+34 944 03 05 53",
    "sg:postcode":"01400",
    "sg:province":"\u00c1lava",
    "wof:name":"Augusto Vecilla Garza",
    "wof:placetype":"venue"
},
  "geometry": {"coordinates":[-2.9661285877,43.1415481567],"type":"Point"}
}