{
  "type": "Feature",
  "properties": {
    "addr:full":"Calle de Esteban Salazar Chapela, 11 Malaga M\u00e1laga 29004",
    "addr:housenumber":"11",
    "addr:postcode":"29004",
    "addr:street":"Calle De Esteban Salazar Chapela;Ma\u0301Laga",
    "iso:country":"ES",
    "sg:address":"Calle de Esteban Salazar Chapela, 11",
    "sg:city":"Malaga",
    "sg:orig_category":"Suministros Y Materiales Industriales",
    "sg:phone":"+34 952 24 38 65",
    "sg:postcode":"29004",
    "sg:province":"M\u00e1laga",
    "wof:name":"Sotecal Distribuciones S.cv.",
    "wof:placetype":"venue"
},
  "geometry": {"coordinates":[-4.4713802338,36.6901855469],"type":"Point"}
}