{
  "type": "Feature",
  "properties": {
    "iso:country":"ES",
    "sg:address":"Avda America (de), 22",
    "sg:city":"Granada",
    "sg:orig_category":"Electrodom\u00c9sticos (al Por Menor)",
    "sg:phone":"+34 958 12 77 69",
    "sg:postcode":"18006",
    "sg:province":"Granada",
    "wof:name":"Moral Medialdea Luis Del",
    "wof:placetype":"venue"
},
  "geometry": {"coordinates":[-3.599419117,37.1611709595],"type":"Point"}
}