{
  "type": "Feature",
  "properties": {
    "addr:full":"Calle de Colmenares, 1 Palmas De Gran Canaria Las Palmas 35003",
    "addr:housenumber":"1",
    "addr:postcode":"35003",
    "addr:street":"Calle De Colmenares",
    "iso:country":"ES",
    "sg:address":"Calle de Colmenares, 1",
    "sg:city":"Palmas De Gran Canaria",
    "sg:orig_category":"Contenedores (mercanc\u00cdas)",
    "sg:phone":"+34 928 37 01 27",
    "sg:postcode":"35003",
    "sg:province":"Las Palmas",
    "wof:name":"Hernandez Sanchez Alfredo",
    "wof:placetype":"venue"
},
  "geometry": {"coordinates":[-15.417014122,28.1096782684],"type":"Point"}
}