{
  "type": "Feature",
  "properties": {
    "addr:full":"Calle de Perpetuo Socorro, 8 Alcala Rio Sevilla 41200",
    "addr:housenumber":"8",
    "addr:postcode":"41200",
    "addr:street":"Calle De Perpetuo Socorro",
    "iso:country":"ES",
    "sg:address":"Calle de Perpetuo Socorro, 8",
    "sg:city":"Alcala Rio",
    "sg:orig_category":"Cajas Para Embalar",
    "sg:phone":"+34 955 65 12 07",
    "sg:postcode":"41200",
    "sg:province":"Sevilla",
    "wof:name":"Caja Rural Del Sur Sociedad Cooperativa",
    "wof:placetype":"venue"
},
  "geometry": {"coordinates":[-5.9795250893,37.5170516968],"type":"Point"}
}