{
  "type": "Feature",
  "properties": {
    "addr:full":"Plaz Mayor De Ciudad Pegaso, S/n Madrid Madrid 28022",
    "addr:housenumber":"s / n",
    "addr:postcode":"28022",
    "addr:street":"Plaz",
    "iso:country":"ES",
    "sg:address":"Plaz Mayor De Ciudad Pegaso, S/n",
    "sg:city":"Madrid",
    "sg:orig_category":"Farmacias",
    "sg:phone":"+34 917 41 07 95",
    "sg:postcode":"28022",
    "sg:province":"Madrid",
    "wof:name":"Gimenez De Cordoba Fernandez-pintado Francisco",
    "wof:placetype":"venue"
},
  "geometry": {"coordinates":[-3.5953979492,40.4471244812],"type":"Point"}
}