{
  "type": "Feature",
  "properties": {
    "iso:country":"ES",
    "sg:address":"Calle de Doctor Ramon Castroviejo, 25",
    "sg:city":"Madrid",
    "sg:orig_category":"Electricidad Veh\u00cdculo",
    "sg:phone":"+34 913 16 67 18",
    "sg:postcode":"28035",
    "sg:province":"Madrid",
    "wof:name":"Polo Lopez Jose",
    "wof:placetype":"venue"
},
  "geometry": {"coordinates":[-3.7156975269,40.47889328],"type":"Point"}
}