{
  "type": "Feature",
  "properties": {
    "addr:full":"Calle de Postas, 13 Ciudad Real Ciudad Real 13001",
    "addr:housenumber":"13",
    "addr:postcode":"13001",
    "addr:street":"Calle De Postas",
    "iso:country":"ES",
    "sg:address":"Calle de Postas, 13",
    "sg:city":"Ciudad Real",
    "sg:orig_category":"Suministros Para Hoteles",
    "sg:phone":"+34 926 21 22 80",
    "sg:postcode":"13001",
    "sg:province":"Ciudad Real",
    "wof:name":"Terriza Barrajon Julian",
    "wof:placetype":"venue"
},
  "geometry": {"coordinates":[-3.9297089577,38.9850959778],"type":"Point"}
}