{
  "type": "Feature",
  "properties": {
    "iso:country":"ES",
    "sg:address":"Calle de Bocairente, 4",
    "sg:city":"Agres",
    "sg:orig_category":"Reposter\u00cdas",
    "sg:phone":"+34 965 51 00 22",
    "sg:postcode":"03870",
    "sg:province":"Alicante",
    "wof:name":"Navarro Pascual Arcadio",
    "wof:placetype":"venue"
},
  "geometry": {"coordinates":[-0.5163276792,38.7801208496],"type":"Point"}
}