{
  "type": "Feature",
  "properties": {
    "addr:full":"Avda Cala (de), 8 Almu\u00f1ecar Granada 18690",
    "addr:postcode":"18690",
    "addr:street":"Avda Cala De 8 Almun\u0303Ecar",
    "iso:country":"ES",
    "sg:address":"Avda Cala (de), 8",
    "sg:city":"Almu\u00f1ecar",
    "sg:orig_category":"Muebles, Minoristas",
    "sg:phone":"+34 958 63 03 56",
    "sg:postcode":"18690",
    "sg:province":"Granada",
    "wof:name":"Roman Jodar Miguel",
    "wof:placetype":"venue"
},
  "geometry": {"coordinates":[-3.6918780804,36.7341003418],"type":"Point"}
}