{
  "type": "Feature",
  "properties": {
    "addr:full":"Calle de Colon, 12 Requena Valencia 46340",
    "addr:housenumber":"12",
    "addr:postcode":"46340",
    "addr:street":"Calle De Colon",
    "iso:country":"ES",
    "sg:address":"Calle de Colon, 12",
    "sg:city":"Requena",
    "sg:orig_category":"Pr\u00c9stamos Personales E Hipotecarios",
    "sg:phone":"+34 962 30 30 04",
    "sg:postcode":"46340",
    "sg:province":"Valencia",
    "wof:name":"Gosalvez Simbor Inmaculada",
    "wof:placetype":"venue"
},
  "geometry": {"coordinates":[-1.1025047302,39.4894676208],"type":"Point"}
}