{
  "type": "Feature",
  "properties": {
    "iso:country":"ES",
    "sg:address":"Calle de Valladolid, 7",
    "sg:city":"Parla",
    "sg:orig_category":"Alquiler De V\u00cddeo",
    "sg:phone":"+34 916 05 77 88",
    "sg:postcode":"28980",
    "sg:province":"Madrid",
    "wof:name":"Murillo Isidoro Antonio",
    "wof:placetype":"venue"
},
  "geometry": {"coordinates":[-3.763988018,40.2421836853],"type":"Point"}
}