{
  "type": "Feature",
  "properties": {
    "addr:full":"Avda Orense, 5 Marin Pontevedra 36900",
    "addr:housenumber":"5",
    "addr:postcode":"36900",
    "addr:street":"Avda Orense",
    "iso:country":"ES",
    "sg:address":"Avda Orense, 5",
    "sg:city":"Marin",
    "sg:orig_category":"Distribuci\u00d3n De Petr\u00d3leo Y Derivados",
    "sg:phone":"+34 986 88 27 56",
    "sg:postcode":"36900",
    "sg:province":"Pontevedra",
    "wof:name":"Nagover S.l.",
    "wof:placetype":"venue"
},
  "geometry": {"coordinates":[-8.6983823776,42.3927574158],"type":"Point"}
}