{
  "type": "Feature",
  "properties": {
    "iso:country":"ES",
    "sg:address":"Calle de Fomento, 17",
    "sg:city":"Mairena Aljarafe",
    "sg:orig_category":"Artes Gr\u00c1ficas, Artes Pl\u00c1sticas (curso)",
    "sg:phone":"+34 955 60 20 19",
    "sg:postcode":"41927",
    "sg:province":"Sevilla",
    "wof:name":"Flamenco Camisetas S.l.",
    "wof:placetype":"venue"
},
  "geometry": {"coordinates":[-6.0615053177,37.354763031],"type":"Point"}
}