{
  "type": "Feature",
  "properties": {
    "addr:full":"Carrer de Torras I Bages, 19 Cornella Llobregat Barcelona 08940",
    "addr:housenumber":"19",
    "addr:postcode":"08940",
    "addr:street":"Carrer De Torras I Bages",
    "iso:country":"ES",
    "sg:address":"Carrer de Torras I Bages, 19",
    "sg:city":"Cornella Llobregat",
    "sg:orig_category":"Molduras, Junquillos, Listones Y Molduras Perforadas",
    "sg:phone":"+34 933 75 76 33",
    "sg:postcode":"08940",
    "sg:province":"Barcelona",
    "wof:name":"Nu\u00f1o Blanco Fermin",
    "wof:placetype":"venue"
},
  "geometry": {"coordinates":[2.0725090504,41.36170578],"type":"Point"}
}