{
  "type": "Feature",
  "properties": {
    "addr:full":"Calle de Obispo Alonso Enriquez, S/n Malaga M\u00e1laga 29014",
    "addr:postcode":"29014",
    "addr:street":"Calle De Obispo Alonso Enriquez S / N;Ma\u0301Laga",
    "iso:country":"ES",
    "sg:address":"Calle de Obispo Alonso Enriquez, S/n",
    "sg:city":"Malaga",
    "sg:orig_category":"Agencias Y Agentes Comerciales, Representantes",
    "sg:phone":"+34 952 26 03 52",
    "sg:postcode":"29014",
    "sg:province":"M\u00e1laga",
    "wof:name":"Perez Sanchez Remedios",
    "wof:placetype":"venue"
},
  "geometry": {"coordinates":[-4.4219741821,36.7356796265],"type":"Point"}
}