{
  "type": "Feature",
  "properties": {
    "iso:country":"ES",
    "sg:address":"Avda Francisco Ayala (de), 58",
    "sg:city":"Granada",
    "sg:orig_category":"Parafarmacias",
    "sg:phone":"+34 958 15 98 09",
    "sg:postcode":"18014",
    "sg:province":"Granada",
    "wof:name":"Wannous Wannous Mahmoud",
    "wof:placetype":"venue"
},
  "geometry": {"coordinates":[-3.6191129684,37.1950912476],"type":"Point"}
}