{
  "type": "Feature",
  "properties": {
    "addr:full":"Calle de San Francisco, 55 Montilla C\u00f3rdoba 14550",
    "addr:housenumber":"55",
    "addr:postcode":"14550",
    "addr:street":"Calle De San Francisco;Co\u0301Rdoba",
    "iso:country":"ES",
    "sg:address":"Calle de San Francisco, 55",
    "sg:city":"Montilla",
    "sg:orig_category":"Mec\u00c1nico Del Autom\u00d3vil",
    "sg:phone":"+34 957 65 16 22",
    "sg:postcode":"14550",
    "sg:province":"C\u00f3rdoba",
    "wof:name":"Automoviles La Fundacion S.l.",
    "wof:placetype":"venue"
},
  "geometry": {"coordinates":[-4.6346383095,37.5931892395],"type":"Point"}
}