{
  "type": "Feature",
  "properties": {
    "addr:full":"Schez. Oca\u00f1a, 20 Bejar Salamanca 37700",
    "addr:housenumber":"20",
    "addr:postcode":"37700",
    "addr:street":"Ocan\u0303A",
    "iso:country":"ES",
    "sg:address":"Schez. Oca\u00f1a, 20",
    "sg:city":"Bejar",
    "sg:orig_category":"Abogados",
    "sg:phone":"+34 923 40 27 60",
    "sg:postcode":"37700",
    "sg:province":"Salamanca",
    "wof:name":"Cid Gomez-rodulfo Jose Maria",
    "wof:placetype":"venue"
},
  "geometry": {"coordinates":[-5.7728161812,40.3881263733],"type":"Point"}
}