{
  "type": "Feature",
  "properties": {
    "iso:country":"ES",
    "sg:address":"Carrer de Sol (el), 6",
    "sg:city":"S. Fost Campsentelles",
    "sg:orig_category":"Lavado, Limpieza De Veh\u00cdculos",
    "sg:phone":"+34 935 93 59 24",
    "sg:postcode":"08105",
    "sg:province":"Barcelona",
    "wof:name":"Devahive Vigneront Francis",
    "wof:placetype":"venue"
},
  "geometry": {"coordinates":[2.2419290543,41.5165901184],"type":"Point"}
}