{
  "type": "Feature",
  "properties": {
    "addr:full":"Calle de Asuncion, 67 Sevilla Sevilla 41011",
    "addr:housenumber":"67",
    "addr:postcode":"41011",
    "addr:street":"Calle De Asuncion",
    "iso:country":"ES",
    "sg:address":"Calle de Asuncion, 67",
    "sg:city":"Sevilla",
    "sg:orig_category":"Agencias De Trabajo Temporal",
    "sg:phone":"+34 954 28 31 76",
    "sg:postcode":"41011",
    "sg:province":"Sevilla",
    "sg:website":"www.adecco.es",
    "wof:name":"Adecco E.t.t. S.a.",
    "wof:placetype":"venue"
},
  "geometry": {"coordinates":[-5.9974212646,37.3729286194],"type":"Point"}
}