{
  "type": "Feature",
  "properties": {
    "iso:country":"ES",
    "sg:address":"Calle de Dos, 10",
    "sg:city":"Consuegra",
    "sg:orig_category":"Mec\u00c1nico Del Autom\u00d3vil",
    "sg:phone":"+34 925 47 50 75",
    "sg:postcode":"45700",
    "sg:province":"Toledo",
    "wof:name":"Lugremi S.l.",
    "wof:placetype":"venue"
},
  "geometry": {"coordinates":[-3.6115398407,39.4641304016],"type":"Point"}
}