{
  "type": "Feature",
  "properties": {
    "addr:full":"Calle de Ruiz De Alarcon, 9 Madrid Madrid 28014",
    "addr:housenumber":"9",
    "addr:postcode":"madrid;28014",
    "addr:street":"Calle De Ruiz De Alarcon",
    "iso:country":"ES",
    "sg:address":"Calle de Ruiz De Alarcon, 9",
    "sg:city":"Madrid",
    "sg:orig_category":"Caf\u00c9s, Bares, Cervecer\u00cdas",
    "sg:phone":"+34 915 21 74 21",
    "sg:postcode":"28014",
    "sg:province":"Madrid",
    "sg:website":"www.vienacapellanes.com",
    "wof:name":"Viena Reposteria Capellanes S. A.",
    "wof:placetype":"venue"
},
  "geometry": {"coordinates":[-3.691339016,40.4162826538],"type":"Point"}
}