{
  "type": "Feature",
  "properties": {
    "iso:country":"ES",
    "sg:address":"Calle de Calderon De La Barca, 24",
    "sg:city":"San Vicente Del Raspeig-sant Vicent Del Raspeig",
    "sg:orig_category":"Peluqueros: De Se\u00d1oras",
    "sg:phone":"+34 965 66 66 63",
    "sg:postcode":"03690",
    "sg:province":"Alicante",
    "wof:name":"Atienza Casarrubios Elvira",
    "wof:placetype":"venue"
},
  "geometry": {"coordinates":[-0.5216816068,38.3994140625],"type":"Point"}
}