{
  "type": "Feature",
  "properties": {
    "addr:full":"Rbla Marina, 213 Hospitalet Llobregat Barcelona 08907",
    "addr:housenumber":"213",
    "addr:postcode":"08907",
    "addr:street":"Rbla Marina",
    "iso:country":"ES",
    "sg:address":"Rbla Marina, 213",
    "sg:city":"Hospitalet Llobregat",
    "sg:orig_category":"Molduras, Junquillos, Listones Y Molduras Perforadas",
    "sg:phone":"+34 933 35 68 53",
    "sg:postcode":"08907",
    "sg:province":"Barcelona",
    "wof:name":"Perea Rincon Antonio",
    "wof:placetype":"venue"
},
  "geometry": {"coordinates":[2.1091890335,41.3510360718],"type":"Point"}
}