{
  "type": "Feature",
  "properties": {
    "iso:country":"ES",
    "sg:address":"Calle de Fernando El Catolico, 8",
    "sg:city":"Alcala Real",
    "sg:orig_category":"Carnicer\u00cdas, Carnicer\u00cdas",
    "sg:phone":"+34 953 58 53 16",
    "sg:postcode":"23680",
    "sg:province":"Ja\u00e9n",
    "wof:name":"Trujillo Aguilera Ana Maria",
    "wof:placetype":"venue"
},
  "geometry": {"coordinates":[-3.921364069,37.4597854614],"type":"Point"}
}