{
  "type": "Feature",
  "properties": {
    "iso:country":"ES",
    "sg:address":"Calle de Manuel Badia, 6",
    "sg:city":"Madrid",
    "sg:orig_category":"Chapister\u00cda",
    "sg:phone":"+34 917 78 03 85",
    "sg:postcode":"28018",
    "sg:province":"Madrid",
    "wof:name":"Orche Velasco Angel",
    "wof:placetype":"venue"
},
  "geometry": {"coordinates":[-3.6518259048,40.3862953186],"type":"Point"}
}