{
  "type": "Feature",
  "properties": {
    "addr:full":"Pase Matutino, S/n Ponteareas Pontevedra 36860",
    "addr:housenumber":"/ n",
    "addr:postcode":"36860",
    "addr:street":"Matutino S",
    "iso:country":"ES",
    "sg:address":"Pase Matutino, S/n",
    "sg:city":"Ponteareas",
    "sg:orig_category":"Centros De Educaci\u00d3n Especial",
    "sg:phone":"+34 986 66 10 84",
    "sg:postcode":"36860",
    "sg:province":"Pontevedra",
    "wof:name":"Colexio Publico Maestro Ramiro Sabell Mosquera",
    "wof:placetype":"venue"
},
  "geometry": {"coordinates":[-8.5163888931,42.1783599854],"type":"Point"}
}