{
  "type": "Feature",
  "properties": {
    "addr:full":"Calle de Ramon Areces, S/n Nueva Andalucia M\u00e1laga 29660",
    "addr:housenumber":"s / n",
    "addr:postcode":"29660",
    "addr:street":"Calle De Ramon Areces;Ma\u0301Laga",
    "iso:country":"ES",
    "sg:address":"Calle de Ramon Areces, S/n",
    "sg:city":"Nueva Andalucia",
    "sg:orig_category":"Relojer\u00cda (al Por Menor, Reparaci\u00d3n)",
    "sg:phone":"+34 952 81 91 20",
    "sg:postcode":"29660",
    "sg:province":"M\u00e1laga",
    "wof:name":"Chartham Holdings S.l.",
    "wof:placetype":"venue"
},
  "geometry": {"coordinates":[-4.9540901184,36.4891586304],"type":"Point"}
}