{
  "type": "Feature",
  "properties": {
    "addr:full":"Calle de Edificio Velasco, 26 Irun Guip\u00f9zcoa 20303",
    "addr:housenumber":"26",
    "addr:postcode":"20303",
    "addr:street":"Calle De Edificio Velasco;Guipu\u0300Zcoa",
    "iso:country":"ES",
    "sg:address":"Calle de Edificio Velasco, 26",
    "sg:city":"Irun",
    "sg:orig_category":"Pescader\u00cdas (al Por Menor)",
    "sg:phone":"+34 943 63 42 87",
    "sg:postcode":"20303",
    "sg:province":"Guip\u00f9zcoa",
    "wof:name":"Bacalaos Eguillor Sa",
    "wof:placetype":"venue"
},
  "geometry": {"coordinates":[-1.7902339697,43.3395233154],"type":"Point"}
}