{
  "type": "Feature",
  "properties": {
    "addr:full":"Antigua Auzoa, S/n Antzuola Guip\u00f9zcoa 20577",
    "addr:housenumber":"s / n",
    "addr:postcode":"20577",
    "addr:street":"Antigua Auzoa;Guipu\u0300Zcoa",
    "iso:country":"ES",
    "sg:address":"Antigua Auzoa, S/n",
    "sg:city":"Antzuola",
    "sg:orig_category":"Fabricaci\u00d3n De Pernos, Tornillos Y Clavos",
    "sg:phone":"+34 943 76 64 66",
    "sg:postcode":"20577",
    "sg:province":"Guip\u00f9zcoa",
    "wof:name":"Talleres Jose Navarro S.l.",
    "wof:placetype":"venue"
},
  "geometry": {"coordinates":[-2.3775429726,43.0959472656],"type":"Point"}
}