{
  "type": "Feature",
  "properties": {
    "iso:country":"ES",
    "sg:address":"Plaz Plaza De Molinar, 9",
    "sg:city":"Sandamendi",
    "sg:orig_category":"Iglesia Cat\u00d3lica",
    "sg:phone":"+34 946 79 80 06",
    "sg:postcode":"48192",
    "sg:province":"Vizcaya",
    "wof:name":"Parroquia De La Degollacion De San Juan Bautista",
    "wof:placetype":"venue"
},
  "geometry": {"coordinates":[-3.0710809231,43.1801567078],"type":"Point"}
}