{
  "type": "Feature",
  "properties": {
    "iso:country":"ES",
    "sg:address":"Carrer de Fluvia, 217",
    "sg:city":"Barcelona",
    "sg:orig_category":"Postigos, Persianas Y Celos\u00cdas",
    "sg:phone":"+34 933 08 50 50",
    "sg:postcode":"08020",
    "sg:province":"Barcelona",
    "wof:name":"Pons Palacin Sergio",
    "wof:placetype":"venue"
},
  "geometry": {"coordinates":[2.196739912,41.4147186279],"type":"Point"}
}