{
  "type": "Feature",
  "properties": {
    "iso:country":"ES",
    "sg:address":"Calle de Padre Espla, 40",
    "sg:city":"Alacant",
    "sg:orig_category":"Asociaciones Y Clubs Deportivos",
    "sg:phone":"+34 965 20 25 70",
    "sg:postcode":"03013",
    "sg:province":"Alicante",
    "sg:website":"www.camontemar.com",
    "wof:name":"Club Atletico Montemar",
    "wof:placetype":"venue"
},
  "geometry": {"coordinates":[-0.4764130116,38.3571434021],"type":"Point"}
}