{
  "type": "Feature",
  "properties": {
    "addr:full":"Calle de Santo Domingo, 21 Talavera Reina Toledo 45600",
    "addr:housenumber":"21",
    "addr:postcode":"45600",
    "addr:street":"Calle De Santo Domingo",
    "iso:country":"ES",
    "sg:address":"Calle de Santo Domingo, 21",
    "sg:city":"Talavera Reina",
    "sg:orig_category":"Internados & Ense\u00d1anza Privada",
    "sg:phone":"+34 925 80 03 33",
    "sg:postcode":"45600",
    "sg:province":"Toledo",
    "wof:name":"Colegio De La Orden De Maria Nuestra Sra",
    "wof:placetype":"venue"
},
  "geometry": {"coordinates":[-4.8371300697,39.9616889954],"type":"Point"}
}