{
  "type": "Feature",
  "properties": {
    "iso:country":"ES",
    "sg:address":"Carrer de Prat De La Riba, 103",
    "sg:city":"Terrassa",
    "sg:orig_category":"Comercio, Reparaci\u00d3n De Motocicletas, Bicicletas Y Piezas Sueltas",
    "sg:phone":"+34 937 84 13 99",
    "sg:postcode":"08222",
    "sg:province":"Barcelona",
    "wof:name":"Moto Recambio Marvea S.l.",
    "wof:placetype":"venue"
},
  "geometry": {"coordinates":[2.0218670368,41.5675201416],"type":"Point"}
}