{
  "type": "Feature",
  "properties": {
    "addr:full":"Calle de Doctor Azpitarte, 1 Granada Granada 18012",
    "addr:housenumber":"1",
    "addr:postcode":"18012",
    "addr:street":"Calle De Doctor Azpitarte",
    "iso:country":"ES",
    "sg:address":"Calle de Doctor Azpitarte, 1",
    "sg:city":"Granada",
    "sg:orig_category":"Abogados",
    "sg:phone":"+34 958 20 21 40",
    "sg:postcode":"18012",
    "sg:province":"Granada",
    "wof:name":"Pi\u00f1ar Diaz Lucia Del Mar",
    "wof:placetype":"venue"
},
  "geometry": {"coordinates":[-3.6074755192,37.1881713867],"type":"Point"}
}