{
  "type": "Feature",
  "properties": {
    "iso:country":"ES",
    "sg:address":"Carrer de Antoni Pons, 7",
    "sg:city":"Palma",
    "sg:orig_category":"Mec\u00c1nico Del Autom\u00d3vil",
    "sg:phone":"+34 971 73 88 53",
    "sg:postcode":"07013",
    "sg:province":"Islas Baleares",
    "wof:name":"Mas Ramis Francisco",
    "wof:placetype":"venue"
},
  "geometry": {"coordinates":[2.6384730339,39.577922821],"type":"Point"}
}