{
  "type": "Feature",
  "properties": {
    "addr:full":"Calle de Mayor, 2 Entrena La Rioja 26375",
    "addr:housenumber":"2",
    "addr:postcode":"26375",
    "addr:street":"Calle De Mayor;Rioja",
    "iso:country":"ES",
    "sg:address":"Calle de Mayor, 2",
    "sg:city":"Entrena",
    "sg:orig_category":"Alimentaci\u00d3n General (al Por Menor)",
    "sg:phone":"+34 941 44 60 35",
    "sg:postcode":"26375",
    "sg:province":"La Rioja",
    "wof:name":"Andres Garcia Carmen",
    "wof:placetype":"venue"
},
  "geometry": {"coordinates":[-2.5306568146,42.3880958557],"type":"Point"}
}