{
  "type": "Feature",
  "properties": {
    "iso:country":"ES",
    "sg:address":"Calle de Costa Rica, 1",
    "sg:city":"Malaga",
    "sg:orig_category":"Psic\u00d3logos",
    "sg:phone":"+34 952 29 42 95",
    "sg:postcode":"29017",
    "sg:province":"M\u00e1laga",
    "wof:name":"Ramirez Montesinos Beatriz",
    "wof:placetype":"venue"
},
  "geometry": {"coordinates":[-4.3787021637,36.7233428955],"type":"Point"}
}