{
  "type": "Feature",
  "properties": {
    "addr:full":"Calle de Domingo Suarez, 14 Arguineguin Las Palmas 35120",
    "addr:housenumber":"14",
    "addr:postcode":"35120",
    "addr:street":"Calle De Domingo Suarez;Palmas",
    "iso:country":"ES",
    "sg:address":"Calle de Domingo Suarez, 14",
    "sg:city":"Arguineguin",
    "sg:orig_category":"Asociaciones, Organismos Culturales Y Socioeducativos",
    "sg:phone":"+34 928 15 03 07",
    "sg:postcode":"35120",
    "sg:province":"Las Palmas",
    "wof:name":"Club Noruego De Gran Canaria",
    "wof:placetype":"venue"
},
  "geometry": {"coordinates":[-15.680516243,27.75740242],"type":"Point"}
}