{
  "type": "Feature",
  "properties": {
    "addr:full":"Calle de Leon Y Castillo, 64 Palmas De Gran Canaria Las Palmas 35003",
    "addr:postcode":"35003",
    "addr:street":"Calle De Leon Y Castillo 64",
    "iso:country":"ES",
    "sg:address":"Calle de Leon Y Castillo, 64",
    "sg:city":"Palmas De Gran Canaria",
    "sg:orig_category":"Cl\u00cdnicas Dentales",
    "sg:phone":"+34 928 38 01 43",
    "sg:postcode":"35003",
    "sg:province":"Las Palmas",
    "wof:name":"Perioimplant S.l.",
    "wof:placetype":"venue"
},
  "geometry": {"coordinates":[-15.4195384979,28.112739563],"type":"Point"}
}