{
  "type": "Feature",
  "properties": {
    "addr:full":"Calle de Miraflores, S/n Constantina Sevilla 41450",
    "addr:housenumber":"s / n",
    "addr:postcode":"41450",
    "addr:street":"Calle De Miraflores",
    "iso:country":"ES",
    "sg:address":"Calle de Miraflores, S/n",
    "sg:city":"Constantina",
    "sg:orig_category":"Hoteles",
    "sg:phone":"+34 955 88 00 77",
    "sg:postcode":"41450",
    "sg:province":"Sevilla",
    "wof:name":"Promotora De Alojamientos Rurales Fg Y Ps S.l.",
    "wof:placetype":"venue"
},
  "geometry": {"coordinates":[-5.6195588112,37.8777809143],"type":"Point"}
}