{
  "type": "Feature",
  "properties": {
    "iso:country":"ES",
    "sg:address":"Calle de Bolivar, 28",
    "sg:city":"Salamanca",
    "sg:orig_category":"Asesor\u00cda Fiscal Y Jur\u00cddica",
    "sg:phone":"+34 923 22 20 04",
    "sg:postcode":"37004",
    "sg:province":"Salamanca",
    "wof:name":"Santos De Vega Maria Teresa",
    "wof:placetype":"venue"
},
  "geometry": {"coordinates":[-5.6543369293,40.9734115601],"type":"Point"}
}