{
  "type": "Feature",
  "properties": {
    "iso:country":"ES",
    "sg:address":"Carrer de Josep Anselm Clave (de), 3",
    "sg:city":"Vila-seca",
    "sg:orig_category":"Laboratorios Y Trabajos De Fotograf\u00cda, V\u00cddeo Y Cine",
    "sg:phone":"+34 977 39 28 79",
    "sg:postcode":"43480",
    "sg:province":"Tarragona",
    "wof:name":"Stanovjkhina  Nataliya",
    "wof:placetype":"venue"
},
  "geometry": {"coordinates":[1.1484520435,41.1118812561],"type":"Point"}
}