{
  "type": "Feature",
  "properties": {
    "addr:full":"Carrer de Arago, 231 Barcelona Barcelona 08007",
    "addr:housenumber":"231",
    "addr:postcode":"08007",
    "addr:street":"Carrer De Arago",
    "iso:country":"ES",
    "sg:address":"Carrer de Arago, 231",
    "sg:city":"Barcelona",
    "sg:orig_category":"Inmobiliaria (agencias)",
    "sg:phone":"+34 934 87 21 05",
    "sg:postcode":"08007",
    "sg:province":"Barcelona",
    "wof:name":"Ribersol S.l",
    "wof:placetype":"venue"
},
  "geometry": {"coordinates":[2.1621038914,41.3902854919],"type":"Point"}
}