{
  "type": "Feature",
  "properties": {
    "addr:full":"Avda Calvo Sotelo, S/n Osorno Palencia 34460",
    "addr:housenumber":"s / n",
    "addr:postcode":"34460",
    "addr:street":"Avda Calvo Sotelo",
    "iso:country":"ES",
    "sg:address":"Avda Calvo Sotelo, S/n",
    "sg:city":"Osorno",
    "sg:orig_category":"Productos Alimentarios",
    "sg:phone":"+34 979 81 72 85",
    "sg:postcode":"34460",
    "sg:province":"Palencia",
    "wof:name":"Cooperativa Comarcal De Piensos Tierra De Campos",
    "wof:placetype":"venue"
},
  "geometry": {"coordinates":[-4.3593549728,42.4124450684],"type":"Point"}
}