{
  "type": "Feature",
  "properties": {
    "addr:full":"Carr Pins, S/n Urbanitzacio Bell-lloc Ii Girona 17245",
    "addr:housenumber":"s / n",
    "addr:postcode":"17245",
    "addr:street":"Carr Pins",
    "iso:country":"ES",
    "sg:address":"Carr Pins, S/n",
    "sg:city":"Urbanitzacio Bell-lloc Ii",
    "sg:orig_category":"Fabricaci\u00d3n De Quesos",
    "sg:phone":"+34 972 83 31 39",
    "sg:postcode":"17245",
    "sg:province":"Girona",
    "wof:name":"Bayoluc S.l.",
    "wof:placetype":"venue"
},
  "geometry": {"coordinates":[2.9791510105,41.8317756653],"type":"Point"}
}