{
  "type": "Feature",
  "properties": {
    "addr:full":"Calle de Nafarroa, 11 Leioa Vizcaya 48940",
    "addr:housenumber":"11",
    "addr:postcode":"48940",
    "addr:street":"Calle De Nafarroa",
    "iso:country":"ES",
    "sg:address":"Calle de Nafarroa, 11",
    "sg:city":"Leioa",
    "sg:orig_category":"Frutas Y Legumbres Secas (al Por Mayor)",
    "sg:phone":"+34 944 64 96 16",
    "sg:postcode":"48940",
    "sg:province":"Vizcaya",
    "wof:name":"Martina Lencero Mantecon",
    "wof:placetype":"venue"
},
  "geometry": {"coordinates":[-3.0052061081,43.3274765015],"type":"Point"}
}