{
  "type": "Feature",
  "properties": {
    "addr:full":"Avda De La Libertad, 1 Vinaros Castell\u00f3n 12500",
    "addr:housenumber":"1",
    "addr:postcode":"12500",
    "addr:street":"Avda De La Libertad",
    "iso:country":"ES",
    "sg:address":"Avda De La Libertad, 1",
    "sg:city":"Vinaros",
    "sg:orig_category":"Arquitectos",
    "sg:phone":"+34 964 45 62 91",
    "sg:postcode":"12500",
    "sg:province":"Castell\u00f3n",
    "wof:name":"Marca Matute Maria Dolores",
    "wof:placetype":"venue"
},
  "geometry": {"coordinates":[0.4749450088,40.4711990356],"type":"Point"}
}