{
  "type": "Feature",
  "properties": {
    "iso:country":"ES",
    "sg:address":"Calle de Fataga, 41",
    "sg:city":"Palmas De Gran Canaria",
    "sg:orig_category":"Chapister\u00cda",
    "sg:phone":"+34 928 46 13 12",
    "sg:postcode":"35009",
    "sg:province":"Las Palmas",
    "wof:name":"Tejera Robaina Francisco",
    "wof:placetype":"venue"
},
  "geometry": {"coordinates":[-15.4249916077,28.1540431976],"type":"Point"}
}