{
  "type": "Feature",
  "properties": {
    "addr:full":"Carrer de Diagonal, 17 Barriada Nova Barcelona 08420",
    "addr:housenumber":"17",
    "addr:postcode":"08420",
    "addr:street":"Carrer De Diagonal;Nova Barcelona",
    "iso:country":"ES",
    "sg:address":"Carrer de Diagonal, 17",
    "sg:city":"Barriada Nova",
    "sg:orig_category":"Animales (al Por Menor)",
    "sg:phone":"+34 938 49 03 04",
    "sg:postcode":"08420",
    "sg:province":"Barcelona",
    "wof:name":"Sanchez Pineda Silvia",
    "wof:placetype":"venue"
},
  "geometry": {"coordinates":[2.2780098915,41.6220703125],"type":"Point"}
}