{
  "type": "Feature",
  "properties": {
    "iso:country":"ES",
    "sg:address":"Calle de Eskalantegi, 32",
    "sg:city":"Donostia-san Sebastian",
    "sg:orig_category":"Farmacias",
    "sg:phone":"+34 943 51 07 81",
    "sg:postcode":"20017",
    "sg:province":"Guip\u00f9zcoa",
    "wof:name":"Ormazabal Iturralde Ignacio",
    "wof:placetype":"venue"
},
  "geometry": {"coordinates":[-1.9209262133,43.312877655],"type":"Point"}
}