{
  "type": "Feature",
  "properties": {
    "iso:country":"ES",
    "sg:address":"Calle de Tilos (los), 3",
    "sg:city":"Teruel",
    "sg:orig_category":"Peluquer\u00cdas, Peluquer\u00cda Mixta",
    "sg:phone":"+34 978 60 35 92",
    "sg:postcode":"44002",
    "sg:province":"Teruel",
    "wof:name":"Pueyo Mercader Elisabeth",
    "wof:placetype":"venue"
},
  "geometry": {"coordinates":[-1.0951189995,40.3294334412],"type":"Point"}
}