{
  "type": "Feature",
  "properties": {
    "addr:full":"Carr Xeresa, 20 Gandia Valencia 46700",
    "addr:housenumber":"20",
    "addr:postcode":"46700",
    "addr:street":"Carr Xeresa;Valencia",
    "iso:country":"ES",
    "sg:address":"Carr Xeresa, 20",
    "sg:city":"Gandia",
    "sg:orig_category":"Inform\u00c1tica, Ofim\u00c1tica (estudios, Asesor\u00cda, Ingenier\u00cda, Formaci\u00d3n)",
    "sg:phone":"+34 962 87 74 38",
    "sg:postcode":"46700",
    "sg:province":"Valencia",
    "sg:website":"www.run-sys.com",
    "wof:name":"Run Sistemas 2000 S.l",
    "wof:placetype":"venue"
},
  "geometry": {"coordinates":[-0.1913339943,38.960735321],"type":"Point"}
}