{
  "type": "Feature",
  "properties": {
    "addr:full":"Carr Alcalde Juan Sancho, 2 Oliva Valencia 46780",
    "addr:housenumber":"2",
    "addr:postcode":"46780",
    "addr:street":"Carr Alcalde Juan Sancho",
    "iso:country":"ES",
    "sg:address":"Carr Alcalde Juan Sancho, 2",
    "sg:city":"Oliva",
    "sg:orig_category":"Centros M\u00c9dicos Y Sociales, Dispensarios",
    "sg:phone":"+34 962 83 90 27",
    "sg:postcode":"46780",
    "sg:province":"Valencia",
    "wof:name":"Consuelo Betty Deusa Gea Y Mercedes Peiro Gea Cdad.",
    "wof:placetype":"venue"
},
  "geometry": {"coordinates":[-0.1177840009,38.9221343994],"type":"Point"}
}