{
  "type": "Feature",
  "properties": {
    "addr:full":"Carrer de Bruc, 58 Barcelona Barcelona 08009",
    "addr:housenumber":"58",
    "addr:postcode":"08009",
    "addr:street":"Carrer De Bruc",
    "iso:country":"ES",
    "sg:address":"Carrer de Bruc, 58",
    "sg:city":"Barcelona",
    "sg:orig_category":"Abogados",
    "sg:phone":"+34 933 01 16 16",
    "sg:postcode":"08009",
    "sg:province":"Barcelona",
    "wof:name":"Alarcon Mondejar Alberto",
    "wof:placetype":"venue"
},
  "geometry": {"coordinates":[2.1715273857,41.3928451538],"type":"Point"}
}