{
  "type": "Feature",
  "properties": {
    "iso:country":"ES",
    "sg:address":"Calle de Cristo, 42",
    "sg:city":"Valdepe\u00f1as",
    "sg:orig_category":"Agencias De Viajes",
    "sg:phone":"+34 926 31 24 91",
    "sg:postcode":"13300",
    "sg:province":"Ciudad Real",
    "wof:name":"Expansion Siglo Xxi S.l.",
    "wof:placetype":"venue"
},
  "geometry": {"coordinates":[-3.3897840977,38.7593345642],"type":"Point"}
}