{
  "type": "Feature",
  "properties": {
    "addr:full":"Carrer de Joaquim Valls, 73 Barcelona Barcelona 08016",
    "addr:housenumber":"73",
    "addr:postcode":"08016",
    "addr:street":"Carrer De Joaquim Valls",
    "iso:country":"ES",
    "sg:address":"Carrer de Joaquim Valls, 73",
    "sg:city":"Barcelona",
    "sg:orig_category":"Cajas De Ahorro",
    "sg:phone":"+34 933 53 60 22",
    "sg:postcode":"08016",
    "sg:province":"Barcelona",
    "wof:name":"Caixa D'estalvis I Pensions De Barcelona",
    "wof:placetype":"venue"
},
  "geometry": {"coordinates":[2.1801071167,41.443649292],"type":"Point"}
}