{
  "type": "Feature",
  "properties": {
    "addr:full":"Barr Venta (la), 13 Venta Cantabria 39593",
    "addr:postcode":"39593",
    "iso:country":"ES",
    "sg:address":"Barr Venta (la), 13",
    "sg:city":"Venta",
    "sg:orig_category":"Bebidas",
    "sg:phone":"+34 942 70 94 05",
    "sg:postcode":"39593",
    "sg:province":"Cantabria",
    "wof:name":"Distribuidora Lamadrid S.l.",
    "wof:placetype":"venue"
},
  "geometry": {"coordinates":[-4.3518548012,43.3186454773],"type":"Point"}
}