{
  "type": "Feature",
  "properties": {
    "iso:country":"ES",
    "sg:address":"Calle de Antonio Machado, 5",
    "sg:city":"Antas",
    "sg:orig_category":"Delegados, Agentes De Tr\u00c1nsito, Auxiliares De Transporte Internacional",
    "sg:phone":"+34 950 45 31 31",
    "sg:postcode":"04628",
    "sg:province":"Almer\u00eda",
    "wof:name":"Transportes Teruel Y Carpintero S.l.",
    "wof:placetype":"venue"
},
  "geometry": {"coordinates":[-1.9179970026,37.2471313477],"type":"Point"}
}