{
  "type": "Feature",
  "properties": {
    "addr:full":"Calle de San Francisco De Borja, 9 Valencia Valencia 46007",
    "addr:housenumber":"9",
    "addr:postcode":"46007",
    "addr:street":"Calle De San Francisco De Borja",
    "iso:country":"ES",
    "sg:address":"Calle de San Francisco De Borja, 9",
    "sg:city":"Valencia",
    "sg:orig_category":"Lavado, Limpieza De Veh\u00cdculos",
    "sg:phone":"+34 963 84 31 75",
    "sg:postcode":"46007",
    "sg:province":"Valencia",
    "wof:name":"Rodriguez Pradas Jorge",
    "wof:placetype":"venue"
},
  "geometry": {"coordinates":[-0.3852300048,39.4659919739],"type":"Point"}
}