{
  "type": "Feature",
  "properties": {
    "iso:country":"ES",
    "sg:address":"Calle de Olivares, 1",
    "sg:city":"Villarejo Del Valle",
    "sg:orig_category":"Reposter\u00cdas",
    "sg:phone":"+34 920 38 32 84",
    "sg:postcode":"05413",
    "sg:province":"\u00c1vila",
    "wof:name":"Barba Rey Juan Jose",
    "wof:placetype":"venue"
},
  "geometry": {"coordinates":[-4.997508049,40.2864227295],"type":"Point"}
}