{
  "type": "Feature",
  "properties": {
    "iso:country":"ES",
    "sg:address":"Calle de Ballesta, 4",
    "sg:city":"Vera",
    "sg:orig_category":"Fotocopias, Reprograf\u00cda",
    "sg:phone":"+34 950 39 04 24",
    "sg:postcode":"04620",
    "sg:province":"Almer\u00eda",
    "wof:name":"Servicio De Reprografia Y Dise\u00f1o Digital S.l.",
    "wof:placetype":"venue"
},
  "geometry": {"coordinates":[-1.8700389862,37.2485618591],"type":"Point"}
}