{
  "type": "Feature",
  "properties": {
    "addr:full":"C\u00f1o. Rio Esteiro, 35 Hio Pontevedra 36948",
    "addr:housenumber":"35",
    "addr:postcode":"36948",
    "addr:street":"Esteiro",
    "iso:country":"ES",
    "sg:address":"C\u00f1o. Rio Esteiro, 35",
    "sg:city":"Hio",
    "sg:orig_category":"Doctores En Medicina",
    "sg:phone":"+34 986 32 95 64",
    "sg:postcode":"36948",
    "sg:province":"Pontevedra",
    "wof:name":"Baqueiro Carballo Maria Jose",
    "wof:placetype":"venue"
},
  "geometry": {"coordinates":[-8.6428003311,42.4304618835],"type":"Point"}
}