{
  "type": "Feature",
  "properties": {
    "addr:full":"La Noria, 33 Fuengirola M\u00e1laga 29640",
    "addr:housenumber":"33",
    "addr:postcode":"29640",
    "addr:street":"La Noria;Ma\u0301Laga",
    "iso:country":"ES",
    "sg:address":"La Noria, 33",
    "sg:city":"Fuengirola",
    "sg:orig_category":"Iglesia Cat\u00d3lica",
    "sg:phone":"+34 952 47 30 34",
    "sg:postcode":"29640",
    "sg:province":"M\u00e1laga",
    "wof:name":"Obispado De Malaga",
    "wof:placetype":"venue"
},
  "geometry": {"coordinates":[-4.6330537796,36.5426368713],"type":"Point"}
}