{
  "type": "Feature",
  "properties": {
    "addr:full":"Avda Cervantes, 44 Ca\u00f1amero C\u00e1ceres 10136",
    "addr:housenumber":"44",
    "addr:postcode":"10136",
    "addr:street":"Avda Cervantes;Ca\u0301Ceres",
    "iso:country":"ES",
    "sg:address":"Avda Cervantes, 44",
    "sg:city":"Ca\u00f1amero",
    "sg:orig_category":"Ense\u00d1anza, Formaci\u00d3n Profesional: Aprendizaje",
    "sg:phone":"+34 927 36 94 63",
    "sg:postcode":"10136",
    "sg:province":"C\u00e1ceres",
    "wof:name":"Martin Colome Francisco Javier",
    "wof:placetype":"venue"
},
  "geometry": {"coordinates":[-5.3884339333,39.381313324],"type":"Point"}
}