{
  "type": "Feature",
  "properties": {
    "iso:country":"ES",
    "sg:address":"Carrer de Rafael Campalans, 77",
    "sg:city":"Hospitalet Llobregat",
    "sg:orig_category":"Molduras, Junquillos, Listones Y Molduras Perforadas",
    "sg:phone":"+34 934 49 11 68",
    "sg:postcode":"08903",
    "sg:province":"Barcelona",
    "wof:name":"Moragreca Planisoles Rosario",
    "wof:placetype":"venue"
},
  "geometry": {"coordinates":[2.1232690811,41.3718795776],"type":"Point"}
}