{
  "type": "Feature",
  "properties": {
    "addr:full":"Partida De La Muela, S/n Monroyo Teruel 44652",
    "addr:housenumber":"s",
    "addr:postcode":"44652",
    "addr:street":"Partida De La Muela;/ N",
    "iso:country":"ES",
    "sg:address":"Partida De La Muela, S/n",
    "sg:city":"Monroyo",
    "sg:orig_category":"Poller\u00cda Y Caza (al Por Menor)",
    "sg:phone":"+34 978 85 60 10",
    "sg:postcode":"44652",
    "sg:province":"Teruel",
    "wof:name":"Lombarte Agut Jose Miguel",
    "wof:placetype":"venue"
},
  "geometry": {"coordinates":[-0.0354860015,40.7876167297],"type":"Point"}
}