{
  "type": "Feature",
  "properties": {
    "addr:full":"Ctra. Valencia-ademus, S/n La Ca\u00f1ada Valencia 46182",
    "addr:housenumber":"s / n",
    "addr:postcode":"46182",
    "addr:street":"Ctra. Valencia-Ademus",
    "iso:country":"ES",
    "sg:address":"Ctra. Valencia-ademus, S/n",
    "sg:city":"La Ca\u00f1ada",
    "sg:orig_category":"Garajes De Veh\u00cdculos",
    "sg:phone":"+34 961 32 20 13",
    "sg:postcode":"46182",
    "sg:province":"Valencia",
    "wof:name":"Centro Valenciano De Vaporizacion",
    "wof:placetype":"venue"
},
  "geometry": {"coordinates":[-0.4846090078,39.5360183716],"type":"Point"}
}