{
  "type": "Feature",
  "properties": {
    "addr:full":"Calle de Aneto, 14 Barbastro Huesca 22300",
    "addr:housenumber":"14",
    "addr:postcode":"22300",
    "addr:street":"Calle De Aneto",
    "iso:country":"ES",
    "sg:address":"Calle de Aneto, 14",
    "sg:city":"Barbastro",
    "sg:orig_category":"Contenedores (mercanc\u00cdas)",
    "sg:phone":"+34 974 31 32 58",
    "sg:postcode":"22300",
    "sg:province":"Huesca",
    "wof:name":"Lopez Lopez Saturnino",
    "wof:placetype":"venue"
},
  "geometry": {"coordinates":[0.1185156032,42.0346069336],"type":"Point"}
}