{
  "type": "Feature",
  "properties": {
    "iso:country":"ES",
    "sg:address":"Av Sant Moritz, 10",
    "sg:city":"Sant Moritz",
    "sg:orig_category":"Papel (al Por Mayor)",
    "sg:phone":"+34 938 43 97 30",
    "sg:postcode":"08185",
    "sg:province":"Barcelona",
    "wof:name":"Cartonajes Sellol S.l.",
    "wof:placetype":"venue"
},
  "geometry": {"coordinates":[2.2324490547,41.5865364075],"type":"Point"}
}