{
  "type": "Feature",
  "properties": {
    "iso:country":"ES",
    "sg:address":"Calle de Oeste, 20",
    "sg:city":"Carbajosa Sagrada",
    "sg:orig_category":"Agencias Y Agentes Comerciales, Representantes",
    "sg:phone":"+34 923 20 89 16",
    "sg:postcode":"37188",
    "sg:province":"Salamanca",
    "wof:name":"Sanchez Santos Jose Maria",
    "wof:placetype":"venue"
},
  "geometry": {"coordinates":[-5.651927948,40.9336662292],"type":"Point"}
}