{
  "type": "Feature",
  "properties": {
    "iso:country":"ES",
    "sg:address":"Calle de Virgen Del Pilar, 38",
    "sg:city":"Palmas De Gran Canaria",
    "sg:orig_category":"Peluqueros: De Se\u00d1oras",
    "sg:phone":"+34 928 42 14 82",
    "sg:postcode":"35012",
    "sg:province":"Las Palmas",
    "wof:name":"Garcia Silva Ana Rosa",
    "wof:placetype":"venue"
},
  "geometry": {"coordinates":[-15.4444255829,28.1167316437],"type":"Point"}
}