{
  "type": "Feature",
  "properties": {
    "addr:full":"Carr Mestre Sagrera, 31 Palafrugell Girona 17200",
    "addr:housenumber":"31",
    "addr:postcode":"17200",
    "addr:street":"Carr Mestre Sagrera",
    "iso:country":"ES",
    "sg:address":"Carr Mestre Sagrera, 31",
    "sg:city":"Palafrugell",
    "sg:orig_category":"Quincaller\u00cda (al Por Menor)",
    "sg:phone":"+34 972 30 61 80",
    "sg:postcode":"17200",
    "sg:province":"Girona",
    "wof:name":"Ferreteria Palafrugell S. A.",
    "wof:placetype":"venue"
},
  "geometry": {"coordinates":[3.1557679176,41.9195022583],"type":"Point"}
}