{
  "type": "Feature",
  "properties": {
    "iso:country":"ES",
    "sg:address":"Calle de Obispo Cobos, 12",
    "sg:city":"Ubeda",
    "sg:orig_category":"Confecci\u00d3n (fabricaci\u00d3n, Al Por Mayor)",
    "sg:phone":"+34 953 79 17 48",
    "sg:postcode":"23400",
    "sg:province":"Ja\u00e9n",
    "wof:name":"Leon Mengibar Consuelo",
    "wof:placetype":"venue"
},
  "geometry": {"coordinates":[-3.3744909763,38.0115394592],"type":"Point"}
}