{
  "type": "Feature",
  "properties": {
    "iso:country":"ES",
    "sg:address":"Rbla Catalunya, 63",
    "sg:city":"Barcelona",
    "sg:orig_category":"Asesor\u00cda Fiscal Y Jur\u00cddica",
    "sg:phone":"+34 932 15 65 90",
    "sg:postcode":"08007",
    "sg:province":"Barcelona",
    "wof:name":"Pijuan Sabate Luis",
    "wof:placetype":"venue"
},
  "geometry": {"coordinates":[2.1630549431,41.3910751343],"type":"Point"}
}