{
  "type": "Feature",
  "properties": {
    "addr:full":"Calle de Agustina De Aragon, 1 Lomo Magullo Las Palmas 35200",
    "addr:housenumber":"1",
    "addr:postcode":"35200",
    "addr:street":"Calle De Agustina De Aragon;Palmas",
    "iso:country":"ES",
    "sg:address":"Calle de Agustina De Aragon, 1",
    "sg:city":"Lomo Magullo",
    "sg:orig_category":"Carnicer\u00cdas, Carnicer\u00cdas",
    "sg:phone":"+34 928 68 24 31",
    "sg:postcode":"35200",
    "sg:province":"Las Palmas",
    "wof:name":"Rodriguez Lopez Juan",
    "wof:placetype":"venue"
},
  "geometry": {"coordinates":[-15.4592876434,27.9836349487],"type":"Point"}
}