{
  "type": "Feature",
  "properties": {
    "iso:country":"ES",
    "sg:address":"O Reino, S/n",
    "sg:city":"Reino",
    "sg:orig_category":"Carnicer\u00cdas, Carnicer\u00cdas",
    "sg:phone":"+34 988 40 32 08",
    "sg:postcode":"32138",
    "sg:province":"Ourense",
    "wof:name":"Garcia Pousa Jose Luis",
    "wof:placetype":"venue"
},
  "geometry": {"coordinates":[-7.8646407127,42.340007782],"type":"Point"}
}