{
  "type": "Feature",
  "properties": {
    "addr:full":"Avda Espinela, 15 Madrid Madrid 28021",
    "addr:housenumber":"15",
    "addr:postcode":"madrid;28021",
    "addr:street":"Avda Espinela",
    "iso:country":"ES",
    "sg:address":"Avda Espinela, 15",
    "sg:city":"Madrid",
    "sg:orig_category":"Postigos, Persianas Y Celos\u00cdas",
    "sg:phone":"+34 917 98 42 68",
    "sg:postcode":"28021",
    "sg:province":"Madrid",
    "wof:name":"Sanchez Plaza Jose",
    "wof:placetype":"venue"
},
  "geometry": {"coordinates":[-3.7093379498,40.3448257446],"type":"Point"}
}