{
  "type": "Feature",
  "properties": {
    "addr:full":"Av Jacquard, 41 Terrassa Barcelona 08222",
    "addr:housenumber":"41",
    "addr:postcode":"08222",
    "addr:street":"Av Jacquard",
    "iso:country":"ES",
    "sg:address":"Av Jacquard, 41",
    "sg:city":"Terrassa",
    "sg:orig_category":"Muebles, Minoristas",
    "sg:phone":"+34 937 85 64 59",
    "sg:postcode":"08222",
    "sg:province":"Barcelona",
    "sg:website":"www.novamobile.es",
    "wof:name":"Mil Solucions S.l.",
    "wof:placetype":"venue"
},
  "geometry": {"coordinates":[2.0199849606,41.5639228821],"type":"Point"}
}