{
  "type": "Feature",
  "properties": {
    "iso:country":"ES",
    "sg:address":"Avda Coru\u00d1a, 19",
    "sg:city":"Pontedeume",
    "sg:orig_category":"Librer\u00cdas",
    "sg:phone":"+34 981 43 38 72",
    "sg:postcode":"15600",
    "sg:province":"La Coru\u00f1a",
    "wof:name":"Ga\u00d1ete Vazquez Amelia",
    "wof:placetype":"venue"
},
  "geometry": {"coordinates":[-8.1673574448,43.4050941467],"type":"Point"}
}