{
  "type": "Feature",
  "properties": {
    "iso:country":"ES",
    "sg:address":"Cmno Real De Zaragoza, S/n",
    "sg:city":"Barbastro",
    "sg:orig_category":"Asilos De Ancianos. Centros Privados",
    "sg:phone":"+34 974 30 85 62",
    "sg:postcode":"22300",
    "sg:province":"Huesca",
    "wof:name":"Regerso S.l.",
    "wof:placetype":"venue"
},
  "geometry": {"coordinates":[0.1143150032,42.0306472778],"type":"Point"}
}