{
  "type": "Feature",
  "properties": {
    "iso:country":"ES",
    "sg:address":"Calle de Alondra, 9",
    "sg:city":"Madrid",
    "sg:orig_category":"Inform\u00c1tica (estudios, Servicios, Asesor\u00cda, Formaci\u00d3n)",
    "sg:phone":"+34 914 66 05 56",
    "sg:postcode":"28025",
    "sg:province":"Madrid",
    "wof:name":"Mainsa Sistemas S.l.",
    "wof:placetype":"venue"
},
  "geometry": {"coordinates":[-3.7348837852,40.387462616],"type":"Point"}
}