{
  "type": "Feature",
  "properties": {
    "iso:country":"ES",
    "sg:address":"Proyecto, 7",
    "sg:city":"Benidorm",
    "sg:orig_category":"M\u00c9dicos: Oftalmolog\u00cda",
    "sg:phone":"+34 966 81 25 81",
    "sg:postcode":"03500",
    "sg:province":"Alicante",
    "wof:name":"Instituto Oftalmologico De Alicante S.l.",
    "wof:placetype":"venue"
},
  "geometry": {"coordinates":[-0.1743289977,38.5408058167],"type":"Point"}
}