{
  "type": "Feature",
  "properties": {
    "addr:full":"Pl Santa Anna, 23 Mataro Barcelona 08302",
    "addr:housenumber":"23",
    "addr:postcode":"08302",
    "addr:street":"Pl Santa Anna",
    "iso:country":"ES",
    "sg:address":"Pl Santa Anna, 23",
    "sg:city":"Mataro",
    "sg:orig_category":"Bisuter\u00cda, Joyer\u00cda, Relojer\u00cda (al Por Menor)",
    "sg:phone":"+34 937 90 33 42",
    "sg:postcode":"08302",
    "sg:province":"Barcelona",
    "wof:name":"Ximenes I Fills S. A.",
    "wof:placetype":"venue"
},
  "geometry": {"coordinates":[2.4443714619,41.5372695923],"type":"Point"}
}