{
  "type": "Feature",
  "properties": {
    "addr:full":"Avda Abaro, 32 Portugalete Vizcaya 48920",
    "addr:housenumber":"32",
    "addr:postcode":"48920",
    "addr:street":"Avda Abaro",
    "iso:country":"ES",
    "sg:address":"Avda Abaro, 32",
    "sg:city":"Portugalete",
    "sg:orig_category":"Peluquer\u00cdas, Peluquer\u00cda Mixta",
    "sg:phone":"+34 944 83 88 99",
    "sg:postcode":"48920",
    "sg:province":"Vizcaya",
    "wof:name":"Peluqueria, Bego\u00f1a Eguskiza Madariaga",
    "wof:placetype":"venue"
},
  "geometry": {"coordinates":[-3.0216679573,43.3234138489],"type":"Point"}
}