{
  "type": "Feature",
  "properties": {
    "addr:full":"Rua Antonio Palacios, 40 Porri\u00f1o Pontevedra 36400",
    "addr:housenumber":"40",
    "addr:postcode":"36400",
    "addr:street":"Rua Antonio Palacios",
    "iso:country":"ES",
    "sg:address":"Rua Antonio Palacios, 40",
    "sg:city":"Porri\u00f1o",
    "sg:orig_category":"Notarios",
    "sg:phone":"+34 986 33 55 44",
    "sg:postcode":"36400",
    "sg:province":"Pontevedra",
    "wof:name":"Regueira Nunez Ernesto",
    "wof:placetype":"venue"
},
  "geometry": {"coordinates":[-8.6179990768,42.1610298157],"type":"Point"}
}