{
  "type": "Feature",
  "properties": {
    "addr:full":"Calle de Ca\u00d1averal, 5 Granada Granada 18003",
    "addr:housenumber":"5",
    "addr:postcode":"18003",
    "addr:street":"Calle De Can\u0303Averal",
    "iso:country":"ES",
    "sg:address":"Calle de Ca\u00d1averal, 5",
    "sg:city":"Granada",
    "sg:orig_category":"Abogados",
    "sg:phone":"+34 958 27 64 05",
    "sg:postcode":"18003",
    "sg:province":"Granada",
    "wof:name":"Sanchez Ruiz Virgilio",
    "wof:placetype":"venue"
},
  "geometry": {"coordinates":[-3.6117041111,37.178352356],"type":"Point"}
}