{
  "type": "Feature",
  "properties": {
    "addr:full":"Ctra. Cabanillas, 18 Alovera Guadalajara 19208",
    "addr:housenumber":"18",
    "addr:postcode":"19208",
    "addr:street":"Ctra. Cabanillas",
    "iso:country":"ES",
    "sg:address":"Ctra. Cabanillas, 18",
    "sg:city":"Alovera",
    "sg:orig_category":"Electricidad: Instaladores",
    "sg:phone":"+34 949 27 01 90",
    "sg:postcode":"19208",
    "sg:province":"Guadalajara",
    "wof:name":"Juan Francisco Perez Blanco S.l.",
    "wof:placetype":"venue"
},
  "geometry": {"coordinates":[-3.2489299774,40.5955467224],"type":"Point"}
}