{
  "type": "Feature",
  "properties": {
    "addr:full":"Calle de Cervantes, 21 Calzada Calatrava Ciudad Real 13370",
    "addr:housenumber":"21",
    "addr:postcode":"13370",
    "addr:street":"Calle De Cervantes",
    "iso:country":"ES",
    "sg:address":"Calle de Cervantes, 21",
    "sg:city":"Calzada Calatrava",
    "sg:orig_category":"Peluquer\u00cdas, Peluquer\u00cda Mixta",
    "sg:phone":"+34 926 87 60 58",
    "sg:postcode":"13370",
    "sg:province":"Ciudad Real",
    "wof:name":"Coello Mansilla Jesus",
    "wof:placetype":"venue"
},
  "geometry": {"coordinates":[-3.7759819031,38.7042045593],"type":"Point"}
}