{
  "type": "Feature",
  "properties": {
    "iso:country":"ES",
    "sg:address":"Calle de Alhambra, 7",
    "sg:city":"Viznar",
    "sg:orig_category":"Carnicer\u00cdas, Carnicer\u00cdas",
    "sg:phone":"+34 958 54 33 32",
    "sg:postcode":"18179",
    "sg:province":"Granada",
    "wof:name":"Espigares Carrillo Jose",
    "wof:placetype":"venue"
},
  "geometry": {"coordinates":[-3.553507328,37.2315864563],"type":"Point"}
}