{
  "type": "Feature",
  "properties": {
    "addr:full":"Carrer de Sant Joan Bosco, 118 Mataro Barcelona 08303",
    "addr:housenumber":"118",
    "addr:postcode":"08303",
    "addr:street":"Carrer De Sant Joan Bosco",
    "iso:country":"ES",
    "sg:address":"Carrer de Sant Joan Bosco, 118",
    "sg:city":"Mataro",
    "sg:orig_category":"Empresas De Demolici\u00d3n",
    "sg:phone":"+34 937 58 67 62",
    "sg:postcode":"08303",
    "sg:province":"Barcelona",
    "wof:name":"Excavaciones Y Aridos Otero S.l.",
    "wof:placetype":"venue"
},
  "geometry": {"coordinates":[2.4210000038,41.5380592346],"type":"Point"}
}