{
  "type": "Feature",
  "properties": {
    "addr:full":"Rua Rio Arnoia, 26 Xinzo De Limia Ourense 32630",
    "addr:housenumber":"26",
    "addr:postcode":"32630",
    "addr:street":"Rua;Arnoia",
    "iso:country":"ES",
    "sg:address":"Rua Rio Arnoia, 26",
    "sg:city":"Xinzo De Limia",
    "sg:orig_category":"Florister\u00cdas",
    "sg:phone":"+34 988 46 12 32",
    "sg:postcode":"32630",
    "sg:province":"Ourense",
    "wof:name":"Rodriguez Otero Adolfo",
    "wof:placetype":"venue"
},
  "geometry": {"coordinates":[-7.7227649689,42.0594406128],"type":"Point"}
}