{
  "type": "Feature",
  "properties": {
    "addr:full":"Ptda Caxola, S/n Finestrat Alicante 03509",
    "addr:housenumber":"s / n",
    "addr:postcode":"03509",
    "addr:street":"Ptda Caxola",
    "iso:country":"ES",
    "sg:address":"Ptda Caxola, S/n",
    "sg:city":"Finestrat",
    "sg:orig_category":"Confiter\u00cdas, Chocolater\u00cdas (al Por Menor)",
    "sg:phone":"+34 966 80 66 15",
    "sg:postcode":"03509",
    "sg:province":"Alicante",
    "wof:name":"Productos Alimenticios Belros S.a.",
    "wof:placetype":"venue"
},
  "geometry": {"coordinates":[-0.2106740028,38.5691642761],"type":"Point"}
}