{
  "type": "Feature",
  "properties": {
    "iso:country":"ES",
    "sg:address":"Carr Bisbe Talladas, Del, 13",
    "sg:city":"Campos",
    "sg:orig_category":"Cajas De Ahorro",
    "sg:phone":"+34 971 65 01 82",
    "sg:postcode":"07630",
    "sg:province":"Islas Baleares",
    "wof:name":"Caja De Ahorros Y Monte De Piedad De Las Baleares",
    "wof:placetype":"venue"
},
  "geometry": {"coordinates":[3.0184309483,39.4302787781],"type":"Point"}
}