{
  "type": "Feature",
  "properties": {
    "addr:full":"Calle de Santiago, 5 Palencia Palencia 34004",
    "addr:housenumber":"5",
    "addr:postcode":"34004",
    "addr:street":"Calle De Santiago",
    "iso:country":"ES",
    "sg:address":"Calle de Santiago, 5",
    "sg:city":"Palencia",
    "sg:orig_category":"Molduras, Junquillos, Listones Y Molduras Perforadas",
    "sg:phone":"+34 979 72 01 04",
    "sg:postcode":"34004",
    "sg:province":"Palencia",
    "wof:name":"Gil Gil Petra",
    "wof:placetype":"venue"
},
  "geometry": {"coordinates":[-4.5227689743,41.9990348816],"type":"Point"}
}