{
  "type": "Feature",
  "properties": {
    "addr:full":"Avda Madrid, 191 Zaragoza Zaragoza 50017",
    "addr:housenumber":"191",
    "addr:postcode":"50017",
    "addr:street":"Avda Madrid",
    "iso:country":"ES",
    "sg:address":"Avda Madrid, 191",
    "sg:city":"Zaragoza",
    "sg:orig_category":"Cajas De Ahorro",
    "sg:phone":"+34 976 32 73 11",
    "sg:postcode":"50017",
    "sg:province":"Zaragoza",
    "wof:name":"Caja De Ahorros De Valencia Castellon Y Alicante",
    "wof:placetype":"venue"
},
  "geometry": {"coordinates":[-0.9080849886,41.6524467468],"type":"Point"}
}