{
  "type": "Feature",
  "properties": {
    "addr:full":"Fernando Urkia Kalea, 15 Arbizu Navarra 31839",
    "addr:housenumber":"15",
    "addr:postcode":"31839",
    "addr:street":"Fernando Urkia Kalea",
    "iso:country":"ES",
    "sg:address":"Fernando Urkia Kalea, 15",
    "sg:city":"Arbizu",
    "sg:orig_category":"Ebanister\u00cda",
    "sg:phone":"+34 948 46 00 29",
    "sg:postcode":"31839",
    "sg:province":"Navarra",
    "wof:name":"Ara\u00f1a Leiza Maria Luisa",
    "wof:placetype":"venue"
},
  "geometry": {"coordinates":[-2.039536953,42.9150505066],"type":"Point"}
}