{
  "type": "Feature",
  "properties": {
    "iso:country":"ES",
    "sg:address":"Calle de Florida (la), 34",
    "sg:city":"Florida",
    "sg:orig_category":"Serigraf\u00cda (material Y Suministros)",
    "sg:phone":"+34 968 62 33 86",
    "sg:postcode":"30565",
    "sg:province":"Murcia",
    "sg:website":"www.stampatallergrafico.com",
    "wof:name":"Stampa Taller Grafico S.l.l.",
    "wof:placetype":"venue"
},
  "geometry": {"coordinates":[-1.2450864315,38.0460853577],"type":"Point"}
}