{
  "type": "Feature",
  "properties": {
    "iso:country":"ES",
    "sg:address":"Plaz Juan De La Cierva, 8",
    "sg:city":"Totana",
    "sg:orig_category":"M\u00c9dicos: Estomatolog\u00cda",
    "sg:phone":"+34 968 42 47 15",
    "sg:postcode":"30850",
    "sg:province":"Murcia",
    "wof:name":"Martinez Gallinal Tania",
    "wof:placetype":"venue"
},
  "geometry": {"coordinates":[-1.4991250038,37.771282196],"type":"Point"}
}