{
  "type": "Feature",
  "properties": {
    "iso:country":"ES",
    "sg:address":"Carrt. Badajoz-granada, Km. 0239,5",
    "sg:city":"El Vacar",
    "sg:orig_category":"Distribuci\u00d3n De Petr\u00d3leo Y Derivados",
    "sg:phone":"+34 957 36 70 31",
    "sg:postcode":"14320",
    "sg:province":"C\u00f3rdoba",
    "wof:name":"Hijos De Joaquin Dominguez S.l.",
    "wof:placetype":"venue"
},
  "geometry": {"coordinates":[-4.7910299301,38.0256881714],"type":"Point"}
}