{
  "type": "Feature",
  "properties": {
    "iso:country":"ES",
    "sg:address":"Carrer de Llobateres, S/n",
    "sg:city":"Barbera Valles",
    "sg:orig_category":"Confecci\u00d3n De Cinturones Y De Tirantes",
    "sg:phone":"+34 937 18 59 14",
    "sg:postcode":"08210",
    "sg:province":"Barcelona",
    "wof:name":"Proiseg Catalunya S.l.",
    "wof:placetype":"venue"
},
  "geometry": {"coordinates":[2.1419599056,41.5272636414],"type":"Point"}
}