{
  "type": "Feature",
  "properties": {
    "iso:country":"ES",
    "sg:address":"Calle de Francisco Villaespesa, 2",
    "sg:city":"Motril",
    "sg:orig_category":"Producci\u00d3n, Distribuci\u00d3n De Electricidad",
    "sg:phone":"+34 958 60 04 00",
    "sg:postcode":"18600",
    "sg:province":"Granada",
    "wof:name":"Lopez Maturana Ricardo",
    "wof:placetype":"venue"
},
  "geometry": {"coordinates":[-3.5188341141,36.7518768311],"type":"Point"}
}