{
  "type": "Feature",
  "properties": {
    "addr:full":"Calle de Senda De Les Animes - Poligono Ind., S/n Catarroja Valencia 46470",
    "addr:housenumber":"s / n",
    "addr:postcode":"46470",
    "addr:street":"Calle De Senda De Les;Poligono Ind.",
    "iso:country":"ES",
    "sg:address":"Calle de Senda De Les Animes - Poligono Ind., S/n",
    "sg:city":"Catarroja",
    "sg:orig_category":"M\u00c1rmoles, Granitos Y Piedras Naturales",
    "sg:phone":"+34 961 26 12 30",
    "sg:postcode":"46470",
    "sg:province":"Valencia",
    "wof:name":"Marmoles Artisticos Casa\u00f1 S.l.",
    "wof:placetype":"venue"
},
  "geometry": {"coordinates":[-0.414440006,39.3972015381],"type":"Point"}
}