{
  "type": "Feature",
  "properties": {
    "addr:full":"Calle de La Florida, 7 San Vicente De Barakaldo Vizcaya 48902",
    "addr:postcode":"48902",
    "addr:street":"Calle De La Florida 7",
    "iso:country":"ES",
    "sg:address":"Calle de La Florida, 7",
    "sg:city":"San Vicente De Barakaldo",
    "sg:orig_category":"Mec\u00c1nico Del Autom\u00d3vil",
    "sg:phone":"+34 944 37 63 97",
    "sg:postcode":"48902",
    "sg:province":"Vizcaya",
    "wof:name":"Servicio De Turismos E Industriales S.a.",
    "wof:placetype":"venue"
},
  "geometry": {"coordinates":[-2.9865620136,43.292842865],"type":"Point"}
}