{
  "type": "Feature",
  "properties": {
    "addr:full":"Cami Fondo, 1 Mataro Barcelona 08301",
    "addr:housenumber":"1",
    "addr:postcode":"08301",
    "addr:street":"Fondo",
    "iso:country":"ES",
    "sg:address":"Cami Fondo, 1",
    "sg:city":"Mataro",
    "sg:orig_category":"Caf\u00c9s, Bares, Cervecer\u00cdas",
    "sg:phone":"+34 937 41 01 92",
    "sg:postcode":"08301",
    "sg:province":"Barcelona",
    "wof:name":"Puyol Alcantara Inmaculada",
    "wof:placetype":"venue"
},
  "geometry": {"coordinates":[2.4472420216,41.5441818237],"type":"Point"}
}