{
  "type": "Feature",
  "properties": {
    "iso:country":"ES",
    "sg:address":"Poli Teknologi Elkartegia, 805",
    "sg:city":"Arteaga",
    "sg:orig_category":"M\u00c9dicos: An\u00c1lisis Cl\u00cdnicos",
    "sg:phone":"+34 944 31 70 48",
    "sg:postcode":"48170",
    "sg:province":"Vizcaya",
    "sg:website":"www.datagene.es",
    "wof:name":"Nuevos Desarrollos Y Aplicaciones Geneticas S. L. L.",
    "wof:placetype":"venue"
},
  "geometry": {"coordinates":[-2.8633139133,43.280834198],"type":"Point"}
}