{
  "type": "Feature",
  "properties": {
    "addr:full":"Calle de Aguila, 13 Chiclana De La Frontera C\u00e1diz 11130",
    "addr:housenumber":"13",
    "addr:postcode":"11130",
    "addr:street":"Calle De Aguila",
    "iso:country":"ES",
    "sg:address":"Calle de Aguila, 13",
    "sg:city":"Chiclana De La Frontera",
    "sg:orig_category":"Inmobiliaria (agencias)",
    "sg:phone":"+34 956 53 64 14",
    "sg:postcode":"11130",
    "sg:province":"C\u00e1diz",
    "wof:name":"Gestion Inmobiliaria Montes Vi\u00f1a Mar Del Mayorazgo",
    "wof:placetype":"venue"
},
  "geometry": {"coordinates":[-6.1496248245,36.4121665955],"type":"Point"}
}