{
  "type": "Feature",
  "properties": {
    "addr:full":"Carrer de Balmes, 299 Barcelona Barcelona 08006",
    "addr:housenumber":"299",
    "addr:postcode":"08006",
    "addr:street":"Carrer De Balmes",
    "iso:country":"ES",
    "sg:address":"Carrer de Balmes, 299",
    "sg:city":"Barcelona",
    "sg:orig_category":"Abogados",
    "sg:phone":"+34 932 09 79 58",
    "sg:postcode":"08006",
    "sg:province":"Barcelona",
    "wof:name":"Rabell Arbos Antonio",
    "wof:placetype":"venue"
},
  "geometry": {"coordinates":[2.1460258961,41.4019622803],"type":"Point"}
}