{
  "type": "Feature",
  "properties": {
    "addr:full":"Calle de Guevara, 6 Santander Cantabria 39001",
    "addr:housenumber":"6",
    "addr:postcode":"39001",
    "addr:street":"Calle De Guevara",
    "iso:country":"ES",
    "sg:address":"Calle de Guevara, 6",
    "sg:city":"Santander",
    "sg:orig_category":"Cuchiller\u00cda (al Por Menor)",
    "sg:phone":"+34 942 36 15 62",
    "sg:postcode":"39001",
    "sg:province":"Cantabria",
    "wof:name":"Iba\u00f1ez Garcia Celso",
    "wof:placetype":"venue"
},
  "geometry": {"coordinates":[-3.8101410866,43.4635772705],"type":"Point"}
}