{
  "type": "Feature",
  "properties": {
    "iso:country":"ES",
    "sg:address":"Praj Club De Tenis, S/n",
    "sg:city":"Urbanizacion Club De Tenis",
    "sg:orig_category":"Chapa Y Pintura Veh\u00cdculos",
    "sg:phone":"+34 950 30 05 09",
    "sg:postcode":"04230",
    "sg:province":"Almer\u00eda",
    "wof:name":"Autotalleres Suanes S.l",
    "wof:placetype":"venue"
},
  "geometry": {"coordinates":[-2.4370388985,36.8798294067],"type":"Point"}
}