{
  "type": "Feature",
  "properties": {
    "iso:country":"ES",
    "sg:address":"Carrer de Missio, 38",
    "sg:city":"Palma",
    "sg:orig_category":"Administradores De Bienes Y Delegados De Comunidades De Propietarios",
    "sg:phone":"+34 971 71 61 56",
    "sg:postcode":"07003",
    "sg:province":"Islas Baleares",
    "wof:name":"Benitez Gallardo Miguel",
    "wof:placetype":"venue"
},
  "geometry": {"coordinates":[2.6508500576,39.5750427246],"type":"Point"}
}