{
  "type": "Feature",
  "properties": {
    "addr:full":"Energia, 3 Gava Barcelona 08850",
    "addr:housenumber":"3",
    "addr:postcode":"08850",
    "addr:street":"Energia",
    "iso:country":"ES",
    "sg:address":"Energia, 3",
    "sg:city":"Gava",
    "sg:orig_category":"Comercio De Hierro",
    "sg:phone":"+34 936 62 84 11",
    "sg:postcode":"08850",
    "sg:province":"Barcelona",
    "wof:name":"Ferros Brugues S. A.",
    "wof:placetype":"venue"
},
  "geometry": {"coordinates":[1.9996210337,41.2960395813],"type":"Point"}
}