{
  "type": "Feature",
  "properties": {
    "iso:country":"ES",
    "sg:address":"Calle de Pio Xii, 10",
    "sg:city":"Barbate",
    "sg:orig_category":"Alimentaci\u00d3n General (al Por Menor)",
    "sg:phone":"+34 956 43 14 45",
    "sg:postcode":"11160",
    "sg:province":"C\u00e1diz",
    "wof:name":"Guillen Oliver Hilario",
    "wof:placetype":"venue"
},
  "geometry": {"coordinates":[-5.922451973,36.1906471252],"type":"Point"}
}