{
  "type": "Feature",
  "properties": {
    "iso:country":"ES",
    "sg:address":"Calle de O\u00d1a, 177",
    "sg:city":"Madrid",
    "sg:orig_category":"M\u00c9dicos: Pediatr\u00cda. Enfermedades De Los Ni\u00d1os",
    "sg:phone":"+34 913 83 27 03",
    "sg:postcode":"28050",
    "sg:province":"Madrid",
    "wof:name":"Noya Beiroa Maria Elena",
    "wof:placetype":"venue"
},
  "geometry": {"coordinates":[-3.6609830856,40.4895019531],"type":"Point"}
}