{
  "type": "Feature",
  "properties": {
    "iso:country":"ES",
    "sg:address":"L. Bravo, S/n",
    "sg:city":"Villalonquejar",
    "sg:orig_category":"Publicidad (soportes Y Gesti\u00d3n)",
    "sg:phone":"+34 947 47 38 22",
    "sg:postcode":"09001",
    "sg:province":"Burgos",
    "sg:website":"www.jcdecaux.com",
    "wof:name":"Jc Decaux Espa\u00d1a S.l.",
    "wof:placetype":"venue"
},
  "geometry": {"coordinates":[-3.7283790112,42.3722801208],"type":"Point"}
}