{
  "type": "Feature",
  "properties": {
    "iso:country":"ES",
    "sg:address":"Carlos Vii, 7",
    "sg:city":"Estella",
    "sg:orig_category":"Fabricaci\u00d3n, Instalaci\u00d3n Y Reparaci\u00d3n De Bombas",
    "sg:phone":"+34 948 55 12 46",
    "sg:postcode":"31200",
    "sg:province":"Navarra",
    "wof:name":"On-bay S.l.",
    "wof:placetype":"venue"
},
  "geometry": {"coordinates":[-2.0318911076,42.6651878357],"type":"Point"}
}