{
  "type": "Feature",
  "properties": {
    "addr:full":"Calle de Andres Borrego, 19 Madrid Madrid 28004",
    "addr:housenumber":"19",
    "addr:postcode":"madrid;28004",
    "addr:street":"Calle De Andres Borrego",
    "iso:country":"ES",
    "sg:address":"Calle de Andres Borrego, 19",
    "sg:city":"Madrid",
    "sg:orig_category":"Aparcamientos (infraestructuras, Accesorios)",
    "sg:phone":"+34 915 32 21 81",
    "sg:postcode":"28004",
    "sg:province":"Madrid",
    "wof:name":"Gutierrez Fernandez Margarita",
    "wof:placetype":"venue"
},
  "geometry": {"coordinates":[-3.706381321,40.4239730835],"type":"Point"}
}