{
  "type": "Feature",
  "properties": {
    "addr:full":"Pl. Flores, 7 Malaga M\u00e1laga 29005",
    "addr:housenumber":"7",
    "addr:postcode":"29005",
    "addr:street":"Flores;Ma\u0301Laga",
    "iso:country":"ES",
    "sg:address":"Pl. Flores, 7",
    "sg:city":"Malaga",
    "sg:orig_category":"Procuradores",
    "sg:phone":"+34 952 60 15 18",
    "sg:postcode":"29005",
    "sg:province":"M\u00e1laga",
    "wof:name":"Gonzalez Illesca Rosa",
    "wof:placetype":"venue"
},
  "geometry": {"coordinates":[-4.4223518372,36.7203102112],"type":"Point"}
}