{
  "type": "Feature",
  "properties": {
    "iso:country":"ES",
    "sg:address":"Cami Vell De Bunyola, 96",
    "sg:city":"Indioteria",
    "sg:classifiers":[
        {
            "category":"Autos & Motor Vehicles",
            "subcategory":"Automobile Sales",
            "type":"Retail Goods"
        }
    ],
    "sg:phone":"+34 971 29 05 15",
    "sg:postcode":"07009",
    "sg:province":"Islas Baleares",
    "sg:website":"www.levante-salas.com",
    "wof:name":"Autoescuelas Levante-salas S.l.",
    "wof:placetype":"venue"
},
  "geometry": {"coordinates":[2.6769104004,39.604473114],"type":"Point"}
}