{
  "type": "Feature",
  "properties": {
    "iso:country":"ES",
    "sg:address":"Calle de Puerta De Almodovar, 2",
    "sg:city":"Cordoba",
    "sg:orig_category":"Farmacias",
    "sg:phone":"+34 957 29 09 20",
    "sg:postcode":"14003",
    "sg:province":"C\u00f3rdoba",
    "wof:name":"Rosas Cristofol Maria Del Pilar",
    "wof:placetype":"venue"
},
  "geometry": {"coordinates":[-4.783703804,37.8808403015],"type":"Point"}
}