{
  "type": "Feature",
  "properties": {
    "addr:full":"Calle de Orion, 36 Madrid Madrid 28042",
    "addr:housenumber":"36",
    "addr:postcode":"madrid;28042",
    "addr:street":"Calle De Orion",
    "iso:country":"ES",
    "sg:address":"Calle de Orion, 36",
    "sg:city":"Madrid",
    "sg:orig_category":"Organizaciones Internacionales",
    "sg:phone":"+34 913 05 51 46",
    "sg:postcode":"28042",
    "sg:province":"Madrid",
    "wof:name":"Arelap",
    "wof:placetype":"venue"
},
  "geometry": {"coordinates":[-3.5792751312,40.4756469727],"type":"Point"}
}