{
  "type": "Feature",
  "properties": {
    "addr:full":"Avda Ramon Y Cajal, 1 Fuengirola M\u00e1laga 29640",
    "addr:housenumber":"1",
    "addr:postcode":"29640",
    "addr:street":"Avda Ramon Y Cajal;Ma\u0301Laga",
    "iso:country":"ES",
    "sg:address":"Avda Ramon Y Cajal, 1",
    "sg:city":"Fuengirola",
    "sg:orig_category":"Bancos",
    "sg:phone":"+34 952 58 71 02",
    "sg:postcode":"29640",
    "sg:province":"M\u00e1laga",
    "sg:website":"www.ebankinter.com",
    "wof:name":"Bankinter S.a.",
    "wof:placetype":"venue"
},
  "geometry": {"coordinates":[-4.6178312302,36.5482406616],"type":"Point"}
}