{
  "type": "Feature",
  "properties": {
    "iso:country":"ES",
    "sg:address":"Carr Illes Balears, 57",
    "sg:city":"Port D'alcudia",
    "sg:orig_category":"Empresas De Carpinter\u00cda De Madera",
    "sg:phone":"+34 971 54 50 54",
    "sg:postcode":"07410",
    "sg:province":"Islas Baleares",
    "wof:name":"Fusteria Biel Palou S.l.",
    "wof:placetype":"venue"
},
  "geometry": {"coordinates":[2.9117100239,39.6136398315],"type":"Point"}
}