{
  "type": "Feature",
  "properties": {
    "addr:full":"El Dosel, 15 Faro Cullera Valencia 46408",
    "addr:housenumber":"15",
    "addr:postcode":"46408",
    "addr:street":"Dosel",
    "iso:country":"ES",
    "sg:address":"El Dosel, 15",
    "sg:city":"Faro Cullera",
    "sg:orig_category":"Cerrajer\u00cda, Ferrallista",
    "sg:phone":"+34 961 74 66 07",
    "sg:postcode":"46408",
    "sg:province":"Valencia",
    "wof:name":"Borras Villena Jose",
    "wof:placetype":"venue"
},
  "geometry": {"coordinates":[-0.2268330008,39.1952667236],"type":"Point"}
}