{
  "type": "Feature",
  "properties": {
    "addr:full":"Carrer de Carrer de Europa, S/n Puerto Rico Las Palmas 35130",
    "addr:housenumber":"s / n",
    "addr:postcode":"35130",
    "addr:street":"Carrer;Carrer De Europa;Rico",
    "iso:country":"ES",
    "sg:address":"Carrer de Carrer de Europa, S/n",
    "sg:city":"Puerto Rico",
    "sg:orig_category":"Bisuter\u00cda, Joyer\u00cda, Relojer\u00cda (al Por Menor)",
    "sg:phone":"+34 928 56 20 81",
    "sg:postcode":"35130",
    "sg:province":"Las Palmas",
    "wof:name":"Sabhnani Sabhnani Lokesh",
    "wof:placetype":"venue"
},
  "geometry": {"coordinates":[-13.9036235809,28.6303958893],"type":"Point"}
}