{
  "type": "Feature",
  "properties": {
    "addr:full":"Calle de Burgos, 7 Madrid Madrid 28039",
    "addr:housenumber":"7",
    "addr:postcode":"madrid;28039",
    "addr:street":"Calle De Burgos",
    "iso:country":"ES",
    "sg:address":"Calle de Burgos, 7",
    "sg:city":"Madrid",
    "sg:orig_category":"Inmobiliaria (agencias)",
    "sg:phone":"+34 913 11 17 11",
    "sg:postcode":"28039",
    "sg:province":"Madrid",
    "wof:name":"Fragarcon S.l.",
    "wof:placetype":"venue"
},
  "geometry": {"coordinates":[-3.7058029175,40.4587593079],"type":"Point"}
}