{
  "type": "Feature",
  "properties": {
    "iso:country":"ES",
    "sg:address":"Ba. Garrapinillos, 137",
    "sg:city":"Garrapinillos",
    "sg:orig_category":"Producci\u00d3n, Venta De Productos De Agricultura Biol\u00d3gica",
    "sg:phone":"+34 976 46 27 54",
    "sg:postcode":"50190",
    "sg:province":"Zaragoza",
    "wof:name":"Eizaguerri Aparicio Antonio",
    "wof:placetype":"venue"
},
  "geometry": {"coordinates":[-1.0269140005,41.6842803955],"type":"Point"}
}