{
  "type": "Feature",
  "properties": {
    "addr:full":"Calle de Rio Ebro, 34 Norias De Daza Almer\u00eda 04716",
    "addr:housenumber":"34",
    "addr:postcode":"04716",
    "addr:street":"Calle De Rio Ebro;Almeri\u0301A",
    "iso:country":"ES",
    "sg:address":"Calle de Rio Ebro, 34",
    "sg:city":"Norias De Daza",
    "sg:orig_category":"Comunidades Religiosas",
    "sg:phone":"+34 950 58 74 08",
    "sg:postcode":"04716",
    "sg:province":"Almer\u00eda",
    "wof:name":"Religiosas Del Sagrado Corazon.",
    "wof:placetype":"venue"
},
  "geometry": {"coordinates":[-2.7523419857,36.758895874],"type":"Point"}
}