{
  "type": "Feature",
  "properties": {
    "iso:country":"ES",
    "sg:address":"Calle de Privilegio De La Union, 13",
    "sg:city":"Zaragoza",
    "sg:orig_category":"Empresas De Carpinter\u00cda Met\u00c1lica",
    "sg:phone":"+34 976 49 26 89",
    "sg:postcode":"50013",
    "sg:province":"Zaragoza",
    "wof:name":"Illan Fernandez Ricardo",
    "wof:placetype":"venue"
},
  "geometry": {"coordinates":[-0.8719819784,41.6423187256],"type":"Point"}
}