{
  "type": "Feature",
  "properties": {
    "iso:country":"ES",
    "sg:address":"Polg. Industrial, Km. 0029,0",
    "sg:city":"Quintana Serena",
    "sg:orig_category":"Mec\u00c1nico Del Autom\u00d3vil",
    "sg:phone":"+34 924 77 71 02",
    "sg:postcode":"06450",
    "sg:province":"Badajoz",
    "wof:name":"Taller Mecanico Hermanos Benitez Garcia S.l.",
    "wof:placetype":"venue"
},
  "geometry": {"coordinates":[-5.6712579727,38.743019104],"type":"Point"}
}