{
  "type": "Feature",
  "properties": {
    "addr:full":"Moruxo, S/n Moruxo La Coru\u00f1a 15165",
    "addr:housenumber":"s / n",
    "addr:postcode":"15165",
    "addr:street":"Moruxo;Moruxo La Corun\u0303A",
    "iso:country":"ES",
    "sg:address":"Moruxo, S/n",
    "sg:city":"Moruxo",
    "sg:orig_category":"Promotores Constructores",
    "sg:phone":"+34 981 79 40 27",
    "sg:postcode":"15165",
    "sg:province":"La Coru\u00f1a",
    "wof:name":"Carabel Cardelle Jose Antonio",
    "wof:placetype":"venue"
},
  "geometry": {"coordinates":[-8.2309961319,43.3134422302],"type":"Point"}
}