{
  "type": "Feature",
  "properties": {
    "iso:country":"ES",
    "sg:address":"Barrio Gardea (industrialdea), 4",
    "sg:city":"Llodio",
    "sg:orig_category":"Veh\u00cdculos De Ocasi\u00d3n",
    "sg:phone":"+34 946 72 81 01",
    "sg:postcode":"01400",
    "sg:province":"\u00c1lava",
    "wof:name":"Esca Ocasion S.l.",
    "wof:placetype":"venue"
},
  "geometry": {"coordinates":[-2.9744229317,43.1318435669],"type":"Point"}
}