{
  "type": "Feature",
  "properties": {
    "iso:country":"ES",
    "sg:address":"La Rosa, 10",
    "sg:city":"Sta Cruz Tenerife",
    "sg:orig_category":"Art\u00cdculos De Regalo (al Por Menor)",
    "sg:phone":"+34 922 28 22 07",
    "sg:postcode":"38002",
    "sg:province":"Santa Cruz De Tenerife",
    "wof:name":"Libreria Papeleria Plumier S. L.",
    "wof:placetype":"venue"
},
  "geometry": {"coordinates":[-16.250207901,28.4700984955],"type":"Point"}
}