{
  "type": "Feature",
  "properties": {
    "addr:full":"Plaz Vicente Iborra, 3 Valencia Valencia 46003",
    "addr:housenumber":"3",
    "addr:postcode":"46003",
    "addr:street":"Plaz;Iborra",
    "iso:country":"ES",
    "sg:address":"Plaz Vicente Iborra, 3",
    "sg:city":"Valencia",
    "sg:orig_category":"Centros Empresariales",
    "sg:phone":"+34 963 91 76 82",
    "sg:postcode":"46003",
    "sg:province":"Valencia",
    "wof:name":"Matarile S.l.",
    "wof:placetype":"venue"
},
  "geometry": {"coordinates":[-0.381415993,39.4766845703],"type":"Point"}
}