{
  "type": "Feature",
  "properties": {
    "addr:full":"Carr Migdia, 20 Girona Girona 17002",
    "addr:housenumber":"20",
    "addr:postcode":"17002",
    "addr:street":"Carr Migdia",
    "iso:country":"ES",
    "sg:address":"Carr Migdia, 20",
    "sg:city":"Girona",
    "sg:orig_category":"Ropa Para Ni\u00d1os (al Por Menor)",
    "sg:phone":"+34 972 21 46 89",
    "sg:postcode":"17002",
    "sg:province":"Girona",
    "wof:name":"Araus Forgas Jorge",
    "wof:placetype":"venue"
},
  "geometry": {"coordinates":[2.8208258152,41.9767799377],"type":"Point"}
}