{
  "type": "Feature",
  "properties": {
    "iso:country":"ES",
    "sg:address":"Calle de Mayor, 16",
    "sg:city":"Albacete",
    "sg:orig_category":"Farmacias",
    "sg:phone":"+34 967 21 53 23",
    "sg:postcode":"02002",
    "sg:province":"Albacete",
    "wof:name":"Casado Sobrino Rosario",
    "wof:placetype":"venue"
},
  "geometry": {"coordinates":[-1.8538589478,38.9929885864],"type":"Point"}
}