{
  "type": "Feature",
  "properties": {
    "addr:full":"Carrer de Marques De Campo, 39 Denia Alicante 03700",
    "addr:housenumber":"39",
    "addr:postcode":"03700",
    "addr:street":"Carrer De Marques De Campo",
    "iso:country":"ES",
    "sg:address":"Carrer de Marques De Campo, 39",
    "sg:city":"Denia",
    "sg:orig_category":"Sociedades, Compa\u00d1\u00cdas Aseguradoras",
    "sg:phone":"+34 966 42 24 24",
    "sg:postcode":"03700",
    "sg:province":"Alicante",
    "wof:name":"Ocaso S.a. Compa\u00f1ia De Seguros Y Reaseguros",
    "wof:placetype":"venue"
},
  "geometry": {"coordinates":[0.1101540029,38.8409805298],"type":"Point"}
}