{
  "type": "Feature",
  "properties": {
    "iso:country":"ES",
    "sg:address":"Calle de Olmo, 7",
    "sg:city":"Valladolid",
    "sg:orig_category":"Agencias Y Agentes Comerciales, Representantes",
    "sg:phone":"+34 983 26 20 71",
    "sg:postcode":"47010",
    "sg:province":"Valladolid",
    "wof:name":"Martinez Martin Jose Maria",
    "wof:placetype":"venue"
},
  "geometry": {"coordinates":[-4.7198328972,41.6608810425],"type":"Point"}
}