{
  "type": "Feature",
  "properties": {
    "addr:full":"Calle de Menorca, 31 Madrid Madrid 28009",
    "addr:housenumber":"31",
    "addr:postcode":"madrid;28009",
    "addr:street":"Calle De Menorca",
    "iso:country":"ES",
    "sg:address":"Calle de Menorca, 31",
    "sg:city":"Madrid",
    "sg:orig_category":"Aparcamientos (infraestructuras, Accesorios)",
    "sg:phone":"+34 915 73 91 17",
    "sg:postcode":"28009",
    "sg:province":"Madrid",
    "wof:name":"Urbanizadora Kinsi S.a.",
    "wof:placetype":"venue"
},
  "geometry": {"coordinates":[-3.6754539013,40.4195289612],"type":"Point"}
}