{
  "type": "Feature",
  "properties": {
    "addr:full":"Carrer de Pujades, 245 Barcelona Barcelona 08005",
    "addr:housenumber":"245",
    "addr:postcode":"08005",
    "addr:street":"Carrer De Pujades",
    "iso:country":"ES",
    "sg:address":"Carrer de Pujades, 245",
    "sg:city":"Barcelona",
    "sg:orig_category":"Agencias Y Agentes Comerciales, Representantes",
    "sg:phone":"+34 933 07 00 60",
    "sg:postcode":"08005",
    "sg:province":"Barcelona",
    "wof:name":"Muntane Simo Juan",
    "wof:placetype":"venue"
},
  "geometry": {"coordinates":[2.2041709423,41.4045372009],"type":"Point"}
}