{
  "type": "Feature",
  "properties": {
    "iso:country":"ES",
    "sg:address":"Calle de Duque De Cantabria, 5",
    "sg:city":"Trespaderne",
    "sg:orig_category":"M\u00c9dicos: Estomatolog\u00cda",
    "sg:phone":"+34 947 30 85 29",
    "sg:postcode":"09540",
    "sg:province":"Burgos",
    "wof:name":"Pereda Aldazabal Irache",
    "wof:placetype":"venue"
},
  "geometry": {"coordinates":[-3.3886497021,42.8040504456],"type":"Point"}
}