{
  "type": "Feature",
  "properties": {
    "iso:country":"ES",
    "sg:address":"Calle de Benito Gutierrez, 6",
    "sg:city":"Madrid",
    "sg:orig_category":"Asociaciones Y Clubs Deportivos",
    "sg:phone":"+34 915 44 79 56",
    "sg:postcode":"28008",
    "sg:province":"Madrid",
    "sg:website":"www.soldiers.com",
    "wof:name":"Eurosurcamp S.a.",
    "wof:placetype":"venue"
},
  "geometry": {"coordinates":[-3.7181031704,40.4321022034],"type":"Point"}
}