{
  "type": "Feature",
  "properties": {
    "iso:country":"ES",
    "sg:address":"Calle de Ramon Y Cajal, 2",
    "sg:city":"Reinosa",
    "sg:orig_category":"Mercer\u00cda, Lencer\u00cda (al Por Menor)",
    "sg:phone":"+34 942 75 06 62",
    "sg:postcode":"39200",
    "sg:province":"Cantabria",
    "wof:name":"Saez Caballero Maria Jose",
    "wof:placetype":"venue"
},
  "geometry": {"coordinates":[-4.1386699677,42.9999542236],"type":"Point"}
}