{
  "type": "Feature",
  "properties": {
    "iso:country":"ES",
    "sg:address":"Calle de Felipe Rinaldi, 18",
    "sg:city":"Valencia",
    "sg:orig_category":"Plomeros",
    "sg:phone":"+34 963 66 07 62",
    "sg:postcode":"46019",
    "sg:province":"Valencia",
    "wof:name":"Fasbany S.l.",
    "wof:placetype":"venue"
},
  "geometry": {"coordinates":[-0.3771561086,39.4933700562],"type":"Point"}
}