{
  "type": "Feature",
  "properties": {
    "addr:full":"Calle de Cybion, 15 Conil De La Frontera C\u00e1diz 11140",
    "addr:housenumber":"15",
    "addr:postcode":"11140",
    "addr:street":"Calle De Cybion",
    "iso:country":"ES",
    "sg:address":"Calle de Cybion, 15",
    "sg:city":"Conil De La Frontera",
    "sg:orig_category":"Farmacias",
    "sg:phone":"+34 956 44 29 44",
    "sg:postcode":"11140",
    "sg:province":"C\u00e1diz",
    "wof:name":"Valencia Roldan Alejandro",
    "wof:placetype":"venue"
},
  "geometry": {"coordinates":[-6.0912938118,36.2826919556],"type":"Point"}
}