{
  "type": "Feature",
  "properties": {
    "addr:full":"Pol Ind Suerte Saavedra, Km. 0003,0 Badajoz Badajoz 06009",
    "addr:postcode":"06009",
    "addr:street":"Saavedra Km. 0003,0",
    "iso:country":"ES",
    "sg:address":"Pol Ind Suerte Saavedra, Km. 0003,0",
    "sg:city":"Badajoz",
    "sg:orig_category":"Agentes, Concesionarios Y Sucursales De Veh\u00cdculos",
    "sg:phone":"+34 924 24 01 43",
    "sg:postcode":"06009",
    "sg:province":"Badajoz",
    "wof:name":"Autoalma S.a.",
    "wof:placetype":"venue"
},
  "geometry": {"coordinates":[-6.770813942,38.7708816528],"type":"Point"}
}