{
  "type": "Feature",
  "properties": {
    "addr:full":"Calle de Burriana, 25 Valencia Valencia 46005",
    "addr:housenumber":"25",
    "addr:postcode":"46005",
    "addr:street":"Calle De Burriana",
    "iso:country":"ES",
    "sg:address":"Calle de Burriana, 25",
    "sg:city":"Valencia",
    "sg:orig_category":"Graf\u00d3logos",
    "sg:phone":"+34 963 34 96 23",
    "sg:postcode":"46005",
    "sg:province":"Valencia",
    "wof:name":"Such Ronda Mari Carmen",
    "wof:placetype":"venue"
},
  "geometry": {"coordinates":[-0.3661977947,39.4653625488],"type":"Point"}
}