{
  "type": "Feature",
  "properties": {
    "iso:country":"ES",
    "sg:address":"Carrer de Sant Honorat, 85",
    "sg:city":"Sabadell",
    "sg:orig_category":"Estudios, Instalaci\u00d3n De Climatizaci\u00d3n",
    "sg:phone":"+34 937 27 90 46",
    "sg:postcode":"08202",
    "sg:province":"Barcelona",
    "wof:name":"Insta%acions I Manteniments Frago S.l.",
    "wof:placetype":"venue"
},
  "geometry": {"coordinates":[2.1109330654,41.5525398254],"type":"Point"}
}