{
  "type": "Feature",
  "properties": {
    "iso:country":"ES",
    "sg:address":"Ptge Treball, 30",
    "sg:city":"Barcelona",
    "sg:orig_category":"Barnizadores",
    "sg:phone":"+34 933 03 39 10",
    "sg:postcode":"08019",
    "sg:province":"Barcelona",
    "wof:name":"Torralba Ferrer Juan",
    "wof:placetype":"venue"
},
  "geometry": {"coordinates":[2.20896101,41.4103469849],"type":"Point"}
}