{
  "type": "Feature",
  "properties": {
    "iso:country":"ES",
    "sg:address":"Avda Castelao, S/n",
    "sg:city":"Ferrol",
    "sg:orig_category":"Confecci\u00d3n (fabricaci\u00d3n, Al Por Mayor)",
    "sg:phone":"+34 981 32 46 54",
    "sg:postcode":"15406",
    "sg:province":"La Coru\u00f1a",
    "wof:name":"Alvarez Montero Jose Luis",
    "wof:placetype":"venue"
},
  "geometry": {"coordinates":[-8.2048921585,43.4828147888],"type":"Point"}
}