{
  "type": "Feature",
  "properties": {
    "addr:full":"O Marco, S/n Carral Lugo 27372",
    "addr:housenumber":"s / n",
    "addr:postcode":"27372",
    "iso:country":"ES",
    "sg:address":"O Marco, S/n",
    "sg:city":"Carral",
    "sg:orig_category":"Urbanistas",
    "sg:phone":"+34 982 39 00 55",
    "sg:postcode":"27372",
    "sg:province":"Lugo",
    "wof:name":"Sociedad Urbanistica Provincial De Lugo S.l.",
    "wof:placetype":"venue"
},
  "geometry": {"coordinates":[-7.7397837639,43.1718521118],"type":"Point"}
}