{
  "type": "Feature",
  "properties": {
    "addr:full":"Rua Urzaiz, 166 Vigo Pontevedra 36205",
    "addr:housenumber":"166",
    "addr:postcode":"36205",
    "addr:street":"Rua Urzaiz",
    "iso:country":"ES",
    "sg:address":"Rua Urzaiz, 166",
    "sg:city":"Vigo",
    "sg:orig_category":"Bisuter\u00cda, Joyer\u00cda, Relojer\u00cda (al Por Menor)",
    "sg:phone":"+34 986 27 26 94",
    "sg:postcode":"36205",
    "sg:province":"Pontevedra",
    "wof:name":"Castro Fernandez Rocio",
    "wof:placetype":"venue"
},
  "geometry": {"coordinates":[-8.7034931183,42.2309417725],"type":"Point"}
}