{
  "type": "Feature",
  "properties": {
    "addr:full":"Calle de Alcalde Pedro Moreno, 178 Lance Las Palmas 35420",
    "addr:housenumber":"178",
    "addr:postcode":"35420",
    "addr:street":"Calle De Alcalde Pedro Moreno",
    "iso:country":"ES",
    "sg:address":"Calle de Alcalde Pedro Moreno, 178",
    "sg:city":"Lance",
    "sg:orig_category":"Panader\u00cdas, Panader\u00cdas",
    "sg:phone":"+34 928 62 04 99",
    "sg:postcode":"35420",
    "sg:province":"Las Palmas",
    "wof:name":"Ramos Rodriguez Esteban",
    "wof:placetype":"venue"
},
  "geometry": {"coordinates":[-15.5679311752,28.1197452545],"type":"Point"}
}