{
  "type": "Feature",
  "properties": {
    "addr:full":"Rua Augusto Gonzalez Besada, 15 Pontevedra Pontevedra 36001",
    "addr:housenumber":"15",
    "addr:postcode":"36001",
    "addr:street":"Rua Augusto Gonzalez Besada",
    "iso:country":"ES",
    "sg:address":"Rua Augusto Gonzalez Besada, 15",
    "sg:city":"Pontevedra",
    "sg:orig_category":"M\u00c9dicos: Psiquiatr\u00cda",
    "sg:phone":"+34 986 84 56 33",
    "sg:postcode":"36001",
    "sg:province":"Pontevedra",
    "wof:name":"Gomez Calle Angel",
    "wof:placetype":"venue"
},
  "geometry": {"coordinates":[-8.6445684433,42.4287338257],"type":"Point"}
}