{
  "type": "Feature",
  "properties": {
    "iso:country":"ES",
    "sg:address":"Calle de Canalejas, 1",
    "sg:city":"Alacant",
    "sg:orig_category":"Abogados",
    "sg:phone":"+34 965 14 08 14",
    "sg:postcode":"03001",
    "sg:province":"Alicante",
    "wof:name":"Alberola Carrasco Maria Rosa",
    "wof:placetype":"venue"
},
  "geometry": {"coordinates":[-0.4864973128,38.3422164917],"type":"Point"}
}