{
  "type": "Feature",
  "properties": {
    "addr:full":"Granada, S/n Ortuella Vizcaya 48530",
    "addr:housenumber":"/ n",
    "addr:postcode":"48530",
    "addr:street":"Granada S",
    "iso:country":"ES",
    "sg:address":"Granada, S/n",
    "sg:city":"Ortuella",
    "sg:orig_category":"Mec\u00c1nico Del Autom\u00d3vil",
    "sg:phone":"+34 946 35 37 11",
    "sg:postcode":"48530",
    "sg:province":"Vizcaya",
    "wof:name":"Talleres El Gallo S.l.",
    "wof:placetype":"venue"
},
  "geometry": {"coordinates":[-3.0431210995,43.3051986694],"type":"Point"}
}