{
  "type": "Feature",
  "properties": {
    "addr:full":"Calle de Luna, 6 Ontur Albacete 02652",
    "addr:housenumber":"6",
    "addr:postcode":"02652",
    "addr:street":"Calle De Luna",
    "iso:country":"ES",
    "sg:address":"Calle de Luna, 6",
    "sg:city":"Ontur",
    "sg:orig_category":"Confecci\u00d3n (fabricaci\u00d3n, Al Por Mayor)",
    "sg:phone":"+34 967 32 34 30",
    "sg:postcode":"02652",
    "sg:province":"Albacete",
    "wof:name":"Om Manufacturas S.l.u.",
    "wof:placetype":"venue"
},
  "geometry": {"coordinates":[-1.4978849888,38.6162872314],"type":"Point"}
}