{
  "type": "Feature",
  "properties": {
    "addr:full":"Calle de Cadiz (de), 11 Humanes De Madrid Madrid 28970",
    "addr:housenumber":"11",
    "addr:postcode":"28970",
    "addr:street":"Calle De Cadiz De",
    "iso:country":"ES",
    "sg:address":"Calle de Cadiz (de), 11",
    "sg:city":"Humanes De Madrid",
    "sg:orig_category":"Delegados, Agentes De Tr\u00c1nsito, Auxiliares De Transporte Internacional",
    "sg:phone":"+34 916 15 79 27",
    "sg:postcode":"28970",
    "sg:province":"Madrid",
    "wof:name":"Frigorifico Trans Alvi S.l.",
    "wof:placetype":"venue"
},
  "geometry": {"coordinates":[-3.8199806213,40.2759819031],"type":"Point"}
}