{
  "type": "Feature",
  "properties": {
    "addr:full":"Avda Emigrante (del), 16 Playa San Juan Santa Cruz De Tenerife 38687",
    "addr:housenumber":"16",
    "addr:postcode":"38687",
    "addr:street":"Avda Emigrante Del",
    "iso:country":"ES",
    "sg:address":"Avda Emigrante (del), 16",
    "sg:city":"Playa San Juan",
    "sg:orig_category":"Asesor\u00cda De Formaci\u00d3n Y Gesti\u00d3n De Personal",
    "sg:phone":"+34 922 86 68 39",
    "sg:postcode":"38687",
    "sg:province":"Santa Cruz De Tenerife",
    "wof:name":"Juan Morin S.l.",
    "wof:placetype":"venue"
},
  "geometry": {"coordinates":[-16.7886390686,28.1805458069],"type":"Point"}
}