{
  "type": "Feature",
  "properties": {
    "addr:full":"Calle de Almendralejo, 12 Merida Badajoz 06800",
    "addr:housenumber":"12",
    "addr:postcode":"06800",
    "addr:street":"Calle De Almendralejo",
    "iso:country":"ES",
    "sg:address":"Calle de Almendralejo, 12",
    "sg:city":"Merida",
    "sg:orig_category":"Fabricaci\u00d3n, Importaci\u00d3n, Venta De Material De Telefon\u00cda, Peritelefon\u00cda",
    "sg:phone":"+34 924 31 14 58",
    "sg:postcode":"06800",
    "sg:province":"Badajoz",
    "wof:name":"Electrificaciones Delgado S.l.",
    "wof:placetype":"venue"
},
  "geometry": {"coordinates":[-6.3486132622,38.9182891846],"type":"Point"}
}