{
  "type": "Feature",
  "properties": {
    "addr:full":"Ctra Jaen (p I Mirabueno), 110 Torredonjimeno Ja\u00e9n 23650",
    "addr:housenumber":"110",
    "addr:postcode":"23650",
    "addr:street":"Ctra Jaen P;Mirabueno",
    "iso:country":"ES",
    "sg:address":"Ctra Jaen (p I Mirabueno), 110",
    "sg:city":"Torredonjimeno",
    "sg:orig_category":"Agentes, Concesionarios Y Sucursales De Camiones Y Veh\u00cdculos Industriales",
    "sg:phone":"+34 953 57 17 94",
    "sg:postcode":"23650",
    "sg:province":"Ja\u00e9n",
    "wof:name":"Serrano Villar Miguel",
    "wof:placetype":"venue"
},
  "geometry": {"coordinates":[-3.9398329258,37.7626190186],"type":"Point"}
}