{
  "type": "Feature",
  "properties": {
    "addr:full":"Avda Manuel Rivera, 4 Palencia Palencia 34002",
    "addr:housenumber":"4",
    "addr:postcode":"34002",
    "addr:street":"Avda Manuel Rivera",
    "iso:country":"ES",
    "sg:address":"Avda Manuel Rivera, 4",
    "sg:city":"Palencia",
    "sg:orig_category":"Abogados",
    "sg:phone":"+34 979 72 77 45",
    "sg:postcode":"34002",
    "sg:province":"Palencia",
    "wof:name":"Rebollo Rodrigo Jose Maria",
    "wof:placetype":"venue"
},
  "geometry": {"coordinates":[-4.5286169052,42.0091819763],"type":"Point"}
}