{
  "type": "Feature",
  "properties": {
    "iso:country":"ES",
    "sg:address":"Carr Doctor Fleming, 8",
    "sg:city":"Aldaia",
    "sg:orig_category":"Ortopedia General",
    "sg:phone":"+34 961 50 13 05",
    "sg:postcode":"46960",
    "sg:province":"Valencia",
    "sg:website":"www.ortoprono.es",
    "wof:name":"Organizacion De Servicios Ortopedicos S.l.",
    "wof:placetype":"venue"
},
  "geometry": {"coordinates":[-0.4697540104,39.4626350403],"type":"Point"}
}