{
  "type": "Feature",
  "properties": {
    "addr:full":"Calle de Riego, 6 Zamora Zamora 49004",
    "addr:housenumber":"6",
    "addr:postcode":"49004",
    "addr:street":"Calle De Riego",
    "iso:country":"ES",
    "sg:address":"Calle de Riego, 6",
    "sg:city":"Zamora",
    "sg:orig_category":"Cl\u00cdnicas Dentales",
    "sg:phone":"+34 980 53 18 97",
    "sg:postcode":"49004",
    "sg:province":"Zamora",
    "wof:name":"Hernandez Aguado Rafaela",
    "wof:placetype":"venue"
},
  "geometry": {"coordinates":[-5.7454662323,41.505241394],"type":"Point"}
}