{
  "type": "Feature",
  "properties": {
    "addr:full":"Calle de Clara Campoamor, 1 Alcazar S. Juan Ciudad Real 13600",
    "addr:housenumber":"1",
    "addr:postcode":"13600",
    "addr:street":"Calle De Clara Campoamor;Alcazar S. Juan Ciudad Real",
    "iso:country":"ES",
    "sg:address":"Calle de Clara Campoamor, 1",
    "sg:city":"Alcazar S. Juan",
    "sg:orig_category":"Peluquer\u00cdas",
    "sg:phone":"+34 926 55 08 67",
    "sg:postcode":"13600",
    "sg:province":"Ciudad Real",
    "wof:name":"La Pelu Estilistas S.l.",
    "wof:placetype":"venue"
},
  "geometry": {"coordinates":[-3.2197546959,39.3941116333],"type":"Point"}
}