{
  "type": "Feature",
  "properties": {
    "addr:full":"La Vega, 16 Leda\u00f1a Cuenca 16237",
    "addr:housenumber":"16",
    "addr:postcode":"16237",
    "addr:street":"La Vega",
    "iso:country":"ES",
    "sg:address":"La Vega, 16",
    "sg:city":"Leda\u00f1a",
    "sg:orig_category":"Sanatorios M\u00c9dico",
    "sg:phone":"+34 967 49 22 88",
    "sg:postcode":"16237",
    "sg:province":"Cuenca",
    "wof:name":"Ayuntamiento De Leda\u00f1a",
    "wof:placetype":"venue"
},
  "geometry": {"coordinates":[-1.7150770426,39.3575363159],"type":"Point"}
}