{
  "type": "Feature",
  "properties": {
    "iso:country":"ES",
    "sg:address":"Calle de Arroyo Jalon, 6",
    "sg:city":"Bembibre",
    "sg:orig_category":"Reposter\u00cdas",
    "sg:phone":"+34 987 51 03 78",
    "sg:postcode":"24300",
    "sg:province":"Le\u00f3n",
    "wof:name":"Ribeiro Ferreira Ivanca Maria",
    "wof:placetype":"venue"
},
  "geometry": {"coordinates":[-6.4247384071,42.6102371216],"type":"Point"}
}