{
  "type": "Feature",
  "properties": {
    "addr:full":"Calle de Granada, 101 Almeria Almer\u00eda 04008",
    "addr:housenumber":"101",
    "addr:postcode":"04008",
    "addr:street":"Calle De Granada",
    "iso:country":"ES",
    "sg:address":"Calle de Granada, 101",
    "sg:city":"Almeria",
    "sg:orig_category":"Instalaci\u00d3n, Reparaci\u00d3n De Ascensores Y Montacargas",
    "sg:phone":"+34 950 25 98 55",
    "sg:postcode":"04008",
    "sg:province":"Almer\u00eda",
    "wof:name":"A.embarba S.a.",
    "wof:placetype":"venue"
},
  "geometry": {"coordinates":[-2.4601721764,36.8451194763],"type":"Point"}
}