{
  "type": "Feature",
  "properties": {
    "addr:full":"Sio, S/n Cervera Lleida 25200",
    "addr:housenumber":"s / n",
    "addr:postcode":"25200",
    "addr:street":"Sio",
    "iso:country":"ES",
    "sg:address":"Sio, S/n",
    "sg:city":"Cervera",
    "sg:orig_category":"Tubos Y Tuber\u00cdas De Goma Y Pl\u00c1stico (fabricaci\u00d3n, Al Por Mayor)",
    "sg:phone":"+34 973 53 03 58",
    "sg:postcode":"25200",
    "sg:province":"Lleida",
    "wof:name":"Rodi Tr S.l.",
    "wof:placetype":"venue"
},
  "geometry": {"coordinates":[1.2714600563,41.6712989807],"type":"Point"}
}