{
  "type": "Feature",
  "properties": {
    "addr:full":"Barr Sant Pol, 5 Sant Pol Girona 17100",
    "addr:housenumber":"5",
    "addr:postcode":"17100",
    "addr:street":"Sant Pol",
    "iso:country":"ES",
    "sg:address":"Barr Sant Pol, 5",
    "sg:city":"Sant Pol",
    "sg:orig_category":"Artes Gr\u00c1ficas, Artes Pl\u00c1sticas: Material Y Suministros (al Por Menor)",
    "sg:phone":"+34 972 64 31 62",
    "sg:postcode":"17100",
    "sg:province":"Girona",
    "wof:name":"Residencia Geriatrica San Pablo S.l.",
    "wof:placetype":"venue"
},
  "geometry": {"coordinates":[3.0360000134,41.9629936218],"type":"Point"}
}