{
  "type": "Feature",
  "properties": {
    "addr:full":"Pl San Agustin, 5 Estella Navarra 31200",
    "addr:housenumber":"5",
    "addr:postcode":"31200",
    "addr:street":"Pl San Agustin",
    "iso:country":"ES",
    "sg:address":"Pl San Agustin, 5",
    "sg:city":"Estella",
    "sg:orig_category":"Delegados, Agentes De Tr\u00c1nsito, Auxiliares De Transporte Internacional",
    "sg:phone":"+34 948 55 32 63",
    "sg:postcode":"31200",
    "sg:province":"Navarra",
    "wof:name":"Peral Chasco Victor",
    "wof:placetype":"venue"
},
  "geometry": {"coordinates":[-2.0254120827,42.6706085205],"type":"Point"}
}