{
  "type": "Feature",
  "properties": {
    "addr:full":"Avda Regne De Valencia, 34 Valencia Valencia 46005",
    "addr:housenumber":"34",
    "addr:postcode":"46005",
    "addr:street":"Avda Regne De Valencia",
    "iso:country":"ES",
    "sg:address":"Avda Regne De Valencia, 34",
    "sg:city":"Valencia",
    "sg:orig_category":"Perfumer\u00cda (al Por Menor)",
    "sg:phone":"+34 963 33 58 65",
    "sg:postcode":"46005",
    "sg:province":"Valencia",
    "wof:name":"Perfumeria Villanueva C.b.",
    "wof:placetype":"venue"
},
  "geometry": {"coordinates":[-0.3700590134,39.4640846252],"type":"Point"}
}