{
  "type": "Feature",
  "properties": {
    "iso:country":"ES",
    "sg:address":"Industria (pol Ind La Borda), 16",
    "sg:city":"Caldes Montbui",
    "sg:orig_category":"Cajas Y Embalajes De Cart\u00d3n Y Papel",
    "sg:phone":"+34 938 65 33 24",
    "sg:postcode":"08140",
    "sg:province":"Barcelona",
    "wof:name":"Cartonajes Laborda S.l.",
    "wof:placetype":"venue"
},
  "geometry": {"coordinates":[2.1757800579,41.6282310486],"type":"Point"}
}