{
  "type": "Feature",
  "properties": {
    "addr:full":"Carrer de Cardener, 32 Barcelona Barcelona 08024",
    "addr:housenumber":"32",
    "addr:postcode":"08024",
    "addr:street":"Carrer De Cardener",
    "iso:country":"ES",
    "sg:address":"Carrer de Cardener, 32",
    "sg:city":"Barcelona",
    "sg:orig_category":"M\u00c9dicos: Ginecolog\u00cda Y Obstetricia",
    "sg:phone":"+34 932 19 78 36",
    "sg:postcode":"08024",
    "sg:province":"Barcelona",
    "wof:name":"Barbara Gonzalez Josefa De",
    "wof:placetype":"venue"
},
  "geometry": {"coordinates":[2.1554648876,41.409072876],"type":"Point"}
}