{
  "type": "Feature",
  "properties": {
    "iso:country":"ES",
    "sg:address":"Calle de Merindades (las), 5",
    "sg:city":"Castejon",
    "sg:orig_category":"Florister\u00cdas",
    "sg:phone":"+34 948 77 02 82",
    "sg:postcode":"31590",
    "sg:province":"Navarra",
    "wof:name":"Fernandez Ruesga Maria Pilar",
    "wof:placetype":"venue"
},
  "geometry": {"coordinates":[-1.6910979748,42.1712188721],"type":"Point"}
}