{
  "type": "Feature",
  "properties": {
    "iso:country":"ES",
    "sg:address":"Ctra. Avila, Km. 0044,3",
    "sg:city":"Maqueda",
    "sg:orig_category":"Producci\u00d3n, Venta De Productos De Agricultura Biol\u00d3gica",
    "sg:phone":"+34 925 79 00 77",
    "sg:postcode":"45515",
    "sg:province":"Toledo",
    "wof:name":"Ramirez Y Sicilia S. A.",
    "wof:placetype":"venue"
},
  "geometry": {"coordinates":[-4.3719921112,40.0646095276],"type":"Point"}
}