{
  "type": "Feature",
  "properties": {
    "iso:country":"ES",
    "sg:address":"Avda America (de), 3",
    "sg:city":"Cordoba",
    "sg:orig_category":"Aud\u00cdfonos",
    "sg:phone":"+34 957 47 95 86",
    "sg:postcode":"14008",
    "sg:province":"C\u00f3rdoba",
    "wof:name":"Sanitaria Cordobesa S. A.",
    "wof:placetype":"venue"
},
  "geometry": {"coordinates":[-4.7829790115,37.8905906677],"type":"Point"}
}