{
  "type": "Feature",
  "properties": {
    "addr:full":"Tejeria, S/n Sos Del Rey Catolico Zaragoza 50680",
    "addr:housenumber":"s / n",
    "addr:postcode":"50680",
    "addr:street":"Tejeria;Sos",
    "iso:country":"ES",
    "sg:address":"Tejeria, S/n",
    "sg:city":"Sos Del Rey Catolico",
    "sg:orig_category":"Ebanister\u00cda",
    "sg:phone":"+34 948 88 80 47",
    "sg:postcode":"50680",
    "sg:province":"Zaragoza",
    "wof:name":"Iriarte Machin Simon Juan",
    "wof:placetype":"venue"
},
  "geometry": {"coordinates":[-1.2161489725,42.4939804077],"type":"Point"}
}