{
  "type": "Feature",
  "properties": {
    "addr:full":"Avda Portugal, 2 Medina Campo Valladolid 47400",
    "addr:housenumber":"2",
    "addr:postcode":"47400",
    "addr:street":"Avda Portugal",
    "iso:country":"ES",
    "sg:address":"Avda Portugal, 2",
    "sg:city":"Medina Campo",
    "sg:orig_category":"Pintura Y Barniz (al Por Menor)",
    "sg:phone":"+34 983 83 72 38",
    "sg:postcode":"47400",
    "sg:province":"Valladolid",
    "wof:name":"Pinturas Oscar",
    "wof:placetype":"venue"
},
  "geometry": {"coordinates":[-4.9211091995,41.303062439],"type":"Point"}
}