{
  "type": "Feature",
  "properties": {
    "iso:country":"ES",
    "sg:address":"Calle de Emeterio Casta\u00d1os, 11",
    "sg:city":"Madrid",
    "sg:orig_category":"Aparatos De Medida, Control, Regulaci\u00d3n Y Detecci\u00d3n",
    "sg:phone":"+34 913 88 52 50",
    "sg:postcode":"28033",
    "sg:province":"Madrid",
    "wof:name":"Promax Electronica S. A.",
    "wof:placetype":"venue"
},
  "geometry": {"coordinates":[-3.6609089375,40.464389801],"type":"Point"}
}