{
  "type": "Feature",
  "properties": {
    "iso:country":"ES",
    "sg:address":"Rua Alameda San Tome, 31",
    "sg:city":"Cambados",
    "sg:orig_category":"T\u00c9cnicos Veterinarios",
    "sg:phone":"+34 986 54 30 50",
    "sg:postcode":"36630",
    "sg:province":"Pontevedra",
    "wof:name":"Calleja Villaverde Maria Carmen",
    "wof:placetype":"venue"
},
  "geometry": {"coordinates":[-8.8161487579,42.5099105835],"type":"Point"}
}