{
  "type": "Feature",
  "properties": {
    "iso:country":"ES",
    "sg:address":"Carrer de Feixa Llarga, 103",
    "sg:city":"Hospitalet Llobregat",
    "sg:orig_category":"Venta, Instalaci\u00d3n De Quemadores",
    "sg:phone":"+34 932 63 43 31",
    "sg:postcode":"08907",
    "sg:province":"Barcelona",
    "wof:name":"Productos Y Servicios Para La Combustion S.l.",
    "wof:placetype":"venue"
},
  "geometry": {"coordinates":[2.0997591019,41.3477134705],"type":"Point"}
}