{
  "type": "Feature",
  "properties": {
    "iso:country":"ES",
    "sg:address":"Carrer de Muralla, 32",
    "sg:city":"Vendrell",
    "sg:orig_category":"Inmobiliaria (agencias)",
    "sg:phone":"+34 977 66 73 17",
    "sg:postcode":"43700",
    "sg:province":"Tarragona",
    "wof:name":"Mar-marsal S.l.",
    "wof:placetype":"venue"
},
  "geometry": {"coordinates":[1.5343960524,41.2209968567],"type":"Point"}
}