{
  "type": "Feature",
  "properties": {
    "addr:full":"Avda Constitucion, 346 Valencia Valencia 46019",
    "addr:housenumber":"346",
    "addr:postcode":"46019",
    "addr:street":"Avda Constitucion",
    "iso:country":"ES",
    "sg:address":"Avda Constitucion, 346",
    "sg:city":"Valencia",
    "sg:orig_category":"Sociedades, Compa\u00d1\u00cdas Aseguradoras",
    "sg:phone":"+34 961 86 90 60",
    "sg:postcode":"46019",
    "sg:province":"Valencia",
    "wof:name":"Secure Valencia S.l.",
    "wof:placetype":"venue"
},
  "geometry": {"coordinates":[-0.3681620061,39.5028800964],"type":"Point"}
}