{
  "type": "Feature",
  "properties": {
    "addr:full":"Avda Orovilla, 14 Madrid Madrid 28041",
    "addr:housenumber":"14",
    "addr:postcode":"madrid;28041",
    "addr:street":"Avda Orovilla",
    "iso:country":"ES",
    "sg:address":"Avda Orovilla, 14",
    "sg:city":"Madrid",
    "sg:orig_category":"Pintura, Barniz, Productos Asimilables (fabricaci\u00d3n, Al Por Mayor)",
    "sg:phone":"+34 916 15 54 44",
    "sg:postcode":"28041",
    "sg:province":"Madrid",
    "wof:name":"Dupont Performance Coatings Iberica S.l.",
    "wof:placetype":"venue"
},
  "geometry": {"coordinates":[-3.6927769184,40.3665008545],"type":"Point"}
}