{
  "type": "Feature",
  "properties": {
    "iso:country":"ES",
    "sg:address":"Carr Fra Vicent Nicolau, 6",
    "sg:city":"Eivissa",
    "sg:orig_category":"Caf\u00c9s, Bares, Cervecer\u00cdas",
    "sg:phone":"+34 971 19 94 53",
    "sg:postcode":"07800",
    "sg:province":"Islas Baleares",
    "wof:name":"Can Friends, S.l.",
    "wof:placetype":"venue"
},
  "geometry": {"coordinates":[1.429164052,38.9110565186],"type":"Point"}
}