{
  "type": "Feature",
  "properties": {
    "addr:full":"Hirigoien Kalea, 18 Lazkao Guip\u00f9zcoa 20210",
    "addr:housenumber":"18",
    "addr:postcode":"20210",
    "addr:street":"Hirigoien Kalea;Guipu\u0300Zcoa",
    "iso:country":"ES",
    "sg:address":"Hirigoien Kalea, 18",
    "sg:city":"Lazkao",
    "sg:orig_category":"Pescader\u00cdas (al Por Menor)",
    "sg:phone":"+34 943 88 51 71",
    "sg:postcode":"20210",
    "sg:province":"Guip\u00f9zcoa",
    "wof:name":"Soraluce Lete Jose Maria",
    "wof:placetype":"venue"
},
  "geometry": {"coordinates":[-2.1854829788,43.0314941406],"type":"Point"}
}