{
  "type": "Feature",
  "properties": {
    "iso:country":"ES",
    "sg:address":"Calle de Libreros, 15",
    "sg:city":"Alcala Henares",
    "sg:orig_category":"Ropa Para Se\u00d1oras (al Por Menor)",
    "sg:phone":"+34 918 78 86 14",
    "sg:postcode":"28801",
    "sg:province":"Madrid",
    "wof:name":"Lobaton Martinez Maria De Los Angeles",
    "wof:placetype":"venue"
},
  "geometry": {"coordinates":[-3.3634250164,40.4840927124],"type":"Point"}
}