{
  "type": "Feature",
  "properties": {
    "iso:country":"ES",
    "sg:address":"Pg Gracia, 19",
    "sg:city":"Barcelona",
    "sg:orig_category":"Ropa Para Ni\u00d1os (al Por Menor)",
    "sg:phone":"+34 934 45 83 60",
    "sg:postcode":"08007",
    "sg:province":"Barcelona",
    "sg:website":"www.diesel.com",
    "wof:name":"Diesel Iberia S.a.",
    "wof:placetype":"venue"
},
  "geometry": {"coordinates":[2.1670060158,41.3900337219],"type":"Point"}
}