{
  "type": "Feature",
  "properties": {
    "addr:full":"Calle de Telletxe, 15 Getxo Vizcaya 48990",
    "addr:housenumber":"15",
    "addr:postcode":"48990",
    "addr:street":"Calle De Telletxe",
    "iso:country":"ES",
    "sg:address":"Calle de Telletxe, 15",
    "sg:city":"Getxo",
    "sg:orig_category":"M\u00c9dicos: Medicina General Orientada A La Homeopat\u00cda",
    "sg:phone":"+34 944 91 21 37",
    "sg:postcode":"48990",
    "sg:province":"Vizcaya",
    "wof:name":"Virginia Olaizola Arzak",
    "wof:placetype":"venue"
},
  "geometry": {"coordinates":[-3.0106210709,43.3531112671],"type":"Point"}
}