{
  "type": "Feature",
  "properties": {
    "iso:country":"ES",
    "sg:address":"Ctra Miraflores Guadalix, Km. 0000,9",
    "sg:city":"Miraflores De La Sierra",
    "sg:orig_category":"Artes Gr\u00c1ficas, Artes Pl\u00c1sticas: Material Y Suministros (al Por Menor)",
    "sg:phone":"+34 918 44 50 50",
    "sg:postcode":"28792",
    "sg:province":"Madrid",
    "wof:name":"Tecdix S.l.",
    "wof:placetype":"venue"
},
  "geometry": {"coordinates":[-3.7532949448,40.7972793579],"type":"Point"}
}