{
  "type": "Feature",
  "properties": {
    "addr:full":"Psj. Los Arcos, 7 S. Clemente Cuenca 16600",
    "addr:housenumber":"7",
    "addr:postcode":"16600",
    "addr:street":"Los Arcos;S. Clemente Cuenca",
    "iso:country":"ES",
    "sg:address":"Psj. Los Arcos, 7",
    "sg:city":"S. Clemente",
    "sg:orig_category":"Peluqueros: De Se\u00d1oras",
    "sg:phone":"+34 969 30 03 93",
    "sg:postcode":"16600",
    "sg:province":"Cuenca",
    "wof:name":"Ortega Torrecilla Maria Isabel",
    "wof:placetype":"venue"
},
  "geometry": {"coordinates":[-2.4270188808,39.3993186951],"type":"Point"}
}