{
  "type": "Feature",
  "properties": {
    "addr:full":"Carrer de Prevere R Barrera, 19 Palma Islas Baleares 07005",
    "addr:housenumber":"19",
    "addr:postcode":"07005",
    "addr:street":"Carrer De;R Barrera",
    "iso:country":"ES",
    "sg:address":"Carrer de Prevere R Barrera, 19",
    "sg:city":"Palma",
    "sg:orig_category":"Electricidad: Instaladores",
    "sg:phone":"+34 971 24 60 50",
    "sg:postcode":"07005",
    "sg:province":"Islas Baleares",
    "wof:name":"Electro Cano Costa Reparaciones E Instalaciones Electricas S.l.",
    "wof:placetype":"venue"
},
  "geometry": {"coordinates":[2.6681001186,39.5841941833],"type":"Point"}
}