{
  "type": "Feature",
  "properties": {
    "addr:full":"Carr Joan Maragall, 31 Girona Girona 17002",
    "addr:housenumber":"31",
    "addr:postcode":"17002",
    "addr:street":"Carr Joan Maragall",
    "iso:country":"ES",
    "sg:address":"Carr Joan Maragall, 31",
    "sg:city":"Girona",
    "sg:orig_category":"M\u00c9dicos: Otorrinolaringolog\u00cda",
    "sg:phone":"+34 972 21 54 13",
    "sg:postcode":"17002",
    "sg:province":"Girona",
    "wof:name":"Liern Caballero Manuel Salvador",
    "wof:placetype":"venue"
},
  "geometry": {"coordinates":[2.820305109,41.9779663086],"type":"Point"}
}