{
  "type": "Feature",
  "properties": {
    "addr:full":"Rua Carreira Do Conde (da), 20 Santiago De Compostela A Coru\u00f1a 15706",
    "addr:housenumber":"20",
    "addr:postcode":"15706",
    "addr:street":"Rua Carreira Do Conde Da;Corun\u0303A",
    "iso:country":"ES",
    "sg:address":"Rua Carreira Do Conde (da), 20",
    "sg:city":"Santiago De Compostela",
    "sg:orig_category":"Agencias De Viajes",
    "sg:phone":"+34 981 57 62 21",
    "sg:postcode":"15706",
    "sg:province":"A Coru\u00f1a",
    "sg:website":"www.halconviajes.com",
    "wof:name":"Viajes Halcon S.a.",
    "wof:placetype":"venue"
},
  "geometry": {"coordinates":[-8.5484333038,42.8758049011],"type":"Point"}
}