{
  "type": "Feature",
  "properties": {
    "iso:country":"ES",
    "sg:address":"Calle de San Juan De Letran, 3",
    "sg:city":"Granada",
    "sg:orig_category":"Doctores En Medicina",
    "sg:phone":"+34 958 28 99 01",
    "sg:postcode":"18012",
    "sg:province":"Granada",
    "wof:name":"Tamayo Lopez Miguel Angel",
    "wof:placetype":"venue"
},
  "geometry": {"coordinates":[-3.607460022,37.186000824],"type":"Point"}
}