{
  "type": "Feature",
  "properties": {
    "iso:country":"ES",
    "sg:address":"Carr Ramon I Cajal, 30",
    "sg:city":"Cabanes",
    "sg:orig_category":"Bancos",
    "sg:phone":"+34 964 33 12 33",
    "sg:postcode":"12180",
    "sg:province":"Castell\u00f3n",
    "wof:name":"Banco Espa\u00f1ol De Credito S.a.",
    "wof:placetype":"venue"
},
  "geometry": {"coordinates":[0.044222001,40.156211853],"type":"Point"}
}