{
  "type": "Feature",
  "properties": {
    "iso:country":"ES",
    "sg:address":"Calle de Tellez, 18",
    "sg:city":"Madrid",
    "sg:orig_category":"Cobro De Pr\u00c9stamos",
    "sg:phone":"+34 915 01 61 00",
    "sg:postcode":"28007",
    "sg:province":"Madrid",
    "wof:name":"Hermanos Alonso Polo S.l.",
    "wof:placetype":"venue"
},
  "geometry": {"coordinates":[-3.6803920269,40.40259552],"type":"Point"}
}