{
  "type": "Feature",
  "properties": {
    "iso:country":"ES",
    "sg:address":"Pla\u00c7 Cal Font, 3",
    "sg:city":"Igualada",
    "sg:orig_category":"Peluqueros: De Se\u00d1oras",
    "sg:phone":"+34 938 04 93 85",
    "sg:postcode":"08700",
    "sg:province":"Barcelona",
    "wof:name":"Ester Cases Maria Merce",
    "wof:placetype":"venue"
},
  "geometry": {"coordinates":[1.6164000034,41.5813026428],"type":"Point"}
}