{
  "type": "Feature",
  "properties": {
    "addr:full":"Calle de Inessa De Gaxen, 2 Donostia-san Sebastian Guip\u00f9zcoa 20018",
    "addr:housenumber":"2",
    "addr:postcode":"20018",
    "addr:street":"Calle De Inessa;Gaxen",
    "iso:country":"ES",
    "sg:address":"Calle de Inessa De Gaxen, 2",
    "sg:city":"Donostia-san Sebastian",
    "sg:orig_category":"Bazares, Art\u00cdculos De Limpieza Y De Cocina (al Por Menor)",
    "sg:phone":"+34 943 21 32 76",
    "sg:postcode":"20018",
    "sg:province":"Guip\u00f9zcoa",
    "wof:name":"Amc Espa\u00d1a Alfa Metalcraft Corp. S.a.",
    "wof:placetype":"venue"
},
  "geometry": {"coordinates":[-2.0061352253,43.3015670776],"type":"Point"}
}