{
  "type": "Feature",
  "properties": {
    "addr:full":"Carrer de Barcelona, 198 Sant Vicen\u00c7 Dels Horts Barcelona 08620",
    "addr:housenumber":"198",
    "addr:postcode":"08620",
    "addr:street":"Carrer De Barcelona;Sant Vicenc\u0327 Dels Horts Barcelona",
    "iso:country":"ES",
    "sg:address":"Carrer de Barcelona, 198",
    "sg:city":"Sant Vicen\u00c7 Dels Horts",
    "sg:orig_category":"Flores Y Plantas Naturales (al Por Mayor)",
    "sg:phone":"+34 936 76 94 33",
    "sg:postcode":"08620",
    "sg:province":"Barcelona",
    "wof:name":"Casasampere Bosch Nuria",
    "wof:placetype":"venue"
},
  "geometry": {"coordinates":[2.0086779594,41.397819519],"type":"Point"}
}