{
  "type": "Feature",
  "properties": {
    "iso:country":"ES",
    "sg:address":"Calle de Fernando Sanchez Sampedro, 9",
    "sg:city":"Badajoz",
    "sg:orig_category":"Cl\u00cdnicas Dentales",
    "sg:phone":"+34 924 22 34 62",
    "sg:postcode":"06003",
    "sg:province":"Badajoz",
    "wof:name":"Sanchez-castilla Saez Nicolas",
    "wof:placetype":"venue"
},
  "geometry": {"coordinates":[-6.9691047668,38.8730926514],"type":"Point"}
}