{
  "type": "Feature",
  "properties": {
    "addr:full":"Carrer de Senieta L'auelet, 26 Castalla Alicante 03420",
    "addr:housenumber":"26",
    "addr:postcode":"03420",
    "addr:street":"Carrer De Senieta L'Auelet",
    "iso:country":"ES",
    "sg:address":"Carrer de Senieta L'auelet, 26",
    "sg:city":"Castalla",
    "sg:orig_category":"Electricidad: Instaladores",
    "sg:phone":"+34 965 56 07 87",
    "sg:postcode":"03420",
    "sg:province":"Alicante",
    "wof:name":"Beneyto Dura Hermenegildo",
    "wof:placetype":"venue"
},
  "geometry": {"coordinates":[-0.6737939715,38.5920143127],"type":"Point"}
}