{
  "type": "Feature",
  "properties": {
    "iso:country":"ES",
    "sg:address":"Calle de Carlos Martin Alvarez, 76",
    "sg:city":"Madrid",
    "sg:orig_category":"Molduras, Junquillos, Listones Y Molduras Perforadas",
    "sg:phone":"+34 914 78 24 90",
    "sg:postcode":"28018",
    "sg:province":"Madrid",
    "wof:name":"Gonzalez Carujo Gerardo",
    "wof:placetype":"venue"
},
  "geometry": {"coordinates":[-3.6655628681,40.3868331909],"type":"Point"}
}