{
  "type": "Feature",
  "properties": {
    "addr:full":"Carrer de Padilla, 284 Barcelona Barcelona 08025",
    "addr:housenumber":"284",
    "addr:postcode":"08025",
    "addr:street":"Carrer De Padilla",
    "iso:country":"ES",
    "sg:address":"Carrer de Padilla, 284",
    "sg:city":"Barcelona",
    "sg:orig_category":"Artes Gr\u00c1ficas, Artes Pl\u00c1sticas: Material Y Suministros (al Por Menor)",
    "sg:phone":"+34 934 36 99 17",
    "sg:postcode":"08025",
    "sg:province":"Barcelona",
    "wof:name":"Herrera Solsona Ana",
    "wof:placetype":"venue"
},
  "geometry": {"coordinates":[2.1751589775,41.407459259],"type":"Point"}
}