{
  "type": "Feature",
  "properties": {
    "addr:full":"Plaz Ruperto Chapi, 6 Alacant Alicante 03001",
    "addr:housenumber":"6",
    "addr:postcode":"03001",
    "addr:street":"Chapi",
    "iso:country":"ES",
    "sg:address":"Plaz Ruperto Chapi, 6",
    "sg:city":"Alacant",
    "sg:orig_category":"Abogados",
    "sg:phone":"+34 965 21 67 86",
    "sg:postcode":"03001",
    "sg:province":"Alicante",
    "wof:name":"Gonzalez Trujillo Augusto",
    "wof:placetype":"venue"
},
  "geometry": {"coordinates":[-0.4855501056,38.3460426331],"type":"Point"}
}