{
  "type": "Feature",
  "properties": {
    "iso:country":"ES",
    "sg:address":"Plaz Conde De Cabra (del), S/n",
    "sg:city":"Cabra",
    "sg:orig_category":"Internados & Ense\u00d1anza Privada",
    "sg:phone":"+34 957 52 01 11",
    "sg:postcode":"14940",
    "sg:province":"C\u00f3rdoba",
    "wof:name":"Madres Escolapias",
    "wof:placetype":"venue"
},
  "geometry": {"coordinates":[-4.4467329979,37.4711227417],"type":"Point"}
}