{
  "type": "Feature",
  "properties": {
    "iso:country":"ES",
    "sg:address":"Calle de Pintor Sorolla, 8",
    "sg:city":"Logro\u00f1o",
    "sg:orig_category":"Arquitectos",
    "sg:phone":"+34 941 51 01 78",
    "sg:postcode":"26007",
    "sg:province":"La Rioja",
    "wof:name":"Curiel Marcos Luis Javier",
    "wof:placetype":"venue"
},
  "geometry": {"coordinates":[-2.4587020874,42.4578437805],"type":"Point"}
}