{
  "type": "Feature",
  "properties": {
    "iso:country":"ES",
    "sg:address":"Calle de Carteya, 15",
    "sg:city":"Linea De La Concepcion",
    "sg:orig_category":"Muebles, Minoristas",
    "sg:phone":"+34 956 17 56 21",
    "sg:postcode":"11300",
    "sg:province":"C\u00e1diz",
    "wof:name":"Rubiales Moreno Maria Del Mar",
    "wof:placetype":"venue"
},
  "geometry": {"coordinates":[-5.3509168625,36.1635093689],"type":"Point"}
}