{
  "type": "Feature",
  "properties": {
    "iso:country":"ES",
    "sg:address":"Calle de San Pelayo, 9",
    "sg:city":"Cangas Onis",
    "sg:orig_category":"Bisuteros (fabricaci\u00d3n, Al Por Mayor)",
    "sg:phone":"+34 985 94 75 67",
    "sg:postcode":"33550",
    "sg:province":"Asturias",
    "wof:name":"Eduardo Y Adrian Joyeros S.l.",
    "wof:placetype":"venue"
},
  "geometry": {"coordinates":[-5.1289777756,43.3497238159],"type":"Point"}
}