{
  "type": "Feature",
  "properties": {
    "iso:country":"ES",
    "sg:address":"Calle de Mota Del Cuervo, 68",
    "sg:city":"Madrid",
    "sg:orig_category":"Empresas De Carpinter\u00cda De Madera",
    "sg:phone":"+34 913 88 99 34",
    "sg:postcode":"28043",
    "sg:province":"Madrid",
    "wof:name":"Alder, S.l.",
    "wof:placetype":"venue"
},
  "geometry": {"coordinates":[-3.6314871311,40.4649238586],"type":"Point"}
}