{
  "type": "Feature",
  "properties": {
    "addr:full":"Calle de Colon, 38 Castellon Castell\u00f3n 12001",
    "addr:housenumber":"38",
    "addr:postcode":"12001",
    "addr:street":"Calle De Colon",
    "iso:country":"ES",
    "sg:address":"Calle de Colon, 38",
    "sg:city":"Castellon",
    "sg:orig_category":"Bisuter\u00cda, Joyer\u00cda, Relojer\u00cda (al Por Menor)",
    "sg:phone":"+34 964 23 06 64",
    "sg:postcode":"12001",
    "sg:province":"Castell\u00f3n",
    "wof:name":"Joyeria Paco-2 Cdad.",
    "wof:placetype":"venue"
},
  "geometry": {"coordinates":[-0.0383522995,39.9867286682],"type":"Point"}
}