{
  "type": "Feature",
  "properties": {
    "iso:country":"ES",
    "sg:address":"Calle de Gallo, 7",
    "sg:city":"Valladolid",
    "sg:orig_category":"Carnicer\u00cdas, Carnicer\u00cdas",
    "sg:phone":"+34 983 39 56 64",
    "sg:postcode":"47012",
    "sg:province":"Valladolid",
    "wof:name":"Gomez Zu\u00f1iga Miguel Angel",
    "wof:placetype":"venue"
},
  "geometry": {"coordinates":[-4.7090349197,41.6461105347],"type":"Point"}
}