{
  "type": "Feature",
  "properties": {
    "iso:country":"ES",
    "sg:address":"Ctra Pamplona, S/n",
    "sg:city":"Villafranca",
    "sg:orig_category":"Producci\u00d3n, Comercio De Cereales",
    "sg:phone":"+34 948 84 51 40",
    "sg:postcode":"31330",
    "sg:province":"Navarra",
    "wof:name":"Arrondo Malo Angel",
    "wof:placetype":"venue"
},
  "geometry": {"coordinates":[-1.7445235252,42.281375885],"type":"Point"}
}