{
  "type": "Feature",
  "properties": {
    "iso:country":"ES",
    "sg:address":"Avda Estacion (la), 3",
    "sg:city":"Alacant",
    "sg:orig_category":"Promotores Constructores",
    "sg:phone":"+34 965 14 61 75",
    "sg:postcode":"03003",
    "sg:province":"Alicante",
    "wof:name":"Oleza Urbana S.l.",
    "wof:placetype":"venue"
},
  "geometry": {"coordinates":[-0.4913829863,38.3456344604],"type":"Point"}
}