{
  "type": "Feature",
  "properties": {
    "iso:country":"ES",
    "sg:address":"Calle de Julio Romero De Torres, 16",
    "sg:city":"Carlota",
    "sg:orig_category":"Enfermeras: Consultas, Atenci\u00d3n A Domicilio",
    "sg:phone":"+34 957 30 03 15",
    "sg:postcode":"14100",
    "sg:province":"C\u00f3rdoba",
    "wof:name":"Garrido Galvez Diego",
    "wof:placetype":"venue"
},
  "geometry": {"coordinates":[-4.930975914,37.6729660034],"type":"Point"}
}