{
  "type": "Feature",
  "properties": {
    "iso:country":"ES",
    "sg:address":"Plaza De La Iglesia, 5",
    "sg:city":"Sta. Magdalena Pulpis",
    "sg:orig_category":"Iglesia Cat\u00d3lica",
    "sg:phone":"+34 964 41 50 71",
    "sg:postcode":"12597",
    "sg:province":"Castell\u00f3n",
    "wof:name":"Parroquia Santa Magdalena",
    "wof:placetype":"venue"
},
  "geometry": {"coordinates":[0.302846998,40.3559379578],"type":"Point"}
}