{
  "type": "Feature",
  "properties": {
    "addr:full":"Santakurtz Kalea, 24 Aretxabaleta Guip\u00f9zcoa 20550",
    "addr:housenumber":"24",
    "addr:postcode":"20550",
    "addr:street":"Santakurtz Kalea;Guipu\u0300Zcoa",
    "iso:country":"ES",
    "sg:address":"Santakurtz Kalea, 24",
    "sg:city":"Aretxabaleta",
    "sg:orig_category":"Quiropr\u00c1cticos",
    "sg:phone":"+34 943 77 04 34",
    "sg:postcode":"20550",
    "sg:province":"Guip\u00f9zcoa",
    "wof:name":"Manteca Sebastian Mirian",
    "wof:placetype":"venue"
},
  "geometry": {"coordinates":[-2.5031559467,43.0348052979],"type":"Point"}
}