{
  "type": "Feature",
  "properties": {
    "iso:country":"ES",
    "sg:address":"Carr Independencia, 42",
    "sg:city":"Burjassot",
    "sg:orig_category":"Instalaci\u00d3n, Reparaci\u00d3n De Calefacci\u00d3n El\u00c9ctrica",
    "sg:phone":"+34 963 64 58 91",
    "sg:postcode":"46100",
    "sg:province":"Valencia",
    "wof:name":"Acliman S.l.",
    "wof:placetype":"venue"
},
  "geometry": {"coordinates":[-0.4153389931,39.5086250305],"type":"Point"}
}