{
  "type": "Feature",
  "properties": {
    "iso:country":"ES",
    "sg:address":"Calle de Concepcion, 22",
    "sg:city":"Almonte",
    "sg:orig_category":"Asesor\u00cda Sobre Comunicaci\u00d3n De Empresas",
    "sg:phone":"+34 959 40 62 02",
    "sg:postcode":"21730",
    "sg:province":"Huelva",
    "wof:name":"Acofi S.l.",
    "wof:placetype":"venue"
},
  "geometry": {"coordinates":[-6.5192136765,37.2614135742],"type":"Point"}
}