{
  "type": "Feature",
  "properties": {
    "iso:country":"ES",
    "sg:address":"Calle de Avila, 6",
    "sg:city":"Bilbao",
    "sg:orig_category":"Masajistas Kinesiterapeutas",
    "sg:phone":"+34 944 10 08 10",
    "sg:postcode":"48012",
    "sg:province":"Vizcaya",
    "wof:name":"Egana Construcciones Y Reformas S.l.",
    "wof:placetype":"venue"
},
  "geometry": {"coordinates":[-2.9395577908,43.2569580078],"type":"Point"}
}