{
  "type": "Feature",
  "properties": {
    "addr:full":"Calle de Consolacion, S/n Carpio Valladolid 47470",
    "addr:housenumber":"s / n",
    "addr:postcode":"47470",
    "addr:street":"Calle De Consolacion",
    "iso:country":"ES",
    "sg:address":"Calle de Consolacion, S/n",
    "sg:city":"Carpio",
    "sg:orig_category":"Granos Y Semillas (producci\u00d3n, Al Por Mayor)",
    "sg:phone":"+34 983 86 35 80",
    "sg:postcode":"47470",
    "sg:province":"Valladolid",
    "wof:name":"Mundisemillas S.a.",
    "wof:placetype":"venue"
},
  "geometry": {"coordinates":[-5.1061220169,41.2133140564],"type":"Point"}
}