{
  "type": "Feature",
  "properties": {
    "iso:country":"ES",
    "sg:address":"Rond San Pedro, S/n",
    "sg:city":"Villaluenga Sagra",
    "sg:orig_category":"Bazares, Art\u00cdculos De Limpieza Y De Cocina (al Por Menor)",
    "sg:phone":"+34 925 53 02 20",
    "sg:postcode":"45520",
    "sg:province":"Toledo",
    "wof:name":"Garcia Garcia Josefa",
    "wof:placetype":"venue"
},
  "geometry": {"coordinates":[-3.9098680019,40.0303573608],"type":"Point"}
}