{
  "type": "Feature",
  "properties": {
    "addr:full":"Carrer de Mestre Joan Corrales, 59 Esplugues Llobregat Barcelona 08950",
    "addr:housenumber":"59",
    "addr:postcode":"08950",
    "addr:street":"Carrer De Mestre Joan Corrales",
    "iso:country":"ES",
    "sg:address":"Carrer de Mestre Joan Corrales, 59",
    "sg:city":"Esplugues Llobregat",
    "sg:orig_category":"Asociaciones, Organismos Culturales Y Socioeducativos",
    "sg:phone":"+34 933 71 55 81",
    "sg:postcode":"08950",
    "sg:province":"Barcelona",
    "wof:name":"Fundacio Viure I Conviure",
    "wof:placetype":"venue"
},
  "geometry": {"coordinates":[2.0875480175,41.3726882935],"type":"Point"}
}