{
  "type": "Feature",
  "properties": {
    "addr:full":"Calle de Magnetita, 2 Guijo Madrid 28260",
    "addr:housenumber":"2",
    "addr:postcode":"28260",
    "addr:street":"Calle De Magnetita",
    "iso:country":"ES",
    "sg:address":"Calle de Magnetita, 2",
    "sg:city":"Guijo",
    "sg:orig_category":"Ayuda En Tareas Dom\u00c9sticas, Ayuda A Domicilio",
    "sg:phone":"+34 918 58 83 08",
    "sg:postcode":"28260",
    "sg:province":"Madrid",
    "wof:name":"Mayo Lamelas Carlos",
    "wof:placetype":"venue"
},
  "geometry": {"coordinates":[-4.0284838676,40.609085083],"type":"Point"}
}