{
  "type": "Feature",
  "properties": {
    "iso:country":"ES",
    "sg:address":"Calle de Marte, 54",
    "sg:city":"Zaragoza",
    "sg:orig_category":"Par\u00cds",
    "sg:phone":"+34 976 75 34 68",
    "sg:postcode":"50012",
    "sg:province":"Zaragoza",
    "wof:name":"Garcia Casado Maria Encarnacion",
    "wof:placetype":"venue"
},
  "geometry": {"coordinates":[-0.9324849844,41.6386680603],"type":"Point"}
}