{
  "type": "Feature",
  "properties": {
    "iso:country":"ES",
    "sg:address":"Calle de Escuderos, 6",
    "sg:city":"Segovia",
    "sg:orig_category":"Carnicer\u00cdas, Carnicer\u00cdas",
    "sg:phone":"+34 921 46 09 52",
    "sg:postcode":"40001",
    "sg:province":"Segovia",
    "wof:name":"Suarez Garcia Marcelo",
    "wof:placetype":"venue"
},
  "geometry": {"coordinates":[-4.124607563,40.9505615234],"type":"Point"}
}