{
  "type": "Feature",
  "properties": {
    "addr:full":"Mercat Sant Antoni, 40 Barcelona Barcelona 08015",
    "addr:housenumber":"40",
    "addr:postcode":"08015",
    "addr:street":"Antoni",
    "iso:country":"ES",
    "sg:address":"Mercat Sant Antoni, 40",
    "sg:city":"Barcelona",
    "sg:orig_category":"Ropa Para Se\u00d1oras (al Por Menor)",
    "sg:phone":"+34 934 25 57 51",
    "sg:postcode":"08015",
    "sg:province":"Barcelona",
    "wof:name":"Bonastre Catalan Maria Carmen",
    "wof:placetype":"venue"
},
  "geometry": {"coordinates":[2.1634581089,41.380645752],"type":"Point"}
}