{
  "type": "Feature",
  "properties": {
    "iso:country":"ES",
    "sg:address":"Kale Barria, 32",
    "sg:city":"O\u00f1ati",
    "sg:orig_category":"\u00d3ptica: Instrumentos (fabricaci\u00d3n)",
    "sg:phone":"+34 943 71 82 88",
    "sg:postcode":"20560",
    "sg:province":"Guip\u00f9zcoa",
    "wof:name":"Altuna Madina Itziar",
    "wof:placetype":"venue"
},
  "geometry": {"coordinates":[-2.4108119011,43.0315628052],"type":"Point"}
}