{
  "type": "Feature",
  "properties": {
    "addr:full":"Avda Pintor Felo Monzon, 24 Palmas De Gran Canaria Las Palmas 35019",
    "addr:housenumber":"24",
    "addr:postcode":"35019",
    "addr:street":"Avda Pintor Felo Monzon",
    "iso:country":"ES",
    "sg:address":"Avda Pintor Felo Monzon, 24",
    "sg:city":"Palmas De Gran Canaria",
    "sg:orig_category":"M\u00c9dicos: An\u00c1lisis Cl\u00cdnicos",
    "sg:phone":"+34 928 42 77 95",
    "sg:postcode":"35019",
    "sg:province":"Las Palmas",
    "wof:name":"Alberto Sanchez Montesdeoca S.l.",
    "wof:placetype":"venue"
},
  "geometry": {"coordinates":[-15.4540748596,28.0999279022],"type":"Point"}
}