{
  "type": "Feature",
  "properties": {
    "iso:country":"ES",
    "sg:address":"Avda Costa Blanca, 148",
    "sg:city":"Alacant",
    "sg:orig_category":"Inmobiliaria (agencias)",
    "sg:phone":"+34 965 16 32 12",
    "sg:postcode":"03540",
    "sg:province":"Alicante",
    "wof:name":"Huidobro Bustamante Jaime",
    "wof:placetype":"venue"
},
  "geometry": {"coordinates":[-0.411736995,38.3713378906],"type":"Point"}
}