{
  "type": "Feature",
  "properties": {
    "iso:country":"ES",
    "sg:address":"Carrer de Lluis Marti, 10",
    "sg:city":"Palma",
    "sg:orig_category":"Confecci\u00d3n De Uniformes",
    "sg:phone":"+34 971 77 73 50",
    "sg:postcode":"07006",
    "sg:province":"Islas Baleares",
    "wof:name":"Uniformes P.g.m. S.l.",
    "wof:placetype":"venue"
},
  "geometry": {"coordinates":[2.6584599018,39.5720710754],"type":"Point"}
}