{
  "type": "Feature",
  "properties": {
    "iso:country":"ES",
    "sg:address":"Rua Rio Arnoia, 18",
    "sg:city":"Xinzo De Limia",
    "sg:orig_category":"Barnizadores",
    "sg:phone":"+34 988 46 07 07",
    "sg:postcode":"32630",
    "sg:province":"Ourense",
    "wof:name":"Garcia Roman Francisco",
    "wof:placetype":"venue"
},
  "geometry": {"coordinates":[-7.7267990112,42.06016922],"type":"Point"}
}