{
  "type": "Feature",
  "properties": {
    "iso:country":"ES",
    "sg:address":"Plaz San Francisco, 12",
    "sg:city":"Le\u00f3n",
    "sg:orig_category":"Peluqueros: De Se\u00d1oras",
    "sg:phone":"+34 987 21 59 63",
    "sg:postcode":"24004",
    "sg:province":"Le\u00f3n",
    "wof:name":"Maria Visitacion Alvarez Garcia Y Otra Cdad",
    "wof:placetype":"venue"
},
  "geometry": {"coordinates":[-5.5701918602,42.5937805176],"type":"Point"}
}