{
  "type": "Feature",
  "properties": {
    "addr:full":"Carrer de Ignasi Iglesias, 9 Barcelona Barcelona 08030",
    "addr:housenumber":"9",
    "addr:postcode":"08030",
    "addr:street":"Carrer De Ignasi Iglesias",
    "iso:country":"ES",
    "sg:address":"Carrer de Ignasi Iglesias, 9",
    "sg:city":"Barcelona",
    "sg:orig_category":"Comercio, Reparaci\u00d3n De Motocicletas, Bicicletas Y Piezas Sueltas",
    "sg:phone":"+34 933 45 05 67",
    "sg:postcode":"08030",
    "sg:province":"Barcelona",
    "wof:name":"Talleres Roca Mora S.c.p.",
    "wof:placetype":"venue"
},
  "geometry": {"coordinates":[2.1888899803,41.4333724976],"type":"Point"}
}