{
  "type": "Feature",
  "properties": {
    "iso:country":"ES",
    "sg:address":"Calle de Isla De La Gomera, 23",
    "sg:city":"Santa Cruz De Tenerife",
    "sg:orig_category":"Asesor\u00cda Fiscal Y Jur\u00cddica",
    "sg:phone":"+34 922 27 79 26",
    "sg:postcode":"38006",
    "sg:province":"Santa Cruz De Tenerife",
    "wof:name":"Blasco Y Garaboto S.l.",
    "wof:placetype":"venue"
},
  "geometry": {"coordinates":[-16.2639083862,28.4688644409],"type":"Point"}
}