{
  "type": "Feature",
  "properties": {
    "iso:country":"ES",
    "sg:address":"Calle de Hermanos Gambra, 2",
    "sg:city":"Zaragoza",
    "sg:orig_category":"Muebles, Minoristas",
    "sg:phone":"+34 976 33 85 25",
    "sg:postcode":"50017",
    "sg:province":"Zaragoza",
    "wof:name":"Muebles Velarte S.l.",
    "wof:placetype":"venue"
},
  "geometry": {"coordinates":[-0.9093750119,41.6493682861],"type":"Point"}
}