{
  "type": "Feature",
  "properties": {
    "iso:country":"ES",
    "sg:address":"Calle de Galeon, 36",
    "sg:city":"Madrid",
    "sg:orig_category":"Sociedades, Compa\u00d1\u00cdas Aseguradoras",
    "sg:phone":"+34 917 47 65 04",
    "sg:postcode":"28042",
    "sg:province":"Madrid",
    "wof:name":"Tellez Sancho Alejandro",
    "wof:placetype":"venue"
},
  "geometry": {"coordinates":[-3.5858991146,40.4555282593],"type":"Point"}
}