{
  "type": "Feature",
  "properties": {
    "addr:full":"Carrer de Sol (del), 11 S. Andreu Barca Barcelona 08740",
    "addr:housenumber":"11",
    "addr:postcode":"08740",
    "addr:street":"Carrer De Sol Del;S. Andreu;Barcelona",
    "iso:country":"ES",
    "sg:address":"Carrer de Sol (del), 11",
    "sg:city":"S. Andreu Barca",
    "sg:orig_category":"Comercio, Reparaci\u00d3n De Bicicletas, De Motocicletas, De Accesorios",
    "sg:phone":"+34 936 82 34 37",
    "sg:postcode":"08740",
    "sg:province":"Barcelona",
    "wof:name":"O.m.bicis S.c.p",
    "wof:placetype":"venue"
},
  "geometry": {"coordinates":[1.9733580351,41.4493331909],"type":"Point"}
}