{
  "type": "Feature",
  "properties": {
    "addr:full":"Calle de Lila, 15 Oviedo Asturias 33002",
    "addr:housenumber":"15",
    "addr:postcode":"33002",
    "addr:street":"Calle De Lila",
    "iso:country":"ES",
    "sg:address":"Calle de Lila, 15",
    "sg:city":"Oviedo",
    "sg:orig_category":"Arquitectos",
    "sg:phone":"+34 985 21 32 88",
    "sg:postcode":"33002",
    "sg:province":"Asturias",
    "wof:name":"Fidalgo Vazquez Fernando",
    "wof:placetype":"venue"
},
  "geometry": {"coordinates":[-5.8476929665,43.3658828735],"type":"Point"}
}