{
  "type": "Feature",
  "properties": {
    "iso:country":"ES",
    "sg:address":"Calle de Nu\u00d1ez De Balboa, 2",
    "sg:city":"Alcala",
    "sg:orig_category":"Mercer\u00cda, Lencer\u00cda (al Por Menor)",
    "sg:phone":"+34 922 86 54 83",
    "sg:postcode":"38686",
    "sg:province":"Santa Cruz De Tenerife",
    "wof:name":"Gonzalez Barreto Maria Teresa",
    "wof:placetype":"venue"
},
  "geometry": {"coordinates":[-16.8278236389,28.2028083801],"type":"Point"}
}