{
  "type": "Feature",
  "properties": {
    "iso:country":"ES",
    "sg:address":"Estacio, 2",
    "sg:city":"Blanes",
    "sg:orig_category":"M\u00c9dicos: Estomatolog\u00cda",
    "sg:phone":"+34 972 33 08 15",
    "sg:postcode":"17300",
    "sg:province":"Girona",
    "wof:name":"Falco Rodrigo Guillermo-alejandro",
    "wof:placetype":"venue"
},
  "geometry": {"coordinates":[2.7710940838,41.6794013977],"type":"Point"}
}