{
  "type": "Feature",
  "properties": {
    "iso:country":"ES",
    "sg:address":"Ventana, S/n",
    "sg:city":"San Emiliano",
    "sg:orig_category":"Albergues",
    "sg:phone":"+34 987 59 41 50",
    "sg:postcode":"24144",
    "sg:province":"Le\u00f3n",
    "wof:name":"Hostal Valle De San Emiliano S.l.",
    "wof:placetype":"venue"
},
  "geometry": {"coordinates":[-6.0007376671,42.9719696045],"type":"Point"}
}