{
  "type": "Feature",
  "properties": {
    "iso:country":"ES",
    "sg:address":"Cami Cabanes, 88",
    "sg:city":"Javea",
    "sg:orig_category":"Aguas (distribuci\u00d3n, Servicios)",
    "sg:phone":"+34 965 79 01 62",
    "sg:postcode":"03730",
    "sg:province":"Alicante",
    "wof:name":"Aguas Municipales De Javea S.a.",
    "wof:placetype":"venue"
},
  "geometry": {"coordinates":[0.1853525043,38.7651443481],"type":"Point"}
}