{
  "type": "Feature",
  "properties": {
    "addr:full":"Carrer de Valencia, 452 Barcelona Barcelona 08013",
    "addr:housenumber":"452",
    "addr:postcode":"08013",
    "addr:street":"Carrer De Valencia",
    "iso:country":"ES",
    "sg:address":"Carrer de Valencia, 452",
    "sg:city":"Barcelona",
    "sg:orig_category":"Prendas Y Chalecos De Punto (al Por Menor)",
    "sg:phone":"+34 932 45 33 95",
    "sg:postcode":"08013",
    "sg:province":"Barcelona",
    "wof:name":"Queralt Baguena Juan",
    "wof:placetype":"venue"
},
  "geometry": {"coordinates":[2.1770849228,41.40284729],"type":"Point"}
}