{
  "type": "Feature",
  "properties": {
    "iso:country":"ES",
    "sg:address":"Calle de Real, 20",
    "sg:city":"Navas San Juan",
    "sg:orig_category":"Molduras, Junquillos, Listones Y Molduras Perforadas",
    "sg:phone":"+34 953 68 72 46",
    "sg:postcode":"23240",
    "sg:province":"Ja\u00e9n",
    "wof:name":"Pelaez Garrido Felix",
    "wof:placetype":"venue"
},
  "geometry": {"coordinates":[-3.3163399696,38.1847343445],"type":"Point"}
}