{
  "type": "Feature",
  "properties": {
    "addr:full":"Calle de Niebla, 11 Huelva Huelva 21007",
    "addr:housenumber":"11",
    "addr:postcode":"21007",
    "addr:street":"Calle De Niebla",
    "iso:country":"ES",
    "sg:address":"Calle de Niebla, 11",
    "sg:city":"Huelva",
    "sg:classifiers":[
        {
            "category":"Casinos & Gambling",
            "type":"Entertainment"
        }
    ],
    "sg:phone":"+34 959 22 31 18",
    "sg:postcode":"21007",
    "sg:province":"Huelva",
    "sg:tags":[
        "locale",
        "de",
        "juego"
    ],
    "wof:name":"Sociedad Onubense De Servicios S.a.",
    "wof:placetype":"venue"
},
  "geometry": {"coordinates":[-6.934679985,37.2569198608],"type":"Point"}
}