{
  "type": "Feature",
  "properties": {
    "addr:full":"Carr Ignasi Iglesias, 19 Badalona Barcelona 08912",
    "addr:housenumber":"19",
    "addr:postcode":"08912",
    "addr:street":"Carr Ignasi Iglesias",
    "iso:country":"ES",
    "sg:address":"Carr Ignasi Iglesias, 19",
    "sg:city":"Badalona",
    "sg:orig_category":"Mec\u00c1nico Del Autom\u00d3vil",
    "sg:phone":"+34 933 89 14 98",
    "sg:postcode":"08912",
    "sg:province":"Barcelona",
    "wof:name":"El Mecanic Del Centre S.c.p.",
    "wof:placetype":"venue"
},
  "geometry": {"coordinates":[2.2394599915,41.4451293945],"type":"Point"}
}