{
  "type": "Feature",
  "properties": {
    "iso:country":"ES",
    "sg:address":"Avda Compromiso De Caspe, 67",
    "sg:city":"Zaragoza",
    "sg:orig_category":"Ropa Para Se\u00d1oras (al Por Menor)",
    "sg:phone":"+34 976 42 67 26",
    "sg:postcode":"50002",
    "sg:province":"Zaragoza",
    "wof:name":"Tovar Acebo Isabel",
    "wof:placetype":"venue"
},
  "geometry": {"coordinates":[-0.8660079837,41.6457519531],"type":"Point"}
}