{
  "type": "Feature",
  "properties": {
    "iso:country":"ES",
    "sg:address":"Calle de Balsas, 9",
    "sg:city":"Santa Eulalia",
    "sg:orig_category":"Encuadernaci\u00d3n E Impresi\u00d3n De Folletos",
    "sg:phone":"+34 968 21 31 00",
    "sg:postcode":"30001",
    "sg:province":"Murcia",
    "wof:name":"Linares Garcia Carlos",
    "wof:placetype":"venue"
},
  "geometry": {"coordinates":[-1.5738861561,37.7936096191],"type":"Point"}
}