{
  "type": "Feature",
  "properties": {
    "iso:country":"ES",
    "sg:address":"La Vi\u00f1a, 17",
    "sg:city":"Aldeanueva Ebro",
    "sg:orig_category":"Electricidad: Instaladores",
    "sg:phone":"+34 941 16 33 78",
    "sg:postcode":"26559",
    "sg:province":"La Rioja",
    "wof:name":"Nalfer Electricidad S.l.l.",
    "wof:placetype":"venue"
},
  "geometry": {"coordinates":[-1.8907790184,42.2265586853],"type":"Point"}
}