{
  "type": "Feature",
  "properties": {
    "iso:country":"ES",
    "sg:address":"Calle de Picatres (de), 12",
    "sg:city":"Alcobendas",
    "sg:orig_category":"Trabajos De Soldaduras",
    "sg:phone":"+34 916 54 56 84",
    "sg:postcode":"28100",
    "sg:province":"Madrid",
    "wof:name":"Pechon 95 S.l.",
    "wof:placetype":"venue"
},
  "geometry": {"coordinates":[-3.6311450005,40.5398864746],"type":"Point"}
}