{
  "type": "Feature",
  "properties": {
    "iso:country":"ES",
    "sg:address":"Carrer de Doctor Marti I Julia, 84",
    "sg:city":"Hospitalet Llobregat",
    "sg:classifiers":[
        {
            "category":"Personal",
            "subcategory":"Barber",
            "type":"Services"
        }
    ],
    "sg:phone":"+34 934 48 12 30",
    "sg:postcode":"08903",
    "sg:province":"Barcelona",
    "sg:tags":[
        "caballeros",
        "de",
        "peluqueros"
    ],
    "wof:name":"Lopez Diaz Felix",
    "wof:placetype":"venue"
},
  "geometry": {"coordinates":[2.123267889,41.3727684021],"type":"Point"}
}