{
  "type": "Feature",
  "properties": {
    "addr:full":"C/ Sant Mateu, De, 6 S. Antoni Portmany Islas Baleares 07820",
    "addr:postcode":"07820",
    "addr:street":"C / Sant Mateu De 6 S. Antoni Portmany",
    "iso:country":"ES",
    "sg:address":"C/ Sant Mateu, De, 6",
    "sg:city":"S. Antoni Portmany",
    "sg:orig_category":"Ropa Para Se\u00d1oras (al Por Menor)",
    "sg:phone":"+34 971 34 44 16",
    "sg:postcode":"07820",
    "sg:province":"Islas Baleares",
    "wof:name":"Costa Torres Jose",
    "wof:placetype":"venue"
},
  "geometry": {"coordinates":[1.5188339949,39.1094055176],"type":"Point"}
}