{
  "type": "Feature",
  "properties": {
    "iso:country":"ES",
    "sg:address":"Pl Porta Sta Catalina, 1",
    "sg:city":"Palma",
    "sg:orig_category":"Molduras, Junquillos, Listones Y Molduras Perforadas",
    "sg:phone":"+34 971 71 18 96",
    "sg:postcode":"07012",
    "sg:province":"Islas Baleares",
    "wof:name":"Martinez Fernandez Felipe",
    "wof:placetype":"venue"
},
  "geometry": {"coordinates":[2.6428179741,39.5706329346],"type":"Point"}
}