{
  "type": "Feature",
  "properties": {
    "iso:country":"ES",
    "sg:address":"Calle de Duque De Ahumada, 11",
    "sg:city":"Roquetas Mar",
    "sg:orig_category":"Servicios De Telecomunicaciones",
    "sg:phone":"+34 950 32 89 02",
    "sg:postcode":"04740",
    "sg:province":"Almer\u00eda",
    "wof:name":"Indalo Bazar S.l.",
    "wof:placetype":"venue"
},
  "geometry": {"coordinates":[-2.6151049137,36.7633666992],"type":"Point"}
}