{
  "type": "Feature",
  "properties": {
    "addr:full":"Ctra Merida, Km. 0558,0 Caceres C\u00e1ceres 10005",
    "addr:postcode":"10005",
    "addr:street":"Ctra Merida Km. 0558,0;Ca\u0301Ceres",
    "iso:country":"ES",
    "sg:address":"Ctra Merida, Km. 0558,0",
    "sg:city":"Caceres",
    "sg:orig_category":"Lavado, Limpieza De Veh\u00cdculos",
    "sg:phone":"+34 927 23 65 39",
    "sg:postcode":"10005",
    "sg:province":"C\u00e1ceres",
    "wof:name":"Valles Camps Jose Angel",
    "wof:placetype":"venue"
},
  "geometry": {"coordinates":[-6.3847317696,39.4618148804],"type":"Point"}
}