{
  "type": "Feature",
  "properties": {
    "iso:country":"ES",
    "sg:address":"La Aldea, Km. 0000,0",
    "sg:city":"Valverde Virgen",
    "sg:orig_category":"Vinos Y Licores (venta Al Por Menor)",
    "sg:phone":"+34 987 30 32 64",
    "sg:postcode":"24391",
    "sg:province":"Le\u00f3n",
    "wof:name":"Sanchez Garcia Agustin",
    "wof:placetype":"venue"
},
  "geometry": {"coordinates":[-5.6244401932,42.5436477661],"type":"Point"}
}