{
  "type": "Feature",
  "properties": {
    "addr:full":"Carrer de L'encarnacio, 180 Barcelona Barcelona 08025",
    "addr:housenumber":"180",
    "addr:postcode":"08025",
    "addr:street":"Carrer De L'Encarnacio",
    "iso:country":"ES",
    "sg:address":"Carrer de L'encarnacio, 180",
    "sg:city":"Barcelona",
    "sg:orig_category":"Confecci\u00d3n : Material, Suministros Y Accesorios",
    "sg:phone":"+34 934 33 48 60",
    "sg:postcode":"08025",
    "sg:province":"Barcelona",
    "wof:name":"Jcpv Perchas Y Hombreras S.l.",
    "wof:placetype":"venue"
},
  "geometry": {"coordinates":[2.1663076878,41.4102745056],"type":"Point"}
}