{
  "type": "Feature",
  "properties": {
    "iso:country":"ES",
    "sg:address":"Calle de Doctor Dauden, 4",
    "sg:city":"Chinchilla Monte-aragon",
    "sg:orig_category":"Asociaciones, Organismos Culturales Y Socioeducativos",
    "sg:phone":"+34 967 26 00 51",
    "sg:postcode":"02520",
    "sg:province":"Albacete",
    "wof:name":"Aderfor",
    "wof:placetype":"venue"
},
  "geometry": {"coordinates":[-1.7248868942,38.9198379517],"type":"Point"}
}