{
  "type": "Feature",
  "properties": {
    "addr:full":"Calle de Infanta Mercedes, 31 Madrid Madrid 28020",
    "addr:housenumber":"31",
    "addr:postcode":"madrid;28020",
    "addr:street":"Calle De Infanta Mercedes",
    "iso:country":"ES",
    "sg:address":"Calle de Infanta Mercedes, 31",
    "sg:city":"Madrid",
    "sg:orig_category":"Artes Gr\u00c1ficas, Artes Pl\u00c1sticas (curso)",
    "sg:phone":"+34 915 79 66 48",
    "sg:postcode":"28020",
    "sg:province":"Madrid",
    "wof:name":"Herza Ivc S.l.",
    "wof:placetype":"venue"
},
  "geometry": {"coordinates":[-3.6989729404,40.4548225403],"type":"Point"}
}