{
  "type": "Feature",
  "properties": {
    "iso:country":"ES",
    "sg:address":"Carr Serra De Garrafa, 8",
    "sg:city":"Port D'andratx",
    "sg:orig_category":"Metales (labores, Pulido)",
    "sg:phone":"+34 971 67 19 13",
    "sg:postcode":"07157",
    "sg:province":"Islas Baleares",
    "wof:name":"Manner Metal A. S.",
    "wof:placetype":"venue"
},
  "geometry": {"coordinates":[2.3764240742,39.5468864441],"type":"Point"}
}