{
  "type": "Feature",
  "properties": {
    "addr:full":"Avda Castilla, 56 Cheste Valencia 46380",
    "addr:housenumber":"56",
    "addr:postcode":"46380",
    "addr:street":"Avda Castilla",
    "iso:country":"ES",
    "sg:address":"Avda Castilla, 56",
    "sg:city":"Cheste",
    "sg:orig_category":"T\u00c9cnicos Veterinarios",
    "sg:phone":"+34 962 51 24 49",
    "sg:postcode":"46380",
    "sg:province":"Valencia",
    "wof:name":"Consultorio Veterinario Cheste S.l",
    "wof:placetype":"venue"
},
  "geometry": {"coordinates":[-0.6816740036,39.4926757812],"type":"Point"}
}