{
  "type": "Feature",
  "properties": {
    "iso:country":"ES",
    "sg:address":"Ptge Forn, 6",
    "sg:city":"Igualada",
    "sg:orig_category":"Centros Comerciales Y Grandes Tiendas",
    "sg:phone":"+34 938 05 46 82",
    "sg:postcode":"08700",
    "sg:province":"Barcelona",
    "wof:name":"Guma Serarols Maria Rosa",
    "wof:placetype":"venue"
},
  "geometry": {"coordinates":[1.6170699596,41.5795402527],"type":"Point"}
}