{
  "type": "Feature",
  "properties": {
    "iso:country":"ES",
    "sg:address":"Avda Moya (de), 6",
    "sg:city":"San Fernando",
    "sg:orig_category":"Centros De Coordinaci\u00d3n",
    "sg:phone":"+34 928 77 90 58",
    "sg:postcode":"35100",
    "sg:province":"Las Palmas",
    "wof:name":"Martin Ojeda Abian",
    "wof:placetype":"venue"
},
  "geometry": {"coordinates":[-15.5842504501,28.0904903412],"type":"Point"}
}