{
  "type": "Feature",
  "properties": {
    "addr:full":"Calle de Navarro Rodrigo, 11 Almeria Almer\u00eda 04001",
    "addr:housenumber":"11",
    "addr:postcode":"04001",
    "addr:street":"Calle De Navarro Rodrigo",
    "iso:country":"ES",
    "sg:address":"Calle de Navarro Rodrigo, 11",
    "sg:city":"Almeria",
    "sg:orig_category":"Ropa Para Se\u00d1oras (al Por Menor)",
    "sg:phone":"+34 950 23 64 58",
    "sg:postcode":"04001",
    "sg:province":"Almer\u00eda",
    "wof:name":"Lara Martinez Antonio",
    "wof:placetype":"venue"
},
  "geometry": {"coordinates":[-2.462749958,36.8395004272],"type":"Point"}
}