{
  "type": "Feature",
  "properties": {
    "addr:full":"Carr Canigo, 11 Badalona Barcelona 08912",
    "addr:housenumber":"11",
    "addr:postcode":"08912",
    "addr:street":"Carr Canigo",
    "iso:country":"ES",
    "sg:address":"Carr Canigo, 11",
    "sg:city":"Badalona",
    "sg:orig_category":"Equipos De Marcado, Etiquetado",
    "sg:phone":"+34 933 87 77 11",
    "sg:postcode":"08912",
    "sg:province":"Barcelona",
    "wof:name":"Monzon Garcia Luis",
    "wof:placetype":"venue"
},
  "geometry": {"coordinates":[2.2357618809,41.4469184875],"type":"Point"}
}