{
  "type": "Feature",
  "properties": {
    "addr:full":"Pg Doctor Moragas, 244 Barbera Valles Barcelona 08210",
    "addr:housenumber":"244",
    "addr:postcode":"08210",
    "addr:street":"Pg Doctor Moragas",
    "iso:country":"ES",
    "sg:address":"Pg Doctor Moragas, 244",
    "sg:city":"Barbera Valles",
    "sg:orig_category":"Zapatos (al Por Menor)",
    "sg:phone":"+34 937 29 54 91",
    "sg:postcode":"08210",
    "sg:province":"Barcelona",
    "wof:name":"Shoes Gestion S.a.",
    "wof:placetype":"venue"
},
  "geometry": {"coordinates":[2.1236670017,41.5171165466],"type":"Point"}
}