{
  "type": "Feature",
  "properties": {
    "addr:full":"Avda Industria (de La), 12 Molina Segura Murcia 30500",
    "addr:housenumber":"12",
    "addr:postcode":"30500",
    "addr:street":"Avda Industria De La",
    "iso:country":"ES",
    "sg:address":"Avda Industria (de La), 12",
    "sg:city":"Molina Segura",
    "sg:orig_category":"Peleter\u00cdas",
    "sg:phone":"+34 968 64 17 22",
    "sg:postcode":"30500",
    "sg:province":"Murcia",
    "wof:name":"Giorgio Pavanello S.l.",
    "wof:placetype":"venue"
},
  "geometry": {"coordinates":[-1.2096710205,38.0466346741],"type":"Point"}
}