{
  "type": "Feature",
  "properties": {
    "addr:full":"Calle de D. Jose Lastiesas, S/n Sabi\u00f1anigo Huesca 22600",
    "addr:housenumber":"s / n",
    "addr:postcode":"22600",
    "addr:street":"Calle De D. Jose Lastiesas",
    "iso:country":"ES",
    "sg:address":"Calle de D. Jose Lastiesas, S/n",
    "sg:city":"Sabi\u00f1anigo",
    "sg:orig_category":"Materiales De Construcci\u00d3n (en General)",
    "sg:phone":"+34 974 48 34 30",
    "sg:postcode":"22600",
    "sg:province":"Huesca",
    "wof:name":"Pavimentos Y Revestimientos Julve S.l.",
    "wof:placetype":"venue"
},
  "geometry": {"coordinates":[-0.3582144976,42.523891449],"type":"Point"}
}