{
  "type": "Feature",
  "properties": {
    "addr:full":"Calle de Estrella De Elola, 11 Valdemoro Madrid 28340",
    "addr:housenumber":"11",
    "addr:postcode":"28340",
    "addr:street":"Calle De Estrella De Elola",
    "iso:country":"ES",
    "sg:address":"Calle de Estrella De Elola, 11",
    "sg:city":"Valdemoro",
    "sg:orig_category":"Asesor\u00cda Fiscal Y Jur\u00cddica",
    "sg:phone":"+34 918 95 55 21",
    "sg:postcode":"28340",
    "sg:province":"Madrid",
    "wof:name":"Marti Garcia Maria Josefa",
    "wof:placetype":"venue"
},
  "geometry": {"coordinates":[-3.6783568859,40.1918983459],"type":"Point"}
}