{
  "type": "Feature",
  "properties": {
    "addr:full":"Carrer de Aneto, 38 Rubi Barcelona 08191",
    "addr:housenumber":"38",
    "addr:postcode":"08191",
    "addr:street":"Carrer De Aneto",
    "iso:country":"ES",
    "sg:address":"Carrer de Aneto, 38",
    "sg:city":"Rubi",
    "sg:orig_category":"Molduras, Junquillos, Listones Y Molduras Perforadas",
    "sg:phone":"+34 936 99 10 02",
    "sg:postcode":"08191",
    "sg:province":"Barcelona",
    "wof:name":"Cordoba Gimenez Francisco",
    "wof:placetype":"venue"
},
  "geometry": {"coordinates":[2.0061221123,41.4952468872],"type":"Point"}
}