{
  "type": "Feature",
  "properties": {
    "iso:country":"ES",
    "sg:address":"Barr Puente (el), 12",
    "sg:city":"Puente",
    "sg:orig_category":"Art\u00cdculos De Limpieza Y De Cocina (fabricaci\u00d3n, Al Por Mayor)",
    "sg:phone":"+34 942 87 79 04",
    "sg:postcode":"39788",
    "sg:province":"Cantabria",
    "sg:website":"www.systemfiltration.com",
    "wof:name":"Ch Sistemas De Reciclaje S.l",
    "wof:placetype":"venue"
},
  "geometry": {"coordinates":[-3.3257288933,43.3466300964],"type":"Point"}
}