{
  "type": "Feature",
  "properties": {
    "iso:country":"ES",
    "sg:address":"Pase Martires Los, 120",
    "sg:city":"Tamaraceite",
    "sg:orig_category":"Centros Empresariales",
    "sg:phone":"+34 928 67 11 93",
    "sg:postcode":"35018",
    "sg:province":"Las Palmas",
    "wof:name":"Melian Baez Olga Maria",
    "wof:placetype":"venue"
},
  "geometry": {"coordinates":[-15.4784650803,28.0919818878],"type":"Point"}
}