{
  "type": "Feature",
  "properties": {
    "addr:full":"Rbla Sant Sebastia, 33 Santa Coloma De Gramenet Barcelona 08921",
    "addr:housenumber":"33",
    "addr:postcode":"08921",
    "addr:street":"Rbla Sant Sebastia",
    "iso:country":"ES",
    "sg:address":"Rbla Sant Sebastia, 33",
    "sg:city":"Santa Coloma De Gramenet",
    "sg:orig_category":"Bancos",
    "sg:phone":"+34 934 66 56 26",
    "sg:postcode":"08921",
    "sg:province":"Barcelona",
    "sg:website":"www.ebankinter.com",
    "wof:name":"Bankinter S.a.",
    "wof:placetype":"venue"
},
  "geometry": {"coordinates":[2.2121798992,41.4506607056],"type":"Point"}
}