{
  "type": "Feature",
  "properties": {
    "addr:full":"Calle de Padre Jofre, 15 Valencia Valencia 46007",
    "addr:housenumber":"15",
    "addr:postcode":"46007",
    "addr:street":"Calle De Padre Jofre",
    "iso:country":"ES",
    "sg:address":"Calle de Padre Jofre, 15",
    "sg:city":"Valencia",
    "sg:orig_category":"Arquitectos",
    "sg:phone":"+34 963 94 44 26",
    "sg:postcode":"46007",
    "sg:province":"Valencia",
    "sg:website":"www.arquitectos-arg.com",
    "wof:name":"Arquitectura Rehabilitacion Y Gestion S.l.",
    "wof:placetype":"venue"
},
  "geometry": {"coordinates":[-0.3818272948,39.4678688049],"type":"Point"}
}