{
  "type": "Feature",
  "properties": {
    "iso:country":"ES",
    "sg:address":"Avda Andalucia (de), 2",
    "sg:city":"Paracuellos De Jarama",
    "sg:orig_category":"Quincaller\u00cda (al Por Menor)",
    "sg:phone":"+34 916 58 19 15",
    "sg:postcode":"28860",
    "sg:province":"Madrid",
    "wof:name":"Gonzalez Perea Suministros S.l.",
    "wof:placetype":"venue"
},
  "geometry": {"coordinates":[-3.5279259682,40.5052680969],"type":"Point"}
}