{
  "type": "Feature",
  "properties": {
    "addr:full":"Calle de Poeta Vicente Aleixandre, 23 S. Roque C\u00e1diz 11360",
    "addr:housenumber":"23",
    "addr:postcode":"11360",
    "addr:street":"Calle De Poeta Vicente Aleixandre;S. Roque Ca\u0301Diz",
    "iso:country":"ES",
    "sg:address":"Calle de Poeta Vicente Aleixandre, 23",
    "sg:city":"S. Roque",
    "sg:orig_category":"Papeler\u00cdas, Librer\u00cdas",
    "sg:phone":"+34 956 78 18 84",
    "sg:postcode":"11360",
    "sg:province":"C\u00e1diz",
    "wof:name":"Serrano Correro Catalina",
    "wof:placetype":"venue"
},
  "geometry": {"coordinates":[-5.3857879639,36.2135620117],"type":"Point"}
}