{
  "type": "Feature",
  "properties": {
    "iso:country":"ES",
    "sg:address":"Luga Autovia 92, Km. 0292,0",
    "sg:city":"Guadix",
    "sg:orig_category":"Promotores Constructores",
    "sg:phone":"+34 958 66 14 33",
    "sg:postcode":"18500",
    "sg:province":"Granada",
    "wof:name":"Andaluza Ferrovial Ute",
    "wof:placetype":"venue"
},
  "geometry": {"coordinates":[-3.0776567459,37.4068832397],"type":"Point"}
}