{
  "type": "Feature",
  "properties": {
    "addr:full":"Calle de Unica, S/n Fanlo Huesca 22375",
    "addr:housenumber":"s / n",
    "addr:postcode":"22375",
    "addr:street":"Calle De Unica",
    "iso:country":"ES",
    "sg:address":"Calle de Unica, S/n",
    "sg:city":"Fanlo",
    "sg:orig_category":"Empresas De Carpinter\u00cda De Madera",
    "sg:phone":"+34 974 48 90 12",
    "sg:postcode":"22375",
    "sg:province":"Huesca",
    "wof:name":"Lorente Lasala Luis",
    "wof:placetype":"venue"
},
  "geometry": {"coordinates":[-0.0217719991,42.587688446],"type":"Point"}
}