{
  "type": "Feature",
  "properties": {
    "addr:full":"Pase Ramon Y Cajal, 24 Huesca Huesca 22001",
    "addr:housenumber":"24",
    "addr:postcode":"22001",
    "addr:street":"Ramon Y Cajal",
    "iso:country":"ES",
    "sg:address":"Pase Ramon Y Cajal, 24",
    "sg:city":"Huesca",
    "sg:orig_category":"Cueros Y Pieles (al Por Mayor)",
    "sg:phone":"+34 974 22 38 96",
    "sg:postcode":"22001",
    "sg:province":"Huesca",
    "wof:name":"Gregorio Reine Pieles Y Lanas S.l.",
    "wof:placetype":"venue"
},
  "geometry": {"coordinates":[-0.4023869932,42.1392707825],"type":"Point"}
}