{
  "type": "Feature",
  "properties": {
    "addr:full":"Calle de Rabida, 12 Huelva Huelva 21001",
    "addr:housenumber":"12",
    "addr:postcode":"21001",
    "addr:street":"Calle De Rabida",
    "iso:country":"ES",
    "sg:address":"Calle de Rabida, 12",
    "sg:city":"Huelva",
    "sg:orig_category":"Complementos De Vestir (al Por Menor)",
    "sg:phone":"+34 959 25 04 29",
    "sg:postcode":"21001",
    "sg:province":"Huelva",
    "wof:name":"Rabida Doce S.l",
    "wof:placetype":"venue"
},
  "geometry": {"coordinates":[-6.9510931969,37.2556648254],"type":"Point"}
}