{
  "type": "Feature",
  "properties": {
    "iso:country":"ES",
    "sg:address":"Ctra Madrid-cadiz, Km. 0622,0",
    "sg:city":"Jerez De La Frontera",
    "sg:orig_category":"Producci\u00d3n, Venta De Productos De Agricultura Biol\u00d3gica",
    "sg:phone":"+34 956 23 72 50",
    "sg:postcode":"11407",
    "sg:province":"C\u00e1diz",
    "wof:name":"Distribuciones Luis Caballero S.a.",
    "wof:placetype":"venue"
},
  "geometry": {"coordinates":[-6.1128687859,36.7094726562],"type":"Point"}
}