{
  "type": "Feature",
  "properties": {
    "iso:country":"ES",
    "sg:address":"Avda Langreo, 52",
    "sg:city":"Nore\u00f1a",
    "sg:orig_category":"Suministros Para Carrocer\u00cdas",
    "sg:phone":"+34 985 74 22 36",
    "sg:postcode":"33180",
    "sg:province":"Asturias",
    "wof:name":"Garcia Rodriguez Wenceslao Manuel",
    "wof:placetype":"venue"
},
  "geometry": {"coordinates":[-5.7019271851,43.3864517212],"type":"Point"}
}