{
  "type": "Feature",
  "properties": {
    "addr:full":"Av. Albufera, 39 Sedavi Valencia 46910",
    "addr:housenumber":"39",
    "addr:postcode":"46910",
    "addr:street":"Av. Albufera",
    "iso:country":"ES",
    "sg:address":"Av. Albufera, 39",
    "sg:city":"Sedavi",
    "sg:orig_category":"Peluqueros: De Se\u00d1oras",
    "sg:phone":"+34 963 76 57 40",
    "sg:postcode":"46910",
    "sg:province":"Valencia",
    "wof:name":"Gabinete Victoria S.l.",
    "wof:placetype":"venue"
},
  "geometry": {"coordinates":[-0.3816620111,39.422416687],"type":"Point"}
}