{
  "type": "Feature",
  "properties": {
    "addr:full":"Calle de Real, 16 Ceuta Ceuta 51001",
    "addr:housenumber":"16",
    "addr:postcode":"51001",
    "addr:street":"Calle De Real",
    "iso:country":"ES",
    "sg:address":"Calle de Real, 16",
    "sg:city":"Ceuta",
    "sg:orig_category":"Alquiler De V\u00cddeo",
    "sg:phone":"+34 956 51 62 50",
    "sg:postcode":"51001",
    "sg:province":"Ceuta",
    "wof:name":"Mata Rivas Luis",
    "wof:placetype":"venue"
},
  "geometry": {"coordinates":[-5.307226181,35.8873519897],"type":"Point"}
}