{
  "type": "Feature",
  "properties": {
    "addr:full":"Los Partidores, 22 Ca\u00f1ada San Urbano Almer\u00eda 04120",
    "addr:housenumber":"22",
    "addr:postcode":"04120",
    "addr:street":"Los Partidores;San;Almeri\u0301A",
    "iso:country":"ES",
    "sg:address":"Los Partidores, 22",
    "sg:city":"Ca\u00f1ada San Urbano",
    "sg:orig_category":"Alimentaci\u00d3n General (al Por Mayor)",
    "sg:phone":"+34 950 29 14 20",
    "sg:postcode":"04120",
    "sg:province":"Almer\u00eda",
    "wof:name":"Ramon Sanchez Antonio",
    "wof:placetype":"venue"
},
  "geometry": {"coordinates":[-2.389688015,36.8369255066],"type":"Point"}
}