{
  "type": "Feature",
  "properties": {
    "addr:full":"Avda Almogavares (de), 36 Cordoba C\u00f3rdoba 14006",
    "addr:housenumber":"36",
    "addr:postcode":"14006",
    "addr:street":"Avda Almogavares De;Co\u0301Rdoba",
    "iso:country":"ES",
    "sg:address":"Avda Almogavares (de), 36",
    "sg:city":"Cordoba",
    "sg:orig_category":"Cl\u00cdnicas M\u00c9dicas",
    "sg:phone":"+34 957 28 05 05",
    "sg:postcode":"14006",
    "sg:province":"C\u00f3rdoba",
    "wof:name":"Policlinica Almogavares S.l.",
    "wof:placetype":"venue"
},
  "geometry": {"coordinates":[-4.7737140656,37.8960838318],"type":"Point"}
}