{
  "type": "Feature",
  "properties": {
    "iso:country":"ES",
    "sg:address":"Carr Antoni Maura, 4",
    "sg:city":"Badalona",
    "sg:orig_category":"Iglesia Cat\u00d3lica",
    "sg:phone":"+34 933 89 23 63",
    "sg:postcode":"08911",
    "sg:province":"Barcelona",
    "wof:name":"Parroquia Nuestra Se\u00f1ora De Lourdes",
    "wof:placetype":"venue"
},
  "geometry": {"coordinates":[2.2460289001,41.4520339966],"type":"Point"}
}