{
  "type": "Feature",
  "properties": {
    "iso:country":"ES",
    "sg:address":"Calle de San Roque, 21",
    "sg:city":"Moron Frontera",
    "sg:orig_category":"Estudios, Instalaci\u00d3n De Climatizaci\u00d3n",
    "sg:phone":"+34 955 85 21 28",
    "sg:postcode":"41530",
    "sg:province":"Sevilla",
    "wof:name":"Sugon Electricidad S.l.",
    "wof:placetype":"venue"
},
  "geometry": {"coordinates":[-5.4492731094,37.1255722046],"type":"Point"}
}