{
  "type": "Feature",
  "properties": {
    "iso:country":"ES",
    "sg:address":"Carrer de Violeta, 7",
    "sg:city":"Vendrell",
    "sg:orig_category":"Delegados, Agentes De Tr\u00c1nsito, Auxiliares De Transporte Internacional",
    "sg:phone":"+34 977 66 00 37",
    "sg:postcode":"43700",
    "sg:province":"Tarragona",
    "wof:name":"Morote Falco Juan Antonio",
    "wof:placetype":"venue"
},
  "geometry": {"coordinates":[1.518813014,41.2297515869],"type":"Point"}
}