{
  "type": "Feature",
  "properties": {
    "iso:country":"ES",
    "sg:address":"Av Germanies, 45",
    "sg:city":"Inca",
    "sg:orig_category":"Abogados",
    "sg:phone":"+34 971 50 19 72",
    "sg:postcode":"07300",
    "sg:province":"Islas Baleares",
    "wof:name":"Canals Mir Miguel",
    "wof:placetype":"venue"
},
  "geometry": {"coordinates":[2.9070351124,39.7205162048],"type":"Point"}
}