{
  "type": "Feature",
  "properties": {
    "iso:country":"ES",
    "sg:address":"Carrer de Cartagena, 326",
    "sg:city":"Barcelona",
    "sg:orig_category":"Reposter\u00cdas",
    "sg:phone":"+34 934 56 87 34",
    "sg:postcode":"08025",
    "sg:province":"Barcelona",
    "wof:name":"Iberpan S.a.",
    "wof:placetype":"venue"
},
  "geometry": {"coordinates":[2.1748371124,41.4110183716],"type":"Point"}
}