{
  "type": "Feature",
  "properties": {
    "addr:full":"Chichemy, 6 Valsequillo Las Palmas 35217",
    "addr:housenumber":"6",
    "addr:postcode":"35217",
    "addr:street":"Chichemy",
    "iso:country":"ES",
    "sg:address":"Chichemy, 6",
    "sg:city":"Valsequillo",
    "sg:orig_category":"Muebles, Minoristas",
    "sg:phone":"+34 928 70 59 45",
    "sg:postcode":"35217",
    "sg:province":"Las Palmas",
    "wof:name":"Benitez Sanchez Vicente Juan",
    "wof:placetype":"venue"
},
  "geometry": {"coordinates":[-15.4940710068,27.9912548065],"type":"Point"}
}