{
  "type": "Feature",
  "properties": {
    "addr:full":"Calle de General Varela, 47 Camarena Toledo 45180",
    "addr:housenumber":"47",
    "addr:postcode":"45180",
    "addr:street":"Calle De General Varela",
    "iso:country":"ES",
    "sg:address":"Calle de General Varela, 47",
    "sg:city":"Camarena",
    "sg:orig_category":"Venta, Instalaci\u00d3n De Calefacci\u00d3n",
    "sg:phone":"+34 918 17 40 00",
    "sg:postcode":"45180",
    "sg:province":"Toledo",
    "wof:name":"Inversiones Ferga S.l.",
    "wof:placetype":"venue"
},
  "geometry": {"coordinates":[-4.1141061783,40.0946540833],"type":"Point"}
}