{
  "type": "Feature",
  "properties": {
    "iso:country":"ES",
    "sg:address":"Calle de Almanzor, 2",
    "sg:city":"Sevilla",
    "sg:orig_category":"Colchones (fabricaci\u00d3n, Al Por Mayor, Al Por Menor)",
    "sg:phone":"+34 954 25 32 94",
    "sg:postcode":"41016",
    "sg:province":"Sevilla",
    "wof:name":"Morente Carmona Maria Del Carmen",
    "wof:placetype":"venue"
},
  "geometry": {"coordinates":[-5.9156079292,37.38539505],"type":"Point"}
}