{
  "type": "Feature",
  "properties": {
    "iso:country":"ES",
    "sg:address":"Pl Duc De Medinaceli, 5",
    "sg:city":"Barcelona",
    "sg:orig_category":"Fabricaci\u00d3n, Reparaci\u00d3n Y Mantenimiento De Construcciones Navales Y Fluviales",
    "sg:phone":"+34 933 01 77 16",
    "sg:postcode":"08002",
    "sg:province":"Barcelona",
    "sg:website":"www.cisam.com",
    "wof:name":"Cisam S.l.",
    "wof:placetype":"venue"
},
  "geometry": {"coordinates":[2.1791210175,41.3779411316],"type":"Point"}
}