{
  "type": "Feature",
  "properties": {
    "iso:country":"ES",
    "sg:address":"Calle de Okendo, 6",
    "sg:city":"Donostia-san Sebastian",
    "sg:orig_category":"Asistencia Social",
    "sg:phone":"+34 943 42 39 42",
    "sg:postcode":"20004",
    "sg:province":"Guip\u00f9zcoa",
    "wof:name":"Asociacion Guipuzcoana Pro Subnormales",
    "wof:placetype":"venue"
},
  "geometry": {"coordinates":[-1.9816981554,43.32239151],"type":"Point"}
}