{
  "type": "Feature",
  "properties": {
    "addr:full":"Calle de Redondo Marques, 2 Cabra C\u00f3rdoba 14940",
    "addr:housenumber":"2",
    "addr:postcode":"14940",
    "addr:street":"Calle De Redondo Marques;Co\u0301Rdoba",
    "iso:country":"ES",
    "sg:address":"Calle de Redondo Marques, 2",
    "sg:city":"Cabra",
    "sg:orig_category":"Cajas De Ahorro",
    "sg:phone":"+34 957 52 06 76",
    "sg:postcode":"14940",
    "sg:province":"C\u00f3rdoba",
    "wof:name":"Unicaja",
    "wof:placetype":"venue"
},
  "geometry": {"coordinates":[-4.4418911934,37.4734764099],"type":"Point"}
}