{
  "type": "Feature",
  "properties": {
    "iso:country":"ES",
    "sg:address":"Ctra. General, 84",
    "sg:city":"Sta.ursula",
    "sg:orig_category":"Centros Comerciales Y Grandes Tiendas",
    "sg:phone":"+34 922 33 70 62",
    "sg:postcode":"38390",
    "sg:province":"Santa Cruz De Tenerife",
    "wof:name":"Quevedo Apolinario Isabel",
    "wof:placetype":"venue"
},
  "geometry": {"coordinates":[-16.4917697906,28.425359726],"type":"Point"}
}