{
  "type": "Feature",
  "properties": {
    "iso:country":"ES",
    "sg:address":"Calle de Gutenberg, 83",
    "sg:city":"Poligono Industrial Los Villares",
    "sg:orig_category":"Equitaci\u00d3n: Guarnicioner\u00cda, Equipo (al Por Menor)",
    "sg:phone":"+34 923 24 84 20",
    "sg:postcode":"37184",
    "sg:province":"Salamanca",
    "wof:name":"Wicmoel S. L.",
    "wof:placetype":"venue"
},
  "geometry": {"coordinates":[-5.6386590004,40.9896697998],"type":"Point"}
}