{
  "type": "Feature",
  "properties": {
    "iso:country":"ES",
    "sg:address":"Luga Parque Tecnologico De Boecillo, S/n",
    "sg:city":"Parque Tecnologico De Boecillo",
    "sg:orig_category":"Inform\u00c1tica (estudios, Servicios, Asesor\u00cda, Formaci\u00d3n)",
    "sg:phone":"+34 983 54 82 64",
    "sg:postcode":"47151",
    "sg:province":"Valladolid",
    "wof:name":"Grupalia Internet S.a.",
    "wof:placetype":"venue"
},
  "geometry": {"coordinates":[-4.7162079811,41.5228118896],"type":"Point"}
}