{
  "type": "Feature",
  "properties": {
    "addr:full":"Av. Jose Antonio, 34 Avila \u00c1vila 05001",
    "addr:housenumber":"34",
    "addr:postcode":"05001",
    "addr:street":"Av. Jose Antonio;A\u0301Vila",
    "iso:country":"ES",
    "sg:address":"Av. Jose Antonio, 34",
    "sg:city":"Avila",
    "sg:orig_category":"Molduras, Junquillos, Listones Y Molduras Perforadas",
    "sg:phone":"+34 920 25 48 86",
    "sg:postcode":"05001",
    "sg:province":"\u00c1vila",
    "wof:name":"Jimenez Jimenez Jose Antonio",
    "wof:placetype":"venue"
},
  "geometry": {"coordinates":[-4.6847229004,40.6568832397],"type":"Point"}
}