{
  "type": "Feature",
  "properties": {
    "iso:country":"ES",
    "sg:address":"Carrer de Ramon I Cajal, 1",
    "sg:city":"Calella",
    "sg:orig_category":"Promotores Constructores",
    "sg:phone":"+34 937 66 30 09",
    "sg:postcode":"08370",
    "sg:province":"Barcelona",
    "wof:name":"Ginesta Obres I Serveis S.l.",
    "wof:placetype":"venue"
},
  "geometry": {"coordinates":[2.6527440548,41.6144523621],"type":"Point"}
}