{
  "type": "Feature",
  "properties": {
    "iso:country":"ES",
    "sg:address":"Calle de Angel Guimera, 85",
    "sg:city":"Palmas De Gran Canaria",
    "sg:orig_category":"M\u00c1quinas De Escribir, M\u00c1quinas De Oficina (al Por Menor, Reparaci\u00d3n)",
    "sg:phone":"+34 928 23 48 27",
    "sg:postcode":"35004",
    "sg:province":"Las Palmas",
    "wof:name":"Olycanarias De Impresion Y Comunicacion S.l.",
    "wof:placetype":"venue"
},
  "geometry": {"coordinates":[-15.425327301,28.1170692444],"type":"Point"}
}