{
  "type": "Feature",
  "properties": {
    "iso:country":"ES",
    "sg:address":"Calle de O'donnell, 6",
    "sg:city":"Madrid",
    "sg:orig_category":"Ingeniero",
    "sg:phone":"+34 915 75 21 63",
    "sg:postcode":"28009",
    "sg:province":"Madrid",
    "wof:name":"Gomez Casado Emilio",
    "wof:placetype":"venue"
},
  "geometry": {"coordinates":[-3.6793766022,40.4216537476],"type":"Point"}
}