{
  "type": "Feature",
  "properties": {
    "iso:country":"ES",
    "sg:address":"Calle de Triste Condesa, 14",
    "sg:city":"Arenas San Pedro",
    "sg:orig_category":"Electrodom\u00c9sticos (fabricaci\u00d3n, Al Por Mayor)",
    "sg:phone":"+34 920 37 28 32",
    "sg:postcode":"05400",
    "sg:province":"\u00c1vila",
    "wof:name":"Electrodomesticos Segundo Mu\u00f1oz S.l.",
    "wof:placetype":"venue"
},
  "geometry": {"coordinates":[-5.0889091492,40.2097930908],"type":"Point"}
}