{
  "type": "Feature",
  "properties": {
    "iso:country":"ES",
    "sg:address":"Calle de Claudio Coello, 111",
    "sg:city":"Madrid",
    "sg:orig_category":"Estancos",
    "sg:phone":"+34 914 35 27 92",
    "sg:postcode":"28006",
    "sg:province":"Madrid",
    "wof:name":"Rodriguez De Santiago-concha Fabra Maria Ines",
    "wof:placetype":"venue"
},
  "geometry": {"coordinates":[-3.6857066154,40.4320755005],"type":"Point"}
}