{
  "type": "Feature",
  "properties": {
    "addr:full":"Carrer de Loreto, 2 Barcelona Barcelona 08029",
    "addr:housenumber":"2",
    "addr:postcode":"08029",
    "addr:street":"Carrer De Loreto",
    "iso:country":"ES",
    "sg:address":"Carrer de Loreto, 2",
    "sg:city":"Barcelona",
    "sg:classifiers":[
        {
            "category":"Personal",
            "subcategory":"Barber",
            "type":"Services"
        }
    ],
    "sg:phone":"+34 934 39 55 73",
    "sg:postcode":"08029",
    "sg:province":"Barcelona",
    "sg:tags":[
        "caballeros",
        "de",
        "peluqueros"
    ],
    "wof:name":"Vazquez Torralba Juan Manuel",
    "wof:placetype":"venue"
},
  "geometry": {"coordinates":[2.1418890953,41.3885574341],"type":"Point"}
}