{
  "type": "Feature",
  "properties": {
    "addr:full":"Rond Levante, 5 Vista Alegre Murcia 30008",
    "addr:housenumber":"5",
    "addr:postcode":"30008",
    "addr:street":"Rond Levante",
    "iso:country":"ES",
    "sg:address":"Rond Levante, 5",
    "sg:city":"Vista Alegre",
    "sg:orig_category":"Farmacias",
    "sg:phone":"+34 968 23 57 25",
    "sg:postcode":"30008",
    "sg:province":"Murcia",
    "wof:name":"Corbalan Belmonte Amelia",
    "wof:placetype":"venue"
},
  "geometry": {"coordinates":[-1.1285649538,37.9922485352],"type":"Point"}
}