{
  "type": "Feature",
  "properties": {
    "addr:full":"Navas De Tolosa, 29 Iru\u00f1a Navarra 31002",
    "addr:housenumber":"29",
    "addr:postcode":"31002",
    "addr:street":"Navas;Tolosa",
    "iso:country":"ES",
    "sg:address":"Navas De Tolosa, 29",
    "sg:city":"Iru\u00f1a",
    "sg:orig_category":"Asesor\u00cda Sobre Comunicaci\u00d3n De Empresas",
    "sg:phone":"+34 948 22 79 53",
    "sg:postcode":"31002",
    "sg:province":"Navarra",
    "wof:name":"Oteiza Obanos Antonio",
    "wof:placetype":"venue"
},
  "geometry": {"coordinates":[-1.6509040594,42.8154602051],"type":"Point"}
}