{
  "type": "Feature",
  "properties": {
    "addr:full":"Calle de Salcillo, 9 Mostoles Madrid 28932",
    "addr:housenumber":"9",
    "addr:postcode":"28932",
    "addr:street":"Calle De Salcillo",
    "iso:country":"ES",
    "sg:address":"Calle de Salcillo, 9",
    "sg:city":"Mostoles",
    "sg:orig_category":"Centros M\u00c9dicos Y Sociales, Dispensarios",
    "sg:phone":"+34 916 18 21 02",
    "sg:postcode":"28932",
    "sg:province":"Madrid",
    "wof:name":"Gonzalez Lopez Jose Antonio",
    "wof:placetype":"venue"
},
  "geometry": {"coordinates":[-3.8653290272,40.3338432312],"type":"Point"}
}