{
  "type": "Feature",
  "properties": {
    "addr:full":"Rua Conde Pallares, 9 Lugo Lugo 27001",
    "addr:housenumber":"9",
    "addr:postcode":"27001",
    "addr:street":"Rua Conde Pallares",
    "iso:country":"ES",
    "sg:address":"Rua Conde Pallares, 9",
    "sg:city":"Lugo",
    "sg:orig_category":"Estilistas Y Estudios De Estilo De Corte Y Confecci\u00d3n",
    "sg:phone":"+34 982 22 62 43",
    "sg:postcode":"27001",
    "sg:province":"Lugo",
    "wof:name":"Ceide Saavedra Josefa",
    "wof:placetype":"venue"
},
  "geometry": {"coordinates":[-7.5571289062,43.0102310181],"type":"Point"}
}