{
  "type": "Feature",
  "properties": {
    "iso:country":"ES",
    "sg:address":"Ademuz, 3",
    "sg:city":"Manises",
    "sg:orig_category":"Caf\u00c9s, Bares, Cervecer\u00cdas",
    "sg:phone":"+34 961 53 22 52",
    "sg:postcode":"46940",
    "sg:province":"Valencia",
    "wof:name":"Franco Delgado Jose",
    "wof:placetype":"venue"
},
  "geometry": {"coordinates":[-0.4840559959,39.4982948303],"type":"Point"}
}