{
  "type": "Feature",
  "properties": {
    "iso:country":"ES",
    "sg:address":"Carrer de Lleida, 16",
    "sg:city":"S. Boi Llobregat",
    "sg:orig_category":"Inform\u00c1tica (estudios, Servicios, Asesor\u00cda, Formaci\u00d3n)",
    "sg:phone":"+34 936 54 22 43",
    "sg:postcode":"08830",
    "sg:province":"Barcelona",
    "wof:name":"Digital Image Systems S.l.",
    "wof:placetype":"venue"
},
  "geometry": {"coordinates":[2.0449779034,41.3480606079],"type":"Point"}
}