{
  "type": "Feature",
  "properties": {
    "addr:full":"Avda De Castelao, 43 Ponteareas Pontevedra 36860",
    "addr:housenumber":"43",
    "addr:postcode":"36860",
    "addr:street":"Avda De Castelao",
    "iso:country":"ES",
    "sg:address":"Avda De Castelao, 43",
    "sg:city":"Ponteareas",
    "sg:orig_category":"Caf\u00c9s, Bares, Cervecer\u00cdas",
    "sg:phone":"+34 986 64 10 01",
    "sg:postcode":"36860",
    "sg:province":"Pontevedra",
    "wof:name":"Hosteleria Luar S.l.",
    "wof:placetype":"venue"
},
  "geometry": {"coordinates":[-8.5092916489,42.174369812],"type":"Point"}
}