{
  "type": "Feature",
  "properties": {
    "iso:country":"ES",
    "sg:address":"Cami Paciencia, S/n",
    "sg:city":"Sant Vicen\u00c7 De Torello",
    "sg:orig_category":"Metalurgia",
    "sg:phone":"+34 938 50 48 98",
    "sg:postcode":"08571",
    "sg:province":"Barcelona",
    "wof:name":"Ferules I Valvules S.l.",
    "wof:placetype":"venue"
},
  "geometry": {"coordinates":[2.2583398819,42.0611610413],"type":"Point"}
}