{
  "type": "Feature",
  "properties": {
    "iso:country":"ES",
    "sg:address":"Calle de Montes De Toledo, 24",
    "sg:city":"Villarrubia De Los Ojos",
    "sg:orig_category":"Muebles, Minoristas",
    "sg:phone":"+34 926 89 66 03",
    "sg:postcode":"13670",
    "sg:province":"Ciudad Real",
    "wof:name":"Alises Amador Felix",
    "wof:placetype":"venue"
},
  "geometry": {"coordinates":[-3.6090807915,39.2261657715],"type":"Point"}
}