{
  "type": "Feature",
  "properties": {
    "iso:country":"ES",
    "sg:address":"Carrer de Tallers, 79",
    "sg:city":"Barcelona",
    "sg:orig_category":"Fabricaci\u00d3n, Distribuci\u00d3n De Discos, V\u00cddeodiscos Y Musicassettes",
    "sg:phone":"+34 933 01 35 75",
    "sg:postcode":"08001",
    "sg:province":"Barcelona",
    "sg:website":"www.discocastello.es",
    "wof:name":"Discos Castello S.a.",
    "wof:placetype":"venue"
},
  "geometry": {"coordinates":[2.1644690037,41.3850631714],"type":"Point"}
}