{
  "type": "Feature",
  "properties": {
    "iso:country":"ES",
    "sg:address":"Calle de Hoces Del Duraton, 113",
    "sg:city":"Salamanca",
    "sg:orig_category":"Panader\u00cdas, Panader\u00cdas",
    "sg:phone":"+34 923 19 19 17",
    "sg:postcode":"37008",
    "sg:province":"Salamanca",
    "wof:name":"Lazarillo De Tornes S. L.",
    "wof:placetype":"venue"
},
  "geometry": {"coordinates":[-5.6620388031,40.9406509399],"type":"Point"}
}