{
  "type": "Feature",
  "properties": {
    "iso:country":"ES",
    "sg:address":"Carr Valencia (de), 35",
    "sg:city":"Lliria",
    "sg:orig_category":"Empresas De Carpinter\u00cda De Madera",
    "sg:phone":"+34 962 79 06 33",
    "sg:postcode":"46160",
    "sg:province":"Valencia",
    "wof:name":"Silvino Garcia Asensi Y Otro Cdad.",
    "wof:placetype":"venue"
},
  "geometry": {"coordinates":[-0.5714480281,39.649143219],"type":"Point"}
}