{
  "type": "Feature",
  "properties": {
    "addr:full":"Calle de Sanatorio, 14 Gines Sevilla 41960",
    "addr:housenumber":"14",
    "addr:postcode":"41960",
    "addr:street":"Calle De Sanatorio;Sevilla",
    "iso:country":"ES",
    "sg:address":"Calle de Sanatorio, 14",
    "sg:city":"Gines",
    "sg:orig_category":"Mec\u00c1nico Del Autom\u00d3vil",
    "sg:phone":"+34 954 71 50 05",
    "sg:postcode":"41960",
    "sg:province":"Sevilla",
    "wof:name":"Cortes Ostos Jose",
    "wof:placetype":"venue"
},
  "geometry": {"coordinates":[-6.0802059174,37.3875694275],"type":"Point"}
}