{
  "type": "Feature",
  "properties": {
    "addr:full":"Carrer de Aureli Maria Escarre, 7 Mollet Valles Barcelona 08100",
    "addr:housenumber":"7",
    "addr:postcode":"08100",
    "addr:street":"Carrer De Aureli Maria Escarre",
    "iso:country":"ES",
    "sg:address":"Carrer de Aureli Maria Escarre, 7",
    "sg:city":"Mollet Valles",
    "sg:orig_category":"Laboratorios Y Cl\u00cdnicas Veterinarias",
    "sg:phone":"+34 935 93 77 51",
    "sg:postcode":"08100",
    "sg:province":"Barcelona",
    "wof:name":"Clinica Veterinaria Mollet",
    "wof:placetype":"venue"
},
  "geometry": {"coordinates":[2.2091441154,41.5394706726],"type":"Point"}
}