{
  "type": "Feature",
  "properties": {
    "iso:country":"ES",
    "sg:address":"Carrer de Camp, 13",
    "sg:city":"Vic",
    "sg:orig_category":"Persianas Interiores, Exteriores",
    "sg:phone":"+34 938 86 45 04",
    "sg:postcode":"08500",
    "sg:province":"Barcelona",
    "wof:name":"Gibert Ramirez Luis",
    "wof:placetype":"venue"
},
  "geometry": {"coordinates":[2.2656280994,41.9349899292],"type":"Point"}
}