{
  "type": "Feature",
  "properties": {
    "iso:country":"ES",
    "sg:address":"Industrialdea, 10",
    "sg:city":"Anoeta",
    "sg:orig_category":"Forjas Y Altos Hornos",
    "sg:phone":"+34 943 65 21 79",
    "sg:postcode":"20270",
    "sg:province":"Guip\u00f9zcoa",
    "wof:name":"Euskal Forging S.a.",
    "wof:placetype":"venue"
},
  "geometry": {"coordinates":[-2.0678970814,43.1588172913],"type":"Point"}
}