{
  "type": "Feature",
  "properties": {
    "iso:country":"ES",
    "sg:address":"Carrer de Sant Felip, 115",
    "sg:city":"Masnou",
    "sg:orig_category":"Formaci\u00d3n A Distancia, Por Correspondencia",
    "sg:phone":"+34 935 55 30 36",
    "sg:postcode":"08320",
    "sg:province":"Barcelona",
    "sg:website":"www.aprendes.com",
    "wof:name":"Cresline S.l.",
    "wof:placetype":"venue"
},
  "geometry": {"coordinates":[2.3232820034,41.4811134338],"type":"Point"}
}