{
  "type": "Feature",
  "properties": {
    "iso:country":"ES",
    "sg:address":"Rbla Anselm Clave, 51",
    "sg:city":"Cornella Llobregat",
    "sg:orig_category":"Inform\u00c1tica: Material Y Suministros",
    "sg:phone":"+34 933 77 07 79",
    "sg:postcode":"08940",
    "sg:province":"Barcelona",
    "sg:website":"www.ahtec.net",
    "wof:name":"Ampliware S.l.",
    "wof:placetype":"venue"
},
  "geometry": {"coordinates":[2.0727500916,41.3542175293],"type":"Point"}
}