{
  "type": "Feature",
  "properties": {
    "addr:full":"Poli Industrial Berriainz, 62 Berriozar Navarra 31013",
    "addr:housenumber":"62",
    "addr:postcode":"31013",
    "addr:street":"Berriainz",
    "iso:country":"ES",
    "sg:address":"Poli Industrial Berriainz, 62",
    "sg:city":"Berriozar",
    "sg:orig_category":"Copas, Insignias, Trofeos",
    "sg:phone":"+34 948 30 30 45",
    "sg:postcode":"31013",
    "sg:province":"Navarra",
    "sg:website":"www.trofeoscima.com",
    "wof:name":"Trofeos Cima S.a.",
    "wof:placetype":"venue"
},
  "geometry": {"coordinates":[-1.6696590185,42.8440933228],"type":"Point"}
}