{
  "type": "Feature",
  "properties": {
    "addr:full":"Carrer de Amalia Soler, 146 Vilafranca Penedes Barcelona 08720",
    "addr:housenumber":"146",
    "addr:postcode":"08720",
    "addr:street":"Carrer De Amalia Soler;Penedes Barcelona",
    "iso:country":"ES",
    "sg:address":"Carrer de Amalia Soler, 146",
    "sg:city":"Vilafranca Penedes",
    "sg:orig_category":"Tintes (fabricaci\u00d3n, Al Por Mayor)",
    "sg:phone":"+34 938 17 29 87",
    "sg:postcode":"08720",
    "sg:province":"Barcelona",
    "wof:name":"Catala Escribano Jose Antonio",
    "wof:placetype":"venue"
},
  "geometry": {"coordinates":[1.6992199421,41.3447799683],"type":"Point"}
}