{
  "type": "Feature",
  "properties": {
    "addr:full":"Calle de Duque De Ahumada, 20 Villafranca De Los Barros Badajoz 06220",
    "addr:housenumber":"20",
    "addr:postcode":"06220",
    "addr:street":"Calle De Duque De Ahumada",
    "iso:country":"ES",
    "sg:address":"Calle de Duque De Ahumada, 20",
    "sg:city":"Villafranca De Los Barros",
    "sg:orig_category":"Ebanister\u00cda",
    "sg:phone":"+34 924 52 40 46",
    "sg:postcode":"06220",
    "sg:province":"Badajoz",
    "wof:name":"Ebanisteria Barradas S.l.",
    "wof:placetype":"venue"
},
  "geometry": {"coordinates":[-6.3354454041,38.5638160706],"type":"Point"}
}