{
  "type": "Feature",
  "properties": {
    "addr:full":"Avda Zamora (de), 106 Ourense Ourense 32005",
    "addr:housenumber":"106",
    "addr:postcode":"32005",
    "addr:street":"Avda Zamora De",
    "iso:country":"ES",
    "sg:address":"Avda Zamora (de), 106",
    "sg:city":"Ourense",
    "sg:orig_category":"Cajas De Ahorro",
    "sg:phone":"+34 988 24 44 50",
    "sg:postcode":"32005",
    "sg:province":"Ourense",
    "wof:name":"Caixa De Aforros De Vigo Ourense E Pontevedra",
    "wof:placetype":"venue"
},
  "geometry": {"coordinates":[-7.8625249863,42.3232536316],"type":"Point"}
}