{
  "type": "Feature",
  "properties": {
    "iso:country":"ES",
    "sg:address":"Pque Empresarial La Muga, 5",
    "sg:city":"Orkoien",
    "sg:orig_category":"Comercio De Piezas De Recambio Y De Accesorios De Veh\u00cdculos, Veh\u00cdculos Industriales",
    "sg:phone":"+34 948 32 15 98",
    "sg:postcode":"31160",
    "sg:province":"Navarra",
    "wof:name":"Elcoro Automotive S.l.",
    "wof:placetype":"venue"
},
  "geometry": {"coordinates":[-1.7060990334,42.8219032288],"type":"Point"}
}