{
  "type": "Feature",
  "properties": {
    "addr:full":"Calle de Juan Jose Ruano, 15 Santo\u00f1a Cantabria 39740",
    "addr:housenumber":"15",
    "addr:postcode":"39740",
    "addr:street":"Calle De Juan Jose Ruano",
    "iso:country":"ES",
    "sg:address":"Calle de Juan Jose Ruano, 15",
    "sg:city":"Santo\u00f1a",
    "sg:orig_category":"Art\u00cdculos De Decoraci\u00d3n",
    "sg:phone":"+34 942 66 04 03",
    "sg:postcode":"39740",
    "sg:province":"Cantabria",
    "wof:name":"Santa Maria Lopez Carlos",
    "wof:placetype":"venue"
},
  "geometry": {"coordinates":[-3.4574649334,43.4415893555],"type":"Point"}
}