{
  "type": "Feature",
  "properties": {
    "iso:country":"ES",
    "sg:address":"Ctra Vic, S/n",
    "sg:city":"Moia",
    "sg:orig_category":"Venta, Instalaci\u00d3n, Mantenimiento De Chimeneas De Interior Y Accesorios",
    "sg:phone":"+34 938 30 06 23",
    "sg:postcode":"08180",
    "sg:province":"Barcelona",
    "wof:name":"Codina Vilardell Jose",
    "wof:placetype":"venue"
},
  "geometry": {"coordinates":[2.1066429615,41.8088912964],"type":"Point"}
}