{
  "type": "Feature",
  "properties": {
    "iso:country":"ES",
    "sg:address":"Carretera De Burgos, 63",
    "sg:city":"Salas Infantes",
    "sg:orig_category":"Reposter\u00cdas",
    "sg:phone":"+34 947 38 08 89",
    "sg:postcode":"09600",
    "sg:province":"Burgos",
    "wof:name":"Huerta Elvira Victor",
    "wof:placetype":"venue"
},
  "geometry": {"coordinates":[-3.293833971,42.0229797363],"type":"Point"}
}