{
  "type": "Feature",
  "properties": {
    "iso:country":"ES",
    "sg:address":"Calle de Zankoeta, 4",
    "sg:city":"Bilbao",
    "sg:orig_category":"Comercio De Piezas De Recambio Y De Accesorios De Veh\u00cdculos, Veh\u00cdculos Industriales",
    "sg:phone":"+34 944 41 06 27",
    "sg:postcode":"48013",
    "sg:province":"Vizcaya",
    "wof:name":"Morfer Wheels & Welding S.l.",
    "wof:placetype":"venue"
},
  "geometry": {"coordinates":[-2.9472930431,43.2582244873],"type":"Point"}
}