{
  "type": "Feature",
  "properties": {
    "addr:full":"Avda Portugal (de), 38 Verin Ourense 32600",
    "addr:housenumber":"38",
    "addr:postcode":"32600",
    "addr:street":"Avda Portugal De",
    "iso:country":"ES",
    "sg:address":"Avda Portugal (de), 38",
    "sg:city":"Verin",
    "sg:orig_category":"Alimentaci\u00d3n General (al Por Menor)",
    "sg:phone":"+34 988 41 21 00",
    "sg:postcode":"32600",
    "sg:province":"Ourense",
    "wof:name":"Distribuciones Froiz S.a.",
    "wof:placetype":"venue"
},
  "geometry": {"coordinates":[-7.4374060631,41.9400863647],"type":"Point"}
}