{
  "type": "Feature",
  "properties": {
    "iso:country":"ES",
    "sg:address":"Calle de Montero Calvo, 1",
    "sg:city":"Valladolid",
    "sg:orig_category":"Art\u00cdculos De Regalo (al Por Menor)",
    "sg:phone":"+34 983 39 79 08",
    "sg:postcode":"47001",
    "sg:province":"Valladolid",
    "wof:name":"Martinez Arribas Camino",
    "wof:placetype":"venue"
},
  "geometry": {"coordinates":[-4.7272567749,41.6498222351],"type":"Point"}
}