{
  "type": "Feature",
  "properties": {
    "iso:country":"ES",
    "sg:address":"Carr Teulera, 29",
    "sg:city":"Santa Cristina D'aro",
    "sg:orig_category":"Farmacias",
    "sg:phone":"+34 972 83 51 89",
    "sg:postcode":"17246",
    "sg:province":"Girona",
    "wof:name":"Fuentes Faig Maria Lourdes",
    "wof:placetype":"venue"
},
  "geometry": {"coordinates":[2.8381810188,41.9668312073],"type":"Point"}
}