{
  "type": "Feature",
  "properties": {
    "iso:country":"ES",
    "sg:address":"Avgd Blondel, 60",
    "sg:city":"Lleida",
    "sg:orig_category":"Electrodom\u00c9sticos (al Por Menor)",
    "sg:phone":"+34 973 28 01 20",
    "sg:postcode":"25002",
    "sg:province":"Lleida",
    "wof:name":"Grup Coel S. A.",
    "wof:placetype":"venue"
},
  "geometry": {"coordinates":[0.6243240237,41.6129074097],"type":"Point"}
}