{
  "type": "Feature",
  "properties": {
    "addr:full":"Av Pais Valenciano, 67 Guardamar Segura Alicante 03140",
    "addr:housenumber":"67",
    "addr:postcode":"03140",
    "addr:street":"Av Pais Valenciano",
    "iso:country":"ES",
    "sg:address":"Av Pais Valenciano, 67",
    "sg:city":"Guardamar Segura",
    "sg:orig_category":"Audiovisuales (producci\u00d3n, Edici\u00d3n, Realizaci\u00d3n)",
    "sg:phone":"+34 966 72 62 77",
    "sg:postcode":"03140",
    "sg:province":"Alicante",
    "wof:name":"Radio Television Guardamar S.l.",
    "wof:placetype":"venue"
},
  "geometry": {"coordinates":[-0.6539019942,38.0864677429],"type":"Point"}
}