{
  "type": "Feature",
  "properties": {
    "iso:country":"ES",
    "sg:address":"Pedrouzos, S/n",
    "sg:city":"Pedrouzos",
    "sg:orig_category":"Restaurantes",
    "sg:phone":"+34 982 51 04 02",
    "sg:postcode":"27813",
    "sg:province":"Lugo",
    "wof:name":"Novo Codesal Fernando",
    "wof:placetype":"venue"
},
  "geometry": {"coordinates":[-7.7691807747,43.2343101501],"type":"Point"}
}