{
  "type": "Feature",
  "properties": {
    "iso:country":"ES",
    "sg:address":"Avda Puente De Carlos Iii, 6",
    "sg:city":"Reinosa",
    "sg:orig_category":"Tractores Agr\u00cdcolas Y Remolques",
    "sg:phone":"+34 942 75 24 93",
    "sg:postcode":"39200",
    "sg:province":"Cantabria",
    "wof:name":"Ebro Forestal S.l.",
    "wof:placetype":"venue"
},
  "geometry": {"coordinates":[-4.1380839348,42.9991950989],"type":"Point"}
}