{
  "type": "Feature",
  "properties": {
    "addr:full":"Calle de El Prado, 6 Vitoria-gasteiz \u00c1lava 01005",
    "addr:housenumber":"6",
    "addr:postcode":"01005",
    "addr:street":"Calle De El Prado",
    "iso:country":"ES",
    "sg:address":"Calle de El Prado, 6",
    "sg:city":"Vitoria-gasteiz",
    "sg:orig_category":"Torrefactado De Caf\u00c9",
    "sg:phone":"+34 945 25 44 48",
    "sg:postcode":"01005",
    "sg:province":"\u00c1lava",
    "wof:name":"Cafes La Brasile\u00f1a S.a.",
    "wof:placetype":"venue"
},
  "geometry": {"coordinates":[-2.6741540432,42.8461494446],"type":"Point"}
}