{
  "type": "Feature",
  "properties": {
    "iso:country":"ES",
    "sg:address":"Luga Poligono Industrial, S/n",
    "sg:city":"Camponaraya",
    "sg:orig_category":"Adaptaciones, Acondicionamientos Especiales Para Veh\u00cdculos, Veh\u00cdculos Industriales",
    "sg:phone":"+34 987 46 32 68",
    "sg:postcode":"24410",
    "sg:province":"Le\u00f3n",
    "wof:name":"Talleres Gonzalez Prada S.l.",
    "wof:placetype":"venue"
},
  "geometry": {"coordinates":[-6.6785559654,42.6148796082],"type":"Point"}
}