{
  "type": "Feature",
  "properties": {
    "addr:full":"Calle de Tagoro, 118 Tagoro Santa Cruz De Tenerife 38350",
    "addr:housenumber":"118",
    "addr:postcode":"38350",
    "addr:street":"Calle De Tagoro",
    "iso:country":"ES",
    "sg:address":"Calle de Tagoro, 118",
    "sg:city":"Tagoro",
    "sg:orig_category":"Fabricaci\u00d3n, Comercio De Flores Y Plantas Artificiales",
    "sg:phone":"+34 922 57 12 20",
    "sg:postcode":"38350",
    "sg:province":"Santa Cruz De Tenerife",
    "wof:name":"Catesa Foods S.l.u.",
    "wof:placetype":"venue"
},
  "geometry": {"coordinates":[-16.4174289703,28.4756546021],"type":"Point"}
}