{
  "type": "Feature",
  "properties": {
    "iso:country":"ES",
    "sg:address":"Calle de El Greco, 13",
    "sg:city":"Madrid",
    "sg:orig_category":"Promotores Constructores",
    "sg:phone":"+34 917 55 02 74",
    "sg:postcode":"28011",
    "sg:province":"Madrid",
    "wof:name":"Portico 2000 S.l.",
    "wof:placetype":"venue"
},
  "geometry": {"coordinates":[-3.744699955,40.4081611633],"type":"Point"}
}