{
  "type": "Feature",
  "properties": {
    "iso:country":"ES",
    "sg:address":"Avenida De San Isidro, S/n",
    "sg:city":"Domingo Perez",
    "sg:orig_category":"Aceites Y Grasas Alimentarias (fabricaci\u00d3n, Al Por Mayor)",
    "sg:phone":"+34 958 39 07 81",
    "sg:postcode":"18567",
    "sg:province":"Granada",
    "sg:website":"www.varaila.com",
    "wof:name":"Varaila De Domingo Perez Scdad.coop.andaluza",
    "wof:placetype":"venue"
},
  "geometry": {"coordinates":[-3.552628994,37.4742546082],"type":"Point"}
}