{
  "type": "Feature",
  "properties": {
    "addr:full":"Pi\u00f1eiro, 50 Pi\u00e7eiro De Villestro La Coru\u00f1a 15896",
    "addr:housenumber":"50",
    "addr:postcode":"15896",
    "addr:street":"Pin\u0303Eiro;Corun\u0303A",
    "iso:country":"ES",
    "sg:address":"Pi\u00f1eiro, 50",
    "sg:city":"Pi\u00e7eiro De Villestro",
    "sg:orig_category":"Grafistas",
    "sg:phone":"+34 981 53 71 97",
    "sg:postcode":"15896",
    "sg:province":"La Coru\u00f1a",
    "wof:name":"Gonzalez Cao Jose Ignacio",
    "wof:placetype":"venue"
},
  "geometry": {"coordinates":[-8.6102218628,42.8763961792],"type":"Point"}
}