{
  "type": "Feature",
  "properties": {
    "addr:full":"Calle de Monteverde, 19 Madrid Madrid 28042",
    "addr:housenumber":"19",
    "addr:postcode":"madrid;28042",
    "addr:street":"Calle De Monteverde",
    "iso:country":"ES",
    "sg:address":"Calle de Monteverde, 19",
    "sg:city":"Madrid",
    "sg:orig_category":"Asesor\u00cda Fiscal Y Jur\u00cddica",
    "sg:phone":"+34 917 42 09 02",
    "sg:postcode":"28042",
    "sg:province":"Madrid",
    "wof:name":"I\u00d1igo Osset & Asociados S.l.",
    "wof:placetype":"venue"
},
  "geometry": {"coordinates":[-3.5960869789,40.4587860107],"type":"Point"}
}