{
  "type": "Feature",
  "properties": {
    "addr:full":"Ctra. Madrid-toledo, Km. 0027,7 Torrejon Calzada Madrid 28991",
    "addr:postcode":"28991",
    "addr:street":"Ctra. Madrid-Toledo Km. 0027,7;Calzada",
    "iso:country":"ES",
    "sg:address":"Ctra. Madrid-toledo, Km. 0027,7",
    "sg:city":"Torrejon Calzada",
    "sg:orig_category":"Revestimiento De Suelos Industriales",
    "sg:phone":"+34 918 16 93 17",
    "sg:postcode":"28991",
    "sg:province":"Madrid",
    "wof:name":"Quimica De Pavimentos S.a.",
    "wof:placetype":"venue"
},
  "geometry": {"coordinates":[-3.8016889095,40.2015762329],"type":"Point"}
}