{
  "type": "Feature",
  "properties": {
    "addr:full":"Trva Geronimos(urb Guadaluz), 60 Guadalupe Murcia 30107",
    "addr:housenumber":"60",
    "addr:postcode":"30107",
    "addr:street":"Trva Geronimos Urb Guadaluz",
    "iso:country":"ES",
    "sg:address":"Trva Geronimos(urb Guadaluz), 60",
    "sg:city":"Guadalupe",
    "sg:orig_category":"Cajas Para Embalar",
    "sg:phone":"+34 968 83 24 78",
    "sg:postcode":"30107",
    "sg:province":"Murcia",
    "sg:website":"www.cajamar.es",
    "wof:name":"Cajamar",
    "wof:placetype":"venue"
},
  "geometry": {"coordinates":[-1.1717339754,38.0002822876],"type":"Point"}
}