{
  "type": "Feature",
  "properties": {
    "addr:full":"Calle de Axular, 1 Santurtzi Vizcaya 48980",
    "addr:housenumber":"1",
    "addr:postcode":"48980",
    "addr:street":"Calle De Axular",
    "iso:country":"ES",
    "sg:address":"Calle de Axular, 1",
    "sg:city":"Santurtzi",
    "sg:orig_category":"Iglesia Cat\u00d3lica",
    "sg:phone":"+34 944 61 35 85",
    "sg:postcode":"48980",
    "sg:province":"Vizcaya",
    "wof:name":"Parroquia San Pedro Apostol",
    "wof:placetype":"venue"
},
  "geometry": {"coordinates":[-3.0364134312,43.321849823],"type":"Point"}
}