{
  "type": "Feature",
  "properties": {
    "addr:full":"Ctra De Coria (pi El Batan), Km. 0511,0 El Batan C\u00e1ceres 10692",
    "addr:postcode":"10692",
    "addr:street":"Ctra De Coria;El Batan Km. 0511,0 El;Ca\u0301Ceres",
    "iso:country":"ES",
    "sg:address":"Ctra De Coria (pi El Batan), Km. 0511,0",
    "sg:city":"El Batan",
    "sg:orig_category":"Venta, Montaje De Neum\u00c1ticos",
    "sg:phone":"+34 927 67 28 85",
    "sg:postcode":"10692",
    "sg:province":"C\u00e1ceres",
    "wof:name":"Neumaticos Jaleo C.b.",
    "wof:placetype":"venue"
},
  "geometry": {"coordinates":[-6.3801989555,39.97448349],"type":"Point"}
}