{
  "type": "Feature",
  "properties": {
    "addr:full":"Calle de Verneuil Sur Seine, 48 Aguilar De La Frontera C\u00f3rdoba 14920",
    "addr:housenumber":"48",
    "addr:postcode":"14920",
    "addr:street":"Calle De Verneuil;Seine",
    "iso:country":"ES",
    "sg:address":"Calle de Verneuil Sur Seine, 48",
    "sg:city":"Aguilar De La Frontera",
    "sg:orig_category":"Agentes, Concesionarios Y Sucursales De Veh\u00cdculos",
    "sg:phone":"+34 957 66 17 43",
    "sg:postcode":"14920",
    "sg:province":"C\u00f3rdoba",
    "wof:name":"Fernandez Lopez Antonio",
    "wof:placetype":"venue"
},
  "geometry": {"coordinates":[-4.6624622345,37.5116348267],"type":"Point"}
}