{
  "type": "Feature",
  "properties": {
    "addr:full":"Luga Parque Tecnologico De Boecillo, 109 Parque Tecnologico De Boecillo Valladolid 47151",
    "addr:housenumber":"109",
    "addr:postcode":"47151",
    "addr:street":"Parque",
    "iso:country":"ES",
    "sg:address":"Luga Parque Tecnologico De Boecillo, 109",
    "sg:city":"Parque Tecnologico De Boecillo",
    "sg:orig_category":"Inform\u00c1tica (estudios, Servicios, Asesor\u00cda, Formaci\u00d3n)",
    "sg:phone":"+34 983 54 80 84",
    "sg:postcode":"47151",
    "sg:province":"Valladolid",
    "sg:website":"www.ars-nova.net",
    "wof:name":"Ars Nova Sistemas Informacion S.a.",
    "wof:placetype":"venue"
},
  "geometry": {"coordinates":[-4.699862957,41.5408973694],"type":"Point"}
}