{
  "type": "Feature",
  "properties": {
    "addr:full":"Calle de Pago De Troya, 3 Pto Real C\u00e1diz 11510",
    "addr:housenumber":"3",
    "addr:postcode":"11510",
    "addr:street":"Calle De Pago De Troya;Ca\u0301Diz",
    "iso:country":"ES",
    "sg:address":"Calle de Pago De Troya, 3",
    "sg:city":"Pto Real",
    "sg:orig_category":"Sindicatos De Trabajadores",
    "sg:phone":"+34 956 83 39 59",
    "sg:postcode":"11510",
    "sg:province":"C\u00e1diz",
    "wof:name":"Union Sindical De Comisiones Obreras",
    "wof:placetype":"venue"
},
  "geometry": {"coordinates":[-6.1941747665,36.5306053162],"type":"Point"}
}