{
  "type": "Feature",
  "properties": {
    "iso:country":"ES",
    "sg:address":"Parroquia, S/n",
    "sg:city":"Corrales",
    "sg:orig_category":"Iglesia Cat\u00d3lica",
    "sg:phone":"+34 959 49 01 43",
    "sg:postcode":"21120",
    "sg:province":"Huelva",
    "wof:name":"Parroquia Nuestra Se\u00f1ora Reina Del Mundo",
    "wof:placetype":"venue"
},
  "geometry": {"coordinates":[-7.006524086,37.2821846008],"type":"Point"}
}