{
  "type": "Feature",
  "properties": {
    "iso:country":"ES",
    "sg:address":"Calle de Jose Dominguez Moreno, S/n",
    "sg:city":"Rodeo",
    "sg:orig_category":"Procuradores",
    "sg:phone":"+34 952 45 44 99",
    "sg:postcode":"29100",
    "sg:province":"M\u00e1laga",
    "wof:name":"Garcia Aguera Felix",
    "wof:placetype":"venue"
},
  "geometry": {"coordinates":[-4.7427639961,36.670009613],"type":"Point"}
}