{
  "type": "Feature",
  "properties": {
    "addr:full":"Calle de Coscojales, 7 Portugalete Vizcaya 48920",
    "addr:housenumber":"7",
    "addr:postcode":"48920",
    "addr:street":"Calle De Coscojales",
    "iso:country":"ES",
    "sg:address":"Calle de Coscojales, 7",
    "sg:city":"Portugalete",
    "sg:orig_category":"Partidos Pol\u00cdticos",
    "sg:phone":"+34 944 95 89 91",
    "sg:postcode":"48920",
    "sg:province":"Vizcaya",
    "wof:name":"Eusko Alkartasuna",
    "wof:placetype":"venue"
},
  "geometry": {"coordinates":[-3.0181353092,43.3211250305],"type":"Point"}
}