{
  "type": "Feature",
  "properties": {
    "iso:country":"ES",
    "sg:address":"Carrer de Eivissa, 15",
    "sg:city":"Cunit",
    "sg:orig_category":"Ense\u00d1ante, Direcci\u00d3n",
    "sg:phone":"+34 977 16 06 51",
    "sg:postcode":"43881",
    "sg:province":"Tarragona",
    "wof:name":"Gonzalez Exposito Cristina",
    "wof:placetype":"venue"
},
  "geometry": {"coordinates":[1.6190210581,41.1972694397],"type":"Point"}
}