{
  "type": "Feature",
  "properties": {
    "addr:full":"Cami Moli, Des, S/n S. Antoni Portmany Islas Baleares 07820",
    "addr:postcode":"07820",
    "addr:street":"S / N S. Antoni Portmany",
    "iso:country":"ES",
    "sg:address":"Cami Moli, Des, S/n",
    "sg:city":"S. Antoni Portmany",
    "sg:orig_category":"Plomeros",
    "sg:phone":"+34 971 34 21 72",
    "sg:postcode":"07820",
    "sg:province":"Islas Baleares",
    "wof:name":"Jamts C.b.",
    "wof:placetype":"venue"
},
  "geometry": {"coordinates":[1.5188339949,39.1094055176],"type":"Point"}
}