{
  "type": "Feature",
  "properties": {
    "addr:full":"Pl S. Francisco De Asis, 4 Estella Navarra 31200",
    "addr:housenumber":"4",
    "addr:postcode":"31200",
    "addr:street":"Pl S. Francisco De Asis",
    "iso:country":"ES",
    "sg:address":"Pl S. Francisco De Asis, 4",
    "sg:city":"Estella",
    "sg:orig_category":"Peluquer\u00cdas, Peluquer\u00cda Mixta",
    "sg:phone":"+34 948 55 47 62",
    "sg:postcode":"31200",
    "sg:province":"Navarra",
    "sg:website":"www.jamaformacion.com/puy",
    "wof:name":"Rodriguez Frechoso Virginia",
    "wof:placetype":"venue"
},
  "geometry": {"coordinates":[-2.0301189423,42.6705589294],"type":"Point"}
}