{
  "type": "Feature",
  "properties": {
    "addr:full":"Calle de Pe\u00d1a Castro, 1 Le\u00f3n Le\u00f3n 24008",
    "addr:housenumber":"1",
    "addr:postcode":"24008",
    "addr:street":"Calle De Pen\u0303A Castro;Leo\u0301N",
    "iso:country":"ES",
    "sg:address":"Calle de Pe\u00d1a Castro, 1",
    "sg:city":"Le\u00f3n",
    "sg:orig_category":"Peluquer\u00cdas, Peluquer\u00cda Mixta",
    "sg:phone":"+34 987 23 97 32",
    "sg:postcode":"24008",
    "sg:province":"Le\u00f3n",
    "wof:name":"Barrera Merino Maria Del Mar",
    "wof:placetype":"venue"
},
  "geometry": {"coordinates":[-5.5700058937,42.6155548096],"type":"Point"}
}