{
  "type": "Feature",
  "properties": {
    "iso:country":"ES",
    "sg:address":"Calle de Fika, 68",
    "sg:city":"Bilbao",
    "sg:orig_category":"Venta, Instalaci\u00d3n, Reparaci\u00d3n De Antenas Para Televisi\u00d3n",
    "sg:phone":"+34 944 33 75 88",
    "sg:postcode":"48004",
    "sg:province":"Vizcaya",
    "sg:website":"www.paginasamarillas.es",
    "wof:name":"Jasmar, C.b.",
    "wof:placetype":"venue"
},
  "geometry": {"coordinates":[-2.9161379337,43.2514839172],"type":"Point"}
}