{
  "type": "Feature",
  "properties": {
    "addr:full":"Calle de Felipe Asenjo, 49 Fuenlabrada Madrid 28947",
    "addr:housenumber":"49",
    "addr:postcode":"28947",
    "addr:street":"Calle De Felipe Asenjo",
    "iso:country":"ES",
    "sg:address":"Calle de Felipe Asenjo, 49",
    "sg:city":"Fuenlabrada",
    "sg:orig_category":"Rectificaci\u00d3n, Mecanizado, Fresado",
    "sg:phone":"+34 916 42 03 96",
    "sg:postcode":"28947",
    "sg:province":"Madrid",
    "wof:name":"Rubio Vaquero Guillermo",
    "wof:placetype":"venue"
},
  "geometry": {"coordinates":[-3.746694088,40.2585868835],"type":"Point"}
}