{
  "type": "Feature",
  "properties": {
    "iso:country":"ES",
    "sg:address":"Calle de Elche, 4",
    "sg:city":"Alcorcon",
    "sg:orig_category":"Instalaci\u00d3n De Aspiraci\u00d3n De Gases Y Humos",
    "sg:phone":"+34 916 43 34 28",
    "sg:postcode":"28922",
    "sg:province":"Madrid",
    "wof:name":"Indo-gas Sociedad Cooperativa Limitada",
    "wof:placetype":"venue"
},
  "geometry": {"coordinates":[-3.8289139271,40.3430786133],"type":"Point"}
}