{
  "type": "Feature",
  "properties": {
    "iso:country":"ES",
    "sg:address":"Pol Tecnol Armilla Ogijares, S/n",
    "sg:city":"Ogijares",
    "sg:orig_category":"Negocio De Madera",
    "sg:phone":"+34 958 50 71 44",
    "sg:postcode":"18151",
    "sg:province":"Granada",
    "wof:name":"Romero Hernandez Antonia",
    "wof:placetype":"venue"
},
  "geometry": {"coordinates":[-3.6051189899,37.1205368042],"type":"Point"}
}