{
  "type": "Feature",
  "properties": {
    "addr:full":"Casanova (celeiro), 13 Viveiro Lugo 27863",
    "addr:housenumber":"13",
    "addr:postcode":"27863",
    "iso:country":"ES",
    "sg:address":"Casanova (celeiro), 13",
    "sg:city":"Viveiro",
    "sg:orig_category":"Alimentaci\u00d3n General (al Por Menor)",
    "sg:phone":"+34 982 56 08 57",
    "sg:postcode":"27863",
    "sg:province":"Lugo",
    "wof:name":"Martinez Rua Laura",
    "wof:placetype":"venue"
},
  "geometry": {"coordinates":[-7.5347719193,43.6102027893],"type":"Point"}
}