{
  "type": "Feature",
  "properties": {
    "addr:full":"Avda Cristobal Colon, 18 Huelva Huelva 21002",
    "addr:housenumber":"18",
    "addr:postcode":"21002",
    "addr:street":"Avda Cristobal Colon",
    "iso:country":"ES",
    "sg:address":"Avda Cristobal Colon, 18",
    "sg:city":"Huelva",
    "sg:orig_category":"Farmacias",
    "sg:phone":"+34 959 24 18 25",
    "sg:postcode":"21002",
    "sg:province":"Huelva",
    "wof:name":"Martin Cartes Maria De Las Cintas",
    "wof:placetype":"venue"
},
  "geometry": {"coordinates":[-6.9517650604,37.2669944763],"type":"Point"}
}