{
  "type": "Feature",
  "properties": {
    "addr:full":"Calle de Republica Argentina, 2 Navalmoral Mata C\u00e1ceres 10300",
    "addr:housenumber":"2",
    "addr:postcode":"10300",
    "addr:street":"Calle De Republica Argentina;Ca\u0301Ceres",
    "iso:country":"ES",
    "sg:address":"Calle de Republica Argentina, 2",
    "sg:city":"Navalmoral Mata",
    "sg:orig_category":"Relojer\u00cda (al Por Menor, Reparaci\u00d3n)",
    "sg:phone":"+34 927 53 08 85",
    "sg:postcode":"10300",
    "sg:province":"C\u00e1ceres",
    "wof:name":"Liron Alvarez Antonio",
    "wof:placetype":"venue"
},
  "geometry": {"coordinates":[-5.5437488556,39.8900566101],"type":"Point"}
}