{
  "type": "Feature",
  "properties": {
    "addr:full":"Avda Maria Auxiliadora, 65 Rota C\u00e1diz 11520",
    "addr:housenumber":"65",
    "addr:postcode":"11520",
    "addr:street":"Avda Maria Auxiliadora;Ca\u0301Diz",
    "iso:country":"ES",
    "sg:address":"Avda Maria Auxiliadora, 65",
    "sg:city":"Rota",
    "sg:orig_category":"Centros Empresariales",
    "sg:phone":"+34 956 81 40 86",
    "sg:postcode":"11520",
    "sg:province":"C\u00e1diz",
    "wof:name":"Lilopa S.l.",
    "wof:placetype":"venue"
},
  "geometry": {"coordinates":[-6.3638491631,36.6251983643],"type":"Point"}
}