{
  "type": "Feature",
  "properties": {
    "addr:full":"Cami Sant Cebria, S/n Barcelona Barcelona 08035",
    "addr:housenumber":"s",
    "addr:postcode":"08035",
    "addr:street":"Cebria;/ N",
    "iso:country":"ES",
    "sg:address":"Cami Sant Cebria, S/n",
    "sg:city":"Barcelona",
    "sg:orig_category":"Restaurantes",
    "sg:phone":"+34 934 28 03 01",
    "sg:postcode":"08035",
    "sg:province":"Barcelona",
    "wof:name":"Can Travi Nou S.l",
    "wof:placetype":"venue"
},
  "geometry": {"coordinates":[2.1522989273,41.430480957],"type":"Point"}
}