{
  "type": "Feature",
  "properties": {
    "addr:full":"Calle de Milagrosa, 2 Cintruenigo Navarra 31592",
    "addr:housenumber":"2",
    "addr:postcode":"31592",
    "addr:street":"Calle De Milagrosa",
    "iso:country":"ES",
    "sg:address":"Calle de Milagrosa, 2",
    "sg:city":"Cintruenigo",
    "sg:orig_category":"Peluquer\u00cdas, Peluquer\u00cda Mixta",
    "sg:phone":"+34 948 81 26 10",
    "sg:postcode":"31592",
    "sg:province":"Navarra",
    "wof:name":"Bea Jimenez Jose Antonio",
    "wof:placetype":"venue"
},
  "geometry": {"coordinates":[-1.8056440353,42.0793418884],"type":"Point"}
}