{
  "type": "Feature",
  "properties": {
    "iso:country":"ES",
    "sg:address":"Calle de Londres, 4",
    "sg:city":"Valdemoro",
    "sg:orig_category":"Empresas De Carpinter\u00cda De Madera",
    "sg:phone":"+34 918 95 66 42",
    "sg:postcode":"28340",
    "sg:province":"Madrid",
    "wof:name":"Ebanisteria Herreros C.b",
    "wof:placetype":"venue"
},
  "geometry": {"coordinates":[-3.6848258972,40.2073440552],"type":"Point"}
}