{
  "type": "Feature",
  "properties": {
    "iso:country":"ES",
    "sg:address":"Carrer de Gabriel Miro, 32",
    "sg:city":"Pedreguer",
    "sg:orig_category":"Arquitectos",
    "sg:phone":"+34 965 76 05 65",
    "sg:postcode":"03750",
    "sg:province":"Alicante",
    "wof:name":"Miralles Mengual Joaquin",
    "wof:placetype":"venue"
},
  "geometry": {"coordinates":[0.0324839987,38.7966384888],"type":"Point"}
}