{
  "type": "Feature",
  "properties": {
    "iso:country":"ES",
    "sg:address":"Calle de Crsta V. Martinez Morella, 3",
    "sg:city":"Alacant",
    "sg:orig_category":"Molduras, Junquillos, Listones Y Molduras Perforadas",
    "sg:phone":"+34 965 18 12 32",
    "sg:postcode":"03015",
    "sg:province":"Alicante",
    "wof:name":"Bruno Soriano Prieto Y Otro C.b.",
    "wof:placetype":"venue"
},
  "geometry": {"coordinates":[-0.4643906057,38.4788208008],"type":"Point"}
}