{
  "type": "Feature",
  "properties": {
    "addr:full":"Calle de Alangobarri, 3 Getxo Vizcaya 48990",
    "addr:housenumber":"3",
    "addr:postcode":"48990",
    "addr:street":"Calle De Alangobarri",
    "iso:country":"ES",
    "sg:address":"Calle de Alangobarri, 3",
    "sg:city":"Getxo",
    "sg:orig_category":"Pescader\u00cdas (al Por Menor)",
    "sg:phone":"+34 944 91 09 30",
    "sg:postcode":"48990",
    "sg:province":"Vizcaya",
    "wof:name":"Belleza E Imagen Amezti",
    "wof:placetype":"venue"
},
  "geometry": {"coordinates":[-3.0096139908,43.3479156494],"type":"Point"}
}