{
  "type": "Feature",
  "properties": {
    "iso:country":"ES",
    "sg:address":"Apeadeiro, S/n",
    "sg:city":"Cambre",
    "sg:orig_category":"Reposter\u00cdas",
    "sg:phone":"+34 981 67 60 35",
    "sg:postcode":"15650",
    "sg:province":"La Coru\u00f1a",
    "wof:name":"Diaz Iglesias Ramiro",
    "wof:placetype":"venue"
},
  "geometry": {"coordinates":[-8.3069343567,43.2885551453],"type":"Point"}
}