{
  "type": "Feature",
  "properties": {
    "addr:full":"Plaz Mediterraneo, 6 Aranda Duero Burgos 09400",
    "addr:housenumber":"6",
    "addr:postcode":"09400",
    "addr:street":"Plaz Mediterraneo",
    "iso:country":"ES",
    "sg:address":"Plaz Mediterraneo, 6",
    "sg:city":"Aranda Duero",
    "sg:orig_category":"Internados & Ense\u00d1anza Privada",
    "sg:phone":"+34 947 54 60 54",
    "sg:postcode":"09400",
    "sg:province":"Burgos",
    "wof:name":"Gabinete Internacional De Renovacion Educativa S.a.",
    "wof:placetype":"venue"
},
  "geometry": {"coordinates":[-3.6889948845,41.6699256897],"type":"Point"}
}