{
  "type": "Feature",
  "properties": {
    "iso:country":"ES",
    "sg:address":"Pso Malecon (p I El Malecon), Km. 0022,0",
    "sg:city":"San Jose Rinconada",
    "sg:orig_category":"Muebles, Minoristas",
    "sg:phone":"+34 955 79 12 27",
    "sg:postcode":"41300",
    "sg:province":"Sevilla",
    "wof:name":"Duomo San Jose S.l.",
    "wof:placetype":"venue"
},
  "geometry": {"coordinates":[-5.9507889748,37.4823112488],"type":"Point"}
}