{
  "type": "Feature",
  "properties": {
    "iso:country":"ES",
    "sg:address":"Avda Vegas Altas, 48",
    "sg:city":"Don Benito",
    "sg:orig_category":"Inmobiliaria (agencias)",
    "sg:phone":"+34 924 80 84 33",
    "sg:postcode":"06400",
    "sg:province":"Badajoz",
    "wof:name":"Inmobiliaria Botoehs S.l.",
    "wof:placetype":"venue"
},
  "geometry": {"coordinates":[-5.8300590515,38.9641304016],"type":"Point"}
}