{
  "type": "Feature",
  "properties": {
    "iso:country":"ES",
    "sg:address":"Calle de Viteri, 2",
    "sg:city":"Errenteria",
    "sg:orig_category":"Inmobiliaria (agencias)",
    "sg:phone":"+34 943 52 36 04",
    "sg:postcode":"20100",
    "sg:province":"Guip\u00f9zcoa",
    "wof:name":"Fernandez Barreiro Coro",
    "wof:placetype":"venue"
},
  "geometry": {"coordinates":[-1.898630023,43.3131980896],"type":"Point"}
}