{
  "type": "Feature",
  "properties": {
    "addr:full":"Calle de Cruces, 32 Fuensalida Toledo 45510",
    "addr:housenumber":"32",
    "addr:postcode":"45510",
    "addr:street":"Calle De Cruces",
    "iso:country":"ES",
    "sg:address":"Calle de Cruces, 32",
    "sg:city":"Fuensalida",
    "sg:orig_category":"Mercados De Productos Alimenticios",
    "sg:phone":"+34 925 78 59 02",
    "sg:postcode":"45510",
    "sg:province":"Toledo",
    "wof:name":"Gonzalez Garcia Ricardo",
    "wof:placetype":"venue"
},
  "geometry": {"coordinates":[-4.2120203972,40.0523452759],"type":"Point"}
}