{
  "type": "Feature",
  "properties": {
    "addr:full":"Carr Virtut, 42 Igualada Barcelona 08700",
    "addr:housenumber":"42",
    "addr:postcode":"08700",
    "addr:street":"Carr Virtut",
    "iso:country":"ES",
    "sg:address":"Carr Virtut, 42",
    "sg:city":"Igualada",
    "sg:orig_category":"Inform\u00c1tica (estudios, Servicios, Asesor\u00cda, Formaci\u00d3n)",
    "sg:phone":"+34 938 04 48 11",
    "sg:postcode":"08700",
    "sg:province":"Barcelona",
    "wof:name":"Expocomputer S.a.",
    "wof:placetype":"venue"
},
  "geometry": {"coordinates":[1.624284029,41.5777168274],"type":"Point"}
}