{
  "type": "Feature",
  "properties": {
    "addr:full":"Ctra. Vitoria, S/n Etxarri-aranatz Navarra 31820",
    "addr:housenumber":"s / n",
    "addr:postcode":"31820",
    "addr:street":"Ctra. Vitoria",
    "iso:country":"ES",
    "sg:address":"Ctra. Vitoria, S/n",
    "sg:city":"Etxarri-aranatz",
    "sg:orig_category":"Mec\u00c1nico Del Autom\u00d3vil",
    "sg:phone":"+34 948 46 03 54",
    "sg:postcode":"31820",
    "sg:province":"Navarra",
    "wof:name":"Villarroel Hernandez Quintin",
    "wof:placetype":"venue"
},
  "geometry": {"coordinates":[-2.0638840199,42.9061965942],"type":"Point"}
}