{
  "type": "Feature",
  "properties": {
    "iso:country":"ES",
    "sg:address":"Calle de San Antonio Abad, 46",
    "sg:city":"Zaragoza",
    "sg:orig_category":"Mercer\u00cda, Lencer\u00cda (al Por Menor)",
    "sg:phone":"+34 976 53 49 81",
    "sg:postcode":"50010",
    "sg:province":"Zaragoza",
    "wof:name":"Perez Chueca Rosa Maria",
    "wof:placetype":"venue"
},
  "geometry": {"coordinates":[-0.9068949819,41.6547584534],"type":"Point"}
}