{
  "type": "Feature",
  "properties": {
    "addr:full":"Trva Union, 26 Valdepe\u00f1as Ciudad Real 13300",
    "addr:housenumber":"26",
    "addr:postcode":"13300",
    "addr:street":"Trva Union",
    "iso:country":"ES",
    "sg:address":"Trva Union, 26",
    "sg:city":"Valdepe\u00f1as",
    "sg:orig_category":"Chapister\u00cda",
    "sg:phone":"+34 926 32 20 44",
    "sg:postcode":"13300",
    "sg:province":"Ciudad Real",
    "wof:name":"Martinez Perez Manuel",
    "wof:placetype":"venue"
},
  "geometry": {"coordinates":[-3.3854401112,38.7644004822],"type":"Point"}
}