{
  "type": "Feature",
  "properties": {
    "iso:country":"ES",
    "sg:address":"Calle de Linajes (los), 2",
    "sg:city":"Soria",
    "sg:orig_category":"Arquitectos",
    "sg:phone":"+34 975 23 11 85",
    "sg:postcode":"42003",
    "sg:province":"Soria",
    "wof:name":"Lopez De La Morena Maximo",
    "wof:placetype":"venue"
},
  "geometry": {"coordinates":[-2.4699959755,41.7626266479],"type":"Point"}
}