{
  "type": "Feature",
  "properties": {
    "iso:country":"ES",
    "sg:address":"Calle de Juan Xxiii, 3",
    "sg:city":"Santurtzi",
    "sg:orig_category":"Inmobiliaria (agencias)",
    "sg:phone":"+34 944 83 36 19",
    "sg:postcode":"48980",
    "sg:province":"Vizcaya",
    "wof:name":"Abaitua Ibarra Ramon Maria",
    "wof:placetype":"venue"
},
  "geometry": {"coordinates":[-3.03398,43.330299],"type":"Point"}
}