{
  "type": "Feature",
  "properties": {
    "iso:country":"ES",
    "sg:address":"Calle de San Pedro, S/n",
    "sg:city":"Pozuelo",
    "sg:orig_category":"Farmacias",
    "sg:phone":"+34 967 36 37 53",
    "sg:postcode":"02327",
    "sg:province":"Albacete",
    "wof:name":"Abellan Maxia Maria Isabel",
    "wof:placetype":"venue"
},
  "geometry": {"coordinates":[-2.100405,38.807297],"type":"Point"}
}