{
  "type": "Feature",
  "properties": {
    "addr:full":"Avda Villajoyosa, 95 Alacant Alicante 03016",
    "addr:housenumber":"95",
    "addr:postcode":"03016",
    "addr:street":"Avda Villajoyosa",
    "iso:country":"ES",
    "sg:address":"Avda Villajoyosa, 95",
    "sg:city":"Alacant",
    "sg:orig_category":"Alimentaci\u00d3n General (al Por Menor)",
    "sg:phone":"+34 965 26 51 45",
    "sg:postcode":"03016",
    "sg:province":"Alicante",
    "wof:name":"Stabile  Daniel Gustavo",
    "wof:placetype":"venue"
},
  "geometry": {"coordinates":[-0.4513700008,38.3606071472],"type":"Point"}
}