{
  "type": "Feature",
  "properties": {
    "addr:full":"Av Comarques Catalanes, 22 Mora D'ebre Tarragona 43740",
    "addr:housenumber":"22",
    "addr:postcode":"43740",
    "addr:street":"Av Comarques Catalanes;D'Ebre",
    "iso:country":"ES",
    "sg:address":"Av Comarques Catalanes, 22",
    "sg:city":"Mora D'ebre",
    "sg:orig_category":"Arquitectos",
    "sg:phone":"+34 977 40 26 98",
    "sg:postcode":"43740",
    "sg:province":"Tarragona",
    "wof:name":"Poyo Perello Rosa Maria",
    "wof:placetype":"venue"
},
  "geometry": {"coordinates":[1.2540999651,41.1169281006],"type":"Point"}
}