{
  "type": "Feature",
  "properties": {
    "iso:country":"ES",
    "sg:address":"Calle de Nueva De San Bernardo, 3",
    "sg:city":"Salamanca",
    "sg:orig_category":"Mec\u00c1nico Del Autom\u00d3vil",
    "sg:phone":"+34 923 26 82 55",
    "sg:postcode":"37007",
    "sg:province":"Salamanca",
    "wof:name":"Auto Salamanca S.a.",
    "wof:placetype":"venue"
},
  "geometry": {"coordinates":[-5.6695423126,40.9670906067],"type":"Point"}
}