{
  "type": "Feature",
  "properties": {
    "iso:country":"ES",
    "sg:address":"Ipar Kalea, 13",
    "sg:city":"Zarautz",
    "sg:orig_category":"Molduras, Junquillos, Listones Y Molduras Perforadas",
    "sg:phone":"+34 943 13 42 36",
    "sg:postcode":"20800",
    "sg:province":"Guip\u00f9zcoa",
    "wof:name":"Sanchez Sirvent Jose Luis",
    "wof:placetype":"venue"
},
  "geometry": {"coordinates":[-2.176076889,43.2863693237],"type":"Point"}
}