{
  "type": "Feature",
  "properties": {
    "iso:country":"ES",
    "sg:address":"Calle de Boqueron, S/n",
    "sg:city":"Marbella",
    "sg:orig_category":"Papeler\u00cdas, Librer\u00cdas",
    "sg:phone":"+34 952 82 82 78",
    "sg:postcode":"29600",
    "sg:province":"M\u00e1laga",
    "wof:name":"Gomez Jimenez Miguel",
    "wof:placetype":"venue"
},
  "geometry": {"coordinates":[-4.882502079,36.512840271],"type":"Point"}
}