{
  "type": "Feature",
  "properties": {
    "iso:country":"ES",
    "sg:address":"C/ Alfonso Xii, 16",
    "sg:city":"Elche",
    "sg:orig_category":"Arquitectos",
    "sg:phone":"+34 965 42 07 46",
    "sg:postcode":"03203",
    "sg:province":"Alicante",
    "wof:name":"Amoros Perez Maria Del Pilar",
    "wof:placetype":"venue"
},
  "geometry": {"coordinates":[-0.6993222833,38.2645606995],"type":"Point"}
}