{
  "type": "Feature",
  "properties": {
    "addr:full":"Calle de Real, S/n Pto Real C\u00e1diz 11510",
    "addr:housenumber":"s / n",
    "addr:postcode":"11510",
    "addr:street":"Calle De Real;Pto;Ca\u0301Diz",
    "iso:country":"ES",
    "sg:address":"Calle de Real, S/n",
    "sg:city":"Pto Real",
    "sg:orig_category":"Asociaciones Humanitarias, De Cooperaci\u00d3n, De Acci\u00d3n Social",
    "sg:phone":"+34 956 83 77 97",
    "sg:postcode":"11510",
    "sg:province":"C\u00e1diz",
    "wof:name":"Federacion Provincial De Minusvalidos Fisicos De Cadiz",
    "wof:placetype":"venue"
},
  "geometry": {"coordinates":[-6.1974492073,36.5309562683],"type":"Point"}
}