{
  "type": "Feature",
  "properties": {
    "iso:country":"ES",
    "sg:address":"Calle de Venecia, 2",
    "sg:city":"Sevilla",
    "sg:orig_category":"Estancos",
    "sg:phone":"+34 954 53 60 59",
    "sg:postcode":"41008",
    "sg:province":"Sevilla",
    "wof:name":"Abascal Diego Rosario",
    "wof:placetype":"venue"
},
  "geometry": {"coordinates":[-5.979868,37.39484],"type":"Point"}
}