{
  "type": "Feature",
  "properties": {
    "addr:full":"Calle de General Lacy, 12 Alacant Alicante 03003",
    "addr:housenumber":"12",
    "addr:postcode":"03003",
    "addr:street":"Calle De General Lacy",
    "iso:country":"ES",
    "sg:address":"Calle de General Lacy, 12",
    "sg:city":"Alacant",
    "sg:orig_category":"Medicamentos",
    "sg:phone":"+34 965 13 07 60",
    "sg:postcode":"03003",
    "sg:province":"Alicante",
    "wof:name":"Canales Mira Conchita",
    "wof:placetype":"venue"
},
  "geometry": {"coordinates":[-0.4921000004,38.3449554443],"type":"Point"}
}