{
  "type": "Feature",
  "properties": {
    "iso:country":"ES",
    "sg:address":"Ctra Almike, 8",
    "sg:city":"Almike",
    "sg:orig_category":"Barbacoas Y Accesorios",
    "sg:phone":"+34 946 88 09 25",
    "sg:postcode":"48370",
    "sg:province":"Vizcaya",
    "wof:name":"Hormaechea Alboniga-menor Maria Jesus",
    "wof:placetype":"venue"
},
  "geometry": {"coordinates":[-2.7251009941,43.41929245],"type":"Point"}
}