{
  "type": "Feature",
  "properties": {
    "addr:full":"Calle de Santa Rosa, 7 Compostilla Le\u00f3n 24400",
    "addr:housenumber":"7",
    "addr:postcode":"24400",
    "addr:street":"Calle De Santa Rosa;Leo\u0301N",
    "iso:country":"ES",
    "sg:address":"Calle de Santa Rosa, 7",
    "sg:city":"Compostilla",
    "sg:orig_category":"Peluqueros: De Se\u00d1oras",
    "sg:phone":"+34 987 40 24 50",
    "sg:postcode":"24400",
    "sg:province":"Le\u00f3n",
    "wof:name":"Villanueva Barredo Maria Del Carmen",
    "wof:placetype":"venue"
},
  "geometry": {"coordinates":[-6.6004748344,42.5651168823],"type":"Point"}
}