{
  "type": "Feature",
  "properties": {
    "iso:country":"ES",
    "sg:address":"Calle de Ontinyent, 3",
    "sg:city":"Valencia",
    "sg:orig_category":"Electrodom\u00c9sticos (al Por Menor)",
    "sg:phone":"+34 963 84 80 00",
    "sg:postcode":"46008",
    "sg:province":"Valencia",
    "wof:name":"Electrodomesticos Pinedo S. A.",
    "wof:placetype":"venue"
},
  "geometry": {"coordinates":[-0.3893019855,39.4673995972],"type":"Point"}
}