{
  "type": "Feature",
  "properties": {
    "addr:full":"Calle de Molino Tenoya El, 46 Tenoya Las Palmas 35018",
    "addr:housenumber":"46",
    "addr:postcode":"35018",
    "addr:street":"Calle De Molino Tenoya El;Palmas",
    "iso:country":"ES",
    "sg:address":"Calle de Molino Tenoya El, 46",
    "sg:city":"Tenoya",
    "sg:orig_category":"Costura (alta Costura, Creaci\u00d3n)",
    "sg:phone":"+34 928 67 27 98",
    "sg:postcode":"35018",
    "sg:province":"Las Palmas",
    "wof:name":"David Henriquez Alvaro",
    "wof:placetype":"venue"
},
  "geometry": {"coordinates":[-15.4934215546,28.1144199371],"type":"Point"}
}