{
  "type": "Feature",
  "properties": {
    "iso:country":"ES",
    "sg:address":"Carrer de Carretera Bunyola, 7",
    "sg:city":"Prat Llobregat",
    "sg:orig_category":"Pizzer\u00cdas",
    "sg:phone":"+34 933 70 43 28",
    "sg:postcode":"08820",
    "sg:province":"Barcelona",
    "wof:name":"Campoy Ramirez Lucia",
    "wof:placetype":"venue"
},
  "geometry": {"coordinates":[2.0864720345,41.3289909363],"type":"Point"}
}