{
  "type": "Feature",
  "properties": {
    "addr:full":"Calle de Jose Picon, 29 Madrid Madrid 28028",
    "addr:housenumber":"29",
    "addr:postcode":"madrid;28028",
    "addr:street":"Calle De Jose Picon",
    "iso:country":"ES",
    "sg:address":"Calle de Jose Picon, 29",
    "sg:city":"Madrid",
    "sg:orig_category":"Tapicer\u00cdas",
    "sg:phone":"+34 913 56 95 22",
    "sg:postcode":"28028",
    "sg:province":"Madrid",
    "wof:name":"Gonzalez Gimenez Florentino",
    "wof:placetype":"venue"
},
  "geometry": {"coordinates":[-3.6713960171,40.4358406067],"type":"Point"}
}