{
  "type": "Feature",
  "properties": {
    "iso:country":"ES",
    "sg:address":"Calle de Heroe De Sostoa, 51",
    "sg:city":"Malaga",
    "sg:orig_category":"Procuradores",
    "sg:phone":"+34 952 02 30 00",
    "sg:postcode":"29002",
    "sg:province":"M\u00e1laga",
    "wof:name":"Parra Delgado Eva Maria",
    "wof:placetype":"venue"
},
  "geometry": {"coordinates":[-4.4349141121,36.7081871033],"type":"Point"}
}