{
  "type": "Feature",
  "properties": {
    "addr:full":"Carr Sant Just, 6 Seu D'urgell Lleida 25700",
    "addr:housenumber":"6",
    "addr:postcode":"25700",
    "addr:street":"Carr Sant Just",
    "iso:country":"ES",
    "sg:address":"Carr Sant Just, 6",
    "sg:city":"Seu D'urgell",
    "sg:orig_category":"Deportes Diversos",
    "sg:phone":"+34 973 35 17 62",
    "sg:postcode":"25700",
    "sg:province":"Lleida",
    "wof:name":"Club D'esqui De Fons Urgellet I Cerdanya",
    "wof:placetype":"venue"
},
  "geometry": {"coordinates":[0.6457189918,41.6027946472],"type":"Point"}
}