{
  "type": "Feature",
  "properties": {
    "addr:full":"Calle de Sanclemente, 6 Zaragoza Zaragoza 50001",
    "addr:housenumber":"6",
    "addr:postcode":"50001",
    "addr:street":"Calle De Sanclemente",
    "iso:country":"ES",
    "sg:address":"Calle de Sanclemente, 6",
    "sg:city":"Zaragoza",
    "sg:orig_category":"\u00d3ptica: Instrumentos (fabricaci\u00d3n)",
    "sg:phone":"+34 976 21 04 95",
    "sg:postcode":"50001",
    "sg:province":"Zaragoza",
    "wof:name":"Manzano Matia Maria Soledad",
    "wof:placetype":"venue"
},
  "geometry": {"coordinates":[-0.8822540045,41.6496772766],"type":"Point"}
}