{
  "type": "Feature",
  "properties": {
    "addr:full":"Ctra Bacarot, 38 Bacarot Alicante 03114",
    "addr:housenumber":"38",
    "addr:postcode":"03114",
    "addr:street":"Ctra Bacarot",
    "iso:country":"ES",
    "sg:address":"Ctra Bacarot, 38",
    "sg:city":"Bacarot",
    "sg:orig_category":"Goma: Productos De Uso Industrial (fabricaci\u00d3n, Al Por Mayor)",
    "sg:phone":"+34 965 28 69 44",
    "sg:postcode":"03114",
    "sg:province":"Alicante",
    "wof:name":"Francisco Casta\u00f1o Pomares S.a.",
    "wof:placetype":"venue"
},
  "geometry": {"coordinates":[-0.5572689772,38.3214912415],"type":"Point"}
}