{
  "type": "Feature",
  "properties": {
    "addr:full":"Avda Bellavista, 8 Algeciras C\u00e1diz 11205",
    "addr:housenumber":"8;ca\u0301diz",
    "addr:postcode":"11205",
    "addr:street":"Avda Bellavista",
    "iso:country":"ES",
    "sg:address":"Avda Bellavista, 8",
    "sg:city":"Algeciras",
    "sg:orig_category":"Peluqueros: De Se\u00d1oras",
    "sg:phone":"+34 956 63 33 25",
    "sg:postcode":"11205",
    "sg:province":"C\u00e1diz",
    "wof:name":"Rodriguez Camacho Maria Luisa",
    "wof:placetype":"venue"
},
  "geometry": {"coordinates":[-5.4572439194,36.1463127136],"type":"Point"}
}