{
  "type": "Feature",
  "properties": {
    "iso:country":"ES",
    "sg:address":"Calle de Principe Felipe, 2",
    "sg:city":"Guijuelo",
    "sg:orig_category":"Alquiler De V\u00cddeo",
    "sg:phone":"+34 923 58 09 59",
    "sg:postcode":"37770",
    "sg:province":"Salamanca",
    "wof:name":"2syb Video 24 S.l.",
    "wof:placetype":"venue"
},
  "geometry": {"coordinates":[-5.673508,40.555099],"type":"Point"}
}