{
  "type": "Feature",
  "properties": {
    "addr:full":"Calle de Manuel Mendez, 6 Ca\u00f1izares Cuenca 16891",
    "addr:housenumber":"6",
    "addr:postcode":"16891",
    "addr:street":"Calle De Manuel Mendez",
    "iso:country":"ES",
    "sg:address":"Calle de Manuel Mendez, 6",
    "sg:city":"Ca\u00f1izares",
    "sg:orig_category":"Carnicer\u00cdas, Carnicer\u00cdas",
    "sg:phone":"+34 969 31 31 17",
    "sg:postcode":"16891",
    "sg:province":"Cuenca",
    "wof:name":"Lopez Garcia Fernando",
    "wof:placetype":"venue"
},
  "geometry": {"coordinates":[-2.1910839081,40.5188903809],"type":"Point"}
}