{
  "type": "Feature",
  "properties": {
    "iso:country":"ES",
    "sg:address":"Carrer de Prat, 7",
    "sg:city":"Hospitalet Llobregat",
    "sg:orig_category":"Reposter\u00cdas",
    "sg:phone":"+34 932 61 82 74",
    "sg:postcode":"08907",
    "sg:province":"Barcelona",
    "wof:name":"Mota Alvarez Maria De Los Angeles",
    "wof:placetype":"venue"
},
  "geometry": {"coordinates":[2.1065859795,41.3516082764],"type":"Point"}
}