{
  "type": "Feature",
  "properties": {
    "addr:full":"Baricentre (centre Comercial), S/n Barbera Valles Barcelona 08210",
    "addr:housenumber":"s / n",
    "addr:postcode":"08210",
    "addr:street":"Comercial",
    "iso:country":"ES",
    "sg:address":"Baricentre (centre Comercial), S/n",
    "sg:city":"Barbera Valles",
    "sg:orig_category":"Electrodom\u00c9sticos (al Por Menor)",
    "sg:phone":"+34 937 18 20 96",
    "sg:postcode":"08210",
    "sg:province":"Barcelona",
    "sg:website":"www.redelite.es",
    "wof:name":"Electro Calbet S.a.",
    "wof:placetype":"venue"
},
  "geometry": {"coordinates":[2.1271760464,41.5150566101],"type":"Point"}
}