{
  "type": "Feature",
  "properties": {
    "iso:country":"ES",
    "sg:address":"Calle de General Millan Astray, 5",
    "sg:city":"Madrid",
    "sg:orig_category":"Puertas Y Portales",
    "sg:phone":"+34 917 05 83 38",
    "sg:postcode":"28044",
    "sg:province":"Madrid",
    "wof:name":"Puertas Madera Elma S.l.",
    "wof:placetype":"venue"
},
  "geometry": {"coordinates":[-3.7669520378,40.3793296814],"type":"Point"}
}