{
  "type": "Feature",
  "properties": {
    "iso:country":"ES",
    "sg:address":"Calle de Mayor, 141",
    "sg:city":"Garrucha",
    "sg:orig_category":"Agencias De Viajes",
    "sg:phone":"+34 902 10 99 00",
    "sg:postcode":"04630",
    "sg:province":"Almer\u00eda",
    "sg:website":"www.mojacar-reservas.com",
    "wof:name":"Viajes Indaltour",
    "wof:placetype":"venue"
},
  "geometry": {"coordinates":[-1.8232610226,37.1742248535],"type":"Point"}
}