{
  "type": "Feature",
  "properties": {
    "iso:country":"ES",
    "sg:address":"Naves, S/n",
    "sg:city":"Naves",
    "sg:orig_category":"Mec\u00c1nico Del Autom\u00d3vil",
    "sg:phone":"+34 985 40 77 36",
    "sg:postcode":"33594",
    "sg:province":"Asturias",
    "wof:name":"Talleres Amor C.b.",
    "wof:placetype":"venue"
},
  "geometry": {"coordinates":[-4.8924798965,43.4417533875],"type":"Point"}
}