{
  "type": "Feature",
  "properties": {
    "addr:full":"Carrer de Espigolera, 3 S. Just Desvern Barcelona 08960",
    "addr:housenumber":"3",
    "addr:postcode":"08960",
    "addr:street":"Carrer De Espigolera",
    "iso:country":"ES",
    "sg:address":"Carrer de Espigolera, 3",
    "sg:city":"S. Just Desvern",
    "sg:orig_category":"Art\u00cdculos De Limpieza Y De Cocina (fabricaci\u00d3n, Al Por Mayor)",
    "sg:phone":"+34 934 73 99 41",
    "sg:postcode":"08960",
    "sg:province":"Barcelona",
    "sg:website":"www.portotecnica.com",
    "wof:name":"Aspiradores Industriales Soteco S.l.",
    "wof:placetype":"venue"
},
  "geometry": {"coordinates":[2.0598428249,41.3834075928],"type":"Point"}
}