{
  "type": "Feature",
  "properties": {
    "iso:country":"ES",
    "sg:address":"Calle de Fragata, 1",
    "sg:city":"Almerimar",
    "sg:orig_category":"Supermercados Y Hipermercados",
    "sg:phone":"+34 950 60 78 81",
    "sg:postcode":"04711",
    "sg:province":"Almer\u00eda",
    "sg:website":"www.mercadona.es",
    "wof:name":"Mercadona S.a.",
    "wof:placetype":"venue"
},
  "geometry": {"coordinates":[-2.788654089,36.6992645264],"type":"Point"}
}