{
  "type": "Feature",
  "properties": {
    "addr:full":"Carrer de Vilamar, 9 Playa De Calafell Tarragona 43820",
    "addr:housenumber":"9",
    "addr:postcode":"43820",
    "addr:street":"Carrer De Vilamar",
    "iso:country":"ES",
    "sg:address":"Carrer de Vilamar, 9",
    "sg:city":"Playa De Calafell",
    "sg:orig_category":"Ropa Para Se\u00d1oras (al Por Menor)",
    "sg:phone":"+34 977 69 38 38",
    "sg:postcode":"43820",
    "sg:province":"Tarragona",
    "wof:name":"Vanessa Duque S.l.",
    "wof:placetype":"venue"
},
  "geometry": {"coordinates":[1.5684100389,41.1977844238],"type":"Point"}
}