{
  "type": "Feature",
  "properties": {
    "iso:country":"ES",
    "sg:address":"Calle de Pleyades (las), 44",
    "sg:city":"Zaragoza",
    "sg:orig_category":"Inform\u00c1tica, Ofim\u00c1tica (estudios, Asesor\u00cda, Ingenier\u00cda, Formaci\u00d3n)",
    "sg:phone":"+34 976 75 34 66",
    "sg:postcode":"50012",
    "sg:province":"Zaragoza",
    "wof:name":"Marti Uson Rita",
    "wof:placetype":"venue"
},
  "geometry": {"coordinates":[-0.9371389747,41.6406288147],"type":"Point"}
}