{
  "type": "Feature",
  "properties": {
    "iso:country":"ES",
    "sg:address":"Calle de San Borondon, S/n",
    "sg:city":"Playa Honda",
    "sg:orig_category":"Alquiler De V\u00cddeo",
    "sg:phone":"+34 928 82 19 42",
    "sg:postcode":"35509",
    "sg:province":"Las Palmas",
    "wof:name":"Puntalmatic S.l.",
    "wof:placetype":"venue"
},
  "geometry": {"coordinates":[-13.587433815,28.9538898468],"type":"Point"}
}