{
  "type": "Feature",
  "properties": {
    "iso:country":"ES",
    "sg:address":"Rua Seixalbo (de), 1",
    "sg:city":"Seixalbo",
    "sg:orig_category":"Mec\u00c1nico Del Autom\u00d3vil",
    "sg:phone":"+34 988 22 53 34",
    "sg:postcode":"32970",
    "sg:province":"Ourense",
    "wof:name":"Aleman Taller Mecanico S.l.",
    "wof:placetype":"venue"
},
  "geometry": {"coordinates":[-7.8646407127,42.340007782],"type":"Point"}
}