{
  "type": "Feature",
  "properties": {
    "iso:country":"ES",
    "sg:address":"Vilar-vilalonga, 4",
    "sg:city":"Vilar",
    "sg:orig_category":"Art\u00cdculos Funerarios (al Por Menor)",
    "sg:phone":"+34 986 74 54 89",
    "sg:postcode":"36990",
    "sg:province":"Pontevedra",
    "wof:name":"Agencia Funeraria Las Angustias S.l.",
    "wof:placetype":"venue"
},
  "geometry": {"coordinates":[-8.4517526627,42.7405128479],"type":"Point"}
}