{
  "type": "Feature",
  "properties": {
    "iso:country":"ES",
    "sg:address":"Calle de San Fernando, 51",
    "sg:city":"Lora Rio",
    "sg:orig_category":"Doctores En Medicina",
    "sg:phone":"+34 955 80 34 88",
    "sg:postcode":"41440",
    "sg:province":"Sevilla",
    "wof:name":"Gomez Cosano Manuel",
    "wof:placetype":"venue"
},
  "geometry": {"coordinates":[-5.5275449753,37.6541786194],"type":"Point"}
}