{
  "type": "Feature",
  "properties": {
    "addr:full":"Po. Ind Corts, 6 Cabrera Mar Barcelona 08349",
    "addr:housenumber":"6",
    "addr:postcode":"08349",
    "addr:street":"Corts",
    "iso:country":"ES",
    "sg:address":"Po. Ind Corts, 6",
    "sg:city":"Cabrera Mar",
    "sg:orig_category":"Impresiones Sobre Tela",
    "sg:phone":"+34 937 56 60 59",
    "sg:postcode":"08349",
    "sg:province":"Barcelona",
    "wof:name":"Cynestamp Sl",
    "wof:placetype":"venue"
},
  "geometry": {"coordinates":[2.3933050632,41.5273513794],"type":"Point"}
}