{
  "type": "Feature",
  "properties": {
    "iso:country":"ES",
    "sg:address":"Plaz Constitucion, 2",
    "sg:city":"Teba",
    "sg:orig_category":"\u00d3ptica: Instrumentos (fabricaci\u00d3n)",
    "sg:phone":"+34 952 74 85 58",
    "sg:postcode":"29327",
    "sg:province":"M\u00e1laga",
    "wof:name":"Garcia Romera Marta De La Concepcion",
    "wof:placetype":"venue"
},
  "geometry": {"coordinates":[-4.9143238068,36.9600715637],"type":"Point"}
}