{
  "type": "Feature",
  "properties": {
    "addr:full":"Carr Fe, 4 Blanes Girona 17300",
    "addr:housenumber":"4",
    "addr:postcode":"17300",
    "addr:street":"Carr Fe",
    "iso:country":"ES",
    "sg:address":"Carr Fe, 4",
    "sg:city":"Blanes",
    "sg:orig_category":"Bisuter\u00cda, Joyer\u00cda, Relojer\u00cda (al Por Menor)",
    "sg:phone":"+34 972 33 15 98",
    "sg:postcode":"17300",
    "sg:province":"Girona",
    "wof:name":"Galvez Porras Francisco",
    "wof:placetype":"venue"
},
  "geometry": {"coordinates":[2.7906849384,41.6724243164],"type":"Point"}
}