{
  "type": "Feature",
  "properties": {
    "addr:full":"Plaz Fueros, 6 Ablitas Navarra 31523",
    "addr:housenumber":"6",
    "addr:postcode":"31523",
    "addr:street":"Plaz Fueros",
    "iso:country":"ES",
    "sg:address":"Plaz Fueros, 6",
    "sg:city":"Ablitas",
    "sg:orig_category":"Estancos",
    "sg:phone":"+34 948 81 36 95",
    "sg:postcode":"31523",
    "sg:province":"Navarra",
    "wof:name":"Laguardia Labarga Maria Villar",
    "wof:placetype":"venue"
},
  "geometry": {"coordinates":[-1.6404190063,41.9752693176],"type":"Point"}
}