{
  "type": "Feature",
  "properties": {
    "iso:country":"ES",
    "sg:address":"Calle de Arganda, 9",
    "sg:city":"Caserio De Perales",
    "sg:orig_category":"Grabados",
    "sg:phone":"+34 916 84 81 62",
    "sg:postcode":"28909",
    "sg:province":"Madrid",
    "wof:name":"Laviada Ingenieria Y Construcciones S.l.",
    "wof:placetype":"venue"
},
  "geometry": {"coordinates":[-3.3521981239,40.2345314026],"type":"Point"}
}