{
  "type": "Feature",
  "properties": {
    "addr:full":"Calle de Remigio Noriega, S/n Unquera Cantabria 39560",
    "addr:housenumber":"s / n",
    "addr:postcode":"39560",
    "addr:street":"Calle De Remigio Noriega",
    "iso:country":"ES",
    "sg:address":"Calle de Remigio Noriega, S/n",
    "sg:city":"Unquera",
    "sg:orig_category":"M\u00c9dicos: Estomatolog\u00cda",
    "sg:phone":"+34 942 71 72 76",
    "sg:postcode":"39560",
    "sg:province":"Cantabria",
    "wof:name":"Laso Garcia Manuel",
    "wof:placetype":"venue"
},
  "geometry": {"coordinates":[-4.5161833763,43.373878479],"type":"Point"}
}