{
  "type": "Feature",
  "properties": {
    "addr:full":"Adanero-gijon, 203 Urb. Monteleon Le\u00f3n 24196",
    "addr:housenumber":"203",
    "addr:postcode":"24196",
    "addr:street":"Adanero-Gijon;Urb. Monteleon Leo\u0301N",
    "iso:country":"ES",
    "sg:address":"Adanero-gijon, 203",
    "sg:city":"Urb. Monteleon",
    "sg:orig_category":"Transportes Por V\u00cdas Navegables",
    "sg:phone":"+34 987 28 41 39",
    "sg:postcode":"24196",
    "sg:province":"Le\u00f3n",
    "wof:name":"Trasportes Salagre S.l.",
    "wof:placetype":"venue"
},
  "geometry": {"coordinates":[-5.6067891121,42.6558914185],"type":"Point"}
}