{
  "type": "Feature",
  "properties": {
    "addr:full":"Carrer de General Llauder, 16 Argentona Barcelona 08310",
    "addr:housenumber":"16",
    "addr:postcode":"08310",
    "addr:street":"Carrer De General Llauder",
    "iso:country":"ES",
    "sg:address":"Carrer de General Llauder, 16",
    "sg:city":"Argentona",
    "sg:orig_category":"Cristaler\u00cdas",
    "sg:phone":"+34 937 56 09 26",
    "sg:postcode":"08310",
    "sg:province":"Barcelona",
    "wof:name":"Cristaleria Argentona S.l.",
    "wof:placetype":"venue"
},
  "geometry": {"coordinates":[2.4041550159,41.5546836853],"type":"Point"}
}