{
  "type": "Feature",
  "properties": {
    "iso:country":"ES",
    "sg:address":"Av. Berganti\u00f1os(paiosaco), 98",
    "sg:city":"Laracha",
    "sg:orig_category":"Muebles Y Accesorios Para Cocinas Y Cuartos De Ba\u00d1o (al Por Menor)",
    "sg:phone":"+34 981 60 63 52",
    "sg:postcode":"15145",
    "sg:province":"La Coru\u00f1a",
    "wof:name":"Castro Borrazas Francisco",
    "wof:placetype":"venue"
},
  "geometry": {"coordinates":[-8.5516586304,43.2559394836],"type":"Point"}
}