{
  "type": "Feature",
  "properties": {
    "iso:country":"ES",
    "sg:address":"Carrer de Germandat, 5",
    "sg:city":"Gandesa",
    "sg:orig_category":"Empresas De Desmonte",
    "sg:phone":"+34 977 42 03 48",
    "sg:postcode":"43780",
    "sg:province":"Tarragona",
    "wof:name":"Jornet Escute Rafael",
    "wof:placetype":"venue"
},
  "geometry": {"coordinates":[0.4377999902,41.053237915],"type":"Point"}
}