{
  "type": "Feature",
  "properties": {
    "addr:full":"Carretera Santander, Km. 0005,5 Villarrodrigo Regueras Le\u00f3n 24197",
    "addr:postcode":"24197",
    "addr:street":"Carretera Santander Km. 0005,5",
    "iso:country":"ES",
    "sg:address":"Carretera Santander, Km. 0005,5",
    "sg:city":"Villarrodrigo Regueras",
    "sg:orig_category":"Porcelanas, Azulejos (fabricaci\u00d3n, Al Por Mayor)",
    "sg:phone":"+34 987 28 16 58",
    "sg:postcode":"24197",
    "sg:province":"Le\u00f3n",
    "wof:name":"Ceramicas Hogar 2000 S.l.",
    "wof:placetype":"venue"
},
  "geometry": {"coordinates":[-5.5188531876,42.66147995],"type":"Point"}
}