{
  "type": "Feature",
  "properties": {
    "iso:country":"ES",
    "sg:address":"Poli Industrial Cagancha, 27",
    "sg:city":"Villanueva Serena",
    "sg:orig_category":"Mec\u00c1nico Del Autom\u00d3vil",
    "sg:phone":"+34 924 84 38 06",
    "sg:postcode":"06700",
    "sg:province":"Badajoz",
    "wof:name":"Talleres Occidente C.b.",
    "wof:placetype":"venue"
},
  "geometry": {"coordinates":[-5.8008708954,38.9688415527],"type":"Point"}
}