{
  "type": "Feature",
  "properties": {
    "addr:full":"Pase General Martinez Campos, 29 Madrid Madrid 28010",
    "addr:housenumber":"29",
    "addr:postcode":"madrid;28010",
    "iso:country":"ES",
    "sg:address":"Pase General Martinez Campos, 29",
    "sg:city":"Madrid",
    "sg:orig_category":"Limpieza De Alfombras",
    "sg:phone":"+34 913 08 50 00",
    "sg:postcode":"28010",
    "sg:province":"Madrid",
    "wof:name":"Alfombras Y Tapices Los Fernandez S.l.",
    "wof:placetype":"venue"
},
  "geometry": {"coordinates":[-3.6941885948,40.4351119995],"type":"Point"}
}