{
  "type": "Feature",
  "properties": {
    "iso:country":"ES",
    "sg:address":"Calle de Concepcion Arenal, S/n",
    "sg:city":"Guarda",
    "sg:orig_category":"Carnicer\u00cdas, Carnicer\u00cdas",
    "sg:phone":"+34 986 61 14 95",
    "sg:postcode":"36780",
    "sg:province":"Pontevedra",
    "wof:name":"Treinta Giraldez Alfonso",
    "wof:placetype":"venue"
},
  "geometry": {"coordinates":[-8.8705892563,41.9015350342],"type":"Point"}
}