{
  "type": "Feature",
  "properties": {
    "iso:country":"ES",
    "sg:address":"Avda Alemania (de), S/n",
    "sg:city":"Playa Del Ingles",
    "sg:orig_category":"Bisuter\u00cda, Joyer\u00cda, Relojer\u00cda (al Por Menor)",
    "sg:phone":"+34 928 72 01 05",
    "sg:postcode":"35100",
    "sg:province":"Las Palmas",
    "wof:name":"Bhugromal  Jeswani Bellaram",
    "wof:placetype":"venue"
},
  "geometry": {"coordinates":[-15.5737190247,27.7490711212],"type":"Point"}
}