{
  "type": "Feature",
  "properties": {
    "iso:country":"ES",
    "sg:address":"Avda Portugal, 17",
    "sg:city":"Salamanca",
    "sg:orig_category":"Carnicer\u00cdas, Carnicer\u00cdas",
    "sg:phone":"+34 923 24 50 51",
    "sg:postcode":"37004",
    "sg:province":"Salamanca",
    "wof:name":"Agropecuaria Chamberi S.l.",
    "wof:placetype":"venue"
},
  "geometry": {"coordinates":[-5.654646,40.970535],"type":"Point"}
}