{
  "type": "Feature",
  "properties": {
    "addr:full":"Calle de San Francisco De Asis, 19 Gijon Asturias 33205",
    "addr:housenumber":"19",
    "addr:postcode":"33205",
    "addr:street":"Calle De San Francisco De Asis",
    "iso:country":"ES",
    "sg:address":"Calle de San Francisco De Asis, 19",
    "sg:city":"Gijon",
    "sg:orig_category":"Asesor\u00cda Sobre Comunicaci\u00d3n De Empresas",
    "sg:phone":"+34 985 13 44 69",
    "sg:postcode":"33205",
    "sg:province":"Asturias",
    "wof:name":"Lastra Garcia-baron Juan Jose",
    "wof:placetype":"venue"
},
  "geometry": {"coordinates":[-5.6551551819,43.5329856873],"type":"Point"}
}