{
  "type": "Feature",
  "properties": {
    "addr:full":"M. Hernandez, 63 Huetor-tajar Granada 18360",
    "addr:housenumber":"63",
    "addr:postcode":"18360",
    "addr:street":"M. Hernandez",
    "iso:country":"ES",
    "sg:address":"M. Hernandez, 63",
    "sg:city":"Huetor-tajar",
    "sg:orig_category":"Trabajos De Perforaciones, Sondeos, Construcci\u00d3n De Pozos",
    "sg:phone":"+34 958 33 38 45",
    "sg:postcode":"18360",
    "sg:province":"Granada",
    "wof:name":"Sondeos Y Perforaciones Geomar S.l.",
    "wof:placetype":"venue"
},
  "geometry": {"coordinates":[-4.0347108841,37.1846199036],"type":"Point"}
}