{
  "type": "Feature",
  "properties": {
    "iso:country":"ES",
    "sg:address":"Plaz San Jose, 7",
    "sg:city":"Santos De Maimona",
    "sg:orig_category":"Mec\u00c1nico Del Autom\u00d3vil",
    "sg:phone":"+34 924 54 40 32",
    "sg:postcode":"06230",
    "sg:province":"Badajoz",
    "wof:name":"Martinez De La Cruz Casimiro",
    "wof:placetype":"venue"
},
  "geometry": {"coordinates":[-6.3725099564,38.4434814453],"type":"Point"}
}