{
  "type": "Feature",
  "properties": {
    "iso:country":"ES",
    "sg:address":"Pque Doctor Calatayud, 10",
    "sg:city":"Aspe",
    "sg:orig_category":"Papeler\u00cdas, Librer\u00cdas",
    "sg:phone":"+34 965 49 10 91",
    "sg:postcode":"03680",
    "sg:province":"Alicante",
    "wof:name":"Requena Gras Jose",
    "wof:placetype":"venue"
},
  "geometry": {"coordinates":[-0.7673379779,38.3465461731],"type":"Point"}
}