{
  "type": "Feature",
  "properties": {
    "addr:full":"Calle de Gaztambide, 60 Madrid Madrid 28015",
    "addr:housenumber":"60",
    "addr:postcode":"madrid;28015",
    "addr:street":"Calle De Gaztambide",
    "iso:country":"ES",
    "sg:address":"Calle de Gaztambide, 60",
    "sg:city":"Madrid",
    "sg:orig_category":"Panader\u00cdas, Panader\u00cdas",
    "sg:phone":"+34 915 44 04 25",
    "sg:postcode":"28015",
    "sg:province":"Madrid",
    "wof:name":"Ruiz Viguera Fidel",
    "wof:placetype":"venue"
},
  "geometry": {"coordinates":[-3.7150909901,40.4385528564],"type":"Point"}
}