{
  "type": "Feature",
  "properties": {
    "addr:full":"Plaz Alcalde Horacio Hermoso, 18 Sevilla Sevilla 41013",
    "addr:housenumber":"18",
    "addr:postcode":"41013",
    "addr:street":"Plaz Alcalde Horacio Hermoso",
    "iso:country":"ES",
    "sg:address":"Plaz Alcalde Horacio Hermoso, 18",
    "sg:city":"Sevilla",
    "sg:orig_category":"Asociaciones, Organismos Culturales Y Socioeducativos",
    "sg:phone":"+34 954 61 55 10",
    "sg:postcode":"41013",
    "sg:province":"Sevilla",
    "wof:name":"El Abrigo De La Tercera Edad",
    "wof:placetype":"venue"
},
  "geometry": {"coordinates":[-5.9757490158,37.3708114624],"type":"Point"}
}