{
  "type": "Feature",
  "properties": {
    "addr:full":"Avda Andalucia (de), 112 Pe\u00e7arroya-pueblonuevo C\u00f3rdoba 14200",
    "addr:housenumber":"112",
    "addr:postcode":"14200",
    "addr:street":"Avda Andalucia De;Co\u0301Rdoba",
    "iso:country":"ES",
    "sg:address":"Avda Andalucia (de), 112",
    "sg:city":"Pe\u00e7arroya-pueblonuevo",
    "sg:orig_category":"Asistencia Y Seguros De Automovilistas Y Turistas",
    "sg:phone":"+34 957 56 10 97",
    "sg:postcode":"14200",
    "sg:province":"C\u00f3rdoba",
    "wof:name":"Hermanos Jurado Delgado S.l.",
    "wof:placetype":"venue"
},
  "geometry": {"coordinates":[-5.2533841133,38.2987060547],"type":"Point"}
}