{
  "type": "Feature",
  "properties": {
    "iso:country":"ES",
    "sg:address":"Calle de Bola, 3",
    "sg:city":"Madrid",
    "sg:orig_category":"Agencias Y Agentes Comerciales, Representantes",
    "sg:phone":"+34 915 47 06 93",
    "sg:postcode":"28013",
    "sg:province":"Madrid",
    "wof:name":"Fernandez Dondova Miguel",
    "wof:placetype":"venue"
},
  "geometry": {"coordinates":[-3.7106423378,40.4198493958],"type":"Point"}
}