{
  "type": "Feature",
  "properties": {
    "addr:full":"Calle de Maria Guerrero, 22 Zaragoza Zaragoza 50009",
    "addr:housenumber":"22",
    "addr:postcode":"50009",
    "addr:street":"Calle De Maria Guerrero",
    "iso:country":"ES",
    "sg:address":"Calle de Maria Guerrero, 22",
    "sg:city":"Zaragoza",
    "sg:orig_category":"Chapister\u00cda",
    "sg:phone":"+34 976 75 25 06",
    "sg:postcode":"50009",
    "sg:province":"Zaragoza",
    "wof:name":"Pintauto Aragon S.l.",
    "wof:placetype":"venue"
},
  "geometry": {"coordinates":[-0.9104689956,41.6437187195],"type":"Point"}
}