{
  "type": "Feature",
  "properties": {
    "iso:country":"ES",
    "sg:address":"Calle de Doctor Bonardell, 24",
    "sg:city":"Alcazar S. Juan",
    "sg:orig_category":"Calzados Ortop\u00c9dicos",
    "sg:phone":"+34 926 54 62 06",
    "sg:postcode":"13600",
    "sg:province":"Ciudad Real",
    "wof:name":"Ortopedia Rafi S.l.",
    "wof:placetype":"venue"
},
  "geometry": {"coordinates":[-3.2120366096,39.3893699646],"type":"Point"}
}