{
  "type": "Feature",
  "properties": {
    "iso:country":"ES",
    "sg:address":"Calle de Escultor Jose Capuz, 15",
    "sg:city":"Valencia",
    "sg:orig_category":"Peluquer\u00cdas, Peluquer\u00cda Mixta",
    "sg:phone":"+34 963 74 09 99",
    "sg:postcode":"46006",
    "sg:province":"Valencia",
    "wof:name":"Arcos Robledillo Juana",
    "wof:placetype":"venue"
},
  "geometry": {"coordinates":[-0.3621929884,39.4610557556],"type":"Point"}
}