{
  "type": "Feature",
  "properties": {
    "iso:country":"ES",
    "sg:address":"Calle de San Crispin, 5",
    "sg:city":"Madrid",
    "sg:orig_category":"Molduras, Junquillos, Listones Y Molduras Perforadas",
    "sg:phone":"+34 914 63 06 39",
    "sg:postcode":"28011",
    "sg:province":"Madrid",
    "wof:name":"Pelaez Silva Dionisio",
    "wof:placetype":"venue"
},
  "geometry": {"coordinates":[-3.7256729603,40.4144325256],"type":"Point"}
}