{
  "type": "Feature",
  "properties": {
    "addr:full":"Ctra. Llucmajor, Km. 0014,5 S'aranjassa Islas Baleares 07199",
    "addr:postcode":"07199",
    "addr:street":"Ctra. Llucmajor Km. 0014,5 S'Aranjassa",
    "iso:country":"ES",
    "sg:address":"Ctra. Llucmajor, Km. 0014,5",
    "sg:city":"S'aranjassa",
    "sg:orig_category":"Explotaci\u00d3n De Canteras",
    "sg:phone":"+34 971 74 29 83",
    "sg:postcode":"07199",
    "sg:province":"Islas Baleares",
    "wof:name":"Formigons C'an Ramis S.l.",
    "wof:placetype":"venue"
},
  "geometry": {"coordinates":[2.9117100239,39.6136398315],"type":"Point"}
}