{
  "type": "Feature",
  "properties": {
    "addr:full":"Calle de Palomeras, 41 Madrid Madrid 28053",
    "addr:housenumber":"41",
    "addr:postcode":"madrid;28053",
    "addr:street":"Calle De Palomeras",
    "iso:country":"ES",
    "sg:address":"Calle de Palomeras, 41",
    "sg:city":"Madrid",
    "sg:orig_category":"Librer\u00cdas",
    "sg:phone":"+34 914 77 60 46",
    "sg:postcode":"28053",
    "sg:province":"Madrid",
    "wof:name":"Vaquero Estrella Juan Manuel",
    "wof:placetype":"venue"
},
  "geometry": {"coordinates":[-3.6661009789,40.3893165588],"type":"Point"}
}