{
  "type": "Feature",
  "properties": {
    "addr:full":"Carr Hospital, 10 Torroella Montgri Girona 17257",
    "addr:housenumber":"10",
    "addr:postcode":"17257",
    "addr:street":"Carr Hospital",
    "iso:country":"ES",
    "sg:address":"Carr Hospital, 10",
    "sg:city":"Torroella Montgri",
    "sg:orig_category":"Asesor\u00cda Sobre Comunicaci\u00d3n De Empresas",
    "sg:phone":"+34 972 76 13 72",
    "sg:postcode":"17257",
    "sg:province":"Girona",
    "wof:name":"Ballesteros Vilarrodona Albert",
    "wof:placetype":"venue"
},
  "geometry": {"coordinates":[3.1277420521,42.042766571],"type":"Point"}
}