{
  "type": "Feature",
  "properties": {
    "addr:full":"Calle de General Aranaz, 49 Madrid Madrid 28027",
    "addr:housenumber":"49",
    "addr:postcode":"madrid;28027",
    "addr:street":"Calle De General Aranaz",
    "iso:country":"ES",
    "sg:address":"Calle de General Aranaz, 49",
    "sg:city":"Madrid",
    "sg:orig_category":"Servicios De Telecomunicaciones",
    "sg:phone":"+34 913 93 29 01",
    "sg:postcode":"28027",
    "sg:province":"Madrid",
    "wof:name":"Manager Internet S.l.",
    "wof:placetype":"venue"
},
  "geometry": {"coordinates":[-3.6393311024,40.443611145],"type":"Point"}
}