{
  "type": "Feature",
  "properties": {
    "iso:country":"ES",
    "sg:address":"Calle de Centro, 9",
    "sg:city":"Zaragoza",
    "sg:orig_category":"Confecci\u00d3n De Trajes Para Se\u00d1oras",
    "sg:phone":"+34 976 56 89 52",
    "sg:postcode":"50009",
    "sg:province":"Zaragoza",
    "wof:name":"Martinez Aguado Maria Isabel",
    "wof:placetype":"venue"
},
  "geometry": {"coordinates":[-0.9091864824,41.6319503784],"type":"Point"}
}