{
  "type": "Feature",
  "properties": {
    "iso:country":"ES",
    "sg:address":"Calle de Carmen Del, 4",
    "sg:city":"Aviles",
    "sg:orig_category":"Suministros Para Carrocer\u00cdas",
    "sg:phone":"+34 985 57 09 83",
    "sg:postcode":"33403",
    "sg:province":"Asturias",
    "wof:name":"Reguero Hidalgo Avelino",
    "wof:placetype":"venue"
},
  "geometry": {"coordinates":[-5.9071483612,43.5425376892],"type":"Point"}
}