{
  "type": "Feature",
  "properties": {
    "addr:full":"Carrer de Nou De La Rambla, 4 Barcelona Barcelona 08001",
    "addr:housenumber":"4",
    "addr:postcode":"08001",
    "addr:street":"Carrer De Nou De La Rambla",
    "iso:country":"ES",
    "sg:address":"Carrer de Nou De La Rambla, 4",
    "sg:city":"Barcelona",
    "sg:orig_category":"Confiter\u00cdas, Chocolater\u00cdas (al Por Menor)",
    "sg:phone":"+34 933 01 94 41",
    "sg:postcode":"08001",
    "sg:province":"Barcelona",
    "wof:name":"Guindo Gamez Fernando",
    "wof:placetype":"venue"
},
  "geometry": {"coordinates":[2.1743340492,41.3793754578],"type":"Point"}
}