{
  "type": "Feature",
  "properties": {
    "iso:country":"ES",
    "sg:address":"Calle de Marques De Mendigorria, 14",
    "sg:city":"Toledo",
    "sg:orig_category":"Molduras, Junquillos, Listones Y Molduras Perforadas",
    "sg:phone":"+34 925 21 58 69",
    "sg:postcode":"45003",
    "sg:province":"Toledo",
    "wof:name":"Herrera Fernandez Jose Javier",
    "wof:placetype":"venue"
},
  "geometry": {"coordinates":[-4.0222988129,39.8671836853],"type":"Point"}
}