{
  "type": "Feature",
  "properties": {
    "addr:full":"Carrer de Mas, 101 Hospitalet Llobregat Barcelona 08904",
    "addr:housenumber":"101",
    "addr:postcode":"08904",
    "addr:street":"Carrer De Mas",
    "iso:country":"ES",
    "sg:address":"Carrer de Mas, 101",
    "sg:city":"Hospitalet Llobregat",
    "sg:orig_category":"Producci\u00d3n De Abonos Y De Fertilizantes",
    "sg:phone":"+34 934 48 48 48",
    "sg:postcode":"08904",
    "sg:province":"Barcelona",
    "sg:website":"www.distribucionesmarianas.com",
    "wof:name":"Sicilia Aliart Margarita",
    "wof:placetype":"venue"
},
  "geometry": {"coordinates":[2.1190500259,41.3707618713],"type":"Point"}
}