{
  "type": "Feature",
  "properties": {
    "addr:full":"Calle de Rafael Lopez, 1 Huelva Huelva 21001",
    "addr:housenumber":"1",
    "addr:postcode":"21001",
    "addr:street":"Calle De Rafael Lopez",
    "iso:country":"ES",
    "sg:address":"Calle de Rafael Lopez, 1",
    "sg:city":"Huelva",
    "sg:orig_category":"Molduras, Junquillos, Listones Y Molduras Perforadas",
    "sg:phone":"+34 959 28 44 67",
    "sg:postcode":"21001",
    "sg:province":"Huelva",
    "wof:name":"Silvera Redondo Luis",
    "wof:placetype":"venue"
},
  "geometry": {"coordinates":[-6.9523019791,37.258228302],"type":"Point"}
}