{
  "type": "Feature",
  "properties": {
    "iso:country":"ES",
    "sg:address":"Carrer de Banys, 32",
    "sg:city":"Garriga",
    "sg:orig_category":"Zapatos (al Por Menor)",
    "sg:phone":"+34 938 71 46 96",
    "sg:postcode":"08530",
    "sg:province":"Barcelona",
    "wof:name":"Castells I Camp S.a.",
    "wof:placetype":"venue"
},
  "geometry": {"coordinates":[2.2857189178,41.6833343506],"type":"Point"}
}