{
  "type": "Feature",
  "properties": {
    "iso:country":"ES",
    "sg:address":"Calle de Sor Mercedes, S/n",
    "sg:city":"Giles",
    "sg:orig_category":"Molduras, Junquillos, Listones Y Molduras Perforadas",
    "sg:phone":"+34 928 67 48 51",
    "sg:postcode":"35010",
    "sg:province":"Las Palmas",
    "wof:name":"Gonzalez Tejera Matias",
    "wof:placetype":"venue"
},
  "geometry": {"coordinates":[-15.4397087097,28.1302242279],"type":"Point"}
}