{
  "type": "Feature",
  "properties": {
    "addr:full":"Calle de Jose Antonio Primo De Rivera, 62 Ingenio Las Palmas 35250",
    "addr:housenumber":"62",
    "addr:postcode":"35250",
    "addr:street":"Calle De Jose Antonio Primo De Rivera",
    "iso:country":"ES",
    "sg:address":"Calle de Jose Antonio Primo De Rivera, 62",
    "sg:city":"Ingenio",
    "sg:orig_category":"Arquitectos",
    "sg:phone":"+34 928 78 51 90",
    "sg:postcode":"35250",
    "sg:province":"Las Palmas",
    "wof:name":"Pe\u00f1a Ramirez Jesus",
    "wof:placetype":"venue"
},
  "geometry": {"coordinates":[-15.4332780838,27.9182224274],"type":"Point"}
}