{
  "type": "Feature",
  "properties": {
    "addr:full":"Calle de Huescar, 23 Malaga M\u00e1laga 29007",
    "addr:housenumber":"23",
    "addr:postcode":"29007",
    "addr:street":"Calle De Huescar;Ma\u0301Laga",
    "iso:country":"ES",
    "sg:address":"Calle de Huescar, 23",
    "sg:city":"Malaga",
    "sg:orig_category":"Caf\u00c9s, Bares, Cervecer\u00cdas",
    "sg:phone":"+34 952 28 69 72",
    "sg:postcode":"29007",
    "sg:province":"M\u00e1laga",
    "wof:name":"Bonilla Plaza Juan",
    "wof:placetype":"venue"
},
  "geometry": {"coordinates":[-4.434735775,36.7185020447],"type":"Point"}
}