{
  "type": "Feature",
  "properties": {
    "addr:full":"Calle de Madre Vedruna, 12 Vitoria-gasteiz \u00c1lava 01008",
    "addr:housenumber":"12",
    "addr:postcode":"01008",
    "addr:street":"Calle De Madre Vedruna",
    "iso:country":"ES",
    "sg:address":"Calle de Madre Vedruna, 12",
    "sg:city":"Vitoria-gasteiz",
    "sg:orig_category":"Alquiler De V\u00cddeo",
    "sg:phone":"+34 945 23 07 24",
    "sg:postcode":"01008",
    "sg:province":"\u00c1lava",
    "wof:name":"Baz Tavares Carlos",
    "wof:placetype":"venue"
},
  "geometry": {"coordinates":[-2.6807370186,42.8461685181],"type":"Point"}
}