{
  "type": "Feature",
  "properties": {
    "iso:country":"ES",
    "sg:address":"Carrer de Antoni Frontera, 4",
    "sg:city":"Palma",
    "sg:orig_category":"Ingenier\u00cda, Centros De Estudios (diversos)",
    "sg:phone":"+34 971 75 42 23",
    "sg:postcode":"07004",
    "sg:province":"Islas Baleares",
    "wof:name":"Fermoselle Paterna Jose",
    "wof:placetype":"venue"
},
  "geometry": {"coordinates":[2.654227972,39.5802650452],"type":"Point"}
}