{
  "type": "Feature",
  "properties": {
    "addr:full":"Av Gaudi, 30 Barcelona Barcelona 08025",
    "addr:housenumber":"30",
    "addr:postcode":"08025",
    "addr:street":"Av Gaudi",
    "iso:country":"ES",
    "sg:address":"Av Gaudi, 30",
    "sg:city":"Barcelona",
    "sg:orig_category":"Art\u00cdculos De Regalo (al Por Menor)",
    "sg:phone":"+34 934 50 26 83",
    "sg:postcode":"08025",
    "sg:province":"Barcelona",
    "wof:name":"Comercial Framan S.a.",
    "wof:placetype":"venue"
},
  "geometry": {"coordinates":[2.1746630669,41.4067420959],"type":"Point"}
}