{
  "type": "Feature",
  "properties": {
    "iso:country":"ES",
    "sg:address":"Calle de Real, 133",
    "sg:city":"Brenes",
    "sg:orig_category":"Inmobiliaria (agencias)",
    "sg:phone":"+34 954 79 67 44",
    "sg:postcode":"41310",
    "sg:province":"Sevilla",
    "wof:name":"Mendez Guarnido Josefa",
    "wof:placetype":"venue"
},
  "geometry": {"coordinates":[-5.8754224777,37.54712677],"type":"Point"}
}