{
  "type": "Feature",
  "properties": {
    "addr:full":"Carrer de Monestir De Poblet, 24 Reus Tarragona 43205",
    "addr:housenumber":"24",
    "addr:postcode":"43205",
    "addr:street":"Carrer De Monestir De Poblet",
    "iso:country":"ES",
    "sg:address":"Carrer de Monestir De Poblet, 24",
    "sg:city":"Reus",
    "sg:orig_category":"Empresas De Pintura Y Revestimientos",
    "sg:phone":"+34 977 75 32 28",
    "sg:postcode":"43205",
    "sg:province":"Tarragona",
    "wof:name":"Asensio Martinez Antonia",
    "wof:placetype":"venue"
},
  "geometry": {"coordinates":[1.1064338684,41.147895813],"type":"Point"}
}