{
  "type": "Feature",
  "properties": {
    "addr:full":"Rapadouro, S/n Rapadouro Pontevedra 36388",
    "addr:postcode":"36388",
    "addr:street":"Rapadouro S / N",
    "iso:country":"ES",
    "sg:address":"Rapadouro, S/n",
    "sg:city":"Rapadouro",
    "sg:orig_category":"Ingenier\u00cda, Centros De Estudios (diversos)",
    "sg:phone":"+34 986 68 70 35",
    "sg:postcode":"36388",
    "sg:province":"Pontevedra",
    "sg:website":"www.geseco.es",
    "wof:name":"Geseco S.a.",
    "wof:placetype":"venue"
},
  "geometry": {"coordinates":[-8.7831964493,42.1088485718],"type":"Point"}
}