{
  "type": "Feature",
  "properties": {
    "addr:full":"Calle de Linares, 23 Valencia Valencia 46018",
    "addr:housenumber":"23",
    "addr:postcode":"46018",
    "addr:street":"Calle De Linares",
    "iso:country":"ES",
    "sg:address":"Calle de Linares, 23",
    "sg:city":"Valencia",
    "sg:orig_category":"Ingenier\u00cda, Centros De Estudios (diversos)",
    "sg:phone":"+34 963 85 41 65",
    "sg:postcode":"46018",
    "sg:province":"Valencia",
    "wof:name":"Gonzalez Beltran Jose Luis",
    "wof:placetype":"venue"
},
  "geometry": {"coordinates":[-0.3944259882,39.4682884216],"type":"Point"}
}