{
  "type": "Feature",
  "properties": {
    "iso:country":"ES",
    "sg:address":"Carrer de Corsega, 516",
    "sg:city":"Barcelona",
    "sg:orig_category":"M\u00c9dicos: Pediatr\u00cda. Enfermedades De Los Ni\u00d1os",
    "sg:phone":"+34 934 36 84 88",
    "sg:postcode":"08025",
    "sg:province":"Barcelona",
    "wof:name":"Unitat Pedriatrica Arc",
    "wof:placetype":"venue"
},
  "geometry": {"coordinates":[2.1713020802,41.4053649902],"type":"Point"}
}