{
  "type": "Feature",
  "properties": {
    "iso:country":"ES",
    "sg:address":"Rua Casas Reais (das), 4",
    "sg:city":"Santiago De Compostela",
    "sg:orig_category":"Bancos",
    "sg:phone":"+34 981 58 35 00",
    "sg:postcode":"15704",
    "sg:province":"La Coru\u00f1a",
    "wof:name":"Banco Caixa Geral S.a.",
    "wof:placetype":"venue"
},
  "geometry": {"coordinates":[-8.5420818329,42.8813552856],"type":"Point"}
}