{
  "type": "Feature",
  "properties": {
    "iso:country":"ES",
    "sg:address":"Calle de Corredera, 49",
    "sg:city":"Arcos Frontera",
    "sg:orig_category":"Pod\u00d3logos: Pedicuros",
    "sg:phone":"+34 956 70 44 88",
    "sg:postcode":"11630",
    "sg:province":"C\u00e1diz",
    "wof:name":"Macias Delgado Cristina",
    "wof:placetype":"venue"
},
  "geometry": {"coordinates":[-5.8104348183,36.7502326965],"type":"Point"}
}