{
  "type": "Feature",
  "properties": {
    "addr:full":"Ctra Pulpi, S/n Cabildo Y Campana Murcia 30813",
    "addr:housenumber":"s / n",
    "addr:postcode":"30813",
    "addr:street":"Ctra Pulpi;Cabildo Y",
    "iso:country":"ES",
    "sg:address":"Ctra Pulpi, S/n",
    "sg:city":"Cabildo Y Campana",
    "sg:orig_category":"Insecticidas, Fumigaci\u00d3n",
    "sg:phone":"+34 968 48 55 11",
    "sg:postcode":"30813",
    "sg:province":"Murcia",
    "wof:name":"Diaz Lorenzo Onofre",
    "wof:placetype":"venue"
},
  "geometry": {"coordinates":[-1.7215889692,37.491394043],"type":"Point"}
}