{
  "type": "Feature",
  "properties": {
    "iso:country":"ES",
    "sg:address":"Carrer de Marques De Montoliu, 4",
    "sg:city":"Tarragona",
    "sg:orig_category":"Asesor\u00cda De Formaci\u00d3n Y Gesti\u00d3n De Personal",
    "sg:phone":"+34 977 21 41 22",
    "sg:postcode":"43002",
    "sg:province":"Tarragona",
    "wof:name":"Lopez Mora Susana",
    "wof:placetype":"venue"
},
  "geometry": {"coordinates":[1.2465800047,41.1204681396],"type":"Point"}
}