{
  "type": "Feature",
  "properties": {
    "addr:full":"Carrer de Mas De La Mora, 3 Vic Barcelona 08500",
    "addr:housenumber":"3",
    "addr:postcode":"08500",
    "addr:street":"Carrer De Mas De La Mora",
    "iso:country":"ES",
    "sg:address":"Carrer de Mas De La Mora, 3",
    "sg:city":"Vic",
    "sg:orig_category":"Construcciones E Instalaciones Agr\u00cdcolas",
    "sg:phone":"+34 938 86 36 79",
    "sg:postcode":"08500",
    "sg:province":"Barcelona",
    "wof:name":"Erra Tecni-ram S.l.",
    "wof:placetype":"venue"
},
  "geometry": {"coordinates":[2.2655580044,41.9478569031],"type":"Point"}
}