{
  "type": "Feature",
  "properties": {
    "addr:full":"Calle de Raimundo Lulio, 22 Madrid Madrid 28010",
    "addr:housenumber":"22",
    "addr:postcode":"madrid;28010",
    "addr:street":"Calle De Raimundo Lulio",
    "iso:country":"ES",
    "sg:address":"Calle de Raimundo Lulio, 22",
    "sg:city":"Madrid",
    "sg:orig_category":"Agencias De Viajes",
    "sg:phone":"+34 914 48 40 26",
    "sg:postcode":"28010",
    "sg:province":"Madrid",
    "wof:name":"Viajes Tovi Tours S. A.",
    "wof:placetype":"venue"
},
  "geometry": {"coordinates":[-3.6981039047,40.4327850342],"type":"Point"}
}