{
  "type": "Feature",
  "properties": {
    "iso:country":"ES",
    "sg:address":"Calle de Aita Elorriaga, 14",
    "sg:city":"Mungia",
    "sg:orig_category":"Inmobiliaria (agencias)",
    "sg:phone":"+34 946 74 07 84",
    "sg:postcode":"48100",
    "sg:province":"Vizcaya",
    "wof:name":"Inmobiliaria Nekasa",
    "wof:placetype":"venue"
},
  "geometry": {"coordinates":[-2.844192028,43.3531761169],"type":"Point"}
}