{
  "type": "Feature",
  "properties": {
    "addr:full":"Ctra. Gibraleon, 3 S. Bartolome Torre Huelva 21510",
    "addr:housenumber":"3",
    "addr:postcode":"21510",
    "addr:street":"Ctra. Gibraleon;S. Bartolome Torre",
    "iso:country":"ES",
    "sg:address":"Ctra. Gibraleon, 3",
    "sg:city":"S. Bartolome Torre",
    "sg:orig_category":"Empresas De Carpinter\u00cda De Madera",
    "sg:phone":"+34 959 38 74 85",
    "sg:postcode":"21510",
    "sg:province":"Huelva",
    "wof:name":"Carpinteria Los Palomos S.l.",
    "wof:placetype":"venue"
},
  "geometry": {"coordinates":[-7.0990271568,37.4437942505],"type":"Point"}
}