{
  "type": "Feature",
  "properties": {
    "addr:full":"Carrer de Costa I Llobera, 15 Palma Islas Baleares 07005",
    "addr:housenumber":"15",
    "addr:postcode":"07005",
    "addr:street":"Carrer De Costa I Llobera",
    "iso:country":"ES",
    "sg:address":"Carrer de Costa I Llobera, 15",
    "sg:city":"Palma",
    "sg:orig_category":"Peluquer\u00cdas, Peluquer\u00cda Mixta",
    "sg:phone":"+34 971 77 14 81",
    "sg:postcode":"07005",
    "sg:province":"Islas Baleares",
    "wof:name":"Absolute Coiffure",
    "wof:placetype":"venue"
},
  "geometry": {"coordinates":[2.657225,39.57478],"type":"Point"}
}