{
  "type": "Feature",
  "properties": {
    "iso:country":"ES",
    "sg:address":"Calle de San Francisco, 32",
    "sg:city":"Donostia-san Sebastian",
    "sg:orig_category":"Panader\u00cdas, Panader\u00cdas",
    "sg:phone":"+34 943 29 26 83",
    "sg:postcode":"20002",
    "sg:province":"Guip\u00f9zcoa",
    "wof:name":"Gonzalez Morcillo Francisco",
    "wof:placetype":"venue"
},
  "geometry": {"coordinates":[-1.9727330208,43.3243904114],"type":"Point"}
}