{
  "type": "Feature",
  "properties": {
    "iso:country":"ES",
    "sg:address":"Calle de Castillo (del), 61",
    "sg:city":"Chipiona",
    "sg:orig_category":"Quincaller\u00cda (al Por Menor)",
    "sg:phone":"+34 956 37 21 16",
    "sg:postcode":"11550",
    "sg:province":"C\u00e1diz",
    "wof:name":"Hermanos Mellado Galan C.b.",
    "wof:placetype":"venue"
},
  "geometry": {"coordinates":[-6.435526371,36.7376861572],"type":"Point"}
}