{
  "type": "Feature",
  "properties": {
    "addr:full":"Calle de Lanzarote, 18 Coria Rio Sevilla 41100",
    "addr:housenumber":"18",
    "addr:postcode":"41100",
    "addr:street":"Calle De Lanzarote;Rio Sevilla",
    "iso:country":"ES",
    "sg:address":"Calle de Lanzarote, 18",
    "sg:city":"Coria Rio",
    "sg:orig_category":"Inmobiliaria (agencias)",
    "sg:phone":"+34 954 77 46 76",
    "sg:postcode":"41100",
    "sg:province":"Sevilla",
    "wof:name":"Suarpa S.l.",
    "wof:placetype":"venue"
},
  "geometry": {"coordinates":[-6.0620536804,37.2776947021],"type":"Point"}
}