{
  "type": "Feature",
  "properties": {
    "addr:full":"Carr Sant Pere, 19 Figueres Girona 17600",
    "addr:housenumber":"19",
    "addr:postcode":"17600",
    "addr:street":"Carr Sant Pere",
    "iso:country":"ES",
    "sg:address":"Carr Sant Pere, 19",
    "sg:city":"Figueres",
    "sg:orig_category":"Caf\u00c9s, Bares, Cervecer\u00cdas",
    "sg:phone":"+34 972 51 11 93",
    "sg:postcode":"17600",
    "sg:province":"Girona",
    "sg:website":"www.delicatessen.com",
    "wof:name":"Dalicatessen Cafe-bar",
    "wof:placetype":"venue"
},
  "geometry": {"coordinates":[2.9598309994,42.2674827576],"type":"Point"}
}