{
  "type": "Feature",
  "properties": {
    "addr:full":"Calle de Santa Maria De La Merced, 8 Jerez De La Frontera C\u00e1diz 11404",
    "addr:housenumber":"8",
    "addr:postcode":"11404",
    "addr:street":"Calle De Santa;La Merced",
    "iso:country":"ES",
    "sg:address":"Calle de Santa Maria De La Merced, 8",
    "sg:city":"Jerez De La Frontera",
    "sg:orig_category":"Artes Gr\u00c1ficas, Artes Pl\u00c1sticas (curso)",
    "sg:phone":"+34 956 34 60 61",
    "sg:postcode":"11404",
    "sg:province":"C\u00e1diz",
    "wof:name":"Artes Graficas Villace S. A.",
    "wof:placetype":"venue"
},
  "geometry": {"coordinates":[-6.1462259293,36.6871337891],"type":"Point"}
}