{
  "type": "Feature",
  "properties": {
    "iso:country":"ES",
    "sg:address":"Carrer de Enric Prat De La Riba, 8",
    "sg:city":"S. Boi Llobregat",
    "sg:orig_category":"Negocio De Materiales De Construcci\u00d3n",
    "sg:phone":"+34 936 37 73 84",
    "sg:postcode":"08830",
    "sg:province":"Barcelona",
    "wof:name":"Pass Puertas S. L.",
    "wof:placetype":"venue"
},
  "geometry": {"coordinates":[2.0302579403,41.3287658691],"type":"Point"}
}