{
  "type": "Feature",
  "properties": {
    "iso:country":"ES",
    "sg:address":"Mondego, 29",
    "sg:city":"Sada",
    "sg:classifiers":[
        {
            "category":"Personal",
            "subcategory":"Barber",
            "type":"Services"
        }
    ],
    "sg:phone":"+34 981 62 31 34",
    "sg:postcode":"15160",
    "sg:province":"La Coru\u00f1a",
    "sg:tags":[
        "caballeros",
        "de",
        "peluqueros"
    ],
    "wof:name":"Nu\u00f1ez Abad Juan",
    "wof:placetype":"venue"
},
  "geometry": {"coordinates":[-8.2941350937,43.3608665466],"type":"Point"}
}