{
  "type": "Feature",
  "properties": {
    "iso:country":"ES",
    "sg:address":"Rua Salustiano Portela Pazos, 3",
    "sg:city":"Pontevedra",
    "sg:orig_category":"Arquitectos",
    "sg:phone":"+34 986 84 10 54",
    "sg:postcode":"36099",
    "sg:province":"Pontevedra",
    "wof:name":"Tobio Cendon Jose Maria",
    "wof:placetype":"venue"
},
  "geometry": {"coordinates":[-8.6394891739,42.4333839417],"type":"Point"}
}