{
  "type": "Feature",
  "properties": {
    "iso:country":"ES",
    "sg:address":"Pase Estacion, De La, 70",
    "sg:city":"Talavera Reina",
    "sg:orig_category":"Librer\u00cdas",
    "sg:phone":"+34 925 80 56 91",
    "sg:postcode":"45600",
    "sg:province":"Toledo",
    "wof:name":"Resino Jimenez Maria Teresa",
    "wof:placetype":"venue"
},
  "geometry": {"coordinates":[-4.8326292038,39.9584884644],"type":"Point"}
}