{
  "type": "Feature",
  "properties": {
    "addr:full":"Calle de Navarrete El Mudo, 5 Logro\u00f1o La Rioja 26005",
    "addr:housenumber":"5",
    "addr:postcode":"26005",
    "addr:street":"Calle De Navarrete El Mudo;Rioja",
    "iso:country":"ES",
    "sg:address":"Calle de Navarrete El Mudo, 5",
    "sg:city":"Logro\u00f1o",
    "sg:orig_category":"Instalaci\u00d3n, Reparaci\u00d3n De Ascensores Y Montacargas",
    "sg:phone":"+34 941 22 55 45",
    "sg:postcode":"26005",
    "sg:province":"La Rioja",
    "sg:website":"www.otis.com",
    "wof:name":"Zardoya Otis S.a.",
    "wof:placetype":"venue"
},
  "geometry": {"coordinates":[-2.4571597576,42.4641532898],"type":"Point"}
}