{
  "type": "Feature",
  "properties": {
    "addr:full":"Calle de San Ramon, 17 Churriana Vega Granada 18194",
    "addr:housenumber":"17",
    "addr:postcode":"18194",
    "addr:street":"Calle De San Ramon",
    "iso:country":"ES",
    "sg:address":"Calle de San Ramon, 17",
    "sg:city":"Churriana Vega",
    "sg:orig_category":"Agentes, Concesionarios Y Sucursales De Veh\u00cdculos",
    "sg:phone":"+34 958 57 28 49",
    "sg:postcode":"18194",
    "sg:province":"Granada",
    "wof:name":"Ali Abdullah Samih Jouse",
    "wof:placetype":"venue"
},
  "geometry": {"coordinates":[-3.6424622536,37.144985199],"type":"Point"}
}