{
  "type": "Feature",
  "properties": {
    "addr:full":"Rua Pino, 3 Carballo La Coru\u00f1a 15100",
    "addr:housenumber":"3",
    "addr:postcode":"15100",
    "addr:street":"Rua Pino;La Corun\u0303A",
    "iso:country":"ES",
    "sg:address":"Rua Pino, 3",
    "sg:city":"Carballo",
    "sg:orig_category":"Producci\u00d3n, Distribuci\u00d3n De Electricidad",
    "sg:phone":"+34 981 75 79 57",
    "sg:postcode":"15100",
    "sg:province":"La Coru\u00f1a",
    "wof:name":"C.h. Electra Batan S.l.",
    "wof:placetype":"venue"
},
  "geometry": {"coordinates":[-8.6953792572,43.2131652832],"type":"Point"}
}