{
  "type": "Feature",
  "properties": {
    "iso:country":"ES",
    "sg:address":"Avda Constitucion, 144",
    "sg:city":"Torrejon Ardoz",
    "sg:orig_category":"Supermercados Y Hipermercados",
    "sg:phone":"+34 916 75 89 04",
    "sg:postcode":"28850",
    "sg:province":"Madrid",
    "wof:name":"Madrile\u00d1a De Negocios S.a.",
    "wof:placetype":"venue"
},
  "geometry": {"coordinates":[-3.4598190784,40.4599609375],"type":"Point"}
}