{
  "type": "Feature",
  "properties": {
    "addr:full":"Pg Estacio, S/n Cellera Ter Girona 17165",
    "addr:housenumber":"s / n",
    "addr:postcode":"17165",
    "addr:street":"Pg Estacio;Cellera Ter",
    "iso:country":"ES",
    "sg:address":"Pg Estacio, S/n",
    "sg:city":"Cellera Ter",
    "sg:orig_category":"Librer\u00cdas",
    "sg:phone":"+34 972 42 17 65",
    "sg:postcode":"17165",
    "sg:province":"Girona",
    "wof:name":"Vidal Garangou Maria Angels",
    "wof:placetype":"venue"
},
  "geometry": {"coordinates":[2.6230649948,41.9693565369],"type":"Point"}
}