{
  "type": "Feature",
  "properties": {
    "addr:full":"La Vega, 4 Leitza Navarra 31880",
    "addr:housenumber":"4",
    "addr:postcode":"31880",
    "addr:street":"La Vega",
    "iso:country":"ES",
    "sg:address":"La Vega, 4",
    "sg:city":"Leitza",
    "sg:orig_category":"Muebles Y Accesorios Para Cocinas Y Cuartos De Ba\u00d1o (al Por Menor)",
    "sg:phone":"+34 948 51 05 29",
    "sg:postcode":"31880",
    "sg:province":"Navarra",
    "sg:website":"www.egoki.cc",
    "wof:name":"Egoki Leitzakoa S. L.",
    "wof:placetype":"venue"
},
  "geometry": {"coordinates":[-1.9149940014,43.0805091858],"type":"Point"}
}