{
  "type": "Feature",
  "properties": {
    "addr:full":"Calle de Don Pedro De Luna, 20 Zaragoza Zaragoza 50010",
    "addr:housenumber":"20",
    "addr:postcode":"50010",
    "addr:street":"Calle De Don Pedro De Luna",
    "iso:country":"ES",
    "sg:address":"Calle de Don Pedro De Luna, 20",
    "sg:city":"Zaragoza",
    "sg:orig_category":"Centros De Coordinaci\u00d3n",
    "sg:phone":"+34 976 34 40 07",
    "sg:postcode":"50010",
    "sg:province":"Zaragoza",
    "wof:name":"Gestoria Latorre Palomera S.l.",
    "wof:placetype":"venue"
},
  "geometry": {"coordinates":[-0.9049540162,41.6520233154],"type":"Point"}
}