{
  "type": "Feature",
  "properties": {
    "addr:full":"Calle de Doctor Barraquer, 3 Segorbe Castell\u00f3n 12400",
    "addr:housenumber":"3",
    "addr:postcode":"12400",
    "addr:street":"Calle De Doctor Barraquer",
    "iso:country":"ES",
    "sg:address":"Calle de Doctor Barraquer, 3",
    "sg:city":"Segorbe",
    "sg:orig_category":"Frutas Y Legumbres Frescas (al Por Mayor)",
    "sg:phone":"+34 964 71 22 84",
    "sg:postcode":"12400",
    "sg:province":"Castell\u00f3n",
    "wof:name":"Sojivit S.l.",
    "wof:placetype":"venue"
},
  "geometry": {"coordinates":[-0.4865750074,39.8482627869],"type":"Point"}
}