{
  "type": "Feature",
  "properties": {
    "iso:country":"ES",
    "sg:address":"Av Estatut, 217",
    "sg:city":"Rubi",
    "sg:orig_category":"Agencias Y Agentes Comerciales, Representantes",
    "sg:phone":"+34 935 88 13 51",
    "sg:postcode":"08191",
    "sg:province":"Barcelona",
    "wof:name":"Ruiz Hernandez Ursula",
    "wof:placetype":"venue"
},
  "geometry": {"coordinates":[2.0378730297,41.5004310608],"type":"Point"}
}