{
  "type": "Feature",
  "properties": {
    "addr:full":"Calle de Corredera, 47 Baza Granada 18800",
    "addr:housenumber":"47",
    "addr:postcode":"18800",
    "addr:street":"Calle De Corredera",
    "iso:country":"ES",
    "sg:address":"Calle de Corredera, 47",
    "sg:city":"Baza",
    "sg:orig_category":"Centros De Coordinaci\u00d3n",
    "sg:phone":"+34 958 70 38 45",
    "sg:postcode":"18800",
    "sg:province":"Granada",
    "wof:name":"Yeste Bautista Antonio",
    "wof:placetype":"venue"
},
  "geometry": {"coordinates":[-2.7701644897,37.4931297302],"type":"Point"}
}