{
  "type": "Feature",
  "properties": {
    "addr:full":"Pase Tierra De Melide, 27 Madrid Madrid 28050",
    "addr:housenumber":"27",
    "addr:postcode":"madrid;28050",
    "iso:country":"ES",
    "sg:address":"Pase Tierra De Melide, 27",
    "sg:city":"Madrid",
    "sg:orig_category":"Papeler\u00cdas, Librer\u00cdas",
    "sg:phone":"+34 917 50 57 17",
    "sg:postcode":"28050",
    "sg:province":"Madrid",
    "wof:name":"Prensa El Sauce S.l",
    "wof:placetype":"venue"
},
  "geometry": {"coordinates":[-3.6657269001,40.5077514648],"type":"Point"}
}