{
  "type": "Feature",
  "properties": {
    "addr:full":"Alto San Agustin, S/n Utiel Valencia 46300",
    "addr:housenumber":"/ n",
    "addr:postcode":"46300",
    "addr:street":"San Agustin S",
    "iso:country":"ES",
    "sg:address":"Alto San Agustin, S/n",
    "sg:city":"Utiel",
    "sg:orig_category":"Serrer\u00cdas De Madera",
    "sg:phone":"+34 962 17 05 68",
    "sg:postcode":"46300",
    "sg:province":"Valencia",
    "wof:name":"Gadea Martinez Julian",
    "wof:placetype":"venue"
},
  "geometry": {"coordinates":[-1.2161849737,39.5644798279],"type":"Point"}
}