{
  "type": "Feature",
  "properties": {
    "addr:full":"Calle de El Orden, 1 Barakaldo Vizcaya 48901",
    "addr:housenumber":"1",
    "addr:postcode":"48901",
    "addr:street":"Calle De El Orden",
    "iso:country":"ES",
    "sg:address":"Calle de El Orden, 1",
    "sg:city":"Barakaldo",
    "sg:orig_category":"Sociedades, Compa\u00d1\u00cdas Aseguradoras",
    "sg:phone":"+34 944 37 87 71",
    "sg:postcode":"48901",
    "sg:province":"Vizcaya",
    "wof:name":"Igor Humberto Lafuente Ballesteros",
    "wof:placetype":"venue"
},
  "geometry": {"coordinates":[-2.98746562,43.298915863],"type":"Point"}
}