{
  "type": "Feature",
  "properties": {
    "iso:country":"ES",
    "sg:address":"Avda Francia, 24",
    "sg:city":"Sevilla",
    "sg:orig_category":"Propiedad Industrial: Patentes De Inventos, Marcas, Modelos, Dise\u00d1os",
    "sg:phone":"+34 902 99 84 67",
    "sg:postcode":"41018",
    "sg:province":"Sevilla",
    "wof:name":"Patenting S.l.",
    "wof:placetype":"venue"
},
  "geometry": {"coordinates":[-5.9768338203,37.3489265442],"type":"Point"}
}