{
  "type": "Feature",
  "properties": {
    "iso:country":"ES",
    "sg:address":"Huesca (p I Prado), 605",
    "sg:city":"Merida",
    "sg:orig_category":"Hielo Artificial (fabricaci\u00d3n, Distribuci\u00d3n)",
    "sg:phone":"+34 924 37 40 88",
    "sg:postcode":"06800",
    "sg:province":"Badajoz",
    "wof:name":"Comunitel Global S.a.",
    "wof:placetype":"venue"
},
  "geometry": {"coordinates":[-6.3861188889,38.929309845],"type":"Point"}
}