{
  "type": "Feature",
  "properties": {
    "addr:full":"Vega De Arriba, 12 Vega Asturias 33391",
    "addr:housenumber":"12",
    "addr:postcode":"33391",
    "addr:street":"Vega;Arriba;Asturias",
    "iso:country":"ES",
    "sg:address":"Vega De Arriba, 12",
    "sg:city":"Vega",
    "sg:orig_category":"Ingeniero",
    "sg:phone":"+34 985 13 80 18",
    "sg:postcode":"33391",
    "sg:province":"Asturias",
    "sg:website":"www.caudalastur.com",
    "wof:name":"Caudal Astur S.l",
    "wof:placetype":"venue"
},
  "geometry": {"coordinates":[-5.6502809525,43.4943695068],"type":"Point"}
}