{
  "type": "Feature",
  "properties": {
    "iso:country":"ES",
    "sg:address":"Carrer de Carrasco I Formiguera, 1",
    "sg:city":"Mataro",
    "sg:classifiers":[
        {
            "category":"Casinos & Gambling",
            "type":"Entertainment"
        }
    ],
    "sg:phone":"+34 937 41 45 00",
    "sg:postcode":"08302",
    "sg:province":"Barcelona",
    "sg:tags":[
        "locale",
        "de",
        "juego"
    ],
    "sg:website":"www.aventurapark.com",
    "wof:name":"Iluro Park S.l.",
    "wof:placetype":"venue"
},
  "geometry": {"coordinates":[2.4316999912,41.534450531],"type":"Point"}
}