{
  "type": "Feature",
  "properties": {
    "iso:country":"ES",
    "sg:address":"Calle de San Vicente Martir, 119",
    "sg:city":"Valencia",
    "sg:orig_category":"M\u00c9dicos: Estomatolog\u00cda",
    "sg:phone":"+34 963 42 21 13",
    "sg:postcode":"46007",
    "sg:province":"Valencia",
    "wof:name":"Koninckx Fuster Pablo Vicente",
    "wof:placetype":"venue"
},
  "geometry": {"coordinates":[-0.3817679882,39.4637947083],"type":"Point"}
}