{
  "type": "Feature",
  "properties": {
    "addr:full":"Alam Principal, 21 Malaga M\u00e1laga 29001",
    "addr:housenumber":"21",
    "addr:postcode":"29001",
    "addr:street":"Alam Principal;Ma\u0301Laga",
    "iso:country":"ES",
    "sg:address":"Alam Principal, 21",
    "sg:city":"Malaga",
    "sg:orig_category":"M\u00c9dicos: Cirug\u00cda General",
    "sg:phone":"+34 952 22 81 97",
    "sg:postcode":"29001",
    "sg:province":"M\u00e1laga",
    "wof:name":"Gimenez Limon Jose Luis",
    "wof:placetype":"venue"
},
  "geometry": {"coordinates":[-4.4227809906,36.7172317505],"type":"Point"}
}