{
  "type": "Feature",
  "properties": {
    "iso:country":"ES",
    "sg:address":"Calle de Justo Vilar, 29",
    "sg:city":"Valencia",
    "sg:orig_category":"Ropa De Hogar (al Por Menor)",
    "sg:phone":"+34 963 71 94 59",
    "sg:postcode":"46011",
    "sg:province":"Valencia",
    "wof:name":"Llorens Candela Maria Trinidad",
    "wof:placetype":"venue"
},
  "geometry": {"coordinates":[-0.3314138055,39.4671211243],"type":"Point"}
}