{
  "type": "Feature",
  "properties": {
    "iso:country":"ES",
    "sg:address":"Muel Santa Catalina, S/n",
    "sg:city":"Palmas De Gran Canaria",
    "sg:orig_category":"Lencer\u00cda Femenina, Corseter\u00cda, Trajes De Ba\u00d1o (al Por Menor)",
    "sg:phone":"+34 928 22 23 66",
    "sg:postcode":"35008",
    "sg:province":"Las Palmas",
    "wof:name":"Susuwoman 2000 S.l.",
    "wof:placetype":"venue"
},
  "geometry": {"coordinates":[-15.4279222488,28.1409034729],"type":"Point"}
}