{
  "type": "Feature",
  "properties": {
    "iso:country":"ES",
    "sg:address":"Carrer de Badajoz, S/n",
    "sg:city":"Miami Playa",
    "sg:orig_category":"Polideportivos",
    "sg:phone":"+34 977 17 05 72",
    "sg:postcode":"43892",
    "sg:province":"Tarragona",
    "wof:name":"Ajuntament De Mont-roig Del Camp",
    "wof:placetype":"venue"
},
  "geometry": {"coordinates":[0.9254534841,41.006023407],"type":"Point"}
}