{
  "type": "Feature",
  "properties": {
    "iso:country":"ES",
    "sg:address":"Partida Valpodrida, S/n",
    "sg:city":"Berge",
    "sg:orig_category":"Poller\u00cda Y Caza (al Por Menor)",
    "sg:phone":"+34 978 84 97 02",
    "sg:postcode":"44556",
    "sg:province":"Teruel",
    "wof:name":"Alemar Avicola S.l.u",
    "wof:placetype":"venue"
},
  "geometry": {"coordinates":[-0.4266439974,40.8569107056],"type":"Point"}
}