{
  "type": "Feature",
  "properties": {
    "addr:full":"Carr Paisos Catalans, 1 Hostalric Girona 17450",
    "addr:housenumber":"1",
    "addr:postcode":"17450",
    "addr:street":"Carr Paisos Catalans",
    "iso:country":"ES",
    "sg:address":"Carr Paisos Catalans, 1",
    "sg:city":"Hostalric",
    "sg:orig_category":"Empresarios",
    "sg:phone":"+34 972 86 42 42",
    "sg:postcode":"17450",
    "sg:province":"Girona",
    "wof:name":"Sau Teodoro Jose",
    "wof:placetype":"venue"
},
  "geometry": {"coordinates":[2.627409935,41.7412261963],"type":"Point"}
}