{
  "type": "Feature",
  "properties": {
    "iso:country":"ES",
    "sg:address":"Pl. Merced, S/n",
    "sg:city":"Martos",
    "sg:orig_category":"Promotores Constructores",
    "sg:phone":"+34 953 55 35 23",
    "sg:postcode":"23600",
    "sg:province":"Ja\u00e9n",
    "wof:name":"Cooperativa Andaluza Construmar",
    "wof:placetype":"venue"
},
  "geometry": {"coordinates":[-3.971973896,37.7217330933],"type":"Point"}
}