{
  "type": "Feature",
  "properties": {
    "iso:country":"ES",
    "sg:address":"Antonio Guirao, S/n",
    "sg:city":"Moratalla",
    "sg:orig_category":"Molduras, Junquillos, Listones Y Molduras Perforadas",
    "sg:phone":"+34 968 70 60 21",
    "sg:postcode":"30440",
    "sg:province":"Murcia",
    "wof:name":"Fernandez Sanchez Adolfo",
    "wof:placetype":"venue"
},
  "geometry": {"coordinates":[-1.8894790411,38.1866531372],"type":"Point"}
}