{
  "type": "Feature",
  "properties": {
    "iso:country":"ES",
    "sg:address":"Calle de Mayor, S/n",
    "sg:city":"Rincon Beniscornia",
    "sg:orig_category":"Cajas Para Embalar",
    "sg:phone":"+34 968 27 42 28",
    "sg:postcode":"30108",
    "sg:province":"Murcia",
    "sg:website":"www.cajamar.es",
    "wof:name":"Cajamar",
    "wof:placetype":"venue"
},
  "geometry": {"coordinates":[-1.1762139797,37.9861755371],"type":"Point"}
}