{
  "type": "Feature",
  "properties": {
    "addr:full":"Calle de Mayor, S/n Rincon Beniscornia Murcia 30108",
    "addr:housenumber":"s / n",
    "addr:postcode":"30108",
    "addr:street":"Calle De Mayor",
    "iso:country":"ES",
    "sg:address":"Calle de Mayor, S/n",
    "sg:city":"Rincon Beniscornia",
    "sg:orig_category":"Cajas Para Embalar",
    "sg:phone":"+34 968 27 42 28",
    "sg:postcode":"30108",
    "sg:province":"Murcia",
    "sg:website":"www.cajamar.es",
    "wof:name":"Cajamar",
    "wof:placetype":"venue"
},
  "geometry": {"coordinates":[-1.1762139797,37.9861755371],"type":"Point"}
}