{
  "type": "Feature",
  "properties": {
    "addr:full":"Calle de Salmeron, 11 Elda Alicante 03600",
    "addr:housenumber":"11",
    "addr:postcode":"03600",
    "addr:street":"Calle De Salmeron",
    "iso:country":"ES",
    "sg:address":"Calle de Salmeron, 11",
    "sg:city":"Elda",
    "sg:orig_category":"Confecci\u00d3n De Zapatos",
    "sg:phone":"+34 965 39 35 33",
    "sg:postcode":"03600",
    "sg:province":"Alicante",
    "sg:website":"sogorbmac@terra.es",
    "wof:name":"Sogorbmac S.l.",
    "wof:placetype":"venue"
},
  "geometry": {"coordinates":[-0.7897846103,38.4815979004],"type":"Point"}
}