{
  "type": "Feature",
  "properties": {
    "addr:full":"Avda Alicante, 21 Denia Alicante 03700",
    "addr:housenumber":"21",
    "addr:postcode":"03700",
    "addr:street":"Avda Alicante",
    "iso:country":"ES",
    "sg:address":"Avda Alicante, 21",
    "sg:city":"Denia",
    "sg:orig_category":"Mec\u00c1nico Del Autom\u00d3vil",
    "sg:phone":"+34 965 78 25 67",
    "sg:postcode":"03700",
    "sg:province":"Alicante",
    "wof:name":"Pastor Rosello Teresa Clara",
    "wof:placetype":"venue"
},
  "geometry": {"coordinates":[0.1002689973,38.8385925293],"type":"Point"}
}