{
  "type": "Feature",
  "properties": {
    "addr:full":"Calle de Santa Cristina, 6 Ejido Almer\u00eda 04700",
    "addr:housenumber":"6",
    "addr:postcode":"04700",
    "addr:street":"Calle De Santa Cristina;Almeri\u0301A",
    "iso:country":"ES",
    "sg:address":"Calle de Santa Cristina, 6",
    "sg:city":"Ejido",
    "sg:classifiers":[
        {
            "category":"Taxi",
            "type":"Transportation"
        }
    ],
    "sg:phone":"+34 950 48 02 24",
    "sg:postcode":"04700",
    "sg:province":"Almer\u00eda",
    "wof:name":"Fernandez Martin Mariano",
    "wof:placetype":"venue"
},
  "geometry": {"coordinates":[-2.8093121052,36.7761421204],"type":"Point"}
}