{
  "type": "Feature",
  "properties": {
    "addr:full":"Plaz Domingo Miral, S/n Anso Huesca 22728",
    "addr:housenumber":"s / n",
    "addr:postcode":"22728",
    "addr:street":"Plaz Domingo Miral",
    "iso:country":"ES",
    "sg:address":"Plaz Domingo Miral, S/n",
    "sg:city":"Anso",
    "sg:orig_category":"Cajas Para Embalar",
    "sg:phone":"+34 974 37 00 58",
    "sg:postcode":"22728",
    "sg:province":"Huesca",
    "wof:name":"Caja Rural Aragonesa Y De Los Pirineos",
    "wof:placetype":"venue"
},
  "geometry": {"coordinates":[-0.8289290071,42.7555236816],"type":"Point"}
}