{
  "type": "Feature",
  "properties": {
    "addr:full":"Calle de Santa Maria, 4 Puerto De Santa Maria C\u00e1diz 11500",
    "addr:housenumber":"4",
    "addr:postcode":"11500",
    "addr:street":"Calle De Santa Maria;Ca\u0301Diz",
    "iso:country":"ES",
    "sg:address":"Calle de Santa Maria, 4",
    "sg:city":"Puerto De Santa Maria",
    "sg:orig_category":"Reposter\u00cdas",
    "sg:phone":"+34 956 85 23 25",
    "sg:postcode":"11500",
    "sg:province":"C\u00e1diz",
    "wof:name":"Panaderia Bolleria Santa Maria S.l.",
    "wof:placetype":"venue"
},
  "geometry": {"coordinates":[-6.2269229889,36.600112915],"type":"Point"}
}