{
  "type": "Feature",
  "properties": {
    "iso:country":"ES",
    "sg:address":"Calle de Camino De Las Nieves, 32",
    "sg:city":"Arcos Frontera",
    "sg:orig_category":"Plomeros",
    "sg:phone":"+34 956 70 13 81",
    "sg:postcode":"11630",
    "sg:province":"C\u00e1diz",
    "wof:name":"Obrians Arcos S.l.",
    "wof:placetype":"venue"
},
  "geometry": {"coordinates":[-5.8082647324,36.7505226135],"type":"Point"}
}