{
  "type": "Feature",
  "properties": {
    "iso:country":"ES",
    "sg:address":"Albatros, 75",
    "sg:city":"Punta Umbria",
    "sg:orig_category":"Distribuci\u00d3n De Petr\u00d3leo Y Derivados",
    "sg:phone":"+34 959 52 84 14",
    "sg:postcode":"21100",
    "sg:province":"Huelva",
    "wof:name":"Pescados Daconmar S.l.",
    "wof:placetype":"venue"
},
  "geometry": {"coordinates":[-7.0448889732,37.2101631165],"type":"Point"}
}