{
  "type": "Feature",
  "properties": {
    "addr:full":"Calle de Camaron De La Isla, S/n Jerez De La Frontera C\u00e1diz 11405",
    "addr:postcode":"11405",
    "addr:street":"Calle De Camaron De La Isla S / N",
    "iso:country":"ES",
    "sg:address":"Calle de Camaron De La Isla, S/n",
    "sg:city":"Jerez De La Frontera",
    "sg:orig_category":"Promotores Constructores",
    "sg:phone":"+34 956 39 64 64",
    "sg:postcode":"11405",
    "sg:province":"C\u00e1diz",
    "wof:name":"Imasatec S.a.",
    "wof:placetype":"venue"
},
  "geometry": {"coordinates":[-6.1127061844,36.6934089661],"type":"Point"}
}