{
  "type": "Feature",
  "properties": {
    "iso:country":"ES",
    "sg:address":"Calle de Carlet, 1",
    "sg:city":"Alacant",
    "sg:orig_category":"Seguridad En El Trabajo Y Prevenci\u00d3n De Riesgos Laborales",
    "sg:phone":"+34 965 13 31 71",
    "sg:postcode":"03007",
    "sg:province":"Alicante",
    "wof:name":"Grupo Mgo S.a.",
    "wof:placetype":"venue"
},
  "geometry": {"coordinates":[-0.4947145879,38.3418769836],"type":"Point"}
}