{
  "type": "Feature",
  "properties": {
    "iso:country":"ES",
    "sg:address":"C/ Sant Tomas, 21",
    "sg:city":"Alcoi",
    "sg:orig_category":"Materias Pl\u00c1sticas: Productos De Consumo Masivo (fabricaci\u00d3n, Al Por Mayor)",
    "sg:phone":"+34 965 54 37 19",
    "sg:postcode":"03801",
    "sg:province":"Alicante",
    "wof:name":"Calero Pico Antonio",
    "wof:placetype":"venue"
},
  "geometry": {"coordinates":[-0.4744989872,38.6992912292],"type":"Point"}
}