{
  "type": "Feature",
  "properties": {
    "addr:full":"Calle de Prim, 17 Bilbao Vizcaya 48006",
    "addr:housenumber":"17",
    "addr:postcode":"48006",
    "addr:street":"Calle De Prim",
    "iso:country":"ES",
    "sg:address":"Calle de Prim, 17",
    "sg:city":"Bilbao",
    "sg:orig_category":"Cristaler\u00cdas",
    "sg:phone":"+34 944 16 01 13",
    "sg:postcode":"48006",
    "sg:province":"Vizcaya",
    "wof:name":"Luis Miralles Ruiz",
    "wof:placetype":"venue"
},
  "geometry": {"coordinates":[-2.9187240601,43.2582359314],"type":"Point"}
}