{
  "type": "Feature",
  "properties": {
    "iso:country":"ES",
    "sg:address":"Pl Carros (dels), 11",
    "sg:city":"Tarragona",
    "sg:orig_category":"Molduras, Junquillos, Listones Y Molduras Perforadas",
    "sg:phone":"+34 977 22 68 26",
    "sg:postcode":"43004",
    "sg:province":"Tarragona",
    "wof:name":"Galais  Christian Jose",
    "wof:placetype":"venue"
},
  "geometry": {"coordinates":[1.2499569654,41.1108055115],"type":"Point"}
}