{
  "type": "Feature",
  "properties": {
    "iso:country":"ES",
    "sg:address":"Av Alacant, 39",
    "sg:city":"Mutxamel",
    "sg:orig_category":"Mec\u00c1nico Del Autom\u00d3vil",
    "sg:phone":"+34 965 95 24 35",
    "sg:postcode":"03110",
    "sg:province":"Alicante",
    "wof:name":"Talleres Y Automoviles Antonio Lopez S.l",
    "wof:placetype":"venue"
},
  "geometry": {"coordinates":[-0.4414950013,38.4095535278],"type":"Point"}
}