{
  "type": "Feature",
  "properties": {
    "iso:country":"ES",
    "sg:address":"Calle de Estacion (la), 8",
    "sg:city":"Aznalcollar",
    "sg:orig_category":"Alimentaci\u00d3n General (al Por Mayor)",
    "sg:phone":"+34 954 13 58 07",
    "sg:postcode":"41870",
    "sg:province":"Sevilla",
    "wof:name":"Distribuciones Manrique Ruiz S.l.",
    "wof:placetype":"venue"
},
  "geometry": {"coordinates":[-6.2640018463,37.5161552429],"type":"Point"}
}