{
  "type": "Feature",
  "properties": {
    "addr:full":"C/ Bisbe Taixequet, 8 Llucmajor Islas Baleares 07620",
    "addr:housenumber":"8",
    "addr:postcode":"07620",
    "addr:street":"C / Bisbe Taixequet",
    "iso:country":"ES",
    "sg:address":"C/ Bisbe Taixequet, 8",
    "sg:city":"Llucmajor",
    "sg:orig_category":"\u00d3ptica: Instrumentos (fabricaci\u00d3n)",
    "sg:phone":"+34 971 12 10 98",
    "sg:postcode":"07620",
    "sg:province":"Islas Baleares",
    "wof:name":"Di Cardore Sl",
    "wof:placetype":"venue"
},
  "geometry": {"coordinates":[2.8904299736,39.4896125793],"type":"Point"}
}