{
  "type": "Feature",
  "properties": {
    "iso:country":"ES",
    "sg:address":"Calle de Gran Via, 31",
    "sg:city":"Madrid",
    "sg:orig_category":"Inmobiliaria (agencias)",
    "sg:phone":"+34 915 22 44 21",
    "sg:postcode":"28013",
    "sg:province":"Madrid",
    "wof:name":"Abando Full Golf S.l.",
    "wof:placetype":"venue"
},
  "geometry": {"coordinates":[-3.703732,40.420097],"type":"Point"}
}