{
  "type": "Feature",
  "properties": {
    "iso:country":"ES",
    "sg:address":"Carr Llibertat, 137",
    "sg:city":"Vilanova I La Geltru",
    "sg:orig_category":"Poller\u00cda Y Caza (al Por Menor)",
    "sg:phone":"+34 938 15 90 40",
    "sg:postcode":"08800",
    "sg:province":"Barcelona",
    "wof:name":"Alba Valles S.l.",
    "wof:placetype":"venue"
},
  "geometry": {"coordinates":[1.7293442488,41.218296051],"type":"Point"}
}