{
  "type": "Feature",
  "properties": {
    "addr:full":"Avda Asturias, 85 Palencia Palencia 34005",
    "addr:housenumber":"85",
    "addr:postcode":"34005",
    "addr:street":"Avda Asturias",
    "iso:country":"ES",
    "sg:address":"Avda Asturias, 85",
    "sg:city":"Palencia",
    "sg:orig_category":"Empresas De Carpinter\u00cda De Madera",
    "sg:phone":"+34 979 74 23 70",
    "sg:postcode":"34005",
    "sg:province":"Palencia",
    "wof:name":"Tejerina Gonzalo Simon",
    "wof:placetype":"venue"
},
  "geometry": {"coordinates":[-4.5456590652,42.0223312378],"type":"Point"}
}