{
  "type": "Feature",
  "properties": {
    "iso:country":"ES",
    "sg:address":"Calle de Reyes De Navarra, 1 E",
    "sg:city":"Vitoria-gasteiz",
    "sg:orig_category":"Cajas Y Embalajes De Cart\u00d3n Y Papel",
    "sg:phone":"+34 945 00 12 51",
    "sg:postcode":"01002",
    "sg:province":"\u00c1lava",
    "wof:name":"Envases Vicmar, S.a.",
    "wof:placetype":"venue"
},
  "geometry": {"coordinates":[-2.6658289433,42.8547668457],"type":"Point"}
}