{
  "type": "Feature",
  "properties": {
    "addr:full":"Rbla Rambla, 186 Sabadell Barcelona 08201",
    "addr:postcode":"08201",
    "addr:street":"Rambla 186",
    "iso:country":"ES",
    "sg:address":"Rbla Rambla, 186",
    "sg:city":"Sabadell",
    "sg:orig_category":"Reposter\u00cdas",
    "sg:phone":"+34 937 25 51 16",
    "sg:postcode":"08201",
    "sg:province":"Barcelona",
    "wof:name":"Aregall Urgelles Montserrat",
    "wof:placetype":"venue"
},
  "geometry": {"coordinates":[2.1120710373,41.5403327942],"type":"Point"}
}