{
  "type": "Feature",
  "properties": {
    "addr:full":"Av Levante, 29 Beniparrell Valencia 46469",
    "addr:housenumber":"29",
    "addr:postcode":"46469",
    "addr:street":"Av Levante",
    "iso:country":"ES",
    "sg:address":"Av Levante, 29",
    "sg:city":"Beniparrell",
    "sg:orig_category":"Fabricaci\u00d3n De Muebles",
    "sg:phone":"+34 961 20 01 87",
    "sg:postcode":"46469",
    "sg:province":"Valencia",
    "wof:name":"Primo Iborra Maria Paz",
    "wof:placetype":"venue"
},
  "geometry": {"coordinates":[-0.4116789997,39.383228302],"type":"Point"}
}