{
  "type": "Feature",
  "properties": {
    "iso:country":"ES",
    "sg:address":"Calle de Doreste Y Molina, S/n",
    "sg:city":"Puerto Rico",
    "sg:orig_category":"Bazares, Art\u00cdculos De Limpieza Y De Cocina (al Por Menor)",
    "sg:phone":"+34 928 56 18 35",
    "sg:postcode":"35130",
    "sg:province":"Las Palmas",
    "wof:name":"Manglani Vijay Vasudev",
    "wof:placetype":"venue"
},
  "geometry": {"coordinates":[-15.7118616104,27.7871952057],"type":"Point"}
}