{
  "type": "Feature",
  "properties": {
    "iso:country":"ES",
    "sg:address":"Send Jose Luis Gonzalo-bilbao, 9",
    "sg:city":"Vitoria-gasteiz",
    "sg:orig_category":"Cl\u00cdnicas M\u00c9dicas",
    "sg:phone":"+34 945 21 74 69",
    "sg:postcode":"01008",
    "sg:province":"\u00c1lava",
    "wof:name":"Mutua Universal Mugenat",
    "wof:placetype":"venue"
},
  "geometry": {"coordinates":[-2.6879570484,42.8509941101],"type":"Point"}
}