{
  "type": "Feature",
  "properties": {
    "addr:full":"Calle de Carmen, 9 Alcaudete Ja\u00e9n 23660",
    "addr:housenumber":"9",
    "addr:postcode":"23660",
    "addr:street":"Calle De Carmen;Jae\u0301N",
    "iso:country":"ES",
    "sg:address":"Calle de Carmen, 9",
    "sg:city":"Alcaudete",
    "sg:orig_category":"\u00d3ptica: Instrumentos (fabricaci\u00d3n)",
    "sg:phone":"+34 953 56 13 67",
    "sg:postcode":"23660",
    "sg:province":"Ja\u00e9n",
    "wof:name":"Delgado Tordera Rafael",
    "wof:placetype":"venue"
},
  "geometry": {"coordinates":[-4.0856580734,37.5908546448],"type":"Point"}
}