{
  "type": "Feature",
  "properties": {
    "addr:full":"Masterreka Kalea, 20 Bergara Guip\u00f9zcoa 20570",
    "addr:housenumber":"20",
    "addr:postcode":"20570",
    "addr:street":"Masterreka Kalea;Guipu\u0300Zcoa",
    "iso:country":"ES",
    "sg:address":"Masterreka Kalea, 20",
    "sg:city":"Bergara",
    "sg:orig_category":"Molduras, Junquillos, Listones Y Molduras Perforadas",
    "sg:phone":"+34 943 76 57 71",
    "sg:postcode":"20570",
    "sg:province":"Guip\u00f9zcoa",
    "wof:name":"Poza Lobo Victor Julian",
    "wof:placetype":"venue"
},
  "geometry": {"coordinates":[-2.4126479626,43.1194915771],"type":"Point"}
}