{
  "type": "Feature",
  "properties": {
    "addr:full":"Avda Brasil, 15 Madrid Madrid 28020",
    "addr:housenumber":"15",
    "addr:postcode":"madrid;28020",
    "addr:street":"Avda Brasil",
    "iso:country":"ES",
    "sg:address":"Avda Brasil, 15",
    "sg:city":"Madrid",
    "sg:orig_category":"Aparcamientos (infraestructuras, Accesorios)",
    "sg:phone":"+34 915 55 72 44",
    "sg:postcode":"28020",
    "sg:province":"Madrid",
    "wof:name":"Comunidad Usuarios Del Estacionamiento Residentes General Yague",
    "wof:placetype":"venue"
},
  "geometry": {"coordinates":[-3.6934370995,40.4566078186],"type":"Point"}
}