{
  "type": "Feature",
  "properties": {
    "addr:full":"Calle de Obispo Estenaga, 4 Ciudad Real Ciudad Real 13002",
    "addr:housenumber":"4",
    "addr:postcode":"13002",
    "addr:street":"Calle De Obispo Estenaga",
    "iso:country":"ES",
    "sg:address":"Calle de Obispo Estenaga, 4",
    "sg:city":"Ciudad Real",
    "sg:orig_category":"M\u00c9dicos: Medicina General",
    "sg:phone":"+34 926 21 59 22",
    "sg:postcode":"13002",
    "sg:province":"Ciudad Real",
    "wof:name":"Pagador Gonzalez De La Higuera Carmen",
    "wof:placetype":"venue"
},
  "geometry": {"coordinates":[-3.9315550327,38.9837341309],"type":"Point"}
}