{
  "type": "Feature",
  "properties": {
    "addr:full":"Calle de Bernart Etxepare, 10 Kurtzea Vizcaya 48960",
    "addr:housenumber":"10",
    "addr:postcode":"48960",
    "addr:street":"Calle De Bernart Etxepare",
    "iso:country":"ES",
    "sg:address":"Calle de Bernart Etxepare, 10",
    "sg:city":"Kurtzea",
    "sg:orig_category":"Fabricaci\u00d3n De Juegos Y Juguetes",
    "sg:phone":"+34 944 36 70 16",
    "sg:postcode":"48960",
    "sg:province":"Vizcaya",
    "wof:name":"Gozo Txori S.l.",
    "wof:placetype":"venue"
},
  "geometry": {"coordinates":[-2.8434097767,43.2316131592],"type":"Point"}
}