{
  "type": "Feature",
  "properties": {
    "addr:full":"Calle de Republica Argentina, 13 Valencia Valencia 46021",
    "addr:housenumber":"13",
    "addr:postcode":"46021",
    "addr:street":"Calle De Republica Argentina",
    "iso:country":"ES",
    "sg:address":"Calle de Republica Argentina, 13",
    "sg:city":"Valencia",
    "sg:orig_category":"Agencias Y Agentes Comerciales, Representantes",
    "sg:phone":"+34 963 69 43 11",
    "sg:postcode":"46021",
    "sg:province":"Valencia",
    "wof:name":"Serra Verdeguer Ricardo",
    "wof:placetype":"venue"
},
  "geometry": {"coordinates":[-0.3517270088,39.4726295471],"type":"Point"}
}