{
  "type": "Feature",
  "properties": {
    "addr:full":"Calle de Zamora (de), 18 Fuenlabrada Madrid 28941",
    "addr:housenumber":"18",
    "addr:postcode":"28941",
    "addr:street":"Calle De Zamora De",
    "iso:country":"ES",
    "sg:address":"Calle de Zamora (de), 18",
    "sg:city":"Fuenlabrada",
    "sg:orig_category":"Estancos",
    "sg:phone":"+34 916 85 62 92",
    "sg:postcode":"28941",
    "sg:province":"Madrid",
    "wof:name":"Rodriguez Garcia Cristina",
    "wof:placetype":"venue"
},
  "geometry": {"coordinates":[-3.801733017,40.2952613831],"type":"Point"}
}