{
  "type": "Feature",
  "properties": {
    "addr:full":"Calle de Pilar Del, 15 Fraga Huesca 22520",
    "addr:housenumber":"15",
    "addr:postcode":"22520",
    "addr:street":"Calle De Pilar Del",
    "iso:country":"ES",
    "sg:address":"Calle de Pilar Del, 15",
    "sg:city":"Fraga",
    "sg:orig_category":"Administradores De Bienes Y Delegados De Comunidades De Propietarios",
    "sg:phone":"+34 974 47 08 93",
    "sg:postcode":"22520",
    "sg:province":"Huesca",
    "wof:name":"Martin Costa Armando",
    "wof:placetype":"venue"
},
  "geometry": {"coordinates":[0.3490802944,41.5209999084],"type":"Point"}
}