{
  "type": "Feature",
  "properties": {
    "addr:full":"Calle de Encomienda, S/n Totana Murcia 30850",
    "addr:housenumber":"s / n",
    "addr:postcode":"30850",
    "addr:street":"Calle De Encomienda",
    "iso:country":"ES",
    "sg:address":"Calle de Encomienda, S/n",
    "sg:city":"Totana",
    "sg:orig_category":"Centros De Educaci\u00d3n Especial",
    "sg:phone":"+34 968 42 05 82",
    "sg:postcode":"30850",
    "sg:province":"Murcia",
    "wof:name":"Colegio Publico Santiago",
    "wof:placetype":"venue"
},
  "geometry": {"coordinates":[-1.4986790419,37.7686004639],"type":"Point"}
}