{
  "type": "Feature",
  "properties": {
    "iso:country":"ES",
    "sg:address":"Carrer de Doctor Ferran, 99",
    "sg:city":"Esplugues Llobregat",
    "sg:orig_category":"Agencias Y Agentes Comerciales, Representantes",
    "sg:phone":"+34 933 71 75 22",
    "sg:postcode":"08950",
    "sg:province":"Barcelona",
    "wof:name":"Domenech Guillen Juan",
    "wof:placetype":"venue"
},
  "geometry": {"coordinates":[2.0859370232,41.3886947632],"type":"Point"}
}