{
  "type": "Feature",
  "properties": {
    "addr:full":"Carrer de Barcelona, 54 Senia Tarragona 43560",
    "addr:housenumber":"54",
    "addr:postcode":"43560",
    "addr:street":"Carrer De Barcelona",
    "iso:country":"ES",
    "sg:address":"Carrer de Barcelona, 54",
    "sg:city":"Senia",
    "sg:orig_category":"Muebles, Minoristas",
    "sg:phone":"+34 977 57 60 94",
    "sg:postcode":"43560",
    "sg:province":"Tarragona",
    "sg:website":"www.nuevalinea.es",
    "wof:name":"Max & Top Indice S.l.",
    "wof:placetype":"venue"
},
  "geometry": {"coordinates":[0.2883200049,40.6326904297],"type":"Point"}
}