{
  "type": "Feature",
  "properties": {
    "addr:full":"San Frantzisko Kalea, 25 Zarautz Guip\u00f9zcoa 20800",
    "addr:housenumber":"25",
    "addr:postcode":"20800",
    "addr:street":"San Frantzisko Kalea;Guipu\u0300Zcoa",
    "iso:country":"ES",
    "sg:address":"San Frantzisko Kalea, 25",
    "sg:city":"Zarautz",
    "sg:orig_category":"Alimentaci\u00d3n General (al Por Menor)",
    "sg:phone":"+34 943 83 37 97",
    "sg:postcode":"20800",
    "sg:province":"Guip\u00f9zcoa",
    "wof:name":"Frutas Dioni S. L.",
    "wof:placetype":"venue"
},
  "geometry": {"coordinates":[-2.1741979122,43.2849464417],"type":"Point"}
}