{
  "type": "Feature",
  "properties": {
    "iso:country":"ES",
    "sg:address":"Carr Mossen Ramon Viladrich, 4",
    "sg:city":"Mollerussa",
    "sg:orig_category":"Reposter\u00cdas",
    "sg:phone":"+34 973 60 01 37",
    "sg:postcode":"25230",
    "sg:province":"Lleida",
    "wof:name":"Guiu Duacastella Jose Maria",
    "wof:placetype":"venue"
},
  "geometry": {"coordinates":[0.8942859769,41.6252784729],"type":"Point"}
}