{
  "type": "Feature",
  "properties": {
    "addr:full":"Carr De Ramon Y Cajal, 47 Benicarlo Castell\u00f3n 12580",
    "addr:housenumber":"47",
    "addr:postcode":"12580",
    "addr:street":"Carr De Ramon Y Cajal",
    "iso:country":"ES",
    "sg:address":"Carr De Ramon Y Cajal, 47",
    "sg:city":"Benicarlo",
    "sg:orig_category":"Electricidad: Instaladores",
    "sg:phone":"+34 964 46 07 66",
    "sg:postcode":"12580",
    "sg:province":"Castell\u00f3n",
    "wof:name":"Montajes Electricos Ferreres S.l.",
    "wof:placetype":"venue"
},
  "geometry": {"coordinates":[0.4042100012,40.4457893372],"type":"Point"}
}