{
  "type": "Feature",
  "properties": {
    "iso:country":"ES",
    "sg:address":"Avda Andalucia, 81",
    "sg:city":"Estepona",
    "sg:orig_category":"Seguridad Social",
    "sg:phone":"+34 952 80 15 67",
    "sg:postcode":"29680",
    "sg:province":"M\u00e1laga",
    "sg:website":"www.fremap.es",
    "wof:name":"Fremap Mutua De Accidentes De Trabajo Y Enferm.profes.de S.s.61",
    "wof:placetype":"venue"
},
  "geometry": {"coordinates":[-5.1446008682,36.4311676025],"type":"Point"}
}