{
  "type": "Feature",
  "properties": {
    "iso:country":"ES",
    "sg:address":"Ctra Zorrotza-kastrexana, 29",
    "sg:city":"Bilbao",
    "sg:orig_category":"Cl\u00cdnicas Dentales",
    "sg:phone":"+34 944 27 63 26",
    "sg:postcode":"48013",
    "sg:province":"Vizcaya",
    "wof:name":"Ortiz De Zarate Maguregui Nicanor",
    "wof:placetype":"venue"
},
  "geometry": {"coordinates":[-2.9728450775,43.274772644],"type":"Point"}
}