{
  "type": "Feature",
  "properties": {
    "addr:full":"Avgd Barcelona, 27 Igualada Barcelona 08700",
    "addr:housenumber":"27",
    "addr:postcode":"08700",
    "iso:country":"ES",
    "sg:address":"Avgd Barcelona, 27",
    "sg:city":"Igualada",
    "sg:orig_category":"Importaci\u00d3n",
    "sg:phone":"+34 938 04 11 92",
    "sg:postcode":"08700",
    "sg:province":"Barcelona",
    "wof:name":"Comercial De Importacion Y Exportacion Jimex S.l.",
    "wof:placetype":"venue"
},
  "geometry": {"coordinates":[1.6183509827,41.5856208801],"type":"Point"}
}