{
  "type": "Feature",
  "properties": {
    "addr:full":"Cra. Dosrius, 187 Cardedeu Barcelona 08440",
    "addr:housenumber":"187",
    "addr:postcode":"08440",
    "iso:country":"ES",
    "sg:address":"Cra. Dosrius, 187",
    "sg:city":"Cardedeu",
    "sg:orig_category":"Limpieza Con Chorro De Arena Y Con Granalla, Pulido",
    "sg:phone":"+34 938 71 13 49",
    "sg:postcode":"08440",
    "sg:province":"Barcelona",
    "wof:name":"Martinez Martinez Jose",
    "wof:placetype":"venue"
},
  "geometry": {"coordinates":[2.3624069691,41.6302528381],"type":"Point"}
}