{
  "type": "Feature",
  "properties": {
    "addr:full":"Calle de Trespaderne, 9 Madrid Madrid 28042",
    "addr:housenumber":"9",
    "addr:postcode":"madrid;28042",
    "addr:street":"Calle De Trespaderne",
    "iso:country":"ES",
    "sg:address":"Calle de Trespaderne, 9",
    "sg:city":"Madrid",
    "sg:orig_category":"Asociaciones Humanitarias, De Cooperaci\u00d3n, De Acci\u00d3n Social",
    "sg:phone":"+34 917 47 80 04",
    "sg:postcode":"28042",
    "sg:province":"Madrid",
    "wof:name":"Asociacion De Empleados De Iberia Padres De Minusvalidos",
    "wof:placetype":"venue"
},
  "geometry": {"coordinates":[-3.5844430923,40.4531059265],"type":"Point"}
}