{
  "type": "Feature",
  "properties": {
    "iso:country":"ES",
    "sg:address":"Ctra Binefar, S/n",
    "sg:city":"Estadilla",
    "sg:orig_category":"Material Y Suministros Para Perforaciones, Sondeos",
    "sg:phone":"+34 974 30 53 49",
    "sg:postcode":"22423",
    "sg:province":"Huesca",
    "wof:name":"Martinez Ortigues Jesus",
    "wof:placetype":"venue"
},
  "geometry": {"coordinates":[0.238064006,42.0571136475],"type":"Point"}
}