{
  "type": "Feature",
  "properties": {
    "addr:full":"Monta\u00f1a De Tejina, 10 Adeje Santa Cruz De Tenerife 38670",
    "addr:housenumber":"10",
    "addr:postcode":"38670",
    "iso:country":"ES",
    "sg:address":"Monta\u00f1a De Tejina, 10",
    "sg:city":"Adeje",
    "sg:orig_category":"Vinos Y Licores (venta Al Por Menor)",
    "sg:phone":"+34 922 71 08 81",
    "sg:postcode":"38670",
    "sg:province":"Santa Cruz De Tenerife",
    "sg:website":"www.ladespensa.net",
    "wof:name":"Prosub Canarias S.l.",
    "wof:placetype":"venue"
},
  "geometry": {"coordinates":[-16.724899292,28.1215400696],"type":"Point"}
}