{
  "type": "Feature",
  "properties": {
    "iso:country":"ES",
    "sg:address":"Av Carles Buigas (de), 8",
    "sg:city":"Salou",
    "sg:orig_category":"Discotecas Y Salas De Baile",
    "sg:phone":"+34 977 38 46 58",
    "sg:postcode":"43840",
    "sg:province":"Tarragona",
    "wof:name":"Reverter Bosh Antonio",
    "wof:placetype":"venue"
},
  "geometry": {"coordinates":[1.1458539963,41.0729522705],"type":"Point"}
}