{
  "type": "Feature",
  "properties": {
    "iso:country":"ES",
    "sg:address":"Carrer de Aritjols, 91",
    "sg:city":"Barcelona",
    "sg:orig_category":"Empresas De Carpinter\u00cda De Madera",
    "sg:phone":"+34 933 59 12 43",
    "sg:postcode":"08016",
    "sg:province":"Barcelona",
    "wof:name":"Castro Cano Nicolas",
    "wof:placetype":"venue"
},
  "geometry": {"coordinates":[2.1836359501,41.4443397522],"type":"Point"}
}