{
  "type": "Feature",
  "properties": {
    "iso:country":"ES",
    "sg:address":"Calle de Calzada, 9",
    "sg:city":"Valencia Ventoso",
    "sg:orig_category":"Quincaller\u00cda (al Por Menor)",
    "sg:phone":"+34 924 56 27 89",
    "sg:postcode":"06330",
    "sg:province":"Badajoz",
    "wof:name":"Supertienfer",
    "wof:placetype":"venue"
},
  "geometry": {"coordinates":[-6.4764938354,38.2654762268],"type":"Point"}
}