{
  "type": "Feature",
  "properties": {
    "iso:country":"ES",
    "sg:address":"Cmno Ronda, 194",
    "sg:city":"Monta\u00d1ana",
    "sg:orig_category":"Promotores Constructores",
    "sg:phone":"+34 976 57 52 51",
    "sg:postcode":"50059",
    "sg:province":"Zaragoza",
    "wof:name":"Ascaso Salvador Jesus",
    "wof:placetype":"venue"
},
  "geometry": {"coordinates":[-0.8225629926,41.6761932373],"type":"Point"}
}