{
  "type": "Feature",
  "properties": {
    "addr:full":"Marie Curie (pque Tecnologico), 14 Parque Tecnologico M\u00e1laga 29590",
    "addr:housenumber":"14",
    "addr:postcode":"29590",
    "addr:street":"Marie;Pque Tecnologico;Ma\u0301Laga",
    "iso:country":"ES",
    "sg:address":"Marie Curie (pque Tecnologico), 14",
    "sg:city":"Parque Tecnologico",
    "sg:orig_category":"Agencias Y Asesores De Publicidad",
    "sg:phone":"+34 952 02 03 97",
    "sg:postcode":"29590",
    "sg:province":"M\u00e1laga",
    "wof:name":"Novasoft Corporacion Empresarial S.l.",
    "wof:placetype":"venue"
},
  "geometry": {"coordinates":[-4.5224900246,36.7190055847],"type":"Point"}
}