{
  "type": "Feature",
  "properties": {
    "addr:full":"Fontan, Km. 0023,4 Fontan Pontevedra 36388",
    "addr:postcode":"36388",
    "iso:country":"ES",
    "sg:address":"Fontan, Km. 0023,4",
    "sg:city":"Fontan",
    "sg:orig_category":"Distribuci\u00d3n De Petr\u00d3leo Y Derivados",
    "sg:phone":"+34 986 38 91 11",
    "sg:postcode":"36388",
    "sg:province":"Pontevedra",
    "wof:name":"Irene Alonso E Hijos S.l.",
    "wof:placetype":"venue"
},
  "geometry": {"coordinates":[-8.7831964493,42.1088485718],"type":"Point"}
}