{
  "type": "Feature",
  "properties": {
    "addr:full":"Rbla Catalunya, 88 Barcelona Barcelona 08008",
    "addr:housenumber":"88",
    "addr:postcode":"08008",
    "addr:street":"Rbla Catalunya",
    "iso:country":"ES",
    "sg:address":"Rbla Catalunya, 88",
    "sg:city":"Barcelona",
    "sg:orig_category":"Cine (distribuci\u00d3n)",
    "sg:phone":"+34 934 67 20 53",
    "sg:postcode":"08008",
    "sg:province":"Barcelona",
    "sg:website":"www.fox.com",
    "wof:name":"Hispano Foxfilm",
    "wof:placetype":"venue"
},
  "geometry": {"coordinates":[2.1611440182,41.3930587769],"type":"Point"}
}