{
  "type": "Feature",
  "properties": {
    "iso:country":"ES",
    "sg:address":"Calle de Grabador Esteve, 9",
    "sg:city":"Valencia",
    "sg:orig_category":"Fabricaci\u00d3n De Tapices Y Moquetas Para Suelos Y Paredes",
    "sg:phone":"+34 963 95 85 61",
    "sg:postcode":"46004",
    "sg:province":"Valencia",
    "wof:name":"Euro-orient S.l.",
    "wof:placetype":"venue"
},
  "geometry": {"coordinates":[-0.3677582145,39.4712409973],"type":"Point"}
}