{
  "type": "Feature",
  "properties": {
    "addr:full":"Avda Adoratrices, 41 Huelva Huelva 21004",
    "addr:housenumber":"41",
    "addr:postcode":"21004",
    "addr:street":"Avda Adoratrices",
    "iso:country":"ES",
    "sg:address":"Avda Adoratrices, 41",
    "sg:city":"Huelva",
    "sg:classifiers":[
        {
            "category":"Personal",
            "subcategory":"Barber",
            "type":"Services"
        }
    ],
    "sg:phone":"+34 959 24 85 65",
    "sg:postcode":"21004",
    "sg:province":"Huelva",
    "sg:tags":[
        "caballeros",
        "de",
        "peluqueros"
    ],
    "wof:name":"Rivera Rivas Juan Manuel",
    "wof:placetype":"venue"
},
  "geometry": {"coordinates":[-6.9428467751,37.2652397156],"type":"Point"}
}