{
  "type": "Feature",
  "properties": {
    "iso:country":"ES",
    "sg:address":"Avda Jose Maria Fernandez, 43",
    "sg:city":"Le\u00f3n",
    "sg:orig_category":"Electrodom\u00c9sticos (al Por Menor)",
    "sg:phone":"+34 987 21 16 23",
    "sg:postcode":"24006",
    "sg:province":"Le\u00f3n",
    "wof:name":"Velasco Gascon Florencio",
    "wof:placetype":"venue"
},
  "geometry": {"coordinates":[-5.561507225,42.5988311768],"type":"Point"}
}