{
  "type": "Feature",
  "properties": {
    "addr:full":"Grup Sagarminaga, 5 Bilbao Vizcaya 48004",
    "addr:housenumber":"5",
    "addr:postcode":"48004",
    "addr:street":"Grup Sagarminaga",
    "iso:country":"ES",
    "sg:address":"Grup Sagarminaga, 5",
    "sg:city":"Bilbao",
    "sg:orig_category":"Restaurantes",
    "sg:phone":"+34 944 12 91 12",
    "sg:postcode":"48004",
    "sg:province":"Vizcaya",
    "wof:name":"Carrasco Gonzalez Estibaliz",
    "wof:placetype":"venue"
},
  "geometry": {"coordinates":[-2.9113759995,43.2483482361],"type":"Point"}
}