{
  "type": "Feature",
  "properties": {
    "iso:country":"ES",
    "sg:address":"Calle de Trinidad, 7",
    "sg:city":"Alcala Henares",
    "sg:orig_category":"Bancos",
    "sg:phone":"+34 918 89 88 03",
    "sg:postcode":"28801",
    "sg:province":"Madrid",
    "wof:name":"Banco Popular Espa\u00f1ol S.a.",
    "wof:placetype":"venue"
},
  "geometry": {"coordinates":[-3.366312027,40.4798164368],"type":"Point"}
}