{
  "type": "Feature",
  "properties": {
    "addr:full":"Rua Cardenal Quiroga, 47 Maceda Ourense 32700",
    "addr:housenumber":"47",
    "addr:postcode":"32700",
    "addr:street":"Rua Cardenal Quiroga",
    "iso:country":"ES",
    "sg:address":"Rua Cardenal Quiroga, 47",
    "sg:city":"Maceda",
    "sg:orig_category":"Empresas De Carpinter\u00cda",
    "sg:phone":"+34 988 46 33 47",
    "sg:postcode":"32700",
    "sg:province":"Ourense",
    "wof:name":"Aluminios Fergon S.l.",
    "wof:placetype":"venue"
},
  "geometry": {"coordinates":[-7.6536860466,42.2691764832],"type":"Point"}
}