{
  "type": "Feature",
  "properties": {
    "iso:country":"ES",
    "sg:address":"Calle de Caballeros, 16",
    "sg:city":"Ciudad Real",
    "sg:orig_category":"Centros P\u00dablicos De Formaci\u00d3n Profesional Y T\u00c9cnica",
    "sg:phone":"+34 926 23 00 11",
    "sg:postcode":"13003",
    "sg:province":"Ciudad Real",
    "wof:name":"Ilustre Colegio De Abogados De Ciudad Real",
    "wof:placetype":"venue"
},
  "geometry": {"coordinates":[-3.9301064014,38.9880714417],"type":"Point"}
}