{
  "type": "Feature",
  "properties": {
    "addr:full":"C/ Miguel De Unamuno, 53 Elche Alicante 03202",
    "addr:housenumber":"53",
    "addr:postcode":"03202",
    "addr:street":"C / Miguel De Unamuno",
    "iso:country":"ES",
    "sg:address":"C/ Miguel De Unamuno, 53",
    "sg:city":"Elche",
    "sg:orig_category":"Automatizaci\u00d3n De Procesos Industriales Y De Edificaci\u00d3n (estudios, Instalaci\u00d3n)",
    "sg:phone":"+34 965 42 17 05",
    "sg:postcode":"03202",
    "sg:province":"Alicante",
    "wof:name":"Vatronic Tecnicos En Automatismos S.l.",
    "wof:placetype":"venue"
},
  "geometry": {"coordinates":[-0.6906690001,38.2679214478],"type":"Point"}
}