{
  "type": "Feature",
  "properties": {
    "iso:country":"ES",
    "sg:address":"Calle de Biosca, 3",
    "sg:city":"Madrid",
    "sg:orig_category":"Molduras, Junquillos, Listones Y Molduras Perforadas",
    "sg:phone":"+34 917 63 97 47",
    "sg:postcode":"28043",
    "sg:province":"Madrid",
    "wof:name":"Vaqueriza Garcia Felipe",
    "wof:placetype":"venue"
},
  "geometry": {"coordinates":[-3.6502642632,40.4702796936],"type":"Point"}
}