{
  "type": "Feature",
  "properties": {
    "iso:country":"ES",
    "sg:address":"Ctra Cami D'albalat, 1",
    "sg:city":"Alzira",
    "sg:orig_category":"Fabricaci\u00d3n, Instalaci\u00d3n Y Reparaci\u00d3n De Bombas",
    "sg:phone":"+34 962 40 16 25",
    "sg:postcode":"46600",
    "sg:province":"Valencia",
    "wof:name":"Gradoli S.l.",
    "wof:placetype":"venue"
},
  "geometry": {"coordinates":[-0.4193289876,39.1732788086],"type":"Point"}
}