{
  "type": "Feature",
  "properties": {
    "addr:full":"La Bolliga, S/n Fuentelespino De Haro Cuenca 16647",
    "addr:housenumber":"s / n",
    "addr:postcode":"16647",
    "iso:country":"ES",
    "sg:address":"La Bolliga, S/n",
    "sg:city":"Fuentelespino De Haro",
    "sg:orig_category":"Producci\u00d3n, Venta De Productos De Agricultura Biol\u00d3gica",
    "sg:phone":"+34 967 18 78 50",
    "sg:postcode":"16647",
    "sg:province":"Cuenca",
    "wof:name":"Galan Lopez Juan",
    "wof:placetype":"venue"
},
  "geometry": {"coordinates":[-2.6741740704,39.6002235413],"type":"Point"}
}