{
  "type": "Feature",
  "properties": {
    "addr:full":"Ctra Circunvalacion, S/n Coru\u00d1a La Coru\u00f1a 15002",
    "addr:postcode":"15002",
    "addr:street":"Ctra Circunvalacion S / N Corun\u0303A La Corun\u0303A",
    "iso:country":"ES",
    "sg:address":"Ctra Circunvalacion, S/n",
    "sg:city":"Coru\u00d1a",
    "sg:orig_category":"Promotores Constructores",
    "sg:phone":"+34 981 20 61 08",
    "sg:postcode":"15002",
    "sg:province":"La Coru\u00f1a",
    "wof:name":"Landscape Grupo Lar S.l.",
    "wof:placetype":"venue"
},
  "geometry": {"coordinates":[-8.4083900452,43.380695343],"type":"Point"}
}