{
  "type": "Feature",
  "properties": {
    "addr:full":"Calle de Benalaque, S/n Cabanillas Campo Guadalajara 19171",
    "addr:housenumber":"s",
    "addr:postcode":"19171",
    "addr:street":"Calle De Benalaque;/ N",
    "iso:country":"ES",
    "sg:address":"Calle de Benalaque, S/n",
    "sg:city":"Cabanillas Campo",
    "sg:orig_category":"Maquinaria, Instalaci\u00d3n Y Equipo Para Garajes Y Estaciones De Servicio",
    "sg:phone":"+34 949 33 21 59",
    "sg:postcode":"19171",
    "sg:province":"Guadalajara",
    "wof:name":"Diges Romanillos Juan",
    "wof:placetype":"venue"
},
  "geometry": {"coordinates":[-3.232732296,40.634223938],"type":"Point"}
}