{
  "type": "Feature",
  "properties": {
    "addr:full":"Plaz Alameda De Hercules, 32 Sevilla Sevilla 41002",
    "addr:housenumber":"32",
    "addr:postcode":"41002",
    "addr:street":"Alameda De Hercules",
    "iso:country":"ES",
    "sg:address":"Plaz Alameda De Hercules, 32",
    "sg:city":"Sevilla",
    "sg:orig_category":"Arquitectos",
    "sg:phone":"+34 954 37 09 96",
    "sg:postcode":"41002",
    "sg:province":"Sevilla",
    "wof:name":"Domoarq Sociedad Cooperativa Andaluza",
    "wof:placetype":"venue"
},
  "geometry": {"coordinates":[-5.9942588806,37.3967475891],"type":"Point"}
}