{
  "type": "Feature",
  "properties": {
    "addr:full":"Avda Cerro Falon (del), 4 Sanlucar De Barrameda C\u00e1diz 11540",
    "addr:housenumber":"4",
    "addr:postcode":"11540",
    "addr:street":"Avda Cerro Falon Del;Ca\u0301Diz",
    "iso:country":"ES",
    "sg:address":"Avda Cerro Falon (del), 4",
    "sg:city":"Sanlucar De Barrameda",
    "sg:orig_category":"Agencias Y Agentes Comerciales, Representantes",
    "sg:phone":"+34 956 36 23 19",
    "sg:postcode":"11540",
    "sg:province":"C\u00e1diz",
    "wof:name":"Ruiz Rodriguez Manuel",
    "wof:placetype":"venue"
},
  "geometry": {"coordinates":[-6.352848053,36.7818717957],"type":"Point"}
}