{
  "type": "Feature",
  "properties": {
    "addr:full":"Calle de Urbina, 21 Vitoria-gasteiz \u00c1lava 01002",
    "addr:housenumber":"21",
    "addr:postcode":"01002",
    "addr:street":"Calle De Urbina",
    "iso:country":"ES",
    "sg:address":"Calle de Urbina, 21",
    "sg:city":"Vitoria-gasteiz",
    "sg:orig_category":"Prot\u00c9sicos Dentales",
    "sg:phone":"+34 945 25 54 20",
    "sg:postcode":"01002",
    "sg:province":"\u00c1lava",
    "wof:name":"Benjamin Calleja Ortiz",
    "wof:placetype":"venue"
},
  "geometry": {"coordinates":[-2.669064045,42.8534431458],"type":"Point"}
}