{
  "type": "Feature",
  "properties": {
    "addr:full":"Carrer de Villarroel, 52 Barcelona Barcelona 08011",
    "addr:housenumber":"52",
    "addr:postcode":"08011",
    "addr:street":"Carrer De Villarroel",
    "iso:country":"ES",
    "sg:address":"Carrer de Villarroel, 52",
    "sg:city":"Barcelona",
    "sg:orig_category":"Asesor\u00cda Sobre Comunicaci\u00d3n De Empresas",
    "sg:phone":"+34 934 51 41 71",
    "sg:postcode":"08011",
    "sg:province":"Barcelona",
    "wof:name":"Data-comp S.l.",
    "wof:placetype":"venue"
},
  "geometry": {"coordinates":[2.1603229046,41.3827209473],"type":"Point"}
}