{
  "type": "Feature",
  "properties": {
    "addr:full":"Calle de Martinez Marina, 3 Oviedo Asturias 33009",
    "addr:housenumber":"3",
    "addr:postcode":"33009",
    "addr:street":"Calle De Martinez Marina",
    "iso:country":"ES",
    "sg:address":"Calle de Martinez Marina, 3",
    "sg:city":"Oviedo",
    "sg:orig_category":"Cueros Y Pieles (al Por Mayor)",
    "sg:phone":"+34 985 20 41 06",
    "sg:postcode":"33009",
    "sg:province":"Asturias",
    "wof:name":"Lasa Suarez Jesus",
    "wof:placetype":"venue"
},
  "geometry": {"coordinates":[-5.8467111588,43.358505249],"type":"Point"}
}