{
  "type": "Feature",
  "properties": {
    "addr:full":"Carr Cami D'alpicat, 5 Torrefarrera Lleida 25123",
    "addr:housenumber":"5",
    "addr:postcode":"25123",
    "addr:street":"Carr Cami D'Alpicat",
    "iso:country":"ES",
    "sg:address":"Carr Cami D'alpicat, 5",
    "sg:city":"Torrefarrera",
    "sg:orig_category":"Material Y Herramientas Agr\u00cdcolas",
    "sg:phone":"+34 973 75 16 01",
    "sg:postcode":"25123",
    "sg:province":"Lleida",
    "wof:name":"Malo Ascaso Antonio",
    "wof:placetype":"venue"
},
  "geometry": {"coordinates":[0.604023993,41.6738471985],"type":"Point"}
}