{
  "type": "Feature",
  "properties": {
    "addr:full":"Plaz Provincia, 4 Ciudad Real Ciudad Real 13001",
    "addr:postcode":"13001",
    "addr:street":"Provincia",
    "iso:country":"ES",
    "sg:address":"Plaz Provincia, 4",
    "sg:city":"Ciudad Real",
    "sg:orig_category":"Cajas De Ahorro",
    "sg:phone":"+34 926 27 32 88",
    "sg:postcode":"13001",
    "sg:province":"Ciudad Real",
    "wof:name":"Unicaja",
    "wof:placetype":"venue"
},
  "geometry": {"coordinates":[-3.9303059578,38.9822540283],"type":"Point"}
}