{
  "type": "Feature",
  "properties": {
    "iso:country":"ES",
    "sg:address":"Calle de Corredera, 39",
    "sg:city":"Toro",
    "sg:orig_category":"Ropa Para Se\u00d1oras Y Caballeros (al Por Menor)",
    "sg:phone":"+34 980 69 30 97",
    "sg:postcode":"49800",
    "sg:province":"Zamora",
    "wof:name":"Posada Ordax Jose Antonio",
    "wof:placetype":"venue"
},
  "geometry": {"coordinates":[-5.3922314644,41.5238800049],"type":"Point"}
}