{
  "type": "Feature",
  "properties": {
    "iso:country":"ES",
    "sg:address":"Plaz Comendadoras, 10",
    "sg:city":"Madrid",
    "sg:orig_category":"Comunidades Religiosas",
    "sg:phone":"+34 915 48 18 42",
    "sg:postcode":"28015",
    "sg:province":"Madrid",
    "wof:name":"Comendadora Mayor De Santiago",
    "wof:placetype":"venue"
},
  "geometry": {"coordinates":[-3.7087879181,40.4272346497],"type":"Point"}
}