{
  "type": "Feature",
  "properties": {
    "iso:country":"ES",
    "sg:address":"Plaz Santo Domingo, 3",
    "sg:city":"Alcorcon",
    "sg:orig_category":"Cristaler\u00cdas",
    "sg:phone":"+34 916 43 05 77",
    "sg:postcode":"28922",
    "sg:province":"Madrid",
    "wof:name":"Barroso Carrasco Antonio",
    "wof:placetype":"venue"
},
  "geometry": {"coordinates":[-3.8267629147,40.3439025879],"type":"Point"}
}