{
  "type": "Feature",
  "properties": {
    "addr:full":"Pase Maritimo Rey De Espa\u00d1a, 54 Fuengirola M\u00e1laga 29640",
    "addr:housenumber":"54",
    "addr:postcode":"29640",
    "addr:street":"Espan\u0303A;Ma\u0301Laga",
    "iso:country":"ES",
    "sg:address":"Pase Maritimo Rey De Espa\u00d1a, 54",
    "sg:city":"Fuengirola",
    "sg:orig_category":"Ropa Para Se\u00d1oras (al Por Menor)",
    "sg:phone":"+34 952 46 28 31",
    "sg:postcode":"29640",
    "sg:province":"M\u00e1laga",
    "wof:name":"Zhou Ye Cheng Hai",
    "wof:placetype":"venue"
},
  "geometry": {"coordinates":[-4.6088852882,36.5691261292],"type":"Point"}
}