{
  "type": "Feature",
  "properties": {
    "iso:country":"ES",
    "sg:address":"El Paramo, 3",
    "sg:city":"Veguellina Orbigo",
    "sg:orig_category":"Pescader\u00cdas (al Por Menor)",
    "sg:phone":"+34 987 37 47 36",
    "sg:postcode":"24350",
    "sg:province":"Le\u00f3n",
    "wof:name":"Alvarez Fuertes Ana Elena",
    "wof:placetype":"venue"
},
  "geometry": {"coordinates":[-5.8824996948,42.4348716736],"type":"Point"}
}