{
  "type": "Feature",
  "properties": {
    "addr:full":"Carrer de Apel.les Mestres, 2 Granollers Barcelona 08402",
    "addr:housenumber":"2",
    "addr:postcode":"08402",
    "addr:street":"Carrer De Apel.Les Mestres",
    "iso:country":"ES",
    "sg:address":"Carrer de Apel.les Mestres, 2",
    "sg:city":"Granollers",
    "sg:orig_category":"Caf\u00c9s, Bares, Cervecer\u00cdas",
    "sg:phone":"+34 938 49 53 48",
    "sg:postcode":"08402",
    "sg:province":"Barcelona",
    "wof:name":"Lorente Diaz Jesus",
    "wof:placetype":"venue"
},
  "geometry": {"coordinates":[2.2915740013,41.6158027649],"type":"Point"}
}