{
  "type": "Feature",
  "properties": {
    "iso:country":"ES",
    "sg:address":"Talleres, 5",
    "sg:city":"Puerto Sagunto",
    "sg:orig_category":"Bricolaje, Herramientas (al Por Menor)",
    "sg:phone":"+34 962 67 46 60",
    "sg:postcode":"46520",
    "sg:province":"Valencia",
    "wof:name":"Bricolage 1 Cb",
    "wof:placetype":"venue"
},
  "geometry": {"coordinates":[-0.2025949955,39.7040786743],"type":"Point"}
}