{
  "type": "Feature",
  "properties": {
    "addr:full":"Calle de General Pardi\u00d1as, 27 Madrid Madrid 28001",
    "addr:housenumber":"27",
    "addr:postcode":"madrid;28001",
    "addr:street":"Calle De General Pardin\u0303As",
    "iso:country":"ES",
    "sg:address":"Calle de General Pardi\u00d1as, 27",
    "sg:city":"Madrid",
    "sg:orig_category":"Plomeros",
    "sg:phone":"+34 914 35 24 17",
    "sg:postcode":"28001",
    "sg:province":"Madrid",
    "wof:name":"Polo Alba Isidro",
    "wof:placetype":"venue"
},
  "geometry": {"coordinates":[-3.6786909103,40.4266929626],"type":"Point"}
}