{
  "type": "Feature",
  "properties": {
    "addr:full":"Pla\u00c7 Carme, 13 Seu D'urgell Lleida 25700",
    "addr:housenumber":"13",
    "addr:postcode":"25700",
    "addr:street":"Carme",
    "iso:country":"ES",
    "sg:address":"Pla\u00c7 Carme, 13",
    "sg:city":"Seu D'urgell",
    "sg:orig_category":"Caf\u00c9s, Bares, Cervecer\u00cdas",
    "sg:phone":"+34 973 35 36 52",
    "sg:postcode":"25700",
    "sg:province":"Lleida",
    "wof:name":"Snack Bar La Raspa S.l.",
    "wof:placetype":"venue"
},
  "geometry": {"coordinates":[0.6232429743,41.6144561768],"type":"Point"}
}