{
  "type": "Feature",
  "properties": {
    "iso:country":"ES",
    "sg:address":"Carrer de Fabrica (la), 20",
    "sg:city":"Riba",
    "sg:orig_category":"Producci\u00d3n De Cart\u00d3n",
    "sg:phone":"+34 977 87 63 11",
    "sg:postcode":"43450",
    "sg:province":"Tarragona",
    "wof:name":"Mora Y Goma S. A.",
    "wof:placetype":"venue"
},
  "geometry": {"coordinates":[1.1767400503,41.3186187744],"type":"Point"}
}