{
  "type": "Feature",
  "properties": {
    "iso:country":"ES",
    "sg:address":"Cmno Molinos (de Los), 55",
    "sg:city":"Zaragoza",
    "sg:orig_category":"Fabricaci\u00d3n De Juguetes Autom\u00c1ticos",
    "sg:phone":"+34 976 51 34 99",
    "sg:postcode":"50015",
    "sg:province":"Zaragoza",
    "wof:name":"Zaratronic S.l.",
    "wof:placetype":"venue"
},
  "geometry": {"coordinates":[-0.8687663078,41.6766395569],"type":"Point"}
}