{
  "type": "Feature",
  "properties": {
    "iso:country":"ES",
    "sg:address":"Carrer de Doctor Salva, 35",
    "sg:city":"Terrassa",
    "sg:orig_category":"Administradores De Bienes Y Delegados De Comunidades De Propietarios",
    "sg:phone":"+34 937 88 18 39",
    "sg:postcode":"08224",
    "sg:province":"Barcelona",
    "wof:name":"Ams S.c.p.",
    "wof:placetype":"venue"
},
  "geometry": {"coordinates":[2.0035150051,41.5605392456],"type":"Point"}
}