{
  "type": "Feature",
  "properties": {
    "iso:country":"ES",
    "sg:address":"Oarso Kalea, 8",
    "sg:city":"Pasaia",
    "sg:orig_category":"Ropa Para Se\u00d1oras (al Por Menor)",
    "sg:phone":"+34 943 34 02 42",
    "sg:postcode":"20110",
    "sg:province":"Guip\u00f9zcoa",
    "wof:name":"Maria Flor Ca\u00f1o Ca\u00f1o",
    "wof:placetype":"venue"
},
  "geometry": {"coordinates":[-1.9181380272,43.316444397],"type":"Point"}
}