{
  "type": "Feature",
  "properties": {
    "iso:country":"ES",
    "sg:address":"Plaz Pablo Neruda, 1",
    "sg:city":"Armunia",
    "sg:orig_category":"Molduras, Junquillos, Listones Y Molduras Perforadas",
    "sg:phone":"+34 987 25 43 51",
    "sg:postcode":"24009",
    "sg:province":"Le\u00f3n",
    "wof:name":"Tascon Rodriguez Virginia",
    "wof:placetype":"venue"
},
  "geometry": {"coordinates":[-5.6094388962,42.5985641479],"type":"Point"}
}