{
  "type": "Feature",
  "properties": {
    "addr:full":"Avgd Francesc Macia, 4 Esterri D'aneu Lleida 25580",
    "addr:housenumber":"4",
    "addr:postcode":"25580",
    "addr:street":"Macia",
    "iso:country":"ES",
    "sg:address":"Avgd Francesc Macia, 4",
    "sg:city":"Esterri D'aneu",
    "sg:orig_category":"Inmobiliaria (agencias)",
    "sg:phone":"+34 973 62 65 28",
    "sg:postcode":"25580",
    "sg:province":"Lleida",
    "wof:name":"Vazquez Vazquez Daniel",
    "wof:placetype":"venue"
},
  "geometry": {"coordinates":[0.6295930147,41.6167678833],"type":"Point"}
}