{
  "type": "Feature",
  "properties": {
    "iso:country":"ES",
    "sg:address":"Av Pais Valenciano, 79",
    "sg:city":"Guardamar Segura",
    "sg:orig_category":"Asesor\u00cda Fiscal Y Jur\u00cddica",
    "sg:phone":"+34 965 72 93 77",
    "sg:postcode":"03140",
    "sg:province":"Alicante",
    "wof:name":"General Legal Asesores S.l.",
    "wof:placetype":"venue"
},
  "geometry": {"coordinates":[-0.6541699767,38.0858573914],"type":"Point"}
}