{
  "type": "Feature",
  "properties": {
    "iso:country":"ES",
    "sg:address":"Luga Pedrera La (la Pedrera), S/n",
    "sg:city":"Pedrera",
    "sg:orig_category":"Controles De Edificaci\u00d3n (construcci\u00d3n, Seguridad)",
    "sg:phone":"+34 985 16 71 33",
    "sg:postcode":"33390",
    "sg:province":"Asturias",
    "wof:name":"Garcia Lopez Rene Javier",
    "wof:placetype":"venue"
},
  "geometry": {"coordinates":[-5.6883621216,43.4970245361],"type":"Point"}
}