{
  "type": "Feature",
  "properties": {
    "addr:full":"Erdiko Kalea, 28 Arrasate Guip\u00f9zcoa 20500",
    "addr:housenumber":"28",
    "addr:postcode":"20500",
    "addr:street":"Erdiko Kalea;Guipu\u0300Zcoa",
    "iso:country":"ES",
    "sg:address":"Erdiko Kalea, 28",
    "sg:city":"Arrasate",
    "sg:orig_category":"Centros De Coordinaci\u00d3n",
    "sg:phone":"+34 943 79 34 33",
    "sg:postcode":"20500",
    "sg:province":"Guip\u00f9zcoa",
    "wof:name":"Aguirre Miota Jose Maria",
    "wof:placetype":"venue"
},
  "geometry": {"coordinates":[-2.4904983044,43.0657463074],"type":"Point"}
}