{
  "type": "Feature",
  "properties": {
    "addr:full":"Calle de Estrella La Espiga, 3 Sevilla Sevilla 41008",
    "addr:housenumber":"3",
    "addr:postcode":"41008",
    "addr:street":"Calle De Estrella La Espiga",
    "iso:country":"ES",
    "sg:address":"Calle de Estrella La Espiga, 3",
    "sg:city":"Sevilla",
    "sg:orig_category":"Centros De Coordinaci\u00d3n",
    "sg:phone":"+34 954 94 12 62",
    "sg:postcode":"41008",
    "sg:province":"Sevilla",
    "wof:name":"Pulido Garces Gestores Administrativos S.l.l.",
    "wof:placetype":"venue"
},
  "geometry": {"coordinates":[-5.967610836,37.4233283997],"type":"Point"}
}