{
  "type": "Feature",
  "properties": {
    "iso:country":"ES",
    "sg:address":"Olazko Amaren Plaza, 9",
    "sg:city":"Azpeitia",
    "sg:orig_category":"Dietistas",
    "sg:phone":"+34 943 81 66 58",
    "sg:postcode":"20730",
    "sg:province":"Guip\u00f9zcoa",
    "wof:name":"Dietetika Zentrua Eliku",
    "wof:placetype":"venue"
},
  "geometry": {"coordinates":[-2.2676000595,43.1831550598],"type":"Point"}
}