{
  "type": "Feature",
  "properties": {
    "iso:country":"ES",
    "sg:address":"Rua Urzaiz, 15",
    "sg:city":"Vigo",
    "sg:orig_category":"Bisuter\u00cda, Joyer\u00cda, Relojer\u00cda (al Por Menor)",
    "sg:phone":"+34 986 44 15 45",
    "sg:postcode":"36201",
    "sg:province":"Pontevedra",
    "sg:website":"www.pianegonda.com",
    "wof:name":"Akechove S.l.",
    "wof:placetype":"venue"
},
  "geometry": {"coordinates":[-8.7186031342,42.2353363037],"type":"Point"}
}