{
  "type": "Feature",
  "properties": {
    "addr:full":"Calle de Cristo (del), 19 Pinto Madrid 28320",
    "addr:housenumber":"19",
    "addr:postcode":"28320",
    "addr:street":"Calle De Cristo Del",
    "iso:country":"ES",
    "sg:address":"Calle de Cristo (del), 19",
    "sg:city":"Pinto",
    "sg:orig_category":"Electrodom\u00c9sticos (al Por Menor)",
    "sg:phone":"+34 916 91 37 64",
    "sg:postcode":"28320",
    "sg:province":"Madrid",
    "wof:name":"Sistelcom-telemensaje,s.a.",
    "wof:placetype":"venue"
},
  "geometry": {"coordinates":[-3.7032940388,40.2422103882],"type":"Point"}
}