{
  "type": "Feature",
  "properties": {
    "iso:country":"ES",
    "sg:address":"Avda Ramon Y Cajal, 39",
    "sg:city":"Bilbao",
    "sg:orig_category":"Comercio, Reparaci\u00d3n De Motocicletas, Bicicletas Y Piezas Sueltas",
    "sg:phone":"+34 944 47 80 66",
    "sg:postcode":"48014",
    "sg:province":"Vizcaya",
    "wof:name":"Palomino Tejeda Vicente",
    "wof:placetype":"venue"
},
  "geometry": {"coordinates":[-2.9479660988,43.2726135254],"type":"Point"}
}