{
  "type": "Feature",
  "properties": {
    "iso:country":"ES",
    "sg:address":"Ctra. Madrid-cadiz, Km. 0285,0",
    "sg:city":"Guarroman",
    "sg:orig_category":"Agricultura: Abastecimiento Y Cosechado (negocio)",
    "sg:phone":"+34 953 12 52 07",
    "sg:postcode":"23210",
    "sg:province":"Ja\u00e9n",
    "wof:name":"Centro De Explotaciones E Investigaciones Agronomicas S.l.",
    "wof:placetype":"venue"
},
  "geometry": {"coordinates":[-3.6845591068,38.1842346191],"type":"Point"}
}