{
  "type": "Feature",
  "properties": {
    "iso:country":"ES",
    "sg:address":"Olite-erriberri Kalea, 40",
    "sg:city":"Iru\u00f1a",
    "sg:orig_category":"Molduras, Junquillos, Listones Y Molduras Perforadas",
    "sg:phone":"+34 948 24 33 22",
    "sg:postcode":"31004",
    "sg:province":"Navarra",
    "wof:name":"Esnaola Auza Miguel",
    "wof:placetype":"venue"
},
  "geometry": {"coordinates":[-1.6336109638,42.8104438782],"type":"Point"}
}