{
  "type": "Feature",
  "properties": {
    "addr:full":"Calle de Rambla De Las Flores, 11 Moclinejo M\u00e1laga 29738",
    "addr:housenumber":"11",
    "addr:postcode":"29738",
    "addr:street":"Calle De Rambla De Las Flores;Ma\u0301Laga",
    "iso:country":"ES",
    "sg:address":"Calle de Rambla De Las Flores, 11",
    "sg:city":"Moclinejo",
    "sg:orig_category":"Cajas Para Embalar",
    "sg:phone":"+34 952 40 05 83",
    "sg:postcode":"29738",
    "sg:province":"M\u00e1laga",
    "wof:name":"Cajamar",
    "wof:placetype":"venue"
},
  "geometry": {"coordinates":[-4.2460689545,36.7377052307],"type":"Point"}
}