{
  "type": "Feature",
  "properties": {
    "addr:full":"Trva Picasso (de), 3 Alcobendas Madrid 28100",
    "addr:postcode":"28100",
    "addr:street":"Trva Picasso De 3",
    "iso:country":"ES",
    "sg:address":"Trva Picasso (de), 3",
    "sg:city":"Alcobendas",
    "sg:orig_category":"Internados & Ense\u00d1anza Privada",
    "sg:phone":"+34 916 51 64 68",
    "sg:postcode":"28100",
    "sg:province":"Madrid",
    "wof:name":"Sanchez Chacon Juan Miguel",
    "wof:placetype":"venue"
},
  "geometry": {"coordinates":[-3.6367599964,40.5417900085],"type":"Point"}
}