{
  "type": "Feature",
  "properties": {
    "addr:full":"Cuesta Pi\u00f1ero, 1 Churra Murcia 30110",
    "addr:housenumber":"1",
    "addr:postcode":"30110",
    "addr:street":"Cuesta Pin\u0303Ero",
    "iso:country":"ES",
    "sg:address":"Cuesta Pi\u00f1ero, 1",
    "sg:city":"Churra",
    "sg:orig_category":"Agencias Y Agentes Comerciales, Representantes",
    "sg:phone":"+34 968 83 08 53",
    "sg:postcode":"30110",
    "sg:province":"Murcia",
    "wof:name":"Lorca Hernandez Angel",
    "wof:placetype":"venue"
},
  "geometry": {"coordinates":[-1.1360189915,38.0214653015],"type":"Point"}
}