{
  "type": "Feature",
  "properties": {
    "addr:full":"Pl Abastos, S/n Cieza Murcia 30530",
    "addr:housenumber":"s / n",
    "addr:postcode":"30530",
    "addr:street":"Abastos",
    "iso:country":"ES",
    "sg:address":"Pl Abastos, S/n",
    "sg:city":"Cieza",
    "sg:orig_category":"Asilos De Ancianos. Centros Privados",
    "sg:phone":"+34 968 45 63 51",
    "sg:postcode":"30530",
    "sg:province":"Murcia",
    "wof:name":"Asociacion Local Para La Cultura Y Tiempo Libre De Los Mayores",
    "wof:placetype":"venue"
},
  "geometry": {"coordinates":[-1.4821481705,38.2650794983],"type":"Point"}
}