{
  "type": "Feature",
  "properties": {
    "addr:full":"Calle de Concha Espina, 25 Alacant Alicante 03016",
    "addr:housenumber":"25",
    "addr:postcode":"03016",
    "addr:street":"Calle De Concha Espina",
    "iso:country":"ES",
    "sg:address":"Calle de Concha Espina, 25",
    "sg:city":"Alacant",
    "sg:orig_category":"Guarder\u00cdas",
    "sg:phone":"+34 965 26 75 29",
    "sg:postcode":"03016",
    "sg:province":"Alicante",
    "wof:name":"Paya Rico Ismael",
    "wof:placetype":"venue"
},
  "geometry": {"coordinates":[-0.4546903968,38.3660507202],"type":"Point"}
}