{
  "type": "Feature",
  "properties": {
    "iso:country":"ES",
    "sg:address":"Carrer de Trasime, 4",
    "sg:city":"Arenal",
    "sg:orig_category":"Molduras, Junquillos, Listones Y Molduras Perforadas",
    "sg:phone":"+34 971 49 24 85",
    "sg:postcode":"07600",
    "sg:province":"Islas Baleares",
    "wof:name":"Gonzalez Sanchez Juan Antonio",
    "wof:placetype":"venue"
},
  "geometry": {"coordinates":[2.7506198883,39.5100402832],"type":"Point"}
}