{
  "type": "Feature",
  "properties": {
    "addr:full":"Avda Angeles (de Los), 2 Almeria Almer\u00eda 04008",
    "addr:housenumber":"2",
    "addr:postcode":"04008",
    "addr:street":"Avda Angeles De Los",
    "iso:country":"ES",
    "sg:address":"Avda Angeles (de Los), 2",
    "sg:city":"Almeria",
    "sg:orig_category":"Impuestos, Tesoro P\u00dablico",
    "sg:phone":"+34 950 25 39 06",
    "sg:postcode":"04008",
    "sg:province":"Almer\u00eda",
    "wof:name":"Gabinete De Peritaciones Ba\u00f1os S.l.",
    "wof:placetype":"venue"
},
  "geometry": {"coordinates":[-2.4570090771,36.8489112854],"type":"Point"}
}