{
  "type": "Feature",
  "properties": {
    "addr:full":"Calle de Fulgencio De Miguel, 11 Madrid Madrid 28039",
    "addr:housenumber":"11",
    "addr:postcode":"madrid;28039",
    "addr:street":"Calle De Fulgencio De Miguel",
    "iso:country":"ES",
    "sg:address":"Calle de Fulgencio De Miguel, 11",
    "sg:city":"Madrid",
    "sg:orig_category":"Arreglo, Reparaci\u00d3n, Piezas Sueltas De Televisi\u00d3n, V\u00cddeo, Hi",
    "sg:phone":"+34 914 50 98 16",
    "sg:postcode":"28039",
    "sg:province":"Madrid",
    "wof:name":"Avila Otero Emiliano",
    "wof:placetype":"venue"
},
  "geometry": {"coordinates":[-3.7033772469,40.4553070068],"type":"Point"}
}