{
  "type": "Feature",
  "properties": {
    "iso:country":"ES",
    "sg:address":"Calle de San Miguel, 2",
    "sg:city":"Fuentespalda",
    "sg:orig_category":"Sanatorios M\u00c9dico",
    "sg:phone":"+34 978 85 62 49",
    "sg:postcode":"44587",
    "sg:province":"Teruel",
    "wof:name":"Ayuntamiento De Fuentespalda",
    "wof:placetype":"venue"
},
  "geometry": {"coordinates":[0.0660519972,40.8063545227],"type":"Point"}
}