{
  "type": "Feature",
  "properties": {
    "addr:full":"Carr Masnou, De, S/n Consell Islas Baleares 07330",
    "addr:housenumber":"/ n",
    "addr:postcode":"07330",
    "addr:street":"Carr Masnou De S",
    "iso:country":"ES",
    "sg:address":"Carr Masnou, De, S/n",
    "sg:city":"Consell",
    "sg:orig_category":"Ense\u00d1anza, Formaci\u00d3n Profesional: Aprendizaje",
    "sg:phone":"+34 971 62 22 02",
    "sg:postcode":"07330",
    "sg:province":"Islas Baleares",
    "wof:name":"Ajuntament De Consell",
    "wof:placetype":"venue"
},
  "geometry": {"coordinates":[2.8080070019,39.6684989929],"type":"Point"}
}