{
  "type": "Feature",
  "properties": {
    "iso:country":"ES",
    "sg:address":"Av Valles, 362",
    "sg:city":"Terrassa",
    "sg:orig_category":"Reciclaje, Tratamiento De Tejidos",
    "sg:phone":"+34 937 86 23 39",
    "sg:postcode":"08227",
    "sg:province":"Barcelona",
    "wof:name":"Acabados Fravi S.l.",
    "wof:placetype":"venue"
},
  "geometry": {"coordinates":[2.03897,41.552692],"type":"Point"}
}