{
  "type": "Feature",
  "properties": {
    "iso:country":"ES",
    "sg:address":"Parque Tecnologico De Zamudio, 100",
    "sg:city":"Zamudio",
    "sg:orig_category":"Ingeniero",
    "sg:phone":"+34 946 02 12 00",
    "sg:postcode":"48170",
    "sg:province":"Vizcaya",
    "sg:website":"www.sisteplant.com",
    "wof:name":"Sisteplant, S. L.",
    "wof:placetype":"venue"
},
  "geometry": {"coordinates":[-2.8633139133,43.280834198],"type":"Point"}
}