{
  "type": "Feature",
  "properties": {
    "addr:full":"Calle de Urbion, 9 Sevilla Sevilla 41005",
    "addr:housenumber":"9",
    "addr:postcode":"41005",
    "addr:street":"Calle De Urbion",
    "iso:country":"ES",
    "sg:address":"Calle de Urbion, 9",
    "sg:city":"Sevilla",
    "sg:orig_category":"Promotores Constructores",
    "sg:phone":"+34 954 64 71 75",
    "sg:postcode":"41005",
    "sg:province":"Sevilla",
    "wof:name":"Caballero Iba\u00f1ez Francisco",
    "wof:placetype":"venue"
},
  "geometry": {"coordinates":[-5.9708018303,37.3745307922],"type":"Point"}
}