{
  "type": "Feature",
  "properties": {
    "iso:country":"ES",
    "sg:address":"Poli Mugazuri, S/n",
    "sg:city":"Burlada",
    "sg:orig_category":"Chapister\u00cda",
    "sg:phone":"+34 948 12 95 90",
    "sg:postcode":"31600",
    "sg:province":"Navarra",
    "wof:name":"Oyaga Lasarte Jose Manuel",
    "wof:placetype":"venue"
},
  "geometry": {"coordinates":[-1.6224989891,42.8306159973],"type":"Point"}
}