{
  "type": "Feature",
  "properties": {
    "addr:full":"Carrer de Torras I Bages, 105 Cornella Llobregat Barcelona 08940",
    "addr:housenumber":"105",
    "addr:postcode":"08940",
    "addr:street":"Carrer De Torras I Bages",
    "iso:country":"ES",
    "sg:address":"Carrer de Torras I Bages, 105",
    "sg:city":"Cornella Llobregat",
    "sg:orig_category":"Asesor\u00cda Fiscal Y Jur\u00cddica",
    "sg:phone":"+34 933 75 14 03",
    "sg:postcode":"08940",
    "sg:province":"Barcelona",
    "wof:name":"Martinez Perez Dolores",
    "wof:placetype":"venue"
},
  "geometry": {"coordinates":[2.0740289688,41.3649406433],"type":"Point"}
}