{
  "type": "Feature",
  "properties": {
    "addr:full":"Avgd Castello (de), 14 Atzeneta Maestrat Castell\u00f3n 12132",
    "addr:postcode":"12132",
    "addr:street":"Castello\u0301N",
    "iso:country":"ES",
    "sg:address":"Avgd Castello (de), 14",
    "sg:city":"Atzeneta Maestrat",
    "sg:orig_category":"Fabricaci\u00d3n De Harinas, S\u00c9molas, Productos De Elaboraci\u00d3n Del Grano",
    "sg:phone":"+34 964 37 00 39",
    "sg:postcode":"12132",
    "sg:province":"Castell\u00f3n",
    "wof:name":"Escrig Badenes Jose Luis",
    "wof:placetype":"venue"
},
  "geometry": {"coordinates":[-0.1707289964,40.2165145874],"type":"Point"}
}