{
  "type": "Feature",
  "properties": {
    "addr:full":"Calle de Avutarda (la), 28 Guadalajara Guadalajara 19005",
    "addr:postcode":"19005",
    "addr:street":"Calle De Avutarda La",
    "iso:country":"ES",
    "sg:address":"Calle de Avutarda (la), 28",
    "sg:city":"Guadalajara",
    "sg:orig_category":"Obras Y Organismos Sociales",
    "sg:phone":"+34 949 22 59 72",
    "sg:postcode":"19005",
    "sg:province":"Guadalajara",
    "wof:name":"Comision Catolica Espa\u00f1ola De Migracion",
    "wof:placetype":"venue"
},
  "geometry": {"coordinates":[-3.1549921036,40.6402244568],"type":"Point"}
}