{
  "type": "Feature",
  "properties": {
    "iso:country":"ES",
    "sg:address":"Avda Aramo Del, 34",
    "sg:city":"Ara",
    "sg:orig_category":"Estancos",
    "sg:phone":"+34 985 76 60 75",
    "sg:postcode":"33160",
    "sg:province":"Asturias",
    "wof:name":"Juan Garrido Angeles",
    "wof:placetype":"venue"
},
  "geometry": {"coordinates":[-5.8822832108,43.2305450439],"type":"Point"}
}