{
  "type": "Feature",
  "properties": {
    "addr:full":"Calle de Jose Mouliaa, 35 San Jose Murcia 30800",
    "addr:housenumber":"35",
    "addr:postcode":"30800",
    "addr:street":"Calle De Jose Mouliaa",
    "iso:country":"ES",
    "sg:address":"Calle de Jose Mouliaa, 35",
    "sg:city":"San Jose",
    "sg:orig_category":"Mec\u00c1nico Del Autom\u00d3vil",
    "sg:phone":"+34 968 46 46 53",
    "sg:postcode":"30800",
    "sg:province":"Murcia",
    "wof:name":"Castellote Carrera Casimiro",
    "wof:placetype":"venue"
},
  "geometry": {"coordinates":[-1.6905640364,37.680557251],"type":"Point"}
}