{
  "type": "Feature",
  "properties": {
    "addr:full":"Calle de Montseny, 27 Madrid Madrid 28038",
    "addr:housenumber":"27",
    "addr:postcode":"madrid;28038",
    "addr:street":"Calle De Montseny",
    "iso:country":"ES",
    "sg:address":"Calle de Montseny, 27",
    "sg:city":"Madrid",
    "sg:orig_category":"Internados & Ense\u00d1anza Privada",
    "sg:phone":"+34 914 33 59 96",
    "sg:postcode":"28038",
    "sg:province":"Madrid",
    "wof:name":"Congregacion De Religiosas De La Asuncion",
    "wof:placetype":"venue"
},
  "geometry": {"coordinates":[-3.662940979,40.400844574],"type":"Point"}
}