{
  "type": "Feature",
  "properties": {
    "iso:country":"ES",
    "sg:address":"C/ Sant Gabriel, 18",
    "sg:city":"Manacor",
    "sg:orig_category":"Pintura, Barniz, Productos Asimilables (fabricaci\u00d3n, Al Por Mayor)",
    "sg:phone":"+34 971 55 32 24",
    "sg:postcode":"07500",
    "sg:province":"Islas Baleares",
    "wof:name":"Mondejar Mu\u00f1oz Juan",
    "wof:placetype":"venue"
},
  "geometry": {"coordinates":[3.2013249397,39.566242218],"type":"Point"}
}