{
  "type": "Feature",
  "properties": {
    "addr:full":"Calle de Santa Lucia, 11 Zaragoza Zaragoza 50003",
    "addr:housenumber":"11",
    "addr:postcode":"50003",
    "addr:street":"Calle De Santa Lucia",
    "iso:country":"ES",
    "sg:address":"Calle de Santa Lucia, 11",
    "sg:city":"Zaragoza",
    "sg:orig_category":"Agencias Y Agentes Comerciales, Representantes",
    "sg:phone":"+34 976 43 61 20",
    "sg:postcode":"50003",
    "sg:province":"Zaragoza",
    "wof:name":"Valero Uson Luis Fernando",
    "wof:placetype":"venue"
},
  "geometry": {"coordinates":[-0.8918030262,41.6579475403],"type":"Point"}
}