{
  "type": "Feature",
  "properties": {
    "iso:country":"ES",
    "sg:address":"Carrer de Joan Torras, 44",
    "sg:city":"Barcelona",
    "sg:orig_category":"Electricidad, Electr\u00d3nica: Suministros (al Por Menor)",
    "sg:phone":"+34 933 11 08 53",
    "sg:postcode":"08030",
    "sg:province":"Barcelona",
    "wof:name":"Sonic Import S.l.",
    "wof:placetype":"venue"
},
  "geometry": {"coordinates":[2.1930749416,41.4376106262],"type":"Point"}
}