{
  "type": "Feature",
  "properties": {
    "iso:country":"ES",
    "sg:address":"Calle de Doctor Mara\u00d1on, 6",
    "sg:city":"Yuncos",
    "sg:orig_category":"Plomeros",
    "sg:phone":"+34 925 53 73 43",
    "sg:postcode":"45210",
    "sg:province":"Toledo",
    "wof:name":"Villalba Martin Rodrigo",
    "wof:placetype":"venue"
},
  "geometry": {"coordinates":[-3.873472929,40.0907669067],"type":"Point"}
}