{
  "type": "Feature",
  "properties": {
    "addr:full":"Calle de Santa Ana, 35 Campillos M\u00e1laga 29320",
    "addr:housenumber":"35",
    "addr:postcode":"29320",
    "addr:street":"Calle De Santa Ana",
    "iso:country":"ES",
    "sg:address":"Calle de Santa Ana, 35",
    "sg:city":"Campillos",
    "sg:orig_category":"Ense\u00d1anza: Profesiones Art\u00cdsticas",
    "sg:phone":"+34 952 72 53 78",
    "sg:postcode":"29320",
    "sg:province":"M\u00e1laga",
    "wof:name":"Padilla Vazquez Juan Carlos",
    "wof:placetype":"venue"
},
  "geometry": {"coordinates":[-4.8644337654,37.0485038757],"type":"Point"}
}