{
  "type": "Feature",
  "properties": {
    "iso:country":"ES",
    "sg:address":"Calle de Jose Maria Beltran, 14",
    "sg:city":"Zaragoza",
    "sg:orig_category":"Art\u00cdculos De Regalo (al Por Menor)",
    "sg:phone":"+34 976 52 04 01",
    "sg:postcode":"50015",
    "sg:province":"Zaragoza",
    "wof:name":"Gracia Lafuente Jesus",
    "wof:placetype":"venue"
},
  "geometry": {"coordinates":[-0.8764669895,41.6600952148],"type":"Point"}
}