{
  "type": "Feature",
  "properties": {
    "iso:country":"ES",
    "sg:address":"Avda Portugal, 83",
    "sg:city":"Talavera Reina",
    "sg:orig_category":"Distribuci\u00d3n De Petr\u00d3leo Y Derivados",
    "sg:phone":"+34 925 81 52 73",
    "sg:postcode":"45600",
    "sg:province":"Toledo",
    "wof:name":"Serta S.l.",
    "wof:placetype":"venue"
},
  "geometry": {"coordinates":[-4.8491630554,39.9575424194],"type":"Point"}
}