{
  "type": "Feature",
  "properties": {
    "addr:full":"Calle de Cristo Rey, 12 Andujar Ja\u00e9n 23740",
    "addr:housenumber":"12",
    "addr:postcode":"23740",
    "addr:street":"Calle De Cristo Rey",
    "iso:country":"ES",
    "sg:address":"Calle de Cristo Rey, 12",
    "sg:city":"Andujar",
    "sg:orig_category":"Electrodom\u00c9sticos (al Por Menor)",
    "sg:phone":"+34 953 50 12 79",
    "sg:postcode":"23740",
    "sg:province":"Ja\u00e9n",
    "wof:name":"Gonzalez Ruano Juan Jose",
    "wof:placetype":"venue"
},
  "geometry": {"coordinates":[-4.0496373177,38.0413131714],"type":"Point"}
}