{
  "type": "Feature",
  "properties": {
    "addr:full":"Calle de Jose Antonio Primo De Rivera, 21 Santa Brigida Las Palmas 35300",
    "addr:housenumber":"21",
    "addr:postcode":"35300",
    "addr:street":"Calle De Jose Antonio Primo De Rivera",
    "iso:country":"ES",
    "sg:address":"Calle de Jose Antonio Primo De Rivera, 21",
    "sg:city":"Santa Brigida",
    "sg:classifiers":[
        {
            "category":"Personal",
            "subcategory":"Barber",
            "type":"Services"
        }
    ],
    "sg:phone":"+34 928 64 22 60",
    "sg:postcode":"35300",
    "sg:province":"Las Palmas",
    "sg:tags":[
        "caballeros",
        "de",
        "peluqueros"
    ],
    "wof:name":"Perez Diaz Eduardo",
    "wof:placetype":"venue"
},
  "geometry": {"coordinates":[-15.4985227585,28.0334949493],"type":"Point"}
}