{
  "type": "Feature",
  "properties": {
    "addr:full":"Calle de Iparraguirre, 75 Bilbao Vizcaya 48012",
    "addr:housenumber":"75",
    "addr:postcode":"48012",
    "addr:street":"Calle De Iparraguirre",
    "iso:country":"ES",
    "sg:address":"Calle de Iparraguirre, 75",
    "sg:city":"Bilbao",
    "sg:orig_category":"Molduras, Junquillos, Listones Y Molduras Perforadas",
    "sg:phone":"+34 944 21 43 72",
    "sg:postcode":"48012",
    "sg:province":"Vizcaya",
    "wof:name":"Losada Rodriguez Fernando",
    "wof:placetype":"venue"
},
  "geometry": {"coordinates":[-2.9387180805,43.256778717],"type":"Point"}
}