{
  "type": "Feature",
  "properties": {
    "addr:full":"Llobregat (pol Can Calopa), S/n Valldoreix Barcelona 08197",
    "addr:housenumber":"s",
    "addr:postcode":"08197",
    "addr:street":"/ N Valldoreix",
    "iso:country":"ES",
    "sg:address":"Llobregat (pol Can Calopa), S/n",
    "sg:city":"Valldoreix",
    "sg:orig_category":"Comercio De Hierro",
    "sg:phone":"+34 935 84 30 22",
    "sg:postcode":"08197",
    "sg:province":"Barcelona",
    "wof:name":"Hierros Sant Cugat S.l.",
    "wof:placetype":"venue"
},
  "geometry": {"coordinates":[2.0480868816,41.4574966431],"type":"Point"}
}