{
  "type": "Feature",
  "properties": {
    "addr:full":"Calle de Calvo Sotelo, 18 Val De Santo Domingo Toledo 45519",
    "addr:housenumber":"18",
    "addr:postcode":"45519",
    "addr:street":"Calle De Calvo Sotelo",
    "iso:country":"ES",
    "sg:address":"Calle de Calvo Sotelo, 18",
    "sg:city":"Val De Santo Domingo",
    "sg:orig_category":"Farmacias",
    "sg:phone":"+34 925 77 90 67",
    "sg:postcode":"45519",
    "sg:province":"Toledo",
    "wof:name":"Mu\u00f1oz Gomez Mercedes",
    "wof:placetype":"venue"
},
  "geometry": {"coordinates":[-4.3274202347,40.0123062134],"type":"Point"}
}