{
  "type": "Feature",
  "properties": {
    "iso:country":"ES",
    "sg:address":"Avda Teniente General Muslera, S/n",
    "sg:city":"Ceuta",
    "sg:orig_category":"Ropa Para Se\u00d1oras (al Por Menor)",
    "sg:phone":"+34 956 50 98 97",
    "sg:postcode":"51002",
    "sg:province":"Ceuta",
    "wof:name":"Torio Ramirez Yolanda",
    "wof:placetype":"venue"
},
  "geometry": {"coordinates":[-5.3299298286,35.8878097534],"type":"Point"}
}