{
  "type": "Feature",
  "properties": {
    "addr:full":"Carr Lloret, 47 Serres Girona 17411",
    "addr:housenumber":"47",
    "addr:postcode":"17411",
    "addr:street":"Carr Lloret",
    "iso:country":"ES",
    "sg:address":"Carr Lloret, 47",
    "sg:city":"Serres",
    "sg:orig_category":"Arquitectos",
    "sg:phone":"+34 972 85 17 47",
    "sg:postcode":"17411",
    "sg:province":"Girona",
    "wof:name":"Deulofeu Bruns Manuel",
    "wof:placetype":"venue"
},
  "geometry": {"coordinates":[2.7773220539,41.789768219],"type":"Point"}
}