{
  "type": "Feature",
  "properties": {
    "iso:country":"ES",
    "sg:address":"Avda Sierra De Gata, S/n",
    "sg:city":"Coria",
    "sg:orig_category":"Ense\u00d1anza, Formaci\u00d3n Profesional: Aprendizaje",
    "sg:phone":"+34 927 50 60 22",
    "sg:postcode":"10800",
    "sg:province":"C\u00e1ceres",
    "wof:name":"Patronato Municipal De Deportes",
    "wof:placetype":"venue"
},
  "geometry": {"coordinates":[-6.5370440483,39.9853553772],"type":"Point"}
}