{
  "type": "Feature",
  "properties": {
    "iso:country":"ES",
    "sg:address":"Ibai-tarte Kalea, 21",
    "sg:city":"Elgoibar",
    "sg:orig_category":"Automatizaci\u00d3n De Procesos Industriales Y De Edificaci\u00d3n (estudios, Instalaci\u00d3n)",
    "sg:phone":"+34 943 74 21 30",
    "sg:postcode":"20870",
    "sg:province":"Guip\u00f9zcoa",
    "sg:website":"www.hre.es",
    "wof:name":"Hre Hidraulic S.l.",
    "wof:placetype":"venue"
},
  "geometry": {"coordinates":[-2.4087660313,43.2226219177],"type":"Point"}
}