{
  "type": "Feature",
  "properties": {
    "iso:country":"ES",
    "sg:address":"Plaz Mayor, 5",
    "sg:city":"Feira Do Monte",
    "sg:orig_category":"Farmacias",
    "sg:phone":"+34 982 52 00 20",
    "sg:postcode":"27377",
    "sg:province":"Lugo",
    "wof:name":"Carracedo Lozano Isabel",
    "wof:placetype":"venue"
},
  "geometry": {"coordinates":[-7.5985860825,43.0185699463],"type":"Point"}
}