{
  "type": "Feature",
  "properties": {
    "iso:country":"ES",
    "sg:address":"Calle de Atarazanas, 8",
    "sg:city":"Malaga",
    "sg:orig_category":"Frutas, Legumbres Frescas Y Tempranas (al Por Menor)",
    "sg:phone":"+34 952 22 15 90",
    "sg:postcode":"29005",
    "sg:province":"M\u00e1laga",
    "wof:name":"Sanchez De Lara Ernesto",
    "wof:placetype":"venue"
},
  "geometry": {"coordinates":[-4.4236679077,36.7182540894],"type":"Point"}
}