{
  "type": "Feature",
  "properties": {
    "addr:full":"El Marquito, 14 Santa Cruz Palma Santa Cruz De Tenerife 38700",
    "addr:housenumber":"14",
    "addr:postcode":"38700",
    "addr:street":"El Marquito",
    "iso:country":"ES",
    "sg:address":"El Marquito, 14",
    "sg:city":"Santa Cruz Palma",
    "sg:orig_category":"Carnicer\u00cdas, Carnicer\u00cdas",
    "sg:phone":"+34 922 41 59 50",
    "sg:postcode":"38700",
    "sg:province":"Santa Cruz De Tenerife",
    "wof:name":"Matos Bravo Rafael",
    "wof:placetype":"venue"
},
  "geometry": {"coordinates":[-17.7642784119,28.687210083],"type":"Point"}
}