{
  "type": "Feature",
  "properties": {
    "iso:country":"ES",
    "sg:address":"Avda Xose Solla, 11",
    "sg:city":"Calle",
    "sg:orig_category":"Asesor\u00cda Sobre Comunicaci\u00d3n De Empresas",
    "sg:phone":"+34 986 67 01 11",
    "sg:postcode":"36690",
    "sg:province":"Pontevedra",
    "wof:name":"Filsa S.l.",
    "wof:placetype":"venue"
},
  "geometry": {"coordinates":[-8.6063833237,42.3409309387],"type":"Point"}
}