{
  "type": "Feature",
  "properties": {
    "addr:full":"Calle de Capitan Garcia Espinosa, 39 Moral Calatrava Ciudad Real 13350",
    "addr:housenumber":"39",
    "addr:postcode":"13350",
    "addr:street":"Calle De Capitan Garcia Espinosa;Calatrava",
    "iso:country":"ES",
    "sg:address":"Calle de Capitan Garcia Espinosa, 39",
    "sg:city":"Moral Calatrava",
    "sg:orig_category":"Lencer\u00cda Femenina, Corseter\u00cda, Trajes De Ba\u00d1o (al Por Menor)",
    "sg:phone":"+34 926 31 94 96",
    "sg:postcode":"13350",
    "sg:province":"Ciudad Real",
    "wof:name":"Moraleda Gomez Angel",
    "wof:placetype":"venue"
},
  "geometry": {"coordinates":[-3.5774977207,38.8310241699],"type":"Point"}
}