{
  "type": "Feature",
  "properties": {
    "iso:country":"ES",
    "sg:address":"Calle de Marques De Cilleruelo, 8",
    "sg:city":"Reinosa",
    "sg:orig_category":"Peluqueros: De Se\u00d1oras",
    "sg:phone":"+34 942 75 38 48",
    "sg:postcode":"39200",
    "sg:province":"Cantabria",
    "wof:name":"Venus S.c.",
    "wof:placetype":"venue"
},
  "geometry": {"coordinates":[-4.1389422417,43.0015411377],"type":"Point"}
}