{
  "type": "Feature",
  "properties": {
    "addr:full":"Carrer de Maria Benlliure, 9 Roses Girona 17480",
    "addr:housenumber":"9",
    "addr:postcode":"17480",
    "addr:street":"Carrer De Maria Benlliure",
    "iso:country":"ES",
    "sg:address":"Carrer de Maria Benlliure, 9",
    "sg:city":"Roses",
    "sg:orig_category":"Reposter\u00cdas",
    "sg:phone":"+34 972 25 71 00",
    "sg:postcode":"17480",
    "sg:province":"Girona",
    "wof:name":"Rizque Racimo Antonio",
    "wof:placetype":"venue"
},
  "geometry": {"coordinates":[3.1758220196,42.2646408081],"type":"Point"}
}