{
  "type": "Feature",
  "properties": {
    "iso:country":"ES",
    "sg:address":"Calle de Tarazona, 28",
    "sg:city":"Villalgordo Jucar",
    "sg:orig_category":"Muebles Y Accesorios Para Cocinas Y Cuartos De Ba\u00d1o (al Por Menor)",
    "sg:phone":"+34 967 45 52 12",
    "sg:postcode":"02636",
    "sg:province":"Albacete",
    "wof:name":"Ponce Mondejar Jose Raul",
    "wof:placetype":"venue"
},
  "geometry": {"coordinates":[-2.0614659786,39.2944526672],"type":"Point"}
}