{
  "type": "Feature",
  "properties": {
    "addr:full":"Calle de Pedro Justo Dorado Dellmans, 5 Madrid Madrid 28040",
    "addr:housenumber":"5",
    "addr:postcode":"28040",
    "addr:street":"Calle De Pedro Justo Dorado Dellmans",
    "iso:country":"ES",
    "sg:address":"Calle de Pedro Justo Dorado Dellmans, 5",
    "sg:city":"Madrid",
    "sg:orig_category":"Promotores Constructores",
    "sg:phone":"+34 915 33 31 82",
    "sg:postcode":"28040",
    "sg:province":"Madrid",
    "wof:name":"Eurogeriatria De Salud S.l.",
    "wof:placetype":"venue"
},
  "geometry": {"coordinates":[-3.7057740688,40.42029953],"type":"Point"}
}