{
  "type": "Feature",
  "properties": {
    "iso:country":"ES",
    "sg:address":"Calle de Silos, 84",
    "sg:city":"Alcala Guadaira",
    "sg:orig_category":"Reposter\u00cdas",
    "sg:phone":"+34 955 61 68 97",
    "sg:postcode":"41500",
    "sg:province":"Sevilla",
    "wof:name":"Fernandez Gonzalez Manuel",
    "wof:placetype":"venue"
},
  "geometry": {"coordinates":[-5.8466749191,37.3439979553],"type":"Point"}
}