{
  "type": "Feature",
  "properties": {
    "iso:country":"ES",
    "sg:address":"Calle de Juan Pantoja, 16",
    "sg:city":"Madrid",
    "sg:orig_category":"Caf\u00c9s, Bares, Cervecer\u00cdas",
    "sg:phone":"+34 915 33 37 03",
    "sg:postcode":"28039",
    "sg:province":"Madrid",
    "wof:name":"Medina Mochales Vicente",
    "wof:placetype":"venue"
},
  "geometry": {"coordinates":[-3.7049241066,40.4502487183],"type":"Point"}
}