{
  "type": "Feature",
  "properties": {
    "iso:country":"ES",
    "sg:address":"Poligon C, S/n",
    "sg:city":"Xativa",
    "sg:orig_category":"Agentes, Concesionarios Y Sucursales De Veh\u00cdculos",
    "sg:phone":"+34 962 27 56 93",
    "sg:postcode":"46800",
    "sg:province":"Valencia",
    "wof:name":"C.c.f. Motors S.l.",
    "wof:placetype":"venue"
},
  "geometry": {"coordinates":[-0.5055789948,38.9977607727],"type":"Point"}
}