{
  "type": "Feature",
  "properties": {
    "addr:full":"Carr Francesc Layret, 199 Badalona Barcelona 08911",
    "addr:housenumber":"199",
    "addr:postcode":"08911",
    "addr:street":"Carr Francesc Layret",
    "iso:country":"ES",
    "sg:address":"Carr Francesc Layret, 199",
    "sg:city":"Badalona",
    "sg:orig_category":"Ropa Para Se\u00d1oras (al Por Menor)",
    "sg:phone":"+34 933 84 45 32",
    "sg:postcode":"08911",
    "sg:province":"Barcelona",
    "wof:name":"Guzman Ruzafa Maria",
    "wof:placetype":"venue"
},
  "geometry": {"coordinates":[2.2500030994,41.452671051],"type":"Point"}
}