{
  "type": "Feature",
  "properties": {
    "iso:country":"ES",
    "sg:address":"Calle de Libertad (de La), 19",
    "sg:city":"Alcobendas",
    "sg:orig_category":"Inmobiliaria (agencias)",
    "sg:phone":"+34 916 23 96 52",
    "sg:postcode":"28100",
    "sg:province":"Madrid",
    "wof:name":"Alquirent Proyectos Inmobiliarios S.l.",
    "wof:placetype":"venue"
},
  "geometry": {"coordinates":[-3.634665966,40.5403518677],"type":"Point"}
}