{
  "type": "Feature",
  "properties": {
    "iso:country":"ES",
    "sg:address":"Calle de Gobernador Fernandez Jimenez (del), 1",
    "sg:city":"Segovia",
    "sg:orig_category":"Asesor\u00cda Sobre Comunicaci\u00d3n De Empresas",
    "sg:phone":"+34 921 42 77 11",
    "sg:postcode":"40001",
    "sg:province":"Segovia",
    "wof:name":"Cuesta Perez S.l.",
    "wof:placetype":"venue"
},
  "geometry": {"coordinates":[-4.118929863,40.9464492798],"type":"Point"}
}