{
  "type": "Feature",
  "properties": {
    "iso:country":"ES",
    "sg:address":"Pg Puda, 16",
    "sg:city":"Banyoles",
    "sg:orig_category":"Agricultores, Agricultores",
    "sg:phone":"+34 972 58 16 17",
    "sg:postcode":"17820",
    "sg:province":"Girona",
    "sg:website":"www.canicat.com",
    "wof:name":"Carulla Gratacos Jordi",
    "wof:placetype":"venue"
},
  "geometry": {"coordinates":[2.7594299316,42.1168212891],"type":"Point"}
}