{
  "type": "Feature",
  "properties": {
    "iso:country":"ES",
    "sg:address":"Carrer de Igualtat, 48",
    "sg:city":"Hospitalet Llobregat",
    "sg:orig_category":"Peluquer\u00cdas, Peluquer\u00cda Mixta",
    "sg:phone":"+34 932 63 32 65",
    "sg:postcode":"08902",
    "sg:province":"Barcelona",
    "wof:name":"Llumitaxi Tuquinga Luis Vicente",
    "wof:placetype":"venue"
},
  "geometry": {"coordinates":[2.1257560253,41.3598823547],"type":"Point"}
}