{
  "type": "Feature",
  "properties": {
    "iso:country":"ES",
    "sg:address":"Calle de Garcia Morato, 25",
    "sg:city":"Alacant",
    "sg:orig_category":"Peluqueros: De Se\u00d1oras",
    "sg:phone":"+34 965 21 49 00",
    "sg:postcode":"03004",
    "sg:province":"Alicante",
    "wof:name":"Asociacion Provincial De Peluqueros De Alicante",
    "wof:placetype":"venue"
},
  "geometry": {"coordinates":[-0.4873738885,38.3487205505],"type":"Point"}
}