{
  "type": "Feature",
  "properties": {
    "addr:full":"Pase Invierno, 9 Tudela Navarra 31500",
    "addr:housenumber":"9",
    "addr:postcode":"31500",
    "addr:street":"Invierno",
    "iso:country":"ES",
    "sg:address":"Pase Invierno, 9",
    "sg:city":"Tudela",
    "sg:orig_category":"Bancos",
    "sg:phone":"+34 948 40 31 77",
    "sg:postcode":"31500",
    "sg:province":"Navarra",
    "sg:website":"www.bancodevalencia.es",
    "wof:name":"Banco De Valencia S.a.",
    "wof:placetype":"venue"
},
  "geometry": {"coordinates":[-1.6011669636,42.0615692139],"type":"Point"}
}