{
  "type": "Feature",
  "properties": {
    "addr:full":"Calle de Sorolla (de), 15 Aranjuez Madrid 28300",
    "addr:housenumber":"15",
    "addr:postcode":"28300",
    "addr:street":"Calle De Sorolla De",
    "iso:country":"ES",
    "sg:address":"Calle de Sorolla (de), 15",
    "sg:city":"Aranjuez",
    "sg:orig_category":"M\u00c9dicos: Estomatolog\u00cda",
    "sg:phone":"+34 918 91 85 60",
    "sg:postcode":"28300",
    "sg:province":"Madrid",
    "wof:name":"Serrano Alcolea Gregorio",
    "wof:placetype":"venue"
},
  "geometry": {"coordinates":[-3.5975210667,40.0267715454],"type":"Point"}
}