{
  "type": "Feature",
  "properties": {
    "addr:full":"Carrer de Pujades, 186 Barcelona Barcelona 08005",
    "addr:housenumber":"186",
    "addr:postcode":"08005",
    "addr:street":"Carrer De Pujades",
    "iso:country":"ES",
    "sg:address":"Carrer de Pujades, 186",
    "sg:city":"Barcelona",
    "sg:orig_category":"Tintorer\u00cdas, Limpieza En Seco",
    "sg:phone":"+34 934 85 46 65",
    "sg:postcode":"08005",
    "sg:province":"Barcelona",
    "wof:name":"Foguet Escote Esteban",
    "wof:placetype":"venue"
},
  "geometry": {"coordinates":[2.2009029388,41.4017181396],"type":"Point"}
}