{
  "type": "Feature",
  "properties": {
    "addr:full":"Avda Canteras (de Las), S/n Valmor-rompecubas Madrid 28340",
    "addr:postcode":"28340",
    "addr:street":"Avda Canteras De Las S / N Valmor-Rompecubas",
    "iso:country":"ES",
    "sg:address":"Avda Canteras (de Las), S/n",
    "sg:city":"Valmor-rompecubas",
    "sg:orig_category":"Dietistas",
    "sg:phone":"+34 918 09 55 15",
    "sg:postcode":"28340",
    "sg:province":"Madrid",
    "wof:name":"Laboratorios Bequisa S.l.",
    "wof:placetype":"venue"
},
  "geometry": {"coordinates":[-3.6677899361,40.1646308899],"type":"Point"}
}