{
  "type": "Feature",
  "properties": {
    "iso:country":"ES",
    "sg:address":"Cra. Canoves, 17",
    "sg:city":"Cardedeu",
    "sg:orig_category":"Cajas De Ahorro",
    "sg:phone":"+34 938 46 26 55",
    "sg:postcode":"08440",
    "sg:province":"Barcelona",
    "sg:website":"www.caixacatalunya.es",
    "wof:name":"Caixa D'estalvis De Catalunya",
    "wof:placetype":"venue"
},
  "geometry": {"coordinates":[2.355659008,41.6400032043],"type":"Point"}
}