{
  "type": "Feature",
  "properties": {
    "iso:country":"ES",
    "sg:address":"Carrer de Nou, 35",
    "sg:city":"Manresa",
    "sg:orig_category":"Lencer\u00cda Femenina, Corseter\u00cda, Trajes De Ba\u00d1o (al Por Menor)",
    "sg:phone":"+34 938 72 41 26",
    "sg:postcode":"08241",
    "sg:province":"Barcelona",
    "sg:website":"www.manresaportal.com/rubicasals",
    "wof:name":"Rubi Sagarra Francesc",
    "wof:placetype":"venue"
},
  "geometry": {"coordinates":[1.8329000473,41.7217712402],"type":"Point"}
}