{
  "type": "Feature",
  "properties": {
    "addr:full":"Sostoa-tarren Kalea, 10 Eibar Guip\u00f9zcoa 20600",
    "addr:housenumber":"10",
    "addr:postcode":"20600",
    "addr:street":"Sostoa-Tarren Kalea;Guipu\u0300Zcoa",
    "iso:country":"ES",
    "sg:address":"Sostoa-tarren Kalea, 10",
    "sg:city":"Eibar",
    "sg:orig_category":"Fabricaci\u00d3n, Venta De Productos Base Farmac\u00c9uticos",
    "sg:phone":"+34 943 20 29 16",
    "sg:postcode":"20600",
    "sg:province":"Guip\u00f9zcoa",
    "wof:name":"Lasheras Iraundegui, C.b.",
    "wof:placetype":"venue"
},
  "geometry": {"coordinates":[-2.4726080894,43.1815414429],"type":"Point"}
}