{
  "type": "Feature",
  "properties": {
    "addr:full":"Ctra Chinchon (de), Km. 0003,2 Puente De Arganda Madrid 28500",
    "addr:postcode":"28500",
    "addr:street":"Ctra Chinchon De Km. 0003,2 Puente De Arganda",
    "iso:country":"ES",
    "sg:address":"Ctra Chinchon (de), Km. 0003,2",
    "sg:city":"Puente De Arganda",
    "sg:orig_category":"Cerrajer\u00cda, Ferrallista",
    "sg:phone":"+34 918 71 92 15",
    "sg:postcode":"28500",
    "sg:province":"Madrid",
    "wof:name":"Hervas Lago Emilio",
    "wof:placetype":"venue"
},
  "geometry": {"coordinates":[-3.5113883018,40.3169517517],"type":"Point"}
}