{
  "type": "Feature",
  "properties": {
    "iso:country":"ES",
    "sg:address":"Calle de Encomienda De Palacios, 2",
    "sg:city":"Madrid",
    "sg:orig_category":"Enfermeras: Consultas, Atenci\u00d3n A Domicilio",
    "sg:phone":"+34 917 73 83 78",
    "sg:postcode":"28030",
    "sg:province":"Madrid",
    "wof:name":"Mu\u00f1oz Banuls Pilar",
    "wof:placetype":"venue"
},
  "geometry": {"coordinates":[-3.6468679905,40.40026474],"type":"Point"}
}