{
  "type": "Feature",
  "properties": {
    "iso:country":"ES",
    "sg:address":"Calle de Portalada (la), 3",
    "sg:city":"Logro\u00f1o",
    "sg:orig_category":"Confecci\u00d3n De Trajes Para Se\u00d1oras",
    "sg:phone":"+34 941 23 23 00",
    "sg:postcode":"26006",
    "sg:province":"La Rioja",
    "wof:name":"Creaciones Valmon S.l.",
    "wof:placetype":"venue"
},
  "geometry": {"coordinates":[-2.4131178856,42.4578018188],"type":"Point"}
}