{
  "type": "Feature",
  "properties": {
    "addr:full":"Calle de Porto Colon, 6 Alcorcon Madrid 28924",
    "addr:housenumber":"6",
    "addr:postcode":"28924",
    "addr:street":"Calle De Porto Colon",
    "iso:country":"ES",
    "sg:address":"Calle de Porto Colon, 6",
    "sg:city":"Alcorcon",
    "sg:orig_category":"Ense\u00d1anza: Idiomas",
    "sg:phone":"+34 916 19 29 27",
    "sg:postcode":"28924",
    "sg:province":"Madrid",
    "sg:website":"www.bugallo.com",
    "wof:name":"Bugallo Espileira Pablo Antonio",
    "wof:placetype":"venue"
},
  "geometry": {"coordinates":[-3.8209218979,40.3522758484],"type":"Point"}
}