{
  "type": "Feature",
  "properties": {
    "iso:country":"ES",
    "sg:address":"Muel Reina Sofia Norte, 5",
    "sg:city":"Palmas De Gran Canaria",
    "sg:orig_category":"Maquinaria Para Industrias Diversas",
    "sg:phone":"+34 928 46 59 22",
    "sg:postcode":"35008",
    "sg:province":"Las Palmas",
    "wof:name":"Tomonsalve S.l.",
    "wof:placetype":"venue"
},
  "geometry": {"coordinates":[-15.4067840576,28.1604404449],"type":"Point"}
}