{
  "type": "Feature",
  "properties": {
    "iso:country":"ES",
    "sg:address":"Calle de Doctor Fleming, 10",
    "sg:city":"Madridejos",
    "sg:orig_category":"Empresas De Carpinter\u00cda De Madera",
    "sg:phone":"+34 925 46 32 45",
    "sg:postcode":"45710",
    "sg:province":"Toledo",
    "wof:name":"Zapero-gonzalez S. C.",
    "wof:placetype":"venue"
},
  "geometry": {"coordinates":[-3.5307040215,39.465221405],"type":"Point"}
}