{
  "type": "Feature",
  "properties": {
    "addr:full":"Calle de San Pascual, 5 Almazora Castell\u00f3n 12550",
    "addr:housenumber":"5",
    "addr:postcode":"12550",
    "addr:street":"Calle De San Pascual",
    "iso:country":"ES",
    "sg:address":"Calle de San Pascual, 5",
    "sg:city":"Almazora",
    "sg:orig_category":"Inmobiliaria (agencias)",
    "sg:phone":"+34 964 56 00 80",
    "sg:postcode":"12550",
    "sg:province":"Castell\u00f3n",
    "sg:website":"www.olucha.com",
    "wof:name":"Olucha Balaguer Vicente",
    "wof:placetype":"venue"
},
  "geometry": {"coordinates":[-0.0631740019,39.9439582825],"type":"Point"}
}