{
  "type": "Feature",
  "properties": {
    "iso:country":"ES",
    "sg:address":"Pl Coc (del), 15",
    "sg:city":"S. Carles Rapita",
    "sg:orig_category":"Ropa Para Se\u00d1oras (al Por Menor)",
    "sg:phone":"+34 977 74 23 78",
    "sg:postcode":"43540",
    "sg:province":"Tarragona",
    "wof:name":"Mora Vilanova Pilar",
    "wof:placetype":"venue"
},
  "geometry": {"coordinates":[0.5933030248,40.6197128296],"type":"Point"}
}