{
  "type": "Feature",
  "properties": {
    "iso:country":"ES",
    "sg:address":"Calle de Manuel Llano Rebanal, 4",
    "sg:city":"Reinosa",
    "sg:orig_category":"Cristaler\u00cdas",
    "sg:phone":"+34 942 75 19 41",
    "sg:postcode":"39200",
    "sg:province":"Cantabria",
    "wof:name":"Nogales Pinelo Rafaela",
    "wof:placetype":"venue"
},
  "geometry": {"coordinates":[-4.1391940117,43.0004043579],"type":"Point"}
}