{
  "type": "Feature",
  "properties": {
    "iso:country":"ES",
    "sg:address":"Carrer de Damas Calvet, 6",
    "sg:city":"Palma",
    "sg:orig_category":"Inmobiliaria (agencias)",
    "sg:phone":"+34 971 73 23 41",
    "sg:postcode":"07011",
    "sg:province":"Islas Baleares",
    "wof:name":"Casa Xela S.l.",
    "wof:placetype":"venue"
},
  "geometry": {"coordinates":[2.6413030624,39.576259613],"type":"Point"}
}