{
  "type": "Feature",
  "properties": {
    "iso:country":"ES",
    "sg:address":"Calle de Covadonga, 37",
    "sg:city":"Palmas De Gran Canaria",
    "sg:orig_category":"Alimentaci\u00d3n General (al Por Menor)",
    "sg:phone":"+34 928 27 09 53",
    "sg:postcode":"35010",
    "sg:province":"Las Palmas",
    "wof:name":"Lorenzo Monagas Miguel",
    "wof:placetype":"venue"
},
  "geometry": {"coordinates":[-15.4461097717,28.129119873],"type":"Point"}
}