{
  "type": "Feature",
  "properties": {
    "addr:full":"Barr Barca (la), 76 Viveda Cantabria 39314",
    "addr:postcode":"39314",
    "iso:country":"ES",
    "sg:address":"Barr Barca (la), 76",
    "sg:city":"Viveda",
    "sg:orig_category":"Tapicer\u00cdas",
    "sg:phone":"+34 942 80 26 79",
    "sg:postcode":"39314",
    "sg:province":"Cantabria",
    "wof:name":"Martin Martin Alejandro",
    "wof:placetype":"venue"
},
  "geometry": {"coordinates":[-4.0517559052,43.3763237],"type":"Point"}
}