{
  "type": "Feature",
  "properties": {
    "iso:country":"ES",
    "sg:address":"Carrer de Doctor Castro, 50",
    "sg:city":"Ensanche Residencial",
    "sg:orig_category":"Asesor\u00cda Sobre Comunicaci\u00d3n De Empresas",
    "sg:phone":"+34 977 65 77 05",
    "sg:postcode":"43883",
    "sg:province":"Tarragona",
    "wof:name":"Soluciones Rentables S.l.",
    "wof:placetype":"venue"
},
  "geometry": {"coordinates":[1.4600640535,41.1879272461],"type":"Point"}
}