{
  "type": "Feature",
  "properties": {
    "iso:country":"ES",
    "sg:address":"Carrer de Pujades, 68",
    "sg:city":"Barcelona",
    "sg:orig_category":"Fabricaci\u00d3n De Moldes Y Modelos",
    "sg:phone":"+34 933 00 45 08",
    "sg:postcode":"08005",
    "sg:province":"Barcelona",
    "wof:name":"Moreno Castello Carlos",
    "wof:placetype":"venue"
},
  "geometry": {"coordinates":[2.1919150352,41.3948402405],"type":"Point"}
}