{
  "type": "Feature",
  "properties": {
    "iso:country":"ES",
    "sg:address":"Calle de Antonio Blazquez, 37",
    "sg:city":"Almaden",
    "sg:orig_category":"Bares, Piano",
    "sg:phone":"+34 926 71 06 52",
    "sg:postcode":"13400",
    "sg:province":"Ciudad Real",
    "wof:name":"El Burladero Almaden S.l.",
    "wof:placetype":"venue"
},
  "geometry": {"coordinates":[-4.8349394798,38.7753601074],"type":"Point"}
}