{
  "type": "Feature",
  "properties": {
    "iso:country":"ES",
    "sg:address":"Calle de Pe\u00d1a Francia, 1",
    "sg:city":"Zamora",
    "sg:orig_category":"Caf\u00c9s, Bares, Cervecer\u00cdas",
    "sg:phone":"+34 980 51 05 60",
    "sg:postcode":"49018",
    "sg:province":"Zamora",
    "wof:name":"Manuel Antonio Alvarez Llamero Y Fernando Rodriguez Raton Cdad",
    "wof:placetype":"venue"
},
  "geometry": {"coordinates":[-5.7457342148,41.5033302307],"type":"Point"}
}