{
  "type": "Feature",
  "properties": {
    "addr:full":"Av Rasos De Peguera, 31 Barcelona Barcelona 08033",
    "addr:housenumber":"31",
    "addr:postcode":"08033",
    "addr:street":"Av Rasos De Peguera",
    "iso:country":"ES",
    "sg:address":"Av Rasos De Peguera, 31",
    "sg:city":"Barcelona",
    "sg:orig_category":"Peluquer\u00cdas, Peluquer\u00cda Mixta",
    "sg:phone":"+34 933 50 43 16",
    "sg:postcode":"08033",
    "sg:province":"Barcelona",
    "wof:name":"Garcia Crespin Ana",
    "wof:placetype":"venue"
},
  "geometry": {"coordinates":[2.1778540611,41.4609870911],"type":"Point"}
}