{
  "type": "Feature",
  "properties": {
    "addr:full":"La Ba\u00f1eza, 1 Veguellina Orbigo Le\u00f3n 24350",
    "addr:housenumber":"1",
    "addr:postcode":"24350",
    "addr:street":"Ban\u0303Eza;Leo\u0301N",
    "iso:country":"ES",
    "sg:address":"La Ba\u00f1eza, 1",
    "sg:city":"Veguellina Orbigo",
    "sg:orig_category":"Psic\u00d3logos",
    "sg:phone":"+34 987 37 62 18",
    "sg:postcode":"24350",
    "sg:province":"Le\u00f3n",
    "wof:name":"Paramio Requejo Ana",
    "wof:placetype":"venue"
},
  "geometry": {"coordinates":[-5.8852372169,42.4383964539],"type":"Point"}
}