{
  "type": "Feature",
  "properties": {
    "addr:full":"Calle de Santa Teresa, 10 Valencia Valencia 46001",
    "addr:housenumber":"10",
    "addr:postcode":"46001",
    "addr:street":"Calle De Santa Teresa",
    "iso:country":"ES",
    "sg:address":"Calle de Santa Teresa, 10",
    "sg:city":"Valencia",
    "sg:orig_category":"Centros De Educaci\u00d3n Especial",
    "sg:phone":"+34 963 92 14 73",
    "sg:postcode":"46001",
    "sg:province":"Valencia",
    "wof:name":"Per L' Horta",
    "wof:placetype":"venue"
},
  "geometry": {"coordinates":[-0.3812381029,39.4746437073],"type":"Point"}
}