{
  "type": "Feature",
  "properties": {
    "iso:country":"ES",
    "sg:address":"Plaz Espa\u00d1a, 14",
    "sg:city":"Villaluenga Sagra",
    "sg:orig_category":"Maquinaria Para Industrias Diversas",
    "sg:phone":"+34 925 53 07 94",
    "sg:postcode":"45520",
    "sg:province":"Toledo",
    "wof:name":"Grugar S.l.",
    "wof:placetype":"venue"
},
  "geometry": {"coordinates":[-4.0244760513,39.8567771912],"type":"Point"}
}