{
  "type": "Feature",
  "properties": {
    "addr:full":"Calle de Sevilla, 29 Ca\u00e7ete La Real M\u00e1laga 29340",
    "addr:housenumber":"29",
    "addr:postcode":"29340",
    "addr:street":"Calle De Sevilla;Ma\u0301Laga",
    "iso:country":"ES",
    "sg:address":"Calle de Sevilla, 29",
    "sg:city":"Ca\u00e7ete La Real",
    "sg:orig_category":"Supermercados Y Hipermercados",
    "sg:phone":"+34 952 18 30 36",
    "sg:postcode":"29340",
    "sg:province":"M\u00e1laga",
    "wof:name":"Cruces Rio Ana Maria",
    "wof:placetype":"venue"
},
  "geometry": {"coordinates":[-5.024728775,36.9514808655],"type":"Point"}
}