{
  "type": "Feature",
  "properties": {
    "iso:country":"ES",
    "sg:address":"Juan Sbtan El Cano, S/n",
    "sg:city":"Almassora",
    "sg:orig_category":"Empresas De Carpinter\u00cda De Madera",
    "sg:phone":"+34 964 55 05 10",
    "sg:postcode":"12550",
    "sg:province":"Castell\u00f3n",
    "wof:name":"Carpinteria Pedro Lopez S.l.",
    "wof:placetype":"venue"
},
  "geometry": {"coordinates":[-0.0631700009,39.9439582825],"type":"Point"}
}