{
  "type": "Feature",
  "properties": {
    "iso:country":"ES",
    "sg:address":"Carrer de Frederic Soler, 43",
    "sg:city":"Prat Llobregat",
    "sg:orig_category":"Ropa Para Caballeros (al Por Menor)",
    "sg:phone":"+34 933 79 82 90",
    "sg:postcode":"08820",
    "sg:province":"Barcelona",
    "wof:name":"Charneco Perez Manuela",
    "wof:placetype":"venue"
},
  "geometry": {"coordinates":[2.0967719555,41.3259124756],"type":"Point"}
}