{
  "type": "Feature",
  "properties": {
    "addr:full":"Carrer de Dansa, 1 Barcelona Barcelona 08035",
    "addr:housenumber":"1",
    "addr:postcode":"08035",
    "addr:street":"Carrer De Dansa",
    "iso:country":"ES",
    "sg:address":"Carrer de Dansa, 1",
    "sg:city":"Barcelona",
    "sg:orig_category":"Supermercados Y Hipermercados",
    "sg:phone":"+34 934 28 11 47",
    "sg:postcode":"08035",
    "sg:province":"Barcelona",
    "wof:name":"Trota Buchaca Jose Maria",
    "wof:placetype":"venue"
},
  "geometry": {"coordinates":[2.1423220634,41.4333381653],"type":"Point"}
}