{
  "type": "Feature",
  "properties": {
    "iso:country":"ES",
    "sg:address":"Calle de Teodoro Gonzalez De Zarate, 20",
    "sg:city":"Vitoria-gasteiz",
    "sg:orig_category":"Art\u00cdculos De Regalo (al Por Menor)",
    "sg:phone":"+34 945 13 29 99",
    "sg:postcode":"01007",
    "sg:province":"\u00c1lava",
    "wof:name":"Milagros Gomez Vilda",
    "wof:placetype":"venue"
},
  "geometry": {"coordinates":[-2.6955170631,42.8404846191],"type":"Point"}
}