{
  "type": "Feature",
  "properties": {
    "iso:country":"ES",
    "sg:address":"Calle de Jacinto Ruiz De Mendoza, 13",
    "sg:city":"Trujillo",
    "sg:orig_category":"\u00d3ptica: Instrumentos (fabricaci\u00d3n)",
    "sg:phone":"+34 927 32 08 70",
    "sg:postcode":"10200",
    "sg:province":"C\u00e1ceres",
    "wof:name":"Optica Corbacho Tercero S.l.",
    "wof:placetype":"venue"
},
  "geometry": {"coordinates":[-5.8830242157,39.4572257996],"type":"Point"}
}