{
  "type": "Feature",
  "properties": {
    "addr:full":"Send Valentin De Foronda, 1 Vitoria-gasteiz \u00c1lava 01010",
    "addr:housenumber":"1",
    "addr:postcode":"01010",
    "addr:street":"Send Valentin De Foronda",
    "iso:country":"ES",
    "sg:address":"Send Valentin De Foronda, 1",
    "sg:city":"Vitoria-gasteiz",
    "sg:orig_category":"Iglesia Cat\u00d3lica",
    "sg:phone":"+34 945 24 76 75",
    "sg:postcode":"01010",
    "sg:province":"\u00c1lava",
    "wof:name":"Parroquia Nuestra Se\u00f1ora De Los Dolores",
    "wof:placetype":"venue"
},
  "geometry": {"coordinates":[-2.6998240948,42.8534507751],"type":"Point"}
}