{
  "type": "Feature",
  "properties": {
    "addr:full":"Carrer de Alacant, 26 Barcelona Barcelona 08022",
    "addr:housenumber":"26",
    "addr:postcode":"08022",
    "addr:street":"Carrer De Alacant",
    "iso:country":"ES",
    "sg:address":"Carrer de Alacant, 26",
    "sg:city":"Barcelona",
    "sg:orig_category":"Ropa Para Se\u00d1oras (al Por Menor)",
    "sg:phone":"+34 934 18 33 82",
    "sg:postcode":"08022",
    "sg:province":"Barcelona",
    "wof:name":"Pages Simon Javier",
    "wof:placetype":"venue"
},
  "geometry": {"coordinates":[2.1350259781,41.4010620117],"type":"Point"}
}