{
  "type": "Feature",
  "properties": {
    "addr:full":"Trva Valderrama, 3 Santander Cantabria 39010",
    "addr:housenumber":"3",
    "addr:postcode":"39010",
    "addr:street":"Trva Valderrama",
    "iso:country":"ES",
    "sg:address":"Trva Valderrama, 3",
    "sg:city":"Santander",
    "sg:orig_category":"Inmobiliaria (agencias)",
    "sg:phone":"+34 942 24 15 82",
    "sg:postcode":"39010",
    "sg:province":"Cantabria",
    "sg:website":"www.inmobelasco.com",
    "wof:name":"Bengochea Pierrugues Petra M",
    "wof:placetype":"venue"
},
  "geometry": {"coordinates":[-3.8248429298,43.4592285156],"type":"Point"}
}