{
  "type": "Feature",
  "properties": {
    "iso:country":"ES",
    "sg:address":"Avda Virgen Del Carmen, 15",
    "sg:city":"Algeciras",
    "sg:orig_category":"Combustibles: Fuel",
    "sg:phone":"+34 956 65 00 11",
    "sg:postcode":"11201",
    "sg:province":"C\u00e1diz",
    "wof:name":"Cia. Iberica De Remolcadores Del Estrecho S.a.",
    "wof:placetype":"venue"
},
  "geometry": {"coordinates":[-5.444606781,36.1295623779],"type":"Point"}
}