{
  "type": "Feature",
  "properties": {
    "addr:full":"C/ Poeta Miguel Hernandez, 25 Elche Alicante 03201",
    "addr:housenumber":"25",
    "addr:postcode":"03201",
    "addr:street":"C / Poeta Miguel Hernandez",
    "iso:country":"ES",
    "sg:address":"C/ Poeta Miguel Hernandez, 25",
    "sg:city":"Elche",
    "sg:orig_category":"Institutos De Belleza",
    "sg:phone":"+34 965 43 30 56",
    "sg:postcode":"03201",
    "sg:province":"Alicante",
    "wof:name":"Catalana De Bellessa S.l.",
    "wof:placetype":"venue"
},
  "geometry": {"coordinates":[-0.7047839761,38.2642555237],"type":"Point"}
}