{
  "type": "Feature",
  "properties": {
    "iso:country":"ES",
    "sg:address":"Carrer de Valles, S/n",
    "sg:city":"Poligono Industrial Ramasa",
    "sg:orig_category":"Distribuci\u00d3n De Petr\u00d3leo Y Derivados",
    "sg:phone":"+34 938 49 20 11",
    "sg:postcode":"08520",
    "sg:province":"Barcelona",
    "wof:name":"Estacio De Servei Del Ramassa S.l.",
    "wof:placetype":"venue"
},
  "geometry": {"coordinates":[2.2992899418,41.6361808777],"type":"Point"}
}