{
  "type": "Feature",
  "properties": {
    "addr:full":"Carrer de Valira, 1 Terrassa Barcelona 08227",
    "addr:housenumber":"1",
    "addr:postcode":"08227",
    "addr:street":"Carrer De Valira",
    "iso:country":"ES",
    "sg:address":"Carrer de Valira, 1",
    "sg:city":"Terrassa",
    "sg:orig_category":"Art\u00cdculos De Regalo (al Por Menor)",
    "sg:phone":"+34 937 86 35 96",
    "sg:postcode":"08227",
    "sg:province":"Barcelona",
    "wof:name":"Hernandez Borrego Vanesa",
    "wof:placetype":"venue"
},
  "geometry": {"coordinates":[2.0364511013,41.5749053955],"type":"Point"}
}