{
  "type": "Feature",
  "properties": {
    "iso:country":"ES",
    "sg:address":"Avda Urdaneta, 13",
    "sg:city":"Zumarraga",
    "sg:orig_category":"Imprenta",
    "sg:phone":"+34 943 72 06 65",
    "sg:postcode":"20700",
    "sg:province":"Guip\u00f9zcoa",
    "wof:name":"Carlos Rodriguez Ayerbe",
    "wof:placetype":"venue"
},
  "geometry": {"coordinates":[-2.3152430058,43.0880775452],"type":"Point"}
}