{
  "type": "Feature",
  "properties": {
    "addr:full":"Cmno Colmenar, 24 Malaga M\u00e1laga 29013",
    "addr:housenumber":"24",
    "addr:postcode":"29013",
    "addr:street":"Cmno Colmenar;Ma\u0301Laga",
    "iso:country":"ES",
    "sg:address":"Cmno Colmenar, 24",
    "sg:city":"Malaga",
    "sg:orig_category":"Abogados",
    "sg:phone":"+34 952 25 02 09",
    "sg:postcode":"29013",
    "sg:province":"M\u00e1laga",
    "wof:name":"Garcia Molina Jose Miguel",
    "wof:placetype":"venue"
},
  "geometry": {"coordinates":[-4.4158172607,36.7344017029],"type":"Point"}
}