{
  "type": "Feature",
  "properties": {
    "addr:full":"Carrer de Eugeni D'ors, S/n Vilafranca Penedes Barcelona 08720",
    "addr:housenumber":"s / n",
    "addr:postcode":"08720",
    "addr:street":"Carrer De Eugeni D'Ors;Penedes Barcelona",
    "iso:country":"ES",
    "sg:address":"Carrer de Eugeni D'ors, S/n",
    "sg:city":"Vilafranca Penedes",
    "sg:orig_category":"Organizaciones Internacionales",
    "sg:phone":"+34 938 91 53 00",
    "sg:postcode":"08720",
    "sg:province":"Barcelona",
    "wof:name":"Cruz Roja Espa\u00f1ola",
    "wof:placetype":"venue"
},
  "geometry": {"coordinates":[1.6922229528,41.3432350159],"type":"Point"}
}