{
  "type": "Feature",
  "properties": {
    "addr:full":"Urbieta Kalea, 7 Hernani Guip\u00f9zcoa 20120",
    "addr:housenumber":"7",
    "addr:postcode":"20120",
    "addr:street":"Urbieta Kalea;Guipu\u0300Zcoa",
    "iso:country":"ES",
    "sg:address":"Urbieta Kalea, 7",
    "sg:city":"Hernani",
    "sg:classifiers":[
        {
            "category":"Autos & Motor Vehicles",
            "subcategory":"Automobile Sales",
            "type":"Retail Goods"
        }
    ],
    "sg:phone":"+34 943 55 34 16",
    "sg:postcode":"20120",
    "sg:province":"Guip\u00f9zcoa",
    "wof:name":"Zulaica Quintela Rafael",
    "wof:placetype":"venue"
},
  "geometry": {"coordinates":[-1.9758909941,43.2669067383],"type":"Point"}
}