{
  "type": "Feature",
  "properties": {
    "iso:country":"ES",
    "sg:address":"Calle de Industria (la), 2",
    "sg:city":"Logro\u00f1o",
    "sg:orig_category":"Farmacias",
    "sg:phone":"+34 941 21 15 92",
    "sg:postcode":"26005",
    "sg:province":"La Rioja",
    "wof:name":"Chorro Martinez Miren Maite",
    "wof:placetype":"venue"
},
  "geometry": {"coordinates":[-2.4562749863,42.4649963379],"type":"Point"}
}