{
  "type": "Feature",
  "properties": {
    "addr:full":"Calle de Villacarrillo (blq), 5 Madrid Madrid 28008",
    "addr:housenumber":"5",
    "addr:postcode":"28008",
    "addr:street":"Calle De Villacarrillo Blq",
    "iso:country":"ES",
    "sg:address":"Calle de Villacarrillo (blq), 5",
    "sg:city":"Madrid",
    "sg:orig_category":"Asesor\u00cdas En Comunicaci\u00d3n",
    "sg:phone":"+34 915 59 23 89",
    "sg:postcode":"28008",
    "sg:province":"Madrid",
    "wof:name":"Barbizon S.l.",
    "wof:placetype":"venue"
},
  "geometry": {"coordinates":[-3.6643579006,40.37550354],"type":"Point"}
}