{
  "type": "Feature",
  "properties": {
    "iso:country":"ES",
    "sg:address":"Rua Castelao, 6",
    "sg:city":"Ca\u00f1iza",
    "sg:orig_category":"Arreglo, Reparaci\u00d3n, Piezas Sueltas De Televisi\u00d3n, V\u00cddeo, Hi",
    "sg:phone":"+34 986 65 13 96",
    "sg:postcode":"36880",
    "sg:province":"Pontevedra",
    "wof:name":"Miguelez Estevez Jose Manuel",
    "wof:placetype":"venue"
},
  "geometry": {"coordinates":[-8.273182869,42.2129859924],"type":"Point"}
}