{
  "type": "Feature",
  "properties": {
    "addr:full":"Carr De Carrer de Sar Cataldo, 72 Benicarlo Castell\u00f3n 12580",
    "addr:housenumber":"72",
    "addr:postcode":"12580",
    "addr:street":"Carr;Carrer De;Cataldo",
    "iso:country":"ES",
    "sg:address":"Carr De Carrer de Sar Cataldo, 72",
    "sg:city":"Benicarlo",
    "sg:orig_category":"Fabricaci\u00d3n De Jabones, Detergentes Y Lej\u00cdas",
    "sg:phone":"+34 964 47 43 51",
    "sg:postcode":"12580",
    "sg:province":"Castell\u00f3n",
    "wof:name":"Hermanos Anvel S. L.",
    "wof:placetype":"venue"
},
  "geometry": {"coordinates":[0.4042100012,40.4457893372],"type":"Point"}
}