{
  "type": "Feature",
  "properties": {
    "iso:country":"ES",
    "sg:address":"Ctr. Herencias, S/n",
    "sg:city":"Villafranca Caballeros",
    "sg:orig_category":"Productores Recolectores, Venta Directa De Vinos",
    "sg:phone":"+34 926 57 80 22",
    "sg:postcode":"45730",
    "sg:province":"Toledo",
    "wof:name":"Cristo De Santa Ana Sociedad Cooperativa De C-lm",
    "wof:placetype":"venue"
},
  "geometry": {"coordinates":[-3.3565769196,39.4263534546],"type":"Point"}
}