{
  "type": "Feature",
  "properties": {
    "addr:full":"Calle de Eusebio Moran, 15 Madrid Madrid 28019",
    "addr:housenumber":"15",
    "addr:postcode":"madrid;28019",
    "addr:street":"Calle De Eusebio Moran",
    "iso:country":"ES",
    "sg:address":"Calle de Eusebio Moran, 15",
    "sg:city":"Madrid",
    "sg:orig_category":"Estudios, Instalaci\u00d3n De Climatizaci\u00d3n",
    "sg:phone":"+34 914 69 98 01",
    "sg:postcode":"28019",
    "sg:province":"Madrid",
    "wof:name":"Nexan Clima S.l.",
    "wof:placetype":"venue"
},
  "geometry": {"coordinates":[-3.7203280926,40.3888626099],"type":"Point"}
}