{
  "type": "Feature",
  "properties": {
    "iso:country":"ES",
    "sg:address":"Carrer de Turo, 17",
    "sg:city":"Can Sant Joan",
    "sg:orig_category":"Cerrajer\u00cda, Ferrallista",
    "sg:phone":"+34 935 72 40 85",
    "sg:postcode":"08110",
    "sg:province":"Barcelona",
    "wof:name":"Coscojuela Coscojuela Angel",
    "wof:placetype":"venue"
},
  "geometry": {"coordinates":[2.1817660332,41.4890899658],"type":"Point"}
}