{
  "type": "Feature",
  "properties": {
    "iso:country":"ES",
    "sg:address":"C/ Alfons Xii, 58",
    "sg:city":"Banyoles",
    "sg:orig_category":"Agentes De Seguros",
    "sg:phone":"+34 972 58 12 37",
    "sg:postcode":"17820",
    "sg:province":"Girona",
    "wof:name":"Casellas I Sans S.l.",
    "wof:placetype":"venue"
},
  "geometry": {"coordinates":[2.7635710239,42.1198577881],"type":"Point"}
}