{
  "type": "Feature",
  "properties": {
    "addr:full":"Calle de Martin Perez Bernardo, 19 Salamanca Salamanca 37005",
    "addr:housenumber":"19",
    "addr:postcode":"37005",
    "addr:street":"Calle De Martin Perez Bernardo",
    "iso:country":"ES",
    "sg:address":"Calle de Martin Perez Bernardo, 19",
    "sg:city":"Salamanca",
    "sg:orig_category":"Alquiler De Salones",
    "sg:phone":"+34 923 24 01 02",
    "sg:postcode":"37005",
    "sg:province":"Salamanca",
    "wof:name":"Serrano Garcia Eladio",
    "wof:placetype":"venue"
},
  "geometry": {"coordinates":[-5.6620988846,40.9700508118],"type":"Point"}
}