{
  "type": "Feature",
  "properties": {
    "addr:full":"Avda Marenostrum, 11 Arroyo De La Miel-benalmadena Costa M\u00e1laga 29631",
    "addr:housenumber":"11",
    "addr:postcode":"29631",
    "addr:street":"Avda Marenostrum;Ma\u0301Laga",
    "iso:country":"ES",
    "sg:address":"Avda Marenostrum, 11",
    "sg:city":"Arroyo De La Miel-benalmadena Costa",
    "sg:orig_category":"Inform\u00c1tica (estudios, Servicios, Asesor\u00cda, Formaci\u00d3n)",
    "sg:phone":"+34 952 56 22 97",
    "sg:postcode":"29631",
    "sg:province":"M\u00e1laga",
    "wof:name":"Tecnisoft Sur S.l",
    "wof:placetype":"venue"
},
  "geometry": {"coordinates":[-4.5404992104,36.5962715149],"type":"Point"}
}