{
  "type": "Feature",
  "properties": {
    "addr:full":"Carr Ferran Puig, 7 Mollerussa Lleida 25230",
    "addr:housenumber":"7",
    "addr:postcode":"25230",
    "addr:street":"Carr Ferran Puig",
    "iso:country":"ES",
    "sg:address":"Carr Ferran Puig, 7",
    "sg:city":"Mollerussa",
    "sg:orig_category":"Electrodom\u00c9sticos (al Por Menor)",
    "sg:phone":"+34 973 71 22 20",
    "sg:postcode":"25230",
    "sg:province":"Lleida",
    "wof:name":"Electro Clotet S.l.",
    "wof:placetype":"venue"
},
  "geometry": {"coordinates":[0.8920099735,41.6281509399],"type":"Point"}
}