{
  "type": "Feature",
  "properties": {
    "addr:full":"Calle de Cristo Del, 1 Bilbao Vizcaya 48007",
    "addr:housenumber":"1",
    "addr:postcode":"48007",
    "addr:street":"Calle De Cristo Del",
    "iso:country":"ES",
    "sg:address":"Calle de Cristo Del, 1",
    "sg:city":"Bilbao",
    "sg:orig_category":"Empresarios Y Productoras De Espect\u00c1culos",
    "sg:phone":"+34 944 46 42 16",
    "sg:postcode":"48007",
    "sg:province":"Vizcaya",
    "wof:name":"Norte Producciones Culturales S.l.",
    "wof:placetype":"venue"
},
  "geometry": {"coordinates":[-2.9223937988,43.2651977539],"type":"Point"}
}