{
  "type": "Feature",
  "properties": {
    "addr:full":"Sobreguexe(cecebre), 31 Sobreguexe La Coru\u00f1a 15650",
    "addr:housenumber":"31",
    "addr:postcode":"15650",
    "addr:street":"Cecebre;La Corun\u0303A",
    "iso:country":"ES",
    "sg:address":"Sobreguexe(cecebre), 31",
    "sg:city":"Sobreguexe",
    "sg:orig_category":"M\u00c1quinas Textiles, Accesorios Y Suministros (fabricaci\u00d3n)",
    "sg:phone":"+34 981 65 61 91",
    "sg:postcode":"15650",
    "sg:province":"La Coru\u00f1a",
    "wof:name":"Kurt Kauf S.a.",
    "wof:placetype":"venue"
},
  "geometry": {"coordinates":[-8.3959693909,43.3714904785],"type":"Point"}
}