{
  "type": "Feature",
  "properties": {
    "addr:full":"Marti L'huma, 7 Quart Poblet Valencia 46930",
    "addr:housenumber":"7",
    "addr:postcode":"46930",
    "addr:street":"L'Huma;Poblet",
    "iso:country":"ES",
    "sg:address":"Marti L'huma, 7",
    "sg:city":"Quart Poblet",
    "sg:orig_category":"Alquiler De Veh\u00cdculos: Turismos Y Utilitarios",
    "sg:phone":"+34 961 52 17 71",
    "sg:postcode":"46930",
    "sg:province":"Valencia",
    "wof:name":"Ibarbus S.l.",
    "wof:placetype":"venue"
},
  "geometry": {"coordinates":[-0.4643115997,39.4776687622],"type":"Point"}
}