{
  "type": "Feature",
  "properties": {
    "addr:full":"Calle de Estrada, 1 Palencia Palencia 34002",
    "addr:housenumber":"1",
    "addr:postcode":"34002",
    "addr:street":"Calle De Estrada",
    "iso:country":"ES",
    "sg:address":"Calle de Estrada, 1",
    "sg:city":"Palencia",
    "sg:orig_category":"Asesor\u00cda Fiscal Y Jur\u00cddica",
    "sg:phone":"+34 979 73 00 39",
    "sg:postcode":"34002",
    "sg:province":"Palencia",
    "wof:name":"Garcia Cortes Maria De Los Angeles",
    "wof:placetype":"venue"
},
  "geometry": {"coordinates":[-4.5297031403,42.0076065063],"type":"Point"}
}