{
  "type": "Feature",
  "properties": {
    "addr:full":"Cno Vjo De Silla, 13 Catarroja Valencia 46470",
    "addr:housenumber":"13",
    "addr:postcode":"46470",
    "addr:street":"Cno Vjo De Silla",
    "iso:country":"ES",
    "sg:address":"Cno Vjo De Silla, 13",
    "sg:city":"Catarroja",
    "sg:orig_category":"Encuadernaci\u00d3n E Impresi\u00d3n De Folletos",
    "sg:phone":"+34 961 26 42 75",
    "sg:postcode":"46470",
    "sg:province":"Valencia",
    "wof:name":"Gomez Encuadernaciones S.a.l.",
    "wof:placetype":"venue"
},
  "geometry": {"coordinates":[-0.414440006,39.3972015381],"type":"Point"}
}