{
  "type": "Feature",
  "properties": {
    "addr:full":"Carrer de Rutlla (la), 25 Terrassa Barcelona 08221",
    "addr:housenumber":"25",
    "addr:postcode":"08221",
    "addr:street":"Carrer De Rutlla La",
    "iso:country":"ES",
    "sg:address":"Carrer de Rutlla (la), 25",
    "sg:city":"Terrassa",
    "sg:orig_category":"Art\u00cdculos De Regalo (al Por Menor)",
    "sg:phone":"+34 937 85 90 39",
    "sg:postcode":"08221",
    "sg:province":"Barcelona",
    "wof:name":"Casamitjana Casals Antonio",
    "wof:placetype":"venue"
},
  "geometry": {"coordinates":[2.011646986,41.560874939],"type":"Point"}
}