{
  "type": "Feature",
  "properties": {
    "addr:full":"Pl Comtat Rossello, 4 Palma Islas Baleares 07002",
    "addr:housenumber":"4",
    "addr:postcode":"07002",
    "addr:street":"Pl Comtat Rossello",
    "iso:country":"ES",
    "sg:address":"Pl Comtat Rossello, 4",
    "sg:city":"Palma",
    "sg:orig_category":"M\u00c9dicos: Estomatolog\u00cda",
    "sg:phone":"+34 971 71 76 39",
    "sg:postcode":"07002",
    "sg:province":"Islas Baleares",
    "wof:name":"Garcia Requejo Azarias",
    "wof:placetype":"venue"
},
  "geometry": {"coordinates":[2.6543700695,39.5741500854],"type":"Point"}
}