{
  "type": "Feature",
  "properties": {
    "iso:country":"ES",
    "sg:address":"Calle de San Antonio Maria Claret, 26",
    "sg:city":"Zaragoza",
    "sg:orig_category":"Molduras, Junquillos, Listones Y Molduras Perforadas",
    "sg:phone":"+34 976 55 51 15",
    "sg:postcode":"50005",
    "sg:province":"Zaragoza",
    "wof:name":"Anton Higes Pedro",
    "wof:placetype":"venue"
},
  "geometry": {"coordinates":[-0.8948575854,41.6450195312],"type":"Point"}
}