{
  "type": "Feature",
  "properties": {
    "addr:full":"Calle de Manuel Garcia Conde, 5 Oviedo Asturias 33001",
    "addr:housenumber":"5",
    "addr:postcode":"33001",
    "addr:street":"Calle De Manuel Garcia Conde",
    "iso:country":"ES",
    "sg:address":"Calle de Manuel Garcia Conde, 5",
    "sg:city":"Oviedo",
    "sg:orig_category":"Abogados",
    "sg:phone":"+34 985 21 64 57",
    "sg:postcode":"33001",
    "sg:province":"Asturias",
    "wof:name":"Diego Martinez Justo De",
    "wof:placetype":"venue"
},
  "geometry": {"coordinates":[-5.8464198112,43.3667869568],"type":"Point"}
}