{
  "type": "Feature",
  "properties": {
    "iso:country":"ES",
    "sg:address":"Calle de General Esparteros, 5",
    "sg:city":"Almaden",
    "sg:orig_category":"Sindicatos De Trabajadores",
    "sg:phone":"+34 926 71 11 14",
    "sg:postcode":"13400",
    "sg:province":"Ciudad Real",
    "wof:name":"Federacion Regional De Ense\u00f1anza De Comisiones Obreras",
    "wof:placetype":"venue"
},
  "geometry": {"coordinates":[-4.8297801018,38.7735939026],"type":"Point"}
}