{
  "type": "Feature",
  "properties": {
    "iso:country":"ES",
    "sg:address":"Calle de Hermanos Garcia Noblejas, 170",
    "sg:city":"Madrid",
    "sg:orig_category":"Centros De Reservas Hoteleras",
    "sg:phone":"+34 913 75 13 42",
    "sg:postcode":"28037",
    "sg:province":"Madrid",
    "wof:name":"Velasco Ortiz Fuensanta",
    "wof:placetype":"venue"
},
  "geometry": {"coordinates":[-3.6278998852,40.4234771729],"type":"Point"}
}