{
  "type": "Feature",
  "properties": {
    "iso:country":"ES",
    "sg:address":"Ctra Nacional Iv, Km. 0451,9",
    "sg:city":"Ecija",
    "sg:orig_category":"Aparatos E Instalaci\u00d3n De Regad\u00cdos",
    "sg:phone":"+34 954 83 18 88",
    "sg:postcode":"41400",
    "sg:province":"Sevilla",
    "wof:name":"Riegos J Vera S.l.",
    "wof:placetype":"venue"
},
  "geometry": {"coordinates":[-5.0782690048,37.5395584106],"type":"Point"}
}