{
  "type": "Feature",
  "properties": {
    "addr:full":"Carrer de Pi I Gibert, 1 S. Adria Besos Barcelona 08930",
    "addr:housenumber":"1",
    "addr:postcode":"08930",
    "addr:street":"Carrer De Pi I Gibert;Barcelona",
    "iso:country":"ES",
    "sg:address":"Carrer de Pi I Gibert, 1",
    "sg:city":"S. Adria Besos",
    "sg:orig_category":"Vidrio, Fabricaci\u00d3n Y Comercio",
    "sg:phone":"+34 933 81 98 13",
    "sg:postcode":"08930",
    "sg:province":"Barcelona",
    "sg:website":"www.schott.es",
    "wof:name":"Schott Iberica S.a.",
    "wof:placetype":"venue"
},
  "geometry": {"coordinates":[2.2153689861,41.4305000305],"type":"Point"}
}