{
  "type": "Feature",
  "properties": {
    "iso:country":"ES",
    "sg:address":"Ctra Arta, 46",
    "sg:city":"Platja D'alcudia",
    "sg:orig_category":"Doctores En Medicina",
    "sg:phone":"+34 971 89 22 22",
    "sg:postcode":"07408",
    "sg:province":"Islas Baleares",
    "wof:name":"Nicolau Alsina Juan Manuel",
    "wof:placetype":"venue"
},
  "geometry": {"coordinates":[3.120937109,39.8396034241],"type":"Point"}
}