{
  "type": "Feature",
  "properties": {
    "iso:country":"ES",
    "sg:address":"Luga Cementerio Municipal, S/n",
    "sg:city":"Toledo",
    "sg:orig_category":"Cementerios",
    "sg:phone":"+34 925 22 03 95",
    "sg:postcode":"45003",
    "sg:province":"Toledo",
    "wof:name":"Ayuntamiento De Toledo",
    "wof:placetype":"venue"
},
  "geometry": {"coordinates":[-3.9827404022,39.8976478577],"type":"Point"}
}