{
  "type": "Feature",
  "properties": {
    "addr:full":"Rua Doutor Teixeiro (do), 17 Santiago De Compostela La Coru\u00f1a 15701",
    "addr:housenumber":"17",
    "addr:postcode":"15701",
    "addr:street":"Rua Doutor Teixeiro Do;Corun\u0303A",
    "iso:country":"ES",
    "sg:address":"Rua Doutor Teixeiro (do), 17",
    "sg:city":"Santiago De Compostela",
    "sg:orig_category":"Ropa Para Se\u00d1oras Y Caballeros (al Por Menor)",
    "sg:phone":"+34 981 57 35 06",
    "sg:postcode":"15701",
    "sg:province":"La Coru\u00f1a",
    "wof:name":"Julian Rus Ca\u00f1ibano S.l.",
    "wof:placetype":"venue"
},
  "geometry": {"coordinates":[-8.5449819565,42.8750915527],"type":"Point"}
}