{
  "type": "Feature",
  "properties": {
    "iso:country":"ES",
    "sg:address":"Calle de Salobral D (cha), 7",
    "sg:city":"Madrid",
    "sg:orig_category":"Radiocomunicaciones, Telefon\u00cda M\u00d3vil, Radiomensajer\u00cda: Servicios, Comercializaci\u00d3n",
    "sg:phone":"+34 914 68 02 77",
    "sg:postcode":"28045",
    "sg:province":"Madrid",
    "wof:name":"C.q.o. S.a.",
    "wof:placetype":"venue"
},
  "geometry": {"coordinates":[-3.7057740688,40.42029953],"type":"Point"}
}