{
  "type": "Feature",
  "properties": {
    "iso:country":"ES",
    "sg:address":"Pol. Industrial, 5",
    "sg:city":"Torredembarra",
    "sg:orig_category":"Agentes, Concesionarios Y Sucursales De Veh\u00cdculos",
    "sg:phone":"+34 977 64 25 80",
    "sg:postcode":"43830",
    "sg:province":"Tarragona",
    "wof:name":"Casino Motor S.l.",
    "wof:placetype":"venue"
},
  "geometry": {"coordinates":[1.395424962,41.1436691284],"type":"Point"}
}