{
  "type": "Feature",
  "properties": {
    "addr:full":"Calle de Pedro Mu\u00d1oz, 60 Ciudad Real Ciudad Real 13005",
    "addr:housenumber":"60",
    "addr:postcode":"13005",
    "addr:street":"Calle De Pedro Mun\u0303Oz",
    "iso:country":"ES",
    "sg:address":"Calle de Pedro Mu\u00d1oz, 60",
    "sg:city":"Ciudad Real",
    "sg:orig_category":"Inform\u00c1tica (estudios, Servicios, Asesor\u00cda, Formaci\u00d3n)",
    "sg:phone":"+34 926 21 73 68",
    "sg:postcode":"13005",
    "sg:province":"Ciudad Real",
    "sg:website":"www.eptron.es",
    "wof:name":"Eptron Multimedia S.a.",
    "wof:placetype":"venue"
},
  "geometry": {"coordinates":[-3.9358739853,38.9764785767],"type":"Point"}
}