{
  "type": "Feature",
  "properties": {
    "iso:country":"ES",
    "sg:address":"Calle de General Aguilera, 10",
    "sg:city":"Ciudad Real",
    "sg:orig_category":"Deportes Y Ocio: Art\u00cdculos Y Ropas (al Por Menor Y Accesorios)",
    "sg:phone":"+34 926 21 40 45",
    "sg:postcode":"13001",
    "sg:province":"Ciudad Real",
    "wof:name":"Conber Sport S.l.",
    "wof:placetype":"venue"
},
  "geometry": {"coordinates":[-3.9254119396,38.9844894409],"type":"Point"}
}