{
  "type": "Feature",
  "properties": {
    "addr:full":"Av M. Celayeta, 30 Iru\u00f1a Navarra 31014",
    "addr:housenumber":"30",
    "addr:postcode":"31014",
    "addr:street":"Av M. Celayeta",
    "iso:country":"ES",
    "sg:address":"Av M. Celayeta, 30",
    "sg:city":"Iru\u00f1a",
    "sg:orig_category":"Molduras, Junquillos, Listones Y Molduras Perforadas",
    "sg:phone":"+34 948 14 95 13",
    "sg:postcode":"31014",
    "sg:province":"Navarra",
    "wof:name":"Mari\u00f1o Ansin Mikel",
    "wof:placetype":"venue"
},
  "geometry": {"coordinates":[-1.6437540054,42.81275177],"type":"Point"}
}