{
  "type": "Feature",
  "properties": {
    "iso:country":"ES",
    "sg:address":"Calle de Espronceda, S/n",
    "sg:city":"Berja",
    "sg:orig_category":"Delegados, Agentes De Tr\u00c1nsito, Auxiliares De Transporte Internacional",
    "sg:phone":"+34 950 49 02 03",
    "sg:postcode":"04760",
    "sg:province":"Almer\u00eda",
    "wof:name":"Villacreces Cabrera Maria Trinidad",
    "wof:placetype":"venue"
},
  "geometry": {"coordinates":[-2.9440588951,36.8491516113],"type":"Point"}
}