{
  "type": "Feature",
  "properties": {
    "addr:full":"Avda San Jorge, 63 Andorra Teruel 44500",
    "addr:housenumber":"63",
    "addr:postcode":"44500",
    "addr:street":"Avda San Jorge",
    "iso:country":"ES",
    "sg:address":"Avda San Jorge, 63",
    "sg:city":"Andorra",
    "sg:orig_category":"Carnicer\u00cdas, Carnicer\u00cdas",
    "sg:phone":"+34 978 84 32 21",
    "sg:postcode":"44500",
    "sg:province":"Teruel",
    "wof:name":"Peguero Calvo Julian",
    "wof:placetype":"venue"
},
  "geometry": {"coordinates":[-0.444795996,40.9768371582],"type":"Point"}
}