{
  "type": "Feature",
  "properties": {
    "addr:full":"Carrer de Morato, 2 Barcelona Barcelona 08032",
    "addr:housenumber":"2",
    "addr:postcode":"08032",
    "addr:street":"Carrer De Morato",
    "iso:country":"ES",
    "sg:address":"Carrer de Morato, 2",
    "sg:city":"Barcelona",
    "sg:orig_category":"Molduras, Junquillos, Listones Y Molduras Perforadas",
    "sg:phone":"+34 933 58 83 79",
    "sg:postcode":"08032",
    "sg:province":"Barcelona",
    "wof:name":"Vazquez Moreno Vicente",
    "wof:placetype":"venue"
},
  "geometry": {"coordinates":[2.1491310596,41.4216308594],"type":"Point"}
}