{
  "type": "Feature",
  "properties": {
    "iso:country":"ES",
    "sg:address":"Avda Del Pais Valencia, 15",
    "sg:city":"Vinaros",
    "sg:orig_category":"Institutos De Belleza",
    "sg:phone":"+34 964 45 91 92",
    "sg:postcode":"12500",
    "sg:province":"Castell\u00f3n",
    "wof:name":"Instituto Biologico De La Salud S.l.",
    "wof:placetype":"venue"
},
  "geometry": {"coordinates":[0.4736498892,40.4687271118],"type":"Point"}
}