{
  "type": "Feature",
  "properties": {
    "iso:country":"ES",
    "sg:address":"Plaz Gimeno Baron, 12",
    "sg:city":"Ain",
    "sg:orig_category":"Cajas Para Embalar",
    "sg:phone":"+34 964 62 90 95",
    "sg:postcode":"12222",
    "sg:province":"Castell\u00f3n",
    "wof:name":"Caja Rural Del Mediterraneo Ruralcaja S Coop De Credito",
    "wof:placetype":"venue"
},
  "geometry": {"coordinates":[-0.354238987,39.915763855],"type":"Point"}
}