{
  "type": "Feature",
  "properties": {
    "iso:country":"ES",
    "sg:address":"Valle Alcudia, 3",
    "sg:city":"Las Rozas",
    "sg:orig_category":"Equipo De Refrigeraci\u00d3n Industrial",
    "sg:phone":"+34 917 21 91 92",
    "sg:postcode":"28230",
    "sg:province":"Madrid",
    "wof:name":"Lu-ve Contardo Iberica S.l.",
    "wof:placetype":"venue"
},
  "geometry": {"coordinates":[-3.8836681843,40.5178222656],"type":"Point"}
}