{
  "type": "Feature",
  "properties": {
    "iso:country":"ES",
    "sg:address":"Calle de Ruiz Zorrilla, 34",
    "sg:city":"Algeciras",
    "sg:orig_category":"Mec\u00c1nico Del Autom\u00d3vil",
    "sg:phone":"+34 956 66 00 55",
    "sg:postcode":"11203",
    "sg:province":"C\u00e1diz",
    "wof:name":"Michan Paulete Jose Manuel",
    "wof:placetype":"venue"
},
  "geometry": {"coordinates":[-5.4517688751,36.1311416626],"type":"Point"}
}