{
  "type": "Feature",
  "properties": {
    "addr:full":"Calle de Jaen, 8 Madrid Madrid 28020",
    "addr:housenumber":"8",
    "addr:postcode":"madrid;28020",
    "addr:street":"Calle De Jaen",
    "iso:country":"ES",
    "sg:address":"Calle de Jaen, 8",
    "sg:city":"Madrid",
    "sg:orig_category":"Electricidad, Electr\u00d3nica: Suministros (al Por Menor)",
    "sg:phone":"+34 915 33 08 27",
    "sg:postcode":"28020",
    "sg:province":"Madrid",
    "wof:name":"Quesada Garcia Rafael",
    "wof:placetype":"venue"
},
  "geometry": {"coordinates":[-3.702614069,40.4503173828],"type":"Point"}
}