{
  "type": "Feature",
  "properties": {
    "iso:country":"ES",
    "sg:address":"Carr Primavera, 1",
    "sg:city":"Son Moro",
    "sg:orig_category":"M\u00c9dicos: Estomatolog\u00cda",
    "sg:phone":"+34 971 58 69 58",
    "sg:postcode":"07560",
    "sg:province":"Islas Baleares",
    "wof:name":"Romero Borrego Antonio",
    "wof:placetype":"venue"
},
  "geometry": {"coordinates":[3.3733510971,39.5831985474],"type":"Point"}
}