{
  "type": "Feature",
  "properties": {
    "iso:country":"ES",
    "sg:address":"Calle de Bilbao, 2",
    "sg:city":"Almu\u00f1ecar",
    "sg:orig_category":"Plomeros",
    "sg:phone":"+34 958 63 11 71",
    "sg:postcode":"18690",
    "sg:province":"Granada",
    "wof:name":"Ruiz Dominguez Jose",
    "wof:placetype":"venue"
},
  "geometry": {"coordinates":[-3.6889116764,36.7322502136],"type":"Point"}
}