{
  "type": "Feature",
  "properties": {
    "iso:country":"ES",
    "sg:address":"Calle de Salud, 13",
    "sg:city":"Valladolid",
    "sg:orig_category":"Servicios Diversos",
    "sg:phone":"+34 983 30 11 74",
    "sg:postcode":"47012",
    "sg:province":"Valladolid",
    "wof:name":"Velasco Sanz Socorro",
    "wof:placetype":"venue"
},
  "geometry": {"coordinates":[-4.7119588852,41.6482315063],"type":"Point"}
}