{
  "type": "Feature",
  "properties": {
    "addr:full":"Carretera De Oliva De Merida, Km. 0002,0 Villagonzalo Badajoz 06473",
    "addr:postcode":"06473",
    "addr:street":"Carretera De Oliva De Merida Km. 0002,0",
    "iso:country":"ES",
    "sg:address":"Carretera De Oliva De Merida, Km. 0002,0",
    "sg:city":"Villagonzalo",
    "sg:orig_category":"Agricultura: Abastecimiento Y Cosechado (negocio)",
    "sg:phone":"+34 924 36 70 96",
    "sg:postcode":"06473",
    "sg:province":"Badajoz",
    "wof:name":"Cooperativa Del Campo Nuestro Padre Jesus",
    "wof:placetype":"venue"
},
  "geometry": {"coordinates":[-6.2000069618,38.861946106],"type":"Point"}
}