{
  "type": "Feature",
  "properties": {
    "addr:full":"Las Prietas, 2 Montilla C\u00f3rdoba 14550",
    "addr:housenumber":"2",
    "addr:postcode":"14550",
    "addr:street":"Prietas;Co\u0301Rdoba",
    "iso:country":"ES",
    "sg:address":"Las Prietas, 2",
    "sg:city":"Montilla",
    "sg:orig_category":"Promotores Constructores",
    "sg:phone":"+34 957 65 38 44",
    "sg:postcode":"14550",
    "sg:province":"C\u00f3rdoba",
    "wof:name":"Coyremar S.l.",
    "wof:placetype":"venue"
},
  "geometry": {"coordinates":[-4.6378769875,37.5838088989],"type":"Point"}
}