{
  "type": "Feature",
  "properties": {
    "iso:country":"ES",
    "sg:address":"Galicia, 20",
    "sg:city":"Ribeira-santa Uxia",
    "sg:orig_category":"Arquitectos",
    "sg:phone":"+34 981 87 44 60",
    "sg:postcode":"15960",
    "sg:province":"La Coru\u00f1a",
    "wof:name":"Fernandez Sarasquete Jose",
    "wof:placetype":"venue"
},
  "geometry": {"coordinates":[-8.989982605,42.5537452698],"type":"Point"}
}