{
  "type": "Feature",
  "properties": {
    "addr:full":"Rbla Pompeu Fabra, 156 Gava Barcelona 08850",
    "addr:housenumber":"156",
    "addr:postcode":"08850",
    "addr:street":"Rbla Pompeu Fabra",
    "iso:country":"ES",
    "sg:address":"Rbla Pompeu Fabra, 156",
    "sg:city":"Gava",
    "sg:orig_category":"Empresas De Carpinter\u00cda Met\u00c1lica",
    "sg:phone":"+34 936 62 83 74",
    "sg:postcode":"08850",
    "sg:province":"Barcelona",
    "wof:name":"Dominguez Macias Victor",
    "wof:placetype":"venue"
},
  "geometry": {"coordinates":[2.0007519722,41.310585022],"type":"Point"}
}