{
  "type": "Feature",
  "properties": {
    "iso:country":"ES",
    "sg:address":"Calle de Ronda Del Mediodia, 39",
    "sg:city":"Navas Oro",
    "sg:orig_category":"Peluquer\u00cdas, Peluquer\u00cda Mixta",
    "sg:phone":"+34 921 59 12 58",
    "sg:postcode":"40470",
    "sg:province":"Segovia",
    "wof:name":"Pastor Blazquez Raquel",
    "wof:placetype":"venue"
},
  "geometry": {"coordinates":[-4.4349751472,41.1947288513],"type":"Point"}
}