{
  "type": "Feature",
  "properties": {
    "iso:country":"ES",
    "sg:address":"Zigordia Kalea, 22",
    "sg:city":"Zarautz",
    "sg:orig_category":"M\u00c9dicos: Medicina Manual",
    "sg:phone":"+34 943 83 16 55",
    "sg:postcode":"20800",
    "sg:province":"Guip\u00f9zcoa",
    "wof:name":"Aguirre Franco Francisco Javier",
    "wof:placetype":"venue"
},
  "geometry": {"coordinates":[-2.1740810871,43.2848968506],"type":"Point"}
}