{
  "type": "Feature",
  "properties": {
    "iso:country":"ES",
    "sg:address":"Plaz Colegio Del Patriarca, 4",
    "sg:city":"Valencia",
    "sg:orig_category":"Ropa Para Ni\u00d1os (al Por Menor)",
    "sg:phone":"+34 963 50 93 23",
    "sg:postcode":"46002",
    "sg:province":"Valencia",
    "wof:name":"Gutierrez & Ali\u00f1o Asociados S.l.",
    "wof:placetype":"venue"
},
  "geometry": {"coordinates":[-0.3735440075,39.4721069336],"type":"Point"}
}