{
  "type": "Feature",
  "properties": {
    "iso:country":"ES",
    "sg:address":"Calle de Isabel Ii, 9",
    "sg:city":"Parla",
    "sg:orig_category":"Farmacias",
    "sg:phone":"+34 916 99 21 68",
    "sg:postcode":"28980",
    "sg:province":"Madrid",
    "wof:name":"Sendino Perez Alvaro",
    "wof:placetype":"venue"
},
  "geometry": {"coordinates":[-3.765474081,40.2356147766],"type":"Point"}
}