{
  "type": "Feature",
  "properties": {
    "iso:country":"ES",
    "sg:address":"Calle de Mercedes Y Carmen Granizo, 19",
    "sg:city":"Pozuelo De Alarcon",
    "sg:orig_category":"Centros M\u00c9dicos Y Sociales, Dispensarios",
    "sg:phone":"+34 913 52 93 26",
    "sg:postcode":"28224",
    "sg:province":"Madrid",
    "wof:name":"Estrategia Desarrollo Y Diversificacion S.l.",
    "wof:placetype":"venue"
},
  "geometry": {"coordinates":[-3.7938899994,40.4486808777],"type":"Point"}
}