{
  "type": "Feature",
  "properties": {
    "addr:full":"Lomo Incienso (la Polvacera), 100 Bre\u00f1a Baja Santa Cruz De Tenerife 38712",
    "addr:housenumber":"100",
    "addr:postcode":"38712",
    "addr:street":"La Polvacera",
    "iso:country":"ES",
    "sg:address":"Lomo Incienso (la Polvacera), 100",
    "sg:city":"Bre\u00f1a Baja",
    "sg:orig_category":"Fabricaci\u00d3n, Importaci\u00d3n De Material Y Sistemas De Telecomunicaciones",
    "sg:phone":"+34 922 43 47 63",
    "sg:postcode":"38712",
    "sg:province":"Santa Cruz De Tenerife",
    "wof:name":"Telyco La Palma S.l.",
    "wof:placetype":"venue"
},
  "geometry": {"coordinates":[-17.7672138214,28.6476554871],"type":"Point"}
}