{
  "type": "Feature",
  "properties": {
    "iso:country":"ES",
    "sg:address":"Av Guiera, 12",
    "sg:city":"Cerdanyola Valles",
    "sg:orig_category":"Alquiler De V\u00cddeo",
    "sg:phone":"+34 935 80 04 61",
    "sg:postcode":"08290",
    "sg:province":"Barcelona",
    "wof:name":"Guijarro Navarta Encarnacion",
    "wof:placetype":"venue"
},
  "geometry": {"coordinates":[2.1412374973,41.4832878113],"type":"Point"}
}