{
  "type": "Feature",
  "properties": {
    "addr:full":"Calle de Alcalde Rodriguez Prieto, 6 Zona De Los Principes Huelva 21810",
    "addr:housenumber":"6",
    "addr:postcode":"21810",
    "addr:street":"Calle De Alcalde Rodriguez Prieto;Zona De Los Principes",
    "iso:country":"ES",
    "sg:address":"Calle de Alcalde Rodriguez Prieto, 6",
    "sg:city":"Zona De Los Principes",
    "sg:orig_category":"Reposter\u00cdas",
    "sg:phone":"+34 959 35 03 20",
    "sg:postcode":"21810",
    "sg:province":"Huelva",
    "wof:name":"San Roman Palos S.l.",
    "wof:placetype":"venue"
},
  "geometry": {"coordinates":[-6.8923411369,37.2240829468],"type":"Point"}
}