{
  "type": "Feature",
  "properties": {
    "addr:full":"Avda Sevilla (de), 32 Trebujena C\u00e1diz 11560",
    "addr:housenumber":"32",
    "addr:postcode":"11560",
    "addr:street":"Avda Sevilla De;Ca\u0301Diz",
    "iso:country":"ES",
    "sg:address":"Avda Sevilla (de), 32",
    "sg:city":"Trebujena",
    "sg:orig_category":"Mec\u00c1nico Del Autom\u00d3vil",
    "sg:phone":"+34 956 39 50 32",
    "sg:postcode":"11560",
    "sg:province":"C\u00e1diz",
    "wof:name":"Bautista Fernandez Juan Feliz",
    "wof:placetype":"venue"
},
  "geometry": {"coordinates":[-6.1733851433,36.8695106506],"type":"Point"}
}