{
  "type": "Feature",
  "properties": {
    "addr:full":"Calle de Alfonso Ix, 1 Le\u00f3n Le\u00f3n 24004",
    "addr:housenumber":"1",
    "addr:postcode":"24004",
    "addr:street":"Calle De Alfonso Ix;Leo\u0301N",
    "iso:country":"ES",
    "sg:address":"Calle de Alfonso Ix, 1",
    "sg:city":"Le\u00f3n",
    "sg:orig_category":"Psic\u00d3logos",
    "sg:phone":"+34 987 20 83 07",
    "sg:postcode":"24004",
    "sg:province":"Le\u00f3n",
    "sg:website":"www.paginasamarillas.es",
    "wof:name":"Herreras Perez Antidio Enrique",
    "wof:placetype":"venue"
},
  "geometry": {"coordinates":[-5.5753931999,42.5948410034],"type":"Point"}
}