{
  "type": "Feature",
  "properties": {
    "iso:country":"ES",
    "sg:address":"Calle de Juan De Herrera, 70",
    "sg:city":"Le\u00f3n",
    "sg:orig_category":"Pescader\u00cdas (al Por Menor)",
    "sg:phone":"+34 987 25 51 20",
    "sg:postcode":"24006",
    "sg:province":"Le\u00f3n",
    "wof:name":"Maestro Lopez Miguel Angel",
    "wof:placetype":"venue"
},
  "geometry": {"coordinates":[-5.5640587807,42.5924110413],"type":"Point"}
}