{
  "type": "Feature",
  "properties": {
    "iso:country":"ES",
    "sg:address":"Carrer de Sant Pau, 109",
    "sg:city":"Barcelona",
    "sg:orig_category":"Reposter\u00cdas",
    "sg:phone":"+34 934 41 06 13",
    "sg:postcode":"08001",
    "sg:province":"Barcelona",
    "wof:name":"Torres Sole Ramon",
    "wof:placetype":"venue"
},
  "geometry": {"coordinates":[2.168348074,41.3755149841],"type":"Point"}
}