{
  "type": "Feature",
  "properties": {
    "iso:country":"ES",
    "sg:address":"Portalez, 41",
    "sg:city":"Fuente Palmera",
    "sg:orig_category":"\u00c1rboles Frutales",
    "sg:phone":"+34 957 63 83 22",
    "sg:postcode":"14120",
    "sg:province":"C\u00f3rdoba",
    "sg:website":"www.agropalmeras.com",
    "wof:name":"Agropalmeras S.l.",
    "wof:placetype":"venue"
},
  "geometry": {"coordinates":[-5.091106,37.709736],"type":"Point"}
}