{
  "type": "Feature",
  "properties": {
    "addr:full":"Urko Plaza - Plaza Urko, 2 Lasarte Guip\u00f9zcoa 20160",
    "addr:housenumber":"2",
    "addr:postcode":"20160",
    "addr:street":"Urko;Lasarte Guipu\u0300Zcoa",
    "iso:country":"ES",
    "sg:address":"Urko Plaza - Plaza Urko, 2",
    "sg:city":"Lasarte",
    "sg:orig_category":"Masajistas Kinesiterapeutas",
    "sg:phone":"+34 943 36 56 71",
    "sg:postcode":"20160",
    "sg:province":"Guip\u00f9zcoa",
    "wof:name":"Gorostidi Manchado Rakel",
    "wof:placetype":"venue"
},
  "geometry": {"coordinates":[-2.020414114,43.2698173523],"type":"Point"}
}