{
  "type": "Feature",
  "properties": {
    "addr:full":"Calle de Olmo De Teclo, 19 Casasimarro Cuenca 16239",
    "addr:housenumber":"19",
    "addr:postcode":"16239",
    "addr:street":"Calle De Olmo De Teclo",
    "iso:country":"ES",
    "sg:address":"Calle de Olmo De Teclo, 19",
    "sg:city":"Casasimarro",
    "sg:orig_category":"Agencias Y Agentes Comerciales, Representantes",
    "sg:phone":"+34 967 48 72 66",
    "sg:postcode":"16239",
    "sg:province":"Cuenca",
    "wof:name":"Rodriguez Leal Jose Luis",
    "wof:placetype":"venue"
},
  "geometry": {"coordinates":[-2.0348880291,39.3925476074],"type":"Point"}
}