{
  "type": "Feature",
  "properties": {
    "iso:country":"ES",
    "sg:address":"Calle de Toledo, 16",
    "sg:city":"Zaragoza",
    "sg:orig_category":"Promotores Constructores",
    "sg:phone":"+34 976 55 21 25",
    "sg:postcode":"50005",
    "sg:province":"Zaragoza",
    "wof:name":"Promociones Guillermo Y Serrano S.l.",
    "wof:placetype":"venue"
},
  "geometry": {"coordinates":[-0.8964999914,41.6478919983],"type":"Point"}
}