{
  "type": "Feature",
  "properties": {
    "addr:full":"Calle de Miguel Redondo, 43 Huelva Huelva 21003",
    "addr:housenumber":"43",
    "addr:postcode":"21003",
    "addr:street":"Calle De Miguel Redondo",
    "iso:country":"ES",
    "sg:address":"Calle de Miguel Redondo, 43",
    "sg:city":"Huelva",
    "sg:orig_category":"Guarder\u00cdas",
    "sg:phone":"+34 959 24 75 75",
    "sg:postcode":"21003",
    "sg:province":"Huelva",
    "wof:name":"Alcantara Delgado Encarnacion",
    "wof:placetype":"venue"
},
  "geometry": {"coordinates":[-6.9513206482,37.2540092468],"type":"Point"}
}