{
  "type": "Feature",
  "properties": {
    "addr:full":"Calle de Miguel De La Roca, 26 Madrid Madrid 28053",
    "addr:housenumber":"26",
    "addr:postcode":"madrid;28053",
    "addr:street":"Calle De Miguel De La Roca",
    "iso:country":"ES",
    "sg:address":"Calle de Miguel De La Roca, 26",
    "sg:city":"Madrid",
    "sg:orig_category":"Tintes (fabricaci\u00d3n, Al Por Mayor)",
    "sg:phone":"+34 915 07 58 11",
    "sg:postcode":"28053",
    "sg:province":"Madrid",
    "wof:name":"Dominguez Navascues Urbano",
    "wof:placetype":"venue"
},
  "geometry": {"coordinates":[-3.6709179878,40.3824653625],"type":"Point"}
}