{
  "type": "Feature",
  "properties": {
    "iso:country":"ES",
    "sg:address":"Ctra Tomares-san Juan, Km. 0001,0",
    "sg:city":"San J. Aznalfarache",
    "sg:orig_category":"Molduras, Junquillos, Listones Y Molduras Perforadas",
    "sg:phone":"+34 954 76 23 54",
    "sg:postcode":"41920",
    "sg:province":"Sevilla",
    "wof:name":"Sistelcom-telemensaj",
    "wof:placetype":"venue"
},
  "geometry": {"coordinates":[-6.0277690887,37.359916687],"type":"Point"}
}