{
  "type": "Feature",
  "properties": {
    "addr:full":"Sadar, 4 Iru\u00f1a Navarra 31006",
    "addr:housenumber":"4",
    "addr:postcode":"31006",
    "addr:street":"Sadar",
    "iso:country":"ES",
    "sg:address":"Sadar, 4",
    "sg:city":"Iru\u00f1a",
    "sg:orig_category":"Agencias Y Agentes Comerciales, Representantes",
    "sg:phone":"+34 948 23 53 48",
    "sg:postcode":"31006",
    "sg:province":"Navarra",
    "wof:name":"Sainz Saez De Camporedondo Cruz",
    "wof:placetype":"venue"
},
  "geometry": {"coordinates":[-1.6422710419,42.798614502],"type":"Point"}
}