{
  "type": "Feature",
  "properties": {
    "addr:full":"Carr Jose Vidal Canet, De, 97 Carcaixent Valencia 46740",
    "addr:postcode":"46740",
    "addr:street":"Carr Jose Vidal",
    "iso:country":"ES",
    "sg:address":"Carr Jose Vidal Canet, De, 97",
    "sg:city":"Carcaixent",
    "sg:orig_category":"Peluqueros: De Se\u00d1oras",
    "sg:phone":"+34 962 43 17 32",
    "sg:postcode":"46740",
    "sg:province":"Valencia",
    "wof:name":"Hurtado Albentosa Jose Maria",
    "wof:placetype":"venue"
},
  "geometry": {"coordinates":[-0.4437969923,39.1231040955],"type":"Point"}
}