{
  "type": "Feature",
  "properties": {
    "iso:country":"ES",
    "sg:address":"Calle de Ba\u00d1os, 15",
    "sg:city":"Albacete",
    "sg:orig_category":"Carnicer\u00cdas, Carnicer\u00cdas",
    "sg:phone":"+34 967 50 83 28",
    "sg:postcode":"02004",
    "sg:province":"Albacete",
    "wof:name":"Rosa Ortega Juan",
    "wof:placetype":"venue"
},
  "geometry": {"coordinates":[-1.8601845503,38.9955177307],"type":"Point"}
}