{
  "type": "Feature",
  "properties": {
    "iso:country":"ES",
    "sg:address":"Calle de Fernando Giraldez, 51",
    "sg:city":"Madrid",
    "sg:orig_category":"Electricidad: Instaladores",
    "sg:phone":"+34 915 51 13 34",
    "sg:postcode":"28038",
    "sg:province":"Madrid",
    "wof:name":"Buenasma\u00f1anas Guijarro Juan",
    "wof:placetype":"venue"
},
  "geometry": {"coordinates":[-3.6611208916,40.4025726318],"type":"Point"}
}