{
  "type": "Feature",
  "properties": {
    "iso:country":"ES",
    "sg:address":"Pg Lluis Companys, 93",
    "sg:city":"S. Pere Ribes",
    "sg:orig_category":"Molduras, Junquillos, Listones Y Molduras Perforadas",
    "sg:phone":"+34 938 14 64 80",
    "sg:postcode":"08810",
    "sg:province":"Barcelona",
    "wof:name":"Hernandez Navarro Scp",
    "wof:placetype":"venue"
},
  "geometry": {"coordinates":[1.7751940489,41.2604522705],"type":"Point"}
}