{
  "type": "Feature",
  "properties": {
    "iso:country":"ES",
    "sg:address":"Urb Nueva Alberca, S/n",
    "sg:city":"Alberca",
    "sg:orig_category":"Supermercados Y Hipermercados",
    "sg:phone":"+34 968 84 39 53",
    "sg:postcode":"30150",
    "sg:province":"Murcia",
    "sg:website":"www.mercadona.es",
    "wof:name":"Mercadona S.a.",
    "wof:placetype":"venue"
},
  "geometry": {"coordinates":[-1.1332499981,37.9421195984],"type":"Point"}
}