{
  "type": "Feature",
  "properties": {
    "addr:full":"Carr Binimaimut, 1 Poima Islas Baleares 07714",
    "addr:housenumber":"1",
    "addr:postcode":"07714",
    "addr:street":"Carr Binimaimut;Islas",
    "iso:country":"ES",
    "sg:address":"Carr Binimaimut, 1",
    "sg:city":"Poima",
    "sg:orig_category":"Empresas De Carpinter\u00cda De Madera",
    "sg:phone":"+34 971 36 07 75",
    "sg:postcode":"07714",
    "sg:province":"Islas Baleares",
    "wof:name":"Carpinteria J.legaz S.l.",
    "wof:placetype":"venue"
},
  "geometry": {"coordinates":[2.9117100239,39.6136398315],"type":"Point"}
}