{
  "type": "Feature",
  "properties": {
    "addr:full":"C/ Arago, 6 Tarrega Lleida 25300",
    "addr:housenumber":"6",
    "addr:postcode":"25300",
    "addr:street":"C / Arago",
    "iso:country":"ES",
    "sg:address":"C/ Arago, 6",
    "sg:city":"Tarrega",
    "sg:orig_category":"M\u00c1rmoles, Granitos Y Piedras Naturales",
    "sg:phone":"+34 973 31 10 41",
    "sg:postcode":"25300",
    "sg:province":"Lleida",
    "wof:name":"Marbres Gracia S.l.",
    "wof:placetype":"venue"
},
  "geometry": {"coordinates":[1.1450309753,41.647102356],"type":"Point"}
}