{
  "type": "Feature",
  "properties": {
    "addr:full":"Ctra Sagunto-puerto, Km. 0002,0 Puerto Sagunto Valencia 46520",
    "addr:postcode":"46520",
    "addr:street":"Ctra Sagunto-Puerto Km. 0002,0 Puerto",
    "iso:country":"ES",
    "sg:address":"Ctra Sagunto-puerto, Km. 0002,0",
    "sg:city":"Puerto Sagunto",
    "sg:orig_category":"Ropa Para Se\u00d1oras (al Por Menor)",
    "sg:phone":"+34 962 67 48 42",
    "sg:postcode":"46520",
    "sg:province":"Valencia",
    "wof:name":"Decache C.b.",
    "wof:placetype":"venue"
},
  "geometry": {"coordinates":[-0.2025949955,39.7040786743],"type":"Point"}
}