{
  "type": "Feature",
  "properties": {
    "iso:country":"ES",
    "sg:address":"Calle de Nueva De La Trinidad, 3",
    "sg:city":"Almu\u00f1ecar",
    "sg:orig_category":"Electrodom\u00c9sticos (al Por Menor)",
    "sg:phone":"+34 958 63 06 48",
    "sg:postcode":"18690",
    "sg:province":"Granada",
    "wof:name":"Prados Bermudez Francisco",
    "wof:placetype":"venue"
},
  "geometry": {"coordinates":[-3.6915318966,36.734413147],"type":"Point"}
}