{
  "type": "Feature",
  "properties": {
    "addr:full":"Calle de Marques De Toca, 4 Madrid Madrid 28012",
    "addr:housenumber":"4",
    "addr:postcode":"28012",
    "addr:street":"Calle De Marques De Toca",
    "iso:country":"ES",
    "sg:address":"Calle de Marques De Toca, 4",
    "sg:city":"Madrid",
    "sg:orig_category":"Cl\u00cdnicas M\u00c9dicas",
    "sg:phone":"+34 915 27 24 10",
    "sg:postcode":"28012",
    "sg:province":"Madrid",
    "wof:name":"Pastor Ramos Maria Victoria",
    "wof:placetype":"venue"
},
  "geometry": {"coordinates":[-3.6962189674,40.4102287292],"type":"Point"}
}