{
  "type": "Feature",
  "properties": {
    "addr:full":"Ctra Comarcal, Km. 0020,3 S. Celoni Barcelona 08470",
    "addr:postcode":"08470",
    "addr:street":"Ctra Comarcal Km. 0020,3 S. Celoni Barcelona",
    "iso:country":"ES",
    "sg:address":"Ctra Comarcal, Km. 0020,3",
    "sg:city":"S. Celoni",
    "sg:orig_category":"Muebles, Minoristas",
    "sg:phone":"+34 938 67 12 28",
    "sg:postcode":"08470",
    "sg:province":"Barcelona",
    "wof:name":"Supermoble S.l.",
    "wof:placetype":"venue"
},
  "geometry": {"coordinates":[2.463572979,41.7227363586],"type":"Point"}
}