{
  "type": "Feature",
  "properties": {
    "iso:country":"ES",
    "sg:address":"Carr Nadal Meroles, 20",
    "sg:city":"Lleida",
    "sg:orig_category":"Centros Empresariales",
    "sg:phone":"+34 973 23 78 22",
    "sg:postcode":"25008",
    "sg:province":"Lleida",
    "wof:name":"Cercle D'economia De Lleida",
    "wof:placetype":"venue"
},
  "geometry": {"coordinates":[0.6211649776,41.6227226257],"type":"Point"}
}