{
  "type": "Feature",
  "properties": {
    "addr:full":"Calle de Frigiliana, 31 Malaga M\u00e1laga 29003",
    "addr:housenumber":"31",
    "addr:postcode":"29003",
    "addr:street":"Calle De Frigiliana;Ma\u0301Laga",
    "iso:country":"ES",
    "sg:address":"Calle de Frigiliana, 31",
    "sg:city":"Malaga",
    "sg:orig_category":"Venta, Alquiler De Instrumentos Y Accesorios De M\u00dasica",
    "sg:phone":"+34 952 34 27 43",
    "sg:postcode":"29003",
    "sg:province":"M\u00e1laga",
    "sg:website":"www.pianocentro.com",
    "wof:name":"Jakob Kolbe Eberhard Martin",
    "wof:placetype":"venue"
},
  "geometry": {"coordinates":[-4.4443202019,36.6960906982],"type":"Point"}
}