{
  "type": "Feature",
  "properties": {
    "addr:full":"Carrer de Salvador Lluch, 2 Gava Barcelona 08850",
    "addr:housenumber":"2",
    "addr:postcode":"08850",
    "addr:street":"Carrer De Salvador Lluch",
    "iso:country":"ES",
    "sg:address":"Carrer de Salvador Lluch, 2",
    "sg:city":"Gava",
    "sg:orig_category":"Heladeros",
    "sg:phone":"+34 936 62 67 27",
    "sg:postcode":"08850",
    "sg:province":"Barcelona",
    "wof:name":"Gonzalez Roldan Encarnacion",
    "wof:placetype":"venue"
},
  "geometry": {"coordinates":[2.0054409504,41.3052520752],"type":"Point"}
}