{
  "type": "Feature",
  "properties": {
    "addr:full":"Ctra Zaragoza, Km. 0051,0 Calahorra La Rioja 26500",
    "addr:postcode":"26500",
    "addr:street":"Ctra Zaragoza Km. 0051,0",
    "iso:country":"ES",
    "sg:address":"Ctra Zaragoza, Km. 0051,0",
    "sg:city":"Calahorra",
    "sg:orig_category":"Muebles, Minoristas",
    "sg:phone":"+34 941 13 41 05",
    "sg:postcode":"26500",
    "sg:province":"La Rioja",
    "wof:name":"Soret S.a.",
    "wof:placetype":"venue"
},
  "geometry": {"coordinates":[-1.9463210106,42.2885627747],"type":"Point"}
}