{
  "type": "Feature",
  "properties": {
    "addr:full":"Lg Val(chacin), S/n Mazaricos-picota La Coru\u00f1a 15258",
    "addr:housenumber":"s",
    "addr:postcode":"15258",
    "addr:street":"/ N Mazaricos-Picota La Corun\u0303A",
    "iso:country":"ES",
    "sg:address":"Lg Val(chacin), S/n",
    "sg:city":"Mazaricos-picota",
    "sg:orig_category":"Energ\u00cda Solar Y Nuevas Energ\u00cdas (equipo, Estudios)",
    "sg:phone":"+34 981 86 71 05",
    "sg:postcode":"15258",
    "sg:province":"La Coru\u00f1a",
    "wof:name":"Energea Servicios Y Mantenimiento S.l.",
    "wof:placetype":"venue"
},
  "geometry": {"coordinates":[-8.9818820953,42.94140625],"type":"Point"}
}