{
  "type": "Feature",
  "properties": {
    "iso:country":"ES",
    "sg:address":"Calle de Real / Errege Kalea, 42",
    "sg:city":"Noain",
    "sg:orig_category":"Supermercados Y Hipermercados",
    "sg:phone":"+34 948 31 27 70",
    "sg:postcode":"31110",
    "sg:province":"Navarra",
    "sg:website":"www.capraboacasa.com",
    "wof:name":"Caprabo S.a.",
    "wof:placetype":"venue"
},
  "geometry": {"coordinates":[-1.6338239908,42.7598800659],"type":"Point"}
}