{
  "type": "Feature",
  "properties": {
    "iso:country":"ES",
    "sg:address":"Calle de Evaristo Bas, 18",
    "sg:city":"Benimamet-beniferri",
    "sg:orig_category":"Molduras, Junquillos, Listones Y Molduras Perforadas",
    "sg:phone":"+34 963 64 53 88",
    "sg:postcode":"46035",
    "sg:province":"Valencia",
    "wof:name":"Jandula Blanco Manuel",
    "wof:placetype":"venue"
},
  "geometry": {"coordinates":[-0.4189310074,39.5040397644],"type":"Point"}
}