{
  "type": "Feature",
  "properties": {
    "addr:full":"Carrer de Girona, 25 Granollers Barcelona 08402",
    "addr:housenumber":"25",
    "addr:postcode":"08402",
    "addr:street":"Carrer De Girona",
    "iso:country":"ES",
    "sg:address":"Carrer de Girona, 25",
    "sg:city":"Granollers",
    "sg:orig_category":"Doctores En Medicina",
    "sg:phone":"+34 938 70 39 96",
    "sg:postcode":"08402",
    "sg:province":"Barcelona",
    "wof:name":"Conde Gomez Amador",
    "wof:placetype":"venue"
},
  "geometry": {"coordinates":[2.2908110619,41.6106987],"type":"Point"}
}