{
  "type": "Feature",
  "properties": {
    "iso:country":"ES",
    "sg:address":"Carrer de Mares De La Pl. De Maig, 41",
    "sg:city":"Castell-arnau",
    "sg:orig_category":"Inmobiliaria (agencias)",
    "sg:phone":"+34 937 47 85 18",
    "sg:postcode":"08206",
    "sg:province":"Barcelona",
    "wof:name":"Cortes Y Dorado 5 S.l.",
    "wof:placetype":"venue"
},
  "geometry": {"coordinates":[2.0729300976,41.5607566833],"type":"Point"}
}