{
  "type": "Feature",
  "properties": {
    "iso:country":"ES",
    "sg:address":"J. Antonio, 26",
    "sg:city":"Alcuescar",
    "sg:orig_category":"Empresas De Carpinter\u00cda De Madera",
    "sg:phone":"+34 927 38 41 32",
    "sg:postcode":"10160",
    "sg:province":"C\u00e1ceres",
    "wof:name":"Encinas Chamorro Jesus Miguel",
    "wof:placetype":"venue"
},
  "geometry": {"coordinates":[-6.2370839119,39.1815299988],"type":"Point"}
}