{
  "type": "Feature",
  "properties": {
    "iso:country":"ES",
    "sg:address":"Calle de Buenos Aires, 2",
    "sg:city":"Bu\u00f1ol",
    "sg:orig_category":"Mec\u00c1nico Del Autom\u00d3vil",
    "sg:phone":"+34 962 50 21 74",
    "sg:postcode":"46360",
    "sg:province":"Valencia",
    "wof:name":"Lambies Perello Vicente",
    "wof:placetype":"venue"
},
  "geometry": {"coordinates":[-0.791752696,39.4221458435],"type":"Point"}
}