{
  "type": "Feature",
  "properties": {
    "addr:full":"Avda Arrabal, 4 Requena Valencia 46340",
    "addr:housenumber":"4",
    "addr:postcode":"46340",
    "addr:street":"Avda Arrabal",
    "iso:country":"ES",
    "sg:address":"Avda Arrabal, 4",
    "sg:city":"Requena",
    "sg:orig_category":"Empresarios",
    "sg:phone":"+34 962 30 60 54",
    "sg:postcode":"46340",
    "sg:province":"Valencia",
    "wof:name":"Fundacion Forem P.v.",
    "wof:placetype":"venue"
},
  "geometry": {"coordinates":[-1.1006449461,39.4881782532],"type":"Point"}
}