{
  "type": "Feature",
  "properties": {
    "iso:country":"ES",
    "sg:address":"Segados, 31",
    "sg:city":"Roldan",
    "sg:orig_category":"Chapister\u00cda",
    "sg:phone":"+34 968 58 92 40",
    "sg:postcode":"30709",
    "sg:province":"Murcia",
    "sg:website":"www.elguerra.com",
    "wof:name":"Jimenez Egea Pedro Jose",
    "wof:placetype":"venue"
},
  "geometry": {"coordinates":[-1.0039789677,37.8001060486],"type":"Point"}
}