{
  "type": "Feature",
  "properties": {
    "iso:country":"ES",
    "sg:address":"Pg Gracia, 50",
    "sg:city":"Barcelona",
    "sg:orig_category":"Sociedades, Compa\u00d1\u00cdas Aseguradoras",
    "sg:phone":"+34 934 87 31 31",
    "sg:postcode":"08007",
    "sg:province":"Barcelona",
    "wof:name":"Seguros Latina S. A.",
    "wof:placetype":"venue"
},
  "geometry": {"coordinates":[2.1656079292,41.3919906616],"type":"Point"}
}