{
  "type": "Feature",
  "properties": {
    "iso:country":"ES",
    "sg:address":"Calle de Conde De Aranda, 19",
    "sg:city":"Madrid",
    "sg:orig_category":"Compraventa De Antig\u00dcedades",
    "sg:phone":"+34 915 75 48 33",
    "sg:postcode":"28001",
    "sg:province":"Madrid",
    "wof:name":"Mena Gutierrez Paloma",
    "wof:placetype":"venue"
},
  "geometry": {"coordinates":[-3.6856079102,40.4216842651],"type":"Point"}
}