{
  "type": "Feature",
  "properties": {
    "addr:full":"Plaz San Pedro Nolasco, 1 Zaragoza Zaragoza 50001",
    "addr:housenumber":"1",
    "addr:postcode":"50001",
    "addr:street":"Plaz San Pedro Nolasco",
    "iso:country":"ES",
    "sg:address":"Plaz San Pedro Nolasco, 1",
    "sg:city":"Zaragoza",
    "sg:orig_category":"M\u00c9dicos: Estomatolog\u00cda",
    "sg:phone":"+34 976 39 42 01",
    "sg:postcode":"50001",
    "sg:province":"Zaragoza",
    "wof:name":"Valle Bernad Francisco Javier",
    "wof:placetype":"venue"
},
  "geometry": {"coordinates":[-0.8772540092,41.652923584],"type":"Point"}
}