{
  "type": "Feature",
  "properties": {
    "iso:country":"ES",
    "sg:address":"Carrer de Tavern, 33",
    "sg:city":"Barcelona",
    "sg:orig_category":"Institutos De Belleza",
    "sg:phone":"+34 934 14 35 84",
    "sg:postcode":"08006",
    "sg:province":"Barcelona",
    "wof:name":"U\u00f1as Mas Belleza S.l.",
    "wof:placetype":"venue"
},
  "geometry": {"coordinates":[2.1429290771,41.3999633789],"type":"Point"}
}