{
  "type": "Feature",
  "properties": {
    "iso:country":"ES",
    "sg:address":"Calle de San Lorenzo, 35",
    "sg:city":"Oliva Frontera",
    "sg:orig_category":"Cerrajer\u00cda, Ferrallista",
    "sg:phone":"+34 924 75 45 87",
    "sg:postcode":"06120",
    "sg:province":"Badajoz",
    "wof:name":"Garrido Lima Rafael",
    "wof:placetype":"venue"
},
  "geometry": {"coordinates":[-6.9205651283,38.2787742615],"type":"Point"}
}