{
  "type": "Feature",
  "properties": {
    "addr:full":"Calle de Alvarez Taladriz, 2 Valladolid Valladolid 47007",
    "addr:housenumber":"2",
    "addr:postcode":"47007",
    "addr:street":"Calle De Alvarez Taladriz",
    "iso:country":"ES",
    "sg:address":"Calle de Alvarez Taladriz, 2",
    "sg:city":"Valladolid",
    "sg:orig_category":"Asociaciones, Organismos Culturales Y Socioeducativos",
    "sg:phone":"+34 983 22 33 09",
    "sg:postcode":"47007",
    "sg:province":"Valladolid",
    "wof:name":"Casa Regional De Castilla La Mancha",
    "wof:placetype":"venue"
},
  "geometry": {"coordinates":[-4.7384037971,41.6380462646],"type":"Point"}
}