{
  "type": "Feature",
  "properties": {
    "iso:country":"ES",
    "sg:address":"Grup Txibitena Auzunea, 13 B",
    "sg:city":"Durango",
    "sg:orig_category":"Tapiceros Y Tapiceros",
    "sg:phone":"+34 946 03 22 00",
    "sg:postcode":"48200",
    "sg:province":"Vizcaya",
    "wof:name":"Domo Gestion Integral",
    "wof:placetype":"venue"
},
  "geometry": {"coordinates":[-2.6117420197,43.194644928],"type":"Point"}
}