{
  "type": "Feature",
  "properties": {
    "iso:country":"ES",
    "sg:address":"Carrer de Baix, 9",
    "sg:city":"Falset",
    "sg:orig_category":"Cajas De Ahorro",
    "sg:phone":"+34 977 83 02 74",
    "sg:postcode":"43730",
    "sg:province":"Tarragona",
    "wof:name":"Caixa D'estalvis De Catalunya",
    "wof:placetype":"venue"
},
  "geometry": {"coordinates":[0.8202819824,41.1450996399],"type":"Point"}
}