{
  "type": "Feature",
  "properties": {
    "addr:full":"C/ Vila De Bilbao, 15 Paterna Valencia 46988",
    "addr:housenumber":"15",
    "addr:postcode":"46988",
    "addr:street":"C / Vila De Bilbao",
    "iso:country":"ES",
    "sg:address":"C/ Vila De Bilbao, 15",
    "sg:city":"Paterna",
    "sg:orig_category":"Aparcamientos (infraestructuras, Accesorios)",
    "sg:phone":"+34 963 85 05 98",
    "sg:postcode":"46988",
    "sg:province":"Valencia",
    "wof:name":"Patrimonial Urbana S.l.",
    "wof:placetype":"venue"
},
  "geometry": {"coordinates":[-0.4627389908,39.5151405334],"type":"Point"}
}