{
  "type": "Feature",
  "properties": {
    "addr:full":"Carrer de Escudellers, 42 Barcelona Barcelona 08002",
    "addr:housenumber":"42",
    "addr:postcode":"08002",
    "addr:street":"Carrer De Escudellers",
    "iso:country":"ES",
    "sg:address":"Carrer de Escudellers, 42",
    "sg:city":"Barcelona",
    "sg:orig_category":"Platos Preparados Refrigerados (fabricaci\u00d3n, Al Por Mayor)",
    "sg:phone":"+34 933 17 09 33",
    "sg:postcode":"08002",
    "sg:province":"Barcelona",
    "sg:website":"www.dionisos.ws",
    "wof:name":"Patisia S.l.",
    "wof:placetype":"venue"
},
  "geometry": {"coordinates":[2.1772720814,41.3802757263],"type":"Point"}
}