{
  "type": "Feature",
  "properties": {
    "iso:country":"ES",
    "sg:address":"Calle de Fuerte, 2",
    "sg:city":"Alhama Granada",
    "sg:orig_category":"Bazares, Art\u00cdculos De Limpieza Y De Cocina (al Por Menor)",
    "sg:phone":"+34 958 35 00 70",
    "sg:postcode":"18120",
    "sg:province":"Granada",
    "wof:name":"Bazar Molina S.l.",
    "wof:placetype":"venue"
},
  "geometry": {"coordinates":[-3.9895288944,37.0024871826],"type":"Point"}
}