{
  "type": "Feature",
  "properties": {
    "addr:full":"Avda Constitucion, 96 Valencia Valencia 46009",
    "addr:housenumber":"96",
    "addr:postcode":"46009",
    "addr:street":"Avda Constitucion",
    "iso:country":"ES",
    "sg:address":"Avda Constitucion, 96",
    "sg:city":"Valencia",
    "sg:orig_category":"Estancos",
    "sg:phone":"+34 963 65 25 26",
    "sg:postcode":"46009",
    "sg:province":"Valencia",
    "wof:name":"Lluch Agustin Julia Maria",
    "wof:placetype":"venue"
},
  "geometry": {"coordinates":[-0.3762300014,39.4885826111],"type":"Point"}
}