{
  "type": "Feature",
  "properties": {
    "addr:full":"Calle de Juan De Garay, 42 Valencia Valencia 46017",
    "addr:housenumber":"42",
    "addr:postcode":"46017",
    "addr:street":"Calle De Juan De Garay",
    "iso:country":"ES",
    "sg:address":"Calle de Juan De Garay, 42",
    "sg:city":"Valencia",
    "sg:orig_category":"Hoteles",
    "sg:phone":"+34 963 78 23 90",
    "sg:postcode":"46017",
    "sg:province":"Valencia",
    "wof:name":"Meson El Desvan S.l.",
    "wof:placetype":"venue"
},
  "geometry": {"coordinates":[-0.3940440118,39.4545593262],"type":"Point"}
}