{
  "type": "Feature",
  "properties": {
    "iso:country":"ES",
    "sg:address":"Calle de San Vicente, 1",
    "sg:city":"San Vicente De Barakaldo",
    "sg:orig_category":"Tapiceros Y Tapiceros",
    "sg:phone":"+34 944 38 69 45",
    "sg:postcode":"48902",
    "sg:province":"Vizcaya",
    "wof:name":"Pro-plax C.b.",
    "wof:placetype":"venue"
},
  "geometry": {"coordinates":[-2.9946470261,43.2955970764],"type":"Point"}
}