{
  "type": "Feature",
  "properties": {
    "iso:country":"ES",
    "sg:address":"Luis Fabregas, 5",
    "sg:city":"Camallera",
    "sg:orig_category":"Inform\u00c1tica (estudios, Servicios, Asesor\u00cda, Formaci\u00d3n)",
    "sg:phone":"+34 972 79 41 00",
    "sg:postcode":"17465",
    "sg:province":"Girona",
    "sg:website":"www.innoveria.com",
    "wof:name":"Castello Jordana Javier",
    "wof:placetype":"venue"
},
  "geometry": {"coordinates":[2.9636991024,42.1225204468],"type":"Point"}
}