{
  "type": "Feature",
  "properties": {
    "addr:full":"Calle de Bailen, 9 Portugalete Vizcaya 48920",
    "addr:housenumber":"9",
    "addr:postcode":"48920",
    "addr:street":"Calle De Bailen",
    "iso:country":"ES",
    "sg:address":"Calle de Bailen, 9",
    "sg:city":"Portugalete",
    "sg:orig_category":"Librer\u00cdas",
    "sg:phone":"+34 944 95 42 84",
    "sg:postcode":"48920",
    "sg:province":"Vizcaya",
    "wof:name":"Pazos Segade Jesusa",
    "wof:placetype":"venue"
},
  "geometry": {"coordinates":[-3.0186247826,43.3189125061],"type":"Point"}
}