{
  "type": "Feature",
  "properties": {
    "addr:full":"Calle de Doctor Pedro Velez, 11 Chiclana De La Frontera C\u00e1diz 11130",
    "addr:housenumber":"11",
    "addr:postcode":"11130",
    "addr:street":"Calle De Doctor Pedro Velez",
    "iso:country":"ES",
    "sg:address":"Calle de Doctor Pedro Velez, 11",
    "sg:city":"Chiclana De La Frontera",
    "sg:orig_category":"Colchones (fabricaci\u00d3n, Al Por Mayor, Al Por Menor)",
    "sg:phone":"+34 956 53 52 63",
    "sg:postcode":"11130",
    "sg:province":"C\u00e1diz",
    "wof:name":"Centro De Descanso Hercules S.l.l.",
    "wof:placetype":"venue"
},
  "geometry": {"coordinates":[-6.1533818245,36.4186706543],"type":"Point"}
}