{
  "type": "Feature",
  "properties": {
    "addr:full":"Calle de Mariano Fernandez, 44 Campo Criptana Ciudad Real 13610",
    "addr:housenumber":"44",
    "addr:postcode":"13610",
    "addr:street":"Calle De Mariano Fernandez;Criptana",
    "iso:country":"ES",
    "sg:address":"Calle de Mariano Fernandez, 44",
    "sg:city":"Campo Criptana",
    "sg:orig_category":"Transportes En Cisternas",
    "sg:phone":"+34 926 56 12 17",
    "sg:postcode":"13610",
    "sg:province":"Ciudad Real",
    "wof:name":"Quintanar Sanchez-guijaldo Juan Jose",
    "wof:placetype":"venue"
},
  "geometry": {"coordinates":[-3.1251690388,39.4003410339],"type":"Point"}
}