{
  "type": "Feature",
  "properties": {
    "addr:full":"Rbla A\u00d1aza (de), S/n A\u00d1aza Santa Cruz De Tenerife 38111",
    "addr:postcode":"38111",
    "addr:street":"Rbla An\u0303Aza De S / N An\u0303Aza",
    "iso:country":"ES",
    "sg:address":"Rbla A\u00d1aza (de), S/n",
    "sg:city":"A\u00d1aza",
    "sg:orig_category":"Administradores De Bienes Y Delegados De Comunidades De Propietarios",
    "sg:phone":"+34 922 68 58 51",
    "sg:postcode":"38111",
    "sg:province":"Santa Cruz De Tenerife",
    "sg:website":"www.comunidadestenerife.com",
    "wof:name":"Comunidades Tenerife S.l.",
    "wof:placetype":"venue"
},
  "geometry": {"coordinates":[-16.3035106659,28.4221992493],"type":"Point"}
}