{
  "type": "Feature",
  "properties": {
    "addr:full":"Rua Telleira, 9 Ourense Ourense 32004",
    "addr:housenumber":"9",
    "addr:postcode":"32004",
    "addr:street":"Rua Telleira",
    "iso:country":"ES",
    "sg:address":"Rua Telleira, 9",
    "sg:city":"Ourense",
    "sg:orig_category":"Agencias Y Agentes Comerciales, Representantes",
    "sg:phone":"+34 988 22 82 70",
    "sg:postcode":"32004",
    "sg:province":"Ourense",
    "wof:name":"Dasilva Rodriguez Nieves",
    "wof:placetype":"venue"
},
  "geometry": {"coordinates":[-7.8544368744,42.3438148499],"type":"Point"}
}