{
  "type": "Feature",
  "properties": {
    "addr:full":"Calle de Valencia, S/n Yecla Murcia 30510",
    "addr:housenumber":"s / n",
    "addr:postcode":"30510",
    "addr:street":"Calle De Valencia",
    "iso:country":"ES",
    "sg:address":"Calle de Valencia, S/n",
    "sg:city":"Yecla",
    "sg:orig_category":"Tapicer\u00cdas",
    "sg:phone":"+34 968 71 82 77",
    "sg:postcode":"30510",
    "sg:province":"Murcia",
    "wof:name":"Akane Internacional Muebles Y Tapizados S.l.",
    "wof:placetype":"venue"
},
  "geometry": {"coordinates":[-1.1103210449,38.6174201965],"type":"Point"}
}