{
  "type": "Feature",
  "properties": {
    "addr:full":"Ptda Serra Del Cavall, S/n Petrer Alicante 03610",
    "addr:housenumber":"s / n",
    "addr:postcode":"03610",
    "addr:street":"Ptda Serra Del Cavall",
    "iso:country":"ES",
    "sg:address":"Ptda Serra Del Cavall, S/n",
    "sg:city":"Petrer",
    "sg:orig_category":"Asilos De Ancianos. Centros Privados",
    "sg:phone":"+34 966 95 61 61",
    "sg:postcode":"03610",
    "sg:province":"Alicante",
    "wof:name":"Asociacion Pro Residencia De Mayores La Molineta",
    "wof:placetype":"venue"
},
  "geometry": {"coordinates":[-0.7342733741,38.5037231445],"type":"Point"}
}