{
  "type": "Feature",
  "properties": {
    "addr:full":"Calle de Ejercito Espa\u00d1ol, 10 Candeleda \u00c1vila 05480",
    "addr:housenumber":"10",
    "addr:postcode":"05480",
    "addr:street":"Calle De Ejercito Espan\u0303Ol",
    "iso:country":"ES",
    "sg:address":"Calle de Ejercito Espa\u00d1ol, 10",
    "sg:city":"Candeleda",
    "sg:orig_category":"Papeler\u00cdas, Librer\u00cdas",
    "sg:phone":"+34 920 38 09 35",
    "sg:postcode":"05480",
    "sg:province":"\u00c1vila",
    "wof:name":"Jimenez Grande Juan Carlos",
    "wof:placetype":"venue"
},
  "geometry": {"coordinates":[-5.2416911125,40.1569786072],"type":"Point"}
}