{
  "type": "Feature",
  "properties": {
    "addr:full":"Gijun, 12 La Carrera Asturias 33187",
    "addr:housenumber":"12",
    "addr:postcode":"33187",
    "addr:street":"Gijun",
    "iso:country":"ES",
    "sg:address":"Gijun, 12",
    "sg:city":"La Carrera",
    "sg:orig_category":"Producci\u00d3n De Cart\u00d3n",
    "sg:phone":"+34 985 74 26 26",
    "sg:postcode":"33187",
    "sg:province":"Asturias",
    "sg:website":"www.reichkrause.com",
    "wof:name":"Norcar S. A.",
    "wof:placetype":"venue"
},
  "geometry": {"coordinates":[-5.7102842331,43.3833198547],"type":"Point"}
}