{
  "type": "Feature",
  "properties": {
    "addr:full":"Carr Simancas, 62 Badalona Barcelona 08918",
    "addr:housenumber":"62",
    "addr:postcode":"08918",
    "addr:street":"Carr Simancas",
    "iso:country":"ES",
    "sg:address":"Carr Simancas, 62",
    "sg:city":"Badalona",
    "sg:orig_category":"Carnicer\u00cdas, Carnicer\u00cdas",
    "sg:phone":"+34 933 88 05 99",
    "sg:postcode":"08918",
    "sg:province":"Barcelona",
    "wof:name":"Del Barco Ba\u00f1os Jose",
    "wof:placetype":"venue"
},
  "geometry": {"coordinates":[2.2216210365,41.43334198],"type":"Point"}
}