{
  "type": "Feature",
  "properties": {
    "addr:full":"Ctra. Madrid-irun, 19 Burgos Burgos 09001",
    "addr:housenumber":"19",
    "addr:postcode":"09001",
    "addr:street":"Ctra. Madrid-Irun",
    "iso:country":"ES",
    "sg:address":"Ctra. Madrid-irun, 19",
    "sg:city":"Burgos",
    "sg:orig_category":"Suministros Para Hoteles",
    "sg:phone":"+34 947 20 08 02",
    "sg:postcode":"09001",
    "sg:province":"Burgos",
    "wof:name":"Lusamir S.l.",
    "wof:placetype":"venue"
},
  "geometry": {"coordinates":[-3.7021090984,42.3170166016],"type":"Point"}
}