{
  "type": "Feature",
  "properties": {
    "addr:full":"Plaz Provincia, 1 Linares Ja\u00e9n 23700",
    "addr:housenumber":"1",
    "addr:postcode":"23700",
    "addr:street":"Provincia;Jae\u0301N",
    "iso:country":"ES",
    "sg:address":"Plaz Provincia, 1",
    "sg:city":"Linares",
    "sg:orig_category":"Estancos",
    "sg:phone":"+34 953 69 68 37",
    "sg:postcode":"23700",
    "sg:province":"Ja\u00e9n",
    "wof:name":"Lozano Aranda Josefa",
    "wof:placetype":"venue"
},
  "geometry": {"coordinates":[-3.6420478821,38.1125907898],"type":"Point"}
}