{
  "type": "Feature",
  "properties": {
    "iso:country":"ES",
    "sg:address":"Calle de Antonio De La Barrera, 3",
    "sg:city":"Priego Cordoba",
    "sg:orig_category":"Empresas De Limpieza",
    "sg:phone":"+34 957 70 18 20",
    "sg:postcode":"14800",
    "sg:province":"C\u00f3rdoba",
    "wof:name":"Limpieza Pimentel S.l.",
    "wof:placetype":"venue"
},
  "geometry": {"coordinates":[-4.1958050728,37.4379844666],"type":"Point"}
}