{
  "type": "Feature",
  "properties": {
    "iso:country":"ES",
    "sg:address":"Calle de Arquitecto Morell, 11",
    "sg:city":"Alacant",
    "sg:orig_category":"Abogados",
    "sg:phone":"+34 965 12 42 77",
    "sg:postcode":"03003",
    "sg:province":"Alicante",
    "wof:name":"Lumbreras Pelaez Ricardo",
    "wof:placetype":"venue"
},
  "geometry": {"coordinates":[-0.4928340912,38.341960907],"type":"Point"}
}