{
  "type": "Feature",
  "properties": {
    "iso:country":"ES",
    "sg:address":"Marruecos(trema\u00f1es), S/n",
    "sg:city":"Gijon",
    "sg:orig_category":"Asociaciones, Organismos Culturales Y Socioeducativos",
    "sg:phone":"+34 985 31 33 66",
    "sg:postcode":"33211",
    "sg:province":"Asturias",
    "wof:name":"Asociacion De Vecinos Evaristo Valle",
    "wof:placetype":"venue"
},
  "geometry": {"coordinates":[-5.6852426529,43.5228233337],"type":"Point"}
}