{
  "type": "Feature",
  "properties": {
    "iso:country":"ES",
    "sg:address":"Calle de Damas, 8",
    "sg:city":"Jaraiz Vera",
    "sg:orig_category":"Ropa Para Se\u00d1oras Y Caballeros (al Por Menor)",
    "sg:phone":"+34 927 46 05 54",
    "sg:postcode":"10400",
    "sg:province":"C\u00e1ceres",
    "wof:name":"Tovar Serradilla Agustin",
    "wof:placetype":"venue"
},
  "geometry": {"coordinates":[-5.7547488213,40.0598106384],"type":"Point"}
}