{
  "type": "Feature",
  "properties": {
    "iso:country":"ES",
    "sg:address":"Plaz San Nicolas, 4",
    "sg:city":"Valladolid",
    "sg:orig_category":"Fabricaci\u00d3n De Muebles",
    "sg:phone":"+34 983 33 46 40",
    "sg:postcode":"47003",
    "sg:province":"Valladolid",
    "wof:name":"Sistemas Buk S. A.",
    "wof:placetype":"venue"
},
  "geometry": {"coordinates":[-4.7312641144,41.6590118408],"type":"Point"}
}