{
  "type": "Feature",
  "properties": {
    "addr:full":"Calle de Luis De Morales, 1 Sevilla Sevilla 41005",
    "addr:housenumber":"1",
    "addr:postcode":"41005",
    "addr:street":"Calle De Luis De Morales",
    "iso:country":"ES",
    "sg:address":"Calle de Luis De Morales, 1",
    "sg:city":"Sevilla",
    "sg:orig_category":"Sociedades, Compa\u00d1\u00cdas Aseguradoras",
    "sg:phone":"+34 954 57 08 34",
    "sg:postcode":"41005",
    "sg:province":"Sevilla",
    "wof:name":"Asociacion De Peritos De Seguros Y Comisarios De Averias",
    "wof:placetype":"venue"
},
  "geometry": {"coordinates":[-5.9724969864,37.3857040405],"type":"Point"}
}