{
  "type": "Feature",
  "properties": {
    "addr:full":"Calle de General Mola, 33 Guitiriz Lugo 27300",
    "addr:housenumber":"33",
    "addr:postcode":"27300",
    "addr:street":"Calle De General Mola",
    "iso:country":"ES",
    "sg:address":"Calle de General Mola, 33",
    "sg:city":"Guitiriz",
    "sg:orig_category":"Frutas, Legumbres Frescas Y Tempranas (al Por Menor)",
    "sg:phone":"+34 982 37 03 63",
    "sg:postcode":"27300",
    "sg:province":"Lugo",
    "wof:name":"Prado Alamancos Carlos",
    "wof:placetype":"venue"
},
  "geometry": {"coordinates":[-7.8988189697,43.1811637878],"type":"Point"}
}