{
  "type": "Feature",
  "properties": {
    "iso:country":"ES",
    "sg:address":"Bloc Montsant, 13",
    "sg:city":"Sant Pere I Sant Pau",
    "sg:orig_category":"Inform\u00c1tica, Ofim\u00c1tica (estudios, Asesor\u00cda, Ingenier\u00cda, Formaci\u00d3n)",
    "sg:phone":"+34 977 20 37 11",
    "sg:postcode":"43007",
    "sg:province":"Tarragona",
    "wof:name":"Manirent Serveis Sl",
    "wof:placetype":"venue"
},
  "geometry": {"coordinates":[1.2959779501,41.1377334595],"type":"Point"}
}