{
  "type": "Feature",
  "properties": {
    "addr:full":"Pl Verge De L'esperan\u00c7a, 2 Canonja Tarragona 43110",
    "addr:housenumber":"2",
    "addr:postcode":"43110",
    "addr:street":"\u0327A",
    "iso:country":"ES",
    "sg:address":"Pl Verge De L'esperan\u00c7a, 2",
    "sg:city":"Canonja",
    "sg:orig_category":"Venta De Caravanas, Casas M\u00d3viles, Camping",
    "sg:phone":"+34 977 54 62 94",
    "sg:postcode":"43110",
    "sg:province":"Tarragona",
    "wof:name":"Rion Llop Francesc",
    "wof:placetype":"venue"
},
  "geometry": {"coordinates":[1.2583609819,41.1172599792],"type":"Point"}
}