{
  "type": "Feature",
  "properties": {
    "addr:full":"Carrer de Casals I Cubero, 238 Barcelona Barcelona 08042",
    "addr:housenumber":"238",
    "addr:postcode":"08042",
    "addr:street":"Carrer De Casals I Cubero",
    "iso:country":"ES",
    "sg:address":"Carrer de Casals I Cubero, 238",
    "sg:city":"Barcelona",
    "sg:orig_category":"Postigos, Persianas Y Celos\u00cdas",
    "sg:phone":"+34 933 50 70 18",
    "sg:postcode":"08042",
    "sg:province":"Barcelona",
    "wof:name":"Barre\u00f1a Vicente Felix",
    "wof:placetype":"venue"
},
  "geometry": {"coordinates":[2.1761140823,41.4417381287],"type":"Point"}
}