{
  "type": "Feature",
  "properties": {
    "iso:country":"ES",
    "sg:address":"Calle de Oria Kalea, 14",
    "sg:city":"Tolosa",
    "sg:orig_category":"Alimentaci\u00d3n General (al Por Menor)",
    "sg:phone":"+34 943 65 20 40",
    "sg:postcode":"20400",
    "sg:province":"Guip\u00f9zcoa",
    "wof:name":"Marichalar Jauregui Arantza",
    "wof:placetype":"venue"
},
  "geometry": {"coordinates":[-2.0789339542,43.1339912415],"type":"Point"}
}