{
  "type": "Feature",
  "properties": {
    "addr:full":"Carrer de Valencia, 606 Barcelona Barcelona 08026",
    "addr:housenumber":"606",
    "addr:postcode":"08026",
    "addr:street":"Carrer De Valencia",
    "iso:country":"ES",
    "sg:address":"Carrer de Valencia, 606",
    "sg:city":"Barcelona",
    "sg:orig_category":"Muebles, Minoristas",
    "sg:phone":"+34 932 32 24 02",
    "sg:postcode":"08026",
    "sg:province":"Barcelona",
    "sg:website":"www.comcordia-muebles.com",
    "wof:name":"Chung  Francisco",
    "wof:placetype":"venue"
},
  "geometry": {"coordinates":[2.1857070923,41.4093017578],"type":"Point"}
}