{
  "type": "Feature",
  "properties": {
    "addr:full":"Calle de Calvo Sotelo, 110 Marin Pontevedra 36900",
    "addr:housenumber":"110",
    "addr:postcode":"36900",
    "addr:street":"Calle De Calvo Sotelo",
    "iso:country":"ES",
    "sg:address":"Calle de Calvo Sotelo, 110",
    "sg:city":"Marin",
    "sg:orig_category":"M\u00c9dicos: Medicina Interna",
    "sg:phone":"+34 986 88 48 20",
    "sg:postcode":"36900",
    "sg:province":"Pontevedra",
    "wof:name":"Nazara Otero Carlos Alberto",
    "wof:placetype":"venue"
},
  "geometry": {"coordinates":[-8.6922874451,42.3951377869],"type":"Point"}
}