{
  "type": "Feature",
  "properties": {
    "iso:country":"ES",
    "sg:address":"A (pol Talluntxe), 8",
    "sg:city":"Noain",
    "sg:orig_category":"Materias Pl\u00c1sticas: Productos De Consumo Masivo (fabricaci\u00d3n, Al Por Mayor)",
    "sg:phone":"+34 948 31 76 95",
    "sg:postcode":"31110",
    "sg:province":"Navarra",
    "wof:name":"Aikel Manufacturas Plasticas S.l.",
    "wof:placetype":"venue"
},
  "geometry": {"coordinates":[-1.5935460329,42.7209968567],"type":"Point"}
}