{
  "type": "Feature",
  "properties": {
    "iso:country":"ES",
    "sg:address":"Calle de Pintor Fortuny, 1",
    "sg:city":"Peligros",
    "sg:orig_category":"Contenedores (mercanc\u00cdas)",
    "sg:phone":"+34 958 40 04 50",
    "sg:postcode":"18210",
    "sg:province":"Granada",
    "wof:name":"Zarza Moreno Eleuterio",
    "wof:placetype":"venue"
},
  "geometry": {"coordinates":[-3.6290955544,37.2343177795],"type":"Point"}
}