{
  "type": "Feature",
  "properties": {
    "addr:full":"Calle de Juan Alvarez Mendizabal, 50 Madrid Madrid 28008",
    "addr:housenumber":"50",
    "addr:postcode":"madrid;28008",
    "addr:street":"Calle De Juan Alvarez Mendizabal",
    "iso:country":"ES",
    "sg:address":"Calle de Juan Alvarez Mendizabal, 50",
    "sg:city":"Madrid",
    "sg:orig_category":"Institutos De Belleza",
    "sg:phone":"+34 915 41 41 21",
    "sg:postcode":"28008",
    "sg:province":"Madrid",
    "wof:name":"Alambique S.c.",
    "wof:placetype":"venue"
},
  "geometry": {"coordinates":[-3.71743536,40.4275741577],"type":"Point"}
}