{
  "type": "Feature",
  "properties": {
    "addr:full":"Calle de Azanuy, 9 Binefar Huesca 22500",
    "addr:housenumber":"9",
    "addr:postcode":"22500",
    "addr:street":"Calle De Azanuy",
    "iso:country":"ES",
    "sg:address":"Calle de Azanuy, 9",
    "sg:city":"Binefar",
    "sg:orig_category":"T\u00c9cnicos Veterinarios",
    "sg:phone":"+34 974 42 97 12",
    "sg:postcode":"22500",
    "sg:province":"Huesca",
    "wof:name":"Centro De Servicios Veterinarios Osca S.l.",
    "wof:placetype":"venue"
},
  "geometry": {"coordinates":[0.2917456925,41.8502807617],"type":"Point"}
}