{
  "type": "Feature",
  "properties": {
    "iso:country":"ES",
    "sg:address":"Calle de Piscinas (las), 10",
    "sg:city":"Cuellar",
    "sg:orig_category":"Venta, Instalaci\u00d3n De Calefacci\u00d3n",
    "sg:phone":"+34 921 14 00 65",
    "sg:postcode":"40200",
    "sg:province":"Segovia",
    "wof:name":"Calefaccion Y Fontaneria Vela S.l.",
    "wof:placetype":"venue"
},
  "geometry": {"coordinates":[-4.3107190132,41.3946647644],"type":"Point"}
}