{
  "type": "Feature",
  "properties": {
    "iso:country":"ES",
    "sg:address":"Calle de Monte Carmelo, 30",
    "sg:city":"Valencia",
    "sg:orig_category":"Molduras, Junquillos, Listones Y Molduras Perforadas",
    "sg:phone":"+34 963 68 06 35",
    "sg:postcode":"46019",
    "sg:province":"Valencia",
    "wof:name":"Tanaka Egawa Kazuo",
    "wof:placetype":"venue"
},
  "geometry": {"coordinates":[-0.3748269975,39.4977836609],"type":"Point"}
}