{
  "type": "Feature",
  "properties": {
    "addr:full":"La Vi\u00f1a, S/n San Pablo De Buceite C\u00e1diz 11320",
    "addr:housenumber":"/ n",
    "addr:postcode":"11320",
    "addr:street":"Vin\u0303A S;Ca\u0301Diz",
    "iso:country":"ES",
    "sg:address":"La Vi\u00f1a, S/n",
    "sg:city":"San Pablo De Buceite",
    "sg:orig_category":"Promotores Constructores",
    "sg:phone":"+34 956 64 22 56",
    "sg:postcode":"11320",
    "sg:province":"C\u00e1diz",
    "wof:name":"Laja Alta S.l.",
    "wof:placetype":"venue"
},
  "geometry": {"coordinates":[-5.4091949463,36.4669303894],"type":"Point"}
}