{
  "type": "Feature",
  "properties": {
    "addr:full":"Carr Torroella, 2 Cervia Ter Girona 17464",
    "addr:housenumber":"2",
    "addr:postcode":"17464",
    "addr:street":"Carr Torroella;Ter",
    "iso:country":"ES",
    "sg:address":"Carr Torroella, 2",
    "sg:city":"Cervia Ter",
    "sg:orig_category":"Explotaci\u00d3n De Bosques",
    "sg:phone":"+34 972 49 60 18",
    "sg:postcode":"17464",
    "sg:province":"Girona",
    "wof:name":"Farres Marisch Joaquin",
    "wof:placetype":"venue"
},
  "geometry": {"coordinates":[2.9534270763,42.0719909668],"type":"Point"}
}