{
  "type": "Feature",
  "properties": {
    "addr:full":"Calle de San Isidro, 8 Tafalla Navarra 31300",
    "addr:housenumber":"8",
    "addr:postcode":"31300",
    "addr:street":"Calle De San Isidro",
    "iso:country":"ES",
    "sg:address":"Calle de San Isidro, 8",
    "sg:city":"Tafalla",
    "sg:orig_category":"Ingenier\u00cda, Centros De Estudios (diversos)",
    "sg:phone":"+34 948 70 34 52",
    "sg:postcode":"31300",
    "sg:province":"Navarra",
    "wof:name":"Arquitrabe Compa\u00f1ia De Ingenieria S.l.l.",
    "wof:placetype":"venue"
},
  "geometry": {"coordinates":[-1.6782437563,42.5258178711],"type":"Point"}
}