{
  "type": "Feature",
  "properties": {
    "addr:full":"Pla\u00c7 Valldecabres, 22 Quart Poblet Valencia 46930",
    "addr:housenumber":"22",
    "addr:postcode":"46930",
    "addr:street":"Valldecabres;Poblet",
    "iso:country":"ES",
    "sg:address":"Pla\u00c7 Valldecabres, 22",
    "sg:city":"Quart Poblet",
    "sg:orig_category":"Cajas De Ahorro",
    "sg:phone":"+34 961 52 31 56",
    "sg:postcode":"46930",
    "sg:province":"Valencia",
    "sg:website":"www.lacaixa.es",
    "wof:name":"Caixa D'estalvis I Pensions De Barcelona",
    "wof:placetype":"venue"
},
  "geometry": {"coordinates":[-0.4419890046,39.482711792],"type":"Point"}
}