{
  "type": "Feature",
  "properties": {
    "iso:country":"ES",
    "sg:address":"Pg Maragall, 145",
    "sg:city":"Barcelona",
    "sg:orig_category":"Molduras, Junquillos, Listones Y Molduras Perforadas",
    "sg:phone":"+34 934 08 24 27",
    "sg:postcode":"08041",
    "sg:province":"Barcelona",
    "wof:name":"Paradela Do Nascimento Isildo",
    "wof:placetype":"venue"
},
  "geometry": {"coordinates":[2.1796441078,41.4215164185],"type":"Point"}
}