{
  "type": "Feature",
  "properties": {
    "iso:country":"ES",
    "sg:address":"Calle de Sese\u00d1a, 68",
    "sg:city":"Madrid",
    "sg:orig_category":"Caf\u00c9s, Bares, Cervecer\u00cdas",
    "sg:phone":"+34 915 18 59 50",
    "sg:postcode":"28024",
    "sg:province":"Madrid",
    "wof:name":"Gonzalez Martin Lucio",
    "wof:placetype":"venue"
},
  "geometry": {"coordinates":[-3.7677280903,40.3961448669],"type":"Point"}
}