{
  "type": "Feature",
  "properties": {
    "iso:country":"ES",
    "sg:address":"Urb Torre Del Moro, S/n",
    "sg:city":"Torrelamata",
    "sg:orig_category":"Organizaci\u00d3n De Actos, Seminarios Y Congresos",
    "sg:phone":"+34 966 92 21 40",
    "sg:postcode":"03188",
    "sg:province":"Alicante",
    "wof:name":"Salaret Ferrer S.l.",
    "wof:placetype":"venue"
},
  "geometry": {"coordinates":[-0.6579220295,38.0312385559],"type":"Point"}
}