{
  "type": "Feature",
  "properties": {
    "iso:country":"ES",
    "sg:address":"Avda Pio Xii, S/n",
    "sg:city":"Salteras",
    "sg:orig_category":"Mec\u00c1nico Del Autom\u00d3vil",
    "sg:phone":"+34 955 70 72 16",
    "sg:postcode":"41909",
    "sg:province":"Sevilla",
    "wof:name":"Garcia Garrote Manuel",
    "wof:placetype":"venue"
},
  "geometry": {"coordinates":[-6.1125559807,37.4220504761],"type":"Point"}
}