{
  "type": "Feature",
  "properties": {
    "iso:country":"ES",
    "sg:address":"Calle de Alfonso Xiii, 2",
    "sg:city":"Callosa Segura",
    "sg:orig_category":"Muebles, Minoristas",
    "sg:phone":"+34 965 31 15 76",
    "sg:postcode":"03360",
    "sg:province":"Alicante",
    "wof:name":"Mora Sig\u00fcenza Maria Dolores",
    "wof:placetype":"venue"
},
  "geometry": {"coordinates":[-0.8850083947,38.1155357361],"type":"Point"}
}