{
  "type": "Feature",
  "properties": {
    "addr:full":"Carrer de Joan Maragall, 45 Calella Barcelona 08370",
    "addr:housenumber":"45",
    "addr:postcode":"08370",
    "addr:street":"Carrer De Joan Maragall",
    "iso:country":"ES",
    "sg:address":"Carrer de Joan Maragall, 45",
    "sg:city":"Calella",
    "sg:orig_category":"Asociaciones Y Clubs Deportivos",
    "sg:phone":"+34 937 66 17 00",
    "sg:postcode":"08370",
    "sg:province":"Barcelona",
    "wof:name":"Zona Deportivo Recreativa Concorde S. A.",
    "wof:placetype":"venue"
},
  "geometry": {"coordinates":[2.6505393982,41.6132545471],"type":"Point"}
}