{
  "type": "Feature",
  "properties": {
    "iso:country":"ES",
    "sg:address":"Ctra Catral, Km. 0003,2",
    "sg:city":"San Jose",
    "sg:orig_category":"Muebles, Minoristas",
    "sg:phone":"+34 966 75 67 92",
    "sg:postcode":"03360",
    "sg:province":"Alicante",
    "wof:name":"Asmobel S.l.",
    "wof:placetype":"venue"
},
  "geometry": {"coordinates":[-0.872558713,38.1240730286],"type":"Point"}
}