{
  "type": "Feature",
  "properties": {
    "iso:country":"ES",
    "sg:address":"Avda San Blas, 6",
    "sg:city":"Legutiano",
    "sg:orig_category":"Metalurgia",
    "sg:phone":"+34 945 46 60 32",
    "sg:postcode":"01170",
    "sg:province":"\u00c1lava",
    "sg:website":"trefusa.com",
    "wof:name":"Trefilados De Urbina S. A.",
    "wof:placetype":"venue"
},
  "geometry": {"coordinates":[-2.678935051,42.9762420654],"type":"Point"}
}