{
  "type": "Feature",
  "properties": {
    "addr:full":"Linar De La Torre, S/n Cerredo Asturias 33812",
    "addr:housenumber":"s / n",
    "addr:postcode":"33812",
    "addr:street":"Torre",
    "iso:country":"ES",
    "sg:address":"Linar De La Torre, S/n",
    "sg:city":"Cerredo",
    "sg:orig_category":"Electrodom\u00c9sticos (al Por Menor)",
    "sg:phone":"+34 985 81 83 81",
    "sg:postcode":"33812",
    "sg:province":"Asturias",
    "wof:name":"Manuel Y Fernandez S. L.",
    "wof:placetype":"venue"
},
  "geometry": {"coordinates":[-6.5779118538,42.94165802],"type":"Point"}
}