{
  "type": "Feature",
  "properties": {
    "addr:full":"Carr Joan Peset, (de), 65 Carlet Valencia 46240",
    "addr:housenumber":"65",
    "addr:postcode":"46240",
    "addr:street":"Carr Joan Peset De",
    "iso:country":"ES",
    "sg:address":"Carr Joan Peset, (de), 65",
    "sg:city":"Carlet",
    "sg:orig_category":"Agencias Y Agentes Comerciales, Representantes",
    "sg:phone":"+34 962 53 03 45",
    "sg:postcode":"46240",
    "sg:province":"Valencia",
    "wof:name":"Balaguer Garcia Vicente",
    "wof:placetype":"venue"
},
  "geometry": {"coordinates":[-0.523186028,39.2249298096],"type":"Point"}
}