{
  "type": "Feature",
  "properties": {
    "iso:country":"ES",
    "sg:address":"Calle de Prieto Ure\u00d1a, 22",
    "sg:city":"Madrid",
    "sg:orig_category":"Estudios, Instalaci\u00d3n De Climatizaci\u00d3n",
    "sg:phone":"+34 913 45 43 72",
    "sg:postcode":"28016",
    "sg:province":"Madrid",
    "wof:name":"Oca\u00d1a S.l.",
    "wof:placetype":"venue"
},
  "geometry": {"coordinates":[-3.6688520908,40.4646110535],"type":"Point"}
}