{
  "type": "Feature",
  "properties": {
    "iso:country":"ES",
    "sg:address":"Av Santa Coloma, 49",
    "sg:city":"Santa Coloma De Gramenet",
    "sg:orig_category":"Agencias De Viajes",
    "sg:phone":"+34 934 66 42 21",
    "sg:postcode":"08922",
    "sg:province":"Barcelona",
    "sg:website":"www.ahsanteviajes.com",
    "wof:name":"Viatges Ahsante S.l.l",
    "wof:placetype":"venue"
},
  "geometry": {"coordinates":[2.2082629204,41.4479942322],"type":"Point"}
}