{
  "type": "Feature",
  "properties": {
    "iso:country":"ES",
    "sg:address":"Plaz San Juan De Los Lagos, 7",
    "sg:city":"Burgos",
    "sg:orig_category":"Carnicer\u00cdas, Carnicer\u00cdas",
    "sg:phone":"+34 947 21 61 88",
    "sg:postcode":"09006",
    "sg:province":"Burgos",
    "wof:name":"Val Aviles Luis Mariano Del",
    "wof:placetype":"venue"
},
  "geometry": {"coordinates":[-3.6845049858,42.3551063538],"type":"Point"}
}