{
  "type": "Feature",
  "properties": {
    "addr:full":"Avda Jose Antonio, 15 Navahermosa Toledo 45150",
    "addr:housenumber":"15",
    "addr:postcode":"45150",
    "addr:street":"Avda Jose Antonio",
    "iso:country":"ES",
    "sg:address":"Avda Jose Antonio, 15",
    "sg:city":"Navahermosa",
    "sg:orig_category":"Molduras, Junquillos, Listones Y Molduras Perforadas",
    "sg:phone":"+34 925 41 00 19",
    "sg:postcode":"45150",
    "sg:province":"Toledo",
    "wof:name":"Perez Roman Angel",
    "wof:placetype":"venue"
},
  "geometry": {"coordinates":[-4.4712791443,39.6334915161],"type":"Point"}
}