{
  "type": "Feature",
  "properties": {
    "addr:full":"Avda De Bara\u00f1ain, 6 Iru\u00f1a Navarra 31011",
    "addr:housenumber":"6",
    "addr:postcode":"31011",
    "addr:street":"Avda De Baran\u0303Ain",
    "iso:country":"ES",
    "sg:address":"Avda De Bara\u00f1ain, 6",
    "sg:city":"Iru\u00f1a",
    "sg:orig_category":"Farmacias",
    "sg:phone":"+34 948 26 62 07",
    "sg:postcode":"31011",
    "sg:province":"Navarra",
    "wof:name":"Hanna Georgi  Hanneh",
    "wof:placetype":"venue"
},
  "geometry": {"coordinates":[-1.6558489799,42.8135681152],"type":"Point"}
}