{
  "type": "Feature",
  "properties": {
    "addr:full":"Ctra Carmona, 3 Marchena Sevilla 41620",
    "addr:housenumber":"3",
    "addr:postcode":"41620",
    "addr:street":"Ctra Carmona",
    "iso:country":"ES",
    "sg:address":"Ctra Carmona, 3",
    "sg:city":"Marchena",
    "sg:orig_category":"Chapister\u00cda",
    "sg:phone":"+34 955 84 51 56",
    "sg:postcode":"41620",
    "sg:province":"Sevilla",
    "wof:name":"Montero Luna S.l.",
    "wof:placetype":"venue"
},
  "geometry": {"coordinates":[-5.4104962349,37.33045578],"type":"Point"}
}