{
  "type": "Feature",
  "properties": {
    "iso:country":"ES",
    "sg:address":"Pl Major, 7",
    "sg:city":"Tarrega",
    "sg:orig_category":"Estudios De Fotograf\u00cda",
    "sg:phone":"+34 973 31 16 29",
    "sg:postcode":"25300",
    "sg:province":"Lleida",
    "sg:website":"www.jaumesole.com",
    "wof:name":"Foto Estudi J.sole S.l.",
    "wof:placetype":"venue"
},
  "geometry": {"coordinates":[1.1395430565,41.6463356018],"type":"Point"}
}