{
  "type": "Feature",
  "properties": {
    "iso:country":"ES",
    "sg:address":"Plaz Colon (de), 12",
    "sg:city":"Cordoba",
    "sg:orig_category":"Arquitectos",
    "sg:phone":"+34 957 48 15 03",
    "sg:postcode":"14001",
    "sg:province":"C\u00f3rdoba",
    "wof:name":"Silgo Iba\u00f1ez Javier Maria",
    "wof:placetype":"venue"
},
  "geometry": {"coordinates":[-4.7797689438,37.8908004761],"type":"Point"}
}