{
  "type": "Feature",
  "properties": {
    "iso:country":"ES",
    "sg:address":"Errotazar, 34",
    "sg:city":"Iru\u00f1a",
    "sg:orig_category":"Arquitectos",
    "sg:phone":"+34 948 13 67 94",
    "sg:postcode":"31014",
    "sg:province":"Navarra",
    "wof:name":"Runa Arquitectos S.l.",
    "wof:placetype":"venue"
},
  "geometry": {"coordinates":[-1.6454509497,42.8242034912],"type":"Point"}
}