{
  "type": "Feature",
  "properties": {
    "addr:full":"Calle de A, 34 Mutiloabeiti Navarra 31192",
    "addr:housenumber":"34",
    "addr:postcode":"31192",
    "addr:street":"Calle De A",
    "iso:country":"ES",
    "sg:address":"Calle de A, 34",
    "sg:city":"Mutiloabeiti",
    "sg:orig_category":"Audiovisuales (producci\u00d3n, Edici\u00d3n, Realizaci\u00d3n)",
    "sg:phone":"+34 948 29 10 86",
    "sg:postcode":"31192",
    "sg:province":"Navarra",
    "wof:name":"Navarra De Cine S.l",
    "wof:placetype":"venue"
},
  "geometry": {"coordinates":[-1.6323760748,42.8051452637],"type":"Point"}
}