{
  "type": "Feature",
  "properties": {
    "addr:full":"Plaz San Pablo, 1 Palencia Palencia 34005",
    "addr:housenumber":"1",
    "addr:postcode":"34005",
    "addr:street":"Plaz San Pablo",
    "iso:country":"ES",
    "sg:address":"Plaz San Pablo, 1",
    "sg:city":"Palencia",
    "sg:orig_category":"Promotores Constructores",
    "sg:phone":"+34 979 74 37 36",
    "sg:postcode":"34005",
    "sg:province":"Palencia",
    "wof:name":"Grijota Urbanizaciones S.l.",
    "wof:placetype":"venue"
},
  "geometry": {"coordinates":[-4.5350818634,42.0140609741],"type":"Point"}
}