{
  "type": "Feature",
  "properties": {
    "addr:full":"Plaz San Francisco, 20 Molina Guadalajara 19300",
    "addr:housenumber":"20",
    "addr:postcode":"19300",
    "addr:street":"Plaz San Francisco",
    "iso:country":"ES",
    "sg:address":"Plaz San Francisco, 20",
    "sg:city":"Molina",
    "sg:orig_category":"Molduras, Junquillos, Listones Y Molduras Perforadas",
    "sg:phone":"+34 949 83 10 15",
    "sg:postcode":"19300",
    "sg:province":"Guadalajara",
    "wof:name":"Serrano Bueno Maria",
    "wof:placetype":"venue"
},
  "geometry": {"coordinates":[-1.8790500164,40.8489608765],"type":"Point"}
}