{
  "type": "Feature",
  "properties": {
    "addr:full":"Calle de Corazon De Maria, 13 Madrid Madrid 28002",
    "addr:housenumber":"13",
    "addr:postcode":"madrid;28002",
    "addr:street":"Calle De Corazon;Maria",
    "iso:country":"ES",
    "sg:address":"Calle de Corazon De Maria, 13",
    "sg:city":"Madrid",
    "sg:orig_category":"Administradores De Bienes Y Delegados De Comunidades De Propietarios",
    "sg:phone":"+34 914 15 51 88",
    "sg:postcode":"28002",
    "sg:province":"Madrid",
    "wof:name":"Gonzalez Garcia Pedro",
    "wof:placetype":"venue"
},
  "geometry": {"coordinates":[-3.6698288918,40.4417076111],"type":"Point"}
}