{
  "type": "Feature",
  "properties": {
    "addr:full":"Calle de Moheda, 2 Zahinos Badajoz 06129",
    "addr:housenumber":"2",
    "addr:postcode":"06129",
    "addr:street":"Calle De Moheda",
    "iso:country":"ES",
    "sg:address":"Calle de Moheda, 2",
    "sg:city":"Zahinos",
    "sg:orig_category":"Art\u00cdculos De Regalo (al Por Menor)",
    "sg:phone":"+34 924 73 82 55",
    "sg:postcode":"06129",
    "sg:province":"Badajoz",
    "wof:name":"Nu\u00f1ez Rodriguez Amelia",
    "wof:placetype":"venue"
},
  "geometry": {"coordinates":[-6.9536180496,38.3308753967],"type":"Point"}
}