{
  "type": "Feature",
  "properties": {
    "addr:full":"Calle de Borja, 45 Zaragoza Zaragoza 50017",
    "addr:housenumber":"45",
    "addr:postcode":"50017",
    "addr:street":"Calle De Borja",
    "iso:country":"ES",
    "sg:address":"Calle de Borja, 45",
    "sg:city":"Zaragoza",
    "sg:orig_category":"Comercio, Reparaci\u00d3n De Bicicletas, De Motocicletas, De Accesorios",
    "sg:phone":"+34 976 46 03 39",
    "sg:postcode":"50017",
    "sg:province":"Zaragoza",
    "wof:name":"Lostao Aliacar Fernando",
    "wof:placetype":"venue"
},
  "geometry": {"coordinates":[-0.9074121714,41.6503715515],"type":"Point"}
}