{
  "type": "Feature",
  "properties": {
    "addr:full":"Pg Vint-i-dos De Juliol, 368 Terrassa Barcelona 08221",
    "addr:housenumber":"368",
    "addr:postcode":"08221",
    "addr:street":"Pg Vint-I-Dos",
    "iso:country":"ES",
    "sg:address":"Pg Vint-i-dos De Juliol, 368",
    "sg:city":"Terrassa",
    "sg:orig_category":"Molduras, Junquillos, Listones Y Molduras Perforadas",
    "sg:phone":"+34 937 83 05 26",
    "sg:postcode":"08221",
    "sg:province":"Barcelona",
    "wof:name":"Masip Egea Carlos",
    "wof:placetype":"venue"
},
  "geometry": {"coordinates":[2.0130579472,41.5698814392],"type":"Point"}
}