{
  "type": "Feature",
  "properties": {
    "iso:country":"ES",
    "sg:address":"Calle de Zubiaurre, 24",
    "sg:city":"Ermua",
    "sg:orig_category":"Internados & Ense\u00d1anza Privada",
    "sg:phone":"+34 943 17 30 66",
    "sg:postcode":"48260",
    "sg:province":"Vizcaya",
    "wof:name":"Perosanz Bartolome Maria Pilar",
    "wof:placetype":"venue"
},
  "geometry": {"coordinates":[-2.5026679039,43.1884498596],"type":"Point"}
}