{
  "type": "Feature",
  "properties": {
    "iso:country":"ES",
    "sg:address":"C/ Vicente Blasco Iba\u00d1ez, 56",
    "sg:city":"Elche",
    "sg:orig_category":"Agencias De Viajes",
    "sg:phone":"+34 966 66 23 07",
    "sg:postcode":"03201",
    "sg:province":"Alicante",
    "sg:website":"www.grupoeuropa.com",
    "wof:name":"Viajes Elche Tours S.l.",
    "wof:placetype":"venue"
},
  "geometry": {"coordinates":[-0.7039960027,38.268081665],"type":"Point"}
}