{
  "type": "Feature",
  "properties": {
    "addr:full":"Calle de Martinez Seco, 14 Madrid Madrid 28021",
    "addr:housenumber":"14",
    "addr:postcode":"madrid;28021",
    "addr:street":"Calle De Martinez Seco",
    "iso:country":"ES",
    "sg:address":"Calle de Martinez Seco, 14",
    "sg:city":"Madrid",
    "sg:orig_category":"Mec\u00c1nico Del Autom\u00d3vil",
    "sg:phone":"+34 915 05 17 71",
    "sg:postcode":"28021",
    "sg:province":"Madrid",
    "wof:name":"Lopez Marquez Julian",
    "wof:placetype":"venue"
},
  "geometry": {"coordinates":[-3.7127981186,40.3462791443],"type":"Point"}
}