{
  "type": "Feature",
  "properties": {
    "iso:country":"ES",
    "sg:address":"Pol Ind Cerro De Jaen, S/n",
    "sg:city":"Villargordo",
    "sg:orig_category":"Heladeros",
    "sg:phone":"+34 953 37 70 53",
    "sg:postcode":"23630",
    "sg:province":"Ja\u00e9n",
    "wof:name":"Agudo Sanchez Jose",
    "wof:placetype":"venue"
},
  "geometry": {"coordinates":[-3.7300820351,37.9401397705],"type":"Point"}
}