{
  "type": "Feature",
  "properties": {
    "addr:full":"Calle de Padre Francisco Suarez, 29 Valladolid Valladolid 47006",
    "addr:housenumber":"29",
    "addr:postcode":"47006",
    "addr:street":"Calle De Padre Francisco Suarez",
    "iso:country":"ES",
    "sg:address":"Calle de Padre Francisco Suarez, 29",
    "sg:city":"Valladolid",
    "sg:orig_category":"Juegos Y Juguetes (al Por Menor)",
    "sg:phone":"+34 983 22 19 74",
    "sg:postcode":"47006",
    "sg:province":"Valladolid",
    "wof:name":"Bolera Holpas S.l.",
    "wof:placetype":"venue"
},
  "geometry": {"coordinates":[-4.7377119064,41.6426582336],"type":"Point"}
}