{
  "type": "Feature",
  "properties": {
    "addr:full":"Carrer de Raval De Sant Joan, 4 Cardona Barcelona 08261",
    "addr:housenumber":"4",
    "addr:postcode":"08261",
    "addr:street":"Carrer De Raval De Sant Joan",
    "iso:country":"ES",
    "sg:address":"Carrer de Raval De Sant Joan, 4",
    "sg:city":"Cardona",
    "sg:orig_category":"Ropa Para Beb\u00c9s Y Ni\u00d1os (confecci\u00d3n, Al Por Mayor)",
    "sg:phone":"+34 938 69 29 94",
    "sg:postcode":"08261",
    "sg:province":"Barcelona",
    "wof:name":"Barons Merono Ascension",
    "wof:placetype":"venue"
},
  "geometry": {"coordinates":[1.6797800064,41.9112739563],"type":"Point"}
}