{
  "type": "Feature",
  "properties": {
    "addr:full":"Calle de San Adrian De Sasabe, 6 Zaragoza Zaragoza 50002",
    "addr:housenumber":"6",
    "addr:postcode":"50002",
    "addr:street":"Calle De San Adrian De Sasabe",
    "iso:country":"ES",
    "sg:address":"Calle de San Adrian De Sasabe, 6",
    "sg:city":"Zaragoza",
    "sg:orig_category":"Molduras, Junquillos, Listones Y Molduras Perforadas",
    "sg:phone":"+34 976 13 48 62",
    "sg:postcode":"50002",
    "sg:province":"Zaragoza",
    "wof:name":"Fernandez Migue Maria Dolores",
    "wof:placetype":"venue"
},
  "geometry": {"coordinates":[-0.8596889973,41.6420288086],"type":"Point"}
}