{
  "type": "Feature",
  "properties": {
    "addr:full":"Pg Nou, 3 Figueres Girona 17600",
    "addr:housenumber":"3",
    "addr:postcode":"17600",
    "addr:street":"Pg Nou",
    "iso:country":"ES",
    "sg:address":"Pg Nou, 3",
    "sg:city":"Figueres",
    "sg:orig_category":"Hilaturas, Hilos Y Actividades Relacionadas",
    "sg:phone":"+34 972 50 07 01",
    "sg:postcode":"17600",
    "sg:province":"Girona",
    "wof:name":"Granes Manera Linia",
    "wof:placetype":"venue"
},
  "geometry": {"coordinates":[2.9576039314,42.2664909363],"type":"Point"}
}