{
  "type": "Feature",
  "properties": {
    "iso:country":"ES",
    "sg:address":"Calle de Hilados, 20",
    "sg:city":"Torrejon Ardoz",
    "sg:orig_category":"Administradores De Bienes Y Delegados De Comunidades De Propietarios",
    "sg:phone":"+34 916 56 71 34",
    "sg:postcode":"28850",
    "sg:province":"Madrid",
    "wof:name":"Moreno Peralta Reyes",
    "wof:placetype":"venue"
},
  "geometry": {"coordinates":[-3.4584336281,40.4451713562],"type":"Point"}
}