{
  "type": "Feature",
  "properties": {
    "addr:full":"Rua Severino Cobas, 64 Sabaxans Pontevedra 36214",
    "addr:housenumber":"64",
    "addr:postcode":"36214",
    "addr:street":"Rua Severino Cobas",
    "iso:country":"ES",
    "sg:address":"Rua Severino Cobas, 64",
    "sg:city":"Sabaxans",
    "sg:orig_category":"Empresas De Portes Y Mensajer\u00cda",
    "sg:phone":"+34 986 26 50 43",
    "sg:postcode":"36214",
    "sg:province":"Pontevedra",
    "wof:name":"Noroeste Expres Servicio Integral De Paqueteria S.l.",
    "wof:placetype":"venue"
},
  "geometry": {"coordinates":[-8.7059106827,42.2124443054],"type":"Point"}
}