{
  "type": "Feature",
  "properties": {
    "iso:country":"ES",
    "sg:address":"Calle de Moret, 26",
    "sg:city":"Caceres",
    "sg:orig_category":"Ropa Para Se\u00d1oras Y Caballeros (al Por Menor)",
    "sg:phone":"+34 927 21 16 78",
    "sg:postcode":"10003",
    "sg:province":"C\u00e1ceres",
    "wof:name":"Rocha Junco Guadalupe",
    "wof:placetype":"venue"
},
  "geometry": {"coordinates":[-6.3732180595,39.4743614197],"type":"Point"}
}