{
  "type": "Feature",
  "properties": {
    "iso:country":"ES",
    "sg:address":"Calle de Virgen De Loreto, 43",
    "sg:city":"Sevilla",
    "sg:orig_category":"Delegados, Agentes De Tr\u00c1nsito, Auxiliares De Transporte Internacional",
    "sg:phone":"+34 954 45 17 12",
    "sg:postcode":"41011",
    "sg:province":"Sevilla",
    "wof:name":"Tu Rueda S.l.",
    "wof:placetype":"venue"
},
  "geometry": {"coordinates":[-5.9999089241,37.3756484985],"type":"Point"}
}