{
  "type": "Feature",
  "properties": {
    "iso:country":"ES",
    "sg:address":"Calle de Francisco Olivan Bayle, 2",
    "sg:city":"Zaragoza",
    "sg:orig_category":"Bisuter\u00cda, Joyer\u00cda, Relojer\u00cda (al Por Menor)",
    "sg:phone":"+34 976 20 22 24",
    "sg:postcode":"50015",
    "sg:province":"Zaragoza",
    "wof:name":"Lopez Lamata Jose Maria",
    "wof:placetype":"venue"
},
  "geometry": {"coordinates":[-0.8718860149,41.6630516052],"type":"Point"}
}