{
  "type": "Feature",
  "properties": {
    "iso:country":"ES",
    "sg:address":"Calle de Masustegi, 2",
    "sg:city":"Bilbao",
    "sg:orig_category":"Peluqueros: De Se\u00d1oras",
    "sg:phone":"+34 944 12 83 55",
    "sg:postcode":"48006",
    "sg:province":"Vizcaya",
    "wof:name":"Elene Ispizua Rodriguez",
    "wof:placetype":"venue"
},
  "geometry": {"coordinates":[-2.9132299423,43.256401062],"type":"Point"}
}