{
  "type": "Feature",
  "properties": {
    "iso:country":"ES",
    "sg:address":"Cno. Ciudad Deport. Santa Maria, 9",
    "sg:city":"Alca\u00f1iz",
    "sg:orig_category":"Transportes Por V\u00cdas Navegables",
    "sg:phone":"+34 978 83 00 23",
    "sg:postcode":"44600",
    "sg:province":"Teruel",
    "wof:name":"Lopez Lopez Juan Jose",
    "wof:placetype":"venue"
},
  "geometry": {"coordinates":[-0.1869643927,41.0795669556],"type":"Point"}
}