{
  "type": "Feature",
  "properties": {
    "addr:full":"Bo Carbonaire, 16 Vall Uixo Castell\u00f3n 12600",
    "addr:housenumber":"16",
    "addr:postcode":"12600",
    "addr:street":"Carbonaire;Castello\u0301N",
    "iso:country":"ES",
    "sg:address":"Bo Carbonaire, 16",
    "sg:city":"Vall Uixo",
    "sg:orig_category":"Carnicer\u00cdas, Carnicer\u00cdas",
    "sg:phone":"+34 964 66 11 36",
    "sg:postcode":"12600",
    "sg:province":"Castell\u00f3n",
    "wof:name":"Lopez Gomez Antonio",
    "wof:placetype":"venue"
},
  "geometry": {"coordinates":[-0.2371300012,39.8286857605],"type":"Point"}
}