{
  "type": "Feature",
  "properties": {
    "iso:country":"ES",
    "sg:address":"Avda Constitucion (de La), 51",
    "sg:city":"Mostoles",
    "sg:orig_category":"Asesor\u00cda Sobre Comunicaci\u00d3n De Empresas",
    "sg:phone":"+34 916 14 33 64",
    "sg:postcode":"28931",
    "sg:province":"Madrid",
    "wof:name":"Asepyme Mostoles S.l.",
    "wof:placetype":"venue"
},
  "geometry": {"coordinates":[-3.8606920242,40.3268470764],"type":"Point"}
}