{
  "type": "Feature",
  "properties": {
    "iso:country":"ES",
    "sg:address":"Av Autopista Del Saler, 4",
    "sg:city":"Valencia",
    "sg:orig_category":"Sociedades, Compa\u00d1\u00cdas Aseguradoras",
    "sg:phone":"+34 963 15 20 32",
    "sg:postcode":"46013",
    "sg:province":"Valencia",
    "sg:website":"www.asefa.es",
    "wof:name":"Asefa S.a.",
    "wof:placetype":"venue"
},
  "geometry": {"coordinates":[-0.3330647051,39.3840255737],"type":"Point"}
}