{
  "type": "Feature",
  "properties": {
    "iso:country":"ES",
    "sg:address":"Calle de Juan Sebastian Elkano, 9",
    "sg:city":"Barakaldo",
    "sg:orig_category":"Medias Y Calcetines (fabricaci\u00d3n, Al Por Mayor)",
    "sg:phone":"+34 944 37 35 08",
    "sg:postcode":"48901",
    "sg:province":"Vizcaya",
    "wof:name":"Marta Delgado Elorduy",
    "wof:placetype":"venue"
},
  "geometry": {"coordinates":[-2.9879341125,43.2963256836],"type":"Point"}
}