{
  "type": "Feature",
  "properties": {
    "addr:full":"Avda Cristo Rey, 2 Ubeda Ja\u00e9n 23400",
    "addr:housenumber":"2",
    "addr:postcode":"23400",
    "addr:street":"Avda Cristo Rey;Jae\u0301N",
    "iso:country":"ES",
    "sg:address":"Avda Cristo Rey, 2",
    "sg:city":"Ubeda",
    "sg:orig_category":"Barbacoas Y Accesorios",
    "sg:phone":"+34 953 75 04 63",
    "sg:postcode":"23400",
    "sg:province":"Ja\u00e9n",
    "wof:name":"Plaza Olivares Agustin",
    "wof:placetype":"venue"
},
  "geometry": {"coordinates":[-3.3762059212,38.0115661621],"type":"Point"}
}