{
  "type": "Feature",
  "properties": {
    "addr:full":"Carr Ample, 100 Palafrugell Girona 17200",
    "addr:housenumber":"100",
    "addr:postcode":"17200",
    "addr:street":"Carr Ample",
    "iso:country":"ES",
    "sg:address":"Carr Ample, 100",
    "sg:city":"Palafrugell",
    "sg:orig_category":"Cajas Registradoras, Terminales De Puntos De Venta",
    "sg:phone":"+34 972 30 49 55",
    "sg:postcode":"17200",
    "sg:province":"Girona",
    "wof:name":"Pavon Cabrera Jose",
    "wof:placetype":"venue"
},
  "geometry": {"coordinates":[3.162858963,41.9123878479],"type":"Point"}
}