{
  "type": "Feature",
  "properties": {
    "addr:full":"Plaz Santa Brigida, 3 Valladolid Valladolid 47003",
    "addr:postcode":"47003",
    "iso:country":"ES",
    "sg:address":"Plaz Santa Brigida, 3",
    "sg:city":"Valladolid",
    "sg:orig_category":"Fabricaci\u00d3n, Distribuci\u00d3n De Discos, V\u00cddeodiscos Y Musicassettes",
    "sg:phone":"+34 983 33 79 61",
    "sg:postcode":"47003",
    "sg:province":"Valladolid",
    "wof:name":"Hernandez Garcia Maria",
    "wof:placetype":"venue"
},
  "geometry": {"coordinates":[-4.7276558876,41.6562423706],"type":"Point"}
}