{
  "type": "Feature",
  "properties": {
    "iso:country":"ES",
    "sg:address":"Carr Torregrossa, Km. 0011,0",
    "sg:city":"Juneda",
    "sg:orig_category":"Centros De Educaci\u00d3n Especial",
    "sg:phone":"+34 973 15 04 14",
    "sg:postcode":"25430",
    "sg:province":"Lleida",
    "wof:name":"Asociacion Pro Minusvalidos De Las Garrigas",
    "wof:placetype":"venue"
},
  "geometry": {"coordinates":[0.8258441091,41.5504837036],"type":"Point"}
}