{
  "type": "Feature",
  "properties": {
    "addr:full":"Calle de Rebullida, 21 Torrecilla De Alca\u00e7iz Teruel 44640",
    "addr:housenumber":"21",
    "addr:postcode":"44640",
    "addr:street":"Calle De Rebullida",
    "iso:country":"ES",
    "sg:address":"Calle de Rebullida, 21",
    "sg:city":"Torrecilla De Alca\u00e7iz",
    "sg:orig_category":"Sanatorios M\u00c9dico",
    "sg:phone":"+34 978 85 21 65",
    "sg:postcode":"44640",
    "sg:province":"Teruel",
    "wof:name":"Ayuntamiento-consultorio Medico",
    "wof:placetype":"venue"
},
  "geometry": {"coordinates":[-1.1069096327,40.3441085815],"type":"Point"}
}