{
  "type": "Feature",
  "properties": {
    "iso:country":"ES",
    "sg:address":"C/ Sant Miquel, 127",
    "sg:city":"Inca",
    "sg:orig_category":"Electricidad: Instaladores",
    "sg:phone":"+34 971 88 12 09",
    "sg:postcode":"07300",
    "sg:province":"Islas Baleares",
    "wof:name":"Llum Salas S.l.",
    "wof:placetype":"venue"
},
  "geometry": {"coordinates":[2.9208989143,39.7179527283],"type":"Point"}
}