{
  "type": "Feature",
  "properties": {
    "iso:country":"ES",
    "sg:address":"Calle de Alicante, 14",
    "sg:city":"Castellon",
    "sg:orig_category":"Abogados",
    "sg:phone":"+34 964 26 06 41",
    "sg:postcode":"12004",
    "sg:province":"Castell\u00f3n",
    "wof:name":"Paz Garcia Jose Vicente De La",
    "wof:placetype":"venue"
},
  "geometry": {"coordinates":[-0.0361329988,39.9944572449],"type":"Point"}
}