{
  "type": "Feature",
  "properties": {
    "iso:country":"ES",
    "sg:address":"Calle de Alanis De La Sierra, 16",
    "sg:city":"Huelva",
    "sg:orig_category":"Ropa Para Ni\u00d1os (al Por Menor)",
    "sg:phone":"+34 959 27 12 59",
    "sg:postcode":"21007",
    "sg:province":"Huelva",
    "wof:name":"Alejandre Marquez Jose",
    "wof:placetype":"venue"
},
  "geometry": {"coordinates":[-6.9274926186,37.2637023926],"type":"Point"}
}