{
  "type": "Feature",
  "properties": {
    "iso:country":"ES",
    "sg:address":"Carrer de Badia, 24",
    "sg:city":"Barcelona",
    "sg:orig_category":"Arquitectos",
    "sg:phone":"+34 932 17 20 02",
    "sg:postcode":"08012",
    "sg:province":"Barcelona",
    "wof:name":"Torrent Bresco Arquitectes Associats",
    "wof:placetype":"venue"
},
  "geometry": {"coordinates":[2.1532590389,41.4044799805],"type":"Point"}
}