{
  "type": "Feature",
  "properties": {
    "addr:full":"Carr Sant Mori, 6 Empuriabrava Girona 17487",
    "addr:housenumber":"6",
    "addr:postcode":"17487",
    "addr:street":"Carr Sant Mori",
    "iso:country":"ES",
    "sg:address":"Carr Sant Mori, 6",
    "sg:city":"Empuriabrava",
    "sg:orig_category":"Librer\u00cdas",
    "sg:phone":"+34 972 45 01 15",
    "sg:postcode":"17487",
    "sg:province":"Girona",
    "wof:name":"Armengol Bardena Rosa",
    "wof:placetype":"venue"
},
  "geometry": {"coordinates":[3.1232326031,42.2435379028],"type":"Point"}
}