{
  "type": "Feature",
  "properties": {
    "iso:country":"ES",
    "sg:address":"Calle de Cadarso, 3",
    "sg:city":"Madrid",
    "sg:orig_category":"Inform\u00c1tica (estudios, Servicios, Asesor\u00cda, Formaci\u00d3n)",
    "sg:phone":"+34 915 47 02 79",
    "sg:postcode":"28008",
    "sg:province":"Madrid",
    "sg:website":"www.compuke.es",
    "wof:name":"Computers Nuevas Tecnologias S.l.",
    "wof:placetype":"venue"
},
  "geometry": {"coordinates":[-3.7141184807,40.4215927124],"type":"Point"}
}