{
  "type": "Feature",
  "properties": {
    "iso:country":"ES",
    "sg:address":"Erribera Kalea, 12",
    "sg:city":"Usurbil",
    "sg:orig_category":"Freidur\u00cdas: Equipos Y Suministros",
    "sg:phone":"+34 943 37 10 11",
    "sg:postcode":"20170",
    "sg:province":"Guip\u00f9zcoa",
    "wof:name":"Patatas San Jeronimo S.l.",
    "wof:placetype":"venue"
},
  "geometry": {"coordinates":[-2.0522699356,43.2708206177],"type":"Point"}
}