{
  "type": "Feature",
  "properties": {
    "iso:country":"ES",
    "sg:address":"Av Comte Guifre, 13",
    "sg:city":"Sant Joan De Les Abadesses",
    "sg:orig_category":"Arquitectos",
    "sg:phone":"+34 972 72 00 90",
    "sg:postcode":"17860",
    "sg:province":"Girona",
    "wof:name":"Llobet Vilaseca Carme",
    "wof:placetype":"venue"
},
  "geometry": {"coordinates":[2.2850320339,42.2336730957],"type":"Point"}
}