{
  "type": "Feature",
  "properties": {
    "addr:full":"Calle de Espronceda, 6 Alhama Murcia Murcia 30840",
    "addr:housenumber":"6",
    "addr:postcode":"30840",
    "addr:street":"Calle De Espronceda",
    "iso:country":"ES",
    "sg:address":"Calle de Espronceda, 6",
    "sg:city":"Alhama Murcia",
    "sg:orig_category":"Ropa De Hogar (al Por Menor)",
    "sg:phone":"+34 968 63 26 34",
    "sg:postcode":"30840",
    "sg:province":"Murcia",
    "wof:name":"Lopez Burgos Ana Maria",
    "wof:placetype":"venue"
},
  "geometry": {"coordinates":[-1.4315520525,37.8512077332],"type":"Point"}
}