{
  "type": "Feature",
  "properties": {
    "iso:country":"ES",
    "sg:address":"Ca\u00f1ada Alta, 4",
    "sg:city":"Ca\u00f1ada",
    "sg:orig_category":"Ferreter\u00cda (diversos)",
    "sg:phone":"+34 965 66 73 43",
    "sg:postcode":"03699",
    "sg:province":"Alicante",
    "wof:name":"Hierros Chimo S.l.",
    "wof:placetype":"venue"
},
  "geometry": {"coordinates":[-0.8098580837,38.675239563],"type":"Point"}
}