{
  "type": "Feature",
  "properties": {
    "iso:country":"ES",
    "sg:address":"Ctra. Valencia, 27",
    "sg:city":"Rotgla I Corbera",
    "sg:orig_category":"Fabricaci\u00d3n De Productos Textiles Sin Tejer",
    "sg:phone":"+34 962 25 42 54",
    "sg:postcode":"46816",
    "sg:province":"Valencia",
    "wof:name":"Damatex S.l.",
    "wof:placetype":"venue"
},
  "geometry": {"coordinates":[-0.5639290214,39.0057487488],"type":"Point"}
}