{
  "type": "Feature",
  "properties": {
    "iso:country":"ES",
    "sg:address":"Calle de Alameda, 8",
    "sg:city":"Najera",
    "sg:orig_category":"Peluquer\u00cdas, Peluquer\u00cda Mixta",
    "sg:phone":"+34 941 36 06 64",
    "sg:postcode":"26300",
    "sg:province":"La Rioja",
    "wof:name":"Hoya Pereda Beatriz",
    "wof:placetype":"venue"
},
  "geometry": {"coordinates":[-2.7299547195,42.4189567566],"type":"Point"}
}