{
  "type": "Feature",
  "properties": {
    "iso:country":"ES",
    "sg:address":"Calle de Mayor, 5",
    "sg:city":"Corella",
    "sg:orig_category":"Zapatos (al Por Menor)",
    "sg:phone":"+34 948 78 02 90",
    "sg:postcode":"31591",
    "sg:province":"Navarra",
    "wof:name":"Mellado Sesma Miguel",
    "wof:placetype":"venue"
},
  "geometry": {"coordinates":[-1.7842960358,42.1148834229],"type":"Point"}
}