{
  "type": "Feature",
  "properties": {
    "addr:full":"Calle de Embajadores, 200 Madrid Madrid 28045",
    "addr:housenumber":"200",
    "addr:postcode":"28045",
    "addr:street":"Calle De Embajadores",
    "iso:country":"ES",
    "sg:address":"Calle de Embajadores, 200",
    "sg:city":"Madrid",
    "sg:orig_category":"Comercio De Piezas De Recambio Y De Accesorios De Veh\u00cdculos, Veh\u00cdculos Industriales",
    "sg:phone":"+34 914 67 10 13",
    "sg:postcode":"28045",
    "sg:province":"Madrid",
    "wof:name":"Auto Comercio Legazpi S.a.l.",
    "wof:placetype":"venue"
},
  "geometry": {"coordinates":[-3.6932570934,40.3916130066],"type":"Point"}
}