{
  "type": "Feature",
  "properties": {
    "addr:full":"Moncayo, 12 Cadrete Zaragoza 50420",
    "addr:housenumber":"12",
    "addr:postcode":"50420",
    "addr:street":"Moncayo",
    "iso:country":"ES",
    "sg:address":"Moncayo, 12",
    "sg:city":"Cadrete",
    "sg:orig_category":"Alimentaci\u00d3n General (al Por Mayor)",
    "sg:phone":"+34 976 12 67 58",
    "sg:postcode":"50420",
    "sg:province":"Zaragoza",
    "wof:name":"Alsual S.l.",
    "wof:placetype":"venue"
},
  "geometry": {"coordinates":[-0.9649108052,41.5512695312],"type":"Point"}
}