{
  "type": "Feature",
  "properties": {
    "addr:full":"Ctra. Rueda, 4 Valladolid Valladolid 47008",
    "addr:housenumber":"4",
    "addr:postcode":"47008",
    "addr:street":"Ctra. Rueda",
    "iso:country":"ES",
    "sg:address":"Ctra. Rueda, 4",
    "sg:city":"Valladolid",
    "sg:orig_category":"Venta, Alquiler, Mantenimiento De Calderas",
    "sg:phone":"+34 983 23 39 63",
    "sg:postcode":"47008",
    "sg:province":"Valladolid",
    "wof:name":"Comanter S.l.",
    "wof:placetype":"venue"
},
  "geometry": {"coordinates":[-4.7414870262,41.6297302246],"type":"Point"}
}