{
  "type": "Feature",
  "properties": {
    "addr:full":"Ctra Agramunt, 55 Artesa Segre Lleida 25730",
    "addr:housenumber":"55",
    "addr:postcode":"25730",
    "addr:street":"Ctra Agramunt",
    "iso:country":"ES",
    "sg:address":"Ctra Agramunt, 55",
    "sg:city":"Artesa Segre",
    "sg:orig_category":"Colchones (fabricaci\u00d3n, Al Por Mayor, Al Por Menor)",
    "sg:phone":"+34 973 40 03 92",
    "sg:postcode":"25730",
    "sg:province":"Lleida",
    "sg:website":"www.eurosomni.com",
    "wof:name":"Palau Del Descans S.l.",
    "wof:placetype":"venue"
},
  "geometry": {"coordinates":[1.0498579741,41.8959960938],"type":"Point"}
}