{
  "type": "Feature",
  "properties": {
    "addr:full":"Calle de Doctor Fleming, 2 Lugo De Llanera Asturias 33690",
    "addr:housenumber":"2",
    "addr:postcode":"33690",
    "addr:street":"Calle De Doctor Fleming",
    "iso:country":"ES",
    "sg:address":"Calle de Doctor Fleming, 2",
    "sg:city":"Lugo De Llanera",
    "sg:orig_category":"Fisioterapia",
    "sg:phone":"+34 985 77 28 23",
    "sg:postcode":"33690",
    "sg:province":"Asturias",
    "wof:name":"Olay Garcia Maria",
    "wof:placetype":"venue"
},
  "geometry": {"coordinates":[-5.8181109428,43.4420471191],"type":"Point"}
}