{
  "type": "Feature",
  "properties": {
    "iso:country":"ES",
    "sg:address":"Ctra De Sabiote(p I Los Cerros), Km. 0000,7",
    "sg:city":"Ubeda",
    "sg:orig_category":"Mec\u00c1nico Del Autom\u00d3vil",
    "sg:phone":"+34 953 75 46 66",
    "sg:postcode":"23400",
    "sg:province":"Ja\u00e9n",
    "wof:name":"Padilla Hidalgo Tomas",
    "wof:placetype":"venue"
},
  "geometry": {"coordinates":[-3.363006115,38.0253677368],"type":"Point"}
}