{
  "type": "Feature",
  "properties": {
    "iso:country":"ES",
    "sg:address":"Carrer de Diluvi, 8",
    "sg:city":"Barcelona",
    "sg:orig_category":"Confecci\u00d3n De Corbatas",
    "sg:phone":"+34 932 18 20 00",
    "sg:postcode":"08012",
    "sg:province":"Barcelona",
    "wof:name":"Corbateria Vendrell & Associats S.l.l.",
    "wof:placetype":"venue"
},
  "geometry": {"coordinates":[2.1586918831,41.4004135132],"type":"Point"}
}