{
  "type": "Feature",
  "properties": {
    "iso:country":"ES",
    "sg:address":"Calle de Poeta Prudencio, 4",
    "sg:city":"Logro\u00f1o",
    "sg:orig_category":"Panader\u00cdas, Panader\u00cdas",
    "sg:phone":"+34 941 22 18 32",
    "sg:postcode":"26006",
    "sg:province":"La Rioja",
    "wof:name":"Vega Iturbe Gimeno Y Otro",
    "wof:placetype":"venue"
},
  "geometry": {"coordinates":[-2.4036989212,42.46043396],"type":"Point"}
}