{
  "type": "Feature",
  "properties": {
    "addr:full":"Avda Libertad (de La), 4 Colmenar Viejo Madrid 28770",
    "addr:housenumber":"4",
    "addr:postcode":"28770",
    "addr:street":"Avda Libertad De La",
    "iso:country":"ES",
    "sg:address":"Avda Libertad (de La), 4",
    "sg:city":"Colmenar Viejo",
    "sg:orig_category":"Alquiler De V\u00cddeo",
    "sg:phone":"+34 918 46 33 99",
    "sg:postcode":"28770",
    "sg:province":"Madrid",
    "wof:name":"Aguilar Medina Nicolas",
    "wof:placetype":"venue"
},
  "geometry": {"coordinates":[-3.7667675018,40.6620826721],"type":"Point"}
}