{
  "type": "Feature",
  "properties": {
    "iso:country":"ES",
    "sg:address":"Calle de Clara Del Rey, 42",
    "sg:city":"Madrid",
    "sg:orig_category":"Complementos De Vestir (al Por Menor)",
    "sg:phone":"+34 914 16 26 37",
    "sg:postcode":"28002",
    "sg:province":"Madrid",
    "wof:name":"Perez Roman Emilia",
    "wof:placetype":"venue"
},
  "geometry": {"coordinates":[-3.6684808731,40.4447479248],"type":"Point"}
}