{
  "type": "Feature",
  "properties": {
    "iso:country":"ES",
    "sg:address":"Calle de Real, 72",
    "sg:city":"S. Fernando",
    "sg:orig_category":"Institutos De Belleza",
    "sg:phone":"+34 956 89 55 51",
    "sg:postcode":"11100",
    "sg:province":"C\u00e1diz",
    "wof:name":"Garcia Aparicio Ana Cristina",
    "wof:placetype":"venue"
},
  "geometry": {"coordinates":[-6.1967067719,36.4655647278],"type":"Point"}
}