{
  "type": "Feature",
  "properties": {
    "addr:full":"Calle de Santa Ana (de), 21 Paracuellos De Jarama Madrid 28860",
    "addr:postcode":"28860",
    "addr:street":"Calle De",
    "iso:country":"ES",
    "sg:address":"Calle de Santa Ana (de), 21",
    "sg:city":"Paracuellos De Jarama",
    "sg:orig_category":"Inmobiliaria (agencias)",
    "sg:phone":"+34 916 58 25 93",
    "sg:postcode":"28860",
    "sg:province":"Madrid",
    "wof:name":"Servicios Inmobiliarios Paracuellos S.l.",
    "wof:placetype":"venue"
},
  "geometry": {"coordinates":[-3.5317959785,40.503704071],"type":"Point"}
}