{
  "type": "Feature",
  "properties": {
    "addr:full":"Valentin Gomez, 5 Calatayud Zaragoza 50300",
    "addr:postcode":"50300",
    "addr:street":"Gomez",
    "iso:country":"ES",
    "sg:address":"Valentin Gomez, 5",
    "sg:city":"Calatayud",
    "sg:orig_category":"Comunidades Religiosas",
    "sg:phone":"+34 976 88 20 30",
    "sg:postcode":"50300",
    "sg:province":"Zaragoza",
    "wof:name":"Parroquia De San Juan",
    "wof:placetype":"venue"
},
  "geometry": {"coordinates":[-1.643138051,41.3523139954],"type":"Point"}
}