{
  "type": "Feature",
  "properties": {
    "addr:full":"Calle de Alejandrina Moran, 21 Madrid Madrid 28047",
    "addr:housenumber":"21",
    "addr:postcode":"madrid;28047",
    "addr:street":"Calle De Alejandrina Moran",
    "iso:country":"ES",
    "sg:address":"Calle de Alejandrina Moran, 21",
    "sg:city":"Madrid",
    "sg:orig_category":"Empresarios",
    "sg:phone":"+34 915 26 00 09",
    "sg:postcode":"28047",
    "sg:province":"Madrid",
    "wof:name":"Navarro Montero Manuel Maria",
    "wof:placetype":"venue"
},
  "geometry": {"coordinates":[-3.7469706535,40.4022407532],"type":"Point"}
}