{
  "type": "Feature",
  "properties": {
    "iso:country":"ES",
    "sg:address":"Calle de Antioquia, 69",
    "sg:city":"Sevilla",
    "sg:orig_category":"Panader\u00cdas, Panader\u00cdas",
    "sg:phone":"+34 954 25 59 66",
    "sg:postcode":"41007",
    "sg:province":"Sevilla",
    "wof:name":"Parrilla Maes Maria De La O",
    "wof:placetype":"venue"
},
  "geometry": {"coordinates":[-5.9563884735,37.3987045288],"type":"Point"}
}