{
  "type": "Feature",
  "properties": {
    "addr:full":"Avda Escaleritas, 66 Palmas De Gran Canaria Las Palmas 35011",
    "addr:housenumber":"66",
    "addr:postcode":"35011",
    "addr:street":"Avda Escaleritas",
    "iso:country":"ES",
    "sg:address":"Avda Escaleritas, 66",
    "sg:city":"Palmas De Gran Canaria",
    "sg:orig_category":"Venta, Reparaci\u00d3n, Localizaci\u00d3n De Balanzas Y De B\u00c1sculas",
    "sg:phone":"+34 928 20 69 05",
    "sg:postcode":"35011",
    "sg:province":"Las Palmas",
    "wof:name":"Rollet S.l.",
    "wof:placetype":"venue"
},
  "geometry": {"coordinates":[-15.43724823,28.1186752319],"type":"Point"}
}