{
  "type": "Feature",
  "properties": {
    "addr:full":"Calle de Santisima Trinidad, 6 Maracena Granada 18200",
    "addr:housenumber":"6",
    "addr:postcode":"18200",
    "addr:street":"Calle De Santisima Trinidad",
    "iso:country":"ES",
    "sg:address":"Calle de Santisima Trinidad, 6",
    "sg:city":"Maracena",
    "sg:orig_category":"Peluqueros: De Se\u00d1oras",
    "sg:phone":"+34 958 41 57 37",
    "sg:postcode":"18200",
    "sg:province":"Granada",
    "wof:name":"Garcia Fernandez Maria Susana",
    "wof:placetype":"venue"
},
  "geometry": {"coordinates":[-3.6349990368,37.2077827454],"type":"Point"}
}