{
  "type": "Feature",
  "properties": {
    "addr:full":"Calle de Saiz De Otero, 8 Zaragoza Zaragoza 50018",
    "addr:housenumber":"8",
    "addr:postcode":"50018",
    "addr:street":"Calle De Saiz De Otero",
    "iso:country":"ES",
    "sg:address":"Calle de Saiz De Otero, 8",
    "sg:city":"Zaragoza",
    "sg:orig_category":"Reposter\u00cdas",
    "sg:phone":"+34 976 73 27 02",
    "sg:postcode":"50018",
    "sg:province":"Zaragoza",
    "wof:name":"Ballestin Ballestin Ana Felicidad",
    "wof:placetype":"venue"
},
  "geometry": {"coordinates":[-0.891685009,41.6703681946],"type":"Point"}
}