{
  "type": "Feature",
  "properties": {
    "iso:country":"ES",
    "sg:address":"Pol. Ind. Can Cortes, S/n",
    "sg:city":"Callus",
    "sg:orig_category":"Delineantes",
    "sg:phone":"+34 938 36 17 00",
    "sg:postcode":"08262",
    "sg:province":"Barcelona",
    "wof:name":"Paper Converting S.l.",
    "wof:placetype":"venue"
},
  "geometry": {"coordinates":[1.7730170488,41.7994041443],"type":"Point"}
}