{
  "type": "Feature",
  "properties": {
    "iso:country":"ES",
    "sg:address":"Calle de Pablo Iglesias, 2",
    "sg:city":"Villargordo",
    "sg:orig_category":"Heladeros",
    "sg:phone":"+34 953 37 77 00",
    "sg:postcode":"23630",
    "sg:province":"Ja\u00e9n",
    "wof:name":"Agudo Sanchez Jose",
    "wof:placetype":"venue"
},
  "geometry": {"coordinates":[-3.7304108143,37.9382781982],"type":"Point"}
}