{
  "type": "Feature",
  "properties": {
    "addr:full":"Tordera (p I Massanes), 8 Massanes Girona 17452",
    "addr:housenumber":"8",
    "addr:postcode":"17452",
    "addr:street":"P I Massanes",
    "iso:country":"ES",
    "sg:address":"Tordera (p I Massanes), 8",
    "sg:city":"Massanes",
    "sg:orig_category":"Materias Pl\u00c1sticas: Productos De Consumo Masivo (fabricaci\u00d3n, Al Por Mayor)",
    "sg:phone":"+34 972 86 41 78",
    "sg:postcode":"17452",
    "sg:province":"Girona",
    "wof:name":"Giperplast S.l.",
    "wof:placetype":"venue"
},
  "geometry": {"coordinates":[2.6517798901,41.7658462524],"type":"Point"}
}