{
  "type": "Feature",
  "properties": {
    "addr:full":"Plza. Victoria, S/n Huescar Granada 18830",
    "addr:housenumber":"/ n",
    "addr:postcode":"18830",
    "addr:street":"Plza. Victoria S",
    "iso:country":"ES",
    "sg:address":"Plza. Victoria, S/n",
    "sg:city":"Huescar",
    "sg:orig_category":"Art\u00cdculos De Regalo (al Por Menor)",
    "sg:phone":"+34 958 74 01 54",
    "sg:postcode":"18830",
    "sg:province":"Granada",
    "wof:name":"Berbel Hernandez Manuel",
    "wof:placetype":"venue"
},
  "geometry": {"coordinates":[-2.5403749943,37.8130683899],"type":"Point"}
}