{
  "type": "Feature",
  "properties": {
    "iso:country":"ES",
    "sg:address":"Avda Roncesvalles, S/n",
    "sg:city":"Olloki",
    "sg:orig_category":"Herramientas Manuales (fabricaci\u00d3n, Al Por Mayor)",
    "sg:phone":"+34 948 33 00 89",
    "sg:postcode":"31699",
    "sg:province":"Navarra",
    "sg:website":"www.bellota.com",
    "wof:name":"Bellota Herramientas",
    "wof:placetype":"venue"
},
  "geometry": {"coordinates":[-1.5716300011,42.8884925842],"type":"Point"}
}