{
  "type": "Feature",
  "properties": {
    "iso:country":"ES",
    "sg:address":"Ptda Casa Blanca, 145",
    "sg:city":"Xara",
    "sg:orig_category":"Centros Empresariales",
    "sg:phone":"+34 966 43 53 86",
    "sg:postcode":"03700",
    "sg:province":"Alicante",
    "wof:name":"Comind Consulting S.l.",
    "wof:placetype":"venue"
},
  "geometry": {"coordinates":[0.1039630026,38.8354949951],"type":"Point"}
}