{
  "type": "Feature",
  "properties": {
    "addr:full":"Calle de Mayor, 24 Daroca Zaragoza 50360",
    "addr:housenumber":"24",
    "addr:postcode":"50360",
    "addr:street":"Calle De Mayor",
    "iso:country":"ES",
    "sg:address":"Calle de Mayor, 24",
    "sg:city":"Daroca",
    "sg:orig_category":"Alimentaci\u00d3n General (al Por Mayor)",
    "sg:phone":"+34 976 80 07 29",
    "sg:postcode":"50360",
    "sg:province":"Zaragoza",
    "wof:name":"Baguena Julian Mariano",
    "wof:placetype":"venue"
},
  "geometry": {"coordinates":[-1.4161250591,41.113368988],"type":"Point"}
}