{
  "type": "Feature",
  "properties": {
    "iso:country":"ES",
    "sg:address":"Ctra Rociana, S/n",
    "sg:city":"Bonares",
    "sg:orig_category":"Agricultura: Abastecimiento Y Cosechado (negocio)",
    "sg:phone":"+34 959 50 05 58",
    "sg:postcode":"21830",
    "sg:province":"Huelva",
    "wof:name":"Francisco Mora Morales S.l.",
    "wof:placetype":"venue"
},
  "geometry": {"coordinates":[-6.6799907684,37.3241653442],"type":"Point"}
}