{
  "type": "Feature",
  "properties": {
    "iso:country":"ES",
    "sg:address":"Avda Maria De Las Mercedes, 1",
    "sg:city":"Alovera",
    "sg:classifiers":[
        {
            "category":"Personal",
            "subcategory":"Barber",
            "type":"Services"
        }
    ],
    "sg:phone":"+34 949 27 57 13",
    "sg:postcode":"19208",
    "sg:province":"Guadalajara",
    "sg:tags":[
        "caballeros",
        "de",
        "peluqueros"
    ],
    "wof:name":"Bertiz Calvo Jesus",
    "wof:placetype":"venue"
},
  "geometry": {"coordinates":[-3.2418730259,40.5984802246],"type":"Point"}
}