{
  "type": "Feature",
  "properties": {
    "addr:full":"Calle de Rector Sichar, 1 Huesca Huesca 22003",
    "addr:housenumber":"1",
    "addr:postcode":"22003",
    "addr:street":"Calle De Rector Sichar",
    "iso:country":"ES",
    "sg:address":"Calle de Rector Sichar, 1",
    "sg:city":"Huesca",
    "sg:orig_category":"Estancos",
    "sg:phone":"+34 974 22 75 83",
    "sg:postcode":"22003",
    "sg:province":"Huesca",
    "wof:name":"Rodriguez Lafuerza Eloy",
    "wof:placetype":"venue"
},
  "geometry": {"coordinates":[-0.4140250087,42.1401596069],"type":"Point"}
}