{
  "type": "Feature",
  "properties": {
    "iso:country":"ES",
    "sg:address":"Calle de Almendro, 3",
    "sg:city":"Guadalajara",
    "sg:orig_category":"Dise\u00d1o Industrial",
    "sg:phone":"+34 949 21 34 06",
    "sg:postcode":"19002",
    "sg:province":"Guadalajara",
    "wof:name":"Arroyo Hernandez Jose Manuel",
    "wof:placetype":"venue"
},
  "geometry": {"coordinates":[-3.1585245132,40.625328064],"type":"Point"}
}