{
  "type": "Feature",
  "properties": {
    "addr:full":"I\u00f1igo Arista, 7 Iru\u00f1a Navarra 31007",
    "addr:housenumber":"7",
    "addr:postcode":"31007",
    "addr:street":"Arista",
    "iso:country":"ES",
    "sg:address":"I\u00f1igo Arista, 7",
    "sg:city":"Iru\u00f1a",
    "sg:orig_category":"Peluquer\u00cdas, Peluquer\u00cda Mixta",
    "sg:phone":"+34 948 17 04 83",
    "sg:postcode":"31007",
    "sg:province":"Navarra",
    "wof:name":"A.r. Peluqueros",
    "wof:placetype":"venue"
},
  "geometry": {"coordinates":[-1.6538414955,42.8072853088],"type":"Point"}
}