{
  "type": "Feature",
  "properties": {
    "addr:full":"Avda Real Fabrica De Sedas, 15 Talavera Reina Toledo 45600",
    "addr:housenumber":"15",
    "addr:postcode":"45600",
    "addr:street":"Avda Real",
    "iso:country":"ES",
    "sg:address":"Avda Real Fabrica De Sedas, 15",
    "sg:city":"Talavera Reina",
    "sg:orig_category":"Asociaciones Humanitarias, De Cooperaci\u00d3n, De Acci\u00d3n Social",
    "sg:phone":"+34 925 81 15 23",
    "sg:postcode":"45600",
    "sg:province":"Toledo",
    "wof:name":"Fundacion Ande",
    "wof:placetype":"venue"
},
  "geometry": {"coordinates":[-4.8355379105,39.9557952881],"type":"Point"}
}