{
  "type": "Feature",
  "properties": {
    "iso:country":"ES",
    "sg:address":"Avda Severino Fernandez, 14",
    "sg:city":"Tafalla",
    "sg:orig_category":"Perfumer\u00cda (al Por Menor)",
    "sg:phone":"+34 948 70 00 21",
    "sg:postcode":"31300",
    "sg:province":"Navarra",
    "wof:name":"Iglesias Bengoa Isabel",
    "wof:placetype":"venue"
},
  "geometry": {"coordinates":[-1.6747380495,42.52734375],"type":"Point"}
}