{
  "type": "Feature",
  "properties": {
    "iso:country":"ES",
    "sg:address":"San J. Bosco, 7",
    "sg:city":"Iru\u00f1a",
    "sg:orig_category":"Transportes Por Carretera: Lotes Completos, Mercanc\u00cdas Diversas",
    "sg:phone":"+34 948 27 12 59",
    "sg:postcode":"31007",
    "sg:province":"Navarra",
    "wof:name":"Irurzun Alegria Jose Maria",
    "wof:placetype":"venue"
},
  "geometry": {"coordinates":[-1.6479300261,42.8058166504],"type":"Point"}
}