{
  "type": "Feature",
  "properties": {
    "iso:country":"ES",
    "sg:address":"Rua Magdalena, 14",
    "sg:city":"Betanzos",
    "sg:orig_category":"Molduras, Junquillos, Listones Y Molduras Perforadas",
    "sg:phone":"+34 981 77 15 54",
    "sg:postcode":"15300",
    "sg:province":"La Coru\u00f1a",
    "wof:name":"Barral Lopez Maria Pilar",
    "wof:placetype":"venue"
},
  "geometry": {"coordinates":[-8.2119092941,43.279914856],"type":"Point"}
}