{
  "type": "Feature",
  "properties": {
    "iso:country":"ES",
    "sg:address":"Carretera De Carcabuey, Km. 0009,1",
    "sg:city":"Rute",
    "sg:orig_category":"Cooperativas Agr\u00cdcolas",
    "sg:phone":"+34 957 53 89 50",
    "sg:postcode":"14960",
    "sg:province":"C\u00f3rdoba",
    "wof:name":"Cooperativa Agricola Virgen Del Castillo",
    "wof:placetype":"venue"
},
  "geometry": {"coordinates":[-4.36434412,37.3276290894],"type":"Point"}
}