{
  "type": "Feature",
  "properties": {
    "addr:full":"Trva Cantabria, 16 Pardavila Pontevedra 36205",
    "addr:housenumber":"16",
    "addr:postcode":"36205",
    "addr:street":"Trva Cantabria",
    "iso:country":"ES",
    "sg:address":"Trva Cantabria, 16",
    "sg:city":"Pardavila",
    "sg:orig_category":"Fabricaci\u00d3n De Jabones, Detergentes Y Lej\u00cdas",
    "sg:phone":"+34 986 25 35 58",
    "sg:postcode":"36205",
    "sg:province":"Pontevedra",
    "wof:name":"Persan S.a.",
    "wof:placetype":"venue"
},
  "geometry": {"coordinates":[-8.70246315,42.2290763855],"type":"Point"}
}