{
  "type": "Feature",
  "properties": {
    "iso:country":"ES",
    "sg:address":"Calle de San Lorenzo, 20",
    "sg:city":"Madrid",
    "sg:orig_category":"Alquiler De Casas Y Habitaciones Amuebladas",
    "sg:phone":"+34 915 21 08 01",
    "sg:postcode":"28004",
    "sg:province":"Madrid",
    "wof:name":"Residencia Patrocinio De San Jose Siervas De San Jose Prov San Agustin",
    "wof:placetype":"venue"
},
  "geometry": {"coordinates":[-3.6991069317,40.4252853394],"type":"Point"}
}