{
  "type": "Feature",
  "properties": {
    "iso:country":"ES",
    "sg:address":"Cno. Viejo, 3",
    "sg:city":"Pulianas",
    "sg:orig_category":"Molduras, Junquillos, Listones Y Molduras Perforadas",
    "sg:phone":"+34 958 42 65 59",
    "sg:postcode":"18197",
    "sg:province":"Granada",
    "wof:name":"Hernandez Lopez Juan De Dios",
    "wof:placetype":"venue"
},
  "geometry": {"coordinates":[-3.6097240448,37.2210998535],"type":"Point"}
}