{
  "type": "Feature",
  "properties": {
    "addr:full":"Rua Montemaior, S/n Verin Ourense 32600",
    "addr:housenumber":"s / n",
    "addr:postcode":"32600",
    "addr:street":"Rua Montemaior",
    "iso:country":"ES",
    "sg:address":"Rua Montemaior, S/n",
    "sg:city":"Verin",
    "sg:orig_category":"Caf\u00c9s, Bares, Cervecer\u00cdas",
    "sg:phone":"+34 988 41 16 70",
    "sg:postcode":"32600",
    "sg:province":"Ourense",
    "wof:name":"Fernandez Ruas Nicanor",
    "wof:placetype":"venue"
},
  "geometry": {"coordinates":[-7.4372239113,41.9398765564],"type":"Point"}
}