{
  "type": "Feature",
  "properties": {
    "iso:country":"ES",
    "sg:address":"Calle de Isabel La Catolica, 40",
    "sg:city":"Sotogrande",
    "sg:orig_category":"Intercambios, Trueques",
    "sg:phone":"+34 956 79 61 94",
    "sg:postcode":"11310",
    "sg:province":"C\u00e1diz",
    "wof:name":"Vega Seis S.l.",
    "wof:placetype":"venue"
},
  "geometry": {"coordinates":[-5.2882261276,36.283996582],"type":"Point"}
}