{
  "type": "Feature",
  "properties": {
    "addr:full":"Plaz Jorge Juan, 1 Denia Alicante 03700",
    "addr:housenumber":"1",
    "addr:postcode":"03700",
    "addr:street":"Juan",
    "iso:country":"ES",
    "sg:address":"Plaz Jorge Juan, 1",
    "sg:city":"Denia",
    "sg:orig_category":"Peluquer\u00cdas, Peluquer\u00cda Mixta",
    "sg:phone":"+34 965 78 78 01",
    "sg:postcode":"03700",
    "sg:province":"Alicante",
    "wof:name":"Salvador Gadea Borras Y Sergio C.b.",
    "wof:placetype":"venue"
},
  "geometry": {"coordinates":[0.1114400029,38.8428153992],"type":"Point"}
}