{
  "type": "Feature",
  "properties": {
    "iso:country":"ES",
    "sg:address":"Calle de Zuloaga, S/n",
    "sg:city":"Fuendetodos",
    "sg:orig_category":"Museos",
    "sg:phone":"+34 976 14 38 30",
    "sg:postcode":"50142",
    "sg:province":"Zaragoza",
    "sg:website":"www.fundetodos.org",
    "wof:name":"Consorcio Cultural Goya-fuendetodos",
    "wof:placetype":"venue"
},
  "geometry": {"coordinates":[-0.959183991,41.3437690735],"type":"Point"}
}