{
  "type": "Feature",
  "properties": {
    "addr:full":"Ctra M-204 (de Ambite), Km. 0005,0 Tielmes Madrid 28550",
    "addr:postcode":"28550",
    "addr:street":"Ctra M-204 De Ambite Km. 0005,0",
    "iso:country":"ES",
    "sg:address":"Ctra M-204 (de Ambite), Km. 0005,0",
    "sg:city":"Tielmes",
    "sg:orig_category":"Producci\u00d3n, Comercio De Cereales",
    "sg:phone":"+34 918 74 67 67",
    "sg:postcode":"28550",
    "sg:province":"Madrid",
    "wof:name":"Cereales Tielmes S.l. Unipersonal",
    "wof:placetype":"venue"
},
  "geometry": {"coordinates":[-3.3143188953,40.2449455261],"type":"Point"}
}