{
  "type": "Feature",
  "properties": {
    "addr:full":"Ctra Cortes (de), Km. 0004,0 Jerez De La Frontera C\u00e1diz 11406",
    "addr:postcode":"11406",
    "addr:street":"Ctra Cortes De Km. 0004,0",
    "iso:country":"ES",
    "sg:address":"Ctra Cortes (de), Km. 0004,0",
    "sg:city":"Jerez De La Frontera",
    "sg:orig_category":"Promotores Constructores",
    "sg:phone":"+34 956 39 77 29",
    "sg:postcode":"11406",
    "sg:province":"C\u00e1diz",
    "wof:name":"Nichos Del Sur S.l.",
    "wof:placetype":"venue"
},
  "geometry": {"coordinates":[-6.1010842323,36.6589164734],"type":"Point"}
}