{
  "type": "Feature",
  "properties": {
    "iso:country":"ES",
    "sg:address":"Calle de Lorenzo Areilza, 2",
    "sg:city":"Algorta",
    "sg:orig_category":"Confecci\u00d3n De Zapatos",
    "sg:phone":"+34 944 60 20 93",
    "sg:postcode":"48993",
    "sg:province":"Vizcaya",
    "wof:name":"Mendivil Alzola S.l.",
    "wof:placetype":"venue"
},
  "geometry": {"coordinates":[-3.0135974884,43.3540000916],"type":"Point"}
}