{
  "type": "Feature",
  "properties": {
    "iso:country":"ES",
    "sg:address":"Avda Alcalde J.elosegi, 140",
    "sg:city":"Donostia-san Sebastian",
    "sg:orig_category":"Equipo De Refrigeraci\u00d3n Industrial",
    "sg:phone":"+34 943 39 56 69",
    "sg:postcode":"20017",
    "sg:province":"Guip\u00f9zcoa",
    "wof:name":"Calle Abad Enrique De La",
    "wof:placetype":"venue"
},
  "geometry": {"coordinates":[-1.9251650572,43.3212585449],"type":"Point"}
}