{
  "type": "Feature",
  "properties": {
    "addr:full":"Carrer de Ignasi Iglesias, 37 Reus Tarragona 43206",
    "addr:housenumber":"37",
    "addr:postcode":"43206",
    "addr:street":"Carrer De Ignasi Iglesias",
    "iso:country":"ES",
    "sg:address":"Carrer de Ignasi Iglesias, 37",
    "sg:city":"Reus",
    "sg:orig_category":"Promotores Constructores",
    "sg:phone":"+34 977 32 29 29",
    "sg:postcode":"43206",
    "sg:province":"Tarragona",
    "wof:name":"Arias I Olive S.l.",
    "wof:placetype":"venue"
},
  "geometry": {"coordinates":[1.1400997639,41.1496086121],"type":"Point"}
}