{
  "type": "Feature",
  "properties": {
    "iso:country":"ES",
    "sg:address":"Calle de Santa Clara, 51",
    "sg:city":"Burgos",
    "sg:orig_category":"Molduras, Junquillos, Listones Y Molduras Perforadas",
    "sg:phone":"+34 947 26 40 91",
    "sg:postcode":"09002",
    "sg:province":"Burgos",
    "wof:name":"Obregon Ortega Luis Manuel",
    "wof:placetype":"venue"
},
  "geometry": {"coordinates":[-3.6930780411,42.3371276855],"type":"Point"}
}