{
  "type": "Feature",
  "properties": {
    "iso:country":"ES",
    "sg:address":"Calle de Padre Romano, 12",
    "sg:city":"Albacete",
    "sg:orig_category":"\u00d3pticos Optometristas (al Por Menor)",
    "sg:phone":"+34 967 52 07 77",
    "sg:postcode":"02005",
    "sg:province":"Albacete",
    "wof:name":"Lopez Cruz Maria",
    "wof:placetype":"venue"
},
  "geometry": {"coordinates":[-1.8569190502,38.9977684021],"type":"Point"}
}