{
  "type": "Feature",
  "properties": {
    "iso:country":"ES",
    "sg:address":"Calle de Heredia, 12",
    "sg:city":"Huesca",
    "sg:orig_category":"Venta, Instalaci\u00d3n, Reparaci\u00d3n De Antenas Para Televisi\u00d3n",
    "sg:phone":"+34 974 22 82 34",
    "sg:postcode":"22001",
    "sg:province":"Huesca",
    "wof:name":"Antonio Rodriguez Torrente S.l.",
    "wof:placetype":"venue"
},
  "geometry": {"coordinates":[-0.4046123028,42.1385726929],"type":"Point"}
}