{
  "type": "Feature",
  "properties": {
    "addr:full":"Calle de San Juan, 15 Medina-sidonia C\u00e1diz 11170",
    "addr:housenumber":"15",
    "addr:postcode":"11170",
    "addr:street":"Calle De San Juan;Ca\u0301Diz",
    "iso:country":"ES",
    "sg:address":"Calle de San Juan, 15",
    "sg:city":"Medina-sidonia",
    "sg:orig_category":"Cajas De Ahorro",
    "sg:phone":"+34 956 41 08 25",
    "sg:postcode":"11170",
    "sg:province":"C\u00e1diz",
    "sg:website":"www.lacaixa.es",
    "wof:name":"Caixa D'estalvis I Pensions De Barcelona",
    "wof:placetype":"venue"
},
  "geometry": {"coordinates":[-5.9280838966,36.4581489563],"type":"Point"}
}