{
  "type": "Feature",
  "properties": {
    "addr:full":"Calle de Ramon Y Cajal, S/n Olula Rio Almer\u00eda 04860",
    "addr:housenumber":"s / n",
    "addr:postcode":"04860",
    "addr:street":"Calle De Ramon Y Cajal;Almeri\u0301A",
    "iso:country":"ES",
    "sg:address":"Calle de Ramon Y Cajal, S/n",
    "sg:city":"Olula Rio",
    "sg:orig_category":"Pintura Y Barniz (al Por Menor)",
    "sg:phone":"+34 950 44 00 42",
    "sg:postcode":"04860",
    "sg:province":"Almer\u00eda",
    "wof:name":"Pintura Y Reformas Indalo S.l.",
    "wof:placetype":"venue"
},
  "geometry": {"coordinates":[-2.2991540432,37.3577804565],"type":"Point"}
}