{
  "type": "Feature",
  "properties": {
    "iso:country":"ES",
    "sg:address":"Carrer de Francesc Layret, 67",
    "sg:city":"Mollet Valles",
    "sg:orig_category":"\u00d3ptica: Instrumentos (fabricaci\u00d3n)",
    "sg:phone":"+34 935 70 42 56",
    "sg:postcode":"08100",
    "sg:province":"Barcelona",
    "wof:name":"Lider Vision S.l.",
    "wof:placetype":"venue"
},
  "geometry": {"coordinates":[2.2032840252,41.5475082397],"type":"Point"}
}