{
  "type": "Feature",
  "properties": {
    "iso:country":"ES",
    "sg:address":"Calle de Compositor Luis Megias, S/n",
    "sg:city":"Granada",
    "sg:orig_category":"Peluqueros: De Se\u00d1oras",
    "sg:phone":"+34 958 12 91 87",
    "sg:postcode":"18006",
    "sg:province":"Granada",
    "wof:name":"Algarra Marquez Maria Encarnacion",
    "wof:placetype":"venue"
},
  "geometry": {"coordinates":[-3.6091170311,37.159488678],"type":"Point"}
}