{
  "type": "Feature",
  "properties": {
    "addr:full":"Calle de Jardines De La Concordia, 9 Zaragoza Zaragoza 50015",
    "addr:housenumber":"9",
    "addr:postcode":"50015",
    "addr:street":"Calle De Jardines De La Concordia",
    "iso:country":"ES",
    "sg:address":"Calle de Jardines De La Concordia, 9",
    "sg:city":"Zaragoza",
    "sg:orig_category":"Papeler\u00cdas, Librer\u00cdas",
    "sg:phone":"+34 976 74 18 53",
    "sg:postcode":"50015",
    "sg:province":"Zaragoza",
    "wof:name":"Gracia Baraza Mari Luz",
    "wof:placetype":"venue"
},
  "geometry": {"coordinates":[-0.8629540205,41.6912841797],"type":"Point"}
}