{
  "type": "Feature",
  "properties": {
    "addr:full":"Carrer de Sant Ramon, 67 Caldes Montbui Barcelona 08140",
    "addr:housenumber":"67",
    "addr:postcode":"08140",
    "addr:street":"Carrer De Sant Ramon;Montbui Barcelona",
    "iso:country":"ES",
    "sg:address":"Carrer de Sant Ramon, 67",
    "sg:city":"Caldes Montbui",
    "sg:orig_category":"Ebanister\u00cda",
    "sg:phone":"+34 938 65 29 60",
    "sg:postcode":"08140",
    "sg:province":"Barcelona",
    "wof:name":"Plaza Bardolet S.l.",
    "wof:placetype":"venue"
},
  "geometry": {"coordinates":[2.1689319611,41.6283569336],"type":"Point"}
}