{
  "type": "Feature",
  "properties": {
    "iso:country":"ES",
    "sg:address":"Barrio De Arganza, S/n",
    "sg:city":"S. Leonardo Yag\u00fce",
    "sg:orig_category":"Serrer\u00cdas De Madera",
    "sg:phone":"+34 975 37 64 75",
    "sg:postcode":"42140",
    "sg:province":"Soria",
    "wof:name":"Hemasa",
    "wof:placetype":"venue"
},
  "geometry": {"coordinates":[-2.4649205208,41.7635993958],"type":"Point"}
}