{
  "type": "Feature",
  "properties": {
    "iso:country":"ES",
    "sg:address":"Calle de Doctor Esquerdo, 20",
    "sg:city":"Madrid",
    "sg:orig_category":"Supermercados Y Hipermercados",
    "sg:phone":"+34 914 01 55 83",
    "sg:postcode":"28007",
    "sg:province":"Madrid",
    "wof:name":"Madrile\u00f1a De Negocios S.a.",
    "wof:placetype":"venue"
},
  "geometry": {"coordinates":[-3.6687877178,40.4254608154],"type":"Point"}
}