{
  "type": "Feature",
  "properties": {
    "addr:full":"Calle de General Espartero, 3 Logro\u00f1o La Rioja 26003",
    "addr:housenumber":"3",
    "addr:postcode":"26003",
    "addr:street":"Calle De General Espartero;Rioja",
    "iso:country":"ES",
    "sg:address":"Calle de General Espartero, 3",
    "sg:city":"Logro\u00f1o",
    "sg:orig_category":"Carnicer\u00cdas, Carnicer\u00cdas",
    "sg:phone":"+34 941 24 51 56",
    "sg:postcode":"26003",
    "sg:province":"La Rioja",
    "wof:name":"Pe\u00f1a Ureta Francisco Javier",
    "wof:placetype":"venue"
},
  "geometry": {"coordinates":[-2.4428339005,42.4589729309],"type":"Point"}
}