{
  "type": "Feature",
  "properties": {
    "addr:full":"Rua Madrid, 2 Sanxenxo Pontevedra 36960",
    "addr:housenumber":"2",
    "addr:postcode":"36960",
    "addr:street":"Rua Madrid",
    "iso:country":"ES",
    "sg:address":"Rua Madrid, 2",
    "sg:city":"Sanxenxo",
    "sg:orig_category":"Doctores En Medicina",
    "sg:phone":"+34 986 72 30 20",
    "sg:postcode":"36960",
    "sg:province":"Pontevedra",
    "wof:name":"Mantilla Gonzalez Miguel Angel",
    "wof:placetype":"venue"
},
  "geometry": {"coordinates":[-8.8000631332,42.4012107849],"type":"Point"}
}