{
  "type": "Feature",
  "properties": {
    "iso:country":"ES",
    "sg:address":"Ctra. Manilva, Km. 0000,2",
    "sg:city":"Manilva",
    "sg:orig_category":"Oficinas De Turismo, Asociaciones De Iniciativa",
    "sg:phone":"+34 952 89 08 45",
    "sg:postcode":"29691",
    "sg:province":"M\u00e1laga",
    "sg:website":"www.ayto-manilva.org",
    "wof:name":"Ayuntamiento De Manilva",
    "wof:placetype":"venue"
},
  "geometry": {"coordinates":[-5.251294136,36.3782348633],"type":"Point"}
}