{
  "type": "Feature",
  "properties": {
    "addr:full":"Av Serrella, 8 Cocentaina Alicante 03820",
    "addr:housenumber":"8",
    "addr:postcode":"03820",
    "addr:street":"Av Serrella",
    "iso:country":"ES",
    "sg:address":"Av Serrella, 8",
    "sg:city":"Cocentaina",
    "sg:orig_category":"Productos Qu\u00cdmicos (fabricaci\u00d3n, Al Por Mayor)",
    "sg:phone":"+34 966 50 02 42",
    "sg:postcode":"03820",
    "sg:province":"Alicante",
    "wof:name":"Francotex S.l.",
    "wof:placetype":"venue"
},
  "geometry": {"coordinates":[-0.4571259916,38.7180976868],"type":"Point"}
}