{
  "type": "Feature",
  "properties": {
    "iso:country":"ES",
    "sg:address":"Avda Condesa Sagasta, 6",
    "sg:city":"Le\u00f3n",
    "sg:orig_category":"M\u00c9dicos: Estomatolog\u00cda",
    "sg:phone":"+34 987 24 73 74",
    "sg:postcode":"24001",
    "sg:province":"Le\u00f3n",
    "wof:name":"Buelga Cuetos Marcelo",
    "wof:placetype":"venue"
},
  "geometry": {"coordinates":[-5.5785498619,42.5975494385],"type":"Point"}
}