{
  "type": "Feature",
  "properties": {
    "iso:country":"ES",
    "sg:address":"Plaz Artesania, 10",
    "sg:city":"Guadalcacin Del Caudillo",
    "sg:orig_category":"Estancos",
    "sg:phone":"+34 956 15 72 74",
    "sg:postcode":"11591",
    "sg:province":"C\u00e1diz",
    "wof:name":"Mu\u00f1oz Giron Rosario",
    "wof:placetype":"venue"
},
  "geometry": {"coordinates":[-6.0885739326,36.7132606506],"type":"Point"}
}