{
  "type": "Feature",
  "properties": {
    "addr:full":"Calle de Barbadillo, 4 Madrid Madrid 28...",
    "addr:housenumber":"4;28 ...",
    "addr:street":"Calle De Barbadillo;Madrid",
    "iso:country":"ES",
    "sg:address":"Calle de Barbadillo, 4",
    "sg:city":"Madrid",
    "sg:orig_category":"Promotores Constructores",
    "sg:phone":"+34 916 78 47 40",
    "sg:postcode":"28...",
    "sg:province":"Madrid",
    "sg:website":"www.grupolabaro.com",
    "wof:name":"Labaro Grupo Inmobiliario S.a.",
    "wof:placetype":"venue"
},
  "geometry": {"coordinates":[-3.6453008652,40.4303779602],"type":"Point"}
}