{
  "type": "Feature",
  "properties": {
    "iso:country":"ES",
    "sg:address":"C/ Estudi, 16",
    "sg:city":"Tarrega",
    "sg:orig_category":"Empresas De Carpinter\u00cda De Madera",
    "sg:phone":"+34 973 31 21 10",
    "sg:postcode":"25300",
    "sg:province":"Lleida",
    "wof:name":"Albareda Rialp Jaume",
    "wof:placetype":"venue"
},
  "geometry": {"coordinates":[1.1401215792,41.6454811096],"type":"Point"}
}