{
  "type": "Feature",
  "properties": {
    "iso:country":"ES",
    "sg:address":"Avda Constitucion, 8",
    "sg:city":"Padul",
    "sg:orig_category":"Maquinaria Para Industrias Diversas",
    "sg:phone":"+34 958 79 02 02",
    "sg:postcode":"18640",
    "sg:province":"Granada",
    "wof:name":"Arias Arias Joaquin",
    "wof:placetype":"venue"
},
  "geometry": {"coordinates":[-3.6306378841,37.0215530396],"type":"Point"}
}