{
  "type": "Feature",
  "properties": {
    "addr:full":"Avda Domingo Bueno, 12 Pontenova Pontevedra 36400",
    "addr:housenumber":"12",
    "addr:postcode":"36400",
    "addr:street":"Avda Domingo Bueno",
    "iso:country":"ES",
    "sg:address":"Avda Domingo Bueno, 12",
    "sg:city":"Pontenova",
    "sg:orig_category":"M\u00c9dicos: Medicina General",
    "sg:phone":"+34 986 33 43 30",
    "sg:postcode":"36400",
    "sg:province":"Pontevedra",
    "wof:name":"Odontos Clinica Dental",
    "wof:placetype":"venue"
},
  "geometry": {"coordinates":[-8.6179990768,42.1610298157],"type":"Point"}
}