{
  "type": "Feature",
  "properties": {
    "addr:full":"Nueve De Agosto, 5 Ribeira-santa Uxia A Coru\u00f1a 15960",
    "addr:housenumber":"5",
    "addr:postcode":"15960",
    "addr:street":"Nueve De Agosto;Uxia;Corun\u0303A",
    "iso:country":"ES",
    "sg:address":"Nueve De Agosto, 5",
    "sg:city":"Ribeira-santa Uxia",
    "sg:orig_category":"Camiser\u00cda Y Ropa Interior Masculina (al Por Menor)",
    "sg:phone":"+34 981 87 46 42",
    "sg:postcode":"15960",
    "sg:province":"A Coru\u00f1a",
    "wof:name":"Vidal Vila Maria",
    "wof:placetype":"venue"
},
  "geometry": {"coordinates":[-8.9940919876,42.554889679],"type":"Point"}
}