{
  "type": "Feature",
  "properties": {
    "addr:full":"Urb. Los Almendros, 15 Zamora Zamora 49005",
    "addr:housenumber":"15",
    "addr:postcode":"49005",
    "addr:street":"Los Almendros",
    "iso:country":"ES",
    "sg:address":"Urb. Los Almendros, 15",
    "sg:city":"Zamora",
    "sg:orig_category":"Caf\u00c9s, Bares, Cervecer\u00cdas",
    "sg:phone":"+34 980 51 00 73",
    "sg:postcode":"49005",
    "sg:province":"Zamora",
    "wof:name":"Cafe Bar Zalomar S.l.",
    "wof:placetype":"venue"
},
  "geometry": {"coordinates":[-6.6216888428,42.0623054504],"type":"Point"}
}