{
  "type": "Feature",
  "properties": {
    "addr:full":"Calle de Empedrada, 10 Vegadeo Asturias 33770",
    "addr:housenumber":"10",
    "addr:postcode":"33770",
    "addr:street":"Calle De Empedrada",
    "iso:country":"ES",
    "sg:address":"Calle de Empedrada, 10",
    "sg:city":"Vegadeo",
    "sg:orig_category":"Muebles, Minoristas",
    "sg:phone":"+34 985 63 41 92",
    "sg:postcode":"33770",
    "sg:province":"Asturias",
    "wof:name":"Muebles Amor S.a",
    "wof:placetype":"venue"
},
  "geometry": {"coordinates":[-7.0480651855,43.4648551941],"type":"Point"}
}