{
  "type": "Feature",
  "properties": {
    "addr:full":"Calle de Garzon, 22 Corral Almaguer Toledo 45880",
    "addr:housenumber":"22",
    "addr:postcode":"45880",
    "addr:street":"Calle De Garzon",
    "iso:country":"ES",
    "sg:address":"Calle de Garzon, 22",
    "sg:city":"Corral Almaguer",
    "sg:orig_category":"Producci\u00d3n, Comercio De Cereales",
    "sg:phone":"+34 925 19 10 16",
    "sg:postcode":"45880",
    "sg:province":"Toledo",
    "wof:name":"Cereales Corral De Almaguer S.l.",
    "wof:placetype":"venue"
},
  "geometry": {"coordinates":[-3.1657299995,39.7634315491],"type":"Point"}
}