{
  "type": "Feature",
  "properties": {
    "addr:full":"Calle de Mayor, 9 San Vicente Del Raspeig-sant Vicent Del Raspeig Alicante 03690",
    "addr:housenumber":"9",
    "addr:postcode":"03690",
    "addr:street":"Calle De Mayor",
    "iso:country":"ES",
    "sg:address":"Calle de Mayor, 9",
    "sg:city":"San Vicente Del Raspeig-sant Vicent Del Raspeig",
    "sg:orig_category":"Estancos",
    "sg:phone":"+34 965 66 11 75",
    "sg:postcode":"03690",
    "sg:province":"Alicante",
    "wof:name":"Pla Garcia Jose Antonio",
    "wof:placetype":"venue"
},
  "geometry": {"coordinates":[-0.5248090029,38.3958702087],"type":"Point"}
}