{
  "type": "Feature",
  "properties": {
    "addr:full":"Rbla Joaquim Vayreda, 61 Gava Barcelona 08850",
    "addr:housenumber":"61",
    "addr:postcode":"08850",
    "addr:street":"Rbla Joaquim Vayreda",
    "iso:country":"ES",
    "sg:address":"Rbla Joaquim Vayreda, 61",
    "sg:city":"Gava",
    "sg:orig_category":"Panader\u00cdas, Panader\u00cdas",
    "sg:phone":"+34 936 62 02 75",
    "sg:postcode":"08850",
    "sg:province":"Barcelona",
    "wof:name":"Navarro Riera Enrique",
    "wof:placetype":"venue"
},
  "geometry": {"coordinates":[2.007133007,41.3054008484],"type":"Point"}
}