{
  "type": "Feature",
  "properties": {
    "addr:full":"Real, S/n Los Corrales Burgos 09219",
    "addr:housenumber":"s / n",
    "addr:postcode":"09219",
    "addr:street":"Real",
    "iso:country":"ES",
    "sg:address":"Real, S/n",
    "sg:city":"Los Corrales",
    "sg:orig_category":"Centros De Coordinaci\u00d3n",
    "sg:phone":"+34 947 32 17 57",
    "sg:postcode":"09219",
    "sg:province":"Burgos",
    "wof:name":"Alavesa De Cobros S.l.",
    "wof:placetype":"venue"
},
  "geometry": {"coordinates":[-4.0475916862,41.6730880737],"type":"Point"}
}