{
  "type": "Feature",
  "properties": {
    "iso:country":"ES",
    "sg:address":"Calle de Medico Anastasio Escudero Ruiz, S/n",
    "sg:city":"Arucas",
    "sg:orig_category":"Promotores Constructores",
    "sg:phone":"+34 928 62 34 06",
    "sg:postcode":"35400",
    "sg:province":"Las Palmas",
    "wof:name":"Coherle S.l.",
    "wof:placetype":"venue"
},
  "geometry": {"coordinates":[-15.5152540207,28.1135654449],"type":"Point"}
}