{
  "type": "Feature",
  "properties": {
    "iso:country":"ES",
    "sg:address":"Calle de Nardos (de Los), 4",
    "sg:city":"Fuenlabrada",
    "sg:orig_category":"Peluqueros: De Se\u00d1oras",
    "sg:phone":"+34 916 15 27 52",
    "sg:postcode":"28941",
    "sg:province":"Madrid",
    "wof:name":"Moreno Mendoza Cristina",
    "wof:placetype":"venue"
},
  "geometry": {"coordinates":[-3.7991960049,40.286819458],"type":"Point"}
}