{
  "type": "Feature",
  "properties": {
    "addr:full":"Calle de Victor Andres Belaunde, 9 Madrid Madrid 28016",
    "addr:housenumber":"9",
    "addr:postcode":"madrid;28016",
    "addr:street":"Calle De Victor Andres Belaunde",
    "iso:country":"ES",
    "sg:address":"Calle de Victor Andres Belaunde, 9",
    "sg:city":"Madrid",
    "sg:orig_category":"Molduras, Junquillos, Listones Y Molduras Perforadas",
    "sg:phone":"+34 913 44 19 22",
    "sg:postcode":"28016",
    "sg:province":"Madrid",
    "wof:name":"Jose Maria Carretero S.l.",
    "wof:placetype":"venue"
},
  "geometry": {"coordinates":[-3.6793990135,40.4546279907],"type":"Point"}
}