{
  "type": "Feature",
  "properties": {
    "addr:full":"Av Granvia, 3 Hospitalet Llobregat Barcelona 08908",
    "addr:housenumber":"3",
    "addr:postcode":"08908",
    "addr:street":"Av Granvia",
    "iso:country":"ES",
    "sg:address":"Av Granvia, 3",
    "sg:city":"Hospitalet Llobregat",
    "sg:orig_category":"Goma: Productos De Uso Industrial (fabricaci\u00d3n, Al Por Mayor)",
    "sg:phone":"+34 934 22 83 82",
    "sg:postcode":"08908",
    "sg:province":"Barcelona",
    "wof:name":"Barrera Garcia Helios",
    "wof:placetype":"venue"
},
  "geometry": {"coordinates":[2.1339640617,41.3632087708],"type":"Point"}
}