{
  "type": "Feature",
  "properties": {
    "iso:country":"ES",
    "sg:address":"Mcdo De Catalu\u00f1a, 26",
    "sg:city":"Zaragoza",
    "sg:orig_category":"Pescader\u00cdas (al Por Menor)",
    "sg:phone":"+34 976 29 58 96",
    "sg:postcode":"50014",
    "sg:province":"Zaragoza",
    "wof:name":"Peco Melendez Maria Azucena",
    "wof:placetype":"venue"
},
  "geometry": {"coordinates":[-0.8708130121,41.6593589783],"type":"Point"}
}