{
  "type": "Feature",
  "properties": {
    "iso:country":"ES",
    "sg:address":"Calle de Marchante, 9",
    "sg:city":"Jumilla",
    "sg:orig_category":"Partidos Pol\u00cdticos",
    "sg:phone":"+34 968 75 63 32",
    "sg:postcode":"30520",
    "sg:province":"Murcia",
    "wof:name":"Partido Socialista Obrero Espaool",
    "wof:placetype":"venue"
},
  "geometry": {"coordinates":[-1.3307590485,38.4762802124],"type":"Point"}
}