{
  "type": "Feature",
  "properties": {
    "iso:country":"ES",
    "sg:address":"Avda Jose Antonio, 56",
    "sg:city":"Barbate",
    "sg:orig_category":"Papeler\u00cdas, Librer\u00cdas",
    "sg:phone":"+34 956 43 02 32",
    "sg:postcode":"11160",
    "sg:province":"C\u00e1diz",
    "wof:name":"Silva Tirado Oliva",
    "wof:placetype":"venue"
},
  "geometry": {"coordinates":[-5.9168138504,36.1922721863],"type":"Point"}
}