{
  "type": "Feature",
  "properties": {
    "addr:full":"Avda Santiago Puig, S/n Playa Americas Santa Cruz De Tenerife 38660",
    "addr:housenumber":"s / n",
    "addr:postcode":"38660",
    "addr:street":"Avda Santiago Puig;Americas",
    "iso:country":"ES",
    "sg:address":"Avda Santiago Puig, S/n",
    "sg:city":"Playa Americas",
    "sg:orig_category":"Supermercados Y Hipermercados",
    "sg:phone":"+34 922 79 47 14",
    "sg:postcode":"38660",
    "sg:province":"Santa Cruz De Tenerife",
    "wof:name":"Yayi Lorenzo S.l.",
    "wof:placetype":"venue"
},
  "geometry": {"coordinates":[-16.7292232513,28.0618228912],"type":"Point"}
}