{
  "type": "Feature",
  "properties": {
    "addr:full":"Calle de San Bernardo, 1 Alcala Henares Madrid 28801",
    "addr:housenumber":"1",
    "addr:postcode":"28801",
    "addr:street":"Calle De San Bernardo",
    "iso:country":"ES",
    "sg:address":"Calle de San Bernardo, 1",
    "sg:city":"Alcala Henares",
    "sg:orig_category":"Muebles, Minoristas",
    "sg:phone":"+34 918 82 60 70",
    "sg:postcode":"28801",
    "sg:province":"Madrid",
    "wof:name":"Doria Mobiliario S.l.",
    "wof:placetype":"venue"
},
  "geometry": {"coordinates":[-3.3693189621,40.4829711914],"type":"Point"}
}