{
  "type": "Feature",
  "properties": {
    "addr:full":"Calle de Recaredo, 19 Sevilla Sevilla 41003",
    "addr:housenumber":"19",
    "addr:postcode":"41003",
    "addr:street":"Calle De Recaredo",
    "iso:country":"ES",
    "sg:address":"Calle de Recaredo, 19",
    "sg:city":"Sevilla",
    "sg:orig_category":"Comunidades Religiosas",
    "sg:phone":"+34 954 41 22 57",
    "sg:postcode":"41003",
    "sg:province":"Sevilla",
    "wof:name":"Hermandad De Los Negritos",
    "wof:placetype":"venue"
},
  "geometry": {"coordinates":[-5.984164238,37.3909721375],"type":"Point"}
}