{
  "type": "Feature",
  "properties": {
    "iso:country":"ES",
    "sg:address":"Plaz Puerta De Jerez, 2",
    "sg:city":"Sevilla",
    "sg:orig_category":"Promotores Constructores",
    "sg:phone":"+34 954 21 29 19",
    "sg:postcode":"41004",
    "sg:province":"Sevilla",
    "wof:name":"Construcciones Sebastian Fernandez S.l.",
    "wof:placetype":"venue"
},
  "geometry": {"coordinates":[-5.993142128,37.3824462891],"type":"Point"}
}