{
  "type": "Feature",
  "properties": {
    "addr:full":"Calle de Lasierra Purroy, 45 Zaragoza Zaragoza 50007",
    "addr:housenumber":"45",
    "addr:postcode":"50007",
    "addr:street":"Calle De Lasierra Purroy",
    "iso:country":"ES",
    "sg:address":"Calle de Lasierra Purroy, 45",
    "sg:city":"Zaragoza",
    "sg:orig_category":"Pescader\u00cdas (al Por Menor)",
    "sg:phone":"+34 976 38 00 20",
    "sg:postcode":"50007",
    "sg:province":"Zaragoza",
    "wof:name":"Quintana Benedi Eduardo",
    "wof:placetype":"venue"
},
  "geometry": {"coordinates":[-0.8839290142,41.6288108826],"type":"Point"}
}