{
  "type": "Feature",
  "properties": {
    "iso:country":"ES",
    "sg:address":"Avda Navarra De, 24",
    "sg:city":"Donostia-san Sebastian",
    "sg:orig_category":"Tapicer\u00cdas",
    "sg:phone":"+34 943 29 08 63",
    "sg:postcode":"20013",
    "sg:province":"Guip\u00f9zcoa",
    "wof:name":"Lucas Erro Jose Angel",
    "wof:placetype":"venue"
},
  "geometry": {"coordinates":[-1.9692490101,43.3244018555],"type":"Point"}
}