{
  "type": "Feature",
  "properties": {
    "iso:country":"ES",
    "sg:address":"Ctra Cardedeu, Km. 0001,0",
    "sg:city":"Corro D'avall",
    "sg:orig_category":"Maquinaria Para Industrias Diversas",
    "sg:phone":"+34 938 49 53 61",
    "sg:postcode":"08520",
    "sg:province":"Barcelona",
    "wof:name":"Farres Domenech Jaime",
    "wof:placetype":"venue"
},
  "geometry": {"coordinates":[2.2960968018,41.6180877686],"type":"Point"}
}