{
  "type": "Feature",
  "properties": {
    "addr:full":"Avgd Marti Pujol, 75 Badalona Barcelona 08912",
    "addr:housenumber":"75",
    "addr:postcode":"08912",
    "addr:street":"Pujol",
    "iso:country":"ES",
    "sg:address":"Avgd Marti Pujol, 75",
    "sg:city":"Badalona",
    "sg:orig_category":"Peluquer\u00cdas, Peluquer\u00cda Mixta",
    "sg:phone":"+34 933 84 26 62",
    "sg:postcode":"08912",
    "sg:province":"Barcelona",
    "wof:name":"Albert Roca Ana Maria",
    "wof:placetype":"venue"
},
  "geometry": {"coordinates":[2.247095108,41.4476165771],"type":"Point"}
}