{
  "type": "Feature",
  "properties": {
    "iso:country":"ES",
    "sg:address":"Calle de Juan Valera, 29",
    "sg:city":"Baena",
    "sg:orig_category":"Arreglo, Reparaci\u00d3n, Piezas Sueltas De Televisi\u00d3n, V\u00cddeo, Hi",
    "sg:phone":"+34 957 67 01 26",
    "sg:postcode":"14850",
    "sg:province":"C\u00f3rdoba",
    "wof:name":"Cruz Caballero Francisco",
    "wof:placetype":"venue"
},
  "geometry": {"coordinates":[-4.3230090141,37.6140899658],"type":"Point"}
}