{
  "type": "Feature",
  "properties": {
    "iso:country":"ES",
    "sg:address":"Carr Industria, 94",
    "sg:city":"Badalona",
    "sg:orig_category":"Electricidad: Instaladores",
    "sg:phone":"+34 933 83 64 07",
    "sg:postcode":"08912",
    "sg:province":"Barcelona",
    "wof:name":"Reparaciones Electricas E Instalaciones S. A.",
    "wof:placetype":"venue"
},
  "geometry": {"coordinates":[2.2444651127,41.4431228638],"type":"Point"}
}