{
  "type": "Feature",
  "properties": {
    "iso:country":"ES",
    "sg:address":"Avgd Congres Eucaristic, S/n",
    "sg:city":"Badalona",
    "sg:orig_category":"Ahumados Y Salazones",
    "sg:phone":"+34 933 99 10 57",
    "sg:postcode":"08918",
    "sg:province":"Barcelona",
    "wof:name":"Ros Cercos Vicente",
    "wof:placetype":"venue"
},
  "geometry": {"coordinates":[2.2297399044,41.4361381531],"type":"Point"}
}