{
  "type": "Feature",
  "properties": {
    "iso:country":"ES",
    "sg:address":"Carrer de Jesus, 25",
    "sg:city":"Reus",
    "sg:orig_category":"Bisuteros (fabricaci\u00d3n, Al Por Mayor)",
    "sg:phone":"+34 977 34 35 07",
    "sg:postcode":"43201",
    "sg:province":"Tarragona",
    "wof:name":"Juan Antonio Alcazar Y Cia",
    "wof:placetype":"venue"
},
  "geometry": {"coordinates":[1.1077879667,41.1544570923],"type":"Point"}
}