{
  "type": "Feature",
  "properties": {
    "iso:country":"ES",
    "sg:address":"Ptge Nogues, 51",
    "sg:city":"Barcelona",
    "sg:orig_category":"Mec\u00c1nico Del Autom\u00d3vil",
    "sg:phone":"+34 932 84 30 77",
    "sg:postcode":"08025",
    "sg:province":"Barcelona",
    "wof:name":"Busquets Royo David",
    "wof:placetype":"venue"
},
  "geometry": {"coordinates":[2.1654551029,41.408531189],"type":"Point"}
}