{
  "type": "Feature",
  "properties": {
    "addr:full":"Carr Sant Domenec, De, 4 Carcaixent Valencia 46740",
    "addr:housenumber":"4",
    "addr:postcode":"46740",
    "addr:street":"Carr Sant Domenec De",
    "iso:country":"ES",
    "sg:address":"Carr Sant Domenec, De, 4",
    "sg:city":"Carcaixent",
    "sg:orig_category":"Supermercados Y Hipermercados",
    "sg:phone":"+34 962 46 71 69",
    "sg:postcode":"46740",
    "sg:province":"Valencia",
    "wof:name":"Distribuidora Internacional De Alimentacion S.a.",
    "wof:placetype":"venue"
},
  "geometry": {"coordinates":[-0.4498789907,39.1257591248],"type":"Point"}
}