{
  "type": "Feature",
  "properties": {
    "addr:full":"Carr Sant Josep, 7 Castell Islas Baleares 07720",
    "addr:housenumber":"7",
    "addr:postcode":"07720",
    "addr:street":"Carr Sant Josep",
    "iso:country":"ES",
    "sg:address":"Carr Sant Josep, 7",
    "sg:city":"Castell",
    "sg:orig_category":"Pescader\u00cdas (al Por Menor)",
    "sg:phone":"+34 971 35 48 51",
    "sg:postcode":"07720",
    "sg:province":"Islas Baleares",
    "wof:name":"Pons Pons Jose",
    "wof:placetype":"venue"
},
  "geometry": {"coordinates":[4.2850251198,39.8720703125],"type":"Point"}
}