{
  "type": "Feature",
  "properties": {
    "addr:full":"Carrer de Muntaner, 10 Barcelona Barcelona 08011",
    "addr:housenumber":"10",
    "addr:postcode":"08011",
    "addr:street":"Carrer De Muntaner",
    "iso:country":"ES",
    "sg:address":"Carrer de Muntaner, 10",
    "sg:city":"Barcelona",
    "sg:orig_category":"Molduras, Junquillos, Listones Y Molduras Perforadas",
    "sg:phone":"+34 933 23 29 49",
    "sg:postcode":"08011",
    "sg:province":"Barcelona",
    "wof:name":"Meijide Carballo Jose",
    "wof:placetype":"venue"
},
  "geometry": {"coordinates":[2.1627459526,41.3842964172],"type":"Point"}
}