{
  "type": "Feature",
  "properties": {
    "addr:full":"Calle de Bolsillo De Santa Paula, 2 Granada Granada 18001",
    "addr:housenumber":"2",
    "addr:postcode":"18001",
    "addr:street":"Calle De Bolsillo De Santa Paula",
    "iso:country":"ES",
    "sg:address":"Calle de Bolsillo De Santa Paula, 2",
    "sg:city":"Granada",
    "sg:orig_category":"Inform\u00c1tica, Ofim\u00c1tica (estudios, Asesor\u00cda, Ingenier\u00cda, Formaci\u00d3n)",
    "sg:phone":"+34 958 80 52 45",
    "sg:postcode":"18001",
    "sg:province":"Granada",
    "wof:name":"Ayfaedes S.coop.and",
    "wof:placetype":"venue"
},
  "geometry": {"coordinates":[-3.6002800465,37.1791305542],"type":"Point"}
}