{
  "type": "Feature",
  "properties": {
    "iso:country":"ES",
    "sg:address":"Carrer de Alfons El Savi, 7",
    "sg:city":"Palma",
    "sg:orig_category":"Transporte En General",
    "sg:phone":"+34 971 29 38 11",
    "sg:postcode":"07010",
    "sg:province":"Islas Baleares",
    "wof:name":"Comercial Bamexpa S.l.",
    "wof:placetype":"venue"
},
  "geometry": {"coordinates":[2.6484160423,39.5890808105],"type":"Point"}
}