{
  "type": "Feature",
  "properties": {
    "addr:full":"Carr Pare Sanahuja, 7 Balaguer Lleida 25600",
    "addr:housenumber":"7",
    "addr:postcode":"25600",
    "addr:street":"Carr Pare Sanahuja",
    "iso:country":"ES",
    "sg:address":"Carr Pare Sanahuja, 7",
    "sg:city":"Balaguer",
    "sg:orig_category":"Muebles, Minoristas",
    "sg:phone":"+34 973 44 55 08",
    "sg:postcode":"25600",
    "sg:province":"Lleida",
    "wof:name":"Mobles Claverol S.c.p.",
    "wof:placetype":"venue"
},
  "geometry": {"coordinates":[0.8085669875,41.7904968262],"type":"Point"}
}