{
  "type": "Feature",
  "properties": {
    "addr:full":"Fustanes, 25 Fustans Ourense 32212",
    "addr:housenumber":"25",
    "addr:postcode":"32212",
    "addr:street":"Fustanes",
    "iso:country":"ES",
    "sg:address":"Fustanes, 25",
    "sg:city":"Fustans",
    "sg:orig_category":"Cajas De Ahorro",
    "sg:phone":"+34 988 48 50 30",
    "sg:postcode":"32212",
    "sg:province":"Ourense",
    "sg:website":"www.caixanova.es",
    "wof:name":"Caixa De Aforros De Vigo Ourense E Pontevedra",
    "wof:placetype":"venue"
},
  "geometry": {"coordinates":[-8.1117248535,42.1979064941],"type":"Point"}
}