{
  "type": "Feature",
  "properties": {
    "iso:country":"ES",
    "sg:address":"Carrer de Proven\u00c7a, 120",
    "sg:city":"Barcelona",
    "sg:orig_category":"Psic\u00d3logos",
    "sg:phone":"+34 933 22 08 88",
    "sg:postcode":"08029",
    "sg:province":"Barcelona",
    "wof:name":"Fundacion Privada Copsa",
    "wof:placetype":"venue"
},
  "geometry": {"coordinates":[2.1499180794,41.3858413696],"type":"Point"}
}