{
  "type": "Feature",
  "properties": {
    "addr:full":"Calle de Adeodato Altamirano, 15 Velez-malaga M\u00e1laga 29700",
    "addr:housenumber":"15",
    "addr:postcode":"29700",
    "addr:street":"Calle De Adeodato Altamirano",
    "iso:country":"ES",
    "sg:address":"Calle de Adeodato Altamirano, 15",
    "sg:city":"Velez-malaga",
    "sg:orig_category":"Molduras, Junquillos, Listones Y Molduras Perforadas",
    "sg:phone":"+34 952 50 80 05",
    "sg:postcode":"29700",
    "sg:province":"M\u00e1laga",
    "wof:name":"Cabello Martin Manuel",
    "wof:placetype":"venue"
},
  "geometry": {"coordinates":[-4.1017155647,36.7771835327],"type":"Point"}
}