{
  "type": "Feature",
  "properties": {
    "addr:full":"Calle de Hernan Cortes, 39 Merida Badajoz 06800",
    "addr:housenumber":"39",
    "addr:postcode":"06800",
    "addr:street":"Calle De Hernan Cortes",
    "iso:country":"ES",
    "sg:address":"Calle de Hernan Cortes, 39",
    "sg:city":"Merida",
    "sg:orig_category":"Pod\u00d3logos: Pedicuros",
    "sg:phone":"+34 924 33 03 30",
    "sg:postcode":"06800",
    "sg:province":"Badajoz",
    "wof:name":"Acedo Ca\u00f1amero Maria",
    "wof:placetype":"venue"
},
  "geometry": {"coordinates":[-6.3402891159,38.9168624878],"type":"Point"}
}