{
  "type": "Feature",
  "properties": {
    "iso:country":"ES",
    "sg:address":"Nueva, 14",
    "sg:city":"Caniles",
    "sg:orig_category":"Estancos",
    "sg:phone":"+34 958 71 03 33",
    "sg:postcode":"18810",
    "sg:province":"Granada",
    "wof:name":"Amat Marin Jose Maria",
    "wof:placetype":"venue"
},
  "geometry": {"coordinates":[-2.7236945629,37.4355888367],"type":"Point"}
}