{
  "type": "Feature",
  "properties": {
    "iso:country":"ES",
    "sg:address":"Nande(san Felix De Sales), 2",
    "sg:city":"S.xian De Sales",
    "sg:orig_category":"Bebidas",
    "sg:phone":"+34 981 51 15 55",
    "sg:postcode":"15885",
    "sg:province":"La Coru\u00f1a",
    "wof:name":"Bual S.c.",
    "wof:placetype":"venue"
},
  "geometry": {"coordinates":[-8.481803894,42.7759590149],"type":"Point"}
}