{
  "type": "Feature",
  "properties": {
    "addr:full":"Calle de Alonso Cano, 1 Rota C\u00e1diz 11520",
    "addr:housenumber":"1",
    "addr:postcode":"11520",
    "addr:street":"Calle De Alonso Cano;Ca\u0301Diz",
    "iso:country":"ES",
    "sg:address":"Calle de Alonso Cano, 1",
    "sg:city":"Rota",
    "sg:orig_category":"Droguer\u00cdas (al Por Menor)",
    "sg:phone":"+34 956 81 50 73",
    "sg:postcode":"11520",
    "sg:province":"C\u00e1diz",
    "wof:name":"Iniesta Zafra Juan Luis",
    "wof:placetype":"venue"
},
  "geometry": {"coordinates":[-6.3608202934,36.6229553223],"type":"Point"}
}