{
  "type": "Feature",
  "properties": {
    "iso:country":"ES",
    "sg:address":"Calle de Jose M. Salaberria, 41",
    "sg:city":"Donostia-san Sebastian",
    "sg:orig_category":"Cl\u00cdnicas Dentales",
    "sg:phone":"+34 943 46 88 82",
    "sg:postcode":"20010",
    "sg:province":"Guip\u00f9zcoa",
    "wof:name":"Aguirre Heriz Amaya",
    "wof:placetype":"venue"
},
  "geometry": {"coordinates":[-1.9802999496,43.3036499023],"type":"Point"}
}