{
  "type": "Feature",
  "properties": {
    "addr:full":"Arriaga Bailara, 1 Elgoibar Guip\u00f9zcoa 20870",
    "addr:housenumber":"1",
    "addr:postcode":"20870",
    "addr:street":"Arriaga Bailara;Guipu\u0300Zcoa",
    "iso:country":"ES",
    "sg:address":"Arriaga Bailara, 1",
    "sg:city":"Elgoibar",
    "sg:orig_category":"Empresas De Carpinter\u00cda De Madera",
    "sg:phone":"+34 943 74 85 27",
    "sg:postcode":"20870",
    "sg:province":"Guip\u00f9zcoa",
    "wof:name":"Arin C.b",
    "wof:placetype":"venue"
},
  "geometry": {"coordinates":[-2.4138290882,43.2163581848],"type":"Point"}
}