{
  "type": "Feature",
  "properties": {
    "addr:full":"Rua Ni\u00d1os, S/n Bastiagueiro La Coru\u00f1a 15172",
    "addr:housenumber":"s",
    "addr:postcode":"15172",
    "addr:street":"Rua Nin\u0303Os;/ N Bastiagueiro La Corun\u0303A",
    "iso:country":"ES",
    "sg:address":"Rua Ni\u00d1os, S/n",
    "sg:city":"Bastiagueiro",
    "sg:orig_category":"Electricidad: Instaladores",
    "sg:phone":"+34 981 63 56 29",
    "sg:postcode":"15172",
    "sg:province":"La Coru\u00f1a",
    "wof:name":"Encinas Garcia Julian",
    "wof:placetype":"venue"
},
  "geometry": {"coordinates":[-8.3740053177,43.3324584961],"type":"Point"}
}