{
  "type": "Feature",
  "properties": {
    "addr:full":"Calle de Dulcinea, 11 Puebla Almoradiel Toledo 45840",
    "addr:housenumber":"11",
    "addr:postcode":"45840",
    "addr:street":"Calle De Dulcinea;Almoradiel",
    "iso:country":"ES",
    "sg:address":"Calle de Dulcinea, 11",
    "sg:city":"Puebla Almoradiel",
    "sg:orig_category":"Asesor\u00cda De Formaci\u00d3n Y Gesti\u00d3n De Personal",
    "sg:phone":"+34 925 17 88 43",
    "sg:postcode":"45840",
    "sg:province":"Toledo",
    "wof:name":"Asesoria Europa Mundo S.l.",
    "wof:placetype":"venue"
},
  "geometry": {"coordinates":[-3.1086182594,39.5968856812],"type":"Point"}
}