{
  "type": "Feature",
  "properties": {
    "iso:country":"ES",
    "sg:address":"Carr Angel Guimera, 76",
    "sg:city":"Badalona",
    "sg:orig_category":"Molduras, Junquillos, Listones Y Molduras Perforadas",
    "sg:phone":"+34 933 88 14 15",
    "sg:postcode":"08917",
    "sg:province":"Barcelona",
    "wof:name":"La Cuna Del Genil S.c.p",
    "wof:placetype":"venue"
},
  "geometry": {"coordinates":[2.2367660999,41.4525375366],"type":"Point"}
}