{
  "type": "Feature",
  "properties": {
    "iso:country":"ES",
    "sg:address":"Calle de Fortunato Arias, 9",
    "sg:city":"Hellin",
    "sg:orig_category":"Papeler\u00cdas: Art\u00cdculos (al Por Mayor)",
    "sg:phone":"+34 967 30 35 77",
    "sg:postcode":"02400",
    "sg:province":"Albacete",
    "wof:name":"Ance 1998,sl",
    "wof:placetype":"venue"
},
  "geometry": {"coordinates":[-1.6961610317,38.5072784424],"type":"Point"}
}