{
  "type": "Feature",
  "properties": {
    "iso:country":"ES",
    "sg:address":"Rua Manuel Rodriguez, 49",
    "sg:city":"Porri\u00f1o",
    "sg:orig_category":"Electrodom\u00c9sticos (al Por Menor)",
    "sg:phone":"+34 986 33 78 15",
    "sg:postcode":"36400",
    "sg:province":"Pontevedra",
    "wof:name":"Rodriguez Presa Maria Jose",
    "wof:placetype":"venue"
},
  "geometry": {"coordinates":[-8.6206235886,42.1582183838],"type":"Point"}
}