{
  "type": "Feature",
  "properties": {
    "addr:full":"Carrer de Industria, 17 Barcelona Barcelona 08037",
    "addr:housenumber":"17",
    "addr:postcode":"08037",
    "addr:street":"Carrer De Industria",
    "iso:country":"ES",
    "sg:address":"Carrer de Industria, 17",
    "sg:city":"Barcelona",
    "sg:orig_category":"Asociaciones Y Clubs Deportivos",
    "sg:phone":"+34 932 07 05 18",
    "sg:postcode":"08037",
    "sg:province":"Barcelona",
    "wof:name":"Corfiset S.l.",
    "wof:placetype":"venue"
},
  "geometry": {"coordinates":[2.165487051,41.4029998779],"type":"Point"}
}