{
  "type": "Feature",
  "properties": {
    "iso:country":"ES",
    "sg:address":"Calle de Campo De La Torre, 16",
    "sg:city":"Madrid",
    "sg:orig_category":"Asesor\u00cda Sobre Comunicaci\u00d3n De Empresas",
    "sg:phone":"+34 917 60 18 86",
    "sg:postcode":"28032",
    "sg:province":"Madrid",
    "wof:name":"Andreu Asesoramiento Y Gestion S.l.",
    "wof:placetype":"venue"
},
  "geometry": {"coordinates":[-3.6061029434,40.3973464966],"type":"Point"}
}