{
  "type": "Feature",
  "properties": {
    "addr:full":"Calle de Estame\u00d1eria Vieja, 6 Valencia Valencia 46001",
    "addr:housenumber":"6",
    "addr:postcode":"46001",
    "addr:street":"Calle De Estamen\u0303Eria Vieja",
    "iso:country":"ES",
    "sg:address":"Calle de Estame\u00d1eria Vieja, 6",
    "sg:city":"Valencia",
    "sg:orig_category":"Loter\u00cda Y T\u00d3mbola",
    "sg:phone":"+34 963 91 74 59",
    "sg:postcode":"46001",
    "sg:province":"Valencia",
    "wof:name":"Soriano Mora Maria Florencia",
    "wof:placetype":"venue"
},
  "geometry": {"coordinates":[-0.377748996,39.4746589661],"type":"Point"}
}