{
  "type": "Feature",
  "properties": {
    "iso:country":"ES",
    "sg:address":"Rua Lisboa (de), S/n",
    "sg:city":"Santiago De Compostela",
    "sg:classifiers":[
        {
            "category":"Taxi",
            "type":"Transportation"
        }
    ],
    "sg:phone":"+34 981 57 59 59",
    "sg:postcode":"15707",
    "sg:province":"La Coru\u00f1a",
    "wof:name":"Asocicion Compostela De Autotaxis",
    "wof:placetype":"venue"
},
  "geometry": {"coordinates":[-8.5278301239,42.8851776123],"type":"Point"}
}