{
  "type": "Feature",
  "properties": {
    "addr:full":"Calle de Federico Garcia Lorca, 5 Conil De La Frontera C\u00e1diz 11140",
    "addr:housenumber":"5",
    "addr:postcode":"11140",
    "addr:street":"Calle De Federico Garcia Lorca",
    "iso:country":"ES",
    "sg:address":"Calle de Federico Garcia Lorca, 5",
    "sg:city":"Conil De La Frontera",
    "sg:orig_category":"Ropa Para Ni\u00d1os (al Por Menor)",
    "sg:phone":"+34 956 44 06 66",
    "sg:postcode":"11140",
    "sg:province":"C\u00e1diz",
    "wof:name":"De Bernedo Zulueta Josu",
    "wof:placetype":"venue"
},
  "geometry": {"coordinates":[-6.0869789124,36.2775230408],"type":"Point"}
}