{
  "type": "Feature",
  "properties": {
    "iso:country":"ES",
    "sg:address":"Avda Alfonso Xiii, 54",
    "sg:city":"Madrid",
    "sg:orig_category":"Internados & Ense\u00d1anza Privada",
    "sg:phone":"+34 914 13 69 78",
    "sg:postcode":"28016",
    "sg:province":"Madrid",
    "wof:name":"Instituto Catolico De Estudios S. A.",
    "wof:placetype":"venue"
},
  "geometry": {"coordinates":[-3.6672070026,40.4527854919],"type":"Point"}
}