{
  "type": "Feature",
  "properties": {
    "addr:full":"Calle de Altamira, 3 Pueblo Nuevo C\u00e1diz 11360",
    "addr:housenumber":"3",
    "addr:postcode":"11360",
    "addr:street":"Calle De Altamira",
    "iso:country":"ES",
    "sg:address":"Calle de Altamira, 3",
    "sg:city":"Pueblo Nuevo",
    "sg:orig_category":"Carpinteros",
    "sg:phone":"+34 956 79 48 08",
    "sg:postcode":"11360",
    "sg:province":"C\u00e1diz",
    "wof:name":"Juan Verdun S.l",
    "wof:placetype":"venue"
},
  "geometry": {"coordinates":[-5.3059587479,36.2952919006],"type":"Point"}
}