{
  "type": "Feature",
  "properties": {
    "addr:full":"Ctra Sant Hipolit, 30 Vic Barcelona 08500",
    "addr:housenumber":"30",
    "addr:postcode":"08500",
    "addr:street":"Ctra Sant Hipolit",
    "iso:country":"ES",
    "sg:address":"Ctra Sant Hipolit, 30",
    "sg:city":"Vic",
    "sg:orig_category":"Electrodom\u00c9sticos (fabricaci\u00d3n, Al Por Mayor)",
    "sg:phone":"+34 938 86 14 00",
    "sg:postcode":"08500",
    "sg:province":"Barcelona",
    "wof:name":"Electro Pla Granollers S. A.",
    "wof:placetype":"venue"
},
  "geometry": {"coordinates":[2.2531399727,41.9452781677],"type":"Point"}
}