{
  "type": "Feature",
  "properties": {
    "addr:full":"Pla\u00c7 Bisbe Coll, 15 Ivars D'urgell Lleida 25260",
    "addr:housenumber":"15",
    "addr:postcode":"25260",
    "addr:street":"Coll",
    "iso:country":"ES",
    "sg:address":"Pla\u00c7 Bisbe Coll, 15",
    "sg:city":"Ivars D'urgell",
    "sg:orig_category":"Cr\u00cda De Animales",
    "sg:phone":"+34 973 58 00 34",
    "sg:postcode":"25260",
    "sg:province":"Lleida",
    "wof:name":"Torrefort S.l.",
    "wof:placetype":"venue"
},
  "geometry": {"coordinates":[0.6457189918,41.6027946472],"type":"Point"}
}