{
  "type": "Feature",
  "properties": {
    "iso:country":"ES",
    "sg:address":"Calle de Valladolid, 13",
    "sg:city":"Avila",
    "sg:orig_category":"Librer\u00cdas",
    "sg:phone":"+34 920 25 00 55",
    "sg:postcode":"05005",
    "sg:province":"\u00c1vila",
    "wof:name":"Calvo Garcia Javier",
    "wof:placetype":"venue"
},
  "geometry": {"coordinates":[-4.6937122345,40.6589660645],"type":"Point"}
}