{
  "type": "Feature",
  "properties": {
    "addr:full":"Melilla Industrial, 3 Melilla Melilla 52006",
    "addr:postcode":"52006",
    "iso:country":"ES",
    "sg:address":"Melilla Industrial, 3",
    "sg:city":"Melilla",
    "sg:orig_category":"Fabricaci\u00d3n De Harinas, S\u00c9molas, Productos De Elaboraci\u00d3n Del Grano",
    "sg:phone":"+34 952 69 65 72",
    "sg:postcode":"52006",
    "sg:province":"Melilla",
    "wof:name":"Harineras Del Mediterraneo S.l.",
    "wof:placetype":"venue"
},
  "geometry": {"coordinates":[-2.9383699894,35.2764587402],"type":"Point"}
}