{
  "type": "Feature",
  "properties": {
    "addr:full":"Avda Pinos (los), 6 Guardamar Segura Alicante 03140",
    "addr:housenumber":"6",
    "addr:postcode":"03140",
    "addr:street":"Avda Pinos Los",
    "iso:country":"ES",
    "sg:address":"Avda Pinos (los), 6",
    "sg:city":"Guardamar Segura",
    "sg:orig_category":"Confecci\u00d3n De Zapatos",
    "sg:phone":"+34 966 72 58 99",
    "sg:postcode":"03140",
    "sg:province":"Alicante",
    "wof:name":"Calzados Cubaelx S.l",
    "wof:placetype":"venue"
},
  "geometry": {"coordinates":[-0.652665019,38.0897254944],"type":"Point"}
}