{
  "type": "Feature",
  "properties": {
    "addr:full":"Calle de Tetuan, 23 Madrid Madrid 28013",
    "addr:housenumber":"23",
    "addr:postcode":"madrid;28013",
    "addr:street":"Calle De Tetuan",
    "iso:country":"ES",
    "sg:address":"Calle de Tetuan, 23",
    "sg:city":"Madrid",
    "sg:orig_category":"Iglesia Cat\u00d3lica",
    "sg:phone":"+34 915 22 67 69",
    "sg:postcode":"28013",
    "sg:province":"Madrid",
    "wof:name":"Parroquia De Nuestra Se\u00f1ora Del Carmen Y San Luis",
    "wof:placetype":"venue"
},
  "geometry": {"coordinates":[-3.7034444809,40.4178123474],"type":"Point"}
}