{
  "type": "Feature",
  "properties": {
    "addr:full":"Carrer de Doma, De La, 7 Garriga Barcelona 08530",
    "addr:housenumber":"7",
    "addr:postcode":"08530",
    "addr:street":"Carrer De Doma De La",
    "iso:country":"ES",
    "sg:address":"Carrer de Doma, De La, 7",
    "sg:city":"Garriga",
    "sg:orig_category":"Bisuter\u00cda, Joyer\u00cda, Relojer\u00cda (al Por Menor)",
    "sg:phone":"+34 938 71 55 95",
    "sg:postcode":"08530",
    "sg:province":"Barcelona",
    "wof:name":"Padros Mas Montserrat",
    "wof:placetype":"venue"
},
  "geometry": {"coordinates":[2.2889399529,41.6845092773],"type":"Point"}
}