{
  "type": "Feature",
  "properties": {
    "addr:full":"Calle de Micer Masco, 22 Valencia Valencia 46010",
    "addr:housenumber":"22",
    "addr:postcode":"46010",
    "addr:street":"Calle De Micer Masco",
    "iso:country":"ES",
    "sg:address":"Calle de Micer Masco, 22",
    "sg:city":"Valencia",
    "sg:orig_category":"Reposter\u00cdas",
    "sg:phone":"+34 963 69 08 20",
    "sg:postcode":"46010",
    "sg:province":"Valencia",
    "wof:name":"Bisbal Alca\u00f1iz Jose Maria",
    "wof:placetype":"venue"
},
  "geometry": {"coordinates":[-0.3630020022,39.4754676819],"type":"Point"}
}