{
  "type": "Feature",
  "properties": {
    "addr:full":"Calle de Alamillo (del), 4 Segovia Segovia 40001",
    "addr:housenumber":"4",
    "addr:postcode":"40001",
    "addr:street":"Calle De Alamillo Del",
    "iso:country":"ES",
    "sg:address":"Calle de Alamillo (del), 4",
    "sg:city":"Segovia",
    "sg:orig_category":"Carnicer\u00cdas, Carnicer\u00cdas",
    "sg:phone":"+34 921 43 16 05",
    "sg:postcode":"40001",
    "sg:province":"Segovia",
    "wof:name":"Valverde Viejo Venancio",
    "wof:placetype":"venue"
},
  "geometry": {"coordinates":[-4.1155500412,40.9479026794],"type":"Point"}
}