{
  "type": "Feature",
  "properties": {
    "addr:full":"Calle de Roble (del), 12 Segovia Segovia 40002",
    "addr:housenumber":"12",
    "addr:postcode":"40002",
    "addr:street":"Calle De Roble Del",
    "iso:country":"ES",
    "sg:address":"Calle de Roble (del), 12",
    "sg:city":"Segovia",
    "sg:orig_category":"Poller\u00cda Y Caza (al Por Menor)",
    "sg:phone":"+34 921 44 43 09",
    "sg:postcode":"40002",
    "sg:province":"Segovia",
    "wof:name":"Servipollo Segovia C.b.",
    "wof:placetype":"venue"
},
  "geometry": {"coordinates":[-4.1180591583,40.9445877075],"type":"Point"}
}