{
  "type": "Feature",
  "properties": {
    "addr:full":"Irizar Pasealekua, S/n Bergara Guip\u00f9zcoa 20570",
    "addr:housenumber":"s / n",
    "addr:postcode":"20570",
    "addr:street":"Irizar Pasealekua;Guipu\u0300Zcoa",
    "iso:country":"ES",
    "sg:address":"Irizar Pasealekua, S/n",
    "sg:city":"Bergara",
    "sg:orig_category":"Carnicer\u00cdas, Carnicer\u00cdas",
    "sg:phone":"+34 943 76 14 12",
    "sg:postcode":"20570",
    "sg:province":"Guip\u00f9zcoa",
    "wof:name":"Igarza I\u00f1arra Jose",
    "wof:placetype":"venue"
},
  "geometry": {"coordinates":[-2.4137489796,43.1188964844],"type":"Point"}
}