{
  "type": "Feature",
  "properties": {
    "addr:full":"Calle de Hernan Cortes, 150 Villanueva Serena Badajoz 06700",
    "addr:housenumber":"150",
    "addr:postcode":"06700",
    "addr:street":"Calle De Hernan Cortes",
    "iso:country":"ES",
    "sg:address":"Calle de Hernan Cortes, 150",
    "sg:city":"Villanueva Serena",
    "sg:orig_category":"Ebanister\u00cda",
    "sg:phone":"+34 924 84 23 50",
    "sg:postcode":"06700",
    "sg:province":"Badajoz",
    "wof:name":"Orrego Sanchez Jose Maria",
    "wof:placetype":"venue"
},
  "geometry": {"coordinates":[-5.7931489944,38.975151062],"type":"Point"}
}