{
  "type": "Feature",
  "properties": {
    "iso:country":"ES",
    "sg:address":"Ctra Valls, S/n",
    "sg:city":"Vendrell",
    "sg:orig_category":"Negocio De Materiales De Construcci\u00d3n",
    "sg:phone":"+34 977 66 01 79",
    "sg:postcode":"43700",
    "sg:province":"Tarragona",
    "wof:name":"Fetra S. A.",
    "wof:placetype":"venue"
},
  "geometry": {"coordinates":[1.5323749781,41.2258415222],"type":"Point"}
}