{
  "type": "Feature",
  "properties": {
    "iso:country":"ES",
    "sg:address":"Carrer de Enric Prat De La Riba, 44",
    "sg:city":"Hospitalet Llobregat",
    "sg:orig_category":"Tratamiento De Metales",
    "sg:phone":"+34 933 38 17 96",
    "sg:postcode":"08901",
    "sg:province":"Barcelona",
    "wof:name":"Tratamientos Almi S.l",
    "wof:placetype":"venue"
},
  "geometry": {"coordinates":[2.1141140461,41.3641319275],"type":"Point"}
}