{
  "type": "Feature",
  "properties": {
    "iso:country":"ES",
    "sg:address":"Calle de Esperanza, 4",
    "sg:city":"Madrid",
    "sg:orig_category":"Aparcamientos (infraestructuras, Accesorios)",
    "sg:phone":"+34 915 27 21 12",
    "sg:postcode":"28012",
    "sg:province":"Madrid",
    "wof:name":"Hammond  Michael",
    "wof:placetype":"venue"
},
  "geometry": {"coordinates":[-3.7005455494,40.4101829529],"type":"Point"}
}