{
  "type": "Feature",
  "properties": {
    "addr:full":"Calle de Industrias Las, S/n Gijon Asturias 33213",
    "addr:postcode":"33213",
    "addr:street":"Calle De Industrias Las S / N",
    "iso:country":"ES",
    "sg:address":"Calle de Industrias Las, S/n",
    "sg:city":"Gijon",
    "sg:orig_category":"Ense\u00d1anza Variada",
    "sg:phone":"+34 985 32 00 77",
    "sg:postcode":"33213",
    "sg:province":"Asturias",
    "wof:name":"Instituto De Formacion Y Estudios Sociales",
    "wof:placetype":"venue"
},
  "geometry": {"coordinates":[-5.6981940269,43.5387496948],"type":"Point"}
}