{
  "type": "Feature",
  "properties": {
    "addr:full":"Calle de Santa Rosa, 1 Cordoba C\u00f3rdoba 14006",
    "addr:housenumber":"1",
    "addr:postcode":"14006",
    "addr:street":"Calle De Santa Rosa;Co\u0301Rdoba",
    "iso:country":"ES",
    "sg:address":"Calle de Santa Rosa, 1",
    "sg:city":"Cordoba",
    "sg:orig_category":"Ropa Y Accesorios",
    "sg:phone":"+34 957 76 71 05",
    "sg:postcode":"14006",
    "sg:province":"C\u00f3rdoba",
    "wof:name":"Hosteleria Y Moda S.l.",
    "wof:placetype":"venue"
},
  "geometry": {"coordinates":[-4.7802190781,37.8969230652],"type":"Point"}
}