{
  "type": "Feature",
  "properties": {
    "iso:country":"ES",
    "sg:address":"Calle de Magallanes, 13",
    "sg:city":"Madrid",
    "sg:orig_category":"Agencias Y Agentes Comerciales, Representantes",
    "sg:phone":"+34 914 45 01 90",
    "sg:postcode":"28015",
    "sg:province":"Madrid",
    "wof:name":"Hernandez Lopez Francisco Javier",
    "wof:placetype":"venue"
},
  "geometry": {"coordinates":[-3.7058670521,40.4343032837],"type":"Point"}
}