{
  "type": "Feature",
  "properties": {
    "iso:country":"ES",
    "sg:address":"Calle de Cordoba, 13",
    "sg:city":"Alacant",
    "sg:orig_category":"Fabricaci\u00d3n De Juegos Y Juguetes",
    "sg:phone":"+34 965 12 18 15",
    "sg:postcode":"03006",
    "sg:province":"Alicante",
    "wof:name":"Tecnitoys Juguetes S.a.",
    "wof:placetype":"venue"
},
  "geometry": {"coordinates":[-0.5001906157,38.3490715027],"type":"Point"}
}