{
  "type": "Feature",
  "properties": {
    "iso:country":"ES",
    "sg:address":"Pl Catalunya, 4",
    "sg:city":"S. Pere Ribes",
    "sg:orig_category":"Agencias Y Asesores De Publicidad",
    "sg:phone":"+34 938 96 41 72",
    "sg:postcode":"08810",
    "sg:province":"Barcelona",
    "wof:name":"Pin.ups Publicitat S.l.",
    "wof:placetype":"venue"
},
  "geometry": {"coordinates":[1.7728290558,41.2590827942],"type":"Point"}
}