{
  "type": "Feature",
  "properties": {
    "addr:full":"Rua San Roque, 32 Vilagarcia Pontevedra 36600",
    "addr:housenumber":"32",
    "addr:postcode":"36600",
    "addr:street":"Rua San Roque",
    "iso:country":"ES",
    "sg:address":"Rua San Roque, 32",
    "sg:city":"Vilagarcia",
    "sg:orig_category":"Molduras, Junquillos, Listones Y Molduras Perforadas",
    "sg:phone":"+34 986 50 25 11",
    "sg:postcode":"36600",
    "sg:province":"Pontevedra",
    "wof:name":"Fuenmayor Otero Rosabel",
    "wof:placetype":"venue"
},
  "geometry": {"coordinates":[-8.7611198425,42.5944519043],"type":"Point"}
}