{
  "type": "Feature",
  "properties": {
    "iso:country":"ES",
    "sg:address":"Calle de Alcalde Pacheco, 1",
    "sg:city":"Yecla",
    "sg:orig_category":"Promotores Constructores",
    "sg:phone":"+34 968 75 18 19",
    "sg:postcode":"30510",
    "sg:province":"Murcia",
    "wof:name":"Juan De Dios Mu\u00f1oz S.l.",
    "wof:placetype":"venue"
},
  "geometry": {"coordinates":[-1.1092410088,38.6155471802],"type":"Point"}
}