{
  "type": "Feature",
  "properties": {
    "addr:full":"Calle de Paloma, 11 Ciudad Real Ciudad Real 13004",
    "addr:housenumber":"11",
    "addr:postcode":"13004",
    "addr:street":"Calle De Paloma",
    "iso:country":"ES",
    "sg:address":"Calle de Paloma, 11",
    "sg:city":"Ciudad Real",
    "sg:orig_category":"Abogados",
    "sg:phone":"+34 926 22 11 85",
    "sg:postcode":"13004",
    "sg:province":"Ciudad Real",
    "wof:name":"Cantos Rodriguez Juan Antonio",
    "wof:placetype":"venue"
},
  "geometry": {"coordinates":[-3.9273269176,38.9862823486],"type":"Point"}
}