{
  "type": "Feature",
  "properties": {
    "iso:country":"ES",
    "sg:address":"Calle de Maladeta, 20",
    "sg:city":"Barbastro",
    "sg:orig_category":"Productos Qu\u00cdmicos (fabricaci\u00d3n, Al Por Mayor)",
    "sg:phone":"+34 974 31 13 59",
    "sg:postcode":"22300",
    "sg:province":"Huesca",
    "wof:name":"Anagalide S.a.",
    "wof:placetype":"venue"
},
  "geometry": {"coordinates":[0.1369773,42.0416374207],"type":"Point"}
}