{
  "type": "Feature",
  "properties": {
    "iso:country":"ES",
    "sg:address":"Calle de Sombrerete, 20",
    "sg:city":"Madrid",
    "sg:orig_category":"Zapatos (al Por Menor)",
    "sg:phone":"+34 915 27 76 62",
    "sg:postcode":"28012",
    "sg:province":"Madrid",
    "wof:name":"Garcia Garcia Luis Miguel",
    "wof:placetype":"venue"
},
  "geometry": {"coordinates":[-3.702933073,40.4082870483],"type":"Point"}
}