{
  "type": "Feature",
  "properties": {
    "iso:country":"ES",
    "sg:address":"Carrer de Casp, 102",
    "sg:city":"Barcelona",
    "sg:orig_category":"Peluqueros: De Se\u00d1oras",
    "sg:phone":"+34 932 45 59 46",
    "sg:postcode":"08010",
    "sg:province":"Barcelona",
    "wof:name":"Prellezo Vila Francisco Javier",
    "wof:placetype":"venue"
},
  "geometry": {"coordinates":[2.1774010658,41.3941993713],"type":"Point"}
}