{
  "type": "Feature",
  "properties": {
    "addr:full":"Avda Regne De Valencia, 55 Valencia Valencia 46005",
    "addr:housenumber":"55",
    "addr:postcode":"46005",
    "addr:street":"Avda Regne De Valencia",
    "iso:country":"ES",
    "sg:address":"Avda Regne De Valencia, 55",
    "sg:city":"Valencia",
    "sg:orig_category":"Perfumer\u00cda Y Cosm\u00c9tica (fabricaci\u00d3n, Al Por Mayor)",
    "sg:phone":"+34 963 74 23 00",
    "sg:postcode":"46005",
    "sg:province":"Valencia",
    "wof:name":"Productos Cosmeticos S.l.",
    "wof:placetype":"venue"
},
  "geometry": {"coordinates":[-0.366012007,39.4635314941],"type":"Point"}
}