{
  "type": "Feature",
  "properties": {
    "addr:full":"Calle de Rododendro (del), 29 Partija-santa Monica Madrid 28529",
    "addr:housenumber":"29",
    "addr:postcode":"28529",
    "addr:street":"Calle De Rododendro Del",
    "iso:country":"ES",
    "sg:address":"Calle de Rododendro (del), 29",
    "sg:city":"Partija-santa Monica",
    "sg:orig_category":"Carb\u00d3n, Carb\u00d3n De Madera (al Por Mayor)",
    "sg:phone":"+34 916 66 35 63",
    "sg:postcode":"28529",
    "sg:province":"Madrid",
    "wof:name":"Combustibles Gallardo S.l.",
    "wof:placetype":"venue"
},
  "geometry": {"coordinates":[-3.5102670193,40.314289093],"type":"Point"}
}