{
  "type": "Feature",
  "properties": {
    "iso:country":"ES",
    "sg:address":"Calle de Gobernador Marin Acu\u00d1a, 47",
    "sg:city":"Palmas De Gran Canaria",
    "sg:orig_category":"Alquiler De V\u00cddeo",
    "sg:phone":"+34 928 38 03 48",
    "sg:postcode":"35014",
    "sg:province":"Las Palmas",
    "wof:name":"Santana Espino Francisco",
    "wof:placetype":"venue"
},
  "geometry": {"coordinates":[-15.4261322021,28.1034011841],"type":"Point"}
}