{
  "type": "Feature",
  "properties": {
    "iso:country":"ES",
    "sg:address":"Carr Rubio I Ors, 23",
    "sg:city":"Badalona",
    "sg:orig_category":"Confecci\u00d3n De Corbatas",
    "sg:phone":"+34 933 83 06 02",
    "sg:postcode":"08915",
    "sg:province":"Barcelona",
    "wof:name":"Uomo S.a",
    "wof:placetype":"venue"
},
  "geometry": {"coordinates":[2.2434821129,41.4608955383],"type":"Point"}
}