{
  "type": "Feature",
  "properties": {
    "addr:full":"Calle de Concepcion Arenal, 20 Palmas De Gran Canaria Las Palmas 35006",
    "addr:housenumber":"20",
    "addr:postcode":"35006",
    "addr:street":"Calle De Concepcion Arenal",
    "iso:country":"ES",
    "sg:address":"Calle de Concepcion Arenal, 20",
    "sg:city":"Palmas De Gran Canaria",
    "sg:orig_category":"Importaci\u00d3n",
    "sg:phone":"+34 928 23 35 37",
    "sg:postcode":"35006",
    "sg:province":"Las Palmas",
    "wof:name":"De La Torre Auguste Mario",
    "wof:placetype":"venue"
},
  "geometry": {"coordinates":[-15.4347314835,28.1330738068],"type":"Point"}
}