{
  "type": "Feature",
  "properties": {
    "addr:full":"Calle de San Pedro, 3 Baltanas Palencia 34240",
    "addr:housenumber":"3",
    "addr:postcode":"34240",
    "addr:street":"Calle De San Pedro",
    "iso:country":"ES",
    "sg:address":"Calle de San Pedro, 3",
    "sg:city":"Baltanas",
    "sg:orig_category":"Muebles, Minoristas",
    "sg:phone":"+34 979 79 00 76",
    "sg:postcode":"34240",
    "sg:province":"Palencia",
    "wof:name":"Muebles Espina S.l.",
    "wof:placetype":"venue"
},
  "geometry": {"coordinates":[-4.2504501343,41.9374237061],"type":"Point"}
}