{
  "type": "Feature",
  "properties": {
    "addr:full":"Pol. 7, S/n Llubi Islas Baleares 07430",
    "addr:housenumber":"s / n",
    "addr:postcode":"07430",
    "addr:street":"Pol. 7",
    "iso:country":"ES",
    "sg:address":"Pol. 7, S/n",
    "sg:city":"Llubi",
    "sg:orig_category":"Cr\u00cda De Animales",
    "sg:phone":"+34 971 18 51 73",
    "sg:postcode":"07430",
    "sg:province":"Islas Baleares",
    "wof:name":"Yeguada Roig-bergado S.l.",
    "wof:placetype":"venue"
},
  "geometry": {"coordinates":[3.0275802612,39.7053070068],"type":"Point"}
}