{
  "type": "Feature",
  "properties": {
    "iso:country":"ES",
    "sg:address":"Plaz Vicente Iborra, 5",
    "sg:city":"Valencia",
    "sg:orig_category":"Administradores De Bienes Y Delegados De Comunidades De Propietarios",
    "sg:phone":"+34 963 91 54 20",
    "sg:postcode":"46003",
    "sg:province":"Valencia",
    "wof:name":"Administraciones Lluch S.l.",
    "wof:placetype":"venue"
},
  "geometry": {"coordinates":[-0.3817529976,39.4769592285],"type":"Point"}
}