{
  "type": "Feature",
  "properties": {
    "addr:full":"Calle de Obispo Jarrin, 14 Salamanca Salamanca 37001",
    "addr:housenumber":"14",
    "addr:postcode":"37001",
    "addr:street":"Calle De Obispo Jarrin",
    "iso:country":"ES",
    "sg:address":"Calle de Obispo Jarrin, 14",
    "sg:city":"Salamanca",
    "sg:orig_category":"Peluquer\u00cdas, Peluquer\u00cda Mixta",
    "sg:phone":"+34 923 26 12 24",
    "sg:postcode":"37001",
    "sg:province":"Salamanca",
    "wof:name":"Resanpe S.l.",
    "wof:placetype":"venue"
},
  "geometry": {"coordinates":[-5.6618142128,40.9646568298],"type":"Point"}
}