{
  "type": "Feature",
  "properties": {
    "addr:full":"Calle de Mu\u00d1oz Seca, 12 Salobre\u00f1a Granada 18680",
    "addr:housenumber":"12",
    "addr:postcode":"18680",
    "addr:street":"Calle De Mun\u0303Oz Seca",
    "iso:country":"ES",
    "sg:address":"Calle de Mu\u00d1oz Seca, 12",
    "sg:city":"Salobre\u00f1a",
    "sg:orig_category":"Promotores Constructores",
    "sg:phone":"+34 958 61 72 06",
    "sg:postcode":"18680",
    "sg:province":"Granada",
    "wof:name":"Priameco S.l.",
    "wof:placetype":"venue"
},
  "geometry": {"coordinates":[-3.583384037,36.7415351868],"type":"Point"}
}