{
  "type": "Feature",
  "properties": {
    "addr:full":"Calle de Villegas, 10 Najera La Rioja 26300",
    "addr:housenumber":"10",
    "addr:postcode":"26300",
    "addr:street":"Calle De Villegas;Rioja",
    "iso:country":"ES",
    "sg:address":"Calle de Villegas, 10",
    "sg:city":"Najera",
    "sg:orig_category":"Bares, Piano",
    "sg:phone":"+34 941 36 24 10",
    "sg:postcode":"26300",
    "sg:province":"La Rioja",
    "wof:name":"Cereceda Marin Cesareo",
    "wof:placetype":"venue"
},
  "geometry": {"coordinates":[-2.7250440121,42.4189338684],"type":"Point"}
}