{
  "type": "Feature",
  "properties": {
    "addr:full":"Carr Salmeron, 2 Lleida Lleida 25004",
    "addr:housenumber":"2",
    "addr:postcode":"25004",
    "addr:street":"Carr Salmeron",
    "iso:country":"ES",
    "sg:address":"Carr Salmeron, 2",
    "sg:city":"Lleida",
    "sg:orig_category":"Granos Y Semillas (producci\u00d3n, Al Por Mayor)",
    "sg:phone":"+34 973 23 16 39",
    "sg:postcode":"25004",
    "sg:province":"Lleida",
    "wof:name":"Sola Villanueva Victor Jaime",
    "wof:placetype":"venue"
},
  "geometry": {"coordinates":[0.6273819804,41.6207275391],"type":"Point"}
}