{
  "type": "Feature",
  "properties": {
    "iso:country":"ES",
    "sg:address":"Avda Cantarranas, 5",
    "sg:city":"Alcorcon",
    "sg:orig_category":"Sociedades, Compa\u00d1\u00cdas Aseguradoras",
    "sg:phone":"+34 916 42 90 20",
    "sg:postcode":"28921",
    "sg:province":"Madrid",
    "sg:website":"www.mmtseguros.es",
    "wof:name":"Mutua Mmt Seguros",
    "wof:placetype":"venue"
},
  "geometry": {"coordinates":[-3.8251628876,40.3503227234],"type":"Point"}
}