{
  "type": "Feature",
  "properties": {
    "iso:country":"ES",
    "sg:address":"Praz Maior, 6",
    "sg:city":"Lugo",
    "sg:orig_category":"Bisuter\u00cda, Joyer\u00cda, Relojer\u00cda (al Por Menor)",
    "sg:phone":"+34 982 22 66 64",
    "sg:postcode":"27001",
    "sg:province":"Lugo",
    "wof:name":"Nu\u00f1ez Beloy Maria Del Carmen",
    "wof:placetype":"venue"
},
  "geometry": {"coordinates":[-7.5561790466,43.0100517273],"type":"Point"}
}