{
  "type": "Feature",
  "properties": {
    "addr:full":"C/ Cervantes, De, 14 S. Antoni Portmany Islas Baleares 07820",
    "addr:housenumber":"14",
    "addr:postcode":"07820",
    "addr:street":"C / Cervantes De",
    "iso:country":"ES",
    "sg:address":"C/ Cervantes, De, 14",
    "sg:city":"S. Antoni Portmany",
    "sg:orig_category":"Restaurantes",
    "sg:phone":"+34 971 34 04 80",
    "sg:postcode":"07820",
    "sg:province":"Islas Baleares",
    "wof:name":"Alvelino Torres Andres",
    "wof:placetype":"venue"
},
  "geometry": {"coordinates":[1.3021731377,38.982624054],"type":"Point"}
}