{
  "type": "Feature",
  "properties": {
    "addr:full":"Calle de Muelle, 3 Mutriku Guip\u00f9zcoa 20830",
    "addr:housenumber":"3",
    "addr:postcode":"20830",
    "addr:street":"Calle De Muelle;Guipu\u0300Zcoa",
    "iso:country":"ES",
    "sg:address":"Calle de Muelle, 3",
    "sg:city":"Mutriku",
    "sg:orig_category":"Promotores Constructores",
    "sg:phone":"+34 943 60 34 40",
    "sg:postcode":"20830",
    "sg:province":"Guip\u00f9zcoa",
    "wof:name":"Mendurre S.l.",
    "wof:placetype":"venue"
},
  "geometry": {"coordinates":[-2.3840429783,43.3079719543],"type":"Point"}
}