{
  "type": "Feature",
  "properties": {
    "iso:country":"ES",
    "sg:address":"Calle de Alquife, S/n",
    "sg:city":"Albolote",
    "sg:orig_category":"Aguas (distribuci\u00d3n, Servicios)",
    "sg:phone":"+34 958 43 07 02",
    "sg:postcode":"18220",
    "sg:province":"Granada",
    "wof:name":"Hidrogestion",
    "wof:placetype":"venue"
},
  "geometry": {"coordinates":[-3.6403040886,37.2235412598],"type":"Point"}
}