{
  "type": "Feature",
  "properties": {
    "addr:full":"Avda Fernando Conde, 1 Estrada Pontevedra 36680",
    "addr:housenumber":"1",
    "addr:postcode":"36680",
    "addr:street":"Avda Fernando Conde;Estrada Pontevedra",
    "iso:country":"ES",
    "sg:address":"Avda Fernando Conde, 1",
    "sg:city":"Estrada",
    "sg:orig_category":"Venta, Instalaci\u00d3n De Calefacci\u00d3n",
    "sg:phone":"+34 986 57 04 14",
    "sg:postcode":"36680",
    "sg:province":"Pontevedra",
    "wof:name":"Maporlux S.l.",
    "wof:placetype":"venue"
},
  "geometry": {"coordinates":[-8.4856405258,42.6900482178],"type":"Point"}
}