{
  "type": "Feature",
  "properties": {
    "addr:full":"Mcdo Azoque, 56 Zaragoza Zaragoza 50004",
    "addr:housenumber":"56",
    "addr:postcode":"50004",
    "addr:street":"Azoque",
    "iso:country":"ES",
    "sg:address":"Mcdo Azoque, 56",
    "sg:city":"Zaragoza",
    "sg:orig_category":"Alimentaci\u00d3n General (al Por Menor)",
    "sg:phone":"+34 976 23 48 42",
    "sg:postcode":"50004",
    "sg:province":"Zaragoza",
    "wof:name":"Lidon Rubio Maria Del Carmen",
    "wof:placetype":"venue"
},
  "geometry": {"coordinates":[-0.8844900131,41.6517295837],"type":"Point"}
}