{
  "type": "Feature",
  "properties": {
    "addr:full":"Calle de Comandante Zorita, 30 Madrid Madrid 28020",
    "addr:housenumber":"30",
    "addr:postcode":"madrid;28020",
    "addr:street":"Calle De Comandante Zorita",
    "iso:country":"ES",
    "sg:address":"Calle de Comandante Zorita, 30",
    "sg:city":"Madrid",
    "sg:orig_category":"Librer\u00cdas",
    "sg:phone":"+34 915 54 36 23",
    "sg:postcode":"28020",
    "sg:province":"Madrid",
    "wof:name":"Lopez Rodriguez Maria Del Carmen",
    "wof:placetype":"venue"
},
  "geometry": {"coordinates":[-3.6983151436,40.4498748779],"type":"Point"}
}