{
  "type": "Feature",
  "properties": {
    "addr:full":"Trva Ezquerro, 28 Autol La Rioja 26560",
    "addr:housenumber":"28",
    "addr:postcode":"26560",
    "addr:street":"Trva Ezquerro;Rioja",
    "iso:country":"ES",
    "sg:address":"Trva Ezquerro, 28",
    "sg:city":"Autol",
    "sg:orig_category":"Electrodom\u00c9sticos (al Por Menor)",
    "sg:phone":"+34 941 39 05 85",
    "sg:postcode":"26560",
    "sg:province":"La Rioja",
    "wof:name":"Hernandez Fuertes Vidal",
    "wof:placetype":"venue"
},
  "geometry": {"coordinates":[-2.0052919388,42.214515686],"type":"Point"}
}