{
  "type": "Feature",
  "properties": {
    "addr:full":"Rua Santa Clara, S/n Monforte De Lemos Lugo 27400",
    "addr:housenumber":"s",
    "addr:postcode":"27400",
    "addr:street":"Rua Santa Clara;/ N",
    "iso:country":"ES",
    "sg:address":"Rua Santa Clara, S/n",
    "sg:city":"Monforte De Lemos",
    "sg:orig_category":"Ingeniero",
    "sg:phone":"+34 982 40 07 73",
    "sg:postcode":"27400",
    "sg:province":"Lugo",
    "wof:name":"Franjo Daga Eladio",
    "wof:placetype":"venue"
},
  "geometry": {"coordinates":[-7.5116991997,42.5297317505],"type":"Point"}
}