{
  "type": "Feature",
  "properties": {
    "addr:full":"Calle de Parroco Juan Gonzalez, 20 Teror Las Palmas 35330",
    "addr:housenumber":"20",
    "addr:postcode":"35330",
    "addr:street":"Calle De Parroco Juan Gonzalez",
    "iso:country":"ES",
    "sg:address":"Calle de Parroco Juan Gonzalez, 20",
    "sg:city":"Teror",
    "sg:orig_category":"M\u00c9dicos: Medicina Interna",
    "sg:phone":"+34 928 63 04 72",
    "sg:postcode":"35330",
    "sg:province":"Las Palmas",
    "wof:name":"Baez Saavedra Fernando Eugenio",
    "wof:placetype":"venue"
},
  "geometry": {"coordinates":[-15.5468254089,28.0619621277],"type":"Point"}
}