{
  "type": "Feature",
  "properties": {
    "iso:country":"ES",
    "sg:address":"Jucar, 8",
    "sg:city":"Collado Villalba",
    "sg:orig_category":"Inform\u00c1tica: Consultores",
    "sg:phone":"+34 918 50 41 30",
    "sg:postcode":"28400",
    "sg:province":"Madrid",
    "sg:website":"www.corabedis.com",
    "wof:name":"Blas Abascal Jesus",
    "wof:placetype":"venue"
},
  "geometry": {"coordinates":[-3.975235939,40.6467018127],"type":"Point"}
}