{
  "type": "Feature",
  "properties": {
    "iso:country":"ES",
    "sg:address":"Calle de Jose Zorrilla, 41",
    "sg:city":"Segovia",
    "sg:orig_category":"Arquitectos",
    "sg:phone":"+34 921 43 20 80",
    "sg:postcode":"40002",
    "sg:province":"Segovia",
    "wof:name":"Arquitectura Y Conservacion De Monumentos S.l.",
    "wof:placetype":"venue"
},
  "geometry": {"coordinates":[-4.1156377792,40.9420890808],"type":"Point"}
}