{
  "type": "Feature",
  "properties": {
    "iso:country":"ES",
    "sg:address":"Urb Villamartin, S/n",
    "sg:city":"Villa Martin",
    "sg:orig_category":"Abogados",
    "sg:phone":"+34 966 76 44 25",
    "sg:postcode":"03189",
    "sg:province":"Alicante",
    "wof:name":"Jarm Villamartin S.l.",
    "wof:placetype":"venue"
},
  "geometry": {"coordinates":[-0.737613976,37.9488296509],"type":"Point"}
}