{
  "type": "Feature",
  "properties": {
    "addr:full":"Carrer de Industria, 214 Barcelona Barcelona 08026",
    "addr:housenumber":"214",
    "addr:postcode":"08026",
    "addr:street":"Carrer De Industria",
    "iso:country":"ES",
    "sg:address":"Carrer de Industria, 214",
    "sg:city":"Barcelona",
    "sg:orig_category":"Molduras, Junquillos, Listones Y Molduras Perforadas",
    "sg:phone":"+34 934 56 16 76",
    "sg:postcode":"08026",
    "sg:province":"Barcelona",
    "wof:name":"Matilla Gorgojo Manuel Jesus",
    "wof:placetype":"venue"
},
  "geometry": {"coordinates":[2.1774199009,41.411655426],"type":"Point"}
}