{
  "type": "Feature",
  "properties": {
    "addr:full":"Calle de San Jose De Calasanz, 38 Binefar Huesca 22500",
    "addr:housenumber":"38",
    "addr:postcode":"22500",
    "addr:street":"Calle De San;De Calasanz",
    "iso:country":"ES",
    "sg:address":"Calle de San Jose De Calasanz, 38",
    "sg:city":"Binefar",
    "sg:orig_category":"Frutas, Legumbres Frescas Y Tempranas (al Por Menor)",
    "sg:phone":"+34 974 42 91 60",
    "sg:postcode":"22500",
    "sg:province":"Huesca",
    "wof:name":"Ruiz Hernandez Esther",
    "wof:placetype":"venue"
},
  "geometry": {"coordinates":[0.2939719856,41.8485603333],"type":"Point"}
}