{
  "type": "Feature",
  "properties": {
    "addr:full":"Calle de Maximino Miyar, S/n Villaviciosa Asturias 33300",
    "addr:housenumber":"s",
    "addr:postcode":"33300",
    "addr:street":"Calle De Maximino Miyar;/ N",
    "iso:country":"ES",
    "sg:address":"Calle de Maximino Miyar, S/n",
    "sg:city":"Villaviciosa",
    "sg:orig_category":"Ense\u00d1anza Secundaria: Colegios Y Escuelas Privadas",
    "sg:phone":"+34 985 89 18 52",
    "sg:postcode":"33300",
    "sg:province":"Asturias",
    "wof:name":"Principado De Asturias",
    "wof:placetype":"venue"
},
  "geometry": {"coordinates":[-5.4385938644,43.4762001038],"type":"Point"}
}