{
  "type": "Feature",
  "properties": {
    "addr:full":"Calle de Coin, Km. 0083,6 Pinos De Alhaurin M\u00e1laga 29130",
    "addr:postcode":"29130",
    "addr:street":"Calle De Coin Km. 0083,6",
    "iso:country":"ES",
    "sg:address":"Calle de Coin, Km. 0083,6",
    "sg:city":"Pinos De Alhaurin",
    "sg:orig_category":"Distribuci\u00d3n De Petr\u00d3leo Y Derivados",
    "sg:phone":"+34 952 41 03 31",
    "sg:postcode":"29130",
    "sg:province":"M\u00e1laga",
    "wof:name":"Estacion De Servicio Alhaurin S. A.",
    "wof:placetype":"venue"
},
  "geometry": {"coordinates":[-4.5796990395,36.6558647156],"type":"Point"}
}