{
  "type": "Feature",
  "properties": {
    "iso:country":"ES",
    "sg:address":"Calle de Lope De Vega, 8",
    "sg:city":"Getxo",
    "sg:orig_category":"Mec\u00c1nico Del Autom\u00d3vil",
    "sg:phone":"+34 944 63 79 98",
    "sg:postcode":"48930",
    "sg:province":"Vizcaya",
    "wof:name":"Talleres Romosport, S.l.",
    "wof:placetype":"venue"
},
  "geometry": {"coordinates":[-3.0079979897,43.3286247253],"type":"Point"}
}