{
  "type": "Feature",
  "properties": {
    "iso:country":"ES",
    "sg:address":"Pase Santa Lucia (de), 2",
    "sg:city":"Arenas San Pedro",
    "sg:orig_category":"Suministros Para Hoteles",
    "sg:phone":"+34 920 37 22 88",
    "sg:postcode":"05400",
    "sg:province":"\u00c1vila",
    "wof:name":"Blazquez Crespo Raul",
    "wof:placetype":"venue"
},
  "geometry": {"coordinates":[-5.0866141319,40.210231781],"type":"Point"}
}