{
  "type": "Feature",
  "properties": {
    "addr:full":"Calle de Oeste, S/n Ejea De Los Caballeros Zaragoza 50600",
    "addr:housenumber":"s / n",
    "addr:postcode":"50600",
    "addr:street":"Calle De Oeste",
    "iso:country":"ES",
    "sg:address":"Calle de Oeste, S/n",
    "sg:city":"Ejea De Los Caballeros",
    "sg:orig_category":"Cables Y Hilos El\u00c9ctricos (fabricaci\u00d3n, Al Por Mayor)",
    "sg:phone":"+34 976 66 35 57",
    "sg:postcode":"50600",
    "sg:province":"Zaragoza",
    "wof:name":"Cableados De La Llana S.coop.",
    "wof:placetype":"venue"
},
  "geometry": {"coordinates":[-1.1412700415,42.1182594299],"type":"Point"}
}