{
  "type": "Feature",
  "properties": {
    "addr:full":"Calle de Claudio Coello, 73 Madrid Madrid 28001",
    "addr:housenumber":"73",
    "addr:postcode":"madrid;28001",
    "addr:street":"Calle De Claudio Coello",
    "iso:country":"ES",
    "sg:address":"Calle de Claudio Coello, 73",
    "sg:city":"Madrid",
    "sg:orig_category":"Agencias De Viajes",
    "sg:phone":"+34 914 35 97 65",
    "sg:postcode":"28001",
    "sg:province":"Madrid",
    "wof:name":"Viajes Iberia S.a.",
    "wof:placetype":"venue"
},
  "geometry": {"coordinates":[-3.6861879826,40.4290161133],"type":"Point"}
}