{
  "type": "Feature",
  "properties": {
    "addr:full":"Calle de Venancio Gonzalez, 7 Toledo Toledo 45001",
    "addr:housenumber":"7",
    "addr:postcode":"45001",
    "addr:street":"Calle De Venancio Gonzalez",
    "iso:country":"ES",
    "sg:address":"Calle de Venancio Gonzalez, 7",
    "sg:city":"Toledo",
    "sg:classifiers":[
        {
            "category":"Autos & Motor Vehicles",
            "subcategory":"Automobile Sales",
            "type":"Retail Goods"
        }
    ],
    "sg:phone":"+34 925 22 15 61",
    "sg:postcode":"45001",
    "sg:province":"Toledo",
    "wof:name":"Sanchez Diaz Jose Luis",
    "wof:placetype":"venue"
},
  "geometry": {"coordinates":[-4.0218238831,39.8611793518],"type":"Point"}
}