{
  "type": "Feature",
  "properties": {
    "addr:full":"Calle de Paz (la), 7 Portugalete Vizcaya 48920",
    "addr:housenumber":"7",
    "addr:postcode":"48920",
    "addr:street":"Calle De Paz La",
    "iso:country":"ES",
    "sg:address":"Calle de Paz (la), 7",
    "sg:city":"Portugalete",
    "sg:orig_category":"Cristaler\u00cdas",
    "sg:phone":"+34 944 95 79 96",
    "sg:postcode":"48920",
    "sg:province":"Vizcaya",
    "wof:name":"Cristaleria Repelega C.b.",
    "wof:placetype":"venue"
},
  "geometry": {"coordinates":[-3.0175430775,43.3173980713],"type":"Point"}
}