{
  "type": "Feature",
  "properties": {
    "addr:full":"Av Frederic Rahola, S/n Barcelona Barcelona 08032",
    "addr:housenumber":"s",
    "addr:postcode":"08032",
    "addr:street":"Av Frederic Rahola;/ N",
    "iso:country":"ES",
    "sg:address":"Av Frederic Rahola, S/n",
    "sg:city":"Barcelona",
    "sg:orig_category":"Empresarios Y Productoras De Espect\u00c1culos",
    "sg:phone":"+34 902 38 38 40",
    "sg:postcode":"08032",
    "sg:province":"Barcelona",
    "sg:website":"www.exitsweb.com",
    "wof:name":"Arts Manageer S.l.",
    "wof:placetype":"venue"
},
  "geometry": {"coordinates":[2.1671390533,41.4252586365],"type":"Point"}
}