{
  "type": "Feature",
  "properties": {
    "addr:full":"Ctra Nacional V Madrid-lisboa, Km. 0400,0 Badajoz Badajoz 06008",
    "addr:postcode":"06008",
    "addr:street":"Ctra Nacional V Madrid-Lisboa Km. 0400,0",
    "iso:country":"ES",
    "sg:address":"Ctra Nacional V Madrid-lisboa, Km. 0400,0",
    "sg:city":"Badajoz",
    "sg:orig_category":"Insecticidas, Fumigaci\u00d3n",
    "sg:phone":"+34 924 24 64 61",
    "sg:postcode":"06008",
    "sg:province":"Badajoz",
    "wof:name":"Fernando Barrera S.l.",
    "wof:placetype":"venue"
},
  "geometry": {"coordinates":[-6.9430441856,38.8723373413],"type":"Point"}
}