{
  "type": "Feature",
  "properties": {
    "addr:full":"Av Francesc Macia, 194 Esparreguera Barcelona 08292",
    "addr:housenumber":"194",
    "addr:postcode":"08292",
    "addr:street":"Av Francesc Macia",
    "iso:country":"ES",
    "sg:address":"Av Francesc Macia, 194",
    "sg:city":"Esparreguera",
    "sg:orig_category":"Asesor\u00cda Sobre Comunicaci\u00d3n De Empresas",
    "sg:phone":"+34 937 77 69 74",
    "sg:postcode":"08292",
    "sg:province":"Barcelona",
    "wof:name":"Navarro Ballesteros Ismael",
    "wof:placetype":"venue"
},
  "geometry": {"coordinates":[1.8648200035,41.5419311523],"type":"Point"}
}