{
  "type": "Feature",
  "properties": {
    "addr:full":"Pda. Juncosa, 70 Balaguer Lleida 25600",
    "addr:housenumber":"70",
    "addr:postcode":"25600",
    "iso:country":"ES",
    "sg:address":"Pda. Juncosa, 70",
    "sg:city":"Balaguer",
    "sg:orig_category":"Agricultores, Agricultores",
    "sg:phone":"+34 973 44 70 18",
    "sg:postcode":"25600",
    "sg:province":"Lleida",
    "wof:name":"Agropecuaria Sant Antoni Balaguer S.l.",
    "wof:placetype":"venue"
},
  "geometry": {"coordinates":[0.7722973824,41.777961731],"type":"Point"}
}