{
  "type": "Feature",
  "properties": {
    "iso:country":"ES",
    "sg:address":"La Bureba, S/n",
    "sg:city":"Burgos",
    "sg:orig_category":"Delegados, Agentes De Tr\u00c1nsito, Auxiliares De Transporte Internacional",
    "sg:phone":"+34 947 48 43 11",
    "sg:postcode":"09007",
    "sg:province":"Burgos",
    "sg:website":"www.guipuzcoana.com",
    "wof:name":"Transportes Burgos S.l.",
    "wof:placetype":"venue"
},
  "geometry": {"coordinates":[-3.6468238831,42.3518028259],"type":"Point"}
}