{
  "type": "Feature",
  "properties": {
    "addr:full":"Carrer de Cano, 4 Barcelona Barcelona 08012",
    "addr:housenumber":"4",
    "addr:postcode":"08012",
    "addr:street":"Carrer De Cano",
    "iso:country":"ES",
    "sg:address":"Carrer de Cano, 4",
    "sg:city":"Barcelona",
    "sg:orig_category":"Arquitectos",
    "sg:phone":"+34 932 17 24 16",
    "sg:postcode":"08012",
    "sg:province":"Barcelona",
    "wof:name":"Actar Architecture Ass S.l.",
    "wof:placetype":"venue"
},
  "geometry": {"coordinates":[2.1574370861,41.4013252258],"type":"Point"}
}