{
  "type": "Feature",
  "properties": {
    "iso:country":"ES",
    "sg:address":"Carrer de Marbella, 42",
    "sg:city":"Maravillas",
    "sg:orig_category":"Alquiler De Veh\u00cdculos: Turismos Y Utilitarios",
    "sg:phone":"+34 971 49 18 18",
    "sg:postcode":"07610",
    "sg:province":"Islas Baleares",
    "sg:website":"www.mallorcar.com",
    "wof:name":"Metro Rend Malorca S.l.",
    "wof:placetype":"venue"
},
  "geometry": {"coordinates":[2.7243249416,39.5336914062],"type":"Point"}
}