{
  "type": "Feature",
  "properties": {
    "iso:country":"ES",
    "sg:address":"Rua Reconquista, 3",
    "sg:city":"Vigo",
    "sg:orig_category":"Agencias De Viajes",
    "sg:phone":"+34 986 44 97 17",
    "sg:postcode":"36201",
    "sg:province":"Pontevedra",
    "sg:website":"www.abramar.com",
    "wof:name":"Viajes Abramar S.a.",
    "wof:placetype":"venue"
},
  "geometry": {"coordinates":[-8.722858429,42.2386398315],"type":"Point"}
}