{
  "type": "Feature",
  "properties": {
    "addr:full":"Calle de Gutemberg, 32 Grela La Coru\u00f1a 15008",
    "addr:housenumber":"32",
    "addr:postcode":"15008",
    "addr:street":"Calle De Gutemberg;La Corun\u0303A",
    "iso:country":"ES",
    "sg:address":"Calle de Gutemberg, 32",
    "sg:city":"Grela",
    "sg:orig_category":"Transporte En General",
    "sg:phone":"+34 981 27 33 03",
    "sg:postcode":"15008",
    "sg:province":"La Coru\u00f1a",
    "wof:name":"Exclusivas Bejar S.l.",
    "wof:placetype":"venue"
},
  "geometry": {"coordinates":[-8.4471950531,43.0565299988],"type":"Point"}
}