{
  "type": "Feature",
  "properties": {
    "addr:full":"Urb Olivares (no Oficial), 43 Oviedo Asturias 33013",
    "addr:postcode":"33013",
    "addr:street":"Urb Olivares No Oficial 43",
    "iso:country":"ES",
    "sg:address":"Urb Olivares (no Oficial), 43",
    "sg:city":"Oviedo",
    "sg:orig_category":"Prot\u00c9sicos Dentales",
    "sg:phone":"+34 985 27 11 26",
    "sg:postcode":"33013",
    "sg:province":"Asturias",
    "wof:name":"Fuertes Gutierrez Luis",
    "wof:placetype":"venue"
},
  "geometry": {"coordinates":[-5.876139164,43.3637809753],"type":"Point"}
}