{
  "type": "Feature",
  "properties": {
    "addr:full":"Carr Avinyonet, S/n Figueres Girona 17600",
    "addr:housenumber":"s / n",
    "addr:postcode":"17600",
    "addr:street":"Carr Avinyonet",
    "iso:country":"ES",
    "sg:address":"Carr Avinyonet, S/n",
    "sg:city":"Figueres",
    "sg:orig_category":"Ense\u00d1anza, Formaci\u00d3n Profesional: Aprendizaje",
    "sg:phone":"+34 972 67 15 90",
    "sg:postcode":"17600",
    "sg:province":"Girona",
    "wof:name":"Institut Catala D'assistencia I Serveis Socials",
    "wof:placetype":"venue"
},
  "geometry": {"coordinates":[2.9473850727,42.2652587891],"type":"Point"}
}