{
  "type": "Feature",
  "properties": {
    "addr:full":"Av Baix Penedes, 61 Vendrell Tarragona 43700",
    "addr:housenumber":"61",
    "addr:postcode":"43700",
    "addr:street":"Av Baix Penedes",
    "iso:country":"ES",
    "sg:address":"Av Baix Penedes, 61",
    "sg:city":"Vendrell",
    "sg:orig_category":"Colchones (fabricaci\u00d3n, Al Por Mayor, Al Por Menor)",
    "sg:phone":"+34 977 15 45 33",
    "sg:postcode":"43700",
    "sg:province":"Tarragona",
    "wof:name":"Sanz Marti David",
    "wof:placetype":"venue"
},
  "geometry": {"coordinates":[1.5278500319,41.2193756104],"type":"Point"}
}