{
  "type": "Feature",
  "properties": {
    "addr:full":"Calle de Zurbano, 51 Madrid Madrid 28010",
    "addr:housenumber":"51",
    "addr:postcode":"madrid;28010",
    "addr:street":"Calle De Zurbano",
    "iso:country":"ES",
    "sg:address":"Calle de Zurbano, 51",
    "sg:city":"Madrid",
    "sg:orig_category":"Importaci\u00d3n",
    "sg:phone":"+34 913 08 15 15",
    "sg:postcode":"28010",
    "sg:province":"Madrid",
    "wof:name":"Prado Ruiz Angel Luis",
    "wof:placetype":"venue"
},
  "geometry": {"coordinates":[-3.6931669712,40.4349861145],"type":"Point"}
}