{
  "type": "Feature",
  "properties": {
    "iso:country":"ES",
    "sg:address":"Carr 9 D'octubre, 1",
    "sg:city":"Pu\u00e7ol",
    "sg:classifiers":[
        {
            "category":"Autos & Motor Vehicles",
            "subcategory":"Automobile Sales",
            "type":"Retail Goods"
        }
    ],
    "sg:phone":"+34 961 42 10 15",
    "sg:postcode":"46530",
    "sg:province":"Valencia",
    "wof:name":"Autoescuela Goya S.l.",
    "wof:placetype":"venue"
},
  "geometry": {"coordinates":[-0.3042778075,39.6152801514],"type":"Point"}
}