{
  "type": "Feature",
  "properties": {
    "addr:full":"Calle de Monse\u00d1or Cadena Y Eleta, S/n Vitoria-gasteiz \u00c1lava 01008",
    "addr:housenumber":"s",
    "addr:postcode":"01008",
    "addr:street":"Calle De Monsen\u0303Or Cadena Y Eleta;/ N",
    "iso:country":"ES",
    "sg:address":"Calle de Monse\u00d1or Cadena Y Eleta, S/n",
    "sg:city":"Vitoria-gasteiz",
    "sg:orig_category":"Museos",
    "sg:phone":"+34 945 15 06 31",
    "sg:postcode":"01008",
    "sg:province":"\u00c1lava",
    "sg:website":"web.alava.net/museosalava",
    "wof:name":"Museo De Arte Sacro",
    "wof:placetype":"venue"
},
  "geometry": {"coordinates":[-2.6768898964,42.8447685242],"type":"Point"}
}