{
  "type": "Feature",
  "properties": {
    "addr:full":"Calle de Ingeniero Fernandez Casado (del), 19 Coslada Madrid 28820",
    "addr:housenumber":"19",
    "addr:postcode":"28820",
    "addr:street":"Calle De Ingeniero Fernandez Casado Del",
    "iso:country":"ES",
    "sg:address":"Calle de Ingeniero Fernandez Casado (del), 19",
    "sg:city":"Coslada",
    "sg:orig_category":"Negocio De Madera",
    "sg:phone":"+34 916 69 00 13",
    "sg:postcode":"28820",
    "sg:province":"Madrid",
    "wof:name":"Derivados Del Bosque Industriales S.l.",
    "wof:placetype":"venue"
},
  "geometry": {"coordinates":[-3.5341930389,40.4309196472],"type":"Point"}
}