{
  "type": "Feature",
  "properties": {
    "iso:country":"ES",
    "sg:address":"Ctra. Redondela, S/n",
    "sg:city":"Isla Cristina",
    "sg:orig_category":"Frutas Y Legumbres Frescas (al Por Mayor)",
    "sg:phone":"+34 959 34 30 15",
    "sg:postcode":"21410",
    "sg:province":"Huelva",
    "wof:name":"Citricos Reunidos S.a.",
    "wof:placetype":"venue"
},
  "geometry": {"coordinates":[-7.3203940392,37.2019615173],"type":"Point"}
}