{
  "type": "Feature",
  "properties": {
    "addr:full":"Plaz Capitan Boixareu Rivera, 53 Guadalajara Guadalajara 19001",
    "addr:housenumber":"53",
    "addr:postcode":"19001",
    "addr:street":"Plaz Capitan Boixareu Rivera",
    "iso:country":"ES",
    "sg:address":"Plaz Capitan Boixareu Rivera, 53",
    "sg:city":"Guadalajara",
    "sg:orig_category":"Inmobiliaria (agencias)",
    "sg:phone":"+34 949 23 40 70",
    "sg:postcode":"19001",
    "sg:province":"Guadalajara",
    "wof:name":"Lorenzo Promociones Y Servicios Inmobiliarios S.a.",
    "wof:placetype":"venue"
},
  "geometry": {"coordinates":[-3.1613988876,40.6317901611],"type":"Point"}
}