{
  "type": "Feature",
  "properties": {
    "addr:full":"Plaz Pinazo, 200 Madrid Madrid 28021",
    "addr:housenumber":"200",
    "addr:postcode":"28021",
    "addr:street":"Plaz Pinazo",
    "iso:country":"ES",
    "sg:address":"Plaz Pinazo, 200",
    "sg:city":"Madrid",
    "sg:orig_category":"Servicio De Salud",
    "sg:phone":"+34 917 96 74 75",
    "sg:postcode":"28021",
    "sg:province":"Madrid",
    "wof:name":"Saneamientos Lope Carrasco S.l.",
    "wof:placetype":"venue"
},
  "geometry": {"coordinates":[-3.6911489964,40.3425483704],"type":"Point"}
}