{
  "type": "Feature",
  "properties": {
    "iso:country":"ES",
    "sg:address":"Avda Alcora, 9",
    "sg:city":"Castellon",
    "sg:orig_category":"Farmacias",
    "sg:phone":"+34 964 21 89 18",
    "sg:postcode":"12006",
    "sg:province":"Castell\u00f3n",
    "wof:name":"Marco Beltran C.b.",
    "wof:placetype":"venue"
},
  "geometry": {"coordinates":[-0.1292939931,40.0168533325],"type":"Point"}
}