{
  "type": "Feature",
  "properties": {
    "addr:full":"Avda. Espinaredo(mestas), S/n San Antonio Asturias 33530",
    "addr:housenumber":"s / n",
    "addr:postcode":"33530",
    "addr:street":"Avda. Espinaredo Mestas",
    "iso:country":"ES",
    "sg:address":"Avda. Espinaredo(mestas), S/n",
    "sg:city":"San Antonio",
    "sg:orig_category":"Molduras, Junquillos, Listones Y Molduras Perforadas",
    "sg:phone":"+34 985 71 03 25",
    "sg:postcode":"33530",
    "sg:province":"Asturias",
    "wof:name":"Andrade Undagoitia Mari Angeles",
    "wof:placetype":"venue"
},
  "geometry": {"coordinates":[-5.6046509743,43.506477356],"type":"Point"}
}