{
  "type": "Feature",
  "properties": {
    "iso:country":"ES",
    "sg:address":"Calle de Jose Miguel Barandiaran, 1",
    "sg:city":"Santurtzi",
    "sg:orig_category":"Ropa Para Se\u00d1oras Y Caballeros (al Por Menor)",
    "sg:phone":"+34 944 05 92 59",
    "sg:postcode":"48980",
    "sg:province":"Vizcaya",
    "wof:name":"Kukele",
    "wof:placetype":"venue"
},
  "geometry": {"coordinates":[-3.0331521034,43.3279495239],"type":"Point"}
}