{
  "type": "Feature",
  "properties": {
    "iso:country":"ES",
    "sg:address":"Plaz Don Hilario Yaben, 2",
    "sg:city":"Sig\u00fcenza",
    "sg:classifiers":[
        {
            "category":"Manufacturing",
            "subcategory":"Building Materials",
            "type":"Manufacturing & Wholesale Goods"
        }
    ],
    "sg:phone":"+34 949 39 09 48",
    "sg:postcode":"19250",
    "sg:province":"Guadalajara",
    "sg:tags":[
        "de",
        "industrial",
        "alquiler"
    ],
    "wof:name":"Antonio Del Barrio Del Amo Y Otros C.b.",
    "wof:placetype":"venue"
},
  "geometry": {"coordinates":[-2.6387794018,41.0697555542],"type":"Point"}
}