{
  "type": "Feature",
  "properties": {
    "iso:country":"ES",
    "sg:address":"Carrer de Gran Via De Lluis Companys, 163",
    "sg:city":"Premia Mar",
    "sg:orig_category":"M\u00c9dicos: Pediatr\u00cda. Enfermedades De Los Ni\u00d1os",
    "sg:phone":"+34 937 51 19 35",
    "sg:postcode":"08330",
    "sg:province":"Barcelona",
    "wof:name":"Crespo Benito Julia",
    "wof:placetype":"venue"
},
  "geometry": {"coordinates":[2.353110075,41.4906196594],"type":"Point"}
}