{
  "type": "Feature",
  "properties": {
    "iso:country":"ES",
    "sg:address":"Rua Pumar Mendez, 17",
    "sg:city":"Cambre",
    "sg:orig_category":"Panader\u00cdas, Panader\u00cdas",
    "sg:phone":"+34 981 67 51 28",
    "sg:postcode":"15660",
    "sg:province":"La Coru\u00f1a",
    "wof:name":"Conmimo S.l.",
    "wof:placetype":"venue"
},
  "geometry": {"coordinates":[-8.3557987213,43.3154907227],"type":"Point"}
}