{
  "type": "Feature",
  "properties": {
    "iso:country":"ES",
    "sg:address":"Calle de Arcangeles, 53",
    "sg:city":"Malaga",
    "sg:orig_category":"M\u00c9dicos: Estomatolog\u00cda",
    "sg:phone":"+34 952 29 06 92",
    "sg:postcode":"29018",
    "sg:province":"M\u00e1laga",
    "wof:name":"Diaz  Carlos Rodolfo",
    "wof:placetype":"venue"
},
  "geometry": {"coordinates":[-4.3787145615,36.7280197144],"type":"Point"}
}