{
  "type": "Feature",
  "properties": {
    "iso:country":"ES",
    "sg:address":"Torres, 8",
    "sg:city":"Lucena",
    "sg:orig_category":"Ropa Para Se\u00d1oras Y Caballeros (al Por Menor)",
    "sg:phone":"+34 957 50 09 94",
    "sg:postcode":"14900",
    "sg:province":"C\u00f3rdoba",
    "wof:name":"Mu\u00f1oz Odriozola Luis",
    "wof:placetype":"venue"
},
  "geometry": {"coordinates":[-4.4869141579,37.4116516113],"type":"Point"}
}