{
  "type": "Feature",
  "properties": {
    "addr:full":"Ctra Rotgla, S/n Llosa Ranes Valencia 46815",
    "addr:housenumber":"s / n",
    "addr:postcode":"46815",
    "addr:street":"Ctra Rotgla",
    "iso:country":"ES",
    "sg:address":"Ctra Rotgla, S/n",
    "sg:city":"Llosa Ranes",
    "sg:orig_category":"Electromec\u00c1nica",
    "sg:phone":"+34 962 23 03 39",
    "sg:postcode":"46815",
    "sg:province":"Valencia",
    "wof:name":"Pons Chaquet Antonio",
    "wof:placetype":"venue"
},
  "geometry": {"coordinates":[-0.5338389874,39.0177955627],"type":"Point"}
}