{
  "type": "Feature",
  "properties": {
    "addr:full":"Araba Etorbidea, 3 Arrasate Guip\u00f9zcoa 20500",
    "addr:housenumber":"3",
    "addr:postcode":"20500",
    "addr:street":"Araba Etorbidea;Guipu\u0300Zcoa",
    "iso:country":"ES",
    "sg:address":"Araba Etorbidea, 3",
    "sg:city":"Arrasate",
    "sg:orig_category":"Pescader\u00cdas (al Por Menor)",
    "sg:phone":"+34 943 79 19 86",
    "sg:postcode":"20500",
    "sg:province":"Guip\u00f9zcoa",
    "wof:name":"Mayora Gantxegui Izaskun",
    "wof:placetype":"venue"
},
  "geometry": {"coordinates":[-2.4907660484,43.0626716614],"type":"Point"}
}