{
  "type": "Feature",
  "properties": {
    "iso:country":"ES",
    "sg:address":"Vred Orihuela (de), S/n",
    "sg:city":"Torre-pacheco",
    "sg:orig_category":"Centros De Educaci\u00d3n Especial",
    "sg:phone":"+34 968 33 64 23",
    "sg:postcode":"30700",
    "sg:province":"Murcia",
    "wof:name":"Cooperativa De Ense\u00f1anza Virgen Del Pasico",
    "wof:placetype":"venue"
},
  "geometry": {"coordinates":[-0.9643790126,37.7505607605],"type":"Point"}
}