{
  "type": "Feature",
  "properties": {
    "iso:country":"ES",
    "sg:address":"Acequia Real Jucar, 13",
    "sg:city":"Silla",
    "sg:orig_category":"Organismos De Reclutamiento",
    "sg:phone":"+34 961 21 42 44",
    "sg:postcode":"46460",
    "sg:province":"Valencia",
    "wof:name":"Improving Logistic & Consulting S.l",
    "wof:placetype":"venue"
},
  "geometry": {"coordinates":[-0.417858988,39.3685531616],"type":"Point"}
}