{
  "type": "Feature",
  "properties": {
    "iso:country":"ES",
    "sg:address":"Cruixidell(urb Torre Conill), 16",
    "sg:city":"Betera",
    "sg:orig_category":"Inmobiliaria (agencias)",
    "sg:phone":"+34 961 60 08 63",
    "sg:postcode":"46117",
    "sg:province":"Valencia",
    "wof:name":"Litttafaner C.b.",
    "wof:placetype":"venue"
},
  "geometry": {"coordinates":[-0.4828529954,39.5713272095],"type":"Point"}
}