{
  "type": "Feature",
  "properties": {
    "addr:full":"Calle de Alazan, 42 Badajoz Badajoz 06008",
    "addr:housenumber":"42",
    "addr:postcode":"06008",
    "addr:street":"Calle De Alazan",
    "iso:country":"ES",
    "sg:address":"Calle de Alazan, 42",
    "sg:city":"Badajoz",
    "sg:orig_category":"Quincaller\u00cda (al Por Menor)",
    "sg:phone":"+34 924 24 70 46",
    "sg:postcode":"06008",
    "sg:province":"Badajoz",
    "wof:name":"Iglesias Casado Gregorio",
    "wof:placetype":"venue"
},
  "geometry": {"coordinates":[-6.9531559944,38.8796463013],"type":"Point"}
}