{
  "type": "Feature",
  "properties": {
    "addr:full":"Calle de Genaro Riestra, 3 Llanes Asturias 33500",
    "addr:housenumber":"3",
    "addr:postcode":"33500",
    "addr:street":"Calle De Genaro Riestra",
    "iso:country":"ES",
    "sg:address":"Calle de Genaro Riestra, 3",
    "sg:city":"Llanes",
    "sg:orig_category":"Carnicer\u00cdas, Carnicer\u00cdas",
    "sg:phone":"+34 985 40 15 62",
    "sg:postcode":"33500",
    "sg:province":"Asturias",
    "wof:name":"Carnicos Y Embutidos La Asturiana Sl",
    "wof:placetype":"venue"
},
  "geometry": {"coordinates":[-4.7559199333,43.4220314026],"type":"Point"}
}