{
  "type": "Feature",
  "properties": {
    "iso:country":"ES",
    "sg:address":"Plaz Espa\u00d1a, 1",
    "sg:city":"Alcazar S. Juan",
    "sg:orig_category":"Ense\u00d1anza, Formaci\u00d3n Profesional: Aprendizaje",
    "sg:phone":"+34 926 57 91 00",
    "sg:postcode":"13...",
    "sg:province":"Ciudad Real",
    "wof:name":"Ayuntamiento De Alcazar De San Juan",
    "wof:placetype":"venue"
},
  "geometry": {"coordinates":[-3.9301700592,38.9844093323],"type":"Point"}
}