{
  "type": "Feature",
  "properties": {
    "addr:full":"Calle de San Isidro, 10 Valladolid Valladolid 47004",
    "addr:housenumber":"10",
    "addr:postcode":"47004",
    "addr:street":"Calle De San Isidro",
    "iso:country":"ES",
    "sg:address":"Calle de San Isidro, 10",
    "sg:city":"Valladolid",
    "sg:orig_category":"Herboristas (al Por Menor)",
    "sg:phone":"+34 983 20 06 46",
    "sg:postcode":"47004",
    "sg:province":"Valladolid",
    "wof:name":"Conde De La Fuente Angel",
    "wof:placetype":"venue"
},
  "geometry": {"coordinates":[-4.7163572311,41.6460227966],"type":"Point"}
}