{
  "type": "Feature",
  "properties": {
    "addr:full":"Avda Andalucia, 86 Estepona M\u00e1laga 29680",
    "addr:housenumber":"86",
    "addr:postcode":"29680",
    "addr:street":"Avda Andalucia",
    "iso:country":"ES",
    "sg:address":"Avda Andalucia, 86",
    "sg:city":"Estepona",
    "sg:orig_category":"Tintes (fabricaci\u00d3n, Al Por Mayor)",
    "sg:phone":"+34 952 79 00 16",
    "sg:postcode":"29680",
    "sg:province":"M\u00e1laga",
    "wof:name":"Tintorerias Manu S.l.",
    "wof:placetype":"venue"
},
  "geometry": {"coordinates":[-5.1428279877,36.4306335449],"type":"Point"}
}