{
  "type": "Feature",
  "properties": {
    "addr:full":"Calle de Maestro Pedro Carmona, 11 Barbate C\u00e1diz 11160",
    "addr:housenumber":"11",
    "addr:postcode":"11160",
    "addr:street":"Calle De Maestro Pedro Carmona",
    "iso:country":"ES",
    "sg:address":"Calle de Maestro Pedro Carmona, 11",
    "sg:city":"Barbate",
    "sg:orig_category":"Bebidas",
    "sg:phone":"+34 956 43 32 55",
    "sg:postcode":"11160",
    "sg:province":"C\u00e1diz",
    "wof:name":"Astorga Bermudez Manuel",
    "wof:placetype":"venue"
},
  "geometry": {"coordinates":[-5.9157648087,36.1925048828],"type":"Point"}
}