{
  "type": "Feature",
  "properties": {
    "addr:full":"Calle de Pintor Sorolla (del), 4 Colmenar Viejo Madrid 28770",
    "addr:postcode":"28770",
    "addr:street":"Calle De Pintor Sorolla Del",
    "iso:country":"ES",
    "sg:address":"Calle de Pintor Sorolla (del), 4",
    "sg:city":"Colmenar Viejo",
    "sg:orig_category":"Peluquer\u00cdas, Peluquer\u00cda Mixta",
    "sg:phone":"+34 918 46 27 24",
    "sg:postcode":"28770",
    "sg:province":"Madrid",
    "wof:name":"Color Style S. C.",
    "wof:placetype":"venue"
},
  "geometry": {"coordinates":[-3.7729411125,40.6699523926],"type":"Point"}
}