{
  "type": "Feature",
  "properties": {
    "addr:full":"C/ Benito Perez Galdos, 53 Elche Alicante 03201",
    "addr:housenumber":"53",
    "addr:postcode":"03201",
    "addr:street":"C / Benito Perez Galdos",
    "iso:country":"ES",
    "sg:address":"C/ Benito Perez Galdos, 53",
    "sg:city":"Elche",
    "sg:orig_category":"Carnicer\u00cdas, Carnicer\u00cdas",
    "sg:phone":"+34 965 44 99 78",
    "sg:postcode":"03201",
    "sg:province":"Alicante",
    "wof:name":"Carnicerias Xamonix S.l.",
    "wof:placetype":"venue"
},
  "geometry": {"coordinates":[-0.7086250186,38.2664031982],"type":"Point"}
}