{
  "type": "Feature",
  "properties": {
    "addr:full":"Calle de Parroco Antonio Gil, 4 Vega S. Mateo Las Palmas 35328",
    "addr:housenumber":"4",
    "addr:postcode":"35328",
    "addr:street":"Calle De Parroco Antonio Gil;S. Mateo Las",
    "iso:country":"ES",
    "sg:address":"Calle de Parroco Antonio Gil, 4",
    "sg:city":"Vega S. Mateo",
    "sg:orig_category":"Iglesia Cat\u00d3lica",
    "sg:phone":"+34 928 66 10 01",
    "sg:postcode":"35328",
    "sg:province":"Las Palmas",
    "wof:name":"Parroquia De San Mateo",
    "wof:placetype":"venue"
},
  "geometry": {"coordinates":[-15.5824928284,28.0158691406],"type":"Point"}
}