{
  "type": "Feature",
  "properties": {
    "iso:country":"ES",
    "sg:address":"Calle de Doctor Jose Manuel Puelles De Los Santos, 8",
    "sg:city":"Sevilla",
    "sg:orig_category":"Material Y Suministros Para Dentistas, Cirujanos",
    "sg:phone":"+34 954 90 14 45",
    "sg:postcode":"41009",
    "sg:province":"Sevilla",
    "wof:name":"Dental Center S.l.",
    "wof:placetype":"venue"
},
  "geometry": {"coordinates":[-5.9912624359,37.4084281921],"type":"Point"}
}