{
  "type": "Feature",
  "properties": {
    "addr:full":"Niza Mostoles Madrid 28936",
    "addr:postcode":"28936",
    "iso:country":"ES",
    "sg:address":"Niza",
    "sg:city":"Mostoles",
    "sg:orig_category":"Empresas De Portes Y Mensajer\u00cda",
    "sg:phone":"+34 916 85 21 17",
    "sg:postcode":"28936",
    "sg:province":"Madrid",
    "wof:name":"Transcom Logistica S.l.",
    "wof:placetype":"venue"
},
  "geometry": {"coordinates":[-3.8498589993,40.3264083862],"type":"Point"}
}