{
  "type": "Feature",
  "properties": {
    "addr:full":"Calle de Tomas Gonzalez Rivero, 2 Tejina Santa Cruz De Tenerife 38260",
    "addr:housenumber":"2",
    "addr:postcode":"38260",
    "addr:street":"Calle De Tomas Gonzalez Rivero",
    "iso:country":"ES",
    "sg:address":"Calle de Tomas Gonzalez Rivero, 2",
    "sg:city":"Tejina",
    "sg:orig_category":"Asesor\u00cda De Formaci\u00d3n Y Gesti\u00d3n De Personal",
    "sg:phone":"+34 922 54 36 31",
    "sg:postcode":"38260",
    "sg:province":"Santa Cruz De Tenerife",
    "wof:name":"Exposito Gonzalez Enrique",
    "wof:placetype":"venue"
},
  "geometry": {"coordinates":[-16.3608856201,28.5342826843],"type":"Point"}
}