{
  "type": "Feature",
  "properties": {
    "iso:country":"ES",
    "sg:address":"Marisma, 30",
    "sg:city":"Coria Rio",
    "sg:orig_category":"Inform\u00c1tica, Ofim\u00c1tica (estudios, Asesor\u00cda, Ingenier\u00cda, Formaci\u00d3n)",
    "sg:phone":"+34 954 77 33 45",
    "sg:postcode":"41100",
    "sg:province":"Sevilla",
    "wof:name":"Llamas Gonzalez Manuel",
    "wof:placetype":"venue"
},
  "geometry": {"coordinates":[-6.0509738922,37.2873153687],"type":"Point"}
}