{
  "type": "Feature",
  "properties": {
    "addr:full":"Avda Alt Rei En Jaume I (l'), 21 Altea Alicante 03590",
    "addr:housenumber":"21",
    "addr:postcode":"03590",
    "addr:street":"Avda Alt Rei En Jaume I L '",
    "iso:country":"ES",
    "sg:address":"Avda Alt Rei En Jaume I (l'), 21",
    "sg:city":"Altea",
    "sg:orig_category":"Ropa Para Se\u00d1oras Y Caballeros (al Por Menor)",
    "sg:phone":"+34 965 84 14 59",
    "sg:postcode":"03590",
    "sg:province":"Alicante",
    "wof:name":"Savall Cortes Vicente",
    "wof:placetype":"venue"
},
  "geometry": {"coordinates":[-0.0471620001,38.6018943787],"type":"Point"}
}