{
  "type": "Feature",
  "properties": {
    "iso:country":"ES",
    "sg:address":"Calle de Ibarra Kalea, 2",
    "sg:city":"Erandio",
    "sg:orig_category":"Bisuter\u00cda, Joyer\u00cda, Relojer\u00cda (al Por Menor)",
    "sg:phone":"+34 944 67 07 82",
    "sg:postcode":"48950",
    "sg:province":"Vizcaya",
    "wof:name":"Ana Maria Lorite Calvo- Eva Maria Lorite Calvo",
    "wof:placetype":"venue"
},
  "geometry": {"coordinates":[-2.9844002724,43.3000259399],"type":"Point"}
}