{
  "type": "Feature",
  "properties": {
    "iso:country":"ES",
    "sg:address":"Calle de Mayor, S/n",
    "sg:city":"Alhondiga",
    "sg:orig_category":"Centros De Educaci\u00d3n Especial",
    "sg:phone":"+34 949 28 42 14",
    "sg:postcode":"19132",
    "sg:province":"Guadalajara",
    "wof:name":"Colegio Rural Agrupado Pastrana",
    "wof:placetype":"venue"
},
  "geometry": {"coordinates":[-2.8241689205,40.5258789062],"type":"Point"}
}