{
  "type": "Feature",
  "properties": {
    "iso:country":"ES",
    "sg:address":"Calle de Illescas, 13",
    "sg:city":"Madrid",
    "sg:orig_category":"Peluqueros: De Se\u00d1oras",
    "sg:phone":"+34 915 18 92 05",
    "sg:postcode":"28024",
    "sg:province":"Madrid",
    "wof:name":"Mateo Puerto Rosa Maria",
    "wof:placetype":"venue"
},
  "geometry": {"coordinates":[-3.7649235725,40.3971939087],"type":"Point"}
}