{
  "type": "Feature",
  "properties": {
    "addr:full":"Rond Muralla (da), 193 Lugo Lugo 27002",
    "addr:housenumber":"193",
    "addr:postcode":"27002",
    "addr:street":"Rond;Da",
    "iso:country":"ES",
    "sg:address":"Rond Muralla (da), 193",
    "sg:city":"Lugo",
    "sg:orig_category":"Asesor\u00cda Fiscal Y Jur\u00cddica",
    "sg:phone":"+34 982 24 18 49",
    "sg:postcode":"27002",
    "sg:province":"Lugo",
    "wof:name":"Foro Avogados S.c.",
    "wof:placetype":"venue"
},
  "geometry": {"coordinates":[-7.5573191643,43.0083007812],"type":"Point"}
}