{
  "type": "Feature",
  "properties": {
    "iso:country":"ES",
    "sg:address":"Carr Conde De Oliva, 1",
    "sg:city":"Oliva",
    "sg:orig_category":"Caf\u00c9s, Bares, Cervecer\u00cdas",
    "sg:phone":"+34 962 83 94 86",
    "sg:postcode":"46780",
    "sg:province":"Valencia",
    "wof:name":"Navarro Anaya Julian",
    "wof:placetype":"venue"
},
  "geometry": {"coordinates":[-0.1150389984,38.9147911072],"type":"Point"}
}