{
  "type": "Feature",
  "properties": {
    "iso:country":"ES",
    "sg:address":"Ctra. Laujar-orgiva, Km. 0022,0",
    "sg:city":"Trevelez",
    "sg:orig_category":"Carnicer\u00cdas, Carnicer\u00cdas",
    "sg:phone":"+34 958 85 86 51",
    "sg:postcode":"18417",
    "sg:province":"Granada",
    "wof:name":"Jamones Cardales S.l.",
    "wof:placetype":"venue"
},
  "geometry": {"coordinates":[-3.2640340328,36.9989242554],"type":"Point"}
}