{
  "type": "Feature",
  "properties": {
    "iso:country":"ES",
    "sg:address":"Carrer de Sant Josep, 38",
    "sg:city":"Sitges",
    "sg:orig_category":"Electricidad: Equipos Industriales, Componentes (fabricaci\u00d3n)",
    "sg:phone":"+34 938 10 22 03",
    "sg:postcode":"08870",
    "sg:province":"Barcelona",
    "wof:name":"Suministros Electricos Abc Castelldefels S.l.",
    "wof:placetype":"venue"
},
  "geometry": {"coordinates":[1.8063240051,41.2380104065],"type":"Point"}
}