{
  "type": "Feature",
  "properties": {
    "iso:country":"ES",
    "sg:address":"Av Catalunya, 33",
    "sg:city":"Mont-ras",
    "sg:orig_category":"Almacenes De Venta: Muebles, Equipo Para El Hogar",
    "sg:phone":"+34 972 30 24 97",
    "sg:postcode":"17253",
    "sg:province":"Girona",
    "sg:website":"www.germobles.com",
    "wof:name":"Gerones Fontfreda Lluis",
    "wof:placetype":"venue"
},
  "geometry": {"coordinates":[3.1471099854,41.9118232727],"type":"Point"}
}