{
  "type": "Feature",
  "properties": {
    "addr:full":"Calle de Moral, 19 Villaverde Y Pasaconsol Cuenca 16110",
    "addr:housenumber":"19",
    "addr:postcode":"16110",
    "addr:street":"Calle De Moral",
    "iso:country":"ES",
    "sg:address":"Calle de Moral, 19",
    "sg:city":"Villaverde Y Pasaconsol",
    "sg:orig_category":"Carnicer\u00cdas, Carnicer\u00cdas",
    "sg:phone":"+34 969 20 26 15",
    "sg:postcode":"16110",
    "sg:province":"Cuenca",
    "wof:name":"Moya Diaz Pedro",
    "wof:placetype":"venue"
},
  "geometry": {"coordinates":[-2.26583004,39.7710037231],"type":"Point"}
}