{
  "type": "Feature",
  "properties": {
    "addr:full":"Calle de Rio Mesa, 28 Torremolinos M\u00e1laga 29620",
    "addr:housenumber":"28",
    "addr:postcode":"29620",
    "addr:street":"Calle De Rio Mesa;Ma\u0301Laga",
    "iso:country":"ES",
    "sg:address":"Calle de Rio Mesa, 28",
    "sg:city":"Torremolinos",
    "sg:orig_category":"M\u00c9dicos: Cirug\u00cda Pl\u00c1stica, Reconstructiva Y Est\u00c9tica",
    "sg:phone":"+34 952 37 06 16",
    "sg:postcode":"29620",
    "sg:province":"M\u00e1laga",
    "wof:name":"Aguilar Rosell Maria Del Pilar",
    "wof:placetype":"venue"
},
  "geometry": {"coordinates":[-4.4994258881,36.6289558411],"type":"Point"}
}