{
  "type": "Feature",
  "properties": {
    "iso:country":"ES",
    "sg:address":"Calle de Tejera, 25",
    "sg:city":"Valdepe\u00f1as",
    "sg:orig_category":"Reposter\u00cdas",
    "sg:phone":"+34 926 32 27 90",
    "sg:postcode":"13300",
    "sg:province":"Ciudad Real",
    "wof:name":"Pan Domench E Hijas S.l.",
    "wof:placetype":"venue"
},
  "geometry": {"coordinates":[-3.3903570175,38.7563056946],"type":"Point"}
}