{
  "type": "Feature",
  "properties": {
    "iso:country":"ES",
    "sg:address":"Plaz Mayor, 2",
    "sg:city":"Chelva",
    "sg:orig_category":"Reparaci\u00d3n Y Restauraci\u00d3n De Objetos Diversos",
    "sg:phone":"+34 962 10 04 02",
    "sg:postcode":"46176",
    "sg:province":"Valencia",
    "wof:name":"Mu\u00f1oz Sevilla Jose",
    "wof:placetype":"venue"
},
  "geometry": {"coordinates":[-0.9949319959,39.7486228943],"type":"Point"}
}