{
  "type": "Feature",
  "properties": {
    "addr:full":"Calle de Velarde, 20 Linares Ja\u00e9n 23700",
    "addr:housenumber":"20",
    "addr:postcode":"23700",
    "addr:street":"Calle De Velarde;Jae\u0301N",
    "iso:country":"ES",
    "sg:address":"Calle de Velarde, 20",
    "sg:city":"Linares",
    "sg:orig_category":"Internados & Ense\u00d1anza Privada",
    "sg:phone":"+34 953 69 77 23",
    "sg:postcode":"23700",
    "sg:province":"Ja\u00e9n",
    "wof:name":"Colegio La Inmaculada Concepcion",
    "wof:placetype":"venue"
},
  "geometry": {"coordinates":[-3.6298270226,38.0985069275],"type":"Point"}
}