{
  "type": "Feature",
  "properties": {
    "addr:full":"Ctra. Gijon-sevilla, Km. 0069,0 Bejar Salamanca 37700",
    "addr:postcode":"37700",
    "addr:street":"Ctra. Gijon-Sevilla Km. 0069,0",
    "iso:country":"ES",
    "sg:address":"Ctra. Gijon-sevilla, Km. 0069,0",
    "sg:city":"Bejar",
    "sg:orig_category":"Fabricaci\u00d3n De Telas Y Sedas",
    "sg:phone":"+34 923 40 25 18",
    "sg:postcode":"37700",
    "sg:province":"Salamanca",
    "wof:name":"Torrico Rubio Gerardo",
    "wof:placetype":"venue"
},
  "geometry": {"coordinates":[-5.7728161812,40.3881263733],"type":"Point"}
}