{
  "type": "Feature",
  "properties": {
    "addr:full":"Carr Moll De Llevant, 217 Mao Islas Baleares 07703",
    "addr:housenumber":"217",
    "addr:postcode":"07703",
    "addr:street":"Carr Moll De Llevant",
    "iso:country":"ES",
    "sg:address":"Carr Moll De Llevant, 217",
    "sg:city":"Mao",
    "sg:orig_category":"Deportes N\u00c1uticos, Acu\u00c1ticos Y Subacu\u00c1ticos: Art\u00cdculos Y Equipo (al Por Menor)",
    "sg:phone":"+34 971 35 33 07",
    "sg:postcode":"07703",
    "sg:province":"Islas Baleares",
    "wof:name":"Barnard Hamilton Menorca, S.l.",
    "wof:placetype":"venue"
},
  "geometry": {"coordinates":[4.265625,39.8903694153],"type":"Point"}
}