{
  "type": "Feature",
  "properties": {
    "addr:full":"Calle de Senador Castillo Olivares, 57 Palmas De Gran Canaria Las Palmas 35003",
    "addr:postcode":"35003",
    "addr:street":"Calle De Senador Castillo Olivares 57",
    "iso:country":"ES",
    "sg:address":"Calle de Senador Castillo Olivares, 57",
    "sg:city":"Palmas De Gran Canaria",
    "sg:orig_category":"Farmacias",
    "sg:phone":"+34 928 36 74 11",
    "sg:postcode":"35003",
    "sg:province":"Las Palmas",
    "wof:name":"Mateo Faura Maria Del Carmen",
    "wof:placetype":"venue"
},
  "geometry": {"coordinates":[-15.4211559296,28.1093120575],"type":"Point"}
}