{
  "type": "Feature",
  "properties": {
    "iso:country":"ES",
    "sg:address":"Calle de Forsitia (de La), 3",
    "sg:city":"Alcobendas",
    "sg:orig_category":"Inmobiliaria (agencias)",
    "sg:phone":"+34 916 50 16 84",
    "sg:postcode":"28109",
    "sg:province":"Madrid",
    "wof:name":"Mejordan Proyectos Inmobiliarios S.l",
    "wof:placetype":"venue"
},
  "geometry": {"coordinates":[-3.6422469616,40.5202827454],"type":"Point"}
}