{
  "type": "Feature",
  "properties": {
    "iso:country":"ES",
    "sg:address":"Calle de Pe\u00d1a Sacra, 18",
    "sg:city":"Galapagar",
    "sg:orig_category":"Asesor\u00cdas En Comunicaci\u00d3n",
    "sg:phone":"+34 918 58 75 55",
    "sg:postcode":"28260",
    "sg:province":"Madrid",
    "sg:website":"www.stelb2m.com",
    "wof:name":"Strong Element S.l.",
    "wof:placetype":"venue"
},
  "geometry": {"coordinates":[-4.0067801476,40.5815086365],"type":"Point"}
}