{
  "type": "Feature",
  "properties": {
    "addr:full":"Carrer de Regal, 36 Palma Islas Baleares 07008",
    "addr:housenumber":"36",
    "addr:postcode":"07008",
    "addr:street":"Carrer De Regal",
    "iso:country":"ES",
    "sg:address":"Carrer de Regal, 36",
    "sg:city":"Palma",
    "sg:orig_category":"Mec\u00c1nico Del Autom\u00d3vil",
    "sg:phone":"+34 971 27 66 71",
    "sg:postcode":"07008",
    "sg:province":"Islas Baleares",
    "wof:name":"Antonio Frau Miguel",
    "wof:placetype":"venue"
},
  "geometry": {"coordinates":[2.6725342274,39.5748329163],"type":"Point"}
}