{
  "type": "Feature",
  "properties": {
    "iso:country":"ES",
    "sg:address":"Calle de Pablo Casals, 11",
    "sg:city":"Marbella",
    "sg:orig_category":"Bisuter\u00cda, Joyer\u00cda, Relojer\u00cda (al Por Menor)",
    "sg:phone":"+34 952 86 86 73",
    "sg:postcode":"29600",
    "sg:province":"M\u00e1laga",
    "wof:name":"Martin Zayas Juan",
    "wof:placetype":"venue"
},
  "geometry": {"coordinates":[-4.8949999809,36.5089035034],"type":"Point"}
}