{
  "type": "Feature",
  "properties": {
    "iso:country":"ES",
    "sg:address":"Calle de Virgen De La Cinta, 27",
    "sg:city":"Sevilla",
    "sg:orig_category":"Papeler\u00cdas, Librer\u00cdas",
    "sg:phone":"+34 954 45 58 43",
    "sg:postcode":"41011",
    "sg:province":"Sevilla",
    "wof:name":"Saucedo Rodriguez Rosario",
    "wof:placetype":"venue"
},
  "geometry": {"coordinates":[-5.9999899864,37.3722991943],"type":"Point"}
}