{
  "type": "Feature",
  "properties": {
    "addr:full":"Calle de Andres Mellado, 65 Madrid Madrid 28015",
    "addr:housenumber":"65",
    "addr:postcode":"madrid;28015",
    "addr:street":"Calle De Andres Mellado",
    "iso:country":"ES",
    "sg:address":"Calle de Andres Mellado, 65",
    "sg:city":"Madrid",
    "sg:orig_category":"Edici\u00d3n De Diarios, Revistas, Boletines",
    "sg:phone":"+34 915 44 82 21",
    "sg:postcode":"28015",
    "sg:province":"Madrid",
    "sg:website":"www.preferente.com",
    "wof:name":"K.b.a. S.l.",
    "wof:placetype":"venue"
},
  "geometry": {"coordinates":[-3.7141890526,40.4378509521],"type":"Point"}
}