{
  "type": "Feature",
  "properties": {
    "iso:country":"ES",
    "sg:address":"Verge Roser, 41",
    "sg:city":"Sedavi",
    "sg:orig_category":"Ebanister\u00cda",
    "sg:phone":"+34 963 75 15 46",
    "sg:postcode":"46910",
    "sg:province":"Valencia",
    "wof:name":"Ricardo Llorca S. L.",
    "wof:placetype":"venue"
},
  "geometry": {"coordinates":[-0.3863910139,39.4272460938],"type":"Point"}
}