{
  "type": "Feature",
  "properties": {
    "iso:country":"ES",
    "sg:address":"Calle de Veracruz, 37",
    "sg:city":"Estepa",
    "sg:classifiers":[
        {
            "category":"Communications",
            "type":"Services"
        }
    ],
    "sg:phone":"+34 955 91 58 62",
    "sg:postcode":"41560",
    "sg:province":"Sevilla",
    "sg:tags":[
        "televisiones",
        "y",
        "radio"
    ],
    "sg:website":"www.cadenaser.com",
    "wof:name":"Estepa De Comunicaciones S.l.",
    "wof:placetype":"venue"
},
  "geometry": {"coordinates":[-4.883518219,37.2881736755],"type":"Point"}
}