{
  "type": "Feature",
  "properties": {
    "addr:full":"Carrer de Almirall Bonifaz, 5 Palma Islas Baleares 07014",
    "addr:housenumber":"5",
    "addr:postcode":"07014",
    "addr:street":"Carrer De Almirall Bonifaz",
    "iso:country":"ES",
    "sg:address":"Carrer de Almirall Bonifaz, 5",
    "sg:city":"Palma",
    "sg:orig_category":"Arquitectos",
    "sg:phone":"+34 971 45 66 80",
    "sg:postcode":"07014",
    "sg:province":"Islas Baleares",
    "wof:name":"Casasayas Ladaria Jose Maria",
    "wof:placetype":"venue"
},
  "geometry": {"coordinates":[2.6265349388,39.5704154968],"type":"Point"}
}