{
  "type": "Feature",
  "properties": {
    "iso:country":"ES",
    "sg:address":"Calle de Real, 7",
    "sg:city":"Valdepe\u00e7as De Jaen",
    "sg:orig_category":"M\u00c9dicos: Estomatolog\u00cda",
    "sg:phone":"+34 953 31 10 36",
    "sg:postcode":"23150",
    "sg:province":"Ja\u00e9n",
    "wof:name":"Jimenez Li\u00f1an Rafael",
    "wof:placetype":"venue"
},
  "geometry": {"coordinates":[-3.8183441162,37.5898704529],"type":"Point"}
}