{
  "type": "Feature",
  "properties": {
    "iso:country":"ES",
    "sg:address":"Avda Paz (de La), 37",
    "sg:city":"Casalarreina",
    "sg:orig_category":"Caf\u00c9s, Bares, Cervecer\u00cdas",
    "sg:phone":"+34 941 32 43 77",
    "sg:postcode":"26230",
    "sg:province":"La Rioja",
    "wof:name":"Saiz Caperos Concepcion",
    "wof:placetype":"venue"
},
  "geometry": {"coordinates":[-2.9114980698,42.5482635498],"type":"Point"}
}