{
  "type": "Feature",
  "properties": {
    "iso:country":"ES",
    "sg:address":"Poli Cantabria, 10",
    "sg:city":"Logro\u00f1o",
    "sg:orig_category":"Electricidad: Instalaciones Industriales",
    "sg:phone":"+34 941 24 20 44",
    "sg:postcode":"26006",
    "sg:province":"La Rioja",
    "wof:name":"Hemasa Montajes Electricos S.l.",
    "wof:placetype":"venue"
},
  "geometry": {"coordinates":[-2.4036989212,42.46043396],"type":"Point"}
}