{
  "type": "Feature",
  "properties": {
    "iso:country":"ES",
    "sg:address":"Plaza Euskadi",
    "sg:city":"Zalla",
    "sg:orig_category":"Sanatorios M\u00c9dico",
    "sg:phone":"+34 946 00 75 90",
    "sg:postcode":"48860",
    "sg:province":"Vizcaya",
    "wof:name":"Osakidetza",
    "wof:placetype":"venue"
},
  "geometry": {"coordinates":[-3.1322689056,43.214630127],"type":"Point"}
}