{
  "type": "Feature",
  "properties": {
    "addr:full":"Cala Finestrat, S/n Finestrat Alicante 03509",
    "addr:housenumber":"s / n",
    "addr:postcode":"03509",
    "iso:country":"ES",
    "sg:address":"Cala Finestrat, S/n",
    "sg:city":"Finestrat",
    "sg:orig_category":"Edici\u00d3n De Diarios, Revistas, Boletines",
    "sg:phone":"+34 965 85 52 86",
    "sg:postcode":"03509",
    "sg:province":"Alicante",
    "wof:name":"Rotativos Del Mediterraneo S.l.",
    "wof:placetype":"venue"
},
  "geometry": {"coordinates":[-0.1988539994,38.5523109436],"type":"Point"}
}