{
  "type": "Feature",
  "properties": {
    "addr:full":"Carr Sant Ciril, 51 Mao Islas Baleares 07702",
    "addr:housenumber":"51",
    "addr:postcode":"07702",
    "addr:street":"Carr Sant Ciril",
    "iso:country":"ES",
    "sg:address":"Carr Sant Ciril, 51",
    "sg:city":"Mao",
    "sg:orig_category":"Inform\u00c1tica (estudios, Servicios, Asesor\u00cda, Formaci\u00d3n)",
    "sg:phone":"+34 971 35 60 45",
    "sg:postcode":"07702",
    "sg:province":"Islas Baleares",
    "wof:name":"Servei D'informatica Local De Menorca S.a.",
    "wof:placetype":"venue"
},
  "geometry": {"coordinates":[4.2662968636,39.8827133179],"type":"Point"}
}