{
  "type": "Feature",
  "properties": {
    "iso:country":"ES",
    "sg:address":"Carrer de Murillo, 8",
    "sg:city":"Cornella Llobregat",
    "sg:orig_category":"Pintura, Barniz, Productos Asimilables (fabricaci\u00d3n, Al Por Mayor)",
    "sg:phone":"+34 933 77 31 35",
    "sg:postcode":"08940",
    "sg:province":"Barcelona",
    "wof:name":"Sanchez Martin Yolanda",
    "wof:placetype":"venue"
},
  "geometry": {"coordinates":[2.0685789585,41.3547897339],"type":"Point"}
}