{
  "type": "Feature",
  "properties": {
    "addr:full":"Calle de Iryda, S/n Vilamartin Valdeorras Ourense 32340",
    "addr:housenumber":"s",
    "addr:postcode":"32340",
    "addr:street":"Calle De Iryda;/ N",
    "iso:country":"ES",
    "sg:address":"Calle de Iryda, S/n",
    "sg:city":"Vilamartin Valdeorras",
    "sg:orig_category":"Reposter\u00cdas",
    "sg:phone":"+34 988 30 00 09",
    "sg:postcode":"32340",
    "sg:province":"Ourense",
    "wof:name":"Vali\u00d1as Alvares Armando",
    "wof:placetype":"venue"
},
  "geometry": {"coordinates":[-7.0576500893,42.4162940979],"type":"Point"}
}