{
  "type": "Feature",
  "properties": {
    "iso:country":"ES",
    "sg:address":"Calle de Predicadores, 119",
    "sg:city":"Zaragoza",
    "sg:orig_category":"Empresas De Carpinter\u00cda",
    "sg:phone":"+34 976 44 67 99",
    "sg:postcode":"50003",
    "sg:province":"Zaragoza",
    "wof:name":"Cerrajeria Y Aluminios Ancora S.l.",
    "wof:placetype":"venue"
},
  "geometry": {"coordinates":[-0.8880540133,41.6576080322],"type":"Point"}
}