{
  "type": "Feature",
  "properties": {
    "iso:country":"ES",
    "sg:address":"Carrer de Enrico Caruso (d'), 37",
    "sg:city":"Pineda",
    "sg:orig_category":"Metales (labores, Pulido)",
    "sg:phone":"+34 977 37 20 56",
    "sg:postcode":"43480",
    "sg:province":"Tarragona",
    "wof:name":"Reus Dfc Metal S.l.",
    "wof:placetype":"venue"
},
  "geometry": {"coordinates":[1.1441899538,41.1080245972],"type":"Point"}
}