{
  "type": "Feature",
  "properties": {
    "iso:country":"ES",
    "sg:address":"Calle de Juan De La Cierva, 33",
    "sg:city":"Grela",
    "sg:orig_category":"Suministros Y Materiales Industriales",
    "sg:phone":"+34 981 25 96 50",
    "sg:postcode":"15008",
    "sg:province":"A Coru\u00f1a",
    "wof:name":"Vazquez Diaz Jose Luis",
    "wof:placetype":"venue"
},
  "geometry": {"coordinates":[-8.4512443542,43.3434753418],"type":"Point"}
}