{
  "type": "Feature",
  "properties": {
    "addr:full":"Via Pasteur (de), 22 Boisaca A Coru\u00f1a 15890",
    "addr:housenumber":"22",
    "addr:postcode":"15890",
    "addr:street":"Via Pasteur De;Corun\u0303A",
    "iso:country":"ES",
    "sg:address":"Via Pasteur (de), 22",
    "sg:city":"Boisaca",
    "sg:classifiers":[
        {
            "category":"Professional",
            "subcategory":"Management & Consulting",
            "type":"Services"
        }
    ],
    "sg:phone":"+34 902 38 13 91",
    "sg:postcode":"15890",
    "sg:province":"A Coru\u00f1a",
    "sg:tags":[
        "asesor\u00cda",
        "en",
        "marketing"
    ],
    "wof:name":"Work Wear S.l.",
    "wof:placetype":"venue"
},
  "geometry": {"coordinates":[-8.3959693909,43.3714904785],"type":"Point"}
}