{
  "type": "Feature",
  "properties": {
    "iso:country":"ES",
    "sg:address":"Ctra Marmoles (de Los), S/n",
    "sg:city":"Arrecife",
    "sg:orig_category":"Madera (al Por Menor)",
    "sg:phone":"+34 928 80 59 93",
    "sg:postcode":"35500",
    "sg:province":"Las Palmas",
    "wof:name":"Maderas M.viera Ftv.s.l.",
    "wof:placetype":"venue"
},
  "geometry": {"coordinates":[-13.5436439514,28.9689598083],"type":"Point"}
}