{
  "type": "Feature",
  "properties": {
    "addr:full":"Logoso, S/n Logoso La Coru\u00f1a 15151",
    "addr:postcode":"15151",
    "addr:street":"Logoso S / N Logoso La Corun\u0303A",
    "iso:country":"ES",
    "sg:address":"Logoso, S/n",
    "sg:city":"Logoso",
    "sg:orig_category":"Empresas De Desmonte",
    "sg:phone":"+34 981 72 76 05",
    "sg:postcode":"15151",
    "sg:province":"La Coru\u00f1a",
    "wof:name":"Excavaciones Y Desmontes",
    "wof:placetype":"venue"
},
  "geometry": {"coordinates":[-9.1179704666,43.0104026794],"type":"Point"}
}