{
  "type": "Feature",
  "properties": {
    "addr:full":"Calle de Sierra Nevada, 64 Urbanizacion Roquetas De Mar Almer\u00eda 04740",
    "addr:housenumber":"64",
    "addr:postcode":"04740",
    "addr:street":"Calle De Sierra Nevada",
    "iso:country":"ES",
    "sg:address":"Calle de Sierra Nevada, 64",
    "sg:city":"Urbanizacion Roquetas De Mar",
    "sg:orig_category":"Alimentaci\u00d3n General (al Por Menor)",
    "sg:phone":"+34 950 33 44 40",
    "sg:postcode":"04740",
    "sg:province":"Almer\u00eda",
    "wof:name":"Suero Seijas Miguel",
    "wof:placetype":"venue"
},
  "geometry": {"coordinates":[-2.6137111187,36.7678031921],"type":"Point"}
}