{
  "type": "Feature",
  "properties": {
    "iso:country":"ES",
    "sg:address":"Avda Madrid (de), 28",
    "sg:city":"Molina Segura",
    "sg:orig_category":"Vinos (agentes)",
    "sg:phone":"+34 968 64 29 72",
    "sg:postcode":"30500",
    "sg:province":"Murcia",
    "wof:name":"Sovisur S.a.",
    "wof:placetype":"venue"
},
  "geometry": {"coordinates":[-1.2137479782,38.0559692383],"type":"Point"}
}