{
  "type": "Feature",
  "properties": {
    "iso:country":"ES",
    "sg:address":"Calle de Capitan Adolfo Paya, 1",
    "sg:city":"Alacant",
    "sg:orig_category":"Carnicer\u00cdas, Carnicer\u00cdas",
    "sg:phone":"+34 965 28 35 96",
    "sg:postcode":"03006",
    "sg:province":"Alicante",
    "wof:name":"Fuster Thaudiere Enrique",
    "wof:placetype":"venue"
},
  "geometry": {"coordinates":[-0.5051968098,38.3462028503],"type":"Point"}
}