{
  "type": "Feature",
  "properties": {
    "addr:full":"Calle de Manuel Rances, 2 Cadiz C\u00e1diz 11004",
    "addr:housenumber":"2",
    "addr:postcode":"11004",
    "addr:street":"Calle De Manuel Rances",
    "iso:country":"ES",
    "sg:address":"Calle de Manuel Rances, 2",
    "sg:city":"Cadiz",
    "sg:orig_category":"Electricidad (montaje, Ensamblaje De Componentes)",
    "sg:phone":"+34 956 22 55 45",
    "sg:postcode":"11004",
    "sg:province":"C\u00e1diz",
    "wof:name":"Sanchez Medina Federico",
    "wof:placetype":"venue"
},
  "geometry": {"coordinates":[-6.2948870659,36.5344467163],"type":"Point"}
}