{
  "type": "Feature",
  "properties": {
    "addr:full":"Av Matadepera, 107 Sabadell Barcelona 08207",
    "addr:housenumber":"107",
    "addr:postcode":"08207",
    "addr:street":"Av Matadepera",
    "iso:country":"ES",
    "sg:address":"Av Matadepera, 107",
    "sg:city":"Sabadell",
    "sg:orig_category":"Molduras, Junquillos, Listones Y Molduras Perforadas",
    "sg:phone":"+34 937 16 37 15",
    "sg:postcode":"08207",
    "sg:province":"Barcelona",
    "wof:name":"Moreno Roldan Jose Ramon",
    "wof:placetype":"venue"
},
  "geometry": {"coordinates":[2.089081049,41.5664024353],"type":"Point"}
}