{
  "type": "Feature",
  "properties": {
    "iso:country":"ES",
    "sg:address":"Calle de Vicente Andres Estelles, 36",
    "sg:city":"Puerto",
    "sg:orig_category":"Art\u00cdculos De Decoraci\u00d3n",
    "sg:phone":"+34 962 69 07 14",
    "sg:postcode":"46520",
    "sg:province":"Valencia",
    "wof:name":"Sanchez Fernandez Alicia Rosario",
    "wof:placetype":"venue"
},
  "geometry": {"coordinates":[-0.2202499956,39.6621665955],"type":"Point"}
}