{
  "type": "Feature",
  "properties": {
    "addr:full":"Calle de Literato Azorin, 17 Valencia Valencia 46006",
    "addr:housenumber":"17",
    "addr:postcode":"46006",
    "addr:street":"Calle De Literato Azorin",
    "iso:country":"ES",
    "sg:address":"Calle de Literato Azorin, 17",
    "sg:city":"Valencia",
    "sg:orig_category":"Copas, Insignias, Trofeos",
    "sg:phone":"+34 963 80 25 58",
    "sg:postcode":"46006",
    "sg:province":"Valencia",
    "wof:name":"Ruiz Palomero Mercedes",
    "wof:placetype":"venue"
},
  "geometry": {"coordinates":[-0.3744390011,39.4601478577],"type":"Point"}
}