{
  "type": "Feature",
  "properties": {
    "addr:full":"Calle de San Andres, 59 Narbarte Navarra 31793",
    "addr:housenumber":"59",
    "addr:postcode":"31793",
    "addr:street":"Calle De San Andres",
    "iso:country":"ES",
    "sg:address":"Calle de San Andres, 59",
    "sg:city":"Narbarte",
    "sg:orig_category":"Asistencia Social",
    "sg:phone":"+34 948 59 24 99",
    "sg:postcode":"31793",
    "sg:province":"Navarra",
    "wof:name":"Sagaseta Irigoyen Alizia",
    "wof:placetype":"venue"
},
  "geometry": {"coordinates":[-1.6282759905,43.1338653564],"type":"Point"}
}