{
  "type": "Feature",
  "properties": {
    "addr:full":"Plaz Ayuntamiento, 2 O\u00f1a Burgos 09530",
    "addr:housenumber":"2",
    "addr:postcode":"09530",
    "addr:street":"Ayuntamiento",
    "iso:country":"ES",
    "sg:address":"Plaz Ayuntamiento, 2",
    "sg:city":"O\u00f1a",
    "sg:orig_category":"Asociaciones, Organismos Culturales Y Socioeducativos",
    "sg:phone":"+34 947 30 02 64",
    "sg:postcode":"09530",
    "sg:province":"Burgos",
    "sg:website":"www.cajadeburgos.es",
    "wof:name":"Caja De Ahorros Municipal De Burgos",
    "wof:placetype":"venue"
},
  "geometry": {"coordinates":[-3.417773962,42.7337493896],"type":"Point"}
}