{
  "type": "Feature",
  "properties": {
    "addr:full":"Calle de Castilla-la Mancha, 13 Barakaldo Vizcaya 48901",
    "addr:housenumber":"13",
    "addr:postcode":"48901",
    "addr:street":"Calle De Castilla-La Mancha",
    "iso:country":"ES",
    "sg:address":"Calle de Castilla-la Mancha, 13",
    "sg:city":"Barakaldo",
    "sg:orig_category":"Alimentaci\u00d3n General (al Por Menor)",
    "sg:phone":"+34 944 37 23 35",
    "sg:postcode":"48901",
    "sg:province":"Vizcaya",
    "wof:name":"Txetxu Zearra Manrique",
    "wof:placetype":"venue"
},
  "geometry": {"coordinates":[-2.984940052,43.2952575684],"type":"Point"}
}