{
  "type": "Feature",
  "properties": {
    "addr:full":"Calle de Bebricio, 3 Calahorra La Rioja 26500",
    "addr:housenumber":"3",
    "addr:postcode":"26500",
    "addr:street":"Calle De Bebricio",
    "iso:country":"ES",
    "sg:address":"Calle de Bebricio, 3",
    "sg:city":"Calahorra",
    "sg:orig_category":"Tintes (fabricaci\u00d3n, Al Por Mayor)",
    "sg:phone":"+34 941 13 08 98",
    "sg:postcode":"26500",
    "sg:province":"La Rioja",
    "sg:website":"www.pressto.com",
    "wof:name":"Quilencheo S.l.",
    "wof:placetype":"venue"
},
  "geometry": {"coordinates":[-1.96884799,42.3056144714],"type":"Point"}
}