{
  "type": "Feature",
  "properties": {
    "iso:country":"ES",
    "sg:address":"Calle de Soria, S/n",
    "sg:city":"Burgos",
    "sg:orig_category":"Caf\u00c9s, Bares, Cervecer\u00cdas",
    "sg:phone":"+34 947 21 84 13",
    "sg:postcode":"09004",
    "sg:province":"Burgos",
    "wof:name":"Cafeteria El Duende S.a.l.",
    "wof:placetype":"venue"
},
  "geometry": {"coordinates":[-3.6911709309,42.3482894897],"type":"Point"}
}