{
  "type": "Feature",
  "properties": {
    "addr:full":"Calle de Luis Bu\u00d1uel, 17 Teruel Teruel 44002",
    "addr:housenumber":"17",
    "addr:postcode":"44002",
    "addr:street":"Calle De Luis Bun\u0303Uel",
    "iso:country":"ES",
    "sg:address":"Calle de Luis Bu\u00d1uel, 17",
    "sg:city":"Teruel",
    "sg:orig_category":"Ense\u00d1anza: Comercio, Gesti\u00d3n, Inform\u00c1tica",
    "sg:phone":"+34 978 61 22 37",
    "sg:postcode":"44002",
    "sg:province":"Teruel",
    "wof:name":"Alonso Infonet S:l",
    "wof:placetype":"venue"
},
  "geometry": {"coordinates":[-1.0906629562,40.3323097229],"type":"Point"}
}