{
  "type": "Feature",
  "properties": {
    "iso:country":"ES",
    "sg:address":"Ctra. Montijo, Km. 0022,8",
    "sg:city":"Merida",
    "sg:orig_category":"Arenas, Guijarros Y Granulados",
    "sg:phone":"+34 924 31 46 12",
    "sg:postcode":"06800",
    "sg:province":"Badajoz",
    "sg:website":"www.carija.es",
    "wof:name":"Carija S. A.",
    "wof:placetype":"venue"
},
  "geometry": {"coordinates":[-6.3464841843,38.916053772],"type":"Point"}
}