{
  "type": "Feature",
  "properties": {
    "iso:country":"ES",
    "sg:address":"Calle de Leon, 19",
    "sg:city":"Orotava",
    "sg:orig_category":"Ense\u00d1anza, Formaci\u00d3n Profesional: Aprendizaje",
    "sg:phone":"+34 922 32 80 47",
    "sg:postcode":"38300",
    "sg:province":"Santa Cruz De Tenerife",
    "wof:name":"Excelentisimo Ayuntamiento De La Orotava",
    "wof:placetype":"venue"
},
  "geometry": {"coordinates":[-16.5236759186,28.3889408112],"type":"Point"}
}