{
  "type": "Feature",
  "properties": {
    "iso:country":"ES",
    "sg:address":"Calle de Valdes, 24",
    "sg:city":"Puerto De Santa Maria",
    "sg:orig_category":"Peluquer\u00cdas, Peluquer\u00cda Mixta",
    "sg:phone":"+34 956 87 55 53",
    "sg:postcode":"11500",
    "sg:province":"C\u00e1diz",
    "wof:name":"Lopez Moreno Juana",
    "wof:placetype":"venue"
},
  "geometry": {"coordinates":[-6.2356801033,36.5978660583],"type":"Point"}
}