{
  "type": "Feature",
  "properties": {
    "addr:full":"Bjad Corral De Don Diego, 9 Toledo Toledo 45001",
    "addr:housenumber":"9",
    "addr:postcode":"45001",
    "addr:street":"Diego",
    "iso:country":"ES",
    "sg:address":"Bjad Corral De Don Diego, 9",
    "sg:city":"Toledo",
    "sg:orig_category":"Empresas De Carpinter\u00cda De Madera",
    "sg:phone":"+34 925 22 32 51",
    "sg:postcode":"45001",
    "sg:province":"Toledo",
    "wof:name":"Badia Ortiz Antonia",
    "wof:placetype":"venue"
},
  "geometry": {"coordinates":[-4.0197424889,39.8591537476],"type":"Point"}
}