{
  "type": "Feature",
  "properties": {
    "addr:full":"Calle de Arguayoda, S/n San Isidro Santa Cruz De Tenerife 38611",
    "addr:housenumber":"s / n",
    "addr:postcode":"38611",
    "addr:street":"Calle De Arguayoda",
    "iso:country":"ES",
    "sg:address":"Calle de Arguayoda, S/n",
    "sg:city":"San Isidro",
    "sg:orig_category":"Periodistas Profesionales",
    "sg:phone":"+34 922 39 26 35",
    "sg:postcode":"38611",
    "sg:province":"Santa Cruz De Tenerife",
    "wof:name":"Editorial Leoncio Rodriguez S.a.",
    "wof:placetype":"venue"
},
  "geometry": {"coordinates":[-16.5545501709,28.0717906952],"type":"Point"}
}