{
  "type": "Feature",
  "properties": {
    "iso:country":"ES",
    "sg:address":"Carrer de Sant Miquel, 12",
    "sg:city":"Argentona",
    "sg:orig_category":"Quincaller\u00cda (al Por Menor)",
    "sg:phone":"+34 937 97 03 03",
    "sg:postcode":"08310",
    "sg:province":"Barcelona",
    "wof:name":"Llado Badosa Marcel",
    "wof:placetype":"venue"
},
  "geometry": {"coordinates":[2.4021959305,41.5547943115],"type":"Point"}
}