{
  "type": "Feature",
  "properties": {
    "iso:country":"ES",
    "sg:address":"Carrer de Ramon Berenguer Iv (de), 6",
    "sg:city":"Salou",
    "sg:orig_category":"Empresas De Limpieza",
    "sg:phone":"+34 977 38 41 02",
    "sg:postcode":"43840",
    "sg:province":"Tarragona",
    "wof:name":"Neteges-cosip S.l.",
    "wof:placetype":"venue"
},
  "geometry": {"coordinates":[1.1403700113,41.0768051147],"type":"Point"}
}