{
  "type": "Feature",
  "properties": {
    "iso:country":"ES",
    "sg:address":"Rbla Pulido, 73",
    "sg:city":"Santa Cruz De Tenerife",
    "sg:orig_category":"Asociaciones Y Clubs Deportivos",
    "sg:phone":"+34 922 29 08 85",
    "sg:postcode":"38004",
    "sg:province":"Santa Cruz De Tenerife",
    "wof:name":"Gilesqui S.l.",
    "wof:placetype":"venue"
},
  "geometry": {"coordinates":[-16.2601604462,28.46758461],"type":"Point"}
}