{
  "type": "Feature",
  "properties": {
    "iso:country":"ES",
    "sg:address":"A Cavadi\u00f1a, S/n",
    "sg:city":"Cabadi\u00d1a",
    "sg:orig_category":"Negocio De Madera",
    "sg:phone":"+34 986 33 09 11",
    "sg:postcode":"36413",
    "sg:province":"Pontevedra",
    "wof:name":"Maceira Lopez Juan",
    "wof:placetype":"venue"
},
  "geometry": {"coordinates":[-8.6597137451,42.1184768677],"type":"Point"}
}