{
  "type": "Feature",
  "properties": {
    "iso:country":"ES",
    "sg:address":"Calle de Garran, 2",
    "sg:city":"Najera",
    "sg:orig_category":"Alimentaci\u00d3n General (al Por Menor)",
    "sg:phone":"+34 941 36 33 97",
    "sg:postcode":"26300",
    "sg:province":"La Rioja",
    "wof:name":"Morras Hernandez Maria Josefa",
    "wof:placetype":"venue"
},
  "geometry": {"coordinates":[-2.7345409393,42.4165000916],"type":"Point"}
}