{
  "type": "Feature",
  "properties": {
    "addr:full":"Avda Menendez Pelayo, 34 Madrid Madrid 28007",
    "addr:housenumber":"34",
    "addr:postcode":"madrid;28007",
    "addr:street":"Avda Menendez Pelayo",
    "iso:country":"ES",
    "sg:address":"Avda Menendez Pelayo, 34",
    "sg:city":"Madrid",
    "sg:orig_category":"Electricidad: Instaladores",
    "sg:phone":"+34 915 51 32 36",
    "sg:postcode":"28007",
    "sg:province":"Madrid",
    "wof:name":"Barberan Martinez Jose Maria",
    "wof:placetype":"venue"
},
  "geometry": {"coordinates":[-3.6802470684,40.4056015015],"type":"Point"}
}