{
  "type": "Feature",
  "properties": {
    "addr:full":"Avda Maria Auxiliadora, S/n Rota C\u00e1diz 11520",
    "addr:housenumber":"s / n",
    "addr:postcode":"11520",
    "addr:street":"Avda Maria Auxiliadora;Ca\u0301Diz",
    "iso:country":"ES",
    "sg:address":"Avda Maria Auxiliadora, S/n",
    "sg:city":"Rota",
    "sg:orig_category":"Cajas De Ahorro",
    "sg:phone":"+34 956 81 61 12",
    "sg:postcode":"11520",
    "sg:province":"C\u00e1diz",
    "wof:name":"Caja Rural Del Sur Sociedad Cooperativa",
    "wof:placetype":"venue"
},
  "geometry": {"coordinates":[-6.3637142181,36.6252441406],"type":"Point"}
}