{
  "type": "Feature",
  "properties": {
    "addr:full":"Calle de Pico Del Mulhacen, 38 Arganda Madrid 28500",
    "addr:housenumber":"38",
    "addr:postcode":"28500",
    "addr:street":"Calle De Pico Del Mulhacen",
    "iso:country":"ES",
    "sg:address":"Calle de Pico Del Mulhacen, 38",
    "sg:city":"Arganda",
    "sg:orig_category":"Productos Qu\u00cdmicos (fabricaci\u00d3n, Al Por Mayor)",
    "sg:phone":"+34 918 70 27 32",
    "sg:postcode":"28500",
    "sg:province":"Madrid",
    "wof:name":"Ribco S.a.",
    "wof:placetype":"venue"
},
  "geometry": {"coordinates":[-3.4828178883,40.306552887],"type":"Point"}
}