{
  "type": "Feature",
  "properties": {
    "addr:full":"Rua Republica Arxentina, 11 Ferrol La Coru\u00f1a 15404",
    "addr:housenumber":"11",
    "addr:postcode":"15404",
    "addr:street":"Rua Republica Arxentina;La Corun\u0303A",
    "iso:country":"ES",
    "sg:address":"Rua Republica Arxentina, 11",
    "sg:city":"Ferrol",
    "sg:orig_category":"Psic\u00d3logos",
    "sg:phone":"+34 981 32 53 28",
    "sg:postcode":"15404",
    "sg:province":"La Coru\u00f1a",
    "wof:name":"Aguilar Ruiz Maria Del Carmen",
    "wof:placetype":"venue"
},
  "geometry": {"coordinates":[-8.2144622803,43.4897613525],"type":"Point"}
}