{
  "type": "Feature",
  "properties": {
    "iso:country":"ES",
    "sg:address":"Calle de Acera Del Darro, 30",
    "sg:city":"Granada",
    "sg:orig_category":"Art\u00cdculos De Regalo (al Por Menor)",
    "sg:phone":"+34 958 52 05 33",
    "sg:postcode":"18005",
    "sg:province":"Granada",
    "wof:name":"Mirpuri Deepak Karishma",
    "wof:placetype":"venue"
},
  "geometry": {"coordinates":[-3.599080801,37.1719932556],"type":"Point"}
}