{
  "type": "Feature",
  "properties": {
    "addr:full":"Calle de Gran Via, 61 Hellin Albacete 02400",
    "addr:housenumber":"61",
    "addr:postcode":"02400",
    "addr:street":"Calle De Gran Via",
    "iso:country":"ES",
    "sg:address":"Calle de Gran Via, 61",
    "sg:city":"Hellin",
    "sg:orig_category":"Ense\u00d1anza Variada",
    "sg:phone":"+34 967 30 72 73",
    "sg:postcode":"02400",
    "sg:province":"Albacete",
    "wof:name":"C.m.s. Formacion S.l.u.",
    "wof:placetype":"venue"
},
  "geometry": {"coordinates":[-1.7035429478,38.507938385],"type":"Point"}
}