{
  "type": "Feature",
  "properties": {
    "addr:full":"San Mamede, S/n Ribadulla A Coru\u00f1a 15880",
    "addr:housenumber":"s / n",
    "addr:postcode":"15880",
    "addr:street":"Corun\u0303A",
    "iso:country":"ES",
    "sg:address":"San Mamede, S/n",
    "sg:city":"Ribadulla",
    "sg:orig_category":"Asociaciones Y Clubs Deportivos",
    "sg:phone":"+34 981 51 20 98",
    "sg:postcode":"15880",
    "sg:province":"A Coru\u00f1a",
    "wof:name":"Sociedad Deportiva San Mamed",
    "wof:placetype":"venue"
},
  "geometry": {"coordinates":[-8.4284906387,42.7795181274],"type":"Point"}
}