{
  "type": "Feature",
  "properties": {
    "iso:country":"ES",
    "sg:address":"Calle de Puerta De Granada, 22",
    "sg:city":"Roda",
    "sg:orig_category":"Supermercados Y Hipermercados",
    "sg:phone":"+34 967 44 32 80",
    "sg:postcode":"02630",
    "sg:province":"Albacete",
    "wof:name":"Rodalimentaria",
    "wof:placetype":"venue"
},
  "geometry": {"coordinates":[-2.1601390839,39.2062911987],"type":"Point"}
}