{
  "type": "Feature",
  "properties": {
    "iso:country":"ES",
    "sg:address":"Calle de Cuenca Tramoyeres, 7",
    "sg:city":"Valencia",
    "sg:orig_category":"Molduras, Junquillos, Listones Y Molduras Perforadas",
    "sg:phone":"+34 963 69 19 39",
    "sg:postcode":"46020",
    "sg:province":"Valencia",
    "wof:name":"Xiangjin  Chen",
    "wof:placetype":"venue"
},
  "geometry": {"coordinates":[-0.3610090017,39.4829063416],"type":"Point"}
}