{
  "type": "Feature",
  "properties": {
    "addr:full":"Carrer de Sant Jordi, 23 Flix Tarragona 43750",
    "addr:housenumber":"23",
    "addr:postcode":"43750",
    "addr:street":"Carrer De Sant Jordi",
    "iso:country":"ES",
    "sg:address":"Carrer de Sant Jordi, 23",
    "sg:city":"Flix",
    "sg:orig_category":"Juegos Y Juguetes (al Por Menor)",
    "sg:phone":"+34 977 41 20 34",
    "sg:postcode":"43750",
    "sg:province":"Tarragona",
    "wof:name":"Pujol Montagut Joan Josep",
    "wof:placetype":"venue"
},
  "geometry": {"coordinates":[0.5510969758,41.2306861877],"type":"Point"}
}