{
  "type": "Feature",
  "properties": {
    "iso:country":"ES",
    "sg:address":"Calle de Iglesia, 49",
    "sg:city":"Honrubia",
    "sg:orig_category":"Reposter\u00cdas",
    "sg:phone":"+34 969 29 21 74",
    "sg:postcode":"16730",
    "sg:province":"Cuenca",
    "wof:name":"Villar Gallego Rufino",
    "wof:placetype":"venue"
},
  "geometry": {"coordinates":[-2.2793149948,39.6140556335],"type":"Point"}
}