{
  "type": "Feature",
  "properties": {
    "iso:country":"ES",
    "sg:address":"Carrer de Corsega, 602",
    "sg:city":"Barcelona",
    "sg:orig_category":"Pescader\u00cdas (al Por Menor)",
    "sg:phone":"+34 934 35 20 48",
    "sg:postcode":"08025",
    "sg:province":"Barcelona",
    "wof:name":"Perez Vidal Ivan",
    "wof:placetype":"venue"
},
  "geometry": {"coordinates":[2.176099062,41.4089393616],"type":"Point"}
}