{
  "type": "Feature",
  "properties": {
    "iso:country":"ES",
    "sg:address":"Pase Salamanca, 33",
    "sg:city":"Le\u00f3n",
    "sg:orig_category":"Barbacoas Y Accesorios",
    "sg:phone":"+34 987 23 62 48",
    "sg:postcode":"24009",
    "sg:province":"Le\u00f3n",
    "wof:name":"Nieto Moreno Juan Jesus",
    "wof:placetype":"venue"
},
  "geometry": {"coordinates":[-5.5824131966,42.5985794067],"type":"Point"}
}