{
  "type": "Feature",
  "properties": {
    "addr:full":"Rua Pablo Iglesias, 12 Vigo Pontevedra 36210",
    "addr:housenumber":"12",
    "addr:postcode":"36210",
    "addr:street":"Rua Pablo Iglesias",
    "iso:country":"ES",
    "sg:address":"Rua Pablo Iglesias, 12",
    "sg:city":"Vigo",
    "sg:orig_category":"Traductores",
    "sg:phone":"+34 986 21 18 89",
    "sg:postcode":"36210",
    "sg:province":"Pontevedra",
    "wof:name":"Traducciones E Interpretaciones Medicas S.l.",
    "wof:placetype":"venue"
},
  "geometry": {"coordinates":[-8.7441587448,42.2112731934],"type":"Point"}
}