{
  "type": "Feature",
  "properties": {
    "addr:full":"Calle de Napoles, 51 Madrid Madrid 28043",
    "addr:housenumber":"51",
    "addr:postcode":"madrid;28043",
    "addr:street":"Calle De Napoles",
    "iso:country":"ES",
    "sg:address":"Calle de Napoles, 51",
    "sg:city":"Madrid",
    "sg:orig_category":"Bisuter\u00cda, Joyer\u00cda, Relojer\u00cda (al Por Menor)",
    "sg:phone":"+34 917 59 91 31",
    "sg:postcode":"28043",
    "sg:province":"Madrid",
    "wof:name":"Milady Hair S.l.",
    "wof:placetype":"venue"
},
  "geometry": {"coordinates":[-3.6501429081,40.4599266052],"type":"Point"}
}