{
  "type": "Feature",
  "properties": {
    "iso:country":"ES",
    "sg:address":"Calle de Valle De La Fuente, 11",
    "sg:city":"Valverde Camino",
    "sg:orig_category":"Abogados",
    "sg:phone":"+34 959 55 00 96",
    "sg:postcode":"21600",
    "sg:province":"Huelva",
    "wof:name":"Zarza Arroyo Juan",
    "wof:placetype":"venue"
},
  "geometry": {"coordinates":[-6.754696846,37.5726280212],"type":"Point"}
}