{
  "type": "Feature",
  "properties": {
    "addr:full":"Pase Aiete De, 99 Donostia-san Sebastian Guip\u00f9zcoa 20009",
    "addr:housenumber":"99",
    "addr:postcode":"20009",
    "addr:street":"Aiete",
    "iso:country":"ES",
    "sg:address":"Pase Aiete De, 99",
    "sg:city":"Donostia-san Sebastian",
    "sg:orig_category":"Supermercados Y Hipermercados",
    "sg:phone":"+34 943 21 14 88",
    "sg:postcode":"20009",
    "sg:province":"Guip\u00f9zcoa",
    "wof:name":"Distribucion De Supermercados S. L.",
    "wof:placetype":"venue"
},
  "geometry": {"coordinates":[-1.9794000387,43.3173789978],"type":"Point"}
}