{
  "type": "Feature",
  "properties": {
    "addr:full":"G.v. Corts Catalanes, 941 Barcelona Barcelona 08018",
    "addr:housenumber":"941",
    "addr:postcode":"08018",
    "addr:street":"Catalanes",
    "iso:country":"ES",
    "sg:address":"G.v. Corts Catalanes, 941",
    "sg:city":"Barcelona",
    "sg:orig_category":"Cajas De Ahorro",
    "sg:phone":"+34 933 07 14 18",
    "sg:postcode":"08018",
    "sg:province":"Barcelona",
    "wof:name":"Caixa D'estalvis Sabadell",
    "wof:placetype":"venue"
},
  "geometry": {"coordinates":[2.1954710484,41.4104537964],"type":"Point"}
}