{
  "type": "Feature",
  "properties": {
    "addr:full":"Calle de Madera, 4 Villaluenga Sagra Toledo 45520",
    "addr:housenumber":"4",
    "addr:postcode":"45520",
    "addr:street":"Calle De Madera",
    "iso:country":"ES",
    "sg:address":"Calle de Madera, 4",
    "sg:city":"Villaluenga Sagra",
    "sg:orig_category":"Contenedores (mercanc\u00cdas)",
    "sg:phone":"+34 925 35 52 38",
    "sg:postcode":"45520",
    "sg:province":"Toledo",
    "wof:name":"Blanco Gomez Guillermo",
    "wof:placetype":"venue"
},
  "geometry": {"coordinates":[-3.9098680019,40.0303573608],"type":"Point"}
}