{
  "type": "Feature",
  "properties": {
    "addr:full":"Poli Industrial Francoli, S/n Campsa Tarragona 43006",
    "addr:housenumber":"s / n",
    "addr:postcode":"43006",
    "addr:street":"Francoli",
    "iso:country":"ES",
    "sg:address":"Poli Industrial Francoli, S/n",
    "sg:city":"Campsa",
    "sg:orig_category":"Suministros Y Materiales Industriales",
    "sg:phone":"+34 977 54 30 11",
    "sg:postcode":"43006",
    "sg:province":"Tarragona",
    "wof:name":"Suministros Queralt S. A.",
    "wof:placetype":"venue"
},
  "geometry": {"coordinates":[1.2209249735,41.1154441833],"type":"Point"}
}