{
  "type": "Feature",
  "properties": {
    "addr:full":"Calle de Cidamon, 2 Madrid Madrid 28043",
    "addr:housenumber":"2",
    "addr:postcode":"28043",
    "addr:street":"Calle De Cidamon",
    "iso:country":"ES",
    "sg:address":"Calle de Cidamon, 2",
    "sg:city":"Madrid",
    "sg:orig_category":"Carnicer\u00cdas, Carnicer\u00cdas",
    "sg:phone":"+34 914 15 79 91",
    "sg:postcode":"28043",
    "sg:province":"Madrid",
    "wof:name":"Capon Parajua Manuel",
    "wof:placetype":"venue"
},
  "geometry": {"coordinates":[-3.657582283,40.4502639771],"type":"Point"}
}