{
  "type": "Feature",
  "properties": {
    "addr:full":"Carr Cura Catala, 50 Manises Valencia 46940",
    "addr:housenumber":"50",
    "addr:postcode":"46940",
    "addr:street":"Carr Cura Catala",
    "iso:country":"ES",
    "sg:address":"Carr Cura Catala, 50",
    "sg:city":"Manises",
    "sg:orig_category":"Lavado, Limpieza De Veh\u00cdculos",
    "sg:phone":"+34 961 54 09 22",
    "sg:postcode":"46940",
    "sg:province":"Valencia",
    "wof:name":"Santana Mendez Manuel",
    "wof:placetype":"venue"
},
  "geometry": {"coordinates":[-0.4604830146,39.4934883118],"type":"Point"}
}