{
  "type": "Feature",
  "properties": {
    "addr:full":"Calle de Jacinto Benavente, 32 Marbella M\u00e1laga 29600",
    "addr:housenumber":"32",
    "addr:postcode":"29600",
    "addr:street":"Calle De Jacinto Benavente;Ma\u0301Laga",
    "iso:country":"ES",
    "sg:address":"Calle de Jacinto Benavente, 32",
    "sg:city":"Marbella",
    "sg:orig_category":"Cl\u00cdnicas Dentales",
    "sg:phone":"+34 952 76 46 53",
    "sg:postcode":"29600",
    "sg:province":"M\u00e1laga",
    "wof:name":"Centro Dental J. Henri",
    "wof:placetype":"venue"
},
  "geometry": {"coordinates":[-4.8975992203,36.5113525391],"type":"Point"}
}