{
  "type": "Feature",
  "properties": {
    "addr:full":"Calle de Madrigal De La Vera, 9 Madrid Madrid 28044",
    "addr:housenumber":"9",
    "addr:postcode":"madrid;28044",
    "addr:street":"Calle De Madrigal De La Vera",
    "iso:country":"ES",
    "sg:address":"Calle de Madrigal De La Vera, 9",
    "sg:city":"Madrid",
    "sg:orig_category":"Librer\u00cdas",
    "sg:phone":"+34 917 06 63 85",
    "sg:postcode":"28044",
    "sg:province":"Madrid",
    "wof:name":"Plaza Martin Luis",
    "wof:placetype":"venue"
},
  "geometry": {"coordinates":[-3.7798190117,40.3773384094],"type":"Point"}
}