{
  "type": "Feature",
  "properties": {
    "addr:full":"Carrer de Ciutat De Granada, 70 Barcelona Barcelona 08005",
    "addr:housenumber":"70",
    "addr:postcode":"08005",
    "addr:street":"Carrer De Ciutat De Granada",
    "iso:country":"ES",
    "sg:address":"Carrer de Ciutat De Granada, 70",
    "sg:city":"Barcelona",
    "sg:orig_category":"Papeler\u00cdas, Librer\u00cdas",
    "sg:phone":"+34 933 09 98 65",
    "sg:postcode":"08005",
    "sg:province":"Barcelona",
    "wof:name":"Batista Lluis Mercedes",
    "wof:placetype":"venue"
},
  "geometry": {"coordinates":[2.1971490383,41.3992424011],"type":"Point"}
}