{
  "type": "Feature",
  "properties": {
    "iso:country":"ES",
    "sg:address":"Pase Maestro Juan Guerrero, 80",
    "sg:city":"Utrera",
    "sg:orig_category":"Agencias Y Agentes Comerciales, Representantes",
    "sg:phone":"+34 954 86 01 34",
    "sg:postcode":"41710",
    "sg:province":"Sevilla",
    "wof:name":"Aguilera Garcia Consolacion",
    "wof:placetype":"venue"
},
  "geometry": {"coordinates":[-5.7724308968,37.1875228882],"type":"Point"}
}