{
  "type": "Feature",
  "properties": {
    "iso:country":"ES",
    "sg:address":"Calle de Corona De Aragon, 20",
    "sg:city":"Barbastro",
    "sg:orig_category":"Albergues",
    "sg:phone":"+34 974 31 24 61",
    "sg:postcode":"22300",
    "sg:province":"Huesca",
    "wof:name":"Monclus Clemente Luis",
    "wof:placetype":"venue"
},
  "geometry": {"coordinates":[0.1278702021,42.0362434387],"type":"Point"}
}