{
  "type": "Feature",
  "properties": {
    "addr:full":"Zubiaurrenea Kalea, 10 Usurbil Guip\u00f9zcoa 20170",
    "addr:housenumber":"10",
    "addr:postcode":"20170",
    "addr:street":"Zubiaurrenea Kalea;Guipu\u0300Zcoa",
    "iso:country":"ES",
    "sg:address":"Zubiaurrenea Kalea, 10",
    "sg:city":"Usurbil",
    "sg:orig_category":"\u00d3ptica: Instrumentos (fabricaci\u00d3n)",
    "sg:phone":"+34 943 37 02 69",
    "sg:postcode":"20170",
    "sg:province":"Guip\u00f9zcoa",
    "wof:name":"Perez Tellechea, Ana",
    "wof:placetype":"venue"
},
  "geometry": {"coordinates":[-2.0489120483,43.2709732056],"type":"Point"}
}