{
  "type": "Feature",
  "properties": {
    "iso:country":"ES",
    "sg:address":"Calle de Placido Pe\u00d1a, 45",
    "sg:city":"Vilalba",
    "sg:orig_category":"Molduras, Junquillos, Listones Y Molduras Perforadas",
    "sg:phone":"+34 982 51 08 25",
    "sg:postcode":"27800",
    "sg:province":"Lugo",
    "wof:name":"Ramudo Ramudo Remedios Delfina",
    "wof:placetype":"venue"
},
  "geometry": {"coordinates":[-7.6791801453,43.3012008667],"type":"Point"}
}