{
  "type": "Feature",
  "properties": {
    "addr:full":"Ctra. Alozaina, Km. 0006,0 Casarabonela M\u00e1laga 29566",
    "addr:postcode":"29566",
    "addr:street":"Ctra. Alozaina Km. 0006,0;Ma\u0301Laga",
    "iso:country":"ES",
    "sg:address":"Ctra. Alozaina, Km. 0006,0",
    "sg:city":"Casarabonela",
    "sg:orig_category":"Aguas (distribuci\u00d3n, Servicios)",
    "sg:phone":"+34 952 11 21 46",
    "sg:postcode":"29566",
    "sg:province":"M\u00e1laga",
    "wof:name":"Aguas Minerales Del Sur S.l.",
    "wof:placetype":"venue"
},
  "geometry": {"coordinates":[-4.8436484337,36.7837791443],"type":"Point"}
}