{
  "type": "Feature",
  "properties": {
    "addr:full":"Avda Constitucion, 24 Don Benito Badajoz 06400",
    "addr:housenumber":"24",
    "addr:postcode":"06400",
    "addr:street":"Avda Constitucion",
    "iso:country":"ES",
    "sg:address":"Avda Constitucion, 24",
    "sg:city":"Don Benito",
    "sg:orig_category":"Art\u00cdculos De Regalo (al Por Menor)",
    "sg:phone":"+34 924 80 09 42",
    "sg:postcode":"06400",
    "sg:province":"Badajoz",
    "wof:name":"Santos Yedro S.a.",
    "wof:placetype":"venue"
},
  "geometry": {"coordinates":[-5.8627138138,38.9662666321],"type":"Point"}
}