{
  "type": "Feature",
  "properties": {
    "iso:country":"ES",
    "sg:address":"Calle de Trancanil, 4",
    "sg:city":"Aeropuerto",
    "sg:orig_category":"Asesor\u00cda Fiscal Y Jur\u00cddica",
    "sg:phone":"+34 928 82 15 45",
    "sg:postcode":"35509",
    "sg:province":"Las Palmas",
    "wof:name":"Perez Sosa Carmen",
    "wof:placetype":"venue"
},
  "geometry": {"coordinates":[-13.5916891098,28.955160141],"type":"Point"}
}