{
  "type": "Feature",
  "properties": {
    "addr:full":"Calle de Arenal, 5 Bilbao Vizcaya 48005",
    "addr:housenumber":"5",
    "addr:postcode":"48005",
    "addr:street":"Calle De Arenal",
    "iso:country":"ES",
    "sg:address":"Calle de Arenal, 5",
    "sg:city":"Bilbao",
    "sg:orig_category":"Asesor\u00cda Sobre Comunicaci\u00d3n De Empresas",
    "sg:phone":"+34 944 15 61 83",
    "sg:postcode":"48005",
    "sg:province":"Vizcaya",
    "wof:name":"Miguel Angel Diaz Acerete (asesoria)",
    "wof:placetype":"venue"
},
  "geometry": {"coordinates":[-2.9239416122,43.2595214844],"type":"Point"}
}