{
  "type": "Feature",
  "properties": {
    "addr:full":"Calle de San Anton, 25 Logro\u00f1o La Rioja 26002",
    "addr:housenumber":"25",
    "addr:postcode":"26002",
    "addr:street":"Calle De San Anton;Rioja",
    "iso:country":"ES",
    "sg:address":"Calle de San Anton, 25",
    "sg:city":"Logro\u00f1o",
    "sg:orig_category":"Ropa Para Caballeros (al Por Menor)",
    "sg:phone":"+34 941 25 87 34",
    "sg:postcode":"26002",
    "sg:province":"La Rioja",
    "sg:website":"www.massimodutti.com",
    "wof:name":"Grupo Massimo Dutti S.a.",
    "wof:placetype":"venue"
},
  "geometry": {"coordinates":[-2.4462549686,42.4611053467],"type":"Point"}
}