{
  "type": "Feature",
  "properties": {
    "iso:country":"ES",
    "sg:address":"Calle de Sacrificio, 27",
    "sg:city":"Santa Olaja De La Ribera",
    "sg:orig_category":"Empresas De Carpinter\u00cda De Madera",
    "sg:phone":"+34 987 21 02 78",
    "sg:postcode":"24199",
    "sg:province":"Le\u00f3n",
    "wof:name":"Amador Tijera E Hijos S.l.",
    "wof:placetype":"venue"
},
  "geometry": {"coordinates":[-5.5540075302,42.5587310791],"type":"Point"}
}