{
  "type": "Feature",
  "properties": {
    "addr:full":"H. Cortes, 1 Olivenza Badajoz 06100",
    "addr:housenumber":"1",
    "addr:postcode":"06100",
    "addr:street":"H. Cortes",
    "iso:country":"ES",
    "sg:address":"H. Cortes, 1",
    "sg:city":"Olivenza",
    "sg:orig_category":"Ense\u00d1anza, Formaci\u00d3n Profesional: Aprendizaje",
    "sg:phone":"+34 924 49 20 68",
    "sg:postcode":"06100",
    "sg:province":"Badajoz",
    "wof:name":"Ayuntamiento De Olivenza",
    "wof:placetype":"venue"
},
  "geometry": {"coordinates":[-7.0980844498,38.684928894],"type":"Point"}
}