{
  "type": "Feature",
  "properties": {
    "addr:full":"Calle de Aduana, 20 Puertollano Ciudad Real 13500",
    "addr:housenumber":"20",
    "addr:postcode":"13500",
    "addr:street":"Calle De Aduana",
    "iso:country":"ES",
    "sg:address":"Calle de Aduana, 20",
    "sg:city":"Puertollano",
    "sg:orig_category":"Florister\u00cdas",
    "sg:phone":"+34 926 41 13 53",
    "sg:postcode":"13500",
    "sg:province":"Ciudad Real",
    "wof:name":"Diaz Gallego Antonio",
    "wof:placetype":"venue"
},
  "geometry": {"coordinates":[-4.1093673706,38.6868629456],"type":"Point"}
}