{
  "type": "Feature",
  "properties": {
    "iso:country":"ES",
    "sg:address":"Calle de German Calvo Gonzalez, 12",
    "sg:city":"Palencia",
    "sg:orig_category":"Panader\u00cdas, Panader\u00cdas",
    "sg:phone":"+34 979 72 88 12",
    "sg:postcode":"34004",
    "sg:province":"Palencia",
    "wof:name":"Lopez Gonzalez Maria Del Rosario",
    "wof:placetype":"venue"
},
  "geometry": {"coordinates":[-4.5228490829,42.0008010864],"type":"Point"}
}