{
  "type": "Feature",
  "properties": {
    "addr:full":"Calle de Manuel Alfaro Pereira, 7 Badajoz Badajoz 06004",
    "addr:housenumber":"7",
    "addr:postcode":"06004",
    "addr:street":"Calle De Manuel Alfaro Pereira",
    "iso:country":"ES",
    "sg:address":"Calle de Manuel Alfaro Pereira, 7",
    "sg:city":"Badajoz",
    "sg:orig_category":"Asesor\u00cda Sobre Comunicaci\u00d3n De Empresas",
    "sg:phone":"+34 924 22 00 52",
    "sg:postcode":"06004",
    "sg:province":"Badajoz",
    "wof:name":"Proemex S.c.",
    "wof:placetype":"venue"
},
  "geometry": {"coordinates":[-6.9716210365,38.8738632202],"type":"Point"}
}