{
  "type": "Feature",
  "properties": {
    "iso:country":"ES",
    "sg:address":"La Fragua, S/n",
    "sg:city":"Palenzuela",
    "sg:orig_category":"Transportes Por V\u00cdas Navegables",
    "sg:phone":"+34 979 79 30 72",
    "sg:postcode":"34257",
    "sg:province":"Palencia",
    "wof:name":"Lopez De Juana Porfirio",
    "wof:placetype":"venue"
},
  "geometry": {"coordinates":[-4.1312241554,42.0956382751],"type":"Point"}
}