{
  "type": "Feature",
  "properties": {
    "iso:country":"ES",
    "sg:address":"Avda Dos De Mayo (del), 22",
    "sg:city":"Mostoles",
    "sg:orig_category":"Poller\u00cda Y Caza (al Por Menor)",
    "sg:phone":"+34 916 14 06 55",
    "sg:postcode":"28934",
    "sg:province":"Madrid",
    "wof:name":"Lopez Diaz-guerra Juan Jose",
    "wof:placetype":"venue"
},
  "geometry": {"coordinates":[-3.866795063,40.3209266663],"type":"Point"}
}