{
  "type": "Feature",
  "properties": {
    "iso:country":"ES",
    "sg:address":"Carr Metge Vicent Verdu I Beltra, 2",
    "sg:city":"Petrer",
    "sg:orig_category":"Agencias Y Asesores De Publicidad",
    "sg:phone":"+34 966 95 50 00",
    "sg:postcode":"03610",
    "sg:province":"Alicante",
    "wof:name":"Horizontes Articulos Publicitarios S.l.",
    "wof:placetype":"venue"
},
  "geometry": {"coordinates":[-0.7874959707,38.4907455444],"type":"Point"}
}