{
  "type": "Feature",
  "properties": {
    "iso:country":"ES",
    "sg:address":"Carr Major, 52",
    "sg:city":"Jonquera",
    "sg:orig_category":"Panader\u00cdas, Panader\u00cdas",
    "sg:phone":"+34 972 55 50 34",
    "sg:postcode":"17700",
    "sg:province":"Girona",
    "wof:name":"Sant Pau Forns De Pa S.l.",
    "wof:placetype":"venue"
},
  "geometry": {"coordinates":[2.8718750477,42.4159698486],"type":"Point"}
}