{
  "type": "Feature",
  "properties": {
    "addr:full":"Avda Rio Guadarrama, 46 Poligono Sta M. De Benquerencia Toledo 45007",
    "addr:housenumber":"46 poligono",
    "addr:postcode":"45007",
    "addr:street":"Avda Rio Guadarrama;Sta M. De Benquerencia",
    "iso:country":"ES",
    "sg:address":"Avda Rio Guadarrama, 46",
    "sg:city":"Poligono Sta M. De Benquerencia",
    "sg:orig_category":"Venta, Instalaci\u00d3n, Reparaci\u00d3n De Antenas Para Televisi\u00d3n",
    "sg:phone":"+34 925 24 10 13",
    "sg:postcode":"45007",
    "sg:province":"Toledo",
    "wof:name":"Antenas Toledo S.l.l.",
    "wof:placetype":"venue"
},
  "geometry": {"coordinates":[-4.0244760513,39.8567771912],"type":"Point"}
}