{
  "type": "Feature",
  "properties": {
    "addr:full":"Pase Maritimo Ciudad De Melilla, 7 Malaga M\u00e1laga 29016",
    "addr:housenumber":"7",
    "addr:postcode":"29016",
    "addr:street":"Melilla;Ma\u0301Laga",
    "iso:country":"ES",
    "sg:address":"Pase Maritimo Ciudad De Melilla, 7",
    "sg:city":"Malaga",
    "sg:orig_category":"Laboratorios Farmac\u00c9uticos",
    "sg:phone":"+34 952 21 12 89",
    "sg:postcode":"29016",
    "sg:province":"M\u00e1laga",
    "wof:name":"Macias Carrasco Pilar",
    "wof:placetype":"venue"
},
  "geometry": {"coordinates":[-4.4128432274,36.7157516479],"type":"Point"}
}