{
  "type": "Feature",
  "properties": {
    "addr:full":"G.v. Corts Catalanes, 623 Barcelona Barcelona 08010",
    "addr:housenumber":"623",
    "addr:postcode":"08010",
    "addr:street":"Catalanes",
    "iso:country":"ES",
    "sg:address":"G.v. Corts Catalanes, 623",
    "sg:city":"Barcelona",
    "sg:orig_category":"Venta, Reparaci\u00d3n, Localizaci\u00d3n De Balanzas Y De B\u00c1sculas",
    "sg:phone":"+34 933 01 95 96",
    "sg:postcode":"08010",
    "sg:province":"Barcelona",
    "wof:name":"Seguridad Internacional M.s.m. S.l.",
    "wof:placetype":"venue"
},
  "geometry": {"coordinates":[2.1697459221,41.3909797668],"type":"Point"}
}