{
  "type": "Feature",
  "properties": {
    "iso:country":"ES",
    "sg:address":"El Regatillo, S/n",
    "sg:city":"Alcorisa",
    "sg:orig_category":"Cer\u00c1micas: Material Y Suministros",
    "sg:phone":"+34 978 84 04 70",
    "sg:postcode":"44550",
    "sg:province":"Teruel",
    "sg:website":"www.gresaragon.com",
    "wof:name":"Ca\u00d1ada S.a.",
    "wof:placetype":"venue"
},
  "geometry": {"coordinates":[-0.3802970052,40.8973426819],"type":"Point"}
}