{
  "type": "Feature",
  "properties": {
    "iso:country":"ES",
    "sg:address":"Carr Alfareria, 3",
    "sg:city":"Burjassot",
    "sg:orig_category":"Charcuter\u00cdas (al Por Mayor)",
    "sg:phone":"+34 963 90 35 93",
    "sg:postcode":"46100",
    "sg:province":"Valencia",
    "wof:name":"Campofrio Alimentacion S.a.",
    "wof:placetype":"venue"
},
  "geometry": {"coordinates":[-0.4049899876,39.5024375916],"type":"Point"}
}