{
  "type": "Feature",
  "properties": {
    "iso:country":"ES",
    "sg:address":"Calle de Jacinta Garcia Hernandez, 19",
    "sg:city":"Badajoz",
    "sg:orig_category":"Centros P\u00dablicos De Formaci\u00d3n Profesional Y T\u00c9cnica",
    "sg:phone":"+34 924 25 74 56",
    "sg:postcode":"06011",
    "sg:province":"Badajoz",
    "wof:name":"Colegio Oficial De Diplomados En Trabajo Social Y Asistentes Sociales",
    "wof:placetype":"venue"
},
  "geometry": {"coordinates":[-6.9874258041,38.8717384338],"type":"Point"}
}