{
  "type": "Feature",
  "properties": {
    "iso:country":"ES",
    "sg:address":"P. Del Lomo, 1",
    "sg:city":"Las Galletas",
    "sg:orig_category":"Agricultura: Abastecimiento Y Cosechado (negocio)",
    "sg:phone":"+34 922 73 33 33",
    "sg:postcode":"38631",
    "sg:province":"Santa Cruz De Tenerife",
    "wof:name":"Sociedad Agraria De Transformacion N 2473 La Estrella",
    "wof:placetype":"venue"
},
  "geometry": {"coordinates":[-16.670463562,28.0141906738],"type":"Point"}
}