{
  "type": "Feature",
  "properties": {
    "iso:country":"ES",
    "sg:address":"Carrer de Sant Miquel, 13",
    "sg:city":"Palau-solita I Plegamans",
    "sg:orig_category":"Frutos Y Legumbres",
    "sg:phone":"+34 938 64 45 22",
    "sg:postcode":"08184",
    "sg:province":"Barcelona",
    "wof:name":"Fruites Montbui S.l.",
    "wof:placetype":"venue"
},
  "geometry": {"coordinates":[2.178260088,41.5884590149],"type":"Point"}
}