{
  "type": "Feature",
  "properties": {
    "addr:full":"C/ Montseny, S/n Salt Girona 17190",
    "addr:housenumber":"s / n",
    "addr:postcode":"17190",
    "addr:street":"C / Montseny",
    "iso:country":"ES",
    "sg:address":"C/ Montseny, S/n",
    "sg:city":"Salt",
    "sg:orig_category":"Centros De Educaci\u00d3n Especial",
    "sg:phone":"+34 972 23 21 27",
    "sg:postcode":"17190",
    "sg:province":"Girona",
    "wof:name":"Ceip Nou Del Salt",
    "wof:placetype":"venue"
},
  "geometry": {"coordinates":[2.7899150848,41.971408844],"type":"Point"}
}