{
  "type": "Feature",
  "properties": {
    "iso:country":"ES",
    "sg:address":"Rua San Clemente (de), 30",
    "sg:city":"Santiago De Compostela",
    "sg:orig_category":"Caf\u00c9s, Bares, Cervecer\u00cdas",
    "sg:phone":"+34 981 58 90 56",
    "sg:postcode":"15705",
    "sg:province":"La Coru\u00f1a",
    "wof:name":"Rey Tojo Victoriano",
    "wof:placetype":"venue"
},
  "geometry": {"coordinates":[-8.5475931168,42.8781242371],"type":"Point"}
}