{
  "type": "Feature",
  "properties": {
    "addr:full":"Avda Palma De Mallorca, 15 Torremolinos M\u00e1laga 29620",
    "addr:housenumber":"15",
    "addr:postcode":"29620",
    "addr:street":"Avda Palma De Mallorca;Ma\u0301Laga",
    "iso:country":"ES",
    "sg:address":"Avda Palma De Mallorca, 15",
    "sg:city":"Torremolinos",
    "sg:orig_category":"\u00d3ptica: Instrumentos (fabricaci\u00d3n)",
    "sg:phone":"+34 952 05 02 83",
    "sg:postcode":"29620",
    "sg:province":"M\u00e1laga",
    "sg:website":"www.multiopticacentro.com",
    "wof:name":"Gonzalez Romero Manuel",
    "wof:placetype":"venue"
},
  "geometry": {"coordinates":[-4.4999232292,36.6225662231],"type":"Point"}
}