{
  "type": "Feature",
  "properties": {
    "addr:full":"Ctra Jesus Pobre, S/n Javea Alicante 03730",
    "addr:housenumber":"s / n",
    "addr:postcode":"03730",
    "addr:street":"Ctra Jesus Pobre",
    "iso:country":"ES",
    "sg:address":"Ctra Jesus Pobre, S/n",
    "sg:city":"Javea",
    "sg:orig_category":"Caf\u00c9s, Bares, Cervecer\u00cdas",
    "sg:phone":"+34 966 46 34 35",
    "sg:postcode":"03730",
    "sg:province":"Alicante",
    "wof:name":"Ceballos Codina Maria Francisca",
    "wof:placetype":"venue"
},
  "geometry": {"coordinates":[0.1378500015,38.7880363464],"type":"Point"}
}