{
  "type": "Feature",
  "properties": {
    "addr:full":"Rua Vilar (do), 68 Santiago De Compostela La Coru\u00f1a 15705",
    "addr:housenumber":"68",
    "addr:postcode":"15705",
    "addr:street":"Rua Vilar Do;Corun\u0303A",
    "iso:country":"ES",
    "sg:address":"Rua Vilar (do), 68",
    "sg:city":"Santiago De Compostela",
    "sg:orig_category":"Librer\u00cdas",
    "sg:phone":"+34 981 57 25 47",
    "sg:postcode":"15705",
    "sg:province":"La Coru\u00f1a",
    "wof:name":"Libreria Encontros S.c.",
    "wof:placetype":"venue"
},
  "geometry": {"coordinates":[-8.5450973511,42.8778610229],"type":"Point"}
}