{
  "type": "Feature",
  "properties": {
    "addr:full":"Pg Fabra I Puig, 167 Barcelona Barcelona 08016",
    "addr:housenumber":"167",
    "addr:postcode":"08016",
    "addr:street":"Pg Fabra I Puig",
    "iso:country":"ES",
    "sg:address":"Pg Fabra I Puig, 167",
    "sg:city":"Barcelona",
    "sg:orig_category":"Administradores De Bienes Y Delegados De Comunidades De Propietarios",
    "sg:phone":"+34 933 52 36 55",
    "sg:postcode":"08016",
    "sg:province":"Barcelona",
    "wof:name":"Fincas Regius S.l.",
    "wof:placetype":"venue"
},
  "geometry": {"coordinates":[2.1783559322,41.4301490784],"type":"Point"}
}