{
  "type": "Feature",
  "properties": {
    "iso:country":"ES",
    "sg:address":"Calle de Luna, 7",
    "sg:city":"Yepes",
    "sg:orig_category":"Vinos (agentes)",
    "sg:phone":"+34 925 15 40 09",
    "sg:postcode":"45313",
    "sg:province":"Toledo",
    "wof:name":"Cerro Sanchez-elvira Luis Juan Del",
    "wof:placetype":"venue"
},
  "geometry": {"coordinates":[-3.6222290993,39.9021987915],"type":"Point"}
}