{
  "type": "Feature",
  "properties": {
    "addr:full":"Plaza Del Fontan, 18 Tineo Asturias 33870",
    "addr:housenumber":"18",
    "addr:postcode":"33870",
    "addr:street":"Del Fontan",
    "iso:country":"ES",
    "sg:address":"Plaza Del Fontan, 18",
    "sg:city":"Tineo",
    "sg:orig_category":"Molduras, Junquillos, Listones Y Molduras Perforadas",
    "sg:phone":"+34 985 80 02 11",
    "sg:postcode":"33870",
    "sg:province":"Asturias",
    "wof:name":"Fernandez Garcia Jose",
    "wof:placetype":"venue"
},
  "geometry": {"coordinates":[-6.4165468216,43.3338775635],"type":"Point"}
}