{
  "type": "Feature",
  "properties": {
    "iso:country":"ES",
    "sg:address":"Pla\u00c7 Turers, 12",
    "sg:city":"Banyoles",
    "sg:orig_category":"Peluquer\u00cdas, Peluquer\u00cda Mixta",
    "sg:phone":"+34 972 57 19 01",
    "sg:postcode":"17820",
    "sg:province":"Girona",
    "wof:name":"Tarradas Planas Francisco",
    "wof:placetype":"venue"
},
  "geometry": {"coordinates":[2.763958931,42.1179046631],"type":"Point"}
}