{
  "type": "Feature",
  "properties": {
    "addr:full":"Calle de Hinojo, 59 Algar Murcia 30366",
    "addr:housenumber":"59",
    "addr:postcode":"30366",
    "addr:street":"Calle De Hinojo",
    "iso:country":"ES",
    "sg:address":"Calle de Hinojo, 59",
    "sg:city":"Algar",
    "sg:orig_category":"Promotores Constructores",
    "sg:phone":"+34 968 13 64 86",
    "sg:postcode":"30366",
    "sg:province":"Murcia",
    "wof:name":"Promociones Pe\u00f1alver Garceran S.l.",
    "wof:placetype":"venue"
},
  "geometry": {"coordinates":[-0.8614889979,37.6490936279],"type":"Point"}
}