{
  "type": "Feature",
  "properties": {
    "iso:country":"ES",
    "sg:address":"Carrer de Marie Curie, 20",
    "sg:city":"S. Esteve Sesrovires",
    "sg:orig_category":"M\u00c1quinas Y Material Para La Industria De La Alimentaci\u00d3n",
    "sg:phone":"+34 937 71 48 14",
    "sg:postcode":"08635",
    "sg:province":"Barcelona",
    "wof:name":"Industrial Electrica Vilar S.l.",
    "wof:placetype":"venue"
},
  "geometry": {"coordinates":[1.8823900223,41.4792747498],"type":"Point"}
}