{
  "type": "Feature",
  "properties": {
    "addr:full":"Calle de Marques De Comillas, 15 Almeria Almer\u00eda 04004",
    "addr:housenumber":"15",
    "addr:postcode":"04004",
    "addr:street":"Calle De Marques De Comillas",
    "iso:country":"ES",
    "sg:address":"Calle de Marques De Comillas, 15",
    "sg:city":"Almeria",
    "sg:orig_category":"M\u00c9dicos: Dermatolog\u00cda Y Venereolog\u00cda",
    "sg:phone":"+34 950 23 30 57",
    "sg:postcode":"04004",
    "sg:province":"Almer\u00eda",
    "wof:name":"Rodriguez Garcia Alfonso",
    "wof:placetype":"venue"
},
  "geometry": {"coordinates":[-2.462241888,36.8367462158],"type":"Point"}
}