{
  "type": "Feature",
  "properties": {
    "iso:country":"ES",
    "sg:address":"Pase Alameda (la), 12",
    "sg:city":"Constantina",
    "sg:orig_category":"Bares, Piano",
    "sg:phone":"+34 955 88 20 55",
    "sg:postcode":"41450",
    "sg:province":"Sevilla",
    "wof:name":"Pub Eslabon S.l",
    "wof:placetype":"venue"
},
  "geometry": {"coordinates":[-5.6211647987,37.8773803711],"type":"Point"}
}