{
  "type": "Feature",
  "properties": {
    "iso:country":"ES",
    "sg:address":"Carrer de Napols, 297",
    "sg:city":"Barcelona",
    "sg:orig_category":"Agencias Y Agentes Comerciales, Representantes",
    "sg:phone":"+34 932 07 11 61",
    "sg:postcode":"08025",
    "sg:province":"Barcelona",
    "wof:name":"Rodriguez Olmos Juan Manuel",
    "wof:placetype":"venue"
},
  "geometry": {"coordinates":[2.1682610512,41.4036331177],"type":"Point"}
}