{
  "type": "Feature",
  "properties": {
    "iso:country":"ES",
    "sg:address":"Calle de Manuel Gonzalez Martin, 18",
    "sg:city":"Palmas De Gran Canaria",
    "sg:orig_category":"Inform\u00c1tica Equipo Y Programas (al Por Mayor)",
    "sg:phone":"+34 928 23 43 71",
    "sg:postcode":"35005",
    "sg:province":"Las Palmas",
    "sg:website":"www.romsocan.com",
    "wof:name":"Romsocan S.l.",
    "wof:placetype":"venue"
},
  "geometry": {"coordinates":[-15.4310436249,28.1293678284],"type":"Point"}
}