{
  "type": "Feature",
  "properties": {
    "addr:full":"Carrer de Industria, 330 Barcelona Barcelona 08026",
    "addr:housenumber":"330",
    "addr:postcode":"08026",
    "addr:street":"Carrer De Industria",
    "iso:country":"ES",
    "sg:address":"Carrer de Industria, 330",
    "sg:city":"Barcelona",
    "sg:orig_category":"Agencias Y Agentes Comerciales, Representantes",
    "sg:phone":"+34 933 51 94 04",
    "sg:postcode":"08026",
    "sg:province":"Barcelona",
    "wof:name":"Mayor Pi\u00f1ol Jose Luis",
    "wof:placetype":"venue"
},
  "geometry": {"coordinates":[2.183768034,41.4165534973],"type":"Point"}
}