{
  "type": "Feature",
  "properties": {
    "addr:full":"Calle de Caunedo, 6 Madrid Madrid 28037",
    "addr:housenumber":"6",
    "addr:postcode":"28037",
    "addr:street":"Calle De Caunedo",
    "iso:country":"ES",
    "sg:address":"Calle de Caunedo, 6",
    "sg:city":"Madrid",
    "sg:orig_category":"Estancos",
    "sg:phone":"+34 913 93 18 66",
    "sg:postcode":"28037",
    "sg:province":"Madrid",
    "wof:name":"Olivar Vicario Vanesa",
    "wof:placetype":"venue"
},
  "geometry": {"coordinates":[-3.6368157864,40.4368972778],"type":"Point"}
}