{
  "type": "Feature",
  "properties": {
    "iso:country":"ES",
    "sg:address":"Pque Joyero (p I Pque Joyero), S/n",
    "sg:city":"Cordoba",
    "sg:orig_category":"Bisuter\u00cda, Joyer\u00cda, Relojer\u00cda (al Por Menor)",
    "sg:phone":"+34 957 32 56 96",
    "sg:postcode":"14005",
    "sg:province":"C\u00f3rdoba",
    "wof:name":"Jorfesa",
    "wof:placetype":"venue"
},
  "geometry": {"coordinates":[-4.8181858063,37.8761711121],"type":"Point"}
}