{
  "type": "Feature",
  "properties": {
    "iso:country":"ES",
    "sg:address":"Avda Alvarez Guerra, 19",
    "sg:city":"Alcazar S. Juan",
    "sg:orig_category":"Ropa Para Se\u00d1oras (al Por Menor)",
    "sg:phone":"+34 926 54 17 78",
    "sg:postcode":"13600",
    "sg:province":"Ciudad Real",
    "wof:name":"Modas Blanca C.b.",
    "wof:placetype":"venue"
},
  "geometry": {"coordinates":[-3.2063369751,39.3944778442],"type":"Point"}
}