{
  "type": "Feature",
  "properties": {
    "addr:full":"Ctra Crevillente, Km. 0034,2 Torretas Alicante 03180",
    "addr:postcode":"03180",
    "addr:street":"Ctra Crevillente Km. 0034,2",
    "iso:country":"ES",
    "sg:address":"Ctra Crevillente, Km. 0034,2",
    "sg:city":"Torretas",
    "sg:orig_category":"Asociaciones Y Clubs Deportivos",
    "sg:phone":"+34 966 92 79 11",
    "sg:postcode":"03180",
    "sg:province":"Alicante",
    "wof:name":"Tovaresport S.a.",
    "wof:placetype":"venue"
},
  "geometry": {"coordinates":[-0.6536790133,38.0173606873],"type":"Point"}
}