{
  "type": "Feature",
  "properties": {
    "iso:country":"ES",
    "sg:address":"Calle de San Quintin, 4",
    "sg:city":"San Lorenzo De El Escorial",
    "sg:orig_category":"Restaurantes",
    "sg:phone":"+34 918 90 33 25",
    "sg:postcode":"28200",
    "sg:province":"Madrid",
    "wof:name":"Almanac Restaurante S.l.",
    "wof:placetype":"venue"
},
  "geometry": {"coordinates":[-4.1483602524,40.592010498],"type":"Point"}
}