{
  "type": "Feature",
  "properties": {
    "iso:country":"ES",
    "sg:address":"Calle de Castillo Pi\u00d1eiro, 6",
    "sg:city":"Madrid",
    "sg:orig_category":"Fotocopias, Reprograf\u00cda",
    "sg:phone":"+34 915 53 45 73",
    "sg:postcode":"28039",
    "sg:province":"Madrid",
    "wof:name":"Copinava S.l",
    "wof:placetype":"venue"
},
  "geometry": {"coordinates":[-3.7068328857,40.4475517273],"type":"Point"}
}