{
  "type": "Feature",
  "properties": {
    "iso:country":"ES",
    "sg:address":"Calle de Venecia, 9",
    "sg:city":"Aguadulce",
    "sg:orig_category":"Guarder\u00cdas",
    "sg:phone":"+34 950 34 61 14",
    "sg:postcode":"04720",
    "sg:province":"Almer\u00eda",
    "wof:name":"Mickey C.b",
    "wof:placetype":"venue"
},
  "geometry": {"coordinates":[-2.5666730404,36.8167724609],"type":"Point"}
}