{
  "type": "Feature",
  "properties": {
    "addr:full":"Pla\u00c7 Soler I Gustems, 10 Vilanova I La Geltru Barcelona 08800",
    "addr:housenumber":"10",
    "addr:postcode":"08800",
    "addr:street":"Gustems",
    "iso:country":"ES",
    "sg:address":"Pla\u00c7 Soler I Gustems, 10",
    "sg:city":"Vilanova I La Geltru",
    "sg:orig_category":"Reposter\u00cdas",
    "sg:phone":"+34 938 93 49 41",
    "sg:postcode":"08800",
    "sg:province":"Barcelona",
    "wof:name":"Morera E Hijos S.a.",
    "wof:placetype":"venue"
},
  "geometry": {"coordinates":[1.7272549868,41.2230567932],"type":"Point"}
}