{
  "type": "Feature",
  "properties": {
    "addr:full":"Carrer de Bellavista, 25 Hospitalet Llobregat Barcelona 08901",
    "addr:housenumber":"25",
    "addr:postcode":"08901",
    "addr:street":"Carrer De Bellavista",
    "iso:country":"ES",
    "sg:address":"Carrer de Bellavista, 25",
    "sg:city":"Hospitalet Llobregat",
    "sg:orig_category":"Asociaciones, Organismos Culturales Y Socioeducativos",
    "sg:phone":"+34 933 38 57 88",
    "sg:postcode":"08901",
    "sg:province":"Barcelona",
    "wof:name":"Asociacion Vell Can Pori",
    "wof:placetype":"venue"
},
  "geometry": {"coordinates":[2.095864296,41.3617477417],"type":"Point"}
}