{
  "type": "Feature",
  "properties": {
    "addr:full":"Calle de Balmes, 3 Palencia Palencia 34004",
    "addr:housenumber":"3",
    "addr:postcode":"34004",
    "addr:street":"Calle De Balmes",
    "iso:country":"ES",
    "sg:address":"Calle de Balmes, 3",
    "sg:city":"Palencia",
    "sg:orig_category":"Puertas Y Portales",
    "sg:phone":"+34 979 72 70 85",
    "sg:postcode":"34004",
    "sg:province":"Palencia",
    "wof:name":"Sendra Calderon Elena Maria",
    "wof:placetype":"venue"
},
  "geometry": {"coordinates":[-4.5248451233,42.0052032471],"type":"Point"}
}