{
  "type": "Feature",
  "properties": {
    "addr:full":"Plaz Musico Lopez Chavarri, 6 Valencia Valencia 46003",
    "addr:housenumber":"6",
    "addr:postcode":"46003",
    "addr:street":"Plaz Musico Lopez Chavarri",
    "iso:country":"ES",
    "sg:address":"Plaz Musico Lopez Chavarri, 6",
    "sg:city":"Valencia",
    "sg:orig_category":"Abogados",
    "sg:phone":"+34 963 91 78 05",
    "sg:postcode":"46003",
    "sg:province":"Valencia",
    "wof:name":"Llopis Perez Maria Jose",
    "wof:placetype":"venue"
},
  "geometry": {"coordinates":[-0.3807390034,39.4767532349],"type":"Point"}
}