{
  "type": "Feature",
  "properties": {
    "addr:full":"Calle de Maria Teresa Oller I Benlloch (musicologa), 1 Valencia Valencia 46019",
    "addr:housenumber":"1",
    "addr:postcode":"46019",
    "addr:street":"Calle De Maria Teresa;Musicologa",
    "iso:country":"ES",
    "sg:address":"Calle de Maria Teresa Oller I Benlloch (musicologa), 1",
    "sg:city":"Valencia",
    "sg:orig_category":"Peluqueros: De Se\u00d1oras",
    "sg:phone":"+34 963 66 63 32",
    "sg:postcode":"46019",
    "sg:province":"Valencia",
    "wof:name":"Noverges Perez Nuria",
    "wof:placetype":"venue"
},
  "geometry": {"coordinates":[-0.3574840128,39.5228233337],"type":"Point"}
}