{
  "type": "Feature",
  "properties": {
    "iso:country":"ES",
    "sg:address":"Calle de Manzana, 11",
    "sg:city":"Sevilla",
    "sg:orig_category":"Pod\u00d3logos: Pedicuros",
    "sg:phone":"+34 954 90 02 76",
    "sg:postcode":"41009",
    "sg:province":"Sevilla",
    "wof:name":"Galan Hurtado Maria Hermas",
    "wof:placetype":"venue"
},
  "geometry": {"coordinates":[-5.9835448265,37.405506134],"type":"Point"}
}