{
  "type": "Feature",
  "properties": {
    "addr:full":"Rond Fluvia, 7 Olot Girona 17800",
    "addr:housenumber":"7",
    "addr:postcode":"17800",
    "addr:street":"Fluvia",
    "iso:country":"ES",
    "sg:address":"Rond Fluvia, 7",
    "sg:city":"Olot",
    "sg:orig_category":"Mec\u00c1nico Del Autom\u00d3vil",
    "sg:phone":"+34 972 26 16 44",
    "sg:postcode":"17800",
    "sg:province":"Girona",
    "wof:name":"Sacrest Pujolar Francesc",
    "wof:placetype":"venue"
},
  "geometry": {"coordinates":[2.4912650585,42.1803703308],"type":"Point"}
}