{
  "type": "Feature",
  "properties": {
    "addr:full":"Carrer de Arago, 284 Barcelona Barcelona 08007",
    "addr:housenumber":"284",
    "addr:postcode":"08007",
    "addr:street":"Carrer De Arago",
    "iso:country":"ES",
    "sg:address":"Carrer de Arago, 284",
    "sg:city":"Barcelona",
    "sg:orig_category":"Centros Empresariales",
    "sg:phone":"+34 934 88 16 78",
    "sg:postcode":"08007",
    "sg:province":"Barcelona",
    "wof:name":"Gremi Provincial D'empresaris De Cinema De Barcelona",
    "wof:placetype":"venue"
},
  "geometry": {"coordinates":[2.166230917,41.3929977417],"type":"Point"}
}