{
  "type": "Feature",
  "properties": {
    "iso:country":"ES",
    "sg:address":"Calle de Augusto Gonzalez Linares, 10",
    "sg:city":"Torrelavega",
    "sg:orig_category":"Reposter\u00cdas",
    "sg:phone":"+34 942 80 48 28",
    "sg:postcode":"39300",
    "sg:province":"Cantabria",
    "wof:name":"Pan Del Besaya S.l.",
    "wof:placetype":"venue"
},
  "geometry": {"coordinates":[-4.0495495796,43.3477172852],"type":"Point"}
}