{
  "type": "Feature",
  "properties": {
    "addr:full":"Carr Centre, 55 Lleida Lleida 25001",
    "addr:housenumber":"55",
    "addr:postcode":"25001",
    "addr:street":"Carr",
    "iso:country":"ES",
    "sg:address":"Carr Centre, 55",
    "sg:city":"Lleida",
    "sg:orig_category":"Pintura Y Barniz (al Por Menor)",
    "sg:phone":"+34 973 20 31 23",
    "sg:postcode":"25001",
    "sg:province":"Lleida",
    "wof:name":"Ilercolor S.l.",
    "wof:placetype":"venue"
},
  "geometry": {"coordinates":[0.6466749907,41.6041717529],"type":"Point"}
}