{
  "type": "Feature",
  "properties": {
    "addr:full":"Calle de Jaime Ferran, 34 Zaragoza Zaragoza 50014",
    "addr:housenumber":"34",
    "addr:postcode":"50014",
    "addr:street":"Calle De Jaime Ferran",
    "iso:country":"ES",
    "sg:address":"Calle de Jaime Ferran, 34",
    "sg:city":"Zaragoza",
    "sg:orig_category":"Art\u00cdculos De Regalo (al Por Menor)",
    "sg:phone":"+34 976 47 25 76",
    "sg:postcode":"50014",
    "sg:province":"Zaragoza",
    "wof:name":"Gran Muralla Zaragoza S.l.",
    "wof:placetype":"venue"
},
  "geometry": {"coordinates":[-0.8640329838,41.6713256836],"type":"Point"}
}