{
  "type": "Feature",
  "properties": {
    "iso:country":"ES",
    "sg:address":"Calle de Pe\u00d1ascales, 14",
    "sg:city":"Madrid",
    "sg:orig_category":"Centros De Educaci\u00d3n Especial",
    "sg:phone":"+34 915 04 51 64",
    "sg:postcode":"28028",
    "sg:province":"Madrid",
    "wof:name":"Fundacion Adsis",
    "wof:placetype":"venue"
},
  "geometry": {"coordinates":[-3.6661479473,40.4238739014],"type":"Point"}
}