{
  "type": "Feature",
  "properties": {
    "iso:country":"ES",
    "sg:address":"Carr Barcelona, 179",
    "sg:city":"Girona",
    "sg:orig_category":"Molduras, Junquillos, Listones Y Molduras Perforadas",
    "sg:phone":"+34 972 20 22 10",
    "sg:postcode":"17003",
    "sg:province":"Girona",
    "wof:name":"Iba\u00f1ez Vidal Felix",
    "wof:placetype":"venue"
},
  "geometry": {"coordinates":[2.8124964237,41.9653663635],"type":"Point"}
}