{
  "type": "Feature",
  "properties": {
    "iso:country":"ES",
    "sg:address":"Carrer de Font, 19",
    "sg:city":"S. Just Desvern",
    "sg:orig_category":"Panader\u00cdas, Panader\u00cdas",
    "sg:phone":"+34 934 73 36 24",
    "sg:postcode":"08960",
    "sg:province":"Barcelona",
    "wof:name":"Panificadora Del Baix Llobregat S.a.",
    "wof:placetype":"venue"
},
  "geometry": {"coordinates":[2.0715389252,41.3819313049],"type":"Point"}
}