{
  "type": "Feature",
  "properties": {
    "addr:full":"Calle de Leopoldo Lugones, 24 Lugones Asturias 33420",
    "addr:housenumber":"24",
    "addr:postcode":"33420",
    "addr:street":"Calle De Leopoldo Lugones",
    "iso:country":"ES",
    "sg:address":"Calle de Leopoldo Lugones, 24",
    "sg:city":"Lugones",
    "sg:orig_category":"Venta, Instalaci\u00d3n De Calefacci\u00d3n",
    "sg:phone":"+34 985 98 71 41",
    "sg:postcode":"33420",
    "sg:province":"Asturias",
    "wof:name":"Ulex Clima,s.l.u",
    "wof:placetype":"venue"
},
  "geometry": {"coordinates":[-5.804954052,43.4016036987],"type":"Point"}
}