{
  "type": "Feature",
  "properties": {
    "addr:full":"Calle de Simon Ruiz, 10 Medina Campo Valladolid 47400",
    "addr:housenumber":"10",
    "addr:postcode":"47400",
    "addr:street":"Calle De Simon Ruiz",
    "iso:country":"ES",
    "sg:address":"Calle de Simon Ruiz, 10",
    "sg:city":"Medina Campo",
    "sg:orig_category":"Cervecer\u00cdas",
    "sg:phone":"+34 983 81 12 16",
    "sg:postcode":"47400",
    "sg:province":"Valladolid",
    "wof:name":"Perez Fernandez Maria Elena",
    "wof:placetype":"venue"
},
  "geometry": {"coordinates":[-4.9129090309,41.3068161011],"type":"Point"}
}