{
  "type": "Feature",
  "properties": {
    "addr:full":"Calle de Baranoa, 6 Madrid Madrid 28033",
    "addr:housenumber":"6",
    "addr:postcode":"28033",
    "addr:street":"Calle De Baranoa",
    "iso:country":"ES",
    "sg:address":"Calle de Baranoa, 6",
    "sg:city":"Madrid",
    "sg:orig_category":"\u00d3ptica: Instrumentos (fabricaci\u00d3n)",
    "sg:phone":"+34 917 64 67 04",
    "sg:postcode":"28033",
    "sg:province":"Madrid",
    "sg:website":"www.optilasa.com",
    "wof:name":"Optilasa S.l.",
    "wof:placetype":"venue"
},
  "geometry": {"coordinates":[-3.638884306,40.474521637],"type":"Point"}
}