{
  "type": "Feature",
  "properties": {
    "iso:country":"ES",
    "sg:address":"Avda Varadero (el), S/n",
    "sg:city":"Playa Blanca",
    "sg:orig_category":"Molduras, Junquillos, Listones Y Molduras Perforadas",
    "sg:phone":"+34 928 51 85 99",
    "sg:postcode":"35580",
    "sg:province":"Las Palmas",
    "wof:name":"Street  Charmaine Patricia",
    "wof:placetype":"venue"
},
  "geometry": {"coordinates":[-13.8302488327,28.8640346527],"type":"Point"}
}