{
  "type": "Feature",
  "properties": {
    "iso:country":"ES",
    "sg:address":"Carr Portell, 15",
    "sg:city":"Torregrossa",
    "sg:orig_category":"Venta, Instalaci\u00d3n De Calefacci\u00d3n",
    "sg:phone":"+34 973 17 00 23",
    "sg:postcode":"25141",
    "sg:province":"Lleida",
    "wof:name":"Falguera Badia Jose",
    "wof:placetype":"venue"
},
  "geometry": {"coordinates":[0.8324049711,41.5803718567],"type":"Point"}
}