{
  "type": "Feature",
  "properties": {
    "addr:full":"Avda Salvador (el), S/n Falces Navarra 31370",
    "addr:housenumber":"/ n",
    "addr:postcode":"31370",
    "addr:street":"Avda Salvador El S",
    "iso:country":"ES",
    "sg:address":"Avda Salvador (el), S/n",
    "sg:city":"Falces",
    "sg:orig_category":"Frutas, Legumbres Frescas Y Tempranas (al Por Menor)",
    "sg:phone":"+34 948 73 42 31",
    "sg:postcode":"31370",
    "sg:province":"Navarra",
    "wof:name":"Alium Almacenes Y Distribucion",
    "wof:placetype":"venue"
},
  "geometry": {"coordinates":[-1.7970621586,42.3917732239],"type":"Point"}
}