{
  "type": "Feature",
  "properties": {
    "addr:full":"C/ Santiago Apostol, 9 Torrellano Alicante 03320",
    "addr:housenumber":"9",
    "addr:postcode":"03320",
    "addr:street":"C / Santiago Apostol",
    "iso:country":"ES",
    "sg:address":"C/ Santiago Apostol, 9",
    "sg:city":"Torrellano",
    "sg:orig_category":"Pintura, Barniz, Productos Asimilables (fabricaci\u00d3n, Al Por Mayor)",
    "sg:phone":"+34 965 68 23 97",
    "sg:postcode":"03320",
    "sg:province":"Alicante",
    "wof:name":"Esclapez Segarra Esteban",
    "wof:placetype":"venue"
},
  "geometry": {"coordinates":[-0.5883889794,38.2921943665],"type":"Point"}
}