{
  "type": "Feature",
  "properties": {
    "iso:country":"ES",
    "sg:address":"Calle de Espiritu Santo, 4",
    "sg:city":"Madrid",
    "sg:orig_category":"Carnicer\u00cdas, Carnicer\u00cdas",
    "sg:phone":"+34 915 21 42 98",
    "sg:postcode":"28004",
    "sg:province":"Madrid",
    "wof:name":"Palacio Garcia Jose Manuel",
    "wof:placetype":"venue"
},
  "geometry": {"coordinates":[-3.7022099495,40.4251441956],"type":"Point"}
}