{
  "type": "Feature",
  "properties": {
    "iso:country":"ES",
    "sg:address":"Calle de Castello, 5",
    "sg:city":"Madrid",
    "sg:orig_category":"Restaurantes",
    "sg:phone":"+34 914 35 93 81",
    "sg:postcode":"28001",
    "sg:province":"Madrid",
    "wof:name":"Abdon Fernand Sancho Y Tres Mas C.b.",
    "wof:placetype":"venue"
},
  "geometry": {"coordinates":[-3.684967,40.439659],"type":"Point"}
}