{
  "type": "Feature",
  "properties": {
    "addr:full":"Calle de Carlote, 7 Esperanza Santa Cruz De Tenerife 38290",
    "addr:housenumber":"7",
    "addr:postcode":"38290",
    "addr:street":"Calle De Carlote",
    "iso:country":"ES",
    "sg:address":"Calle de Carlote, 7",
    "sg:city":"Esperanza",
    "sg:orig_category":"Chapister\u00cda",
    "sg:phone":"+34 922 54 80 61",
    "sg:postcode":"38290",
    "sg:province":"Santa Cruz De Tenerife",
    "wof:name":"Alonso Labrador Juan Jose",
    "wof:placetype":"venue"
},
  "geometry": {"coordinates":[-16.3583850861,28.4529132843],"type":"Point"}
}