{
  "type": "Feature",
  "properties": {
    "addr:full":"Calle de Ecuador, S/n Valladolid Valladolid 47014",
    "addr:housenumber":"s / n",
    "addr:postcode":"47014",
    "addr:street":"Calle De Ecuador",
    "iso:country":"ES",
    "sg:address":"Calle de Ecuador, S/n",
    "sg:city":"Valladolid",
    "sg:orig_category":"Frutas, Legumbres Frescas Y Tempranas (al Por Menor)",
    "sg:phone":"+34 983 47 46 43",
    "sg:postcode":"47014",
    "sg:province":"Valladolid",
    "wof:name":"Marcos Gonzalez Julian",
    "wof:placetype":"venue"
},
  "geometry": {"coordinates":[-4.7468900681,41.6306304932],"type":"Point"}
}