{
  "type": "Feature",
  "properties": {
    "iso:country":"ES",
    "sg:address":"Calle de Ametzaga\u00d1a, 39",
    "sg:city":"Donostia-san Sebastian",
    "sg:orig_category":"Art\u00cdculos De Decoraci\u00d3n",
    "sg:phone":"+34 943 32 05 03",
    "sg:postcode":"20012",
    "sg:province":"Guip\u00f9zcoa",
    "wof:name":"Azcona Mingo Chiara",
    "wof:placetype":"venue"
},
  "geometry": {"coordinates":[-1.9686344862,43.3172950745],"type":"Point"}
}