{
  "type": "Feature",
  "properties": {
    "addr:full":"Carrer de Noi Del Sucre, 21 Viladecans Barcelona 08840",
    "addr:housenumber":"21",
    "addr:postcode":"08840",
    "addr:street":"Carrer De Noi Del Sucre",
    "iso:country":"ES",
    "sg:address":"Carrer de Noi Del Sucre, 21",
    "sg:city":"Viladecans",
    "sg:orig_category":"Panader\u00cdas, Panader\u00cdas",
    "sg:phone":"+34 936 37 75 53",
    "sg:postcode":"08840",
    "sg:province":"Barcelona",
    "wof:name":"Meripast S.l.",
    "wof:placetype":"venue"
},
  "geometry": {"coordinates":[2.0201261044,41.3121452332],"type":"Point"}
}