{
  "type": "Feature",
  "properties": {
    "iso:country":"ES",
    "sg:address":"Carrer de Thous, 4",
    "sg:city":"Barcelona",
    "sg:orig_category":"Traductores",
    "sg:phone":"+34 932 31 72 84",
    "sg:postcode":"08024",
    "sg:province":"Barcelona",
    "wof:name":"Podivin 2000",
    "wof:placetype":"venue"
},
  "geometry": {"coordinates":[2.1669249535,41.4144668579],"type":"Point"}
}