{
  "type": "Feature",
  "properties": {
    "iso:country":"ES",
    "sg:address":"Plazoleta Del Muelle, 1",
    "sg:city":"Santa Cruz Palma",
    "sg:orig_category":"Librer\u00cdas",
    "sg:phone":"+34 922 41 76 31",
    "sg:postcode":"38700",
    "sg:province":"Santa Cruz De Tenerife",
    "wof:name":"Inversiones Hermoyal S.l.",
    "wof:placetype":"venue"
},
  "geometry": {"coordinates":[-17.7677326202,28.6805782318],"type":"Point"}
}