{
  "type": "Feature",
  "properties": {
    "iso:country":"ES",
    "sg:address":"Avda Sevilla, S/n",
    "sg:city":"Dos Hermanas",
    "sg:classifiers":[
        {
            "category":"Professional",
            "subcategory":"Management & Consulting",
            "type":"Services"
        }
    ],
    "sg:phone":"+34 955 67 40 58",
    "sg:postcode":"41700",
    "sg:province":"Sevilla",
    "sg:tags":[
        "asesor\u00cda",
        "en",
        "marketing"
    ],
    "wof:name":"Grupo De Danza Ciudad De Dos Hermanas",
    "wof:placetype":"venue"
},
  "geometry": {"coordinates":[-5.9275331497,37.2882728577],"type":"Point"}
}