{
  "type": "Feature",
  "properties": {
    "iso:country":"ES",
    "sg:address":"Muel Puntilla (de La), S/n",
    "sg:city":"Ceuta",
    "sg:orig_category":"Peritos Mar\u00cdtimos",
    "sg:phone":"+34 956 50 97 03",
    "sg:postcode":"51001",
    "sg:province":"Ceuta",
    "wof:name":"Jose Salama Y Compa\u00f1ia S.l.",
    "wof:placetype":"venue"
},
  "geometry": {"coordinates":[-5.3302302361,35.8947601318],"type":"Point"}
}