{
  "type": "Feature",
  "properties": {
    "iso:country":"ES",
    "sg:address":"Entd Casa El Vi\u00d1ero, 33",
    "sg:city":"Castellar-oliveral",
    "sg:orig_category":"Limpieza Con Chorro De Arena Y Con Granalla, Pulido",
    "sg:phone":"+34 963 96 15 05",
    "sg:postcode":"46026",
    "sg:province":"Valencia",
    "wof:name":"Furio Mejias Enrique",
    "wof:placetype":"venue"
},
  "geometry": {"coordinates":[-0.3637839854,39.4265289307],"type":"Point"}
}