{
  "type": "Feature",
  "properties": {
    "iso:country":"ES",
    "sg:address":"Calle de Hermana Andresa De La, 5",
    "sg:city":"Fraga",
    "sg:orig_category":"Empresas De Carpinter\u00cda De Madera",
    "sg:phone":"+34 974 47 06 11",
    "sg:postcode":"22520",
    "sg:province":"Huesca",
    "wof:name":"Carpinteria Sanz S.cv.",
    "wof:placetype":"venue"
},
  "geometry": {"coordinates":[0.3399530053,41.5238380432],"type":"Point"}
}