{
  "type": "Feature",
  "properties": {
    "addr:full":"Avda Marina (de La), 9 Rota C\u00e1diz 11520",
    "addr:housenumber":"9",
    "addr:postcode":"11520",
    "addr:street":"Avda Marina De La;Ca\u0301Diz",
    "iso:country":"ES",
    "sg:address":"Avda Marina (de La), 9",
    "sg:city":"Rota",
    "sg:orig_category":"Pod\u00d3logos: Pedicuros",
    "sg:phone":"+34 956 84 06 51",
    "sg:postcode":"11520",
    "sg:province":"C\u00e1diz",
    "wof:name":"Rodriguez Fuentes Sagrario",
    "wof:placetype":"venue"
},
  "geometry": {"coordinates":[-6.3612289429,36.6233406067],"type":"Point"}
}