{
  "type": "Feature",
  "properties": {
    "iso:country":"ES",
    "sg:address":"Calle de Miguel Fluiters, 6",
    "sg:city":"Guadalajara",
    "sg:orig_category":"Mercer\u00cda, Lencer\u00cda (al Por Menor)",
    "sg:phone":"+34 949 21 14 65",
    "sg:postcode":"19001",
    "sg:province":"Guadalajara",
    "wof:name":"Fernandez Villanueva Carmen Irene",
    "wof:placetype":"venue"
},
  "geometry": {"coordinates":[-3.1671319008,40.634349823],"type":"Point"}
}