{
  "type": "Feature",
  "properties": {
    "addr:full":"Urb. Caserio De Urgel, 14 San Ildefonso Segovia 40100",
    "addr:housenumber":"14",
    "addr:postcode":"40100",
    "iso:country":"ES",
    "sg:address":"Urb. Caserio De Urgel, 14",
    "sg:city":"San Ildefonso",
    "sg:orig_category":"Construcciones Met\u00c1licas",
    "sg:phone":"+34 921 47 22 02",
    "sg:postcode":"40100",
    "sg:province":"Segovia",
    "wof:name":"Marcos Gomez Juan Pedro",
    "wof:placetype":"venue"
},
  "geometry": {"coordinates":[-4.0079989433,40.8997459412],"type":"Point"}
}