{
  "type": "Feature",
  "properties": {
    "addr:full":"Albardinal, S/n Mojacar Almer\u00eda 04638",
    "addr:postcode":"04638",
    "addr:street":"Albardinal S / N;Almeri\u0301A",
    "iso:country":"ES",
    "sg:address":"Albardinal, S/n",
    "sg:city":"Mojacar",
    "sg:orig_category":"Sanatorios M\u00c9dico",
    "sg:phone":"+34 950 47 51 13",
    "sg:postcode":"04638",
    "sg:province":"Almer\u00eda",
    "wof:name":"Servicio Andaluz De Salud",
    "wof:placetype":"venue"
},
  "geometry": {"coordinates":[-1.8295990229,37.1382598877],"type":"Point"}
}