{
  "type": "Feature",
  "properties": {
    "iso:country":"ES",
    "sg:address":"Carr Doctor Trueta, 25",
    "sg:city":"Cassa Selva",
    "sg:orig_category":"Empresarios",
    "sg:phone":"+34 972 46 05 61",
    "sg:postcode":"17244",
    "sg:province":"Girona",
    "wof:name":"Lloveras Victorio Albert",
    "wof:placetype":"venue"
},
  "geometry": {"coordinates":[2.8815801144,41.8868255615],"type":"Point"}
}