{
  "type": "Feature",
  "properties": {
    "addr:full":"Calle de Guadiana, 115 Bosque Madrid 28670",
    "addr:housenumber":"115",
    "addr:postcode":"28670",
    "addr:street":"Calle De Guadiana",
    "iso:country":"ES",
    "sg:address":"Calle de Guadiana, 115",
    "sg:city":"Bosque",
    "sg:orig_category":"Audiovisuales (producci\u00d3n, Edici\u00d3n, Realizaci\u00d3n)",
    "sg:phone":"+34 916 16 87 88",
    "sg:postcode":"28670",
    "sg:province":"Madrid",
    "wof:name":"Lozano Iba\u00f1ez Monserrat",
    "wof:placetype":"venue"
},
  "geometry": {"coordinates":[-3.9391698837,40.3783302307],"type":"Point"}
}