{
  "type": "Feature",
  "properties": {
    "addr:full":"Calle de Valenzuela Soler, 2 Maria Huerva Zaragoza 50430",
    "addr:housenumber":"2",
    "addr:postcode":"50430",
    "addr:street":"Calle De Valenzuela Soler;Huerva",
    "iso:country":"ES",
    "sg:address":"Calle de Valenzuela Soler, 2",
    "sg:city":"Maria Huerva",
    "sg:orig_category":"Cajas De Ahorro",
    "sg:phone":"+34 976 12 40 92",
    "sg:postcode":"50430",
    "sg:province":"Zaragoza",
    "sg:website":"www.cajarural.es",
    "wof:name":"Caja Rural Aragonesa Y De Los Pirineos",
    "wof:placetype":"venue"
},
  "geometry": {"coordinates":[-0.9959070086,41.5378684998],"type":"Point"}
}