{
  "type": "Feature",
  "properties": {
    "addr:full":"Calle de Maestro Falla, 21 S. Pedro Pinatar Murcia 30740",
    "addr:housenumber":"21",
    "addr:postcode":"30740",
    "addr:street":"Calle De Maestro Falla;S. Pedro",
    "iso:country":"ES",
    "sg:address":"Calle de Maestro Falla, 21",
    "sg:city":"S. Pedro Pinatar",
    "sg:orig_category":"Florister\u00cdas",
    "sg:phone":"+34 968 18 04 29",
    "sg:postcode":"30740",
    "sg:province":"Murcia",
    "wof:name":"Albaladejo Sanchez Jose",
    "wof:placetype":"venue"
},
  "geometry": {"coordinates":[-0.7927753925,37.8293266296],"type":"Point"}
}