{
  "type": "Feature",
  "properties": {
    "addr:full":"Calle de Pregoneros (los), 15 Ponferrada Le\u00f3n 24400",
    "addr:housenumber":"15",
    "addr:postcode":"24400",
    "addr:street":"Calle De Pregoneros Los",
    "iso:country":"ES",
    "sg:address":"Calle de Pregoneros (los), 15",
    "sg:city":"Ponferrada",
    "sg:orig_category":"Asesor\u00cda Sobre Comunicaci\u00d3n De Empresas",
    "sg:phone":"+34 987 41 89 28",
    "sg:postcode":"24400",
    "sg:province":"Le\u00f3n",
    "wof:name":"Despacho Profesional Ballester S.l.l.",
    "wof:placetype":"venue"
},
  "geometry": {"coordinates":[-6.5904040337,42.5433654785],"type":"Point"}
}