{
  "type": "Feature",
  "properties": {
    "addr:full":"Calle de Angustias, 29 Tabernas Almer\u00eda 04200",
    "addr:housenumber":"29",
    "addr:postcode":"04200",
    "addr:street":"Calle De Angustias;Almeri\u0301A",
    "iso:country":"ES",
    "sg:address":"Calle de Angustias, 29",
    "sg:city":"Tabernas",
    "sg:orig_category":"Inmobiliaria (agencias)",
    "sg:phone":"+34 950 36 93 00",
    "sg:postcode":"04200",
    "sg:province":"Almer\u00eda",
    "wof:name":"Fincas Calatrava S.l.",
    "wof:placetype":"venue"
},
  "geometry": {"coordinates":[-2.3980448246,37.0491333008],"type":"Point"}
}