{
  "type": "Feature",
  "properties": {
    "addr:full":"Calle de Sotera De La Mier, 10 Sestao Vizcaya 48910",
    "addr:housenumber":"10",
    "addr:postcode":"48910",
    "addr:street":"Calle De Sotera De La Mier",
    "iso:country":"ES",
    "sg:address":"Calle de Sotera De La Mier, 10",
    "sg:city":"Sestao",
    "sg:orig_category":"Empresas De Carpinter\u00cda De Madera",
    "sg:phone":"+34 944 95 68 04",
    "sg:postcode":"48910",
    "sg:province":"Vizcaya",
    "wof:name":"Martin Fuente Jesus Maria",
    "wof:placetype":"venue"
},
  "geometry": {"coordinates":[-3.0067150593,43.3124008179],"type":"Point"}
}