{
  "type": "Feature",
  "properties": {
    "addr:full":"Calle de Antonio Machado, 3 Caspe Zaragoza 50700",
    "addr:housenumber":"3",
    "addr:postcode":"50700",
    "addr:street":"Calle De Antonio Machado",
    "iso:country":"ES",
    "sg:address":"Calle de Antonio Machado, 3",
    "sg:city":"Caspe",
    "sg:orig_category":"Plomeros",
    "sg:phone":"+34 976 63 12 16",
    "sg:postcode":"50700",
    "sg:province":"Zaragoza",
    "wof:name":"Fontaneria Y Calefaccion Guiu S.l.",
    "wof:placetype":"venue"
},
  "geometry": {"coordinates":[-0.0461543016,41.2388725281],"type":"Point"}
}