{
  "type": "Feature",
  "properties": {
    "iso:country":"ES",
    "sg:address":"Avda Parayas, 10",
    "sg:city":"Malia\u00d1o",
    "sg:orig_category":"Agentes, Concesionarios Y Sucursales De Veh\u00cdculos",
    "sg:phone":"+34 942 25 18 44",
    "sg:postcode":"39600",
    "sg:province":"Cantabria",
    "wof:name":"Jose Luis Sangrones S.l.",
    "wof:placetype":"venue"
},
  "geometry": {"coordinates":[-3.8393390179,43.4179153442],"type":"Point"}
}