{
  "type": "Feature",
  "properties": {
    "iso:country":"ES",
    "sg:address":"Calle de Rey Carlos Iii, 19",
    "sg:city":"Aguilas",
    "sg:orig_category":"Cajas De Ahorro",
    "sg:phone":"+34 968 44 70 88",
    "sg:postcode":"30880",
    "sg:province":"Murcia",
    "sg:website":"www.lacaixa.es",
    "wof:name":"Caixa D'estalvis I Pensions De Barcelona",
    "wof:placetype":"venue"
},
  "geometry": {"coordinates":[-1.5855820179,37.4039001465],"type":"Point"}
}