{
  "type": "Feature",
  "properties": {
    "addr:full":"Industrial, S/n San Pedro Arroyo \u00c1vila 05350",
    "addr:housenumber":"/ n",
    "addr:postcode":"05350",
    "addr:street":"Industrial",
    "iso:country":"ES",
    "sg:address":"Industrial, S/n",
    "sg:city":"San Pedro Arroyo",
    "sg:orig_category":"Reciclaje Y Tratamiento De Desechos Varios",
    "sg:phone":"+34 920 24 06 17",
    "sg:postcode":"05350",
    "sg:province":"\u00c1vila",
    "wof:name":"Castellana De Medio Ambiente S.l.",
    "wof:placetype":"venue"
},
  "geometry": {"coordinates":[-4.8702588081,40.8017959595],"type":"Point"}
}