{
  "type": "Feature",
  "properties": {
    "iso:country":"ES",
    "sg:address":"Ctra. General, 94",
    "sg:city":"Guia Isora",
    "sg:orig_category":"Embalajes",
    "sg:phone":"+34 922 85 20 13",
    "sg:postcode":"38680",
    "sg:province":"Santa Cruz De Tenerife",
    "wof:name":"Pretoso S.l.",
    "wof:placetype":"venue"
},
  "geometry": {"coordinates":[-16.7654438019,28.1817798615],"type":"Point"}
}