{
  "type": "Feature",
  "properties": {
    "iso:country":"ES",
    "sg:address":"Plaz Principado De Asturias, 3",
    "sg:city":"Pola De Lena",
    "sg:orig_category":"Caf\u00c9s, Bares, Cervecer\u00cdas",
    "sg:phone":"+34 985 49 19 87",
    "sg:postcode":"33630",
    "sg:province":"Asturias",
    "wof:name":"Montes Rodriguez Araceli",
    "wof:placetype":"venue"
},
  "geometry": {"coordinates":[-5.8280730247,43.1639785767],"type":"Point"}
}