{
  "type": "Feature",
  "properties": {
    "iso:country":"ES",
    "sg:address":"Carrer de Marques Montroig, 6",
    "sg:city":"Sitges",
    "sg:orig_category":"Art\u00cdculos De Regalo (al Por Menor)",
    "sg:phone":"+34 938 94 44 00",
    "sg:postcode":"08870",
    "sg:province":"Barcelona",
    "wof:name":"Abdullatif Lodhi Kairron",
    "wof:placetype":"venue"
},
  "geometry": {"coordinates":[1.861101,41.255829],"type":"Point"}
}