{
  "type": "Feature",
  "properties": {
    "iso:country":"ES",
    "sg:address":"Carr Ignasi Bastus, 19",
    "sg:city":"Lleida",
    "sg:orig_category":"Molduras, Junquillos, Listones Y Molduras Perforadas",
    "sg:phone":"+34 973 21 15 66",
    "sg:postcode":"25001",
    "sg:province":"Lleida",
    "wof:name":"Saez Invernon Julio",
    "wof:placetype":"venue"
},
  "geometry": {"coordinates":[0.6442120075,41.6051673889],"type":"Point"}
}