{
  "type": "Feature",
  "properties": {
    "addr:full":"Calle de Hernando De Soto, 27 Sevilla Sevilla 41007",
    "addr:housenumber":"27",
    "addr:postcode":"41007",
    "addr:street":"Calle De Hernando De Soto",
    "iso:country":"ES",
    "sg:address":"Calle de Hernando De Soto, 27",
    "sg:city":"Sevilla",
    "sg:orig_category":"M\u00dasicos Int\u00c9rpretes",
    "sg:phone":"+34 954 51 96 19",
    "sg:postcode":"41007",
    "sg:province":"Sevilla",
    "wof:name":"Mu\u00f1oz Fores Francisco",
    "wof:placetype":"venue"
},
  "geometry": {"coordinates":[-5.9534840584,37.3964195251],"type":"Point"}
}