{
  "type": "Feature",
  "properties": {
    "addr:full":"Nou, 9 Argilaga Tarragona 43765",
    "addr:housenumber":"9",
    "addr:postcode":"43765",
    "addr:street":"Nou",
    "iso:country":"ES",
    "sg:address":"Nou, 9",
    "sg:city":"Argilaga",
    "sg:orig_category":"Productores Recolectores, Venta Directa De Vinos",
    "sg:phone":"+34 977 61 13 62",
    "sg:postcode":"43765",
    "sg:province":"Tarragona",
    "wof:name":"Cooperativa Agricola",
    "wof:placetype":"venue"
},
  "geometry": {"coordinates":[1.2795100212,41.2023468018],"type":"Point"}
}