{
  "type": "Feature",
  "properties": {
    "addr:full":"Ctra Montblanc (de), 20 Espluga Francoli Tarragona 43440",
    "addr:housenumber":"20",
    "addr:postcode":"43440",
    "addr:street":"Ctra Montblanc De",
    "iso:country":"ES",
    "sg:address":"Ctra Montblanc (de), 20",
    "sg:city":"Espluga Francoli",
    "sg:orig_category":"Empresas De Carpinter\u00cda De Madera",
    "sg:phone":"+34 977 87 07 71",
    "sg:postcode":"43440",
    "sg:province":"Tarragona",
    "wof:name":"Fusteria Baldrich I Fills S.l.",
    "wof:placetype":"venue"
},
  "geometry": {"coordinates":[1.1068999767,41.3965377808],"type":"Point"}
}