{
  "type": "Feature",
  "properties": {
    "addr:full":"Calle de Ingeniero La Cierva, 62 Sevilla Sevilla 41006",
    "addr:housenumber":"62",
    "addr:postcode":"41006",
    "addr:street":"Calle De Ingeniero La Cierva",
    "iso:country":"ES",
    "sg:address":"Calle de Ingeniero La Cierva, 62",
    "sg:city":"Sevilla",
    "sg:orig_category":"Ropa Para Se\u00d1oras Y Caballeros (al Por Menor)",
    "sg:phone":"+34 954 63 29 88",
    "sg:postcode":"41006",
    "sg:province":"Sevilla",
    "wof:name":"Euromod Grupo Textil S.l.",
    "wof:placetype":"venue"
},
  "geometry": {"coordinates":[-5.9494051933,37.3720932007],"type":"Point"}
}