{
  "type": "Feature",
  "properties": {
    "iso:country":"ES",
    "sg:address":"El Barranco, S/n",
    "sg:city":"Lanjaron",
    "sg:orig_category":"Laboratorios",
    "sg:phone":"+34 958 77 11 31",
    "sg:postcode":"18420",
    "sg:province":"Granada",
    "wof:name":"Torres Fernandez-pi\u00f1as Cristina",
    "wof:placetype":"venue"
},
  "geometry": {"coordinates":[-3.4924139977,36.9212532043],"type":"Point"}
}