{
  "type": "Feature",
  "properties": {
    "addr:full":"Carr Bailen, 69 Vilanova I La Geltru Barcelona 08800",
    "addr:housenumber":"69",
    "addr:postcode":"08800",
    "addr:street":"Carr Bailen",
    "iso:country":"ES",
    "sg:address":"Carr Bailen, 69",
    "sg:city":"Vilanova I La Geltru",
    "sg:orig_category":"Ropa Para Se\u00d1oras Y Caballeros (al Por Menor)",
    "sg:phone":"+34 938 15 38 56",
    "sg:postcode":"08800",
    "sg:province":"Barcelona",
    "wof:name":"Tot Confeccio S.l.",
    "wof:placetype":"venue"
},
  "geometry": {"coordinates":[1.7164839506,41.2225570679],"type":"Point"}
}