{
  "type": "Feature",
  "properties": {
    "addr:full":"Calle de Alameda, 11 Navalmanzano Segovia 40280",
    "addr:housenumber":"11",
    "addr:postcode":"40280",
    "addr:street":"Calle De Alameda",
    "iso:country":"ES",
    "sg:address":"Calle de Alameda, 11",
    "sg:city":"Navalmanzano",
    "sg:orig_category":"Plomeros",
    "sg:phone":"+34 921 57 51 21",
    "sg:postcode":"40280",
    "sg:province":"Segovia",
    "wof:name":"Fontaneria Polofi S.l.",
    "wof:placetype":"venue"
},
  "geometry": {"coordinates":[-4.2583441734,41.2156295776],"type":"Point"}
}