{
  "type": "Feature",
  "properties": {
    "iso:country":"ES",
    "sg:address":"Av Sant Narcis, 113",
    "sg:city":"Girona",
    "sg:orig_category":"Fabricaci\u00d3n, Distribuci\u00d3n De Material Para La Climatizaci\u00d3n, Aireaci\u00d3n Y Ventilaci\u00d3n",
    "sg:phone":"+34 972 24 48 60",
    "sg:postcode":"17005",
    "sg:province":"Girona",
    "wof:name":"Garcia Guidux Eulalio",
    "wof:placetype":"venue"
},
  "geometry": {"coordinates":[2.8113780022,41.9693527222],"type":"Point"}
}