{
  "type": "Feature",
  "properties": {
    "addr:full":"Calle de Cid Campeador, 16 Linares Ja\u00e9n 23700",
    "addr:housenumber":"16",
    "addr:postcode":"23700",
    "addr:street":"Calle De Cid Campeador;Jae\u0301N",
    "iso:country":"ES",
    "sg:address":"Calle de Cid Campeador, 16",
    "sg:city":"Linares",
    "sg:orig_category":"Papeler\u00cdas, Librer\u00cdas",
    "sg:phone":"+34 953 69 28 99",
    "sg:postcode":"23700",
    "sg:province":"Ja\u00e9n",
    "wof:name":"Fernandez Robles Manuela",
    "wof:placetype":"venue"
},
  "geometry": {"coordinates":[-3.6399614811,38.0924758911],"type":"Point"}
}