{
  "type": "Feature",
  "properties": {
    "addr:full":"Avda Vicalvaro (de), 133 Coslada Madrid 28820",
    "addr:housenumber":"133",
    "addr:postcode":"28820",
    "addr:street":"Avda Vicalvaro De",
    "iso:country":"ES",
    "sg:address":"Avda Vicalvaro (de), 133",
    "sg:city":"Coslada",
    "sg:orig_category":"Tapicer\u00cdas",
    "sg:phone":"+34 916 72 82 89",
    "sg:postcode":"28820",
    "sg:province":"Madrid",
    "wof:name":"Montero Suarez Mercedes",
    "wof:placetype":"venue"
},
  "geometry": {"coordinates":[-3.5392200947,40.4191207886],"type":"Point"}
}