{
  "type": "Feature",
  "properties": {
    "iso:country":"ES",
    "sg:address":"Calle de Iparraguirre, 67",
    "sg:city":"Irun",
    "sg:orig_category":"Centros De Coordinaci\u00d3n",
    "sg:phone":"+34 943 63 05 73",
    "sg:postcode":"20305",
    "sg:province":"Guip\u00f9zcoa",
    "wof:name":"Jorge Behobide Peralta",
    "wof:placetype":"venue"
},
  "geometry": {"coordinates":[-1.7637690306,43.3425445557],"type":"Point"}
}