{
  "type": "Feature",
  "properties": {
    "addr:full":"Calle de Monte, 16 Quesada Ja\u00e9n 23480",
    "addr:housenumber":"16",
    "addr:postcode":"23480",
    "addr:street":"Calle De Monte",
    "iso:country":"ES",
    "sg:address":"Calle de Monte, 16",
    "sg:city":"Quesada",
    "sg:orig_category":"Electrodom\u00c9sticos (al Por Menor)",
    "sg:phone":"+34 953 73 37 03",
    "sg:postcode":"23480",
    "sg:province":"Ja\u00e9n",
    "wof:name":"Ferla Electrodomesticos S.l",
    "wof:placetype":"venue"
},
  "geometry": {"coordinates":[-3.0687921047,37.845451355],"type":"Point"}
}