{
  "type": "Feature",
  "properties": {
    "iso:country":"ES",
    "sg:address":"Calle de Mairena, 2",
    "sg:city":"Alcala Guadaira",
    "sg:orig_category":"Zapatos (al Por Menor)",
    "sg:phone":"+34 955 68 03 61",
    "sg:postcode":"41500",
    "sg:province":"Sevilla",
    "wof:name":"Kika Zapatos Y Complementos, S.l.",
    "wof:placetype":"venue"
},
  "geometry": {"coordinates":[-5.8426594734,37.3463745117],"type":"Point"}
}