{
  "type": "Feature",
  "properties": {
    "iso:country":"ES",
    "sg:address":"Calle de Inglaterra, 1",
    "sg:city":"Candelaria",
    "sg:orig_category":"Inmobiliaria (agencias)",
    "sg:phone":"+34 922 50 22 70",
    "sg:postcode":"38530",
    "sg:province":"Santa Cruz De Tenerife",
    "wof:name":"Daluz E Hijos S.l",
    "wof:placetype":"venue"
},
  "geometry": {"coordinates":[-16.3693084717,28.3615665436],"type":"Point"}
}