{
  "type": "Feature",
  "properties": {
    "addr:full":"Calle de San Miguel Alta, 6 Granada Granada 18002",
    "addr:housenumber":"6",
    "addr:postcode":"18002",
    "addr:street":"Calle De San;Alta",
    "iso:country":"ES",
    "sg:address":"Calle de San Miguel Alta, 6",
    "sg:city":"Granada",
    "sg:orig_category":"Bazares, Art\u00cdculos De Limpieza Y De Cocina (al Por Menor)",
    "sg:phone":"+34 958 26 52 53",
    "sg:postcode":"18002",
    "sg:province":"Granada",
    "wof:name":"Pe\u00f1a Egea Maria Del Carmen",
    "wof:placetype":"venue"
},
  "geometry": {"coordinates":[-3.6031301022,37.1731452942],"type":"Point"}
}