{
  "type": "Feature",
  "properties": {
    "addr:full":"Calle de Grupo Escolar, S/n Fuentealbilla Albacete 02260",
    "addr:housenumber":"s / n",
    "addr:postcode":"02260",
    "addr:street":"Calle De Grupo",
    "iso:country":"ES",
    "sg:address":"Calle de Grupo Escolar, S/n",
    "sg:city":"Fuentealbilla",
    "sg:orig_category":"Centros De Educaci\u00d3n Especial",
    "sg:phone":"+34 967 47 76 27",
    "sg:postcode":"02260",
    "sg:province":"Albacete",
    "wof:name":"Colegio Publico Cristo Del Valle",
    "wof:placetype":"venue"
},
  "geometry": {"coordinates":[-1.5516239405,39.268081665],"type":"Point"}
}