{
  "type": "Feature",
  "properties": {
    "iso:country":"ES",
    "sg:address":"Avda Antonio Cortes, 119",
    "sg:city":"Fuentes Nuevas",
    "sg:orig_category":"Reposter\u00cdas",
    "sg:phone":"+34 987 45 56 56",
    "sg:postcode":"24411",
    "sg:province":"Le\u00f3n",
    "wof:name":"Alvarez Dominguez Pedro",
    "wof:placetype":"venue"
},
  "geometry": {"coordinates":[-6.6395363808,42.5700759888],"type":"Point"}
}