{
  "type": "Feature",
  "properties": {
    "addr:full":"Calle de Doctor Encinas, 9 Potes Cantabria 39570",
    "addr:housenumber":"9",
    "addr:postcode":"39570",
    "addr:street":"Calle De Doctor Encinas",
    "iso:country":"ES",
    "sg:address":"Calle de Doctor Encinas, 9",
    "sg:city":"Potes",
    "sg:orig_category":"Cajas De Ahorro",
    "sg:phone":"+34 942 73 09 97",
    "sg:postcode":"39570",
    "sg:province":"Cantabria",
    "sg:website":"www.lacaixa.es",
    "wof:name":"Caixa D'estalvis I Pensions De Barcelona",
    "wof:placetype":"venue"
},
  "geometry": {"coordinates":[-4.6221885681,43.1538887024],"type":"Point"}
}