{
  "type": "Feature",
  "properties": {
    "addr:full":"Calle de Camino De Valladolid, 1 Torrelodones Madrid 28250",
    "addr:housenumber":"1",
    "addr:postcode":"28250",
    "addr:street":"Calle De Camino De Valladolid",
    "iso:country":"ES",
    "sg:address":"Calle de Camino De Valladolid, 1",
    "sg:city":"Torrelodones",
    "sg:orig_category":"Ingenier\u00cda, Centros De Estudios (diversos)",
    "sg:phone":"+34 918 59 67 50",
    "sg:postcode":"28250",
    "sg:province":"Madrid",
    "wof:name":"Proing S.l.",
    "wof:placetype":"venue"
},
  "geometry": {"coordinates":[-3.9273142815,40.5745735168],"type":"Point"}
}