{
  "type": "Feature",
  "properties": {
    "addr:full":"Calle de Cuesta De San Francisco, S/n San Mateo Murcia 30800",
    "addr:housenumber":"/ n",
    "addr:postcode":"30800",
    "addr:street":"Calle De Cuesta De San Francisco S",
    "iso:country":"ES",
    "sg:address":"Calle de Cuesta De San Francisco, S/n",
    "sg:city":"San Mateo",
    "sg:orig_category":"Electricidad: Instaladores",
    "sg:phone":"+34 968 46 65 32",
    "sg:postcode":"30800",
    "sg:province":"Murcia",
    "wof:name":"Pe\u00f1as Lario Rafael",
    "wof:placetype":"venue"
},
  "geometry": {"coordinates":[-1.1298867464,37.9834747314],"type":"Point"}
}