{
  "type": "Feature",
  "properties": {
    "iso:country":"ES",
    "sg:address":"Poli Industrial C/s, 6",
    "sg:city":"Rozas De Madrid",
    "sg:orig_category":"Ferreter\u00cda Artesanal",
    "sg:phone":"+34 916 36 32 19",
    "sg:postcode":"28230",
    "sg:province":"Madrid",
    "wof:name":"Forja Toledana S.l.",
    "wof:placetype":"venue"
},
  "geometry": {"coordinates":[-3.8913800716,40.5247497559],"type":"Point"}
}