{
  "type": "Feature",
  "properties": {
    "addr:full":"Ctra Cartama (de), 2 Alhaurin El Grande M\u00e1laga 29120",
    "addr:postcode":"29120",
    "addr:street":"Ctra Cartama De 2",
    "iso:country":"ES",
    "sg:address":"Ctra Cartama (de), 2",
    "sg:city":"Alhaurin El Grande",
    "sg:orig_category":"Enfermeras: Consultas, Atenci\u00d3n A Domicilio",
    "sg:phone":"+34 952 49 92 25",
    "sg:postcode":"29120",
    "sg:province":"M\u00e1laga",
    "wof:name":"Ramirez Garcia Josera Maria",
    "wof:placetype":"venue"
},
  "geometry": {"coordinates":[-4.6825361252,36.6441001892],"type":"Point"}
}