{
  "type": "Feature",
  "properties": {
    "iso:country":"ES",
    "sg:address":"Pl Esglesia (de L'), 1",
    "sg:city":"Casco Urbano",
    "sg:orig_category":"Cajas De Ahorro",
    "sg:phone":"+34 938 41 30 00",
    "sg:postcode":"08450",
    "sg:province":"Barcelona",
    "wof:name":"Caixa D'estalvis Sabadell",
    "wof:placetype":"venue"
},
  "geometry": {"coordinates":[2.4019749165,41.6397705078],"type":"Point"}
}