{
  "type": "Feature",
  "properties": {
    "addr:full":"C/ Urgell, 21 Tarrega Lleida 25300",
    "addr:housenumber":"21",
    "addr:postcode":"25300",
    "addr:street":"C / Urgell",
    "iso:country":"ES",
    "sg:address":"C/ Urgell, 21",
    "sg:city":"Tarrega",
    "sg:orig_category":"Peluqueros: De Se\u00d1oras",
    "sg:phone":"+34 973 31 04 97",
    "sg:postcode":"25300",
    "sg:province":"Lleida",
    "wof:name":"Soto Segura Ana",
    "wof:placetype":"venue"
},
  "geometry": {"coordinates":[1.1380879879,41.6465301514],"type":"Point"}
}