{
  "type": "Feature",
  "properties": {
    "addr:full":"Ctra Granollers A Sant Celoni, Km. 0014,0 Pla Morato Barcelona 08450",
    "addr:postcode":"08450",
    "addr:street":"Ctra Granollers A Sant Celoni Km. 0014,0 Pla",
    "iso:country":"ES",
    "sg:address":"Ctra Granollers A Sant Celoni, Km. 0014,0",
    "sg:city":"Pla Morato",
    "sg:orig_category":"Construcciones Met\u00c1licas",
    "sg:phone":"+34 938 41 22 61",
    "sg:postcode":"08450",
    "sg:province":"Barcelona",
    "wof:name":"Bruc Jardi S.l.",
    "wof:placetype":"venue"
},
  "geometry": {"coordinates":[2.3952701092,41.6382713318],"type":"Point"}
}