{
  "type": "Feature",
  "properties": {
    "addr:full":"Prol. Av. Catalunya, 19 Amposta Tarragona 43870",
    "addr:housenumber":"19",
    "addr:postcode":"43870",
    "addr:street":"Prol. Av. Catalunya",
    "iso:country":"ES",
    "sg:address":"Prol. Av. Catalunya, 19",
    "sg:city":"Amposta",
    "sg:orig_category":"Restaurantes",
    "sg:phone":"+34 977 70 56 26",
    "sg:postcode":"43870",
    "sg:province":"Tarragona",
    "wof:name":"Asensio Caballe Francisca",
    "wof:placetype":"venue"
},
  "geometry": {"coordinates":[0.5735542774,40.7095794678],"type":"Point"}
}