{
  "type": "Feature",
  "properties": {
    "iso:country":"ES",
    "sg:address":"Ctra Nacional Ii, Km. 0727,0",
    "sg:city":"Sarria Ter",
    "sg:orig_category":"Transporte En General",
    "sg:phone":"+34 972 17 27 27",
    "sg:postcode":"17840",
    "sg:province":"Girona",
    "wof:name":"Fullets I Fulletons S.l.",
    "wof:placetype":"venue"
},
  "geometry": {"coordinates":[2.8208498955,42.0173606873],"type":"Point"}
}