{
  "type": "Feature",
  "properties": {
    "addr:full":"Carrer de Maria Cubi, 7 Barcelona Barcelona 08006",
    "addr:housenumber":"7",
    "addr:postcode":"08006",
    "addr:street":"Carrer De Maria Cubi",
    "iso:country":"ES",
    "sg:address":"Carrer de Maria Cubi, 7",
    "sg:city":"Barcelona",
    "sg:orig_category":"Productos Qu\u00cdmicos (fabricaci\u00d3n, Al Por Mayor)",
    "sg:phone":"+34 932 37 18 94",
    "sg:postcode":"08006",
    "sg:province":"Barcelona",
    "wof:name":"Industrias Augusta S. L.",
    "wof:placetype":"venue"
},
  "geometry": {"coordinates":[2.1517219543,41.3993225098],"type":"Point"}
}