{
  "type": "Feature",
  "properties": {
    "iso:country":"ES",
    "sg:address":"Calle de San Jose, 21",
    "sg:city":"San Vicente Del Raspeig-sant Vicent Del Raspeig",
    "sg:orig_category":"Bazares, Art\u00cdculos De Limpieza Y De Cocina (al Por Menor)",
    "sg:phone":"+34 965 66 11 84",
    "sg:postcode":"03690",
    "sg:province":"Alicante",
    "wof:name":"Marin Bueno Ramon",
    "wof:placetype":"venue"
},
  "geometry": {"coordinates":[-0.5240951777,38.3964996338],"type":"Point"}
}