{
  "type": "Feature",
  "properties": {
    "iso:country":"ES",
    "sg:address":"Carrer de Francesc Vidal Sur, 72",
    "sg:city":"Sant Agusti",
    "sg:orig_category":"Asilos De Ancianos. Centros Privados",
    "sg:phone":"+34 971 40 55 13",
    "sg:postcode":"07015",
    "sg:province":"Islas Baleares",
    "wof:name":"Sodexho Espa\u00f1a S.a.",
    "wof:placetype":"venue"
},
  "geometry": {"coordinates":[2.606345892,39.5533103943],"type":"Point"}
}