{
  "type": "Feature",
  "properties": {
    "addr:full":"Rua Nova, 2 Veiga Ourense 32360",
    "addr:housenumber":"2",
    "addr:postcode":"32360",
    "addr:street":"Rua Nova",
    "iso:country":"ES",
    "sg:address":"Rua Nova, 2",
    "sg:city":"Veiga",
    "sg:orig_category":"Confecci\u00d3n (fabricaci\u00d3n, Al Por Mayor)",
    "sg:phone":"+34 988 35 00 18",
    "sg:postcode":"32360",
    "sg:province":"Ourense",
    "wof:name":"Fernandez Feliz Manuela",
    "wof:placetype":"venue"
},
  "geometry": {"coordinates":[-7.0262551308,42.2513656616],"type":"Point"}
}