{
  "type": "Feature",
  "properties": {
    "addr:full":"Calle de Harina (de La), 14 Fuenlabrada Madrid 28944",
    "addr:housenumber":"14",
    "addr:postcode":"28944",
    "addr:street":"Calle De Harina De La",
    "iso:country":"ES",
    "sg:address":"Calle de Harina (de La), 14",
    "sg:city":"Fuenlabrada",
    "sg:orig_category":"Institutos De Belleza",
    "sg:phone":"+34 916 06 05 70",
    "sg:postcode":"28944",
    "sg:province":"Madrid",
    "wof:name":"Eduardo Mu\u00f1oz Aguilera S.l.",
    "wof:placetype":"venue"
},
  "geometry": {"coordinates":[-3.7909169197,40.2832756042],"type":"Point"}
}