{
  "type": "Feature",
  "properties": {
    "addr:full":"Calle de Guzman El Bueno, 28 Madrid Madrid 28015",
    "addr:housenumber":"28",
    "addr:postcode":"madrid;28015",
    "addr:street":"Calle De Guzman El Bueno",
    "iso:country":"ES",
    "sg:address":"Calle de Guzman El Bueno, 28",
    "sg:city":"Madrid",
    "sg:orig_category":"Productos Alimentarios",
    "sg:phone":"+34 915 43 43 77",
    "sg:postcode":"28015",
    "sg:province":"Madrid",
    "sg:website":"www.naturasi.es",
    "wof:name":"Naturasite S.l.u.",
    "wof:placetype":"venue"
},
  "geometry": {"coordinates":[-3.7131159306,40.4335098267],"type":"Point"}
}