{
  "type": "Feature",
  "properties": {
    "addr:full":"Carrer de La Rambla, 75 Barcelona Barcelona 08002",
    "addr:housenumber":"75",
    "addr:postcode":"08002",
    "addr:street":"Carrer De La Rambla",
    "iso:country":"ES",
    "sg:address":"Carrer de La Rambla, 75",
    "sg:city":"Barcelona",
    "sg:orig_category":"Pe\u00d1as Y Asociaciones Varias",
    "sg:phone":"+34 933 01 80 15",
    "sg:postcode":"08002",
    "sg:province":"Barcelona",
    "wof:name":"Plataforma Unitaria De Residencias De La Tercera Edad",
    "wof:placetype":"venue"
},
  "geometry": {"coordinates":[2.172921896,41.381275177],"type":"Point"}
}