{
  "type": "Feature",
  "properties": {
    "addr:full":"Monjas, S/n Oropesa Toledo 45560",
    "addr:housenumber":"s / n",
    "addr:postcode":"45560",
    "addr:street":"Monjas",
    "iso:country":"ES",
    "sg:address":"Monjas, S/n",
    "sg:city":"Oropesa",
    "sg:orig_category":"Cl\u00cdnicas Dentales",
    "sg:phone":"+34 925 43 00 12",
    "sg:postcode":"45560",
    "sg:province":"Toledo",
    "wof:name":"Dental Oropesa 2004 S.l.",
    "wof:placetype":"venue"
},
  "geometry": {"coordinates":[-5.1757278442,39.9182548523],"type":"Point"}
}