{
  "type": "Feature",
  "properties": {
    "addr:full":"Calle de Doctor Aquilino Hurle, 30 Gijon Asturias 33203",
    "addr:housenumber":"30",
    "addr:postcode":"33203",
    "addr:street":"Calle De Doctor Aquilino Hurle",
    "iso:country":"ES",
    "sg:address":"Calle de Doctor Aquilino Hurle, 30",
    "sg:city":"Gijon",
    "sg:orig_category":"T\u00c9s (al Por Menor)",
    "sg:phone":"+34 985 36 49 12",
    "sg:postcode":"33203",
    "sg:province":"Asturias",
    "wof:name":"Cafe De La Arena S. L.",
    "wof:placetype":"venue"
},
  "geometry": {"coordinates":[-5.6467089653,43.5400810242],"type":"Point"}
}