{
  "type": "Feature",
  "properties": {
    "addr:full":"Calle de San Luciano, 5 Madrid Madrid 28041",
    "addr:housenumber":"5",
    "addr:postcode":"28041",
    "addr:street":"Calle De San Luciano",
    "iso:country":"ES",
    "sg:address":"Calle de San Luciano, 5",
    "sg:city":"Madrid",
    "sg:orig_category":"Cl\u00cdnicas Dentales",
    "sg:phone":"+34 913 17 04 81",
    "sg:postcode":"28041",
    "sg:province":"Madrid",
    "wof:name":"Sanaden S.l.",
    "wof:placetype":"venue"
},
  "geometry": {"coordinates":[-3.6991429329,40.3633384705],"type":"Point"}
}