{
  "type": "Feature",
  "properties": {
    "addr:full":"Calle de Alberto Lista, 31 San Jose Rinconada Sevilla 41300",
    "addr:housenumber":"31",
    "addr:postcode":"41300",
    "addr:street":"Calle De Alberto Lista",
    "iso:country":"ES",
    "sg:address":"Calle de Alberto Lista, 31",
    "sg:city":"San Jose Rinconada",
    "sg:orig_category":"\u00d3ptica: Instrumentos (fabricaci\u00d3n)",
    "sg:phone":"+34 955 79 20 50",
    "sg:postcode":"41300",
    "sg:province":"Sevilla",
    "wof:name":"Urraca Velasco Alberto",
    "wof:placetype":"venue"
},
  "geometry": {"coordinates":[-5.9507889748,37.4823112488],"type":"Point"}
}