{
  "type": "Feature",
  "properties": {
    "iso:country":"ES",
    "sg:address":"Carr Hernan Cortes, S/n",
    "sg:city":"Burjassot",
    "sg:orig_category":"Supermercados Y Hipermercados",
    "sg:phone":"+34 963 90 23 95",
    "sg:postcode":"46100",
    "sg:province":"Valencia",
    "sg:website":"www.mercadona.es",
    "wof:name":"Mercadona S.a.",
    "wof:placetype":"venue"
},
  "geometry": {"coordinates":[-0.4173940122,39.5121192932],"type":"Point"}
}