{
  "type": "Feature",
  "properties": {
    "addr:full":"Calle de Bustamante De La Camara, 1 Alcala Henares Madrid 28801",
    "addr:housenumber":"1",
    "addr:postcode":"28801",
    "addr:street":"Calle De Bustamante De La Camara",
    "iso:country":"ES",
    "sg:address":"Calle de Bustamante De La Camara, 1",
    "sg:city":"Alcala Henares",
    "sg:orig_category":"Caf\u00c9s, Bares, Cervecer\u00cdas",
    "sg:phone":"+34 918 80 76 41",
    "sg:postcode":"28801",
    "sg:province":"Madrid",
    "wof:name":"Rodriguez Castillo Jose Rodriguez",
    "wof:placetype":"venue"
},
  "geometry": {"coordinates":[-3.3639011383,40.4830207825],"type":"Point"}
}