{
  "type": "Feature",
  "properties": {
    "iso:country":"ES",
    "sg:address":"Carr Moncada, 2",
    "sg:city":"Xativa",
    "sg:orig_category":"Complementos De Vestir (al Por Menor)",
    "sg:phone":"+34 962 28 13 96",
    "sg:postcode":"46800",
    "sg:province":"Valencia",
    "wof:name":"Galerias Martin S.a.",
    "wof:placetype":"venue"
},
  "geometry": {"coordinates":[-0.5200830102,38.9934272766],"type":"Point"}
}