{
  "type": "Feature",
  "properties": {
    "addr:full":"Calle de Brazal De La Almontilla, 23 Cuarte Huerva Zaragoza 50410",
    "addr:housenumber":"23",
    "addr:postcode":"50410",
    "addr:street":"Calle De Brazal De La Almontilla",
    "iso:country":"ES",
    "sg:address":"Calle de Brazal De La Almontilla, 23",
    "sg:city":"Cuarte Huerva",
    "sg:orig_category":"Fabricaci\u00d3n, Instalaci\u00d3n Y Reparaci\u00d3n De Bombas",
    "sg:phone":"+34 976 75 12 68",
    "sg:postcode":"50410",
    "sg:province":"Zaragoza",
    "wof:name":"Remagua S. L.",
    "wof:placetype":"venue"
},
  "geometry": {"coordinates":[-0.8765661716,41.6563491821],"type":"Point"}
}