{
  "type": "Feature",
  "properties": {
    "addr:full":"Cami Muntanya, S/n Pol Indu Marratxi Islas Baleares 07141",
    "addr:housenumber":"s / n",
    "addr:postcode":"07141",
    "addr:street":"Muntanya;Indu;Islas",
    "iso:country":"ES",
    "sg:address":"Cami Muntanya, S/n",
    "sg:city":"Pol Indu Marratxi",
    "sg:orig_category":"Parques De Atracciones Y Centros De Esparcimiento",
    "sg:phone":"+34 971 22 96 25",
    "sg:postcode":"07141",
    "sg:province":"Islas Baleares",
    "wof:name":"Baehren  Paul Daniel",
    "wof:placetype":"venue"
},
  "geometry": {"coordinates":[2.7521929741,39.6421279907],"type":"Point"}
}