{
  "type": "Feature",
  "properties": {
    "addr:full":"Av Josep Anselm Clave, 136 Prat Llobregat Barcelona 08820",
    "addr:housenumber":"136",
    "addr:postcode":"08820",
    "addr:street":"Av Josep Anselm Clave;Llobregat",
    "iso:country":"ES",
    "sg:address":"Av Josep Anselm Clave, 136",
    "sg:city":"Prat Llobregat",
    "sg:orig_category":"Delegados, Agentes De Tr\u00c1nsito, Auxiliares De Transporte Internacional",
    "sg:phone":"+34 934 78 23 64",
    "sg:postcode":"08820",
    "sg:province":"Barcelona",
    "wof:name":"Man Vehiculos Industriales (espa\u00d1a",
    "wof:placetype":"venue"
},
  "geometry": {"coordinates":[2.1013801098,41.3343811035],"type":"Point"}
}