{
  "type": "Feature",
  "properties": {
    "addr:full":"Calle de Colina, 25 Madrid Madrid 28008",
    "addr:housenumber":"25",
    "addr:postcode":"madrid;28008",
    "addr:street":"Calle De Colina",
    "iso:country":"ES",
    "sg:address":"Calle de Colina, 25",
    "sg:city":"Madrid",
    "sg:orig_category":"Transportes Por V\u00cdas Navegables",
    "sg:phone":"+34 915 59 72 35",
    "sg:postcode":"28008",
    "sg:province":"Madrid",
    "wof:name":"Transportes Segovia E Hijos S.a.",
    "wof:placetype":"venue"
},
  "geometry": {"coordinates":[-3.7352519035,40.4289207458],"type":"Point"}
}