{
  "type": "Feature",
  "properties": {
    "iso:country":"ES",
    "sg:address":"Calle de Se\u00d1ora Sergia, 24",
    "sg:city":"Torrelodones",
    "sg:orig_category":"Asesor\u00cda Fiscal Y Jur\u00cddica",
    "sg:phone":"+34 918 59 12 85",
    "sg:postcode":"28250",
    "sg:province":"Madrid",
    "wof:name":"J.j.calven Gestion S.l.",
    "wof:placetype":"venue"
},
  "geometry": {"coordinates":[-3.9265880585,40.5790405273],"type":"Point"}
}