{
  "type": "Feature",
  "properties": {
    "addr:full":"Pl Mayor, S/n Wamba Valladolid 47190",
    "addr:housenumber":"s",
    "addr:postcode":"47190",
    "addr:street":"Pl Mayor;/ N",
    "iso:country":"ES",
    "sg:address":"Pl Mayor, S/n",
    "sg:city":"Wamba",
    "sg:orig_category":"Centros De Educaci\u00d3n Especial",
    "sg:phone":"+34 983 56 33 96",
    "sg:postcode":"47190",
    "sg:province":"Valladolid",
    "wof:name":"Colegio Rural Agrupado Padre Hoyos",
    "wof:placetype":"venue"
},
  "geometry": {"coordinates":[-4.9172887802,41.6762657166],"type":"Point"}
}