{
  "type": "Feature",
  "properties": {
    "addr:full":"Calle de Alfonso Xii, 1 Mostoles Madrid 28934",
    "addr:housenumber":"1",
    "addr:postcode":"28934",
    "addr:street":"Calle De Alfonso Xii",
    "iso:country":"ES",
    "sg:address":"Calle de Alfonso Xii, 1",
    "sg:city":"Mostoles",
    "sg:orig_category":"Ense\u00d1anza: Idiomas",
    "sg:phone":"+34 916 13 48 78",
    "sg:postcode":"28934",
    "sg:province":"Madrid",
    "wof:name":"Romero Capmany Maria Angeles",
    "wof:placetype":"venue"
},
  "geometry": {"coordinates":[-3.8759133816,40.318775177],"type":"Point"}
}