{
  "type": "Feature",
  "properties": {
    "iso:country":"ES",
    "sg:address":"Avda Fernando Conde, 123",
    "sg:city":"Estrada",
    "sg:orig_category":"Agentes, Concesionarios Y Sucursales De Veh\u00cdculos",
    "sg:phone":"+34 986 59 00 59",
    "sg:postcode":"36680",
    "sg:province":"Pontevedra",
    "wof:name":"Automoviles Gestoso S.l.",
    "wof:placetype":"venue"
},
  "geometry": {"coordinates":[-8.4813985825,42.6901435852],"type":"Point"}
}