{
  "type": "Feature",
  "properties": {
    "addr:full":"Ctra. Acces. Los Cristianos, S/n Los Cristianos Santa Cruz De Tenerife 38650",
    "addr:housenumber":"s / n",
    "addr:postcode":"38650",
    "addr:street":"Ctra. Acces. Los Cristianos",
    "iso:country":"ES",
    "sg:address":"Ctra. Acces. Los Cristianos, S/n",
    "sg:city":"Los Cristianos",
    "sg:orig_category":"Agencias De Viajes",
    "sg:phone":"+34 922 79 08 65",
    "sg:postcode":"38650",
    "sg:province":"Santa Cruz De Tenerife",
    "wof:name":"Mytravel Canarias Incoming Ser",
    "wof:placetype":"venue"
},
  "geometry": {"coordinates":[-16.7136135101,28.0558757782],"type":"Point"}
}