{
  "type": "Feature",
  "properties": {
    "iso:country":"ES",
    "sg:address":"Carrer de Llull, 189",
    "sg:city":"Barcelona",
    "sg:orig_category":"Loter\u00cda Y T\u00d3mbola",
    "sg:phone":"+34 934 85 21 00",
    "sg:postcode":"08005",
    "sg:province":"Barcelona",
    "wof:name":"Alvarez-builla Montero Juan Ramon",
    "wof:placetype":"venue"
},
  "geometry": {"coordinates":[2.2024044991,41.4012031555],"type":"Point"}
}