{
  "type": "Feature",
  "properties": {
    "addr:full":"Pase Mostoles (de), 16 Parque Coimbra Madrid 28935",
    "addr:postcode":"28935",
    "iso:country":"ES",
    "sg:address":"Pase Mostoles (de), 16",
    "sg:city":"Parque Coimbra",
    "sg:orig_category":"Metalurgia",
    "sg:phone":"+34 916 45 64 57",
    "sg:postcode":"28935",
    "sg:province":"Madrid",
    "wof:name":"Fuente Margalef Carmen",
    "wof:placetype":"venue"
},
  "geometry": {"coordinates":[-3.9207830429,40.3068466187],"type":"Point"}
}