{
  "type": "Feature",
  "properties": {
    "iso:country":"ES",
    "sg:address":"Avda Europa, 1",
    "sg:city":"Toledo",
    "sg:orig_category":"Asesor\u00cda Sobre Comunicaci\u00d3n De Empresas",
    "sg:phone":"+34 925 24 09 42",
    "sg:postcode":"45003",
    "sg:province":"Toledo",
    "wof:name":"Alvarez Pelayo Luis",
    "wof:placetype":"venue"
},
  "geometry": {"coordinates":[-4.028075695,39.871925354],"type":"Point"}
}