{
  "type": "Feature",
  "properties": {
    "iso:country":"ES",
    "sg:address":"Port Torredembarra, S/n",
    "sg:city":"Torredembarra",
    "sg:orig_category":"Deportes N\u00c1uticos, Acu\u00c1ticos Y Subacu\u00c1ticos: Art\u00cdculos Y Equipo (al Por Menor)",
    "sg:phone":"+34 977 64 28 71",
    "sg:postcode":"43830",
    "sg:province":"Tarragona",
    "wof:name":"Sevil Comas Wifredo",
    "wof:placetype":"venue"
},
  "geometry": {"coordinates":[1.395424962,41.1436691284],"type":"Point"}
}