{
  "type": "Feature",
  "properties": {
    "addr:full":"Calle de Moises De Leon, S/n Le\u00f3n Le\u00f3n 24006",
    "addr:postcode":"24006",
    "addr:street":"Calle De Moises De Leon S / N Leo\u0301N Leo\u0301N",
    "iso:country":"ES",
    "sg:address":"Calle de Moises De Leon, S/n",
    "sg:city":"Le\u00f3n",
    "sg:orig_category":"Fabricaci\u00d3n Y Venta De Volquetes Y Remolques",
    "sg:phone":"+34 987 25 79 13",
    "sg:postcode":"24006",
    "sg:province":"Le\u00f3n",
    "wof:name":"Montenegro Iberica S.a.",
    "wof:placetype":"venue"
},
  "geometry": {"coordinates":[-5.5604667664,42.5924835205],"type":"Point"}
}