{
  "type": "Feature",
  "properties": {
    "addr:full":"Prza De Abastos, S/n Estrada Pontevedra 36680",
    "addr:housenumber":"s / n",
    "addr:postcode":"36680",
    "addr:street":"Estrada Pontevedra",
    "iso:country":"ES",
    "sg:address":"Prza De Abastos, S/n",
    "sg:city":"Estrada",
    "sg:orig_category":"Carnicer\u00cdas, Carnicer\u00cdas",
    "sg:phone":"+34 986 57 30 07",
    "sg:postcode":"36680",
    "sg:province":"Pontevedra",
    "wof:name":"Vahamonde Sanluis Ramiro",
    "wof:placetype":"venue"
},
  "geometry": {"coordinates":[-8.4910736084,42.6887664795],"type":"Point"}
}