{
  "type": "Feature",
  "properties": {
    "iso:country":"ES",
    "sg:address":"Av Sant Francesc, 21",
    "sg:city":"Girona",
    "sg:orig_category":"Mutuas De Seguros",
    "sg:phone":"+34 972 20 38 69",
    "sg:postcode":"17001",
    "sg:province":"Girona",
    "wof:name":"Mutualidad General De Prevision Del Hogar",
    "wof:placetype":"venue"
},
  "geometry": {"coordinates":[2.8212740421,41.9823036194],"type":"Point"}
}