{
  "type": "Feature",
  "properties": {
    "addr:full":"Calle de Segundo Izpizua, 29 Donostia-san Sebastian Guip\u00f9zcoa 20001",
    "addr:housenumber":"29",
    "addr:postcode":"20001",
    "addr:street":"Calle De Segundo Izpizua",
    "iso:country":"ES",
    "sg:address":"Calle de Segundo Izpizua, 29",
    "sg:city":"Donostia-san Sebastian",
    "sg:orig_category":"Electricidad Veh\u00cdculo",
    "sg:phone":"+34 943 28 08 12",
    "sg:postcode":"20001",
    "sg:province":"Guip\u00f9zcoa",
    "wof:name":"San Jose Arce Juan Bautista",
    "wof:placetype":"venue"
},
  "geometry": {"coordinates":[-1.9699920416,43.3241043091],"type":"Point"}
}