{
  "type": "Feature",
  "properties": {
    "iso:country":"ES",
    "sg:address":"Calle de Progreso (del), 23",
    "sg:city":"Chiclana De La Frontera",
    "sg:orig_category":"Carnicer\u00cdas, Carnicer\u00cdas",
    "sg:phone":"+34 956 53 81 56",
    "sg:postcode":"11130",
    "sg:province":"C\u00e1diz",
    "wof:name":"Fernandez Tosso Eduardo",
    "wof:placetype":"venue"
},
  "geometry": {"coordinates":[-6.1312160492,36.4023704529],"type":"Point"}
}