{
  "type": "Feature",
  "properties": {
    "addr:full":"Pase Santa Fe, 7 Huelva Huelva 21003",
    "addr:housenumber":"7",
    "addr:postcode":"21003",
    "addr:street":"Santa Fe",
    "iso:country":"ES",
    "sg:address":"Pase Santa Fe, 7",
    "sg:city":"Huelva",
    "sg:orig_category":"Ense\u00d1anza: Idiomas",
    "sg:phone":"+34 959 24 30 23",
    "sg:postcode":"21003",
    "sg:province":"Huelva",
    "wof:name":"Stevenson Gonzalez Corinne",
    "wof:placetype":"venue"
},
  "geometry": {"coordinates":[-6.9495940208,37.256313324],"type":"Point"}
}