{
  "type": "Feature",
  "properties": {
    "iso:country":"ES",
    "sg:address":"Avda Cid Campeador, 36",
    "sg:city":"Burgos",
    "sg:orig_category":"Panader\u00cdas, Panader\u00cdas",
    "sg:phone":"+34 947 22 90 90",
    "sg:postcode":"09005",
    "sg:province":"Burgos",
    "wof:name":"Confiterias Burgos S.l",
    "wof:placetype":"venue"
},
  "geometry": {"coordinates":[-3.6974010468,42.3464126587],"type":"Point"}
}