{
  "type": "Feature",
  "properties": {
    "iso:country":"ES",
    "sg:address":"Rua Zamora, 1",
    "sg:city":"Vigo",
    "sg:orig_category":"Bancos",
    "sg:phone":"+34 986 42 16 33",
    "sg:postcode":"36203",
    "sg:province":"Pontevedra",
    "wof:name":"Banco Caixa Geral S.a.",
    "wof:placetype":"venue"
},
  "geometry": {"coordinates":[-8.7204637527,42.2286338806],"type":"Point"}
}