{
  "type": "Feature",
  "properties": {
    "addr:full":"Calle de Antonio Lopez, 20 Cadiz C\u00e1diz 11004",
    "addr:housenumber":"20",
    "addr:postcode":"11004",
    "addr:street":"Calle De Antonio Lopez",
    "iso:country":"ES",
    "sg:address":"Calle de Antonio Lopez, 20",
    "sg:city":"Cadiz",
    "sg:orig_category":"Agencias Y Agentes Comerciales, Representantes",
    "sg:phone":"+34 956 21 13 92",
    "sg:postcode":"11004",
    "sg:province":"C\u00e1diz",
    "wof:name":"Alcedo Garcia Agustin",
    "wof:placetype":"venue"
},
  "geometry": {"coordinates":[-6.294356823,36.5348510742],"type":"Point"}
}