{
  "type": "Feature",
  "properties": {
    "addr:full":"Avda Jarea (la), S/n Alagon Zaragoza 50630",
    "addr:postcode":"50630",
    "addr:street":"Avda Jarea La S / N Alagon",
    "iso:country":"ES",
    "sg:address":"Avda Jarea (la), S/n",
    "sg:city":"Alagon",
    "sg:orig_category":"Centros De Educaci\u00d3n Especial",
    "sg:phone":"+34 976 61 13 54",
    "sg:postcode":"50630",
    "sg:province":"Zaragoza",
    "wof:name":"Colegio Publico Aragon De Alagon",
    "wof:placetype":"venue"
},
  "geometry": {"coordinates":[-1.1267240047,41.768196106],"type":"Point"}
}