{
  "type": "Feature",
  "properties": {
    "iso:country":"ES",
    "sg:address":"Santa Ana, 6",
    "sg:city":"Marchena",
    "sg:orig_category":"Fotograf\u00cda Art\u00cdstica Y Retratos",
    "sg:phone":"+34 955 84 54 68",
    "sg:postcode":"41620",
    "sg:province":"Sevilla",
    "sg:website":"www.paquedigital.com",
    "wof:name":"Rey Paque Ismael",
    "wof:placetype":"venue"
},
  "geometry": {"coordinates":[-5.4173588753,37.3319358826],"type":"Point"}
}