{
  "type": "Feature",
  "properties": {
    "addr:full":"Dels Teixidors, 24 Inca Islas Baleares 07300",
    "addr:housenumber":"24",
    "addr:postcode":"07300",
    "addr:street":"Teixidors",
    "iso:country":"ES",
    "sg:address":"Dels Teixidors, 24",
    "sg:city":"Inca",
    "sg:orig_category":"Cajas Y Embalajes De Cart\u00d3n Y Papel",
    "sg:phone":"+34 971 50 42 73",
    "sg:postcode":"07300",
    "sg:province":"Islas Baleares",
    "wof:name":"Envases B.a.t. S.l.",
    "wof:placetype":"venue"
},
  "geometry": {"coordinates":[2.9037139416,39.7100715637],"type":"Point"}
}