{
  "type": "Feature",
  "properties": {
    "addr:full":"Tv Monaterio Urdax, 2 Iru\u00f1a Navarra 31011",
    "addr:housenumber":"2",
    "addr:postcode":"31011",
    "addr:street":"Urdax",
    "iso:country":"ES",
    "sg:address":"Tv Monaterio Urdax, 2",
    "sg:city":"Iru\u00f1a",
    "sg:orig_category":"Quincaller\u00cda (al Por Menor)",
    "sg:phone":"+34 948 26 04 12",
    "sg:postcode":"31011",
    "sg:province":"Navarra",
    "sg:website":"www.euskalferr.com",
    "wof:name":"Garate Uncetabarrenechea Marcelino",
    "wof:placetype":"venue"
},
  "geometry": {"coordinates":[-1.6578519344,42.8164863586],"type":"Point"}
}