{
  "type": "Feature",
  "properties": {
    "iso:country":"ES",
    "sg:address":"Carrer de Valldoreix, 23",
    "sg:city":"S. Cugat Valles",
    "sg:orig_category":"Venta, Instalaci\u00d3n De Calefacci\u00d3n",
    "sg:phone":"+34 936 75 67 85",
    "sg:postcode":"08172",
    "sg:province":"Barcelona",
    "sg:website":"www.cmsnet.net",
    "wof:name":"General Gas Y Climas S.l.",
    "wof:placetype":"venue"
},
  "geometry": {"coordinates":[2.0805170536,41.4701499939],"type":"Point"}
}