{
  "type": "Feature",
  "properties": {
    "addr:full":"Calle de Tiendas (las), 37 Molina Guadalajara 19300",
    "addr:housenumber":"37",
    "addr:postcode":"19300",
    "addr:street":"Calle De Tiendas Las",
    "iso:country":"ES",
    "sg:address":"Calle de Tiendas (las), 37",
    "sg:city":"Molina",
    "sg:orig_category":"Alimentaci\u00d3n General (al Por Menor)",
    "sg:phone":"+34 949 83 03 16",
    "sg:postcode":"19300",
    "sg:province":"Guadalajara",
    "wof:name":"Onsurbe Alvaro Yolanda",
    "wof:placetype":"venue"
},
  "geometry": {"coordinates":[-1.8871740103,40.8437767029],"type":"Point"}
}