{
  "type": "Feature",
  "properties": {
    "addr:full":"Calle de Guillem De Castro, 41 Valencia Valencia 46007",
    "addr:housenumber":"41",
    "addr:postcode":"46007",
    "addr:street":"Calle De Guillem De Castro",
    "iso:country":"ES",
    "sg:address":"Calle de Guillem De Castro, 41",
    "sg:city":"Valencia",
    "sg:orig_category":"M\u00c9dicos: Estomatolog\u00cda",
    "sg:phone":"+34 963 51 86 89",
    "sg:postcode":"46007",
    "sg:province":"Valencia",
    "wof:name":"Clinica Martinez Canuto,integracion Odontologica S.l.",
    "wof:placetype":"venue"
},
  "geometry": {"coordinates":[-0.3805080056,39.4682617188],"type":"Point"}
}