{
  "type": "Feature",
  "properties": {
    "addr:full":"Calle de Jamaica, 4 Alcala Real Ja\u00e9n 23680",
    "addr:housenumber":"4",
    "addr:postcode":"23680",
    "addr:street":"Calle De Jamaica;Jae\u0301N",
    "iso:country":"ES",
    "sg:address":"Calle de Jamaica, 4",
    "sg:city":"Alcala Real",
    "sg:orig_category":"Electricidad: Instaladores",
    "sg:phone":"+34 953 58 32 10",
    "sg:postcode":"23680",
    "sg:province":"Ja\u00e9n",
    "wof:name":"Montajes Electro Automaticos Elektro Well S.l.",
    "wof:placetype":"venue"
},
  "geometry": {"coordinates":[-3.9269170761,37.4551811218],"type":"Point"}
}