{
  "type": "Feature",
  "properties": {
    "addr:full":"Avda Constitucion (de La), 220 Poligono Industrial Monte Boyal Toledo 45950",
    "addr:housenumber":"220",
    "addr:postcode":"45950",
    "addr:street":"Avda Constitucion De La;Industrial",
    "iso:country":"ES",
    "sg:address":"Avda Constitucion (de La), 220",
    "sg:city":"Poligono Industrial Monte Boyal",
    "sg:orig_category":"Freidur\u00cdas: Equipos Y Suministros",
    "sg:phone":"+34 918 17 00 90",
    "sg:postcode":"45950",
    "sg:province":"Toledo",
    "wof:name":"Aperitivos La Golondrina S.l.",
    "wof:placetype":"venue"
},
  "geometry": {"coordinates":[-4.0244760513,39.8567771912],"type":"Point"}
}