{
  "type": "Feature",
  "properties": {
    "addr:full":"Carrer de Paris, 161 Barcelona Barcelona 08036",
    "addr:housenumber":"161",
    "addr:postcode":"08036",
    "addr:street":"Carrer De Paris",
    "iso:country":"ES",
    "sg:address":"Carrer de Paris, 161",
    "sg:city":"Barcelona",
    "sg:orig_category":"Peluquer\u00cdas, Peluquer\u00cda Mixta",
    "sg:phone":"+34 933 21 76 06",
    "sg:postcode":"08036",
    "sg:province":"Barcelona",
    "wof:name":"Dos Mil Vilga S.l.",
    "wof:placetype":"venue"
},
  "geometry": {"coordinates":[2.1510009766,41.3920860291],"type":"Point"}
}