{
  "type": "Feature",
  "properties": {
    "iso:country":"ES",
    "sg:address":"Calle de Cifuentes, 42",
    "sg:city":"Guadalajara",
    "sg:orig_category":"Molduras, Junquillos, Listones Y Molduras Perforadas",
    "sg:phone":"+34 949 22 84 48",
    "sg:postcode":"19003",
    "sg:province":"Guadalajara",
    "wof:name":"Yague Rodriguez S.l.",
    "wof:placetype":"venue"
},
  "geometry": {"coordinates":[-3.1739017963,40.6321029663],"type":"Point"}
}