{
  "type": "Feature",
  "properties": {
    "addr:full":"Carrer de Montserrat, 24 Esparreguera Barcelona 08292",
    "addr:housenumber":"24",
    "addr:postcode":"08292",
    "addr:street":"Carrer De Montserrat",
    "iso:country":"ES",
    "sg:address":"Carrer de Montserrat, 24",
    "sg:city":"Esparreguera",
    "sg:orig_category":"Bricolaje, Herramientas (al Por Menor)",
    "sg:phone":"+34 937 77 23 93",
    "sg:postcode":"08292",
    "sg:province":"Barcelona",
    "wof:name":"Castillo Bel Maria Carme",
    "wof:placetype":"venue"
},
  "geometry": {"coordinates":[1.8670150042,41.5418968201],"type":"Point"}
}