{
  "type": "Feature",
  "properties": {
    "addr:full":"Calle de Canalejas, 4 Valencia Valencia 46024",
    "addr:housenumber":"4",
    "addr:postcode":"46024",
    "addr:street":"Calle De Canalejas",
    "iso:country":"ES",
    "sg:address":"Calle de Canalejas, 4",
    "sg:city":"Valencia",
    "sg:orig_category":"Delegados, Agentes De Tr\u00c1nsito, Auxiliares De Transporte Internacional",
    "sg:phone":"+34 963 31 16 03",
    "sg:postcode":"46024",
    "sg:province":"Valencia",
    "wof:name":"Dura Moraton Maria Carmen",
    "wof:placetype":"venue"
},
  "geometry": {"coordinates":[-0.3387247026,39.4593315125],"type":"Point"}
}