{
  "type": "Feature",
  "properties": {
    "addr:full":"Calle de Antonio Suarez, 6 Valencia Valencia 46021",
    "addr:housenumber":"6",
    "addr:postcode":"46021",
    "addr:street":"Calle De Antonio Suarez",
    "iso:country":"ES",
    "sg:address":"Calle de Antonio Suarez, 6",
    "sg:city":"Valencia",
    "sg:orig_category":"M\u00c9dicos: Endocrinolog\u00cda Y Metabolismo",
    "sg:phone":"+34 963 37 21 28",
    "sg:postcode":"46021",
    "sg:province":"Valencia",
    "wof:name":"Mu\u00f1oz Ferrer Maria Luisa",
    "wof:placetype":"venue"
},
  "geometry": {"coordinates":[-0.3576884866,39.4677505493],"type":"Point"}
}