{
  "type": "Feature",
  "properties": {
    "addr:full":"Calle de San Adrian De Sasabe, 12 Zaragoza Zaragoza 50002",
    "addr:housenumber":"12",
    "addr:postcode":"50002",
    "addr:street":"Calle De San Adrian De Sasabe",
    "iso:country":"ES",
    "sg:address":"Calle de San Adrian De Sasabe, 12",
    "sg:city":"Zaragoza",
    "sg:orig_category":"Electricidad: Instaladores",
    "sg:phone":"+34 976 41 04 84",
    "sg:postcode":"50002",
    "sg:province":"Zaragoza",
    "wof:name":"Montero Garcia Antonio",
    "wof:placetype":"venue"
},
  "geometry": {"coordinates":[-0.8596889973,41.6420288086],"type":"Point"}
}