{
  "type": "Feature",
  "properties": {
    "addr:full":"Carr Independencia, 154 Badalona Barcelona 08915",
    "addr:housenumber":"154",
    "addr:postcode":"08915",
    "addr:street":"Carr Independencia",
    "iso:country":"ES",
    "sg:address":"Carr Independencia, 154",
    "sg:city":"Badalona",
    "sg:orig_category":"Zapatos (al Por Menor)",
    "sg:phone":"+34 933 88 92 09",
    "sg:postcode":"08915",
    "sg:province":"Barcelona",
    "wof:name":"Calzados Botier S.c.p.",
    "wof:placetype":"venue"
},
  "geometry": {"coordinates":[2.2420699596,41.4590530396],"type":"Point"}
}