{
  "type": "Feature",
  "properties": {
    "iso:country":"ES",
    "sg:address":"Carrer de Ebre (de L') (torreforta), 16",
    "sg:city":"Torreforta",
    "sg:orig_category":"Institutos De Belleza",
    "sg:phone":"+34 977 54 15 13",
    "sg:postcode":"43006",
    "sg:province":"Tarragona",
    "wof:name":"Rojano Gonzalez Maria Jose",
    "wof:placetype":"venue"
},
  "geometry": {"coordinates":[1.2186139822,41.1205673218],"type":"Point"}
}