{
  "type": "Feature",
  "properties": {
    "addr:full":"Carrer de Bruc, 206 Sabadell Barcelona 08203",
    "addr:housenumber":"206",
    "addr:postcode":"08203",
    "addr:street":"Carrer De Bruc",
    "iso:country":"ES",
    "sg:address":"Carrer de Bruc, 206",
    "sg:city":"Sabadell",
    "sg:orig_category":"Rectificaci\u00d3n, Mecanizado, Fresado",
    "sg:phone":"+34 937 10 11 42",
    "sg:postcode":"08203",
    "sg:province":"Barcelona",
    "wof:name":"Talleres Tecme S.l.",
    "wof:placetype":"venue"
},
  "geometry": {"coordinates":[2.1116600037,41.5313415527],"type":"Point"}
}