{
  "type": "Feature",
  "properties": {
    "iso:country":"ES",
    "sg:address":"Calle de Aperribai, 3",
    "sg:city":"Agirre-aperribai",
    "sg:orig_category":"Agentes, Concesionarios Y Sucursales De Veh\u00cdculos",
    "sg:phone":"+34 944 40 43 11",
    "sg:postcode":"48960",
    "sg:province":"Vizcaya",
    "wof:name":"Cross-road S.l.",
    "wof:placetype":"venue"
},
  "geometry": {"coordinates":[-2.8626608849,43.2336578369],"type":"Point"}
}