{
  "type": "Feature",
  "properties": {
    "addr:full":"Calle de Vendeja, 17 Malaga M\u00e1laga 29001",
    "addr:housenumber":"17",
    "addr:postcode":"29001",
    "addr:street":"Calle De Vendeja;Ma\u0301Laga",
    "iso:country":"ES",
    "sg:address":"Calle de Vendeja, 17",
    "sg:city":"Malaga",
    "sg:orig_category":"Asociaciones, Organismos Culturales Y Socioeducativos",
    "sg:phone":"+34 952 22 14 46",
    "sg:postcode":"29001",
    "sg:province":"M\u00e1laga",
    "wof:name":"Hermandad De Veteranos De Las Fuerzas Ar",
    "wof:placetype":"venue"
},
  "geometry": {"coordinates":[-4.4236741066,36.7161445618],"type":"Point"}
}