{
  "type": "Feature",
  "properties": {
    "iso:country":"ES",
    "sg:address":"Carr Moli Del Perxe, 2",
    "sg:city":"Castellnou Seana",
    "sg:orig_category":"Maquinaria Neum\u00c1tica",
    "sg:phone":"+34 973 32 10 69",
    "sg:postcode":"25265",
    "sg:province":"Lleida",
    "wof:name":"Inpla Tjf S.l.",
    "wof:placetype":"venue"
},
  "geometry": {"coordinates":[0.9706739783,41.6483421326],"type":"Point"}
}