{
  "type": "Feature",
  "properties": {
    "iso:country":"ES",
    "sg:address":"Calle de Virgen Del Val, 25",
    "sg:city":"Madrid",
    "sg:orig_category":"Mec\u00c1nico Del Autom\u00d3vil",
    "sg:phone":"+34 913 26 17 15",
    "sg:postcode":"28027",
    "sg:province":"Madrid",
    "wof:name":"Caballero Torrico Norman Elisaldi",
    "wof:placetype":"venue"
},
  "geometry": {"coordinates":[-3.6519770622,40.4390525818],"type":"Point"}
}