{
  "type": "Feature",
  "properties": {
    "iso:country":"ES",
    "sg:address":"Calle de Santa Rita, 28",
    "sg:city":"Aviles",
    "sg:orig_category":"Ense\u00d1anza, Formaci\u00d3n Profesional: Aprendizaje",
    "sg:phone":"+34 985 51 65 51",
    "sg:postcode":"33403",
    "sg:province":"Asturias",
    "wof:name":"Ayuntamiento De Aviles",
    "wof:placetype":"venue"
},
  "geometry": {"coordinates":[-5.9064116478,43.5459899902],"type":"Point"}
}