{
  "type": "Feature",
  "properties": {
    "addr:full":"Carrer de Vendrell, 31 Manlleu Barcelona 08560",
    "addr:housenumber":"31",
    "addr:postcode":"08560",
    "addr:street":"Carrer De Vendrell",
    "iso:country":"ES",
    "sg:address":"Carrer de Vendrell, 31",
    "sg:city":"Manlleu",
    "sg:orig_category":"Librer\u00cdas",
    "sg:phone":"+34 938 51 02 56",
    "sg:postcode":"08560",
    "sg:province":"Barcelona",
    "wof:name":"Vallbona Danes Assumpta",
    "wof:placetype":"venue"
},
  "geometry": {"coordinates":[2.2807040215,41.9997634888],"type":"Point"}
}