{
  "type": "Feature",
  "properties": {
    "addr:full":"Calle de Bernabe Soriano, 18 Jaen Ja\u00e9n 23001",
    "addr:housenumber":"18;jae\u0301n",
    "addr:postcode":"23001",
    "addr:street":"Calle De Bernabe Soriano",
    "iso:country":"ES",
    "sg:address":"Calle de Bernabe Soriano, 18",
    "sg:city":"Jaen",
    "sg:orig_category":"M\u00c9dicos: Estomatolog\u00cda",
    "sg:phone":"+34 953 23 40 52",
    "sg:postcode":"23001",
    "sg:province":"Ja\u00e9n",
    "wof:name":"Vargas-machuca Gutierrez Juan",
    "wof:placetype":"venue"
},
  "geometry": {"coordinates":[-3.7882258892,37.7663726807],"type":"Point"}
}