{
  "type": "Feature",
  "properties": {
    "iso:country":"ES",
    "sg:address":"Carrer de Mallorca, 8",
    "sg:city":"Playa De Calafell",
    "sg:orig_category":"Transportes Por Carretera: Lotes Completos, Mercanc\u00cdas Diversas",
    "sg:phone":"+34 977 69 15 27",
    "sg:postcode":"43820",
    "sg:province":"Tarragona",
    "wof:name":"Baldris Ferrandiz Joaquim",
    "wof:placetype":"venue"
},
  "geometry": {"coordinates":[1.5708240271,41.18724823],"type":"Point"}
}