{
  "type": "Feature",
  "properties": {
    "iso:country":"ES",
    "sg:address":"Av. Sierra Gredos, 11",
    "sg:city":"Villanueva Ca\u00f1ada",
    "sg:orig_category":"Renovaci\u00d3n Inmobiliaria",
    "sg:phone":"+34 918 11 87 20",
    "sg:postcode":"28691",
    "sg:province":"Madrid",
    "wof:name":"Restauracion De Fincas Comunitarias S.l.",
    "wof:placetype":"venue"
},
  "geometry": {"coordinates":[-4.0039811134,40.4393196106],"type":"Point"}
}