{
  "type": "Feature",
  "properties": {
    "iso:country":"ES",
    "sg:address":"Pase Extremadura, 324",
    "sg:city":"Madrid",
    "sg:orig_category":"Inform\u00c1tica Equipo Y Programas (al Por Mayor)",
    "sg:phone":"+34 915 18 71 28",
    "sg:postcode":"28024",
    "sg:province":"Madrid",
    "sg:website":"www.perfetmedical.net",
    "wof:name":"Perfect Medical Tecnology S.l.",
    "wof:placetype":"venue"
},
  "geometry": {"coordinates":[-3.7887589931,40.3810882568],"type":"Point"}
}