{
  "type": "Feature",
  "properties": {
    "addr:full":"Avda Zaragoza, 70 Tudela Navarra 31500",
    "addr:housenumber":"70",
    "addr:postcode":"31500",
    "addr:street":"Avda Zaragoza",
    "iso:country":"ES",
    "sg:address":"Avda Zaragoza, 70",
    "sg:city":"Tudela",
    "sg:orig_category":"Muebles, Minoristas",
    "sg:phone":"+34 948 84 73 84",
    "sg:postcode":"31500",
    "sg:province":"Navarra",
    "wof:name":"Arco Mobiliario Y Decoracion S.l.",
    "wof:placetype":"venue"
},
  "geometry": {"coordinates":[-1.5976959467,42.0538787842],"type":"Point"}
}