{
  "type": "Feature",
  "properties": {
    "addr:full":"Cmno Txipio Bidea, S/n Txipio Vizcaya 48620",
    "addr:housenumber":"s / n",
    "addr:postcode":"48620",
    "addr:street":"Cmno Txipio Bidea",
    "iso:country":"ES",
    "sg:address":"Cmno Txipio Bidea, S/n",
    "sg:city":"Txipio",
    "sg:orig_category":"Ebanister\u00cda",
    "sg:phone":"+34 946 77 14 13",
    "sg:postcode":"48620",
    "sg:province":"Vizcaya",
    "wof:name":"Jose Ignacio Mezo Ibarra Y Otro Cdad",
    "wof:placetype":"venue"
},
  "geometry": {"coordinates":[-2.9458739758,43.4066467285],"type":"Point"}
}