{
  "type": "Feature",
  "properties": {
    "addr:full":"Calle de Tutor, 54 Madrid Madrid 28008",
    "addr:housenumber":"54",
    "addr:postcode":"madrid;28008",
    "addr:street":"Calle De Tutor",
    "iso:country":"ES",
    "sg:address":"Calle de Tutor, 54",
    "sg:city":"Madrid",
    "sg:orig_category":"Confecci\u00d3n De Ropa Interior",
    "sg:phone":"+34 915 44 00 11",
    "sg:postcode":"28008",
    "sg:province":"Madrid",
    "wof:name":"Arandilla Blanco Manuel",
    "wof:placetype":"venue"
},
  "geometry": {"coordinates":[-3.7166376114,40.4293136597],"type":"Point"}
}