{
  "type": "Feature",
  "properties": {
    "iso:country":"ES",
    "sg:address":"Pla\u00c7 Germans Maristes (dels), 3",
    "sg:city":"Lloret Mar",
    "sg:orig_category":"Loter\u00cda Y T\u00d3mbola",
    "sg:phone":"+34 972 36 79 15",
    "sg:postcode":"17310",
    "sg:province":"Girona",
    "wof:name":"Administracion De Loterias N\u00ba 1",
    "wof:placetype":"venue"
},
  "geometry": {"coordinates":[2.8236999512,41.9817962646],"type":"Point"}
}