{
  "type": "Feature",
  "properties": {
    "addr:full":"Plaz Maestro Jose Aucejo Sena, 4 Meliana Valencia 46133",
    "addr:postcode":"46133",
    "addr:street":"Plaz;Jose Aucejo",
    "iso:country":"ES",
    "sg:address":"Plaz Maestro Jose Aucejo Sena, 4",
    "sg:city":"Meliana",
    "sg:orig_category":"Agentes Generales De Seguros",
    "sg:phone":"+34 961 49 31 79",
    "sg:postcode":"46133",
    "sg:province":"Valencia",
    "wof:name":"Ferrer Balaguer Rafael",
    "wof:placetype":"venue"
},
  "geometry": {"coordinates":[-0.3457970023,39.5281105042],"type":"Point"}
}