{
  "type": "Feature",
  "properties": {
    "iso:country":"ES",
    "sg:address":"Esquirols, 18",
    "sg:city":"Maspons",
    "sg:orig_category":"Cester\u00cda (fabricaci\u00d3n)",
    "sg:phone":"+34 938 44 87 62",
    "sg:postcode":"08140",
    "sg:province":"Barcelona",
    "sg:website":"www.importsur.com",
    "wof:name":"Quintana Santallusia Blas",
    "wof:placetype":"venue"
},
  "geometry": {"coordinates":[2.2017900944,41.6332626343],"type":"Point"}
}