{
  "type": "Feature",
  "properties": {
    "addr:full":"Calle de Duques De Najera, 19 Logro\u00f1o La Rioja 26002",
    "addr:housenumber":"19",
    "addr:postcode":"26002",
    "addr:street":"Calle De Duques De Najera;Rioja",
    "iso:country":"ES",
    "sg:address":"Calle de Duques De Najera, 19",
    "sg:city":"Logro\u00f1o",
    "sg:orig_category":"Internados & Ense\u00d1anza Privada",
    "sg:phone":"+34 941 22 17 00",
    "sg:postcode":"26002",
    "sg:province":"La Rioja",
    "wof:name":"Colegio Y Escuela Profesional Sagrado Corazon",
    "wof:placetype":"venue"
},
  "geometry": {"coordinates":[-2.453275919,42.4588470459],"type":"Point"}
}