{
  "type": "Feature",
  "properties": {
    "addr:full":"Calle de Camarena, 304 Madrid Madrid 28047",
    "addr:housenumber":"304",
    "addr:postcode":"28047",
    "addr:street":"Calle De Camarena",
    "iso:country":"ES",
    "sg:address":"Calle de Camarena, 304",
    "sg:city":"Madrid",
    "sg:orig_category":"Cl\u00cdnicas M\u00c9dicas",
    "sg:phone":"+34 917 19 87 47",
    "sg:postcode":"28047",
    "sg:province":"Madrid",
    "wof:name":"Well Sanz Vanesa",
    "wof:placetype":"venue"
},
  "geometry": {"coordinates":[-3.7573490143,40.3863945007],"type":"Point"}
}