{
  "type": "Feature",
  "properties": {
    "iso:country":"ES",
    "sg:address":"Cmno Pillotegi De, 12",
    "sg:city":"Donostia-san Sebastian",
    "sg:orig_category":"Empresas De Vigilancia, Guardia Y Protecci\u00d3n",
    "sg:phone":"+34 943 22 37 35",
    "sg:postcode":"20018",
    "sg:province":"Guip\u00f9zcoa",
    "wof:name":"Proteccion Y Seguridad Tecnica S.a.",
    "wof:placetype":"venue"
},
  "geometry": {"coordinates":[-2.0029520988,43.2836837769],"type":"Point"}
}