{
  "type": "Feature",
  "properties": {
    "addr:full":"Avda Maestro Augusto Miguel, 7 Castellnovo Castell\u00f3n 12413",
    "addr:housenumber":"7",
    "addr:postcode":"12413",
    "addr:street":"Avda Maestro Augusto Miguel",
    "iso:country":"ES",
    "sg:address":"Avda Maestro Augusto Miguel, 7",
    "sg:city":"Castellnovo",
    "sg:orig_category":"Art\u00cdculos De Pl\u00c1stico",
    "sg:phone":"+34 964 13 75 10",
    "sg:postcode":"12413",
    "sg:province":"Castell\u00f3n",
    "wof:name":"Muley Sales Maria Jose",
    "wof:placetype":"venue"
},
  "geometry": {"coordinates":[-0.4101420045,39.8707008362],"type":"Point"}
}