{
  "type": "Feature",
  "properties": {
    "addr:full":"Plaz Virgen De La Antigua, 9 Guadalajara Guadalajara 19001",
    "addr:housenumber":"9",
    "addr:postcode":"19001",
    "addr:street":"Plaz Virgen De La Antigua",
    "iso:country":"ES",
    "sg:address":"Plaz Virgen De La Antigua, 9",
    "sg:city":"Guadalajara",
    "sg:orig_category":"Carnicer\u00cdas, Carnicer\u00cdas",
    "sg:phone":"+34 949 21 20 38",
    "sg:postcode":"19001",
    "sg:province":"Guadalajara",
    "wof:name":"Esteban Recuero Maria",
    "wof:placetype":"venue"
},
  "geometry": {"coordinates":[-3.1686680317,40.6324424744],"type":"Point"}
}