{
  "type": "Feature",
  "properties": {
    "addr:full":"Calle de Mu\u00d1oz Degrain, 6 Oviedo Asturias 33007",
    "addr:housenumber":"6",
    "addr:postcode":"33007",
    "addr:street":"Calle De Mun\u0303Oz Degrain",
    "iso:country":"ES",
    "sg:address":"Calle de Mu\u00d1oz Degrain, 6",
    "sg:city":"Oviedo",
    "sg:orig_category":"Expertos Contables, Revisores De Cuentas",
    "sg:phone":"+34 985 23 83 66",
    "sg:postcode":"33007",
    "sg:province":"Asturias",
    "wof:name":"Asespa\u00f1a Economistas Consultores S.l.",
    "wof:placetype":"venue"
},
  "geometry": {"coordinates":[-5.8503227234,43.3557319641],"type":"Point"}
}