{
  "type": "Feature",
  "properties": {
    "addr:full":"Ctra Alca\u00d1iz, 7 Teruel Teruel 44003",
    "addr:housenumber":"7",
    "addr:postcode":"44003",
    "addr:street":"Ctra Alcan\u0303Iz",
    "iso:country":"ES",
    "sg:address":"Ctra Alca\u00d1iz, 7",
    "sg:city":"Teruel",
    "sg:orig_category":"Peluquer\u00cdas, Peluquer\u00cda Mixta",
    "sg:phone":"+34 978 60 17 14",
    "sg:postcode":"44003",
    "sg:province":"Teruel",
    "wof:name":"Collados Catalan Raquel",
    "wof:placetype":"venue"
},
  "geometry": {"coordinates":[-1.1093809605,40.3478775024],"type":"Point"}
}