{
  "type": "Feature",
  "properties": {
    "iso:country":"ES",
    "sg:address":"Rua Sol, 123",
    "sg:city":"Ferrol",
    "sg:orig_category":"Peluquer\u00cdas, Peluquer\u00cda Mixta",
    "sg:phone":"+34 981 35 75 44",
    "sg:postcode":"15401",
    "sg:province":"A Coru\u00f1a",
    "wof:name":"Sequeiro Pazos Marta",
    "wof:placetype":"venue"
},
  "geometry": {"coordinates":[-8.2356052399,43.4840354919],"type":"Point"}
}