{
  "type": "Feature",
  "properties": {
    "addr:full":"Calle de Tizo, 11 Malaga M\u00e1laga 29013",
    "addr:housenumber":"11",
    "addr:postcode":"29013",
    "addr:street":"Calle De Tizo;Ma\u0301Laga",
    "iso:country":"ES",
    "sg:address":"Calle de Tizo, 11",
    "sg:city":"Malaga",
    "sg:orig_category":"Asociaciones Humanitarias, De Cooperaci\u00d3n, De Acci\u00d3n Social",
    "sg:phone":"+34 952 25 69 51",
    "sg:postcode":"29013",
    "sg:province":"M\u00e1laga",
    "wof:name":"Asociacion Para La Atencion A Mujeres Mastectomizadas",
    "wof:placetype":"venue"
},
  "geometry": {"coordinates":[-4.4223031998,36.7277069092],"type":"Point"}
}