{
  "type": "Feature",
  "properties": {
    "addr:full":"Teniente Molina, 13 Rociana Condado Huelva 21720",
    "addr:housenumber":"13",
    "addr:postcode":"21720",
    "addr:street":"Teniente Molina",
    "iso:country":"ES",
    "sg:address":"Teniente Molina, 13",
    "sg:city":"Rociana Condado",
    "sg:orig_category":"Farmacias",
    "sg:phone":"+34 959 41 61 64",
    "sg:postcode":"21720",
    "sg:province":"Huelva",
    "wof:name":"Sanchez Lopez Abelardo",
    "wof:placetype":"venue"
},
  "geometry": {"coordinates":[-6.594783783,37.3093147278],"type":"Point"}
}