{
  "type": "Feature",
  "properties": {
    "iso:country":"ES",
    "sg:address":"Avda Espa\u00d1a (de), 4",
    "sg:city":"Dos Hermanas",
    "sg:orig_category":"Cl\u00cdnicas Dentales",
    "sg:phone":"+34 955 67 77 46",
    "sg:postcode":"41700",
    "sg:province":"Sevilla",
    "wof:name":"Valverde Laborde Maria Del Valle",
    "wof:placetype":"venue"
},
  "geometry": {"coordinates":[-5.9340319633,37.2805252075],"type":"Point"}
}