{
  "type": "Feature",
  "properties": {
    "iso:country":"ES",
    "sg:address":"Avda Florez Estrada, 15",
    "sg:city":"Grado",
    "sg:orig_category":"Madera Para Construcci\u00d3n E Industria",
    "sg:phone":"+34 985 75 01 64",
    "sg:postcode":"33820",
    "sg:province":"Asturias",
    "wof:name":"Diaz Alvarez Fermin",
    "wof:placetype":"venue"
},
  "geometry": {"coordinates":[-6.0743889809,43.3870582581],"type":"Point"}
}