{
  "type": "Feature",
  "properties": {
    "addr:full":"Calle de Santo Domingo Henares, 5 Baena C\u00f3rdoba 14850",
    "addr:housenumber":"5",
    "addr:postcode":"14850",
    "addr:street":"Calle De Santo;Henares",
    "iso:country":"ES",
    "sg:address":"Calle de Santo Domingo Henares, 5",
    "sg:city":"Baena",
    "sg:orig_category":"Asociaciones, Organismos Culturales Y Socioeducativos",
    "sg:phone":"+34 957 67 19 46",
    "sg:postcode":"14850",
    "sg:province":"C\u00f3rdoba",
    "wof:name":"Ayuntamiento De Baena-punto De Informacion Turistica",
    "wof:placetype":"venue"
},
  "geometry": {"coordinates":[-4.3272790909,37.6141624451],"type":"Point"}
}