{
  "type": "Feature",
  "properties": {
    "iso:country":"ES",
    "sg:address":"Carrer de Balmes, 111",
    "sg:city":"S. Adria Besos",
    "sg:orig_category":"Electricidad: Equipos Industriales, Componentes (fabricaci\u00d3n)",
    "sg:phone":"+34 932 74 25 34",
    "sg:postcode":"08930",
    "sg:province":"Barcelona",
    "sg:website":"www.peisa.com",
    "wof:name":"Peisa Barcelona S.a.",
    "wof:placetype":"venue"
},
  "geometry": {"coordinates":[2.2092928886,41.4303588867],"type":"Point"}
}