{
  "type": "Feature",
  "properties": {
    "iso:country":"ES",
    "sg:address":"Calle de San Juan, 6",
    "sg:city":"Alhaurin Torre",
    "sg:orig_category":"Ropa Para Caballeros (al Por Menor)",
    "sg:phone":"+34 952 41 33 80",
    "sg:postcode":"29130",
    "sg:province":"M\u00e1laga",
    "wof:name":"Campos Cuenca Pedro",
    "wof:placetype":"venue"
},
  "geometry": {"coordinates":[-4.5618839264,36.6618843079],"type":"Point"}
}