{
  "type": "Feature",
  "properties": {
    "iso:country":"ES",
    "sg:address":"Calle de Hereu, 2",
    "sg:city":"Borriol",
    "sg:orig_category":"Bisuter\u00cda, Joyer\u00cda, Relojer\u00cda (al Por Menor)",
    "sg:phone":"+34 964 32 11 82",
    "sg:postcode":"12190",
    "sg:province":"Castell\u00f3n",
    "wof:name":"Zaragoza Silvestre Francisco",
    "wof:placetype":"venue"
},
  "geometry": {"coordinates":[-0.0713590011,40.0424575806],"type":"Point"}
}