{
  "type": "Feature",
  "properties": {
    "iso:country":"ES",
    "sg:address":"Ctra Rubi, 76",
    "sg:city":"Mira-sol",
    "sg:orig_category":"Agentes, Concesionarios Y Sucursales De Veh\u00cdculos",
    "sg:phone":"+34 935 44 29 38",
    "sg:postcode":"08173",
    "sg:province":"Barcelona",
    "sg:website":"www.autosaenz.com",
    "wof:name":"Auto Saenz S.a.",
    "wof:placetype":"venue"
},
  "geometry": {"coordinates":[2.0583388805,41.4800453186],"type":"Point"}
}