{
  "type": "Feature",
  "properties": {
    "addr:full":"Calle de Tampico, 101 Madrid Madrid 28027",
    "addr:housenumber":"101",
    "addr:postcode":"28027",
    "addr:street":"Calle De Tampico",
    "iso:country":"ES",
    "sg:address":"Calle de Tampico, 101",
    "sg:city":"Madrid",
    "sg:orig_category":"Asesor\u00cda Sobre Comunicaci\u00d3n De Empresas",
    "sg:phone":"+34 913 20 15 85",
    "sg:postcode":"28027",
    "sg:province":"Madrid",
    "wof:name":"Santos Y Segador C.b",
    "wof:placetype":"venue"
},
  "geometry": {"coordinates":[-3.6362578869,40.4455871582],"type":"Point"}
}