{
  "type": "Feature",
  "properties": {
    "iso:country":"ES",
    "sg:address":"Avda Mairena, 7",
    "sg:city":"Bormujos",
    "sg:orig_category":"Lecher\u00cdas",
    "sg:phone":"+34 955 72 51 53",
    "sg:postcode":"41930",
    "sg:province":"Sevilla",
    "wof:name":"Parmalat S.a.",
    "wof:placetype":"venue"
},
  "geometry": {"coordinates":[-6.0711288452,37.3726081848],"type":"Point"}
}