{
  "type": "Feature",
  "properties": {
    "addr:full":"Calle de Nuestro Padre Jesus, 12 Cantillana Sevilla 41320",
    "addr:housenumber":"12",
    "addr:postcode":"41320",
    "addr:street":"Calle De Nuestro Padre Jesus",
    "iso:country":"ES",
    "sg:address":"Calle de Nuestro Padre Jesus, 12",
    "sg:city":"Cantillana",
    "sg:orig_category":"Zapatos (al Por Menor)",
    "sg:phone":"+34 955 73 04 76",
    "sg:postcode":"41320",
    "sg:province":"Sevilla",
    "wof:name":"Calzados Edupast S.l.",
    "wof:placetype":"venue"
},
  "geometry": {"coordinates":[-5.8254799843,37.6085357666],"type":"Point"}
}