{
  "type": "Feature",
  "properties": {
    "iso:country":"ES",
    "sg:address":"Calle de Teniente Mu\u00d1oz Diaz, 9",
    "sg:city":"Madrid",
    "sg:orig_category":"Prot\u00c9sicos Dentales",
    "sg:phone":"+34 914 77 99 74",
    "sg:postcode":"28018",
    "sg:province":"Madrid",
    "wof:name":"Anguident 99 S.l.",
    "wof:placetype":"venue"
},
  "geometry": {"coordinates":[-3.6575605869,40.3909492493],"type":"Point"}
}