{
  "type": "Feature",
  "properties": {
    "addr:full":"Plaz Cervantes, 19 Badajoz Badajoz 06002",
    "addr:housenumber":"19",
    "addr:postcode":"06002",
    "addr:street":"Plaz Cervantes",
    "iso:country":"ES",
    "sg:address":"Plaz Cervantes, 19",
    "sg:city":"Badajoz",
    "sg:orig_category":"Farmacias",
    "sg:phone":"+34 924 22 46 50",
    "sg:postcode":"06002",
    "sg:province":"Badajoz",
    "wof:name":"Delgado Fernandez Isabel",
    "wof:placetype":"venue"
},
  "geometry": {"coordinates":[-6.9676160812,38.8780517578],"type":"Point"}
}