{
  "type": "Feature",
  "properties": {
    "addr:full":"Calle de Valencia, 1 Basauri Vizcaya 48970",
    "addr:housenumber":"1",
    "addr:postcode":"48970",
    "addr:street":"Calle De Valencia",
    "iso:country":"ES",
    "sg:address":"Calle de Valencia, 1",
    "sg:city":"Basauri",
    "sg:orig_category":"Estancos",
    "sg:phone":"+34 944 05 65 61",
    "sg:postcode":"48970",
    "sg:province":"Vizcaya",
    "wof:name":"Lourdes Azarloza Sierra",
    "wof:placetype":"venue"
},
  "geometry": {"coordinates":[-2.8807170391,43.2375030518],"type":"Point"}
}