{
  "type": "Feature",
  "properties": {
    "iso:country":"ES",
    "sg:address":"Calle de Jacinto Verdaguer, 19",
    "sg:city":"Madrid",
    "sg:orig_category":"Centros De Coordinaci\u00d3n",
    "sg:phone":"+34 914 71 84 46",
    "sg:postcode":"28019",
    "sg:province":"Madrid",
    "sg:website":"www.sigraph.com",
    "wof:name":"Sigraph Gestion Y Sistemas S.l.",
    "wof:placetype":"venue"
},
  "geometry": {"coordinates":[-3.7169649601,40.3955039978],"type":"Point"}
}