{
  "type": "Feature",
  "properties": {
    "addr:full":"Avda Paz (de La), 2 Villaca\u00f1as Toledo 45860",
    "addr:housenumber":"2",
    "addr:postcode":"45860",
    "addr:street":"Avda Paz De La",
    "iso:country":"ES",
    "sg:address":"Avda Paz (de La), 2",
    "sg:city":"Villaca\u00f1as",
    "sg:orig_category":"Caf\u00c9s, Bares, Cervecer\u00cdas",
    "sg:phone":"+34 925 16 01 01",
    "sg:postcode":"45860",
    "sg:province":"Toledo",
    "wof:name":"Lopez Tello Agustina",
    "wof:placetype":"venue"
},
  "geometry": {"coordinates":[-3.3350930214,39.6200294495],"type":"Point"}
}