{
  "type": "Feature",
  "properties": {
    "addr:full":"C/ Major, 5 Puigcerda Girona 17520",
    "addr:housenumber":"5",
    "addr:postcode":"17520",
    "addr:street":"C / Major",
    "iso:country":"ES",
    "sg:address":"C/ Major, 5",
    "sg:city":"Puigcerda",
    "sg:orig_category":"Perfumer\u00cda (al Por Menor)",
    "sg:phone":"+34 972 14 09 24",
    "sg:postcode":"17520",
    "sg:province":"Girona",
    "wof:name":"Biel Ramonet Nuria",
    "wof:placetype":"venue"
},
  "geometry": {"coordinates":[1.9276009798,42.4312553406],"type":"Point"}
}