{
  "type": "Feature",
  "properties": {
    "iso:country":"ES",
    "sg:address":"Carrer de Llinars, 16",
    "sg:city":"Cardedeu",
    "sg:orig_category":"Piedra Natural",
    "sg:phone":"+34 938 46 19 70",
    "sg:postcode":"08440",
    "sg:province":"Barcelona",
    "wof:name":"Calatayud Fortuny Andres",
    "wof:placetype":"venue"
},
  "geometry": {"coordinates":[2.360024929,41.6375465393],"type":"Point"}
}