{
  "type": "Feature",
  "properties": {
    "iso:country":"ES",
    "sg:address":"Calle de Acacio Gutierrez, 98",
    "sg:city":"Suances",
    "sg:orig_category":"Centros De Reservas Hoteleras",
    "sg:phone":"+34 942 81 15 51",
    "sg:postcode":"39340",
    "sg:province":"Cantabria",
    "wof:name":"Punta Del Dichoso S.l",
    "wof:placetype":"venue"
},
  "geometry": {"coordinates":[-4.0461149216,43.434425354],"type":"Point"}
}