{
  "type": "Feature",
  "properties": {
    "iso:country":"ES",
    "sg:address":"Calle de Almibar (del), 128",
    "sg:city":"Aranjuez",
    "sg:orig_category":"Mercer\u00cda, Lencer\u00cda (al Por Menor)",
    "sg:phone":"+34 918 91 85 70",
    "sg:postcode":"28300",
    "sg:province":"Madrid",
    "wof:name":"Ana Y Julia S.l.",
    "wof:placetype":"venue"
},
  "geometry": {"coordinates":[-3.6031839848,40.0297393799],"type":"Point"}
}