{
  "type": "Feature",
  "properties": {
    "addr:full":"Pg Aiguadol\u00c7, 22 Sitges Barcelona 08870",
    "addr:housenumber":"22",
    "addr:postcode":"08870",
    "addr:street":"Pg Aiguadolc\u0327",
    "iso:country":"ES",
    "sg:address":"Pg Aiguadol\u00c7, 22",
    "sg:city":"Sitges",
    "sg:orig_category":"Fabricaci\u00d3n, Reparaci\u00d3n Y Mantenimiento De Construcciones Navales Y Fluviales",
    "sg:phone":"+34 938 94 45 03",
    "sg:postcode":"08870",
    "sg:province":"Barcelona",
    "wof:name":"Nauticas Emilio S.l.",
    "wof:placetype":"venue"
},
  "geometry": {"coordinates":[1.8256709576,41.2351493835],"type":"Point"}
}