{
  "type": "Feature",
  "properties": {
    "addr:full":"Calle de Reyes De Navarra, 45 Vitoria-gasteiz \u00c1lava 01013",
    "addr:housenumber":"45",
    "addr:postcode":"01013",
    "addr:street":"Calle De Reyes De Navarra",
    "iso:country":"ES",
    "sg:address":"Calle de Reyes De Navarra, 45",
    "sg:city":"Vitoria-gasteiz",
    "sg:orig_category":"Instalaci\u00d3n, Reparaci\u00d3n De Ascensores Y Montacargas",
    "sg:phone":"+34 945 12 01 81",
    "sg:postcode":"01013",
    "sg:province":"\u00c1lava",
    "wof:name":"Thyssenkrupp Elevadores S.l.",
    "wof:placetype":"venue"
},
  "geometry": {"coordinates":[-2.6698250771,42.8601799011],"type":"Point"}
}