{
  "type": "Feature",
  "properties": {
    "iso:country":"ES",
    "sg:address":"Avda Pero Mingo (de), 27",
    "sg:city":"Sevilla",
    "sg:orig_category":"Imprenta",
    "sg:phone":"+34 954 51 04 10",
    "sg:postcode":"41016",
    "sg:province":"Sevilla",
    "wof:name":"Gonzalez Ferrer Emilio",
    "wof:placetype":"venue"
},
  "geometry": {"coordinates":[-5.9110507965,37.3859710693],"type":"Point"}
}