{
  "type": "Feature",
  "properties": {
    "addr:full":"Calle de Isla De Tavira, 20 Madrid Madrid 28035",
    "addr:housenumber":"20",
    "addr:postcode":"madrid;28035",
    "addr:street":"Calle De Isla De Tavira",
    "iso:country":"ES",
    "sg:address":"Calle de Isla De Tavira, 20",
    "sg:city":"Madrid",
    "sg:orig_category":"Frutas, Legumbres Frescas Y Tempranas (al Por Menor)",
    "sg:phone":"+34 917 39 65 69",
    "sg:postcode":"28035",
    "sg:province":"Madrid",
    "wof:name":"Exposito Gonzalez Francisco",
    "wof:placetype":"venue"
},
  "geometry": {"coordinates":[-3.7182099819,40.4817276001],"type":"Point"}
}