{
  "type": "Feature",
  "properties": {
    "addr:full":"Ctra Yecla, S/n Villena Alicante 03400",
    "addr:housenumber":"s / n",
    "addr:postcode":"03400",
    "addr:street":"Ctra Yecla",
    "iso:country":"ES",
    "sg:address":"Ctra Yecla, S/n",
    "sg:city":"Villena",
    "sg:orig_category":"Molduras, Junquillos, Listones Y Molduras Perforadas",
    "sg:phone":"+34 965 80 75 47",
    "sg:postcode":"03400",
    "sg:province":"Alicante",
    "wof:name":"Garcia Arias Amador",
    "wof:placetype":"venue"
},
  "geometry": {"coordinates":[-0.8702349067,38.6358375549],"type":"Point"}
}