{
  "type": "Feature",
  "properties": {
    "addr:full":"Rua Cuba, 18 Vigo Pontevedra 36204",
    "addr:housenumber":"18",
    "addr:postcode":"36204",
    "addr:street":"Rua Cuba",
    "iso:country":"ES",
    "sg:address":"Rua Cuba, 18",
    "sg:city":"Vigo",
    "sg:orig_category":"Peluquer\u00cdas, Peluquer\u00cda Mixta",
    "sg:phone":"+34 986 42 48 78",
    "sg:postcode":"36204",
    "sg:province":"Pontevedra",
    "wof:name":"Jimenez Garcia Pedro",
    "wof:placetype":"venue"
},
  "geometry": {"coordinates":[-8.7163238525,42.2332801819],"type":"Point"}
}