{
  "type": "Feature",
  "properties": {
    "addr:full":"Plaz Labores (las), S/n Parla Madrid 28980",
    "addr:postcode":"28980",
    "addr:street":"Las S / N",
    "iso:country":"ES",
    "sg:address":"Plaz Labores (las), S/n",
    "sg:city":"Parla",
    "sg:orig_category":"Electricidad: Instaladores",
    "sg:phone":"+34 916 99 73 10",
    "sg:postcode":"28980",
    "sg:province":"Madrid",
    "wof:name":"Aslama Lenjiri Llassan",
    "wof:placetype":"venue"
},
  "geometry": {"coordinates":[-3.7727413177,40.237537384],"type":"Point"}
}