{
  "type": "Feature",
  "properties": {
    "addr:full":"Avda Dos De Mayo (del), 27 Mostoles Madrid 28934",
    "addr:housenumber":"27",
    "addr:postcode":"28934",
    "addr:street":"Avda Dos De Mayo Del",
    "iso:country":"ES",
    "sg:address":"Avda Dos De Mayo (del), 27",
    "sg:city":"Mostoles",
    "sg:orig_category":"Inform\u00c1tica (estudios, Servicios, Asesor\u00cda, Formaci\u00d3n)",
    "sg:phone":"+34 916 64 33 42",
    "sg:postcode":"28934",
    "sg:province":"Madrid",
    "sg:website":"www.batch-pc.com",
    "wof:name":"Batch Pc S.l.",
    "wof:placetype":"venue"
},
  "geometry": {"coordinates":[-3.8699660301,40.3201293945],"type":"Point"}
}