{
  "type": "Feature",
  "properties": {
    "iso:country":"ES",
    "sg:address":"Calle de Real, 30",
    "sg:city":"Arguedas",
    "sg:orig_category":"Panader\u00cdas, Panader\u00cdas",
    "sg:phone":"+34 948 83 00 81",
    "sg:postcode":"31513",
    "sg:province":"Navarra",
    "wof:name":"Samanes Esparza Ismael",
    "wof:placetype":"venue"
},
  "geometry": {"coordinates":[-1.5985519886,42.1767044067],"type":"Point"}
}