{
  "type": "Feature",
  "properties": {
    "iso:country":"ES",
    "sg:address":"Quebrantos-la Arena, S/n",
    "sg:city":"Ranon",
    "sg:orig_category":"Supermercados Y Hipermercados",
    "sg:phone":"+34 985 58 67 01",
    "sg:postcode":"33125",
    "sg:province":"Asturias",
    "wof:name":"Merkaprecio S.a.",
    "wof:placetype":"venue"
},
  "geometry": {"coordinates":[-6.0765638351,43.557674408],"type":"Point"}
}