{
  "type": "Feature",
  "properties": {
    "addr:full":"Calle de Ciega, 3 S.gregorio Las Palmas 35200",
    "addr:housenumber":"3",
    "addr:postcode":"35200",
    "addr:street":"Calle De Ciega;Las Palmas",
    "iso:country":"ES",
    "sg:address":"Calle de Ciega, 3",
    "sg:city":"S.gregorio",
    "sg:orig_category":"Manicuras",
    "sg:phone":"+34 928 70 21 13",
    "sg:postcode":"35200",
    "sg:province":"Las Palmas",
    "wof:name":"Tus U\u00d1as S.l.",
    "wof:placetype":"venue"
},
  "geometry": {"coordinates":[-15.4144220352,28.0029888153],"type":"Point"}
}