{
  "type": "Feature",
  "properties": {
    "addr:full":"Rua Marcelo Macias, 31 Ourense Ourense 32002",
    "addr:housenumber":"31",
    "addr:postcode":"32002",
    "addr:street":"Rua Marcelo Macias",
    "iso:country":"ES",
    "sg:address":"Rua Marcelo Macias, 31",
    "sg:city":"Ourense",
    "sg:classifiers":[
        {
            "category":"Personal",
            "subcategory":"Barber",
            "type":"Services"
        }
    ],
    "sg:phone":"+34 988 24 48 46",
    "sg:postcode":"32002",
    "sg:province":"Ourense",
    "sg:tags":[
        "caballeros",
        "de",
        "peluqueros"
    ],
    "wof:name":"Fernandez Conde Aurelio",
    "wof:placetype":"venue"
},
  "geometry": {"coordinates":[-7.8701581955,42.3291702271],"type":"Point"}
}