{
  "type": "Feature",
  "properties": {
    "iso:country":"ES",
    "sg:address":"Calle de Libertad (la), 12",
    "sg:city":"Azuqueca Henares",
    "sg:orig_category":"Promotores Constructores",
    "sg:phone":"+34 949 26 30 59",
    "sg:postcode":"19200",
    "sg:province":"Guadalajara",
    "wof:name":"Soriano Carnero Balbino",
    "wof:placetype":"venue"
},
  "geometry": {"coordinates":[-3.2615799904,40.5670471191],"type":"Point"}
}