{
  "type": "Feature",
  "properties": {
    "iso:country":"ES",
    "sg:address":"Pl Tetuan, 15",
    "sg:city":"Barcelona",
    "sg:orig_category":"Farmacias",
    "sg:phone":"+34 932 65 73 06",
    "sg:postcode":"08010",
    "sg:province":"Barcelona",
    "wof:name":"Del Arco Casanovas Ana",
    "wof:placetype":"venue"
},
  "geometry": {"coordinates":[2.1747639179,41.3947067261],"type":"Point"}
}