{
  "type": "Feature",
  "properties": {
    "addr:full":"Calle de Jose Maria Pereda, 10 Alcala Henares Madrid 28806",
    "addr:housenumber":"10",
    "addr:postcode":"28806",
    "addr:street":"Calle De Jose Maria Pereda",
    "iso:country":"ES",
    "sg:address":"Calle de Jose Maria Pereda, 10",
    "sg:city":"Alcala Henares",
    "sg:orig_category":"Promotores Constructores",
    "sg:phone":"+34 918 02 52 75",
    "sg:postcode":"28806",
    "sg:province":"Madrid",
    "wof:name":"Algara Gomez Adela",
    "wof:placetype":"venue"
},
  "geometry": {"coordinates":[-3.3637740612,40.4973449707],"type":"Point"}
}