{
  "type": "Feature",
  "properties": {
    "addr:full":"Calle de Quevedo, 2 Ciudad Rodrigo Salamanca 37500",
    "addr:housenumber":"2",
    "addr:postcode":"37500",
    "addr:street":"Calle De Quevedo",
    "iso:country":"ES",
    "sg:address":"Calle de Quevedo, 2",
    "sg:city":"Ciudad Rodrigo",
    "sg:orig_category":"Electricidad: Instaladores",
    "sg:phone":"+34 923 48 08 67",
    "sg:postcode":"37500",
    "sg:province":"Salamanca",
    "wof:name":"Vicente Sanchez Benito",
    "wof:placetype":"venue"
},
  "geometry": {"coordinates":[-6.5295171738,40.6046218872],"type":"Point"}
}