{
  "type": "Feature",
  "properties": {
    "addr:full":"Ctra Barrosa (de La), 1 Chiclana De La Frontera C\u00e1diz 11130",
    "addr:postcode":"11130",
    "addr:street":"Ctra Barrosa De La 1",
    "iso:country":"ES",
    "sg:address":"Ctra Barrosa (de La), 1",
    "sg:city":"Chiclana De La Frontera",
    "sg:orig_category":"Art\u00cdculos De Regalo (al Por Menor)",
    "sg:phone":"+34 956 49 63 85",
    "sg:postcode":"11130",
    "sg:province":"C\u00e1diz",
    "wof:name":"Sanchez Alba Francisca",
    "wof:placetype":"venue"
},
  "geometry": {"coordinates":[-6.177834034,36.3926925659],"type":"Point"}
}