{
  "type": "Feature",
  "properties": {
    "iso:country":"ES",
    "sg:address":"Venta (la), 10",
    "sg:city":"Carpio",
    "sg:orig_category":"Agencias Y Agentes Comerciales, Representantes",
    "sg:phone":"+34 957 18 04 89",
    "sg:postcode":"14620",
    "sg:province":"C\u00f3rdoba",
    "wof:name":"Gaitan Serrano Francisco Jose",
    "wof:placetype":"venue"
},
  "geometry": {"coordinates":[-4.4988470078,37.9402809143],"type":"Point"}
}