{
  "type": "Feature",
  "properties": {
    "iso:country":"ES",
    "sg:address":"Calle de San Antonio, 3",
    "sg:city":"Bujalance",
    "sg:orig_category":"Cajas Para Embalar",
    "sg:phone":"+34 957 17 03 00",
    "sg:postcode":"14650",
    "sg:province":"C\u00f3rdoba",
    "wof:name":"Caja Rural De Cordoba",
    "wof:placetype":"venue"
},
  "geometry": {"coordinates":[-4.3809480667,37.8960380554],"type":"Point"}
}