{
  "type": "Feature",
  "properties": {
    "iso:country":"ES",
    "sg:address":"Carrer de Banys Nous, 15",
    "sg:city":"Barcelona",
    "sg:orig_category":"Muebles Y Decoraci\u00d3n De Jardines (fabricaci\u00d3n, Venta)",
    "sg:phone":"+34 933 18 66 46",
    "sg:postcode":"08002",
    "sg:province":"Barcelona",
    "wof:name":"Germanes Garcia S.c.",
    "wof:placetype":"venue"
},
  "geometry": {"coordinates":[2.1747090816,41.382358551],"type":"Point"}
}