{
  "type": "Feature",
  "properties": {
    "iso:country":"ES",
    "sg:address":"Avda Conde De Guadalhorce, 3",
    "sg:city":"Aviles",
    "sg:orig_category":"Empresas Portuarias",
    "sg:phone":"+34 985 52 60 41",
    "sg:postcode":"33401",
    "sg:province":"Asturias",
    "sg:website":"www.atlansur.es",
    "wof:name":"Atlantic Survey S.l.",
    "wof:placetype":"venue"
},
  "geometry": {"coordinates":[-5.9214501381,43.5601806641],"type":"Point"}
}