{
  "type": "Feature",
  "properties": {
    "addr:full":"Ctro Cial Calahonda, S/n Calahonda M\u00e1laga 29647",
    "addr:housenumber":"s / n",
    "addr:postcode":"29647",
    "addr:street":"Calahonda Ma\u0301Laga",
    "iso:country":"ES",
    "sg:address":"Ctro Cial Calahonda, S/n",
    "sg:city":"Calahonda",
    "sg:orig_category":"Arquitectos",
    "sg:phone":"+34 952 93 53 65",
    "sg:postcode":"29647",
    "sg:province":"M\u00e1laga",
    "wof:name":"Escassi Gil Rafael",
    "wof:placetype":"venue"
},
  "geometry": {"coordinates":[-4.7157039642,36.4931945801],"type":"Point"}
}