{
  "type": "Feature",
  "properties": {
    "addr:full":"Calle de Miguel Zazo, 16 Melilla Melilla 52004",
    "addr:housenumber":"16",
    "addr:postcode":"52004",
    "addr:street":"Calle De Miguel Zazo",
    "iso:country":"ES",
    "sg:address":"Calle de Miguel Zazo, 16",
    "sg:city":"Melilla",
    "sg:orig_category":"Perfumer\u00cda (al Por Menor)",
    "sg:phone":"+34 952 68 34 09",
    "sg:postcode":"52004",
    "sg:province":"Melilla",
    "wof:name":"Harrar Belilty Angel",
    "wof:placetype":"venue"
},
  "geometry": {"coordinates":[-2.9439430237,35.2909469604],"type":"Point"}
}