{
  "type": "Feature",
  "properties": {
    "addr:full":"Mondragones, S/n Arrasate Edo Mondragon Guip\u00f9zcoa 20500",
    "addr:housenumber":"/ n",
    "addr:postcode":"20500",
    "addr:street":"S;Edo;Guipu\u0300Zcoa",
    "iso:country":"ES",
    "sg:address":"Mondragones, S/n",
    "sg:city":"Arrasate Edo Mondragon",
    "sg:orig_category":"Carnicer\u00cdas, Carnicer\u00cdas",
    "sg:phone":"+34 943 79 95 54",
    "sg:postcode":"20500",
    "sg:province":"Guip\u00f9zcoa",
    "wof:name":"Murillo Nogales Alfonso",
    "wof:placetype":"venue"
},
  "geometry": {"coordinates":[-2.4945991039,43.060295105],"type":"Point"}
}