{
  "type": "Feature",
  "properties": {
    "addr:full":"Bule Luciano Demetrio Herrero, 2 Torrelavega Cantabria 39300",
    "addr:housenumber":"2",
    "addr:postcode":"39300",
    "iso:country":"ES",
    "sg:address":"Bule Luciano Demetrio Herrero, 2",
    "sg:city":"Torrelavega",
    "sg:orig_category":"Asesor\u00cda Sobre Comunicaci\u00d3n De Empresas",
    "sg:phone":"+34 942 80 28 74",
    "sg:postcode":"39300",
    "sg:province":"Cantabria",
    "wof:name":"Escobedo G. Latorre S.l.",
    "wof:placetype":"venue"
},
  "geometry": {"coordinates":[-4.0504288673,43.3493003845],"type":"Point"}
}