{
  "type": "Feature",
  "properties": {
    "addr:full":"Rua Castelao, 4 Milladoiro La Coru\u00f1a 15895",
    "addr:housenumber":"4",
    "addr:postcode":"15895",
    "addr:street":"Rua Castelao;La Corun\u0303A",
    "iso:country":"ES",
    "sg:address":"Rua Castelao, 4",
    "sg:city":"Milladoiro",
    "sg:orig_category":"Diarios, Revistas Y Boletines (distribuidores)",
    "sg:phone":"+34 981 52 23 99",
    "sg:postcode":"15895",
    "sg:province":"La Coru\u00f1a",
    "wof:name":"Milladoiro Motor S.l.",
    "wof:placetype":"venue"
},
  "geometry": {"coordinates":[-8.5783472061,42.8416023254],"type":"Point"}
}