{
  "type": "Feature",
  "properties": {
    "addr:full":"Ctra Albacete, 69 Casas-iba\u00e7ez Albacete 02200",
    "addr:housenumber":"69",
    "addr:postcode":"02200",
    "addr:street":"Ctra Albacete",
    "iso:country":"ES",
    "sg:address":"Ctra Albacete, 69",
    "sg:city":"Casas-iba\u00e7ez",
    "sg:orig_category":"Caf\u00c9s, Bares, Cervecer\u00cdas",
    "sg:phone":"+34 967 46 04 30",
    "sg:postcode":"02200",
    "sg:province":"Albacete",
    "wof:name":"Navarro Navalon Ursula",
    "wof:placetype":"venue"
},
  "geometry": {"coordinates":[-1.475728035,39.2844161987],"type":"Point"}
}