{
  "type": "Feature",
  "properties": {
    "addr:full":"Calle de Alberola, 30 Alacant Alicante 03007",
    "addr:housenumber":"30",
    "addr:postcode":"03007",
    "addr:street":"Calle De Alberola",
    "iso:country":"ES",
    "sg:address":"Calle de Alberola, 30",
    "sg:city":"Alacant",
    "sg:orig_category":"Promotores Constructores",
    "sg:phone":"+34 965 10 36 90",
    "sg:postcode":"03007",
    "sg:province":"Alicante",
    "wof:name":"Tecnoequip J.l.q. S.l.",
    "wof:placetype":"venue"
},
  "geometry": {"coordinates":[-0.4992119968,38.3413162231],"type":"Point"}
}