{
  "type": "Feature",
  "properties": {
    "iso:country":"ES",
    "sg:address":"Calle de Anton De Medellin, 16",
    "sg:city":"Alcala Guadaira",
    "sg:orig_category":"Electricidad: Instaladores",
    "sg:phone":"+34 954 10 26 06",
    "sg:postcode":"41500",
    "sg:province":"Sevilla",
    "wof:name":"Instalaciones Y Montajes Electricos Cald",
    "wof:placetype":"venue"
},
  "geometry": {"coordinates":[-5.8358950615,37.3407707214],"type":"Point"}
}