{
  "type": "Feature",
  "properties": {
    "iso:country":"ES",
    "sg:address":"Calle de Casta\u00d1os Los, 11",
    "sg:city":"Santa Eulalia",
    "sg:orig_category":"Doctores En Medicina",
    "sg:phone":"+34 985 26 17 26",
    "sg:postcode":"33423",
    "sg:province":"Asturias",
    "wof:name":"Trigo Gonzalez Antonio",
    "wof:placetype":"venue"
},
  "geometry": {"coordinates":[-5.6109199524,43.4562606812],"type":"Point"}
}