{
  "type": "Feature",
  "properties": {
    "addr:full":"Carrer de Aurora, 11 Martorelles Barcelona 08107",
    "addr:housenumber":"11",
    "addr:postcode":"08107",
    "addr:street":"Carrer De Aurora",
    "iso:country":"ES",
    "sg:address":"Carrer de Aurora, 11",
    "sg:city":"Martorelles",
    "sg:orig_category":"Comercio, Reparaci\u00d3n De Motocicletas, Bicicletas Y Piezas Sueltas",
    "sg:phone":"+34 935 70 62 29",
    "sg:postcode":"08107",
    "sg:province":"Barcelona",
    "sg:website":"www.pous.net",
    "wof:name":"Comercial Pous S.a.",
    "wof:placetype":"venue"
},
  "geometry": {"coordinates":[2.2393019199,41.5260429382],"type":"Point"}
}