{
  "type": "Feature",
  "properties": {
    "iso:country":"ES",
    "sg:address":"Parderrubias, 8",
    "sg:city":"Parderrubias",
    "sg:orig_category":"Negocio De Materiales De Construcci\u00d3n",
    "sg:phone":"+34 988 26 07 26",
    "sg:postcode":"32830",
    "sg:province":"Ourense",
    "wof:name":"Sierra Fernandez Cesar",
    "wof:placetype":"venue"
},
  "geometry": {"coordinates":[-7.921295166,42.238571167],"type":"Point"}
}