{
  "type": "Feature",
  "properties": {
    "addr:full":"Calle de Hermanos Gonzalez Blanco, 15 Luanco Asturias 33440",
    "addr:housenumber":"15",
    "addr:postcode":"33440",
    "addr:street":"Calle De Hermanos Gonzalez Blanco;Luanco Asturias",
    "iso:country":"ES",
    "sg:address":"Calle de Hermanos Gonzalez Blanco, 15",
    "sg:city":"Luanco",
    "sg:orig_category":"Molduras, Junquillos, Listones Y Molduras Perforadas",
    "sg:phone":"+34 985 88 24 22",
    "sg:postcode":"33440",
    "sg:province":"Asturias",
    "wof:name":"Fernandez Blancas Angeles",
    "wof:placetype":"venue"
},
  "geometry": {"coordinates":[-5.7930088043,43.6157417297],"type":"Point"}
}