{
  "type": "Feature",
  "properties": {
    "addr:full":"Carrer de Baix, 11 S. Vicen\u00e7 Montalt Barcelona 08394",
    "addr:housenumber":"11",
    "addr:postcode":"08394",
    "addr:street":"Carrer De Baix;S. Vicenc\u0327 Montalt Barcelona",
    "iso:country":"ES",
    "sg:address":"Carrer de Baix, 11",
    "sg:city":"S. Vicen\u00e7 Montalt",
    "sg:orig_category":"Cintas, Balduques Y Cierres De Tela (fabricaci\u00d3n, Al Por Mayor)",
    "sg:phone":"+34 937 91 02 11",
    "sg:postcode":"08394",
    "sg:province":"Barcelona",
    "sg:website":"www.artesana.biz",
    "wof:name":"Artesana De Clofent S.a.",
    "wof:placetype":"venue"
},
  "geometry": {"coordinates":[2.5089640617,41.579082489],"type":"Point"}
}