{
  "type": "Feature",
  "properties": {
    "addr:full":"O Castelo, S/n Castelo La Coru\u00f1a 15824",
    "addr:housenumber":"s / n",
    "addr:postcode":"15824",
    "addr:street":"Castelo;La Corun\u0303A",
    "iso:country":"ES",
    "sg:address":"O Castelo, S/n",
    "sg:city":"Castelo",
    "sg:orig_category":"Productos Qu\u00cdmicos (fabricaci\u00d3n, Al Por Mayor)",
    "sg:phone":"+34 981 81 45 06",
    "sg:postcode":"15824",
    "sg:province":"La Coru\u00f1a",
    "sg:website":"www.galchimia.com",
    "wof:name":"Galchimia S.l.",
    "wof:placetype":"venue"
},
  "geometry": {"coordinates":[-8.2970218658,43.3350982666],"type":"Point"}
}