{
  "type": "Feature",
  "properties": {
    "iso:country":"ES",
    "sg:address":"Crta. Gijon-sevilla, Km. 0287,0",
    "sg:city":"Merida",
    "sg:orig_category":"Cajas Y Embalajes Met\u00c1licos",
    "sg:phone":"+34 924 37 00 12",
    "sg:postcode":"06800",
    "sg:province":"Badajoz",
    "wof:name":"Mivisa Envases S.a.",
    "wof:placetype":"venue"
},
  "geometry": {"coordinates":[-6.3500027657,38.9179878235],"type":"Point"}
}