{
  "type": "Feature",
  "properties": {
    "iso:country":"ES",
    "sg:address":"Rua Progreso, 15",
    "sg:city":"Ca\u00f1iza",
    "sg:orig_category":"Transportes Por V\u00cdas Navegables",
    "sg:phone":"+34 986 66 30 30",
    "sg:postcode":"36880",
    "sg:province":"Pontevedra",
    "wof:name":"Castro Martinez Maria Azuzena",
    "wof:placetype":"venue"
},
  "geometry": {"coordinates":[-8.2739887238,42.2132987976],"type":"Point"}
}