{
  "type": "Feature",
  "properties": {
    "addr:full":"Calle de Paulina Odiaga, 24 Madrid Madrid 28019",
    "addr:housenumber":"24",
    "addr:postcode":"madrid;28019",
    "addr:street":"Calle De Paulina Odiaga",
    "iso:country":"ES",
    "sg:address":"Calle de Paulina Odiaga, 24",
    "sg:city":"Madrid",
    "sg:orig_category":"Cerrajer\u00cda, Ferrallista",
    "sg:phone":"+34 914 71 16 24",
    "sg:postcode":"28019",
    "sg:province":"Madrid",
    "wof:name":"Perez Carrascosa Jorge",
    "wof:placetype":"venue"
},
  "geometry": {"coordinates":[-3.7243900299,40.3941307068],"type":"Point"}
}