{
  "type": "Feature",
  "properties": {
    "addr:full":"Carrer de Villar De Grau, 23 Can Villa Barcelona 08395",
    "addr:housenumber":"23",
    "addr:postcode":"08395",
    "addr:street":"Carrer De Villar De Grau;Barcelona",
    "iso:country":"ES",
    "sg:address":"Carrer de Villar De Grau, 23",
    "sg:city":"Can Villa",
    "sg:orig_category":"Peritos Mar\u00cdtimos",
    "sg:phone":"+34 937 60 21 67",
    "sg:postcode":"08395",
    "sg:province":"Barcelona",
    "wof:name":"Arbues Inmuebles S.l.",
    "wof:placetype":"venue"
},
  "geometry": {"coordinates":[2.6142921448,41.5993041992],"type":"Point"}
}