{
  "type": "Feature",
  "properties": {
    "addr:full":"Calle de Mayor, S/n Alera Zaragoza 50679",
    "addr:housenumber":"s",
    "addr:postcode":"50679",
    "addr:street":"Calle De Mayor;/ N Alera",
    "iso:country":"ES",
    "sg:address":"Calle de Mayor, S/n",
    "sg:city":"Alera",
    "sg:classifiers":[
        {
            "category":"Casinos & Gambling",
            "type":"Entertainment"
        }
    ],
    "sg:phone":"+34 976 67 52 52",
    "sg:postcode":"50679",
    "sg:province":"Zaragoza",
    "sg:tags":[
        "locale",
        "de",
        "juego"
    ],
    "wof:name":"Junta De Colonos De Alera",
    "wof:placetype":"venue"
},
  "geometry": {"coordinates":[-1.3545980453,42.3070678711],"type":"Point"}
}