{
  "type": "Feature",
  "properties": {
    "addr:full":"Carr Odena, 32 Igualada Barcelona 08700",
    "addr:housenumber":"32",
    "addr:postcode":"08700",
    "addr:street":"Carr Odena",
    "iso:country":"ES",
    "sg:address":"Carr Odena, 32",
    "sg:city":"Igualada",
    "sg:orig_category":"Muebles, Minoristas",
    "sg:phone":"+34 938 05 28 45",
    "sg:postcode":"08700",
    "sg:province":"Barcelona",
    "wof:name":"Muxi Sole Miguel Angel",
    "wof:placetype":"venue"
},
  "geometry": {"coordinates":[1.6190890074,41.5804901123],"type":"Point"}
}