{
  "type": "Feature",
  "properties": {
    "addr:full":"Calle de Arte Mayor De La Seda, 7 Valencia Valencia 46018",
    "addr:housenumber":"7",
    "addr:postcode":"46018",
    "addr:street":"Calle De Arte Mayor De La Seda",
    "iso:country":"ES",
    "sg:address":"Calle de Arte Mayor De La Seda, 7",
    "sg:city":"Valencia",
    "sg:orig_category":"Edici\u00d3n De Diarios, Revistas, Boletines",
    "sg:phone":"+34 963 50 15 10",
    "sg:postcode":"46018",
    "sg:province":"Valencia",
    "wof:name":"Vicente Martinez Nuria",
    "wof:placetype":"venue"
},
  "geometry": {"coordinates":[-0.3966920078,39.4693489075],"type":"Point"}
}