{
  "type": "Feature",
  "properties": {
    "iso:country":"ES",
    "sg:address":"Calle de Rio, 11",
    "sg:city":"Milagros",
    "sg:orig_category":"Carnicer\u00cdas, Carnicer\u00cdas",
    "sg:phone":"+34 947 54 80 77",
    "sg:postcode":"09460",
    "sg:province":"Burgos",
    "wof:name":"Sanz Miguel Angel",
    "wof:placetype":"venue"
},
  "geometry": {"coordinates":[-3.6975591183,41.5758018494],"type":"Point"}
}