{
  "type": "Feature",
  "properties": {
    "addr:full":"Avda Ricardo Mella, 444 San Xurxo Pontevedra 36390",
    "addr:housenumber":"444",
    "addr:postcode":"36390",
    "addr:street":"Avda Ricardo Mella",
    "iso:country":"ES",
    "sg:address":"Avda Ricardo Mella, 444",
    "sg:city":"San Xurxo",
    "sg:orig_category":"Distribuci\u00d3n De Petr\u00d3leo Y Derivados",
    "sg:phone":"+34 986 46 01 96",
    "sg:postcode":"36390",
    "sg:province":"Pontevedra",
    "wof:name":"Explotacion De Carburantes De Canido S.l.",
    "wof:placetype":"venue"
},
  "geometry": {"coordinates":[-8.798915863,42.1908302307],"type":"Point"}
}