{
  "type": "Feature",
  "properties": {
    "iso:country":"ES",
    "sg:address":"Carrer de Pardo, 66",
    "sg:city":"Barcelona",
    "sg:orig_category":"Institutos De Belleza",
    "sg:phone":"+34 933 45 97 16",
    "sg:postcode":"08016",
    "sg:province":"Barcelona",
    "wof:name":"Torralbo Ramirez Araceli",
    "wof:placetype":"venue"
},
  "geometry": {"coordinates":[2.1827740669,41.4299888611],"type":"Point"}
}