{
  "type": "Feature",
  "properties": {
    "iso:country":"ES",
    "sg:address":"Calle de Sargo, 9",
    "sg:city":"Alacant",
    "sg:orig_category":"Promotores Constructores",
    "sg:phone":"+34 965 15 57 81",
    "sg:postcode":"03540",
    "sg:province":"Alicante",
    "wof:name":"Nuepro Empresa Constructora S.l.",
    "wof:placetype":"venue"
},
  "geometry": {"coordinates":[-0.4154089987,38.359828949],"type":"Point"}
}