{
  "type": "Feature",
  "properties": {
    "addr:full":"Calle de Cimadevila, 21 Boiro La Coru\u00f1a 15930",
    "addr:housenumber":"21",
    "addr:postcode":"15930",
    "addr:street":"Calle De Cimadevila;La Corun\u0303A",
    "iso:country":"ES",
    "sg:address":"Calle de Cimadevila, 21",
    "sg:city":"Boiro",
    "sg:orig_category":"Producci\u00d3n De Abonos Y De Fertilizantes",
    "sg:phone":"+34 981 84 82 15",
    "sg:postcode":"15930",
    "sg:province":"La Coru\u00f1a",
    "wof:name":"Agro Mafer S.l.",
    "wof:placetype":"venue"
},
  "geometry": {"coordinates":[-8.8747062683,42.6569137573],"type":"Point"}
}