{
  "type": "Feature",
  "properties": {
    "iso:country":"ES",
    "sg:address":"Calle de Puerta Del Sol, 12",
    "sg:city":"Jaen",
    "sg:orig_category":"Electricidad: Instaladores",
    "sg:phone":"+34 953 22 79 51",
    "sg:postcode":"23007",
    "sg:province":"Ja\u00e9n",
    "wof:name":"Cytel S.l.",
    "wof:placetype":"venue"
},
  "geometry": {"coordinates":[-3.7917780876,37.7739524841],"type":"Point"}
}