{
  "type": "Feature",
  "properties": {
    "iso:country":"ES",
    "sg:address":"Calle de Ancha, 80",
    "sg:city":"Rambla",
    "sg:orig_category":"Mec\u00c1nico Del Autom\u00d3vil",
    "sg:phone":"+34 957 68 30 93",
    "sg:postcode":"14540",
    "sg:province":"C\u00f3rdoba",
    "wof:name":"Ruz Osuna Octavio Ramon",
    "wof:placetype":"venue"
},
  "geometry": {"coordinates":[-4.7453322411,37.6073875427],"type":"Point"}
}