{
  "type": "Feature",
  "properties": {
    "addr:full":"Calle de Doctor Fleming, 2 Santomera Murcia 30140",
    "addr:housenumber":"2",
    "addr:postcode":"30140",
    "addr:street":"Calle De Doctor Fleming",
    "iso:country":"ES",
    "sg:address":"Calle de Doctor Fleming, 2",
    "sg:city":"Santomera",
    "sg:orig_category":"Peluqueros: De Se\u00d1oras",
    "sg:phone":"+34 968 86 00 98",
    "sg:postcode":"30140",
    "sg:province":"Murcia",
    "wof:name":"Joaquin Y Susi Peluqueros S.l",
    "wof:placetype":"venue"
},
  "geometry": {"coordinates":[-1.0502794981,38.063835144],"type":"Point"}
}