{
  "type": "Feature",
  "properties": {
    "iso:country":"ES",
    "sg:address":"Calle de Pio Xii, 1",
    "sg:city":"Aranda Duero",
    "sg:orig_category":"Molduras, Junquillos, Listones Y Molduras Perforadas",
    "sg:phone":"+34 947 50 93 14",
    "sg:postcode":"09400",
    "sg:province":"Burgos",
    "wof:name":"Perez Cuesta Florentino",
    "wof:placetype":"venue"
},
  "geometry": {"coordinates":[-3.6856570244,41.6775474548],"type":"Point"}
}