{
  "type": "Feature",
  "properties": {
    "iso:country":"ES",
    "sg:address":"Av Generalitat, 30",
    "sg:city":"Santa Coloma De Gramenet",
    "sg:orig_category":"Supermercados Y Hipermercados",
    "sg:phone":"+34 933 86 20 32",
    "sg:postcode":"08922",
    "sg:province":"Barcelona",
    "wof:name":"Almazan Saez Manuel",
    "wof:placetype":"venue"
},
  "geometry": {"coordinates":[2.2101328373,41.4499206543],"type":"Point"}
}