{
  "type": "Feature",
  "properties": {
    "addr:full":"Calle de Gloria, 9 San Juan Murcia 30003",
    "addr:housenumber":"9",
    "addr:postcode":"30003",
    "addr:street":"Calle De Gloria",
    "iso:country":"ES",
    "sg:address":"Calle de Gloria, 9",
    "sg:city":"San Juan",
    "sg:classifiers":[
        {
            "category":"Autos & Motor Vehicles",
            "subcategory":"Automobile Sales",
            "type":"Retail Goods"
        }
    ],
    "sg:phone":"+34 968 22 24 16",
    "sg:postcode":"30003",
    "sg:province":"Murcia",
    "wof:name":"Autoescuela Chicamo S.l.",
    "wof:placetype":"venue"
},
  "geometry": {"coordinates":[-1.1259870529,37.9824256897],"type":"Point"}
}