{
  "type": "Feature",
  "properties": {
    "iso:country":"ES",
    "sg:address":"Ctra Arenales (los), Km. 0008,0",
    "sg:city":"Arenales",
    "sg:orig_category":"Producci\u00d3n, Venta De Productos De Agricultura Biol\u00d3gica",
    "sg:phone":"+34 957 60 50 73",
    "sg:postcode":"14500",
    "sg:province":"C\u00f3rdoba",
    "wof:name":"Bocio Andrade Maria",
    "wof:placetype":"venue"
},
  "geometry": {"coordinates":[-4.7779579163,37.3909187317],"type":"Point"}
}