{
  "type": "Feature",
  "properties": {
    "iso:country":"ES",
    "sg:address":"Calle de Antonio Fernandez 'maza', 6",
    "sg:city":"Albacete",
    "sg:orig_category":"Peluqueros: De Se\u00d1oras",
    "sg:phone":"+34 967 23 60 36",
    "sg:postcode":"02004",
    "sg:province":"Albacete",
    "wof:name":"Cifuentes Ortega Angeles",
    "wof:placetype":"venue"
},
  "geometry": {"coordinates":[-1.8665504456,38.9900627136],"type":"Point"}
}