{
  "type": "Feature",
  "properties": {
    "addr:full":"Plaz San Lorenzo, 2 San Lorenzo De El Escorial Madrid 28200",
    "addr:housenumber":"2",
    "addr:postcode":"28200",
    "addr:street":"Plaz San Lorenzo",
    "iso:country":"ES",
    "sg:address":"Plaz San Lorenzo, 2",
    "sg:city":"San Lorenzo De El Escorial",
    "sg:orig_category":"Bisuter\u00cda, Joyer\u00cda, Relojer\u00cda (al Por Menor)",
    "sg:phone":"+34 918 90 82 33",
    "sg:postcode":"28200",
    "sg:province":"Madrid",
    "wof:name":"M & M Azul Joyeros S.l.",
    "wof:placetype":"venue"
},
  "geometry": {"coordinates":[-4.1481161118,40.5912208557],"type":"Point"}
}