{
  "type": "Feature",
  "properties": {
    "iso:country":"ES",
    "sg:address":"Carrer de Orfeo Catala, 9",
    "sg:city":"S. Joan Despi",
    "sg:orig_category":"Comercio De Piezas De Recambio Y De Accesorios De Veh\u00cdculos, Veh\u00cdculos Industriales",
    "sg:phone":"+34 934 77 61 66",
    "sg:postcode":"08970",
    "sg:province":"Barcelona",
    "wof:name":"V8 Recambios Americanos S.l.",
    "wof:placetype":"venue"
},
  "geometry": {"coordinates":[2.0730481148,41.3671150208],"type":"Point"}
}