{
  "type": "Feature",
  "properties": {
    "addr:full":"Carrer de Joan Maragall, 11 Rubi Barcelona 08191",
    "addr:housenumber":"11",
    "addr:postcode":"08191",
    "addr:street":"Carrer De Joan Maragall",
    "iso:country":"ES",
    "sg:address":"Carrer de Joan Maragall, 11",
    "sg:city":"Rubi",
    "sg:orig_category":"M\u00c9dicos: Ginecolog\u00cda Y Obstetricia",
    "sg:phone":"+34 936 99 35 54",
    "sg:postcode":"08191",
    "sg:province":"Barcelona",
    "wof:name":"Ila Bruned Vicente",
    "wof:placetype":"venue"
},
  "geometry": {"coordinates":[2.0367119312,41.4873847961],"type":"Point"}
}