{
  "type": "Feature",
  "properties": {
    "iso:country":"ES",
    "sg:address":"Calle de Gilaberto Centelles, 27",
    "sg:city":"Nules",
    "sg:orig_category":"Carnicer\u00cdas, Carnicer\u00cdas",
    "sg:phone":"+34 964 67 23 01",
    "sg:postcode":"12520",
    "sg:province":"Castell\u00f3n",
    "wof:name":"Esbri Villarroya Antonio",
    "wof:placetype":"venue"
},
  "geometry": {"coordinates":[-0.1572719961,39.8525085449],"type":"Point"}
}