{
  "type": "Feature",
  "properties": {
    "addr:full":"Calle de Ilustracion, 17 Madrid Madrid 28008",
    "addr:housenumber":"17",
    "addr:postcode":"madrid;28008",
    "addr:street":"Calle De Ilustracion",
    "iso:country":"ES",
    "sg:address":"Calle de Ilustracion, 17",
    "sg:city":"Madrid",
    "sg:orig_category":"Empresarios Y Productoras De Espect\u00c1culos",
    "sg:phone":"+34 915 47 93 28",
    "sg:postcode":"28008",
    "sg:province":"Madrid",
    "wof:name":"Sanchez Gomez Jose",
    "wof:placetype":"venue"
},
  "geometry": {"coordinates":[-3.717416048,40.4210624695],"type":"Point"}
}