{
  "type": "Feature",
  "properties": {
    "iso:country":"ES",
    "sg:address":"Plaz Catedral, 3",
    "sg:city":"Huesca",
    "sg:orig_category":"Organizaciones Internacionales",
    "sg:phone":"+34 974 22 65 56",
    "sg:postcode":"22002",
    "sg:province":"Huesca",
    "sg:website":"www.manosunidas.org",
    "wof:name":"Manos Unidas",
    "wof:placetype":"venue"
},
  "geometry": {"coordinates":[-0.4087589979,42.1408843994],"type":"Point"}
}