{
  "type": "Feature",
  "properties": {
    "iso:country":"ES",
    "sg:address":"Calle de Coso, 105",
    "sg:city":"Zaragoza",
    "sg:orig_category":"Ense\u00d1anza: Idiomas",
    "sg:phone":"+34 976 29 56 31",
    "sg:postcode":"50001",
    "sg:province":"Zaragoza",
    "wof:name":"Societa Dante Alighieri",
    "wof:placetype":"venue"
},
  "geometry": {"coordinates":[-0.8758708239,41.6508522034],"type":"Point"}
}