{
  "type": "Feature",
  "properties": {
    "addr:full":"Avda Alcalde Federico Molina, 40 Huelva Huelva 21006",
    "addr:housenumber":"40",
    "addr:postcode":"21006",
    "addr:street":"Avda Alcalde Federico Molina",
    "iso:country":"ES",
    "sg:address":"Avda Alcalde Federico Molina, 40",
    "sg:city":"Huelva",
    "sg:orig_category":"M\u00c9dicos: An\u00c1lisis Cl\u00cdnicos",
    "sg:phone":"+34 959 22 64 18",
    "sg:postcode":"21006",
    "sg:province":"Huelva",
    "wof:name":"Lopez Orta Juan Alberto",
    "wof:placetype":"venue"
},
  "geometry": {"coordinates":[-6.9340348244,37.2584381104],"type":"Point"}
}