{
  "type": "Feature",
  "properties": {
    "addr:full":"Calle de Henequen (el), 4 Pto. Rosario Las Palmas 35600",
    "addr:housenumber":"4",
    "addr:postcode":"35600",
    "addr:street":"Calle De Henequen El;Pto. Rosario Las",
    "iso:country":"ES",
    "sg:address":"Calle de Henequen (el), 4",
    "sg:city":"Pto. Rosario",
    "sg:orig_category":"Productos Qu\u00cdmicos (fabricaci\u00d3n, Al Por Mayor)",
    "sg:phone":"+34 928 53 05 68",
    "sg:postcode":"35600",
    "sg:province":"Las Palmas",
    "wof:name":"Quimicas Morales S. L.",
    "wof:placetype":"venue"
},
  "geometry": {"coordinates":[-13.8644685745,28.5023498535],"type":"Point"}
}