{
  "type": "Feature",
  "properties": {
    "iso:country":"ES",
    "sg:address":"Ctra Llano De Brujas, Km. 0001,0",
    "sg:city":"Puente Tocinos",
    "sg:orig_category":"Droguer\u00cdas (al Por Mayor)",
    "sg:phone":"+34 968 24 51 35",
    "sg:postcode":"30006",
    "sg:province":"Murcia",
    "wof:name":"Cash Martin S.l.",
    "wof:placetype":"venue"
},
  "geometry": {"coordinates":[-1.1008939743,37.9940185547],"type":"Point"}
}