{
  "type": "Feature",
  "properties": {
    "addr:full":"Calle de Capitan Antonio De Oro Pulido (de), 5 Ciempozuelos Madrid 28350",
    "addr:postcode":"28350",
    "addr:street":"Calle De Capitan Antonio De Oro",
    "iso:country":"ES",
    "sg:address":"Calle de Capitan Antonio De Oro Pulido (de), 5",
    "sg:city":"Ciempozuelos",
    "sg:orig_category":"Fabricaci\u00d3n De Cervezas",
    "sg:phone":"+34 918 93 06 07",
    "sg:postcode":"28350",
    "sg:province":"Madrid",
    "wof:name":"Oro Carrera Julian De",
    "wof:placetype":"venue"
},
  "geometry": {"coordinates":[-3.6184461117,40.1602134705],"type":"Point"}
}