{
  "type": "Feature",
  "properties": {
    "addr:full":"Carrer de Tresols, 26 Gava Barcelona 08850",
    "addr:housenumber":"26",
    "addr:postcode":"08850",
    "addr:street":"Carrer De Tresols",
    "iso:country":"ES",
    "sg:address":"Carrer de Tresols, 26",
    "sg:city":"Gava",
    "sg:orig_category":"Inmobiliaria (agencias)",
    "sg:phone":"+34 936 62 76 76",
    "sg:postcode":"08850",
    "sg:province":"Barcelona",
    "wof:name":"Dofi Inversiones Inmobiliarias S.l.",
    "wof:placetype":"venue"
},
  "geometry": {"coordinates":[2.0010740757,41.3065719604],"type":"Point"}
}