{
  "type": "Feature",
  "properties": {
    "iso:country":"ES",
    "sg:address":"Av Prat De La Riba, 9",
    "sg:city":"Reus",
    "sg:orig_category":"Abogados",
    "sg:phone":"+34 977 32 63 66",
    "sg:postcode":"43201",
    "sg:province":"Tarragona",
    "wof:name":"Jara Trilla Carles S.l.n.e.",
    "wof:placetype":"venue"
},
  "geometry": {"coordinates":[1.1044290066,41.1576499939],"type":"Point"}
}