{
  "type": "Feature",
  "properties": {
    "addr:full":"Calle de Neptuno, 68 Granada Granada 18004",
    "addr:housenumber":"68",
    "addr:postcode":"18004",
    "addr:street":"Calle De Neptuno",
    "iso:country":"ES",
    "sg:address":"Calle de Neptuno, 68",
    "sg:city":"Granada",
    "sg:orig_category":"Agencias De Viajes",
    "sg:phone":"+34 958 53 62 17",
    "sg:postcode":"18004",
    "sg:province":"Granada",
    "wof:name":"Viajes Granasur S.l.",
    "wof:placetype":"venue"
},
  "geometry": {"coordinates":[-3.6069130898,37.1697807312],"type":"Point"}
}