{
  "type": "Feature",
  "properties": {
    "iso:country":"ES",
    "sg:address":"Rua Urzaiz, 31",
    "sg:city":"Vigo",
    "sg:orig_category":"Psic\u00d3logos",
    "sg:phone":"+34 986 22 48 01",
    "sg:postcode":"36201",
    "sg:province":"Pontevedra",
    "wof:name":"Mencia Tome Beatriz",
    "wof:placetype":"venue"
},
  "geometry": {"coordinates":[-8.7176818848,42.2351646423],"type":"Point"}
}