{
  "type": "Feature",
  "properties": {
    "addr:full":"Crt Aldea Del Rey, Km. 0011,0 Pozuelo Calatrava Ciudad Real 13179",
    "addr:postcode":"13179",
    "addr:street":"Crt Aldea Del Rey Km. 0011,0 Pozuelo",
    "iso:country":"ES",
    "sg:address":"Crt Aldea Del Rey, Km. 0011,0",
    "sg:city":"Pozuelo Calatrava",
    "sg:orig_category":"Agricultores, Agricultores",
    "sg:phone":"+34 926 84 03 52",
    "sg:postcode":"13179",
    "sg:province":"Ciudad Real",
    "wof:name":"Promociones Sampoz S.a.",
    "wof:placetype":"venue"
},
  "geometry": {"coordinates":[-3.8354260921,38.9131889343],"type":"Point"}
}