{
  "type": "Feature",
  "properties": {
    "addr:full":"Calle de Comedero, 33 Porcuna Ja\u00e9n 23790",
    "addr:housenumber":"33",
    "addr:postcode":"23790",
    "addr:street":"Calle De Comedero",
    "iso:country":"ES",
    "sg:address":"Calle de Comedero, 33",
    "sg:city":"Porcuna",
    "sg:orig_category":"Empresas De Pintura Y Revestimientos",
    "sg:phone":"+34 953 54 55 47",
    "sg:postcode":"23790",
    "sg:province":"Ja\u00e9n",
    "wof:name":"Frias Serrano Maria Angeles",
    "wof:placetype":"venue"
},
  "geometry": {"coordinates":[-4.188639164,37.8748588562],"type":"Point"}
}