{
  "type": "Feature",
  "properties": {
    "iso:country":"ES",
    "sg:address":"Botiguers(pol Ind), 3",
    "sg:city":"Pol Ind Fuente Jarro",
    "sg:orig_category":"Construcciones Met\u00c1licas",
    "sg:phone":"+34 963 33 60 31",
    "sg:postcode":"46988",
    "sg:province":"Valencia",
    "wof:name":"Pretersa-prenavisa Estructuras De Hormig",
    "wof:placetype":"venue"
},
  "geometry": {"coordinates":[-0.376819998,39.4691886902],"type":"Point"}
}