{
  "type": "Feature",
  "properties": {
    "iso:country":"ES",
    "sg:address":"N. Monturiol (po Ind Plans D'arau), 15",
    "sg:city":"Pobla Claramunt",
    "sg:orig_category":"Tubos Y Tuber\u00cdas De Metales Ferrosos (fabricaci\u00d3n, Negocio)",
    "sg:phone":"+34 938 08 77 01",
    "sg:postcode":"08787",
    "sg:province":"Barcelona",
    "wof:name":"Caldereria Bolarin-cardus S.l.",
    "wof:placetype":"venue"
},
  "geometry": {"coordinates":[1.6380000114,41.5322113037],"type":"Point"}
}