{
  "type": "Feature",
  "properties": {
    "iso:country":"ES",
    "sg:address":"Carrer de Aprestadora, 21",
    "sg:city":"Hospitalet Llobregat",
    "sg:orig_category":"Electricidad: Instaladores",
    "sg:phone":"+34 932 96 91 47",
    "sg:postcode":"08902",
    "sg:province":"Barcelona",
    "wof:name":"Mont-roig Instalacions C.b.",
    "wof:placetype":"venue"
},
  "geometry": {"coordinates":[2.1314110756,41.3638648987],"type":"Point"}
}