{
  "type": "Feature",
  "properties": {
    "iso:country":"ES",
    "sg:address":"Calle de Paez De Ribera, 12",
    "sg:city":"Sevilla",
    "sg:orig_category":"Farmacias",
    "sg:phone":"+34 954 09 72 41",
    "sg:postcode":"41012",
    "sg:province":"Sevilla",
    "wof:name":"Moron Ledro Antonio",
    "wof:placetype":"venue"
},
  "geometry": {"coordinates":[-5.9880290031,37.3636932373],"type":"Point"}
}