{
  "type": "Feature",
  "properties": {
    "addr:full":"Calle de El Crucero, 4 San Juan De Muskiz Vizcaya 48550",
    "addr:housenumber":"4",
    "addr:postcode":"48550",
    "addr:street":"Calle De El Crucero",
    "iso:country":"ES",
    "sg:address":"Calle de El Crucero, 4",
    "sg:city":"San Juan De Muskiz",
    "sg:orig_category":"Caf\u00c9s, Bares, Cervecer\u00cdas",
    "sg:phone":"+34 946 70 81 95",
    "sg:postcode":"48550",
    "sg:province":"Vizcaya",
    "wof:name":"Phone Euskadi S. L.",
    "wof:placetype":"venue"
},
  "geometry": {"coordinates":[-3.1151459217,43.3221206665],"type":"Point"}
}