{
  "type": "Feature",
  "properties": {
    "iso:country":"ES",
    "sg:address":"Carrer de Cubelles, 4",
    "sg:city":"Vilafranca Penedes",
    "sg:orig_category":"Carpinteros",
    "sg:phone":"+34 938 17 19 50",
    "sg:postcode":"08720",
    "sg:province":"Barcelona",
    "wof:name":"Vecesam S.l.",
    "wof:placetype":"venue"
},
  "geometry": {"coordinates":[1.6901160479,41.3378448486],"type":"Point"}
}