{
  "type": "Feature",
  "properties": {
    "iso:country":"ES",
    "sg:address":"C/ Pintor Soler Jorba, 2",
    "sg:city":"Cerdanyola Valles",
    "sg:classifiers":[
        {
            "category":"Tea Room",
            "subcategory":"None",
            "type":"Food & Drink"
        }
    ],
    "sg:phone":"+34 936 91 45 59",
    "sg:postcode":"08290",
    "sg:province":"Barcelona",
    "sg:tags":[
        "snack"
    ],
    "wof:name":"Mohedano Tena Francisco",
    "wof:placetype":"venue"
},
  "geometry": {"coordinates":[2.1470150948,41.4924812317],"type":"Point"}
}