{
  "type": "Feature",
  "properties": {
    "iso:country":"ES",
    "sg:address":"Av Mas D'en Puig, 2",
    "sg:city":"Sitges",
    "sg:orig_category":"Prot\u00c9sicos Dentales",
    "sg:phone":"+34 938 14 65 97",
    "sg:postcode":"08870",
    "sg:province":"Barcelona",
    "wof:name":"Boston Scientific Iberica S.a.",
    "wof:placetype":"venue"
},
  "geometry": {"coordinates":[1.8502800465,41.2549095154],"type":"Point"}
}