{
  "type": "Feature",
  "properties": {
    "iso:country":"ES",
    "sg:address":"Carrer de Malats, 58",
    "sg:city":"Barcelona",
    "sg:orig_category":"Equipo De Refrigeraci\u00d3n Industrial",
    "sg:phone":"+34 933 11 96 11",
    "sg:postcode":"08030",
    "sg:province":"Barcelona",
    "wof:name":"Ramon Vizcaino Refrigeracion",
    "wof:placetype":"venue"
},
  "geometry": {"coordinates":[2.1875789165,41.4365119934],"type":"Point"}
}