{
  "type": "Feature",
  "properties": {
    "addr:full":"Calle de Porvera, 31 Jerez De La Frontera C\u00e1diz 11403",
    "addr:housenumber":"31",
    "addr:postcode":"11403",
    "addr:street":"Calle De Porvera",
    "iso:country":"ES",
    "sg:address":"Calle de Porvera, 31",
    "sg:city":"Jerez De La Frontera",
    "sg:orig_category":"M\u00c9dicos: Estomatolog\u00cda",
    "sg:phone":"+34 956 33 54 04",
    "sg:postcode":"11403",
    "sg:province":"C\u00e1diz",
    "wof:name":"Alvargonzalez Mendez Claudio",
    "wof:placetype":"venue"
},
  "geometry": {"coordinates":[-6.1392931938,36.687171936],"type":"Point"}
}