{
  "type": "Feature",
  "properties": {
    "addr:full":"Calle de Poza Licenciado, 28 Bilbao Vizcaya 48011",
    "addr:housenumber":"28",
    "addr:postcode":"48011",
    "addr:street":"Calle De Poza Licenciado",
    "iso:country":"ES",
    "sg:address":"Calle de Poza Licenciado, 28",
    "sg:city":"Bilbao",
    "sg:orig_category":"Asesor\u00cda Fiscal Y Jur\u00cddica",
    "sg:phone":"+34 944 41 88 74",
    "sg:postcode":"48011",
    "sg:province":"Vizcaya",
    "wof:name":"Larizgoitia Angulo Miren Edurne",
    "wof:placetype":"venue"
},
  "geometry": {"coordinates":[-2.9388227463,43.2640609741],"type":"Point"}
}