{
  "type": "Feature",
  "properties": {
    "iso:country":"ES",
    "sg:address":"Rua Otero Pedraio, 5",
    "sg:city":"Gondomar",
    "sg:orig_category":"Caf\u00c9s, Bares, Cervecer\u00cdas",
    "sg:phone":"+34 986 38 93 38",
    "sg:postcode":"36380",
    "sg:province":"Pontevedra",
    "wof:name":"Etinorte S.l.",
    "wof:placetype":"venue"
},
  "geometry": {"coordinates":[-8.7624816895,42.1114273071],"type":"Point"}
}