{
  "type": "Feature",
  "properties": {
    "addr:full":"Avgd Alacant, 90 Pedreguer Alicante 03750",
    "addr:housenumber":"90",
    "addr:postcode":"03750",
    "addr:street":"Alacant",
    "iso:country":"ES",
    "sg:address":"Avgd Alacant, 90",
    "sg:city":"Pedreguer",
    "sg:orig_category":"Confecci\u00d3n De Sombreros Y Tocados",
    "sg:phone":"+34 966 45 63 15",
    "sg:postcode":"03750",
    "sg:province":"Alicante",
    "wof:name":"Miralles Costa Jaime",
    "wof:placetype":"venue"
},
  "geometry": {"coordinates":[0.0406799987,38.7915039062],"type":"Point"}
}