{
  "type": "Feature",
  "properties": {
    "iso:country":"ES",
    "sg:address":"Grup Vint-i-cinc De Setembre, 48",
    "sg:city":"Rubi",
    "sg:orig_category":"Iglesia Cat\u00d3lica",
    "sg:phone":"+34 936 99 67 69",
    "sg:postcode":"08191",
    "sg:province":"Barcelona",
    "wof:name":"Parroquia De San Pablo",
    "wof:placetype":"venue"
},
  "geometry": {"coordinates":[2.0394999981,41.4846916199],"type":"Point"}
}