{
  "type": "Feature",
  "properties": {
    "addr:full":"Calle de Pizarro (de), 5 San Fernando De Henares Madrid 28830",
    "addr:postcode":"28830",
    "addr:street":"Calle De Pizarro De 5",
    "iso:country":"ES",
    "sg:address":"Calle de Pizarro (de), 5",
    "sg:city":"San Fernando De Henares",
    "sg:orig_category":"Agencias De Viajes",
    "sg:phone":"+34 916 69 38 54",
    "sg:postcode":"28830",
    "sg:province":"Madrid",
    "wof:name":"Imagen Coral S.l.",
    "wof:placetype":"venue"
},
  "geometry": {"coordinates":[-3.5326941013,40.4247283936],"type":"Point"}
}