{
  "type": "Feature",
  "properties": {
    "addr:full":"Camino Viejo Simancas, 16 Valladolid Valladolid 47008",
    "addr:housenumber":"16",
    "addr:postcode":"47008",
    "addr:street":"Camino Viejo Simancas",
    "iso:country":"ES",
    "sg:address":"Camino Viejo Simancas, 16",
    "sg:city":"Valladolid",
    "sg:orig_category":"Pintura, Barniz, Productos Asimilables (fabricaci\u00d3n, Al Por Mayor)",
    "sg:phone":"+34 983 47 12 14",
    "sg:postcode":"47008",
    "sg:province":"Valladolid",
    "wof:name":"Fondomovil Industrial S.l.",
    "wof:placetype":"venue"
},
  "geometry": {"coordinates":[-4.747358799,41.6265296936],"type":"Point"}
}