{
  "type": "Feature",
  "properties": {
    "iso:country":"ES",
    "sg:address":"Ctra Gral, Km. 0182,0",
    "sg:city":"Cartes",
    "sg:orig_category":"Mec\u00c1nico Del Autom\u00d3vil",
    "sg:phone":"+34 942 81 92 63",
    "sg:postcode":"39311",
    "sg:province":"Cantabria",
    "wof:name":"Automoviles Torrelavega S. L.",
    "wof:placetype":"venue"
},
  "geometry": {"coordinates":[-4.0702290535,43.3219108582],"type":"Point"}
}