{
  "type": "Feature",
  "properties": {
    "addr:full":"Calle de General San Martin, 7 Valencia Valencia 46004",
    "addr:housenumber":"7",
    "addr:postcode":"46004",
    "addr:street":"Calle De General San Martin",
    "iso:country":"ES",
    "sg:address":"Calle de General San Martin, 7",
    "sg:city":"Valencia",
    "sg:orig_category":"Abogados",
    "sg:phone":"+34 963 52 92 45",
    "sg:postcode":"46004",
    "sg:province":"Valencia",
    "wof:name":"Mondria Mateu Rafael",
    "wof:placetype":"venue"
},
  "geometry": {"coordinates":[-0.5301448703,39.5653457642],"type":"Point"}
}