{
  "type": "Feature",
  "properties": {
    "addr:full":"Calle de Alfonso Xi, 15 Algeciras C\u00e1diz 11201",
    "addr:housenumber":"15;ca\u0301diz",
    "addr:postcode":"11201",
    "addr:street":"Calle De Alfonso Xi",
    "iso:country":"ES",
    "sg:address":"Calle de Alfonso Xi, 15",
    "sg:city":"Algeciras",
    "sg:orig_category":"Cl\u00cdnicas M\u00c9dicas",
    "sg:phone":"+34 956 66 63 13",
    "sg:postcode":"11201",
    "sg:province":"C\u00e1diz",
    "wof:name":"Compa\u00f1ia De Seguros Adeslas S.a.",
    "wof:placetype":"venue"
},
  "geometry": {"coordinates":[-5.4397826195,36.135761261],"type":"Point"}
}