{
  "type": "Feature",
  "properties": {
    "addr:full":"Calle de Isabel Ii, 7 Parla Madrid 28980",
    "addr:housenumber":"7",
    "addr:postcode":"28980",
    "addr:street":"Calle De Isabel Ii",
    "iso:country":"ES",
    "sg:address":"Calle de Isabel Ii, 7",
    "sg:city":"Parla",
    "sg:orig_category":"Diarios, Revistas Y Boletines (suscripciones)",
    "sg:phone":"+34 916 05 59 15",
    "sg:postcode":"28980",
    "sg:province":"Madrid",
    "wof:name":"Yzpisua Dominguez Susana",
    "wof:placetype":"venue"
},
  "geometry": {"coordinates":[-3.7650635242,40.2350311279],"type":"Point"}
}