{
  "type": "Feature",
  "properties": {
    "iso:country":"ES",
    "sg:address":"Carretera Viver, S/n",
    "sg:city":"Sestrica",
    "sg:orig_category":"Empresas De Carpinter\u00cda De Madera",
    "sg:phone":"+34 976 82 63 13",
    "sg:postcode":"50248",
    "sg:province":"Zaragoza",
    "wof:name":"Herrero Morales Jose Ramon",
    "wof:placetype":"venue"
},
  "geometry": {"coordinates":[-1.5949640274,41.4864006042],"type":"Point"}
}