{
  "type": "Feature",
  "properties": {
    "addr:full":"Vgen Buen Acuerdo, 54 Zaragoza Zaragoza 50014",
    "addr:housenumber":"54",
    "addr:postcode":"50014",
    "addr:street":"Vgen Buen Acuerdo",
    "iso:country":"ES",
    "sg:address":"Vgen Buen Acuerdo, 54",
    "sg:city":"Zaragoza",
    "sg:orig_category":"Puertas Y Portales",
    "sg:phone":"+34 976 43 60 11",
    "sg:postcode":"50014",
    "sg:province":"Zaragoza",
    "sg:website":"www.zaragoza-ciudad.com/comercialbenedi",
    "wof:name":"Comercial Benedi S. L.",
    "wof:placetype":"venue"
},
  "geometry": {"coordinates":[-0.8612239957,41.6785926819],"type":"Point"}
}