{
  "type": "Feature",
  "properties": {
    "iso:country":"ES",
    "sg:address":"Autopista Del Norte, Km. 0025,0",
    "sg:city":"La Matanza Acentejo",
    "sg:orig_category":"Distribuci\u00d3n De Petr\u00d3leo Y Derivados",
    "sg:phone":"+34 922 57 91 90",
    "sg:postcode":"38370",
    "sg:province":"Santa Cruz De Tenerife",
    "wof:name":"El Bohio De Tenerife S.l.",
    "wof:placetype":"venue"
},
  "geometry": {"coordinates":[-16.2645397186,28.4603805542],"type":"Point"}
}