{
  "type": "Feature",
  "properties": {
    "iso:country":"ES",
    "sg:address":"Calle de Mar De Bering, 5",
    "sg:city":"Madrid",
    "sg:orig_category":"Empresas De Electricidad En General",
    "sg:phone":"+34 913 81 57 11",
    "sg:postcode":"28033",
    "sg:province":"Madrid",
    "wof:name":"Njl Bering Factory S.l.",
    "wof:placetype":"venue"
},
  "geometry": {"coordinates":[-3.642111063,40.47315979],"type":"Point"}
}