{
  "type": "Feature",
  "properties": {
    "addr:full":"Plaz Santa Ana, 26 Sevilla Sevilla 41002",
    "addr:housenumber":"26",
    "addr:postcode":"41002",
    "addr:street":"Santa Ana",
    "iso:country":"ES",
    "sg:address":"Plaz Santa Ana, 26",
    "sg:city":"Sevilla",
    "sg:orig_category":"Arquitectos",
    "sg:phone":"+34 954 90 32 41",
    "sg:postcode":"41002",
    "sg:province":"Sevilla",
    "wof:name":"Arquiana Arquitectos Sl",
    "wof:placetype":"venue"
},
  "geometry": {"coordinates":[-5.9959607124,37.3980102539],"type":"Point"}
}