{
  "type": "Feature",
  "properties": {
    "addr:full":"Calle de Compositor Lehmberg Ruiz, 32 Malaga M\u00e1laga 29007",
    "addr:housenumber":"32",
    "addr:postcode":"29007",
    "addr:street":"Calle De Compositor Lehmberg Ruiz;Ma\u0301Laga",
    "iso:country":"ES",
    "sg:address":"Calle de Compositor Lehmberg Ruiz, 32",
    "sg:city":"Malaga",
    "sg:orig_category":"Asesor\u00cda Sobre Comunicaci\u00d3n De Empresas",
    "sg:phone":"+34 952 30 06 62",
    "sg:postcode":"29007",
    "sg:province":"M\u00e1laga",
    "sg:website":"www.cpmasesores.es",
    "wof:name":"Centro Profesional Malague\u00d1o De Asesoramientos S.a.",
    "wof:placetype":"venue"
},
  "geometry": {"coordinates":[-4.4349360466,36.7187194824],"type":"Point"}
}