{
  "type": "Feature",
  "properties": {
    "iso:country":"ES",
    "sg:address":"Calle de Cura, 5",
    "sg:city":"Herencias",
    "sg:orig_category":"Comunidades Religiosas",
    "sg:phone":"+34 925 70 91 32",
    "sg:postcode":"45664",
    "sg:province":"Toledo",
    "wof:name":"Parroquia De La Purisima Concepcion",
    "wof:placetype":"venue"
},
  "geometry": {"coordinates":[-4.923019886,39.8680725098],"type":"Point"}
}