{
  "type": "Feature",
  "properties": {
    "addr:full":"Carrer de Josep Anselm Clave, 8 Hospitalet Llobregat Barcelona 08902",
    "addr:housenumber":"8",
    "addr:postcode":"08902",
    "addr:street":"Carrer De Josep Anselm Clave",
    "iso:country":"ES",
    "sg:address":"Carrer de Josep Anselm Clave, 8",
    "sg:city":"Hospitalet Llobregat",
    "sg:orig_category":"Limpieza Industrial",
    "sg:phone":"+34 934 32 17 93",
    "sg:postcode":"08902",
    "sg:province":"Barcelona",
    "wof:name":"Falguera Montiel Pedro",
    "wof:placetype":"venue"
},
  "geometry": {"coordinates":[2.1261889935,41.3666648865],"type":"Point"}
}