{
  "type": "Feature",
  "properties": {
    "iso:country":"ES",
    "sg:address":"Calle de Pardo Jimeno, 47",
    "sg:city":"Alacant",
    "sg:orig_category":"Caf\u00c9s, Bares, Cervecer\u00cdas",
    "sg:phone":"+34 965 10 13 85",
    "sg:postcode":"03007",
    "sg:province":"Alicante",
    "wof:name":"Cascales Soto Miriam",
    "wof:placetype":"venue"
},
  "geometry": {"coordinates":[-0.5013620257,38.3414878845],"type":"Point"}
}