{
  "type": "Feature",
  "properties": {
    "addr:full":"Avda Galtzaraborda, 101 Errenteria Guip\u00f9zcoa 20100",
    "addr:housenumber":"101",
    "addr:postcode":"20100",
    "addr:street":"Avda Galtzaraborda;Guipu\u0300Zcoa",
    "iso:country":"ES",
    "sg:address":"Avda Galtzaraborda, 101",
    "sg:city":"Errenteria",
    "sg:orig_category":"Peluquer\u00cdas, Peluquer\u00cda Mixta",
    "sg:phone":"+34 943 34 15 86",
    "sg:postcode":"20100",
    "sg:province":"Guip\u00f9zcoa",
    "wof:name":"Hernandez Sanchez Sofia",
    "wof:placetype":"venue"
},
  "geometry": {"coordinates":[-1.9070509672,43.3161430359],"type":"Point"}
}