{
  "type": "Feature",
  "properties": {
    "iso:country":"ES",
    "sg:address":"Calle de Jesus Del Gran Poder, 13",
    "sg:city":"Madrid",
    "sg:orig_category":"Peluqueros: De Se\u00d1oras",
    "sg:phone":"+34 914 76 37 07",
    "sg:postcode":"28026",
    "sg:province":"Madrid",
    "wof:name":"Blanco Gonzalez Manuel",
    "wof:placetype":"venue"
},
  "geometry": {"coordinates":[-3.7023870945,40.3879623413],"type":"Point"}
}