{
  "type": "Feature",
  "properties": {
    "addr:full":"Calle de Angustias, 37 Nerja M\u00e1laga 29780",
    "addr:housenumber":"37",
    "addr:postcode":"29780",
    "addr:street":"Calle De Angustias",
    "iso:country":"ES",
    "sg:address":"Calle de Angustias, 37",
    "sg:city":"Nerja",
    "sg:orig_category":"Peluquer\u00cdas, Peluquer\u00cda Mixta",
    "sg:phone":"+34 952 52 53 07",
    "sg:postcode":"29780",
    "sg:province":"M\u00e1laga",
    "wof:name":"Gordo Armijo Lucia",
    "wof:placetype":"venue"
},
  "geometry": {"coordinates":[-3.8778789043,36.748374939],"type":"Point"}
}