{
  "type": "Feature",
  "properties": {
    "iso:country":"ES",
    "sg:address":"Carrer de Sant Miquel, 13",
    "sg:city":"Palma",
    "sg:orig_category":"Bisuter\u00cda, Joyer\u00cda, Relojer\u00cda (al Por Menor)",
    "sg:phone":"+34 971 72 40 86",
    "sg:postcode":"07002",
    "sg:province":"Islas Baleares",
    "wof:name":"Estrany Joieries I Serveiss.l.",
    "wof:placetype":"venue"
},
  "geometry": {"coordinates":[2.6519908905,39.5723495483],"type":"Point"}
}