{
  "type": "Feature",
  "properties": {
    "addr:full":"Carr Ausias March (d'), S/n Lliria Valencia 46160",
    "addr:housenumber":"s / n",
    "addr:postcode":"46160",
    "addr:street":"Carr Ausias March D '",
    "iso:country":"ES",
    "sg:address":"Carr Ausias March (d'), S/n",
    "sg:city":"Lliria",
    "sg:orig_category":"Promotores Constructores",
    "sg:phone":"+34 962 78 13 53",
    "sg:postcode":"46160",
    "sg:province":"Valencia",
    "wof:name":"Edibafor S.l.",
    "wof:placetype":"venue"
},
  "geometry": {"coordinates":[-0.6006439924,39.6298332214],"type":"Point"}
}