{
  "type": "Feature",
  "properties": {
    "addr:full":"Pase Jardin De La Reina, 2 Granada Granada 18006",
    "addr:housenumber":"2",
    "addr:postcode":"18006",
    "addr:street":"Reina",
    "iso:country":"ES",
    "sg:address":"Pase Jardin De La Reina, 2",
    "sg:city":"Granada",
    "sg:orig_category":"Cl\u00cdnicas M\u00c9dicas",
    "sg:phone":"+34 958 12 86 88",
    "sg:postcode":"18006",
    "sg:province":"Granada",
    "wof:name":"Clinica Traumatologica Dr.garcia Nieves S.l.",
    "wof:placetype":"venue"
},
  "geometry": {"coordinates":[-3.6024889946,37.1630401611],"type":"Point"}
}