{
  "type": "Feature",
  "properties": {
    "iso:country":"ES",
    "sg:address":"Carr Francesc Layret, 34",
    "sg:city":"Badalona",
    "sg:orig_category":"Prendas Y Chalecos De Punto (al Por Menor)",
    "sg:phone":"+34 933 84 10 01",
    "sg:postcode":"08911",
    "sg:province":"Barcelona",
    "wof:name":"Salsas Sabater Maria Rosa",
    "wof:placetype":"venue"
},
  "geometry": {"coordinates":[2.2467730045,41.4497261047],"type":"Point"}
}