{
  "type": "Feature",
  "properties": {
    "addr:full":"Calle de Senderillo, 10 Ajalvir Madrid 28864",
    "addr:housenumber":"10",
    "addr:postcode":"28864",
    "addr:street":"Calle De Senderillo",
    "iso:country":"ES",
    "sg:address":"Calle de Senderillo, 10",
    "sg:city":"Ajalvir",
    "sg:orig_category":"Cables Y Hilos El\u00c9ctricos (fabricaci\u00d3n, Al Por Mayor)",
    "sg:phone":"+34 918 84 45 18",
    "sg:postcode":"28864",
    "sg:province":"Madrid",
    "wof:name":"Cableados Y Montajes Electronicos S.a.",
    "wof:placetype":"venue"
},
  "geometry": {"coordinates":[-3.4824650288,40.5302391052],"type":"Point"}
}