{
  "type": "Feature",
  "properties": {
    "iso:country":"ES",
    "sg:address":"Calle de Roa De La Vega, 8",
    "sg:city":"Le\u00f3n",
    "sg:orig_category":"Art\u00cdculos De Decoraci\u00d3n",
    "sg:phone":"+34 987 22 15 28",
    "sg:postcode":"24002",
    "sg:province":"Le\u00f3n",
    "wof:name":"Galeria H Y Bernesga S.l.",
    "wof:placetype":"venue"
},
  "geometry": {"coordinates":[-5.5766677856,42.6008987427],"type":"Point"}
}