{
  "type": "Feature",
  "properties": {
    "iso:country":"ES",
    "sg:address":"Calle de Urreta, 21",
    "sg:city":"Kurtzea",
    "sg:orig_category":"Conservatorios",
    "sg:phone":"+34 944 56 72 41",
    "sg:postcode":"48960",
    "sg:province":"Vizcaya",
    "wof:name":"Centro Municipal De Actividades Musicales De Galdakao",
    "wof:placetype":"venue"
},
  "geometry": {"coordinates":[-2.8499519825,43.2315635681],"type":"Point"}
}