{
  "type": "Feature",
  "properties": {
    "addr:full":"Calle de Gremis, Dels, 8 Valencia Valencia 46014",
    "addr:housenumber":"8",
    "addr:postcode":"46014",
    "addr:street":"Calle De Gremis Dels",
    "iso:country":"ES",
    "sg:address":"Calle de Gremis, Dels, 8",
    "sg:city":"Valencia",
    "sg:orig_category":"Molduras, Junquillos, Listones Y Molduras Perforadas",
    "sg:phone":"+34 963 50 02 48",
    "sg:postcode":"46014",
    "sg:province":"Valencia",
    "wof:name":"Vivo Peinado Evelio",
    "wof:placetype":"venue"
},
  "geometry": {"coordinates":[-0.4103930891,39.4598884583],"type":"Point"}
}