{
  "type": "Feature",
  "properties": {
    "iso:country":"ES",
    "sg:address":"Calle de Real, 11",
    "sg:city":"Roda Andalucia",
    "sg:orig_category":"Cajas De Ahorro",
    "sg:phone":"+34 954 01 60 87",
    "sg:postcode":"41590",
    "sg:province":"Sevilla",
    "wof:name":"Caja San Fernando De Sevilla Y Jerez",
    "wof:placetype":"venue"
},
  "geometry": {"coordinates":[-4.7799220085,37.2006530762],"type":"Point"}
}