{
  "type": "Feature",
  "properties": {
    "iso:country":"ES",
    "sg:address":"Carrer de Demostenes, 13",
    "sg:city":"Sabadell",
    "sg:orig_category":"Fotograf\u00cda Art\u00cdstica Y Retratos",
    "sg:phone":"+34 937 23 61 63",
    "sg:postcode":"08206",
    "sg:province":"Barcelona",
    "wof:name":"Caudevilla Alameda Jose Luis",
    "wof:placetype":"venue"
},
  "geometry": {"coordinates":[2.0863039494,41.5548210144],"type":"Point"}
}