{
  "type": "Feature",
  "properties": {
    "iso:country":"ES",
    "sg:address":"Carrer de Sardana, 8",
    "sg:city":"Reus",
    "sg:orig_category":"Dietistas",
    "sg:phone":"+34 977 31 94 24",
    "sg:postcode":"43205",
    "sg:province":"Tarragona",
    "wof:name":"Gomez Salvado Juan",
    "wof:placetype":"venue"
},
  "geometry": {"coordinates":[1.1054810286,41.1507987976],"type":"Point"}
}