{
  "type": "Feature",
  "properties": {
    "iso:country":"ES",
    "sg:address":"Carrer de Occitania, 99",
    "sg:city":"Olesa Montserrat",
    "sg:orig_category":"Agencias Y Agentes Comerciales, Representantes",
    "sg:phone":"+34 937 78 40 26",
    "sg:postcode":"08640",
    "sg:province":"Barcelona",
    "wof:name":"Fajardo Gonzalez David",
    "wof:placetype":"venue"
},
  "geometry": {"coordinates":[1.8915079832,41.5530853271],"type":"Point"}
}