{
  "type": "Feature",
  "properties": {
    "addr:full":"Calle de Olivar, 12 Madrid Madrid 28012",
    "addr:housenumber":"12",
    "addr:postcode":"madrid;28012",
    "addr:street":"Calle De Olivar",
    "iso:country":"ES",
    "sg:address":"Calle de Olivar, 12",
    "sg:city":"Madrid",
    "sg:orig_category":"Peluquer\u00cdas, Peluquer\u00cda Mixta",
    "sg:phone":"+34 915 39 22 54",
    "sg:postcode":"28012",
    "sg:province":"Madrid",
    "wof:name":"Felipe Y Quinti S.l.",
    "wof:placetype":"venue"
},
  "geometry": {"coordinates":[-3.701859951,40.4113807678],"type":"Point"}
}