{
  "type": "Feature",
  "properties": {
    "addr:full":"Nafar Kalea, 17 Hernani Guip\u00f9zcoa 20120",
    "addr:housenumber":"17",
    "addr:postcode":"20120",
    "addr:street":"Nafar Kalea;Guipu\u0300Zcoa",
    "iso:country":"ES",
    "sg:address":"Nafar Kalea, 17",
    "sg:city":"Hernani",
    "sg:orig_category":"Ropa Para Ni\u00d1os (al Por Menor)",
    "sg:phone":"+34 943 33 14 10",
    "sg:postcode":"20120",
    "sg:province":"Guip\u00f9zcoa",
    "wof:name":"Amparo Olazabal (ipotx)",
    "wof:placetype":"venue"
},
  "geometry": {"coordinates":[-1.9762233496,43.2665100098],"type":"Point"}
}