{
  "type": "Feature",
  "properties": {
    "iso:country":"ES",
    "sg:address":"Calle de Pedro Tena, 2",
    "sg:city":"Fi\u00f1ana",
    "sg:orig_category":"Guarder\u00cdas",
    "sg:phone":"+34 950 35 23 93",
    "sg:postcode":"04500",
    "sg:province":"Almer\u00eda",
    "wof:name":"Ayuntamiento De Finana",
    "wof:placetype":"venue"
},
  "geometry": {"coordinates":[-2.8423640728,37.1711730957],"type":"Point"}
}