{
  "type": "Feature",
  "properties": {
    "iso:country":"ES",
    "sg:address":"Carrer de Sant Francesc, S/n",
    "sg:city":"Denia",
    "sg:orig_category":"Museos",
    "sg:phone":"+34 966 42 06 56",
    "sg:postcode":"03700",
    "sg:province":"Alicante",
    "wof:name":"Ayuntamiento De Denia",
    "wof:placetype":"venue"
},
  "geometry": {"coordinates":[0.1052550003,38.8415603638],"type":"Point"}
}