{
  "type": "Feature",
  "properties": {
    "iso:country":"ES",
    "sg:address":"Avda Diaz Martinez Jesus, 8",
    "sg:city":"Agreda",
    "sg:orig_category":"Maquinaria Para Industrias Diversas",
    "sg:phone":"+34 976 64 72 93",
    "sg:postcode":"42100",
    "sg:province":"Soria",
    "wof:name":"Sevillano Lavilla Felix",
    "wof:placetype":"venue"
},
  "geometry": {"coordinates":[-1.9253499508,41.8543930054],"type":"Point"}
}