{
  "type": "Feature",
  "properties": {
    "iso:country":"ES",
    "sg:address":"Carrer de Ramon Moncada, 9",
    "sg:city":"Santa Pon\u00c7a",
    "sg:orig_category":"Caf\u00c9s, Bares, Cervecer\u00cdas",
    "sg:phone":"+34 971 69 68 87",
    "sg:postcode":"07180",
    "sg:province":"Islas Baleares",
    "wof:name":"Ritche  Irene",
    "wof:placetype":"venue"
},
  "geometry": {"coordinates":[2.474848032,39.5195274353],"type":"Point"}
}