{
  "type": "Feature",
  "properties": {
    "addr:full":"Rua Irmans Moreno, 22 Verin Ourense 32600",
    "addr:housenumber":"22",
    "addr:postcode":"32600",
    "addr:street":"Rua Irmans Moreno",
    "iso:country":"ES",
    "sg:address":"Rua Irmans Moreno, 22",
    "sg:city":"Verin",
    "sg:orig_category":"Caf\u00c9s, Bares, Cervecer\u00cdas",
    "sg:phone":"+34 988 41 36 97",
    "sg:postcode":"32600",
    "sg:province":"Ourense",
    "wof:name":"Telefourense S.l.",
    "wof:placetype":"venue"
},
  "geometry": {"coordinates":[-7.432888031,41.9377555847],"type":"Point"}
}