{
  "type": "Feature",
  "properties": {
    "iso:country":"ES",
    "sg:address":"Carrer de Progres, 69",
    "sg:city":"Gava",
    "sg:orig_category":"Fabricaci\u00d3n De Sobres, Bolsas Y Fundas",
    "sg:phone":"+34 936 38 14 07",
    "sg:postcode":"08850",
    "sg:province":"Barcelona",
    "wof:name":"D.c.m. Argentona S.l.",
    "wof:placetype":"venue"
},
  "geometry": {"coordinates":[2.0115170479,41.2989578247],"type":"Point"}
}