{
  "type": "Feature",
  "properties": {
    "addr:full":"Via Europa, 153 Mataro Barcelona 08303",
    "addr:housenumber":"153",
    "addr:postcode":"08303",
    "addr:street":"Via Europa",
    "iso:country":"ES",
    "sg:address":"Via Europa, 153",
    "sg:city":"Mataro",
    "sg:orig_category":"Arquitectos",
    "sg:phone":"+34 937 99 51 97",
    "sg:postcode":"08303",
    "sg:province":"Barcelona",
    "wof:name":"I.m.tecnics Project Management S.l.l.",
    "wof:placetype":"venue"
},
  "geometry": {"coordinates":[2.4325299263,41.5437507629],"type":"Point"}
}