{
  "type": "Feature",
  "properties": {
    "addr:full":"Creuera, 13 Tortosa Tarragona 43500",
    "addr:housenumber":"13",
    "addr:postcode":"43500",
    "addr:street":"Creuera",
    "iso:country":"ES",
    "sg:address":"Creuera, 13",
    "sg:city":"Tortosa",
    "sg:orig_category":"Alimentaci\u00d3n General (al Por Menor)",
    "sg:phone":"+34 977 44 56 57",
    "sg:postcode":"43500",
    "sg:province":"Tarragona",
    "wof:name":"Verge Verge Teresa",
    "wof:placetype":"venue"
},
  "geometry": {"coordinates":[0.5216360092,40.8142738342],"type":"Point"}
}