{
  "type": "Feature",
  "properties": {
    "addr:full":"Pl Constitucio (la), 35 Vilafranca Penedes Barcelona 08720",
    "addr:housenumber":"35",
    "addr:postcode":"08720",
    "addr:street":"Pl Constitucio La",
    "iso:country":"ES",
    "sg:address":"Pl Constitucio (la), 35",
    "sg:city":"Vilafranca Penedes",
    "sg:orig_category":"Bisuter\u00cda, Joyer\u00cda, Relojer\u00cda (al Por Menor)",
    "sg:phone":"+34 938 92 13 90",
    "sg:postcode":"08720",
    "sg:province":"Barcelona",
    "wof:name":"Lecegui Fernandez Jose",
    "wof:placetype":"venue"
},
  "geometry": {"coordinates":[1.6992199421,41.3447799683],"type":"Point"}
}