{
  "type": "Feature",
  "properties": {
    "addr:full":"Calle de Portalada (la), 1 Santurtzi Vizcaya 48980",
    "addr:postcode":"48980",
    "addr:street":"Calle De Portalada La 1",
    "iso:country":"ES",
    "sg:address":"Calle de Portalada (la), 1",
    "sg:city":"Santurtzi",
    "sg:orig_category":"Ense\u00d1anza: Idiomas",
    "sg:phone":"+34 944 83 46 96",
    "sg:postcode":"48980",
    "sg:province":"Vizcaya",
    "wof:name":"Maria Isabel Martin Albizu Academia De Idiomas",
    "wof:placetype":"venue"
},
  "geometry": {"coordinates":[-3.0341188908,43.3297348022],"type":"Point"}
}