{
  "type": "Feature",
  "properties": {
    "addr:full":"Avda Angeles (los), 27 Loja Granada 18300",
    "addr:housenumber":"27 loja",
    "addr:postcode":"18300",
    "addr:street":"Avda Angeles Los",
    "iso:country":"ES",
    "sg:address":"Avda Angeles (los), 27",
    "sg:city":"Loja",
    "sg:orig_category":"Asesor\u00cda Fiscal Y Jur\u00cddica",
    "sg:phone":"+34 958 32 02 16",
    "sg:postcode":"18300",
    "sg:province":"Granada",
    "wof:name":"Fylcon Loxa Asesores S.l.",
    "wof:placetype":"venue"
},
  "geometry": {"coordinates":[-4.1463670731,37.1648139954],"type":"Point"}
}