{
  "type": "Feature",
  "properties": {
    "iso:country":"ES",
    "sg:address":"Carrer de Sant Sebastia, 3",
    "sg:city":"Molins Rei",
    "sg:orig_category":"Textil",
    "sg:phone":"+34 936 68 51 72",
    "sg:postcode":"08750",
    "sg:province":"Barcelona",
    "wof:name":"Chatelet Dise\u00f1o S.l",
    "wof:placetype":"venue"
},
  "geometry": {"coordinates":[2.0251801014,41.4056053162],"type":"Point"}
}