{
  "type": "Feature",
  "properties": {
    "iso:country":"ES",
    "sg:address":"Carrer de Bori I Fontesta, 16",
    "sg:city":"Barcelona",
    "sg:orig_category":"Aparcamientos (infraestructuras, Accesorios)",
    "sg:phone":"+34 932 01 91 77",
    "sg:postcode":"08021",
    "sg:province":"Barcelona",
    "wof:name":"Acervo Caneque S.l.",
    "wof:placetype":"venue"
},
  "geometry": {"coordinates":[2.1393256187,41.3932113647],"type":"Point"}
}