{
  "type": "Feature",
  "properties": {
    "addr:full":"Calle de Fuenlabrada, 20 Getafe Madrid 28901",
    "addr:housenumber":"20",
    "addr:postcode":"28901",
    "addr:street":"Calle De Fuenlabrada",
    "iso:country":"ES",
    "sg:address":"Calle de Fuenlabrada, 20",
    "sg:city":"Getafe",
    "sg:orig_category":"Ense\u00d1anza, Formaci\u00d3n Profesional: Aprendizaje",
    "sg:phone":"+34 916 83 21 00",
    "sg:postcode":"28901",
    "sg:province":"Madrid",
    "wof:name":"Organismo Autonomo De Informatica Y Comunicaciones De La Comunidad De Madrid",
    "wof:placetype":"venue"
},
  "geometry": {"coordinates":[-3.7339010239,40.3033981323],"type":"Point"}
}