{
  "type": "Feature",
  "properties": {
    "addr:full":"Carrer de Pere Martell (de), 52 Tarragona Tarragona 43005",
    "addr:housenumber":"52",
    "addr:postcode":"43005",
    "addr:street":"Carrer De Pere Martell De",
    "iso:country":"ES",
    "sg:address":"Carrer de Pere Martell (de), 52",
    "sg:city":"Tarragona",
    "sg:orig_category":"Bancos",
    "sg:phone":"+34 977 22 03 08",
    "sg:postcode":"43005",
    "sg:province":"Tarragona",
    "sg:website":"www.bancopopular.es",
    "wof:name":"Banco Popular Espa\u00f1ol",
    "wof:placetype":"venue"
},
  "geometry": {"coordinates":[1.2432750463,41.1127510071],"type":"Point"}
}