{
  "type": "Feature",
  "properties": {
    "iso:country":"ES",
    "sg:address":"Avda Jorge Bonsor, 10",
    "sg:city":"Carmona",
    "sg:orig_category":"Producci\u00d3n, Comercio De Cereales",
    "sg:phone":"+34 954 14 01 92",
    "sg:postcode":"41410",
    "sg:province":"Sevilla",
    "wof:name":"Gabriel Avila S.l.",
    "wof:placetype":"venue"
},
  "geometry": {"coordinates":[-5.649075985,37.4687767029],"type":"Point"}
}