{
  "type": "Feature",
  "properties": {
    "iso:country":"ES",
    "sg:address":"Ctra Pinilla De Buitrago (de), Km. 0001,6",
    "sg:city":"San Mames",
    "sg:orig_category":"Ense\u00d1anza, Formaci\u00d3n Profesional: Aprendizaje",
    "sg:phone":"+34 918 69 53 07",
    "sg:postcode":"28739",
    "sg:province":"Madrid",
    "wof:name":"Fundacion Hospital San Salvador-escuela Taller San Francisco De Asis",
    "wof:placetype":"venue"
},
  "geometry": {"coordinates":[-3.7090079784,40.9914360046],"type":"Point"}
}