{
  "type": "Feature",
  "properties": {
    "iso:country":"ES",
    "sg:address":"Calle de Colon, 23",
    "sg:city":"Zamora",
    "sg:orig_category":"Lavado, Limpieza De Veh\u00cdculos",
    "sg:phone":"+34 980 52 17 15",
    "sg:postcode":"49019",
    "sg:province":"Zamora",
    "wof:name":"Urue\u00f1a Teson Luis",
    "wof:placetype":"venue"
},
  "geometry": {"coordinates":[-5.7323198318,41.5107574463],"type":"Point"}
}