{
  "type": "Feature",
  "properties": {
    "iso:country":"ES",
    "sg:address":"Avda Daganzo, 12",
    "sg:city":"Alcala Henares",
    "sg:orig_category":"Distribuci\u00d3n De Petr\u00d3leo Y Derivados",
    "sg:phone":"+34 918 88 38 14",
    "sg:postcode":"28806",
    "sg:province":"Madrid",
    "sg:website":"www.cepsa.es",
    "wof:name":"Lorenzo Pardo E Hijos S.l.",
    "wof:placetype":"venue"
},
  "geometry": {"coordinates":[-3.3793439865,40.4924926758],"type":"Point"}
}