{
  "type": "Feature",
  "properties": {
    "iso:country":"ES",
    "sg:address":"Calle de Almas, 2",
    "sg:city":"Segorbe",
    "sg:orig_category":"Procuradores",
    "sg:phone":"+34 964 71 33 15",
    "sg:postcode":"12400",
    "sg:province":"Castell\u00f3n",
    "wof:name":"Domingo Hernanz Julia",
    "wof:placetype":"venue"
},
  "geometry": {"coordinates":[-0.4852190912,39.8533096313],"type":"Point"}
}