{
  "type": "Feature",
  "properties": {
    "iso:country":"ES",
    "sg:address":"Ctra Marcosende, S/n",
    "sg:city":"Marcosende",
    "sg:orig_category":"Supermercados Y Hipermercados",
    "sg:phone":"+34 986 46 70 96",
    "sg:postcode":"36310",
    "sg:province":"Pontevedra",
    "wof:name":"Tenda Universitaria De Vigo S.l.u.",
    "wof:placetype":"venue"
},
  "geometry": {"coordinates":[-8.6795969009,42.1573181152],"type":"Point"}
}