{
  "type": "Feature",
  "properties": {
    "addr:full":"Avda Iparralde, 16 Irun Guip\u00f9zcoa 20304",
    "addr:housenumber":"16",
    "addr:postcode":"20304",
    "addr:street":"Avda Iparralde;Guipu\u0300Zcoa",
    "iso:country":"ES",
    "sg:address":"Avda Iparralde, 16",
    "sg:city":"Irun",
    "sg:orig_category":"Electricidad Veh\u00cdculo",
    "sg:phone":"+34 943 62 00 40",
    "sg:postcode":"20304",
    "sg:province":"Guip\u00f9zcoa",
    "wof:name":"Nicolas Del Rio Antonio",
    "wof:placetype":"venue"
},
  "geometry": {"coordinates":[-1.7881720066,43.3446121216],"type":"Point"}
}