{
  "type": "Feature",
  "properties": {
    "addr:full":"Calle de Emilio Prados, 6 Sevilla Sevilla 41008",
    "addr:housenumber":"6",
    "addr:postcode":"41008",
    "addr:street":"Calle De Emilio Prados",
    "iso:country":"ES",
    "sg:address":"Calle de Emilio Prados, 6",
    "sg:city":"Sevilla",
    "sg:orig_category":"Librer\u00cdas",
    "sg:phone":"+34 954 35 89 11",
    "sg:postcode":"41008",
    "sg:province":"Sevilla",
    "wof:name":"Moreno Ramirez Maria Jesus",
    "wof:placetype":"venue"
},
  "geometry": {"coordinates":[-5.9748439789,37.4059486389],"type":"Point"}
}