{
  "type": "Feature",
  "properties": {
    "iso:country":"ES",
    "sg:address":"Carr Bellpuig, 56",
    "sg:city":"Felanitx",
    "sg:orig_category":"Art\u00cdculos De Regalo (al Por Menor)",
    "sg:phone":"+34 971 58 15 74",
    "sg:postcode":"07200",
    "sg:province":"Islas Baleares",
    "wof:name":"Oliver Mestre Francisca",
    "wof:placetype":"venue"
},
  "geometry": {"coordinates":[3.1571409702,39.4732131958],"type":"Point"}
}