{
  "type": "Feature",
  "properties": {
    "iso:country":"ES",
    "sg:address":"Calle de Pico De Los Artilleros, 116",
    "sg:city":"Madrid",
    "sg:orig_category":"Inform\u00c1tica: Consultores",
    "sg:phone":"+34 913 71 52 80",
    "sg:postcode":"28030",
    "sg:province":"Madrid",
    "wof:name":"Grupo Asociados Nusadua S.l.",
    "wof:placetype":"venue"
},
  "geometry": {"coordinates":[-3.6412351131,40.4060668945],"type":"Point"}
}