{
  "type": "Feature",
  "properties": {
    "iso:country":"ES",
    "sg:address":"Calle de Escofina, 36",
    "sg:city":"Estacion",
    "sg:orig_category":"Farmacias",
    "sg:phone":"+34 918 49 01 67",
    "sg:postcode":"28400",
    "sg:province":"Madrid",
    "wof:name":"Moreno Olmedo Manuel",
    "wof:placetype":"venue"
},
  "geometry": {"coordinates":[-4.01836586,40.6269798279],"type":"Point"}
}