{
  "type": "Feature",
  "properties": {
    "addr:full":"Carrer de Maresme, 230 Barcelona Barcelona 08020",
    "addr:housenumber":"230",
    "addr:postcode":"08020",
    "addr:street":"Carrer De Maresme",
    "iso:country":"ES",
    "sg:address":"Carrer de Maresme, 230",
    "sg:city":"Barcelona",
    "sg:orig_category":"Comerciantes Al Por Mayor De Vinos, Licores Y Alcoholes",
    "sg:phone":"+34 933 14 17 16",
    "sg:postcode":"08020",
    "sg:province":"Barcelona",
    "wof:name":"Rodriguez Garcia Maria",
    "wof:placetype":"venue"
},
  "geometry": {"coordinates":[2.2050800323,41.4205131531],"type":"Point"}
}