{
  "type": "Feature",
  "properties": {
    "addr:full":"Calle de Pedro Laborde, 15 Madrid Madrid 28038",
    "addr:housenumber":"15",
    "addr:postcode":"madrid;28038",
    "addr:street":"Calle De Pedro Laborde",
    "iso:country":"ES",
    "sg:address":"Calle de Pedro Laborde, 15",
    "sg:city":"Madrid",
    "sg:orig_category":"Librer\u00cdas",
    "sg:phone":"+34 913 03 77 07",
    "sg:postcode":"28038",
    "sg:province":"Madrid",
    "wof:name":"Quiros Pinel Emilia",
    "wof:placetype":"venue"
},
  "geometry": {"coordinates":[-3.6476318836,40.3888320923],"type":"Point"}
}