{
  "type": "Feature",
  "properties": {
    "iso:country":"ES",
    "sg:address":"Cmno Migueles (los), S/n",
    "sg:city":"Buzanada",
    "sg:orig_category":"Equitaci\u00d3n Y Centros De H\u00cdpica",
    "sg:phone":"+34 922 72 06 43",
    "sg:postcode":"38626",
    "sg:province":"Santa Cruz De Tenerife",
    "wof:name":"Hernandez Vayes Pedro",
    "wof:placetype":"venue"
},
  "geometry": {"coordinates":[-16.6597824097,28.0691337585],"type":"Point"}
}