{
  "type": "Feature",
  "properties": {
    "iso:country":"ES",
    "sg:address":"Region Murciana(base Dos Mil), 4",
    "sg:city":"Lorqui",
    "sg:orig_category":"Material Y Herramientas Agr\u00cdcolas",
    "sg:phone":"+34 968 69 41 77",
    "sg:postcode":"30564",
    "sg:province":"Murcia",
    "wof:name":"Agrosegura Maquinaria S.l.",
    "wof:placetype":"venue"
},
  "geometry": {"coordinates":[-1.2554111481,38.104057312],"type":"Point"}
}