{
  "type": "Feature",
  "properties": {
    "iso:country":"ES",
    "sg:address":"Carrer de Emili Vendrell (d'), S/n",
    "sg:city":"Pineda",
    "sg:orig_category":"Alquiler De Casas Y Habitaciones Amuebladas",
    "sg:phone":"+34 977 37 04 84",
    "sg:postcode":"43480",
    "sg:province":"Tarragona",
    "wof:name":"Cye Salou S.a.",
    "wof:placetype":"venue"
},
  "geometry": {"coordinates":[1.1441899538,41.1080245972],"type":"Point"}
}