{
  "type": "Feature",
  "properties": {
    "addr:full":"Avda Teodomiro, 21 Orihuela Alicante 03300",
    "addr:housenumber":"21",
    "addr:postcode":"03300",
    "addr:street":"Avda Teodomiro",
    "iso:country":"ES",
    "sg:address":"Avda Teodomiro, 21",
    "sg:city":"Orihuela",
    "sg:orig_category":"Agencias Y Agentes Comerciales, Representantes",
    "sg:phone":"+34 966 74 05 98",
    "sg:postcode":"03300",
    "sg:province":"Alicante",
    "wof:name":"Fabregat Paya Jose",
    "wof:placetype":"venue"
},
  "geometry": {"coordinates":[-0.9454860091,38.0809783936],"type":"Point"}
}