{
  "type": "Feature",
  "properties": {
    "addr:full":"Calle de Castellar, 19 Angeles C\u00e1diz 11330",
    "addr:housenumber":"19",
    "addr:postcode":"11330",
    "addr:street":"Calle De Castellar",
    "iso:country":"ES",
    "sg:address":"Calle de Castellar, 19",
    "sg:city":"Angeles",
    "sg:orig_category":"Negocio De Materiales De Construcci\u00d3n",
    "sg:phone":"+34 956 64 00 15",
    "sg:postcode":"11330",
    "sg:province":"C\u00e1diz",
    "wof:name":"Macias Sanchez Jose Maria",
    "wof:placetype":"venue"
},
  "geometry": {"coordinates":[-5.4363894463,36.4231109619],"type":"Point"}
}