{
  "type": "Feature",
  "properties": {
    "addr:full":"Carrer de Sant Antoni, 37 Valls Tarragona 43800",
    "addr:housenumber":"37",
    "addr:postcode":"43800",
    "addr:street":"Carrer De Sant Antoni",
    "iso:country":"ES",
    "sg:address":"Carrer de Sant Antoni, 37",
    "sg:city":"Valls",
    "sg:orig_category":"Carnicer\u00cdas, Carnicer\u00cdas",
    "sg:phone":"+34 977 60 12 41",
    "sg:postcode":"43800",
    "sg:province":"Tarragona",
    "wof:name":"Montala Mercade Maribel",
    "wof:placetype":"venue"
},
  "geometry": {"coordinates":[1.2489980459,41.283706665],"type":"Point"}
}