{
  "type": "Feature",
  "properties": {
    "iso:country":"ES",
    "sg:address":"Avda Andalucia, 36",
    "sg:city":"Atarfe",
    "sg:orig_category":"Bisuter\u00cda, Joyer\u00cda, Relojer\u00cda (al Por Menor)",
    "sg:phone":"+34 958 43 88 38",
    "sg:postcode":"18230",
    "sg:province":"Granada",
    "wof:name":"Perez Castro Cyra",
    "wof:placetype":"venue"
},
  "geometry": {"coordinates":[-3.6859340668,37.2228469849],"type":"Point"}
}