{
  "type": "Feature",
  "properties": {
    "iso:country":"ES",
    "sg:address":"Calle de Panama, 3",
    "sg:city":"Madrid",
    "sg:orig_category":"M\u00c9dicos: Cirug\u00cda Pl\u00c1stica, Reconstructiva Y Est\u00c9tica",
    "sg:phone":"+34 914 58 72 52",
    "sg:postcode":"28036",
    "sg:province":"Madrid",
    "wof:name":"Jimenez Garcia Elena",
    "wof:placetype":"venue"
},
  "geometry": {"coordinates":[-3.6879563332,40.456703186],"type":"Point"}
}