{
  "type": "Feature",
  "properties": {
    "addr:full":"Ctra Montaverner (de), S/n Olleria Valencia 46850",
    "addr:postcode":"46850",
    "addr:street":"Ctra Montaverner De S / N",
    "iso:country":"ES",
    "sg:address":"Ctra Montaverner (de), S/n",
    "sg:city":"Olleria",
    "sg:orig_category":"Fabricaci\u00d3n De Taburetes, Sillas Y Sillones",
    "sg:phone":"+34 962 20 13 83",
    "sg:postcode":"46850",
    "sg:province":"Valencia",
    "wof:name":"Casanova Valls Juan",
    "wof:placetype":"venue"
},
  "geometry": {"coordinates":[-0.5401989818,38.9090194702],"type":"Point"}
}