{
  "type": "Feature",
  "properties": {
    "iso:country":"ES",
    "sg:address":"Carrer de Providencia, 27",
    "sg:city":"S. Boi Llobregat",
    "sg:orig_category":"Ropa Para Se\u00d1oras (al Por Menor)",
    "sg:phone":"+34 936 30 34 36",
    "sg:postcode":"08830",
    "sg:province":"Barcelona",
    "wof:name":"Garcia Pascual Ascencion",
    "wof:placetype":"venue"
},
  "geometry": {"coordinates":[2.0296940804,41.3488082886],"type":"Point"}
}