{
  "type": "Feature",
  "properties": {
    "iso:country":"ES",
    "sg:address":"Iturrama, 34",
    "sg:city":"Iru\u00f1a",
    "sg:orig_category":"Ropa Para Se\u00d1oras (al Por Menor)",
    "sg:phone":"+34 948 27 76 17",
    "sg:postcode":"31007",
    "sg:province":"Navarra",
    "wof:name":"Kretta S.i",
    "wof:placetype":"venue"
},
  "geometry": {"coordinates":[-1.6556689739,42.8066711426],"type":"Point"}
}