{
  "type": "Feature",
  "properties": {
    "addr:full":"Avda Fuente Del Maestre, 4 Zafra Badajoz 06300",
    "addr:housenumber":"4",
    "addr:postcode":"06300",
    "addr:street":"Avda Fuente Del Maestre",
    "iso:country":"ES",
    "sg:address":"Avda Fuente Del Maestre, 4",
    "sg:city":"Zafra",
    "sg:orig_category":"M\u00c9dicos: Oftalmolog\u00cda",
    "sg:phone":"+34 924 55 50 88",
    "sg:postcode":"06300",
    "sg:province":"Badajoz",
    "wof:name":"Espejo Marquez Jose Jacinto",
    "wof:placetype":"venue"
},
  "geometry": {"coordinates":[-6.417318821,38.426990509],"type":"Point"}
}