{
  "type": "Feature",
  "properties": {
    "iso:country":"ES",
    "sg:address":"Pla\u00c7 Constitucio, 2",
    "sg:city":"Felanitx",
    "sg:orig_category":"M\u00c9dicos: Estomatolog\u00cda",
    "sg:phone":"+34 971 58 11 08",
    "sg:postcode":"07200",
    "sg:province":"Islas Baleares",
    "wof:name":"Barcelo Ramonell Gabriel",
    "wof:placetype":"venue"
},
  "geometry": {"coordinates":[3.1523449421,39.4752311707],"type":"Point"}
}