{
  "type": "Feature",
  "properties": {
    "addr:full":"Calle de Resejo, 8 Ria\u00f1o Le\u00f3n 24900",
    "addr:housenumber":"8",
    "addr:postcode":"24900",
    "addr:street":"Calle De Resejo;Leo\u0301N",
    "iso:country":"ES",
    "sg:address":"Calle de Resejo, 8",
    "sg:city":"Ria\u00f1o",
    "sg:orig_category":"Supermercados Y Hipermercados",
    "sg:phone":"+34 987 74 06 82",
    "sg:postcode":"24900",
    "sg:province":"Le\u00f3n",
    "wof:name":"Garcia De Celis Mauricio",
    "wof:placetype":"venue"
},
  "geometry": {"coordinates":[-5.0033960342,42.9769210815],"type":"Point"}
}