{
  "type": "Feature",
  "properties": {
    "iso:country":"ES",
    "sg:address":"Calle de Huete, 22",
    "sg:city":"Ceuti",
    "sg:orig_category":"Laboratorios Y Trabajos De Fotograf\u00cda, V\u00cddeo Y Cine",
    "sg:phone":"+34 968 69 33 42",
    "sg:postcode":"30562",
    "sg:province":"Murcia",
    "wof:name":"Bolarin Nieto Antonia",
    "wof:placetype":"venue"
},
  "geometry": {"coordinates":[-1.2729250193,38.0785713196],"type":"Point"}
}