{
  "type": "Feature",
  "properties": {
    "addr:full":"Calle de Jesus Alvarez, 65 Alzira Valencia 46600",
    "addr:housenumber":"65",
    "addr:postcode":"46600",
    "addr:street":"Calle De Jesus Alvarez",
    "iso:country":"ES",
    "sg:address":"Calle de Jesus Alvarez, 65",
    "sg:city":"Alzira",
    "sg:orig_category":"Panader\u00cdas, Panader\u00cdas",
    "sg:phone":"+34 962 40 24 98",
    "sg:postcode":"46600",
    "sg:province":"Valencia",
    "wof:name":"Llopis Perez Salvador Enrique",
    "wof:placetype":"venue"
},
  "geometry": {"coordinates":[-0.4279600084,39.1552085876],"type":"Point"}
}