{
  "type": "Feature",
  "properties": {
    "addr:full":"Calle de Canonigo, 10 Dos Hermanas Sevilla 41700",
    "addr:housenumber":"10",
    "addr:postcode":"41700",
    "addr:street":"Calle De Canonigo",
    "iso:country":"ES",
    "sg:address":"Calle de Canonigo, 10",
    "sg:city":"Dos Hermanas",
    "sg:orig_category":"Ingeniero",
    "sg:phone":"+34 955 66 15 45",
    "sg:postcode":"41700",
    "sg:province":"Sevilla",
    "wof:name":"Martinez Monta\u00f1o Manuel",
    "wof:placetype":"venue"
},
  "geometry": {"coordinates":[-5.9240002632,37.2857627869],"type":"Point"}
}