{
  "type": "Feature",
  "properties": {
    "addr:full":"O Vilar De Calo, 41 Vilar De Calo La Coru\u00f1a 15895",
    "addr:housenumber":"41",
    "addr:postcode":"15895",
    "addr:street":"O Vilar De Calo;Calo;Corun\u0303A",
    "iso:country":"ES",
    "sg:address":"O Vilar De Calo, 41",
    "sg:city":"Vilar De Calo",
    "sg:orig_category":"Prot\u00c9sicos Dentales",
    "sg:phone":"+34 981 53 10 15",
    "sg:postcode":"15895",
    "sg:province":"La Coru\u00f1a",
    "wof:name":"Perez Gippini I\u00f1igo",
    "wof:placetype":"venue"
},
  "geometry": {"coordinates":[-8.5794343948,42.8416137695],"type":"Point"}
}