{
  "type": "Feature",
  "properties": {
    "addr:full":"Calle de Madre De Dios, 52 Arahal Sevilla 41600",
    "addr:housenumber":"52",
    "addr:postcode":"41600",
    "addr:street":"Calle De Madre;Dios",
    "iso:country":"ES",
    "sg:address":"Calle de Madre De Dios, 52",
    "sg:city":"Arahal",
    "sg:orig_category":"Carnicer\u00cdas, Carnicer\u00cdas",
    "sg:phone":"+34 954 84 06 35",
    "sg:postcode":"41600",
    "sg:province":"Sevilla",
    "wof:name":"Jamones Benito Garcia S.a.",
    "wof:placetype":"venue"
},
  "geometry": {"coordinates":[-5.543410778,37.2603607178],"type":"Point"}
}