{
  "type": "Feature",
  "properties": {
    "addr:full":"Carrer de Arcadia, 14 Sabadell Barcelona 08206",
    "addr:housenumber":"14",
    "addr:postcode":"08206",
    "addr:street":"Carrer De Arcadia",
    "iso:country":"ES",
    "sg:address":"Carrer de Arcadia, 14",
    "sg:city":"Sabadell",
    "sg:orig_category":"Distribuci\u00d3n De Petr\u00d3leo Y Derivados",
    "sg:phone":"+34 937 16 20 24",
    "sg:postcode":"08206",
    "sg:province":"Barcelona",
    "wof:name":"Via Arcadia S.l.",
    "wof:placetype":"venue"
},
  "geometry": {"coordinates":[2.0904328823,41.5546531677],"type":"Point"}
}