{
  "type": "Feature",
  "properties": {
    "iso:country":"ES",
    "sg:address":"Calle de Industria (la), 57",
    "sg:city":"Astillero",
    "sg:orig_category":"Centros De Educaci\u00d3n Especial",
    "sg:phone":"+34 942 55 81 77",
    "sg:postcode":"39610",
    "sg:province":"Cantabria",
    "wof:name":"Centro De Educacion Permanente De Adultos El Astillero",
    "wof:placetype":"venue"
},
  "geometry": {"coordinates":[-3.817581892,43.3960647583],"type":"Point"}
}