{
  "type": "Feature",
  "properties": {
    "addr:full":"Ctr. Landete-utiel, Km. 0220,0 Talayuelas Cuenca 16320",
    "addr:postcode":"16320",
    "addr:street":"Landete-Utiel Km. 0220,0",
    "iso:country":"ES",
    "sg:address":"Ctr. Landete-utiel, Km. 0220,0",
    "sg:city":"Talayuelas",
    "sg:classifiers":[
        {
            "category":"Manufacturing",
            "subcategory":"Building Materials",
            "type":"Manufacturing & Wholesale Goods"
        }
    ],
    "sg:phone":"+34 969 14 40 30",
    "sg:postcode":"16320",
    "sg:province":"Cuenca",
    "sg:tags":[
        "cemento",
        "y",
        "de",
        "fabricaci\u00d3n",
        "cal"
    ],
    "wof:name":"Hercucas S.l.",
    "wof:placetype":"venue"
},
  "geometry": {"coordinates":[-1.2841750383,39.8494186401],"type":"Point"}
}