{
  "type": "Feature",
  "properties": {
    "addr:full":"Calle de Roque Barcia, 15 Huelva Huelva 21003",
    "addr:housenumber":"15",
    "addr:postcode":"21003",
    "addr:street":"Calle De Roque Barcia",
    "iso:country":"ES",
    "sg:address":"Calle de Roque Barcia, 15",
    "sg:city":"Huelva",
    "sg:orig_category":"Agencias Y Agentes Comerciales, Representantes",
    "sg:phone":"+34 959 23 18 15",
    "sg:postcode":"21003",
    "sg:province":"Huelva",
    "wof:name":"Burguillos Martin Juan Maria",
    "wof:placetype":"venue"
},
  "geometry": {"coordinates":[-6.9368438721,37.2554092407],"type":"Point"}
}