{
  "type": "Feature",
  "properties": {
    "addr:full":"Calle de Santa Clara, 2 Bilbao Vizcaya 48006",
    "addr:housenumber":"2",
    "addr:postcode":"48006",
    "addr:street":"Calle De Santa Clara",
    "iso:country":"ES",
    "sg:address":"Calle de Santa Clara, 2",
    "sg:city":"Bilbao",
    "sg:orig_category":"Fabricaci\u00d3n, Venta De Cuadros, Accesorios Para Enmarcar",
    "sg:phone":"+34 944 12 56 86",
    "sg:postcode":"48006",
    "sg:province":"Vizcaya",
    "wof:name":"Agustin Garrido Bautista",
    "wof:placetype":"venue"
},
  "geometry": {"coordinates":[-2.9188439846,43.2573242188],"type":"Point"}
}