{
  "type": "Feature",
  "properties": {
    "iso:country":"ES",
    "sg:address":"Ctra Tamajon, S/n",
    "sg:city":"Yunquera Henares",
    "sg:orig_category":"Cerrajer\u00cda, Ferrallista",
    "sg:phone":"+34 949 33 00 22",
    "sg:postcode":"19210",
    "sg:province":"Guadalajara",
    "wof:name":"Union De Cerrajeros S.a.l.",
    "wof:placetype":"venue"
},
  "geometry": {"coordinates":[-3.1744329929,40.7602844238],"type":"Point"}
}