{
  "type": "Feature",
  "properties": {
    "iso:country":"ES",
    "sg:address":"Avda Toledo, 6",
    "sg:city":"Nombela",
    "sg:orig_category":"Electricidad: Instaladores",
    "sg:phone":"+34 925 79 23 10",
    "sg:postcode":"45917",
    "sg:province":"Toledo",
    "wof:name":"Diaz Jimenez Jose Javier",
    "wof:placetype":"venue"
},
  "geometry": {"coordinates":[-4.5091848373,40.153678894],"type":"Point"}
}