{
  "type": "Feature",
  "properties": {
    "iso:country":"ES",
    "sg:address":"Calle de Labradores, 54",
    "sg:city":"Maello",
    "sg:orig_category":"Cerrajer\u00cda, Ferrallista",
    "sg:phone":"+34 921 19 20 95",
    "sg:postcode":"05291",
    "sg:province":"\u00c1vila",
    "wof:name":"Martin Cristobal Jesus",
    "wof:placetype":"venue"
},
  "geometry": {"coordinates":[-4.508559227,40.8077087402],"type":"Point"}
}