{
  "type": "Feature",
  "properties": {
    "addr:full":"Calle de Jose Luis Diez, 9 Jerez De La Frontera C\u00e1diz 11403",
    "addr:housenumber":"9",
    "addr:postcode":"11403",
    "addr:street":"Calle De Jose Luis Diez",
    "iso:country":"ES",
    "sg:address":"Calle de Jose Luis Diez, 9",
    "sg:city":"Jerez De La Frontera",
    "sg:orig_category":"Calzados Ortop\u00c9dicos",
    "sg:phone":"+34 956 33 52 04",
    "sg:postcode":"11403",
    "sg:province":"C\u00e1diz",
    "wof:name":"Ortopedia Medica Jerezana S.l.",
    "wof:placetype":"venue"
},
  "geometry": {"coordinates":[-6.1394920349,36.6829299927],"type":"Point"}
}