{
  "type": "Feature",
  "properties": {
    "iso:country":"ES",
    "sg:address":"Calle de Vega (la), 6",
    "sg:city":"Trillo",
    "sg:orig_category":"Cajas De Ahorro",
    "sg:phone":"+34 949 81 50 82",
    "sg:postcode":"19450",
    "sg:province":"Guadalajara",
    "wof:name":"Caja De Ahorro Provincial De Guadalajara",
    "wof:placetype":"venue"
},
  "geometry": {"coordinates":[-2.5915679932,40.7016601562],"type":"Point"}
}