{
  "type": "Feature",
  "properties": {
    "iso:country":"ES",
    "sg:address":"Carrer de Major, 30",
    "sg:city":"Roquetes",
    "sg:orig_category":"Inmobiliaria (agencias)",
    "sg:phone":"+34 977 50 43 96",
    "sg:postcode":"43520",
    "sg:province":"Tarragona",
    "wof:name":"Finques Ebre-mont S.l.",
    "wof:placetype":"venue"
},
  "geometry": {"coordinates":[0.5034400225,40.8200302124],"type":"Point"}
}