{
  "type": "Feature",
  "properties": {
    "iso:country":"ES",
    "sg:address":"Avda Virgen (de La), 3",
    "sg:city":"Villarrubia De Los Ojos",
    "sg:orig_category":"Chapister\u00cda",
    "sg:phone":"+34 926 89 71 77",
    "sg:postcode":"13670",
    "sg:province":"Ciudad Real",
    "wof:name":"Patrimaren S.l.u",
    "wof:placetype":"venue"
},
  "geometry": {"coordinates":[-3.6121239662,39.2139816284],"type":"Point"}
}