{
  "type": "Feature",
  "properties": {
    "iso:country":"ES",
    "sg:address":"Carrer de Roc Boronat, 115",
    "sg:city":"Barcelona",
    "sg:classifiers":[
        {
            "category":"Banks & Credit Unions",
            "subcategory":"Bureau De Change",
            "type":"Services"
        }
    ],
    "sg:phone":"+34 933 20 80 15",
    "sg:postcode":"08018",
    "sg:province":"Barcelona",
    "sg:tags":[
        "organismos",
        "control"
    ],
    "wof:name":"Eptisa Enginyeria I Serveis S.a.",
    "wof:placetype":"venue"
},
  "geometry": {"coordinates":[2.1949930191,41.4022216797],"type":"Point"}
}