{
  "type": "Feature",
  "properties": {
    "addr:full":"Rua Castelao, 150 Grove Pontevedra 36980",
    "addr:housenumber":"150",
    "addr:postcode":"36980",
    "addr:street":"Rua Castelao;Grove Pontevedra",
    "iso:country":"ES",
    "sg:address":"Rua Castelao, 150",
    "sg:city":"Grove",
    "sg:orig_category":"Restaurantes",
    "sg:phone":"+34 986 73 18 42",
    "sg:postcode":"36980",
    "sg:province":"Pontevedra",
    "wof:name":"Prieto Devesa Marisol",
    "wof:placetype":"venue"
},
  "geometry": {"coordinates":[-8.858259201,42.4904518127],"type":"Point"}
}