{
  "type": "Feature",
  "properties": {
    "iso:country":"ES",
    "sg:address":"Plaz Luis Bu\u00d1uel, 9",
    "sg:city":"Huelva",
    "sg:orig_category":"Molduras, Junquillos, Listones Y Molduras Perforadas",
    "sg:phone":"+34 959 15 23 01",
    "sg:postcode":"21005",
    "sg:province":"Huelva",
    "wof:name":"Sema Hosteleria S.l.",
    "wof:placetype":"venue"
},
  "geometry": {"coordinates":[-6.9067587852,37.3151283264],"type":"Point"}
}