{
  "type": "Feature",
  "properties": {
    "iso:country":"ES",
    "sg:address":"Calle de San Francisco, 6",
    "sg:city":"Talavera Reina",
    "sg:orig_category":"Peleter\u00cdas",
    "sg:phone":"+34 925 83 01 15",
    "sg:postcode":"45600",
    "sg:province":"Toledo",
    "sg:website":"www.hervaspiel.com",
    "wof:name":"Hervas Piel S. A.",
    "wof:placetype":"venue"
},
  "geometry": {"coordinates":[-4.8305888176,39.9603424072],"type":"Point"}
}