{
  "type": "Feature",
  "properties": {
    "addr:full":"Plaz Constitucion (de La), 12 Carpio C\u00f3rdoba 14620",
    "addr:postcode":"14620",
    "addr:street":"Co\u0301Rdoba",
    "iso:country":"ES",
    "sg:address":"Plaz Constitucion (de La), 12",
    "sg:city":"Carpio",
    "sg:orig_category":"Electricidad: Instaladores",
    "sg:phone":"+34 957 18 01 91",
    "sg:postcode":"14620",
    "sg:province":"C\u00f3rdoba",
    "wof:name":"Electroreparaciones Carranza C.b.",
    "wof:placetype":"venue"
},
  "geometry": {"coordinates":[-4.4988470078,37.9402809143],"type":"Point"}
}