{
  "type": "Feature",
  "properties": {
    "addr:full":"Cmno Hoya Calvo, 162 Fronton Las Palmas 35420",
    "addr:housenumber":"162",
    "addr:postcode":"35420",
    "addr:street":"Cmno Hoya Calvo",
    "iso:country":"ES",
    "sg:address":"Cmno Hoya Calvo, 162",
    "sg:city":"Fronton",
    "sg:orig_category":"Centros De Educaci\u00d3n Especial",
    "sg:phone":"+34 928 61 10 57",
    "sg:postcode":"35420",
    "sg:province":"Las Palmas",
    "wof:name":"Gobierno De Canarias",
    "wof:placetype":"venue"
},
  "geometry": {"coordinates":[-15.5827121735,28.109287262],"type":"Point"}
}