{
  "type": "Feature",
  "properties": {
    "addr:full":"Pl Carme, 7 Tarrega Lleida 25300",
    "addr:housenumber":"7",
    "addr:postcode":"25300",
    "addr:street":"Pl Carme",
    "iso:country":"ES",
    "sg:address":"Pl Carme, 7",
    "sg:city":"Tarrega",
    "sg:orig_category":"Telas Y Sedas (al Por Menor)",
    "sg:phone":"+34 973 31 07 76",
    "sg:postcode":"25300",
    "sg:province":"Lleida",
    "wof:name":"Maymo Parareda Roman",
    "wof:placetype":"venue"
},
  "geometry": {"coordinates":[1.1395900249,41.6472434998],"type":"Point"}
}