{
  "type": "Feature",
  "properties": {
    "addr:full":"Calle de Doctor Limon, 8 Puertollano Ciudad Real 13500",
    "addr:housenumber":"8",
    "addr:postcode":"13500",
    "addr:street":"Calle De Doctor Limon",
    "iso:country":"ES",
    "sg:address":"Calle de Doctor Limon, 8",
    "sg:city":"Puertollano",
    "sg:classifiers":[
        {
            "category":"Banks & Credit Unions",
            "subcategory":"Bureau De Change",
            "type":"Services"
        }
    ],
    "sg:phone":"+34 926 41 40 09",
    "sg:postcode":"13500",
    "sg:province":"Ciudad Real",
    "sg:tags":[
        "organismos",
        "control"
    ],
    "wof:name":"Ingenieros Asesores S.a.",
    "wof:placetype":"venue"
},
  "geometry": {"coordinates":[-4.1116981506,38.6867027283],"type":"Point"}
}