{
  "type": "Feature",
  "properties": {
    "addr:full":"Carrer de Sant Gaieta, 75 Terrassa Barcelona 08221",
    "addr:housenumber":"75",
    "addr:postcode":"08221",
    "addr:street":"Carrer De Sant Gaieta",
    "iso:country":"ES",
    "sg:address":"Carrer de Sant Gaieta, 75",
    "sg:city":"Terrassa",
    "sg:orig_category":"Arquitectos",
    "sg:phone":"+34 937 33 14 26",
    "sg:postcode":"08221",
    "sg:province":"Barcelona",
    "wof:name":"Arquitectos Arab S.c.c.l.",
    "wof:placetype":"venue"
},
  "geometry": {"coordinates":[2.0092163086,41.568157196],"type":"Point"}
}