{
  "type": "Feature",
  "properties": {
    "addr:full":"Calle de Coru\u00d1a, 8 Laracha La Coru\u00f1a 15145",
    "addr:housenumber":"8",
    "addr:postcode":"15145",
    "addr:street":"Calle De Corun\u0303A;La Corun\u0303A",
    "iso:country":"ES",
    "sg:address":"Calle de Coru\u00d1a, 8",
    "sg:city":"Laracha",
    "sg:orig_category":"Electrodom\u00c9sticos (al Por Menor)",
    "sg:phone":"+34 981 60 53 68",
    "sg:postcode":"15145",
    "sg:province":"La Coru\u00f1a",
    "wof:name":"Jose Manuel Pallas Vazquez Y Otro S.c.",
    "wof:placetype":"venue"
},
  "geometry": {"coordinates":[-8.5857257843,43.2482452393],"type":"Point"}
}