{
  "type": "Feature",
  "properties": {
    "iso:country":"ES",
    "sg:address":"Calle de Puerto De Navacerrada, 4",
    "sg:city":"Arroyomolinos",
    "sg:orig_category":"Confecci\u00d3n De Zapatillas",
    "sg:phone":"+34 916 47 97 76",
    "sg:postcode":"28939",
    "sg:province":"Madrid",
    "sg:website":"www.skechers.com",
    "wof:name":"Skechers Usa Iberia S.l.",
    "wof:placetype":"venue"
},
  "geometry": {"coordinates":[-3.9287240505,40.3007850647],"type":"Point"}
}