{
  "type": "Feature",
  "properties": {
    "addr:full":"Rua Zamora, 89 Vigo Pontevedra 36211",
    "addr:housenumber":"89",
    "addr:postcode":"36211",
    "addr:street":"Rua Zamora",
    "iso:country":"ES",
    "sg:address":"Rua Zamora, 89",
    "sg:city":"Vigo",
    "sg:orig_category":"Peluquer\u00cdas, Peluquer\u00cda Mixta",
    "sg:phone":"+34 986 42 32 67",
    "sg:postcode":"36211",
    "sg:province":"Pontevedra",
    "wof:name":"Peluqueria Ramon Blanco S.l.",
    "wof:placetype":"venue"
},
  "geometry": {"coordinates":[-8.7283649445,42.2220153809],"type":"Point"}
}