{
  "type": "Feature",
  "properties": {
    "iso:country":"ES",
    "sg:address":"Calle de Mato, S/n",
    "sg:city":"Aracena",
    "sg:orig_category":"Empresas De Carpinter\u00cda Met\u00c1lica",
    "sg:phone":"+34 959 12 75 79",
    "sg:postcode":"21200",
    "sg:province":"Huelva",
    "wof:name":"Guerra Sanchez Felipe",
    "wof:placetype":"venue"
},
  "geometry": {"coordinates":[-6.5650939941,37.8961982727],"type":"Point"}
}