{
  "type": "Feature",
  "properties": {
    "addr:full":"Calle de Galileo, 26 Madrid Madrid 28015",
    "addr:housenumber":"26",
    "addr:postcode":"madrid;28015",
    "addr:street":"Calle De Galileo",
    "iso:country":"ES",
    "sg:address":"Calle de Galileo, 26",
    "sg:city":"Madrid",
    "sg:orig_category":"Caf\u00c9s, Bares, Cervecer\u00cdas",
    "sg:phone":"+34 914 47 40 20",
    "sg:postcode":"28015",
    "sg:province":"Madrid",
    "wof:name":"Castro Barbudo Manuel",
    "wof:placetype":"venue"
},
  "geometry": {"coordinates":[-3.7102138996,40.4323616028],"type":"Point"}
}