{
  "type": "Feature",
  "properties": {
    "addr:full":"Ctra. Mercadal-fornells, Km. 0004,5 Mercadal Islas Baleares 07740",
    "addr:postcode":"07740",
    "addr:street":"Ctra. Mercadal-Fornells Km. 0004,5",
    "iso:country":"ES",
    "sg:address":"Ctra. Mercadal-fornells, Km. 0004,5",
    "sg:city":"Mercadal",
    "sg:orig_category":"Lecher\u00cdas",
    "sg:phone":"+34 971 18 85 02",
    "sg:postcode":"07740",
    "sg:province":"Islas Baleares",
    "wof:name":"Es Prat De Binicreixent S.r.m.",
    "wof:placetype":"venue"
},
  "geometry": {"coordinates":[4.0921797752,39.9863700867],"type":"Point"}
}