{
  "type": "Feature",
  "properties": {
    "iso:country":"ES",
    "sg:address":"Plaz Mayor, 10",
    "sg:city":"Fuentepelayo",
    "sg:orig_category":"Molduras, Junquillos, Listones Y Molduras Perforadas",
    "sg:phone":"+34 921 57 41 68",
    "sg:postcode":"40260",
    "sg:province":"Segovia",
    "wof:name":"Zaera Tejedor Manuel",
    "wof:placetype":"venue"
},
  "geometry": {"coordinates":[-4.1764755249,41.2215156555],"type":"Point"}
}