{
  "type": "Feature",
  "properties": {
    "addr:full":"Pase Estacion, 23 Tarancon Cuenca 16400",
    "addr:housenumber":"23",
    "addr:postcode":"16400",
    "addr:street":"Estacion",
    "iso:country":"ES",
    "sg:address":"Pase Estacion, 23",
    "sg:city":"Tarancon",
    "sg:orig_category":"Carnicer\u00cdas, Carnicer\u00cdas",
    "sg:phone":"+34 969 32 11 08",
    "sg:postcode":"16400",
    "sg:province":"Cuenca",
    "wof:name":"Ossa Rubiato Francisco De La",
    "wof:placetype":"venue"
},
  "geometry": {"coordinates":[-3.0046839714,40.0113143921],"type":"Point"}
}