{
  "type": "Feature",
  "properties": {
    "addr:full":"Pasaje De La Iglesia, 2 Castellar Ja\u00e9n 23260",
    "addr:housenumber":"2",
    "addr:postcode":"23260",
    "addr:street":"Pasaje De La Iglesia",
    "iso:country":"ES",
    "sg:address":"Pasaje De La Iglesia, 2",
    "sg:city":"Castellar",
    "sg:orig_category":"Farmacias",
    "sg:phone":"+34 953 46 00 57",
    "sg:postcode":"23260",
    "sg:province":"Ja\u00e9n",
    "wof:name":"Monedero Albacete Jesus",
    "wof:placetype":"venue"
},
  "geometry": {"coordinates":[-3.1285169125,38.2554779053],"type":"Point"}
}