{
  "type": "Feature",
  "properties": {
    "addr:full":"Carr Pla Del Rei, Des, 70 S. Francesc Formentera Islas Baleares 07860",
    "addr:postcode":"07860",
    "addr:street":"Carr Pla Del Rei Des 70 S. Francesc",
    "iso:country":"ES",
    "sg:address":"Carr Pla Del Rei, Des, 70",
    "sg:city":"S. Francesc Formentera",
    "sg:orig_category":"Fabricaci\u00d3n, Importaci\u00d3n, Venta De Material De Telefon\u00cda, Peritelefon\u00cda",
    "sg:phone":"+34 971 32 10 55",
    "sg:postcode":"07860",
    "sg:province":"Islas Baleares",
    "wof:name":"Fonocomunicaciones Ibiza S. L.",
    "wof:placetype":"venue"
},
  "geometry": {"coordinates":[1.4309200048,38.7072410583],"type":"Point"}
}