{
  "type": "Feature",
  "properties": {
    "addr:full":"Plaz Argel, 14 Alacant Alicante 03011",
    "addr:housenumber":"14",
    "addr:postcode":"03011",
    "addr:street":"Argel",
    "iso:country":"ES",
    "sg:address":"Plaz Argel, 14",
    "sg:city":"Alacant",
    "sg:orig_category":"Comerciantes Al Por Mayor De Vinos, Licores Y Alcoholes",
    "sg:phone":"+34 965 18 34 31",
    "sg:postcode":"03011",
    "sg:province":"Alicante",
    "wof:name":"Moreno Tornero Juan",
    "wof:placetype":"venue"
},
  "geometry": {"coordinates":[-0.4804739952,38.3440856934],"type":"Point"}
}