{
  "type": "Feature",
  "properties": {
    "addr:full":"Carrer de Mare De Deu De Port, 260 Barcelona Barcelona 08038",
    "addr:housenumber":"260",
    "addr:postcode":"08038",
    "addr:street":"Carrer De Mare De Deu;Port",
    "iso:country":"ES",
    "sg:address":"Carrer de Mare De Deu De Port, 260",
    "sg:city":"Barcelona",
    "sg:orig_category":"Peluqueros: De Se\u00d1oras",
    "sg:phone":"+34 933 31 81 81",
    "sg:postcode":"08038",
    "sg:province":"Barcelona",
    "wof:name":"Fernandez Lavela Julio",
    "wof:placetype":"venue"
},
  "geometry": {"coordinates":[2.1398169994,41.3618240356],"type":"Point"}
}