{
  "type": "Feature",
  "properties": {
    "iso:country":"ES",
    "sg:address":"Calle de Ganaderos, 12",
    "sg:city":"Caudiel",
    "sg:orig_category":"T\u00c9cnicos Veterinarios",
    "sg:phone":"+34 964 14 42 11",
    "sg:postcode":"12440",
    "sg:province":"Castell\u00f3n",
    "wof:name":"Ponz Benedicto Francisco",
    "wof:placetype":"venue"
},
  "geometry": {"coordinates":[-0.5645560026,39.9491539001],"type":"Point"}
}