{
  "type": "Feature",
  "properties": {
    "iso:country":"ES",
    "sg:address":"Calle de Puerto Del Monasterio, 10",
    "sg:city":"Madrid",
    "sg:orig_category":"Motocicletas (agentes, Concesionarios)",
    "sg:phone":"+34 914 78 08 00",
    "sg:postcode":"28053",
    "sg:province":"Madrid",
    "wof:name":"Martinez Mata Agustin",
    "wof:placetype":"venue"
},
  "geometry": {"coordinates":[-3.6651599407,40.3946800232],"type":"Point"}
}