{
  "type": "Feature",
  "properties": {
    "iso:country":"ES",
    "sg:address":"Carrer de Valencia, 9",
    "sg:city":"Cambrils",
    "sg:orig_category":"Agencias Y Agentes Comerciales, Representantes",
    "sg:phone":"+34 977 79 20 02",
    "sg:postcode":"43850",
    "sg:province":"Tarragona",
    "wof:name":"Martinez Garcia Juan Tomas",
    "wof:placetype":"venue"
},
  "geometry": {"coordinates":[1.0587650537,41.0679550171],"type":"Point"}
}