{
  "type": "Feature",
  "properties": {
    "iso:country":"ES",
    "sg:address":"Ctra Nova, 127",
    "sg:city":"Garriga",
    "sg:orig_category":"Fabricaci\u00d3n Y Comercio De M\u00c1quinas",
    "sg:phone":"+34 938 71 70 95",
    "sg:postcode":"08530",
    "sg:province":"Barcelona",
    "sg:website":"www.automator.com",
    "wof:name":"Iberomark Marcado Industrial S.l.",
    "wof:placetype":"venue"
},
  "geometry": {"coordinates":[2.2845532894,41.6789970398],"type":"Point"}
}