{
  "type": "Feature",
  "properties": {
    "addr:full":"Carr Caba\u00d1al, 24 Cullera Valencia 46400",
    "addr:housenumber":"24",
    "addr:postcode":"46400",
    "addr:street":"Carr Caban\u0303Al",
    "iso:country":"ES",
    "sg:address":"Carr Caba\u00d1al, 24",
    "sg:city":"Cullera",
    "sg:orig_category":"Peluquer\u00cdas, Peluquer\u00cda Mixta",
    "sg:phone":"+34 961 72 24 97",
    "sg:postcode":"46400",
    "sg:province":"Valencia",
    "sg:website":"www.alberopeluqueros.com",
    "wof:name":"Malonda Albero Jose Javier",
    "wof:placetype":"venue"
},
  "geometry": {"coordinates":[-0.2424629927,39.1642494202],"type":"Point"}
}