{
  "type": "Feature",
  "properties": {
    "iso:country":"ES",
    "sg:address":"Avda Todos Los Santos (de), 3",
    "sg:city":"Beniel",
    "sg:orig_category":"Ense\u00d1anza Secundaria: Colegios Y Escuelas Privadas",
    "sg:phone":"+34 968 60 21 02",
    "sg:postcode":"30130",
    "sg:province":"Murcia",
    "wof:name":"M.e.c.direccion Provincial De Murcia",
    "wof:placetype":"venue"
},
  "geometry": {"coordinates":[-0.9992740154,38.0493011475],"type":"Point"}
}