{
  "type": "Feature",
  "properties": {
    "iso:country":"ES",
    "sg:address":"G Esteban Torre, 2",
    "sg:city":"Motril",
    "sg:orig_category":"Construcciones Met\u00c1licas",
    "sg:phone":"+34 958 83 32 08",
    "sg:postcode":"18600",
    "sg:province":"Granada",
    "wof:name":"Estructuras Gonzalez Salvador S.l.",
    "wof:placetype":"venue"
},
  "geometry": {"coordinates":[-3.5152790546,36.7456130981],"type":"Point"}
}