{
  "type": "Feature",
  "properties": {
    "addr:full":"Calle de Colombia, 25 Santa Cruz De Tenerife Santa Cruz De Tenerife 38009",
    "addr:housenumber":"25",
    "addr:postcode":"38009",
    "addr:street":"Calle De Colombia",
    "iso:country":"ES",
    "sg:address":"Calle de Colombia, 25",
    "sg:city":"Santa Cruz De Tenerife",
    "sg:orig_category":"Comercio De Piezas De Recambio Y De Accesorios De Veh\u00cdculos, Veh\u00cdculos Industriales",
    "sg:phone":"+34 922 22 18 01",
    "sg:postcode":"38009",
    "sg:province":"Santa Cruz De Tenerife",
    "wof:name":"Vehiculos Siniestrados Autorepuestos S.l.",
    "wof:placetype":"venue"
},
  "geometry": {"coordinates":[-16.2680225372,28.4551811218],"type":"Point"}
}