{
  "type": "Feature",
  "properties": {
    "addr:full":"Carrer de Mendez Nu\u00d1ez (de), 17 S. Carles Rapita Tarragona 43540",
    "addr:housenumber":"17",
    "addr:postcode":"43540",
    "addr:street":"Carrer De Mendez Nun\u0303Ez De;S. Carles Rapita",
    "iso:country":"ES",
    "sg:address":"Carrer de Mendez Nu\u00d1ez (de), 17",
    "sg:city":"S. Carles Rapita",
    "sg:orig_category":"Promotores Constructores",
    "sg:phone":"+34 977 74 00 10",
    "sg:postcode":"43540",
    "sg:province":"Tarragona",
    "wof:name":"Construccions Vizcarro Badia S.l.",
    "wof:placetype":"venue"
},
  "geometry": {"coordinates":[0.5942800045,40.620891571],"type":"Point"}
}