{
  "type": "Feature",
  "properties": {
    "iso:country":"ES",
    "sg:address":"Rua Concepcion Arenal, 1",
    "sg:city":"Burela",
    "sg:orig_category":"Empresas De Desmonte",
    "sg:phone":"+34 982 58 15 66",
    "sg:postcode":"27880",
    "sg:province":"Lugo",
    "wof:name":"Excavaciones Abeledo S.l.",
    "wof:placetype":"venue"
},
  "geometry": {"coordinates":[-7.3586421013,43.662612915],"type":"Point"}
}