{
  "type": "Feature",
  "properties": {
    "iso:country":"ES",
    "sg:address":"Avda Constitucion, 99",
    "sg:city":"Onil",
    "sg:orig_category":"Pesca Y Caza: Art\u00cdculos (al Por Menor)",
    "sg:phone":"+34 965 56 44 05",
    "sg:postcode":"03430",
    "sg:province":"Alicante",
    "wof:name":"Sociedad De Cazadores El Ruise\u00f1or",
    "wof:placetype":"venue"
},
  "geometry": {"coordinates":[-0.6732379794,38.6301765442],"type":"Point"}
}