{
  "type": "Feature",
  "properties": {
    "iso:country":"ES",
    "sg:address":"Ctra Madrid, 89",
    "sg:city":"Santa Marta De Tormes",
    "sg:orig_category":"Molduras, Junquillos, Listones Y Molduras Perforadas",
    "sg:phone":"+34 923 13 01 56",
    "sg:postcode":"37900",
    "sg:province":"Salamanca",
    "wof:name":"Jimenez Guerrero Rosa",
    "wof:placetype":"venue"
},
  "geometry": {"coordinates":[-5.6230530739,40.9498977661],"type":"Point"}
}