{
  "type": "Feature",
  "properties": {
    "addr:full":"Calle de Teniente Mu\u00d1oz Diaz, 5 Madrid Madrid 28018",
    "addr:housenumber":"5",
    "addr:postcode":"28018",
    "addr:street":"Calle De Teniente Mun\u0303Oz Diaz",
    "iso:country":"ES",
    "sg:address":"Calle de Teniente Mu\u00d1oz Diaz, 5",
    "sg:city":"Madrid",
    "sg:orig_category":"Organismos Y Centros De Vacaciones Y Esparcimiento Para Ni\u00d1os Y Adolescentes",
    "sg:phone":"+34 914 77 03 52",
    "sg:postcode":"28018",
    "sg:province":"Madrid",
    "sg:website":"www.arcinature.com",
    "wof:name":"Arci-nature S.l.",
    "wof:placetype":"venue"
},
  "geometry": {"coordinates":[-3.6576817036,40.3914604187],"type":"Point"}
}