{
  "type": "Feature",
  "properties": {
    "addr:full":"Rbla Mendez Nu\u00d1ez, 64 Alacant Alicante 03002",
    "addr:housenumber":"64",
    "addr:postcode":"03002",
    "addr:street":"Rbla Mendez Nun\u0303Ez",
    "iso:country":"ES",
    "sg:address":"Rbla Mendez Nu\u00d1ez, 64",
    "sg:city":"Alacant",
    "sg:orig_category":"\u00d3ptica: Instrumentos (fabricaci\u00d3n)",
    "sg:phone":"+34 965 21 70 27",
    "sg:postcode":"03002",
    "sg:province":"Alicante",
    "wof:name":"Marcos Torres Francisco",
    "wof:placetype":"venue"
},
  "geometry": {"coordinates":[-0.4845989943,38.3477210999],"type":"Point"}
}