{
  "type": "Feature",
  "properties": {
    "addr:full":"Calle de Francisco Vales Villamarin, 36 Coru\u00d1a A Coru\u00f1a 15006",
    "addr:housenumber":"36",
    "addr:postcode":"15006",
    "addr:street":"Calle De Francisco Vales Villamarin;Corun\u0303A",
    "iso:country":"ES",
    "sg:address":"Calle de Francisco Vales Villamarin, 36",
    "sg:city":"Coru\u00d1a",
    "sg:orig_category":"Peluquer\u00cdas, Peluquer\u00cda Mixta",
    "sg:phone":"+34 981 13 23 43",
    "sg:postcode":"15006",
    "sg:province":"A Coru\u00f1a",
    "wof:name":"Vazquez Carreira Maria",
    "wof:placetype":"venue"
},
  "geometry": {"coordinates":[-8.3885250092,43.3529853821],"type":"Point"}
}