{
  "type": "Feature",
  "properties": {
    "addr:full":"Calle de Royal, S/n Alcorisa Teruel 44550",
    "addr:housenumber":"s / n",
    "addr:postcode":"44550",
    "addr:street":"Calle De Royal",
    "iso:country":"ES",
    "sg:address":"Calle de Royal, S/n",
    "sg:city":"Alcorisa",
    "sg:orig_category":"Empresas De Carpinter\u00cda De Madera",
    "sg:phone":"+34 978 88 30 54",
    "sg:postcode":"44550",
    "sg:province":"Teruel",
    "wof:name":"Carpinteria Hernandez Membrado S.l.",
    "wof:placetype":"venue"
},
  "geometry": {"coordinates":[-0.3729200065,40.8966560364],"type":"Point"}
}