{
  "type": "Feature",
  "properties": {
    "addr:full":"Cabojal, 58 Figaredo Asturias 33683",
    "addr:housenumber":"58",
    "addr:postcode":"33683",
    "addr:street":"Cabojal",
    "iso:country":"ES",
    "sg:address":"Cabojal, 58",
    "sg:city":"Figaredo",
    "sg:orig_category":"Carnicer\u00cdas, Carnicer\u00cdas",
    "sg:phone":"+34 985 43 23 01",
    "sg:postcode":"33683",
    "sg:province":"Asturias",
    "wof:name":"Garcia Gutierrez Ana Isabel",
    "wof:placetype":"venue"
},
  "geometry": {"coordinates":[-5.7497859001,43.2142066956],"type":"Point"}
}