{
  "type": "Feature",
  "properties": {
    "addr:full":"Carrer de Providencia, 38 Manresa Barcelona 08241",
    "addr:housenumber":"38",
    "addr:postcode":"08241",
    "addr:street":"Carrer De Providencia",
    "iso:country":"ES",
    "sg:address":"Carrer de Providencia, 38",
    "sg:city":"Manresa",
    "sg:orig_category":"Encuadernaci\u00d3n E Impresi\u00d3n De Folletos",
    "sg:phone":"+34 938 36 22 12",
    "sg:postcode":"08241",
    "sg:province":"Barcelona",
    "wof:name":"Soler Conde Agustin",
    "wof:placetype":"venue"
},
  "geometry": {"coordinates":[1.8364839554,41.7246856689],"type":"Point"}
}