{
  "type": "Feature",
  "properties": {
    "iso:country":"ES",
    "sg:address":"Avda Logro\u00d1o, 271",
    "sg:city":"Madrid",
    "sg:orig_category":"Muebles, Minoristas",
    "sg:phone":"+34 913 29 02 75",
    "sg:postcode":"28042",
    "sg:province":"Madrid",
    "wof:name":"Orejon Gonzalez Maria De Los Angeles",
    "wof:placetype":"venue"
},
  "geometry": {"coordinates":[-3.5847530365,40.4654121399],"type":"Point"}
}