{
  "type": "Feature",
  "properties": {
    "iso:country":"ES",
    "sg:address":"Calle de Tutor, 59",
    "sg:city":"Madrid",
    "sg:orig_category":"Peluqueros: De Se\u00d1oras",
    "sg:phone":"+34 915 49 21 70",
    "sg:postcode":"28008",
    "sg:province":"Madrid",
    "wof:name":"Alvarez Llorente S.l.",
    "wof:placetype":"venue"
},
  "geometry": {"coordinates":[-3.7188334465,40.4320373535],"type":"Point"}
}