{
  "type": "Feature",
  "properties": {
    "iso:country":"ES",
    "sg:address":"Plaz Iglesia, 6",
    "sg:city":"Mora Rubielos",
    "sg:orig_category":"Muebles, Minoristas",
    "sg:phone":"+34 978 80 05 54",
    "sg:postcode":"44400",
    "sg:province":"Teruel",
    "wof:name":"Valero Sanchez Vicente",
    "wof:placetype":"venue"
},
  "geometry": {"coordinates":[-0.7552589774,40.2504005432],"type":"Point"}
}