{
  "type": "Feature",
  "properties": {
    "addr:full":"Avda Zunzunegui Juan Antonio, 9 Bilbao Vizcaya 48013",
    "addr:housenumber":"9",
    "addr:postcode":"48013",
    "addr:street":"Avda Zunzunegui Juan Antonio",
    "iso:country":"ES",
    "sg:address":"Avda Zunzunegui Juan Antonio, 9",
    "sg:city":"Bilbao",
    "sg:orig_category":"Servicios De Telecomunicaciones",
    "sg:phone":"+34 944 41 02 89",
    "sg:postcode":"48013",
    "sg:province":"Vizcaya",
    "wof:name":"Micro Berri S.l.",
    "wof:placetype":"venue"
},
  "geometry": {"coordinates":[-2.948579073,43.2613296509],"type":"Point"}
}