{
  "type": "Feature",
  "properties": {
    "addr:full":"Calle de Malaga, 15 Marbella M\u00e1laga 29600",
    "addr:housenumber":"15",
    "addr:postcode":"29600",
    "addr:street":"Calle De Malaga;Ma\u0301Laga",
    "iso:country":"ES",
    "sg:address":"Calle de Malaga, 15",
    "sg:city":"Marbella",
    "sg:orig_category":"Sindicatos De Trabajadores",
    "sg:phone":"+34 952 76 62 23",
    "sg:postcode":"29600",
    "sg:province":"M\u00e1laga",
    "wof:name":"Sindicato U.t.",
    "wof:placetype":"venue"
},
  "geometry": {"coordinates":[-4.8807621002,36.5098266602],"type":"Point"}
}