{
  "type": "Feature",
  "properties": {
    "iso:country":"ES",
    "sg:address":"Calle de Canet De Mar, S/n",
    "sg:city":"Isla Cristina",
    "sg:orig_category":"Abogados",
    "sg:phone":"+34 959 33 00 06",
    "sg:postcode":"21410",
    "sg:province":"Huelva",
    "wof:name":"Velez Aibar Rafael Jose",
    "wof:placetype":"venue"
},
  "geometry": {"coordinates":[-7.3230490685,37.2013549805],"type":"Point"}
}