{
  "type": "Feature",
  "properties": {
    "addr:full":"Trav Corts, 228 Barcelona Barcelona 08028",
    "addr:housenumber":"228",
    "addr:postcode":"08028",
    "addr:street":"Trav Corts",
    "iso:country":"ES",
    "sg:address":"Trav Corts, 228",
    "sg:city":"Barcelona",
    "sg:orig_category":"Agencias Y Agentes Comerciales, Representantes",
    "sg:phone":"+34 934 90 98 60",
    "sg:postcode":"08028",
    "sg:province":"Barcelona",
    "wof:name":"Comas Chaler Daniel",
    "wof:placetype":"venue"
},
  "geometry": {"coordinates":[2.1317470074,41.3845939636],"type":"Point"}
}