{
  "type": "Feature",
  "properties": {
    "addr:full":"Carrer de Canuda, 3 Barcelona Barcelona 08002",
    "addr:housenumber":"3",
    "addr:postcode":"08002",
    "addr:street":"Carrer De Canuda",
    "iso:country":"ES",
    "sg:address":"Carrer de Canuda, 3",
    "sg:city":"Barcelona",
    "sg:orig_category":"Ropa Y Accesorios",
    "sg:phone":"+34 933 02 10 35",
    "sg:postcode":"08002",
    "sg:province":"Barcelona",
    "wof:name":"Puig Casado Rosario",
    "wof:placetype":"venue"
},
  "geometry": {"coordinates":[2.1710560322,41.3848686218],"type":"Point"}
}