{
  "type": "Feature",
  "properties": {
    "iso:country":"ES",
    "sg:address":"Carrer de Santa Teresa, 33",
    "sg:city":"Gava",
    "sg:orig_category":"Empresas De Carpinter\u00cda De Madera",
    "sg:phone":"+34 936 62 09 34",
    "sg:postcode":"08850",
    "sg:province":"Barcelona",
    "wof:name":"Camps C.b",
    "wof:placetype":"venue"
},
  "geometry": {"coordinates":[1.9998910427,41.3066444397],"type":"Point"}
}