{
  "type": "Feature",
  "properties": {
    "addr:full":"Calle de Nueva, 13 Villaviciosa Odon Madrid 28670",
    "addr:housenumber":"13",
    "addr:postcode":"28670",
    "addr:street":"Calle De Nueva;Odon",
    "iso:country":"ES",
    "sg:address":"Calle de Nueva, 13",
    "sg:city":"Villaviciosa Odon",
    "sg:orig_category":"Laboratorios Y Trabajos De Fotograf\u00cda, V\u00cddeo Y Cine",
    "sg:phone":"+34 916 16 99 85",
    "sg:postcode":"28670",
    "sg:province":"Madrid",
    "wof:name":"Nueva 13 S.l",
    "wof:placetype":"venue"
},
  "geometry": {"coordinates":[-3.9004294872,40.3569831848],"type":"Point"}
}