{
  "type": "Feature",
  "properties": {
    "iso:country":"ES",
    "sg:address":"Calle de Brasil, 6",
    "sg:city":"Zona De Los Principes",
    "sg:orig_category":"Molduras, Junquillos, Listones Y Molduras Perforadas",
    "sg:phone":"+34 959 35 09 99",
    "sg:postcode":"21810",
    "sg:province":"Huelva",
    "wof:name":"Pancho Villalba Manuel",
    "wof:placetype":"venue"
},
  "geometry": {"coordinates":[-6.9495549202,37.2570991516],"type":"Point"}
}