{
  "type": "Feature",
  "properties": {
    "iso:country":"ES",
    "sg:address":"Usabal, 202",
    "sg:city":"Tolosa",
    "sg:orig_category":"Empresas De Carpinter\u00cda De Madera",
    "sg:phone":"+34 943 57 75 74",
    "sg:postcode":"20400",
    "sg:province":"Guip\u00f9zcoa",
    "wof:name":"Carpinteria De Madera Calvo, S.l.",
    "wof:placetype":"venue"
},
  "geometry": {"coordinates":[-2.0806159973,43.1255187988],"type":"Point"}
}