{
  "type": "Feature",
  "properties": {
    "addr:full":"Calle de Colon, 10 Cuenca Cuenca 16002",
    "addr:housenumber":"10",
    "addr:postcode":"16002",
    "addr:street":"Calle De Colon",
    "iso:country":"ES",
    "sg:address":"Calle de Colon, 10",
    "sg:city":"Cuenca",
    "sg:orig_category":"Azafatas De Vuelo",
    "sg:phone":"+34 902 10 02 19",
    "sg:postcode":"16002",
    "sg:province":"Cuenca",
    "wof:name":"Mateo Mateo Comunicacion S.l.",
    "wof:placetype":"venue"
},
  "geometry": {"coordinates":[-2.1379740238,40.0753211975],"type":"Point"}
}