{
  "type": "Feature",
  "properties": {
    "iso:country":"ES",
    "sg:address":"Mi\u00f1o, 11",
    "sg:city":"Lugo",
    "sg:orig_category":"Electrodom\u00c9sticos (al Por Menor)",
    "sg:phone":"+34 982 22 88 57",
    "sg:postcode":"27001",
    "sg:province":"Lugo",
    "wof:name":"Lopez Mera Jose Maria",
    "wof:placetype":"venue"
},
  "geometry": {"coordinates":[-7.5597381592,43.0101966858],"type":"Point"}
}