{
  "type": "Feature",
  "properties": {
    "addr:full":"Carr Hostaleria, 13 Port D'alcudia Islas Baleares 07410",
    "addr:housenumber":"13",
    "addr:postcode":"07410",
    "addr:street":"Carr Hostaleria",
    "iso:country":"ES",
    "sg:address":"Carr Hostaleria, 13",
    "sg:city":"Port D'alcudia",
    "sg:orig_category":"Ropa Para Se\u00d1oras Y Caballeros (al Por Menor)",
    "sg:phone":"+34 971 54 81 81",
    "sg:postcode":"07410",
    "sg:province":"Islas Baleares",
    "wof:name":"Bruixa 1 Mussol S.l.",
    "wof:placetype":"venue"
},
  "geometry": {"coordinates":[3.1328918934,39.8422393799],"type":"Point"}
}