{
  "type": "Feature",
  "properties": {
    "iso:country":"ES",
    "sg:address":"Cornalvo, 4",
    "sg:city":"Merida",
    "sg:orig_category":"Frutas, Legumbres Frescas Y Tempranas (al Por Menor)",
    "sg:phone":"+34 924 37 13 06",
    "sg:postcode":"06800",
    "sg:province":"Badajoz",
    "wof:name":"Perez Prieto Fernando",
    "wof:placetype":"venue"
},
  "geometry": {"coordinates":[-6.3600091934,38.9113388062],"type":"Point"}
}