{
  "type": "Feature",
  "properties": {
    "addr:full":"Avda Madrid De, 5 Donostia-san Sebastian Guip\u00f9zcoa 20011",
    "addr:housenumber":"5",
    "addr:postcode":"20011",
    "addr:street":"Avda Madrid De",
    "iso:country":"ES",
    "sg:address":"Avda Madrid De, 5",
    "sg:city":"Donostia-san Sebastian",
    "sg:orig_category":"Ropa Para Caballeros (al Por Menor)",
    "sg:phone":"+34 943 45 22 96",
    "sg:postcode":"20011",
    "sg:province":"Guip\u00f9zcoa",
    "wof:name":"Francisco Javier Algarra Olague",
    "wof:placetype":"venue"
},
  "geometry": {"coordinates":[-1.9770729542,43.3050575256],"type":"Point"}
}