{
  "type": "Feature",
  "properties": {
    "iso:country":"ES",
    "sg:address":"Carrer de Lepanto, 63",
    "sg:city":"Mataro",
    "sg:orig_category":"Electrodom\u00c9sticos (al Por Menor)",
    "sg:phone":"+34 937 96 30 12",
    "sg:postcode":"08301",
    "sg:province":"Barcelona",
    "wof:name":"Revenga Gracia Luis Carlos",
    "wof:placetype":"venue"
},
  "geometry": {"coordinates":[2.4454410076,41.5349273682],"type":"Point"}
}