{
  "type": "Feature",
  "properties": {
    "iso:country":"ES",
    "sg:address":"Calle de Alvar Fa\u00d1ez, 7",
    "sg:city":"Medina Campo",
    "sg:orig_category":"Equitaci\u00d3n: Guarnicioner\u00cda, Equipo (al Por Menor)",
    "sg:phone":"+34 983 81 13 62",
    "sg:postcode":"47400",
    "sg:province":"Valladolid",
    "wof:name":"Alberto Rodriguez Y Otro C.b.",
    "wof:placetype":"venue"
},
  "geometry": {"coordinates":[-4.921933651,41.3111724854],"type":"Point"}
}