{
  "type": "Feature",
  "properties": {
    "addr:full":"Carrer de Joan Ramon Benapres, 1 Sitges Barcelona 08870",
    "addr:housenumber":"1",
    "addr:postcode":"08870",
    "addr:street":"Carrer De Joan Ramon Benapres",
    "iso:country":"ES",
    "sg:address":"Carrer de Joan Ramon Benapres, 1",
    "sg:city":"Sitges",
    "sg:orig_category":"Fabricaci\u00d3n, Importaci\u00d3n De L\u00c1mparas Y Bombillas",
    "sg:phone":"+34 938 94 99 52",
    "sg:postcode":"08870",
    "sg:province":"Barcelona",
    "wof:name":"Icpep Sitges S.l",
    "wof:placetype":"venue"
},
  "geometry": {"coordinates":[1.8126740456,41.2391014099],"type":"Point"}
}