{
  "type": "Feature",
  "properties": {
    "iso:country":"ES",
    "sg:address":"Calle de Alferez Provisional, 57",
    "sg:city":"Bola\u00e7os De Calatrava",
    "sg:orig_category":"Pescader\u00cdas (al Por Menor)",
    "sg:phone":"+34 926 87 07 90",
    "sg:postcode":"13260",
    "sg:province":"Ciudad Real",
    "wof:name":"Chacon Martin Emiliano",
    "wof:placetype":"venue"
},
  "geometry": {"coordinates":[-3.9272627831,38.9860954285],"type":"Point"}
}