{
  "type": "Feature",
  "properties": {
    "addr:full":"Calle de La Hiruela, 1 Madrid Madrid 28035",
    "addr:housenumber":"1",
    "addr:postcode":"28035",
    "addr:street":"Calle De La Hiruela",
    "iso:country":"ES",
    "sg:address":"Calle de La Hiruela, 1",
    "sg:city":"Madrid",
    "sg:orig_category":"Agencias Y Asesores De Publicidad",
    "sg:phone":"+34 913 86 60 22",
    "sg:postcode":"28035",
    "sg:province":"Madrid",
    "sg:website":"www.masspublic.com",
    "wof:name":"C.p.m. Masspublic S.l.",
    "wof:placetype":"venue"
},
  "geometry": {"coordinates":[-3.7188739777,40.4725418091],"type":"Point"}
}