{
  "type": "Feature",
  "properties": {
    "addr:full":"Avda Euskadi, S/n San Vicente De Barakaldo Vizcaya 48901",
    "addr:housenumber":"s / n",
    "addr:postcode":"48901",
    "addr:street":"Avda Euskadi",
    "iso:country":"ES",
    "sg:address":"Avda Euskadi, S/n",
    "sg:city":"San Vicente De Barakaldo",
    "sg:orig_category":"Aparcamientos (infraestructuras, Accesorios)",
    "sg:phone":"+34 944 99 51 27",
    "sg:postcode":"48901",
    "sg:province":"Vizcaya",
    "wof:name":"Compa\u00f1ia Concesionaria Del Aparcamiento De La Plaza Gernikako Arbola De Barakaldo Parking Juzgados S",
    "wof:placetype":"venue"
},
  "geometry": {"coordinates":[-2.9858388901,43.2973098755],"type":"Point"}
}