{
  "type": "Feature",
  "properties": {
    "iso:country":"ES",
    "sg:address":"Calle de Manuel Maria De Zulueta (de), 2",
    "sg:city":"Coslada",
    "sg:orig_category":"Electrodom\u00c9sticos (al Por Menor)",
    "sg:phone":"+34 916 69 06 38",
    "sg:postcode":"28820",
    "sg:province":"Madrid",
    "wof:name":"Rivera Marquez Rafael",
    "wof:placetype":"venue"
},
  "geometry": {"coordinates":[-3.566286087,40.4271583557],"type":"Point"}
}