{
  "type": "Feature",
  "properties": {
    "addr:full":"Carrer de Sant Francesc, 23 Reus Tarragona 43205",
    "addr:housenumber":"23",
    "addr:postcode":"43205",
    "addr:street":"Carrer De Sant Francesc",
    "iso:country":"ES",
    "sg:address":"Carrer de Sant Francesc, 23",
    "sg:city":"Reus",
    "sg:orig_category":"Peluqueros: De Se\u00d1oras",
    "sg:phone":"+34 977 32 31 59",
    "sg:postcode":"43205",
    "sg:province":"Tarragona",
    "wof:name":"Aguilas Papaseit Juan Francisco",
    "wof:placetype":"venue"
},
  "geometry": {"coordinates":[1.1077833176,41.1526145935],"type":"Point"}
}