{
  "type": "Feature",
  "properties": {
    "addr:full":"Barr Murtatza, S/n Murtatza Vizcaya 48390",
    "addr:postcode":"48390",
    "addr:street":"Murtatza S / N",
    "iso:country":"ES",
    "sg:address":"Barr Murtatza, S/n",
    "sg:city":"Murtatza",
    "sg:orig_category":"Importaci\u00d3n",
    "sg:phone":"+34 946 31 41 89",
    "sg:postcode":"48390",
    "sg:province":"Vizcaya",
    "wof:name":"Afesa Asociacion De Fabricantes Para La Exportacion S. A.",
    "wof:placetype":"venue"
},
  "geometry": {"coordinates":[-2.8106722832,43.2135391235],"type":"Point"}
}