{
  "type": "Feature",
  "properties": {
    "addr:full":"Calle de Villamediana, 5 Logro\u00f1o La Rioja 26003",
    "addr:housenumber":"5",
    "addr:postcode":"26003",
    "addr:street":"Calle De Villamediana;Rioja",
    "iso:country":"ES",
    "sg:address":"Calle de Villamediana, 5",
    "sg:city":"Logro\u00f1o",
    "sg:orig_category":"Ropa Para Ni\u00d1os (al Por Menor)",
    "sg:phone":"+34 941 25 28 44",
    "sg:postcode":"26003",
    "sg:province":"La Rioja",
    "wof:name":"Soto Ajamil Jose Carlos",
    "wof:placetype":"venue"
},
  "geometry": {"coordinates":[-2.4431190491,42.4620895386],"type":"Point"}
}