{
  "type": "Feature",
  "properties": {
    "addr:full":"Rosen, S/n Rosen Ourense 32655",
    "addr:housenumber":"s / n",
    "addr:postcode":"32655",
    "addr:street":"Rosen",
    "iso:country":"ES",
    "sg:address":"Rosen, S/n",
    "sg:city":"Rosen",
    "sg:orig_category":"Piedra Natural",
    "sg:phone":"+34 988 45 26 02",
    "sg:postcode":"32655",
    "sg:province":"Ourense",
    "wof:name":"Granitos Rosen Rairiz S.l.",
    "wof:placetype":"venue"
},
  "geometry": {"coordinates":[-7.832736969,42.1320266724],"type":"Point"}
}