{
  "type": "Feature",
  "properties": {
    "addr:full":"Calle de Arregueses, 1 Sabi\u00f1anigo Huesca 22600",
    "addr:housenumber":"1",
    "addr:postcode":"22600",
    "addr:street":"Calle De Arregueses",
    "iso:country":"ES",
    "sg:address":"Calle de Arregueses, 1",
    "sg:city":"Sabi\u00f1anigo",
    "sg:orig_category":"Empresas De Limpieza",
    "sg:phone":"+34 974 48 31 87",
    "sg:postcode":"22600",
    "sg:province":"Huesca",
    "wof:name":"Ascaso Lanuza Eugenio",
    "wof:placetype":"venue"
},
  "geometry": {"coordinates":[-0.3729768097,42.5207672119],"type":"Point"}
}