{
  "type": "Feature",
  "properties": {
    "iso:country":"ES",
    "sg:address":"Maritima, 18",
    "sg:city":"Puerto Santiago",
    "sg:orig_category":"Inmobiliaria (agencias)",
    "sg:phone":"+34 922 86 09 11",
    "sg:postcode":"38683",
    "sg:province":"Santa Cruz De Tenerife",
    "wof:name":"King  Robert",
    "wof:placetype":"venue"
},
  "geometry": {"coordinates":[-16.8399295807,28.2440795898],"type":"Point"}
}