{
  "type": "Feature",
  "properties": {
    "iso:country":"ES",
    "sg:address":"Poligono Los Jarales, S/n",
    "sg:city":"Tobaruela-la Tortilla",
    "sg:orig_category":"Mec\u00c1nico Del Autom\u00d3vil",
    "sg:phone":"+34 953 69 64 07",
    "sg:postcode":"23700",
    "sg:province":"Ja\u00e9n",
    "wof:name":"Pasquau Talleres S.l.",
    "wof:placetype":"venue"
},
  "geometry": {"coordinates":[-3.6356039047,38.093914032],"type":"Point"}
}