{
  "type": "Feature",
  "properties": {
    "iso:country":"ES",
    "sg:address":"Plaz Alfonso X, 4",
    "sg:city":"Galapagar",
    "sg:orig_category":"Asesor\u00cda De Formaci\u00d3n Y Gesti\u00d3n De Personal",
    "sg:phone":"+34 918 59 73 91",
    "sg:postcode":"28260",
    "sg:province":"Madrid",
    "wof:name":"Andres Andres Jose Luis",
    "wof:placetype":"venue"
},
  "geometry": {"coordinates":[-4.0037550926,40.5770759583],"type":"Point"}
}