{
  "type": "Feature",
  "properties": {
    "iso:country":"ES",
    "sg:address":"Carrer de Carrio, 18",
    "sg:city":"Manresa",
    "sg:orig_category":"Pr\u00c9stamos Personales E Hipotecarios",
    "sg:phone":"+34 938 72 19 22",
    "sg:postcode":"08242",
    "sg:province":"Barcelona",
    "wof:name":"Guillarte Martin Calero Luis Vicente",
    "wof:placetype":"venue"
},
  "geometry": {"coordinates":[1.8229659796,41.7284431458],"type":"Point"}
}