{
  "type": "Feature",
  "properties": {
    "addr:full":"C/ Capita Baltasar Tristany, 96 Elche Alicante 03201",
    "addr:housenumber":"96",
    "addr:postcode":"03201",
    "addr:street":"C / Capita Baltasar Tristany",
    "iso:country":"ES",
    "sg:address":"C/ Capita Baltasar Tristany, 96",
    "sg:city":"Elche",
    "sg:orig_category":"Textil",
    "sg:phone":"+34 966 67 41 49",
    "sg:postcode":"03201",
    "sg:province":"Alicante",
    "wof:name":"Escalados Joants C. B.",
    "wof:placetype":"venue"
},
  "geometry": {"coordinates":[-0.7090200186,38.262676239],"type":"Point"}
}