{
  "type": "Feature",
  "properties": {
    "iso:country":"ES",
    "sg:address":"Calle de Miguel Marrero Rodriguez, 18",
    "sg:city":"Arguineguin",
    "sg:orig_category":"Asociaciones Y Clubs Deportivos",
    "sg:phone":"+34 928 73 59 80",
    "sg:postcode":"35120",
    "sg:province":"Las Palmas",
    "wof:name":"Gutierrez Rodriguez Pedro",
    "wof:placetype":"venue"
},
  "geometry": {"coordinates":[-15.682923317,27.7607383728],"type":"Point"}
}