{
  "type": "Feature",
  "properties": {
    "iso:country":"ES",
    "sg:address":"Carrer de Victoria (de La), 34",
    "sg:city":"Santa Barbara",
    "sg:orig_category":"Peluqueros: De Se\u00d1oras",
    "sg:phone":"+34 977 71 89 12",
    "sg:postcode":"43570",
    "sg:province":"Tarragona",
    "wof:name":"Campos Senar Montserrat",
    "wof:placetype":"venue"
},
  "geometry": {"coordinates":[0.4947510064,40.7144699097],"type":"Point"}
}