{
  "type": "Feature",
  "properties": {
    "addr:full":"Calle de Evaristo Valle, 15 Oviedo Asturias 33011",
    "addr:housenumber":"15",
    "addr:postcode":"33011",
    "addr:street":"Calle De Evaristo Valle",
    "iso:country":"ES",
    "sg:address":"Calle de Evaristo Valle, 15",
    "sg:city":"Oviedo",
    "sg:orig_category":"Internados & Ense\u00d1anza Privada",
    "sg:phone":"+34 985 28 05 73",
    "sg:postcode":"33011",
    "sg:province":"Asturias",
    "wof:name":"Colegio Amor De Dios En Oviedo Amor De Dios Hermanas Del Prov Oeste",
    "wof:placetype":"venue"
},
  "geometry": {"coordinates":[-5.8447442055,43.36951828],"type":"Point"}
}