{
  "type": "Feature",
  "properties": {
    "iso:country":"ES",
    "sg:address":"Carrer de Mallorca, 304",
    "sg:city":"Barcelona",
    "sg:orig_category":"M\u00c9dicos: Otorrinolaringolog\u00cda",
    "sg:phone":"+34 934 57 96 25",
    "sg:postcode":"08037",
    "sg:province":"Barcelona",
    "wof:name":"Bosch Borrell Maria Del Carmen",
    "wof:placetype":"venue"
},
  "geometry": {"coordinates":[2.1671130657,41.3970756531],"type":"Point"}
}