{
  "type": "Feature",
  "properties": {
    "addr:full":"Calle de Alfonso Gurrea, 5 Melilla Melilla 52006",
    "addr:housenumber":"5",
    "addr:postcode":"52006",
    "addr:street":"Calle De Alfonso Gurrea",
    "iso:country":"ES",
    "sg:address":"Calle de Alfonso Gurrea, 5",
    "sg:city":"Melilla",
    "sg:orig_category":"Venta, Montaje De Neum\u00c1ticos",
    "sg:phone":"+34 952 67 69 88",
    "sg:postcode":"52006",
    "sg:province":"Melilla",
    "wof:name":"Mohamedi Abdeselam Hassan",
    "wof:placetype":"venue"
},
  "geometry": {"coordinates":[-2.9417324066,35.28465271],"type":"Point"}
}