{
  "type": "Feature",
  "properties": {
    "iso:country":"ES",
    "sg:address":"Europa (sec Ind Can Mora Nord), 7",
    "sg:city":"S. Antoni Vilamajor",
    "sg:orig_category":"Naipes, Carteles, Artilugios",
    "sg:phone":"+34 938 42 70 42",
    "sg:postcode":"08459",
    "sg:province":"Barcelona",
    "wof:name":"B15 Imatge Coorporativa S.l.",
    "wof:placetype":"venue"
},
  "geometry": {"coordinates":[2.1699187756,41.3879165649],"type":"Point"}
}