{
  "type": "Feature",
  "properties": {
    "iso:country":"ES",
    "sg:address":"Avda Marconi, 8",
    "sg:city":"Valencia",
    "sg:orig_category":"Estancos",
    "sg:phone":"+34 963 79 90 89",
    "sg:postcode":"46014",
    "sg:province":"Valencia",
    "wof:name":"Pascual Guerrero Maria Consuelo",
    "wof:placetype":"venue"
},
  "geometry": {"coordinates":[-0.4145379961,39.4680557251],"type":"Point"}
}