{
  "type": "Feature",
  "properties": {
    "addr:full":"Rua Lope De Vega, 9 Rabade Lugo 27370",
    "addr:housenumber":"9",
    "addr:postcode":"27370",
    "addr:street":"Rua Lope De Vega",
    "iso:country":"ES",
    "sg:address":"Rua Lope De Vega, 9",
    "sg:city":"Rabade",
    "sg:orig_category":"Cl\u00cdnicas Dentales",
    "sg:phone":"+34 982 39 01 13",
    "sg:postcode":"27370",
    "sg:province":"Lugo",
    "wof:name":"Dental Ruicam C.b.",
    "wof:placetype":"venue"
},
  "geometry": {"coordinates":[-7.6200489998,43.1191978455],"type":"Point"}
}