{
  "type": "Feature",
  "properties": {
    "iso:country":"ES",
    "sg:address":"Calle de Garay Juan De, 1",
    "sg:city":"Bilbao",
    "sg:orig_category":"Art\u00cdculos De Decoraci\u00d3n",
    "sg:phone":"+34 944 21 90 01",
    "sg:postcode":"48003",
    "sg:province":"Vizcaya",
    "wof:name":"Decoraciones Domingo S. A.",
    "wof:placetype":"venue"
},
  "geometry": {"coordinates":[-2.933686018,43.2570152283],"type":"Point"}
}