{
  "type": "Feature",
  "properties": {
    "iso:country":"ES",
    "sg:address":"Calle de Fray Cristobal Oramas, 27",
    "sg:city":"Mancha",
    "sg:orig_category":"Quincaller\u00cda (al Por Menor)",
    "sg:phone":"+34 922 81 23 55",
    "sg:postcode":"38430",
    "sg:province":"Santa Cruz De Tenerife",
    "wof:name":"Prefabricados Santa Barbara S.a.",
    "wof:placetype":"venue"
},
  "geometry": {"coordinates":[-16.7105464935,28.3677330017],"type":"Point"}
}