{
  "type": "Feature",
  "properties": {
    "iso:country":"ES",
    "sg:address":"Calle de Obispo Rafael Bellido Caro, 7",
    "sg:city":"Castilleja Cuesta",
    "sg:orig_category":"Molduras, Junquillos, Listones Y Molduras Perforadas",
    "sg:phone":"+34 954 16 02 08",
    "sg:postcode":"41950",
    "sg:province":"Sevilla",
    "wof:name":"Navarro Chavez Fernando",
    "wof:placetype":"venue"
},
  "geometry": {"coordinates":[-6.0493650436,37.3874816895],"type":"Point"}
}