{
  "type": "Feature",
  "properties": {
    "addr:full":"Avda Reina Sofia, 15 Playa San Juan Santa Cruz De Tenerife 38687",
    "addr:housenumber":"15",
    "addr:postcode":"38687",
    "addr:street":"Avda Reina Sofia",
    "iso:country":"ES",
    "sg:address":"Avda Reina Sofia, 15",
    "sg:city":"Playa San Juan",
    "sg:orig_category":"Art\u00cdculos De Regalo (al Por Menor)",
    "sg:phone":"+34 922 83 21 84",
    "sg:postcode":"38687",
    "sg:province":"Santa Cruz De Tenerife",
    "wof:name":"Gonzalez Hernandez C.b.",
    "wof:placetype":"venue"
},
  "geometry": {"coordinates":[-16.7886390686,28.1805458069],"type":"Point"}
}