{
  "type": "Feature",
  "properties": {
    "addr:full":"C/ Francisco Ruiz Bru, 24 Elche Alicante 03205",
    "addr:housenumber":"24",
    "addr:postcode":"03205",
    "addr:street":"C / Francisco Ruiz Bru",
    "iso:country":"ES",
    "sg:address":"C/ Francisco Ruiz Bru, 24",
    "sg:city":"Elche",
    "sg:orig_category":"Supermercados Y Hipermercados",
    "sg:phone":"+34 965 44 76 51",
    "sg:postcode":"03205",
    "sg:province":"Alicante",
    "wof:name":"Hiperber Distribucion Y Logistica S.a.",
    "wof:placetype":"venue"
},
  "geometry": {"coordinates":[-0.7159349918,38.2727661133],"type":"Point"}
}