{
  "type": "Feature",
  "properties": {
    "iso:country":"ES",
    "sg:address":"Calle de Poniente, 3",
    "sg:city":"Valdeganga",
    "sg:orig_category":"Muebles, Minoristas",
    "sg:phone":"+34 967 40 02 15",
    "sg:postcode":"02150",
    "sg:province":"Albacete",
    "wof:name":"Muebles Antonio Cordoba S.l.l.",
    "wof:placetype":"venue"
},
  "geometry": {"coordinates":[-1.6807719469,39.1348495483],"type":"Point"}
}