{
  "type": "Feature",
  "properties": {
    "addr:full":"Calle de General Casta\u00d1os, 13 Madrid Madrid 28004",
    "addr:housenumber":"13",
    "addr:postcode":"madrid;28004",
    "addr:street":"Calle De General Castan\u0303Os",
    "iso:country":"ES",
    "sg:address":"Calle de General Casta\u00d1os, 13",
    "sg:city":"Madrid",
    "sg:orig_category":"Abogados",
    "sg:phone":"+34 913 08 08 03",
    "sg:postcode":"28004",
    "sg:province":"Madrid",
    "wof:name":"Gimeno Lopez-doriga Fernando",
    "wof:placetype":"venue"
},
  "geometry": {"coordinates":[-3.6938021183,40.4260826111],"type":"Point"}
}