{
  "type": "Feature",
  "properties": {
    "iso:country":"ES",
    "sg:address":"Calle de Macia Francesc, 11",
    "sg:city":"Bilbao",
    "sg:orig_category":"Sindicatos Y Colegios Profesionales",
    "sg:phone":"+34 944 75 71 12",
    "sg:postcode":"48014",
    "sg:province":"Vizcaya",
    "wof:name":"Deusto Bizirik Agrupacion",
    "wof:placetype":"venue"
},
  "geometry": {"coordinates":[-2.942168951,43.2707252502],"type":"Point"}
}