{
  "type": "Feature",
  "properties": {
    "addr:full":"Cmno Arana Bidea, 14 Berango Vizcaya 48640",
    "addr:housenumber":"14",
    "addr:postcode":"48640",
    "addr:street":"Cmno Arana Bidea",
    "iso:country":"ES",
    "sg:address":"Cmno Arana Bidea, 14",
    "sg:city":"Berango",
    "sg:orig_category":"Empresas De Carpinter\u00cda Met\u00c1lica",
    "sg:phone":"+34 946 68 07 07",
    "sg:postcode":"48640",
    "sg:province":"Vizcaya",
    "wof:name":"Carpinteria Metalica Txomin S.l.",
    "wof:placetype":"venue"
},
  "geometry": {"coordinates":[-2.99928689,43.3656997681],"type":"Point"}
}