{
  "type": "Feature",
  "properties": {
    "addr:full":"Plaz San Miguel, 7 Zaragoza Zaragoza 50001",
    "addr:housenumber":"7",
    "addr:postcode":"50001",
    "addr:street":"Plaz San Miguel",
    "iso:country":"ES",
    "sg:address":"Plaz San Miguel, 7",
    "sg:city":"Zaragoza",
    "sg:orig_category":"Arquitectos",
    "sg:phone":"+34 976 39 22 58",
    "sg:postcode":"50001",
    "sg:province":"Zaragoza",
    "wof:name":"Bernal Rojo Fernando",
    "wof:placetype":"venue"
},
  "geometry": {"coordinates":[-0.8759300113,41.6497001648],"type":"Point"}
}