{
  "type": "Feature",
  "properties": {
    "iso:country":"ES",
    "sg:address":"Avda Pio Xii, 4",
    "sg:city":"Talavera Reina",
    "sg:orig_category":"Arquitectos",
    "sg:phone":"+34 925 80 00 29",
    "sg:postcode":"45600",
    "sg:province":"Toledo",
    "wof:name":"Urtiaga De Vivar Pecharroman Alberto",
    "wof:placetype":"venue"
},
  "geometry": {"coordinates":[-4.8236131668,39.9642448425],"type":"Point"}
}