{
  "type": "Feature",
  "properties": {
    "iso:country":"ES",
    "sg:address":"Calle de Alvarez Pelayo, 26",
    "sg:city":"Granada",
    "sg:orig_category":"Inform\u00c1tica (estudios, Servicios, Asesor\u00cda, Formaci\u00d3n)",
    "sg:phone":"+34 958 15 00 10",
    "sg:postcode":"18014",
    "sg:province":"Granada",
    "wof:name":"Esteban Linde Jose",
    "wof:placetype":"venue"
},
  "geometry": {"coordinates":[-3.6098599434,37.193977356],"type":"Point"}
}