{
  "type": "Feature",
  "properties": {
    "addr:full":"Calle de Villablino, 59 Fuenlabrada Madrid 28947",
    "addr:housenumber":"59",
    "addr:postcode":"28947",
    "addr:street":"Calle De Villablino",
    "iso:country":"ES",
    "sg:address":"Calle de Villablino, 59",
    "sg:city":"Fuenlabrada",
    "sg:orig_category":"Fabricaci\u00d3n De Sobres, Bolsas Y Fundas",
    "sg:phone":"+34 916 42 08 38",
    "sg:postcode":"28947",
    "sg:province":"Madrid",
    "wof:name":"Guangxin  Liu",
    "wof:placetype":"venue"
},
  "geometry": {"coordinates":[-3.7467939854,40.2566108704],"type":"Point"}
}