{
  "type": "Feature",
  "properties": {
    "iso:country":"ES",
    "sg:address":"Calle de Cano, 17",
    "sg:city":"Paredilla I",
    "sg:orig_category":"Cerrajer\u00cda, Ferrallista",
    "sg:phone":"+34 928 75 22 17",
    "sg:postcode":"35110",
    "sg:province":"Las Palmas",
    "wof:name":"Adrima Puertas Automaticas S.l.",
    "wof:placetype":"venue"
},
  "geometry": {"coordinates":[-15.4472293854,27.8423423767],"type":"Point"}
}