{
  "type": "Feature",
  "properties": {
    "iso:country":"ES",
    "sg:address":"Ctra Manlleu, Km. 0001,0",
    "sg:city":"Diseminados",
    "sg:orig_category":"Cr\u00cda De Cerdos",
    "sg:phone":"+34 938 51 07 87",
    "sg:postcode":"08510",
    "sg:province":"Barcelona",
    "wof:name":"Explotacions Ramaderes Jan S.l.",
    "wof:placetype":"venue"
},
  "geometry": {"coordinates":[2.3096299171,41.9834785461],"type":"Point"}
}