{
  "type": "Feature",
  "properties": {
    "addr:full":"Carrer de Cristofor Colom, 30 S. Cugat Valles Barcelona 08172",
    "addr:housenumber":"30",
    "addr:postcode":"08172",
    "addr:street":"Carrer De Cristofor Colom;S. Cugat Valles Barcelona",
    "iso:country":"ES",
    "sg:address":"Carrer de Cristofor Colom, 30",
    "sg:city":"S. Cugat Valles",
    "sg:orig_category":"Construcci\u00d3n, Mantenimiento De Piscinas",
    "sg:phone":"+34 936 75 13 13",
    "sg:postcode":"08172",
    "sg:province":"Barcelona",
    "wof:name":"Bcn Piscinas I Spas Del Valles S.l",
    "wof:placetype":"venue"
},
  "geometry": {"coordinates":[2.0798990726,41.4721679688],"type":"Point"}
}