{
  "type": "Feature",
  "properties": {
    "addr:full":"Calle de Mendoza, 1 Coin M\u00e1laga 29100",
    "addr:housenumber":"1",
    "addr:postcode":"29100",
    "addr:street":"Calle De Mendoza;Ma\u0301Laga",
    "iso:country":"ES",
    "sg:address":"Calle de Mendoza, 1",
    "sg:city":"Coin",
    "sg:orig_category":"Alimentaci\u00d3n General (al Por Menor)",
    "sg:phone":"+34 952 45 08 82",
    "sg:postcode":"29100",
    "sg:province":"M\u00e1laga",
    "wof:name":"Rodriguez Lucena Jose",
    "wof:placetype":"venue"
},
  "geometry": {"coordinates":[-4.7615189552,36.6586303711],"type":"Point"}
}