{
  "type": "Feature",
  "properties": {
    "iso:country":"ES",
    "sg:address":"Ptda Pla De La Serra, S/n",
    "sg:city":"Alfas Pi",
    "sg:orig_category":"Asociaciones Y Clubs Deportivos",
    "sg:phone":"+34 966 86 62 33",
    "sg:postcode":"03580",
    "sg:province":"Alicante",
    "wof:name":"Club De Tenis La Marina",
    "wof:placetype":"venue"
},
  "geometry": {"coordinates":[-0.1106439978,38.5881652832],"type":"Point"}
}