{
  "type": "Feature",
  "properties": {
    "addr:full":"Av Mare Deu De Montserrat, 203 Barcelona Barcelona 08041",
    "addr:housenumber":"203",
    "addr:postcode":"08041",
    "addr:street":"Av Mare;De Montserrat",
    "iso:country":"ES",
    "sg:address":"Av Mare Deu De Montserrat, 203",
    "sg:city":"Barcelona",
    "sg:orig_category":"Instalaci\u00d3n De Sanitarios",
    "sg:phone":"+34 934 35 45 78",
    "sg:postcode":"08041",
    "sg:province":"Barcelona",
    "wof:name":"Domenjo Castella Maria",
    "wof:placetype":"venue"
},
  "geometry": {"coordinates":[2.173429966,41.4209022522],"type":"Point"}
}