{
  "type": "Feature",
  "properties": {
    "iso:country":"ES",
    "sg:address":"Calle de Madrid, 12",
    "sg:city":"Guardamar Segura",
    "sg:orig_category":"Agentes, Concesionarios Y Sucursales De Veh\u00cdculos",
    "sg:phone":"+34 966 72 56 36",
    "sg:postcode":"03140",
    "sg:province":"Alicante",
    "wof:name":"Vicegar S.l.",
    "wof:placetype":"venue"
},
  "geometry": {"coordinates":[-0.6571769714,38.0952415466],"type":"Point"}
}