{
  "type": "Feature",
  "properties": {
    "iso:country":"ES",
    "sg:address":"Carrer de Merce Rodoreda, 13",
    "sg:city":"Eixample",
    "sg:orig_category":"Pintura Y Barniz (al Por Menor)",
    "sg:phone":"+34 935 62 20 56",
    "sg:postcode":"08150",
    "sg:province":"Barcelona",
    "wof:name":"Rodriguez Moya Juan Antonio",
    "wof:placetype":"venue"
},
  "geometry": {"coordinates":[2.2319469452,41.5694198608],"type":"Point"}
}