{
  "type": "Feature",
  "properties": {
    "iso:country":"ES",
    "sg:address":"Calle de Sombrereria, 1",
    "sg:city":"Valencia",
    "sg:orig_category":"Bisuter\u00cda, Joyer\u00cda, Relojer\u00cda (al Por Menor)",
    "sg:phone":"+34 963 92 38 21",
    "sg:postcode":"46001",
    "sg:province":"Valencia",
    "wof:name":"Mena Polo Amparo",
    "wof:placetype":"venue"
},
  "geometry": {"coordinates":[-0.3763149977,39.4738388062],"type":"Point"}
}