{
  "type": "Feature",
  "properties": {
    "addr:full":"Ctra. Monturque-alcala, S/n Cabra C\u00f3rdoba 14940",
    "addr:housenumber":"s",
    "addr:postcode":"14940",
    "addr:street":"Ctra. Monturque-Alcala;/ N",
    "iso:country":"ES",
    "sg:address":"Ctra. Monturque-alcala, S/n",
    "sg:city":"Cabra",
    "sg:orig_category":"Reposter\u00cdas",
    "sg:phone":"+34 957 52 11 01",
    "sg:postcode":"14940",
    "sg:province":"C\u00f3rdoba",
    "wof:name":"Panificadora Subbetica S.a.l.",
    "wof:placetype":"venue"
},
  "geometry": {"coordinates":[-4.4467329979,37.4725837708],"type":"Point"}
}