{
  "type": "Feature",
  "properties": {
    "iso:country":"ES",
    "sg:address":"Cmno Horno De Alcedo, 2",
    "sg:city":"Horno De Alcedo",
    "sg:orig_category":"Cer\u00c1micas: Material Y Suministros",
    "sg:phone":"+34 963 96 45 13",
    "sg:postcode":"46026",
    "sg:province":"Valencia",
    "wof:name":"Miralles Ruiz Miguel",
    "wof:placetype":"venue"
},
  "geometry": {"coordinates":[-0.3771519959,39.4322128296],"type":"Point"}
}