{
  "type": "Feature",
  "properties": {
    "addr:full":"Pol Ind Urbayecla, 8 Yecla Murcia 30510",
    "addr:housenumber":"8",
    "addr:postcode":"30510",
    "addr:street":"Urbayecla",
    "iso:country":"ES",
    "sg:address":"Pol Ind Urbayecla, 8",
    "sg:city":"Yecla",
    "sg:orig_category":"Tapicer\u00cdas",
    "sg:phone":"+34 968 75 22 24",
    "sg:postcode":"30510",
    "sg:province":"Murcia",
    "wof:name":"Ensomar Tapizados S L",
    "wof:placetype":"venue"
},
  "geometry": {"coordinates":[-1.1149940491,38.6145591736],"type":"Point"}
}