{
  "type": "Feature",
  "properties": {
    "iso:country":"ES",
    "sg:address":"Avda Santa Maria Micaela, 50",
    "sg:city":"Guadalajara",
    "sg:orig_category":"Arquitectos",
    "sg:phone":"+34 949 21 87 12",
    "sg:postcode":"19002",
    "sg:province":"Guadalajara",
    "wof:name":"Casas Mayoral Rafael",
    "wof:placetype":"venue"
},
  "geometry": {"coordinates":[-3.1572089195,40.6264228821],"type":"Point"}
}