{
  "type": "Feature",
  "properties": {
    "addr:full":"Calle de Jaenar, 19 Madrid Madrid 28043",
    "addr:housenumber":"19",
    "addr:postcode":"madrid;28043",
    "addr:street":"Calle De Jaenar",
    "iso:country":"ES",
    "sg:address":"Calle de Jaenar, 19",
    "sg:city":"Madrid",
    "sg:orig_category":"Fabricaci\u00d3n De Mobiliario De Oficina",
    "sg:phone":"+34 913 88 07 06",
    "sg:postcode":"28043",
    "sg:province":"Madrid",
    "wof:name":"Coordinacion Tecnica Y Organizacion S.a.",
    "wof:placetype":"venue"
},
  "geometry": {"coordinates":[-3.6496419907,40.4540863037],"type":"Point"}
}