{
  "type": "Feature",
  "properties": {
    "iso:country":"ES",
    "sg:address":"Pso Ladera, 2",
    "sg:city":"Churra",
    "sg:orig_category":"Cajas De Ahorro",
    "sg:phone":"+34 968 83 04 41",
    "sg:postcode":"30110",
    "sg:province":"Murcia",
    "wof:name":"Caja De Ahorros De Murcia",
    "wof:placetype":"venue"
},
  "geometry": {"coordinates":[-1.1360189915,38.0214653015],"type":"Point"}
}