{
  "type": "Feature",
  "properties": {
    "addr:full":"Calle de G(campollano), 35 Albacete Albacete 02006",
    "addr:housenumber":"35",
    "addr:postcode":"02006",
    "addr:street":"Calle De G Campollano",
    "iso:country":"ES",
    "sg:address":"Calle de G(campollano), 35",
    "sg:city":"Albacete",
    "sg:orig_category":"Bancos",
    "sg:phone":"+34 967 52 27 30",
    "sg:postcode":"02006",
    "sg:province":"Albacete",
    "wof:name":"Banco Popular Espa\u00f1ol S.a.",
    "wof:placetype":"venue"
},
  "geometry": {"coordinates":[-1.8794189692,39.0138320923],"type":"Point"}
}