{
  "type": "Feature",
  "properties": {
    "addr:full":"Avda Valladolid, 97 Soria Soria 42004",
    "addr:housenumber":"97",
    "addr:postcode":"42004",
    "addr:street":"Avda Valladolid",
    "iso:country":"ES",
    "sg:address":"Avda Valladolid, 97",
    "sg:city":"Soria",
    "sg:orig_category":"Muebles, Minoristas",
    "sg:phone":"+34 975 22 08 32",
    "sg:postcode":"42004",
    "sg:province":"Soria",
    "wof:name":"Establecimientos Blazquez S.a.",
    "wof:placetype":"venue"
},
  "geometry": {"coordinates":[-2.4864270687,41.7686805725],"type":"Point"}
}