{
  "type": "Feature",
  "properties": {
    "iso:country":"ES",
    "sg:address":"Carrer de Novell, 37",
    "sg:city":"Barcelona",
    "sg:orig_category":"Alimentaci\u00d3n General (al Por Menor)",
    "sg:phone":"+34 934 11 07 39",
    "sg:postcode":"08028",
    "sg:province":"Barcelona",
    "wof:name":"Ali Superali",
    "wof:placetype":"venue"
},
  "geometry": {"coordinates":[2.1323926449,41.3831520081],"type":"Point"}
}