{
  "type": "Feature",
  "properties": {
    "addr:full":"Carr Borriana, 22 Villarreal Castell\u00f3n 12540",
    "addr:housenumber":"22",
    "addr:postcode":"12540",
    "addr:street":"Carr Borriana",
    "iso:country":"ES",
    "sg:address":"Carr Borriana, 22",
    "sg:city":"Villarreal",
    "sg:orig_category":"Promotores Constructores",
    "sg:phone":"+34 964 52 51 26",
    "sg:postcode":"12540",
    "sg:province":"Castell\u00f3n",
    "wof:name":"Castellopro S.l.",
    "wof:placetype":"venue"
},
  "geometry": {"coordinates":[-0.0952939987,39.9453048706],"type":"Point"}
}