{
  "type": "Feature",
  "properties": {
    "addr:full":"Calle de Industria, 1 Villanueva Cordoba C\u00f3rdoba 14440",
    "addr:housenumber":"1;cordoba co\u0301rdoba",
    "addr:postcode":"14440",
    "addr:street":"Calle De Industria",
    "iso:country":"ES",
    "sg:address":"Calle de Industria, 1",
    "sg:city":"Villanueva Cordoba",
    "sg:orig_category":"Supermercados Y Hipermercados",
    "sg:phone":"+34 957 12 11 11",
    "sg:postcode":"14440",
    "sg:province":"C\u00f3rdoba",
    "wof:name":"Cepas Castillo Damiana",
    "wof:placetype":"venue"
},
  "geometry": {"coordinates":[-4.6330537796,38.3238525391],"type":"Point"}
}