{
  "type": "Feature",
  "properties": {
    "addr:full":"Calle de Matematico Marzal, 8 Valencia Valencia 46007",
    "addr:housenumber":"8",
    "addr:postcode":"46007",
    "addr:street":"Calle De Matematico Marzal",
    "iso:country":"ES",
    "sg:address":"Calle de Matematico Marzal, 8",
    "sg:city":"Valencia",
    "sg:orig_category":"Centros Empresariales",
    "sg:phone":"+34 963 41 03 50",
    "sg:postcode":"46007",
    "sg:province":"Valencia",
    "wof:name":"Robbia S.l.",
    "wof:placetype":"venue"
},
  "geometry": {"coordinates":[-0.3804840147,39.466545105],"type":"Point"}
}