{
  "type": "Feature",
  "properties": {
    "addr:full":"M. Claros, 10 Iznajar C\u00f3rdoba 14970",
    "addr:housenumber":"10",
    "addr:postcode":"14970",
    "addr:street":"M. Claros;Co\u0301Rdoba",
    "iso:country":"ES",
    "sg:address":"M. Claros, 10",
    "sg:city":"Iznajar",
    "sg:orig_category":"Droguer\u00cdas (al Por Menor)",
    "sg:phone":"+34 957 53 43 62",
    "sg:postcode":"14970",
    "sg:province":"C\u00f3rdoba",
    "wof:name":"Hope  Sheila",
    "wof:placetype":"venue"
},
  "geometry": {"coordinates":[-4.3103551865,37.2565841675],"type":"Point"}
}