{
  "type": "Feature",
  "properties": {
    "addr:full":"Calle de Santa Maria De La Cabeza, 6 Guarroman Ja\u00e9n 23210",
    "addr:housenumber":"6",
    "addr:postcode":"23210",
    "addr:street":"Calle De Santa;Cabeza",
    "iso:country":"ES",
    "sg:address":"Calle de Santa Maria De La Cabeza, 6",
    "sg:city":"Guarroman",
    "sg:orig_category":"Centros De Educaci\u00d3n Especial",
    "sg:phone":"+34 953 61 51 80",
    "sg:postcode":"23210",
    "sg:province":"Ja\u00e9n",
    "wof:name":"Junta De Andalucia",
    "wof:placetype":"venue"
},
  "geometry": {"coordinates":[-3.6863770485,38.1846542358],"type":"Point"}
}