{
  "type": "Feature",
  "properties": {
    "iso:country":"ES",
    "sg:address":"Calle de Onesimo Redondo, 12",
    "sg:city":"Socuellamos",
    "sg:orig_category":"Pintura, Barniz, Productos Asimilables (fabricaci\u00d3n, Al Por Mayor)",
    "sg:phone":"+34 926 53 29 16",
    "sg:postcode":"13630",
    "sg:province":"Ciudad Real",
    "wof:name":"Pintura Y Decoracion Depisell Sl",
    "wof:placetype":"venue"
},
  "geometry": {"coordinates":[-2.7915756702,39.2849845886],"type":"Point"}
}