{
  "type": "Feature",
  "properties": {
    "iso:country":"ES",
    "sg:address":"Avda Madrid (de), S/n",
    "sg:city":"Alamo",
    "sg:orig_category":"Art\u00cdculos De Madera (fabricaci\u00d3n Y Al Por Mayor)",
    "sg:phone":"+34 918 12 11 05",
    "sg:postcode":"28607",
    "sg:province":"Madrid",
    "wof:name":"Carpinteros Y Ebanistas Ceide",
    "wof:placetype":"venue"
},
  "geometry": {"coordinates":[-3.9855349064,40.2318878174],"type":"Point"}
}