{
  "type": "Feature",
  "properties": {
    "addr:full":"Carrer de Jerez, 70 Terrassa Barcelona 08226",
    "addr:housenumber":"70",
    "addr:postcode":"08226",
    "addr:street":"Carrer De Jerez",
    "iso:country":"ES",
    "sg:address":"Carrer de Jerez, 70",
    "sg:city":"Terrassa",
    "sg:orig_category":"Limpieza Con Chorro De Arena Y Con Granalla, Pulido",
    "sg:phone":"+34 937 85 06 26",
    "sg:postcode":"08226",
    "sg:province":"Barcelona",
    "wof:name":"Mes Net S.l.",
    "wof:placetype":"venue"
},
  "geometry": {"coordinates":[2.0324010849,41.5712928772],"type":"Point"}
}