{
  "type": "Feature",
  "properties": {
    "addr:full":"Calle de Leon, 7 Madrid Madrid 28014",
    "addr:housenumber":"7",
    "addr:postcode":"madrid;28014",
    "addr:street":"Calle De Leon",
    "iso:country":"ES",
    "sg:address":"Calle de Leon, 7",
    "sg:city":"Madrid",
    "sg:orig_category":"Zapatos (al Por Menor)",
    "sg:phone":"+34 914 29 49 95",
    "sg:postcode":"28014",
    "sg:province":"Madrid",
    "wof:name":"Espinosa Lopez-lucendo Emiliano",
    "wof:placetype":"venue"
},
  "geometry": {"coordinates":[-3.6985259056,40.4144363403],"type":"Point"}
}