{
  "type": "Feature",
  "properties": {
    "iso:country":"ES",
    "sg:address":"Vred Tabala, 1",
    "sg:city":"Huerta De Alquerias",
    "sg:orig_category":"Supermercados Y Hipermercados",
    "sg:phone":"+34 968 81 01 58",
    "sg:postcode":"30580",
    "sg:province":"Murcia",
    "wof:name":"Jara Ortiz Pedro",
    "wof:placetype":"venue"
},
  "geometry": {"coordinates":[-1.0310490131,38.0146942139],"type":"Point"}
}