{
  "type": "Feature",
  "properties": {
    "addr:full":"Ntra. Sra. Reina Angeles, 12 Jimena Frontera C\u00e1diz 11330",
    "addr:housenumber":"12",
    "addr:postcode":"11330",
    "addr:street":"Jimena;Ca\u0301Diz",
    "iso:country":"ES",
    "sg:address":"Ntra. Sra. Reina Angeles, 12",
    "sg:city":"Jimena Frontera",
    "sg:orig_category":"Quincaller\u00cda (al Por Menor)",
    "sg:phone":"+34 956 64 03 02",
    "sg:postcode":"11330",
    "sg:province":"C\u00e1diz",
    "wof:name":"Quintero Sanchez Jose Antonio",
    "wof:placetype":"venue"
},
  "geometry": {"coordinates":[-5.4481987953,36.4326057434],"type":"Point"}
}