{
  "type": "Feature",
  "properties": {
    "addr:full":"Calle de Olivares, 5 Sevilla Sevilla 41010",
    "addr:housenumber":"5",
    "addr:postcode":"41010",
    "addr:street":"Calle De Olivares",
    "iso:country":"ES",
    "sg:address":"Calle de Olivares, 5",
    "sg:city":"Sevilla",
    "sg:orig_category":"Electromec\u00c1nica",
    "sg:phone":"+34 954 33 55 54",
    "sg:postcode":"41010",
    "sg:province":"Sevilla",
    "wof:name":"Moreno Castillo Manuel",
    "wof:placetype":"venue"
},
  "geometry": {"coordinates":[-6.0074548721,37.3813972473],"type":"Point"}
}