{
  "type": "Feature",
  "properties": {
    "addr:full":"Rond Caballero De La Mancha, 139 Madrid Madrid 28034",
    "addr:housenumber":"139",
    "addr:postcode":"28034",
    "addr:street":"Rond Caballero De La Mancha",
    "iso:country":"ES",
    "sg:address":"Rond Caballero De La Mancha, 139",
    "sg:city":"Madrid",
    "sg:orig_category":"Fotograf\u00cda Art\u00cdstica Y Retratos",
    "sg:phone":"+34 917 35 98 02",
    "sg:postcode":"28034",
    "sg:province":"Madrid",
    "wof:name":"Santos Aragundi Rafael",
    "wof:placetype":"venue"
},
  "geometry": {"coordinates":[-3.6886720657,40.5002288818],"type":"Point"}
}