{
  "type": "Feature",
  "properties": {
    "addr:full":"Calle de Calvario, 22 Burgos Burgos 09002",
    "addr:housenumber":"22",
    "addr:postcode":"09002",
    "addr:street":"Calle De Calvario",
    "iso:country":"ES",
    "sg:address":"Calle de Calvario, 22",
    "sg:city":"Burgos",
    "sg:orig_category":"Empresas De Carpinter\u00cda",
    "sg:phone":"+34 947 20 87 13",
    "sg:postcode":"09002",
    "sg:province":"Burgos",
    "wof:name":"Cogolos Tome Teodoro",
    "wof:placetype":"venue"
},
  "geometry": {"coordinates":[-3.6954107285,42.3349494934],"type":"Point"}
}