{
  "type": "Feature",
  "properties": {
    "addr:full":"Pase Alberto Palacios, 18 Madrid Madrid 28021",
    "addr:housenumber":"18",
    "addr:postcode":"madrid;28021",
    "addr:street":"Alberto Palacios",
    "iso:country":"ES",
    "sg:address":"Pase Alberto Palacios, 18",
    "sg:city":"Madrid",
    "sg:orig_category":"Alimentaci\u00d3n General (al Por Menor)",
    "sg:phone":"+34 917 97 23 07",
    "sg:postcode":"28021",
    "sg:province":"Madrid",
    "wof:name":"Quesos Benito S.a.",
    "wof:placetype":"venue"
},
  "geometry": {"coordinates":[-3.7126040459,40.3432235718],"type":"Point"}
}