{
  "type": "Feature",
  "properties": {
    "addr:full":"Calle de Colon, 4 Requena Valencia 46340",
    "addr:housenumber":"4",
    "addr:postcode":"46340",
    "addr:street":"Calle De Colon",
    "iso:country":"ES",
    "sg:address":"Calle de Colon, 4",
    "sg:city":"Requena",
    "sg:orig_category":"Fabricaci\u00d3n De Muebles",
    "sg:phone":"+34 962 30 02 43",
    "sg:postcode":"46340",
    "sg:province":"Valencia",
    "wof:name":"Muebles Gomez Torrijos Cdad",
    "wof:placetype":"venue"
},
  "geometry": {"coordinates":[-1.1026793718,39.4885139465],"type":"Point"}
}