{
  "type": "Feature",
  "properties": {
    "iso:country":"ES",
    "sg:address":"Cmno Ronda (de), 100",
    "sg:city":"Granada",
    "sg:orig_category":"M\u00c9dicos: Psiquiatr\u00cda",
    "sg:phone":"+34 958 25 66 16",
    "sg:postcode":"18004",
    "sg:province":"Granada",
    "wof:name":"Luque Baena Antonio",
    "wof:placetype":"venue"
},
  "geometry": {"coordinates":[-3.607227087,37.1726303101],"type":"Point"}
}