{
  "type": "Feature",
  "properties": {
    "addr:full":"Carrer de Proven\u00c7als, 267 Barcelona Barcelona 08020",
    "addr:housenumber":"267",
    "addr:postcode":"08020",
    "addr:street":"Carrer De Provenc\u0327Als",
    "iso:country":"ES",
    "sg:address":"Carrer de Proven\u00c7als, 267",
    "sg:city":"Barcelona",
    "sg:orig_category":"Dibujantes (diversos)",
    "sg:phone":"+34 933 03 37 14",
    "sg:postcode":"08020",
    "sg:province":"Barcelona",
    "wof:name":"Ballesteros Guardia Maria Cristina",
    "wof:placetype":"venue"
},
  "geometry": {"coordinates":[2.1959218979,41.4168815613],"type":"Point"}
}