{
  "type": "Feature",
  "properties": {
    "iso:country":"ES",
    "sg:address":"Calle de Ntra Sra De Gracia, 6",
    "sg:city":"Marbella",
    "sg:orig_category":"Caf\u00c9s, Bares, Cervecer\u00cdas",
    "sg:phone":"+34 952 82 31 88",
    "sg:postcode":"29600",
    "sg:province":"M\u00e1laga",
    "wof:name":"Jufevi S.c.",
    "wof:placetype":"venue"
},
  "geometry": {"coordinates":[-4.8908510208,36.5089111328],"type":"Point"}
}