{
  "type": "Feature",
  "properties": {
    "addr:full":"Calle de Martinez De Escobar Los, 3 Palmas De Gran Canaria Las Palmas 35007",
    "addr:postcode":"35007",
    "addr:street":"Calle De Martinez De Escobar Los",
    "iso:country":"ES",
    "sg:address":"Calle de Martinez De Escobar Los, 3",
    "sg:city":"Palmas De Gran Canaria",
    "sg:orig_category":"Abogados",
    "sg:phone":"+34 928 27 33 37",
    "sg:postcode":"35007",
    "sg:province":"Las Palmas",
    "wof:name":"Ruano Perez Carlos",
    "wof:placetype":"venue"
},
  "geometry": {"coordinates":[-15.4309406281,28.1384296417],"type":"Point"}
}