{
  "type": "Feature",
  "properties": {
    "addr:full":"Calle de Alozaina, 53 Malaga M\u00e1laga 29006",
    "addr:housenumber":"53",
    "addr:postcode":"29006",
    "addr:street":"Calle De Alozaina;Ma\u0301Laga",
    "iso:country":"ES",
    "sg:address":"Calle de Alozaina, 53",
    "sg:city":"Malaga",
    "sg:orig_category":"Ense\u00d1anza Secundaria: Colegios Y Escuelas Privadas",
    "sg:phone":"+34 952 36 28 61",
    "sg:postcode":"29006",
    "sg:province":"M\u00e1laga",
    "wof:name":"Junta De Andalucia- Ies Rafael Perez Estrada",
    "wof:placetype":"venue"
},
  "geometry": {"coordinates":[-4.4490947723,36.7096862793],"type":"Point"}
}