{
  "type": "Feature",
  "properties": {
    "iso:country":"ES",
    "sg:address":"Calle de Feduchy, 17",
    "sg:city":"Cadiz",
    "sg:orig_category":"Bisuter\u00cda, Joyer\u00cda, Relojer\u00cda (al Por Menor)",
    "sg:phone":"+34 956 28 36 05",
    "sg:postcode":"11005",
    "sg:province":"C\u00e1diz",
    "wof:name":"Freire Gestoso Jose Enrique",
    "wof:placetype":"venue"
},
  "geometry": {"coordinates":[-6.294195652,36.5316619873],"type":"Point"}
}