{
  "type": "Feature",
  "properties": {
    "iso:country":"ES",
    "sg:address":"Calle de Jeremias, 5",
    "sg:city":"Lodosa",
    "sg:orig_category":"Peluqueros: De Se\u00d1oras",
    "sg:phone":"+34 948 69 38 90",
    "sg:postcode":"31580",
    "sg:province":"Navarra",
    "wof:name":"Miranda Narbaiza Inmaculada",
    "wof:placetype":"venue"
},
  "geometry": {"coordinates":[-2.0766670704,42.4237327576],"type":"Point"}
}