{
  "type": "Feature",
  "properties": {
    "addr:full":"Avda Habana, 12 Melide La Coru\u00f1a 15800",
    "addr:housenumber":"12",
    "addr:postcode":"15800",
    "addr:street":"Avda Habana;La Corun\u0303A",
    "iso:country":"ES",
    "sg:address":"Avda Habana, 12",
    "sg:city":"Melide",
    "sg:orig_category":"Electricidad, Electr\u00d3nica: Suministros (al Por Menor)",
    "sg:phone":"+34 981 50 55 21",
    "sg:postcode":"15800",
    "sg:province":"La Coru\u00f1a",
    "wof:name":"Nu\u00f1ez Taboada Miguel",
    "wof:placetype":"venue"
},
  "geometry": {"coordinates":[-8.0128622055,42.9140319824],"type":"Point"}
}