{
  "type": "Feature",
  "properties": {
    "addr:full":"Urb Cuba (la), 1 Crespos \u00c1vila 05300",
    "addr:postcode":"05300",
    "addr:street":"Urb;La 1;A\u0301Vila",
    "iso:country":"ES",
    "sg:address":"Urb Cuba (la), 1",
    "sg:city":"Crespos",
    "sg:orig_category":"Promotores Constructores",
    "sg:phone":"+34 920 24 40 81",
    "sg:postcode":"05300",
    "sg:province":"\u00c1vila",
    "wof:name":"Martin Martin Juan Jose",
    "wof:placetype":"venue"
},
  "geometry": {"coordinates":[-4.9710350037,40.8741416931],"type":"Point"}
}