{
  "type": "Feature",
  "properties": {
    "addr:full":"Calle de Panama, 5 Madrid Madrid 28036",
    "addr:housenumber":"5",
    "addr:postcode":"28036",
    "addr:street":"Calle De Panama",
    "iso:country":"ES",
    "sg:address":"Calle de Panama, 5",
    "sg:city":"Madrid",
    "sg:orig_category":"Administradores De Bienes Y Delegados De Comunidades De Propietarios",
    "sg:phone":"+34 914 58 16 77",
    "sg:postcode":"28036",
    "sg:province":"Madrid",
    "wof:name":"Aguayo & Escamez S.l.",
    "wof:placetype":"venue"
},
  "geometry": {"coordinates":[-3.6872992516,40.4566650391],"type":"Point"}
}