{
  "type": "Feature",
  "properties": {
    "addr:full":"Ctra Torrejon (de), Km. 0000,9 Ajalvir Madrid 28864",
    "addr:postcode":"28864",
    "addr:street":"Ctra Torrejon De Km. 0000,9",
    "iso:country":"ES",
    "sg:address":"Ctra Torrejon (de), Km. 0000,9",
    "sg:city":"Ajalvir",
    "sg:orig_category":"Librer\u00cdas",
    "sg:phone":"+34 918 86 28 06",
    "sg:postcode":"28864",
    "sg:province":"Madrid",
    "wof:name":"Edicciones Altosa S.l.",
    "wof:placetype":"venue"
},
  "geometry": {"coordinates":[-3.4812130928,40.5272102356],"type":"Point"}
}