{
  "type": "Feature",
  "properties": {
    "iso:country":"ES",
    "sg:address":"Carrer de Cometa, 4",
    "sg:city":"Barcelona",
    "sg:orig_category":"Agencias Y Agentes Comerciales, Representantes",
    "sg:phone":"+34 933 15 24 21",
    "sg:postcode":"08002",
    "sg:province":"Barcelona",
    "wof:name":"Schapira Gorban Enrique Mario",
    "wof:placetype":"venue"
},
  "geometry": {"coordinates":[2.179156065,41.3820457458],"type":"Point"}
}