{
  "type": "Feature",
  "properties": {
    "iso:country":"ES",
    "sg:address":"Rua Juan Xxiii, 8",
    "sg:city":"Ourense",
    "sg:orig_category":"Supermercados Y Hipermercados",
    "sg:phone":"+34 988 21 18 08",
    "sg:postcode":"32003",
    "sg:province":"Ourense",
    "wof:name":"Rodriguez Vilar Jose",
    "wof:placetype":"venue"
},
  "geometry": {"coordinates":[-7.8657679558,42.34034729],"type":"Point"}
}