{
  "type": "Feature",
  "properties": {
    "iso:country":"ES",
    "sg:address":"Calle de Etxaburua, 21",
    "sg:city":"Berriozar",
    "sg:orig_category":"Arquitectos",
    "sg:phone":"+34 948 24 65 62",
    "sg:postcode":"31013",
    "sg:province":"Navarra",
    "wof:name":"Barcos Y Enriquez Arquitectos",
    "wof:placetype":"venue"
},
  "geometry": {"coordinates":[-1.672942996,42.8451271057],"type":"Point"}
}