{
  "type": "Feature",
  "properties": {
    "iso:country":"ES",
    "sg:address":"Carr Andalucia, 40",
    "sg:city":"Villarreal",
    "sg:orig_category":"Cerrajer\u00cda, Ferrallista",
    "sg:phone":"+34 964 52 19 77",
    "sg:postcode":"12540",
    "sg:province":"Castell\u00f3n",
    "wof:name":"Fertica C.b",
    "wof:placetype":"venue"
},
  "geometry": {"coordinates":[-0.0951087996,39.948551178],"type":"Point"}
}