{
  "type": "Feature",
  "properties": {
    "addr:full":"Ctra Sentmenat, 60 Poligono Barcelona 08213",
    "addr:housenumber":"60 poligono",
    "addr:postcode":"08213",
    "addr:street":"Ctra Sentmenat;Barcelona",
    "iso:country":"ES",
    "sg:address":"Ctra Sentmenat, 60",
    "sg:city":"Poligono",
    "sg:orig_category":"Agentes, Concesionarios Y Sucursales De Veh\u00cdculos",
    "sg:phone":"+34 937 13 17 76",
    "sg:postcode":"08213",
    "sg:province":"Barcelona",
    "wof:name":"Garriga Vidal Pedro",
    "wof:placetype":"venue"
},
  "geometry": {"coordinates":[2.1571440697,41.5534934998],"type":"Point"}
}