{
  "type": "Feature",
  "properties": {
    "addr:full":"Avda Doctor Mara\u00d1on, 7 Catarroja Valencia 46470",
    "addr:housenumber":"7",
    "addr:postcode":"46470",
    "addr:street":"Avda Doctor Maran\u0303On",
    "iso:country":"ES",
    "sg:address":"Avda Doctor Mara\u00d1on, 7",
    "sg:city":"Catarroja",
    "sg:orig_category":"Promotores Constructores",
    "sg:phone":"+34 961 27 46 99",
    "sg:postcode":"46470",
    "sg:province":"Valencia",
    "wof:name":"Construcciones Paterna 2000 S.l.",
    "wof:placetype":"venue"
},
  "geometry": {"coordinates":[-0.4000940025,39.4058227539],"type":"Point"}
}