{
  "type": "Feature",
  "properties": {
    "addr:full":"Urb N Enramadilla, S/n Sevilla Sevilla 41018",
    "addr:housenumber":"/ n",
    "addr:postcode":"41018",
    "addr:street":"Urb;Enramadilla S",
    "iso:country":"ES",
    "sg:address":"Urb N Enramadilla, S/n",
    "sg:city":"Sevilla",
    "sg:orig_category":"Abogados",
    "sg:phone":"+34 954 65 89 61",
    "sg:postcode":"41018",
    "sg:province":"Sevilla",
    "wof:name":"Valverde Mu\u00f1oz Manuel",
    "wof:placetype":"venue"
},
  "geometry": {"coordinates":[-5.978913784,37.3786201477],"type":"Point"}
}