{
  "type": "Feature",
  "properties": {
    "iso:country":"ES",
    "sg:address":"C/ Alcalde Juan Hernandez Rizo, 11",
    "sg:city":"Elche",
    "sg:orig_category":"Abogados",
    "sg:phone":"+34 965 42 31 54",
    "sg:postcode":"03203",
    "sg:province":"Alicante",
    "wof:name":"Proclismar S.l",
    "wof:placetype":"venue"
},
  "geometry": {"coordinates":[-0.6723440289,38.267162323],"type":"Point"}
}