{
  "type": "Feature",
  "properties": {
    "addr:full":"Carrer de Despuig, 49 Palma Islas Baleares 07013",
    "addr:housenumber":"49",
    "addr:postcode":"07013",
    "addr:street":"Carrer De Despuig",
    "iso:country":"ES",
    "sg:address":"Carrer de Despuig, 49",
    "sg:city":"Palma",
    "sg:orig_category":"Muebles Y Accesorios Para Cocinas Y Cuartos De Ba\u00d1o (al Por Menor)",
    "sg:phone":"+34 971 28 99 00",
    "sg:postcode":"07013",
    "sg:province":"Islas Baleares",
    "wof:name":"Bricolage Vives S.l.",
    "wof:placetype":"venue"
},
  "geometry": {"coordinates":[2.6354689598,39.5725631714],"type":"Point"}
}