{
  "type": "Feature",
  "properties": {
    "addr:full":"Calle de Jose De Sosa, S/n Roque Las Palmas 35460",
    "addr:housenumber":"s / n",
    "addr:postcode":"35460",
    "addr:street":"Calle De Jose De Sosa;Roque Las Palmas",
    "iso:country":"ES",
    "sg:address":"Calle de Jose De Sosa, S/n",
    "sg:city":"Roque",
    "sg:orig_category":"Asilos De Ancianos. Centros Privados",
    "sg:phone":"+34 928 88 23 10",
    "sg:postcode":"35460",
    "sg:province":"Las Palmas",
    "wof:name":"Ayuntamiento De Galdar",
    "wof:placetype":"venue"
},
  "geometry": {"coordinates":[-15.4771022797,27.9428863525],"type":"Point"}
}