{
  "type": "Feature",
  "properties": {
    "iso:country":"ES",
    "sg:address":"Calle de Camara La, 77",
    "sg:city":"Aviles",
    "sg:orig_category":"Panader\u00cdas, Panader\u00cdas",
    "sg:phone":"+34 985 56 92 06",
    "sg:postcode":"33401",
    "sg:province":"Asturias",
    "wof:name":"Conejo Roco Vidal",
    "wof:placetype":"venue"
},
  "geometry": {"coordinates":[-5.9257535934,43.5608634949],"type":"Point"}
}