{
  "type": "Feature",
  "properties": {
    "iso:country":"ES",
    "sg:address":"Urb Eden Residencial, 1",
    "sg:city":"Manga Mar Menor",
    "sg:orig_category":"Empresas De Limpieza",
    "sg:phone":"+34 968 14 11 22",
    "sg:postcode":"30380",
    "sg:province":"Murcia",
    "wof:name":"Diaz De Icaza Fernando",
    "wof:placetype":"venue"
},
  "geometry": {"coordinates":[-0.7281540036,37.6686553955],"type":"Point"}
}