{
  "type": "Feature",
  "properties": {
    "iso:country":"ES",
    "sg:address":"Calle de Lineros, 19",
    "sg:city":"Sevilla",
    "sg:orig_category":"Bazares, Art\u00cdculos De Limpieza Y De Cocina (al Por Menor)",
    "sg:phone":"+34 954 21 45 30",
    "sg:postcode":"41004",
    "sg:province":"Sevilla",
    "wof:name":"Cano Cordoba Francisco Javier",
    "wof:placetype":"venue"
},
  "geometry": {"coordinates":[-5.9922709465,37.3905563354],"type":"Point"}
}