{
  "type": "Feature",
  "properties": {
    "addr:full":"Plaz Tomas Y Valiente, 2 Logro\u00f1o La Rioja 26004",
    "addr:housenumber":"2",
    "addr:postcode":"26004",
    "addr:street":"Plaz Tomas Y Valiente;Rioja",
    "iso:country":"ES",
    "sg:address":"Plaz Tomas Y Valiente, 2",
    "sg:city":"Logro\u00f1o",
    "sg:orig_category":"Escayola Y Productos De Escayola (fabricaci\u00d3n, Al Por Mayor)",
    "sg:phone":"+34 941 24 80 52",
    "sg:postcode":"26004",
    "sg:province":"La Rioja",
    "wof:name":"Escayolas Marce S.l.",
    "wof:placetype":"venue"
},
  "geometry": {"coordinates":[-2.4319770336,42.4692001343],"type":"Point"}
}