{
  "type": "Feature",
  "properties": {
    "iso:country":"ES",
    "sg:address":"Calle de Gaztelubide, S/n",
    "sg:city":"Lamiako",
    "sg:orig_category":"Asesor\u00cda Sobre Comunicaci\u00d3n De Empresas",
    "sg:phone":"+34 944 63 92 35",
    "sg:postcode":"48940",
    "sg:province":"Vizcaya",
    "sg:website":"www.gaztelueta.com",
    "wof:name":"Asociacion Loizaga",
    "wof:placetype":"venue"
},
  "geometry": {"coordinates":[-3.0050320625,43.3257904053],"type":"Point"}
}