{
  "type": "Feature",
  "properties": {
    "iso:country":"ES",
    "sg:address":"Pg Sant Joan Bosco, 104",
    "sg:city":"Girona",
    "sg:orig_category":"Pintura Y Barniz (al Por Menor)",
    "sg:phone":"+34 972 20 96 21",
    "sg:postcode":"17007",
    "sg:province":"Girona",
    "wof:name":"Pintures M. Vich S. A.",
    "wof:placetype":"venue"
},
  "geometry": {"coordinates":[2.8252310753,42.00963974],"type":"Point"}
}