{
  "type": "Feature",
  "properties": {
    "addr:full":"Calle de Venenciadores, 10 Conil De La Frontera C\u00e1diz 11140",
    "addr:housenumber":"10",
    "addr:postcode":"11140",
    "addr:street":"Calle De Venenciadores",
    "iso:country":"ES",
    "sg:address":"Calle de Venenciadores, 10",
    "sg:city":"Conil De La Frontera",
    "sg:orig_category":"Zapatos (al Por Menor)",
    "sg:phone":"+34 956 44 34 14",
    "sg:postcode":"11140",
    "sg:province":"C\u00e1diz",
    "wof:name":"Jimenez Caro Jose Carlos",
    "wof:placetype":"venue"
},
  "geometry": {"coordinates":[-6.0884289742,36.2783584595],"type":"Point"}
}