{
  "type": "Feature",
  "properties": {
    "addr:full":"Carr Pons I Arola, 79 Linyola Lleida 25240",
    "addr:housenumber":"79",
    "addr:postcode":"25240",
    "addr:street":"Carr Pons;Arola",
    "iso:country":"ES",
    "sg:address":"Carr Pons I Arola, 79",
    "sg:city":"Linyola",
    "sg:orig_category":"Chapister\u00cda",
    "sg:phone":"+34 973 57 55 69",
    "sg:postcode":"25240",
    "sg:province":"Lleida",
    "wof:name":"Auto Gamero S.l.",
    "wof:placetype":"venue"
},
  "geometry": {"coordinates":[0.9038066268,41.7073669434],"type":"Point"}
}