{
  "type": "Feature",
  "properties": {
    "addr:full":"Calle de Diecinueve De Abril, 36 Dos Hermanas Sevilla 41700",
    "addr:housenumber":"36",
    "addr:postcode":"41700",
    "addr:street":"Calle De Diecinueve De Abril",
    "iso:country":"ES",
    "sg:address":"Calle de Diecinueve De Abril, 36",
    "sg:city":"Dos Hermanas",
    "sg:orig_category":"Fabricaci\u00d3n, Venta De Cuadros, Accesorios Para Enmarcar",
    "sg:phone":"+34 955 66 74 88",
    "sg:postcode":"41700",
    "sg:province":"Sevilla",
    "wof:name":"Andaluza De Marqueteria S.l.",
    "wof:placetype":"venue"
},
  "geometry": {"coordinates":[-5.9341044426,37.2881126404],"type":"Point"}
}