{
  "type": "Feature",
  "properties": {
    "iso:country":"ES",
    "sg:address":"Carrer de Parellada (la), 26",
    "sg:city":"Vilafranca Penedes",
    "sg:orig_category":"Ropa Para Ni\u00d1os (al Por Menor)",
    "sg:phone":"+34 938 92 10 94",
    "sg:postcode":"08720",
    "sg:province":"Barcelona",
    "sg:website":"www.ikks.com",
    "wof:name":"Montfort Canals Juan",
    "wof:placetype":"venue"
},
  "geometry": {"coordinates":[1.6996320486,41.3463249207],"type":"Point"}
}