{
  "type": "Feature",
  "properties": {
    "iso:country":"ES",
    "sg:address":"Avda Villamayor, 54",
    "sg:city":"Salamanca",
    "sg:orig_category":"Droguer\u00cdas (al Por Menor)",
    "sg:phone":"+34 923 22 69 84",
    "sg:postcode":"37007",
    "sg:province":"Salamanca",
    "wof:name":"Cembellin Lorenzo Eusebio",
    "wof:placetype":"venue"
},
  "geometry": {"coordinates":[-5.6702489853,40.9706687927],"type":"Point"}
}