{
  "type": "Feature",
  "properties": {
    "iso:country":"ES",
    "sg:address":"Av Republica Argentina, 191",
    "sg:city":"Barcelona",
    "sg:orig_category":"Venta, Colocaci\u00d3n De Moquetas, Revestimiento De Suelos Y De Paredes",
    "sg:phone":"+34 932 11 15 99",
    "sg:postcode":"08023",
    "sg:province":"Barcelona",
    "wof:name":"Vidal Torres Juan",
    "wof:placetype":"venue"
},
  "geometry": {"coordinates":[2.1415240765,41.4115257263],"type":"Point"}
}