{
  "type": "Feature",
  "properties": {
    "iso:country":"ES",
    "sg:address":"Calle de Latina, 26",
    "sg:city":"Madrid",
    "sg:orig_category":"Ingenier\u00cda, Centros De Estudios (diversos)",
    "sg:phone":"+34 914 64 65 73",
    "sg:postcode":"28047",
    "sg:province":"Madrid",
    "wof:name":"Intemon Ingenieria S.l.",
    "wof:placetype":"venue"
},
  "geometry": {"coordinates":[-3.7511839867,40.4009552002],"type":"Point"}
}