{
  "type": "Feature",
  "properties": {
    "iso:country":"ES",
    "sg:address":"Avgd Salvador Espriu, S/n",
    "sg:city":"Badalona",
    "sg:orig_category":"Asociaciones Y Clubs Deportivos",
    "sg:phone":"+34 933 83 86 98",
    "sg:postcode":"08917",
    "sg:province":"Barcelona",
    "wof:name":"Asociacio Esportiva Pere Gol",
    "wof:placetype":"venue"
},
  "geometry": {"coordinates":[2.2321147919,41.4460601807],"type":"Point"}
}