{
  "type": "Feature",
  "properties": {
    "addr:full":"Crri Santa Rosa, 4 Malaga M\u00e1laga 29007",
    "addr:housenumber":"4",
    "addr:postcode":"29007",
    "addr:street":"Santa Rosa;Ma\u0301Laga",
    "iso:country":"ES",
    "sg:address":"Crri Santa Rosa, 4",
    "sg:city":"Malaga",
    "sg:orig_category":"Servidores Y Editores De Bases De Datos",
    "sg:phone":"+34 952 61 75 12",
    "sg:postcode":"29007",
    "sg:province":"M\u00e1laga",
    "sg:website":"www.une-internet.com",
    "wof:name":"Une Internet Factory Spain S.l.",
    "wof:placetype":"venue"
},
  "geometry": {"coordinates":[-4.4201588631,36.7183189392],"type":"Point"}
}