{
  "type": "Feature",
  "properties": {
    "addr:full":"Calle de Vitoria, 162 Burgos Burgos 09007",
    "addr:housenumber":"162",
    "addr:postcode":"09007",
    "addr:street":"Calle De Vitoria",
    "iso:country":"ES",
    "sg:address":"Calle de Vitoria, 162",
    "sg:city":"Burgos",
    "sg:orig_category":"Aud\u00cdfonos",
    "sg:phone":"+34 947 24 21 73",
    "sg:postcode":"09007",
    "sg:province":"Burgos",
    "wof:name":"Asociacion Nacional De Audioprotesistas",
    "wof:placetype":"venue"
},
  "geometry": {"coordinates":[-3.6731975079,42.3509788513],"type":"Point"}
}