{
  "type": "Feature",
  "properties": {
    "iso:country":"ES",
    "sg:address":"Otaola Hiribidea, 1",
    "sg:city":"Eibar",
    "sg:orig_category":"Asociaciones, Organismos Culturales Y Socioeducativos",
    "sg:phone":"+34 943 82 14 26",
    "sg:postcode":"20600",
    "sg:province":"Guip\u00f9zcoa",
    "wof:name":"Udako Euskal Unibertsitatea Ueu",
    "wof:placetype":"venue"
},
  "geometry": {"coordinates":[-2.4795749187,43.1831512451],"type":"Point"}
}