{
  "type": "Feature",
  "properties": {
    "addr:full":"Calle de Victor Pradera, 36 Chipiona C\u00e1diz 11550",
    "addr:housenumber":"36",
    "addr:postcode":"11550",
    "addr:street":"Calle De Victor Pradera",
    "iso:country":"ES",
    "sg:address":"Calle de Victor Pradera, 36",
    "sg:city":"Chipiona",
    "sg:orig_category":"Asesor\u00cda Fiscal Y Jur\u00cddica",
    "sg:phone":"+34 956 37 08 62",
    "sg:postcode":"11550",
    "sg:province":"C\u00e1diz",
    "wof:name":"Aficon T.m.c. S.l.l.",
    "wof:placetype":"venue"
},
  "geometry": {"coordinates":[-6.4330396652,36.7385902405],"type":"Point"}
}