{
  "type": "Feature",
  "properties": {
    "iso:country":"ES",
    "sg:address":"Carr Ramon Muntaner, 69",
    "sg:city":"Eivissa",
    "sg:orig_category":"Alquiler De Veh\u00cdculos: Turismos Y Utilitarios",
    "sg:phone":"+34 971 30 49 20",
    "sg:postcode":"07800",
    "sg:province":"Islas Baleares",
    "wof:name":"Autos Es Cana S.a.",
    "wof:placetype":"venue"
},
  "geometry": {"coordinates":[1.4282574654,38.9047775269],"type":"Point"}
}