{
  "type": "Feature",
  "properties": {
    "addr:full":"Calle de Estocolmo, 25 Alcorcon Madrid 28921",
    "addr:housenumber":"25",
    "addr:postcode":"28921",
    "addr:street":"Calle De Estocolmo",
    "iso:country":"ES",
    "sg:address":"Calle de Estocolmo, 25",
    "sg:city":"Alcorcon",
    "sg:orig_category":"Trabajos De Perforaciones, Sondeos, Construcci\u00d3n De Pozos",
    "sg:phone":"+34 916 09 18 73",
    "sg:postcode":"28921",
    "sg:province":"Madrid",
    "wof:name":"Geohercas S.l.",
    "wof:placetype":"venue"
},
  "geometry": {"coordinates":[-3.8242239952,40.3513946533],"type":"Point"}
}