{
  "type": "Feature",
  "properties": {
    "iso:country":"ES",
    "sg:address":"Carril Ortigosa, S/n",
    "sg:city":"Mahora",
    "sg:orig_category":"Semiller\u00cdas",
    "sg:phone":"+34 967 49 41 54",
    "sg:postcode":"02240",
    "sg:province":"Albacete",
    "wof:name":"Secadema S.c.a.",
    "wof:placetype":"venue"
},
  "geometry": {"coordinates":[-1.7249890566,39.2094345093],"type":"Point"}
}