{
  "type": "Feature",
  "properties": {
    "iso:country":"ES",
    "sg:address":"Gaig (urb El Serrat De L'ocata), 3",
    "sg:city":"Ametlla Valles",
    "sg:orig_category":"Promotores Constructores",
    "sg:phone":"+34 938 45 70 44",
    "sg:postcode":"08480",
    "sg:province":"Barcelona",
    "wof:name":"Construcciones Y Reformas Acevil,s.l.",
    "wof:placetype":"venue"
},
  "geometry": {"coordinates":[2.2421710491,41.692615509],"type":"Point"}
}