{
  "type": "Feature",
  "properties": {
    "iso:country":"ES",
    "sg:address":"Calle de Santa Catalina, 9",
    "sg:city":"Loja",
    "sg:orig_category":"Frutas, Legumbres Frescas Y Tempranas (al Por Menor)",
    "sg:phone":"+34 958 32 36 92",
    "sg:postcode":"18300",
    "sg:province":"Granada",
    "wof:name":"Saavedra Hermanos S.l.",
    "wof:placetype":"venue"
},
  "geometry": {"coordinates":[-4.1494069099,37.1652069092],"type":"Point"}
}