{
  "type": "Feature",
  "properties": {
    "iso:country":"ES",
    "sg:address":"Carr Jose Vidal Canet, De, 7",
    "sg:city":"Carcaixent",
    "sg:orig_category":"Aparcamientos (infraestructuras, Accesorios)",
    "sg:phone":"+34 962 43 10 11",
    "sg:postcode":"46740",
    "sg:province":"Valencia",
    "wof:name":"Garaje Vidal Carcaixent S.l.",
    "wof:placetype":"venue"
},
  "geometry": {"coordinates":[-0.4494690895,39.124961853],"type":"Point"}
}