{
  "type": "Feature",
  "properties": {
    "addr:full":"Calle de Alfonso Quintanilla, 1 Medina Campo Valladolid 47400",
    "addr:housenumber":"1",
    "addr:postcode":"47400",
    "addr:street":"Calle De Alfonso Quintanilla",
    "iso:country":"ES",
    "sg:address":"Calle de Alfonso Quintanilla, 1",
    "sg:city":"Medina Campo",
    "sg:orig_category":"Mercer\u00cda, Lencer\u00cda (al Por Menor)",
    "sg:phone":"+34 983 81 05 19",
    "sg:postcode":"47400",
    "sg:province":"Valladolid",
    "wof:name":"Medina La Rueca S.l.",
    "wof:placetype":"venue"
},
  "geometry": {"coordinates":[-4.9170622826,41.3090705872],"type":"Point"}
}