{
  "type": "Feature",
  "properties": {
    "iso:country":"ES",
    "sg:address":"Carrer de Eugeni D'ors, 48",
    "sg:city":"Vilafranca Penedes",
    "sg:orig_category":"Restaurantes",
    "sg:phone":"+34 938 17 13 19",
    "sg:postcode":"08720",
    "sg:province":"Barcelona",
    "wof:name":"Mata Gimenez Andres",
    "wof:placetype":"venue"
},
  "geometry": {"coordinates":[1.6916046143,41.3425331116],"type":"Point"}
}