{
  "type": "Feature",
  "properties": {
    "iso:country":"ES",
    "sg:address":"Ctra. Mera, 61",
    "sg:city":"Cari\u00f1o",
    "sg:orig_category":"Carnicer\u00cdas, Carnicer\u00cdas",
    "sg:phone":"+34 981 40 52 57",
    "sg:postcode":"15360",
    "sg:province":"La Coru\u00f1a",
    "wof:name":"Dopico Sande Francisco Luis",
    "wof:placetype":"venue"
},
  "geometry": {"coordinates":[-7.8746237755,43.7365341187],"type":"Point"}
}