{
  "type": "Feature",
  "properties": {
    "iso:country":"ES",
    "sg:address":"Calle de Espinillo (del), 7",
    "sg:city":"Valdemoro",
    "sg:orig_category":"Loter\u00cda Y T\u00d3mbola",
    "sg:phone":"+34 918 09 46 13",
    "sg:postcode":"28340",
    "sg:province":"Madrid",
    "wof:name":"Garcia Calles Tomas",
    "wof:placetype":"venue"
},
  "geometry": {"coordinates":[-3.6880578995,40.1907043457],"type":"Point"}
}