{
  "type": "Feature",
  "properties": {
    "iso:country":"ES",
    "sg:address":"Plaz Lonja (la), 2",
    "sg:city":"Gerena",
    "sg:orig_category":"Cajas Para Embalar",
    "sg:phone":"+34 955 78 20 65",
    "sg:postcode":"41860",
    "sg:province":"Sevilla",
    "wof:name":"Caja Rural Del Sur Sociedad Cooperativa",
    "wof:placetype":"venue"
},
  "geometry": {"coordinates":[-6.1561160088,37.5270805359],"type":"Point"}
}