{
  "type": "Feature",
  "properties": {
    "addr:full":"Calle de Cabeza, 8 Madrid Madrid 28012",
    "addr:housenumber":"8",
    "addr:postcode":"madrid;28012",
    "addr:street":"Calle De Cabeza",
    "iso:country":"ES",
    "sg:address":"Calle de Cabeza, 8",
    "sg:city":"Madrid",
    "sg:orig_category":"Lencer\u00cda Femenina, Corseter\u00cda, Trajes De Ba\u00d1o (al Por Menor)",
    "sg:phone":"+34 914 68 08 01",
    "sg:postcode":"28012",
    "sg:province":"Madrid",
    "wof:name":"Lenceria Corseteria Marisa S.a.",
    "wof:placetype":"venue"
},
  "geometry": {"coordinates":[-3.7034552097,40.4117889404],"type":"Point"}
}