{
  "type": "Feature",
  "properties": {
    "iso:country":"ES",
    "sg:address":"Carrer de Mare De Deu De La Cisa, 32",
    "sg:city":"Mataro",
    "sg:orig_category":"Pescader\u00cdas (al Por Menor)",
    "sg:phone":"+34 937 99 82 07",
    "sg:postcode":"08303",
    "sg:province":"Barcelona",
    "wof:name":"Pescados Marquero S.l.",
    "wof:placetype":"venue"
},
  "geometry": {"coordinates":[2.4269080162,41.5373840332],"type":"Point"}
}