{
  "type": "Feature",
  "properties": {
    "addr:full":"Calle de Santiago Lozano, 17 Granada Granada 18011",
    "addr:housenumber":"17",
    "addr:postcode":"18011",
    "addr:street":"Calle De Santiago Lozano",
    "iso:country":"ES",
    "sg:address":"Calle de Santiago Lozano, 17",
    "sg:city":"Granada",
    "sg:orig_category":"Arreglo, Reparaci\u00d3n, Piezas Sueltas De Televisi\u00d3n, V\u00cddeo, Hi",
    "sg:phone":"+34 958 15 45 07",
    "sg:postcode":"18011",
    "sg:province":"Granada",
    "wof:name":"Jimenez Diaz Jose",
    "wof:placetype":"venue"
},
  "geometry": {"coordinates":[-3.6018199921,37.1972961426],"type":"Point"}
}