{
  "type": "Feature",
  "properties": {
    "addr:full":"Calle de Alcalde Suarez Franchy, 21 Arucas Las Palmas 35400",
    "addr:housenumber":"21",
    "addr:postcode":"35400",
    "addr:street":"Calle De Alcalde Suarez Franchy",
    "iso:country":"ES",
    "sg:address":"Calle de Alcalde Suarez Franchy, 21",
    "sg:city":"Arucas",
    "sg:orig_category":"Peluqueros: De Se\u00d1oras",
    "sg:phone":"+34 928 60 58 03",
    "sg:postcode":"35400",
    "sg:province":"Las Palmas",
    "wof:name":"Henriquez Perez Maria Pino",
    "wof:placetype":"venue"
},
  "geometry": {"coordinates":[-15.5245132446,28.1180667877],"type":"Point"}
}