{
  "type": "Feature",
  "properties": {
    "addr:full":"Calle de Tellez, 30 Madrid Madrid 28007",
    "addr:housenumber":"30",
    "addr:postcode":"madrid;28007",
    "addr:street":"Calle De Tellez",
    "iso:country":"ES",
    "sg:address":"Calle de Tellez, 30",
    "sg:city":"Madrid",
    "sg:orig_category":"Agencias De Viajes",
    "sg:phone":"+34 915 02 18 47",
    "sg:postcode":"28007",
    "sg:province":"Madrid",
    "sg:website":"www.sierranevadaski.com",
    "wof:name":"Sierra Nevada Club Agencia De Viajes S.a.",
    "wof:placetype":"venue"
},
  "geometry": {"coordinates":[-3.6796329021,40.4013786316],"type":"Point"}
}