{
  "type": "Feature",
  "properties": {
    "iso:country":"ES",
    "sg:address":"Gayos (areas), 6",
    "sg:city":"Gayos",
    "sg:orig_category":"Centros De Educaci\u00d3n Especial",
    "sg:phone":"+34 986 60 37 27",
    "sg:postcode":"36711",
    "sg:province":"Pontevedra",
    "wof:name":"Ayuntamiento De Tuy",
    "wof:placetype":"venue"
},
  "geometry": {"coordinates":[-8.6480531693,42.4336204529],"type":"Point"}
}