{
  "type": "Feature",
  "properties": {
    "addr:full":"Calle de Emigrante (el), S/n Santisteban Puerto Ja\u00e9n 23250",
    "addr:housenumber":"s / n",
    "addr:postcode":"23250",
    "addr:street":"Calle De Emigrante El;Jae\u0301N",
    "iso:country":"ES",
    "sg:address":"Calle de Emigrante (el), S/n",
    "sg:city":"Santisteban Puerto",
    "sg:orig_category":"Promotores Constructores",
    "sg:phone":"+34 953 40 23 87",
    "sg:postcode":"23250",
    "sg:province":"Ja\u00e9n",
    "wof:name":"Gonzalez Padilla Agapito",
    "wof:placetype":"venue"
},
  "geometry": {"coordinates":[-3.1991055012,38.2509422302],"type":"Point"}
}