{
  "type": "Feature",
  "properties": {
    "iso:country":"ES",
    "sg:address":"Cm\u00d1o Espedrigada, 11",
    "sg:city":"Vigo",
    "sg:orig_category":"Fabrica, Negocio De Vidrieras, Productos Vidriados Y Espejos",
    "sg:phone":"+34 986 29 47 47",
    "sg:postcode":"36210",
    "sg:province":"Pontevedra",
    "wof:name":"Cristartevigo S.l.",
    "wof:placetype":"venue"
},
  "geometry": {"coordinates":[-8.734913826,42.2175483704],"type":"Point"}
}