{
  "type": "Feature",
  "properties": {
    "addr:full":"Edif. San Jose, 6 Badajoz Badajoz 06005",
    "addr:housenumber":"6",
    "addr:postcode":"06005",
    "iso:country":"ES",
    "sg:address":"Edif. San Jose, 6",
    "sg:city":"Badajoz",
    "sg:orig_category":"Agencias Y Agentes Comerciales, Representantes",
    "sg:phone":"+34 924 23 01 46",
    "sg:postcode":"06005",
    "sg:province":"Badajoz",
    "wof:name":"Torrado Pacheco Rafael",
    "wof:placetype":"venue"
},
  "geometry": {"coordinates":[-6.9726238251,38.874835968],"type":"Point"}
}