{
  "type": "Feature",
  "properties": {
    "addr:full":"Calle de Puerto, 34 Huelva Huelva 21001",
    "addr:housenumber":"34",
    "addr:postcode":"21001",
    "addr:street":"Calle De Puerto",
    "iso:country":"ES",
    "sg:address":"Calle de Puerto, 34",
    "sg:city":"Huelva",
    "sg:orig_category":"Servicios Diversos",
    "sg:phone":"+34 959 28 37 44",
    "sg:postcode":"21001",
    "sg:province":"Huelva",
    "wof:name":"Sistemasdeoficinasdehuelvas.a.",
    "wof:placetype":"venue"
},
  "geometry": {"coordinates":[-6.9538459778,37.2588882446],"type":"Point"}
}