{
  "type": "Feature",
  "properties": {
    "iso:country":"ES",
    "sg:address":"Avda Castrelos, 62",
    "sg:city":"Vigo",
    "sg:orig_category":"Peluquer\u00cdas, Peluquer\u00cda Mixta",
    "sg:phone":"+34 986 29 18 08",
    "sg:postcode":"36210",
    "sg:province":"Pontevedra",
    "wof:name":"Peluqueria Maruja S.l.",
    "wof:placetype":"venue"
},
  "geometry": {"coordinates":[-8.7325754166,42.2171134949],"type":"Point"}
}