{
  "type": "Feature",
  "properties": {
    "iso:country":"ES",
    "sg:address":"Avda Republica Argentina, 12",
    "sg:city":"Sevilla",
    "sg:orig_category":"Perfumer\u00cda (al Por Menor)",
    "sg:phone":"+34 954 28 08 50",
    "sg:postcode":"41011",
    "sg:province":"Sevilla",
    "sg:website":"www.avon.es",
    "wof:name":"Avon Cosmetics S.a.",
    "wof:placetype":"venue"
},
  "geometry": {"coordinates":[-5.9994397163,37.3791999817],"type":"Point"}
}