{
  "type": "Feature",
  "properties": {
    "addr:full":"Calle de General Villacampa, 1 Sabi\u00f1anigo Huesca 22600",
    "addr:housenumber":"1",
    "addr:postcode":"22600",
    "addr:street":"Calle De General Villacampa",
    "iso:country":"ES",
    "sg:address":"Calle de General Villacampa, 1",
    "sg:city":"Sabi\u00f1anigo",
    "sg:orig_category":"Peluquer\u00cdas, Peluquer\u00cda Mixta",
    "sg:phone":"+34 974 48 15 58",
    "sg:postcode":"22600",
    "sg:province":"Huesca",
    "wof:name":"Usieto Santolaria Amelia",
    "wof:placetype":"venue"
},
  "geometry": {"coordinates":[-0.3638640046,42.5195350647],"type":"Point"}
}