{
  "type": "Feature",
  "properties": {
    "iso:country":"ES",
    "sg:address":"Calle de Seneca, 23",
    "sg:city":"Posadas",
    "sg:orig_category":"Zapatos (al Por Menor)",
    "sg:phone":"+34 957 63 22 35",
    "sg:postcode":"14730",
    "sg:province":"C\u00f3rdoba",
    "wof:name":"Rodriguez Leon Maria Salut",
    "wof:placetype":"venue"
},
  "geometry": {"coordinates":[-97.78224945069999,45.7040786743],"type":"Point"}
}