{
  "type": "Feature",
  "properties": {
    "iso:country":"ES",
    "sg:address":"Avda Txori Erri, 46",
    "sg:city":"Basozabal",
    "sg:orig_category":"Automatizaci\u00d3n De Procesos Industriales Y De Edificaci\u00d3n (estudios, Instalaci\u00d3n)",
    "sg:phone":"+34 944 53 50 20",
    "sg:postcode":"48150",
    "sg:province":"Vizcaya",
    "wof:name":"Pepperl & Fuchs S. A.",
    "wof:placetype":"venue"
},
  "geometry": {"coordinates":[-2.9210519791,43.2983283997],"type":"Point"}
}