{
  "type": "Feature",
  "properties": {
    "addr:full":"Rbla Generalitat, 210 Vilafranca Penedes Barcelona 08720",
    "addr:housenumber":"210",
    "addr:postcode":"08720",
    "addr:street":"Rbla Generalitat;Penedes Barcelona",
    "iso:country":"ES",
    "sg:address":"Rbla Generalitat, 210",
    "sg:city":"Vilafranca Penedes",
    "sg:orig_category":"Herramientas Manuales (fabricaci\u00d3n, Al Por Mayor)",
    "sg:phone":"+34 938 17 30 34",
    "sg:postcode":"08720",
    "sg:province":"Barcelona",
    "sg:website":"www.penedesindustrial.es",
    "wof:name":"Penedes Industrial S. L.",
    "wof:placetype":"venue"
},
  "geometry": {"coordinates":[1.7022750378,41.3370666504],"type":"Point"}
}