{
  "type": "Feature",
  "properties": {
    "addr:full":"Calle de Cefiro, 9 Sevilla Sevilla 41018",
    "addr:housenumber":"9",
    "addr:postcode":"41018",
    "addr:street":"Calle De Cefiro",
    "iso:country":"ES",
    "sg:address":"Calle de Cefiro, 9",
    "sg:city":"Sevilla",
    "sg:orig_category":"Peluquer\u00cdas, Peluquer\u00cda Mixta",
    "sg:phone":"+34 954 58 32 39",
    "sg:postcode":"41018",
    "sg:province":"Sevilla",
    "wof:name":"Siles Peluqueros S.l.",
    "wof:placetype":"venue"
},
  "geometry": {"coordinates":[-5.9747848511,37.3885498047],"type":"Point"}
}