{
  "type": "Feature",
  "properties": {
    "addr:full":"Ctra Vic, 15 Manresa Barcelona 08241",
    "addr:housenumber":"15",
    "addr:postcode":"08241",
    "addr:street":"Ctra Vic",
    "iso:country":"ES",
    "sg:address":"Ctra Vic, 15",
    "sg:city":"Manresa",
    "sg:orig_category":"Asociaciones Y Clubs Deportivos",
    "sg:phone":"+34 938 72 97 71",
    "sg:postcode":"08241",
    "sg:province":"Barcelona",
    "wof:name":"Dual Sports S.l.",
    "wof:placetype":"venue"
},
  "geometry": {"coordinates":[1.8258789778,41.7258720398],"type":"Point"}
}