{
  "type": "Feature",
  "properties": {
    "addr:full":"Carrer de Muralla De Santa Tecla, 5 Montblanc Tarragona 43400",
    "addr:housenumber":"5",
    "addr:postcode":"43400",
    "addr:street":"Carrer De Muralla De Santa Tecla",
    "iso:country":"ES",
    "sg:address":"Carrer de Muralla De Santa Tecla, 5",
    "sg:city":"Montblanc",
    "sg:orig_category":"Agentes, Concesionarios Y Sucursales De Veh\u00cdculos",
    "sg:phone":"+34 977 86 00 69",
    "sg:postcode":"43400",
    "sg:province":"Tarragona",
    "wof:name":"Recanvis I Ferreteria Alt Camp S.l.",
    "wof:placetype":"venue"
},
  "geometry": {"coordinates":[1.1643300056,41.3753395081],"type":"Point"}
}