{
  "type": "Feature",
  "properties": {
    "iso:country":"ES",
    "sg:address":"C/ Ample, 22",
    "sg:city":"S. Antoni Portmany",
    "sg:orig_category":"Confecci\u00d3n De Trajes Para Se\u00d1oras",
    "sg:phone":"+34 971 34 64 95",
    "sg:postcode":"07820",
    "sg:province":"Islas Baleares",
    "wof:name":"Van Breda Leijsen Juana Guillermina",
    "wof:placetype":"venue"
},
  "geometry": {"coordinates":[1.5188339949,39.1094055176],"type":"Point"}
}