{
  "type": "Feature",
  "properties": {
    "addr:full":"Calle de General Garcia Escamez, 17 Madrid Madrid 28044",
    "addr:housenumber":"17",
    "addr:postcode":"madrid;28044",
    "addr:street":"Calle De General Garcia Escamez",
    "iso:country":"ES",
    "sg:address":"Calle de General Garcia Escamez, 17",
    "sg:city":"Madrid",
    "sg:orig_category":"Electricidad Veh\u00cdculo",
    "sg:phone":"+34 917 06 24 13",
    "sg:postcode":"28044",
    "sg:province":"Madrid",
    "wof:name":"Marquez Romero Antonio",
    "wof:placetype":"venue"
},
  "geometry": {"coordinates":[-3.7688949108,40.3818817139],"type":"Point"}
}