{
  "type": "Feature",
  "properties": {
    "iso:country":"ES",
    "sg:address":"C/ Soledat, De La, 53",
    "sg:city":"S. Antoni Portmany",
    "sg:orig_category":"Artes Gr\u00c1ficas, Artes Pl\u00c1sticas (curso)",
    "sg:phone":"+34 971 34 03 53",
    "sg:postcode":"07820",
    "sg:province":"Islas Baleares",
    "wof:name":"Imprenta Insular S.l.",
    "wof:placetype":"venue"
},
  "geometry": {"coordinates":[1.5188339949,39.1094055176],"type":"Point"}
}