{
  "type": "Feature",
  "properties": {
    "addr:full":"Carrer de Hiroshima, 17 Palma Islas Baleares 07004",
    "addr:housenumber":"17",
    "addr:postcode":"07004",
    "addr:street":"Carrer De Hiroshima",
    "iso:country":"ES",
    "sg:address":"Carrer de Hiroshima, 17",
    "sg:city":"Palma",
    "sg:orig_category":"Electricidad (montaje, Ensamblaje De Componentes)",
    "sg:phone":"+34 971 75 50 41",
    "sg:postcode":"07004",
    "sg:province":"Islas Baleares",
    "wof:name":"Segura Alarcon Miguel",
    "wof:placetype":"venue"
},
  "geometry": {"coordinates":[2.6597619057,39.5846061707],"type":"Point"}
}