{
  "type": "Feature",
  "properties": {
    "iso:country":"ES",
    "sg:address":"Calle de Soledad, S/n",
    "sg:city":"Escalonilla",
    "sg:orig_category":"F\u00c1bricas De Ladrillo Y Tejas",
    "sg:phone":"+34 925 75 84 01",
    "sg:postcode":"45517",
    "sg:province":"Toledo",
    "wof:name":"Ceramica Escalonilla S.l.",
    "wof:placetype":"venue"
},
  "geometry": {"coordinates":[-4.3516941071,39.9261398315],"type":"Point"}
}