{
  "type": "Feature",
  "properties": {
    "iso:country":"ES",
    "sg:address":"Pase Carolinas, 12",
    "sg:city":"Santa Uxia De Ribeira",
    "sg:orig_category":"Muebles Y Accesorios Para Cocinas Y Cuartos De Ba\u00d1o (al Por Menor)",
    "sg:phone":"+34 981 87 25 06",
    "sg:postcode":"15960",
    "sg:province":"La Coru\u00f1a",
    "wof:name":"Arco Iris 2002 Sl",
    "wof:placetype":"venue"
},
  "geometry": {"coordinates":[-8.9963178635,42.583316803],"type":"Point"}
}