{
  "type": "Feature",
  "properties": {
    "addr:full":"Calle de Doz, 2 Tarazona Zaragoza 50500",
    "addr:housenumber":"2",
    "addr:postcode":"50500",
    "addr:street":"Calle De Doz",
    "iso:country":"ES",
    "sg:address":"Calle de Doz, 2",
    "sg:city":"Tarazona",
    "sg:orig_category":"Art\u00cdculos De Regalo (al Por Menor)",
    "sg:phone":"+34 976 64 26 46",
    "sg:postcode":"50500",
    "sg:province":"Zaragoza",
    "wof:name":"Melendez La Torre Ada",
    "wof:placetype":"venue"
},
  "geometry": {"coordinates":[-1.726765275,41.905380249],"type":"Point"}
}