{
  "type": "Feature",
  "properties": {
    "iso:country":"ES",
    "sg:address":"Nuno Sanc, 14",
    "sg:city":"Manacor",
    "sg:orig_category":"Fabricaci\u00d3n De Muebles",
    "sg:phone":"+34 971 55 36 52",
    "sg:postcode":"07500",
    "sg:province":"Islas Baleares",
    "wof:name":"Riera Bauza S.l.",
    "wof:placetype":"venue"
},
  "geometry": {"coordinates":[3.2025859356,39.5683021545],"type":"Point"}
}