{
  "type": "Feature",
  "properties": {
    "iso:country":"ES",
    "sg:address":"Avda Gran Via Rey Juan Carlos I, 10",
    "sg:city":"Logro\u00f1o",
    "sg:orig_category":"Arquitectos",
    "sg:phone":"+34 941 22 16 84",
    "sg:postcode":"26002",
    "sg:province":"La Rioja",
    "wof:name":"San Pedro Sotelo Ruben",
    "wof:placetype":"venue"
},
  "geometry": {"coordinates":[-2.4463729858,42.4633255005],"type":"Point"}
}