{
  "type": "Feature",
  "properties": {
    "addr:full":"Luga Arboledas (las), S/n Arboledas Murcia 30600",
    "addr:postcode":"30600",
    "addr:street":"Las S / N",
    "iso:country":"ES",
    "sg:address":"Luga Arboledas (las), S/n",
    "sg:city":"Arboledas",
    "sg:orig_category":"Alimentaci\u00d3n General (al Por Menor)",
    "sg:phone":"+34 968 67 02 23",
    "sg:postcode":"30600",
    "sg:province":"Murcia",
    "wof:name":"Moreno Martinez Manuela Luisa",
    "wof:placetype":"venue"
},
  "geometry": {"coordinates":[-1.2987289429,38.117401123],"type":"Point"}
}