{
  "type": "Feature",
  "properties": {
    "iso:country":"ES",
    "sg:address":"Carrer de Celtibers, 1",
    "sg:city":"Sabadell",
    "sg:orig_category":"Suministros Para Carrocer\u00cdas",
    "sg:phone":"+34 937 16 35 89",
    "sg:postcode":"08208",
    "sg:province":"Barcelona",
    "wof:name":"Benitez Vi\u00f1as Juan",
    "wof:placetype":"venue"
},
  "geometry": {"coordinates":[2.1010000706,41.5642585754],"type":"Point"}
}