{
  "type": "Feature",
  "properties": {
    "iso:country":"ES",
    "sg:address":"Calle de Butarque, 12",
    "sg:city":"Leganes",
    "sg:orig_category":"Laboratorios Y Trabajos De Fotograf\u00cda, V\u00cddeo Y Cine",
    "sg:phone":"+34 916 88 02 96",
    "sg:postcode":"28911",
    "sg:province":"Madrid",
    "wof:name":"Hernandez Gonzalez Maria Del Rosario",
    "wof:placetype":"venue"
},
  "geometry": {"coordinates":[-3.7658574581,40.3307991028],"type":"Point"}
}