{
  "type": "Feature",
  "properties": {
    "iso:country":"ES",
    "sg:address":"Calle de Alferez Provisional, 13",
    "sg:city":"Chantada",
    "sg:orig_category":"Talleres: Ropa A Medida",
    "sg:phone":"+34 982 44 06 49",
    "sg:postcode":"27500",
    "sg:province":"Lugo",
    "wof:name":"Lagos Carballo Guillermo",
    "wof:placetype":"venue"
},
  "geometry": {"coordinates":[-7.7704615593,42.610660553],"type":"Point"}
}