{
  "type": "Feature",
  "properties": {
    "iso:country":"ES",
    "sg:address":"Pl Sierra De Aralar, 9",
    "sg:city":"Estella",
    "sg:orig_category":"Peluqueros: De Se\u00d1oras",
    "sg:phone":"+34 948 54 65 11",
    "sg:postcode":"31200",
    "sg:province":"Navarra",
    "wof:name":"Arrastio Casanellas Cristina",
    "wof:placetype":"venue"
},
  "geometry": {"coordinates":[-2.0347299576,42.671295166],"type":"Point"}
}