{
  "type": "Feature",
  "properties": {
    "addr:full":"Ismael Dom\u00ednguez, 157 Tacoronte Santa Cruz De Tenerife 38350",
    "addr:housenumber":"157",
    "addr:postcode":"38350",
    "addr:street":"Domi\u0301Nguez",
    "iso:country":"ES",
    "sg:address":"Ismael Dom\u00ednguez, 157",
    "sg:city":"Tacoronte",
    "sg:orig_category":"Ingeniero",
    "sg:phone":"+34 922 56 22 49",
    "sg:postcode":"38350",
    "sg:province":"Santa Cruz De Tenerife",
    "wof:name":"Diaz Sabina Santiago",
    "wof:placetype":"venue"
},
  "geometry": {"coordinates":[-16.4188194275,28.4823799133],"type":"Point"}
}