{
  "type": "Feature",
  "properties": {
    "iso:country":"ES",
    "sg:address":"Calle de Espada, 20",
    "sg:city":"Alcorcon",
    "sg:orig_category":"Empresarios",
    "sg:phone":"+34 914 86 02 48",
    "sg:postcode":"28921",
    "sg:province":"Madrid",
    "wof:name":"Reformas Y Decoraciones S.l.",
    "wof:placetype":"venue"
},
  "geometry": {"coordinates":[-3.8265299797,40.3466148376],"type":"Point"}
}