{
  "type": "Feature",
  "properties": {
    "addr:full":"Ctra. General, 121 Valle S. Lorenzo Santa Cruz De Tenerife 38626",
    "addr:housenumber":"121",
    "addr:postcode":"38626",
    "addr:street":"Ctra. General;S. Lorenzo",
    "iso:country":"ES",
    "sg:address":"Ctra. General, 121",
    "sg:city":"Valle S. Lorenzo",
    "sg:orig_category":"Inform\u00c1tica: Mantenimiento Y Reparaci\u00d3n De Ordenadores",
    "sg:phone":"+34 922 72 20 72",
    "sg:postcode":"38626",
    "sg:province":"Santa Cruz De Tenerife",
    "wof:name":"Barrios Gonzalez Juan Jose",
    "wof:placetype":"venue"
},
  "geometry": {"coordinates":[-16.6702098846,28.0729980469],"type":"Point"}
}