{
  "type": "Feature",
  "properties": {
    "addr:full":"Rua Rochel, 22 Ferrol La Coru\u00f1a 15402",
    "addr:housenumber":"22",
    "addr:postcode":"15402",
    "addr:street":"Rua Rochel;La Corun\u0303A",
    "iso:country":"ES",
    "sg:address":"Rua Rochel, 22",
    "sg:city":"Ferrol",
    "sg:orig_category":"Art\u00cdculos De Regalo (al Por Menor)",
    "sg:phone":"+34 981 32 09 33",
    "sg:postcode":"15402",
    "sg:province":"La Coru\u00f1a",
    "wof:name":"Nortfein S.l.",
    "wof:placetype":"venue"
},
  "geometry": {"coordinates":[-8.2290802002,43.4849967957],"type":"Point"}
}