{
  "type": "Feature",
  "properties": {
    "addr:full":"Santa Marta, 45 Santa Marta Lugo 27421",
    "addr:housenumber":"45",
    "addr:postcode":"27421",
    "addr:street":"Santa Marta",
    "iso:country":"ES",
    "sg:address":"Santa Marta, 45",
    "sg:city":"Santa Marta",
    "sg:classifiers":[
        {
            "category":"Taxi",
            "type":"Transportation"
        }
    ],
    "sg:phone":"+34 982 46 02 82",
    "sg:postcode":"27421",
    "sg:province":"Lugo",
    "wof:name":"Perez Vidal Venancio",
    "wof:placetype":"venue"
},
  "geometry": {"coordinates":[-7.5627799034,42.9439506531],"type":"Point"}
}