{
  "type": "Feature",
  "properties": {
    "addr:full":"Calle de Manuel Machado, 45 Roquetas Mar Almer\u00eda 04740",
    "addr:housenumber":"45",
    "addr:postcode":"04740",
    "addr:street":"Calle De Manuel Machado;Mar Almeri\u0301A",
    "iso:country":"ES",
    "sg:address":"Calle de Manuel Machado, 45",
    "sg:city":"Roquetas Mar",
    "sg:orig_category":"Herboristas (al Por Menor)",
    "sg:phone":"+34 950 32 10 46",
    "sg:postcode":"04740",
    "sg:province":"Almer\u00eda",
    "wof:name":"Perez Sivestre Maria Isabel",
    "wof:placetype":"venue"
},
  "geometry": {"coordinates":[-2.6139490604,36.7637214661],"type":"Point"}
}