{
  "type": "Feature",
  "properties": {
    "addr:full":"Carrer de Selva, 20 Barcelona Barcelona 08016",
    "addr:housenumber":"20",
    "addr:postcode":"08016",
    "addr:street":"Carrer De Selva",
    "iso:country":"ES",
    "sg:address":"Carrer de Selva, 20",
    "sg:city":"Barcelona",
    "sg:orig_category":"Transporte En General",
    "sg:phone":"+34 933 59 80 84",
    "sg:postcode":"08016",
    "sg:province":"Barcelona",
    "wof:name":"Qui\u00f1ones Arias Alfonso",
    "wof:placetype":"venue"
},
  "geometry": {"coordinates":[2.1766409874,41.4376296997],"type":"Point"}
}