{
  "type": "Feature",
  "properties": {
    "addr:full":"Plaza De La Esperanza, 15 Cumbres Mayores Huelva 21380",
    "addr:housenumber":"15",
    "addr:postcode":"21380",
    "addr:street":"La Esperanza",
    "iso:country":"ES",
    "sg:address":"Plaza De La Esperanza, 15",
    "sg:city":"Cumbres Mayores",
    "sg:orig_category":"Comadronas",
    "sg:phone":"+34 959 71 00 79",
    "sg:postcode":"21380",
    "sg:province":"Huelva",
    "wof:name":"Casta\u00f1o Guijarro Concepcion",
    "wof:placetype":"venue"
},
  "geometry": {"coordinates":[-6.6433019638,38.0596694946],"type":"Point"}
}