{
  "type": "Feature",
  "properties": {
    "iso:country":"ES",
    "sg:address":"Calle de Santa Barbara, 17",
    "sg:city":"Monzon",
    "sg:orig_category":"Ropa Para Ni\u00d1os (al Por Menor)",
    "sg:phone":"+34 974 40 13 88",
    "sg:postcode":"22400",
    "sg:province":"Huesca",
    "wof:name":"Solanas Bag\u00fces Jose Luis",
    "wof:placetype":"venue"
},
  "geometry": {"coordinates":[0.1945994049,41.9109802246],"type":"Point"}
}