{
  "type": "Feature",
  "properties": {
    "iso:country":"ES",
    "sg:address":"Ctra. Valladolid-tortoles, S/n",
    "sg:city":"Esguevillas Esgueva",
    "sg:orig_category":"Producci\u00d3n De Abonos Y De Fertilizantes",
    "sg:phone":"+34 983 68 61 61",
    "sg:postcode":"47176",
    "sg:province":"Valladolid",
    "wof:name":"Valle Esgueva Sociedad Cooperativa Limitada",
    "wof:placetype":"venue"
},
  "geometry": {"coordinates":[-4.3804039955,41.7496337891],"type":"Point"}
}