{
  "type": "Feature",
  "properties": {
    "iso:country":"ES",
    "sg:address":"Calle de Sierra Nevada, 8",
    "sg:city":"Arganda",
    "sg:orig_category":"Venta, Localizaci\u00d3n, Reparaci\u00d3n De Material E Instrumental M\u00c9dico",
    "sg:phone":"+34 918 71 91 93",
    "sg:postcode":"28500",
    "sg:province":"Madrid",
    "wof:name":"Gonzalo Lopez Pablo",
    "wof:placetype":"venue"
},
  "geometry": {"coordinates":[-3.4758150578,40.3061981201],"type":"Point"}
}