{
  "type": "Feature",
  "properties": {
    "addr:full":"Rond Sant Bernat, 6 Olot Girona 17800",
    "addr:housenumber":"6",
    "addr:postcode":"17800",
    "addr:street":"Bernat",
    "iso:country":"ES",
    "sg:address":"Rond Sant Bernat, 6",
    "sg:city":"Olot",
    "sg:orig_category":"Ense\u00d1anza: Comercio, Gesti\u00d3n, Inform\u00c1tica",
    "sg:phone":"+34 972 27 29 85",
    "sg:postcode":"17800",
    "sg:province":"Girona",
    "wof:name":"Enginyeria Informatica Olot S.l.",
    "wof:placetype":"venue"
},
  "geometry": {"coordinates":[2.4915549755,42.1840438843],"type":"Point"}
}