{
  "type": "Feature",
  "properties": {
    "iso:country":"ES",
    "sg:address":"Carrer de Balmes, 292",
    "sg:city":"Barcelona",
    "sg:orig_category":"Agencias De Viajes",
    "sg:phone":"+34 932 01 29 30",
    "sg:postcode":"08006",
    "sg:province":"Barcelona",
    "wof:name":"Special Events Design For Barcelona S.l.",
    "wof:placetype":"venue"
},
  "geometry": {"coordinates":[2.1465899944,41.401927948],"type":"Point"}
}