{
  "type": "Feature",
  "properties": {
    "addr:full":"Carrer de Major, 28 Caldes Montbui Barcelona 08140",
    "addr:housenumber":"28",
    "addr:postcode":"08140",
    "addr:street":"Carrer De Major;Montbui Barcelona",
    "iso:country":"ES",
    "sg:address":"Carrer de Major, 28",
    "sg:city":"Caldes Montbui",
    "sg:orig_category":"Centros Empresariales",
    "sg:phone":"+34 938 62 61 96",
    "sg:postcode":"08140",
    "sg:province":"Barcelona",
    "wof:name":"Unique Interim S.a.",
    "wof:placetype":"venue"
},
  "geometry": {"coordinates":[2.1622231007,41.6370391846],"type":"Point"}
}