{
  "type": "Feature",
  "properties": {
    "iso:country":"ES",
    "sg:address":"Carrer de Craywinckel, 12",
    "sg:city":"Barcelona",
    "sg:orig_category":"Juegos Y Juguetes (al Por Menor)",
    "sg:phone":"+34 934 17 22 84",
    "sg:postcode":"08022",
    "sg:province":"Barcelona",
    "wof:name":"Toys Centre S.l.",
    "wof:placetype":"venue"
},
  "geometry": {"coordinates":[2.1393380165,41.4121665955],"type":"Point"}
}