{
  "type": "Feature",
  "properties": {
    "iso:country":"ES",
    "sg:address":"Calle de Mariano Royo, 15",
    "sg:city":"Zaragoza",
    "sg:orig_category":"Servicios De Higiene Y Peluquer\u00cda Para Perros Y Gatos",
    "sg:phone":"+34 976 23 67 32",
    "sg:postcode":"50006",
    "sg:province":"Zaragoza",
    "wof:name":"Galindo Falcon Maria Carmen",
    "wof:placetype":"venue"
},
  "geometry": {"coordinates":[-0.8870170116,41.6451683044],"type":"Point"}
}