{
  "type": "Feature",
  "properties": {
    "addr:full":"Avda Alfonso El Sabio, 38 Alacant Alicante 03004",
    "addr:housenumber":"38",
    "addr:postcode":"03004",
    "addr:street":"Avda Alfonso El Sabio",
    "iso:country":"ES",
    "sg:address":"Avda Alfonso El Sabio, 38",
    "sg:city":"Alacant",
    "sg:orig_category":"Art\u00cdculos De Decoraci\u00d3n",
    "sg:phone":"+34 965 14 48 26",
    "sg:postcode":"03004",
    "sg:province":"Alicante",
    "wof:name":"Saez Hernandez Santiago",
    "wof:placetype":"venue"
},
  "geometry": {"coordinates":[-0.4889509976,38.3468322754],"type":"Point"}
}