{
  "type": "Feature",
  "properties": {
    "addr:full":"Calle de Sor Emilia, 12 Alcala Guadaira Sevilla 41500",
    "addr:housenumber":"12",
    "addr:postcode":"41500",
    "addr:street":"Calle De Sor Emilia",
    "iso:country":"ES",
    "sg:address":"Calle de Sor Emilia, 12",
    "sg:city":"Alcala Guadaira",
    "sg:orig_category":"Ense\u00d1anza Variada",
    "sg:phone":"+34 955 68 40 24",
    "sg:postcode":"41500",
    "sg:province":"Sevilla",
    "wof:name":"Alguadaira Formacion S.l.",
    "wof:placetype":"venue"
},
  "geometry": {"coordinates":[-5.8457231522,37.3378295898],"type":"Point"}
}