{
  "type": "Feature",
  "properties": {
    "iso:country":"ES",
    "sg:address":"V. Espinel, 40",
    "sg:city":"Ronda",
    "sg:orig_category":"Abogados",
    "sg:phone":"+34 952 87 73 62",
    "sg:postcode":"29400",
    "sg:province":"M\u00e1laga",
    "wof:name":"Alcaide Guerrero Alvaro",
    "wof:placetype":"venue"
},
  "geometry": {"coordinates":[-5.1645274162,36.7430686951],"type":"Point"}
}