{
  "type": "Feature",
  "properties": {
    "iso:country":"ES",
    "sg:address":"Calle de Biblioteca, 2",
    "sg:city":"Algodonales",
    "sg:orig_category":"Supermercados Y Hipermercados",
    "sg:phone":"+34 956 13 73 88",
    "sg:postcode":"11680",
    "sg:province":"C\u00e1diz",
    "wof:name":"Salas Becerra Pedro",
    "wof:placetype":"venue"
},
  "geometry": {"coordinates":[-5.4069781303,36.8810882568],"type":"Point"}
}