{
  "type": "Feature",
  "properties": {
    "iso:country":"ES",
    "sg:address":"Plaz Cerro Palacio, 3",
    "sg:city":"Mocejon",
    "sg:orig_category":"Trabajos De Topograf\u00cda",
    "sg:phone":"+34 925 36 00 60",
    "sg:postcode":"45270",
    "sg:province":"Toledo",
    "wof:name":"Calvo Rodriguez Juan",
    "wof:placetype":"venue"
},
  "geometry": {"coordinates":[-3.9156069756,39.9399757385],"type":"Point"}
}