{
  "type": "Feature",
  "properties": {
    "addr:full":"Carr Cristofor Colom, 33 Portocolom Islas Baleares 07670",
    "addr:housenumber":"33",
    "addr:postcode":"07670",
    "addr:street":"Carr Cristofor Colom",
    "iso:country":"ES",
    "sg:address":"Carr Cristofor Colom, 33",
    "sg:city":"Portocolom",
    "sg:orig_category":"Distribuci\u00d3n De Petr\u00d3leo Y Derivados",
    "sg:phone":"+34 971 82 42 01",
    "sg:postcode":"07670",
    "sg:province":"Islas Baleares",
    "sg:website":"www.cepsa.es",
    "wof:name":"Benzinera A. Artigues S.l",
    "wof:placetype":"venue"
},
  "geometry": {"coordinates":[3.2615349293,39.4209976196],"type":"Point"}
}