{
  "type": "Feature",
  "properties": {
    "addr:full":"Calle de Juan De Garay, 3 Villarcayo Burgos 09550",
    "addr:housenumber":"3",
    "addr:postcode":"09550",
    "addr:street":"Calle De Juan De Garay",
    "iso:country":"ES",
    "sg:address":"Calle de Juan De Garay, 3",
    "sg:city":"Villarcayo",
    "sg:orig_category":"Venta, Instalaci\u00d3n De Calefacci\u00d3n",
    "sg:phone":"+34 947 13 15 29",
    "sg:postcode":"09550",
    "sg:province":"Burgos",
    "wof:name":"Nevagar S.l.",
    "wof:placetype":"venue"
},
  "geometry": {"coordinates":[-3.571999073,42.9364013672],"type":"Point"}
}