{
  "type": "Feature",
  "properties": {
    "addr:full":"Calle de Monte Blanco (del), 11 Fuenlabrada Madrid 28944",
    "addr:housenumber":"11",
    "addr:postcode":"28944",
    "addr:street":"Calle De Monte Blanco Del",
    "iso:country":"ES",
    "sg:address":"Calle de Monte Blanco (del), 11",
    "sg:city":"Fuenlabrada",
    "sg:orig_category":"Fabrica, Negocio De Vidrieras, Productos Vidriados Y Espejos",
    "sg:phone":"+34 916 15 17 81",
    "sg:postcode":"28944",
    "sg:province":"Madrid",
    "wof:name":"Enrique Pozo Vidrieras S.l.",
    "wof:placetype":"venue"
},
  "geometry": {"coordinates":[-3.8051629066,40.2761573792],"type":"Point"}
}