{
  "type": "Feature",
  "properties": {
    "iso:country":"ES",
    "sg:address":"Avda Principe Felipe, Del, 23",
    "sg:city":"Talavera Reina",
    "sg:orig_category":"Peluquer\u00cdas, Peluquer\u00cda Mixta",
    "sg:phone":"+34 925 80 55 13",
    "sg:postcode":"45600",
    "sg:province":"Toledo",
    "sg:website":"www.peluqueriasparis.com",
    "wof:name":"Peluqueria Paris S. C. L.",
    "wof:placetype":"venue"
},
  "geometry": {"coordinates":[-4.8326292038,39.9584884644],"type":"Point"}
}