{
  "type": "Feature",
  "properties": {
    "iso:country":"ES",
    "sg:address":"Ctra. General, Km. 0026,0",
    "sg:city":"Guia Isora",
    "sg:orig_category":"Distribuci\u00d3n De Petr\u00d3leo Y Derivados",
    "sg:phone":"+34 922 85 07 52",
    "sg:postcode":"38680",
    "sg:province":"Santa Cruz De Tenerife",
    "wof:name":"Sociedad Delgado Salazar S.l.",
    "wof:placetype":"venue"
},
  "geometry": {"coordinates":[-16.7817249298,28.2119045258],"type":"Point"}
}