{
  "type": "Feature",
  "properties": {
    "iso:country":"ES",
    "sg:address":"Carrer de Foc Follet, 6",
    "sg:city":"Barcelona",
    "sg:orig_category":"Molduras, Junquillos, Listones Y Molduras Perforadas",
    "sg:phone":"+34 933 14 78 59",
    "sg:postcode":"08030",
    "sg:province":"Barcelona",
    "wof:name":"Gonzalez Rodriguez Fernando",
    "wof:placetype":"venue"
},
  "geometry": {"coordinates":[2.2023890018,41.4341201782],"type":"Point"}
}