{
  "type": "Feature",
  "properties": {
    "addr:full":"Calle de Segura, 10 Bosque Madrid 28670",
    "addr:housenumber":"10",
    "addr:postcode":"28670",
    "addr:street":"Calle De Segura",
    "iso:country":"ES",
    "sg:address":"Calle de Segura, 10",
    "sg:city":"Bosque",
    "sg:orig_category":"Escultores, Estatuarios E Imagineros",
    "sg:phone":"+34 916 16 71 51",
    "sg:postcode":"28670",
    "sg:province":"Madrid",
    "wof:name":"Esculturas Nacho Martin S.l.",
    "wof:placetype":"venue"
},
  "geometry": {"coordinates":[-3.9189929962,40.3930053711],"type":"Point"}
}