{
  "type": "Feature",
  "properties": {
    "addr:full":"Calle de Hermosilla, 114 Madrid Madrid 28009",
    "addr:housenumber":"114",
    "addr:postcode":"28009",
    "addr:street":"Calle De Hermosilla",
    "iso:country":"ES",
    "sg:address":"Calle de Hermosilla, 114",
    "sg:city":"Madrid",
    "sg:orig_category":"Organizaciones Internacionales",
    "sg:phone":"+34 914 01 96 95",
    "sg:postcode":"28009",
    "sg:province":"Madrid",
    "sg:website":"www.ligaproderechoshumans.org",
    "wof:name":"Liga Espa\u00f1ola Proderechos Humanos",
    "wof:placetype":"venue"
},
  "geometry": {"coordinates":[-3.6703119278,40.4255142212],"type":"Point"}
}