{
  "type": "Feature",
  "properties": {
    "addr:full":"Carrer de Major, 73 S. Pere Ribes Barcelona 08810",
    "addr:housenumber":"73",
    "addr:postcode":"08810",
    "addr:street":"Carrer De Major;S. Pere Ribes Barcelona",
    "iso:country":"ES",
    "sg:address":"Carrer de Major, 73",
    "sg:city":"S. Pere Ribes",
    "sg:orig_category":"Molduras, Junquillos, Listones Y Molduras Perforadas",
    "sg:phone":"+34 938 96 42 42",
    "sg:postcode":"08810",
    "sg:province":"Barcelona",
    "wof:name":"Salas Llavanera Hortensia",
    "wof:placetype":"venue"
},
  "geometry": {"coordinates":[1.7668819427,41.2602005005],"type":"Point"}
}