{
  "type": "Feature",
  "properties": {
    "iso:country":"ES",
    "sg:address":"Calle de Piedrahita, 27",
    "sg:city":"Madrid",
    "sg:orig_category":"Electricidad: Instaladores",
    "sg:phone":"+34 915 25 19 56",
    "sg:postcode":"28025",
    "sg:province":"Madrid",
    "wof:name":"Caflu S.a.",
    "wof:placetype":"venue"
},
  "geometry": {"coordinates":[-3.7414190769,40.3770713806],"type":"Point"}
}