{
  "type": "Feature",
  "properties": {
    "addr:full":"Calle de Magacela, 57 Villanueva Serena Badajoz 06700",
    "addr:housenumber":"57",
    "addr:postcode":"06700",
    "addr:street":"Calle De Magacela",
    "iso:country":"ES",
    "sg:address":"Calle de Magacela, 57",
    "sg:city":"Villanueva Serena",
    "sg:orig_category":"Cr\u00cda De Animales",
    "sg:phone":"+34 924 84 08 90",
    "sg:postcode":"06700",
    "sg:province":"Badajoz",
    "wof:name":"Juan Nombela Mariano",
    "wof:placetype":"venue"
},
  "geometry": {"coordinates":[-5.7974638939,38.971321106],"type":"Point"}
}