{
  "type": "Feature",
  "properties": {
    "iso:country":"ES",
    "sg:address":"Rbla Exposicio, S/n",
    "sg:city":"Vilanova I La Geltru",
    "sg:orig_category":"Material Ferroviario",
    "sg:phone":"+34 938 14 13 00",
    "sg:postcode":"08800",
    "sg:province":"Barcelona",
    "wof:name":"Alston Transporte S.a.",
    "wof:placetype":"venue"
},
  "geometry": {"coordinates":[1.7347137928,41.2233657837],"type":"Point"}
}