{
  "type": "Feature",
  "properties": {
    "iso:country":"ES",
    "sg:address":"Calle de Tambor De Granaderos, 4",
    "sg:city":"Villena",
    "sg:orig_category":"Confecci\u00d3n De Zapatos",
    "sg:phone":"+34 965 81 37 45",
    "sg:postcode":"03400",
    "sg:province":"Alicante",
    "wof:name":"Calzanova S.l.",
    "wof:placetype":"venue"
},
  "geometry": {"coordinates":[-0.8682100177,38.6419067383],"type":"Point"}
}