{
  "type": "Feature",
  "properties": {
    "iso:country":"ES",
    "sg:address":"Avda Madrid, 42",
    "sg:city":"Torrejon Ardoz",
    "sg:orig_category":"Frutas, Legumbres Frescas Y Tempranas (al Por Menor)",
    "sg:phone":"+34 916 75 04 24",
    "sg:postcode":"28850",
    "sg:province":"Madrid",
    "wof:name":"Abad Frutas S.l.",
    "wof:placetype":"venue"
},
  "geometry": {"coordinates":[-3.465917,40.464069],"type":"Point"}
}