{
  "type": "Feature",
  "properties": {
    "addr:full":"Carr Metge Rossell, 4 Lloseta Islas Baleares 07360",
    "addr:housenumber":"4",
    "addr:postcode":"07360",
    "addr:street":"Carr Metge Rossell",
    "iso:country":"ES",
    "sg:address":"Carr Metge Rossell, 4",
    "sg:city":"Lloseta",
    "sg:orig_category":"Agencias Y Agentes Comerciales, Representantes",
    "sg:phone":"+34 971 51 43 25",
    "sg:postcode":"07360",
    "sg:province":"Islas Baleares",
    "wof:name":"Villalonga Llabres Gabriel",
    "wof:placetype":"venue"
},
  "geometry": {"coordinates":[2.8716249466,39.7204742432],"type":"Point"}
}