{
  "type": "Feature",
  "properties": {
    "addr:full":"Calle de Latina, 39 Madrid Madrid 28047",
    "addr:housenumber":"39",
    "addr:postcode":"madrid;28047",
    "addr:street":"Calle De Latina",
    "iso:country":"ES",
    "sg:address":"Calle de Latina, 39",
    "sg:city":"Madrid",
    "sg:orig_category":"Agencias De Viajes",
    "sg:phone":"+34 914 79 06 85",
    "sg:postcode":"28047",
    "sg:province":"Madrid",
    "wof:name":"Sky Dreams S.l.",
    "wof:placetype":"venue"
},
  "geometry": {"coordinates":[-3.7519750595,40.4008522034],"type":"Point"}
}