{
  "type": "Feature",
  "properties": {
    "iso:country":"ES",
    "sg:address":"Calle de Capuchinos, 14",
    "sg:city":"Tudela",
    "sg:orig_category":"Ingeniero",
    "sg:phone":"+34 948 82 58 77",
    "sg:postcode":"31500",
    "sg:province":"Navarra",
    "wof:name":"Ingenieria Formel S.l.",
    "wof:placetype":"venue"
},
  "geometry": {"coordinates":[-1.6030652523,42.0600395203],"type":"Point"}
}