{
  "type": "Feature",
  "properties": {
    "iso:country":"ES",
    "sg:address":"Rua Padres Franciscanos, 16",
    "sg:city":"Tomadas",
    "sg:orig_category":"Electricidad: Instaladores",
    "sg:phone":"+34 986 38 60 76",
    "sg:postcode":"36379",
    "sg:province":"Pontevedra",
    "wof:name":"Construcciones Comesa\u00f1a E Hijos S.l.",
    "wof:placetype":"venue"
},
  "geometry": {"coordinates":[-8.8124990463,42.1194648743],"type":"Point"}
}