{
  "type": "Feature",
  "properties": {
    "iso:country":"ES",
    "sg:address":"Carr Sant Lluc, 11",
    "sg:city":"Badalona",
    "sg:orig_category":"Fabricaci\u00d3n De Clavijas Y De Pistones",
    "sg:phone":"+34 933 87 64 45",
    "sg:postcode":"08918",
    "sg:province":"Barcelona",
    "sg:website":"www.plasticosjuarez.com",
    "wof:name":"Plasticos Juarez S.a.",
    "wof:placetype":"venue"
},
  "geometry": {"coordinates":[2.236522913,41.4343185425],"type":"Point"}
}