{
  "type": "Feature",
  "properties": {
    "iso:country":"ES",
    "sg:address":"Trva Rioja (de La), 11",
    "sg:city":"Najera",
    "sg:orig_category":"Empresas De Carpinter\u00cda Met\u00c1lica",
    "sg:phone":"+34 941 36 17 12",
    "sg:postcode":"26300",
    "sg:province":"La Rioja",
    "wof:name":"Hernandez Hernandez Esteban",
    "wof:placetype":"venue"
},
  "geometry": {"coordinates":[-2.7318389416,42.4178581238],"type":"Point"}
}