{
  "type": "Feature",
  "properties": {
    "iso:country":"ES",
    "sg:address":"Calle de Santa Barbara, 5",
    "sg:city":"Madrid",
    "sg:orig_category":"Peluquer\u00cdas, Peluquer\u00cda Mixta",
    "sg:phone":"+34 915 22 72 98",
    "sg:postcode":"28004",
    "sg:province":"Madrid",
    "wof:name":"Bermudez Zabala Susane",
    "wof:placetype":"venue"
},
  "geometry": {"coordinates":[-3.7012529373,40.4241867065],"type":"Point"}
}