{
  "type": "Feature",
  "properties": {
    "iso:country":"ES",
    "sg:address":"Calle de Melchor Fernandez Almagro, 8",
    "sg:city":"Madrid",
    "sg:orig_category":"Arenas, Guijarros Y Granulados",
    "sg:phone":"+34 913 23 76 57",
    "sg:postcode":"28029",
    "sg:province":"Madrid",
    "wof:name":"Explotaciones Minerales Santa Ines S.a.",
    "wof:placetype":"venue"
},
  "geometry": {"coordinates":[-3.6938281059,40.477558136],"type":"Point"}
}