{
  "type": "Feature",
  "properties": {
    "iso:country":"ES",
    "sg:address":"Calle de Lardero, 20",
    "sg:city":"Logro\u00f1o",
    "sg:orig_category":"Ropa Para Se\u00d1oras (al Por Menor)",
    "sg:phone":"+34 941 22 73 20",
    "sg:postcode":"26002",
    "sg:province":"La Rioja",
    "wof:name":"Sanchez Gonzalez Manuela",
    "wof:placetype":"venue"
},
  "geometry": {"coordinates":[-2.4517240524,42.4618492126],"type":"Point"}
}