{
  "type": "Feature",
  "properties": {
    "addr:full":"Rua Eduardo Iglesias, 18 Vigo Pontevedra 36202",
    "addr:housenumber":"18",
    "addr:postcode":"36202",
    "addr:street":"Rua Eduardo Iglesias",
    "iso:country":"ES",
    "sg:address":"Rua Eduardo Iglesias, 18",
    "sg:city":"Vigo",
    "sg:orig_category":"Ropa Para Se\u00d1oras Y Caballeros (al Por Menor)",
    "sg:phone":"+34 986 22 11 97",
    "sg:postcode":"36202",
    "sg:province":"Pontevedra",
    "wof:name":"Costa Progreso S.l.",
    "wof:placetype":"venue"
},
  "geometry": {"coordinates":[-8.722902298,42.2354469299],"type":"Point"}
}