{
  "type": "Feature",
  "properties": {
    "iso:country":"ES",
    "sg:address":"Partida Carga, S/n",
    "sg:city":"Crevillent",
    "sg:orig_category":"Contenedores (mercanc\u00cdas)",
    "sg:phone":"+34 965 40 00 36",
    "sg:postcode":"03330",
    "sg:province":"Alicante",
    "wof:name":"Frigorificos Tisco I Sl",
    "wof:placetype":"venue"
},
  "geometry": {"coordinates":[-0.8163840175,38.2342567444],"type":"Point"}
}