{
  "type": "Feature",
  "properties": {
    "addr:full":"Calle de Marcos De Orueta, 7 Madrid Madrid 28034",
    "addr:housenumber":"7",
    "addr:postcode":"madrid;28034",
    "addr:street":"Calle De Marcos De Orueta",
    "iso:country":"ES",
    "sg:address":"Calle de Marcos De Orueta, 7",
    "sg:city":"Madrid",
    "sg:orig_category":"Molduras, Junquillos, Listones Y Molduras Perforadas",
    "sg:phone":"+34 913 58 06 17",
    "sg:postcode":"28034",
    "sg:province":"Madrid",
    "wof:name":"Sanchez Escudero Joaquin",
    "wof:placetype":"venue"
},
  "geometry": {"coordinates":[-3.6859641075,40.4845085144],"type":"Point"}
}