{
  "type": "Feature",
  "properties": {
    "addr:full":"Miguel Bernadas, 17 Puigcerda Girona 17520",
    "addr:housenumber":"17",
    "addr:postcode":"17520",
    "addr:street":"Bernadas",
    "iso:country":"ES",
    "sg:address":"Miguel Bernadas, 17",
    "sg:city":"Puigcerda",
    "sg:orig_category":"Carnicer\u00cdas, Carnicer\u00cdas",
    "sg:phone":"+34 972 88 06 92",
    "sg:postcode":"17520",
    "sg:province":"Girona",
    "wof:name":"Calvet Baldivia Juan",
    "wof:placetype":"venue"
},
  "geometry": {"coordinates":[1.9269679785,42.4323425293],"type":"Point"}
}