{
  "type": "Feature",
  "properties": {
    "addr:full":"Carr Hostal De La Bordeta, 4 Lleida Lleida 25001",
    "addr:housenumber":"4",
    "addr:postcode":"25001",
    "addr:street":"Carr Hostal De La Bordeta",
    "iso:country":"ES",
    "sg:address":"Carr Hostal De La Bordeta, 4",
    "sg:city":"Lleida",
    "sg:orig_category":"Reposter\u00cdas",
    "sg:phone":"+34 973 20 06 15",
    "sg:postcode":"25001",
    "sg:province":"Lleida",
    "wof:name":"Casa Pons S.l.",
    "wof:placetype":"venue"
},
  "geometry": {"coordinates":[0.6418250203,41.6044998169],"type":"Point"}
}