{
  "type": "Feature",
  "properties": {
    "iso:country":"ES",
    "sg:address":"Calle de Alfonso Xiii, 79",
    "sg:city":"Dolores",
    "sg:orig_category":"Art\u00cdculos De Regalo (al Por Menor)",
    "sg:phone":"+34 968 51 36 37",
    "sg:postcode":"30310",
    "sg:province":"Murcia",
    "wof:name":"Aparicio Martinez Rosario",
    "wof:placetype":"venue"
},
  "geometry": {"coordinates":[-1.0036549568,37.6419181824],"type":"Point"}
}