{
  "type": "Feature",
  "properties": {
    "addr:full":"Calle de San Antonio, 19 Torreblanca Castell\u00f3n 12596",
    "addr:housenumber":"19",
    "addr:postcode":"12596",
    "addr:street":"Calle De San Antonio;Castello\u0301N",
    "iso:country":"ES",
    "sg:address":"Calle de San Antonio, 19",
    "sg:city":"Torreblanca",
    "sg:orig_category":"Controles De Edificaci\u00d3n (construcci\u00d3n, Seguridad)",
    "sg:phone":"+34 964 42 09 27",
    "sg:postcode":"12596",
    "sg:province":"Castell\u00f3n",
    "wof:name":"Cerramel-torre S.l.",
    "wof:placetype":"venue"
},
  "geometry": {"coordinates":[0.1946599931,40.2203140259],"type":"Point"}
}