{
  "type": "Feature",
  "properties": {
    "addr:full":"Carr Barracar Alt, 56 Petra Islas Baleares 07520",
    "addr:housenumber":"56",
    "addr:postcode":"07520",
    "addr:street":"Carr Barracar Alt",
    "iso:country":"ES",
    "sg:address":"Carr Barracar Alt, 56",
    "sg:city":"Petra",
    "sg:orig_category":"Vinos Y Licores (venta Al Por Menor)",
    "sg:phone":"+34 971 56 16 75",
    "sg:postcode":"07520",
    "sg:province":"Islas Baleares",
    "wof:name":"Galmes Ferrer Arnau",
    "wof:placetype":"venue"
},
  "geometry": {"coordinates":[3.1119039059,39.6091690063],"type":"Point"}
}