{
  "type": "Feature",
  "properties": {
    "iso:country":"ES",
    "sg:address":"Carrer de (poligon Ind Ronda Ponent), 14",
    "sg:city":"Mollerussa",
    "sg:orig_category":"Calefacci\u00d3n Central: Material (fabricaci\u00d3n, Al Por Mayor)",
    "sg:phone":"+34 973 60 20 12",
    "sg:postcode":"25230",
    "sg:province":"Lleida",
    "wof:name":"Sumfo S. L.",
    "wof:placetype":"venue"
},
  "geometry": {"coordinates":[0.8936949968,41.6300392151],"type":"Point"}
}