{
  "type": "Feature",
  "properties": {
    "addr:full":"Rua Libertad, 21 Ourense Ourense 32005",
    "addr:housenumber":"21",
    "addr:postcode":"32005",
    "addr:street":"Rua Libertad",
    "iso:country":"ES",
    "sg:address":"Rua Libertad, 21",
    "sg:city":"Ourense",
    "sg:orig_category":"Tapicer\u00cdas",
    "sg:phone":"+34 988 22 59 91",
    "sg:postcode":"32005",
    "sg:province":"Ourense",
    "wof:name":"Fernandez Pi\u00f1eiro Castor",
    "wof:placetype":"venue"
},
  "geometry": {"coordinates":[-7.8628120422,42.3335533142],"type":"Point"}
}