{
  "type": "Feature",
  "properties": {
    "addr:full":"Calle de Chorrillo, 4 Alcala Henares Madrid 28806",
    "addr:housenumber":"4",
    "addr:postcode":"28806",
    "addr:street":"Calle De Chorrillo",
    "iso:country":"ES",
    "sg:address":"Calle de Chorrillo, 4",
    "sg:city":"Alcala Henares",
    "sg:orig_category":"Droguer\u00cdas (al Por Menor)",
    "sg:phone":"+34 918 89 21 97",
    "sg:postcode":"28806",
    "sg:province":"Madrid",
    "wof:name":"Sanz Garcia Concepcion",
    "wof:placetype":"venue"
},
  "geometry": {"coordinates":[-3.3759338856,40.4896011353],"type":"Point"}
}