{
  "type": "Feature",
  "properties": {
    "addr:full":"Calle de Trinidad, 8 Burgos Burgos 09003",
    "addr:housenumber":"8",
    "addr:postcode":"09003",
    "addr:street":"Calle De Trinidad",
    "iso:country":"ES",
    "sg:address":"Calle de Trinidad, 8",
    "sg:city":"Burgos",
    "sg:orig_category":"Organizaciones Profesionales",
    "sg:phone":"+34 947 20 46 21",
    "sg:postcode":"09003",
    "sg:province":"Burgos",
    "wof:name":"Sagredo Frias Pedro",
    "wof:placetype":"venue"
},
  "geometry": {"coordinates":[-3.7010719776,42.3438644409],"type":"Point"}
}