{
  "type": "Feature",
  "properties": {
    "addr:full":"Carrer de Pubilla Casas, 26 Esplugues Llobregat Barcelona 08950",
    "addr:housenumber":"26",
    "addr:postcode":"08950",
    "addr:street":"Carrer De Pubilla Casas",
    "iso:country":"ES",
    "sg:address":"Carrer de Pubilla Casas, 26",
    "sg:city":"Esplugues Llobregat",
    "sg:orig_category":"Barbacoas Y Accesorios",
    "sg:phone":"+34 933 71 99 03",
    "sg:postcode":"08950",
    "sg:province":"Barcelona",
    "wof:name":"Restaurante La Pubilla S.l.",
    "wof:placetype":"venue"
},
  "geometry": {"coordinates":[2.0985689163,41.3720359802],"type":"Point"}
}