{
  "type": "Feature",
  "properties": {
    "iso:country":"ES",
    "sg:address":"Avda Buenavista De, S/n",
    "sg:city":"Oviedo",
    "sg:orig_category":"Distribuci\u00d3n De Petr\u00d3leo Y Derivados",
    "sg:phone":"+34 985 23 30 20",
    "sg:postcode":"33006",
    "sg:province":"Asturias",
    "wof:name":"Campa Fernandez Vigil S. A.",
    "wof:placetype":"venue"
},
  "geometry": {"coordinates":[-5.8644747734,43.3593292236],"type":"Point"}
}