{
  "type": "Feature",
  "properties": {
    "iso:country":"ES",
    "sg:address":"C/ Cid Campeador, 5",
    "sg:city":"Manacor",
    "sg:orig_category":"Empresas De Carpinter\u00cda Met\u00c1lica",
    "sg:phone":"+34 971 55 59 22",
    "sg:postcode":"07500",
    "sg:province":"Islas Baleares",
    "wof:name":"Ferro Negre S.l.",
    "wof:placetype":"venue"
},
  "geometry": {"coordinates":[3.2007908821,39.5685882568],"type":"Point"}
}