{
  "type": "Feature",
  "properties": {
    "iso:country":"ES",
    "sg:address":"Calle de Carretero, 290",
    "sg:city":"Coria Rio",
    "sg:orig_category":"Promotores Constructores",
    "sg:phone":"+34 954 77 12 62",
    "sg:postcode":"41100",
    "sg:province":"Sevilla",
    "wof:name":"Fuenlop S.l.",
    "wof:placetype":"venue"
},
  "geometry": {"coordinates":[-6.0597596169,37.2877807617],"type":"Point"}
}