{
  "type": "Feature",
  "properties": {
    "addr:full":"Carrer de Pare Claret, 209 Mallorquines Barcelona 08390",
    "addr:housenumber":"209",
    "addr:postcode":"08390",
    "addr:street":"Carrer De Pare Claret;Barcelona",
    "iso:country":"ES",
    "sg:address":"Carrer de Pare Claret, 209",
    "sg:city":"Mallorquines",
    "sg:orig_category":"Estudios, Instalaci\u00d3n De Climatizaci\u00d3n",
    "sg:phone":"+34 934 69 04 18",
    "sg:postcode":"08390",
    "sg:province":"Barcelona",
    "wof:name":"Comercial De Refrigeracion Sl",
    "wof:placetype":"venue"
},
  "geometry": {"coordinates":[2.2785899639,41.4666290283],"type":"Point"}
}