{
  "type": "Feature",
  "properties": {
    "iso:country":"ES",
    "sg:address":"Carrer de Bassa, 20",
    "sg:city":"Prat De Comte",
    "sg:orig_category":"Centros De Educaci\u00d3n Especial",
    "sg:phone":"+34 977 42 83 07",
    "sg:postcode":"43595",
    "sg:province":"Tarragona",
    "wof:name":"Ajuntament De Prat De Comte",
    "wof:placetype":"venue"
},
  "geometry": {"coordinates":[0.4043582082,40.9843330383],"type":"Point"}
}