{
  "type": "Feature",
  "properties": {
    "iso:country":"ES",
    "sg:address":"Calle de Alamillos, 2",
    "sg:city":"Valladolid",
    "sg:orig_category":"Farmacias",
    "sg:phone":"+34 983 29 14 59",
    "sg:postcode":"47005",
    "sg:province":"Valladolid",
    "wof:name":"Mato Vazquez Fidel",
    "wof:placetype":"venue"
},
  "geometry": {"coordinates":[-4.7159609795,41.6542625427],"type":"Point"}
}