{
  "type": "Feature",
  "properties": {
    "addr:full":"Calle de Gustavo Fernandez Balbuena, 19 Madrid Madrid 28002",
    "addr:housenumber":"19",
    "addr:postcode":"madrid;28002",
    "addr:street":"Calle De Gustavo Fernandez Balbuena",
    "iso:country":"ES",
    "sg:address":"Calle de Gustavo Fernandez Balbuena, 19",
    "sg:city":"Madrid",
    "sg:orig_category":"Molduras, Junquillos, Listones Y Molduras Perforadas",
    "sg:phone":"+34 914 15 12 49",
    "sg:postcode":"28002",
    "sg:province":"Madrid",
    "wof:name":"Figon El Baco S.a.",
    "wof:placetype":"venue"
},
  "geometry": {"coordinates":[-3.6683983803,40.4505767822],"type":"Point"}
}