{
  "type": "Feature",
  "properties": {
    "iso:country":"ES",
    "sg:address":"Calle de Santa Lucia, 45",
    "sg:city":"Haro",
    "sg:orig_category":"Relojer\u00cda (al Por Menor, Reparaci\u00d3n)",
    "sg:phone":"+34 941 30 30 93",
    "sg:postcode":"26200",
    "sg:province":"La Rioja",
    "wof:name":"Azofra Mendoza Jaime",
    "wof:placetype":"venue"
},
  "geometry": {"coordinates":[-2.8475270271,42.5740966797],"type":"Point"}
}