{
  "type": "Feature",
  "properties": {
    "addr:full":"Calle de Balbino Orensanz, 41 Zaragoza Zaragoza 50014",
    "addr:housenumber":"41",
    "addr:postcode":"50014",
    "addr:street":"Calle De Balbino Orensanz",
    "iso:country":"ES",
    "sg:address":"Calle de Balbino Orensanz, 41",
    "sg:city":"Zaragoza",
    "sg:orig_category":"Cajas De Ahorro",
    "sg:phone":"+34 976 29 58 07",
    "sg:postcode":"50014",
    "sg:province":"Zaragoza",
    "wof:name":"Caja De Ahorros Y Monte De Piedad De Zaragoza Aragon Y Rioja",
    "wof:placetype":"venue"
},
  "geometry": {"coordinates":[-0.8585751057,41.6570091248],"type":"Point"}
}