{
  "type": "Feature",
  "properties": {
    "iso:country":"ES",
    "sg:address":"Avda Barcelona, 36",
    "sg:city":"Malaga",
    "sg:orig_category":"Bosques (trabajos, Asesor\u00cda, Gesti\u00d3n)",
    "sg:phone":"+34 952 39 41 50",
    "sg:postcode":"29009",
    "sg:province":"M\u00e1laga",
    "wof:name":"Faura Cuyas Joaquin",
    "wof:placetype":"venue"
},
  "geometry": {"coordinates":[-4.4309391975,36.7251548767],"type":"Point"}
}