{
  "type": "Feature",
  "properties": {
    "addr:full":"Carr Verderol, 9 Albir Alicante 03580",
    "addr:housenumber":"9",
    "addr:postcode":"03580",
    "addr:street":"Carr Verderol;Alicante",
    "iso:country":"ES",
    "sg:address":"Carr Verderol, 9",
    "sg:city":"Albir",
    "sg:orig_category":"Molduras, Junquillos, Listones Y Molduras Perforadas",
    "sg:phone":"+34 966 86 70 12",
    "sg:postcode":"03580",
    "sg:province":"Alicante",
    "wof:name":"Martinez Navarro Paulino",
    "wof:placetype":"venue"
},
  "geometry": {"coordinates":[-0.1033039987,38.5793037415],"type":"Point"}
}