{
  "type": "Feature",
  "properties": {
    "addr:full":"Calle de Anselmo Perez De Brito, 9 Santa Cruz Palma Santa Cruz De Tenerife 38700",
    "addr:housenumber":"9",
    "addr:postcode":"38700",
    "addr:street":"Calle De Anselmo Perez De Brito",
    "iso:country":"ES",
    "sg:address":"Calle de Anselmo Perez De Brito, 9",
    "sg:city":"Santa Cruz Palma",
    "sg:orig_category":"Zapatos (al Por Menor)",
    "sg:phone":"+34 922 41 67 97",
    "sg:postcode":"38700",
    "sg:province":"Santa Cruz De Tenerife",
    "wof:name":"Fernandez Lopez Fernando",
    "wof:placetype":"venue"
},
  "geometry": {"coordinates":[-17.764175415,28.6839065552],"type":"Point"}
}