{
  "type": "Feature",
  "properties": {
    "addr:full":"Carrer de Moli, El, S/n Castellfort Castell\u00f3n 12159",
    "addr:postcode":"12159",
    "addr:street":"Carrer De Moli El S / N Castellfort Castello\u0301N",
    "iso:country":"ES",
    "sg:address":"Carrer de Moli, El, S/n",
    "sg:city":"Castellfort",
    "sg:orig_category":"Centros De Educaci\u00d3n Especial",
    "sg:phone":"+34 964 44 57 93",
    "sg:postcode":"12159",
    "sg:province":"Castell\u00f3n",
    "wof:name":"Generalitat Valenciana",
    "wof:placetype":"venue"
},
  "geometry": {"coordinates":[-0.2726689875,40.4442329407],"type":"Point"}
}