{
  "type": "Feature",
  "properties": {
    "iso:country":"ES",
    "sg:address":"Calle de Puebla De Sanabria, 7",
    "sg:city":"Zamora",
    "sg:orig_category":"Institutos De Belleza",
    "sg:phone":"+34 980 67 16 94",
    "sg:postcode":"49005",
    "sg:province":"Zamora",
    "sg:website":"www.paginasamarillas.es",
    "wof:name":"Malillos Fernandez Maite",
    "wof:placetype":"venue"
},
  "geometry": {"coordinates":[-5.7503490448,41.5058517456],"type":"Point"}
}