{
  "type": "Feature",
  "properties": {
    "iso:country":"ES",
    "sg:address":"Cm\u00d1o Cabreira (da), S/n",
    "sg:city":"Ramallosa",
    "sg:orig_category":"Peluquer\u00cdas, Peluquer\u00cda Mixta",
    "sg:phone":"+34 986 35 47 32",
    "sg:postcode":"36379",
    "sg:province":"Pontevedra",
    "wof:name":"Peluqueria Tetris S.l.",
    "wof:placetype":"venue"
},
  "geometry": {"coordinates":[-8.8124990463,42.1194648743],"type":"Point"}
}