{
  "type": "Feature",
  "properties": {
    "addr:full":"Carrer de Gilabert Centelles, 2 Palma Islas Baleares 07005",
    "addr:housenumber":"2",
    "addr:postcode":"07005",
    "addr:street":"Carrer De Gilabert Centelles",
    "iso:country":"ES",
    "sg:address":"Carrer de Gilabert Centelles, 2",
    "sg:city":"Palma",
    "sg:orig_category":"Ense\u00d1anza, Formaci\u00d3n Profesional: Aprendizaje",
    "sg:phone":"+34 971 46 02 06",
    "sg:postcode":"07005",
    "sg:province":"Islas Baleares",
    "wof:name":"Misinew S.l.",
    "wof:placetype":"venue"
},
  "geometry": {"coordinates":[2.6573960781,39.5737266541],"type":"Point"}
}