{
  "type": "Feature",
  "properties": {
    "iso:country":"ES",
    "sg:address":"Calle de Torrenueva, 13",
    "sg:city":"Ubeda",
    "sg:orig_category":"Inmobiliaria (agencias)",
    "sg:phone":"+34 953 79 21 02",
    "sg:postcode":"23400",
    "sg:province":"Ja\u00e9n",
    "wof:name":"Martinez Triguero Andres",
    "wof:placetype":"venue"
},
  "geometry": {"coordinates":[-3.3715190887,38.0160560608],"type":"Point"}
}