{
  "type": "Feature",
  "properties": {
    "iso:country":"ES",
    "sg:address":"Calle de Concepcion, 28",
    "sg:city":"Navas San Juan",
    "sg:orig_category":"Ense\u00d1anza Variada",
    "sg:phone":"+34 953 68 80 03",
    "sg:postcode":"23240",
    "sg:province":"Ja\u00e9n",
    "wof:name":"Martinez Lopez Maria Soledad",
    "wof:placetype":"venue"
},
  "geometry": {"coordinates":[-3.3133409023,38.1847000122],"type":"Point"}
}