{
  "type": "Feature",
  "properties": {
    "iso:country":"ES",
    "sg:address":"C/ Maximilia Thous, 123",
    "sg:city":"Elche",
    "sg:orig_category":"Puertas Y Portales",
    "sg:phone":"+34 966 63 38 08",
    "sg:postcode":"03204",
    "sg:province":"Alicante",
    "sg:website":"www.indespal.com",
    "wof:name":"Importadora Espa\u00f1ola De Puertas Y Automatismo Del Levante S.a.l.",
    "wof:placetype":"venue"
},
  "geometry": {"coordinates":[-0.7060980201,38.2536468506],"type":"Point"}
}