{
  "type": "Feature",
  "properties": {
    "addr:full":"Calle de Esperanto, 13 Malaga M\u00e1laga 29007",
    "addr:housenumber":"13",
    "addr:postcode":"29007",
    "addr:street":"Calle De Esperanto;Ma\u0301Laga",
    "iso:country":"ES",
    "sg:address":"Calle de Esperanto, 13",
    "sg:city":"Malaga",
    "sg:orig_category":"Institutos De Belleza",
    "sg:phone":"+34 952 61 40 42",
    "sg:postcode":"29007",
    "sg:province":"M\u00e1laga",
    "wof:name":"Alcaide Granados Alicia",
    "wof:placetype":"venue"
},
  "geometry": {"coordinates":[-4.4333791733,36.718711853],"type":"Point"}
}