{
  "type": "Feature",
  "properties": {
    "iso:country":"ES",
    "sg:address":"Barr Larretxo Auzategia, 5",
    "sg:city":"Zumaia",
    "sg:orig_category":"Asociaciones, Organismos Culturales Y Socioeducativos",
    "sg:phone":"+34 943 14 31 04",
    "sg:postcode":"20750",
    "sg:province":"Guip\u00f9zcoa",
    "wof:name":"Sociedad Gastronomica Inda-mendi",
    "wof:placetype":"venue"
},
  "geometry": {"coordinates":[-2.2579610348,43.2989044189],"type":"Point"}
}