{
  "type": "Feature",
  "properties": {
    "iso:country":"ES",
    "sg:address":"Calle de Espejo, 21",
    "sg:city":"Montalban De Cordoba",
    "sg:orig_category":"Fabricaci\u00d3n De Muebles",
    "sg:phone":"+34 957 31 07 83",
    "sg:postcode":"14548",
    "sg:province":"C\u00f3rdoba",
    "wof:name":"Muebles El Mesto S.l.",
    "wof:placetype":"venue"
},
  "geometry": {"coordinates":[-4.7470159531,37.5790863037],"type":"Point"}
}