{
  "type": "Feature",
  "properties": {
    "addr:full":"Ctra Lardero, 42 Entrena La Rioja 26375",
    "addr:housenumber":"42",
    "addr:postcode":"26375",
    "addr:street":"Ctra Lardero;Rioja",
    "iso:country":"ES",
    "sg:address":"Ctra Lardero, 42",
    "sg:city":"Entrena",
    "sg:orig_category":"Mec\u00c1nico Del Autom\u00d3vil",
    "sg:phone":"+34 941 44 62 01",
    "sg:postcode":"26375",
    "sg:province":"La Rioja",
    "wof:name":"Talleres Leyda S.cv.",
    "wof:placetype":"venue"
},
  "geometry": {"coordinates":[-2.5248169899,42.3890037537],"type":"Point"}
}