{
  "type": "Feature",
  "properties": {
    "iso:country":"ES",
    "sg:address":"Calle de Nuestro Padre Jesus Nazareno, 1",
    "sg:city":"Carmona",
    "sg:orig_category":"Desinfecci\u00d3n, Desinsectaci\u00d3n, Desratizaci\u00d3n",
    "sg:phone":"+34 954 19 05 49",
    "sg:postcode":"41410",
    "sg:province":"Sevilla",
    "wof:name":"Investigacion Y Control De Plagas S.l.",
    "wof:placetype":"venue"
},
  "geometry": {"coordinates":[-5.6469378471,37.4755706787],"type":"Point"}
}