{
  "type": "Feature",
  "properties": {
    "addr:full":"Calle de San Roque, 53 Ribadeo Lugo 27700",
    "addr:housenumber":"53",
    "addr:postcode":"27700",
    "addr:street":"Calle De San Roque",
    "iso:country":"ES",
    "sg:address":"Calle de San Roque, 53",
    "sg:city":"Ribadeo",
    "sg:orig_category":"Producci\u00d3n, Distribuci\u00d3n De Gas Butano Y Propano",
    "sg:phone":"+34 982 12 80 04",
    "sg:postcode":"27700",
    "sg:province":"Lugo",
    "wof:name":"Coldeira Amor Jose Luis",
    "wof:placetype":"venue"
},
  "geometry": {"coordinates":[-7.0450692177,43.5376281738],"type":"Point"}
}