{
  "type": "Feature",
  "properties": {
    "iso:country":"ES",
    "sg:address":"Rua Pereira (da), 19",
    "sg:city":"Sobradelo",
    "sg:orig_category":"Escayola Y Productos De Escayola (fabricaci\u00d3n, Al Por Mayor)",
    "sg:phone":"+34 986 50 45 38",
    "sg:postcode":"36611",
    "sg:province":"Pontevedra",
    "wof:name":"Navia Paz Manuel",
    "wof:placetype":"venue"
},
  "geometry": {"coordinates":[-8.7828540802,42.5872116089],"type":"Point"}
}