{
  "type": "Feature",
  "properties": {
    "addr:full":"Calle de Zurbaran, 13 Castuera Badajoz 06420",
    "addr:housenumber":"13",
    "addr:postcode":"06420",
    "addr:street":"Calle De Zurbaran",
    "iso:country":"ES",
    "sg:address":"Calle de Zurbaran, 13",
    "sg:city":"Castuera",
    "sg:orig_category":"Electricidad: Equipos Industriales, Componentes (fabricaci\u00d3n)",
    "sg:phone":"+34 924 76 08 53",
    "sg:postcode":"06420",
    "sg:province":"Badajoz",
    "wof:name":"Lorenzo Roman S.a.",
    "wof:placetype":"venue"
},
  "geometry": {"coordinates":[-5.5454063416,38.7263641357],"type":"Point"}
}