{
  "type": "Feature",
  "properties": {
    "iso:country":"ES",
    "sg:address":"Calle de Sigfrido, 7",
    "sg:city":"Malaga",
    "sg:orig_category":"Agentes, Concesionarios Y Sucursales De Veh\u00cdculos",
    "sg:phone":"+34 952 36 08 28",
    "sg:postcode":"29006",
    "sg:province":"M\u00e1laga",
    "wof:name":"Villalta Villalva Miguel",
    "wof:placetype":"venue"
},
  "geometry": {"coordinates":[-4.469329834,36.7080039978],"type":"Point"}
}