{
  "type": "Feature",
  "properties": {
    "iso:country":"ES",
    "sg:address":"Calle de San Francisco, 2",
    "sg:city":"Ribadeo",
    "sg:orig_category":"Complementos De Vestir (al Por Menor)",
    "sg:phone":"+34 982 13 19 38",
    "sg:postcode":"27700",
    "sg:province":"Lugo",
    "wof:name":"Regodeseves Regodeseves Monica",
    "wof:placetype":"venue"
},
  "geometry": {"coordinates":[-7.0414581299,43.5354270935],"type":"Point"}
}