{
  "type": "Feature",
  "properties": {
    "iso:country":"ES",
    "sg:address":"Principal (touza), S/n",
    "sg:city":"San Fiz",
    "sg:classifiers":[
        {
            "category":"Taxi",
            "type":"Transportation"
        }
    ],
    "sg:phone":"+34 988 28 83 26",
    "sg:postcode":"32574",
    "sg:province":"Ourense",
    "wof:name":"Garcia Alvarez Julio",
    "wof:placetype":"venue"
},
  "geometry": {"coordinates":[-8.0229282379,42.4114875793],"type":"Point"}
}