{
  "type": "Feature",
  "properties": {
    "iso:country":"ES",
    "sg:address":"Rond Sant Antoni Maria Claret, 14",
    "sg:city":"Girona",
    "sg:orig_category":"Lanas (al Por Menor)",
    "sg:phone":"+34 972 21 96 28",
    "sg:postcode":"17001",
    "sg:province":"Girona",
    "wof:name":"Ripoll Borrell Maria Nuria",
    "wof:placetype":"venue"
},
  "geometry": {"coordinates":[2.8202450275,41.9797668457],"type":"Point"}
}