{
  "type": "Feature",
  "properties": {
    "addr:full":"Calle de F(poligono Industrial), S/n Villarrobledo Albacete 02600",
    "addr:postcode":"02600",
    "addr:street":"Calle De F Poligono Industrial S / N",
    "iso:country":"ES",
    "sg:address":"Calle de F(poligono Industrial), S/n",
    "sg:city":"Villarrobledo",
    "sg:orig_category":"Contenedores (mercanc\u00cdas)",
    "sg:phone":"+34 967 14 06 84",
    "sg:postcode":"02600",
    "sg:province":"Albacete",
    "wof:name":"Transportes Pedro Romero Martinez S.l.",
    "wof:placetype":"venue"
},
  "geometry": {"coordinates":[-2.6026189327,39.2637481689],"type":"Point"}
}