{
  "type": "Feature",
  "properties": {
    "iso:country":"ES",
    "sg:address":"Ptge Sagrament, 6",
    "sg:city":"Sant Feliu Llobregat",
    "sg:orig_category":"Supermercados Y Hipermercados",
    "sg:phone":"+34 936 66 33 42",
    "sg:postcode":"08980",
    "sg:province":"Barcelona",
    "wof:name":"Autoservicio Aujo S.l.",
    "wof:placetype":"venue"
},
  "geometry": {"coordinates":[2.045122385,41.3882904053],"type":"Point"}
}