{
  "type": "Feature",
  "properties": {
    "iso:country":"ES",
    "sg:address":"Calle de Achuri, 18",
    "sg:city":"Madrid",
    "sg:orig_category":"Transportes De Material De Construcci\u00d3n",
    "sg:phone":"+34 913 67 89 16",
    "sg:postcode":"28017",
    "sg:province":"Madrid",
    "wof:name":"Encinar Jimenez Victoriano",
    "wof:placetype":"venue"
},
  "geometry": {"coordinates":[-3.6415922642,40.4287261963],"type":"Point"}
}