{
  "type": "Feature",
  "properties": {
    "iso:country":"ES",
    "sg:address":"Av De Andalucia, 78",
    "sg:city":"Torrox-costa",
    "sg:orig_category":"Inform\u00c1tica, Ofim\u00c1tica (estudios, Asesor\u00cda, Ingenier\u00cda, Formaci\u00d3n)",
    "sg:phone":"+34 952 53 07 45",
    "sg:postcode":"29793",
    "sg:province":"M\u00e1laga",
    "sg:website":"www.elmorche.net",
    "wof:name":"Frias Montero Jorge",
    "wof:placetype":"venue"
},
  "geometry": {"coordinates":[-3.9873039722,36.7375984192],"type":"Point"}
}