{
  "type": "Feature",
  "properties": {
    "iso:country":"ES",
    "sg:address":"Calle de Kristo Eskilara, 8",
    "sg:city":"Plentzia",
    "sg:orig_category":"Ense\u00d1anza: Idiomas",
    "sg:phone":"+34 946 77 36 07",
    "sg:postcode":"48620",
    "sg:province":"Vizcaya",
    "wof:name":"Euskaraz Koop. E.",
    "wof:placetype":"venue"
},
  "geometry": {"coordinates":[-2.9467689991,43.4036178589],"type":"Point"}
}