{
  "type": "Feature",
  "properties": {
    "addr:full":"Calle de Doctor Recasens, 3 Alacant Alicante 03009",
    "addr:housenumber":"3",
    "addr:postcode":"03009",
    "addr:street":"Calle De Doctor Recasens",
    "iso:country":"ES",
    "sg:address":"Calle de Doctor Recasens, 3",
    "sg:city":"Alacant",
    "sg:orig_category":"Aer\u00d3grafo",
    "sg:phone":"+34 965 17 03 50",
    "sg:postcode":"03009",
    "sg:province":"Alicante",
    "wof:name":"Ros Sanchez Antonio",
    "wof:placetype":"venue"
},
  "geometry": {"coordinates":[-0.5055958033,38.3650512695],"type":"Point"}
}