{
  "type": "Feature",
  "properties": {
    "addr:full":"Pl Marques De Caldes De Montbui, 7 Caldes Montbui Barcelona 08140",
    "addr:housenumber":"7",
    "addr:postcode":"08140",
    "addr:street":"Pl Marques De Caldes De Montbui;Montbui Barcelona",
    "iso:country":"ES",
    "sg:address":"Pl Marques De Caldes De Montbui, 7",
    "sg:city":"Caldes Montbui",
    "sg:orig_category":"Doctores En Medicina",
    "sg:phone":"+34 938 62 63 02",
    "sg:postcode":"08140",
    "sg:province":"Barcelona",
    "wof:name":"Monserrat Delgado Jose Luis",
    "wof:placetype":"venue"
},
  "geometry": {"coordinates":[2.1686599255,41.631111145],"type":"Point"}
}