{
  "type": "Feature",
  "properties": {
    "iso:country":"ES",
    "sg:address":"Avda Miguel De Cervantes, 53",
    "sg:city":"Tarancon",
    "sg:orig_category":"Bisuter\u00cda, Joyer\u00cda, Relojer\u00cda (al Por Menor)",
    "sg:phone":"+34 969 32 33 05",
    "sg:postcode":"16400",
    "sg:province":"Cuenca",
    "wof:name":"Perez Perez Antonia",
    "wof:placetype":"venue"
},
  "geometry": {"coordinates":[-3.011605978,40.0100135803],"type":"Point"}
}