{
  "type": "Feature",
  "properties": {
    "iso:country":"ES",
    "sg:address":"Pg Elx, 6",
    "sg:city":"Crevillent",
    "sg:orig_category":"Mec\u00c1nico Del Autom\u00d3vil",
    "sg:phone":"+34 965 40 08 15",
    "sg:postcode":"03330",
    "sg:province":"Alicante",
    "wof:name":"Guilabert Alfonso Francisco Javier",
    "wof:placetype":"venue"
},
  "geometry": {"coordinates":[-0.8017249703,38.2477607727],"type":"Point"}
}