{
  "type": "Feature",
  "properties": {
    "addr:full":"Pase San Francisco De Sales, 21 Madrid Madrid 28003",
    "addr:housenumber":"21",
    "addr:postcode":"madrid;28003",
    "addr:street":"Francisco De Sales",
    "iso:country":"ES",
    "sg:address":"Pase San Francisco De Sales, 21",
    "sg:city":"Madrid",
    "sg:orig_category":"Doctores En Medicina",
    "sg:phone":"+34 915 44 42 87",
    "sg:postcode":"28003",
    "sg:province":"Madrid",
    "wof:name":"Ruiz De La Hermosa Andres Angel",
    "wof:placetype":"venue"
},
  "geometry": {"coordinates":[-3.7149569988,40.4411506653],"type":"Point"}
}