{
  "type": "Feature",
  "properties": {
    "addr:full":"Rua Roberto Baamonde, 104 Monforte De Lemos Lugo 27400",
    "addr:housenumber":"104",
    "addr:postcode":"27400",
    "addr:street":"Rua Roberto Baamonde",
    "iso:country":"ES",
    "sg:address":"Rua Roberto Baamonde, 104",
    "sg:city":"Monforte De Lemos",
    "sg:orig_category":"Electromec\u00c1nica",
    "sg:phone":"+34 982 40 27 24",
    "sg:postcode":"27400",
    "sg:province":"Lugo",
    "wof:name":"Iglesias Almeida Beatriz",
    "wof:placetype":"venue"
},
  "geometry": {"coordinates":[-7.5078439713,42.5215759277],"type":"Point"}
}