{
  "type": "Feature",
  "properties": {
    "iso:country":"ES",
    "sg:address":"Avgd Sucro, 1",
    "sg:city":"Alzira",
    "sg:orig_category":"Complementos De Vestir (al Por Menor)",
    "sg:phone":"+34 962 41 01 33",
    "sg:postcode":"46600",
    "sg:province":"Valencia",
    "wof:name":"Martinez Samblancat Maria Luisa",
    "wof:placetype":"venue"
},
  "geometry": {"coordinates":[-0.4381920099,39.1502151489],"type":"Point"}
}