{
  "type": "Feature",
  "properties": {
    "iso:country":"ES",
    "sg:address":"Ctra. Trassierra, S/n",
    "sg:city":"Castillo Albaida",
    "sg:orig_category":"Equitaci\u00d3n Y Centros De H\u00cdpica",
    "sg:phone":"+34 957 33 00 25",
    "sg:postcode":"14011",
    "sg:province":"C\u00f3rdoba",
    "wof:name":"Poni Club De Cordoba S.l.",
    "wof:placetype":"venue"
},
  "geometry": {"coordinates":[-4.8999910355,37.9277877808],"type":"Point"}
}