{
  "type": "Feature",
  "properties": {
    "iso:country":"ES",
    "sg:address":"Avenida De La Vera, 105",
    "sg:city":"Villanueva Vera",
    "sg:orig_category":"M\u00c9dicos: Estomatolog\u00cda",
    "sg:phone":"+34 927 56 71 99",
    "sg:postcode":"10470",
    "sg:province":"C\u00e1ceres",
    "wof:name":"De La Calle Leal Silvia",
    "wof:placetype":"venue"
},
  "geometry": {"coordinates":[-5.4646830559,40.1295509338],"type":"Point"}
}