{
  "type": "Feature",
  "properties": {
    "addr:full":"Carr Pirineos, 50 Ma\u00e7anet Selva Girona 17412",
    "addr:housenumber":"50",
    "addr:postcode":"17412",
    "addr:street":"Carr Pirineos",
    "iso:country":"ES",
    "sg:address":"Carr Pirineos, 50",
    "sg:city":"Ma\u00e7anet Selva",
    "sg:orig_category":"Muebles, Minoristas",
    "sg:phone":"+34 972 85 87 57",
    "sg:postcode":"17412",
    "sg:province":"Girona",
    "wof:name":"Mobles Campeny S.l.",
    "wof:placetype":"venue"
},
  "geometry": {"coordinates":[2.7342700958,41.7778396606],"type":"Point"}
}