{
  "type": "Feature",
  "properties": {
    "addr:full":"Calle de Castilla, 1 Marchamalo Guadalajara 19180",
    "addr:housenumber":"1",
    "addr:postcode":"19180",
    "addr:street":"Calle De Castilla",
    "iso:country":"ES",
    "sg:address":"Calle de Castilla, 1",
    "sg:city":"Marchamalo",
    "sg:orig_category":"Librer\u00cdas",
    "sg:phone":"+34 949 25 01 86",
    "sg:postcode":"19180",
    "sg:province":"Guadalajara",
    "wof:name":"Buendia Fernandez Jesus",
    "wof:placetype":"venue"
},
  "geometry": {"coordinates":[-3.2066056728,40.6684417725],"type":"Point"}
}