{
  "type": "Feature",
  "properties": {
    "addr:full":"Monjas, 3 Huete Cuenca 16500",
    "addr:housenumber":"3",
    "addr:postcode":"16500",
    "addr:street":"Monjas",
    "iso:country":"ES",
    "sg:address":"Monjas, 3",
    "sg:city":"Huete",
    "sg:orig_category":"Agentes Generales De Seguros",
    "sg:phone":"+34 969 37 20 51",
    "sg:postcode":"16500",
    "sg:province":"Cuenca",
    "wof:name":"Fernandez Picon Carlos",
    "wof:placetype":"venue"
},
  "geometry": {"coordinates":[-2.6889390945,40.1415786743],"type":"Point"}
}