{
  "type": "Feature",
  "properties": {
    "addr:full":"Calle de Cervantes, 25 Ejido Almer\u00eda 04700",
    "addr:housenumber":"25 ejido",
    "addr:postcode":"04700",
    "addr:street":"Calle De Cervantes;Almeri\u0301A",
    "iso:country":"ES",
    "sg:address":"Calle de Cervantes, 25",
    "sg:city":"Ejido",
    "sg:orig_category":"Empleado Administrativo",
    "sg:phone":"+34 950 48 33 17",
    "sg:postcode":"04700",
    "sg:province":"Almer\u00eda",
    "wof:name":"Vazquez Garcia Maria Josefa",
    "wof:placetype":"venue"
},
  "geometry": {"coordinates":[-2.8156659603,36.774723053],"type":"Point"}
}