{
  "type": "Feature",
  "properties": {
    "addr:full":"Calle de Mar Negro, 4 Madrid Madrid 28033",
    "addr:housenumber":"4",
    "addr:postcode":"28033",
    "addr:street":"Calle De Mar Negro",
    "iso:country":"ES",
    "sg:address":"Calle de Mar Negro, 4",
    "sg:city":"Madrid",
    "sg:orig_category":"Alimentaci\u00d3n General (al Por Menor)",
    "sg:phone":"+34 917 64 54 27",
    "sg:postcode":"28033",
    "sg:province":"Madrid",
    "wof:name":"Perez Paredes Alejandro",
    "wof:placetype":"venue"
},
  "geometry": {"coordinates":[-3.6430768967,40.4740142822],"type":"Point"}
}