{
  "type": "Feature",
  "properties": {
    "addr:full":"Calle de 31 De Agosto, 11 Donostia-san Sebastian Guip\u00f9zcoa 20003",
    "addr:housenumber":"31;11",
    "addr:postcode":"20003",
    "addr:street":"Calle De;De Agosto",
    "iso:country":"ES",
    "sg:address":"Calle de 31 De Agosto, 11",
    "sg:city":"Donostia-san Sebastian",
    "sg:orig_category":"Art\u00cdculos De Regalo (al Por Menor)",
    "sg:phone":"+34 943 42 60 48",
    "sg:postcode":"20003",
    "sg:province":"Guip\u00f9zcoa",
    "wof:name":"Verdeny Toha Laura",
    "wof:placetype":"venue"
},
  "geometry": {"coordinates":[-1.9850130081,43.3242034912],"type":"Point"}
}