{
  "type": "Feature",
  "properties": {
    "iso:country":"ES",
    "sg:address":"Miluze, 4",
    "sg:city":"Iru\u00f1a",
    "sg:orig_category":"Talleres El\u00c9ctricos Para Veh\u00cdculos",
    "sg:phone":"+34 948 25 23 36",
    "sg:postcode":"31008",
    "sg:province":"Navarra",
    "wof:name":"Francos Gonzalez Santiago",
    "wof:placetype":"venue"
},
  "geometry": {"coordinates":[-1.673635006,42.8058166504],"type":"Point"}
}