{
  "type": "Feature",
  "properties": {
    "addr:full":"Plaz Ramon Y Cajal, 14 Valderas Le\u00f3n 24220",
    "addr:housenumber":"14",
    "addr:postcode":"24220",
    "addr:street":"Ramon Y Cajal",
    "iso:country":"ES",
    "sg:address":"Plaz Ramon Y Cajal, 14",
    "sg:city":"Valderas",
    "sg:orig_category":"Venta, Instalaci\u00d3n De Cocinas",
    "sg:phone":"+34 987 76 23 77",
    "sg:postcode":"24220",
    "sg:province":"Le\u00f3n",
    "wof:name":"Rueda Garcia Nuria",
    "wof:placetype":"venue"
},
  "geometry": {"coordinates":[-5.4439268112,42.0789871216],"type":"Point"}
}