{
  "type": "Feature",
  "properties": {
    "addr:full":"Urb La Espartera, S/n Guadix Granada 18500",
    "addr:housenumber":"s",
    "addr:postcode":"18500",
    "addr:street":"/ N",
    "iso:country":"ES",
    "sg:address":"Urb La Espartera, S/n",
    "sg:city":"Guadix",
    "sg:orig_category":"Empresas De Desmonte",
    "sg:phone":"+34 958 66 64 70",
    "sg:postcode":"18500",
    "sg:province":"Granada",
    "wof:name":"Excavaciones El Bicicletas S.l.",
    "wof:placetype":"venue"
},
  "geometry": {"coordinates":[-3.1343688965,37.303894043],"type":"Point"}
}