{
  "type": "Feature",
  "properties": {
    "iso:country":"ES",
    "sg:address":"C/ Gabriel Y Galan, 12",
    "sg:city":"Elche",
    "sg:orig_category":"Asociaciones, Organismos Culturales Y Socioeducativos",
    "sg:phone":"+34 965 45 01 67",
    "sg:postcode":"03202",
    "sg:province":"Alicante",
    "wof:name":"Asociacion Cultural Maracaibo Teatro",
    "wof:placetype":"venue"
},
  "geometry": {"coordinates":[-0.6929191947,38.2680587769],"type":"Point"}
}