{
  "type": "Feature",
  "properties": {
    "iso:country":"ES",
    "sg:address":"Av Ramon I Cajal, 31",
    "sg:city":"Tarragona",
    "sg:orig_category":"M\u00c9dicos: Cirug\u00cda Pl\u00c1stica, Reconstructiva Y Est\u00c9tica",
    "sg:phone":"+34 977 24 59 04",
    "sg:postcode":"43001",
    "sg:province":"Tarragona",
    "wof:name":"Gallego Andrade Maria Victoria",
    "wof:placetype":"venue"
},
  "geometry": {"coordinates":[1.2458809614,41.1163635254],"type":"Point"}
}