{
  "type": "Feature",
  "properties": {
    "iso:country":"ES",
    "sg:address":"Calle de Poza Licenciado, 20",
    "sg:city":"Bilbao",
    "sg:orig_category":"Farmacias",
    "sg:phone":"+34 944 41 12 38",
    "sg:postcode":"48011",
    "sg:province":"Vizcaya",
    "wof:name":"Gema Hernandez Dominguez (farmacia)",
    "wof:placetype":"venue"
},
  "geometry": {"coordinates":[-2.938710928,43.2617416382],"type":"Point"}
}