{
  "type": "Feature",
  "properties": {
    "iso:country":"ES",
    "sg:address":"Avda San Jose, 2",
    "sg:city":"Gines",
    "sg:orig_category":"Sales (al Por Mayor)",
    "sg:phone":"+34 954 71 32 62",
    "sg:postcode":"41960",
    "sg:province":"Sevilla",
    "sg:website":"www.ginenecina.com",
    "wof:name":"Sat El Aljarafe",
    "wof:placetype":"venue"
},
  "geometry": {"coordinates":[-6.0775527954,37.3883132935],"type":"Point"}
}