{
  "type": "Feature",
  "properties": {
    "iso:country":"ES",
    "sg:address":"Calle de Siena, 27",
    "sg:city":"Madrid",
    "sg:orig_category":"Sellos De Goma Y Met\u00c1licos",
    "sg:phone":"+34 913 26 45 32",
    "sg:postcode":"28027",
    "sg:province":"Madrid",
    "wof:name":"Marin Escobar Josefa",
    "wof:placetype":"venue"
},
  "geometry": {"coordinates":[-3.654086113,40.4330482483],"type":"Point"}
}