{
  "type": "Feature",
  "properties": {
    "addr:full":"Avda Gijon, 17 Valladolid Valladolid 47009",
    "addr:housenumber":"17",
    "addr:postcode":"47009",
    "addr:street":"Avda Gijon",
    "iso:country":"ES",
    "sg:address":"Avda Gijon, 17",
    "sg:city":"Valladolid",
    "sg:orig_category":"Empresarios",
    "sg:phone":"+34 983 37 72 74",
    "sg:postcode":"47009",
    "sg:province":"Valladolid",
    "wof:name":"Fundacion Escuelas Cristo Rey",
    "wof:placetype":"venue"
},
  "geometry": {"coordinates":[-4.7486691475,41.6605911255],"type":"Point"}
}