{
  "type": "Feature",
  "properties": {
    "iso:country":"ES",
    "sg:address":"Calle de Neurketa, 1",
    "sg:city":"Mungia",
    "sg:orig_category":"Lavado, Limpieza De Veh\u00cdculos",
    "sg:phone":"+34 946 15 59 15",
    "sg:postcode":"48100",
    "sg:province":"Vizcaya",
    "wof:name":"Engrase Luis",
    "wof:placetype":"venue"
},
  "geometry": {"coordinates":[-2.8478939533,43.3557624817],"type":"Point"}
}