{
  "type": "Feature",
  "properties": {
    "addr:full":"Carrer de Freser, 114 Barcelona Barcelona 08026",
    "addr:housenumber":"114",
    "addr:postcode":"08026",
    "addr:street":"Carrer De Freser",
    "iso:country":"ES",
    "sg:address":"Carrer de Freser, 114",
    "sg:city":"Barcelona",
    "sg:orig_category":"Mec\u00c1nico Del Autom\u00d3vil",
    "sg:phone":"+34 934 33 57 57",
    "sg:postcode":"08026",
    "sg:province":"Barcelona",
    "sg:website":"www.meridianamotors.com",
    "wof:name":"Meridiana Motors S.a.",
    "wof:placetype":"venue"
},
  "geometry": {"coordinates":[2.1810901165,41.4128723145],"type":"Point"}
}