{
  "type": "Feature",
  "properties": {
    "iso:country":"ES",
    "sg:address":"Calle de Blas Infante, 1",
    "sg:city":"Ubeda",
    "sg:orig_category":"Centros De Educaci\u00d3n Especial",
    "sg:phone":"+34 953 75 50 00",
    "sg:postcode":"23400",
    "sg:province":"Ja\u00e9n",
    "wof:name":"Ayuntamiento De Ubeda",
    "wof:placetype":"venue"
},
  "geometry": {"coordinates":[-3.3795692921,38.0152130127],"type":"Point"}
}