{
  "type": "Feature",
  "properties": {
    "iso:country":"ES",
    "sg:address":"Calle de Santa Maria, 10",
    "sg:city":"Bilbao",
    "sg:orig_category":"Molduras, Junquillos, Listones Y Molduras Perforadas",
    "sg:phone":"+34 944 15 48 61",
    "sg:postcode":"48005",
    "sg:province":"Vizcaya",
    "wof:name":"Ramos Robles Carlos",
    "wof:placetype":"venue"
},
  "geometry": {"coordinates":[-2.9260709286,43.2582054138],"type":"Point"}
}