{
  "type": "Feature",
  "properties": {
    "addr:full":"San Miguel, S/n Vega Arboles Le\u00f3n 24219",
    "addr:housenumber":"s / n",
    "addr:postcode":"24219",
    "addr:street":"San Miguel;Arboles Leo\u0301N",
    "iso:country":"ES",
    "sg:address":"San Miguel, S/n",
    "sg:city":"Vega Arboles",
    "sg:orig_category":"Cooperativas Agr\u00cdcolas",
    "sg:phone":"+34 987 31 36 26",
    "sg:postcode":"24219",
    "sg:province":"Le\u00f3n",
    "wof:name":"Veroga S.a.t.",
    "wof:placetype":"venue"
},
  "geometry": {"coordinates":[-5.4137969017,42.5331802368],"type":"Point"}
}