{
  "type": "Feature",
  "properties": {
    "iso:country":"ES",
    "sg:address":"Calle de Robles, 1",
    "sg:city":"Talavera Reina",
    "sg:orig_category":"Negocio De Materiales De Construcci\u00d3n",
    "sg:phone":"+34 925 80 55 54",
    "sg:postcode":"45600",
    "sg:province":"Toledo",
    "wof:name":"Bloques Del Tajo S.l.",
    "wof:placetype":"venue"
},
  "geometry": {"coordinates":[-4.8326430321,39.9509849548],"type":"Point"}
}