{
  "type": "Feature",
  "properties": {
    "iso:country":"ES",
    "sg:address":"Calle de Independencia, 11",
    "sg:city":"Pizarra",
    "sg:orig_category":"Quincaller\u00cda (al Por Menor)",
    "sg:phone":"+34 952 48 37 26",
    "sg:postcode":"29560",
    "sg:province":"M\u00e1laga",
    "wof:name":"Rueda Gomez Antonio",
    "wof:placetype":"venue"
},
  "geometry": {"coordinates":[-4.7078108788,36.7659683228],"type":"Point"}
}