{
  "type": "Feature",
  "properties": {
    "iso:country":"ES",
    "sg:address":"Calle de Tesifonte Gallego, 9",
    "sg:city":"Albacete",
    "sg:orig_category":"Reposter\u00cdas",
    "sg:phone":"+34 967 21 43 99",
    "sg:postcode":"02002",
    "sg:province":"Albacete",
    "wof:name":"Fernandez Fernandez,guadalupe",
    "wof:placetype":"venue"
},
  "geometry": {"coordinates":[-1.8553769588,38.9922676086],"type":"Point"}
}