{
  "type": "Feature",
  "properties": {
    "iso:country":"ES",
    "sg:address":"Calle de Casimiro Escudero, 4",
    "sg:city":"Madrid",
    "sg:orig_category":"Servicio De Salud",
    "sg:phone":"+34 914 28 41 69",
    "sg:postcode":"28025",
    "sg:province":"Madrid",
    "wof:name":"Herrerocons Saneamientos S.l.",
    "wof:placetype":"venue"
},
  "geometry": {"coordinates":[-3.742497921,40.3898429871],"type":"Point"}
}