{
  "type": "Feature",
  "properties": {
    "addr:full":"Carr Valencia, S/n Almenara Castell\u00f3n 12590",
    "addr:housenumber":"s / n",
    "addr:postcode":"12590",
    "addr:street":"Carr Valencia",
    "iso:country":"ES",
    "sg:address":"Carr Valencia, S/n",
    "sg:city":"Almenara",
    "sg:orig_category":"Transportes Internacionales",
    "sg:phone":"+34 962 61 01 51",
    "sg:postcode":"12590",
    "sg:province":"Castell\u00f3n",
    "wof:name":"Trans-for S. L.",
    "wof:placetype":"venue"
},
  "geometry": {"coordinates":[-0.2252819985,39.7522544861],"type":"Point"}
}