{
  "type": "Feature",
  "properties": {
    "addr:full":"Pg Joanot Martorell, 1 Granollers Barcelona 08403",
    "addr:housenumber":"1",
    "addr:postcode":"08403",
    "addr:street":"Pg Joanot Martorell",
    "iso:country":"ES",
    "sg:address":"Pg Joanot Martorell, 1",
    "sg:city":"Granollers",
    "sg:orig_category":"Molduras, Junquillos, Listones Y Molduras Perforadas",
    "sg:phone":"+34 938 46 31 65",
    "sg:postcode":"08403",
    "sg:province":"Barcelona",
    "wof:name":"Bar Rumi S.cv.",
    "wof:placetype":"venue"
},
  "geometry": {"coordinates":[2.2780330181,41.6110839844],"type":"Point"}
}