{
  "type": "Feature",
  "properties": {
    "addr:full":"Carrer de Doctor Trueta, S/n Castelldefels Barcelona 08860",
    "addr:housenumber":"s",
    "addr:postcode":"08860",
    "addr:street":"Carrer De Doctor Trueta;/ N",
    "iso:country":"ES",
    "sg:address":"Carrer de Doctor Trueta, S/n",
    "sg:city":"Castelldefels",
    "sg:orig_category":"Centros De Educaci\u00d3n Especial",
    "sg:phone":"+34 936 65 57 73",
    "sg:postcode":"08860",
    "sg:province":"Barcelona",
    "wof:name":"Col.legi Public Can Roca",
    "wof:placetype":"venue"
},
  "geometry": {"coordinates":[1.9757699966,41.2801246643],"type":"Point"}
}