{
  "type": "Feature",
  "properties": {
    "addr:full":"C/ Doctor Josep Maria Vilaseca, 17 Calonge Girona 17251",
    "addr:housenumber":"17",
    "addr:postcode":"17251",
    "addr:street":"C / Doctor Josep Maria Vilaseca",
    "iso:country":"ES",
    "sg:address":"C/ Doctor Josep Maria Vilaseca, 17",
    "sg:city":"Calonge",
    "sg:orig_category":"Panader\u00cdas, Panader\u00cdas",
    "sg:phone":"+34 972 65 01 35",
    "sg:postcode":"17251",
    "sg:province":"Girona",
    "wof:name":"Robert Quintana Jose",
    "wof:placetype":"venue"
},
  "geometry": {"coordinates":[3.0748510361,41.8590126038],"type":"Point"}
}