{
  "type": "Feature",
  "properties": {
    "addr:full":"Plaz San Miguel, 5 Madrid Madrid 28005",
    "addr:housenumber":"5",
    "addr:postcode":"28005",
    "addr:street":"Plaz San Miguel",
    "iso:country":"ES",
    "sg:address":"Plaz San Miguel, 5",
    "sg:city":"Madrid",
    "sg:orig_category":"Herboristas (al Por Menor)",
    "sg:phone":"+34 913 66 58 51",
    "sg:postcode":"28005",
    "sg:province":"Madrid",
    "wof:name":"Perez Torrado Manuel Felipe",
    "wof:placetype":"venue"
},
  "geometry": {"coordinates":[-3.7090280056,40.4150848389],"type":"Point"}
}