{
  "type": "Feature",
  "properties": {
    "addr:full":"Calle de Lectoral Sirvent, 10 Almeria Almer\u00eda 04003",
    "addr:housenumber":"10",
    "addr:postcode":"04003",
    "addr:street":"Calle De Lectoral Sirvent",
    "iso:country":"ES",
    "sg:address":"Calle de Lectoral Sirvent, 10",
    "sg:city":"Almeria",
    "sg:orig_category":"Asociaciones, Organismos Culturales Y Socioeducativos",
    "sg:phone":"+34 950 26 83 21",
    "sg:postcode":"04003",
    "sg:province":"Almer\u00eda",
    "wof:name":"Hermandad Eucaristica De La Santa Cena",
    "wof:placetype":"venue"
},
  "geometry": {"coordinates":[-2.4664061069,36.8408699036],"type":"Point"}
}