{
  "type": "Feature",
  "properties": {
    "iso:country":"ES",
    "sg:address":"Calle de Poeta Alberola, 22",
    "sg:city":"Valencia",
    "sg:orig_category":"Agencias Y Agentes Comerciales, Representantes",
    "sg:phone":"+34 963 84 93 84",
    "sg:postcode":"46018",
    "sg:province":"Valencia",
    "wof:name":"Fernandez Parra Joaquin",
    "wof:placetype":"venue"
},
  "geometry": {"coordinates":[-0.3942250013,39.4697227478],"type":"Point"}
}