{
  "type": "Feature",
  "properties": {
    "addr:full":"Calle de Melilla, 30 Alcala Henares Madrid 28805",
    "addr:housenumber":"30",
    "addr:postcode":"28805",
    "addr:street":"Calle De Melilla",
    "iso:country":"ES",
    "sg:address":"Calle de Melilla, 30",
    "sg:city":"Alcala Henares",
    "sg:orig_category":"Cerrajer\u00cda, Ferrallista",
    "sg:phone":"+34 918 88 00 17",
    "sg:postcode":"28805",
    "sg:province":"Madrid",
    "wof:name":"Construcciones Metalicas Desman S.l.",
    "wof:placetype":"venue"
},
  "geometry": {"coordinates":[-3.3406550884,40.4937095642],"type":"Point"}
}