{
  "type": "Feature",
  "properties": {
    "addr:full":"Carrer de Rierot (el), 2 Mataro Barcelona 08301",
    "addr:housenumber":"2",
    "addr:postcode":"08301",
    "addr:street":"Carrer De Rierot El",
    "iso:country":"ES",
    "sg:address":"Carrer de Rierot (el), 2",
    "sg:city":"Mataro",
    "sg:orig_category":"Frutas, Legumbres Frescas Y Tempranas (al Por Menor)",
    "sg:phone":"+34 937 55 05 28",
    "sg:postcode":"08301",
    "sg:province":"Barcelona",
    "wof:name":"Jimenez Linares Gabriel",
    "wof:placetype":"venue"
},
  "geometry": {"coordinates":[2.4474570751,41.5441741943],"type":"Point"}
}