{
  "type": "Feature",
  "properties": {
    "iso:country":"ES",
    "sg:address":"Calle de Jarama (del), 10",
    "sg:city":"Alcobendas",
    "sg:orig_category":"Postigos, Persianas Y Celos\u00cdas",
    "sg:phone":"+34 916 52 94 95",
    "sg:postcode":"28100",
    "sg:province":"Madrid",
    "wof:name":"Persianas Ollero C.b.",
    "wof:placetype":"venue"
},
  "geometry": {"coordinates":[-3.6389949322,40.544216156],"type":"Point"}
}