{
  "type": "Feature",
  "properties": {
    "iso:country":"ES",
    "sg:address":"Calle de Granada, 49",
    "sg:city":"Malaga",
    "sg:orig_category":"Ropa Para Se\u00d1oras Y Caballeros (al Por Menor)",
    "sg:phone":"+34 952 22 02 20",
    "sg:postcode":"29015",
    "sg:province":"M\u00e1laga",
    "sg:website":"www.sharmamalaga.com",
    "wof:name":"Vega Aguilera Juan Carlos",
    "wof:placetype":"venue"
},
  "geometry": {"coordinates":[-4.4183659554,36.7220878601],"type":"Point"}
}