{
  "type": "Feature",
  "properties": {
    "addr:full":"Calle de Benitagla, 21 Almeria Almer\u00eda 04006",
    "addr:housenumber":"21",
    "addr:postcode":"04006",
    "addr:street":"Calle De Benitagla",
    "iso:country":"ES",
    "sg:address":"Calle de Benitagla, 21",
    "sg:city":"Almeria",
    "sg:orig_category":"Cajas De Ahorro",
    "sg:phone":"+34 950 26 85 77",
    "sg:postcode":"04006",
    "sg:province":"Almer\u00eda",
    "sg:website":"www.cajadeahorros.sur",
    "wof:name":"Caja De Ahorros Y Monte De Piedad De Cordoba",
    "wof:placetype":"venue"
},
  "geometry": {"coordinates":[-2.443543911,36.8369102478],"type":"Point"}
}