{
  "type": "Feature",
  "properties": {
    "addr:full":"Barr Axpe, 64 Axpe-san Bartolome Vizcaya 48350",
    "addr:housenumber":"64",
    "addr:postcode":"48350",
    "addr:street":"Barr Axpe",
    "iso:country":"ES",
    "sg:address":"Barr Axpe, 64",
    "sg:city":"Axpe-san Bartolome",
    "sg:orig_category":"Asilos De Ancianos. Centros Privados",
    "sg:phone":"+34 946 87 00 03",
    "sg:postcode":"48350",
    "sg:province":"Vizcaya",
    "wof:name":"Fundacion Benefica Don Nicolas Domingo De Arrotegui",
    "wof:placetype":"venue"
},
  "geometry": {"coordinates":[-2.6975340843,43.3843383789],"type":"Point"}
}