{
  "type": "Feature",
  "properties": {
    "addr:full":"Sta T. Jornet, 53 Cabra C\u00f3rdoba 14940",
    "addr:housenumber":"53",
    "addr:postcode":"14940",
    "addr:street":"Sta T. Jornet;Co\u0301Rdoba",
    "iso:country":"ES",
    "sg:address":"Sta T. Jornet, 53",
    "sg:city":"Cabra",
    "sg:orig_category":"Fotocopias, Reprograf\u00cda",
    "sg:phone":"+34 957 52 30 67",
    "sg:postcode":"14940",
    "sg:province":"C\u00f3rdoba",
    "wof:name":"Moreno Chacon Gregorio",
    "wof:placetype":"venue"
},
  "geometry": {"coordinates":[-4.4276199341,37.4778366089],"type":"Point"}
}