{
  "type": "Feature",
  "properties": {
    "addr:full":"Casal De Veco, 1 Casaldeveco Ourense 32226",
    "addr:housenumber":"1",
    "addr:postcode":"32226",
    "addr:street":"Casal;Veco",
    "iso:country":"ES",
    "sg:address":"Casal De Veco, 1",
    "sg:city":"Casaldeveco",
    "sg:classifiers":[
        {
            "category":"Taxi",
            "type":"Transportation"
        }
    ],
    "sg:phone":"+34 988 47 50 14",
    "sg:postcode":"32226",
    "sg:province":"Ourense",
    "wof:name":"Mendes Ferreira Dasilva Abilio",
    "wof:placetype":"venue"
},
  "geometry": {"coordinates":[-8.1632843018,42.1366500854],"type":"Point"}
}