{
  "type": "Feature",
  "properties": {
    "addr:full":"Calle de Pizarro, 3 Tomelloso Ciudad Real 13700",
    "addr:housenumber":"3",
    "addr:postcode":"13700",
    "addr:street":"Calle De Pizarro",
    "iso:country":"ES",
    "sg:address":"Calle de Pizarro, 3",
    "sg:city":"Tomelloso",
    "sg:orig_category":"Cerrajer\u00cda, Ferrallista",
    "sg:phone":"+34 926 51 47 31",
    "sg:postcode":"13700",
    "sg:province":"Ciudad Real",
    "wof:name":"Medina Navarro S.l.",
    "wof:placetype":"venue"
},
  "geometry": {"coordinates":[-3.0216650963,39.1687889099],"type":"Point"}
}