{
  "type": "Feature",
  "properties": {
    "addr:full":"Calle de Barco, 52 Fuente Victoria Almer\u00eda 04479",
    "addr:housenumber":"52",
    "addr:postcode":"04479",
    "addr:street":"Calle De Barco",
    "iso:country":"ES",
    "sg:address":"Calle de Barco, 52",
    "sg:city":"Fuente Victoria",
    "sg:orig_category":"Productores Recolectores, Venta Directa De Vinos",
    "sg:phone":"+34 950 51 43 64",
    "sg:postcode":"04479",
    "sg:province":"Almer\u00eda",
    "wof:name":"Selecccion De Vinos De Fondon S.l",
    "wof:placetype":"venue"
},
  "geometry": {"coordinates":[-2.9953010082,37.0303382874],"type":"Point"}
}