{
  "type": "Feature",
  "properties": {
    "addr:full":"Carrer de Ramon Berenguer Iv, 4 Cambrils Tarragona 43850",
    "addr:housenumber":"4",
    "addr:postcode":"43850",
    "addr:street":"Carrer De Ramon Berenguer Iv",
    "iso:country":"ES",
    "sg:address":"Carrer de Ramon Berenguer Iv, 4",
    "sg:city":"Cambrils",
    "sg:orig_category":"Abogados",
    "sg:phone":"+34 977 36 85 96",
    "sg:postcode":"43850",
    "sg:province":"Tarragona",
    "wof:name":"Vilaplana Juncosa Laura",
    "wof:placetype":"venue"
},
  "geometry": {"coordinates":[1.0538259745,41.0713233948],"type":"Point"}
}