{
  "type": "Feature",
  "properties": {
    "addr:full":"Calle de Vicente Marco Miranda, 10 Burriana Castell\u00f3n 12530",
    "addr:housenumber":"10",
    "addr:postcode":"12530",
    "addr:street":"Calle De Vicente Marco Miranda",
    "iso:country":"ES",
    "sg:address":"Calle de Vicente Marco Miranda, 10",
    "sg:city":"Burriana",
    "sg:orig_category":"Abogados",
    "sg:phone":"+34 964 51 53 03",
    "sg:postcode":"12530",
    "sg:province":"Castell\u00f3n",
    "wof:name":"Valero Garcia Antonio",
    "wof:placetype":"venue"
},
  "geometry": {"coordinates":[-0.088297002,39.8923301697],"type":"Point"}
}