{
  "type": "Feature",
  "properties": {
    "addr:full":"Calle de Hurtado De Amezaga, 44 Bilbao Vizcaya 48008",
    "addr:housenumber":"44",
    "addr:postcode":"48008",
    "addr:street":"Calle De Hurtado De Amezaga",
    "iso:country":"ES",
    "sg:address":"Calle de Hurtado De Amezaga, 44",
    "sg:city":"Bilbao",
    "sg:orig_category":"Internados & Ense\u00d1anza Privada",
    "sg:phone":"+34 944 22 18 75",
    "sg:postcode":"48008",
    "sg:province":"Vizcaya",
    "wof:name":"Fundacion Obra Social Y Cultural Sope\u00f1a",
    "wof:placetype":"venue"
},
  "geometry": {"coordinates":[-2.9322988987,43.2583198547],"type":"Point"}
}