{
  "type": "Feature",
  "properties": {
    "addr:full":"Plaz Pio V, 3 Bello Teruel 44232",
    "addr:housenumber":"3",
    "addr:postcode":"44232",
    "addr:street":"V",
    "iso:country":"ES",
    "sg:address":"Plaz Pio V, 3",
    "sg:city":"Bello",
    "sg:orig_category":"Agricultura: Abastecimiento Y Cosechado (negocio)",
    "sg:phone":"+34 978 73 41 46",
    "sg:postcode":"44232",
    "sg:province":"Teruel",
    "wof:name":"Simon Bartolo Teresa",
    "wof:placetype":"venue"
},
  "geometry": {"coordinates":[-1.4975420237,40.9239120483],"type":"Point"}
}