{
  "type": "Feature",
  "properties": {
    "addr:full":"Carrer de Miquel Capllonch, 24 Palma Islas Baleares 07010",
    "addr:housenumber":"24",
    "addr:postcode":"07010",
    "addr:street":"Carrer De Miquel Capllonch",
    "iso:country":"ES",
    "sg:address":"Carrer de Miquel Capllonch, 24",
    "sg:city":"Palma",
    "sg:orig_category":"Promotores Constructores",
    "sg:phone":"+34 971 20 30 28",
    "sg:postcode":"07010",
    "sg:province":"Islas Baleares",
    "wof:name":"Gafisan S. A.",
    "wof:placetype":"venue"
},
  "geometry": {"coordinates":[2.6521570683,39.590763092],"type":"Point"}
}