{
  "type": "Feature",
  "properties": {
    "iso:country":"ES",
    "sg:address":"Carr Provincial, 24",
    "sg:city":"Cassa Selva",
    "sg:orig_category":"Concepci\u00d3n Y Realizaci\u00d3n De Maquetas Profesionales Y Prototipos",
    "sg:phone":"+34 972 46 17 56",
    "sg:postcode":"17244",
    "sg:province":"Girona",
    "wof:name":"Pdqarquitectura S.c.",
    "wof:placetype":"venue"
},
  "geometry": {"coordinates":[2.8780760765,41.8896598816],"type":"Point"}
}