{
  "type": "Feature",
  "properties": {
    "iso:country":"ES",
    "sg:address":"Calle de Virgen Del Coro, 3",
    "sg:city":"Madrid",
    "sg:orig_category":"Colchones (fabricaci\u00d3n, Al Por Mayor, Al Por Menor)",
    "sg:phone":"+34 914 04 56 97",
    "sg:postcode":"28027",
    "sg:province":"Madrid",
    "wof:name":"Espada Toledano Valentin",
    "wof:placetype":"venue"
},
  "geometry": {"coordinates":[-3.6582980156,40.433883667],"type":"Point"}
}