{
  "type": "Feature",
  "properties": {
    "addr:full":"Pg Pau Casals (de), 87 Pineda Tarragona 43480",
    "addr:housenumber":"87",
    "addr:postcode":"43480",
    "addr:street":"Pg Pau Casals De",
    "iso:country":"ES",
    "sg:address":"Pg Pau Casals (de), 87",
    "sg:city":"Pineda",
    "sg:orig_category":"Edici\u00d3n De Diarios, Revistas, Boletines",
    "sg:phone":"+34 977 37 00 41",
    "sg:postcode":"43480",
    "sg:province":"Tarragona",
    "wof:name":"Pujals Escoda Jose Maria",
    "wof:placetype":"venue"
},
  "geometry": {"coordinates":[1.1441899538,41.1080245972],"type":"Point"}
}