{
  "type": "Feature",
  "properties": {
    "iso:country":"ES",
    "sg:address":"Po Enamorados, 41",
    "sg:city":"Iru\u00f1a",
    "sg:orig_category":"Contenedores (mercanc\u00cdas)",
    "sg:phone":"+34 948 14 66 47",
    "sg:postcode":"31014",
    "sg:province":"Navarra",
    "wof:name":"Aranzadi Mari\u00f1elarena Javier",
    "wof:placetype":"venue"
},
  "geometry": {"coordinates":[-1.6493531466,42.8251419067],"type":"Point"}
}