{
  "type": "Feature",
  "properties": {
    "iso:country":"ES",
    "sg:address":"Nueve De Mayo",
    "sg:city":"Oviedo",
    "sg:orig_category":"Ropa De Hogar (al Por Menor)",
    "sg:phone":"+34 985 11 89 47",
    "sg:postcode":"33002",
    "sg:province":"Asturias",
    "sg:website":"www.revitex.com",
    "wof:name":"Almacenes Revitex S.l.",
    "wof:placetype":"venue"
},
  "geometry": {"coordinates":[-5.8503770828,43.3656806946],"type":"Point"}
}