{
  "type": "Feature",
  "properties": {
    "iso:country":"ES",
    "sg:address":"Calle de Cristobal Colon, 23",
    "sg:city":"Sanlucar De Barrameda",
    "sg:orig_category":"Ropa Para Se\u00d1oras (al Por Menor)",
    "sg:phone":"+34 956 96 01 18",
    "sg:postcode":"11540",
    "sg:province":"C\u00e1diz",
    "wof:name":"Rodriguez Avila Maria Jose",
    "wof:placetype":"venue"
},
  "geometry": {"coordinates":[-6.3530216217,36.7780723572],"type":"Point"}
}