{
  "type": "Feature",
  "properties": {
    "iso:country":"ES",
    "sg:address":"Calle de Triana, 2",
    "sg:city":"Almonte",
    "sg:orig_category":"Bazares, Art\u00cdculos De Limpieza Y De Cocina (al Por Menor)",
    "sg:phone":"+34 959 45 13 19",
    "sg:postcode":"21730",
    "sg:province":"Huelva",
    "wof:name":"Doulfikar S.l.",
    "wof:placetype":"venue"
},
  "geometry": {"coordinates":[-6.5152411461,37.2604904175],"type":"Point"}
}