{
  "type": "Feature",
  "properties": {
    "iso:country":"ES",
    "sg:address":"Ptge Llubi (particular), 5",
    "sg:city":"Palma",
    "sg:orig_category":"Farmacias",
    "sg:phone":"+34 971 47 63 11",
    "sg:postcode":"07008",
    "sg:province":"Islas Baleares",
    "wof:name":"Coll Solivellas Rafael",
    "wof:placetype":"venue"
},
  "geometry": {"coordinates":[2.676459074,39.5804252625],"type":"Point"}
}