{
  "type": "Feature",
  "properties": {
    "addr:full":"C/ Charles Darwin, 6 Torrellano Alicante 03320",
    "addr:housenumber":"6",
    "addr:postcode":"03320",
    "addr:street":"C / Charles Darwin",
    "iso:country":"ES",
    "sg:address":"C/ Charles Darwin, 6",
    "sg:city":"Torrellano",
    "sg:orig_category":"Centros Empresariales",
    "sg:phone":"+34 965 68 53 54",
    "sg:postcode":"03320",
    "sg:province":"Alicante",
    "wof:name":"Novi Footwear S.l.",
    "wof:placetype":"venue"
},
  "geometry": {"coordinates":[-0.5883839726,38.2929649353],"type":"Point"}
}