{
  "type": "Feature",
  "properties": {
    "iso:country":"ES",
    "sg:address":"G.v. Corts Catalanes, 1056",
    "sg:city":"Barcelona",
    "sg:orig_category":"Zapatos (al Por Menor)",
    "sg:phone":"+34 932 66 05 16",
    "sg:postcode":"08020",
    "sg:province":"Barcelona",
    "wof:name":"Calzados Moya S.l.",
    "wof:placetype":"venue"
},
  "geometry": {"coordinates":[2.2016820908,41.4138183594],"type":"Point"}
}