{
  "type": "Feature",
  "properties": {
    "iso:country":"ES",
    "sg:address":"C/ Creuers, Dels, 16",
    "sg:city":"Manacor",
    "sg:orig_category":"Electrodom\u00c9sticos (al Por Menor)",
    "sg:phone":"+34 971 55 31 97",
    "sg:postcode":"07500",
    "sg:province":"Islas Baleares",
    "wof:name":"Timoner Gomila Miguel",
    "wof:placetype":"venue"
},
  "geometry": {"coordinates":[3.2047450542,39.568649292],"type":"Point"}
}