{
  "type": "Feature",
  "properties": {
    "addr:full":"Beheko Plaza, S/n Lesaka Navarra 31770",
    "addr:housenumber":"s / n",
    "addr:postcode":"31770",
    "addr:street":"Beheko",
    "iso:country":"ES",
    "sg:address":"Beheko Plaza, S/n",
    "sg:city":"Lesaka",
    "sg:classifiers":[
        {
            "category":"Taxi",
            "type":"Transportation"
        }
    ],
    "sg:phone":"+34 948 63 72 35",
    "sg:postcode":"31770",
    "sg:province":"Navarra",
    "wof:name":"Goiecnetxe Telletxea Unai",
    "wof:placetype":"venue"
},
  "geometry": {"coordinates":[-1.7038340569,43.2470741272],"type":"Point"}
}