{
  "type": "Feature",
  "properties": {
    "iso:country":"ES",
    "sg:address":"Pl Sant Francesc, S/n",
    "sg:city":"Valls",
    "sg:orig_category":"Aparcamientos (infraestructuras, Accesorios)",
    "sg:phone":"+34 977 60 93 95",
    "sg:postcode":"43800",
    "sg:province":"Tarragona",
    "wof:name":"Valls Infraestructures Aparcaments I Serveis S.a.",
    "wof:placetype":"venue"
},
  "geometry": {"coordinates":[1.2514920235,41.2837944031],"type":"Point"}
}