{
  "type": "Feature",
  "properties": {
    "addr:full":"Calle de Dos Hermanas, 11 Madrid Madrid 28012",
    "addr:housenumber":"11",
    "addr:postcode":"madrid;28012",
    "addr:street":"Calle De Dos Hermanas",
    "iso:country":"ES",
    "sg:address":"Calle de Dos Hermanas, 11",
    "sg:city":"Madrid",
    "sg:orig_category":"Ropa Para Ni\u00d1os (al Por Menor)",
    "sg:phone":"+34 915 28 36 76",
    "sg:postcode":"28012",
    "sg:province":"Madrid",
    "wof:name":"Linares Alcaide Jose",
    "wof:placetype":"venue"
},
  "geometry": {"coordinates":[-3.7055518627,40.4104194641],"type":"Point"}
}