{
  "type": "Feature",
  "properties": {
    "iso:country":"ES",
    "sg:address":"Carrer de Cadiz, 26",
    "sg:city":"Castelldefels",
    "sg:orig_category":"Estudios, Instalaci\u00d3n De Climatizaci\u00d3n",
    "sg:phone":"+34 936 64 26 66",
    "sg:postcode":"08860",
    "sg:province":"Barcelona",
    "wof:name":"I.e.c. Friaben S.l.",
    "wof:placetype":"venue"
},
  "geometry": {"coordinates":[1.9789340496,41.2738876343],"type":"Point"}
}