{
  "type": "Feature",
  "properties": {
    "iso:country":"ES",
    "sg:address":"Muelle, S/n",
    "sg:city":"Puerto De Vega",
    "sg:classifiers":[
        {
            "category":"Autos & Motor Vehicles",
            "subcategory":"Automobile Sales",
            "type":"Retail Goods"
        }
    ],
    "sg:phone":"+34 985 64 80 38",
    "sg:postcode":"33790",
    "sg:province":"Asturias",
    "wof:name":"Perez Fernandez Manuel",
    "wof:placetype":"venue"
},
  "geometry": {"coordinates":[-6.6460638046,43.5641136169],"type":"Point"}
}