{
  "type": "Feature",
  "properties": {
    "iso:country":"ES",
    "sg:address":"Luga Arme\u00d1ime, 30",
    "sg:city":"Arme\u00d1ime",
    "sg:orig_category":"Florister\u00cdas",
    "sg:phone":"+34 922 74 00 33",
    "sg:postcode":"38678",
    "sg:province":"Santa Cruz De Tenerife",
    "wof:name":"Mederos Cruz Maria Del Carmen",
    "wof:placetype":"venue"
},
  "geometry": {"coordinates":[-16.7524356842,28.1338157654],"type":"Point"}
}