{
  "type": "Feature",
  "properties": {
    "addr:full":"Avda Angeles (los), S/n Loja Granada 18300",
    "addr:housenumber":"loja",
    "addr:postcode":"18300",
    "addr:street":"Avda Angeles Los S / N",
    "iso:country":"ES",
    "sg:address":"Avda Angeles (los), S/n",
    "sg:city":"Loja",
    "sg:orig_category":"Molduras, Junquillos, Listones Y Molduras Perforadas",
    "sg:phone":"+34 958 32 23 15",
    "sg:postcode":"18300",
    "sg:province":"Granada",
    "wof:name":"Cano Fernandez Dolores Maria",
    "wof:placetype":"venue"
},
  "geometry": {"coordinates":[-4.1452388763,37.1644744873],"type":"Point"}
}