{
  "type": "Feature",
  "properties": {
    "addr:full":"Calle de Reyes Catolicos, 43 Manzanares Ciudad Real 13200",
    "addr:housenumber":"43",
    "addr:postcode":"13200",
    "addr:street":"Calle De Reyes Catolicos",
    "iso:country":"ES",
    "sg:address":"Calle de Reyes Catolicos, 43",
    "sg:city":"Manzanares",
    "sg:orig_category":"Agencias Y Agentes Comerciales, Representantes",
    "sg:phone":"+34 926 61 29 66",
    "sg:postcode":"13200",
    "sg:province":"Ciudad Real",
    "wof:name":"Sanchez De La Blanca Ruiz Jesus",
    "wof:placetype":"venue"
},
  "geometry": {"coordinates":[-3.3703188896,38.9991111755],"type":"Point"}
}