{
  "type": "Feature",
  "properties": {
    "iso:country":"ES",
    "sg:address":"Ctra. Cdad. Rodrigo, S/n",
    "sg:city":"Torrejoncillo",
    "sg:orig_category":"Poller\u00cda Y Caza (al Por Menor)",
    "sg:phone":"+34 927 30 33 33",
    "sg:postcode":"10830",
    "sg:province":"C\u00e1ceres",
    "wof:name":"Dominguez Fresno Domiciano",
    "wof:placetype":"venue"
},
  "geometry": {"coordinates":[-6.4705591202,39.8993339539],"type":"Point"}
}