{
  "type": "Feature",
  "properties": {
    "addr:full":"Calle de Iglesia, 17 Campillo Sevilla 41439",
    "addr:housenumber":"17",
    "addr:postcode":"41439",
    "addr:street":"Calle De Iglesia",
    "iso:country":"ES",
    "sg:address":"Calle de Iglesia, 17",
    "sg:city":"Campillo",
    "sg:orig_category":"Estancos",
    "sg:phone":"+34 955 90 74 02",
    "sg:postcode":"41439",
    "sg:province":"Sevilla",
    "wof:name":"Nu\u00f1ez Hans Josefa",
    "wof:placetype":"venue"
},
  "geometry": {"coordinates":[-5.2171831131,37.5445861816],"type":"Point"}
}