{
  "type": "Feature",
  "properties": {
    "iso:country":"ES",
    "sg:address":"Carrer de Gavatxons, 12",
    "sg:city":"Terrassa",
    "sg:orig_category":"Peluquer\u00cdas, Peluquer\u00cda Mixta",
    "sg:phone":"+34 937 33 64 19",
    "sg:postcode":"08221",
    "sg:province":"Barcelona",
    "wof:name":"Perruqueries Ganzo S.l.",
    "wof:placetype":"venue"
},
  "geometry": {"coordinates":[2.0113070011,41.5624427795],"type":"Point"}
}