{
  "type": "Feature",
  "properties": {
    "addr:full":"Calle de Francisco Alonso, 29 Elda Alicante 03600",
    "addr:housenumber":"29",
    "addr:postcode":"03600",
    "addr:street":"Calle De Francisco Alonso",
    "iso:country":"ES",
    "sg:address":"Calle de Francisco Alonso, 29",
    "sg:city":"Elda",
    "sg:orig_category":"Prot\u00c9sicos Dentales",
    "sg:phone":"+34 965 39 16 13",
    "sg:postcode":"03600",
    "sg:province":"Alicante",
    "wof:name":"Ortobennett S L",
    "wof:placetype":"venue"
},
  "geometry": {"coordinates":[-0.7900660038,38.4801368713],"type":"Point"}
}