{
  "type": "Feature",
  "properties": {
    "iso:country":"ES",
    "sg:address":"Carr Cronista Llorens Y Raga, 34",
    "sg:city":"Moncada",
    "sg:orig_category":"Guarder\u00cdas",
    "sg:phone":"+34 961 30 08 73",
    "sg:postcode":"46113",
    "sg:province":"Valencia",
    "wof:name":"Pe\u00f1alver Segovia Maria Alicia",
    "wof:placetype":"venue"
},
  "geometry": {"coordinates":[-0.3985790014,39.5476036072],"type":"Point"}
}