{
  "type": "Feature",
  "properties": {
    "iso:country":"ES",
    "sg:address":"Calle de Encina, 9",
    "sg:city":"Ogijares",
    "sg:orig_category":"Delegados, Agentes De Tr\u00c1nsito, Auxiliares De Transporte Internacional",
    "sg:phone":"+34 958 59 77 36",
    "sg:postcode":"18151",
    "sg:province":"Granada",
    "wof:name":"Transportes Antonio Megias Cayetano S.l.",
    "wof:placetype":"venue"
},
  "geometry": {"coordinates":[-3.6098232269,37.1178588867],"type":"Point"}
}