{
  "type": "Feature",
  "properties": {
    "addr:full":"Calle de Jerusalen, 4 Sevilla Sevilla 41007",
    "addr:housenumber":"4",
    "addr:postcode":"41007",
    "addr:street":"Calle De Jerusalen",
    "iso:country":"ES",
    "sg:address":"Calle de Jerusalen, 4",
    "sg:city":"Sevilla",
    "sg:orig_category":"Iglesia Cat\u00d3lica",
    "sg:phone":"+34 954 25 44 75",
    "sg:postcode":"41007",
    "sg:province":"Sevilla",
    "wof:name":"Parroquia San Juan De Ribera",
    "wof:placetype":"venue"
},
  "geometry": {"coordinates":[-5.9615278244,37.3940734863],"type":"Point"}
}