{
  "type": "Feature",
  "properties": {
    "iso:country":"ES",
    "sg:address":"Calle de Nueva, 14",
    "sg:city":"Carboneras",
    "sg:orig_category":"Bibliotecas, Mediatecas",
    "sg:phone":"+34 950 13 07 75",
    "sg:postcode":"04140",
    "sg:province":"Almer\u00eda",
    "wof:name":"Ayuntamiento De Carboneras",
    "wof:placetype":"venue"
},
  "geometry": {"coordinates":[-1.8950116634,36.9965858459],"type":"Point"}
}