{
  "type": "Feature",
  "properties": {
    "addr:full":"C/ Major, 212 Salt Girona 17190",
    "addr:housenumber":"212",
    "addr:postcode":"17190",
    "addr:street":"C / Major",
    "iso:country":"ES",
    "sg:address":"C/ Major, 212",
    "sg:city":"Salt",
    "sg:orig_category":"Servicios De Telecomunicaciones",
    "sg:phone":"+34 972 24 06 50",
    "sg:postcode":"17190",
    "sg:province":"Girona",
    "wof:name":"Gironasoft S.l.",
    "wof:placetype":"venue"
},
  "geometry": {"coordinates":[2.7907280922,41.9749107361],"type":"Point"}
}