{
  "type": "Feature",
  "properties": {
    "addr:full":"Ctra Almunia (de La), 10 Cari\u00f1ena Zaragoza 50400",
    "addr:housenumber":"10",
    "addr:postcode":"50400",
    "addr:street":"Ctra Almunia De La",
    "iso:country":"ES",
    "sg:address":"Ctra Almunia (de La), 10",
    "sg:city":"Cari\u00f1ena",
    "sg:orig_category":"Vinos (agentes)",
    "sg:phone":"+34 976 62 07 02",
    "sg:postcode":"50400",
    "sg:province":"Zaragoza",
    "wof:name":"Xucrogas S.a.",
    "wof:placetype":"venue"
},
  "geometry": {"coordinates":[-1.2269200087,41.3425064087],"type":"Point"}
}