{
  "type": "Feature",
  "properties": {
    "addr:full":"Avda Madrid, 18 Lora Rio Sevilla 41440",
    "addr:housenumber":"18",
    "addr:postcode":"41440",
    "addr:street":"Avda Madrid;Rio Sevilla",
    "iso:country":"ES",
    "sg:address":"Avda Madrid, 18",
    "sg:city":"Lora Rio",
    "sg:orig_category":"Art\u00cdculos Funerarios (al Por Menor)",
    "sg:phone":"+34 955 80 05 33",
    "sg:postcode":"41440",
    "sg:province":"Sevilla",
    "wof:name":"Servicios Especiales S.a.",
    "wof:placetype":"venue"
},
  "geometry": {"coordinates":[-5.529624939,37.660533905],"type":"Point"}
}