{
  "type": "Feature",
  "properties": {
    "addr:full":"Calle de Reina Victoria, 21 Parla Madrid 28980",
    "addr:housenumber":"21",
    "addr:postcode":"28980",
    "addr:street":"Calle De Reina Victoria",
    "iso:country":"ES",
    "sg:address":"Calle de Reina Victoria, 21",
    "sg:city":"Parla",
    "sg:orig_category":"Producci\u00d3n, Distribuci\u00d3n De Electricidad",
    "sg:phone":"+34 916 99 80 77",
    "sg:postcode":"28980",
    "sg:province":"Madrid",
    "wof:name":"Torre Naranjo Pedro De La",
    "wof:placetype":"venue"
},
  "geometry": {"coordinates":[-3.7703061104,40.2339706421],"type":"Point"}
}