{
  "type": "Feature",
  "properties": {
    "addr:full":"Psaj Doctor Bartual Moret, S/n Valencia Valencia 46010",
    "addr:housenumber":"s / n",
    "addr:postcode":"46010",
    "addr:street":"Doctor Bartual Moret",
    "iso:country":"ES",
    "sg:address":"Psaj Doctor Bartual Moret, S/n",
    "sg:city":"Valencia",
    "sg:orig_category":"Universidades",
    "sg:phone":"+34 963 69 60 83",
    "sg:postcode":"46010",
    "sg:province":"Valencia",
    "sg:website":"www.estudiesabroad.com",
    "wof:name":"E.l.e. Asesores Linguisticos S.l.",
    "wof:placetype":"venue"
},
  "geometry": {"coordinates":[-0.3568690121,39.4775657654],"type":"Point"}
}