{
  "type": "Feature",
  "properties": {
    "iso:country":"ES",
    "sg:address":"Calle de Manuel De Leon Falcon, 12",
    "sg:city":"Palmas De Gran Canaria",
    "sg:orig_category":"M\u00c9dicos: Oftalmolog\u00cda",
    "sg:phone":"+34 928 26 01 14",
    "sg:postcode":"35011",
    "sg:province":"Las Palmas",
    "wof:name":"Lopez Gracia Matias",
    "wof:placetype":"venue"
},
  "geometry": {"coordinates":[-15.4366588593,28.1252479553],"type":"Point"}
}