{
  "type": "Feature",
  "properties": {
    "iso:country":"ES",
    "sg:address":"Calle de Granada, 190",
    "sg:city":"Almeria",
    "sg:orig_category":"Telas Y Sedas (al Por Menor)",
    "sg:phone":"+34 950 26 73 27",
    "sg:postcode":"04008",
    "sg:province":"Almer\u00eda",
    "wof:name":"Godoy Godoy Francisco",
    "wof:placetype":"venue"
},
  "geometry": {"coordinates":[-2.4571828842,36.847694397],"type":"Point"}
}