{
  "type": "Feature",
  "properties": {
    "addr:full":"Calle de Betsaida, 4 Malaga M\u00e1laga 29006",
    "addr:housenumber":"4",
    "addr:postcode":"29006",
    "addr:street":"Calle De Betsaida;Ma\u0301Laga",
    "iso:country":"ES",
    "sg:address":"Calle de Betsaida, 4",
    "sg:city":"Malaga",
    "sg:orig_category":"Papeler\u00cdas, Librer\u00cdas",
    "sg:phone":"+34 952 32 46 19",
    "sg:postcode":"29006",
    "sg:province":"M\u00e1laga",
    "wof:name":"Macias Ruiz Socorro",
    "wof:placetype":"venue"
},
  "geometry": {"coordinates":[-4.439139843,36.7129211426],"type":"Point"}
}