{
  "type": "Feature",
  "properties": {
    "iso:country":"ES",
    "sg:address":"Avda De Bara\u00f1ain, 13",
    "sg:city":"Iru\u00f1a",
    "sg:orig_category":"Arquitectos",
    "sg:phone":"+34 948 25 81 44",
    "sg:postcode":"31008",
    "sg:province":"Navarra",
    "wof:name":"Alonso Del Val Miguel Angel",
    "wof:placetype":"venue"
},
  "geometry": {"coordinates":[-1.6581888199,42.812877655],"type":"Point"}
}