{
  "type": "Feature",
  "properties": {
    "addr:full":"Calle de Comunidad De Madrid, S/n Rozas De Madrid Madrid 28230",
    "addr:housenumber":"s",
    "addr:postcode":"28230",
    "addr:street":"Calle De Comunidad;Madrid;/ N Rozas",
    "iso:country":"ES",
    "sg:address":"Calle de Comunidad De Madrid, S/n",
    "sg:city":"Rozas De Madrid",
    "sg:orig_category":"Institutos De Belleza",
    "sg:phone":"+34 916 37 24 40",
    "sg:postcode":"28230",
    "sg:province":"Madrid",
    "wof:name":"Carrasco Mosquera S.l.",
    "wof:placetype":"venue"
},
  "geometry": {"coordinates":[-3.8762562275,40.4902877808],"type":"Point"}
}