{
  "type": "Feature",
  "properties": {
    "addr:full":"Av Los Tilos, 6 Villatuerta Navarra 31132",
    "addr:housenumber":"6",
    "addr:postcode":"31132",
    "addr:street":"Av Los Tilos",
    "iso:country":"ES",
    "sg:address":"Av Los Tilos, 6",
    "sg:city":"Villatuerta",
    "sg:orig_category":"Bebidas",
    "sg:phone":"+34 948 54 13 66",
    "sg:postcode":"31132",
    "sg:province":"Navarra",
    "wof:name":"Distribuciones Zaldu S.l.",
    "wof:placetype":"venue"
},
  "geometry": {"coordinates":[-1.9989290237,42.6569252014],"type":"Point"}
}