{
  "type": "Feature",
  "properties": {
    "addr:full":"Ezkaba, 38 Iru\u00f1a Navarra 31015",
    "addr:housenumber":"38",
    "addr:postcode":"31015",
    "addr:street":"Ezkaba",
    "iso:country":"ES",
    "sg:address":"Ezkaba, 38",
    "sg:city":"Iru\u00f1a",
    "sg:orig_category":"Empresas De Limpieza",
    "sg:phone":"+34 948 12 01 85",
    "sg:postcode":"31015",
    "sg:province":"Navarra",
    "wof:name":"De La Parte Lopez Jesus",
    "wof:placetype":"venue"
},
  "geometry": {"coordinates":[-1.6263539791,42.8298301697],"type":"Point"}
}