{
  "type": "Feature",
  "properties": {
    "addr:full":"Calle de Baile (el), 5 Madrigal Altas Torres \u00c1vila 05220",
    "addr:housenumber":"5",
    "addr:postcode":"05220",
    "addr:street":"Calle De Baile El;A\u0301Vila",
    "iso:country":"ES",
    "sg:address":"Calle de Baile (el), 5",
    "sg:city":"Madrigal Altas Torres",
    "sg:orig_category":"Cajas Para Embalar",
    "sg:phone":"+34 920 32 01 57",
    "sg:postcode":"05220",
    "sg:province":"\u00c1vila",
    "sg:website":"www.ruralvia.com",
    "wof:name":"Caja Rural Del Duero",
    "wof:placetype":"venue"
},
  "geometry": {"coordinates":[-4.9986028671,41.0890808105],"type":"Point"}
}