{
  "type": "Feature",
  "properties": {
    "iso:country":"ES",
    "sg:address":"Poli Tejerias Calle de Rifondo, 6",
    "sg:city":"Calahorra",
    "sg:orig_category":"Suministros Y Materiales Industriales",
    "sg:phone":"+34 941 14 66 46",
    "sg:postcode":"26500",
    "sg:province":"La Rioja",
    "wof:name":"Electro Stocks La Rioja S.a.",
    "wof:placetype":"venue"
},
  "geometry": {"coordinates":[-1.9620640278,42.3058395386],"type":"Point"}
}