{
  "type": "Feature",
  "properties": {
    "addr:full":"Martinet (pol Ind Casanova Baix), 13 Ripoll Girona 17500",
    "addr:housenumber":"13",
    "addr:postcode":"17500",
    "addr:street":"Baix",
    "iso:country":"ES",
    "sg:address":"Martinet (pol Ind Casanova Baix), 13",
    "sg:city":"Ripoll",
    "sg:orig_category":"Promotores Constructores",
    "sg:phone":"+34 972 70 42 38",
    "sg:postcode":"17500",
    "sg:province":"Girona",
    "wof:name":"Construccions Paez I Costa S.l.",
    "wof:placetype":"venue"
},
  "geometry": {"coordinates":[2.1694149971,42.2192497253],"type":"Point"}
}