{
  "type": "Feature",
  "properties": {
    "iso:country":"ES",
    "sg:address":"Avda Galtzaraborda, 34",
    "sg:city":"Errenteria",
    "sg:orig_category":"Carnicer\u00cdas, Carnicer\u00cdas",
    "sg:phone":"+34 943 51 10 39",
    "sg:postcode":"20100",
    "sg:province":"Guip\u00f9zcoa",
    "wof:name":"Irizar Murua Daniel",
    "wof:placetype":"venue"
},
  "geometry": {"coordinates":[-1.9061658382,43.3115158081],"type":"Point"}
}