{
  "type": "Feature",
  "properties": {
    "iso:country":"ES",
    "sg:address":"Av Torrent Gornal, S/n",
    "sg:city":"Hospitalet Llobregat",
    "sg:orig_category":"Carnicer\u00cdas, Carnicer\u00cdas",
    "sg:phone":"+34 933 33 96 43",
    "sg:postcode":"08904",
    "sg:province":"Barcelona",
    "wof:name":"Sarda\u00f1es Segarra Juan",
    "wof:placetype":"venue"
},
  "geometry": {"coordinates":[2.111784935,41.3740348816],"type":"Point"}
}