{
  "type": "Feature",
  "properties": {
    "iso:country":"ES",
    "sg:address":"Calle de Alfonso Xii, 20",
    "sg:city":"Madrid",
    "sg:orig_category":"Administradores De Bienes Y Delegados De Comunidades De Propietarios",
    "sg:phone":"+34 915 23 82 30",
    "sg:postcode":"28014",
    "sg:province":"Madrid",
    "wof:name":"Bekibros S.l.",
    "wof:placetype":"venue"
},
  "geometry": {"coordinates":[-3.6890802383,40.4168128967],"type":"Point"}
}