{
  "type": "Feature",
  "properties": {
    "addr:full":"Praz Maior, S/n Neves Pontevedra 36440",
    "addr:housenumber":"s / n",
    "addr:postcode":"36440",
    "addr:street":"Praz Maior",
    "iso:country":"ES",
    "sg:address":"Praz Maior, S/n",
    "sg:city":"Neves",
    "sg:orig_category":"Iglesia Cat\u00d3lica",
    "sg:phone":"+34 986 64 81 64",
    "sg:postcode":"36440",
    "sg:province":"Pontevedra",
    "wof:name":"Janeiro Lopez Manuel",
    "wof:placetype":"venue"
},
  "geometry": {"coordinates":[-8.411822319,42.0887565613],"type":"Point"}
}