{
  "type": "Feature",
  "properties": {
    "addr:full":"Ctra Alcorcon-plasencia, S/n Casavieja \u00c1vila 05450",
    "addr:housenumber":"s",
    "addr:postcode":"05450",
    "addr:street":"Ctra Alcorcon-Plasencia;/ N Casavieja A\u0301Vila",
    "iso:country":"ES",
    "sg:address":"Ctra Alcorcon-plasencia, S/n",
    "sg:city":"Casavieja",
    "sg:orig_category":"Molduras, Junquillos, Listones Y Molduras Perforadas",
    "sg:phone":"+34 918 67 80 38",
    "sg:postcode":"05450",
    "sg:province":"\u00c1vila",
    "wof:name":"Cuerva Gonzalez Maria Dolores",
    "wof:placetype":"venue"
},
  "geometry": {"coordinates":[-4.7661142349,40.2842102051],"type":"Point"}
}