{
  "type": "Feature",
  "properties": {
    "iso:country":"ES",
    "sg:address":"Av Constitucio, 1",
    "sg:city":"Ciutadella Menorca",
    "sg:orig_category":"Agencias De Viajes",
    "sg:phone":"+34 971 38 36 30",
    "sg:postcode":"07760",
    "sg:province":"Islas Baleares",
    "wof:name":"Thalassa Vacaciones S.a.",
    "wof:placetype":"venue"
},
  "geometry": {"coordinates":[3.8409700394,40.0027885437],"type":"Point"}
}