{
  "type": "Feature",
  "properties": {
    "iso:country":"ES",
    "sg:address":"Plaz Virgen (la), 1",
    "sg:city":"Lezuza",
    "sg:orig_category":"Iglesia Cat\u00d3lica",
    "sg:phone":"+34 967 35 40 22",
    "sg:postcode":"02160",
    "sg:province":"Albacete",
    "wof:name":"Parroquia Nuestra Se?ora De La Asuncion",
    "wof:placetype":"venue"
},
  "geometry": {"coordinates":[-2.3325669765,38.9598464966],"type":"Point"}
}