{
  "type": "Feature",
  "properties": {
    "addr:full":"Calle de Eria Del Hospital, 19 Pola De Siero Asturias 33510",
    "addr:housenumber":"19",
    "addr:postcode":"33510",
    "addr:street":"Calle De Eria Del Hospital",
    "iso:country":"ES",
    "sg:address":"Calle de Eria Del Hospital, 19",
    "sg:city":"Pola De Siero",
    "sg:orig_category":"Cl\u00cdnicas M\u00c9dicas",
    "sg:phone":"+34 985 72 64 81",
    "sg:postcode":"33510",
    "sg:province":"Asturias",
    "wof:name":"Mediasalud Siero S.l.",
    "wof:placetype":"venue"
},
  "geometry": {"coordinates":[-5.6607718468,43.3928604126],"type":"Point"}
}