{
  "type": "Feature",
  "properties": {
    "iso:country":"ES",
    "sg:address":"Calle de Ramon Y Cajal, 6",
    "sg:city":"Donostia-san Sebastian",
    "sg:orig_category":"Locales Y Clases De Danza",
    "sg:phone":"+34 943 27 93 98",
    "sg:postcode":"20002",
    "sg:province":"Guip\u00f9zcoa",
    "wof:name":"Iradier Jorge Maria De La Concepcion",
    "wof:placetype":"venue"
},
  "geometry": {"coordinates":[-1.9759119749,43.324344635],"type":"Point"}
}