{
  "type": "Feature",
  "properties": {
    "iso:country":"ES",
    "sg:address":"Calle de Obispo Perez Caceres, 26",
    "sg:city":"Candelaria",
    "sg:orig_category":"Bazares, Art\u00cdculos De Limpieza Y De Cocina (al Por Menor)",
    "sg:phone":"+34 922 50 48 66",
    "sg:postcode":"38530",
    "sg:province":"Santa Cruz De Tenerife",
    "wof:name":"Hernandez Diaz Claudio Francisco",
    "wof:placetype":"venue"
},
  "geometry": {"coordinates":[-16.3698673248,28.3532371521],"type":"Point"}
}