{
  "type": "Feature",
  "properties": {
    "addr:full":"Calle de Cardenal Cisneros, 67 Madrid Madrid 28010",
    "addr:housenumber":"67",
    "addr:postcode":"madrid;28010",
    "addr:street":"Calle De Cardenal Cisneros",
    "iso:country":"ES",
    "sg:address":"Calle de Cardenal Cisneros, 67",
    "sg:city":"Madrid",
    "sg:orig_category":"Agencias De Viajes",
    "sg:phone":"+34 915 91 97 97",
    "sg:postcode":"28010",
    "sg:province":"Madrid",
    "sg:website":"www.explora-accion.com",
    "wof:name":"Exploracion Viajes Y Aventura S.l.",
    "wof:placetype":"venue"
},
  "geometry": {"coordinates":[-3.7029156685,40.434513092],"type":"Point"}
}