{
  "type": "Feature",
  "properties": {
    "addr:full":"Zapateria, 10 Estella Navarra 31200",
    "addr:housenumber":"10",
    "addr:postcode":"31200",
    "iso:country":"ES",
    "sg:address":"Zapateria, 10",
    "sg:city":"Estella",
    "sg:orig_category":"Postigos, Persianas Y Celos\u00cdas",
    "sg:phone":"+34 948 55 37 05",
    "sg:postcode":"31200",
    "sg:province":"Navarra",
    "wof:name":"Persianas Chasco-antia",
    "wof:placetype":"venue"
},
  "geometry": {"coordinates":[-2.029088974,42.6707344055],"type":"Point"}
}