{
  "type": "Feature",
  "properties": {
    "addr:full":"Carrer de Villa, 10 S. Cugat Valles Barcelona 08172",
    "addr:housenumber":"10",
    "addr:postcode":"08172",
    "addr:street":"Carrer De Villa;Barcelona",
    "iso:country":"ES",
    "sg:address":"Carrer de Villa, 10",
    "sg:city":"S. Cugat Valles",
    "sg:orig_category":"Asesor\u00cda Sobre Comunicaci\u00d3n De Empresas",
    "sg:phone":"+34 936 74 87 76",
    "sg:postcode":"08172",
    "sg:province":"Barcelona",
    "wof:name":"Plataforma Abierta S.l.",
    "wof:placetype":"venue"
},
  "geometry": {"coordinates":[2.0794320107,41.468044281],"type":"Point"}
}