{
  "type": "Feature",
  "properties": {
    "iso:country":"ES",
    "sg:address":"Rua Pardo Bazan, 13",
    "sg:city":"Burela",
    "sg:orig_category":"Asesor\u00cda Sobre Comunicaci\u00d3n De Empresas",
    "sg:phone":"+34 982 58 14 90",
    "sg:postcode":"27880",
    "sg:province":"Lugo",
    "wof:name":"Asoremsa Mari\u00d1a S.l.",
    "wof:placetype":"venue"
},
  "geometry": {"coordinates":[-7.3607783318,43.6622161865],"type":"Point"}
}