{
  "type": "Feature",
  "properties": {
    "addr:full":"Carrer de Ramon Turro, 109 Barcelona Barcelona 08005",
    "addr:housenumber":"109",
    "addr:postcode":"08005",
    "addr:street":"Carrer De Ramon Turro",
    "iso:country":"ES",
    "sg:address":"Carrer de Ramon Turro, 109",
    "sg:city":"Barcelona",
    "sg:orig_category":"Zapatos: Material, Suministros, Accesorios (fabricaci\u00d3n, Al Por Mayor)",
    "sg:phone":"+34 933 00 24 24",
    "sg:postcode":"08005",
    "sg:province":"Barcelona",
    "sg:website":"www.texon.com",
    "wof:name":"Texon Materiales S. L.",
    "wof:placetype":"venue"
},
  "geometry": {"coordinates":[2.1969180107,41.3955764771],"type":"Point"}
}