{
  "type": "Feature",
  "properties": {
    "addr:full":"Calle de Julian Caba\u00d1as, 9 Villabragima Valladolid 47820",
    "addr:housenumber":"9",
    "addr:postcode":"47820",
    "addr:street":"Calle De Julian Caban\u0303As",
    "iso:country":"ES",
    "sg:address":"Calle de Julian Caba\u00d1as, 9",
    "sg:city":"Villabragima",
    "sg:orig_category":"Agentes Generales De Seguros",
    "sg:phone":"+34 983 71 43 35",
    "sg:postcode":"47820",
    "sg:province":"Valladolid",
    "wof:name":"Pelaz Gento Maria Antonia",
    "wof:placetype":"venue"
},
  "geometry": {"coordinates":[-5.1146807671,41.8214607239],"type":"Point"}
}