{
  "type": "Feature",
  "properties": {
    "iso:country":"ES",
    "sg:address":"Carrer de Comte Borrell, 179",
    "sg:city":"Barcelona",
    "sg:orig_category":"Electricidad: Equipos Industriales, Componentes (fabricaci\u00d3n)",
    "sg:phone":"+34 932 26 38 45",
    "sg:postcode":"08015",
    "sg:province":"Barcelona",
    "wof:name":"Finder Electrica S.l.u.",
    "wof:placetype":"venue"
},
  "geometry": {"coordinates":[2.1536331177,41.3839950562],"type":"Point"}
}