{
  "type": "Feature",
  "properties": {
    "iso:country":"ES",
    "sg:address":"Rua Carballeira De San Lourenzo (da), S/n",
    "sg:city":"Santiago De Compostela",
    "sg:orig_category":"Cl\u00cdnicas Psiqui\u00c1tricas",
    "sg:phone":"+34 981 57 06 27",
    "sg:postcode":"15705",
    "sg:province":"La Coru\u00f1a",
    "wof:name":"Carrero Fernandez Narciso",
    "wof:placetype":"venue"
},
  "geometry": {"coordinates":[-8.5564813614,42.8809967041],"type":"Point"}
}