{
  "type": "Feature",
  "properties": {
    "iso:country":"ES",
    "sg:address":"Calle de Tetuan, 5",
    "sg:city":"Almu\u00f1ecar",
    "sg:orig_category":"Empresas De Limpieza",
    "sg:phone":"+34 958 63 36 50",
    "sg:postcode":"18690",
    "sg:province":"Granada",
    "wof:name":"Limpiezas Geronimo S.l.",
    "wof:placetype":"venue"
},
  "geometry": {"coordinates":[-3.6873540878,36.7349433899],"type":"Point"}
}