{
  "type": "Feature",
  "properties": {
    "addr:full":"Ctra. La Horra, Km. 0003,8 Roa Burgos 09300",
    "addr:postcode":"09300",
    "addr:street":"Ctra. La Horra Km. 0003,8",
    "iso:country":"ES",
    "sg:address":"Ctra. La Horra, Km. 0003,8",
    "sg:city":"Roa",
    "sg:orig_category":"Productores Recolectores, Venta Directa De Vinos",
    "sg:phone":"+34 947 56 11 45",
    "sg:postcode":"09300",
    "sg:province":"Burgos",
    "wof:name":"Duron S.a.",
    "wof:placetype":"venue"
},
  "geometry": {"coordinates":[-3.9295990467,41.6983032227],"type":"Point"}
}