{
  "type": "Feature",
  "properties": {
    "addr:full":"Carrer de Furs (dels), 11 Denia Alicante 03700",
    "addr:housenumber":"11",
    "addr:postcode":"03700",
    "addr:street":"Carrer De Furs Dels",
    "iso:country":"ES",
    "sg:address":"Carrer de Furs (dels), 11",
    "sg:city":"Denia",
    "sg:orig_category":"Asesor\u00cda Fiscal Y Jur\u00cddica",
    "sg:phone":"+34 966 43 18 76",
    "sg:postcode":"03700",
    "sg:province":"Alicante",
    "wof:name":"Eme D 2000 S.l.",
    "wof:placetype":"venue"
},
  "geometry": {"coordinates":[0.1025130004,38.8448905945],"type":"Point"}
}