{
  "type": "Feature",
  "properties": {
    "iso:country":"ES",
    "sg:address":"Calle de Juan Miranda, 1",
    "sg:city":"Guadalajara",
    "sg:orig_category":"Ropa Para Beb\u00c9s Y Ni\u00d1os (confecci\u00d3n, Al Por Mayor)",
    "sg:phone":"+34 949 22 29 36",
    "sg:postcode":"19001",
    "sg:province":"Guadalajara",
    "wof:name":"Viajes Andarin Sl",
    "wof:placetype":"venue"
},
  "geometry": {"coordinates":[-3.1649250984,40.6315002441],"type":"Point"}
}