{
  "type": "Feature",
  "properties": {
    "iso:country":"ES",
    "sg:address":"Avda Playas (las), 39",
    "sg:city":"Puerto Del Carmen",
    "sg:orig_category":"Pizzer\u00cdas",
    "sg:phone":"+34 928 51 07 25",
    "sg:postcode":"35510",
    "sg:province":"Las Palmas",
    "wof:name":"Garcia Martin Antonio",
    "wof:placetype":"venue"
},
  "geometry": {"coordinates":[-13.6550951004,28.9199447632],"type":"Point"}
}