{
  "type": "Feature",
  "properties": {
    "iso:country":"ES",
    "sg:address":"Pl S. Francisco De Asis, 10",
    "sg:city":"Estella",
    "sg:orig_category":"Inmobiliaria (agencias)",
    "sg:phone":"+34 948 55 39 49",
    "sg:postcode":"31200",
    "sg:province":"Navarra",
    "wof:name":"Ardanche S.l.",
    "wof:placetype":"venue"
},
  "geometry": {"coordinates":[-2.0299272537,42.6706314087],"type":"Point"}
}