{
  "type": "Feature",
  "properties": {
    "iso:country":"ES",
    "sg:address":"Calle de Jerez, 7",
    "sg:city":"Madrid",
    "sg:orig_category":"Inversiones",
    "sg:phone":"+34 913 50 05 19",
    "sg:postcode":"28016",
    "sg:province":"Madrid",
    "wof:name":"Pries Y Bertran Adolfo",
    "wof:placetype":"venue"
},
  "geometry": {"coordinates":[-3.6768651009,40.4642181396],"type":"Point"}
}