{
  "type": "Feature",
  "properties": {
    "iso:country":"ES",
    "sg:address":"Avda Gonzalez Mayo, 4",
    "sg:city":"Tineo",
    "sg:orig_category":"Zapatos (al Por Menor)",
    "sg:phone":"+34 985 80 04 14",
    "sg:postcode":"33870",
    "sg:province":"Asturias",
    "wof:name":"Fernandez Garcia Iciar",
    "wof:placetype":"venue"
},
  "geometry": {"coordinates":[-6.4165782928,43.3346939087],"type":"Point"}
}