{
  "type": "Feature",
  "properties": {
    "addr:full":"Carretera De Nerpio, Km. 0039,8 Letur Albacete 02434",
    "addr:postcode":"02434",
    "addr:street":"Carretera De Nerpio Km. 0039,8",
    "iso:country":"ES",
    "sg:address":"Carretera De Nerpio, Km. 0039,8",
    "sg:city":"Letur",
    "sg:orig_category":"Distribuci\u00d3n De Petr\u00d3leo Y Derivados",
    "sg:phone":"+34 967 42 61 95",
    "sg:postcode":"02434",
    "sg:province":"Albacete",
    "wof:name":"Estacion De Servicio Sierra Del Segura S.l.",
    "wof:placetype":"venue"
},
  "geometry": {"coordinates":[-2.1644289494,38.3347587585],"type":"Point"}
}