{
  "type": "Feature",
  "properties": {
    "addr:full":"Pl Revolucio De Setembre 1868, S/n Barcelona Barcelona 08012",
    "addr:housenumber":"1868 s / n",
    "addr:postcode":"08012",
    "addr:street":"Pl Revolucio De Setembre",
    "iso:country":"ES",
    "sg:address":"Pl Revolucio De Setembre 1868, S/n",
    "sg:city":"Barcelona",
    "sg:orig_category":"Aparcamientos (infraestructuras, Accesorios)",
    "sg:phone":"+34 932 85 13 74",
    "sg:postcode":"08012",
    "sg:province":"Barcelona",
    "wof:name":"Claret Uno S.l.",
    "wof:placetype":"venue"
},
  "geometry": {"coordinates":[2.1580250263,41.4026031494],"type":"Point"}
}