{
  "type": "Feature",
  "properties": {
    "iso:country":"ES",
    "sg:address":"Calle de Arquitecto Morell, 6",
    "sg:city":"Alacant",
    "sg:orig_category":"Sociedades, Compa\u00d1\u00cdas Aseguradoras",
    "sg:phone":"+34 965 12 15 88",
    "sg:postcode":"03003",
    "sg:province":"Alicante",
    "wof:name":"Prevision Sanitaria Nacional-mutua De Seguros Y Reaseguros",
    "wof:placetype":"venue"
},
  "geometry": {"coordinates":[-0.4920755029,38.3422737122],"type":"Point"}
}