{
  "type": "Feature",
  "properties": {
    "addr:full":"Avda Txori Erri, 46 Basozabal Vizcaya 48150",
    "addr:housenumber":"46",
    "addr:postcode":"48150",
    "addr:street":"Avda Txori Erri",
    "iso:country":"ES",
    "sg:address":"Avda Txori Erri, 46",
    "sg:city":"Basozabal",
    "sg:orig_category":"Ingenier\u00cda, Centros De Estudios (diversos)",
    "sg:phone":"+34 944 71 11 66",
    "sg:postcode":"48150",
    "sg:province":"Vizcaya",
    "sg:website":"www.sika.es",
    "wof:name":"Sika S.a.",
    "wof:placetype":"venue"
},
  "geometry": {"coordinates":[-2.9210519791,43.2983283997],"type":"Point"}
}