{
  "type": "Feature",
  "properties": {
    "iso:country":"ES",
    "sg:address":"Pietat, 4",
    "sg:city":"Bossost",
    "sg:orig_category":"Peluquer\u00cdas, Peluquer\u00cda Mixta",
    "sg:phone":"+34 973 64 81 45",
    "sg:postcode":"25550",
    "sg:province":"Lleida",
    "wof:name":"Antonio Casals Ribes Y Gloria Saez Sanjuan C.b.",
    "wof:placetype":"venue"
},
  "geometry": {"coordinates":[0.6915392876,42.7787971497],"type":"Point"}
}