{
  "type": "Feature",
  "properties": {
    "addr:full":"Carr Templers, 8 Lleida Lleida 25002",
    "addr:housenumber":"8",
    "addr:postcode":"25002",
    "addr:street":"Carr Templers",
    "iso:country":"ES",
    "sg:address":"Carr Templers, 8",
    "sg:city":"Lleida",
    "sg:orig_category":"M\u00c1quinas De Escribir, M\u00c1quinas De Oficina (al Por Menor, Reparaci\u00d3n)",
    "sg:phone":"+34 973 26 16 15",
    "sg:postcode":"25002",
    "sg:province":"Lleida",
    "wof:name":"Liebana Carpio Luciano",
    "wof:placetype":"venue"
},
  "geometry": {"coordinates":[0.6170579791,41.6108551025],"type":"Point"}
}