{
  "type": "Feature",
  "properties": {
    "addr:full":"Calle de Lago Titicaca, 3 Madrid Madrid 28032",
    "addr:housenumber":"3",
    "addr:postcode":"28032",
    "addr:street":"Calle De Lago Titicaca",
    "iso:country":"ES",
    "sg:address":"Calle de Lago Titicaca, 3",
    "sg:city":"Madrid",
    "sg:orig_category":"Enfermeras: Consultas, Atenci\u00d3n A Domicilio",
    "sg:phone":"+34 917 76 35 61",
    "sg:postcode":"28032",
    "sg:province":"Madrid",
    "wof:name":"Dones Camino Jose",
    "wof:placetype":"venue"
},
  "geometry": {"coordinates":[-3.6080799103,40.4026489258],"type":"Point"}
}