{
  "type": "Feature",
  "properties": {
    "addr:full":"Calle de Santa Clara, 5 Zafra Badajoz 06300",
    "addr:housenumber":"5",
    "addr:postcode":"06300",
    "addr:street":"Calle De Santa Clara",
    "iso:country":"ES",
    "sg:address":"Calle de Santa Clara, 5",
    "sg:city":"Zafra",
    "sg:orig_category":"Fabricaci\u00d3n De Juguetes Autom\u00c1ticos",
    "sg:phone":"+34 924 55 54 52",
    "sg:postcode":"06300",
    "sg:province":"Badajoz",
    "wof:name":"Automaticos Ceca S.l.",
    "wof:placetype":"venue"
},
  "geometry": {"coordinates":[-6.4165239334,38.4269142151],"type":"Point"}
}