{
  "type": "Feature",
  "properties": {
    "addr:full":"Calle de Luis Vives, 7 Valencia Valencia 46003",
    "addr:housenumber":"7",
    "addr:postcode":"46003",
    "addr:street":"Calle De Luis Vives",
    "iso:country":"ES",
    "sg:address":"Calle de Luis Vives, 7",
    "sg:city":"Valencia",
    "sg:orig_category":"Asociaciones Y Clubs Deportivos",
    "sg:phone":"+34 963 52 61 83",
    "sg:postcode":"46003",
    "sg:province":"Valencia",
    "wof:name":"Ripoll Carbonell Jose",
    "wof:placetype":"venue"
},
  "geometry": {"coordinates":[-0.3748190105,39.4736404419],"type":"Point"}
}