{
  "type": "Feature",
  "properties": {
    "iso:country":"ES",
    "sg:address":"Calle de Bernardo Juan, 19",
    "sg:city":"Yatova",
    "sg:orig_category":"Empresarios",
    "sg:phone":"+34 962 51 61 56",
    "sg:postcode":"46367",
    "sg:province":"Valencia",
    "wof:name":"Lujan Corbera Francisco",
    "wof:placetype":"venue"
},
  "geometry": {"coordinates":[-0.8069213033,39.3855705261],"type":"Point"}
}