{
  "type": "Feature",
  "properties": {
    "iso:country":"ES",
    "sg:address":"Calle de Alberche, 14",
    "sg:city":"Madrid",
    "sg:orig_category":"Sociedades, Compa\u00d1\u00cdas Aseguradoras",
    "sg:phone":"+34 915 01 96 42",
    "sg:postcode":"28007",
    "sg:province":"Madrid",
    "wof:name":"Intermediarios De Seguros S.l.",
    "wof:placetype":"venue"
},
  "geometry": {"coordinates":[-3.6769618988,40.4014930725],"type":"Point"}
}