{
  "type": "Feature",
  "properties": {
    "addr:full":"Ctra. Portugal, Km. 0031,0 Notaria Ourense 32236",
    "addr:postcode":"32236",
    "addr:street":"Ctra. Portugal Km. 0031,0",
    "iso:country":"ES",
    "sg:address":"Ctra. Portugal, Km. 0031,0",
    "sg:city":"Notaria",
    "sg:orig_category":"Asesor\u00cda Fiscal Y Jur\u00cddica",
    "sg:phone":"+34 988 49 41 68",
    "sg:postcode":"32236",
    "sg:province":"Ourense",
    "wof:name":"Chao Asesoria Y Gestion S.l.",
    "wof:placetype":"venue"
},
  "geometry": {"coordinates":[-8.1897850037,42.1536026001],"type":"Point"}
}