{
  "type": "Feature",
  "properties": {
    "iso:country":"ES",
    "sg:address":"Via Augusta, 295",
    "sg:city":"Barcelona",
    "sg:orig_category":"Ingenier\u00cda, Centros De Estudios (diversos)",
    "sg:phone":"+34 932 03 13 69",
    "sg:postcode":"08017",
    "sg:province":"Barcelona",
    "wof:name":"Bofill Thomasa Juan Antonio",
    "wof:placetype":"venue"
},
  "geometry": {"coordinates":[2.1279358864,41.3976364136],"type":"Point"}
}