{
  "type": "Feature",
  "properties": {
    "addr:full":"Avgd De Daniel Gil, 16 Ontinyent Valencia 46870",
    "addr:housenumber":"16",
    "addr:postcode":"46870",
    "addr:street":"Gil",
    "iso:country":"ES",
    "sg:address":"Avgd De Daniel Gil, 16",
    "sg:city":"Ontinyent",
    "sg:orig_category":"Transportes Internacionales",
    "sg:phone":"+34 962 91 60 92",
    "sg:postcode":"46870",
    "sg:province":"Valencia",
    "wof:name":"Decoexsa Mediterraneo S.a.",
    "wof:placetype":"venue"
},
  "geometry": {"coordinates":[-0.6022679806,38.8249778748],"type":"Point"}
}