{
  "type": "Feature",
  "properties": {
    "addr:full":"Avgd Antic Regne De Valencia, 58 Quart Poblet Valencia 46930",
    "addr:housenumber":"58",
    "addr:postcode":"46930",
    "addr:street":"Poblet",
    "iso:country":"ES",
    "sg:address":"Avgd Antic Regne De Valencia, 58",
    "sg:city":"Quart Poblet",
    "sg:orig_category":"Venta, Colocaci\u00d3n, Tratamiento De Enlosados, Soler\u00cdas",
    "sg:phone":"+34 961 54 81 38",
    "sg:postcode":"46930",
    "sg:province":"Valencia",
    "wof:name":"Azulejos Sanchis E Hijos S.l.",
    "wof:placetype":"venue"
},
  "geometry": {"coordinates":[-0.3768048882,39.4702377319],"type":"Point"}
}