{
  "type": "Feature",
  "properties": {
    "iso:country":"ES",
    "sg:address":"Ctra Enekuri-artxanda, Km. 0003,0",
    "sg:city":"Bilbao",
    "sg:orig_category":"Laboratorios",
    "sg:phone":"+34 944 74 78 71",
    "sg:postcode":"48015",
    "sg:province":"Vizcaya",
    "wof:name":"Laboratorios Bromatologicos Araba S.a.",
    "wof:placetype":"venue"
},
  "geometry": {"coordinates":[-2.9467461109,43.2794914246],"type":"Point"}
}