{
  "type": "Feature",
  "properties": {
    "addr:full":"Calle de San Isidro, 16 Azuaga Badajoz 06920",
    "addr:housenumber":"16",
    "addr:postcode":"06920",
    "addr:street":"Calle De San Isidro",
    "iso:country":"ES",
    "sg:address":"Calle de San Isidro, 16",
    "sg:city":"Azuaga",
    "sg:orig_category":"Enfermeras: Consultas, Atenci\u00d3n A Domicilio",
    "sg:phone":"+34 924 89 03 55",
    "sg:postcode":"06920",
    "sg:province":"Badajoz",
    "wof:name":"Duran Li\u00f1an Francisco",
    "wof:placetype":"venue"
},
  "geometry": {"coordinates":[-5.6805868149,38.2613983154],"type":"Point"}
}