{
  "type": "Feature",
  "properties": {
    "iso:country":"ES",
    "sg:address":"Avda Galicia De, 11",
    "sg:city":"Salas",
    "sg:orig_category":"Librer\u00cdas",
    "sg:phone":"+34 985 83 01 05",
    "sg:postcode":"33860",
    "sg:province":"Asturias",
    "wof:name":"Cernuda Garcia Gerardo Millan",
    "wof:placetype":"venue"
},
  "geometry": {"coordinates":[-6.2590689659,43.4085884094],"type":"Point"}
}