{
  "type": "Feature",
  "properties": {
    "addr:full":"Carrer de Illa, 34 Sabadell Barcelona 08202",
    "addr:housenumber":"34",
    "addr:postcode":"08202",
    "addr:street":"Carrer De Illa",
    "iso:country":"ES",
    "sg:address":"Carrer de Illa, 34",
    "sg:city":"Sabadell",
    "sg:orig_category":"Fabricaci\u00d3n De Telas Y Sedas",
    "sg:phone":"+34 937 25 53 89",
    "sg:postcode":"08202",
    "sg:province":"Barcelona",
    "wof:name":"Sarda Masllovet Joan",
    "wof:placetype":"venue"
},
  "geometry": {"coordinates":[2.1127920151,41.5487174988],"type":"Point"}
}