{
  "type": "Feature",
  "properties": {
    "iso:country":"ES",
    "sg:address":"Carrer de Treball, 255",
    "sg:city":"Barcelona",
    "sg:orig_category":"Florister\u00cdas",
    "sg:phone":"+34 933 14 60 20",
    "sg:postcode":"08020",
    "sg:province":"Barcelona",
    "wof:name":"Aleman Saez Sergi",
    "wof:placetype":"venue"
},
  "geometry": {"coordinates":[2.198266983,41.4187088013],"type":"Point"}
}