{
  "type": "Feature",
  "properties": {
    "iso:country":"ES",
    "sg:address":"Rond Fonti\u00d1as (das), 97",
    "sg:city":"Lugo",
    "sg:orig_category":"Bancos",
    "sg:phone":"+34 982 24 10 92",
    "sg:postcode":"27002",
    "sg:province":"Lugo",
    "wof:name":"Banco Pastor",
    "wof:placetype":"venue"
},
  "geometry": {"coordinates":[-7.5479869843,43.0096702576],"type":"Point"}
}