{
  "type": "Feature",
  "properties": {
    "iso:country":"ES",
    "sg:address":"Calle de Constitucion, 12",
    "sg:city":"Alcora",
    "sg:orig_category":"Bancos",
    "sg:phone":"+34 964 36 31 54",
    "sg:postcode":"12110",
    "sg:province":"Castell\u00f3n",
    "wof:name":"Banco Popular Espa\u00f1ol S.a.",
    "wof:placetype":"venue"
},
  "geometry": {"coordinates":[-0.213944003,40.0757713318],"type":"Point"}
}