{
  "type": "Feature",
  "properties": {
    "iso:country":"ES",
    "sg:address":"Calle de San Sebastian, 19",
    "sg:city":"Alcala Guadaira",
    "sg:classifiers":[
        {
            "category":"Autos & Motor Vehicles",
            "subcategory":"Automobile Sales",
            "type":"Retail Goods"
        }
    ],
    "sg:phone":"+34 955 68 33 21",
    "sg:postcode":"41500",
    "sg:province":"Sevilla",
    "wof:name":"Miguel Perez M. S.l.",
    "wof:placetype":"venue"
},
  "geometry": {"coordinates":[-5.8425331116,37.3390045166],"type":"Point"}
}