{
  "type": "Feature",
  "properties": {
    "iso:country":"ES",
    "sg:address":"Calle de Paco Seco De Lucena, 6",
    "sg:city":"Granada",
    "sg:orig_category":"Reposter\u00cdas",
    "sg:phone":"+34 958 22 26 74",
    "sg:postcode":"18009",
    "sg:province":"Granada",
    "wof:name":"Fernandez Martin Juan",
    "wof:placetype":"venue"
},
  "geometry": {"coordinates":[-3.594504118,37.1722106934],"type":"Point"}
}