{
  "type": "Feature",
  "properties": {
    "iso:country":"ES",
    "sg:address":"Calle de Hermanos Machado, 80",
    "sg:city":"Caba\u00d1uelas",
    "sg:orig_category":"Guarder\u00cdas",
    "sg:phone":"+34 950 55 40 24",
    "sg:postcode":"04738",
    "sg:province":"Almer\u00eda",
    "wof:name":"Gallego Rodriguez Emilia",
    "wof:placetype":"venue"
},
  "geometry": {"coordinates":[-2.6318690777,36.8073196411],"type":"Point"}
}