{
  "type": "Feature",
  "properties": {
    "iso:country":"ES",
    "sg:address":"Bertoa, S/n",
    "sg:city":"Carballo",
    "sg:orig_category":"Sindicatos De Trabajadores",
    "sg:phone":"+34 981 75 53 00",
    "sg:postcode":"15105",
    "sg:province":"La Coru\u00f1a",
    "wof:name":"C. Prop Del Pol Ind Y Comercial 1\u00aa Fase De Carballo",
    "wof:placetype":"venue"
},
  "geometry": {"coordinates":[-8.6750936508,43.2290306091],"type":"Point"}
}