{
  "type": "Feature",
  "properties": {
    "iso:country":"ES",
    "sg:address":"Calle de Miguel De Cervantes, S/n",
    "sg:city":"Guijuelo",
    "sg:orig_category":"Centros De Educaci\u00d3n Especial",
    "sg:phone":"+34 923 58 01 32",
    "sg:postcode":"37770",
    "sg:province":"Salamanca",
    "wof:name":"Colegio Publico Miguel De Cervantes",
    "wof:placetype":"venue"
},
  "geometry": {"coordinates":[-5.6688489914,40.5617713928],"type":"Point"}
}