{
  "type": "Feature",
  "properties": {
    "addr:full":"Plaz San Francisco, 3 Cifuentes Guadalajara 19420",
    "addr:housenumber":"3",
    "addr:postcode":"19420",
    "addr:street":"Plaz San Francisco",
    "iso:country":"ES",
    "sg:address":"Plaz San Francisco, 3",
    "sg:city":"Cifuentes",
    "sg:orig_category":"Empresas De Carpinter\u00cda",
    "sg:phone":"+34 949 81 02 29",
    "sg:postcode":"19420",
    "sg:province":"Guadalajara",
    "wof:name":"Hermanos Hernando C.b.",
    "wof:placetype":"venue"
},
  "geometry": {"coordinates":[-2.6206140518,40.7864151001],"type":"Point"}
}