{
  "type": "Feature",
  "properties": {
    "iso:country":"ES",
    "sg:address":"Calle de Vistanorte, S/n",
    "sg:city":"Navas Del Marques",
    "sg:orig_category":"Plomeros",
    "sg:phone":"+34 918 97 13 90",
    "sg:postcode":"05230",
    "sg:province":"\u00c1vila",
    "wof:name":"Martin Sanchez Jesus",
    "wof:placetype":"venue"
},
  "geometry": {"coordinates":[-4.3320841789,40.59349823],"type":"Point"}
}