{
  "type": "Feature",
  "properties": {
    "addr:full":"Calle de Doctor Bellido, 13 Playa Castell\u00f3n 12594",
    "addr:housenumber":"13",
    "addr:postcode":"12594",
    "addr:street":"Calle De Doctor Bellido;Playa Castello\u0301N",
    "iso:country":"ES",
    "sg:address":"Calle de Doctor Bellido, 13",
    "sg:city":"Playa",
    "sg:orig_category":"Importaci\u00d3n",
    "sg:phone":"+34 964 31 28 26",
    "sg:postcode":"12594",
    "sg:province":"Castell\u00f3n",
    "wof:name":"Planet Import S.l.",
    "wof:placetype":"venue"
},
  "geometry": {"coordinates":[-0.0360242017,39.9860687256],"type":"Point"}
}