{
  "type": "Feature",
  "properties": {
    "iso:country":"ES",
    "sg:address":"Avda Alcalde Cantos Ropero, 103",
    "sg:city":"Jerez De La Frontera",
    "sg:orig_category":"Porcelanas, Azulejos (fabricaci\u00d3n, Al Por Mayor)",
    "sg:phone":"+34 956 14 03 45",
    "sg:postcode":"11408",
    "sg:province":"C\u00e1diz",
    "wof:name":"Aridos Y Material Ceramico Rive S.l.",
    "wof:placetype":"venue"
},
  "geometry": {"coordinates":[-6.1296410561,36.6525993347],"type":"Point"}
}