{
  "type": "Feature",
  "properties": {
    "iso:country":"ES",
    "sg:address":"Calle de San Juan, 15",
    "sg:city":"Malaga",
    "sg:orig_category":"Confecci\u00d3n De Zapatos",
    "sg:phone":"+34 952 21 30 55",
    "sg:postcode":"29005",
    "sg:province":"M\u00e1laga",
    "wof:name":"Calzados Calderon De La Barca S.a.l.",
    "wof:placetype":"venue"
},
  "geometry": {"coordinates":[-4.4232821465,36.7200546265],"type":"Point"}
}