{
  "type": "Feature",
  "properties": {
    "iso:country":"ES",
    "sg:address":"Rua Casti\u00d1eiros, 21",
    "sg:city":"Sanxenxo",
    "sg:orig_category":"Electricidad: Instaladores",
    "sg:phone":"+34 986 72 04 64",
    "sg:postcode":"36960",
    "sg:province":"Pontevedra",
    "wof:name":"Maza Dopazo Manuel Benigno De La",
    "wof:placetype":"venue"
},
  "geometry": {"coordinates":[-8.8101892471,42.4071807861],"type":"Point"}
}