{
  "type": "Feature",
  "properties": {
    "addr:full":"Calle de Real, 44 Orellana Vieja Badajoz 06740",
    "addr:housenumber":"44",
    "addr:postcode":"06740",
    "addr:street":"Calle De Real",
    "iso:country":"ES",
    "sg:address":"Calle de Real, 44",
    "sg:city":"Orellana Vieja",
    "sg:orig_category":"Transportes Por V\u00cdas Navegables",
    "sg:phone":"+34 924 86 70 99",
    "sg:postcode":"06740",
    "sg:province":"Badajoz",
    "wof:name":"Barbosa Espinosa Anselmo",
    "wof:placetype":"venue"
},
  "geometry": {"coordinates":[-5.533372879,39.0085754395],"type":"Point"}
}