{
  "type": "Feature",
  "properties": {
    "iso:country":"ES",
    "sg:address":"Avda Cesareo Alierta, 16",
    "sg:city":"Zaragoza",
    "sg:orig_category":"Costura (alta Costura, Creaci\u00d3n)",
    "sg:phone":"+34 976 21 15 69",
    "sg:postcode":"50008",
    "sg:province":"Zaragoza",
    "wof:name":"Claveria Mustieles Julia",
    "wof:placetype":"venue"
},
  "geometry": {"coordinates":[-0.8787479997,41.645816803],"type":"Point"}
}