{
  "type": "Feature",
  "properties": {
    "iso:country":"ES",
    "sg:address":"Calle de Venancio Benito, 4",
    "sg:city":"Mendavia",
    "sg:orig_category":"Sanatorios M\u00c9dico",
    "sg:phone":"+34 948 68 58 07",
    "sg:postcode":"31587",
    "sg:province":"Navarra",
    "wof:name":"Ayuntamiento De Mendavia",
    "wof:placetype":"venue"
},
  "geometry": {"coordinates":[-2.1966629028,42.4445304871],"type":"Point"}
}