{
  "type": "Feature",
  "properties": {
    "addr:full":"Carrer de Escipions (dels), 10 Tarragona Tarragona 43002",
    "addr:housenumber":"10",
    "addr:postcode":"43002",
    "addr:street":"Carrer De Escipions Dels",
    "iso:country":"ES",
    "sg:address":"Carrer de Escipions (dels), 10",
    "sg:city":"Tarragona",
    "sg:orig_category":"Maquinaria Para Industrias Diversas",
    "sg:phone":"+34 977 22 60 87",
    "sg:postcode":"43002",
    "sg:province":"Tarragona",
    "wof:name":"Marti Queralt Excavaciones S.l.",
    "wof:placetype":"venue"
},
  "geometry": {"coordinates":[1.2534019947,41.121307373],"type":"Point"}
}