{
  "type": "Feature",
  "properties": {
    "addr:full":"Calle de Alcalde Pe\u00d1amaria De Llano, S/n Coru\u00d1a La Coru\u00f1a 15010",
    "addr:postcode":"15010",
    "addr:street":"Calle De Alcalde Pen\u0303Amaria De Llano S / N Corun\u0303A La Corun\u0303A",
    "iso:country":"ES",
    "sg:address":"Calle de Alcalde Pe\u00d1amaria De Llano, S/n",
    "sg:city":"Coru\u00d1a",
    "sg:orig_category":"Empresas De Desmonte",
    "sg:phone":"+34 981 26 06 60",
    "sg:postcode":"15010",
    "sg:province":"La Coru\u00f1a",
    "wof:name":"Fernandez Pacin Antonio",
    "wof:placetype":"venue"
},
  "geometry": {"coordinates":[-8.4258232117,43.3607902527],"type":"Point"}
}