{
  "type": "Feature",
  "properties": {
    "iso:country":"ES",
    "sg:address":"Calle de Paraguay, 1",
    "sg:city":"Coru\u00d1a",
    "sg:orig_category":"Mercer\u00cda, Lencer\u00cda (al Por Menor)",
    "sg:phone":"+34 981 27 26 90",
    "sg:postcode":"15011",
    "sg:province":"La Coru\u00f1a",
    "wof:name":"Rey Lema Olivia",
    "wof:placetype":"venue"
},
  "geometry": {"coordinates":[-8.4241790771,43.3734283447],"type":"Point"}
}