{
  "type": "Feature",
  "properties": {
    "iso:country":"ES",
    "sg:address":"Ctra Tf-324-la Perdoma, 171",
    "sg:city":"Perdoma",
    "sg:orig_category":"Venta, Montaje De Neum\u00c1ticos",
    "sg:phone":"+34 922 30 90 44",
    "sg:postcode":"38315",
    "sg:province":"Santa Cruz De Tenerife",
    "wof:name":"Mesa Perez Manuel Nicolas",
    "wof:placetype":"venue"
},
  "geometry": {"coordinates":[-16.5055618286,28.3659114838],"type":"Point"}
}