{
  "type": "Feature",
  "properties": {
    "iso:country":"ES",
    "sg:address":"Calle de Sagasta, 26",
    "sg:city":"San Pedro",
    "sg:orig_category":"Asociaciones Y Clubs Deportivos",
    "sg:phone":"+34 968 22 06 79",
    "sg:postcode":"30005",
    "sg:province":"Murcia",
    "wof:name":"Porras Garcia Antonio",
    "wof:placetype":"venue"
},
  "geometry": {"coordinates":[-1.1361819506,37.9850158691],"type":"Point"}
}