{
  "type": "Feature",
  "properties": {
    "addr:full":"Carrer de Maximi Fornes, 24 Rubi Barcelona 08191",
    "addr:housenumber":"24",
    "addr:postcode":"08191",
    "addr:street":"Carrer De Maximi Fornes",
    "iso:country":"ES",
    "sg:address":"Carrer de Maximi Fornes, 24",
    "sg:city":"Rubi",
    "sg:orig_category":"Imprenta",
    "sg:phone":"+34 936 99 13 06",
    "sg:postcode":"08191",
    "sg:province":"Barcelona",
    "wof:name":"Imprenta Casanovas S.l.",
    "wof:placetype":"venue"
},
  "geometry": {"coordinates":[2.031003952,41.4910316467],"type":"Point"}
}