{
  "type": "Feature",
  "properties": {
    "iso:country":"ES",
    "sg:address":"Carrer de Benimantell, 34",
    "sg:city":"Nucia",
    "sg:orig_category":"Molduras, Junquillos, Listones Y Molduras Perforadas",
    "sg:phone":"+34 966 89 63 35",
    "sg:postcode":"03530",
    "sg:province":"Alicante",
    "wof:name":"Bar Restaurante Lucio Y Dolores",
    "wof:placetype":"venue"
},
  "geometry": {"coordinates":[-0.1213990003,38.594619751],"type":"Point"}
}