{
  "type": "Feature",
  "properties": {
    "addr:full":"Praz Comandante Manso, 7 Lugo Lugo 27001",
    "addr:housenumber":"7",
    "addr:postcode":"27001",
    "addr:street":"Praz Comandante Manso",
    "iso:country":"ES",
    "sg:address":"Praz Comandante Manso, 7",
    "sg:city":"Lugo",
    "sg:orig_category":"Inmobiliaria (agencias)",
    "sg:phone":"+34 982 24 16 90",
    "sg:postcode":"27001",
    "sg:province":"Lugo",
    "wof:name":"Fernandez Arias M Pilar",
    "wof:placetype":"venue"
},
  "geometry": {"coordinates":[-7.569381237,43.0095176697],"type":"Point"}
}