{
  "type": "Feature",
  "properties": {
    "addr:full":"Ntra Sra De La Asuncion, 2 Jumilla Murcia 30520",
    "addr:housenumber":"2",
    "addr:postcode":"30520",
    "addr:street":"Ntra Sra De La Asuncion",
    "iso:country":"ES",
    "sg:address":"Ntra Sra De La Asuncion, 2",
    "sg:city":"Jumilla",
    "sg:orig_category":"Promotores Constructores",
    "sg:phone":"+34 968 75 62 76",
    "sg:postcode":"30520",
    "sg:province":"Murcia",
    "wof:name":"Promobesa",
    "wof:placetype":"venue"
},
  "geometry": {"coordinates":[-1.330065012,38.4735412598],"type":"Point"}
}