{
  "type": "Feature",
  "properties": {
    "addr:full":"Carrer de Loreto, 50 Barcelona Barcelona 08029",
    "addr:housenumber":"50",
    "addr:postcode":"08029",
    "addr:street":"Carrer De Loreto",
    "iso:country":"ES",
    "sg:address":"Carrer de Loreto, 50",
    "sg:city":"Barcelona",
    "sg:orig_category":"Ense\u00d1ante, Direcci\u00d3n",
    "sg:phone":"+34 934 10 26 06",
    "sg:postcode":"08029",
    "sg:province":"Barcelona",
    "wof:name":"Azori Compte Juan",
    "wof:placetype":"venue"
},
  "geometry": {"coordinates":[2.1427140236,41.3914489746],"type":"Point"}
}