{
  "type": "Feature",
  "properties": {
    "addr:full":"Ctra Palamos-nucli, 58 Bordils Girona 17462",
    "addr:housenumber":"58",
    "addr:postcode":"17462",
    "addr:street":"Ctra Palamos-Nucli",
    "iso:country":"ES",
    "sg:address":"Ctra Palamos-nucli, 58",
    "sg:city":"Bordils",
    "sg:orig_category":"T\u00c9cnicos Veterinarios",
    "sg:phone":"+34 972 49 01 51",
    "sg:postcode":"17462",
    "sg:province":"Girona",
    "wof:name":"Figueras Capdeferro Irene",
    "wof:placetype":"venue"
},
  "geometry": {"coordinates":[2.9117949009,42.0443763733],"type":"Point"}
}