{
  "type": "Feature",
  "properties": {
    "addr:full":"Carrer de Espinoi, 4 Barcelona Barcelona 08023",
    "addr:housenumber":"4",
    "addr:postcode":"08023",
    "addr:street":"Carrer De Espinoi",
    "iso:country":"ES",
    "sg:address":"Carrer de Espinoi, 4",
    "sg:city":"Barcelona",
    "sg:orig_category":"Promotores Constructores",
    "sg:phone":"+34 932 11 83 42",
    "sg:postcode":"08023",
    "sg:province":"Barcelona",
    "wof:name":"Inmobiliaria Aries S. A.",
    "wof:placetype":"venue"
},
  "geometry": {"coordinates":[2.1408729553,41.4108047485],"type":"Point"}
}