{
  "type": "Feature",
  "properties": {
    "addr:full":"Calle de Linares Rivas, 28 Sada La Coru\u00f1a 15160",
    "addr:housenumber":"28",
    "addr:postcode":"15160",
    "addr:street":"Calle De Linares Rivas;La",
    "iso:country":"ES",
    "sg:address":"Calle de Linares Rivas, 28",
    "sg:city":"Sada",
    "sg:orig_category":"Ropa Para Se\u00d1oras Y Caballeros (al Por Menor)",
    "sg:phone":"+34 981 62 27 29",
    "sg:postcode":"15160",
    "sg:province":"La Coru\u00f1a",
    "wof:name":"Asesoria Inmobiliaria S.l.",
    "wof:placetype":"venue"
},
  "geometry": {"coordinates":[-8.2534017563,43.3497314453],"type":"Point"}
}