{
  "type": "Feature",
  "properties": {
    "addr:full":"Calle de Goya, 37 Valencia Valencia 46018",
    "addr:housenumber":"37",
    "addr:postcode":"46018",
    "addr:street":"Calle De Goya",
    "iso:country":"ES",
    "sg:address":"Calle de Goya, 37",
    "sg:city":"Valencia",
    "sg:orig_category":"Cl\u00cdnicas Dentales",
    "sg:phone":"+34 963 59 01 96",
    "sg:postcode":"46018",
    "sg:province":"Valencia",
    "wof:name":"Garcia Lopez Ricardo",
    "wof:placetype":"venue"
},
  "geometry": {"coordinates":[-0.3984321058,39.4718894958],"type":"Point"}
}