{
  "type": "Feature",
  "properties": {
    "iso:country":"ES",
    "sg:address":"Ctra Alcazaren, Km. 0008,0",
    "sg:city":"Pedrajas S. Esteban",
    "sg:orig_category":"Distribuci\u00d3n De Petr\u00d3leo Y Derivados",
    "sg:phone":"+34 983 60 52 51",
    "sg:postcode":"47430",
    "sg:province":"Valladolid",
    "wof:name":"Gasoleos Eresma S.l.",
    "wof:placetype":"venue"
},
  "geometry": {"coordinates":[-4.580698967,41.3408317566],"type":"Point"}
}