{
  "type": "Feature",
  "properties": {
    "iso:country":"ES",
    "sg:address":"Avda Basagoiti, 64",
    "sg:city":"Algorta",
    "sg:orig_category":"Art\u00cdculos De Decoraci\u00d3n (fabricaci\u00d3n Y Al Por Mayor)",
    "sg:phone":"+34 944 91 42 65",
    "sg:postcode":"48991",
    "sg:province":"Vizcaya",
    "wof:name":"Hamar Estilo S.l",
    "wof:placetype":"venue"
},
  "geometry": {"coordinates":[-3.0120139122,43.3511924744],"type":"Point"}
}