{
  "type": "Feature",
  "properties": {
    "iso:country":"ES",
    "sg:address":"Ctra Barcelona, 172",
    "sg:city":"Cerdanyola Valles",
    "sg:orig_category":"Venta, Colocaci\u00d3n, Reparaci\u00d3n De Parabrisas, Techos Descapotables",
    "sg:phone":"+34 935 92 15 19",
    "sg:postcode":"08290",
    "sg:province":"Barcelona",
    "sg:website":"www.ralarsa.com",
    "wof:name":"Samarsa S.a.",
    "wof:placetype":"venue"
},
  "geometry": {"coordinates":[2.1470150948,41.4924812317],"type":"Point"}
}