{
  "type": "Feature",
  "properties": {
    "addr:full":"Carrer de Major, 23 Torroja Del Priorat Tarragona 43737",
    "addr:housenumber":"23",
    "addr:postcode":"43737",
    "addr:street":"Carrer De Major",
    "iso:country":"ES",
    "sg:address":"Carrer de Major, 23",
    "sg:city":"Torroja Del Priorat",
    "sg:orig_category":"Venta, Alquiler De Instrumentos Y Accesorios De M\u00dasica",
    "sg:phone":"+34 977 83 93 48",
    "sg:postcode":"43737",
    "sg:province":"Tarragona",
    "sg:website":"www.geosifis.com/wpraet",
    "wof:name":"Praet  Wilfried",
    "wof:placetype":"venue"
},
  "geometry": {"coordinates":[0.8103010058,41.2135543823],"type":"Point"}
}