{
  "type": "Feature",
  "properties": {
    "addr:full":"Carrer de Rector Ubach, 7 Barcelona Barcelona 08021",
    "addr:housenumber":"7",
    "addr:postcode":"08021",
    "addr:street":"Carrer De Rector Ubach",
    "iso:country":"ES",
    "sg:address":"Carrer de Rector Ubach, 7",
    "sg:city":"Barcelona",
    "sg:orig_category":"Muebles Y Accesorios Para Cocinas Y Cuartos De Ba\u00d1o (al Por Menor)",
    "sg:phone":"+34 932 00 00 09",
    "sg:postcode":"08021",
    "sg:province":"Barcelona",
    "wof:name":"Lopez Bohigas Antonio",
    "wof:placetype":"venue"
},
  "geometry": {"coordinates":[2.1449680328,41.3989562988],"type":"Point"}
}