{
  "type": "Feature",
  "properties": {
    "addr:full":"Andres Segovia, 20 Xirivella Valencia 46950",
    "addr:housenumber":"20",
    "addr:postcode":"46950",
    "addr:street":"Segovia",
    "iso:country":"ES",
    "sg:address":"Andres Segovia, 20",
    "sg:city":"Xirivella",
    "sg:orig_category":"Fabricaci\u00d3n De Juguetes Autom\u00c1ticos",
    "sg:phone":"+34 963 50 08 46",
    "sg:postcode":"46950",
    "sg:province":"Valencia",
    "wof:name":"Recreativos Villa Los Santos S.l.",
    "wof:placetype":"venue"
},
  "geometry": {"coordinates":[-0.4149160087,39.4661064148],"type":"Point"}
}