{
  "type": "Feature",
  "properties": {
    "iso:country":"ES",
    "sg:address":"Carrer de Closa De Mestres, 24",
    "sg:city":"Reus",
    "sg:orig_category":"Librer\u00cdas",
    "sg:phone":"+34 977 77 04 18",
    "sg:postcode":"43204",
    "sg:province":"Tarragona",
    "wof:name":"Sancho Save Agustin",
    "wof:placetype":"venue"
},
  "geometry": {"coordinates":[1.111232996,41.1519088745],"type":"Point"}
}