{
  "type": "Feature",
  "properties": {
    "iso:country":"ES",
    "sg:address":"Kale Gasteiz Bidea, 35",
    "sg:city":"Alegria-dulantzi",
    "sg:orig_category":"Contenedores (mercanc\u00cdas)",
    "sg:phone":"+34 945 40 05 61",
    "sg:postcode":"01240",
    "sg:province":"\u00c1lava",
    "wof:name":"Garcia Moreno Ricardo",
    "wof:placetype":"venue"
},
  "geometry": {"coordinates":[-2.5141289234,42.8400802612],"type":"Point"}
}