{
  "type": "Feature",
  "properties": {
    "addr:full":"Plaz Xuquer, 3 Valencia Valencia 46021",
    "addr:housenumber":"3",
    "addr:postcode":"46021",
    "addr:street":"Plaz Xuquer",
    "iso:country":"ES",
    "sg:address":"Plaz Xuquer, 3",
    "sg:city":"Valencia",
    "sg:orig_category":"Doctores En Medicina",
    "sg:phone":"+34 963 60 67 83",
    "sg:postcode":"46021",
    "sg:province":"Valencia",
    "wof:name":"Magraner Camarasa Ricardo",
    "wof:placetype":"venue"
},
  "geometry": {"coordinates":[-0.350917995,39.4759483337],"type":"Point"}
}