{
  "type": "Feature",
  "properties": {
    "iso:country":"ES",
    "sg:address":"Carrer de Rutlla, 26",
    "sg:city":"S. Feliu Guixols",
    "sg:orig_category":"Institutos De Belleza",
    "sg:phone":"+34 972 82 20 28",
    "sg:postcode":"17220",
    "sg:province":"Girona",
    "wof:name":"Prat Pou Esther",
    "wof:placetype":"venue"
},
  "geometry": {"coordinates":[3.0291099548,41.782119751],"type":"Point"}
}