{
  "type": "Feature",
  "properties": {
    "addr:full":"Calle de Santa Teresa De Jesus, 20 Zaragoza Zaragoza 50006",
    "addr:housenumber":"20",
    "addr:postcode":"50006",
    "addr:street":"Calle De Santa Teresa De Jesus",
    "iso:country":"ES",
    "sg:address":"Calle de Santa Teresa De Jesus, 20",
    "sg:city":"Zaragoza",
    "sg:classifiers":[
        {
            "category":"Personal",
            "subcategory":"Barber",
            "type":"Services"
        }
    ],
    "sg:phone":"+34 976 35 22 65",
    "sg:postcode":"50006",
    "sg:province":"Zaragoza",
    "sg:tags":[
        "caballeros",
        "de",
        "peluqueros"
    ],
    "wof:name":"Fortmen S.c",
    "wof:placetype":"venue"
},
  "geometry": {"coordinates":[-0.8926159739,41.6414527893],"type":"Point"}
}