{
  "type": "Feature",
  "properties": {
    "iso:country":"ES",
    "sg:address":"Edif. Las Barqueras, 4",
    "sg:city":"Llanes",
    "sg:orig_category":"Frutas, Legumbres Frescas Y Tempranas (al Por Menor)",
    "sg:phone":"+34 985 40 24 57",
    "sg:postcode":"33500",
    "sg:province":"Asturias",
    "wof:name":"Frutas Antonio Due\u00f1as S.l.",
    "wof:placetype":"venue"
},
  "geometry": {"coordinates":[-4.7549939156,43.4207191467],"type":"Point"}
}