{
  "type": "Feature",
  "properties": {
    "iso:country":"ES",
    "sg:address":"A Pedreira, S/n",
    "sg:city":"Pedreira",
    "sg:orig_category":"Automatizaci\u00d3n De Procesos Industriales Y De Edificaci\u00d3n (estudios, Instalaci\u00d3n)",
    "sg:phone":"+34 981 53 90 13",
    "sg:postcode":"15866",
    "sg:province":"La Coru\u00f1a",
    "wof:name":"Hoerbiger Origa S. A.",
    "wof:placetype":"venue"
},
  "geometry": {"coordinates":[-8.063044548,42.8541641235],"type":"Point"}
}