{
  "type": "Feature",
  "properties": {
    "addr:full":"Carrer de Arbucies, 12 Barcelona Barcelona 08030",
    "addr:housenumber":"12",
    "addr:postcode":"08030",
    "addr:street":"Carrer De Arbucies",
    "iso:country":"ES",
    "sg:address":"Carrer de Arbucies, 12",
    "sg:city":"Barcelona",
    "sg:orig_category":"Marroquiner\u00cda (confecci\u00d3n)",
    "sg:phone":"+34 933 46 35 24",
    "sg:postcode":"08030",
    "sg:province":"Barcelona",
    "wof:name":"Lugones Perez Manuel",
    "wof:placetype":"venue"
},
  "geometry": {"coordinates":[2.1862080097,41.4364051819],"type":"Point"}
}