{
  "type": "Feature",
  "properties": {
    "addr:full":"Calle de Nuestra Se\u00d1ora Del Aguila, 58 Alcala Guadaira Sevilla 41500",
    "addr:housenumber":"58",
    "addr:postcode":"41500",
    "addr:street":"Calle De Nuestra;Del Aguila",
    "iso:country":"ES",
    "sg:address":"Calle de Nuestra Se\u00d1ora Del Aguila, 58",
    "sg:city":"Alcala Guadaira",
    "sg:orig_category":"Reciclaje Y Tratamiento De Desechos Varios",
    "sg:phone":"+34 955 69 89 68",
    "sg:postcode":"41500",
    "sg:province":"Sevilla",
    "wof:name":"Mancomunidad De Los Alcores",
    "wof:placetype":"venue"
},
  "geometry": {"coordinates":[-5.8486380577,37.3346748352],"type":"Point"}
}