{
  "type": "Feature",
  "properties": {
    "iso:country":"ES",
    "sg:address":"Carrer de Narcis Monturiol, 14",
    "sg:city":"Manresa",
    "sg:orig_category":"Maquinaria Para Industrias Diversas",
    "sg:phone":"+34 938 74 59 52",
    "sg:postcode":"08243",
    "sg:province":"Barcelona",
    "wof:name":"Alquiler Y Plataformas S.l.",
    "wof:placetype":"venue"
},
  "geometry": {"coordinates":[1.8481942415,41.7185516357],"type":"Point"}
}