{
  "type": "Feature",
  "properties": {
    "addr:full":"Huerta Teneria, S/n Casarabonela M\u00e1laga 29566",
    "addr:housenumber":"s",
    "addr:postcode":"29566",
    "addr:street":"/ N Casarabonela Ma\u0301Laga",
    "iso:country":"ES",
    "sg:address":"Huerta Teneria, S/n",
    "sg:city":"Casarabonela",
    "sg:orig_category":"Frutas Y Legumbres Frescas (al Por Mayor)",
    "sg:phone":"+34 952 45 68 38",
    "sg:postcode":"29566",
    "sg:province":"M\u00e1laga",
    "wof:name":"Miguel Garcia Carmen",
    "wof:placetype":"venue"
},
  "geometry": {"coordinates":[-4.8421673775,36.7852401733],"type":"Point"}
}