{
  "type": "Feature",
  "properties": {
    "iso:country":"ES",
    "sg:address":"Rbla Hospital, 4",
    "sg:city":"Vic",
    "sg:orig_category":"M\u00c9dicos: Dermatolog\u00cda Y Venereolog\u00cda",
    "sg:phone":"+34 938 85 24 36",
    "sg:postcode":"08500",
    "sg:province":"Barcelona",
    "wof:name":"Arimany Manso Jose",
    "wof:placetype":"venue"
},
  "geometry": {"coordinates":[2.2529475689,41.9301567078],"type":"Point"}
}