{
  "type": "Feature",
  "properties": {
    "iso:country":"ES",
    "sg:address":"Calle de Barbara De Braganza (de), 22",
    "sg:city":"Boadilla Del Monte",
    "sg:orig_category":"Controles De Edificaci\u00d3n (construcci\u00d3n, Seguridad)",
    "sg:phone":"+34 916 33 33 10",
    "sg:postcode":"28660",
    "sg:province":"Madrid",
    "wof:name":"M.g.ingenieria Aplicada S.l.",
    "wof:placetype":"venue"
},
  "geometry": {"coordinates":[-3.8838195801,40.4077949524],"type":"Point"}
}