{
  "type": "Feature",
  "properties": {
    "iso:country":"ES",
    "sg:address":"Calle de San Pedro, 1",
    "sg:city":"Plasencia",
    "sg:orig_category":"Electrodom\u00c9sticos (al Por Menor)",
    "sg:phone":"+34 927 42 13 47",
    "sg:postcode":"10600",
    "sg:province":"C\u00e1ceres",
    "wof:name":"Calvo Martin Valentin",
    "wof:placetype":"venue"
},
  "geometry": {"coordinates":[-6.0875520706,40.0302009583],"type":"Point"}
}