{
  "type": "Feature",
  "properties": {
    "iso:country":"ES",
    "sg:address":"C/ Concepcion Arenal, 62",
    "sg:city":"Elche",
    "sg:orig_category":"Instalaci\u00d3n, Reparaci\u00d3n De Calefacci\u00d3n Por Gas",
    "sg:phone":"+34 965 43 56 76",
    "sg:postcode":"03201",
    "sg:province":"Alicante",
    "wof:name":"Acrogas S.l",
    "wof:placetype":"venue"
},
  "geometry": {"coordinates":[-0.7075045109,38.2640533447],"type":"Point"}
}