{
  "type": "Feature",
  "properties": {
    "addr:full":"Calle de Corredera Alta De San Pablo, 6 Madrid Madrid 28004",
    "addr:housenumber":"6",
    "addr:postcode":"28004",
    "addr:street":"Calle De Corredera Alta De San Pablo",
    "iso:country":"ES",
    "sg:address":"Calle de Corredera Alta De San Pablo, 6",
    "sg:city":"Madrid",
    "sg:orig_category":"Tatuajes",
    "sg:phone":"+34 915 31 19 73",
    "sg:postcode":"28004",
    "sg:province":"Madrid",
    "wof:name":"Madrid Tatto Crew S.l",
    "wof:placetype":"venue"
},
  "geometry": {"coordinates":[-3.7020242214,40.4247245789],"type":"Point"}
}