{
  "type": "Feature",
  "properties": {
    "iso:country":"ES",
    "sg:address":"Estacion Del Norte, S/n",
    "sg:city":"Valencia",
    "sg:orig_category":"Oficinas De Turismo, Asociaciones De Iniciativa",
    "sg:phone":"+34 963 52 85 73",
    "sg:postcode":"46007",
    "sg:province":"Valencia",
    "wof:name":"Agencia Valenciana Del Turisme",
    "wof:placetype":"venue"
},
  "geometry": {"coordinates":[-0.3771289885,39.4669532776],"type":"Point"}
}