{
  "type": "Feature",
  "properties": {
    "addr:full":"Rua Marina (a), 14 Grove Pontevedra 36980",
    "addr:housenumber":"14",
    "addr:postcode":"36980",
    "addr:street":"Rua Marina A;Grove Pontevedra",
    "iso:country":"ES",
    "sg:address":"Rua Marina (a), 14",
    "sg:city":"Grove",
    "sg:orig_category":"Restaurantes",
    "sg:phone":"+34 986 73 16 40",
    "sg:postcode":"36980",
    "sg:province":"Pontevedra",
    "wof:name":"Dominguez Gali\u00f1anes Carmen",
    "wof:placetype":"venue"
},
  "geometry": {"coordinates":[-8.8629894257,42.4953689575],"type":"Point"}
}