{
  "type": "Feature",
  "properties": {
    "iso:country":"ES",
    "sg:address":"Calle de Santa Quiteria, 4",
    "sg:city":"Higueruela",
    "sg:orig_category":"Ambulancias",
    "sg:phone":"+34 967 28 73 10",
    "sg:postcode":"02694",
    "sg:province":"Albacete",
    "wof:name":"Arnedo Gomez Pedro",
    "wof:placetype":"venue"
},
  "geometry": {"coordinates":[-1.4477119446,38.962978363],"type":"Point"}
}