{
  "type": "Feature",
  "properties": {
    "addr:full":"Calle de Historiador Antonio Terrones, 14 Andujar Ja\u00e9n 23740",
    "addr:housenumber":"14",
    "addr:postcode":"23740",
    "addr:street":"Calle De Historiador Antonio Terrones",
    "iso:country":"ES",
    "sg:address":"Calle de Historiador Antonio Terrones, 14",
    "sg:city":"Andujar",
    "sg:orig_category":"Lencer\u00cda Femenina, Corseter\u00cda, Trajes De Ba\u00d1o (al Por Menor)",
    "sg:phone":"+34 953 50 60 91",
    "sg:postcode":"23740",
    "sg:province":"Ja\u00e9n",
    "wof:name":"Pulido Pe\u00f1a Manuela",
    "wof:placetype":"venue"
},
  "geometry": {"coordinates":[-4.0468459129,38.0396270752],"type":"Point"}
}