{
  "type": "Feature",
  "properties": {
    "iso:country":"ES",
    "sg:address":"E Poligono, S/n",
    "sg:city":"Soria",
    "sg:orig_category":"Mantenimiento Y Reparaci\u00d3n De Motores Industriales",
    "sg:phone":"+34 975 22 31 19",
    "sg:postcode":"42005",
    "sg:province":"Soria",
    "wof:name":"Rectiduero S.l.",
    "wof:placetype":"venue"
},
  "geometry": {"coordinates":[-2.4691669941,41.7646598816],"type":"Point"}
}