{
  "type": "Feature",
  "properties": {
    "addr:full":"Chantrea-txantreako, 6 Iru\u00f1a Navarra 31015",
    "addr:housenumber":"6",
    "addr:postcode":"31015",
    "addr:street":"Chantrea-Txantreako",
    "iso:country":"ES",
    "sg:address":"Chantrea-txantreako, 6",
    "sg:city":"Iru\u00f1a",
    "sg:orig_category":"Molduras, Junquillos, Listones Y Molduras Perforadas",
    "sg:phone":"+34 948 12 21 97",
    "sg:postcode":"31015",
    "sg:province":"Navarra",
    "wof:name":"Beperet Iriarte Francisco Javier",
    "wof:placetype":"venue"
},
  "geometry": {"coordinates":[-1.6305010319,42.829158783],"type":"Point"}
}