{
  "type": "Feature",
  "properties": {
    "iso:country":"ES",
    "sg:address":"Rond Muralla (da), 81",
    "sg:city":"Lugo",
    "sg:orig_category":"M\u00c9dicos: Estomatolog\u00cda",
    "sg:phone":"+34 982 25 11 45",
    "sg:postcode":"27003",
    "sg:province":"Lugo",
    "wof:name":"Santalices Vieira Alfonso",
    "wof:placetype":"venue"
},
  "geometry": {"coordinates":[-7.5763959885,43.0335426331],"type":"Point"}
}