{
  "type": "Feature",
  "properties": {
    "addr:full":"Calle de Dos Hermanas, 4 Le\u00f3n Le\u00f3n 24005",
    "addr:housenumber":"4",
    "addr:postcode":"24005",
    "addr:street":"Calle De Dos Hermanas;Leo\u0301N",
    "iso:country":"ES",
    "sg:address":"Calle de Dos Hermanas, 4",
    "sg:city":"Le\u00f3n",
    "sg:orig_category":"Institutos De Belleza",
    "sg:phone":"+34 987 21 19 34",
    "sg:postcode":"24005",
    "sg:province":"Le\u00f3n",
    "wof:name":"Tecnoestetica Belena S.l.",
    "wof:placetype":"venue"
},
  "geometry": {"coordinates":[-5.554669857,42.5806999207],"type":"Point"}
}