{
  "type": "Feature",
  "properties": {
    "addr:full":"Calle de Justo Comin, 4 Sari\u00f1ena Huesca 22200",
    "addr:housenumber":"4",
    "addr:postcode":"22200",
    "addr:street":"Calle De Justo Comin",
    "iso:country":"ES",
    "sg:address":"Calle de Justo Comin, 4",
    "sg:city":"Sari\u00f1ena",
    "sg:orig_category":"Peluqueros: De Se\u00d1oras",
    "sg:phone":"+34 974 57 09 78",
    "sg:postcode":"22200",
    "sg:province":"Huesca",
    "wof:name":"Cabellud Brualla Maria Teresa",
    "wof:placetype":"venue"
},
  "geometry": {"coordinates":[-0.156445995,41.7922554016],"type":"Point"}
}