{
  "type": "Feature",
  "properties": {
    "addr:full":"Revoltas, S/n Canduas La Coru\u00f1a 15116",
    "addr:postcode":"15116",
    "addr:street":"Revoltas S / N Canduas La Corun\u0303A",
    "iso:country":"ES",
    "sg:address":"Revoltas, S/n",
    "sg:city":"Canduas",
    "sg:orig_category":"Productos Fitosanitarios (negocio, Aplicaci\u00d3n)",
    "sg:phone":"+34 981 75 43 20",
    "sg:postcode":"15116",
    "sg:province":"La Coru\u00f1a",
    "wof:name":"Moreira Lema Manuel Francisco",
    "wof:placetype":"venue"
},
  "geometry": {"coordinates":[-8.9571723938,43.2205734253],"type":"Point"}
}