{
  "type": "Feature",
  "properties": {
    "iso:country":"ES",
    "sg:address":"Calle de Mora\u00d1a, 12",
    "sg:city":"Leganes",
    "sg:orig_category":"Asesor\u00cda Fiscal Y Jur\u00cddica",
    "sg:phone":"+34 916 87 19 29",
    "sg:postcode":"28915",
    "sg:province":"Madrid",
    "wof:name":"Vazquez Escudero Maria Sampedro",
    "wof:placetype":"venue"
},
  "geometry": {"coordinates":[-3.755284071,40.3322677612],"type":"Point"}
}