{
  "type": "Feature",
  "properties": {
    "addr:full":"Cmno Laderas De La Font, S/n Sant Joan D'alacant Alicante 03550",
    "addr:housenumber":"s",
    "addr:postcode":"03550",
    "addr:street":"Cmno Laderas De La Font;/ N",
    "iso:country":"ES",
    "sg:address":"Cmno Laderas De La Font, S/n",
    "sg:city":"Sant Joan D'alacant",
    "sg:orig_category":"Deportes N\u00c1uticos, Acu\u00c1ticos Y Subacu\u00c1ticos: Art\u00cdculos Y Equipo (al Por Menor)",
    "sg:phone":"+34 965 65 34 06",
    "sg:postcode":"03550",
    "sg:province":"Alicante",
    "wof:name":"Nautica Boronad S.l.",
    "wof:placetype":"venue"
},
  "geometry": {"coordinates":[-0.4804700017,38.3440818787],"type":"Point"}
}