{
  "type": "Feature",
  "properties": {
    "iso:country":"ES",
    "sg:address":"Calle de Aduana, 58",
    "sg:city":"Irun",
    "sg:orig_category":"Molduras, Junquillos, Listones Y Molduras Perforadas",
    "sg:phone":"+34 943 62 82 43",
    "sg:postcode":"20303",
    "sg:province":"Guip\u00f9zcoa",
    "wof:name":"Bar La Gruta-juan Carlos Vicente Hernandez",
    "wof:placetype":"venue"
},
  "geometry": {"coordinates":[-1.7985001802,43.3358306885],"type":"Point"}
}