{
  "type": "Feature",
  "properties": {
    "addr:full":"San Silvestre, 13 Ayamonte Huelva 21400",
    "addr:postcode":"21400",
    "addr:street":"Silvestre",
    "iso:country":"ES",
    "sg:address":"San Silvestre, 13",
    "sg:city":"Ayamonte",
    "sg:orig_category":"Mec\u00c1nico Del Autom\u00d3vil",
    "sg:phone":"+34 959 32 04 82",
    "sg:postcode":"21400",
    "sg:province":"Huelva",
    "wof:name":"Morales Y Verdun S.l.",
    "wof:placetype":"venue"
},
  "geometry": {"coordinates":[-7.4089279175,37.2172279358],"type":"Point"}
}