{
  "type": "Feature",
  "properties": {
    "iso:country":"ES",
    "sg:address":"Calle de Manuel Fernandez Caballero, 6",
    "sg:city":"Torre-pacheco",
    "sg:orig_category":"Cristaler\u00cdas",
    "sg:phone":"+34 968 58 52 15",
    "sg:postcode":"30700",
    "sg:province":"Murcia",
    "wof:name":"Cristaleria Torre Pacheco S.l.",
    "wof:placetype":"venue"
},
  "geometry": {"coordinates":[-1.1769800186,37.9866371155],"type":"Point"}
}