{
  "type": "Feature",
  "properties": {
    "addr:full":"Calle de Comercio, 3 Madrid Madrid 28007",
    "addr:housenumber":"3",
    "addr:postcode":"28007",
    "addr:street":"Calle De Comercio",
    "iso:country":"ES",
    "sg:address":"Calle de Comercio, 3",
    "sg:city":"Madrid",
    "sg:orig_category":"Alquiler De V\u00cddeo",
    "sg:phone":"+34 915 01 97 83",
    "sg:postcode":"28007",
    "sg:province":"Madrid",
    "wof:name":"Telemensajeros Las Rozas S.l.",
    "wof:placetype":"venue"
},
  "geometry": {"coordinates":[-3.6812300682,40.403503418],"type":"Point"}
}