{
  "type": "Feature",
  "properties": {
    "addr:full":"Plaz Pelicano, 4 Sevilla Sevilla 41003",
    "addr:housenumber":"4",
    "addr:postcode":"41003",
    "addr:street":"Pelicano",
    "iso:country":"ES",
    "sg:address":"Plaz Pelicano, 4",
    "sg:city":"Sevilla",
    "sg:orig_category":"Fabricaci\u00d3n De Art\u00cdculos Y Ornamentos Religiosos",
    "sg:phone":"+34 954 53 73 43",
    "sg:postcode":"41003",
    "sg:province":"Sevilla",
    "wof:name":"Lopez Olmedo Emilio",
    "wof:placetype":"venue"
},
  "geometry": {"coordinates":[-6.0018129349,37.3876953125],"type":"Point"}
}