{
  "type": "Feature",
  "properties": {
    "addr:full":"Calle de Montera, 20 Poligono Industrial Los Villares Salamanca 37184",
    "addr:housenumber":"20",
    "addr:postcode":"37184",
    "addr:street":"Calle De Montera;Industrial",
    "iso:country":"ES",
    "sg:address":"Calle de Montera, 20",
    "sg:city":"Poligono Industrial Los Villares",
    "sg:orig_category":"Art\u00cdculos De Regalo (al Por Menor)",
    "sg:phone":"+34 923 22 46 55",
    "sg:postcode":"37184",
    "sg:province":"Salamanca",
    "sg:website":"www.castiarte.com",
    "wof:name":"Castiarte S.l.",
    "wof:placetype":"venue"
},
  "geometry": {"coordinates":[-5.6384940147,40.9902381897],"type":"Point"}
}