{
  "type": "Feature",
  "properties": {
    "addr:full":"Pase Francisco Mir Berlanga, Maritimo, 19 Melilla Melilla 52006",
    "addr:housenumber":"19",
    "addr:postcode":"52006",
    "addr:street":"Francisco Mir;Maritimo",
    "iso:country":"ES",
    "sg:address":"Pase Francisco Mir Berlanga, Maritimo, 19",
    "sg:city":"Melilla",
    "sg:orig_category":"Asesor\u00cda Fiscal Y Jur\u00cddica",
    "sg:phone":"+34 952 67 28 80",
    "sg:postcode":"52006",
    "sg:province":"Melilla",
    "wof:name":"Consulting Melilla S L",
    "wof:placetype":"venue"
},
  "geometry": {"coordinates":[-2.9364590645,35.2799301147],"type":"Point"}
}