{
  "type": "Feature",
  "properties": {
    "addr:full":"Xagobe-vilavedra, 26 Xagobe-vilavedra Pontevedra 36193",
    "addr:housenumber":"26",
    "addr:postcode":"36193",
    "addr:street":"Xagobe-Vilavedra",
    "iso:country":"ES",
    "sg:address":"Xagobe-vilavedra, 26",
    "sg:city":"Xagobe-vilavedra",
    "sg:orig_category":"Venta, Instalaci\u00d3n, Reparaci\u00d3n De Antenas Para Televisi\u00d3n",
    "sg:phone":"+34 986 53 64 73",
    "sg:postcode":"36193",
    "sg:province":"Pontevedra",
    "wof:name":"Comunicaciones E Instalaciones De Romay S.l.",
    "wof:placetype":"venue"
},
  "geometry": {"coordinates":[-8.6565513611,42.5349349976],"type":"Point"}
}