{
  "type": "Feature",
  "properties": {
    "iso:country":"ES",
    "sg:address":"Cami Geganta (de La), 109",
    "sg:city":"Mataro",
    "sg:orig_category":"Muebles, Minoristas",
    "sg:phone":"+34 937 99 29 96",
    "sg:postcode":"08302",
    "sg:province":"Barcelona",
    "wof:name":"Acedo Nogales Manuela",
    "wof:placetype":"venue"
},
  "geometry": {"coordinates":[2.4366042614,41.5412712097],"type":"Point"}
}