{
  "type": "Feature",
  "properties": {
    "addr:full":"Carrer de Sant Francesc Xavier, 24 Hospitalet Llobregat Barcelona 08905",
    "addr:housenumber":"24",
    "addr:postcode":"08905",
    "addr:street":"Carrer De Sant Francesc Xavier",
    "iso:country":"ES",
    "sg:address":"Carrer de Sant Francesc Xavier, 24",
    "sg:city":"Hospitalet Llobregat",
    "sg:orig_category":"Florister\u00cdas",
    "sg:phone":"+34 934 37 45 42",
    "sg:postcode":"08905",
    "sg:province":"Barcelona",
    "wof:name":"Del Clot Montesinos Ana Maria",
    "wof:placetype":"venue"
},
  "geometry": {"coordinates":[2.1077969074,41.3670272827],"type":"Point"}
}