{
  "type": "Feature",
  "properties": {
    "iso:country":"ES",
    "sg:address":"Carrer de Pi, 11",
    "sg:city":"Barcelona",
    "sg:orig_category":"Comit\u00c9s De Organizaci\u00d3n De Exposiciones, Ferias, Salones",
    "sg:phone":"+34 933 17 71 29",
    "sg:postcode":"08002",
    "sg:province":"Barcelona",
    "wof:name":"Semfyc Congresos S.l.",
    "wof:placetype":"venue"
},
  "geometry": {"coordinates":[2.173787117,41.3836364746],"type":"Point"}
}