{
  "type": "Feature",
  "properties": {
    "addr:full":"Avda Democracia, De La, 11 Melilla Melilla 52004",
    "addr:housenumber":"11",
    "addr:postcode":"52004",
    "addr:street":"Avda Democracia De La",
    "iso:country":"ES",
    "sg:address":"Avda Democracia, De La, 11",
    "sg:city":"Melilla",
    "sg:orig_category":"Arquitectos",
    "sg:phone":"+34 952 67 26 96",
    "sg:postcode":"52004",
    "sg:province":"Melilla",
    "wof:name":"El Ouaamari  Ahmed",
    "wof:placetype":"venue"
},
  "geometry": {"coordinates":[-2.9414598942,35.2887496948],"type":"Point"}
}