{
  "type": "Feature",
  "properties": {
    "addr:full":"Calle de Nasa, 18 Playa Honda Las Palmas 35509",
    "addr:housenumber":"18",
    "addr:postcode":"35509",
    "addr:street":"Calle De Nasa",
    "iso:country":"ES",
    "sg:address":"Calle de Nasa, 18",
    "sg:city":"Playa Honda",
    "sg:orig_category":"Doctores En Medicina",
    "sg:phone":"+34 928 82 00 72",
    "sg:postcode":"35509",
    "sg:province":"Las Palmas",
    "wof:name":"Francisco Lorenzo Martin",
    "wof:placetype":"venue"
},
  "geometry": {"coordinates":[-13.5900497437,28.9528446198],"type":"Point"}
}