{
  "type": "Feature",
  "properties": {
    "iso:country":"ES",
    "sg:address":"Calle de Arenal, 30",
    "sg:city":"Madrid",
    "sg:orig_category":"Caf\u00c9s, Bares, Cervecer\u00cdas",
    "sg:phone":"+34 915 59 53 97",
    "sg:postcode":"28013",
    "sg:province":"Madrid",
    "sg:website":"www.vienacapellanes.com",
    "wof:name":"Viena Reposteria Capellanes S.a.",
    "wof:placetype":"venue"
},
  "geometry": {"coordinates":[-3.7089858055,40.4178466797],"type":"Point"}
}