{
  "type": "Feature",
  "properties": {
    "iso:country":"ES",
    "sg:address":"Calle de Legion, La, 85",
    "sg:city":"Melilla",
    "sg:orig_category":"Caf\u00c9s, Bares, Cervecer\u00cdas",
    "sg:phone":"+34 952 67 50 02",
    "sg:postcode":"52006",
    "sg:province":"Melilla",
    "wof:name":"Mohand Abdelkader Hamed",
    "wof:placetype":"venue"
},
  "geometry": {"coordinates":[-2.9428670406,35.2758293152],"type":"Point"}
}