{
  "type": "Feature",
  "properties": {
    "iso:country":"ES",
    "sg:address":"Avda Americas (das), 19",
    "sg:city":"Lugo",
    "sg:orig_category":"Administradores De Bienes Y Delegados De Comunidades De Propietarios",
    "sg:phone":"+34 982 21 05 42",
    "sg:postcode":"27004",
    "sg:province":"Lugo",
    "wof:name":"Lastres Carballa Jose Luciano",
    "wof:placetype":"venue"
},
  "geometry": {"coordinates":[-7.5689668655,43.0099220276],"type":"Point"}
}