{
  "type": "Feature",
  "properties": {
    "addr:full":"Calle de Lope De Vega, 1 Andujar Ja\u00e9n 23740",
    "addr:housenumber":"1",
    "addr:postcode":"23740",
    "addr:street":"Calle De Lope De Vega",
    "iso:country":"ES",
    "sg:address":"Calle de Lope De Vega, 1",
    "sg:city":"Andujar",
    "sg:orig_category":"Imprenta",
    "sg:phone":"+34 953 50 42 44",
    "sg:postcode":"23740",
    "sg:province":"Ja\u00e9n",
    "wof:name":"Lopez Ortiz Manuel",
    "wof:placetype":"venue"
},
  "geometry": {"coordinates":[-4.0505599976,38.0431289673],"type":"Point"}
}