{
  "type": "Feature",
  "properties": {
    "iso:country":"ES",
    "sg:address":"President Companys, 17",
    "sg:city":"Selva Del Camp",
    "sg:orig_category":"Empresas De Carpinter\u00cda De Madera",
    "sg:phone":"+34 977 84 44 96",
    "sg:postcode":"43470",
    "sg:province":"Tarragona",
    "wof:name":"Carles Moline Joaquin",
    "wof:placetype":"venue"
},
  "geometry": {"coordinates":[1.1409749985,41.2144813538],"type":"Point"}
}