{
  "type": "Feature",
  "properties": {
    "addr:full":"Fonte De Curro, 51 Curro Pontevedra 36692",
    "addr:housenumber":"51",
    "addr:postcode":"36692",
    "addr:street":"Curro",
    "iso:country":"ES",
    "sg:address":"Fonte De Curro, 51",
    "sg:city":"Curro",
    "sg:orig_category":"Transportes Por V\u00cdas Navegables",
    "sg:phone":"+34 986 71 30 62",
    "sg:postcode":"36692",
    "sg:province":"Pontevedra",
    "wof:name":"Rebon Fiel Isidoro",
    "wof:placetype":"venue"
},
  "geometry": {"coordinates":[-8.663807869,42.5055503845],"type":"Point"}
}