{
  "type": "Feature",
  "properties": {
    "addr:full":"Avda Solvay, 192 Barreda Cantabria 39300",
    "addr:housenumber":"192",
    "addr:postcode":"39300",
    "addr:street":"Avda Solvay",
    "iso:country":"ES",
    "sg:address":"Avda Solvay, 192",
    "sg:city":"Barreda",
    "sg:orig_category":"Molduras, Junquillos, Listones Y Molduras Perforadas",
    "sg:phone":"+34 942 80 74 26",
    "sg:postcode":"39300",
    "sg:province":"Cantabria",
    "wof:name":"Diez Suarez Irene",
    "wof:placetype":"venue"
},
  "geometry": {"coordinates":[-4.0380592346,43.3777999878],"type":"Point"}
}