{
  "type": "Feature",
  "properties": {
    "addr:full":"Carrer de Palamos, 6 Prat Llobregat Barcelona 08820",
    "addr:housenumber":"6",
    "addr:postcode":"08820",
    "addr:street":"Carrer De Palamos;Llobregat",
    "iso:country":"ES",
    "sg:address":"Carrer de Palamos, 6",
    "sg:city":"Prat Llobregat",
    "sg:orig_category":"Farmacias",
    "sg:phone":"+34 933 79 47 56",
    "sg:postcode":"08820",
    "sg:province":"Barcelona",
    "wof:name":"Comas Bondia Maria Del Pilar",
    "wof:placetype":"venue"
},
  "geometry": {"coordinates":[2.0987319946,41.3234367371],"type":"Point"}
}