{
  "type": "Feature",
  "properties": {
    "iso:country":"ES",
    "sg:address":"Avda Eladio Perlado, 29",
    "sg:city":"Burgos",
    "sg:orig_category":"Asesor\u00cda Fiscal Y Jur\u00cddica",
    "sg:phone":"+34 947 48 73 19",
    "sg:postcode":"09007",
    "sg:province":"Burgos",
    "wof:name":"Velez Fernandez Carlos Fermin",
    "wof:placetype":"venue"
},
  "geometry": {"coordinates":[-3.6668689251,42.3514862061],"type":"Point"}
}