{
  "type": "Feature",
  "properties": {
    "iso:country":"ES",
    "sg:address":"Calle de Beurko Viejo, 1",
    "sg:city":"San Vicente De Barakaldo",
    "sg:orig_category":"Promotores Constructores",
    "sg:phone":"+34 944 37 83 26",
    "sg:postcode":"48902",
    "sg:province":"Vizcaya",
    "wof:name":"Construcciones Y Reformas Bear Sl",
    "wof:placetype":"venue"
},
  "geometry": {"coordinates":[-2.9950582981,43.2927894592],"type":"Point"}
}