{
  "type": "Feature",
  "properties": {
    "iso:country":"ES",
    "sg:address":"Ctra Torreblanca-mairena, Km. 0002,8",
    "sg:city":"Alcala Guadaira",
    "sg:orig_category":"M\u00c1rmoles, Granitos Y Piedras Naturales",
    "sg:phone":"+34 955 63 43 12",
    "sg:postcode":"41500",
    "sg:province":"Sevilla",
    "wof:name":"Almacen De Marmoles Sanchez S.l.",
    "wof:placetype":"venue"
},
  "geometry": {"coordinates":[-5.8877263069,37.3837127686],"type":"Point"}
}