{
  "type": "Feature",
  "properties": {
    "addr:full":"San Xulian, 6 San Xulian Lugo 27614",
    "addr:housenumber":"6",
    "addr:postcode":"27614",
    "addr:street":"San Xulian",
    "iso:country":"ES",
    "sg:address":"San Xulian, 6",
    "sg:city":"San Xulian",
    "sg:orig_category":"Art\u00cdculos De Madera (fabricaci\u00d3n Y Al Por Mayor)",
    "sg:phone":"+34 982 53 13 05",
    "sg:postcode":"27614",
    "sg:province":"Lugo",
    "wof:name":"Alvaredo Diaz Francisco",
    "wof:placetype":"venue"
},
  "geometry": {"coordinates":[-7.6662549973,42.834148407],"type":"Point"}
}