{
  "type": "Feature",
  "properties": {
    "iso:country":"ES",
    "sg:address":"C/ Francesc Layret, 55",
    "sg:city":"Cerdanyola Valles",
    "sg:orig_category":"Internados & Ense\u00d1anza Privada",
    "sg:phone":"+34 936 92 08 84",
    "sg:postcode":"08290",
    "sg:province":"Barcelona",
    "wof:name":"Religiosas Dominicas De La Anunciata",
    "wof:placetype":"venue"
},
  "geometry": {"coordinates":[2.1422650814,41.4918022156],"type":"Point"}
}