{
  "type": "Feature",
  "properties": {
    "iso:country":"ES",
    "sg:address":"Carrer de Pere Iv, 113",
    "sg:city":"Barcelona",
    "sg:orig_category":"Pararrayos, Tomas De Tierra (fabricaci\u00d3n, Colocaci\u00d3n)",
    "sg:phone":"+34 933 00 16 33",
    "sg:postcode":"08018",
    "sg:province":"Barcelona",
    "wof:name":"Jic Aubch C.b.",
    "wof:placetype":"venue"
},
  "geometry": {"coordinates":[2.1951949596,41.3999710083],"type":"Point"}
}