{
  "type": "Feature",
  "properties": {
    "addr:full":"Calle de Donantes De Sangre, 32 Lucena C\u00f3rdoba 14900",
    "addr:housenumber":"32",
    "addr:postcode":"14900",
    "addr:street":"Calle De Donantes De Sangre",
    "iso:country":"ES",
    "sg:address":"Calle de Donantes De Sangre, 32",
    "sg:city":"Lucena",
    "sg:orig_category":"Reposter\u00cdas",
    "sg:phone":"+34 957 50 39 00",
    "sg:postcode":"14900",
    "sg:province":"C\u00f3rdoba",
    "wof:name":"Panaderia Hermanos Serrano Luna S.l.",
    "wof:placetype":"venue"
},
  "geometry": {"coordinates":[-4.4952030182,37.4113082886],"type":"Point"}
}