{
  "type": "Feature",
  "properties": {
    "iso:country":"ES",
    "sg:address":"Cant Toural (do), 7",
    "sg:city":"Santiago De Compostela",
    "sg:orig_category":"Librer\u00cdas",
    "sg:phone":"+34 981 58 89 92",
    "sg:postcode":"15705",
    "sg:province":"La Coru\u00f1a",
    "wof:name":"Pardi\u00f1as Romero Fernando",
    "wof:placetype":"venue"
},
  "geometry": {"coordinates":[-8.5447597504,42.8774642944],"type":"Point"}
}