{
  "type": "Feature",
  "properties": {
    "iso:country":"ES",
    "sg:address":"Calle de Gerona, 11",
    "sg:city":"Alacant",
    "sg:orig_category":"Asociaciones, Organismos Culturales Y Socioeducativos",
    "sg:phone":"+34 965 21 81 44",
    "sg:postcode":"03001",
    "sg:province":"Alicante",
    "wof:name":"Asociacion De Pensionistas De Hidroelectrica Espa\u00d1ola",
    "wof:placetype":"venue"
},
  "geometry": {"coordinates":[-0.4853006899,38.3444900513],"type":"Point"}
}