{
  "type": "Feature",
  "properties": {
    "addr:full":"Carr Sant Joan, 1 Muro Islas Baleares 07440",
    "addr:housenumber":"1",
    "addr:postcode":"07440",
    "addr:street":"Carr Sant Joan",
    "iso:country":"ES",
    "sg:address":"Carr Sant Joan, 1",
    "sg:city":"Muro",
    "sg:orig_category":"Farmacias",
    "sg:phone":"+34 971 53 77 81",
    "sg:postcode":"07440",
    "sg:province":"Islas Baleares",
    "wof:name":"Sabater Gost Rafael",
    "wof:placetype":"venue"
},
  "geometry": {"coordinates":[3.0576388836,39.7363052368],"type":"Point"}
}