{
  "type": "Feature",
  "properties": {
    "iso:country":"ES",
    "sg:address":"Calle de General Oraa, 16",
    "sg:city":"Madrid",
    "sg:orig_category":"Centros Empresariales",
    "sg:phone":"+34 914 11 27 68",
    "sg:postcode":"28006",
    "sg:province":"Madrid",
    "sg:website":"www.asimccaf.com",
    "wof:name":"Asociacion De Instaladores Y Mantenedores De Climatizacion Calefaccion Fontaneria Gas Y Proteccion C",
    "wof:placetype":"venue"
},
  "geometry": {"coordinates":[-3.6852221489,40.436252594],"type":"Point"}
}