{
  "type": "Feature",
  "properties": {
    "addr:full":"Urb Castillo Caleta De Fuste, S/n Caleta De Fuste Las Palmas 35610",
    "addr:housenumber":"/ n",
    "addr:postcode":"35610",
    "addr:street":"Urb Castillo Caleta;Fuste S;Palmas",
    "iso:country":"ES",
    "sg:address":"Urb Castillo Caleta De Fuste, S/n",
    "sg:city":"Caleta De Fuste",
    "sg:orig_category":"Electricidad, Electr\u00d3nica: Material Y Suministros (al Por Mayor)",
    "sg:phone":"+34 928 54 75 73",
    "sg:postcode":"35610",
    "sg:province":"Las Palmas",
    "wof:name":"Automaticos Canarios S.a.",
    "wof:placetype":"venue"
},
  "geometry": {"coordinates":[-13.863199234,28.3980941772],"type":"Point"}
}