{
  "type": "Feature",
  "properties": {
    "addr:full":"Carrer de Industria, 226 Barcelona Barcelona 08026",
    "addr:housenumber":"226",
    "addr:postcode":"08026",
    "addr:street":"Carrer De Industria",
    "iso:country":"ES",
    "sg:address":"Carrer de Industria, 226",
    "sg:city":"Barcelona",
    "sg:orig_category":"Carnicer\u00cdas, Carnicer\u00cdas",
    "sg:phone":"+34 933 47 11 55",
    "sg:postcode":"08026",
    "sg:province":"Barcelona",
    "wof:name":"Gracia Garcia Javier",
    "wof:placetype":"venue"
},
  "geometry": {"coordinates":[2.1779439449,41.4121284485],"type":"Point"}
}