{
  "type": "Feature",
  "properties": {
    "addr:full":"Carrer de Hort Gran, 14 Sitges Barcelona 08870",
    "addr:housenumber":"14",
    "addr:postcode":"08870",
    "addr:street":"Carrer De Hort Gran",
    "iso:country":"ES",
    "sg:address":"Carrer de Hort Gran, 14",
    "sg:city":"Sitges",
    "sg:orig_category":"Chapister\u00cda",
    "sg:phone":"+34 938 94 56 01",
    "sg:postcode":"08870",
    "sg:province":"Barcelona",
    "wof:name":"Cid Montero Pedro",
    "wof:placetype":"venue"
},
  "geometry": {"coordinates":[1.8110150099,41.2385902405],"type":"Point"}
}