{
  "type": "Feature",
  "properties": {
    "iso:country":"ES",
    "sg:address":"Carr Pla, 8",
    "sg:city":"Queralbs",
    "sg:orig_category":"Molduras, Junquillos, Listones Y Molduras Perforadas",
    "sg:phone":"+34 972 72 77 44",
    "sg:postcode":"17534",
    "sg:province":"Girona",
    "wof:name":"Torner Ribas Francisco",
    "wof:placetype":"venue"
},
  "geometry": {"coordinates":[2.166011095,42.3068962097],"type":"Point"}
}