{
  "type": "Feature",
  "properties": {
    "iso:country":"ES",
    "sg:address":"Avda Zaragoza, 22",
    "sg:city":"Tudela",
    "sg:orig_category":"Cajas De Ahorro",
    "sg:phone":"+34 948 41 12 97",
    "sg:postcode":"31500",
    "sg:province":"Navarra",
    "wof:name":"Caja De Ahorros Y Monte De Piedad De Zaragoza Aragon Y Rioja",
    "wof:placetype":"venue"
},
  "geometry": {"coordinates":[-1.6015319824,42.0607719421],"type":"Point"}
}