{
  "type": "Feature",
  "properties": {
    "iso:country":"ES",
    "sg:address":"Carrer de L'arc De Santa Eulalia, 1",
    "sg:city":"Barcelona",
    "sg:orig_category":"Molduras, Junquillos, Listones Y Molduras Perforadas",
    "sg:phone":"+34 933 02 67 64",
    "sg:postcode":"08002",
    "sg:province":"Barcelona",
    "wof:name":"Marti Borbones Jose",
    "wof:placetype":"venue"
},
  "geometry": {"coordinates":[2.1749885082,41.3815917969],"type":"Point"}
}