{
  "type": "Feature",
  "properties": {
    "addr:full":"C/ Bambu, 1 Alcoi Alicante 03801",
    "addr:postcode":"03801",
    "addr:street":"C / Bambu 1",
    "iso:country":"ES",
    "sg:address":"C/ Bambu, 1",
    "sg:city":"Alcoi",
    "sg:orig_category":"Ingeniero",
    "sg:phone":"+34 965 54 14 31",
    "sg:postcode":"03801",
    "sg:province":"Alicante",
    "wof:name":"Gil Ferrando Jose",
    "wof:placetype":"venue"
},
  "geometry": {"coordinates":[-0.4765230119,38.696811676],"type":"Point"}
}