{
  "type": "Feature",
  "properties": {
    "iso:country":"ES",
    "sg:address":"Av Comte De Sallent, 4",
    "sg:city":"Palma",
    "sg:orig_category":"Institutos De Belleza",
    "sg:phone":"+34 971 76 08 43",
    "sg:postcode":"07003",
    "sg:province":"Islas Baleares",
    "wof:name":"Bellod Abat Ernestina",
    "wof:placetype":"venue"
},
  "geometry": {"coordinates":[2.6520080566,39.5777435303],"type":"Point"}
}