{
  "type": "Feature",
  "properties": {
    "iso:country":"ES",
    "sg:address":"Calle de Montevideo, 3",
    "sg:city":"Palmas De Gran Canaria",
    "sg:orig_category":"Discotecas Y Salas De Baile",
    "sg:phone":"+34 928 22 24 95",
    "sg:postcode":"35007",
    "sg:province":"Las Palmas",
    "wof:name":"Rimardi S.l.",
    "wof:placetype":"venue"
},
  "geometry": {"coordinates":[-15.4298334122,28.13621521],"type":"Point"}
}