{
  "type": "Feature",
  "properties": {
    "iso:country":"ES",
    "sg:address":"Industrialdea, S/n",
    "sg:city":"Itziar",
    "sg:orig_category":"Veh\u00cdculos De Ocasi\u00d3n",
    "sg:phone":"+34 943 19 90 45",
    "sg:postcode":"20829",
    "sg:province":"Guip\u00f9zcoa",
    "wof:name":"Automoviles Andutz C.b.",
    "wof:placetype":"venue"
},
  "geometry": {"coordinates":[-2.3308770657,43.276473999],"type":"Point"}
}