{
  "type": "Feature",
  "properties": {
    "iso:country":"ES",
    "sg:address":"Rbla General Vives, 33",
    "sg:city":"Igualada",
    "sg:orig_category":"Ropa Para Ni\u00d1os (al Por Menor)",
    "sg:phone":"+34 938 03 54 56",
    "sg:postcode":"08700",
    "sg:province":"Barcelona",
    "wof:name":"Brugues Brugues Antonio",
    "wof:placetype":"venue"
},
  "geometry": {"coordinates":[1.6197429895,41.5792503357],"type":"Point"}
}