{
  "type": "Feature",
  "properties": {
    "iso:country":"ES",
    "sg:address":"Ctra Alicante, S/n",
    "sg:city":"Grajuela",
    "sg:orig_category":"Fabricaci\u00d3n Y Comercio De M\u00c1quinas",
    "sg:phone":"+34 968 19 15 36",
    "sg:postcode":"30730",
    "sg:province":"Murcia",
    "wof:name":"Expo Billares San Javier S.l.",
    "wof:placetype":"venue"
},
  "geometry": {"coordinates":[-0.8377289772,37.8054389954],"type":"Point"}
}