{
  "type": "Feature",
  "properties": {
    "iso:country":"ES",
    "sg:address":"Carr Bisbe Lorenzana, 38",
    "sg:city":"Girona",
    "sg:orig_category":"Psic\u00d3logos",
    "sg:phone":"+34 972 20 14 04",
    "sg:postcode":"17002",
    "sg:province":"Girona",
    "wof:name":"Iglesias Marti Francesc",
    "wof:placetype":"venue"
},
  "geometry": {"coordinates":[2.8194210529,41.9788818359],"type":"Point"}
}