{
  "type": "Feature",
  "properties": {
    "iso:country":"ES",
    "sg:address":"Carrer de Can Cuyas, 67",
    "sg:city":"Can Cuias",
    "sg:orig_category":"Empresas De Empaquetado, Embalajes Por Encargo",
    "sg:phone":"+34 935 64 47 98",
    "sg:postcode":"08110",
    "sg:province":"Barcelona",
    "wof:name":"Estuchados Del Azucar S.l.",
    "wof:placetype":"venue"
},
  "geometry": {"coordinates":[2.1859691143,41.4872894287],"type":"Point"}
}