{
  "type": "Feature",
  "properties": {
    "iso:country":"ES",
    "sg:address":"Calle de Ferrol, 9",
    "sg:city":"Cangas",
    "sg:orig_category":"Formaci\u00d3n Continuada (variada)",
    "sg:phone":"+34 986 30 24 31",
    "sg:postcode":"36940",
    "sg:province":"Pontevedra",
    "wof:name":"Mari\u00f1o Juncal Mercedes",
    "wof:placetype":"venue"
},
  "geometry": {"coordinates":[-8.7799844742,42.2656974792],"type":"Point"}
}