{
  "type": "Feature",
  "properties": {
    "addr:full":"Calle de Virgen Del Portillo, 37 Madrid Madrid 28027",
    "addr:housenumber":"37",
    "addr:postcode":"madrid;28027",
    "addr:street":"Calle De Virgen Del Portillo",
    "iso:country":"ES",
    "sg:address":"Calle de Virgen Del Portillo, 37",
    "sg:city":"Madrid",
    "sg:orig_category":"Juegos Y Juguetes (al Por Menor)",
    "sg:phone":"+34 914 04 73 94",
    "sg:postcode":"28027",
    "sg:province":"Madrid",
    "wof:name":"Vazquez Vazquez Aurelio",
    "wof:placetype":"venue"
},
  "geometry": {"coordinates":[-3.6484110355,40.4388847351],"type":"Point"}
}