{
  "type": "Feature",
  "properties": {
    "iso:country":"ES",
    "sg:address":"Calle de Conde De Sastago, 4",
    "sg:city":"Zaragoza",
    "sg:orig_category":"Clases De M\u00dasica Y Canto",
    "sg:phone":"+34 976 59 52 91",
    "sg:postcode":"50013",
    "sg:province":"Zaragoza",
    "wof:name":"Garcia Hernando Jose Antonio",
    "wof:placetype":"venue"
},
  "geometry": {"coordinates":[-0.8721064925,41.640247345],"type":"Point"}
}