{
  "type": "Feature",
  "properties": {
    "iso:country":"ES",
    "sg:address":"Avda Palma De Mallorca, 24",
    "sg:city":"Torremolinos",
    "sg:orig_category":"Ropa Para Se\u00d1oras Y Caballeros (al Por Menor)",
    "sg:phone":"+34 952 05 89 75",
    "sg:postcode":"29620",
    "sg:province":"M\u00e1laga",
    "wof:name":"Maria Isabel Cruz Y Asociados S.l.",
    "wof:placetype":"venue"
},
  "geometry": {"coordinates":[-4.5001730919,36.6221733093],"type":"Point"}
}