{
  "type": "Feature",
  "properties": {
    "iso:country":"ES",
    "sg:address":"Calle de Lopez Gomez, 9",
    "sg:city":"Valladolid",
    "sg:orig_category":"Cer\u00c1micas: Material Y Suministros",
    "sg:phone":"+34 983 30 51 58",
    "sg:postcode":"47002",
    "sg:province":"Valladolid",
    "wof:name":"Expoceramica S. A.",
    "wof:placetype":"venue"
},
  "geometry": {"coordinates":[-4.7235989571,41.650554657],"type":"Point"}
}