{
  "type": "Feature",
  "properties": {
    "addr:full":"Calle de Rufino Rejon, 2 Madrid Madrid 28044",
    "addr:housenumber":"2",
    "addr:postcode":"28044",
    "addr:street":"Calle De Rufino Rejon",
    "iso:country":"ES",
    "sg:address":"Calle de Rufino Rejon, 2",
    "sg:city":"Madrid",
    "sg:orig_category":"Tapicer\u00cdas",
    "sg:phone":"+34 915 08 80 50",
    "sg:postcode":"28044",
    "sg:province":"Madrid",
    "wof:name":"Guijarro Ventoso Jose Maria",
    "wof:placetype":"venue"
},
  "geometry": {"coordinates":[-3.7607560158,40.3685035706],"type":"Point"}
}