{
  "type": "Feature",
  "properties": {
    "iso:country":"ES",
    "sg:address":"Avda Principe De Espa\u00d1a, 10",
    "sg:city":"Almoradi",
    "sg:orig_category":"Distribuci\u00d3n De Petr\u00d3leo Y Derivados",
    "sg:phone":"+34 965 70 27 67",
    "sg:postcode":"03160",
    "sg:province":"Alicante",
    "wof:name":"Galpgest Petrogal Estaciones De Servicio S.l.u.",
    "wof:placetype":"venue"
},
  "geometry": {"coordinates":[-0.7876480818,38.1164588928],"type":"Point"}
}