{
  "type": "Feature",
  "properties": {
    "iso:country":"ES",
    "sg:address":"O Couso, S/n",
    "sg:city":"Rosal",
    "sg:orig_category":"Laboratorios Y Cl\u00cdnicas Veterinarias",
    "sg:phone":"+34 986 62 62 06",
    "sg:postcode":"36770",
    "sg:province":"Pontevedra",
    "wof:name":"Gonzalez Carrera Graciela Maria",
    "wof:placetype":"venue"
},
  "geometry": {"coordinates":[-8.8362493515,41.9370346069],"type":"Point"}
}