{
  "type": "Feature",
  "properties": {
    "iso:country":"ES",
    "sg:address":"Calle de Cristo, 31",
    "sg:city":"Velez-malaga",
    "sg:orig_category":"Muebles, Minoristas",
    "sg:phone":"+34 952 50 44 48",
    "sg:postcode":"29700",
    "sg:province":"M\u00e1laga",
    "wof:name":"Galvez Ramirez Dolores",
    "wof:placetype":"venue"
},
  "geometry": {"coordinates":[-4.1032924652,36.7797431946],"type":"Point"}
}