{
  "type": "Feature",
  "properties": {
    "addr:full":"Calle de Ca\u00d1ada Toledana, S/n Humanes De Madrid Madrid 28970",
    "addr:housenumber":"s / n",
    "addr:postcode":"28970",
    "addr:street":"Calle De Can\u0303Ada Toledana",
    "iso:country":"ES",
    "sg:address":"Calle de Ca\u00d1ada Toledana, S/n",
    "sg:city":"Humanes De Madrid",
    "sg:orig_category":"Venta, Alquiler De Toldos",
    "sg:phone":"+34 916 09 47 37",
    "sg:postcode":"28970",
    "sg:province":"Madrid",
    "sg:website":"www.aiscupal.com",
    "wof:name":"Aislamientos Y Cubiertas Palomares",
    "wof:placetype":"venue"
},
  "geometry": {"coordinates":[-3.8572580814,40.2166023254],"type":"Point"}
}