{
  "type": "Feature",
  "properties": {
    "iso:country":"ES",
    "sg:address":"Calle de Kasune, 25",
    "sg:city":"Getxo",
    "sg:orig_category":"Florister\u00cdas",
    "sg:phone":"+34 944 30 12 68",
    "sg:postcode":"48990",
    "sg:province":"Vizcaya",
    "wof:name":"Eider Martinez Del Tio",
    "wof:placetype":"venue"
},
  "geometry": {"coordinates":[-3.0094540119,43.3488540649],"type":"Point"}
}