{
  "type": "Feature",
  "properties": {
    "addr:full":"Calle de Dean Silverio, 30 Realejo Alto Santa Cruz De Tenerife 38410",
    "addr:housenumber":"30",
    "addr:postcode":"38410",
    "addr:street":"Calle De Dean Silverio",
    "iso:country":"ES",
    "sg:address":"Calle de Dean Silverio, 30",
    "sg:city":"Realejo Alto",
    "sg:orig_category":"Cerrajer\u00cda, Ferrallista",
    "sg:phone":"+34 922 35 40 65",
    "sg:postcode":"38410",
    "sg:province":"Santa Cruz De Tenerife",
    "wof:name":"Gonzalez Mendez Pedro David",
    "wof:placetype":"venue"
},
  "geometry": {"coordinates":[-16.5824222565,28.376411438],"type":"Point"}
}