{
  "type": "Feature",
  "properties": {
    "addr:full":"Calle de Particular Torre De Ugao, 2 Ugao-miraballes Vizcaya 48490",
    "addr:housenumber":"2",
    "addr:postcode":"48490",
    "addr:street":"Calle De Particular Torre De Ugao",
    "iso:country":"ES",
    "sg:address":"Calle de Particular Torre De Ugao, 2",
    "sg:city":"Ugao-miraballes",
    "sg:orig_category":"Lencer\u00cda Femenina, Corseter\u00cda, Trajes De Ba\u00d1o (al Por Menor)",
    "sg:phone":"+34 946 33 30 39",
    "sg:postcode":"48490",
    "sg:province":"Vizcaya",
    "wof:name":"Argi\u00f1e Garay Gonzalez",
    "wof:placetype":"venue"
},
  "geometry": {"coordinates":[-2.9027614594,43.1808357239],"type":"Point"}
}