{
  "type": "Feature",
  "properties": {
    "iso:country":"ES",
    "sg:address":"Calle de Bolta\u00d1a, 3",
    "sg:city":"Huesca",
    "sg:orig_category":"Zapater\u00cdas",
    "sg:phone":"+34 974 21 84 52",
    "sg:postcode":"22002",
    "sg:province":"Huesca",
    "wof:name":"Generelo Lanaspa Maria Dolores",
    "wof:placetype":"venue"
},
  "geometry": {"coordinates":[-0.4072049856,42.1354598999],"type":"Point"}
}