{
  "type": "Feature",
  "properties": {
    "addr:full":"Calle de Periodista Matias Mendez Vellido, 1 Granada Granada 18015",
    "addr:housenumber":"1",
    "addr:postcode":"18015",
    "addr:street":"Calle De Periodista Matias Mendez Vellido",
    "iso:country":"ES",
    "sg:address":"Calle de Periodista Matias Mendez Vellido, 1",
    "sg:city":"Granada",
    "sg:orig_category":"Asesor\u00cda Para La Organizaci\u00d3n Y Gesti\u00d3n Del Transporte",
    "sg:phone":"+34 958 16 28 78",
    "sg:postcode":"18015",
    "sg:province":"Granada",
    "wof:name":"Rodriguez Fernandez Trinidad",
    "wof:placetype":"venue"
},
  "geometry": {"coordinates":[-3.6213240623,37.1931610107],"type":"Point"}
}