{
  "type": "Feature",
  "properties": {
    "iso:country":"ES",
    "sg:address":"Calle de Hortaleza, 48",
    "sg:city":"Madrid",
    "sg:orig_category":"Arquitectos",
    "sg:phone":"+34 915 32 16 50",
    "sg:postcode":"28004",
    "sg:province":"Madrid",
    "wof:name":"Iruretagoyena Serna Jose Luis",
    "wof:placetype":"venue"
},
  "geometry": {"coordinates":[-3.6994130611,40.4223480225],"type":"Point"}
}