{
  "type": "Feature",
  "properties": {
    "addr:full":"Calle de Maria Zambrano, 35 Zaragoza Zaragoza 50018",
    "addr:housenumber":"35",
    "addr:postcode":"50018",
    "addr:street":"Calle De Maria Zambrano",
    "iso:country":"ES",
    "sg:address":"Calle de Maria Zambrano, 35",
    "sg:city":"Zaragoza",
    "sg:orig_category":"Art\u00cdculos De Regalo (al Por Menor)",
    "sg:phone":"+34 976 51 37 15",
    "sg:postcode":"50018",
    "sg:province":"Zaragoza",
    "wof:name":"Natura Gameto S.l.",
    "wof:placetype":"venue"
},
  "geometry": {"coordinates":[-0.8901329041,41.6717720032],"type":"Point"}
}