{
  "type": "Feature",
  "properties": {
    "addr:full":"Calle de Virgen De Los Milagros, 85 Puerto De Santa Maria C\u00e1diz 11500",
    "addr:housenumber":"85",
    "addr:postcode":"11500",
    "addr:street":"Calle De Virgen De Los Milagros;Ca\u0301Diz",
    "iso:country":"ES",
    "sg:address":"Calle de Virgen De Los Milagros, 85",
    "sg:city":"Puerto De Santa Maria",
    "sg:orig_category":"Psic\u00d3logos",
    "sg:phone":"+34 956 85 72 01",
    "sg:postcode":"11500",
    "sg:province":"C\u00e1diz",
    "wof:name":"Gomez Zaragoza Pedro",
    "wof:placetype":"venue"
},
  "geometry": {"coordinates":[-6.2250027657,36.5994110107],"type":"Point"}
}