{
  "type": "Feature",
  "properties": {
    "addr:full":"Carr Pere Iv, 3 Xativa Valencia 46800",
    "addr:housenumber":"3",
    "addr:postcode":"46800",
    "addr:street":"Carr Pere Iv",
    "iso:country":"ES",
    "sg:address":"Carr Pere Iv, 3",
    "sg:city":"Xativa",
    "sg:orig_category":"Chapister\u00cda",
    "sg:phone":"+34 962 27 27 14",
    "sg:postcode":"46800",
    "sg:province":"Valencia",
    "wof:name":"Pino Cardona Raul",
    "wof:placetype":"venue"
},
  "geometry": {"coordinates":[-0.5221599936,38.9913368225],"type":"Point"}
}