{
  "type": "Feature",
  "properties": {
    "iso:country":"ES",
    "sg:address":"Av Joan Maragall, 3",
    "sg:city":"Tossa",
    "sg:orig_category":"Electricidad: Instaladores",
    "sg:phone":"+34 972 34 07 99",
    "sg:postcode":"17320",
    "sg:province":"Girona",
    "wof:name":"Riemar Proyectes I Instalacions S.l",
    "wof:placetype":"venue"
},
  "geometry": {"coordinates":[2.9316489697,41.7250785828],"type":"Point"}
}