{
  "type": "Feature",
  "properties": {
    "addr:full":"Calle de Iniesta, 4 Navas De Jorquera Albacete 02246",
    "addr:housenumber":"4",
    "addr:postcode":"02246",
    "addr:street":"Calle De Iniesta",
    "iso:country":"ES",
    "sg:address":"Calle de Iniesta, 4",
    "sg:city":"Navas De Jorquera",
    "sg:orig_category":"Cajas De Ahorro",
    "sg:phone":"+34 967 48 21 42",
    "sg:postcode":"02246",
    "sg:province":"Albacete",
    "wof:name":"Caja De Ahorros De Castilla La Mancha",
    "wof:placetype":"venue"
},
  "geometry": {"coordinates":[-1.7195099592,39.2802391052],"type":"Point"}
}