{
  "type": "Feature",
  "properties": {
    "addr:full":"Urb Pinares De Oromana, S/n Alcala Guadaira Sevilla 41500",
    "addr:housenumber":"s",
    "addr:postcode":"41500",
    "addr:street":"/ N",
    "iso:country":"ES",
    "sg:address":"Urb Pinares De Oromana, S/n",
    "sg:city":"Alcala Guadaira",
    "sg:orig_category":"Frutas Y Legumbres Frescas (al Por Mayor)",
    "sg:phone":"+34 955 68 63 86",
    "sg:postcode":"41500",
    "sg:province":"Sevilla",
    "wof:name":"Bernardo Herrera S.l.",
    "wof:placetype":"venue"
},
  "geometry": {"coordinates":[-5.8557419777,37.3193359375],"type":"Point"}
}