{
  "type": "Feature",
  "properties": {
    "iso:country":"ES",
    "sg:address":"Calle de Ermita, 21",
    "sg:city":"Calpe",
    "sg:orig_category":"Navegaci\u00d3n (equipos Fluviales)",
    "sg:phone":"+34 965 83 07 90",
    "sg:postcode":"03710",
    "sg:province":"Alicante",
    "wof:name":"Solivelles Rosello Jose Luis",
    "wof:placetype":"venue"
},
  "geometry": {"coordinates":[0.0424071997,38.6438560486],"type":"Point"}
}