{
  "type": "Feature",
  "properties": {
    "addr:full":"Calle de Hospital, 3 Valencia Valencia 46001",
    "addr:housenumber":"3",
    "addr:postcode":"46001",
    "addr:street":"Calle De Hospital",
    "iso:country":"ES",
    "sg:address":"Calle de Hospital, 3",
    "sg:city":"Valencia",
    "sg:orig_category":"Bibliotecas, Mediatecas",
    "sg:phone":"+34 963 94 12 74",
    "sg:postcode":"46001",
    "sg:province":"Valencia",
    "wof:name":"Comercial Igove 94 S.l.",
    "wof:placetype":"venue"
},
  "geometry": {"coordinates":[-0.380708009,39.4709358215],"type":"Point"}
}