{
  "type": "Feature",
  "properties": {
    "addr:full":"Ctra. General, 36 Tamames Salamanca 37600",
    "addr:housenumber":"36",
    "addr:postcode":"37600",
    "addr:street":"Ctra. General",
    "iso:country":"ES",
    "sg:address":"Ctra. General, 36",
    "sg:city":"Tamames",
    "sg:orig_category":"Alimentaci\u00d3n General (al Por Menor)",
    "sg:phone":"+34 923 44 95 93",
    "sg:postcode":"37600",
    "sg:province":"Salamanca",
    "wof:name":"Productos Ibericos Gomez S.a.",
    "wof:placetype":"venue"
},
  "geometry": {"coordinates":[-6.1087841988,40.656791687],"type":"Point"}
}