{
  "type": "Feature",
  "properties": {
    "addr:full":"Carrer de Ample, 8 Reus Tarragona 43202",
    "addr:housenumber":"8",
    "addr:postcode":"43202",
    "addr:street":"Carrer De Ample",
    "iso:country":"ES",
    "sg:address":"Carrer de Ample, 8",
    "sg:city":"Reus",
    "sg:orig_category":"Abogados",
    "sg:phone":"+34 977 31 93 70",
    "sg:postcode":"43202",
    "sg:province":"Tarragona",
    "wof:name":"Sabate Vidal Francesc",
    "wof:placetype":"venue"
},
  "geometry": {"coordinates":[1.1049560308,41.1581306458],"type":"Point"}
}