{
  "type": "Feature",
  "properties": {
    "addr:full":"Joan Carles I, 3 Batea Tarragona 43786",
    "addr:postcode":"43786",
    "addr:street":"Joan",
    "iso:country":"ES",
    "sg:address":"Joan Carles I, 3",
    "sg:city":"Batea",
    "sg:orig_category":"Alimentaci\u00d3n General (al Por Menor)",
    "sg:phone":"+34 977 43 00 07",
    "sg:postcode":"43786",
    "sg:province":"Tarragona",
    "wof:name":"Maijo Tramunt Juan Bautista",
    "wof:placetype":"venue"
},
  "geometry": {"coordinates":[0.3124229908,41.0934448242],"type":"Point"}
}