{
  "type": "Feature",
  "properties": {
    "addr:full":"Calle de Valencia, 2 Orihuela Alicante 03300",
    "addr:housenumber":"2",
    "addr:postcode":"03300",
    "addr:street":"Calle De Valencia",
    "iso:country":"ES",
    "sg:address":"Calle de Valencia, 2",
    "sg:city":"Orihuela",
    "sg:orig_category":"Perfumer\u00cda (al Por Menor)",
    "sg:phone":"+34 965 30 62 72",
    "sg:postcode":"03300",
    "sg:province":"Alicante",
    "wof:name":"Hijos De Vicente Masip C.b.",
    "wof:placetype":"venue"
},
  "geometry": {"coordinates":[-0.944806993,38.0816345215],"type":"Point"}
}