{
  "type": "Feature",
  "properties": {
    "iso:country":"ES",
    "sg:address":"Calle de Embajadores, 208",
    "sg:city":"Madrid",
    "sg:orig_category":"Contables",
    "sg:phone":"+34 914 68 40 49",
    "sg:postcode":"28045",
    "sg:province":"Madrid",
    "wof:name":"Casas Paredes Concepcion",
    "wof:placetype":"venue"
},
  "geometry": {"coordinates":[-3.6928958893,40.3908805847],"type":"Point"}
}