{
  "type": "Feature",
  "properties": {
    "addr:full":"Calle de Rafael Herrera, 9 Madrid Madrid 28036",
    "addr:housenumber":"9",
    "addr:postcode":"madrid;28036",
    "addr:street":"Calle De Rafael Herrera",
    "iso:country":"ES",
    "sg:address":"Calle de Rafael Herrera, 9",
    "sg:city":"Madrid",
    "sg:orig_category":"Inmobiliaria (agencias)",
    "sg:phone":"+34 913 14 23 04",
    "sg:postcode":"28036",
    "sg:province":"Madrid",
    "wof:name":"General De Asistencia Proyectos E Inversiones S.l.",
    "wof:placetype":"venue"
},
  "geometry": {"coordinates":[-3.6848549843,40.4678230286],"type":"Point"}
}