{
  "type": "Feature",
  "properties": {
    "iso:country":"ES",
    "sg:address":"Av Fortalesa, 1",
    "sg:city":"Hostalric",
    "sg:orig_category":"Alquiler De V\u00cddeo",
    "sg:phone":"+34 972 86 49 16",
    "sg:postcode":"17450",
    "sg:province":"Girona",
    "wof:name":"Sauri Tarres Albert",
    "wof:placetype":"venue"
},
  "geometry": {"coordinates":[2.6267089844,41.745300293],"type":"Point"}
}