{
  "type": "Feature",
  "properties": {
    "addr:full":"Carrer de Monlau, 41 Barcelona Barcelona 08027",
    "addr:housenumber":"41",
    "addr:postcode":"08027",
    "addr:street":"Carrer De Monlau",
    "iso:country":"ES",
    "sg:address":"Carrer de Monlau, 41",
    "sg:city":"Barcelona",
    "sg:orig_category":"Cervecer\u00cdas",
    "sg:phone":"+34 933 52 13 74",
    "sg:postcode":"08027",
    "sg:province":"Barcelona",
    "wof:name":"Ye  Jianping",
    "wof:placetype":"venue"
},
  "geometry": {"coordinates":[2.1902439594,41.4250869751],"type":"Point"}
}