{
  "type": "Feature",
  "properties": {
    "addr:full":"Calle de Libertad, 1 Sestao Vizcaya 48910",
    "addr:housenumber":"1",
    "addr:postcode":"48910",
    "addr:street":"Calle De Libertad",
    "iso:country":"ES",
    "sg:address":"Calle de Libertad, 1",
    "sg:city":"Sestao",
    "sg:orig_category":"T\u00c9cnicos Veterinarios",
    "sg:phone":"+34 944 06 30 66",
    "sg:postcode":"48910",
    "sg:province":"Vizcaya",
    "wof:name":"Agustin Regulez Barriocanal",
    "wof:placetype":"venue"
},
  "geometry": {"coordinates":[-3.0089359283,43.3087768555],"type":"Point"}
}