{
  "type": "Feature",
  "properties": {
    "iso:country":"ES",
    "sg:address":"Calle de Juan De Soto, 9",
    "sg:city":"Alcala Henares",
    "sg:orig_category":"Peluquer\u00cdas, Peluquer\u00cda Mixta",
    "sg:phone":"+34 918 83 03 54",
    "sg:postcode":"28804",
    "sg:province":"Madrid",
    "wof:name":"Lozoya Y Delgado C.b.",
    "wof:placetype":"venue"
},
  "geometry": {"coordinates":[-3.3533790112,40.4843902588],"type":"Point"}
}