{
  "type": "Feature",
  "properties": {
    "iso:country":"ES",
    "sg:address":"Calle de Fruela, 2",
    "sg:city":"Oviedo",
    "sg:orig_category":"Asesor\u00cda Fiscal Y Jur\u00cddica",
    "sg:phone":"+34 984 05 19 36",
    "sg:postcode":"33007",
    "sg:province":"Asturias",
    "wof:name":"Global Tax 5 Asesores S.l.",
    "wof:placetype":"venue"
},
  "geometry": {"coordinates":[-5.8461732864,43.3606681824],"type":"Point"}
}