{
  "type": "Feature",
  "properties": {
    "iso:country":"ES",
    "sg:address":"Calle de Zorita, 2",
    "sg:city":"Castellon",
    "sg:orig_category":"Bancos",
    "sg:phone":"+34 964 24 17 84",
    "sg:postcode":"12006",
    "sg:province":"Castell\u00f3n",
    "wof:name":"Banco Popular Espa\u00f1ol",
    "wof:placetype":"venue"
},
  "geometry": {"coordinates":[-0.1292939931,40.0168533325],"type":"Point"}
}