{
  "type": "Feature",
  "properties": {
    "addr:full":"Calle de Tomas Redondo, 1 Madrid Madrid 28033",
    "addr:housenumber":"1",
    "addr:postcode":"28033",
    "addr:street":"Calle De Tomas Redondo",
    "iso:country":"ES",
    "sg:address":"Calle de Tomas Redondo, 1",
    "sg:city":"Madrid",
    "sg:orig_category":"Agencias Y Asesores De Publicidad",
    "sg:phone":"+34 913 81 81 18",
    "sg:postcode":"28033",
    "sg:province":"Madrid",
    "wof:name":"Publivista Rotulos S.l.",
    "wof:placetype":"venue"
},
  "geometry": {"coordinates":[-3.6297280788,40.4726524353],"type":"Point"}
}