{
  "type": "Feature",
  "properties": {
    "addr:full":"Calle de Juan Mambrilla, 19 Valladolid Valladolid 47003",
    "addr:housenumber":"19",
    "addr:postcode":"47003",
    "addr:street":"Calle De Juan Mambrilla",
    "iso:country":"ES",
    "sg:address":"Calle de Juan Mambrilla, 19",
    "sg:city":"Valladolid",
    "sg:orig_category":"Empresarios",
    "sg:phone":"+34 983 39 67 87",
    "sg:postcode":"47003",
    "sg:province":"Valladolid",
    "wof:name":"Fundacion Cruz De Los Angeles",
    "wof:placetype":"venue"
},
  "geometry": {"coordinates":[-4.7197051048,41.6534881592],"type":"Point"}
}