{
  "type": "Feature",
  "properties": {
    "addr:full":"Casa Parinou, S/n Llutxent Valencia 46838",
    "addr:housenumber":"s",
    "addr:postcode":"46838",
    "addr:street":"/ N",
    "iso:country":"ES",
    "sg:address":"Casa Parinou, S/n",
    "sg:city":"Llutxent",
    "sg:orig_category":"Producci\u00d3n, Venta De Productos De Agricultura Biol\u00d3gica",
    "sg:phone":"+34 962 29 40 64",
    "sg:postcode":"46838",
    "sg:province":"Valencia",
    "wof:name":"Sociedad Agraria De Transformacion Ciscar 4470",
    "wof:placetype":"venue"
},
  "geometry": {"coordinates":[-0.3564560115,38.9408912659],"type":"Point"}
}