{
  "type": "Feature",
  "properties": {
    "addr:full":"Carrer de Lluis Companys, 2 Berga-ciudad Barcelona 08600",
    "addr:housenumber":"2",
    "addr:postcode":"08600",
    "addr:street":"Carrer De Lluis Companys;Barcelona",
    "iso:country":"ES",
    "sg:address":"Carrer de Lluis Companys, 2",
    "sg:city":"Berga-ciudad",
    "sg:orig_category":"Cajas De Ahorro",
    "sg:phone":"+34 938 21 17 51",
    "sg:postcode":"08600",
    "sg:province":"Barcelona",
    "wof:name":"Caixa D'estalvis I Pensions De Barcelona",
    "wof:placetype":"venue"
},
  "geometry": {"coordinates":[1.8445719481,42.0975227356],"type":"Point"}
}