{
  "type": "Feature",
  "properties": {
    "addr:full":"Avda Principes De Espa\u00d1a, 80 Rota C\u00e1diz 11520",
    "addr:housenumber":"80",
    "addr:postcode":"11520",
    "addr:street":"Avda Principes De Espan\u0303A;Ca\u0301Diz",
    "iso:country":"ES",
    "sg:address":"Avda Principes De Espa\u00d1a, 80",
    "sg:city":"Rota",
    "sg:orig_category":"Comercio De Cuadros, L\u00c1minas Y Reproducciones De Obras De Arte",
    "sg:phone":"+34 956 81 10 39",
    "sg:postcode":"11520",
    "sg:province":"C\u00e1diz",
    "wof:name":"Pacheco Fuentes Cayetano",
    "wof:placetype":"venue"
},
  "geometry": {"coordinates":[-6.3673138618,36.624294281],"type":"Point"}
}