{
  "type": "Feature",
  "properties": {
    "iso:country":"ES",
    "sg:address":"Calle de Nueva, S/n",
    "sg:city":"Carboneras",
    "sg:orig_category":"Ense\u00d1anza, Formaci\u00d3n Profesional: Aprendizaje",
    "sg:phone":"+34 950 13 08 74",
    "sg:postcode":"04140",
    "sg:province":"Almer\u00eda",
    "wof:name":"Junta De Andalucia-consejeria De Cultura",
    "wof:placetype":"venue"
},
  "geometry": {"coordinates":[-1.8940739632,36.9966659546],"type":"Point"}
}