{
  "type": "Feature",
  "properties": {
    "addr:full":"Rua Jose Antonio, 24 Ordes La Coru\u00f1a 15680",
    "addr:housenumber":"24",
    "addr:postcode":"15680",
    "addr:street":"Rua Jose Antonio;La Corun\u0303A",
    "iso:country":"ES",
    "sg:address":"Rua Jose Antonio, 24",
    "sg:city":"Ordes",
    "sg:orig_category":"Lanas (al Por Mayor)",
    "sg:phone":"+34 981 68 14 20",
    "sg:postcode":"15680",
    "sg:province":"La Coru\u00f1a",
    "wof:name":"Cooperativa Cibegama S.c.l.",
    "wof:placetype":"venue"
},
  "geometry": {"coordinates":[-8.4081506729,43.0758972168],"type":"Point"}
}