{
  "type": "Feature",
  "properties": {
    "iso:country":"ES",
    "sg:address":"Carr Paseo Industria, 9",
    "sg:city":"Canals",
    "sg:orig_category":"Agentes Generales De Seguros",
    "sg:phone":"+34 962 24 12 19",
    "sg:postcode":"46650",
    "sg:province":"Valencia",
    "wof:name":"Gomez Grandal Jesus Antonio",
    "wof:placetype":"venue"
},
  "geometry": {"coordinates":[-0.588168025,38.9644203186],"type":"Point"}
}