{
  "type": "Feature",
  "properties": {
    "addr:full":"Pda. Cort, 9 Lleida Lleida 25005",
    "addr:housenumber":"9",
    "addr:postcode":"25005",
    "addr:street":"Pda. Cort",
    "iso:country":"ES",
    "sg:address":"Pda. Cort, 9",
    "sg:city":"Lleida",
    "sg:orig_category":"Cerrajer\u00cda, Ferrallista",
    "sg:phone":"+34 973 24 14 48",
    "sg:postcode":"25005",
    "sg:province":"Lleida",
    "wof:name":"As-metal S.c.p.",
    "wof:placetype":"venue"
},
  "geometry": {"coordinates":[0.6322615147,41.6268920898],"type":"Point"}
}