{
  "type": "Feature",
  "properties": {
    "addr:full":"Calle de Arguelles, 23 Arriondas Asturias 33540",
    "addr:housenumber":"23",
    "addr:postcode":"33540",
    "addr:street":"Calle De Arguelles",
    "iso:country":"ES",
    "sg:address":"Calle de Arguelles, 23",
    "sg:city":"Arriondas",
    "sg:orig_category":"Electricidad: Instaladores",
    "sg:phone":"+34 985 84 05 43",
    "sg:postcode":"33540",
    "sg:province":"Asturias",
    "wof:name":"Ordiales Vega Jose Luis",
    "wof:placetype":"venue"
},
  "geometry": {"coordinates":[-5.1876268387,43.3882408142],"type":"Point"}
}