{
  "type": "Feature",
  "properties": {
    "addr:full":"Plaz Provincia, 1 Sodeto Huesca 22212",
    "addr:housenumber":"1",
    "addr:postcode":"22212",
    "addr:street":"Provincia",
    "iso:country":"ES",
    "sg:address":"Plaz Provincia, 1",
    "sg:city":"Sodeto",
    "sg:orig_category":"Centros De Educaci\u00d3n Especial",
    "sg:phone":"+34 974 39 54 96",
    "sg:postcode":"22212",
    "sg:province":"Huesca",
    "wof:name":"Ayuntamiento De Alberuela De Tubo",
    "wof:placetype":"venue"
},
  "geometry": {"coordinates":[-0.2516515851,41.8904037476],"type":"Point"}
}