{
  "type": "Feature",
  "properties": {
    "iso:country":"ES",
    "sg:address":"Calle de Caldas, 48",
    "sg:city":"Jerez De La Frontera",
    "sg:orig_category":"Inmobiliaria (agencias)",
    "sg:phone":"+34 956 31 76 18",
    "sg:postcode":"11405",
    "sg:province":"C\u00e1diz",
    "wof:name":"Mayolin Vazquez Manuel",
    "wof:placetype":"venue"
},
  "geometry": {"coordinates":[-6.1350564957,36.6943473816],"type":"Point"}
}