{
  "type": "Feature",
  "properties": {
    "iso:country":"ES",
    "sg:address":"Avda Carlota Alessandri, 31",
    "sg:city":"Torremolinos",
    "sg:orig_category":"Hospitales",
    "sg:phone":"+34 952 37 49 89",
    "sg:postcode":"29620",
    "sg:province":"M\u00e1laga",
    "wof:name":"Hospital De Benalmadena Xanit S.l.",
    "wof:placetype":"venue"
},
  "geometry": {"coordinates":[-4.5046401024,36.612323761],"type":"Point"}
}