{
  "type": "Feature",
  "properties": {
    "addr:full":"Calle de Baltasar De Alcazar, 17 San Jose Rinconada Sevilla 41300",
    "addr:housenumber":"17",
    "addr:postcode":"41300",
    "addr:street":"Calle De Baltasar De Alcazar",
    "iso:country":"ES",
    "sg:address":"Calle de Baltasar De Alcazar, 17",
    "sg:city":"San Jose Rinconada",
    "sg:orig_category":"Guarder\u00cdas",
    "sg:phone":"+34 954 79 11 72",
    "sg:postcode":"41300",
    "sg:province":"Sevilla",
    "wof:name":"Escuela Infantil Burbuja Uncala Martin S.c.",
    "wof:placetype":"venue"
},
  "geometry": {"coordinates":[-5.945579052,37.486125946],"type":"Point"}
}