{
  "type": "Feature",
  "properties": {
    "addr:full":"Calle de Bugarra, 51 Pedralba Valencia 46164",
    "addr:housenumber":"51",
    "addr:postcode":"46164",
    "addr:street":"Calle De Bugarra",
    "iso:country":"ES",
    "sg:address":"Calle de Bugarra, 51",
    "sg:city":"Pedralba",
    "sg:orig_category":"Contenedores (mercanc\u00cdas)",
    "sg:phone":"+34 962 70 72 07",
    "sg:postcode":"46164",
    "sg:province":"Valencia",
    "wof:name":"Rodrigo Cervera Enrique",
    "wof:placetype":"venue"
},
  "geometry": {"coordinates":[-0.7295199037,39.6059761047],"type":"Point"}
}