{
  "type": "Feature",
  "properties": {
    "iso:country":"ES",
    "sg:address":"Carr Socors, 39",
    "sg:city":"Felanitx",
    "sg:orig_category":"Molduras, Junquillos, Listones Y Molduras Perforadas",
    "sg:phone":"+34 971 82 72 68",
    "sg:postcode":"07200",
    "sg:province":"Islas Baleares",
    "wof:name":"Radi  Ahmed",
    "wof:placetype":"venue"
},
  "geometry": {"coordinates":[3.1469929218,39.4749412537],"type":"Point"}
}