{
  "type": "Feature",
  "properties": {
    "addr:full":"Calle de Fermin Caballero, 5 Madrid Madrid 28034",
    "addr:housenumber":"5",
    "addr:postcode":"28034",
    "addr:street":"Calle De Fermin Caballero",
    "iso:country":"ES",
    "sg:address":"Calle de Fermin Caballero, 5",
    "sg:city":"Madrid",
    "sg:orig_category":"M\u00c9dicos: Estomatolog\u00cda",
    "sg:phone":"+34 917 38 26 61",
    "sg:postcode":"28034",
    "sg:province":"Madrid",
    "wof:name":"Pujols Baez Isabel Cristina",
    "wof:placetype":"venue"
},
  "geometry": {"coordinates":[-3.6993489265,40.4869003296],"type":"Point"}
}