{
  "type": "Feature",
  "properties": {
    "iso:country":"ES",
    "sg:address":"Cra. Vall D'aran, S/n",
    "sg:city":"Lleida",
    "sg:orig_category":"Negocio De Madera",
    "sg:phone":"+34 973 24 72 06",
    "sg:postcode":"25091",
    "sg:province":"Lleida",
    "wof:name":"Alberch S.a.",
    "wof:placetype":"venue"
},
  "geometry": {"coordinates":[0.6079785228,41.665512085],"type":"Point"}
}