{
  "type": "Feature",
  "properties": {
    "iso:country":"ES",
    "sg:address":"Carrer de Mur, 16",
    "sg:city":"Martorell",
    "sg:orig_category":"Alquiler De Veh\u00cdculos: Turismos Y Utilitarios",
    "sg:phone":"+34 937 75 11 47",
    "sg:postcode":"08760",
    "sg:province":"Barcelona",
    "wof:name":"Mur Lloguer S.l.",
    "wof:placetype":"venue"
},
  "geometry": {"coordinates":[1.9286949635,41.4735527039],"type":"Point"}
}