{
  "type": "Feature",
  "properties": {
    "iso:country":"ES",
    "sg:address":"Avgd Beniparrell, S/n",
    "sg:city":"Silla",
    "sg:orig_category":"Fabricaci\u00d3n De Muebles",
    "sg:phone":"+34 961 21 30 22",
    "sg:postcode":"46460",
    "sg:province":"Valencia",
    "wof:name":"Artidis Mobiliario S.l.",
    "wof:placetype":"venue"
},
  "geometry": {"coordinates":[-0.4090240002,39.3727493286],"type":"Point"}
}