{
  "type": "Feature",
  "properties": {
    "addr:full":"Carrer de Santiago Rusi\u00d1ol, 4 S. Quirze Valles Barcelona 08192",
    "addr:housenumber":"4",
    "addr:postcode":"08192",
    "addr:street":"Carrer De Santiago Rusin\u0303Ol;Barcelona",
    "iso:country":"ES",
    "sg:address":"Carrer de Santiago Rusi\u00d1ol, 4",
    "sg:city":"S. Quirze Valles",
    "sg:orig_category":"Inmobiliaria (agencias)",
    "sg:phone":"+34 937 21 90 50",
    "sg:postcode":"08192",
    "sg:province":"Barcelona",
    "wof:name":"Lasbru S.l.",
    "wof:placetype":"venue"
},
  "geometry": {"coordinates":[2.0846719742,41.5308647156],"type":"Point"}
}