{
  "type": "Feature",
  "properties": {
    "addr:full":"Calle de Venerables, 2 Burgos Burgos 09003",
    "addr:housenumber":"2",
    "addr:postcode":"09003",
    "addr:street":"Calle De Venerables",
    "iso:country":"ES",
    "sg:address":"Calle de Venerables, 2",
    "sg:city":"Burgos",
    "sg:orig_category":"Ingeniero",
    "sg:phone":"+34 947 22 81 04",
    "sg:postcode":"09003",
    "sg:province":"Burgos",
    "wof:name":"Rivadeneira Garcia Belen",
    "wof:placetype":"venue"
},
  "geometry": {"coordinates":[-3.6998100281,42.3410835266],"type":"Point"}
}