{
  "type": "Feature",
  "properties": {
    "iso:country":"ES",
    "sg:address":"Calle de Progreso, S/n",
    "sg:city":"Puebla Calzada",
    "sg:orig_category":"Empresas De Limpieza",
    "sg:phone":"+34 924 45 69 48",
    "sg:postcode":"06490",
    "sg:province":"Badajoz",
    "wof:name":"Servicios Limpieza Fersega S.l.",
    "wof:placetype":"venue"
},
  "geometry": {"coordinates":[-6.6282038689,38.8885383606],"type":"Point"}
}