{
  "type": "Feature",
  "properties": {
    "addr:full":"Uistin Kalea-calle Uistin, 13 Lasarte Guip\u00f9zcoa 20160",
    "addr:housenumber":"13",
    "addr:postcode":"20160",
    "addr:street":"Uistin;Guipu\u0300Zcoa",
    "iso:country":"ES",
    "sg:address":"Uistin Kalea-calle Uistin, 13",
    "sg:city":"Lasarte",
    "sg:orig_category":"Aparatos E Instalaci\u00d3n De Regad\u00cdos",
    "sg:phone":"+34 943 36 61 04",
    "sg:postcode":"20160",
    "sg:province":"Guip\u00f9zcoa",
    "wof:name":"Ganuza Gonzalez Alberto",
    "wof:placetype":"venue"
},
  "geometry": {"coordinates":[-2.020414114,43.2698173523],"type":"Point"}
}