{
  "type": "Feature",
  "properties": {
    "iso:country":"ES",
    "sg:address":"Calle de Donantes De Sangre, 3",
    "sg:city":"Agoncillo",
    "sg:orig_category":"Empresarios",
    "sg:phone":"+34 941 43 10 34",
    "sg:postcode":"26509",
    "sg:province":"La Rioja",
    "wof:name":"Sanchez Gutierrez Jose Antonio",
    "wof:placetype":"venue"
},
  "geometry": {"coordinates":[-2.2521352768,42.4356575012],"type":"Point"}
}