{
  "type": "Feature",
  "properties": {
    "iso:country":"ES",
    "sg:address":"Calle de Somera, 35",
    "sg:city":"Bilbao",
    "sg:orig_category":"Molduras, Junquillos, Listones Y Molduras Perforadas",
    "sg:phone":"+34 944 16 99 03",
    "sg:postcode":"48005",
    "sg:province":"Vizcaya",
    "wof:name":"Ul Hassam Sied",
    "wof:placetype":"venue"
},
  "geometry": {"coordinates":[-2.9227778912,43.2566566467],"type":"Point"}
}