{
  "type": "Feature",
  "properties": {
    "iso:country":"ES",
    "sg:address":"Estd Xunqueira (de), S/n",
    "sg:city":"Allariz",
    "sg:orig_category":"Muebles Y Accesorios Para Cocinas Y Cuartos De Ba\u00d1o (al Por Menor)",
    "sg:phone":"+34 988 44 03 64",
    "sg:postcode":"32660",
    "sg:province":"Ourense",
    "wof:name":"Exclusivas Servizel S.l.",
    "wof:placetype":"venue"
},
  "geometry": {"coordinates":[-7.798304081,42.1901702881],"type":"Point"}
}