{
  "type": "Feature",
  "properties": {
    "iso:country":"ES",
    "sg:address":"Calle de Xose Neira Vilas, 44",
    "sg:city":"Vila Cruces",
    "sg:orig_category":"Centros De Educaci\u00d3n Especial",
    "sg:phone":"+34 986 58 21 00",
    "sg:postcode":"36590",
    "sg:province":"Pontevedra",
    "wof:name":"Centro De Educacion Infantil E Primaria Nosa Se\u00f1ora Da Piedade",
    "wof:placetype":"venue"
},
  "geometry": {"coordinates":[-8.1684417725,42.7941474915],"type":"Point"}
}