{
  "type": "Feature",
  "properties": {
    "iso:country":"ES",
    "sg:address":"Avda Federico Anaya, 28",
    "sg:city":"Salamanca",
    "sg:orig_category":"Carnicer\u00cdas, Carnicer\u00cdas",
    "sg:phone":"+34 923 22 96 96",
    "sg:postcode":"37004",
    "sg:province":"Salamanca",
    "wof:name":"Jamonema S.l.",
    "wof:placetype":"venue"
},
  "geometry": {"coordinates":[-5.6566691399,40.9732780457],"type":"Point"}
}