{
  "type": "Feature",
  "properties": {
    "iso:country":"ES",
    "sg:address":"Pascual Andagoya(vaguada), 22",
    "sg:city":"Cartagena",
    "sg:orig_category":"Perreras, Pensiones Para Perros, Gatos Y Otros Animales",
    "sg:phone":"+34 968 51 53 00",
    "sg:postcode":"30393",
    "sg:province":"Murcia",
    "wof:name":"Lopez Perez Antonio",
    "wof:placetype":"venue"
},
  "geometry": {"coordinates":[-1.0475349426,37.6296386719],"type":"Point"}
}