{
  "type": "Feature",
  "properties": {
    "addr:full":"Parque Glez. Hontoria, S/n Jerez C\u00e1diz 11405",
    "addr:housenumber":"s / n",
    "addr:postcode":"11405",
    "iso:country":"ES",
    "sg:address":"Parque Glez. Hontoria, S/n",
    "sg:city":"Jerez",
    "sg:orig_category":"Ense\u00d1anza, Formaci\u00d3n Profesional: Aprendizaje",
    "sg:phone":"+34 956 18 41 20",
    "sg:postcode":"11405",
    "sg:province":"C\u00e1diz",
    "sg:website":"www.dipucadiz.es/ifeca",
    "wof:name":"Institucion Ferial De Cadiz",
    "wof:placetype":"venue"
},
  "geometry": {"coordinates":[-6.1005191803,36.7067260742],"type":"Point"}
}