{
  "type": "Feature",
  "properties": {
    "addr:full":"Calle de Miguel Hernandez, 11 Calahorra La Rioja 26500",
    "addr:housenumber":"11",
    "addr:postcode":"26500",
    "addr:street":"Calle De Miguel Hernandez",
    "iso:country":"ES",
    "sg:address":"Calle de Miguel Hernandez, 11",
    "sg:city":"Calahorra",
    "sg:orig_category":"Organizaciones Internacionales",
    "sg:phone":"+34 941 14 62 39",
    "sg:postcode":"26500",
    "sg:province":"La Rioja",
    "wof:name":"Caritas Diocesana",
    "wof:placetype":"venue"
},
  "geometry": {"coordinates":[-1.9653320312,42.3027114868],"type":"Point"}
}