{
  "type": "Feature",
  "properties": {
    "iso:country":"ES",
    "sg:address":"Calle de Joaquin Arroyo, 5",
    "sg:city":"Madrid",
    "sg:orig_category":"Centros Empresariales",
    "sg:phone":"+34 913 02 56 67",
    "sg:postcode":"28033",
    "sg:province":"Madrid",
    "wof:name":"Aicila 97 Sl",
    "wof:placetype":"venue"
},
  "geometry": {"coordinates":[-3.6651525497,40.468132019],"type":"Point"}
}