{
  "type": "Feature",
  "properties": {
    "addr:full":"Calle de General Moscardo, 30 Madrid Madrid 28020",
    "addr:housenumber":"30",
    "addr:postcode":"madrid;28020",
    "addr:street":"Calle De General Moscardo",
    "iso:country":"ES",
    "sg:address":"Calle de General Moscardo, 30",
    "sg:city":"Madrid",
    "sg:orig_category":"Peluqueros: De Se\u00d1oras",
    "sg:phone":"+34 915 34 61 45",
    "sg:postcode":"28020",
    "sg:province":"Madrid",
    "sg:website":"www.carlosgalico.com",
    "wof:name":"Carlos Galico S.l.",
    "wof:placetype":"venue"
},
  "geometry": {"coordinates":[-3.6964900494,40.4512481689],"type":"Point"}
}