{
  "type": "Feature",
  "properties": {
    "addr:full":"Calle de Jesus, 34 Palma Islas Baleares 07010",
    "addr:housenumber":"34",
    "addr:postcode":"07010",
    "addr:street":"Calle De Jesus",
    "iso:country":"ES",
    "sg:address":"Calle de Jesus, 34",
    "sg:city":"Palma",
    "sg:orig_category":"Inmobiliaria (agencias)",
    "sg:phone":"+34 971 29 06 86",
    "sg:postcode":"07010",
    "sg:province":"Islas Baleares",
    "wof:name":"Vimega Unidad De Gestion S.l.",
    "wof:placetype":"venue"
},
  "geometry": {"coordinates":[2.6304440498,39.5952682495],"type":"Point"}
}