{
  "type": "Feature",
  "properties": {
    "iso:country":"ES",
    "sg:address":"Carr Gran Bretanya, S/n",
    "sg:city":"Igualada",
    "sg:orig_category":"Vidrio, Fabricaci\u00d3n Y Comercio",
    "sg:phone":"+34 938 05 17 00",
    "sg:postcode":"08700",
    "sg:province":"Barcelona",
    "wof:name":"Vidres Igualada S.l.",
    "wof:placetype":"venue"
},
  "geometry": {"coordinates":[1.6278599501,41.5891952515],"type":"Point"}
}