{
  "type": "Feature",
  "properties": {
    "iso:country":"ES",
    "sg:address":"Calle de Apostoles, 3",
    "sg:city":"Catedral",
    "sg:orig_category":"Notarios",
    "sg:phone":"+34 968 22 59 50",
    "sg:postcode":"30001",
    "sg:province":"Murcia",
    "wof:name":"Navarro Aleman Francisco Luis",
    "wof:placetype":"venue"
},
  "geometry": {"coordinates":[-1.1298867464,37.9834747314],"type":"Point"}
}