{
  "type": "Feature",
  "properties": {
    "iso:country":"ES",
    "sg:address":"Plaz Fueros, 2",
    "sg:city":"Tudela",
    "sg:orig_category":"Molduras, Junquillos, Listones Y Molduras Perforadas",
    "sg:phone":"+34 948 82 10 54",
    "sg:postcode":"31500",
    "sg:province":"Navarra",
    "wof:name":"Ace\u00f1a Schames Boris",
    "wof:placetype":"venue"
},
  "geometry": {"coordinates":[-1.6053234339,42.0615234375],"type":"Point"}
}