{
  "type": "Feature",
  "properties": {
    "addr:full":"Plaz Capuchinos (de), 1 Cordoba C\u00f3rdoba 14001",
    "addr:postcode":"14001",
    "addr:street":"Co\u0301Rdoba",
    "iso:country":"ES",
    "sg:address":"Plaz Capuchinos (de), 1",
    "sg:city":"Cordoba",
    "sg:orig_category":"Abogados",
    "sg:phone":"+34 957 49 19 80",
    "sg:postcode":"14001",
    "sg:province":"C\u00f3rdoba",
    "wof:name":"A\u00f1on Aguilera Jesus",
    "wof:placetype":"venue"
},
  "geometry": {"coordinates":[-4.7769255638,37.8897323608],"type":"Point"}
}