{
  "type": "Feature",
  "properties": {
    "iso:country":"ES",
    "sg:address":"Avda Ramon Y Cajal, 40",
    "sg:city":"Candeleda",
    "sg:orig_category":"Farmacias",
    "sg:phone":"+34 920 38 00 29",
    "sg:postcode":"05480",
    "sg:province":"\u00c1vila",
    "wof:name":"Jose Miguel Rico Moreno Y Maria Dolores Rico Moreno Cdad.",
    "wof:placetype":"venue"
},
  "geometry": {"coordinates":[-5.2417287827,40.1541900635],"type":"Point"}
}