{
  "type": "Feature",
  "properties": {
    "iso:country":"ES",
    "sg:address":"Avda Nueve De Octubre, 82",
    "sg:city":"Puerto",
    "sg:orig_category":"Informaci\u00d3n Financiera Y Comercial",
    "sg:phone":"+34 962 69 82 82",
    "sg:postcode":"46520",
    "sg:province":"Valencia",
    "wof:name":"Mundi Sancho Desamparados",
    "wof:placetype":"venue"
},
  "geometry": {"coordinates":[-0.2246830016,39.6608695984],"type":"Point"}
}