{
  "type": "Feature",
  "properties": {
    "iso:country":"ES",
    "sg:address":"Carrer de Santa Fe, 2",
    "sg:city":"Rubi",
    "sg:orig_category":"Molduras, Junquillos, Listones Y Molduras Perforadas",
    "sg:phone":"+34 936 99 77 44",
    "sg:postcode":"08191",
    "sg:province":"Barcelona",
    "wof:name":"Moreno Pubil Daniel",
    "wof:placetype":"venue"
},
  "geometry": {"coordinates":[2.0348870754,41.4962005615],"type":"Point"}
}