{
  "type": "Feature",
  "properties": {
    "addr:full":"Calle de Gavilan, 32 Fuenlabrada Madrid 28946",
    "addr:housenumber":"32",
    "addr:postcode":"28946",
    "addr:street":"Calle De Gavilan",
    "iso:country":"ES",
    "sg:address":"Calle de Gavilan, 32",
    "sg:city":"Fuenlabrada",
    "sg:orig_category":"Tratamiento De Metales",
    "sg:phone":"+34 916 42 19 88",
    "sg:postcode":"28946",
    "sg:province":"Madrid",
    "sg:website":"www.la-red.com-impol",
    "wof:name":"Impol-impregnaciones De Metales S. A.",
    "wof:placetype":"venue"
},
  "geometry": {"coordinates":[-3.7650592327,40.2575302124],"type":"Point"}
}