{
  "type": "Feature",
  "properties": {
    "addr:full":"Avda Salazar Y Torres, 4 Almazan Soria 42200",
    "addr:housenumber":"4",
    "addr:postcode":"42200",
    "addr:street":"Avda Salazar Y Torres",
    "iso:country":"ES",
    "sg:address":"Avda Salazar Y Torres, 4",
    "sg:city":"Almazan",
    "sg:orig_category":"Bazares, Art\u00cdculos De Limpieza Y De Cocina (al Por Menor)",
    "sg:phone":"+34 975 30 05 13",
    "sg:postcode":"42200",
    "sg:province":"Soria",
    "wof:name":"Wu  Qiangwei",
    "wof:placetype":"venue"
},
  "geometry": {"coordinates":[-2.5310382843,41.4853248596],"type":"Point"}
}