{
  "type": "Feature",
  "properties": {
    "addr:full":"Calle de Herrerias, 8 Montoro C\u00f3rdoba 14600",
    "addr:housenumber":"8",
    "addr:postcode":"14600",
    "addr:street":"Calle De Herrerias;Co\u0301Rdoba",
    "iso:country":"ES",
    "sg:address":"Calle de Herrerias, 8",
    "sg:city":"Montoro",
    "sg:classifiers":[
        {
            "category":"Autos & Motor Vehicles",
            "subcategory":"Automobile Sales",
            "type":"Retail Goods"
        }
    ],
    "sg:phone":"+34 957 16 01 95",
    "sg:postcode":"14600",
    "sg:province":"C\u00f3rdoba",
    "wof:name":"Mateo Calero Ruano Y Jose Antonio Fernandez Lopez S. Cv.",
    "wof:placetype":"venue"
},
  "geometry": {"coordinates":[-4.3825659752,38.0229682922],"type":"Point"}
}