{
  "type": "Feature",
  "properties": {
    "addr:full":"Carrer de L'art, 54 Barcelona Barcelona 08041",
    "addr:housenumber":"54",
    "addr:postcode":"08041",
    "addr:street":"Carrer De L'Art",
    "iso:country":"ES",
    "sg:address":"Carrer de L'art, 54",
    "sg:city":"Barcelona",
    "sg:orig_category":"Confecci\u00d3n De Trajes Para Se\u00d1oras",
    "sg:phone":"+34 933 47 53 44",
    "sg:postcode":"08041",
    "sg:province":"Barcelona",
    "wof:name":"Daty's S.l.",
    "wof:placetype":"venue"
},
  "geometry": {"coordinates":[2.1764893532,41.4201126099],"type":"Point"}
}