{
  "type": "Feature",
  "properties": {
    "addr:full":"Carr Arcipreste Vila, 16 Moncada Valencia 46113",
    "addr:housenumber":"16",
    "addr:postcode":"46113",
    "addr:street":"Carr Arcipreste Vila",
    "iso:country":"ES",
    "sg:address":"Carr Arcipreste Vila, 16",
    "sg:city":"Moncada",
    "sg:orig_category":"Cursos Particulares, Asistencia Escolar",
    "sg:phone":"+34 961 39 06 23",
    "sg:postcode":"46113",
    "sg:province":"Valencia",
    "wof:name":"Fort Fenollosa Francisco",
    "wof:placetype":"venue"
},
  "geometry": {"coordinates":[-0.3899190128,39.546131134],"type":"Point"}
}