{
  "type": "Feature",
  "properties": {
    "addr:full":"Pla\u00c7 Josep Irla I Bosch, 3 Girona Girona 17003",
    "addr:housenumber":"3",
    "addr:postcode":"17003",
    "addr:street":"Josep Irla I Bosch",
    "iso:country":"ES",
    "sg:address":"Pla\u00c7 Josep Irla I Bosch, 3",
    "sg:city":"Girona",
    "sg:orig_category":"Abogados",
    "sg:phone":"+34 972 21 55 67",
    "sg:postcode":"17003",
    "sg:province":"Girona",
    "wof:name":"G\u00fcell Ordis Valentin",
    "wof:placetype":"venue"
},
  "geometry": {"coordinates":[2.8193430901,41.9699745178],"type":"Point"}
}