{
  "type": "Feature",
  "properties": {
    "iso:country":"ES",
    "sg:address":"Carrer de Ricart, 17",
    "sg:city":"S. Adria Besos",
    "sg:orig_category":"Institutos De Belleza",
    "sg:phone":"+34 933 81 45 63",
    "sg:postcode":"08930",
    "sg:province":"Barcelona",
    "wof:name":"Fetoan S.l.",
    "wof:placetype":"venue"
},
  "geometry": {"coordinates":[2.2153689861,41.4305000305],"type":"Point"}
}