{
  "type": "Feature",
  "properties": {
    "iso:country":"ES",
    "sg:address":"Calle de Torres Quevedo, 13",
    "sg:city":"Zaragoza",
    "sg:orig_category":"Ropa Para Se\u00d1oras (al Por Menor)",
    "sg:phone":"+34 976 33 49 52",
    "sg:postcode":"50010",
    "sg:province":"Zaragoza",
    "wof:name":"Castejon Giner Maria Luisa",
    "wof:placetype":"venue"
},
  "geometry": {"coordinates":[-0.9070649743,41.6539726257],"type":"Point"}
}