{
  "type": "Feature",
  "properties": {
    "iso:country":"ES",
    "sg:address":"Urb. Guadalmina Alta, 813",
    "sg:city":"San Pedro Alcantara",
    "sg:orig_category":"Asesor\u00cda Fiscal Y Jur\u00cddica",
    "sg:phone":"+34 952 88 34 34",
    "sg:postcode":"29670",
    "sg:province":"M\u00e1laga",
    "wof:name":"Asesoria Troyano S.l.",
    "wof:placetype":"venue"
},
  "geometry": {"coordinates":[-4.9894766808,36.4856033325],"type":"Point"}
}