{
  "type": "Feature",
  "properties": {
    "iso:country":"ES",
    "sg:address":"Calle de Sargento Provisional, 2",
    "sg:city":"Oviedo",
    "sg:orig_category":"Agencias Y Agentes Comerciales, Representantes",
    "sg:phone":"+34 985 23 04 29",
    "sg:postcode":"33005",
    "sg:province":"Asturias",
    "wof:name":"Blanco Montero Jose Carlos",
    "wof:placetype":"venue"
},
  "geometry": {"coordinates":[-5.859058857,43.3583183289],"type":"Point"}
}