{
  "type": "Feature",
  "properties": {
    "iso:country":"ES",
    "sg:address":"Avda San Francisco Javier, 24",
    "sg:city":"Sevilla",
    "sg:orig_category":"Asesor\u00cda Fiscal Y Jur\u00cddica",
    "sg:phone":"+34 954 65 78 89",
    "sg:postcode":"41018",
    "sg:province":"Sevilla",
    "wof:name":"Servicios De Apoyo Al Derecho S.l.",
    "wof:placetype":"venue"
},
  "geometry": {"coordinates":[-5.9753189087,37.3774452209],"type":"Point"}
}