{
  "type": "Feature",
  "properties": {
    "iso:country":"ES",
    "sg:address":"Alam Boulevard Del, 3",
    "sg:city":"Donostia-san Sebastian",
    "sg:orig_category":"Zapater\u00cdas",
    "sg:phone":"+34 943 43 35 65",
    "sg:postcode":"20003",
    "sg:province":"Guip\u00f9zcoa",
    "wof:name":"Javier Ayestaran S.l.",
    "wof:placetype":"venue"
},
  "geometry": {"coordinates":[-1.9826079607,43.3228874207],"type":"Point"}
}