{
  "type": "Feature",
  "properties": {
    "addr:full":"Ptge Escudellers, 3 Barcelona Barcelona 08002",
    "addr:housenumber":"3",
    "addr:postcode":"08002",
    "addr:street":"Ptge Escudellers",
    "iso:country":"ES",
    "sg:address":"Ptge Escudellers, 3",
    "sg:city":"Barcelona",
    "sg:orig_category":"Caf\u00c9s, Bares, Cervecer\u00cdas",
    "sg:phone":"+34 933 17 54 11",
    "sg:postcode":"08002",
    "sg:province":"Barcelona",
    "wof:name":"Loayza Martin Ainhoa",
    "wof:placetype":"venue"
},
  "geometry": {"coordinates":[2.1765139103,41.3792076111],"type":"Point"}
}