{
  "type": "Feature",
  "properties": {
    "iso:country":"ES",
    "sg:address":"Bras Nou, 5",
    "sg:city":"Beniparrell",
    "sg:orig_category":"Persianas Interiores, Exteriores",
    "sg:phone":"+34 961 21 39 13",
    "sg:postcode":"46469",
    "sg:province":"Valencia",
    "wof:name":"Lonas Y Toldos Navarro S.l.",
    "wof:placetype":"venue"
},
  "geometry": {"coordinates":[-0.4154840112,39.3789367676],"type":"Point"}
}