{
  "type": "Feature",
  "properties": {
    "iso:country":"ES",
    "sg:address":"Calle de Sanchez Balderas, 6",
    "sg:city":"Madrid",
    "sg:orig_category":"Molduras, Junquillos, Listones Y Molduras Perforadas",
    "sg:phone":"+34 914 13 76 21",
    "sg:postcode":"28002",
    "sg:province":"Madrid",
    "wof:name":"Tortajada Rodriguez Joaquin",
    "wof:placetype":"venue"
},
  "geometry": {"coordinates":[-3.6625049114,40.4461097717],"type":"Point"}
}