{
  "type": "Feature",
  "properties": {
    "iso:country":"ES",
    "sg:address":"Calle de Fernando Mugica, 13",
    "sg:city":"Donostia-san Sebastian",
    "sg:orig_category":"Venta, Instalaci\u00d3n, Mantenimiento De Chimeneas De Interior Y Accesorios",
    "sg:phone":"+34 943 36 32 20",
    "sg:postcode":"20018",
    "sg:province":"Guip\u00f9zcoa",
    "sg:website":"www.kebidek.com",
    "wof:name":"Lizaso Iturriza Jose Ignacio",
    "wof:placetype":"venue"
},
  "geometry": {"coordinates":[-2.0131142139,43.2807044983],"type":"Point"}
}