{
  "type": "Feature",
  "properties": {
    "addr:full":"Pla\u00c7 Parc De L'estacio, 2 Gandia Valencia 46700",
    "addr:housenumber":"2",
    "addr:postcode":"46700",
    "addr:street":"Valencia",
    "iso:country":"ES",
    "sg:address":"Pla\u00c7 Parc De L'estacio, 2",
    "sg:city":"Gandia",
    "sg:orig_category":"Inmobiliaria (agencias)",
    "sg:phone":"+34 962 96 59 24",
    "sg:postcode":"46700",
    "sg:province":"Valencia",
    "wof:name":"Grupo Inmobiliario Pichincha S.l.",
    "wof:placetype":"venue"
},
  "geometry": {"coordinates":[-0.1852236986,38.9690284729],"type":"Point"}
}