{
  "type": "Feature",
  "properties": {
    "iso:country":"ES",
    "sg:address":"Avda Cea (de), S/n",
    "sg:city":"Barrela",
    "sg:orig_category":"Farmacias",
    "sg:phone":"+34 982 46 63 55",
    "sg:postcode":"27520",
    "sg:province":"Lugo",
    "wof:name":"Yebra Pimentel Rodriguez C.b.",
    "wof:placetype":"venue"
},
  "geometry": {"coordinates":[-7.8162169456,42.5403213501],"type":"Point"}
}