{
  "type": "Feature",
  "properties": {
    "iso:country":"ES",
    "sg:address":"Calle de Cabo Cervera, 7",
    "sg:city":"Ejido",
    "sg:orig_category":"Centros De Coordinaci\u00d3n",
    "sg:phone":"+34 950 48 62 03",
    "sg:postcode":"04700",
    "sg:province":"Almer\u00eda",
    "wof:name":"Lopez Escobar Antonia Carmen",
    "wof:placetype":"venue"
},
  "geometry": {"coordinates":[-2.8214373589,36.7726593018],"type":"Point"}
}