{
  "type": "Feature",
  "properties": {
    "addr:full":"Calle de Ciudad De Mondo\u00d1edo, 14 Vicedo Lugo 27860",
    "addr:housenumber":"14",
    "addr:postcode":"27860",
    "addr:street":"Calle De Ciudad De Mondon\u0303Edo",
    "iso:country":"ES",
    "sg:address":"Calle de Ciudad De Mondo\u00d1edo, 14",
    "sg:city":"Vicedo",
    "sg:orig_category":"Asesor\u00cda De Formaci\u00d3n Y Gesti\u00d3n De Personal",
    "sg:phone":"+34 982 59 03 76",
    "sg:postcode":"27860",
    "sg:province":"Lugo",
    "wof:name":"Asesoria Goam C.b.",
    "wof:placetype":"venue"
},
  "geometry": {"coordinates":[-7.6717209816,43.7336540222],"type":"Point"}
}