{
  "type": "Feature",
  "properties": {
    "addr:full":"Calle de Cultura (la), 9 Bara\u00f1ain Navarra 31010",
    "addr:housenumber":"9",
    "addr:postcode":"31010",
    "addr:street":"Calle De Cultura La",
    "iso:country":"ES",
    "sg:address":"Calle de Cultura (la), 9",
    "sg:city":"Bara\u00f1ain",
    "sg:orig_category":"Sindicatos Y Colegios Profesionales",
    "sg:phone":"+34 948 18 51 34",
    "sg:postcode":"31010",
    "sg:province":"Navarra",
    "wof:name":"Asociacion Profesional De Vendedores De Prensa De Navarra",
    "wof:placetype":"venue"
},
  "geometry": {"coordinates":[-1.6870664358,42.8041191101],"type":"Point"}
}