{
  "type": "Feature",
  "properties": {
    "iso:country":"ES",
    "sg:address":"Plaz Gernikako, 2",
    "sg:city":"Amorebieta",
    "sg:orig_category":"Molduras, Junquillos, Listones Y Molduras Perforadas",
    "sg:phone":"+34 946 30 82 10",
    "sg:postcode":"48340",
    "sg:province":"Vizcaya",
    "wof:name":"Isasi Martinez Ruben",
    "wof:placetype":"venue"
},
  "geometry": {"coordinates":[-2.7316410542,43.2185287476],"type":"Point"}
}