{
  "type": "Feature",
  "properties": {
    "addr:full":"Carrer de Magi Ramentol, 9 Rubi Barcelona 08191",
    "addr:housenumber":"9",
    "addr:postcode":"08191",
    "addr:street":"Carrer De Magi Ramentol",
    "iso:country":"ES",
    "sg:address":"Carrer de Magi Ramentol, 9",
    "sg:city":"Rubi",
    "sg:orig_category":"Lencer\u00cda Femenina, Corseter\u00cda, Trajes De Ba\u00d1o (al Por Menor)",
    "sg:phone":"+34 935 88 22 92",
    "sg:postcode":"08191",
    "sg:province":"Barcelona",
    "wof:name":"Alvarez Gonzalez Noelia",
    "wof:placetype":"venue"
},
  "geometry": {"coordinates":[2.033834219,41.4897003174],"type":"Point"}
}