{
  "type": "Feature",
  "properties": {
    "iso:country":"ES",
    "sg:address":"Carrer de Terol (de), 3",
    "sg:city":"Salou",
    "sg:orig_category":"Alimentaci\u00d3n General (al Por Mayor)",
    "sg:phone":"+34 977 35 06 04",
    "sg:postcode":"43840",
    "sg:province":"Tarragona",
    "sg:website":"www.vanyera3.com",
    "wof:name":"Sarr  Demba",
    "wof:placetype":"venue"
},
  "geometry": {"coordinates":[1.1465929747,41.0736694336],"type":"Point"}
}