{
  "type": "Feature",
  "properties": {
    "addr:full":"Calle de San Francisco, 43 Bilbao Vizcaya 48003",
    "addr:housenumber":"43",
    "addr:postcode":"48003",
    "addr:street":"Calle De San Francisco",
    "iso:country":"ES",
    "sg:address":"Calle de San Francisco, 43",
    "sg:city":"Bilbao",
    "sg:orig_category":"Peluquer\u00cdas, Peluquer\u00cda Mixta",
    "sg:phone":"+34 944 16 48 43",
    "sg:postcode":"48003",
    "sg:province":"Vizcaya",
    "wof:name":"Uuafa  Muulay Taeb",
    "wof:placetype":"venue"
},
  "geometry": {"coordinates":[-2.929049015,43.2559432983],"type":"Point"}
}