{
  "type": "Feature",
  "properties": {
    "iso:country":"ES",
    "sg:address":"Calle de Jose Lujan, 28",
    "sg:city":"Palmar  O Lugar De Don Juan",
    "sg:orig_category":"Contenedores (mercanc\u00cdas)",
    "sg:phone":"+34 968 88 47 04",
    "sg:postcode":"30120",
    "sg:province":"Murcia",
    "wof:name":"Romero Perez Francisco",
    "wof:placetype":"venue"
},
  "geometry": {"coordinates":[-1.1302490234,37.9829597473],"type":"Point"}
}