{
  "type": "Feature",
  "properties": {
    "iso:country":"ES",
    "sg:address":"Calle de Mayor, 17",
    "sg:city":"Villaca\u00f1as",
    "sg:orig_category":"Molduras, Junquillos, Listones Y Molduras Perforadas",
    "sg:phone":"+34 925 16 14 04",
    "sg:postcode":"45860",
    "sg:province":"Toledo",
    "wof:name":"Hermanos Felipe C.b.",
    "wof:placetype":"venue"
},
  "geometry": {"coordinates":[-3.3436601162,39.6221160889],"type":"Point"}
}