{
  "type": "Feature",
  "properties": {
    "iso:country":"ES",
    "sg:address":"Calle de San Esteban, 13",
    "sg:city":"Albacete",
    "sg:orig_category":"Molduras, Junquillos, Listones Y Molduras Perforadas",
    "sg:phone":"+34 967 52 01 08",
    "sg:postcode":"02006",
    "sg:province":"Albacete",
    "wof:name":"Exposito Tomas Nicasio",
    "wof:placetype":"venue"
},
  "geometry": {"coordinates":[-1.8657209873,38.9845161438],"type":"Point"}
}