{
  "type": "Feature",
  "properties": {
    "iso:country":"ES",
    "sg:address":"Calle de Esteban Terradas, 6",
    "sg:city":"Madrid",
    "sg:orig_category":"Urbanistas",
    "sg:phone":"+34 913 15 32 57",
    "sg:postcode":"28036",
    "sg:province":"Madrid",
    "sg:website":"www.optivos.es",
    "wof:name":"Ramos Lobo Paloma",
    "wof:placetype":"venue"
},
  "geometry": {"coordinates":[-3.6851110458,40.4690475464],"type":"Point"}
}