{
  "type": "Feature",
  "properties": {
    "iso:country":"ES",
    "sg:address":"Calle de Don Ricardo, 2",
    "sg:city":"Malaga",
    "sg:orig_category":"Veh\u00cdculos De Ocasi\u00d3n",
    "sg:phone":"+34 952 30 10 00",
    "sg:postcode":"29007",
    "sg:province":"M\u00e1laga",
    "wof:name":"Marc Motor S.l.",
    "wof:placetype":"venue"
},
  "geometry": {"coordinates":[-4.4301557541,36.7193222046],"type":"Point"}
}