{
  "type": "Feature",
  "properties": {
    "addr:full":"Pase Santa Barbara, 9 Soria Soria 42002",
    "addr:housenumber":"9",
    "addr:postcode":"42002",
    "addr:street":"Santa Barbara",
    "iso:country":"ES",
    "sg:address":"Pase Santa Barbara, 9",
    "sg:city":"Soria",
    "sg:orig_category":"Venta, Instalaci\u00d3n De Cocinas",
    "sg:phone":"+34 975 21 33 34",
    "sg:postcode":"42002",
    "sg:province":"Soria",
    "wof:name":"Sayeba S.l.",
    "wof:placetype":"venue"
},
  "geometry": {"coordinates":[-2.4691669941,41.7646598816],"type":"Point"}
}