{
  "type": "Feature",
  "properties": {
    "iso:country":"ES",
    "sg:address":"Cra Sant Boi, 238",
    "sg:city":"Sant Vicen\u00c7 Dels Horts",
    "sg:orig_category":"Negocio De Madera",
    "sg:phone":"+34 936 56 17 14",
    "sg:postcode":"08620",
    "sg:province":"Barcelona",
    "wof:name":"Tecnicas Y Aplicaciones Modulares En Madera S.a.l.",
    "wof:placetype":"venue"
},
  "geometry": {"coordinates":[2.0100400448,41.3932189941],"type":"Point"}
}