{
  "type": "Feature",
  "properties": {
    "iso:country":"ES",
    "sg:address":"Plaz Andalucia (de), S/n",
    "sg:city":"Chiclana De La Frontera",
    "sg:orig_category":"Cajas De Ahorro",
    "sg:phone":"+34 956 53 68 40",
    "sg:postcode":"11130",
    "sg:province":"C\u00e1diz",
    "sg:website":"www.ruralvia.com",
    "wof:name":"Caja Rural Del Sur Sociedad Cooperativa",
    "wof:placetype":"venue"
},
  "geometry": {"coordinates":[-6.1449551582,36.4212188721],"type":"Point"}
}