{
  "type": "Feature",
  "properties": {
    "iso:country":"ES",
    "sg:address":"Calle de Diego Manchado, 25",
    "sg:city":"Madrid",
    "sg:orig_category":"Alimentaci\u00d3n General (al Por Menor)",
    "sg:phone":"+34 913 03 73 04",
    "sg:postcode":"28038",
    "sg:province":"Madrid",
    "wof:name":"Zhan  Yong Jun",
    "wof:placetype":"venue"
},
  "geometry": {"coordinates":[-3.6474568844,40.3898124695],"type":"Point"}
}