{
  "type": "Feature",
  "properties": {
    "iso:country":"ES",
    "sg:address":"Calle de Escuelas, 7",
    "sg:city":"Vivares",
    "sg:orig_category":"Asociaciones, Organismos Culturales Y Socioeducativos",
    "sg:phone":"+34 924 85 35 27",
    "sg:postcode":"06412",
    "sg:province":"Badajoz",
    "wof:name":"Centro Rural Joven Vida",
    "wof:placetype":"venue"
},
  "geometry": {"coordinates":[-5.8974399567,39.0861930847],"type":"Point"}
}