{
  "type": "Feature",
  "properties": {
    "addr:full":"Calle de General Sueiro, 9 Zaragoza Zaragoza 50008",
    "addr:housenumber":"9",
    "addr:postcode":"50008",
    "addr:street":"Calle De General Sueiro",
    "iso:country":"ES",
    "sg:address":"Calle de General Sueiro, 9",
    "sg:city":"Zaragoza",
    "sg:orig_category":"Abogados",
    "sg:phone":"+34 976 21 65 80",
    "sg:postcode":"50008",
    "sg:province":"Zaragoza",
    "wof:name":"Garcia Soria Ricardo",
    "wof:placetype":"venue"
},
  "geometry": {"coordinates":[-0.8828129768,41.6460838318],"type":"Point"}
}