{
  "type": "Feature",
  "properties": {
    "addr:full":"Plaz San Pedro, 1 Priego Cordoba C\u00f3rdoba 14800",
    "addr:housenumber":"1",
    "addr:postcode":"14800",
    "addr:street":"Plaz San Pedro;Cordoba Co\u0301Rdoba",
    "iso:country":"ES",
    "sg:address":"Plaz San Pedro, 1",
    "sg:city":"Priego Cordoba",
    "sg:orig_category":"Florister\u00cdas",
    "sg:phone":"+34 957 70 01 37",
    "sg:postcode":"14800",
    "sg:province":"C\u00f3rdoba",
    "wof:name":"Diaz Suarez Emilio",
    "wof:placetype":"venue"
},
  "geometry": {"coordinates":[-4.1962990761,37.4413757324],"type":"Point"}
}