{
  "type": "Feature",
  "properties": {
    "addr:full":"Calle de Nalona La, 4 Langreo Asturias 33900",
    "addr:housenumber":"4",
    "addr:postcode":"33900",
    "addr:street":"Calle De Nalona La",
    "iso:country":"ES",
    "sg:address":"Calle de Nalona La, 4",
    "sg:city":"Langreo",
    "sg:orig_category":"Estancos",
    "sg:phone":"+34 985 69 48 34",
    "sg:postcode":"33900",
    "sg:province":"Asturias",
    "wof:name":"Garcia Alvarez Angeles",
    "wof:placetype":"venue"
},
  "geometry": {"coordinates":[-5.6851520538,43.2966766357],"type":"Point"}
}