{
  "type": "Feature",
  "properties": {
    "iso:country":"ES",
    "sg:address":"Praz Independencia, 3",
    "sg:city":"Vigo",
    "sg:orig_category":"Peluqueros: De Se\u00d1oras",
    "sg:phone":"+34 986 20 68 20",
    "sg:postcode":"36211",
    "sg:province":"Pontevedra",
    "wof:name":"Lago Dominguez Patricia",
    "wof:placetype":"venue"
},
  "geometry": {"coordinates":[-8.7302560806,42.223777771],"type":"Point"}
}