{
  "type": "Feature",
  "properties": {
    "addr:full":"Calle de San Pedro, 12 Caceres C\u00e1ceres 10003",
    "addr:housenumber":"12",
    "addr:postcode":"10003",
    "addr:street":"Calle De San Pedro;Ca\u0301Ceres",
    "iso:country":"ES",
    "sg:address":"Calle de San Pedro, 12",
    "sg:city":"Caceres",
    "sg:orig_category":"Peluquer\u00cdas, Peluquer\u00cda Mixta",
    "sg:phone":"+34 927 21 41 75",
    "sg:postcode":"10003",
    "sg:province":"C\u00e1ceres",
    "wof:name":"Aznar Gallego Lucia",
    "wof:placetype":"venue"
},
  "geometry": {"coordinates":[-6.3743238449,39.4735069275],"type":"Point"}
}