{
  "type": "Feature",
  "properties": {
    "addr:full":"Avda Alfonso Vi, 18 Salamanca Salamanca 37005",
    "addr:housenumber":"18",
    "addr:postcode":"37005",
    "addr:street":"Avda Alfonso Vi",
    "iso:country":"ES",
    "sg:address":"Avda Alfonso Vi, 18",
    "sg:city":"Salamanca",
    "sg:orig_category":"Molduras, Junquillos, Listones Y Molduras Perforadas",
    "sg:phone":"+34 923 25 69 01",
    "sg:postcode":"37005",
    "sg:province":"Salamanca",
    "wof:name":"Collantes Dieguez Jose",
    "wof:placetype":"venue"
},
  "geometry": {"coordinates":[-5.6610689163,40.976234436],"type":"Point"}
}