{
  "type": "Feature",
  "properties": {
    "iso:country":"ES",
    "sg:address":"Pase Rosales, 26",
    "sg:city":"Zaragoza",
    "sg:orig_category":"Papeler\u00cdas, Librer\u00cdas",
    "sg:phone":"+34 976 59 27 13",
    "sg:postcode":"50008",
    "sg:province":"Zaragoza",
    "wof:name":"Floria Cebollada Milagros",
    "wof:placetype":"venue"
},
  "geometry": {"coordinates":[-0.878929019,41.6420288086],"type":"Point"}
}