{
  "type": "Feature",
  "properties": {
    "iso:country":"ES",
    "sg:address":"Calle de Pintor Zurbaran, 30",
    "sg:city":"Caceres",
    "sg:classifiers":[
        {
            "category":"Communications",
            "type":"Services"
        }
    ],
    "sg:phone":"+34 927 21 40 19",
    "sg:postcode":"10004",
    "sg:province":"C\u00e1ceres",
    "sg:tags":[
        "televisiones",
        "y",
        "radio"
    ],
    "sg:website":"www.vianorbatv.com",
    "wof:name":"Via Norba Television S.a",
    "wof:placetype":"venue"
},
  "geometry": {"coordinates":[-6.3740868568,39.4772453308],"type":"Point"}
}