{
  "type": "Feature",
  "properties": {
    "addr:full":"Calle de Ancha, 89 Nules Castell\u00f3n 12520",
    "addr:housenumber":"89",
    "addr:postcode":"12520",
    "addr:street":"Calle De Ancha",
    "iso:country":"ES",
    "sg:address":"Calle de Ancha, 89",
    "sg:city":"Nules",
    "sg:orig_category":"Empresas De Demolici\u00d3n",
    "sg:phone":"+34 964 67 03 77",
    "sg:postcode":"12520",
    "sg:province":"Castell\u00f3n",
    "wof:name":"Casaus Bueso Vicente",
    "wof:placetype":"venue"
},
  "geometry": {"coordinates":[-0.158861801,39.8475151062],"type":"Point"}
}