{
  "type": "Feature",
  "properties": {
    "iso:country":"ES",
    "sg:address":"Calle de Anton Tobalo, 97",
    "sg:city":"Torres Cotillas",
    "sg:orig_category":"Chapister\u00cda",
    "sg:phone":"+34 968 62 66 98",
    "sg:postcode":"30565",
    "sg:province":"Murcia",
    "wof:name":"Arnaldos Bermudez Juan",
    "wof:placetype":"venue"
},
  "geometry": {"coordinates":[-1.2441687584,38.0373039246],"type":"Point"}
}