{
  "type": "Feature",
  "properties": {
    "addr:full":"Ctra Armilla Zona Feria De Muestra, S/n Armilla Granada 18100",
    "addr:housenumber":"s / n",
    "addr:postcode":"18100",
    "addr:street":"Ctra Armilla Zona",
    "iso:country":"ES",
    "sg:address":"Ctra Armilla Zona Feria De Muestra, S/n",
    "sg:city":"Armilla",
    "sg:orig_category":"Comit\u00c9s De Organizaci\u00d3n De Exposiciones, Ferias, Salones",
    "sg:phone":"+34 958 81 79 29",
    "sg:postcode":"18100",
    "sg:province":"Granada",
    "sg:website":"www.fermasa.org",
    "wof:name":"Feria De Muestras De Armilla S.a.",
    "wof:placetype":"venue"
},
  "geometry": {"coordinates":[-3.6233580112,37.1459732056],"type":"Point"}
}