{
  "type": "Feature",
  "properties": {
    "iso:country":"ES",
    "sg:address":"Calle de Diego De Mesa, 1",
    "sg:city":"Orotava",
    "sg:orig_category":"Transporte En General",
    "sg:phone":"+34 922 33 33 50",
    "sg:postcode":"38300",
    "sg:province":"Santa Cruz De Tenerife",
    "wof:name":"E Antonio Suarez Baute E Hijos S.l.",
    "wof:placetype":"venue"
},
  "geometry": {"coordinates":[-16.5256538391,28.3815841675],"type":"Point"}
}