{
  "type": "Feature",
  "properties": {
    "addr:full":"Calle de Gardenia, 27 Humanes De Madrid Madrid 28970",
    "addr:housenumber":"27",
    "addr:postcode":"28970",
    "addr:street":"Calle De Gardenia",
    "iso:country":"ES",
    "sg:address":"Calle de Gardenia, 27",
    "sg:city":"Humanes De Madrid",
    "sg:orig_category":"Fabricaci\u00d3n, Comercio De Muebles Para Ni\u00d1os",
    "sg:phone":"+34 916 07 02 05",
    "sg:postcode":"28970",
    "sg:province":"Madrid",
    "wof:name":"Rodriguez Bonilla S.a.",
    "wof:placetype":"venue"
},
  "geometry": {"coordinates":[-3.8400928974,40.2683372498],"type":"Point"}
}