{
  "type": "Feature",
  "properties": {
    "iso:country":"ES",
    "sg:address":"Rua C, 10",
    "sg:city":"Lalin",
    "sg:orig_category":"Psic\u00d3logos",
    "sg:phone":"+34 986 78 37 20",
    "sg:postcode":"36500",
    "sg:province":"Pontevedra",
    "wof:name":"Rodriguez Fernandez Pablo",
    "wof:placetype":"venue"
},
  "geometry": {"coordinates":[-8.1086959839,42.659362793],"type":"Point"}
}