{
  "type": "Feature",
  "properties": {
    "iso:country":"ES",
    "sg:address":"Carrer de Nou, 26",
    "sg:city":"Manresa",
    "sg:orig_category":"Bisuter\u00cda, Joyer\u00cda, Relojer\u00cda (al Por Menor)",
    "sg:phone":"+34 938 72 43 71",
    "sg:postcode":"08241",
    "sg:province":"Barcelona",
    "wof:name":"Toscano Ortega Maria Jesus",
    "wof:placetype":"venue"
},
  "geometry": {"coordinates":[1.8329299688,41.7215194702],"type":"Point"}
}