{
  "type": "Feature",
  "properties": {
    "iso:country":"ES",
    "sg:address":"Carr Joan Maragall, 21",
    "sg:city":"Girona",
    "sg:orig_category":"Arquitectos",
    "sg:phone":"+34 972 20 38 97",
    "sg:postcode":"17002",
    "sg:province":"Girona",
    "wof:name":"Noguera Nieto Soledad",
    "wof:placetype":"venue"
},
  "geometry": {"coordinates":[2.8216640949,41.9796943665],"type":"Point"}
}