{
  "type": "Feature",
  "properties": {
    "addr:full":"Avda Habana, 68 Pontes Garcia Rodriguez La Coru\u00f1a 15320",
    "addr:housenumber":"68",
    "addr:postcode":"15320",
    "addr:street":"Avda Habana;Corun\u0303A",
    "iso:country":"ES",
    "sg:address":"Avda Habana, 68",
    "sg:city":"Pontes Garcia Rodriguez",
    "sg:orig_category":"Electricidad: Instalaciones Industriales",
    "sg:phone":"+34 981 45 28 13",
    "sg:postcode":"15320",
    "sg:province":"La Coru\u00f1a",
    "wof:name":"Pico Castro Francisco Javier",
    "wof:placetype":"venue"
},
  "geometry": {"coordinates":[-7.8490958214,43.448299408],"type":"Point"}
}