{
  "type": "Feature",
  "properties": {
    "addr:full":"Av Montgo, 46 Escala Girona 17130",
    "addr:housenumber":"46",
    "addr:postcode":"17130",
    "addr:street":"Av Montgo",
    "iso:country":"ES",
    "sg:address":"Av Montgo, 46",
    "sg:city":"Escala",
    "sg:orig_category":"Abogados",
    "sg:phone":"+34 972 77 26 58",
    "sg:postcode":"17130",
    "sg:province":"Girona",
    "wof:name":"Izquierdo Sanchez David",
    "wof:placetype":"venue"
},
  "geometry": {"coordinates":[3.1429319382,42.1134376526],"type":"Point"}
}