{
  "type": "Feature",
  "properties": {
    "addr:full":"Calle de Carrera, 6 Osuna Sevilla 41640",
    "addr:postcode":"41640",
    "addr:street":"Calle De Carrera 6",
    "iso:country":"ES",
    "sg:address":"Calle de Carrera, 6",
    "sg:city":"Osuna",
    "sg:orig_category":"Pintura Y Barniz (al Por Menor)",
    "sg:phone":"+34 954 81 05 94",
    "sg:postcode":"41640",
    "sg:province":"Sevilla",
    "sg:website":"www.miguelcarrera.com",
    "wof:name":"Miguel Caceres S. A.",
    "wof:placetype":"venue"
},
  "geometry": {"coordinates":[-5.1032366753,37.2379722595],"type":"Point"}
}