{
  "type": "Feature",
  "properties": {
    "addr:full":"Calle de Sombrerero (del), 14 Colmenar Viejo Madrid 28770",
    "addr:postcode":"28770",
    "addr:street":"Calle De Sombrerero Del",
    "iso:country":"ES",
    "sg:address":"Calle de Sombrerero (del), 14",
    "sg:city":"Colmenar Viejo",
    "sg:orig_category":"Centros Empresariales",
    "sg:phone":"+34 918 48 61 71",
    "sg:postcode":"28770",
    "sg:province":"Madrid",
    "wof:name":"Turegano Chozas Maria Jesus",
    "wof:placetype":"venue"
},
  "geometry": {"coordinates":[-3.7697319984,40.6582984924],"type":"Point"}
}