{
  "type": "Feature",
  "properties": {
    "iso:country":"ES",
    "sg:address":"Avda Francisco Guerrero, 4",
    "sg:city":"San Sebastian De Los Reyes",
    "sg:orig_category":"Ense\u00d1anza: Idiomas",
    "sg:phone":"+34 916 59 57 65",
    "sg:postcode":"28700",
    "sg:province":"Madrid",
    "wof:name":"Equinox T&b Inglish And Teamwork",
    "wof:placetype":"venue"
},
  "geometry": {"coordinates":[-3.5838758945,40.6059265137],"type":"Point"}
}