{
  "type": "Feature",
  "properties": {
    "iso:country":"ES",
    "sg:address":"Luga Poligono De San Telmo, S/n",
    "sg:city":"Jerez De La Frontera",
    "sg:orig_category":"Congelados: Productos Alimentarios (al Por Menor)",
    "sg:phone":"+34 956 33 14 84",
    "sg:postcode":"11408",
    "sg:province":"C\u00e1diz",
    "wof:name":"Carrasco Romero Francisco",
    "wof:placetype":"venue"
},
  "geometry": {"coordinates":[-6.1592831612,36.6686592102],"type":"Point"}
}