{
  "type": "Feature",
  "properties": {
    "addr:full":"Plaz Constitucion, S/n Bedar Almer\u00eda 04288",
    "addr:postcode":"04288",
    "addr:street":"Constitucion S / N Bedar Almeri\u0301A",
    "iso:country":"ES",
    "sg:address":"Plaz Constitucion, S/n",
    "sg:city":"Bedar",
    "sg:orig_category":"Administraciones Regionales, Departamentales Y Locales",
    "sg:phone":"+34 950 46 92 77",
    "sg:postcode":"04288",
    "sg:province":"Almer\u00eda",
    "wof:name":"Ayuntamiento",
    "wof:placetype":"venue"
},
  "geometry": {"coordinates":[-1.9818929434,37.1897735596],"type":"Point"}
}