{
  "type": "Feature",
  "properties": {
    "addr:full":"Plaz Constitucion, 7 Fuente Cantos Badajoz 06240",
    "addr:postcode":"06240",
    "addr:street":"Constitucion 7 Fuente Cantos",
    "iso:country":"ES",
    "sg:address":"Plaz Constitucion, 7",
    "sg:city":"Fuente Cantos",
    "sg:orig_category":"Molduras, Junquillos, Listones Y Molduras Perforadas",
    "sg:phone":"+34 924 50 02 50",
    "sg:postcode":"06240",
    "sg:province":"Badajoz",
    "wof:name":"Ibarra Berjano Francisco",
    "wof:placetype":"venue"
},
  "geometry": {"coordinates":[-6.2997288704,38.2481498718],"type":"Point"}
}