{
  "type": "Feature",
  "properties": {
    "addr:full":"Calle de San Bernardo, 11 Puebla Sanabria Zamora 49300",
    "addr:housenumber":"11",
    "addr:postcode":"49300",
    "addr:street":"Calle De San Bernardo;Sanabria Zamora",
    "iso:country":"ES",
    "sg:address":"Calle de San Bernardo, 11",
    "sg:city":"Puebla Sanabria",
    "sg:orig_category":"Internados & Ense\u00d1anza Privada",
    "sg:phone":"+34 980 62 00 16",
    "sg:postcode":"49300",
    "sg:province":"Zamora",
    "wof:name":"Religiosas Del Amor De Dios",
    "wof:placetype":"venue"
},
  "geometry": {"coordinates":[-6.63377285,42.053943634],"type":"Point"}
}