{
  "type": "Feature",
  "properties": {
    "iso:country":"ES",
    "sg:address":"Via Julia, 201",
    "sg:city":"Barcelona",
    "sg:orig_category":"M\u00dasica Diversa",
    "sg:phone":"+34 933 50 60 89",
    "sg:postcode":"08042",
    "sg:province":"Barcelona",
    "wof:name":"Fundacio Privada Procat",
    "wof:placetype":"venue"
},
  "geometry": {"coordinates":[2.1790819168,41.4456634521],"type":"Point"}
}