{
  "type": "Feature",
  "properties": {
    "addr:full":"Calle de Ferrol (del), 7 Pinto Madrid 28320",
    "addr:housenumber":"7",
    "addr:postcode":"28320",
    "addr:street":"Calle De Ferrol Del;Pinto",
    "iso:country":"ES",
    "sg:address":"Calle de Ferrol (del), 7",
    "sg:city":"Pinto",
    "sg:orig_category":"Rectificaci\u00d3n, Mecanizado, Fresado",
    "sg:phone":"+34 916 92 00 73",
    "sg:postcode":"28320",
    "sg:province":"Madrid",
    "wof:name":"Industrias Rasede S.l.",
    "wof:placetype":"venue"
},
  "geometry": {"coordinates":[-3.7045750618,40.2461547852],"type":"Point"}
}