{
  "type": "Feature",
  "properties": {
    "iso:country":"ES",
    "sg:address":"Calle de Almu\u00d1ecar, 1",
    "sg:city":"Albolote",
    "sg:orig_category":"Centros Empresariales",
    "sg:phone":"+34 958 46 85 08",
    "sg:postcode":"18220",
    "sg:province":"Granada",
    "wof:name":"Dalmacio Trans Sl",
    "wof:placetype":"venue"
},
  "geometry": {"coordinates":[-3.6434030533,37.2244758606],"type":"Point"}
}