{
  "type": "Feature",
  "properties": {
    "addr:full":"Calle de Paris, 4 Valdemoro Madrid 28340",
    "addr:housenumber":"4",
    "addr:postcode":"28340",
    "addr:street":"Calle De Paris",
    "iso:country":"ES",
    "sg:address":"Calle de Paris, 4",
    "sg:city":"Valdemoro",
    "sg:orig_category":"Cerrajer\u00cda, Ferrallista",
    "sg:phone":"+34 918 95 40 03",
    "sg:postcode":"28340",
    "sg:province":"Madrid",
    "wof:name":"Cerrajerias Hersan S.l.",
    "wof:placetype":"venue"
},
  "geometry": {"coordinates":[-3.6850550175,40.2109985352],"type":"Point"}
}