{
  "type": "Feature",
  "properties": {
    "iso:country":"ES",
    "sg:address":"Calle de Tablada, 22",
    "sg:city":"S. Pedro Pinatar",
    "sg:orig_category":"Caf\u00c9s, Bares, Cervecer\u00cdas",
    "sg:phone":"+34 968 18 26 58",
    "sg:postcode":"30740",
    "sg:province":"Murcia",
    "wof:name":"Navarro Garcia Manuel",
    "wof:placetype":"venue"
},
  "geometry": {"coordinates":[-0.7958456874,37.8343009949],"type":"Point"}
}