{
  "type": "Feature",
  "properties": {
    "addr:full":"Trva Asensio Neila, S/n Hervas C\u00e1ceres 10700",
    "addr:housenumber":"s / n",
    "addr:postcode":"10700",
    "addr:street":"Trva Asensio Neila;Ca\u0301Ceres",
    "iso:country":"ES",
    "sg:address":"Trva Asensio Neila, S/n",
    "sg:city":"Hervas",
    "sg:orig_category":"Cajas De Ahorro",
    "sg:phone":"+34 927 47 48 35",
    "sg:postcode":"10700",
    "sg:province":"C\u00e1ceres",
    "wof:name":"Fundacio 'la Caixa'",
    "wof:placetype":"venue"
},
  "geometry": {"coordinates":[-5.8596191406,40.2743186951],"type":"Point"}
}