{
  "type": "Feature",
  "properties": {
    "iso:country":"ES",
    "sg:address":"Carrer de Cami De L'escorial, 33",
    "sg:city":"Vic",
    "sg:orig_category":"Iglesias Cristianas Diversas",
    "sg:phone":"+34 938 89 15 52",
    "sg:postcode":"08500",
    "sg:province":"Barcelona",
    "wof:name":"Testigos Cristianos De Jehova",
    "wof:placetype":"venue"
},
  "geometry": {"coordinates":[2.2515759468,41.945438385],"type":"Point"}
}