{
  "type": "Feature",
  "properties": {
    "iso:country":"ES",
    "sg:address":"Avda Mari\u00d1a (da), 54",
    "sg:city":"San Cibrao",
    "sg:orig_category":"Librer\u00cdas",
    "sg:phone":"+34 982 59 30 05",
    "sg:postcode":"27890",
    "sg:province":"Lugo",
    "wof:name":"Fernandez Lopez Alvaro",
    "wof:placetype":"venue"
},
  "geometry": {"coordinates":[-7.4396090508,43.6968574524],"type":"Point"}
}