{
  "type": "Feature",
  "properties": {
    "addr:full":"Calle de Bolivia, 3 Valladolid Valladolid 47014",
    "addr:housenumber":"3",
    "addr:postcode":"47014",
    "addr:street":"Calle De Bolivia",
    "iso:country":"ES",
    "sg:address":"Calle de Bolivia, 3",
    "sg:city":"Valladolid",
    "sg:orig_category":"Ingeniero",
    "sg:phone":"+34 983 22 63 72",
    "sg:postcode":"47014",
    "sg:province":"Valladolid",
    "wof:name":"Garcia Villafranca I\u00f1igo",
    "wof:placetype":"venue"
},
  "geometry": {"coordinates":[-4.750140667,41.632610321],"type":"Point"}
}