{
  "type": "Feature",
  "properties": {
    "addr:full":"Calle de Pedro Alonso Ni\u00d1o, 17 Moguer Huelva 21800",
    "addr:housenumber":"17",
    "addr:postcode":"21800",
    "addr:street":"Calle De Pedro Alonso Nin\u0303O",
    "iso:country":"ES",
    "sg:address":"Calle de Pedro Alonso Ni\u00d1o, 17",
    "sg:city":"Moguer",
    "sg:orig_category":"Promotores Constructores",
    "sg:phone":"+34 959 37 26 49",
    "sg:postcode":"21800",
    "sg:province":"Huelva",
    "wof:name":"Moguer Loygo Construcciones S.l.u.",
    "wof:placetype":"venue"
},
  "geometry": {"coordinates":[-6.8372430801,37.2771263123],"type":"Point"}
}