{
  "type": "Feature",
  "properties": {
    "addr:full":"Isasi Kalea, 20 Eibar Guip\u00f9zcoa 20600",
    "addr:housenumber":"20",
    "addr:postcode":"20600",
    "addr:street":"Isasi Kalea;Guipu\u0300Zcoa",
    "iso:country":"ES",
    "sg:address":"Isasi Kalea, 20",
    "sg:city":"Eibar",
    "sg:orig_category":"Autob\u00das (explotaci\u00d3n Y Servicios De)",
    "sg:phone":"+34 943 20 17 33",
    "sg:postcode":"20600",
    "sg:province":"Guip\u00f9zcoa",
    "wof:name":"Eibarbus S. A. L.",
    "wof:placetype":"venue"
},
  "geometry": {"coordinates":[-2.4783499241,43.1834564209],"type":"Point"}
}