{
  "type": "Feature",
  "properties": {
    "iso:country":"ES",
    "sg:address":"Ctra Valls, Km. 0002,0",
    "sg:city":"Alcover",
    "sg:orig_category":"Producci\u00d3n De Huevos",
    "sg:phone":"+34 977 84 68 16",
    "sg:postcode":"43460",
    "sg:province":"Tarragona",
    "wof:name":"Eurovolinea S.l.",
    "wof:placetype":"venue"
},
  "geometry": {"coordinates":[1.1718250513,41.2622566223],"type":"Point"}
}