{
  "type": "Feature",
  "properties": {
    "iso:country":"ES",
    "sg:address":"Barrio De San Cristobal, S/n",
    "sg:city":"Ca\u00f1ada Benatanduz",
    "sg:orig_category":"Molduras, Junquillos, Listones Y Molduras Perforadas",
    "sg:phone":"+34 978 77 30 53",
    "sg:postcode":"44559",
    "sg:province":"Teruel",
    "wof:name":"Jarque Buj Urbano",
    "wof:placetype":"venue"
},
  "geometry": {"coordinates":[-0.5355629921,40.5766677856],"type":"Point"}
}