{
  "type": "Feature",
  "properties": {
    "addr:full":"Avda Ausias March, 34 Valencia Valencia 46006",
    "addr:housenumber":"34",
    "addr:postcode":"46006",
    "addr:street":"Avda Ausias March",
    "iso:country":"ES",
    "sg:address":"Avda Ausias March, 34",
    "sg:city":"Valencia",
    "sg:orig_category":"Electricidad Veh\u00cdculo",
    "sg:phone":"+34 963 73 26 61",
    "sg:postcode":"46006",
    "sg:province":"Valencia",
    "wof:name":"Electromovil Villarrolla S.l.",
    "wof:placetype":"venue"
},
  "geometry": {"coordinates":[-0.3740380108,39.4537506104],"type":"Point"}
}