{
  "type": "Feature",
  "properties": {
    "iso:country":"ES",
    "sg:address":"Avda Bruselas (de), 38",
    "sg:city":"Alcobendas",
    "sg:orig_category":"Agencias De Viajes",
    "sg:phone":"+34 916 61 44 72",
    "sg:postcode":"28108",
    "sg:province":"Madrid",
    "wof:name":"Travel Store S.l.",
    "wof:placetype":"venue"
},
  "geometry": {"coordinates":[-3.6425430775,40.5304412842],"type":"Point"}
}