{
  "type": "Feature",
  "properties": {
    "addr:full":"Mercasturias, S/n Lugo Asturias 33192",
    "addr:housenumber":"/ n",
    "addr:postcode":"33192",
    "addr:street":"Mercasturias S",
    "iso:country":"ES",
    "sg:address":"Mercasturias, S/n",
    "sg:city":"Lugo",
    "sg:orig_category":"Patatas (al Por Mayor)",
    "sg:phone":"+34 985 26 02 67",
    "sg:postcode":"33192",
    "sg:province":"Asturias",
    "wof:name":"Ardura Cano Rafael Juan",
    "wof:placetype":"venue"
},
  "geometry": {"coordinates":[-5.820224762,43.4187202454],"type":"Point"}
}