{
  "type": "Feature",
  "properties": {
    "iso:country":"ES",
    "sg:address":"Calle de Reina Regente, 4",
    "sg:city":"Donostia-san Sebastian",
    "sg:orig_category":"Confecci\u00d3n (fabricaci\u00d3n, Al Por Mayor)",
    "sg:phone":"+34 943 42 79 20",
    "sg:postcode":"20003",
    "sg:province":"Guip\u00f9zcoa",
    "wof:name":"Dominguez Dominguez Jose",
    "wof:placetype":"venue"
},
  "geometry": {"coordinates":[-1.9814740419,43.3228797913],"type":"Point"}
}