{
  "type": "Feature",
  "properties": {
    "iso:country":"ES",
    "sg:address":"Calle de Cervantes, 18",
    "sg:city":"Bembibre",
    "sg:orig_category":"Molduras, Junquillos, Listones Y Molduras Perforadas",
    "sg:phone":"+34 987 51 12 99",
    "sg:postcode":"24300",
    "sg:province":"Le\u00f3n",
    "wof:name":"Bierro Linea S.l",
    "wof:placetype":"venue"
},
  "geometry": {"coordinates":[-6.4193530083,42.6178016663],"type":"Point"}
}