{
  "type": "Feature",
  "properties": {
    "addr:full":"Gale Oliva (la), S/n Pontevedra Pontevedra 36001",
    "addr:postcode":"36001",
    "addr:street":"La S / N",
    "iso:country":"ES",
    "sg:address":"Gale Oliva (la), S/n",
    "sg:city":"Pontevedra",
    "sg:orig_category":"Confecci\u00d3n (fabricaci\u00d3n, Al Por Mayor)",
    "sg:phone":"+34 986 86 17 84",
    "sg:postcode":"36001",
    "sg:province":"Pontevedra",
    "wof:name":"Gonzalez Bayon Bernardino",
    "wof:placetype":"venue"
},
  "geometry": {"coordinates":[-8.6444606781,42.4303627014],"type":"Point"}
}