{
  "type": "Feature",
  "properties": {
    "addr:full":"Urb Poligono Juncaril, S/n Albolote Granada 18220",
    "addr:housenumber":"s / n",
    "addr:postcode":"18220",
    "addr:street":"Urb Poligono Juncaril",
    "iso:country":"ES",
    "sg:address":"Urb Poligono Juncaril, S/n",
    "sg:city":"Albolote",
    "sg:orig_category":"Fabricaci\u00d3n, Instalaci\u00d3n Y Reparaci\u00d3n De Bombas",
    "sg:phone":"+34 902 46 57 59",
    "sg:postcode":"18220",
    "sg:province":"Granada",
    "sg:website":"www.bombashidraulicas-saer.com",
    "wof:name":"Bohisa Bombas Hidraulicas S.a.",
    "wof:placetype":"venue"
},
  "geometry": {"coordinates":[-3.6585440636,37.2332839966],"type":"Point"}
}