{
  "type": "Feature",
  "properties": {
    "iso:country":"ES",
    "sg:address":"Avda Galicia De, 8",
    "sg:city":"Oviedo",
    "sg:orig_category":"Empresas De Desmonte",
    "sg:phone":"+34 985 96 60 10",
    "sg:postcode":"33005",
    "sg:province":"Asturias",
    "wof:name":"Sanchez Y Lago S.l.",
    "wof:placetype":"venue"
},
  "geometry": {"coordinates":[-5.8546757698,43.3614654541],"type":"Point"}
}