{
  "type": "Feature",
  "properties": {
    "addr:full":"Calle de Santiago, 55 Llerena Badajoz 06900",
    "addr:housenumber":"55",
    "addr:postcode":"06900",
    "addr:street":"Calle De Santiago",
    "iso:country":"ES",
    "sg:address":"Calle de Santiago, 55",
    "sg:city":"Llerena",
    "sg:orig_category":"Material Y Suministros Para Imprenta E Industrias Gr\u00c1ficas",
    "sg:phone":"+34 924 87 00 77",
    "sg:postcode":"06900",
    "sg:province":"Badajoz",
    "wof:name":"Lopez Vi\u00f1as Jose Adelardo",
    "wof:placetype":"venue"
},
  "geometry": {"coordinates":[-6.016828537,38.2376670837],"type":"Point"}
}