{
  "type": "Feature",
  "properties": {
    "iso:country":"ES",
    "sg:address":"Plaz Tranvia (del), 6",
    "sg:city":"Motril",
    "sg:orig_category":"Agencias De Viajes",
    "sg:phone":"+34 958 60 89 71",
    "sg:postcode":"18600",
    "sg:province":"Granada",
    "wof:name":"Harurvi S.l.",
    "wof:placetype":"venue"
},
  "geometry": {"coordinates":[-3.5182778835,36.7441368103],"type":"Point"}
}