{
  "type": "Feature",
  "properties": {
    "iso:country":"ES",
    "sg:address":"Calle de Moguer, 11",
    "sg:city":"Alcala Guadaira",
    "sg:orig_category":"Alimentaci\u00d3n General (al Por Menor)",
    "sg:phone":"+34 955 68 31 52",
    "sg:postcode":"41500",
    "sg:province":"Sevilla",
    "wof:name":"Benitez Chamorro Francisco",
    "wof:placetype":"venue"
},
  "geometry": {"coordinates":[-5.834045887,37.333240509],"type":"Point"}
}