{
  "type": "Feature",
  "properties": {
    "addr:full":"Plaz Mayor, 12 Bujalance C\u00f3rdoba 14650",
    "addr:housenumber":"12",
    "addr:postcode":"14650",
    "addr:street":"Plaz Mayor",
    "iso:country":"ES",
    "sg:address":"Plaz Mayor, 12",
    "sg:city":"Bujalance",
    "sg:orig_category":"M\u00c9dicos: Estomatolog\u00cda",
    "sg:phone":"+34 957 17 15 83",
    "sg:postcode":"14650",
    "sg:province":"C\u00f3rdoba",
    "wof:name":"Cabrerizo Izquierdo Laura",
    "wof:placetype":"venue"
},
  "geometry": {"coordinates":[-4.3821210861,37.8962135315],"type":"Point"}
}