{
  "type": "Feature",
  "properties": {
    "addr:full":"Carrer de Sant Francesc Xavier, 45 Esplugues Llobregat Barcelona 08950",
    "addr:housenumber":"45",
    "addr:postcode":"08950",
    "addr:street":"Carrer De Sant Francesc Xavier",
    "iso:country":"ES",
    "sg:address":"Carrer de Sant Francesc Xavier, 45",
    "sg:city":"Esplugues Llobregat",
    "sg:orig_category":"Electrodom\u00c9sticos (al Por Menor)",
    "sg:phone":"+34 933 71 40 46",
    "sg:postcode":"08950",
    "sg:province":"Barcelona",
    "wof:name":"Linea Blanca Burguillos S.l.",
    "wof:placetype":"venue"
},
  "geometry": {"coordinates":[2.0843989849,41.3765258789],"type":"Point"}
}