{
  "type": "Feature",
  "properties": {
    "iso:country":"ES",
    "sg:address":"Pol Ind El Ejido, S/n",
    "sg:city":"Osuna",
    "sg:orig_category":"Torneros Sobre Madera",
    "sg:phone":"+34 954 81 02 74",
    "sg:postcode":"41640",
    "sg:province":"Sevilla",
    "wof:name":"Fernandez Garcia Juan Maria",
    "wof:placetype":"venue"
},
  "geometry": {"coordinates":[-5.1015224457,37.2303657532],"type":"Point"}
}