{
  "type": "Feature",
  "properties": {
    "iso:country":"ES",
    "sg:address":"Gral. Mola, 58",
    "sg:city":"Trujillo",
    "sg:orig_category":"Cl\u00cdnicas Dentales",
    "sg:phone":"+34 927 32 28 66",
    "sg:postcode":"10200",
    "sg:province":"C\u00e1ceres",
    "wof:name":"Garcia Ventanas Juan Francisco",
    "wof:placetype":"venue"
},
  "geometry": {"coordinates":[-5.8752059937,39.4580307007],"type":"Point"}
}