{
  "type": "Feature",
  "properties": {
    "addr:full":"Carr Miguel De Cervantes, 34 Palamos Girona 17230",
    "addr:housenumber":"34",
    "addr:postcode":"17230",
    "addr:street":"Carr Miguel De Cervantes",
    "iso:country":"ES",
    "sg:address":"Carr Miguel De Cervantes, 34",
    "sg:city":"Palamos",
    "sg:orig_category":"Carnicer\u00cdas, Carnicer\u00cdas",
    "sg:phone":"+34 972 31 59 83",
    "sg:postcode":"17230",
    "sg:province":"Girona",
    "wof:name":"Dalmau Canovas Ernets",
    "wof:placetype":"venue"
},
  "geometry": {"coordinates":[3.1297080517,41.8486289978],"type":"Point"}
}