{
  "type": "Feature",
  "properties": {
    "iso:country":"ES",
    "sg:address":"Cmno Pajales (los), 31",
    "sg:city":"Guamasa",
    "sg:orig_category":"Semiller\u00cdas",
    "sg:phone":"+34 922 63 62 66",
    "sg:postcode":"38330",
    "sg:province":"Santa Cruz De Tenerife",
    "wof:name":"Machado Von Tschusi Eugenio",
    "wof:placetype":"venue"
},
  "geometry": {"coordinates":[-16.3771266937,28.4956588745],"type":"Point"}
}