{
  "type": "Feature",
  "properties": {
    "iso:country":"ES",
    "sg:address":"Carrer de M D Montserrat, 116",
    "sg:city":"Viladecans",
    "sg:orig_category":"Zapatos (al Por Menor)",
    "sg:phone":"+34 936 47 31 23",
    "sg:postcode":"08840",
    "sg:province":"Barcelona",
    "wof:name":"Calzados Jaime Vila S.l.",
    "wof:placetype":"venue"
},
  "geometry": {"coordinates":[2.0112099648,41.3260803223],"type":"Point"}
}