{
  "type": "Feature",
  "properties": {
    "iso:country":"ES",
    "sg:address":"Carrer de Girona, 14",
    "sg:city":"Mollet Valles",
    "sg:orig_category":"Transportes Por Carretera: Lotes Completos, Mercanc\u00cdas Diversas",
    "sg:phone":"+34 935 70 17 31",
    "sg:postcode":"08100",
    "sg:province":"Barcelona",
    "wof:name":"La Vostra Cuina S.l.",
    "wof:placetype":"venue"
},
  "geometry": {"coordinates":[2.207570076,41.5342826843],"type":"Point"}
}