{
  "type": "Feature",
  "properties": {
    "iso:country":"ES",
    "sg:address":"Carr Ciutat De Lleida, 4",
    "sg:city":"Mollerussa",
    "sg:orig_category":"Asesor\u00cda Fiscal Y Jur\u00cddica",
    "sg:phone":"+34 973 60 11 39",
    "sg:postcode":"25230",
    "sg:province":"Lleida",
    "wof:name":"Servicios Contables S.l.",
    "wof:placetype":"venue"
},
  "geometry": {"coordinates":[0.8962849975,41.629825592],"type":"Point"}
}