{
  "type": "Feature",
  "properties": {
    "addr:full":"Avda Blasco Iba\u00d1ez, 26 Bu\u00f1ol Valencia 46360",
    "addr:housenumber":"26",
    "addr:postcode":"46360",
    "addr:street":"Avda Blasco Iban\u0303Ez",
    "iso:country":"ES",
    "sg:address":"Avda Blasco Iba\u00d1ez, 26",
    "sg:city":"Bu\u00f1ol",
    "sg:orig_category":"Asesor\u00cda Sobre Comunicaci\u00d3n De Empresas",
    "sg:phone":"+34 962 50 02 46",
    "sg:postcode":"46360",
    "sg:province":"Valencia",
    "wof:name":"Paco Galarza Asesores S.l.",
    "wof:placetype":"venue"
},
  "geometry": {"coordinates":[-0.7871609926,39.4257621765],"type":"Point"}
}