{
  "type": "Feature",
  "properties": {
    "iso:country":"ES",
    "sg:address":"Calle de Misericordia, 7",
    "sg:city":"Medina Rioseco",
    "sg:orig_category":"Inmobiliaria (agencias)",
    "sg:phone":"+34 983 70 00 68",
    "sg:postcode":"47800",
    "sg:province":"Valladolid",
    "wof:name":"Habitat Intermedio S.l.",
    "wof:placetype":"venue"
},
  "geometry": {"coordinates":[-5.0432190895,41.881603241],"type":"Point"}
}