{
  "type": "Feature",
  "properties": {
    "iso:country":"ES",
    "sg:address":"Calle de Molinos, 42",
    "sg:city":"Moron Frontera",
    "sg:orig_category":"Molduras, Junquillos, Listones Y Molduras Perforadas",
    "sg:phone":"+34 954 85 06 62",
    "sg:postcode":"41530",
    "sg:province":"Sevilla",
    "wof:name":"Bocanegra Rodriguez Juan",
    "wof:placetype":"venue"
},
  "geometry": {"coordinates":[-5.4560270309,37.1187210083],"type":"Point"}
}