{
  "type": "Feature",
  "properties": {
    "addr:full":"Ciento Treinta B, S/n Masias Valencia 46116",
    "addr:housenumber":"s / n",
    "addr:postcode":"46116",
    "iso:country":"ES",
    "sg:address":"Ciento Treinta B, S/n",
    "sg:city":"Masias",
    "sg:orig_category":"Agencias Y Asesores De Publicidad",
    "sg:phone":"+34 961 30 09 22",
    "sg:postcode":"46116",
    "sg:province":"Valencia",
    "sg:website":"www.joyfel.com",
    "wof:name":"Distribuciones Publicitarias Joyfer S.l",
    "wof:placetype":"venue"
},
  "geometry": {"coordinates":[-0.4100939929,39.5571746826],"type":"Point"}
}