{
  "type": "Feature",
  "properties": {
    "iso:country":"ES",
    "sg:address":"Calle de Manuel Tovar, 45",
    "sg:city":"Madrid",
    "sg:orig_category":"Aparatos, Material Y Suministros Para Laboratorios",
    "sg:phone":"+34 913 58 06 29",
    "sg:postcode":"28034",
    "sg:province":"Madrid",
    "wof:name":"Biomerieux S. A.",
    "wof:placetype":"venue"
},
  "geometry": {"coordinates":[-3.6926081181,40.4887008667],"type":"Point"}
}