{
  "type": "Feature",
  "properties": {
    "addr:full":"Avda Sancho El Sabio, 26 Donostia-san Sebastian Guip\u00f9zcoa 20010",
    "addr:housenumber":"26",
    "addr:postcode":"20010",
    "addr:street":"Avda Sancho El Sabio",
    "iso:country":"ES",
    "sg:address":"Avda Sancho El Sabio, 26",
    "sg:city":"Donostia-san Sebastian",
    "sg:orig_category":"Molduras, Junquillos, Listones Y Molduras Perforadas",
    "sg:phone":"+34 943 46 19 98",
    "sg:postcode":"20010",
    "sg:province":"Guip\u00f9zcoa",
    "wof:name":"Otero Fernandez Antonio",
    "wof:placetype":"venue"
},
  "geometry": {"coordinates":[-1.9799870253,43.3086051941],"type":"Point"}
}