{
  "type": "Feature",
  "properties": {
    "addr:full":"San Lorentzo Auzoa, 10 O\u00f1ati Guip\u00f9zcoa 20560",
    "addr:housenumber":"10",
    "addr:postcode":"20560",
    "addr:street":"San Lorentzo Auzoa;Guipu\u0300Zcoa",
    "iso:country":"ES",
    "sg:address":"San Lorentzo Auzoa, 10",
    "sg:city":"O\u00f1ati",
    "sg:orig_category":"Molduras, Junquillos, Listones Y Molduras Perforadas",
    "sg:phone":"+34 943 78 33 47",
    "sg:postcode":"20560",
    "sg:province":"Guip\u00f9zcoa",
    "wof:name":"Teciruna S.l.",
    "wof:placetype":"venue"
},
  "geometry": {"coordinates":[-2.405203104,43.0318450928],"type":"Point"}
}