{
  "type": "Feature",
  "properties": {
    "iso:country":"ES",
    "sg:address":"Rua Pontevedra, S/n",
    "sg:city":"Santa Comba",
    "sg:orig_category":"Plomeros",
    "sg:phone":"+34 981 88 03 29",
    "sg:postcode":"15840",
    "sg:province":"La Coru\u00f1a",
    "wof:name":"Amigo Garcia Manuel",
    "wof:placetype":"venue"
},
  "geometry": {"coordinates":[-8.8101882935,43.0326690674],"type":"Point"}
}