{
  "type": "Feature",
  "properties": {
    "iso:country":"ES",
    "sg:address":"Calle de Concepcion Arenal, 37",
    "sg:city":"Madro\u00f1era",
    "sg:orig_category":"Electricidad: Instaladores",
    "sg:phone":"+34 927 33 40 51",
    "sg:postcode":"10210",
    "sg:province":"C\u00e1ceres",
    "wof:name":"Gil Costa Eladio",
    "wof:placetype":"venue"
},
  "geometry": {"coordinates":[-5.7570810318,39.4227714539],"type":"Point"}
}