{
  "type": "Feature",
  "properties": {
    "addr:full":"Calle de Francisco Iglesias, 24 Madrid Madrid 28038",
    "addr:housenumber":"24",
    "addr:postcode":"madrid;28038",
    "addr:street":"Calle De Francisco Iglesias",
    "iso:country":"ES",
    "sg:address":"Calle de Francisco Iglesias, 24",
    "sg:city":"Madrid",
    "sg:orig_category":"M\u00c9dicos: Medicina General Orientada A La Homeopat\u00cda",
    "sg:phone":"+34 914 33 80 05",
    "sg:postcode":"28038",
    "sg:province":"Madrid",
    "wof:name":"Llorente Reyes C.b.",
    "wof:placetype":"venue"
},
  "geometry": {"coordinates":[-3.6651940346,40.3985862732],"type":"Point"}
}