{
  "type": "Feature",
  "properties": {
    "iso:country":"ES",
    "sg:address":"Calle de Doctor Esquerdo, 110",
    "sg:city":"Madrid",
    "sg:orig_category":"Librer\u00cdas",
    "sg:phone":"+34 915 01 95 11",
    "sg:postcode":"28007",
    "sg:province":"Madrid",
    "wof:name":"Diaz Flores Felipe",
    "wof:placetype":"venue"
},
  "geometry": {"coordinates":[-3.670122385,40.4092330933],"type":"Point"}
}