{
  "type": "Feature",
  "properties": {
    "addr:full":"Carr Santisimo Cristo, 12 Oliva Valencia 46780",
    "addr:housenumber":"12",
    "addr:postcode":"46780",
    "addr:street":"Carr Santisimo Cristo",
    "iso:country":"ES",
    "sg:address":"Carr Santisimo Cristo, 12",
    "sg:city":"Oliva",
    "sg:orig_category":"Agentes Generales De Seguros",
    "sg:phone":"+34 962 83 96 39",
    "sg:postcode":"46780",
    "sg:province":"Valencia",
    "wof:name":"Cerrajeros El Autonomo Oscar Marino Lamamie",
    "wof:placetype":"venue"
},
  "geometry": {"coordinates":[-0.1221290007,38.9185714722],"type":"Point"}
}