{
  "type": "Feature",
  "properties": {
    "addr:full":"Calle de Antonio Maura, 32 Oviedo Asturias 33012",
    "addr:housenumber":"32",
    "addr:postcode":"33012",
    "addr:street":"Calle De Antonio Maura",
    "iso:country":"ES",
    "sg:address":"Calle de Antonio Maura, 32",
    "sg:city":"Oviedo",
    "sg:orig_category":"Estancos",
    "sg:phone":"+34 985 25 65 81",
    "sg:postcode":"33012",
    "sg:province":"Asturias",
    "wof:name":"Arguelles Rodriguez Manuel",
    "wof:placetype":"venue"
},
  "geometry": {"coordinates":[-5.8627524376,43.3655128479],"type":"Point"}
}