{
  "type": "Feature",
  "properties": {
    "addr:full":"Calle de Camilo Jose Cela, 1 Solana Ciudad Real 13240",
    "addr:housenumber":"1",
    "addr:postcode":"solana;13240",
    "addr:street":"Calle De Camilo Jose Cela;Real",
    "iso:country":"ES",
    "sg:address":"Calle de Camilo Jose Cela, 1",
    "sg:city":"Solana",
    "sg:orig_category":"Armas Y Municiones (fabricaci\u00d3n, Al Por Mayor)",
    "sg:phone":"+34 926 63 14 29",
    "sg:postcode":"13240",
    "sg:province":"Ciudad Real",
    "wof:name":"Chaparro Mateos-aparicio Francisco",
    "wof:placetype":"venue"
},
  "geometry": {"coordinates":[-3.2350788116,38.9385032654],"type":"Point"}
}