{
  "type": "Feature",
  "properties": {
    "addr:full":"Avda Herencia, S/n Alcazar S. Juan Ciudad Real 13600",
    "addr:housenumber":"s / n",
    "addr:postcode":"13600",
    "addr:street":"Avda Herencia;Alcazar S. Juan Ciudad Real",
    "iso:country":"ES",
    "sg:address":"Avda Herencia, S/n",
    "sg:city":"Alcazar S. Juan",
    "sg:orig_category":"Asociaciones Y Clubs Deportivos",
    "sg:phone":"+34 926 54 03 05",
    "sg:postcode":"13600",
    "sg:province":"Ciudad Real",
    "wof:name":"Club De Futbol Ginnastico De Alcazar De San Juan",
    "wof:placetype":"venue"
},
  "geometry": {"coordinates":[-3.2183539867,39.3883552551],"type":"Point"}
}