{
  "type": "Feature",
  "properties": {
    "addr:full":"Calle de Arguelles, 18 Arriondas Asturias 33540",
    "addr:housenumber":"18",
    "addr:postcode":"33540",
    "addr:street":"Calle De Arguelles",
    "iso:country":"ES",
    "sg:address":"Calle de Arguelles, 18",
    "sg:city":"Arriondas",
    "sg:orig_category":"Explotaci\u00d3n De Bosques",
    "sg:phone":"+34 985 84 10 65",
    "sg:postcode":"33540",
    "sg:province":"Asturias",
    "wof:name":"Calvo Heredia Marta",
    "wof:placetype":"venue"
},
  "geometry": {"coordinates":[-5.1877074242,43.388053894],"type":"Point"}
}