{
  "type": "Feature",
  "properties": {
    "addr:full":"Camino De La Roda, Km. 0002,0 Pozoamargo Cuenca 16708",
    "addr:postcode":"16708",
    "addr:street":"Camino De La Roda Km. 0002,0",
    "iso:country":"ES",
    "sg:address":"Camino De La Roda, Km. 0002,0",
    "sg:city":"Pozoamargo",
    "sg:orig_category":"M\u00c9dicos: Medicina General Orientada A La Acupuntura",
    "sg:phone":"+34 969 38 76 90",
    "sg:postcode":"16708",
    "sg:province":"Cuenca",
    "wof:name":"Tien C.b.",
    "wof:placetype":"venue"
},
  "geometry": {"coordinates":[-2.1951870918,39.3646965027],"type":"Point"}
}