{
  "type": "Feature",
  "properties": {
    "iso:country":"ES",
    "sg:address":"Dique Sur, S/n",
    "sg:city":"Melilla",
    "sg:orig_category":"Aguas (distribuci\u00d3n, Servicios)",
    "sg:phone":"+34 952 67 76 30",
    "sg:postcode":"52006",
    "sg:province":"Melilla",
    "wof:name":"Tratamientos Tecnicos Aguas S.a.",
    "wof:placetype":"venue"
},
  "geometry": {"coordinates":[-2.9361999035,35.2828216553],"type":"Point"}
}