{
  "type": "Feature",
  "properties": {
    "addr:full":"Rua Galiano, 1 Ferrol La Coru\u00f1a 15402",
    "addr:housenumber":"1",
    "addr:postcode":"15402",
    "addr:street":"Rua Galiano;La Corun\u0303A",
    "iso:country":"ES",
    "sg:address":"Rua Galiano, 1",
    "sg:city":"Ferrol",
    "sg:orig_category":"Farmacias",
    "sg:phone":"+34 981 32 14 68",
    "sg:postcode":"15402",
    "sg:province":"La Coru\u00f1a",
    "wof:name":"Guerreiro Gonzalez Fernando",
    "wof:placetype":"venue"
},
  "geometry": {"coordinates":[-8.2291641235,43.485874176],"type":"Point"}
}