{
  "type": "Feature",
  "properties": {
    "iso:country":"ES",
    "sg:address":"Av Argentina, 12",
    "sg:city":"Palma",
    "sg:orig_category":"Dietistas",
    "sg:phone":"+34 971 45 61 84",
    "sg:postcode":"07011",
    "sg:province":"Islas Baleares",
    "wof:name":"Puig Mojer Marta",
    "wof:placetype":"venue"
},
  "geometry": {"coordinates":[2.6408350468,39.5736618042],"type":"Point"}
}