{
  "type": "Feature",
  "properties": {
    "addr:full":"Calle de Molino Velasco, S/n Velez-malaga M\u00e1laga 29700",
    "addr:postcode":"29700",
    "addr:street":"Calle De Molino Velasco S / N Velez-Malaga Ma\u0301Laga",
    "iso:country":"ES",
    "sg:address":"Calle de Molino Velasco, S/n",
    "sg:city":"Velez-malaga",
    "sg:orig_category":"Carnicer\u00cdas, Carnicer\u00cdas",
    "sg:phone":"+34 952 50 32 46",
    "sg:postcode":"29700",
    "sg:province":"M\u00e1laga",
    "wof:name":"Pelaez Mu\u00f1oz Purificacion",
    "wof:placetype":"venue"
},
  "geometry": {"coordinates":[-4.102025032,36.7747764587],"type":"Point"}
}