{
  "type": "Feature",
  "properties": {
    "iso:country":"ES",
    "sg:address":"Calle de Asistente Arjona, 7",
    "sg:city":"Osuna",
    "sg:orig_category":"Flores Y Plantas Naturales (al Por Mayor)",
    "sg:phone":"+34 954 81 01 56",
    "sg:postcode":"41640",
    "sg:province":"Sevilla",
    "wof:name":"Zamora Alvarez Antonio",
    "wof:placetype":"venue"
},
  "geometry": {"coordinates":[-5.10247612,37.2368431091],"type":"Point"}
}