{
  "type": "Feature",
  "properties": {
    "iso:country":"ES",
    "sg:address":"Av Alcudia, 99",
    "sg:city":"Benissa",
    "sg:orig_category":"Peluquer\u00cdas, Peluquer\u00cda Mixta",
    "sg:phone":"+34 965 73 17 37",
    "sg:postcode":"03720",
    "sg:province":"Alicante",
    "wof:name":"Peluqueria Laygos S.c",
    "wof:placetype":"venue"
},
  "geometry": {"coordinates":[0.0458000004,38.7130317688],"type":"Point"}
}