{
  "type": "Feature",
  "properties": {
    "iso:country":"ES",
    "sg:address":"Calle de Cervantes, 20",
    "sg:city":"Pe\u00e7arroya-pueblonuevo",
    "sg:orig_category":"Transportes Por Carretera: Lotes Completos, Mercanc\u00cdas Diversas",
    "sg:phone":"+34 957 56 04 80",
    "sg:postcode":"14200",
    "sg:province":"C\u00f3rdoba",
    "wof:name":"Transportes Togar S.l.",
    "wof:placetype":"venue"
},
  "geometry": {"coordinates":[-5.2641129494,38.2975158691],"type":"Point"}
}