{
  "type": "Feature",
  "properties": {
    "addr:full":"Calle de Marques De Urquijo, 15 Madrid Madrid 28008",
    "addr:housenumber":"15",
    "addr:postcode":"madrid;28008",
    "addr:street":"Calle De Marques De Urquijo",
    "iso:country":"ES",
    "sg:address":"Calle de Marques De Urquijo, 15",
    "sg:city":"Madrid",
    "sg:orig_category":"Art\u00cdculos De Regalo (al Por Menor)",
    "sg:phone":"+34 915 47 91 73",
    "sg:postcode":"28008",
    "sg:province":"Madrid",
    "wof:name":"Diaz Agudelo Francisco",
    "wof:placetype":"venue"
},
  "geometry": {"coordinates":[-3.7178320885,40.4299888611],"type":"Point"}
}