{
  "type": "Feature",
  "properties": {
    "addr:full":"Urb Monte Elvira, S/n Albolote Granada 18220",
    "addr:housenumber":"s / n",
    "addr:postcode":"18220",
    "iso:country":"ES",
    "sg:address":"Urb Monte Elvira, S/n",
    "sg:city":"Albolote",
    "sg:orig_category":"Lavado, Limpieza De Veh\u00cdculos",
    "sg:phone":"+34 958 46 53 44",
    "sg:postcode":"18220",
    "sg:province":"Granada",
    "wof:name":"Carrocerias Autosvillegas S.l",
    "wof:placetype":"venue"
},
  "geometry": {"coordinates":[-3.6585440636,37.2332839966],"type":"Point"}
}