{
  "type": "Feature",
  "properties": {
    "addr:full":"Calle de Arrabal, 13 Santander Cantabria 39003",
    "addr:housenumber":"13",
    "addr:postcode":"39003",
    "addr:street":"Calle De Arrabal",
    "iso:country":"ES",
    "sg:address":"Calle de Arrabal, 13",
    "sg:city":"Santander",
    "sg:orig_category":"Ropa Para Se\u00d1oras (al Por Menor)",
    "sg:phone":"+34 942 31 11 56",
    "sg:postcode":"39003",
    "sg:province":"Cantabria",
    "wof:name":"Urgarte Sainz Marta",
    "wof:placetype":"venue"
},
  "geometry": {"coordinates":[-3.8049020767,43.4631156921],"type":"Point"}
}