{
  "type": "Feature",
  "properties": {
    "iso:country":"ES",
    "sg:address":"Calle de Huesca (de), 4",
    "sg:city":"Fuenlabrada",
    "sg:orig_category":"Arreglo, Reparaci\u00d3n, Piezas Sueltas De Televisi\u00d3n, V\u00cddeo, Hi",
    "sg:phone":"+34 916 90 70 99",
    "sg:postcode":"28941",
    "sg:province":"Madrid",
    "wof:name":"Donher Electronica S.l.",
    "wof:placetype":"venue"
},
  "geometry": {"coordinates":[-3.7951180935,40.2944221497],"type":"Point"}
}