{
  "type": "Feature",
  "properties": {
    "iso:country":"ES",
    "sg:address":"Avda Palo Dulce, 26",
    "sg:city":"Gibraleon",
    "sg:orig_category":"Discapacitados",
    "sg:phone":"+34 959 30 24 03",
    "sg:postcode":"21500",
    "sg:province":"Huelva",
    "wof:name":"Asociacion De Discapacitados Propio Impulso",
    "wof:placetype":"venue"
},
  "geometry": {"coordinates":[-6.9678120613,37.3747062683],"type":"Point"}
}