{
  "type": "Feature",
  "properties": {
    "iso:country":"ES",
    "sg:address":"Carrer de Ginebra, 26",
    "sg:city":"Barcelona",
    "sg:orig_category":"Molduras, Junquillos, Listones Y Molduras Perforadas",
    "sg:phone":"+34 932 68 29 80",
    "sg:postcode":"08003",
    "sg:province":"Barcelona",
    "wof:name":"Audifonos Y Telefonos S.l.",
    "wof:placetype":"venue"
},
  "geometry": {"coordinates":[2.1896269321,41.3817405701],"type":"Point"}
}