{
  "type": "Feature",
  "properties": {
    "iso:country":"ES",
    "sg:address":"Carrer de Tous I Maroto, 4",
    "sg:city":"Palma",
    "sg:orig_category":"Complementos De Vestir (al Por Menor)",
    "sg:phone":"+34 971 72 83 49",
    "sg:postcode":"07001",
    "sg:province":"Islas Baleares",
    "wof:name":"Navarro Marcoa Yolanda",
    "wof:placetype":"venue"
},
  "geometry": {"coordinates":[2.6479790211,39.5694274902],"type":"Point"}
}