{
  "type": "Feature",
  "properties": {
    "addr:full":"Ctra Pe\u00d1afiel, 3 Canalejas De Pe\u00e7afiel Valladolid 47311",
    "addr:housenumber":"3",
    "addr:postcode":"47311",
    "addr:street":"Ctra Pen\u0303Afiel",
    "iso:country":"ES",
    "sg:address":"Ctra Pe\u00d1afiel, 3",
    "sg:city":"Canalejas De Pe\u00e7afiel",
    "sg:orig_category":"Maquinaria Para Industrias Diversas",
    "sg:phone":"+34 983 89 21 54",
    "sg:postcode":"47311",
    "sg:province":"Valladolid",
    "wof:name":"Santos Arranz Isidoro",
    "wof:placetype":"venue"
},
  "geometry": {"coordinates":[-4.1132898331,41.5253372192],"type":"Point"}
}