{
  "type": "Feature",
  "properties": {
    "addr:full":"Calle de Meliton Corti\u00d1as, 8 Viveiro Lugo 27850",
    "addr:housenumber":"8",
    "addr:postcode":"27850",
    "addr:street":"Calle De Meliton Cortin\u0303As",
    "iso:country":"ES",
    "sg:address":"Calle de Meliton Corti\u00d1as, 8",
    "sg:city":"Viveiro",
    "sg:orig_category":"Ropa Para Ni\u00d1os (al Por Menor)",
    "sg:phone":"+34 982 55 09 03",
    "sg:postcode":"27850",
    "sg:province":"Lugo",
    "wof:name":"Rodriguez Ramos Raquel",
    "wof:placetype":"venue"
},
  "geometry": {"coordinates":[-7.5962991714,43.6611289978],"type":"Point"}
}