{
  "type": "Feature",
  "properties": {
    "iso:country":"ES",
    "sg:address":"Calle de Don Quijote, 20",
    "sg:city":"Molina Segura",
    "sg:orig_category":"Reposter\u00cdas",
    "sg:phone":"+34 968 61 61 60",
    "sg:postcode":"30500",
    "sg:province":"Murcia",
    "wof:name":"Ramos Aznar Juan De Dios",
    "wof:placetype":"venue"
},
  "geometry": {"coordinates":[-1.2052657604,38.0472259521],"type":"Point"}
}