{
  "type": "Feature",
  "properties": {
    "addr:full":"Av Meridiana, 348 Barcelona Barcelona 08027",
    "addr:housenumber":"348",
    "addr:postcode":"08027",
    "addr:street":"Meridiana",
    "iso:country":"ES",
    "sg:address":"Av Meridiana, 348",
    "sg:city":"Barcelona",
    "sg:orig_category":"Plomeros",
    "sg:phone":"+34 932 74 41 96",
    "sg:postcode":"08027",
    "sg:province":"Barcelona",
    "wof:name":"Grupo Unisit S.a.",
    "wof:placetype":"venue"
},
  "geometry": {"coordinates":[2.1857349873,41.4267807007],"type":"Point"}
}