{
  "type": "Feature",
  "properties": {
    "addr:full":"Carr Ample, 18 Bisbal D'emporda Girona 17100",
    "addr:housenumber":"18",
    "addr:postcode":"17100",
    "addr:street":"Carr Ample",
    "iso:country":"ES",
    "sg:address":"Carr Ample, 18",
    "sg:city":"Bisbal D'emporda",
    "sg:orig_category":"Peluqueros: De Se\u00d1oras",
    "sg:phone":"+34 972 64 23 43",
    "sg:postcode":"17100",
    "sg:province":"Girona",
    "wof:name":"Janoher Frigola Josep",
    "wof:placetype":"venue"
},
  "geometry": {"coordinates":[2.813131094,41.9749221802],"type":"Point"}
}