{
  "type": "Feature",
  "properties": {
    "iso:country":"ES",
    "sg:address":"Avda Historiador Bernardo Herrero, 35",
    "sg:city":"Sax",
    "sg:orig_category":"Materias Pl\u00c1sticas: Productos De Consumo Masivo (fabricaci\u00d3n, Al Por Mayor)",
    "sg:phone":"+34 965 47 56 64",
    "sg:postcode":"03630",
    "sg:province":"Alicante",
    "wof:name":"Creaciones Frut Mary S.l.",
    "wof:placetype":"venue"
},
  "geometry": {"coordinates":[-0.8217170238,38.5338935852],"type":"Point"}
}