{
  "type": "Feature",
  "properties": {
    "iso:country":"ES",
    "sg:address":"Rua Aragon, 9",
    "sg:city":"Vigo",
    "sg:orig_category":"Confiter\u00cdas, Chocolater\u00cdas (al Por Menor)",
    "sg:phone":"+34 986 37 73 94",
    "sg:postcode":"36206",
    "sg:province":"Pontevedra",
    "wof:name":"Fernandez Garcia Luisa",
    "wof:placetype":"venue"
},
  "geometry": {"coordinates":[-8.7023353577,42.2314529419],"type":"Point"}
}