{
  "type": "Feature",
  "properties": {
    "addr:full":"O Crucero(san Miguel), S/n Rosal Pontevedra 36760",
    "addr:housenumber":"s / n",
    "addr:postcode":"36760",
    "addr:street":"San Miguel",
    "iso:country":"ES",
    "sg:address":"O Crucero(san Miguel), S/n",
    "sg:city":"Rosal",
    "sg:orig_category":"Asociaciones, Organismos Culturales Y Socioeducativos",
    "sg:phone":"+34 986 61 38 69",
    "sg:postcode":"36760",
    "sg:province":"Pontevedra",
    "wof:name":"Sociedad Recreativa Y Cultural Centro San Miguel",
    "wof:placetype":"venue"
},
  "geometry": {"coordinates":[-8.8146686554,41.9170913696],"type":"Point"}
}