{
  "type": "Feature",
  "properties": {
    "addr:full":"Calle de Tortola, 13 Fuenlabrada Madrid 28946",
    "addr:housenumber":"13",
    "addr:postcode":"28946",
    "addr:street":"Calle De Tortola",
    "iso:country":"ES",
    "sg:address":"Calle de Tortola, 13",
    "sg:city":"Fuenlabrada",
    "sg:orig_category":"Adaptaciones, Acondicionamientos Especiales Para Veh\u00cdculos, Veh\u00cdculos Industriales",
    "sg:phone":"+34 916 42 15 54",
    "sg:postcode":"28946",
    "sg:province":"Madrid",
    "wof:name":"Talleres Mape S.c.",
    "wof:placetype":"venue"
},
  "geometry": {"coordinates":[-3.761826992,40.2649688721],"type":"Point"}
}