{
  "type": "Feature",
  "properties": {
    "addr:full":"Carrer de Puigmal, S/n Vic Barcelona 08500",
    "addr:housenumber":"s",
    "addr:postcode":"08500",
    "addr:street":"Carrer De Puigmal;/ N",
    "iso:country":"ES",
    "sg:address":"Carrer de Puigmal, S/n",
    "sg:city":"Vic",
    "sg:orig_category":"T\u00c9cnicos Veterinarios",
    "sg:phone":"+34 938 86 17 73",
    "sg:postcode":"08500",
    "sg:province":"Barcelona",
    "wof:name":"Sola Pairo Juan",
    "wof:placetype":"venue"
},
  "geometry": {"coordinates":[2.2446689606,41.9341926575],"type":"Point"}
}