{
  "type": "Feature",
  "properties": {
    "iso:country":"ES",
    "sg:address":"San Fermin, 55",
    "sg:city":"Iru\u00f1a",
    "sg:orig_category":"Productos Fitosanitarios (negocio, Aplicaci\u00d3n)",
    "sg:phone":"+34 948 24 65 99",
    "sg:postcode":"31003",
    "sg:province":"Navarra",
    "wof:name":"Comercial Del Campo Navarra S. L.",
    "wof:placetype":"venue"
},
  "geometry": {"coordinates":[-1.6411679983,42.8106880188],"type":"Point"}
}