{
  "type": "Feature",
  "properties": {
    "iso:country":"ES",
    "sg:address":"Plaz Espa\u00d1a, 1",
    "sg:city":"Sanlucar Guadiana",
    "sg:orig_category":"Administraciones Regionales, Departamentales Y Locales",
    "sg:phone":"+34 959 38 80 71",
    "sg:postcode":"21595",
    "sg:province":"Huelva",
    "wof:name":"Ayuntamiento De Sanlucar De Guadiana",
    "wof:placetype":"venue"
},
  "geometry": {"coordinates":[-7.4675960541,37.473941803],"type":"Point"}
}