{
  "type": "Feature",
  "properties": {
    "addr:full":"Calle de Santiago, 2 Sang\u00fcesa Navarra 31400",
    "addr:housenumber":"2",
    "addr:postcode":"31400",
    "addr:street":"Calle De Santiago",
    "iso:country":"ES",
    "sg:address":"Calle de Santiago, 2",
    "sg:city":"Sang\u00fcesa",
    "sg:orig_category":"Alquiler De V\u00cddeo",
    "sg:phone":"+34 948 43 02 20",
    "sg:postcode":"31400",
    "sg:province":"Navarra",
    "wof:name":"Echeverria Ayesa Ana Isabel",
    "wof:placetype":"venue"
},
  "geometry": {"coordinates":[-1.283182025,42.5753173828],"type":"Point"}
}