{
  "type": "Feature",
  "properties": {
    "iso:country":"ES",
    "sg:address":"Carrer de Juvenal, 12",
    "sg:city":"Sabadell",
    "sg:orig_category":"Farmacias",
    "sg:phone":"+34 937 16 08 27",
    "sg:postcode":"08206",
    "sg:province":"Barcelona",
    "wof:name":"Herrero Torres Ignacio",
    "wof:placetype":"venue"
},
  "geometry": {"coordinates":[2.0851049423,41.5552711487],"type":"Point"}
}