{
  "type": "Feature",
  "properties": {
    "addr:full":"Calle de Estebanes, 31 Zaragoza Zaragoza 50003",
    "addr:housenumber":"31",
    "addr:postcode":"50003",
    "addr:street":"Calle De Estebanes",
    "iso:country":"ES",
    "sg:address":"Calle de Estebanes, 31",
    "sg:city":"Zaragoza",
    "sg:orig_category":"Fabricaci\u00d3n, Venta De Productos Base Farmac\u00c9uticos",
    "sg:phone":"+34 976 29 76 80",
    "sg:postcode":"50003",
    "sg:province":"Zaragoza",
    "wof:name":"Farmacia Ucelay C.b.",
    "wof:placetype":"venue"
},
  "geometry": {"coordinates":[-0.8798208833,41.6532821655],"type":"Point"}
}