{
  "type": "Feature",
  "properties": {
    "iso:country":"ES",
    "sg:address":"Goribar Auzoa, S/n",
    "sg:city":"Goribar",
    "sg:orig_category":"Producci\u00d3n De Cart\u00d3n",
    "sg:phone":"+34 943 78 30 94",
    "sg:postcode":"20560",
    "sg:province":"Guip\u00f9zcoa",
    "wof:name":"Cartonajes Arregui S. L.",
    "wof:placetype":"venue"
},
  "geometry": {"coordinates":[-2.4079990387,43.0313835144],"type":"Point"}
}