{
  "type": "Feature",
  "properties": {
    "iso:country":"ES",
    "sg:address":"Calle de Principe De Asturias, 10",
    "sg:city":"Pinoso",
    "sg:orig_category":"Peluquer\u00cdas, Peluquer\u00cda Mixta",
    "sg:phone":"+34 965 47 78 18",
    "sg:postcode":"03650",
    "sg:province":"Alicante",
    "wof:name":"Perez Canto Maria Jose",
    "wof:placetype":"venue"
},
  "geometry": {"coordinates":[-1.0397759676,38.3997268677],"type":"Point"}
}