{
  "type": "Feature",
  "properties": {
    "iso:country":"ES",
    "sg:address":"Calle de Jose Ortega Y Gasset, 1",
    "sg:city":"Arrecife",
    "sg:orig_category":"Instalaci\u00d3n, Reparaci\u00d3n De Ascensores Y Montacargas",
    "sg:phone":"+34 928 80 01 22",
    "sg:postcode":"35500",
    "sg:province":"Las Palmas",
    "sg:website":"www.otis.com",
    "wof:name":"Zardoya Otis S.a.",
    "wof:placetype":"venue"
},
  "geometry": {"coordinates":[-13.5559024811,28.9610042572],"type":"Point"}
}