{
  "type": "Feature",
  "properties": {
    "addr:full":"Plaz Fresco El, 1 Zamora Zamora 49004",
    "addr:postcode":"49004",
    "iso:country":"ES",
    "sg:address":"Plaz Fresco El, 1",
    "sg:city":"Zamora",
    "sg:orig_category":"Agentes, Concesionarios Y Sucursales De Veh\u00cdculos",
    "sg:phone":"+34 980 53 17 47",
    "sg:postcode":"49004",
    "sg:province":"Zamora",
    "wof:name":"De Dios Pe\u00f1in Jose Jorge",
    "wof:placetype":"venue"
},
  "geometry": {"coordinates":[-5.7457342148,41.5033302307],"type":"Point"}
}