{
  "type": "Feature",
  "properties": {
    "addr:full":"Calle de Suecia, 3 Madrid Madrid 28022",
    "addr:housenumber":"3",
    "addr:postcode":"28022",
    "addr:street":"Calle De Suecia",
    "iso:country":"ES",
    "sg:address":"Calle de Suecia, 3",
    "sg:city":"Madrid",
    "sg:orig_category":"Zapatos (al Por Menor)",
    "sg:phone":"+34 917 75 65 03",
    "sg:postcode":"28022",
    "sg:province":"Madrid",
    "wof:name":"Mas Cebrian Antonio",
    "wof:placetype":"venue"
},
  "geometry": {"coordinates":[-3.6099770069,40.4218063354],"type":"Point"}
}