{
  "type": "Feature",
  "properties": {
    "iso:country":"ES",
    "sg:address":"Ptge Diposit, S/n",
    "sg:city":"S. Andreu Llavaneres",
    "sg:orig_category":"M\u00c9dicos: Cardiolog\u00cda Y Afecciones Cardiovasculares",
    "sg:phone":"+34 937 92 67 69",
    "sg:postcode":"08392",
    "sg:province":"Barcelona",
    "wof:name":"Torner Soler Miguel",
    "wof:placetype":"venue"
},
  "geometry": {"coordinates":[2.482352972,41.5803756714],"type":"Point"}
}