{
  "type": "Feature",
  "properties": {
    "iso:country":"ES",
    "sg:address":"Plaz Universidad (de La), S/n",
    "sg:city":"Granada",
    "sg:orig_category":"Iglesia Cat\u00d3lica",
    "sg:phone":"+34 958 27 87 92",
    "sg:postcode":"18001",
    "sg:province":"Granada",
    "wof:name":"Parroquia De San Justo Y Pastor",
    "wof:placetype":"venue"
},
  "geometry": {"coordinates":[-3.6016340256,37.1783218384],"type":"Point"}
}