{
  "type": "Feature",
  "properties": {
    "iso:country":"ES",
    "sg:address":"Calle de Murga, 48",
    "sg:city":"Palmas De Gran Canaria",
    "sg:orig_category":"Art\u00cdculos De Decoraci\u00d3n (fabricaci\u00d3n Y Al Por Mayor)",
    "sg:phone":"+34 928 37 33 52",
    "sg:postcode":"35003",
    "sg:province":"Las Palmas",
    "wof:name":"Santana Marrero Leoncio",
    "wof:placetype":"venue"
},
  "geometry": {"coordinates":[-15.4215669632,28.110042572],"type":"Point"}
}