{
  "type": "Feature",
  "properties": {
    "addr:full":"Rua Restollal (do), 37 Santiago De Compostela La Coru\u00f1a 15...",
    "addr:housenumber":"37;15 ...",
    "addr:street":"Rua Restollal Do;Corun\u0303A",
    "iso:country":"ES",
    "sg:address":"Rua Restollal (do), 37",
    "sg:city":"Santiago De Compostela",
    "sg:orig_category":"Agencias De Trabajo Temporal",
    "sg:phone":"+34 981 59 05 65",
    "sg:postcode":"15...",
    "sg:province":"La Coru\u00f1a",
    "wof:name":"Nortempo Empresa De Trabajo Temporal S.l.",
    "wof:placetype":"venue"
},
  "geometry": {"coordinates":[-8.5424451828,42.8637084961],"type":"Point"}
}