{
  "type": "Feature",
  "properties": {
    "iso:country":"ES",
    "sg:address":"Calle de Tejerias, S/n",
    "sg:city":"Lapuebla Labarca",
    "sg:orig_category":"Internados & Ense\u00d1anza Privada",
    "sg:phone":"+34 945 60 71 99",
    "sg:postcode":"01306",
    "sg:province":"\u00c1lava",
    "wof:name":"Ikastola Assa Sociedad Cooperativa Limitada",
    "wof:placetype":"venue"
},
  "geometry": {"coordinates":[-2.577393055,42.4931793213],"type":"Point"}
}