{
  "type": "Feature",
  "properties": {
    "addr:full":"Carrer de Major, 56 Castellbisbal Barcelona 08755",
    "addr:housenumber":"56",
    "addr:postcode":"08755",
    "addr:street":"Carrer De Major",
    "iso:country":"ES",
    "sg:address":"Carrer de Major, 56",
    "sg:city":"Castellbisbal",
    "sg:orig_category":"Quincaller\u00cda (al Por Menor)",
    "sg:phone":"+34 937 72 07 22",
    "sg:postcode":"08755",
    "sg:province":"Barcelona",
    "wof:name":"Ferreteria Y Drogueria Roure Juni S.l.",
    "wof:placetype":"venue"
},
  "geometry": {"coordinates":[1.9800260067,41.476764679],"type":"Point"}
}