{
  "type": "Feature",
  "properties": {
    "addr:full":"Calle de San Fermin, 9 Motril Granada 18600",
    "addr:housenumber":"9",
    "addr:postcode":"18600",
    "addr:street":"Calle De San Fermin",
    "iso:country":"ES",
    "sg:address":"Calle de San Fermin, 9",
    "sg:city":"Motril",
    "sg:orig_category":"Confiter\u00cdas, Chocolater\u00cdas (al Por Menor)",
    "sg:phone":"+34 958 82 09 99",
    "sg:postcode":"18600",
    "sg:province":"Granada",
    "wof:name":"Garcia Moreno Antonio",
    "wof:placetype":"venue"
},
  "geometry": {"coordinates":[-3.5097088814,36.7524795532],"type":"Point"}
}