{
  "type": "Feature",
  "properties": {
    "iso:country":"ES",
    "sg:address":"Calle de Don Bosco, 4",
    "sg:city":"Ubeda",
    "sg:orig_category":"Pod\u00d3logos: Pedicuros",
    "sg:phone":"+34 953 75 34 32",
    "sg:postcode":"23400",
    "sg:province":"Ja\u00e9n",
    "wof:name":"Sevilla Martinez Francisco",
    "wof:placetype":"venue"
},
  "geometry": {"coordinates":[-3.3769180775,38.014087677],"type":"Point"}
}