{
  "type": "Feature",
  "properties": {
    "addr:full":"Avda Solana, 35 Mentrida Toledo 45930",
    "addr:housenumber":"35",
    "addr:postcode":"45930",
    "addr:street":"Avda Solana",
    "iso:country":"ES",
    "sg:address":"Avda Solana, 35",
    "sg:city":"Mentrida",
    "sg:orig_category":"Supermercados Y Hipermercados",
    "sg:phone":"+34 918 17 71 51",
    "sg:postcode":"45930",
    "sg:province":"Toledo",
    "wof:name":"Supermercados Brunete S.l.",
    "wof:placetype":"venue"
},
  "geometry": {"coordinates":[-4.1902990341,40.2380485535],"type":"Point"}
}