{
  "type": "Feature",
  "properties": {
    "addr:full":"Ptda Murteres, S/n Vinaros Castell\u00f3n 12500",
    "addr:housenumber":"s / n",
    "addr:postcode":"12500",
    "addr:street":"Ptda Murteres",
    "iso:country":"ES",
    "sg:address":"Ptda Murteres, S/n",
    "sg:city":"Vinaros",
    "sg:orig_category":"Frutas Y Legumbres Frescas (al Por Mayor)",
    "sg:phone":"+34 964 40 05 37",
    "sg:postcode":"12500",
    "sg:province":"Castell\u00f3n",
    "wof:name":"Inmueble Torver S.a.",
    "wof:placetype":"venue"
},
  "geometry": {"coordinates":[0.4408037066,40.501701355],"type":"Point"}
}