{
  "type": "Feature",
  "properties": {
    "iso:country":"ES",
    "sg:address":"Calle de Akilino Arriola, 10",
    "sg:city":"Moreaga",
    "sg:orig_category":"Agencias Y Agentes Comerciales, Representantes",
    "sg:phone":"+34 946 76 18 54",
    "sg:postcode":"48600",
    "sg:province":"Vizcaya",
    "wof:name":"Comunidad De Propietarios Aquilino Arriola 12",
    "wof:placetype":"venue"
},
  "geometry": {"coordinates":[-2.9855926037,43.3797683716],"type":"Point"}
}