{
  "type": "Feature",
  "properties": {
    "addr:full":"Calle de San Jose, 61 Yecla Murcia 30510",
    "addr:housenumber":"61",
    "addr:postcode":"30510",
    "addr:street":"Calle De San",
    "iso:country":"ES",
    "sg:address":"Calle de San Jose, 61",
    "sg:city":"Yecla",
    "sg:orig_category":"Ropa Para Se\u00d1oras (al Por Menor)",
    "sg:phone":"+34 968 79 19 59",
    "sg:postcode":"30510",
    "sg:province":"Murcia",
    "wof:name":"Azorin Vall Purificacion",
    "wof:placetype":"venue"
},
  "geometry": {"coordinates":[-1.1121007204,38.6129150391],"type":"Point"}
}