{
  "type": "Feature",
  "properties": {
    "iso:country":"ES",
    "sg:address":"Plaz Mercado, 4",
    "sg:city":"Barbastro",
    "sg:orig_category":"Pescader\u00cdas (al Por Menor)",
    "sg:phone":"+34 974 31 09 95",
    "sg:postcode":"22300",
    "sg:province":"Huesca",
    "wof:name":"Miguel Heredia Inmaculada",
    "wof:placetype":"venue"
},
  "geometry": {"coordinates":[0.125485003,42.0363769531],"type":"Point"}
}