{
  "type": "Feature",
  "properties": {
    "iso:country":"ES",
    "sg:address":"Calle de Autonomia, 9",
    "sg:city":"San Vicente De Barakaldo",
    "sg:orig_category":"Agencias Y Agentes Comerciales, Representantes",
    "sg:phone":"+34 944 38 35 39",
    "sg:postcode":"48902",
    "sg:province":"Vizcaya",
    "wof:name":"N. Myrtle",
    "wof:placetype":"venue"
},
  "geometry": {"coordinates":[-2.9898409843,43.2949676514],"type":"Point"}
}