{
  "type": "Feature",
  "properties": {
    "addr:full":"Avda Sandoval, 9 Santiago Ribera Murcia 30720",
    "addr:housenumber":"9",
    "addr:postcode":"30720",
    "addr:street":"Avda Sandoval",
    "iso:country":"ES",
    "sg:address":"Avda Sandoval, 9",
    "sg:city":"Santiago Ribera",
    "sg:orig_category":"Contenedores (mercanc\u00cdas)",
    "sg:phone":"+34 968 57 21 28",
    "sg:postcode":"30720",
    "sg:province":"Murcia",
    "wof:name":"Navarro Salinas Jesus",
    "wof:placetype":"venue"
},
  "geometry": {"coordinates":[-0.8055070043,37.7973518372],"type":"Point"}
}