{
  "type": "Feature",
  "properties": {
    "iso:country":"ES",
    "sg:address":"Avda Ollerias (de Las), 19",
    "sg:city":"Cordoba",
    "sg:orig_category":"Suministros Y Materiales Industriales",
    "sg:phone":"+34 957 48 33 17",
    "sg:postcode":"14001",
    "sg:province":"C\u00f3rdoba",
    "wof:name":"Sierra Cuenca S.l.",
    "wof:placetype":"venue"
},
  "geometry": {"coordinates":[-4.7740440369,37.8919792175],"type":"Point"}
}