{
  "type": "Feature",
  "properties": {
    "addr:full":"Carr Creu, 20 Girona Girona 17002",
    "addr:housenumber":"20",
    "addr:postcode":"17002",
    "addr:street":"Carr Creu",
    "iso:country":"ES",
    "sg:address":"Carr Creu, 20",
    "sg:city":"Girona",
    "sg:orig_category":"M\u00c9dicos: Psiquiatr\u00cda",
    "sg:phone":"+34 972 22 44 57",
    "sg:postcode":"17002",
    "sg:province":"Girona",
    "wof:name":"Benitez Eiroa Andres",
    "wof:placetype":"venue"
},
  "geometry": {"coordinates":[2.8187448978,41.9808616638],"type":"Point"}
}