{
  "type": "Feature",
  "properties": {
    "iso:country":"ES",
    "sg:address":"Plaz Estrella, 3",
    "sg:city":"Iniesta",
    "sg:orig_category":"Alimentaci\u00d3n General (al Por Mayor)",
    "sg:phone":"+34 967 49 03 13",
    "sg:postcode":"16235",
    "sg:province":"Cuenca",
    "wof:name":"Fajardo Diaz Jose Leopoldo",
    "wof:placetype":"venue"
},
  "geometry": {"coordinates":[-1.7448840141,39.4404411316],"type":"Point"}
}