{
  "type": "Feature",
  "properties": {
    "iso:country":"ES",
    "sg:address":"Rua Urzaiz, 120",
    "sg:city":"Vigo",
    "sg:orig_category":"Asociaciones, Organismos Culturales Y Socioeducativos",
    "sg:phone":"+34 986 48 16 00",
    "sg:postcode":"36204",
    "sg:province":"Pontevedra",
    "wof:name":"Asociacion Cultural Gallega De Formacion Permanente De Adultos",
    "wof:placetype":"venue"
},
  "geometry": {"coordinates":[-8.7087202072,42.2315139771],"type":"Point"}
}