{
  "type": "Feature",
  "properties": {
    "iso:country":"ES",
    "sg:address":"C. Boque, S/n",
    "sg:city":"Las Norias",
    "sg:orig_category":"Fotocopias, Reprograf\u00cda",
    "sg:phone":"+34 950 60 68 91",
    "sg:postcode":"04716",
    "sg:province":"Almer\u00eda",
    "wof:name":"Reciponiente S.l.",
    "wof:placetype":"venue"
},
  "geometry": {"coordinates":[-2.7524790764,36.7588195801],"type":"Point"}
}