{
  "type": "Feature",
  "properties": {
    "iso:country":"ES",
    "sg:address":"Calle de Morera, 18",
    "sg:city":"Santiago El Mayor",
    "sg:orig_category":"Electricidad: Equipos Industriales, Componentes (fabricaci\u00d3n)",
    "sg:phone":"+34 968 34 69 16",
    "sg:postcode":"30012",
    "sg:province":"Murcia",
    "wof:name":"Tecnosur S.l.",
    "wof:placetype":"venue"
},
  "geometry": {"coordinates":[-1.1255890131,37.9707870483],"type":"Point"}
}