{
  "type": "Feature",
  "properties": {
    "iso:country":"ES",
    "sg:address":"Plaz Mayor, 1",
    "sg:city":"Cantimpalos",
    "sg:orig_category":"Abogados",
    "sg:phone":"+34 921 49 64 27",
    "sg:postcode":"40360",
    "sg:province":"Segovia",
    "wof:name":"Ayuntamiento De Cantimpalos",
    "wof:placetype":"venue"
},
  "geometry": {"coordinates":[-4.1582875252,41.0744972229],"type":"Point"}
}