{
  "type": "Feature",
  "properties": {
    "addr:full":"Calle de Jazmines, 2 Ugijar Granada 18480",
    "addr:housenumber":"2",
    "addr:postcode":"18480",
    "addr:street":"Calle De Jazmines",
    "iso:country":"ES",
    "sg:address":"Calle de Jazmines, 2",
    "sg:city":"Ugijar",
    "sg:orig_category":"Fotograf\u00cda Y Cine: Aparatos, Pel\u00cdculas Y Accesorios (fabricaci\u00d3n, Al Por Mayor)",
    "sg:phone":"+34 958 85 40 23",
    "sg:postcode":"18480",
    "sg:province":"Granada",
    "wof:name":"Fernandez Garcia Manuel",
    "wof:placetype":"venue"
},
  "geometry": {"coordinates":[-3.0542740822,36.9632530212],"type":"Point"}
}