{
  "type": "Feature",
  "properties": {
    "iso:country":"ES",
    "sg:address":"Calle de Libertad, 55",
    "sg:city":"Tias",
    "sg:orig_category":"Inform\u00c1tica, Ofim\u00c1tica (estudios, Asesor\u00cda, Ingenier\u00cda, Formaci\u00d3n)",
    "sg:phone":"+34 928 52 40 75",
    "sg:postcode":"35572",
    "sg:province":"Las Palmas",
    "wof:name":"Lanzacomputer S.l.",
    "wof:placetype":"venue"
},
  "geometry": {"coordinates":[-13.6533231735,28.9525260925],"type":"Point"}
}