{
  "type": "Feature",
  "properties": {
    "iso:country":"ES",
    "sg:address":"Calle de Pez Volador, 20",
    "sg:city":"Madrid",
    "sg:orig_category":"Agencias Y Agentes Comerciales, Representantes",
    "sg:phone":"+34 915 73 83 95",
    "sg:postcode":"28007",
    "sg:province":"Madrid",
    "wof:name":"Gonzalez Casado Miguel",
    "wof:placetype":"venue"
},
  "geometry": {"coordinates":[-3.6673619747,40.413318634],"type":"Point"}
}