{
  "type": "Feature",
  "properties": {
    "iso:country":"ES",
    "sg:address":"Plaz Salvador (el), 1",
    "sg:city":"Soria",
    "sg:orig_category":"Arquitectos",
    "sg:phone":"+34 975 23 00 62",
    "sg:postcode":"42001",
    "sg:province":"Soria",
    "wof:name":"Gimenez Morales Luis",
    "wof:placetype":"venue"
},
  "geometry": {"coordinates":[-2.4691669941,41.7646598816],"type":"Point"}
}