{
  "type": "Feature",
  "properties": {
    "addr:full":"Calle de Luarca, S/n Bomberos Madrid 28250",
    "addr:housenumber":"s / n",
    "addr:postcode":"28250",
    "addr:street":"Calle De Luarca",
    "iso:country":"ES",
    "sg:address":"Calle de Luarca, S/n",
    "sg:city":"Bomberos",
    "sg:orig_category":"Supermercados Y Hipermercados",
    "sg:phone":"+34 918 59 35 17",
    "sg:postcode":"28250",
    "sg:province":"Madrid",
    "sg:website":"www.mercadona.es",
    "wof:name":"Mercadona S.a.",
    "wof:placetype":"venue"
},
  "geometry": {"coordinates":[-3.9306790829,40.57654953],"type":"Point"}
}