{
  "type": "Feature",
  "properties": {
    "addr:full":"Calle de Amor De Dios, 15 Madrid Madrid 28014",
    "addr:housenumber":"15",
    "addr:postcode":"madrid;28014",
    "addr:street":"Calle De Amor De Dios",
    "iso:country":"ES",
    "sg:address":"Calle de Amor De Dios, 15",
    "sg:city":"Madrid",
    "sg:orig_category":"Peluqueros: De Se\u00d1oras",
    "sg:phone":"+34 914 29 95 49",
    "sg:postcode":"28014",
    "sg:province":"Madrid",
    "wof:name":"Cabello Cotera Francisco Jose",
    "wof:placetype":"venue"
},
  "geometry": {"coordinates":[-3.6984722614,40.4125556946],"type":"Point"}
}