{
  "type": "Feature",
  "properties": {
    "iso:country":"ES",
    "sg:address":"Cmno Castejon (de), S/n",
    "sg:city":"Ventarique",
    "sg:orig_category":"Confecci\u00d3n De Ropa Interior",
    "sg:phone":"+34 968 47 20 57",
    "sg:postcode":"30800",
    "sg:province":"Murcia",
    "wof:name":"Lencelor S.l.",
    "wof:placetype":"venue"
},
  "geometry": {"coordinates":[-1.6905640364,37.680557251],"type":"Point"}
}