{
  "type": "Feature",
  "properties": {
    "addr:full":"Calle de Rey Don Pelayo, 4 Roda Albacete 02630",
    "addr:housenumber":"4",
    "addr:postcode":"02630",
    "addr:street":"Calle De Rey Don Pelayo",
    "iso:country":"ES",
    "sg:address":"Calle de Rey Don Pelayo, 4",
    "sg:city":"Roda",
    "sg:orig_category":"Centros De Coordinaci\u00d3n",
    "sg:phone":"+34 967 44 34 45",
    "sg:postcode":"02630",
    "sg:province":"Albacete",
    "wof:name":"Huedo Martinez Sagrario",
    "wof:placetype":"venue"
},
  "geometry": {"coordinates":[-2.1599180698,39.2055397034],"type":"Point"}
}