{
  "type": "Feature",
  "properties": {
    "iso:country":"ES",
    "sg:address":"Calle de Rioja, 6",
    "sg:city":"Zaragoza",
    "sg:orig_category":"Cristaler\u00cdas",
    "sg:phone":"+34 976 53 37 71",
    "sg:postcode":"50017",
    "sg:province":"Zaragoza",
    "wof:name":"Gascler S.l.",
    "wof:placetype":"venue"
},
  "geometry": {"coordinates":[-0.9102979898,41.6526451111],"type":"Point"}
}