{
  "type": "Feature",
  "properties": {
    "addr:full":"Calle de Ollerias, 51 Andujar Ja\u00e9n 23740",
    "addr:housenumber":"51",
    "addr:postcode":"23740",
    "addr:street":"Calle De Ollerias",
    "iso:country":"ES",
    "sg:address":"Calle de Ollerias, 51",
    "sg:city":"Andujar",
    "sg:orig_category":"Bancos",
    "sg:phone":"+34 953 50 02 35",
    "sg:postcode":"23740",
    "sg:province":"Ja\u00e9n",
    "wof:name":"Banco Espa\u00f1ol De Credito S.a.",
    "wof:placetype":"venue"
},
  "geometry": {"coordinates":[-4.0546789169,38.0393829346],"type":"Point"}
}