{
  "type": "Feature",
  "properties": {
    "addr:full":"Calle de Antillas, S/n Puerto De Santa Maria C\u00e1diz 11500",
    "addr:housenumber":"s / n",
    "addr:postcode":"11500",
    "addr:street":"Calle De Antillas;Ca\u0301Diz",
    "iso:country":"ES",
    "sg:address":"Calle de Antillas, S/n",
    "sg:city":"Puerto De Santa Maria",
    "sg:orig_category":"Peluquer\u00cdas, Peluquer\u00cda Mixta",
    "sg:phone":"+34 956 87 21 87",
    "sg:postcode":"11500",
    "sg:province":"C\u00e1diz",
    "wof:name":"Castillo Ventura Rosa",
    "wof:placetype":"venue"
},
  "geometry": {"coordinates":[-6.2450313568,36.5934066772],"type":"Point"}
}