{
  "type": "Feature",
  "properties": {
    "addr:full":"Calle de Deire, S/n Torrox M\u00e1laga 29770",
    "addr:housenumber":"s / n",
    "addr:postcode":"29770",
    "addr:street":"Calle De Deire",
    "iso:country":"ES",
    "sg:address":"Calle de Deire, S/n",
    "sg:city":"Torrox",
    "sg:classifiers":[
        {
            "category":"Taxi",
            "type":"Transportation"
        }
    ],
    "sg:phone":"+34 952 53 80 45",
    "sg:postcode":"29770",
    "sg:province":"M\u00e1laga",
    "wof:name":"Bueno Castro Manuel",
    "wof:placetype":"venue"
},
  "geometry": {"coordinates":[-3.9546689987,36.7476959229],"type":"Point"}
}