{
  "type": "Feature",
  "properties": {
    "addr:full":"Rua Fari\u00d1a Ferre\u00d1o, 2 Vilagarcia Pontevedra 36600",
    "addr:housenumber":"2",
    "addr:postcode":"36600",
    "addr:street":"Rua Farin\u0303A Ferren\u0303O",
    "iso:country":"ES",
    "sg:address":"Rua Fari\u00d1a Ferre\u00d1o, 2",
    "sg:city":"Vilagarcia",
    "sg:orig_category":"Inform\u00c1tica, Ofim\u00c1tica (estudios, Asesor\u00cda, Ingenier\u00cda, Formaci\u00d3n)",
    "sg:phone":"+34 986 51 26 02",
    "sg:postcode":"36600",
    "sg:province":"Pontevedra",
    "wof:name":"Tecnologia Fonteboa S.l.",
    "wof:placetype":"venue"
},
  "geometry": {"coordinates":[-8.7636508942,42.5924377441],"type":"Point"}
}