{
  "type": "Feature",
  "properties": {
    "iso:country":"ES",
    "sg:address":"Calle de Salcillo, 1",
    "sg:city":"Mostoles",
    "sg:orig_category":"Artes Gr\u00c1ficas, Artes Pl\u00c1sticas (curso)",
    "sg:phone":"+34 916 13 25 63",
    "sg:postcode":"28932",
    "sg:province":"Madrid",
    "wof:name":"Rayo Sanchez Benito",
    "wof:placetype":"venue"
},
  "geometry": {"coordinates":[-3.8627450466,40.3342514038],"type":"Point"}
}