{
  "type": "Feature",
  "properties": {
    "addr:full":"Calle de San Fernando, 44 Villena Alicante 03400",
    "addr:housenumber":"44",
    "addr:postcode":"03400",
    "addr:street":"Calle De San Fernando",
    "iso:country":"ES",
    "sg:address":"Calle de San Fernando, 44",
    "sg:city":"Villena",
    "sg:orig_category":"Dibujo",
    "sg:phone":"+34 965 80 73 06",
    "sg:postcode":"03400",
    "sg:province":"Alicante",
    "wof:name":"Vidal Macias Juan",
    "wof:placetype":"venue"
},
  "geometry": {"coordinates":[-0.8634290099,38.6376800537],"type":"Point"}
}