{
  "type": "Feature",
  "properties": {
    "iso:country":"ES",
    "sg:address":"Calle de Nicanor Del Campo, 14",
    "sg:city":"Luarca",
    "sg:orig_category":"Inform\u00c1tica (estudios, Servicios, Asesor\u00cda, Formaci\u00d3n)",
    "sg:phone":"+34 985 64 14 75",
    "sg:postcode":"33700",
    "sg:province":"Asturias",
    "wof:name":"Perez Perez Andres",
    "wof:placetype":"venue"
},
  "geometry": {"coordinates":[-6.5369348526,43.5415496826],"type":"Point"}
}