{
  "type": "Feature",
  "properties": {
    "iso:country":"ES",
    "sg:address":"Calle de Virgen Del Rocio, 3",
    "sg:city":"Alacant",
    "sg:orig_category":"Servidores Y Editores De Bases De Datos",
    "sg:phone":"+34 965 17 52 28",
    "sg:postcode":"03009",
    "sg:province":"Alicante",
    "sg:website":"www.alicante-ciudad.com",
    "wof:name":"Lazaro Poveda Francisco Javier",
    "wof:placetype":"venue"
},
  "geometry": {"coordinates":[-0.5003299713,38.3674049377],"type":"Point"}
}