{
  "type": "Feature",
  "properties": {
    "addr:full":"Plaz Joaquin Maria Lopez, 7 Alacant Alicante 03009",
    "addr:postcode":"03009",
    "addr:street":"Lopez",
    "iso:country":"ES",
    "sg:address":"Plaz Joaquin Maria Lopez, 7",
    "sg:city":"Alacant",
    "sg:orig_category":"Locales Y Clases De Danza",
    "sg:phone":"+34 965 17 53 62",
    "sg:postcode":"03009",
    "sg:province":"Alicante",
    "wof:name":"Castro Beekman Guillermina",
    "wof:placetype":"venue"
},
  "geometry": {"coordinates":[-0.4952819943,38.3622894287],"type":"Point"}
}