{
  "type": "Feature",
  "properties": {
    "iso:country":"ES",
    "sg:address":"Calle de Leon Felipe, 8",
    "sg:city":"Madrid",
    "sg:orig_category":"Molduras, Junquillos, Listones Y Molduras Perforadas",
    "sg:phone":"+34 913 80 10 96",
    "sg:postcode":"28038",
    "sg:province":"Madrid",
    "wof:name":"Sierra Manzanero Antonio",
    "wof:placetype":"venue"
},
  "geometry": {"coordinates":[-3.6365039349,40.387878418],"type":"Point"}
}