{
  "type": "Feature",
  "properties": {
    "iso:country":"ES",
    "sg:address":"Calle de Emilio Llorente Navacerrada, 30",
    "sg:city":"Torrelodones",
    "sg:orig_category":"Ingenier\u00cda, Centros De Estudios (diversos)",
    "sg:phone":"+34 918 59 41 06",
    "sg:postcode":"28250",
    "sg:province":"Madrid",
    "sg:website":"www.image-ingenieria-alimentaria.com",
    "wof:name":"Image Ingenieria Marketing Y Gestion S.l.",
    "wof:placetype":"venue"
},
  "geometry": {"coordinates":[-3.9334859848,40.5813102722],"type":"Point"}
}