{
  "type": "Feature",
  "properties": {
    "iso:country":"ES",
    "sg:address":"Carrer de Fernando Pessoa, 9",
    "sg:city":"Barcelona",
    "sg:orig_category":"Venta, Localizaci\u00d3n, Reparaci\u00d3n De Material E Instrumental M\u00c9dico",
    "sg:phone":"+34 933 45 07 27",
    "sg:postcode":"08030",
    "sg:province":"Barcelona",
    "wof:name":"Quirurgical Bontempi Espa\u00f1a S.l.",
    "wof:placetype":"venue"
},
  "geometry": {"coordinates":[2.1933050156,41.4381790161],"type":"Point"}
}