{
  "type": "Feature",
  "properties": {
    "addr:full":"Paraje Los Algibes, 32 Ejido Almer\u00eda 04700",
    "addr:housenumber":"32 ejido",
    "addr:postcode":"04700",
    "addr:street":"Paraje Los Algibes;Almeri\u0301A",
    "iso:country":"ES",
    "sg:address":"Paraje Los Algibes, 32",
    "sg:city":"Ejido",
    "sg:orig_category":"Frutas Y Legumbres Frescas (al Por Mayor)",
    "sg:phone":"+34 950 48 51 51",
    "sg:postcode":"04700",
    "sg:province":"Almer\u00eda",
    "sg:website":"www.dofran.com",
    "wof:name":"Frutas Y Hortalizas Dofran S.l.",
    "wof:placetype":"venue"
},
  "geometry": {"coordinates":[-2.8176040649,36.7727012634],"type":"Point"}
}