{
  "type": "Feature",
  "properties": {
    "addr:full":"Ronda Del Golf, S/n Benalmadena-costa M\u00e1laga 29630",
    "addr:housenumber":"s / n",
    "addr:postcode":"29630",
    "addr:street":"Ronda Del Golf;Ma\u0301Laga",
    "iso:country":"ES",
    "sg:address":"Ronda Del Golf, S/n",
    "sg:city":"Benalmadena-costa",
    "sg:orig_category":"Agencias De Viajes",
    "sg:phone":"+34 952 44 54 87",
    "sg:postcode":"29630",
    "sg:province":"M\u00e1laga",
    "wof:name":"Anchica S.a.",
    "wof:placetype":"venue"
},
  "geometry": {"coordinates":[-4.5476050377,36.5820808411],"type":"Point"}
}