{
  "type": "Feature",
  "properties": {
    "addr:full":"Carrer de Major, 1 Montcada Centre Barcelona 08110",
    "addr:housenumber":"1",
    "addr:postcode":"08110",
    "addr:street":"Carrer De Major",
    "iso:country":"ES",
    "sg:address":"Carrer de Major, 1",
    "sg:city":"Montcada Centre",
    "sg:orig_category":"Papeler\u00cdas, Librer\u00cdas",
    "sg:phone":"+34 935 64 25 89",
    "sg:postcode":"08110",
    "sg:province":"Barcelona",
    "wof:name":"Castillo Campoy Augusto",
    "wof:placetype":"venue"
},
  "geometry": {"coordinates":[2.1881930828,41.4873313904],"type":"Point"}
}