{
  "type": "Feature",
  "properties": {
    "addr:full":"Ctra Villacastin, S/n Tabara Zamora 49140",
    "addr:housenumber":"s / n",
    "addr:postcode":"49140",
    "addr:street":"Ctra Villacastin",
    "iso:country":"ES",
    "sg:address":"Ctra Villacastin, S/n",
    "sg:city":"Tabara",
    "sg:orig_category":"Albergues",
    "sg:phone":"+34 980 59 01 36",
    "sg:postcode":"49140",
    "sg:province":"Zamora",
    "wof:name":"Bar Restaurante Fonda Galicia",
    "wof:placetype":"venue"
},
  "geometry": {"coordinates":[-5.9588150978,41.8262939453],"type":"Point"}
}