{
  "type": "Feature",
  "properties": {
    "iso:country":"ES",
    "sg:address":"Calle de Karmen, S/n",
    "sg:city":"Amorebieta",
    "sg:orig_category":"Caf\u00c9s, Bares, Cervecer\u00cdas",
    "sg:phone":"+34 946 73 15 95",
    "sg:postcode":"48340",
    "sg:province":"Vizcaya",
    "wof:name":"Usaola Uribe Ana Isabel",
    "wof:placetype":"venue"
},
  "geometry": {"coordinates":[-2.7321670055,43.2206420898],"type":"Point"}
}