{
  "type": "Feature",
  "properties": {
    "addr:full":"Avda Galicia De, 8 Salas Asturias 33860",
    "addr:postcode":"33860",
    "addr:street":"Avda Galicia De 8",
    "iso:country":"ES",
    "sg:address":"Avda Galicia De, 8",
    "sg:city":"Salas",
    "sg:orig_category":"Transportes Por Carretera: Lotes Completos, Mercanc\u00cdas Diversas",
    "sg:phone":"+34 985 83 00 24",
    "sg:postcode":"33860",
    "sg:province":"Asturias",
    "wof:name":"Grupo El Arbol Distribucion Y Supermercados S.a. Unipersonal",
    "wof:placetype":"venue"
},
  "geometry": {"coordinates":[-6.2590689659,43.4085884094],"type":"Point"}
}