{
  "type": "Feature",
  "properties": {
    "addr:full":"Calle de Zaragoza, 1 Huesca Huesca 22002",
    "addr:housenumber":"1",
    "addr:postcode":"22002",
    "addr:street":"Calle De Zaragoza",
    "iso:country":"ES",
    "sg:address":"Calle de Zaragoza, 1",
    "sg:city":"Huesca",
    "sg:orig_category":"Bancos",
    "sg:phone":"+34 974 24 12 61",
    "sg:postcode":"22002",
    "sg:province":"Huesca",
    "wof:name":"Bankinter S.a.",
    "wof:placetype":"venue"
},
  "geometry": {"coordinates":[-0.4083940089,42.1356163025],"type":"Point"}
}