{
  "type": "Feature",
  "properties": {
    "iso:country":"ES",
    "sg:address":"Darsena De Levante, 25",
    "sg:city":"Benalmadena-costa",
    "sg:orig_category":"Fabricaci\u00d3n De Juguetes Autom\u00c1ticos",
    "sg:phone":"+34 952 56 00 03",
    "sg:postcode":"29630",
    "sg:province":"M\u00e1laga",
    "wof:name":"Keabeech Espa\u00d1a S.l.",
    "wof:placetype":"venue"
},
  "geometry": {"coordinates":[-4.521381855,36.5971374512],"type":"Point"}
}