{
  "type": "Feature",
  "properties": {
    "addr:full":"Kale Nagusia, 40 Azkoitia Guip\u00f9zcoa 20720",
    "addr:housenumber":"40",
    "addr:postcode":"20720",
    "addr:street":"Kale Nagusia;Guipu\u0300Zcoa",
    "iso:country":"ES",
    "sg:address":"Kale Nagusia, 40",
    "sg:city":"Azkoitia",
    "sg:orig_category":"Art\u00cdculos De Decoraci\u00d3n",
    "sg:phone":"+34 943 02 53 21",
    "sg:postcode":"20720",
    "sg:province":"Guip\u00f9zcoa",
    "wof:name":"Martinzar, Iziar Larra\u00f1aga Ansola",
    "wof:placetype":"venue"
},
  "geometry": {"coordinates":[-2.3134639263,43.1762886047],"type":"Point"}
}