{
  "type": "Feature",
  "properties": {
    "addr:full":"Cm\u00d1o Espi\u00d1eiro, S/n Vigo Pontevedra 36207",
    "addr:housenumber":"s",
    "addr:postcode":"36207",
    "addr:street":"/ N",
    "iso:country":"ES",
    "sg:address":"Cm\u00d1o Espi\u00d1eiro, S/n",
    "sg:city":"Vigo",
    "sg:orig_category":"Empresas De Carpinter\u00cda De Madera",
    "sg:phone":"+34 986 26 48 40",
    "sg:postcode":"36207",
    "sg:province":"Pontevedra",
    "wof:name":"Reparaciones Generales Navales S.a.",
    "wof:placetype":"venue"
},
  "geometry": {"coordinates":[-8.701751709,42.2519798279],"type":"Point"}
}