{
  "type": "Feature",
  "properties": {
    "iso:country":"ES",
    "sg:address":"Carrer de Pacific, 54",
    "sg:city":"Barcelona",
    "sg:orig_category":"Abogados",
    "sg:phone":"+34 933 51 58 63",
    "sg:postcode":"08027",
    "sg:province":"Barcelona",
    "wof:name":"Campillo Torrecilla Carlos Jose",
    "wof:placetype":"venue"
},
  "geometry": {"coordinates":[2.1881759167,41.4263916016],"type":"Point"}
}