{
  "type": "Feature",
  "properties": {
    "iso:country":"ES",
    "sg:address":"Fumoril(cueto), 30",
    "sg:city":"Cueto",
    "sg:orig_category":"Inmobiliaria (agencias)",
    "sg:phone":"+34 942 39 12 67",
    "sg:postcode":"39012",
    "sg:province":"Cantabria",
    "wof:name":"Barreda Y Mendez S.l.",
    "wof:placetype":"venue"
},
  "geometry": {"coordinates":[-3.8604888916,43.4665527344],"type":"Point"}
}