{
  "type": "Feature",
  "properties": {
    "addr:full":"Calle de Real, S/n Belvis Jara Toledo 45660",
    "addr:housenumber":"s / n",
    "addr:postcode":"45660",
    "addr:street":"Calle De Real",
    "iso:country":"ES",
    "sg:address":"Calle de Real, S/n",
    "sg:city":"Belvis Jara",
    "sg:orig_category":"Negocio De Materiales De Construcci\u00d3n",
    "sg:phone":"+34 925 85 82 50",
    "sg:postcode":"45660",
    "sg:province":"Toledo",
    "wof:name":"Basilio Basilio Jesus",
    "wof:placetype":"venue"
},
  "geometry": {"coordinates":[-4.9487538338,39.7602729797],"type":"Point"}
}