{
  "type": "Feature",
  "properties": {
    "addr:full":"Pla Pou, 23 Paterna Valencia 46980",
    "addr:housenumber":"23",
    "addr:postcode":"46980",
    "addr:street":"Pla Pou",
    "iso:country":"ES",
    "sg:address":"Pla Pou, 23",
    "sg:city":"Paterna",
    "sg:orig_category":"Farmacias (repartici\u00d3n Y Al Por Mayor)",
    "sg:phone":"+34 961 32 20 23",
    "sg:postcode":"46980",
    "sg:province":"Valencia",
    "wof:name":"Suministros A Farmacias O.t.c. S.l.",
    "wof:placetype":"venue"
},
  "geometry": {"coordinates":[-0.4395389855,39.500629425],"type":"Point"}
}