{
  "type": "Feature",
  "properties": {
    "addr:full":"Zepai Kalea, 6 Idiazabal Guip\u00f9zcoa 20213",
    "addr:housenumber":"6",
    "addr:postcode":"20213",
    "addr:street":"Zepai Kalea;Guipu\u0300Zcoa",
    "iso:country":"ES",
    "sg:address":"Zepai Kalea, 6",
    "sg:city":"Idiazabal",
    "sg:orig_category":"Centros De Educaci\u00d3n Especial",
    "sg:phone":"+34 943 18 71 51",
    "sg:postcode":"20213",
    "sg:province":"Guip\u00f9zcoa",
    "wof:name":"Gobierno Vasco-eusko Jaurlaritza",
    "wof:placetype":"venue"
},
  "geometry": {"coordinates":[-2.2338349819,43.0090675354],"type":"Point"}
}