{
  "type": "Feature",
  "properties": {
    "addr:full":"Calle de Juan Bravo, 42 Madrid Madrid 28006",
    "addr:housenumber":"42",
    "addr:postcode":"madrid;28006",
    "addr:street":"Calle De Juan Bravo",
    "iso:country":"ES",
    "sg:address":"Calle de Juan Bravo, 42",
    "sg:city":"Madrid",
    "sg:orig_category":"Iglesia Cat\u00d3lica",
    "sg:phone":"+34 914 02 63 02",
    "sg:postcode":"28006",
    "sg:province":"Madrid",
    "wof:name":"Parroquia De Nuestra Se\u00d1ora Del Pilar. Madrid",
    "wof:placetype":"venue"
},
  "geometry": {"coordinates":[-3.6777470112,40.4323348999],"type":"Point"}
}