{
  "type": "Feature",
  "properties": {
    "iso:country":"ES",
    "sg:address":"Calle de Osorio, 8",
    "sg:city":"Palmas De Gran Canaria",
    "sg:orig_category":"Supermercados Y Hipermercados",
    "sg:phone":"+34 928 46 89 40",
    "sg:postcode":"35009",
    "sg:province":"Las Palmas",
    "wof:name":"Deniz Reunidos S.l.",
    "wof:placetype":"venue"
},
  "geometry": {"coordinates":[-15.4270687103,28.1527824402],"type":"Point"}
}