{
  "type": "Feature",
  "properties": {
    "iso:country":"ES",
    "sg:address":"A. Reales, Km. 0001,0",
    "sg:city":"Valladolid",
    "sg:orig_category":"Asilos De Ancianos. Centros Privados",
    "sg:phone":"+34 983 45 80 39",
    "sg:postcode":"47008",
    "sg:province":"Valladolid",
    "wof:name":"Escuelas Cristianas Hermanos De Las Distrito De Valladolid Curia Provincial",
    "wof:placetype":"venue"
},
  "geometry": {"coordinates":[-4.7927489281,41.6193618774],"type":"Point"}
}