{
  "type": "Feature",
  "properties": {
    "iso:country":"ES",
    "sg:address":"Calle de Pajarillos, S/n",
    "sg:city":"Valladolid",
    "sg:orig_category":"Discapacitados",
    "sg:phone":"+34 983 39 84 00",
    "sg:postcode":"47012",
    "sg:province":"Valladolid",
    "wof:name":"Servicios Sociales De La Junta De Castilla Y Leon",
    "wof:placetype":"venue"
},
  "geometry": {"coordinates":[-4.7039117813,41.6471138],"type":"Point"}
}