{
  "type": "Feature",
  "properties": {
    "addr:full":"Avda San Jose, 12 Gines Sevilla 41960",
    "addr:housenumber":"12",
    "addr:postcode":"41960",
    "addr:street":"Avda San Jose;Sevilla",
    "iso:country":"ES",
    "sg:address":"Avda San Jose, 12",
    "sg:city":"Gines",
    "sg:orig_category":"Arquitectos",
    "sg:phone":"+34 954 71 71 76",
    "sg:postcode":"41960",
    "sg:province":"Sevilla",
    "wof:name":"Henche Nieto Jose Ignacio",
    "wof:placetype":"venue"
},
  "geometry": {"coordinates":[-6.07878685,37.3887748718],"type":"Point"}
}