{
  "type": "Feature",
  "properties": {
    "addr:full":"Calle de Jose Serrano, 1 Jerez De La Frontera C\u00e1diz 11406",
    "addr:housenumber":"1",
    "addr:postcode":"11406",
    "addr:street":"Calle De Jose Serrano",
    "iso:country":"ES",
    "sg:address":"Calle de Jose Serrano, 1",
    "sg:city":"Jerez De La Frontera",
    "sg:orig_category":"Florister\u00cdas",
    "sg:phone":"+34 956 32 46 34",
    "sg:postcode":"11406",
    "sg:province":"C\u00e1diz",
    "wof:name":"Jimenez Ruiz Susana",
    "wof:placetype":"venue"
},
  "geometry": {"coordinates":[-6.1199169159,36.6729698181],"type":"Point"}
}