{
  "type": "Feature",
  "properties": {
    "addr:full":"Torrent D'en Negre, 8 S. Joan Despi Barcelona 08970",
    "addr:housenumber":"8",
    "addr:postcode":"08970",
    "addr:street":"Joan",
    "iso:country":"ES",
    "sg:address":"Torrent D'en Negre, 8",
    "sg:city":"S. Joan Despi",
    "sg:orig_category":"Bancos",
    "sg:phone":"+34 933 73 10 51",
    "sg:postcode":"08970",
    "sg:province":"Barcelona",
    "wof:name":"Banc Sabadell S.a.",
    "wof:placetype":"venue"
},
  "geometry": {"coordinates":[2.0570659637,41.3670005798],"type":"Point"}
}