{
  "type": "Feature",
  "properties": {
    "iso:country":"ES",
    "sg:address":"Avda Castilla (de), S/n",
    "sg:city":"Villarrubio",
    "sg:orig_category":"Muebles Y Accesorios Para Cocinas Y Cuartos De Ba\u00d1o (al Por Menor)",
    "sg:phone":"+34 969 13 60 19",
    "sg:postcode":"16420",
    "sg:province":"Cuenca",
    "sg:website":"www.bcastilla.es",
    "wof:name":"Ba\u00f1os De Castilla S.a.",
    "wof:placetype":"venue"
},
  "geometry": {"coordinates":[-2.8869988918,39.9201622009],"type":"Point"}
}