{
  "type": "Feature",
  "properties": {
    "iso:country":"ES",
    "sg:address":"Calle de Valdemorillo, 33",
    "sg:city":"Ventorro Del Cano",
    "sg:orig_category":"Bebidas",
    "sg:phone":"+34 916 33 17 74",
    "sg:postcode":"28925",
    "sg:province":"Madrid",
    "wof:name":"Calvin S. A.",
    "wof:placetype":"venue"
},
  "geometry": {"coordinates":[-3.8344049454,40.3903121948],"type":"Point"}
}