{
  "type": "Feature",
  "properties": {
    "addr:full":"Pol Ind El Romeral, S/n Durcal Granada 18650",
    "addr:housenumber":"s / n",
    "addr:postcode":"18650",
    "iso:country":"ES",
    "sg:address":"Pol Ind El Romeral, S/n",
    "sg:city":"Durcal",
    "sg:orig_category":"Empresas De Carpinter\u00cda Met\u00c1lica",
    "sg:phone":"+34 958 78 14 07",
    "sg:postcode":"18650",
    "sg:province":"Granada",
    "wof:name":"Lopez Robles Damian",
    "wof:placetype":"venue"
},
  "geometry": {"coordinates":[-3.5704190731,36.9924316406],"type":"Point"}
}