{
  "type": "Feature",
  "properties": {
    "addr:full":"Calle de Constancia, 3 Malaga M\u00e1laga 29002",
    "addr:housenumber":"3",
    "addr:postcode":"29002",
    "addr:street":"Calle De Constancia;Ma\u0301Laga",
    "iso:country":"ES",
    "sg:address":"Calle de Constancia, 3",
    "sg:city":"Malaga",
    "sg:orig_category":"Asesor\u00cda De Formaci\u00d3n Y Gesti\u00d3n De Personal",
    "sg:phone":"+34 952 04 03 97",
    "sg:postcode":"29002",
    "sg:province":"M\u00e1laga",
    "wof:name":"Juan Manuel Perez Y Asociados S.l.",
    "wof:placetype":"venue"
},
  "geometry": {"coordinates":[-4.426733017,36.7131576538],"type":"Point"}
}