{
  "type": "Feature",
  "properties": {
    "iso:country":"ES",
    "sg:address":"Pase Cayetano De Lugo, 21",
    "sg:city":"Palmas De Gran Canaria",
    "sg:orig_category":"Pod\u00d3logos: Pedicuros",
    "sg:phone":"+34 928 23 45 10",
    "sg:postcode":"35004",
    "sg:province":"Las Palmas",
    "wof:name":"Rodriguez Moreno Francisco",
    "wof:placetype":"venue"
},
  "geometry": {"coordinates":[-15.4248189926,28.1178722382],"type":"Point"}
}