{
  "type": "Feature",
  "properties": {
    "iso:country":"ES",
    "sg:address":"Calle de Casado Del Alisal, 4",
    "sg:city":"Madrid",
    "sg:orig_category":"Asociaciones, Organismos Culturales Y Socioeducativos",
    "sg:phone":"+34 914 20 34 80",
    "sg:postcode":"28014",
    "sg:province":"Madrid",
    "wof:name":"Asociacion De Los Hijos Del Sagrado Corazon",
    "wof:placetype":"venue"
},
  "geometry": {"coordinates":[-3.6910529137,40.4139175415],"type":"Point"}
}