{
  "type": "Feature",
  "properties": {
    "addr:full":"Avda Leitariegos, 6 Cangas Narcea Asturias 33800",
    "addr:housenumber":"6",
    "addr:postcode":"33800",
    "addr:street":"Avda Leitariegos",
    "iso:country":"ES",
    "sg:address":"Avda Leitariegos, 6",
    "sg:city":"Cangas Narcea",
    "sg:orig_category":"Muebles",
    "sg:phone":"+34 985 81 12 15",
    "sg:postcode":"33800",
    "sg:province":"Asturias",
    "wof:name":"Raposo Fernandez Ignacio",
    "wof:placetype":"venue"
},
  "geometry": {"coordinates":[-6.5460147858,43.1730422974],"type":"Point"}
}