{
  "type": "Feature",
  "properties": {
    "addr:full":"Carr Sant Marti, 15 Lleida Lleida 25004",
    "addr:housenumber":"15",
    "addr:postcode":"25004",
    "addr:street":"Carr Sant Marti",
    "iso:country":"ES",
    "sg:address":"Carr Sant Marti, 15",
    "sg:city":"Lleida",
    "sg:orig_category":"Administradores De Bienes Y Delegados De Comunidades De Propietarios",
    "sg:phone":"+34 973 28 25 01",
    "sg:postcode":"25004",
    "sg:province":"Lleida",
    "wof:name":"Comunidad De Propietarios Sant Marti 15",
    "wof:placetype":"venue"
},
  "geometry": {"coordinates":[0.6236119866,41.6168861389],"type":"Point"}
}