{
  "type": "Feature",
  "properties": {
    "addr:full":"Las Monta\u00f1as, 1 Villamartin C\u00e1diz 11650",
    "addr:housenumber":"1",
    "addr:postcode":"11650",
    "addr:street":"Montan\u0303As;Ca\u0301Diz",
    "iso:country":"ES",
    "sg:address":"Las Monta\u00f1as, 1",
    "sg:city":"Villamartin",
    "sg:orig_category":"Marroquiner\u00cda (confecci\u00d3n)",
    "sg:phone":"+34 956 73 09 40",
    "sg:postcode":"11650",
    "sg:province":"C\u00e1diz",
    "wof:name":"Aguilera Rivera Francisco",
    "wof:placetype":"venue"
},
  "geometry": {"coordinates":[-5.6394667625,36.8586387634],"type":"Point"}
}