{
  "type": "Feature",
  "properties": {
    "iso:country":"ES",
    "sg:address":"Raurell (z. Ind Cami Ral), 6",
    "sg:city":"Gava",
    "sg:orig_category":"Empresas De Limpieza",
    "sg:phone":"+34 936 36 00 96",
    "sg:postcode":"08850",
    "sg:province":"Barcelona",
    "wof:name":"Sodyman S.a.",
    "wof:placetype":"venue"
},
  "geometry": {"coordinates":[1.9921599627,41.2877044678],"type":"Point"}
}