{
  "type": "Feature",
  "properties": {
    "iso:country":"ES",
    "sg:address":"Carr Sant Lluis, 50",
    "sg:city":"Balaguer",
    "sg:orig_category":"Ense\u00d1anza, Formaci\u00d3n Profesional: Aprendizaje",
    "sg:phone":"+34 973 44 59 12",
    "sg:postcode":"25600",
    "sg:province":"Lleida",
    "wof:name":"Acser S. Coop.",
    "wof:placetype":"venue"
},
  "geometry": {"coordinates":[0.8088151813,41.7896347046],"type":"Point"}
}