{
  "type": "Feature",
  "properties": {
    "iso:country":"ES",
    "sg:address":"Calle de Bailen, 47",
    "sg:city":"Pinoso",
    "sg:orig_category":"Medias Y Calcetines (al Por Menor)",
    "sg:phone":"+34 965 47 73 25",
    "sg:postcode":"03650",
    "sg:province":"Alicante",
    "wof:name":"Aliaga Martinez Cristina",
    "wof:placetype":"venue"
},
  "geometry": {"coordinates":[-1.0410832167,38.3984107971],"type":"Point"}
}