{
  "type": "Feature",
  "properties": {
    "addr:full":"Calle de Villanueva, 42 Madrid Madrid 28001",
    "addr:housenumber":"42",
    "addr:postcode":"madrid;28001",
    "addr:street":"Calle De Villanueva",
    "iso:country":"ES",
    "sg:address":"Calle de Villanueva, 42",
    "sg:city":"Madrid",
    "sg:orig_category":"Comisarios",
    "sg:phone":"+34 915 78 22 01",
    "sg:postcode":"28001",
    "sg:province":"Madrid",
    "wof:name":"Ortega Machuca Jose Ramon",
    "wof:placetype":"venue"
},
  "geometry": {"coordinates":[-3.6824560165,40.4221038818],"type":"Point"}
}