{
  "type": "Feature",
  "properties": {
    "addr:full":"St. Jordi, 1 Fontcoberta Girona 17833",
    "addr:housenumber":"1",
    "addr:postcode":"17833",
    "addr:street":"Jordi",
    "iso:country":"ES",
    "sg:address":"St. Jordi, 1",
    "sg:city":"Fontcoberta",
    "sg:orig_category":"Asilos De Ancianos. Centros Privados",
    "sg:phone":"+34 972 58 15 94",
    "sg:postcode":"17833",
    "sg:province":"Girona",
    "sg:website":"www.residencialatorre.com",
    "wof:name":"Parx-2000 S.l.",
    "wof:placetype":"venue"
},
  "geometry": {"coordinates":[2.775454998,42.1477508545],"type":"Point"}
}