{
  "type": "Feature",
  "properties": {
    "iso:country":"ES",
    "sg:address":"Calle de Reyes Catolicos, 2",
    "sg:city":"Orihuela",
    "sg:orig_category":"Sociedades, Compa\u00d1\u00cdas Aseguradoras",
    "sg:phone":"+34 965 30 02 05",
    "sg:postcode":"03300",
    "sg:province":"Alicante",
    "wof:name":"Quesada Villaverde S.l.",
    "wof:placetype":"venue"
},
  "geometry": {"coordinates":[-0.9458919764,38.0805206299],"type":"Point"}
}