{
  "type": "Feature",
  "properties": {
    "addr:full":"Hendaia Kalea, 3 Hondarribia Guip\u00f9zcoa 20280",
    "addr:housenumber":"3",
    "addr:postcode":"20280",
    "addr:street":"Hendaia Kalea;Guipu\u0300Zcoa",
    "iso:country":"ES",
    "sg:address":"Hendaia Kalea, 3",
    "sg:city":"Hondarribia",
    "sg:orig_category":"Electricidad: Instaladores",
    "sg:phone":"+34 943 64 50 48",
    "sg:postcode":"20280",
    "sg:province":"Guip\u00f9zcoa",
    "wof:name":"Argote Hermanos, C.b.",
    "wof:placetype":"venue"
},
  "geometry": {"coordinates":[-1.789467454,43.361869812],"type":"Point"}
}