{
  "type": "Feature",
  "properties": {
    "addr:full":"Calle de Larga, 27 Bollullos Mitacion Sevilla 41110",
    "addr:housenumber":"27",
    "addr:postcode":"41110",
    "addr:street":"Calle De Larga",
    "iso:country":"ES",
    "sg:address":"Calle de Larga, 27",
    "sg:city":"Bollullos Mitacion",
    "sg:orig_category":"Farmacias",
    "sg:phone":"+34 955 76 50 60",
    "sg:postcode":"41110",
    "sg:province":"Sevilla",
    "wof:name":"Escalante Fernandez-palacios Mercedes",
    "wof:placetype":"venue"
},
  "geometry": {"coordinates":[-6.1378030777,37.3389930725],"type":"Point"}
}