{
  "type": "Feature",
  "properties": {
    "addr:full":"Calle de Magdalena Alta, 1 Jaen Ja\u00e9n 23004",
    "addr:housenumber":"1;jae\u0301n",
    "addr:postcode":"23004",
    "addr:street":"Calle De Magdalena Alta",
    "iso:country":"ES",
    "sg:address":"Calle de Magdalena Alta, 1",
    "sg:city":"Jaen",
    "sg:orig_category":"Pescader\u00cdas (al Por Menor)",
    "sg:phone":"+34 953 24 16 25",
    "sg:postcode":"23004",
    "sg:province":"Ja\u00e9n",
    "wof:name":"Sanchez Mena Juan Jose",
    "wof:placetype":"venue"
},
  "geometry": {"coordinates":[-3.7971549034,37.7721405029],"type":"Point"}
}