{
  "type": "Feature",
  "properties": {
    "iso:country":"ES",
    "sg:address":"Calle de Concha General, 19",
    "sg:city":"Bilbao",
    "sg:classifiers":[
        {
            "category":"Casinos & Gambling",
            "type":"Entertainment"
        }
    ],
    "sg:phone":"+34 944 43 15 53",
    "sg:postcode":"48010",
    "sg:province":"Vizcaya",
    "sg:tags":[
        "locale",
        "de",
        "juego"
    ],
    "wof:name":"Bingos Asociados De Euskadi",
    "wof:placetype":"venue"
},
  "geometry": {"coordinates":[-2.9350209236,43.2586402893],"type":"Point"}
}