{
  "type": "Feature",
  "properties": {
    "addr:full":"Calle de Antonio Gaudi (de), 7 Fuenlabrada Madrid 28946",
    "addr:housenumber":"7",
    "addr:postcode":"28946",
    "addr:street":"Calle De Antonio Gaudi De",
    "iso:country":"ES",
    "sg:address":"Calle de Antonio Gaudi (de), 7",
    "sg:city":"Fuenlabrada",
    "sg:orig_category":"Barnizadores",
    "sg:phone":"+34 916 15 15 43",
    "sg:postcode":"28946",
    "sg:province":"Madrid",
    "wof:name":"Diaz Mota Jose Luis",
    "wof:placetype":"venue"
},
  "geometry": {"coordinates":[-3.7793033123,40.2811508179],"type":"Point"}
}