{
  "type": "Feature",
  "properties": {
    "addr:full":"C/ Empedrat, 8 Elche Alicante 03203",
    "addr:housenumber":"8",
    "addr:postcode":"03203",
    "addr:street":"C / Empedrat",
    "iso:country":"ES",
    "sg:address":"C/ Empedrat, 8",
    "sg:city":"Elche",
    "sg:orig_category":"Arquitectos",
    "sg:phone":"+34 965 42 32 84",
    "sg:postcode":"03203",
    "sg:province":"Alicante",
    "wof:name":"Santiago Pastor Arquitecto Sl",
    "wof:placetype":"venue"
},
  "geometry": {"coordinates":[-0.6959149837,38.2658996582],"type":"Point"}
}