{
  "type": "Feature",
  "properties": {
    "addr:full":"Carrer de Guifre El Pelos, 54 Manresa Barcelona 08242",
    "addr:housenumber":"54",
    "addr:postcode":"08242",
    "addr:street":"Carrer De Guifre El Pelos",
    "iso:country":"ES",
    "sg:address":"Carrer de Guifre El Pelos, 54",
    "sg:city":"Manresa",
    "sg:orig_category":"Pescader\u00cdas (al Por Menor)",
    "sg:phone":"+34 938 73 06 54",
    "sg:postcode":"08242",
    "sg:province":"Barcelona",
    "wof:name":"Alimentos Congelados Friman S.a.",
    "wof:placetype":"venue"
},
  "geometry": {"coordinates":[1.7396820784,41.7626686096],"type":"Point"}
}