{
  "type": "Feature",
  "properties": {
    "iso:country":"ES",
    "sg:address":"Carrer de Santa Eulalia, 14",
    "sg:city":"Caldes Montbui",
    "sg:orig_category":"Promotores Constructores",
    "sg:phone":"+34 938 65 14 56",
    "sg:postcode":"08140",
    "sg:province":"Barcelona",
    "wof:name":"Construcciones Luis Mu\u00f1oz",
    "wof:placetype":"venue"
},
  "geometry": {"coordinates":[2.1655299664,41.6338157654],"type":"Point"}
}