{
  "type": "Feature",
  "properties": {
    "addr:full":"Carretera, 30 San Felipe Neri Alicante 03158",
    "addr:housenumber":"30",
    "addr:postcode":"03158",
    "addr:street":"Carretera",
    "iso:country":"ES",
    "sg:address":"Carretera, 30",
    "sg:city":"San Felipe Neri",
    "sg:orig_category":"Caf\u00c9s, Bares, Cervecer\u00cdas",
    "sg:phone":"+34 965 48 45 60",
    "sg:postcode":"03158",
    "sg:province":"Alicante",
    "wof:name":"Gil Hernandez Ildefonso",
    "wof:placetype":"venue"
},
  "geometry": {"coordinates":[-0.8036929965,38.1611442566],"type":"Point"}
}