{
  "type": "Feature",
  "properties": {
    "iso:country":"ES",
    "sg:address":"Carrer de Batan, 6",
    "sg:city":"Reus",
    "sg:orig_category":"Ropa Y Art\u00cdculos Pre",
    "sg:phone":"+34 977 75 11 11",
    "sg:postcode":"43204",
    "sg:province":"Tarragona",
    "wof:name":"Boque S. A.",
    "wof:placetype":"venue"
},
  "geometry": {"coordinates":[1.1109529734,41.1531562805],"type":"Point"}
}