{
  "type": "Feature",
  "properties": {
    "addr:full":"Avda Asturias, 75 Villablino Le\u00f3n 24100",
    "addr:housenumber":"75",
    "addr:postcode":"24100",
    "addr:street":"Avda Asturias",
    "iso:country":"ES",
    "sg:address":"Avda Asturias, 75",
    "sg:city":"Villablino",
    "sg:orig_category":"Farmacias",
    "sg:phone":"+34 987 47 02 97",
    "sg:postcode":"24100",
    "sg:province":"Le\u00f3n",
    "wof:name":"Alonso Gancedo Cb",
    "wof:placetype":"venue"
},
  "geometry": {"coordinates":[-6.3259720802,42.9411849976],"type":"Point"}
}