{
  "type": "Feature",
  "properties": {
    "addr:full":"Calle de Hernan Cortes, 15 Santa Amalia Badajoz 06410",
    "addr:housenumber":"15",
    "addr:postcode":"06410",
    "addr:street":"Calle De Hernan Cortes",
    "iso:country":"ES",
    "sg:address":"Calle de Hernan Cortes, 15",
    "sg:city":"Santa Amalia",
    "sg:orig_category":"Alquiler De Gr\u00daas",
    "sg:phone":"+34 924 83 04 01",
    "sg:postcode":"06410",
    "sg:province":"Badajoz",
    "wof:name":"Dorado Cerezo Manuel",
    "wof:placetype":"venue"
},
  "geometry": {"coordinates":[-6.0084037781,39.009803772],"type":"Point"}
}