{
  "type": "Feature",
  "properties": {
    "addr:full":"Calle de Pomaluengo, S/n Pomaluengo Cantabria 39660",
    "addr:housenumber":"s",
    "addr:postcode":"39660",
    "addr:street":"Calle De Pomaluengo;/ N",
    "iso:country":"ES",
    "sg:address":"Calle de Pomaluengo, S/n",
    "sg:city":"Pomaluengo",
    "sg:orig_category":"M\u00c1rmoles, Granitos Y Piedras Naturales",
    "sg:phone":"+34 942 59 21 76",
    "sg:postcode":"39660",
    "sg:province":"Cantabria",
    "wof:name":"Marmoleria Quijano Martinez S.l.",
    "wof:placetype":"venue"
},
  "geometry": {"coordinates":[-3.9358739853,43.3105735779],"type":"Point"}
}