{
  "type": "Feature",
  "properties": {
    "iso:country":"ES",
    "sg:address":"Avda San Miguel, 24",
    "sg:city":"Guardo",
    "sg:orig_category":"Electrodom\u00c9sticos (al Por Menor)",
    "sg:phone":"+34 979 85 03 86",
    "sg:postcode":"34880",
    "sg:province":"Palencia",
    "wof:name":"Estrada Serrano Julia",
    "wof:placetype":"venue"
},
  "geometry": {"coordinates":[-4.845413208,42.7923583984],"type":"Point"}
}