{
  "type": "Feature",
  "properties": {
    "addr:full":"Calle de Fabrica Vieja, 18 Granada Granada 18002",
    "addr:housenumber":"18",
    "addr:postcode":"18002",
    "addr:street":"Calle De Fabrica Vieja",
    "iso:country":"ES",
    "sg:address":"Calle de Fabrica Vieja, 18",
    "sg:city":"Granada",
    "sg:orig_category":"Albergues",
    "sg:phone":"+34 958 27 85 13",
    "sg:postcode":"18002",
    "sg:province":"Granada",
    "wof:name":"Sanchez Maza Ana Maria",
    "wof:placetype":"venue"
},
  "geometry": {"coordinates":[-3.6025679111,37.1769638062],"type":"Point"}
}