{
  "type": "Feature",
  "properties": {
    "addr:full":"Cami Justada (de La), 1 Montornes Centre Barcelona 08170",
    "addr:housenumber":"1",
    "addr:postcode":"08170",
    "addr:street":"Centre Barcelona",
    "iso:country":"ES",
    "sg:address":"Cami Justada (de La), 1",
    "sg:city":"Montornes Centre",
    "sg:orig_category":"Comercio De Piezas De Recambio Y De Accesorios De Veh\u00cdculos, Veh\u00cdculos Industriales",
    "sg:phone":"+34 935 68 62 64",
    "sg:postcode":"08170",
    "sg:province":"Barcelona",
    "wof:name":"Conelson S.l.",
    "wof:placetype":"venue"
},
  "geometry": {"coordinates":[2.2664198875,41.54529953],"type":"Point"}
}