{
  "type": "Feature",
  "properties": {
    "addr:full":"Calle de Viver, 38 Valencia Valencia 46020",
    "addr:housenumber":"38",
    "addr:postcode":"46020",
    "addr:street":"Calle De Viver",
    "iso:country":"ES",
    "sg:address":"Calle de Viver, 38",
    "sg:city":"Valencia",
    "sg:orig_category":"Ingenier\u00cda, Centros De Estudios (diversos)",
    "sg:phone":"+34 963 93 54 65",
    "sg:postcode":"46020",
    "sg:province":"Valencia",
    "wof:name":"Marti Guillamon Antonio",
    "wof:placetype":"venue"
},
  "geometry": {"coordinates":[-0.3641490042,39.4879608154],"type":"Point"}
}