{
  "type": "Feature",
  "properties": {
    "addr:full":"Ctra Muel, 65 Epila Zaragoza 50290",
    "addr:housenumber":"65",
    "addr:postcode":"50290",
    "addr:street":"Ctra Muel",
    "iso:country":"ES",
    "sg:address":"Ctra Muel, 65",
    "sg:city":"Epila",
    "sg:orig_category":"Alquiler De Veh\u00cdculos: Turismos Y Utilitarios",
    "sg:phone":"+34 976 60 30 89",
    "sg:postcode":"50290",
    "sg:province":"Zaragoza",
    "wof:name":"Autolanceros S.l.",
    "wof:placetype":"venue"
},
  "geometry": {"coordinates":[-1.2749818563,41.5948867798],"type":"Point"}
}