{
  "type": "Feature",
  "properties": {
    "iso:country":"ES",
    "sg:address":"Avda Palencia, 80",
    "sg:city":"Cabezon.barrio Nuevo",
    "sg:orig_category":"Fotograf\u00cda Art\u00cdstica Y Retratos",
    "sg:phone":"+34 983 54 72 03",
    "sg:postcode":"47260",
    "sg:province":"Valladolid",
    "wof:name":"Diez Sanchez Justino",
    "wof:placetype":"venue"
},
  "geometry": {"coordinates":[-4.6461081505,41.7319450378],"type":"Point"}
}