{
  "type": "Feature",
  "properties": {
    "iso:country":"ES",
    "sg:address":"Calle de Peguerinos, 27",
    "sg:city":"Madrid",
    "sg:orig_category":"Inmobiliaria (agencias)",
    "sg:phone":"+34 913 73 02 61",
    "sg:postcode":"28035",
    "sg:province":"Madrid",
    "wof:name":"Corporacion Comercial S.a.",
    "wof:placetype":"venue"
},
  "geometry": {"coordinates":[-3.7353188992,40.4709281921],"type":"Point"}
}