{
  "type": "Feature",
  "properties": {
    "iso:country":"ES",
    "sg:address":"Calle de Cea Bermudez, 27",
    "sg:city":"Madrid",
    "sg:orig_category":"Procuradores",
    "sg:phone":"+34 915 35 80 81",
    "sg:postcode":"28003",
    "sg:province":"Madrid",
    "wof:name":"Oliva Collar Alicia",
    "wof:placetype":"venue"
},
  "geometry": {"coordinates":[-3.7103953362,40.4388465881],"type":"Point"}
}