{
  "type": "Feature",
  "properties": {
    "iso:country":"ES",
    "sg:address":"Carrer de Carme, S/n",
    "sg:city":"Esplugues Llobregat",
    "sg:orig_category":"Frutas, Legumbres Frescas Y Tempranas (al Por Menor)",
    "sg:phone":"+34 934 73 60 58",
    "sg:postcode":"08950",
    "sg:province":"Barcelona",
    "wof:name":"Salvador Iserte Emiliano",
    "wof:placetype":"venue"
},
  "geometry": {"coordinates":[2.0846951008,41.3726844788],"type":"Point"}
}