{
  "type": "Feature",
  "properties": {
    "iso:country":"ES",
    "sg:address":"Carrer de Pons I Gallarza, 75",
    "sg:city":"Barcelona",
    "sg:orig_category":"Asociaciones Humanitarias, De Cooperaci\u00d3n, De Acci\u00d3n Social",
    "sg:phone":"+34 933 45 73 18",
    "sg:postcode":"08030",
    "sg:province":"Barcelona",
    "wof:name":"Jugadores Anonimos",
    "wof:placetype":"venue"
},
  "geometry": {"coordinates":[2.1860589981,41.4354019165],"type":"Point"}
}