{
  "type": "Feature",
  "properties": {
    "iso:country":"ES",
    "sg:address":"Plaz Mayor, 8",
    "sg:city":"Valladolid",
    "sg:orig_category":"Procuradores",
    "sg:phone":"+34 983 37 11 84",
    "sg:postcode":"47001",
    "sg:province":"Valladolid",
    "wof:name":"Abril Vega Maria Del Mar",
    "wof:placetype":"venue"
},
  "geometry": {"coordinates":[-4.72827,41.651691],"type":"Point"}
}