{
  "type": "Feature",
  "properties": {
    "addr:full":"Carrer de Progres, 45 Almeda Mercader Barcelona 08940",
    "addr:housenumber":"45",
    "addr:postcode":"08940",
    "addr:street":"Carrer De Progres;Mercader Barcelona",
    "iso:country":"ES",
    "sg:address":"Carrer de Progres, 45",
    "sg:city":"Almeda Mercader",
    "sg:orig_category":"Albergues",
    "sg:phone":"+34 933 77 05 16",
    "sg:postcode":"08940",
    "sg:province":"Barcelona",
    "wof:name":"Acierta Promo S.l.",
    "wof:placetype":"venue"
},
  "geometry": {"coordinates":[2.0839192867,41.3470993042],"type":"Point"}
}