{
  "type": "Feature",
  "properties": {
    "iso:country":"ES",
    "sg:address":"Carrer de Llovera, 29",
    "sg:city":"Reus",
    "sg:orig_category":"Juegos Y Juguetes (al Por Menor)",
    "sg:phone":"+34 977 34 42 29",
    "sg:postcode":"43201",
    "sg:province":"Tarragona",
    "wof:name":"Segu Palau Guillermo",
    "wof:placetype":"venue"
},
  "geometry": {"coordinates":[1.1066639423,41.1568946838],"type":"Point"}
}