{
  "type": "Feature",
  "properties": {
    "addr:full":"Calle de Vizcaya, 33 San Sebastian De Los Reyes Madrid 28700",
    "addr:housenumber":"33",
    "addr:postcode":"28700",
    "addr:street":"Calle De Vizcaya",
    "iso:country":"ES",
    "sg:address":"Calle de Vizcaya, 33",
    "sg:city":"San Sebastian De Los Reyes",
    "sg:orig_category":"Papeler\u00cdas, Librer\u00cdas",
    "sg:phone":"+34 916 52 99 71",
    "sg:postcode":"28700",
    "sg:province":"Madrid",
    "wof:name":"De Mena De Dios Jose Luis",
    "wof:placetype":"venue"
},
  "geometry": {"coordinates":[-3.6386399269,40.552230835],"type":"Point"}
}