{
  "type": "Feature",
  "properties": {
    "addr:full":"Carr Rambla, De La, 35 Campos Islas Baleares 07630",
    "addr:housenumber":"35",
    "addr:postcode":"07630",
    "addr:street":"Carr Rambla De La",
    "iso:country":"ES",
    "sg:address":"Carr Rambla, De La, 35",
    "sg:city":"Campos",
    "sg:orig_category":"Cueros Y Pieles (al Por Mayor)",
    "sg:phone":"+34 971 65 12 05",
    "sg:postcode":"07630",
    "sg:province":"Islas Baleares",
    "wof:name":"Incampos C.b.",
    "wof:placetype":"venue"
},
  "geometry": {"coordinates":[3.0197050571,39.430480957],"type":"Point"}
}