{
  "type": "Feature",
  "properties": {
    "iso:country":"ES",
    "sg:address":"Carr Ramon Y Cajal, 3",
    "sg:city":"Sueca",
    "sg:orig_category":"Farmacias",
    "sg:phone":"+34 961 70 22 92",
    "sg:postcode":"46410",
    "sg:province":"Valencia",
    "wof:name":"Farmacia Brull-roses C.b.",
    "wof:placetype":"venue"
},
  "geometry": {"coordinates":[-0.3161740005,39.2007904053],"type":"Point"}
}