{
  "type": "Feature",
  "properties": {
    "addr:full":"Calle de Francisco De Medina Y Mendoza, 3 Cabanillas Campo Guadalajara 19171",
    "addr:housenumber":"3",
    "addr:postcode":"19171",
    "addr:street":"Calle De Francisco De Medina Y Mendoza",
    "iso:country":"ES",
    "sg:address":"Calle de Francisco De Medina Y Mendoza, 3",
    "sg:city":"Cabanillas Campo",
    "sg:orig_category":"Producci\u00d3n, Distribuci\u00d3n De Electricidad",
    "sg:phone":"+34 949 20 15 42",
    "sg:postcode":"19171",
    "sg:province":"Guadalajara",
    "wof:name":"Electricidad Aja S.l.",
    "wof:placetype":"venue"
},
  "geometry": {"coordinates":[-3.2374420166,40.6377639771],"type":"Point"}
}