{
  "type": "Feature",
  "properties": {
    "iso:country":"ES",
    "sg:address":"Calle de Don Rodrigo, S/n",
    "sg:city":"Pastrana",
    "sg:orig_category":"Equipo De Refrigeraci\u00d3n Industrial",
    "sg:phone":"+34 956 36 36 99",
    "sg:postcode":"11540",
    "sg:province":"C\u00e1diz",
    "wof:name":"Frio Doncel S.l.",
    "wof:placetype":"venue"
},
  "geometry": {"coordinates":[-6.29240942,36.5299415588],"type":"Point"}
}