{
  "type": "Feature",
  "properties": {
    "addr:full":"Ctra Masnou, Km. 0014,0 Granollers Barcelona 08402",
    "addr:postcode":"08402",
    "addr:street":"Ctra Masnou Km. 0014,0",
    "iso:country":"ES",
    "sg:address":"Ctra Masnou, Km. 0014,0",
    "sg:city":"Granollers",
    "sg:orig_category":"Jardiner\u00cdas, Vegetales, Art\u00cdculos De Jardiner\u00cda (al Por Menor)",
    "sg:phone":"+34 938 70 44 97",
    "sg:postcode":"08402",
    "sg:province":"Barcelona",
    "wof:name":"Codina Torruella Jaime",
    "wof:placetype":"venue"
},
  "geometry": {"coordinates":[2.2856500149,41.5928993225],"type":"Point"}
}