{
  "type": "Feature",
  "properties": {
    "addr:full":"Plaz Juderia (de La), 1 Teruel Teruel 44001",
    "addr:postcode":"44001",
    "iso:country":"ES",
    "sg:address":"Plaz Juderia (de La), 1",
    "sg:city":"Teruel",
    "sg:orig_category":"Molduras, Junquillos, Listones Y Molduras Perforadas",
    "sg:phone":"+34 978 60 26 56",
    "sg:postcode":"44001",
    "sg:province":"Teruel",
    "wof:name":"Martin Rodrigo Fernando",
    "wof:placetype":"venue"
},
  "geometry": {"coordinates":[-1.1050000191,40.3426246643],"type":"Point"}
}