{
  "type": "Feature",
  "properties": {
    "addr:full":"Calle de Puerto Rico, 39 Valencia Valencia 46006",
    "addr:housenumber":"39",
    "addr:postcode":"46006",
    "addr:street":"Calle De Puerto Rico",
    "iso:country":"ES",
    "sg:address":"Calle de Puerto Rico, 39",
    "sg:city":"Valencia",
    "sg:orig_category":"M\u00c9dicos: Ginecolog\u00cda Y Obstetricia",
    "sg:phone":"+34 963 41 20 20",
    "sg:postcode":"46006",
    "sg:province":"Valencia",
    "wof:name":"Martinez Paya Maria Josefa",
    "wof:placetype":"venue"
},
  "geometry": {"coordinates":[-0.3769949973,39.4606399536],"type":"Point"}
}