{
  "type": "Feature",
  "properties": {
    "addr:full":"El Pilo, 10 Soto Valdeon Le\u00f3n 24914",
    "addr:housenumber":"10",
    "addr:postcode":"24914",
    "addr:street":"El Pilo;Leo\u0301N",
    "iso:country":"ES",
    "sg:address":"El Pilo, 10",
    "sg:city":"Soto Valdeon",
    "sg:classifiers":[
        {
            "category":"Taxi",
            "type":"Transportation"
        }
    ],
    "sg:phone":"+34 987 74 26 19",
    "sg:postcode":"24914",
    "sg:province":"Le\u00f3n",
    "wof:name":"Guerra Perez Angel",
    "wof:placetype":"venue"
},
  "geometry": {"coordinates":[-5.5717520714,42.5998764038],"type":"Point"}
}