{
  "type": "Feature",
  "properties": {
    "iso:country":"ES",
    "sg:address":"Calle de Andres Llorente, 1",
    "sg:city":"Alcala Henares",
    "sg:orig_category":"Plomeros",
    "sg:phone":"+34 918 80 84 38",
    "sg:postcode":"28807",
    "sg:province":"Madrid",
    "wof:name":"Instalaciones De Fontaneria El Val S.l.",
    "wof:placetype":"venue"
},
  "geometry": {"coordinates":[-3.3700752258,40.485824585],"type":"Point"}
}