{
  "type": "Feature",
  "properties": {
    "iso:country":"ES",
    "sg:address":"Rbla Juan Mateo Garcia, 60",
    "sg:city":"Torrevieja",
    "sg:orig_category":"Empresas De Carpinter\u00cda De Madera",
    "sg:phone":"+34 965 71 10 36",
    "sg:postcode":"03180",
    "sg:province":"Alicante",
    "wof:name":"Aracil Ortigosa Angel",
    "wof:placetype":"venue"
},
  "geometry": {"coordinates":[-0.6800482869,37.9814071655],"type":"Point"}
}