{
  "type": "Feature",
  "properties": {
    "addr:full":"Avda Madrid, 156 Zaragoza Zaragoza 50017",
    "addr:housenumber":"156",
    "addr:postcode":"50017",
    "addr:street":"Avda Madrid",
    "iso:country":"ES",
    "sg:address":"Avda Madrid, 156",
    "sg:city":"Zaragoza",
    "sg:orig_category":"Estilistas Y Estudios De Estilo De Corte Y Confecci\u00d3n",
    "sg:phone":"+34 976 34 11 25",
    "sg:postcode":"50017",
    "sg:province":"Zaragoza",
    "wof:name":"Lacilla Gil Lorenzo",
    "wof:placetype":"venue"
},
  "geometry": {"coordinates":[-0.9128649831,41.6516304016],"type":"Point"}
}