{
  "type": "Feature",
  "properties": {
    "iso:country":"ES",
    "sg:address":"Calle de Bravo Murillo, 318",
    "sg:city":"Madrid",
    "sg:orig_category":"Agencias De Viajes",
    "sg:phone":"+34 915 71 96 91",
    "sg:postcode":"28020",
    "sg:province":"Madrid",
    "sg:website":"www.viajeslepanto.com",
    "wof:name":"Viajes Lepanto S. L.",
    "wof:placetype":"venue"
},
  "geometry": {"coordinates":[-3.6959719658,40.4639854431],"type":"Point"}
}