{
  "type": "Feature",
  "properties": {
    "addr:full":"Alcora(pol Ind Carrus), 62 Elche Alicante 03291",
    "addr:housenumber":"62",
    "addr:postcode":"03291",
    "addr:street":"Ind Carrus",
    "iso:country":"ES",
    "sg:address":"Alcora(pol Ind Carrus), 62",
    "sg:city":"Elche",
    "sg:orig_category":"Electromec\u00c1nica",
    "sg:phone":"+34 965 43 00 47",
    "sg:postcode":"03291",
    "sg:province":"Alicante",
    "sg:website":"tenzamachine@terra.es",
    "wof:name":"Tenza Machine S.l.",
    "wof:placetype":"venue"
},
  "geometry": {"coordinates":[-0.6862289906,38.2990188599],"type":"Point"}
}