{
  "type": "Feature",
  "properties": {
    "iso:country":"ES",
    "sg:address":"Carr Major, 103",
    "sg:city":"Cervera",
    "sg:orig_category":"Transportes Por V\u00cdas Navegables",
    "sg:phone":"+34 973 53 03 79",
    "sg:postcode":"25200",
    "sg:province":"Lleida",
    "wof:name":"Pedros Puig Ramon",
    "wof:placetype":"venue"
},
  "geometry": {"coordinates":[1.2718600035,41.6688652039],"type":"Point"}
}