{
  "type": "Feature",
  "properties": {
    "iso:country":"ES",
    "sg:address":"Calle de Vitoria, 4",
    "sg:city":"Burgos",
    "sg:orig_category":"Abogados",
    "sg:phone":"+34 947 26 68 69",
    "sg:postcode":"09004",
    "sg:province":"Burgos",
    "wof:name":"Lopez Arribas Roman",
    "wof:placetype":"venue"
},
  "geometry": {"coordinates":[-3.6991350651,42.3409156799],"type":"Point"}
}