{
  "type": "Feature",
  "properties": {
    "addr:full":"Plaz Zumarraga, 4 Bilbao Vizcaya 48006",
    "addr:housenumber":"4",
    "addr:postcode":"48006",
    "addr:street":"Zumarraga",
    "iso:country":"ES",
    "sg:address":"Plaz Zumarraga, 4",
    "sg:city":"Bilbao",
    "sg:orig_category":"Carnicer\u00cdas, Carnicer\u00cdas",
    "sg:phone":"+34 944 15 11 64",
    "sg:postcode":"48006",
    "sg:province":"Vizcaya",
    "wof:name":"Carniceria Pablo C B",
    "wof:placetype":"venue"
},
  "geometry": {"coordinates":[-2.9197409153,43.2574195862],"type":"Point"}
}