{
  "type": "Feature",
  "properties": {
    "addr:full":"Abaran(la Polvorista), 3 Molina Segura Murcia 30500",
    "addr:housenumber":"3",
    "addr:postcode":"30500",
    "addr:street":"Polvorista",
    "iso:country":"ES",
    "sg:address":"Abaran(la Polvorista), 3",
    "sg:city":"Molina Segura",
    "sg:orig_category":"Servicios De Telecomunicaciones",
    "sg:phone":"+34 968 64 45 32",
    "sg:postcode":"30500",
    "sg:province":"Murcia",
    "wof:name":"Install Telecom S.a.",
    "wof:placetype":"venue"
},
  "geometry": {"coordinates":[-1.1888509989,38.0401763916],"type":"Point"}
}