{
  "type": "Feature",
  "properties": {
    "iso:country":"ES",
    "sg:address":"Calle de Ni\u00d1o Jesus, 5",
    "sg:city":"Gijon",
    "sg:orig_category":"Internados & Ense\u00d1anza Privada",
    "sg:phone":"+34 985 15 45 55",
    "sg:postcode":"33209",
    "sg:province":"Asturias",
    "wof:name":"Colegio De La Milagrosa",
    "wof:placetype":"venue"
},
  "geometry": {"coordinates":[-5.6665000916,43.5263748169],"type":"Point"}
}