{
  "type": "Feature",
  "properties": {
    "addr:full":"Calle de Federico Echevarria, 13 Le\u00f3n Le\u00f3n 24002",
    "addr:housenumber":"13",
    "addr:postcode":"24002",
    "addr:street":"Calle De Federico Echevarria;Leo\u0301N",
    "iso:country":"ES",
    "sg:address":"Calle de Federico Echevarria, 13",
    "sg:city":"Le\u00f3n",
    "sg:orig_category":"Arreglo, Reparaci\u00d3n, Piezas Sueltas De Televisi\u00d3n, V\u00cddeo, Hi",
    "sg:phone":"+34 987 23 31 23",
    "sg:postcode":"24002",
    "sg:province":"Le\u00f3n",
    "wof:name":"Jaumot Garcia Isabel",
    "wof:placetype":"venue"
},
  "geometry": {"coordinates":[-5.5742650032,42.6035461426],"type":"Point"}
}