{
  "type": "Feature",
  "properties": {
    "addr:full":"Calle de Campoverde, 46 Almeria Almer\u00eda 04008",
    "addr:housenumber":"46",
    "addr:postcode":"04008",
    "addr:street":"Calle De Campoverde",
    "iso:country":"ES",
    "sg:address":"Calle de Campoverde, 46",
    "sg:city":"Almeria",
    "sg:orig_category":"Charcuter\u00cdas (al Por Mayor)",
    "sg:phone":"+34 950 27 04 20",
    "sg:postcode":"04008",
    "sg:province":"Almer\u00eda",
    "wof:name":"Garcia Lara Juan Jose",
    "wof:placetype":"venue"
},
  "geometry": {"coordinates":[-2.4582419395,36.8485412598],"type":"Point"}
}