{
  "type": "Feature",
  "properties": {
    "iso:country":"ES",
    "sg:address":"Calle de Espa\u00d1a, 22",
    "sg:city":"Huetor-vega",
    "sg:orig_category":"Universidades",
    "sg:phone":"+34 958 30 34 89",
    "sg:postcode":"18198",
    "sg:province":"Granada",
    "wof:name":"De La Rosa Olivera Pedro",
    "wof:placetype":"venue"
},
  "geometry": {"coordinates":[-3.5710330009,37.1477775574],"type":"Point"}
}