{
  "type": "Feature",
  "properties": {
    "addr:full":"Calle de Menendez Pelayo, 2 Valladolid Valladolid 47001",
    "addr:housenumber":"2",
    "addr:postcode":"47001",
    "addr:street":"Calle De Menendez Pelayo",
    "iso:country":"ES",
    "sg:address":"Calle de Menendez Pelayo, 2",
    "sg:city":"Valladolid",
    "sg:orig_category":"Peluquer\u00cdas, Peluquer\u00cda Mixta",
    "sg:phone":"+34 983 34 48 95",
    "sg:postcode":"47001",
    "sg:province":"Valladolid",
    "wof:name":"Suarez Amador Candelas",
    "wof:placetype":"venue"
},
  "geometry": {"coordinates":[-4.7277169228,41.6508712769],"type":"Point"}
}