{
  "type": "Feature",
  "properties": {
    "addr:full":"Carrer de Nou, 128 Sant Vicen\u00c7 Dels Horts Barcelona 08620",
    "addr:housenumber":"128",
    "addr:postcode":"08620",
    "addr:street":"Carrer De Nou",
    "iso:country":"ES",
    "sg:address":"Carrer de Nou, 128",
    "sg:city":"Sant Vicen\u00c7 Dels Horts",
    "sg:orig_category":"Veh\u00cdculos De Ocasi\u00d3n",
    "sg:phone":"+34 936 56 06 85",
    "sg:postcode":"08620",
    "sg:province":"Barcelona",
    "wof:name":"Perez Ca\u00f1izares Manuel",
    "wof:placetype":"venue"
},
  "geometry": {"coordinates":[2.0138399601,41.388961792],"type":"Point"}
}