{
  "type": "Feature",
  "properties": {
    "iso:country":"ES",
    "sg:address":"Avda Virgen De La Monta\u00d1a, 19",
    "sg:city":"Caceres",
    "sg:orig_category":"Cl\u00cdnicas Dentales",
    "sg:phone":"+34 927 22 16 71",
    "sg:postcode":"10004",
    "sg:province":"C\u00e1ceres",
    "wof:name":"Rodriguez Prieto German",
    "wof:placetype":"venue"
},
  "geometry": {"coordinates":[-6.3745031357,39.4702720642],"type":"Point"}
}