{
  "type": "Feature",
  "properties": {
    "iso:country":"ES",
    "sg:address":"Calle de Juan De La Cierva, 45",
    "sg:city":"Estepona",
    "sg:orig_category":"Fabricaci\u00d3n, Venta, Instalaci\u00d3n De R\u00d3tulos, De R\u00d3tulos Luminosos",
    "sg:phone":"+34 952 79 22 82",
    "sg:postcode":"29680",
    "sg:province":"M\u00e1laga",
    "wof:name":"Luminosos Y Toldos Hesla S.l.",
    "wof:placetype":"venue"
},
  "geometry": {"coordinates":[-5.166809082,36.4279518127],"type":"Point"}
}