{
  "type": "Feature",
  "properties": {
    "addr:full":"Ctra Murcia (de), 59 Cehegin Murcia 30430",
    "addr:housenumber":"59",
    "addr:postcode":"30430",
    "addr:street":"Ctra Murcia De",
    "iso:country":"ES",
    "sg:address":"Ctra Murcia (de), 59",
    "sg:city":"Cehegin",
    "sg:orig_category":"Abogados",
    "sg:phone":"+34 968 74 18 09",
    "sg:postcode":"30430",
    "sg:province":"Murcia",
    "wof:name":"Lopez-fajardo Lopez Lucio",
    "wof:placetype":"venue"
},
  "geometry": {"coordinates":[-1.787217021,38.0864334106],"type":"Point"}
}