{
  "type": "Feature",
  "properties": {
    "iso:country":"ES",
    "sg:address":"Barr Larrea, 3",
    "sg:city":"Villabona",
    "sg:orig_category":"Institutos De Belleza",
    "sg:phone":"+34 943 69 20 26",
    "sg:postcode":"20150",
    "sg:province":"Guip\u00f9zcoa",
    "wof:name":"Felix Y Gelatxo S.l.",
    "wof:placetype":"venue"
},
  "geometry": {"coordinates":[-2.0503959656,43.1817092896],"type":"Point"}
}