{
  "type": "Feature",
  "properties": {
    "addr:full":"Rio Mero, S/n Culleredo A Coru\u00f1a 15180",
    "addr:housenumber":"s / n",
    "addr:postcode":"15180",
    "addr:street":"Mero;Corun\u0303A",
    "iso:country":"ES",
    "sg:address":"Rio Mero, S/n",
    "sg:city":"Culleredo",
    "sg:orig_category":"Chapister\u00cda",
    "sg:phone":"+34 981 65 45 58",
    "sg:postcode":"15180",
    "sg:province":"A Coru\u00f1a",
    "wof:name":"Talleres Merelas German S.l.",
    "wof:placetype":"venue"
},
  "geometry": {"coordinates":[-8.3581266403,43.3022460938],"type":"Point"}
}