{
  "type": "Feature",
  "properties": {
    "addr:full":"Calle de Royo, 12 Arnedo La Rioja 26580",
    "addr:housenumber":"12",
    "addr:postcode":"26580",
    "addr:street":"Calle De Royo;Rioja",
    "iso:country":"ES",
    "sg:address":"Calle de Royo, 12",
    "sg:city":"Arnedo",
    "sg:orig_category":"Alimentaci\u00d3n General (al Por Menor)",
    "sg:phone":"+34 941 38 02 16",
    "sg:postcode":"26580",
    "sg:province":"La Rioja",
    "wof:name":"Martinez-losa Tomas Antonia",
    "wof:placetype":"venue"
},
  "geometry": {"coordinates":[-2.1011829376,42.2288322449],"type":"Point"}
}