{
  "type": "Feature",
  "properties": {
    "iso:country":"ES",
    "sg:address":"Urb Mies Del Calero, 2",
    "sg:city":"Mortera",
    "sg:orig_category":"M\u00c9dicos: Estomatolog\u00cda",
    "sg:phone":"+34 942 58 20 31",
    "sg:postcode":"39120",
    "sg:province":"Cantabria",
    "wof:name":"Odontoberr S.l.",
    "wof:placetype":"venue"
},
  "geometry": {"coordinates":[-3.9333629608,43.4453544617],"type":"Point"}
}