{
  "type": "Feature",
  "properties": {
    "iso:country":"ES",
    "sg:address":"Calle de Torres Isunza, 29",
    "sg:city":"Don Benito",
    "sg:orig_category":"Pintura, Barniz, Productos Asimilables (fabricaci\u00d3n, Al Por Mayor)",
    "sg:phone":"+34 924 80 20 96",
    "sg:postcode":"06400",
    "sg:province":"Badajoz",
    "wof:name":"Tamurejo Martin S.l.",
    "wof:placetype":"venue"
},
  "geometry": {"coordinates":[-5.8728356361,38.9567718506],"type":"Point"}
}