{
  "type": "Feature",
  "properties": {
    "addr:full":"Plaz Se\u00d1orio De Bizkaia, 7 Santurtzi Vizcaya 48980",
    "addr:housenumber":"7",
    "addr:postcode":"48980",
    "addr:street":"Plaz;Bizkaia",
    "iso:country":"ES",
    "sg:address":"Plaz Se\u00d1orio De Bizkaia, 7",
    "sg:city":"Santurtzi",
    "sg:orig_category":"Loter\u00cda Y T\u00d3mbola",
    "sg:phone":"+34 944 62 50 25",
    "sg:postcode":"48980",
    "sg:province":"Vizcaya",
    "wof:name":"Palomo Torres Francisca",
    "wof:placetype":"venue"
},
  "geometry": {"coordinates":[-3.0287311077,43.3271102905],"type":"Point"}
}