{
  "type": "Feature",
  "properties": {
    "iso:country":"ES",
    "sg:address":"Crt. Gijon-sevilla, Km. 0700,0",
    "sg:city":"Fuente Cantos",
    "sg:orig_category":"Agricultores, Agricultores",
    "sg:phone":"+34 924 58 00 96",
    "sg:postcode":"06240",
    "sg:province":"Badajoz",
    "wof:name":"Garcia Mimbrero Rafael",
    "wof:placetype":"venue"
},
  "geometry": {"coordinates":[-6.9702835083,38.8785972595],"type":"Point"}
}