{
  "type": "Feature",
  "properties": {
    "iso:country":"ES",
    "sg:address":"Carrer de Sant Josep, 8",
    "sg:city":"Calella",
    "sg:orig_category":"Centros De Coordinaci\u00d3n",
    "sg:phone":"+34 937 69 12 65",
    "sg:postcode":"08370",
    "sg:province":"Barcelona",
    "wof:name":"Buch Guinart Maria Rosa",
    "wof:placetype":"venue"
},
  "geometry": {"coordinates":[2.6615200043,41.6134376526],"type":"Point"}
}