{
  "type": "Feature",
  "properties": {
    "addr:full":"Calle de Alejandro De Vida Hidalgo, 2 Cabra C\u00f3rdoba 14940",
    "addr:postcode":"14940",
    "addr:street":"Calle De Alejandro;Hidalgo 2",
    "iso:country":"ES",
    "sg:address":"Calle de Alejandro De Vida Hidalgo, 2",
    "sg:city":"Cabra",
    "sg:orig_category":"Prot\u00c9sicos Dentales",
    "sg:phone":"+34 957 52 07 64",
    "sg:postcode":"14940",
    "sg:province":"C\u00f3rdoba",
    "wof:name":"Egaprotesis S.l.l.",
    "wof:placetype":"venue"
},
  "geometry": {"coordinates":[-4.4441809654,37.4703598022],"type":"Point"}
}