{
  "type": "Feature",
  "properties": {
    "addr:full":"Calle de Ribadavia, 2 Alcorcon Madrid 28925",
    "addr:housenumber":"2",
    "addr:postcode":"28925",
    "addr:street":"Calle De Ribadavia",
    "iso:country":"ES",
    "sg:address":"Calle de Ribadavia, 2",
    "sg:city":"Alcorcon",
    "sg:orig_category":"Comunidades Religiosas",
    "sg:phone":"+34 916 10 00 26",
    "sg:postcode":"28925",
    "sg:province":"Madrid",
    "wof:name":"Obispado De Getafe",
    "wof:placetype":"venue"
},
  "geometry": {"coordinates":[-3.812541008,40.3549842834],"type":"Point"}
}