{
  "type": "Feature",
  "properties": {
    "addr:full":"Avda Portugal, 1 Aranda Duero Burgos 09400",
    "addr:housenumber":"1",
    "addr:postcode":"09400",
    "addr:street":"Avda Portugal",
    "iso:country":"ES",
    "sg:address":"Avda Portugal, 1",
    "sg:city":"Aranda Duero",
    "sg:orig_category":"Chapister\u00cda",
    "sg:phone":"+34 947 50 99 20",
    "sg:postcode":"09400",
    "sg:province":"Burgos",
    "wof:name":"Autos Vallecillo S.l.",
    "wof:placetype":"venue"
},
  "geometry": {"coordinates":[-3.7274754047,41.6662101746],"type":"Point"}
}