{
  "type": "Feature",
  "properties": {
    "addr:full":"Jdin Glorieta, 5 Hellin Albacete 02400",
    "addr:housenumber":"5",
    "addr:postcode":"02400",
    "addr:street":"Glorieta",
    "iso:country":"ES",
    "sg:address":"Jdin Glorieta, 5",
    "sg:city":"Hellin",
    "sg:orig_category":"Instalaci\u00d3n, Reparaci\u00d3n De Ascensores Y Montacargas",
    "sg:phone":"+34 967 30 01 41",
    "sg:postcode":"02400",
    "sg:province":"Albacete",
    "wof:name":"Devega S. A.",
    "wof:placetype":"venue"
},
  "geometry": {"coordinates":[-1.693846941,38.5102844238],"type":"Point"}
}