{
  "type": "Feature",
  "properties": {
    "iso:country":"ES",
    "sg:address":"Plaz Ayuntamiento, 7",
    "sg:city":"Oliva Frontera",
    "sg:orig_category":"Cajas De Ahorro",
    "sg:phone":"+34 924 75 45 51",
    "sg:postcode":"06120",
    "sg:province":"Badajoz",
    "sg:website":"www. cajaextremadura.es",
    "wof:name":"Caja De Ahorros Y Monte De Piedad De Extremadura",
    "wof:placetype":"venue"
},
  "geometry": {"coordinates":[-6.9155139923,38.2829017639],"type":"Point"}
}