{
  "type": "Feature",
  "properties": {
    "iso:country":"ES",
    "sg:address":"Calle de Carrion De Los Condes, 53",
    "sg:city":"Madrid",
    "sg:orig_category":"Edici\u00d3n De Diarios, Revistas, Boletines",
    "sg:phone":"+34 917 66 03 65",
    "sg:postcode":"28033",
    "sg:province":"Madrid",
    "wof:name":"Buropres S.l.",
    "wof:placetype":"venue"
},
  "geometry": {"coordinates":[-3.6583418846,40.4754066467],"type":"Point"}
}