{
  "type": "Feature",
  "properties": {
    "addr:full":"Carrer de Antoninus Pius, 189 Terrassa Barcelona 08224",
    "addr:housenumber":"189",
    "addr:postcode":"08224",
    "addr:street":"Carrer De Antoninus Pius",
    "iso:country":"ES",
    "sg:address":"Carrer de Antoninus Pius, 189",
    "sg:city":"Terrassa",
    "sg:orig_category":"Florister\u00cdas",
    "sg:phone":"+34 937 88 73 73",
    "sg:postcode":"08224",
    "sg:province":"Barcelona",
    "wof:name":"Lopez Millan Veronica",
    "wof:placetype":"venue"
},
  "geometry": {"coordinates":[2.0001189709,41.558139801],"type":"Point"}
}