{
  "type": "Feature",
  "properties": {
    "addr:full":"Calle de Bailen, 2 Mengibar Ja\u00e9n 23620",
    "addr:housenumber":"2",
    "addr:postcode":"23620",
    "addr:street":"Calle De Bailen;Jae\u0301N",
    "iso:country":"ES",
    "sg:address":"Calle de Bailen, 2",
    "sg:city":"Mengibar",
    "sg:orig_category":"Promotores Constructores",
    "sg:phone":"+34 953 37 07 64",
    "sg:postcode":"23620",
    "sg:province":"Ja\u00e9n",
    "sg:website":"www.gvalderrama.es",
    "wof:name":"Construcciones Gomez Valderrama S.l.",
    "wof:placetype":"venue"
},
  "geometry": {"coordinates":[-3.8024349213,37.9693412781],"type":"Point"}
}