{
  "type": "Feature",
  "properties": {
    "addr:full":"Calle de Alonso Heredia, 32 Madrid Madrid 28028",
    "addr:housenumber":"32",
    "addr:postcode":"madrid;28028",
    "addr:street":"Calle De Alonso Heredia",
    "iso:country":"ES",
    "sg:address":"Calle de Alonso Heredia, 32",
    "sg:city":"Madrid",
    "sg:orig_category":"Empresas De Portes Y Mensajer\u00cda",
    "sg:phone":"+34 913 61 22 24",
    "sg:postcode":"28028",
    "sg:province":"Madrid",
    "wof:name":"Menfis Madrid S.a.",
    "wof:placetype":"venue"
},
  "geometry": {"coordinates":[-3.6715459824,40.4365119934],"type":"Point"}
}