{
  "type": "Feature",
  "properties": {
    "addr:full":"Avda Juan Perez Arcas, S/n Cullar Granada 18850",
    "addr:housenumber":"s / n",
    "addr:postcode":"18850",
    "addr:street":"Avda Juan Perez Arcas",
    "iso:country":"ES",
    "sg:address":"Avda Juan Perez Arcas, S/n",
    "sg:city":"Cullar",
    "sg:orig_category":"Albergues",
    "sg:phone":"+34 958 73 09 95",
    "sg:postcode":"18850",
    "sg:province":"Granada",
    "wof:name":"Masegosa Morales Yolanda",
    "wof:placetype":"venue"
},
  "geometry": {"coordinates":[-2.5766971111,37.5827636719],"type":"Point"}
}