{
  "type": "Feature",
  "properties": {
    "addr:full":"Calle de Comandante Vallespin, 23 Oviedo Asturias 33013",
    "addr:housenumber":"23",
    "addr:postcode":"33013",
    "addr:street":"Calle De Comandante Vallespin",
    "iso:country":"ES",
    "sg:address":"Calle de Comandante Vallespin, 23",
    "sg:city":"Oviedo",
    "sg:orig_category":"Caf\u00c9s, Bares, Cervecer\u00cdas",
    "sg:phone":"+34 985 25 04 96",
    "sg:postcode":"33013",
    "sg:province":"Asturias",
    "wof:name":"Arguelles Alvarez Ismael",
    "wof:placetype":"venue"
},
  "geometry": {"coordinates":[-5.86105299,43.3628845215],"type":"Point"}
}