{
  "type": "Feature",
  "properties": {
    "iso:country":"ES",
    "sg:address":"Calle de Lavaderos, 63",
    "sg:city":"Burgos",
    "sg:orig_category":"Delegados, Agentes De Tr\u00c1nsito, Auxiliares De Transporte Internacional",
    "sg:phone":"+34 947 24 47 55",
    "sg:postcode":"09007",
    "sg:province":"Burgos",
    "wof:name":"Travel Lgk 2001 S.l.",
    "wof:placetype":"venue"
},
  "geometry": {"coordinates":[-3.6715290546,42.3530426025],"type":"Point"}
}