{
  "type": "Feature",
  "properties": {
    "iso:country":"ES",
    "sg:address":"Avda Benigno Rivera, 37",
    "sg:city":"Lugo",
    "sg:orig_category":"Chapister\u00cda",
    "sg:phone":"+34 982 26 42 23",
    "sg:postcode":"27003",
    "sg:province":"Lugo",
    "wof:name":"El Parabrisas Lugo S. L.",
    "wof:placetype":"venue"
},
  "geometry": {"coordinates":[-7.5730628967,43.040813446],"type":"Point"}
}