{
  "type": "Feature",
  "properties": {
    "addr:full":"Carrer de Emporda, 3 Cornella Llobregat Barcelona 08940",
    "addr:housenumber":"3",
    "addr:postcode":"08940",
    "addr:street":"Carrer De Emporda",
    "iso:country":"ES",
    "sg:address":"Carrer de Emporda, 3",
    "sg:city":"Cornella Llobregat",
    "sg:orig_category":"Molduras, Junquillos, Listones Y Molduras Perforadas",
    "sg:phone":"+34 933 75 50 44",
    "sg:postcode":"08940",
    "sg:province":"Barcelona",
    "wof:name":"Baumatel S.l. L.",
    "wof:placetype":"venue"
},
  "geometry": {"coordinates":[2.0795149803,41.359413147],"type":"Point"}
}