{
  "type": "Feature",
  "properties": {
    "addr:full":"Calle de Vascos, 8 Fuenlabrada Madrid 28947",
    "addr:housenumber":"8",
    "addr:postcode":"28947",
    "addr:street":"Calle De Vascos",
    "iso:country":"ES",
    "sg:address":"Calle de Vascos, 8",
    "sg:city":"Fuenlabrada",
    "sg:orig_category":"Comercio De Piezas De Recambio Y De Accesorios De Veh\u00cdculos, Veh\u00cdculos Industriales",
    "sg:phone":"+34 916 42 19 52",
    "sg:postcode":"28947",
    "sg:province":"Madrid",
    "wof:name":"Madrid Motor S.l.",
    "wof:placetype":"venue"
},
  "geometry": {"coordinates":[-3.7567698956,40.2641487122],"type":"Point"}
}