{
  "type": "Feature",
  "properties": {
    "iso:country":"ES",
    "sg:address":"Calle de Iglesia, 16",
    "sg:city":"Viso",
    "sg:orig_category":"Cajas Para Embalar",
    "sg:phone":"+34 957 12 70 71",
    "sg:postcode":"14470",
    "sg:province":"C\u00f3rdoba",
    "wof:name":"Caja Rural De Cordoba",
    "wof:placetype":"venue"
},
  "geometry": {"coordinates":[-4.9548239708,38.4833526611],"type":"Point"}
}