{
  "type": "Feature",
  "properties": {
    "addr:full":"Calle de Sagarminaga, 7 Bilbao Vizcaya 48004",
    "addr:housenumber":"7",
    "addr:postcode":"48004",
    "addr:street":"Calle De Sagarminaga",
    "iso:country":"ES",
    "sg:address":"Calle de Sagarminaga, 7",
    "sg:city":"Bilbao",
    "sg:orig_category":"Plomeros",
    "sg:phone":"+34 944 12 41 16",
    "sg:postcode":"48004",
    "sg:province":"Vizcaya",
    "wof:name":"Pozo Sanchez Jose Ramon",
    "wof:placetype":"venue"
},
  "geometry": {"coordinates":[-2.9114689827,43.2480506897],"type":"Point"}
}