{
  "type": "Feature",
  "properties": {
    "iso:country":"ES",
    "sg:address":"Calle de Curtidores (los), 4",
    "sg:city":"Segovia",
    "sg:orig_category":"Inmobiliaria (agencias)",
    "sg:phone":"+34 921 42 93 30",
    "sg:postcode":"40004",
    "sg:province":"Segovia",
    "wof:name":"Inmobiliaria Inversion Y Gestion Sierra",
    "wof:placetype":"venue"
},
  "geometry": {"coordinates":[-4.1173319817,40.9439849854],"type":"Point"}
}