{
  "type": "Feature",
  "properties": {
    "iso:country":"ES",
    "sg:address":"Calle de Camino De Los Carbayos, 19",
    "sg:city":"Urbanizacion La Fresneda",
    "sg:orig_category":"M\u00c9dicos: Foniatr\u00cda Y Logopedia",
    "sg:phone":"+34 985 26 21 23",
    "sg:postcode":"33429",
    "sg:province":"Asturias",
    "wof:name":"Gorjon Hernandez Alfonso",
    "wof:placetype":"venue"
},
  "geometry": {"coordinates":[-5.7888607979,43.4130096436],"type":"Point"}
}