{
  "type": "Feature",
  "properties": {
    "iso:country":"ES",
    "sg:address":"Calle de Lopez De Alba, 13",
    "sg:city":"Cordoba",
    "sg:orig_category":"Empresas De Carpinter\u00cda De Madera",
    "sg:phone":"+34 957 26 66 59",
    "sg:postcode":"14007",
    "sg:province":"C\u00f3rdoba",
    "wof:name":"Alonso Almendro Serafin",
    "wof:placetype":"venue"
},
  "geometry": {"coordinates":[-4.7670416832,37.8947563171],"type":"Point"}
}