{
  "type": "Feature",
  "properties": {
    "addr:full":"C/ Sant Dionis, 138 Salt Girona 17190",
    "addr:housenumber":"138",
    "addr:postcode":"17190",
    "addr:street":"C / Sant Dionis",
    "iso:country":"ES",
    "sg:address":"C/ Sant Dionis, 138",
    "sg:city":"Salt",
    "sg:orig_category":"Promotores Constructores",
    "sg:phone":"+34 972 40 17 12",
    "sg:postcode":"17190",
    "sg:province":"Girona",
    "wof:name":"Perforaciones J.c.,s.c.",
    "wof:placetype":"venue"
},
  "geometry": {"coordinates":[2.7950398922,41.9770889282],"type":"Point"}
}