{
  "type": "Feature",
  "properties": {
    "addr:full":"Calle de Coso, 126 Zaragoza Zaragoza 50001",
    "addr:housenumber":"126",
    "addr:postcode":"50001",
    "addr:street":"Calle De Coso",
    "iso:country":"ES",
    "sg:address":"Calle de Coso, 126",
    "sg:city":"Zaragoza",
    "sg:orig_category":"Agentes, Concesionarios Y Sucursales De Veh\u00cdculos",
    "sg:phone":"+34 976 20 31 55",
    "sg:postcode":"50001",
    "sg:province":"Zaragoza",
    "wof:name":"Publigrab S. L.",
    "wof:placetype":"venue"
},
  "geometry": {"coordinates":[-0.8755838275,41.6509132385],"type":"Point"}
}