{
  "type": "Feature",
  "properties": {
    "addr:full":"Carrer de Praga, 16 Barcelona Barcelona 08024",
    "addr:housenumber":"16",
    "addr:postcode":"08024",
    "addr:street":"Carrer De Praga",
    "iso:country":"ES",
    "sg:address":"Carrer de Praga, 16",
    "sg:city":"Barcelona",
    "sg:orig_category":"Electricidad, Electr\u00d3nica: Suministros (al Por Menor)",
    "sg:phone":"+34 934 56 33 77",
    "sg:postcode":"08024",
    "sg:province":"Barcelona",
    "wof:name":"Aparicio Bragulat Jorge",
    "wof:placetype":"venue"
},
  "geometry": {"coordinates":[2.1636755466,41.4132232666],"type":"Point"}
}