{
  "type": "Feature",
  "properties": {
    "iso:country":"ES",
    "sg:address":"Calle de Simon Martinez Abad, S/n",
    "sg:city":"Salvatierra O Agurain",
    "sg:orig_category":"Plomeros",
    "sg:phone":"+34 945 30 02 80",
    "sg:postcode":"01200",
    "sg:province":"\u00c1lava",
    "wof:name":"Lafuente Diaz Javier",
    "wof:placetype":"venue"
},
  "geometry": {"coordinates":[-2.3894340992,42.852973938],"type":"Point"}
}