{
  "type": "Feature",
  "properties": {
    "addr:full":"Ctra Bajada De Las Guayarminas, 30 Galdar Las Palmas 35460",
    "addr:housenumber":"30",
    "addr:postcode":"35460",
    "addr:street":"Ctra Bajada De Las Guayarminas",
    "iso:country":"ES",
    "sg:address":"Ctra Bajada De Las Guayarminas, 30",
    "sg:city":"Galdar",
    "sg:orig_category":"Fabricaci\u00d3n, Distribuci\u00d3n De Discos, V\u00cddeodiscos Y Musicassettes",
    "sg:phone":"+34 928 55 33 84",
    "sg:postcode":"35460",
    "sg:province":"Las Palmas",
    "wof:name":"Comercial Santana Noda S.l.",
    "wof:placetype":"venue"
},
  "geometry": {"coordinates":[-15.6528720856,28.1450138092],"type":"Point"}
}