{
  "type": "Feature",
  "properties": {
    "addr:full":"Av Generalitat, 2 Ponts Lleida 25740",
    "addr:housenumber":"2",
    "addr:postcode":"25740",
    "addr:street":"Av Generalitat",
    "iso:country":"ES",
    "sg:address":"Av Generalitat, 2",
    "sg:city":"Ponts",
    "sg:orig_category":"Productores Recolectores, Venta Directa De Vinos",
    "sg:phone":"+34 973 46 22 37",
    "sg:postcode":"25740",
    "sg:province":"Lleida",
    "wof:name":"Cercavins Gourmet S.l.",
    "wof:placetype":"venue"
},
  "geometry": {"coordinates":[1.1874300241,41.9121437073],"type":"Point"}
}