{
  "type": "Feature",
  "properties": {
    "addr:full":"Calle de Parque, 21 Zaragoza Zaragoza 50007",
    "addr:housenumber":"21",
    "addr:postcode":"50007",
    "addr:street":"Calle De Parque",
    "iso:country":"ES",
    "sg:address":"Calle de Parque, 21",
    "sg:city":"Zaragoza",
    "sg:orig_category":"Administradores De Bienes Y Delegados De Comunidades De Propietarios",
    "sg:phone":"+34 976 25 58 02",
    "sg:postcode":"50007",
    "sg:province":"Zaragoza",
    "wof:name":"Administracion Y Gestion De Fincas Abadias S.l.l",
    "wof:placetype":"venue"
},
  "geometry": {"coordinates":[-0.8890584111,41.6292037964],"type":"Point"}
}