{
  "type": "Feature",
  "properties": {
    "addr:full":"Carrer de Sant Josep, 23 Busot Alicante 03111",
    "addr:housenumber":"23",
    "addr:postcode":"03111",
    "addr:street":"Carrer De Sant Josep",
    "iso:country":"ES",
    "sg:address":"Carrer de Sant Josep, 23",
    "sg:city":"Busot",
    "sg:orig_category":"Molduras, Junquillos, Listones Y Molduras Perforadas",
    "sg:phone":"+34 965 69 90 32",
    "sg:postcode":"03111",
    "sg:province":"Alicante",
    "wof:name":"Molina Garcia Antonio",
    "wof:placetype":"venue"
},
  "geometry": {"coordinates":[-0.4181640148,38.4825630188],"type":"Point"}
}