{
  "type": "Feature",
  "properties": {
    "iso:country":"ES",
    "sg:address":"Av Jaume Balmes, 36",
    "sg:city":"Vilanova I La Geltru",
    "sg:orig_category":"Aparcamientos (infraestructuras, Accesorios)",
    "sg:phone":"+34 938 15 45 16",
    "sg:postcode":"08800",
    "sg:province":"Barcelona",
    "wof:name":"Vilanova-centra Parking S.l.",
    "wof:placetype":"venue"
},
  "geometry": {"coordinates":[1.7217650414,41.2196960449],"type":"Point"}
}