{
  "type": "Feature",
  "properties": {
    "iso:country":"ES",
    "sg:address":"Calle de Luchana, 25",
    "sg:city":"Madrid",
    "sg:orig_category":"M\u00c9dicos: Alergolog\u00cda",
    "sg:phone":"+34 914 46 79 89",
    "sg:postcode":"28010",
    "sg:province":"Madrid",
    "wof:name":"Olmeda Y Torreblanca S.l.",
    "wof:placetype":"venue"
},
  "geometry": {"coordinates":[-3.6993219852,40.4314041138],"type":"Point"}
}