{
  "type": "Feature",
  "properties": {
    "addr:full":"Txiplao Kalea, 10 Hondarribia Guip\u00f9zcoa 20280",
    "addr:housenumber":"10",
    "addr:postcode":"20280",
    "addr:street":"Txiplao Kalea;Guipu\u0300Zcoa",
    "iso:country":"ES",
    "sg:address":"Txiplao Kalea, 10",
    "sg:city":"Hondarribia",
    "sg:orig_category":"Molduras, Junquillos, Listones Y Molduras Perforadas",
    "sg:phone":"+34 943 64 05 46",
    "sg:postcode":"20280",
    "sg:province":"Guip\u00f9zcoa",
    "sg:website":"www.banako.com",
    "wof:name":"Banakobar S.l.",
    "wof:placetype":"venue"
},
  "geometry": {"coordinates":[-1.7970939875,43.3614845276],"type":"Point"}
}