{
  "type": "Feature",
  "properties": {
    "addr:full":"Pl. Constitucion, 13 Aguas Nuevas Albacete 02049",
    "addr:housenumber":"13",
    "addr:postcode":"02049",
    "addr:street":"Constitucion",
    "iso:country":"ES",
    "sg:address":"Pl. Constitucion, 13",
    "sg:city":"Aguas Nuevas",
    "sg:orig_category":"Farmacias",
    "sg:phone":"+34 967 27 31 04",
    "sg:postcode":"02049",
    "sg:province":"Albacete",
    "wof:name":"Frias Mirasol Emilia",
    "wof:placetype":"venue"
},
  "geometry": {"coordinates":[-1.9201190472,38.9184341431],"type":"Point"}
}