{
  "type": "Feature",
  "properties": {
    "iso:country":"ES",
    "sg:address":"Calle de Antonio De Cabezon, 33",
    "sg:city":"Madrid",
    "sg:orig_category":"Hormigonados",
    "sg:phone":"+34 917 29 00 49",
    "sg:postcode":"28034",
    "sg:province":"Madrid",
    "sg:website":"www.readymixasland.es",
    "wof:name":"Lafarge Aridos Y Hormigones S.a.",
    "wof:placetype":"venue"
},
  "geometry": {"coordinates":[-3.6812410355,40.4935569763],"type":"Point"}
}