{
  "type": "Feature",
  "properties": {
    "addr:full":"Calle de Vasco Nu\u00d1ez, 3 Badajoz Badajoz 06001",
    "addr:housenumber":"3",
    "addr:postcode":"06001",
    "addr:street":"Calle De Vasco Nun\u0303Ez",
    "iso:country":"ES",
    "sg:address":"Calle de Vasco Nu\u00d1ez, 3",
    "sg:city":"Badajoz",
    "sg:orig_category":"Asistencia Y Consejos",
    "sg:phone":"+34 924 22 19 64",
    "sg:postcode":"06001",
    "sg:province":"Badajoz",
    "wof:name":"Gragera Villalobos Luis",
    "wof:placetype":"venue"
},
  "geometry": {"coordinates":[-6.9738211632,38.8775367737],"type":"Point"}
}