{
  "type": "Feature",
  "properties": {
    "iso:country":"ES",
    "sg:address":"Calle de Pastrana, 15",
    "sg:city":"Miraflores De La Sierra",
    "sg:orig_category":"Trabajos De Drenaje, De Regad\u00cdo",
    "sg:phone":"+34 918 44 40 90",
    "sg:postcode":"28792",
    "sg:province":"Madrid",
    "wof:name":"Blasco Perea Daniel",
    "wof:placetype":"venue"
},
  "geometry": {"coordinates":[-3.7625041008,40.8141822815],"type":"Point"}
}