{
  "type": "Feature",
  "properties": {
    "iso:country":"ES",
    "sg:address":"Kale Zaharra, 55",
    "sg:city":"O\u00f1ati",
    "sg:orig_category":"Grafistas",
    "sg:phone":"+34 943 71 64 67",
    "sg:postcode":"20560",
    "sg:province":"Guip\u00f9zcoa",
    "wof:name":"Javier Erostarbe Garitano",
    "wof:placetype":"venue"
},
  "geometry": {"coordinates":[-2.4141891003,43.0343017578],"type":"Point"}
}