{
  "type": "Feature",
  "properties": {
    "addr:full":"Tajinaste (cuesta Villa), 2 Sta.ursula Santa Cruz De Tenerife 38390",
    "addr:housenumber":"2",
    "addr:postcode":"38390",
    "addr:street":"Cuesta Villa",
    "iso:country":"ES",
    "sg:address":"Tajinaste (cuesta Villa), 2",
    "sg:city":"Sta.ursula",
    "sg:orig_category":"Centros Empresariales",
    "sg:phone":"+34 922 33 77 22",
    "sg:postcode":"38390",
    "sg:province":"Santa Cruz De Tenerife",
    "wof:name":"Phi Management Systems S.l",
    "wof:placetype":"venue"
},
  "geometry": {"coordinates":[-16.4917697906,28.425359726],"type":"Point"}
}