{
  "type": "Feature",
  "properties": {
    "iso:country":"ES",
    "sg:address":"Calle de Baron De Eroles, 1",
    "sg:city":"Monzon",
    "sg:orig_category":"Inmobiliaria (agencias)",
    "sg:phone":"+34 974 41 77 83",
    "sg:postcode":"22400",
    "sg:province":"Huesca",
    "sg:website":"www.donpiso.com",
    "wof:name":"Oferta Y Hogar S.l.",
    "wof:placetype":"venue"
},
  "geometry": {"coordinates":[0.192633301,41.9132461548],"type":"Point"}
}