{
  "type": "Feature",
  "properties": {
    "iso:country":"ES",
    "sg:address":"Pase Alca\u00d1iz, 15",
    "sg:city":"Calanda",
    "sg:orig_category":"Ense\u00d1anza Variada",
    "sg:phone":"+34 978 84 69 74",
    "sg:postcode":"44570",
    "sg:province":"Teruel",
    "wof:name":"Abadia Milian Jose Miguel",
    "wof:placetype":"venue"
},
  "geometry": {"coordinates":[-0.280787,40.978539],"type":"Point"}
}