{
  "type": "Feature",
  "properties": {
    "addr:full":"Rua San Antonio, 21 Melide A Coru\u00f1a 15800",
    "addr:housenumber":"21",
    "addr:postcode":"15800",
    "addr:street":"Rua San Antonio;Corun\u0303A",
    "iso:country":"ES",
    "sg:address":"Rua San Antonio, 21",
    "sg:city":"Melide",
    "sg:orig_category":"Reposter\u00cdas",
    "sg:phone":"+34 981 50 53 82",
    "sg:postcode":"15800",
    "sg:province":"A Coru\u00f1a",
    "wof:name":"Tarrio Prieto Jose Luis",
    "wof:placetype":"venue"
},
  "geometry": {"coordinates":[-8.0174474716,42.9147834778],"type":"Point"}
}