{
  "type": "Feature",
  "properties": {
    "iso:country":"ES",
    "sg:address":"Ctra Valls, 11",
    "sg:city":"Querol",
    "sg:orig_category":"Venta, Instalaci\u00d3n De Cocinas",
    "sg:phone":"+34 977 63 84 62",
    "sg:postcode":"43816",
    "sg:province":"Tarragona",
    "wof:name":"Restaurante San Jordi S.a.l.",
    "wof:placetype":"venue"
},
  "geometry": {"coordinates":[1.3971450329,41.4226913452],"type":"Point"}
}