{
  "type": "Feature",
  "properties": {
    "addr:full":"Rua Lonia (da), 36 Ourense Ourense 32004",
    "addr:postcode":"32004",
    "addr:street":"Rua Lonia Da",
    "iso:country":"ES",
    "sg:address":"Rua Lonia (da), 36",
    "sg:city":"Ourense",
    "sg:orig_category":"Negocio De Madera",
    "sg:phone":"+34 988 23 12 06",
    "sg:postcode":"32004",
    "sg:province":"Ourense",
    "wof:name":"Ocampo Alvarez Moises",
    "wof:placetype":"venue"
},
  "geometry": {"coordinates":[-7.8504590988,42.3482284546],"type":"Point"}
}