{
  "type": "Feature",
  "properties": {
    "addr:full":"Calle de San Juan, 18 Chilluevar Ja\u00e9n 23477",
    "addr:housenumber":"18",
    "addr:postcode":"23477",
    "addr:street":"Calle De San Juan;Jae\u0301N",
    "iso:country":"ES",
    "sg:address":"Calle de San Juan, 18",
    "sg:city":"Chilluevar",
    "sg:classifiers":[
        {
            "category":"Taxi",
            "type":"Transportation"
        }
    ],
    "sg:phone":"+34 953 71 70 23",
    "sg:postcode":"23477",
    "sg:province":"Ja\u00e9n",
    "wof:name":"Grima Romo Juan",
    "wof:placetype":"venue"
},
  "geometry": {"coordinates":[-3.0330350399,37.9995956421],"type":"Point"}
}