{
  "type": "Feature",
  "properties": {
    "addr:full":"Calle de Txinbo Kalea, 9 Zamudio Vizcaya 48170",
    "addr:housenumber":"9",
    "addr:postcode":"48170",
    "addr:street":"Calle De Txinbo Kalea",
    "iso:country":"ES",
    "sg:address":"Calle de Txinbo Kalea, 9",
    "sg:city":"Zamudio",
    "sg:orig_category":"Caf\u00c9s, Bares, Cervecer\u00cdas",
    "sg:phone":"+34 944 52 26 75",
    "sg:postcode":"48170",
    "sg:province":"Vizcaya",
    "wof:name":"Maria Fe Rodriguez Martin",
    "wof:placetype":"venue"
},
  "geometry": {"coordinates":[-2.8624989986,43.2820358276],"type":"Point"}
}