{
  "type": "Feature",
  "properties": {
    "addr:full":"Avda Algorta, 76 B Getxo Vizcaya 48990",
    "addr:housenumber":"76 b",
    "addr:postcode":"48990",
    "addr:street":"Avda Algorta",
    "iso:country":"ES",
    "sg:address":"Avda Algorta, 76 B",
    "sg:city":"Getxo",
    "sg:classifiers":[
        {
            "category":"Personal",
            "subcategory":"Barber",
            "type":"Services"
        }
    ],
    "sg:phone":"+34 944 91 05 17",
    "sg:postcode":"48990",
    "sg:province":"Vizcaya",
    "sg:tags":[
        "caballeros",
        "de",
        "peluqueros"
    ],
    "wof:name":"Maria Nieves Rodriguez Orellano (peluqueria Adonis)",
    "wof:placetype":"venue"
},
  "geometry": {"coordinates":[-3.0094540119,43.3488540649],"type":"Point"}
}