{
  "type": "Feature",
  "properties": {
    "iso:country":"ES",
    "sg:address":"Carrer de Mossen Josep Bundo, 24",
    "sg:city":"Barcelona",
    "sg:orig_category":"Equipos De Marcado, Etiquetado",
    "sg:phone":"+34 934 20 35 98",
    "sg:postcode":"08032",
    "sg:province":"Barcelona",
    "wof:name":"Turon Retolacio S. L.",
    "wof:placetype":"venue"
},
  "geometry": {"coordinates":[2.166285038,41.426738739],"type":"Point"}
}