{
  "type": "Feature",
  "properties": {
    "iso:country":"ES",
    "sg:address":"Calle de Regalado, 2",
    "sg:city":"Valladolid",
    "sg:orig_category":"Zapatos (al Por Menor)",
    "sg:phone":"+34 983 30 65 39",
    "sg:postcode":"47001",
    "sg:province":"Valladolid",
    "wof:name":"Curiel Hernando Sabas",
    "wof:placetype":"venue"
},
  "geometry": {"coordinates":[-4.7263989449,41.6512145996],"type":"Point"}
}