{
  "type": "Feature",
  "properties": {
    "iso:country":"ES",
    "sg:address":"Afueras, 44",
    "sg:city":"Binissalem",
    "sg:orig_category":"Producci\u00d3n, Venta De Productos De Agricultura Biol\u00d3gica",
    "sg:phone":"+34 971 51 12 29",
    "sg:postcode":"07350",
    "sg:province":"Islas Baleares",
    "wof:name":"Biniagual Explotaciones Agricolas S. A.",
    "wof:placetype":"venue"
},
  "geometry": {"coordinates":[2.8465650082,39.6841163635],"type":"Point"}
}