{
  "type": "Feature",
  "properties": {
    "iso:country":"ES",
    "sg:address":"Calle de Do\u00d1a Urraca, 23",
    "sg:city":"Madrid",
    "sg:orig_category":"Molduras, Junquillos, Listones Y Molduras Perforadas",
    "sg:phone":"+34 914 79 03 98",
    "sg:postcode":"28011",
    "sg:province":"Madrid",
    "wof:name":"Gomez Gonzalez Felix",
    "wof:placetype":"venue"
},
  "geometry": {"coordinates":[-3.7271811962,40.4128723145],"type":"Point"}
}