{
  "type": "Feature",
  "properties": {
    "addr:full":"Calle de Nu\u00d1ez De Balboa, 17 Madrid Madrid 28001",
    "addr:housenumber":"17",
    "addr:postcode":"madrid;28001",
    "addr:street":"Calle De Nun\u0303Ez De Balboa",
    "iso:country":"ES",
    "sg:address":"Calle de Nu\u00d1ez De Balboa, 17",
    "sg:city":"Madrid",
    "sg:orig_category":"Inmobiliaria (agencias)",
    "sg:phone":"+34 917 81 34 99",
    "sg:postcode":"28001",
    "sg:province":"Madrid",
    "wof:name":"Oppenheim Inmobilien Kag Sucursal En Espa\u00d1a",
    "wof:placetype":"venue"
},
  "geometry": {"coordinates":[-3.6831169128,40.4232177734],"type":"Point"}
}