{
  "type": "Feature",
  "properties": {
    "addr:full":"Calle de Maestro Guerrero, 3 Valencia Valencia 46008",
    "addr:housenumber":"3",
    "addr:postcode":"46008",
    "addr:street":"Calle De Maestro Guerrero",
    "iso:country":"ES",
    "sg:address":"Calle de Maestro Guerrero, 3",
    "sg:city":"Valencia",
    "sg:orig_category":"Iglesia Cat\u00d3lica",
    "sg:phone":"+34 963 85 07 77",
    "sg:postcode":"46008",
    "sg:province":"Valencia",
    "wof:name":"Parroquia De San Pedro Pascual",
    "wof:placetype":"venue"
},
  "geometry": {"coordinates":[-0.3924489915,39.4734687805],"type":"Point"}
}