{
  "type": "Feature",
  "properties": {
    "iso:country":"ES",
    "sg:address":"Calle de Autonomia, 12",
    "sg:city":"San Vicente De Barakaldo",
    "sg:orig_category":"Papel Pintado (al Por Menor)",
    "sg:phone":"+34 944 38 63 98",
    "sg:postcode":"48902",
    "sg:province":"Vizcaya",
    "wof:name":"Marin Rodriguez Angel",
    "wof:placetype":"venue"
},
  "geometry": {"coordinates":[-2.9904344082,43.2952575684],"type":"Point"}
}