{
  "type": "Feature",
  "properties": {
    "addr:full":"Avda Jose Martinez Gonzalez, 25 Elda Alicante 03600",
    "addr:housenumber":"25",
    "addr:postcode":"03600",
    "addr:street":"Avda Jose Martinez Gonzalez",
    "iso:country":"ES",
    "sg:address":"Avda Jose Martinez Gonzalez, 25",
    "sg:city":"Elda",
    "sg:orig_category":"Cl\u00cdnicas M\u00c9dicas",
    "sg:phone":"+34 965 39 03 58",
    "sg:postcode":"03600",
    "sg:province":"Alicante",
    "wof:name":"Clinica Monasterio S. L.",
    "wof:placetype":"venue"
},
  "geometry": {"coordinates":[-0.7863190174,38.4774208069],"type":"Point"}
}