{
  "type": "Feature",
  "properties": {
    "iso:country":"ES",
    "sg:address":"Pase Larratxo De, 16",
    "sg:city":"Donostia-san Sebastian",
    "sg:orig_category":"Zapater\u00cdas",
    "sg:phone":"+34 943 39 14 15",
    "sg:postcode":"20017",
    "sg:province":"Guip\u00f9zcoa",
    "wof:name":"Rosa Hidalgo Mos",
    "wof:placetype":"venue"
},
  "geometry": {"coordinates":[-1.9399199486,43.3149986267],"type":"Point"}
}