{
  "type": "Feature",
  "properties": {
    "iso:country":"ES",
    "sg:address":"Calle de Medio, 29",
    "sg:city":"Tormantos",
    "sg:orig_category":"Cr\u00cda De Animales",
    "sg:phone":"+34 941 32 71 42",
    "sg:postcode":"26213",
    "sg:province":"La Rioja",
    "wof:name":"Aguero Diez Julio",
    "wof:placetype":"venue"
},
  "geometry": {"coordinates":[-3.0756313801,42.4939460754],"type":"Point"}
}