{
  "type": "Feature",
  "properties": {
    "addr:full":"Av America, 15 Mataro Barcelona 08304",
    "addr:housenumber":"15",
    "addr:postcode":"08304",
    "addr:street":"Av America",
    "iso:country":"ES",
    "sg:address":"Av America, 15",
    "sg:city":"Mataro",
    "sg:orig_category":"Molduras, Junquillos, Listones Y Molduras Perforadas",
    "sg:phone":"+34 937 55 08 97",
    "sg:postcode":"08304",
    "sg:province":"Barcelona",
    "wof:name":"Sanz Saez Miguel",
    "wof:placetype":"venue"
},
  "geometry": {"coordinates":[2.4460010529,41.5477600098],"type":"Point"}
}