{
  "type": "Feature",
  "properties": {
    "addr:full":"Rua Sol, 165 Ferrol A Coru\u00f1a 15401",
    "addr:housenumber":"165",
    "addr:postcode":"15401",
    "addr:street":"Rua Sol;A Corun\u0303A",
    "iso:country":"ES",
    "sg:address":"Rua Sol, 165",
    "sg:city":"Ferrol",
    "sg:orig_category":"Fabricaci\u00d3n, Venta De Cuadros, Accesorios Para Enmarcar",
    "sg:phone":"+34 981 35 61 48",
    "sg:postcode":"15401",
    "sg:province":"A Coru\u00f1a",
    "wof:name":"Villaamil Abad Carlota",
    "wof:placetype":"venue"
},
  "geometry": {"coordinates":[-8.2374868393,43.4832115173],"type":"Point"}
}