{
  "type": "Feature",
  "properties": {
    "addr:full":"Lagoa-cruceiro De Roo, S/n Roo La Coru\u00f1a 15287",
    "addr:postcode":"15287",
    "addr:street":"S / N Roo La Corun\u0303A",
    "iso:country":"ES",
    "sg:address":"Lagoa-cruceiro De Roo, S/n",
    "sg:city":"Roo",
    "sg:orig_category":"Reposter\u00cdas",
    "sg:phone":"+34 981 76 54 87",
    "sg:postcode":"15287",
    "sg:province":"La Coru\u00f1a",
    "wof:name":"Forno San Cosme S.l.",
    "wof:placetype":"venue"
},
  "geometry": {"coordinates":[-8.9290475845,42.8262710571],"type":"Point"}
}