{
  "type": "Feature",
  "properties": {
    "iso:country":"ES",
    "sg:address":"Rua Monti\u00d1o G, 5",
    "sg:city":"Grove",
    "sg:orig_category":"Fisioterapia",
    "sg:phone":"+34 986 73 37 64",
    "sg:postcode":"36980",
    "sg:province":"Pontevedra",
    "wof:name":"Costa Iglesias Joaquina",
    "wof:placetype":"venue"
},
  "geometry": {"coordinates":[-8.8660106659,42.4928321838],"type":"Point"}
}