{
  "type": "Feature",
  "properties": {
    "iso:country":"ES",
    "sg:address":"Carrer de Cambrils, 3",
    "sg:city":"Mont-roig Camp",
    "sg:orig_category":"Quincaller\u00cda (al Por Menor)",
    "sg:phone":"+34 977 83 81 90",
    "sg:postcode":"43300",
    "sg:province":"Tarragona",
    "wof:name":"Ferreteria Olesti S.l.",
    "wof:placetype":"venue"
},
  "geometry": {"coordinates":[0.9610750079,41.0863227844],"type":"Point"}
}