{
  "type": "Feature",
  "properties": {
    "addr:full":"Calle de Innovacion, S/n Sevilla Sevilla 41020",
    "addr:housenumber":"s / n",
    "addr:postcode":"41020",
    "addr:street":"Calle De Innovacion",
    "iso:country":"ES",
    "sg:address":"Calle de Innovacion, S/n",
    "sg:city":"Sevilla",
    "sg:orig_category":"Bazares, Art\u00cdculos De Limpieza Y De Cocina (al Por Menor)",
    "sg:phone":"+34 954 67 24 56",
    "sg:postcode":"41020",
    "sg:province":"Sevilla",
    "wof:name":"Villegas Lancha Antonio",
    "wof:placetype":"venue"
},
  "geometry": {"coordinates":[-5.9279742241,37.4058189392],"type":"Point"}
}