{
  "type": "Feature",
  "properties": {
    "iso:country":"ES",
    "sg:address":"Carrer de Mallorca, 91",
    "sg:city":"Barcelona",
    "sg:orig_category":"Teatro, Ballet, Danza (agrupaciones, Compa\u00d1\u00cdas)",
    "sg:phone":"+34 933 21 96 52",
    "sg:postcode":"08029",
    "sg:province":"Barcelona",
    "wof:name":"Arana Actors Action S.l.",
    "wof:placetype":"venue"
},
  "geometry": {"coordinates":[2.1513779163,41.3854598999],"type":"Point"}
}