{
  "type": "Feature",
  "properties": {
    "iso:country":"ES",
    "sg:address":"Calle de Juan De La Cierva, 18",
    "sg:city":"Arganda",
    "sg:orig_category":"Tapicer\u00cdas",
    "sg:phone":"+34 918 71 71 47",
    "sg:postcode":"28500",
    "sg:province":"Madrid",
    "wof:name":"Barrero Soto Jose",
    "wof:placetype":"venue"
},
  "geometry": {"coordinates":[-3.4397630692,40.3012046814],"type":"Point"}
}