{
  "type": "Feature",
  "properties": {
    "iso:country":"ES",
    "sg:address":"Calle de Nazaries, 4",
    "sg:city":"Granada",
    "sg:orig_category":"Fabricaci\u00d3n, Importaci\u00d3n, Venta De Material De Telefon\u00cda, Peritelefon\u00cda",
    "sg:phone":"+34 958 26 17 85",
    "sg:postcode":"18005",
    "sg:province":"Granada",
    "wof:name":"Reinson S.l.",
    "wof:placetype":"venue"
},
  "geometry": {"coordinates":[-3.6006970406,37.1669578552],"type":"Point"}
}