{
  "type": "Feature",
  "properties": {
    "iso:country":"ES",
    "sg:address":"Carrer de Francesc Marti I M, 58",
    "sg:city":"Palma",
    "sg:orig_category":"Piscinas, Accesorios, Suministros (fabricaci\u00d3n, Al Por Mayor)",
    "sg:phone":"+34 971 45 06 74",
    "sg:postcode":"07011",
    "sg:province":"Islas Baleares",
    "wof:name":"Ruiz Lopez Jose",
    "wof:placetype":"venue"
},
  "geometry": {"coordinates":[2.6373300552,39.5834007263],"type":"Point"}
}