{
  "type": "Feature",
  "properties": {
    "iso:country":"ES",
    "sg:address":"Carrer de Bejar, 37",
    "sg:city":"Barcelona",
    "sg:orig_category":"Teatro, Ballet, Danza (agrupaciones, Compa\u00d1\u00cdas)",
    "sg:phone":"+34 934 25 26 93",
    "sg:postcode":"08014",
    "sg:province":"Barcelona",
    "wof:name":"Ballesteros Sacla Javier",
    "wof:placetype":"venue"
},
  "geometry": {"coordinates":[2.145387888,41.3769111633],"type":"Point"}
}