{
  "type": "Feature",
  "properties": {
    "iso:country":"ES",
    "sg:address":"Carr Arravaleta, 7",
    "sg:city":"Mao",
    "sg:orig_category":"Bancos",
    "sg:phone":"+34 971 36 36 00",
    "sg:postcode":"07702",
    "sg:province":"Islas Baleares",
    "sg:website":"www.bancamarch.es",
    "wof:name":"Banca March S.a.",
    "wof:placetype":"venue"
},
  "geometry": {"coordinates":[4.265625,39.8903694153],"type":"Point"}
}