{
  "type": "Feature",
  "properties": {
    "iso:country":"ES",
    "sg:address":"Calle de Alcala, 151",
    "sg:city":"Madrid",
    "sg:orig_category":"Confecci\u00d3n De Trajes Para Se\u00d1oras",
    "sg:phone":"+34 915 76 55 35",
    "sg:postcode":"28009",
    "sg:province":"Madrid",
    "wof:name":"Giver S. A.",
    "wof:placetype":"venue"
},
  "geometry": {"coordinates":[-3.6756360531,40.4248199463],"type":"Point"}
}