{
  "type": "Feature",
  "properties": {
    "addr:full":"Trascorrales, 13 Oviedo Asturias 33009",
    "addr:housenumber":"13",
    "addr:postcode":"33009",
    "addr:street":"Trascorrales",
    "iso:country":"ES",
    "sg:address":"Trascorrales, 13",
    "sg:city":"Oviedo",
    "sg:orig_category":"Granos Y Semillas (producci\u00d3n, Al Por Mayor)",
    "sg:phone":"+34 985 21 21 38",
    "sg:postcode":"33009",
    "sg:province":"Asturias",
    "wof:name":"Arg\u00fcelles Gonzalez Santiago",
    "wof:placetype":"venue"
},
  "geometry": {"coordinates":[-5.8439202309,43.3608589172],"type":"Point"}
}