{
  "type": "Feature",
  "properties": {
    "iso:country":"ES",
    "sg:address":"Calle de Baltasar Gracian, 5",
    "sg:city":"Zaragoza",
    "sg:orig_category":"Arquitectos",
    "sg:phone":"+34 976 56 60 59",
    "sg:postcode":"50005",
    "sg:province":"Zaragoza",
    "wof:name":"Aldanondo Y Laurenzana Arquitectura Y Urbanismo S.l.",
    "wof:placetype":"venue"
},
  "geometry": {"coordinates":[-0.8930355906,41.6441268921],"type":"Point"}
}