{
  "type": "Feature",
  "properties": {
    "addr:full":"Calle de Motilla Del Palancar, 15 Valencia Valencia 46019",
    "addr:housenumber":"15",
    "addr:postcode":"46019",
    "addr:street":"Calle De Motilla Del Palancar",
    "iso:country":"ES",
    "sg:address":"Calle de Motilla Del Palancar, 15",
    "sg:city":"Valencia",
    "sg:orig_category":"Abogados",
    "sg:phone":"+34 963 66 60 26",
    "sg:postcode":"46019",
    "sg:province":"Valencia",
    "wof:name":"Lopez Pardo Maria Carmen",
    "wof:placetype":"venue"
},
  "geometry": {"coordinates":[-0.3688040972,39.4904327393],"type":"Point"}
}