{
  "type": "Feature",
  "properties": {
    "addr:full":"Avda Maruja Mallo, S/n Madrid Madrid 28050",
    "addr:housenumber":"s / n",
    "addr:postcode":"28050",
    "addr:street":"Avda Maruja Mallo",
    "iso:country":"ES",
    "sg:address":"Avda Maruja Mallo, S/n",
    "sg:city":"Madrid",
    "sg:orig_category":"Farmacias",
    "sg:phone":"+34 913 82 50 33",
    "sg:postcode":"28050",
    "sg:province":"Madrid",
    "wof:name":"Noguera Cases Maria Dolores",
    "wof:placetype":"venue"
},
  "geometry": {"coordinates":[-3.63083601,40.4798774719],"type":"Point"}
}