{
  "type": "Feature",
  "properties": {
    "addr:full":"Pl Carros (dels), 11 Tarragona Tarragona 43004",
    "addr:housenumber":"11",
    "addr:postcode":"43004",
    "addr:street":"Pl;Dels",
    "iso:country":"ES",
    "sg:address":"Pl Carros (dels), 11",
    "sg:city":"Tarragona",
    "sg:orig_category":"Juegos Y Juguetes (al Por Menor)",
    "sg:phone":"+34 977 24 01 44",
    "sg:postcode":"43004",
    "sg:province":"Tarragona",
    "wof:name":"Solana Gabas Ramon",
    "wof:placetype":"venue"
},
  "geometry": {"coordinates":[1.2499569654,41.1108055115],"type":"Point"}
}