{
  "type": "Feature",
  "properties": {
    "addr:full":"Avda Principal, 19 Navas Del Marques \u00c1vila 05230",
    "addr:housenumber":"19",
    "addr:postcode":"05230",
    "addr:street":"Avda Principal;A\u0301Vila",
    "iso:country":"ES",
    "sg:address":"Avda Principal, 19",
    "sg:city":"Navas Del Marques",
    "sg:orig_category":"Molduras, Junquillos, Listones Y Molduras Perforadas",
    "sg:phone":"+34 918 97 00 60",
    "sg:postcode":"05230",
    "sg:province":"\u00c1vila",
    "wof:name":"Pe\u00f1a Bernardo De Quiros Gregorio",
    "wof:placetype":"venue"
},
  "geometry": {"coordinates":[-4.3329401016,40.6029129028],"type":"Point"}
}