{
  "type": "Feature",
  "properties": {
    "iso:country":"ES",
    "sg:address":"Carr Santa Sofia, 5",
    "sg:city":"Villarreal",
    "sg:orig_category":"Internados & Ense\u00d1anza Privada",
    "sg:phone":"+34 964 52 11 26",
    "sg:postcode":"12540",
    "sg:province":"Castell\u00f3n",
    "wof:name":"Colegio Obispo Pont",
    "wof:placetype":"venue"
},
  "geometry": {"coordinates":[-0.0952939987,39.9453048706],"type":"Point"}
}