{
  "type": "Feature",
  "properties": {
    "addr:full":"Carrer de Joan Vidal I Jumbert, 5 Granollers Barcelona 08403",
    "addr:housenumber":"5",
    "addr:postcode":"08403",
    "addr:street":"Carrer De Joan Vidal I Jumbert",
    "iso:country":"ES",
    "sg:address":"Carrer de Joan Vidal I Jumbert, 5",
    "sg:city":"Granollers",
    "sg:orig_category":"Agentes Generales De Seguros",
    "sg:phone":"+34 938 40 36 57",
    "sg:postcode":"08403",
    "sg:province":"Barcelona",
    "wof:name":"Rodriguez Pedraza Salvador",
    "wof:placetype":"venue"
},
  "geometry": {"coordinates":[2.2817111015,41.6133804321],"type":"Point"}
}