{
  "type": "Feature",
  "properties": {
    "iso:country":"ES",
    "sg:address":"Florencio Ansoleaga, 16",
    "sg:city":"Iru\u00f1a",
    "sg:orig_category":"Restaurantes",
    "sg:phone":"+34 948 22 32 26",
    "sg:postcode":"31001",
    "sg:province":"Navarra",
    "wof:name":"Mariezcurrena Elizalde Ignacio Mariezcur",
    "wof:placetype":"venue"
},
  "geometry": {"coordinates":[-1.6462459564,42.8172950745],"type":"Point"}
}