{
  "type": "Feature",
  "properties": {
    "addr:full":"Calle de Folklore (del), 4 Partija-santa Monica Madrid 28529",
    "addr:housenumber":"4",
    "addr:postcode":"28529",
    "addr:street":"Calle De Folklore Del",
    "iso:country":"ES",
    "sg:address":"Calle de Folklore (del), 4",
    "sg:city":"Partija-santa Monica",
    "sg:orig_category":"Empresarios",
    "sg:phone":"+34 916 70 22 34",
    "sg:postcode":"28529",
    "sg:province":"Madrid",
    "wof:name":"Cespedes Prieto Sergio",
    "wof:placetype":"venue"
},
  "geometry": {"coordinates":[-3.5102670193,40.314289093],"type":"Point"}
}