{
  "type": "Feature",
  "properties": {
    "iso:country":"ES",
    "sg:address":"Calle de Postiguillo, 18",
    "sg:city":"Torredonjimeno",
    "sg:orig_category":"Pod\u00d3logos: Pedicuros",
    "sg:phone":"+34 953 57 13 70",
    "sg:postcode":"23650",
    "sg:province":"Ja\u00e9n",
    "wof:name":"Pamos Ure\u00f1a Manuel",
    "wof:placetype":"venue"
},
  "geometry": {"coordinates":[-3.9577949047,37.7670402527],"type":"Point"}
}