{
  "type": "Feature",
  "properties": {
    "addr:full":"Carr Colomer, 9 Palafrugell Girona 17200",
    "addr:housenumber":"9",
    "addr:postcode":"17200",
    "addr:street":"Carr Colomer",
    "iso:country":"ES",
    "sg:address":"Carr Colomer, 9",
    "sg:city":"Palafrugell",
    "sg:orig_category":"Ropa Para Caballeros (al Por Menor)",
    "sg:phone":"+34 972 30 23 37",
    "sg:postcode":"17200",
    "sg:province":"Girona",
    "wof:name":"Marti Corominas Roberto",
    "wof:placetype":"venue"
},
  "geometry": {"coordinates":[3.1636381149,41.9188041687],"type":"Point"}
}