{
  "type": "Feature",
  "properties": {
    "iso:country":"ES",
    "sg:address":"Calle de Doctor Velazquez, 11",
    "sg:city":"Segorbe",
    "sg:orig_category":"Agentes Generales De Seguros",
    "sg:phone":"+34 964 71 35 65",
    "sg:postcode":"12400",
    "sg:province":"Castell\u00f3n",
    "wof:name":"Casamayor Marco Juan",
    "wof:placetype":"venue"
},
  "geometry": {"coordinates":[-0.4872210026,39.8488578796],"type":"Point"}
}