{
  "type": "Feature",
  "properties": {
    "iso:country":"ES",
    "sg:address":"Ctra Madrid, S/n",
    "sg:city":"Corella",
    "sg:orig_category":"Ferreter\u00cda Artesanal",
    "sg:phone":"+34 948 78 02 26",
    "sg:postcode":"31591",
    "sg:province":"Navarra",
    "wof:name":"Forja Artistica El Molino Viejo S.l.",
    "wof:placetype":"venue"
},
  "geometry": {"coordinates":[-1.7783639431,42.1147994995],"type":"Point"}
}