{
  "type": "Feature",
  "properties": {
    "iso:country":"ES",
    "sg:address":"Avda Paseo De Almeria, 22",
    "sg:city":"Almeria",
    "sg:orig_category":"Promotores Constructores",
    "sg:phone":"+34 950 26 73 44",
    "sg:postcode":"04001",
    "sg:province":"Almer\u00eda",
    "sg:website":"www.la-romana.com",
    "wof:name":"Desarrollos Inmobiliarios Almerimar S.a.",
    "wof:placetype":"venue"
},
  "geometry": {"coordinates":[-2.4608390331,36.8422698975],"type":"Point"}
}