{
  "type": "Feature",
  "properties": {
    "addr:full":"Cust Corvales, 2 Zubia Granada 18140",
    "addr:housenumber":"2",
    "addr:postcode":"18140",
    "addr:street":"Corvales",
    "iso:country":"ES",
    "sg:address":"Cust Corvales, 2",
    "sg:city":"Zubia",
    "sg:orig_category":"\u00d3ptica: Instrumentos (fabricaci\u00d3n)",
    "sg:phone":"+34 958 59 01 01",
    "sg:postcode":"18140",
    "sg:province":"Granada",
    "wof:name":"Granados Linde Silvia",
    "wof:placetype":"venue"
},
  "geometry": {"coordinates":[-3.5853440762,37.1218338013],"type":"Point"}
}