{
  "type": "Feature",
  "properties": {
    "addr:full":"Calle de Galicia, 21 Mancha Real Ja\u00e9n 23100",
    "addr:housenumber":"21",
    "addr:postcode":"23100",
    "addr:street":"Calle De Galicia",
    "iso:country":"ES",
    "sg:address":"Calle de Galicia, 21",
    "sg:city":"Mancha Real",
    "sg:orig_category":"Vinos (agentes)",
    "sg:phone":"+34 953 35 10 17",
    "sg:postcode":"23100",
    "sg:province":"Ja\u00e9n",
    "wof:name":"Jimenez Abadia Catalina",
    "wof:placetype":"venue"
},
  "geometry": {"coordinates":[-3.6077167988,37.7839622498],"type":"Point"}
}