{
  "type": "Feature",
  "properties": {
    "addr:full":"Av Alameda (l'), 19 Alcoi Alicante 03803",
    "addr:housenumber":"19",
    "addr:postcode":"03803",
    "addr:street":"Av Alameda L '",
    "iso:country":"ES",
    "sg:address":"Av Alameda (l'), 19",
    "sg:city":"Alcoi",
    "sg:orig_category":"M\u00c9dicos: Ginecolog\u00cda Y Obstetricia",
    "sg:phone":"+34 965 33 10 54",
    "sg:postcode":"03803",
    "sg:province":"Alicante",
    "wof:name":"Miguel Cifuentes Angel",
    "wof:placetype":"venue"
},
  "geometry": {"coordinates":[-0.4795460105,38.7002677917],"type":"Point"}
}