{
  "type": "Feature",
  "properties": {
    "addr:full":"Calle de Fudre (del), 3 Valdepe\u00f1as Ciudad Real 13300",
    "addr:housenumber":"3",
    "addr:postcode":"13300",
    "addr:street":"Calle De Fudre Del",
    "iso:country":"ES",
    "sg:address":"Calle de Fudre (del), 3",
    "sg:city":"Valdepe\u00f1as",
    "sg:orig_category":"Zapatos (al Por Menor)",
    "sg:phone":"+34 926 31 05 97",
    "sg:postcode":"13300",
    "sg:province":"Ciudad Real",
    "wof:name":"Pepe-iha S.a.",
    "wof:placetype":"venue"
},
  "geometry": {"coordinates":[-3.3955519199,38.7776527405],"type":"Point"}
}