{
  "type": "Feature",
  "properties": {
    "addr:full":"Calle de Sagrada Familia, 21 Granada Granada 18015",
    "addr:housenumber":"21",
    "addr:postcode":"18015",
    "addr:street":"Calle De Sagrada Familia",
    "iso:country":"ES",
    "sg:address":"Calle de Sagrada Familia, 21",
    "sg:city":"Granada",
    "sg:orig_category":"Zapatos (al Por Menor)",
    "sg:phone":"+34 958 20 37 31",
    "sg:postcode":"18015",
    "sg:province":"Granada",
    "wof:name":"Escudero Cabello Montserrat",
    "wof:placetype":"venue"
},
  "geometry": {"coordinates":[-3.6249120235,37.1905899048],"type":"Point"}
}