{
  "type": "Feature",
  "properties": {
    "iso:country":"ES",
    "sg:address":"Carrer de Cardenal Lluch, 9",
    "sg:city":"Manresa",
    "sg:orig_category":"Quiropr\u00c1cticos",
    "sg:phone":"+34 938 72 88 28",
    "sg:postcode":"08241",
    "sg:province":"Barcelona",
    "wof:name":"Fargas Moncunil Rosa",
    "wof:placetype":"venue"
},
  "geometry": {"coordinates":[1.8224929571,41.7265625],"type":"Point"}
}