{
  "type": "Feature",
  "properties": {
    "iso:country":"ES",
    "sg:address":"Av La Devesa, 12",
    "sg:city":"Silla",
    "sg:orig_category":"Fabricaci\u00d3n De Clavijas Y De Pistones",
    "sg:phone":"+34 961 21 24 22",
    "sg:postcode":"46460",
    "sg:province":"Valencia",
    "sg:website":"www.tapeplast.com",
    "wof:name":"Tapeplast S.l.",
    "wof:placetype":"venue"
},
  "geometry": {"coordinates":[-0.4074940085,39.3736076355],"type":"Point"}
}