{
  "type": "Feature",
  "properties": {
    "iso:country":"ES",
    "sg:address":"Calle de Budapest, S/n",
    "sg:city":"Torrejon Ardoz",
    "sg:orig_category":"Centros De Educaci\u00d3n Especial",
    "sg:phone":"+34 916 77 00 68",
    "sg:postcode":"28850",
    "sg:province":"Madrid",
    "wof:name":"Colegio Publico Uno De Mayo",
    "wof:placetype":"venue"
},
  "geometry": {"coordinates":[-3.4633927345,40.4623680115],"type":"Point"}
}