{
  "type": "Feature",
  "properties": {
    "addr:full":"Carrer de Nou, 97 Vic Barcelona 08500",
    "addr:housenumber":"97",
    "addr:postcode":"08500",
    "addr:street":"Carrer De Nou",
    "iso:country":"ES",
    "sg:address":"Carrer de Nou, 97",
    "sg:city":"Vic",
    "sg:orig_category":"Pescader\u00cdas (al Por Menor)",
    "sg:phone":"+34 938 86 29 73",
    "sg:postcode":"08500",
    "sg:province":"Barcelona",
    "wof:name":"Reyes Colomer Josefa",
    "wof:placetype":"venue"
},
  "geometry": {"coordinates":[2.2588670254,41.931678772],"type":"Point"}
}