{
  "type": "Feature",
  "properties": {
    "iso:country":"ES",
    "sg:address":"San Prudentzio Kalea, 17",
    "sg:city":"Lazkao",
    "sg:orig_category":"Carnicer\u00cdas, Carnicer\u00cdas",
    "sg:phone":"+34 943 88 33 52",
    "sg:postcode":"20210",
    "sg:province":"Guip\u00f9zcoa",
    "wof:name":"Aracama Mugica Miguel",
    "wof:placetype":"venue"
},
  "geometry": {"coordinates":[-2.1899123192,43.0292854309],"type":"Point"}
}