{
  "type": "Feature",
  "properties": {
    "iso:country":"ES",
    "sg:address":"Calle de Escritor Carrillo Lasso, S/n",
    "sg:city":"Cordoba",
    "sg:orig_category":"Agencias Y Asesores De Publicidad",
    "sg:phone":"+34 957 43 61 20",
    "sg:postcode":"14007",
    "sg:province":"C\u00f3rdoba",
    "wof:name":"Equipamientos Urbanos Del Sur S.a.",
    "wof:placetype":"venue"
},
  "geometry": {"coordinates":[-4.7549190521,37.8951416016],"type":"Point"}
}