{
  "type": "Feature",
  "properties": {
    "iso:country":"ES",
    "sg:address":"Rua Ronda Don Bosco, 41",
    "sg:city":"Vigo",
    "sg:orig_category":"Mercer\u00cda, Lencer\u00cda (al Por Menor)",
    "sg:phone":"+34 986 22 58 53",
    "sg:postcode":"36202",
    "sg:province":"Pontevedra",
    "wof:name":"Lugo Cota Sara",
    "wof:placetype":"venue"
},
  "geometry": {"coordinates":[-8.7225008011,42.235168457],"type":"Point"}
}