{
  "type": "Feature",
  "properties": {
    "iso:country":"ES",
    "sg:address":"Ptge Alio, 29",
    "sg:city":"Barcelona",
    "sg:orig_category":"Inmobiliaria (agencias)",
    "sg:phone":"+34 932 07 02 20",
    "sg:postcode":"08037",
    "sg:province":"Barcelona",
    "wof:name":"Cabo Condal S.l.",
    "wof:placetype":"venue"
},
  "geometry": {"coordinates":[2.1652560234,41.4033546448],"type":"Point"}
}