{
  "type": "Feature",
  "properties": {
    "iso:country":"ES",
    "sg:address":"Carrer de Joan Torruella I Urpina, 21",
    "sg:city":"Cervello",
    "sg:orig_category":"Condimentos, Especias, Vinagres, Salsas Preparadas (fabricaci\u00d3n, Al Por Mayor)",
    "sg:phone":"+34 936 84 27 22",
    "sg:postcode":"08758",
    "sg:province":"Barcelona",
    "wof:name":"Especialidades Aromaticas S.l.",
    "wof:placetype":"venue"
},
  "geometry": {"coordinates":[1.9612640142,41.3989944458],"type":"Point"}
}