{
  "type": "Feature",
  "properties": {
    "addr:full":"Ctra. Benalup-vejer, S/n Benalup C\u00e1diz 11190",
    "addr:housenumber":"s",
    "addr:postcode":"11190",
    "addr:street":"Ctra. Benalup-Vejer;/ N;Ca\u0301Diz",
    "iso:country":"ES",
    "sg:address":"Ctra. Benalup-vejer, S/n",
    "sg:city":"Benalup",
    "sg:orig_category":"Ense\u00d1anza Secundaria: Colegios Y Escuelas Privadas",
    "sg:phone":"+34 956 41 76 81",
    "sg:postcode":"11190",
    "sg:province":"C\u00e1diz",
    "wof:name":"Junta De Andalucia",
    "wof:placetype":"venue"
},
  "geometry": {"coordinates":[-5.8207888603,36.3441352844],"type":"Point"}
}