{
  "type": "Feature",
  "properties": {
    "addr:full":"Calle de Jose Reus Garcia, 3 Alacant Alicante 03010",
    "addr:housenumber":"3",
    "addr:postcode":"03010",
    "addr:street":"Calle De Jose Reus Garcia",
    "iso:country":"ES",
    "sg:address":"Calle de Jose Reus Garcia, 3",
    "sg:city":"Alacant",
    "sg:orig_category":"Automatizaci\u00d3n De Procesos Industriales Y De Edificaci\u00d3n (estudios, Instalaci\u00d3n)",
    "sg:phone":"+34 965 17 20 36",
    "sg:postcode":"03010",
    "sg:province":"Alicante",
    "wof:name":"Electricidad Manuel Garcia S. L.",
    "wof:placetype":"venue"
},
  "geometry": {"coordinates":[-0.492610991,38.3638458252],"type":"Point"}
}