{
  "type": "Feature",
  "properties": {
    "addr:full":"Avda Gonzalez Meneses, 1 Cabra C\u00f3rdoba 14940",
    "addr:housenumber":"1",
    "addr:postcode":"14940",
    "addr:street":"Avda Gonzalez Meneses;Co\u0301Rdoba",
    "iso:country":"ES",
    "sg:address":"Avda Gonzalez Meneses, 1",
    "sg:city":"Cabra",
    "sg:orig_category":"Centros De Educaci\u00d3n Especial",
    "sg:phone":"+34 957 52 09 24",
    "sg:postcode":"14940",
    "sg:province":"C\u00f3rdoba",
    "wof:name":"Junta De Andalucia",
    "wof:placetype":"venue"
},
  "geometry": {"coordinates":[-4.4368805885,37.4717941284],"type":"Point"}
}