{
  "type": "Feature",
  "properties": {
    "iso:country":"ES",
    "sg:address":"Plaz Constitucion (de La), 1",
    "sg:city":"Villamanrique De Tajo",
    "sg:orig_category":"Administraciones Regionales, Departamentales Y Locales",
    "sg:phone":"+34 918 72 71 86",
    "sg:postcode":"28598",
    "sg:province":"Madrid",
    "wof:name":"Ayuntamiento De Villamanrique De Tajo",
    "wof:placetype":"venue"
},
  "geometry": {"coordinates":[-3.2483057976,40.0691604614],"type":"Point"}
}