{
  "type": "Feature",
  "properties": {
    "addr:full":"Calle de Puerto Rico, 8 Valencia Valencia 46006",
    "addr:housenumber":"8",
    "addr:postcode":"46006",
    "addr:street":"Calle De Puerto Rico",
    "iso:country":"ES",
    "sg:address":"Calle de Puerto Rico, 8",
    "sg:city":"Valencia",
    "sg:orig_category":"Agentes, Concesionarios Y Sucursales De Veh\u00cdculos",
    "sg:phone":"+34 963 42 06 22",
    "sg:postcode":"46006",
    "sg:province":"Valencia",
    "sg:website":"www.grupo-iberica.com",
    "wof:name":"Iberlogistic Spares Company S.l.",
    "wof:placetype":"venue"
},
  "geometry": {"coordinates":[-0.3744539917,39.4620132446],"type":"Point"}
}