{
  "type": "Feature",
  "properties": {
    "addr:full":"Carrer de Angel Guimera, 9 Esplugues Llobregat Barcelona 08950",
    "addr:housenumber":"9",
    "addr:postcode":"08950",
    "addr:street":"Carrer De Angel Guimera",
    "iso:country":"ES",
    "sg:address":"Carrer de Angel Guimera, 9",
    "sg:city":"Esplugues Llobregat",
    "sg:orig_category":"Farmacias",
    "sg:phone":"+34 933 71 00 49",
    "sg:postcode":"08950",
    "sg:province":"Barcelona",
    "wof:name":"Jene Borras Francesc",
    "wof:placetype":"venue"
},
  "geometry": {"coordinates":[2.0865499973,41.37733078],"type":"Point"}
}