{
  "type": "Feature",
  "properties": {
    "iso:country":"ES",
    "sg:address":"Calle de Alianza (la), 9",
    "sg:city":"Aljorra",
    "sg:orig_category":"M\u00c9dicos: Estomatolog\u00cda",
    "sg:phone":"+34 968 55 81 23",
    "sg:postcode":"30390",
    "sg:province":"Murcia",
    "wof:name":"Urios Rodriguez Carmelo",
    "wof:placetype":"venue"
},
  "geometry": {"coordinates":[-1.0730890036,37.6916542053],"type":"Point"}
}