{
  "type": "Feature",
  "properties": {
    "iso:country":"ES",
    "sg:address":"Barr Urioste, 91",
    "sg:city":"Urioste",
    "sg:orig_category":"Empresarios",
    "sg:phone":"+34 946 64 05 08",
    "sg:postcode":"48530",
    "sg:province":"Vizcaya",
    "wof:name":"Garcia Fernandez Manuel",
    "wof:placetype":"venue"
},
  "geometry": {"coordinates":[-3.0566248894,43.3107376099],"type":"Point"}
}