{
  "type": "Feature",
  "properties": {
    "iso:country":"ES",
    "sg:address":"Ferdinand Zeppelin, 29",
    "sg:city":"Mi\u00f1ano Menor",
    "sg:orig_category":"Maquinaria Para Industrias Diversas",
    "sg:phone":"+34 945 29 81 81",
    "sg:postcode":"01510",
    "sg:province":"\u00c1lava",
    "wof:name":"Azul Multimedia S.l.",
    "wof:placetype":"venue"
},
  "geometry": {"coordinates":[-2.6619389057,42.9128570557],"type":"Point"}
}