{
  "type": "Feature",
  "properties": {
    "iso:country":"ES",
    "sg:address":"Calle de Allende Manuel, 16",
    "sg:city":"Bilbao",
    "sg:orig_category":"M\u00c9dicos: Oftalmolog\u00cda",
    "sg:phone":"+34 944 21 19 23",
    "sg:postcode":"48010",
    "sg:province":"Vizcaya",
    "wof:name":"Grijalvo Lopez Jesus Alfonso",
    "wof:placetype":"venue"
},
  "geometry": {"coordinates":[-2.942022562,43.2596092224],"type":"Point"}
}