{
  "type": "Feature",
  "properties": {
    "addr:full":"Calle de De Los Herreros, 8 Benavente Zamora 49600",
    "addr:housenumber":"8",
    "addr:postcode":"49600",
    "addr:street":"Calle De De Los Herreros",
    "iso:country":"ES",
    "sg:address":"Calle de De Los Herreros, 8",
    "sg:city":"Benavente",
    "sg:classifiers":[
        {
            "category":"Communications",
            "type":"Services"
        }
    ],
    "sg:phone":"+34 980 63 51 88",
    "sg:postcode":"49600",
    "sg:province":"Zamora",
    "sg:tags":[
        "televisiones",
        "y",
        "radio"
    ],
    "wof:name":"Radio Popular S.a. Cadena De Ondas Populares Esp",
    "wof:placetype":"venue"
},
  "geometry": {"coordinates":[-5.6773509979,42.0072517395],"type":"Point"}
}