{
  "type": "Feature",
  "properties": {
    "iso:country":"ES",
    "sg:address":"Carrer de Francesc Moragas, 9",
    "sg:city":"Hospitalet Llobregat",
    "sg:orig_category":"Seguridad En El Trabajo Y Prevenci\u00d3n De Riesgos Laborales",
    "sg:phone":"+34 932 60 06 03",
    "sg:postcode":"08901",
    "sg:province":"Barcelona",
    "wof:name":"Preven-gest Asesores Prevencion Gestion Riesgos Laborales S.l.",
    "wof:placetype":"venue"
},
  "geometry": {"coordinates":[2.0966110229,41.3587150574],"type":"Point"}
}