{
  "type": "Feature",
  "properties": {
    "addr:full":"Pl Merce, 4 Elche Alicante 03202",
    "addr:housenumber":"4",
    "addr:postcode":"03202",
    "addr:street":"Pl Merce",
    "iso:country":"ES",
    "sg:address":"Pl Merce, 4",
    "sg:city":"Elche",
    "sg:orig_category":"Ropa Para Ni\u00d1os (al Por Menor)",
    "sg:phone":"+34 966 61 08 31",
    "sg:postcode":"03202",
    "sg:province":"Alicante",
    "wof:name":"Lemur Caribu S.a.",
    "wof:placetype":"venue"
},
  "geometry": {"coordinates":[-0.6964139938,38.2671775818],"type":"Point"}
}