{
  "type": "Feature",
  "properties": {
    "addr:full":"Plaz Canovas Del Castillo, 8 Valdemoro Madrid 28340",
    "addr:housenumber":"8",
    "addr:postcode":"28340",
    "addr:street":"Plaz Canovas Del Castillo",
    "iso:country":"ES",
    "sg:address":"Plaz Canovas Del Castillo, 8",
    "sg:city":"Valdemoro",
    "sg:orig_category":"Ropa Para Ni\u00d1os (al Por Menor)",
    "sg:phone":"+34 918 08 25 13",
    "sg:postcode":"28340",
    "sg:province":"Madrid",
    "wof:name":"Farfan Diaz Maria Inmaculada",
    "wof:placetype":"venue"
},
  "geometry": {"coordinates":[-3.6796751022,40.190738678],"type":"Point"}
}