{
  "type": "Feature",
  "properties": {
    "iso:country":"ES",
    "sg:address":"Calle de Hermanos Machado, 17",
    "sg:city":"Madrid",
    "sg:orig_category":"Molduras, Junquillos, Listones Y Molduras Perforadas",
    "sg:phone":"+34 914 07 10 98",
    "sg:postcode":"28017",
    "sg:province":"Madrid",
    "wof:name":"Piza Segura Yadira Margarita",
    "wof:placetype":"venue"
},
  "geometry": {"coordinates":[-3.6491076946,40.4315681458],"type":"Point"}
}