{
  "type": "Feature",
  "properties": {
    "addr:full":"Calle de Pintor Velazquez (del), 38 Alcobendas Madrid 28100",
    "addr:postcode":"28100",
    "addr:street":"Calle De Pintor Velazquez Del;Alcobendas",
    "iso:country":"ES",
    "sg:address":"Calle de Pintor Velazquez (del), 38",
    "sg:city":"Alcobendas",
    "sg:orig_category":"Centros De Educaci\u00d3n Especial",
    "sg:phone":"+34 916 61 75 08",
    "sg:postcode":"28100",
    "sg:province":"Madrid",
    "wof:name":"Comunidad Autonoma De Madrid-centros De Educacion",
    "wof:placetype":"venue"
},
  "geometry": {"coordinates":[-3.6432890892,40.5407485962],"type":"Point"}
}