{
  "type": "Feature",
  "properties": {
    "iso:country":"ES",
    "sg:address":"Calle de Ramiro Ii, 10",
    "sg:city":"Madrid",
    "sg:orig_category":"Electricidad: Instaladores",
    "sg:phone":"+34 915 53 13 92",
    "sg:postcode":"28003",
    "sg:province":"Madrid",
    "wof:name":"Instalaciones Electricas Mas S. A.",
    "wof:placetype":"venue"
},
  "geometry": {"coordinates":[-3.7053010464,40.4434623718],"type":"Point"}
}