{
  "type": "Feature",
  "properties": {
    "iso:country":"ES",
    "sg:address":"Plaz Victoria, 11",
    "sg:city":"Malaga",
    "sg:orig_category":"M\u00c9dicos: Psiquiatr\u00cda",
    "sg:phone":"+34 952 65 24 87",
    "sg:postcode":"29012",
    "sg:province":"M\u00e1laga",
    "wof:name":"Galan Pajuelo Alfonso",
    "wof:placetype":"venue"
},
  "geometry": {"coordinates":[-4.4117789268,36.7286949158],"type":"Point"}
}