{
  "type": "Feature",
  "properties": {
    "iso:country":"ES",
    "sg:address":"Plaz Oretania (de La), 3",
    "sg:city":"Viso Marques",
    "sg:orig_category":"Sanatorios M\u00c9dico",
    "sg:phone":"+34 926 33 71 72",
    "sg:postcode":"13770",
    "sg:province":"Ciudad Real",
    "wof:name":"Servicio De Salud De Castilla La Mancha",
    "wof:placetype":"venue"
},
  "geometry": {"coordinates":[-3.5667779446,38.5230789185],"type":"Point"}
}