{
  "type": "Feature",
  "properties": {
    "addr:full":"Calle de Calzada, 7 Jimena Frontera C\u00e1diz 11330",
    "addr:housenumber":"7",
    "addr:postcode":"11330",
    "addr:street":"Calle De Calzada",
    "iso:country":"ES",
    "sg:address":"Calle de Calzada, 7",
    "sg:city":"Jimena Frontera",
    "sg:orig_category":"Ense\u00d1anza, Formaci\u00d3n Profesional: Aprendizaje",
    "sg:phone":"+34 956 64 11 70",
    "sg:postcode":"11330",
    "sg:province":"C\u00e1diz",
    "wof:name":"Ayuntamiento De Jimena De La Frontera",
    "wof:placetype":"venue"
},
  "geometry": {"coordinates":[-5.4542298317,36.4374847412],"type":"Point"}
}