{
  "type": "Feature",
  "properties": {
    "addr:full":"Calle de Antonio Salvador, 73 Madrid Madrid 28026",
    "addr:housenumber":"73",
    "addr:postcode":"madrid;28026",
    "addr:street":"Calle De Antonio Salvador",
    "iso:country":"ES",
    "sg:address":"Calle de Antonio Salvador, 73",
    "sg:city":"Madrid",
    "sg:orig_category":"Quincaller\u00cda (al Por Menor)",
    "sg:phone":"+34 915 00 25 53",
    "sg:postcode":"28026",
    "sg:province":"Madrid",
    "wof:name":"Cerezo Toro Julio",
    "wof:placetype":"venue"
},
  "geometry": {"coordinates":[-3.7041037083,40.3848648071],"type":"Point"}
}