{
  "type": "Feature",
  "properties": {
    "iso:country":"ES",
    "sg:address":"Calle de Raimundo Rodriguez, 3",
    "sg:city":"Caravaca Cruz",
    "sg:orig_category":"Procuradores",
    "sg:phone":"+34 968 70 77 62",
    "sg:postcode":"30400",
    "sg:province":"Murcia",
    "sg:website":"www.procuradoresnavarro.iespana.es",
    "wof:name":"Navarro Lopez Juan Esmeraldo",
    "wof:placetype":"venue"
},
  "geometry": {"coordinates":[-1.8590129614,38.1060562134],"type":"Point"}
}