{
  "type": "Feature",
  "properties": {
    "addr:full":"Avda Aragon, 17 Alca\u00f1iz Teruel 44600",
    "addr:housenumber":"17",
    "addr:postcode":"44600",
    "addr:street":"Avda Aragon",
    "iso:country":"ES",
    "sg:address":"Avda Aragon, 17",
    "sg:city":"Alca\u00f1iz",
    "sg:orig_category":"Quincaller\u00cda (al Por Menor)",
    "sg:phone":"+34 978 83 19 21",
    "sg:postcode":"44600",
    "sg:province":"Teruel",
    "wof:name":"Febrise S.l.",
    "wof:placetype":"venue"
},
  "geometry": {"coordinates":[-0.1302350014,41.0496101379],"type":"Point"}
}