{
  "type": "Feature",
  "properties": {
    "iso:country":"ES",
    "sg:address":"Calle de Pintor Manuel Siguenza, 3",
    "sg:city":"Pinedo",
    "sg:orig_category":"Mec\u00c1nico Del Autom\u00d3vil",
    "sg:phone":"+34 963 24 81 45",
    "sg:postcode":"46012",
    "sg:province":"Valencia",
    "wof:name":"Vivo Girba Jose",
    "wof:placetype":"venue"
},
  "geometry": {"coordinates":[-0.3391740024,39.421836853],"type":"Point"}
}