{
  "type": "Feature",
  "properties": {
    "addr:full":"Calle de Mesonero Mayor, 4 Coca Segovia 40480",
    "addr:housenumber":"4",
    "addr:postcode":"40480",
    "addr:street":"Calle De Mesonero Mayor",
    "iso:country":"ES",
    "sg:address":"Calle de Mesonero Mayor, 4",
    "sg:city":"Coca",
    "sg:orig_category":"Ense\u00d1anza: Comercio, Gesti\u00d3n, Inform\u00c1tica",
    "sg:phone":"+34 921 58 61 62",
    "sg:postcode":"40480",
    "sg:province":"Segovia",
    "wof:name":"Lape\u00f1a Catalina Jose Manuel",
    "wof:placetype":"venue"
},
  "geometry": {"coordinates":[-4.5216941833,41.2152137756],"type":"Point"}
}