{
  "type": "Feature",
  "properties": {
    "iso:country":"ES",
    "sg:address":"C/ Verge De Montserrat, 3",
    "sg:city":"Ripollet",
    "sg:orig_category":"Inmobiliaria (agencias)",
    "sg:phone":"+34 935 86 54 01",
    "sg:postcode":"08291",
    "sg:province":"Barcelona",
    "wof:name":"Fincas Esparco S.l",
    "wof:placetype":"venue"
},
  "geometry": {"coordinates":[2.1509120464,41.4930152893],"type":"Point"}
}