{
  "type": "Feature",
  "properties": {
    "addr:full":"Calle de Martinez De La Riva, 6 Madrid Madrid 28053",
    "addr:housenumber":"6",
    "addr:postcode":"28053",
    "addr:street":"Calle De Martinez De La Riva",
    "iso:country":"ES",
    "sg:address":"Calle de Martinez De La Riva, 6",
    "sg:city":"Madrid",
    "sg:orig_category":"Frutas, Legumbres Frescas Y Tempranas (al Por Menor)",
    "sg:phone":"+34 914 77 20 16",
    "sg:postcode":"28053",
    "sg:province":"Madrid",
    "wof:name":"Fruta El Capricho S.l.",
    "wof:placetype":"venue"
},
  "geometry": {"coordinates":[-3.6675620079,40.3950462341],"type":"Point"}
}