{
  "type": "Feature",
  "properties": {
    "iso:country":"ES",
    "sg:address":"Calle de Santa Engracia, 29",
    "sg:city":"Madrid",
    "sg:orig_category":"Frutas, Legumbres Frescas Y Tempranas (al Por Menor)",
    "sg:phone":"+34 914 46 45 37",
    "sg:postcode":"28010",
    "sg:province":"Madrid",
    "wof:name":"Alvarez Sanchez Juan Jose",
    "wof:placetype":"venue"
},
  "geometry": {"coordinates":[-3.6971189976,40.4311523438],"type":"Point"}
}