{
  "type": "Feature",
  "properties": {
    "addr:full":"B. La Iglesia-berron, 9 La Carrera Asturias 33186",
    "addr:housenumber":"9",
    "addr:postcode":"33186",
    "addr:street":"B.;Iglesia-Berron",
    "iso:country":"ES",
    "sg:address":"B. La Iglesia-berron, 9",
    "sg:city":"La Carrera",
    "sg:orig_category":"Iglesia Cat\u00d3lica",
    "sg:phone":"+34 985 74 09 61",
    "sg:postcode":"33186",
    "sg:province":"Asturias",
    "wof:name":"Diocesis De Oviedo",
    "wof:placetype":"venue"
},
  "geometry": {"coordinates":[-5.7012858391,43.3833732605],"type":"Point"}
}