{
  "type": "Feature",
  "properties": {
    "addr:full":"Avda Manzanares, 160 Madrid Madrid 28019",
    "addr:housenumber":"160",
    "addr:postcode":"28019",
    "addr:street":"Avda Manzanares",
    "iso:country":"ES",
    "sg:address":"Avda Manzanares, 160",
    "sg:city":"Madrid",
    "sg:orig_category":"Ense\u00d1anza: Comercio, Gesti\u00d3n, Inform\u00c1tica",
    "sg:phone":"+34 914 69 74 41",
    "sg:postcode":"28019",
    "sg:province":"Madrid",
    "sg:website":"www.areteia.com",
    "wof:name":"Areteia Consultores S.l.",
    "wof:placetype":"venue"
},
  "geometry": {"coordinates":[-3.7089853287,40.3957824707],"type":"Point"}
}