{
  "type": "Feature",
  "properties": {
    "addr:full":"Avda Alberto Alcocer, 46 Madrid Madrid 28016",
    "addr:housenumber":"46",
    "addr:postcode":"madrid;28016",
    "addr:street":"Alberto Alcocer",
    "iso:country":"ES",
    "sg:address":"Avda Alberto Alcocer, 46",
    "sg:city":"Madrid",
    "sg:orig_category":"Ropa Para Ni\u00d1os (al Por Menor)",
    "sg:phone":"+34 914 57 91 72",
    "sg:postcode":"28016",
    "sg:province":"Madrid",
    "wof:name":"Lopez Bartolozzi Maria Luisa",
    "wof:placetype":"venue"
},
  "geometry": {"coordinates":[-3.6775848866,40.4584197998],"type":"Point"}
}