{
  "type": "Feature",
  "properties": {
    "iso:country":"ES",
    "sg:address":"Av Catalunya, 19",
    "sg:city":"Fuliola",
    "sg:orig_category":"Empresas De Hormig\u00d3n, Hormig\u00d3n Armado Y Pretensado",
    "sg:phone":"+34 973 57 00 62",
    "sg:postcode":"25332",
    "sg:province":"Lleida",
    "wof:name":"Colomines Vicens Antonio",
    "wof:placetype":"venue"
},
  "geometry": {"coordinates":[1.0148179531,41.71616745],"type":"Point"}
}