{
  "type": "Feature",
  "properties": {
    "iso:country":"ES",
    "sg:address":"Avda Andalucia, 38",
    "sg:city":"Lanjaron",
    "sg:orig_category":"Carnicer\u00cdas, Carnicer\u00cdas",
    "sg:phone":"+34 958 77 00 27",
    "sg:postcode":"18420",
    "sg:province":"Granada",
    "wof:name":"Rubio Alonso Gustavo Adolfo",
    "wof:placetype":"venue"
},
  "geometry": {"coordinates":[-3.485033989,36.9184837341],"type":"Point"}
}