{
  "type": "Feature",
  "properties": {
    "addr:full":"Calle de Guillem De Castro, 118 Valencia Valencia 46...",
    "addr:housenumber":"118",
    "addr:street":"Calle De Guillem De Castro;Valencia",
    "iso:country":"ES",
    "sg:address":"Calle de Guillem De Castro, 118",
    "sg:city":"Valencia",
    "sg:orig_category":"Comit\u00c9s De Organizaci\u00d3n De Exposiciones, Ferias, Salones",
    "sg:phone":"+34 963 86 30 00",
    "sg:postcode":"46...",
    "sg:province":"Valencia",
    "sg:website":"www.ivam.es",
    "wof:name":"Generalitat Valenciana",
    "wof:placetype":"venue"
},
  "geometry": {"coordinates":[-0.3831704855,39.4798469543],"type":"Point"}
}