{
  "type": "Feature",
  "properties": {
    "addr:full":"Calle de Cristo, 40 Velez-malaga M\u00e1laga 29700",
    "addr:housenumber":"40",
    "addr:postcode":"29700",
    "addr:street":"Calle De Cristo",
    "iso:country":"ES",
    "sg:address":"Calle de Cristo, 40",
    "sg:city":"Velez-malaga",
    "sg:orig_category":"Inmobiliaria (agencias)",
    "sg:phone":"+34 952 54 93 34",
    "sg:postcode":"29700",
    "sg:province":"M\u00e1laga",
    "wof:name":"Vara Bernal Jesus",
    "wof:placetype":"venue"
},
  "geometry": {"coordinates":[-4.1026592255,36.7791824341],"type":"Point"}
}