{
  "type": "Feature",
  "properties": {
    "addr:full":"Calle de Lepanto, 2 Castilleja Cuesta Sevilla 41950",
    "addr:housenumber":"2",
    "addr:postcode":"41950",
    "addr:street":"Calle De Lepanto;Cuesta Sevilla",
    "iso:country":"ES",
    "sg:address":"Calle de Lepanto, 2",
    "sg:city":"Castilleja Cuesta",
    "sg:orig_category":"Alimentaci\u00d3n General (al Por Menor)",
    "sg:phone":"+34 954 16 01 55",
    "sg:postcode":"41950",
    "sg:province":"Sevilla",
    "wof:name":"Garcia Iglesias Angel",
    "wof:placetype":"venue"
},
  "geometry": {"coordinates":[-6.0532741547,37.3874359131],"type":"Point"}
}