{
  "type": "Feature",
  "properties": {
    "addr:full":"Pase Chil, 9 Palmas De Gran Canaria Las Palmas 35014",
    "addr:postcode":"35014",
    "iso:country":"ES",
    "sg:address":"Pase Chil, 9",
    "sg:city":"Palmas De Gran Canaria",
    "sg:orig_category":"Abogados",
    "sg:phone":"+34 928 38 11 34",
    "sg:postcode":"35014",
    "sg:province":"Las Palmas",
    "wof:name":"Benitez-inglott Diaz Luis Fernando",
    "wof:placetype":"venue"
},
  "geometry": {"coordinates":[-15.4340200424,28.1030693054],"type":"Point"}
}