{
  "type": "Feature",
  "properties": {
    "addr:full":"Illes Balears, 156 Palma Islas Baleares 07014",
    "addr:postcode":"156;07014",
    "iso:country":"ES",
    "sg:address":"Illes Balears, 156",
    "sg:city":"Palma",
    "sg:orig_category":"Psic\u00d3logos",
    "sg:phone":"+34 971 73 63 63",
    "sg:postcode":"07014",
    "sg:province":"Islas Baleares",
    "wof:name":"Di Carlo Surraco Isabella Maria",
    "wof:placetype":"venue"
},
  "geometry": {"coordinates":[2.6144959927,39.5714378357],"type":"Point"}
}