{
  "type": "Feature",
  "properties": {
    "iso:country":"ES",
    "sg:address":"Calle de Federico Gomez Clemente, 27",
    "sg:city":"Alzira",
    "sg:orig_category":"Agencias Y Agentes Comerciales, Representantes",
    "sg:phone":"+34 962 41 82 30",
    "sg:postcode":"46600",
    "sg:province":"Valencia",
    "wof:name":"Pallas Gil Manuel",
    "wof:placetype":"venue"
},
  "geometry": {"coordinates":[-0.4315510094,39.1489143372],"type":"Point"}
}