{
  "type": "Feature",
  "properties": {
    "iso:country":"ES",
    "sg:address":"Calle de Arroyo Pradillo, S/n",
    "sg:city":"San Juan De La Nava",
    "sg:orig_category":"Transporte En General",
    "sg:phone":"+34 920 29 70 64",
    "sg:postcode":"05111",
    "sg:province":"\u00c1vila",
    "wof:name":"Varas Yuste Santos",
    "wof:placetype":"venue"
},
  "geometry": {"coordinates":[-4.683631897,40.478302002],"type":"Point"}
}