{
  "type": "Feature",
  "properties": {
    "iso:country":"ES",
    "sg:address":"Av. Generalisimo, S/n",
    "sg:city":"Alceda",
    "sg:orig_category":"Restaurantes",
    "sg:phone":"+34 942 59 40 29",
    "sg:postcode":"39680",
    "sg:province":"Cantabria",
    "wof:name":"Calderon Saiz Jesus Angel",
    "wof:placetype":"venue"
},
  "geometry": {"coordinates":[-3.9219191074,43.1962852478],"type":"Point"}
}