{
  "type": "Feature",
  "properties": {
    "iso:country":"ES",
    "sg:address":"Ctra Albares, Km. 0000,7",
    "sg:city":"Ventas De Albares",
    "sg:orig_category":"Estaciones De Servicio",
    "sg:phone":"+34 987 51 34 19",
    "sg:postcode":"24317",
    "sg:province":"Le\u00f3n",
    "wof:name":"Carbones De Bembibre S.l.",
    "wof:placetype":"venue"
},
  "geometry": {"coordinates":[-6.3911437988,42.6028747559],"type":"Point"}
}