{
  "type": "Feature",
  "properties": {
    "addr:full":"Ctra. Estacion, 13 Ca\u00f1averal C\u00e1ceres 10820",
    "addr:housenumber":"13",
    "addr:postcode":"10820",
    "addr:street":"Ctra. Estacion;Ca\u0301Ceres",
    "iso:country":"ES",
    "sg:address":"Ctra. Estacion, 13",
    "sg:city":"Ca\u00f1averal",
    "sg:orig_category":"Transporte En General",
    "sg:phone":"+34 927 30 06 44",
    "sg:postcode":"10820",
    "sg:province":"C\u00e1ceres",
    "wof:name":"Boticario Distribuciones Alimenticias S.l.",
    "wof:placetype":"venue"
},
  "geometry": {"coordinates":[-6.3750081062,39.7896156311],"type":"Point"}
}