{
  "type": "Feature",
  "properties": {
    "addr:full":"Calle de Consolacion, 7 Torrelavega Cantabria 39300",
    "addr:housenumber":"7",
    "addr:postcode":"39300",
    "addr:street":"Calle De Consolacion",
    "iso:country":"ES",
    "sg:address":"Calle de Consolacion, 7",
    "sg:city":"Torrelavega",
    "sg:orig_category":"Edici\u00d3n De Diarios, Revistas, Boletines",
    "sg:phone":"+34 942 80 49 25",
    "sg:postcode":"39300",
    "sg:province":"Cantabria",
    "wof:name":"Gonzalez Gutirrez Maria Elsa",
    "wof:placetype":"venue"
},
  "geometry": {"coordinates":[-4.0482788086,43.3489761353],"type":"Point"}
}