{
  "type": "Feature",
  "properties": {
    "iso:country":"ES",
    "sg:address":"Rua Pablo Iglesias, 26",
    "sg:city":"Grove",
    "sg:orig_category":"Albergues",
    "sg:phone":"+34 986 73 30 07",
    "sg:postcode":"36980",
    "sg:province":"Pontevedra",
    "wof:name":"Martinez Gali\u00f1anes Jacobo Manuel",
    "wof:placetype":"venue"
},
  "geometry": {"coordinates":[-8.8651094437,42.4959487915],"type":"Point"}
}