{
  "type": "Feature",
  "properties": {
    "iso:country":"ES",
    "sg:address":"C/ Ausias March, 1",
    "sg:city":"Moncofa",
    "sg:orig_category":"Organismos De Investigaciones Cient\u00cdficas Y T\u00c9cnicas",
    "sg:phone":"+34 964 57 93 97",
    "sg:postcode":"12593",
    "sg:province":"Castell\u00f3n",
    "wof:name":"Biosensores S.l.",
    "wof:placetype":"venue"
},
  "geometry": {"coordinates":[-0.1475539953,39.8062973022],"type":"Point"}
}