{
  "type": "Feature",
  "properties": {
    "iso:country":"ES",
    "sg:address":"Calle de Marbella, 14",
    "sg:city":"Fuengirola",
    "sg:orig_category":"M\u00c9dicos: Medicina General Orientada A La Homeopat\u00cda",
    "sg:phone":"+34 952 46 60 79",
    "sg:postcode":"29640",
    "sg:province":"M\u00e1laga",
    "wof:name":"Sanchez Onieva Maria Eufemia",
    "wof:placetype":"venue"
},
  "geometry": {"coordinates":[-4.6244168282,36.5379142761],"type":"Point"}
}