{
  "type": "Feature",
  "properties": {
    "iso:country":"ES",
    "sg:address":"Calle de Mayor, 18",
    "sg:city":"Caravaca Cruz",
    "sg:orig_category":"Prendas Y Chalecos De Punto (al Por Menor)",
    "sg:phone":"+34 968 70 83 75",
    "sg:postcode":"30400",
    "sg:province":"Murcia",
    "wof:name":"Martinez Segarra Maria Del Carmen",
    "wof:placetype":"venue"
},
  "geometry": {"coordinates":[-1.8611210585,38.1072273254],"type":"Point"}
}