{
  "type": "Feature",
  "properties": {
    "iso:country":"ES",
    "sg:address":"Calle de Fernando El Catolico, 59",
    "sg:city":"Madrid",
    "sg:orig_category":"Papeler\u00cdas, Librer\u00cdas",
    "sg:phone":"+34 915 44 23 35",
    "sg:postcode":"28015",
    "sg:province":"Madrid",
    "wof:name":"Vega Martinez Jose Manuel",
    "wof:placetype":"venue"
},
  "geometry": {"coordinates":[-3.714687109,40.4342308044],"type":"Point"}
}