{
  "type": "Feature",
  "properties": {
    "addr:full":"Ctra Villafranca, S/n Fuente Maestre Badajoz 06360",
    "addr:housenumber":"s",
    "addr:postcode":"06360",
    "addr:street":"Ctra Villafranca;/ N Fuente Maestre",
    "iso:country":"ES",
    "sg:address":"Ctra Villafranca, S/n",
    "sg:city":"Fuente Maestre",
    "sg:orig_category":"Empresas De Carpinter\u00cda De Madera",
    "sg:phone":"+34 924 53 00 84",
    "sg:postcode":"06360",
    "sg:province":"Badajoz",
    "wof:name":"Zambrano Franco Felix",
    "wof:placetype":"venue"
},
  "geometry": {"coordinates":[-6.4096641541,38.5261955261],"type":"Point"}
}