{
  "type": "Feature",
  "properties": {
    "iso:country":"ES",
    "sg:address":"Av Gatassa, 69",
    "sg:city":"Mataro",
    "sg:orig_category":"Ropa Para Se\u00d1oras Y Caballeros (al Por Menor)",
    "sg:phone":"+34 937 57 49 01",
    "sg:postcode":"08303",
    "sg:province":"Barcelona",
    "wof:name":"Soliva Papell Maria Rosa",
    "wof:placetype":"venue"
},
  "geometry": {"coordinates":[2.4279561043,41.537563324],"type":"Point"}
}