{
  "type": "Feature",
  "properties": {
    "addr:full":"Pr. Ayuntamiento, S/n Verin Ourense 32600",
    "addr:housenumber":"/ n",
    "addr:postcode":"32600",
    "addr:street":"S",
    "iso:country":"ES",
    "sg:address":"Pr. Ayuntamiento, S/n",
    "sg:city":"Verin",
    "sg:classifiers":[
        {
            "category":"Taxi",
            "type":"Transportation"
        }
    ],
    "sg:phone":"+34 988 41 11 13",
    "sg:postcode":"32600",
    "sg:province":"Ourense",
    "wof:name":"Concello De Verin",
    "wof:placetype":"venue"
},
  "geometry": {"coordinates":[-7.435254097,41.9402198792],"type":"Point"}
}