{
  "type": "Feature",
  "properties": {
    "iso:country":"ES",
    "sg:address":"Sect Literatos, 23",
    "sg:city":"Tres Cantos",
    "sg:orig_category":"Cajas De Ahorro",
    "sg:phone":"+34 918 03 68 97",
    "sg:postcode":"28760",
    "sg:province":"Madrid",
    "wof:name":"Bilbao Bizkaia Kutxa",
    "wof:placetype":"venue"
},
  "geometry": {"coordinates":[-3.7131690979,40.6076164246],"type":"Point"}
}