{
  "type": "Feature",
  "properties": {
    "addr:full":"Carrer de Prudencia, 14 Rubi Barcelona 08191",
    "addr:housenumber":"14",
    "addr:postcode":"08191",
    "addr:street":"Carrer De Prudencia",
    "iso:country":"ES",
    "sg:address":"Carrer de Prudencia, 14",
    "sg:city":"Rubi",
    "sg:orig_category":"Ense\u00d1anza: Profesiones Art\u00cdsticas",
    "sg:phone":"+34 935 88 00 65",
    "sg:postcode":"08191",
    "sg:province":"Barcelona",
    "wof:name":"G.r.n. Fotografia Publicitaria S.c.p.",
    "wof:placetype":"venue"
},
  "geometry": {"coordinates":[2.0110399723,41.4877510071],"type":"Point"}
}