{
  "type": "Feature",
  "properties": {
    "addr:full":"Calle de Mamariga, 137 Santurtzi Vizcaya 48980",
    "addr:housenumber":"137",
    "addr:postcode":"48980",
    "addr:street":"Calle De Mamariga",
    "iso:country":"ES",
    "sg:address":"Calle de Mamariga, 137",
    "sg:city":"Santurtzi",
    "sg:orig_category":"Molduras, Junquillos, Listones Y Molduras Perforadas",
    "sg:phone":"+34 944 83 78 80",
    "sg:postcode":"48980",
    "sg:province":"Vizcaya",
    "wof:name":"Tejerina Martinez Isaias",
    "wof:placetype":"venue"
},
  "geometry": {"coordinates":[-3.0391726494,43.3316383362],"type":"Point"}
}