{
  "type": "Feature",
  "properties": {
    "iso:country":"ES",
    "sg:address":"Calle de Zaragoza, 33",
    "sg:city":"Castellon",
    "sg:orig_category":"Promotores Constructores",
    "sg:phone":"+34 964 21 82 11",
    "sg:postcode":"12001",
    "sg:province":"Castell\u00f3n",
    "wof:name":"Babiloni Gomez Vicente",
    "wof:placetype":"venue"
},
  "geometry": {"coordinates":[-0.0420988984,39.987651825],"type":"Point"}
}