{
  "type": "Feature",
  "properties": {
    "iso:country":"ES",
    "sg:address":"Calle de Diez Calixto, 11",
    "sg:city":"Bilbao",
    "sg:orig_category":"Agencias Y Asesores De Publicidad",
    "sg:phone":"+34 944 70 12 84",
    "sg:postcode":"48012",
    "sg:province":"Vizcaya",
    "wof:name":"Bilinkar S.l.",
    "wof:placetype":"venue"
},
  "geometry": {"coordinates":[-2.941395998,43.2564201355],"type":"Point"}
}