{
  "type": "Feature",
  "properties": {
    "iso:country":"ES",
    "sg:address":"Circunvalacion, 28",
    "sg:city":"Granada",
    "sg:orig_category":"Ropa Para Se\u00d1oras Y Caballeros (al Por Menor)",
    "sg:phone":"+34 958 13 66 96",
    "sg:postcode":"18007",
    "sg:province":"Granada",
    "sg:website":"www.aguaesport.net",
    "wof:name":"Agua Ropa Sport S.l.",
    "wof:placetype":"venue"
},
  "geometry": {"coordinates":[-3.5999937057,37.1594581604],"type":"Point"}
}