{
  "type": "Feature",
  "properties": {
    "iso:country":"ES",
    "sg:address":"Carrer de Duquessa D'orleans, 29",
    "sg:city":"Barcelona",
    "sg:orig_category":"Deportes Diversos",
    "sg:phone":"+34 932 80 27 38",
    "sg:postcode":"08034",
    "sg:province":"Barcelona",
    "wof:name":"Federacion Provincial Tenis De Mesa",
    "wof:placetype":"venue"
},
  "geometry": {"coordinates":[2.1192522049,41.3993453979],"type":"Point"}
}