{
  "type": "Feature",
  "properties": {
    "iso:country":"ES",
    "sg:address":"Calle de Maestro Serrano, 40",
    "sg:city":"Paiporta",
    "sg:orig_category":"Electrodom\u00c9sticos (al Por Menor)",
    "sg:phone":"+34 963 97 01 67",
    "sg:postcode":"46200",
    "sg:province":"Valencia",
    "wof:name":"Coinsat Mt S.l.",
    "wof:placetype":"venue"
},
  "geometry": {"coordinates":[-0.4168010056,39.4250869751],"type":"Point"}
}