{
  "type": "Feature",
  "properties": {
    "iso:country":"ES",
    "sg:address":"Calle de Pilarica, 49",
    "sg:city":"Madrid",
    "sg:orig_category":"Equipo De Refrigeraci\u00d3n Industrial",
    "sg:phone":"+34 914 75 12 34",
    "sg:postcode":"28026",
    "sg:province":"Madrid",
    "wof:name":"Adrover Conde Alfonso",
    "wof:placetype":"venue"
},
  "geometry": {"coordinates":[-3.7031495571,40.3849220276],"type":"Point"}
}