{
  "type": "Feature",
  "properties": {
    "addr:full":"Ctra. Alicante, 39 Monteagudo Murcia 30160",
    "addr:housenumber":"39",
    "addr:postcode":"30160",
    "addr:street":"Ctra. Alicante",
    "iso:country":"ES",
    "sg:address":"Ctra. Alicante, 39",
    "sg:city":"Monteagudo",
    "sg:orig_category":"Mec\u00c1nico Del Autom\u00d3vil",
    "sg:phone":"+34 968 85 03 33",
    "sg:postcode":"30160",
    "sg:province":"Murcia",
    "wof:name":"Talleres M.iniesta S.l.",
    "wof:placetype":"venue"
},
  "geometry": {"coordinates":[-1.0982600451,38.0171508789],"type":"Point"}
}