{
  "type": "Feature",
  "properties": {
    "addr:full":"P Baroja, 8 Aljaraque Huelva 21110",
    "addr:housenumber":"8",
    "addr:postcode":"21110",
    "addr:street":"Baroja",
    "iso:country":"ES",
    "sg:address":"P Baroja, 8",
    "sg:city":"Aljaraque",
    "sg:orig_category":"Formaci\u00d3n Continuada (variada)",
    "sg:phone":"+34 959 31 90 34",
    "sg:postcode":"21110",
    "sg:province":"Huelva",
    "wof:name":"Cabrita Marquez Luis",
    "wof:placetype":"venue"
},
  "geometry": {"coordinates":[-7.0241990089,37.2709159851],"type":"Point"}
}