{
  "type": "Feature",
  "properties": {
    "addr:full":"Col Weil, S/n Ceuta Ceuta 51002",
    "addr:housenumber":"s",
    "addr:postcode":"51002",
    "addr:street":"Col;/ N",
    "iso:country":"ES",
    "sg:address":"Col Weil, S/n",
    "sg:city":"Ceuta",
    "sg:orig_category":"Cajas De Ahorro",
    "sg:phone":"+34 956 52 25 12",
    "sg:postcode":"51002",
    "sg:province":"Ceuta",
    "wof:name":"Unicaja",
    "wof:placetype":"venue"
},
  "geometry": {"coordinates":[-5.3299298286,35.8878097534],"type":"Point"}
}