{
  "type": "Feature",
  "properties": {
    "iso:country":"ES",
    "sg:address":"Calle de Luz Casanova, S/n",
    "sg:city":"Granada",
    "sg:orig_category":"Periodistas Profesionales",
    "sg:phone":"+34 958 15 28 07",
    "sg:postcode":"18011",
    "sg:province":"Granada",
    "wof:name":"Majdoubi  El Houssine",
    "wof:placetype":"venue"
},
  "geometry": {"coordinates":[-3.602189064,37.2011909485],"type":"Point"}
}