{
  "type": "Feature",
  "properties": {
    "iso:country":"ES",
    "sg:address":"Carrer de Massenet, S/n",
    "sg:city":"Rubi",
    "sg:orig_category":"Agencias Y Asesores De Publicidad",
    "sg:phone":"+34 935 86 04 35",
    "sg:postcode":"08191",
    "sg:province":"Barcelona",
    "wof:name":"Rodriguez Calderon Estela",
    "wof:placetype":"venue"
},
  "geometry": {"coordinates":[2.0227200985,41.4710540771],"type":"Point"}
}