{
  "type": "Feature",
  "properties": {
    "addr:full":"Calle de Gerona, 13 Villafranca De Los Barros Badajoz 06220",
    "addr:housenumber":"13",
    "addr:postcode":"06220",
    "addr:street":"Calle De Gerona",
    "iso:country":"ES",
    "sg:address":"Calle de Gerona, 13",
    "sg:city":"Villafranca De Los Barros",
    "sg:orig_category":"Centros Comerciales Y Grandes Tiendas",
    "sg:phone":"+34 924 52 62 08",
    "sg:postcode":"06220",
    "sg:province":"Badajoz",
    "wof:name":"Verjano Garcia Maxima",
    "wof:placetype":"venue"
},
  "geometry": {"coordinates":[-6.3382439613,38.5608291626],"type":"Point"}
}