{
  "type": "Feature",
  "properties": {
    "iso:country":"ES",
    "sg:address":"Calle de Mendez Nu\u00d1ez, 4",
    "sg:city":"Guarda",
    "sg:orig_category":"Carnicer\u00cdas, Carnicer\u00cdas",
    "sg:phone":"+34 986 61 09 13",
    "sg:postcode":"36780",
    "sg:province":"Pontevedra",
    "wof:name":"Alonso Alonso Manuel",
    "wof:placetype":"venue"
},
  "geometry": {"coordinates":[-8.8743715286,41.9016304016],"type":"Point"}
}