{
  "type": "Feature",
  "properties": {
    "iso:country":"ES",
    "sg:address":"Calle de San Roque, 28",
    "sg:city":"Palmar  O Lugar De Don Juan",
    "sg:orig_category":"Librer\u00cdas",
    "sg:phone":"+34 968 88 31 26",
    "sg:postcode":"30120",
    "sg:province":"Murcia",
    "wof:name":"Libreria 4 Esquinas Antonia Alburquerque Y Rosa Faus S.c.",
    "wof:placetype":"venue"
},
  "geometry": {"coordinates":[-1.1298867464,37.9834747314],"type":"Point"}
}