{
  "type": "Feature",
  "properties": {
    "iso:country":"ES",
    "sg:address":"Calle de Doctor Alfonso Spinola, 3",
    "sg:city":"Arrecife",
    "sg:orig_category":"Alimentaci\u00d3n General (al Por Menor)",
    "sg:phone":"+34 928 81 14 05",
    "sg:postcode":"35500",
    "sg:province":"Las Palmas",
    "wof:name":"Martin Martin Martin",
    "wof:placetype":"venue"
},
  "geometry": {"coordinates":[-13.544500351,28.9658145905],"type":"Point"}
}