{
  "type": "Feature",
  "properties": {
    "iso:country":"ES",
    "sg:address":"Carr Arnus, S/n",
    "sg:city":"Badalona",
    "sg:orig_category":"Poller\u00cda Y Caza (al Por Menor)",
    "sg:phone":"+34 933 84 00 84",
    "sg:postcode":"08911",
    "sg:province":"Barcelona",
    "wof:name":"Rodriguez Celdran Isabel",
    "wof:placetype":"venue"
},
  "geometry": {"coordinates":[2.2464900017,41.4490394592],"type":"Point"}
}