{
  "type": "Feature",
  "properties": {
    "addr:full":"Plaz Coronacion De La, 20 Moguer Huelva 21800",
    "addr:postcode":"21800",
    "addr:street":"Plaz",
    "iso:country":"ES",
    "sg:address":"Plaz Coronacion De La, 20",
    "sg:city":"Moguer",
    "sg:orig_category":"Asesor\u00cda Fiscal Y Jur\u00cddica",
    "sg:phone":"+34 959 37 31 50",
    "sg:postcode":"21800",
    "sg:province":"Huelva",
    "wof:name":"Morga Asesoramiento S.l.",
    "wof:placetype":"venue"
},
  "geometry": {"coordinates":[-6.8342490196,37.2783584595],"type":"Point"}
}