{
  "type": "Feature",
  "properties": {
    "iso:country":"ES",
    "sg:address":"Calle de San Emilio, 24",
    "sg:city":"Madrid",
    "sg:orig_category":"Art\u00cdculos De Decoraci\u00d3n (fabricaci\u00d3n Y Al Por Mayor)",
    "sg:phone":"+34 913 55 11 47",
    "sg:postcode":"28017",
    "sg:province":"Madrid",
    "wof:name":"Alhambra Perez Jose",
    "wof:placetype":"venue"
},
  "geometry": {"coordinates":[-3.6591131687,40.4275054932],"type":"Point"}
}