{
  "type": "Feature",
  "properties": {
    "addr:full":"Calle de Alcorcon, 17 Parla Madrid 28980",
    "addr:housenumber":"17",
    "addr:postcode":"28980",
    "addr:street":"Calle De Alcorcon",
    "iso:country":"ES",
    "sg:address":"Calle de Alcorcon, 17",
    "sg:city":"Parla",
    "sg:orig_category":"Sociedades, Compa\u00d1\u00cdas Aseguradoras",
    "sg:phone":"+34 916 05 23 52",
    "sg:postcode":"28980",
    "sg:province":"Madrid",
    "wof:name":"Mapfre Servicios De Informatica",
    "wof:placetype":"venue"
},
  "geometry": {"coordinates":[-3.7746722698,40.2418212891],"type":"Point"}
}