{
  "type": "Feature",
  "properties": {
    "addr:full":"Ptda Cachapet, 3 Crevillente Alicante 03330",
    "addr:housenumber":"3",
    "addr:postcode":"03330",
    "addr:street":"Ptda Cachapet",
    "iso:country":"ES",
    "sg:address":"Ptda Cachapet, 3",
    "sg:city":"Crevillente",
    "sg:orig_category":"Construcciones Met\u00c1licas",
    "sg:phone":"+34 965 40 41 57",
    "sg:postcode":"03330",
    "sg:province":"Alicante",
    "wof:name":"Metalia Estructuras Metalicas S.l.u.",
    "wof:placetype":"venue"
},
  "geometry": {"coordinates":[-0.8163840175,38.2342567444],"type":"Point"}
}