{
  "type": "Feature",
  "properties": {
    "addr:full":"Avda Paris, 26 Caceres C\u00e1ceres 10005",
    "addr:housenumber":"26",
    "addr:postcode":"10005",
    "addr:street":"Avda Paris;Ca\u0301Ceres",
    "iso:country":"ES",
    "sg:address":"Avda Paris, 26",
    "sg:city":"Caceres",
    "sg:orig_category":"Mutuas De Seguros",
    "sg:phone":"+34 927 23 71 30",
    "sg:postcode":"10005",
    "sg:province":"C\u00e1ceres",
    "wof:name":"Union Mutuas Matepss",
    "wof:placetype":"venue"
},
  "geometry": {"coordinates":[-6.3873591423,39.4689331055],"type":"Point"}
}