{
  "type": "Feature",
  "properties": {
    "iso:country":"ES",
    "sg:address":"F. Moncloa, S/n",
    "sg:city":"Mascaraque",
    "sg:orig_category":"Agricultores, Agricultores",
    "sg:phone":"+34 925 59 41 36",
    "sg:postcode":"45430",
    "sg:province":"Toledo",
    "sg:website":"www.oleoquiros.com",
    "wof:name":"Garcia Lujan Margarita",
    "wof:placetype":"venue"
},
  "geometry": {"coordinates":[-3.8139560223,39.7182388306],"type":"Point"}
}