{
  "type": "Feature",
  "properties": {
    "iso:country":"ES",
    "sg:address":"Ctra Montoro-puente Genil, Km. 0079,0",
    "sg:city":"Aguilar De La Frontera",
    "sg:orig_category":"Frutas Y Legumbres Frescas (al Por Mayor)",
    "sg:phone":"+34 957 66 09 25",
    "sg:postcode":"14920",
    "sg:province":"C\u00f3rdoba",
    "wof:name":"Cooperativa San Roque",
    "wof:placetype":"venue"
},
  "geometry": {"coordinates":[-4.6576538086,37.5145149231],"type":"Point"}
}