{
  "type": "Feature",
  "properties": {
    "iso:country":"ES",
    "sg:address":"Carrer de Doctor Fleming, 40",
    "sg:city":"Campello",
    "sg:orig_category":"Peluqueros: De Se\u00d1oras",
    "sg:phone":"+34 965 63 25 29",
    "sg:postcode":"03560",
    "sg:province":"Alicante",
    "wof:name":"Checa Mateo Dolores",
    "wof:placetype":"venue"
},
  "geometry": {"coordinates":[-0.3983429968,38.4279747009],"type":"Point"}
}