{
  "type": "Feature",
  "properties": {
    "iso:country":"ES",
    "sg:address":"Avda Askatasun Etorbidea, 22",
    "sg:city":"Durango",
    "sg:orig_category":"Electrodom\u00c9sticos (al Por Menor)",
    "sg:phone":"+34 946 20 36 23",
    "sg:postcode":"48200",
    "sg:province":"Vizcaya",
    "wof:name":"Gutierrez Cossio Elena",
    "wof:placetype":"venue"
},
  "geometry": {"coordinates":[-2.6385009289,43.1694641113],"type":"Point"}
}