{
  "type": "Feature",
  "properties": {
    "iso:country":"ES",
    "sg:address":"Rbla Pau, 109",
    "sg:city":"Vilanova I La Geltru",
    "sg:orig_category":"Promotores Constructores",
    "sg:phone":"+34 938 10 65 20",
    "sg:postcode":"08800",
    "sg:province":"Barcelona",
    "wof:name":"Promociones Adail S.l.",
    "wof:placetype":"venue"
},
  "geometry": {"coordinates":[1.7293790579,41.2163887024],"type":"Point"}
}