{
  "type": "Feature",
  "properties": {
    "iso:country":"ES",
    "sg:address":"Calle de Concepcion, 3",
    "sg:city":"Torrevieja",
    "sg:orig_category":"Sociedades, Compa\u00d1\u00cdas Aseguradoras",
    "sg:phone":"+34 965 71 48 63",
    "sg:postcode":"03180",
    "sg:province":"Alicante",
    "wof:name":"Lomerper S.l.",
    "wof:placetype":"venue"
},
  "geometry": {"coordinates":[-0.6827815771,37.9763259888],"type":"Point"}
}