{
  "type": "Feature",
  "properties": {
    "iso:country":"ES",
    "sg:address":"Calle de Dolores Marques, 8",
    "sg:city":"Valencia",
    "sg:orig_category":"Ingenier\u00cda, Centros De Estudios (diversos)",
    "sg:phone":"+34 963 69 06 26",
    "sg:postcode":"46020",
    "sg:province":"Valencia",
    "wof:name":"Miquel Bartual Jacobo",
    "wof:placetype":"venue"
},
  "geometry": {"coordinates":[-0.3631193042,39.4860687256],"type":"Point"}
}