{
  "type": "Feature",
  "properties": {
    "addr:full":"Pg Salzereda, 86 Santa Coloma De Gramenet Barcelona 08921",
    "addr:housenumber":"86",
    "addr:postcode":"08921",
    "addr:street":"Pg Salzereda",
    "iso:country":"ES",
    "sg:address":"Pg Salzereda, 86",
    "sg:city":"Santa Coloma De Gramenet",
    "sg:orig_category":"Molduras, Junquillos, Listones Y Molduras Perforadas",
    "sg:phone":"+34 933 85 23 14",
    "sg:postcode":"08921",
    "sg:province":"Barcelona",
    "wof:name":"Rivilla Rivilla Juan Jose",
    "wof:placetype":"venue"
},
  "geometry": {"coordinates":[2.2024381161,41.450504303],"type":"Point"}
}