{
  "type": "Feature",
  "properties": {
    "iso:country":"ES",
    "sg:address":"Calle de Coria, 60",
    "sg:city":"Moraleja",
    "sg:orig_category":"Hielo Artificial (fabricaci\u00d3n, Distribuci\u00d3n)",
    "sg:phone":"+34 927 51 51 51",
    "sg:postcode":"10840",
    "sg:province":"C\u00e1ceres",
    "wof:name":"Helados Sierra De Gata S.l.",
    "wof:placetype":"venue"
},
  "geometry": {"coordinates":[-6.6570062637,40.0645065308],"type":"Point"}
}