{
  "type": "Feature",
  "properties": {
    "iso:country":"ES",
    "sg:address":"Calle de Alcazabilla, S/n",
    "sg:city":"Malaga",
    "sg:orig_category":"Negocio De Materiales De Construcci\u00d3n",
    "sg:phone":"+34 952 60 16 19",
    "sg:postcode":"29015",
    "sg:province":"M\u00e1laga",
    "wof:name":"Hermanos Campano S.l.",
    "wof:placetype":"venue"
},
  "geometry": {"coordinates":[-4.4171919823,36.7217254639],"type":"Point"}
}