{
  "type": "Feature",
  "properties": {
    "iso:country":"ES",
    "sg:address":"Psaj Canal De Suez, 16",
    "sg:city":"Madrid",
    "sg:orig_category":"Agentes, Concesionarios Y Sucursales De Veh\u00cdculos",
    "sg:phone":"+34 917 47 63 34",
    "sg:postcode":"28042",
    "sg:province":"Madrid",
    "wof:name":"Autorreparciones Baraja S.a.",
    "wof:placetype":"venue"
},
  "geometry": {"coordinates":[-3.5802352428,40.4720191956],"type":"Point"}
}