{
  "type": "Feature",
  "properties": {
    "iso:country":"ES",
    "sg:address":"Calle de Ancha, 3",
    "sg:city":"Corral De Calatrava",
    "sg:classifiers":[
        {
            "category":"Casinos & Gambling",
            "type":"Entertainment"
        }
    ],
    "sg:phone":"+34 926 83 03 32",
    "sg:postcode":"13190",
    "sg:province":"Ciudad Real",
    "sg:tags":[
        "locale",
        "de",
        "juego"
    ],
    "wof:name":"Casino Nuestra Se\u00f1ora De La Paz",
    "wof:placetype":"venue"
},
  "geometry": {"coordinates":[-4.0807976723,38.8588142395],"type":"Point"}
}