{
  "type": "Feature",
  "properties": {
    "addr:full":"Carrer de Pere Iv, 129 Barcelona Barcelona 08018",
    "addr:housenumber":"129",
    "addr:postcode":"08018",
    "addr:street":"Carrer De Pere Iv",
    "iso:country":"ES",
    "sg:address":"Carrer de Pere Iv, 129",
    "sg:city":"Barcelona",
    "sg:orig_category":"Agentes, Concesionarios Y Sucursales De Veh\u00cdculos",
    "sg:phone":"+34 933 00 00 16",
    "sg:postcode":"08018",
    "sg:province":"Barcelona",
    "sg:website":"www.centpoblenou-citroen.es",
    "wof:name":"Central Poblenou S.a.",
    "wof:placetype":"venue"
},
  "geometry": {"coordinates":[2.1906960011,41.3977851868],"type":"Point"}
}