{
  "type": "Feature",
  "properties": {
    "iso:country":"ES",
    "sg:address":"Calle de Jaen, 1",
    "sg:city":"Villanueva Reina",
    "sg:orig_category":"Alimentaci\u00d3n General (al Por Menor)",
    "sg:phone":"+34 953 54 80 05",
    "sg:postcode":"23730",
    "sg:province":"Ja\u00e9n",
    "wof:name":"Valero Camara Juana",
    "wof:placetype":"venue"
},
  "geometry": {"coordinates":[-3.9176690578,38.0045318604],"type":"Point"}
}