{
  "type": "Feature",
  "properties": {
    "addr:full":"Carr Sant Joan, 18 Lleida Lleida 25007",
    "addr:housenumber":"18",
    "addr:postcode":"25007",
    "addr:street":"Carr Sant Joan",
    "iso:country":"ES",
    "sg:address":"Carr Sant Joan, 18",
    "sg:city":"Lleida",
    "sg:orig_category":"Abogados",
    "sg:phone":"+34 973 24 15 58",
    "sg:postcode":"25007",
    "sg:province":"Lleida",
    "wof:name":"Porta Advocats Associats S.c.p.",
    "wof:placetype":"venue"
},
  "geometry": {"coordinates":[0.6282659769,41.6168136597],"type":"Point"}
}