{
  "type": "Feature",
  "properties": {
    "iso:country":"ES",
    "sg:address":"Calle de Capuchinos, 1",
    "sg:city":"Borja",
    "sg:orig_category":"Ense\u00d1anza Secundaria: Colegios Y Escuelas Privadas",
    "sg:phone":"+34 976 86 73 68",
    "sg:postcode":"50540",
    "sg:province":"Zaragoza",
    "wof:name":"Instituto De Eduacion Secundaria Juan De Lanuza",
    "wof:placetype":"venue"
},
  "geometry": {"coordinates":[-1.5280760527,41.833026886],"type":"Point"}
}