{
  "type": "Feature",
  "properties": {
    "iso:country":"ES",
    "sg:address":"Cm\u00d1o Forti\u00d1on, 157",
    "sg:city":"Forti\u00d1on",
    "sg:orig_category":"Instalaci\u00d3n, Mantenimiento De Porteros Electr\u00d3nicos Y Controles De Acceso",
    "sg:phone":"+34 986 46 05 48",
    "sg:postcode":"36392",
    "sg:province":"Pontevedra",
    "wof:name":"Fernandez Rial Isidro",
    "wof:placetype":"venue"
},
  "geometry": {"coordinates":[-8.8130493164,42.170173645],"type":"Point"}
}