{
  "type": "Feature",
  "properties": {
    "iso:country":"ES",
    "sg:address":"Calle de Martinez Villena, 3",
    "sg:city":"Albacete",
    "sg:orig_category":"Abogados",
    "sg:phone":"+34 967 21 59 25",
    "sg:postcode":"02001",
    "sg:province":"Albacete",
    "wof:name":"Martinez Moratalla Jorge",
    "wof:placetype":"venue"
},
  "geometry": {"coordinates":[-1.8563799858,38.9961128235],"type":"Point"}
}