{
  "type": "Feature",
  "properties": {
    "addr:full":"Calle de Vara Del Rey, 2 Melilla Melilla 52002",
    "addr:housenumber":"2",
    "addr:postcode":"52002",
    "addr:street":"Calle De Vara Del Rey",
    "iso:country":"ES",
    "sg:address":"Calle de Vara Del Rey, 2",
    "sg:city":"Melilla",
    "sg:orig_category":"Molduras, Junquillos, Listones Y Molduras Perforadas",
    "sg:phone":"+34 952 68 51 86",
    "sg:postcode":"52002",
    "sg:province":"Melilla",
    "wof:name":"Hermandad De Antiguos Caballeros Legionarios",
    "wof:placetype":"venue"
},
  "geometry": {"coordinates":[-2.9444730282,35.294254303],"type":"Point"}
}