{
  "type": "Feature",
  "properties": {
    "iso:country":"ES",
    "sg:address":"Carrer de Sant Andreu, 31",
    "sg:city":"Santa Coloma De Gramenet",
    "sg:orig_category":"Ropa De Cuero Y De Piel (confecci\u00d3n, Al Por Mayor)",
    "sg:phone":"+34 933 85 59 59",
    "sg:postcode":"08923",
    "sg:province":"Barcelona",
    "wof:name":"Villar Bustos Andres",
    "wof:placetype":"venue"
},
  "geometry": {"coordinates":[2.2149369717,41.4458656311],"type":"Point"}
}