{
  "type": "Feature",
  "properties": {
    "iso:country":"ES",
    "sg:address":"Rua De Castelao, 17",
    "sg:city":"Padron",
    "sg:orig_category":"Asociaciones Y Clubs Deportivos",
    "sg:phone":"+34 981 81 15 48",
    "sg:postcode":"15900",
    "sg:province":"La Coru\u00f1a",
    "wof:name":"Peregrino Lois Rodriguez S.l.",
    "wof:placetype":"venue"
},
  "geometry": {"coordinates":[-8.6615276337,42.7377853394],"type":"Point"}
}