{
  "type": "Feature",
  "properties": {
    "iso:country":"ES",
    "sg:address":"Calle de Peso, 2",
    "sg:city":"Valladolid",
    "sg:orig_category":"Comunidades Religiosas",
    "sg:phone":"+34 983 33 10 26",
    "sg:postcode":"47001",
    "sg:province":"Valladolid",
    "wof:name":"Cofradia Penitencial De Nuestro Padre Jesus Nazareno",
    "wof:placetype":"venue"
},
  "geometry": {"coordinates":[-4.729183197,41.6526451111],"type":"Point"}
}