{
  "type": "Feature",
  "properties": {
    "addr:full":"Avda Palomares, 13 San Juan De Aznalfarache Sevilla 41920",
    "addr:housenumber":"13",
    "addr:postcode":"41920",
    "addr:street":"Avda Palomares",
    "iso:country":"ES",
    "sg:address":"Avda Palomares, 13",
    "sg:city":"San Juan De Aznalfarache",
    "sg:orig_category":"Agencias De Viajes",
    "sg:phone":"+34 954 17 89 89",
    "sg:postcode":"41920",
    "sg:province":"Sevilla",
    "wof:name":"Auro Agencia Viajes Minorista S.l.",
    "wof:placetype":"venue"
},
  "geometry": {"coordinates":[-6.0341362953,37.3570976257],"type":"Point"}
}