{
  "type": "Feature",
  "properties": {
    "addr:full":"Ctra Jaen (santa Ana), S/n Santa Ana Albacete 02328",
    "addr:housenumber":"s / n",
    "addr:postcode":"02328",
    "addr:street":"Ctra Jaen Santa Ana",
    "iso:country":"ES",
    "sg:address":"Ctra Jaen (santa Ana), S/n",
    "sg:city":"Santa Ana",
    "sg:orig_category":"Conservas De Legumbres (fabricaci\u00d3n, Al Por Mayor)",
    "sg:phone":"+34 967 27 01 55",
    "sg:postcode":"02328",
    "sg:province":"Albacete",
    "wof:name":"Ardovries Espa\u00f1a S.a.",
    "wof:placetype":"venue"
},
  "geometry": {"coordinates":[-1.9895231724,38.9002761841],"type":"Point"}
}