{
  "type": "Feature",
  "properties": {
    "iso:country":"ES",
    "sg:address":"Avda Estacion (la), 15",
    "sg:city":"Alacant",
    "sg:orig_category":"Inmobiliaria (agencias)",
    "sg:phone":"+34 965 92 66 56",
    "sg:postcode":"03003",
    "sg:province":"Alicante",
    "sg:website":"www.gesinar.es",
    "wof:name":"Gesinar Servicios Inmobiliarios S.l.u.",
    "wof:placetype":"venue"
},
  "geometry": {"coordinates":[-0.49327299,38.3449363708],"type":"Point"}
}