{
  "type": "Feature",
  "properties": {
    "iso:country":"ES",
    "sg:address":"Carrer de Muralla De Sant Francesc, 7",
    "sg:city":"Montblanc",
    "sg:orig_category":"Frutas, Legumbres Frescas Y Tempranas (al Por Menor)",
    "sg:phone":"+34 977 86 05 58",
    "sg:postcode":"43400",
    "sg:province":"Tarragona",
    "wof:name":"Fontava Moix S.l.",
    "wof:placetype":"venue"
},
  "geometry": {"coordinates":[1.1643300056,41.3753395081],"type":"Point"}
}