{
  "type": "Feature",
  "properties": {
    "iso:country":"ES",
    "sg:address":"Carrer de Rodes, 16",
    "sg:city":"Hospitalet Llobregat",
    "sg:orig_category":"Papeler\u00cdas, Librer\u00cdas",
    "sg:phone":"+34 932 61 07 43",
    "sg:postcode":"08901",
    "sg:province":"Barcelona",
    "wof:name":"Balbas Salvatierra Jesus Angel",
    "wof:placetype":"venue"
},
  "geometry": {"coordinates":[2.1083848476,41.3610191345],"type":"Point"}
}