{
  "type": "Feature",
  "properties": {
    "addr:full":"Pianton, S/n Pianton Asturias 33778",
    "addr:postcode":"33778",
    "addr:street":"Pianton S / N Pianton Asturias",
    "iso:country":"ES",
    "sg:address":"Pianton, S/n",
    "sg:city":"Pianton",
    "sg:orig_category":"Alimentaci\u00d3n General (al Por Menor)",
    "sg:phone":"+34 985 47 62 51",
    "sg:postcode":"33778",
    "sg:province":"Asturias",
    "wof:name":"Soc.coop.eo Leche R.l.",
    "wof:placetype":"venue"
},
  "geometry": {"coordinates":[-6.9966740608,43.45104599],"type":"Point"}
}