{
  "type": "Feature",
  "properties": {
    "addr:full":"Carrer de Doctor Pi I Sunyer, 8 Roses Girona 17480",
    "addr:housenumber":"8",
    "addr:postcode":"17480",
    "addr:street":"Carrer De Doctor Pi I Sunyer",
    "iso:country":"ES",
    "sg:address":"Carrer de Doctor Pi I Sunyer, 8",
    "sg:city":"Roses",
    "sg:orig_category":"Zapatos (al Por Menor)",
    "sg:phone":"+34 972 25 71 90",
    "sg:postcode":"17480",
    "sg:province":"Girona",
    "wof:name":"Calzados Palmira S. A.",
    "wof:placetype":"venue"
},
  "geometry": {"coordinates":[3.175549984,42.2626991272],"type":"Point"}
}