{
  "type": "Feature",
  "properties": {
    "iso:country":"ES",
    "sg:address":"Calle de Cadenas De San Gregorio, 2",
    "sg:city":"Valladolid",
    "sg:orig_category":"Arte, Cultura, Edici\u00d3n",
    "sg:phone":"+34 983 25 40 83",
    "sg:postcode":"47011",
    "sg:province":"Valladolid",
    "sg:website":"www.pymes.tsai.es/museoescultura",
    "wof:name":"Museo Nacional De Escultura",
    "wof:placetype":"venue"
},
  "geometry": {"coordinates":[-4.7240219116,41.6569252014],"type":"Point"}
}