{
  "type": "Feature",
  "properties": {
    "iso:country":"ES",
    "sg:address":"Calle de Valle (el), S/n",
    "sg:city":"Baeza",
    "sg:orig_category":"Alimentaci\u00d3n General (al Por Mayor)",
    "sg:phone":"+34 953 74 18 27",
    "sg:postcode":"23440",
    "sg:province":"Ja\u00e9n",
    "wof:name":"Piensos Noves",
    "wof:placetype":"venue"
},
  "geometry": {"coordinates":[-3.4627649784,37.9994125366],"type":"Point"}
}