{
  "type": "Feature",
  "properties": {
    "addr:full":"Pase Quintanilla, 20 Le\u00f3n Le\u00f3n 24007",
    "addr:housenumber":"20",
    "addr:postcode":"24007",
    "addr:street":"Quintanilla;Leo\u0301N",
    "iso:country":"ES",
    "sg:address":"Pase Quintanilla, 20",
    "sg:city":"Le\u00f3n",
    "sg:orig_category":"Panader\u00cdas, Panader\u00cdas",
    "sg:phone":"+34 987 23 59 98",
    "sg:postcode":"24007",
    "sg:province":"Le\u00f3n",
    "wof:name":"Robles Miranda Nuria",
    "wof:placetype":"venue"
},
  "geometry": {"coordinates":[-5.5640258789,42.6031837463],"type":"Point"}
}