{
  "type": "Feature",
  "properties": {
    "iso:country":"ES",
    "sg:address":"Calle de Molino, 37",
    "sg:city":"Ronda",
    "sg:orig_category":"Pr\u00c9stamos Personales E Hipotecarios",
    "sg:phone":"+34 952 87 50 41",
    "sg:postcode":"29400",
    "sg:province":"M\u00e1laga",
    "wof:name":"Martin Hernandez Luis",
    "wof:placetype":"venue"
},
  "geometry": {"coordinates":[-5.1673650742,36.7455062866],"type":"Point"}
}