{
  "type": "Feature",
  "properties": {
    "addr:full":"Calle de Baeza, 7 Jaen Ja\u00e9n 23008",
    "addr:housenumber":"7;jae\u0301n",
    "addr:postcode":"23008",
    "addr:street":"Calle De Baeza",
    "iso:country":"ES",
    "sg:address":"Calle de Baeza, 7",
    "sg:city":"Jaen",
    "sg:orig_category":"Procuradores",
    "sg:phone":"+34 953 25 11 36",
    "sg:postcode":"23008",
    "sg:province":"Ja\u00e9n",
    "wof:name":"Fuentes Alonso Maria Luisa",
    "wof:placetype":"venue"
},
  "geometry": {"coordinates":[-3.7869489193,37.773475647],"type":"Point"}
}