{
  "type": "Feature",
  "properties": {
    "addr:full":"Carrer de Doctor Reig, 5 Viladecans Barcelona 08840",
    "addr:housenumber":"5",
    "addr:postcode":"08840",
    "addr:street":"Carrer De Doctor Reig",
    "iso:country":"ES",
    "sg:address":"Carrer de Doctor Reig, 5",
    "sg:city":"Viladecans",
    "sg:orig_category":"Sociedades, Compa\u00d1\u00cdas Aseguradoras",
    "sg:phone":"+34 936 37 55 60",
    "sg:postcode":"08840",
    "sg:province":"Barcelona",
    "wof:name":"Ags Aguilar Gestion De Seguros S.l.",
    "wof:placetype":"venue"
},
  "geometry": {"coordinates":[2.0161840916,41.3160552979],"type":"Point"}
}