{
  "type": "Feature",
  "properties": {
    "addr:full":"Calle de Magdalena, 4 Errenteria Guip\u00f9zcoa 20100",
    "addr:housenumber":"4",
    "addr:postcode":"20100",
    "addr:street":"Calle De Magdalena;Guipu\u0300Zcoa",
    "iso:country":"ES",
    "sg:address":"Calle de Magdalena, 4",
    "sg:city":"Errenteria",
    "sg:orig_category":"Carnicer\u00cdas, Carnicer\u00cdas",
    "sg:phone":"+34 943 51 65 44",
    "sg:postcode":"20100",
    "sg:province":"Guip\u00f9zcoa",
    "sg:website":"www.labarandilla.com",
    "wof:name":"Rotatxa S.l.",
    "wof:placetype":"venue"
},
  "geometry": {"coordinates":[-1.899263978,43.3122520447],"type":"Point"}
}