{
  "type": "Feature",
  "properties": {
    "addr:full":"Calle de Ventura Rodriguez, 32 Zaragoza Zaragoza 50007",
    "addr:housenumber":"32",
    "addr:postcode":"50007",
    "addr:street":"Calle De Ventura Rodriguez",
    "iso:country":"ES",
    "sg:address":"Calle de Ventura Rodriguez, 32",
    "sg:city":"Zaragoza",
    "sg:orig_category":"Agencias Y Agentes Comerciales, Representantes",
    "sg:phone":"+34 976 27 70 45",
    "sg:postcode":"50007",
    "sg:province":"Zaragoza",
    "wof:name":"Ballesteros Beamonte Luis Adrian",
    "wof:placetype":"venue"
},
  "geometry": {"coordinates":[-0.8764889836,41.6361579895],"type":"Point"}
}