{
  "type": "Feature",
  "properties": {
    "iso:country":"ES",
    "sg:address":"Avda Rioja De (la), 15",
    "sg:city":"Quel",
    "sg:orig_category":"Peluquer\u00cdas, Peluquer\u00cda Mixta",
    "sg:phone":"+34 941 39 24 44",
    "sg:postcode":"26570",
    "sg:province":"La Rioja",
    "wof:name":"O\u00f1ate Rada Cristina",
    "wof:placetype":"venue"
},
  "geometry": {"coordinates":[-2.0563650131,42.233341217],"type":"Point"}
}