{
  "type": "Feature",
  "properties": {
    "iso:country":"ES",
    "sg:address":"Carrer de Batllevell, 173",
    "sg:city":"Sabadell",
    "sg:orig_category":"Estudios, Instalaci\u00d3n De Climatizaci\u00d3n",
    "sg:phone":"+34 937 16 76 01",
    "sg:postcode":"08208",
    "sg:province":"Barcelona",
    "wof:name":"Instaeco Soler S.l.",
    "wof:placetype":"venue"
},
  "geometry": {"coordinates":[2.1048219204,41.5592002869],"type":"Point"}
}