{
  "type": "Feature",
  "properties": {
    "addr:full":"Carrer de Prat De La Riba, 6 Viladecans Barcelona 08840",
    "addr:housenumber":"6",
    "addr:postcode":"08840",
    "addr:street":"Carrer De Prat De La Riba",
    "iso:country":"ES",
    "sg:address":"Carrer de Prat De La Riba, 6",
    "sg:city":"Viladecans",
    "sg:orig_category":"Calderer\u00cda",
    "sg:phone":"+34 936 58 22 83",
    "sg:postcode":"08840",
    "sg:province":"Barcelona",
    "wof:name":"Molina Tomas Juan",
    "wof:placetype":"venue"
},
  "geometry": {"coordinates":[2.0100181103,41.3152236938],"type":"Point"}
}