{
  "type": "Feature",
  "properties": {
    "addr:full":"Carrer de Torcuato Luca Tena, 3 Palma Islas Baleares 07005",
    "addr:housenumber":"3",
    "addr:postcode":"07005",
    "addr:street":"Carrer De Torcuato Luca Tena",
    "iso:country":"ES",
    "sg:address":"Carrer de Torcuato Luca Tena, 3",
    "sg:city":"Palma",
    "sg:orig_category":"Agentes, Concesionarios Y Sucursales De Camiones Y Veh\u00cdculos Industriales",
    "sg:phone":"+34 971 27 69 06",
    "sg:postcode":"07005",
    "sg:province":"Islas Baleares",
    "wof:name":"Llompart Mestre Rafael",
    "wof:placetype":"venue"
},
  "geometry": {"coordinates":[2.6638350487,39.5756378174],"type":"Point"}
}