{
  "type": "Feature",
  "properties": {
    "addr:full":"Ctra Segorbe, S/n Castellnovo Castell\u00f3n 12413",
    "addr:housenumber":"s / n",
    "addr:postcode":"12413",
    "addr:street":"Ctra Segorbe",
    "iso:country":"ES",
    "sg:address":"Ctra Segorbe, S/n",
    "sg:city":"Castellnovo",
    "sg:orig_category":"Cooperativas Agr\u00cdcolas",
    "sg:phone":"+34 964 13 73 85",
    "sg:postcode":"12413",
    "sg:province":"Castell\u00f3n",
    "wof:name":"Sociedad Cooperativa Agricola Castellnovo Coop.v.ltda.",
    "wof:placetype":"venue"
},
  "geometry": {"coordinates":[-0.4101420045,39.8707008362],"type":"Point"}
}