{
  "type": "Feature",
  "properties": {
    "addr:full":"G.v. Corts Catalanes, 759 Barcelona Barcelona 08013",
    "addr:housenumber":"759",
    "addr:postcode":"08013",
    "addr:street":"Catalanes",
    "iso:country":"ES",
    "sg:address":"G.v. Corts Catalanes, 759",
    "sg:city":"Barcelona",
    "sg:orig_category":"Doctores En Medicina",
    "sg:phone":"+34 932 32 90 04",
    "sg:postcode":"08013",
    "sg:province":"Barcelona",
    "wof:name":"Olavide Miret Juan Eduardo",
    "wof:placetype":"venue"
},
  "geometry": {"coordinates":[2.1838750839,41.4015197754],"type":"Point"}
}