{
  "type": "Feature",
  "properties": {
    "addr:full":"Calle de Mosquilona (de La), 22 Colmenar Viejo Madrid 28770",
    "addr:postcode":"28770",
    "addr:street":"Calle De Mosquilona De La",
    "iso:country":"ES",
    "sg:address":"Calle de Mosquilona (de La), 22",
    "sg:city":"Colmenar Viejo",
    "sg:orig_category":"Caf\u00c9s, Bares, Cervecer\u00cdas",
    "sg:phone":"+34 918 45 22 19",
    "sg:postcode":"28770",
    "sg:province":"Madrid",
    "wof:name":"Diez Mejias Marcos",
    "wof:placetype":"venue"
},
  "geometry": {"coordinates":[-3.7716760635,40.6634941101],"type":"Point"}
}