{
  "type": "Feature",
  "properties": {
    "addr:full":"Rbla Pulido, 3 Santa Cruz De Tenerife Santa Cruz De Tenerife 38004",
    "addr:housenumber":"3",
    "addr:postcode":"38004",
    "addr:street":"Rbla Pulido",
    "iso:country":"ES",
    "sg:address":"Rbla Pulido, 3",
    "sg:city":"Santa Cruz De Tenerife",
    "sg:orig_category":"Bancos",
    "sg:phone":"+34 922 27 33 50",
    "sg:postcode":"38004",
    "sg:province":"Santa Cruz De Tenerife",
    "wof:name":"Banca March S.a.",
    "wof:placetype":"venue"
},
  "geometry": {"coordinates":[-16.2565288544,28.4672908783],"type":"Point"}
}