{
  "type": "Feature",
  "properties": {
    "iso:country":"ES",
    "sg:address":"Rond Frederic Mistral, 14",
    "sg:city":"Mataro",
    "sg:orig_category":"Puericultora",
    "sg:phone":"+34 937 58 69 04",
    "sg:postcode":"08304",
    "sg:province":"Barcelona",
    "wof:name":"Pu\u00f1et Tuset Laura",
    "wof:placetype":"venue"
},
  "geometry": {"coordinates":[2.4393019676,41.5505638123],"type":"Point"}
}