{
  "type": "Feature",
  "properties": {
    "addr:full":"Calle de Larga, S/n Santiago Millas Le\u00f3n 24732",
    "addr:housenumber":"s / n",
    "addr:postcode":"24732",
    "addr:street":"Calle De Larga",
    "iso:country":"ES",
    "sg:address":"Calle de Larga, S/n",
    "sg:city":"Santiago Millas",
    "sg:orig_category":"Fabricaci\u00d3n De Quesos",
    "sg:phone":"+34 987 69 13 13",
    "sg:postcode":"24732",
    "sg:province":"Le\u00f3n",
    "wof:name":"La Moldera Real S.l.",
    "wof:placetype":"venue"
},
  "geometry": {"coordinates":[-6.1032819748,42.3802337646],"type":"Point"}
}