{
  "type": "Feature",
  "properties": {
    "iso:country":"ES",
    "sg:address":"Calle de Asomadillas, 2",
    "sg:city":"Cordoba",
    "sg:orig_category":"Internados & Ense\u00d1anza Privada",
    "sg:phone":"+34 957 27 11 96",
    "sg:postcode":"14012",
    "sg:province":"C\u00f3rdoba",
    "wof:name":"Colegio Almanzor",
    "wof:placetype":"venue"
},
  "geometry": {"coordinates":[-4.7843198776,37.9070358276],"type":"Point"}
}