{
  "type": "Feature",
  "properties": {
    "iso:country":"ES",
    "sg:address":"Av Francesc Macia, 78",
    "sg:city":"Sabadell",
    "sg:orig_category":"Urbanistas",
    "sg:phone":"+34 937 23 71 99",
    "sg:postcode":"08206",
    "sg:province":"Barcelona",
    "wof:name":"Atic Macia 78 Arquitectes S.l.",
    "wof:placetype":"venue"
},
  "geometry": {"coordinates":[2.0973222256,41.5585975647],"type":"Point"}
}