{
  "type": "Feature",
  "properties": {
    "addr:full":"Calle de Ugarte, 24 Bilbao Vizcaya 48004",
    "addr:housenumber":"24",
    "addr:postcode":"48004",
    "addr:street":"Calle De Ugarte",
    "iso:country":"ES",
    "sg:address":"Calle de Ugarte, 24",
    "sg:city":"Bilbao",
    "sg:orig_category":"Ferreter\u00cda (diversos)",
    "sg:phone":"+34 944 12 30 34",
    "sg:postcode":"48004",
    "sg:province":"Vizcaya",
    "wof:name":"Martin Madrid Teodoro",
    "wof:placetype":"venue"
},
  "geometry": {"coordinates":[-2.9023339748,43.2595672607],"type":"Point"}
}