{
  "type": "Feature",
  "properties": {
    "addr:full":"Calle de Valmojado, 195 Madrid Madrid 28047",
    "addr:housenumber":"195",
    "addr:postcode":"28047",
    "addr:street":"Calle De Valmojado",
    "iso:country":"ES",
    "sg:address":"Calle de Valmojado, 195",
    "sg:city":"Madrid",
    "sg:orig_category":"Farmacias (repartici\u00d3n Y Al Por Mayor)",
    "sg:phone":"+34 917 17 26 69",
    "sg:postcode":"28047",
    "sg:province":"Madrid",
    "wof:name":"Firma Ambu S.l.",
    "wof:placetype":"venue"
},
  "geometry": {"coordinates":[-3.7575690746,40.3907814026],"type":"Point"}
}