{
  "type": "Feature",
  "properties": {
    "addr:full":"Carrer de Salze, 1 Sant Julia D'alfou Barcelona 08459",
    "addr:housenumber":"1",
    "addr:postcode":"08459",
    "addr:street":"Carrer De Salze;Sant Julia",
    "iso:country":"ES",
    "sg:address":"Carrer de Salze, 1",
    "sg:city":"Sant Julia D'alfou",
    "sg:orig_category":"Venta, Colocaci\u00d3n, Reparaci\u00d3n De Parabrisas, Techos Descapotables",
    "sg:phone":"+34 938 41 89 70",
    "sg:postcode":"08459",
    "sg:province":"Barcelona",
    "wof:name":"Orient Glass S.l.",
    "wof:placetype":"venue"
},
  "geometry": {"coordinates":[2.3815906048,41.649810791],"type":"Point"}
}