{
  "type": "Feature",
  "properties": {
    "addr:full":"Calle de Itzurun Zuhaizbidea, 1 Zumaia Guip\u00f9zcoa 20750",
    "addr:housenumber":"1",
    "addr:postcode":"20750",
    "addr:street":"Calle De Itzurun Zuhaizbidea;Guipu\u0300Zcoa",
    "iso:country":"ES",
    "sg:address":"Calle de Itzurun Zuhaizbidea, 1",
    "sg:city":"Zumaia",
    "sg:orig_category":"Carnicer\u00cdas, Carnicer\u00cdas",
    "sg:phone":"+34 943 86 24 30",
    "sg:postcode":"20750",
    "sg:province":"Guip\u00f9zcoa",
    "wof:name":"Agustin Ibarguren S.l.",
    "wof:placetype":"venue"
},
  "geometry": {"coordinates":[-2.256711483,43.2984809875],"type":"Point"}
}