{
  "type": "Feature",
  "properties": {
    "addr:full":"Calle de Balsas (las), 12 Logro\u00f1o La Rioja 26006",
    "addr:housenumber":"12",
    "addr:postcode":"26006",
    "addr:street":"Calle De Balsas Las;Rioja",
    "iso:country":"ES",
    "sg:address":"Calle de Balsas (las), 12",
    "sg:city":"Logro\u00f1o",
    "sg:orig_category":"Pintura: M\u00c1quinas (instalaci\u00d3n)",
    "sg:phone":"+34 941 25 79 63",
    "sg:postcode":"26006",
    "sg:province":"La Rioja",
    "wof:name":"Comercial Maquinaria Y Sistemas De Aplicacion S.l.",
    "wof:placetype":"venue"
},
  "geometry": {"coordinates":[-2.4103929996,42.4696350098],"type":"Point"}
}