{
  "type": "Feature",
  "properties": {
    "iso:country":"ES",
    "sg:address":"Calle de Cigue\u00d1a (la), 61",
    "sg:city":"Logro\u00f1o",
    "sg:orig_category":"Loter\u00cda Y T\u00d3mbola",
    "sg:phone":"+34 941 23 57 65",
    "sg:postcode":"26004",
    "sg:province":"La Rioja",
    "wof:name":"Clavel Martinez Julian",
    "wof:placetype":"venue"
},
  "geometry": {"coordinates":[-2.4289050102,42.4644546509],"type":"Point"}
}