{
  "type": "Feature",
  "properties": {
    "addr:full":"Plaz Palillero (del), 2 Cadiz C\u00e1diz 11001",
    "addr:housenumber":"2",
    "addr:postcode":"11001",
    "addr:street":"Plaz;Del",
    "iso:country":"ES",
    "sg:address":"Plaz Palillero (del), 2",
    "sg:city":"Cadiz",
    "sg:orig_category":"Perfumer\u00cda (al Por Menor)",
    "sg:phone":"+34 956 80 70 25",
    "sg:postcode":"11001",
    "sg:province":"C\u00e1diz",
    "sg:website":"www.bodybell.com",
    "wof:name":"Iberica De Drogueria Y Perfumeria S.a.",
    "wof:placetype":"venue"
},
  "geometry": {"coordinates":[-6.2976894379,36.5320510864],"type":"Point"}
}