{
  "type": "Feature",
  "properties": {
    "iso:country":"ES",
    "sg:address":"Pol Ind Plazaola Manzana E, S/n",
    "sg:city":"Aizoain",
    "sg:orig_category":"Pintura, Barniz, Productos Asimilables (fabricaci\u00d3n, Al Por Mayor)",
    "sg:phone":"+34 948 30 63 50",
    "sg:postcode":"31195",
    "sg:province":"Navarra",
    "sg:website":"www.seraxa.com",
    "wof:name":"Seraxa Plazaola Distribuciones S.l.l.",
    "wof:placetype":"venue"
},
  "geometry": {"coordinates":[-1.6867979765,42.8470611572],"type":"Point"}
}