{
  "type": "Feature",
  "properties": {
    "iso:country":"ES",
    "sg:address":"Moll Barcelona, 13",
    "sg:city":"Barcelona",
    "sg:orig_category":"Promotores Constructores",
    "sg:phone":"+34 933 42 84 93",
    "sg:postcode":"08039",
    "sg:province":"Barcelona",
    "wof:name":"Marquillas Olondrs Eduardo",
    "wof:placetype":"venue"
},
  "geometry": {"coordinates":[2.1776499748,41.3729553223],"type":"Point"}
}