{
  "type": "Feature",
  "properties": {
    "addr:full":"Calle de Joaquin Huarte, 6 Lagartera Toledo 45567",
    "addr:housenumber":"6",
    "addr:postcode":"45567",
    "addr:street":"Calle De Joaquin Huarte",
    "iso:country":"ES",
    "sg:address":"Calle de Joaquin Huarte, 6",
    "sg:city":"Lagartera",
    "sg:orig_category":"Molduras, Junquillos, Listones Y Molduras Perforadas",
    "sg:phone":"+34 925 45 01 87",
    "sg:postcode":"45567",
    "sg:province":"Toledo",
    "wof:name":"Moreno Toribio Fabio",
    "wof:placetype":"venue"
},
  "geometry": {"coordinates":[-5.2021517754,39.9059638977],"type":"Point"}
}