{
  "type": "Feature",
  "properties": {
    "iso:country":"ES",
    "sg:address":"Carrer de Sant Josep (de), 95",
    "sg:city":"S. Carles Rapita",
    "sg:orig_category":"Veh\u00cdculos De Ocasi\u00d3n",
    "sg:phone":"+34 977 74 27 68",
    "sg:postcode":"43540",
    "sg:province":"Tarragona",
    "wof:name":"Automobils Cajigos S. L.",
    "wof:placetype":"venue"
},
  "geometry": {"coordinates":[0.5952810049,40.6255645752],"type":"Point"}
}