{
  "type": "Feature",
  "properties": {
    "iso:country":"ES",
    "sg:address":"Calle de Horno, 5",
    "sg:city":"Malaga",
    "sg:orig_category":"Arquitectos",
    "sg:phone":"+34 952 22 60 18",
    "sg:postcode":"29005",
    "sg:province":"M\u00e1laga",
    "wof:name":"Pozo Garcia-baquero Rafael",
    "wof:placetype":"venue"
},
  "geometry": {"coordinates":[-4.4239168167,36.7208061218],"type":"Point"}
}