{
  "type": "Feature",
  "properties": {
    "addr:full":"Ctra Alcora, S/n Castellon De La Plana Castell\u00f3n 12006",
    "addr:housenumber":"s / n",
    "addr:postcode":"12006",
    "addr:street":"Ctra Alcora",
    "iso:country":"ES",
    "sg:address":"Ctra Alcora, S/n",
    "sg:city":"Castellon De La Plana",
    "sg:orig_category":"Fabrica De Cer\u00c1micas",
    "sg:phone":"+34 964 25 60 25",
    "sg:postcode":"12006",
    "sg:province":"Castell\u00f3n",
    "sg:website":"www.recercasa.com",
    "wof:name":"Revestimientos Ceramicos Castellon S.a.",
    "wof:placetype":"venue"
},
  "geometry": {"coordinates":[-0.1106889993,40.0054092407],"type":"Point"}
}