{
  "type": "Feature",
  "properties": {
    "addr:full":"Praz Suarez Llanos, 2 Vigo Pontevedra 36208",
    "addr:housenumber":"2",
    "addr:postcode":"36208",
    "addr:street":"Praz Suarez Llanos",
    "iso:country":"ES",
    "sg:address":"Praz Suarez Llanos, 2",
    "sg:city":"Vigo",
    "sg:orig_category":"Agentes Generales De Seguros",
    "sg:phone":"+34 986 23 16 12",
    "sg:postcode":"36208",
    "sg:province":"Pontevedra",
    "wof:name":"Perez Martinez Jose Manuel",
    "wof:placetype":"venue"
},
  "geometry": {"coordinates":[-8.7332239151,42.2212409973],"type":"Point"}
}