{
  "type": "Feature",
  "properties": {
    "iso:country":"ES",
    "sg:address":"Carrer de Agusti I Mila, 10",
    "sg:city":"Barcelona",
    "sg:orig_category":"Molduras, Junquillos, Listones Y Molduras Perforadas",
    "sg:phone":"+34 933 11 25 67",
    "sg:postcode":"08030",
    "sg:province":"Barcelona",
    "wof:name":"Asorey Saramdeses Isabel Oliva",
    "wof:placetype":"venue"
},
  "geometry": {"coordinates":[2.1885550022,41.437953949],"type":"Point"}
}