{
  "type": "Feature",
  "properties": {
    "iso:country":"ES",
    "sg:address":"Av Roma, 5",
    "sg:city":"Barcelona",
    "sg:orig_category":"Empresas De Portes Y Mensajer\u00cda",
    "sg:phone":"+34 934 19 11 11",
    "sg:postcode":"08029",
    "sg:province":"Barcelona",
    "sg:website":"www.nacex.es",
    "wof:name":"Citior S.l.",
    "wof:placetype":"venue"
},
  "geometry": {"coordinates":[2.1435210705,41.3809432983],"type":"Point"}
}