{
  "type": "Feature",
  "properties": {
    "addr:full":"Calle de Daoiz, 25 Palmas De Gran Canaria Las Palmas 35010",
    "addr:housenumber":"25",
    "addr:postcode":"35010",
    "addr:street":"Calle De Daoiz",
    "iso:country":"ES",
    "sg:address":"Calle de Daoiz, 25",
    "sg:city":"Palmas De Gran Canaria",
    "sg:orig_category":"Venta, Localizaci\u00d3n, Reparaci\u00d3n De Material E Instrumental M\u00c9dico",
    "sg:phone":"+34 928 22 99 55",
    "sg:postcode":"35010",
    "sg:province":"Las Palmas",
    "sg:website":"www.fatarca.com",
    "wof:name":"Fatarca Tecnicas Y Sistemas Sl",
    "wof:placetype":"venue"
},
  "geometry": {"coordinates":[-15.4396715164,28.1320953369],"type":"Point"}
}