{
  "type": "Feature",
  "properties": {
    "addr:full":"Avda Reyes Catolicos, 23 Albolote Granada 18220",
    "addr:housenumber":"23",
    "addr:postcode":"18220",
    "addr:street":"Avda Reyes Catolicos",
    "iso:country":"ES",
    "sg:address":"Avda Reyes Catolicos, 23",
    "sg:city":"Albolote",
    "sg:orig_category":"Fabricaci\u00d3n De Cortinas Y Visillos",
    "sg:phone":"+34 958 46 80 09",
    "sg:postcode":"18220",
    "sg:province":"Granada",
    "wof:name":"Carmona Jimenez Enrique",
    "wof:placetype":"venue"
},
  "geometry": {"coordinates":[-3.6565210819,37.227848053],"type":"Point"}
}