{
  "type": "Feature",
  "properties": {
    "addr:full":"Calle de Jose Ruiz Ruiz, 22 Caudete Albacete 02660",
    "addr:housenumber":"22",
    "addr:postcode":"02660",
    "addr:street":"Calle De Jose Ruiz Ruiz",
    "iso:country":"ES",
    "sg:address":"Calle de Jose Ruiz Ruiz, 22",
    "sg:city":"Caudete",
    "sg:orig_category":"Sanatorios M\u00c9dico",
    "sg:phone":"+34 965 82 76 61",
    "sg:postcode":"02660",
    "sg:province":"Albacete",
    "wof:name":"Servicio De Salud De Castilla La Mancha",
    "wof:placetype":"venue"
},
  "geometry": {"coordinates":[-0.9849889874,38.705581665],"type":"Point"}
}