{
  "type": "Feature",
  "properties": {
    "iso:country":"ES",
    "sg:address":"Calle de Princesa Guacimara, 34",
    "sg:city":"Santa Cruz De Tenerife",
    "sg:orig_category":"Iglesia Cat\u00d3lica",
    "sg:phone":"+34 922 22 13 05",
    "sg:postcode":"38008",
    "sg:province":"Santa Cruz De Tenerife",
    "wof:name":"Parroquia De La Salud",
    "wof:placetype":"venue"
},
  "geometry": {"coordinates":[-16.2712020874,28.4690475464],"type":"Point"}
}