{
  "type": "Feature",
  "properties": {
    "iso:country":"ES",
    "sg:address":"Calle de Idioma Esperanto, 18",
    "sg:city":"Madrid",
    "sg:orig_category":"Prot\u00c9sicos Dentales",
    "sg:phone":"+34 913 06 01 95",
    "sg:postcode":"28017",
    "sg:province":"Madrid",
    "wof:name":"Laboratorios Bertinio S.l.",
    "wof:placetype":"venue"
},
  "geometry": {"coordinates":[-3.6256039143,40.4184036255],"type":"Point"}
}