{
  "type": "Feature",
  "properties": {
    "iso:country":"ES",
    "sg:address":"Calle de Garcia Llamas, 4",
    "sg:city":"Madrid",
    "sg:orig_category":"Asociaciones Y Clubs Deportivos",
    "sg:phone":"+34 914 78 49 34",
    "sg:postcode":"28053",
    "sg:province":"Madrid",
    "wof:name":"Cepeda Ruiz Jose Vicente",
    "wof:placetype":"venue"
},
  "geometry": {"coordinates":[-3.668587923,40.3867530823],"type":"Point"}
}