{
  "type": "Feature",
  "properties": {
    "addr:full":"Avda Osa Mayor, 48 Madrid Madrid 28023",
    "addr:housenumber":"48",
    "addr:postcode":"madrid;28023",
    "addr:street":"Avda Osa Mayor",
    "iso:country":"ES",
    "sg:address":"Avda Osa Mayor, 48",
    "sg:city":"Madrid",
    "sg:orig_category":"Tintorer\u00cdas, Limpieza En Seco",
    "sg:phone":"+34 913 07 04 04",
    "sg:postcode":"28023",
    "sg:province":"Madrid",
    "wof:name":"Mayoral Solana Francisco",
    "wof:placetype":"venue"
},
  "geometry": {"coordinates":[-3.7813689709,40.4593429565],"type":"Point"}
}