{
  "type": "Feature",
  "properties": {
    "iso:country":"ES",
    "sg:address":"Avda Virgen Desamparados, 5",
    "sg:city":"Xirivella",
    "sg:orig_category":"Servicios Gsm",
    "sg:phone":"+34 963 13 51 51",
    "sg:postcode":"46950",
    "sg:province":"Valencia",
    "wof:name":"Comunicaciones Telcoval S.l.",
    "wof:placetype":"venue"
},
  "geometry": {"coordinates":[-0.4310849905,39.4659805298],"type":"Point"}
}