{
  "type": "Feature",
  "properties": {
    "addr:full":"Calle de Urkiola, 1 Algorta Vizcaya 48993",
    "addr:housenumber":"1",
    "addr:postcode":"48993",
    "addr:street":"Calle De Urkiola",
    "iso:country":"ES",
    "sg:address":"Calle de Urkiola, 1",
    "sg:city":"Algorta",
    "sg:orig_category":"Peluquer\u00cdas, Peluquer\u00cda Mixta",
    "sg:phone":"+34 944 30 31 67",
    "sg:postcode":"48993",
    "sg:province":"Vizcaya",
    "wof:name":"Lekuona Apraiz Miren Igone",
    "wof:placetype":"venue"
},
  "geometry": {"coordinates":[-3.0097219944,43.3563308716],"type":"Point"}
}