{
  "type": "Feature",
  "properties": {
    "iso:country":"ES",
    "sg:address":"Calle de Coronel Calaza, 13",
    "sg:city":"Coru\u00d1a",
    "sg:orig_category":"Autob\u00das (explotaci\u00d3n Y Servicios De)",
    "sg:phone":"+34 981 20 46 16",
    "sg:postcode":"15002",
    "sg:province":"A Coru\u00f1a",
    "wof:name":"Seren Castro Angel",
    "wof:placetype":"venue"
},
  "geometry": {"coordinates":[-8.4027147293,43.377117157],"type":"Point"}
}