{
  "type": "Feature",
  "properties": {
    "addr:full":"Calle de Ventura Rodriguez, 2 Arenas San Pedro \u00c1vila 05400",
    "addr:housenumber":"2",
    "addr:postcode":"05400",
    "addr:street":"Calle De Ventura Rodriguez;A\u0301Vila",
    "iso:country":"ES",
    "sg:address":"Calle de Ventura Rodriguez, 2",
    "sg:city":"Arenas San Pedro",
    "sg:orig_category":"Promotores Constructores",
    "sg:phone":"+34 920 37 11 63",
    "sg:postcode":"05400",
    "sg:province":"\u00c1vila",
    "wof:name":"Mimas Y Tanit S.l.",
    "wof:placetype":"venue"
},
  "geometry": {"coordinates":[-5.088078022,40.2127418518],"type":"Point"}
}