{
  "type": "Feature",
  "properties": {
    "addr:full":"Plaz Madera (la), 1 Santa Maria Del Paramo Le\u00f3n 24240",
    "addr:housenumber":"1",
    "addr:postcode":"24240",
    "addr:street":"Plaz Madera La",
    "iso:country":"ES",
    "sg:address":"Plaz Madera (la), 1",
    "sg:city":"Santa Maria Del Paramo",
    "sg:orig_category":"M\u00c9dicos: Estomatolog\u00cda",
    "sg:phone":"+34 987 35 09 06",
    "sg:postcode":"24240",
    "sg:province":"Le\u00f3n",
    "sg:website":"www.paginasamarillas.es",
    "wof:name":"Montas Pimentel Moises",
    "wof:placetype":"venue"
},
  "geometry": {"coordinates":[-5.7474999428,42.3531570435],"type":"Point"}
}