{
  "type": "Feature",
  "properties": {
    "addr:full":"Calle de San Francisco, 21 Cadiz C\u00e1diz 11004",
    "addr:housenumber":"21",
    "addr:postcode":"11004",
    "addr:street":"Calle De San Francisco",
    "iso:country":"ES",
    "sg:address":"Calle de San Francisco, 21",
    "sg:city":"Cadiz",
    "sg:orig_category":"Art\u00cdculos De Regalo (al Por Menor)",
    "sg:phone":"+34 956 22 27 35",
    "sg:postcode":"11004",
    "sg:province":"C\u00e1diz",
    "wof:name":"Sanchez Villegas Pilar",
    "wof:placetype":"venue"
},
  "geometry": {"coordinates":[-6.2942080498,36.5325012207],"type":"Point"}
}