{
  "type": "Feature",
  "properties": {
    "iso:country":"ES",
    "sg:address":"Carr Alcalde Pere Rovira, 8",
    "sg:city":"Sant Joan De Les Abadesses",
    "sg:orig_category":"Bisuter\u00cda, Joyer\u00cda, Relojer\u00cda (al Por Menor)",
    "sg:phone":"+34 972 72 01 32",
    "sg:postcode":"17860",
    "sg:province":"Girona",
    "wof:name":"Rellotgeria Casademunt",
    "wof:placetype":"venue"
},
  "geometry": {"coordinates":[2.2861940861,42.2335548401],"type":"Point"}
}