{
  "type": "Feature",
  "properties": {
    "addr:full":"Plaz General Gimenez Salas, 2 Segorbe Castell\u00f3n 12400",
    "addr:housenumber":"2",
    "addr:postcode":"12400",
    "addr:street":"Salas",
    "iso:country":"ES",
    "sg:address":"Plaz General Gimenez Salas, 2",
    "sg:city":"Segorbe",
    "sg:orig_category":"Seguros",
    "sg:phone":"+34 964 71 36 36",
    "sg:postcode":"12400",
    "sg:province":"Castell\u00f3n",
    "wof:name":"Mutua Segorbina De Seguros A Prima Fija",
    "wof:placetype":"venue"
},
  "geometry": {"coordinates":[-0.4885739982,39.8518714905],"type":"Point"}
}