{
  "type": "Feature",
  "properties": {
    "iso:country":"ES",
    "sg:address":"Calle de Cromo, S/n",
    "sg:city":"Valladolid",
    "sg:orig_category":"Carnes De Carnicer\u00cda (al Por Mayor)",
    "sg:phone":"+34 983 39 84 66",
    "sg:postcode":"47012",
    "sg:province":"Valladolid",
    "wof:name":"Carnicas Pisuerga S.a.",
    "wof:placetype":"venue"
},
  "geometry": {"coordinates":[-4.706551075,41.6261901855],"type":"Point"}
}