{
  "type": "Feature",
  "properties": {
    "addr:full":"Cra. Costa Brava, Km. 0002,0 Palafolls Barcelona 08389",
    "addr:postcode":"08389",
    "addr:street":"Brava Km. 0002,0",
    "iso:country":"ES",
    "sg:address":"Cra. Costa Brava, Km. 0002,0",
    "sg:city":"Palafolls",
    "sg:orig_category":"Goma: Materias Primas (producci\u00d3n, Distribuci\u00d3n)",
    "sg:phone":"+34 937 65 26 30",
    "sg:postcode":"08389",
    "sg:province":"Barcelona",
    "sg:website":"www.polysack.com",
    "wof:name":"Polysack Europa S.l.",
    "wof:placetype":"venue"
},
  "geometry": {"coordinates":[2.7497739792,41.6659660339],"type":"Point"}
}