{
  "type": "Feature",
  "properties": {
    "iso:country":"ES",
    "sg:address":"Calle de Margarita De Pedroso, S/n",
    "sg:city":"Brihuega",
    "sg:orig_category":"T\u00c9cnicos Veterinarios",
    "sg:phone":"+34 949 28 11 82",
    "sg:postcode":"19400",
    "sg:province":"Guadalajara",
    "wof:name":"Ayuntamiento De Brihuega",
    "wof:placetype":"venue"
},
  "geometry": {"coordinates":[-2.8776638508,40.7409095764],"type":"Point"}
}