{
  "type": "Feature",
  "properties": {
    "iso:country":"ES",
    "sg:address":"Calle de Llanos, 8",
    "sg:city":"Pantoja",
    "sg:orig_category":"Mec\u00c1nico Del Autom\u00d3vil",
    "sg:phone":"+34 925 55 41 86",
    "sg:postcode":"45290",
    "sg:province":"Toledo",
    "wof:name":"Manzanedo Gonzalez Eduardo",
    "wof:placetype":"venue"
},
  "geometry": {"coordinates":[-3.8347835541,40.0495986938],"type":"Point"}
}