{
  "type": "Feature",
  "properties": {
    "iso:country":"ES",
    "sg:address":"C/ Antonio Mora Ferrandez, 62",
    "sg:city":"Elche",
    "sg:orig_category":"Venta, Localizaci\u00d3n, Reparaci\u00d3n De Material E Instrumental M\u00c9dico",
    "sg:phone":"+34 965 42 37 53",
    "sg:postcode":"03202",
    "sg:province":"Alicante",
    "wof:name":"A.g.s. Hospitalaria S.l.",
    "wof:placetype":"venue"
},
  "geometry": {"coordinates":[-0.6781944036,38.2732849121],"type":"Point"}
}