{
  "type": "Feature",
  "properties": {
    "addr:full":"Calle de Pi Y Margall, 2 Palmas De Gran Canaria Las Palmas 35006",
    "addr:housenumber":"2",
    "addr:postcode":"35006",
    "addr:street":"Calle De Pi Y Margall",
    "iso:country":"ES",
    "sg:address":"Calle de Pi Y Margall, 2",
    "sg:city":"Palmas De Gran Canaria",
    "sg:orig_category":"Organizaciones Internacionales",
    "sg:phone":"+34 928 24 08 84",
    "sg:postcode":"35006",
    "sg:province":"Las Palmas",
    "wof:name":"Asociacion Canaria De Solidaridad Con El Pueblo Saharaui",
    "wof:placetype":"venue"
},
  "geometry": {"coordinates":[-15.430267334,28.132484436],"type":"Point"}
}