{
  "type": "Feature",
  "properties": {
    "addr:full":"C/ Severo Ochoa, 40 Torrellano Alicante 03320",
    "addr:housenumber":"40",
    "addr:postcode":"03320",
    "addr:street":"C / Severo Ochoa",
    "iso:country":"ES",
    "sg:address":"C/ Severo Ochoa, 40",
    "sg:city":"Torrellano",
    "sg:orig_category":"Confecci\u00d3n De Zapatos",
    "sg:phone":"+34 965 68 59 85",
    "sg:postcode":"03320",
    "sg:province":"Alicante",
    "wof:name":"Calzados Bartisolo S.l.",
    "wof:placetype":"venue"
},
  "geometry": {"coordinates":[-0.5883839726,38.2929649353],"type":"Point"}
}