{
  "type": "Feature",
  "properties": {
    "iso:country":"ES",
    "sg:address":"Carrer de Milanesat, 32",
    "sg:city":"Barcelona",
    "sg:orig_category":"Perfumer\u00cda Y Cosm\u00c9tica (fabricaci\u00d3n, Al Por Mayor)",
    "sg:phone":"+34 932 03 56 34",
    "sg:postcode":"08017",
    "sg:province":"Barcelona",
    "wof:name":"Gili S. L.",
    "wof:placetype":"venue"
},
  "geometry": {"coordinates":[2.1307311058,41.3982276917],"type":"Point"}
}