{
  "type": "Feature",
  "properties": {
    "addr:full":"Urb Calders, 13 Vallmoll Tarragona 43144",
    "addr:housenumber":"13",
    "addr:postcode":"43144",
    "addr:street":"Urb Calders",
    "iso:country":"ES",
    "sg:address":"Urb Calders, 13",
    "sg:city":"Vallmoll",
    "sg:orig_category":"Fabricaci\u00d3n De Productos Textiles Sin Tejer",
    "sg:phone":"+34 977 60 06 93",
    "sg:postcode":"43144",
    "sg:province":"Tarragona",
    "wof:name":"Plana Aguade Joan",
    "wof:placetype":"venue"
},
  "geometry": {"coordinates":[1.249235034,41.2438163757],"type":"Point"}
}