{
  "type": "Feature",
  "properties": {
    "iso:country":"ES",
    "sg:address":"Calle de Sor Livia Alcorta, 12",
    "sg:city":"Illescas",
    "sg:orig_category":"Peluquer\u00cdas, Peluquer\u00cda Mixta",
    "sg:phone":"+34 925 51 10 07",
    "sg:postcode":"45200",
    "sg:province":"Toledo",
    "wof:name":"Maxfinancial, S.l.",
    "wof:placetype":"venue"
},
  "geometry": {"coordinates":[-3.8464090824,40.1239318848],"type":"Point"}
}