{
  "type": "Feature",
  "properties": {
    "addr:full":"Av Catalunya, S/n Alcoletge Lleida 25660",
    "addr:housenumber":"s / n",
    "addr:postcode":"25660",
    "addr:street":"Av Catalunya",
    "iso:country":"ES",
    "sg:address":"Av Catalunya, S/n",
    "sg:city":"Alcoletge",
    "sg:orig_category":"Fabricaci\u00d3n De Equipos Y Piezas Para Veh\u00cdculos, Veh\u00cdculos Industriales",
    "sg:phone":"+34 973 19 71 54",
    "sg:postcode":"25660",
    "sg:province":"Lleida",
    "sg:website":"www.iresa-web.com",
    "wof:name":"Iresa S.l.",
    "wof:placetype":"venue"
},
  "geometry": {"coordinates":[0.6932650208,41.6500549316],"type":"Point"}
}