{
  "type": "Feature",
  "properties": {
    "iso:country":"ES",
    "sg:address":"Rond San Francisco, 5",
    "sg:city":"Almazan",
    "sg:orig_category":"Mercer\u00cda, Lencer\u00cda (al Por Menor)",
    "sg:phone":"+34 975 30 19 72",
    "sg:postcode":"42200",
    "sg:province":"Soria",
    "wof:name":"Andres Garcia Maria Victoria",
    "wof:placetype":"venue"
},
  "geometry": {"coordinates":[-2.5280570984,41.487071991],"type":"Point"}
}