{
  "type": "Feature",
  "properties": {
    "iso:country":"ES",
    "sg:address":"Can Gelats, S/n",
    "sg:city":"Campllong",
    "sg:orig_category":"Comercio De Piezas De Recambio Y De Accesorios De Veh\u00cdculos, Veh\u00cdculos Industriales",
    "sg:phone":"+34 972 46 13 81",
    "sg:postcode":"17457",
    "sg:province":"Girona",
    "wof:name":"Clavero Baena Maria Josefa",
    "wof:placetype":"venue"
},
  "geometry": {"coordinates":[2.8040299416,41.8944282532],"type":"Point"}
}