{
  "type": "Feature",
  "properties": {
    "iso:country":"ES",
    "sg:address":"Calle de Elkano, 6",
    "sg:city":"Donostia-san Sebastian",
    "sg:orig_category":"Inmobiliaria (agencias)",
    "sg:phone":"+34 943 42 28 24",
    "sg:postcode":"20004",
    "sg:province":"Guip\u00f9zcoa",
    "wof:name":"Agencia Inmobiliaria Metropoli",
    "wof:placetype":"venue"
},
  "geometry": {"coordinates":[-1.9831655025,43.321723938],"type":"Point"}
}