{
  "type": "Feature",
  "properties": {
    "iso:country":"ES",
    "sg:address":"Ctra Fuengirola Mijas, Km. 0003,0",
    "sg:city":"Mijas",
    "sg:orig_category":"Carnicer\u00cdas, Carnicer\u00cdas",
    "sg:phone":"+34 952 59 08 84",
    "sg:postcode":"29650",
    "sg:province":"M\u00e1laga",
    "wof:name":"Oca\u00f1a Huercano Agustin",
    "wof:placetype":"venue"
},
  "geometry": {"coordinates":[-4.6364178658,36.5977363586],"type":"Point"}
}