{
  "type": "Feature",
  "properties": {
    "addr:full":"Calle de Infanzones De Langreo, S/n Langreo Asturias 33900",
    "addr:housenumber":"s / n",
    "addr:postcode":"33900",
    "addr:street":"Calle De Infanzones De Langreo",
    "iso:country":"ES",
    "sg:address":"Calle de Infanzones De Langreo, S/n",
    "sg:city":"Langreo",
    "sg:orig_category":"Sanatorios M\u00c9dico",
    "sg:phone":"+34 985 67 49 11",
    "sg:postcode":"33900",
    "sg:province":"Asturias",
    "wof:name":"Insalud-atencion Primaria Viii-ambulatorio Sama De Langreo",
    "wof:placetype":"venue"
},
  "geometry": {"coordinates":[-5.6687488556,43.2891159058],"type":"Point"}
}