{
  "type": "Feature",
  "properties": {
    "iso:country":"ES",
    "sg:address":"P Sarasate, 34",
    "sg:city":"Iru\u00f1a",
    "sg:orig_category":"Abogados",
    "sg:phone":"+34 948 22 54 00",
    "sg:postcode":"31001",
    "sg:province":"Navarra",
    "wof:name":"Arbeloa Iriarte Miguel Angel",
    "wof:placetype":"venue"
},
  "geometry": {"coordinates":[-1.6464419365,42.8150787354],"type":"Point"}
}