{
  "type": "Feature",
  "properties": {
    "addr:full":"Urb Motilla, 54 Dos Hermanas Sevilla 41700",
    "addr:housenumber":"54",
    "addr:postcode":"41700",
    "addr:street":"Motilla",
    "iso:country":"ES",
    "sg:address":"Urb Motilla, 54",
    "sg:city":"Dos Hermanas",
    "sg:orig_category":"Farmacias",
    "sg:phone":"+34 954 72 87 04",
    "sg:postcode":"41700",
    "sg:province":"Sevilla",
    "wof:name":"Turmo Fernandez Pilar",
    "wof:placetype":"venue"
},
  "geometry": {"coordinates":[-5.9281339645,37.2829055786],"type":"Point"}
}