{
  "type": "Feature",
  "properties": {
    "iso:country":"ES",
    "sg:address":"Calle de Pinar, 7",
    "sg:city":"Irun",
    "sg:orig_category":"Librer\u00cdas",
    "sg:phone":"+34 943 61 92 85",
    "sg:postcode":"20301",
    "sg:province":"Guip\u00f9zcoa",
    "wof:name":"Blasco Duque Lara",
    "wof:placetype":"venue"
},
  "geometry": {"coordinates":[-1.7997469902,43.3436508179],"type":"Point"}
}