{
  "type": "Feature",
  "properties": {
    "iso:country":"ES",
    "sg:address":"Carrer de Sant Blai, 5",
    "sg:city":"Manresa",
    "sg:orig_category":"Reposter\u00cdas",
    "sg:phone":"+34 938 73 36 07",
    "sg:postcode":"08241",
    "sg:province":"Barcelona",
    "wof:name":"Forn Sirera S.c.p.",
    "wof:placetype":"venue"
},
  "geometry": {"coordinates":[1.8388390541,41.723400116],"type":"Point"}
}