{
  "type": "Feature",
  "properties": {
    "addr:full":"Rua Calvo Sotelo, 84 Sarria Lugo 27600",
    "addr:housenumber":"84",
    "addr:postcode":"27600",
    "addr:street":"Rua Calvo Sotelo",
    "iso:country":"ES",
    "sg:address":"Rua Calvo Sotelo, 84",
    "sg:city":"Sarria",
    "sg:orig_category":"Bancos",
    "sg:phone":"+34 982 53 24 93",
    "sg:postcode":"27600",
    "sg:province":"Lugo",
    "sg:website":"www.bancosimeon.es",
    "wof:name":"Banco Caixa Geral S.a.",
    "wof:placetype":"venue"
},
  "geometry": {"coordinates":[-7.4125890732,42.7799110413],"type":"Point"}
}