{
  "type": "Feature",
  "properties": {
    "iso:country":"ES",
    "sg:address":"Avda Gran Via Rey Juan Carlos I, 29",
    "sg:city":"Logro\u00f1o",
    "sg:orig_category":"Electricidad (montaje, Ensamblaje De Componentes)",
    "sg:phone":"+34 941 24 47 04",
    "sg:postcode":"26002",
    "sg:province":"La Rioja",
    "wof:name":"Garcia Gomez Maria Luisa",
    "wof:placetype":"venue"
},
  "geometry": {"coordinates":[-2.4490029812,42.4635505676],"type":"Point"}
}