{
  "type": "Feature",
  "properties": {
    "addr:full":"Calle de Antonio Machado, 8 Macael Almer\u00eda 04867",
    "addr:housenumber":"8",
    "addr:postcode":"04867",
    "addr:street":"Calle De Antonio Machado",
    "iso:country":"ES",
    "sg:address":"Calle de Antonio Machado, 8",
    "sg:city":"Macael",
    "sg:orig_category":"Bisuter\u00cda, Joyer\u00cda, Relojer\u00cda (al Por Menor)",
    "sg:phone":"+34 950 44 54 26",
    "sg:postcode":"04867",
    "sg:province":"Almer\u00eda",
    "wof:name":"Martinez Navarro Antonio",
    "wof:placetype":"venue"
},
  "geometry": {"coordinates":[-2.3046693802,37.3321647644],"type":"Point"}
}