{
  "type": "Feature",
  "properties": {
    "iso:country":"ES",
    "sg:address":"Alam Principal, 35",
    "sg:city":"Malaga",
    "sg:orig_category":"Electrodom\u00c9sticos (al Por Menor)",
    "sg:phone":"+34 952 21 07 12",
    "sg:postcode":"29001",
    "sg:province":"M\u00e1laga",
    "wof:name":"Ruiz Fernandez Joaquin",
    "wof:placetype":"venue"
},
  "geometry": {"coordinates":[-4.423968792,36.7169113159],"type":"Point"}
}