{
  "type": "Feature",
  "properties": {
    "addr:full":"Calle de Pintor Vilar, 4 Valencia Valencia 46010",
    "addr:housenumber":"4",
    "addr:postcode":"46010",
    "addr:street":"Calle De Pintor Vilar",
    "iso:country":"ES",
    "sg:address":"Calle de Pintor Vilar, 4",
    "sg:city":"Valencia",
    "sg:orig_category":"M\u00c9dicos: Pediatr\u00cda. Enfermedades De Los Ni\u00d1os",
    "sg:phone":"+34 963 89 15 58",
    "sg:postcode":"46010",
    "sg:province":"Valencia",
    "wof:name":"Reyes Aibar Miguel",
    "wof:placetype":"venue"
},
  "geometry": {"coordinates":[-0.37203601,39.4822883606],"type":"Point"}
}