{
  "type": "Feature",
  "properties": {
    "iso:country":"ES",
    "sg:address":"Calle de Huertas (las), 5",
    "sg:city":"Santo\u00f1a",
    "sg:orig_category":"Muebles, Minoristas",
    "sg:phone":"+34 942 66 10 58",
    "sg:postcode":"39740",
    "sg:province":"Cantabria",
    "wof:name":"Olavarrieta Redondo Carlos",
    "wof:placetype":"venue"
},
  "geometry": {"coordinates":[-3.4538838863,43.4431838989],"type":"Point"}
}