{
  "type": "Feature",
  "properties": {
    "iso:country":"ES",
    "sg:address":"Finca Casa Avelina, S/n",
    "sg:city":"Tinajeros",
    "sg:orig_category":"Producci\u00d3n, Venta De Productos De Agricultura Biol\u00d3gica",
    "sg:phone":"+34 967 58 05 20",
    "sg:postcode":"02155",
    "sg:province":"Albacete",
    "wof:name":"Agricola Villa Avelina S.l.",
    "wof:placetype":"venue"
},
  "geometry": {"coordinates":[-1.7438440323,39.0690307617],"type":"Point"}
}