{
  "type": "Feature",
  "properties": {
    "addr:full":"Ctra Torregrossa, Km. 0002,0 Mollerussa Lleida 25230",
    "addr:postcode":"25230",
    "addr:street":"Ctra Torregrossa Km. 0002,0",
    "iso:country":"ES",
    "sg:address":"Ctra Torregrossa, Km. 0002,0",
    "sg:city":"Mollerussa",
    "sg:orig_category":"Almacenes Frigor\u00cdficos",
    "sg:phone":"+34 973 71 13 40",
    "sg:postcode":"25230",
    "sg:province":"Lleida",
    "wof:name":"Maimo Domingo Javier",
    "wof:placetype":"venue"
},
  "geometry": {"coordinates":[0.8882099986,41.6263847351],"type":"Point"}
}