{
  "type": "Feature",
  "properties": {
    "iso:country":"ES",
    "sg:address":"Calle de Ancha, 1",
    "sg:city":"Huetor-tajar",
    "sg:orig_category":"\u00d3ptica: Instrumentos (fabricaci\u00d3n)",
    "sg:phone":"+34 958 33 27 41",
    "sg:postcode":"18360",
    "sg:province":"Granada",
    "wof:name":"Opticas Mayorvision S.l.",
    "wof:placetype":"venue"
},
  "geometry": {"coordinates":[-4.0464839935,37.1950035095],"type":"Point"}
}