{
  "type": "Feature",
  "properties": {
    "addr:full":"Calle de Santo Domingo, 16 Puerto Cruz Santa Cruz De Tenerife 38400",
    "addr:housenumber":"16",
    "addr:postcode":"38400",
    "addr:street":"Calle De Santo Domingo;Puerto Cruz",
    "iso:country":"ES",
    "sg:address":"Calle de Santo Domingo, 16",
    "sg:city":"Puerto Cruz",
    "sg:orig_category":"Fabricaci\u00d3n De Art\u00cdculos Y Equipos Deportivos Y De Ocio",
    "sg:phone":"+34 922 38 20 52",
    "sg:postcode":"38400",
    "sg:province":"Santa Cruz De Tenerife",
    "wof:name":"Alruber",
    "wof:placetype":"venue"
},
  "geometry": {"coordinates":[-16.5481243134,28.4174919128],"type":"Point"}
}