{
  "type": "Feature",
  "properties": {
    "addr:full":"Calle de Mercurio, 3 Arganda Madrid 28500",
    "addr:housenumber":"3",
    "addr:postcode":"28500",
    "addr:street":"Calle De Mercurio",
    "iso:country":"ES",
    "sg:address":"Calle de Mercurio, 3",
    "sg:city":"Arganda",
    "sg:orig_category":"Tratamiento De Metales",
    "sg:phone":"+34 918 71 56 94",
    "sg:postcode":"28500",
    "sg:province":"Madrid",
    "wof:name":"Indugal S.a.",
    "wof:placetype":"venue"
},
  "geometry": {"coordinates":[-3.4672091007,40.3001441956],"type":"Point"}
}