{
  "type": "Feature",
  "properties": {
    "addr:full":"Calle de Regueron, 10 Pobladura Pelayo Garcia Le\u00f3n 24249",
    "addr:housenumber":"10",
    "addr:postcode":"24249",
    "addr:street":"Calle De Regueron;Leo\u0301N",
    "iso:country":"ES",
    "sg:address":"Calle de Regueron, 10",
    "sg:city":"Pobladura Pelayo Garcia",
    "sg:orig_category":"Transportes Por V\u00cdas Navegables",
    "sg:phone":"+34 987 38 41 67",
    "sg:postcode":"24249",
    "sg:province":"Le\u00f3n",
    "wof:name":"Transportes Anerul S.l.",
    "wof:placetype":"venue"
},
  "geometry": {"coordinates":[-5.6835098267,42.3096656799],"type":"Point"}
}