{
  "type": "Feature",
  "properties": {
    "addr:full":"Orfebreria, 22 Palau-solita Plegamans Barcelona 08184",
    "addr:housenumber":"22",
    "addr:postcode":"08184",
    "addr:street":"Orfebreria",
    "iso:country":"ES",
    "sg:address":"Orfebreria, 22",
    "sg:city":"Palau-solita Plegamans",
    "sg:orig_category":"Extinci\u00d3n De Incendios: Material Y Suministros (fabricaci\u00d3n, Al Por Mayor)",
    "sg:phone":"+34 938 63 96 22",
    "sg:postcode":"08184",
    "sg:province":"Barcelona",
    "wof:name":"Extin-llama S.l.",
    "wof:placetype":"venue"
},
  "geometry": {"coordinates":[2.178137064,41.5713233948],"type":"Point"}
}