{
  "type": "Feature",
  "properties": {
    "iso:country":"ES",
    "sg:address":"Avda Arias Maldonado, S/n",
    "sg:city":"Marbella",
    "sg:orig_category":"Fotograf\u00cda Art\u00cdstica Y Retratos",
    "sg:phone":"+34 952 77 55 42",
    "sg:postcode":"29600",
    "sg:province":"M\u00e1laga",
    "wof:name":"Lanza Fernandez Andres",
    "wof:placetype":"venue"
},
  "geometry": {"coordinates":[-4.8926091194,36.5074005127],"type":"Point"}
}