{
  "type": "Feature",
  "properties": {
    "iso:country":"ES",
    "sg:address":"Calle de Aire (del), 30",
    "sg:city":"Cartagena",
    "sg:orig_category":"Asociaciones, Organismos Culturales Y Socioeducativos",
    "sg:phone":"+34 968 50 20 39",
    "sg:postcode":"30202",
    "sg:province":"Murcia",
    "wof:name":"Cofradia California",
    "wof:placetype":"venue"
},
  "geometry": {"coordinates":[-0.9989169836,37.6317214966],"type":"Point"}
}