{
  "type": "Feature",
  "properties": {
    "addr:full":"Calle de Padre Angel, 13 S. Vicente Barquera Cantabria 39540",
    "addr:housenumber":"13",
    "addr:postcode":"39540",
    "addr:street":"Calle De Padre Angel;S. Vicente",
    "iso:country":"ES",
    "sg:address":"Calle de Padre Angel, 13",
    "sg:city":"S. Vicente Barquera",
    "sg:orig_category":"Abogados",
    "sg:phone":"+34 942 71 10 74",
    "sg:postcode":"39540",
    "sg:province":"Cantabria",
    "wof:name":"Gonzalez Gonzalez Maria Antonia",
    "wof:placetype":"venue"
},
  "geometry": {"coordinates":[-4.3981161118,43.3821601868],"type":"Point"}
}