{
  "type": "Feature",
  "properties": {
    "iso:country":"ES",
    "sg:address":"Carrer de Sant Casimir, 9",
    "sg:city":"S. Cugat Valles",
    "sg:orig_category":"Promotores Constructores",
    "sg:phone":"+34 936 75 92 32",
    "sg:postcode":"08172",
    "sg:province":"Barcelona",
    "wof:name":"Edial S. A.",
    "wof:placetype":"venue"
},
  "geometry": {"coordinates":[2.0842399597,41.4679336548],"type":"Point"}
}