{
  "type": "Feature",
  "properties": {
    "iso:country":"ES",
    "sg:address":"Pase Antonio Gala (de), 18",
    "sg:city":"Adamuz",
    "sg:orig_category":"Bares, Piano",
    "sg:phone":"+34 957 16 62 26",
    "sg:postcode":"14430",
    "sg:province":"C\u00f3rdoba",
    "wof:name":"Cuadrado Amil Maria",
    "wof:placetype":"venue"
},
  "geometry": {"coordinates":[-4.5193319321,38.0255393982],"type":"Point"}
}