{
  "type": "Feature",
  "properties": {
    "addr:full":"Calle de Union, 1 Castellon Castell\u00f3n 12004",
    "addr:housenumber":"1",
    "addr:postcode":"12004",
    "addr:street":"Calle De Union;Castello\u0301N",
    "iso:country":"ES",
    "sg:address":"Calle de Union, 1",
    "sg:city":"Castellon",
    "sg:orig_category":"Laboratorios Y Cl\u00cdnicas Veterinarias",
    "sg:phone":"+34 964 21 53 06",
    "sg:postcode":"12004",
    "sg:province":"Castell\u00f3n",
    "wof:name":"Puchol Porcar Rosario",
    "wof:placetype":"venue"
},
  "geometry": {"coordinates":[-0.0475130007,39.9892272949],"type":"Point"}
}