{
  "type": "Feature",
  "properties": {
    "iso:country":"ES",
    "sg:address":"Carrer de Bruc, 10",
    "sg:city":"Ametlla Valles",
    "sg:orig_category":"Importaci\u00d3n",
    "sg:phone":"+34 938 43 09 93",
    "sg:postcode":"08480",
    "sg:province":"Barcelona",
    "wof:name":"Progalvano Espa\u00d1ola S.l.",
    "wof:placetype":"venue"
},
  "geometry": {"coordinates":[2.2650399208,41.6646308899],"type":"Point"}
}