{
  "type": "Feature",
  "properties": {
    "addr:full":"Carrer de Merceria (de La), 25 Tarragona Tarragona 43003",
    "addr:housenumber":"25",
    "addr:postcode":"43003",
    "addr:street":"Carrer De Merceria De La",
    "iso:country":"ES",
    "sg:address":"Carrer de Merceria (de La), 25",
    "sg:city":"Tarragona",
    "sg:orig_category":"Carnicer\u00cdas, Carnicer\u00cdas",
    "sg:phone":"+34 977 23 31 34",
    "sg:postcode":"43003",
    "sg:province":"Tarragona",
    "wof:name":"Guivernau Queralt Jose",
    "wof:placetype":"venue"
},
  "geometry": {"coordinates":[1.2585229874,41.1178703308],"type":"Point"}
}