{
  "type": "Feature",
  "properties": {
    "addr:full":"Plaz Felix Saenz, 7 Malaga M\u00e1laga 29005",
    "addr:housenumber":"7",
    "addr:postcode":"29005",
    "addr:street":"Plaz Felix Saenz;Ma\u0301Laga",
    "iso:country":"ES",
    "sg:address":"Plaz Felix Saenz, 7",
    "sg:city":"Malaga",
    "sg:orig_category":"Comerciantes Al Por Mayor De Vinos, Licores Y Alcoholes",
    "sg:phone":"+34 952 22 32 17",
    "sg:postcode":"29005",
    "sg:province":"M\u00e1laga",
    "wof:name":"Palma Medina Belen",
    "wof:placetype":"venue"
},
  "geometry": {"coordinates":[-4.4232649803,36.7192611694],"type":"Point"}
}