{
  "type": "Feature",
  "properties": {
    "addr:full":"Rua Barrancon, S/n Becerrea Lugo 27640",
    "addr:housenumber":"s",
    "addr:postcode":"27640",
    "addr:street":"Rua Barrancon;/ N",
    "iso:country":"ES",
    "sg:address":"Rua Barrancon, S/n",
    "sg:city":"Becerrea",
    "sg:orig_category":"Mec\u00c1nico Del Autom\u00d3vil",
    "sg:phone":"+34 982 36 04 55",
    "sg:postcode":"27640",
    "sg:province":"Lugo",
    "wof:name":"Talleres Jose Maria Diaz S.l.",
    "wof:placetype":"venue"
},
  "geometry": {"coordinates":[-7.1622071266,42.8534240723],"type":"Point"}
}