{
  "type": "Feature",
  "properties": {
    "addr:full":"Villafranca, 11 Iru\u00f1a Navarra 31015",
    "addr:housenumber":"11",
    "addr:postcode":"31015",
    "addr:street":"Villafranca",
    "iso:country":"ES",
    "sg:address":"Villafranca, 11",
    "sg:city":"Iru\u00f1a",
    "sg:orig_category":"Metalurgia",
    "sg:phone":"+34 948 12 79 14",
    "sg:postcode":"31015",
    "sg:province":"Navarra",
    "wof:name":"Velasco Delgado Amador",
    "wof:placetype":"venue"
},
  "geometry": {"coordinates":[-1.6313489676,42.8328895569],"type":"Point"}
}