{
  "type": "Feature",
  "properties": {
    "addr:full":"Calle de Peru, 49 Bormujos Sevilla 41930",
    "addr:housenumber":"49",
    "addr:postcode":"41930",
    "addr:street":"Calle De Peru",
    "iso:country":"ES",
    "sg:address":"Calle de Peru, 49",
    "sg:city":"Bormujos",
    "sg:orig_category":"Arquitectos",
    "sg:phone":"+34 955 72 35 94",
    "sg:postcode":"41930",
    "sg:province":"Sevilla",
    "wof:name":"Arquitectos Raul Nu\u00f1ez Sl",
    "wof:placetype":"venue"
},
  "geometry": {"coordinates":[-6.0782575607,37.3752365112],"type":"Point"}
}