{
  "type": "Feature",
  "properties": {
    "addr:full":"Calle de Jose De Ribera, 5 Ciudad Real Ciudad Real 13002",
    "addr:housenumber":"5",
    "addr:postcode":"13002",
    "addr:street":"Calle De Jose De Ribera",
    "iso:country":"ES",
    "sg:address":"Calle de Jose De Ribera, 5",
    "sg:city":"Ciudad Real",
    "sg:orig_category":"Agencias Y Asesores De Publicidad",
    "sg:phone":"+34 926 21 21 07",
    "sg:postcode":"13002",
    "sg:province":"Ciudad Real",
    "wof:name":"Medina Espinosa Mariela Eugenia",
    "wof:placetype":"venue"
},
  "geometry": {"coordinates":[-3.9382200241,38.9825057983],"type":"Point"}
}