{
  "type": "Feature",
  "properties": {
    "addr:full":"Avda San Sebastian, 8 Malaga M\u00e1laga 29010",
    "addr:housenumber":"8",
    "addr:postcode":"29010",
    "addr:street":"Avda San Sebastian;Ma\u0301Laga",
    "iso:country":"ES",
    "sg:address":"Avda San Sebastian, 8",
    "sg:city":"Malaga",
    "sg:orig_category":"Inmobiliaria (agencias)",
    "sg:phone":"+34 952 39 51 09",
    "sg:postcode":"29010",
    "sg:province":"M\u00e1laga",
    "wof:name":"Estudio Nueva Malaga S.l.",
    "wof:placetype":"venue"
},
  "geometry": {"coordinates":[-4.436645031,36.7231826782],"type":"Point"}
}