{
  "type": "Feature",
  "properties": {
    "addr:full":"Erguin Kalea, 1 Arrasate Guip\u00f9zcoa 20500",
    "addr:housenumber":"1",
    "addr:postcode":"20500",
    "addr:street":"Erguin Kalea;Guipu\u0300Zcoa",
    "iso:country":"ES",
    "sg:address":"Erguin Kalea, 1",
    "sg:city":"Arrasate",
    "sg:orig_category":"Audiovisuales (producci\u00d3n, Edici\u00d3n, Realizaci\u00d3n)",
    "sg:phone":"+34 943 79 01 83",
    "sg:postcode":"20500",
    "sg:province":"Guip\u00f9zcoa",
    "wof:name":"Dragoi Produkzioak , S.l",
    "wof:placetype":"venue"
},
  "geometry": {"coordinates":[-2.4973430634,43.063495636],"type":"Point"}
}