{
  "type": "Feature",
  "properties": {
    "iso:country":"ES",
    "sg:address":"Calle de San Roque, 19",
    "sg:city":"Santo Domingo De La Calzada",
    "sg:orig_category":"Bancos",
    "sg:phone":"+34 941 34 00 31",
    "sg:postcode":"26250",
    "sg:province":"La Rioja",
    "sg:website":"www.bancozaragozano.es",
    "wof:name":"Barclays Bank S.a.e.",
    "wof:placetype":"venue"
},
  "geometry": {"coordinates":[-2.9510800838,42.4394035339],"type":"Point"}
}