{
  "type": "Feature",
  "properties": {
    "addr:full":"Cachafeiro, 2 Forcarei Pontevedra 36559",
    "addr:housenumber":"2",
    "addr:postcode":"36559",
    "addr:street":"Cachafeiro",
    "iso:country":"ES",
    "sg:address":"Cachafeiro, 2",
    "sg:city":"Forcarei",
    "sg:orig_category":"Mec\u00c1nico Del Autom\u00d3vil",
    "sg:phone":"+34 986 75 52 40",
    "sg:postcode":"36559",
    "sg:province":"Pontevedra",
    "wof:name":"Talleres Nu\u00f1ez San Martin S.c.",
    "wof:placetype":"venue"
},
  "geometry": {"coordinates":[-8.3382253647,42.5734405518],"type":"Point"}
}