{
  "type": "Feature",
  "properties": {
    "addr:full":"Pl Vila, 15 Santa Coloma De Gramenet Barcelona 08921",
    "addr:housenumber":"15",
    "addr:postcode":"08921",
    "addr:street":"Pl Vila",
    "iso:country":"ES",
    "sg:address":"Pl Vila, 15",
    "sg:city":"Santa Coloma De Gramenet",
    "sg:orig_category":"Centros M\u00c9dicos Y Sociales, Dispensarios",
    "sg:phone":"+34 934 66 24 44",
    "sg:postcode":"08921",
    "sg:province":"Barcelona",
    "wof:name":"Centre Medic Sant Ramon S.l.",
    "wof:placetype":"venue"
},
  "geometry": {"coordinates":[2.2090559006,41.4513282776],"type":"Point"}
}