{
  "type": "Feature",
  "properties": {
    "iso:country":"ES",
    "sg:address":"Calle de Carlos Martin Alvarez (de), 6",
    "sg:city":"Alalpardo",
    "sg:orig_category":"Administraciones Regionales, Departamentales Y Locales",
    "sg:phone":"+34 916 20 26 65",
    "sg:postcode":"28130",
    "sg:province":"Madrid",
    "wof:name":"Ayuntamiento De Valdeolmos",
    "wof:placetype":"venue"
},
  "geometry": {"coordinates":[-3.4753870964,40.6289901733],"type":"Point"}
}