{
  "type": "Feature",
  "properties": {
    "addr:full":"Calle de Estacion, 25 Villarrobledo Albacete 02600",
    "addr:housenumber":"25",
    "addr:postcode":"02600",
    "addr:street":"Calle De Estacion",
    "iso:country":"ES",
    "sg:address":"Calle de Estacion, 25",
    "sg:city":"Villarrobledo",
    "sg:orig_category":"Abogados",
    "sg:phone":"+34 967 14 64 64",
    "sg:postcode":"02600",
    "sg:province":"Albacete",
    "wof:name":"Aboart Asesores S.l.",
    "wof:placetype":"venue"
},
  "geometry": {"coordinates":[-2.602649,39.262177],"type":"Point"}
}