{
  "type": "Feature",
  "properties": {
    "iso:country":"ES",
    "sg:address":"Ctra Brazatortas, S/n",
    "sg:city":"Cabezarrubias Del Puerto",
    "sg:orig_category":"Agricultura: Abastecimiento Y Cosechado (negocio)",
    "sg:phone":"+34 926 69 83 77",
    "sg:postcode":"13591",
    "sg:province":"Ciudad Real",
    "wof:name":"Antonio Manuel Morales Moreno Y Maria Nieves Bustamante Amunategui (c.b. Omega",
    "wof:placetype":"venue"
},
  "geometry": {"coordinates":[-4.2435894012,38.5658035278],"type":"Point"}
}