{
  "type": "Feature",
  "properties": {
    "addr:full":"Calle de Murillo, 31 Moron Frontera Sevilla 41530",
    "addr:housenumber":"31",
    "addr:postcode":"41530",
    "addr:street":"Calle De Murillo",
    "iso:country":"ES",
    "sg:address":"Calle de Murillo, 31",
    "sg:city":"Moron Frontera",
    "sg:orig_category":"Persianas Interiores, Exteriores",
    "sg:phone":"+34 955 85 29 10",
    "sg:postcode":"41530",
    "sg:province":"Sevilla",
    "wof:name":"Cantero Candil Juan Antonio",
    "wof:placetype":"venue"
},
  "geometry": {"coordinates":[-5.4528231621,37.1294212341],"type":"Point"}
}