{
  "type": "Feature",
  "properties": {
    "iso:country":"ES",
    "sg:address":"El Greco, 32",
    "sg:city":"Lebrija",
    "sg:orig_category":"Alquiler De V\u00cddeo",
    "sg:phone":"+34 955 97 09 93",
    "sg:postcode":"41740",
    "sg:province":"Sevilla",
    "wof:name":"Acuario, Ocio Ytiempo Libre S.l.l.",
    "wof:placetype":"venue"
},
  "geometry": {"coordinates":[-6.0683913231,36.9187316895],"type":"Point"}
}