{
  "type": "Feature",
  "properties": {
    "iso:country":"ES",
    "sg:address":"Carrer de Born, 13",
    "sg:city":"Manresa",
    "sg:orig_category":"Zapatos (al Por Menor)",
    "sg:phone":"+34 938 72 57 67",
    "sg:postcode":"08241",
    "sg:province":"Barcelona",
    "wof:name":"Calzados Pe\u00f1arroya S. A.",
    "wof:placetype":"venue"
},
  "geometry": {"coordinates":[1.8242390156,41.7244148254],"type":"Point"}
}