{
  "type": "Feature",
  "properties": {
    "addr:full":"Calle de Jaime I, 10 Ejea De Los Caballeros Zaragoza 50600",
    "addr:housenumber":"10",
    "addr:postcode":"50600",
    "addr:street":"Calle De Jaime I",
    "iso:country":"ES",
    "sg:address":"Calle de Jaime I, 10",
    "sg:city":"Ejea De Los Caballeros",
    "sg:orig_category":"Promotores Constructores",
    "sg:phone":"+34 976 66 00 34",
    "sg:postcode":"50600",
    "sg:province":"Zaragoza",
    "wof:name":"Hercasa Ejea 2003 S. A.",
    "wof:placetype":"venue"
},
  "geometry": {"coordinates":[-1.1415929794,42.1235694885],"type":"Point"}
}