{
  "type": "Feature",
  "properties": {
    "iso:country":"ES",
    "sg:address":"Calle de Panaderos, 35",
    "sg:city":"Valladolid",
    "sg:orig_category":"Ense\u00d1ante, Direcci\u00d3n",
    "sg:phone":"+34 983 20 32 91",
    "sg:postcode":"47004",
    "sg:province":"Valladolid",
    "wof:name":"Alvarez Ramos Maria Victoria",
    "wof:placetype":"venue"
},
  "geometry": {"coordinates":[-4.7228884697,41.6467552185],"type":"Point"}
}