{
  "type": "Feature",
  "properties": {
    "iso:country":"ES",
    "sg:address":"Calle de Wellington, 1",
    "sg:city":"Salamanca",
    "sg:orig_category":"Promotores Constructores",
    "sg:phone":"+34 923 25 76 68",
    "sg:postcode":"37004",
    "sg:province":"Salamanca",
    "wof:name":"Sanchez Rivas Jose",
    "wof:placetype":"venue"
},
  "geometry": {"coordinates":[-5.6548318863,40.9738311768],"type":"Point"}
}