{
  "type": "Feature",
  "properties": {
    "iso:country":"ES",
    "sg:address":"Juan Gisasola Kalea, 6",
    "sg:city":"Eibar",
    "sg:orig_category":"Sociedades, Compa\u00d1\u00cdas Aseguradoras",
    "sg:phone":"+34 943 70 29 98",
    "sg:postcode":"20600",
    "sg:province":"Guip\u00f9zcoa",
    "wof:name":"Carasa Cilveti Lacort Y Cia S.a.",
    "wof:placetype":"venue"
},
  "geometry": {"coordinates":[-2.4733569622,43.183265686],"type":"Point"}
}