{
  "type": "Feature",
  "properties": {
    "addr:full":"Calle de Carlos Iii, 5 Fuente Palmera C\u00f3rdoba 14120",
    "addr:housenumber":"5",
    "addr:postcode":"14120",
    "addr:street":"Calle De Carlos Iii",
    "iso:country":"ES",
    "sg:address":"Calle de Carlos Iii, 5",
    "sg:city":"Fuente Palmera",
    "sg:orig_category":"Ense\u00d1anza: Profesiones Art\u00cdsticas",
    "sg:phone":"+34 957 63 85 37",
    "sg:postcode":"14120",
    "sg:province":"C\u00f3rdoba",
    "wof:name":"Moreno Abellan Jose Luis",
    "wof:placetype":"venue"
},
  "geometry": {"coordinates":[-5.1038928032,37.7042961121],"type":"Point"}
}