{
  "type": "Feature",
  "properties": {
    "addr:full":"Av Llibertat, 45 Mollet Valles Barcelona 08100",
    "addr:housenumber":"45",
    "addr:postcode":"08100",
    "addr:street":"Av Llibertat",
    "iso:country":"ES",
    "sg:address":"Av Llibertat, 45",
    "sg:city":"Mollet Valles",
    "sg:orig_category":"Material Y Suministros Para Peluquer\u00cda",
    "sg:phone":"+34 935 79 32 74",
    "sg:postcode":"08100",
    "sg:province":"Barcelona",
    "wof:name":"Tosp Perruqueria S.c.p.",
    "wof:placetype":"venue"
},
  "geometry": {"coordinates":[2.2111759186,41.5354728699],"type":"Point"}
}