{
  "type": "Feature",
  "properties": {
    "addr:full":"Calle de Mauricio Legendre, 16 Madrid Madrid 28046",
    "addr:housenumber":"16",
    "addr:postcode":"madrid;28046",
    "addr:street":"Calle De Mauricio Legendre",
    "iso:country":"ES",
    "sg:address":"Calle de Mauricio Legendre, 16",
    "sg:city":"Madrid",
    "sg:orig_category":"Agencias Y Agentes Comerciales, Representantes",
    "sg:phone":"+34 917 33 97 79",
    "sg:postcode":"28046",
    "sg:province":"Madrid",
    "wof:name":"Del Rey Avila Juan Manuel",
    "wof:placetype":"venue"
},
  "geometry": {"coordinates":[-3.6856539249,40.4722213745],"type":"Point"}
}