{
  "type": "Feature",
  "properties": {
    "iso:country":"ES",
    "sg:address":"Calle de Capitan, 51",
    "sg:city":"Osuna",
    "sg:orig_category":"Art\u00cdculos De Regalo (al Por Menor)",
    "sg:phone":"+34 954 81 29 61",
    "sg:postcode":"41640",
    "sg:province":"Sevilla",
    "wof:name":"Fernandez Herrera Francisco Javier",
    "wof:placetype":"venue"
},
  "geometry": {"coordinates":[-5.0987668037,37.2333221436],"type":"Point"}
}