{
  "type": "Feature",
  "properties": {
    "iso:country":"ES",
    "sg:address":"Carrer de L'alfambra, 14",
    "sg:city":"Barcelona",
    "sg:orig_category":"Procuradores",
    "sg:phone":"+34 932 05 42 77",
    "sg:postcode":"08034",
    "sg:province":"Barcelona",
    "wof:name":"Moratal Bohigues Pedro",
    "wof:placetype":"venue"
},
  "geometry": {"coordinates":[2.1125383377,41.3865318298],"type":"Point"}
}