{
  "type": "Feature",
  "properties": {
    "iso:country":"ES",
    "sg:address":"Erreka, 9",
    "sg:city":"Erreka",
    "sg:orig_category":"Poller\u00cda Y Caza (al Por Menor)",
    "sg:phone":"+34 948 39 70 39",
    "sg:postcode":"31880",
    "sg:province":"Navarra",
    "wof:name":"Bizkotx S.l.",
    "wof:placetype":"venue"
},
  "geometry": {"coordinates":[-1.9149940014,43.0805091858],"type":"Point"}
}