{
  "type": "Feature",
  "properties": {
    "addr:full":"Pepe Clausell Impulsor De La Clausellina, 55 Almassora Castell\u00f3n 12550",
    "addr:housenumber":"55",
    "addr:postcode":"12550",
    "addr:street":"Almassora Castello\u0301N",
    "iso:country":"ES",
    "sg:address":"Pepe Clausell Impulsor De La Clausellina, 55",
    "sg:city":"Almassora",
    "sg:orig_category":"Arquitectos",
    "sg:phone":"+34 964 56 26 68",
    "sg:postcode":"12550",
    "sg:province":"Castell\u00f3n",
    "wof:name":"Catala Arenos Blas",
    "wof:placetype":"venue"
},
  "geometry": {"coordinates":[-0.0631700009,39.9439582825],"type":"Point"}
}