{
  "type": "Feature",
  "properties": {
    "iso:country":"ES",
    "sg:address":"Avda Mediterraneo, 22",
    "sg:city":"Madrid",
    "sg:orig_category":"Farmacias",
    "sg:phone":"+34 914 33 75 80",
    "sg:postcode":"28007",
    "sg:province":"Madrid",
    "wof:name":"Galvez Pazos Luisa Maria",
    "wof:placetype":"venue"
},
  "geometry": {"coordinates":[-3.6741080284,40.406955719],"type":"Point"}
}