{
  "type": "Feature",
  "properties": {
    "iso:country":"ES",
    "sg:address":"Cmno San Rafael, 1",
    "sg:city":"Malaga",
    "sg:orig_category":"Estilistas Y Estudios De Estilo De Corte Y Confecci\u00d3n",
    "sg:phone":"+34 952 32 26 80",
    "sg:postcode":"29006",
    "sg:province":"M\u00e1laga",
    "wof:name":"Confecciones Cervantes S.c.",
    "wof:placetype":"venue"
},
  "geometry": {"coordinates":[-4.4412379265,36.7116851807],"type":"Point"}
}