{
  "type": "Feature",
  "properties": {
    "addr:full":"Carrer de Lusitania, 69 Sabadell Barcelona 08206",
    "addr:housenumber":"69",
    "addr:postcode":"08206",
    "addr:street":"Carrer De Lusitania",
    "iso:country":"ES",
    "sg:address":"Carrer de Lusitania, 69",
    "sg:city":"Sabadell",
    "sg:orig_category":"Peluquer\u00cdas, Peluquer\u00cda Mixta",
    "sg:phone":"+34 937 23 72 57",
    "sg:postcode":"08206",
    "sg:province":"Barcelona",
    "wof:name":"Grupo Peinados S.c.p.",
    "wof:placetype":"venue"
},
  "geometry": {"coordinates":[2.0913209915,41.5599327087],"type":"Point"}
}