{
  "type": "Feature",
  "properties": {
    "iso:country":"ES",
    "sg:address":"Calle de Antonio Perez, 19",
    "sg:city":"Madrid",
    "sg:orig_category":"Contenedores Para Dep\u00d3sito De Sustancias Peligrosas (fabricaci\u00d3n, Al Por Mayor)",
    "sg:phone":"+34 915 61 75 85",
    "sg:postcode":"28002",
    "sg:province":"Madrid",
    "wof:name":"Recomar S.a.",
    "wof:placetype":"venue"
},
  "geometry": {"coordinates":[-3.6824057102,40.4428405762],"type":"Point"}
}