{
  "type": "Feature",
  "properties": {
    "addr:full":"Calle de Valverde De Los Arroyos (de), 1 Fuenlabrada Madrid 28944",
    "addr:housenumber":"1",
    "addr:postcode":"28944",
    "addr:street":"Calle De Valverde De Los Arroyos De",
    "iso:country":"ES",
    "sg:address":"Calle de Valverde De Los Arroyos (de), 1",
    "sg:city":"Fuenlabrada",
    "sg:orig_category":"Equipo De Refrigeraci\u00d3n Industrial",
    "sg:phone":"+34 916 06 53 83",
    "sg:postcode":"28944",
    "sg:province":"Madrid",
    "wof:name":"Suministros Hortet S.l.",
    "wof:placetype":"venue"
},
  "geometry": {"coordinates":[-3.8037345409,40.2751083374],"type":"Point"}
}