{
  "type": "Feature",
  "properties": {
    "addr:full":"Calle de Nuestra Se\u00d1ora De Los Olmos, 52 Torre Juan Abad Ciudad Real 13344",
    "addr:housenumber":"52",
    "addr:postcode":"13344",
    "addr:street":"Calle De Nuestra Sen\u0303Ora De Los Olmos",
    "iso:country":"ES",
    "sg:address":"Calle de Nuestra Se\u00d1ora De Los Olmos, 52",
    "sg:city":"Torre Juan Abad",
    "sg:classifiers":[
        {
            "category":"Taxi",
            "type":"Transportation"
        }
    ],
    "sg:phone":"+34 926 38 30 80",
    "sg:postcode":"13344",
    "sg:province":"Ciudad Real",
    "wof:name":"Martinez Frias Emilio",
    "wof:placetype":"venue"
},
  "geometry": {"coordinates":[-3.9222910404,38.9792785645],"type":"Point"}
}