{
  "type": "Feature",
  "properties": {
    "addr:full":"Rua Murillo (pintor), 8 Lugo Lugo 27002",
    "addr:housenumber":"8",
    "addr:postcode":"27002",
    "addr:street":"Rua Murillo Pintor",
    "iso:country":"ES",
    "sg:address":"Rua Murillo (pintor), 8",
    "sg:city":"Lugo",
    "sg:orig_category":"M\u00c9dicos: Medicina Interna",
    "sg:phone":"+34 982 24 21 59",
    "sg:postcode":"27002",
    "sg:province":"Lugo",
    "wof:name":"Rodriguez Castro Antonio",
    "wof:placetype":"venue"
},
  "geometry": {"coordinates":[-7.5544919968,42.9978370667],"type":"Point"}
}