{
  "type": "Feature",
  "properties": {
    "addr:full":"Calle de Pascual Y Genis, 22 Valencia Valencia 46...",
    "addr:housenumber":"22",
    "addr:street":"Calle De Pascual Y Genis;Valencia",
    "iso:country":"ES",
    "sg:address":"Calle de Pascual Y Genis, 22",
    "sg:city":"Valencia",
    "sg:orig_category":"Cajas De Ahorro",
    "sg:phone":"+34 963 88 70 00",
    "sg:postcode":"46...",
    "sg:province":"Valencia",
    "wof:name":"Caja De Ahorros Del Mediterraneo",
    "wof:placetype":"venue"
},
  "geometry": {"coordinates":[-0.3739989996,39.4683532715],"type":"Point"}
}