{
  "type": "Feature",
  "properties": {
    "iso:country":"ES",
    "sg:address":"Calle de Escorial (del), 20",
    "sg:city":"Navalcarnero",
    "sg:orig_category":"Trabajos De Perforaciones, Sondeos, Construcci\u00d3n De Pozos",
    "sg:phone":"+34 918 11 04 89",
    "sg:postcode":"28600",
    "sg:province":"Madrid",
    "wof:name":"Blanco Sanchez Francisco",
    "wof:placetype":"venue"
},
  "geometry": {"coordinates":[-4.0157499313,40.2889213562],"type":"Point"}
}