{
  "type": "Feature",
  "properties": {
    "iso:country":"ES",
    "sg:address":"Calle de Peris Brell, 31",
    "sg:city":"Valencia",
    "sg:orig_category":"Electricidad: Instaladores",
    "sg:phone":"+34 963 30 09 71",
    "sg:postcode":"46022",
    "sg:province":"Valencia",
    "wof:name":"Montajes Electricos Instaluz S.l.",
    "wof:placetype":"venue"
},
  "geometry": {"coordinates":[-0.3468610048,39.4669532776],"type":"Point"}
}