{
  "type": "Feature",
  "properties": {
    "iso:country":"ES",
    "sg:address":"Ctra Cortijo, Km. 0003,0",
    "sg:city":"Logro\u00f1o",
    "sg:orig_category":"Alimentaci\u00d3n: Aditivos, Esencias Alimentarias, Levaduras (fabricaci\u00d3n, Al Por Mayor)",
    "sg:phone":"+34 941 20 65 01",
    "sg:postcode":"26006",
    "sg:province":"La Rioja",
    "wof:name":"Alfocea Sedo Salvador",
    "wof:placetype":"venue"
},
  "geometry": {"coordinates":[-2.5202503204,42.4919700623],"type":"Point"}
}