{
  "type": "Feature",
  "properties": {
    "iso:country":"ES",
    "sg:address":"Calle de Santa Cruz De La Zarza, S/n",
    "sg:city":"Valencia",
    "sg:orig_category":"Promotores Constructores",
    "sg:phone":"+34 963 69 12 54",
    "sg:postcode":"46021",
    "sg:province":"Valencia",
    "sg:website":"www.novain.net",
    "wof:name":"Novain S.l.",
    "wof:placetype":"venue"
},
  "geometry": {"coordinates":[-0.3517090082,39.4790649414],"type":"Point"}
}