{
  "type": "Feature",
  "properties": {
    "addr:full":"Calle de Hacienda De Pavones, 182 Madrid Madrid 28030",
    "addr:housenumber":"182",
    "addr:postcode":"28030",
    "addr:street":"Calle De Hacienda De Pavones",
    "iso:country":"ES",
    "sg:address":"Calle de Hacienda De Pavones, 182",
    "sg:city":"Madrid",
    "sg:orig_category":"Transportes Por Carretera: Lotes Completos, Mercanc\u00cdas Diversas",
    "sg:phone":"+34 913 05 17 40",
    "sg:postcode":"28030",
    "sg:province":"Madrid",
    "wof:name":"Europoal S.l.",
    "wof:placetype":"venue"
},
  "geometry": {"coordinates":[-3.641294241,40.4016075134],"type":"Point"}
}