{
  "type": "Feature",
  "properties": {
    "iso:country":"ES",
    "sg:address":"Calle de Colon, 28",
    "sg:city":"Requena",
    "sg:orig_category":"Promotores Constructores",
    "sg:phone":"+34 962 30 07 15",
    "sg:postcode":"46340",
    "sg:province":"Valencia",
    "wof:name":"Construcciones Bleda Y Falcon S.l",
    "wof:placetype":"venue"
},
  "geometry": {"coordinates":[-1.1022671461,39.4909896851],"type":"Point"}
}