{
  "type": "Feature",
  "properties": {
    "addr:full":"Avda Constitucion (la), 55 Sabiote Ja\u00e9n 23410",
    "addr:housenumber":"55",
    "addr:postcode":"23410",
    "addr:street":"Avda Constitucion La;Jae\u0301N",
    "iso:country":"ES",
    "sg:address":"Avda Constitucion (la), 55",
    "sg:city":"Sabiote",
    "sg:orig_category":"Muebles, Minoristas",
    "sg:phone":"+34 953 77 31 11",
    "sg:postcode":"23410",
    "sg:province":"Ja\u00e9n",
    "wof:name":"Muebles Augusto S.l.",
    "wof:placetype":"venue"
},
  "geometry": {"coordinates":[-3.3138461113,38.0648956299],"type":"Point"}
}