{
  "type": "Feature",
  "properties": {
    "iso:country":"ES",
    "sg:address":"Calle de Pi\u00d1on, 9",
    "sg:city":"Liandres",
    "sg:orig_category":"Asesor\u00cda Sobre Comunicaci\u00d3n De Empresas",
    "sg:phone":"+34 942 74 63 91",
    "sg:postcode":"39527",
    "sg:province":"Cantabria",
    "wof:name":"Larce Asesores S.l.",
    "wof:placetype":"venue"
},
  "geometry": {"coordinates":[-4.2520489693,43.3805046082],"type":"Point"}
}