{
  "type": "Feature",
  "properties": {
    "iso:country":"ES",
    "sg:address":"Carrer de Montsant, 30",
    "sg:city":"Barcelona",
    "sg:orig_category":"Mercer\u00cda, Lencer\u00cda (al Por Menor)",
    "sg:phone":"+34 934 20 67 22",
    "sg:postcode":"08031",
    "sg:province":"Barcelona",
    "wof:name":"Pons Pons Carmen",
    "wof:placetype":"venue"
},
  "geometry": {"coordinates":[2.1696929932,41.4339523315],"type":"Point"}
}