{
  "type": "Feature",
  "properties": {
    "iso:country":"ES",
    "sg:address":"Melaza, 16",
    "sg:city":"Motril",
    "sg:orig_category":"Agencias Y Agentes Comerciales, Representantes",
    "sg:phone":"+34 958 82 40 64",
    "sg:postcode":"18600",
    "sg:province":"Granada",
    "wof:name":"Lozano Lozano Juan Alexis",
    "wof:placetype":"venue"
},
  "geometry": {"coordinates":[-3.5240139961,36.7517623901],"type":"Point"}
}