{
  "type": "Feature",
  "properties": {
    "iso:country":"ES",
    "sg:address":"Carrer de Alps, 18",
    "sg:city":"Sabadell",
    "sg:orig_category":"Reparaciones Y Remolcado De Veh\u00cdculos",
    "sg:phone":"+34 937 17 73 51",
    "sg:postcode":"08207",
    "sg:province":"Barcelona",
    "wof:name":"Humanes Zamora Cayetano",
    "wof:placetype":"venue"
},
  "geometry": {"coordinates":[2.0902628899,41.5722236633],"type":"Point"}
}