{
  "type": "Feature",
  "properties": {
    "addr:full":"Trss Mas Romeu, 17 Mas Romeu Residencial Girona 17310",
    "addr:housenumber":"17",
    "addr:postcode":"17310",
    "iso:country":"ES",
    "sg:address":"Trss Mas Romeu, 17",
    "sg:city":"Mas Romeu Residencial",
    "sg:orig_category":"Importaci\u00d3n",
    "sg:phone":"+34 972 37 00 98",
    "sg:postcode":"17310",
    "sg:province":"Girona",
    "wof:name":"Hammys Import S.l.",
    "wof:placetype":"venue"
},
  "geometry": {"coordinates":[2.846834898,41.6981697083],"type":"Point"}
}