{
  "type": "Feature",
  "properties": {
    "iso:country":"ES",
    "sg:address":"C/ Filet De Fora, 50",
    "sg:city":"Elche",
    "sg:orig_category":"M\u00c9dicos: Cirug\u00cda Pl\u00c1stica, Reconstructiva Y Est\u00c9tica",
    "sg:phone":"+34 965 42 55 92",
    "sg:postcode":"03203",
    "sg:province":"Alicante",
    "wof:name":"Corpo. Quirurgica Del Mediterraneo Sll",
    "wof:placetype":"venue"
},
  "geometry": {"coordinates":[-0.6962440014,38.2619895935],"type":"Point"}
}