{
  "type": "Feature",
  "properties": {
    "addr:full":"Urb Albarizas, S/n Antequera M\u00e1laga 29200",
    "addr:housenumber":"s",
    "addr:postcode":"29200",
    "addr:street":"Urb Albarizas;/ N;Ma\u0301Laga",
    "iso:country":"ES",
    "sg:address":"Urb Albarizas, S/n",
    "sg:city":"Antequera",
    "sg:orig_category":"Carnicer\u00cdas, Carnicer\u00cdas",
    "sg:phone":"+34 952 70 40 98",
    "sg:postcode":"29200",
    "sg:province":"M\u00e1laga",
    "wof:name":"Carnicas Picasso S.l.",
    "wof:placetype":"venue"
},
  "geometry": {"coordinates":[-4.5694842339,37.0237731934],"type":"Point"}
}