{
  "type": "Feature",
  "properties": {
    "iso:country":"ES",
    "sg:address":"Ribas, S/n",
    "sg:city":"Oza",
    "sg:orig_category":"Molduras, Junquillos, Listones Y Molduras Perforadas",
    "sg:phone":"+34 981 80 74 58",
    "sg:postcode":"15886",
    "sg:province":"La Coru\u00f1a",
    "wof:name":"Fernandez Meijide M Dolores",
    "wof:placetype":"venue"
},
  "geometry": {"coordinates":[-8.5489406586,42.79429245],"type":"Point"}
}