{
  "type": "Feature",
  "properties": {
    "addr:full":"Calle de Pintor Varela, 1 Torrelavega Cantabria 39300",
    "addr:housenumber":"1",
    "addr:postcode":"39300",
    "addr:street":"Calle De Pintor Varela",
    "iso:country":"ES",
    "sg:address":"Calle de Pintor Varela, 1",
    "sg:city":"Torrelavega",
    "sg:orig_category":"Venta, Colocaci\u00d3n, Reparaci\u00d3n De Parabrisas, Techos Descapotables",
    "sg:phone":"+34 942 89 31 02",
    "sg:postcode":"39300",
    "sg:province":"Cantabria",
    "wof:name":"Carglass B.v.sucursal En Espa\u00d1a",
    "wof:placetype":"venue"
},
  "geometry": {"coordinates":[-4.044216156,43.3524436951],"type":"Point"}
}