{
  "type": "Feature",
  "properties": {
    "iso:country":"ES",
    "sg:address":"Calle de Santa Cruz, 28",
    "sg:city":"Almazora",
    "sg:orig_category":"Empresas De Carpinter\u00cda De Madera",
    "sg:phone":"+34 964 56 06 66",
    "sg:postcode":"12550",
    "sg:province":"Castell\u00f3n",
    "wof:name":"Renau Arenos Vicente",
    "wof:placetype":"venue"
},
  "geometry": {"coordinates":[-0.0631740019,39.9439582825],"type":"Point"}
}