{
  "type": "Feature",
  "properties": {
    "addr:full":"Calle de Pintor Adrian Aldecoa, 8 Vitoria-gasteiz \u00c1lava 01008",
    "addr:housenumber":"8",
    "addr:postcode":"01008",
    "addr:street":"Calle De Pintor Adrian Aldecoa",
    "iso:country":"ES",
    "sg:address":"Calle de Pintor Adrian Aldecoa, 8",
    "sg:city":"Vitoria-gasteiz",
    "sg:orig_category":"Molduras, Junquillos, Listones Y Molduras Perforadas",
    "sg:phone":"+34 945 13 65 95",
    "sg:postcode":"01008",
    "sg:province":"\u00c1lava",
    "wof:name":"Pontejo Martinez Vidalina",
    "wof:placetype":"venue"
},
  "geometry": {"coordinates":[-2.6849930286,42.8440818787],"type":"Point"}
}