{
  "type": "Feature",
  "properties": {
    "iso:country":"ES",
    "sg:address":"Ctra. Murcia-granada, 23",
    "sg:city":"Velez-rubio",
    "sg:orig_category":"Chapister\u00cda",
    "sg:phone":"+34 950 41 02 16",
    "sg:postcode":"04820",
    "sg:province":"Almer\u00eda",
    "wof:name":"Talleres J Yeste Sl",
    "wof:placetype":"venue"
},
  "geometry": {"coordinates":[-2.0770230293,37.6492118835],"type":"Point"}
}