{
  "type": "Feature",
  "properties": {
    "addr:full":"Calle de Tres Forques, 34 Valencia Valencia 46018",
    "addr:housenumber":"34",
    "addr:postcode":"46018",
    "addr:street":"Calle De Tres Forques",
    "iso:country":"ES",
    "sg:address":"Calle de Tres Forques, 34",
    "sg:city":"Valencia",
    "sg:orig_category":"Agentes, Concesionarios Y Sucursales De Veh\u00cdculos",
    "sg:phone":"+34 963 85 05 95",
    "sg:postcode":"46018",
    "sg:province":"Valencia",
    "wof:name":"Servicios Y Tramitaciones De Automocion Y Rematriculacion S.a.",
    "wof:placetype":"venue"
},
  "geometry": {"coordinates":[-0.3918670118,39.4642677307],"type":"Point"}
}