{
  "type": "Feature",
  "properties": {
    "iso:country":"ES",
    "sg:address":"Calle de Joaquin Maria Lopez, 41",
    "sg:city":"Madrid",
    "sg:orig_category":"M\u00c9dicos: Pediatr\u00cda. Enfermedades De Los Ni\u00d1os",
    "sg:phone":"+34 915 49 60 83",
    "sg:postcode":"28015",
    "sg:province":"Madrid",
    "wof:name":"Gonzalez De Leon Santos Maria Luisa",
    "wof:placetype":"venue"
},
  "geometry": {"coordinates":[-3.7150731087,40.4376029968],"type":"Point"}
}