{
  "type": "Feature",
  "properties": {
    "addr:full":"Calle de Ingeniero Torroja Y Miret, 2 Cordoba C\u00f3rdoba 14013",
    "addr:housenumber":"2",
    "addr:postcode":"14013",
    "addr:street":"Calle De Ingeniero Torroja Y Miret;Co\u0301Rdoba",
    "iso:country":"ES",
    "sg:address":"Calle de Ingeniero Torroja Y Miret, 2",
    "sg:city":"Cordoba",
    "sg:orig_category":"Mec\u00c1nico Del Autom\u00d3vil",
    "sg:phone":"+34 957 29 97 98",
    "sg:postcode":"14013",
    "sg:province":"C\u00f3rdoba",
    "wof:name":"Talleres Cortijo S.l.",
    "wof:placetype":"venue"
},
  "geometry": {"coordinates":[-4.7922887802,37.8547477722],"type":"Point"}
}