{
  "type": "Feature",
  "properties": {
    "iso:country":"ES",
    "sg:address":"Calle de Marques De Nervion, 89",
    "sg:city":"Sevilla",
    "sg:orig_category":"Cl\u00cdnicas Dentales",
    "sg:phone":"+34 954 92 42 65",
    "sg:postcode":"41005",
    "sg:province":"Sevilla",
    "wof:name":"Dental Dent S.l.",
    "wof:placetype":"venue"
},
  "geometry": {"coordinates":[-5.9689698219,37.3782234192],"type":"Point"}
}