{
  "type": "Feature",
  "properties": {
    "iso:country":"ES",
    "sg:address":"Avda Estacion (de La), 32",
    "sg:city":"Almeria",
    "sg:orig_category":"Mercer\u00cda, Lencer\u00cda (al Por Menor)",
    "sg:phone":"+34 950 26 08 35",
    "sg:postcode":"04005",
    "sg:province":"Almer\u00eda",
    "wof:name":"Saez Rueda Juan",
    "wof:placetype":"venue"
},
  "geometry": {"coordinates":[-2.4574780464,36.8368453979],"type":"Point"}
}