{
  "type": "Feature",
  "properties": {
    "addr:full":"Carrer de Pere Iv, 495 Barcelona Barcelona 08020",
    "addr:housenumber":"495",
    "addr:postcode":"08020",
    "addr:street":"Carrer De Pere Iv",
    "iso:country":"ES",
    "sg:address":"Carrer de Pere Iv, 495",
    "sg:city":"Barcelona",
    "sg:orig_category":"Empresas De Carpinter\u00cda De Madera",
    "sg:phone":"+34 932 78 02 64",
    "sg:postcode":"08020",
    "sg:province":"Barcelona",
    "wof:name":"Demonti S.c.p.",
    "wof:placetype":"venue"
},
  "geometry": {"coordinates":[2.2086191177,41.4172325134],"type":"Point"}
}