{
  "type": "Feature",
  "properties": {
    "addr:full":"Calle de Balmes, 2 Palencia Palencia 34004",
    "addr:housenumber":"2",
    "addr:postcode":"34004",
    "addr:street":"Calle De Balmes",
    "iso:country":"ES",
    "sg:address":"Calle de Balmes, 2",
    "sg:city":"Palencia",
    "sg:orig_category":"Mercer\u00cda, Lencer\u00cda (al Por Menor)",
    "sg:phone":"+34 979 72 01 86",
    "sg:postcode":"34004",
    "sg:province":"Palencia",
    "wof:name":"Alonso Lluguero Almudena",
    "wof:placetype":"venue"
},
  "geometry": {"coordinates":[-4.5262131691,42.0055580139],"type":"Point"}
}