{
  "type": "Feature",
  "properties": {
    "iso:country":"ES",
    "sg:address":"Plaz Trinidad De La, 3",
    "sg:city":"Villalba Alcor",
    "sg:orig_category":"Servicios Gsm",
    "sg:phone":"+34 959 42 01 83",
    "sg:postcode":"21860",
    "sg:province":"Huelva",
    "wof:name":"Movil Phone Alcor S.l.u.",
    "wof:placetype":"venue"
},
  "geometry": {"coordinates":[-6.4754738808,37.397064209],"type":"Point"}
}