{
  "type": "Feature",
  "properties": {
    "iso:country":"ES",
    "sg:address":"Calle de Trench, 2",
    "sg:city":"Valencia",
    "sg:orig_category":"Complementos De Vestir (al Por Menor)",
    "sg:phone":"+34 963 92 56 48",
    "sg:postcode":"46001",
    "sg:province":"Valencia",
    "wof:name":"Romoba Scp",
    "wof:placetype":"venue"
},
  "geometry": {"coordinates":[-0.3769460022,39.4737472534],"type":"Point"}
}