{
  "type": "Feature",
  "properties": {
    "addr:full":"Calle de Veguillas, 13 Almorox Toledo 45900",
    "addr:housenumber":"13",
    "addr:postcode":"45900",
    "addr:street":"Calle De Veguillas",
    "iso:country":"ES",
    "sg:address":"Calle de Veguillas, 13",
    "sg:city":"Almorox",
    "sg:orig_category":"Empresas De Pintura Y Revestimientos",
    "sg:phone":"+34 918 62 35 04",
    "sg:postcode":"45900",
    "sg:province":"Toledo",
    "wof:name":"Notario Cuellar Pedro",
    "wof:placetype":"venue"
},
  "geometry": {"coordinates":[-4.3924841881,40.2344436646],"type":"Point"}
}