{
  "type": "Feature",
  "properties": {
    "iso:country":"ES",
    "sg:address":"Avda Candido Lobera, 7",
    "sg:city":"Melilla",
    "sg:orig_category":"Auditores De Empresas",
    "sg:phone":"+34 952 68 10 18",
    "sg:postcode":"52001",
    "sg:province":"Melilla",
    "wof:name":"Ciudad Autonoma De Melilla",
    "wof:placetype":"venue"
},
  "geometry": {"coordinates":[-2.9395699501,35.2943153381],"type":"Point"}
}