{
  "type": "Feature",
  "properties": {
    "addr:full":"Avda Andalucia, 50 Ecija Sevilla 41400",
    "addr:housenumber":"50",
    "addr:postcode":"41400",
    "addr:street":"Avda Andalucia",
    "iso:country":"ES",
    "sg:address":"Avda Andalucia, 50",
    "sg:city":"Ecija",
    "sg:orig_category":"Quincaller\u00cda (al Por Menor)",
    "sg:phone":"+34 955 90 31 41",
    "sg:postcode":"41400",
    "sg:province":"Sevilla",
    "wof:name":"Herrero Cilla Bernardo",
    "wof:placetype":"venue"
},
  "geometry": {"coordinates":[-5.0741901398,37.5375289917],"type":"Point"}
}