{
  "type": "Feature",
  "properties": {
    "addr:full":"Carr Major, 112 Jonquera Girona 17700",
    "addr:housenumber":"112",
    "addr:postcode":"17700",
    "addr:street":"Carr Major",
    "iso:country":"ES",
    "sg:address":"Carr Major, 112",
    "sg:city":"Jonquera",
    "sg:orig_category":"Peluquer\u00cdas, Peluquer\u00cda Mixta",
    "sg:phone":"+34 972 55 49 52",
    "sg:postcode":"17700",
    "sg:province":"Girona",
    "wof:name":"Perruqueria Mixta C.m.s.c.",
    "wof:placetype":"venue"
},
  "geometry": {"coordinates":[2.8718750477,42.4159698486],"type":"Point"}
}