{
  "type": "Feature",
  "properties": {
    "addr:full":"Calle de Diaz De Mendoza, 5 Zaragoza Zaragoza 50009",
    "addr:housenumber":"5",
    "addr:postcode":"50009",
    "addr:street":"Calle De Diaz De Mendoza",
    "iso:country":"ES",
    "sg:address":"Calle de Diaz De Mendoza, 5",
    "sg:city":"Zaragoza",
    "sg:orig_category":"Chapister\u00cda",
    "sg:phone":"+34 976 75 09 11",
    "sg:postcode":"50009",
    "sg:province":"Zaragoza",
    "wof:name":"Domingo Leal Antonio",
    "wof:placetype":"venue"
},
  "geometry": {"coordinates":[-0.9095889926,41.6429328918],"type":"Point"}
}