{
  "type": "Feature",
  "properties": {
    "addr:full":"Calle de Infanta Mercedes, 10 Madrid Madrid 28020",
    "addr:housenumber":"10",
    "addr:postcode":"madrid;28020",
    "addr:street":"Calle De Infanta Mercedes",
    "iso:country":"ES",
    "sg:address":"Calle de Infanta Mercedes, 10",
    "sg:city":"Madrid",
    "sg:orig_category":"Estancos",
    "sg:phone":"+34 915 70 70 39",
    "sg:postcode":"28020",
    "sg:province":"Madrid",
    "wof:name":"Suarez Cuendias Consolacion",
    "wof:placetype":"venue"
},
  "geometry": {"coordinates":[-3.6990470886,40.4541320801],"type":"Point"}
}