{
  "type": "Feature",
  "properties": {
    "addr:full":"Calle de Periodista Ramon Resa, 39 Sevilla Sevilla 41012",
    "addr:housenumber":"39",
    "addr:postcode":"41012",
    "addr:street":"Calle De Periodista Ramon Resa",
    "iso:country":"ES",
    "sg:address":"Calle de Periodista Ramon Resa, 39",
    "sg:city":"Sevilla",
    "sg:orig_category":"Asilos De Ancianos. Centros Privados",
    "sg:phone":"+34 954 62 78 83",
    "sg:postcode":"41012",
    "sg:province":"Sevilla",
    "wof:name":"Gherispalis S.l.",
    "wof:placetype":"venue"
},
  "geometry": {"coordinates":[-5.9832859039,37.3589782715],"type":"Point"}
}