{
  "type": "Feature",
  "properties": {
    "iso:country":"ES",
    "sg:address":"Calle de Mercedes, 3",
    "sg:city":"Madrid",
    "sg:orig_category":"Sociedades Y Organismos Burs\u00c1tiles",
    "sg:phone":"+34 915 72 29 92",
    "sg:postcode":"28020",
    "sg:province":"Madrid",
    "wof:name":"Intermediarios Agentes Bancarios S.l.",
    "wof:placetype":"venue"
},
  "geometry": {"coordinates":[-3.7024109364,40.454624176],"type":"Point"}
}