{
  "type": "Feature",
  "properties": {
    "addr:full":"Calle de Bario, 14 Madrid Madrid 28021",
    "addr:housenumber":"14",
    "addr:postcode":"madrid;28021",
    "addr:street":"Calle De Bario",
    "iso:country":"ES",
    "sg:address":"Calle de Bario, 14",
    "sg:city":"Madrid",
    "sg:orig_category":"Peluquer\u00cdas, Peluquer\u00cda Mixta",
    "sg:phone":"+34 915 05 56 58",
    "sg:postcode":"28021",
    "sg:province":"Madrid",
    "wof:name":"Alamo Diaz Cristina",
    "wof:placetype":"venue"
},
  "geometry": {"coordinates":[-3.6778466702,40.3478851318],"type":"Point"}
}