{
  "type": "Feature",
  "properties": {
    "addr:full":"Calle de Ciudad Real, 1 Sabatera Alicante 03725",
    "addr:housenumber":"1",
    "addr:postcode":"03725",
    "addr:street":"Calle De Ciudad Real;Alicante",
    "iso:country":"ES",
    "sg:address":"Calle de Ciudad Real, 1",
    "sg:city":"Sabatera",
    "sg:orig_category":"Inmobiliaria (agencias)",
    "sg:phone":"+34 965 74 15 14",
    "sg:postcode":"03725",
    "sg:province":"Alicante",
    "wof:name":"Bretur S.l.",
    "wof:placetype":"venue"
},
  "geometry": {"coordinates":[0.1012500003,38.7296409607],"type":"Point"}
}