{
  "type": "Feature",
  "properties": {
    "iso:country":"ES",
    "sg:address":"Pla\u00c7 Mediterrania, 1",
    "sg:city":"Grau I Platja",
    "sg:orig_category":"Pescader\u00cdas (al Por Menor)",
    "sg:phone":"+34 962 84 01 89",
    "sg:postcode":"46730",
    "sg:province":"Valencia",
    "wof:name":"Salvador Boix S.l.",
    "wof:placetype":"venue"
},
  "geometry": {"coordinates":[-0.1664949954,38.9994888306],"type":"Point"}
}