{
  "type": "Feature",
  "properties": {
    "addr:full":"Carr Sant Mori, 5 Empuriabrava Girona 17487",
    "addr:housenumber":"5",
    "addr:postcode":"17487",
    "addr:street":"Carr Sant Mori",
    "iso:country":"ES",
    "sg:address":"Carr Sant Mori, 5",
    "sg:city":"Empuriabrava",
    "sg:orig_category":"Ropa Para Se\u00d1oras (al Por Menor)",
    "sg:phone":"+34 972 45 17 03",
    "sg:postcode":"17487",
    "sg:province":"Girona",
    "wof:name":"Ribas Segura Laura",
    "wof:placetype":"venue"
},
  "geometry": {"coordinates":[3.1070549488,42.2568092346],"type":"Point"}
}