{
  "type": "Feature",
  "properties": {
    "addr:full":"Cami Ral, 33 Vilassar Barcelona 08340",
    "addr:postcode":"08340",
    "addr:street":"Ral;Vilassar Barcelona",
    "iso:country":"ES",
    "sg:address":"Cami Ral, 33",
    "sg:city":"Vilassar",
    "sg:orig_category":"Doctores En Medicina",
    "sg:phone":"+34 937 59 31 39",
    "sg:postcode":"08340",
    "sg:province":"Barcelona",
    "wof:name":"Roma Pujalet Juan",
    "wof:placetype":"venue"
},
  "geometry": {"coordinates":[2.3948609829,41.5033035278],"type":"Point"}
}