{
  "type": "Feature",
  "properties": {
    "addr:full":"Calle de Doctor Jimenez Diaz, 2 Fuensalida Toledo 45510",
    "addr:housenumber":"2",
    "addr:postcode":"45510",
    "addr:street":"Calle De Doctor Jimenez Diaz",
    "iso:country":"ES",
    "sg:address":"Calle de Doctor Jimenez Diaz, 2",
    "sg:city":"Fuensalida",
    "sg:orig_category":"Confecci\u00d3n De Zapatos",
    "sg:phone":"+34 925 78 42 51",
    "sg:postcode":"45510",
    "sg:province":"Toledo",
    "sg:website":"www.kangaroos.es",
    "wof:name":"Kangaroos S.l.",
    "wof:placetype":"venue"
},
  "geometry": {"coordinates":[-4.2020316124,40.0538482666],"type":"Point"}
}