{
  "type": "Feature",
  "properties": {
    "iso:country":"ES",
    "sg:address":"Calle de Vizconde De Arlesson, 8",
    "sg:city":"Madrid",
    "sg:orig_category":"Alimentaci\u00d3n General (al Por Menor)",
    "sg:phone":"+34 917 85 52 47",
    "sg:postcode":"28018",
    "sg:province":"Madrid",
    "wof:name":"Wang  Minhua",
    "wof:placetype":"venue"
},
  "geometry": {"coordinates":[-3.664712429,40.3821754456],"type":"Point"}
}