{
  "type": "Feature",
  "properties": {
    "iso:country":"ES",
    "sg:address":"Germans Pinzon, 65",
    "sg:city":"Palmanova",
    "sg:orig_category":"Perfumer\u00cda, Art\u00cdculos De Ba\u00d1o (fabricaci\u00d3n, Al Por Mayor)",
    "sg:phone":"+34 971 68 26 64",
    "sg:postcode":"07181",
    "sg:province":"Islas Baleares",
    "wof:name":"Perfumeria Borne Internacional S.l.",
    "wof:placetype":"venue"
},
  "geometry": {"coordinates":[2.5346190929,39.5188713074],"type":"Point"}
}