{
  "type": "Feature",
  "properties": {
    "addr:full":"Calle de Jardines, 57 Elda Alicante 03600",
    "addr:housenumber":"57",
    "addr:postcode":"03600",
    "addr:street":"Calle De Jardines",
    "iso:country":"ES",
    "sg:address":"Calle de Jardines, 57",
    "sg:city":"Elda",
    "sg:orig_category":"Cueros Y Pieles (al Por Mayor)",
    "sg:phone":"+34 965 39 12 11",
    "sg:postcode":"03600",
    "sg:province":"Alicante",
    "wof:name":"Martinez Serrano Francisco",
    "wof:placetype":"venue"
},
  "geometry": {"coordinates":[-0.7931755781,38.4785842896],"type":"Point"}
}