{
  "type": "Feature",
  "properties": {
    "iso:country":"ES",
    "sg:address":"Calle de Gordoniz, 31",
    "sg:city":"Bilbao",
    "sg:orig_category":"Peluqueros: De Se\u00d1oras",
    "sg:phone":"+34 944 21 51 52",
    "sg:postcode":"48010",
    "sg:province":"Vizcaya",
    "wof:name":"Nuance Peluqueros, S.l.",
    "wof:placetype":"venue"
},
  "geometry": {"coordinates":[-2.941229105,43.2576255798],"type":"Point"}
}