{
  "type": "Feature",
  "properties": {
    "iso:country":"ES",
    "sg:address":"Carrer de Ali Bei, 80",
    "sg:city":"Barcelona",
    "sg:orig_category":"Autob\u00das (explotaci\u00d3n Y Servicios De)",
    "sg:phone":"+34 932 65 68 66",
    "sg:postcode":"08013",
    "sg:province":"Barcelona",
    "sg:website":"www.alsinagraells.com",
    "wof:name":"Sociedad Anonima Alsina Graells De Autotransportes",
    "wof:placetype":"venue"
},
  "geometry": {"coordinates":[2.1824519634,41.3946228027],"type":"Point"}
}