{
  "type": "Feature",
  "properties": {
    "addr:full":"Calle de Virgen, 36 Madrigueras Albacete 02230",
    "addr:housenumber":"36",
    "addr:postcode":"02230",
    "addr:street":"Calle De Virgen",
    "iso:country":"ES",
    "sg:address":"Calle de Virgen, 36",
    "sg:city":"Madrigueras",
    "sg:orig_category":"Asesor\u00cda Fiscal Y Jur\u00cddica",
    "sg:phone":"+34 967 54 53 19",
    "sg:postcode":"02230",
    "sg:province":"Albacete",
    "wof:name":"Gestimar Asesores S.cooperativa",
    "wof:placetype":"venue"
},
  "geometry": {"coordinates":[-1.8012969494,39.2355155945],"type":"Point"}
}