{
  "type": "Feature",
  "properties": {
    "addr:full":"Calle de Gran Via, 16 Madrid Madrid 28013",
    "addr:housenumber":"16",
    "addr:postcode":"madrid;28013",
    "addr:street":"Calle De Gran Via",
    "iso:country":"ES",
    "sg:address":"Calle de Gran Via, 16",
    "sg:city":"Madrid",
    "sg:orig_category":"Deportes Y Programas De Aventura",
    "sg:phone":"+34 915 21 47 96",
    "sg:postcode":"28013",
    "sg:province":"Madrid",
    "sg:website":"www.aderutas.com",
    "wof:name":"Agrupacion Deportiva Rutas",
    "wof:placetype":"venue"
},
  "geometry": {"coordinates":[-3.6995220184,40.419670105],"type":"Point"}
}