{
  "type": "Feature",
  "properties": {
    "iso:country":"ES",
    "sg:address":"Calle de Paredes, 10",
    "sg:city":"Casar Caceres",
    "sg:orig_category":"Escayola Y Productos De Escayola (fabricaci\u00d3n, Al Por Mayor)",
    "sg:phone":"+34 927 29 04 00",
    "sg:postcode":"10190",
    "sg:province":"C\u00e1ceres",
    "wof:name":"Blanco Bueno Aniceto",
    "wof:placetype":"venue"
},
  "geometry": {"coordinates":[-6.4176640511,39.5611419678],"type":"Point"}
}