{
  "type": "Feature",
  "properties": {
    "addr:full":"Calle de Concepcion, 42 Fuente Palmera C\u00f3rdoba 14120",
    "addr:housenumber":"42",
    "addr:postcode":"14120",
    "addr:street":"Calle De Concepcion",
    "iso:country":"ES",
    "sg:address":"Calle de Concepcion, 42",
    "sg:city":"Fuente Palmera",
    "sg:orig_category":"Centros De Coordinaci\u00d3n",
    "sg:phone":"+34 957 63 82 26",
    "sg:postcode":"14120",
    "sg:province":"C\u00f3rdoba",
    "wof:name":"Martinez Y Wals S.c.",
    "wof:placetype":"venue"
},
  "geometry": {"coordinates":[-5.1009578705,37.7038612366],"type":"Point"}
}