{
  "type": "Feature",
  "properties": {
    "iso:country":"ES",
    "sg:address":"Carrer de Lluis Domenech I Muntaner, 6",
    "sg:city":"Esplugues Llobregat",
    "sg:orig_category":"M\u00c9dicos: Cirug\u00cda Urol\u00d3gica",
    "sg:phone":"+34 933 71 03 07",
    "sg:postcode":"08950",
    "sg:province":"Barcelona",
    "wof:name":"Aguilo Lucia Fernando",
    "wof:placetype":"venue"
},
  "geometry": {"coordinates":[2.0756115913,41.3649406433],"type":"Point"}
}