{
  "type": "Feature",
  "properties": {
    "iso:country":"ES",
    "sg:address":"Calle de Convento, 27",
    "sg:city":"Santisteban Puerto",
    "sg:orig_category":"Farmacias",
    "sg:phone":"+34 953 40 11 50",
    "sg:postcode":"23250",
    "sg:province":"Ja\u00e9n",
    "wof:name":"Martinez Higueras Ana",
    "wof:placetype":"venue"
},
  "geometry": {"coordinates":[-3.2057700157,38.250793457],"type":"Point"}
}