{
  "type": "Feature",
  "properties": {
    "addr:full":"Avda Astudillo (de), Km. 0249,0 Puerto Lumbreras Murcia 30890",
    "addr:postcode":"30890",
    "addr:street":"Avda Astudillo De Km. 0249,0",
    "iso:country":"ES",
    "sg:address":"Avda Astudillo (de), Km. 0249,0",
    "sg:city":"Puerto Lumbreras",
    "sg:orig_category":"Cr\u00cda De Animales",
    "sg:phone":"+34 968 40 28 37",
    "sg:postcode":"30890",
    "sg:province":"Murcia",
    "wof:name":"Gazquez Parra Francisco",
    "wof:placetype":"venue"
},
  "geometry": {"coordinates":[-1.8125690222,37.5551490784],"type":"Point"}
}