{
  "type": "Feature",
  "properties": {
    "addr:full":"Carr Paborde Marti, 23 Ciutadella Menorca Islas Baleares 07760",
    "addr:housenumber":"23",
    "addr:postcode":"07760",
    "addr:street":"Carr Paborde Marti",
    "iso:country":"ES",
    "sg:address":"Carr Paborde Marti, 23",
    "sg:city":"Ciutadella Menorca",
    "sg:orig_category":"Plomeros",
    "sg:phone":"+34 971 38 29 07",
    "sg:postcode":"07760",
    "sg:province":"Islas Baleares",
    "wof:name":"Fontaneria Fedelich S.l.",
    "wof:placetype":"venue"
},
  "geometry": {"coordinates":[3.8425049782,40.0011062622],"type":"Point"}
}