{
  "type": "Feature",
  "properties": {
    "addr:full":"Pl. El Pozo, 5 Roa Burgos 09300",
    "addr:housenumber":"5",
    "addr:postcode":"09300",
    "addr:street":"El Pozo",
    "iso:country":"ES",
    "sg:address":"Pl. El Pozo, 5",
    "sg:city":"Roa",
    "sg:orig_category":"Pescader\u00cdas (al Por Menor)",
    "sg:phone":"+34 947 54 01 05",
    "sg:postcode":"09300",
    "sg:province":"Burgos",
    "wof:name":"Ma\u00f1ero Farri\u00f1as Pedro",
    "wof:placetype":"venue"
},
  "geometry": {"coordinates":[-3.9271559715,41.6972465515],"type":"Point"}
}