{
  "type": "Feature",
  "properties": {
    "iso:country":"ES",
    "sg:address":"Calle de Rua, 11",
    "sg:city":"Le\u00f3n",
    "sg:orig_category":"Abogados",
    "sg:phone":"+34 987 20 64 73",
    "sg:postcode":"24003",
    "sg:province":"Le\u00f3n",
    "sg:website":"www.paginasamarillas.es",
    "wof:name":"Mendez Pedrero Juan Antonio",
    "wof:placetype":"venue"
},
  "geometry": {"coordinates":[-5.5698862076,42.5973854065],"type":"Point"}
}