{
  "type": "Feature",
  "properties": {
    "iso:country":"ES",
    "sg:address":"Calle de Ambroz, 5",
    "sg:city":"Madrid",
    "sg:orig_category":"Inmobiliaria (agencias)",
    "sg:phone":"+34 913 71 90 18",
    "sg:postcode":"28032",
    "sg:province":"Madrid",
    "wof:name":"Merino Lopez Luis Manuel",
    "wof:placetype":"venue"
},
  "geometry": {"coordinates":[-3.6059598923,40.4045524597],"type":"Point"}
}