{
  "type": "Feature",
  "properties": {
    "addr:full":"Calle de Puerto Principe, 3 Madrid Madrid 28043",
    "addr:housenumber":"3",
    "addr:postcode":"28043",
    "addr:street":"Calle De Puerto Principe",
    "iso:country":"ES",
    "sg:address":"Calle de Puerto Principe, 3",
    "sg:city":"Madrid",
    "sg:orig_category":"Asesor\u00cda Sobre Comunicaci\u00d3n De Empresas",
    "sg:phone":"+34 913 81 83 00",
    "sg:postcode":"28043",
    "sg:province":"Madrid",
    "wof:name":"Rp Tax Consultants S.l.",
    "wof:placetype":"venue"
},
  "geometry": {"coordinates":[-3.6452040672,40.469379425],"type":"Point"}
}