{
  "type": "Feature",
  "properties": {
    "addr:full":"Calle de Polavieja, General, S/n Melilla Melilla 52005",
    "addr:housenumber":"/ n",
    "addr:postcode":"52005",
    "addr:street":"Calle De Polavieja General S",
    "iso:country":"ES",
    "sg:address":"Calle de Polavieja, General, S/n",
    "sg:city":"Melilla",
    "sg:orig_category":"Asistencia Social",
    "sg:phone":"+34 952 67 50 51",
    "sg:postcode":"52005",
    "sg:province":"Melilla",
    "wof:name":"Instituto Nacional De La Seguridad Social.hermandad De Donantes De Sangre",
    "wof:placetype":"venue"
},
  "geometry": {"coordinates":[-2.9556701183,35.2835693359],"type":"Point"}
}