{
  "type": "Feature",
  "properties": {
    "iso:country":"ES",
    "sg:address":"Avgd Joaquim Sorolla, 37",
    "sg:city":"Alcasser",
    "sg:orig_category":"Agentes, Concesionarios Y Sucursales De Veh\u00cdculos",
    "sg:phone":"+34 961 24 11 13",
    "sg:postcode":"46290",
    "sg:province":"Valencia",
    "wof:name":"Bemon Motors S.l.",
    "wof:placetype":"venue"
},
  "geometry": {"coordinates":[-0.4431299865,39.3717384338],"type":"Point"}
}