{
  "type": "Feature",
  "properties": {
    "iso:country":"ES",
    "sg:address":"Calle de Ander Deuna, S/n",
    "sg:city":"Usansolo",
    "sg:orig_category":"Sanatorios M\u00c9dico",
    "sg:phone":"+34 944 36 37 00",
    "sg:postcode":"48960",
    "sg:province":"Vizcaya",
    "wof:name":"Euskaltel S.a.",
    "wof:placetype":"venue"
},
  "geometry": {"coordinates":[-2.819258213,43.2189826965],"type":"Point"}
}