{
  "type": "Feature",
  "properties": {
    "addr:full":"Calle de Bentejui, 82 Pto. Rosario Las Palmas 35600",
    "addr:housenumber":"82",
    "addr:postcode":"35600",
    "addr:street":"Calle De Bentejui;Pto. Rosario Las",
    "iso:country":"ES",
    "sg:address":"Calle de Bentejui, 82",
    "sg:city":"Pto. Rosario",
    "sg:orig_category":"Quincaller\u00cda (al Por Menor)",
    "sg:phone":"+34 928 85 13 48",
    "sg:postcode":"35600",
    "sg:province":"Las Palmas",
    "wof:name":"Saavedra Brito S.l.",
    "wof:placetype":"venue"
},
  "geometry": {"coordinates":[-13.8729152679,28.5087547302],"type":"Point"}
}