{
  "type": "Feature",
  "properties": {
    "addr:full":"Calle de Carde\u00d1as (de Las), 1 Navalcarnero Madrid 28600",
    "addr:housenumber":"1",
    "addr:postcode":"28600",
    "addr:street":"Calle De Carden\u0303As De Las",
    "iso:country":"ES",
    "sg:address":"Calle de Carde\u00d1as (de Las), 1",
    "sg:city":"Navalcarnero",
    "sg:orig_category":"Comercio De Piezas De Recambio Y De Accesorios De Veh\u00cdculos, Veh\u00cdculos Industriales",
    "sg:phone":"+34 918 11 00 25",
    "sg:postcode":"28600",
    "sg:province":"Madrid",
    "wof:name":"Recambios Mostoles S.l.",
    "wof:placetype":"venue"
},
  "geometry": {"coordinates":[-4.0073227882,40.2869377136],"type":"Point"}
}