{
  "type": "Feature",
  "properties": {
    "addr:full":"Calle de Colon, 52 Paiporta Valencia 46200",
    "addr:housenumber":"52",
    "addr:postcode":"46200",
    "addr:street":"Calle De Colon",
    "iso:country":"ES",
    "sg:address":"Calle de Colon, 52",
    "sg:city":"Paiporta",
    "sg:orig_category":"Cajas Para Embalar",
    "sg:phone":"+34 963 97 04 50",
    "sg:postcode":"46200",
    "sg:province":"Valencia",
    "sg:website":"www.ruraltorrent.com",
    "wof:name":"Caja Rural De Torrente",
    "wof:placetype":"venue"
},
  "geometry": {"coordinates":[-0.4170508087,39.425075531],"type":"Point"}
}