{
  "type": "Feature",
  "properties": {
    "iso:country":"ES",
    "sg:address":"Rua Canadelo Baixo, 64",
    "sg:city":"Vigo",
    "sg:orig_category":"Alimentaci\u00d3n General (al Por Menor)",
    "sg:phone":"+34 986 43 65 09",
    "sg:postcode":"36201",
    "sg:province":"Pontevedra",
    "wof:name":"Lago Abeleira Dolores",
    "wof:placetype":"venue"
},
  "geometry": {"coordinates":[-8.7095012665,42.2370071411],"type":"Point"}
}