{
  "type": "Feature",
  "properties": {
    "iso:country":"ES",
    "sg:address":"Avda Monelos, 109",
    "sg:city":"Coru\u00d1a",
    "sg:orig_category":"M\u00c9dicos: Reumatolog\u00cda",
    "sg:phone":"+34 981 28 32 59",
    "sg:postcode":"15009",
    "sg:province":"La Coru\u00f1a",
    "wof:name":"Atanes Sandoval Antonio Domingo",
    "wof:placetype":"venue"
},
  "geometry": {"coordinates":[-8.4013957977,43.346988678],"type":"Point"}
}