{
  "type": "Feature",
  "properties": {
    "addr:full":"Carrer de Sant Miquel, 6 Palma Islas Baleares 07002",
    "addr:housenumber":"6",
    "addr:postcode":"07002",
    "addr:street":"Carrer De Sant Miquel",
    "iso:country":"ES",
    "sg:address":"Carrer de Sant Miquel, 6",
    "sg:city":"Palma",
    "sg:orig_category":"Confiter\u00cdas, Chocolater\u00cdas (al Por Menor)",
    "sg:phone":"+34 971 72 48 08",
    "sg:postcode":"07002",
    "sg:province":"Islas Baleares",
    "wof:name":"Tutti Frutti 2000 S.l.",
    "wof:placetype":"venue"
},
  "geometry": {"coordinates":[2.652066946,39.5717849731],"type":"Point"}
}