{
  "type": "Feature",
  "properties": {
    "iso:country":"ES",
    "sg:address":"Calle de San Juan Bosco, 49",
    "sg:city":"Almeria",
    "sg:orig_category":"Agencias De Viajes",
    "sg:phone":"+34 950 28 10 82",
    "sg:postcode":"04005",
    "sg:province":"Almer\u00eda",
    "wof:name":"Creditos Bancarios Kasa",
    "wof:placetype":"venue"
},
  "geometry": {"coordinates":[-2.4553210735,36.8426628113],"type":"Point"}
}