{
  "type": "Feature",
  "properties": {
    "iso:country":"ES",
    "sg:address":"Rua Sanchez Calvi\u00d1o, 32",
    "sg:city":"Ferrol",
    "sg:orig_category":"Molduras, Junquillos, Listones Y Molduras Perforadas",
    "sg:phone":"+34 981 32 33 03",
    "sg:postcode":"15404",
    "sg:province":"La Coru\u00f1a",
    "wof:name":"Padin Pereiro Jose Manuel",
    "wof:placetype":"venue"
},
  "geometry": {"coordinates":[-8.2208023071,43.4877166748],"type":"Point"}
}