{
  "type": "Feature",
  "properties": {
    "iso:country":"ES",
    "sg:address":"Avda San Miguel, Km. 0017,8",
    "sg:city":"Iscar",
    "sg:orig_category":"Producci\u00d3n, Venta De Productos De Agricultura Biol\u00d3gica",
    "sg:phone":"+34 983 61 14 61",
    "sg:postcode":"47420",
    "sg:province":"Valladolid",
    "wof:name":"Castillo De Iscar Sociedad Cooperativa Agricola Limitada",
    "wof:placetype":"venue"
},
  "geometry": {"coordinates":[-4.5376338959,41.3601837158],"type":"Point"}
}