{
  "type": "Feature",
  "properties": {
    "iso:country":"ES",
    "sg:address":"Calle de Federico Ruiz Vertedor, 1",
    "sg:city":"Fuengirola",
    "sg:orig_category":"Animales (al Por Menor)",
    "sg:phone":"+34 952 46 26 70",
    "sg:postcode":"29640",
    "sg:province":"M\u00e1laga",
    "wof:name":"Rodriguez Garro Rocio",
    "wof:placetype":"venue"
},
  "geometry": {"coordinates":[-4.6239790916,36.5414886475],"type":"Point"}
}