{
  "type": "Feature",
  "properties": {
    "addr:full":"Cmno Vives (los), 8 Murada Alicante 03315",
    "addr:housenumber":"8",
    "addr:postcode":"03315",
    "addr:street":"Cmno Vives Los",
    "iso:country":"ES",
    "sg:address":"Cmno Vives (los), 8",
    "sg:city":"Murada",
    "sg:orig_category":"Empresas De Desmonte",
    "sg:phone":"+34 966 77 94 81",
    "sg:postcode":"03315",
    "sg:province":"Alicante",
    "wof:name":"Excavaciones Ramon E Hjos S.l.",
    "wof:placetype":"venue"
},
  "geometry": {"coordinates":[-0.9603610039,38.1707115173],"type":"Point"}
}