{
  "type": "Feature",
  "properties": {
    "addr:full":"Pase Santo Tomas (de), 24 Avila \u00c1vila 05003",
    "addr:postcode":"05003",
    "addr:street":"A\u0301Vila",
    "iso:country":"ES",
    "sg:address":"Pase Santo Tomas (de), 24",
    "sg:city":"Avila",
    "sg:orig_category":"Promotores Constructores",
    "sg:phone":"+34 920 22 94 85",
    "sg:postcode":"05003",
    "sg:province":"\u00c1vila",
    "wof:name":"Mugasa3 S.l.",
    "wof:placetype":"venue"
},
  "geometry": {"coordinates":[-4.6914691925,40.6520195007],"type":"Point"}
}