{
  "type": "Feature",
  "properties": {
    "addr:full":"Carrer de Gran, 22 Argentona Barcelona 08310",
    "addr:housenumber":"22",
    "addr:postcode":"08310",
    "addr:street":"Carrer De Gran",
    "iso:country":"ES",
    "sg:address":"Carrer de Gran, 22",
    "sg:city":"Argentona",
    "sg:orig_category":"Carnicer\u00cdas, Carnicer\u00cdas",
    "sg:phone":"+34 937 97 03 07",
    "sg:postcode":"08310",
    "sg:province":"Barcelona",
    "wof:name":"Delicater Milenium S.l.",
    "wof:placetype":"venue"
},
  "geometry": {"coordinates":[2.4015479088,41.5547981262],"type":"Point"}
}