{
  "type": "Feature",
  "properties": {
    "addr:full":"Ntra Sra De La Asuncion, 4 Jumilla Murcia 30520",
    "addr:housenumber":"4",
    "addr:postcode":"30520",
    "addr:street":"Ntra Sra De La Asuncion",
    "iso:country":"ES",
    "sg:address":"Ntra Sra De La Asuncion, 4",
    "sg:city":"Jumilla",
    "sg:orig_category":"Ingeniero",
    "sg:phone":"+34 968 75 74 31",
    "sg:postcode":"30520",
    "sg:province":"Murcia",
    "wof:name":"Burruezo Mateo Pedro Miguel",
    "wof:placetype":"venue"
},
  "geometry": {"coordinates":[-1.3305770159,38.4706459045],"type":"Point"}
}