{
  "type": "Feature",
  "properties": {
    "addr:full":"Avda Aljarafe (el), 25 Pilas Sevilla 41840",
    "addr:postcode":"41840",
    "addr:street":"Avda Aljarafe",
    "iso:country":"ES",
    "sg:address":"Avda Aljarafe (el), 25",
    "sg:city":"Pilas",
    "sg:orig_category":"Mec\u00c1nico Del Autom\u00d3vil",
    "sg:phone":"+34 954 75 02 90",
    "sg:postcode":"41840",
    "sg:province":"Sevilla",
    "wof:name":"Medina Barragan Antonio",
    "wof:placetype":"venue"
},
  "geometry": {"coordinates":[-6.2948679924,37.3025741577],"type":"Point"}
}