{
  "type": "Feature",
  "properties": {
    "addr:full":"Carr Bastio, 10 Mao Islas Baleares 07703",
    "addr:housenumber":"10",
    "addr:postcode":"07703",
    "addr:street":"Carr Bastio",
    "iso:country":"ES",
    "sg:address":"Carr Bastio, 10",
    "sg:city":"Mao",
    "sg:orig_category":"Empresarios",
    "sg:phone":"+34 971 35 37 25",
    "sg:postcode":"07703",
    "sg:province":"Islas Baleares",
    "wof:name":"Fundacion Convivencia",
    "wof:placetype":"venue"
},
  "geometry": {"coordinates":[4.2623901367,39.8890190125],"type":"Point"}
}