{
  "type": "Feature",
  "properties": {
    "addr:full":"Avda Constitucion, 30 Torredelcampo Ja\u00e9n 23640",
    "addr:housenumber":"30",
    "addr:postcode":"23640",
    "addr:street":"Avda Constitucion;Jae\u0301N",
    "iso:country":"ES",
    "sg:address":"Avda Constitucion, 30",
    "sg:city":"Torredelcampo",
    "sg:orig_category":"Caf\u00c9s, Bares, Cervecer\u00cdas",
    "sg:phone":"+34 953 56 81 07",
    "sg:postcode":"23640",
    "sg:province":"Ja\u00e9n",
    "wof:name":"Moral Lopez Francisco",
    "wof:placetype":"venue"
},
  "geometry": {"coordinates":[-3.8999290466,37.7694549561],"type":"Point"}
}