{
  "type": "Feature",
  "properties": {
    "iso:country":"ES",
    "sg:address":"Calle de Katalina Eleizegi, 7",
    "sg:city":"Donostia-san Sebastian",
    "sg:orig_category":"Asociaciones, Organismos Culturales Y Socioeducativos",
    "sg:phone":"+34 943 45 15 65",
    "sg:postcode":"20009",
    "sg:province":"Guip\u00f9zcoa",
    "wof:name":"Gambara Kultur Taldea S.l.",
    "wof:placetype":"venue"
},
  "geometry": {"coordinates":[-1.9876439571,43.3054924011],"type":"Point"}
}