{
  "type": "Feature",
  "properties": {
    "iso:country":"ES",
    "sg:address":"Calle de Doctor Morcillo, 7",
    "sg:city":"Tarancon",
    "sg:orig_category":"M\u00c9dicos: An\u00c1lisis Cl\u00cdnicos",
    "sg:phone":"+34 969 32 00 09",
    "sg:postcode":"16400",
    "sg:province":"Cuenca",
    "wof:name":"Cimar C.b.",
    "wof:placetype":"venue"
},
  "geometry": {"coordinates":[-3.0064089298,40.0107192993],"type":"Point"}
}