{
  "type": "Feature",
  "properties": {
    "iso:country":"ES",
    "sg:address":"Calle de Hierro, 6",
    "sg:city":"Villa Rio",
    "sg:orig_category":"Asesor\u00cda Fiscal Y Jur\u00cddica",
    "sg:phone":"+34 957 17 76 10",
    "sg:postcode":"14640",
    "sg:province":"C\u00f3rdoba",
    "wof:name":"Castellano Rodriguez Antonio Manuel",
    "wof:placetype":"venue"
},
  "geometry": {"coordinates":[-4.2913088799,37.9817695618],"type":"Point"}
}