{
  "type": "Feature",
  "properties": {
    "addr:full":"Avda Generalisimo - Curtis-estacion, 37 Curtis-estacion A Coru\u00f1a 15379",
    "addr:housenumber":"37",
    "addr:postcode":"15379",
    "addr:street":"Avda Generalisimo Curtis-Estacion;Corun\u0303A",
    "iso:country":"ES",
    "sg:address":"Avda Generalisimo - Curtis-estacion, 37",
    "sg:city":"Curtis-estacion",
    "sg:orig_category":"Caf\u00c9s, Bares, Cervecer\u00cdas",
    "sg:phone":"+34 981 78 62 56",
    "sg:postcode":"15379",
    "sg:province":"A Coru\u00f1a",
    "wof:name":"Vazquez Vazquez Jose",
    "wof:placetype":"venue"
},
  "geometry": {"coordinates":[-8.3964595795,43.3701095581],"type":"Point"}
}