{
  "type": "Feature",
  "properties": {
    "iso:country":"ES",
    "sg:address":"Carrer de Sant Josep, 20",
    "sg:city":"Sabadell",
    "sg:orig_category":"Mec\u00c1nico Del Autom\u00d3vil",
    "sg:phone":"+34 937 26 17 07",
    "sg:postcode":"08202",
    "sg:province":"Barcelona",
    "wof:name":"Valle Molina Antonio",
    "wof:placetype":"venue"
},
  "geometry": {"coordinates":[2.110656023,41.5478134155],"type":"Point"}
}