{
  "type": "Feature",
  "properties": {
    "addr:full":"Avda Pescadores (los), 8 Alcala Santa Cruz De Tenerife 38686",
    "addr:housenumber":"8",
    "addr:postcode":"38686",
    "addr:street":"Avda Pescadores Los",
    "iso:country":"ES",
    "sg:address":"Avda Pescadores (los), 8",
    "sg:city":"Alcala",
    "sg:orig_category":"Peluquer\u00cdas, Peluquer\u00cda Mixta",
    "sg:phone":"+34 922 86 50 67",
    "sg:postcode":"38686",
    "sg:province":"Santa Cruz De Tenerife",
    "wof:name":"Afonso De Leon Maria Candelaria",
    "wof:placetype":"venue"
},
  "geometry": {"coordinates":[-16.8274040222,28.2016620636],"type":"Point"}
}