{
  "type": "Feature",
  "properties": {
    "addr:full":"Pl Joanic, 3 Barcelona Barcelona 08024",
    "addr:housenumber":"3",
    "addr:postcode":"08024",
    "addr:street":"Pl Joanic",
    "iso:country":"ES",
    "sg:address":"Pl Joanic, 3",
    "sg:city":"Barcelona",
    "sg:orig_category":"Asociaciones, Organismos Culturales Y Socioeducativos",
    "sg:phone":"+34 932 84 04 91",
    "sg:postcode":"08024",
    "sg:province":"Barcelona",
    "wof:name":"Asociacion De Taichi Taoista De Espa\u00f1a",
    "wof:placetype":"venue"
},
  "geometry": {"coordinates":[2.1623942852,41.4052009583],"type":"Point"}
}