{
  "type": "Feature",
  "properties": {
    "iso:country":"ES",
    "sg:address":"Calle de Cabeza, 4",
    "sg:city":"Baza",
    "sg:orig_category":"Confecci\u00d3n De Trajes Para Se\u00d1oras",
    "sg:phone":"+34 958 70 04 76",
    "sg:postcode":"18800",
    "sg:province":"Granada",
    "wof:name":"Martinez Sanchez Jose Luis",
    "wof:placetype":"venue"
},
  "geometry": {"coordinates":[-2.7733290195,37.4898948669],"type":"Point"}
}