{
  "type": "Feature",
  "properties": {
    "iso:country":"ES",
    "sg:address":"Calle de Feria, S/n",
    "sg:city":"Arjona",
    "sg:orig_category":"Imprenta",
    "sg:phone":"+34 953 52 37 56",
    "sg:postcode":"23760",
    "sg:province":"Ja\u00e9n",
    "wof:name":"Castillo Burgos Juan Carlos",
    "wof:placetype":"venue"
},
  "geometry": {"coordinates":[-4.0609068871,37.9375991821],"type":"Point"}
}