{
  "type": "Feature",
  "properties": {
    "addr:full":"Av Joan Miro, 155 Sant Agusti Islas Baleares 07015",
    "addr:housenumber":"155",
    "addr:postcode":"07015",
    "addr:street":"Av Joan Miro;Sant Agusti",
    "iso:country":"ES",
    "sg:address":"Av Joan Miro, 155",
    "sg:city":"Sant Agusti",
    "sg:orig_category":"Juegos Y Juguetes (al Por Menor)",
    "sg:phone":"+34 971 40 50 58",
    "sg:postcode":"07015",
    "sg:province":"Islas Baleares",
    "wof:name":"Pamadi S.l.",
    "wof:placetype":"venue"
},
  "geometry": {"coordinates":[2.6173250675,39.5514450073],"type":"Point"}
}