{
  "type": "Feature",
  "properties": {
    "addr:full":"Calle de Espoz Y Mina, 1 Madrid Madrid 28012",
    "addr:housenumber":"1",
    "addr:postcode":"28012",
    "addr:street":"Calle De Espoz Y Mina",
    "iso:country":"ES",
    "sg:address":"Calle de Espoz Y Mina, 1",
    "sg:city":"Madrid",
    "sg:orig_category":"Loter\u00cda Y T\u00d3mbola",
    "sg:phone":"+34 915 32 54 97",
    "sg:postcode":"28012",
    "sg:province":"Madrid",
    "wof:name":"Lucas Fernandez-aviles Carlos",
    "wof:placetype":"venue"
},
  "geometry": {"coordinates":[-3.7021079063,40.4165458679],"type":"Point"}
}