{
  "type": "Feature",
  "properties": {
    "iso:country":"ES",
    "sg:address":"Plaz Arco (del), 6",
    "sg:city":"Colmenar Oreja",
    "sg:orig_category":"Material Y Herramientas Agr\u00cdcolas",
    "sg:phone":"+34 918 94 31 83",
    "sg:postcode":"28380",
    "sg:province":"Madrid",
    "wof:name":"Crespo Garcia David",
    "wof:placetype":"venue"
},
  "geometry": {"coordinates":[-3.3868250847,40.1092643738],"type":"Point"}
}