{
  "type": "Feature",
  "properties": {
    "addr:full":"Calle de Ronda De Las Cuestas, 69 Paracuellos De Jarama Madrid 28860",
    "addr:housenumber":"69",
    "addr:postcode":"28860",
    "addr:street":"Calle De Ronda De Las Cuestas",
    "iso:country":"ES",
    "sg:address":"Calle de Ronda De Las Cuestas, 69",
    "sg:city":"Paracuellos De Jarama",
    "sg:orig_category":"Urbanistas",
    "sg:phone":"+34 916 58 13 47",
    "sg:postcode":"28860",
    "sg:province":"Madrid",
    "sg:website":"www.carlosclemente.com",
    "wof:name":"Carlos Clemente S.l.",
    "wof:placetype":"venue"
},
  "geometry": {"coordinates":[-3.5341498852,40.5063552856],"type":"Point"}
}