{
  "type": "Feature",
  "properties": {
    "addr:full":"Calle de Fernan Perez De Oliva, 30 Albacete Albacete 02005",
    "addr:housenumber":"30",
    "addr:postcode":"02005",
    "addr:street":"Calle De Fernan Perez De Oliva",
    "iso:country":"ES",
    "sg:address":"Calle de Fernan Perez De Oliva, 30",
    "sg:city":"Albacete",
    "sg:orig_category":"Chapister\u00cda",
    "sg:phone":"+34 967 24 10 31",
    "sg:postcode":"02005",
    "sg:province":"Albacete",
    "wof:name":"Lopez Perez Antonio",
    "wof:placetype":"venue"
},
  "geometry": {"coordinates":[-1.8610990047,39.0030593872],"type":"Point"}
}