{
  "type": "Feature",
  "properties": {
    "addr:full":"Avgd Abu-masaifa, 16 Xativa Valencia 46800",
    "addr:housenumber":"16",
    "addr:postcode":"46800",
    "addr:street":"Abu-Masaifa",
    "iso:country":"ES",
    "sg:address":"Avgd Abu-masaifa, 16",
    "sg:city":"Xativa",
    "sg:orig_category":"Cajas Para Embalar",
    "sg:phone":"+34 962 28 13 33",
    "sg:postcode":"46800",
    "sg:province":"Valencia",
    "wof:name":"Caja Rural Del Mediterraneo Ruralcaja S Coop De Credito",
    "wof:placetype":"venue"
},
  "geometry": {"coordinates":[-0.5286419988,38.988735199],"type":"Point"}
}