{
  "type": "Feature",
  "properties": {
    "iso:country":"ES",
    "sg:address":"Calle de Modesto Lafuente, 47",
    "sg:city":"Mayorga",
    "sg:orig_category":"Promotores Constructores",
    "sg:phone":"+34 983 75 14 07",
    "sg:postcode":"47680",
    "sg:province":"Valladolid",
    "wof:name":"Construcciones Nivavi S.l.",
    "wof:placetype":"venue"
},
  "geometry": {"coordinates":[-5.2655391693,42.1644897461],"type":"Point"}
}