{
  "type": "Feature",
  "properties": {
    "addr:full":"Calle de Astorga, S/n Villoria De Orbigo Le\u00f3n 24358",
    "addr:housenumber":"s / n",
    "addr:postcode":"24358",
    "addr:street":"Calle De Astorga;Leo\u0301N",
    "iso:country":"ES",
    "sg:address":"Calle de Astorga, S/n",
    "sg:city":"Villoria De Orbigo",
    "sg:orig_category":"Iglesia Cat\u00d3lica",
    "sg:phone":"+34 987 37 43 82",
    "sg:postcode":"24358",
    "sg:province":"Le\u00f3n",
    "wof:name":"Parroquia De Villoria De Orbigo",
    "wof:placetype":"venue"
},
  "geometry": {"coordinates":[-5.8861675262,42.4145927429],"type":"Point"}
}