{
  "type": "Feature",
  "properties": {
    "addr:full":"Calle de Maria De Molina, 12 Palencia Palencia 34002",
    "addr:housenumber":"12",
    "addr:postcode":"34002",
    "addr:street":"Calle De Maria De Molina",
    "iso:country":"ES",
    "sg:address":"Calle de Maria De Molina, 12",
    "sg:city":"Palencia",
    "sg:orig_category":"Farmacias",
    "sg:phone":"+34 979 72 50 47",
    "sg:postcode":"34002",
    "sg:province":"Palencia",
    "wof:name":"Gutierrez Martin Maria Del Carmen",
    "wof:placetype":"venue"
},
  "geometry": {"coordinates":[-4.5258860588,42.0030822754],"type":"Point"}
}