{
  "type": "Feature",
  "properties": {
    "addr:full":"Calle de Sanchez Perrier, 6 Sevilla Sevilla 41009",
    "addr:housenumber":"6",
    "addr:postcode":"41009",
    "addr:street":"Calle De Sanchez Perrier",
    "iso:country":"ES",
    "sg:address":"Calle de Sanchez Perrier, 6",
    "sg:city":"Sevilla",
    "sg:orig_category":"Agentes Generales De Seguros",
    "sg:phone":"+34 954 90 63 35",
    "sg:postcode":"41009",
    "sg:province":"Sevilla",
    "wof:name":"Pe\u00f1as Cano Amelia",
    "wof:placetype":"venue"
},
  "geometry": {"coordinates":[-5.9854531288,37.4033164978],"type":"Point"}
}