{
  "type": "Feature",
  "properties": {
    "iso:country":"ES",
    "sg:address":"Sol, 25",
    "sg:city":"Cala Millor",
    "sg:orig_category":"Marroquiner\u00cda (confecci\u00d3n)",
    "sg:phone":"+34 971 58 56 27",
    "sg:postcode":"07560",
    "sg:province":"Islas Baleares",
    "wof:name":"Servera Servera Margarita",
    "wof:placetype":"venue"
},
  "geometry": {"coordinates":[3.3840200901,39.6013717651],"type":"Point"}
}