{
  "type": "Feature",
  "properties": {
    "iso:country":"ES",
    "sg:address":"Calle de Traperia, 30",
    "sg:city":"Catedral",
    "sg:orig_category":"Panader\u00cdas, Panader\u00cdas",
    "sg:phone":"+34 968 21 18 00",
    "sg:postcode":"30001",
    "sg:province":"Murcia",
    "wof:name":"Lorca Espada Antonio",
    "wof:placetype":"venue"
},
  "geometry": {"coordinates":[-1.1290949583,37.9861907959],"type":"Point"}
}