{
  "type": "Feature",
  "properties": {
    "iso:country":"ES",
    "sg:address":"Plaz Souto (do), 20",
    "sg:city":"Amoeiro",
    "sg:orig_category":"Art\u00cdculos Funerarios (al Por Menor)",
    "sg:phone":"+34 988 28 10 50",
    "sg:postcode":"32170",
    "sg:province":"Ourense",
    "wof:name":"Vazquez Pi\u00f1eiro Ramon",
    "wof:placetype":"venue"
},
  "geometry": {"coordinates":[-7.9451670647,42.4144706726],"type":"Point"}
}