{
  "type": "Feature",
  "properties": {
    "iso:country":"ES",
    "sg:address":"Avda Primero De Mayo, 35",
    "sg:city":"Calasparra",
    "sg:orig_category":"Pod\u00d3logos: Pedicuros",
    "sg:phone":"+34 968 74 55 52",
    "sg:postcode":"30420",
    "sg:province":"Murcia",
    "wof:name":"Alonso Iba\u00f1ez Lourdes",
    "wof:placetype":"venue"
},
  "geometry": {"coordinates":[-1.6966679096,38.2282104492],"type":"Point"}
}