{
  "type": "Feature",
  "properties": {
    "addr:full":"Calle de Moros (los), S/n Puerto De Santa Maria C\u00e1diz 11500",
    "addr:housenumber":"s / n",
    "addr:postcode":"11500",
    "addr:street":"Calle De Moros Los;Ca\u0301Diz",
    "iso:country":"ES",
    "sg:address":"Calle de Moros (los), S/n",
    "sg:city":"Puerto De Santa Maria",
    "sg:orig_category":"Peluqueros: De Se\u00d1oras",
    "sg:phone":"+34 956 87 33 58",
    "sg:postcode":"11500",
    "sg:province":"C\u00e1diz",
    "wof:name":"Torres Trujillo Francisca De",
    "wof:placetype":"venue"
},
  "geometry": {"coordinates":[-6.2300691605,36.5959892273],"type":"Point"}
}