{
  "type": "Feature",
  "properties": {
    "iso:country":"ES",
    "sg:address":"Avda Mariano Diaz (de), 15",
    "sg:city":"Villarejo Salvanes",
    "sg:orig_category":"Pirotecnia (espect\u00c1culos)",
    "sg:phone":"+34 918 74 24 47",
    "sg:postcode":"28590",
    "sg:province":"Madrid",
    "wof:name":"Pirotecnia Vulcano S.l.",
    "wof:placetype":"venue"
},
  "geometry": {"coordinates":[-3.2829840183,40.1690788269],"type":"Point"}
}