{
  "type": "Feature",
  "properties": {
    "iso:country":"ES",
    "sg:address":"Avda Espa\u00d1a, 20",
    "sg:city":"Majadahonda",
    "sg:orig_category":"Asociaciones Y Clubs Deportivos",
    "sg:phone":"+34 916 39 40 39",
    "sg:postcode":"28220",
    "sg:province":"Madrid",
    "wof:name":"Club Taekwondo Las Rozas",
    "wof:placetype":"venue"
},
  "geometry": {"coordinates":[-3.8684430122,40.4728240967],"type":"Point"}
}