{
  "type": "Feature",
  "properties": {
    "iso:country":"ES",
    "sg:address":"Calle de Enmedio, 91",
    "sg:city":"Castellon",
    "sg:orig_category":"Cl\u00cdnicas Dentales",
    "sg:phone":"+34 964 21 44 64",
    "sg:postcode":"12001",
    "sg:province":"Castell\u00f3n",
    "wof:name":"Llorente Illeras Jose Victor",
    "wof:placetype":"venue"
},
  "geometry": {"coordinates":[-0.0379570015,39.987701416],"type":"Point"}
}