{
  "type": "Feature",
  "properties": {
    "iso:country":"ES",
    "sg:address":"Avda Marques De Corbera, 44",
    "sg:city":"Madrid",
    "sg:orig_category":"Pod\u00d3logos: Pedicuros",
    "sg:phone":"+34 914 04 94 18",
    "sg:postcode":"28017",
    "sg:province":"Madrid",
    "wof:name":"Lopez Benito Adriana",
    "wof:placetype":"venue"
},
  "geometry": {"coordinates":[-3.6521120071,40.425327301],"type":"Point"}
}