{
  "type": "Feature",
  "properties": {
    "addr:full":"Pase Delicias, 120 Madrid Madrid 28045",
    "addr:housenumber":"120",
    "addr:postcode":"madrid;28045",
    "iso:country":"ES",
    "sg:address":"Pase Delicias, 120",
    "sg:city":"Madrid",
    "sg:orig_category":"Administradores De Bienes Y Delegados De Comunidades De Propietarios",
    "sg:phone":"+34 914 74 02 24",
    "sg:postcode":"28045",
    "sg:province":"Madrid",
    "wof:name":"Fincas Corral S.l.",
    "wof:placetype":"venue"
},
  "geometry": {"coordinates":[-3.6948049068,40.3948745728],"type":"Point"}
}