{
  "type": "Feature",
  "properties": {
    "iso:country":"ES",
    "sg:address":"Av Sant Jordi, De, 5",
    "sg:city":"Eivissa",
    "sg:orig_category":"Poller\u00cda Y Caza (al Por Menor)",
    "sg:phone":"+34 971 30 62 08",
    "sg:postcode":"07800",
    "sg:province":"Islas Baleares",
    "wof:name":"Polleria Residencial S.l.",
    "wof:placetype":"venue"
},
  "geometry": {"coordinates":[1.4187940359,38.9045906067],"type":"Point"}
}