{
  "type": "Feature",
  "properties": {
    "addr:full":"Carrer de Maresme, 147 Barcelona Barcelona 08019",
    "addr:housenumber":"147",
    "addr:postcode":"08019",
    "addr:street":"Carrer De Maresme",
    "iso:country":"ES",
    "sg:address":"Carrer de Maresme, 147",
    "sg:city":"Barcelona",
    "sg:orig_category":"Molduras, Junquillos, Listones Y Molduras Perforadas",
    "sg:phone":"+34 933 07 85 62",
    "sg:postcode":"08019",
    "sg:province":"Barcelona",
    "wof:name":"Casta\u00f1er Magallon Maria Eugenia",
    "wof:placetype":"venue"
},
  "geometry": {"coordinates":[2.2094500065,41.4169273376],"type":"Point"}
}