{
  "type": "Feature",
  "properties": {
    "iso:country":"ES",
    "sg:address":"Ctra Belagua, Km. 0009,0",
    "sg:city":"Isaba",
    "sg:orig_category":"Fabricaci\u00d3n De Quesos",
    "sg:phone":"+34 948 39 40 39",
    "sg:postcode":"31417",
    "sg:province":"Navarra",
    "wof:name":"Hualde Ituarte Maria Gema Y Marco Garces Jose Manuel S.cv.",
    "wof:placetype":"venue"
},
  "geometry": {"coordinates":[-0.9265909791,42.8597221375],"type":"Point"}
}