{
  "type": "Feature",
  "properties": {
    "iso:country":"ES",
    "sg:address":"Carrer de Girona, 62",
    "sg:city":"Granollers",
    "sg:orig_category":"Urbanistas",
    "sg:phone":"+34 938 79 25 61",
    "sg:postcode":"08402",
    "sg:province":"Barcelona",
    "wof:name":"Vila Pont Juan",
    "wof:placetype":"venue"
},
  "geometry": {"coordinates":[2.291328907,41.6111984253],"type":"Point"}
}