{
  "type": "Feature",
  "properties": {
    "iso:country":"ES",
    "sg:address":"Calle de Hermanos Alvarez Quintero, 1",
    "sg:city":"Mazarron",
    "sg:orig_category":"Centros De Educaci\u00d3n Especial",
    "sg:phone":"+34 968 59 08 97",
    "sg:postcode":"30870",
    "sg:province":"Murcia",
    "wof:name":"Colegio Publico La Ace\u00f1a",
    "wof:placetype":"venue"
},
  "geometry": {"coordinates":[-1.3125959635,37.6036186218],"type":"Point"}
}