{
  "type": "Feature",
  "properties": {
    "iso:country":"ES",
    "sg:address":"Calle de Nicolas Sanchez, 108",
    "sg:city":"Madrid",
    "sg:orig_category":"Mec\u00c1nico Del Autom\u00d3vil",
    "sg:phone":"+34 914 75 36 12",
    "sg:postcode":"28026",
    "sg:province":"Madrid",
    "wof:name":"Talleres Moya Sport S.l.",
    "wof:placetype":"venue"
},
  "geometry": {"coordinates":[-3.7056670189,40.3813400269],"type":"Point"}
}