{
  "type": "Feature",
  "properties": {
    "iso:country":"ES",
    "sg:address":"Calle de Santiago Prieto, 3",
    "sg:city":"Madrid",
    "sg:orig_category":"Asesor\u00cda Fiscal Y Jur\u00cddica",
    "sg:phone":"+34 914 60 50 79",
    "sg:postcode":"28019",
    "sg:province":"Madrid",
    "wof:name":"C.g.i. Asesores S.a.c.",
    "wof:placetype":"venue"
},
  "geometry": {"coordinates":[-3.7219049931,40.3872871399],"type":"Point"}
}