{
  "type": "Feature",
  "properties": {
    "iso:country":"ES",
    "sg:address":"Calle de Jose Zorrilla, 75",
    "sg:city":"Segovia",
    "sg:orig_category":"Pescader\u00cdas (al Por Menor)",
    "sg:phone":"+34 921 42 13 92",
    "sg:postcode":"40002",
    "sg:province":"Segovia",
    "wof:name":"Rivero Marcos Javier",
    "wof:placetype":"venue"
},
  "geometry": {"coordinates":[-4.1152291298,40.940612793],"type":"Point"}
}