{
  "type": "Feature",
  "properties": {
    "addr:full":"G.v. Corts Catalanes, 743 Barcelona Barcelona 08013",
    "addr:housenumber":"743",
    "addr:postcode":"08013",
    "addr:street":"Catalanes",
    "iso:country":"ES",
    "sg:address":"G.v. Corts Catalanes, 743",
    "sg:city":"Barcelona",
    "sg:orig_category":"Librer\u00cdas",
    "sg:phone":"+34 932 45 14 99",
    "sg:postcode":"08013",
    "sg:province":"Barcelona",
    "wof:name":"Martinez Roca Isidro",
    "wof:placetype":"venue"
},
  "geometry": {"coordinates":[2.1805579662,41.3990821838],"type":"Point"}
}