{
  "type": "Feature",
  "properties": {
    "addr:full":"Carrer de Pedrell, 78 Barcelona Barcelona 08032",
    "addr:housenumber":"78",
    "addr:postcode":"08032",
    "addr:street":"Carrer De Pedrell",
    "iso:country":"ES",
    "sg:address":"Carrer de Pedrell, 78",
    "sg:city":"Barcelona",
    "sg:orig_category":"Enfermeras: Consultas, Atenci\u00d3n A Domicilio",
    "sg:phone":"+34 934 20 61 98",
    "sg:postcode":"08032",
    "sg:province":"Barcelona",
    "wof:name":"Celma Palacios Maria Jose",
    "wof:placetype":"venue"
},
  "geometry": {"coordinates":[2.1639020443,41.424331665],"type":"Point"}
}