{
  "type": "Feature",
  "properties": {
    "iso:country":"ES",
    "sg:address":"Avda Gaspar Aguilar, 24",
    "sg:city":"Valencia",
    "sg:orig_category":"Inmobiliaria (agencias)",
    "sg:phone":"+34 963 58 11 26",
    "sg:postcode":"46007",
    "sg:province":"Valencia",
    "wof:name":"Gimeno Gil Pablo",
    "wof:placetype":"venue"
},
  "geometry": {"coordinates":[-0.3899889886,39.4571113586],"type":"Point"}
}