{
  "type": "Feature",
  "properties": {
    "addr:full":"Carrer de Saragossa, 46 Barcelona Barcelona 08006",
    "addr:housenumber":"46",
    "addr:postcode":"08006",
    "addr:street":"Carrer De Saragossa",
    "iso:country":"ES",
    "sg:address":"Carrer de Saragossa, 46",
    "sg:city":"Barcelona",
    "sg:orig_category":"Comercio, Reparaci\u00d3n De Motocicletas, Bicicletas Y Piezas Sueltas",
    "sg:phone":"+34 934 15 08 03",
    "sg:postcode":"08006",
    "sg:province":"Barcelona",
    "wof:name":"Warm-up S.c.",
    "wof:placetype":"venue"
},
  "geometry": {"coordinates":[2.1483120918,41.4026565552],"type":"Point"}
}