{
  "type": "Feature",
  "properties": {
    "iso:country":"ES",
    "sg:address":"Cno. Real, 141",
    "sg:city":"Agua Garcia",
    "sg:orig_category":"Agentes, Concesionarios Y Sucursales De Veh\u00cdculos",
    "sg:phone":"+34 922 56 72 19",
    "sg:postcode":"38355",
    "sg:province":"Santa Cruz De Tenerife",
    "wof:name":"Autos Ramos 24 S.l.",
    "wof:placetype":"venue"
},
  "geometry": {"coordinates":[-16.3987197876,28.4689788818],"type":"Point"}
}