{
  "type": "Feature",
  "properties": {
    "addr:full":"Carrer de Bosch I Gimpera, 26 Barcelona Barcelona 08034",
    "addr:housenumber":"26",
    "addr:postcode":"08034",
    "addr:street":"Carrer De Bosch I Gimpera",
    "iso:country":"ES",
    "sg:address":"Carrer de Bosch I Gimpera, 26",
    "sg:city":"Barcelona",
    "sg:orig_category":"Inmobiliaria (agencias)",
    "sg:phone":"+34 932 05 56 47",
    "sg:postcode":"08034",
    "sg:province":"Barcelona",
    "wof:name":"Edas Inversion Expansion Inmobiliaria S.l.",
    "wof:placetype":"venue"
},
  "geometry": {"coordinates":[2.1171739101,41.3955955505],"type":"Point"}
}