{
  "type": "Feature",
  "properties": {
    "iso:country":"ES",
    "sg:address":"Avda San Miguel, 15",
    "sg:city":"Iscar",
    "sg:orig_category":"Ense\u00d1anza, Formaci\u00d3n Profesional: Aprendizaje",
    "sg:phone":"+34 983 62 04 87",
    "sg:postcode":"47420",
    "sg:province":"Valladolid",
    "wof:name":"Cruz Roja Espa\u00f1ola",
    "wof:placetype":"venue"
},
  "geometry": {"coordinates":[-4.5376338959,41.3601837158],"type":"Point"}
}