{
  "type": "Feature",
  "properties": {
    "iso:country":"ES",
    "sg:address":"Rinconada De Grabiel Y Galan, 70",
    "sg:city":"Navalmoral Mata",
    "sg:orig_category":"Psic\u00d3logos",
    "sg:phone":"+34 927 53 49 83",
    "sg:postcode":"10300",
    "sg:province":"C\u00e1ceres",
    "wof:name":"Centro De Psicolgia Aplicada Soledad Pulido",
    "wof:placetype":"venue"
},
  "geometry": {"coordinates":[-5.5375142097,39.8904418945],"type":"Point"}
}