{
  "type": "Feature",
  "properties": {
    "iso:country":"ES",
    "sg:address":"Calle de Bronce, 46",
    "sg:city":"Moraleja Enmedio",
    "sg:orig_category":"Maquinaria Para Industrias Diversas",
    "sg:phone":"+34 916 09 31 70",
    "sg:postcode":"28950",
    "sg:province":"Madrid",
    "wof:name":"Somain S.l.",
    "wof:placetype":"venue"
},
  "geometry": {"coordinates":[-3.8492472172,40.2643051147],"type":"Point"}
}