{
  "type": "Feature",
  "properties": {
    "addr:full":"Calle de Cruz, 81 Casillas  O Ermita De Buendia Murcia 30007",
    "addr:housenumber":"81",
    "addr:postcode":"30007",
    "addr:street":"Calle De Cruz",
    "iso:country":"ES",
    "sg:address":"Calle de Cruz, 81",
    "sg:city":"Casillas  O Ermita De Buendia",
    "sg:orig_category":"Reposter\u00cdas",
    "sg:phone":"+34 968 85 03 90",
    "sg:postcode":"30007",
    "sg:province":"Murcia",
    "wof:name":"Vidal Saez Juan",
    "wof:placetype":"venue"
},
  "geometry": {"coordinates":[-1.1298867464,37.9834747314],"type":"Point"}
}