{
  "type": "Feature",
  "properties": {
    "iso:country":"ES",
    "sg:address":"Laskibar Bailara, S/n",
    "sg:city":"Irura",
    "sg:orig_category":"Mec\u00c1nico Del Autom\u00d3vil",
    "sg:phone":"+34 943 69 12 48",
    "sg:postcode":"20271",
    "sg:province":"Guip\u00f9zcoa",
    "wof:name":"Autolabaka S.l.",
    "wof:placetype":"venue"
},
  "geometry": {"coordinates":[-2.0564050674,43.1760864258],"type":"Point"}
}