{
  "type": "Feature",
  "properties": {
    "iso:country":"ES",
    "sg:address":"Calle de Motilla Del Palancar, 37",
    "sg:city":"Madrid",
    "sg:orig_category":"Frutas, Legumbres Frescas Y Tempranas (al Por Menor)",
    "sg:phone":"+34 913 00 11 80",
    "sg:postcode":"28043",
    "sg:province":"Madrid",
    "wof:name":"Juan Alonso Jacinto De",
    "wof:placetype":"venue"
},
  "geometry": {"coordinates":[-3.6326639652,40.4655189514],"type":"Point"}
}