{
  "type": "Feature",
  "properties": {
    "addr:full":"Illes Columbretes, 15 Burriana Castell\u00f3n 12530",
    "addr:housenumber":"15",
    "addr:postcode":"12530",
    "addr:street":"Columbretes",
    "iso:country":"ES",
    "sg:address":"Illes Columbretes, 15",
    "sg:city":"Burriana",
    "sg:orig_category":"Agencias Y Agentes Comerciales, Representantes",
    "sg:phone":"+34 964 58 51 65",
    "sg:postcode":"12530",
    "sg:province":"Castell\u00f3n",
    "wof:name":"Subogra S.l.",
    "wof:placetype":"venue"
},
  "geometry": {"coordinates":[-0.0735760033,39.8666877747],"type":"Point"}
}