{
  "type": "Feature",
  "properties": {
    "addr:full":"Avda Perez Galdos, 10 Logro\u00f1o La Rioja 26002",
    "addr:housenumber":"10",
    "addr:postcode":"26002",
    "addr:street":"Avda Perez Galdos;Rioja",
    "iso:country":"ES",
    "sg:address":"Avda Perez Galdos, 10",
    "sg:city":"Logro\u00f1o",
    "sg:orig_category":"Promotores Constructores",
    "sg:phone":"+34 941 25 52 86",
    "sg:postcode":"26002",
    "sg:province":"La Rioja",
    "wof:name":"Promociones Camal & Co. S.cv.",
    "wof:placetype":"venue"
},
  "geometry": {"coordinates":[-2.4473071098,42.4612388611],"type":"Point"}
}