{
  "type": "Feature",
  "properties": {
    "addr:full":"Calle de San Pedro, 97 Quintanar Rey Cuenca 16220",
    "addr:housenumber":"97",
    "addr:postcode":"16220",
    "addr:street":"Calle De San Pedro",
    "iso:country":"ES",
    "sg:address":"Calle de San Pedro, 97",
    "sg:city":"Quintanar Rey",
    "sg:orig_category":"Electricidad: Instaladores",
    "sg:phone":"+34 967 49 55 72",
    "sg:postcode":"16220",
    "sg:province":"Cuenca",
    "wof:name":"Zamora Mu\u00f1oz Jose",
    "wof:placetype":"venue"
},
  "geometry": {"coordinates":[-1.9293621778,39.3465919495],"type":"Point"}
}