{
  "type": "Feature",
  "properties": {
    "iso:country":"ES",
    "sg:address":"Calle de Victoriano Perez Vidal, 48",
    "sg:city":"Esfarrapada",
    "sg:orig_category":"Promotores Constructores",
    "sg:phone":"+34 986 34 96 84",
    "sg:postcode":"36470",
    "sg:province":"Pontevedra",
    "wof:name":"Viviendas Caselas S.l.",
    "wof:placetype":"venue"
},
  "geometry": {"coordinates":[-8.561375618,42.104434967],"type":"Point"}
}