{
  "type": "Feature",
  "properties": {
    "addr:full":"Avda Villajoyosa, 103 Alacant Alicante 03016",
    "addr:housenumber":"103",
    "addr:postcode":"03016",
    "addr:street":"Avda Villajoyosa",
    "iso:country":"ES",
    "sg:address":"Avda Villajoyosa, 103",
    "sg:city":"Alacant",
    "sg:orig_category":"Bares, Piano",
    "sg:phone":"+34 965 26 87 55",
    "sg:postcode":"03016",
    "sg:province":"Alicante",
    "wof:name":"Rodriguez Rodriguez Jose Maria",
    "wof:placetype":"venue"
},
  "geometry": {"coordinates":[-0.4480609894,38.3625068665],"type":"Point"}
}