{
  "type": "Feature",
  "properties": {
    "iso:country":"ES",
    "sg:address":"Calle de Aeropuerto (del), 16",
    "sg:city":"Coslada",
    "sg:orig_category":"Electricidad: Instaladores",
    "sg:phone":"+34 916 71 23 25",
    "sg:postcode":"28820",
    "sg:province":"Madrid",
    "wof:name":"Fernandez Duran Francisco",
    "wof:placetype":"venue"
},
  "geometry": {"coordinates":[-3.5597648621,40.4261054993],"type":"Point"}
}