{
  "type": "Feature",
  "properties": {
    "iso:country":"ES",
    "sg:address":"Plaz Centro, 2",
    "sg:city":"Nava",
    "sg:orig_category":"Institutos De Belleza",
    "sg:phone":"+34 985 71 70 10",
    "sg:postcode":"33520",
    "sg:province":"Asturias",
    "wof:name":"Vigon Garcia Sonia",
    "wof:placetype":"venue"
},
  "geometry": {"coordinates":[-5.5084810257,43.3585662842],"type":"Point"}
}