{
  "type": "Feature",
  "properties": {
    "addr:full":"Carrer de Major, 12 Montcada Centre Barcelona 08110",
    "addr:housenumber":"12",
    "addr:postcode":"08110",
    "addr:street":"Carrer De Major",
    "iso:country":"ES",
    "sg:address":"Carrer de Major, 12",
    "sg:city":"Montcada Centre",
    "sg:orig_category":"Cajas De Ahorro",
    "sg:phone":"+34 935 75 11 99",
    "sg:postcode":"08110",
    "sg:province":"Barcelona",
    "wof:name":"Caixa D'estalvis De Manresa",
    "wof:placetype":"venue"
},
  "geometry": {"coordinates":[2.1880700588,41.4858093262],"type":"Point"}
}