{
  "type": "Feature",
  "properties": {
    "addr:full":"Pla\u00c7 Del Mestre Ferrero, 9 Ontinyent Valencia 46870",
    "addr:postcode":"46870",
    "iso:country":"ES",
    "sg:address":"Pla\u00c7 Del Mestre Ferrero, 9",
    "sg:city":"Ontinyent",
    "sg:orig_category":"Abogados",
    "sg:phone":"+34 962 91 19 18",
    "sg:postcode":"46870",
    "sg:province":"Valencia",
    "wof:name":"Tortosa Y Penades Abogados C.b.",
    "wof:placetype":"venue"
},
  "geometry": {"coordinates":[-0.5989660025,38.8217926025],"type":"Point"}
}