{
  "type": "Feature",
  "properties": {
    "iso:country":"ES",
    "sg:address":"Calle de Tarragona, 18",
    "sg:city":"Madrid",
    "sg:orig_category":"Agencias Y Asesores De Publicidad",
    "sg:phone":"+34 914 67 52 06",
    "sg:postcode":"28045",
    "sg:province":"Madrid",
    "wof:name":"Hispano Television Y Telefonia S.l.",
    "wof:placetype":"venue"
},
  "geometry": {"coordinates":[-3.6967730522,40.4014587402],"type":"Point"}
}