{
  "type": "Feature",
  "properties": {
    "addr:full":"Calle de Gran Via De San Marcos, 22 Le\u00f3n Le\u00f3n 24002",
    "addr:housenumber":"22",
    "addr:postcode":"24002",
    "addr:street":"Calle De Gran Via De San Marcos;Leo\u0301N",
    "iso:country":"ES",
    "sg:address":"Calle de Gran Via De San Marcos, 22",
    "sg:city":"Le\u00f3n",
    "sg:orig_category":"Abogados",
    "sg:phone":"+34 987 27 37 33",
    "sg:postcode":"24002",
    "sg:province":"Le\u00f3n",
    "wof:name":"Roa Nonide Luis Fernando",
    "wof:placetype":"venue"
},
  "geometry": {"coordinates":[-5.5716609955,42.5981369019],"type":"Point"}
}