{
  "type": "Feature",
  "properties": {
    "iso:country":"ES",
    "sg:address":"Calle de Illescas, 5",
    "sg:city":"Madrid",
    "sg:orig_category":"Notarios",
    "sg:phone":"+34 915 18 21 66",
    "sg:postcode":"28024",
    "sg:province":"Madrid",
    "wof:name":"Garcia De Cortazar Nebreda Jose Antonio",
    "wof:placetype":"venue"
},
  "geometry": {"coordinates":[-3.7658998966,40.3972625732],"type":"Point"}
}