{
  "type": "Feature",
  "properties": {
    "addr:full":"Carrer de Mare De Deu Dels Dolors, 66 Gava Barcelona 08850",
    "addr:housenumber":"66",
    "addr:postcode":"08850",
    "addr:street":"Carrer De Mare De Deu Dels Dolors",
    "iso:country":"ES",
    "sg:address":"Carrer de Mare De Deu Dels Dolors, 66",
    "sg:city":"Gava",
    "sg:orig_category":"Empresas De Pintura Y Revestimientos",
    "sg:phone":"+34 936 38 22 08",
    "sg:postcode":"08850",
    "sg:province":"Barcelona",
    "wof:name":"Dios Rodriguez Manuel Vicente De",
    "wof:placetype":"venue"
},
  "geometry": {"coordinates":[2.0003490448,41.3072929382],"type":"Point"}
}