{
  "type": "Feature",
  "properties": {
    "iso:country":"ES",
    "sg:address":"Calle de Mariano Benlliure, S/n",
    "sg:city":"Tavernes Blanques",
    "sg:orig_category":"Laboratorios Y Cl\u00cdnicas Veterinarias",
    "sg:phone":"+34 961 86 10 54",
    "sg:postcode":"46016",
    "sg:province":"Valencia",
    "wof:name":"Esteve Monzo Francisco Javier",
    "wof:placetype":"venue"
},
  "geometry": {"coordinates":[-0.3672389984,39.5058441162],"type":"Point"}
}