{
  "type": "Feature",
  "properties": {
    "iso:country":"ES",
    "sg:address":"C/ Menendez Pidal, De, 17",
    "sg:city":"S. Antoni Portmany",
    "sg:orig_category":"Fabricaci\u00d3n, Importaci\u00d3n De L\u00c1mparas Y Bombillas",
    "sg:phone":"+34 971 80 31 21",
    "sg:postcode":"07820",
    "sg:province":"Islas Baleares",
    "wof:name":"Can Emecta S.l.",
    "wof:placetype":"venue"
},
  "geometry": {"coordinates":[1.5188339949,39.1094055176],"type":"Point"}
}