{
  "type": "Feature",
  "properties": {
    "addr:full":"Calle de Toledo, 101 Madrid Madrid 28005",
    "addr:housenumber":"101",
    "addr:postcode":"28005",
    "addr:street":"Calle De Toledo",
    "iso:country":"ES",
    "sg:address":"Calle de Toledo, 101",
    "sg:city":"Madrid",
    "sg:orig_category":"Radiocomunicaciones, Telefon\u00cda M\u00d3vil, Radiomensajer\u00cda: Servicios, Comercializaci\u00d3n",
    "sg:phone":"+34 913 64 12 01",
    "sg:postcode":"28005",
    "sg:province":"Madrid",
    "wof:name":"Speed Line Phone S.l.",
    "wof:placetype":"venue"
},
  "geometry": {"coordinates":[-3.7100162506,40.4092597961],"type":"Point"}
}