{
  "type": "Feature",
  "properties": {
    "iso:country":"ES",
    "sg:address":"Ctra Cadiz (de), Km. 0192,0",
    "sg:city":"Marbella",
    "sg:orig_category":"Asociaciones Humanitarias, De Cooperaci\u00d3n, De Acci\u00d3n Social",
    "sg:phone":"+34 952 77 67 02",
    "sg:postcode":"29600",
    "sg:province":"M\u00e1laga",
    "wof:name":"Aspandem",
    "wof:placetype":"venue"
},
  "geometry": {"coordinates":[-4.7285289764,36.5027770996],"type":"Point"}
}