{
  "type": "Feature",
  "properties": {
    "iso:country":"ES",
    "sg:address":"Calle de Obispo (del), 11",
    "sg:city":"Jaca",
    "sg:orig_category":"Imprenta",
    "sg:phone":"+34 974 35 57 51",
    "sg:postcode":"22700",
    "sg:province":"Huesca",
    "wof:name":"Lain Ascaso Julio",
    "wof:placetype":"venue"
},
  "geometry": {"coordinates":[-0.5500450134,42.5703811646],"type":"Point"}
}