{
  "type": "Feature",
  "properties": {
    "addr:full":"Calle de Cardenal Cisneros, 29 Santander Cantabria 39007",
    "addr:housenumber":"29",
    "addr:postcode":"39007",
    "addr:street":"Calle De Cardenal Cisneros",
    "iso:country":"ES",
    "sg:address":"Calle de Cardenal Cisneros, 29",
    "sg:city":"Santander",
    "sg:orig_category":"Promotores Constructores",
    "sg:phone":"+34 942 23 94 32",
    "sg:postcode":"39007",
    "sg:province":"Cantabria",
    "wof:name":"Restauraciones La Venera S.l.",
    "wof:placetype":"venue"
},
  "geometry": {"coordinates":[-3.8141355515,43.4632225037],"type":"Point"}
}