{
  "type": "Feature",
  "properties": {
    "addr:full":"Calle de Vergara, 14 Palmas De Gran Canaria Las Palmas 35010",
    "addr:housenumber":"14",
    "addr:postcode":"35010",
    "addr:street":"Calle De Vergara",
    "iso:country":"ES",
    "sg:address":"Calle de Vergara, 14",
    "sg:city":"Palmas De Gran Canaria",
    "sg:classifiers":[
        {
            "category":"Arts & Performance",
            "subcategory":"Art Gallery",
            "type":"Entertainment"
        }
    ],
    "sg:phone":"+34 928 27 98 49",
    "sg:postcode":"35010",
    "sg:province":"Las Palmas",
    "sg:tags":[
        "arte",
        "de",
        "galer\u00cdas"
    ],
    "wof:name":"Garcia Diaz Rosario",
    "wof:placetype":"venue"
},
  "geometry": {"coordinates":[-15.442070961,28.1297798157],"type":"Point"}
}