{
  "type": "Feature",
  "properties": {
    "addr:full":"Calle de Penitencia, 10 Valladolid Valladolid 47011",
    "addr:housenumber":"10",
    "addr:postcode":"47011",
    "addr:street":"Calle De Penitencia",
    "iso:country":"ES",
    "sg:address":"Calle de Penitencia, 10",
    "sg:city":"Valladolid",
    "sg:orig_category":"Centros Empresariales",
    "sg:phone":"+34 983 26 58 64",
    "sg:postcode":"47011",
    "sg:province":"Valladolid",
    "wof:name":"Feltrero Perez Manuel",
    "wof:placetype":"venue"
},
  "geometry": {"coordinates":[-4.7156591415,41.6597595215],"type":"Point"}
}