{
  "type": "Feature",
  "properties": {
    "iso:country":"ES",
    "sg:address":"Avda Burjasot, 126",
    "sg:city":"Valencia",
    "sg:orig_category":"Supermercados Y Hipermercados",
    "sg:phone":"+34 963 48 01 82",
    "sg:postcode":"46025",
    "sg:province":"Valencia",
    "sg:website":"www.consum.es",
    "wof:name":"Consum Sociedad Cooperativa Limitada",
    "wof:placetype":"venue"
},
  "geometry": {"coordinates":[-0.3898159862,39.4892234802],"type":"Point"}
}