{
  "type": "Feature",
  "properties": {
    "iso:country":"ES",
    "sg:address":"Calle de Elias Ramos Gonzalez, 1",
    "sg:city":"Santa Cruz De Tenerife",
    "sg:orig_category":"T\u00c9cnicos Veterinarios",
    "sg:phone":"+34 922 28 55 14",
    "sg:postcode":"38001",
    "sg:province":"Santa Cruz De Tenerife",
    "wof:name":"Mesa Bencomo Rosa",
    "wof:placetype":"venue"
},
  "geometry": {"coordinates":[-16.2441806793,28.4788818359],"type":"Point"}
}