{
  "type": "Feature",
  "properties": {
    "addr:full":"Calle de San Francisco, S/n Guadix Granada 18500",
    "addr:postcode":"18500",
    "addr:street":"Calle De San Francisco S / N",
    "iso:country":"ES",
    "sg:address":"Calle de San Francisco, S/n",
    "sg:city":"Guadix",
    "sg:orig_category":"Ense\u00d1anza, Formaci\u00d3n Profesional: Aprendizaje",
    "sg:phone":"+34 958 66 62 71",
    "sg:postcode":"18500",
    "sg:province":"Granada",
    "wof:name":"Junta De Andalucia-consejeria De Cultura",
    "wof:placetype":"venue"
},
  "geometry": {"coordinates":[-3.1331739426,37.2996559143],"type":"Point"}
}