{
  "type": "Feature",
  "properties": {
    "addr:full":"Calle de Teodora Lamadrid, 2 Zaragoza Zaragoza 50011",
    "addr:housenumber":"2",
    "addr:postcode":"50011",
    "addr:street":"Calle De Teodora Lamadrid",
    "iso:country":"ES",
    "sg:address":"Calle de Teodora Lamadrid, 2",
    "sg:city":"Zaragoza",
    "sg:orig_category":"Papeler\u00cdas, Librer\u00cdas",
    "sg:phone":"+34 976 32 91 72",
    "sg:postcode":"50011",
    "sg:province":"Zaragoza",
    "wof:name":"Seral Cristobal Narciso",
    "wof:placetype":"venue"
},
  "geometry": {"coordinates":[-0.9220870137,41.6504631042],"type":"Point"}
}