{
  "type": "Feature",
  "properties": {
    "addr:full":"Carrer de Corsega, 49 Barcelona Barcelona 08029",
    "addr:housenumber":"49",
    "addr:postcode":"08029",
    "addr:street":"Carrer De Corsega",
    "iso:country":"ES",
    "sg:address":"Carrer de Corsega, 49",
    "sg:city":"Barcelona",
    "sg:classifiers":[
        {
            "category":"Personal",
            "subcategory":"Barber",
            "type":"Services"
        }
    ],
    "sg:phone":"+34 934 30 51 80",
    "sg:postcode":"08029",
    "sg:province":"Barcelona",
    "sg:tags":[
        "caballeros",
        "de",
        "peluqueros"
    ],
    "wof:name":"Cruz Sanchez Jose",
    "wof:placetype":"venue"
},
  "geometry": {"coordinates":[2.1429998875,41.3843841553],"type":"Point"}
}