{
  "type": "Feature",
  "properties": {
    "addr:full":"Avda Paralela, 20 Majadahonda Madrid 28220",
    "addr:housenumber":"20",
    "addr:postcode":"28220",
    "addr:street":"Avda Paralela",
    "iso:country":"ES",
    "sg:address":"Avda Paralela, 20",
    "sg:city":"Majadahonda",
    "sg:orig_category":"Cl\u00cdnicas Dentales",
    "sg:phone":"+34 916 38 94 03",
    "sg:postcode":"28220",
    "sg:province":"Madrid",
    "wof:name":"Ph Salud S.a.",
    "wof:placetype":"venue"
},
  "geometry": {"coordinates":[-3.8636949062,40.4747924805],"type":"Point"}
}