{
  "type": "Feature",
  "properties": {
    "iso:country":"ES",
    "sg:address":"Avda Andalucia, 59",
    "sg:city":"Beas",
    "sg:orig_category":"Cooperativas Agr\u00cdcolas",
    "sg:phone":"+34 959 30 80 61",
    "sg:postcode":"21630",
    "sg:province":"Huelva",
    "sg:website":"www.olibeas.com",
    "wof:name":"Cooperativa Del Campo San Bartolome",
    "wof:placetype":"venue"
},
  "geometry": {"coordinates":[-6.7946472168,37.4227333069],"type":"Point"}
}