{
  "type": "Feature",
  "properties": {
    "iso:country":"ES",
    "sg:address":"Carrer de Osi, 22",
    "sg:city":"Barcelona",
    "sg:orig_category":"Abogados",
    "sg:phone":"+34 932 04 56 94",
    "sg:postcode":"08034",
    "sg:province":"Barcelona",
    "wof:name":"Kleinklaus  Andre",
    "wof:placetype":"venue"
},
  "geometry": {"coordinates":[2.1232979298,41.3949317932],"type":"Point"}
}