{
  "type": "Feature",
  "properties": {
    "iso:country":"ES",
    "sg:address":"Parque De Los Enamorados, 8",
    "sg:city":"Iru\u00f1a",
    "sg:orig_category":"\u00d3ptica: Instrumentos (fabricaci\u00d3n)",
    "sg:phone":"+34 948 12 03 95",
    "sg:postcode":"31014",
    "sg:province":"Navarra",
    "wof:name":"Optica Boulevard Rotxa S.l.",
    "wof:placetype":"venue"
},
  "geometry": {"coordinates":[-1.6506210566,42.8251152039],"type":"Point"}
}