{
  "type": "Feature",
  "properties": {
    "iso:country":"ES",
    "sg:address":"Carrer de Gran De Gracia, 247",
    "sg:city":"Barcelona",
    "sg:orig_category":"Zapatos (al Por Menor)",
    "sg:phone":"+34 932 17 40 62",
    "sg:postcode":"08012",
    "sg:province":"Barcelona",
    "wof:name":"Ceretana De Zapaterias S.l.",
    "wof:placetype":"venue"
},
  "geometry": {"coordinates":[2.1501960754,41.4057922363],"type":"Point"}
}