{
  "type": "Feature",
  "properties": {
    "iso:country":"ES",
    "sg:address":"Avda Vilagarcia (de), 7",
    "sg:city":"Santiago De Compostela",
    "sg:orig_category":"Restaurantes",
    "sg:phone":"+34 981 55 31 12",
    "sg:postcode":"15706",
    "sg:province":"La Coru\u00f1a",
    "wof:name":"Congresos Sant Yago S.l.",
    "wof:placetype":"venue"
},
  "geometry": {"coordinates":[-8.5518293381,42.8730278015],"type":"Point"}
}