{
  "type": "Feature",
  "properties": {
    "iso:country":"ES",
    "sg:address":"Calle de Iglesia, 4",
    "sg:city":"Donostia-san Sebastian",
    "sg:orig_category":"Iglesia Cat\u00d3lica",
    "sg:phone":"+34 943 45 67 87",
    "sg:postcode":"20014",
    "sg:province":"Guip\u00f9zcoa",
    "wof:name":"Parroquia Del Sagrado Corazon",
    "wof:placetype":"venue"
},
  "geometry": {"coordinates":[-1.966209054,43.3100471497],"type":"Point"}
}