{
  "type": "Feature",
  "properties": {
    "iso:country":"ES",
    "sg:address":"Calle de Juan De La Cierva, 16",
    "sg:city":"Castalla",
    "sg:orig_category":"Fabricaci\u00d3n De Moldes Y Modelos",
    "sg:phone":"+34 965 56 06 48",
    "sg:postcode":"03420",
    "sg:province":"Alicante",
    "wof:name":"Matriceria Mira S.l.",
    "wof:placetype":"venue"
},
  "geometry": {"coordinates":[-0.6759300232,38.5924606323],"type":"Point"}
}