{
  "type": "Feature",
  "properties": {
    "addr:full":"Trva Madrid, Km. 0014,5 Aranjuez Madrid 28300",
    "addr:postcode":"28300",
    "addr:street":"Trva Madrid Km. 0014,5",
    "iso:country":"ES",
    "sg:address":"Trva Madrid, Km. 0014,5",
    "sg:city":"Aranjuez",
    "sg:orig_category":"Zootecnia",
    "sg:phone":"+34 918 91 88 19",
    "sg:postcode":"28300",
    "sg:province":"Madrid",
    "wof:name":"Los Callejones Del Duende S.l.",
    "wof:placetype":"venue"
},
  "geometry": {"coordinates":[-3.6042790413,40.0360946655],"type":"Point"}
}