{
  "type": "Feature",
  "properties": {
    "iso:country":"ES",
    "sg:address":"Calle de Francisco Madariaga, 30",
    "sg:city":"Madrid",
    "sg:orig_category":"Promotores Constructores",
    "sg:phone":"+34 914 11 37 62",
    "sg:postcode":"28017",
    "sg:province":"Madrid",
    "wof:name":"Argedion S.l",
    "wof:placetype":"venue"
},
  "geometry": {"coordinates":[-3.6404819489,40.4354438782],"type":"Point"}
}