{
  "type": "Feature",
  "properties": {
    "iso:country":"ES",
    "sg:address":"Ctra Jaen, 57",
    "sg:city":"Hellin",
    "sg:orig_category":"Promotores Constructores",
    "sg:phone":"+34 967 30 05 84",
    "sg:postcode":"02400",
    "sg:province":"Albacete",
    "wof:name":"Tauste Valero Joaquin",
    "wof:placetype":"venue"
},
  "geometry": {"coordinates":[-1.708575964,38.5055427551],"type":"Point"}
}