{
  "type": "Feature",
  "properties": {
    "addr:full":"Calle de Sol Del, 3 Tineo Asturias 33870",
    "addr:housenumber":"3",
    "addr:postcode":"33870",
    "addr:street":"Calle De Sol Del",
    "iso:country":"ES",
    "sg:address":"Calle de Sol Del, 3",
    "sg:city":"Tineo",
    "sg:orig_category":"Promotores Constructores",
    "sg:phone":"+34 985 80 00 81",
    "sg:postcode":"33870",
    "sg:province":"Asturias",
    "wof:name":"Desarrollo Y Construcciones Mario S.l.",
    "wof:placetype":"venue"
},
  "geometry": {"coordinates":[-6.4165468216,43.3338775635],"type":"Point"}
}