{
  "type": "Feature",
  "properties": {
    "addr:full":"Calle de Alfredo Calderon, 71 Palmas De Gran Canaria Las Palmas 35006",
    "addr:postcode":"35006",
    "addr:street":"Calle De Alfredo Calderon 71",
    "iso:country":"ES",
    "sg:address":"Calle de Alfredo Calderon, 71",
    "sg:city":"Palmas De Gran Canaria",
    "sg:orig_category":"Bazares, Art\u00cdculos De Limpieza Y De Cocina (al Por Menor)",
    "sg:phone":"+34 928 24 28 07",
    "sg:postcode":"35006",
    "sg:province":"Las Palmas",
    "wof:name":"Ortega Lorenzo Maria Auxiliadora",
    "wof:placetype":"venue"
},
  "geometry": {"coordinates":[-15.4344854355,28.1304912567],"type":"Point"}
}