{
  "type": "Feature",
  "properties": {
    "iso:country":"ES",
    "sg:address":"Carrer de Flors, 12",
    "sg:city":"Vic",
    "sg:orig_category":"Abogados",
    "sg:phone":"+34 938 83 32 47",
    "sg:postcode":"08500",
    "sg:province":"Barcelona",
    "wof:name":"Roca Font Eduard",
    "wof:placetype":"venue"
},
  "geometry": {"coordinates":[2.2499248981,41.9272422791],"type":"Point"}
}