{
  "type": "Feature",
  "properties": {
    "iso:country":"ES",
    "sg:address":"El Velero, 1",
    "sg:city":"Arrecife",
    "sg:orig_category":"Molduras, Junquillos, Listones Y Molduras Perforadas",
    "sg:phone":"+34 928 84 45 67",
    "sg:postcode":"35500",
    "sg:province":"Las Palmas",
    "wof:name":"Lanobras S.l.",
    "wof:placetype":"venue"
},
  "geometry": {"coordinates":[-13.5490036011,28.9582099915],"type":"Point"}
}