{
  "type": "Feature",
  "properties": {
    "iso:country":"ES",
    "sg:address":"Calle de Barrio Nuevo, 4",
    "sg:city":"Talavera Reina",
    "sg:orig_category":"Contenedores (mercanc\u00cdas)",
    "sg:phone":"+34 925 80 28 57",
    "sg:postcode":"45600",
    "sg:province":"Toledo",
    "wof:name":"Blanco Mu\u00f1oz Julian",
    "wof:placetype":"venue"
},
  "geometry": {"coordinates":[-4.8288807869,39.9622993469],"type":"Point"}
}