{
  "type": "Feature",
  "properties": {
    "iso:country":"ES",
    "sg:address":"Carr Reverendo Jeronimo Pons, 1",
    "sg:city":"Deya",
    "sg:orig_category":"Iglesia Cat\u00d3lica",
    "sg:phone":"+34 971 63 91 72",
    "sg:postcode":"07179",
    "sg:province":"Islas Baleares",
    "wof:name":"Obispado De Mallorca",
    "wof:placetype":"venue"
},
  "geometry": {"coordinates":[2.6499259472,39.7486763],"type":"Point"}
}