{
  "type": "Feature",
  "properties": {
    "iso:country":"ES",
    "sg:address":"Calle de Garrovillas, S/n",
    "sg:city":"Madrid",
    "sg:orig_category":"Aparcamientos (infraestructuras, Accesorios)",
    "sg:phone":"+34 915 09 28 13",
    "sg:postcode":"28044",
    "sg:province":"Madrid",
    "wof:name":"Comunidad De Concesionarios",
    "wof:placetype":"venue"
},
  "geometry": {"coordinates":[-3.779225111,40.380279541],"type":"Point"}
}