{
  "type": "Feature",
  "properties": {
    "iso:country":"ES",
    "sg:address":"Calle de Carvajal, 10",
    "sg:city":"Palmas De Gran Canaria",
    "sg:orig_category":"Empresas De Portes Y Mensajer\u00cda",
    "sg:phone":"+34 928 24 77 18",
    "sg:postcode":"35004",
    "sg:province":"Las Palmas",
    "wof:name":"Canaritrans Courier S.l.",
    "wof:placetype":"venue"
},
  "geometry": {"coordinates":[-15.4220428467,28.1173820496],"type":"Point"}
}