{
  "type": "Feature",
  "properties": {
    "addr:full":"Calle de Corona De Aragon, 35 Barbastro Huesca 22300",
    "addr:housenumber":"35",
    "addr:postcode":"22300",
    "addr:street":"Calle De Corona De Aragon",
    "iso:country":"ES",
    "sg:address":"Calle de Corona De Aragon, 35",
    "sg:city":"Barbastro",
    "sg:orig_category":"Transportes Por V\u00cdas Navegables",
    "sg:phone":"+34 974 31 29 68",
    "sg:postcode":"22300",
    "sg:province":"Huesca",
    "wof:name":"Transportes Avellanas S.l.",
    "wof:placetype":"venue"
},
  "geometry": {"coordinates":[0.1284669936,42.0351676941],"type":"Point"}
}