{
  "type": "Feature",
  "properties": {
    "iso:country":"ES",
    "sg:address":"Calle de Malaga (de), 2",
    "sg:city":"Fuenlabrada",
    "sg:orig_category":"Muebles, Minoristas",
    "sg:phone":"+34 916 90 29 19",
    "sg:postcode":"28945",
    "sg:province":"Madrid",
    "wof:name":"Gonzalez Peinado Elpidio",
    "wof:placetype":"venue"
},
  "geometry": {"coordinates":[-3.7923920155,40.2882003784],"type":"Point"}
}