{
  "type": "Feature",
  "properties": {
    "addr:full":"Rua Marmoiral, 12 Fonsagrada Lugo 27100",
    "addr:housenumber":"12",
    "addr:postcode":"27100",
    "addr:street":"Rua Marmoiral",
    "iso:country":"ES",
    "sg:address":"Rua Marmoiral, 12",
    "sg:city":"Fonsagrada",
    "sg:orig_category":"Armas Y Municiones (fabricaci\u00d3n, Al Por Mayor)",
    "sg:phone":"+34 982 34 04 18",
    "sg:postcode":"27100",
    "sg:province":"Lugo",
    "wof:name":"Cendan Flores Maria Concepcion",
    "wof:placetype":"venue"
},
  "geometry": {"coordinates":[-7.0673189163,43.125995636],"type":"Point"}
}