{
  "type": "Feature",
  "properties": {
    "iso:country":"ES",
    "sg:address":"Cra. Nal Tres-cents Quaranta, S/n",
    "sg:city":"Amposta",
    "sg:orig_category":"Adaptaciones, Acondicionamientos Especiales Para Veh\u00cdculos, Veh\u00cdculos Industriales",
    "sg:phone":"+34 977 70 08 95",
    "sg:postcode":"43870",
    "sg:province":"Tarragona",
    "sg:website":"www.tomasexpediciones.es",
    "wof:name":"Tomas Expediciones S.a.",
    "wof:placetype":"venue"
},
  "geometry": {"coordinates":[0.5797849894,40.7130432129],"type":"Point"}
}