{
  "type": "Feature",
  "properties": {
    "addr:full":"Carrer de Mar, 6 Vendrell Tarragona 43700",
    "addr:housenumber":"6",
    "addr:postcode":"43700",
    "addr:street":"Carrer De Mar",
    "iso:country":"ES",
    "sg:address":"Carrer de Mar, 6",
    "sg:city":"Vendrell",
    "sg:orig_category":"Iglesia Cat\u00d3lica",
    "sg:phone":"+34 977 18 10 90",
    "sg:postcode":"43700",
    "sg:province":"Tarragona",
    "wof:name":"Arquebisbat De Tarragona",
    "wof:placetype":"venue"
},
  "geometry": {"coordinates":[1.5347373486,41.2200431824],"type":"Point"}
}