{
  "type": "Feature",
  "properties": {
    "iso:country":"ES",
    "sg:address":"Diseminados, 13",
    "sg:city":"Urretxu",
    "sg:orig_category":"Industria Qu\u00cdmica",
    "sg:phone":"+34 943 72 39 53",
    "sg:postcode":"20700",
    "sg:province":"Guip\u00f9zcoa",
    "sg:website":"www.sasieta.net",
    "wof:name":"Mancomunidad Sasieta",
    "wof:placetype":"venue"
},
  "geometry": {"coordinates":[-2.3134770393,43.086730957],"type":"Point"}
}