{
  "type": "Feature",
  "properties": {
    "addr:full":"Rua Ramon Cabanillas, 70 Praia Pontevedra 36950",
    "addr:housenumber":"70",
    "addr:postcode":"36950",
    "addr:street":"Rua Ramon Cabanillas",
    "iso:country":"ES",
    "sg:address":"Rua Ramon Cabanillas, 70",
    "sg:city":"Praia",
    "sg:orig_category":"Sociedades, Compa\u00d1\u00cdas Aseguradoras",
    "sg:phone":"+34 986 31 39 77",
    "sg:postcode":"36950",
    "sg:province":"Pontevedra",
    "wof:name":"Mapfre Servicios De Informatica",
    "wof:placetype":"venue"
},
  "geometry": {"coordinates":[-8.738442421,42.2772254944],"type":"Point"}
}