{
  "type": "Feature",
  "properties": {
    "addr:full":"Calle de Maldonado, 48 Madrid Madrid 28006",
    "addr:housenumber":"48",
    "addr:postcode":"madrid;28006",
    "addr:street":"Calle De Maldonado",
    "iso:country":"ES",
    "sg:address":"Calle de Maldonado, 48",
    "sg:city":"Madrid",
    "sg:orig_category":"Laboratorios Farmac\u00c9uticos",
    "sg:phone":"+34 914 01 17 17",
    "sg:postcode":"28006",
    "sg:province":"Madrid",
    "wof:name":"Duran Egea Rosario",
    "wof:placetype":"venue"
},
  "geometry": {"coordinates":[-3.6762180328,40.433391571],"type":"Point"}
}