{
  "type": "Feature",
  "properties": {
    "iso:country":"ES",
    "sg:address":"Trva Arbolantxa, 2",
    "sg:city":"Bilbao",
    "sg:orig_category":"Peluquer\u00cdas, Peluquer\u00cda Mixta",
    "sg:phone":"+34 944 12 63 23",
    "sg:postcode":"48004",
    "sg:province":"Vizcaya",
    "wof:name":"Minayo Conde Maria De Las Mercedes",
    "wof:placetype":"venue"
},
  "geometry": {"coordinates":[-2.8981080055,43.2613143921],"type":"Point"}
}