{
  "type": "Feature",
  "properties": {
    "iso:country":"ES",
    "sg:address":"Calle de Arcediano, 6",
    "sg:city":"Plasencia",
    "sg:orig_category":"Artes Gr\u00c1ficas, Artes Pl\u00c1sticas: Productos Y Suministros (al Por Mayor)",
    "sg:phone":"+34 927 41 93 13",
    "sg:postcode":"10600",
    "sg:province":"C\u00e1ceres",
    "sg:website":"www.belarte3.com",
    "wof:name":"Geferca S.l.",
    "wof:placetype":"venue"
},
  "geometry": {"coordinates":[-6.0879459381,40.0300445557],"type":"Point"}
}