{
  "type": "Feature",
  "properties": {
    "iso:country":"ES",
    "sg:address":"Calle de Hoyo, 6",
    "sg:city":"Torremolinos",
    "sg:orig_category":"Centros De Coordinaci\u00d3n",
    "sg:phone":"+34 952 38 36 41",
    "sg:postcode":"29620",
    "sg:province":"M\u00e1laga",
    "wof:name":"Martin Montalvo Aguado Maria De Los Angeles",
    "wof:placetype":"venue"
},
  "geometry": {"coordinates":[-4.4992818832,36.6257896423],"type":"Point"}
}