{
  "type": "Feature",
  "properties": {
    "addr:full":"Avda Castilla, 73 Aranda Duero Burgos 09400",
    "addr:housenumber":"73",
    "addr:postcode":"09400",
    "addr:street":"Avda Castilla",
    "iso:country":"ES",
    "sg:address":"Avda Castilla, 73",
    "sg:city":"Aranda Duero",
    "sg:orig_category":"Molduras, Junquillos, Listones Y Molduras Perforadas",
    "sg:phone":"+34 947 51 27 80",
    "sg:postcode":"09400",
    "sg:province":"Burgos",
    "wof:name":"Veganzones Ruiz Juan",
    "wof:placetype":"venue"
},
  "geometry": {"coordinates":[-3.6915659904,41.659324646],"type":"Point"}
}