{
  "type": "Feature",
  "properties": {
    "iso:country":"ES",
    "sg:address":"Carrer de Rovellat, 12",
    "sg:city":"Esplugues Llobregat",
    "sg:orig_category":"Fabricaci\u00d3n De Sobres, Bolsas Y Fundas",
    "sg:phone":"+34 933 72 08 17",
    "sg:postcode":"08950",
    "sg:province":"Barcelona",
    "wof:name":"Catala Nin Juan Miquel",
    "wof:placetype":"venue"
},
  "geometry": {"coordinates":[2.0880360603,41.3721313477],"type":"Point"}
}