{
  "type": "Feature",
  "properties": {
    "iso:country":"ES",
    "sg:address":"Av Reus, 3",
    "sg:city":"Alcover",
    "sg:orig_category":"Par\u00cds",
    "sg:phone":"+34 977 84 62 88",
    "sg:postcode":"43460",
    "sg:province":"Tarragona",
    "wof:name":"Masdeu Magrane Ramon",
    "wof:placetype":"venue"
},
  "geometry": {"coordinates":[1.1712839603,41.2621917725],"type":"Point"}
}