{
  "type": "Feature",
  "properties": {
    "addr:full":"Calle de Joaquin Turina, 3 Jumilla Murcia 30520",
    "addr:housenumber":"3",
    "addr:postcode":"30520",
    "addr:street":"Calle De Joaquin Turina",
    "iso:country":"ES",
    "sg:address":"Calle de Joaquin Turina, 3",
    "sg:city":"Jumilla",
    "sg:orig_category":"Dise\u00d1o Industrial",
    "sg:phone":"+34 968 78 15 36",
    "sg:postcode":"30520",
    "sg:province":"Murcia",
    "wof:name":"Digargo S.l.",
    "wof:placetype":"venue"
},
  "geometry": {"coordinates":[-1.3218120337,38.473815918],"type":"Point"}
}