{
  "type": "Feature",
  "properties": {
    "addr:full":"Calle de Julio Romero, 11 Ubrique C\u00e1diz 11600",
    "addr:housenumber":"11",
    "addr:postcode":"11600",
    "addr:street":"Calle De Julio Romero;Ca\u0301Diz",
    "iso:country":"ES",
    "sg:address":"Calle de Julio Romero, 11",
    "sg:city":"Ubrique",
    "sg:orig_category":"Marroquiner\u00cda (confecci\u00d3n)",
    "sg:phone":"+34 956 46 17 99",
    "sg:postcode":"11600",
    "sg:province":"C\u00e1diz",
    "wof:name":"Piel Galvan S.l.",
    "wof:placetype":"venue"
},
  "geometry": {"coordinates":[-5.4466590881,36.6801605225],"type":"Point"}
}