{
  "type": "Feature",
  "properties": {
    "iso:country":"ES",
    "sg:address":"Carretera Seros, Km. 0003,0",
    "sg:city":"Fraga",
    "sg:orig_category":"Alquiler De Gr\u00daas",
    "sg:phone":"+34 974 47 01 68",
    "sg:postcode":"22520",
    "sg:province":"Huesca",
    "wof:name":"Gruas Y Servicios, Gruyser S.l.u.",
    "wof:placetype":"venue"
},
  "geometry": {"coordinates":[0.3640623093,41.5235176086],"type":"Point"}
}