{
  "type": "Feature",
  "properties": {
    "addr:full":"Carrer de Proven\u00c7a, 116 Terrassa Barcelona 08226",
    "addr:housenumber":"116",
    "addr:postcode":"08226",
    "addr:street":"Carrer De Provenc\u0327A",
    "iso:country":"ES",
    "sg:address":"Carrer de Proven\u00c7a, 116",
    "sg:city":"Terrassa",
    "sg:orig_category":"Alimentaci\u00d3n General (al Por Menor)",
    "sg:phone":"+34 937 85 22 90",
    "sg:postcode":"08226",
    "sg:province":"Barcelona",
    "wof:name":"Alvarez Martinez Esperanza",
    "wof:placetype":"venue"
},
  "geometry": {"coordinates":[2.0249669552,41.5759048462],"type":"Point"}
}