{
  "type": "Feature",
  "properties": {
    "iso:country":"ES",
    "sg:address":"Carrer de Om, 12",
    "sg:city":"Barcelona",
    "sg:orig_category":"Alquiler De V\u00cddeo",
    "sg:phone":"+34 934 41 99 64",
    "sg:postcode":"08001",
    "sg:province":"Barcelona",
    "wof:name":"Ros Herrero Daniel",
    "wof:placetype":"venue"
},
  "geometry": {"coordinates":[2.1725299358,41.3757591248],"type":"Point"}
}