{
  "type": "Feature",
  "properties": {
    "iso:country":"ES",
    "sg:address":"Carrer de Villarroel, 149",
    "sg:city":"Barcelona",
    "sg:orig_category":"Agencias Y Agentes Comerciales, Representantes",
    "sg:phone":"+34 933 23 41 45",
    "sg:postcode":"08036",
    "sg:province":"Barcelona",
    "wof:name":"Schwippl  Martina",
    "wof:placetype":"venue"
},
  "geometry": {"coordinates":[2.1539950371,41.3871307373],"type":"Point"}
}