{
  "type": "Feature",
  "properties": {
    "addr:full":"Calle de Francisco De Orellana, 1 Utrera Sevilla 41710",
    "addr:housenumber":"1",
    "addr:postcode":"41710",
    "addr:street":"Calle De Francisco De Orellana",
    "iso:country":"ES",
    "sg:address":"Calle de Francisco De Orellana, 1",
    "sg:city":"Utrera",
    "sg:orig_category":"Pr\u00c9stamos Personales E Hipotecarios",
    "sg:phone":"+34 954 86 06 21",
    "sg:postcode":"41710",
    "sg:province":"Sevilla",
    "wof:name":"Alvarez Y Capitan Registradores De Utrer",
    "wof:placetype":"venue"
},
  "geometry": {"coordinates":[-5.7758378983,37.1831893921],"type":"Point"}
}