{
  "type": "Feature",
  "properties": {
    "iso:country":"ES",
    "sg:address":"Calle de Badaran, 14",
    "sg:city":"Najera",
    "sg:orig_category":"Transporte En General",
    "sg:phone":"+34 941 36 31 51",
    "sg:postcode":"26300",
    "sg:province":"La Rioja",
    "wof:name":"Mendoza Gomez Maria Pilar",
    "wof:placetype":"venue"
},
  "geometry": {"coordinates":[-2.8136076927,42.3830604553],"type":"Point"}
}