{
  "type": "Feature",
  "properties": {
    "iso:country":"ES",
    "sg:address":"Barr Ontaneda, 22",
    "sg:city":"Ontaneda",
    "sg:orig_category":"Panader\u00cdas, Panader\u00cdas",
    "sg:phone":"+34 942 59 45 76",
    "sg:postcode":"39680",
    "sg:province":"Cantabria",
    "wof:name":"Figueras Martinez Consuelo",
    "wof:placetype":"venue"
},
  "geometry": {"coordinates":[-3.9252300262,43.1992073059],"type":"Point"}
}