{
  "type": "Feature",
  "properties": {
    "addr:full":"Carr Hostal De La Bordeta, 2 Lleida Lleida 25001",
    "addr:housenumber":"2",
    "addr:postcode":"25001",
    "addr:street":"Carr Hostal De La Bordeta",
    "iso:country":"ES",
    "sg:address":"Carr Hostal De La Bordeta, 2",
    "sg:city":"Lleida",
    "sg:classifiers":[
        {
            "category":"Autos & Motor Vehicles",
            "subcategory":"Automobile Sales",
            "type":"Retail Goods"
        }
    ],
    "sg:phone":"+34 973 21 14 19",
    "sg:postcode":"25001",
    "sg:province":"Lleida",
    "wof:name":"Autoescola Transit S.c.p.",
    "wof:placetype":"venue"
},
  "geometry": {"coordinates":[0.6416705251,41.6046791077],"type":"Point"}
}