{
  "type": "Feature",
  "properties": {
    "iso:country":"ES",
    "sg:address":"Calle de Cabo De Finisterre, 18",
    "sg:city":"Arganda",
    "sg:orig_category":"Fabricaci\u00d3n De Ropa De Deportes",
    "sg:phone":"+34 918 70 14 29",
    "sg:postcode":"28500",
    "sg:province":"Madrid",
    "wof:name":"Amilcar Sport S.l.",
    "wof:placetype":"venue"
},
  "geometry": {"coordinates":[-3.4746155739,40.3118476868],"type":"Point"}
}