{
  "type": "Feature",
  "properties": {
    "iso:country":"ES",
    "sg:address":"Carrer de Mossen Tatcher, 10",
    "sg:city":"Terrassa",
    "sg:orig_category":"Guarder\u00cdas",
    "sg:phone":"+34 937 31 34 29",
    "sg:postcode":"08226",
    "sg:province":"Barcelona",
    "wof:name":"Escalera Barrionuevo Maria Del Carmen",
    "wof:placetype":"venue"
},
  "geometry": {"coordinates":[2.0273549557,41.5751304626],"type":"Point"}
}