{
  "type": "Feature",
  "properties": {
    "iso:country":"ES",
    "sg:address":"Calle de Hernando De Soto, 1",
    "sg:city":"Alcala Henares",
    "sg:orig_category":"Radiocomunicaciones, Telefon\u00cda M\u00d3vil, Radiomensajer\u00cda: Servicios, Comercializaci\u00d3n",
    "sg:phone":"+34 918 80 02 66",
    "sg:postcode":"28802",
    "sg:province":"Madrid",
    "wof:name":"Alcaraz Devia Marco Antonio",
    "wof:placetype":"venue"
},
  "geometry": {"coordinates":[-3.3834638596,40.4773445129],"type":"Point"}
}