{
  "type": "Feature",
  "properties": {
    "iso:country":"ES",
    "sg:address":"Carr Sant Miquel, 6",
    "sg:city":"Santa Margarida De Montbui B-urbano",
    "sg:orig_category":"Bibliotecas, Mediatecas",
    "sg:phone":"+34 938 05 26 66",
    "sg:postcode":"08710",
    "sg:province":"Barcelona",
    "wof:name":"Ajuntament De Santa Margarida De Montbui",
    "wof:placetype":"venue"
},
  "geometry": {"coordinates":[1.6071647406,41.5745849609],"type":"Point"}
}