{
  "type": "Feature",
  "properties": {
    "iso:country":"ES",
    "sg:address":"Cllo Huerta Rosario, 25",
    "sg:city":"Chiclana De La Frontera",
    "sg:orig_category":"Promotores Constructores",
    "sg:phone":"+34 956 40 56 60",
    "sg:postcode":"11130",
    "sg:province":"C\u00e1diz",
    "wof:name":"Inmopar 92 Alicante S.l.",
    "wof:placetype":"venue"
},
  "geometry": {"coordinates":[-6.1350498199,36.4183425903],"type":"Point"}
}