{
  "type": "Feature",
  "properties": {
    "addr:full":"Rua Real, 51 Ferrol La Coru\u00f1a 15402",
    "addr:housenumber":"51",
    "addr:postcode":"15402",
    "addr:street":"Rua Real;La Corun\u0303A",
    "iso:country":"ES",
    "sg:address":"Rua Real, 51",
    "sg:city":"Ferrol",
    "sg:orig_category":"Arquitectos",
    "sg:phone":"+34 981 35 31 80",
    "sg:postcode":"15402",
    "sg:province":"La Coru\u00f1a",
    "wof:name":"Estudios Tecnicos Crespo S.l.",
    "wof:placetype":"venue"
},
  "geometry": {"coordinates":[-8.2308502197,43.4847335815],"type":"Point"}
}