{
  "type": "Feature",
  "properties": {
    "addr:full":"Carr S Cristofor, 18 Igualada Barcelona 08700",
    "addr:housenumber":"18",
    "addr:postcode":"08700",
    "addr:street":"Carr S Cristofor",
    "iso:country":"ES",
    "sg:address":"Carr S Cristofor, 18",
    "sg:city":"Igualada",
    "sg:orig_category":"Sociedades, Compa\u00d1\u00cdas Aseguradoras",
    "sg:phone":"+34 938 04 25 28",
    "sg:postcode":"08700",
    "sg:province":"Barcelona",
    "wof:name":"Seguros Catalana Occidente S.a. De Seguros Y Reaseguros",
    "wof:placetype":"venue"
},
  "geometry": {"coordinates":[1.6197450161,41.5786933899],"type":"Point"}
}