{
  "type": "Feature",
  "properties": {
    "iso:country":"ES",
    "sg:address":"Calle de Oreitiasolo, 15",
    "sg:city":"Vitoria-gasteiz",
    "sg:orig_category":"Promotores Constructores",
    "sg:phone":"+34 945 23 34 53",
    "sg:postcode":"01006",
    "sg:province":"\u00c1lava",
    "wof:name":"Construcciones Igoroin Sl",
    "wof:placetype":"venue"
},
  "geometry": {"coordinates":[-2.6566519737,42.8405723572],"type":"Point"}
}