{
  "type": "Feature",
  "properties": {
    "iso:country":"ES",
    "sg:address":"Calle de Ciscar, 25",
    "sg:city":"Valencia",
    "sg:orig_category":"Asesor\u00cda Fiscal Y Jur\u00cddica",
    "sg:phone":"+34 963 74 79 30",
    "sg:postcode":"46005",
    "sg:province":"Valencia",
    "wof:name":"Llacer Flores Rafael",
    "wof:placetype":"venue"
},
  "geometry": {"coordinates":[-0.3655382991,39.4659080505],"type":"Point"}
}