{
  "type": "Feature",
  "properties": {
    "addr:full":"Estd Xeral, 4 Pontenova Lugo 27720",
    "addr:housenumber":"4",
    "addr:postcode":"27720",
    "addr:street":"Xeral",
    "iso:country":"ES",
    "sg:address":"Estd Xeral, 4",
    "sg:city":"Pontenova",
    "sg:orig_category":"Quincaller\u00cda (al Por Menor)",
    "sg:phone":"+34 982 34 20 81",
    "sg:postcode":"27720",
    "sg:province":"Lugo",
    "wof:name":"Lopez Requejo Alberto",
    "wof:placetype":"venue"
},
  "geometry": {"coordinates":[-7.1766328812,43.3744239807],"type":"Point"}
}