{
  "type": "Feature",
  "properties": {
    "iso:country":"ES",
    "sg:address":"Rua San Mauro, 31",
    "sg:city":"Barco",
    "sg:orig_category":"M\u00c9dicos: Estomatolog\u00cda",
    "sg:phone":"+34 988 32 53 52",
    "sg:postcode":"32300",
    "sg:province":"Ourense",
    "wof:name":"Gacio Pacios Maria Remedios",
    "wof:placetype":"venue"
},
  "geometry": {"coordinates":[-6.9802799225,42.4146461487],"type":"Point"}
}