{
  "type": "Feature",
  "properties": {
    "addr:full":"Av Pau, 16 S. Celoni Barcelona 08470",
    "addr:housenumber":"16",
    "addr:postcode":"08470",
    "addr:street":"Av Pau;S. Celoni Barcelona",
    "iso:country":"ES",
    "sg:address":"Av Pau, 16",
    "sg:city":"S. Celoni",
    "sg:orig_category":"Molduras, Junquillos, Listones Y Molduras Perforadas",
    "sg:phone":"+34 938 67 43 54",
    "sg:postcode":"08470",
    "sg:province":"Barcelona",
    "wof:name":"Costa Sala Joaquima",
    "wof:placetype":"venue"
},
  "geometry": {"coordinates":[2.463572979,41.7227363586],"type":"Point"}
}