{
  "type": "Feature",
  "properties": {
    "addr:full":"Av Sant Vicen\u00c7, 12 Vendrell Tarragona 43700",
    "addr:housenumber":"12",
    "addr:postcode":"43700",
    "addr:street":"Av Sant Vicenc\u0327",
    "iso:country":"ES",
    "sg:address":"Av Sant Vicen\u00c7, 12",
    "sg:city":"Vendrell",
    "sg:orig_category":"Reposter\u00cdas",
    "sg:phone":"+34 977 66 12 51",
    "sg:postcode":"43700",
    "sg:province":"Tarragona",
    "wof:name":"Coll Tuset Jose",
    "wof:placetype":"venue"
},
  "geometry": {"coordinates":[1.5318850279,41.2157936096],"type":"Point"}
}