{
  "type": "Feature",
  "properties": {
    "addr:full":"Calle de San Fernando, 56 Najera La Rioja 26300",
    "addr:housenumber":"56",
    "addr:postcode":"26300",
    "addr:street":"Calle De San Fernando;Rioja",
    "iso:country":"ES",
    "sg:address":"Calle de San Fernando, 56",
    "sg:city":"Najera",
    "sg:orig_category":"Ingenier\u00cda, Centros De Estudios (diversos)",
    "sg:phone":"+34 941 36 22 55",
    "sg:postcode":"26300",
    "sg:province":"La Rioja",
    "sg:website":"www.eurofincainmobiliaria.es",
    "wof:name":"Eurofinca Scv",
    "wof:placetype":"venue"
},
  "geometry": {"coordinates":[-2.7282509804,42.4177589417],"type":"Point"}
}