{
  "type": "Feature",
  "properties": {
    "addr:full":"Carrer de Camp De Mar, 6 Premia Mar Barcelona 08330",
    "addr:housenumber":"6",
    "addr:postcode":"08330",
    "addr:street":"Carrer De Camp De Mar",
    "iso:country":"ES",
    "sg:address":"Carrer de Camp De Mar, 6",
    "sg:city":"Premia Mar",
    "sg:orig_category":"Molduras, Junquillos, Listones Y Molduras Perforadas",
    "sg:phone":"+34 937 51 62 83",
    "sg:postcode":"08330",
    "sg:province":"Barcelona",
    "wof:name":"Gilbert Ruibal S. C. P.",
    "wof:placetype":"venue"
},
  "geometry": {"coordinates":[2.3739910126,41.494052887],"type":"Point"}
}