{
  "type": "Feature",
  "properties": {
    "addr:full":"Ctra Madrid, 48 Zaragoza Zaragoza 50012",
    "addr:housenumber":"48",
    "addr:postcode":"50012",
    "addr:street":"Ctra Madrid",
    "iso:country":"ES",
    "sg:address":"Ctra Madrid, 48",
    "sg:city":"Zaragoza",
    "sg:orig_category":"Estancos",
    "sg:phone":"+34 976 33 42 54",
    "sg:postcode":"50012",
    "sg:province":"Zaragoza",
    "wof:name":"Aranaz Gargallo Ana Cristina",
    "wof:placetype":"venue"
},
  "geometry": {"coordinates":[-0.9026641846,41.6539535522],"type":"Point"}
}