{
  "type": "Feature",
  "properties": {
    "addr:full":"Carrer de Arquitecte F. Casas, 14 Cas Catala-illetes Islas Baleares 07181",
    "addr:housenumber":"14",
    "addr:postcode":"07181",
    "addr:street":"Carrer De Arquitecte F. Casas;Islas",
    "iso:country":"ES",
    "sg:address":"Carrer de Arquitecte F. Casas, 14",
    "sg:city":"Cas Catala-illetes",
    "sg:orig_category":"Centros De Educaci\u00d3n Especial",
    "sg:phone":"+34 971 70 01 27",
    "sg:postcode":"07181",
    "sg:province":"Islas Baleares",
    "wof:name":"Colegio Publico Migjorn",
    "wof:placetype":"venue"
},
  "geometry": {"coordinates":[2.5352098942,39.5245780945],"type":"Point"}
}