{
  "type": "Feature",
  "properties": {
    "addr:full":"Ctra. Muro, 21 Sa Pobla Islas Baleares 07420",
    "addr:housenumber":"21",
    "addr:postcode":"07420",
    "addr:street":"Ctra. Muro",
    "iso:country":"ES",
    "sg:address":"Ctra. Muro, 21",
    "sg:city":"Sa Pobla",
    "sg:orig_category":"Insecticidas, Fumigaci\u00d3n",
    "sg:phone":"+34 971 86 27 17",
    "sg:postcode":"07420",
    "sg:province":"Islas Baleares",
    "wof:name":"Torrandell Cas Siulet S.l.",
    "wof:placetype":"venue"
},
  "geometry": {"coordinates":[3.0291249752,39.7663536072],"type":"Point"}
}