{
  "type": "Feature",
  "properties": {
    "addr:full":"Carrer de Ronda Boada Vell, 41 Poligon Industrial Riera De Caldes Barcelona 08184",
    "addr:housenumber":"41",
    "addr:postcode":"08184",
    "addr:street":"Carrer De Ronda Boada Vell;Industrial",
    "iso:country":"ES",
    "sg:address":"Carrer de Ronda Boada Vell, 41",
    "sg:city":"Poligon Industrial Riera De Caldes",
    "sg:orig_category":"Prensas Industriales",
    "sg:phone":"+34 938 64 92 21",
    "sg:postcode":"08184",
    "sg:province":"Barcelona",
    "wof:name":"Rapunsa S. L.",
    "wof:placetype":"venue"
},
  "geometry": {"coordinates":[2.181032896,41.5802307129],"type":"Point"}
}