{
  "type": "Feature",
  "properties": {
    "addr:full":"Plaz Jose Antonio, 5 Alcorisa Teruel 44550",
    "addr:housenumber":"5",
    "addr:postcode":"44550",
    "addr:street":"Jose Antonio",
    "iso:country":"ES",
    "sg:address":"Plaz Jose Antonio, 5",
    "sg:city":"Alcorisa",
    "sg:orig_category":"Empresas De Carpinter\u00cda De Madera",
    "sg:phone":"+34 978 84 06 35",
    "sg:postcode":"44550",
    "sg:province":"Teruel",
    "wof:name":"Felez Bernad Pascual",
    "wof:placetype":"venue"
},
  "geometry": {"coordinates":[-0.3821119964,40.8914375305],"type":"Point"}
}