{
  "type": "Feature",
  "properties": {
    "iso:country":"ES",
    "sg:address":"Calle de Dec. Higueras Del Castillo, S/n",
    "sg:city":"Torremolinos",
    "sg:orig_category":"Lencer\u00cda Femenina, Corseter\u00cda, Trajes De Ba\u00d1o (al Por Menor)",
    "sg:phone":"+34 952 05 89 64",
    "sg:postcode":"29620",
    "sg:province":"M\u00e1laga",
    "wof:name":"Carrascosa Madan Concepcion",
    "wof:placetype":"venue"
},
  "geometry": {"coordinates":[-4.5025839806,36.6133155823],"type":"Point"}
}