{
  "type": "Feature",
  "properties": {
    "addr:full":"Calle de Andalucia, 2 Martos Ja\u00e9n 23600",
    "addr:housenumber":"2",
    "addr:postcode":"23600",
    "addr:street":"Calle De Andalucia;Jae\u0301N",
    "iso:country":"ES",
    "sg:address":"Calle de Andalucia, 2",
    "sg:city":"Martos",
    "sg:orig_category":"Asesor\u00cda Sobre Comunicaci\u00d3n De Empresas",
    "sg:phone":"+34 953 55 15 41",
    "sg:postcode":"23600",
    "sg:province":"Ja\u00e9n",
    "wof:name":"Francisco Olid Melero Y Otro C.b.",
    "wof:placetype":"venue"
},
  "geometry": {"coordinates":[-3.9730072021,37.7208442688],"type":"Point"}
}