{
  "type": "Feature",
  "properties": {
    "addr:full":"Calle de Emperador Adriano, 6 Andujar Ja\u00e9n 23740",
    "addr:housenumber":"6",
    "addr:postcode":"23740",
    "addr:street":"Calle De Emperador Adriano",
    "iso:country":"ES",
    "sg:address":"Calle de Emperador Adriano, 6",
    "sg:city":"Andujar",
    "sg:orig_category":"Financiaci\u00d3n Y Cr\u00c9ditos",
    "sg:phone":"+34 953 50 65 44",
    "sg:postcode":"23740",
    "sg:province":"Ja\u00e9n",
    "wof:name":"Exchange Red De Consultores Financieros Ruve S.l.",
    "wof:placetype":"venue"
},
  "geometry": {"coordinates":[-4.0506091118,38.039855957],"type":"Point"}
}