{
  "type": "Feature",
  "properties": {
    "addr:full":"Calle de Hermanos Becerril, 9 Cuenca Cuenca 16004",
    "addr:housenumber":"9",
    "addr:postcode":"16004",
    "addr:street":"Calle De Hermanos Becerril",
    "iso:country":"ES",
    "sg:address":"Calle de Hermanos Becerril, 9",
    "sg:city":"Cuenca",
    "sg:classifiers":[
        {
            "category":"Government",
            "subcategory":"Office",
            "type":"Public Place"
        }
    ],
    "sg:phone":"+34 969 22 35 51",
    "sg:postcode":"16004",
    "sg:province":"Cuenca",
    "sg:tags":[
        "interior",
        "administraci\u00d3n",
        "en"
    ],
    "wof:name":"Direccion General De Trafico",
    "wof:placetype":"venue"
},
  "geometry": {"coordinates":[-2.1333179474,40.0648918152],"type":"Point"}
}