{
  "type": "Feature",
  "properties": {
    "addr:full":"Caleta-fa\u00f1abe, S/n Adeje Santa Cruz De Tenerife 38670",
    "addr:postcode":"38670",
    "addr:street":"Caleta-Fan\u0303Abe S / N",
    "iso:country":"ES",
    "sg:address":"Caleta-fa\u00f1abe, S/n",
    "sg:city":"Adeje",
    "sg:orig_category":"Turismo",
    "sg:phone":"+34 922 71 70 16",
    "sg:postcode":"38670",
    "sg:province":"Santa Cruz De Tenerife",
    "wof:name":"Isla Bella S.a.",
    "wof:placetype":"venue"
},
  "geometry": {"coordinates":[-16.7376403809,28.0857772827],"type":"Point"}
}