{
  "type": "Feature",
  "properties": {
    "addr:full":"Carrer de Viladomat, 316 Barcelona Barcelona 08029",
    "addr:housenumber":"316",
    "addr:postcode":"08029",
    "addr:street":"Carrer De Viladomat",
    "iso:country":"ES",
    "sg:address":"Carrer de Viladomat, 316",
    "sg:city":"Barcelona",
    "sg:orig_category":"Molduras, Junquillos, Listones Y Molduras Perforadas",
    "sg:phone":"+34 934 10 77 56",
    "sg:postcode":"08029",
    "sg:province":"Barcelona",
    "wof:name":"Fernandez Pereira Juan Gil",
    "wof:placetype":"venue"
},
  "geometry": {"coordinates":[2.1443319321,41.3896446228],"type":"Point"}
}