{
  "type": "Feature",
  "properties": {
    "addr:full":"Calle de A - Poligono Industrial De Asipo, 6 Coru\u00d1o Asturias 33428",
    "addr:housenumber":"6",
    "addr:postcode":"33428",
    "addr:street":"Calle De A Poligono Industrial De Asipo;Asturias",
    "iso:country":"ES",
    "sg:address":"Calle de A - Poligono Industrial De Asipo, 6",
    "sg:city":"Coru\u00d1o",
    "sg:orig_category":"Mec\u00c1nico Del Autom\u00d3vil",
    "sg:phone":"+34 985 98 02 50",
    "sg:postcode":"33428",
    "sg:province":"Asturias",
    "wof:name":"Traktos Automocion S.l.",
    "wof:placetype":"venue"
},
  "geometry": {"coordinates":[-5.8358402252,43.4143867493],"type":"Point"}
}