{
  "type": "Feature",
  "properties": {
    "iso:country":"ES",
    "sg:address":"Terminos De Campillos, S/n",
    "sg:city":"Villafranca Ebro",
    "sg:orig_category":"Agricultores, Agricultores",
    "sg:phone":"+34 976 16 70 28",
    "sg:postcode":"50174",
    "sg:province":"Zaragoza",
    "wof:name":"Barreras S.c.",
    "wof:placetype":"venue"
},
  "geometry": {"coordinates":[-0.6457740068,41.5761795044],"type":"Point"}
}