{
  "type": "Feature",
  "properties": {
    "iso:country":"ES",
    "sg:address":"Calle de Major Sant Agusti, 19",
    "sg:city":"Alzira",
    "sg:orig_category":"Lavado, Limpieza De Veh\u00cdculos",
    "sg:phone":"+34 962 41 20 27",
    "sg:postcode":"46600",
    "sg:province":"Valencia",
    "wof:name":"Alcazar Fernandez Aurelio",
    "wof:placetype":"venue"
},
  "geometry": {"coordinates":[-0.4365738928,39.1496429443],"type":"Point"}
}