{
  "type": "Feature",
  "properties": {
    "addr:full":"Jazmin, 12 La Nucia Alicante 03530",
    "addr:housenumber":"12",
    "addr:postcode":"03530",
    "addr:street":"Jazmin",
    "iso:country":"ES",
    "sg:address":"Jazmin, 12",
    "sg:city":"La Nucia",
    "sg:orig_category":"M\u00c9dicos: Medicina General Orientada A La Homeopat\u00cda",
    "sg:phone":"+34 965 87 34 27",
    "sg:postcode":"03530",
    "sg:province":"Alicante",
    "wof:name":"Biotic Center S.l.",
    "wof:placetype":"venue"
},
  "geometry": {"coordinates":[-0.1246320009,38.5821800232],"type":"Point"}
}