{
  "type": "Feature",
  "properties": {
    "iso:country":"ES",
    "sg:address":"Plaz Honduras, 38",
    "sg:city":"Valencia",
    "sg:orig_category":"Molduras, Junquillos, Listones Y Molduras Perforadas",
    "sg:phone":"+34 963 55 41 42",
    "sg:postcode":"46022",
    "sg:province":"Valencia",
    "wof:name":"Bar Honduras 38 S.l.",
    "wof:placetype":"venue"
},
  "geometry": {"coordinates":[-0.3451620042,39.4741363525],"type":"Point"}
}