{
  "type": "Feature",
  "properties": {
    "iso:country":"ES",
    "sg:address":"Calle de Baldomero Villegas, S/n",
    "sg:city":"Santo\u00f1a",
    "sg:orig_category":"Conservas De Pescados Y Salazones Mar\u00cdtimos (fabricaci\u00d3n, Al Por Mayor)",
    "sg:phone":"+34 942 66 15 36",
    "sg:postcode":"39740",
    "sg:province":"Cantabria",
    "wof:name":"Conservas Del Norte S.l.",
    "wof:placetype":"venue"
},
  "geometry": {"coordinates":[-3.4598538876,43.4457511902],"type":"Point"}
}