{
  "type": "Feature",
  "properties": {
    "addr:full":"Calle de Espinosa Y Carcel, 43 Sevilla Sevilla 41005",
    "addr:housenumber":"43",
    "addr:postcode":"41005",
    "addr:street":"Calle De Espinosa Y Carcel",
    "iso:country":"ES",
    "sg:address":"Calle de Espinosa Y Carcel, 43",
    "sg:city":"Sevilla",
    "sg:orig_category":"Centros P\u00dablicos De Formaci\u00d3n Profesional Y T\u00c9cnica",
    "sg:phone":"+34 954 66 30 76",
    "sg:postcode":"41005",
    "sg:province":"Sevilla",
    "wof:name":"Colegio Oficial De Psicologos De Andalucia Occidental",
    "wof:placetype":"venue"
},
  "geometry": {"coordinates":[-5.9734330177,37.3783683777],"type":"Point"}
}