{
  "type": "Feature",
  "properties": {
    "iso:country":"ES",
    "sg:address":"Calle de General Gutierrez Mellado, S/n",
    "sg:city":"Valderrobres",
    "sg:orig_category":"Centros De Educaci\u00d3n Especial",
    "sg:phone":"+34 978 89 08 99",
    "sg:postcode":"44580",
    "sg:province":"Teruel",
    "wof:name":"D.g.a.-c.e.p.a.de Valderrobres-valderrobres",
    "wof:placetype":"venue"
},
  "geometry": {"coordinates":[0.1538449973,40.8726615906],"type":"Point"}
}