{
  "type": "Feature",
  "properties": {
    "addr:full":"Ctra. Nacional T. Cuarenta, Km. 0184,0 Marbella M\u00e1laga 29600",
    "addr:postcode":"29600",
    "addr:street":"Ctra. Nacional T. Cuarenta Km. 0184,0;Ma\u0301Laga",
    "iso:country":"ES",
    "sg:address":"Ctra. Nacional T. Cuarenta, Km. 0184,0",
    "sg:city":"Marbella",
    "sg:orig_category":"Electrodom\u00c9sticos (al Por Menor)",
    "sg:phone":"+34 952 90 33 03",
    "sg:postcode":"29600",
    "sg:province":"M\u00e1laga",
    "wof:name":"V 12 Trade S.l.",
    "wof:placetype":"venue"
},
  "geometry": {"coordinates":[-4.8833007812,36.5079956055],"type":"Point"}
}