{
  "type": "Feature",
  "properties": {
    "iso:country":"ES",
    "sg:address":"Av Sant Pau, 25",
    "sg:city":"Alcover",
    "sg:orig_category":"Ingenier\u00cda, Centros De Estudios (diversos)",
    "sg:phone":"+34 977 84 62 82",
    "sg:postcode":"43460",
    "sg:province":"Tarragona",
    "wof:name":"Barbera Gomis Josep",
    "wof:placetype":"venue"
},
  "geometry": {"coordinates":[1.1734390259,41.2606964111],"type":"Point"}
}