{
  "type": "Feature",
  "properties": {
    "iso:country":"ES",
    "sg:address":"A, S/n",
    "sg:city":"P. I. El Romeral",
    "sg:orig_category":"Empresas De Carpinter\u00cda Met\u00c1lica",
    "sg:phone":"+34 962 30 57 12",
    "sg:postcode":"46340",
    "sg:province":"Valencia",
    "wof:name":"Perez Montes Carlos",
    "wof:placetype":"venue"
},
  "geometry": {"coordinates":[-1.0998990536,39.4906158447],"type":"Point"}
}