{
  "type": "Feature",
  "properties": {
    "addr:full":"Pl. Ayuntamiento, S/n Campo Caso Asturias 33990",
    "addr:housenumber":"/ n",
    "addr:postcode":"33990",
    "addr:street":"Ayuntamiento S",
    "iso:country":"ES",
    "sg:address":"Pl. Ayuntamiento, S/n",
    "sg:city":"Campo Caso",
    "sg:orig_category":"Confiter\u00cda, Galletas Y Pastas, Chocolater\u00cda (al Por Mayor)",
    "sg:phone":"+34 985 60 80 23",
    "sg:postcode":"33990",
    "sg:province":"Asturias",
    "wof:name":"Suspiros Del Nalon S. L.",
    "wof:placetype":"venue"
},
  "geometry": {"coordinates":[-5.3443040848,43.1825866699],"type":"Point"}
}