{
  "type": "Feature",
  "properties": {
    "addr:full":"Av Valles, 322 Terrassa Barcelona 08227",
    "addr:housenumber":"322",
    "addr:postcode":"08227",
    "addr:street":"Av Valles",
    "iso:country":"ES",
    "sg:address":"Av Valles, 322",
    "sg:city":"Terrassa",
    "sg:orig_category":"Aparatos, Material Y Suministros Para Laboratorios",
    "sg:phone":"+34 937 84 51 12",
    "sg:postcode":"08227",
    "sg:province":"Barcelona",
    "wof:name":"Trade Raypa S.l",
    "wof:placetype":"venue"
},
  "geometry": {"coordinates":[2.0399770737,41.5507545471],"type":"Point"}
}