{
  "type": "Feature",
  "properties": {
    "iso:country":"ES",
    "sg:address":"Pase San Jose, 46",
    "sg:city":"Palmas De Gran Canaria",
    "sg:orig_category":"Relojer\u00cda (al Por Menor, Reparaci\u00d3n)",
    "sg:phone":"+34 928 31 19 39",
    "sg:postcode":"35015",
    "sg:province":"Las Palmas",
    "wof:name":"Gonzalez Trujillo Antonio",
    "wof:placetype":"venue"
},
  "geometry": {"coordinates":[-15.4232616425,28.095746994],"type":"Point"}
}