{
  "type": "Feature",
  "properties": {
    "addr:full":"Calle de Elfo, 76 Madrid Madrid 28027",
    "addr:housenumber":"76",
    "addr:postcode":"madrid;28027",
    "addr:street":"Calle De Elfo",
    "iso:country":"ES",
    "sg:address":"Calle de Elfo, 76",
    "sg:city":"Madrid",
    "sg:orig_category":"Peluquer\u00cdas, Peluquer\u00cda Mixta",
    "sg:phone":"+34 914 08 16 51",
    "sg:postcode":"28027",
    "sg:province":"Madrid",
    "wof:name":"Anic Gabana Estilistas S.l.",
    "wof:placetype":"venue"
},
  "geometry": {"coordinates":[-3.6483263969,40.4344711304],"type":"Point"}
}