{
  "type": "Feature",
  "properties": {
    "addr:full":"Calle de Sirio, 50 Madrid Madrid 28007",
    "addr:housenumber":"50",
    "addr:postcode":"madrid;28007",
    "addr:street":"Calle De Sirio",
    "iso:country":"ES",
    "sg:address":"Calle de Sirio, 50",
    "sg:city":"Madrid",
    "sg:orig_category":"Inform\u00c1tica, Ofim\u00c1tica (estudios, Asesor\u00cda, Ingenier\u00cda, Formaci\u00d3n)",
    "sg:phone":"+34 915 04 00 87",
    "sg:postcode":"28007",
    "sg:province":"Madrid",
    "wof:name":"Investigacion Y Desarrollo Humano S.l.",
    "wof:placetype":"venue"
},
  "geometry": {"coordinates":[-3.6643431187,40.4101982117],"type":"Point"}
}