{
  "type": "Feature",
  "properties": {
    "addr:full":"Carrer de Navarra, 1 Horta S. Joan Tarragona 43596",
    "addr:housenumber":"1",
    "addr:postcode":"43596",
    "addr:street":"Carrer De Navarra;S. Joan",
    "iso:country":"ES",
    "sg:address":"Carrer de Navarra, 1",
    "sg:city":"Horta S. Joan",
    "sg:orig_category":"Comercio De Muebles De Estilo Y Contempor\u00c1neos",
    "sg:phone":"+34 977 43 50 84",
    "sg:postcode":"43596",
    "sg:province":"Tarragona",
    "wof:name":"Asensio Rel Marcelino",
    "wof:placetype":"venue"
},
  "geometry": {"coordinates":[0.3136079013,40.9545783997],"type":"Point"}
}