{
  "type": "Feature",
  "properties": {
    "addr:full":"Avda Burjasot, 148 Valencia Valencia 46025",
    "addr:housenumber":"148",
    "addr:postcode":"46025",
    "addr:street":"Avda Burjasot",
    "iso:country":"ES",
    "sg:address":"Avda Burjasot, 148",
    "sg:city":"Valencia",
    "sg:orig_category":"Ropa Para Ni\u00d1os (al Por Menor)",
    "sg:phone":"+34 963 49 66 76",
    "sg:postcode":"46025",
    "sg:province":"Valencia",
    "wof:name":"Cuerda Cabezuelo Matilde",
    "wof:placetype":"venue"
},
  "geometry": {"coordinates":[-0.3914220035,39.4907722473],"type":"Point"}
}