{
  "type": "Feature",
  "properties": {
    "iso:country":"ES",
    "sg:address":"Calle de Aragon (de), 43",
    "sg:city":"Mejorada Campo",
    "sg:orig_category":"Zapater\u00cds Y Cordeler\u00cda",
    "sg:phone":"+34 916 79 13 93",
    "sg:postcode":"28840",
    "sg:province":"Madrid",
    "wof:name":"Arosa Coral S.l.",
    "wof:placetype":"venue"
},
  "geometry": {"coordinates":[-3.4807844162,40.3841094971],"type":"Point"}
}