{
  "type": "Feature",
  "properties": {
    "iso:country":"ES",
    "sg:address":"Carrer de Don Alarico Lopez Teruel, 5",
    "sg:city":"Crevillent",
    "sg:orig_category":"Promotores Constructores",
    "sg:phone":"+34 966 68 09 53",
    "sg:postcode":"03330",
    "sg:province":"Alicante",
    "wof:name":"Construcciones Crevi-alcaina S.l.",
    "wof:placetype":"venue"
},
  "geometry": {"coordinates":[-0.8056899905,38.2489204407],"type":"Point"}
}