{
  "type": "Feature",
  "properties": {
    "addr:full":"Rinaldi, 17 Iru\u00f1a Navarra 31007",
    "addr:housenumber":"17",
    "addr:postcode":"31007",
    "addr:street":"Rinaldi",
    "iso:country":"ES",
    "sg:address":"Rinaldi, 17",
    "sg:city":"Iru\u00f1a",
    "sg:orig_category":"Cristaler\u00cdas",
    "sg:phone":"+34 948 27 01 57",
    "sg:postcode":"31007",
    "sg:province":"Navarra",
    "wof:name":"Lopez Diaz Rafael",
    "wof:placetype":"venue"
},
  "geometry": {"coordinates":[-1.6484446526,42.8064231873],"type":"Point"}
}