{
  "type": "Feature",
  "properties": {
    "addr:full":"Rua Rosalia De Castro, 33 Burela Lugo 27880",
    "addr:housenumber":"33",
    "addr:postcode":"27880",
    "addr:street":"Rua Rosalia De Castro",
    "iso:country":"ES",
    "sg:address":"Rua Rosalia De Castro, 33",
    "sg:city":"Burela",
    "sg:orig_category":"Centros Empresariales",
    "sg:phone":"+34 982 58 04 53",
    "sg:postcode":"27880",
    "sg:province":"Lugo",
    "wof:name":"Fari\u00f1a Alonso Patricia",
    "wof:placetype":"venue"
},
  "geometry": {"coordinates":[-7.3609890938,43.6615982056],"type":"Point"}
}