{
  "type": "Feature",
  "properties": {
    "iso:country":"ES",
    "sg:address":"Pque Doctor Calatayud, 14",
    "sg:city":"Aspe",
    "sg:orig_category":"Quincaller\u00cda (al Por Mayor)",
    "sg:phone":"+34 965 49 16 99",
    "sg:postcode":"03680",
    "sg:province":"Alicante",
    "wof:name":"Prieto Pastor Jose Maria",
    "wof:placetype":"venue"
},
  "geometry": {"coordinates":[-0.7667800188,38.3463249207],"type":"Point"}
}