{
  "type": "Feature",
  "properties": {
    "iso:country":"ES",
    "sg:address":"Calle de Roque Del Este, 89",
    "sg:city":"Puerto Del Carmen",
    "sg:orig_category":"Centros De Coordinaci\u00d3n",
    "sg:phone":"+34 928 51 44 44",
    "sg:postcode":"35510",
    "sg:province":"Las Palmas",
    "wof:name":"Garrido Lopez Jose Maria",
    "wof:placetype":"venue"
},
  "geometry": {"coordinates":[-13.668847084,28.9203872681],"type":"Point"}
}