{
  "type": "Feature",
  "properties": {
    "iso:country":"ES",
    "sg:address":"Calle de Sagunto, 192",
    "sg:city":"Valencia",
    "sg:orig_category":"Asociaciones, Organismos Culturales Y Socioeducativos",
    "sg:phone":"+34 963 65 69 88",
    "sg:postcode":"46009",
    "sg:province":"Valencia",
    "wof:name":"Confederacion De Centros Juveniles Don Bosco",
    "wof:placetype":"venue"
},
  "geometry": {"coordinates":[-0.373842001,39.4917945862],"type":"Point"}
}