{
  "type": "Feature",
  "properties": {
    "iso:country":"ES",
    "sg:address":"Calle de Almenillas, 6",
    "sg:city":"Granada",
    "sg:orig_category":"Peluqueros: De Se\u00d1oras",
    "sg:phone":"+34 958 20 24 84",
    "sg:postcode":"18003",
    "sg:province":"Granada",
    "wof:name":"Ruiz Castillo Maria Del Carmen",
    "wof:placetype":"venue"
},
  "geometry": {"coordinates":[-3.6106908321,37.1793556213],"type":"Point"}
}