{
  "type": "Feature",
  "properties": {
    "addr:full":"Calle de Ayala, 88 Madrid Madrid 28001",
    "addr:housenumber":"88",
    "addr:postcode":"madrid;28001",
    "addr:street":"Calle De Ayala",
    "iso:country":"ES",
    "sg:address":"Calle de Ayala, 88",
    "sg:city":"Madrid",
    "sg:orig_category":"Importaci\u00d3n",
    "sg:phone":"+34 914 35 42 51",
    "sg:postcode":"28001",
    "sg:province":"Madrid",
    "sg:website":"www.troyani.com",
    "wof:name":"Liberty Laser S.l.",
    "wof:placetype":"venue"
},
  "geometry": {"coordinates":[-3.6772098541,40.4273681641],"type":"Point"}
}