{
  "type": "Feature",
  "properties": {
    "iso:country":"ES",
    "sg:address":"Calle de Gran Via, 1",
    "sg:city":"Almazan",
    "sg:orig_category":"Peluquer\u00cdas, Peluquer\u00cda Mixta",
    "sg:phone":"+34 975 30 18 00",
    "sg:postcode":"42200",
    "sg:province":"Soria",
    "wof:name":"Garcia Contreras Maria Isabel",
    "wof:placetype":"venue"
},
  "geometry": {"coordinates":[-2.5315070152,41.4871520996],"type":"Point"}
}