{
  "type": "Feature",
  "properties": {
    "iso:country":"ES",
    "sg:address":"Calle de Rio Conilete, 3",
    "sg:city":"Conil De La Frontera",
    "sg:orig_category":"Oficinas Y Gesti\u00d3n De Inmuebles",
    "sg:phone":"+34 956 44 34 72",
    "sg:postcode":"11140",
    "sg:province":"C\u00e1diz",
    "sg:website":"www.paradise-now.net",
    "wof:name":"Paraiso Ahora, S.l.",
    "wof:placetype":"venue"
},
  "geometry": {"coordinates":[-6.0850758553,36.27784729],"type":"Point"}
}