{
  "type": "Feature",
  "properties": {
    "iso:country":"ES",
    "sg:address":"Calle de La Calzada, 8",
    "sg:city":"San Vicente De Barakaldo",
    "sg:orig_category":"Ense\u00d1anza: Comercio, Gesti\u00d3n, Inform\u00c1tica",
    "sg:phone":"+34 944 97 07 05",
    "sg:postcode":"48903",
    "sg:province":"Vizcaya",
    "wof:name":"Santamaria Gonzalez Arantza",
    "wof:placetype":"venue"
},
  "geometry": {"coordinates":[-2.980312109,43.2803421021],"type":"Point"}
}