{
  "type": "Feature",
  "properties": {
    "addr:full":"Carr Ferran Rambla, 52 Lleida Lleida 25007",
    "addr:housenumber":"52",
    "addr:postcode":"25007",
    "addr:street":"Carr Ferran Rambla",
    "iso:country":"ES",
    "sg:address":"Carr Ferran Rambla, 52",
    "sg:city":"Lleida",
    "sg:orig_category":"Abogados",
    "sg:phone":"+34 973 23 70 33",
    "sg:postcode":"25007",
    "sg:province":"Lleida",
    "wof:name":"Portoles Aixala Miguel Angel",
    "wof:placetype":"venue"
},
  "geometry": {"coordinates":[0.627129972,41.6145210266],"type":"Point"}
}