{
  "type": "Feature",
  "properties": {
    "addr:full":"Calle de Frailes, 14 Granada Granada 18005",
    "addr:housenumber":"14",
    "addr:postcode":"18005",
    "addr:street":"Calle De Frailes",
    "iso:country":"ES",
    "sg:address":"Calle de Frailes, 14",
    "sg:city":"Granada",
    "sg:orig_category":"Peluqueros: De Se\u00d1oras",
    "sg:phone":"+34 958 25 50 38",
    "sg:postcode":"18005",
    "sg:province":"Granada",
    "wof:name":"Peluqueria Y Belleza Daniel S.l.",
    "wof:placetype":"venue"
},
  "geometry": {"coordinates":[-3.6013889313,37.1720809937],"type":"Point"}
}