{
  "type": "Feature",
  "properties": {
    "addr:full":"Poligono Berroa, S/n Tajonar Navarra 31192",
    "addr:housenumber":"s / n",
    "addr:postcode":"31192",
    "addr:street":"Poligono Berroa",
    "iso:country":"ES",
    "sg:address":"Poligono Berroa, S/n",
    "sg:city":"Tajonar",
    "sg:orig_category":"Explotaci\u00d3n De Canteras",
    "sg:phone":"+34 948 31 64 64",
    "sg:postcode":"31192",
    "sg:province":"Navarra",
    "wof:name":"Grupo Cetya S.a.",
    "wof:placetype":"venue"
},
  "geometry": {"coordinates":[-1.6151809692,42.7892303467],"type":"Point"}
}