{
  "type": "Feature",
  "properties": {
    "iso:country":"ES",
    "sg:address":"Calle de Veredas, 22",
    "sg:city":"Cantillana",
    "sg:orig_category":"Centros De Educaci\u00d3n Especial",
    "sg:phone":"+34 955 73 01 47",
    "sg:postcode":"41320",
    "sg:province":"Sevilla",
    "wof:name":"Maqueda Perez Maria Jose",
    "wof:placetype":"venue"
},
  "geometry": {"coordinates":[-5.822947979,37.6061325073],"type":"Point"}
}