{
  "type": "Feature",
  "properties": {
    "iso:country":"ES",
    "sg:address":"Ctra. Salamanca, Km. 0019,7",
    "sg:city":"Boveda Toro",
    "sg:orig_category":"Producci\u00d3n, Comercio De Cereales",
    "sg:phone":"+34 980 60 20 20",
    "sg:postcode":"49155",
    "sg:province":"Zamora",
    "wof:name":"Semillas Y Cereales Esteban Ruiz S.l.",
    "wof:placetype":"venue"
},
  "geometry": {"coordinates":[-5.4101099968,41.343334198],"type":"Point"}
}