{
  "type": "Feature",
  "properties": {
    "iso:country":"ES",
    "sg:address":"Rua Lalin, 2",
    "sg:city":"Vigo",
    "sg:orig_category":"Caf\u00c9s, Bares, Cervecer\u00cdas",
    "sg:phone":"+34 986 20 59 56",
    "sg:postcode":"36209",
    "sg:province":"Pontevedra",
    "wof:name":"Galtelcom",
    "wof:placetype":"venue"
},
  "geometry": {"coordinates":[-8.7341461182,42.2215919495],"type":"Point"}
}