{
  "type": "Feature",
  "properties": {
    "iso:country":"ES",
    "sg:address":"Carrer de Sant Cristofol, 24",
    "sg:city":"Piera",
    "sg:orig_category":"Sociedades, Compa\u00d1\u00cdas Aseguradoras",
    "sg:phone":"+34 937 76 23 01",
    "sg:postcode":"08784",
    "sg:province":"Barcelona",
    "wof:name":"Seguros Catalana Occidente S.a. De Seguros Y Reaseguros",
    "wof:placetype":"venue"
},
  "geometry": {"coordinates":[1.7496210337,41.5209693909],"type":"Point"}
}