{
  "type": "Feature",
  "properties": {
    "iso:country":"ES",
    "sg:address":"Ctra Cordoba-malaga, Km. 0447,0",
    "sg:city":"Montilla",
    "sg:orig_category":"Hormigonados",
    "sg:phone":"+34 957 65 18 04",
    "sg:postcode":"14550",
    "sg:province":"C\u00f3rdoba",
    "wof:name":"Hormigones Marques Marquez S.a.",
    "wof:placetype":"venue"
},
  "geometry": {"coordinates":[-4.6605410576,37.5884437561],"type":"Point"}
}