{
  "type": "Feature",
  "properties": {
    "iso:country":"ES",
    "sg:address":"Carretera Madrid, 33",
    "sg:city":"Sta. Barbara",
    "sg:orig_category":"Mec\u00c1nico Del Autom\u00d3vil",
    "sg:phone":"+34 977 71 80 17",
    "sg:postcode":"43570",
    "sg:province":"Tarragona",
    "wof:name":"Muria Queral Joaquin",
    "wof:placetype":"venue"
},
  "geometry": {"coordinates":[0.5016599894,40.7150039673],"type":"Point"}
}