{
  "type": "Feature",
  "properties": {
    "iso:country":"ES",
    "sg:address":"Plaz Tirso De Molina, 18",
    "sg:city":"Madrid",
    "sg:classifiers":[
        {
            "category":"Autos & Motor Vehicles",
            "subcategory":"Automobile Sales",
            "type":"Retail Goods"
        }
    ],
    "sg:phone":"+34 913 69 38 36",
    "sg:postcode":"28012",
    "sg:province":"Madrid",
    "wof:name":"Martin Martin Santiago",
    "wof:placetype":"venue"
},
  "geometry": {"coordinates":[-3.7041840553,40.4126205444],"type":"Point"}
}