{
  "type": "Feature",
  "properties": {
    "iso:country":"ES",
    "sg:address":"Alto San Agustin, 36",
    "sg:city":"Utiel",
    "sg:orig_category":"Cerrajer\u00cda, Ferrallista",
    "sg:phone":"+34 962 17 12 42",
    "sg:postcode":"46300",
    "sg:province":"Valencia",
    "wof:name":"Hermanos Paquilletes C.b.",
    "wof:placetype":"venue"
},
  "geometry": {"coordinates":[-1.2161849737,39.5644798279],"type":"Point"}
}