{
  "type": "Feature",
  "properties": {
    "iso:country":"ES",
    "sg:address":"Av Francesc Macia, 71",
    "sg:city":"Vilanova I La Geltru",
    "sg:orig_category":"Zapatos (al Por Menor)",
    "sg:phone":"+34 938 15 88 09",
    "sg:postcode":"08800",
    "sg:province":"Barcelona",
    "wof:name":"Ruiz Martinez Carmen",
    "wof:placetype":"venue"
},
  "geometry": {"coordinates":[1.7210530043,41.2225418091],"type":"Point"}
}