{
  "type": "Feature",
  "properties": {
    "addr:full":"Calle de Cuba, 8 Aviles Asturias 33401",
    "addr:housenumber":"8",
    "addr:postcode":"33401",
    "addr:street":"Calle De Cuba",
    "iso:country":"ES",
    "sg:address":"Calle de Cuba, 8",
    "sg:city":"Aviles",
    "sg:orig_category":"Agencias Y Agentes Comerciales, Representantes",
    "sg:phone":"+34 985 56 12 53",
    "sg:postcode":"33401",
    "sg:province":"Asturias",
    "wof:name":"Llames Del Canto Jose Enrique",
    "wof:placetype":"venue"
},
  "geometry": {"coordinates":[-5.9256424904,43.5574035645],"type":"Point"}
}