{
  "type": "Feature",
  "properties": {
    "iso:country":"ES",
    "sg:address":"Plaza Europa, 3",
    "sg:city":"Barakaldo",
    "sg:orig_category":"Formaci\u00d3n Continuada (variada)",
    "sg:phone":"+34 944 38 28 03",
    "sg:postcode":"48901",
    "sg:province":"Vizcaya",
    "wof:name":"Lanor Elkartea, S.l.",
    "wof:placetype":"venue"
},
  "geometry": {"coordinates":[-2.9881269932,43.2987213135],"type":"Point"}
}