{
  "type": "Feature",
  "properties": {
    "iso:country":"ES",
    "sg:address":"Av. B. Navarra, 1",
    "sg:city":"Iru\u00f1a",
    "sg:orig_category":"Comisarios",
    "sg:phone":"+34 948 22 59 93",
    "sg:postcode":"31002",
    "sg:province":"Navarra",
    "wof:name":"Elorz Sanchez Marco Maria Teresa",
    "wof:placetype":"venue"
},
  "geometry": {"coordinates":[-1.6415859461,42.8130455017],"type":"Point"}
}