{
  "type": "Feature",
  "properties": {
    "addr:full":"Calle de Doctor Collado Pi\u00d1a, 83 Albacete Albacete 02003",
    "addr:housenumber":"83",
    "addr:postcode":"02003",
    "addr:street":"Calle De Doctor Collado Pin\u0303A",
    "iso:country":"ES",
    "sg:address":"Calle de Doctor Collado Pi\u00d1a, 83",
    "sg:city":"Albacete",
    "sg:orig_category":"Albergues",
    "sg:phone":"+34 967 23 85 30",
    "sg:postcode":"02003",
    "sg:province":"Albacete",
    "wof:name":"Moya Alarcon Juana",
    "wof:placetype":"venue"
},
  "geometry": {"coordinates":[-1.8625540733,38.9883117676],"type":"Point"}
}