{
  "type": "Feature",
  "properties": {
    "iso:country":"ES",
    "sg:address":"Carrer de Joan Maragall, S/n",
    "sg:city":"S. Boi Llobregat",
    "sg:orig_category":"Pescader\u00cdas (al Por Menor)",
    "sg:phone":"+34 936 54 11 03",
    "sg:postcode":"08830",
    "sg:province":"Barcelona",
    "wof:name":"Nocarpeix S.l.",
    "wof:placetype":"venue"
},
  "geometry": {"coordinates":[2.0351920128,41.3556785583],"type":"Point"}
}