{
  "type": "Feature",
  "properties": {
    "iso:country":"ES",
    "sg:address":"Calle de Honduras, 2",
    "sg:city":"Salamanca",
    "sg:orig_category":"Laboratorios Y Trabajos De Fotograf\u00cda, V\u00cddeo Y Cine",
    "sg:phone":"+34 923 22 90 90",
    "sg:postcode":"37003",
    "sg:province":"Salamanca",
    "wof:name":"Seisdedos Martin Jesus",
    "wof:placetype":"venue"
},
  "geometry": {"coordinates":[-5.6551790237,40.9647102356],"type":"Point"}
}