{
  "type": "Feature",
  "properties": {
    "addr:full":"Plaz Juan Carlos I, 1 Salobre\u00f1a Granada 18680",
    "addr:housenumber":"1",
    "addr:postcode":"18680",
    "addr:street":"Plaz Juan Carlos I",
    "iso:country":"ES",
    "sg:address":"Plaz Juan Carlos I, 1",
    "sg:city":"Salobre\u00f1a",
    "sg:orig_category":"Discapacitados",
    "sg:phone":"+34 958 61 21 86",
    "sg:postcode":"18680",
    "sg:province":"Granada",
    "wof:name":"Asmisa",
    "wof:placetype":"venue"
},
  "geometry": {"coordinates":[-3.5913939476,36.7602424622],"type":"Point"}
}