{
  "type": "Feature",
  "properties": {
    "addr:full":"Calle de Do\u00d1a Guillerma, S/n Caravaca Cruz Murcia 30400",
    "addr:housenumber":"s",
    "addr:postcode":"30400",
    "addr:street":"Calle De Don\u0303A Guillerma;/ N Caravaca Cruz",
    "iso:country":"ES",
    "sg:address":"Calle de Do\u00d1a Guillerma, S/n",
    "sg:city":"Caravaca Cruz",
    "sg:orig_category":"Bares, Piano",
    "sg:phone":"+34 968 70 33 71",
    "sg:postcode":"30400",
    "sg:province":"Murcia",
    "wof:name":"Sanchez Martinez Jesus",
    "wof:placetype":"venue"
},
  "geometry": {"coordinates":[-1.8597240448,38.1049346924],"type":"Point"}
}