{
  "type": "Feature",
  "properties": {
    "addr:full":"Calle de Qui\u00d1ones De Leon, 6 Le\u00f3n Le\u00f3n 24009",
    "addr:housenumber":"6",
    "addr:postcode":"24009",
    "addr:street":"Calle De Quin\u0303Ones De Leon;Leo\u0301N",
    "iso:country":"ES",
    "sg:address":"Calle de Qui\u00d1ones De Leon, 6",
    "sg:city":"Le\u00f3n",
    "sg:orig_category":"Carnicer\u00cdas, Carnicer\u00cdas",
    "sg:phone":"+34 987 23 39 63",
    "sg:postcode":"24009",
    "sg:province":"Le\u00f3n",
    "wof:name":"Garcia Campelo Eduardo",
    "wof:placetype":"venue"
},
  "geometry": {"coordinates":[-5.5818390846,42.5977287292],"type":"Point"}
}