{
  "type": "Feature",
  "properties": {
    "addr:full":"Calle de Escorial (del), 37 Navalcarnero Madrid 28600",
    "addr:housenumber":"37",
    "addr:postcode":"28600",
    "addr:street":"Calle De Escorial Del",
    "iso:country":"ES",
    "sg:address":"Calle de Escorial (del), 37",
    "sg:city":"Navalcarnero",
    "sg:orig_category":"Ropa Para Se\u00d1oras (al Por Menor)",
    "sg:phone":"+34 918 11 29 09",
    "sg:postcode":"28600",
    "sg:province":"Madrid",
    "wof:name":"Del Carmen Ruiz Sonia",
    "wof:placetype":"venue"
},
  "geometry": {"coordinates":[-4.0160360336,40.2892112732],"type":"Point"}
}