{
  "type": "Feature",
  "properties": {
    "addr:full":"Ctra Pont De Molins, Km. 0001,5 Masies De Dalt Girona 17761",
    "addr:postcode":"17761",
    "addr:street":"Ctra Pont De Molins Km. 0001,5 Masies De Dalt",
    "iso:country":"ES",
    "sg:address":"Ctra Pont De Molins, Km. 0001,5",
    "sg:city":"Masies De Dalt",
    "sg:orig_category":"Material Y Herramientas Agr\u00cdcolas",
    "sg:phone":"+34 972 50 90 09",
    "sg:postcode":"17761",
    "sg:province":"Girona",
    "wof:name":"Jorda Pereda Jorge",
    "wof:placetype":"venue"
},
  "geometry": {"coordinates":[2.9780449867,42.3078231812],"type":"Point"}
}