{
  "type": "Feature",
  "properties": {
    "iso:country":"ES",
    "sg:address":"Carrer de Anfos, 5",
    "sg:city":"Can Pastilla",
    "sg:orig_category":"Muebles, Minoristas",
    "sg:phone":"+34 971 26 71 42",
    "sg:postcode":"07610",
    "sg:province":"Islas Baleares",
    "wof:name":"Solera Ripoll Victoria",
    "wof:placetype":"venue"
},
  "geometry": {"coordinates":[2.7132771015,39.5375747681],"type":"Point"}
}