{
  "type": "Feature",
  "properties": {
    "addr:full":"Plaz Gutierrez Semprun, 5 Valladolid Valladolid 47012",
    "addr:housenumber":"5",
    "addr:postcode":"47012",
    "addr:street":"Plaz;Semprun",
    "iso:country":"ES",
    "sg:address":"Plaz Gutierrez Semprun, 5",
    "sg:city":"Valladolid",
    "sg:orig_category":"Carnicer\u00cdas, Carnicer\u00cdas",
    "sg:phone":"+34 983 21 01 84",
    "sg:postcode":"47012",
    "sg:province":"Valladolid",
    "wof:name":"Gonzalez Miguelez Carlos",
    "wof:placetype":"venue"
},
  "geometry": {"coordinates":[-4.7165460587,41.6414794922],"type":"Point"}
}