{
  "type": "Feature",
  "properties": {
    "iso:country":"ES",
    "sg:address":"Pase Maritimo, S/n",
    "sg:city":"Puerto Rico",
    "sg:orig_category":"Restaurantes",
    "sg:phone":"+34 928 56 04 31",
    "sg:postcode":"35130",
    "sg:province":"Las Palmas",
    "wof:name":"Nu\u00f1ez Navarro Rafael",
    "wof:placetype":"venue"
},
  "geometry": {"coordinates":[-15.7132101059,27.785446167],"type":"Point"}
}