{
  "type": "Feature",
  "properties": {
    "iso:country":"ES",
    "sg:address":"Calle de Conde De Osborne, 27",
    "sg:city":"Sevilla",
    "sg:orig_category":"M\u00c9dicos: Estomatolog\u00cda",
    "sg:phone":"+34 954 51 45 36",
    "sg:postcode":"41007",
    "sg:province":"Sevilla",
    "wof:name":"Caballo Giles Maria Del Rosario",
    "wof:placetype":"venue"
},
  "geometry": {"coordinates":[-5.9502177238,37.401889801],"type":"Point"}
}