{
  "type": "Feature",
  "properties": {
    "addr:full":"Sa Volta, 11 Sant Lluis Islas Baleares 07710",
    "addr:housenumber":"11",
    "addr:postcode":"07710",
    "addr:street":"Volta",
    "iso:country":"ES",
    "sg:address":"Sa Volta, 11",
    "sg:city":"Sant Lluis",
    "sg:orig_category":"Telas: Impresi\u00d3n, Tinte, Tratamiento, Transformaci\u00d3n",
    "sg:phone":"+34 971 15 15 91",
    "sg:postcode":"07710",
    "sg:province":"Islas Baleares",
    "wof:name":"Mehoca Serveis S.l.",
    "wof:placetype":"venue"
},
  "geometry": {"coordinates":[4.2637519836,39.8616676331],"type":"Point"}
}