{
  "type": "Feature",
  "properties": {
    "iso:country":"ES",
    "sg:address":"Ctra. Andratx, 59",
    "sg:city":"Peguera",
    "sg:orig_category":"Estancos",
    "sg:phone":"+34 971 68 61 46",
    "sg:postcode":"07160",
    "sg:province":"Islas Baleares",
    "wof:name":"Mari Riera Francisca",
    "wof:placetype":"venue"
},
  "geometry": {"coordinates":[2.4631509781,39.5322647095],"type":"Point"}
}