{
  "type": "Feature",
  "properties": {
    "iso:country":"ES",
    "sg:address":"Pl Carme, 15",
    "sg:city":"Tarrega",
    "sg:orig_category":"Asesor\u00cda Sobre Comunicaci\u00d3n De Empresas",
    "sg:phone":"+34 973 31 39 90",
    "sg:postcode":"25300",
    "sg:province":"Lleida",
    "wof:name":"R.c.c. Tarrega, S.l.l.",
    "wof:placetype":"venue"
},
  "geometry": {"coordinates":[1.1398260593,41.6474990845],"type":"Point"}
}