{
  "type": "Feature",
  "properties": {
    "iso:country":"ES",
    "sg:address":"Plgno Ind Moncada Iii, 35",
    "sg:city":"Moncada",
    "sg:orig_category":"Promotores Constructores",
    "sg:phone":"+34 961 39 90 38",
    "sg:postcode":"46113",
    "sg:province":"Valencia",
    "wof:name":"Construnaves Levante",
    "wof:placetype":"venue"
},
  "geometry": {"coordinates":[-0.3982529938,39.5452728271],"type":"Point"}
}