{
  "type": "Feature",
  "properties": {
    "iso:country":"ES",
    "sg:address":"Calle de Numancia, 2",
    "sg:city":"Madrid",
    "sg:orig_category":"Agencias Y Agentes Comerciales, Representantes",
    "sg:phone":"+34 914 50 90 31",
    "sg:postcode":"28039",
    "sg:province":"Madrid",
    "wof:name":"Hernandez Atienza Enrique",
    "wof:placetype":"venue"
},
  "geometry": {"coordinates":[-3.7118940353,40.454750061],"type":"Point"}
}