{
  "type": "Feature",
  "properties": {
    "iso:country":"ES",
    "sg:address":"Avda Galicia, 99",
    "sg:city":"Gijon",
    "sg:orig_category":"Bisuter\u00cda, Joyer\u00cda, Relojer\u00cda (al Por Menor)",
    "sg:phone":"+34 985 31 11 50",
    "sg:postcode":"33212",
    "sg:province":"Asturias",
    "wof:name":"Suarez Alvarez Mercedes",
    "wof:placetype":"venue"
},
  "geometry": {"coordinates":[-5.6928291321,43.5395812988],"type":"Point"}
}