{
  "type": "Feature",
  "properties": {
    "iso:country":"ES",
    "sg:address":"Pg Carretera, 27",
    "sg:city":"Benidorm",
    "sg:orig_category":"Farmacias",
    "sg:phone":"+34 965 85 40 36",
    "sg:postcode":"03500",
    "sg:province":"Alicante",
    "wof:name":"Luz Ivars Matias Rafael",
    "wof:placetype":"venue"
},
  "geometry": {"coordinates":[-0.1310590059,38.5364379883],"type":"Point"}
}