{
  "type": "Feature",
  "properties": {
    "addr:full":"Calle de Santa Ana, 8 Zamora Zamora 49006",
    "addr:housenumber":"8",
    "addr:postcode":"49006",
    "addr:street":"Calle De Santa Ana",
    "iso:country":"ES",
    "sg:address":"Calle de Santa Ana, 8",
    "sg:city":"Zamora",
    "sg:orig_category":"Muebles Y Accesorios Para Cocinas Y Cuartos De Ba\u00d1o (al Por Menor)",
    "sg:phone":"+34 980 53 28 30",
    "sg:postcode":"49006",
    "sg:province":"Zamora",
    "wof:name":"Cociduero S.l.",
    "wof:placetype":"venue"
},
  "geometry": {"coordinates":[-5.7473511696,41.5067405701],"type":"Point"}
}