{
  "type": "Feature",
  "properties": {
    "addr:full":"Pol. Moli Bastida, S/n Rubi Barcelona 08191",
    "addr:housenumber":"s",
    "addr:postcode":"08191",
    "addr:street":"Pol.;Bastida;/ N",
    "iso:country":"ES",
    "sg:address":"Pol. Moli Bastida, S/n",
    "sg:city":"Rubi",
    "sg:orig_category":"Frutas Y Legumbres Frescas (al Por Mayor)",
    "sg:phone":"+34 936 99 75 00",
    "sg:postcode":"08191",
    "sg:province":"Barcelona",
    "sg:website":"www.olivasca\u00f1ete.com",
    "wof:name":"Olivas Y Encurtidos Ca\u00f1ete S.l.",
    "wof:placetype":"venue"
},
  "geometry": {"coordinates":[2.0281500816,41.4989509583],"type":"Point"}
}