{
  "type": "Feature",
  "properties": {
    "iso:country":"ES",
    "sg:address":"Avda Jandia (de), S/n",
    "sg:city":"Morro Jable",
    "sg:orig_category":"Alquiler De Veh\u00cdculos: Turismos Y Utilitarios",
    "sg:phone":"+34 928 54 16 56",
    "sg:postcode":"35625",
    "sg:province":"Las Palmas",
    "sg:website":"www.cicar.com",
    "wof:name":"Canary Islands Car S.l.",
    "wof:placetype":"venue"
},
  "geometry": {"coordinates":[-14.35019207,28.0503005981],"type":"Point"}
}