{
  "type": "Feature",
  "properties": {
    "iso:country":"ES",
    "sg:address":"Calle de Silio, 15",
    "sg:city":"Santiponce",
    "sg:orig_category":"Papeler\u00cdas, Librer\u00cdas",
    "sg:phone":"+34 955 99 77 69",
    "sg:postcode":"41970",
    "sg:province":"Sevilla",
    "wof:name":"Barrios Gonzalez Antonio",
    "wof:placetype":"venue"
},
  "geometry": {"coordinates":[-6.0410881042,37.4368209839],"type":"Point"}
}