{
  "type": "Feature",
  "properties": {
    "addr:full":"Calle de Nueva, 29 Villaviciosa Odon Madrid 28670",
    "addr:housenumber":"29",
    "addr:postcode":"28670",
    "addr:street":"Calle De Nueva;Odon",
    "iso:country":"ES",
    "sg:address":"Calle de Nueva, 29",
    "sg:city":"Villaviciosa Odon",
    "sg:orig_category":"Inmobiliaria (agencias)",
    "sg:phone":"+34 916 65 82 47",
    "sg:postcode":"28670",
    "sg:province":"Madrid",
    "wof:name":"Aliter Grupo Inmobiliario S.l.",
    "wof:placetype":"venue"
},
  "geometry": {"coordinates":[-3.9004294872,40.3569831848],"type":"Point"}
}