{
  "type": "Feature",
  "properties": {
    "addr:full":"Urb San Roque, 21 Cacabelos Le\u00f3n 24540",
    "addr:housenumber":"21",
    "addr:postcode":"24540",
    "addr:street":"San Roque",
    "iso:country":"ES",
    "sg:address":"Urb San Roque, 21",
    "sg:city":"Cacabelos",
    "sg:orig_category":"Mec\u00c1nico Del Autom\u00d3vil",
    "sg:phone":"+34 987 54 95 85",
    "sg:postcode":"24540",
    "sg:province":"Le\u00f3n",
    "wof:name":"Moreno Quintana Jesus",
    "wof:placetype":"venue"
},
  "geometry": {"coordinates":[-6.7260937691,42.5987586975],"type":"Point"}
}