{
  "type": "Feature",
  "properties": {
    "iso:country":"ES",
    "sg:address":"Calle de Lagasca, 98",
    "sg:city":"Madrid",
    "sg:orig_category":"Embajadas, Consulados Y Otras Representaciones Diplom\u00c1ticas",
    "sg:phone":"+34 914 23 33 00",
    "sg:postcode":"28...",
    "sg:province":"Madrid",
    "wof:name":"Embajada De Italia",
    "wof:placetype":"venue"
},
  "geometry": {"coordinates":[-3.6844630241,40.4322013855],"type":"Point"}
}