{
  "type": "Feature",
  "properties": {
    "addr:full":"Guadalmina Baja, S/n San Pedro Alcantara M\u00e1laga 29670",
    "addr:housenumber":"s / n",
    "addr:postcode":"29670",
    "addr:street":"Guadalmina Baja",
    "iso:country":"ES",
    "sg:address":"Guadalmina Baja, S/n",
    "sg:city":"San Pedro Alcantara",
    "sg:orig_category":"Importaci\u00d3n",
    "sg:phone":"+34 952 88 51 52",
    "sg:postcode":"29670",
    "sg:province":"M\u00e1laga",
    "wof:name":"Yamlet Trading Corporation S.l.",
    "wof:placetype":"venue"
},
  "geometry": {"coordinates":[-4.9986419678,36.4744491577],"type":"Point"}
}