{
  "type": "Feature",
  "properties": {
    "iso:country":"ES",
    "sg:address":"Pg Gran Passeig Ronda, 10",
    "sg:city":"Lleida",
    "sg:orig_category":"Centros P\u00dablicos De Formaci\u00d3n Profesional Y T\u00c9cnica",
    "sg:phone":"+34 973 28 27 05",
    "sg:postcode":"25002",
    "sg:province":"Lleida",
    "wof:name":"Co%egi Oficial De Doctors I Llicenciats",
    "wof:placetype":"venue"
},
  "geometry": {"coordinates":[0.627129972,41.6145210266],"type":"Point"}
}