{
  "type": "Feature",
  "properties": {
    "iso:country":"ES",
    "sg:address":"Avda Doctor Severo Ochoa (del), 43",
    "sg:city":"Alcobendas",
    "sg:orig_category":"Electricidad, Electr\u00d3nica: Suministros (al Por Menor)",
    "sg:phone":"+34 916 61 97 95",
    "sg:postcode":"28100",
    "sg:province":"Madrid",
    "wof:name":"Asp Electronic S.l.",
    "wof:placetype":"venue"
},
  "geometry": {"coordinates":[-3.6546041965,40.5410385132],"type":"Point"}
}