{
  "type": "Feature",
  "properties": {
    "addr:full":"Ctra. Loeches-torrejon Ardoz, S/n Loeches Madrid 28890",
    "addr:housenumber":"s / n",
    "addr:postcode":"28890",
    "addr:street":"Ctra. Loeches-Torrejon Ardoz",
    "iso:country":"ES",
    "sg:address":"Ctra. Loeches-torrejon Ardoz, S/n",
    "sg:city":"Loeches",
    "sg:orig_category":"Maquinaria Para Industrias Diversas",
    "sg:phone":"+34 918 85 18 25",
    "sg:postcode":"28890",
    "sg:province":"Madrid",
    "wof:name":"Servecar De Elevacion S.l.",
    "wof:placetype":"venue"
},
  "geometry": {"coordinates":[-3.4364190102,40.427444458],"type":"Point"}
}