{
  "type": "Feature",
  "properties": {
    "addr:full":"Ctra Caravaca (de), S/n Mula Murcia 30170",
    "addr:postcode":"30170",
    "addr:street":"Ctra Caravaca De S / N",
    "iso:country":"ES",
    "sg:address":"Ctra Caravaca (de), S/n",
    "sg:city":"Mula",
    "sg:orig_category":"Muebles, Minoristas",
    "sg:phone":"+34 968 66 17 08",
    "sg:postcode":"30170",
    "sg:province":"Murcia",
    "wof:name":"Lopez Martinez Pedro Gines",
    "wof:placetype":"venue"
},
  "geometry": {"coordinates":[-1.4951039553,38.0389518738],"type":"Point"}
}