{
  "type": "Feature",
  "properties": {
    "addr:full":"Trav Dalt, 74 Barcelona Barcelona 08024",
    "addr:housenumber":"74",
    "addr:postcode":"08024",
    "addr:street":"Trav Dalt",
    "iso:country":"ES",
    "sg:address":"Trav Dalt, 74",
    "sg:city":"Barcelona",
    "sg:orig_category":"M\u00c1quinas Y Material Para La Industria De La Alimentaci\u00d3n",
    "sg:phone":"+34 932 10 44 58",
    "sg:postcode":"08024",
    "sg:province":"Barcelona",
    "wof:name":"Eqypa I D Alimentaria S.l.",
    "wof:placetype":"venue"
},
  "geometry": {"coordinates":[2.1562559605,41.4102668762],"type":"Point"}
}