{
  "type": "Feature",
  "properties": {
    "iso:country":"ES",
    "sg:address":"Plaza Santa Monica, S/n",
    "sg:city":"Elviria",
    "sg:orig_category":"Administradores De Bienes Y Delegados De Comunidades De Propietarios",
    "sg:phone":"+34 952 83 36 36",
    "sg:postcode":"29604",
    "sg:province":"M\u00e1laga",
    "sg:website":"www.gomezvinas.com",
    "wof:name":"Gomez Vi\u00f1as Asesores S.l.",
    "wof:placetype":"venue"
},
  "geometry": {"coordinates":[-4.7516288757,36.4928512573],"type":"Point"}
}