{
  "type": "Feature",
  "properties": {
    "iso:country":"ES",
    "sg:address":"C/ Pedro Tuduri, 56",
    "sg:city":"Sant Lluis",
    "sg:orig_category":"Promotores Constructores",
    "sg:phone":"+34 971 15 17 18",
    "sg:postcode":"07710",
    "sg:province":"Islas Baleares",
    "wof:name":"Sefarat, S.c.",
    "wof:placetype":"venue"
},
  "geometry": {"coordinates":[4.2691421509,39.8487739563],"type":"Point"}
}