{
  "type": "Feature",
  "properties": {
    "addr:full":"Plaz Escultor Frechina, 9 Valencia Valencia 46017",
    "addr:housenumber":"9",
    "addr:postcode":"46017",
    "addr:street":"Frechina",
    "iso:country":"ES",
    "sg:address":"Plaz Escultor Frechina, 9",
    "sg:city":"Valencia",
    "sg:orig_category":"Peluqueros: De Se\u00d1oras",
    "sg:phone":"+34 963 78 26 04",
    "sg:postcode":"46017",
    "sg:province":"Valencia",
    "wof:name":"Gabaldon Garcia Antonio",
    "wof:placetype":"venue"
},
  "geometry": {"coordinates":[-0.3898000121,39.4515647888],"type":"Point"}
}