{
  "type": "Feature",
  "properties": {
    "iso:country":"ES",
    "sg:address":"Carrer de Endavallada, 23",
    "sg:city":"S. Cugat Valles",
    "sg:orig_category":"Ropa Para Se\u00d1oras Y Caballeros (al Por Menor)",
    "sg:phone":"+34 935 87 97 10",
    "sg:postcode":"08172",
    "sg:province":"Barcelona",
    "wof:name":"Sabadell Vila Leonor",
    "wof:placetype":"venue"
},
  "geometry": {"coordinates":[2.0820820332,41.4728469849],"type":"Point"}
}