{
  "type": "Feature",
  "properties": {
    "addr:full":"Ctra. La Morera, Km. 0000,4 La Parra Badajoz 06176",
    "addr:postcode":"06176",
    "addr:street":"Ctra. La Morera Km. 0000,4",
    "iso:country":"ES",
    "sg:address":"Ctra. La Morera, Km. 0000,4",
    "sg:city":"La Parra",
    "sg:orig_category":"Maquinaria, Instalaci\u00d3n Y Equipo Para Garajes Y Estaciones De Servicio",
    "sg:phone":"+34 924 68 24 58",
    "sg:postcode":"06176",
    "sg:province":"Badajoz",
    "wof:name":"Seticel Y Servicios S.l.",
    "wof:placetype":"venue"
},
  "geometry": {"coordinates":[-6.6211590767,38.5236854553],"type":"Point"}
}