{
  "type": "Feature",
  "properties": {
    "addr:full":"Urba Montemar, 32 Montemar-la Vi\u00e7a Alicante 03720",
    "addr:housenumber":"urba;32",
    "addr:postcode":"03720",
    "addr:street":"Montemar",
    "iso:country":"ES",
    "sg:address":"Urba Montemar, 32",
    "sg:city":"Montemar-la Vi\u00e7a",
    "sg:orig_category":"Supermercados Y Hipermercados",
    "sg:phone":"+34 965 74 74 41",
    "sg:postcode":"03720",
    "sg:province":"Alicante",
    "wof:name":"Daynes  Allen Justin",
    "wof:placetype":"venue"
},
  "geometry": {"coordinates":[0.0773060024,38.6906890869],"type":"Point"}
}