{
  "type": "Feature",
  "properties": {
    "iso:country":"ES",
    "sg:address":"Calle de Bolulla, 7",
    "sg:city":"Alacant",
    "sg:orig_category":"Lencer\u00cda Femenina, Corseter\u00cda, Trajes De Ba\u00d1o (al Por Menor)",
    "sg:phone":"+34 965 18 22 33",
    "sg:postcode":"03009",
    "sg:province":"Alicante",
    "wof:name":"Comercial Distribuidora Textil Coditex S.l.",
    "wof:placetype":"venue"
},
  "geometry": {"coordinates":[-0.5026009083,38.3765716553],"type":"Point"}
}