{
  "type": "Feature",
  "properties": {
    "iso:country":"ES",
    "sg:address":"Manuel De Falla, 15",
    "sg:city":"Iru\u00f1a",
    "sg:orig_category":"Maquinaria Para Industrias Diversas",
    "sg:phone":"+34 948 23 91 93",
    "sg:postcode":"31005",
    "sg:province":"Navarra",
    "wof:name":"Navarra Comercial Bs S.l.",
    "wof:placetype":"venue"
},
  "geometry": {"coordinates":[-1.6422059536,42.8048248291],"type":"Point"}
}