{
  "type": "Feature",
  "properties": {
    "iso:country":"ES",
    "sg:address":"Calle de Ancha, 8",
    "sg:city":"Motril",
    "sg:orig_category":"Bancos",
    "sg:phone":"+34 958 83 48 62",
    "sg:postcode":"18600",
    "sg:province":"Granada",
    "sg:website":"www.ruralvia.es",
    "wof:name":"Caja Rural De Granada",
    "wof:placetype":"venue"
},
  "geometry": {"coordinates":[-3.5149297714,36.7521400452],"type":"Point"}
}