{
  "type": "Feature",
  "properties": {
    "addr:full":"Calle de Cascajera, 3 Castronu\u00f1o Valladolid 47520",
    "addr:housenumber":"3",
    "addr:postcode":"47520",
    "addr:street":"Calle De Cascajera",
    "iso:country":"ES",
    "sg:address":"Calle de Cascajera, 3",
    "sg:city":"Castronu\u00f1o",
    "sg:orig_category":"Transportes Por V\u00cdas Navegables",
    "sg:phone":"+34 983 86 62 34",
    "sg:postcode":"47520",
    "sg:province":"Valladolid",
    "wof:name":"Maestre Hernandez Antonio",
    "wof:placetype":"venue"
},
  "geometry": {"coordinates":[-5.267457962,41.3864555359],"type":"Point"}
}