{
  "type": "Feature",
  "properties": {
    "addr:full":"Calle de Arrabalejo, 55 Baena C\u00f3rdoba 14850",
    "addr:housenumber":"55",
    "addr:postcode":"14850",
    "addr:street":"Calle De Arrabalejo",
    "iso:country":"ES",
    "sg:address":"Calle de Arrabalejo, 55",
    "sg:city":"Baena",
    "sg:orig_category":"Alimentaci\u00d3n General (al Por Menor)",
    "sg:phone":"+34 957 67 02 40",
    "sg:postcode":"14850",
    "sg:province":"C\u00f3rdoba",
    "wof:name":"Morenas Arjona Jose De Las",
    "wof:placetype":"venue"
},
  "geometry": {"coordinates":[-4.3242125511,37.6125984192],"type":"Point"}
}