{
  "type": "Feature",
  "properties": {
    "addr:full":"Carrer de Sant Bartomeu, 122 Campello Alicante 03560",
    "addr:housenumber":"122",
    "addr:postcode":"03560",
    "addr:street":"Carrer De Sant Bartomeu",
    "iso:country":"ES",
    "sg:address":"Carrer de Sant Bartomeu, 122",
    "sg:city":"Campello",
    "sg:orig_category":"Peluquer\u00cdas, Peluquer\u00cda Mixta",
    "sg:phone":"+34 965 63 35 76",
    "sg:postcode":"03560",
    "sg:province":"Alicante",
    "wof:name":"Hermanos Llorca Ruzafa C.b.",
    "wof:placetype":"venue"
},
  "geometry": {"coordinates":[-0.3895379901,38.4290084839],"type":"Point"}
}