{
  "type": "Feature",
  "properties": {
    "iso:country":"ES",
    "sg:address":"Avda Espa\u00d1a, 17",
    "sg:city":"Albacete",
    "sg:orig_category":"Cr\u00cda De Animales",
    "sg:phone":"+34 967 22 25 45",
    "sg:postcode":"02002",
    "sg:province":"Albacete",
    "wof:name":"Agropecuaria Albacete S.l.",
    "wof:placetype":"venue"
},
  "geometry": {"coordinates":[-1.85698,38.993214],"type":"Point"}
}