{
  "type": "Feature",
  "properties": {
    "addr:full":"Calle de Asin Y Palacios, 11 Zaragoza Zaragoza 50009",
    "addr:housenumber":"11",
    "addr:postcode":"50009",
    "addr:street":"Calle De Asin Y Palacios",
    "iso:country":"ES",
    "sg:address":"Calle de Asin Y Palacios, 11",
    "sg:city":"Zaragoza",
    "sg:orig_category":"Molduras, Junquillos, Listones Y Molduras Perforadas",
    "sg:phone":"+34 976 35 46 24",
    "sg:postcode":"50009",
    "sg:province":"Zaragoza",
    "wof:name":"Segura Val German",
    "wof:placetype":"venue"
},
  "geometry": {"coordinates":[-0.9039310217,41.6376113892],"type":"Point"}
}