{
  "type": "Feature",
  "properties": {
    "addr:full":"Calle de Sagasta, 9 Sevilla Sevilla 41004",
    "addr:housenumber":"9",
    "addr:postcode":"41004",
    "addr:street":"Calle De Sagasta",
    "iso:country":"ES",
    "sg:address":"Calle de Sagasta, 9",
    "sg:city":"Sevilla",
    "sg:orig_category":"Cajas De Ahorro",
    "sg:phone":"+34 954 21 74 33",
    "sg:postcode":"41004",
    "sg:province":"Sevilla",
    "wof:name":"Caja De Ahorros Y Monte De Piedad De Cordoba",
    "wof:placetype":"venue"
},
  "geometry": {"coordinates":[-5.9938797951,37.3900642395],"type":"Point"}
}