{
  "type": "Feature",
  "properties": {
    "iso:country":"ES",
    "sg:address":"Calle de Nueva, 88",
    "sg:city":"Puente-genil",
    "sg:orig_category":"Molduras, Junquillos, Listones Y Molduras Perforadas",
    "sg:phone":"+34 957 60 10 37",
    "sg:postcode":"14500",
    "sg:province":"C\u00f3rdoba",
    "wof:name":"Aguilar Morillo Domingo",
    "wof:placetype":"venue"
},
  "geometry": {"coordinates":[-4.7809176445,37.3828697205],"type":"Point"}
}