{
  "type": "Feature",
  "properties": {
    "addr:full":"Trav De Gracia, 38 Barcelona Barcelona 08021",
    "addr:housenumber":"38",
    "addr:postcode":"08021",
    "addr:street":"Trav De Gracia",
    "iso:country":"ES",
    "sg:address":"Trav De Gracia, 38",
    "sg:city":"Barcelona",
    "sg:orig_category":"Complementos De Vestir (al Por Menor)",
    "sg:phone":"+34 932 09 23 08",
    "sg:postcode":"08021",
    "sg:province":"Barcelona",
    "wof:name":"Nikias Sl",
    "wof:placetype":"venue"
},
  "geometry": {"coordinates":[2.1482949257,41.3951911926],"type":"Point"}
}