{
  "type": "Feature",
  "properties": {
    "addr:full":"Avda Nuestra Se\u00d1ora De Montserrat, 16 Almeria Almer\u00eda 04006",
    "addr:housenumber":"16",
    "addr:postcode":"04006",
    "addr:street":"Avda Nuestra Sen\u0303Ora De Montserrat",
    "iso:country":"ES",
    "sg:address":"Avda Nuestra Se\u00d1ora De Montserrat, 16",
    "sg:city":"Almeria",
    "sg:orig_category":"Organismos De Reclutamiento",
    "sg:phone":"+34 950 26 42 53",
    "sg:postcode":"04006",
    "sg:province":"Almer\u00eda",
    "wof:name":"Innovacion Humana Consultores Y Asociados S.l",
    "wof:placetype":"venue"
},
  "geometry": {"coordinates":[-2.4553439617,36.8366737366],"type":"Point"}
}