{
  "type": "Feature",
  "properties": {
    "addr:full":"Carretera, S/n Ventas Zafarraya Granada 18128",
    "addr:postcode":"18128",
    "addr:street":"Carretera S / N",
    "iso:country":"ES",
    "sg:address":"Carretera, S/n",
    "sg:city":"Ventas Zafarraya",
    "sg:orig_category":"Frutas Y Legumbres Frescas (al Por Mayor)",
    "sg:phone":"+34 958 34 12 72",
    "sg:postcode":"18128",
    "sg:province":"Granada",
    "wof:name":"Moreno Moreno Juan Antonio",
    "wof:placetype":"venue"
},
  "geometry": {"coordinates":[-4.1472039223,36.9733467102],"type":"Point"}
}