{
  "type": "Feature",
  "properties": {
    "addr:full":"Calle de Pereda, 15 Le\u00f3n Le\u00f3n 24006",
    "addr:housenumber":"15",
    "addr:postcode":"24006",
    "addr:street":"Calle De Pereda;Leo\u0301N",
    "iso:country":"ES",
    "sg:address":"Calle de Pereda, 15",
    "sg:city":"Le\u00f3n",
    "sg:orig_category":"Arreglo, Reparaci\u00d3n, Piezas Sueltas De Televisi\u00d3n, V\u00cddeo, Hi",
    "sg:phone":"+34 987 25 99 53",
    "sg:postcode":"24006",
    "sg:province":"Le\u00f3n",
    "wof:name":"Jimeno Perez Jose Antonio",
    "wof:placetype":"venue"
},
  "geometry": {"coordinates":[-5.5617117882,42.5915641785],"type":"Point"}
}