{
  "type": "Feature",
  "properties": {
    "iso:country":"ES",
    "sg:address":"Carrer de Ramon Y Cajal, 36",
    "sg:city":"Barcelona",
    "sg:orig_category":"Confiter\u00cdas, Chocolater\u00cdas (al Por Menor)",
    "sg:phone":"+34 932 85 14 76",
    "sg:postcode":"08012",
    "sg:province":"Barcelona",
    "wof:name":"Ruyun Levens S.l.",
    "wof:placetype":"venue"
},
  "geometry": {"coordinates":[2.1588869095,41.4025840759],"type":"Point"}
}