{
  "type": "Feature",
  "properties": {
    "iso:country":"ES",
    "sg:address":"Calle de Montejurra, 25",
    "sg:city":"Madrid",
    "sg:orig_category":"Caf\u00c9s, Bares, Cervecer\u00cdas",
    "sg:phone":"+34 914 05 24 14",
    "sg:postcode":"28017",
    "sg:province":"Madrid",
    "wof:name":"Ranero Fernandez Pedro",
    "wof:placetype":"venue"
},
  "geometry": {"coordinates":[-3.6563460827,40.4251976013],"type":"Point"}
}