{
  "type": "Feature",
  "properties": {
    "iso:country":"ES",
    "sg:address":"Carrer de Sant Agusti, 16",
    "sg:city":"Alcanar",
    "sg:orig_category":"Peluquer\u00cdas, Peluquer\u00cda Mixta",
    "sg:phone":"+34 977 73 17 06",
    "sg:postcode":"43530",
    "sg:province":"Tarragona",
    "wof:name":"Cruselles Barrera Anna",
    "wof:placetype":"venue"
},
  "geometry": {"coordinates":[0.4794090092,40.5452270508],"type":"Point"}
}