{
  "type": "Feature",
  "properties": {
    "addr:full":"Sta. Mari\u00f1a, 36 Cabreiros Lugo 27163",
    "addr:housenumber":"36",
    "addr:postcode":"27163",
    "addr:street":"Marin\u0303A",
    "iso:country":"ES",
    "sg:address":"Sta. Mari\u00f1a, 36",
    "sg:city":"Cabreiros",
    "sg:orig_category":"M\u00c9dicos: Pediatr\u00cda. Enfermedades De Los Ni\u00d1os",
    "sg:phone":"+34 982 30 04 24",
    "sg:postcode":"27163",
    "sg:province":"Lugo",
    "wof:name":"Morales Redondo Ramon",
    "wof:placetype":"venue"
},
  "geometry": {"coordinates":[-7.4650249481,42.9521522522],"type":"Point"}
}