{
  "type": "Feature",
  "properties": {
    "iso:country":"ES",
    "sg:address":"Calle de Rioja, 1",
    "sg:city":"Benidorm",
    "sg:orig_category":"Doctores En Medicina",
    "sg:phone":"+34 965 86 07 49",
    "sg:postcode":"03500",
    "sg:province":"Alicante",
    "wof:name":"Pastor Del Pozo Rafael Nicolas",
    "wof:placetype":"venue"
},
  "geometry": {"coordinates":[-0.1295659989,38.5379943848],"type":"Point"}
}