{
  "type": "Feature",
  "properties": {
    "addr:full":"Avda El Ferial, 63 Benavente Zamora 49600",
    "addr:housenumber":"63",
    "addr:postcode":"49600",
    "addr:street":"Avda El Ferial",
    "iso:country":"ES",
    "sg:address":"Avda El Ferial, 63",
    "sg:city":"Benavente",
    "sg:orig_category":"Producci\u00d3n, Comercio De Cereales",
    "sg:phone":"+34 980 63 78 46",
    "sg:postcode":"49600",
    "sg:province":"Zamora",
    "wof:name":"Geras Cereales S.l.",
    "wof:placetype":"venue"
},
  "geometry": {"coordinates":[-5.6773190498,41.9971694946],"type":"Point"}
}