{
  "type": "Feature",
  "properties": {
    "iso:country":"ES",
    "sg:address":"Goiburu, Barrio, 11",
    "sg:city":"Urnieta",
    "sg:orig_category":"Molduras, Junquillos, Listones Y Molduras Perforadas",
    "sg:phone":"+34 943 33 42 41",
    "sg:postcode":"20130",
    "sg:province":"Guip\u00f9zcoa",
    "wof:name":"Ochotorena Oyarbide Victor",
    "wof:placetype":"venue"
},
  "geometry": {"coordinates":[-1.9588739872,43.2261962891],"type":"Point"}
}