{
  "type": "Feature",
  "properties": {
    "iso:country":"ES",
    "sg:address":"S. Grazalema (p I La Gangosa), S/n",
    "sg:city":"Parador Hortichuelas",
    "sg:orig_category":"Equipo De Refrigeraci\u00d3n Industrial",
    "sg:phone":"+34 950 34 96 78",
    "sg:postcode":"04720",
    "sg:province":"Almer\u00eda",
    "wof:name":"Indafret S.l.",
    "wof:placetype":"venue"
},
  "geometry": {"coordinates":[-2.4679217339,36.8401641846],"type":"Point"}
}