{
  "type": "Feature",
  "properties": {
    "iso:country":"ES",
    "sg:address":"Calle de Imperial, 89",
    "sg:city":"Madrid",
    "sg:orig_category":"Cl\u00cdnicas M\u00c9dicas",
    "sg:phone":"+34 914 35 74 18",
    "sg:postcode":"28012",
    "sg:province":"Madrid",
    "wof:name":"Clinica Trauma S.l.",
    "wof:placetype":"venue"
},
  "geometry": {"coordinates":[-3.7071990967,40.414390564],"type":"Point"}
}