{
  "type": "Feature",
  "properties": {
    "addr:full":"Calle de Isla La, 3 Pola De Siero Asturias 33510",
    "addr:postcode":"33510",
    "addr:street":"Calle De Isla La 3",
    "iso:country":"ES",
    "sg:address":"Calle de Isla La, 3",
    "sg:city":"Pola De Siero",
    "sg:orig_category":"Fabricaci\u00d3n De Sobres, Bolsas Y Fundas",
    "sg:phone":"+34 985 72 47 45",
    "sg:postcode":"33510",
    "sg:province":"Asturias",
    "wof:name":"Canteli Cueto Cristina",
    "wof:placetype":"venue"
},
  "geometry": {"coordinates":[-5.6648221016,43.3890991211],"type":"Point"}
}