{
  "type": "Feature",
  "properties": {
    "addr:full":"Teide, 7 S Sebasti\u00e1n Reyes Madrid 28700",
    "addr:housenumber":"7",
    "addr:postcode":"28700",
    "addr:street":"Teide;S Sebastia\u0301N Reyes",
    "iso:country":"ES",
    "sg:address":"Teide, 7",
    "sg:city":"S Sebasti\u00e1n Reyes",
    "sg:orig_category":"Marketing Directo",
    "sg:phone":"+34 902 21 10 10",
    "sg:postcode":"28700",
    "sg:province":"Madrid",
    "wof:name":"Agm Contacta S.l.",
    "wof:placetype":"venue"
},
  "geometry": {"coordinates":[-3.6193680763,40.5552787781],"type":"Point"}
}