{
  "type": "Feature",
  "properties": {
    "iso:country":"ES",
    "sg:address":"Calle de Fernando Moline, 45",
    "sg:city":"Puebla Alfinden",
    "sg:orig_category":"Hoteles",
    "sg:phone":"+34 976 10 80 22",
    "sg:postcode":"50171",
    "sg:province":"Zaragoza",
    "wof:name":"Gasca Hernando S.l.",
    "wof:placetype":"venue"
},
  "geometry": {"coordinates":[-0.7549650073,41.6321334839],"type":"Point"}
}