{
  "type": "Feature",
  "properties": {
    "addr:full":"Carrer de Baro S M Sepulcre, 9 Palma Islas Baleares 07012",
    "addr:housenumber":"9",
    "addr:postcode":"07012",
    "addr:street":"Carrer De Baro S;Sepulcre",
    "iso:country":"ES",
    "sg:address":"Carrer de Baro S M Sepulcre, 9",
    "sg:city":"Palma",
    "sg:orig_category":"Peluqueros: De Se\u00d1oras",
    "sg:phone":"+34 971 72 63 03",
    "sg:postcode":"07012",
    "sg:province":"Islas Baleares",
    "wof:name":"Llabres Mieras Francisca",
    "wof:placetype":"venue"
},
  "geometry": {"coordinates":[2.6440999508,39.5733642578],"type":"Point"}
}