{
  "type": "Feature",
  "properties": {
    "iso:country":"ES",
    "sg:address":"Foruen Plaza, 2",
    "sg:city":"Elgoibar",
    "sg:orig_category":"Iglesia Cat\u00d3lica",
    "sg:phone":"+34 943 74 08 42",
    "sg:postcode":"20870",
    "sg:province":"Guip\u00f9zcoa",
    "wof:name":"Parroquia De San Bartolome",
    "wof:placetype":"venue"
},
  "geometry": {"coordinates":[-2.4168519974,43.2144203186],"type":"Point"}
}