{
  "type": "Feature",
  "properties": {
    "addr:full":"Plaz Cruz (de La), 5 Boadilla Del Monte Madrid 28660",
    "addr:housenumber":"5",
    "addr:postcode":"28660",
    "addr:street":"Plaz Cruz De La",
    "iso:country":"ES",
    "sg:address":"Plaz Cruz (de La), 5",
    "sg:city":"Boadilla Del Monte",
    "sg:orig_category":"Caf\u00c9s, Bares, Cervecer\u00cdas",
    "sg:phone":"+34 916 32 07 28",
    "sg:postcode":"28660",
    "sg:province":"Madrid",
    "wof:name":"Martin Nu\u00f1ez Concepcion",
    "wof:placetype":"venue"
},
  "geometry": {"coordinates":[-3.8742079735,40.4075012207],"type":"Point"}
}