{
  "type": "Feature",
  "properties": {
    "addr:full":"Plaz Reyes Catolicos, 15 Ba\u00d1eza Le\u00f3n 24750",
    "addr:housenumber":"15",
    "addr:postcode":"24750",
    "addr:street":"Plaz Reyes Catolicos;Leo\u0301N",
    "iso:country":"ES",
    "sg:address":"Plaz Reyes Catolicos, 15",
    "sg:city":"Ba\u00d1eza",
    "sg:orig_category":"Frutas Y Legumbres Frescas (al Por Mayor)",
    "sg:phone":"+34 987 65 56 40",
    "sg:postcode":"24750",
    "sg:province":"Le\u00f3n",
    "wof:name":"Martinez Sanchez Valentin",
    "wof:placetype":"venue"
},
  "geometry": {"coordinates":[-5.5717520714,42.5998764038],"type":"Point"}
}