{
  "type": "Feature",
  "properties": {
    "addr:full":"Calle de Martinez Monta\u00d1es, 48 Santiponce Sevilla 41970",
    "addr:housenumber":"48",
    "addr:postcode":"41970",
    "addr:street":"Calle De Martinez Montan\u0303Es",
    "iso:country":"ES",
    "sg:address":"Calle de Martinez Monta\u00d1es, 48",
    "sg:city":"Santiponce",
    "sg:orig_category":"Venta, Montaje De Neum\u00c1ticos",
    "sg:phone":"+34 955 99 81 37",
    "sg:postcode":"41970",
    "sg:province":"Sevilla",
    "wof:name":"Pantoja Mesa Maria Carmen",
    "wof:placetype":"venue"
},
  "geometry": {"coordinates":[-6.0443181992,37.4311218262],"type":"Point"}
}