{
  "type": "Feature",
  "properties": {
    "iso:country":"ES",
    "sg:address":"Calle de Santiago, 24",
    "sg:city":"Aranda Duero",
    "sg:orig_category":"Comercio De Piezas De Recambio Y De Accesorios De Veh\u00cdculos, Veh\u00cdculos Industriales",
    "sg:phone":"+34 947 50 15 90",
    "sg:postcode":"09400",
    "sg:province":"Burgos",
    "wof:name":"Blanco Lopez Eloy",
    "wof:placetype":"venue"
},
  "geometry": {"coordinates":[-3.6784389019,41.6725082397],"type":"Point"}
}