{
  "type": "Feature",
  "properties": {
    "addr:full":"Avda Moratalaz, 139 Madrid Madrid 28030",
    "addr:housenumber":"139",
    "addr:postcode":"28030",
    "addr:street":"Avda Moratalaz",
    "iso:country":"ES",
    "sg:address":"Avda Moratalaz, 139",
    "sg:city":"Madrid",
    "sg:orig_category":"Periodistas Profesionales",
    "sg:phone":"+34 914 39 09 61",
    "sg:postcode":"28030",
    "sg:province":"Madrid",
    "wof:name":"Senante Lamaignese Maria Josefa",
    "wof:placetype":"venue"
},
  "geometry": {"coordinates":[-3.6491110325,40.4066810608],"type":"Point"}
}