{
  "type": "Feature",
  "properties": {
    "addr:full":"Calle de Miguel Hernandez, 2 Arnedo La Rioja 26580",
    "addr:housenumber":"2",
    "addr:postcode":"26580",
    "addr:street":"Calle De Miguel Hernandez;Rioja",
    "iso:country":"ES",
    "sg:address":"Calle de Miguel Hernandez, 2",
    "sg:city":"Arnedo",
    "sg:orig_category":"Centros Empresariales",
    "sg:phone":"+34 941 38 31 50",
    "sg:postcode":"26580",
    "sg:province":"La Rioja",
    "wof:name":"Comunidad De Propietarios Miguel Hernandez 2",
    "wof:placetype":"venue"
},
  "geometry": {"coordinates":[-2.1020009518,42.2235908508],"type":"Point"}
}