{
  "type": "Feature",
  "properties": {
    "addr:full":"Calle de Oviedo, 22 Humanes De Madrid Madrid 28970",
    "addr:housenumber":"22",
    "addr:postcode":"28970",
    "addr:street":"Calle De Oviedo",
    "iso:country":"ES",
    "sg:address":"Calle de Oviedo, 22",
    "sg:city":"Humanes De Madrid",
    "sg:orig_category":"Inform\u00c1tica (estudios, Servicios, Asesor\u00cda, Formaci\u00d3n)",
    "sg:phone":"+34 914 92 03 03",
    "sg:postcode":"28970",
    "sg:province":"Madrid",
    "wof:name":"Informatica Empresarial Sangom S.l.",
    "wof:placetype":"venue"
},
  "geometry": {"coordinates":[-3.8254299164,40.2715148926],"type":"Point"}
}