{
  "type": "Feature",
  "properties": {
    "addr:full":"Calle de Diego Maria Crehuet, 24 Caceres C\u00e1ceres 10004",
    "addr:housenumber":"24",
    "addr:postcode":"10004",
    "addr:street":"Calle De Diego Maria Crehuet;Ca\u0301Ceres",
    "iso:country":"ES",
    "sg:address":"Calle de Diego Maria Crehuet, 24",
    "sg:city":"Caceres",
    "sg:orig_category":"Asociaciones, Instituciones De Consumidores Y Usuarios",
    "sg:phone":"+34 927 22 64 82",
    "sg:postcode":"10004",
    "sg:province":"C\u00e1ceres",
    "wof:name":"Asociacion De Consumidores Y Usuarios De Extremadura",
    "wof:placetype":"venue"
},
  "geometry": {"coordinates":[-6.3742880821,39.4707794189],"type":"Point"}
}