{
  "type": "Feature",
  "properties": {
    "iso:country":"ES",
    "sg:address":"Avda Madrid, 70",
    "sg:city":"Don Benito",
    "sg:orig_category":"Granos Y Semillas (producci\u00d3n, Al Por Mayor)",
    "sg:phone":"+34 924 80 46 51",
    "sg:postcode":"06400",
    "sg:province":"Badajoz",
    "wof:name":"Carabias S.a.",
    "wof:placetype":"venue"
},
  "geometry": {"coordinates":[-5.8557801247,38.965587616],"type":"Point"}
}