{
  "type": "Feature",
  "properties": {
    "iso:country":"ES",
    "sg:address":"Plaz Iglesia Horno De Alcedo, 12",
    "sg:city":"Horno De Alcedo",
    "sg:orig_category":"Iglesia Cat\u00d3lica",
    "sg:phone":"+34 963 76 50 37",
    "sg:postcode":"46026",
    "sg:province":"Valencia",
    "wof:name":"Parroquia Santisimo Cristo De La Agonia",
    "wof:placetype":"venue"
},
  "geometry": {"coordinates":[-0.3768819869,39.4323883057],"type":"Point"}
}