{
  "type": "Feature",
  "properties": {
    "addr:full":"Calle de Tomas Gonzalez Rivero, 6 Tejina Santa Cruz De Tenerife 38260",
    "addr:housenumber":"6",
    "addr:postcode":"38260",
    "addr:street":"Calle De Tomas Gonzalez Rivero",
    "iso:country":"ES",
    "sg:address":"Calle de Tomas Gonzalez Rivero, 6",
    "sg:city":"Tejina",
    "sg:orig_category":"Estudios Y Construcci\u00d3n De Acuarios Y Viveros",
    "sg:phone":"+34 922 54 00 05",
    "sg:postcode":"38260",
    "sg:province":"Santa Cruz De Tenerife",
    "wof:name":"Rodriguez De La Cruz Segundo",
    "wof:placetype":"venue"
},
  "geometry": {"coordinates":[-16.3607273102,28.5338802338],"type":"Point"}
}