{
  "type": "Feature",
  "properties": {
    "iso:country":"ES",
    "sg:address":"Avgd Constitucion, 2",
    "sg:city":"Betera",
    "sg:orig_category":"Vallados Y Barreras",
    "sg:phone":"+34 961 69 82 55",
    "sg:postcode":"46117",
    "sg:province":"Valencia",
    "wof:name":"Cumebet, S.l.u",
    "wof:placetype":"venue"
},
  "geometry": {"coordinates":[-0.4545669854,39.5895309448],"type":"Point"}
}