{
  "type": "Feature",
  "properties": {
    "iso:country":"ES",
    "sg:address":"Calle de Maria Auxiliadora, 3",
    "sg:city":"Almodovar Campo",
    "sg:orig_category":"Contenedores (mercanc\u00cdas)",
    "sg:phone":"+34 926 48 32 69",
    "sg:postcode":"13580",
    "sg:province":"Ciudad Real",
    "wof:name":"Martin Bermejo Maria Del Carmen",
    "wof:placetype":"venue"
},
  "geometry": {"coordinates":[-4.1688199043,38.712436676],"type":"Point"}
}