{
  "type": "Feature",
  "properties": {
    "iso:country":"ES",
    "sg:address":"Calle de Mayor, 19",
    "sg:city":"Zaragoza",
    "sg:orig_category":"Papeler\u00cdas, Librer\u00cdas",
    "sg:phone":"+34 976 29 84 66",
    "sg:postcode":"50001",
    "sg:province":"Zaragoza",
    "wof:name":"Almansa Mayolas Jose Andres",
    "wof:placetype":"venue"
},
  "geometry": {"coordinates":[-0.876963377,41.6538963318],"type":"Point"}
}