{
  "type": "Feature",
  "properties": {
    "iso:country":"ES",
    "sg:address":"Carrer de Marques De Comillas, 93",
    "sg:city":"Sabadell",
    "sg:orig_category":"Sales (al Por Mayor)",
    "sg:phone":"+34 937 45 93 34",
    "sg:postcode":"08202",
    "sg:province":"Barcelona",
    "wof:name":"Importacion Y Comercio Galo S.l.",
    "wof:placetype":"venue"
},
  "geometry": {"coordinates":[2.116494894,41.5446891785],"type":"Point"}
}