{
  "type": "Feature",
  "properties": {
    "iso:country":"ES",
    "sg:address":"Calle de Pedro Cabanes, 20",
    "sg:city":"Valencia",
    "sg:orig_category":"Farmacias",
    "sg:phone":"+34 963 65 36 31",
    "sg:postcode":"46019",
    "sg:province":"Valencia",
    "wof:name":"Garcia Contell-pons C.b.",
    "wof:placetype":"venue"
},
  "geometry": {"coordinates":[-0.3738079965,39.4953575134],"type":"Point"}
}