{
  "type": "Feature",
  "properties": {
    "addr:full":"Carrer de Navas, S/n S. Fruitos Bages Barcelona 08272",
    "addr:housenumber":"s",
    "addr:postcode":"08272",
    "addr:street":"Carrer De Navas;/ N S. Fruitos Bages Barcelona",
    "iso:country":"ES",
    "sg:address":"Carrer de Navas, S/n",
    "sg:city":"S. Fruitos Bages",
    "sg:orig_category":"Alquiler De Material Y De Programas Audiovisuales",
    "sg:phone":"+34 938 78 80 72",
    "sg:postcode":"08272",
    "sg:province":"Barcelona",
    "wof:name":"Graells So I Llums S.l.",
    "wof:placetype":"venue"
},
  "geometry": {"coordinates":[1.8745299578,41.7687149048],"type":"Point"}
}