{
  "type": "Feature",
  "properties": {
    "iso:country":"ES",
    "sg:address":"Carrer de Galio, 1",
    "sg:city":"Reus",
    "sg:orig_category":"Ropa Para Ni\u00d1os (al Por Menor)",
    "sg:phone":"+34 977 34 56 15",
    "sg:postcode":"43201",
    "sg:province":"Tarragona",
    "wof:name":"Tolran S.a.",
    "wof:placetype":"venue"
},
  "geometry": {"coordinates":[1.1079779863,41.1550445557],"type":"Point"}
}