{
  "type": "Feature",
  "properties": {
    "addr:full":"Carr Maria Sauret, 1 Lleida Lleida 25007",
    "addr:housenumber":"1",
    "addr:postcode":"25007",
    "addr:street":"Carr Maria Sauret",
    "iso:country":"ES",
    "sg:address":"Carr Maria Sauret, 1",
    "sg:city":"Lleida",
    "sg:orig_category":"Inform\u00c1tica (estudios, Servicios, Asesor\u00cda, Formaci\u00d3n)",
    "sg:phone":"+34 973 24 91 34",
    "sg:postcode":"25007",
    "sg:province":"Lleida",
    "wof:name":"Bosch Falco Pere",
    "wof:placetype":"venue"
},
  "geometry": {"coordinates":[0.6314820051,41.6171379089],"type":"Point"}
}