{
  "type": "Feature",
  "properties": {
    "addr:full":"Calle de Mayor, 12 Benabarre Huesca 22580",
    "addr:housenumber":"12",
    "addr:postcode":"22580",
    "addr:street":"Calle De Mayor",
    "iso:country":"ES",
    "sg:address":"Calle de Mayor, 12",
    "sg:city":"Benabarre",
    "sg:orig_category":"Alimentaci\u00d3n General (al Por Menor)",
    "sg:phone":"+34 974 54 30 15",
    "sg:postcode":"22580",
    "sg:province":"Huesca",
    "wof:name":"Latorre Sorigue Ramiro",
    "wof:placetype":"venue"
},
  "geometry": {"coordinates":[0.4802249968,42.1071968079],"type":"Point"}
}