{
  "type": "Feature",
  "properties": {
    "iso:country":"ES",
    "sg:address":"Calle de Santo Domingo, S/n",
    "sg:city":"Motril",
    "sg:orig_category":"Droguer\u00cdas (al Por Menor)",
    "sg:phone":"+34 958 83 48 61",
    "sg:postcode":"18600",
    "sg:province":"Granada",
    "wof:name":"Rabema S.l.",
    "wof:placetype":"venue"
},
  "geometry": {"coordinates":[-3.5198891163,36.7472648621],"type":"Point"}
}