{
  "type": "Feature",
  "properties": {
    "iso:country":"ES",
    "sg:address":"Calle de Doctor Manuel Candela, 65",
    "sg:city":"Valencia",
    "sg:orig_category":"Edici\u00d3n De Diarios, Revistas, Boletines",
    "sg:phone":"+34 963 89 05 00",
    "sg:postcode":"46021",
    "sg:province":"Valencia",
    "sg:website":"www.oup.com/es",
    "wof:name":"Oxford University Press Espa\u00f1a S.a.",
    "wof:placetype":"venue"
},
  "geometry": {"coordinates":[-0.3488439918,39.4717750549],"type":"Point"}
}