{
  "type": "Feature",
  "properties": {
    "addr:full":"Carrer de Antoni Maura, 5 Terrassa Barcelona 08225",
    "addr:housenumber":"5",
    "addr:postcode":"08225",
    "addr:street":"Carrer De Antoni Maura",
    "iso:country":"ES",
    "sg:address":"Carrer de Antoni Maura, 5",
    "sg:city":"Terrassa",
    "sg:orig_category":"Ense\u00d1anza: Profesiones Art\u00cdsticas",
    "sg:phone":"+34 937 80 93 17",
    "sg:postcode":"08225",
    "sg:province":"Barcelona",
    "wof:name":"Folch Casanova Montserrat",
    "wof:placetype":"venue"
},
  "geometry": {"coordinates":[2.0022211075,41.5717544556],"type":"Point"}
}