{
  "type": "Feature",
  "properties": {
    "addr:full":"Calle de Medea, 4 Madrid Madrid 28032",
    "addr:housenumber":"4",
    "addr:postcode":"28032",
    "addr:street":"Calle De Medea",
    "iso:country":"ES",
    "sg:address":"Calle de Medea, 4",
    "sg:city":"Madrid",
    "sg:orig_category":"Fabricaci\u00d3n De Art\u00cdculos Y Equipos Deportivos Y De Ocio",
    "sg:phone":"+34 913 75 03 73",
    "sg:postcode":"28032",
    "sg:province":"Madrid",
    "wof:name":"Productos Para Gente Deportiva Proged S.a.",
    "wof:placetype":"venue"
},
  "geometry": {"coordinates":[-3.6244060993,40.4396400452],"type":"Point"}
}