{
  "type": "Feature",
  "properties": {
    "addr:full":"Calle de Diecinueve De Julio, 10 Oviedo Asturias 33002",
    "addr:housenumber":"10",
    "addr:postcode":"33002",
    "addr:street":"Calle De Diecinueve De Julio",
    "iso:country":"ES",
    "sg:address":"Calle de Diecinueve De Julio, 10",
    "sg:city":"Oviedo",
    "sg:orig_category":"Sociedades, Compa\u00d1\u00cdas Aseguradoras",
    "sg:phone":"+34 985 20 44 41",
    "sg:postcode":"33002",
    "sg:province":"Asturias",
    "wof:name":"Palupri S.l.",
    "wof:placetype":"venue"
},
  "geometry": {"coordinates":[-5.8485445976,43.3636169434],"type":"Point"}
}