{
  "type": "Feature",
  "properties": {
    "addr:full":"Ctra Almarcha, S/n S. Clemente Cuenca 16600",
    "addr:housenumber":"s",
    "addr:postcode":"16600",
    "addr:street":"Ctra Almarcha;/ N S. Clemente Cuenca",
    "iso:country":"ES",
    "sg:address":"Ctra Almarcha, S/n",
    "sg:city":"S. Clemente",
    "sg:orig_category":"Mec\u00c1nico Del Autom\u00d3vil",
    "sg:phone":"+34 969 30 00 75",
    "sg:postcode":"16600",
    "sg:province":"Cuenca",
    "wof:name":"Talleres Belmar La Pe\u00f1a S.l:",
    "wof:placetype":"venue"
},
  "geometry": {"coordinates":[-2.4217588902,39.4065589905],"type":"Point"}
}