{
  "type": "Feature",
  "properties": {
    "addr:full":"Calle de San Martin, 16 Medina Campo Valladolid 47400",
    "addr:housenumber":"16",
    "addr:postcode":"47400",
    "addr:street":"Calle De San Martin",
    "iso:country":"ES",
    "sg:address":"Calle de San Martin, 16",
    "sg:city":"Medina Campo",
    "sg:orig_category":"Centros Empresariales",
    "sg:phone":"+34 983 83 73 31",
    "sg:postcode":"47400",
    "sg:province":"Valladolid",
    "wof:name":"Circulo De Progreso Medina Del Campo",
    "wof:placetype":"venue"
},
  "geometry": {"coordinates":[-4.917347908,41.3095436096],"type":"Point"}
}