{
  "type": "Feature",
  "properties": {
    "iso:country":"ES",
    "sg:address":"Calle de Higuera, 10",
    "sg:city":"Puebla Alfinden",
    "sg:orig_category":"Empresas De Carpinter\u00cda Met\u00c1lica",
    "sg:phone":"+34 976 45 54 13",
    "sg:postcode":"50171",
    "sg:province":"Zaragoza",
    "wof:name":"Tamel S.c.",
    "wof:placetype":"venue"
},
  "geometry": {"coordinates":[-0.7673540115,41.6446151733],"type":"Point"}
}