{
  "type": "Feature",
  "properties": {
    "addr:full":"Calle de Jesus, 26 Valencia Valencia 46007",
    "addr:housenumber":"26",
    "addr:postcode":"46007",
    "addr:street":"Calle De Jesus",
    "iso:country":"ES",
    "sg:address":"Calle de Jesus, 26",
    "sg:city":"Valencia",
    "sg:orig_category":"Droguer\u00cdas (al Por Menor)",
    "sg:phone":"+34 963 52 88 24",
    "sg:postcode":"46007",
    "sg:province":"Valencia",
    "wof:name":"Morell Llavata Antonio",
    "wof:placetype":"venue"
},
  "geometry": {"coordinates":[-0.382573992,39.4673805237],"type":"Point"}
}