{
  "type": "Feature",
  "properties": {
    "iso:country":"ES",
    "sg:address":"Ctra Perales-albares, Km. 0072,8",
    "sg:city":"Mondejar",
    "sg:orig_category":"Productos L\u00c1cteos Y Av\u00cdcolas (al Por Mayor)",
    "sg:phone":"+34 949 38 56 75",
    "sg:postcode":"19110",
    "sg:province":"Guadalajara",
    "wof:name":"Francisco De Lucas E Hijos S.a.",
    "wof:placetype":"venue"
},
  "geometry": {"coordinates":[-3.1068348885,40.3210334778],"type":"Point"}
}