{
  "type": "Feature",
  "properties": {
    "iso:country":"ES",
    "sg:address":"Calle de Alcala, S/n",
    "sg:city":"Ventorros De San Jose",
    "sg:orig_category":"Producci\u00d3n De Abonos Y De Fertilizantes",
    "sg:phone":"+34 958 31 50 58",
    "sg:postcode":"18311",
    "sg:province":"Granada",
    "wof:name":"Nogales Martin Jacinto",
    "wof:placetype":"venue"
},
  "geometry": {"coordinates":[-4.1497383118,37.2471351624],"type":"Point"}
}