{
  "type": "Feature",
  "properties": {
    "addr:full":"Plaz Conde De Colombi, 6 Alcala Guadaira Sevilla 41500",
    "addr:housenumber":"6",
    "addr:postcode":"41500",
    "iso:country":"ES",
    "sg:address":"Plaz Conde De Colombi, 6",
    "sg:city":"Alcala Guadaira",
    "sg:orig_category":"Contenedores (mercanc\u00cdas)",
    "sg:phone":"+34 955 61 11 17",
    "sg:postcode":"41500",
    "sg:province":"Sevilla",
    "wof:name":"Transportes Frigocongelados Maranata S.l.",
    "wof:placetype":"venue"
},
  "geometry": {"coordinates":[-5.8398590088,37.3383140564],"type":"Point"}
}