{
  "type": "Feature",
  "properties": {
    "iso:country":"ES",
    "sg:address":"Cami Can Basora, 5",
    "sg:city":"Tiana",
    "sg:orig_category":"Pintores",
    "sg:phone":"+34 934 65 02 82",
    "sg:postcode":"08391",
    "sg:province":"Barcelona",
    "wof:name":"Su\u00f1ol Mu\u00f1oz-ramos Alvaro",
    "wof:placetype":"venue"
},
  "geometry": {"coordinates":[2.2730150223,41.4738578796],"type":"Point"}
}