{
  "type": "Feature",
  "properties": {
    "iso:country":"ES",
    "sg:address":"Carrer de Mare De Deu De Nuria, 9",
    "sg:city":"Granollers",
    "sg:orig_category":"Lavado, Limpieza De Veh\u00cdculos",
    "sg:phone":"+34 938 70 48 97",
    "sg:postcode":"08401",
    "sg:province":"Barcelona",
    "wof:name":"Barbany Curniellas Francisco",
    "wof:placetype":"venue"
},
  "geometry": {"coordinates":[2.2849390507,41.6087875366],"type":"Point"}
}