{
  "type": "Feature",
  "properties": {
    "iso:country":"ES",
    "sg:address":"Plaz Mayor (guadiana), 5",
    "sg:city":"Guadiana Caudillo",
    "sg:orig_category":"Iglesia Cat\u00d3lica",
    "sg:phone":"+34 924 47 00 29",
    "sg:postcode":"06186",
    "sg:province":"Badajoz",
    "wof:name":"Parroquia De Nuestra Se\u00f1ora De La Soledad",
    "wof:placetype":"venue"
},
  "geometry": {"coordinates":[-6.6902589798,38.9282913208],"type":"Point"}
}