{
  "type": "Feature",
  "properties": {
    "addr:full":"Calle de Camino Viejo De Leganes, 142 Madrid Madrid 28025",
    "addr:housenumber":"142",
    "addr:postcode":"28025",
    "addr:street":"Calle De Camino Viejo De Leganes",
    "iso:country":"ES",
    "sg:address":"Calle de Camino Viejo De Leganes, 142",
    "sg:city":"Madrid",
    "sg:orig_category":"Comercio De Piezas De Recambio Y De Accesorios De Veh\u00cdculos, Veh\u00cdculos Industriales",
    "sg:phone":"+34 914 65 54 21",
    "sg:postcode":"28025",
    "sg:province":"Madrid",
    "wof:name":"Motor Diper S.l.",
    "wof:placetype":"venue"
},
  "geometry": {"coordinates":[-3.7310395241,40.3813285828],"type":"Point"}
}