{
  "type": "Feature",
  "properties": {
    "iso:country":"ES",
    "sg:address":"Calle de Nogal (el), 3",
    "sg:city":"Torrelodones",
    "sg:orig_category":"Inform\u00c1tica: Consultores",
    "sg:phone":"+34 918 59 62 64",
    "sg:postcode":"28250",
    "sg:province":"Madrid",
    "wof:name":"Bequest I & D S.l.",
    "wof:placetype":"venue"
},
  "geometry": {"coordinates":[-3.9311048985,40.5754737854],"type":"Point"}
}