{
  "type": "Feature",
  "properties": {
    "addr:full":"Calle de Ctra. Almaden, S/n Castilblanco De Los Arroyos Sevilla 41230",
    "addr:housenumber":"s / n",
    "addr:postcode":"41230",
    "addr:street":"Calle De Ctra. Almaden",
    "iso:country":"ES",
    "sg:address":"Calle de Ctra. Almaden, S/n",
    "sg:city":"Castilblanco De Los Arroyos",
    "sg:orig_category":"Electrodom\u00c9sticos (al Por Menor)",
    "sg:phone":"+34 955 95 21 97",
    "sg:postcode":"41230",
    "sg:province":"Sevilla",
    "wof:name":"Baserma S.a.",
    "wof:placetype":"venue"
},
  "geometry": {"coordinates":[-5.9854841232,37.6786766052],"type":"Point"}
}