{
  "type": "Feature",
  "properties": {
    "addr:full":"Carr Industria, 14 Borges Blanques Lleida 25400",
    "addr:housenumber":"14",
    "addr:postcode":"25400",
    "addr:street":"Carr Industria",
    "iso:country":"ES",
    "sg:address":"Carr Industria, 14",
    "sg:city":"Borges Blanques",
    "sg:orig_category":"Quincaller\u00cda (al Por Menor)",
    "sg:phone":"+34 973 14 04 34",
    "sg:postcode":"25400",
    "sg:province":"Lleida",
    "sg:website":"www.laclaud.es",
    "wof:name":"La Clau Del Confort S.l.",
    "wof:placetype":"venue"
},
  "geometry": {"coordinates":[0.8711360097,41.5198669434],"type":"Point"}
}