{
  "type": "Feature",
  "properties": {
    "iso:country":"ES",
    "sg:address":"Avda Juan Bautista Lafora, 3",
    "sg:city":"Alacant",
    "sg:orig_category":"Procuradores",
    "sg:phone":"+34 965 20 29 40",
    "sg:postcode":"03002",
    "sg:province":"Alicante",
    "wof:name":"Quesada Polo Jesus",
    "wof:placetype":"venue"
},
  "geometry": {"coordinates":[-0.4793789983,38.3450698853],"type":"Point"}
}