{
  "type": "Feature",
  "properties": {
    "iso:country":"ES",
    "sg:address":"Av. Del Istmo, S/n",
    "sg:city":"La Pared",
    "sg:orig_category":"Laboratorios Dentales",
    "sg:phone":"+34 928 54 90 06",
    "sg:postcode":"35627",
    "sg:province":"Las Palmas",
    "wof:name":"Laboratorio Dental Jourdant S.l.",
    "wof:placetype":"venue"
},
  "geometry": {"coordinates":[-14.2158041,28.2136192322],"type":"Point"}
}