{
  "type": "Feature",
  "properties": {
    "addr:full":"Avda Jose Antonio, 4 Pe\u00f1iscola Castell\u00f3n 12598",
    "addr:housenumber":"4",
    "addr:postcode":"12598",
    "addr:street":"Avda Jose Antonio;Castello\u0301N",
    "iso:country":"ES",
    "sg:address":"Avda Jose Antonio, 4",
    "sg:city":"Pe\u00f1iscola",
    "sg:orig_category":"Bisuter\u00cda, Joyer\u00cda, Relojer\u00cda (al Por Menor)",
    "sg:phone":"+34 964 48 91 46",
    "sg:postcode":"12598",
    "sg:province":"Castell\u00f3n",
    "wof:name":"Pi\u00f1ol Edo Josefa",
    "wof:placetype":"venue"
},
  "geometry": {"coordinates":[0.4024550021,40.3601646423],"type":"Point"}
}