{
  "type": "Feature",
  "properties": {
    "addr:full":"Avda Telares De Los, 17 Aviles Asturias 33401",
    "addr:housenumber":"17",
    "addr:postcode":"33401",
    "addr:street":"Avda Telares De Los",
    "iso:country":"ES",
    "sg:address":"Avda Telares De Los, 17",
    "sg:city":"Aviles",
    "sg:orig_category":"M\u00c9dicos: Oftalmolog\u00cda",
    "sg:phone":"+34 985 56 44 18",
    "sg:postcode":"33401",
    "sg:province":"Asturias",
    "wof:name":"Fernandez Ortiz Jesus",
    "wof:placetype":"venue"
},
  "geometry": {"coordinates":[-5.9232120514,43.5610466003],"type":"Point"}
}