{
  "type": "Feature",
  "properties": {
    "addr:full":"Calle de O\u00d1ate, 12 Madrid Madrid 28020",
    "addr:housenumber":"12",
    "addr:postcode":"madrid;28020",
    "addr:street":"Calle De On\u0303Ate",
    "iso:country":"ES",
    "sg:address":"Calle de O\u00d1ate, 12",
    "sg:city":"Madrid",
    "sg:orig_category":"Empresarios Y Productoras De Espect\u00c1culos",
    "sg:phone":"+34 915 71 89 44",
    "sg:postcode":"28020",
    "sg:province":"Madrid",
    "wof:name":"El Septimo Sello Records S.l.",
    "wof:placetype":"venue"
},
  "geometry": {"coordinates":[-3.6948649883,40.4632797241],"type":"Point"}
}