{
  "type": "Feature",
  "properties": {
    "addr:full":"Calle de Medico Manero Molla, 15 Alacant Alicante 03001",
    "addr:housenumber":"15",
    "addr:postcode":"03001",
    "addr:street":"Calle De Medico Manero Molla",
    "iso:country":"ES",
    "sg:address":"Calle de Medico Manero Molla, 15",
    "sg:city":"Alacant",
    "sg:orig_category":"M\u00c9dicos: Estomatolog\u00cda",
    "sg:phone":"+34 965 20 69 08",
    "sg:postcode":"03001",
    "sg:province":"Alicante",
    "wof:name":"Moscardo Blanco Vicente",
    "wof:placetype":"venue"
},
  "geometry": {"coordinates":[-0.4845179915,38.3437728882],"type":"Point"}
}