{
  "type": "Feature",
  "properties": {
    "addr:full":"Carr Sant Sebastia, 36 Girona Girona 17006",
    "addr:housenumber":"36",
    "addr:postcode":"17006",
    "addr:street":"Carr Sant Sebastia",
    "iso:country":"ES",
    "sg:address":"Carr Sant Sebastia, 36",
    "sg:city":"Girona",
    "sg:orig_category":"Farmacias",
    "sg:phone":"+34 972 24 03 90",
    "sg:postcode":"17006",
    "sg:province":"Girona",
    "wof:name":"Farmacia Badia C.b",
    "wof:placetype":"venue"
},
  "geometry": {"coordinates":[2.8068110943,41.9740905762],"type":"Point"}
}