{
  "type": "Feature",
  "properties": {
    "iso:country":"ES",
    "sg:address":"Urb Valles (los), 6",
    "sg:city":"Collado Villalba",
    "sg:orig_category":"Bares, Piano",
    "sg:phone":"+34 918 49 93 33",
    "sg:postcode":"28400",
    "sg:province":"Madrid",
    "wof:name":"Juarez Manzano Jose Luis",
    "wof:placetype":"venue"
},
  "geometry": {"coordinates":[-4.0064492226,40.6153297424],"type":"Point"}
}