{
  "type": "Feature",
  "properties": {
    "iso:country":"ES",
    "sg:address":"Trva San Francisco, 8",
    "sg:city":"Calatayud",
    "sg:orig_category":"Empresas De Pintura Y Revestimientos",
    "sg:phone":"+34 976 88 55 97",
    "sg:postcode":"50300",
    "sg:province":"Zaragoza",
    "wof:name":"Pinturas Y Decoracion Servicolor S.l.",
    "wof:placetype":"venue"
},
  "geometry": {"coordinates":[-1.6409169436,41.3531303406],"type":"Point"}
}