{
  "type": "Feature",
  "properties": {
    "iso:country":"ES",
    "sg:address":"Calle de Arturo Soria, 126",
    "sg:city":"Madrid",
    "sg:orig_category":"Inversiones",
    "sg:phone":"+34 913 88 21 60",
    "sg:postcode":"28043",
    "sg:province":"Madrid",
    "wof:name":"Folli Follie Spain S.a.",
    "wof:placetype":"venue"
},
  "geometry": {"coordinates":[-3.6510543823,40.4495353699],"type":"Point"}
}