{
  "type": "Feature",
  "properties": {
    "iso:country":"ES",
    "sg:address":"Calle de Pedro Monedero, S/n",
    "sg:city":"Cevico De La Torre",
    "sg:orig_category":"Fabricaci\u00d3n De Quesos",
    "sg:phone":"+34 979 78 30 15",
    "sg:postcode":"34218",
    "sg:province":"Palencia",
    "wof:name":"Crego Hoyos Maria Del Carmen",
    "wof:placetype":"venue"
},
  "geometry": {"coordinates":[-4.4114642143,41.852355957],"type":"Point"}
}