{
  "type": "Feature",
  "properties": {
    "addr:full":"Calle de Llamaquique, 2 Oviedo Asturias 33005",
    "addr:housenumber":"2",
    "addr:postcode":"33005",
    "addr:street":"Calle De Llamaquique",
    "iso:country":"ES",
    "sg:address":"Calle de Llamaquique, 2",
    "sg:city":"Oviedo",
    "sg:orig_category":"Panader\u00cdas, Panader\u00cdas",
    "sg:phone":"+34 985 27 77 99",
    "sg:postcode":"33005",
    "sg:province":"Asturias",
    "wof:name":"Roales Iglesias Marciana",
    "wof:placetype":"venue"
},
  "geometry": {"coordinates":[-5.8525657654,43.3581390381],"type":"Point"}
}