{
  "type": "Feature",
  "properties": {
    "addr:full":"Plaz Venerables, 8 Sevilla Sevilla 41004",
    "addr:housenumber":"8",
    "addr:postcode":"41004",
    "addr:street":"Plaz Venerables",
    "iso:country":"ES",
    "sg:address":"Plaz Venerables, 8",
    "sg:city":"Sevilla",
    "sg:orig_category":"Asociaciones, Organismos Culturales Y Socioeducativos",
    "sg:phone":"+34 954 56 26 96",
    "sg:postcode":"41004",
    "sg:province":"Sevilla",
    "sg:website":"www.focus.abengoa.es",
    "wof:name":"Fundacion Foco De Cultura De Sevilla",
    "wof:placetype":"venue"
},
  "geometry": {"coordinates":[-5.9896941185,37.3850631714],"type":"Point"}
}