{
  "type": "Feature",
  "properties": {
    "iso:country":"ES",
    "sg:address":"Plaz Padre Juan De Mariana, 7",
    "sg:city":"Toledo",
    "sg:orig_category":"Aer\u00d3grafo",
    "sg:phone":"+34 925 21 19 98",
    "sg:postcode":"45002",
    "sg:province":"Toledo",
    "wof:name":"Martin Valenciano Fernando 000680010s S.l.n.e.",
    "wof:placetype":"venue"
},
  "geometry": {"coordinates":[-4.0259141922,39.8581237793],"type":"Point"}
}