{
  "type": "Feature",
  "properties": {
    "addr:full":"Ctra Palma Del Rio (villarrubia), Km. 0013,7 Villarrubia C\u00f3rdoba 14710",
    "addr:postcode":"14710",
    "addr:street":"Ctra Palma Del Rio Villarrubia Km. 0013,7 Villarrubia Co\u0301Rdoba",
    "iso:country":"ES",
    "sg:address":"Ctra Palma Del Rio (villarrubia), Km. 0013,7",
    "sg:city":"Villarrubia",
    "sg:orig_category":"Abogados",
    "sg:phone":"+34 957 32 76 04",
    "sg:postcode":"14710",
    "sg:province":"C\u00f3rdoba",
    "wof:name":"Galan Moreno Inmaculada",
    "wof:placetype":"venue"
},
  "geometry": {"coordinates":[-4.9000496864,37.8542518616],"type":"Point"}
}