{
  "type": "Feature",
  "properties": {
    "iso:country":"ES",
    "sg:address":"Av Verge Montserrat, 43",
    "sg:city":"Prat Llobregat",
    "sg:orig_category":"Cl\u00cdnicas Dentales",
    "sg:phone":"+34 934 78 65 88",
    "sg:postcode":"08820",
    "sg:province":"Barcelona",
    "wof:name":"Instituto De Rehabilitacion Oral S.c.p.",
    "wof:placetype":"venue"
},
  "geometry": {"coordinates":[2.0990240574,41.3271751404],"type":"Point"}
}