{
  "type": "Feature",
  "properties": {
    "iso:country":"ES",
    "sg:address":"Calle de Calderon De La Barca, 4",
    "sg:city":"Madrid",
    "sg:orig_category":"Inmobiliaria (agencias)",
    "sg:phone":"+34 915 59 95 39",
    "sg:postcode":"28013",
    "sg:province":"Madrid",
    "wof:name":"Calderon De La Barca 4 Promocion Y Gestion S.l.",
    "wof:placetype":"venue"
},
  "geometry": {"coordinates":[-3.711076498,40.4157104492],"type":"Point"}
}