{
  "type": "Feature",
  "properties": {
    "addr:full":"Calle de Obispo Rocamora, 29 Orihuela Alicante 03300",
    "addr:housenumber":"29",
    "addr:postcode":"03300",
    "addr:street":"Calle De Obispo Rocamora",
    "iso:country":"ES",
    "sg:address":"Calle de Obispo Rocamora, 29",
    "sg:city":"Orihuela",
    "sg:orig_category":"Ingenier\u00cda, Centros De Estudios (diversos)",
    "sg:phone":"+34 966 74 50 28",
    "sg:postcode":"03300",
    "sg:province":"Alicante",
    "wof:name":"Ingenieria Industrial Y Urbanistica Del Sureste S.l",
    "wof:placetype":"venue"
},
  "geometry": {"coordinates":[-0.9430990219,38.0836677551],"type":"Point"}
}