{
  "type": "Feature",
  "properties": {
    "iso:country":"ES",
    "sg:address":"Avda Compostela (de), 177",
    "sg:city":"Carballi\u00f1o",
    "sg:orig_category":"Vinos Y Licores (venta Al Por Menor)",
    "sg:phone":"+34 988 27 28 85",
    "sg:postcode":"32500",
    "sg:province":"Ourense",
    "wof:name":"Distribucions A Madanela S.l.",
    "wof:placetype":"venue"
},
  "geometry": {"coordinates":[-8.0743541718,42.4344444275],"type":"Point"}
}