{
  "type": "Feature",
  "properties": {
    "iso:country":"ES",
    "sg:address":"Calle de Roger De Flor, 5",
    "sg:city":"Zaragoza",
    "sg:orig_category":"Carnicer\u00cdas, Carnicer\u00cdas",
    "sg:phone":"+34 976 31 81 95",
    "sg:postcode":"50017",
    "sg:province":"Zaragoza",
    "wof:name":"Gregorio Magallon Jose",
    "wof:placetype":"venue"
},
  "geometry": {"coordinates":[-0.9167829752,41.6497154236],"type":"Point"}
}