{
  "type": "Feature",
  "properties": {
    "iso:country":"ES",
    "sg:address":"Plaz Mercado, S/n",
    "sg:city":"Salamanca",
    "sg:orig_category":"Pescader\u00cdas (al Por Menor)",
    "sg:phone":"+34 923 21 35 08",
    "sg:postcode":"37001",
    "sg:province":"Salamanca",
    "wof:name":"Perez Fernandez Eduardo",
    "wof:placetype":"venue"
},
  "geometry": {"coordinates":[-5.6633839607,40.9647140503],"type":"Point"}
}