{
  "type": "Feature",
  "properties": {
    "iso:country":"ES",
    "sg:address":"Calle de Valencia (de), 7",
    "sg:city":"Humanes De Madrid",
    "sg:orig_category":"Charcuter\u00cdas (al Por Mayor)",
    "sg:phone":"+34 916 06 41 38",
    "sg:postcode":"28970",
    "sg:province":"Madrid",
    "wof:name":"Vitulia S. A.",
    "wof:placetype":"venue"
},
  "geometry": {"coordinates":[-3.8163218498,40.2764511108],"type":"Point"}
}