{
  "type": "Feature",
  "properties": {
    "addr:full":"Av Dr. Fleming, De, 38 S. Antoni Portmany Islas Baleares 07820",
    "addr:housenumber":"38",
    "addr:postcode":"07820",
    "addr:street":"Av Dr. Fleming De",
    "iso:country":"ES",
    "sg:address":"Av Dr. Fleming, De, 38",
    "sg:city":"S. Antoni Portmany",
    "sg:orig_category":"Reposter\u00cdas",
    "sg:phone":"+34 971 34 76 23",
    "sg:postcode":"07820",
    "sg:province":"Islas Baleares",
    "wof:name":"Can Rafal S.l.",
    "wof:placetype":"venue"
},
  "geometry": {"coordinates":[1.3101600409,38.9698181152],"type":"Point"}
}