{
  "type": "Feature",
  "properties": {
    "addr:full":"Calle de Collado (el), 23 Soria Soria 42002",
    "addr:housenumber":"23",
    "addr:postcode":"42002",
    "addr:street":"Calle De Collado El",
    "iso:country":"ES",
    "sg:address":"Calle de Collado (el), 23",
    "sg:city":"Soria",
    "sg:orig_category":"Asociaciones, Organismos Culturales Y Socioeducativos",
    "sg:phone":"+34 975 21 11 64",
    "sg:postcode":"42002",
    "sg:province":"Soria",
    "wof:name":"Circulo De La Amistad De Numancia",
    "wof:placetype":"venue"
},
  "geometry": {"coordinates":[-2.466023922,41.7641220093],"type":"Point"}
}