{
  "type": "Feature",
  "properties": {
    "addr:full":"Pg Mar, 5 S. Feliu Guixols Girona 17220",
    "addr:housenumber":"5",
    "addr:postcode":"17220",
    "addr:street":"Pg Mar;Feliu",
    "iso:country":"ES",
    "sg:address":"Pg Mar, 5",
    "sg:city":"S. Feliu Guixols",
    "sg:orig_category":"Pintores",
    "sg:phone":"+34 972 32 26 71",
    "sg:postcode":"17220",
    "sg:province":"Girona",
    "wof:name":"Amat Pages Jose",
    "wof:placetype":"venue"
},
  "geometry": {"coordinates":[3.0288214684,41.7799606323],"type":"Point"}
}