{
  "type": "Feature",
  "properties": {
    "iso:country":"ES",
    "sg:address":"Ignacio Zuloaga Kalea, 4",
    "sg:city":"Arrasate",
    "sg:orig_category":"Molduras, Junquillos, Listones Y Molduras Perforadas",
    "sg:phone":"+34 943 79 89 99",
    "sg:postcode":"20500",
    "sg:province":"Guip\u00f9zcoa",
    "wof:name":"Garcia Portero , Juan Antonio",
    "wof:placetype":"venue"
},
  "geometry": {"coordinates":[-2.4899702072,43.0672264099],"type":"Point"}
}