{
  "type": "Feature",
  "properties": {
    "iso:country":"ES",
    "sg:address":"Avda Sants De La Pedra, 22",
    "sg:city":"Sagunt",
    "sg:orig_category":"Cuidado Del Cabello",
    "sg:phone":"+34 962 66 62 40",
    "sg:postcode":"46500",
    "sg:province":"Valencia",
    "wof:name":"Salon De Belleza Duo S.l.",
    "wof:placetype":"venue"
},
  "geometry": {"coordinates":[-0.2719230056,39.6807098389],"type":"Point"}
}