{
  "type": "Feature",
  "properties": {
    "iso:country":"ES",
    "sg:address":"Carrer de Quevedo, 21",
    "sg:city":"Barcelona",
    "sg:orig_category":"Carnicer\u00cdas, Carnicer\u00cdas",
    "sg:phone":"+34 932 19 64 48",
    "sg:postcode":"08012",
    "sg:province":"Barcelona",
    "wof:name":"Ciurana Mas Manuel",
    "wof:placetype":"venue"
},
  "geometry": {"coordinates":[2.161853075,41.4027557373],"type":"Point"}
}