{
  "type": "Feature",
  "properties": {
    "iso:country":"ES",
    "sg:address":"Plaz San Francisco, 5",
    "sg:city":"Baza",
    "sg:orig_category":"Ropa Para Se\u00d1oras (al Por Menor)",
    "sg:phone":"+34 958 86 11 48",
    "sg:postcode":"18800",
    "sg:province":"Granada",
    "sg:website":"www.amichi.com",
    "wof:name":"Magdaleno Rodriguez Pilar",
    "wof:placetype":"venue"
},
  "geometry": {"coordinates":[-2.7822339535,37.4883460999],"type":"Point"}
}