{
  "type": "Feature",
  "properties": {
    "iso:country":"ES",
    "sg:address":"Calle de Tarazona, S/n",
    "sg:city":"Madrigueras",
    "sg:orig_category":"Mec\u00c1nico Del Autom\u00d3vil",
    "sg:phone":"+34 967 48 43 25",
    "sg:postcode":"02230",
    "sg:province":"Albacete",
    "wof:name":"Ballesteros Merino Federico",
    "wof:placetype":"venue"
},
  "geometry": {"coordinates":[-1.8046640158,39.2374839783],"type":"Point"}
}