{
  "type": "Feature",
  "properties": {
    "addr:full":"Ptda La Plana, S/n Almenar Lleida 25126",
    "addr:housenumber":"s / n",
    "addr:postcode":"25126",
    "addr:street":"Ptda La Plana",
    "iso:country":"ES",
    "sg:address":"Ptda La Plana, S/n",
    "sg:city":"Almenar",
    "sg:orig_category":"Producci\u00d3n, Venta De Productos De Agricultura Biol\u00d3gica",
    "sg:phone":"+34 973 77 04 44",
    "sg:postcode":"25126",
    "sg:province":"Lleida",
    "wof:name":"Rota Pociello Andres",
    "wof:placetype":"venue"
},
  "geometry": {"coordinates":[0.5640100241,41.7948417664],"type":"Point"}
}