{
  "type": "Feature",
  "properties": {
    "iso:country":"ES",
    "sg:address":"Calle de Santiago Ramon Y Cajal, 39",
    "sg:city":"Cartagena",
    "sg:orig_category":"Ropa Para Caballeros (al Por Menor)",
    "sg:phone":"+34 968 51 78 81",
    "sg:postcode":"30204",
    "sg:province":"Murcia",
    "wof:name":"Checa Y Fenol S.l.",
    "wof:placetype":"venue"
},
  "geometry": {"coordinates":[-0.9922369719,37.6133117676],"type":"Point"}
}