{
  "type": "Feature",
  "properties": {
    "addr:full":"Barr Larzabal, 7 Errenteria Guip\u00f9zcoa 20100",
    "addr:housenumber":"7",
    "addr:postcode":"20100",
    "addr:street":"Barr Larzabal;Guipu\u0300Zcoa",
    "iso:country":"ES",
    "sg:address":"Barr Larzabal, 7",
    "sg:city":"Errenteria",
    "sg:orig_category":"Molduras, Junquillos, Listones Y Molduras Perforadas",
    "sg:phone":"+34 943 51 10 65",
    "sg:postcode":"20100",
    "sg:province":"Guip\u00f9zcoa",
    "wof:name":"Fernandez Valencia Fatina",
    "wof:placetype":"venue"
},
  "geometry": {"coordinates":[-1.8836790323,43.3098678589],"type":"Point"}
}