{
  "type": "Feature",
  "properties": {
    "addr:full":"Calle de Belianes, 8 Madrid Madrid 28043",
    "addr:housenumber":"8",
    "addr:postcode":"madrid;28043",
    "addr:street":"Calle De Belianes",
    "iso:country":"ES",
    "sg:address":"Calle de Belianes, 8",
    "sg:city":"Madrid",
    "sg:orig_category":"Enfermeras: Consultas, Atenci\u00d3n A Domicilio",
    "sg:phone":"+34 913 81 25 65",
    "sg:postcode":"28043",
    "sg:province":"Madrid",
    "wof:name":"Moreno Lopez Francisco",
    "wof:placetype":"venue"
},
  "geometry": {"coordinates":[-3.6458098888,40.4702949524],"type":"Point"}
}