{
  "type": "Feature",
  "properties": {
    "iso:country":"ES",
    "sg:address":"Calle de Enrique Larreta, 9",
    "sg:city":"Madrid",
    "sg:orig_category":"Abogados",
    "sg:phone":"+34 913 15 77 22",
    "sg:postcode":"28036",
    "sg:province":"Madrid",
    "wof:name":"Martinez Gonzalez Alejandro",
    "wof:placetype":"venue"
},
  "geometry": {"coordinates":[-3.6866934299,40.468421936],"type":"Point"}
}