{
  "type": "Feature",
  "properties": {
    "iso:country":"ES",
    "sg:address":"Carrer de Anselm Clave, 141",
    "sg:city":"Olesa Montserrat",
    "sg:orig_category":"Institutos De Belleza",
    "sg:phone":"+34 937 78 27 76",
    "sg:postcode":"08640",
    "sg:province":"Barcelona",
    "wof:name":"Pablos Garcia Maria Guadalupe",
    "wof:placetype":"venue"
},
  "geometry": {"coordinates":[1.8938210011,41.5435142517],"type":"Point"}
}