{
  "type": "Feature",
  "properties": {
    "iso:country":"ES",
    "sg:address":"Calle de Rosalia De Castro, 28",
    "sg:city":"Villena",
    "sg:orig_category":"Suministros Para Hoteles",
    "sg:phone":"+34 965 81 38 58",
    "sg:postcode":"03400",
    "sg:province":"Alicante",
    "wof:name":"Eurotoque S.l",
    "wof:placetype":"venue"
},
  "geometry": {"coordinates":[-0.8631989956,38.6273384094],"type":"Point"}
}