{
  "type": "Feature",
  "properties": {
    "iso:country":"ES",
    "sg:address":"Calle de Vasco De Gama, S/n",
    "sg:city":"Totana",
    "sg:orig_category":"Polideportivos",
    "sg:phone":"+34 968 42 26 01",
    "sg:postcode":"30850",
    "sg:province":"Murcia",
    "wof:name":"Ayuntamiento De Totana",
    "wof:placetype":"venue"
},
  "geometry": {"coordinates":[-1.501544714,37.7613067627],"type":"Point"}
}