{
  "type": "Feature",
  "properties": {
    "addr:full":"Calle de Numancia, 26 Soria Soria 42001",
    "addr:housenumber":"26",
    "addr:postcode":"42001",
    "addr:street":"Calle De Numancia",
    "iso:country":"ES",
    "sg:address":"Calle de Numancia, 26",
    "sg:city":"Soria",
    "sg:orig_category":"Ropa Para Caballeros (al Por Menor)",
    "sg:phone":"+34 975 23 00 20",
    "sg:postcode":"42001",
    "sg:province":"Soria",
    "wof:name":"Max Modos Soria S.l.",
    "wof:placetype":"venue"
},
  "geometry": {"coordinates":[-2.4682035446,41.7655105591],"type":"Point"}
}