{
  "type": "Feature",
  "properties": {
    "addr:full":"Calle de Torrejon, 7 Priego Cordoba C\u00f3rdoba 14800",
    "addr:housenumber":"7",
    "addr:postcode":"14800",
    "addr:street":"Calle De Torrejon;Cordoba Co\u0301Rdoba",
    "iso:country":"ES",
    "sg:address":"Calle de Torrejon, 7",
    "sg:city":"Priego Cordoba",
    "sg:orig_category":"Agencias Y Agentes Comerciales, Representantes",
    "sg:phone":"+34 957 54 70 78",
    "sg:postcode":"14800",
    "sg:province":"C\u00f3rdoba",
    "wof:name":"Murube Carreto Cristina",
    "wof:placetype":"venue"
},
  "geometry": {"coordinates":[-4.194067955,37.4380073547],"type":"Point"}
}