{
  "type": "Feature",
  "properties": {
    "iso:country":"ES",
    "sg:address":"Pla\u00c7 Marques De Camps, 16",
    "sg:city":"Girona",
    "sg:orig_category":"M\u00c9dicos: Estomatolog\u00cda",
    "sg:phone":"+34 972 21 30 53",
    "sg:postcode":"17001",
    "sg:province":"Girona",
    "wof:name":"Clinica Dental Doctors Banchilleria S.c.p.",
    "wof:placetype":"venue"
},
  "geometry": {"coordinates":[2.8193640709,41.9820899963],"type":"Point"}
}