{
  "type": "Feature",
  "properties": {
    "addr:full":"Avda Europa (de), 10 Rincon Soto La Rioja 26550",
    "addr:housenumber":"10",
    "addr:postcode":"26550",
    "addr:street":"Avda Europa De;Rioja",
    "iso:country":"ES",
    "sg:address":"Avda Europa (de), 10",
    "sg:city":"Rincon Soto",
    "sg:orig_category":"Plomeros",
    "sg:phone":"+34 941 16 00 54",
    "sg:postcode":"26550",
    "sg:province":"La Rioja",
    "wof:name":"Navascues Pedriza Ignacio",
    "wof:placetype":"venue"
},
  "geometry": {"coordinates":[-1.8502299786,42.2380065918],"type":"Point"}
}