{
  "type": "Feature",
  "properties": {
    "addr:full":"Calle de Tiro, 10 Moron Frontera Sevilla 41530",
    "addr:housenumber":"10",
    "addr:postcode":"41530",
    "addr:street":"Calle De Tiro",
    "iso:country":"ES",
    "sg:address":"Calle de Tiro, 10",
    "sg:city":"Moron Frontera",
    "sg:orig_category":"Art\u00cdculos Funerarios (al Por Menor)",
    "sg:phone":"+34 955 85 17 66",
    "sg:postcode":"41530",
    "sg:province":"Sevilla",
    "wof:name":"Servicios Especiales S.a.",
    "wof:placetype":"venue"
},
  "geometry": {"coordinates":[-5.4523081779,37.1235847473],"type":"Point"}
}