{
  "type": "Feature",
  "properties": {
    "addr:full":"Calle de Sagasta, 51 Moron Frontera Sevilla 41530",
    "addr:housenumber":"51",
    "addr:postcode":"41530",
    "addr:street":"Calle De Sagasta",
    "iso:country":"ES",
    "sg:address":"Calle de Sagasta, 51",
    "sg:city":"Moron Frontera",
    "sg:orig_category":"Molduras, Junquillos, Listones Y Molduras Perforadas",
    "sg:phone":"+34 955 85 21 57",
    "sg:postcode":"41530",
    "sg:province":"Sevilla",
    "wof:name":"Alcantara Troya Manuel",
    "wof:placetype":"venue"
},
  "geometry": {"coordinates":[-5.4561271667,37.1198196411],"type":"Point"}
}