{
  "type": "Feature",
  "properties": {
    "addr:full":"Calle de Ramon Y Cajal, 2 Sacedon Guadalajara 19120",
    "addr:housenumber":"2",
    "addr:postcode":"19120",
    "addr:street":"Calle De Ramon Y Cajal",
    "iso:country":"ES",
    "sg:address":"Calle de Ramon Y Cajal, 2",
    "sg:city":"Sacedon",
    "sg:orig_category":"Notarios",
    "sg:phone":"+34 949 35 04 61",
    "sg:postcode":"19120",
    "sg:province":"Guadalajara",
    "wof:name":"De La Torre Pedrosa Maria De La Concepcion",
    "wof:placetype":"venue"
},
  "geometry": {"coordinates":[-2.73320508,40.4808921814],"type":"Point"}
}