{
  "type": "Feature",
  "properties": {
    "addr:full":"Calle de Virgen Del Mar, 18 Santurtzi Vizcaya 48980",
    "addr:housenumber":"18",
    "addr:postcode":"48980",
    "addr:street":"Calle De Virgen Del Mar",
    "iso:country":"ES",
    "sg:address":"Calle de Virgen Del Mar, 18",
    "sg:city":"Santurtzi",
    "sg:orig_category":"Molduras, Junquillos, Listones Y Molduras Perforadas",
    "sg:phone":"+34 944 83 22 23",
    "sg:postcode":"48980",
    "sg:province":"Vizcaya",
    "wof:name":"Quiroga Docasar Mercedes",
    "wof:placetype":"venue"
},
  "geometry": {"coordinates":[-3.0369501114,43.3319473267],"type":"Point"}
}