{
  "type": "Feature",
  "properties": {
    "addr:full":"Calle de San Roque, 37 Villarcayo Burgos 09550",
    "addr:housenumber":"37",
    "addr:postcode":"09550",
    "addr:street":"Calle De San Roque",
    "iso:country":"ES",
    "sg:address":"Calle de San Roque, 37",
    "sg:city":"Villarcayo",
    "sg:orig_category":"Psic\u00d3logos",
    "sg:phone":"+34 947 13 21 43",
    "sg:postcode":"09550",
    "sg:province":"Burgos",
    "wof:name":"Varona Alvarez Belen",
    "wof:placetype":"venue"
},
  "geometry": {"coordinates":[-3.5674788952,42.9422912598],"type":"Point"}
}