{
  "type": "Feature",
  "properties": {
    "iso:country":"ES",
    "sg:address":"Av Ntra. Sra. De L'assumpcio, 149",
    "sg:city":"Deltebre",
    "sg:orig_category":"Molduras, Junquillos, Listones Y Molduras Perforadas",
    "sg:phone":"+34 977 48 90 59",
    "sg:postcode":"43580",
    "sg:province":"Tarragona",
    "wof:name":"Guillen Dolz Humildad",
    "wof:placetype":"venue"
},
  "geometry": {"coordinates":[0.7110379934,40.7193870544],"type":"Point"}
}