{
  "type": "Feature",
  "properties": {
    "addr:full":"Calle de Lugo, 40 Arzua La Coru\u00f1a 15810",
    "addr:housenumber":"40",
    "addr:postcode":"15810",
    "addr:street":"Calle De Lugo;La Corun\u0303A",
    "iso:country":"ES",
    "sg:address":"Calle de Lugo, 40",
    "sg:city":"Arzua",
    "sg:orig_category":"Promotores Constructores",
    "sg:phone":"+34 981 50 81 59",
    "sg:postcode":"15810",
    "sg:province":"La Coru\u00f1a",
    "wof:name":"Conser Arzua S.l.",
    "wof:placetype":"venue"
},
  "geometry": {"coordinates":[-8.1595993042,42.927570343],"type":"Point"}
}