{
  "type": "Feature",
  "properties": {
    "iso:country":"ES",
    "sg:address":"Sigueiro, 8",
    "sg:city":"Sigueiro",
    "sg:orig_category":"Molduras, Junquillos, Listones Y Molduras Perforadas",
    "sg:phone":"+34 981 69 14 92",
    "sg:postcode":"15888",
    "sg:province":"La Coru\u00f1a",
    "wof:name":"Balado Hermida Ramon",
    "wof:placetype":"venue"
},
  "geometry": {"coordinates":[-8.4479351044,42.9691963196],"type":"Point"}
}