{
  "type": "Feature",
  "properties": {
    "addr:full":"Calle de Escalinata, 3 Pozuelo De Alarcon Madrid 28223",
    "addr:housenumber":"3",
    "addr:postcode":"28223",
    "addr:street":"Calle De Escalinata",
    "iso:country":"ES",
    "sg:address":"Calle de Escalinata, 3",
    "sg:city":"Pozuelo De Alarcon",
    "sg:orig_category":"Frutas, Legumbres Frescas Y Tempranas (al Por Menor)",
    "sg:phone":"+34 913 52 28 32",
    "sg:postcode":"28223",
    "sg:province":"Madrid",
    "wof:name":"Fernandez Duran Manuel",
    "wof:placetype":"venue"
},
  "geometry": {"coordinates":[-3.8144109249,40.4359169006],"type":"Point"}
}