{
  "type": "Feature",
  "properties": {
    "addr:full":"Calle de Rui-velez, 6 Huelva Huelva 21002",
    "addr:housenumber":"6",
    "addr:postcode":"21002",
    "addr:street":"Calle De Rui-Velez",
    "iso:country":"ES",
    "sg:address":"Calle de Rui-velez, 6",
    "sg:city":"Huelva",
    "sg:orig_category":"Ense\u00d1anza: Profesiones Art\u00cdsticas",
    "sg:phone":"+34 959 28 56 04",
    "sg:postcode":"21002",
    "sg:province":"Huelva",
    "wof:name":"Photonuba Servicios Fotograficos Sll",
    "wof:placetype":"venue"
},
  "geometry": {"coordinates":[-6.9526219368,37.2605056763],"type":"Point"}
}