{
  "type": "Feature",
  "properties": {
    "addr:full":"Avda Florida, 15 Vigo Pontevedra 36210",
    "addr:housenumber":"15",
    "addr:postcode":"36210",
    "addr:street":"Avda Florida",
    "iso:country":"ES",
    "sg:address":"Avda Florida, 15",
    "sg:city":"Vigo",
    "sg:orig_category":"Institutos De Belleza (productos Y Aparatos)",
    "sg:phone":"+34 986 29 27 27",
    "sg:postcode":"36210",
    "sg:province":"Pontevedra",
    "wof:name":"Alvarez Santos Yolanda",
    "wof:placetype":"venue"
},
  "geometry": {"coordinates":[-8.7343406677,42.2196846008],"type":"Point"}
}