{
  "type": "Feature",
  "properties": {
    "iso:country":"ES",
    "sg:address":"Calle de Doctor Aquilino Hurle, 24",
    "sg:city":"Gijon",
    "sg:orig_category":"Alquiler De V\u00cddeo",
    "sg:phone":"+34 985 13 13 89",
    "sg:postcode":"33203",
    "sg:province":"Asturias",
    "wof:name":"Kira Films",
    "wof:placetype":"venue"
},
  "geometry": {"coordinates":[-5.6480846405,43.5385894775],"type":"Point"}
}