{
  "type": "Feature",
  "properties": {
    "iso:country":"ES",
    "sg:address":"Prje Mos Del Bou, 7",
    "sg:city":"Albatera",
    "sg:orig_category":"Madera Para Construcci\u00d3n E Industria",
    "sg:phone":"+34 965 48 90 01",
    "sg:postcode":"03340",
    "sg:province":"Alicante",
    "wof:name":"Brezo Y Ca\u00f1izos Albatera S.l.",
    "wof:placetype":"venue"
},
  "geometry": {"coordinates":[-0.8711339831,38.1797294617],"type":"Point"}
}