{
  "type": "Feature",
  "properties": {
    "iso:country":"ES",
    "sg:address":"Carrer de Ebre (de L'), 1",
    "sg:city":"Salou",
    "sg:orig_category":"Art\u00cdculos De Regalo (al Por Menor)",
    "sg:phone":"+34 977 38 09 35",
    "sg:postcode":"43840",
    "sg:province":"Tarragona",
    "wof:name":"Donkers  Willem",
    "wof:placetype":"venue"
},
  "geometry": {"coordinates":[1.1323029995,41.0813140869],"type":"Point"}
}