{
  "type": "Feature",
  "properties": {
    "addr:full":"Pase Estacion, S/n Ferrol La Coru\u00f1a 15405",
    "addr:postcode":"15405",
    "addr:street":"S / N;La Corun\u0303A",
    "iso:country":"ES",
    "sg:address":"Pase Estacion, S/n",
    "sg:city":"Ferrol",
    "sg:orig_category":"Ense\u00d1anza, Formaci\u00d3n Profesional: Aprendizaje",
    "sg:phone":"+34 981 37 04 01",
    "sg:postcode":"15405",
    "sg:province":"La Coru\u00f1a",
    "wof:name":"Ferrocarriles De Via Estrecha",
    "wof:placetype":"venue"
},
  "geometry": {"coordinates":[-8.2314767838,43.4877433777],"type":"Point"}
}