{
  "type": "Feature",
  "properties": {
    "addr:full":"Carrer de Diana, 7 Denia Alicante 03700",
    "addr:housenumber":"7",
    "addr:postcode":"03700",
    "addr:street":"Carrer De Diana",
    "iso:country":"ES",
    "sg:address":"Carrer de Diana, 7",
    "sg:city":"Denia",
    "sg:orig_category":"Tapiceros Y Tapiceros",
    "sg:phone":"+34 965 78 90 16",
    "sg:postcode":"03700",
    "sg:province":"Alicante",
    "wof:name":"B.i.s. Dise\u00f1o E Interiorismo S.l",
    "wof:placetype":"venue"
},
  "geometry": {"coordinates":[0.107032001,38.8405151367],"type":"Point"}
}