{
  "type": "Feature",
  "properties": {
    "iso:country":"ES",
    "sg:address":"Calle de Clavel (del), 10",
    "sg:city":"Segovia",
    "sg:orig_category":"Promotores Constructores",
    "sg:phone":"+34 921 43 31 18",
    "sg:postcode":"40001",
    "sg:province":"Segovia",
    "wof:name":"Promociones El Romeral S.l.",
    "wof:placetype":"venue"
},
  "geometry": {"coordinates":[-4.1184558868,40.9408035278],"type":"Point"}
}