{
  "type": "Feature",
  "properties": {
    "addr:full":"Calle de Calvario (del), 2 Alcolea Cinca Huesca 22410",
    "addr:housenumber":"2",
    "addr:postcode":"22410",
    "addr:street":"Calle De Calvario Del",
    "iso:country":"ES",
    "sg:address":"Calle de Calvario (del), 2",
    "sg:city":"Alcolea Cinca",
    "sg:orig_category":"Carnicer\u00cdas, Carnicer\u00cdas",
    "sg:phone":"+34 974 46 83 95",
    "sg:postcode":"22410",
    "sg:province":"Huesca",
    "wof:name":"Cascarosa Periz Jose Fernando",
    "wof:placetype":"venue"
},
  "geometry": {"coordinates":[0.1156608015,41.7196502686],"type":"Point"}
}