{
  "type": "Feature",
  "properties": {
    "addr:full":"San Caetano, S/n San Caetano Pontevedra 36099",
    "addr:housenumber":"s / n",
    "addr:postcode":"36099",
    "iso:country":"ES",
    "sg:address":"San Caetano, S/n",
    "sg:city":"San Caetano",
    "sg:orig_category":"Material Y Herramientas Agr\u00cdcolas",
    "sg:phone":"+34 986 87 18 21",
    "sg:postcode":"36099",
    "sg:province":"Pontevedra",
    "wof:name":"Comercial Vazpe S. L.",
    "wof:placetype":"venue"
},
  "geometry": {"coordinates":[-8.6489601135,42.4695892334],"type":"Point"}
}