{
  "type": "Feature",
  "properties": {
    "addr:full":"Ctr. Madrid-soria, S/n Jadraque Guadalajara 19240",
    "addr:postcode":"19240",
    "addr:street":"Madrid-Soria S / N Jadraque",
    "iso:country":"ES",
    "sg:address":"Ctr. Madrid-soria, S/n",
    "sg:city":"Jadraque",
    "sg:orig_category":"Albergues",
    "sg:phone":"+34 949 89 02 54",
    "sg:postcode":"19240",
    "sg:province":"Guadalajara",
    "wof:name":"Gregorio Navarro Hermanos S.l.",
    "wof:placetype":"venue"
},
  "geometry": {"coordinates":[-2.9276280403,40.9257965088],"type":"Point"}
}