{
  "type": "Feature",
  "properties": {
    "addr:full":"Part Antonio Rodriguez, 9 Madrid Madrid 28044",
    "addr:housenumber":"9",
    "addr:postcode":"28044",
    "addr:street":"Madrid",
    "iso:country":"ES",
    "sg:address":"Part Antonio Rodriguez, 9",
    "sg:city":"Madrid",
    "sg:orig_category":"Charcuter\u00cdas (al Por Mayor)",
    "sg:phone":"+34 915 25 61 16",
    "sg:postcode":"28044",
    "sg:province":"Madrid",
    "wof:name":"Distribuciones Eulalio Perez S.l.",
    "wof:placetype":"venue"
},
  "geometry": {"coordinates":[-3.745609045,40.3736953735],"type":"Point"}
}