{
  "type": "Feature",
  "properties": {
    "iso:country":"ES",
    "sg:address":"Avda Miraflores, 72",
    "sg:city":"Sevilla",
    "sg:orig_category":"Caf\u00c9s, Bares, Cervecer\u00cdas",
    "sg:phone":"+34 954 35 76 16",
    "sg:postcode":"41008",
    "sg:province":"Sevilla",
    "wof:name":"Burgos Gomez Manuel",
    "wof:placetype":"venue"
},
  "geometry": {"coordinates":[-5.9502968788,37.4202232361],"type":"Point"}
}