{
  "type": "Feature",
  "properties": {
    "addr:full":"P. Los Cancajos, 33 Los Cancajos Santa Cruz De Tenerife 38712",
    "addr:housenumber":"33",
    "addr:postcode":"38712",
    "addr:street":"P.;Cancajos;Cancajos",
    "iso:country":"ES",
    "sg:address":"P. Los Cancajos, 33",
    "sg:city":"Los Cancajos",
    "sg:orig_category":"Alquiler De Veh\u00cdculos: Turismos Y Utilitarios",
    "sg:phone":"+34 922 43 54 53",
    "sg:postcode":"38712",
    "sg:province":"Santa Cruz De Tenerife",
    "sg:website":"www.ferraz.de",
    "wof:name":"Autos Ferraz S.l.",
    "wof:placetype":"venue"
},
  "geometry": {"coordinates":[-16.2548561096,28.4698104858],"type":"Point"}
}