{
  "type": "Feature",
  "properties": {
    "addr:full":"Carr Parra (canals) (la), 44 Canals Valencia 46650",
    "addr:postcode":"46650",
    "addr:street":"Carr Parra;La",
    "iso:country":"ES",
    "sg:address":"Carr Parra (canals) (la), 44",
    "sg:city":"Canals",
    "sg:orig_category":"Herboristas (al Por Menor)",
    "sg:phone":"+34 962 24 00 49",
    "sg:postcode":"46650",
    "sg:province":"Valencia",
    "wof:name":"Bertomeu Garcia Maria Amparo",
    "wof:placetype":"venue"
},
  "geometry": {"coordinates":[-0.5831859708,38.9633674622],"type":"Point"}
}