{
  "type": "Feature",
  "properties": {
    "iso:country":"ES",
    "sg:address":"Calle de San Vicente Martir, 112",
    "sg:city":"Valencia",
    "sg:orig_category":"Abogados",
    "sg:phone":"+34 963 50 93 07",
    "sg:postcode":"46007",
    "sg:province":"Valencia",
    "wof:name":"Brines Flames Ignacio Jose",
    "wof:placetype":"venue"
},
  "geometry": {"coordinates":[-0.3814690113,39.46641922],"type":"Point"}
}