{
  "type": "Feature",
  "properties": {
    "addr:full":"Ctra General Santa Cruz Laguna, 315 Cuesta Santa Cruz De Tenerife 38320",
    "addr:housenumber":"315",
    "addr:postcode":"38320",
    "addr:street":"Ctra General;Cuesta Santa Cruz De",
    "iso:country":"ES",
    "sg:address":"Ctra General Santa Cruz Laguna, 315",
    "sg:city":"Cuesta",
    "sg:orig_category":"M\u00c9dicos: Estomatolog\u00cda",
    "sg:phone":"+34 922 66 05 45",
    "sg:postcode":"38320",
    "sg:province":"Santa Cruz De Tenerife",
    "wof:name":"Hernandez Brito Sonia Alicia",
    "wof:placetype":"venue"
},
  "geometry": {"coordinates":[-16.2899017334,28.4690818787],"type":"Point"}
}