{
  "type": "Feature",
  "properties": {
    "iso:country":"ES",
    "sg:address":"Moli De La Sal, 46",
    "sg:city":"Canovelles",
    "sg:orig_category":"Caf\u00c9s, Bares, Cervecer\u00cdas",
    "sg:phone":"+34 938 49 98 52",
    "sg:postcode":"08420",
    "sg:province":"Barcelona",
    "wof:name":"Sanchez Modenes Luis Miguel",
    "wof:placetype":"venue"
},
  "geometry": {"coordinates":[2.2798349857,41.615688324],"type":"Point"}
}