{
  "type": "Feature",
  "properties": {
    "addr:full":"Calle de Venus (de), 8 Poligono De San Fernando De Henares Madrid 28830",
    "addr:housenumber":"8",
    "addr:postcode":"28830",
    "addr:street":"Calle De Venus De",
    "iso:country":"ES",
    "sg:address":"Calle de Venus (de), 8",
    "sg:city":"Poligono De San Fernando De Henares",
    "sg:orig_category":"Alquiler De Veh\u00cdculos: Turismos Y Utilitarios",
    "sg:phone":"+34 915 01 93 13",
    "sg:postcode":"28830",
    "sg:province":"Madrid",
    "sg:website":"www.driverlimousine.com",
    "wof:name":"Driver Limousine S.l.",
    "wof:placetype":"venue"
},
  "geometry": {"coordinates":[-3.5011639595,40.4484634399],"type":"Point"}
}