{
  "type": "Feature",
  "properties": {
    "addr:full":"Calle de Capitan Gaona, 9 Logro\u00f1o La Rioja 26001",
    "addr:housenumber":"9",
    "addr:postcode":"26001",
    "addr:street":"Calle De Capitan Gaona;Rioja",
    "iso:country":"ES",
    "sg:address":"Calle de Capitan Gaona, 9",
    "sg:city":"Logro\u00f1o",
    "sg:orig_category":"Electricidad: Instalaciones Industriales",
    "sg:phone":"+34 941 25 52 19",
    "sg:postcode":"26001",
    "sg:province":"La Rioja",
    "wof:name":"Garcia-mancha Rejado Alberto",
    "wof:placetype":"venue"
},
  "geometry": {"coordinates":[-2.4407427311,42.4676895142],"type":"Point"}
}