{
  "type": "Feature",
  "properties": {
    "addr:full":"Calle de Iparraguirre, 39 Bilbao Vizcaya 48011",
    "addr:housenumber":"39",
    "addr:postcode":"48011",
    "addr:street":"Calle De Iparraguirre",
    "iso:country":"ES",
    "sg:address":"Calle de Iparraguirre, 39",
    "sg:city":"Bilbao",
    "sg:orig_category":"Maquinaria Para Industrias Diversas",
    "sg:phone":"+34 944 43 57 00",
    "sg:postcode":"48011",
    "sg:province":"Vizcaya",
    "wof:name":"Arcadio D. De Corcuera S. A.",
    "wof:placetype":"venue"
},
  "geometry": {"coordinates":[-2.936827898,43.2619171143],"type":"Point"}
}