{
  "type": "Feature",
  "properties": {
    "addr:full":"Ptge Horta De Sant Josep, 20 Vic Barcelona 08500",
    "addr:housenumber":"20",
    "addr:postcode":"08500",
    "addr:street":"Ptge;Josep",
    "iso:country":"ES",
    "sg:address":"Ptge Horta De Sant Josep, 20",
    "sg:city":"Vic",
    "sg:orig_category":"Abogados",
    "sg:phone":"+34 938 89 32 83",
    "sg:postcode":"08500",
    "sg:province":"Barcelona",
    "wof:name":"Serrat Faba Mercedes",
    "wof:placetype":"venue"
},
  "geometry": {"coordinates":[2.2567679882,41.9324455261],"type":"Point"}
}