{
  "type": "Feature",
  "properties": {
    "iso:country":"ES",
    "sg:address":"Cust Del Hospital, 14",
    "sg:city":"Benavente",
    "sg:orig_category":"Cerrajer\u00cda, Ferrallista",
    "sg:phone":"+34 980 63 33 55",
    "sg:postcode":"49600",
    "sg:province":"Zamora",
    "wof:name":"Dieguez Izquierdo Gregorio",
    "wof:placetype":"venue"
},
  "geometry": {"coordinates":[-5.677795887,42.0033531189],"type":"Point"}
}