{
  "type": "Feature",
  "properties": {
    "iso:country":"ES",
    "sg:address":"Plaz Espa\u00d1a (de), 4",
    "sg:city":"Valdepe\u00f1as",
    "sg:classifiers":[
        {
            "category":"Taxi",
            "type":"Transportation"
        }
    ],
    "sg:phone":"+34 926 32 03 76",
    "sg:postcode":"13300",
    "sg:province":"Ciudad Real",
    "wof:name":"Ayuntamiento Parada Taxis",
    "wof:placetype":"venue"
},
  "geometry": {"coordinates":[-3.3849329948,38.7599258423],"type":"Point"}
}