{
  "type": "Feature",
  "properties": {
    "addr:full":"Carrer de Blanco, 50 Barcelona Barcelona 08028",
    "addr:housenumber":"50",
    "addr:postcode":"08028",
    "addr:street":"Carrer De Blanco",
    "iso:country":"ES",
    "sg:address":"Carrer de Blanco, 50",
    "sg:city":"Barcelona",
    "sg:orig_category":"Peluquer\u00cdas, Peluquer\u00cda Mixta",
    "sg:phone":"+34 934 90 10 66",
    "sg:postcode":"08028",
    "sg:province":"Barcelona",
    "wof:name":"Puigtio Higueras Melchor",
    "wof:placetype":"venue"
},
  "geometry": {"coordinates":[2.1325480938,41.3760604858],"type":"Point"}
}