{
  "type": "Feature",
  "properties": {
    "iso:country":"ES",
    "sg:address":"Calle de La Revoltosa, 11",
    "sg:city":"Madrid",
    "sg:orig_category":"Frutas, Legumbres Frescas Y Tempranas (al Por Menor)",
    "sg:phone":"+34 913 31 71 66",
    "sg:postcode":"28031",
    "sg:province":"Madrid",
    "wof:name":"Barcala Alique Emilio",
    "wof:placetype":"venue"
},
  "geometry": {"coordinates":[-3.6208109856,40.3752975464],"type":"Point"}
}