{
  "type": "Feature",
  "properties": {
    "addr:full":"Calle de Ruben Dario, 22 Rota C\u00e1diz 11520",
    "addr:housenumber":"22",
    "addr:postcode":"11520",
    "addr:street":"Calle De Ruben Dario;Ca\u0301Diz",
    "iso:country":"ES",
    "sg:address":"Calle de Ruben Dario, 22",
    "sg:city":"Rota",
    "sg:orig_category":"Peluquer\u00cdas, Peluquer\u00cda Mixta",
    "sg:phone":"+34 956 81 31 61",
    "sg:postcode":"11520",
    "sg:province":"C\u00e1diz",
    "wof:name":"Fernandez Benitez Maria Jose",
    "wof:placetype":"venue"
},
  "geometry": {"coordinates":[-6.3601098061,36.6267242432],"type":"Point"}
}