{
  "type": "Feature",
  "properties": {
    "addr:full":"Partida Collastret, S/n Alcarras Lleida 25180",
    "addr:housenumber":"s",
    "addr:postcode":"25180",
    "addr:street":"Partida Collastret;/ N",
    "iso:country":"ES",
    "sg:address":"Partida Collastret, S/n",
    "sg:city":"Alcarras",
    "sg:orig_category":"Agricultura: Abastecimiento Y Cosechado (negocio)",
    "sg:phone":"+34 973 79 04 10",
    "sg:postcode":"25180",
    "sg:province":"Lleida",
    "wof:name":"Explotacions Agricoles Cervera Carras S.l.",
    "wof:placetype":"venue"
},
  "geometry": {"coordinates":[0.5199109912,41.561088562],"type":"Point"}
}