{
  "type": "Feature",
  "properties": {
    "addr:full":"C/ Ferreries, De, 22 Alaior Islas Baleares 07730",
    "addr:housenumber":"22",
    "addr:postcode":"07730",
    "addr:street":"C / Ferreries De",
    "iso:country":"ES",
    "sg:address":"C/ Ferreries, De, 22",
    "sg:city":"Alaior",
    "sg:orig_category":"Mec\u00c1nico Del Autom\u00d3vil",
    "sg:phone":"+34 971 37 22 04",
    "sg:postcode":"07730",
    "sg:province":"Islas Baleares",
    "wof:name":"Pons Mercadal Jose",
    "wof:placetype":"venue"
},
  "geometry": {"coordinates":[4.1401391029,39.9297981262],"type":"Point"}
}