{
  "type": "Feature",
  "properties": {
    "addr:full":"Avda Jose M Rivero De Aguilar, 20 Vilagarcia Pontevedra 36600",
    "addr:housenumber":"20",
    "addr:postcode":"36600",
    "addr:street":"Avda Jose M Rivero De Aguilar",
    "iso:country":"ES",
    "sg:address":"Avda Jose M Rivero De Aguilar, 20",
    "sg:city":"Vilagarcia",
    "sg:orig_category":"Promotores Constructores",
    "sg:phone":"+34 986 50 93 04",
    "sg:postcode":"36600",
    "sg:province":"Pontevedra",
    "wof:name":"Poxectos Inmobiliarios Royco S.l.",
    "wof:placetype":"venue"
},
  "geometry": {"coordinates":[-8.7652978897,42.5917396545],"type":"Point"}
}