{
  "type": "Feature",
  "properties": {
    "iso:country":"ES",
    "sg:address":"Carrer de Fra Luis De Leon, 218",
    "sg:city":"Sabadell",
    "sg:orig_category":"Empresarios",
    "sg:phone":"+34 937 11 40 60",
    "sg:postcode":"08203",
    "sg:province":"Barcelona",
    "wof:name":"Prosell Obras Y Proyectos S.l.",
    "wof:placetype":"venue"
},
  "geometry": {"coordinates":[2.1158099174,41.5350418091],"type":"Point"}
}