{
  "type": "Feature",
  "properties": {
    "iso:country":"ES",
    "sg:address":"Calle de Jorge Juan, 68",
    "sg:city":"Madrid",
    "sg:orig_category":"Abogados",
    "sg:phone":"+34 914 31 79 60",
    "sg:postcode":"28009",
    "sg:province":"Madrid",
    "wof:name":"Martins Y Rubio Abogados S.l.",
    "wof:placetype":"venue"
},
  "geometry": {"coordinates":[-3.6776280403,40.423324585],"type":"Point"}
}