{
  "type": "Feature",
  "properties": {
    "addr:full":"Avda Eusebio Salvador Merino, S/n Herrera Pisuerga Palencia 34400",
    "addr:housenumber":"s",
    "addr:postcode":"34400",
    "addr:street":"Avda Eusebio Salvador Merino;/ N Herrera Pisuerga",
    "iso:country":"ES",
    "sg:address":"Avda Eusebio Salvador Merino, S/n",
    "sg:city":"Herrera Pisuerga",
    "sg:orig_category":"Arqueolog\u00cda Y Patrimonio Cultural",
    "sg:phone":"+34 979 13 05 19",
    "sg:postcode":"34400",
    "sg:province":"Palencia",
    "wof:name":"Instituto De Estudios Pisoraca",
    "wof:placetype":"venue"
},
  "geometry": {"coordinates":[-4.3312392235,42.591091156],"type":"Point"}
}