{
  "type": "Feature",
  "properties": {
    "addr:full":"Calle de Colon, 22 Alcorcon Madrid 28921",
    "addr:housenumber":"22",
    "addr:postcode":"28921",
    "addr:street":"Calle De Colon",
    "iso:country":"ES",
    "sg:address":"Calle de Colon, 22",
    "sg:city":"Alcorcon",
    "sg:orig_category":"Caf\u00c9s, Bares, Cervecer\u00cdas",
    "sg:phone":"+34 916 43 74 82",
    "sg:postcode":"28921",
    "sg:province":"Madrid",
    "wof:name":"Moya Redondo Francisco",
    "wof:placetype":"venue"
},
  "geometry": {"coordinates":[-3.8283996582,40.3468360901],"type":"Point"}
}