{
  "type": "Feature",
  "properties": {
    "addr:full":"Vallinas, S/n Vallinas Asturias 33819",
    "addr:postcode":"33819",
    "addr:street":"Vallinas S / N Vallinas Asturias",
    "iso:country":"ES",
    "sg:address":"Vallinas, S/n",
    "sg:city":"Vallinas",
    "sg:orig_category":"Industria Qu\u00cdmica",
    "sg:phone":"+34 985 81 31 89",
    "sg:postcode":"33819",
    "sg:province":"Asturias",
    "sg:website":"www.pirotecniapablo.com",
    "wof:name":"Pirotecnia Pablo S.l.",
    "wof:placetype":"venue"
},
  "geometry": {"coordinates":[-6.4327960014,43.2157478333],"type":"Point"}
}