{
  "type": "Feature",
  "properties": {
    "iso:country":"ES",
    "sg:address":"Avda Menendez Pelayo, 31",
    "sg:city":"Sevilla",
    "sg:orig_category":"Farmacias",
    "sg:phone":"+34 954 42 10 55",
    "sg:postcode":"41003",
    "sg:province":"Sevilla",
    "wof:name":"Wamba Carnicero Pedro",
    "wof:placetype":"venue"
},
  "geometry": {"coordinates":[-5.9852404594,37.387336731],"type":"Point"}
}