{
  "type": "Feature",
  "properties": {
    "iso:country":"ES",
    "sg:address":"Avgd Valencia, 13",
    "sg:city":"Muro Alcoy",
    "sg:orig_category":"M\u00c1rmoles, Granitos Y Piedras Naturales",
    "sg:phone":"+34 965 53 16 78",
    "sg:postcode":"03830",
    "sg:province":"Alicante",
    "wof:name":"Piedra A.muro C.b",
    "wof:placetype":"venue"
},
  "geometry": {"coordinates":[-0.4414289892,38.7812538147],"type":"Point"}
}