{
  "type": "Feature",
  "properties": {
    "addr:full":"Calle de Hospital (del), 26 Pinto Madrid 28320",
    "addr:postcode":"28320",
    "addr:street":"Calle De",
    "iso:country":"ES",
    "sg:address":"Calle de Hospital (del), 26",
    "sg:city":"Pinto",
    "sg:orig_category":"Inmobiliaria (agencias)",
    "sg:phone":"+34 916 92 88 10",
    "sg:postcode":"28320",
    "sg:province":"Madrid",
    "wof:name":"Londres Sur Comercializadora S.a.",
    "wof:placetype":"venue"
},
  "geometry": {"coordinates":[-3.6994390488,40.2426681519],"type":"Point"}
}