{
  "type": "Feature",
  "properties": {
    "addr:full":"Carr Palma, De, S/n Consell Islas Baleares 07330",
    "addr:housenumber":"/ n",
    "addr:postcode":"07330",
    "addr:street":"Carr Palma De S",
    "iso:country":"ES",
    "sg:address":"Carr Palma, De, S/n",
    "sg:city":"Consell",
    "sg:orig_category":"Fabrica De Cer\u00c1micas",
    "sg:phone":"+34 971 62 25 56",
    "sg:postcode":"07330",
    "sg:province":"Islas Baleares",
    "wof:name":"Amengual Salom Maria Francisca",
    "wof:placetype":"venue"
},
  "geometry": {"coordinates":[2.8096218109,39.6671943665],"type":"Point"}
}