{
  "type": "Feature",
  "properties": {
    "addr:full":"Calle de Van Gogh, 25 Campanillas M\u00e1laga 29590",
    "addr:housenumber":"25",
    "addr:postcode":"29590",
    "addr:street":"Calle De Van Gogh;Ma\u0301Laga",
    "iso:country":"ES",
    "sg:address":"Calle de Van Gogh, 25",
    "sg:city":"Campanillas",
    "sg:orig_category":"Carnicer\u00cdas, Carnicer\u00cdas",
    "sg:phone":"+34 952 62 51 65",
    "sg:postcode":"29590",
    "sg:province":"M\u00e1laga",
    "wof:name":"Macar J.e. S.l.",
    "wof:placetype":"venue"
},
  "geometry": {"coordinates":[-4.5224900246,36.7190055847],"type":"Point"}
}