{
  "type": "Feature",
  "properties": {
    "addr:full":"Avda Filipinas, 4 Madrid Madrid 28003",
    "addr:housenumber":"4",
    "addr:postcode":"28003",
    "addr:street":"Avda Filipinas",
    "iso:country":"ES",
    "sg:address":"Avda Filipinas, 4",
    "sg:city":"Madrid",
    "sg:orig_category":"Farmacias",
    "sg:phone":"+34 915 34 93 99",
    "sg:postcode":"28003",
    "sg:province":"Madrid",
    "wof:name":"Fernandez De Heredia Peche Luis",
    "wof:placetype":"venue"
},
  "geometry": {"coordinates":[-3.7124478817,40.4390792847],"type":"Point"}
}