{
  "type": "Feature",
  "properties": {
    "addr:full":"C/ Torres Quevedo, 39 Elche Alicante 03204",
    "addr:housenumber":"39",
    "addr:postcode":"03204",
    "addr:street":"C / Torres Quevedo",
    "iso:country":"ES",
    "sg:address":"C/ Torres Quevedo, 39",
    "sg:city":"Elche",
    "sg:orig_category":"Zapatos: Material, Suministros, Accesorios (fabricaci\u00d3n, Al Por Mayor)",
    "sg:phone":"+34 966 64 00 22",
    "sg:postcode":"03204",
    "sg:province":"Alicante",
    "wof:name":"Palomino Duran Juan Jose",
    "wof:placetype":"venue"
},
  "geometry": {"coordinates":[-0.7066559792,38.2615585327],"type":"Point"}
}