{
  "type": "Feature",
  "properties": {
    "addr:full":"Avda Menceyes (los), 4 Gracia Santa Cruz De Tenerife 38295",
    "addr:housenumber":"4",
    "addr:postcode":"38295",
    "addr:street":"Avda Menceyes Los",
    "iso:country":"ES",
    "sg:address":"Avda Menceyes (los), 4",
    "sg:city":"Gracia",
    "sg:orig_category":"Doctores En Medicina",
    "sg:phone":"+34 922 25 46 35",
    "sg:postcode":"38295",
    "sg:province":"Santa Cruz De Tenerife",
    "wof:name":"Lopez Roa Margarita",
    "wof:placetype":"venue"
},
  "geometry": {"coordinates":[-16.3025226593,28.4732723236],"type":"Point"}
}