{
  "type": "Feature",
  "properties": {
    "addr:full":"Partida Cabiscol, S/n Amposta Tarragona 43870",
    "addr:housenumber":"s / n",
    "addr:postcode":"43870",
    "addr:street":"Partida Cabiscol",
    "iso:country":"ES",
    "sg:address":"Partida Cabiscol, S/n",
    "sg:city":"Amposta",
    "sg:orig_category":"Billares Y Accesorios",
    "sg:phone":"+34 977 70 54 60",
    "sg:postcode":"43870",
    "sg:province":"Tarragona",
    "wof:name":"Aliau Arques Felix",
    "wof:placetype":"venue"
},
  "geometry": {"coordinates":[0.6298921704,40.683719635],"type":"Point"}
}