{
  "type": "Feature",
  "properties": {
    "addr:full":"Barr Euba, S/n Euba Vizcaya 48290",
    "addr:housenumber":"s / n",
    "addr:postcode":"48290",
    "iso:country":"ES",
    "sg:address":"Barr Euba, S/n",
    "sg:city":"Euba",
    "sg:orig_category":"Explotaci\u00d3n De Canteras",
    "sg:phone":"+34 946 73 05 92",
    "sg:postcode":"48290",
    "sg:province":"Vizcaya",
    "wof:name":"Barrenechea Aguirre Juan",
    "wof:placetype":"venue"
},
  "geometry": {"coordinates":[-2.6911990643,43.1808815002],"type":"Point"}
}