{
  "type": "Feature",
  "properties": {
    "iso:country":"ES",
    "sg:address":"Calle de Rosa De Los Vientos, 37",
    "sg:city":"Malaga",
    "sg:orig_category":"Vidrio, Fabricaci\u00d3n Y Comercio",
    "sg:phone":"+34 952 32 20 93",
    "sg:postcode":"29006",
    "sg:province":"M\u00e1laga",
    "wof:name":"Cristaleria Herrera Malaga S. A.",
    "wof:placetype":"venue"
},
  "geometry": {"coordinates":[-4.48478508,36.7103004456],"type":"Point"}
}