{
  "type": "Feature",
  "properties": {
    "iso:country":"ES",
    "sg:address":"Calle de Eliana, La, 6",
    "sg:city":"Vilamarxant",
    "sg:orig_category":"Tractores Agr\u00cdcolas Y Remolques",
    "sg:phone":"+34 962 71 03 36",
    "sg:postcode":"46191",
    "sg:province":"Valencia",
    "wof:name":"Cervera Santamaria Jose",
    "wof:placetype":"venue"
},
  "geometry": {"coordinates":[-0.6272540092,39.5677604675],"type":"Point"}
}