{
  "type": "Feature",
  "properties": {
    "iso:country":"ES",
    "sg:address":"C/ Cendra, 2",
    "sg:city":"Tarrega",
    "sg:orig_category":"Encuadernaci\u00d3n E Impresi\u00d3n De Folletos",
    "sg:phone":"+34 973 31 35 50",
    "sg:postcode":"25300",
    "sg:province":"Lleida",
    "wof:name":"Camps Pamies Maria",
    "wof:placetype":"venue"
},
  "geometry": {"coordinates":[1.1392489672,41.6462249756],"type":"Point"}
}