{
  "type": "Feature",
  "properties": {
    "iso:country":"ES",
    "sg:address":"Ctra Torrecardenas, 50",
    "sg:city":"Fuensanta -villa Ines",
    "sg:orig_category":"Reposter\u00cdas",
    "sg:phone":"+34 950 14 08 50",
    "sg:postcode":"04230",
    "sg:province":"Almer\u00eda",
    "wof:name":"Rosal Fron S.l.",
    "wof:placetype":"venue"
},
  "geometry": {"coordinates":[-2.4411959648,36.8665809631],"type":"Point"}
}