{
  "type": "Feature",
  "properties": {
    "iso:country":"ES",
    "sg:address":"Pase Galicia De, 5",
    "sg:city":"Donostia-san Sebastian",
    "sg:orig_category":"Arquitectos",
    "sg:phone":"+34 943 29 76 66",
    "sg:postcode":"20015",
    "sg:province":"Guip\u00f9zcoa",
    "wof:name":"Soroa Arquitectos S.l.",
    "wof:placetype":"venue"
},
  "geometry": {"coordinates":[-1.9561200142,43.3129272461],"type":"Point"}
}