{
  "type": "Feature",
  "properties": {
    "iso:country":"ES",
    "sg:address":"Avda Andalucia (de), 517",
    "sg:city":"Valdemoro",
    "sg:orig_category":"Frutas Y Legumbres Frescas (al Por Mayor)",
    "sg:phone":"+34 918 09 51 06",
    "sg:postcode":"28340",
    "sg:province":"Madrid",
    "wof:name":"Frutas Juan Navarro S.l.",
    "wof:placetype":"venue"
},
  "geometry": {"coordinates":[-3.6812589169,40.2075996399],"type":"Point"}
}