{
  "type": "Feature",
  "properties": {
    "addr:full":"Calle de Jose Manuel Pedregal, 3 Aviles Asturias 33401",
    "addr:housenumber":"3",
    "addr:postcode":"33401",
    "addr:street":"Calle De Jose Manuel Pedregal",
    "iso:country":"ES",
    "sg:address":"Calle de Jose Manuel Pedregal, 3",
    "sg:city":"Aviles",
    "sg:orig_category":"Ropa Para Se\u00d1oras Y Caballeros (al Por Menor)",
    "sg:phone":"+34 985 56 37 96",
    "sg:postcode":"33401",
    "sg:province":"Asturias",
    "wof:name":"Salgado Manso Cesareo",
    "wof:placetype":"venue"
},
  "geometry": {"coordinates":[-5.9259309769,43.5594558716],"type":"Point"}
}