{
  "type": "Feature",
  "properties": {
    "iso:country":"ES",
    "sg:address":"Calle de Velez Malaga, S/n",
    "sg:city":"Malaga",
    "sg:orig_category":"Restaurantes",
    "sg:phone":"+34 952 22 50 43",
    "sg:postcode":"29016",
    "sg:province":"M\u00e1laga",
    "wof:name":"Garcia Cortes Jose",
    "wof:placetype":"venue"
},
  "geometry": {"coordinates":[-4.4114642143,36.7184753418],"type":"Point"}
}