{
  "type": "Feature",
  "properties": {
    "iso:country":"ES",
    "sg:address":"Calle de Zamora, 54",
    "sg:city":"Salamanca",
    "sg:orig_category":"Alquiler De Casas Y Habitaciones Amuebladas",
    "sg:phone":"+34 923 26 53 55",
    "sg:postcode":"37002",
    "sg:province":"Salamanca",
    "wof:name":"Delgado Gil Lourdes",
    "wof:placetype":"venue"
},
  "geometry": {"coordinates":[-5.6637039185,40.967956543],"type":"Point"}
}