{
  "type": "Feature",
  "properties": {
    "iso:country":"ES",
    "sg:address":"Carrer de Monterols, 1",
    "sg:city":"Barcelona",
    "sg:orig_category":"Papeler\u00cdas, Librer\u00cdas",
    "sg:phone":"+34 932 03 29 39",
    "sg:postcode":"08034",
    "sg:province":"Barcelona",
    "wof:name":"Vidosa Gallastegui Ramon",
    "wof:placetype":"venue"
},
  "geometry": {"coordinates":[2.1221659184,41.3968544006],"type":"Point"}
}