{
  "type": "Feature",
  "properties": {
    "addr:full":"Carr Dr. Carles Pol I Aleu, 37 Sort Lleida 25560",
    "addr:housenumber":"37",
    "addr:postcode":"25560",
    "addr:street":"Carr Dr.;Pol;Aleu",
    "iso:country":"ES",
    "sg:address":"Carr Dr. Carles Pol I Aleu, 37",
    "sg:city":"Sort",
    "sg:orig_category":"Reparaciones Y Remolcado De Veh\u00cdculos",
    "sg:phone":"+34 973 62 00 54",
    "sg:postcode":"25560",
    "sg:province":"Lleida",
    "wof:name":"Nou Garage Esport S.l.",
    "wof:placetype":"venue"
},
  "geometry": {"coordinates":[1.1319500208,42.4144287109],"type":"Point"}
}