{
  "type": "Feature",
  "properties": {
    "addr:full":"Carrer de Costes De Farigola, 38 Sentmenat Barcelona 08181",
    "addr:housenumber":"38",
    "addr:postcode":"08181",
    "addr:street":"Carrer De Costes De Farigola",
    "iso:country":"ES",
    "sg:address":"Carrer de Costes De Farigola, 38",
    "sg:city":"Sentmenat",
    "sg:orig_category":"Promotores Constructores",
    "sg:phone":"+34 937 15 11 14",
    "sg:postcode":"08181",
    "sg:province":"Barcelona",
    "wof:name":"Construsol Sentmenat S.l.",
    "wof:placetype":"venue"
},
  "geometry": {"coordinates":[2.1389799118,41.608631134],"type":"Point"}
}