{
  "type": "Feature",
  "properties": {
    "addr:full":"Calle de Joaquin Coronel, 39 Elda Alicante 03600",
    "addr:housenumber":"39",
    "addr:postcode":"03600",
    "addr:street":"Calle De Joaquin Coronel",
    "iso:country":"ES",
    "sg:address":"Calle de Joaquin Coronel, 39",
    "sg:city":"Elda",
    "sg:orig_category":"Centros M\u00c9dicos Y Sociales, Dispensarios",
    "sg:phone":"+34 965 39 42 62",
    "sg:postcode":"03600",
    "sg:province":"Alicante",
    "wof:name":"Centro Medico Los Angeles Elda-petrel S.l.",
    "wof:placetype":"venue"
},
  "geometry": {"coordinates":[-0.788425982,38.4782447815],"type":"Point"}
}