{
  "type": "Feature",
  "properties": {
    "iso:country":"ES",
    "sg:address":"Calle de Eduardo Marquina, 16",
    "sg:city":"Avila",
    "sg:classifiers":[
        {
            "category":"Banks & Credit Unions",
            "subcategory":"Bureau De Change",
            "type":"Services"
        }
    ],
    "sg:phone":"+34 920 25 21 20",
    "sg:postcode":"05001",
    "sg:province":"\u00c1vila",
    "sg:tags":[
        "organismos",
        "control"
    ],
    "wof:name":"Asistencia Tecnica Industrial S.a.e.",
    "wof:placetype":"venue"
},
  "geometry": {"coordinates":[-4.692653656,40.656463623],"type":"Point"}
}