{
  "type": "Feature",
  "properties": {
    "addr:full":"Pais Lapido, 51 Noia La Coru\u00f1a 15200",
    "addr:housenumber":"51",
    "addr:postcode":"15200",
    "addr:street":"Pais Lapido;La Corun\u0303A",
    "iso:country":"ES",
    "sg:address":"Pais Lapido, 51",
    "sg:city":"Noia",
    "sg:orig_category":"Transporte En General",
    "sg:phone":"+34 981 82 02 95",
    "sg:postcode":"15200",
    "sg:province":"La Coru\u00f1a",
    "wof:name":"Corbal Ferreiro Jose",
    "wof:placetype":"venue"
},
  "geometry": {"coordinates":[-8.8883037567,42.788608551],"type":"Point"}
}