{
  "type": "Feature",
  "properties": {
    "iso:country":"ES",
    "sg:address":"Dblat. Farigola, 26",
    "sg:city":"Vilablareix",
    "sg:orig_category":"Empresas De Pintura Y Revestimientos",
    "sg:phone":"+34 972 24 13 78",
    "sg:postcode":"17180",
    "sg:province":"Girona",
    "wof:name":"Portulas Massana Narciso",
    "wof:placetype":"venue"
},
  "geometry": {"coordinates":[2.7989549637,41.9561538696],"type":"Point"}
}