{
  "type": "Feature",
  "properties": {
    "iso:country":"ES",
    "sg:address":"Plaz Callao, 4",
    "sg:city":"Madrid",
    "sg:classifiers":[
        {
            "category":"Cinema",
            "subcategory":"Movie Theater",
            "type":"Entertainment"
        }
    ],
    "sg:phone":"+34 915 21 99 00",
    "sg:postcode":"28013",
    "sg:province":"Madrid",
    "sg:tags":[
        "salas",
        "de",
        "cine"
    ],
    "wof:name":"Espectaculos Callao S.l.",
    "wof:placetype":"venue"
},
  "geometry": {"coordinates":[-3.7055690289,40.4203414917],"type":"Point"}
}