{
  "type": "Feature",
  "properties": {
    "iso:country":"ES",
    "sg:address":"Avda Costa, 133",
    "sg:city":"Gijon",
    "sg:orig_category":"Supermercados Y Hipermercados",
    "sg:phone":"+34 985 33 80 59",
    "sg:postcode":"33204",
    "sg:province":"Asturias",
    "wof:name":"Supermercados Oblanca S.l.",
    "wof:placetype":"venue"
},
  "geometry": {"coordinates":[-5.6493887901,43.5369110107],"type":"Point"}
}