{
  "type": "Feature",
  "properties": {
    "iso:country":"ES",
    "sg:address":"Carrer de Sant Jaume, 17",
    "sg:city":"Palma",
    "sg:orig_category":"Promotores Constructores",
    "sg:phone":"+34 971 72 78 06",
    "sg:postcode":"07012",
    "sg:province":"Islas Baleares",
    "wof:name":"Sant Jaume 17",
    "wof:placetype":"venue"
},
  "geometry": {"coordinates":[2.6476609707,39.5732345581],"type":"Point"}
}