{
  "type": "Feature",
  "properties": {
    "iso:country":"ES",
    "sg:address":"Av Pirineus, 10",
    "sg:city":"Figueres",
    "sg:orig_category":"Expertos Contables, Revisores De Cuentas",
    "sg:phone":"+34 972 50 19 09",
    "sg:postcode":"17600",
    "sg:province":"Girona",
    "wof:name":"Buixeda Isern Miguel",
    "wof:placetype":"venue"
},
  "geometry": {"coordinates":[2.9567120075,42.2633018494],"type":"Point"}
}