{
  "type": "Feature",
  "properties": {
    "addr:full":"Pl Sant Joan, 9 Vilafranca Penedes Barcelona 08720",
    "addr:housenumber":"9",
    "addr:postcode":"08720",
    "addr:street":"Pl Sant Joan;Penedes Barcelona",
    "iso:country":"ES",
    "sg:address":"Pl Sant Joan, 9",
    "sg:city":"Vilafranca Penedes",
    "sg:orig_category":"Ropa Para Se\u00d1oras Y Caballeros (al Por Menor)",
    "sg:phone":"+34 938 18 11 86",
    "sg:postcode":"08720",
    "sg:province":"Barcelona",
    "wof:name":"Jorba Bisbal Maria Gema",
    "wof:placetype":"venue"
},
  "geometry": {"coordinates":[1.6994730234,41.3456420898],"type":"Point"}
}