{
  "type": "Feature",
  "properties": {
    "iso:country":"ES",
    "sg:address":"Av. Arostegui, 21",
    "sg:city":"Iru\u00f1a",
    "sg:orig_category":"Empresas De Carpinter\u00cda Met\u00c1lica",
    "sg:phone":"+34 948 18 40 69",
    "sg:postcode":"31009",
    "sg:province":"Navarra",
    "wof:name":"Gomez Dominguez Miguel",
    "wof:placetype":"venue"
},
  "geometry": {"coordinates":[-1.6776020527,42.7961387634],"type":"Point"}
}