{
  "type": "Feature",
  "properties": {
    "addr:full":"Calle de Paloma, 2 Ciudad Real Ciudad Real 13001",
    "addr:housenumber":"2",
    "addr:postcode":"13001",
    "addr:street":"Calle De Paloma",
    "iso:country":"ES",
    "sg:address":"Calle de Paloma, 2",
    "sg:city":"Ciudad Real",
    "sg:orig_category":"Caf\u00c9s, Bares, Cervecer\u00cdas",
    "sg:phone":"+34 926 22 92 35",
    "sg:postcode":"13001",
    "sg:province":"Ciudad Real",
    "wof:name":"C.b. Hijos De Feliciano Rodriguez",
    "wof:placetype":"venue"
},
  "geometry": {"coordinates":[-3.9269139767,38.9852638245],"type":"Point"}
}