{
  "type": "Feature",
  "properties": {
    "addr:full":"Carretera Cordoba, S/n Pinos-puente Granada 18240",
    "addr:housenumber":"s / n",
    "addr:postcode":"18240",
    "addr:street":"Carretera Cordoba",
    "iso:country":"ES",
    "sg:address":"Carretera Cordoba, S/n",
    "sg:city":"Pinos-puente",
    "sg:orig_category":"Agentes, Concesionarios Y Sucursales De Veh\u00cdculos",
    "sg:phone":"+34 958 45 23 28",
    "sg:postcode":"18240",
    "sg:province":"Granada",
    "wof:name":"Comba Ferro Julio Antonio",
    "wof:placetype":"venue"
},
  "geometry": {"coordinates":[-3.7566990852,37.2546691895],"type":"Point"}
}