{
  "type": "Feature",
  "properties": {
    "addr:full":"Carrer de Montiu, 12 Montcada Centre Barcelona 08110",
    "addr:housenumber":"12",
    "addr:postcode":"08110",
    "addr:street":"Carrer De Montiu",
    "iso:country":"ES",
    "sg:address":"Carrer de Montiu, 12",
    "sg:city":"Montcada Centre",
    "sg:orig_category":"Partidos Pol\u00cdticos",
    "sg:phone":"+34 935 64 22 06",
    "sg:postcode":"08110",
    "sg:province":"Barcelona",
    "wof:name":"Partit Dels Comunistes De Catalunya",
    "wof:placetype":"venue"
},
  "geometry": {"coordinates":[2.1817660332,41.4890899658],"type":"Point"}
}