{
  "type": "Feature",
  "properties": {
    "iso:country":"ES",
    "sg:address":"Calle de San Pablo, 17",
    "sg:city":"Burgos",
    "sg:orig_category":"Farmacias",
    "sg:phone":"+34 947 26 13 25",
    "sg:postcode":"09002",
    "sg:province":"Burgos",
    "wof:name":"Marcos Torre Carmen",
    "wof:placetype":"venue"
},
  "geometry": {"coordinates":[-3.6988689899,42.3381996155],"type":"Point"}
}