{
  "type": "Feature",
  "properties": {
    "iso:country":"ES",
    "sg:address":"Calle de Sierra Salvada, 10",
    "sg:city":"Madrid",
    "sg:orig_category":"Contenedores (mercanc\u00cdas)",
    "sg:phone":"+34 917 78 62 66",
    "sg:postcode":"28038",
    "sg:province":"Madrid",
    "wof:name":"Sanchez Matias Gerardo",
    "wof:placetype":"venue"
},
  "geometry": {"coordinates":[-3.6523768902,40.3892631531],"type":"Point"}
}