{
  "type": "Feature",
  "properties": {
    "iso:country":"ES",
    "sg:address":"C/ Nord, 13",
    "sg:city":"Ripollet",
    "sg:orig_category":"Iglesias Cristianas Diversas",
    "sg:phone":"+34 935 80 17 68",
    "sg:postcode":"08291",
    "sg:province":"Barcelona",
    "wof:name":"Testigos Cristianos De Jehova",
    "wof:placetype":"venue"
},
  "geometry": {"coordinates":[2.1559700966,41.501449585],"type":"Point"}
}