{
  "type": "Feature",
  "properties": {
    "addr:full":"Ptge G Torrella (parti), 1 Palma Islas Baleares 07002",
    "addr:housenumber":"1",
    "addr:postcode":"07002",
    "addr:street":"Ptge G Torrella Parti",
    "iso:country":"ES",
    "sg:address":"Ptge G Torrella (parti), 1",
    "sg:city":"Palma",
    "sg:orig_category":"Ropa Para Caballeros (al Por Menor)",
    "sg:phone":"+34 971 71 65 02",
    "sg:postcode":"07002",
    "sg:province":"Islas Baleares",
    "wof:name":"Laver S. A.",
    "wof:placetype":"venue"
},
  "geometry": {"coordinates":[2.6474909782,39.5729827881],"type":"Point"}
}