{
  "type": "Feature",
  "properties": {
    "iso:country":"ES",
    "sg:address":"Carrer de Mossen Vall, 4",
    "sg:city":"Manresa",
    "sg:orig_category":"Teatros Y Salas De Espect\u00c1culos",
    "sg:phone":"+34 938 76 80 84",
    "sg:postcode":"08241",
    "sg:province":"Barcelona",
    "wof:name":"Espectaculos Minorisa S. A.",
    "wof:placetype":"venue"
},
  "geometry": {"coordinates":[1.8206750154,41.7218894958],"type":"Point"}
}