{
  "type": "Feature",
  "properties": {
    "addr:full":"Carrer de Aritjols, 16 Barcelona Barcelona 08016",
    "addr:housenumber":"16",
    "addr:postcode":"08016",
    "addr:street":"Carrer De Aritjols",
    "iso:country":"ES",
    "sg:address":"Carrer de Aritjols, 16",
    "sg:city":"Barcelona",
    "sg:orig_category":"Peluqueros: De Se\u00d1oras",
    "sg:phone":"+34 933 50 47 43",
    "sg:postcode":"08016",
    "sg:province":"Barcelona",
    "wof:name":"Ferrero Gracia Vicenta",
    "wof:placetype":"venue"
},
  "geometry": {"coordinates":[2.1822121143,41.4421043396],"type":"Point"}
}