{
  "type": "Feature",
  "properties": {
    "addr:full":"Poligono Industrial, S/n Inca Islas Baleares 07300",
    "addr:postcode":"07300",
    "addr:street":"Industrial S / N",
    "iso:country":"ES",
    "sg:address":"Poligono Industrial, S/n",
    "sg:city":"Inca",
    "sg:orig_category":"Zapatos (al Por Menor)",
    "sg:phone":"+34 902 36 45 98",
    "sg:postcode":"07300",
    "sg:province":"Islas Baleares",
    "sg:website":"www.camper.com",
    "wof:name":"Coflusa S.a.u.",
    "wof:placetype":"venue"
},
  "geometry": {"coordinates":[2.9209609032,39.7178268433],"type":"Point"}
}