{
  "type": "Feature",
  "properties": {
    "addr:full":"Ctra Candeleda, S/n Arenas San Pedro \u00c1vila 05400",
    "addr:housenumber":"s / n",
    "addr:postcode":"05400",
    "addr:street":"Ctra Candeleda;A\u0301Vila",
    "iso:country":"ES",
    "sg:address":"Ctra Candeleda, S/n",
    "sg:city":"Arenas San Pedro",
    "sg:orig_category":"Molduras, Junquillos, Listones Y Molduras Perforadas",
    "sg:phone":"+34 920 37 01 86",
    "sg:postcode":"05400",
    "sg:province":"\u00c1vila",
    "wof:name":"Plaza Colorado Julia",
    "wof:placetype":"venue"
},
  "geometry": {"coordinates":[-5.0920572281,40.2101097107],"type":"Point"}
}