{
  "type": "Feature",
  "properties": {
    "iso:country":"ES",
    "sg:address":"C/ Alfons Xii, 206",
    "sg:city":"Banyoles",
    "sg:orig_category":"Mec\u00c1nico Del Autom\u00d3vil",
    "sg:phone":"+34 972 57 02 43",
    "sg:postcode":"17820",
    "sg:province":"Girona",
    "wof:name":"Peiro-jorda S.l.",
    "wof:placetype":"venue"
},
  "geometry": {"coordinates":[2.7631690502,42.1246833801],"type":"Point"}
}