{
  "type": "Feature",
  "properties": {
    "addr:full":"Calle de San Lucas, 25 Almazora Castell\u00f3n 12550",
    "addr:housenumber":"25",
    "addr:postcode":"12550",
    "addr:street":"Calle De San Lucas",
    "iso:country":"ES",
    "sg:address":"Calle de San Lucas, 25",
    "sg:city":"Almazora",
    "sg:orig_category":"Centros De Coordinaci\u00d3n",
    "sg:phone":"+34 964 55 11 55",
    "sg:postcode":"12550",
    "sg:province":"Castell\u00f3n",
    "wof:name":"Hernandez Martin Jose Lorenzo",
    "wof:placetype":"venue"
},
  "geometry": {"coordinates":[-0.0620529987,39.9462280273],"type":"Point"}
}