{
  "type": "Feature",
  "properties": {
    "addr:full":"Avda Huertas (de Las), S/n Fuente Alamo Murcia 30320",
    "addr:postcode":"30320",
    "addr:street":"Avda Huertas De Las S / N",
    "iso:country":"ES",
    "sg:address":"Avda Huertas (de Las), S/n",
    "sg:city":"Fuente Alamo",
    "sg:orig_category":"Hormigonados",
    "sg:phone":"+34 968 59 72 33",
    "sg:postcode":"30320",
    "sg:province":"Murcia",
    "wof:name":"Garcia Diaz Antonio",
    "wof:placetype":"venue"
},
  "geometry": {"coordinates":[-1.1763139963,37.7182502747],"type":"Point"}
}