{
  "type": "Feature",
  "properties": {
    "addr:full":"La Garea, S/n Ortigueira La Coru\u00f1a 15330",
    "addr:housenumber":"s / n",
    "addr:postcode":"15330",
    "addr:street":"La Corun\u0303A",
    "iso:country":"ES",
    "sg:address":"La Garea, S/n",
    "sg:city":"Ortigueira",
    "sg:orig_category":"Distribuci\u00d3n De Petr\u00d3leo Y Derivados",
    "sg:phone":"+34 981 42 24 42",
    "sg:postcode":"15330",
    "sg:province":"La Coru\u00f1a",
    "wof:name":"Antonio Lopez Guntin Y Otros Cdad.",
    "wof:placetype":"venue"
},
  "geometry": {"coordinates":[-7.8177599907,43.6668701172],"type":"Point"}
}