{
  "type": "Feature",
  "properties": {
    "addr:full":"Av Lluis Companys, 8 Abrera Barcelona 08630",
    "addr:housenumber":"8",
    "addr:postcode":"08630",
    "addr:street":"Av Lluis Companys",
    "iso:country":"ES",
    "sg:address":"Av Lluis Companys, 8",
    "sg:city":"Abrera",
    "sg:orig_category":"Partidos Pol\u00cdticos",
    "sg:phone":"+34 937 70 72 48",
    "sg:postcode":"08630",
    "sg:province":"Barcelona",
    "wof:name":"Partit Dels Socialistes De Catalunya Psc-psoe",
    "wof:placetype":"venue"
},
  "geometry": {"coordinates":[1.9013589621,41.5159683228],"type":"Point"}
}