{
  "type": "Feature",
  "properties": {
    "addr:full":"Calle de Junco, 79 Malaga M\u00e1laga 29190",
    "addr:housenumber":"79",
    "addr:postcode":"29190",
    "addr:street":"Calle De Junco;Ma\u0301Laga",
    "iso:country":"ES",
    "sg:address":"Calle de Junco, 79",
    "sg:city":"Malaga",
    "sg:orig_category":"Centros Empresariales",
    "sg:phone":"+34 952 43 15 77",
    "sg:postcode":"29190",
    "sg:province":"M\u00e1laga",
    "wof:name":"Soto Y Velasco S.l.",
    "wof:placetype":"venue"
},
  "geometry": {"coordinates":[-4.4902100563,36.7424659729],"type":"Point"}
}