{
  "type": "Feature",
  "properties": {
    "addr:full":"Calle de Loiola, 4 Donostia-san Sebastian Guip\u00f9zcoa 20005",
    "addr:housenumber":"4",
    "addr:postcode":"20005",
    "addr:street":"Calle De Loiola",
    "iso:country":"ES",
    "sg:address":"Calle de Loiola, 4",
    "sg:city":"Donostia-san Sebastian",
    "sg:orig_category":"Asesor\u00cda Sobre Comunicaci\u00d3n De Empresas",
    "sg:phone":"+34 943 42 19 06",
    "sg:postcode":"20005",
    "sg:province":"Guip\u00f9zcoa",
    "wof:name":"Yrizar Llanos Ignacio",
    "wof:placetype":"venue"
},
  "geometry": {"coordinates":[-1.9832539558,43.3187789917],"type":"Point"}
}