{
  "type": "Feature",
  "properties": {
    "iso:country":"ES",
    "sg:address":"Avda Constitucion, 2",
    "sg:city":"Merida",
    "sg:orig_category":"Animales (al Por Menor)",
    "sg:phone":"+34 924 37 18 65",
    "sg:postcode":"06800",
    "sg:province":"Badajoz",
    "wof:name":"Hurtado Villegas Maria Del Rosario",
    "wof:placetype":"venue"
},
  "geometry": {"coordinates":[-6.3562850952,38.9114494324],"type":"Point"}
}