{
  "type": "Feature",
  "properties": {
    "addr:full":"Avda De Andalucia, 23 Santa Olalla Del Cala Huelva 21260",
    "addr:housenumber":"23",
    "addr:postcode":"21260",
    "addr:street":"Avda De Andalucia",
    "iso:country":"ES",
    "sg:address":"Avda De Andalucia, 23",
    "sg:city":"Santa Olalla Del Cala",
    "sg:orig_category":"Asesor\u00cda Sobre Comunicaci\u00d3n De Empresas",
    "sg:phone":"+34 959 19 04 43",
    "sg:postcode":"21260",
    "sg:province":"Huelva",
    "wof:name":"Hermoso Nu\u00f1ez Pedro",
    "wof:placetype":"venue"
},
  "geometry": {"coordinates":[-6.2283787727,37.9063682556],"type":"Point"}
}