{
  "type": "Feature",
  "properties": {
    "iso:country":"ES",
    "sg:address":"C/ Maria Cristina, 2",
    "sg:city":"Celra",
    "sg:orig_category":"Estancos",
    "sg:phone":"+34 972 49 41 71",
    "sg:postcode":"17460",
    "sg:province":"Girona",
    "wof:name":"Roca Coll Montserrat",
    "wof:placetype":"venue"
},
  "geometry": {"coordinates":[2.8789949417,42.0245780945],"type":"Point"}
}