{
  "type": "Feature",
  "properties": {
    "addr:full":"Avda Valladolid, 11 Valencia Valencia 46020",
    "addr:housenumber":"11",
    "addr:postcode":"46020",
    "addr:street":"Avda Valladolid",
    "iso:country":"ES",
    "sg:address":"Avda Valladolid, 11",
    "sg:city":"Valencia",
    "sg:orig_category":"Cajas De Ahorro",
    "sg:phone":"+34 963 62 45 11",
    "sg:postcode":"46020",
    "sg:province":"Valencia",
    "wof:name":"Caja De Ahorros De Valencia Castellon Y Alicante",
    "wof:placetype":"venue"
},
  "geometry": {"coordinates":[-0.3599720001,39.4891624451],"type":"Point"}
}