{
  "type": "Feature",
  "properties": {
    "iso:country":"ES",
    "sg:address":"Avda Mari\u00d1a (da), 40",
    "sg:city":"Vilagarcia",
    "sg:orig_category":"Asesor\u00cda Sobre Comunicaci\u00d3n De Empresas",
    "sg:phone":"+34 986 51 09 96",
    "sg:postcode":"36600",
    "sg:province":"Pontevedra",
    "wof:name":"Asega S.l.",
    "wof:placetype":"venue"
},
  "geometry": {"coordinates":[-8.7658100128,42.5980300903],"type":"Point"}
}