{
  "type": "Feature",
  "properties": {
    "iso:country":"ES",
    "sg:address":"Avda Salsidu, 12",
    "sg:city":"Algorta",
    "sg:orig_category":"Alumbrados",
    "sg:phone":"+34 944 30 81 07",
    "sg:postcode":"48991",
    "sg:province":"Vizcaya",
    "wof:name":"Esesumaga Azcorra Pedro",
    "wof:placetype":"venue"
},
  "geometry": {"coordinates":[-3.0090539455,43.3517303467],"type":"Point"}
}