{
  "type": "Feature",
  "properties": {
    "addr:full":"Carrer de Manigua, 47 Barcelona Barcelona 08027",
    "addr:housenumber":"47",
    "addr:postcode":"08027",
    "addr:street":"Carrer De Manigua",
    "iso:country":"ES",
    "sg:address":"Carrer de Manigua, 47",
    "sg:city":"Barcelona",
    "sg:orig_category":"Detectives, Agentes Investigadores Privados",
    "sg:phone":"+34 933 52 02 42",
    "sg:postcode":"08027",
    "sg:province":"Barcelona",
    "wof:name":"Bernal Neto Maria Amparo",
    "wof:placetype":"venue"
},
  "geometry": {"coordinates":[2.1796429157,41.4249839783],"type":"Point"}
}