{
  "type": "Feature",
  "properties": {
    "iso:country":"ES",
    "sg:address":"C/ Sant Joan, 2",
    "sg:city":"Manacor",
    "sg:orig_category":"Peluqueros: De Se\u00d1oras",
    "sg:phone":"+34 971 55 00 53",
    "sg:postcode":"07500",
    "sg:province":"Islas Baleares",
    "wof:name":"Jaume Girard Maria",
    "wof:placetype":"venue"
},
  "geometry": {"coordinates":[3.2044732571,39.5716247559],"type":"Point"}
}