{
  "type": "Feature",
  "properties": {
    "addr:full":"Carr Pintor Sorolla, 35 Gandia Valencia 46700",
    "addr:housenumber":"35",
    "addr:postcode":"46700",
    "addr:street":"Carr Pintor Sorolla;Valencia",
    "iso:country":"ES",
    "sg:address":"Carr Pintor Sorolla, 35",
    "sg:city":"Gandia",
    "sg:orig_category":"Peluqueros: De Se\u00d1oras",
    "sg:phone":"+34 962 86 37 88",
    "sg:postcode":"46700",
    "sg:province":"Valencia",
    "wof:name":"Signes Xaixo Rosario",
    "wof:placetype":"venue"
},
  "geometry": {"coordinates":[-0.1913339943,38.960735321],"type":"Point"}
}