{
  "type": "Feature",
  "properties": {
    "addr:full":"Avda Corts Valencianes, De Les, 37 Valencia Valencia 46015",
    "addr:housenumber":"37",
    "addr:postcode":"46015",
    "addr:street":"Avda Corts Valencianes De Les",
    "iso:country":"ES",
    "sg:address":"Avda Corts Valencianes, De Les, 37",
    "sg:city":"Valencia",
    "sg:orig_category":"Inmobiliaria (agencias)",
    "sg:phone":"+34 963 49 79 28",
    "sg:postcode":"46015",
    "sg:province":"Valencia",
    "wof:name":"A.d.c. 2000 Inmobiliaria S.l",
    "wof:placetype":"venue"
},
  "geometry": {"coordinates":[-0.4011006951,39.4920158386],"type":"Point"}
}