{
  "type": "Feature",
  "properties": {
    "iso:country":"ES",
    "sg:address":"Calle de Murcia, 37",
    "sg:city":"Paracuellos De Jarama",
    "sg:orig_category":"Laboratorios Farmac\u00c9uticos",
    "sg:phone":"+34 916 58 30 39",
    "sg:postcode":"28860",
    "sg:province":"Madrid",
    "wof:name":"Lundbeck Espa\u00d1a S.a.",
    "wof:placetype":"venue"
},
  "geometry": {"coordinates":[-3.5260622501,40.5049667358],"type":"Point"}
}