{
  "type": "Feature",
  "properties": {
    "iso:country":"ES",
    "sg:address":"Carrer de Miami, 49",
    "sg:city":"Reus",
    "sg:orig_category":"Supermercados Y Hipermercados",
    "sg:phone":"+34 977 75 78 65",
    "sg:postcode":"43205",
    "sg:province":"Tarragona",
    "sg:website":"www.capraboacasa.com",
    "wof:name":"Caprabo S.a.",
    "wof:placetype":"venue"
},
  "geometry": {"coordinates":[1.1058989763,41.1454162598],"type":"Point"}
}