{
  "type": "Feature",
  "properties": {
    "iso:country":"ES",
    "sg:address":"Carr Papa Juan Xxiii, 15",
    "sg:city":"Alcudia",
    "sg:orig_category":"Zapatos (al Por Menor)",
    "sg:phone":"+34 962 54 30 20",
    "sg:postcode":"46250",
    "sg:province":"Valencia",
    "wof:name":"Llobregat Bosch Rebeca",
    "wof:placetype":"venue"
},
  "geometry": {"coordinates":[-0.5076360106,39.1996307373],"type":"Point"}
}