{
  "type": "Feature",
  "properties": {
    "addr:full":"Avda Grecia, 27 Sevilla Sevilla 41012",
    "addr:housenumber":"27",
    "addr:postcode":"41012",
    "addr:street":"Avda Grecia",
    "iso:country":"ES",
    "sg:address":"Avda Grecia, 27",
    "sg:city":"Sevilla",
    "sg:orig_category":"Electricidad: Equipos Industriales, Componentes (fabricaci\u00d3n)",
    "sg:phone":"+34 954 23 18 74",
    "sg:postcode":"41012",
    "sg:province":"Sevilla",
    "wof:name":"Dicomat S.l.",
    "wof:placetype":"venue"
},
  "geometry": {"coordinates":[-5.9842391014,37.3505706787],"type":"Point"}
}