{
  "type": "Feature",
  "properties": {
    "iso:country":"ES",
    "sg:address":"Avda Pescadores (los), 61",
    "sg:city":"Alcala",
    "sg:orig_category":"Cine (distribuci\u00d3n)",
    "sg:phone":"+34 922 86 62 28",
    "sg:postcode":"38686",
    "sg:province":"Santa Cruz De Tenerife",
    "wof:name":"Guajara Cines S.l.",
    "wof:placetype":"venue"
},
  "geometry": {"coordinates":[-16.8293361664,28.2034664154],"type":"Point"}
}