{
  "type": "Feature",
  "properties": {
    "addr:full":"Calle de Carabela La Pinta, 6 Baiona Pontevedra 36300",
    "addr:housenumber":"6",
    "addr:postcode":"36300",
    "addr:street":"Calle De Carabela La Pinta",
    "iso:country":"ES",
    "sg:address":"Calle de Carabela La Pinta, 6",
    "sg:city":"Baiona",
    "sg:orig_category":"Peluqueros: De Se\u00d1oras",
    "sg:phone":"+34 986 35 57 55",
    "sg:postcode":"36300",
    "sg:province":"Pontevedra",
    "wof:name":"Gestido Lorenzo Mari Luz",
    "wof:placetype":"venue"
},
  "geometry": {"coordinates":[-8.8499956131,42.1204338074],"type":"Point"}
}