{
  "type": "Feature",
  "properties": {
    "addr:full":"Pase Santa Maria De La Cabeza, 21 Madrid Madrid 28045",
    "addr:housenumber":"21",
    "addr:postcode":"madrid;28045",
    "addr:street":"Cabeza",
    "iso:country":"ES",
    "sg:address":"Pase Santa Maria De La Cabeza, 21",
    "sg:city":"Madrid",
    "sg:orig_category":"Inform\u00c1tica (estudios, Servicios, Asesor\u00cda, Formaci\u00d3n)",
    "sg:phone":"+34 915 28 01 54",
    "sg:postcode":"28045",
    "sg:province":"Madrid",
    "wof:name":"Consultores Y Desarrolladores De Aplicaciones Informaticas S.l.",
    "wof:placetype":"venue"
},
  "geometry": {"coordinates":[-3.6949319839,40.405418396],"type":"Point"}
}