{
  "type": "Feature",
  "properties": {
    "addr:full":"Calle de Crucero De San Julian, 8 Burgos Burgos 09002",
    "addr:housenumber":"8",
    "addr:postcode":"09002",
    "addr:street":"Calle De Crucero De San Julian",
    "iso:country":"ES",
    "sg:address":"Calle de Crucero De San Julian, 8",
    "sg:city":"Burgos",
    "sg:orig_category":"Confecci\u00d3n De Botones",
    "sg:phone":"+34 947 25 62 48",
    "sg:postcode":"09002",
    "sg:province":"Burgos",
    "wof:name":"Boutibon S.l.",
    "wof:placetype":"venue"
},
  "geometry": {"coordinates":[-3.6904492378,42.3363571167],"type":"Point"}
}