{
  "type": "Feature",
  "properties": {
    "addr:full":"Carr Clos, 3 Igualada Barcelona 08700",
    "addr:housenumber":"3",
    "addr:postcode":"08700",
    "addr:street":"Carr Clos",
    "iso:country":"ES",
    "sg:address":"Carr Clos, 3",
    "sg:city":"Igualada",
    "sg:orig_category":"Inform\u00c1tica Equipo Y Programas (al Por Mayor)",
    "sg:phone":"+34 938 05 38 46",
    "sg:postcode":"08700",
    "sg:province":"Barcelona",
    "wof:name":"Io Grup S.c.p.",
    "wof:placetype":"venue"
},
  "geometry": {"coordinates":[1.6170699596,41.5795402527],"type":"Point"}
}