{
  "type": "Feature",
  "properties": {
    "iso:country":"ES",
    "sg:address":"Avda Aragon, 25",
    "sg:city":"Binefar",
    "sg:orig_category":"Ropa Para Se\u00d1oras (al Por Menor)",
    "sg:phone":"+34 974 42 83 69",
    "sg:postcode":"22500",
    "sg:province":"Huesca",
    "wof:name":"Ibarz Santolaria Maria Pilar",
    "wof:placetype":"venue"
},
  "geometry": {"coordinates":[0.2940570116,41.8512458801],"type":"Point"}
}