{
  "type": "Feature",
  "properties": {
    "addr:full":"Carrer de Neptu, 34 Barcelona Barcelona 08006",
    "addr:housenumber":"34",
    "addr:postcode":"08006",
    "addr:street":"Carrer De Neptu",
    "iso:country":"ES",
    "sg:address":"Carrer de Neptu, 34",
    "sg:city":"Barcelona",
    "sg:orig_category":"Inform\u00c1tica (estudios, Servicios, Asesor\u00cda, Formaci\u00d3n)",
    "sg:phone":"+34 932 37 02 13",
    "sg:postcode":"08006",
    "sg:province":"Barcelona",
    "sg:website":"www.protec.es",
    "wof:name":"Protec S.a.",
    "wof:placetype":"venue"
},
  "geometry": {"coordinates":[2.1540338993,41.3985595703],"type":"Point"}
}