{
  "type": "Feature",
  "properties": {
    "addr:full":"Av Carles Buigas (de), 10 Salou Tarragona 43840",
    "addr:housenumber":"10",
    "addr:postcode":"43840",
    "addr:street":"Av Carles Buigas De",
    "iso:country":"ES",
    "sg:address":"Av Carles Buigas (de), 10",
    "sg:city":"Salou",
    "sg:orig_category":"Art\u00cdculos De Regalo (al Por Menor)",
    "sg:phone":"+34 977 38 27 17",
    "sg:postcode":"43840",
    "sg:province":"Tarragona",
    "wof:name":"Gasol Rue Ramon",
    "wof:placetype":"venue"
},
  "geometry": {"coordinates":[1.1465929747,41.0727844238],"type":"Point"}
}