{
  "type": "Feature",
  "properties": {
    "addr:full":"Carrer de Figueral, 42 Ametlla Valles Barcelona 08480",
    "addr:housenumber":"42",
    "addr:postcode":"08480",
    "addr:street":"Carrer De Figueral",
    "iso:country":"ES",
    "sg:address":"Carrer de Figueral, 42",
    "sg:city":"Ametlla Valles",
    "sg:orig_category":"Tubos De Cart\u00d3n Y Papel",
    "sg:phone":"+34 938 43 13 03",
    "sg:postcode":"08480",
    "sg:province":"Barcelona",
    "wof:name":"Distribuidora Joan S.a.",
    "wof:placetype":"venue"
},
  "geometry": {"coordinates":[2.2544798851,41.6593093872],"type":"Point"}
}