{
  "type": "Feature",
  "properties": {
    "addr:full":"Calle de Santo Tome, 27 Toledo Toledo 45002",
    "addr:housenumber":"27",
    "addr:postcode":"45002",
    "addr:street":"Calle De Santo Tome",
    "iso:country":"ES",
    "sg:address":"Calle de Santo Tome, 27",
    "sg:city":"Toledo",
    "sg:orig_category":"Restaurantes",
    "sg:phone":"+34 925 21 63 24",
    "sg:postcode":"45002",
    "sg:province":"Toledo",
    "wof:name":"Gomez Sanchez Perfecto",
    "wof:placetype":"venue"
},
  "geometry": {"coordinates":[-4.02835989,39.8569564819],"type":"Point"}
}