{
  "type": "Feature",
  "properties": {
    "iso:country":"ES",
    "sg:address":"S. Vicente Ferrer, 34",
    "sg:city":"Lliria",
    "sg:orig_category":"Abogados",
    "sg:phone":"+34 962 78 25 30",
    "sg:postcode":"46160",
    "sg:province":"Valencia",
    "wof:name":"Torres Carpio Jose Miguel",
    "wof:placetype":"venue"
},
  "geometry": {"coordinates":[-0.595713973,39.6287155151],"type":"Point"}
}