{
  "type": "Feature",
  "properties": {
    "addr:full":"Calle de Molino, S/n Alameda Sagra Toledo 45240",
    "addr:housenumber":"s / n",
    "addr:postcode":"45240",
    "addr:street":"Calle De Molino;Sagra",
    "iso:country":"ES",
    "sg:address":"Calle de Molino, S/n",
    "sg:city":"Alameda Sagra",
    "sg:orig_category":"Aceites Y Grasas Alimentarias (fabricaci\u00d3n, Al Por Mayor)",
    "sg:phone":"+34 925 50 02 95",
    "sg:postcode":"45240",
    "sg:province":"Toledo",
    "wof:name":"Aceite De Oliva Virgen Hermanos Jerez S.l.",
    "wof:placetype":"venue"
},
  "geometry": {"coordinates":[-3.7974715233,40.01039505],"type":"Point"}
}