{
  "type": "Feature",
  "properties": {
    "addr:full":"Calle de Estacion De Basurtu, 5 Bilbao Vizcaya 48002",
    "addr:housenumber":"5",
    "addr:postcode":"48002",
    "addr:street":"Calle De Estacion De Basurtu",
    "iso:country":"ES",
    "sg:address":"Calle de Estacion De Basurtu, 5",
    "sg:city":"Bilbao",
    "sg:orig_category":"Molduras, Junquillos, Listones Y Molduras Perforadas",
    "sg:phone":"+34 944 27 30 50",
    "sg:postcode":"48002",
    "sg:province":"Vizcaya",
    "wof:name":"Suarez Garcia Jose",
    "wof:placetype":"venue"
},
  "geometry": {"coordinates":[-2.9509415627,43.2569160461],"type":"Point"}
}