{
  "type": "Feature",
  "properties": {
    "addr:full":"Calle de Antonio Martin Lopez, 6 San Fernando Las Palmas 35100",
    "addr:housenumber":"6",
    "addr:postcode":"35100",
    "addr:street":"Calle De Antonio Martin Lopez",
    "iso:country":"ES",
    "sg:address":"Calle de Antonio Martin Lopez, 6",
    "sg:city":"San Fernando",
    "sg:orig_category":"Restaurantes",
    "sg:phone":"+34 928 76 86 16",
    "sg:postcode":"35100",
    "sg:province":"Las Palmas",
    "wof:name":"Gertino S.l.",
    "wof:placetype":"venue"
},
  "geometry": {"coordinates":[-15.5837392807,28.090631485],"type":"Point"}
}