{
  "type": "Feature",
  "properties": {
    "iso:country":"ES",
    "sg:address":"Calle de Artasamina, 10",
    "sg:city":"Bilbao",
    "sg:orig_category":"Venta, Localizaci\u00d3n, Reparaci\u00d3n De Material E Instrumental M\u00c9dico",
    "sg:phone":"+34 944 00 09 94",
    "sg:postcode":"48007",
    "sg:province":"Vizcaya",
    "wof:name":"Sermebi, 97 S.l.",
    "wof:placetype":"venue"
},
  "geometry": {"coordinates":[-2.9268820286,43.2698516846],"type":"Point"}
}