{
  "type": "Feature",
  "properties": {
    "addr:full":"Plaz Doctor Felix Rodriguez De La Fuente, 2 San Juan De Aznalfarache Sevilla 41920",
    "addr:housenumber":"2",
    "addr:postcode":"41920",
    "addr:street":"Doctor Felix Rodriguez De La Fuente",
    "iso:country":"ES",
    "sg:address":"Plaz Doctor Felix Rodriguez De La Fuente, 2",
    "sg:city":"San Juan De Aznalfarache",
    "sg:orig_category":"Ropa Para Se\u00d1oras Y Caballeros (al Por Menor)",
    "sg:phone":"+34 954 76 40 52",
    "sg:postcode":"41920",
    "sg:province":"Sevilla",
    "wof:name":"Henares Bautista Joaquin",
    "wof:placetype":"venue"
},
  "geometry": {"coordinates":[-6.0358738899,37.3578987122],"type":"Point"}
}