{
  "type": "Feature",
  "properties": {
    "addr:full":"Avda Doce De Agosto, 9 Andujar Ja\u00e9n 23740",
    "addr:housenumber":"9",
    "addr:postcode":"23740",
    "addr:street":"Avda Doce De Agosto",
    "iso:country":"ES",
    "sg:address":"Avda Doce De Agosto, 9",
    "sg:city":"Andujar",
    "sg:orig_category":"Bisuteros (fabricaci\u00d3n, Al Por Mayor)",
    "sg:phone":"+34 953 50 26 29",
    "sg:postcode":"23740",
    "sg:province":"Ja\u00e9n",
    "wof:name":"Molina Sanchez Angel",
    "wof:placetype":"venue"
},
  "geometry": {"coordinates":[-4.0552101135,38.0388145447],"type":"Point"}
}