{
  "type": "Feature",
  "properties": {
    "iso:country":"ES",
    "sg:address":"Calle de Jose Jauregui, 8",
    "sg:city":"Salamanca",
    "sg:orig_category":"Cr\u00cda De Animales",
    "sg:phone":"+34 923 21 68 22",
    "sg:postcode":"37002",
    "sg:province":"Salamanca",
    "wof:name":"Arranz Porres Maria Del Carmen",
    "wof:placetype":"venue"
},
  "geometry": {"coordinates":[-5.6630935669,40.9694976807],"type":"Point"}
}