{
  "type": "Feature",
  "properties": {
    "iso:country":"ES",
    "sg:address":"Avda Europa, 19",
    "sg:city":"Pozuelo De Alarcon",
    "sg:orig_category":"Agentes Generales De Seguros",
    "sg:phone":"+34 913 51 70 44",
    "sg:postcode":"28224",
    "sg:province":"Madrid",
    "wof:name":"Scor Iberica Sucursal",
    "wof:placetype":"venue"
},
  "geometry": {"coordinates":[-3.7874910831,40.4409637451],"type":"Point"}
}