{
  "type": "Feature",
  "properties": {
    "addr:full":"Plaz San Cristobal, 1 Alacant Alicante 03...",
    "addr:housenumber":"1;03 ...",
    "addr:street":"Plaz San Cristobal;Alicante",
    "iso:country":"ES",
    "sg:address":"Plaz San Cristobal, 1",
    "sg:city":"Alacant",
    "sg:orig_category":"Ense\u00d1anza, Formaci\u00d3n Profesional: Aprendizaje",
    "sg:phone":"+34 965 14 85 00",
    "sg:postcode":"03...",
    "sg:province":"Alicante",
    "wof:name":"Suma Gestion Tributaria Diputacion Alicante",
    "wof:placetype":"venue"
},
  "geometry": {"coordinates":[-0.4840529859,38.3466491699],"type":"Point"}
}