{
  "type": "Feature",
  "properties": {
    "iso:country":"ES",
    "sg:address":"Pl Catalunya, 10",
    "sg:city":"Prat Llobregat",
    "sg:orig_category":"Zapatos (al Por Menor)",
    "sg:phone":"+34 933 70 48 05",
    "sg:postcode":"08820",
    "sg:province":"Barcelona",
    "wof:name":"Avila Parra Andres",
    "wof:placetype":"venue"
},
  "geometry": {"coordinates":[2.0924859047,41.3221054077],"type":"Point"}
}