{
  "type": "Feature",
  "properties": {
    "addr:full":"Cami Estacio, 8 Poal Lleida 25143",
    "addr:housenumber":"8",
    "addr:postcode":"25143",
    "addr:street":"Estacio",
    "iso:country":"ES",
    "sg:address":"Cami Estacio, 8",
    "sg:city":"Poal",
    "sg:orig_category":"Empresas De Demolici\u00d3n",
    "sg:phone":"+34 973 56 52 68",
    "sg:postcode":"25143",
    "sg:province":"Lleida",
    "wof:name":"Badia Lloan Custodio",
    "wof:placetype":"venue"
},
  "geometry": {"coordinates":[0.8557279706,41.6774978638],"type":"Point"}
}