{
  "type": "Feature",
  "properties": {
    "iso:country":"ES",
    "sg:address":"Avda San Jorge, 104",
    "sg:city":"Andorra",
    "sg:orig_category":"Centros Comerciales Y Grandes Tiendas",
    "sg:phone":"+34 978 84 39 42",
    "sg:postcode":"44500",
    "sg:province":"Teruel",
    "wof:name":"Alquezar Medina Francisco Javier",
    "wof:placetype":"venue"
},
  "geometry": {"coordinates":[-0.4446949959,40.9769973755],"type":"Point"}
}