{
  "type": "Feature",
  "properties": {
    "addr:full":"Pg Maritim Neptu, 69 Grau I Platja Valencia 46730",
    "addr:housenumber":"69",
    "addr:postcode":"46730",
    "addr:street":"Pg Maritim Neptu",
    "iso:country":"ES",
    "sg:address":"Pg Maritim Neptu, 69",
    "sg:city":"Grau I Platja",
    "sg:orig_category":"Abogados",
    "sg:phone":"+34 962 84 04 14",
    "sg:postcode":"46730",
    "sg:province":"Valencia",
    "wof:name":"Colomina Boti Emilio",
    "wof:placetype":"venue"
},
  "geometry": {"coordinates":[-0.1641820073,39.0060195923],"type":"Point"}
}