{
  "type": "Feature",
  "properties": {
    "iso:country":"ES",
    "sg:address":"Carr Custiol, 12",
    "sg:city":"Igualada",
    "sg:orig_category":"Fabricaci\u00d3n, Distribuci\u00d3n De Discos, V\u00cddeodiscos Y Musicassettes",
    "sg:phone":"+34 938 03 19 98",
    "sg:postcode":"08700",
    "sg:province":"Barcelona",
    "wof:name":"Ferrer Abad Maria Dolores",
    "wof:placetype":"venue"
},
  "geometry": {"coordinates":[1.6186749935,41.5787353516],"type":"Point"}
}