{
  "type": "Feature",
  "properties": {
    "iso:country":"ES",
    "sg:address":"Calle de Huesca, S/n",
    "sg:city":"Fonz",
    "sg:orig_category":"Cr\u00cda De Perros Y De Gatos",
    "sg:phone":"+34 974 41 24 86",
    "sg:postcode":"22422",
    "sg:province":"Huesca",
    "wof:name":"Delgado Garcia Blanca",
    "wof:placetype":"venue"
},
  "geometry": {"coordinates":[0.2617810071,42.0093231201],"type":"Point"}
}