{
  "type": "Feature",
  "properties": {
    "iso:country":"ES",
    "sg:address":"Pl Espanya, 5",
    "sg:city":"S. Joan Despi",
    "sg:orig_category":"Delegados, Agentes De Tr\u00c1nsito, Auxiliares De Transporte Internacional",
    "sg:phone":"+34 934 77 30 00",
    "sg:postcode":"08970",
    "sg:province":"Barcelona",
    "wof:name":"Servipont Cornella S.l.",
    "wof:placetype":"venue"
},
  "geometry": {"coordinates":[2.0743010044,41.368183136],"type":"Point"}
}