{
  "type": "Feature",
  "properties": {
    "addr:full":"Colegio, 20 Pedreguer Alicante 03750",
    "addr:housenumber":"20",
    "addr:postcode":"03750",
    "addr:street":"Colegio",
    "iso:country":"ES",
    "sg:address":"Colegio, 20",
    "sg:city":"Pedreguer",
    "sg:orig_category":"Fabricaci\u00d3n De Sobres, Bolsas Y Fundas",
    "sg:phone":"+34 965 76 05 55",
    "sg:postcode":"03750",
    "sg:province":"Alicante",
    "wof:name":"Vicosta S. L.",
    "wof:placetype":"venue"
},
  "geometry": {"coordinates":[0.0336409993,38.7958030701],"type":"Point"}
}