{
  "type": "Feature",
  "properties": {
    "iso:country":"ES",
    "sg:address":"Calle de Jardin, 4",
    "sg:city":"Aguadulce",
    "sg:orig_category":"Ingeniero",
    "sg:phone":"+34 950 34 95 62",
    "sg:postcode":"04720",
    "sg:province":"Almer\u00eda",
    "wof:name":"Indalo Vision C.b.",
    "wof:placetype":"venue"
},
  "geometry": {"coordinates":[-2.5752630234,36.8140602112],"type":"Point"}
}