{
  "type": "Feature",
  "properties": {
    "iso:country":"ES",
    "sg:address":"Rua Corzan, 13",
    "sg:city":"Negreira",
    "sg:orig_category":"M\u00c9dicos: Pediatr\u00cda. Enfermedades De Los Ni\u00d1os",
    "sg:phone":"+34 981 88 57 57",
    "sg:postcode":"15830",
    "sg:province":"La Coru\u00f1a",
    "wof:name":"Chewkey Rauas Marwan",
    "wof:placetype":"venue"
},
  "geometry": {"coordinates":[-8.7355337143,42.91147995],"type":"Point"}
}