{
  "type": "Feature",
  "properties": {
    "iso:country":"ES",
    "sg:address":"Las Eras, 15",
    "sg:city":"Zaragoza",
    "sg:orig_category":"Desinfecci\u00d3n, Desinsectaci\u00d3n, Desratizaci\u00d3n",
    "sg:phone":"+34 976 20 49 27",
    "sg:postcode":"50002",
    "sg:province":"Zaragoza",
    "wof:name":"Soluciones En Calidad Y Medio Ambiente S.l(secma",
    "wof:placetype":"venue"
},
  "geometry": {"coordinates":[-0.8721929789,41.6497383118],"type":"Point"}
}