{
  "type": "Feature",
  "properties": {
    "addr:full":"Pl. Mercado, S/n Vegadeo Asturias 33770",
    "addr:housenumber":"/ n",
    "addr:postcode":"33770",
    "addr:street":"Mercado S",
    "iso:country":"ES",
    "sg:address":"Pl. Mercado, S/n",
    "sg:city":"Vegadeo",
    "sg:orig_category":"Telas Y Sedas (al Por Menor)",
    "sg:phone":"+34 985 47 60 86",
    "sg:postcode":"33770",
    "sg:province":"Asturias",
    "wof:name":"Lopez Cancelas Hermelina",
    "wof:placetype":"venue"
},
  "geometry": {"coordinates":[-7.0507240295,43.464225769],"type":"Point"}
}