{
  "type": "Feature",
  "properties": {
    "addr:full":"Crta Ulldecona, Km. 0001,4 Vinaros Castell\u00f3n 12500",
    "addr:postcode":"12500",
    "addr:street":"Crta Ulldecona Km. 0001,4;Castello\u0301N",
    "iso:country":"ES",
    "sg:address":"Crta Ulldecona, Km. 0001,4",
    "sg:city":"Vinaros",
    "sg:orig_category":"Muebles, Minoristas",
    "sg:phone":"+34 964 45 45 51",
    "sg:postcode":"12500",
    "sg:province":"Castell\u00f3n",
    "wof:name":"Alsilac S.l.",
    "wof:placetype":"venue"
},
  "geometry": {"coordinates":[0.4408037066,40.501701355],"type":"Point"}
}