{
  "type": "Feature",
  "properties": {
    "iso:country":"ES",
    "sg:address":"Rua Preguntoiro (do), 16",
    "sg:city":"Santiago De Compostela",
    "sg:orig_category":"Zapatos (al Por Menor)",
    "sg:phone":"+34 981 58 25 06",
    "sg:postcode":"15704",
    "sg:province":"La Coru\u00f1a",
    "wof:name":"Romero Rodriguez Jose Ramon",
    "wof:placetype":"venue"
},
  "geometry": {"coordinates":[-8.542350769,42.8806304932],"type":"Point"}
}