{
  "type": "Feature",
  "properties": {
    "addr:full":"Calle de Galaroza, 6 Huelva Huelva 21006",
    "addr:housenumber":"6",
    "addr:postcode":"21006",
    "addr:street":"Calle De Galaroza",
    "iso:country":"ES",
    "sg:address":"Calle de Galaroza, 6",
    "sg:city":"Huelva",
    "sg:orig_category":"Agentes Generales De Seguros",
    "sg:phone":"+34 959 23 09 71",
    "sg:postcode":"21006",
    "sg:province":"Huelva",
    "wof:name":"Camacho Vargas Jose",
    "wof:placetype":"venue"
},
  "geometry": {"coordinates":[-6.931866169,37.2610626221],"type":"Point"}
}