{
  "type": "Feature",
  "properties": {
    "addr:full":"Calle de Manuel Bermudo Barrera, 3 Sevilla Sevilla 41004",
    "addr:housenumber":"3",
    "addr:postcode":"41004",
    "addr:street":"Calle De Manuel Bermudo Barrera",
    "iso:country":"ES",
    "sg:address":"Calle de Manuel Bermudo Barrera, 3",
    "sg:city":"Sevilla",
    "sg:orig_category":"Asesor\u00cda Sobre Comunicaci\u00d3n De Empresas",
    "sg:phone":"+34 954 09 12 07",
    "sg:postcode":"41004",
    "sg:province":"Sevilla",
    "wof:name":"Asinpe S.l.",
    "wof:placetype":"venue"
},
  "geometry": {"coordinates":[-5.9866743088,37.3817367554],"type":"Point"}
}