{
  "type": "Feature",
  "properties": {
    "iso:country":"ES",
    "sg:address":"Calle de Encrucijada, 11",
    "sg:city":"Maracena",
    "sg:orig_category":"Zapatos (al Por Menor)",
    "sg:phone":"+34 958 41 56 24",
    "sg:postcode":"18200",
    "sg:province":"Granada",
    "wof:name":"Moreno Jimenez Purificacion",
    "wof:placetype":"venue"
},
  "geometry": {"coordinates":[-3.6349210739,37.2066802979],"type":"Point"}
}