{
  "type": "Feature",
  "properties": {
    "iso:country":"ES",
    "sg:address":"Carrer de Solanes (les), S/n",
    "sg:city":"Mas Alba",
    "sg:orig_category":"Cerrajer\u00cda, Ferrallista",
    "sg:phone":"+34 938 94 48 99",
    "sg:postcode":"08810",
    "sg:province":"Barcelona",
    "wof:name":"Hernandez Gordon Juan Claudio",
    "wof:placetype":"venue"
},
  "geometry": {"coordinates":[1.8079710007,41.2609138489],"type":"Point"}
}