{
  "type": "Feature",
  "properties": {
    "addr:full":"Avgd German Sapi\u00d1a, 9 Cullera Valencia 46400",
    "addr:housenumber":"9",
    "addr:postcode":"46400",
    "addr:street":"Sapin\u0303A",
    "iso:country":"ES",
    "sg:address":"Avgd German Sapi\u00d1a, 9",
    "sg:city":"Cullera",
    "sg:orig_category":"Asociaciones Y Clubs Deportivos",
    "sg:phone":"+34 961 72 40 27",
    "sg:postcode":"46400",
    "sg:province":"Valencia",
    "wof:name":"Motoclub Cullera",
    "wof:placetype":"venue"
},
  "geometry": {"coordinates":[-0.2587139904,39.1657600403],"type":"Point"}
}