{
  "type": "Feature",
  "properties": {
    "iso:country":"ES",
    "sg:address":"Carrer de Castell, 74",
    "sg:city":"Palau-solita I Plegamans",
    "sg:orig_category":"Restaurantes",
    "sg:phone":"+34 938 64 46 46",
    "sg:postcode":"08184",
    "sg:province":"Barcelona",
    "wof:name":"Les Tentacions 2005 S.c.p.",
    "wof:placetype":"venue"
},
  "geometry": {"coordinates":[2.1805229187,41.587802887],"type":"Point"}
}