{
  "type": "Feature",
  "properties": {
    "iso:country":"ES",
    "sg:address":"Carrer de Muntaner, 84",
    "sg:city":"Barcelona",
    "sg:orig_category":"Supermercados Y Hipermercados",
    "sg:phone":"+34 934 54 83 04",
    "sg:postcode":"08011",
    "sg:province":"Barcelona",
    "sg:website":"www.miquel.es",
    "wof:name":"Miquel Alimentacio Grup S.a.",
    "wof:placetype":"venue"
},
  "geometry": {"coordinates":[2.1579220295,41.3879470825],"type":"Point"}
}