{
  "type": "Feature",
  "properties": {
    "addr:full":"Calle de Pelayo, 38 Madrid Madrid 28004",
    "addr:housenumber":"38",
    "addr:postcode":"madrid;28004",
    "addr:street":"Calle De Pelayo",
    "iso:country":"ES",
    "sg:address":"Calle de Pelayo, 38",
    "sg:city":"Madrid",
    "sg:classifiers":[
        {
            "category":"Arts & Performance",
            "subcategory":"Art Gallery",
            "type":"Entertainment"
        }
    ],
    "sg:phone":"+34 913 19 96 90",
    "sg:postcode":"28004",
    "sg:province":"Madrid",
    "sg:tags":[
        "arte",
        "de",
        "galer\u00cdas"
    ],
    "wof:name":"Bellas Artes Jeco S.l.",
    "wof:placetype":"venue"
},
  "geometry": {"coordinates":[-3.6978700161,40.4233779907],"type":"Point"}
}