{
  "type": "Feature",
  "properties": {
    "addr:full":"Avda Azorin, 48 Cieza Murcia 30530",
    "addr:housenumber":"48",
    "addr:postcode":"30530",
    "addr:street":"Avda Azorin",
    "iso:country":"ES",
    "sg:address":"Avda Azorin, 48",
    "sg:city":"Cieza",
    "sg:orig_category":"Centros Empresariales",
    "sg:phone":"+34 968 45 60 84",
    "sg:postcode":"30530",
    "sg:province":"Murcia",
    "wof:name":"Construcciones Y Mamposteria Almadenes S.l.",
    "wof:placetype":"venue"
},
  "geometry": {"coordinates":[-1.4125490189,38.2344169617],"type":"Point"}
}