{
  "type": "Feature",
  "properties": {
    "addr:full":"Ctra Murcia-alicante, Km. 0028,0 Orihuela Alicante 03300",
    "addr:postcode":"03300",
    "addr:street":"Ctra Murcia-Alicante Km. 0028,0",
    "iso:country":"ES",
    "sg:address":"Ctra Murcia-alicante, Km. 0028,0",
    "sg:city":"Orihuela",
    "sg:orig_category":"Art\u00cdculos De Madera (fabricaci\u00d3n Y Al Por Mayor)",
    "sg:phone":"+34 966 73 60 84",
    "sg:postcode":"03300",
    "sg:province":"Alicante",
    "wof:name":"Muebleria Sarabia S.l.",
    "wof:placetype":"venue"
},
  "geometry": {"coordinates":[-0.9448040128,38.0817642212],"type":"Point"}
}