{
  "type": "Feature",
  "properties": {
    "iso:country":"ES",
    "sg:address":"Calle de Secundino Esnaola, 7",
    "sg:city":"Donostia-san Sebastian",
    "sg:orig_category":"Ropa Para Se\u00d1oras Y Caballeros (al Por Menor)",
    "sg:phone":"+34 943 32 19 79",
    "sg:postcode":"20001",
    "sg:province":"Guip\u00f9zcoa",
    "wof:name":"Morenru Moda Y Complementos C.b.",
    "wof:placetype":"venue"
},
  "geometry": {"coordinates":[-1.9748719931,43.3225402832],"type":"Point"}
}