{
  "type": "Feature",
  "properties": {
    "iso:country":"ES",
    "sg:address":"Calle de Do\u00d1a Blanca, 13",
    "sg:city":"Jerez De La Frontera",
    "sg:orig_category":"Supermercados Y Hipermercados",
    "sg:phone":"+34 956 34 45 79",
    "sg:postcode":"11402",
    "sg:province":"C\u00e1diz",
    "wof:name":"Supermercados Champion S A",
    "wof:placetype":"venue"
},
  "geometry": {"coordinates":[-6.1352009773,36.6820831299],"type":"Point"}
}