{
  "type": "Feature",
  "properties": {
    "iso:country":"ES",
    "sg:address":"Calle de Platon, 1",
    "sg:city":"Albujon",
    "sg:orig_category":"Agencias Y Agentes Comerciales, Representantes",
    "sg:phone":"+34 968 55 01 87",
    "sg:postcode":"30330",
    "sg:province":"Murcia",
    "wof:name":"Perez Martinez Maria Isabel",
    "wof:placetype":"venue"
},
  "geometry": {"coordinates":[-1.0470769405,37.7176551819],"type":"Point"}
}