{
  "type": "Feature",
  "properties": {
    "addr:full":"Al-andalus, S/n Medina-sidonia C\u00e1diz 11170",
    "addr:housenumber":"s / n",
    "addr:postcode":"11170",
    "addr:street":"Medina-Sidonia Ca\u0301Diz",
    "iso:country":"ES",
    "sg:address":"Al-andalus, S/n",
    "sg:city":"Medina-sidonia",
    "sg:orig_category":"Sanatorios M\u00c9dico",
    "sg:phone":"+34 956 41 11 39",
    "sg:postcode":"11170",
    "sg:province":"C\u00e1diz",
    "wof:name":"Servicio Andaluz De Salud",
    "wof:placetype":"venue"
},
  "geometry": {"coordinates":[-5.9275169373,36.4657745361],"type":"Point"}
}