{
  "type": "Feature",
  "properties": {
    "iso:country":"ES",
    "sg:address":"C/ Pla De La Coromina, S/n",
    "sg:city":"Banyoles",
    "sg:orig_category":"Asesor\u00cda, Estudio Y Control Medioambiental",
    "sg:phone":"+34 972 57 25 16",
    "sg:postcode":"17820",
    "sg:province":"Girona",
    "wof:name":"Valderas Barranco Pedro Jose",
    "wof:placetype":"venue"
},
  "geometry": {"coordinates":[2.7795200348,42.1163368225],"type":"Point"}
}