{
  "type": "Feature",
  "properties": {
    "addr:full":"San Xian De Sales, S/n S.xian De Sales La Coru\u00f1a 15885",
    "addr:housenumber":"s",
    "addr:postcode":"15885",
    "addr:street":"/ N;Corun\u0303A",
    "iso:country":"ES",
    "sg:address":"San Xian De Sales, S/n",
    "sg:city":"S.xian De Sales",
    "sg:orig_category":"Empresarios",
    "sg:phone":"+34 981 51 16 29",
    "sg:postcode":"15885",
    "sg:province":"La Coru\u00f1a",
    "wof:name":"Ferro Louzao Jesus",
    "wof:placetype":"venue"
},
  "geometry": {"coordinates":[-8.481803894,42.7759590149],"type":"Point"}
}