{
  "type": "Feature",
  "properties": {
    "iso:country":"ES",
    "sg:address":"Ctra Caldes, Km. 0034,0",
    "sg:city":"Sentmenat",
    "sg:orig_category":"Promotores Constructores",
    "sg:phone":"+34 937 15 27 25",
    "sg:postcode":"08181",
    "sg:province":"Barcelona",
    "wof:name":"Wagmosa S L.",
    "wof:placetype":"venue"
},
  "geometry": {"coordinates":[2.1361973286,41.6073608398],"type":"Point"}
}