{
  "type": "Feature",
  "properties": {
    "addr:full":"La Iglesia, 17 Fuentearmegil Soria 42143",
    "addr:housenumber":"17",
    "addr:postcode":"42143",
    "addr:street":"Iglesia",
    "iso:country":"ES",
    "sg:address":"La Iglesia, 17",
    "sg:city":"Fuentearmegil",
    "sg:orig_category":"Material Y Herramientas Agr\u00cdcolas",
    "sg:phone":"+34 975 37 50 43",
    "sg:postcode":"42143",
    "sg:province":"Soria",
    "wof:name":"Cabrerizo Cabrerizo German",
    "wof:placetype":"venue"
},
  "geometry": {"coordinates":[-3.2247800827,41.6958427429],"type":"Point"}
}