{
  "type": "Feature",
  "properties": {
    "addr:full":"Avda Monasterio De Silos, S/n Madrid Madrid 28049",
    "addr:housenumber":"s / n",
    "addr:postcode":"28049",
    "addr:street":"Avda Monasterio De Silos",
    "iso:country":"ES",
    "sg:address":"Avda Monasterio De Silos, S/n",
    "sg:city":"Madrid",
    "sg:orig_category":"Aguas (distribuci\u00d3n, Servicios)",
    "sg:phone":"+34 917 36 27 68",
    "sg:postcode":"28049",
    "sg:province":"Madrid",
    "wof:name":"Femaral S.l.",
    "wof:placetype":"venue"
},
  "geometry": {"coordinates":[-3.6910989285,40.5106811523],"type":"Point"}
}