{
  "type": "Feature",
  "properties": {
    "iso:country":"ES",
    "sg:address":"Rua Faustino Miguez, 4",
    "sg:city":"Ourense",
    "sg:orig_category":"Fisioterapia",
    "sg:phone":"+34 988 25 25 64",
    "sg:postcode":"32002",
    "sg:province":"Ourense",
    "wof:name":"Melfi  Ingrid",
    "wof:placetype":"venue"
},
  "geometry": {"coordinates":[-7.8719792366,42.3406715393],"type":"Point"}
}