{
  "type": "Feature",
  "properties": {
    "addr:full":"Pg Barcelona, 12 Olot Girona 17800",
    "addr:housenumber":"12",
    "addr:postcode":"17800",
    "addr:street":"Pg Barcelona",
    "iso:country":"ES",
    "sg:address":"Pg Barcelona, 12",
    "sg:city":"Olot",
    "sg:orig_category":"Ense\u00d1anza: Idiomas",
    "sg:phone":"+34 972 26 01 10",
    "sg:postcode":"17800",
    "sg:province":"Girona",
    "wof:name":"Valverde Argelich Ruth",
    "wof:placetype":"venue"
},
  "geometry": {"coordinates":[2.4834189415,42.1783599854],"type":"Point"}
}