{
  "type": "Feature",
  "properties": {
    "iso:country":"ES",
    "sg:address":"Calle de Mariscal Gutierrez De Otero, 3",
    "sg:city":"Madrid",
    "sg:orig_category":"Mec\u00c1nico Del Autom\u00d3vil",
    "sg:phone":"+34 917 97 01 34",
    "sg:postcode":"28021",
    "sg:province":"Madrid",
    "wof:name":"Moreno Gomez Javier",
    "wof:placetype":"venue"
},
  "geometry": {"coordinates":[-3.7059900761,40.345500946],"type":"Point"}
}