{
  "type": "Feature",
  "properties": {
    "addr:full":"Avgd Rei Juan Carlos I, 6 Vila Joiosa Alicante 03570",
    "addr:housenumber":"6",
    "addr:postcode":"03570",
    "addr:street":"Juan Carlos I",
    "iso:country":"ES",
    "sg:address":"Avgd Rei Juan Carlos I, 6",
    "sg:city":"Vila Joiosa",
    "sg:orig_category":"Peluqueros: De Se\u00d1oras",
    "sg:phone":"+34 965 89 00 86",
    "sg:postcode":"03570",
    "sg:province":"Alicante",
    "wof:name":"Sanchez Lloret Maria Vicenta",
    "wof:placetype":"venue"
},
  "geometry": {"coordinates":[-0.7466139793,38.3102035522],"type":"Point"}
}