{
  "type": "Feature",
  "properties": {
    "iso:country":"ES",
    "sg:address":"Calle de Carrera Chica, S/n",
    "sg:city":"Villafranca De Los Barros",
    "sg:orig_category":"Pod\u00d3logos: Pedicuros",
    "sg:phone":"+34 924 52 62 00",
    "sg:postcode":"06220",
    "sg:province":"Badajoz",
    "wof:name":"Mena Miranda Antonio Miguel",
    "wof:placetype":"venue"
},
  "geometry": {"coordinates":[-6.3419456482,38.5610046387],"type":"Point"}
}