{
  "type": "Feature",
  "properties": {
    "addr:full":"Carrer de Major, 8 S. Esteve Sesrovires Barcelona 08635",
    "addr:housenumber":"8",
    "addr:postcode":"08635",
    "addr:street":"Carrer De Major",
    "iso:country":"ES",
    "sg:address":"Carrer de Major, 8",
    "sg:city":"S. Esteve Sesrovires",
    "sg:orig_category":"Administraciones Regionales, Departamentales Y Locales",
    "sg:phone":"+34 937 71 30 17",
    "sg:postcode":"08635",
    "sg:province":"Barcelona",
    "wof:name":"Ajuntament De Sant Esteve De Sesrovires",
    "wof:placetype":"venue"
},
  "geometry": {"coordinates":[1.8742573261,41.4930267334],"type":"Point"}
}