{
  "type": "Feature",
  "properties": {
    "addr:full":"Rua Castelao, 43 Lugo Lugo 27001",
    "addr:housenumber":"43",
    "addr:postcode":"27001",
    "addr:street":"Rua Castelao",
    "iso:country":"ES",
    "sg:address":"Rua Castelao, 43",
    "sg:city":"Lugo",
    "sg:classifiers":[
        {
            "category":"Cinema",
            "subcategory":"Movie Theater",
            "type":"Entertainment"
        }
    ],
    "sg:phone":"+34 982 25 03 94",
    "sg:postcode":"27001",
    "sg:province":"Lugo",
    "sg:tags":[
        "salas",
        "de",
        "cine"
    ],
    "wof:name":"Oliveros Cine S.l.",
    "wof:placetype":"venue"
},
  "geometry": {"coordinates":[-7.5540390015,43.0144538879],"type":"Point"}
}