{
  "type": "Feature",
  "properties": {
    "addr:full":"Calle de Tizona, 6 Majadahonda Madrid 28220",
    "addr:housenumber":"6",
    "addr:postcode":"28220",
    "addr:street":"Calle De Tizona",
    "iso:country":"ES",
    "sg:address":"Calle de Tizona, 6",
    "sg:city":"Majadahonda",
    "sg:classifiers":[
        {
            "category":"Personal",
            "subcategory":"Barber",
            "type":"Services"
        }
    ],
    "sg:phone":"+34 916 38 35 33",
    "sg:postcode":"28220",
    "sg:province":"Madrid",
    "sg:tags":[
        "caballeros",
        "de",
        "peluqueros"
    ],
    "wof:name":"Ayuga Herrera Juan",
    "wof:placetype":"venue"
},
  "geometry": {"coordinates":[-3.8707466125,40.4706420898],"type":"Point"}
}