{
  "type": "Feature",
  "properties": {
    "addr:full":"Pase Calanda, 19 Zaragoza Zaragoza 50010",
    "addr:housenumber":"19",
    "addr:postcode":"50010",
    "addr:street":"Calanda",
    "iso:country":"ES",
    "sg:address":"Pase Calanda, 19",
    "sg:city":"Zaragoza",
    "sg:orig_category":"Radiocomunicaciones, Telefon\u00cda M\u00d3vil, Radiomensajer\u00cda: Servicios, Comercializaci\u00d3n",
    "sg:phone":"+34 976 31 32 11",
    "sg:postcode":"50010",
    "sg:province":"Zaragoza",
    "sg:website":"www.telyco.es",
    "wof:name":"Teleinformatica Y Comunicaciones S.a.",
    "wof:placetype":"venue"
},
  "geometry": {"coordinates":[-0.9038419724,41.6526641846],"type":"Point"}
}