{
  "type": "Feature",
  "properties": {
    "iso:country":"ES",
    "sg:address":"Calle de Llaviada, 3",
    "sg:city":"Oviedo",
    "sg:orig_category":"Alquiler De V\u00cddeo",
    "sg:phone":"+34 985 11 04 85",
    "sg:postcode":"33011",
    "sg:province":"Asturias",
    "wof:name":"Alvarez Sala Y Florez S.l.",
    "wof:placetype":"venue"
},
  "geometry": {"coordinates":[-5.8166060448,43.385723114],"type":"Point"}
}