{
  "type": "Feature",
  "properties": {
    "iso:country":"ES",
    "sg:address":"Rbla Rambla, 174",
    "sg:city":"Sabadell",
    "sg:orig_category":"Ense\u00d1ante, Direcci\u00d3n",
    "sg:phone":"+34 937 25 09 73",
    "sg:postcode":"08201",
    "sg:province":"Barcelona",
    "wof:name":"Martin Delgado Jose Luis",
    "wof:placetype":"venue"
},
  "geometry": {"coordinates":[2.11135602,41.5414390564],"type":"Point"}
}