{
  "type": "Feature",
  "properties": {
    "addr:full":"Ctra Carballi\u00d1o (a), S/n San Cristovo Ourense 32416",
    "addr:housenumber":"s / n",
    "addr:postcode":"32416",
    "addr:street":"Ctra Carballin\u0303O A",
    "iso:country":"ES",
    "sg:address":"Ctra Carballi\u00d1o (a), S/n",
    "sg:city":"San Cristovo",
    "sg:orig_category":"Carnicer\u00cdas, Carnicer\u00cdas",
    "sg:phone":"+34 988 47 17 03",
    "sg:postcode":"32416",
    "sg:province":"Ourense",
    "wof:name":"Rivas Guntin Julio",
    "wof:placetype":"venue"
},
  "geometry": {"coordinates":[-8.1273260117,42.3060646057],"type":"Point"}
}