{
  "type": "Feature",
  "properties": {
    "iso:country":"ES",
    "sg:address":"Calle de Adolfo Diaz Ambrona, 34",
    "sg:city":"Villanueva Serena",
    "sg:orig_category":"Inform\u00c1tica (estudios, Servicios, Asesor\u00cda, Formaci\u00d3n)",
    "sg:phone":"+34 924 84 56 30",
    "sg:postcode":"06700",
    "sg:province":"Badajoz",
    "wof:name":"Gesproemsa S.l.",
    "wof:placetype":"venue"
},
  "geometry": {"coordinates":[-5.7976813316,38.9729728699],"type":"Point"}
}