{
  "type": "Feature",
  "properties": {
    "iso:country":"ES",
    "sg:address":"Mayor, 64",
    "sg:city":"Gares",
    "sg:orig_category":"Molduras, Junquillos, Listones Y Molduras Perforadas",
    "sg:phone":"+34 948 34 00 61",
    "sg:postcode":"31100",
    "sg:province":"Navarra",
    "wof:name":"Francisco Javier Lopez Polo Y Asun Sola Imaz",
    "wof:placetype":"venue"
},
  "geometry": {"coordinates":[-1.8161309958,42.6716537476],"type":"Point"}
}