{
  "type": "Feature",
  "properties": {
    "iso:country":"ES",
    "sg:address":"Carrer de Trinxant, 134",
    "sg:city":"Barcelona",
    "sg:orig_category":"Prendas Y Chalecos De Punto (al Por Menor)",
    "sg:phone":"+34 933 52 58 12",
    "sg:postcode":"08041",
    "sg:province":"Barcelona",
    "wof:name":"Comercial Calypreu S.a.l.",
    "wof:placetype":"venue"
},
  "geometry": {"coordinates":[2.1816909313,41.4177284241],"type":"Point"}
}