{
  "type": "Feature",
  "properties": {
    "iso:country":"ES",
    "sg:address":"Calle de Buenavista, 47",
    "sg:city":"Coin",
    "sg:orig_category":"Fabricaci\u00d3n, Importaci\u00d3n, Venta De Material De Telefon\u00cda, Peritelefon\u00cda",
    "sg:phone":"+34 952 45 40 28",
    "sg:postcode":"29100",
    "sg:province":"M\u00e1laga",
    "wof:name":"Telefonia Francisco Galvez S.l",
    "wof:placetype":"venue"
},
  "geometry": {"coordinates":[-4.7570590973,36.6594200134],"type":"Point"}
}