{
  "type": "Feature",
  "properties": {
    "iso:country":"ES",
    "sg:address":"Arane Kalea, 6",
    "sg:city":"Eibar",
    "sg:orig_category":"Suministros Para Carrocer\u00cdas",
    "sg:phone":"+34 943 70 26 20",
    "sg:postcode":"20600",
    "sg:province":"Guip\u00f9zcoa",
    "wof:name":"Garcia De Pedro Felix",
    "wof:placetype":"venue"
},
  "geometry": {"coordinates":[-2.464756012,43.1844100952],"type":"Point"}
}