{
  "type": "Feature",
  "properties": {
    "iso:country":"ES",
    "sg:address":"Ctra N-iv Madrid-cadiz, Km. 0117,8",
    "sg:city":"Madridejos",
    "sg:orig_category":"Mec\u00c1nico Del Autom\u00d3vil",
    "sg:phone":"+34 925 46 03 86",
    "sg:postcode":"45710",
    "sg:province":"Toledo",
    "wof:name":"Autos Pedro S.l.l.",
    "wof:placetype":"venue"
},
  "geometry": {"coordinates":[-3.5295538902,39.4659385681],"type":"Point"}
}