{
  "type": "Feature",
  "properties": {
    "addr:full":"Carrer de Merce, 18 Premia Mar Barcelona 08330",
    "addr:housenumber":"18",
    "addr:postcode":"08330",
    "addr:street":"Carrer De Merce",
    "iso:country":"ES",
    "sg:address":"Carrer de Merce, 18",
    "sg:city":"Premia Mar",
    "sg:orig_category":"Delineantes",
    "sg:phone":"+34 937 52 39 43",
    "sg:postcode":"08330",
    "sg:province":"Barcelona",
    "wof:name":"Blue Channel S.l",
    "wof:placetype":"venue"
},
  "geometry": {"coordinates":[2.3540370464,41.4945106506],"type":"Point"}
}