{
  "type": "Feature",
  "properties": {
    "iso:country":"ES",
    "sg:address":"Carr Ferrocarril D'alcoi, 104",
    "sg:city":"Gandia",
    "sg:classifiers":[
        {
            "category":"Personal",
            "subcategory":"Barber",
            "type":"Services"
        }
    ],
    "sg:phone":"+34 962 87 51 70",
    "sg:postcode":"46700",
    "sg:province":"Valencia",
    "sg:tags":[
        "caballeros",
        "de",
        "peluqueros"
    ],
    "wof:name":"Gadea Pedro Francisco Vicente",
    "wof:placetype":"venue"
},
  "geometry": {"coordinates":[-0.1845992953,38.9679794312],"type":"Point"}
}