{
  "type": "Feature",
  "properties": {
    "addr:full":"Calle de Tierra, 7 Valladolid Valladolid 47009",
    "addr:housenumber":"7",
    "addr:postcode":"47009",
    "addr:street":"Calle De Tierra",
    "iso:country":"ES",
    "sg:address":"Calle de Tierra, 7",
    "sg:city":"Valladolid",
    "sg:orig_category":"Asesor\u00cda Fiscal Y Jur\u00cddica",
    "sg:phone":"+34 983 37 57 58",
    "sg:postcode":"47009",
    "sg:province":"Valladolid",
    "wof:name":"Gallego Gomez Tomas Ignacio",
    "wof:placetype":"venue"
},
  "geometry": {"coordinates":[-4.7339100838,41.6647109985],"type":"Point"}
}