{
  "type": "Feature",
  "properties": {
    "iso:country":"ES",
    "sg:address":"Plaz Espa\u00d1a (de), 5",
    "sg:city":"Santiago",
    "sg:orig_category":"Compraventa De Antig\u00dcedades",
    "sg:phone":"+34 968 46 99 16",
    "sg:postcode":"30800",
    "sg:province":"Murcia",
    "wof:name":"Molina Martinez Miguel",
    "wof:placetype":"venue"
},
  "geometry": {"coordinates":[-1.6905640364,37.680557251],"type":"Point"}
}