{
  "type": "Feature",
  "properties": {
    "iso:country":"ES",
    "sg:address":"Calle de Mira El Rio Alta, 14",
    "sg:city":"Madrid",
    "sg:orig_category":"Compraventa De Antig\u00dcedades",
    "sg:phone":"+34 913 65 97 07",
    "sg:postcode":"28005",
    "sg:province":"Madrid",
    "wof:name":"Gamella Rodriguez Luis",
    "wof:placetype":"venue"
},
  "geometry": {"coordinates":[-3.7098479271,40.4087982178],"type":"Point"}
}