{
  "type": "Feature",
  "properties": {
    "addr:full":"Calle de Sevilla, 14 Valencia Valencia 46006",
    "addr:housenumber":"14",
    "addr:postcode":"46006",
    "addr:street":"Calle De Sevilla",
    "iso:country":"ES",
    "sg:address":"Calle de Sevilla, 14",
    "sg:city":"Valencia",
    "sg:orig_category":"Empresas De Carpinter\u00cda De Madera",
    "sg:phone":"+34 963 41 48 12",
    "sg:postcode":"46006",
    "sg:province":"Valencia",
    "wof:name":"Jose Luis Sanchis Perez S.l.",
    "wof:placetype":"venue"
},
  "geometry": {"coordinates":[-0.3741419911,39.4636192322],"type":"Point"}
}