{
  "type": "Feature",
  "properties": {
    "iso:country":"ES",
    "sg:address":"Calle de Doctor Thebussem, 5",
    "sg:city":"Medina-sidonia",
    "sg:orig_category":"Ense\u00d1anza Variada",
    "sg:phone":"+34 956 41 15 59",
    "sg:postcode":"11170",
    "sg:province":"C\u00e1diz",
    "wof:name":"Mu\u00f1oz Gonzalez Maria",
    "wof:placetype":"venue"
},
  "geometry": {"coordinates":[-5.9278473854,36.4584960938],"type":"Point"}
}