{
  "type": "Feature",
  "properties": {
    "iso:country":"ES",
    "sg:address":"Calle de Bravo Murillo, 179",
    "sg:city":"Madrid",
    "sg:orig_category":"Caf\u00c9s, Bares, Cervecer\u00cdas",
    "sg:phone":"+34 914 50 28 67",
    "sg:postcode":"28020",
    "sg:province":"Madrid",
    "wof:name":"Cafeteria Cerveceria Estrecho Cb",
    "wof:placetype":"venue"
},
  "geometry": {"coordinates":[-3.7030086517,40.4534606934],"type":"Point"}
}