{
  "type": "Feature",
  "properties": {
    "addr:full":"Rua Alcalde Hevia (do), 9 Pontevedra Pontevedra 36003",
    "addr:housenumber":"9",
    "addr:postcode":"36003",
    "addr:street":"Rua Alcalde Hevia Do",
    "iso:country":"ES",
    "sg:address":"Rua Alcalde Hevia (do), 9",
    "sg:city":"Pontevedra",
    "sg:orig_category":"Institutos De Belleza",
    "sg:phone":"+34 986 84 17 01",
    "sg:postcode":"36003",
    "sg:province":"Pontevedra",
    "wof:name":"Carmona Perez Ascension",
    "wof:placetype":"venue"
},
  "geometry": {"coordinates":[-8.6556968689,42.4145812988],"type":"Point"}
}