{
  "type": "Feature",
  "properties": {
    "iso:country":"ES",
    "sg:address":"Carballosa, 93",
    "sg:city":"Mos",
    "sg:orig_category":"Cr\u00cda De Animales",
    "sg:phone":"+34 982 31 02 06",
    "sg:postcode":"27268",
    "sg:province":"Lugo",
    "wof:name":"Dominguez Lopez Juan",
    "wof:placetype":"venue"
},
  "geometry": {"coordinates":[-7.5376400948,43.1623382568],"type":"Point"}
}