{
  "type": "Feature",
  "properties": {
    "addr:full":"Calle de Eskurtze, 12 Bilbao Vizcaya 48012",
    "addr:housenumber":"12",
    "addr:postcode":"48012",
    "addr:street":"Calle De Eskurtze",
    "iso:country":"ES",
    "sg:address":"Calle de Eskurtze, 12",
    "sg:city":"Bilbao",
    "sg:orig_category":"Estudios, Instalaci\u00d3n De Climatizaci\u00d3n",
    "sg:phone":"+34 944 43 85 66",
    "sg:postcode":"48012",
    "sg:province":"Vizcaya",
    "wof:name":"Quintero Alonso Maria Pilar",
    "wof:placetype":"venue"
},
  "geometry": {"coordinates":[-2.939068079,43.252166748],"type":"Point"}
}