{
  "type": "Feature",
  "properties": {
    "addr:full":"Calle de Marques De Larios, 8 Malaga M\u00e1laga 29005",
    "addr:housenumber":"8",
    "addr:postcode":"29005",
    "addr:street":"Calle De Marques De Larios;Ma\u0301Laga",
    "iso:country":"ES",
    "sg:address":"Calle de Marques De Larios, 8",
    "sg:city":"Malaga",
    "sg:orig_category":"Ingenier\u00cda, Centros De Estudios (diversos)",
    "sg:phone":"+34 952 21 14 28",
    "sg:postcode":"29005",
    "sg:province":"M\u00e1laga",
    "wof:name":"Proseco S.l.",
    "wof:placetype":"venue"
},
  "geometry": {"coordinates":[-4.4216890335,36.7193527222],"type":"Point"}
}