{
  "type": "Feature",
  "properties": {
    "addr:full":"Calle de Madrigal De La Vera, 7 Madrid Madrid 28044",
    "addr:housenumber":"7",
    "addr:postcode":"madrid;28044",
    "addr:street":"Calle De Madrigal De La Vera",
    "iso:country":"ES",
    "sg:address":"Calle de Madrigal De La Vera, 7",
    "sg:city":"Madrid",
    "sg:orig_category":"Peluquer\u00cdas, Peluquer\u00cda Mixta",
    "sg:phone":"+34 917 05 71 57",
    "sg:postcode":"28044",
    "sg:province":"Madrid",
    "wof:name":"Casas Castillo Gloria Maria",
    "wof:placetype":"venue"
},
  "geometry": {"coordinates":[-3.7800500393,40.3771629333],"type":"Point"}
}