{
  "type": "Feature",
  "properties": {
    "addr:full":"Calle de Concepcion, S/n Yebenes Toledo 45470",
    "addr:housenumber":"s / n",
    "addr:postcode":"45470",
    "addr:street":"Calle De Concepcion",
    "iso:country":"ES",
    "sg:address":"Calle de Concepcion, S/n",
    "sg:city":"Yebenes",
    "sg:orig_category":"Centros De Educaci\u00d3n Especial",
    "sg:phone":"+34 925 32 00 17",
    "sg:postcode":"45470",
    "sg:province":"Toledo",
    "wof:name":"Colegio Nacional San Jose De Calasanz",
    "wof:placetype":"venue"
},
  "geometry": {"coordinates":[-3.8765842915,39.5779495239],"type":"Point"}
}