{
  "type": "Feature",
  "properties": {
    "addr:full":"Calle de Ca\u00d1izares, 5 Madrid Madrid 28012",
    "addr:housenumber":"5",
    "addr:postcode":"28012",
    "addr:street":"Calle De Can\u0303Izares",
    "iso:country":"ES",
    "sg:address":"Calle de Ca\u00d1izares, 5",
    "sg:city":"Madrid",
    "sg:orig_category":"Inmobiliaria (agencias)",
    "sg:phone":"+34 913 69 47 29",
    "sg:postcode":"28012",
    "sg:province":"Madrid",
    "wof:name":"Paruma S. A.",
    "wof:placetype":"venue"
},
  "geometry": {"coordinates":[-3.7016522884,40.4127693176],"type":"Point"}
}