{
  "type": "Feature",
  "properties": {
    "iso:country":"ES",
    "sg:address":"Avda Miguel De Cervantes, 45",
    "sg:city":"San Basilio",
    "sg:orig_category":"Promotores Constructores",
    "sg:phone":"+34 968 29 73 01",
    "sg:postcode":"30009",
    "sg:province":"Murcia",
    "wof:name":"Promobralia",
    "wof:placetype":"venue"
},
  "geometry": {"coordinates":[-1.1440390348,38.0012702942],"type":"Point"}
}