{
  "type": "Feature",
  "properties": {
    "iso:country":"ES",
    "sg:address":"Plaz Sol (del), S/n",
    "sg:city":"Linea De La Concepcion",
    "sg:orig_category":"Ense\u00d1anza, Formaci\u00d3n Profesional: Aprendizaje",
    "sg:phone":"+34 956 76 73 87",
    "sg:postcode":"11300",
    "sg:province":"C\u00e1diz",
    "wof:name":"Instituto Social De La Marina-casa Del Mar",
    "wof:placetype":"venue"
},
  "geometry": {"coordinates":[-5.340939045,36.1683044434],"type":"Point"}
}