{
  "type": "Feature",
  "properties": {
    "addr:full":"Carrer de Lepant, 147 Barcelona Barcelona 08013",
    "addr:housenumber":"147",
    "addr:postcode":"08013",
    "addr:street":"Carrer De Lepant",
    "iso:country":"ES",
    "sg:address":"Carrer de Lepant, 147",
    "sg:city":"Barcelona",
    "sg:orig_category":"Promotores Constructores",
    "sg:phone":"+34 932 32 91 32",
    "sg:postcode":"08013",
    "sg:province":"Barcelona",
    "wof:name":"Zabala Arrizabalaga Juan Carlos",
    "wof:placetype":"venue"
},
  "geometry": {"coordinates":[2.1842279434,41.3985214233],"type":"Point"}
}