{
  "type": "Feature",
  "properties": {
    "addr:full":"Calle de Cerro De Los Pinos, 3 Caceres C\u00e1ceres 10005",
    "addr:housenumber":"3",
    "addr:postcode":"10005",
    "addr:street":"Calle De Cerro De Los Pinos;Ca\u0301Ceres",
    "iso:country":"ES",
    "sg:address":"Calle de Cerro De Los Pinos, 3",
    "sg:city":"Caceres",
    "sg:orig_category":"Agencias Y Agentes Comerciales, Representantes",
    "sg:phone":"+34 927 23 16 81",
    "sg:postcode":"10005",
    "sg:province":"C\u00e1ceres",
    "wof:name":"Morgado Iglesias Julia",
    "wof:placetype":"venue"
},
  "geometry": {"coordinates":[-6.5356450081,39.3445549011],"type":"Point"}
}