{
  "type": "Feature",
  "properties": {
    "addr:full":"Plaz Constitucion (de La), 1 Tielmes Madrid 28550",
    "addr:postcode":"28550",
    "iso:country":"ES",
    "sg:address":"Plaz Constitucion (de La), 1",
    "sg:city":"Tielmes",
    "sg:orig_category":"Administraciones Regionales, Departamentales Y Locales",
    "sg:phone":"+34 918 74 66 19",
    "sg:postcode":"28550",
    "sg:province":"Madrid",
    "wof:name":"Ayuntamiento De Tielmes",
    "wof:placetype":"venue"
},
  "geometry": {"coordinates":[-3.3153777122,40.2460861206],"type":"Point"}
}