{
  "type": "Feature",
  "properties": {
    "iso:country":"ES",
    "sg:address":"Carr Balmes, 1",
    "sg:city":"Almenara",
    "sg:orig_category":"Molduras, Junquillos, Listones Y Molduras Perforadas",
    "sg:phone":"+34 962 62 40 10",
    "sg:postcode":"12590",
    "sg:province":"Castell\u00f3n",
    "wof:name":"Roldan Domingo Vicente",
    "wof:placetype":"venue"
},
  "geometry": {"coordinates":[-0.2252819985,39.7522544861],"type":"Point"}
}