{
  "type": "Feature",
  "properties": {
    "addr:full":"Calle de Zocotin, 11 Jaca Huesca 22700",
    "addr:housenumber":"11",
    "addr:postcode":"22700",
    "addr:street":"Calle De Zocotin",
    "iso:country":"ES",
    "sg:address":"Calle de Zocotin, 11",
    "sg:city":"Jaca",
    "sg:orig_category":"Molduras, Junquillos, Listones Y Molduras Perforadas",
    "sg:phone":"+34 974 36 12 21",
    "sg:postcode":"22700",
    "sg:province":"Huesca",
    "wof:name":"Ferrandez Brun Miguel",
    "wof:placetype":"venue"
},
  "geometry": {"coordinates":[-0.5488989949,42.5699310303],"type":"Point"}
}