{
  "type": "Feature",
  "properties": {
    "iso:country":"ES",
    "sg:address":"Carrer de Torrijos, 10",
    "sg:city":"Barcelona",
    "sg:orig_category":"Prendas Y Chalecos De Punto (al Por Menor)",
    "sg:phone":"+34 932 19 80 20",
    "sg:postcode":"08012",
    "sg:province":"Barcelona",
    "wof:name":"Roura Pie Montserrat",
    "wof:placetype":"venue"
},
  "geometry": {"coordinates":[2.1597421169,41.4026565552],"type":"Point"}
}