{
  "type": "Feature",
  "properties": {
    "addr:full":"Carrer de Cigne, 19 Barcelona Barcelona 08012",
    "addr:housenumber":"19",
    "addr:postcode":"08012",
    "addr:street":"Carrer De Cigne",
    "iso:country":"ES",
    "sg:address":"Carrer de Cigne, 19",
    "sg:city":"Barcelona",
    "sg:orig_category":"Art\u00cdculos De Regalo (al Por Menor)",
    "sg:phone":"+34 932 17 92 58",
    "sg:postcode":"08012",
    "sg:province":"Barcelona",
    "wof:name":"Ordemundo S.l.",
    "wof:placetype":"venue"
},
  "geometry": {"coordinates":[2.153801918,41.4003067017],"type":"Point"}
}