{
  "type": "Feature",
  "properties": {
    "iso:country":"ES",
    "sg:address":"Calle de Valle Aureliano, 3",
    "sg:city":"Bilbao",
    "sg:orig_category":"Aud\u00cdfonos",
    "sg:phone":"+34 944 44 37 33",
    "sg:postcode":"48010",
    "sg:province":"Vizcaya",
    "wof:name":"Llopart Centro Auditivo S. L.",
    "wof:placetype":"venue"
},
  "geometry": {"coordinates":[-2.9400770664,43.2593421936],"type":"Point"}
}