{
  "type": "Feature",
  "properties": {
    "addr:full":"Calle de Alcalde Gomez Gomez, 21 Malaga M\u00e1laga 29006",
    "addr:housenumber":"21",
    "addr:postcode":"29006",
    "addr:street":"Calle De Alcalde Gomez Gomez;Ma\u0301Laga",
    "iso:country":"ES",
    "sg:address":"Calle de Alcalde Gomez Gomez, 21",
    "sg:city":"Malaga",
    "sg:orig_category":"Art\u00cdculos De Decoraci\u00d3n",
    "sg:phone":"+34 952 34 52 70",
    "sg:postcode":"29006",
    "sg:province":"M\u00e1laga",
    "sg:website":"www.manudecor.com",
    "wof:name":"Manudecor International S.l.",
    "wof:placetype":"venue"
},
  "geometry": {"coordinates":[-4.478664875,36.709728241],"type":"Point"}
}