{
  "type": "Feature",
  "properties": {
    "addr:full":"Albereda Escultor Ramon Ingles, 3 Betera Valencia 46117",
    "addr:housenumber":"3",
    "addr:postcode":"46117",
    "addr:street":"Escultor Ramon Ingles",
    "iso:country":"ES",
    "sg:address":"Albereda Escultor Ramon Ingles, 3",
    "sg:city":"Betera",
    "sg:orig_category":"Centros M\u00c9dicos Y Sociales, Dispensarios",
    "sg:phone":"+34 961 69 03 73",
    "sg:postcode":"46117",
    "sg:province":"Valencia",
    "wof:name":"Coval C.b.",
    "wof:placetype":"venue"
},
  "geometry": {"coordinates":[-0.4584990144,39.5926628113],"type":"Point"}
}