{
  "type": "Feature",
  "properties": {
    "addr:full":"Pl Esglesia (de L'), 1 Pla Santa Maria Tarragona 43810",
    "addr:housenumber":"1",
    "addr:postcode":"43810",
    "addr:street":"Pl Esglesia De L '",
    "iso:country":"ES",
    "sg:address":"Pl Esglesia (de L'), 1",
    "sg:city":"Pla Santa Maria",
    "sg:orig_category":"Iglesia Cat\u00d3lica",
    "sg:phone":"+34 977 63 00 34",
    "sg:postcode":"43810",
    "sg:province":"Tarragona",
    "wof:name":"Arquebisbat De Tarragona",
    "wof:placetype":"venue"
},
  "geometry": {"coordinates":[1.2900400162,41.3642730713],"type":"Point"}
}