{
  "type": "Feature",
  "properties": {
    "iso:country":"ES",
    "sg:address":"Calle de Compositor Lehmberg Ruiz, 21",
    "sg:city":"Malaga",
    "sg:orig_category":"Bancos",
    "sg:phone":"+34 952 07 18 81",
    "sg:postcode":"29007",
    "sg:province":"M\u00e1laga",
    "wof:name":"Deutsche Bank S.a.e.",
    "wof:placetype":"venue"
},
  "geometry": {"coordinates":[-4.435005188,36.7183036804],"type":"Point"}
}