{
  "type": "Feature",
  "properties": {
    "iso:country":"ES",
    "sg:address":"Av Catalunya, 14",
    "sg:city":"Espluga Francoli",
    "sg:orig_category":"Reposter\u00cdas",
    "sg:phone":"+34 977 87 14 28",
    "sg:postcode":"43440",
    "sg:province":"Tarragona",
    "wof:name":"Cal Tullet S.c.p.",
    "wof:placetype":"venue"
},
  "geometry": {"coordinates":[1.0984799862,41.3945999146],"type":"Point"}
}