{
  "type": "Feature",
  "properties": {
    "iso:country":"ES",
    "sg:address":"Calle de Virgen De Criptana, 15",
    "sg:city":"Campo Criptana",
    "sg:orig_category":"Inmobiliaria (agencias)",
    "sg:phone":"+34 926 58 91 36",
    "sg:postcode":"13610",
    "sg:province":"Ciudad Real",
    "wof:name":"Jimenez Iniesta Jose Manuel",
    "wof:placetype":"venue"
},
  "geometry": {"coordinates":[-3.1252179146,39.4051475525],"type":"Point"}
}