{
  "type": "Feature",
  "properties": {
    "iso:country":"ES",
    "sg:address":"Avda E. Mtnez Garrido-alcalde, 55",
    "sg:city":"Vigo",
    "sg:orig_category":"Agentes Generales De Seguros",
    "sg:phone":"+34 986 37 39 25",
    "sg:postcode":"36205",
    "sg:province":"Pontevedra",
    "wof:name":"Gestion Administrativa Y Tramitacion De Sanciones S.l.",
    "wof:placetype":"venue"
},
  "geometry": {"coordinates":[-8.7043333054,42.2255134583],"type":"Point"}
}