{
  "type": "Feature",
  "properties": {
    "addr:full":"Pl Viladecans, 1 Viladecans Barcelona 08840",
    "addr:housenumber":"1",
    "addr:postcode":"08840",
    "addr:street":"Viladecans",
    "iso:country":"ES",
    "sg:address":"Pl Viladecans, 1",
    "sg:city":"Viladecans",
    "sg:orig_category":"Estancos",
    "sg:phone":"+34 936 37 52 74",
    "sg:postcode":"08840",
    "sg:province":"Barcelona",
    "wof:name":"Lorenzo Baliu Joanna",
    "wof:placetype":"venue"
},
  "geometry": {"coordinates":[2.0204401016,41.3158111572],"type":"Point"}
}