{
  "type": "Feature",
  "properties": {
    "iso:country":"ES",
    "sg:address":"Calle de San Francisco, 19",
    "sg:city":"Talavera Reina",
    "sg:orig_category":"Ropa Para Ni\u00d1os (al Por Menor)",
    "sg:phone":"+34 925 80 64 53",
    "sg:postcode":"45600",
    "sg:province":"Toledo",
    "wof:name":"Garcia Martin C.b.",
    "wof:placetype":"venue"
},
  "geometry": {"coordinates":[-4.8300671577,39.9610939026],"type":"Point"}
}