{
  "type": "Feature",
  "properties": {
    "addr:full":"Calle de Aldeanueva De La Vera, 29 Madrid Madrid 28044",
    "addr:housenumber":"29",
    "addr:postcode":"madrid;28044",
    "addr:street":"Calle De Aldeanueva;La Vera",
    "iso:country":"ES",
    "sg:address":"Calle de Aldeanueva De La Vera, 29",
    "sg:city":"Madrid",
    "sg:orig_category":"Tiendas De Grano, Frutas Y Legumbres Secas (al Por Menor)",
    "sg:phone":"+34 917 05 93 77",
    "sg:postcode":"28044",
    "sg:province":"Madrid",
    "wof:name":"Redondo San Juan Alicia",
    "wof:placetype":"venue"
},
  "geometry": {"coordinates":[-3.7766053677,40.3756942749],"type":"Point"}
}