{
  "type": "Feature",
  "properties": {
    "addr:full":"Ctra. Casas Iba\u00f1ez, Km. 0001,6 Albacete Albacete 02006",
    "addr:postcode":"02006",
    "addr:street":"Ctra. Casas Iban\u0303Ez Km. 0001,6",
    "iso:country":"ES",
    "sg:address":"Ctra. Casas Iba\u00f1ez, Km. 0001,6",
    "sg:city":"Albacete",
    "sg:orig_category":"Alquiler De Gr\u00daas",
    "sg:phone":"+34 967 52 24 50",
    "sg:postcode":"02006",
    "sg:province":"Albacete",
    "wof:name":"Autogruas La Mancha S.l.",
    "wof:placetype":"venue"
},
  "geometry": {"coordinates":[-1.8657491207,39.0044898987],"type":"Point"}
}