{
  "type": "Feature",
  "properties": {
    "addr:full":"Calle de Arzobispo Almaraz, 11 Moguer Huelva 21800",
    "addr:housenumber":"11",
    "addr:postcode":"21800",
    "addr:street":"Calle De Arzobispo Almaraz",
    "iso:country":"ES",
    "sg:address":"Calle de Arzobispo Almaraz, 11",
    "sg:city":"Moguer",
    "sg:orig_category":"Bisuter\u00cda, Joyer\u00cda, Relojer\u00cda (al Por Menor)",
    "sg:phone":"+34 959 37 02 78",
    "sg:postcode":"21800",
    "sg:province":"Huelva",
    "wof:name":"Franco Alfaro Asuncion",
    "wof:placetype":"venue"
},
  "geometry": {"coordinates":[-6.838183403,37.2785453796],"type":"Point"}
}