{
  "type": "Feature",
  "properties": {
    "iso:country":"ES",
    "sg:address":"C/ Mario Pastor Sempere, 47",
    "sg:city":"Elche",
    "sg:orig_category":"Parques De Atracciones Y Centros De Esparcimiento",
    "sg:phone":"+34 965 43 19 73",
    "sg:postcode":"03206",
    "sg:province":"Alicante",
    "wof:name":"Genper S.a.",
    "wof:placetype":"venue"
},
  "geometry": {"coordinates":[-0.7068030238,38.2714729309],"type":"Point"}
}