{
  "type": "Feature",
  "properties": {
    "addr:full":"Calle de Nu\u00d1ez De Balboa, 95 Madrid Madrid 28006",
    "addr:housenumber":"95",
    "addr:postcode":"madrid;28006",
    "addr:street":"Calle De Nun\u0303Ez De Balboa",
    "iso:country":"ES",
    "sg:address":"Calle de Nu\u00d1ez De Balboa, 95",
    "sg:city":"Madrid",
    "sg:orig_category":"Bibliotecas, Mediatecas",
    "sg:phone":"+34 914 35 94 70",
    "sg:postcode":"28006",
    "sg:province":"Madrid",
    "wof:name":"Organismo Autonomo De Informatica Y Comunicaciones De La Comunidad De Madrid",
    "wof:placetype":"venue"
},
  "geometry": {"coordinates":[-3.6821761131,40.4345283508],"type":"Point"}
}