{
  "type": "Feature",
  "properties": {
    "addr:full":"Avda Mediterraneo, 51 Benidorm Alicante 03500",
    "addr:housenumber":"51",
    "addr:postcode":"03500",
    "addr:street":"Avda Mediterraneo",
    "iso:country":"ES",
    "sg:address":"Avda Mediterraneo, 51",
    "sg:city":"Benidorm",
    "sg:orig_category":"Asociaciones Y Clubs Deportivos",
    "sg:phone":"+34 966 80 76 73",
    "sg:postcode":"03500",
    "sg:province":"Alicante",
    "wof:name":"Deportes Salamanca S.l.",
    "wof:placetype":"venue"
},
  "geometry": {"coordinates":[-0.1094169989,38.5355606079],"type":"Point"}
}