{
  "type": "Feature",
  "properties": {
    "iso:country":"ES",
    "sg:address":"Poligono Landazabal, 4",
    "sg:city":"Atarrabia",
    "sg:orig_category":"Distribuci\u00d3n De Petr\u00d3leo Y Derivados",
    "sg:phone":"+34 948 33 30 53",
    "sg:postcode":"31610",
    "sg:province":"Navarra",
    "wof:name":"Batey Ezcaba S.l.",
    "wof:placetype":"venue"
},
  "geometry": {"coordinates":[-1.615144968,42.8330116272],"type":"Point"}
}