{
  "type": "Feature",
  "properties": {
    "addr:full":"Calle de Salvador Gomez De Lia\u00d1o, 26 Pe\u00e7aranda De Bracamonte Salamanca 37300",
    "addr:housenumber":"26",
    "addr:postcode":"37300",
    "addr:street":"Calle De Salvador Gomez De Lian\u0303O",
    "iso:country":"ES",
    "sg:address":"Calle de Salvador Gomez De Lia\u00d1o, 26",
    "sg:city":"Pe\u00e7aranda De Bracamonte",
    "sg:orig_category":"Peluquer\u00cdas, Peluquer\u00cda Mixta",
    "sg:phone":"+34 923 54 19 82",
    "sg:postcode":"37300",
    "sg:province":"Salamanca",
    "wof:name":"Arroyo Gil Rosa Maria",
    "wof:placetype":"venue"
},
  "geometry": {"coordinates":[-5.6630473137,40.9649734497],"type":"Point"}
}