{
  "type": "Feature",
  "properties": {
    "iso:country":"ES",
    "sg:address":"Calle de Estalajes, 32",
    "sg:city":"Azuaga",
    "sg:orig_category":"Ropa Para Se\u00d1oras Y Caballeros (al Por Menor)",
    "sg:phone":"+34 924 89 20 28",
    "sg:postcode":"06920",
    "sg:province":"Badajoz",
    "wof:name":"Marcelo S.c",
    "wof:placetype":"venue"
},
  "geometry": {"coordinates":[-5.6834478378,38.2612342834],"type":"Point"}
}