{
  "type": "Feature",
  "properties": {
    "iso:country":"ES",
    "sg:address":"Calle de Encina, 1",
    "sg:city":"Pueblanueva",
    "sg:orig_category":"Electricidad: Equipos Industriales, Componentes (fabricaci\u00d3n)",
    "sg:phone":"+34 925 86 05 94",
    "sg:postcode":"45690",
    "sg:province":"Toledo",
    "wof:name":"Instalaciones Electricas Oscar E Hijos S.l.l.",
    "wof:placetype":"venue"
},
  "geometry": {"coordinates":[-4.6810851097,39.9090309143],"type":"Point"}
}