{
  "type": "Feature",
  "properties": {
    "iso:country":"ES",
    "sg:address":"Calle de Muelle, S/n",
    "sg:city":"Palma",
    "sg:orig_category":"Agentes, Concesionarios Y Sucursales De Veh\u00cdculos",
    "sg:phone":"+34 971 71 80 12",
    "sg:postcode":"07012",
    "sg:province":"Islas Baleares",
    "sg:website":"www.tradisa.es",
    "wof:name":"Tradisa Servicios Corporativos S.l.",
    "wof:placetype":"venue"
},
  "geometry": {"coordinates":[2.6449849606,39.5714836121],"type":"Point"}
}