{
  "type": "Feature",
  "properties": {
    "iso:country":"ES",
    "sg:address":"Calle de Claudio Coello, 16",
    "sg:city":"Madrid",
    "sg:orig_category":"Servidores Y Editores De Bases De Datos",
    "sg:phone":"+34 917 81 13 03",
    "sg:postcode":"28001",
    "sg:province":"Madrid",
    "wof:name":"Hispanar Spain S.l.",
    "wof:placetype":"venue"
},
  "geometry": {"coordinates":[-3.6869935989,40.4223480225],"type":"Point"}
}