{
  "type": "Feature",
  "properties": {
    "iso:country":"ES",
    "sg:address":"Calle de Parque San Julian, 11",
    "sg:city":"Cuenca",
    "sg:orig_category":"Molduras, Junquillos, Listones Y Molduras Perforadas",
    "sg:phone":"+34 969 22 78 21",
    "sg:postcode":"16002",
    "sg:province":"Cuenca",
    "wof:name":"Martinez Belmar Dionisio",
    "wof:placetype":"venue"
},
  "geometry": {"coordinates":[-2.1340270042,40.0727462769],"type":"Point"}
}