{
  "type": "Feature",
  "properties": {
    "iso:country":"ES",
    "sg:address":"Calle de Alberto Schommer, 3",
    "sg:city":"Vitoria-gasteiz",
    "sg:orig_category":"Arquitectos",
    "sg:phone":"+34 945 13 17 41",
    "sg:postcode":"01006",
    "sg:province":"\u00c1lava",
    "wof:name":"J+d Arquitectos S.c.",
    "wof:placetype":"venue"
},
  "geometry": {"coordinates":[-2.6667723656,42.83776474],"type":"Point"}
}