{
  "type": "Feature",
  "properties": {
    "addr:full":"Calle de Serrano, 20 Benidorm Alicante 03500",
    "addr:housenumber":"20",
    "addr:postcode":"03500",
    "addr:street":"Calle De Serrano",
    "iso:country":"ES",
    "sg:address":"Calle de Serrano, 20",
    "sg:city":"Benidorm",
    "sg:orig_category":"Agencias Y Agentes Comerciales, Representantes",
    "sg:phone":"+34 966 80 66 03",
    "sg:postcode":"03500",
    "sg:province":"Alicante",
    "wof:name":"Heredia Heredia Juan",
    "wof:placetype":"venue"
},
  "geometry": {"coordinates":[-0.1342409998,38.5449981689],"type":"Point"}
}