{
  "type": "Feature",
  "properties": {
    "iso:country":"ES",
    "sg:address":"Calle de Reyes Catolicos, 9",
    "sg:city":"Le\u00f3n",
    "sg:orig_category":"Instalaci\u00d3n, Reparaci\u00d3n De Calefacci\u00d3n El\u00c9ctrica",
    "sg:phone":"+34 987 23 56 37",
    "sg:postcode":"24007",
    "sg:province":"Le\u00f3n",
    "wof:name":"Calefaccion Lody S.l.",
    "wof:placetype":"venue"
},
  "geometry": {"coordinates":[-5.5701360703,42.6071510315],"type":"Point"}
}