{
  "type": "Feature",
  "properties": {
    "iso:country":"ES",
    "sg:address":"Erletokieta, 1",
    "sg:city":"Iru\u00f1a",
    "sg:orig_category":"Pe\u00d1as Y Asociaciones Varias",
    "sg:phone":"+34 948 25 55 10",
    "sg:postcode":"31007",
    "sg:province":"Navarra",
    "wof:name":"Asociacion Navarra Residencias Ancianos",
    "wof:placetype":"venue"
},
  "geometry": {"coordinates":[-1.6474181414,42.8071136475],"type":"Point"}
}