{
  "type": "Feature",
  "properties": {
    "addr:full":"Calle de Delfin, 3 Madrid Madrid 28029",
    "addr:housenumber":"3",
    "addr:postcode":"28029",
    "addr:street":"Calle De Delfin",
    "iso:country":"ES",
    "sg:address":"Calle de Delfin, 3",
    "sg:city":"Madrid",
    "sg:orig_category":"Encuadernaci\u00d3n E Impresi\u00d3n De Folletos",
    "sg:phone":"+34 913 15 35 19",
    "sg:postcode":"28029",
    "sg:province":"Madrid",
    "wof:name":"Mo\u00f1ino Olivera Jose",
    "wof:placetype":"venue"
},
  "geometry": {"coordinates":[-3.6940891743,40.4670982361],"type":"Point"}
}