{
  "type": "Feature",
  "properties": {
    "iso:country":"ES",
    "sg:address":"El Campo, S/n",
    "sg:city":"Matarrosa Sil",
    "sg:orig_category":"Centros De Educaci\u00d3n Especial",
    "sg:phone":"+34 987 52 50 04",
    "sg:postcode":"24460",
    "sg:province":"Le\u00f3n",
    "wof:name":"Colegio Nacional Mixto",
    "wof:placetype":"venue"
},
  "geometry": {"coordinates":[-6.5314741135,42.7562103271],"type":"Point"}
}