{
  "type": "Feature",
  "properties": {
    "iso:country":"ES",
    "sg:address":"Calle de Torreblanca, 1",
    "sg:city":"Castellon",
    "sg:orig_category":"Molduras, Junquillos, Listones Y Molduras Perforadas",
    "sg:phone":"+34 964 22 22 24",
    "sg:postcode":"12003",
    "sg:province":"Castell\u00f3n",
    "wof:name":"Bar Blasco C De B",
    "wof:placetype":"venue"
},
  "geometry": {"coordinates":[-0.0310849994,39.9854431152],"type":"Point"}
}