{
  "type": "Feature",
  "properties": {
    "addr:full":"Calle de San Juan, 12 Jumilla Murcia 30520",
    "addr:housenumber":"12",
    "addr:postcode":"30520",
    "addr:street":"Calle De San Juan",
    "iso:country":"ES",
    "sg:address":"Calle de San Juan, 12",
    "sg:city":"Jumilla",
    "sg:orig_category":"Reposter\u00cdas",
    "sg:phone":"+34 968 78 39 44",
    "sg:postcode":"30520",
    "sg:province":"Murcia",
    "wof:name":"Chupe S.l.",
    "wof:placetype":"venue"
},
  "geometry": {"coordinates":[-1.3189320564,38.4777412415],"type":"Point"}
}