{
  "type": "Feature",
  "properties": {
    "addr:full":"Avda Legion De (la), 29 Antequera M\u00e1laga 29200",
    "addr:housenumber":"29",
    "addr:postcode":"29200",
    "addr:street":"Avda Legion De La",
    "iso:country":"ES",
    "sg:address":"Avda Legion De (la), 29",
    "sg:city":"Antequera",
    "sg:orig_category":"T\u00c9cnicos Veterinarios",
    "sg:phone":"+34 952 70 22 31",
    "sg:postcode":"29200",
    "sg:province":"M\u00e1laga",
    "wof:name":"Productos Ganaderos Del Sur S.l.",
    "wof:placetype":"venue"
},
  "geometry": {"coordinates":[-4.5655441284,37.0183448792],"type":"Point"}
}