{
  "type": "Feature",
  "properties": {
    "iso:country":"ES",
    "sg:address":"Ctra Javea, Km. 0007,0",
    "sg:city":"Benitachell",
    "sg:orig_category":"Distribuci\u00d3n De Petr\u00d3leo Y Derivados",
    "sg:phone":"+34 966 49 35 13",
    "sg:postcode":"03726",
    "sg:province":"Alicante",
    "wof:name":"Car Lluca S.l.",
    "wof:placetype":"venue"
},
  "geometry": {"coordinates":[0.1413500011,38.7316513062],"type":"Point"}
}