{
  "type": "Feature",
  "properties": {
    "iso:country":"ES",
    "sg:address":"Pl Vall Del Castell, 9",
    "sg:city":"Vilafranca Penedes",
    "sg:orig_category":"Institutos De Belleza",
    "sg:phone":"+34 938 17 07 95",
    "sg:postcode":"08720",
    "sg:province":"Barcelona",
    "wof:name":"Sellares Sapera Susanna",
    "wof:placetype":"venue"
},
  "geometry": {"coordinates":[1.6967090368,41.3477859497],"type":"Point"}
}