{
  "type": "Feature",
  "properties": {
    "addr:full":"Calle de Ntra Sra De Gracia, 7 Marbella M\u00e1laga 29600",
    "addr:housenumber":"7",
    "addr:postcode":"29600",
    "addr:street":"Calle De Ntra Sra De Gracia;Ma\u0301Laga",
    "iso:country":"ES",
    "sg:address":"Calle de Ntra Sra De Gracia, 7",
    "sg:city":"Marbella",
    "sg:orig_category":"Papeler\u00cdas, Librer\u00cdas",
    "sg:phone":"+34 952 77 09 09",
    "sg:postcode":"29600",
    "sg:province":"M\u00e1laga",
    "sg:website":"www.disofic.es",
    "wof:name":"Distribuidora Malague\u00f1a De Papeleria S. A.",
    "wof:placetype":"venue"
},
  "geometry": {"coordinates":[-4.8902440071,36.5083580017],"type":"Point"}
}