{
  "type": "Feature",
  "properties": {
    "iso:country":"ES",
    "sg:address":"Avgd Benidorm, 26",
    "sg:city":"Vila Joiosa",
    "sg:orig_category":"Fabricaci\u00d3n De Enlosados, Soler\u00cdas",
    "sg:phone":"+34 965 89 23 63",
    "sg:postcode":"03570",
    "sg:province":"Alicante",
    "wof:name":"Taulells El Polopi A.c. S.l.",
    "wof:placetype":"venue"
},
  "geometry": {"coordinates":[-0.7466139793,38.3102035522],"type":"Point"}
}