{
  "type": "Feature",
  "properties": {
    "iso:country":"ES",
    "sg:address":"Pase Reding, 9",
    "sg:city":"Malaga",
    "sg:orig_category":"Ropa Para Se\u00d1oras (al Por Menor)",
    "sg:phone":"+34 952 21 70 10",
    "sg:postcode":"29016",
    "sg:province":"M\u00e1laga",
    "wof:name":"Feucha S. L.",
    "wof:placetype":"venue"
},
  "geometry": {"coordinates":[-4.4109621048,36.7180747986],"type":"Point"}
}