{
  "type": "Feature",
  "properties": {
    "iso:country":"ES",
    "sg:address":"Calle de Pino, 2",
    "sg:city":"Torrejon Ardoz",
    "sg:orig_category":"Grifer\u00cda",
    "sg:phone":"+34 916 76 81 01",
    "sg:postcode":"28850",
    "sg:province":"Madrid",
    "wof:name":"Comercial Sanitarios Presto S.a.",
    "wof:placetype":"venue"
},
  "geometry": {"coordinates":[-3.4543869495,40.4536247253],"type":"Point"}
}