{
  "type": "Feature",
  "properties": {
    "addr:full":"Avda Doctor Beltran Baguena, 4 Bu\u00f1ol Valencia 46360",
    "addr:housenumber":"4",
    "addr:postcode":"46360",
    "addr:street":"Avda Doctor Beltran Baguena",
    "iso:country":"ES",
    "sg:address":"Avda Doctor Beltran Baguena, 4",
    "sg:city":"Bu\u00f1ol",
    "sg:orig_category":"Zapatos (al Por Menor)",
    "sg:phone":"+34 962 50 22 33",
    "sg:postcode":"46360",
    "sg:province":"Valencia",
    "wof:name":"Mu\u00f1oz Fernandez Graciano",
    "wof:placetype":"venue"
},
  "geometry": {"coordinates":[-0.7879459858,39.4166259766],"type":"Point"}
}