{
  "type": "Feature",
  "properties": {
    "addr:full":"Calle de Santa Tecla, 24 Madrid Madrid 28022",
    "addr:housenumber":"24",
    "addr:postcode":"madrid;28022",
    "addr:street":"Calle De Santa Tecla",
    "iso:country":"ES",
    "sg:address":"Calle de Santa Tecla, 24",
    "sg:city":"Madrid",
    "sg:orig_category":"Asilos De Ancianos. Centros Privados",
    "sg:phone":"+34 913 20 13 70",
    "sg:postcode":"28022",
    "sg:province":"Madrid",
    "wof:name":"Serinalma S.l.",
    "wof:placetype":"venue"
},
  "geometry": {"coordinates":[-3.6145501137,40.44272995],"type":"Point"}
}