{
  "type": "Feature",
  "properties": {
    "iso:country":"ES",
    "sg:address":"Calle de Colon, 31",
    "sg:city":"Benaguasil",
    "sg:orig_category":"Electricidad Veh\u00cdculo",
    "sg:phone":"+34 962 73 16 65",
    "sg:postcode":"46180",
    "sg:province":"Valencia",
    "wof:name":"Puchau Subiela Jose",
    "wof:placetype":"venue"
},
  "geometry": {"coordinates":[-0.5865216255,39.5974159241],"type":"Point"}
}