{
  "type": "Feature",
  "properties": {
    "addr:full":"Plaz Joaquin Costa, 5 Union Murcia 30360",
    "addr:housenumber":"5",
    "addr:postcode":"30360",
    "addr:street":"Costa",
    "iso:country":"ES",
    "sg:address":"Plaz Joaquin Costa, 5",
    "sg:city":"Union",
    "sg:orig_category":"Carnicer\u00cdas, Carnicer\u00cdas",
    "sg:phone":"+34 968 56 03 21",
    "sg:postcode":"30360",
    "sg:province":"Murcia",
    "wof:name":"Benedicto Paredes Francisco",
    "wof:placetype":"venue"
},
  "geometry": {"coordinates":[-0.8840990067,37.6215133667],"type":"Point"}
}