{
  "type": "Feature",
  "properties": {
    "addr:full":"C/ Cami Dels Magros, 66 Elche Alicante 03206",
    "addr:housenumber":"66",
    "addr:postcode":"03206",
    "addr:street":"C / Cami Dels Magros",
    "iso:country":"ES",
    "sg:address":"C/ Cami Dels Magros, 66",
    "sg:city":"Elche",
    "sg:orig_category":"Molduras, Junquillos, Listones Y Molduras Perforadas",
    "sg:phone":"+34 965 43 53 88",
    "sg:postcode":"03206",
    "sg:province":"Alicante",
    "wof:name":"Ruiz Garcia Primitiva",
    "wof:placetype":"venue"
},
  "geometry": {"coordinates":[-0.7049430013,38.2751235962],"type":"Point"}
}