{
  "type": "Feature",
  "properties": {
    "iso:country":"ES",
    "sg:address":"Carrer de Gravina, 1",
    "sg:city":"Hospitalet Llobregat",
    "sg:orig_category":"Empresas De Carpinter\u00cda",
    "sg:phone":"+34 934 38 04 19",
    "sg:postcode":"08906",
    "sg:province":"Barcelona",
    "wof:name":"Nou Cometal S.l.",
    "wof:placetype":"venue"
},
  "geometry": {"coordinates":[2.1017079353,41.3748855591],"type":"Point"}
}