{
  "type": "Feature",
  "properties": {
    "iso:country":"ES",
    "sg:address":"Avda Galicia (de), 19",
    "sg:city":"Monforte De Lemos",
    "sg:orig_category":"Muebles, Minoristas",
    "sg:phone":"+34 982 40 22 28",
    "sg:postcode":"27400",
    "sg:province":"Lugo",
    "wof:name":"Lopez Vazquez Jose Antonio",
    "wof:placetype":"venue"
},
  "geometry": {"coordinates":[-7.5147538185,42.5205688477],"type":"Point"}
}