{
  "type": "Feature",
  "properties": {
    "addr:full":"Calle de Doctor Santero, 4 Madrid Madrid 28039",
    "addr:housenumber":"4",
    "addr:postcode":"28039",
    "addr:street":"Calle De Doctor Santero",
    "iso:country":"ES",
    "sg:address":"Calle de Doctor Santero, 4",
    "sg:city":"Madrid",
    "sg:orig_category":"Loter\u00cda Y T\u00d3mbola",
    "sg:phone":"+34 915 34 71 76",
    "sg:postcode":"28039",
    "sg:province":"Madrid",
    "wof:name":"Olegario Campos Y Compa\u00f1ia S. L.",
    "wof:placetype":"venue"
},
  "geometry": {"coordinates":[-3.7040894032,40.4476890564],"type":"Point"}
}