{
  "type": "Feature",
  "properties": {
    "iso:country":"ES",
    "sg:address":"Calle de Camino De Puntallana, 35",
    "sg:city":"S. Sebastian Gomera",
    "sg:orig_category":"Reposter\u00cdas",
    "sg:phone":"+34 922 87 10 57",
    "sg:postcode":"38800",
    "sg:province":"Santa Cruz De Tenerife",
    "wof:name":"Panaderia La Rama S.l.",
    "wof:placetype":"venue"
},
  "geometry": {"coordinates":[-17.1083202362,28.0925865173],"type":"Point"}
}