{
  "type": "Feature",
  "properties": {
    "addr:full":"Carr Torroella, 2 Palafrugell Girona 17200",
    "addr:housenumber":"2",
    "addr:postcode":"17200",
    "addr:street":"Carr Torroella",
    "iso:country":"ES",
    "sg:address":"Carr Torroella, 2",
    "sg:city":"Palafrugell",
    "sg:orig_category":"Asesor\u00cda Sobre Comunicaci\u00d3n De Empresas",
    "sg:phone":"+34 972 30 03 92",
    "sg:postcode":"17200",
    "sg:province":"Girona",
    "wof:name":"Tecofisa S. L.",
    "wof:placetype":"venue"
},
  "geometry": {"coordinates":[3.1573989391,41.9163665771],"type":"Point"}
}