{
  "type": "Feature",
  "properties": {
    "iso:country":"ES",
    "sg:address":"Avda Doctor Sanchez Malo, 37",
    "sg:city":"Ecija",
    "sg:orig_category":"M\u00c9dicos: Estomatolog\u00cda",
    "sg:phone":"+34 954 83 59 64",
    "sg:postcode":"41400",
    "sg:province":"Sevilla",
    "wof:name":"Palma Cantero Lorenzo",
    "wof:placetype":"venue"
},
  "geometry": {"coordinates":[-5.085916996,37.5358047485],"type":"Point"}
}