{
  "type": "Feature",
  "properties": {
    "addr:full":"Calle de General Garcia Escamez, 109 Arrecife Las Palmas 35500",
    "addr:housenumber":"109",
    "addr:postcode":"35500",
    "addr:street":"Calle De General Garcia Escamez",
    "iso:country":"ES",
    "sg:address":"Calle de General Garcia Escamez, 109",
    "sg:city":"Arrecife",
    "sg:orig_category":"Ense\u00d1anza, Formaci\u00d3n Profesional: Aprendizaje",
    "sg:phone":"+34 928 81 57 58",
    "sg:postcode":"35500",
    "sg:province":"Las Palmas",
    "wof:name":"Cabildo Insular De Lanzarote",
    "wof:placetype":"venue"
},
  "geometry": {"coordinates":[-13.5590391159,28.9669456482],"type":"Point"}
}