{
  "type": "Feature",
  "properties": {
    "addr:full":"Ctra Vieja, 38 Bajos Y Tagoro Santa Cruz De Tenerife 38380",
    "addr:housenumber":"38",
    "addr:postcode":"38380",
    "addr:street":"Ctra Vieja",
    "iso:country":"ES",
    "sg:address":"Ctra Vieja, 38",
    "sg:city":"Bajos Y Tagoro",
    "sg:orig_category":"Chapister\u00cda",
    "sg:phone":"+34 922 58 03 81",
    "sg:postcode":"38380",
    "sg:province":"Santa Cruz De Tenerife",
    "wof:name":"Garcia Hernandez Domingo",
    "wof:placetype":"venue"
},
  "geometry": {"coordinates":[-16.4766902924,28.4301795959],"type":"Point"}
}