{
  "type": "Feature",
  "properties": {
    "iso:country":"ES",
    "sg:address":"Calle de Parque Eugenia De Montijo, 80",
    "sg:city":"Madrid",
    "sg:orig_category":"Medicamentos",
    "sg:phone":"+34 914 62 00 70",
    "sg:postcode":"28047",
    "sg:province":"Madrid",
    "wof:name":"Enriquez Paraled Monica",
    "wof:placetype":"venue"
},
  "geometry": {"coordinates":[-3.7529330254,40.3790855408],"type":"Point"}
}