{
  "type": "Feature",
  "properties": {
    "iso:country":"ES",
    "sg:address":"Carrer de Temple De Sant Telm, 5",
    "sg:city":"Denia",
    "sg:orig_category":"Pr\u00c9stamos Personales E Hipotecarios",
    "sg:phone":"+34 965 78 02 87",
    "sg:postcode":"03700",
    "sg:province":"Alicante",
    "wof:name":"Aguilera Anegon Gonzalo",
    "wof:placetype":"venue"
},
  "geometry": {"coordinates":[0.1093937978,38.8429031372],"type":"Point"}
}