{
  "type": "Feature",
  "properties": {
    "iso:country":"ES",
    "sg:address":"Carrer de Dolfi, 3",
    "sg:city":"Peguera",
    "sg:orig_category":"Alquiler De Veh\u00cdculos: Turismos Y Utilitarios",
    "sg:phone":"+34 971 68 70 71",
    "sg:postcode":"07160",
    "sg:province":"Islas Baleares",
    "wof:name":"Internacional Smilei S.l.",
    "wof:placetype":"venue"
},
  "geometry": {"coordinates":[2.444740057,39.5373916626],"type":"Point"}
}