{
  "type": "Feature",
  "properties": {
    "iso:country":"ES",
    "sg:address":"Calle de San Jose De Calasanz, 55",
    "sg:city":"Valladolid",
    "sg:orig_category":"Asociaciones, Organismos Culturales Y Socioeducativos",
    "sg:phone":"+34 983 22 07 92",
    "sg:postcode":"47013",
    "sg:province":"Valladolid",
    "wof:name":"Asociacion Cultural Y Deportiva Fenix",
    "wof:placetype":"venue"
},
  "geometry": {"coordinates":[-4.7191057205,41.6379203796],"type":"Point"}
}