{
  "type": "Feature",
  "properties": {
    "iso:country":"ES",
    "sg:address":"Plaz Convento, 3",
    "sg:city":"Biar",
    "sg:orig_category":"Cajas Para Embalar",
    "sg:phone":"+34 965 81 01 00",
    "sg:postcode":"03410",
    "sg:province":"Alicante",
    "wof:name":"Caja Rural Del Mediterraneo Ruralcaja S Coop De Credito",
    "wof:placetype":"venue"
},
  "geometry": {"coordinates":[-0.7641710043,38.6285438538],"type":"Point"}
}