{
  "type": "Feature",
  "properties": {
    "iso:country":"ES",
    "sg:address":"Carr Peralada, 16",
    "sg:city":"Figueres",
    "sg:orig_category":"Distribuci\u00d3n De Petr\u00d3leo Y Derivados",
    "sg:phone":"+34 972 50 17 55",
    "sg:postcode":"17600",
    "sg:province":"Girona",
    "wof:name":"Peixateria Montjoi S.l.",
    "wof:placetype":"venue"
},
  "geometry": {"coordinates":[2.9616770744,42.2676849365],"type":"Point"}
}