{
  "type": "Feature",
  "properties": {
    "addr:full":"Pol Vda Osuna, S/n Arahal Sevilla 41600",
    "addr:housenumber":"/ n",
    "addr:postcode":"41600",
    "addr:street":"S",
    "iso:country":"ES",
    "sg:address":"Pol Vda Osuna, S/n",
    "sg:city":"Arahal",
    "sg:orig_category":"Sanatorios M\u00c9dico",
    "sg:phone":"+34 954 84 02 87",
    "sg:postcode":"41600",
    "sg:province":"Sevilla",
    "wof:name":"Servicio Andaluz De Salud",
    "wof:placetype":"venue"
},
  "geometry": {"coordinates":[-5.5389637947,37.2638549805],"type":"Point"}
}