{
  "type": "Feature",
  "properties": {
    "addr:full":"Calle de Simon De Anda, 21 Vitoria-gasteiz \u00c1lava 01012",
    "addr:housenumber":"21",
    "addr:postcode":"01012",
    "addr:street":"Calle De Simon De Anda",
    "iso:country":"ES",
    "sg:address":"Calle de Simon De Anda, 21",
    "sg:city":"Vitoria-gasteiz",
    "sg:orig_category":"Promotores Constructores",
    "sg:phone":"+34 945 22 38 44",
    "sg:postcode":"01012",
    "sg:province":"\u00c1lava",
    "wof:name":"Bernal Diez Angel",
    "wof:placetype":"venue"
},
  "geometry": {"coordinates":[-2.674186945,42.8552093506],"type":"Point"}
}