{
  "type": "Feature",
  "properties": {
    "addr:full":"Calle de Galo Donaire, 39 Casas Millan C\u00e1ceres 10592",
    "addr:housenumber":"39",
    "addr:postcode":"10592",
    "addr:street":"Calle De Galo Donaire;Ca\u0301Ceres",
    "iso:country":"ES",
    "sg:address":"Calle de Galo Donaire, 39",
    "sg:city":"Casas Millan",
    "sg:classifiers":[
        {
            "category":"Taxi",
            "type":"Transportation"
        }
    ],
    "sg:phone":"+34 927 30 60 30",
    "sg:postcode":"10592",
    "sg:province":"C\u00e1ceres",
    "wof:name":"Martin Arroyo Juan Carlos",
    "wof:placetype":"venue"
},
  "geometry": {"coordinates":[-6.329228878,39.8168106079],"type":"Point"}
}