{
  "type": "Feature",
  "properties": {
    "iso:country":"ES",
    "sg:address":"Rua Devesa Santa Tegra, 71",
    "sg:city":"Vigo",
    "sg:orig_category":"Librer\u00cdas",
    "sg:phone":"+34 986 37 86 74",
    "sg:postcode":"36207",
    "sg:province":"Pontevedra",
    "wof:name":"Dacosta Carreras Aurora",
    "wof:placetype":"venue"
},
  "geometry": {"coordinates":[-8.7014007568,42.2502784729],"type":"Point"}
}