{
  "type": "Feature",
  "properties": {
    "iso:country":"ES",
    "sg:address":"Calle de Nu\u00d1ez Morgado, 5",
    "sg:city":"Madrid",
    "sg:orig_category":"Edici\u00d3n De Diarios, Revistas, Boletines",
    "sg:phone":"+34 913 23 17 19",
    "sg:postcode":"28036",
    "sg:province":"Madrid",
    "sg:website":"www.motorpoint.com",
    "wof:name":"Motor Point Network S.a.",
    "wof:placetype":"venue"
},
  "geometry": {"coordinates":[-3.6852459908,40.4686775208],"type":"Point"}
}