{
  "type": "Feature",
  "properties": {
    "addr:full":"Avda Joaquin Planells Riera, S/n Coru\u00d1a La Coru\u00f1a 15008",
    "addr:postcode":"15008",
    "addr:street":"Avda Joaquin Planells Riera S / N Corun\u0303A La Corun\u0303A",
    "iso:country":"ES",
    "sg:address":"Avda Joaquin Planells Riera, S/n",
    "sg:city":"Coru\u00d1a",
    "sg:orig_category":"Ense\u00d1anza Secundaria: Colegios Y Escuelas Privadas",
    "sg:phone":"+34 981 23 15 45",
    "sg:postcode":"15008",
    "sg:province":"La Coru\u00f1a",
    "wof:name":"Diputacion Provincial De La Coru\u00f1a",
    "wof:placetype":"venue"
},
  "geometry": {"coordinates":[-8.4157838821,43.3466644287],"type":"Point"}
}