{
  "type": "Feature",
  "properties": {
    "addr:full":"Avda Rafol De Almunia, 2 Monte Pego Alicante 03780",
    "addr:housenumber":"2",
    "addr:postcode":"03780",
    "addr:street":"Avda Rafol De Almunia",
    "iso:country":"ES",
    "sg:address":"Avda Rafol De Almunia, 2",
    "sg:city":"Monte Pego",
    "sg:orig_category":"Asilos De Ancianos. Centros Privados",
    "sg:phone":"+34 965 57 18 84",
    "sg:postcode":"03780",
    "sg:province":"Alicante",
    "sg:website":"www.fadesa.es",
    "wof:name":"Fadesa Inmobiliaria S.a.",
    "wof:placetype":"venue"
},
  "geometry": {"coordinates":[-0.1101740003,38.8434486389],"type":"Point"}
}