{
  "type": "Feature",
  "properties": {
    "iso:country":"ES",
    "sg:address":"Carrer de Pare Pere, 15",
    "sg:city":"Denia",
    "sg:orig_category":"Ropa Para Se\u00d1oras Y Caballeros (al Por Menor)",
    "sg:phone":"+34 965 78 38 52",
    "sg:postcode":"03700",
    "sg:province":"Alicante",
    "sg:website":"www.adolfodominguez.com",
    "wof:name":"Lino Basic, S.l.",
    "wof:placetype":"venue"
},
  "geometry": {"coordinates":[0.1054100022,38.8393211365],"type":"Point"}
}