{
  "type": "Feature",
  "properties": {
    "iso:country":"ES",
    "sg:address":"Cra. Valladolid, Km. 0095,0",
    "sg:city":"Due\u00f1as",
    "sg:orig_category":"Cr\u00cda De Animales",
    "sg:phone":"+34 979 78 03 77",
    "sg:postcode":"34210",
    "sg:province":"Palencia",
    "wof:name":"Sa\u00f1udo Borbolla Manuel",
    "wof:placetype":"venue"
},
  "geometry": {"coordinates":[-4.5456790924,41.8751182556],"type":"Point"}
}