{
  "type": "Feature",
  "properties": {
    "addr:full":"Calle de Rio, 53 Peralta Navarra 31350",
    "addr:housenumber":"53",
    "addr:postcode":"31350",
    "addr:street":"Calle De Rio",
    "iso:country":"ES",
    "sg:address":"Calle de Rio, 53",
    "sg:city":"Peralta",
    "sg:orig_category":"Ense\u00d1anza Secundaria: Colegios Y Escuelas Privadas",
    "sg:phone":"+34 948 75 16 13",
    "sg:postcode":"31350",
    "sg:province":"Navarra",
    "wof:name":"Gobierno De Navarra",
    "wof:placetype":"venue"
},
  "geometry": {"coordinates":[-1.7918330431,42.3394966125],"type":"Point"}
}