{
  "type": "Feature",
  "properties": {
    "addr:full":"Calle de Graus, 18 Zaragoza Zaragoza 50010",
    "addr:housenumber":"18",
    "addr:postcode":"50010",
    "addr:street":"Calle De Graus",
    "iso:country":"ES",
    "sg:address":"Calle de Graus, 18",
    "sg:city":"Zaragoza",
    "sg:orig_category":"Veh\u00cdculos De Ocasi\u00d3n",
    "sg:phone":"+34 976 30 00 25",
    "sg:postcode":"50010",
    "sg:province":"Zaragoza",
    "wof:name":"Mur Moliner Carmelo",
    "wof:placetype":"venue"
},
  "geometry": {"coordinates":[-0.903226018,41.6524238586],"type":"Point"}
}