{
  "type": "Feature",
  "properties": {
    "iso:country":"ES",
    "sg:address":"Pg Torras I Bages, 24",
    "sg:city":"Barcelona",
    "sg:orig_category":"Caf\u00c9s, Bares, Cervecer\u00cdas",
    "sg:phone":"+34 933 11 52 37",
    "sg:postcode":"08030",
    "sg:province":"Barcelona",
    "wof:name":"Anaxinamdro S.l.l",
    "wof:placetype":"venue"
},
  "geometry": {"coordinates":[2.1911771297,41.4374427795],"type":"Point"}
}