{
  "type": "Feature",
  "properties": {
    "addr:full":"Carr Ramon Y Cajal, De, S/n Casco Urbano Valencia 46760",
    "addr:housenumber":"/ n",
    "addr:postcode":"46760",
    "addr:street":"Carr Ramon Y Cajal De S",
    "iso:country":"ES",
    "sg:address":"Carr Ramon Y Cajal, De, S/n",
    "sg:city":"Casco Urbano",
    "sg:orig_category":"Carnicer\u00cdas, Carnicer\u00cdas",
    "sg:phone":"+34 962 83 79 97",
    "sg:postcode":"46760",
    "sg:province":"Valencia",
    "wof:name":"Cremades Corella Vicente",
    "wof:placetype":"venue"
},
  "geometry": {"coordinates":[-0.2594090104,39.0749702454],"type":"Point"}
}