{
  "type": "Feature",
  "properties": {
    "iso:country":"ES",
    "sg:address":"Carrer de Murcia, 52",
    "sg:city":"S. Boi Llobregat",
    "sg:orig_category":"Electricidad, Electr\u00d3nica: Material Y Suministros (al Por Mayor)",
    "sg:phone":"+34 936 52 84 26",
    "sg:postcode":"08830",
    "sg:province":"Barcelona",
    "wof:name":"Miguel Y Furno S.c.p.",
    "wof:placetype":"venue"
},
  "geometry": {"coordinates":[2.0402610302,41.3273925781],"type":"Point"}
}