{
  "type": "Feature",
  "properties": {
    "addr:full":"Calle de Paraiso, 7 Valladolid Valladolid 47003",
    "addr:housenumber":"7",
    "addr:postcode":"47003",
    "addr:street":"Calle De Paraiso",
    "iso:country":"ES",
    "sg:address":"Calle de Paraiso, 7",
    "sg:city":"Valladolid",
    "sg:orig_category":"Farmacias",
    "sg:phone":"+34 983 25 90 03",
    "sg:postcode":"47003",
    "sg:province":"Valladolid",
    "wof:name":"Llorente Dominguez Maria Rosa",
    "wof:placetype":"venue"
},
  "geometry": {"coordinates":[-4.7207999229,41.6544075012],"type":"Point"}
}