{
  "type": "Feature",
  "properties": {
    "addr:full":"Cra. De Manresa A Vic, Km. 0010,0 Calders Barcelona 08275",
    "addr:postcode":"08275",
    "addr:street":"Km. 0010,0",
    "iso:country":"ES",
    "sg:address":"Cra. De Manresa A Vic, Km. 0010,0",
    "sg:city":"Calders",
    "sg:orig_category":"Agricultores, Agricultores",
    "sg:phone":"+34 938 30 92 99",
    "sg:postcode":"08275",
    "sg:province":"Barcelona",
    "wof:name":"Pujol Dordal Lluis",
    "wof:placetype":"venue"
},
  "geometry": {"coordinates":[1.9948869944,41.791519165],"type":"Point"}
}