{
  "type": "Feature",
  "properties": {
    "addr:full":"Ntra Sra Salud, 1 Medina-sidonia C\u00e1diz 11170",
    "addr:postcode":"11170",
    "addr:street":"Medina-Sidonia Ca\u0301Diz",
    "iso:country":"ES",
    "sg:address":"Ntra Sra Salud, 1",
    "sg:city":"Medina-sidonia",
    "sg:orig_category":"Bebidas",
    "sg:phone":"+34 956 41 16 80",
    "sg:postcode":"11170",
    "sg:province":"C\u00e1diz",
    "wof:name":"Aguas De Medina Sidonia S.l.",
    "wof:placetype":"venue"
},
  "geometry": {"coordinates":[-5.9409708977,36.4186630249],"type":"Point"}
}