{
  "type": "Feature",
  "properties": {
    "addr:full":"C/ Verge Del Pedregal, 39 Tarrega Lleida 25300",
    "addr:housenumber":"39",
    "addr:postcode":"25300",
    "addr:street":"C / Verge Del Pedregal",
    "iso:country":"ES",
    "sg:address":"C/ Verge Del Pedregal, 39",
    "sg:city":"Tarrega",
    "sg:orig_category":"Transportes Por V\u00cdas Navegables",
    "sg:phone":"+34 973 31 05 89",
    "sg:postcode":"25300",
    "sg:province":"Lleida",
    "wof:name":"Haro Garcia Francisca",
    "wof:placetype":"venue"
},
  "geometry": {"coordinates":[1.1512999535,41.6487083435],"type":"Point"}
}