{
  "type": "Feature",
  "properties": {
    "iso:country":"ES",
    "sg:address":"Calle de Puerta De Avila, S/n",
    "sg:city":"Piedrahita",
    "sg:orig_category":"Notarios",
    "sg:phone":"+34 920 36 01 00",
    "sg:postcode":"05500",
    "sg:province":"\u00c1vila",
    "wof:name":"Carmona Cuenca Jose Enrique",
    "wof:placetype":"venue"
},
  "geometry": {"coordinates":[-5.3263239861,40.4657211304],"type":"Point"}
}