{
  "type": "Feature",
  "properties": {
    "addr:full":"Calle de General Ramirez De Madrid, 18 Madrid Madrid 28020",
    "addr:housenumber":"18",
    "addr:postcode":"madrid;28020",
    "addr:street":"Calle De General Ramirez De Madrid",
    "iso:country":"ES",
    "sg:address":"Calle de General Ramirez De Madrid, 18",
    "sg:city":"Madrid",
    "sg:orig_category":"Farmacias",
    "sg:phone":"+34 915 70 12 40",
    "sg:postcode":"28020",
    "sg:province":"Madrid",
    "wof:name":"Saenz De Santa Maria Vierna Maria Dolores",
    "wof:placetype":"venue"
},
  "geometry": {"coordinates":[-3.6976718903,40.4555168152],"type":"Point"}
}