{
  "type": "Feature",
  "properties": {
    "iso:country":"ES",
    "sg:address":"Calle de Maria Auxiliadora, 19",
    "sg:city":"Sanlucar Mayor",
    "sg:orig_category":"Molduras, Junquillos, Listones Y Molduras Perforadas",
    "sg:phone":"+34 955 70 11 05",
    "sg:postcode":"41800",
    "sg:province":"Sevilla",
    "wof:name":"Rodriguez Garcia Carmen",
    "wof:placetype":"venue"
},
  "geometry": {"coordinates":[-6.1997361183,37.3839416504],"type":"Point"}
}