{
  "type": "Feature",
  "properties": {
    "iso:country":"ES",
    "sg:address":"Calle de Maria De Molina, 32",
    "sg:city":"Madrid",
    "sg:orig_category":"Lencer\u00cda Femenina, Corseter\u00cda, Trajes De Ba\u00d1o (al Por Menor)",
    "sg:phone":"+34 915 62 54 54",
    "sg:postcode":"28006",
    "sg:province":"Madrid",
    "wof:name":"Mu\u00f1oz Gonzalez Pedro Eduardo",
    "wof:placetype":"venue"
},
  "geometry": {"coordinates":[-3.6843590736,40.4375305176],"type":"Point"}
}