{
  "type": "Feature",
  "properties": {
    "iso:country":"ES",
    "sg:address":"Aeropuerto Del Hierro, 1",
    "sg:city":"Valverde",
    "sg:orig_category":"Agentes, Concesionarios Y Sucursales De Camiones Y Veh\u00cdculos Industriales",
    "sg:phone":"+34 922 55 01 23",
    "sg:postcode":"38910",
    "sg:province":"Santa Cruz De Tenerife",
    "wof:name":"Auto Rosamar S.l.",
    "wof:placetype":"venue"
},
  "geometry": {"coordinates":[-17.8887481689,27.8037948608],"type":"Point"}
}