{
  "type": "Feature",
  "properties": {
    "iso:country":"ES",
    "sg:address":"Calle de Clara Campoamor, 7",
    "sg:city":"Zaragoza",
    "sg:orig_category":"Peluquer\u00cdas, Peluquer\u00cda Mixta",
    "sg:phone":"+34 976 73 49 59",
    "sg:postcode":"50015",
    "sg:province":"Zaragoza",
    "wof:name":"Arza Romo Faustino Javier",
    "wof:placetype":"venue"
},
  "geometry": {"coordinates":[-0.8911523819,41.6680450439],"type":"Point"}
}