{
  "type": "Feature",
  "properties": {
    "iso:country":"ES",
    "sg:address":"Pase Marques De Zafra, 27",
    "sg:city":"Madrid",
    "sg:orig_category":"Reposter\u00cdas",
    "sg:phone":"+34 917 26 80 80",
    "sg:postcode":"28028",
    "sg:province":"Madrid",
    "wof:name":"Pozo Diaz Maria Cruz",
    "wof:placetype":"venue"
},
  "geometry": {"coordinates":[-3.6623950005,40.4261131287],"type":"Point"}
}