{
  "type": "Feature",
  "properties": {
    "iso:country":"ES",
    "sg:address":"Avda Menendez Pelayo, 20",
    "sg:city":"Madrid",
    "sg:orig_category":"Abogados",
    "sg:phone":"+34 914 33 34 53",
    "sg:postcode":"28007",
    "sg:province":"Madrid",
    "wof:name":"Balabasquer Izquierdo Angel Jose",
    "wof:placetype":"venue"
},
  "geometry": {"coordinates":[-3.6793210506,40.4067573547],"type":"Point"}
}