{
  "type": "Feature",
  "properties": {
    "iso:country":"ES",
    "sg:address":"Av Argentina, 51",
    "sg:city":"Palma",
    "sg:orig_category":"Confecci\u00d3n De Ropa Interior",
    "sg:phone":"+34 971 73 09 40",
    "sg:postcode":"07013",
    "sg:province":"Islas Baleares",
    "wof:name":"Roca Olsen Vicky",
    "wof:placetype":"venue"
},
  "geometry": {"coordinates":[2.6403510571,39.5729446411],"type":"Point"}
}