{
  "type": "Feature",
  "properties": {
    "iso:country":"ES",
    "sg:address":"Calle de Hortaleza, 82",
    "sg:city":"Madrid",
    "sg:orig_category":"Ingenieros Asesor\u00cda",
    "sg:phone":"+34 913 10 54 07",
    "sg:postcode":"28004",
    "sg:province":"Madrid",
    "wof:name":"Arde-95",
    "wof:placetype":"venue"
},
  "geometry": {"coordinates":[-3.6985590458,40.4237747192],"type":"Point"}
}