{
  "type": "Feature",
  "properties": {
    "addr:full":"Calle de Carricalta, 24 Alcorisa Teruel 44550",
    "addr:housenumber":"24",
    "addr:postcode":"44550",
    "addr:street":"Calle De Carricalta",
    "iso:country":"ES",
    "sg:address":"Calle de Carricalta, 24",
    "sg:city":"Alcorisa",
    "sg:orig_category":"Reposter\u00cdas",
    "sg:phone":"+34 978 84 04 13",
    "sg:postcode":"44550",
    "sg:province":"Teruel",
    "wof:name":"Benedi Arguedas Pascual",
    "wof:placetype":"venue"
},
  "geometry": {"coordinates":[-0.3817929924,40.8912315369],"type":"Point"}
}