{
  "type": "Feature",
  "properties": {
    "iso:country":"ES",
    "sg:address":"Calle de Redonda De San Fernando, S/n",
    "sg:city":"Bujalance",
    "sg:orig_category":"Producci\u00d3n, Venta De Productos De Agricultura Biol\u00d3gica",
    "sg:phone":"+34 957 17 21 29",
    "sg:postcode":"14650",
    "sg:province":"C\u00f3rdoba",
    "wof:name":"Nieto Alvarez Juan",
    "wof:placetype":"venue"
},
  "geometry": {"coordinates":[-4.3766641617,37.8974914551],"type":"Point"}
}