{
  "type": "Feature",
  "properties": {
    "iso:country":"ES",
    "sg:address":"Calle de Joaquin Pacheco, 30",
    "sg:city":"Soto Mora",
    "sg:orig_category":"M\u00c9dicos: Estomatolog\u00cda",
    "sg:phone":"+34 918 90 60 08",
    "sg:postcode":"28280",
    "sg:province":"Madrid",
    "wof:name":"Garcia Candia Ruben Horacio",
    "wof:placetype":"venue"
},
  "geometry": {"coordinates":[-4.1260890961,40.5817756653],"type":"Point"}
}