{
  "type": "Feature",
  "properties": {
    "addr:full":"Carrer de Tarrega, 17 Terrassa Barcelona 08227",
    "addr:housenumber":"17",
    "addr:postcode":"08227",
    "addr:street":"Carrer De Tarrega",
    "iso:country":"ES",
    "sg:address":"Carrer de Tarrega, 17",
    "sg:city":"Terrassa",
    "sg:orig_category":"Hoteles",
    "sg:phone":"+34 937 36 36 40",
    "sg:postcode":"08227",
    "sg:province":"Barcelona",
    "wof:name":"Hotel Tarrega C.b.",
    "wof:placetype":"venue"
},
  "geometry": {"coordinates":[2.0356600285,41.5779914856],"type":"Point"}
}