{
  "type": "Feature",
  "properties": {
    "addr:full":"Calle de Henao, 23 Bilbao Vizcaya 48009",
    "addr:housenumber":"23",
    "addr:postcode":"48009",
    "addr:street":"Calle De Henao",
    "iso:country":"ES",
    "sg:address":"Calle de Henao, 23",
    "sg:city":"Bilbao",
    "sg:orig_category":"Asilos De Ancianos. Centros Privados",
    "sg:phone":"+34 944 24 12 22",
    "sg:postcode":"48009",
    "sg:province":"Vizcaya",
    "wof:name":"V.c. Tercera Edad Henao",
    "wof:placetype":"venue"
},
  "geometry": {"coordinates":[-2.9337239265,43.2648735046],"type":"Point"}
}