{
  "type": "Feature",
  "properties": {
    "iso:country":"ES",
    "sg:address":"Calle de General Manuel Saavedra Palmeiro, 12",
    "sg:city":"Badajoz",
    "sg:orig_category":"Asesor\u00cda Fiscal Y Jur\u00cddica",
    "sg:phone":"+34 924 26 10 26",
    "sg:postcode":"06004",
    "sg:province":"Badajoz",
    "wof:name":"Carrasco Caro Raquel",
    "wof:placetype":"venue"
},
  "geometry": {"coordinates":[-6.9756770134,38.8721733093],"type":"Point"}
}