{
  "type": "Feature",
  "properties": {
    "iso:country":"ES",
    "sg:address":"Avda Doctor Federico Rubio Y Gali, 67",
    "sg:city":"Madrid",
    "sg:orig_category":"Telas (al Por Mayor)",
    "sg:phone":"+34 914 59 32 89",
    "sg:postcode":"28040",
    "sg:province":"Madrid",
    "sg:website":"www.creationbaumann.es",
    "wof:name":"Creation Baumann S. L.",
    "wof:placetype":"venue"
},
  "geometry": {"coordinates":[-3.7146921158,40.4545898438],"type":"Point"}
}