{
  "type": "Feature",
  "properties": {
    "iso:country":"ES",
    "sg:address":"Calle de Doctor Cornago, 24",
    "sg:city":"Pozuelo De Alarcon",
    "sg:orig_category":"Droguer\u00cdas (al Por Menor)",
    "sg:phone":"+34 917 15 00 11",
    "sg:postcode":"28223",
    "sg:province":"Madrid",
    "wof:name":"Montes Iglesias Timoteo",
    "wof:placetype":"venue"
},
  "geometry": {"coordinates":[-3.814009428,40.4371147156],"type":"Point"}
}