{
  "type": "Feature",
  "properties": {
    "iso:country":"ES",
    "sg:address":"Calle de Valencia, 11",
    "sg:city":"Granada",
    "sg:orig_category":"Inmobiliaria (agencias)",
    "sg:phone":"+34 958 18 30 06",
    "sg:postcode":"18007",
    "sg:province":"Granada",
    "wof:name":"Inmobiliaria Jimenez Y Agis S.l",
    "wof:placetype":"venue"
},
  "geometry": {"coordinates":[-3.5972909927,37.1553535461],"type":"Point"}
}