{
  "type": "Feature",
  "properties": {
    "iso:country":"ES",
    "sg:address":"Carr Miquel Servet, 178",
    "sg:city":"Badalona",
    "sg:orig_category":"Ense\u00d1anza: Profesiones Art\u00cdsticas",
    "sg:phone":"+34 933 83 53 53",
    "sg:postcode":"08912",
    "sg:province":"Barcelona",
    "wof:name":"Graupera Costa Maria Teresa",
    "wof:placetype":"venue"
},
  "geometry": {"coordinates":[2.2400150299,41.4465675354],"type":"Point"}
}