{
  "type": "Feature",
  "properties": {
    "iso:country":"ES",
    "sg:address":"Avda Alcalde Alvaro Domecq, 18",
    "sg:city":"Jerez De La Frontera",
    "sg:orig_category":"M\u00c9dicos: Neurolog\u00cda",
    "sg:phone":"+34 956 31 49 39",
    "sg:postcode":"11405",
    "sg:province":"C\u00e1diz",
    "wof:name":"Gicalse S.l.",
    "wof:placetype":"venue"
},
  "geometry": {"coordinates":[-6.1226420403,36.6981925964],"type":"Point"}
}