{
  "type": "Feature",
  "properties": {
    "iso:country":"ES",
    "sg:address":"Barr San Antonio, S/n",
    "sg:city":"Renedo",
    "sg:orig_category":"Lecher\u00cdas",
    "sg:phone":"+34 942 57 14 78",
    "sg:postcode":"39470",
    "sg:province":"Cantabria",
    "wof:name":"Degesa Monta\u00d1esa S.a.",
    "wof:placetype":"venue"
},
  "geometry": {"coordinates":[-3.941644907,43.3522872925],"type":"Point"}
}