{
  "type": "Feature",
  "properties": {
    "addr:full":"Urb C.r. Real De La Barrosa, 179 Gallos -cerromolino C\u00e1diz 11130",
    "addr:housenumber":"179",
    "addr:postcode":"11130",
    "addr:street":"Urb C.R. Real De La Barrosa;Ca\u0301Diz",
    "iso:country":"ES",
    "sg:address":"Urb C.r. Real De La Barrosa, 179",
    "sg:city":"Gallos -cerromolino",
    "sg:orig_category":"Cerrajer\u00cda, Ferrallista",
    "sg:phone":"+34 956 53 02 60",
    "sg:postcode":"11130",
    "sg:province":"C\u00e1diz",
    "wof:name":"Ruiz Rosa Juan Luis",
    "wof:placetype":"venue"
},
  "geometry": {"coordinates":[-6.1447038651,36.4212188721],"type":"Point"}
}