{
  "type": "Feature",
  "properties": {
    "addr:full":"Poligono Industrial Calle de A, 18 Iraizotz Navarra 31797",
    "addr:housenumber":"18",
    "addr:postcode":"31797",
    "addr:street":"Calle De A",
    "iso:country":"ES",
    "sg:address":"Poligono Industrial Calle de A, 18",
    "sg:city":"Iraizotz",
    "sg:orig_category":"Construcciones Met\u00c1licas",
    "sg:phone":"+34 948 30 50 82",
    "sg:postcode":"31797",
    "sg:province":"Navarra",
    "wof:name":"Metalicas Tuferreta S.a.l.",
    "wof:placetype":"venue"
},
  "geometry": {"coordinates":[-1.6957390308,42.9793548584],"type":"Point"}
}