{
  "type": "Feature",
  "properties": {
    "addr:full":"Calle de Rosales, 4 Alberca De Las Torres Murcia 30150",
    "addr:housenumber":"4",
    "addr:postcode":"30150",
    "addr:street":"Calle De Rosales",
    "iso:country":"ES",
    "sg:address":"Calle de Rosales, 4",
    "sg:city":"Alberca De Las Torres",
    "sg:orig_category":"Desinfecci\u00d3n, Desinsectaci\u00d3n, Desratizaci\u00d3n",
    "sg:phone":"+34 968 84 81 65",
    "sg:postcode":"30150",
    "sg:province":"Murcia",
    "wof:name":"Sanitary Pons S.l.",
    "wof:placetype":"venue"
},
  "geometry": {"coordinates":[-1.1443300247,37.9391288757],"type":"Point"}
}