{
  "type": "Feature",
  "properties": {
    "iso:country":"ES",
    "sg:address":"Ptge Merce Rodoreda, 18",
    "sg:city":"Castelldefels",
    "sg:orig_category":"Centros De Coordinaci\u00d3n",
    "sg:phone":"+34 936 65 63 13",
    "sg:postcode":"08860",
    "sg:province":"Barcelona",
    "wof:name":"Servigest S.coop.l.",
    "wof:placetype":"venue"
},
  "geometry": {"coordinates":[1.9735200405,41.2831802368],"type":"Point"}
}