{
  "type": "Feature",
  "properties": {
    "addr:full":"Calle de Stmo Cristo De La Sala, 18 Bargas Toledo 45593",
    "addr:housenumber":"18",
    "addr:postcode":"45593",
    "addr:street":"Calle De;Sala",
    "iso:country":"ES",
    "sg:address":"Calle de Stmo Cristo De La Sala, 18",
    "sg:city":"Bargas",
    "sg:orig_category":"Empresas De Carpinter\u00cda De Madera",
    "sg:phone":"+34 925 35 88 64",
    "sg:postcode":"45593",
    "sg:province":"Toledo",
    "wof:name":"Puertas De La Sagra S L L",
    "wof:placetype":"venue"
},
  "geometry": {"coordinates":[-4.0181689262,39.9423141479],"type":"Point"}
}