{
  "type": "Feature",
  "properties": {
    "iso:country":"ES",
    "sg:address":"Calle de Chiclana, 5",
    "sg:city":"Berja",
    "sg:orig_category":"Cooperativas Agr\u00cdcolas",
    "sg:phone":"+34 950 49 26 44",
    "sg:postcode":"04760",
    "sg:province":"Almer\u00eda",
    "wof:name":"Union De Peque\u00f1os Agricultores Y Ganaderos De Almeria",
    "wof:placetype":"venue"
},
  "geometry": {"coordinates":[-2.9482851028,36.8480491638],"type":"Point"}
}