{
  "type": "Feature",
  "properties": {
    "addr:full":"Rond Muralla (da), 46 Lugo Lugo 27002",
    "addr:postcode":"27002",
    "addr:street":"Rond;Da",
    "iso:country":"ES",
    "sg:address":"Rond Muralla (da), 46",
    "sg:city":"Lugo",
    "sg:orig_category":"Fabricaci\u00d3n De Mobiliario De Oficina",
    "sg:phone":"+34 982 24 37 20",
    "sg:postcode":"27002",
    "sg:province":"Lugo",
    "sg:website":"www.ofiprecios.com",
    "wof:name":"Ofi Precios S. L.",
    "wof:placetype":"venue"
},
  "geometry": {"coordinates":[-7.5533528328,43.0122070312],"type":"Point"}
}