{
  "type": "Feature",
  "properties": {
    "addr:full":"Carrer de Begues, 6 Gava Barcelona 08850",
    "addr:housenumber":"6",
    "addr:postcode":"08850",
    "addr:street":"Carrer De Begues",
    "iso:country":"ES",
    "sg:address":"Carrer de Begues, 6",
    "sg:city":"Gava",
    "sg:orig_category":"Laboratorios Y Cl\u00cdnicas Veterinarias",
    "sg:phone":"+34 936 62 59 51",
    "sg:postcode":"08850",
    "sg:province":"Barcelona",
    "wof:name":"Diaz Garcia Maria Teresa",
    "wof:placetype":"venue"
},
  "geometry": {"coordinates":[2.0006399155,41.3082504272],"type":"Point"}
}