{
  "type": "Feature",
  "properties": {
    "iso:country":"ES",
    "sg:address":"El Rabil, S/n",
    "sg:city":"Simancas",
    "sg:orig_category":"Carnicer\u00cdas, Carnicer\u00cdas",
    "sg:phone":"+34 983 59 10 68",
    "sg:postcode":"47130",
    "sg:province":"Valladolid",
    "wof:name":"Castellana De Carnes S.a.",
    "wof:placetype":"venue"
},
  "geometry": {"coordinates":[-4.822450161,41.5905151367],"type":"Point"}
}