{
  "type": "Feature",
  "properties": {
    "addr:full":"Plaz Santa Barbara, S/n Mieres Asturias 33600",
    "addr:postcode":"33600",
    "addr:street":"Barbara S / N",
    "iso:country":"ES",
    "sg:address":"Plaz Santa Barbara, S/n",
    "sg:city":"Mieres",
    "sg:orig_category":"Producci\u00d3n, Distribuci\u00d3n De Gas Butano Y Propano",
    "sg:phone":"+34 985 46 02 72",
    "sg:postcode":"33600",
    "sg:province":"Asturias",
    "wof:name":"Fernandez Menendez Angel",
    "wof:placetype":"venue"
},
  "geometry": {"coordinates":[-5.7777690887,43.2518501282],"type":"Point"}
}