{
  "type": "Feature",
  "properties": {
    "addr:full":"Calle de Oto\u00d1o, 44 Arganda Madrid 28500",
    "addr:housenumber":"44",
    "addr:postcode":"28500",
    "addr:street":"Calle De Oton\u0303O",
    "iso:country":"ES",
    "sg:address":"Calle de Oto\u00d1o, 44",
    "sg:city":"Arganda",
    "sg:orig_category":"Automatizaci\u00d3n De Procesos Industriales Y De Edificaci\u00d3n (estudios, Instalaci\u00d3n)",
    "sg:phone":"+34 918 72 07 48",
    "sg:postcode":"28500",
    "sg:province":"Madrid",
    "sg:website":"www.maclysa.com",
    "wof:name":"Maclisa Sociedad Civil",
    "wof:placetype":"venue"
},
  "geometry": {"coordinates":[-3.4859089851,40.3102607727],"type":"Point"}
}