{
  "type": "Feature",
  "properties": {
    "iso:country":"ES",
    "sg:address":"Ctra. Madrid-irun, Km. 0099,0",
    "sg:city":"Villarejo",
    "sg:orig_category":"Hoteles",
    "sg:phone":"+34 921 55 71 05",
    "sg:postcode":"40590",
    "sg:province":"Segovia",
    "wof:name":"Hotel Mirasierra S.l.",
    "wof:placetype":"venue"
},
  "geometry": {"coordinates":[-3.5787808895,41.1958312988],"type":"Point"}
}