{
  "type": "Feature",
  "properties": {
    "iso:country":"ES",
    "sg:address":"Calle de Padres Capuchinos, 5",
    "sg:city":"Manzanares",
    "sg:orig_category":"Deportes Y Ocio: Art\u00cdculos Y Ropas (al Por Menor Y Accesorios)",
    "sg:phone":"+34 926 61 48 76",
    "sg:postcode":"13200",
    "sg:province":"Ciudad Real",
    "sg:website":"www.mon-sport.com",
    "wof:name":"Gallego Galiano Juan Ramon",
    "wof:placetype":"venue"
},
  "geometry": {"coordinates":[-3.3682370186,39.0007209778],"type":"Point"}
}