{
  "type": "Feature",
  "properties": {
    "addr:full":"Principe, 20 Moraleja C\u00e1ceres 10840",
    "addr:housenumber":"20",
    "addr:postcode":"10840",
    "addr:street":"Principe;Ca\u0301Ceres",
    "iso:country":"ES",
    "sg:address":"Principe, 20",
    "sg:city":"Moraleja",
    "sg:orig_category":"Papeler\u00cdas, Librer\u00cdas",
    "sg:phone":"+34 927 51 53 56",
    "sg:postcode":"10840",
    "sg:province":"C\u00e1ceres",
    "wof:name":"Fernandez Garcia Antonio",
    "wof:placetype":"venue"
},
  "geometry": {"coordinates":[-6.6549448967,40.070766449],"type":"Point"}
}