{
  "type": "Feature",
  "properties": {
    "addr:full":"Carrer de Independencia, 397 Barcelona Barcelona 08041",
    "addr:housenumber":"397",
    "addr:postcode":"08041",
    "addr:street":"Carrer De Independencia",
    "iso:country":"ES",
    "sg:address":"Carrer de Independencia, 397",
    "sg:city":"Barcelona",
    "sg:orig_category":"Molduras, Junquillos, Listones Y Molduras Perforadas",
    "sg:phone":"+34 934 35 39 46",
    "sg:postcode":"08041",
    "sg:province":"Barcelona",
    "wof:name":"Sanchez Iba\u00f1ez Julio",
    "wof:placetype":"venue"
},
  "geometry": {"coordinates":[2.1766700745,41.4127349854],"type":"Point"}
}