{
  "type": "Feature",
  "properties": {
    "iso:country":"ES",
    "sg:address":"Calle de Joaquin Costa, 5",
    "sg:city":"Garrovillas De Alconetar",
    "sg:orig_category":"Alimentaci\u00d3n General (al Por Menor)",
    "sg:phone":"+34 927 30 90 71",
    "sg:postcode":"10940",
    "sg:province":"C\u00e1ceres",
    "wof:name":"Dominguez Macias Jesus",
    "wof:placetype":"venue"
},
  "geometry": {"coordinates":[-6.5505838394,39.7115211487],"type":"Point"}
}