{
  "type": "Feature",
  "properties": {
    "addr:full":"Calle de Isla De La Alegranza, 2 San Sebastian De Los Reyes Madrid 28700",
    "addr:housenumber":"2",
    "addr:postcode":"28700",
    "addr:street":"Calle De Isla De La Alegranza",
    "iso:country":"ES",
    "sg:address":"Calle de Isla De La Alegranza, 2",
    "sg:city":"San Sebastian De Los Reyes",
    "sg:orig_category":"Art\u00cdculos De Limpieza Y De Cocina (fabricaci\u00d3n, Al Por Mayor)",
    "sg:phone":"+34 916 51 27 13",
    "sg:postcode":"28700",
    "sg:province":"Madrid",
    "wof:name":"P'hogar Distribucion Internacional De Pr",
    "wof:placetype":"venue"
},
  "geometry": {"coordinates":[-3.6253190041,40.5473556519],"type":"Point"}
}