{
  "type": "Feature",
  "properties": {
    "iso:country":"ES",
    "sg:address":"Carr Maestro Serrano, 23",
    "sg:city":"Alboraya",
    "sg:orig_category":"Grafistas",
    "sg:phone":"+34 961 85 90 56",
    "sg:postcode":"46120",
    "sg:province":"Valencia",
    "wof:name":"Boluda Bausa Pablo",
    "wof:placetype":"venue"
},
  "geometry": {"coordinates":[-0.3508479893,39.4946289062],"type":"Point"}
}