{
  "type": "Feature",
  "properties": {
    "addr:full":"Calle de Domingo Beltran De Otazu, 40 Vitoria-gasteiz \u00c1lava 01012",
    "addr:housenumber":"40",
    "addr:postcode":"01012",
    "addr:street":"Calle De Domingo Beltran De Otazu",
    "iso:country":"ES",
    "sg:address":"Calle de Domingo Beltran De Otazu, 40",
    "sg:city":"Vitoria-gasteiz",
    "sg:orig_category":"Empresas De Limpieza",
    "sg:phone":"+34 945 22 52 50",
    "sg:postcode":"01012",
    "sg:province":"\u00c1lava",
    "wof:name":"Logistimur S.l.",
    "wof:placetype":"venue"
},
  "geometry": {"coordinates":[-2.6769754887,42.8530387878],"type":"Point"}
}