{
  "type": "Feature",
  "properties": {
    "addr:full":"Carrer de Melcior De Palau, 129 Barcelona Barcelona 08014",
    "addr:housenumber":"129",
    "addr:postcode":"08014",
    "addr:street":"Carrer De Melcior De Palau",
    "iso:country":"ES",
    "sg:address":"Carrer de Melcior De Palau, 129",
    "sg:city":"Barcelona",
    "sg:orig_category":"Grabados",
    "sg:phone":"+34 934 90 68 67",
    "sg:postcode":"08014",
    "sg:province":"Barcelona",
    "wof:name":"Muniesa Gimenez Manuel",
    "wof:placetype":"venue"
},
  "geometry": {"coordinates":[2.1375129223,41.3809890747],"type":"Point"}
}