{
  "type": "Feature",
  "properties": {
    "addr:full":"Carr Infanta, 24 Mao Islas Baleares 07702",
    "addr:housenumber":"24",
    "addr:postcode":"07702",
    "addr:street":"Carr Infanta",
    "iso:country":"ES",
    "sg:address":"Carr Infanta, 24",
    "sg:city":"Mao",
    "sg:orig_category":"Abogados",
    "sg:phone":"+34 971 35 30 57",
    "sg:postcode":"07702",
    "sg:province":"Islas Baleares",
    "wof:name":"Segui Maspoch Daniel",
    "wof:placetype":"venue"
},
  "geometry": {"coordinates":[4.2650737762,39.8873214722],"type":"Point"}
}