{
  "type": "Feature",
  "properties": {
    "addr:full":"Pase Landabarri Bidea, 4 Landabarri Vizcaya 48940",
    "addr:housenumber":"4",
    "addr:postcode":"48940",
    "addr:street":"Landabarri Bidea",
    "iso:country":"ES",
    "sg:address":"Pase Landabarri Bidea, 4",
    "sg:city":"Landabarri",
    "sg:orig_category":"Importaci\u00d3n",
    "sg:phone":"+34 944 80 12 99",
    "sg:postcode":"48940",
    "sg:province":"Vizcaya",
    "sg:website":"www.embco.es",
    "wof:name":"Embco S.l.",
    "wof:placetype":"venue"
},
  "geometry": {"coordinates":[-2.9860789776,43.3275489807],"type":"Point"}
}