{
  "type": "Feature",
  "properties": {
    "iso:country":"ES",
    "sg:address":"Calle de Fortuny, 47",
    "sg:city":"Madrid",
    "sg:orig_category":"Centros De Coordinaci\u00d3n",
    "sg:phone":"+34 913 10 52 75",
    "sg:postcode":"28010",
    "sg:province":"Madrid",
    "wof:name":"Gyscoa S.l.",
    "wof:placetype":"venue"
},
  "geometry": {"coordinates":[-3.6901242733,40.4337234497],"type":"Point"}
}