{
  "type": "Feature",
  "properties": {
    "iso:country":"ES",
    "sg:address":"Calle de Esteban Mora, 41",
    "sg:city":"Madrid",
    "sg:orig_category":"Panader\u00cdas, Panader\u00cdas",
    "sg:phone":"+34 914 04 00 13",
    "sg:postcode":"28027",
    "sg:province":"Madrid",
    "wof:name":"Fernandez Guijarro Violeta",
    "wof:placetype":"venue"
},
  "geometry": {"coordinates":[-3.6542701721,40.4387588501],"type":"Point"}
}