{
  "type": "Feature",
  "properties": {
    "addr:full":"Calle de Miramar, 2 Cadiz C\u00e1diz 11010",
    "addr:housenumber":"2",
    "addr:postcode":"11010",
    "addr:street":"Calle De Miramar",
    "iso:country":"ES",
    "sg:address":"Calle de Miramar, 2",
    "sg:city":"Cadiz",
    "sg:orig_category":"Arquitectos",
    "sg:phone":"+34 956 26 24 60",
    "sg:postcode":"11010",
    "sg:province":"C\u00e1diz",
    "wof:name":"Espada Gonzalez Manuel",
    "wof:placetype":"venue"
},
  "geometry": {"coordinates":[-6.2734408379,36.5035133362],"type":"Point"}
}