{
  "type": "Feature",
  "properties": {
    "addr:full":"Ctra Cartama, Km. 0015,0 Cartama M\u00e1laga 29580",
    "addr:postcode":"29580",
    "addr:street":"Ctra Cartama Km. 0015,0;Ma\u0301Laga",
    "iso:country":"ES",
    "sg:address":"Ctra Cartama, Km. 0015,0",
    "sg:city":"Cartama",
    "sg:orig_category":"Semiller\u00cdas",
    "sg:phone":"+34 952 42 43 93",
    "sg:postcode":"29580",
    "sg:province":"M\u00e1laga",
    "wof:name":"Dos Santos Gaspar Maria Teresa",
    "wof:placetype":"venue"
},
  "geometry": {"coordinates":[-4.6037940979,36.7364044189],"type":"Point"}
}