{
  "type": "Feature",
  "properties": {
    "addr:full":"Calle de Serrano, 78 Madrid Madrid 28006",
    "addr:housenumber":"78",
    "addr:postcode":"madrid;28006",
    "addr:street":"Calle De Serrano",
    "iso:country":"ES",
    "sg:address":"Calle de Serrano, 78",
    "sg:city":"Madrid",
    "sg:orig_category":"Inmobiliaria (agencias)",
    "sg:phone":"+34 914 35 48 00",
    "sg:postcode":"28006",
    "sg:province":"Madrid",
    "wof:name":"Prolar Monedero S.l.",
    "wof:placetype":"venue"
},
  "geometry": {"coordinates":[-3.6866760254,40.4309806824],"type":"Point"}
}