{
  "type": "Feature",
  "properties": {
    "addr:full":"Calle de Pintor Murillo (del), 29 Alcobendas Madrid 28100",
    "addr:postcode":"28100",
    "addr:street":"Calle De Pintor Murillo Del;Alcobendas",
    "iso:country":"ES",
    "sg:address":"Calle de Pintor Murillo (del), 29",
    "sg:city":"Alcobendas",
    "sg:orig_category":"Fotograf\u00cda Art\u00cdstica Y Retratos",
    "sg:phone":"+34 916 62 51 34",
    "sg:postcode":"28100",
    "sg:province":"Madrid",
    "wof:name":"Diaz Bourgeot Estudio S.l.",
    "wof:placetype":"venue"
},
  "geometry": {"coordinates":[-3.6491780281,40.5439910889],"type":"Point"}
}