{
  "type": "Feature",
  "properties": {
    "iso:country":"ES",
    "sg:address":"Carrer de Vilamar, 2",
    "sg:city":"Playa De Calafell",
    "sg:orig_category":"Agentes Generales De Seguros",
    "sg:phone":"+34 977 69 09 19",
    "sg:postcode":"43820",
    "sg:province":"Tarragona",
    "wof:name":"Pedro Grifols Bartolome",
    "wof:placetype":"venue"
},
  "geometry": {"coordinates":[1.5684100389,41.1977844238],"type":"Point"}
}