{
  "type": "Feature",
  "properties": {
    "addr:full":"Calle de Pradillo, 12 Madrid Madrid 28002",
    "addr:housenumber":"12",
    "addr:postcode":"madrid;28002",
    "addr:street":"Calle De Pradillo",
    "iso:country":"ES",
    "sg:address":"Calle de Pradillo, 12",
    "sg:city":"Madrid",
    "sg:orig_category":"Inform\u00c1tica, Ofim\u00c1tica (estudios, Asesor\u00cda, Ingenier\u00cda, Formaci\u00d3n)",
    "sg:phone":"+34 915 10 09 96",
    "sg:postcode":"28002",
    "sg:province":"Madrid",
    "sg:website":"www.checksl.com",
    "wof:name":"Check Computers S.l.",
    "wof:placetype":"venue"
},
  "geometry": {"coordinates":[-3.6745929718,40.448474884],"type":"Point"}
}