{
  "type": "Feature",
  "properties": {
    "addr:full":"Psaj Briales, 16 Malaga M\u00e1laga 29009",
    "addr:housenumber":"16",
    "addr:postcode":"29009",
    "addr:street":"Briales;Ma\u0301Laga",
    "iso:country":"ES",
    "sg:address":"Psaj Briales, 16",
    "sg:city":"Malaga",
    "sg:orig_category":"Comunidades Religiosas",
    "sg:phone":"+34 952 39 19 29",
    "sg:postcode":"29009",
    "sg:province":"M\u00e1laga",
    "wof:name":"Movimiento De Apostolado Familiar San Juan De Avila",
    "wof:placetype":"venue"
},
  "geometry": {"coordinates":[-4.4302392006,36.7242660522],"type":"Point"}
}