{
  "type": "Feature",
  "properties": {
    "iso:country":"ES",
    "sg:address":"Pase Marques De Corvera, 5",
    "sg:city":"Carmen",
    "sg:classifiers":[
        {
            "category":"Casinos & Gambling",
            "type":"Entertainment"
        }
    ],
    "sg:phone":"+34 968 34 11 65",
    "sg:postcode":"30002",
    "sg:province":"Murcia",
    "sg:tags":[
        "locale",
        "de",
        "juego"
    ],
    "wof:name":"Azar 5 Slu",
    "wof:placetype":"venue"
},
  "geometry": {"coordinates":[-1.1298867464,37.9834747314],"type":"Point"}
}