{
  "type": "Feature",
  "properties": {
    "iso:country":"ES",
    "sg:address":"Avda J. Solis Ruiz, 83",
    "sg:city":"Cabra",
    "sg:orig_category":"Agentes Generales De Seguros",
    "sg:phone":"+34 957 52 43 50",
    "sg:postcode":"14940",
    "sg:province":"C\u00f3rdoba",
    "wof:name":"Moscoso Flores Jose",
    "wof:placetype":"venue"
},
  "geometry": {"coordinates":[-4.442440033,37.474357605],"type":"Point"}
}