{
  "type": "Feature",
  "properties": {
    "addr:full":"Calle de Reina Victoria, 14 Parla Madrid 28980",
    "addr:housenumber":"14",
    "addr:postcode":"28980",
    "addr:street":"Calle De Reina Victoria",
    "iso:country":"ES",
    "sg:address":"Calle de Reina Victoria, 14",
    "sg:city":"Parla",
    "sg:orig_category":"Carnicer\u00cdas, Carnicer\u00cdas",
    "sg:phone":"+34 916 98 38 63",
    "sg:postcode":"28980",
    "sg:province":"Madrid",
    "wof:name":"Carias Palomares Jose Miguel",
    "wof:placetype":"venue"
},
  "geometry": {"coordinates":[-3.7693378925,40.2349586487],"type":"Point"}
}