{
  "type": "Feature",
  "properties": {
    "addr:full":"Plaz Conde De Ferreria, 27 Malaga M\u00e1laga 29009",
    "addr:housenumber":"27",
    "addr:postcode":"29009",
    "addr:street":"Malaga Ma\u0301Laga",
    "iso:country":"ES",
    "sg:address":"Plaz Conde De Ferreria, 27",
    "sg:city":"Malaga",
    "sg:orig_category":"Reposter\u00cdas",
    "sg:phone":"+34 952 27 28 47",
    "sg:postcode":"29009",
    "sg:province":"M\u00e1laga",
    "wof:name":"Blanco Anaya Alfonso",
    "wof:placetype":"venue"
},
  "geometry": {"coordinates":[-4.4287490845,36.7309913635],"type":"Point"}
}