{
  "type": "Feature",
  "properties": {
    "iso:country":"ES",
    "sg:address":"Carrer de Callao, 2",
    "sg:city":"Barcelona",
    "sg:orig_category":"Tintes (fabricaci\u00d3n, Al Por Mayor)",
    "sg:phone":"+34 932 96 56 44",
    "sg:postcode":"08014",
    "sg:province":"Barcelona",
    "wof:name":"Tintorerias Del Eixample S.l.",
    "wof:placetype":"venue"
},
  "geometry": {"coordinates":[2.1440060139,41.3753738403],"type":"Point"}
}