{
  "type": "Feature",
  "properties": {
    "addr:full":"Carrer de Tomas Rul.lan, 68 Palma Islas Baleares 07008",
    "addr:housenumber":"68",
    "addr:postcode":"07008",
    "addr:street":"Carrer De Tomas Rul.Lan",
    "iso:country":"ES",
    "sg:address":"Carrer de Tomas Rul.lan, 68",
    "sg:city":"Palma",
    "sg:orig_category":"Cl\u00cdnicas Dentales",
    "sg:phone":"+34 971 24 05 98",
    "sg:postcode":"07008",
    "sg:province":"Islas Baleares",
    "wof:name":"Instituto Dental Doctora Acosta S.l.",
    "wof:placetype":"venue"
},
  "geometry": {"coordinates":[2.6734249592,39.5772705078],"type":"Point"}
}