{
  "type": "Feature",
  "properties": {
    "iso:country":"ES",
    "sg:address":"Av Josep Tarradellas, 1",
    "sg:city":"Barcelona",
    "sg:orig_category":"Panader\u00cdas, Panader\u00cdas",
    "sg:phone":"+34 934 30 19 02",
    "sg:postcode":"08029",
    "sg:province":"Barcelona",
    "wof:name":"Rodriguez Prieto Rafael",
    "wof:placetype":"venue"
},
  "geometry": {"coordinates":[2.1419808865,41.3812789917],"type":"Point"}
}