{
  "type": "Feature",
  "properties": {
    "addr:full":"Av Marques De Comillas, S/n Barcelona Barcelona 08038",
    "addr:housenumber":"s / n",
    "addr:postcode":"08038",
    "addr:street":"Av Marques De Comillas",
    "iso:country":"ES",
    "sg:address":"Av Marques De Comillas, S/n",
    "sg:city":"Barcelona",
    "sg:orig_category":"Inform\u00c1tica (estudios, Servicios, Asesor\u00cda, Formaci\u00d3n)",
    "sg:phone":"+34 934 24 29 15",
    "sg:postcode":"08038",
    "sg:province":"Barcelona",
    "wof:name":"Argus Serveis Telematics S.l.",
    "wof:placetype":"venue"
},
  "geometry": {"coordinates":[2.1480827332,41.3694458008],"type":"Point"}
}