{
  "type": "Feature",
  "properties": {
    "addr:full":"Calle de Maria De Molina, 3 Valladolid Valladolid 47001",
    "addr:housenumber":"3",
    "addr:postcode":"47001",
    "addr:street":"Calle De Maria De Molina",
    "iso:country":"ES",
    "sg:address":"Calle de Maria De Molina, 3",
    "sg:city":"Valladolid",
    "sg:orig_category":"Empresarios",
    "sg:phone":"+34 983 21 38 86",
    "sg:postcode":"47001",
    "sg:province":"Valladolid",
    "sg:website":"www.fundacionsiglo.org",
    "wof:name":"Fundacion Siglo Para Las Artes Y La Cultura",
    "wof:placetype":"venue"
},
  "geometry": {"coordinates":[-4.730342865,41.65001297],"type":"Point"}
}