{
  "type": "Feature",
  "properties": {
    "iso:country":"ES",
    "sg:address":"Calle de Camino Llano, 39",
    "sg:city":"Caceres",
    "sg:orig_category":"Mec\u00c1nico Del Autom\u00d3vil",
    "sg:phone":"+34 927 24 85 03",
    "sg:postcode":"10002",
    "sg:province":"C\u00e1ceres",
    "wof:name":"Vivas Perez Juan",
    "wof:placetype":"venue"
},
  "geometry": {"coordinates":[-6.3705692291,39.4700202942],"type":"Point"}
}