{
  "type": "Feature",
  "properties": {
    "addr:full":"Calle de Doctor Grai\u00d1o Del, 15 Aviles Asturias 33401",
    "addr:housenumber":"15",
    "addr:postcode":"33401",
    "addr:street":"Calle De Doctor Grain\u0303O Del",
    "iso:country":"ES",
    "sg:address":"Calle de Doctor Grai\u00d1o Del, 15",
    "sg:city":"Aviles",
    "sg:classifiers":[
        {
            "category":"Autos & Motor Vehicles",
            "subcategory":"Automobile Sales",
            "type":"Retail Goods"
        }
    ],
    "sg:phone":"+34 985 56 46 70",
    "sg:postcode":"33401",
    "sg:province":"Asturias",
    "wof:name":"Cernuda Couz Armando",
    "wof:placetype":"venue"
},
  "geometry": {"coordinates":[-5.9258260727,43.5564613342],"type":"Point"}
}