{
  "type": "Feature",
  "properties": {
    "iso:country":"ES",
    "sg:address":"Rua Maria Berdiales, 9",
    "sg:city":"Vigo",
    "sg:orig_category":"M\u00c9dicos: Neurolog\u00cda",
    "sg:phone":"+34 986 22 24 34",
    "sg:postcode":"36203",
    "sg:province":"Pontevedra",
    "wof:name":"Permuy Rodriguez Javier Eulogio",
    "wof:placetype":"venue"
},
  "geometry": {"coordinates":[-8.71986866,42.235080719],"type":"Point"}
}