{
  "type": "Feature",
  "properties": {
    "addr:full":"Carr Miquel Servet, 208 Badalona Barcelona 08912",
    "addr:housenumber":"208",
    "addr:postcode":"08912",
    "addr:street":"Carr Miquel Servet",
    "iso:country":"ES",
    "sg:address":"Carr Miquel Servet, 208",
    "sg:city":"Badalona",
    "sg:orig_category":"Fachadas",
    "sg:phone":"+34 933 83 78 42",
    "sg:postcode":"08912",
    "sg:province":"Barcelona",
    "wof:name":"Rehabilitacion Y Construccion Bonavista S.l.",
    "wof:placetype":"venue"
},
  "geometry": {"coordinates":[2.2389910221,41.4472618103],"type":"Point"}
}