{
  "type": "Feature",
  "properties": {
    "addr:full":"Calle de Capitan Salom, 5 Palma Islas Baleares 07004",
    "addr:housenumber":"5",
    "addr:postcode":"07004",
    "addr:street":"Calle De Capitan Salom",
    "iso:country":"ES",
    "sg:address":"Calle de Capitan Salom, 5",
    "sg:city":"Palma",
    "sg:orig_category":"Supermercados Y Hipermercados",
    "sg:phone":"+34 971 20 25 06",
    "sg:postcode":"07004",
    "sg:province":"Islas Baleares",
    "sg:website":"www.capraboacasa.com",
    "wof:name":"Caprabo S.a.",
    "wof:placetype":"venue"
},
  "geometry": {"coordinates":[2.6531443596,39.5895576477],"type":"Point"}
}