{
  "type": "Feature",
  "properties": {
    "iso:country":"ES",
    "sg:address":"Calle de San Miguel, 17",
    "sg:city":"Zuera",
    "sg:orig_category":"Notarios",
    "sg:phone":"+34 976 68 00 48",
    "sg:postcode":"50800",
    "sg:province":"Zaragoza",
    "wof:name":"Yuste Gonzalez De Rueda Juan Antonio",
    "wof:placetype":"venue"
},
  "geometry": {"coordinates":[-0.7870817184,41.8706512451],"type":"Point"}
}