{
  "type": "Feature",
  "properties": {
    "iso:country":"ES",
    "sg:address":"Carrer de Gonzalo Ortola, 7",
    "sg:city":"Ondara",
    "sg:orig_category":"Ebanister\u00cda",
    "sg:phone":"+34 965 76 75 32",
    "sg:postcode":"03760",
    "sg:province":"Alicante",
    "wof:name":"Tecnica En Lacados S.l.",
    "wof:placetype":"venue"
},
  "geometry": {"coordinates":[0.0206049997,38.8226318359],"type":"Point"}
}