{
  "type": "Feature",
  "properties": {
    "addr:full":"Rond Ambeles (de), 1 Teruel Teruel 44001",
    "addr:postcode":"44001",
    "iso:country":"ES",
    "sg:address":"Rond Ambeles (de), 1",
    "sg:city":"Teruel",
    "sg:orig_category":"Autob\u00das (explotaci\u00d3n Y Servicios De)",
    "sg:phone":"+34 978 60 34 50",
    "sg:postcode":"44001",
    "sg:province":"Teruel",
    "sg:website":"www.samar.es",
    "wof:name":"Autocares Samar S. A.",
    "wof:placetype":"venue"
},
  "geometry": {"coordinates":[-1.1051300764,40.3428497314],"type":"Point"}
}