{
  "type": "Feature",
  "properties": {
    "addr:full":"Calle de Buenos Aires, 12 Poligono Industrial Los Villares Salamanca 37184",
    "addr:housenumber":"12",
    "addr:postcode":"37184",
    "addr:street":"Calle De Buenos Aires;Industrial",
    "iso:country":"ES",
    "sg:address":"Calle de Buenos Aires, 12",
    "sg:city":"Poligono Industrial Los Villares",
    "sg:orig_category":"Bebidas",
    "sg:phone":"+34 923 24 45 01",
    "sg:postcode":"37184",
    "sg:province":"Salamanca",
    "wof:name":"Vicente Barrueco S.a.l.",
    "wof:placetype":"venue"
},
  "geometry": {"coordinates":[-5.6337089539,40.9970054626],"type":"Point"}
}