{
  "type": "Feature",
  "properties": {
    "iso:country":"ES",
    "sg:address":"Carrer de Sant Raimundo Pe\u00d1afort, S/n",
    "sg:city":"S. Adria Besos",
    "sg:orig_category":"Equipo Y Material Deportivo Y De Actividades Invernales Y De Monta\u00d1a",
    "sg:phone":"+34 934 62 25 23",
    "sg:postcode":"08930",
    "sg:province":"Barcelona",
    "wof:name":"Ajuntament De Sant Adria Del Besos",
    "wof:placetype":"venue"
},
  "geometry": {"coordinates":[2.1699187756,41.3879165649],"type":"Point"}
}