{
  "type": "Feature",
  "properties": {
    "iso:country":"ES",
    "sg:address":"Calle de Escultor Pablo Serrano, 4",
    "sg:city":"Almodovar Del Rio",
    "sg:orig_category":"Electricidad: Instaladores",
    "sg:phone":"+34 957 71 32 06",
    "sg:postcode":"14720",
    "sg:province":"C\u00f3rdoba",
    "wof:name":"Antenas Cordoba S.l",
    "wof:placetype":"venue"
},
  "geometry": {"coordinates":[-5.0189523697,37.8109703064],"type":"Point"}
}