{
  "type": "Feature",
  "properties": {
    "addr:full":"Carr Rei Jaume I, S/n Albalat Dels Sorells Valencia 46135",
    "addr:housenumber":"s",
    "addr:postcode":"46135",
    "addr:street":"Carr Rei Jaume I;/ N",
    "iso:country":"ES",
    "sg:address":"Carr Rei Jaume I, S/n",
    "sg:city":"Albalat Dels Sorells",
    "sg:orig_category":"C\u00c1maras De Comercio E Industria, Oficios, Agricultura",
    "sg:phone":"+34 961 49 80 41",
    "sg:postcode":"46135",
    "sg:province":"Valencia",
    "wof:name":"Norland Iberica S.a.",
    "wof:placetype":"venue"
},
  "geometry": {"coordinates":[-0.3438760042,39.5438804626],"type":"Point"}
}