{
  "type": "Feature",
  "properties": {
    "iso:country":"ES",
    "sg:address":"Calle de Rastrojo, 1",
    "sg:city":"Valladolid",
    "sg:orig_category":"Comit\u00c9s De Organizaci\u00d3n De Exposiciones, Ferias, Salones",
    "sg:phone":"+34 983 33 58 65",
    "sg:postcode":"47014",
    "sg:province":"Valladolid",
    "wof:name":"Sinergia Opc Sl",
    "wof:placetype":"venue"
},
  "geometry": {"coordinates":[-4.7449069023,41.6503677368],"type":"Point"}
}