{
  "type": "Feature",
  "properties": {
    "iso:country":"ES",
    "sg:address":"Calle de Santiago Hernandez, 53",
    "sg:city":"Valderrobres",
    "sg:orig_category":"Electrodom\u00c9sticos (al Por Menor)",
    "sg:phone":"+34 978 85 00 60",
    "sg:postcode":"44580",
    "sg:province":"Teruel",
    "wof:name":"Electrodomesticos Puyo S.cv.",
    "wof:placetype":"venue"
},
  "geometry": {"coordinates":[0.1565809995,40.8742179871],"type":"Point"}
}