{
  "type": "Feature",
  "properties": {
    "iso:country":"ES",
    "sg:address":"Calle de Tanger, 8",
    "sg:city":"Madrid",
    "sg:orig_category":"Asociaciones Humanitarias, De Cooperaci\u00d3n, De Acci\u00d3n Social",
    "sg:phone":"+34 917 78 29 60",
    "sg:postcode":"28018",
    "sg:province":"Madrid",
    "wof:name":"Madres Unidas Contra La Droga De Madrid",
    "wof:placetype":"venue"
},
  "geometry": {"coordinates":[-3.6492331028,40.3841438293],"type":"Point"}
}