{
  "type": "Feature",
  "properties": {
    "addr:full":"Calle de Ortubia, 11 Almunia De Do\u00e7a Godina Zaragoza 50100",
    "addr:housenumber":"11",
    "addr:postcode":"50100",
    "addr:street":"Calle De Ortubia",
    "iso:country":"ES",
    "sg:address":"Calle de Ortubia, 11",
    "sg:city":"Almunia De Do\u00e7a Godina",
    "sg:orig_category":"Carnicer\u00cdas, Carnicer\u00cdas",
    "sg:phone":"+34 976 60 09 37",
    "sg:postcode":"50100",
    "sg:province":"Zaragoza",
    "wof:name":"Lacarcel Moreno Isidro",
    "wof:placetype":"venue"
},
  "geometry": {"coordinates":[-1.3742870092,41.4786491394],"type":"Point"}
}