{
  "type": "Feature",
  "properties": {
    "iso:country":"ES",
    "sg:address":"Calle de Islas Cies, 55",
    "sg:city":"Madrid",
    "sg:orig_category":"Supermercados Y Hipermercados",
    "sg:phone":"+34 917 30 25 27",
    "sg:postcode":"28035",
    "sg:province":"Madrid",
    "wof:name":"Mingo Chamorro Jose De",
    "wof:placetype":"venue"
},
  "geometry": {"coordinates":[-3.7202644348,40.4790649414],"type":"Point"}
}