{
  "type": "Feature",
  "properties": {
    "addr:full":"Avda Habaneras (de Las), 38 Torrevieja Alicante 03180",
    "addr:housenumber":"38",
    "addr:postcode":"03180",
    "addr:street":"Avda Habaneras De Las",
    "iso:country":"ES",
    "sg:address":"Avda Habaneras (de Las), 38",
    "sg:city":"Torrevieja",
    "sg:orig_category":"Administradores De Bienes Y Delegados De Comunidades De Propietarios",
    "sg:phone":"+34 966 70 03 12",
    "sg:postcode":"03180",
    "sg:province":"Alicante",
    "wof:name":"Servicios E Inversiones Castmar S.l.",
    "wof:placetype":"venue"
},
  "geometry": {"coordinates":[-0.6536790133,38.0173606873],"type":"Point"}
}