{
  "type": "Feature",
  "properties": {
    "addr:full":"Calle de Gordillo, 9 Palmas De Gran Canaria Las Palmas 35008",
    "addr:housenumber":"9",
    "addr:postcode":"35008",
    "addr:street":"Calle De Gordillo",
    "iso:country":"ES",
    "sg:address":"Calle de Gordillo, 9",
    "sg:city":"Palmas De Gran Canaria",
    "sg:orig_category":"Inmobiliaria (agencias)",
    "sg:phone":"+34 928 47 22 49",
    "sg:postcode":"35008",
    "sg:province":"Las Palmas",
    "wof:name":"Jorge Fernandez Paulino",
    "wof:placetype":"venue"
},
  "geometry": {"coordinates":[-15.4258489609,28.1483001709],"type":"Point"}
}