{
  "type": "Feature",
  "properties": {
    "iso:country":"ES",
    "sg:address":"Avda Menendez Pidal, 14",
    "sg:city":"Valencia",
    "sg:orig_category":"Contenedores (mercanc\u00cdas)",
    "sg:phone":"+34 963 49 42 61",
    "sg:postcode":"46009",
    "sg:province":"Valencia",
    "sg:website":"www.atlassib.ro-atlas",
    "wof:name":"Atlassieb S.l.",
    "wof:placetype":"venue"
},
  "geometry": {"coordinates":[-0.3871994019,39.4804916382],"type":"Point"}
}