{
  "type": "Feature",
  "properties": {
    "addr:full":"Calle de Bouza Brey, 40 Cortegada Ourense 32200",
    "addr:housenumber":"40",
    "addr:postcode":"32200",
    "addr:street":"Calle De Bouza Brey",
    "iso:country":"ES",
    "sg:address":"Calle de Bouza Brey, 40",
    "sg:city":"Cortegada",
    "sg:orig_category":"Cajas De Ahorro",
    "sg:phone":"+34 988 48 30 05",
    "sg:postcode":"32200",
    "sg:province":"Ourense",
    "sg:website":"www.caixanova.es",
    "wof:name":"Caixa De Aforros De Vigo Ourense E Pontevedra",
    "wof:placetype":"venue"
},
  "geometry": {"coordinates":[-8.1639022827,42.203994751],"type":"Point"}
}