{
  "type": "Feature",
  "properties": {
    "iso:country":"ES",
    "sg:address":"Calle de Roman Ochando, 15",
    "sg:city":"Sinarcas",
    "sg:orig_category":"Productores Recolectores, Venta Directa De Vinos",
    "sg:phone":"+34 962 31 54 36",
    "sg:postcode":"46320",
    "sg:province":"Valencia",
    "sg:website":"www.bodegassinarcas.es",
    "wof:name":"Caja Campo",
    "wof:placetype":"venue"
},
  "geometry": {"coordinates":[-1.2299489975,39.7316398621],"type":"Point"}
}