{
  "type": "Feature",
  "properties": {
    "iso:country":"ES",
    "sg:address":"Pase Cortes De Aragon, 14",
    "sg:city":"Calatayud",
    "sg:orig_category":"Farmacias",
    "sg:phone":"+34 976 88 18 31",
    "sg:postcode":"50300",
    "sg:province":"Zaragoza",
    "wof:name":"Palacian Gil Marta",
    "wof:placetype":"venue"
},
  "geometry": {"coordinates":[-1.6396189928,41.351852417],"type":"Point"}
}