{
  "type": "Feature",
  "properties": {
    "addr:full":"S. Alberes, 29 Empuriabrava Girona 17487",
    "addr:housenumber":"29",
    "addr:postcode":"17487",
    "addr:street":"S. Alberes",
    "iso:country":"ES",
    "sg:address":"S. Alberes, 29",
    "sg:city":"Empuriabrava",
    "sg:orig_category":"Inmobiliaria (agencias)",
    "sg:phone":"+34 972 45 39 99",
    "sg:postcode":"17487",
    "sg:province":"Girona",
    "wof:name":"Dynamic Inmo,s.a,",
    "wof:placetype":"venue"
},
  "geometry": {"coordinates":[3.1070549488,42.2568092346],"type":"Point"}
}