{
  "type": "Feature",
  "properties": {
    "addr:full":"Avda Castillos (los), S/n Alcorcon Madrid 28925",
    "addr:postcode":"28925",
    "addr:street":"Avda Castillos Los S / N Alcorcon",
    "iso:country":"ES",
    "sg:address":"Avda Castillos (los), S/n",
    "sg:city":"Alcorcon",
    "sg:orig_category":"Polideportivos",
    "sg:phone":"+34 916 10 50 52",
    "sg:postcode":"28925",
    "sg:province":"Madrid",
    "wof:name":"Patronato Deportivo Municipal",
    "wof:placetype":"venue"
},
  "geometry": {"coordinates":[-3.8122498989,40.3584022522],"type":"Point"}
}