{
  "type": "Feature",
  "properties": {
    "iso:country":"ES",
    "sg:address":"Calle de Julian Romea, 11",
    "sg:city":"Madrid",
    "sg:orig_category":"Acondicionamiento, Mantenimiento De Jardines Y Parques",
    "sg:phone":"+34 915 54 22 61",
    "sg:postcode":"28003",
    "sg:province":"Madrid",
    "wof:name":"Garcia-fogeda Prado Angel",
    "wof:placetype":"venue"
},
  "geometry": {"coordinates":[-3.7150149345,40.4425773621],"type":"Point"}
}