{
  "type": "Feature",
  "properties": {
    "iso:country":"ES",
    "sg:address":"Calle de Manzanares, 6",
    "sg:city":"Coria Rio",
    "sg:orig_category":"Molduras, Junquillos, Listones Y Molduras Perforadas",
    "sg:phone":"+34 954 77 53 44",
    "sg:postcode":"41100",
    "sg:province":"Sevilla",
    "wof:name":"Bodegon Rociero La Resaca S.l.",
    "wof:placetype":"venue"
},
  "geometry": {"coordinates":[-6.0584440231,37.2773513794],"type":"Point"}
}