{
  "type": "Feature",
  "properties": {
    "addr:full":"Meloxo, S/n Meloxo Pontevedra 36989",
    "addr:postcode":"36989",
    "addr:street":"Meloxo S / N",
    "iso:country":"ES",
    "sg:address":"Meloxo, S/n",
    "sg:city":"Meloxo",
    "sg:orig_category":"Centros De Educaci\u00d3n Especial",
    "sg:phone":"+34 986 73 18 14",
    "sg:postcode":"36989",
    "sg:province":"Pontevedra",
    "wof:name":"Colexio Publico De Melojo",
    "wof:placetype":"venue"
},
  "geometry": {"coordinates":[-8.8799791336,42.4873313904],"type":"Point"}
}