{
  "type": "Feature",
  "properties": {
    "iso:country":"ES",
    "sg:address":"Avda Najera, 7",
    "sg:city":"Santo Domingo De La Calzada",
    "sg:orig_category":"Patatas (al Por Mayor)",
    "sg:phone":"+34 941 34 02 00",
    "sg:postcode":"26250",
    "sg:province":"La Rioja",
    "sg:website":"www.carsa.net",
    "wof:name":"Comercial Agricola Riojana S. A.",
    "wof:placetype":"venue"
},
  "geometry": {"coordinates":[-2.9466590881,42.4394683838],"type":"Point"}
}