{
  "type": "Feature",
  "properties": {
    "iso:country":"ES",
    "sg:address":"Avgd Exercit (l'), 43",
    "sg:city":"Betera",
    "sg:orig_category":"Reposter\u00cdas",
    "sg:phone":"+34 961 60 22 36",
    "sg:postcode":"46117",
    "sg:province":"Valencia",
    "wof:name":"Navarro Navarro Francisco",
    "wof:placetype":"venue"
},
  "geometry": {"coordinates":[-0.4646939933,39.5906906128],"type":"Point"}
}