{
  "type": "Feature",
  "properties": {
    "iso:country":"ES",
    "sg:address":"Calle de Pino, 21",
    "sg:city":"Alcala Guadaira",
    "sg:orig_category":"Molduras, Junquillos, Listones Y Molduras Perforadas",
    "sg:phone":"+34 955 68 44 69",
    "sg:postcode":"41500",
    "sg:province":"Sevilla",
    "wof:name":"Navarro Vega Juan Jose",
    "wof:placetype":"venue"
},
  "geometry": {"coordinates":[-5.8331389427,37.3315315247],"type":"Point"}
}