{
  "type": "Feature",
  "properties": {
    "addr:full":"Avda Ricardo Carapeto Zambrano, 61 Badajoz Badajoz 06008",
    "addr:housenumber":"61",
    "addr:postcode":"06008",
    "addr:street":"Avda Ricardo Carapeto Zambrano",
    "iso:country":"ES",
    "sg:address":"Avda Ricardo Carapeto Zambrano, 61",
    "sg:city":"Badajoz",
    "sg:orig_category":"Bancos",
    "sg:phone":"+34 924 26 07 63",
    "sg:postcode":"06008",
    "sg:province":"Badajoz",
    "wof:name":"Banco Popular Espa\u00f1ol S.a.",
    "wof:placetype":"venue"
},
  "geometry": {"coordinates":[-6.9513192177,38.8783493042],"type":"Point"}
}