{
  "type": "Feature",
  "properties": {
    "iso:country":"ES",
    "sg:address":"Plaz Mercado, 11",
    "sg:city":"Barbastro",
    "sg:orig_category":"Asociaciones, Organismos Culturales Y Socioeducativos",
    "sg:phone":"+34 974 31 17 00",
    "sg:postcode":"22300",
    "sg:province":"Huesca",
    "wof:name":"Asociacion Labierre",
    "wof:placetype":"venue"
},
  "geometry": {"coordinates":[0.1252714992,42.0368881226],"type":"Point"}
}