{
  "type": "Feature",
  "properties": {
    "iso:country":"ES",
    "sg:address":"Carr Maluquer Salvador, 29",
    "sg:city":"Girona",
    "sg:orig_category":"Arquitectos",
    "sg:phone":"+34 972 22 17 50",
    "sg:postcode":"17002",
    "sg:province":"Girona",
    "wof:name":"Romagos Planas Narcis",
    "wof:placetype":"venue"
},
  "geometry": {"coordinates":[2.822685957,41.9766273499],"type":"Point"}
}