{
  "type": "Feature",
  "properties": {
    "iso:country":"ES",
    "sg:address":"Calle de Vi\u00d1a (de La), 47",
    "sg:city":"Velilla S.antonio",
    "sg:orig_category":"Reparaciones Y Remolcado De Veh\u00cdculos",
    "sg:phone":"+34 916 60 76 69",
    "sg:postcode":"28891",
    "sg:province":"Madrid",
    "wof:name":"Moreno Medina Francisco",
    "wof:placetype":"venue"
},
  "geometry": {"coordinates":[-3.4881379604,40.3709983826],"type":"Point"}
}