{
  "type": "Feature",
  "properties": {
    "iso:country":"ES",
    "sg:address":"Calle de Lope De Vega, 8",
    "sg:city":"Le\u00f3n",
    "sg:orig_category":"Agencias De Viajes",
    "sg:phone":"+34 987 24 55 60",
    "sg:postcode":"24002",
    "sg:province":"Le\u00f3n",
    "wof:name":"Viajes Mantur Sl",
    "wof:placetype":"venue"
},
  "geometry": {"coordinates":[-5.5724959373,42.599407196],"type":"Point"}
}