{
  "type": "Feature",
  "properties": {
    "addr:full":"Avda Gernikako Arbola, 6 San Vicente De Barakaldo Vizcaya 48902",
    "addr:housenumber":"6",
    "addr:postcode":"48902",
    "addr:street":"Avda Gernikako Arbola",
    "iso:country":"ES",
    "sg:address":"Avda Gernikako Arbola, 6",
    "sg:city":"San Vicente De Barakaldo",
    "sg:orig_category":"Agencias Y Agentes Comerciales, Representantes",
    "sg:phone":"+34 944 37 61 08",
    "sg:postcode":"48902",
    "sg:province":"Vizcaya",
    "wof:name":"Varona Huidobro Leandro",
    "wof:placetype":"venue"
},
  "geometry": {"coordinates":[-2.9909009933,43.2942848206],"type":"Point"}
}