{
  "type": "Feature",
  "properties": {
    "iso:country":"ES",
    "sg:address":"Ctra Huercal Overa, S/n",
    "sg:city":"Pulpi",
    "sg:orig_category":"Mec\u00c1nico Del Autom\u00d3vil",
    "sg:phone":"+34 950 46 54 98",
    "sg:postcode":"04640",
    "sg:province":"Almer\u00eda",
    "wof:name":"Locrifer S.l.",
    "wof:placetype":"venue"
},
  "geometry": {"coordinates":[-1.7453733683,37.4054756165],"type":"Point"}
}