{
  "type": "Feature",
  "properties": {
    "addr:full":"Pg S'abanell, S/n Blanes Girona 17300",
    "addr:housenumber":"s / n",
    "addr:postcode":"17300",
    "addr:street":"Pg S'Abanell",
    "iso:country":"ES",
    "sg:address":"Pg S'abanell, S/n",
    "sg:city":"Blanes",
    "sg:orig_category":"Restaurantes",
    "sg:phone":"+34 972 33 57 07",
    "sg:postcode":"17300",
    "sg:province":"Girona",
    "wof:name":"Artiola Vallespi Jorge",
    "wof:placetype":"venue"
},
  "geometry": {"coordinates":[2.7829604149,41.6922187805],"type":"Point"}
}