{
  "type": "Feature",
  "properties": {
    "iso:country":"ES",
    "sg:address":"Calle de Manuel Roldan, 8",
    "sg:city":"S. Fernando",
    "sg:orig_category":"Agencias Y Agentes Comerciales, Representantes",
    "sg:phone":"+34 956 88 34 99",
    "sg:postcode":"11100",
    "sg:province":"C\u00e1diz",
    "wof:name":"Del Solar Fernandez Victoriano",
    "wof:placetype":"venue"
},
  "geometry": {"coordinates":[-6.1944160461,36.4686508179],"type":"Point"}
}