{
  "type": "Feature",
  "properties": {
    "iso:country":"ES",
    "sg:address":"Carr Calvari, S/n",
    "sg:city":"Sineu",
    "sg:orig_category":"Cooperativas Agr\u00cdcolas",
    "sg:phone":"+34 971 52 03 89",
    "sg:postcode":"07510",
    "sg:province":"Islas Baleares",
    "wof:name":"Sociedad Cooperativa Limitada Agraria De Sineu",
    "wof:placetype":"venue"
},
  "geometry": {"coordinates":[3.0102500916,39.6449584961],"type":"Point"}
}