{
  "type": "Feature",
  "properties": {
    "iso:country":"ES",
    "sg:address":"Calle de Doctor Ayela, 28",
    "sg:city":"Alacant",
    "sg:orig_category":"Seguridad Social",
    "sg:phone":"+34 965 14 27 60",
    "sg:postcode":"03013",
    "sg:province":"Alicante",
    "wof:name":"Instituto Nacional De La Seguridad Social-direccion Provincial De Alicante",
    "wof:placetype":"venue"
},
  "geometry": {"coordinates":[-0.4771414101,38.3540763855],"type":"Point"}
}