{
  "type": "Feature",
  "properties": {
    "addr:full":"Cmno Ca\u00d1adillas, 22 Alcaudete Ja\u00e9n 23660",
    "addr:housenumber":"22",
    "addr:postcode":"23660",
    "addr:street":"Cmno Can\u0303Adillas;Jae\u0301N",
    "iso:country":"ES",
    "sg:address":"Cmno Ca\u00d1adillas, 22",
    "sg:city":"Alcaudete",
    "sg:orig_category":"Charcuter\u00cdas (al Por Mayor)",
    "sg:phone":"+34 953 70 85 35",
    "sg:postcode":"23660",
    "sg:province":"Ja\u00e9n",
    "wof:name":"Hijos De Miguel Ariza S.l.",
    "wof:placetype":"venue"
},
  "geometry": {"coordinates":[-4.0798048973,37.5945205688],"type":"Point"}
}