{
  "type": "Feature",
  "properties": {
    "iso:country":"ES",
    "sg:address":"Avda Juan Xxiii, 49",
    "sg:city":"Malaga",
    "sg:orig_category":"Inmobiliaria (agencias)",
    "sg:phone":"+34 952 36 38 92",
    "sg:postcode":"29006",
    "sg:province":"M\u00e1laga",
    "wof:name":"Ibercasa De Malaga Gestion Y Promocion S.l.",
    "wof:placetype":"venue"
},
  "geometry": {"coordinates":[-4.4457688332,36.7107124329],"type":"Point"}
}