{
  "type": "Feature",
  "properties": {
    "addr:full":"Luga Lomo Galeon, 18 Santa Agueda Las Palmas 35290",
    "addr:housenumber":"18",
    "addr:postcode":"35290",
    "addr:street":"Galeon",
    "iso:country":"ES",
    "sg:address":"Luga Lomo Galeon, 18",
    "sg:city":"Santa Agueda",
    "sg:orig_category":"Delegados, Agentes De Tr\u00c1nsito, Auxiliares De Transporte Internacional",
    "sg:phone":"+34 928 17 21 81",
    "sg:postcode":"35290",
    "sg:province":"Las Palmas",
    "wof:name":"Leon Leon Juan",
    "wof:placetype":"venue"
},
  "geometry": {"coordinates":[-15.5732269287,27.9242973328],"type":"Point"}
}