{
  "type": "Feature",
  "properties": {
    "iso:country":"ES",
    "sg:address":"Carrer de Vte Ya\u00d1ez Pinzon, 4",
    "sg:city":"Palma",
    "sg:classifiers":[
        {
            "category":"Personal",
            "subcategory":"Barber",
            "type":"Services"
        }
    ],
    "sg:phone":"+34 971 45 42 13",
    "sg:postcode":"07014",
    "sg:province":"Islas Baleares",
    "sg:tags":[
        "caballeros",
        "de",
        "peluqueros"
    ],
    "wof:name":"Castellano Martin Marcos",
    "wof:placetype":"venue"
},
  "geometry": {"coordinates":[2.6298639774,39.5692672729],"type":"Point"}
}