{
  "type": "Feature",
  "properties": {
    "iso:country":"ES",
    "sg:address":"Calle de Larrinaga, 3",
    "sg:city":"Bilbao",
    "sg:orig_category":"Asociaciones, Organismos Culturales Y Socioeducativos",
    "sg:phone":"+34 944 16 61 23",
    "sg:postcode":"48006",
    "sg:province":"Vizcaya",
    "wof:name":"Asociacion Para La Cultura Y El Ocio De La Tercera Edad",
    "wof:placetype":"venue"
},
  "geometry": {"coordinates":[-2.920958519,43.2561988831],"type":"Point"}
}