{
  "type": "Feature",
  "properties": {
    "iso:country":"ES",
    "sg:address":"Carrer de Francesc Macia I Llussa, 1",
    "sg:city":"Lloret Mar",
    "sg:orig_category":"Centros Empresariales",
    "sg:phone":"+34 972 37 33 12",
    "sg:postcode":"17310",
    "sg:province":"Girona",
    "wof:name":"Guardiola Ribe S.a.",
    "wof:placetype":"venue"
},
  "geometry": {"coordinates":[2.846834898,41.6981697083],"type":"Point"}
}