{
  "type": "Feature",
  "properties": {
    "iso:country":"ES",
    "sg:address":"Calle de Arabial, 104",
    "sg:city":"Granada",
    "sg:orig_category":"Material Y Suministros Para Perforaciones, Sondeos",
    "sg:phone":"+34 958 20 05 97",
    "sg:postcode":"18003",
    "sg:province":"Granada",
    "wof:name":"Walkira S.l.",
    "wof:placetype":"venue"
},
  "geometry": {"coordinates":[-3.6123569012,37.1789970398],"type":"Point"}
}