{
  "type": "Feature",
  "properties": {
    "addr:full":"Ctra Torre Pacheco, Km. 0002,0 Los Alcazares Murcia 30710",
    "addr:postcode":"30710",
    "addr:street":"Ctra Torre Pacheco Km. 0002,0 Los Alcazares",
    "iso:country":"ES",
    "sg:address":"Ctra Torre Pacheco, Km. 0002,0",
    "sg:city":"Los Alcazares",
    "sg:orig_category":"Muebles, Minoristas",
    "sg:phone":"+34 968 58 25 46",
    "sg:postcode":"30710",
    "sg:province":"Murcia",
    "wof:name":"Global Imports & Retail S.l.",
    "wof:placetype":"venue"
},
  "geometry": {"coordinates":[-0.8867102861,37.7383804321],"type":"Point"}
}