{
  "type": "Feature",
  "properties": {
    "iso:country":"ES",
    "sg:address":"Carr Barcelona, 165",
    "sg:city":"Girona",
    "sg:orig_category":"Bazares, Art\u00cdculos De Limpieza Y De Cocina (al Por Menor)",
    "sg:phone":"+34 972 41 28 26",
    "sg:postcode":"17003",
    "sg:province":"Girona",
    "wof:name":"Expostore S.l.",
    "wof:placetype":"venue"
},
  "geometry": {"coordinates":[2.8129279613,41.9659576416],"type":"Point"}
}