{
  "type": "Feature",
  "properties": {
    "addr:full":"Calle de Hibisco, 24 Badajoz Badajoz 06011",
    "addr:housenumber":"24",
    "addr:postcode":"06011",
    "addr:street":"Calle De Hibisco",
    "iso:country":"ES",
    "sg:address":"Calle de Hibisco, 24",
    "sg:city":"Badajoz",
    "sg:orig_category":"Farmacias",
    "sg:phone":"+34 924 23 92 53",
    "sg:postcode":"06011",
    "sg:province":"Badajoz",
    "wof:name":"Cortes Gonzalez Maria Lourdes",
    "wof:placetype":"venue"
},
  "geometry": {"coordinates":[-6.9887337685,38.8582839966],"type":"Point"}
}