{
  "type": "Feature",
  "properties": {
    "iso:country":"ES",
    "sg:address":"Calle de Plateria, 10",
    "sg:city":"San Bartolome",
    "sg:orig_category":"\u00d3ptica: Instrumentos (fabricaci\u00d3n)",
    "sg:phone":"+34 968 35 50 61",
    "sg:postcode":"30004",
    "sg:province":"Murcia",
    "wof:name":"Tomas Marco Elena",
    "wof:placetype":"venue"
},
  "geometry": {"coordinates":[-1.1317559481,37.9854431152],"type":"Point"}
}