{
  "type": "Feature",
  "properties": {
    "iso:country":"ES",
    "sg:address":"Pl Herenni, 11",
    "sg:city":"Barcelona",
    "sg:orig_category":"Alimentaci\u00d3n General (al Por Menor)",
    "sg:phone":"+34 934 26 81 08",
    "sg:postcode":"08014",
    "sg:province":"Barcelona",
    "wof:name":"Rocamora Salat Joaquin",
    "wof:placetype":"venue"
},
  "geometry": {"coordinates":[2.1435620785,41.3761177063],"type":"Point"}
}