{
  "type": "Feature",
  "properties": {
    "iso:country":"ES",
    "sg:address":"Calle de Melendez Valdes, 19",
    "sg:city":"Madrid",
    "sg:orig_category":"Ingenier\u00cda, Centros De Estudios (diversos)",
    "sg:phone":"+34 914 45 82 52",
    "sg:postcode":"28015",
    "sg:province":"Madrid",
    "wof:name":"Mu\u00f1oz Sancho Miguel",
    "wof:placetype":"venue"
},
  "geometry": {"coordinates":[-3.7111339569,40.4328117371],"type":"Point"}
}