{
  "type": "Feature",
  "properties": {
    "addr:full":"Calle de Valverde, 19 Madrid Madrid 28004",
    "addr:housenumber":"19",
    "addr:postcode":"madrid;28004",
    "addr:street":"Calle De Valverde",
    "iso:country":"ES",
    "sg:address":"Calle de Valverde, 19",
    "sg:city":"Madrid",
    "sg:orig_category":"Abogados",
    "sg:phone":"+34 915 32 40 77",
    "sg:postcode":"28004",
    "sg:province":"Madrid",
    "wof:name":"Perez Pousa Jose Angel",
    "wof:placetype":"venue"
},
  "geometry": {"coordinates":[-3.7019000053,40.4222679138],"type":"Point"}
}