{
  "type": "Feature",
  "properties": {
    "iso:country":"ES",
    "sg:address":"Carrer de Sinia Morera, 2",
    "sg:city":"Sitges",
    "sg:orig_category":"Abogados",
    "sg:phone":"+34 938 11 09 90",
    "sg:postcode":"08870",
    "sg:province":"Barcelona",
    "wof:name":"Alavedra Advocats S.l.",
    "wof:placetype":"venue"
},
  "geometry": {"coordinates":[1.8053812981,41.2384872437],"type":"Point"}
}