{
  "type": "Feature",
  "properties": {
    "iso:country":"ES",
    "sg:address":"Avgd Joan Xxiii, De, 97",
    "sg:city":"Carcaixent",
    "sg:orig_category":"Mec\u00c1nico Del Autom\u00d3vil",
    "sg:phone":"+34 962 43 25 40",
    "sg:postcode":"46740",
    "sg:province":"Valencia",
    "wof:name":"Guzman Santamaria Vicente",
    "wof:placetype":"venue"
},
  "geometry": {"coordinates":[-0.4427599907,39.1241416931],"type":"Point"}
}