{
  "type": "Feature",
  "properties": {
    "iso:country":"ES",
    "sg:address":"Calle de Ramon Y Cajal, 17",
    "sg:city":"Miranda Ebro",
    "sg:orig_category":"Bisuter\u00cda, Joyer\u00cda, Relojer\u00cda (al Por Menor)",
    "sg:phone":"+34 947 31 03 79",
    "sg:postcode":"09200",
    "sg:province":"Burgos",
    "wof:name":"Fresno Lopez Maria Reyes",
    "wof:placetype":"venue"
},
  "geometry": {"coordinates":[-2.9452259541,42.686290741],"type":"Point"}
}