{
  "type": "Feature",
  "properties": {
    "iso:country":"ES",
    "sg:address":"Pase Rollo, 5",
    "sg:city":"Salamanca",
    "sg:orig_category":"Barnizadores",
    "sg:phone":"+34 923 23 23 84",
    "sg:postcode":"37003",
    "sg:province":"Salamanca",
    "wof:name":"Sequeros Dominguez Francisco",
    "wof:placetype":"venue"
},
  "geometry": {"coordinates":[-5.6535181999,40.9650421143],"type":"Point"}
}