{
  "type": "Feature",
  "properties": {
    "iso:country":"ES",
    "sg:address":"Calle de Jata, 3",
    "sg:city":"Getxo",
    "sg:orig_category":"Promotores Constructores",
    "sg:phone":"+34 944 60 40 64",
    "sg:postcode":"48990",
    "sg:province":"Vizcaya",
    "wof:name":"Construcciones Andoni Deusto",
    "wof:placetype":"venue"
},
  "geometry": {"coordinates":[-3.0135359764,43.3574295044],"type":"Point"}
}