{
  "type": "Feature",
  "properties": {
    "iso:country":"ES",
    "sg:address":"Carrer de Francoli, 29",
    "sg:city":"Barcelona",
    "sg:orig_category":"Poller\u00cda Y Caza (al Por Menor)",
    "sg:phone":"+34 932 18 78 41",
    "sg:postcode":"08006",
    "sg:province":"Barcelona",
    "wof:name":"Sastrada Bueno Francisco Javier",
    "wof:placetype":"venue"
},
  "geometry": {"coordinates":[2.1472620964,41.4040527344],"type":"Point"}
}