{
  "type": "Feature",
  "properties": {
    "addr:full":"Ctra. General, Km. 0025,5 La Matanza Acentejo Santa Cruz De Tenerife 38370",
    "addr:postcode":"38370",
    "addr:street":"Ctra. General Km. 0025,5",
    "iso:country":"ES",
    "sg:address":"Ctra. General, Km. 0025,5",
    "sg:city":"La Matanza Acentejo",
    "sg:orig_category":"Quincaller\u00cda (al Por Menor)",
    "sg:phone":"+34 922 57 93 44",
    "sg:postcode":"38370",
    "sg:province":"Santa Cruz De Tenerife",
    "wof:name":"Martin De La Cruz Rosa Maria",
    "wof:placetype":"venue"
},
  "geometry": {"coordinates":[-16.2645397186,28.4603805542],"type":"Point"}
}