{
  "type": "Feature",
  "properties": {
    "iso:country":"ES",
    "sg:address":"Ptge Marimon, 9",
    "sg:city":"Barcelona",
    "sg:orig_category":"Pod\u00d3logos: Pedicuros",
    "sg:phone":"+34 932 00 61 53",
    "sg:postcode":"08021",
    "sg:province":"Barcelona",
    "wof:name":"Arenas Torras Jaime",
    "wof:placetype":"venue"
},
  "geometry": {"coordinates":[2.1479701996,41.3944511414],"type":"Point"}
}