{
  "type": "Feature",
  "properties": {
    "iso:country":"ES",
    "sg:address":"Pase Marina Espa\u00d1ola (de La), 18",
    "sg:city":"Ceuta",
    "sg:orig_category":"Centros Empresariales",
    "sg:phone":"+34 856 20 02 82",
    "sg:postcode":"51001",
    "sg:province":"Ceuta",
    "wof:name":"Telefonica Data Espa\u00f1a S.a.",
    "wof:placetype":"venue"
},
  "geometry": {"coordinates":[-5.3302302361,35.8947601318],"type":"Point"}
}