{
  "type": "Feature",
  "properties": {
    "iso:country":"ES",
    "sg:address":"Calle de Almazara, 3",
    "sg:city":"Villanueva Rio Segura",
    "sg:orig_category":"Administraciones Regionales, Departamentales Y Locales",
    "sg:phone":"+34 968 69 86 01",
    "sg:postcode":"30613",
    "sg:province":"Murcia",
    "wof:name":"Ayuntamiento De Villanueva Del Rio Segur",
    "wof:placetype":"venue"
},
  "geometry": {"coordinates":[-1.2699043751,38.0745315552],"type":"Point"}
}