{
  "type": "Feature",
  "properties": {
    "iso:country":"ES",
    "sg:address":"Rua Xeneral Aranda, 18",
    "sg:city":"Ourense",
    "sg:orig_category":"Imprenta",
    "sg:phone":"+34 988 21 90 08",
    "sg:postcode":"32001",
    "sg:province":"Ourense",
    "wof:name":"Perez Canabal Manuel Alvaro",
    "wof:placetype":"venue"
},
  "geometry": {"coordinates":[-7.8666148186,42.3469543457],"type":"Point"}
}