{
  "type": "Feature",
  "properties": {
    "iso:country":"ES",
    "sg:address":"Carrer de Malloles, 8",
    "sg:city":"Vic",
    "sg:orig_category":"Transportes Frigor\u00cdficos",
    "sg:phone":"+34 938 89 29 52",
    "sg:postcode":"08500",
    "sg:province":"Barcelona",
    "wof:name":"Fredelectric Vic S.l.",
    "wof:placetype":"venue"
},
  "geometry": {"coordinates":[2.2832438946,41.9458885193],"type":"Point"}
}