{
  "type": "Feature",
  "properties": {
    "addr:full":"Calle de 28 (monte Colorado), 10 Monte Colorado Valencia 46185",
    "addr:housenumber":"28;10",
    "addr:postcode":"46185",
    "addr:street":"Calle De;Colorado",
    "iso:country":"ES",
    "sg:address":"Calle de 28 (monte Colorado), 10",
    "sg:city":"Monte Colorado",
    "sg:orig_category":"Agencias Y Asesores De Publicidad",
    "sg:phone":"+34 962 76 18 60",
    "sg:postcode":"46185",
    "sg:province":"Valencia",
    "wof:name":"Pop Team Display S.l.",
    "wof:placetype":"venue"
},
  "geometry": {"coordinates":[-0.3768048882,39.4702377319],"type":"Point"}
}