{
  "type": "Feature",
  "properties": {
    "addr:full":"Calle de Refugio, 7 Zaragoza Zaragoza 50001",
    "addr:housenumber":"7",
    "addr:postcode":"50001",
    "addr:street":"Calle De Refugio",
    "iso:country":"ES",
    "sg:address":"Calle de Refugio, 7",
    "sg:city":"Zaragoza",
    "sg:orig_category":"Guarder\u00cdas",
    "sg:phone":"+34 976 20 39 24",
    "sg:postcode":"50001",
    "sg:province":"Zaragoza",
    "wof:name":"Bolandrina S.l.l.",
    "wof:placetype":"venue"
},
  "geometry": {"coordinates":[-0.8777120113,41.6531944275],"type":"Point"}
}