{
  "type": "Feature",
  "properties": {
    "addr:full":"Plaz Iglesia, 2 Balsapintada Murcia 30332",
    "addr:housenumber":"2",
    "addr:postcode":"30332",
    "addr:street":"Iglesia",
    "iso:country":"ES",
    "sg:address":"Plaz Iglesia, 2",
    "sg:city":"Balsapintada",
    "sg:orig_category":"Iglesia Cat\u00d3lica",
    "sg:phone":"+34 968 15 16 33",
    "sg:postcode":"30332",
    "sg:province":"Murcia",
    "wof:name":"Parroquia La Purisima",
    "wof:placetype":"venue"
},
  "geometry": {"coordinates":[-1.103227973,37.7544136047],"type":"Point"}
}