{
  "type": "Feature",
  "properties": {
    "iso:country":"ES",
    "sg:address":"Calle de Rio, 2",
    "sg:city":"Pe\u00e7aranda De Duero",
    "sg:orig_category":"Agricultura: Abastecimiento Y Cosechado (negocio)",
    "sg:phone":"+34 947 55 21 49",
    "sg:postcode":"09410",
    "sg:province":"Burgos",
    "wof:name":"Jose Luis Andres Tudela Y Otro S.cv.",
    "wof:placetype":"venue"
},
  "geometry": {"coordinates":[-3.4791579247,41.6870727539],"type":"Point"}
}