{
  "type": "Feature",
  "properties": {
    "iso:country":"ES",
    "sg:address":"Poli Pol.ind.belcaire, S/n",
    "sg:city":"Vall D'uixo",
    "sg:orig_category":"Institutos De Belleza (productos Y Aparatos)",
    "sg:phone":"+34 964 66 13 44",
    "sg:postcode":"12600",
    "sg:province":"Castell\u00f3n",
    "wof:name":"Construplas S.l.",
    "wof:placetype":"venue"
},
  "geometry": {"coordinates":[-0.0456800014,39.9851417542],"type":"Point"}
}