{
  "type": "Feature",
  "properties": {
    "iso:country":"ES",
    "sg:address":"A Ribeira Do Maio, 45",
    "sg:city":"Ribeira De Maio",
    "sg:orig_category":"Alimentaci\u00d3n General (al Por Mayor)",
    "sg:phone":"+34 981 76 41 20",
    "sg:postcode":"15240",
    "sg:province":"La Coru\u00f1a",
    "wof:name":"Piensos Y Cereales Caldas S.l.",
    "wof:placetype":"venue"
},
  "geometry": {"coordinates":[-8.9785079956,42.7931213379],"type":"Point"}
}