{
  "type": "Feature",
  "properties": {
    "addr:full":"Calle de Juan Mari Altuna Kalea, 10 Durango Vizcaya 48200",
    "addr:housenumber":"10",
    "addr:postcode":"48200",
    "addr:street":"Calle De Juan Mari Altuna Kalea",
    "iso:country":"ES",
    "sg:address":"Calle de Juan Mari Altuna Kalea, 10",
    "sg:city":"Durango",
    "sg:orig_category":"Moquetas, Alfombras (al Por Menor)",
    "sg:phone":"+34 946 81 00 38",
    "sg:postcode":"48200",
    "sg:province":"Vizcaya",
    "wof:name":"Gonzalez Zubillaga Fausto",
    "wof:placetype":"venue"
},
  "geometry": {"coordinates":[-2.6281061172,43.1683311462],"type":"Point"}
}