{
  "type": "Feature",
  "properties": {
    "iso:country":"ES",
    "sg:address":"Carrer de Guillermo Marconi, 7",
    "sg:city":"Castelldefels",
    "sg:orig_category":"Transportes Por V\u00cdas Navegables",
    "sg:phone":"+34 936 65 38 35",
    "sg:postcode":"08860",
    "sg:province":"Barcelona",
    "wof:name":"Cao Lopez Manuel",
    "wof:placetype":"venue"
},
  "geometry": {"coordinates":[1.9806449413,41.2847290039],"type":"Point"}
}