{
  "type": "Feature",
  "properties": {
    "addr:full":"Avda Zumalacarregui, 97 Bilbao Vizcaya 48007",
    "addr:housenumber":"97",
    "addr:postcode":"48007",
    "addr:street":"Avda Zumalacarregui",
    "iso:country":"ES",
    "sg:address":"Avda Zumalacarregui, 97",
    "sg:city":"Bilbao",
    "sg:orig_category":"Aparatos De Iluminaci\u00d3n (al Por Menor)",
    "sg:phone":"+34 944 45 86 26",
    "sg:postcode":"48007",
    "sg:province":"Vizcaya",
    "wof:name":"Zulueta Y Otros C.b",
    "wof:placetype":"venue"
},
  "geometry": {"coordinates":[-2.9166278839,43.2628173828],"type":"Point"}
}