{
  "type": "Feature",
  "properties": {
    "addr:full":"Cust Jesus, 12 Almazan Soria 42200",
    "addr:housenumber":"12",
    "addr:postcode":"42200",
    "iso:country":"ES",
    "sg:address":"Cust Jesus, 12",
    "sg:city":"Almazan",
    "sg:classifiers":[
        {
            "category":"Personal",
            "subcategory":"Barber",
            "type":"Services"
        }
    ],
    "sg:phone":"+34 975 30 11 65",
    "sg:postcode":"42200",
    "sg:province":"Soria",
    "sg:tags":[
        "caballeros",
        "de",
        "peluqueros"
    ],
    "wof:name":"Almeria Garijo Jesus",
    "wof:placetype":"venue"
},
  "geometry": {"coordinates":[-2.519793272,41.5536994934],"type":"Point"}
}