{
  "type": "Feature",
  "properties": {
    "iso:country":"ES",
    "sg:address":"Montcabrer, 16",
    "sg:city":"Aldaia",
    "sg:orig_category":"Cristaler\u00cdas",
    "sg:phone":"+34 961 51 91 98",
    "sg:postcode":"46960",
    "sg:province":"Valencia",
    "wof:name":"Vitallar C.b",
    "wof:placetype":"venue"
},
  "geometry": {"coordinates":[-0.4647895098,39.472240448],"type":"Point"}
}