{
  "type": "Feature",
  "properties": {
    "addr:full":"Osi\u00d1a Kalea, 1 Usurbil Guip\u00f9zcoa 20170",
    "addr:housenumber":"1",
    "addr:postcode":"20170",
    "addr:street":"Osin\u0303A Kalea;Guipu\u0300Zcoa",
    "iso:country":"ES",
    "sg:address":"Osi\u00d1a Kalea, 1",
    "sg:city":"Usurbil",
    "sg:orig_category":"Fabricaci\u00d3n De Etiquetas",
    "sg:phone":"+34 943 36 60 51",
    "sg:postcode":"20170",
    "sg:province":"Guip\u00f9zcoa",
    "wof:name":"Nomura S.a.",
    "wof:placetype":"venue"
},
  "geometry": {"coordinates":[-2.049959898,43.2698554993],"type":"Point"}
}