{
  "type": "Feature",
  "properties": {
    "addr:full":"Calle de Bolivia, 89 Malaga M\u00e1laga 29017",
    "addr:housenumber":"89",
    "addr:postcode":"29017",
    "addr:street":"Calle De Bolivia;Ma\u0301Laga",
    "iso:country":"ES",
    "sg:address":"Calle de Bolivia, 89",
    "sg:city":"Malaga",
    "sg:orig_category":"Psic\u00d3logos",
    "sg:phone":"+34 952 20 22 77",
    "sg:postcode":"29017",
    "sg:province":"M\u00e1laga",
    "wof:name":"Cabanillas Gutierrez Victor Manuel",
    "wof:placetype":"venue"
},
  "geometry": {"coordinates":[-4.3761258125,36.7216720581],"type":"Point"}
}