{
  "type": "Feature",
  "properties": {
    "addr:full":"Calle de Juana De Vega, 6 Coru\u00d1a La Coru\u00f1a 15003",
    "addr:housenumber":"6",
    "addr:postcode":"15003",
    "addr:street":"Calle De Juana De Vega;La Corun\u0303A",
    "iso:country":"ES",
    "sg:address":"Calle de Juana De Vega, 6",
    "sg:city":"Coru\u00d1a",
    "sg:orig_category":"Doctores En Medicina",
    "sg:phone":"+34 981 22 14 20",
    "sg:postcode":"15003",
    "sg:province":"La Coru\u00f1a",
    "wof:name":"Diz-lois Martinez Fernando",
    "wof:placetype":"venue"
},
  "geometry": {"coordinates":[-8.4052772522,43.3667602539],"type":"Point"}
}