{
  "type": "Feature",
  "properties": {
    "iso:country":"ES",
    "sg:address":"Calle de Casablanca, 24",
    "sg:city":"Torremolinos",
    "sg:orig_category":"Centros De Adelgazamiento Y De Est\u00c9tica",
    "sg:phone":"+34 952 05 83 25",
    "sg:postcode":"29620",
    "sg:province":"M\u00e1laga",
    "wof:name":"Camara Aguilera Manuel",
    "wof:placetype":"venue"
},
  "geometry": {"coordinates":[-4.4991269112,36.6200714111],"type":"Point"}
}