{
  "type": "Feature",
  "properties": {
    "addr:full":"Calle de Barcelona, 28 Fuenlabrada Madrid 28945",
    "addr:housenumber":"28",
    "addr:postcode":"28945",
    "addr:street":"Calle De Barcelona",
    "iso:country":"ES",
    "sg:address":"Calle de Barcelona, 28",
    "sg:city":"Fuenlabrada",
    "sg:orig_category":"Electricidad: Instaladores",
    "sg:phone":"+34 916 06 22 90",
    "sg:postcode":"28945",
    "sg:province":"Madrid",
    "wof:name":"Mu\u00f1oz Vallejo Emilio",
    "wof:placetype":"venue"
},
  "geometry": {"coordinates":[-3.7921116352,40.2962989807],"type":"Point"}
}