{
  "type": "Feature",
  "properties": {
    "iso:country":"ES",
    "sg:address":"Calle de Uruguay, 1",
    "sg:city":"Cehegin",
    "sg:orig_category":"Cl\u00cdnicas Dentales",
    "sg:phone":"+34 968 74 13 17",
    "sg:postcode":"30430",
    "sg:province":"Murcia",
    "wof:name":"Lopez Bastida Pedrol",
    "wof:placetype":"venue"
},
  "geometry": {"coordinates":[-1.7990727425,38.0904502869],"type":"Point"}
}