{
  "type": "Feature",
  "properties": {
    "addr:full":"Av Josep Tarradellas I Joan, 227 Hospitalet Llobregat Barcelona 08901",
    "addr:housenumber":"227",
    "addr:postcode":"08901",
    "addr:street":"Av Josep Tarradellas I Joan",
    "iso:country":"ES",
    "sg:address":"Av Josep Tarradellas I Joan, 227",
    "sg:city":"Hospitalet Llobregat",
    "sg:orig_category":"Sociedades, Compa\u00d1\u00cdas Aseguradoras",
    "sg:phone":"+34 933 38 23 36",
    "sg:postcode":"08901",
    "sg:province":"Barcelona",
    "wof:name":"Toll & Velez Agencia De Assegurances S.r.l.",
    "wof:placetype":"venue"
},
  "geometry": {"coordinates":[2.0972659588,41.3627510071],"type":"Point"}
}