{
  "type": "Feature",
  "properties": {
    "addr:full":"Marie Curie (pque Tecnologico), 1 Parque Tecnologico M\u00e1laga 29590",
    "addr:postcode":"29590",
    "addr:street":"Marie;Pque Tecnologico;Parque;Ma\u0301Laga",
    "iso:country":"ES",
    "sg:address":"Marie Curie (pque Tecnologico), 1",
    "sg:city":"Parque Tecnologico",
    "sg:orig_category":"Cajas De Ahorro",
    "sg:phone":"+34 952 02 02 83",
    "sg:postcode":"29590",
    "sg:province":"M\u00e1laga",
    "sg:website":"www.unicaja.es",
    "wof:name":"Unicaja",
    "wof:placetype":"venue"
},
  "geometry": {"coordinates":[-4.5224900246,36.7190055847],"type":"Point"}
}