{
  "type": "Feature",
  "properties": {
    "iso:country":"ES",
    "sg:address":"R. Pinto Costa, 1",
    "sg:city":"Lumbrales",
    "sg:orig_category":"Bancos",
    "sg:phone":"+34 923 51 23 22",
    "sg:postcode":"37240",
    "sg:province":"Salamanca",
    "sg:website":"www.bancocastilla.es",
    "wof:name":"Banco De Castilla",
    "wof:placetype":"venue"
},
  "geometry": {"coordinates":[-6.7207231522,40.9344863892],"type":"Point"}
}