{
  "type": "Feature",
  "properties": {
    "iso:country":"ES",
    "sg:address":"Carrer de Manacor, 35",
    "sg:city":"Palma",
    "sg:orig_category":"Comercio, Reparaci\u00d3n De Motocicletas, Bicicletas Y Piezas Sueltas",
    "sg:phone":"+34 971 46 19 52",
    "sg:postcode":"07006",
    "sg:province":"Islas Baleares",
    "wof:name":"Ferrer Bibiloni Matias",
    "wof:placetype":"venue"
},
  "geometry": {"coordinates":[2.6603391171,39.5716018677],"type":"Point"}
}