{
  "type": "Feature",
  "properties": {
    "addr:full":"Av Lucena, 18 Bonares Huelva 21830",
    "addr:housenumber":"18",
    "addr:postcode":"21830",
    "addr:street":"Av Lucena",
    "iso:country":"ES",
    "sg:address":"Av Lucena, 18",
    "sg:city":"Bonares",
    "sg:orig_category":"Electricidad Veh\u00cdculo",
    "sg:phone":"+34 959 36 63 79",
    "sg:postcode":"21830",
    "sg:province":"Huelva",
    "wof:name":"Electro-auto Rosendo S.l.",
    "wof:placetype":"venue"
},
  "geometry": {"coordinates":[-6.6799907684,37.3241653442],"type":"Point"}
}