{
  "type": "Feature",
  "properties": {
    "addr:full":"Calle de Torrejon, 49 Guardia De Jaen Ja\u00e9n 23170",
    "addr:housenumber":"49",
    "addr:postcode":"23170",
    "addr:street":"Calle De Torrejon",
    "iso:country":"ES",
    "sg:address":"Calle de Torrejon, 49",
    "sg:city":"Guardia De Jaen",
    "sg:orig_category":"Ingenieros Asesor\u00cda",
    "sg:phone":"+34 953 32 81 39",
    "sg:postcode":"23170",
    "sg:province":"Ja\u00e9n",
    "sg:website":"www.igeaconsultoria.com",
    "wof:name":"Igea Consultoria Y Laboratorio S.l.l",
    "wof:placetype":"venue"
},
  "geometry": {"coordinates":[-3.6955730915,37.7455368042],"type":"Point"}
}