{
  "type": "Feature",
  "properties": {
    "addr:full":"Plaz Constitucion, 13 Huesa Ja\u00e9n 23487",
    "addr:housenumber":"13",
    "addr:postcode":"23487",
    "addr:street":"Constitucion",
    "iso:country":"ES",
    "sg:address":"Plaz Constitucion, 13",
    "sg:city":"Huesa",
    "sg:orig_category":"Administraciones Regionales, Departamentales Y Locales",
    "sg:phone":"+34 953 71 50 09",
    "sg:postcode":"23487",
    "sg:province":"Ja\u00e9n",
    "wof:name":"Ayuntamiento De Huesa",
    "wof:placetype":"venue"
},
  "geometry": {"coordinates":[-3.0778930187,37.7643585205],"type":"Point"}
}