{
  "type": "Feature",
  "properties": {
    "addr:full":"Carrer de Nostra Senyora De Lourdes, S/n Molins Rei Barcelona 08750",
    "addr:housenumber":"s / n",
    "addr:postcode":"08750",
    "addr:street":"Carrer De Nostra Senyora De Lourdes;Barcelona",
    "iso:country":"ES",
    "sg:address":"Carrer de Nostra Senyora De Lourdes, S/n",
    "sg:city":"Molins Rei",
    "sg:orig_category":"Ense\u00d1anza Secundaria: Colegios Y Escuelas Privadas",
    "sg:phone":"+34 936 68 37 62",
    "sg:postcode":"08750",
    "sg:province":"Barcelona",
    "wof:name":"Generalitat Catalunya",
    "wof:placetype":"venue"
},
  "geometry": {"coordinates":[2.0264298916,41.410282135],"type":"Point"}
}