{
  "type": "Feature",
  "properties": {
    "addr:full":"Plaz Cervantes, 12 Paiporta Valencia 46200",
    "addr:housenumber":"12",
    "addr:postcode":"46200",
    "addr:street":"Plaz Cervantes",
    "iso:country":"ES",
    "sg:address":"Plaz Cervantes, 12",
    "sg:city":"Paiporta",
    "sg:orig_category":"Tintes (fabricaci\u00d3n, Al Por Mayor)",
    "sg:phone":"+34 963 97 12 17",
    "sg:postcode":"46200",
    "sg:province":"Valencia",
    "wof:name":"Tintoreria Cervantes S.l.",
    "wof:placetype":"venue"
},
  "geometry": {"coordinates":[-0.4186060131,39.427822113],"type":"Point"}
}