{
  "type": "Feature",
  "properties": {
    "addr:full":"Avda Andalucia, 149 Caleta Velez M\u00e1laga 29751",
    "addr:housenumber":"149",
    "addr:postcode":"29751",
    "addr:street":"Avda Andalucia;Ma\u0301Laga",
    "iso:country":"ES",
    "sg:address":"Avda Andalucia, 149",
    "sg:city":"Caleta Velez",
    "sg:orig_category":"Centros De Coordinaci\u00d3n",
    "sg:phone":"+34 952 51 19 66",
    "sg:postcode":"29751",
    "sg:province":"M\u00e1laga",
    "wof:name":"Centro De Gestiones Gestimar S.l.",
    "wof:placetype":"venue"
},
  "geometry": {"coordinates":[-4.0681238174,36.7494049072],"type":"Point"}
}