{
  "type": "Feature",
  "properties": {
    "iso:country":"ES",
    "sg:address":"Carrer de Doctor Torras I Bages, 112",
    "sg:city":"Terrassa",
    "sg:orig_category":"Productos Qu\u00cdmicos (fabricaci\u00d3n, Al Por Mayor)",
    "sg:phone":"+34 937 86 12 53",
    "sg:postcode":"08223",
    "sg:province":"Barcelona",
    "wof:name":"Chemital S. A.",
    "wof:placetype":"venue"
},
  "geometry": {"coordinates":[2.014480114,41.553150177],"type":"Point"}
}