{
  "type": "Feature",
  "properties": {
    "iso:country":"ES",
    "sg:address":"Calle de Agricultores (de Los), S/n",
    "sg:city":"Colmenar Viejo",
    "sg:orig_category":"Negocio De Materiales De Construcci\u00d3n",
    "sg:phone":"+34 918 45 10 55",
    "sg:postcode":"28770",
    "sg:province":"Madrid",
    "wof:name":"Materiales Abacon S.a.",
    "wof:placetype":"venue"
},
  "geometry": {"coordinates":[-3.7592236996,40.6632766724],"type":"Point"}
}