{
  "type": "Feature",
  "properties": {
    "iso:country":"ES",
    "sg:address":"G.v. Escultor Francisco Salzillo, 14",
    "sg:city":"Santa Catalina",
    "sg:orig_category":"Bisuter\u00cda, Joyer\u00cda, Relojer\u00cda (al Por Menor)",
    "sg:phone":"+34 968 21 24 98",
    "sg:postcode":"30004",
    "sg:province":"Murcia",
    "sg:website":"www.tous.es",
    "wof:name":"Tous Joyeros Murcia S.l.",
    "wof:placetype":"venue"
},
  "geometry": {"coordinates":[-1.1317919493,37.9856681824],"type":"Point"}
}