{
  "type": "Feature",
  "properties": {
    "addr:full":"Calle de Comandante Ruiz Marcet, 8 S. Fernando C\u00e1diz 11100",
    "addr:housenumber":"8",
    "addr:postcode":"11100",
    "addr:street":"Calle De Comandante Ruiz Marcet;Ca\u0301Diz",
    "iso:country":"ES",
    "sg:address":"Calle de Comandante Ruiz Marcet, 8",
    "sg:city":"S. Fernando",
    "sg:orig_category":"Producci\u00d3n, Distribuci\u00d3n De Electricidad",
    "sg:phone":"+34 956 88 76 02",
    "sg:postcode":"11100",
    "sg:province":"C\u00e1diz",
    "wof:name":"Servan Sanchez Jose",
    "wof:placetype":"venue"
},
  "geometry": {"coordinates":[-6.1969690323,36.47133255],"type":"Point"}
}