{
  "type": "Feature",
  "properties": {
    "addr:full":"Calle de Jose Picon, 6 Madrid Madrid 28028",
    "addr:housenumber":"6",
    "addr:postcode":"28028",
    "addr:street":"Calle De Jose Picon",
    "iso:country":"ES",
    "sg:address":"Calle de Jose Picon, 6",
    "sg:city":"Madrid",
    "sg:orig_category":"Chapister\u00cda",
    "sg:phone":"+34 917 26 01 05",
    "sg:postcode":"28028",
    "sg:province":"Madrid",
    "wof:name":"Emijo S.l.",
    "wof:placetype":"venue"
},
  "geometry": {"coordinates":[-3.6730918884,40.4342536926],"type":"Point"}
}