{
  "type": "Feature",
  "properties": {
    "addr:full":"Avda Jose Antonio, 34 Paso Santa Cruz De Tenerife 38750",
    "addr:housenumber":"34",
    "addr:postcode":"38750",
    "addr:street":"Avda Jose Antonio",
    "iso:country":"ES",
    "sg:address":"Avda Jose Antonio, 34",
    "sg:city":"Paso",
    "sg:orig_category":"Enfermeras: Consultas, Atenci\u00d3n A Domicilio",
    "sg:phone":"+34 922 48 63 48",
    "sg:postcode":"38750",
    "sg:province":"Santa Cruz De Tenerife",
    "wof:name":"Nazco Hernandez Victor Miguel",
    "wof:placetype":"venue"
},
  "geometry": {"coordinates":[-17.8800582886,28.6532783508],"type":"Point"}
}