{
  "type": "Feature",
  "properties": {
    "addr:full":"Calle de Lillo Juan, 70 San Vicente Del Raspeig-sant Vicent Del Raspeig Alicante 03690",
    "addr:housenumber":"70",
    "addr:postcode":"03690",
    "addr:street":"Calle De Lillo Juan",
    "iso:country":"ES",
    "sg:address":"Calle de Lillo Juan, 70",
    "sg:city":"San Vicente Del Raspeig-sant Vicent Del Raspeig",
    "sg:orig_category":"Escayola Y Productos De Escayola (fabricaci\u00d3n, Al Por Mayor)",
    "sg:phone":"+34 965 66 80 18",
    "sg:postcode":"03690",
    "sg:province":"Alicante",
    "wof:name":"Giner Pastor Juan Jose",
    "wof:placetype":"venue"
},
  "geometry": {"coordinates":[-0.5265690088,38.3999290466],"type":"Point"}
}