{
  "type": "Feature",
  "properties": {
    "iso:country":"ES",
    "sg:address":"Calle de Carretas (de Las), 17",
    "sg:city":"Colmenar Viejo",
    "sg:orig_category":"Molduras, Junquillos, Listones Y Molduras Perforadas",
    "sg:phone":"+34 918 46 39 61",
    "sg:postcode":"28770",
    "sg:province":"Madrid",
    "wof:name":"Viera Fernandez Juan Carlos",
    "wof:placetype":"venue"
},
  "geometry": {"coordinates":[-3.7685630322,40.6607131958],"type":"Point"}
}