{
  "type": "Feature",
  "properties": {
    "addr:full":"Plaz San Martin, 4 Le\u00f3n Le\u00f3n 24003",
    "addr:housenumber":"4",
    "addr:postcode":"24003",
    "addr:street":"Plaz San Martin;Leo\u0301N",
    "iso:country":"ES",
    "sg:address":"Plaz San Martin, 4",
    "sg:city":"Le\u00f3n",
    "sg:orig_category":"Molduras, Junquillos, Listones Y Molduras Perforadas",
    "sg:phone":"+34 987 25 65 18",
    "sg:postcode":"24003",
    "sg:province":"Le\u00f3n",
    "wof:name":"Lopez Caballero Francisco",
    "wof:placetype":"venue"
},
  "geometry": {"coordinates":[-5.5682911873,42.5982131958],"type":"Point"}
}