{
  "type": "Feature",
  "properties": {
    "iso:country":"ES",
    "sg:address":"Calle de Kamaraka, 8",
    "sg:orig_category":"Alimentaci\u00d3n General (al Por Menor)",
    "sg:phone":"+34 946 72 44 90",
    "sg:postcode":"01400",
    "sg:province":"\u00c1lava",
    "wof:name":"Zurigoiko",
    "wof:placetype":"venue"
},
  "geometry": {"coordinates":[-2.9606046677,43.1406593323],"type":"Point"}
}