{
  "type": "Feature",
  "properties": {
    "addr:full":"Av Miranda (la), 30 Esplugues Llobregat Barcelona 08950",
    "addr:housenumber":"30",
    "addr:postcode":"08950",
    "addr:street":"Av Miranda La",
    "iso:country":"ES",
    "sg:address":"Av Miranda (la), 30",
    "sg:city":"Esplugues Llobregat",
    "sg:orig_category":"Arquitectos",
    "sg:phone":"+34 933 71 08 93",
    "sg:postcode":"08950",
    "sg:province":"Barcelona",
    "wof:name":"Doce Goicoechea Jose Eduardo",
    "wof:placetype":"venue"
},
  "geometry": {"coordinates":[2.0855269432,41.3847122192],"type":"Point"}
}