{
  "type": "Feature",
  "properties": {
    "addr:full":"Guaza, 9 Guaza Santa Cruz De Tenerife 38627",
    "addr:housenumber":"9",
    "addr:postcode":"38627",
    "addr:street":"Guaza",
    "iso:country":"ES",
    "sg:address":"Guaza, 9",
    "sg:city":"Guaza",
    "sg:orig_category":"Limpieza Industrial",
    "sg:phone":"+34 922 16 90 42",
    "sg:postcode":"38627",
    "sg:province":"Santa Cruz De Tenerife",
    "wof:name":"Comunidad De Bienes Lavanderia Santa Fe",
    "wof:placetype":"venue"
},
  "geometry": {"coordinates":[-16.6800937653,28.0790691376],"type":"Point"}
}