{
  "type": "Feature",
  "properties": {
    "iso:country":"ES",
    "sg:address":"Av Catalunya (de), 37",
    "sg:city":"S. Carles Rapita",
    "sg:orig_category":"Electricidad: Instaladores",
    "sg:phone":"+34 977 74 09 98",
    "sg:postcode":"43540",
    "sg:province":"Tarragona",
    "wof:name":"Insta%acions J.d.s.l.",
    "wof:placetype":"venue"
},
  "geometry": {"coordinates":[0.5856299996,40.6168289185],"type":"Point"}
}