{
  "type": "Feature",
  "properties": {
    "iso:country":"ES",
    "sg:address":"Calle de Cava Alta, 25",
    "sg:city":"Madrid",
    "sg:orig_category":"Comunidades Religiosas",
    "sg:phone":"+34 913 65 58 30",
    "sg:postcode":"28005",
    "sg:province":"Madrid",
    "wof:name":"Archicofradia Sacramental De San Justo",
    "wof:placetype":"venue"
},
  "geometry": {"coordinates":[-3.7099523544,40.411819458],"type":"Point"}
}