{
  "type": "Feature",
  "properties": {
    "addr:full":"Calle de General Davila, 4 Madrid Madrid 28003",
    "addr:housenumber":"4",
    "addr:postcode":"28003",
    "addr:street":"Calle De General Davila",
    "iso:country":"ES",
    "sg:address":"Calle de General Davila, 4",
    "sg:city":"Madrid",
    "sg:orig_category":"Escayola Y Productos De Escayola (fabricaci\u00d3n, Al Por Mayor)",
    "sg:phone":"+34 915 36 37 04",
    "sg:postcode":"28003",
    "sg:province":"Madrid",
    "wof:name":"Vecino Reformas S.l.",
    "wof:placetype":"venue"
},
  "geometry": {"coordinates":[-3.7130279541,40.4438438416],"type":"Point"}
}