{
  "type": "Feature",
  "properties": {
    "iso:country":"ES",
    "sg:address":"B La Gandara, S/n",
    "sg:city":"Cudon",
    "sg:orig_category":"Quincaller\u00cda (al Por Menor)",
    "sg:phone":"+34 942 57 73 77",
    "sg:postcode":"39318",
    "sg:province":"Cantabria",
    "wof:name":"Ferreterias Cubas Suministros Industriales S.a.",
    "wof:placetype":"venue"
},
  "geometry": {"coordinates":[-4.0119838715,43.4161262512],"type":"Point"}
}