{
  "type": "Feature",
  "properties": {
    "iso:country":"ES",
    "sg:address":"Calle de Alcala, 324",
    "sg:city":"Madrid",
    "sg:orig_category":"Ropa Para Se\u00d1oras Y Caballeros (al Por Menor)",
    "sg:phone":"+34 913 67 23 45",
    "sg:postcode":"28027",
    "sg:province":"Madrid",
    "wof:name":"Orte Serrano Antonio",
    "wof:placetype":"venue"
},
  "geometry": {"coordinates":[-3.6475141048,40.4333648682],"type":"Point"}
}