{
  "type": "Feature",
  "properties": {
    "addr:full":"Avda Caza (de La), 7 Campodon Madrid 28922",
    "addr:housenumber":"7",
    "addr:postcode":"28922",
    "addr:street":"Avda Caza De La",
    "iso:country":"ES",
    "sg:address":"Avda Caza (de La), 7",
    "sg:city":"Campodon",
    "sg:orig_category":"Empresarios",
    "sg:phone":"+34 916 16 12 69",
    "sg:postcode":"28922",
    "sg:province":"Madrid",
    "wof:name":"Reformas Hermanos De La Fuente C.b.",
    "wof:placetype":"venue"
},
  "geometry": {"coordinates":[-3.8681409359,40.3610076904],"type":"Point"}
}