{
  "type": "Feature",
  "properties": {
    "addr:full":"Av Barcelona, S/n Miami Playa Tarragona 43892",
    "addr:housenumber":"/ n",
    "addr:postcode":"43892",
    "addr:street":"Av Barcelona S",
    "iso:country":"ES",
    "sg:address":"Av Barcelona, S/n",
    "sg:city":"Miami Playa",
    "sg:orig_category":"Organizaciones Internacionales",
    "sg:phone":"+34 977 81 11 17",
    "sg:postcode":"43892",
    "sg:province":"Tarragona",
    "wof:name":"Asamblea Local De La Cruz Roja",
    "wof:placetype":"venue"
},
  "geometry": {"coordinates":[0.9385489821,41.0090446472],"type":"Point"}
}