{
  "type": "Feature",
  "properties": {
    "iso:country":"ES",
    "sg:address":"Avda Constitucion (de La), 18",
    "sg:city":"Granada",
    "sg:orig_category":"Arquitectos",
    "sg:phone":"+34 958 28 88 77",
    "sg:postcode":"18012",
    "sg:province":"Granada",
    "wof:name":"Rodriguez Jimenez Gabriel",
    "wof:placetype":"venue"
},
  "geometry": {"coordinates":[-3.6048688889,37.1846618652],"type":"Point"}
}