{
  "type": "Feature",
  "properties": {
    "addr:full":"Carrer de Joan Xxiii, 10 S. Adria Besos Barcelona 08930",
    "addr:housenumber":"10",
    "addr:postcode":"08930",
    "addr:street":"Carrer De Joan Xxiii;Barcelona",
    "iso:country":"ES",
    "sg:address":"Carrer de Joan Xxiii, 10",
    "sg:city":"S. Adria Besos",
    "sg:orig_category":"Comercio, Reparaci\u00d3n De Bicicletas, De Motocicletas, De Accesorios",
    "sg:phone":"+34 933 81 19 43",
    "sg:postcode":"08930",
    "sg:province":"Barcelona",
    "sg:website":"www.telefonica.net/web/badabici",
    "wof:name":"Izquierdo Gutierrez Pedro",
    "wof:placetype":"venue"
},
  "geometry": {"coordinates":[2.2189640999,41.4319877625],"type":"Point"}
}