{
  "type": "Feature",
  "properties": {
    "addr:full":"Calle de Angustias, 42 Medina Campo Valladolid 47400",
    "addr:housenumber":"42",
    "addr:postcode":"47400",
    "addr:street":"Calle De Angustias",
    "iso:country":"ES",
    "sg:address":"Calle de Angustias, 42",
    "sg:city":"Medina Campo",
    "sg:orig_category":"Mec\u00c1nico Del Autom\u00d3vil",
    "sg:phone":"+34 983 81 02 05",
    "sg:postcode":"47400",
    "sg:province":"Valladolid",
    "wof:name":"Monsalvo Mendo Jesus Manuel",
    "wof:placetype":"venue"
},
  "geometry": {"coordinates":[-4.9160695076,41.3035163879],"type":"Point"}
}