{
  "type": "Feature",
  "properties": {
    "addr:full":"Avda Industria (de La), 42 Tres Cantos Madrid 28760",
    "addr:housenumber":"42",
    "addr:postcode":"28760",
    "addr:street":"Avda Industria De La",
    "iso:country":"ES",
    "sg:address":"Avda Industria (de La), 42",
    "sg:city":"Tres Cantos",
    "sg:orig_category":"Suministros Para Hoteles",
    "sg:phone":"+34 918 03 26 12",
    "sg:postcode":"28760",
    "sg:province":"Madrid",
    "sg:website":"www.tecno-sistema.com",
    "wof:name":"Sistema S. A.",
    "wof:placetype":"venue"
},
  "geometry": {"coordinates":[-3.7008481026,40.6138496399],"type":"Point"}
}