{
  "type": "Feature",
  "properties": {
    "addr:full":"Calle de Gomeznarro, 122 Madrid Madrid 28043",
    "addr:housenumber":"122",
    "addr:postcode":"28043",
    "addr:street":"Calle De Gomeznarro",
    "iso:country":"ES",
    "sg:address":"Calle de Gomeznarro, 122",
    "sg:city":"Madrid",
    "sg:orig_category":"Librer\u00cdas",
    "sg:phone":"+34 917 59 89 21",
    "sg:postcode":"28043",
    "sg:province":"Madrid",
    "wof:name":"Martin Martin Manuel",
    "wof:placetype":"venue"
},
  "geometry": {"coordinates":[-3.6497581005,40.4608764648],"type":"Point"}
}