{
  "type": "Feature",
  "properties": {
    "addr:full":"Calle de Mesones, 3 Carcaboso C\u00e1ceres 10670",
    "addr:housenumber":"3",
    "addr:postcode":"10670",
    "addr:street":"Calle De Mesones;Ca\u0301Ceres",
    "iso:country":"ES",
    "sg:address":"Calle de Mesones, 3",
    "sg:city":"Carcaboso",
    "sg:orig_category":"Peluquer\u00cdas, Peluquer\u00cda Mixta",
    "sg:phone":"+34 927 40 21 52",
    "sg:postcode":"10670",
    "sg:province":"C\u00e1ceres",
    "wof:name":"Barquero Gregorio Luz Maria",
    "wof:placetype":"venue"
},
  "geometry": {"coordinates":[-6.212594986,40.0490150452],"type":"Point"}
}