{
  "type": "Feature",
  "properties": {
    "iso:country":"ES",
    "sg:address":"Calle de Obispo Nieto, 29",
    "sg:city":"Zamora",
    "sg:orig_category":"Alimentaci\u00d3n General (al Por Mayor)",
    "sg:phone":"+34 980 51 51 32",
    "sg:postcode":"49026",
    "sg:province":"Zamora",
    "wof:name":"Herrero Rivas Jose Antonio",
    "wof:placetype":"venue"
},
  "geometry": {"coordinates":[-5.7549519539,41.5038070679],"type":"Point"}
}