{
  "type": "Feature",
  "properties": {
    "iso:country":"ES",
    "sg:address":"Plaz Rafael Alberti (de), 9",
    "sg:city":"Partija-santa Monica",
    "sg:orig_category":"Partidos Pol\u00cdticos",
    "sg:phone":"+34 916 66 35 13",
    "sg:postcode":"28529",
    "sg:province":"Madrid",
    "wof:name":"Partido Comunista De Espa\u00f1a",
    "wof:placetype":"venue"
},
  "geometry": {"coordinates":[-3.5102670193,40.314289093],"type":"Point"}
}