{
  "type": "Feature",
  "properties": {
    "iso:country":"ES",
    "sg:address":"Calle de Rio Manzanares, 2",
    "sg:city":"Alcorcon",
    "sg:orig_category":"Guarder\u00cdas",
    "sg:phone":"+34 916 19 06 47",
    "sg:postcode":"28923",
    "sg:province":"Madrid",
    "wof:name":"Gozalo Fernandez-lomana Francisco Javier",
    "wof:placetype":"venue"
},
  "geometry": {"coordinates":[-3.8162989616,40.3462715149],"type":"Point"}
}