{
  "type": "Feature",
  "properties": {
    "iso:country":"ES",
    "sg:address":"Calle de Doctor Encinas, 6",
    "sg:city":"Potes",
    "sg:orig_category":"Cl\u00cdnicas M\u00c9dicas",
    "sg:phone":"+34 942 73 21 11",
    "sg:postcode":"39570",
    "sg:province":"Cantabria",
    "wof:name":"Santamaria Cabrillo Guillermo",
    "wof:placetype":"venue"
},
  "geometry": {"coordinates":[-4.6193008423,43.156085968],"type":"Point"}
}