{
  "type": "Feature",
  "properties": {
    "addr:full":"Calle de Marcelo Usera, 78 Madrid Madrid 28026",
    "addr:housenumber":"78",
    "addr:postcode":"madrid;28026",
    "addr:street":"Calle De Marcelo Usera",
    "iso:country":"ES",
    "sg:address":"Calle de Marcelo Usera, 78",
    "sg:city":"Madrid",
    "sg:orig_category":"Ropa Para Caballeros (al Por Menor)",
    "sg:phone":"+34 914 76 44 80",
    "sg:postcode":"28026",
    "sg:province":"Madrid",
    "wof:name":"El Corte Italiano S. A.",
    "wof:placetype":"venue"
},
  "geometry": {"coordinates":[-3.7058908939,40.3859214783],"type":"Point"}
}