{
  "type": "Feature",
  "properties": {
    "iso:country":"ES",
    "sg:address":"Ctra Nacional 240, Km. 0026,0",
    "sg:city":"Armi\u00f1on",
    "sg:orig_category":"Poli\u00c9ster",
    "sg:phone":"+34 945 36 50 54",
    "sg:postcode":"01220",
    "sg:province":"\u00c1lava",
    "wof:name":"Industrias Tecnicas De La Espuma S.l.",
    "wof:placetype":"venue"
},
  "geometry": {"coordinates":[-2.8282105923,42.765335083],"type":"Point"}
}