{
  "type": "Feature",
  "properties": {
    "addr:full":"Carrer de Villarroel, 213 Barcelona Barcelona 08036",
    "addr:housenumber":"213",
    "addr:postcode":"08036",
    "addr:street":"Carrer De Villarroel",
    "iso:country":"ES",
    "sg:address":"Carrer de Villarroel, 213",
    "sg:city":"Barcelona",
    "sg:orig_category":"Aparcamientos (infraestructuras, Accesorios)",
    "sg:phone":"+34 933 22 04 70",
    "sg:postcode":"08036",
    "sg:province":"Barcelona",
    "wof:name":"Parking Lider S. A.",
    "wof:placetype":"venue"
},
  "geometry": {"coordinates":[2.1499009132,41.3902015686],"type":"Point"}
}