{
  "type": "Feature",
  "properties": {
    "iso:country":"ES",
    "sg:address":"Des Sol, 52",
    "sg:city":"Santanyi",
    "sg:orig_category":"Centros De Coordinaci\u00d3n",
    "sg:phone":"+34 971 16 34 32",
    "sg:postcode":"07650",
    "sg:province":"Islas Baleares",
    "wof:name":"Gabinet Llado S.l.",
    "wof:placetype":"venue"
},
  "geometry": {"coordinates":[3.1274299622,39.3544082642],"type":"Point"}
}