{
  "type": "Feature",
  "properties": {
    "iso:country":"ES",
    "sg:address":"Ctra Barcelona, 43",
    "sg:city":"Cerdanyola Valles",
    "sg:orig_category":"Puertas Y Portales",
    "sg:phone":"+34 935 80 72 92",
    "sg:postcode":"08290",
    "sg:province":"Barcelona",
    "wof:name":"Tecnogar Pass S.l.",
    "wof:placetype":"venue"
},
  "geometry": {"coordinates":[2.1503520012,41.4916191101],"type":"Point"}
}