{
  "type": "Feature",
  "properties": {
    "iso:country":"ES",
    "sg:address":"Pg Riera (la), 35",
    "sg:city":"Teia Centre,sector Riera Esquerre",
    "sg:orig_category":"Metales (labores, Pulido)",
    "sg:phone":"+34 935 55 33 06",
    "sg:postcode":"08329",
    "sg:province":"Barcelona",
    "wof:name":"Cafor S. A.",
    "wof:placetype":"venue"
},
  "geometry": {"coordinates":[2.3220570087,41.4969978333],"type":"Point"}
}