{
  "type": "Feature",
  "properties": {
    "iso:country":"ES",
    "sg:address":"Urola Enparantza, 4",
    "sg:city":"Zumaia",
    "sg:orig_category":"Estilistas Y Estudios De Estilo De Corte Y Confecci\u00d3n",
    "sg:phone":"+34 943 86 14 07",
    "sg:postcode":"20750",
    "sg:province":"Guip\u00f9zcoa",
    "wof:name":"Echave Aizpurua Antonio",
    "wof:placetype":"venue"
},
  "geometry": {"coordinates":[-2.2503430843,43.2933769226],"type":"Point"}
}