{
  "type": "Feature",
  "properties": {
    "iso:country":"ES",
    "sg:address":"Carrer de Dante Alighieri, 155",
    "sg:city":"Barcelona",
    "sg:orig_category":"Ropa Para Se\u00d1oras (al Por Menor)",
    "sg:phone":"+34 933 57 73 86",
    "sg:postcode":"08032",
    "sg:province":"Barcelona",
    "sg:website":"www.traposmoda.com",
    "wof:name":"Traposmoda Bcn Difussion S.l.",
    "wof:placetype":"venue"
},
  "geometry": {"coordinates":[2.1538140774,41.4254188538],"type":"Point"}
}