{
  "type": "Feature",
  "properties": {
    "addr:full":"Calle de Maristas (salidos), 2 Lucena C\u00f3rdoba 14900",
    "addr:housenumber":"2",
    "addr:postcode":"14900",
    "addr:street":"Calle De Maristas Salidos",
    "iso:country":"ES",
    "sg:address":"Calle de Maristas (salidos), 2",
    "sg:city":"Lucena",
    "sg:orig_category":"Zapatos (al Por Menor)",
    "sg:phone":"+34 957 50 27 08",
    "sg:postcode":"14900",
    "sg:province":"C\u00f3rdoba",
    "wof:name":"Guerrero Pineda Manuel",
    "wof:placetype":"venue"
},
  "geometry": {"coordinates":[-4.4854049683,37.4105224609],"type":"Point"}
}