{
  "type": "Feature",
  "properties": {
    "iso:country":"ES",
    "sg:address":"Ctra Almeria, S/n",
    "sg:city":"Llanos",
    "sg:orig_category":"Hoteles",
    "sg:phone":"+34 952 53 00 49",
    "sg:postcode":"29793",
    "sg:province":"M\u00e1laga",
    "wof:name":"Rico Olalla Manuel",
    "wof:placetype":"venue"
},
  "geometry": {"coordinates":[-3.9633140564,36.7310066223],"type":"Point"}
}