{
  "type": "Feature",
  "properties": {
    "addr:full":"Calle de Caminos Viejos, 4 Llodio \u00c1lava 01400",
    "addr:housenumber":"4",
    "addr:postcode":"01400",
    "addr:street":"Calle De Caminos Viejos",
    "iso:country":"ES",
    "sg:address":"Calle de Caminos Viejos, 4",
    "sg:city":"Llodio",
    "sg:orig_category":"Empresas De Carpinter\u00cda De Madera",
    "sg:phone":"+34 946 72 17 94",
    "sg:postcode":"01400",
    "sg:province":"\u00c1lava",
    "wof:name":"Carpinteria Urquijo S.l.",
    "wof:placetype":"venue"
},
  "geometry": {"coordinates":[-2.9517240524,43.1480789185],"type":"Point"}
}