{
  "type": "Feature",
  "properties": {
    "iso:country":"ES",
    "sg:address":"Calle de Doctor Gomez Ferrer, 18",
    "sg:city":"Valencia",
    "sg:orig_category":"Promotores Constructores",
    "sg:phone":"+34 963 61 15 82",
    "sg:postcode":"46010",
    "sg:province":"Valencia",
    "wof:name":"Vitas De Amarre S.l.",
    "wof:placetype":"venue"
},
  "geometry": {"coordinates":[-0.3610340953,39.479888916],"type":"Point"}
}