{
  "type": "Feature",
  "properties": {
    "addr:full":"Monasterio Fitero, 27 Iru\u00f1a Navarra 31011",
    "addr:housenumber":"27",
    "addr:postcode":"31011",
    "addr:street":"Fitero",
    "iso:country":"ES",
    "sg:address":"Monasterio Fitero, 27",
    "sg:city":"Iru\u00f1a",
    "sg:orig_category":"Asociaciones Y Clubs Deportivos",
    "sg:phone":"+34 948 26 14 16",
    "sg:postcode":"31011",
    "sg:province":"Navarra",
    "wof:name":"Lee  Seunjae",
    "wof:placetype":"venue"
},
  "geometry": {"coordinates":[-1.6643029451,42.8162841797],"type":"Point"}
}