{
  "type": "Feature",
  "properties": {
    "iso:country":"ES",
    "sg:address":"Avda America, 30",
    "sg:city":"Madrid",
    "sg:orig_category":"Asesor\u00cdas Y Estudios Financieros",
    "sg:phone":"+34 913 56 50 66",
    "sg:postcode":"28028",
    "sg:province":"Madrid",
    "wof:name":"Guzman Justicia Luis",
    "wof:placetype":"venue"
},
  "geometry": {"coordinates":[-3.6734569073,40.438785553],"type":"Point"}
}