{
  "type": "Feature",
  "properties": {
    "iso:country":"ES",
    "sg:address":"Av. Serapio Huici, 8",
    "sg:city":"Atarrabia",
    "sg:orig_category":"Bancos",
    "sg:phone":"+34 948 12 93 99",
    "sg:postcode":"31610",
    "sg:province":"Navarra",
    "wof:name":"Banco De Vasconia",
    "wof:placetype":"venue"
},
  "geometry": {"coordinates":[-1.6090170145,42.8306694031],"type":"Point"}
}