{
  "type": "Feature",
  "properties": {
    "iso:country":"ES",
    "sg:address":"Calle de Serrano, 15",
    "sg:city":"Villarta S. Juan",
    "sg:orig_category":"Agencias Y Agentes Comerciales, Representantes",
    "sg:phone":"+34 926 64 10 69",
    "sg:postcode":"13210",
    "sg:province":"Ciudad Real",
    "wof:name":"Mu\u00f1oz Gomez-lobo Marcelina",
    "wof:placetype":"venue"
},
  "geometry": {"coordinates":[-3.4243600368,39.2356071472],"type":"Point"}
}