{
  "type": "Feature",
  "properties": {
    "iso:country":"ES",
    "sg:address":"Poli Ciruela (la), 11",
    "sg:city":"Alagon",
    "sg:orig_category":"Maquinaria Para Industrias Diversas",
    "sg:phone":"+34 976 65 33 19",
    "sg:postcode":"50630",
    "sg:province":"Zaragoza",
    "wof:name":"Talleres Violade S. L.",
    "wof:placetype":"venue"
},
  "geometry": {"coordinates":[-1.1267240047,41.768196106],"type":"Point"}
}