{
  "type": "Feature",
  "properties": {
    "addr:full":"Alvaro Mutis, 4 Mijas Costa M\u00e1laga 29649",
    "addr:housenumber":"4",
    "addr:postcode":"29649",
    "addr:street":"Mutis",
    "iso:country":"ES",
    "sg:address":"Alvaro Mutis, 4",
    "sg:city":"Mijas Costa",
    "sg:orig_category":"Distribuci\u00d3n De Petr\u00d3leo Y Derivados",
    "sg:phone":"+34 952 47 24 96",
    "sg:postcode":"29649",
    "sg:province":"M\u00e1laga",
    "wof:name":"Retail Operating Company S.l.",
    "wof:placetype":"venue"
},
  "geometry": {"coordinates":[-4.6310629845,36.5238952637],"type":"Point"}
}