{
  "type": "Feature",
  "properties": {
    "addr:full":"Calle de Comandante Martos, 11 Padul Granada 18640",
    "addr:housenumber":"11",
    "addr:postcode":"18640",
    "addr:street":"Calle De Comandante Martos",
    "iso:country":"ES",
    "sg:address":"Calle de Comandante Martos, 11",
    "sg:city":"Padul",
    "sg:orig_category":"Promotores Constructores",
    "sg:phone":"+34 958 77 37 97",
    "sg:postcode":"18640",
    "sg:province":"Granada",
    "wof:name":"Payan Y Almendros S.l.",
    "wof:placetype":"venue"
},
  "geometry": {"coordinates":[-3.624060154,37.0199203491],"type":"Point"}
}