{
  "type": "Feature",
  "properties": {
    "iso:country":"ES",
    "sg:address":"Calle de Henao, 6",
    "sg:city":"Bilbao",
    "sg:classifiers":[
        {
            "category":"Government",
            "subcategory":"Post Office",
            "type":"Public Place"
        }
    ],
    "sg:phone":"+34 944 24 91 91",
    "sg:postcode":"48009",
    "sg:province":"Vizcaya",
    "sg:tags":[
        "de",
        "yoga",
        "clases"
    ],
    "wof:name":"Markiegi Gomez Ana Isabel",
    "wof:placetype":"venue"
},
  "geometry": {"coordinates":[-2.9294769764,43.2642364502],"type":"Point"}
}