{
  "type": "Feature",
  "properties": {
    "addr:full":"Calle de Reloj (del), 49 Casavieja \u00c1vila 05450",
    "addr:housenumber":"49",
    "addr:postcode":"05450",
    "addr:street":"Calle De Reloj Del;A\u0301Vila",
    "iso:country":"ES",
    "sg:address":"Calle de Reloj (del), 49",
    "sg:city":"Casavieja",
    "sg:orig_category":"Cajas De Ahorro",
    "sg:phone":"+34 918 67 80 56",
    "sg:postcode":"05450",
    "sg:province":"\u00c1vila",
    "sg:website":"www.cajadeavila.es",
    "wof:name":"Caja De Avila",
    "wof:placetype":"venue"
},
  "geometry": {"coordinates":[-4.7674889565,40.2815513611],"type":"Point"}
}