{
  "type": "Feature",
  "properties": {
    "addr:full":"Pg Estacio De L', 31 Valls Tarragona 43800",
    "addr:housenumber":"31",
    "addr:postcode":"43800",
    "addr:street":"Pg Estacio De L '",
    "iso:country":"ES",
    "sg:address":"Pg Estacio De L', 31",
    "sg:city":"Valls",
    "sg:orig_category":"Fisioterapia",
    "sg:phone":"+34 977 61 38 88",
    "sg:postcode":"43800",
    "sg:province":"Tarragona",
    "sg:website":"www.paginasamarillas.es",
    "wof:name":"Centre De Prevencio I Recuperacio S.l.",
    "wof:placetype":"venue"
},
  "geometry": {"coordinates":[1.2525299788,41.2871513367],"type":"Point"}
}