{
  "type": "Feature",
  "properties": {
    "addr:full":"Plaz Isaac Peral, 2 Puerto De Santa Maria C\u00e1diz 11500",
    "addr:housenumber":"2",
    "addr:postcode":"11500",
    "addr:street":"Peral;Ca\u0301Diz",
    "iso:country":"ES",
    "sg:address":"Plaz Isaac Peral, 2",
    "sg:city":"Puerto De Santa Maria",
    "sg:orig_category":"Asesor\u00cda Sobre Comunicaci\u00d3n De Empresas",
    "sg:phone":"+34 956 87 27 98",
    "sg:postcode":"11500",
    "sg:province":"C\u00e1diz",
    "wof:name":"Paez Hernandez David",
    "wof:placetype":"venue"
},
  "geometry": {"coordinates":[-6.2197542191,36.6056632996],"type":"Point"}
}