{
  "type": "Feature",
  "properties": {
    "iso:country":"ES",
    "sg:address":"Calle de Picatres (de), 28",
    "sg:city":"Alcobendas",
    "sg:orig_category":"Contenedores (mercanc\u00cdas)",
    "sg:phone":"+34 916 63 98 93",
    "sg:postcode":"28100",
    "sg:province":"Madrid",
    "wof:name":"Transporte Y Clasificacion De R.c.d.",
    "wof:placetype":"venue"
},
  "geometry": {"coordinates":[-3.6305809021,40.5401611328],"type":"Point"}
}