{
  "type": "Feature",
  "properties": {
    "iso:country":"ES",
    "sg:address":"Carr Creuer, 1",
    "sg:city":"Platja De Muro",
    "sg:orig_category":"Molduras, Junquillos, Listones Y Molduras Perforadas",
    "sg:phone":"+34 971 89 10 15",
    "sg:postcode":"07440",
    "sg:province":"Islas Baleares",
    "wof:name":"Atkin  Benjamin",
    "wof:placetype":"venue"
},
  "geometry": {"coordinates":[3.0536057949,39.7340774536],"type":"Point"}
}