{
  "type": "Feature",
  "properties": {
    "addr:full":"Calle de Cervantes, 3 Malaga M\u00e1laga 29016",
    "addr:housenumber":"3",
    "addr:postcode":"29016",
    "addr:street":"Calle De Cervantes;Ma\u0301Laga",
    "iso:country":"ES",
    "sg:address":"Calle de Cervantes, 3",
    "sg:city":"Malaga",
    "sg:orig_category":"Molduras, Junquillos, Listones Y Molduras Perforadas",
    "sg:phone":"+34 952 60 15 24",
    "sg:postcode":"29016",
    "sg:province":"M\u00e1laga",
    "wof:name":"Diaz Compian Antonio",
    "wof:placetype":"venue"
},
  "geometry": {"coordinates":[-4.4096708298,36.7204284668],"type":"Point"}
}