{
  "type": "Feature",
  "properties": {
    "addr:full":"Avda Alcarria (de La), 1 Alcala Henares Madrid 28806",
    "addr:postcode":"28806",
    "addr:street":"Avda Alcarria De La 1",
    "iso:country":"ES",
    "sg:address":"Avda Alcarria (de La), 1",
    "sg:city":"Alcala Henares",
    "sg:orig_category":"Cajas De Ahorro",
    "sg:phone":"+34 918 79 68 33",
    "sg:postcode":"28806",
    "sg:province":"Madrid",
    "sg:website":"www.caixanova.es",
    "wof:name":"Caixa De Aforros De Vigo Ourense E Pontevedra",
    "wof:placetype":"venue"
},
  "geometry": {"coordinates":[-3.364358902,40.4909515381],"type":"Point"}
}