{
  "type": "Feature",
  "properties": {
    "iso:country":"ES",
    "sg:address":"Trva Cisneros, 5",
    "sg:city":"Alcorcon",
    "sg:orig_category":"Quincaller\u00cda (al Por Menor)",
    "sg:phone":"+34 916 43 53 46",
    "sg:postcode":"28922",
    "sg:province":"Madrid",
    "wof:name":"Burgo Redondo Miguel Del",
    "wof:placetype":"venue"
},
  "geometry": {"coordinates":[-3.8326380253,40.3456840515],"type":"Point"}
}