{
  "type": "Feature",
  "properties": {
    "addr:full":"Carrer de Major, 17 S. Cugat Valles Barcelona 08172",
    "addr:housenumber":"17",
    "addr:postcode":"08172",
    "addr:street":"Carrer De Major;S. Cugat Valles Barcelona",
    "iso:country":"ES",
    "sg:address":"Carrer de Major, 17",
    "sg:city":"S. Cugat Valles",
    "sg:orig_category":"Carnicer\u00cdas, Carnicer\u00cdas",
    "sg:phone":"+34 936 74 01 61",
    "sg:postcode":"08172",
    "sg:province":"Barcelona",
    "wof:name":"Ribas Corbella Lorenzo",
    "wof:placetype":"venue"
},
  "geometry": {"coordinates":[2.083053112,41.4731521606],"type":"Point"}
}