{
  "type": "Feature",
  "properties": {
    "addr:full":"Plaz Euskadi, 5 Zumarraga Guip\u00f9zcoa 20700",
    "addr:housenumber":"5",
    "addr:postcode":"20700",
    "addr:street":"Plaz Euskadi;Guipu\u0300Zcoa",
    "iso:country":"ES",
    "sg:address":"Plaz Euskadi, 5",
    "sg:city":"Zumarraga",
    "sg:orig_category":"Agencias De Trabajo Temporal",
    "sg:phone":"+34 943 72 52 16",
    "sg:postcode":"20700",
    "sg:province":"Guip\u00f9zcoa",
    "wof:name":"Urola Garaiko Garapenarako Agentzia S.a.",
    "wof:placetype":"venue"
},
  "geometry": {"coordinates":[-2.3145129681,43.0899734497],"type":"Point"}
}