{
  "type": "Feature",
  "properties": {
    "iso:country":"ES",
    "sg:address":"Calle de Alcalde Guillermo Rein, 146",
    "sg:city":"Malaga",
    "sg:orig_category":"Fabricaci\u00d3n De Productos L\u00c1cteos Y Derivados",
    "sg:phone":"+34 952 33 49 42",
    "sg:postcode":"29006",
    "sg:province":"M\u00e1laga",
    "wof:name":"Industrias Lacteas Asturianas S.a.",
    "wof:placetype":"venue"
},
  "geometry": {"coordinates":[-4.4826545715,36.7112121582],"type":"Point"}
}