{
  "type": "Feature",
  "properties": {
    "addr:full":"Avgd Picassent, 3 Silla Valencia 46460",
    "addr:housenumber":"3",
    "addr:postcode":"46460",
    "addr:street":"Picassent",
    "iso:country":"ES",
    "sg:address":"Avgd Picassent, 3",
    "sg:city":"Silla",
    "sg:orig_category":"Ferreter\u00cda (diversos)",
    "sg:phone":"+34 961 20 03 79",
    "sg:postcode":"46460",
    "sg:province":"Valencia",
    "wof:name":"Jap-2 Recuperaciones S.l.",
    "wof:placetype":"venue"
},
  "geometry": {"coordinates":[-0.417858988,39.3685531616],"type":"Point"}
}