{
  "type": "Feature",
  "properties": {
    "addr:full":"Calle de Jose Reus Garcia, 7 Alacant Alicante 03010",
    "addr:housenumber":"7",
    "addr:postcode":"03010",
    "addr:street":"Calle De Jose Reus Garcia",
    "iso:country":"ES",
    "sg:address":"Calle de Jose Reus Garcia, 7",
    "sg:city":"Alacant",
    "sg:orig_category":"Molduras, Junquillos, Listones Y Molduras Perforadas",
    "sg:phone":"+34 965 17 74 26",
    "sg:postcode":"03010",
    "sg:province":"Alicante",
    "wof:name":"Sanchez Perez Juan Carlos",
    "wof:placetype":"venue"
},
  "geometry": {"coordinates":[-0.492610991,38.3638458252],"type":"Point"}
}