{
  "type": "Feature",
  "properties": {
    "iso:country":"ES",
    "sg:address":"Avda Galicia, 52",
    "sg:city":"Ponferrada",
    "sg:orig_category":"Supermercados Y Hipermercados",
    "sg:phone":"+34 987 40 00 12",
    "sg:postcode":"24400",
    "sg:province":"Le\u00f3n",
    "wof:name":"Supermercados Cuatrovientos Bierzo S.l.",
    "wof:placetype":"venue"
},
  "geometry": {"coordinates":[-6.6117401123,42.5545005798],"type":"Point"}
}