{
  "type": "Feature",
  "properties": {
    "iso:country":"ES",
    "sg:address":"Calle de Angeles (de Los), 10",
    "sg:city":"Fuenlabrada",
    "sg:orig_category":"Dietistas",
    "sg:phone":"+34 916 90 23 80",
    "sg:postcode":"28944",
    "sg:province":"Madrid",
    "wof:name":"Housediet S.l Sociedad Unipersonal",
    "wof:placetype":"venue"
},
  "geometry": {"coordinates":[-3.7906353474,40.2866592407],"type":"Point"}
}