{
  "type": "Feature",
  "properties": {
    "addr:full":"Calle de Nueva, 113 Valverde Camino Huelva 21600",
    "addr:housenumber":"113",
    "addr:postcode":"21600",
    "addr:street":"Calle De Nueva;Camino Huelva",
    "iso:country":"ES",
    "sg:address":"Calle de Nueva, 113",
    "sg:city":"Valverde Camino",
    "sg:orig_category":"Reposter\u00cdas",
    "sg:phone":"+34 959 55 18 11",
    "sg:postcode":"21600",
    "sg:province":"Huelva",
    "wof:name":"Mantero Corralejo Diego",
    "wof:placetype":"venue"
},
  "geometry": {"coordinates":[-6.7592101097,37.5750732422],"type":"Point"}
}