{
  "type": "Feature",
  "properties": {
    "iso:country":"ES",
    "sg:address":"Rua Urzaiz, 158",
    "sg:city":"Vigo",
    "sg:orig_category":"Cl\u00cdnicas Dentales",
    "sg:phone":"+34 986 27 65 38",
    "sg:postcode":"36205",
    "sg:province":"Pontevedra",
    "wof:name":"Pampin Ruibal Constantino",
    "wof:placetype":"venue"
},
  "geometry": {"coordinates":[-8.70429039,42.2308921814],"type":"Point"}
}