{
  "type": "Feature",
  "properties": {
    "addr:full":"Carrer de Pla De Fornells, 12 Barcelona Barcelona 08042",
    "addr:housenumber":"12",
    "addr:postcode":"08042",
    "addr:street":"Carrer De Pla De Fornells",
    "iso:country":"ES",
    "sg:address":"Carrer de Pla De Fornells, 12",
    "sg:city":"Barcelona",
    "sg:orig_category":"Peluqueros: De Se\u00d1oras",
    "sg:phone":"+34 933 59 47 96",
    "sg:postcode":"08042",
    "sg:province":"Barcelona",
    "wof:name":"Fe Pascual Cristagil-cristian",
    "wof:placetype":"venue"
},
  "geometry": {"coordinates":[2.1768209934,41.4464073181],"type":"Point"}
}