{
  "type": "Feature",
  "properties": {
    "addr:full":"Av Isidre Marti, 20 Esplugues Llobregat Barcelona 08950",
    "addr:housenumber":"20",
    "addr:postcode":"08950",
    "addr:street":"Av Isidre Marti",
    "iso:country":"ES",
    "sg:address":"Av Isidre Marti, 20",
    "sg:city":"Esplugues Llobregat",
    "sg:orig_category":"Inmobiliaria (agencias)",
    "sg:phone":"+34 933 72 96 31",
    "sg:postcode":"08950",
    "sg:province":"Barcelona",
    "wof:name":"Morgo Canal, Pascual",
    "wof:placetype":"venue"
},
  "geometry": {"coordinates":[2.0837380886,41.3747825623],"type":"Point"}
}