{
  "type": "Feature",
  "properties": {
    "addr:full":"Calle de Federico Garcia Lorca, 5 Tarancon Cuenca 16400",
    "addr:housenumber":"5",
    "addr:postcode":"16400",
    "addr:street":"Calle De Federico Garcia Lorca",
    "iso:country":"ES",
    "sg:address":"Calle de Federico Garcia Lorca, 5",
    "sg:city":"Tarancon",
    "sg:orig_category":"Reposter\u00cdas",
    "sg:phone":"+34 969 32 01 44",
    "sg:postcode":"16400",
    "sg:province":"Cuenca",
    "wof:name":"Burgo Mu\u00f1oz Angel Del",
    "wof:placetype":"venue"
},
  "geometry": {"coordinates":[-3.0148169994,40.0119132996],"type":"Point"}
}