{
  "type": "Feature",
  "properties": {
    "addr:full":"Calle de Aragon (de), 17 Fuenlabrada Madrid 28941",
    "addr:housenumber":"17",
    "addr:postcode":"28941",
    "addr:street":"Calle De Aragon De",
    "iso:country":"ES",
    "sg:address":"Calle de Aragon (de), 17",
    "sg:city":"Fuenlabrada",
    "sg:orig_category":"Mayoristas E Intermediarios En Alcoholes",
    "sg:phone":"+34 916 90 34 44",
    "sg:postcode":"28941",
    "sg:province":"Madrid",
    "wof:name":"Delegacion De Productos Especiales S.l",
    "wof:placetype":"venue"
},
  "geometry": {"coordinates":[-3.7952198982,40.2918777466],"type":"Point"}
}