{
  "type": "Feature",
  "properties": {
    "iso:country":"ES",
    "sg:address":"Calle de Arbollon, 18",
    "sg:city":"Almodovar Campo",
    "sg:orig_category":"Reposter\u00cdas",
    "sg:phone":"+34 926 48 40 90",
    "sg:postcode":"13580",
    "sg:province":"Ciudad Real",
    "wof:name":"Panificadora Gavidia S.c.p.",
    "wof:placetype":"venue"
},
  "geometry": {"coordinates":[-4.1818804741,38.7080001831],"type":"Point"}
}