{
  "type": "Feature",
  "properties": {
    "iso:country":"ES",
    "sg:address":"Poligono Jessica, 27",
    "sg:city":"Gerindote",
    "sg:orig_category":"Insecticidas, Fumigaci\u00d3n",
    "sg:phone":"+34 925 77 00 43",
    "sg:postcode":"45518",
    "sg:province":"Toledo",
    "wof:name":"Suato S.l.",
    "wof:placetype":"venue"
},
  "geometry": {"coordinates":[-4.3021659851,39.9683151245],"type":"Point"}
}