{
  "type": "Feature",
  "properties": {
    "addr:full":"Calle de Zurbaran, 36 Roquetas Mar Almer\u00eda 04740",
    "addr:housenumber":"36",
    "addr:postcode":"04740",
    "addr:street":"Calle De Zurbaran;Mar Almeri\u0301A",
    "iso:country":"ES",
    "sg:address":"Calle de Zurbaran, 36",
    "sg:city":"Roquetas Mar",
    "sg:orig_category":"Prot\u00c9sicos Dentales",
    "sg:phone":"+34 950 32 39 61",
    "sg:postcode":"04740",
    "sg:province":"Almer\u00eda",
    "wof:name":"Moreno Diaz Noelia",
    "wof:placetype":"venue"
},
  "geometry": {"coordinates":[-2.6164550781,36.7619094849],"type":"Point"}
}