{
  "type": "Feature",
  "properties": {
    "addr:full":"Calle de Pizarro, 18 Granja Torrehermosa Badajoz 06910",
    "addr:housenumber":"18",
    "addr:postcode":"06910",
    "addr:street":"Calle De Pizarro",
    "iso:country":"ES",
    "sg:address":"Calle de Pizarro, 18",
    "sg:city":"Granja Torrehermosa",
    "sg:orig_category":"Loter\u00cda Y T\u00d3mbola",
    "sg:phone":"+34 924 89 51 82",
    "sg:postcode":"06910",
    "sg:province":"Badajoz",
    "wof:name":"Quesada Fernandez Ines Maria",
    "wof:placetype":"venue"
},
  "geometry": {"coordinates":[-5.5952420235,38.309677124],"type":"Point"}
}