{
  "type": "Feature",
  "properties": {
    "addr:full":"Plaz Marques De Aracena, 22 Aracena Huelva 21200",
    "addr:housenumber":"22",
    "addr:postcode":"21200",
    "addr:street":"Marques;Aracena",
    "iso:country":"ES",
    "sg:address":"Plaz Marques De Aracena, 22",
    "sg:city":"Aracena",
    "sg:orig_category":"Electrodom\u00c9sticos (al Por Menor)",
    "sg:phone":"+34 959 12 81 23",
    "sg:postcode":"21200",
    "sg:province":"Huelva",
    "wof:name":"Fernandez Rivero Manuel",
    "wof:placetype":"venue"
},
  "geometry": {"coordinates":[-6.5593090057,37.892288208],"type":"Point"}
}