{
  "type": "Feature",
  "properties": {
    "iso:country":"ES",
    "sg:address":"Calle de Navaleno, 5",
    "sg:city":"Madrid",
    "sg:orig_category":"Ense\u00d1anza: Profesiones Art\u00cdsticas",
    "sg:phone":"+34 917 66 26 78",
    "sg:postcode":"28033",
    "sg:province":"Madrid",
    "wof:name":"Mango Producciones S.l.",
    "wof:placetype":"venue"
},
  "geometry": {"coordinates":[-3.6615319252,40.4701957703],"type":"Point"}
}