{
  "type": "Feature",
  "properties": {
    "iso:country":"ES",
    "sg:address":"Calle de Bayer, 1",
    "sg:city":"Castellon",
    "sg:orig_category":"Tiendas De Grano, Frutas Y Legumbres Secas (al Por Menor)",
    "sg:phone":"+34 964 21 52 14",
    "sg:postcode":"12002",
    "sg:province":"Castell\u00f3n",
    "wof:name":"Archiles Pascual Jose",
    "wof:placetype":"venue"
},
  "geometry": {"coordinates":[-0.0408364981,39.9852371216],"type":"Point"}
}