{
  "type": "Feature",
  "properties": {
    "iso:country":"ES",
    "sg:address":"Luga Santa Marina, S/n",
    "sg:city":"Santa Marina",
    "sg:orig_category":"Calderer\u00cda",
    "sg:phone":"+34 985 64 84 38",
    "sg:postcode":"33790",
    "sg:province":"Asturias",
    "sg:website":"www.armonastilleros.com",
    "wof:name":"Auxiliar Naval Del Principado S.a.",
    "wof:placetype":"venue"
},
  "geometry": {"coordinates":[-6.6495690346,43.5633850098],"type":"Point"}
}