{
  "type": "Feature",
  "properties": {
    "addr:full":"Calle de Rudiana, 15 Tarazona Zaragoza 50500",
    "addr:housenumber":"15",
    "addr:postcode":"50500",
    "addr:street":"Calle De Rudiana",
    "iso:country":"ES",
    "sg:address":"Calle de Rudiana, 15",
    "sg:city":"Tarazona",
    "sg:orig_category":"Venta, Instalaci\u00d3n De Calefacci\u00d3n",
    "sg:phone":"+34 976 64 48 31",
    "sg:postcode":"50500",
    "sg:province":"Zaragoza",
    "wof:name":"Osca Gas S.a.",
    "wof:placetype":"venue"
},
  "geometry": {"coordinates":[-1.7261610031,41.9074211121],"type":"Point"}
}