{
  "type": "Feature",
  "properties": {
    "addr:full":"Calle de Bidebarrieta, 16 Bilbao Vizcaya 48005",
    "addr:housenumber":"16",
    "addr:postcode":"48005",
    "addr:street":"Calle De Bidebarrieta",
    "iso:country":"ES",
    "sg:address":"Calle de Bidebarrieta, 16",
    "sg:city":"Bilbao",
    "sg:orig_category":"Loter\u00cda Y T\u00d3mbola",
    "sg:phone":"+34 944 15 46 52",
    "sg:postcode":"48005",
    "sg:province":"Vizcaya",
    "wof:name":"Ortega Eceiza Juan",
    "wof:placetype":"venue"
},
  "geometry": {"coordinates":[-2.9242455959,43.2576789856],"type":"Point"}
}