{
  "type": "Feature",
  "properties": {
    "addr:full":"Plaz Farolas, S/n Mula Murcia 30170",
    "addr:housenumber":"s / n",
    "addr:postcode":"30170",
    "addr:street":"Plaz Farolas",
    "iso:country":"ES",
    "sg:address":"Plaz Farolas, S/n",
    "sg:city":"Mula",
    "sg:orig_category":"Agencias Y Agentes Comerciales, Representantes",
    "sg:phone":"+34 968 66 05 78",
    "sg:postcode":"30170",
    "sg:province":"Murcia",
    "wof:name":"Buitrago Olivares Francisco",
    "wof:placetype":"venue"
},
  "geometry": {"coordinates":[-1.4960340261,38.0398864746],"type":"Point"}
}