{
  "type": "Feature",
  "properties": {
    "addr:full":"Calle de Valdeseria, 2 Palencia Palencia 34005",
    "addr:housenumber":"2",
    "addr:postcode":"34005",
    "addr:street":"Calle De Valdeseria",
    "iso:country":"ES",
    "sg:address":"Calle de Valdeseria, 2",
    "sg:city":"Palencia",
    "sg:orig_category":"Arquitectos",
    "sg:phone":"+34 979 74 83 04",
    "sg:postcode":"34005",
    "sg:province":"Palencia",
    "wof:name":"Diez Garcia Eduardo",
    "wof:placetype":"venue"
},
  "geometry": {"coordinates":[-4.5377058983,42.0101470947],"type":"Point"}
}