{
  "type": "Feature",
  "properties": {
    "addr:full":"Calle de Santa Ana, 10 Cieza Murcia 30530",
    "addr:housenumber":"10",
    "addr:postcode":"30530",
    "addr:street":"Calle De Santa Ana",
    "iso:country":"ES",
    "sg:address":"Calle de Santa Ana, 10",
    "sg:city":"Cieza",
    "sg:classifiers":[
        {
            "category":"Autos & Motor Vehicles",
            "subcategory":"Automobile Sales",
            "type":"Retail Goods"
        }
    ],
    "sg:phone":"+34 968 76 21 01",
    "sg:postcode":"30530",
    "sg:province":"Murcia",
    "sg:website":"www.iespana.es/autoescuelasmarin",
    "wof:name":"C.f.vial Marin S.l.",
    "wof:placetype":"venue"
},
  "geometry": {"coordinates":[-1.4217699766,38.23828125],"type":"Point"}
}