{
  "type": "Feature",
  "properties": {
    "iso:country":"ES",
    "sg:address":"Calle de Silva, 6",
    "sg:city":"Madrid",
    "sg:orig_category":"M\u00dasica, Direcci\u00d3n",
    "sg:phone":"+34 915 48 77 09",
    "sg:postcode":"28013",
    "sg:province":"Madrid",
    "wof:name":"Tool Music S. L.",
    "wof:placetype":"venue"
},
  "geometry": {"coordinates":[-3.7074279785,40.4205970764],"type":"Point"}
}