{
  "type": "Feature",
  "properties": {
    "iso:country":"ES",
    "sg:address":"Avda Puerto, 17",
    "sg:city":"Pueblo Blanco",
    "sg:orig_category":"Agencias Y Agentes Comerciales, Representantes",
    "sg:phone":"+34 965 79 50 50",
    "sg:postcode":"03730",
    "sg:province":"Alicante",
    "wof:name":"Alemany Zurraquez Pedro",
    "wof:placetype":"venue"
},
  "geometry": {"coordinates":[-0.4810059965,38.3452033997],"type":"Point"}
}