{
  "type": "Feature",
  "properties": {
    "addr:full":"Carrer de Copernic, 6 Barcelona Barcelona 08021",
    "addr:housenumber":"6",
    "addr:postcode":"08021",
    "addr:street":"Carrer De Copernic",
    "iso:country":"ES",
    "sg:address":"Carrer de Copernic, 6",
    "sg:city":"Barcelona",
    "sg:orig_category":"Asociaciones, Organismos Culturales Y Socioeducativos",
    "sg:phone":"+34 934 14 24 51",
    "sg:postcode":"08021",
    "sg:province":"Barcelona",
    "wof:name":"Asociacion Cultural Y Asistencial Montalt",
    "wof:placetype":"venue"
},
  "geometry": {"coordinates":[2.1353971958,41.3999328613],"type":"Point"}
}