{
  "type": "Feature",
  "properties": {
    "addr:full":"Calle de Zurbano, 54 Madrid Madrid 28010",
    "addr:housenumber":"54",
    "addr:postcode":"madrid;28010",
    "addr:street":"Calle De Zurbano",
    "iso:country":"ES",
    "sg:address":"Calle de Zurbano, 54",
    "sg:city":"Madrid",
    "sg:orig_category":"Traductores",
    "sg:phone":"+34 913 08 18 77",
    "sg:postcode":"28010",
    "sg:province":"Madrid",
    "wof:name":"Realizacion Y Consultas De Servicios S.a.",
    "wof:placetype":"venue"
},
  "geometry": {"coordinates":[-3.6930170059,40.4344291687],"type":"Point"}
}