{
  "type": "Feature",
  "properties": {
    "iso:country":"ES",
    "sg:address":"Calle de Cura Antonio Martin, 5",
    "sg:city":"Berja",
    "sg:orig_category":"Asesor\u00cda Fiscal Y Jur\u00cddica",
    "sg:phone":"+34 950 60 51 72",
    "sg:postcode":"04760",
    "sg:province":"Almer\u00eda",
    "wof:name":"Ruiz Carretero Francisco",
    "wof:placetype":"venue"
},
  "geometry": {"coordinates":[-2.9471311569,36.8448448181],"type":"Point"}
}