{
  "type": "Feature",
  "properties": {
    "iso:country":"ES",
    "sg:address":"Carr Castellon, 3",
    "sg:city":"Manises",
    "sg:orig_category":"Folclore",
    "sg:phone":"+34 961 53 78 78",
    "sg:postcode":"46940",
    "sg:province":"Valencia",
    "wof:name":"Felip Gomez Jose Manuel",
    "wof:placetype":"venue"
},
  "geometry": {"coordinates":[-0.457367003,39.4936103821],"type":"Point"}
}