{
  "type": "Feature",
  "properties": {
    "addr:full":"Calle de Industrias, 24 Valladolid Valladolid 47005",
    "addr:housenumber":"24",
    "addr:postcode":"47005",
    "addr:street":"Calle De Industrias",
    "iso:country":"ES",
    "sg:address":"Calle de Industrias, 24",
    "sg:city":"Valladolid",
    "sg:orig_category":"Electromec\u00c1nica",
    "sg:phone":"+34 983 39 30 07",
    "sg:postcode":"47005",
    "sg:province":"Valladolid",
    "wof:name":"Fernandez Gonzalez Carlos",
    "wof:placetype":"venue"
},
  "geometry": {"coordinates":[-4.7144069672,41.6480484009],"type":"Point"}
}