{
  "type": "Feature",
  "properties": {
    "addr:full":"Calle de Centro (del), 171 Villaverde Las Palmas 35640",
    "addr:housenumber":"171",
    "addr:postcode":"35640",
    "addr:street":"Calle De Centro Del",
    "iso:country":"ES",
    "sg:address":"Calle de Centro (del), 171",
    "sg:city":"Villaverde",
    "sg:orig_category":"Parques De Atracciones Y Centros De Esparcimiento",
    "sg:phone":"+34 928 17 53 25",
    "sg:postcode":"35640",
    "sg:province":"Las Palmas",
    "wof:name":"Promotora Turcanarian S.l.",
    "wof:placetype":"venue"
},
  "geometry": {"coordinates":[-13.9043645859,28.6300735474],"type":"Point"}
}