{
  "type": "Feature",
  "properties": {
    "iso:country":"ES",
    "sg:address":"Calle de Sixto Celorrio, 48",
    "sg:city":"Zaragoza",
    "sg:orig_category":"Peluqueros: De Se\u00d1oras",
    "sg:phone":"+34 976 52 15 69",
    "sg:postcode":"50015",
    "sg:province":"Zaragoza",
    "wof:name":"Puertolas Fanlo Beatriz",
    "wof:placetype":"venue"
},
  "geometry": {"coordinates":[-0.8758890033,41.6602592468],"type":"Point"}
}