{
  "type": "Feature",
  "properties": {
    "iso:country":"ES",
    "sg:address":"Calle de Cromo, 8",
    "sg:city":"Valladolid",
    "sg:orig_category":"Mec\u00c1nico Del Autom\u00d3vil",
    "sg:phone":"+34 983 30 97 97",
    "sg:postcode":"47012",
    "sg:province":"Valladolid",
    "wof:name":"Diez Dominguez Julio",
    "wof:placetype":"venue"
},
  "geometry": {"coordinates":[-4.7033853531,41.6276321411],"type":"Point"}
}