{
  "type": "Feature",
  "properties": {
    "iso:country":"ES",
    "sg:address":"Carr Josep Bas, 17",
    "sg:city":"Platja D'aro",
    "sg:orig_category":"Agencias De Viajes",
    "sg:phone":"+34 972 82 58 78",
    "sg:postcode":"17250",
    "sg:province":"Girona",
    "wof:name":"Meli Viajes Sl",
    "wof:placetype":"venue"
},
  "geometry": {"coordinates":[2.8258359432,41.9823913574],"type":"Point"}
}