{
  "type": "Feature",
  "properties": {
    "iso:country":"ES",
    "sg:address":"Pol Ind Cornicabral, S/n",
    "sg:city":"Beas Segura",
    "sg:orig_category":"Deportes Diversos",
    "sg:phone":"+34 953 42 54 80",
    "sg:postcode":"23280",
    "sg:province":"Ja\u00e9n",
    "wof:name":"Real Federacion Aeronautica Espa\u00f1ola",
    "wof:placetype":"venue"
},
  "geometry": {"coordinates":[-2.8957929611,38.25440979],"type":"Point"}
}