{
  "type": "Feature",
  "properties": {
    "iso:country":"ES",
    "sg:address":"Calle de Ribera, 15",
    "sg:city":"Aranjuez",
    "sg:orig_category":"Venta, Montaje De Neum\u00c1ticos",
    "sg:phone":"+34 918 91 67 22",
    "sg:postcode":"28300",
    "sg:province":"Madrid",
    "wof:name":"Neumaticos Medina S.l.",
    "wof:placetype":"venue"
},
  "geometry": {"coordinates":[-3.5875229836,40.0320587158],"type":"Point"}
}