{
  "type": "Feature",
  "properties": {
    "addr:full":"Av. Anllons(a Trabe), S/n Ponteceso A Coru\u00f1a 15110",
    "addr:housenumber":"s / n",
    "addr:postcode":"15110",
    "addr:street":"Av. Anllons A Trabe;Corun\u0303A",
    "iso:country":"ES",
    "sg:address":"Av. Anllons(a Trabe), S/n",
    "sg:city":"Ponteceso",
    "sg:orig_category":"Electrodom\u00c9sticos (al Por Menor)",
    "sg:phone":"+34 981 71 53 11",
    "sg:postcode":"15110",
    "sg:province":"A Coru\u00f1a",
    "wof:name":"Telecmovi Anllons S.l.v.",
    "wof:placetype":"venue"
},
  "geometry": {"coordinates":[-8.8991184235,43.2422790527],"type":"Point"}
}