{
  "type": "Feature",
  "properties": {
    "iso:country":"ES",
    "sg:address":"Calle de Royal Golf, 58",
    "sg:city":"Altorreal",
    "sg:orig_category":"Inform\u00c1tica: Consultores",
    "sg:phone":"+34 968 64 88 88",
    "sg:postcode":"30500",
    "sg:province":"Murcia",
    "wof:name":"Roma Escribano Concha",
    "wof:placetype":"venue"
},
  "geometry": {"coordinates":[-1.2119740248,38.0535736084],"type":"Point"}
}