{
  "type": "Feature",
  "properties": {
    "addr:full":"Calle de Garcia Morato, 9 Alacant Alicante 03004",
    "addr:housenumber":"9",
    "addr:postcode":"03004",
    "addr:street":"Calle De Garcia Morato",
    "iso:country":"ES",
    "sg:address":"Calle de Garcia Morato, 9",
    "sg:city":"Alacant",
    "sg:orig_category":"Muebles Y Accesorios Para Cocinas Y Cuartos De Ba\u00d1o (al Por Menor)",
    "sg:phone":"+34 965 20 32 50",
    "sg:postcode":"03004",
    "sg:province":"Alicante",
    "wof:name":"Cocinas Del Mediterraneo Cooperativa Valenciana",
    "wof:placetype":"venue"
},
  "geometry": {"coordinates":[-0.487112999,38.3479728699],"type":"Point"}
}