{
  "type": "Feature",
  "properties": {
    "iso:country":"ES",
    "sg:address":"Ctra Berrazales (los), S/n",
    "sg:city":"Agaete",
    "sg:orig_category":"Organizaciones Internacionales",
    "sg:phone":"+34 928 55 41 50",
    "sg:postcode":"35480",
    "sg:province":"Las Palmas",
    "wof:name":"Caritas Diocesana De Las Palmas",
    "wof:placetype":"venue"
},
  "geometry": {"coordinates":[-15.6936187744,28.0996494293],"type":"Point"}
}