{
  "type": "Feature",
  "properties": {
    "addr:full":"Calle de Padilla, 5 Valencia Valencia 46001",
    "addr:housenumber":"5",
    "addr:postcode":"46001",
    "addr:street":"Calle De Padilla",
    "iso:country":"ES",
    "sg:address":"Calle de Padilla, 5",
    "sg:city":"Valencia",
    "sg:orig_category":"M\u00c9dicos: Oftalmolog\u00cda",
    "sg:phone":"+34 963 51 65 25",
    "sg:postcode":"46001",
    "sg:province":"Valencia",
    "wof:name":"Garcia Gomez Salvador",
    "wof:placetype":"venue"
},
  "geometry": {"coordinates":[-0.3792090118,39.4698562622],"type":"Point"}
}