{
  "type": "Feature",
  "properties": {
    "iso:country":"ES",
    "sg:address":"Ctra. Daganzo, Km. 0001,8",
    "sg:city":"Alcala Henares",
    "sg:orig_category":"Empresas De Estuco",
    "sg:phone":"+34 918 77 16 41",
    "sg:postcode":"28806",
    "sg:province":"Madrid",
    "wof:name":"Proyectos Y Decoracion Herrero Slu",
    "wof:placetype":"venue"
},
  "geometry": {"coordinates":[-3.422385931,40.5286216736],"type":"Point"}
}