{
  "type": "Feature",
  "properties": {
    "iso:country":"ES",
    "sg:address":"Calle de Mayor, 18",
    "sg:city":"Castillonroy",
    "sg:orig_category":"Contenedores (mercanc\u00cdas)",
    "sg:phone":"+34 974 43 40 73",
    "sg:postcode":"22572",
    "sg:province":"Huesca",
    "wof:name":"Menal Perera Luis",
    "wof:placetype":"venue"
},
  "geometry": {"coordinates":[0.5145050287,41.8841362],"type":"Point"}
}