{
  "type": "Feature",
  "properties": {
    "addr:full":"Calle de Titulcia, 37 Getafe Madrid 28903",
    "addr:housenumber":"37",
    "addr:postcode":"28903",
    "addr:street":"Calle De Titulcia",
    "iso:country":"ES",
    "sg:address":"Calle de Titulcia, 37",
    "sg:city":"Getafe",
    "sg:orig_category":"Ebanister\u00cda",
    "sg:phone":"+34 916 95 13 54",
    "sg:postcode":"28903",
    "sg:province":"Madrid",
    "wof:name":"Hilario Garcia Paredes Y Otros C.b.",
    "wof:placetype":"venue"
},
  "geometry": {"coordinates":[-3.7231590748,40.3123397827],"type":"Point"}
}