{
  "type": "Feature",
  "properties": {
    "iso:country":"ES",
    "sg:address":"Carrer de Ample, 17",
    "sg:city":"Barcelona",
    "sg:orig_category":"Centros Empresariales",
    "sg:phone":"+34 934 12 51 29",
    "sg:postcode":"08002",
    "sg:province":"Barcelona",
    "wof:name":"Verges Meya Daniel",
    "wof:placetype":"venue"
},
  "geometry": {"coordinates":[2.1792500019,41.3795852661],"type":"Point"}
}