{
  "type": "Feature",
  "properties": {
    "addr:full":"C/ 6, 12 Ca\u00d1ada Valencia 46182",
    "addr:housenumber":"12",
    "addr:postcode":"46182",
    "addr:street":"C / 6",
    "iso:country":"ES",
    "sg:address":"C/ 6, 12",
    "sg:city":"Ca\u00d1ada",
    "sg:orig_category":"Asesor\u00cda Fiscal Y Jur\u00cddica",
    "sg:phone":"+34 961 32 57 30",
    "sg:postcode":"46182",
    "sg:province":"Valencia",
    "wof:name":"M 2 Clave T Asesores S.l",
    "wof:placetype":"venue"
},
  "geometry": {"coordinates":[-0.4852339923,39.5221443176],"type":"Point"}
}