{
  "type": "Feature",
  "properties": {
    "addr:full":"Calle de Palangre, 13 Alacant Alicante 03540",
    "addr:housenumber":"13",
    "addr:postcode":"03540",
    "addr:street":"Calle De Palangre",
    "iso:country":"ES",
    "sg:address":"Calle de Palangre, 13",
    "sg:city":"Alacant",
    "sg:orig_category":"Marketing Directo",
    "sg:phone":"+34 965 26 06 38",
    "sg:postcode":"03540",
    "sg:province":"Alicante",
    "wof:name":"Jumbo Milenio Company S.l.",
    "wof:placetype":"venue"
},
  "geometry": {"coordinates":[-0.4256075919,38.3590316772],"type":"Point"}
}