{
  "type": "Feature",
  "properties": {
    "addr:full":"Calle de Mayor, 2 Casillas Murcia 30007",
    "addr:housenumber":"2",
    "addr:postcode":"30007",
    "addr:street":"Calle De Mayor",
    "iso:country":"ES",
    "sg:address":"Calle de Mayor, 2",
    "sg:city":"Casillas",
    "sg:orig_category":"Cajas De Ahorro",
    "sg:phone":"+34 968 30 30 09",
    "sg:postcode":"30007",
    "sg:province":"Murcia",
    "sg:website":"www.cajamurcia.es",
    "wof:name":"Caja De Ahorros De Murcia",
    "wof:placetype":"venue"
},
  "geometry": {"coordinates":[-1.091277957,38.0090713501],"type":"Point"}
}