{
  "type": "Feature",
  "properties": {
    "iso:country":"ES",
    "sg:address":"Plaz Madrid, 3",
    "sg:city":"Salamanca",
    "sg:orig_category":"Promotores Constructores",
    "sg:phone":"+34 923 25 29 51",
    "sg:postcode":"37005",
    "sg:province":"Salamanca",
    "wof:name":"Construcciones Colpasa S.l.",
    "wof:placetype":"venue"
},
  "geometry": {"coordinates":[-5.658727169,40.9756011963],"type":"Point"}
}