{
  "type": "Feature",
  "properties": {
    "iso:country":"ES",
    "sg:address":"Calle de Urbion, 7",
    "sg:city":"Sevilla",
    "sg:orig_category":"Empresas De Carpinter\u00cda Met\u00c1lica",
    "sg:phone":"+34 954 64 69 66",
    "sg:postcode":"41005",
    "sg:province":"Sevilla",
    "wof:name":"Interxia S.l.",
    "wof:placetype":"venue"
},
  "geometry": {"coordinates":[-5.9706091881,37.3747825623],"type":"Point"}
}