{
  "type": "Feature",
  "properties": {
    "addr:full":"Calle de Ca\u00d1ada Real, 2 Plasencia C\u00e1ceres 10600",
    "addr:housenumber":"2",
    "addr:postcode":"10600",
    "addr:street":"Calle De Can\u0303Ada Real;Ca\u0301Ceres",
    "iso:country":"ES",
    "sg:address":"Calle de Ca\u00d1ada Real, 2",
    "sg:city":"Plasencia",
    "sg:orig_category":"Bisuter\u00cda, Joyer\u00cda, Relojer\u00cda (al Por Menor)",
    "sg:phone":"+34 927 42 00 93",
    "sg:postcode":"10600",
    "sg:province":"C\u00e1ceres",
    "wof:name":"Gil Gomez Pedro",
    "wof:placetype":"venue"
},
  "geometry": {"coordinates":[-6.0823774338,40.0386734009],"type":"Point"}
}