{
  "type": "Feature",
  "properties": {
    "iso:country":"ES",
    "sg:address":"Carrer de Josep Maria De Sagarra, 45",
    "sg:city":"Hospitalet Llobregat",
    "sg:orig_category":"Papeler\u00cdas, Librer\u00cdas",
    "sg:phone":"+34 932 61 21 79",
    "sg:postcode":"08901",
    "sg:province":"Barcelona",
    "wof:name":"Roman Antunez Maite",
    "wof:placetype":"venue"
},
  "geometry": {"coordinates":[2.0976250172,41.3567276001],"type":"Point"}
}