{
  "type": "Feature",
  "properties": {
    "addr:full":"Avda Valdecilla, 21 Santander Cantabria 39008",
    "addr:housenumber":"21",
    "addr:postcode":"39008",
    "addr:street":"Avda Valdecilla",
    "iso:country":"ES",
    "sg:address":"Avda Valdecilla, 21",
    "sg:city":"Santander",
    "sg:orig_category":"Muebles, Minoristas",
    "sg:phone":"+34 942 34 14 00",
    "sg:postcode":"39008",
    "sg:province":"Cantabria",
    "sg:website":"www.nuevalinea.es",
    "wof:name":"Jose Maria Muebles Decoracion S.a.",
    "wof:placetype":"venue"
},
  "geometry": {"coordinates":[-3.8332419395,43.4550552368],"type":"Point"}
}