{
  "type": "Feature",
  "properties": {
    "iso:country":"ES",
    "sg:address":"Calle de Cebreros, 19",
    "sg:city":"Madrid",
    "sg:orig_category":"Pescader\u00cdas (al Por Menor)",
    "sg:phone":"+34 914 64 62 71",
    "sg:postcode":"28011",
    "sg:province":"Madrid",
    "wof:name":"Alonso Alonso Agustin",
    "wof:placetype":"venue"
},
  "geometry": {"coordinates":[-3.7433822155,40.4048652649],"type":"Point"}
}