{
  "type": "Feature",
  "properties": {
    "iso:country":"ES",
    "sg:address":"Calle de Conserva, 14",
    "sg:city":"Valencia",
    "sg:orig_category":"Molduras, Junquillos, Listones Y Molduras Perforadas",
    "sg:phone":"+34 963 30 24 08",
    "sg:postcode":"46022",
    "sg:province":"Valencia",
    "wof:name":"Collazo Gonzalez Gerado",
    "wof:placetype":"venue"
},
  "geometry": {"coordinates":[-0.3446567059,39.4650726318],"type":"Point"}
}