{
  "type": "Feature",
  "properties": {
    "iso:country":"ES",
    "sg:address":"Avda Estacion (de La), 24",
    "sg:city":"Almeria",
    "sg:orig_category":"Agencias De Viajes",
    "sg:phone":"+34 950 27 56 00",
    "sg:postcode":"04005",
    "sg:province":"Almer\u00eda",
    "sg:website":"www.halconviajes.com",
    "wof:name":"Viajes Halcon S.a.",
    "wof:placetype":"venue"
},
  "geometry": {"coordinates":[-2.4579999447,36.8370704651],"type":"Point"}
}