{
  "type": "Feature",
  "properties": {
    "addr:full":"Cami Vell Pedrera, S/n Barcelona Barcelona 08042",
    "addr:housenumber":"s / n",
    "addr:postcode":"08042",
    "addr:street":"Cami Vell Pedrera",
    "iso:country":"ES",
    "sg:address":"Cami Vell Pedrera, S/n",
    "sg:city":"Barcelona",
    "sg:orig_category":"Alimentaci\u00d3n General (al Por Menor)",
    "sg:phone":"+34 933 54 76 19",
    "sg:postcode":"08042",
    "sg:province":"Barcelona",
    "wof:name":"Supermercados Antunez S.l.",
    "wof:placetype":"venue"
},
  "geometry": {"coordinates":[2.1784889698,41.446937561],"type":"Point"}
}