{
  "type": "Feature",
  "properties": {
    "addr:full":"Carrer de Fluvia, 194 Barcelona Barcelona 08020",
    "addr:housenumber":"194",
    "addr:postcode":"08020",
    "addr:street":"Carrer De Fluvia",
    "iso:country":"ES",
    "sg:address":"Carrer de Fluvia, 194",
    "sg:city":"Barcelona",
    "sg:orig_category":"Farmacias",
    "sg:phone":"+34 933 07 73 44",
    "sg:postcode":"08020",
    "sg:province":"Barcelona",
    "wof:name":"Moreu Y Moreu S.c.p.",
    "wof:placetype":"venue"
},
  "geometry": {"coordinates":[2.1983671188,41.4136772156],"type":"Point"}
}