{
  "type": "Feature",
  "properties": {
    "iso:country":"ES",
    "sg:address":"Calle de Murillo, 7",
    "sg:city":"Huelva",
    "sg:orig_category":"Inmobiliaria (agencias)",
    "sg:phone":"+34 959 24 20 03",
    "sg:postcode":"21001",
    "sg:province":"Huelva",
    "wof:name":"Inrocorsa S.l.",
    "wof:placetype":"venue"
},
  "geometry": {"coordinates":[-6.9518008232,37.2549324036],"type":"Point"}
}