{
  "type": "Feature",
  "properties": {
    "iso:country":"ES",
    "sg:address":"Avda Primero De Mayo, S/n",
    "sg:city":"Palmar  O Lugar De Don Juan",
    "sg:orig_category":"Cajas Para Embalar",
    "sg:phone":"+34 968 88 27 94",
    "sg:postcode":"30120",
    "sg:province":"Murcia",
    "wof:name":"Cajamar",
    "wof:placetype":"venue"
},
  "geometry": {"coordinates":[-1.1606040001,37.9361457825],"type":"Point"}
}