{
  "type": "Feature",
  "properties": {
    "iso:country":"ES",
    "sg:address":"Pg Gran Passeig Ronda, 155",
    "sg:city":"Lleida",
    "sg:orig_category":"Papeler\u00cdas, Librer\u00cdas",
    "sg:phone":"+34 973 23 46 55",
    "sg:postcode":"25008",
    "sg:province":"Lleida",
    "wof:name":"Cavero Olivera Maximo",
    "wof:placetype":"venue"
},
  "geometry": {"coordinates":[0.6212469935,41.623966217],"type":"Point"}
}