{
  "type": "Feature",
  "properties": {
    "iso:country":"ES",
    "sg:address":"Carrer de Setze De Juliol, 39",
    "sg:city":"Poligon Industrial De Son Castello",
    "sg:orig_category":"Maquinaria Para Industrias Diversas",
    "sg:phone":"+34 971 43 09 93",
    "sg:postcode":"07009",
    "sg:province":"Islas Baleares",
    "sg:website":"wwwsociassuministros.com",
    "wof:name":"Socias Suministros Industriales S.l.",
    "wof:placetype":"venue"
},
  "geometry": {"coordinates":[2.6741399765,39.6011390686],"type":"Point"}
}