{
  "type": "Feature",
  "properties": {
    "addr:full":"Calle de Caro Sanchez, 14 Malaga M\u00e1laga 29018",
    "addr:housenumber":"14",
    "addr:postcode":"29018",
    "addr:street":"Calle De Caro Sanchez;Ma\u0301Laga",
    "iso:country":"ES",
    "sg:address":"Calle de Caro Sanchez, 14",
    "sg:city":"Malaga",
    "sg:orig_category":"Animales (al Por Menor)",
    "sg:phone":"+34 952 30 55 15",
    "sg:postcode":"29018",
    "sg:province":"M\u00e1laga",
    "wof:name":"Rembado Reina Julian Jose",
    "wof:placetype":"venue"
},
  "geometry": {"coordinates":[-4.3711585999,36.7299537659],"type":"Point"}
}