{
  "type": "Feature",
  "properties": {
    "addr:full":"Carrer de Puigbarral, 32 Terrassa Barcelona 08227",
    "addr:housenumber":"32",
    "addr:postcode":"08227",
    "addr:street":"Carrer De Puigbarral",
    "iso:country":"ES",
    "sg:address":"Carrer de Puigbarral, 32",
    "sg:city":"Terrassa",
    "sg:orig_category":"M\u00c1rmoles, Granitos Y Piedras Naturales",
    "sg:phone":"+34 937 85 36 43",
    "sg:postcode":"08227",
    "sg:province":"Barcelona",
    "wof:name":"Marmoles Marsal S.l.",
    "wof:placetype":"venue"
},
  "geometry": {"coordinates":[2.0346040726,41.5808105469],"type":"Point"}
}