{
  "type": "Feature",
  "properties": {
    "iso:country":"ES",
    "sg:address":"Calle de Fernan Gonzalez, 30",
    "sg:city":"Madrid",
    "sg:orig_category":"Fotocopias, Reprograf\u00cda",
    "sg:phone":"+34 915 76 36 86",
    "sg:postcode":"28009",
    "sg:province":"Madrid",
    "sg:website":"www.fg30.com",
    "wof:name":"Fernan Gonzalez 30 S.l.",
    "wof:placetype":"venue"
},
  "geometry": {"coordinates":[-3.6745688915,40.4216880798],"type":"Point"}
}