{
  "type": "Feature",
  "properties": {
    "iso:country":"ES",
    "sg:address":"Avda Andalucia, 21",
    "sg:city":"Gibraleon",
    "sg:orig_category":"Muebles, Minoristas",
    "sg:phone":"+34 959 30 00 37",
    "sg:postcode":"21500",
    "sg:province":"Huelva",
    "wof:name":"Dominguez Rodriguez Teresa",
    "wof:placetype":"venue"
},
  "geometry": {"coordinates":[-6.9689230919,37.3758125305],"type":"Point"}
}