{
  "type": "Feature",
  "properties": {
    "iso:country":"ES",
    "sg:address":"Cami Fontanelles, Ses, 11",
    "sg:city":"Soller",
    "sg:orig_category":"Centros Empresariales",
    "sg:phone":"+34 971 63 14 44",
    "sg:postcode":"07100",
    "sg:province":"Islas Baleares",
    "wof:name":"Pedro Estades E Hijos S.l.",
    "wof:placetype":"venue"
},
  "geometry": {"coordinates":[2.7147779465,39.7659072876],"type":"Point"}
}