{
  "type": "Feature",
  "properties": {
    "addr:full":"Calle de Gredos, 8 Villanueva Arzobispo Ja\u00e9n 23330",
    "addr:housenumber":"8",
    "addr:postcode":"23330",
    "addr:street":"Calle De Gredos",
    "iso:country":"ES",
    "sg:address":"Calle de Gredos, 8",
    "sg:city":"Villanueva Arzobispo",
    "sg:orig_category":"Material Y Herramientas Agr\u00cdcolas",
    "sg:phone":"+34 953 45 23 59",
    "sg:postcode":"23330",
    "sg:province":"Ja\u00e9n",
    "wof:name":"Navarrete Alamo Antonio",
    "wof:placetype":"venue"
},
  "geometry": {"coordinates":[-3.0039041042,38.172039032],"type":"Point"}
}