{
  "type": "Feature",
  "properties": {
    "iso:country":"ES",
    "sg:address":"Plaz Doctor Collado, 7",
    "sg:city":"Valencia",
    "sg:orig_category":"Peluquer\u00cdas, Peluquer\u00cda Mixta",
    "sg:phone":"+34 963 91 08 22",
    "sg:postcode":"46001",
    "sg:province":"Valencia",
    "wof:name":"Gracia Pozo Julio",
    "wof:placetype":"venue"
},
  "geometry": {"coordinates":[-0.3777318895,39.4744338989],"type":"Point"}
}