{
  "type": "Feature",
  "properties": {
    "iso:country":"ES",
    "sg:address":"Carrer de Urbanitzacio Palou, 21",
    "sg:city":"Cornella Llobregat",
    "sg:orig_category":"Reparaci\u00d3n Y Restauraci\u00d3n De Objetos Diversos",
    "sg:phone":"+34 933 75 74 03",
    "sg:postcode":"08940",
    "sg:province":"Barcelona",
    "wof:name":"Neumaticos San Ildefonso S.l.",
    "wof:placetype":"venue"
},
  "geometry": {"coordinates":[2.0708940029,41.3559417725],"type":"Point"}
}