{
  "type": "Feature",
  "properties": {
    "iso:country":"ES",
    "sg:address":"Calle de Bravo Murillo, 124",
    "sg:city":"Madrid",
    "sg:orig_category":"Telas Y Sedas (al Por Menor)",
    "sg:phone":"+34 915 33 53 57",
    "sg:postcode":"28020",
    "sg:province":"Madrid",
    "wof:name":"Aguirre Serrador Manuel",
    "wof:placetype":"venue"
},
  "geometry": {"coordinates":[-3.7036283016,40.4491233826],"type":"Point"}
}