{
  "type": "Feature",
  "properties": {
    "addr:full":"Carrer de Granja, 23 Barcelona Barcelona 08024",
    "addr:housenumber":"23",
    "addr:postcode":"08024",
    "addr:street":"Carrer De Granja",
    "iso:country":"ES",
    "sg:address":"Carrer de Granja, 23",
    "sg:city":"Barcelona",
    "sg:orig_category":"Agentes Generales De Seguros",
    "sg:phone":"+34 932 18 30 42",
    "sg:postcode":"08024",
    "sg:province":"Barcelona",
    "wof:name":"Vila Vendrell Rosa",
    "wof:placetype":"venue"
},
  "geometry": {"coordinates":[2.1541910172,41.4084129333],"type":"Point"}
}