{
  "type": "Feature",
  "properties": {
    "iso:country":"ES",
    "sg:address":"Pase Serapio Mugica De, 8",
    "sg:city":"Donostia-san Sebastian",
    "sg:orig_category":"Mercer\u00cda, Lencer\u00cda (al Por Menor)",
    "sg:phone":"+34 943 40 12 10",
    "sg:postcode":"20016",
    "sg:province":"Guip\u00f9zcoa",
    "wof:name":"Maria Jesus Calvo Merino",
    "wof:placetype":"venue"
},
  "geometry": {"coordinates":[-1.9452079535,43.3222961426],"type":"Point"}
}