{
  "type": "Feature",
  "properties": {
    "iso:country":"ES",
    "sg:address":"Calle de Ria\u00d1o, 14",
    "sg:city":"Salamanca",
    "sg:orig_category":"Instalaci\u00d3n, Reparaci\u00d3n De Ascensores Y Montacargas",
    "sg:phone":"+34 923 12 53 61",
    "sg:postcode":"37006",
    "sg:province":"Salamanca",
    "wof:name":"Orona S.c.l.",
    "wof:placetype":"venue"
},
  "geometry": {"coordinates":[-5.6677808762,40.9796066284],"type":"Point"}
}