{
  "type": "Feature",
  "properties": {
    "addr:full":"Cmno Berra, 15 Donostia-san Sebastian Guip\u00f9zcoa 20017",
    "addr:housenumber":"15",
    "addr:postcode":"20017",
    "addr:street":"Cmno Berra",
    "iso:country":"ES",
    "sg:address":"Cmno Berra, 15",
    "sg:city":"Donostia-san Sebastian",
    "sg:orig_category":"Panader\u00cdas, Panader\u00cdas",
    "sg:phone":"+34 943 35 19 39",
    "sg:postcode":"20017",
    "sg:province":"Guip\u00f9zcoa",
    "wof:name":"Cortes Fernandez Francisco",
    "wof:placetype":"venue"
},
  "geometry": {"coordinates":[-1.9794000387,43.3173789978],"type":"Point"}
}