{
  "type": "Feature",
  "properties": {
    "iso:country":"ES",
    "sg:address":"Avda Rafael Cabrera, 22",
    "sg:city":"Palmas De Gran Canaria",
    "sg:orig_category":"Electrodom\u00c9sticos (fabricaci\u00d3n, Al Por Mayor)",
    "sg:phone":"+34 928 36 40 38",
    "sg:postcode":"35002",
    "sg:province":"Las Palmas",
    "wof:name":"Organizacion Martinez S. A.",
    "wof:placetype":"venue"
},
  "geometry": {"coordinates":[-15.4150238037,28.1069698334],"type":"Point"}
}