{
  "type": "Feature",
  "properties": {
    "addr:full":"Monasterio Urdax, 49 Iru\u00f1a Navarra 31011",
    "addr:housenumber":"49",
    "addr:postcode":"31011",
    "addr:street":"Urdax",
    "iso:country":"ES",
    "sg:address":"Monasterio Urdax, 49",
    "sg:city":"Iru\u00f1a",
    "sg:orig_category":"Institutos De Belleza",
    "sg:phone":"+34 948 27 87 15",
    "sg:postcode":"31011",
    "sg:province":"Navarra",
    "wof:name":"Elizondo Barberena Laura",
    "wof:placetype":"venue"
},
  "geometry": {"coordinates":[-1.65832901,42.8167495728],"type":"Point"}
}