{
  "type": "Feature",
  "properties": {
    "iso:country":"ES",
    "sg:address":"Calle de Garcia Lorca, 10",
    "sg:city":"Illescas",
    "sg:orig_category":"Chapister\u00cda",
    "sg:phone":"+34 925 51 19 36",
    "sg:postcode":"45200",
    "sg:province":"Toledo",
    "wof:name":"Hnos Martin Labarra S.l.",
    "wof:placetype":"venue"
},
  "geometry": {"coordinates":[-3.8556380272,40.1159858704],"type":"Point"}
}