{
  "type": "Feature",
  "properties": {
    "addr:full":"Avda Arias Maldonado, 2 Marbella M\u00e1laga 29600",
    "addr:housenumber":"2",
    "addr:postcode":"29600",
    "addr:street":"Avda Arias Maldonado;Ma\u0301Laga",
    "iso:country":"ES",
    "sg:address":"Avda Arias Maldonado, 2",
    "sg:city":"Marbella",
    "sg:orig_category":"Asesor\u00cdas Y Estudios Financieros",
    "sg:phone":"+34 952 82 62 53",
    "sg:postcode":"29600",
    "sg:province":"M\u00e1laga",
    "wof:name":"Vicioso Sanchez Isabel",
    "wof:placetype":"venue"
},
  "geometry": {"coordinates":[-4.8930158615,36.5101089478],"type":"Point"}
}