{
  "type": "Feature",
  "properties": {
    "addr:full":"Calle de Agua, 12 Villafranca De Los Barros Badajoz 06220",
    "addr:housenumber":"12",
    "addr:postcode":"06220",
    "addr:street":"Calle De Agua",
    "iso:country":"ES",
    "sg:address":"Calle de Agua, 12",
    "sg:city":"Villafranca De Los Barros",
    "sg:orig_category":"Plomeros",
    "sg:phone":"+34 924 52 46 13",
    "sg:postcode":"06220",
    "sg:province":"Badajoz",
    "wof:name":"Romafon S.l.",
    "wof:placetype":"venue"
},
  "geometry": {"coordinates":[-6.3412003517,38.5653762817],"type":"Point"}
}