{
  "type": "Feature",
  "properties": {
    "addr:full":"Calle de Rio Cares, 27 Pola De Laviana Asturias 33980",
    "addr:housenumber":"27",
    "addr:postcode":"33980",
    "addr:street":"Calle De Rio Cares;Pola",
    "iso:country":"ES",
    "sg:address":"Calle de Rio Cares, 27",
    "sg:city":"Pola De Laviana",
    "sg:orig_category":"Lencer\u00cda Femenina, Corseter\u00cda, Trajes De Ba\u00d1o (al Por Menor)",
    "sg:phone":"+34 985 61 08 72",
    "sg:postcode":"33980",
    "sg:province":"Asturias",
    "wof:name":"Vega Fernandez Susana",
    "wof:placetype":"venue"
},
  "geometry": {"coordinates":[-5.5641798973,43.2431755066],"type":"Point"}
}