{
  "type": "Feature",
  "properties": {
    "iso:country":"ES",
    "sg:address":"Pl Sant Ignasi, 17",
    "sg:city":"Manresa",
    "sg:orig_category":"Centros Empresariales",
    "sg:phone":"+34 938 73 41 06",
    "sg:postcode":"08241",
    "sg:province":"Barcelona",
    "wof:name":"Associacio Per A La Promocio De L'espectacle Infantil I Juvenil A Manresa",
    "wof:placetype":"venue"
},
  "geometry": {"coordinates":[1.8292269707,41.7242660522],"type":"Point"}
}