{
  "type": "Feature",
  "properties": {
    "addr:full":"C(pol Talluntxe), 21 Noain Navarra 31110",
    "addr:housenumber":"21",
    "addr:postcode":"31110",
    "addr:street":"C;Talluntxe",
    "iso:country":"ES",
    "sg:address":"C(pol Talluntxe), 21",
    "sg:city":"Noain",
    "sg:orig_category":"Radiocomunicaciones, Telefon\u00cda M\u00d3vil, Radiomensajer\u00cda: Servicios, Comercializaci\u00d3n",
    "sg:phone":"+34 948 36 80 39",
    "sg:postcode":"31110",
    "sg:province":"Navarra",
    "sg:website":"www.noditel.com",
    "wof:name":"Noditel S.l.",
    "wof:placetype":"venue"
},
  "geometry": {"coordinates":[-1.641849041,42.7574386597],"type":"Point"}
}