{
  "type": "Feature",
  "properties": {
    "iso:country":"ES",
    "sg:address":"Calle de Corta, 2",
    "sg:city":"Andujar",
    "sg:orig_category":"Asesor\u00cda De Formaci\u00d3n Y Gesti\u00d3n De Personal",
    "sg:phone":"+34 953 50 68 32",
    "sg:postcode":"23740",
    "sg:province":"Ja\u00e9n",
    "sg:website":"www.arquesytorres.com",
    "wof:name":"Antonio Arques Barios Y Otro Cdad.",
    "wof:placetype":"venue"
},
  "geometry": {"coordinates":[-4.0533452034,38.0392837524],"type":"Point"}
}