{
  "type": "Feature",
  "properties": {
    "iso:country":"ES",
    "sg:address":"Polig. A Gandara, S/n",
    "sg:city":"Ferrol",
    "sg:orig_category":"Lavado, Limpieza De Veh\u00cdculos",
    "sg:phone":"+34 981 37 04 44",
    "sg:postcode":"15407",
    "sg:province":"La Coru\u00f1a",
    "wof:name":"Imo Autolavados S.a.",
    "wof:placetype":"venue"
},
  "geometry": {"coordinates":[-8.201675415,43.4867858887],"type":"Point"}
}