{
  "type": "Feature",
  "properties": {
    "addr:full":"Calle de Febo, 3 Valdemoro Madrid 28340",
    "addr:housenumber":"3",
    "addr:postcode":"28340",
    "addr:street":"Calle De Febo",
    "iso:country":"ES",
    "sg:address":"Calle de Febo, 3",
    "sg:city":"Valdemoro",
    "sg:orig_category":"Quincaller\u00cda (al Por Menor)",
    "sg:phone":"+34 918 01 81 21",
    "sg:postcode":"28340",
    "sg:province":"Madrid",
    "wof:name":"Nu\u00f1ez Albarez Manuel",
    "wof:placetype":"venue"
},
  "geometry": {"coordinates":[-3.6854228973,40.1816673279],"type":"Point"}
}