{
  "type": "Feature",
  "properties": {
    "iso:country":"ES",
    "sg:address":"Calle de Sebastian Fernandez De Leceta, 8",
    "sg:city":"Vitoria-gasteiz",
    "sg:orig_category":"Alimentaci\u00d3n General (al Por Menor)",
    "sg:phone":"+34 945 21 35 93",
    "sg:postcode":"01009",
    "sg:province":"\u00c1lava",
    "wof:name":"Losada Mangana Nemesio",
    "wof:placetype":"venue"
},
  "geometry": {"coordinates":[-2.6822359562,42.8511314392],"type":"Point"}
}