{
  "type": "Feature",
  "properties": {
    "iso:country":"ES",
    "sg:address":"Carrer de Velia, 18",
    "sg:city":"Barcelona",
    "sg:orig_category":"Agencias Y Agentes Comerciales, Representantes",
    "sg:phone":"+34 933 40 92 28",
    "sg:postcode":"08016",
    "sg:province":"Barcelona",
    "wof:name":"Navarro Mora Antonio",
    "wof:placetype":"venue"
},
  "geometry": {"coordinates":[2.1809420586,41.4283828735],"type":"Point"}
}