{
  "type": "Feature",
  "properties": {
    "iso:country":"ES",
    "sg:address":"Calle de Ezcaray, 3",
    "sg:city":"Madrid",
    "sg:orig_category":"Centros De Educaci\u00d3n Especial",
    "sg:phone":"+34 917 75 27 15",
    "sg:postcode":"28032",
    "sg:province":"Madrid",
    "wof:name":"Colegio Nacional Severo Ochoa",
    "wof:placetype":"venue"
},
  "geometry": {"coordinates":[-3.6136960983,40.4103469849],"type":"Point"}
}