{
  "type": "Feature",
  "properties": {
    "iso:country":"ES",
    "sg:address":"Av Alameda (l'), 44",
    "sg:city":"Alcoi",
    "sg:orig_category":"Procuradores",
    "sg:phone":"+34 966 52 14 59",
    "sg:postcode":"03803",
    "sg:province":"Alicante",
    "wof:name":"Terol Calatayud Silvia",
    "wof:placetype":"venue"
},
  "geometry": {"coordinates":[-0.4783810079,38.7008628845],"type":"Point"}
}