{
  "type": "Feature",
  "properties": {
    "addr:full":"Carrer de Esglesia, 71 Calella Barcelona 08370",
    "addr:housenumber":"71",
    "addr:postcode":"08370",
    "addr:street":"Carrer De Esglesia",
    "iso:country":"ES",
    "sg:address":"Carrer de Esglesia, 71",
    "sg:city":"Calella",
    "sg:orig_category":"Fabricaci\u00d3n De Su\u00c9ters Y Chalecos De Punto",
    "sg:phone":"+34 937 66 30 61",
    "sg:postcode":"08370",
    "sg:province":"Barcelona",
    "wof:name":"Baby's Image S.l.",
    "wof:placetype":"venue"
},
  "geometry": {"coordinates":[2.6599121094,41.614151001],"type":"Point"}
}