{
  "type": "Feature",
  "properties": {
    "iso:country":"ES",
    "sg:address":"Calle de Dr Fleming, 12",
    "sg:city":"Guadalajara",
    "sg:orig_category":"Sociedades, Compa\u00d1\u00cdas Aseguradoras",
    "sg:phone":"+34 949 25 38 08",
    "sg:postcode":"19003",
    "sg:province":"Guadalajara",
    "wof:name":"Peritel S.l.",
    "wof:placetype":"venue"
},
  "geometry": {"coordinates":[-3.1645560265,40.6278533936],"type":"Point"}
}