{
  "type": "Feature",
  "properties": {
    "iso:country":"ES",
    "sg:address":"Rua Mendez Nu\u00d1ez, 2",
    "sg:city":"Ferrol",
    "sg:orig_category":"Distribuci\u00d3n De Petr\u00d3leo Y Derivados",
    "sg:phone":"+34 981 35 21 81",
    "sg:postcode":"15402",
    "sg:province":"La Coru\u00f1a",
    "wof:name":"Pindusa S.l.",
    "wof:placetype":"venue"
},
  "geometry": {"coordinates":[-8.2365312576,43.4817733765],"type":"Point"}
}