{
  "type": "Feature",
  "properties": {
    "addr:full":"C/ Segle Xx, 19 Tarrega Lleida 25300",
    "addr:housenumber":"19",
    "addr:postcode":"25300",
    "addr:street":"C / Segle Xx",
    "iso:country":"ES",
    "sg:address":"C/ Segle Xx, 19",
    "sg:city":"Tarrega",
    "sg:orig_category":"Promotores Constructores",
    "sg:phone":"+34 973 50 18 67",
    "sg:postcode":"25300",
    "sg:province":"Lleida",
    "wof:name":"Casanellas I Bras S.l.",
    "wof:placetype":"venue"
},
  "geometry": {"coordinates":[1.1368650198,41.6494293213],"type":"Point"}
}