{
  "type": "Feature",
  "properties": {
    "addr:full":"Carrer de Sant Pere, 34 Altea Alicante 03590",
    "addr:housenumber":"34",
    "addr:postcode":"03590",
    "addr:street":"Carrer De Sant Pere",
    "iso:country":"ES",
    "sg:address":"Carrer de Sant Pere, 34",
    "sg:city":"Altea",
    "sg:orig_category":"Caf\u00c9s, Bares, Cervecer\u00cdas",
    "sg:phone":"+34 965 84 01 49",
    "sg:postcode":"03590",
    "sg:province":"Alicante",
    "wof:name":"Navarro Alvado Francisco Jesus",
    "wof:placetype":"venue"
},
  "geometry": {"coordinates":[-0.050960999,38.595741272],"type":"Point"}
}