{
  "type": "Feature",
  "properties": {
    "iso:country":"ES",
    "sg:address":"Ctra Zorrotza-kastrexana, 2",
    "sg:city":"Bilbao",
    "sg:orig_category":"Fotograf\u00cda Y Cine: Aparatos, Pel\u00cdculas Y Accesorios (fabricaci\u00d3n, Al Por Mayor)",
    "sg:phone":"+34 944 41 90 31",
    "sg:postcode":"48013",
    "sg:province":"Vizcaya",
    "wof:name":"Rosa Maria Perez Cuartango",
    "wof:placetype":"venue"
},
  "geometry": {"coordinates":[-2.9713950157,43.2761573792],"type":"Point"}
}