{
  "type": "Feature",
  "properties": {
    "addr:full":"Carr Pere Cavasequia, 20 Lleida Lleida 25005",
    "addr:housenumber":"20",
    "addr:postcode":"25005",
    "addr:street":"Carr Pere Cavasequia",
    "iso:country":"ES",
    "sg:address":"Carr Pere Cavasequia, 20",
    "sg:city":"Lleida",
    "sg:orig_category":"Peluquer\u00cdas",
    "sg:phone":"+34 973 23 92 91",
    "sg:postcode":"25005",
    "sg:province":"Lleida",
    "wof:name":"Guitart Salvado Luis",
    "wof:placetype":"venue"
},
  "geometry": {"coordinates":[0.6369339824,41.6213226318],"type":"Point"}
}