{
  "type": "Feature",
  "properties": {
    "iso:country":"ES",
    "sg:address":"Carr Via Romana, 3",
    "sg:city":"Eivissa",
    "sg:orig_category":"Abogados",
    "sg:phone":"+34 971 39 05 76",
    "sg:postcode":"07800",
    "sg:province":"Islas Baleares",
    "wof:name":"Valdes Prats Matilde Maria",
    "wof:placetype":"venue"
},
  "geometry": {"coordinates":[1.4188899994,38.9061164856],"type":"Point"}
}