{
  "type": "Feature",
  "properties": {
    "iso:country":"ES",
    "sg:address":"Calle de Virgen De Los Reyes, 14",
    "sg:city":"Madrid",
    "sg:orig_category":"Reposter\u00cdas",
    "sg:phone":"+34 914 04 45 05",
    "sg:postcode":"28027",
    "sg:province":"Madrid",
    "wof:name":"Cancelo Gallego Laudino",
    "wof:placetype":"venue"
},
  "geometry": {"coordinates":[-3.6517260075,40.4382095337],"type":"Point"}
}