{
  "type": "Feature",
  "properties": {
    "iso:country":"ES",
    "sg:address":"Calle de Aldamar, 24",
    "sg:city":"Donostia-san Sebastian",
    "sg:orig_category":"Librer\u00cdas",
    "sg:phone":"+34 943 43 15 05",
    "sg:postcode":"20003",
    "sg:province":"Guip\u00f9zcoa",
    "sg:website":"www.e-shambhala.com",
    "wof:name":"Garbi\u00f1e Garzo Rodriguez Y Otro C.b.",
    "wof:placetype":"venue"
},
  "geometry": {"coordinates":[-1.9828697443,43.3241119385],"type":"Point"}
}