{
  "type": "Feature",
  "properties": {
    "addr:full":"Calle de Jaboneria, 5 Azuaga Badajoz 06920",
    "addr:housenumber":"5",
    "addr:postcode":"06920",
    "addr:street":"Calle De Jaboneria",
    "iso:country":"ES",
    "sg:address":"Calle de Jaboneria, 5",
    "sg:city":"Azuaga",
    "sg:orig_category":"Doctores En Medicina",
    "sg:phone":"+34 924 89 24 45",
    "sg:postcode":"06920",
    "sg:province":"Badajoz",
    "wof:name":"Santos Rodriguez Wilfredo",
    "wof:placetype":"venue"
},
  "geometry": {"coordinates":[-5.6735839844,38.256603241],"type":"Point"}
}