{
  "type": "Feature",
  "properties": {
    "iso:country":"ES",
    "sg:address":"Carrer de Castellsapera, 82",
    "sg:city":"Terrassa",
    "sg:orig_category":"Peluqueros: De Se\u00d1oras",
    "sg:phone":"+34 937 85 54 92",
    "sg:postcode":"08227",
    "sg:province":"Barcelona",
    "wof:name":"Sanchez Diaz Ana",
    "wof:placetype":"venue"
},
  "geometry": {"coordinates":[2.0318961143,41.5767593384],"type":"Point"}
}