{
  "type": "Feature",
  "properties": {
    "iso:country":"ES",
    "sg:address":"Calle de Alcalde Luis Pascual, 32",
    "sg:city":"Caudete",
    "sg:orig_category":"Electrodom\u00c9sticos (al Por Menor)",
    "sg:phone":"+34 965 82 74 40",
    "sg:postcode":"02660",
    "sg:province":"Albacete",
    "wof:name":"Electrodomesticos Perez Camarasa S.l.",
    "wof:placetype":"venue"
},
  "geometry": {"coordinates":[-0.9869611263,38.7046127319],"type":"Point"}
}