{
  "type": "Feature",
  "properties": {
    "addr:full":"Calle de Reyes Catolicos, 45 Granada Granada 18001",
    "addr:housenumber":"45",
    "addr:postcode":"18001",
    "addr:street":"Calle De Reyes Catolicos",
    "iso:country":"ES",
    "sg:address":"Calle de Reyes Catolicos, 45",
    "sg:city":"Granada",
    "sg:orig_category":"Equitaci\u00d3n Y Centros De H\u00cdpica",
    "sg:phone":"+34 958 22 22 54",
    "sg:postcode":"18001",
    "sg:province":"Granada",
    "sg:website":"www.elcaballo.com",
    "wof:name":"El Caballo-ferlano S.l.",
    "wof:placetype":"venue"
},
  "geometry": {"coordinates":[-3.5980989933,37.175491333],"type":"Point"}
}