{
  "type": "Feature",
  "properties": {
    "iso:country":"ES",
    "sg:address":"San Mauro, 14",
    "sg:city":"Lampon",
    "sg:orig_category":"Autob\u00das (explotaci\u00d3n Y Servicios De)",
    "sg:phone":"+34 981 84 64 26",
    "sg:postcode":"15992",
    "sg:province":"La Coru\u00f1a",
    "wof:name":"Rodriguez Campa\u00f1a Jose",
    "wof:placetype":"venue"
},
  "geometry": {"coordinates":[-8.9047136307,42.6364364624],"type":"Point"}
}