{
  "type": "Feature",
  "properties": {
    "addr:full":"Carrer de Llobateres, S/n Barbera Valles Barcelona 08210",
    "addr:housenumber":"s / n",
    "addr:postcode":"08210",
    "addr:street":"Carrer De Llobateres",
    "iso:country":"ES",
    "sg:address":"Carrer de Llobateres, S/n",
    "sg:city":"Barbera Valles",
    "sg:orig_category":"Electricidad, Electr\u00d3nica: Material Y Suministros (al Por Mayor)",
    "sg:phone":"+34 937 18 28 03",
    "sg:postcode":"08210",
    "sg:province":"Barcelona",
    "sg:website":"www.mebsa.com",
    "wof:name":"Maquinaria Electrica Bilbao S. A.",
    "wof:placetype":"venue"
},
  "geometry": {"coordinates":[2.1419599056,41.5272636414],"type":"Point"}
}