{
  "type": "Feature",
  "properties": {
    "iso:country":"ES",
    "sg:address":"Avda San Martin De Valdeiglesia, 24",
    "sg:city":"Alcorcon",
    "sg:orig_category":"Lencer\u00cda Femenina, Corseter\u00cda, Trajes De Ba\u00d1o (al Por Menor)",
    "sg:phone":"+34 916 11 29 76",
    "sg:postcode":"28922",
    "sg:province":"Madrid",
    "wof:name":"Zamodos S.l.",
    "wof:placetype":"venue"
},
  "geometry": {"coordinates":[-3.8553507328,40.3570022583],"type":"Point"}
}