{
  "type": "Feature",
  "properties": {
    "iso:country":"ES",
    "sg:address":"Carrer de Anselm Clave, 160",
    "sg:city":"Olesa Montserrat",
    "sg:orig_category":"Zapatos (al Por Menor)",
    "sg:phone":"+34 937 78 58 18",
    "sg:postcode":"08640",
    "sg:province":"Barcelona",
    "wof:name":"Zamora Maresme S.l.",
    "wof:placetype":"venue"
},
  "geometry": {"coordinates":[1.893366456,41.5439910889],"type":"Point"}
}