{
  "type": "Feature",
  "properties": {
    "addr:full":"Calle de Arapiles, 51 Salamanca Salamanca 37007",
    "addr:housenumber":"51",
    "addr:postcode":"37007",
    "addr:street":"Calle De Arapiles",
    "iso:country":"ES",
    "sg:address":"Calle de Arapiles, 51",
    "sg:city":"Salamanca",
    "sg:orig_category":"Transportes De Animales Vivos",
    "sg:phone":"+34 923 23 54 37",
    "sg:postcode":"37007",
    "sg:province":"Salamanca",
    "wof:name":"Grande Gonzalez Fausto",
    "wof:placetype":"venue"
},
  "geometry": {"coordinates":[-5.6743979454,40.9688835144],"type":"Point"}
}