{
  "type": "Feature",
  "properties": {
    "iso:country":"ES",
    "sg:address":"Avda Oporto, 71",
    "sg:city":"Madrid",
    "sg:orig_category":"Caf\u00c9s, Bares, Cervecer\u00cdas",
    "sg:phone":"+34 914 71 09 37",
    "sg:postcode":"28019",
    "sg:province":"Madrid",
    "wof:name":"Caballero Diaz Santiago",
    "wof:placetype":"venue"
},
  "geometry": {"coordinates":[-3.7292649746,40.3867759705],"type":"Point"}
}