{
  "type": "Feature",
  "properties": {
    "iso:country":"ES",
    "sg:address":"Pl Rovira I Trias, 2",
    "sg:city":"Barcelona",
    "sg:orig_category":"Delegados, Agentes De Tr\u00c1nsito, Auxiliares De Transporte Internacional",
    "sg:phone":"+34 932 13 34 37",
    "sg:postcode":"08024",
    "sg:province":"Barcelona",
    "wof:name":"Arcarons Simo Jaime",
    "wof:placetype":"venue"
},
  "geometry": {"coordinates":[2.1584706306,41.4074249268],"type":"Point"}
}