{
  "type": "Feature",
  "properties": {
    "iso:country":"ES",
    "sg:address":"Calle de Asuncion, 44",
    "sg:city":"Molina Segura",
    "sg:orig_category":"Estudios, Instalaci\u00d3n De Climatizaci\u00d3n",
    "sg:phone":"+34 968 61 32 00",
    "sg:postcode":"30500",
    "sg:province":"Murcia",
    "wof:name":"Frio Lopez Meseguer S.l.",
    "wof:placetype":"venue"
},
  "geometry": {"coordinates":[-1.2106328011,38.0539741516],"type":"Point"}
}