{
  "type": "Feature",
  "properties": {
    "addr:full":"Entd Moli Dels Canyars, 7 Carpesa Valencia 46016",
    "addr:housenumber":"7",
    "addr:postcode":"46016",
    "addr:street":"Canyars",
    "iso:country":"ES",
    "sg:address":"Entd Moli Dels Canyars, 7",
    "sg:city":"Carpesa",
    "sg:orig_category":"Venta, Alquiler De Instrumentos Y Accesorios De M\u00dasica",
    "sg:phone":"+34 961 85 94 74",
    "sg:postcode":"46016",
    "sg:province":"Valencia",
    "wof:name":"Percussions De Valencia S.cv.",
    "wof:placetype":"venue"
},
  "geometry": {"coordinates":[-0.3657299876,39.5067596436],"type":"Point"}
}