{
  "type": "Feature",
  "properties": {
    "addr:full":"Carrer de Comte D'urgell, 21 Sabadell Barcelona 08208",
    "addr:housenumber":"21",
    "addr:postcode":"08208",
    "addr:street":"Carrer De Comte D'Urgell",
    "iso:country":"ES",
    "sg:address":"Carrer de Comte D'urgell, 21",
    "sg:city":"Sabadell",
    "sg:orig_category":"Fisioterapia",
    "sg:phone":"+34 937 24 34 20",
    "sg:postcode":"08208",
    "sg:province":"Barcelona",
    "wof:name":"Ortex",
    "wof:placetype":"venue"
},
  "geometry": {"coordinates":[2.1033017635,41.5695343018],"type":"Point"}
}