{
  "type": "Feature",
  "properties": {
    "iso:country":"ES",
    "sg:address":"Avda Ferrol, 77",
    "sg:city":"Pontedeume",
    "sg:orig_category":"Bebidas",
    "sg:phone":"+34 981 43 01 21",
    "sg:postcode":"15600",
    "sg:province":"La Coru\u00f1a",
    "wof:name":"Bodegas Nistal S.l.",
    "wof:placetype":"venue"
},
  "geometry": {"coordinates":[-8.1797790527,43.4115180969],"type":"Point"}
}