{
  "type": "Feature",
  "properties": {
    "addr:full":"Ptge Emporda, 1 S. Boi Llobregat Barcelona 08830",
    "addr:housenumber":"1",
    "addr:postcode":"08830",
    "addr:street":"Ptge Emporda",
    "iso:country":"ES",
    "sg:address":"Ptge Emporda, 1",
    "sg:city":"S. Boi Llobregat",
    "sg:orig_category":"Veh\u00cdculos De Ocasi\u00d3n",
    "sg:phone":"+34 936 30 07 79",
    "sg:postcode":"08830",
    "sg:province":"Barcelona",
    "wof:name":"Automoviles Isamar S.c.p.",
    "wof:placetype":"venue"
},
  "geometry": {"coordinates":[2.0379929543,41.3475456238],"type":"Point"}
}