{
  "type": "Feature",
  "properties": {
    "iso:country":"ES",
    "sg:address":"Pol. Ind. La Tapiada, S/n",
    "sg:city":"S. Esteban Gormaz",
    "sg:orig_category":"Muebles, Minoristas",
    "sg:phone":"+34 975 35 05 36",
    "sg:postcode":"42330",
    "sg:province":"Soria",
    "wof:name":"Lagunas Carretero S.l.",
    "wof:placetype":"venue"
},
  "geometry": {"coordinates":[-3.1995689869,41.5723457336],"type":"Point"}
}