{
  "type": "Feature",
  "properties": {
    "addr:full":"Calle de Jose Marco, 8 Binefar Huesca 22500",
    "addr:housenumber":"8",
    "addr:postcode":"22500",
    "addr:street":"Calle De Jose Marco",
    "iso:country":"ES",
    "sg:address":"Calle de Jose Marco, 8",
    "sg:city":"Binefar",
    "sg:orig_category":"Peluqueros: De Se\u00d1oras",
    "sg:phone":"+34 974 42 86 19",
    "sg:postcode":"22500",
    "sg:province":"Huesca",
    "wof:name":"Badal Ferrer Aurelia",
    "wof:placetype":"venue"
},
  "geometry": {"coordinates":[0.2938441038,41.8475036621],"type":"Point"}
}