{
  "type": "Feature",
  "properties": {
    "addr:full":"Calle de Chile, 42 Logro\u00f1o La Rioja 26005",
    "addr:housenumber":"42",
    "addr:postcode":"26005",
    "addr:street":"Calle De Chile;Rioja",
    "iso:country":"ES",
    "sg:address":"Calle de Chile, 42",
    "sg:city":"Logro\u00f1o",
    "sg:orig_category":"Centros De Educaci\u00d3n Especial",
    "sg:phone":"+34 941 21 08 77",
    "sg:postcode":"26005",
    "sg:province":"La Rioja",
    "wof:name":"Comunidad Autonoma De La Rioja",
    "wof:placetype":"venue"
},
  "geometry": {"coordinates":[-2.4564890862,42.4586715698],"type":"Point"}
}