{
  "type": "Feature",
  "properties": {
    "iso:country":"ES",
    "sg:address":"Avda. Margaritas, S/n",
    "sg:city":"Mijas Costa",
    "sg:classifiers":[
        {
            "category":"Autos & Motor Vehicles",
            "subcategory":"Automobile Sales",
            "type":"Retail Goods"
        }
    ],
    "sg:phone":"+34 952 66 65 42",
    "sg:postcode":"29649",
    "sg:province":"M\u00e1laga",
    "wof:name":"Autoescuelas Villablanca S.l.",
    "wof:placetype":"venue"
},
  "geometry": {"coordinates":[-4.713206768,36.491027832],"type":"Point"}
}