{
  "type": "Feature",
  "properties": {
    "addr:full":"Calle de Alameda, 16 Coslada Madrid 28820",
    "addr:housenumber":"16",
    "addr:postcode":"28820",
    "addr:street":"Calle De Alameda",
    "iso:country":"ES",
    "sg:address":"Calle de Alameda, 16",
    "sg:city":"Coslada",
    "sg:orig_category":"Zapatos (al Por Menor)",
    "sg:phone":"+34 916 72 52 48",
    "sg:postcode":"28820",
    "sg:province":"Madrid",
    "wof:name":"Lopez Cobo Juana",
    "wof:placetype":"venue"
},
  "geometry": {"coordinates":[-3.560675621,40.4298706055],"type":"Point"}
}