{
  "type": "Feature",
  "properties": {
    "addr:full":"Avda Sierra (de La), 1 San Sebastian De Los Reyes Madrid 28700",
    "addr:postcode":"28700",
    "addr:street":"Avda Sierra De La 1",
    "iso:country":"ES",
    "sg:address":"Avda Sierra (de La), 1",
    "sg:city":"San Sebastian De Los Reyes",
    "sg:orig_category":"Peluquer\u00cdas, Peluquer\u00cda Mixta",
    "sg:phone":"+34 916 52 63 02",
    "sg:postcode":"28700",
    "sg:province":"Madrid",
    "wof:name":"A Tu Aire Peluqueros S.l.",
    "wof:placetype":"venue"
},
  "geometry": {"coordinates":[-3.630959034,40.5520782471],"type":"Point"}
}