{
  "type": "Feature",
  "properties": {
    "addr:full":"Jose Artetxe Kalea, 10 Azpeitia Guip\u00f9zcoa 20730",
    "addr:housenumber":"10",
    "addr:postcode":"20730",
    "addr:street":"Jose Artetxe Kalea;Guipu\u0300Zcoa",
    "iso:country":"ES",
    "sg:address":"Jose Artetxe Kalea, 10",
    "sg:city":"Azpeitia",
    "sg:orig_category":"Decoradores",
    "sg:phone":"+34 943 08 03 71",
    "sg:postcode":"20730",
    "sg:province":"Guip\u00f9zcoa",
    "wof:name":"Balenziaga Interiores",
    "wof:placetype":"venue"
},
  "geometry": {"coordinates":[-2.2671461105,43.1817626953],"type":"Point"}
}