{
  "type": "Feature",
  "properties": {
    "iso:country":"ES",
    "sg:address":"Praz Castelao, 6",
    "sg:city":"Corcubion",
    "sg:orig_category":"Lencer\u00cda Femenina, Corseter\u00cda, Trajes De Ba\u00d1o (al Por Menor)",
    "sg:phone":"+34 981 74 62 61",
    "sg:postcode":"15130",
    "sg:province":"La Coru\u00f1a",
    "wof:name":"Martinez Caama\u00f1o Almudena",
    "wof:placetype":"venue"
},
  "geometry": {"coordinates":[-9.1982126236,42.92811203],"type":"Point"}
}