{
  "type": "Feature",
  "properties": {
    "addr:full":"Jesus Artesano, 6 Navas Del Rey Madrid 28695",
    "addr:postcode":"28695",
    "iso:country":"ES",
    "sg:address":"Jesus Artesano, 6",
    "sg:city":"Navas Del Rey",
    "sg:orig_category":"Cer\u00c1micas: Material Y Suministros",
    "sg:phone":"+34 918 65 02 11",
    "sg:postcode":"28695",
    "sg:province":"Madrid",
    "wof:name":"Pavimarsa S.a.",
    "wof:placetype":"venue"
},
  "geometry": {"coordinates":[-4.243543148,40.3851356506],"type":"Point"}
}