{
  "type": "Feature",
  "properties": {
    "iso:country":"ES",
    "sg:address":"Calle de Eucalipto (del), 4",
    "sg:city":"Parque Coimbra",
    "sg:orig_category":"Par\u00cds",
    "sg:phone":"+34 916 47 91 38",
    "sg:postcode":"28935",
    "sg:province":"Madrid",
    "wof:name":"Sanchez Quintanilla Eulogio",
    "wof:placetype":"venue"
},
  "geometry": {"coordinates":[-3.9251389503,40.3101272583],"type":"Point"}
}