{
  "type": "Feature",
  "properties": {
    "iso:country":"ES",
    "sg:address":"Calle de Sorolla, 5",
    "sg:city":"Estacion",
    "sg:orig_category":"Electricidad: Instaladores",
    "sg:phone":"+34 952 42 02 54",
    "sg:postcode":"29580",
    "sg:province":"M\u00e1laga",
    "wof:name":"Jimenez Pozo Francisco",
    "wof:placetype":"venue"
},
  "geometry": {"coordinates":[-4.6124329567,36.7320213318],"type":"Point"}
}