{
  "type": "Feature",
  "properties": {
    "addr:full":"Calle de Goya, 68 Sevilla Sevilla 41005",
    "addr:housenumber":"68",
    "addr:postcode":"41005",
    "addr:street":"Calle De Goya",
    "iso:country":"ES",
    "sg:address":"Calle de Goya, 68",
    "sg:city":"Sevilla",
    "sg:orig_category":"Procuradores",
    "sg:phone":"+34 954 92 57 72",
    "sg:postcode":"41005",
    "sg:province":"Sevilla",
    "wof:name":"Barbera Rubini Lourdes",
    "wof:placetype":"venue"
},
  "geometry": {"coordinates":[-5.9692649841,37.3825111389],"type":"Point"}
}