{
  "type": "Feature",
  "properties": {
    "addr:full":"Carrer de Poblet, 27 Terra Nostra Barcelona 08110",
    "addr:housenumber":"27",
    "addr:postcode":"08110",
    "addr:street":"Carrer De Poblet",
    "iso:country":"ES",
    "sg:address":"Carrer de Poblet, 27",
    "sg:city":"Terra Nostra",
    "sg:orig_category":"Carnicer\u00cdas, Carnicer\u00cdas",
    "sg:phone":"+34 935 64 51 74",
    "sg:postcode":"08110",
    "sg:province":"Barcelona",
    "wof:name":"Puerta Valderrama Rafael",
    "wof:placetype":"venue"
},
  "geometry": {"coordinates":[2.1682169437,41.4829750061],"type":"Point"}
}