{
  "type": "Feature",
  "properties": {
    "addr:full":"Calle de Giralda, 8 Madrid Madrid 28041",
    "addr:housenumber":"8",
    "addr:postcode":"madrid;28041",
    "addr:street":"Calle De Giralda",
    "iso:country":"ES",
    "sg:address":"Calle de Giralda, 8",
    "sg:city":"Madrid",
    "sg:orig_category":"Peluquer\u00cdas, Peluquer\u00cda Mixta",
    "sg:phone":"+34 917 92 10 84",
    "sg:postcode":"28041",
    "sg:province":"Madrid",
    "wof:name":"Blazquez Matias Ana Maria",
    "wof:placetype":"venue"
},
  "geometry": {"coordinates":[-3.6914229393,40.3743515015],"type":"Point"}
}