{
  "type": "Feature",
  "properties": {
    "iso:country":"ES",
    "sg:address":"Calle de Azucarera, 14",
    "sg:city":"Cortes",
    "sg:orig_category":"Empresas De Carpinter\u00cda De Madera",
    "sg:phone":"+34 948 80 03 27",
    "sg:postcode":"31530",
    "sg:province":"Navarra",
    "wof:name":"Gonzalez Sancho Jose",
    "wof:placetype":"venue"
},
  "geometry": {"coordinates":[-1.4212967157,41.9160194397],"type":"Point"}
}