{
  "type": "Feature",
  "properties": {
    "iso:country":"ES",
    "sg:address":"Pl. Petita, 7",
    "sg:city":"Riudoms",
    "sg:orig_category":"Inmobiliaria (agencias)",
    "sg:phone":"+34 977 85 16 23",
    "sg:postcode":"43330",
    "sg:province":"Tarragona",
    "wof:name":"Gest-tram Riudoms S.l.",
    "wof:placetype":"venue"
},
  "geometry": {"coordinates":[1.051486969,41.1385002136],"type":"Point"}
}