{
  "type": "Feature",
  "properties": {
    "addr:full":"Avda Castelao, 15 Vigo Pontevedra 36209",
    "addr:housenumber":"15",
    "addr:postcode":"36209",
    "addr:street":"Avda Castelao",
    "iso:country":"ES",
    "sg:address":"Avda Castelao, 15",
    "sg:city":"Vigo",
    "sg:orig_category":"Asesor\u00cda Sobre Comunicaci\u00d3n De Empresas",
    "sg:phone":"+34 986 20 81 87",
    "sg:postcode":"36209",
    "sg:province":"Pontevedra",
    "wof:name":"Agam Msf S.l.",
    "wof:placetype":"venue"
},
  "geometry": {"coordinates":[-8.7362937927,42.2198181152],"type":"Point"}
}