{
  "type": "Feature",
  "properties": {
    "addr:full":"Avda Ricardo Soriano, 12 Marbella M\u00e1laga 29600",
    "addr:housenumber":"12",
    "addr:postcode":"29600",
    "addr:street":"Avda Ricardo Soriano;Ma\u0301Laga",
    "iso:country":"ES",
    "sg:address":"Avda Ricardo Soriano, 12",
    "sg:city":"Marbella",
    "sg:orig_category":"M\u00c9dicos: Otorrinolaringolog\u00cda",
    "sg:phone":"+34 952 86 28 72",
    "sg:postcode":"29600",
    "sg:province":"M\u00e1laga",
    "wof:name":"Ruiz Rico Ruiz Moron Rafael",
    "wof:placetype":"venue"
},
  "geometry": {"coordinates":[-4.8877000809,36.5098266602],"type":"Point"}
}