{
  "type": "Feature",
  "properties": {
    "iso:country":"ES",
    "sg:address":"Calle de Carretera, S/n",
    "sg:city":"Bercianos De Aliste",
    "sg:orig_category":"Empresas De Carpinter\u00cda De Madera",
    "sg:phone":"+34 980 59 42 16",
    "sg:postcode":"49592",
    "sg:province":"Zamora",
    "wof:name":"Pergusan S.l",
    "wof:placetype":"venue"
},
  "geometry": {"coordinates":[-6.2276792526,41.7891693115],"type":"Point"}
}