{
  "type": "Feature",
  "properties": {
    "iso:country":"ES",
    "sg:address":"Pl. San J. Cadena, 4",
    "sg:city":"Iru\u00f1a",
    "sg:orig_category":"Peluqueros: De Se\u00d1oras",
    "sg:phone":"+34 948 25 80 42",
    "sg:postcode":"31008",
    "sg:province":"Navarra",
    "wof:name":"Fernandez Fernandez Maria Concepcion",
    "wof:placetype":"venue"
},
  "geometry": {"coordinates":[-1.6575989723,42.8112831116],"type":"Point"}
}