{
  "type": "Feature",
  "properties": {
    "iso:country":"ES",
    "sg:address":"Calle de Enmedio, 28",
    "sg:city":"Castellon",
    "sg:orig_category":"Fabricaci\u00d3n De Sobres, Bolsas Y Fundas",
    "sg:phone":"+34 964 22 46 70",
    "sg:postcode":"12001",
    "sg:province":"Castell\u00f3n",
    "wof:name":"Asencio Hidalgo Francisco",
    "wof:placetype":"venue"
},
  "geometry": {"coordinates":[-0.0388171002,39.9853630066],"type":"Point"}
}