{
  "type": "Feature",
  "properties": {
    "addr:full":"Calle de Cervantes, 76 Coria Rio Sevilla 41100",
    "addr:housenumber":"76",
    "addr:postcode":"41100",
    "addr:street":"Calle De Cervantes;Rio Sevilla",
    "iso:country":"ES",
    "sg:address":"Calle de Cervantes, 76",
    "sg:city":"Coria Rio",
    "sg:orig_category":"M\u00c9dicos: An\u00c1lisis Cl\u00cdnicos",
    "sg:phone":"+34 954 77 35 93",
    "sg:postcode":"41100",
    "sg:province":"Sevilla",
    "wof:name":"Nu\u00f1ez Gallo Ruperto",
    "wof:placetype":"venue"
},
  "geometry": {"coordinates":[-6.0527453423,37.2838630676],"type":"Point"}
}