{
  "type": "Feature",
  "properties": {
    "addr:full":"Ctra. Eivissa Portinatx, 54 Portinatx Islas Baleares 07810",
    "addr:housenumber":"54",
    "addr:postcode":"07810",
    "addr:street":"Ctra. Eivissa Portinatx",
    "iso:country":"ES",
    "sg:address":"Ctra. Eivissa Portinatx, 54",
    "sg:city":"Portinatx",
    "sg:orig_category":"Forjas Y Altos Hornos",
    "sg:phone":"+34 971 32 06 66",
    "sg:postcode":"07810",
    "sg:province":"Islas Baleares",
    "wof:name":"Herreria Y Construccion Murtera S.l.",
    "wof:placetype":"venue"
},
  "geometry": {"coordinates":[1.5129300356,39.0777397156],"type":"Point"}
}