{
  "type": "Feature",
  "properties": {
    "addr:full":"Calle de General Urrutia, 71 Logro\u00f1o La Rioja 26006",
    "addr:housenumber":"71",
    "addr:postcode":"26006",
    "addr:street":"Calle De General Urrutia;Rioja",
    "iso:country":"ES",
    "sg:address":"Calle de General Urrutia, 71",
    "sg:city":"Logro\u00f1o",
    "sg:orig_category":"Cajas De Ahorro",
    "sg:phone":"+34 941 21 66 32",
    "sg:postcode":"26006",
    "sg:province":"La Rioja",
    "wof:name":"Caja De Ahorros De La Rioja",
    "wof:placetype":"venue"
},
  "geometry": {"coordinates":[-2.4615991116,42.4714393616],"type":"Point"}
}