{
  "type": "Feature",
  "properties": {
    "addr:full":"Cristofol De Moura, S/n S. Adria Besos Barcelona 08930",
    "addr:housenumber":"s",
    "addr:postcode":"08930",
    "addr:street":"Cristofol;Moura;/ N S.;Barcelona",
    "iso:country":"ES",
    "sg:address":"Cristofol De Moura, S/n",
    "sg:city":"S. Adria Besos",
    "sg:orig_category":"Bancos",
    "sg:phone":"+34 934 62 10 85",
    "sg:postcode":"08930",
    "sg:province":"Barcelona",
    "wof:name":"Auna Telecomunicaciones S.a.u.",
    "wof:placetype":"venue"
},
  "geometry": {"coordinates":[2.2201168537,41.4213638306],"type":"Point"}
}