{
  "type": "Feature",
  "properties": {
    "addr:full":"Calle de Estivella, 6 Sagunt Valencia 46500",
    "addr:housenumber":"6",
    "addr:postcode":"46500",
    "addr:street":"Calle De Estivella",
    "iso:country":"ES",
    "sg:address":"Calle de Estivella, 6",
    "sg:city":"Sagunt",
    "sg:orig_category":"Instalaci\u00d3n, Reparaci\u00d3n De Calefacci\u00d3n Por Gas",
    "sg:phone":"+34 962 66 36 37",
    "sg:postcode":"46500",
    "sg:province":"Valencia",
    "wof:name":"Recalgas S.c.p.",
    "wof:placetype":"venue"
},
  "geometry": {"coordinates":[-0.2831799984,39.6820335388],"type":"Point"}
}