{
  "type": "Feature",
  "properties": {
    "addr:full":"Carrer de Valencia, 29 Galatzo Islas Baleares 07180",
    "addr:housenumber":"29",
    "addr:postcode":"07180",
    "addr:street":"Carrer De Valencia;Islas",
    "iso:country":"ES",
    "sg:address":"Carrer de Valencia, 29",
    "sg:city":"Galatzo",
    "sg:orig_category":"Promotores Constructores",
    "sg:phone":"+34 971 69 22 69",
    "sg:postcode":"07180",
    "sg:province":"Islas Baleares",
    "wof:name":"Jinks  David",
    "wof:placetype":"venue"
},
  "geometry": {"coordinates":[2.5089640617,39.5304412842],"type":"Point"}
}