{
  "type": "Feature",
  "properties": {
    "addr:full":"Calle de Jose Maria Pereda, 5 Alcala Henares Madrid 28806",
    "addr:housenumber":"5",
    "addr:postcode":"28806",
    "addr:street":"Calle De Jose Maria Pereda",
    "iso:country":"ES",
    "sg:address":"Calle de Jose Maria Pereda, 5",
    "sg:city":"Alcala Henares",
    "sg:orig_category":"Abogados",
    "sg:phone":"+34 918 02 65 75",
    "sg:postcode":"28806",
    "sg:province":"Madrid",
    "wof:name":"Smm-abogados C.b.",
    "wof:placetype":"venue"
},
  "geometry": {"coordinates":[-3.3636538982,40.496673584],"type":"Point"}
}