{
  "type": "Feature",
  "properties": {
    "addr:full":"Calle de Ejido De San Juan, 10 Almagro Ciudad Real 13270",
    "addr:housenumber":"10",
    "addr:postcode":"13270",
    "addr:street":"Calle De Ejido De San Juan",
    "iso:country":"ES",
    "sg:address":"Calle de Ejido De San Juan, 10",
    "sg:city":"Almagro",
    "sg:orig_category":"Veh\u00cdculos De Ocasi\u00d3n",
    "sg:phone":"+34 926 88 23 61",
    "sg:postcode":"13270",
    "sg:province":"Ciudad Real",
    "wof:name":"Castellanos Romero Luis",
    "wof:placetype":"venue"
},
  "geometry": {"coordinates":[-3.7066090107,38.8862190247],"type":"Point"}
}