{
  "type": "Feature",
  "properties": {
    "addr:full":"Calle de Real, S/n Lavandera Le\u00f3n 24837",
    "addr:housenumber":"s / n",
    "addr:postcode":"24837",
    "addr:street":"Calle De Real;Lavandera Leo\u0301N",
    "iso:country":"ES",
    "sg:address":"Calle de Real, S/n",
    "sg:city":"Lavandera",
    "sg:orig_category":"Cr\u00cda De Animales",
    "sg:phone":"+34 987 57 65 86",
    "sg:postcode":"24837",
    "sg:province":"Le\u00f3n",
    "wof:name":"Gonzalez Fernandez Eduardo",
    "wof:placetype":"venue"
},
  "geometry": {"coordinates":[-5.5138921738,42.9499664307],"type":"Point"}
}