{
  "type": "Feature",
  "properties": {
    "addr:full":"Nva Apertura, 3 Cabra C\u00f3rdoba 14940",
    "addr:housenumber":"3",
    "addr:postcode":"14940",
    "addr:street":"Apertura;Co\u0301Rdoba",
    "iso:country":"ES",
    "sg:address":"Nva Apertura, 3",
    "sg:city":"Cabra",
    "sg:orig_category":"Pescader\u00cdas (al Por Menor)",
    "sg:phone":"+34 957 52 13 96",
    "sg:postcode":"14940",
    "sg:province":"C\u00f3rdoba",
    "wof:name":"Hnos Granados C.b.",
    "wof:placetype":"venue"
},
  "geometry": {"coordinates":[-4.4284410477,37.4765968323],"type":"Point"}
}