{
  "type": "Feature",
  "properties": {
    "addr:full":"Av Bartomeu Riutort, 14 Can Pastilla Islas Baleares 07610",
    "addr:housenumber":"14",
    "addr:postcode":"07610",
    "addr:street":"Av Bartomeu Riutort",
    "iso:country":"ES",
    "sg:address":"Av Bartomeu Riutort, 14",
    "sg:city":"Can Pastilla",
    "sg:orig_category":"Art\u00cdculos De Regalo (al Por Menor)",
    "sg:phone":"+34 971 26 02 23",
    "sg:postcode":"07610",
    "sg:province":"Islas Baleares",
    "wof:name":"Godoy Montero Maria Concepcion",
    "wof:placetype":"venue"
},
  "geometry": {"coordinates":[2.7170391083,39.5362625122],"type":"Point"}
}