{
  "type": "Feature",
  "properties": {
    "iso:country":"ES",
    "sg:address":"Carrer de Balmes, 223",
    "sg:city":"Barcelona",
    "sg:orig_category":"M\u00c9dicos: Psiquiatr\u00cda",
    "sg:phone":"+34 932 18 71 23",
    "sg:postcode":"08006",
    "sg:province":"Barcelona",
    "wof:name":"Sola Castello Alberto",
    "wof:placetype":"venue"
},
  "geometry": {"coordinates":[2.1507799625,41.3988075256],"type":"Point"}
}