{
  "type": "Feature",
  "properties": {
    "addr:full":"Avda Galdar (de), 74 San Fernando Las Palmas 35100",
    "addr:housenumber":"74",
    "addr:postcode":"35100",
    "addr:street":"Avda Galdar De",
    "iso:country":"ES",
    "sg:address":"Avda Galdar (de), 74",
    "sg:city":"San Fernando",
    "sg:orig_category":"Asociaciones Y Clubs Deportivos",
    "sg:phone":"+34 928 76 94 54",
    "sg:postcode":"35100",
    "sg:province":"Las Palmas",
    "wof:name":"Fernandez Conde Luis",
    "wof:placetype":"venue"
},
  "geometry": {"coordinates":[-15.5842504501,28.0904903412],"type":"Point"}
}