{
  "type": "Feature",
  "properties": {
    "iso:country":"ES",
    "sg:address":"C/ Severo Ochoa, 38",
    "sg:city":"Torrellano",
    "sg:orig_category":"Confecci\u00d3n De Zapatos",
    "sg:phone":"+34 965 68 37 63",
    "sg:postcode":"03320",
    "sg:province":"Alicante",
    "wof:name":"Vulkeli Shoes S. L.",
    "wof:placetype":"venue"
},
  "geometry": {"coordinates":[-0.6116794944,38.2934684753],"type":"Point"}
}