{
  "type": "Feature",
  "properties": {
    "iso:country":"ES",
    "sg:address":"Avda Rafael Cabrera, 12",
    "sg:city":"Palmas De Gran Canaria",
    "sg:orig_category":"M\u00c9dicos: Otorrinolaringolog\u00cda",
    "sg:phone":"+34 928 37 17 32",
    "sg:postcode":"35002",
    "sg:province":"Las Palmas",
    "wof:name":"Acosta Ramirez Manuel Jesus",
    "wof:placetype":"venue"
},
  "geometry": {"coordinates":[-15.4150457382,28.1066684723],"type":"Point"}
}