{
  "type": "Feature",
  "properties": {
    "iso:country":"ES",
    "sg:address":"Cala Blanca, 8",
    "sg:city":"Palmanova",
    "sg:orig_category":"Alimentaci\u00d3n General (al Por Menor)",
    "sg:phone":"+34 971 68 10 10",
    "sg:postcode":"07181",
    "sg:province":"Islas Baleares",
    "wof:name":"Mawasli Tawfik Mahmoud",
    "wof:placetype":"venue"
},
  "geometry": {"coordinates":[2.5657799244,39.5388221741],"type":"Point"}
}