{
  "type": "Feature",
  "properties": {
    "iso:country":"ES",
    "sg:address":"Calle de Jai-alai, 9",
    "sg:city":"Zumarraga",
    "sg:orig_category":"Art\u00cdculos De Decoraci\u00d3n (fabricaci\u00d3n Y Al Por Mayor)",
    "sg:phone":"+34 943 03 79 79",
    "sg:postcode":"20700",
    "sg:province":"Guip\u00f9zcoa",
    "wof:name":"Agurtzane Decoracion S.l.",
    "wof:placetype":"venue"
},
  "geometry": {"coordinates":[-2.3143639565,43.0893783569],"type":"Point"}
}