{
  "type": "Feature",
  "properties": {
    "iso:country":"ES",
    "sg:address":"Calle de Romero, 32",
    "sg:city":"Totana",
    "sg:orig_category":"Reposter\u00cdas",
    "sg:phone":"+34 968 42 05 46",
    "sg:postcode":"30850",
    "sg:province":"Murcia",
    "wof:name":"Gimenez Lorca Miguel",
    "wof:placetype":"venue"
},
  "geometry": {"coordinates":[-1.5057849884,37.7682113647],"type":"Point"}
}