{
  "type": "Feature",
  "properties": {
    "iso:country":"ES",
    "sg:address":"Carrer de Josep Miquel, 8",
    "sg:city":"Sabadell",
    "sg:orig_category":"Mercer\u00cda, Lencer\u00cda (al Por Menor)",
    "sg:phone":"+34 937 10 35 82",
    "sg:postcode":"08204",
    "sg:province":"Barcelona",
    "wof:name":"Balasch Martinez Josep",
    "wof:placetype":"venue"
},
  "geometry": {"coordinates":[2.1212649345,41.5259933472],"type":"Point"}
}