{
  "type": "Feature",
  "properties": {
    "addr:full":"Ctra Lillo (del), S/n Villaca\u00f1as Toledo 45860",
    "addr:postcode":"45860",
    "addr:street":"Ctra Lillo Del S / N Villacan\u0303As",
    "iso:country":"ES",
    "sg:address":"Ctra Lillo (del), S/n",
    "sg:city":"Villaca\u00f1as",
    "sg:orig_category":"Productores Recolectores, Venta Directa De Vinos",
    "sg:phone":"+34 925 16 04 39",
    "sg:postcode":"45860",
    "sg:province":"Toledo",
    "wof:name":"Jose Luis Guillermo Mendieta S.l.",
    "wof:placetype":"venue"
},
  "geometry": {"coordinates":[-3.3362140656,39.6249198914],"type":"Point"}
}