{
  "type": "Feature",
  "properties": {
    "addr:full":"Barr Basadi Auzategia, 15 Zumaia Guip\u00f9zcoa 20750",
    "addr:housenumber":"15",
    "addr:postcode":"20750",
    "addr:street":"Basadi Auzategia;Guipu\u0300Zcoa",
    "iso:country":"ES",
    "sg:address":"Barr Basadi Auzategia, 15",
    "sg:city":"Zumaia",
    "sg:orig_category":"Polideportivos",
    "sg:phone":"+34 943 86 20 21",
    "sg:postcode":"20750",
    "sg:province":"Guip\u00f9zcoa",
    "wof:name":"Kirolzer S.l",
    "wof:placetype":"venue"
},
  "geometry": {"coordinates":[-2.2583589554,43.2942314148],"type":"Point"}
}