{
  "type": "Feature",
  "properties": {
    "addr:full":"Calle de Haya, 1 Madrid Madrid 28044",
    "addr:housenumber":"1",
    "addr:postcode":"28044",
    "addr:street":"Calle De Haya",
    "iso:country":"ES",
    "sg:address":"Calle de Haya, 1",
    "sg:city":"Madrid",
    "sg:orig_category":"Confecci\u00d3n De Trajes Para Se\u00d1oras",
    "sg:phone":"+34 915 08 38 59",
    "sg:postcode":"28044",
    "sg:province":"Madrid",
    "wof:name":"Arteoriente Importacion Exportacion S.l.",
    "wof:placetype":"venue"
},
  "geometry": {"coordinates":[-3.7472276688,40.3684806824],"type":"Point"}
}