{
  "type": "Feature",
  "properties": {
    "iso:country":"ES",
    "sg:address":"Avda Alfonso Vii, 44",
    "sg:city":"Coria",
    "sg:orig_category":"Aguas (distribuci\u00d3n, Servicios)",
    "sg:phone":"+34 927 50 02 11",
    "sg:postcode":"10800",
    "sg:province":"C\u00e1ceres",
    "wof:name":"Comunidad De Regantes Margen Derecha Rio Alagon",
    "wof:placetype":"venue"
},
  "geometry": {"coordinates":[-6.5384459496,39.9941253662],"type":"Point"}
}