{
  "type": "Feature",
  "properties": {
    "iso:country":"ES",
    "sg:address":"Calle de Rio Guadiana, 44",
    "sg:city":"San Vicente Del Raspeig-sant Vicent Del Raspeig",
    "sg:orig_category":"Doctores En Medicina",
    "sg:phone":"+34 965 66 12 99",
    "sg:postcode":"03690",
    "sg:province":"Alicante",
    "wof:name":"Lopez Martinez Enrique",
    "wof:placetype":"venue"
},
  "geometry": {"coordinates":[-0.5036249757,38.3929481506],"type":"Point"}
}