{
  "type": "Feature",
  "properties": {
    "addr:full":"Carrer de Pont, 1 Manlleu Barcelona 08560",
    "addr:housenumber":"1",
    "addr:postcode":"08560",
    "addr:street":"Carrer De Pont",
    "iso:country":"ES",
    "sg:address":"Carrer de Pont, 1",
    "sg:city":"Manlleu",
    "sg:orig_category":"Cajas De Ahorro",
    "sg:phone":"+34 938 51 07 38",
    "sg:postcode":"08560",
    "sg:province":"Barcelona",
    "wof:name":"Caixa D'estalvis De Catalunya",
    "wof:placetype":"venue"
},
  "geometry": {"coordinates":[2.2848479748,42.0005836487],"type":"Point"}
}