{
  "type": "Feature",
  "properties": {
    "iso:country":"ES",
    "sg:address":"Pase Estacion, 6",
    "sg:city":"Pe\u00e7aranda De Bracamonte",
    "sg:orig_category":"Enfermeras: Consultas, Atenci\u00d3n A Domicilio",
    "sg:phone":"+34 923 54 05 40",
    "sg:postcode":"37300",
    "sg:province":"Salamanca",
    "wof:name":"Andres Monsalvo Laureano",
    "wof:placetype":"venue"
},
  "geometry": {"coordinates":[-5.6630473137,40.9649734497],"type":"Point"}
}