{
  "type": "Feature",
  "properties": {
    "addr:full":"Carrer de Coll I Vehi, 87 Barcelona Barcelona 08026",
    "addr:housenumber":"87",
    "addr:postcode":"08026",
    "addr:street":"Carrer De Coll I Vehi",
    "iso:country":"ES",
    "sg:address":"Carrer de Coll I Vehi, 87",
    "sg:city":"Barcelona",
    "sg:orig_category":"Promotores Constructores",
    "sg:phone":"+34 934 55 62 75",
    "sg:postcode":"08026",
    "sg:province":"Barcelona",
    "wof:name":"Pavimientos Y Tratamientos S.l.",
    "wof:placetype":"venue"
},
  "geometry": {"coordinates":[2.1831429005,41.4145698547],"type":"Point"}
}