{
  "type": "Feature",
  "properties": {
    "iso:country":"ES",
    "sg:address":"Calle de Teniente Ruiz, 15",
    "sg:city":"Alcala Henares",
    "sg:orig_category":"Imprenta",
    "sg:phone":"+34 918 88 07 23",
    "sg:postcode":"28805",
    "sg:province":"Madrid",
    "wof:name":"Jadraque Gil Jose",
    "wof:placetype":"venue"
},
  "geometry": {"coordinates":[-3.3599030972,40.4846572876],"type":"Point"}
}