{
  "type": "Feature",
  "properties": {
    "addr:full":"Vgen Dolores, 1 Fuentes De Andalucia Sevilla 41420",
    "addr:housenumber":"1",
    "addr:postcode":"41420",
    "addr:street":"Dolores",
    "iso:country":"ES",
    "sg:address":"Vgen Dolores, 1",
    "sg:city":"Fuentes De Andalucia",
    "sg:orig_category":"Cooperativas Agr\u00cdcolas",
    "sg:phone":"+34 954 83 72 01",
    "sg:postcode":"41420",
    "sg:province":"Sevilla",
    "wof:name":"Cooperativa Del Campo Nuestra Se\u00f1ora Del Rosario",
    "wof:placetype":"venue"
},
  "geometry": {"coordinates":[-5.3430690765,37.4635467529],"type":"Point"}
}