{
  "type": "Feature",
  "properties": {
    "addr:full":"Calle de Carniceros, 20 Valencia Valencia 46001",
    "addr:housenumber":"20",
    "addr:postcode":"46001",
    "addr:street":"Calle De Carniceros",
    "iso:country":"ES",
    "sg:address":"Calle de Carniceros, 20",
    "sg:city":"Valencia",
    "sg:orig_category":"Artes Gr\u00c1ficas, Artes Pl\u00c1sticas (curso)",
    "sg:phone":"+34 963 91 53 07",
    "sg:postcode":"46001",
    "sg:province":"Valencia",
    "wof:name":"Pe\u00f1afort Brusel Vicente",
    "wof:placetype":"venue"
},
  "geometry": {"coordinates":[-0.3833911121,39.4739837646],"type":"Point"}
}