{
  "type": "Feature",
  "properties": {
    "iso:country":"ES",
    "sg:address":"Ctra Iglesuela, 5",
    "sg:city":"Cantavieja",
    "sg:orig_category":"Alquiler De Casas Y Habitaciones Amuebladas",
    "sg:phone":"+34 964 18 50 27",
    "sg:postcode":"44140",
    "sg:province":"Teruel",
    "wof:name":"Escuela Hogar.criet",
    "wof:placetype":"venue"
},
  "geometry": {"coordinates":[-0.405054003,40.5264396667],"type":"Point"}
}