{
  "type": "Feature",
  "properties": {
    "iso:country":"ES",
    "sg:address":"Avda Alf.provisionales, S/n",
    "sg:city":"Playa Del Ingles",
    "sg:orig_category":"Alquiler De Bicicletas Y Motocicletas",
    "sg:phone":"+34 928 77 74 79",
    "sg:postcode":"35100",
    "sg:province":"Las Palmas",
    "wof:name":"Freesports Marketing S.l.",
    "wof:placetype":"venue"
},
  "geometry": {"coordinates":[-15.5756196976,27.759519577],"type":"Point"}
}