{
  "type": "Feature",
  "properties": {
    "iso:country":"ES",
    "sg:address":"Calle de Cruz (la), 46",
    "sg:city":"Coin",
    "sg:orig_category":"Empresas De Carpinter\u00cda De Madera",
    "sg:phone":"+34 952 45 44 31",
    "sg:postcode":"29100",
    "sg:province":"M\u00e1laga",
    "wof:name":"Lome\u00f1a Rodriguez Jose",
    "wof:placetype":"venue"
},
  "geometry": {"coordinates":[-4.7613387108,36.6571311951],"type":"Point"}
}