{
  "type": "Feature",
  "properties": {
    "addr:full":"Calle de Corpus Christi, 37 Adeje Santa Cruz De Tenerife 38670",
    "addr:housenumber":"37",
    "addr:postcode":"38670",
    "addr:street":"Calle De Corpus Christi",
    "iso:country":"ES",
    "sg:address":"Calle de Corpus Christi, 37",
    "sg:city":"Adeje",
    "sg:orig_category":"Herboristas (al Por Menor)",
    "sg:phone":"+34 922 78 13 66",
    "sg:postcode":"38670",
    "sg:province":"Santa Cruz De Tenerife",
    "wof:name":"Galindo Clemente Luis Miguel",
    "wof:placetype":"venue"
},
  "geometry": {"coordinates":[-16.7241096497,28.1211853027],"type":"Point"}
}