{
  "type": "Feature",
  "properties": {
    "iso:country":"ES",
    "sg:address":"Calle de Canillas, 15",
    "sg:city":"Madrid",
    "sg:orig_category":"Cervecer\u00cdas",
    "sg:phone":"+34 915 62 95 33",
    "sg:postcode":"28002",
    "sg:province":"Madrid",
    "wof:name":"Sanz Jimenez Celia",
    "wof:placetype":"venue"
},
  "geometry": {"coordinates":[-3.6764640808,40.4412117004],"type":"Point"}
}