{
  "type": "Feature",
  "properties": {
    "iso:country":"ES",
    "sg:address":"Mcdo Nuevo, S/n",
    "sg:city":"Iru\u00f1a",
    "sg:orig_category":"Frutas Y Legumbres Frescas (al Por Mayor)",
    "sg:phone":"+34 948 23 24 16",
    "sg:postcode":"31004",
    "sg:province":"Navarra",
    "wof:name":"Perez Chavarri Margarita",
    "wof:placetype":"venue"
},
  "geometry": {"coordinates":[-1.6437540054,42.81275177],"type":"Point"}
}