{
  "type": "Feature",
  "properties": {
    "iso:country":"ES",
    "sg:address":"C/ Sant Quinti, 45",
    "sg:city":"Ribes Freser",
    "sg:orig_category":"Cervecer\u00cdas",
    "sg:phone":"+34 972 72 73 00",
    "sg:postcode":"17534",
    "sg:province":"Girona",
    "wof:name":"Garcia Galvez Gonzalo",
    "wof:placetype":"venue"
},
  "geometry": {"coordinates":[2.1667571068,42.3054161072],"type":"Point"}
}