{
  "type": "Feature",
  "properties": {
    "addr:full":"Av Onze De Setembre, 80 Llagosta Barcelona 08120",
    "addr:housenumber":"80",
    "addr:postcode":"08120",
    "addr:street":"Av Onze De Setembre",
    "iso:country":"ES",
    "sg:address":"Av Onze De Setembre, 80",
    "sg:city":"Llagosta",
    "sg:orig_category":"Fabricaci\u00d3n, Instalaci\u00d3n De Armarios",
    "sg:phone":"+34 935 60 75 56",
    "sg:postcode":"08120",
    "sg:province":"Barcelona",
    "wof:name":"Armirall Sociedad Civil",
    "wof:placetype":"venue"
},
  "geometry": {"coordinates":[2.1936745644,41.5146713257],"type":"Point"}
}