{
  "type": "Feature",
  "properties": {
    "addr:full":"Gta Valencia (de), S/n Alca\u00f1iz Teruel 44600",
    "addr:postcode":"44600",
    "addr:street":"Gta;De S / N",
    "iso:country":"ES",
    "sg:address":"Gta Valencia (de), S/n",
    "sg:city":"Alca\u00f1iz",
    "sg:orig_category":"Asilos De Ancianos. Centros Privados",
    "sg:phone":"+34 978 83 07 81",
    "sg:postcode":"44600",
    "sg:province":"Teruel",
    "wof:name":"Instituto Aragones De Servicios Sociales",
    "wof:placetype":"venue"
},
  "geometry": {"coordinates":[-0.1337540001,41.0496292114],"type":"Point"}
}