{
  "type": "Feature",
  "properties": {
    "iso:country":"ES",
    "sg:address":"Carr Major, 26",
    "sg:city":"Torres Segre",
    "sg:orig_category":"Agricultura: Abastecimiento Y Cosechado (negocio)",
    "sg:phone":"+34 973 79 60 98",
    "sg:postcode":"25170",
    "sg:province":"Lleida",
    "wof:name":"Filella Calvo Carlos",
    "wof:placetype":"venue"
},
  "geometry": {"coordinates":[0.5142099857,41.5340461731],"type":"Point"}
}