{
  "type": "Feature",
  "properties": {
    "iso:country":"ES",
    "sg:address":"Calle de Ramon Asensio, 13",
    "sg:city":"Valencia",
    "sg:orig_category":"M\u00c9dicos: Evaluaci\u00d3n Y Tratamiento Del Dolor",
    "sg:phone":"+34 963 60 69 24",
    "sg:postcode":"46020",
    "sg:province":"Valencia",
    "wof:name":"Barelles-garcia Vilar Cb",
    "wof:placetype":"venue"
},
  "geometry": {"coordinates":[-0.358002007,39.4832267761],"type":"Point"}
}