{
  "type": "Feature",
  "properties": {
    "iso:country":"ES",
    "sg:address":"Carrer de Jacint Verdaguer, 12",
    "sg:city":"Vic",
    "sg:orig_category":"Cajas De Ahorro",
    "sg:phone":"+34 938 83 38 20",
    "sg:postcode":"08500",
    "sg:province":"Barcelona",
    "sg:website":"www.caixamanresa.es",
    "wof:name":"Caixa D'estalvis De Manresa",
    "wof:placetype":"venue"
},
  "geometry": {"coordinates":[2.2522239685,41.9306869507],"type":"Point"}
}