{
  "type": "Feature",
  "properties": {
    "addr:full":"Prol. Dominguez Alfonso, S/n Arona Santa Cruz De Tenerife 38640",
    "addr:postcode":"38640",
    "addr:street":"Prol. Dominguez Alfonso S / N",
    "iso:country":"ES",
    "sg:address":"Prol. Dominguez Alfonso, S/n",
    "sg:city":"Arona",
    "sg:orig_category":"Asociaciones Humanitarias, De Cooperaci\u00d3n, De Acci\u00d3n Social",
    "sg:phone":"+34 922 72 55 12",
    "sg:postcode":"38640",
    "sg:province":"Santa Cruz De Tenerife",
    "wof:name":"Asociacion Centro Para El Menor Nuestra Se\u00f1ora Del Rosario",
    "wof:placetype":"venue"
},
  "geometry": {"coordinates":[-16.6813869476,28.0992393494],"type":"Point"}
}