{
  "type": "Feature",
  "properties": {
    "iso:country":"ES",
    "sg:address":"Calle de Zaragoza, 8",
    "sg:city":"Pilar Horadada",
    "sg:orig_category":"Fabricaci\u00d3n De Muebles",
    "sg:phone":"+34 966 76 64 62",
    "sg:postcode":"03190",
    "sg:province":"Alicante",
    "wof:name":"Samper Trivi\u00f1o Maria Gracia",
    "wof:placetype":"venue"
},
  "geometry": {"coordinates":[-0.7887430191,37.864112854],"type":"Point"}
}