{
  "type": "Feature",
  "properties": {
    "addr:full":"Pl. Abeuradors, 6 Muro Islas Baleares 07440",
    "addr:housenumber":"6",
    "addr:postcode":"07440",
    "addr:street":"Pl. Abeuradors",
    "iso:country":"ES",
    "sg:address":"Pl. Abeuradors, 6",
    "sg:city":"Muro",
    "sg:orig_category":"Panader\u00cdas, Panader\u00cdas",
    "sg:phone":"+34 971 53 70 80",
    "sg:postcode":"07440",
    "sg:province":"Islas Baleares",
    "wof:name":"Tugores Segura Juan",
    "wof:placetype":"venue"
},
  "geometry": {"coordinates":[3.0578489304,39.7362747192],"type":"Point"}
}