{
  "type": "Feature",
  "properties": {
    "iso:country":"ES",
    "sg:address":"Pase Juan Xxiii, 5",
    "sg:city":"Madrid",
    "sg:orig_category":"Ense\u00d1anza, Formaci\u00d3n Profesional: Aprendizaje",
    "sg:phone":"+34 915 54 35 16",
    "sg:postcode":"28040",
    "sg:province":"Madrid",
    "wof:name":"Ministerio De Educacion Y Ciencia",
    "wof:placetype":"venue"
},
  "geometry": {"coordinates":[-3.719990015,40.4451599121],"type":"Point"}
}