{
  "type": "Feature",
  "properties": {
    "addr:full":"Calle de Gil Roger, 3 Valencia Valencia 46009",
    "addr:housenumber":"3",
    "addr:postcode":"46009",
    "addr:street":"Calle De Gil Roger",
    "iso:country":"ES",
    "sg:address":"Calle de Gil Roger, 3",
    "sg:city":"Valencia",
    "sg:orig_category":"Electricidad: Instaladores",
    "sg:phone":"+34 963 40 60 69",
    "sg:postcode":"46009",
    "sg:province":"Valencia",
    "wof:name":"Asensio Villalba Francisco",
    "wof:placetype":"venue"
},
  "geometry": {"coordinates":[-0.3904435933,39.4862594604],"type":"Point"}
}