{
  "type": "Feature",
  "properties": {
    "iso:country":"ES",
    "sg:address":"Calle de Alicante, 54",
    "sg:city":"San Vicente Del Raspeig-sant Vicent Del Raspeig",
    "sg:orig_category":"Muebles, Minoristas",
    "sg:phone":"+34 965 66 18 16",
    "sg:postcode":"03690",
    "sg:province":"Alicante",
    "wof:name":"Leste S. A.",
    "wof:placetype":"venue"
},
  "geometry": {"coordinates":[-0.5186859965,38.3934898376],"type":"Point"}
}