{
  "type": "Feature",
  "properties": {
    "iso:country":"ES",
    "sg:address":"Calle de Pancho Cossio, S/n",
    "sg:city":"Torrelavega",
    "sg:orig_category":"Transporte En General",
    "sg:phone":"+34 942 88 12 65",
    "sg:postcode":"39300",
    "sg:province":"Cantabria",
    "wof:name":"Ves S. L.",
    "wof:placetype":"venue"
},
  "geometry": {"coordinates":[-4.0518918037,43.3516616821],"type":"Point"}
}