{
  "type": "Feature",
  "properties": {
    "addr:full":"Plaz Jacobea, 4 Santo Domingo De La Calzada La Rioja 26250",
    "addr:housenumber":"4",
    "addr:postcode":"26250",
    "addr:street":"Plaz Jacobea;Calzada;Rioja",
    "iso:country":"ES",
    "sg:address":"Plaz Jacobea, 4",
    "sg:city":"Santo Domingo De La Calzada",
    "sg:classifiers":[
        {
            "category":"Taxi",
            "type":"Transportation"
        }
    ],
    "sg:phone":"+34 941 34 31 30",
    "sg:postcode":"26250",
    "sg:province":"La Rioja",
    "wof:name":"Moreno Soriano Jose Domingo",
    "wof:placetype":"venue"
},
  "geometry": {"coordinates":[-2.9525289536,42.4388923645],"type":"Point"}
}