{
  "type": "Feature",
  "properties": {
    "iso:country":"ES",
    "sg:address":"Carrer de Anselm Turmeda, 20",
    "sg:city":"Sabadell",
    "sg:orig_category":"Fabricaci\u00d3n De Distribuidores Autom\u00c1ticos",
    "sg:phone":"+34 937 45 65 00",
    "sg:postcode":"08...",
    "sg:province":"Barcelona",
    "wof:name":"Daba S.a.",
    "wof:placetype":"venue"
},
  "geometry": {"coordinates":[2.100413084,41.5287780762],"type":"Point"}
}