{
  "type": "Feature",
  "properties": {
    "addr:full":"Calle de Zaragoza, 6 Tauste Zaragoza 50660",
    "addr:housenumber":"6",
    "addr:postcode":"50660",
    "addr:street":"Calle De Zaragoza",
    "iso:country":"ES",
    "sg:address":"Calle de Zaragoza, 6",
    "sg:city":"Tauste",
    "sg:orig_category":"Inform\u00c1tica, Ofim\u00c1tica (estudios, Asesor\u00cda, Ingenier\u00cda, Formaci\u00d3n)",
    "sg:phone":"+34 976 86 61 70",
    "sg:postcode":"50660",
    "sg:province":"Zaragoza",
    "sg:website":"www.dysicenter.com",
    "wof:name":"Goldnet Informatica S.l.",
    "wof:placetype":"venue"
},
  "geometry": {"coordinates":[-1.2531379461,41.9190254211],"type":"Point"}
}