{
  "type": "Feature",
  "properties": {
    "iso:country":"ES",
    "sg:address":"Avda Conde De Lumiares, 18",
    "sg:city":"Alacant",
    "sg:orig_category":"Hielo Artificial (fabricaci\u00d3n, Distribuci\u00d3n)",
    "sg:phone":"+34 965 25 70 73",
    "sg:postcode":"03010",
    "sg:province":"Alicante",
    "wof:name":"Centrogel Costa Blanca S.l.",
    "wof:placetype":"venue"
},
  "geometry": {"coordinates":[-0.4894230068,38.3593635559],"type":"Point"}
}