{
  "type": "Feature",
  "properties": {
    "addr:full":"Calle de Arzobispo Morcillo, 22 Madrid Madrid 28029",
    "addr:housenumber":"22",
    "addr:postcode":"madrid;28029",
    "addr:street":"Calle De Arzobispo Morcillo",
    "iso:country":"ES",
    "sg:address":"Calle de Arzobispo Morcillo, 22",
    "sg:city":"Madrid",
    "sg:orig_category":"Inform\u00c1tica, Ofim\u00c1tica (estudios, Asesor\u00cda, Ingenier\u00cda, Formaci\u00d3n)",
    "sg:phone":"+34 913 14 28 39",
    "sg:postcode":"28029",
    "sg:province":"Madrid",
    "wof:name":"Alvarez Garcia Carlos",
    "wof:placetype":"venue"
},
  "geometry": {"coordinates":[-3.6970233917,40.4821853638],"type":"Point"}
}