{
  "type": "Feature",
  "properties": {
    "addr:full":"Calle de Conde De Ribadeo, 3 Valladolid Valladolid 47003",
    "addr:housenumber":"3",
    "addr:postcode":"47003",
    "addr:street":"Calle De Conde De Ribadeo",
    "iso:country":"ES",
    "sg:address":"Calle de Conde De Ribadeo, 3",
    "sg:city":"Valladolid",
    "sg:orig_category":"Inmobiliaria (agencias)",
    "sg:phone":"+34 983 25 23 90",
    "sg:postcode":"47003",
    "sg:province":"Valladolid",
    "wof:name":"Construcciones Villa Del Olmo S.a.",
    "wof:placetype":"venue"
},
  "geometry": {"coordinates":[-4.7247095108,41.6554107666],"type":"Point"}
}