{
  "type": "Feature",
  "properties": {
    "addr:full":"Pg Bonanova, 66 Barcelona Barcelona 08017",
    "addr:housenumber":"66",
    "addr:postcode":"08017",
    "addr:street":"Pg Bonanova",
    "iso:country":"ES",
    "sg:address":"Pg Bonanova, 66",
    "sg:city":"Barcelona",
    "sg:orig_category":"Peluquer\u00cdas, Peluquer\u00cda Mixta",
    "sg:phone":"+34 932 03 97 20",
    "sg:postcode":"08017",
    "sg:province":"Barcelona",
    "wof:name":"Temprado Tapias Maria Jose",
    "wof:placetype":"venue"
},
  "geometry": {"coordinates":[2.1263699532,41.4028625488],"type":"Point"}
}