{
  "type": "Feature",
  "properties": {
    "iso:country":"ES",
    "sg:address":"Plaz Luz (de La), 3",
    "sg:city":"Ciempozuelos",
    "sg:orig_category":"Laboratorios Y Trabajos De Fotograf\u00cda, V\u00cddeo Y Cine",
    "sg:phone":"+34 918 93 27 59",
    "sg:postcode":"28350",
    "sg:province":"Madrid",
    "wof:name":"Portillo Piquer Fernando",
    "wof:placetype":"venue"
},
  "geometry": {"coordinates":[-3.6182239056,40.1593360901],"type":"Point"}
}