{
  "type": "Feature",
  "properties": {
    "addr:full":"Bard Pio Xii, S/n Almonte Huelva 21730",
    "addr:housenumber":"s / n",
    "addr:postcode":"21730",
    "addr:street":"Pio Xii",
    "iso:country":"ES",
    "sg:address":"Bard Pio Xii, S/n",
    "sg:city":"Almonte",
    "sg:orig_category":"Chapister\u00cda",
    "sg:phone":"+34 959 40 63 79",
    "sg:postcode":"21730",
    "sg:province":"Huelva",
    "wof:name":"Talleres Ramos S.l.",
    "wof:placetype":"venue"
},
  "geometry": {"coordinates":[-6.5241889954,37.2648086548],"type":"Point"}
}