{
  "type": "Feature",
  "properties": {
    "iso:country":"ES",
    "sg:address":"Calle de Mayor, 73",
    "sg:city":"Castellon",
    "sg:orig_category":"Procuradores",
    "sg:phone":"+34 964 22 33 60",
    "sg:postcode":"12001",
    "sg:province":"Castell\u00f3n",
    "wof:name":"Pesudo Arenos Eva Maria",
    "wof:placetype":"venue"
},
  "geometry": {"coordinates":[-0.0390900001,39.9866714478],"type":"Point"}
}