{
  "type": "Feature",
  "properties": {
    "iso:country":"ES",
    "sg:address":"Ctra Sevilla-malaga, 1",
    "sg:city":"Sevilla",
    "sg:orig_category":"Contenedores (mercanc\u00cdas)",
    "sg:phone":"+34 954 25 40 58",
    "sg:postcode":"41016",
    "sg:province":"Sevilla",
    "wof:name":"Transportes Urbanos De Sevilla",
    "wof:placetype":"venue"
},
  "geometry": {"coordinates":[-6.0018129349,37.3876953125],"type":"Point"}
}