{
  "type": "Feature",
  "properties": {
    "addr:full":"Carrer de Pallars, 224 Barcelona Barcelona 08005",
    "addr:housenumber":"224",
    "addr:postcode":"08005",
    "addr:street":"Carrer De Pallars",
    "iso:country":"ES",
    "sg:address":"Carrer de Pallars, 224",
    "sg:city":"Barcelona",
    "sg:orig_category":"Masajistas Kinesiterapeutas",
    "sg:phone":"+34 933 00 27 07",
    "sg:postcode":"08005",
    "sg:province":"Barcelona",
    "wof:name":"Feliu Hoyer Jaime",
    "wof:placetype":"venue"
},
  "geometry": {"coordinates":[2.1999430656,41.4025993347],"type":"Point"}
}