{
  "type": "Feature",
  "properties": {
    "iso:country":"ES",
    "sg:address":"Calle de Gregorio Mara\u00d1on, 19",
    "sg:city":"Oviedo",
    "sg:orig_category":"Electricidad (montaje, Ensamblaje De Componentes)",
    "sg:phone":"+34 985 23 46 96",
    "sg:postcode":"33012",
    "sg:province":"Asturias",
    "wof:name":"Fernandez Prado Jose Manuel",
    "wof:placetype":"venue"
},
  "geometry": {"coordinates":[-5.8629245758,43.3677597046],"type":"Point"}
}