{
  "type": "Feature",
  "properties": {
    "addr:full":"Av Forja-p I Ca\u00f1ada Fuente, S/n Martos Ja\u00e9n 23600",
    "addr:housenumber":"s / n",
    "addr:postcode":"23600",
    "addr:street":"Av Forja-P;Can\u0303Ada Fuente;Jae\u0301N",
    "iso:country":"ES",
    "sg:address":"Av Forja-p I Ca\u00f1ada Fuente, S/n",
    "sg:city":"Martos",
    "sg:orig_category":"Electromec\u00c1nica",
    "sg:phone":"+34 953 55 51 33",
    "sg:postcode":"23600",
    "sg:province":"Ja\u00e9n",
    "wof:name":"Lara Serrano Rafael Antonio",
    "wof:placetype":"venue"
},
  "geometry": {"coordinates":[-3.971973896,37.7217330933],"type":"Point"}
}