{
  "type": "Feature",
  "properties": {
    "iso:country":"ES",
    "sg:address":"Av Vila De Madrid, 12",
    "sg:city":"Blanes",
    "sg:orig_category":"Frutas, Legumbres Frescas Y Tempranas (al Por Menor)",
    "sg:phone":"+34 972 33 39 08",
    "sg:postcode":"17300",
    "sg:province":"Girona",
    "wof:name":"Sabate Llobet Bartolome",
    "wof:placetype":"venue"
},
  "geometry": {"coordinates":[2.7807741165,41.6608963013],"type":"Point"}
}