{
  "type": "Feature",
  "properties": {
    "addr:full":"Av Meridiana, 574 Barcelona Barcelona 08030",
    "addr:housenumber":"574",
    "addr:postcode":"08030",
    "addr:street":"Meridiana",
    "iso:country":"ES",
    "sg:address":"Av Meridiana, 574",
    "sg:city":"Barcelona",
    "sg:orig_category":"Cl\u00cdnicas Dentales",
    "sg:phone":"+34 932 74 25 14",
    "sg:postcode":"08030",
    "sg:province":"Barcelona",
    "wof:name":"Rodent S.l.",
    "wof:placetype":"venue"
},
  "geometry": {"coordinates":[2.1868081093,41.4423522949],"type":"Point"}
}