{
  "type": "Feature",
  "properties": {
    "iso:country":"ES",
    "sg:address":"Avda Juan Carlos I, 81",
    "sg:city":"Aguilas",
    "sg:orig_category":"Electrodom\u00c9sticos (al Por Menor)",
    "sg:phone":"+34 968 41 00 36",
    "sg:postcode":"30880",
    "sg:province":"Murcia",
    "wof:name":"Gil Adan Antonio",
    "wof:placetype":"venue"
},
  "geometry": {"coordinates":[-1.5835089684,37.407787323],"type":"Point"}
}