{
  "type": "Feature",
  "properties": {
    "iso:country":"ES",
    "sg:address":"Calle de Polvoranca (de), 7",
    "sg:city":"Fuenlabrada",
    "sg:orig_category":"Comercio, Reparaci\u00d3n De Bicicletas, De Motocicletas, De Accesorios",
    "sg:phone":"+34 916 97 77 56",
    "sg:postcode":"28945",
    "sg:province":"Madrid",
    "wof:name":"Cedena Martinez Francisco Javier",
    "wof:placetype":"venue"
},
  "geometry": {"coordinates":[-3.7938671112,40.2868804932],"type":"Point"}
}