{
  "type": "Feature",
  "properties": {
    "addr:full":"Gta San Vicente, S/n San Mateo Murcia 30800",
    "addr:housenumber":"s / n",
    "addr:postcode":"30800",
    "addr:street":"Gta San Vicente",
    "iso:country":"ES",
    "sg:address":"Gta San Vicente, S/n",
    "sg:city":"San Mateo",
    "sg:classifiers":[
        {
            "category":"Taxi",
            "type":"Transportation"
        }
    ],
    "sg:phone":"+34 968 46 60 77",
    "sg:postcode":"30800",
    "sg:province":"Murcia",
    "wof:name":"Moreno Hidalgo Antonio",
    "wof:placetype":"venue"
},
  "geometry": {"coordinates":[-1.6905640364,37.680557251],"type":"Point"}
}