{
  "type": "Feature",
  "properties": {
    "iso:country":"ES",
    "sg:address":"Avda Zamora, S/n",
    "sg:city":"Benidorm",
    "sg:orig_category":"Inmobiliaria (agencias)",
    "sg:phone":"+34 966 83 07 93",
    "sg:postcode":"03500",
    "sg:province":"Alicante",
    "wof:name":"Ben Loix S. A.",
    "wof:placetype":"venue"
},
  "geometry": {"coordinates":[-0.1078720018,38.5403404236],"type":"Point"}
}