{
  "type": "Feature",
  "properties": {
    "iso:country":"ES",
    "sg:address":"Calle de Costa Rica, 68",
    "sg:city":"Fuenlabrada",
    "sg:orig_category":"Serigraf\u00cda (material Y Suministros)",
    "sg:phone":"+34 914 92 14 74",
    "sg:postcode":"28945",
    "sg:province":"Madrid",
    "wof:name":"Garcia Carou Encarnacion",
    "wof:placetype":"venue"
},
  "geometry": {"coordinates":[-3.7831962109,40.2914810181],"type":"Point"}
}