{
  "type": "Feature",
  "properties": {
    "iso:country":"ES",
    "sg:address":"Pase Estacion (de La), 9",
    "sg:city":"Alcala Henares",
    "sg:orig_category":"Expertos Contables",
    "sg:phone":"+34 918 88 92 71",
    "sg:postcode":"28807",
    "sg:province":"Madrid",
    "wof:name":"Asociacion De Economistas S.l.",
    "wof:placetype":"venue"
},
  "geometry": {"coordinates":[-3.3641457558,40.4877319336],"type":"Point"}
}