{
  "type": "Feature",
  "properties": {
    "iso:country":"ES",
    "sg:address":"Calle de Fontanares, 16",
    "sg:city":"Valencia",
    "sg:orig_category":"Caf\u00c9s, Bares, Cervecer\u00cdas",
    "sg:phone":"+34 963 77 00 31",
    "sg:postcode":"46007",
    "sg:province":"Valencia",
    "wof:name":"Tahona De Carmen S.l.",
    "wof:placetype":"venue"
},
  "geometry": {"coordinates":[-0.3911530077,39.4574012756],"type":"Point"}
}