{
  "type": "Feature",
  "properties": {
    "addr:full":"Calle de Pintor Villacis, 4 Catedral Murcia 30003",
    "addr:housenumber":"4",
    "addr:postcode":"30003",
    "addr:street":"Calle De Pintor Villacis",
    "iso:country":"ES",
    "sg:address":"Calle de Pintor Villacis, 4",
    "sg:city":"Catedral",
    "sg:orig_category":"Pod\u00d3logos: Pedicuros",
    "sg:phone":"+34 968 21 18 82",
    "sg:postcode":"30003",
    "sg:province":"Murcia",
    "wof:name":"Iniesta Galvan Jose Maria",
    "wof:placetype":"venue"
},
  "geometry": {"coordinates":[-1.1267180443,37.9835586548],"type":"Point"}
}