{
  "type": "Feature",
  "properties": {
    "iso:country":"ES",
    "sg:address":"Av Sant Ramon Nonat, 8",
    "sg:city":"Barcelona",
    "sg:orig_category":"Agencias De Viajes",
    "sg:phone":"+34 934 49 39 09",
    "sg:postcode":"08028",
    "sg:province":"Barcelona",
    "wof:name":"Exodus Travel S.a.",
    "wof:placetype":"venue"
},
  "geometry": {"coordinates":[2.117317915,41.3763275146],"type":"Point"}
}