{
  "type": "Feature",
  "properties": {
    "addr:full":"Calle de Carlos Martin Alvarez, 10 Madrid Madrid 28018",
    "addr:housenumber":"10",
    "addr:postcode":"madrid;28018",
    "addr:street":"Calle De Carlos Martin Alvarez",
    "iso:country":"ES",
    "sg:address":"Calle de Carlos Martin Alvarez, 10",
    "sg:city":"Madrid",
    "sg:orig_category":"Artes Gr\u00c1ficas, Artes Pl\u00c1sticas (curso)",
    "sg:phone":"+34 913 80 48 62",
    "sg:postcode":"28018",
    "sg:province":"Madrid",
    "sg:website":"www.personal.telefonica.terra.es/bw-eb/fotocomposicion",
    "wof:name":"Joma Fotocomposicion S.l.",
    "wof:placetype":"venue"
},
  "geometry": {"coordinates":[-3.6620225906,40.3911819458],"type":"Point"}
}