{
  "type": "Feature",
  "properties": {
    "addr:full":"Carr Perez Galdos, 66 Badalona Barcelona 08913",
    "addr:housenumber":"66",
    "addr:postcode":"08913",
    "addr:street":"Carr Perez Galdos",
    "iso:country":"ES",
    "sg:address":"Carr Perez Galdos, 66",
    "sg:city":"Badalona",
    "sg:orig_category":"Bazares, Art\u00cdculos De Limpieza Y De Cocina (al Por Menor)",
    "sg:phone":"+34 934 60 34 47",
    "sg:postcode":"08913",
    "sg:province":"Barcelona",
    "wof:name":"Perguets S.l.",
    "wof:placetype":"venue"
},
  "geometry": {"coordinates":[2.2164540291,41.4398231506],"type":"Point"}
}