{
  "type": "Feature",
  "properties": {
    "addr:full":"Avgd Exercit (l'), 39 Betera Valencia 46117",
    "addr:housenumber":"39",
    "addr:postcode":"46117",
    "addr:street":"L '",
    "iso:country":"ES",
    "sg:address":"Avgd Exercit (l'), 39",
    "sg:city":"Betera",
    "sg:orig_category":"Agentes, Concesionarios Y Sucursales De Veh\u00cdculos",
    "sg:phone":"+34 961 69 04 06",
    "sg:postcode":"46117",
    "sg:province":"Valencia",
    "wof:name":"Adenau Motor S.l.",
    "wof:placetype":"venue"
},
  "geometry": {"coordinates":[-0.4580965042,39.5941200256],"type":"Point"}
}