{
  "type": "Feature",
  "properties": {
    "iso:country":"ES",
    "sg:address":"Ctra Argelita, S/n",
    "sg:city":"Ludiente",
    "sg:orig_category":"Suministros Para Carrocer\u00cdas",
    "sg:phone":"+34 964 37 50 75",
    "sg:postcode":"12123",
    "sg:province":"Castell\u00f3n",
    "wof:name":"Abargues Chiva Nomesio",
    "wof:placetype":"venue"
},
  "geometry": {"coordinates":[-0.369774,40.08688],"type":"Point"}
}