{
  "type": "Feature",
  "properties": {
    "addr:full":"Rua Colon, 33 Vigo Pontevedra 36201",
    "addr:housenumber":"33",
    "addr:postcode":"36201",
    "addr:street":"Rua Colon",
    "iso:country":"ES",
    "sg:address":"Rua Colon, 33",
    "sg:city":"Vigo",
    "sg:orig_category":"Notarios",
    "sg:phone":"+34 986 43 67 00",
    "sg:postcode":"36201",
    "sg:province":"Pontevedra",
    "wof:name":"Notaria Colon 33-35 C.b.",
    "wof:placetype":"venue"
},
  "geometry": {"coordinates":[-8.7198896408,42.2364006042],"type":"Point"}
}