{
  "type": "Feature",
  "properties": {
    "iso:country":"ES",
    "sg:address":"Calle de Virgen De Las Canteras, 3",
    "sg:city":"Toledo",
    "sg:orig_category":"Deportes Diversos",
    "sg:phone":"+34 925 21 69 51",
    "sg:postcode":"45006",
    "sg:province":"Toledo",
    "wof:name":"Federacion Castellano Manchega De Judo",
    "wof:placetype":"venue"
},
  "geometry": {"coordinates":[-4.0015058517,39.8582954407],"type":"Point"}
}