{
  "type": "Feature",
  "properties": {
    "addr:full":"Calle de Inmaculada (de La), 25 Mostoles Madrid 28931",
    "addr:housenumber":"25",
    "addr:postcode":"28931",
    "addr:street":"Calle De Inmaculada De La",
    "iso:country":"ES",
    "sg:address":"Calle de Inmaculada (de La), 25",
    "sg:city":"Mostoles",
    "sg:orig_category":"Molduras, Junquillos, Listones Y Molduras Perforadas",
    "sg:phone":"+34 916 14 69 56",
    "sg:postcode":"28931",
    "sg:province":"Madrid",
    "wof:name":"Cerveceria El Colmao S.l.",
    "wof:placetype":"venue"
},
  "geometry": {"coordinates":[-3.8703079224,40.3226356506],"type":"Point"}
}