{
  "type": "Feature",
  "properties": {
    "addr:full":"Avda General Palacio, 8 Getafe Madrid 28902",
    "addr:housenumber":"8",
    "addr:postcode":"28902",
    "addr:street":"Avda General Palacio",
    "iso:country":"ES",
    "sg:address":"Avda General Palacio, 8",
    "sg:city":"Getafe",
    "sg:orig_category":"Perfumer\u00cda (al Por Menor)",
    "sg:phone":"+34 916 65 03 00",
    "sg:postcode":"28902",
    "sg:province":"Madrid",
    "wof:name":"Gil Go S. A.",
    "wof:placetype":"venue"
},
  "geometry": {"coordinates":[-3.7263200283,40.3086509705],"type":"Point"}
}