{
  "type": "Feature",
  "properties": {
    "addr:full":"Carrer de Concepcio, 1 Sabadell Barcelona 08202",
    "addr:housenumber":"1",
    "addr:postcode":"08202",
    "addr:street":"Carrer De Concepcio",
    "iso:country":"ES",
    "sg:address":"Carrer de Concepcio, 1",
    "sg:city":"Sabadell",
    "sg:orig_category":"M\u00c9dicos: Ginecolog\u00cda Y Obstetricia",
    "sg:phone":"+34 937 25 01 55",
    "sg:postcode":"08202",
    "sg:province":"Barcelona",
    "wof:name":"Centre Medic Fuster S.a.",
    "wof:placetype":"venue"
},
  "geometry": {"coordinates":[2.1125690937,41.5484771729],"type":"Point"}
}