{
  "type": "Feature",
  "properties": {
    "iso:country":"ES",
    "sg:address":"La Puja, 3",
    "sg:city":"Nules",
    "sg:orig_category":"Asesor\u00cda De Formaci\u00d3n Y Gesti\u00d3n De Personal",
    "sg:phone":"+34 964 67 48 55",
    "sg:postcode":"12520",
    "sg:province":"Castell\u00f3n",
    "wof:name":"Asesoria Normes S.l.",
    "wof:placetype":"venue"
},
  "geometry": {"coordinates":[-0.158861801,39.8475151062],"type":"Point"}
}