{
  "type": "Feature",
  "properties": {
    "addr:full":"Carrer de Barcelona, 46 Masnou Barcelona 08320",
    "addr:housenumber":"46",
    "addr:postcode":"08320",
    "addr:street":"Carrer De Barcelona",
    "iso:country":"ES",
    "sg:address":"Carrer de Barcelona, 46",
    "sg:city":"Masnou",
    "sg:orig_category":"Asociaciones, Organismos Culturales Y Socioeducativos",
    "sg:phone":"+34 935 55 20 18",
    "sg:postcode":"08320",
    "sg:province":"Barcelona",
    "wof:name":"Sociedad Cultural Nueva Union Masnouense",
    "wof:placetype":"venue"
},
  "geometry": {"coordinates":[2.3162930012,41.4785194397],"type":"Point"}
}