{
  "type": "Feature",
  "properties": {
    "iso:country":"ES",
    "sg:address":"Calle de Vega, 28",
    "sg:city":"Chiclana De La Frontera",
    "sg:orig_category":"Procuradores",
    "sg:phone":"+34 956 53 54 56",
    "sg:postcode":"11130",
    "sg:province":"C\u00e1diz",
    "wof:name":"Berton Belizon Ana",
    "wof:placetype":"venue"
},
  "geometry": {"coordinates":[-6.1490678787,36.4201049805],"type":"Point"}
}