{
  "type": "Feature",
  "properties": {
    "iso:country":"ES",
    "sg:address":"Calle de Onda, 1",
    "sg:city":"Benimamet-beniferri",
    "sg:orig_category":"Asesor\u00cda Fiscal Y Jur\u00cddica",
    "sg:phone":"+34 963 46 32 22",
    "sg:postcode":"46035",
    "sg:province":"Valencia",
    "wof:name":"Viu Pascual. S.l",
    "wof:placetype":"venue"
},
  "geometry": {"coordinates":[-0.4177750051,39.498714447],"type":"Point"}
}