{
  "type": "Feature",
  "properties": {
    "addr:full":"Calle de Orihuela, 13 Torrevieja Alicante 03180",
    "addr:housenumber":"13",
    "addr:postcode":"03180",
    "addr:street":"Calle De Orihuela",
    "iso:country":"ES",
    "sg:address":"Calle de Orihuela, 13",
    "sg:city":"Torrevieja",
    "sg:orig_category":"Estancos",
    "sg:phone":"+34 965 70 36 50",
    "sg:postcode":"03180",
    "sg:province":"Alicante",
    "wof:name":"Perez Sanchez Carolina",
    "wof:placetype":"venue"
},
  "geometry": {"coordinates":[-0.6967399716,38.0022315979],"type":"Point"}
}