{
  "type": "Feature",
  "properties": {
    "iso:country":"ES",
    "sg:address":"Carr Maset, S/n",
    "sg:city":"Silla",
    "sg:orig_category":"Engranajes Y Elementos De Transmisi\u00d3n",
    "sg:phone":"+34 961 20 20 20",
    "sg:postcode":"46460",
    "sg:province":"Valencia",
    "wof:name":"Ernesto Marco Pardo S.a.",
    "wof:placetype":"venue"
},
  "geometry": {"coordinates":[-0.4176610112,39.3742408752],"type":"Point"}
}