{
  "type": "Feature",
  "properties": {
    "iso:country":"ES",
    "sg:address":"Plaz Ortega Y Gasset, 1",
    "sg:city":"Alhama Murcia",
    "sg:orig_category":"Platos Preparados Refrigerados (fabricaci\u00d3n, Al Por Mayor)",
    "sg:phone":"+34 968 63 30 07",
    "sg:postcode":"30840",
    "sg:province":"Murcia",
    "wof:name":"Rodriguez Rodriguez Benita",
    "wof:placetype":"venue"
},
  "geometry": {"coordinates":[-1.4279609919,37.8482170105],"type":"Point"}
}