{
  "type": "Feature",
  "properties": {
    "iso:country":"ES",
    "sg:address":"Calle de Alfonso V, 7",
    "sg:city":"Le\u00f3n",
    "sg:orig_category":"M\u00c9dicos: Ginecolog\u00cda Y Obstetricia",
    "sg:phone":"+34 987 24 68 20",
    "sg:postcode":"24001",
    "sg:province":"Le\u00f3n",
    "wof:name":"Gonzalez Diez Miguel",
    "wof:placetype":"venue"
},
  "geometry": {"coordinates":[-5.5741376877,42.5980148315],"type":"Point"}
}