{
  "type": "Feature",
  "properties": {
    "iso:country":"ES",
    "sg:address":"Av Josep Tarradellas, 13",
    "sg:city":"Terrassa",
    "sg:orig_category":"Zapatos (al Por Menor)",
    "sg:phone":"+34 937 80 40 20",
    "sg:postcode":"08225",
    "sg:province":"Barcelona",
    "wof:name":"Diaz Diaz Dalmacio",
    "wof:placetype":"venue"
},
  "geometry": {"coordinates":[2.0036389828,41.5701675415],"type":"Point"}
}