{
  "type": "Feature",
  "properties": {
    "iso:country":"ES",
    "sg:address":"Carr Mariano Amigo, 31",
    "sg:city":"Pu\u00e7ol",
    "sg:orig_category":"Empresas De Carpinter\u00cda Met\u00c1lica",
    "sg:phone":"+34 961 42 05 79",
    "sg:postcode":"46530",
    "sg:province":"Valencia",
    "wof:name":"Gimeno Corbaton Victor",
    "wof:placetype":"venue"
},
  "geometry": {"coordinates":[-0.3009830117,39.6173591614],"type":"Point"}
}