{
  "type": "Feature",
  "properties": {
    "iso:country":"ES",
    "sg:address":"Carrer de Mallorca, 425",
    "sg:city":"Barcelona",
    "sg:orig_category":"Carnicer\u00cdas, Carnicer\u00cdas",
    "sg:phone":"+34 934 35 74 43",
    "sg:postcode":"08013",
    "sg:province":"Barcelona",
    "wof:name":"Moreno Torne Oscar",
    "wof:placetype":"venue"
},
  "geometry": {"coordinates":[2.1772561073,41.4049797058],"type":"Point"}
}