{
  "type": "Feature",
  "properties": {
    "iso:country":"ES",
    "sg:address":"Carrer de Arimon, 26",
    "sg:city":"Barcelona",
    "sg:orig_category":"Estancos",
    "sg:phone":"+34 934 17 91 44",
    "sg:postcode":"08022",
    "sg:province":"Barcelona",
    "wof:name":"Carrasco Parcerisa Carme",
    "wof:placetype":"venue"
},
  "geometry": {"coordinates":[2.1366679668,41.4042816162],"type":"Point"}
}