{
  "type": "Feature",
  "properties": {
    "iso:country":"ES",
    "sg:address":"Doctor Rovira, 1",
    "sg:city":"Banyoles",
    "sg:orig_category":"Inmobiliaria (agencias)",
    "sg:phone":"+34 972 58 09 46",
    "sg:postcode":"17820",
    "sg:province":"Girona",
    "wof:name":"Palmada Badia Isidre",
    "wof:placetype":"venue"
},
  "geometry": {"coordinates":[2.7644319534,42.1171798706],"type":"Point"}
}