{
  "type": "Feature",
  "properties": {
    "iso:country":"ES",
    "sg:address":"Loiolako Inazio Hiribidea, 25",
    "sg:city":"Azpeitia",
    "sg:orig_category":"Florister\u00cdas",
    "sg:phone":"+34 943 08 05 48",
    "sg:postcode":"20730",
    "sg:province":"Guip\u00f9zcoa",
    "wof:name":"Maria Altuna Gurruchaga",
    "wof:placetype":"venue"
},
  "geometry": {"coordinates":[-2.2699849606,43.1802635193],"type":"Point"}
}