{
  "type": "Feature",
  "properties": {
    "iso:country":"ES",
    "sg:address":"Carr Del Canyeret, 1",
    "sg:city":"Lleida",
    "sg:orig_category":"Centros De Educaci\u00d3n Especial",
    "sg:phone":"+34 973 22 24 27",
    "sg:postcode":"25007",
    "sg:province":"Lleida",
    "wof:name":"Ceip Cervantes Lleida",
    "wof:placetype":"venue"
},
  "geometry": {"coordinates":[0.627129972,41.6145210266],"type":"Point"}
}