{
  "type": "Feature",
  "properties": {
    "iso:country":"ES",
    "sg:address":"Pje. Polvero, S/n",
    "sg:city":"Jun",
    "sg:orig_category":"Construcciones Met\u00c1licas",
    "sg:phone":"+34 958 41 65 24",
    "sg:postcode":"18213",
    "sg:province":"Granada",
    "wof:name":"Gaferjo,cb",
    "wof:placetype":"venue"
},
  "geometry": {"coordinates":[-3.593818903,37.220161438],"type":"Point"}
}