{
  "type": "Feature",
  "properties": {
    "addr:full":"Calle de Marques De Salamanca, S/n Torremolinos M\u00e1laga 29620",
    "addr:housenumber":"s / n",
    "addr:postcode":"29620",
    "addr:street":"Calle De Marques De Salamanca;Ma\u0301Laga",
    "iso:country":"ES",
    "sg:address":"Calle de Marques De Salamanca, S/n",
    "sg:city":"Torremolinos",
    "sg:orig_category":"Arquitectos",
    "sg:phone":"+34 952 05 40 50",
    "sg:postcode":"29620",
    "sg:province":"M\u00e1laga",
    "wof:name":"Gonzalez Jandula Aurora",
    "wof:placetype":"venue"
},
  "geometry": {"coordinates":[-4.4983530045,36.6255378723],"type":"Point"}
}