{
  "type": "Feature",
  "properties": {
    "iso:country":"ES",
    "sg:address":"Ctra Coin, 106",
    "sg:city":"Alhaurin El Grande",
    "sg:orig_category":"Semiller\u00cdas",
    "sg:phone":"+34 952 59 48 36",
    "sg:postcode":"29120",
    "sg:province":"M\u00e1laga",
    "wof:name":"Gonzalez Garcia Juan",
    "wof:placetype":"venue"
},
  "geometry": {"coordinates":[-4.698102951,36.6454238892],"type":"Point"}
}