{
  "type": "Feature",
  "properties": {
    "addr:full":"Carr Puigmal, 20 Blanes Girona 17300",
    "addr:housenumber":"20",
    "addr:postcode":"17300",
    "addr:street":"Carr Puigmal",
    "iso:country":"ES",
    "sg:address":"Carr Puigmal, 20",
    "sg:city":"Blanes",
    "sg:orig_category":"Empresas De Carpinter\u00cda De Madera",
    "sg:phone":"+34 972 33 48 15",
    "sg:postcode":"17300",
    "sg:province":"Girona",
    "wof:name":"Lopez Valero Manuel",
    "wof:placetype":"venue"
},
  "geometry": {"coordinates":[2.7771890163,41.6795043945],"type":"Point"}
}