{
  "type": "Feature",
  "properties": {
    "iso:country":"ES",
    "sg:address":"C. Guetara (p I Villarrosa), 5",
    "sg:city":"Malaga",
    "sg:orig_category":"Mec\u00c1nico Del Autom\u00d3vil",
    "sg:phone":"+34 952 23 88 47",
    "sg:postcode":"29004",
    "sg:province":"M\u00e1laga",
    "wof:name":"Carrocerias Urda Kar Cb",
    "wof:placetype":"venue"
},
  "geometry": {"coordinates":[-4.4747099876,36.6753234863],"type":"Point"}
}