{
  "type": "Feature",
  "properties": {
    "addr:full":"Carrer de Proven\u00c7a, 533 Barcelona Barcelona 08025",
    "addr:housenumber":"533",
    "addr:postcode":"08025",
    "addr:street":"Carrer De Provenc\u0327A",
    "iso:country":"ES",
    "sg:address":"Carrer de Proven\u00c7a, 533",
    "sg:city":"Barcelona",
    "sg:orig_category":"Electricidad, Electr\u00d3nica: Material Y Suministros (al Por Mayor)",
    "sg:phone":"+34 934 46 30 50",
    "sg:postcode":"08025",
    "sg:province":"Barcelona",
    "sg:website":"www.afeisa.es",
    "wof:name":"Afei Sistemas Y Automatizacion S. A.",
    "wof:placetype":"venue"
},
  "geometry": {"coordinates":[2.1796233654,41.4083213806],"type":"Point"}
}