{
  "type": "Feature",
  "properties": {
    "iso:country":"ES",
    "sg:address":"Carrer de Forn, 82",
    "sg:city":"Sabadell",
    "sg:orig_category":"Agencias De Trabajo Temporal",
    "sg:phone":"+34 937 15 58 30",
    "sg:postcode":"08208",
    "sg:province":"Barcelona",
    "wof:name":"United Services Spain Back-office S.l.",
    "wof:placetype":"venue"
},
  "geometry": {"coordinates":[2.1031799316,41.5520706177],"type":"Point"}
}