{
  "type": "Feature",
  "properties": {
    "iso:country":"ES",
    "sg:address":"Calle de Montera, 10",
    "sg:city":"Madrid",
    "sg:orig_category":"Empresas De Carpinter\u00cda De Madera",
    "sg:phone":"+34 915 22 85 87",
    "sg:postcode":"28013",
    "sg:province":"Madrid",
    "wof:name":"Barnizados Y Montajes Villaca\u00f1as Sal",
    "wof:placetype":"venue"
},
  "geometry": {"coordinates":[-3.7026998997,40.4175071716],"type":"Point"}
}