{
  "type": "Feature",
  "properties": {
    "iso:country":"ES",
    "sg:address":"Calle de Morente, 2",
    "sg:city":"Bujalance",
    "sg:orig_category":"Alimentaci\u00d3n General (al Por Menor)",
    "sg:phone":"+34 957 17 05 70",
    "sg:postcode":"14650",
    "sg:province":"C\u00f3rdoba",
    "wof:name":"Lopez Caro Antonia",
    "wof:placetype":"venue"
},
  "geometry": {"coordinates":[-4.3846979141,37.8991127014],"type":"Point"}
}