{
  "type": "Feature",
  "properties": {
    "iso:country":"ES",
    "sg:address":"Santa Catalina, 3",
    "sg:city":"Lucena",
    "sg:orig_category":"Peluqueros: De Se\u00d1oras",
    "sg:phone":"+34 957 50 23 62",
    "sg:postcode":"14900",
    "sg:province":"C\u00f3rdoba",
    "wof:name":"Garcia Huete Mercedes",
    "wof:placetype":"venue"
},
  "geometry": {"coordinates":[-4.4875302315,37.4091682434],"type":"Point"}
}