{
  "type": "Feature",
  "properties": {
    "addr:full":"Calle de Genova, 1 Sevilla Sevilla 41010",
    "addr:housenumber":"1",
    "addr:postcode":"41010",
    "addr:street":"Calle De Genova",
    "iso:country":"ES",
    "sg:address":"Calle de Genova, 1",
    "sg:city":"Sevilla",
    "sg:orig_category":"M\u00c9dicos: Ginecolog\u00cda Y Obstetricia",
    "sg:phone":"+34 954 27 99 47",
    "sg:postcode":"41010",
    "sg:province":"Sevilla",
    "wof:name":"Jimenez Diaz De La Serna Antonio",
    "wof:placetype":"venue"
},
  "geometry": {"coordinates":[-5.9986591339,37.3802757263],"type":"Point"}
}