{
  "type": "Feature",
  "properties": {
    "iso:country":"ES",
    "sg:address":"Calle de San Vicente Martir, 119",
    "sg:city":"Valencia",
    "sg:orig_category":"M\u00c9dicos: Ginecolog\u00cda Y Obstetricia",
    "sg:phone":"+34 963 41 19 59",
    "sg:postcode":"46007",
    "sg:province":"Valencia",
    "wof:name":"Argudo Millan Antonio",
    "wof:placetype":"venue"
},
  "geometry": {"coordinates":[-0.3819228113,39.4637451172],"type":"Point"}
}