{
  "type": "Feature",
  "properties": {
    "addr:full":"Carrer de Josefa Trocha, 20 Molins Rei Barcelona 08750",
    "addr:housenumber":"20",
    "addr:postcode":"08750",
    "addr:street":"Carrer De Josefa Trocha;Barcelona",
    "iso:country":"ES",
    "sg:address":"Carrer de Josefa Trocha, 20",
    "sg:city":"Molins Rei",
    "sg:orig_category":"Centros De Coordinaci\u00d3n",
    "sg:phone":"+34 936 68 54 49",
    "sg:postcode":"08750",
    "sg:province":"Barcelona",
    "wof:name":"Thismiflay S.l.",
    "wof:placetype":"venue"
},
  "geometry": {"coordinates":[2.0164849758,41.414604187],"type":"Point"}
}