{
  "type": "Feature",
  "properties": {
    "addr:full":"Pl Joaquim Folguera, 3 Barcelona Barcelona 08022",
    "addr:housenumber":"3",
    "addr:postcode":"08022",
    "addr:street":"Pl Joaquim Folguera",
    "iso:country":"ES",
    "sg:address":"Pl Joaquim Folguera, 3",
    "sg:city":"Barcelona",
    "sg:orig_category":"Decoradores",
    "sg:phone":"+34 932 12 01 60",
    "sg:postcode":"08022",
    "sg:province":"Barcelona",
    "wof:name":"Travieso Lillo Martin",
    "wof:placetype":"venue"
},
  "geometry": {"coordinates":[2.13905406,41.4052391052],"type":"Point"}
}