{
  "type": "Feature",
  "properties": {
    "addr:full":"Pase Chil, 309 Palmas De Gran Canaria Las Palmas 35010",
    "addr:housenumber":"309",
    "addr:postcode":"35010",
    "iso:country":"ES",
    "sg:address":"Pase Chil, 309",
    "sg:city":"Palmas De Gran Canaria",
    "sg:orig_category":"Arquitectos",
    "sg:phone":"+34 928 22 56 67",
    "sg:postcode":"35010",
    "sg:province":"Las Palmas",
    "wof:name":"Ortiz De Landaluce Perdomo Juan Carlos",
    "wof:placetype":"venue"
},
  "geometry": {"coordinates":[-15.4397087097,28.1302242279],"type":"Point"}
}