{
  "type": "Feature",
  "properties": {
    "addr:full":"Calle de Miguel Juan Pascual, 7 Castellon Castell\u00f3n 12002",
    "addr:housenumber":"7",
    "addr:postcode":"12002",
    "addr:street":"Calle De Miguel Juan Pascual;Castello\u0301N",
    "iso:country":"ES",
    "sg:address":"Calle de Miguel Juan Pascual, 7",
    "sg:city":"Castellon",
    "sg:orig_category":"Carnicer\u00cdas, Carnicer\u00cdas",
    "sg:phone":"+34 964 21 57 70",
    "sg:postcode":"12002",
    "sg:province":"Castell\u00f3n",
    "wof:name":"Gallen Iba\u00f1ez Joaquin",
    "wof:placetype":"venue"
},
  "geometry": {"coordinates":[-0.0417400002,39.9835395813],"type":"Point"}
}