{
  "type": "Feature",
  "properties": {
    "addr:full":"Calle de Jardin, 21 San Fernando De Henares Madrid 28830",
    "addr:housenumber":"21",
    "addr:postcode":"28830",
    "addr:street":"Calle De Jardin",
    "iso:country":"ES",
    "sg:address":"Calle de Jardin, 21",
    "sg:city":"San Fernando De Henares",
    "sg:orig_category":"Molduras, Junquillos, Listones Y Molduras Perforadas",
    "sg:phone":"+34 916 71 00 28",
    "sg:postcode":"28830",
    "sg:province":"Madrid",
    "wof:name":"Prieto Pastor Mariano",
    "wof:placetype":"venue"
},
  "geometry": {"coordinates":[-3.5298559666,40.4254417419],"type":"Point"}
}