{
  "type": "Feature",
  "properties": {
    "iso:country":"ES",
    "sg:address":"Carrer de Rocafort, 143",
    "sg:city":"Barcelona",
    "sg:orig_category":"Institutos De Belleza",
    "sg:phone":"+34 933 25 29 80",
    "sg:postcode":"08015",
    "sg:province":"Barcelona",
    "wof:name":"Montserrate Buj Montserrat",
    "wof:placetype":"venue"
},
  "geometry": {"coordinates":[2.1506619453,41.3810997009],"type":"Point"}
}