{
  "type": "Feature",
  "properties": {
    "addr:full":"Carr Francesc Ciurana, 8 Girona Girona 17002",
    "addr:housenumber":"8",
    "addr:postcode":"17002",
    "addr:street":"Carr Francesc Ciurana",
    "iso:country":"ES",
    "sg:address":"Carr Francesc Ciurana, 8",
    "sg:city":"Girona",
    "sg:orig_category":"Abogados",
    "sg:phone":"+34 972 22 48 33",
    "sg:postcode":"17002",
    "sg:province":"Girona",
    "wof:name":"Delgado Padrosa Jose Miguel",
    "wof:placetype":"venue"
},
  "geometry": {"coordinates":[2.8187320232,41.9773254395],"type":"Point"}
}