{
  "type": "Feature",
  "properties": {
    "iso:country":"ES",
    "sg:address":"Pl Madrid, 11",
    "sg:city":"Palma",
    "sg:orig_category":"Ropa De Hogar (al Por Menor)",
    "sg:phone":"+34 971 73 71 35",
    "sg:postcode":"07011",
    "sg:province":"Islas Baleares",
    "wof:name":"Bellinfante Morante Francisco",
    "wof:placetype":"venue"
},
  "geometry": {"coordinates":[2.6408350468,39.5780067444],"type":"Point"}
}