{
  "type": "Feature",
  "properties": {
    "iso:country":"ES",
    "sg:address":"Calle de Union, 36",
    "sg:city":"Malaga",
    "sg:orig_category":"Inmobiliaria (agencias)",
    "sg:phone":"+34 952 32 61 94",
    "sg:postcode":"29006",
    "sg:province":"M\u00e1laga",
    "wof:name":"Grupo Geliman S.l.",
    "wof:placetype":"venue"
},
  "geometry": {"coordinates":[-4.4386339188,36.7112731934],"type":"Point"}
}