{
  "type": "Feature",
  "properties": {
    "iso:country":"ES",
    "sg:address":"Avda Francia, 0",
    "sg:city":"Sevilla",
    "sg:orig_category":"Centros De Educaci\u00d3n Especial",
    "sg:phone":"+34 954 64 57 40",
    "sg:postcode":"41006",
    "sg:province":"Sevilla",
    "wof:name":"Junta De Andalucia Ies Profesor Pablo De Saz",
    "wof:placetype":"venue"
},
  "geometry": {"coordinates":[-5.9768338203,37.3489265442],"type":"Point"}
}