{
  "type": "Feature",
  "properties": {
    "iso:country":"ES",
    "sg:address":"Calle de Sol, 14",
    "sg:city":"Dolores",
    "sg:orig_category":"Plomeros",
    "sg:phone":"+34 968 51 14 35",
    "sg:postcode":"30310",
    "sg:province":"Murcia",
    "wof:name":"Pujante Soto Mariano",
    "wof:placetype":"venue"
},
  "geometry": {"coordinates":[-1.0017479658,37.638923645],"type":"Point"}
}