{
  "type": "Feature",
  "properties": {
    "addr:full":"Pl. Gral. Franco, S/n Hervas C\u00e1ceres 10700",
    "addr:housenumber":"s / n",
    "addr:postcode":"10700",
    "addr:street":"Gral. Franco;Ca\u0301Ceres",
    "iso:country":"ES",
    "sg:address":"Pl. Gral. Franco, S/n",
    "sg:city":"Hervas",
    "sg:orig_category":"Pescader\u00cdas (al Por Menor)",
    "sg:phone":"+34 927 48 10 53",
    "sg:postcode":"10700",
    "sg:province":"C\u00e1ceres",
    "wof:name":"Gonzalez Martin Manuel",
    "wof:placetype":"venue"
},
  "geometry": {"coordinates":[-5.8459339142,40.2736587524],"type":"Point"}
}