{
  "type": "Feature",
  "properties": {
    "addr:full":"Carrer de Argenteria, 7 Palma Islas Baleares 07001",
    "addr:housenumber":"7",
    "addr:postcode":"07001",
    "addr:street":"Carrer De Argenteria",
    "iso:country":"ES",
    "sg:address":"Carrer de Argenteria, 7",
    "sg:city":"Palma",
    "sg:orig_category":"Compraventa De Antig\u00dcedades",
    "sg:phone":"+34 971 72 69 29",
    "sg:postcode":"07001",
    "sg:province":"Islas Baleares",
    "wof:name":"Jodurosa S.l.",
    "wof:placetype":"venue"
},
  "geometry": {"coordinates":[2.651184082,39.57006073],"type":"Point"}
}