{
  "type": "Feature",
  "properties": {
    "addr:full":"As Cancelas, 1 Riobo Pontevedra 36685",
    "addr:housenumber":"1",
    "addr:postcode":"36685",
    "addr:street":"Cancelas",
    "iso:country":"ES",
    "sg:address":"As Cancelas, 1",
    "sg:city":"Riobo",
    "sg:orig_category":"Comercio, Reparaci\u00d3n De Motocicletas, Bicicletas Y Piezas Sueltas",
    "sg:phone":"+34 986 58 78 42",
    "sg:postcode":"36685",
    "sg:province":"Pontevedra",
    "wof:name":"Hermida Seijas Jose Luis",
    "wof:placetype":"venue"
},
  "geometry": {"coordinates":[-8.4040679932,42.6911468506],"type":"Point"}
}