{
  "type": "Feature",
  "properties": {
    "addr:full":"Avda Brasil (do), S/n Santa Comba La Coru\u00f1a 15840",
    "addr:housenumber":"s / n",
    "addr:postcode":"15840",
    "addr:street":"Avda Brasil;Corun\u0303A",
    "iso:country":"ES",
    "sg:address":"Avda Brasil (do), S/n",
    "sg:city":"Santa Comba",
    "sg:orig_category":"Caf\u00c9s, Bares, Cervecer\u00cdas",
    "sg:phone":"+34 981 88 12 90",
    "sg:postcode":"15840",
    "sg:province":"La Coru\u00f1a",
    "wof:name":"Rego Velo Lucia",
    "wof:placetype":"venue"
},
  "geometry": {"coordinates":[-8.805024147,43.0334434509],"type":"Point"}
}