{
  "type": "Feature",
  "properties": {
    "iso:country":"ES",
    "sg:address":"Calle de Carrequemada, 3",
    "sg:city":"Aranda Duero",
    "sg:orig_category":"Barbacoas Y Accesorios",
    "sg:phone":"+34 947 50 80 43",
    "sg:postcode":"09400",
    "sg:province":"Burgos",
    "wof:name":"Rubio Andres Jose Maria",
    "wof:placetype":"venue"
},
  "geometry": {"coordinates":[-3.6849198341,41.6715431213],"type":"Point"}
}