{
  "type": "Feature",
  "properties": {
    "addr:full":"Carrer de Ter, S/n Gleva Barcelona 08508",
    "addr:housenumber":"s",
    "addr:postcode":"08508",
    "addr:street":"Carrer De Ter;/ N Gleva",
    "iso:country":"ES",
    "sg:address":"Carrer de Ter, S/n",
    "sg:city":"Gleva",
    "sg:orig_category":"Distribuci\u00d3n De Petr\u00d3leo Y Derivados",
    "sg:phone":"+34 938 50 25 31",
    "sg:postcode":"08508",
    "sg:province":"Barcelona",
    "wof:name":"Movil La Gleva S.a.",
    "wof:placetype":"venue"
},
  "geometry": {"coordinates":[2.242579937,42.0044517517],"type":"Point"}
}