{
  "type": "Feature",
  "properties": {
    "iso:country":"ES",
    "sg:address":"Avda Maria Auxiliadora, 16",
    "sg:city":"Rota",
    "sg:orig_category":"Alimentaci\u00d3n General (al Por Menor)",
    "sg:phone":"+34 956 81 29 75",
    "sg:postcode":"11520",
    "sg:province":"C\u00e1diz",
    "wof:name":"Curtido Sanchez Antonio",
    "wof:placetype":"venue"
},
  "geometry": {"coordinates":[-6.361041069,36.6207847595],"type":"Point"}
}