{
  "type": "Feature",
  "properties": {
    "addr:full":"Calle de Prim, General, 13 Melilla Melilla 52004",
    "addr:housenumber":"13",
    "addr:postcode":"52004",
    "addr:street":"Calle De Prim General",
    "iso:country":"ES",
    "sg:address":"Calle de Prim, General, 13",
    "sg:city":"Melilla",
    "sg:orig_category":"Asesor\u00cda Fiscal Y Jur\u00cddica",
    "sg:phone":"+34 952 68 43 29",
    "sg:postcode":"52004",
    "sg:province":"Melilla",
    "wof:name":"Dris Maanan Abbas",
    "wof:placetype":"venue"
},
  "geometry": {"coordinates":[-2.9414598942,35.2887496948],"type":"Point"}
}