{
  "type": "Feature",
  "properties": {
    "iso:country":"ES",
    "sg:address":"Carrer de Arenal, 26",
    "sg:city":"Riudoms",
    "sg:orig_category":"Peluqueros: De Se\u00d1oras",
    "sg:phone":"+34 977 85 04 19",
    "sg:postcode":"43330",
    "sg:province":"Tarragona",
    "wof:name":"Nat Ferre Lina",
    "wof:placetype":"venue"
},
  "geometry": {"coordinates":[1.0523200035,41.1389312744],"type":"Point"}
}