{
  "type": "Feature",
  "properties": {
    "iso:country":"ES",
    "sg:address":"Luga Sabariz, 44",
    "sg:city":"Sabariz",
    "sg:orig_category":"Cr\u00cda De Poller\u00cda Y De Conejos",
    "sg:phone":"+34 988 30 21 97",
    "sg:postcode":"32653",
    "sg:province":"Ourense",
    "wof:name":"Fernandez Perez Olga",
    "wof:placetype":"venue"
},
  "geometry": {"coordinates":[-7.8637681007,42.09948349],"type":"Point"}
}