{
  "type": "Feature",
  "properties": {
    "addr:full":"Calle de Luz (de La), S/n Arevalo \u00c1vila 05200",
    "addr:postcode":"05200",
    "addr:street":"Calle De Luz De La S / N",
    "iso:country":"ES",
    "sg:address":"Calle de Luz (de La), S/n",
    "sg:city":"Arevalo",
    "sg:orig_category":"Pescader\u00cdas (al Por Menor)",
    "sg:phone":"+34 920 30 07 51",
    "sg:postcode":"05200",
    "sg:province":"\u00c1vila",
    "wof:name":"Dominguez Dominguez Felisa",
    "wof:placetype":"venue"
},
  "geometry": {"coordinates":[-4.7189540863,41.0582389832],"type":"Point"}
}