{
  "type": "Feature",
  "properties": {
    "addr:full":"Calle de Lain Calvo, 4 Burgos Burgos 09003",
    "addr:housenumber":"4",
    "addr:postcode":"09003",
    "addr:street":"Calle De Lain Calvo",
    "iso:country":"ES",
    "sg:address":"Calle de Lain Calvo, 4",
    "sg:city":"Burgos",
    "sg:orig_category":"Administradores De Bienes Y Delegados De Comunidades De Propietarios",
    "sg:phone":"+34 947 20 79 71",
    "sg:postcode":"09003",
    "sg:province":"Burgos",
    "wof:name":"New Lc 4 S.l.",
    "wof:placetype":"venue"
},
  "geometry": {"coordinates":[-3.7019050121,42.3418540955],"type":"Point"}
}