{
  "type": "Feature",
  "properties": {
    "iso:country":"ES",
    "sg:address":"Covadonga, 18",
    "sg:city":"Infiesto",
    "sg:orig_category":"\u00d3ptica: Instrumentos (fabricaci\u00d3n)",
    "sg:phone":"+34 985 71 11 88",
    "sg:postcode":"33530",
    "sg:province":"Asturias",
    "wof:name":"Lavandera Llerandi S.l.",
    "wof:placetype":"venue"
},
  "geometry": {"coordinates":[-5.3632831573,43.3476791382],"type":"Point"}
}