{
  "type": "Feature",
  "properties": {
    "iso:country":"ES",
    "sg:address":"Calle de Extension Agraria, S/n",
    "sg:city":"Muniesa",
    "sg:orig_category":"Internados & Ense\u00d1anza Privada",
    "sg:phone":"+34 978 81 05 32",
    "sg:postcode":"44780",
    "sg:province":"Teruel",
    "wof:name":"Aula Publica De Educacion De Personas Adultas",
    "wof:placetype":"venue"
},
  "geometry": {"coordinates":[-0.8116362095,41.0336685181],"type":"Point"}
}