{
  "type": "Feature",
  "properties": {
    "iso:country":"ES",
    "sg:address":"Calle de Ibiza, 1",
    "sg:city":"Madrid",
    "sg:orig_category":"Marketing Directo",
    "sg:phone":"+34 915 04 55 84",
    "sg:postcode":"28009",
    "sg:province":"Madrid",
    "wof:name":"Ibernova S.a.",
    "wof:placetype":"venue"
},
  "geometry": {"coordinates":[-3.678745985,40.4184417725],"type":"Point"}
}