{
  "type": "Feature",
  "properties": {
    "addr:full":"Maestro Jose Velasco, 1 Esparragal Murcia 30163",
    "addr:housenumber":"1",
    "addr:postcode":"30163",
    "addr:street":"Velasco",
    "iso:country":"ES",
    "sg:address":"Maestro Jose Velasco, 1",
    "sg:city":"Esparragal",
    "sg:orig_category":"Reposter\u00cdas",
    "sg:phone":"+34 968 85 02 83",
    "sg:postcode":"30163",
    "sg:province":"Murcia",
    "wof:name":"Carmen Vivancos Gonzalez Y Otro C.b.",
    "wof:placetype":"venue"
},
  "geometry": {"coordinates":[-1.0736939907,38.0533943176],"type":"Point"}
}