{
  "type": "Feature",
  "properties": {
    "addr:full":"Calle de Padre Isla, 9 Cistierna Le\u00f3n 24800",
    "addr:housenumber":"9",
    "addr:postcode":"24800",
    "addr:street":"Calle De Padre Isla;Leo\u0301N",
    "iso:country":"ES",
    "sg:address":"Calle de Padre Isla, 9",
    "sg:city":"Cistierna",
    "sg:orig_category":"Carnicer\u00cdas, Carnicer\u00cdas",
    "sg:phone":"+34 987 70 12 88",
    "sg:postcode":"24800",
    "sg:province":"Le\u00f3n",
    "wof:name":"Moreno Fernandez Alfonso Ramon",
    "wof:placetype":"venue"
},
  "geometry": {"coordinates":[-5.1271481514,42.8036193848],"type":"Point"}
}