{
  "type": "Feature",
  "properties": {
    "iso:country":"ES",
    "sg:address":"Avda. Santos Ruano, 37",
    "sg:city":"Marchena",
    "sg:orig_category":"Empresas De Pintura Y Revestimientos",
    "sg:phone":"+34 954 84 32 85",
    "sg:postcode":"41620",
    "sg:province":"Sevilla",
    "wof:name":"Rueda Martin Jose",
    "wof:placetype":"venue"
},
  "geometry": {"coordinates":[-5.4204659462,37.3324165344],"type":"Point"}
}