{
  "type": "Feature",
  "properties": {
    "iso:country":"ES",
    "sg:address":"Carrer de Capita Arenas, 61",
    "sg:city":"Barcelona",
    "sg:orig_category":"Tapiceros Y Tapiceros",
    "sg:phone":"+34 932 05 80 73",
    "sg:postcode":"08034",
    "sg:province":"Barcelona",
    "wof:name":"Estudio Gv Inter Arq, S.l.",
    "wof:placetype":"venue"
},
  "geometry": {"coordinates":[2.1244471073,41.3940505981],"type":"Point"}
}