{
  "type": "Feature",
  "properties": {
    "iso:country":"ES",
    "sg:address":"Cami Afores, S/n",
    "sg:city":"Torres Segre",
    "sg:orig_category":"Explosivos",
    "sg:phone":"+34 973 79 74 74",
    "sg:postcode":"25170",
    "sg:province":"Lleida",
    "wof:name":"Maxamcorp S.a.u.",
    "wof:placetype":"venue"
},
  "geometry": {"coordinates":[0.5142099857,41.5340461731],"type":"Point"}
}