{
  "type": "Feature",
  "properties": {
    "iso:country":"ES",
    "sg:address":"Avda Jorge Vigon, 4",
    "sg:city":"Logro\u00f1o",
    "sg:orig_category":"Ropa Para Ni\u00d1os (al Por Menor)",
    "sg:phone":"+34 941 23 62 31",
    "sg:postcode":"26003",
    "sg:province":"La Rioja",
    "wof:name":"Mayoral Perez Jesus Roberto",
    "wof:placetype":"venue"
},
  "geometry": {"coordinates":[-2.4448127747,42.46276474],"type":"Point"}
}