{
  "type": "Feature",
  "properties": {
    "iso:country":"ES",
    "sg:address":"Pl Josep Maluquer I Salvador, 11",
    "sg:city":"Granollers",
    "sg:orig_category":"Farmacias",
    "sg:phone":"+34 938 79 40 29",
    "sg:postcode":"08401",
    "sg:province":"Barcelona",
    "wof:name":"Arimany Barcelo Marina",
    "wof:placetype":"venue"
},
  "geometry": {"coordinates":[2.2802755833,41.5911216736],"type":"Point"}
}