{
  "type": "Feature",
  "properties": {
    "addr:full":"Calle de Engredal, 51 Saelices Cuenca 16430",
    "addr:housenumber":"51",
    "addr:postcode":"16430",
    "addr:street":"Calle De Engredal",
    "iso:country":"ES",
    "sg:address":"Calle de Engredal, 51",
    "sg:city":"Saelices",
    "sg:orig_category":"Fabricaci\u00d3n De Quesos",
    "sg:phone":"+34 969 13 21 17",
    "sg:postcode":"16430",
    "sg:province":"Cuenca",
    "wof:name":"Chaves Fernandez Emerito",
    "wof:placetype":"venue"
},
  "geometry": {"coordinates":[-2.806732893,39.9214324951],"type":"Point"}
}