{
  "type": "Feature",
  "properties": {
    "addr:full":"Calle de Hermanos Gonzalez Blanco, 8 Luanco Asturias 33440",
    "addr:housenumber":"8",
    "addr:postcode":"33440",
    "addr:street":"Calle De Hermanos Gonzalez Blanco;Luanco Asturias",
    "iso:country":"ES",
    "sg:address":"Calle de Hermanos Gonzalez Blanco, 8",
    "sg:city":"Luanco",
    "sg:orig_category":"Zapatos (al Por Menor)",
    "sg:phone":"+34 985 88 18 55",
    "sg:postcode":"33440",
    "sg:province":"Asturias",
    "wof:name":"Garcia Gutierrez Maria De Los Dolores",
    "wof:placetype":"venue"
},
  "geometry": {"coordinates":[-5.7922801971,43.6164207458],"type":"Point"}
}