{
  "type": "Feature",
  "properties": {
    "addr:full":"Ctra. Talavera, S/n Alcaudete De La Jara Toledo 45662",
    "addr:housenumber":"s / n",
    "addr:postcode":"45662",
    "addr:street":"Ctra. Talavera",
    "iso:country":"ES",
    "sg:address":"Ctra. Talavera, S/n",
    "sg:city":"Alcaudete De La Jara",
    "sg:orig_category":"Producci\u00d3n, Venta De Productos De Agricultura Biol\u00d3gica",
    "sg:phone":"+34 925 85 33 86",
    "sg:postcode":"45662",
    "sg:province":"Toledo",
    "wof:name":"Florpin S.l.",
    "wof:placetype":"venue"
},
  "geometry": {"coordinates":[-4.86977005,39.7909088135],"type":"Point"}
}