{
  "type": "Feature",
  "properties": {
    "iso:country":"ES",
    "sg:address":"Calle de Rafael Alberti, 1",
    "sg:city":"San Pedro Alcantara",
    "sg:orig_category":"Procuradores",
    "sg:phone":"+34 952 92 77 07",
    "sg:postcode":"29670",
    "sg:province":"M\u00e1laga",
    "wof:name":"Bonet Texeira Javier",
    "wof:placetype":"venue"
},
  "geometry": {"coordinates":[-4.9922437668,36.4831466675],"type":"Point"}
}