{
  "type": "Feature",
  "properties": {
    "addr:full":"Calle de Comandante Zorita, 49 Madrid Madrid 28020",
    "addr:housenumber":"49",
    "addr:postcode":"madrid;28020",
    "addr:street":"Calle De Comandante Zorita",
    "iso:country":"ES",
    "sg:address":"Calle de Comandante Zorita, 49",
    "sg:city":"Madrid",
    "sg:orig_category":"Art\u00cdculos De Regalo (al Por Menor)",
    "sg:phone":"+34 915 54 18 89",
    "sg:postcode":"28020",
    "sg:province":"Madrid",
    "wof:name":"Comercial Isben S. A.",
    "wof:placetype":"venue"
},
  "geometry": {"coordinates":[-3.6983425617,40.4515151978],"type":"Point"}
}