{
  "type": "Feature",
  "properties": {
    "iso:country":"ES",
    "sg:address":"Rua Peregrina (da), 16",
    "sg:city":"Pontevedra",
    "sg:orig_category":"Zapatos (al Por Menor)",
    "sg:phone":"+34 986 85 43 85",
    "sg:postcode":"36001",
    "sg:province":"Pontevedra",
    "wof:name":"Paredes Cereijo Francisco",
    "wof:placetype":"venue"
},
  "geometry": {"coordinates":[-8.643740654,42.4301338196],"type":"Point"}
}