{
  "type": "Feature",
  "properties": {
    "iso:country":"ES",
    "sg:address":"Calle de Convento Santa Clara, 1",
    "sg:city":"Valencia",
    "sg:orig_category":"Pod\u00d3logos: Pedicuros",
    "sg:phone":"+34 963 94 10 67",
    "sg:postcode":"46002",
    "sg:province":"Valencia",
    "wof:name":"Rodrigalvarez Espi Jose Miguel",
    "wof:placetype":"venue"
},
  "geometry": {"coordinates":[-0.3753474951,39.4682922363],"type":"Point"}
}