{
  "type": "Feature",
  "properties": {
    "addr:full":"Calle de Celestino Cabeza, 23 Langreo Asturias 33900",
    "addr:housenumber":"23",
    "addr:postcode":"33900",
    "addr:street":"Calle De Celestino Cabeza",
    "iso:country":"ES",
    "sg:address":"Calle de Celestino Cabeza, 23",
    "sg:city":"Langreo",
    "sg:orig_category":"Peluquer\u00cdas, Peluquer\u00cda Mixta",
    "sg:phone":"+34 985 69 17 96",
    "sg:postcode":"33900",
    "sg:province":"Asturias",
    "wof:name":"Narseo Vallina S.l.",
    "wof:placetype":"venue"
},
  "geometry": {"coordinates":[-5.6938881874,43.3096084595],"type":"Point"}
}