{
  "type": "Feature",
  "properties": {
    "addr:full":"Rbla Poblenou, 88 Barcelona Barcelona 08005",
    "addr:housenumber":"88",
    "addr:postcode":"08005",
    "addr:street":"Rbla Poblenou",
    "iso:country":"ES",
    "sg:address":"Rbla Poblenou, 88",
    "sg:city":"Barcelona",
    "sg:orig_category":"Bisuter\u00cda, Joyer\u00cda, Relojer\u00cda (al Por Menor)",
    "sg:phone":"+34 933 00 07 99",
    "sg:postcode":"08005",
    "sg:province":"Barcelona",
    "wof:name":"Kronosur S.l.",
    "wof:placetype":"venue"
},
  "geometry": {"coordinates":[2.2003700733,41.4019317627],"type":"Point"}
}