{
  "type": "Feature",
  "properties": {
    "iso:country":"ES",
    "sg:address":"Pg Urrutia, 121",
    "sg:city":"Barcelona",
    "sg:orig_category":"Alquiler De V\u00cddeo",
    "sg:phone":"+34 933 53 23 00",
    "sg:postcode":"08042",
    "sg:province":"Barcelona",
    "wof:name":"Video Club Libra S. A.",
    "wof:placetype":"venue"
},
  "geometry": {"coordinates":[2.1712379456,41.4350090027],"type":"Point"}
}