{
  "type": "Feature",
  "properties": {
    "addr:full":"Calle de Bravo Murillo, 93 Madrid Madrid 28003",
    "addr:housenumber":"93",
    "addr:postcode":"madrid;28003",
    "addr:street":"Calle De Bravo Murillo",
    "iso:country":"ES",
    "sg:address":"Calle de Bravo Murillo, 93",
    "sg:city":"Madrid",
    "sg:orig_category":"Iglesia Cat\u00d3lica",
    "sg:phone":"+34 915 54 62 36",
    "sg:postcode":"28003",
    "sg:province":"Madrid",
    "wof:name":"Parroquia Personal De Sordomudos Santa Maria Del Silencio Madrid",
    "wof:placetype":"venue"
},
  "geometry": {"coordinates":[-3.7040140629,40.4459953308],"type":"Point"}
}