{
  "type": "Feature",
  "properties": {
    "addr:full":"Plaz Constitucion, 16 Fuengirola M\u00e1laga 29640",
    "addr:housenumber":"16",
    "addr:postcode":"29640",
    "addr:street":"Constitucion;Ma\u0301Laga",
    "iso:country":"ES",
    "sg:address":"Plaz Constitucion, 16",
    "sg:city":"Fuengirola",
    "sg:orig_category":"Bisuter\u00cda, Joyer\u00cda, Relojer\u00cda (al Por Menor)",
    "sg:phone":"+34 952 19 93 22",
    "sg:postcode":"29640",
    "sg:province":"M\u00e1laga",
    "wof:name":"Romero Acevedo Concepcion",
    "wof:placetype":"venue"
},
  "geometry": {"coordinates":[-4.6232252121,36.5388298035],"type":"Point"}
}