{
  "type": "Feature",
  "properties": {
    "addr:full":"Calle de Prim, 29 Donostia-san Sebastian Guip\u00f9zcoa 20006",
    "addr:housenumber":"29",
    "addr:postcode":"20006",
    "addr:street":"Calle De Prim",
    "iso:country":"ES",
    "sg:address":"Calle de Prim, 29",
    "sg:city":"Donostia-san Sebastian",
    "sg:orig_category":"Ense\u00d1anza: Idiomas",
    "sg:phone":"+34 943 45 02 76",
    "sg:postcode":"20006",
    "sg:province":"Guip\u00f9zcoa",
    "wof:name":"Azpiroz Villar Carmen",
    "wof:placetype":"venue"
},
  "geometry": {"coordinates":[-1.9798439741,43.3158874512],"type":"Point"}
}