{
  "type": "Feature",
  "properties": {
    "iso:country":"ES",
    "sg:address":"Calle de San Juan De La Pe\u00d1a, 178",
    "sg:city":"San Gregorio",
    "sg:orig_category":"Lavado, Limpieza De Veh\u00cdculos",
    "sg:phone":"+34 976 73 02 33",
    "sg:postcode":"50015",
    "sg:province":"Zaragoza",
    "wof:name":"Imo Autolavados S.a.",
    "wof:placetype":"venue"
},
  "geometry": {"coordinates":[-0.8709290028,41.6748924255],"type":"Point"}
}