{
  "type": "Feature",
  "properties": {
    "iso:country":"ES",
    "sg:address":"Calle de Mayor, 12",
    "sg:city":"Fuentes Ebro",
    "sg:classifiers":[
        {
            "category":"Autos & Motor Vehicles",
            "subcategory":"Automobile Sales",
            "type":"Retail Goods"
        }
    ],
    "sg:phone":"+34 976 16 05 27",
    "sg:postcode":"50740",
    "sg:province":"Zaragoza",
    "wof:name":"Autoescuela Europa-oroel S.l.",
    "wof:placetype":"venue"
},
  "geometry": {"coordinates":[-0.6295521259,41.5120620728],"type":"Point"}
}