{
  "type": "Feature",
  "properties": {
    "addr:full":"Calle de Misericordia, 22 Puerto De Santa Maria C\u00e1diz 11500",
    "addr:housenumber":"22",
    "addr:postcode":"11500",
    "addr:street":"Calle De Misericordia;Ca\u0301Diz",
    "iso:country":"ES",
    "sg:address":"Calle de Misericordia, 22",
    "sg:city":"Puerto De Santa Maria",
    "sg:orig_category":"M\u00c9dicos: An\u00c1lisis Cl\u00cdnicos",
    "sg:phone":"+34 956 85 98 58",
    "sg:postcode":"11500",
    "sg:province":"C\u00e1diz",
    "wof:name":"Almorza Salas Angel",
    "wof:placetype":"venue"
},
  "geometry": {"coordinates":[-6.2261095047,36.5974121094],"type":"Point"}
}