{
  "type": "Feature",
  "properties": {
    "iso:country":"ES",
    "sg:address":"Calle de Ramon Y Cajal, 15",
    "sg:city":"Teruel",
    "sg:orig_category":"Ropa Para Ni\u00d1os (al Por Menor)",
    "sg:phone":"+34 978 61 08 65",
    "sg:postcode":"44001",
    "sg:province":"Teruel",
    "wof:name":"Ana Isabel Martin S.l.",
    "wof:placetype":"venue"
},
  "geometry": {"coordinates":[-1.1072009802,40.342010498],"type":"Point"}
}