{
  "type": "Feature",
  "properties": {
    "addr:full":"Carrer de Calaf, 44 Barcelona Barcelona 08021",
    "addr:housenumber":"44",
    "addr:postcode":"08021",
    "addr:street":"Carrer De Calaf",
    "iso:country":"ES",
    "sg:address":"Carrer de Calaf, 44",
    "sg:city":"Barcelona",
    "sg:orig_category":"Agencias De Viajes",
    "sg:phone":"+34 932 41 16 91",
    "sg:postcode":"08021",
    "sg:province":"Barcelona",
    "sg:website":"www.viajeseroski.es",
    "wof:name":"Viajes Eroski S.a.",
    "wof:placetype":"venue"
},
  "geometry": {"coordinates":[2.1426460743,41.396522522],"type":"Point"}
}