{
  "type": "Feature",
  "properties": {
    "addr:full":"Calle de Padres Redentoristas, 1 Astorga Le\u00f3n 24700",
    "addr:housenumber":"1",
    "addr:postcode":"24700",
    "addr:street":"Calle De Padres Redentoristas;Leo\u0301N",
    "iso:country":"ES",
    "sg:address":"Calle de Padres Redentoristas, 1",
    "sg:city":"Astorga",
    "sg:orig_category":"Relojer\u00cda (al Por Menor, Reparaci\u00d3n)",
    "sg:phone":"+34 987 61 67 59",
    "sg:postcode":"24700",
    "sg:province":"Le\u00f3n",
    "wof:name":"Diguele Gonzalez Ramon",
    "wof:placetype":"venue"
},
  "geometry": {"coordinates":[-6.0520138741,42.4536590576],"type":"Point"}
}