{
  "type": "Feature",
  "properties": {
    "addr:full":"Calle de Santiago, S/n Villafranca Bierzo Le\u00f3n 24500",
    "addr:housenumber":"s / n",
    "addr:postcode":"24500",
    "addr:street":"Calle De Santiago",
    "iso:country":"ES",
    "sg:address":"Calle de Santiago, S/n",
    "sg:city":"Villafranca Bierzo",
    "sg:orig_category":"Empresas De Carpinter\u00cda De Madera",
    "sg:phone":"+34 987 54 03 82",
    "sg:postcode":"24500",
    "sg:province":"Le\u00f3n",
    "wof:name":"Alfonso Garcia Delfin",
    "wof:placetype":"venue"
},
  "geometry": {"coordinates":[-6.8084406853,42.6041526794],"type":"Point"}
}