{
  "type": "Feature",
  "properties": {
    "iso:country":"ES",
    "sg:address":"Santa Eulalia, S/n",
    "sg:city":"Santa Eulalia",
    "sg:orig_category":"Alimentaci\u00d3n General (al Por Mayor)",
    "sg:phone":"+34 985 88 78 41",
    "sg:postcode":"33438",
    "sg:province":"Asturias",
    "wof:name":"Valentin Gonzalez Y Otro C.b.",
    "wof:placetype":"venue"
},
  "geometry": {"coordinates":[-5.8532137871,43.552028656],"type":"Point"}
}