{
  "type": "Feature",
  "properties": {
    "addr:full":"Calle de Escoplillo, 36 Daimiel Ciudad Real 13250",
    "addr:housenumber":"36",
    "addr:postcode":"13250",
    "addr:street":"Calle De Escoplillo",
    "iso:country":"ES",
    "sg:address":"Calle de Escoplillo, 36",
    "sg:city":"Daimiel",
    "sg:orig_category":"Mec\u00c1nico Del Autom\u00d3vil",
    "sg:phone":"+34 926 85 41 80",
    "sg:postcode":"13250",
    "sg:province":"Ciudad Real",
    "wof:name":"Garcia-mu\u00f1oz Sanchez-valdepe\u00f1as Manuel",
    "wof:placetype":"venue"
},
  "geometry": {"coordinates":[-3.6181681156,39.0742835999],"type":"Point"}
}