{
  "type": "Feature",
  "properties": {
    "addr:full":"Calle de Doctor Martinez Bordiu, S/n Jaen Ja\u00e9n 23006",
    "addr:housenumber":"s / n;jae\u0301n",
    "addr:postcode":"23006",
    "addr:street":"Calle De Doctor Martinez Bordiu",
    "iso:country":"ES",
    "sg:address":"Calle de Doctor Martinez Bordiu, S/n",
    "sg:city":"Jaen",
    "sg:orig_category":"Estancos",
    "sg:phone":"+34 953 22 03 13",
    "sg:postcode":"23006",
    "sg:province":"Ja\u00e9n",
    "wof:name":"Duro Duro Concepcion",
    "wof:placetype":"venue"
},
  "geometry": {"coordinates":[-3.7994940281,37.7803268433],"type":"Point"}
}