{
  "type": "Feature",
  "properties": {
    "addr:full":"Calle de General Sanz Pastor, 6 Burgos Burgos 09003",
    "addr:housenumber":"6",
    "addr:postcode":"09003",
    "addr:street":"Calle De General Sanz Pastor",
    "iso:country":"ES",
    "sg:address":"Calle de General Sanz Pastor, 6",
    "sg:city":"Burgos",
    "sg:orig_category":"Venta, Colocaci\u00d3n De Moquetas, Revestimiento De Suelos Y De Paredes",
    "sg:phone":"+34 947 27 49 18",
    "sg:postcode":"09003",
    "sg:province":"Burgos",
    "wof:name":"Leal Garcia Luis",
    "wof:placetype":"venue"
},
  "geometry": {"coordinates":[-3.6988840103,42.344707489],"type":"Point"}
}