{
  "type": "Feature",
  "properties": {
    "iso:country":"ES",
    "sg:address":"Calle de Cirilo Amoros, 59",
    "sg:city":"Valencia",
    "sg:orig_category":"Metalurgia: Maquinaria Y Equipos",
    "sg:phone":"+34 963 51 32 64",
    "sg:postcode":"46004",
    "sg:province":"Valencia",
    "wof:name":"Font Vazquez Enrique",
    "wof:placetype":"venue"
},
  "geometry": {"coordinates":[-0.3689596057,39.4683990479],"type":"Point"}
}