{
  "type": "Feature",
  "properties": {
    "addr:full":"Av Matadepera, 167 Sabadell Barcelona 08207",
    "addr:housenumber":"167",
    "addr:postcode":"08207",
    "addr:street":"Av Matadepera",
    "iso:country":"ES",
    "sg:address":"Av Matadepera, 167",
    "sg:city":"Sabadell",
    "sg:orig_category":"Carnicer\u00cdas, Carnicer\u00cdas",
    "sg:phone":"+34 937 17 77 04",
    "sg:postcode":"08207",
    "sg:province":"Barcelona",
    "wof:name":"Jose Gracia Monzon E Hijos S.l.",
    "wof:placetype":"venue"
},
  "geometry": {"coordinates":[2.0866599083,41.5684318542],"type":"Point"}
}