{
  "type": "Feature",
  "properties": {
    "iso:country":"ES",
    "sg:address":"Carrer de Sant Roc, 2",
    "sg:city":"Crevillent",
    "sg:orig_category":"Farmacias",
    "sg:phone":"+34 965 40 18 37",
    "sg:postcode":"03330",
    "sg:province":"Alicante",
    "wof:name":"Oliver Candela Maria Del Carmen",
    "wof:placetype":"venue"
},
  "geometry": {"coordinates":[-0.8093159795,38.2484092712],"type":"Point"}
}