{
  "type": "Feature",
  "properties": {
    "addr:full":"Barrio Prellezo, 2 Prellezo Cantabria 39548",
    "addr:housenumber":"2",
    "addr:postcode":"39548",
    "addr:street":"Barrio Prellezo",
    "iso:country":"ES",
    "sg:address":"Barrio Prellezo, 2",
    "sg:city":"Prellezo",
    "sg:orig_category":"Servicios De Telecomunicaciones",
    "sg:phone":"+34 942 71 23 26",
    "sg:postcode":"39548",
    "sg:province":"Cantabria",
    "wof:name":"Erictel S.l.",
    "wof:placetype":"venue"
},
  "geometry": {"coordinates":[-4.4482369423,43.3865699768],"type":"Point"}
}