{
  "type": "Feature",
  "properties": {
    "iso:country":"ES",
    "sg:address":"Calle de Libertad (de La), 7",
    "sg:city":"Navalcarnero",
    "sg:orig_category":"Reposter\u00cdas",
    "sg:phone":"+34 918 11 03 19",
    "sg:postcode":"28600",
    "sg:province":"Madrid",
    "wof:name":"Barrio Tarami Modesto Del",
    "wof:placetype":"venue"
},
  "geometry": {"coordinates":[-4.0136008263,40.2880477905],"type":"Point"}
}