{
  "type": "Feature",
  "properties": {
    "addr:full":"Calle de Canovas Del Castillo, 6 Cadiz C\u00e1diz 11001",
    "addr:housenumber":"6",
    "addr:postcode":"11001",
    "addr:street":"Calle De Canovas Del Castillo",
    "iso:country":"ES",
    "sg:address":"Calle de Canovas Del Castillo, 6",
    "sg:city":"Cadiz",
    "sg:classifiers":[
        {
            "category":"Personal",
            "subcategory":"Barber",
            "type":"Services"
        }
    ],
    "sg:phone":"+34 956 21 12 12",
    "sg:postcode":"11001",
    "sg:province":"C\u00e1diz",
    "sg:tags":[
        "caballeros",
        "de",
        "peluqueros"
    ],
    "wof:name":"Delgado Bravo Manuel",
    "wof:placetype":"venue"
},
  "geometry": {"coordinates":[-6.297729969,36.5346717834],"type":"Point"}
}