{
  "type": "Feature",
  "properties": {
    "addr:full":"Calle de Andalucia, 74 Palencia Palencia 34004",
    "addr:housenumber":"74",
    "addr:postcode":"34004",
    "addr:street":"Calle De Andalucia",
    "iso:country":"ES",
    "sg:address":"Calle de Andalucia, 74",
    "sg:city":"Palencia",
    "sg:orig_category":"Material Y Herramientas Agr\u00cdcolas",
    "sg:phone":"+34 979 71 38 26",
    "sg:postcode":"34004",
    "sg:province":"Palencia",
    "wof:name":"Instalaciones De Riego Y Maquinaria Agricola Agrima S.l.",
    "wof:placetype":"venue"
},
  "geometry": {"coordinates":[-4.5117969513,41.9997940063],"type":"Point"}
}