{
  "type": "Feature",
  "properties": {
    "addr:full":"Carrer de Escudellers, 5 Barcelona Barcelona 08002",
    "addr:housenumber":"5",
    "addr:postcode":"08002",
    "addr:street":"Carrer De Escudellers",
    "iso:country":"ES",
    "sg:address":"Carrer de Escudellers, 5",
    "sg:city":"Barcelona",
    "sg:orig_category":"Molduras, Junquillos, Listones Y Molduras Perforadas",
    "sg:phone":"+34 933 18 87 30",
    "sg:postcode":"08002",
    "sg:province":"Barcelona",
    "wof:name":"Ferrer Sanvicente Bienvenido",
    "wof:placetype":"venue"
},
  "geometry": {"coordinates":[2.1757109165,41.3791427612],"type":"Point"}
}