{
  "type": "Feature",
  "properties": {
    "iso:country":"ES",
    "sg:address":"C/ Pedreres, 5",
    "sg:city":"Banyoles",
    "sg:orig_category":"Cr\u00cda De Animales",
    "sg:phone":"+34 972 58 02 57",
    "sg:postcode":"17820",
    "sg:province":"Girona",
    "wof:name":"Oliver Carles Josep Maria",
    "wof:placetype":"venue"
},
  "geometry": {"coordinates":[2.7598619461,42.1175994873],"type":"Point"}
}