{
  "type": "Feature",
  "properties": {
    "addr:full":"Pl Miguel Indurain, 6 Atarrabia Navarra 31610",
    "addr:housenumber":"6",
    "addr:postcode":"31610",
    "addr:street":"Pl Miguel Indurain",
    "iso:country":"ES",
    "sg:address":"Pl Miguel Indurain, 6",
    "sg:city":"Atarrabia",
    "sg:orig_category":"Plomeros",
    "sg:phone":"+34 948 33 10 54",
    "sg:postcode":"31610",
    "sg:province":"Navarra",
    "wof:name":"Oteiza Laplaza Antonio Oteiza Ocariz Jose Antonio Y Oteiza Ocariz Francisco Javier S.cv.",
    "wof:placetype":"venue"
},
  "geometry": {"coordinates":[-1.6083669662,42.8325080872],"type":"Point"}
}