{
  "type": "Feature",
  "properties": {
    "iso:country":"ES",
    "sg:address":"Calle de Regimiento De Toledo, 22",
    "sg:city":"Zamora",
    "sg:orig_category":"Ense\u00d1anza Variada",
    "sg:phone":"+34 980 52 19 35",
    "sg:postcode":"49012",
    "sg:province":"Zamora",
    "wof:name":"Gonzalez Franco Pedro Jesus",
    "wof:placetype":"venue"
},
  "geometry": {"coordinates":[-5.7377500534,41.5103302002],"type":"Point"}
}