{
  "type": "Feature",
  "properties": {
    "iso:country":"ES",
    "sg:address":"San Pedro Martir, 2",
    "sg:city":"Javea",
    "sg:orig_category":"Electrodom\u00c9sticos (al Por Menor)",
    "sg:phone":"+34 965 79 12 95",
    "sg:postcode":"03730",
    "sg:province":"Alicante",
    "wof:name":"Sapena Serrat Vicenta",
    "wof:placetype":"venue"
},
  "geometry": {"coordinates":[0.1624380052,38.789024353],"type":"Point"}
}