{
  "type": "Feature",
  "properties": {
    "iso:country":"ES",
    "sg:address":"Alam Antso Estegiz Zumardia, 7",
    "sg:city":"Durango",
    "sg:orig_category":"Cerrajer\u00cda, Ferrallista",
    "sg:phone":"+34 946 21 80 46",
    "sg:postcode":"48200",
    "sg:province":"Vizcaya",
    "wof:name":"Cerrajeria Y Ferreteria Montejo S.l.",
    "wof:placetype":"venue"
},
  "geometry": {"coordinates":[-2.6292231083,43.1663284302],"type":"Point"}
}