{
  "type": "Feature",
  "properties": {
    "iso:country":"ES",
    "sg:address":"Carr De Sant Francesc, 24",
    "sg:city":"Benicarlo",
    "sg:orig_category":"Obras Y Organismos Sociales",
    "sg:phone":"+34 964 47 08 78",
    "sg:postcode":"12580",
    "sg:province":"Castell\u00f3n",
    "wof:name":"Caritas Diocesana De Tortosa",
    "wof:placetype":"venue"
},
  "geometry": {"coordinates":[0.4042100012,40.4457893372],"type":"Point"}
}