{
  "type": "Feature",
  "properties": {
    "addr:full":"Avda Francisco Ayala (de), 14 Granada Granada 18014",
    "addr:housenumber":"14",
    "addr:postcode":"18014",
    "addr:street":"Avda Francisco Ayala De",
    "iso:country":"ES",
    "sg:address":"Avda Francisco Ayala (de), 14",
    "sg:city":"Granada",
    "sg:orig_category":"Guarder\u00cdas",
    "sg:phone":"+34 958 16 21 24",
    "sg:postcode":"18014",
    "sg:province":"Granada",
    "wof:name":"Guarderia Colorines S.l.",
    "wof:placetype":"venue"
},
  "geometry": {"coordinates":[-3.6191129684,37.1950912476],"type":"Point"}
}