{
  "type": "Feature",
  "properties": {
    "iso:country":"ES",
    "sg:address":"Calle de Principe De Vergara, 35",
    "sg:city":"Madrid",
    "sg:orig_category":"Psic\u00d3logos",
    "sg:phone":"+34 915 77 60 39",
    "sg:postcode":"28001",
    "sg:province":"Madrid",
    "wof:name":"Grupo Quipu De Psicoterapia S.c.l.",
    "wof:placetype":"venue"
},
  "geometry": {"coordinates":[-3.680202961,40.4267616272],"type":"Point"}
}