{
  "type": "Feature",
  "properties": {
    "addr:full":"Calle de Escultor Viciano, 5 Castellon Castell\u00f3n 12002",
    "addr:housenumber":"5",
    "addr:postcode":"12002",
    "addr:street":"Calle De Escultor Viciano;Castello\u0301N",
    "iso:country":"ES",
    "sg:address":"Calle de Escultor Viciano, 5",
    "sg:city":"Castellon",
    "sg:orig_category":"Sales (al Por Mayor)",
    "sg:phone":"+34 964 23 08 90",
    "sg:postcode":"12002",
    "sg:province":"Castell\u00f3n",
    "wof:name":"Forcada Valls Jose Ramon",
    "wof:placetype":"venue"
},
  "geometry": {"coordinates":[-0.0369039997,39.9840316772],"type":"Point"}
}