{
  "type": "Feature",
  "properties": {
    "iso:country":"ES",
    "sg:address":"Calle de Estacion, 11",
    "sg:city":"Roquetas Mar",
    "sg:orig_category":"Bisuter\u00cda, Joyer\u00cda, Relojer\u00cda (al Por Menor)",
    "sg:phone":"+34 950 32 00 33",
    "sg:postcode":"04740",
    "sg:province":"Almer\u00eda",
    "wof:name":"Luque Alcala Jose",
    "wof:placetype":"venue"
},
  "geometry": {"coordinates":[-2.6159129143,36.7643318176],"type":"Point"}
}