{
  "type": "Feature",
  "properties": {
    "iso:country":"ES",
    "sg:address":"Calle de Athos, 32",
    "sg:city":"Madrid",
    "sg:orig_category":"Electricidad: Equipos Industriales, Componentes (fabricaci\u00d3n)",
    "sg:phone":"+34 914 70 07 36",
    "sg:postcode":"28011",
    "sg:province":"Madrid",
    "wof:name":"Dominguez Beltran De Caicedo Miguel",
    "wof:placetype":"venue"
},
  "geometry": {"coordinates":[-3.7314589024,40.407661438],"type":"Point"}
}