{
  "type": "Feature",
  "properties": {
    "iso:country":"ES",
    "sg:address":"El Castillo, 39",
    "sg:city":"Baltanas",
    "sg:orig_category":"Promotores Constructores",
    "sg:phone":"+34 979 79 05 35",
    "sg:postcode":"34240",
    "sg:province":"Palencia",
    "wof:name":"Mate Masa Emeterio",
    "wof:placetype":"venue"
},
  "geometry": {"coordinates":[-4.2450690269,41.9383010864],"type":"Point"}
}