{
  "type": "Feature",
  "properties": {
    "addr:full":"Calle de Amargura, 3 Teruel Teruel 44001",
    "addr:housenumber":"3",
    "addr:postcode":"44001",
    "addr:street":"Calle De Amargura",
    "iso:country":"ES",
    "sg:address":"Calle de Amargura, 3",
    "sg:city":"Teruel",
    "sg:orig_category":"Administradores De Bienes Y Delegados De Comunidades De Propietarios",
    "sg:phone":"+34 978 61 81 85",
    "sg:postcode":"44001",
    "sg:province":"Teruel",
    "wof:name":"Gestora Turolense De Inmuebles S.l.",
    "wof:placetype":"venue"
},
  "geometry": {"coordinates":[-1.1074666977,40.3417434692],"type":"Point"}
}