{
  "type": "Feature",
  "properties": {
    "iso:country":"ES",
    "sg:address":"Carretera De Mancha Real-cazorla, S/n",
    "sg:city":"Bedmar",
    "sg:orig_category":"Aparatos E Instalaci\u00d3n De Regad\u00cdos",
    "sg:phone":"+34 953 77 21 59",
    "sg:postcode":"23537",
    "sg:province":"Ja\u00e9n",
    "wof:name":"Amezcua Martinez Antonio",
    "wof:placetype":"venue"
},
  "geometry": {"coordinates":[-3.4150800705,37.8228988647],"type":"Point"}
}