{
  "type": "Feature",
  "properties": {
    "iso:country":"ES",
    "sg:address":"Calle de Inglaterra, 32",
    "sg:city":"Palencia",
    "sg:orig_category":"Diarios, Revistas Y Boletines (suscripciones)",
    "sg:phone":"+34 979 71 38 98",
    "sg:postcode":"34004",
    "sg:province":"Palencia",
    "wof:name":"Merino Abia S.l.",
    "wof:placetype":"venue"
},
  "geometry": {"coordinates":[-4.5077648163,42.0027389526],"type":"Point"}
}