{
  "type": "Feature",
  "properties": {
    "iso:country":"ES",
    "sg:address":"Calle de Luis Sauquillo, 2",
    "sg:city":"Fuenlabrada",
    "sg:orig_category":"Librer\u00cdas",
    "sg:phone":"+34 916 15 77 08",
    "sg:postcode":"28944",
    "sg:province":"Madrid",
    "wof:name":"Pe\u00f1a Velazquez Guadalupe",
    "wof:placetype":"venue"
},
  "geometry": {"coordinates":[-3.7951450348,40.2840690613],"type":"Point"}
}