{
  "type": "Feature",
  "properties": {
    "addr:full":"Avda Algorta, 110 Algorta Vizcaya 48991",
    "addr:housenumber":"110",
    "addr:postcode":"48991",
    "addr:street":"Avda Algorta",
    "iso:country":"ES",
    "sg:address":"Avda Algorta, 110",
    "sg:city":"Algorta",
    "sg:orig_category":"Agencias De Viajes",
    "sg:phone":"+34 944 60 59 54",
    "sg:postcode":"48991",
    "sg:province":"Vizcaya",
    "sg:website":"www.barceloviajes.com",
    "wof:name":"Artasatur S.l.",
    "wof:placetype":"venue"
},
  "geometry": {"coordinates":[-3.010340929,43.3518981934],"type":"Point"}
}