{
  "type": "Feature",
  "properties": {
    "iso:country":"ES",
    "sg:address":"Carrer de Lluis Pascual Roca, 63",
    "sg:city":"S. Boi Llobregat",
    "sg:orig_category":"Art\u00cdculos De Regalo (al Por Menor)",
    "sg:phone":"+34 936 35 47 82",
    "sg:postcode":"08830",
    "sg:province":"Barcelona",
    "wof:name":"Fernandez Oller Alejandro",
    "wof:placetype":"venue"
},
  "geometry": {"coordinates":[2.0363099575,41.3450012207],"type":"Point"}
}