{
  "type": "Feature",
  "properties": {
    "addr:full":"Plaz Verdura Plaza, 1 Tolosa Guip\u00f9zcoa 20400",
    "addr:housenumber":"1",
    "addr:postcode":"20400",
    "addr:street":"Guipu\u0300Zcoa",
    "iso:country":"ES",
    "sg:address":"Plaz Verdura Plaza, 1",
    "sg:city":"Tolosa",
    "sg:orig_category":"Carnes De Carnicer\u00cda (al Por Mayor)",
    "sg:phone":"+34 943 67 18 18",
    "sg:postcode":"20400",
    "sg:province":"Guip\u00f9zcoa",
    "wof:name":"Lopetegui Zubeldia Antonio",
    "wof:placetype":"venue"
},
  "geometry": {"coordinates":[-2.0724620819,43.1388816833],"type":"Point"}
}