{
  "type": "Feature",
  "properties": {
    "addr:full":"Avda Vi\u00d1agrande, 25 Alcorcon Madrid 28925",
    "addr:housenumber":"25",
    "addr:postcode":"28925",
    "addr:street":"Avda Vin\u0303Agrande",
    "iso:country":"ES",
    "sg:address":"Avda Vi\u00d1agrande, 25",
    "sg:city":"Alcorcon",
    "sg:orig_category":"Empresas De Pintura Y Revestimientos",
    "sg:phone":"+34 916 11 78 43",
    "sg:postcode":"28925",
    "sg:province":"Madrid",
    "wof:name":"Dominguez San Roman Jesus",
    "wof:placetype":"venue"
},
  "geometry": {"coordinates":[-3.8055789471,40.349029541],"type":"Point"}
}