{
  "type": "Feature",
  "properties": {
    "addr:full":"Jose Antonio Primo De Rivera, 6 Medina Rioseco Valladolid 47800",
    "addr:housenumber":"6",
    "addr:postcode":"47800",
    "addr:street":"Jose Antonio Primo De Rivera",
    "iso:country":"ES",
    "sg:address":"Jose Antonio Primo De Rivera, 6",
    "sg:city":"Medina Rioseco",
    "sg:orig_category":"Panader\u00cdas, Panader\u00cdas",
    "sg:phone":"+34 983 70 09 22",
    "sg:postcode":"47800",
    "sg:province":"Valladolid",
    "wof:name":"Novo Perez Francisco",
    "wof:placetype":"venue"
},
  "geometry": {"coordinates":[-5.0413942337,41.8812446594],"type":"Point"}
}