{
  "type": "Feature",
  "properties": {
    "addr:full":"Rbla Mossen Jaume Tobella, 80 Residencial Tarragona 43820",
    "addr:housenumber":"80",
    "addr:postcode":"43820",
    "addr:street":"Rbla Mossen Jaume Tobella",
    "iso:country":"ES",
    "sg:address":"Rbla Mossen Jaume Tobella, 80",
    "sg:city":"Residencial",
    "sg:orig_category":"Mec\u00c1nico Del Autom\u00d3vil",
    "sg:phone":"+34 977 69 29 40",
    "sg:postcode":"43820",
    "sg:province":"Tarragona",
    "wof:name":"Guinovart Mecanics S.l.",
    "wof:placetype":"venue"
},
  "geometry": {"coordinates":[1.5684100389,41.1977844238],"type":"Point"}
}