{
  "type": "Feature",
  "properties": {
    "addr:full":"Calle de Germanies, 47 Torrent Valencia 46900",
    "addr:housenumber":"47",
    "addr:postcode":"46900",
    "addr:street":"Calle De Germanies;Valencia",
    "iso:country":"ES",
    "sg:address":"Calle de Germanies, 47",
    "sg:city":"Torrent",
    "sg:orig_category":"Librer\u00cdas",
    "sg:phone":"+34 961 55 49 05",
    "sg:postcode":"46900",
    "sg:province":"Valencia",
    "wof:name":"Fuertes Julvez Lorenzo",
    "wof:placetype":"venue"
},
  "geometry": {"coordinates":[-0.472825408,39.4332122803],"type":"Point"}
}