{
  "type": "Feature",
  "properties": {
    "addr:full":"Calle de San Sebastian (de), 44 Colmenar Viejo Madrid 28770",
    "addr:postcode":"28770",
    "addr:street":"Calle De",
    "iso:country":"ES",
    "sg:address":"Calle de San Sebastian (de), 44",
    "sg:city":"Colmenar Viejo",
    "sg:orig_category":"Bisuter\u00cda, Joyer\u00cda, Relojer\u00cda (al Por Menor)",
    "sg:phone":"+34 918 48 60 26",
    "sg:postcode":"28770",
    "sg:province":"Madrid",
    "wof:name":"Wang  Aimei",
    "wof:placetype":"venue"
},
  "geometry": {"coordinates":[-3.7689139843,40.6636734009],"type":"Point"}
}