{
  "type": "Feature",
  "properties": {
    "iso:country":"ES",
    "sg:address":"Carrer de Maria Cubi, 90",
    "sg:city":"Barcelona",
    "sg:orig_category":"Molduras, Junquillos, Listones Y Molduras Perforadas",
    "sg:phone":"+34 932 00 76 34",
    "sg:postcode":"08021",
    "sg:province":"Barcelona",
    "wof:name":"Kanfach  Izat",
    "wof:placetype":"venue"
},
  "geometry": {"coordinates":[2.1475820541,41.3971748352],"type":"Point"}
}