{
  "type": "Feature",
  "properties": {
    "addr:full":"Cami Ral, 16 Vilassar Barcelona 08340",
    "addr:postcode":"08340",
    "addr:street":"Ral;Vilassar Barcelona",
    "iso:country":"ES",
    "sg:address":"Cami Ral, 16",
    "sg:city":"Vilassar",
    "sg:orig_category":"Ense\u00d1anza: Profesiones Art\u00cdsticas",
    "sg:phone":"+34 937 50 08 04",
    "sg:postcode":"08340",
    "sg:province":"Barcelona",
    "wof:name":"Consorci De Serveis Grafics S.l.",
    "wof:placetype":"venue"
},
  "geometry": {"coordinates":[2.394769907,41.5030784607],"type":"Point"}
}