{
  "type": "Feature",
  "properties": {
    "addr:full":"Calle de Mejorana, 9 Madrid Madrid 28053",
    "addr:housenumber":"9",
    "addr:postcode":"madrid;28053",
    "addr:street":"Calle De Mejorana",
    "iso:country":"ES",
    "sg:address":"Calle de Mejorana, 9",
    "sg:city":"Madrid",
    "sg:orig_category":"Mec\u00c1nico Del Autom\u00d3vil",
    "sg:phone":"+34 914 77 77 01",
    "sg:postcode":"28053",
    "sg:province":"Madrid",
    "wof:name":"Garcia Flores Mercedes",
    "wof:placetype":"venue"
},
  "geometry": {"coordinates":[-3.6717870235,40.3849945068],"type":"Point"}
}