{
  "type": "Feature",
  "properties": {
    "iso:country":"ES",
    "sg:address":"Plaz Don Hilario Yaben, 2",
    "sg:city":"Sig\u00fcenza",
    "sg:orig_category":"Carnicer\u00cdas, Carnicer\u00cdas",
    "sg:phone":"+34 949 39 17 53",
    "sg:postcode":"19250",
    "sg:province":"Guadalajara",
    "wof:name":"Atienza Sanz Juan",
    "wof:placetype":"venue"
},
  "geometry": {"coordinates":[-2.6387794018,41.0697555542],"type":"Point"}
}