{
  "type": "Feature",
  "properties": {
    "addr:full":"Calle de Acera Del Darro, 48 Granada Granada 18005",
    "addr:housenumber":"48",
    "addr:postcode":"18005",
    "addr:street":"Calle De Acera Del Darro",
    "iso:country":"ES",
    "sg:address":"Calle de Acera Del Darro, 48",
    "sg:city":"Granada",
    "sg:orig_category":"Molduras, Junquillos, Listones Y Molduras Perforadas",
    "sg:phone":"+34 958 26 34 90",
    "sg:postcode":"18005",
    "sg:province":"Granada",
    "wof:name":"Fernandez Fiestas Antonio",
    "wof:placetype":"venue"
},
  "geometry": {"coordinates":[-3.5986616611,37.1712532043],"type":"Point"}
}