{
  "type": "Feature",
  "properties": {
    "addr:full":"Calle de Sanz De Bremond, 22 Castellon Castell\u00f3n 12004",
    "addr:housenumber":"22",
    "addr:postcode":"12004",
    "addr:street":"Calle De Sanz De Bremond",
    "iso:country":"ES",
    "sg:address":"Calle de Sanz De Bremond, 22",
    "sg:city":"Castellon",
    "sg:orig_category":"Pescader\u00cdas (al Por Menor)",
    "sg:phone":"+34 964 22 04 30",
    "sg:postcode":"12004",
    "sg:province":"Castell\u00f3n",
    "wof:name":"Pescados Y Mariscos Paches Y Campos S.l.",
    "wof:placetype":"venue"
},
  "geometry": {"coordinates":[-0.032949999,39.9913902283],"type":"Point"}
}