{
  "type": "Feature",
  "properties": {
    "iso:country":"ES",
    "sg:address":"Calle de Gabika Monte, 6",
    "sg:city":"Bilbao",
    "sg:orig_category":"Electricidad Veh\u00cdculo",
    "sg:phone":"+34 944 43 77 19",
    "sg:postcode":"48003",
    "sg:province":"Vizcaya",
    "wof:name":"Autoelectricidad Arturo",
    "wof:placetype":"venue"
},
  "geometry": {"coordinates":[-2.9306023121,43.2483100891],"type":"Point"}
}