{
  "type": "Feature",
  "properties": {
    "addr:full":"Calle de Edificio Velasco, 37 Irun Guip\u00f9zcoa 20303",
    "addr:housenumber":"37",
    "addr:postcode":"20303",
    "addr:street":"Calle De Edificio Velasco;Guipu\u0300Zcoa",
    "iso:country":"ES",
    "sg:address":"Calle de Edificio Velasco, 37",
    "sg:city":"Irun",
    "sg:orig_category":"Suministros Para Carrocer\u00cdas",
    "sg:phone":"+34 943 62 88 22",
    "sg:postcode":"20303",
    "sg:province":"Guip\u00f9zcoa",
    "wof:name":"Rastrilla Vazquez Jose Maria",
    "wof:placetype":"venue"
},
  "geometry": {"coordinates":[-1.7902339697,43.3395233154],"type":"Point"}
}