{
  "type": "Feature",
  "properties": {
    "addr:full":"Avda Palos De La Frontera, 64 Niebla Huelva 21840",
    "addr:housenumber":"64",
    "addr:postcode":"21840",
    "addr:street":"Avda Palos De La Frontera",
    "iso:country":"ES",
    "sg:address":"Avda Palos De La Frontera, 64",
    "sg:city":"Niebla",
    "sg:orig_category":"Bares, Piano",
    "sg:phone":"+34 959 36 32 50",
    "sg:postcode":"21840",
    "sg:province":"Huelva",
    "wof:name":"Ramos Gonzalez Juan",
    "wof:placetype":"venue"
},
  "geometry": {"coordinates":[-6.6840372086,37.3594589233],"type":"Point"}
}