{
  "type": "Feature",
  "properties": {
    "iso:country":"ES",
    "sg:address":"Calle de Otero Blas De, 28",
    "sg:city":"Bilbao",
    "sg:orig_category":"Carnicer\u00cdas, Carnicer\u00cdas",
    "sg:phone":"+34 944 75 28 11",
    "sg:postcode":"48014",
    "sg:province":"Vizcaya",
    "wof:name":"Jaunene S.l.",
    "wof:placetype":"venue"
},
  "geometry": {"coordinates":[-2.9459071159,43.2702102661],"type":"Point"}
}