{
  "type": "Feature",
  "properties": {
    "iso:country":"ES",
    "sg:address":"Avda Castelao, 111",
    "sg:city":"Muros",
    "sg:orig_category":"Abogados",
    "sg:phone":"+34 981 76 24 45",
    "sg:postcode":"15250",
    "sg:province":"La Coru\u00f1a",
    "wof:name":"Fernandez-refoxo Gonzalez Oscar",
    "wof:placetype":"venue"
},
  "geometry": {"coordinates":[-9.0596208572,42.7771911621],"type":"Point"}
}