{
  "type": "Feature",
  "properties": {
    "iso:country":"ES",
    "sg:address":"Calle de Francisco Martinez Cascales, S/n",
    "sg:city":"Ceuti",
    "sg:orig_category":"Importaci\u00d3n",
    "sg:phone":"+34 968 69 13 59",
    "sg:postcode":"30562",
    "sg:province":"Murcia",
    "wof:name":"Sitomar S.l.",
    "wof:placetype":"venue"
},
  "geometry": {"coordinates":[-1.2719039917,38.0765838623],"type":"Point"}
}