{
  "type": "Feature",
  "properties": {
    "addr:full":"Calle de Oca, 56 Madrid Madrid 28025",
    "addr:housenumber":"56",
    "addr:postcode":"madrid;28025",
    "addr:street":"Calle De Oca",
    "iso:country":"ES",
    "sg:address":"Calle de Oca, 56",
    "sg:city":"Madrid",
    "sg:orig_category":"Fabricaci\u00d3n, Alquiler, Venta De Encofrados",
    "sg:phone":"+34 914 62 32 58",
    "sg:postcode":"28025",
    "sg:province":"Madrid",
    "wof:name":"Sistemas Tecnicos De Encofrados S.a.",
    "wof:placetype":"venue"
},
  "geometry": {"coordinates":[-3.7378380299,40.389415741],"type":"Point"}
}