{
  "type": "Feature",
  "properties": {
    "iso:country":"ES",
    "sg:address":"Calle de Perez De La Sala, 25",
    "sg:city":"Oviedo",
    "sg:orig_category":"Molduras, Junquillos, Listones Y Molduras Perforadas",
    "sg:phone":"+34 985 25 05 99",
    "sg:postcode":"33007",
    "sg:province":"Asturias",
    "wof:name":"Llera Rodriguez Maria Teresa",
    "wof:placetype":"venue"
},
  "geometry": {"coordinates":[-5.8505067825,43.3576660156],"type":"Point"}
}