{
  "type": "Feature",
  "properties": {
    "iso:country":"ES",
    "sg:address":"Pase Alparrache (del), 15",
    "sg:city":"Navalcarnero",
    "sg:orig_category":"Carb\u00d3n, Carb\u00d3n De Madera (al Por Mayor)",
    "sg:phone":"+34 918 11 02 05",
    "sg:postcode":"28600",
    "sg:province":"Madrid",
    "wof:name":"Diaz Licas Antonio",
    "wof:placetype":"venue"
},
  "geometry": {"coordinates":[-4.0076651573,40.2900695801],"type":"Point"}
}