{
  "type": "Feature",
  "properties": {
    "addr:full":"Carrer de Mestre Turina, 95 Olot Girona 17800",
    "addr:housenumber":"95",
    "addr:postcode":"17800",
    "addr:street":"Carrer De Mestre Turina",
    "iso:country":"ES",
    "sg:address":"Carrer de Mestre Turina, 95",
    "sg:city":"Olot",
    "sg:orig_category":"Electricidad: Instaladores",
    "sg:phone":"+34 972 27 48 74",
    "sg:postcode":"17800",
    "sg:province":"Girona",
    "wof:name":"Nogue Batlle Joan",
    "wof:placetype":"venue"
},
  "geometry": {"coordinates":[2.5069179535,42.1914901733],"type":"Point"}
}