{
  "type": "Feature",
  "properties": {
    "addr:full":"Calle de Virgen De La Vega, 23 Haro La Rioja 26200",
    "addr:housenumber":"23",
    "addr:postcode":"26200",
    "addr:street":"Calle De Virgen De La Vega",
    "iso:country":"ES",
    "sg:address":"Calle de Virgen De La Vega, 23",
    "sg:city":"Haro",
    "sg:orig_category":"Material Y Suministros Para Imprenta E Industrias Gr\u00c1ficas",
    "sg:phone":"+34 941 31 02 43",
    "sg:postcode":"26200",
    "sg:province":"La Rioja",
    "wof:name":"Viela Rubio Francisco",
    "wof:placetype":"venue"
},
  "geometry": {"coordinates":[-2.8492894173,42.5769920349],"type":"Point"}
}