{
  "type": "Feature",
  "properties": {
    "addr:full":"Calle de Miguel De Cervantes, 5 Cabanillas Campo Guadalajara 19171",
    "addr:housenumber":"5",
    "addr:postcode":"19171",
    "addr:street":"Calle De Miguel De Cervantes",
    "iso:country":"ES",
    "sg:address":"Calle de Miguel De Cervantes, 5",
    "sg:city":"Cabanillas Campo",
    "sg:orig_category":"Alquiler De V\u00cddeo",
    "sg:phone":"+34 949 33 71 84",
    "sg:postcode":"19171",
    "sg:province":"Guadalajara",
    "wof:name":"Macrix Cb",
    "wof:placetype":"venue"
},
  "geometry": {"coordinates":[-3.236768961,40.626209259],"type":"Point"}
}