{
  "type": "Feature",
  "properties": {
    "addr:full":"Calle de Amezketa De Los, 21 Donostia-san Sebastian Guip\u00f9zcoa 20010",
    "addr:postcode":"20010",
    "addr:street":"Calle De Amezketa De Los 21",
    "iso:country":"ES",
    "sg:address":"Calle de Amezketa De Los, 21",
    "sg:city":"Donostia-san Sebastian",
    "sg:orig_category":"Promotores Constructores",
    "sg:phone":"+34 943 47 06 14",
    "sg:postcode":"20010",
    "sg:province":"Guip\u00f9zcoa",
    "wof:name":"Promociones Ongarai 2001 S.l.",
    "wof:placetype":"venue"
},
  "geometry": {"coordinates":[-1.9820388556,43.3035163879],"type":"Point"}
}