{
  "type": "Feature",
  "properties": {
    "addr:full":"Arturo Cuadrado Moure, 25 Santiago De Compostela La Coru\u00f1a 15705",
    "addr:housenumber":"25",
    "addr:postcode":"15705",
    "addr:street":"Arturo Cuadrado Moure;Corun\u0303A",
    "iso:country":"ES",
    "sg:address":"Arturo Cuadrado Moure, 25",
    "sg:city":"Santiago De Compostela",
    "sg:orig_category":"Farmacias",
    "sg:phone":"+34 981 57 00 65",
    "sg:postcode":"15705",
    "sg:province":"La Coru\u00f1a",
    "wof:name":"Gilead Sciences S.l.",
    "wof:placetype":"venue"
},
  "geometry": {"coordinates":[-8.5463924408,42.8961181641],"type":"Point"}
}