{
  "type": "Feature",
  "properties": {
    "addr:full":"Av Benissa, S/n Benidorm Alicante 03500",
    "addr:housenumber":"s / n",
    "addr:postcode":"03500",
    "addr:street":"Av Benissa",
    "iso:country":"ES",
    "sg:address":"Av Benissa, S/n",
    "sg:city":"Benidorm",
    "sg:orig_category":"Promotores Constructores",
    "sg:phone":"+34 965 86 31 02",
    "sg:postcode":"03500",
    "sg:province":"Alicante",
    "wof:name":"Rover Alcisa S.a.",
    "wof:placetype":"venue"
},
  "geometry": {"coordinates":[-0.1623460054,38.5360946655],"type":"Point"}
}