{
  "type": "Feature",
  "properties": {
    "iso:country":"ES",
    "sg:address":"Pl Gcia Ceballos, S/n",
    "sg:city":"Gerena",
    "sg:orig_category":"Agricultura: Abastecimiento Y Cosechado (negocio)",
    "sg:phone":"+34 955 78 24 00",
    "sg:postcode":"41860",
    "sg:province":"Sevilla",
    "wof:name":"Sociedad Cooperativa Andaluza Campo De Gerena",
    "wof:placetype":"venue"
},
  "geometry": {"coordinates":[-6.1584191322,37.5270690918],"type":"Point"}
}