{
  "type": "Feature",
  "properties": {
    "iso:country":"ES",
    "sg:address":"Carrer de Joan Maragall, 8",
    "sg:city":"Alcanar",
    "sg:orig_category":"Deportes Y Ocio: Art\u00cdculos Y Equipos (al Por Mayor)",
    "sg:phone":"+34 977 73 21 41",
    "sg:postcode":"43530",
    "sg:province":"Tarragona",
    "wof:name":"Capseta Bayarri Leonor",
    "wof:placetype":"venue"
},
  "geometry": {"coordinates":[0.4749970138,40.5401763916],"type":"Point"}
}