{
  "type": "Feature",
  "properties": {
    "iso:country":"ES",
    "sg:address":"Calle de Nu\u00d1ez De Balboa, 35",
    "sg:city":"Madrid",
    "sg:orig_category":"Ingenier\u00cda, Centros De Estudios (diversos)",
    "sg:phone":"+34 914 31 33 37",
    "sg:postcode":"28001",
    "sg:province":"Madrid",
    "wof:name":"Nb 35 S.l.",
    "wof:placetype":"venue"
},
  "geometry": {"coordinates":[-3.6829369068,40.4253730774],"type":"Point"}
}