{
  "type": "Feature",
  "properties": {
    "addr:full":"Calle de Comunicacion (la), 5 Azuqueca Henares Guadalajara 19200",
    "addr:housenumber":"5",
    "addr:postcode":"19200",
    "addr:street":"Calle De Comunicacion La",
    "iso:country":"ES",
    "sg:address":"Calle de Comunicacion (la), 5",
    "sg:city":"Azuqueca Henares",
    "sg:orig_category":"Encuadernaci\u00d3n E Impresi\u00d3n De Folletos",
    "sg:phone":"+34 949 26 14 94",
    "sg:postcode":"19200",
    "sg:province":"Guadalajara",
    "wof:name":"Taller De Encuadernacion Del Henares S.l.",
    "wof:placetype":"venue"
},
  "geometry": {"coordinates":[-3.2677440643,40.5646400452],"type":"Point"}
}