{
  "type": "Feature",
  "properties": {
    "addr:full":"Plaz Alamitos, 1 Plasencia C\u00e1ceres 10600",
    "addr:housenumber":"1",
    "addr:postcode":"10600",
    "addr:street":"Plaz Alamitos;Ca\u0301Ceres",
    "iso:country":"ES",
    "sg:address":"Plaz Alamitos, 1",
    "sg:city":"Plasencia",
    "sg:orig_category":"Farmacias",
    "sg:phone":"+34 927 41 01 15",
    "sg:postcode":"10600",
    "sg:province":"C\u00e1ceres",
    "wof:name":"Lopez-mateos Orantos Maria Del Puerto",
    "wof:placetype":"venue"
},
  "geometry": {"coordinates":[-6.0823411942,40.0387229919],"type":"Point"}
}