{
  "type": "Feature",
  "properties": {
    "addr:full":"Calle de Zuberoa, 2 Legizamon Vizcaya 48450",
    "addr:housenumber":"2",
    "addr:postcode":"48450",
    "addr:street":"Calle De Zuberoa",
    "iso:country":"ES",
    "sg:address":"Calle de Zuberoa, 2",
    "sg:city":"Legizamon",
    "sg:orig_category":"Diarios, Revistas Y Boletines (suscripciones)",
    "sg:phone":"+34 944 26 12 27",
    "sg:postcode":"48450",
    "sg:province":"Vizcaya",
    "wof:name":"Guinea Simo S.l.",
    "wof:placetype":"venue"
},
  "geometry": {"coordinates":[-2.8955059052,43.2510108948],"type":"Point"}
}