{
  "type": "Feature",
  "properties": {
    "addr:full":"Calle de Magantina (la), S/n Huesca Huesca 22006",
    "addr:postcode":"22006",
    "addr:street":"Calle De Magantina La S / N",
    "iso:country":"ES",
    "sg:address":"Calle de Magantina (la), S/n",
    "sg:city":"Huesca",
    "sg:orig_category":"Serigraf\u00cda",
    "sg:phone":"+34 974 23 07 07",
    "sg:postcode":"22006",
    "sg:province":"Huesca",
    "wof:name":"Cebollero Gracia Jorge",
    "wof:placetype":"venue"
},
  "geometry": {"coordinates":[-0.4066239893,42.1458702087],"type":"Point"}
}