{
  "type": "Feature",
  "properties": {
    "addr:full":"Calle de Carmen, 1 Nerja M\u00e1laga 29780",
    "addr:housenumber":"1",
    "addr:postcode":"29780",
    "addr:street":"Calle De Carmen",
    "iso:country":"ES",
    "sg:address":"Calle de Carmen, 1",
    "sg:city":"Nerja",
    "sg:orig_category":"Promotores Constructores",
    "sg:phone":"+34 952 52 07 87",
    "sg:postcode":"29780",
    "sg:province":"M\u00e1laga",
    "wof:name":"Valle Axarco S.l.",
    "wof:placetype":"venue"
},
  "geometry": {"coordinates":[-3.8766899109,36.745174408],"type":"Point"}
}