{
  "type": "Feature",
  "properties": {
    "addr:full":"Avda Salvador Allende, 91 Zaragoza Zaragoza 50015",
    "addr:housenumber":"91",
    "addr:postcode":"50015",
    "addr:street":"Avda Salvador Allende",
    "iso:country":"ES",
    "sg:address":"Avda Salvador Allende, 91",
    "sg:city":"Zaragoza",
    "sg:orig_category":"Molduras, Junquillos, Listones Y Molduras Perforadas",
    "sg:phone":"+34 976 73 59 46",
    "sg:postcode":"50015",
    "sg:province":"Zaragoza",
    "wof:name":"Vencotel S.l.",
    "wof:placetype":"venue"
},
  "geometry": {"coordinates":[-0.8737130165,41.6777610779],"type":"Point"}
}