{
  "type": "Feature",
  "properties": {
    "iso:country":"ES",
    "sg:address":"Part. Porpores, S/n",
    "sg:city":"Reus",
    "sg:orig_category":"Aguas (distribuci\u00d3n, Servicios)",
    "sg:phone":"+34 977 75 37 00",
    "sg:postcode":"43206",
    "sg:province":"Tarragona",
    "wof:name":"Sanejament Ambiental S.a.",
    "wof:placetype":"venue"
},
  "geometry": {"coordinates":[1.1039400101,41.1745300293],"type":"Point"}
}