{
  "type": "Feature",
  "properties": {
    "addr:full":"Avda Carlos I De, 11 Donostia-san Sebastian Guip\u00f9zcoa 20011",
    "addr:housenumber":"11",
    "addr:postcode":"20011",
    "addr:street":"Avda Carlos I De",
    "iso:country":"ES",
    "sg:address":"Avda Carlos I De, 11",
    "sg:city":"Donostia-san Sebastian",
    "sg:orig_category":"Sociedades, Compa\u00d1\u00cdas Aseguradoras",
    "sg:phone":"+34 943 46 71 65",
    "sg:postcode":"20011",
    "sg:province":"Guip\u00f9zcoa",
    "sg:website":"www.prevenalia.net",
    "wof:name":"Prevenalia",
    "wof:placetype":"venue"
},
  "geometry": {"coordinates":[-1.9784059525,43.3036689758],"type":"Point"}
}