{
  "type": "Feature",
  "properties": {
    "iso:country":"ES",
    "sg:address":"Calle de Huetor Vega, 11",
    "sg:city":"Zubia",
    "sg:orig_category":"Prot\u00c9sicos Dentales",
    "sg:phone":"+34 958 89 10 18",
    "sg:postcode":"18140",
    "sg:province":"Granada",
    "wof:name":"Megias De Haro Manuel",
    "wof:placetype":"venue"
},
  "geometry": {"coordinates":[-3.5764930248,37.1227264404],"type":"Point"}
}