{
  "type": "Feature",
  "properties": {
    "iso:country":"ES",
    "sg:address":"Calle de Manuel Nu\u00d1ez Perez, 30",
    "sg:city":"Benavides De Orbigo",
    "sg:orig_category":"Delegados, Agentes De Tr\u00c1nsito, Auxiliares De Transporte Internacional",
    "sg:phone":"+34 987 37 03 49",
    "sg:postcode":"24280",
    "sg:province":"Le\u00f3n",
    "wof:name":"Arias Coello Sabina",
    "wof:placetype":"venue"
},
  "geometry": {"coordinates":[-5.9005317688,42.5038604736],"type":"Point"}
}