{
  "type": "Feature",
  "properties": {
    "addr:full":"Carr Murcia, 15 Lleida Lleida 25002",
    "addr:housenumber":"15",
    "addr:postcode":"25002",
    "addr:street":"Carr Murcia",
    "iso:country":"ES",
    "sg:address":"Carr Murcia, 15",
    "sg:city":"Lleida",
    "sg:orig_category":"Reposter\u00cdas",
    "sg:phone":"+34 973 28 14 25",
    "sg:postcode":"25002",
    "sg:province":"Lleida",
    "wof:name":"Panaderia Aguila S.l.",
    "wof:placetype":"venue"
},
  "geometry": {"coordinates":[0.627129972,41.6145210266],"type":"Point"}
}