{
  "type": "Feature",
  "properties": {
    "iso:country":"ES",
    "sg:address":"Avda Isabel Ii De, 6",
    "sg:city":"Donostia-san Sebastian",
    "sg:orig_category":"M\u00c9dicos: Estomatolog\u00cda",
    "sg:phone":"+34 943 47 07 31",
    "sg:postcode":"20011",
    "sg:province":"Guip\u00f9zcoa",
    "wof:name":"Bustinza Aldecoa Montserrat",
    "wof:placetype":"venue"
},
  "geometry": {"coordinates":[-1.9760500193,43.3047103882],"type":"Point"}
}