{
  "type": "Feature",
  "properties": {
    "iso:country":"ES",
    "sg:address":"Ptor Asenjo, 10",
    "sg:city":"Iru\u00f1a",
    "sg:orig_category":"M\u00c9dicos: Pediatr\u00cda. Enfermedades De Los Ni\u00d1os",
    "sg:phone":"+34 948 17 17 33",
    "sg:postcode":"31008",
    "sg:province":"Navarra",
    "wof:name":"Molina Garicano Javier",
    "wof:placetype":"venue"
},
  "geometry": {"coordinates":[-1.6579879522,42.8085975647],"type":"Point"}
}