{
  "type": "Feature",
  "properties": {
    "addr:full":"Calle de Trinidad, 53 Talavera Reina Toledo 45600",
    "addr:housenumber":"53",
    "addr:postcode":"45600",
    "addr:street":"Calle De Trinidad",
    "iso:country":"ES",
    "sg:address":"Calle de Trinidad, 53",
    "sg:city":"Talavera Reina",
    "sg:orig_category":"Bisuter\u00cda, Joyer\u00cda, Relojer\u00cda (al Por Menor)",
    "sg:phone":"+34 925 82 01 49",
    "sg:postcode":"45600",
    "sg:province":"Toledo",
    "wof:name":"Rodriguez Nu\u00f1o Maria Piedad",
    "wof:placetype":"venue"
},
  "geometry": {"coordinates":[-4.8262147903,39.9639701843],"type":"Point"}
}