{
  "type": "Feature",
  "properties": {
    "iso:country":"ES",
    "sg:address":"Rua Paseo (do), 37",
    "sg:city":"Ourense",
    "sg:orig_category":"Pod\u00d3logos: Pedicuros",
    "sg:phone":"+34 988 21 13 84",
    "sg:postcode":"32003",
    "sg:province":"Ourense",
    "wof:name":"Gallego Rodriguez Monica",
    "wof:placetype":"venue"
},
  "geometry": {"coordinates":[-7.8646678925,42.3411827087],"type":"Point"}
}