{
  "type": "Feature",
  "properties": {
    "iso:country":"ES",
    "sg:address":"Carrer de Maria, 9",
    "sg:city":"Barcelona",
    "sg:orig_category":"Empresas De Carpinter\u00cda De Madera",
    "sg:phone":"+34 932 18 86 82",
    "sg:postcode":"08012",
    "sg:province":"Barcelona",
    "wof:name":"Garcia Feijoo Teresa",
    "wof:placetype":"venue"
},
  "geometry": {"coordinates":[2.1570839882,41.3992996216],"type":"Point"}
}