{
  "type": "Feature",
  "properties": {
    "iso:country":"ES",
    "sg:address":"Calle de Aire (del), 27",
    "sg:city":"Cartagena",
    "sg:orig_category":"Asesor\u00cda Sobre Comunicaci\u00d3n De Empresas",
    "sg:phone":"+34 968 12 22 31",
    "sg:postcode":"30202",
    "sg:province":"Murcia",
    "wof:name":"Gestion Y Tramitacion Notarial S.l.",
    "wof:placetype":"venue"
},
  "geometry": {"coordinates":[-0.9862887263,37.6010551453],"type":"Point"}
}