{
  "type": "Feature",
  "properties": {
    "addr:full":"Calle de Ramiro Don, S/n Zamora Zamora 49026",
    "addr:postcode":"49026",
    "addr:street":"Calle De Ramiro Don S / N",
    "iso:country":"ES",
    "sg:address":"Calle de Ramiro Don, S/n",
    "sg:city":"Zamora",
    "sg:orig_category":"Mec\u00c1nico Del Autom\u00d3vil",
    "sg:phone":"+34 980 52 50 96",
    "sg:postcode":"49026",
    "sg:province":"Zamora",
    "wof:name":"Talleres Chapam S.l.",
    "wof:placetype":"venue"
},
  "geometry": {"coordinates":[-5.754368782,41.5030937195],"type":"Point"}
}