{
  "type": "Feature",
  "properties": {
    "iso:country":"ES",
    "sg:address":"Calle de Villa Benavente, 7",
    "sg:city":"Le\u00f3n",
    "sg:orig_category":"Abogados",
    "sg:phone":"+34 987 26 24 18",
    "sg:postcode":"24004",
    "sg:province":"Le\u00f3n",
    "wof:name":"Celemin Santos Jose Luis",
    "wof:placetype":"venue"
},
  "geometry": {"coordinates":[-5.5734190941,42.5948600769],"type":"Point"}
}