{
  "type": "Feature",
  "properties": {
    "iso:country":"ES",
    "sg:address":"Av Meridiana, 110",
    "sg:city":"Barcelona",
    "sg:orig_category":"Fabricaci\u00d3n, Importaci\u00d3n De L\u00c1mparas Y Bombillas",
    "sg:phone":"+34 932 46 37 14",
    "sg:postcode":"08018",
    "sg:province":"Barcelona",
    "wof:name":"Teruel Laborda Carlos",
    "wof:placetype":"venue"
},
  "geometry": {"coordinates":[2.1872038841,41.4018173218],"type":"Point"}
}