{
  "type": "Feature",
  "properties": {
    "iso:country":"ES",
    "sg:address":"Cmno Herencia, 3",
    "sg:city":"Villarrubia De Los Ojos",
    "sg:orig_category":"Negocio De Materiales De Construcci\u00d3n",
    "sg:phone":"+34 926 89 93 55",
    "sg:postcode":"13670",
    "sg:province":"Ciudad Real",
    "wof:name":"Cigarrones C.b.",
    "wof:placetype":"venue"
},
  "geometry": {"coordinates":[-3.6060490608,39.2222137451],"type":"Point"}
}