{
  "type": "Feature",
  "properties": {
    "iso:country":"ES",
    "sg:address":"Calle de Ancha De Capuchinos, 22",
    "sg:city":"Granada",
    "sg:orig_category":"Peluquer\u00cdas, Peluquer\u00cda Mixta",
    "sg:phone":"+34 958 20 85 12",
    "sg:postcode":"18012",
    "sg:province":"Granada",
    "wof:name":"Iba\u00f1ez Cantero Miguel",
    "wof:placetype":"venue"
},
  "geometry": {"coordinates":[-3.6027309895,37.1858558655],"type":"Point"}
}