{
  "type": "Feature",
  "properties": {
    "addr:full":"Calle de Gil Y Carrasco, 1 Le\u00f3n Le\u00f3n 24001",
    "addr:housenumber":"1",
    "addr:postcode":"24001",
    "addr:street":"Calle De Gil Y Carrasco;Leo\u0301N",
    "iso:country":"ES",
    "sg:address":"Calle de Gil Y Carrasco, 1",
    "sg:city":"Le\u00f3n",
    "sg:orig_category":"Inmobiliaria (agencias)",
    "sg:phone":"+34 987 21 44 16",
    "sg:postcode":"24001",
    "sg:province":"Le\u00f3n",
    "wof:name":"Inmobiliaria R3 2002 S.l.",
    "wof:placetype":"venue"
},
  "geometry": {"coordinates":[-5.573486805,42.5972671509],"type":"Point"}
}