{
  "type": "Feature",
  "properties": {
    "addr:full":"Calle de San Roque, 19 Briviesca Burgos 09240",
    "addr:housenumber":"19",
    "addr:postcode":"09240",
    "addr:street":"Calle De San Roque",
    "iso:country":"ES",
    "sg:address":"Calle de San Roque, 19",
    "sg:city":"Briviesca",
    "sg:orig_category":"Insecticidas, Fumigaci\u00d3n",
    "sg:phone":"+34 947 59 11 40",
    "sg:postcode":"09240",
    "sg:province":"Burgos",
    "wof:name":"Rubio Lopez Luis Maria",
    "wof:placetype":"venue"
},
  "geometry": {"coordinates":[-3.3252930641,42.5521469116],"type":"Point"}
}