{
  "type": "Feature",
  "properties": {
    "addr:full":"Calle de Alicante, 23 Getafe Madrid 28903",
    "addr:housenumber":"23",
    "addr:postcode":"28903",
    "addr:street":"Calle De Alicante",
    "iso:country":"ES",
    "sg:address":"Calle de Alicante, 23",
    "sg:city":"Getafe",
    "sg:orig_category":"Empresas De Pintura Y Revestimientos",
    "sg:phone":"+34 916 95 35 91",
    "sg:postcode":"28903",
    "sg:province":"Madrid",
    "wof:name":"Hoyo Mu\u00f1oz Daniel Del",
    "wof:placetype":"venue"
},
  "geometry": {"coordinates":[-3.7190086842,40.3111877441],"type":"Point"}
}