{
  "type": "Feature",
  "properties": {
    "iso:country":"ES",
    "sg:address":"Calle de Bocangel, 12",
    "sg:city":"Madrid",
    "sg:orig_category":"Institutos De Belleza",
    "sg:phone":"+34 913 61 47 32",
    "sg:postcode":"28028",
    "sg:province":"Madrid",
    "wof:name":"Angela Y Almudena C.b.",
    "wof:placetype":"venue"
},
  "geometry": {"coordinates":[-3.6635663509,40.429107666],"type":"Point"}
}