{
  "type": "Feature",
  "properties": {
    "iso:country":"ES",
    "sg:address":"Calle de Infantas (de Las), 62",
    "sg:city":"Aranjuez",
    "sg:orig_category":"Juegos Y Juguetes (al Por Menor)",
    "sg:phone":"+34 918 92 24 84",
    "sg:postcode":"28300",
    "sg:province":"Madrid",
    "wof:name":"Nieto Fernandez Coral",
    "wof:placetype":"venue"
},
  "geometry": {"coordinates":[-3.5993099213,40.0340156555],"type":"Point"}
}