{
  "type": "Feature",
  "properties": {
    "addr:full":"Avda Goya, 3 Zaragoza Zaragoza 50006",
    "addr:housenumber":"3",
    "addr:postcode":"50006",
    "addr:street":"Avda Goya",
    "iso:country":"ES",
    "sg:address":"Avda Goya, 3",
    "sg:city":"Zaragoza",
    "sg:orig_category":"M\u00c9dicos: Medicina Interna",
    "sg:phone":"+34 976 38 10 14",
    "sg:postcode":"50006",
    "sg:province":"Zaragoza",
    "wof:name":"Rubio Montesinos Luis",
    "wof:placetype":"venue"
},
  "geometry": {"coordinates":[-1.0291110277,41.7223625183],"type":"Point"}
}