{
  "type": "Feature",
  "properties": {
    "addr:full":"Calle de Jacinto Benavente, 28 Torres Cotillas Murcia 30565",
    "addr:housenumber":"28",
    "addr:postcode":"30565",
    "addr:street":"Calle De Jacinto Benavente",
    "iso:country":"ES",
    "sg:address":"Calle de Jacinto Benavente, 28",
    "sg:city":"Torres Cotillas",
    "sg:orig_category":"Centros De Educaci\u00d3n Especial",
    "sg:phone":"+34 968 62 77 66",
    "sg:postcode":"30565",
    "sg:province":"Murcia",
    "wof:name":"Colegio Publico El Parque",
    "wof:placetype":"venue"
},
  "geometry": {"coordinates":[-1.2454990149,38.0257148743],"type":"Point"}
}