{
  "type": "Feature",
  "properties": {
    "addr:full":"Carrer de Santiago Apostol, 70 Hospitalet Llobregat Barcelona 08903",
    "addr:housenumber":"70",
    "addr:postcode":"08903",
    "addr:street":"Carrer De Santiago Apostol",
    "iso:country":"ES",
    "sg:address":"Carrer de Santiago Apostol, 70",
    "sg:city":"Hospitalet Llobregat",
    "sg:orig_category":"Asociaciones, Organismos Culturales Y Socioeducativos",
    "sg:phone":"+34 934 32 28 93",
    "sg:postcode":"08903",
    "sg:province":"Barcelona",
    "wof:name":"Club Esportiu Escola Collblanc-torrassa De L'hospitalet",
    "wof:placetype":"venue"
},
  "geometry": {"coordinates":[2.1242759228,41.3697052002],"type":"Point"}
}