{
  "type": "Feature",
  "properties": {
    "addr:full":"Rond Ciruela, 30 Ciudad Real Ciudad Real 13004",
    "addr:housenumber":"30",
    "addr:postcode":"13004",
    "addr:street":"Rond Ciruela",
    "iso:country":"ES",
    "sg:address":"Rond Ciruela, 30",
    "sg:city":"Ciudad Real",
    "sg:orig_category":"Plomeros",
    "sg:phone":"+34 926 22 08 41",
    "sg:postcode":"13004",
    "sg:province":"Ciudad Real",
    "wof:name":"Ruiz Garcia Francisco",
    "wof:placetype":"venue"
},
  "geometry": {"coordinates":[-3.9301741123,38.9844093323],"type":"Point"}
}