{
  "type": "Feature",
  "properties": {
    "iso:country":"ES",
    "sg:address":"Calle de Altea, 9",
    "sg:city":"Madrid",
    "sg:orig_category":"Contenedores (mercanc\u00cdas)",
    "sg:phone":"+34 914 50 82 90",
    "sg:postcode":"28039",
    "sg:province":"Madrid",
    "wof:name":"Herrero Ramos Enrique",
    "wof:placetype":"venue"
},
  "geometry": {"coordinates":[-3.7156383991,40.4634857178],"type":"Point"}
}