{
  "type": "Feature",
  "properties": {
    "iso:country":"ES",
    "sg:address":"Cruz Caminos, S/n",
    "sg:city":"Esparragal",
    "sg:orig_category":"Asociaciones, Organismos Culturales Y Socioeducativos",
    "sg:phone":"+34 968 85 01 34",
    "sg:postcode":"30163",
    "sg:province":"Murcia",
    "wof:name":"Club Cultural Agricola",
    "wof:placetype":"venue"
},
  "geometry": {"coordinates":[-1.0827640295,38.0387153625],"type":"Point"}
}