{
  "type": "Feature",
  "properties": {
    "addr:full":"Calle de Maimonides, 2 Sevilla Sevilla 41002",
    "addr:housenumber":"2",
    "addr:postcode":"41002",
    "addr:street":"Calle De Maimonides",
    "iso:country":"ES",
    "sg:address":"Calle de Maimonides, 2",
    "sg:city":"Sevilla",
    "sg:orig_category":"Centros De Coordinaci\u00d3n",
    "sg:phone":"+34 954 90 22 00",
    "sg:postcode":"41002",
    "sg:province":"Sevilla",
    "wof:name":"Tacea Martinez Patricia Esther",
    "wof:placetype":"venue"
},
  "geometry": {"coordinates":[-5.991710186,37.4067382812],"type":"Point"}
}