{
  "type": "Feature",
  "properties": {
    "iso:country":"ES",
    "sg:address":"Calle de Pablo Morillo, 31",
    "sg:city":"Zamora",
    "sg:orig_category":"Arreglo, Reparaci\u00d3n, Piezas Sueltas De Televisi\u00d3n, V\u00cddeo, Hi",
    "sg:phone":"+34 980 53 07 26",
    "sg:postcode":"49011",
    "sg:province":"Zamora",
    "wof:name":"Franganillo Gorgojo Angel Jose",
    "wof:placetype":"venue"
},
  "geometry": {"coordinates":[-5.738931179,41.5109329224],"type":"Point"}
}