{
  "type": "Feature",
  "properties": {
    "iso:country":"ES",
    "sg:address":"Calle de Virgen, 14",
    "sg:city":"Valdepe\u00f1as",
    "sg:orig_category":"Peluquer\u00cdas, Peluquer\u00cda Mixta",
    "sg:phone":"+34 926 32 34 53",
    "sg:postcode":"13300",
    "sg:province":"Ciudad Real",
    "wof:name":"Fernandez Martinez Ezequiel",
    "wof:placetype":"venue"
},
  "geometry": {"coordinates":[-3.3872969151,38.7553787231],"type":"Point"}
}