{
  "type": "Feature",
  "properties": {
    "addr:full":"Pase Prado, 26 Madrid Madrid 28014",
    "addr:housenumber":"26",
    "addr:postcode":"madrid;28014",
    "addr:street":"Prado",
    "iso:country":"ES",
    "sg:address":"Pase Prado, 26",
    "sg:city":"Madrid",
    "sg:orig_category":"Farmacias",
    "sg:phone":"+34 914 20 22 63",
    "sg:postcode":"28014",
    "sg:province":"Madrid",
    "wof:name":"Jimenez Alarcon Carmen",
    "wof:placetype":"venue"
},
  "geometry": {"coordinates":[-3.6971399784,40.4152297974],"type":"Point"}
}