{
  "type": "Feature",
  "properties": {
    "addr:full":"Calle de Huerta De Casta\u00d1eda, 38 Madrid Madrid 28011",
    "addr:housenumber":"38",
    "addr:postcode":"madrid;28011",
    "addr:street":"Calle De Huerta De Castan\u0303Eda",
    "iso:country":"ES",
    "sg:address":"Calle de Huerta De Casta\u00d1eda, 38",
    "sg:city":"Madrid",
    "sg:orig_category":"Agencias Y Agentes Comerciales, Representantes",
    "sg:phone":"+34 915 26 18 76",
    "sg:postcode":"28011",
    "sg:province":"Madrid",
    "wof:name":"Representaciones Arellanos S.l.",
    "wof:placetype":"venue"
},
  "geometry": {"coordinates":[-3.7422540188,40.405544281],"type":"Point"}
}