{
  "type": "Feature",
  "properties": {
    "addr:full":"Calle de Alejandro Bell, 11 Zaragoza Zaragoza 50014",
    "addr:housenumber":"11",
    "addr:postcode":"50014",
    "addr:street":"Calle De Alejandro Bell",
    "iso:country":"ES",
    "sg:address":"Calle de Alejandro Bell, 11",
    "sg:city":"Zaragoza",
    "sg:orig_category":"Fiesta: Art\u00cdculos De (al Por Menor)",
    "sg:phone":"+34 976 47 18 48",
    "sg:postcode":"50014",
    "sg:province":"Zaragoza",
    "wof:name":"Productos Fiesta S.a.",
    "wof:placetype":"venue"
},
  "geometry": {"coordinates":[-0.861066103,41.6671905518],"type":"Point"}
}