{
  "type": "Feature",
  "properties": {
    "addr:full":"Avda Europa, 17 Pozuelo De Alarcon Madrid 28224",
    "addr:housenumber":"17",
    "addr:postcode":"28224",
    "addr:street":"Avda Europa",
    "iso:country":"ES",
    "sg:address":"Avda Europa, 17",
    "sg:city":"Pozuelo De Alarcon",
    "sg:orig_category":"Molduras, Junquillos, Listones Y Molduras Perforadas",
    "sg:phone":"+34 913 51 30 41",
    "sg:postcode":"28224",
    "sg:province":"Madrid",
    "wof:name":"Alfran Gimenez S.l.",
    "wof:placetype":"venue"
},
  "geometry": {"coordinates":[-3.7888975143,40.4402351379],"type":"Point"}
}