{
  "type": "Feature",
  "properties": {
    "addr:full":"Rua Valdemos, 21 Raxo Pontevedra 36992",
    "addr:housenumber":"21",
    "addr:postcode":"36992",
    "addr:street":"Rua Valdemos",
    "iso:country":"ES",
    "sg:address":"Rua Valdemos, 21",
    "sg:city":"Raxo",
    "sg:orig_category":"Conservas De Pescados Y Salazones Mar\u00cdtimos (fabricaci\u00d3n, Al Por Mayor)",
    "sg:phone":"+34 986 74 00 08",
    "sg:postcode":"36992",
    "sg:province":"Pontevedra",
    "wof:name":"Rafael Casaponsa Bausili Sa",
    "wof:placetype":"venue"
},
  "geometry": {"coordinates":[-8.6428003311,42.4304618835],"type":"Point"}
}