{
  "type": "Feature",
  "properties": {
    "addr:full":"Carr Calau, 2 Calella Girona 17210",
    "addr:housenumber":"2",
    "addr:postcode":"17210",
    "addr:street":"Carr Calau",
    "iso:country":"ES",
    "sg:address":"Carr Calau, 2",
    "sg:city":"Calella",
    "sg:orig_category":"Electrodom\u00c9sticos (al Por Menor)",
    "sg:phone":"+34 972 61 60 14",
    "sg:postcode":"17210",
    "sg:province":"Girona",
    "wof:name":"Ampurdanesa De Desarrollos Turisticos S.l.",
    "wof:placetype":"venue"
},
  "geometry": {"coordinates":[3.1842868328,41.8884468079],"type":"Point"}
}