{
  "type": "Feature",
  "properties": {
    "iso:country":"ES",
    "sg:address":"Plaz Feria De La, 31",
    "sg:city":"Palmas De Gran Canaria",
    "sg:orig_category":"Empleado Administrativo",
    "sg:phone":"+34 928 23 30 44",
    "sg:postcode":"35003",
    "sg:province":"Las Palmas",
    "wof:name":"Asesoria Gestoria Plaza De La Feria S.l.",
    "wof:placetype":"venue"
},
  "geometry": {"coordinates":[-15.4199867249,28.1103744507],"type":"Point"}
}