{
  "type": "Feature",
  "properties": {
    "addr:full":"Calle de Guillermo Cabrera Infante, S/n Alcala Henares Madrid 28806",
    "addr:postcode":"28806",
    "addr:street":"Calle De Guillermo Cabrera Infante S / N",
    "iso:country":"ES",
    "sg:address":"Calle de Guillermo Cabrera Infante, S/n",
    "sg:city":"Alcala Henares",
    "sg:orig_category":"Supermercados Y Hipermercados",
    "sg:phone":"+34 918 02 15 30",
    "sg:postcode":"28806",
    "sg:province":"Madrid",
    "sg:website":"www.mercadona.es",
    "wof:name":"Mercadona S.a.",
    "wof:placetype":"venue"
},
  "geometry": {"coordinates":[-3.3708043098,40.4994049072],"type":"Point"}
}