{
  "type": "Feature",
  "properties": {
    "addr:full":"Avgd Germanies, De Les, 13 Casco Urbano Valencia 46760",
    "addr:postcode":"46760",
    "addr:street":"Avgd",
    "iso:country":"ES",
    "sg:address":"Avgd Germanies, De Les, 13",
    "sg:city":"Casco Urbano",
    "sg:orig_category":"Ropa Para Se\u00d1oras Y Caballeros (al Por Menor)",
    "sg:phone":"+34 962 83 76 58",
    "sg:postcode":"46760",
    "sg:province":"Valencia",
    "wof:name":"Brines Vercher Amparo",
    "wof:placetype":"venue"
},
  "geometry": {"coordinates":[-0.2594090104,39.0749702454],"type":"Point"}
}