{
  "type": "Feature",
  "properties": {
    "addr:full":"Calle de Plateria, 35 San Bartolome Murcia 30001",
    "addr:housenumber":"35",
    "addr:postcode":"30001",
    "addr:street":"Calle De Plateria",
    "iso:country":"ES",
    "sg:address":"Calle de Plateria, 35",
    "sg:city":"San Bartolome",
    "sg:orig_category":"Alimentaci\u00d3n General (al Por Menor)",
    "sg:phone":"+34 968 21 31 99",
    "sg:postcode":"30001",
    "sg:province":"Murcia",
    "wof:name":"Sanchez-pedre\u00f1o Martinez Juan",
    "wof:placetype":"venue"
},
  "geometry": {"coordinates":[-1.1296190023,37.98595047],"type":"Point"}
}