{
  "type": "Feature",
  "properties": {
    "iso:country":"ES",
    "sg:address":"Carrer de Jaume Juan, 9",
    "sg:city":"Sant Agusti",
    "sg:orig_category":"Fotograf\u00cda Art\u00cdstica Y Retratos",
    "sg:phone":"+34 971 70 34 48",
    "sg:postcode":"07015",
    "sg:province":"Islas Baleares",
    "wof:name":"Font Jaume Miguel",
    "wof:placetype":"venue"
},
  "geometry": {"coordinates":[2.6091389656,39.5536727905],"type":"Point"}
}