{
  "type": "Feature",
  "properties": {
    "iso:country":"ES",
    "sg:address":"Calle de Fundicion (de La), 2",
    "sg:city":"Logro\u00f1o",
    "sg:orig_category":"Ense\u00d1anza: Idiomas",
    "sg:phone":"+34 941 20 63 08",
    "sg:postcode":"26005",
    "sg:province":"La Rioja",
    "wof:name":"Ochoa Espiga Sara",
    "wof:placetype":"venue"
},
  "geometry": {"coordinates":[-2.4522280693,42.4636268616],"type":"Point"}
}