{
  "type": "Feature",
  "properties": {
    "addr:full":"Avda Inmaculada Concepcion, 1 Arroyo De La Miel-benalmadena Costa M\u00e1laga 29631",
    "addr:housenumber":"1",
    "addr:postcode":"29631",
    "addr:street":"Avda Inmaculada Concepcion;Arroyo De La Miel-Benalmadena Costa Ma\u0301Laga",
    "iso:country":"ES",
    "sg:address":"Avda Inmaculada Concepcion, 1",
    "sg:city":"Arroyo De La Miel-benalmadena Costa",
    "sg:orig_category":"Muebles, Minoristas",
    "sg:phone":"+34 952 56 03 91",
    "sg:postcode":"29631",
    "sg:province":"M\u00e1laga",
    "wof:name":"Rokimar Sdad.",
    "wof:placetype":"venue"
},
  "geometry": {"coordinates":[-4.5325288773,36.6004676819],"type":"Point"}
}