{
  "type": "Feature",
  "properties": {
    "addr:full":"Calle de Jesus De Monasterio, 3 Santander Cantabria 39008",
    "addr:housenumber":"3",
    "addr:postcode":"39008",
    "addr:street":"Calle De Jesus De Monasterio",
    "iso:country":"ES",
    "sg:address":"Calle de Jesus De Monasterio, 3",
    "sg:city":"Santander",
    "sg:orig_category":"Abogados",
    "sg:phone":"+34 942 36 47 44",
    "sg:postcode":"39008",
    "sg:province":"Cantabria",
    "wof:name":"Trueba Argui\u00f1arena Leopoldo",
    "wof:placetype":"venue"
},
  "geometry": {"coordinates":[-3.8103353977,43.4615402222],"type":"Point"}
}