{
  "type": "Feature",
  "properties": {
    "addr:full":"Calle de Reyes Catolicos, 11 Palmas De Gran Canaria Las Palmas 35001",
    "addr:housenumber":"11",
    "addr:postcode":"35001",
    "addr:street":"Calle De Reyes Catolicos",
    "iso:country":"ES",
    "sg:address":"Calle de Reyes Catolicos, 11",
    "sg:city":"Palmas De Gran Canaria",
    "sg:orig_category":"Abogados",
    "sg:phone":"+34 928 31 41 77",
    "sg:postcode":"35001",
    "sg:province":"Las Palmas",
    "wof:name":"Afonso Arencbia Lidia Esther",
    "wof:placetype":"venue"
},
  "geometry": {"coordinates":[-15.4138813019,28.0997524261],"type":"Point"}
}