{
  "type": "Feature",
  "properties": {
    "iso:country":"ES",
    "sg:address":"Avda Colon, 132",
    "sg:city":"San Antonio Abad",
    "sg:orig_category":"Imprenta",
    "sg:phone":"+34 968 51 10 31",
    "sg:postcode":"30205",
    "sg:province":"Murcia",
    "wof:name":"Vivancos Costa Salvador Bernardino",
    "wof:placetype":"venue"
},
  "geometry": {"coordinates":[-0.9975132942,37.6201629639],"type":"Point"}
}