{
  "type": "Feature",
  "properties": {
    "iso:country":"ES",
    "sg:address":"Carr Mestre Joan Mayans, 8",
    "sg:city":"Eivissa",
    "sg:orig_category":"Electrodom\u00c9sticos (al Por Menor)",
    "sg:phone":"+34 971 31 14 77",
    "sg:postcode":"07800",
    "sg:province":"Islas Baleares",
    "wof:name":"Garcia Jimenez Jose Ramon",
    "wof:placetype":"venue"
},
  "geometry": {"coordinates":[1.4371999502,38.909450531],"type":"Point"}
}