{
  "type": "Feature",
  "properties": {
    "addr:full":"Avda Lisboa, 8 Alcorcon Madrid 28924",
    "addr:housenumber":"8",
    "addr:postcode":"28924",
    "addr:street":"Avda Lisboa",
    "iso:country":"ES",
    "sg:address":"Avda Lisboa, 8",
    "sg:city":"Alcorcon",
    "sg:orig_category":"Papeler\u00cdas, Librer\u00cdas",
    "sg:phone":"+34 916 11 63 30",
    "sg:postcode":"28924",
    "sg:province":"Madrid",
    "wof:name":"Condado Sacristan Julian",
    "wof:placetype":"venue"
},
  "geometry": {"coordinates":[-3.8186569214,40.35313797],"type":"Point"}
}