{
  "type": "Feature",
  "properties": {
    "iso:country":"ES",
    "sg:address":"Ctra Godelleta, Km. 0003,0",
    "sg:city":"Residencial La Loma",
    "sg:orig_category":"Arquitectos",
    "sg:phone":"+34 961 80 41 81",
    "sg:postcode":"46370",
    "sg:province":"Valencia",
    "wof:name":"Estruch Moran Antonio",
    "wof:placetype":"venue"
},
  "geometry": {"coordinates":[-0.7179690003,39.4728012085],"type":"Point"}
}