{
  "type": "Feature",
  "properties": {
    "addr:full":"Pl Catalunya, S/n Olesa Montserrat Barcelona 08640",
    "addr:housenumber":"s / n",
    "addr:postcode":"08640",
    "addr:street":"Pl Catalunya",
    "iso:country":"ES",
    "sg:address":"Pl Catalunya, S/n",
    "sg:city":"Olesa Montserrat",
    "sg:orig_category":"Congelados: Productos Alimentarios (fabricaci\u00d3n, Al Por Mayor)",
    "sg:phone":"+34 937 78 49 19",
    "sg:postcode":"08640",
    "sg:province":"Barcelona",
    "wof:name":"Naturgel Els Congelats S.l.",
    "wof:placetype":"venue"
},
  "geometry": {"coordinates":[1.8934999704,41.5430831909],"type":"Point"}
}