{
  "type": "Feature",
  "properties": {
    "addr:full":"Calle de Medico Alvarez Mu\u00d1oz, 3 Estepa Sevilla 41560",
    "addr:housenumber":"3",
    "addr:postcode":"41560",
    "addr:street":"Calle De Medico;Mun\u0303Oz;Sevilla",
    "iso:country":"ES",
    "sg:address":"Calle de Medico Alvarez Mu\u00d1oz, 3",
    "sg:city":"Estepa",
    "sg:orig_category":"Abogados",
    "sg:phone":"+34 955 91 42 73",
    "sg:postcode":"41560",
    "sg:province":"Sevilla",
    "wof:name":"Marquez Machuca Gonzalo",
    "wof:placetype":"venue"
},
  "geometry": {"coordinates":[-4.8792920113,37.2921409607],"type":"Point"}
}