{
  "type": "Feature",
  "properties": {
    "addr:full":"Carrer de Terra Baixa, 63 Hospitalet Llobregat Barcelona 08901",
    "addr:housenumber":"63",
    "addr:postcode":"08901",
    "addr:street":"Carrer De Terra Baixa",
    "iso:country":"ES",
    "sg:address":"Carrer de Terra Baixa, 63",
    "sg:city":"Hospitalet Llobregat",
    "sg:orig_category":"Confecci\u00d3n De Ropa Interior",
    "sg:phone":"+34 933 37 30 00",
    "sg:postcode":"08901",
    "sg:province":"Barcelona",
    "wof:name":"Creaciones Mayun S. A.",
    "wof:placetype":"venue"
},
  "geometry": {"coordinates":[2.1138830185,41.366733551],"type":"Point"}
}