{
  "type": "Feature",
  "properties": {
    "addr:full":"Calle de General Diaz Porlier, 26 Madrid Madrid 28001",
    "addr:housenumber":"26",
    "addr:postcode":"madrid;28001",
    "addr:street":"Calle De General Diaz Porlier",
    "iso:country":"ES",
    "sg:address":"Calle de General Diaz Porlier, 26",
    "sg:city":"Madrid",
    "sg:orig_category":"Centros Empresariales",
    "sg:phone":"+34 915 78 48 03",
    "sg:postcode":"28001",
    "sg:province":"Madrid",
    "wof:name":"Bbc Lastres S.l.",
    "wof:placetype":"venue"
},
  "geometry": {"coordinates":[-3.6768710613,40.4270591736],"type":"Point"}
}