{
  "type": "Feature",
  "properties": {
    "iso:country":"ES",
    "sg:address":"Calle de Fuente De La Parrita, 31",
    "sg:city":"Fuente Maestre",
    "sg:orig_category":"Contenedores (mercanc\u00cdas)",
    "sg:phone":"+34 924 53 04 83",
    "sg:postcode":"06360",
    "sg:province":"Badajoz",
    "wof:name":"Vaca Lopez Antonio",
    "wof:placetype":"venue"
},
  "geometry": {"coordinates":[-6.442150116,38.5292739868],"type":"Point"}
}