{
  "type": "Feature",
  "properties": {
    "iso:country":"ES",
    "sg:address":"Carr Poncio Torrellas, S/n",
    "sg:city":"Cabanes",
    "sg:orig_category":"Plomeros",
    "sg:phone":"+34 964 33 10 60",
    "sg:postcode":"12180",
    "sg:province":"Castell\u00f3n",
    "wof:name":"Bonet Sidro Javier",
    "wof:placetype":"venue"
},
  "geometry": {"coordinates":[0.0448350012,40.1544303894],"type":"Point"}
}