{
  "type": "Feature",
  "properties": {
    "addr:full":"Av La Paz, 8 Onil Alicante 03430",
    "addr:housenumber":"8",
    "addr:postcode":"03430",
    "addr:street":"Av La Paz",
    "iso:country":"ES",
    "sg:address":"Av La Paz, 8",
    "sg:city":"Onil",
    "sg:orig_category":"Quincaller\u00cda (al Por Menor)",
    "sg:phone":"+34 966 54 47 53",
    "sg:postcode":"03430",
    "sg:province":"Alicante",
    "wof:name":"Mataix Ferri Ismael",
    "wof:placetype":"venue"
},
  "geometry": {"coordinates":[-0.6753669977,38.6283683777],"type":"Point"}
}