{
  "type": "Feature",
  "properties": {
    "iso:country":"ES",
    "sg:address":"Calle de Ayala, 117",
    "sg:city":"Madrid",
    "sg:orig_category":"Cervecer\u00cdas",
    "sg:phone":"+34 914 01 31 79",
    "sg:postcode":"28009",
    "sg:province":"Madrid",
    "wof:name":"Jimenez Garcia Irenio",
    "wof:placetype":"venue"
},
  "geometry": {"coordinates":[-3.6690969467,40.426990509],"type":"Point"}
}