{
  "type": "Feature",
  "properties": {
    "iso:country":"ES",
    "sg:address":"Avenida De Fraga, 16",
    "sg:city":"Sari\u00f1ena",
    "sg:orig_category":"Laboratorios Y Trabajos De Fotograf\u00cda, V\u00cddeo Y Cine",
    "sg:phone":"+34 974 57 01 03",
    "sg:postcode":"22200",
    "sg:province":"Huesca",
    "wof:name":"Rosendo Lopez Rodes S.l.",
    "wof:placetype":"venue"
},
  "geometry": {"coordinates":[-0.1592289954,41.7914009094],"type":"Point"}
}