{
  "type": "Feature",
  "properties": {
    "addr:full":"Calle de Venezuela, 21 Valencia Valencia 46007",
    "addr:housenumber":"21",
    "addr:postcode":"46007",
    "addr:street":"Calle De Venezuela",
    "iso:country":"ES",
    "sg:address":"Calle de Venezuela, 21",
    "sg:city":"Valencia",
    "sg:orig_category":"Cristaler\u00cdas",
    "sg:phone":"+34 963 77 56 10",
    "sg:postcode":"46007",
    "sg:province":"Valencia",
    "wof:name":"Mu\u00f1oz Hernandorena Andres",
    "wof:placetype":"venue"
},
  "geometry": {"coordinates":[-0.3885119855,39.4556045532],"type":"Point"}
}