{
  "type": "Feature",
  "properties": {
    "addr:full":"Calle de Rodriguez Arias, 63 Bilbao Vizcaya 48013",
    "addr:housenumber":"63",
    "addr:postcode":"48013",
    "addr:street":"Calle De Rodriguez Arias",
    "iso:country":"ES",
    "sg:address":"Calle de Rodriguez Arias, 63",
    "sg:city":"Bilbao",
    "sg:orig_category":"Frutas, Legumbres Frescas Y Tempranas (al Por Menor)",
    "sg:phone":"+34 944 42 02 12",
    "sg:postcode":"48013",
    "sg:province":"Vizcaya",
    "wof:name":"Ayerdi Ria Maria Teresa",
    "wof:placetype":"venue"
},
  "geometry": {"coordinates":[-2.9428162575,43.2635345459],"type":"Point"}
}