{
  "type": "Feature",
  "properties": {
    "iso:country":"ES",
    "sg:address":"Carrer de Ferrer Vidal, S/n",
    "sg:city":"Manresa",
    "sg:orig_category":"Farmacias",
    "sg:phone":"+34 938 75 05 98",
    "sg:postcode":"08241",
    "sg:province":"Barcelona",
    "wof:name":"Vintro Brichfeus Jordi",
    "wof:placetype":"venue"
},
  "geometry": {"coordinates":[1.8155449629,41.7252502441],"type":"Point"}
}