{
  "type": "Feature",
  "properties": {
    "addr:full":"Calle de Huesca, 68 Logro\u00f1o La Rioja 26005",
    "addr:housenumber":"68",
    "addr:postcode":"26005",
    "addr:street":"Calle De Huesca;Rioja",
    "iso:country":"ES",
    "sg:address":"Calle de Huesca, 68",
    "sg:city":"Logro\u00f1o",
    "sg:orig_category":"Mec\u00c1nico Del Autom\u00d3vil",
    "sg:phone":"+34 941 20 14 16",
    "sg:postcode":"26005",
    "sg:province":"La Rioja",
    "wof:name":"Primo Ainse Tomas",
    "wof:placetype":"venue"
},
  "geometry": {"coordinates":[-2.456496954,42.4610099792],"type":"Point"}
}