{
  "type": "Feature",
  "properties": {
    "iso:country":"ES",
    "sg:address":"Carrer de Fe, 41",
    "sg:city":"Palma",
    "sg:orig_category":"Electromec\u00c1nica",
    "sg:phone":"+34 971 24 10 47",
    "sg:postcode":"07007",
    "sg:province":"Islas Baleares",
    "sg:website":"www.mecanizadosmasmiquel.com",
    "wof:name":"Mecanizados Masmiquel S.l.",
    "wof:placetype":"venue"
},
  "geometry": {"coordinates":[2.6691679955,39.5689964294],"type":"Point"}
}