{
  "type": "Feature",
  "properties": {
    "iso:country":"ES",
    "sg:address":"Calle de Puerto De La Cruz Verde, 6",
    "sg:city":"Madrid",
    "sg:orig_category":"Metalurgia",
    "sg:phone":"+34 915 27 92 24",
    "sg:postcode":"28045",
    "sg:province":"Madrid",
    "sg:website":"www.lacasadelosmuelles.com",
    "wof:name":"Espinosa Garcia Ramon",
    "wof:placetype":"venue"
},
  "geometry": {"coordinates":[-3.6873550415,40.3872642517],"type":"Point"}
}