{
  "type": "Feature",
  "properties": {
    "iso:country":"ES",
    "sg:address":"Avda Reyes Catolicos, 18",
    "sg:city":"Alcala Henares",
    "sg:orig_category":"Supermercados Y Hipermercados",
    "sg:phone":"+34 918 80 64 82",
    "sg:postcode":"28802",
    "sg:province":"Madrid",
    "wof:name":"Todymas S. A.",
    "wof:placetype":"venue"
},
  "geometry": {"coordinates":[-3.3752140999,40.4762496948],"type":"Point"}
}