{
  "type": "Feature",
  "properties": {
    "addr:full":"Carrer de Mendez Nu\u00d1ez, 7 Rubi Barcelona 08191",
    "addr:housenumber":"7",
    "addr:postcode":"08191",
    "addr:street":"Carrer De Mendez Nun\u0303Ez",
    "iso:country":"ES",
    "sg:address":"Carrer de Mendez Nu\u00d1ez, 7",
    "sg:city":"Rubi",
    "sg:orig_category":"Panader\u00cdas, Panader\u00cdas",
    "sg:phone":"+34 935 88 71 64",
    "sg:postcode":"08191",
    "sg:province":"Barcelona",
    "wof:name":"Domenech Y Campderros Dicbo S.l",
    "wof:placetype":"venue"
},
  "geometry": {"coordinates":[2.0308361053,41.4887161255],"type":"Point"}
}