{
  "type": "Feature",
  "properties": {
    "iso:country":"ES",
    "sg:address":"Pol Industrial, 20",
    "sg:city":"Alkotz",
    "sg:orig_category":"Alimentaci\u00d3n General (al Por Mayor)",
    "sg:phone":"+34 948 30 66 56",
    "sg:postcode":"31797",
    "sg:province":"Navarra",
    "wof:name":"Piensos Saioa S.l.",
    "wof:placetype":"venue"
},
  "geometry": {"coordinates":[-1.6957390308,42.9793548584],"type":"Point"}
}