{
  "type": "Feature",
  "properties": {
    "iso:country":"ES",
    "sg:address":"Plaz Marquesa De Aracena, 3",
    "sg:city":"Aracena",
    "sg:orig_category":"Telas Y Sedas (al Por Menor)",
    "sg:phone":"+34 959 12 60 66",
    "sg:postcode":"21200",
    "sg:province":"Huelva",
    "wof:name":"Duran Romero Agustin",
    "wof:placetype":"venue"
},
  "geometry": {"coordinates":[-6.5595932007,37.8925819397],"type":"Point"}
}