{
  "type": "Feature",
  "properties": {
    "iso:country":"ES",
    "sg:address":"Poli Vernicha (la), S/n",
    "sg:city":"Vall D'uixo",
    "sg:orig_category":"Promotores Constructores",
    "sg:phone":"+34 964 66 36 72",
    "sg:postcode":"12600",
    "sg:province":"Castell\u00f3n",
    "wof:name":"Construcciones Valcarcel Martin . S.l",
    "wof:placetype":"venue"
},
  "geometry": {"coordinates":[-0.0482099988,39.992477417],"type":"Point"}
}