{
  "type": "Feature",
  "properties": {
    "addr:full":"Calle de Pontevedra, 24 Zaragoza Zaragoza 50007",
    "addr:housenumber":"24",
    "addr:postcode":"50007",
    "addr:street":"Calle De Pontevedra",
    "iso:country":"ES",
    "sg:address":"Calle de Pontevedra, 24",
    "sg:city":"Zaragoza",
    "sg:orig_category":"Quincaller\u00cda (al Por Menor)",
    "sg:phone":"+34 976 27 93 01",
    "sg:postcode":"50007",
    "sg:province":"Zaragoza",
    "wof:name":"Angara S.l.",
    "wof:placetype":"venue"
},
  "geometry": {"coordinates":[-0.8852238059,41.6281166077],"type":"Point"}
}