{
  "type": "Feature",
  "properties": {
    "iso:country":"ES",
    "sg:address":"Calle de Zaragoza, 9",
    "sg:city":"Jaraiz Vera",
    "sg:orig_category":"Droguer\u00cdas (al Por Menor)",
    "sg:phone":"+34 927 46 08 58",
    "sg:postcode":"10400",
    "sg:province":"C\u00e1ceres",
    "wof:name":"Morales Macias Valentin",
    "wof:placetype":"venue"
},
  "geometry": {"coordinates":[-5.7523651123,40.0612335205],"type":"Point"}
}