{
  "type": "Feature",
  "properties": {
    "iso:country":"ES",
    "sg:address":"Pla\u00c7 Constitucion, 18",
    "sg:city":"Massamagrell",
    "sg:orig_category":"Iglesia Cat\u00d3lica",
    "sg:phone":"+34 961 45 11 02",
    "sg:postcode":"46130",
    "sg:province":"Valencia",
    "wof:name":"Parroquia San Juan Evangelista",
    "wof:placetype":"venue"
},
  "geometry": {"coordinates":[-0.3298389912,39.5704917908],"type":"Point"}
}