{
  "type": "Feature",
  "properties": {
    "iso:country":"ES",
    "sg:address":"Carrer de Alvarez De Castro, 30",
    "sg:city":"Hospitalet Llobregat",
    "sg:orig_category":"Artes Gr\u00c1ficas, Artes Pl\u00c1sticas (curso)",
    "sg:phone":"+34 933 37 71 36",
    "sg:postcode":"08901",
    "sg:province":"Barcelona",
    "wof:name":"Arrieta Aymeni Antonio",
    "wof:placetype":"venue"
},
  "geometry": {"coordinates":[2.0946753025,41.3604698181],"type":"Point"}
}