{
  "type": "Feature",
  "properties": {
    "addr:full":"Pla\u00c7 Argentina, 5 Blanes Girona 17300",
    "addr:housenumber":"5",
    "addr:postcode":"17300",
    "addr:street":"Argentina",
    "iso:country":"ES",
    "sg:address":"Pla\u00c7 Argentina, 5",
    "sg:city":"Blanes",
    "sg:orig_category":"Ense\u00d1anza, Formaci\u00d3n Profesional: Aprendizaje",
    "sg:phone":"+34 972 33 61 11",
    "sg:postcode":"17300",
    "sg:province":"Girona",
    "wof:name":"Ajuntament De Blanes",
    "wof:placetype":"venue"
},
  "geometry": {"coordinates":[2.7829604149,41.6922187805],"type":"Point"}
}