{
  "type": "Feature",
  "properties": {
    "iso:country":"ES",
    "sg:address":"Calle de Constitucion, 21",
    "sg:city":"Catadau",
    "sg:orig_category":"Trabajos De Topograf\u00cda",
    "sg:phone":"+34 962 55 10 74",
    "sg:postcode":"46196",
    "sg:province":"Valencia",
    "wof:name":"Mico Alvarez Juan Ricardo",
    "wof:placetype":"venue"
},
  "geometry": {"coordinates":[-0.5716580749,39.2759590149],"type":"Point"}
}