{
  "type": "Feature",
  "properties": {
    "addr:full":"Pla\u00c7 Maestro Palau, 12 Moncada Valencia 46113",
    "addr:housenumber":"12",
    "addr:postcode":"46113",
    "addr:street":"Maestro Palau",
    "iso:country":"ES",
    "sg:address":"Pla\u00c7 Maestro Palau, 12",
    "sg:city":"Moncada",
    "sg:orig_category":"Bibliotecas, Mediatecas",
    "sg:phone":"+34 961 30 34 76",
    "sg:postcode":"46113",
    "sg:province":"Valencia",
    "wof:name":"Parroquia San Jaime Apostol",
    "wof:placetype":"venue"
},
  "geometry": {"coordinates":[-0.3917939961,39.5450401306],"type":"Point"}
}