{
  "type": "Feature",
  "properties": {
    "iso:country":"ES",
    "sg:address":"Av Tudela, 41",
    "sg:city":"Manresa",
    "sg:orig_category":"Cl\u00cdnicas Dentales",
    "sg:phone":"+34 938 77 13 43",
    "sg:postcode":"08242",
    "sg:province":"Barcelona",
    "wof:name":"Clinica Dental Folch-caro S.l.",
    "wof:placetype":"venue"
},
  "geometry": {"coordinates":[1.8167669773,41.731262207],"type":"Point"}
}