{
  "type": "Feature",
  "properties": {
    "addr:full":"Mlle Poniente, S/n Alacant Alicante 03001",
    "addr:housenumber":"s / n",
    "addr:postcode":"03001",
    "addr:street":"Mlle Poniente",
    "iso:country":"ES",
    "sg:address":"Mlle Poniente, S/n",
    "sg:city":"Alacant",
    "sg:orig_category":"Contenedores (mercanc\u00cdas)",
    "sg:phone":"+34 965 12 37 81",
    "sg:postcode":"03001",
    "sg:province":"Alicante",
    "wof:name":"Transportes Quico S.l.",
    "wof:placetype":"venue"
},
  "geometry": {"coordinates":[-0.4804739952,38.3440856934],"type":"Point"}
}