{
  "type": "Feature",
  "properties": {
    "addr:full":"Avda San Diego, 83 Madrid Madrid 28018",
    "addr:housenumber":"83",
    "addr:postcode":"madrid;28018",
    "addr:street":"Avda San Diego",
    "iso:country":"ES",
    "sg:address":"Avda San Diego, 83",
    "sg:city":"Madrid",
    "sg:orig_category":"Molduras, Junquillos, Listones Y Molduras Perforadas",
    "sg:phone":"+34 914 78 76 47",
    "sg:postcode":"28018",
    "sg:province":"Madrid",
    "wof:name":"Iniesta Pereira Luis",
    "wof:placetype":"venue"
},
  "geometry": {"coordinates":[-3.6664299965,40.3855361938],"type":"Point"}
}