{
  "type": "Feature",
  "properties": {
    "addr:full":"Calle de Gran Via, 5 Madrid Madrid 28013",
    "addr:housenumber":"5",
    "addr:postcode":"28013",
    "addr:street":"Calle De Gran Via",
    "iso:country":"ES",
    "sg:address":"Calle de Gran Via, 5",
    "sg:city":"Madrid",
    "sg:classifiers":[
        {
            "category":"Banks & Credit Unions",
            "subcategory":"Bureau De Change",
            "type":"Services"
        }
    ],
    "sg:phone":"+34 915 22 10 77",
    "sg:postcode":"28013",
    "sg:province":"Madrid",
    "sg:tags":[
        "organismos",
        "control"
    ],
    "wof:name":"Burotec Consultoria Tecnica S.l.",
    "wof:placetype":"venue"
},
  "geometry": {"coordinates":[-3.6987628937,40.4193305969],"type":"Point"}
}