{
  "type": "Feature",
  "properties": {
    "iso:country":"ES",
    "sg:address":"Ctra Mairena-brenes, S/n",
    "sg:city":"Mairena Alcor",
    "sg:orig_category":"Bazares, Art\u00cdculos De Limpieza Y De Cocina (al Por Menor)",
    "sg:phone":"+34 955 74 68 22",
    "sg:postcode":"41510",
    "sg:province":"Sevilla",
    "wof:name":"Montesinos Asencio Rafael",
    "wof:placetype":"venue"
},
  "geometry": {"coordinates":[-5.7439141273,37.377117157],"type":"Point"}
}