{
  "type": "Feature",
  "properties": {
    "iso:country":"ES",
    "sg:address":"Avda Comuneros, 37",
    "sg:city":"Salamanca",
    "sg:orig_category":"Peluquer\u00cdas, Peluquer\u00cda Mixta",
    "sg:phone":"+34 923 12 43 48",
    "sg:postcode":"37003",
    "sg:province":"Salamanca",
    "wof:name":"Rubio Sevillano C.b.",
    "wof:placetype":"venue"
},
  "geometry": {"coordinates":[-5.6498208046,40.968460083],"type":"Point"}
}