{
  "type": "Feature",
  "properties": {
    "addr:full":"Plaza Nueva, 10 Albox Almer\u00eda 04800",
    "addr:housenumber":"10",
    "addr:postcode":"04800",
    "addr:street":"Nueva",
    "iso:country":"ES",
    "sg:address":"Plaza Nueva, 10",
    "sg:city":"Albox",
    "sg:orig_category":"Inmobiliaria (agencias)",
    "sg:phone":"+34 950 12 04 06",
    "sg:postcode":"04800",
    "sg:province":"Almer\u00eda",
    "wof:name":"Inmobiliaria Nuestra Se\u00f1ora Del Saliente S.l",
    "wof:placetype":"venue"
},
  "geometry": {"coordinates":[-2.1454439163,37.3878860474],"type":"Point"}
}