{
  "type": "Feature",
  "properties": {
    "iso:country":"ES",
    "sg:address":"Calle de Colon, 16",
    "sg:city":"S. Fernando",
    "sg:orig_category":"Ropa Para Ni\u00d1os (al Por Menor)",
    "sg:phone":"+34 956 59 33 61",
    "sg:postcode":"11100",
    "sg:province":"C\u00e1diz",
    "wof:name":"Rodriguez Ruiz Francisco",
    "wof:placetype":"venue"
},
  "geometry": {"coordinates":[-6.1956129074,36.4683532715],"type":"Point"}
}