{
  "type": "Feature",
  "properties": {
    "addr:full":"Calle de Federico Garcia Lorca, 1 Aldeatejada Salamanca 37187",
    "addr:housenumber":"1",
    "addr:postcode":"37187",
    "addr:street":"Calle De Federico Garcia Lorca",
    "iso:country":"ES",
    "sg:address":"Calle de Federico Garcia Lorca, 1",
    "sg:city":"Aldeatejada",
    "sg:orig_category":"Cerrajer\u00cda, Ferrallista",
    "sg:phone":"+34 923 34 13 28",
    "sg:postcode":"37187",
    "sg:province":"Salamanca",
    "wof:name":"Cerrajeria Caybe",
    "wof:placetype":"venue"
},
  "geometry": {"coordinates":[-5.6834378242,40.8861274719],"type":"Point"}
}