{
  "type": "Feature",
  "properties": {
    "addr:full":"Carr Saragossa, 18 Badalona Barcelona 08912",
    "addr:housenumber":"18",
    "addr:postcode":"08912",
    "addr:street":"Carr Saragossa",
    "iso:country":"ES",
    "sg:address":"Carr Saragossa, 18",
    "sg:city":"Badalona",
    "sg:orig_category":"Internados & Ense\u00d1anza Privada",
    "sg:phone":"+34 933 88 14 47",
    "sg:postcode":"08912",
    "sg:province":"Barcelona",
    "wof:name":"Garriga Martinez Ana",
    "wof:placetype":"venue"
},
  "geometry": {"coordinates":[2.2388980389,41.4456825256],"type":"Point"}
}