{
  "type": "Feature",
  "properties": {
    "addr:full":"Fuentespino, S/n Fuentespino Asturias 33188",
    "addr:postcode":"33188",
    "addr:street":"Fuentespino S / N Fuentespino Asturias",
    "iso:country":"ES",
    "sg:address":"Fuentespino, S/n",
    "sg:city":"Fuentespino",
    "sg:orig_category":"Iglesia Cat\u00d3lica",
    "sg:phone":"+34 985 74 06 92",
    "sg:postcode":"33188",
    "sg:province":"Asturias",
    "wof:name":"Diocesis De Oviedo",
    "wof:placetype":"venue"
},
  "geometry": {"coordinates":[-5.7278189659,43.3858985901],"type":"Point"}
}