{
  "type": "Feature",
  "properties": {
    "addr:full":"Avda Luis Gonzalez Taboada, 5 Lalin Pontevedra 36500",
    "addr:housenumber":"5",
    "addr:postcode":"36500",
    "addr:street":"Avda Luis Gonzalez Taboada",
    "iso:country":"ES",
    "sg:address":"Avda Luis Gonzalez Taboada, 5",
    "sg:city":"Lalin",
    "sg:orig_category":"Supermercados Y Hipermercados",
    "sg:phone":"+34 986 78 00 36",
    "sg:postcode":"36500",
    "sg:province":"Pontevedra",
    "wof:name":"Vego Supermercados S.a.",
    "wof:placetype":"venue"
},
  "geometry": {"coordinates":[-8.1106281281,42.661239624],"type":"Point"}
}