{
  "type": "Feature",
  "properties": {
    "iso:country":"ES",
    "sg:address":"Urb Lunamar, 173",
    "sg:city":"Elviria",
    "sg:orig_category":"Alquiler De Veh\u00cdculos: Turismos Y Utilitarios",
    "sg:phone":"+34 952 83 06 09",
    "sg:postcode":"29604",
    "sg:province":"M\u00e1laga",
    "wof:name":"Lomoza Forever S.l.",
    "wof:placetype":"venue"
},
  "geometry": {"coordinates":[-4.7747840881,36.4966812134],"type":"Point"}
}