{
  "type": "Feature",
  "properties": {
    "addr:full":"De Arriba, 8 Quintanilla Coco Burgos 09348",
    "addr:housenumber":"8",
    "addr:postcode":"09348",
    "addr:street":"Arriba",
    "iso:country":"ES",
    "sg:address":"De Arriba, 8",
    "sg:city":"Quintanilla Coco",
    "sg:orig_category":"Importaci\u00d3n",
    "sg:phone":"+34 947 56 93 39",
    "sg:postcode":"09348",
    "sg:province":"Burgos",
    "wof:name":"Gutierrez Exporci S.l.",
    "wof:placetype":"venue"
},
  "geometry": {"coordinates":[-3.5171079636,41.9781951904],"type":"Point"}
}