{
  "type": "Feature",
  "properties": {
    "addr:full":"Avda Salvador De Madariaga, 44 Coru\u00d1a La Coru\u00f1a 15008",
    "addr:housenumber":"44",
    "addr:postcode":"15008",
    "addr:street":"Avda Salvador De Madariaga;Corun\u0303A",
    "iso:country":"ES",
    "sg:address":"Avda Salvador De Madariaga, 44",
    "sg:city":"Coru\u00d1a",
    "sg:orig_category":"Estancos",
    "sg:phone":"+34 981 28 29 94",
    "sg:postcode":"15008",
    "sg:province":"La Coru\u00f1a",
    "wof:name":"Peteiro Ramos Jose",
    "wof:placetype":"venue"
},
  "geometry": {"coordinates":[-8.4069318771,43.3454284668],"type":"Point"}
}