{
  "type": "Feature",
  "properties": {
    "iso:country":"ES",
    "sg:address":"Av. Asturias, 4",
    "sg:city":"Miranda",
    "sg:orig_category":"Cr\u00cda De Animales",
    "sg:phone":"+34 985 54 63 70",
    "sg:postcode":"33401",
    "sg:province":"Asturias",
    "wof:name":"Granda Fidalgo Maria Teresa",
    "wof:placetype":"venue"
},
  "geometry": {"coordinates":[-5.9211349487,43.5584754944],"type":"Point"}
}