{
  "type": "Feature",
  "properties": {
    "iso:country":"ES",
    "sg:address":"Ctra. Trassierra, S/n",
    "sg:city":"Castillo Albaida",
    "sg:orig_category":"Cr\u00cda De Animales",
    "sg:phone":"+34 957 28 05 02",
    "sg:postcode":"14011",
    "sg:province":"C\u00f3rdoba",
    "wof:name":"Ganados Molina C.b",
    "wof:placetype":"venue"
},
  "geometry": {"coordinates":[-4.8999910355,37.9277877808],"type":"Point"}
}