{
  "type": "Feature",
  "properties": {
    "addr:full":"Plaz Republica Argentina, 1 Ponferrada Le\u00f3n 24400",
    "addr:housenumber":"1",
    "addr:postcode":"24400",
    "addr:street":"Argentina",
    "iso:country":"ES",
    "sg:address":"Plaz Republica Argentina, 1",
    "sg:city":"Ponferrada",
    "sg:orig_category":"Tintes (fabricaci\u00d3n, Al Por Mayor)",
    "sg:phone":"+34 987 41 13 24",
    "sg:postcode":"24400",
    "sg:province":"Le\u00f3n",
    "wof:name":"Cuellas Gonzalez Alfredo",
    "wof:placetype":"venue"
},
  "geometry": {"coordinates":[-6.6004910469,42.5483856201],"type":"Point"}
}