{
  "type": "Feature",
  "properties": {
    "iso:country":"ES",
    "sg:address":"Rond Sant Pere, 7",
    "sg:city":"Barcelona",
    "sg:orig_category":"Embajadas, Consulados Y Otras Representaciones Diplom\u00c1ticas",
    "sg:phone":"+34 933 18 81 50",
    "sg:postcode":"08010",
    "sg:province":"Barcelona",
    "wof:name":"Consulado General De Portugal",
    "wof:placetype":"venue"
},
  "geometry": {"coordinates":[2.170883894,41.3883972168],"type":"Point"}
}