{
  "type": "Feature",
  "properties": {
    "iso:country":"ES",
    "sg:address":"Ctra Irun (de), Km. 0014,5",
    "sg:city":"Alcobendas",
    "sg:orig_category":"Bisuter\u00cda, Joyer\u00cda, Relojer\u00cda (al Por Menor)",
    "sg:phone":"+34 916 62 01 39",
    "sg:postcode":"28108",
    "sg:province":"Madrid",
    "wof:name":"Moraleda Campos Jose Luis",
    "wof:placetype":"venue"
},
  "geometry": {"coordinates":[-3.6225941181,40.5358009338],"type":"Point"}
}