{
  "type": "Feature",
  "properties": {
    "iso:country":"ES",
    "sg:address":"Carr Pau Piferrer, 7",
    "sg:city":"Badalona",
    "sg:orig_category":"Inmobiliaria (agencias)",
    "sg:phone":"+34 934 60 40 41",
    "sg:postcode":"08914",
    "sg:province":"Barcelona",
    "wof:name":"Flat Fincas Grupo Inmobiliario S.l.",
    "wof:placetype":"venue"
},
  "geometry": {"coordinates":[2.2240591049,41.4430122375],"type":"Point"}
}