{
  "type": "Feature",
  "properties": {
    "addr:full":"Ctra Hiniesta, 109 Zamora Zamora 49025",
    "addr:housenumber":"109",
    "addr:postcode":"49025",
    "addr:street":"Ctra Hiniesta",
    "iso:country":"ES",
    "sg:address":"Ctra Hiniesta, 109",
    "sg:city":"Zamora",
    "sg:orig_category":"Farmacias",
    "sg:phone":"+34 980 51 15 60",
    "sg:postcode":"49025",
    "sg:province":"Zamora",
    "wof:name":"Gonzalez Hierro Francisco Javier",
    "wof:placetype":"venue"
},
  "geometry": {"coordinates":[-5.7536392212,41.5116081238],"type":"Point"}
}