{
  "type": "Feature",
  "properties": {
    "addr:full":"Iturrama, 8 Iru\u00f1a Navarra 31007",
    "addr:housenumber":"8",
    "addr:postcode":"31007",
    "addr:street":"Iturrama",
    "iso:country":"ES",
    "sg:address":"Iturrama, 8",
    "sg:city":"Iru\u00f1a",
    "sg:orig_category":"Ense\u00d1anza: Idiomas",
    "sg:phone":"+34 948 17 26 38",
    "sg:postcode":"31007",
    "sg:province":"Navarra",
    "wof:name":"Yes-english S.l.",
    "wof:placetype":"venue"
},
  "geometry": {"coordinates":[-1.6508387327,42.8042602539],"type":"Point"}
}