{
  "type": "Feature",
  "properties": {
    "addr:full":"Plaz Espa\u00d1a, S/n Carpio Tajo Toledo 45533",
    "addr:housenumber":"s / n",
    "addr:postcode":"45533",
    "addr:street":"Plaz Espan\u0303A",
    "iso:country":"ES",
    "sg:address":"Plaz Espa\u00d1a, S/n",
    "sg:city":"Carpio Tajo",
    "sg:orig_category":"Iglesia Cat\u00d3lica",
    "sg:phone":"+34 925 75 70 10",
    "sg:postcode":"45533",
    "sg:province":"Toledo",
    "wof:name":"Parroquia San Miguel Arcangel",
    "wof:placetype":"venue"
},
  "geometry": {"coordinates":[-4.4543619156,39.8877754211],"type":"Point"}
}