{
  "type": "Feature",
  "properties": {
    "iso:country":"ES",
    "sg:address":"Ctra. Malaga, Km. 0212,5",
    "sg:city":"Moraleda Zafayona",
    "sg:orig_category":"Florister\u00cdas",
    "sg:phone":"+34 958 49 71 03",
    "sg:postcode":"18370",
    "sg:province":"Granada",
    "wof:name":"Expo Jardin S.l.l.",
    "wof:placetype":"venue"
},
  "geometry": {"coordinates":[-3.9661040306,37.1709251404],"type":"Point"}
}