{
  "type": "Feature",
  "properties": {
    "addr:full":"Calle de Tamarindos, 25 Cadiz C\u00e1diz 11007",
    "addr:housenumber":"25",
    "addr:postcode":"11007",
    "addr:street":"Calle De Tamarindos",
    "iso:country":"ES",
    "sg:address":"Calle de Tamarindos, 25",
    "sg:city":"Cadiz",
    "sg:orig_category":"Dietistas",
    "sg:phone":"+34 956 22 02 98",
    "sg:postcode":"11007",
    "sg:province":"C\u00e1diz",
    "wof:name":"Escobar Jimenez Luis",
    "wof:placetype":"venue"
},
  "geometry": {"coordinates":[-6.2844691277,36.5249786377],"type":"Point"}
}