{
  "type": "Feature",
  "properties": {
    "addr:full":"Calle de Ledesma, 7 Salamanca Salamanca 37007",
    "addr:housenumber":"7",
    "addr:postcode":"37007",
    "addr:street":"Calle De Ledesma",
    "iso:country":"ES",
    "sg:address":"Calle de Ledesma, 7",
    "sg:city":"Salamanca",
    "sg:orig_category":"Agencias Y Agentes Comerciales, Representantes",
    "sg:phone":"+34 923 23 35 17",
    "sg:postcode":"37007",
    "sg:province":"Salamanca",
    "wof:name":"Perin Dudes Rafael",
    "wof:placetype":"venue"
},
  "geometry": {"coordinates":[-5.6681079865,40.971912384],"type":"Point"}
}