{
  "type": "Feature",
  "properties": {
    "addr:full":"Calle de Miranda, 4 Burgos Burgos 09002",
    "addr:housenumber":"4",
    "addr:postcode":"09002",
    "addr:street":"Calle De Miranda",
    "iso:country":"ES",
    "sg:address":"Calle de Miranda, 4",
    "sg:city":"Burgos",
    "sg:orig_category":"Autob\u00das (explotaci\u00d3n Y Servicios De)",
    "sg:phone":"+34 947 26 89 95",
    "sg:postcode":"09002",
    "sg:province":"Burgos",
    "wof:name":"Automoviles La Serrana S. L.",
    "wof:placetype":"venue"
},
  "geometry": {"coordinates":[-3.701253891,42.3381881714],"type":"Point"}
}