{
  "type": "Feature",
  "properties": {
    "iso:country":"ES",
    "sg:address":"Calle de Uribitarte, 5",
    "sg:city":"Bilbao",
    "sg:orig_category":"Arquitectos",
    "sg:phone":"+34 944 24 15 18",
    "sg:postcode":"48001",
    "sg:province":"Vizcaya",
    "wof:name":"Paja Fano Manuel",
    "wof:placetype":"venue"
},
  "geometry": {"coordinates":[-2.9273548126,43.2639579773],"type":"Point"}
}