{
  "type": "Feature",
  "properties": {
    "addr:full":"Calle de Narciso Martinez Cabezas, 26 Estacion Madrid 28400",
    "addr:housenumber":"26 estacion",
    "addr:postcode":"28400",
    "addr:street":"Calle De Narciso Martinez Cabezas",
    "iso:country":"ES",
    "sg:address":"Calle de Narciso Martinez Cabezas, 26",
    "sg:city":"Estacion",
    "sg:orig_category":"Fotocopias, Reprograf\u00cda",
    "sg:phone":"+34 918 51 14 63",
    "sg:postcode":"28400",
    "sg:province":"Madrid",
    "wof:name":"Reprografia Roal S.l.",
    "wof:placetype":"venue"
},
  "geometry": {"coordinates":[-3.9919650555,40.6455612183],"type":"Point"}
}