{
  "type": "Feature",
  "properties": {
    "iso:country":"ES",
    "sg:address":"Aranzubi Kalea, 2",
    "sg:city":"Urnieta",
    "sg:orig_category":"Frutas, Legumbres Frescas Y Tempranas (al Por Menor)",
    "sg:phone":"+34 943 33 15 57",
    "sg:postcode":"20130",
    "sg:province":"Guip\u00f9zcoa",
    "wof:name":"Eko-tolosa S.l.",
    "wof:placetype":"venue"
},
  "geometry": {"coordinates":[-1.9916349649,43.2457809448],"type":"Point"}
}