{
  "type": "Feature",
  "properties": {
    "addr:full":"Avda Torrelaguna (de), 27 Azuqueca Henares Guadalajara 19200",
    "addr:housenumber":"27",
    "addr:postcode":"19200",
    "addr:street":"Avda Torrelaguna De",
    "iso:country":"ES",
    "sg:address":"Avda Torrelaguna (de), 27",
    "sg:city":"Azuqueca Henares",
    "sg:orig_category":"Cajas De Ahorro",
    "sg:phone":"+34 949 27 72 45",
    "sg:postcode":"19200",
    "sg:province":"Guadalajara",
    "wof:name":"Caja De Ahorros De Valencia Castellon Y Alicante",
    "wof:placetype":"venue"
},
  "geometry": {"coordinates":[-3.2653489113,40.565486908],"type":"Point"}
}