{
  "type": "Feature",
  "properties": {
    "addr:full":"Rua Manolo Martinez, 13 Vigo Pontevedra 36210",
    "addr:housenumber":"13",
    "addr:postcode":"36210",
    "addr:street":"Rua Manolo Martinez",
    "iso:country":"ES",
    "sg:address":"Rua Manolo Martinez, 13",
    "sg:city":"Vigo",
    "sg:orig_category":"Molduras, Junquillos, Listones Y Molduras Perforadas",
    "sg:phone":"+34 986 23 57 83",
    "sg:postcode":"36210",
    "sg:province":"Pontevedra",
    "wof:name":"Gomez Fernandez Gonzalo",
    "wof:placetype":"venue"
},
  "geometry": {"coordinates":[-8.7337341309,42.2190513611],"type":"Point"}
}