{
  "type": "Feature",
  "properties": {
    "addr:full":"Calle de Alfonso X El Sabio, 42 Parla Madrid 28980",
    "addr:housenumber":"42",
    "addr:postcode":"28980",
    "addr:street":"Calle De Alfonso X El Sabio",
    "iso:country":"ES",
    "sg:address":"Calle de Alfonso X El Sabio, 42",
    "sg:city":"Parla",
    "sg:orig_category":"Peluquer\u00cdas, Peluquer\u00cda Mixta",
    "sg:phone":"+34 916 98 26 49",
    "sg:postcode":"28980",
    "sg:province":"Madrid",
    "wof:name":"Nieto Bahamonde Belen",
    "wof:placetype":"venue"
},
  "geometry": {"coordinates":[-3.7674369812,40.2316017151],"type":"Point"}
}