{
  "type": "Feature",
  "properties": {
    "addr:full":"Calle de Alfonso Vi, S/n Cebreros \u00c1vila 05260",
    "addr:housenumber":"s / n",
    "addr:postcode":"05260",
    "addr:street":"Calle De Alfonso Vi",
    "iso:country":"ES",
    "sg:address":"Calle de Alfonso Vi, S/n",
    "sg:city":"Cebreros",
    "sg:orig_category":"Transporte En General",
    "sg:phone":"+34 918 63 01 06",
    "sg:postcode":"05260",
    "sg:province":"\u00c1vila",
    "wof:name":"Hermanos Gonzalez Rosado S.l.",
    "wof:placetype":"venue"
},
  "geometry": {"coordinates":[-4.4638252258,40.4540557861],"type":"Point"}
}