{
  "type": "Feature",
  "properties": {
    "addr:full":"Pase San Vicente, 16 Salamanca Salamanca 37007",
    "addr:housenumber":"16",
    "addr:postcode":"37007",
    "addr:street":"San Vicente",
    "iso:country":"ES",
    "sg:address":"Pase San Vicente, 16",
    "sg:city":"Salamanca",
    "sg:orig_category":"Empresarios",
    "sg:phone":"+34 923 26 12 52",
    "sg:postcode":"37007",
    "sg:province":"Salamanca",
    "wof:name":"Elros V S. L.",
    "wof:placetype":"venue"
},
  "geometry": {"coordinates":[-5.6730461121,40.9630584717],"type":"Point"}
}