{
  "type": "Feature",
  "properties": {
    "addr:full":"Calle de Nueve De Octubre, 7 Aspe Alicante 03680",
    "addr:housenumber":"7",
    "addr:postcode":"03680",
    "addr:street":"Calle De Nueve De Octubre",
    "iso:country":"ES",
    "sg:address":"Calle de Nueve De Octubre, 7",
    "sg:city":"Aspe",
    "sg:orig_category":"Bebidas",
    "sg:phone":"+34 965 49 01 92",
    "sg:postcode":"03680",
    "sg:province":"Alicante",
    "wof:name":"Llopis Boyer Ramon",
    "wof:placetype":"venue"
},
  "geometry": {"coordinates":[-0.7649521232,38.3458976746],"type":"Point"}
}