{
  "type": "Feature",
  "properties": {
    "addr:full":"Avda Vista De La, S/n Benalmadena M\u00e1laga 29639",
    "addr:postcode":"29639",
    "addr:street":"Avda Vista De La S / N;Ma\u0301Laga",
    "iso:country":"ES",
    "sg:address":"Avda Vista De La, S/n",
    "sg:city":"Benalmadena",
    "sg:orig_category":"Pantallas, Mamparas Y Accesorios (fabricaci\u00d3n)",
    "sg:phone":"+34 952 56 83 42",
    "sg:postcode":"29639",
    "sg:province":"M\u00e1laga",
    "wof:name":"Del Grosso Degola Maria Alejandra",
    "wof:placetype":"venue"
},
  "geometry": {"coordinates":[-4.5676450729,36.5964622498],"type":"Point"}
}