{
  "type": "Feature",
  "properties": {
    "iso:country":"ES",
    "sg:address":"Calle de Exacta (de La), 15",
    "sg:city":"Pinto",
    "sg:orig_category":"Comercio De Piezas De Recambio Y De Accesorios De Veh\u00cdculos, Veh\u00cdculos Industriales",
    "sg:phone":"+34 916 91 55 72",
    "sg:postcode":"28320",
    "sg:province":"Madrid",
    "wof:name":"Europea De Accesorios Y Recambios S.a.",
    "wof:placetype":"venue"
},
  "geometry": {"coordinates":[-3.6945335865,40.2455978394],"type":"Point"}
}