{
  "type": "Feature",
  "properties": {
    "iso:country":"ES",
    "sg:address":"Calle de Angel Barajas, 1",
    "sg:city":"Pozuelo De Alarcon",
    "sg:orig_category":"Florister\u00cdas",
    "sg:phone":"+34 917 15 29 59",
    "sg:postcode":"28224",
    "sg:province":"Madrid",
    "wof:name":"R Y R Floristas S.l.",
    "wof:placetype":"venue"
},
  "geometry": {"coordinates":[-3.8019046783,40.4456787109],"type":"Point"}
}