{
  "type": "Feature",
  "properties": {
    "addr:full":"Calle de Perchel, 4 Capileira Granada 18413",
    "addr:housenumber":"4",
    "addr:postcode":"18413",
    "addr:street":"Calle De Perchel",
    "iso:country":"ES",
    "sg:address":"Calle de Perchel, 4",
    "sg:city":"Capileira",
    "sg:orig_category":"Albergues",
    "sg:phone":"+34 958 76 30 25",
    "sg:postcode":"18413",
    "sg:province":"Granada",
    "wof:name":"Robles Puga Eduardo",
    "wof:placetype":"venue"
},
  "geometry": {"coordinates":[-3.3578410149,36.9596786499],"type":"Point"}
}