{
  "type": "Feature",
  "properties": {
    "iso:country":"ES",
    "sg:address":"Calle de Francisco Ramos, 95",
    "sg:city":"Cuesta",
    "sg:orig_category":"Tapicer\u00cdas",
    "sg:phone":"+34 922 64 25 57",
    "sg:postcode":"38320",
    "sg:province":"Santa Cruz De Tenerife",
    "wof:name":"Tapizados La Cuesta",
    "wof:placetype":"venue"
},
  "geometry": {"coordinates":[-16.2838191986,28.4732398987],"type":"Point"}
}