{
  "type": "Feature",
  "properties": {
    "addr:full":"Avda Ciudad Almeria, 206 Nonduermas Murcia 30166",
    "addr:housenumber":"206",
    "addr:postcode":"30166",
    "addr:street":"Avda Ciudad",
    "iso:country":"ES",
    "sg:address":"Avda Ciudad Almeria, 206",
    "sg:city":"Nonduermas",
    "sg:orig_category":"Promotores Constructores",
    "sg:phone":"+34 968 34 52 72",
    "sg:postcode":"30166",
    "sg:province":"Murcia",
    "wof:name":"Menchon S.l.",
    "wof:placetype":"venue"
},
  "geometry": {"coordinates":[-1.1673840284,37.9729614258],"type":"Point"}
}