{
  "type": "Feature",
  "properties": {
    "addr:full":"Calle de Ronda, 16 Algodonales C\u00e1diz 11680",
    "addr:housenumber":"16",
    "addr:postcode":"11680",
    "addr:street":"Calle De Ronda",
    "iso:country":"ES",
    "sg:address":"Calle de Ronda, 16",
    "sg:city":"Algodonales",
    "sg:orig_category":"Notarios",
    "sg:phone":"+34 956 13 71 36",
    "sg:postcode":"11680",
    "sg:province":"C\u00e1diz",
    "wof:name":"Furrasola Gonzalez Juan Ramon",
    "wof:placetype":"venue"
},
  "geometry": {"coordinates":[-5.4053659439,36.8799324036],"type":"Point"}
}