{
  "type": "Feature",
  "properties": {
    "iso:country":"ES",
    "sg:address":"Barr Fuentona (la), 61",
    "sg:city":"Veguilla",
    "sg:orig_category":"Hielo Artificial (fabricaci\u00d3n, Distribuci\u00d3n)",
    "sg:phone":"+34 942 82 13 42",
    "sg:postcode":"39538",
    "sg:province":"Cantabria",
    "wof:name":"Escudero Martin Gerardo",
    "wof:placetype":"venue"
},
  "geometry": {"coordinates":[-4.0969400406,43.3434638977],"type":"Point"}
}