{
  "type": "Feature",
  "properties": {
    "addr:full":"Calle de Puerto De La Espina, 3 Gijon Asturias 33207",
    "addr:housenumber":"3",
    "addr:postcode":"33207",
    "addr:street":"Calle De Puerto De La Espina",
    "iso:country":"ES",
    "sg:address":"Calle de Puerto De La Espina, 3",
    "sg:city":"Gijon",
    "sg:orig_category":"Supermercados Y Hipermercados",
    "sg:phone":"+34 985 99 06 90",
    "sg:postcode":"33207",
    "sg:province":"Asturias",
    "wof:name":"Supercor S.a.",
    "wof:placetype":"venue"
},
  "geometry": {"coordinates":[-5.6720895767,43.5325660706],"type":"Point"}
}