{
  "type": "Feature",
  "properties": {
    "iso:country":"ES",
    "sg:address":"Calle de Nuestra Se\u00d1ora Del Rosario, 2",
    "sg:city":"Mimetiz",
    "sg:orig_category":"Iglesia Cat\u00d3lica",
    "sg:phone":"+34 946 39 02 28",
    "sg:postcode":"48860",
    "sg:province":"Vizcaya",
    "wof:name":"Parroquia De San Miguel Arcangel",
    "wof:placetype":"venue"
},
  "geometry": {"coordinates":[-3.1296989918,43.2133483887],"type":"Point"}
}