{
  "type": "Feature",
  "properties": {
    "addr:full":"Calle de Padre Villoslada, 1 Villacarrillo Ja\u00e9n 23300",
    "addr:housenumber":"1",
    "addr:postcode":"23300",
    "addr:street":"Calle De Padre Villoslada;Jae\u0301N",
    "iso:country":"ES",
    "sg:address":"Calle de Padre Villoslada, 1",
    "sg:city":"Villacarrillo",
    "sg:orig_category":"Internados & Ense\u00d1anza Privada",
    "sg:phone":"+34 953 44 08 77",
    "sg:postcode":"23300",
    "sg:province":"Ja\u00e9n",
    "wof:name":"Escuelas Profesionales Sagrada Familia",
    "wof:placetype":"venue"
},
  "geometry": {"coordinates":[-3.0807509422,38.1169242859],"type":"Point"}
}