{
  "type": "Feature",
  "properties": {
    "addr:full":"Av Gaspar Bennazar, 54 Palma Islas Baleares 07004",
    "addr:housenumber":"54",
    "addr:postcode":"07004",
    "addr:street":"Av Gaspar Bennazar",
    "iso:country":"ES",
    "sg:address":"Av Gaspar Bennazar, 54",
    "sg:city":"Palma",
    "sg:orig_category":"Televisi\u00d3n, V\u00cddeo: Aparatos Y Accesorios (venta)",
    "sg:phone":"+34 971 75 53 41",
    "sg:postcode":"07004",
    "sg:province":"Islas Baleares",
    "wof:name":"Francisco Mu\u00f1oz Lopez Y Otros Cdad.",
    "wof:placetype":"venue"
},
  "geometry": {"coordinates":[2.6552760601,39.584072113],"type":"Point"}
}