{
  "type": "Feature",
  "properties": {
    "iso:country":"ES",
    "sg:address":"Major, 135",
    "sg:city":"Almacelles",
    "sg:orig_category":"T\u00c9cnicos Veterinarios",
    "sg:phone":"+34 973 74 18 90",
    "sg:postcode":"25100",
    "sg:province":"Lleida",
    "wof:name":"Centre Veterinari De Almacelles S.l.",
    "wof:placetype":"venue"
},
  "geometry": {"coordinates":[0.4432899952,41.7261390686],"type":"Point"}
}