{
  "type": "Feature",
  "properties": {
    "addr:full":"Cabezo Cortado, S/n Espinardo Murcia 30100",
    "addr:housenumber":"s / n",
    "addr:postcode":"30100",
    "iso:country":"ES",
    "sg:address":"Cabezo Cortado, S/n",
    "sg:city":"Espinardo",
    "sg:orig_category":"Maquinaria Para Industrias Diversas",
    "sg:phone":"+34 968 83 03 62",
    "sg:postcode":"30100",
    "sg:province":"Murcia",
    "wof:name":"Jesus Alcatud S.a.",
    "wof:placetype":"venue"
},
  "geometry": {"coordinates":[-1.1565090418,38.0138816833],"type":"Point"}
}