{
  "type": "Feature",
  "properties": {
    "addr:full":"G.v. Carles Iii, 65 Barcelona Barcelona 08028",
    "addr:housenumber":"65",
    "addr:postcode":"08028",
    "iso:country":"ES",
    "sg:address":"G.v. Carles Iii, 65",
    "sg:city":"Barcelona",
    "sg:orig_category":"Importaci\u00d3n",
    "sg:phone":"+34 934 90 99 71",
    "sg:postcode":"08028",
    "sg:province":"Barcelona",
    "wof:name":"Agrimares S.l.",
    "wof:placetype":"venue"
},
  "geometry": {"coordinates":[2.1273670197,41.3840370178],"type":"Point"}
}