{
  "type": "Feature",
  "properties": {
    "iso:country":"ES",
    "sg:address":"Calle de Salazar, 12",
    "sg:city":"Archidona",
    "sg:orig_category":"Droguer\u00cdas (al Por Menor)",
    "sg:phone":"+34 952 71 44 84",
    "sg:postcode":"29300",
    "sg:province":"M\u00e1laga",
    "wof:name":"Cordoba Cordoba Joaquin",
    "wof:placetype":"venue"
},
  "geometry": {"coordinates":[-4.3908400536,37.095500946],"type":"Point"}
}