{
  "type": "Feature",
  "properties": {
    "addr:full":"Avda Castilla La Mancha, 41 Illescas Toledo 45200",
    "addr:housenumber":"41",
    "addr:postcode":"45200",
    "addr:street":"Avda Castilla La Mancha",
    "iso:country":"ES",
    "sg:address":"Avda Castilla La Mancha, 41",
    "sg:city":"Illescas",
    "sg:orig_category":"Servicios Gsm",
    "sg:phone":"+34 925 51 38 60",
    "sg:postcode":"45200",
    "sg:province":"Toledo",
    "wof:name":"Informatica Y Telefonia Iris S.l.",
    "wof:placetype":"venue"
},
  "geometry": {"coordinates":[-3.8459351063,40.1230163574],"type":"Point"}
}