{
  "type": "Feature",
  "properties": {
    "addr:full":"Calle de Albarizuela, 32 Osuna Sevilla 41640",
    "addr:housenumber":"32",
    "addr:postcode":"41640",
    "addr:street":"Calle De Albarizuela",
    "iso:country":"ES",
    "sg:address":"Calle de Albarizuela, 32",
    "sg:city":"Osuna",
    "sg:orig_category":"Supermercados Y Hipermercados",
    "sg:phone":"+34 954 81 19 72",
    "sg:postcode":"41640",
    "sg:province":"Sevilla",
    "wof:name":"Hermanos Cardenas Y Gallego Sc",
    "wof:placetype":"venue"
},
  "geometry": {"coordinates":[-5.1056447029,37.232925415],"type":"Point"}
}