{
  "type": "Feature",
  "properties": {
    "iso:country":"ES",
    "sg:address":"Calle de Bernia, 3",
    "sg:city":"Valencia",
    "sg:orig_category":"Edici\u00d3n De Diarios, Revistas, Boletines",
    "sg:phone":"+34 963 74 34 20",
    "sg:postcode":"46013",
    "sg:province":"Valencia",
    "wof:name":"Cambrigde Universsity Press Sucursal En Espa\u00d1a",
    "wof:placetype":"venue"
},
  "geometry": {"coordinates":[-0.3717882931,39.4547309875],"type":"Point"}
}