{
  "type": "Feature",
  "properties": {
    "addr:full":"C/ Clemente Gonzalvez Valls, 13 Elche Alicante 03202",
    "addr:housenumber":"13",
    "addr:postcode":"03202",
    "addr:street":"C / Clemente Gonzalvez Valls",
    "iso:country":"ES",
    "sg:address":"C/ Clemente Gonzalvez Valls, 13",
    "sg:city":"Elche",
    "sg:orig_category":"Quincaller\u00cda (al Por Menor)",
    "sg:phone":"+34 965 42 14 06",
    "sg:postcode":"03202",
    "sg:province":"Alicante",
    "wof:name":"Alberola Nu\u00f1ez Raul",
    "wof:placetype":"venue"
},
  "geometry": {"coordinates":[-0.6862322092,38.2718505859],"type":"Point"}
}