{
  "type": "Feature",
  "properties": {
    "addr:full":"Bda. Las Abiertas, S/n Las Abiertas C\u00e1diz 11630",
    "addr:housenumber":"/ n",
    "addr:postcode":"11630",
    "addr:street":"Abiertas S;Abiertas Ca\u0301Diz",
    "iso:country":"ES",
    "sg:address":"Bda. Las Abiertas, S/n",
    "sg:city":"Las Abiertas",
    "sg:orig_category":"Mataderos Y Talleres De Despiezado",
    "sg:phone":"+34 956 23 11 63",
    "sg:postcode":"11630",
    "sg:province":"C\u00e1diz",
    "wof:name":"Carnicas Las Abiertas S.l.u.",
    "wof:placetype":"venue"
},
  "geometry": {"coordinates":[-5.8115739822,36.7515716553],"type":"Point"}
}