{
  "type": "Feature",
  "properties": {
    "iso:country":"ES",
    "sg:address":"Calle de Beatriz De Silva, S/n",
    "sg:city":"Ceuta",
    "sg:orig_category":"Comunidades Religiosas",
    "sg:phone":"+34 956 51 70 20",
    "sg:postcode":"51001",
    "sg:province":"Ceuta",
    "wof:name":"Cofradia Las Penas",
    "wof:placetype":"venue"
},
  "geometry": {"coordinates":[-5.3073606491,35.8869056702],"type":"Point"}
}