{
  "type": "Feature",
  "properties": {
    "iso:country":"ES",
    "sg:address":"Calle de Granja (la), 9",
    "sg:city":"Sese\u00e7a Nuevo",
    "sg:orig_category":"Ropa Para Se\u00d1oras Y Caballeros (al Por Menor)",
    "sg:phone":"+34 918 01 28 51",
    "sg:postcode":"45224",
    "sg:province":"Toledo",
    "wof:name":"Hipertextil Gonzalez S.l.",
    "wof:placetype":"venue"
},
  "geometry": {"coordinates":[-3.6494669914,40.1070709229],"type":"Point"}
}