{
  "type": "Feature",
  "properties": {
    "addr:full":"Carrer de Rossello, 15 Sabadell Barcelona 08207",
    "addr:housenumber":"15",
    "addr:postcode":"08207",
    "addr:street":"Carrer De Rossello",
    "iso:country":"ES",
    "sg:address":"Carrer de Rossello, 15",
    "sg:city":"Sabadell",
    "sg:orig_category":"Radiocomunicaciones, Telefon\u00cda M\u00d3vil, Radiomensajer\u00cda: Servicios, Comercializaci\u00d3n",
    "sg:phone":"+34 937 17 69 62",
    "sg:postcode":"08207",
    "sg:province":"Barcelona",
    "wof:name":"Salazar Celin Sandra Maribel",
    "wof:placetype":"venue"
},
  "geometry": {"coordinates":[2.0890789032,41.56407547],"type":"Point"}
}