{
  "type": "Feature",
  "properties": {
    "iso:country":"ES",
    "sg:address":"A Cancela, S/n",
    "sg:city":"Portela",
    "sg:orig_category":"Poller\u00cda Y Caza (al Por Menor)",
    "sg:phone":"+34 986 71 11 30",
    "sg:postcode":"36692",
    "sg:province":"Pontevedra",
    "wof:name":"Doux Iberica S.a.",
    "wof:placetype":"venue"
},
  "geometry": {"coordinates":[-8.663807869,42.5055503845],"type":"Point"}
}