{
  "type": "Feature",
  "properties": {
    "iso:country":"ES",
    "sg:address":"Pase Revellin (del), 1",
    "sg:city":"Ceuta",
    "sg:orig_category":"Peritos Mar\u00cdtimos",
    "sg:phone":"+34 956 51 85 30",
    "sg:postcode":"51001",
    "sg:province":"Ceuta",
    "wof:name":"Cristobal Mu\u00f1oz Consignaciones S.l.",
    "wof:placetype":"venue"
},
  "geometry": {"coordinates":[-5.3302302361,35.8947601318],"type":"Point"}
}