{
  "type": "Feature",
  "properties": {
    "addr:full":"Calle de Peru, 38 Palmas De Gran Canaria Las Palmas 35010",
    "addr:housenumber":"38",
    "addr:postcode":"35010",
    "addr:street":"Calle De Peru",
    "iso:country":"ES",
    "sg:address":"Calle de Peru, 38",
    "sg:city":"Palmas De Gran Canaria",
    "sg:orig_category":"Empresas De Carpinter\u00cda De Madera",
    "sg:phone":"+34 928 26 01 42",
    "sg:postcode":"35010",
    "sg:province":"Las Palmas",
    "wof:name":"Godoy Sosa Rafael",
    "wof:placetype":"venue"
},
  "geometry": {"coordinates":[-15.4436006546,28.1314506531],"type":"Point"}
}