{
  "type": "Feature",
  "properties": {
    "addr:full":"Calle de Manuel Salda\u00d1a, 14 Badajoz Badajoz 06010",
    "addr:housenumber":"14",
    "addr:postcode":"06010",
    "addr:street":"Calle De Manuel Saldan\u0303A",
    "iso:country":"ES",
    "sg:address":"Calle de Manuel Salda\u00d1a, 14",
    "sg:city":"Badajoz",
    "sg:orig_category":"Lavado, Limpieza De Veh\u00cdculos",
    "sg:phone":"+34 924 22 34 83",
    "sg:postcode":"06010",
    "sg:province":"Badajoz",
    "wof:name":"Palma Lozano Miguel",
    "wof:placetype":"venue"
},
  "geometry": {"coordinates":[-6.9789481163,38.8685188293],"type":"Point"}
}