{
  "type": "Feature",
  "properties": {
    "addr:full":"Calle de Asuncion, 18 Sevilla Sevilla 41011",
    "addr:housenumber":"18",
    "addr:postcode":"41011",
    "addr:street":"Calle De Asuncion",
    "iso:country":"ES",
    "sg:address":"Calle de Asuncion, 18",
    "sg:city":"Sevilla",
    "sg:orig_category":"M\u00c9dicos: Oftalmolog\u00cda",
    "sg:phone":"+34 954 45 54 22",
    "sg:postcode":"41011",
    "sg:province":"Sevilla",
    "wof:name":"Reguera Garcia Ricardo",
    "wof:placetype":"venue"
},
  "geometry": {"coordinates":[-5.9976978302,37.3781356812],"type":"Point"}
}