{
  "type": "Feature",
  "properties": {
    "iso:country":"ES",
    "sg:address":"Calle de Santiago Lopez, 6",
    "sg:city":"Pravia",
    "sg:orig_category":"Farmacias",
    "sg:phone":"+34 985 82 07 39",
    "sg:postcode":"33120",
    "sg:province":"Asturias",
    "wof:name":"Cividanes Perez Maria Isabel",
    "wof:placetype":"venue"
},
  "geometry": {"coordinates":[-6.111825943,43.4872016907],"type":"Point"}
}