{
  "type": "Feature",
  "properties": {
    "addr:full":"Carr Major, 31 Torroella Montgri Girona 17257",
    "addr:housenumber":"31",
    "addr:postcode":"17257",
    "addr:street":"Carr Major",
    "iso:country":"ES",
    "sg:address":"Carr Major, 31",
    "sg:city":"Torroella Montgri",
    "sg:orig_category":"Museos",
    "sg:phone":"+34 972 75 73 01",
    "sg:postcode":"17257",
    "sg:province":"Girona",
    "wof:name":"Ajuntament De Torroella De Montgri",
    "wof:placetype":"venue"
},
  "geometry": {"coordinates":[3.1260015965,42.0398712158],"type":"Point"}
}