{
  "type": "Feature",
  "properties": {
    "addr:full":"G.v. Corts Catalanes, 540 Barcelona Barcelona 08011",
    "addr:housenumber":"540",
    "addr:postcode":"08011",
    "addr:street":"Catalanes",
    "iso:country":"ES",
    "sg:address":"G.v. Corts Catalanes, 540",
    "sg:city":"Barcelona",
    "sg:orig_category":"Asilos De Ancianos. Centros Privados",
    "sg:phone":"+34 934 51 35 07",
    "sg:postcode":"08011",
    "sg:province":"Barcelona",
    "wof:name":"Sidi Bel 2001 S.l.",
    "wof:placetype":"venue"
},
  "geometry": {"coordinates":[2.1597499847,41.3825950623],"type":"Point"}
}