{
  "type": "Feature",
  "properties": {
    "addr:full":"Calle de Soria, 33 Ajalvir Madrid 28864",
    "addr:housenumber":"33",
    "addr:postcode":"28864",
    "addr:street":"Calle De Soria",
    "iso:country":"ES",
    "sg:address":"Calle de Soria, 33",
    "sg:city":"Ajalvir",
    "sg:orig_category":"Tratamiento De Metales",
    "sg:phone":"+34 918 84 34 37",
    "sg:postcode":"28864",
    "sg:province":"Madrid",
    "sg:website":"www.inehor.com",
    "wof:name":"Industrias Y Esmaltados Al Horno S.a.",
    "wof:placetype":"venue"
},
  "geometry": {"coordinates":[-3.4850029945,40.5301246643],"type":"Point"}
}