{
  "type": "Feature",
  "properties": {
    "addr:full":"Calle de Palacio, 1 Cogolludo Guadalajara 19230",
    "addr:housenumber":"1",
    "addr:postcode":"19230",
    "addr:street":"Calle De Palacio",
    "iso:country":"ES",
    "sg:address":"Calle de Palacio, 1",
    "sg:city":"Cogolludo",
    "sg:orig_category":"Molduras, Junquillos, Listones Y Molduras Perforadas",
    "sg:phone":"+34 949 85 71 29",
    "sg:postcode":"19230",
    "sg:province":"Guadalajara",
    "wof:name":"Duce Aragues Felix",
    "wof:placetype":"venue"
},
  "geometry": {"coordinates":[-3.0885269642,40.9474182129],"type":"Point"}
}