{
  "type": "Feature",
  "properties": {
    "addr:full":"O Rego Do Espi\u00f1o, 9 Piugos Lugo 27294",
    "addr:housenumber":"9",
    "addr:postcode":"27294",
    "addr:street":"Piugos",
    "iso:country":"ES",
    "sg:address":"O Rego Do Espi\u00f1o, 9",
    "sg:city":"Piugos",
    "sg:orig_category":"Alimentaci\u00d3n General (al Por Mayor)",
    "sg:phone":"+34 982 23 04 19",
    "sg:postcode":"27294",
    "sg:province":"Lugo",
    "wof:name":"O Rego Do Espi\u00f1o S.l.",
    "wof:placetype":"venue"
},
  "geometry": {"coordinates":[-7.5726881027,42.991443634],"type":"Point"}
}