{
  "type": "Feature",
  "properties": {
    "addr:full":"Calle de Puerta Del Sol, 13 Jerez De La Frontera C\u00e1diz 11401",
    "addr:housenumber":"13",
    "addr:postcode":"11401",
    "addr:street":"Calle De Puerta Del Sol",
    "iso:country":"ES",
    "sg:address":"Calle de Puerta Del Sol, 13",
    "sg:city":"Jerez De La Frontera",
    "sg:orig_category":"Bisuter\u00cda, Joyer\u00cda, Relojer\u00cda (al Por Menor)",
    "sg:phone":"+34 956 34 84 97",
    "sg:postcode":"11401",
    "sg:province":"C\u00e1diz",
    "wof:name":"Juncal Sanchez Francisco Jose",
    "wof:placetype":"venue"
},
  "geometry": {"coordinates":[-6.130133152,36.6776237488],"type":"Point"}
}