{
  "type": "Feature",
  "properties": {
    "addr:full":"Calle de Gazteluondo, 5 Bilbao Vizcaya 48002",
    "addr:housenumber":"5",
    "addr:postcode":"48002",
    "addr:street":"Calle De Gazteluondo",
    "iso:country":"ES",
    "sg:address":"Calle de Gazteluondo, 5",
    "sg:city":"Bilbao",
    "sg:orig_category":"Bebidas",
    "sg:phone":"+34 944 44 20 18",
    "sg:postcode":"48002",
    "sg:province":"Vizcaya",
    "wof:name":"Iturri-bide S.l.",
    "wof:placetype":"venue"
},
  "geometry": {"coordinates":[-2.944653511,43.2486877441],"type":"Point"}
}