{
  "type": "Feature",
  "properties": {
    "addr:full":"Pase Resecos (los), 4 Arenas San Pedro \u00c1vila 05400",
    "addr:postcode":"05400",
    "addr:street":"A\u0301Vila",
    "iso:country":"ES",
    "sg:address":"Pase Resecos (los), 4",
    "sg:city":"Arenas San Pedro",
    "sg:orig_category":"Psic\u00d3logos",
    "sg:phone":"+34 920 37 14 69",
    "sg:postcode":"05400",
    "sg:province":"\u00c1vila",
    "wof:name":"Perandones Arevalo Maria De Las Mercedes",
    "wof:placetype":"venue"
},
  "geometry": {"coordinates":[-5.0866141319,40.210231781],"type":"Point"}
}