{
  "type": "Feature",
  "properties": {
    "iso:country":"ES",
    "sg:address":"Calle de Consenso, 25",
    "sg:city":"Madrid",
    "sg:orig_category":"Guarder\u00cdas",
    "sg:phone":"+34 913 18 18 22",
    "sg:postcode":"28041",
    "sg:province":"Madrid",
    "wof:name":"Lesvi S.l.",
    "wof:placetype":"venue"
},
  "geometry": {"coordinates":[-3.6861608028,40.3579711914],"type":"Point"}
}