{
  "type": "Feature",
  "properties": {
    "addr:full":"Calle de Bejar, 12 Huelva Huelva 21001",
    "addr:housenumber":"12",
    "addr:postcode":"21001",
    "addr:street":"Calle De Bejar",
    "iso:country":"ES",
    "sg:address":"Calle de Bejar, 12",
    "sg:city":"Huelva",
    "sg:orig_category":"Abogados",
    "sg:phone":"+34 959 24 59 31",
    "sg:postcode":"21001",
    "sg:province":"Huelva",
    "wof:name":"Garcia Flores Augusto",
    "wof:placetype":"venue"
},
  "geometry": {"coordinates":[-6.9552731514,37.2581367493],"type":"Point"}
}