{
  "type": "Feature",
  "properties": {
    "iso:country":"ES",
    "sg:address":"Carr Nou, 56",
    "sg:city":"Caldes Malavella",
    "sg:orig_category":"Agentes Generales De Seguros",
    "sg:phone":"+34 972 47 09 08",
    "sg:postcode":"17455",
    "sg:province":"Girona",
    "wof:name":"Ascal Gestio C.b.",
    "wof:placetype":"venue"
},
  "geometry": {"coordinates":[2.8070905209,41.8366737366],"type":"Point"}
}