{
  "type": "Feature",
  "properties": {
    "addr:full":"Avda Marques De Lacy, 24 Murada Alicante 03315",
    "addr:housenumber":"24",
    "addr:postcode":"03315",
    "addr:street":"Avda Marques De Lacy",
    "iso:country":"ES",
    "sg:address":"Avda Marques De Lacy, 24",
    "sg:city":"Murada",
    "sg:orig_category":"Ropa Para Se\u00d1oras Y Caballeros (al Por Menor)",
    "sg:phone":"+34 966 77 92 34",
    "sg:postcode":"03315",
    "sg:province":"Alicante",
    "wof:name":"Oltra Gomez Pilar",
    "wof:placetype":"venue"
},
  "geometry": {"coordinates":[-0.9639940262,38.1715431213],"type":"Point"}
}