{
  "type": "Feature",
  "properties": {
    "addr:full":"G.v. Marques Del Turia, 55 Valencia Valencia 46005",
    "addr:housenumber":"55",
    "addr:postcode":"46005",
    "addr:street":"Turia",
    "iso:country":"ES",
    "sg:address":"G.v. Marques Del Turia, 55",
    "sg:city":"Valencia",
    "sg:orig_category":"Procuradores",
    "sg:phone":"+34 963 94 48 60",
    "sg:postcode":"46005",
    "sg:province":"Valencia",
    "wof:name":"Ba\u00f1on Navarro Maria Lourdes",
    "wof:placetype":"venue"
},
  "geometry": {"coordinates":[-0.3678750098,39.4676895142],"type":"Point"}
}