{
  "type": "Feature",
  "properties": {
    "iso:country":"ES",
    "sg:address":"Carrer de Torrent De Vallbona, S/n",
    "sg:city":"Casc Urba",
    "sg:orig_category":"Fotograf\u00cda Art\u00cdstica Y Retratos",
    "sg:phone":"+34 935 55 65 53",
    "sg:postcode":"08328",
    "sg:province":"Barcelona",
    "wof:name":"Baena Bernal Maria Isabel",
    "wof:placetype":"venue"
},
  "geometry": {"coordinates":[2.2946848869,41.4925308228],"type":"Point"}
}