{
  "type": "Feature",
  "properties": {
    "iso:country":"ES",
    "sg:address":"Pl. Arco Iris, S/n",
    "sg:city":"Tres Cantos",
    "sg:orig_category":"Librer\u00cdas",
    "sg:phone":"+34 918 04 37 90",
    "sg:postcode":"28760",
    "sg:province":"Madrid",
    "wof:name":"Martinez Espuelas Teodosio",
    "wof:placetype":"venue"
},
  "geometry": {"coordinates":[-3.7086620331,40.6027030945],"type":"Point"}
}