{
  "type": "Feature",
  "properties": {
    "iso:country":"ES",
    "sg:address":"Calle de San Juan, 5",
    "sg:city":"Alsasua",
    "sg:orig_category":"Peluqueros: De Se\u00d1oras",
    "sg:phone":"+34 948 46 70 04",
    "sg:postcode":"31800",
    "sg:province":"Navarra",
    "wof:name":"Urdiain Tobar Ascension",
    "wof:placetype":"venue"
},
  "geometry": {"coordinates":[-2.1700592041,42.8957824707],"type":"Point"}
}