{
  "type": "Feature",
  "properties": {
    "iso:country":"ES",
    "sg:address":"Rua Pumar Mendez, 1",
    "sg:city":"Cambre",
    "sg:orig_category":"Farmacias",
    "sg:phone":"+34 981 67 42 11",
    "sg:postcode":"15660",
    "sg:province":"La Coru\u00f1a",
    "wof:name":"Ameixeiras Marra Maria Pilar",
    "wof:placetype":"venue"
},
  "geometry": {"coordinates":[-8.3415651321,43.2923736572],"type":"Point"}
}