{
  "type": "Feature",
  "properties": {
    "addr:full":"Carrer de Carrer de Atlantico, S/n Corralejo Las Palmas 35660",
    "addr:housenumber":"s",
    "addr:postcode":"35660",
    "addr:street":"Carrer;Carrer De Atlantico;/ N",
    "iso:country":"ES",
    "sg:address":"Carrer de Carrer de Atlantico, S/n",
    "sg:city":"Corralejo",
    "sg:orig_category":"Electrodom\u00c9sticos (al Por Menor)",
    "sg:phone":"+34 928 53 51 32",
    "sg:postcode":"35660",
    "sg:province":"Las Palmas",
    "wof:name":"Prados Gonzalez Manuel",
    "wof:placetype":"venue"
},
  "geometry": {"coordinates":[-13.8692493439,28.7350444794],"type":"Point"}
}