{
  "type": "Feature",
  "properties": {
    "iso:country":"ES",
    "sg:address":"Pol Ind Los Arroyos, S/n",
    "sg:city":"Moguer",
    "sg:orig_category":"Frutas, Legumbres Frescas Y Tempranas (al Por Menor)",
    "sg:phone":"+34 959 37 16 69",
    "sg:postcode":"21800",
    "sg:province":"Huelva",
    "wof:name":"Frutas Diaz Moguer S.l.",
    "wof:placetype":"venue"
},
  "geometry": {"coordinates":[-6.8342490196,37.2783584595],"type":"Point"}
}