{
  "type": "Feature",
  "properties": {
    "iso:country":"ES",
    "sg:address":"Quinto Centenario, 58",
    "sg:city":"Puerto Santiago",
    "sg:orig_category":"Art\u00cdculos De Regalo (al Por Menor)",
    "sg:phone":"+34 922 86 01 05",
    "sg:postcode":"38683",
    "sg:province":"Santa Cruz De Tenerife",
    "wof:name":"Yedey Canarias S.l.",
    "wof:placetype":"venue"
},
  "geometry": {"coordinates":[-16.8146114349,28.2961444855],"type":"Point"}
}