{
  "type": "Feature",
  "properties": {
    "iso:country":"ES",
    "sg:address":"Calle de General Orgaz, 18",
    "sg:city":"Madrid",
    "sg:orig_category":"Zapatos (al Por Menor)",
    "sg:phone":"+34 915 55 74 18",
    "sg:postcode":"28020",
    "sg:province":"Madrid",
    "wof:name":"Arroyo Lopez Jesus Angel",
    "wof:placetype":"venue"
},
  "geometry": {"coordinates":[-3.6970434189,40.4541320801],"type":"Point"}
}