{
  "type": "Feature",
  "properties": {
    "addr:full":"Calle de Enrique Wolfson, 42 Santa Cruz De Tenerife Santa Cruz De Tenerife 38004",
    "addr:housenumber":"42",
    "addr:postcode":"38004",
    "addr:street":"Calle De Enrique Wolfson",
    "iso:country":"ES",
    "sg:address":"Calle de Enrique Wolfson, 42",
    "sg:city":"Santa Cruz De Tenerife",
    "sg:orig_category":"Inmobiliaria (agencias)",
    "sg:phone":"+34 922 24 39 06",
    "sg:postcode":"38004",
    "sg:province":"Santa Cruz De Tenerife",
    "wof:name":"Galcosur S.l.",
    "wof:placetype":"venue"
},
  "geometry": {"coordinates":[-16.254989624,28.474357605],"type":"Point"}
}