{
  "type": "Feature",
  "properties": {
    "addr:full":"Calle de Jose Alvarez, 3 Mansilla Mulas Le\u00f3n 24210",
    "addr:housenumber":"3",
    "addr:postcode":"24210",
    "addr:street":"Calle De Jose Alvarez",
    "iso:country":"ES",
    "sg:address":"Calle de Jose Alvarez, 3",
    "sg:city":"Mansilla Mulas",
    "sg:orig_category":"Molduras, Junquillos, Listones Y Molduras Perforadas",
    "sg:phone":"+34 987 31 09 52",
    "sg:postcode":"24210",
    "sg:province":"Le\u00f3n",
    "wof:name":"Perez Testera Julio Cesar",
    "wof:placetype":"venue"
},
  "geometry": {"coordinates":[-5.4153442383,42.4976081848],"type":"Point"}
}