{
  "type": "Feature",
  "properties": {
    "addr:full":"Coure (pol Ind Clota), 4 Cerdanyola Valles Barcelona 08290",
    "addr:housenumber":"4",
    "addr:postcode":"08290",
    "addr:street":"Clota;Valles Barcelona",
    "iso:country":"ES",
    "sg:address":"Coure (pol Ind Clota), 4",
    "sg:city":"Cerdanyola Valles",
    "sg:orig_category":"Importaci\u00d3n",
    "sg:phone":"+34 935 94 74 00",
    "sg:postcode":"08290",
    "sg:province":"Barcelona",
    "sg:website":"www.mapri.es",
    "wof:name":"M.p.mapri Materias Primas S.a.",
    "wof:placetype":"venue"
},
  "geometry": {"coordinates":[2.1318449974,41.4999465942],"type":"Point"}
}