{
  "type": "Feature",
  "properties": {
    "addr:full":"Avda Deporte (del), S/n Olvega Soria 42110",
    "addr:postcode":"42110",
    "addr:street":"Avda Deporte Del S / N",
    "iso:country":"ES",
    "sg:address":"Avda Deporte (del), S/n",
    "sg:city":"Olvega",
    "sg:orig_category":"Centros De Educaci\u00d3n Especial",
    "sg:phone":"+34 976 19 61 77",
    "sg:postcode":"42110",
    "sg:province":"Soria",
    "wof:name":"Ayuntamiento De Olvega",
    "wof:placetype":"venue"
},
  "geometry": {"coordinates":[-1.9848589897,41.7767982483],"type":"Point"}
}