{
  "type": "Feature",
  "properties": {
    "addr:full":"Avda Paz De (la), 57 Logro\u00f1o La Rioja 26004",
    "addr:housenumber":"57",
    "addr:postcode":"26004",
    "addr:street":"Avda Paz De La;Rioja",
    "iso:country":"ES",
    "sg:address":"Avda Paz De (la), 57",
    "sg:city":"Logro\u00f1o",
    "sg:orig_category":"\u00d3ptica: Instrumentos (fabricaci\u00d3n)",
    "sg:phone":"+34 941 26 31 31",
    "sg:postcode":"26004",
    "sg:province":"La Rioja",
    "wof:name":"Visual Esymi S.l.",
    "wof:placetype":"venue"
},
  "geometry": {"coordinates":[-2.4343326092,42.4644165039],"type":"Point"}
}