{
  "type": "Feature",
  "properties": {
    "addr:full":"Calle de Vicente Aleixandre, S/n Angeles C\u00e1diz 11330",
    "addr:housenumber":"s / n",
    "addr:postcode":"11330",
    "addr:street":"Calle De Vicente Aleixandre",
    "iso:country":"ES",
    "sg:address":"Calle de Vicente Aleixandre, S/n",
    "sg:city":"Angeles",
    "sg:orig_category":"Carnicer\u00cdas, Carnicer\u00cdas",
    "sg:phone":"+34 956 64 01 33",
    "sg:postcode":"11330",
    "sg:province":"C\u00e1diz",
    "wof:name":"Rondon Rondon Francisca",
    "wof:placetype":"venue"
},
  "geometry": {"coordinates":[-5.4481987953,36.4326057434],"type":"Point"}
}