{
  "type": "Feature",
  "properties": {
    "iso:country":"ES",
    "sg:address":"Carrer de Pi I Margall, 6",
    "sg:city":"Barcelona",
    "sg:orig_category":"Agencias De Viajes",
    "sg:phone":"+34 932 13 39 62",
    "sg:postcode":"08025",
    "sg:province":"Barcelona",
    "wof:name":"Travelling Barcelona S.l.",
    "wof:placetype":"venue"
},
  "geometry": {"coordinates":[2.1632549763,41.4056968689],"type":"Point"}
}