{
  "type": "Feature",
  "properties": {
    "addr:full":"Luga Orovales (los), 1 Durazno Santa Cruz De Tenerife 38300",
    "addr:postcode":"38300",
    "addr:street":"Durazno",
    "iso:country":"ES",
    "sg:address":"Luga Orovales (los), 1",
    "sg:city":"Durazno",
    "sg:orig_category":"Inform\u00c1tica (estudios, Servicios, Asesor\u00cda, Formaci\u00d3n)",
    "sg:phone":"+34 922 32 38 54",
    "sg:postcode":"38300",
    "sg:province":"Santa Cruz De Tenerife",
    "wof:name":"Perez Wehbe Feida Maria",
    "wof:placetype":"venue"
},
  "geometry": {"coordinates":[-16.5189990997,28.3903846741],"type":"Point"}
}