{
  "type": "Feature",
  "properties": {
    "iso:country":"ES",
    "sg:address":"Carrer de Lliri, 19",
    "sg:city":"Granollers",
    "sg:orig_category":"Comercio De Piezas De Recambio Y De Accesorios De Veh\u00cdculos, Veh\u00cdculos Industriales",
    "sg:phone":"+34 938 70 19 60",
    "sg:postcode":"08402",
    "sg:province":"Barcelona",
    "wof:name":"Maspons Recanvis S.l.",
    "wof:placetype":"venue"
},
  "geometry": {"coordinates":[2.2895820141,41.6056976318],"type":"Point"}
}