{
  "type": "Feature",
  "properties": {
    "iso:country":"ES",
    "sg:address":"Calle de Habana (de La), 21",
    "sg:city":"Fuenlabrada",
    "sg:orig_category":"Molduras, Junquillos, Listones Y Molduras Perforadas",
    "sg:phone":"+34 916 06 19 10",
    "sg:postcode":"28945",
    "sg:province":"Madrid",
    "wof:name":"Clavero Castellanos Leopoldo",
    "wof:placetype":"venue"
},
  "geometry": {"coordinates":[-3.7864251137,40.2896194458],"type":"Point"}
}