{
  "type": "Feature",
  "properties": {
    "iso:country":"ES",
    "sg:address":"Carrer de Riera Alta, 67",
    "sg:city":"Barcelona",
    "sg:orig_category":"Frutas, Legumbres Frescas Y Tempranas (al Por Menor)",
    "sg:phone":"+34 933 24 82 60",
    "sg:postcode":"08001",
    "sg:province":"Barcelona",
    "wof:name":"Iqbal Akhtar Khurram",
    "wof:placetype":"venue"
},
  "geometry": {"coordinates":[2.1637721062,41.3803482056],"type":"Point"}
}