{
  "type": "Feature",
  "properties": {
    "iso:country":"ES",
    "sg:address":"Calle de Miguel Villanueva, 30",
    "sg:city":"Zarraton",
    "sg:orig_category":"Asociaciones Ecologistas",
    "sg:phone":"+34 941 32 44 01",
    "sg:postcode":"26291",
    "sg:province":"La Rioja",
    "wof:name":"Comunidad De Regantes Del Najerilla",
    "wof:placetype":"venue"
},
  "geometry": {"coordinates":[-2.8800311089,42.5160484314],"type":"Point"}
}