{
  "type": "Feature",
  "properties": {
    "addr:full":"Calle de Camino De Murcia, 48 Cieza Murcia 30530",
    "addr:housenumber":"48",
    "addr:postcode":"30530",
    "addr:street":"Calle De Camino De Murcia",
    "iso:country":"ES",
    "sg:address":"Calle de Camino De Murcia, 48",
    "sg:city":"Cieza",
    "sg:orig_category":"Centros De Coordinaci\u00d3n",
    "sg:phone":"+34 968 76 01 48",
    "sg:postcode":"30530",
    "sg:province":"Murcia",
    "wof:name":"Gestoria Administrativa Mercedes Villena S.l.",
    "wof:placetype":"venue"
},
  "geometry": {"coordinates":[-1.4206570387,38.2369117737],"type":"Point"}
}