{
  "type": "Feature",
  "properties": {
    "iso:country":"ES",
    "sg:address":"Calle de Humanista Mariner, 17",
    "sg:city":"Valencia",
    "sg:orig_category":"Promotores Constructores",
    "sg:phone":"+34 963 57 42 49",
    "sg:postcode":"46018",
    "sg:province":"Valencia",
    "wof:name":"Jusona S.l.",
    "wof:placetype":"venue"
},
  "geometry": {"coordinates":[-0.393550992,39.4604492188],"type":"Point"}
}