{
  "type": "Feature",
  "properties": {
    "addr:full":"Avda Canarias, 270 Vecindario Las Palmas 35110",
    "addr:housenumber":"270",
    "addr:postcode":"35110",
    "addr:street":"Avda Canarias;Las Palmas",
    "iso:country":"ES",
    "sg:address":"Avda Canarias, 270",
    "sg:city":"Vecindario",
    "sg:orig_category":"Inmobiliaria (agencias)",
    "sg:phone":"+34 928 14 95 29",
    "sg:postcode":"35110",
    "sg:province":"Las Palmas",
    "sg:website":"www.inmocan.com",
    "wof:name":"Inmobiliaria Gran Canaria S.c.p.",
    "wof:placetype":"venue"
},
  "geometry": {"coordinates":[-15.44298172,27.8483161926],"type":"Point"}
}