{
  "type": "Feature",
  "properties": {
    "addr:full":"Avda Doctor Fleming, 4 Le\u00f3n Le\u00f3n 24009",
    "addr:housenumber":"4",
    "addr:postcode":"24009",
    "addr:street":"Avda Doctor Fleming;Leo\u0301N",
    "iso:country":"ES",
    "sg:address":"Avda Doctor Fleming, 4",
    "sg:city":"Le\u00f3n",
    "sg:orig_category":"Librer\u00cdas",
    "sg:phone":"+34 987 22 21 27",
    "sg:postcode":"24009",
    "sg:province":"Le\u00f3n",
    "wof:name":"Ampudia Vazquez Maria Jose",
    "wof:placetype":"venue"
},
  "geometry": {"coordinates":[-5.5846614838,42.5892868042],"type":"Point"}
}