{
  "type": "Feature",
  "properties": {
    "iso:country":"ES",
    "sg:address":"Roferos, 14",
    "sg:city":"Puerto Del Carmen",
    "sg:orig_category":"Molduras, Junquillos, Listones Y Molduras Perforadas",
    "sg:phone":"+34 928 51 15 13",
    "sg:postcode":"35510",
    "sg:province":"Las Palmas",
    "wof:name":"Perez Calvo Carlos",
    "wof:placetype":"venue"
},
  "geometry": {"coordinates":[-13.6642465591,28.9270324707],"type":"Point"}
}