{
  "type": "Feature",
  "properties": {
    "addr:full":"Av Aiguera, 8 Benidorm Alicante 03500",
    "addr:housenumber":"8",
    "addr:postcode":"03500",
    "addr:street":"Av Aiguera",
    "iso:country":"ES",
    "sg:address":"Av Aiguera, 8",
    "sg:city":"Benidorm",
    "sg:orig_category":"Abogados",
    "sg:phone":"+34 966 83 03 87",
    "sg:postcode":"03500",
    "sg:province":"Alicante",
    "wof:name":"Verdu Vera Maria Salud",
    "wof:placetype":"venue"
},
  "geometry": {"coordinates":[-0.1739459932,38.5365180969],"type":"Point"}
}