{
  "type": "Feature",
  "properties": {
    "addr:full":"Av Pais Valenciano, 63 Guardamar Segura Alicante 03140",
    "addr:housenumber":"63",
    "addr:postcode":"03140",
    "addr:street":"Av Pais Valenciano",
    "iso:country":"ES",
    "sg:address":"Av Pais Valenciano, 63",
    "sg:city":"Guardamar Segura",
    "sg:orig_category":"Ahumados Y Salazones",
    "sg:phone":"+34 965 72 80 17",
    "sg:postcode":"03140",
    "sg:province":"Alicante",
    "wof:name":"Canovas Jover Jose Manuel",
    "wof:placetype":"venue"
},
  "geometry": {"coordinates":[-0.653859973,38.0866584778],"type":"Point"}
}