{
  "type": "Feature",
  "properties": {
    "addr:full":"Calle de Enmedio, 20 Castellon Castell\u00f3n 12001",
    "addr:housenumber":"20",
    "addr:postcode":"12001",
    "addr:street":"Calle De Enmedio",
    "iso:country":"ES",
    "sg:address":"Calle de Enmedio, 20",
    "sg:city":"Castellon",
    "sg:orig_category":"Arquitectos",
    "sg:phone":"+34 964 22 32 96",
    "sg:postcode":"12001",
    "sg:province":"Castell\u00f3n",
    "wof:name":"Alvarez Martin Miguel",
    "wof:placetype":"venue"
},
  "geometry": {"coordinates":[-0.0388907008,39.9851226807],"type":"Point"}
}