{
  "type": "Feature",
  "properties": {
    "iso:country":"ES",
    "sg:address":"Avda Marques De Sotelo, 11",
    "sg:city":"Valencia",
    "sg:orig_category":"Sociedades, Compa\u00d1\u00cdas Aseguradoras",
    "sg:phone":"+34 963 53 38 41",
    "sg:postcode":"46002",
    "sg:province":"Valencia",
    "wof:name":"Credyse S.l.",
    "wof:placetype":"venue"
},
  "geometry": {"coordinates":[-0.3768430054,39.4681053162],"type":"Point"}
}