{
  "type": "Feature",
  "properties": {
    "addr:full":"Calle de Luis Badia, 74 Albacete Albacete 02004",
    "addr:housenumber":"74",
    "addr:postcode":"02004",
    "addr:street":"Calle De Luis Badia",
    "iso:country":"ES",
    "sg:address":"Calle de Luis Badia, 74",
    "sg:city":"Albacete",
    "sg:orig_category":"Molduras, Junquillos, Listones Y Molduras Perforadas",
    "sg:phone":"+34 967 50 36 52",
    "sg:postcode":"02004",
    "sg:province":"Albacete",
    "wof:name":"Mero\u00f1o De La Osa Jose Francisco",
    "wof:placetype":"venue"
},
  "geometry": {"coordinates":[-1.8661609888,38.9890022278],"type":"Point"}
}