{
  "type": "Feature",
  "properties": {
    "addr:full":"Carrer de Dos De Maig, 206 Barcelona Barcelona 08013",
    "addr:housenumber":"206",
    "addr:postcode":"08013",
    "addr:street":"Carrer De Dos De Maig",
    "iso:country":"ES",
    "sg:address":"Carrer de Dos De Maig, 206",
    "sg:city":"Barcelona",
    "sg:orig_category":"Peluqueros: De Se\u00d1oras",
    "sg:phone":"+34 932 46 09 95",
    "sg:postcode":"08013",
    "sg:province":"Barcelona",
    "wof:name":"Moreno Fernandez Maria Encarnacion",
    "wof:placetype":"venue"
},
  "geometry": {"coordinates":[2.1837720871,41.4059486389],"type":"Point"}
}