{
  "type": "Feature",
  "properties": {
    "iso:country":"ES",
    "sg:address":"Lugar Mouris(xallas), 16",
    "sg:city":"Negreira",
    "sg:orig_category":"Reposter\u00cdas",
    "sg:phone":"+34 981 19 24 39",
    "sg:postcode":"15830",
    "sg:province":"La Coru\u00f1a",
    "wof:name":"Panaderia Xallas S.l.",
    "wof:placetype":"venue"
},
  "geometry": {"coordinates":[-8.7368841171,42.9089660645],"type":"Point"}
}