{
  "type": "Feature",
  "properties": {
    "addr:full":"Calle de Rey Carlos Iii, 2 Cabrera Madrid 28751",
    "addr:housenumber":"2",
    "addr:postcode":"28751",
    "addr:street":"Calle De Rey Carlos Iii",
    "iso:country":"ES",
    "sg:address":"Calle de Rey Carlos Iii, 2",
    "sg:city":"Cabrera",
    "sg:orig_category":"Limpieza Industrial",
    "sg:phone":"+34 918 68 89 20",
    "sg:postcode":"28751",
    "sg:province":"Madrid",
    "wof:name":"Burgos Rodriguez Angel",
    "wof:placetype":"venue"
},
  "geometry": {"coordinates":[-3.614233017,40.8660011292],"type":"Point"}
}