{
  "type": "Feature",
  "properties": {
    "addr:full":"Calle de Antonio Machado, 4 Fuente El Fresno Ciudad Real 13680",
    "addr:housenumber":"4",
    "addr:postcode":"13680",
    "addr:street":"Calle De Antonio Machado",
    "iso:country":"ES",
    "sg:address":"Calle de Antonio Machado, 4",
    "sg:city":"Fuente El Fresno",
    "sg:orig_category":"Contables",
    "sg:phone":"+34 926 80 45 51",
    "sg:postcode":"13680",
    "sg:province":"Ciudad Real",
    "wof:name":"Santos Exposito Maria Del Rosario",
    "wof:placetype":"venue"
},
  "geometry": {"coordinates":[-3.7752189636,39.2270317078],"type":"Point"}
}