{
  "type": "Feature",
  "properties": {
    "addr:full":"Carr Joan Llimona Gabarro, 28 Igualada Barcelona 08700",
    "addr:housenumber":"28",
    "addr:postcode":"08700",
    "addr:street":"Carr Joan Llimona Gabarro",
    "iso:country":"ES",
    "sg:address":"Carr Joan Llimona Gabarro, 28",
    "sg:city":"Igualada",
    "sg:orig_category":"M\u00c1quinas Textiles, Accesorios Y Suministros (fabricaci\u00d3n)",
    "sg:phone":"+34 938 03 08 91",
    "sg:postcode":"08700",
    "sg:province":"Barcelona",
    "sg:website":"www.fontanellas.com",
    "wof:name":"Fontanellas Maquinaria S.l.",
    "wof:placetype":"venue"
},
  "geometry": {"coordinates":[1.6079640388,41.5819358826],"type":"Point"}
}