{
  "type": "Feature",
  "properties": {
    "addr:full":"Ctra Burgos Portugal, S/n Mu\u00d1oz Salamanca 37493",
    "addr:housenumber":"s / n",
    "addr:postcode":"37493",
    "addr:street":"Ctra Burgos Portugal",
    "iso:country":"ES",
    "sg:address":"Ctra Burgos Portugal, S/n",
    "sg:city":"Mu\u00d1oz",
    "sg:orig_category":"Chapister\u00cda",
    "sg:phone":"+34 923 45 11 13",
    "sg:postcode":"37493",
    "sg:province":"Salamanca",
    "wof:name":"Sanchez Martin Isidoro",
    "wof:placetype":"venue"
},
  "geometry": {"coordinates":[-6.1982607841,40.815120697],"type":"Point"}
}