{
  "type": "Feature",
  "properties": {
    "iso:country":"ES",
    "sg:address":"Calle de Nueva, 14",
    "sg:city":"Aljaraque",
    "sg:orig_category":"Inmobiliaria (agencias)",
    "sg:phone":"+34 959 31 89 47",
    "sg:postcode":"21110",
    "sg:province":"Huelva",
    "wof:name":"Servicios Inmobiliarios A Su Medida C.b",
    "wof:placetype":"venue"
},
  "geometry": {"coordinates":[-7.0229887962,37.2714118958],"type":"Point"}
}