{
  "type": "Feature",
  "properties": {
    "addr:full":"Calle de Batalla Del Salado, 23 Tarifa C\u00e1diz 11380",
    "addr:housenumber":"23",
    "addr:postcode":"11380",
    "addr:street":"Calle De Batalla Del Salado;Ca\u0301Diz",
    "iso:country":"ES",
    "sg:address":"Calle de Batalla Del Salado, 23",
    "sg:city":"Tarifa",
    "sg:orig_category":"Bancos",
    "sg:phone":"+34 956 68 43 40",
    "sg:postcode":"11380",
    "sg:province":"C\u00e1diz",
    "wof:name":"Bt Espa\u00d1a Compa\u00d1ia De Servicios Globales De Telecomunicaciones S.a.u.",
    "wof:placetype":"venue"
},
  "geometry": {"coordinates":[-5.6064090729,36.0161705017],"type":"Point"}
}