{
  "type": "Feature",
  "properties": {
    "iso:country":"ES",
    "sg:address":"Diseminados, S/n",
    "sg:city":"Urretxu",
    "sg:orig_category":"Forjas Y Altos Hornos",
    "sg:phone":"+34 943 72 50 27",
    "sg:postcode":"20700",
    "sg:province":"Guip\u00f9zcoa",
    "wof:name":"Diez Simon Miguel",
    "wof:placetype":"venue"
},
  "geometry": {"coordinates":[-2.3134770393,43.086730957],"type":"Point"}
}