{
  "type": "Feature",
  "properties": {
    "iso:country":"ES",
    "sg:address":"Torron (se\u00f1orin), S/n",
    "sg:city":"Torron",
    "sg:orig_category":"Poller\u00cda Y Caza (al Por Menor)",
    "sg:phone":"+34 988 27 03 27",
    "sg:postcode":"32500",
    "sg:province":"Ourense",
    "wof:name":"Puga Paz Jorge",
    "wof:placetype":"venue"
},
  "geometry": {"coordinates":[-8.0741043091,42.433265686],"type":"Point"}
}