{
  "type": "Feature",
  "properties": {
    "addr:full":"Calle de Fundicion (de La), 59 Partija-santa Monica Madrid 28529",
    "addr:housenumber":"59",
    "addr:postcode":"28529",
    "addr:street":"Calle De Fundicion De La",
    "iso:country":"ES",
    "sg:address":"Calle de Fundicion (de La), 59",
    "sg:city":"Partija-santa Monica",
    "sg:orig_category":"Neum\u00c1ticos (fabricaci\u00d3n, Al Por Mayor)",
    "sg:phone":"+34 916 66 25 89",
    "sg:postcode":"28529",
    "sg:province":"Madrid",
    "wof:name":"Dimaroil S.l.",
    "wof:placetype":"venue"
},
  "geometry": {"coordinates":[-3.5102670193,40.314289093],"type":"Point"}
}