{
  "type": "Feature",
  "properties": {
    "addr:full":"Carrer de Arago, 119 Barcelona Barcelona 08015",
    "addr:housenumber":"119",
    "addr:postcode":"08015",
    "addr:street":"Carrer De Arago",
    "iso:country":"ES",
    "sg:address":"Carrer de Arago, 119",
    "sg:city":"Barcelona",
    "sg:orig_category":"Detectives, Agentes Investigadores Privados",
    "sg:phone":"+34 934 51 07 82",
    "sg:postcode":"08015",
    "sg:province":"Barcelona",
    "wof:name":"Jesus Oteo S.l.",
    "wof:placetype":"venue"
},
  "geometry": {"coordinates":[2.15290308,41.3833503723],"type":"Point"}
}