{
  "type": "Feature",
  "properties": {
    "iso:country":"ES",
    "sg:address":"Carrer de Girona, 272",
    "sg:city":"Terrassa",
    "sg:orig_category":"Impresiones Sobre Tela",
    "sg:phone":"+34 937 35 11 69",
    "sg:postcode":"08226",
    "sg:province":"Barcelona",
    "wof:name":"Salmerone E Hijos S.l.",
    "wof:placetype":"venue"
},
  "geometry": {"coordinates":[2.0225698948,41.5773735046],"type":"Point"}
}