{
  "type": "Feature",
  "properties": {
    "addr:full":"Calle de Hermanos Pinzon, 17 Almeria Almer\u00eda 04005",
    "addr:housenumber":"17",
    "addr:postcode":"04005",
    "addr:street":"Calle De Hermanos Pinzon",
    "iso:country":"ES",
    "sg:address":"Calle de Hermanos Pinzon, 17",
    "sg:city":"Almeria",
    "sg:orig_category":"Procuradores",
    "sg:phone":"+34 950 22 96 67",
    "sg:postcode":"04005",
    "sg:province":"Almer\u00eda",
    "wof:name":"Fernandez Valero Isabel",
    "wof:placetype":"venue"
},
  "geometry": {"coordinates":[-2.4570629597,36.8381843567],"type":"Point"}
}