{
  "type": "Feature",
  "properties": {
    "iso:country":"ES",
    "sg:address":"Av Catalunya, 20",
    "sg:city":"S. Joan Mollet",
    "sg:orig_category":"Centros De Educaci\u00d3n Especial",
    "sg:phone":"+34 972 48 81 81",
    "sg:postcode":"17463",
    "sg:province":"Girona",
    "wof:name":"Ajuntament De Sant Joan De Mollet",
    "wof:placetype":"venue"
},
  "geometry": {"coordinates":[2.906327486,42.0655937195],"type":"Point"}
}