{
  "type": "Feature",
  "properties": {
    "iso:country":"ES",
    "sg:address":"Plaz San Juan De La Cruz, 3",
    "sg:city":"Madrid",
    "sg:orig_category":"Centros M\u00c9dicos Y Sociales, Dispensarios",
    "sg:phone":"+34 915 33 22 21",
    "sg:postcode":"28003",
    "sg:province":"Madrid",
    "sg:website":"www.prosalud.net",
    "wof:name":"Prosalud Consultas Medicas S.l.",
    "wof:placetype":"venue"
},
  "geometry": {"coordinates":[-3.6922900677,40.4413795471],"type":"Point"}
}