{
  "type": "Feature",
  "properties": {
    "iso:country":"ES",
    "sg:address":"Calle de Nogal, 1",
    "sg:city":"Rozas De Madrid",
    "sg:orig_category":"Agencias Y Asesores De Publicidad",
    "sg:phone":"+34 916 37 39 15",
    "sg:postcode":"28230",
    "sg:province":"Madrid",
    "sg:website":"www.thebox-adv.com",
    "wof:name":"The Box Advertising S.l.",
    "wof:placetype":"venue"
},
  "geometry": {"coordinates":[-3.9308977127,40.5756797791],"type":"Point"}
}