{
  "type": "Feature",
  "properties": {
    "addr:full":"Avda Guadalajara, 99 Madrid Madrid 28032",
    "addr:housenumber":"99",
    "addr:postcode":"madrid;28032",
    "addr:street":"Avda Guadalajara",
    "iso:country":"ES",
    "sg:address":"Avda Guadalajara, 99",
    "sg:city":"Madrid",
    "sg:orig_category":"Artes Gr\u00c1ficas, Artes Pl\u00c1sticas (curso)",
    "sg:phone":"+34 913 06 73 06",
    "sg:postcode":"28032",
    "sg:province":"Madrid",
    "wof:name":"Sanchez Frutos Santiago",
    "wof:placetype":"venue"
},
  "geometry": {"coordinates":[-3.6137740612,40.4219741821],"type":"Point"}
}