{
  "type": "Feature",
  "properties": {
    "addr:full":"Calle de Manuel Fal Conde, 5 Sevilla Sevilla 41013",
    "addr:housenumber":"5",
    "addr:postcode":"41013",
    "addr:street":"Calle De Manuel Fal Conde",
    "iso:country":"ES",
    "sg:address":"Calle de Manuel Fal Conde, 5",
    "sg:city":"Sevilla",
    "sg:orig_category":"Obras Y Organismos Sociales",
    "sg:phone":"+34 954 62 21 54",
    "sg:postcode":"41013",
    "sg:province":"Sevilla",
    "wof:name":"Misioneras Doctrina Cristiana Curia Gener",
    "wof:placetype":"venue"
},
  "geometry": {"coordinates":[-5.9729037285,37.3591117859],"type":"Point"}
}