{
  "type": "Feature",
  "properties": {
    "iso:country":"ES",
    "sg:address":"Avda Europa, 1",
    "sg:city":"Arriondas",
    "sg:orig_category":"Electricidad: Instaladores",
    "sg:phone":"+34 985 84 00 88",
    "sg:postcode":"33540",
    "sg:province":"Asturias",
    "wof:name":"Prieto Gonzalez Gonzalo",
    "wof:placetype":"venue"
},
  "geometry": {"coordinates":[-5.1836371422,43.3900756836],"type":"Point"}
}