{
  "type": "Feature",
  "properties": {
    "iso:country":"ES",
    "sg:address":"Calle de Concepcion, 3",
    "sg:city":"Valladolid",
    "sg:orig_category":"Iglesia Cat\u00d3lica",
    "sg:phone":"+34 983 35 30 59",
    "sg:postcode":"47003",
    "sg:province":"Valladolid",
    "wof:name":"Parroquia De San Miguel",
    "wof:placetype":"venue"
},
  "geometry": {"coordinates":[-4.7279443741,41.6553993225],"type":"Point"}
}