{
  "type": "Feature",
  "properties": {
    "addr:full":"Carr Terreres, 9 Figueres Girona 17600",
    "addr:housenumber":"9",
    "addr:postcode":"17600",
    "addr:street":"Carr Terreres",
    "iso:country":"ES",
    "sg:address":"Carr Terreres, 9",
    "sg:city":"Figueres",
    "sg:orig_category":"Reposter\u00cdas",
    "sg:phone":"+34 972 50 40 87",
    "sg:postcode":"17600",
    "sg:province":"Girona",
    "wof:name":"Llobet Mas Pere",
    "wof:placetype":"venue"
},
  "geometry": {"coordinates":[2.9612801075,42.2643318176],"type":"Point"}
}