{
  "type": "Feature",
  "properties": {
    "iso:country":"ES",
    "sg:address":"Calle de San Sebastian (de), 17",
    "sg:city":"Pinto",
    "sg:orig_category":"Plomeros",
    "sg:phone":"+34 916 92 03 56",
    "sg:postcode":"28320",
    "sg:province":"Madrid",
    "wof:name":"Covarrubias Santos Felix",
    "wof:placetype":"venue"
},
  "geometry": {"coordinates":[-3.6989328861,40.246383667],"type":"Point"}
}