{
  "type": "Feature",
  "properties": {
    "addr:full":"Mazaido, S/n Mazaido La Coru\u00f1a 15010",
    "addr:housenumber":"s / n",
    "addr:postcode":"15010",
    "addr:street":"Mazaido;Mazaido La Corun\u0303A",
    "iso:country":"ES",
    "sg:address":"Mazaido, S/n",
    "sg:city":"Mazaido",
    "sg:orig_category":"Obras Y Organismos Sociales",
    "sg:phone":"+34 981 14 30 88",
    "sg:postcode":"15010",
    "sg:province":"La Coru\u00f1a",
    "wof:name":"Hogar De Sor Eusebia",
    "wof:placetype":"venue"
},
  "geometry": {"coordinates":[-8.3964595795,43.3701095581],"type":"Point"}
}