{
  "type": "Feature",
  "properties": {
    "iso:country":"ES",
    "sg:address":"Calle de Guecho, 36",
    "sg:city":"Madrid",
    "sg:orig_category":"Promotores Constructores",
    "sg:phone":"+34 913 72 92 78",
    "sg:postcode":"28023",
    "sg:province":"Madrid",
    "wof:name":"Residencial Centro S.l.",
    "wof:placetype":"venue"
},
  "geometry": {"coordinates":[-3.8208870888,40.4746055603],"type":"Point"}
}