{
  "type": "Feature",
  "properties": {
    "iso:country":"ES",
    "sg:address":"Calle de Alfonso I, 4",
    "sg:city":"Zaragoza",
    "sg:orig_category":"Material Y Accesorios Para Bisuter\u00cda Y Joyer\u00cda",
    "sg:phone":"+34 976 39 16 28",
    "sg:postcode":"50003",
    "sg:province":"Zaragoza",
    "wof:name":"Martinez Ferrer Maria Pilar",
    "wof:placetype":"venue"
},
  "geometry": {"coordinates":[-0.8819342256,41.6532058716],"type":"Point"}
}