{
  "type": "Feature",
  "properties": {
    "iso:country":"ES",
    "sg:address":"Plaz Jose Maria Bautista Hernandez, 12",
    "sg:city":"San Pedro",
    "sg:orig_category":"Peluquer\u00cdas, Peluquer\u00cda Mixta",
    "sg:phone":"+34 968 21 46 06",
    "sg:postcode":"30004",
    "sg:province":"Murcia",
    "wof:name":"Belando Perez Encarnacion",
    "wof:placetype":"venue"
},
  "geometry": {"coordinates":[-1.1354490519,37.9855308533],"type":"Point"}
}