{
  "type": "Feature",
  "properties": {
    "addr:full":"Calle de Sancho Davila, 3 Jerez De La Frontera C\u00e1diz 11407",
    "addr:housenumber":"3",
    "addr:postcode":"11407",
    "addr:street":"Calle De Sancho Davila",
    "iso:country":"ES",
    "sg:address":"Calle de Sancho Davila, 3",
    "sg:city":"Jerez De La Frontera",
    "sg:orig_category":"Alimentaci\u00d3n General (al Por Menor)",
    "sg:phone":"+34 956 31 05 37",
    "sg:postcode":"11407",
    "sg:province":"C\u00e1diz",
    "wof:name":"Sanchez Caro Ana",
    "wof:placetype":"venue"
},
  "geometry": {"coordinates":[-6.1367111206,36.6996612549],"type":"Point"}
}