{
  "type": "Feature",
  "properties": {
    "addr:full":"Cmno Lerin, S/n Oteiza Navarra 31250",
    "addr:postcode":"31250",
    "addr:street":"Cmno Lerin S / N",
    "iso:country":"ES",
    "sg:address":"Cmno Lerin, S/n",
    "sg:city":"Oteiza",
    "sg:orig_category":"Producci\u00d3n, Comercio De Cereales",
    "sg:phone":"+34 948 53 62 01",
    "sg:postcode":"31250",
    "sg:province":"Navarra",
    "wof:name":"Sociedad Cooperativa Litxarra",
    "wof:placetype":"venue"
},
  "geometry": {"coordinates":[-1.9553389549,42.61693573],"type":"Point"}
}