{
  "type": "Feature",
  "properties": {
    "iso:country":"ES",
    "sg:address":"Calle de Salces Anselma De, 1",
    "sg:city":"Bilbao",
    "sg:orig_category":"Panader\u00cdas, Panader\u00cdas",
    "sg:phone":"+34 944 46 09 64",
    "sg:postcode":"48007",
    "sg:province":"Vizcaya",
    "wof:name":"Picazo Gimenez Esther",
    "wof:placetype":"venue"
},
  "geometry": {"coordinates":[-2.9230189323,43.2661514282],"type":"Point"}
}