{
  "type": "Feature",
  "properties": {
    "iso:country":"ES",
    "sg:address":"Calle de Cura Teresi, 8",
    "sg:city":"Riba-roja Turia",
    "sg:orig_category":"Cl\u00cdnicas Dentales",
    "sg:phone":"+34 961 65 35 22",
    "sg:postcode":"46190",
    "sg:province":"Valencia",
    "wof:name":"Martinez Gosalbez Juan",
    "wof:placetype":"venue"
},
  "geometry": {"coordinates":[-0.5677589774,39.5475921631],"type":"Point"}
}