{
  "type": "Feature",
  "properties": {
    "addr:full":"Llanete De Abajo, 2 Casabermeja M\u00e1laga 29160",
    "addr:housenumber":"2",
    "addr:postcode":"29160",
    "addr:street":"Abajo",
    "iso:country":"ES",
    "sg:address":"Llanete De Abajo, 2",
    "sg:city":"Casabermeja",
    "sg:orig_category":"Administraciones Regionales, Departamentales Y Locales",
    "sg:phone":"+34 952 75 83 77",
    "sg:postcode":"29160",
    "sg:province":"M\u00e1laga",
    "wof:name":"Ayuntamiento De Casabermeja",
    "wof:placetype":"venue"
},
  "geometry": {"coordinates":[-4.4302635193,36.8945350647],"type":"Point"}
}