{
  "type": "Feature",
  "properties": {
    "iso:country":"ES",
    "sg:address":"Rbla General Garcia Escamez, S/n",
    "sg:city":"Santa Cruz De Tenerife",
    "sg:orig_category":"Peluqueros: De Se\u00d1oras",
    "sg:phone":"+34 922 21 94 04",
    "sg:postcode":"38009",
    "sg:province":"Santa Cruz De Tenerife",
    "wof:name":"Perez Perez Argelia",
    "wof:placetype":"venue"
},
  "geometry": {"coordinates":[-16.2734584808,28.4538555145],"type":"Point"}
}