{
  "type": "Feature",
  "properties": {
    "iso:country":"ES",
    "sg:address":"Calle de Goethe, 12",
    "sg:city":"Malaga",
    "sg:orig_category":"Arquitectos",
    "sg:phone":"+34 952 60 91 24",
    "sg:postcode":"29016",
    "sg:province":"M\u00e1laga",
    "wof:name":"Roldan Montiel Manuel",
    "wof:placetype":"venue"
},
  "geometry": {"coordinates":[-4.3970208168,36.7282829285],"type":"Point"}
}