{
  "type": "Feature",
  "properties": {
    "iso:country":"ES",
    "sg:address":"Calle de Herreros, 84",
    "sg:city":"Medina Campo",
    "sg:orig_category":"Mec\u00c1nico Del Autom\u00d3vil",
    "sg:phone":"+34 983 80 17 86",
    "sg:postcode":"47400",
    "sg:province":"Valladolid",
    "wof:name":"Talleres Delsa S.l.",
    "wof:placetype":"venue"
},
  "geometry": {"coordinates":[-4.913184166,41.3120155334],"type":"Point"}
}