{
  "type": "Feature",
  "properties": {
    "addr:full":"Carrer de Ramon Albo, 54 Barcelona Barcelona 08027",
    "addr:housenumber":"54",
    "addr:postcode":"08027",
    "addr:street":"Carrer De Ramon Albo",
    "iso:country":"ES",
    "sg:address":"Carrer de Ramon Albo, 54",
    "sg:city":"Barcelona",
    "sg:orig_category":"Ropa Para Ni\u00d1os (al Por Menor)",
    "sg:phone":"+34 933 52 92 56",
    "sg:postcode":"08027",
    "sg:province":"Barcelona",
    "wof:name":"Capel Cazorla Aurelia",
    "wof:placetype":"venue"
},
  "geometry": {"coordinates":[2.1775150299,41.4261016846],"type":"Point"}
}