{
  "type": "Feature",
  "properties": {
    "iso:country":"ES",
    "sg:address":"Calle de Cuevas Puente La Reina, 8",
    "sg:city":"Teruel",
    "sg:orig_category":"Tintorer\u00cdas, Limpieza En Seco",
    "sg:phone":"+34 978 60 21 48",
    "sg:postcode":"44003",
    "sg:province":"Teruel",
    "wof:name":"Cruzado Estevan Mario",
    "wof:placetype":"venue"
},
  "geometry": {"coordinates":[-1.1085330248,40.3462753296],"type":"Point"}
}