{
  "type": "Feature",
  "properties": {
    "iso:country":"ES",
    "sg:address":"Calle de Fragua (de La), 2",
    "sg:city":"San Fernando De Henares",
    "sg:orig_category":"Abogados",
    "sg:phone":"+34 916 74 12 15",
    "sg:postcode":"28830",
    "sg:province":"Madrid",
    "wof:name":"Comunidad De Vecinos Calle De La Fragua N\u00ba 2",
    "wof:placetype":"venue"
},
  "geometry": {"coordinates":[-3.532941103,40.4235877991],"type":"Point"}
}