{
  "type": "Feature",
  "properties": {
    "addr:full":"Calle de Lopez De Hoyos, 166 Madrid Madrid 28002",
    "addr:housenumber":"166",
    "addr:postcode":"28002",
    "addr:street":"Calle De Lopez De Hoyos",
    "iso:country":"ES",
    "sg:address":"Calle de Lopez De Hoyos, 166",
    "sg:city":"Madrid",
    "sg:orig_category":"Comunidades Religiosas",
    "sg:phone":"+34 914 13 28 20",
    "sg:postcode":"28002",
    "sg:province":"Madrid",
    "wof:name":"Parroquia De Santa Matilde",
    "wof:placetype":"venue"
},
  "geometry": {"coordinates":[-3.6702489853,40.4465293884],"type":"Point"}
}