{
  "type": "Feature",
  "properties": {
    "addr:full":"Calle de Angel Mugica, 13 Madrid Madrid 28034",
    "addr:housenumber":"13",
    "addr:postcode":"madrid;28034",
    "addr:street":"Calle De Angel Mugica",
    "iso:country":"ES",
    "sg:address":"Calle de Angel Mugica, 13",
    "sg:city":"Madrid",
    "sg:orig_category":"Confecci\u00d3n De Zapatos",
    "sg:phone":"+34 917 29 07 40",
    "sg:postcode":"28034",
    "sg:province":"Madrid",
    "wof:name":"Alonso Asenjo Maria Bego\u00f1a",
    "wof:placetype":"venue"
},
  "geometry": {"coordinates":[-3.6863455772,40.4858360291],"type":"Point"}
}