{
  "type": "Feature",
  "properties": {
    "addr:full":"Muel Ca\u00d1onero Dato, S/n Ceuta Ceuta 51001",
    "addr:postcode":"51001",
    "addr:street":"Dato S / N",
    "iso:country":"ES",
    "sg:address":"Muel Ca\u00d1onero Dato, S/n",
    "sg:city":"Ceuta",
    "sg:orig_category":"Ense\u00d1anza, Formaci\u00d3n Profesional: Aprendizaje",
    "sg:phone":"+34 956 50 89 11",
    "sg:postcode":"51001",
    "sg:province":"Ceuta",
    "wof:name":"Agencia Estatal De Administracion Tributaria",
    "wof:placetype":"venue"
},
  "geometry": {"coordinates":[-5.3193998337,35.8888816833],"type":"Point"}
}