{
  "type": "Feature",
  "properties": {
    "addr:full":"Calle de Granada, 25 Peligros Granada 18210",
    "addr:housenumber":"25",
    "addr:postcode":"18210",
    "addr:street":"Calle De Granada",
    "iso:country":"ES",
    "sg:address":"Calle de Granada, 25",
    "sg:city":"Peligros",
    "sg:orig_category":"Fabricaci\u00d3n De Moldes Y Modelos",
    "sg:phone":"+34 958 40 59 62",
    "sg:postcode":"18210",
    "sg:province":"Granada",
    "wof:name":"Sanchez Rodriguez Fernando",
    "wof:placetype":"venue"
},
  "geometry": {"coordinates":[-3.6258990765,37.2293281555],"type":"Point"}
}