{
  "type": "Feature",
  "properties": {
    "iso:country":"ES",
    "sg:address":"Calle de Andalucia, 18",
    "sg:city":"Berja",
    "sg:orig_category":"Promotores Constructores",
    "sg:phone":"+34 950 49 27 05",
    "sg:postcode":"04760",
    "sg:province":"Almer\u00eda",
    "wof:name":"Berja De La Vivienda S.a.",
    "wof:placetype":"venue"
},
  "geometry": {"coordinates":[-2.9421510696,36.8412628174],"type":"Point"}
}