{
  "type": "Feature",
  "properties": {
    "addr:full":"Calle de Berlin, 26 Parla Madrid 28980",
    "addr:housenumber":"26",
    "addr:postcode":"28980",
    "addr:street":"Calle De Berlin",
    "iso:country":"ES",
    "sg:address":"Calle de Berlin, 26",
    "sg:city":"Parla",
    "sg:orig_category":"Alumbrados",
    "sg:phone":"+34 916 99 80 13",
    "sg:postcode":"28980",
    "sg:province":"Madrid",
    "wof:name":"Columnas Y Baculos S.l.",
    "wof:placetype":"venue"
},
  "geometry": {"coordinates":[-3.7546591759,40.238243103],"type":"Point"}
}