{
  "type": "Feature",
  "properties": {
    "iso:country":"ES",
    "sg:address":"Carrer de Ample, 55",
    "sg:city":"Reus",
    "sg:orig_category":"M\u00c9dicos: Oftalmolog\u00cda",
    "sg:phone":"+34 977 31 39 49",
    "sg:postcode":"43202",
    "sg:province":"Tarragona",
    "wof:name":"Romero Aroca Pedro",
    "wof:placetype":"venue"
},
  "geometry": {"coordinates":[1.103358984,41.1597137451],"type":"Point"}
}