{
  "type": "Feature",
  "properties": {
    "iso:country":"ES",
    "sg:address":"Calle de Bahia De Santa Pola, 28",
    "sg:city":"Madrid",
    "sg:orig_category":"Grafistas",
    "sg:phone":"+34 913 29 21 90",
    "sg:postcode":"28042",
    "sg:province":"Madrid",
    "sg:website":"www.sansonydalila.net",
    "wof:name":"Sanson Y Dalila S.l.",
    "wof:placetype":"venue"
},
  "geometry": {"coordinates":[-3.5917890072,40.4668579102],"type":"Point"}
}