{
  "type": "Feature",
  "properties": {
    "iso:country":"ES",
    "sg:address":"Plaz Fueros, 5",
    "sg:city":"Tudela",
    "sg:orig_category":"Loter\u00cda Y T\u00d3mbola",
    "sg:phone":"+34 948 82 59 59",
    "sg:postcode":"31500",
    "sg:province":"Navarra",
    "wof:name":"Apastegui Nadal Ana",
    "wof:placetype":"venue"
},
  "geometry": {"coordinates":[-1.6059288979,42.0613098145],"type":"Point"}
}