{
  "type": "Feature",
  "properties": {
    "iso:country":"ES",
    "sg:address":"Calle de Domingo Guerra Del Rio, 7",
    "sg:city":"Palmas De Gran Canaria",
    "sg:orig_category":"Tubos De Cart\u00d3n Y Papel",
    "sg:phone":"+34 928 36 14 47",
    "sg:postcode":"35014",
    "sg:province":"Las Palmas",
    "wof:name":"Electroradiologia S.l",
    "wof:placetype":"venue"
},
  "geometry": {"coordinates":[-15.42075634,28.1062450409],"type":"Point"}
}