{
  "type": "Feature",
  "properties": {
    "addr:full":"Calle de Chapi, 8 Ogijares Granada 18151",
    "addr:housenumber":"8",
    "addr:postcode":"18151",
    "addr:street":"Calle De Chapi",
    "iso:country":"ES",
    "sg:address":"Calle de Chapi, 8",
    "sg:city":"Ogijares",
    "sg:orig_category":"Frutas, Legumbres Frescas Y Tempranas (al Por Menor)",
    "sg:phone":"+34 958 50 71 99",
    "sg:postcode":"18151",
    "sg:province":"Granada",
    "wof:name":"Barrales Fernandez Rafael",
    "wof:placetype":"venue"
},
  "geometry": {"coordinates":[-3.6070098877,37.1229476929],"type":"Point"}
}