{
  "type": "Feature",
  "properties": {
    "iso:country":"ES",
    "sg:address":"Calle de Castelar, 54",
    "sg:city":"Zaragoza",
    "sg:orig_category":"Negocio De Materiales De Construcci\u00d3n",
    "sg:phone":"+34 976 41 34 23",
    "sg:postcode":"50013",
    "sg:province":"Zaragoza",
    "wof:name":"Pina Monta\u00f1es Angel",
    "wof:placetype":"venue"
},
  "geometry": {"coordinates":[-0.8698093295,41.6392593384],"type":"Point"}
}