{
  "type": "Feature",
  "properties": {
    "iso:country":"ES",
    "sg:address":"Plaz Obispo Inocencio Rodriguez Diez, 6",
    "sg:city":"Cuenca",
    "sg:orig_category":"Empresas De Limpieza",
    "sg:phone":"+34 969 22 00 71",
    "sg:postcode":"16003",
    "sg:province":"Cuenca",
    "wof:name":"Rihuete Sanz Angustias",
    "wof:placetype":"venue"
},
  "geometry": {"coordinates":[-2.1370170116,40.0660057068],"type":"Point"}
}