{
  "type": "Feature",
  "properties": {
    "iso:country":"ES",
    "sg:address":"Avda Yurramendi, S/n",
    "sg:city":"Ciudad Rodrigo",
    "sg:orig_category":"Confecci\u00d3n (fabricaci\u00d3n, Al Por Mayor)",
    "sg:phone":"+34 923 48 21 85",
    "sg:postcode":"37500",
    "sg:province":"Salamanca",
    "wof:name":"Arevalo Fuentes Maria Josefa",
    "wof:placetype":"venue"
},
  "geometry": {"coordinates":[-6.5329618454,40.6001472473],"type":"Point"}
}