{
  "type": "Feature",
  "properties": {
    "iso:country":"ES",
    "sg:address":"Carrer de Mossen Coy, 15",
    "sg:city":"Vilafranca Penedes",
    "sg:orig_category":"Promotores Constructores",
    "sg:phone":"+34 938 92 21 93",
    "sg:postcode":"08720",
    "sg:province":"Barcelona",
    "wof:name":"Construcciones Y Explanaciones Gras S. A.",
    "wof:placetype":"venue"
},
  "geometry": {"coordinates":[1.7027169466,41.3516578674],"type":"Point"}
}