{
  "type": "Feature",
  "properties": {
    "addr:full":"Calle de Union, 41 Castellon Castell\u00f3n 12004",
    "addr:housenumber":"41",
    "addr:postcode":"12004",
    "addr:street":"Calle De;Castellon Castello\u0301N",
    "iso:country":"ES",
    "sg:address":"Calle de Union, 41",
    "sg:city":"Castellon",
    "sg:orig_category":"Electricidad: Instaladores",
    "sg:phone":"+34 964 21 73 05",
    "sg:postcode":"12004",
    "sg:province":"Castell\u00f3n",
    "wof:name":"Renau Carsi Fermin",
    "wof:placetype":"venue"
},
  "geometry": {"coordinates":[-0.0456110016,39.9912414551],"type":"Point"}
}