{
  "type": "Feature",
  "properties": {
    "addr:full":"Calle de Patricio Ferrandiz, 22 Denia Alicante 03700",
    "addr:housenumber":"22",
    "addr:postcode":"03700",
    "addr:street":"Calle De Patricio Ferrandiz",
    "iso:country":"ES",
    "sg:address":"Calle de Patricio Ferrandiz, 22",
    "sg:city":"Denia",
    "sg:orig_category":"Electricidad: Instaladores",
    "sg:phone":"+34 965 78 53 40",
    "sg:postcode":"03700",
    "sg:province":"Alicante",
    "wof:name":"Palu Instalaciones Electricas S.l.",
    "wof:placetype":"venue"
},
  "geometry": {"coordinates":[0.1059902012,38.8372154236],"type":"Point"}
}