{
  "type": "Feature",
  "properties": {
    "iso:country":"ES",
    "sg:address":"Calle de Camino De Santiago, 4",
    "sg:city":"Ponferrada",
    "sg:orig_category":"Ropa Para Ni\u00d1os (al Por Menor)",
    "sg:phone":"+34 987 42 85 91",
    "sg:postcode":"24400",
    "sg:province":"Le\u00f3n",
    "wof:name":"Funcho S.a.",
    "wof:placetype":"venue"
},
  "geometry": {"coordinates":[-6.5985517502,42.5481491089],"type":"Point"}
}