{
  "type": "Feature",
  "properties": {
    "addr:full":"Urb Zayamar, 20 Caleta Velez M\u00e1laga 29751",
    "addr:housenumber":"20",
    "addr:postcode":"29751",
    "addr:street":"Urb Zayamar;Ma\u0301Laga",
    "iso:country":"ES",
    "sg:address":"Urb Zayamar, 20",
    "sg:city":"Caleta Velez",
    "sg:orig_category":"Alquiler De Apartamentos",
    "sg:phone":"+34 952 51 13 76",
    "sg:postcode":"29751",
    "sg:province":"M\u00e1laga",
    "wof:name":"Broncealia S.l.l.",
    "wof:placetype":"venue"
},
  "geometry": {"coordinates":[-4.0726838112,36.7514686584],"type":"Point"}
}