{
  "type": "Feature",
  "properties": {
    "addr:full":"Avda Santa Apolonia, 27 Monte Vedat Valencia 46901",
    "addr:housenumber":"27",
    "addr:postcode":"46901",
    "addr:street":"Avda Santa Apolonia;Vedat",
    "iso:country":"ES",
    "sg:address":"Avda Santa Apolonia, 27",
    "sg:city":"Monte Vedat",
    "sg:orig_category":"Ingeniero",
    "sg:phone":"+34 961 55 28 11",
    "sg:postcode":"46901",
    "sg:province":"Valencia",
    "wof:name":"Marti Perez Ezequiel",
    "wof:placetype":"venue"
},
  "geometry": {"coordinates":[-0.485789001,39.4092483521],"type":"Point"}
}