{
  "type": "Feature",
  "properties": {
    "addr:full":"Rua Garcia Camba, 10 Pontevedra Pontevedra 36001",
    "addr:housenumber":"10",
    "addr:postcode":"36001",
    "addr:street":"Rua Garcia Camba",
    "iso:country":"ES",
    "sg:address":"Rua Garcia Camba, 10",
    "sg:city":"Pontevedra",
    "sg:orig_category":"Bancos",
    "sg:phone":"+34 986 85 60 50",
    "sg:postcode":"36001",
    "sg:province":"Pontevedra",
    "wof:name":"Deutsche Bank S.a.e.",
    "wof:placetype":"venue"
},
  "geometry": {"coordinates":[-8.6443958282,42.4299812317],"type":"Point"}
}