{
  "type": "Feature",
  "properties": {
    "iso:country":"ES",
    "sg:address":"Pase Mikeletes De Los, 16",
    "sg:city":"Donostia-san Sebastian",
    "sg:orig_category":"Arquitectos",
    "sg:phone":"+34 943 21 17 07",
    "sg:postcode":"20008",
    "sg:province":"Guip\u00f9zcoa",
    "wof:name":"Lizancos Aguirre Juan Antonio",
    "wof:placetype":"venue"
},
  "geometry": {"coordinates":[-2.0392899513,43.3088798523],"type":"Point"}
}