{
  "type": "Feature",
  "properties": {
    "addr:full":"Calle de Mayor, 1 Biescas Huesca 22630",
    "addr:housenumber":"1",
    "addr:postcode":"22630",
    "addr:street":"Calle De Mayor",
    "iso:country":"ES",
    "sg:address":"Calle de Mayor, 1",
    "sg:city":"Biescas",
    "sg:orig_category":"Bancos",
    "sg:phone":"+34 974 48 50 15",
    "sg:postcode":"22630",
    "sg:province":"Huesca",
    "wof:name":"Banco Espa\u00f1ol De Credito S.a.",
    "wof:placetype":"venue"
},
  "geometry": {"coordinates":[-0.32130301,42.6287307739],"type":"Point"}
}