{
  "type": "Feature",
  "properties": {
    "iso:country":"ES",
    "sg:address":"Calle de Reverendo Padre Gomez, 3",
    "sg:city":"Cabez\u00f3n Sal",
    "sg:orig_category":"Art\u00cdculos De Regalo (al Por Menor)",
    "sg:phone":"+34 942 70 10 54",
    "sg:postcode":"39500",
    "sg:province":"Cantabria",
    "wof:name":"Ena Escalante Valera",
    "wof:placetype":"venue"
},
  "geometry": {"coordinates":[-4.2374691963,43.3085784912],"type":"Point"}
}