{
  "type": "Feature",
  "properties": {
    "addr:full":"Ctra Soria, Km. 0015,2 Tudela Duero Valladolid 47320",
    "addr:postcode":"47320",
    "addr:street":"Ctra Soria Km. 0015,2",
    "iso:country":"ES",
    "sg:address":"Ctra Soria, Km. 0015,2",
    "sg:city":"Tudela Duero",
    "sg:orig_category":"Mec\u00c1nico Del Autom\u00d3vil",
    "sg:phone":"+34 983 52 04 12",
    "sg:postcode":"47320",
    "sg:province":"Valladolid",
    "wof:name":"Garcia Sanchez Maria Rosa",
    "wof:placetype":"venue"
},
  "geometry": {"coordinates":[-4.454182148,41.507068634],"type":"Point"}
}