{
  "type": "Feature",
  "properties": {
    "iso:country":"ES",
    "sg:address":"Calle de Artemi Semidan, 49",
    "sg:city":"Palmas De Gran Canaria",
    "sg:orig_category":"Construcci\u00d3n Mec\u00c1nica",
    "sg:phone":"+34 928 46 11 59",
    "sg:postcode":"35009",
    "sg:province":"Las Palmas",
    "wof:name":"Taller Hermanos Palmes S.c.p.",
    "wof:placetype":"venue"
},
  "geometry": {"coordinates":[-15.4257688522,28.1515045166],"type":"Point"}
}