{
  "type": "Feature",
  "properties": {
    "iso:country":"ES",
    "sg:address":"Calle de Leon Y Castillo, 411",
    "sg:city":"Palmas De Gran Canaria",
    "sg:orig_category":"Agencias Y Asesores De Publicidad",
    "sg:phone":"+34 928 22 42 20",
    "sg:postcode":"35007",
    "sg:province":"Las Palmas",
    "wof:name":"Loren's Moreira S.l.",
    "wof:placetype":"venue"
},
  "geometry": {"coordinates":[-15.4305686951,28.1383094788],"type":"Point"}
}