{
  "type": "Feature",
  "properties": {
    "iso:country":"ES",
    "sg:address":"Carretera Casablanca, S/n",
    "sg:city":"Buenavista Norte",
    "sg:orig_category":"Abogados",
    "sg:phone":"+34 922 12 73 84",
    "sg:postcode":"38480",
    "sg:province":"Santa Cruz De Tenerife",
    "wof:name":"Gonzalez Dorta Miguel Jose",
    "wof:placetype":"venue"
},
  "geometry": {"coordinates":[-16.8514194489,28.3723888397],"type":"Point"}
}