{
  "type": "Feature",
  "properties": {
    "iso:country":"ES",
    "sg:address":"Ctra Valencia, S/n",
    "sg:city":"S. Juan Alicante",
    "sg:orig_category":"Fabricaci\u00d3n De Enlosados, Soler\u00cdas",
    "sg:phone":"+34 965 65 58 72",
    "sg:postcode":"03550",
    "sg:province":"Alicante",
    "sg:website":"www.saloni.com",
    "wof:name":"Ceramica Saloni",
    "wof:placetype":"venue"
},
  "geometry": {"coordinates":[-0.4289290011,38.400390625],"type":"Point"}
}