{
  "type": "Feature",
  "properties": {
    "addr:full":"Calle de Jazmin, 18 Madrid Madrid 28033",
    "addr:housenumber":"18",
    "addr:postcode":"madrid;28033",
    "addr:street":"Calle De Jazmin",
    "iso:country":"ES",
    "sg:address":"Calle de Jazmin, 18",
    "sg:city":"Madrid",
    "sg:orig_category":"\u00d3ptica: Instrumentos (fabricaci\u00d3n)",
    "sg:phone":"+34 917 66 82 11",
    "sg:postcode":"28033",
    "sg:province":"Madrid",
    "wof:name":"Rubio Alvarez Juan Jose",
    "wof:placetype":"venue"
},
  "geometry": {"coordinates":[-3.6672530174,40.4780883789],"type":"Point"}
}