{
  "type": "Feature",
  "properties": {
    "iso:country":"ES",
    "sg:address":"Calle de Santa Quiteria, 6",
    "sg:city":"Burlada",
    "sg:orig_category":"Empresas De Pintura Y Revestimientos",
    "sg:phone":"+34 948 14 62 56",
    "sg:postcode":"31600",
    "sg:province":"Navarra",
    "wof:name":"Iriarte Larrayoz Luis",
    "wof:placetype":"venue"
},
  "geometry": {"coordinates":[-1.6160060167,42.8253440857],"type":"Point"}
}