{
  "type": "Feature",
  "properties": {
    "iso:country":"ES",
    "sg:address":"Calle de Jose Luis Palomar, 4",
    "sg:city":"Soria",
    "sg:orig_category":"Peluquer\u00cdas, Peluquer\u00cda Mixta",
    "sg:phone":"+34 975 22 96 63",
    "sg:postcode":"42005",
    "sg:province":"Soria",
    "wof:name":"Ruiz Corredor Maria Jose",
    "wof:placetype":"venue"
},
  "geometry": {"coordinates":[-2.473279953,41.7709541321],"type":"Point"}
}