{
  "type": "Feature",
  "properties": {
    "addr:full":"Calle de Miguel De Cervantes (de), 7 Colmenar Viejo Madrid 28770",
    "addr:postcode":"28770",
    "addr:street":"Calle De Miguel De Cervantes De",
    "iso:country":"ES",
    "sg:address":"Calle de Miguel De Cervantes (de), 7",
    "sg:city":"Colmenar Viejo",
    "sg:orig_category":"Centros De Educaci\u00d3n Especial",
    "sg:phone":"+34 918 45 50 04",
    "sg:postcode":"28770",
    "sg:province":"Madrid",
    "wof:name":"Colegio Publico Antonio Machado",
    "wof:placetype":"venue"
},
  "geometry": {"coordinates":[-3.7764830589,40.663646698],"type":"Point"}
}