{
  "type": "Feature",
  "properties": {
    "addr:full":"Pla\u00c7 Lluis Companys, 1 Vidreres Girona 17411",
    "addr:housenumber":"1",
    "addr:postcode":"17411",
    "addr:street":"Companys",
    "iso:country":"ES",
    "sg:address":"Pla\u00c7 Lluis Companys, 1",
    "sg:city":"Vidreres",
    "sg:orig_category":"Puericultora",
    "sg:phone":"+34 972 85 09 16",
    "sg:postcode":"17411",
    "sg:province":"Girona",
    "wof:name":"Gama Cincuanta S.l.",
    "wof:placetype":"venue"
},
  "geometry": {"coordinates":[2.7787849903,41.7893218994],"type":"Point"}
}