{
  "type": "Feature",
  "properties": {
    "iso:country":"ES",
    "sg:address":"Calle de Eleizalde, S/n",
    "sg:city":"Moreaga",
    "sg:orig_category":"Peluqueros: De Se\u00d1oras",
    "sg:phone":"+34 946 76 53 70",
    "sg:postcode":"48600",
    "sg:province":"Vizcaya",
    "wof:name":"Rodriguez Villardon Maria Antonia",
    "wof:placetype":"venue"
},
  "geometry": {"coordinates":[-2.9825758934,43.3806724548],"type":"Point"}
}