{
  "type": "Feature",
  "properties": {
    "iso:country":"ES",
    "sg:address":"Poblado De San Francisco, S/n",
    "sg:city":"San Francisco",
    "sg:orig_category":"Molduras, Junquillos, Listones Y Molduras Perforadas",
    "sg:phone":"+34 950 47 04 92",
    "sg:postcode":"04600",
    "sg:province":"Almer\u00eda",
    "wof:name":"Miron Sanchez Feliciana",
    "wof:placetype":"venue"
},
  "geometry": {"coordinates":[-1.878254056,37.4218711853],"type":"Point"}
}