{
  "type": "Feature",
  "properties": {
    "addr:full":"Carrer de Consell De Cent, 253 Barcelona Barcelona 08011",
    "addr:housenumber":"253",
    "addr:postcode":"08011",
    "addr:street":"Carrer De Consell De Cent",
    "iso:country":"ES",
    "sg:address":"Carrer de Consell De Cent, 253",
    "sg:city":"Barcelona",
    "sg:orig_category":"Farmacias",
    "sg:phone":"+34 934 53 47 04",
    "sg:postcode":"08011",
    "sg:province":"Barcelona",
    "wof:name":"Alomar Ferrer Patricia",
    "wof:placetype":"venue"
},
  "geometry": {"coordinates":[2.1596477032,41.3865585327],"type":"Point"}
}