{
  "type": "Feature",
  "properties": {
    "addr:full":"Calle de Quart, 103 Valencia Valencia 46008",
    "addr:housenumber":"103",
    "addr:postcode":"46008",
    "addr:street":"Calle De Quart",
    "iso:country":"ES",
    "sg:address":"Calle de Quart, 103",
    "sg:city":"Valencia",
    "sg:orig_category":"Peluquer\u00cdas, Peluquer\u00cda Mixta",
    "sg:phone":"+34 963 91 68 43",
    "sg:postcode":"46008",
    "sg:province":"Valencia",
    "wof:name":"Lazaro Soler Javier",
    "wof:placetype":"venue"
},
  "geometry": {"coordinates":[-0.3878419995,39.4750175476],"type":"Point"}
}