{
  "type": "Feature",
  "properties": {
    "iso:country":"ES",
    "sg:address":"Carr Anselm Turmeda, 5",
    "sg:city":"Algaida",
    "sg:classifiers":[
        {
            "category":"Autos & Motor Vehicles",
            "subcategory":"Automobile Sales",
            "type":"Retail Goods"
        }
    ],
    "sg:phone":"+34 971 66 50 31",
    "sg:postcode":"07210",
    "sg:province":"Islas Baleares",
    "wof:name":"Gonzalez Alvarez Justo",
    "wof:placetype":"venue"
},
  "geometry": {"coordinates":[2.897589922,39.5593910217],"type":"Point"}
}