{
  "type": "Feature",
  "properties": {
    "iso:country":"ES",
    "sg:address":"Calle de Pescarranas, 32",
    "sg:city":"Alcorisa",
    "sg:orig_category":"Asociaciones Y Clubs Deportivos",
    "sg:phone":"+34 978 84 07 63",
    "sg:postcode":"44550",
    "sg:province":"Teruel",
    "wof:name":"Pe\u00f1a Zaragocista Juan Se\u00f1or",
    "wof:placetype":"venue"
},
  "geometry": {"coordinates":[-0.3786149919,40.8920974731],"type":"Point"}
}