{
  "type": "Feature",
  "properties": {
    "iso:country":"ES",
    "sg:address":"Calle de Rafael Finat, 14",
    "sg:city":"Madrid",
    "sg:orig_category":"Florister\u00cdas",
    "sg:phone":"+34 917 06 07 48",
    "sg:postcode":"28044",
    "sg:province":"Madrid",
    "wof:name":"Diaz Correas Eugenio",
    "wof:placetype":"venue"
},
  "geometry": {"coordinates":[-3.7659330368,40.3831481934],"type":"Point"}
}