{
  "type": "Feature",
  "properties": {
    "iso:country":"ES",
    "sg:address":"Pg Sant Joan, 128",
    "sg:city":"Barcelona",
    "sg:orig_category":"Aparcamientos (infraestructuras, Accesorios)",
    "sg:phone":"+34 932 07 54 01",
    "sg:postcode":"08037",
    "sg:province":"Barcelona",
    "wof:name":"Aparcamientos Chile S. A.",
    "wof:placetype":"venue"
},
  "geometry": {"coordinates":[2.1678152084,41.4010009766],"type":"Point"}
}