{
  "type": "Feature",
  "properties": {
    "addr:full":"Calle de Olivo (del), 25 Arganda Madrid 28500",
    "addr:housenumber":"25",
    "addr:postcode":"28500",
    "addr:street":"Calle De Olivo Del",
    "iso:country":"ES",
    "sg:address":"Calle de Olivo (del), 25",
    "sg:city":"Arganda",
    "sg:orig_category":"Maquinaria Para Industrias Diversas",
    "sg:phone":"+34 918 70 44 30",
    "sg:postcode":"28500",
    "sg:province":"Madrid",
    "wof:name":"Mecanizados An-pe S.l.",
    "wof:placetype":"venue"
},
  "geometry": {"coordinates":[-3.4621889591,40.3137817383],"type":"Point"}
}