{
  "type": "Feature",
  "properties": {
    "addr:full":"Avda Primero De Mayo, 68 Algaba Sevilla 41980",
    "addr:housenumber":"68",
    "addr:postcode":"41980",
    "addr:street":"Avda Primero De Mayo",
    "iso:country":"ES",
    "sg:address":"Avda Primero De Mayo, 68",
    "sg:city":"Algaba",
    "sg:orig_category":"Frutas, Legumbres Frescas Y Tempranas (al Por Menor)",
    "sg:phone":"+34 955 78 74 85",
    "sg:postcode":"41980",
    "sg:province":"Sevilla",
    "wof:name":"Bazan Robles Manuel",
    "wof:placetype":"venue"
},
  "geometry": {"coordinates":[-6.0109019279,37.4620018005],"type":"Point"}
}