{
  "type": "Feature",
  "properties": {
    "iso:country":"ES",
    "sg:address":"Calle de Isla De Lobos, 9",
    "sg:city":"Costa Teguise",
    "sg:orig_category":"Ense\u00d1anza: Idiomas",
    "sg:phone":"+34 928 82 66 17",
    "sg:postcode":"35509",
    "sg:province":"Las Palmas",
    "wof:name":"Smith  Eric John",
    "wof:placetype":"venue"
},
  "geometry": {"coordinates":[-13.4914770126,29.0053825378],"type":"Point"}
}