{
  "type": "Feature",
  "properties": {
    "addr:full":"Calle de Principe De Asturias, 2 Coin M\u00e1laga 29100",
    "addr:housenumber":"2",
    "addr:postcode":"29100",
    "addr:street":"Calle De Principe De Asturias;Ma\u0301Laga",
    "iso:country":"ES",
    "sg:address":"Calle de Principe De Asturias, 2",
    "sg:city":"Coin",
    "sg:orig_category":"Comercio, Reparaci\u00d3n De Motocicletas, Bicicletas Y Piezas Sueltas",
    "sg:phone":"+34 952 45 36 98",
    "sg:postcode":"29100",
    "sg:province":"M\u00e1laga",
    "wof:name":"Sanchez Millan Salvador",
    "wof:placetype":"venue"
},
  "geometry": {"coordinates":[-4.7547550201,36.6623916626],"type":"Point"}
}