{
  "type": "Feature",
  "properties": {
    "iso:country":"ES",
    "sg:address":"Calle de Jesus Y Maria, 29",
    "sg:city":"San Gregorio",
    "sg:orig_category":"Asilos De Ancianos. Centros Privados",
    "sg:phone":"+34 976 52 65 32",
    "sg:postcode":"50015",
    "sg:province":"Zaragoza",
    "wof:name":"Servicios Geriatricos San Gregorio S.l.",
    "wof:placetype":"venue"
},
  "geometry": {"coordinates":[-0.8678839803,41.6944007874],"type":"Point"}
}