{
  "type": "Feature",
  "properties": {
    "iso:country":"ES",
    "sg:address":"Avda Soria, Km. 0357,6",
    "sg:city":"Valladolid",
    "sg:orig_category":"Centros Empresariales",
    "sg:phone":"+34 983 30 27 31",
    "sg:postcode":"47012",
    "sg:province":"Valladolid",
    "wof:name":"Barrero Arteaga Ignacion Felix",
    "wof:placetype":"venue"
},
  "geometry": {"coordinates":[-4.695494175,41.6288452148],"type":"Point"}
}