{
  "type": "Feature",
  "properties": {
    "iso:country":"ES",
    "sg:address":"Calle de Granada, 2",
    "sg:city":"Otura",
    "sg:orig_category":"Farmacias",
    "sg:phone":"+34 958 55 50 66",
    "sg:postcode":"18630",
    "sg:province":"Granada",
    "wof:name":"Gomez La Mayor Purificacion",
    "wof:placetype":"venue"
},
  "geometry": {"coordinates":[-3.6358559132,37.0908660889],"type":"Point"}
}