{
  "type": "Feature",
  "properties": {
    "addr:full":"Rua Santiago De Chile (de), 16 Santiago De Compostela La Coru\u00f1a 15706",
    "addr:housenumber":"16",
    "addr:postcode":"15706",
    "addr:street":"Rua Santiago De Chile De;Corun\u0303A",
    "iso:country":"ES",
    "sg:address":"Rua Santiago De Chile (de), 16",
    "sg:city":"Santiago De Compostela",
    "sg:orig_category":"Abogados",
    "sg:phone":"+34 981 59 57 25",
    "sg:postcode":"15706",
    "sg:province":"La Coru\u00f1a",
    "wof:name":"Ferrer Jaureguizar Ricardo",
    "wof:placetype":"venue"
},
  "geometry": {"coordinates":[-8.5507116318,42.8720932007],"type":"Point"}
}