{
  "type": "Feature",
  "properties": {
    "iso:country":"ES",
    "sg:address":"Calle de Fronton, S/n",
    "sg:city":"Villanueva Alcardete",
    "sg:orig_category":"Maquinaria Para Industrias Diversas",
    "sg:phone":"+34 925 16 70 39",
    "sg:postcode":"45810",
    "sg:province":"Toledo",
    "wof:name":"Fatero Santos Daniel",
    "wof:placetype":"venue"
},
  "geometry": {"coordinates":[-3.0220088959,39.6750411987],"type":"Point"}
}