{
  "type": "Feature",
  "properties": {
    "iso:country":"ES",
    "sg:address":"Av. Pio Xii, 55",
    "sg:city":"Iru\u00f1a",
    "sg:orig_category":"Empresarios",
    "sg:phone":"+34 948 19 47 00",
    "sg:postcode":"31...",
    "sg:province":"Navarra",
    "sg:website":"www.cima.es",
    "wof:name":"Fundacion Para La Investigacion Medica Aplicada",
    "wof:placetype":"venue"
},
  "geometry": {"coordinates":[-1.6586179733,42.8088378906],"type":"Point"}
}