{
  "type": "Feature",
  "properties": {
    "addr:full":"Calle de Muelle, 5 Mutriku Guip\u00f9zcoa 20830",
    "addr:housenumber":"5",
    "addr:postcode":"20830",
    "addr:street":"Calle De Muelle;Guipu\u0300Zcoa",
    "iso:country":"ES",
    "sg:address":"Calle de Muelle, 5",
    "sg:city":"Mutriku",
    "sg:orig_category":"Deportes N\u00c1uticos, Acu\u00c1ticos Y Subacu\u00c1ticos: Art\u00cdculos Y Equipo (al Por Menor)",
    "sg:phone":"+34 943 60 38 72",
    "sg:postcode":"20830",
    "sg:province":"Guip\u00f9zcoa",
    "wof:name":"Alcorta Churruca Pedro",
    "wof:placetype":"venue"
},
  "geometry": {"coordinates":[-2.3839561939,43.3078460693],"type":"Point"}
}