{
  "type": "Feature",
  "properties": {
    "addr:full":"Calle de Marques De La Hermida, 12 Santander Cantabria 39009",
    "addr:housenumber":"12",
    "addr:postcode":"39009",
    "addr:street":"Calle De Marques De La Hermida",
    "iso:country":"ES",
    "sg:address":"Calle de Marques De La Hermida, 12",
    "sg:city":"Santander",
    "sg:orig_category":"Delegados, Agentes De Tr\u00c1nsito, Auxiliares De Transporte Internacional",
    "sg:phone":"+34 942 36 38 58",
    "sg:postcode":"39009",
    "sg:province":"Cantabria",
    "sg:website":"www.transportesanero.com",
    "wof:name":"Transportes Anero S.l.",
    "wof:placetype":"venue"
},
  "geometry": {"coordinates":[-3.8130931854,43.4555091858],"type":"Point"}
}