{
  "type": "Feature",
  "properties": {
    "addr:full":"Carrer de Carmen Desvalls, 9 Segur Calafell Tarragona 43882",
    "addr:housenumber":"9",
    "addr:postcode":"43882",
    "addr:street":"Carrer De Carmen Desvalls",
    "iso:country":"ES",
    "sg:address":"Carrer de Carmen Desvalls, 9",
    "sg:city":"Segur Calafell",
    "sg:orig_category":"Bares, Piano",
    "sg:phone":"+34 977 16 37 84",
    "sg:postcode":"43882",
    "sg:province":"Tarragona",
    "sg:website":"www.imad.com",
    "wof:name":"Ciber I Mad S.l",
    "wof:placetype":"venue"
},
  "geometry": {"coordinates":[1.6025240421,41.1904945374],"type":"Point"}
}