{
  "type": "Feature",
  "properties": {
    "iso:country":"ES",
    "sg:address":"Calle de Trafalgar, 33",
    "sg:city":"Valencia",
    "sg:orig_category":"Condimentos, Especias, Vinagres, Salsas Preparadas (fabricaci\u00d3n, Al Por Mayor)",
    "sg:phone":"+34 963 31 10 90",
    "sg:postcode":"46023",
    "sg:province":"Valencia",
    "wof:name":"Pascual Carrasco Julio",
    "wof:placetype":"venue"
},
  "geometry": {"coordinates":[-0.3448399901,39.4613647461],"type":"Point"}
}