{
  "type": "Feature",
  "properties": {
    "iso:country":"ES",
    "sg:address":"Calle de San Gregorio, 5",
    "sg:city":"Villanueva Cordoba",
    "sg:orig_category":"Centros Comerciales Y Grandes Tiendas",
    "sg:phone":"+34 957 12 22 86",
    "sg:postcode":"14440",
    "sg:province":"C\u00f3rdoba",
    "wof:name":"Rico Cabrera Enrique",
    "wof:placetype":"venue"
},
  "geometry": {"coordinates":[-4.6251020432,38.3227577209],"type":"Point"}
}