{
  "type": "Feature",
  "properties": {
    "iso:country":"ES",
    "sg:address":"Carrer de Platja, 72",
    "sg:city":"Peguera",
    "sg:orig_category":"Electrodom\u00c9sticos (al Por Menor)",
    "sg:phone":"+34 971 68 73 49",
    "sg:postcode":"07160",
    "sg:province":"Islas Baleares",
    "wof:name":"Martinez Gomez Jose Antonio",
    "wof:placetype":"venue"
},
  "geometry": {"coordinates":[2.4549601078,39.5355491638],"type":"Point"}
}