{
  "type": "Feature",
  "properties": {
    "iso:country":"ES",
    "sg:address":"Carrer de Eugeni D'ors, 25",
    "sg:city":"Vilafranca Penedes",
    "sg:orig_category":"Limpieza Industrial",
    "sg:phone":"+34 938 90 46 18",
    "sg:postcode":"08720",
    "sg:province":"Barcelona",
    "wof:name":"Rentat Roba Juncosa S.l.",
    "wof:placetype":"venue"
},
  "geometry": {"coordinates":[1.693027854,41.3446731567],"type":"Point"}
}