{
  "type": "Feature",
  "properties": {
    "iso:country":"ES",
    "sg:address":"Calle de Ramon Y Cajal, 13",
    "sg:city":"Granada",
    "sg:orig_category":"Empresas De Pintura Y Revestimientos",
    "sg:phone":"+34 958 27 85 38",
    "sg:postcode":"18003",
    "sg:province":"Granada",
    "wof:name":"Jose Manuel Gomez Nogueray Otro C.b.",
    "wof:placetype":"venue"
},
  "geometry": {"coordinates":[-3.6156640053,37.1824913025],"type":"Point"}
}