{
  "type": "Feature",
  "properties": {
    "iso:country":"ES",
    "sg:address":"Carr Ter, 10",
    "sg:city":"Empuriabrava",
    "sg:orig_category":"Promotores Constructores",
    "sg:phone":"+34 972 45 11 30",
    "sg:postcode":"17487",
    "sg:province":"Girona",
    "wof:name":"Dvn Holding S.l",
    "wof:placetype":"venue"
},
  "geometry": {"coordinates":[3.1070549488,42.2568092346],"type":"Point"}
}