{
  "type": "Feature",
  "properties": {
    "iso:country":"ES",
    "sg:address":"Carrer de Mestre Nicolau, 7",
    "sg:city":"Barcelona",
    "sg:orig_category":"Doctores En Medicina",
    "sg:phone":"+34 932 09 18 68",
    "sg:postcode":"08021",
    "sg:province":"Barcelona",
    "wof:name":"Sostres Ferrer Ramon",
    "wof:placetype":"venue"
},
  "geometry": {"coordinates":[2.1417899132,41.3929290771],"type":"Point"}
}