{
  "type": "Feature",
  "properties": {
    "iso:country":"ES",
    "sg:address":"Ctra San Martin De Valdeiglesias, Km. 0001,3",
    "sg:city":"Carretera De San Martin",
    "sg:orig_category":"Ense\u00d1anza Variada",
    "sg:phone":"+34 916 10 12 09",
    "sg:postcode":"28925",
    "sg:province":"Madrid",
    "wof:name":"Formacion Y Gestion Hostelera S.l",
    "wof:placetype":"venue"
},
  "geometry": {"coordinates":[-3.8353390694,40.3956756592],"type":"Point"}
}