{
  "type": "Feature",
  "properties": {
    "iso:country":"ES",
    "sg:address":"Andres Ramirez, 1",
    "sg:city":"Chauchina",
    "sg:orig_category":"Producci\u00d3n, Comercio De Cereales",
    "sg:phone":"+34 958 44 70 29",
    "sg:postcode":"18330",
    "sg:province":"Granada",
    "wof:name":"Fernandez Hernandez Jose",
    "wof:placetype":"venue"
},
  "geometry": {"coordinates":[-3.7684431076,37.2015151978],"type":"Point"}
}