{
  "type": "Feature",
  "properties": {
    "addr:full":"Carrer de Ciutadella Menorca, 3 Palma Islas Baleares 07007",
    "addr:housenumber":"3",
    "addr:postcode":"07007",
    "addr:street":"Carrer De Ciutadella Menorca",
    "iso:country":"ES",
    "sg:address":"Carrer de Ciutadella Menorca, 3",
    "sg:city":"Palma",
    "sg:orig_category":"Material Y Suministros Para Imprenta E Industrias Gr\u00c1ficas",
    "sg:phone":"+34 971 24 44 31",
    "sg:postcode":"07007",
    "sg:province":"Islas Baleares",
    "sg:website":"www.italoagendassa.es",
    "wof:name":"Italoagendas S.a.",
    "wof:placetype":"venue"
},
  "geometry": {"coordinates":[2.6825869083,39.5563621521],"type":"Point"}
}