{
  "type": "Feature",
  "properties": {
    "addr:full":"Calle de Arias Montano, 11 Fregenal Sierra Badajoz 06340",
    "addr:housenumber":"11",
    "addr:postcode":"06340",
    "addr:street":"Calle De Arias Montano",
    "iso:country":"ES",
    "sg:address":"Calle de Arias Montano, 11",
    "sg:city":"Fregenal Sierra",
    "sg:orig_category":"Agencias Y Agentes Comerciales, Representantes",
    "sg:phone":"+34 924 70 08 45",
    "sg:postcode":"06340",
    "sg:province":"Badajoz",
    "wof:name":"Gallardo Dominguez Francisco",
    "wof:placetype":"venue"
},
  "geometry": {"coordinates":[-6.6539731026,38.168296814],"type":"Point"}
}