{
  "type": "Feature",
  "properties": {
    "addr:full":"Calle de Bustillo Del Oro, 23 Madrid Madrid 28039",
    "addr:housenumber":"23",
    "addr:postcode":"madrid;28039",
    "addr:street":"Calle De Bustillo Del Oro",
    "iso:country":"ES",
    "sg:address":"Calle de Bustillo Del Oro, 23",
    "sg:city":"Madrid",
    "sg:orig_category":"Cerrajer\u00cda, Ferrallista",
    "sg:phone":"+34 913 11 14 32",
    "sg:postcode":"28039",
    "sg:province":"Madrid",
    "wof:name":"Perez Perez Gines",
    "wof:placetype":"venue"
},
  "geometry": {"coordinates":[-3.7073435783,40.461063385],"type":"Point"}
}