{
  "type": "Feature",
  "properties": {
    "addr:full":"Av Garraf, 27 Vilanova I La Geltru Barcelona 08800",
    "addr:housenumber":"27",
    "addr:postcode":"08800",
    "addr:street":"Av Garraf",
    "iso:country":"ES",
    "sg:address":"Av Garraf, 27",
    "sg:city":"Vilanova I La Geltru",
    "sg:orig_category":"Estudios, Instalaci\u00d3n De Climatizaci\u00d3n",
    "sg:phone":"+34 938 93 01 77",
    "sg:postcode":"08800",
    "sg:province":"Barcelona",
    "wof:name":"Amo Balsas Maria Dolores",
    "wof:placetype":"venue"
},
  "geometry": {"coordinates":[1.7311733961,41.2236595154],"type":"Point"}
}