{
  "type": "Feature",
  "properties": {
    "addr:full":"Calle de Hilarion Eslava, 5 Madrid Madrid 28015",
    "addr:housenumber":"5",
    "addr:postcode":"28015",
    "addr:street":"Calle De Hilarion Eslava",
    "iso:country":"ES",
    "sg:address":"Calle de Hilarion Eslava, 5",
    "sg:city":"Madrid",
    "sg:orig_category":"Centros Empresariales",
    "sg:phone":"+34 915 49 16 86",
    "sg:postcode":"28015",
    "sg:province":"Madrid",
    "wof:name":"Wilson  Rebecca",
    "wof:placetype":"venue"
},
  "geometry": {"coordinates":[-3.7168693542,40.4324188232],"type":"Point"}
}