{
  "type": "Feature",
  "properties": {
    "addr:full":"Carrer de Gaieta Ventallo, 33 Mollet Valles Barcelona 08100",
    "addr:housenumber":"33",
    "addr:postcode":"08100",
    "addr:street":"Carrer De Gaieta Ventallo",
    "iso:country":"ES",
    "sg:address":"Carrer de Gaieta Ventallo, 33",
    "sg:city":"Mollet Valles",
    "sg:orig_category":"Molduras, Junquillos, Listones Y Molduras Perforadas",
    "sg:phone":"+34 935 70 76 86",
    "sg:postcode":"08100",
    "sg:province":"Barcelona",
    "wof:name":"Marin Murillo Amelia",
    "wof:placetype":"venue"
},
  "geometry": {"coordinates":[2.2143959999,41.5396575928],"type":"Point"}
}