{
  "type": "Feature",
  "properties": {
    "addr:full":"Calle de Pergolas, 5 Cadiz C\u00e1diz 11007",
    "addr:housenumber":"5",
    "addr:postcode":"11007",
    "addr:street":"Calle De Pergolas",
    "iso:country":"ES",
    "sg:address":"Calle de Pergolas, 5",
    "sg:city":"Cadiz",
    "sg:orig_category":"Ense\u00d1anza: Idiomas",
    "sg:phone":"+34 956 26 05 57",
    "sg:postcode":"11007",
    "sg:province":"C\u00e1diz",
    "wof:name":"Escuela Internacional De Espa\u00f1ol Gadir S.l.",
    "wof:placetype":"venue"
},
  "geometry": {"coordinates":[-6.2856359482,36.5252227783],"type":"Point"}
}