{
  "type": "Feature",
  "properties": {
    "addr:full":"Calle de Atocha, 70 Madrid Madrid 28012",
    "addr:housenumber":"70",
    "addr:postcode":"madrid;28012",
    "addr:street":"Calle De Atocha",
    "iso:country":"ES",
    "sg:address":"Calle de Atocha, 70",
    "sg:city":"Madrid",
    "sg:orig_category":"Bisuteros (fabricaci\u00d3n, Al Por Mayor)",
    "sg:phone":"+34 915 28 46 01",
    "sg:postcode":"28012",
    "sg:province":"Madrid",
    "wof:name":"Montura Y Dise\u00f1o S.l.",
    "wof:placetype":"venue"
},
  "geometry": {"coordinates":[-3.6978075504,40.4116249084],"type":"Point"}
}