{
  "type": "Feature",
  "properties": {
    "addr:full":"Avda Mariano Vicen, 4 Soria Soria 42003",
    "addr:housenumber":"4",
    "addr:postcode":"42003",
    "addr:street":"Avda Mariano Vicen",
    "iso:country":"ES",
    "sg:address":"Avda Mariano Vicen, 4",
    "sg:city":"Soria",
    "sg:orig_category":"Procuradores",
    "sg:phone":"+34 975 23 27 77",
    "sg:postcode":"42003",
    "sg:province":"Soria",
    "wof:name":"Ya\u00f1ez Sanchez Carmen Maria",
    "wof:placetype":"venue"
},
  "geometry": {"coordinates":[-2.4700434208,41.7618942261],"type":"Point"}
}