{
  "type": "Feature",
  "properties": {
    "iso:country":"ES",
    "sg:address":"Calle de Miguel Ortiz, 8",
    "sg:city":"Tardienta",
    "sg:orig_category":"Alimentaci\u00d3n General (al Por Menor)",
    "sg:phone":"+34 974 25 30 03",
    "sg:postcode":"22240",
    "sg:province":"Huesca",
    "wof:name":"Ortiz Oses Javier",
    "wof:placetype":"venue"
},
  "geometry": {"coordinates":[-0.5370879769,41.9792289734],"type":"Point"}
}