{
  "type": "Feature",
  "properties": {
    "iso:country":"ES",
    "sg:address":"Calle de Hernan Perez Del Pulgar, 2",
    "sg:city":"Ciudad Real",
    "sg:orig_category":"M\u00c9dicos: Cirug\u00cda Urol\u00d3gica",
    "sg:phone":"+34 926 22 23 17",
    "sg:postcode":"13001",
    "sg:province":"Ciudad Real",
    "wof:name":"Martinez Urzay German",
    "wof:placetype":"venue"
},
  "geometry": {"coordinates":[-3.9274189472,38.9835281372],"type":"Point"}
}