{
  "type": "Feature",
  "properties": {
    "addr:full":"Calle de Virgen De Lourdes, 12 Madrid Madrid 28027",
    "addr:housenumber":"12",
    "addr:postcode":"madrid;28027",
    "addr:street":"Calle De Virgen De Lourdes",
    "iso:country":"ES",
    "sg:address":"Calle de Virgen De Lourdes, 12",
    "sg:city":"Madrid",
    "sg:orig_category":"Cables Y Hilos El\u00c9ctricos (fabricaci\u00d3n, Al Por Mayor)",
    "sg:phone":"+34 914 05 91 80",
    "sg:postcode":"28027",
    "sg:province":"Madrid",
    "wof:name":"Coemi Comunicaciones Y Electronica S.l.",
    "wof:placetype":"venue"
},
  "geometry": {"coordinates":[-3.6583640575,40.436050415],"type":"Point"}
}