{
  "type": "Feature",
  "properties": {
    "addr:full":"Avda Valencia, 1 Calpe Alicante 03710",
    "addr:housenumber":"1",
    "addr:postcode":"03710",
    "addr:street":"Avda Valencia",
    "iso:country":"ES",
    "sg:address":"Avda Valencia, 1",
    "sg:city":"Calpe",
    "sg:orig_category":"Dise\u00d1o Industrial",
    "sg:phone":"+34 965 83 09 96",
    "sg:postcode":"03710",
    "sg:province":"Alicante",
    "wof:name":"Ifacgrafigs S.l",
    "wof:placetype":"venue"
},
  "geometry": {"coordinates":[0.0453809984,38.6439208984],"type":"Point"}
}