{
  "type": "Feature",
  "properties": {
    "iso:country":"ES",
    "sg:address":"G.v. Corts Catalanes, 1072",
    "sg:city":"Barcelona",
    "sg:orig_category":"Reposter\u00cdas",
    "sg:phone":"+34 933 08 26 89",
    "sg:postcode":"08020",
    "sg:province":"Barcelona",
    "wof:name":"Forns Enrich S.l.",
    "wof:placetype":"venue"
},
  "geometry": {"coordinates":[2.2026519775,41.4146690369],"type":"Point"}
}