{
  "type": "Feature",
  "properties": {
    "addr:full":"Carr Llibertat, 18 Tornabous Lleida 25331",
    "addr:housenumber":"18",
    "addr:postcode":"25331",
    "addr:street":"Carr Llibertat",
    "iso:country":"ES",
    "sg:address":"Carr Llibertat, 18",
    "sg:city":"Tornabous",
    "sg:orig_category":"Equipo De Refrigeraci\u00d3n Industrial",
    "sg:phone":"+34 973 57 02 32",
    "sg:postcode":"25331",
    "sg:province":"Lleida",
    "wof:name":"Farre Monels Florencio",
    "wof:placetype":"venue"
},
  "geometry": {"coordinates":[1.0549240112,41.7010002136],"type":"Point"}
}