{
  "type": "Feature",
  "properties": {
    "iso:country":"ES",
    "sg:address":"Calle de Cava, 25",
    "sg:city":"Priego Cordoba",
    "sg:orig_category":"Electricidad: Instaladores",
    "sg:phone":"+34 957 54 13 24",
    "sg:postcode":"14800",
    "sg:province":"C\u00f3rdoba",
    "wof:name":"Electricidad Alcala Zamora S.l.",
    "wof:placetype":"venue"
},
  "geometry": {"coordinates":[-4.1967840195,37.4399223328],"type":"Point"}
}