{
  "type": "Feature",
  "properties": {
    "iso:country":"ES",
    "sg:address":"Calle de Vermondo Resta, 2",
    "sg:city":"Sevilla",
    "sg:orig_category":"Cobro De Pr\u00c9stamos",
    "sg:phone":"+34 954 65 84 75",
    "sg:postcode":"41018",
    "sg:province":"Sevilla",
    "wof:name":"Balear De Datos Y Procesos S.a.",
    "wof:placetype":"venue"
},
  "geometry": {"coordinates":[-5.9789423943,37.3792610168],"type":"Point"}
}