{
  "type": "Feature",
  "properties": {
    "iso:country":"ES",
    "sg:address":"Calle de Maria Moliner, 75",
    "sg:city":"Zaragoza",
    "sg:orig_category":"M\u00c9dicos: Estomatolog\u00cda",
    "sg:phone":"+34 976 25 90 26",
    "sg:postcode":"50007",
    "sg:province":"Zaragoza",
    "wof:name":"Carrera Blecua Fernando",
    "wof:placetype":"venue"
},
  "geometry": {"coordinates":[-0.8796520233,41.6377906799],"type":"Point"}
}