{
  "type": "Feature",
  "properties": {
    "iso:country":"ES",
    "sg:address":"Calle de Imeldo Seris, 20",
    "sg:city":"Santa Cruz De Tenerife",
    "sg:orig_category":"Agentes Generales De Seguros",
    "sg:phone":"+34 922 27 86 23",
    "sg:postcode":"38003",
    "sg:province":"Santa Cruz De Tenerife",
    "wof:name":"Porta Rosello Jose",
    "wof:placetype":"venue"
},
  "geometry": {"coordinates":[-16.2494525909,28.4657459259],"type":"Point"}
}