{
  "type": "Feature",
  "properties": {
    "addr:full":"Calle de Colon, 6 Seijo Pontevedra 36740",
    "addr:housenumber":"6",
    "addr:postcode":"36740",
    "addr:street":"Calle De Colon",
    "iso:country":"ES",
    "sg:address":"Calle de Colon, 6",
    "sg:city":"Seijo",
    "sg:orig_category":"Molduras, Junquillos, Listones Y Molduras Perforadas",
    "sg:phone":"+34 986 62 25 79",
    "sg:postcode":"36740",
    "sg:province":"Pontevedra",
    "wof:name":"Rodriguez Fernandez Manuel",
    "wof:placetype":"venue"
},
  "geometry": {"coordinates":[-8.7436075211,41.9906234741],"type":"Point"}
}