{
  "type": "Feature",
  "properties": {
    "addr:full":"Carr Major, 56 Almenara Castell\u00f3n 12590",
    "addr:housenumber":"56",
    "addr:postcode":"12590",
    "addr:street":"Carr Major",
    "iso:country":"ES",
    "sg:address":"Carr Major, 56",
    "sg:city":"Almenara",
    "sg:orig_category":"Mercer\u00cda, Lencer\u00cda (al Por Menor)",
    "sg:phone":"+34 962 62 40 50",
    "sg:postcode":"12590",
    "sg:province":"Castell\u00f3n",
    "wof:name":"Ten Forner Nuria",
    "wof:placetype":"venue"
},
  "geometry": {"coordinates":[-0.2252819985,39.7522544861],"type":"Point"}
}