{
  "type": "Feature",
  "properties": {
    "iso:country":"ES",
    "sg:address":"Calle de Constitucion, 11",
    "sg:city":"Azuaga",
    "sg:orig_category":"Ebanister\u00cda",
    "sg:phone":"+34 924 89 00 55",
    "sg:postcode":"06920",
    "sg:province":"Badajoz",
    "wof:name":"Alejandre Aldana Trinidad",
    "wof:placetype":"venue"
},
  "geometry": {"coordinates":[-5.6766695976,38.2603569031],"type":"Point"}
}