{
  "type": "Feature",
  "properties": {
    "addr:full":"Calle de Francisco Gourie, 28 Palmas De Gran Canaria Las Palmas 35002",
    "addr:housenumber":"28",
    "addr:postcode":"35002",
    "addr:street":"Calle De Francisco Gourie",
    "iso:country":"ES",
    "sg:address":"Calle de Francisco Gourie, 28",
    "sg:city":"Palmas De Gran Canaria",
    "sg:orig_category":"Procuradores",
    "sg:phone":"+34 928 36 19 08",
    "sg:postcode":"35002",
    "sg:province":"Las Palmas",
    "wof:name":"Cruz Afonso Rita De La",
    "wof:placetype":"venue"
},
  "geometry": {"coordinates":[-15.4154043198,28.1051673889],"type":"Point"}
}