{
  "type": "Feature",
  "properties": {
    "addr:full":"Carretera Cordoba-valencia, S/n Rus Ja\u00e9n 23430",
    "addr:housenumber":"s / n",
    "addr:postcode":"23430",
    "addr:street":"Carretera Cordoba-Valencia;Jae\u0301N",
    "iso:country":"ES",
    "sg:address":"Carretera Cordoba-valencia, S/n",
    "sg:city":"Rus",
    "sg:orig_category":"Bebidas",
    "sg:phone":"+34 953 77 09 16",
    "sg:postcode":"23430",
    "sg:province":"Ja\u00e9n",
    "wof:name":"Campos Siles Manuel",
    "wof:placetype":"venue"
},
  "geometry": {"coordinates":[-3.4641931057,38.0461196899],"type":"Point"}
}