{
  "type": "Feature",
  "properties": {
    "addr:full":"Barrio Santa Cruz, 1 Sepulveda Segovia 40300",
    "addr:housenumber":"1",
    "addr:postcode":"40300",
    "addr:street":"Barrio Santa Cruz",
    "iso:country":"ES",
    "sg:address":"Barrio Santa Cruz, 1",
    "sg:city":"Sepulveda",
    "sg:orig_category":"Alquiler De Casas Y Habitaciones Amuebladas",
    "sg:phone":"+34 921 54 00 11",
    "sg:postcode":"40300",
    "sg:province":"Segovia",
    "wof:name":"Ortiz Egea Gema",
    "wof:placetype":"venue"
},
  "geometry": {"coordinates":[-3.7487390041,41.2972755432],"type":"Point"}
}