{
  "type": "Feature",
  "properties": {
    "addr:full":"Calle de Santa Marta, 6 Malaga M\u00e1laga 29006",
    "addr:housenumber":"6",
    "addr:postcode":"29006",
    "addr:street":"Calle De Santa Marta;Ma\u0301Laga",
    "iso:country":"ES",
    "sg:address":"Calle de Santa Marta, 6",
    "sg:city":"Malaga",
    "sg:orig_category":"Asesor\u00cda Fiscal Y Jur\u00cddica",
    "sg:phone":"+34 952 36 34 98",
    "sg:postcode":"29006",
    "sg:province":"M\u00e1laga",
    "wof:name":"Barbudo Santiago Antonio",
    "wof:placetype":"venue"
},
  "geometry": {"coordinates":[-4.4400072098,36.7110061646],"type":"Point"}
}