{
  "type": "Feature",
  "properties": {
    "addr:full":"Calle de Subida A San Miguel, 3 Burgos Burgos 09003",
    "addr:housenumber":"3",
    "addr:postcode":"09003",
    "addr:street":"Calle De Subida A San Miguel",
    "iso:country":"ES",
    "sg:address":"Calle de Subida A San Miguel, 3",
    "sg:city":"Burgos",
    "sg:orig_category":"Molduras, Junquillos, Listones Y Molduras Perforadas",
    "sg:phone":"+34 947 27 50 20",
    "sg:postcode":"09003",
    "sg:province":"Burgos",
    "wof:name":"Mu\u00f1oz Alonso Alberto",
    "wof:placetype":"venue"
},
  "geometry": {"coordinates":[-3.7026441097,42.3444290161],"type":"Point"}
}