{
  "type": "Feature",
  "properties": {
    "iso:country":"ES",
    "sg:address":"Calle de Via Complutense, 137",
    "sg:city":"Alcala Henares",
    "sg:orig_category":"Agentes, Concesionarios Y Sucursales De Veh\u00cdculos",
    "sg:phone":"+34 918 88 67 59",
    "sg:postcode":"28805",
    "sg:province":"Madrid",
    "wof:name":"Corregidor Gil Motor S.a.",
    "wof:placetype":"venue"
},
  "geometry": {"coordinates":[-3.3476719856,40.4937934875],"type":"Point"}
}