{
  "type": "Feature",
  "properties": {
    "iso:country":"ES",
    "sg:address":"Carrer de Havana (l'), 57",
    "sg:city":"Deltebre",
    "sg:orig_category":"Peluqueros: De Se\u00d1oras",
    "sg:phone":"+34 977 48 10 75",
    "sg:postcode":"43580",
    "sg:province":"Tarragona",
    "wof:name":"Navarro Callau Leocricia",
    "wof:placetype":"venue"
},
  "geometry": {"coordinates":[0.7355229855,40.7157173157],"type":"Point"}
}