{
  "type": "Feature",
  "properties": {
    "iso:country":"ES",
    "sg:address":"Carrer de Sant Isidre (de), 117",
    "sg:city":"S. Carles Rapita",
    "sg:orig_category":"Carnicer\u00cdas, Carnicer\u00cdas",
    "sg:phone":"+34 977 74 16 03",
    "sg:postcode":"43540",
    "sg:province":"Tarragona",
    "wof:name":"Monta\u00f1es Navarro Miguel",
    "wof:placetype":"venue"
},
  "geometry": {"coordinates":[0.5879560113,40.6156082153],"type":"Point"}
}