{
  "type": "Feature",
  "properties": {
    "addr:full":"Avda Santa Ana, 22 Lora Rio Sevilla 41440",
    "addr:housenumber":"22",
    "addr:postcode":"41440",
    "addr:street":"Avda Santa Ana;Rio Sevilla",
    "iso:country":"ES",
    "sg:address":"Avda Santa Ana, 22",
    "sg:city":"Lora Rio",
    "sg:orig_category":"Producci\u00d3n, Venta De Productos De Agricultura Biol\u00d3gica",
    "sg:phone":"+34 955 80 28 21",
    "sg:postcode":"41440",
    "sg:province":"Sevilla",
    "wof:name":"Garcia Arcos Rafael",
    "wof:placetype":"venue"
},
  "geometry": {"coordinates":[-5.5272359848,37.658416748],"type":"Point"}
}