{
  "type": "Feature",
  "properties": {
    "addr:full":"Calle de Asilo, 3 Puertollano Ciudad Real 13500",
    "addr:housenumber":"3",
    "addr:postcode":"13500",
    "addr:street":"Calle De Asilo",
    "iso:country":"ES",
    "sg:address":"Calle de Asilo, 3",
    "sg:city":"Puertollano",
    "sg:orig_category":"Empresas De Impermeabilizaci\u00d3n",
    "sg:phone":"+34 926 41 19 36",
    "sg:postcode":"13500",
    "sg:province":"Ciudad Real",
    "wof:name":"Calero Marquez Juan Carlos",
    "wof:placetype":"venue"
},
  "geometry": {"coordinates":[-4.0990962982,38.6850814819],"type":"Point"}
}