{
  "type": "Feature",
  "properties": {
    "iso:country":"ES",
    "sg:address":"Calle de Corredera, 113",
    "sg:city":"Almansa",
    "sg:orig_category":"Molduras, Junquillos, Listones Y Molduras Perforadas",
    "sg:phone":"+34 967 31 11 13",
    "sg:postcode":"02640",
    "sg:province":"Albacete",
    "wof:name":"Marquez Marques Eladio",
    "wof:placetype":"venue"
},
  "geometry": {"coordinates":[-1.0910820961,38.8637084961],"type":"Point"}
}