{
  "type": "Feature",
  "properties": {
    "addr:full":"Carrer de Camp Arriassa, 121 Barcelona Barcelona 08020",
    "addr:housenumber":"121",
    "addr:postcode":"08020",
    "addr:street":"Carrer De Camp Arriassa",
    "iso:country":"ES",
    "sg:address":"Carrer de Camp Arriassa, 121",
    "sg:city":"Barcelona",
    "sg:orig_category":"Cojinetes De Bolas, Agujas Y Rodillos (fabricaci\u00d3n, Al Por Mayor)",
    "sg:phone":"+34 932 78 17 99",
    "sg:postcode":"08020",
    "sg:province":"Barcelona",
    "wof:name":"Rios Galceran Jose Maria",
    "wof:placetype":"venue"
},
  "geometry": {"coordinates":[2.201777935,41.4252624512],"type":"Point"}
}