{
  "type": "Feature",
  "properties": {
    "addr:full":"Ondarreta Kalea, 8 Andoain Guip\u00f9zcoa 20140",
    "addr:housenumber":"8",
    "addr:postcode":"20140",
    "addr:street":"Ondarreta Kalea;Guipu\u0300Zcoa",
    "iso:country":"ES",
    "sg:address":"Ondarreta Kalea, 8",
    "sg:city":"Andoain",
    "sg:orig_category":"Farmacias",
    "sg:phone":"+34 943 59 13 02",
    "sg:postcode":"20140",
    "sg:province":"Guip\u00f9zcoa",
    "wof:name":"Maria Jesus Ansa Iribar",
    "wof:placetype":"venue"
},
  "geometry": {"coordinates":[-2.021791935,43.2178497314],"type":"Point"}
}