{
  "type": "Feature",
  "properties": {
    "iso:country":"ES",
    "sg:address":"Pol. Arenal, S/n",
    "sg:city":"Santovenia Pisuerga",
    "sg:orig_category":"Automatizaci\u00d3n De Procesos Industriales Y De Edificaci\u00d3n (estudios, Instalaci\u00d3n)",
    "sg:phone":"+34 983 40 05 84",
    "sg:postcode":"47155",
    "sg:province":"Valladolid",
    "wof:name":"Came S.a.",
    "wof:placetype":"venue"
},
  "geometry": {"coordinates":[-4.6879892349,41.6882209778],"type":"Point"}
}