{
  "type": "Feature",
  "properties": {
    "iso:country":"ES",
    "sg:address":"Pl Espanya, 19",
    "sg:city":"Mataro",
    "sg:orig_category":"Inmobiliaria (agencias)",
    "sg:phone":"+34 937 99 44 74",
    "sg:postcode":"08304",
    "sg:province":"Barcelona",
    "wof:name":"Macia I Merlos Associats S.l.",
    "wof:placetype":"venue"
},
  "geometry": {"coordinates":[2.4420523643,41.5445175171],"type":"Point"}
}