{
  "type": "Feature",
  "properties": {
    "iso:country":"ES",
    "sg:address":"Major, S/n",
    "sg:city":"Llesp",
    "sg:orig_category":"Cr\u00cda De Animales",
    "sg:phone":"+34 973 69 06 99",
    "sg:postcode":"25526",
    "sg:province":"Lleida",
    "wof:name":"Aigueres S.l.",
    "wof:placetype":"venue"
},
  "geometry": {"coordinates":[0.7403590083,42.4077224731],"type":"Point"}
}