{
  "type": "Feature",
  "properties": {
    "iso:country":"ES",
    "sg:address":"Carrer de Cisa, 1",
    "sg:city":"Premia Mar",
    "sg:orig_category":"Pod\u00d3logos: Pedicuros",
    "sg:phone":"+34 937 52 24 02",
    "sg:postcode":"08330",
    "sg:province":"Barcelona",
    "wof:name":"Vazquez Martinez Pascual",
    "wof:placetype":"venue"
},
  "geometry": {"coordinates":[2.3539919853,41.4941902161],"type":"Point"}
}