{
  "type": "Feature",
  "properties": {
    "addr:full":"Calle de Manuel Alejo, 3 Peal Becerro Ja\u00e9n 23460",
    "addr:housenumber":"3",
    "addr:postcode":"23460",
    "addr:street":"Calle De Manuel Alejo",
    "iso:country":"ES",
    "sg:address":"Calle de Manuel Alejo, 3",
    "sg:city":"Peal Becerro",
    "sg:orig_category":"Charcuter\u00cdas (al Por Mayor)",
    "sg:phone":"+34 953 73 04 38",
    "sg:postcode":"23460",
    "sg:province":"Ja\u00e9n",
    "wof:name":"Navarro Munuera Jose",
    "wof:placetype":"venue"
},
  "geometry": {"coordinates":[-3.1237080097,37.9141693115],"type":"Point"}
}