{
  "type": "Feature",
  "properties": {
    "iso:country":"ES",
    "sg:address":"Avda Rafael Cabrera, 13",
    "sg:city":"Palmas De Gran Canaria",
    "sg:orig_category":"M\u00c9dicos: Otorrinolaringolog\u00cda",
    "sg:phone":"+34 928 36 11 88",
    "sg:postcode":"35002",
    "sg:province":"Las Palmas",
    "wof:name":"De Leon Suarez Juan",
    "wof:placetype":"venue"
},
  "geometry": {"coordinates":[-15.4155988693,28.1074714661],"type":"Point"}
}