{
  "type": "Feature",
  "properties": {
    "iso:country":"ES",
    "sg:address":"Rua Orense, 32",
    "sg:city":"Monforte De Lemos",
    "sg:orig_category":"Procuradores",
    "sg:phone":"+34 982 40 05 05",
    "sg:postcode":"27400",
    "sg:province":"Lugo",
    "wof:name":"Rivas Rodriguez Avelino",
    "wof:placetype":"venue"
},
  "geometry": {"coordinates":[-7.5230269432,42.5195007324],"type":"Point"}
}