{
  "type": "Feature",
  "properties": {
    "addr:full":"Pl Esglesia (de L'), 23 Vila-seca Tarragona 43480",
    "addr:housenumber":"23",
    "addr:postcode":"43480",
    "addr:street":"Pl Esglesia De L '",
    "iso:country":"ES",
    "sg:address":"Pl Esglesia (de L'), 23",
    "sg:city":"Vila-seca",
    "sg:orig_category":"Aguas (distribuci\u00d3n, Servicios)",
    "sg:phone":"+34 977 39 34 04",
    "sg:postcode":"43480",
    "sg:province":"Tarragona",
    "wof:name":"Aquair Control S.l.",
    "wof:placetype":"venue"
},
  "geometry": {"coordinates":[1.1451617479,41.1109390259],"type":"Point"}
}