{
  "type": "Feature",
  "properties": {
    "iso:country":"ES",
    "sg:address":"Torrent De Les Piques, 14",
    "sg:city":"Mataro",
    "sg:orig_category":"Peluquer\u00cdas, Peluquer\u00cda Mixta",
    "sg:phone":"+34 937 99 31 11",
    "sg:postcode":"08304",
    "sg:province":"Barcelona",
    "wof:name":"Raigon Sanchez Angela",
    "wof:placetype":"venue"
},
  "geometry": {"coordinates":[2.4399530888,41.5537261963],"type":"Point"}
}