{
  "type": "Feature",
  "properties": {
    "addr:full":"Calle de Ca\u00d1o, 12 Cordoba C\u00f3rdoba 14001",
    "addr:housenumber":"12",
    "addr:postcode":"14001",
    "addr:street":"Calle De Can\u0303O;Co\u0301Rdoba",
    "iso:country":"ES",
    "sg:address":"Calle de Ca\u00d1o, 12",
    "sg:city":"Cordoba",
    "sg:orig_category":"Deportes Diversos",
    "sg:phone":"+34 957 48 25 18",
    "sg:postcode":"14001",
    "sg:province":"C\u00f3rdoba",
    "wof:name":"Asociacion Cultural De Tecnicas Orientales Wutan",
    "wof:placetype":"venue"
},
  "geometry": {"coordinates":[-4.7800626755,37.8885536194],"type":"Point"}
}