{
  "type": "Feature",
  "properties": {
    "iso:country":"ES",
    "sg:address":"Calle de Avicena, 23",
    "sg:city":"Sevilla",
    "sg:orig_category":"Doctores En Medicina",
    "sg:phone":"+34 954 90 28 45",
    "sg:postcode":"41009",
    "sg:province":"Sevilla",
    "wof:name":"Gomez Arroyo Jose Antonio",
    "wof:placetype":"venue"
},
  "geometry": {"coordinates":[-5.9935369492,37.4055480957],"type":"Point"}
}