{
  "type": "Feature",
  "properties": {
    "addr:full":"Estacion, S/n Cala\u00f1as Huelva 21300",
    "addr:postcode":"21300",
    "addr:street":"S / N Calan\u0303As",
    "iso:country":"ES",
    "sg:address":"Estacion, S/n",
    "sg:city":"Cala\u00f1as",
    "sg:orig_category":"Empresas De Carpinter\u00cda De Madera",
    "sg:phone":"+34 959 56 52 84",
    "sg:postcode":"21300",
    "sg:province":"Huelva",
    "wof:name":"Casto Pantrigo Vicente 000500962h, S.l.n.e.u.",
    "wof:placetype":"venue"
},
  "geometry": {"coordinates":[-6.8769288063,37.6487083435],"type":"Point"}
}