{
  "type": "Feature",
  "properties": {
    "iso:country":"ES",
    "sg:address":"Juan Bautista Erro Kalea, 2",
    "sg:city":"Andoain",
    "sg:orig_category":"Perfumer\u00cda (al Por Menor)",
    "sg:phone":"+34 943 59 21 46",
    "sg:postcode":"20140",
    "sg:province":"Guip\u00f9zcoa",
    "wof:name":"Ana Isabel Zalakain Mendizabal",
    "wof:placetype":"venue"
},
  "geometry": {"coordinates":[-2.0207867622,43.2178001404],"type":"Point"}
}