{
  "type": "Feature",
  "properties": {
    "iso:country":"ES",
    "sg:address":"Calle de Fray Julian Garces, 76",
    "sg:city":"Zaragoza",
    "sg:orig_category":"Mec\u00c1nico Del Autom\u00d3vil",
    "sg:phone":"+34 976 25 24 28",
    "sg:postcode":"50007",
    "sg:province":"Zaragoza",
    "wof:name":"Talleres Becars S.l.",
    "wof:placetype":"venue"
},
  "geometry": {"coordinates":[-0.8879740238,41.6285133362],"type":"Point"}
}