{
  "type": "Feature",
  "properties": {
    "addr:full":"Rua Rei Don Garcia, 84 Lugo Lugo 27002",
    "addr:housenumber":"84",
    "addr:postcode":"27002",
    "addr:street":"Rua Rei Don Garcia",
    "iso:country":"ES",
    "sg:address":"Rua Rei Don Garcia, 84",
    "sg:city":"Lugo",
    "sg:orig_category":"Peluqueros: De Se\u00d1oras",
    "sg:phone":"+34 982 22 76 03",
    "sg:postcode":"27002",
    "sg:province":"Lugo",
    "wof:name":"Monir C.b.",
    "wof:placetype":"venue"
},
  "geometry": {"coordinates":[-7.5471878052,43.0025291443],"type":"Point"}
}