{
  "type": "Feature",
  "properties": {
    "addr:full":"Calle de Mayor, 20 Robla Le\u00f3n 24640",
    "addr:housenumber":"20",
    "addr:postcode":"24640",
    "addr:street":"Calle De Mayor;Leo\u0301N",
    "iso:country":"ES",
    "sg:address":"Calle de Mayor, 20",
    "sg:city":"Robla",
    "sg:orig_category":"Electricidad: Instaladores",
    "sg:phone":"+34 987 57 23 37",
    "sg:postcode":"24640",
    "sg:province":"Le\u00f3n",
    "wof:name":"Arias Gonzalez Javier Francisco",
    "wof:placetype":"venue"
},
  "geometry": {"coordinates":[-5.6283774376,42.804561615],"type":"Point"}
}