{
  "type": "Feature",
  "properties": {
    "iso:country":"ES",
    "sg:address":"Emilio Arrieta, 16",
    "sg:city":"Iru\u00f1a",
    "sg:orig_category":"Peluquer\u00cdas, Peluquer\u00cda Mixta",
    "sg:phone":"+34 948 22 25 07",
    "sg:postcode":"31002",
    "sg:province":"Navarra",
    "wof:name":"Francisco Hidalgo S. L.",
    "wof:placetype":"venue"
},
  "geometry": {"coordinates":[-1.6418550014,42.8136405945],"type":"Point"}
}