{
  "type": "Feature",
  "properties": {
    "iso:country":"ES",
    "sg:address":"Carr Fortaleny, 12",
    "sg:city":"Algemesi",
    "sg:orig_category":"Ense\u00d1anza: Profesiones Art\u00cdsticas",
    "sg:phone":"+34 962 48 29 39",
    "sg:postcode":"46680",
    "sg:province":"Valencia",
    "wof:name":"Santos Lleonart Vicente",
    "wof:placetype":"venue"
},
  "geometry": {"coordinates":[-0.4368099868,39.1963157654],"type":"Point"}
}