{
  "type": "Feature",
  "properties": {
    "iso:country":"ES",
    "sg:address":"Calle de Turia, 23",
    "sg:city":"Linea De La Concepcion",
    "sg:orig_category":"Empresas De Carpinter\u00cda De Madera",
    "sg:phone":"+34 956 76 21 10",
    "sg:postcode":"11300",
    "sg:province":"C\u00e1diz",
    "wof:name":"General De Carpinteria Andaluza Sociedad Cooperativa Andaluza",
    "wof:placetype":"venue"
},
  "geometry": {"coordinates":[-5.340939045,36.1683044434],"type":"Point"}
}