{
  "type": "Feature",
  "properties": {
    "iso:country":"ES",
    "sg:address":"Av Cas Corb(p I Montecristo), S/n",
    "sg:city":"S. Rafel Creu",
    "sg:orig_category":"Hielo Artificial (fabricaci\u00d3n, Distribuci\u00d3n)",
    "sg:phone":"+34 971 19 08 81",
    "sg:postcode":"07816",
    "sg:province":"Islas Baleares",
    "sg:website":"www.menorquina.com",
    "wof:name":"Grupo Kalise Menorquina S.a.",
    "wof:placetype":"venue"
},
  "geometry": {"coordinates":[1.3828419447,39.0397987366],"type":"Point"}
}