{
  "type": "Feature",
  "properties": {
    "iso:country":"ES",
    "sg:address":"Calle de Luxemburgo, 7",
    "sg:city":"Castellon De La Plana",
    "sg:orig_category":"Maquinaria Para Industrias Diversas",
    "sg:phone":"+34 964 24 47 44",
    "sg:postcode":"12006",
    "sg:province":"Castell\u00f3n",
    "sg:website":"www.alfe.es",
    "wof:name":"Alfe Renta Catalunya S.a.",
    "wof:placetype":"venue"
},
  "geometry": {"coordinates":[-0.0705545992,39.9706840515],"type":"Point"}
}