{
  "type": "Feature",
  "properties": {
    "iso:country":"ES",
    "sg:address":"Av Valles, 115",
    "sg:city":"Terrassa",
    "sg:orig_category":"Equipo De Refrigeraci\u00d3n Industrial",
    "sg:phone":"+34 937 88 08 52",
    "sg:postcode":"08223",
    "sg:province":"Barcelona",
    "wof:name":"Comercial P. Valls S.a.",
    "wof:placetype":"venue"
},
  "geometry": {"coordinates":[2.0389940739,41.5477027893],"type":"Point"}
}