{
  "type": "Feature",
  "properties": {
    "iso:country":"ES",
    "sg:address":"Mcdo Sto Domingo, S/n",
    "sg:city":"Iru\u00f1a",
    "sg:orig_category":"Mercados De Productos Alimenticios",
    "sg:phone":"+34 948 22 18 58",
    "sg:postcode":"31001",
    "sg:province":"Navarra",
    "wof:name":"Mercado De Santo Domingo S.l.",
    "wof:placetype":"venue"
},
  "geometry": {"coordinates":[-1.6446839571,42.8185958862],"type":"Point"}
}