{
  "type": "Feature",
  "properties": {
    "iso:country":"ES",
    "sg:address":"Toedo, S/n",
    "sg:city":"Toedo",
    "sg:orig_category":"Limpieza Industrial",
    "sg:phone":"+34 986 59 01 13",
    "sg:postcode":"36682",
    "sg:province":"Pontevedra",
    "wof:name":"Centro De Lavado Elegante C.b.",
    "wof:placetype":"venue"
},
  "geometry": {"coordinates":[-8.4540214539,42.7098999023],"type":"Point"}
}