{
  "type": "Feature",
  "properties": {
    "iso:country":"ES",
    "sg:address":"Calle de Julian Ceballos, 37",
    "sg:city":"Torrelavega",
    "sg:orig_category":"M\u00c9dicos: Ginecolog\u00cda Y Obstetricia",
    "sg:phone":"+34 942 89 22 87",
    "sg:postcode":"39300",
    "sg:province":"Cantabria",
    "wof:name":"Sanchez Gonzalez Segundo",
    "wof:placetype":"venue"
},
  "geometry": {"coordinates":[-4.0458807945,43.3480567932],"type":"Point"}
}