{
  "type": "Feature",
  "properties": {
    "addr:full":"Calle de Batalla De Bailen, 1 Jaen Ja\u00e9n 23001",
    "addr:housenumber":"1;jae\u0301n",
    "addr:postcode":"23001",
    "addr:street":"Calle De Batalla De Bailen",
    "iso:country":"ES",
    "sg:address":"Calle de Batalla De Bailen, 1",
    "sg:city":"Jaen",
    "sg:orig_category":"Caf\u00c9s, Bares, Cervecer\u00cdas",
    "sg:phone":"+34 953 22 77 35",
    "sg:postcode":"23001",
    "sg:province":"Ja\u00e9n",
    "wof:name":"Mofersa S.l.",
    "wof:placetype":"venue"
},
  "geometry": {"coordinates":[-3.7878034115,37.7693977356],"type":"Point"}
}