{
  "type": "Feature",
  "properties": {
    "iso:country":"ES",
    "sg:address":"Calle de Mayor, 63",
    "sg:city":"Union",
    "sg:orig_category":"Inmobiliaria (agencias)",
    "sg:phone":"+34 968 56 08 64",
    "sg:postcode":"30360",
    "sg:province":"Murcia",
    "wof:name":"Sanchez Perez Federico",
    "wof:placetype":"venue"
},
  "geometry": {"coordinates":[-0.8773880005,37.6173782349],"type":"Point"}
}