{
  "type": "Feature",
  "properties": {
    "iso:country":"ES",
    "sg:address":"Calle de Pascual Perez O\u00d1ate, 1",
    "sg:city":"Corella",
    "sg:orig_category":"Notarios",
    "sg:phone":"+34 948 78 00 41",
    "sg:postcode":"31591",
    "sg:province":"Navarra",
    "wof:name":"Garcia Lamarca Maria Pilar",
    "wof:placetype":"venue"
},
  "geometry": {"coordinates":[-1.7834689617,42.115234375],"type":"Point"}
}