{
  "type": "Feature",
  "properties": {
    "iso:country":"ES",
    "sg:address":"Urb El Chaparral, 5",
    "sg:city":"Mijas Costa",
    "sg:orig_category":"Locales De Saunas, De Ba\u00d1os",
    "sg:phone":"+34 952 59 90 65",
    "sg:postcode":"29649",
    "sg:province":"M\u00e1laga",
    "wof:name":"Garces Torres Gladys",
    "wof:placetype":"venue"
},
  "geometry": {"coordinates":[-4.6411604881,36.5099143982],"type":"Point"}
}