{
  "type": "Feature",
  "properties": {
    "addr:full":"Calle de Escritor Torquemada, 11 Cordoba C\u00f3rdoba 14011",
    "addr:housenumber":"11",
    "addr:postcode":"14011",
    "addr:street":"Calle De Escritor Torquemada;Co\u0301Rdoba",
    "iso:country":"ES",
    "sg:address":"Calle de Escritor Torquemada, 11",
    "sg:city":"Cordoba",
    "sg:orig_category":"Frutas, Legumbres Frescas Y Tempranas (al Por Menor)",
    "sg:phone":"+34 957 40 25 99",
    "sg:postcode":"14011",
    "sg:province":"C\u00f3rdoba",
    "wof:name":"Montes Marton Rafael",
    "wof:placetype":"venue"
},
  "geometry": {"coordinates":[-4.7915740013,37.8905639648],"type":"Point"}
}