{
  "type": "Feature",
  "properties": {
    "iso:country":"ES",
    "sg:address":"Ctra Boadilla, 2",
    "sg:city":"Majadahonda",
    "sg:orig_category":"\u00d3ptica: Instrumentos (fabricaci\u00d3n)",
    "sg:phone":"+34 916 38 07 32",
    "sg:postcode":"28220",
    "sg:province":"Madrid",
    "wof:name":"Optica Sanavision Cb",
    "wof:placetype":"venue"
},
  "geometry": {"coordinates":[-3.869863987,40.4637145996],"type":"Point"}
}