{
  "type": "Feature",
  "properties": {
    "addr:full":"Errondoa, S/n Atarrabia Navarra 31610",
    "addr:housenumber":"/ n",
    "addr:postcode":"31610",
    "addr:street":"Errondoa S",
    "iso:country":"ES",
    "sg:address":"Errondoa, S/n",
    "sg:city":"Atarrabia",
    "sg:orig_category":"Electrolisis, Depurado Del Aluminio Y De Aleaciones",
    "sg:phone":"+34 948 14 11 00",
    "sg:postcode":"31610",
    "sg:province":"Navarra",
    "wof:name":"Iongraf S.a.",
    "wof:placetype":"venue"
},
  "geometry": {"coordinates":[-1.6063289642,42.8279685974],"type":"Point"}
}