{
  "type": "Feature",
  "properties": {
    "addr:full":"Ctra Estacion, 87 Pe\u00f1iscola Castell\u00f3n 12598",
    "addr:housenumber":"87",
    "addr:postcode":"12598",
    "addr:street":"Ctra Estacion;Castello\u0301N",
    "iso:country":"ES",
    "sg:address":"Ctra Estacion, 87",
    "sg:city":"Pe\u00f1iscola",
    "sg:orig_category":"Artesan\u00cda",
    "sg:phone":"+34 964 48 08 60",
    "sg:postcode":"12598",
    "sg:province":"Castell\u00f3n",
    "wof:name":"Magre Mestre Isidro",
    "wof:placetype":"venue"
},
  "geometry": {"coordinates":[-0.0456800014,39.9851417542],"type":"Point"}
}