{
  "type": "Feature",
  "properties": {
    "addr:full":"Calle de Parvillas Altas, 13 Madrid Madrid 28021",
    "addr:housenumber":"13",
    "addr:postcode":"madrid;28021",
    "addr:street":"Calle De Parvillas Altas",
    "iso:country":"ES",
    "sg:address":"Calle de Parvillas Altas, 13",
    "sg:city":"Madrid",
    "sg:orig_category":"Aparcamientos (infraestructuras, Accesorios)",
    "sg:phone":"+34 915 05 00 44",
    "sg:postcode":"28021",
    "sg:province":"Madrid",
    "wof:name":"Quilon Gascon Pedro",
    "wof:placetype":"venue"
},
  "geometry": {"coordinates":[-3.7079520226,40.3447036743],"type":"Point"}
}