{
  "type": "Feature",
  "properties": {
    "addr:full":"Calle de Santa Quiteria, 8 Fraga Huesca 22520",
    "addr:housenumber":"8",
    "addr:postcode":"22520",
    "addr:street":"Calle De Santa Quiteria",
    "iso:country":"ES",
    "sg:address":"Calle de Santa Quiteria, 8",
    "sg:city":"Fraga",
    "sg:orig_category":"Electricidad: Instaladores",
    "sg:phone":"+34 974 47 09 95",
    "sg:postcode":"22520",
    "sg:province":"Huesca",
    "wof:name":"Chine Martinez Jose",
    "wof:placetype":"venue"
},
  "geometry": {"coordinates":[0.3496620059,41.5205917358],"type":"Point"}
}