{
  "type": "Feature",
  "properties": {
    "iso:country":"ES",
    "sg:address":"Rbla Menceyes (los), S/n",
    "sg:city":"Candelaria",
    "sg:orig_category":"Tintes (fabricaci\u00d3n, Al Por Mayor)",
    "sg:phone":"+34 922 50 49 24",
    "sg:postcode":"38530",
    "sg:province":"Santa Cruz De Tenerife",
    "wof:name":"Manganiello Leal Consiglia",
    "wof:placetype":"venue"
},
  "geometry": {"coordinates":[-16.3678607941,28.3607463837],"type":"Point"}
}