{
  "type": "Feature",
  "properties": {
    "iso:country":"ES",
    "sg:address":"Calle de Perojo, 6",
    "sg:city":"Palmas De Gran Canaria",
    "sg:classifiers":[
        {
            "category":"Banks & Credit Unions",
            "subcategory":"Bureau De Change",
            "type":"Services"
        }
    ],
    "sg:phone":"+34 928 43 37 80",
    "sg:postcode":"35003",
    "sg:province":"Las Palmas",
    "sg:tags":[
        "organismos",
        "control"
    ],
    "sg:website":"www.gocsa.es",
    "wof:name":"Goc S.a.",
    "wof:placetype":"venue"
},
  "geometry": {"coordinates":[-15.4194555283,28.1096038818],"type":"Point"}
}