{
  "type": "Feature",
  "properties": {
    "iso:country":"ES",
    "sg:address":"Urb Parque Miraflores, 50",
    "sg:city":"Miraflores",
    "sg:orig_category":"Asesor\u00cda Fiscal Y Jur\u00cddica",
    "sg:phone":"+34 916 46 15 44",
    "sg:postcode":"28942",
    "sg:province":"Madrid",
    "wof:name":"Torres Y Moreno Asesores S.l.",
    "wof:placetype":"venue"
},
  "geometry": {"coordinates":[-3.8372960091,40.3133621216],"type":"Point"}
}