{
  "type": "Feature",
  "properties": {
    "iso:country":"ES",
    "sg:address":"Calle de Ramon Y Cajal, 16",
    "sg:city":"Cox",
    "sg:orig_category":"Fotograf\u00cda Art\u00cdstica Y Retratos",
    "sg:phone":"+34 965 36 01 32",
    "sg:postcode":"03350",
    "sg:province":"Alicante",
    "wof:name":"Simon Miralles Joaquin",
    "wof:placetype":"venue"
},
  "geometry": {"coordinates":[-0.8864340186,38.1404762268],"type":"Point"}
}