{
  "type": "Feature",
  "properties": {
    "iso:country":"ES",
    "sg:address":"Cmno Molino (del), S/n",
    "sg:city":"Cieza",
    "sg:orig_category":"Empresas De Pintura Y Revestimientos",
    "sg:phone":"+34 968 76 44 40",
    "sg:postcode":"30530",
    "sg:province":"Murcia",
    "wof:name":"Marin Hernandez Francisco",
    "wof:placetype":"venue"
},
  "geometry": {"coordinates":[-1.4242889881,38.2405166626],"type":"Point"}
}