{
  "type": "Feature",
  "properties": {
    "addr:full":"Calle de Florida, 15 Porvenir Murcia 30816",
    "addr:housenumber":"15",
    "addr:postcode":"30816",
    "addr:street":"Calle De Florida",
    "iso:country":"ES",
    "sg:address":"Calle de Florida, 15",
    "sg:city":"Porvenir",
    "sg:orig_category":"Reposter\u00cdas",
    "sg:phone":"+34 968 46 86 58",
    "sg:postcode":"30816",
    "sg:province":"Murcia",
    "wof:name":"Lopez Leon Isabel",
    "wof:placetype":"venue"
},
  "geometry": {"coordinates":[-1.5710790157,37.7104187012],"type":"Point"}
}