{
  "type": "Feature",
  "properties": {
    "addr:full":"Avia Puente Colgante, S/n Valladolid Valladolid 47014",
    "addr:housenumber":"s / n",
    "addr:postcode":"47014",
    "addr:street":"Puente Colgante",
    "iso:country":"ES",
    "sg:address":"Avia Puente Colgante, S/n",
    "sg:city":"Valladolid",
    "sg:orig_category":"Agencias De Viajes",
    "sg:phone":"+34 983 33 07 46",
    "sg:postcode":"47014",
    "sg:province":"Valladolid",
    "sg:website":"www.carrefour.es/viajes",
    "wof:name":"Viajes Carrefour S.l.",
    "wof:placetype":"venue"
},
  "geometry": {"coordinates":[-4.7453589439,41.6415557861],"type":"Point"}
}