{
  "type": "Feature",
  "properties": {
    "addr:full":"Carr Lleida, 45 Igualada Barcelona 08700",
    "addr:housenumber":"45",
    "addr:postcode":"08700",
    "addr:street":"Carr Lleida",
    "iso:country":"ES",
    "sg:address":"Carr Lleida, 45",
    "sg:city":"Igualada",
    "sg:orig_category":"Electricidad: Instaladores",
    "sg:phone":"+34 938 03 70 69",
    "sg:postcode":"08700",
    "sg:province":"Barcelona",
    "wof:name":"Alfons Samper S.l.",
    "wof:placetype":"venue"
},
  "geometry": {"coordinates":[1.6270525455,41.5829772949],"type":"Point"}
}