{
  "type": "Feature",
  "properties": {
    "iso:country":"ES",
    "sg:address":"Avda Manuel Gorria, 36",
    "sg:city":"Malaga",
    "sg:orig_category":"Contenedores (mercanc\u00cdas)",
    "sg:phone":"+34 952 25 90 45",
    "sg:postcode":"29013",
    "sg:province":"M\u00e1laga",
    "wof:name":"Aguilar Jimenez Victoria",
    "wof:placetype":"venue"
},
  "geometry": {"coordinates":[-4.4170951843,36.7364883423],"type":"Point"}
}