{
  "type": "Feature",
  "properties": {
    "addr:full":"Carrer de Palma De Sant Just, 12 Barcelona Barcelona 08002",
    "addr:housenumber":"12",
    "addr:postcode":"08002",
    "addr:street":"Carrer De Palma De Sant Just",
    "iso:country":"ES",
    "sg:address":"Carrer de Palma De Sant Just, 12",
    "sg:city":"Barcelona",
    "sg:orig_category":"Peluquer\u00cdas, Peluquer\u00cda Mixta",
    "sg:phone":"+34 932 68 74 75",
    "sg:postcode":"08002",
    "sg:province":"Barcelona",
    "wof:name":"Carrizo Fonseca Scp",
    "wof:placetype":"venue"
},
  "geometry": {"coordinates":[2.1787810326,41.3821258545],"type":"Point"}
}