{
  "type": "Feature",
  "properties": {
    "addr:full":"Carrer de Torras I Bages, 30 Santa Coloma De Gramenet Barcelona 08923",
    "addr:housenumber":"30",
    "addr:postcode":"08923",
    "addr:street":"Carrer De Torras I Bages",
    "iso:country":"ES",
    "sg:address":"Carrer de Torras I Bages, 30",
    "sg:city":"Santa Coloma De Gramenet",
    "sg:orig_category":"Pod\u00d3logos: Pedicuros",
    "sg:phone":"+34 933 86 05 79",
    "sg:postcode":"08923",
    "sg:province":"Barcelona",
    "wof:name":"Moral Ca\u00f1as Susana",
    "wof:placetype":"venue"
},
  "geometry": {"coordinates":[2.2130680084,41.4465827942],"type":"Point"}
}