{
  "type": "Feature",
  "properties": {
    "iso:country":"ES",
    "sg:address":"Calle de Mayor, 13",
    "sg:city":"Sonseca",
    "sg:orig_category":"Sociedades, Compa\u00d1\u00cdas Aseguradoras",
    "sg:phone":"+34 925 38 17 33",
    "sg:postcode":"45100",
    "sg:province":"Toledo",
    "wof:name":"Solimat M.a.t.e.p.s.s.",
    "wof:placetype":"venue"
},
  "geometry": {"coordinates":[-3.9743344784,39.674785614],"type":"Point"}
}