{
  "type": "Feature",
  "properties": {
    "addr:full":"Calle de Emaus, 21 Montalban Teruel 44700",
    "addr:housenumber":"21",
    "addr:postcode":"44700",
    "addr:street":"Calle De Emaus",
    "iso:country":"ES",
    "sg:address":"Calle de Emaus, 21",
    "sg:city":"Montalban",
    "sg:orig_category":"Supermercados Y Hipermercados",
    "sg:phone":"+34 978 75 06 81",
    "sg:postcode":"44700",
    "sg:province":"Teruel",
    "wof:name":"Alimentacion Marmesat Rg S.l.u.",
    "wof:placetype":"venue"
},
  "geometry": {"coordinates":[-0.7995119095,40.8324356079],"type":"Point"}
}