{
  "type": "Feature",
  "properties": {
    "addr:full":"Carr Vicent Serra I Orvay, 33 Eivissa Islas Baleares 07800",
    "addr:housenumber":"33",
    "addr:postcode":"07800",
    "addr:street":"Carr Vicent;Orvay",
    "iso:country":"ES",
    "sg:address":"Carr Vicent Serra I Orvay, 33",
    "sg:city":"Eivissa",
    "sg:classifiers":[
        {
            "category":"Autos & Motor Vehicles",
            "subcategory":"Automobile Sales",
            "type":"Retail Goods"
        }
    ],
    "sg:phone":"+34 971 19 12 06",
    "sg:postcode":"07800",
    "sg:province":"Islas Baleares",
    "wof:name":"Autoescuela Mediterranea S.c.",
    "wof:placetype":"venue"
},
  "geometry": {"coordinates":[1.4323778152,38.9088554382],"type":"Point"}
}