{
  "type": "Feature",
  "properties": {
    "addr:full":"Rua Estacion (da), 9 Burela Lugo 27880",
    "addr:postcode":"27880",
    "addr:street":"Rua Estacion Da 9",
    "iso:country":"ES",
    "sg:address":"Rua Estacion (da), 9",
    "sg:city":"Burela",
    "sg:orig_category":"Electricidad Veh\u00cdculo",
    "sg:phone":"+34 982 58 08 07",
    "sg:postcode":"27880",
    "sg:province":"Lugo",
    "wof:name":"Taller Electrico Nilo S.l.",
    "wof:placetype":"venue"
},
  "geometry": {"coordinates":[-7.3615269661,43.6601028442],"type":"Point"}
}