{
  "type": "Feature",
  "properties": {
    "iso:country":"ES",
    "sg:address":"Carrer de Gremi De Boters, 25",
    "sg:city":"Poligon Industrial De Son Castello",
    "sg:orig_category":"Producci\u00d3n De Huevos",
    "sg:phone":"+34 971 29 38 67",
    "sg:postcode":"07009",
    "sg:province":"Islas Baleares",
    "wof:name":"Agusti Coll S.a.",
    "wof:placetype":"venue"
},
  "geometry": {"coordinates":[2.8577105999,39.5341796875],"type":"Point"}
}