{
  "type": "Feature",
  "properties": {
    "addr:full":"Forjadores, 5 Boadilla Madrid 28660",
    "addr:housenumber":"5",
    "addr:postcode":"28660",
    "addr:street":"Forjadores",
    "iso:country":"ES",
    "sg:address":"Forjadores, 5",
    "sg:city":"Boadilla",
    "sg:orig_category":"Papel (al Por Mayor)",
    "sg:phone":"+34 916 33 32 00",
    "sg:postcode":"28660",
    "sg:province":"Madrid",
    "sg:website":"www.decein.com",
    "wof:name":"Decein S.l.",
    "wof:placetype":"venue"
},
  "geometry": {"coordinates":[-3.8480689526,40.3929100037],"type":"Point"}
}