{
  "type": "Feature",
  "properties": {
    "addr:full":"Fnc. Santa Maria, S/n Vegas Y S. Antonio Toledo 45691",
    "addr:housenumber":"/ n",
    "addr:postcode":"45691",
    "addr:street":"S",
    "iso:country":"ES",
    "sg:address":"Fnc. Santa Maria, S/n",
    "sg:city":"Vegas Y S. Antonio",
    "sg:orig_category":"Cr\u00cda De Animales",
    "sg:phone":"+34 925 59 71 71",
    "sg:postcode":"45691",
    "sg:province":"Toledo",
    "wof:name":"Ovinos Hibridos S. A.",
    "wof:placetype":"venue"
},
  "geometry": {"coordinates":[-4.6991839409,39.9589996338],"type":"Point"}
}