{
  "type": "Feature",
  "properties": {
    "addr:full":"Calle de Duggi, 47 Santa Cruz De Tenerife Santa Cruz De Tenerife 38004",
    "addr:housenumber":"47",
    "addr:postcode":"38004",
    "addr:street":"Calle De Duggi",
    "iso:country":"ES",
    "sg:address":"Calle de Duggi, 47",
    "sg:city":"Santa Cruz De Tenerife",
    "sg:orig_category":"Peluqueros: De Se\u00d1oras",
    "sg:phone":"+34 922 24 90 03",
    "sg:postcode":"38004",
    "sg:province":"Santa Cruz De Tenerife",
    "wof:name":"Garcia Rodriguez Ana Luisa",
    "wof:placetype":"venue"
},
  "geometry": {"coordinates":[-16.2595310211,28.4655704498],"type":"Point"}
}