{
  "type": "Feature",
  "properties": {
    "addr:full":"Carrer de Castellet, S/n S. Vicen\u00e7 Castellet Barcelona 08295",
    "addr:housenumber":"s",
    "addr:postcode":"08295",
    "addr:street":"Carrer De Castellet;/ N S. Vicenc\u0327;Barcelona",
    "iso:country":"ES",
    "sg:address":"Carrer de Castellet, S/n",
    "sg:city":"S. Vicen\u00e7 Castellet",
    "sg:orig_category":"Hilaturas, Hilos Y Actividades Relacionadas",
    "sg:phone":"+34 938 33 11 33",
    "sg:postcode":"08295",
    "sg:province":"Barcelona",
    "wof:name":"Corylen S.l.",
    "wof:placetype":"venue"
},
  "geometry": {"coordinates":[1.8632650375,41.6662864685],"type":"Point"}
}