{
  "type": "Feature",
  "properties": {
    "addr:full":"Calle de Eduardo Dato, 46 Vitoria-gasteiz \u00c1lava 01005",
    "addr:housenumber":"46",
    "addr:postcode":"01005",
    "addr:street":"Calle De Eduardo Dato",
    "iso:country":"ES",
    "sg:address":"Calle de Eduardo Dato, 46",
    "sg:city":"Vitoria-gasteiz",
    "sg:orig_category":"Arquitectos",
    "sg:phone":"+34 945 14 44 05",
    "sg:postcode":"01005",
    "sg:province":"\u00c1lava",
    "wof:name":"Marti Rodriguez Maria Isabel",
    "wof:placetype":"venue"
},
  "geometry": {"coordinates":[-2.6725285053,42.8438720703],"type":"Point"}
}