{
  "type": "Feature",
  "properties": {
    "addr:full":"Calle de Jose Bernabeu, 11 Montealegre Castillo Albacete 02650",
    "addr:housenumber":"11",
    "addr:postcode":"02650",
    "addr:street":"Calle De Jose Bernabeu",
    "iso:country":"ES",
    "sg:address":"Calle de Jose Bernabeu, 11",
    "sg:city":"Montealegre Castillo",
    "sg:orig_category":"Mercer\u00cda, Lencer\u00cda (al Por Menor)",
    "sg:phone":"+34 967 33 60 06",
    "sg:postcode":"02650",
    "sg:province":"Albacete",
    "wof:name":"Campos Sanchez Ezequiel",
    "wof:placetype":"venue"
},
  "geometry": {"coordinates":[-1.3267689943,38.7878494263],"type":"Point"}
}