{
  "type": "Feature",
  "properties": {
    "addr:full":"Carrer de Almansa, 10 Barcelona Barcelona 08042",
    "addr:housenumber":"10",
    "addr:postcode":"08042",
    "addr:street":"Carrer De Almansa",
    "iso:country":"ES",
    "sg:address":"Carrer de Almansa, 10",
    "sg:city":"Barcelona",
    "sg:orig_category":"Delegados, Agentes De Tr\u00c1nsito, Auxiliares De Transporte Internacional",
    "sg:phone":"+34 933 53 30 85",
    "sg:postcode":"08042",
    "sg:province":"Barcelona",
    "wof:name":"Llorens Vidal Rafael",
    "wof:placetype":"venue"
},
  "geometry": {"coordinates":[2.1765720844,41.4417572021],"type":"Point"}
}