{
  "type": "Feature",
  "properties": {
    "iso:country":"ES",
    "sg:address":"Carrer de Gasometre, S/n",
    "sg:city":"Hospitalet Llobregat",
    "sg:orig_category":"Asociaciones, Organismos Culturales Y Socioeducativos",
    "sg:phone":"+34 934 32 10 65",
    "sg:postcode":"08902",
    "sg:province":"Barcelona",
    "wof:name":"Agrupacio Esportiva Santa Eulalia",
    "wof:placetype":"venue"
},
  "geometry": {"coordinates":[2.1226670742,41.365524292],"type":"Point"}
}