{
  "type": "Feature",
  "properties": {
    "iso:country":"ES",
    "sg:address":"G.v. Corts Catalanes, 594",
    "sg:city":"Barcelona",
    "sg:orig_category":"Asesor\u00cda Sobre Comunicaci\u00d3n De Empresas",
    "sg:phone":"+34 933 02 69 24",
    "sg:postcode":"08007",
    "sg:province":"Barcelona",
    "sg:website":"sduran-sindreu@ctv.es",
    "wof:name":"Duran-sindreu Y Compa\u00f1ia Sociedad Encomandita Por Acciones",
    "wof:placetype":"venue"
},
  "geometry": {"coordinates":[2.1647479534,41.3863487244],"type":"Point"}
}