{
  "type": "Feature",
  "properties": {
    "addr:full":"Calle de Carretera Zaragoza, Km. 0009,5 Casco Nuevo Navarra 31191",
    "addr:postcode":"31191",
    "addr:street":"Calle De Carretera Zaragoza Km. 0009,5",
    "iso:country":"ES",
    "sg:address":"Calle de Carretera Zaragoza, Km. 0009,5",
    "sg:city":"Casco Nuevo",
    "sg:orig_category":"Garajes De Veh\u00cdculos",
    "sg:phone":"+34 948 31 08 71",
    "sg:postcode":"31191",
    "sg:province":"Navarra",
    "sg:website":"www.navadaf.es",
    "wof:name":"Navadaf S.l.",
    "wof:placetype":"venue"
},
  "geometry": {"coordinates":[-1.6760691404,42.6953926086],"type":"Point"}
}