{
  "type": "Feature",
  "properties": {
    "iso:country":"ES",
    "sg:address":"Calle de Pola De Siero, 5",
    "sg:city":"Gijon",
    "sg:orig_category":"Abogados",
    "sg:phone":"+34 985 34 85 85",
    "sg:postcode":"33207",
    "sg:province":"Asturias",
    "wof:name":"Rodriguez Noval Guillermo Pelayo",
    "wof:placetype":"venue"
},
  "geometry": {"coordinates":[-5.6694722176,43.5388565063],"type":"Point"}
}