{
  "type": "Feature",
  "properties": {
    "addr:full":"Calle de Torrejon De Velasco, 8 Getafe Madrid 28901",
    "addr:housenumber":"8",
    "addr:postcode":"28901",
    "addr:street":"Calle De Torrejon De Velasco",
    "iso:country":"ES",
    "sg:address":"Calle de Torrejon De Velasco, 8",
    "sg:city":"Getafe",
    "sg:orig_category":"Colchones (fabricaci\u00d3n, Al Por Mayor, Al Por Menor)",
    "sg:phone":"+34 916 82 12 66",
    "sg:postcode":"28901",
    "sg:province":"Madrid",
    "wof:name":"Nieto Ramirez Dolores",
    "wof:placetype":"venue"
},
  "geometry": {"coordinates":[-3.7318909168,40.3019828796],"type":"Point"}
}