{
  "type": "Feature",
  "properties": {
    "addr:full":"Carrer de Rocafort, 35 Sabadell Barcelona 08205",
    "addr:housenumber":"35",
    "addr:postcode":"08205",
    "addr:street":"Carrer De Rocafort",
    "iso:country":"ES",
    "sg:address":"Carrer de Rocafort, 35",
    "sg:city":"Sabadell",
    "sg:orig_category":"Hilaturas, Hilos Y Actividades Relacionadas",
    "sg:phone":"+34 937 25 17 76",
    "sg:postcode":"08205",
    "sg:province":"Barcelona",
    "wof:name":"Auca S.l.",
    "wof:placetype":"venue"
},
  "geometry": {"coordinates":[2.0976829529,41.5378990173],"type":"Point"}
}