{
  "type": "Feature",
  "properties": {
    "iso:country":"ES",
    "sg:address":"J Gaztambide, 10",
    "sg:city":"Iru\u00f1a",
    "sg:orig_category":"Prot\u00c9sicos Dentales",
    "sg:phone":"+34 948 23 75 26",
    "sg:postcode":"31005",
    "sg:province":"Navarra",
    "wof:name":"Sarasibar Iriguibar Idoia",
    "wof:placetype":"venue"
},
  "geometry": {"coordinates":[-1.6437540054,42.81275177],"type":"Point"}
}