{
  "type": "Feature",
  "properties": {
    "iso:country":"ES",
    "sg:address":"Calle de Huertas, 14",
    "sg:city":"Madrid",
    "sg:orig_category":"Albergues",
    "sg:phone":"+34 914 29 69 35",
    "sg:postcode":"28012",
    "sg:province":"Madrid",
    "wof:name":"Chic And Basic Colors S.l.u.",
    "wof:placetype":"venue"
},
  "geometry": {"coordinates":[-3.7004840374,40.4138145447],"type":"Point"}
}