{
  "type": "Feature",
  "properties": {
    "iso:country":"ES",
    "sg:address":"Carrer de Flassaders, 25",
    "sg:city":"Barcelona",
    "sg:orig_category":"Confecci\u00d3n : Material, Suministros Y Accesorios",
    "sg:phone":"+34 933 19 52 95",
    "sg:postcode":"08003",
    "sg:province":"Barcelona",
    "wof:name":"Mora Santacreu Ricardo",
    "wof:placetype":"venue"
},
  "geometry": {"coordinates":[2.182131052,41.3854255676],"type":"Point"}
}