{
  "type": "Feature",
  "properties": {
    "addr:full":"Calle de Avellanos, 4 Burgos Burgos 09003",
    "addr:housenumber":"4",
    "addr:postcode":"09003",
    "addr:street":"Calle De Avellanos",
    "iso:country":"ES",
    "sg:address":"Calle de Avellanos, 4",
    "sg:city":"Burgos",
    "sg:orig_category":"Financiaci\u00d3n Y Cr\u00c9ditos",
    "sg:phone":"+34 947 27 91 98",
    "sg:postcode":"09003",
    "sg:province":"Burgos",
    "wof:name":"Enter Gestion S.l.",
    "wof:placetype":"venue"
},
  "geometry": {"coordinates":[-3.7011809349,42.3433036804],"type":"Point"}
}