{
  "type": "Feature",
  "properties": {
    "addr:full":"Balvis, S/n Cari\u00f1o La Coru\u00f1a 15360",
    "addr:postcode":"15360",
    "addr:street":"Balvis S / N Carin\u0303O La Corun\u0303A",
    "iso:country":"ES",
    "sg:address":"Balvis, S/n",
    "sg:city":"Cari\u00f1o",
    "sg:orig_category":"Carnicer\u00cdas, Carnicer\u00cdas",
    "sg:phone":"+34 981 42 02 81",
    "sg:postcode":"15360",
    "sg:province":"La Coru\u00f1a",
    "wof:name":"Lopez Pena Remedios",
    "wof:placetype":"venue"
},
  "geometry": {"coordinates":[-7.8690891266,43.7409934998],"type":"Point"}
}