{
  "type": "Feature",
  "properties": {
    "iso:country":"ES",
    "sg:address":"Ctra Viella (de), S/n",
    "sg:city":"Benabarre",
    "sg:orig_category":"Agricultores, Agricultores",
    "sg:phone":"+34 974 54 32 12",
    "sg:postcode":"22580",
    "sg:province":"Huesca",
    "wof:name":"Prior Ganadera S.l.",
    "wof:placetype":"venue"
},
  "geometry": {"coordinates":[0.4834649861,42.1052017212],"type":"Point"}
}