{
  "type": "Feature",
  "properties": {
    "iso:country":"ES",
    "sg:address":"Carretera De Busot, Km. 0001,0",
    "sg:city":"Jijona",
    "sg:orig_category":"Confiter\u00cdas, Chocolater\u00cdas (al Por Menor)",
    "sg:phone":"+34 965 61 11 14",
    "sg:postcode":"03100",
    "sg:province":"Alicante",
    "wof:name":"Peladillera De Jijona S.l.",
    "wof:placetype":"venue"
},
  "geometry": {"coordinates":[-0.4973269999,38.5448608398],"type":"Point"}
}