{
  "type": "Feature",
  "properties": {
    "addr:full":"Rua Tino Grandio (pintor), 22 Lugo Lugo 27004",
    "addr:housenumber":"22",
    "addr:postcode":"27004",
    "addr:street":"Rua Tino Grandio Pintor",
    "iso:country":"ES",
    "sg:address":"Rua Tino Grandio (pintor), 22",
    "sg:city":"Lugo",
    "sg:orig_category":"Tapiceros Y Tapiceros",
    "sg:phone":"+34 982 22 61 09",
    "sg:postcode":"27004",
    "sg:province":"Lugo",
    "wof:name":"Decorinex S. L.",
    "wof:placetype":"venue"
},
  "geometry": {"coordinates":[-7.5623941422,43.0166702271],"type":"Point"}
}