{
  "type": "Feature",
  "properties": {
    "iso:country":"ES",
    "sg:address":"Avda Ca\u00d1ete De Las Torres, 56",
    "sg:city":"Baena",
    "sg:orig_category":"Electricidad: Instaladores",
    "sg:phone":"+34 957 69 03 09",
    "sg:postcode":"14850",
    "sg:province":"C\u00f3rdoba",
    "wof:name":"Instalaciones Electricas Trillo S.l.l.",
    "wof:placetype":"venue"
},
  "geometry": {"coordinates":[-4.3263406754,37.6200141907],"type":"Point"}
}