{
  "type": "Feature",
  "properties": {
    "addr:full":"Calle de San Cipriano, S/n Madrid Madrid 28032",
    "addr:housenumber":"s / n",
    "addr:postcode":"28032",
    "addr:street":"Calle De San",
    "iso:country":"ES",
    "sg:address":"Calle de San Cipriano, S/n",
    "sg:city":"Madrid",
    "sg:orig_category":"Bisuter\u00cda, Joyer\u00cda, Relojer\u00cda (al Por Menor)",
    "sg:phone":"+34 917 76 07 26",
    "sg:postcode":"28032",
    "sg:province":"Madrid",
    "wof:name":"Lopez Y Miranda Joyeros S.l",
    "wof:placetype":"venue"
},
  "geometry": {"coordinates":[-3.6086690426,40.4042053223],"type":"Point"}
}