{
  "type": "Feature",
  "properties": {
    "addr:full":"Satrexas, 118 Monterroso Lugo 27560",
    "addr:housenumber":"118",
    "addr:postcode":"27560",
    "addr:street":"Satrexas",
    "iso:country":"ES",
    "sg:address":"Satrexas, 118",
    "sg:city":"Monterroso",
    "sg:orig_category":"Mec\u00c1nico Del Autom\u00d3vil",
    "sg:phone":"+34 982 37 73 02",
    "sg:postcode":"27560",
    "sg:province":"Lugo",
    "wof:name":"Carrocerias Espi\u00f1o S.l.",
    "wof:placetype":"venue"
},
  "geometry": {"coordinates":[-7.8364238739,42.7928886414],"type":"Point"}
}