{
  "type": "Feature",
  "properties": {
    "iso:country":"ES",
    "sg:address":"Pase San Antonio, 67",
    "sg:city":"Palmas De Gran Canaria",
    "sg:orig_category":"Agencias Y Agentes Comerciales, Representantes",
    "sg:phone":"+34 928 36 37 86",
    "sg:postcode":"35014",
    "sg:province":"Las Palmas",
    "wof:name":"Jimenez Molinero Juan Santiago",
    "wof:placetype":"venue"
},
  "geometry": {"coordinates":[-15.4233427048,28.1095027924],"type":"Point"}
}