{
  "type": "Feature",
  "properties": {
    "iso:country":"ES",
    "sg:address":"Calle de Oleta, 3",
    "sg:city":"Basauri",
    "sg:orig_category":"Alumbrados",
    "sg:phone":"+34 944 05 65 75",
    "sg:postcode":"48970",
    "sg:province":"Vizcaya",
    "wof:name":"Luxbi, S.l.",
    "wof:placetype":"venue"
},
  "geometry": {"coordinates":[-2.879983902,43.2373695374],"type":"Point"}
}