{
  "type": "Feature",
  "properties": {
    "addr:full":"Can Ferrer Del Mas, 6 Sant Sadurni D'anoia Barcelona 08770",
    "addr:postcode":"08770",
    "iso:country":"ES",
    "sg:address":"Can Ferrer Del Mas, 6",
    "sg:city":"Sant Sadurni D'anoia",
    "sg:orig_category":"Cajas De Ahorro",
    "sg:phone":"+34 938 91 00 56",
    "sg:postcode":"08770",
    "sg:province":"Barcelona",
    "wof:name":"Caixa D'estalvis Del Penedes",
    "wof:placetype":"venue"
},
  "geometry": {"coordinates":[1.6083999872,41.6151885986],"type":"Point"}
}