{
  "type": "Feature",
  "properties": {
    "addr:full":"Av Fco Salzillo(pol Ind Oeste), S/n S. Gines Murcia 30169",
    "addr:housenumber":"s",
    "addr:postcode":"30169",
    "addr:street":"Av Fco Salzillo Pol Ind Oeste;/ N S.",
    "iso:country":"ES",
    "sg:address":"Av Fco Salzillo(pol Ind Oeste), S/n",
    "sg:city":"S. Gines",
    "sg:orig_category":"Grabados Y Decoraci\u00d3n De Metales",
    "sg:phone":"+34 968 88 01 70",
    "sg:postcode":"30169",
    "sg:province":"Murcia",
    "wof:name":"Fundicion Hermanos Oliva C.b.",
    "wof:placetype":"venue"
},
  "geometry": {"coordinates":[-1.177366972,37.9589958191],"type":"Point"}
}