{
  "type": "Feature",
  "properties": {
    "addr:full":"Carr Conquistador, Del, 98 Binissalem Islas Baleares 07350",
    "addr:housenumber":"98",
    "addr:postcode":"07350",
    "addr:street":"Carr Conquistador Del",
    "iso:country":"ES",
    "sg:address":"Carr Conquistador, Del, 98",
    "sg:city":"Binissalem",
    "sg:orig_category":"Restaurantes",
    "sg:phone":"+34 971 51 13 73",
    "sg:postcode":"07350",
    "sg:province":"Islas Baleares",
    "wof:name":"Binivinya S.l.",
    "wof:placetype":"venue"
},
  "geometry": {"coordinates":[2.8433868885,39.6827278137],"type":"Point"}
}