{
  "type": "Feature",
  "properties": {
    "iso:country":"ES",
    "sg:address":"Pase Tomas Morales, 42",
    "sg:city":"Palmas De Gran Canaria",
    "sg:orig_category":"M\u00c9dicos: Otorrinolaringolog\u00cda",
    "sg:phone":"+34 928 37 32 01",
    "sg:postcode":"35003",
    "sg:province":"Las Palmas",
    "wof:name":"Ceotocan Grupo Sl",
    "wof:placetype":"venue"
},
  "geometry": {"coordinates":[-15.4213848114,28.1094760895],"type":"Point"}
}