{
  "type": "Feature",
  "properties": {
    "addr:full":"Calle de Antonio Moreno, 25 Madrid Madrid 28025",
    "addr:housenumber":"25",
    "addr:postcode":"madrid;28025",
    "addr:street":"Calle De Antonio Moreno",
    "iso:country":"ES",
    "sg:address":"Calle de Antonio Moreno, 25",
    "sg:city":"Madrid",
    "sg:orig_category":"Centros De Educaci\u00d3n Especial",
    "sg:phone":"+34 915 60 54 95",
    "sg:postcode":"28025",
    "sg:province":"Madrid",
    "wof:name":"Comunidad Autonoma De Madrid-centros De Educacion",
    "wof:placetype":"venue"
},
  "geometry": {"coordinates":[-3.7257788181,40.3847045898],"type":"Point"}
}