{
  "type": "Feature",
  "properties": {
    "addr:full":"Rua Leonardo Alonso, 4 Balsa Pontevedra 36213",
    "addr:housenumber":"4",
    "addr:postcode":"36213",
    "addr:street":"Rua Leonardo Alonso",
    "iso:country":"ES",
    "sg:address":"Rua Leonardo Alonso, 4",
    "sg:city":"Balsa",
    "sg:orig_category":"Peluquer\u00cdas, Peluquer\u00cda Mixta",
    "sg:phone":"+34 986 24 36 62",
    "sg:postcode":"36213",
    "sg:province":"Pontevedra",
    "wof:name":"Iglesias Alonso Trinidad",
    "wof:placetype":"venue"
},
  "geometry": {"coordinates":[-8.7210121155,42.1948318481],"type":"Point"}
}