{
  "type": "Feature",
  "properties": {
    "iso:country":"ES",
    "sg:address":"Calle de Easo, 71",
    "sg:city":"Donostia-san Sebastian",
    "sg:orig_category":"Procuradores",
    "sg:phone":"+34 943 47 36 80",
    "sg:postcode":"20006",
    "sg:province":"Guip\u00f9zcoa",
    "wof:name":"Alvarez Lopez Bego\u00f1a",
    "wof:placetype":"venue"
},
  "geometry": {"coordinates":[-1.9815380573,43.3135299683],"type":"Point"}
}