{
  "type": "Feature",
  "properties": {
    "iso:country":"ES",
    "sg:address":"Calle de Pintor Soler Blasco, 24",
    "sg:city":"Castellon",
    "sg:orig_category":"Clases De M\u00dasica Y Canto",
    "sg:phone":"+34 964 22 02 75",
    "sg:postcode":"12003",
    "sg:province":"Castell\u00f3n",
    "wof:name":"Asociacion Tres Per Quatre",
    "wof:placetype":"venue"
},
  "geometry": {"coordinates":[-0.0287254006,39.9809265137],"type":"Point"}
}