{
  "type": "Feature",
  "properties": {
    "addr:full":"Carr Enginyer Balaguer, (de L'), 112 Carlet Valencia 46240",
    "addr:housenumber":"112",
    "addr:postcode":"46240",
    "addr:street":"Carr Enginyer;De L '",
    "iso:country":"ES",
    "sg:address":"Carr Enginyer Balaguer, (de L'), 112",
    "sg:city":"Carlet",
    "sg:orig_category":"Inmobiliaria (agencias)",
    "sg:phone":"+34 962 53 13 45",
    "sg:postcode":"46240",
    "sg:province":"Valencia",
    "wof:name":"Garcia Valero Jose",
    "wof:placetype":"venue"
},
  "geometry": {"coordinates":[-0.5192459822,39.2225112915],"type":"Point"}
}