{
  "type": "Feature",
  "properties": {
    "iso:country":"ES",
    "sg:address":"Calle de Molares, 38",
    "sg:city":"Utrera",
    "sg:orig_category":"Pescader\u00cdas (al Por Menor)",
    "sg:phone":"+34 954 86 34 91",
    "sg:postcode":"41710",
    "sg:province":"Sevilla",
    "wof:name":"Gomez Rayo Felipe Jesus",
    "wof:placetype":"venue"
},
  "geometry": {"coordinates":[-5.7744598389,37.1785697937],"type":"Point"}
}