{
  "type": "Feature",
  "properties": {
    "iso:country":"ES",
    "sg:address":"Calle de Francisco Pallas, 1",
    "sg:city":"Bigastro",
    "sg:orig_category":"Aguas (distribuci\u00d3n, Servicios)",
    "sg:phone":"+34 965 35 00 16",
    "sg:postcode":"03380",
    "sg:province":"Alicante",
    "wof:name":"Comunidad De Regantes Santo Domingo",
    "wof:placetype":"venue"
},
  "geometry": {"coordinates":[-0.8946830034,38.0626182556],"type":"Point"}
}