{
  "type": "Feature",
  "properties": {
    "addr:full":"Calle de Chacel, General, 6 Melilla Melilla 52001",
    "addr:housenumber":"6",
    "addr:postcode":"52001",
    "addr:street":"Calle De Chacel General",
    "iso:country":"ES",
    "sg:address":"Calle de Chacel, General, 6",
    "sg:city":"Melilla",
    "sg:orig_category":"M\u00c9dicos: Ginecolog\u00cda Y Obstetricia",
    "sg:phone":"+34 952 68 34 16",
    "sg:postcode":"52001",
    "sg:province":"Melilla",
    "wof:name":"Sancho-mi\u00f1ano Belmonte Justo",
    "wof:placetype":"venue"
},
  "geometry": {"coordinates":[-2.9404172897,35.2931060791],"type":"Point"}
}