{
  "type": "Feature",
  "properties": {
    "iso:country":"ES",
    "sg:address":"Rua Antonio Puga, 28",
    "sg:city":"Ourense",
    "sg:orig_category":"Molduras, Junquillos, Listones Y Molduras Perforadas",
    "sg:phone":"+34 988 22 18 86",
    "sg:postcode":"32002",
    "sg:province":"Ourense",
    "wof:name":"Carreira Lopez Jose",
    "wof:placetype":"venue"
},
  "geometry": {"coordinates":[-7.8690547943,42.3411827087],"type":"Point"}
}