{
  "type": "Feature",
  "properties": {
    "iso:country":"ES",
    "sg:address":"Calle de Juan Francisco, 7",
    "sg:city":"Madrid",
    "sg:orig_category":"Arquitectos",
    "sg:phone":"+34 914 71 50 01",
    "sg:postcode":"28025",
    "sg:province":"Madrid",
    "wof:name":"Rodriguez Vozmediano Antonio",
    "wof:placetype":"venue"
},
  "geometry": {"coordinates":[-3.7314589024,40.3874740601],"type":"Point"}
}