{
  "type": "Feature",
  "properties": {
    "iso:country":"ES",
    "sg:address":"Av Pere Matutes Noguera, S/n",
    "sg:city":"Eivissa",
    "sg:orig_category":"Ropa Para Caballeros (al Por Menor)",
    "sg:phone":"+34 971 39 98 07",
    "sg:postcode":"07800",
    "sg:province":"Islas Baleares",
    "sg:website":"www.lacoste.es",
    "wof:name":"Ferrer Lopez Carlos",
    "wof:placetype":"venue"
},
  "geometry": {"coordinates":[1.4183349609,38.9009246826],"type":"Point"}
}