{
  "type": "Feature",
  "properties": {
    "addr:full":"Calle de Hoyo De Esparteros, 1 Malaga M\u00e1laga 29005",
    "addr:housenumber":"1",
    "addr:postcode":"29005",
    "addr:street":"Calle De Hoyo De Esparteros;Ma\u0301Laga",
    "iso:country":"ES",
    "sg:address":"Calle de Hoyo De Esparteros, 1",
    "sg:city":"Malaga",
    "sg:orig_category":"Panader\u00cdas, Panader\u00cdas",
    "sg:phone":"+34 952 60 40 95",
    "sg:postcode":"29005",
    "sg:province":"M\u00e1laga",
    "wof:name":"Alorpan S.l.",
    "wof:placetype":"venue"
},
  "geometry": {"coordinates":[-4.4248967171,36.7178916931],"type":"Point"}
}