{
  "type": "Feature",
  "properties": {
    "iso:country":"ES",
    "sg:address":"Calle de Maestro Mu\u00d1oz Molleda, 9",
    "sg:city":"Linea De La Concepcion",
    "sg:orig_category":"Dom\u00d3tica",
    "sg:phone":"+34 956 69 00 75",
    "sg:postcode":"11300",
    "sg:province":"C\u00e1diz",
    "wof:name":"Instamaya S.l.",
    "wof:placetype":"venue"
},
  "geometry": {"coordinates":[-5.3476209641,36.1631240845],"type":"Point"}
}