{
  "type": "Feature",
  "properties": {
    "addr:full":"Calle de Rafael Barez, 8 Coru\u00d1a La Coru\u00f1a 15009",
    "addr:housenumber":"8",
    "addr:postcode":"15009",
    "addr:street":"Calle De Rafael Barez;La Corun\u0303A",
    "iso:country":"ES",
    "sg:address":"Calle de Rafael Barez, 8",
    "sg:city":"Coru\u00d1a",
    "sg:orig_category":"Muebles Y Accesorios Para Cocinas Y Cuartos De Ba\u00d1o (al Por Menor)",
    "sg:phone":"+34 981 13 84 95",
    "sg:postcode":"15009",
    "sg:province":"La Coru\u00f1a",
    "wof:name":"Mui\u00f1os Gonzalez Eulogio",
    "wof:placetype":"venue"
},
  "geometry": {"coordinates":[-8.4001913071,43.3474311829],"type":"Point"}
}