{
  "type": "Feature",
  "properties": {
    "iso:country":"ES",
    "sg:address":"Zaldibi Bidea, 1",
    "sg:city":"Ordizia",
    "sg:orig_category":"Mec\u00c1nico Del Autom\u00d3vil",
    "sg:phone":"+34 943 88 10 73",
    "sg:postcode":"20240",
    "sg:province":"Guip\u00f9zcoa",
    "wof:name":"Goierri Autoak S.a.l.",
    "wof:placetype":"venue"
},
  "geometry": {"coordinates":[-2.1773040295,43.0538711548],"type":"Point"}
}