{
  "type": "Feature",
  "properties": {
    "iso:country":"ES",
    "sg:address":"Carrer de Reial, 33",
    "sg:city":"Tarragona",
    "sg:orig_category":"Electricidad: Instaladores",
    "sg:phone":"+34 977 21 42 45",
    "sg:postcode":"43004",
    "sg:province":"Tarragona",
    "wof:name":"Merino Requena Cristobal",
    "wof:placetype":"venue"
},
  "geometry": {"coordinates":[1.2440710068,41.1118164062],"type":"Point"}
}