{
  "type": "Feature",
  "properties": {
    "addr:full":"Carr Fra Junipero Serra, 1 Son Serra De Marina Islas Baleares 07459",
    "addr:housenumber":"1",
    "addr:postcode":"07459",
    "addr:street":"Carr Fra Junipero Serra",
    "iso:country":"ES",
    "sg:address":"Carr Fra Junipero Serra, 1",
    "sg:city":"Son Serra De Marina",
    "sg:orig_category":"M\u00c9dicos: Cirug\u00cda Pl\u00c1stica, Reconstructiva Y Est\u00c9tica",
    "sg:phone":"+34 971 85 40 00",
    "sg:postcode":"07459",
    "sg:province":"Islas Baleares",
    "wof:name":"Gallego Soler Jose Fermin",
    "wof:placetype":"venue"
},
  "geometry": {"coordinates":[3.2355809212,39.7311553955],"type":"Point"}
}