{
  "type": "Feature",
  "properties": {
    "addr:full":"Calle de Zaragoza, 32 Estepona M\u00e1laga 29680",
    "addr:housenumber":"32",
    "addr:postcode":"29680",
    "addr:street":"Calle De Zaragoza",
    "iso:country":"ES",
    "sg:address":"Calle de Zaragoza, 32",
    "sg:city":"Estepona",
    "sg:orig_category":"Ropa Para Se\u00d1oras Y Caballeros (al Por Menor)",
    "sg:phone":"+34 952 80 02 28",
    "sg:postcode":"29680",
    "sg:province":"M\u00e1laga",
    "wof:name":"Cortes Abril Carlos",
    "wof:placetype":"venue"
},
  "geometry": {"coordinates":[-5.1446452141,36.4280853271],"type":"Point"}
}