{
  "type": "Feature",
  "properties": {
    "iso:country":"ES",
    "sg:address":"Avda Madrid, 19",
    "sg:city":"Laguna Duero",
    "sg:orig_category":"Inmobiliaria (agencias)",
    "sg:phone":"+34 983 54 62 90",
    "sg:postcode":"47140",
    "sg:province":"Valladolid",
    "wof:name":"Ceigrup Valladolid S.l.",
    "wof:placetype":"venue"
},
  "geometry": {"coordinates":[-4.7192249298,41.5834388733],"type":"Point"}
}