{
  "type": "Feature",
  "properties": {
    "addr:full":"Calle de Molino (el), 17 Ba\u00d1eza Le\u00f3n 24750",
    "addr:postcode":"24750",
    "addr:street":"Calle De Molino El;Ban\u0303Eza Leo\u0301N",
    "iso:country":"ES",
    "sg:address":"Calle de Molino (el), 17",
    "sg:city":"Ba\u00d1eza",
    "sg:orig_category":"Molduras, Junquillos, Listones Y Molduras Perforadas",
    "sg:phone":"+34 987 64 06 83",
    "sg:postcode":"24750",
    "sg:province":"Le\u00f3n",
    "wof:name":"Gonzalez Cela Maria Dolores",
    "wof:placetype":"venue"
},
  "geometry": {"coordinates":[-5.9242091179,42.3069114685],"type":"Point"}
}