{
  "type": "Feature",
  "properties": {
    "addr:full":"Calle de Rio Sella, S/n Castellon Castell\u00f3n 12005",
    "addr:housenumber":"s / n",
    "addr:postcode":"12005",
    "addr:street":"Calle De Rio Sella",
    "iso:country":"ES",
    "sg:address":"Calle de Rio Sella, S/n",
    "sg:city":"Castellon",
    "sg:orig_category":"Promotores Constructores",
    "sg:phone":"+34 964 76 03 74",
    "sg:postcode":"12005",
    "sg:province":"Castell\u00f3n",
    "wof:name":"Promojucar S.a.",
    "wof:placetype":"venue"
},
  "geometry": {"coordinates":[-0.0335940011,39.97423172],"type":"Point"}
}