{
  "type": "Feature",
  "properties": {
    "iso:country":"ES",
    "sg:address":"Calle de Balsas, 12",
    "sg:city":"Santa Cruz De La Zarza",
    "sg:orig_category":"Empresas De Limpieza",
    "sg:phone":"+34 925 12 52 98",
    "sg:postcode":"45370",
    "sg:province":"Toledo",
    "wof:name":"Limpiezas Y Pulidos F. Camara",
    "wof:placetype":"venue"
},
  "geometry": {"coordinates":[-3.1890947819,39.986000061],"type":"Point"}
}