{
  "type": "Feature",
  "properties": {
    "addr:full":"Calle de Ricardo Velazquez, 11 Huelva Huelva 21003",
    "addr:housenumber":"11",
    "addr:postcode":"21003",
    "addr:street":"Calle De Ricardo Velazquez",
    "iso:country":"ES",
    "sg:address":"Calle de Ricardo Velazquez, 11",
    "sg:city":"Huelva",
    "sg:orig_category":"Asesor\u00cda De Formaci\u00d3n Y Gesti\u00d3n De Personal",
    "sg:phone":"+34 959 25 11 37",
    "sg:postcode":"21003",
    "sg:province":"Huelva",
    "wof:name":"Herrera Mariscal,bocharan,lopez,despacho Laboralista S.l.l.",
    "wof:placetype":"venue"
},
  "geometry": {"coordinates":[-6.948102951,37.2569732666],"type":"Point"}
}