{
  "type": "Feature",
  "properties": {
    "addr:full":"C/ Pintor Casanova, 24 Alcoi Alicante 03801",
    "addr:housenumber":"24",
    "addr:postcode":"03801",
    "addr:street":"C / Pintor Casanova",
    "iso:country":"ES",
    "sg:address":"C/ Pintor Casanova, 24",
    "sg:city":"Alcoi",
    "sg:orig_category":"Internados & Ense\u00d1anza Privada",
    "sg:phone":"+34 965 54 47 02",
    "sg:postcode":"03801",
    "sg:province":"Alicante",
    "wof:name":"Colegio De La Presentacion Hermanas Carmelitas",
    "wof:placetype":"venue"
},
  "geometry": {"coordinates":[-0.4730120003,38.699306488],"type":"Point"}
}