{
  "type": "Feature",
  "properties": {
    "iso:country":"ES",
    "sg:address":"Avda Carabanchel Alto, 3",
    "sg:city":"Madrid",
    "sg:orig_category":"Laboratorios Y Trabajos De Fotograf\u00cda, V\u00cddeo Y Cine",
    "sg:phone":"+34 915 08 97 97",
    "sg:postcode":"28044",
    "sg:province":"Madrid",
    "wof:name":"I.d.imagen S.l.",
    "wof:placetype":"venue"
},
  "geometry": {"coordinates":[-3.7513289452,40.3728027344],"type":"Point"}
}