{
  "type": "Feature",
  "properties": {
    "iso:country":"ES",
    "sg:address":"Calle de Balmes, 38",
    "sg:city":"Alaquas",
    "sg:orig_category":"Asesor\u00cda Fiscal Y Jur\u00cddica",
    "sg:phone":"+34 961 51 50 00",
    "sg:postcode":"46970",
    "sg:province":"Valencia",
    "wof:name":"Asd European Tranding Group Iberica S.l.",
    "wof:placetype":"venue"
},
  "geometry": {"coordinates":[-0.4662907124,39.456325531],"type":"Point"}
}