{
  "type": "Feature",
  "properties": {
    "addr:full":"Calle de Pastrana, 14 Mondejar Guadalajara 19110",
    "addr:housenumber":"14",
    "addr:postcode":"19110",
    "addr:street":"Calle De Pastrana",
    "iso:country":"ES",
    "sg:address":"Calle de Pastrana, 14",
    "sg:city":"Mondejar",
    "sg:orig_category":"Empresas De Pintura Y Revestimientos",
    "sg:phone":"+34 949 38 56 97",
    "sg:postcode":"19110",
    "sg:province":"Guadalajara",
    "wof:name":"Torres Segovia Pedro",
    "wof:placetype":"venue"
},
  "geometry": {"coordinates":[-3.1035583019,40.327331543],"type":"Point"}
}