{
  "type": "Feature",
  "properties": {
    "addr:full":"Calle de Ricardo De La Vega, 3 Getafe Madrid 28901",
    "addr:housenumber":"3",
    "addr:postcode":"28901",
    "addr:street":"Calle De Ricardo De La Vega",
    "iso:country":"ES",
    "sg:address":"Calle de Ricardo De La Vega, 3",
    "sg:city":"Getafe",
    "sg:orig_category":"M\u00c9dicos: Estomatolog\u00cda",
    "sg:phone":"+34 916 82 98 32",
    "sg:postcode":"28901",
    "sg:province":"Madrid",
    "wof:name":"Fernandez Pujol Ramon",
    "wof:placetype":"venue"
},
  "geometry": {"coordinates":[-3.7298519611,40.3067169189],"type":"Point"}
}