{
  "type": "Feature",
  "properties": {
    "addr:full":"Carrer de Narcis Monturiol, 2 Mas Rampinyo Barcelona 08110",
    "addr:housenumber":"2",
    "addr:postcode":"08110",
    "addr:street":"Carrer De Narcis Monturiol",
    "iso:country":"ES",
    "sg:address":"Carrer de Narcis Monturiol, 2",
    "sg:city":"Mas Rampinyo",
    "sg:orig_category":"Chapister\u00cda",
    "sg:phone":"+34 935 64 50 47",
    "sg:postcode":"08110",
    "sg:province":"Barcelona",
    "wof:name":"Autoreparacion Agm S.l.",
    "wof:placetype":"venue"
},
  "geometry": {"coordinates":[2.1809530258,41.4910163879],"type":"Point"}
}