{
  "type": "Feature",
  "properties": {
    "addr:full":"Avda Extremadura, 20 Navaconcejo C\u00e1ceres 10613",
    "addr:housenumber":"20",
    "addr:postcode":"10613",
    "addr:street":"Avda Extremadura;Ca\u0301Ceres",
    "iso:country":"ES",
    "sg:address":"Avda Extremadura, 20",
    "sg:city":"Navaconcejo",
    "sg:orig_category":"Librer\u00cdas",
    "sg:phone":"+34 927 17 34 98",
    "sg:postcode":"10613",
    "sg:province":"C\u00e1ceres",
    "wof:name":"Perez Barroso Roberto",
    "wof:placetype":"venue"
},
  "geometry": {"coordinates":[-5.8326358795,40.175453186],"type":"Point"}
}