{
  "type": "Feature",
  "properties": {
    "iso:country":"ES",
    "sg:address":"Carrer de Sant Isidre, 29",
    "sg:city":"Molins Rei",
    "sg:orig_category":"Transporte En General",
    "sg:phone":"+34 936 68 08 49",
    "sg:postcode":"08750",
    "sg:province":"Barcelona",
    "wof:name":"Edding 04 S.l.",
    "wof:placetype":"venue"
},
  "geometry": {"coordinates":[2.02135396,41.4070358276],"type":"Point"}
}