{
  "type": "Feature",
  "properties": {
    "iso:country":"ES",
    "sg:address":"Plaz Mikel Deuna Plaza, 7",
    "sg:city":"Arteaga Derio",
    "sg:orig_category":"Carnicer\u00cdas, Carnicer\u00cdas",
    "sg:phone":"+34 944 54 52 94",
    "sg:postcode":"48160",
    "sg:province":"Vizcaya",
    "wof:name":"Ruiz Soto Miguel Angel",
    "wof:placetype":"venue"
},
  "geometry": {"coordinates":[-2.8862609863,43.2926712036],"type":"Point"}
}