{
  "type": "Feature",
  "properties": {
    "iso:country":"ES",
    "sg:address":"Avgd Segre, 1",
    "sg:city":"Lleida",
    "sg:orig_category":"Suministros Y Materiales Industriales",
    "sg:phone":"+34 973 23 68 91",
    "sg:postcode":"25007",
    "sg:province":"Lleida",
    "wof:name":"Agustin Mestre S.a.",
    "wof:placetype":"venue"
},
  "geometry": {"coordinates":[0.6303461194,41.6161842346],"type":"Point"}
}