{
  "type": "Feature",
  "properties": {
    "iso:country":"ES",
    "sg:address":"La Puente, 5",
    "sg:city":"Azadinos",
    "sg:orig_category":"Molduras, Junquillos, Listones Y Molduras Perforadas",
    "sg:phone":"+34 987 28 05 62",
    "sg:postcode":"24121",
    "sg:province":"Le\u00f3n",
    "wof:name":"Aller Sierra Jose",
    "wof:placetype":"venue"
},
  "geometry": {"coordinates":[-5.6133904457,42.6386184692],"type":"Point"}
}