{
  "type": "Feature",
  "properties": {
    "iso:country":"ES",
    "sg:address":"Avda Duque De Ahumada, S/n",
    "sg:city":"Torre Mar",
    "sg:orig_category":"Fabricaci\u00d3n, Venta, Instalaci\u00d3n De R\u00d3tulos, De R\u00d3tulos Luminosos",
    "sg:phone":"+34 952 54 01 91",
    "sg:postcode":"29740",
    "sg:province":"M\u00e1laga",
    "wof:name":"Maldonado Jimenez Antonio",
    "wof:placetype":"venue"
},
  "geometry": {"coordinates":[-4.0968747139,36.739074707],"type":"Point"}
}