{
  "type": "Feature",
  "properties": {
    "iso:country":"ES",
    "sg:address":"Calle de San Bartolome, 4",
    "sg:city":"Barbastro",
    "sg:orig_category":"Agencias De Trabajo Temporal",
    "sg:phone":"+34 974 31 54 18",
    "sg:postcode":"22300",
    "sg:province":"Huesca",
    "sg:website":"www.adecco.es",
    "wof:name":"Adecco E.t.t. S.a.",
    "wof:placetype":"venue"
},
  "geometry": {"coordinates":[0.1259817928,42.0361480713],"type":"Point"}
}