{
  "type": "Feature",
  "properties": {
    "iso:country":"ES",
    "sg:address":"Calle de Carlos Gangoiti, 1",
    "sg:city":"Gernika-lumo",
    "sg:orig_category":"Arquitectos",
    "sg:phone":"+34 946 27 06 63",
    "sg:postcode":"48300",
    "sg:province":"Vizcaya",
    "wof:name":"Igaralde Tellechea Urbano",
    "wof:placetype":"venue"
},
  "geometry": {"coordinates":[-2.6785542965,43.3200378418],"type":"Point"}
}