{
  "type": "Feature",
  "properties": {
    "addr:full":"Calle de Vallejo, 18 Autol La Rioja 26560",
    "addr:housenumber":"18",
    "addr:postcode":"26560",
    "addr:street":"Calle De Vallejo;Rioja",
    "iso:country":"ES",
    "sg:address":"Calle de Vallejo, 18",
    "sg:city":"Autol",
    "sg:orig_category":"Agencias Y Agentes Comerciales, Representantes",
    "sg:phone":"+34 941 40 12 48",
    "sg:postcode":"26560",
    "sg:province":"La Rioja",
    "wof:name":"Jimenez Ezquerro Valentin",
    "wof:placetype":"venue"
},
  "geometry": {"coordinates":[-2.0066177845,42.2160301208],"type":"Point"}
}