{
  "type": "Feature",
  "properties": {
    "addr:full":"Calle de Hospital, 29 Yecla Murcia 30510",
    "addr:housenumber":"29",
    "addr:postcode":"30510",
    "addr:street":"Calle De Hospital",
    "iso:country":"ES",
    "sg:address":"Calle de Hospital, 29",
    "sg:city":"Yecla",
    "sg:orig_category":"Consultas M\u00c9dicas",
    "sg:phone":"+34 968 79 47 55",
    "sg:postcode":"30510",
    "sg:province":"Murcia",
    "wof:name":"Luis Azorin S.l.",
    "wof:placetype":"venue"
},
  "geometry": {"coordinates":[-1.1146370173,38.6123352051],"type":"Point"}
}