{
  "type": "Feature",
  "properties": {
    "addr:full":"Avda Hernan Cortes, 36 Caceres C\u00e1ceres 10004",
    "addr:housenumber":"36",
    "addr:postcode":"10004",
    "addr:street":"Avda Hernan Cortes;Ca\u0301Ceres",
    "iso:country":"ES",
    "sg:address":"Avda Hernan Cortes, 36",
    "sg:city":"Caceres",
    "sg:orig_category":"Asociaciones Y Clubs Deportivos",
    "sg:phone":"+34 927 24 51 52",
    "sg:postcode":"10004",
    "sg:province":"C\u00e1ceres",
    "wof:name":"Martinez Garcia Domingo",
    "wof:placetype":"venue"
},
  "geometry": {"coordinates":[-6.3793668747,39.4761238098],"type":"Point"}
}