{
  "type": "Feature",
  "properties": {
    "addr:full":"Mercado De Abastos, S/n Cabeza Buey Badajoz 06600",
    "addr:housenumber":"s / n",
    "addr:postcode":"06600",
    "iso:country":"ES",
    "sg:address":"Mercado De Abastos, S/n",
    "sg:city":"Cabeza Buey",
    "sg:orig_category":"Pescader\u00cdas (al Por Menor)",
    "sg:phone":"+34 924 60 00 85",
    "sg:postcode":"06600",
    "sg:province":"Badajoz",
    "wof:name":"Casco Riballo Jacinto",
    "wof:placetype":"venue"
},
  "geometry": {"coordinates":[-5.2242388725,38.7196540833],"type":"Point"}
}