{
  "type": "Feature",
  "properties": {
    "addr:full":"Carrer de Sant Sebastia, 32 Sitges Barcelona 08870",
    "addr:housenumber":"32",
    "addr:postcode":"08870",
    "addr:street":"Carrer De Sant Sebastia",
    "iso:country":"ES",
    "sg:address":"Carrer de Sant Sebastia, 32",
    "sg:city":"Sitges",
    "sg:orig_category":"Artes Gr\u00c1ficas, Artes Pl\u00c1sticas (curso)",
    "sg:phone":"+34 938 94 64 86",
    "sg:postcode":"08870",
    "sg:province":"Barcelona",
    "wof:name":"Corretge Igea Nuria",
    "wof:placetype":"venue"
},
  "geometry": {"coordinates":[1.8120349646,41.2370491028],"type":"Point"}
}