{
  "type": "Feature",
  "properties": {
    "iso:country":"ES",
    "sg:address":"Calle de Dionisio Alcala Galiano, 12",
    "sg:city":"Cabra",
    "sg:orig_category":"Abogados",
    "sg:phone":"+34 957 52 48 70",
    "sg:postcode":"14940",
    "sg:province":"C\u00f3rdoba",
    "wof:name":"Paniego Velez Maximo",
    "wof:placetype":"venue"
},
  "geometry": {"coordinates":[-4.4444117546,37.4709815979],"type":"Point"}
}