{
  "type": "Feature",
  "properties": {
    "iso:country":"ES",
    "sg:address":"Calle de Petunia, 7",
    "sg:city":"Arroyo De La Miel-benalmadena Costa",
    "sg:orig_category":"Electricidad: Instaladores",
    "sg:phone":"+34 952 44 01 11",
    "sg:postcode":"29630",
    "sg:province":"M\u00e1laga",
    "wof:name":"Man 2000 S.l.",
    "wof:placetype":"venue"
},
  "geometry": {"coordinates":[-4.5382881165,36.581993103],"type":"Point"}
}