{
  "type": "Feature",
  "properties": {
    "iso:country":"ES",
    "sg:address":"Calle de Francisco Carrion Mejias, 9",
    "sg:city":"Sevilla",
    "sg:orig_category":"Arquitectos",
    "sg:phone":"+34 954 21 03 35",
    "sg:postcode":"41003",
    "sg:province":"Sevilla",
    "wof:name":"Sanchez Mu\u00f1oz Juan Antonio",
    "wof:placetype":"venue"
},
  "geometry": {"coordinates":[-5.9877958298,37.391910553],"type":"Point"}
}