{
  "type": "Feature",
  "properties": {
    "addr:full":"Calle de Mayor, 80 Almunia De Do\u00e7a Godina Zaragoza 50100",
    "addr:housenumber":"80",
    "addr:postcode":"50100",
    "addr:street":"Calle De Mayor",
    "iso:country":"ES",
    "sg:address":"Calle de Mayor, 80",
    "sg:city":"Almunia De Do\u00e7a Godina",
    "sg:orig_category":"Asistencia Social",
    "sg:phone":"+34 976 81 25 90",
    "sg:postcode":"50100",
    "sg:province":"Zaragoza",
    "wof:name":"Andues Romero Luis",
    "wof:placetype":"venue"
},
  "geometry": {"coordinates":[-0.8765661716,41.6563491821],"type":"Point"}
}