{
  "type": "Feature",
  "properties": {
    "iso:country":"ES",
    "sg:address":"Urb. B. Azul, S/n",
    "sg:city":"Bahia Azul",
    "sg:orig_category":"Arquitectos",
    "sg:phone":"+34 971 74 10 58",
    "sg:postcode":"07609",
    "sg:province":"Islas Baleares",
    "wof:name":"Ortega Ballester Luis Miguel",
    "wof:placetype":"venue"
},
  "geometry": {"coordinates":[2.7440850735,39.4852790833],"type":"Point"}
}