{
  "type": "Feature",
  "properties": {
    "iso:country":"ES",
    "sg:address":"Pla\u00c7 Carme, 3",
    "sg:city":"Mao",
    "sg:orig_category":"Inmobiliaria (agencias)",
    "sg:phone":"+34 971 36 78 52",
    "sg:postcode":"07702",
    "sg:province":"Islas Baleares",
    "wof:name":"Vilasanchez Martinez Ramon",
    "wof:placetype":"venue"
},
  "geometry": {"coordinates":[4.265625,39.8903694153],"type":"Point"}
}