{
  "type": "Feature",
  "properties": {
    "iso:country":"ES",
    "sg:address":"Calle de Garay, 2",
    "sg:city":"Almunia De Do\u00e7a Godina",
    "sg:orig_category":"Florister\u00cdas",
    "sg:phone":"+34 976 60 09 58",
    "sg:postcode":"50100",
    "sg:province":"Zaragoza",
    "wof:name":"Balsa Soria Araceli",
    "wof:placetype":"venue"
},
  "geometry": {"coordinates":[-1.3743289709,41.4771995544],"type":"Point"}
}