{
  "type": "Feature",
  "properties": {
    "addr:full":"Poli Poligono Industrial, 29 Barros Cantabria 39408",
    "addr:housenumber":"29",
    "addr:postcode":"39408",
    "addr:street":"Poligono Industrial",
    "iso:country":"ES",
    "sg:address":"Poli Poligono Industrial, 29",
    "sg:city":"Barros",
    "sg:orig_category":"Negocio De Materiales De Construcci\u00d3n",
    "sg:phone":"+34 942 83 27 84",
    "sg:postcode":"39408",
    "sg:province":"Cantabria",
    "sg:website":"www.paislant.com",
    "wof:name":"Aislamientos Pais S.l.",
    "wof:placetype":"venue"
},
  "geometry": {"coordinates":[-4.0775737762,43.2798995972],"type":"Point"}
}