{
  "type": "Feature",
  "properties": {
    "addr:full":"Calle de Doctor Zarco Bohorquez, 9 Ubrique C\u00e1diz 11600",
    "addr:housenumber":"9",
    "addr:postcode":"11600",
    "addr:street":"Calle De Doctor Zarco Bohorquez;Ca\u0301Diz",
    "iso:country":"ES",
    "sg:address":"Calle de Doctor Zarco Bohorquez, 9",
    "sg:city":"Ubrique",
    "sg:orig_category":"Cueros Y Pieles (al Por Mayor)",
    "sg:phone":"+34 956 46 24 29",
    "sg:postcode":"11600",
    "sg:province":"C\u00e1diz",
    "wof:name":"Jorge Luis Gonzalez S.l.",
    "wof:placetype":"venue"
},
  "geometry": {"coordinates":[-5.4475164413,36.6768569946],"type":"Point"}
}