{
  "type": "Feature",
  "properties": {
    "iso:country":"ES",
    "sg:address":"Calle de Amos De Escalante, 4",
    "sg:city":"Madrid",
    "sg:orig_category":"Fabricaci\u00d3n De Muebles",
    "sg:phone":"+34 913 77 33 54",
    "sg:postcode":"28017",
    "sg:province":"Madrid",
    "wof:name":"Escalantres S.l.",
    "wof:placetype":"venue"
},
  "geometry": {"coordinates":[-3.6423938274,40.4350738525],"type":"Point"}
}