{
  "type": "Feature",
  "properties": {
    "addr:full":"Pl Major De La Vila, 9 Benaguasil Valencia 46180",
    "addr:postcode":"46180",
    "addr:street":"Pl",
    "iso:country":"ES",
    "sg:address":"Pl Major De La Vila, 9",
    "sg:city":"Benaguasil",
    "sg:orig_category":"Bancos",
    "sg:phone":"+34 962 73 00 25",
    "sg:postcode":"46180",
    "sg:province":"Valencia",
    "wof:name":"Banco Espa\u00f1ol De Credito S.a.",
    "wof:placetype":"venue"
},
  "geometry": {"coordinates":[-0.5846890211,39.5935783386],"type":"Point"}
}