{
  "type": "Feature",
  "properties": {
    "addr:full":"Plaz Mayor, 1 Santa Marta De Tormes Salamanca 37900",
    "addr:housenumber":"1",
    "addr:postcode":"37900",
    "addr:street":"Plaz Mayor",
    "iso:country":"ES",
    "sg:address":"Plaz Mayor, 1",
    "sg:city":"Santa Marta De Tormes",
    "sg:orig_category":"Ense\u00d1anza, Formaci\u00d3n Profesional: Aprendizaje",
    "sg:phone":"+34 923 20 00 05",
    "sg:postcode":"37900",
    "sg:province":"Salamanca",
    "wof:name":"Ayuntamiento De Santa Marta De Tormes",
    "wof:placetype":"venue"
},
  "geometry": {"coordinates":[-5.6323928833,40.9500236511],"type":"Point"}
}