{
  "type": "Feature",
  "properties": {
    "iso:country":"ES",
    "sg:address":"Carrer de Miquel Granell, 15",
    "sg:city":"Amposta",
    "sg:orig_category":"Fisioterapia",
    "sg:phone":"+34 977 70 29 55",
    "sg:postcode":"43870",
    "sg:province":"Tarragona",
    "wof:name":"Centre De Fisioterapia Montsia C.b.",
    "wof:placetype":"venue"
},
  "geometry": {"coordinates":[0.579185009,40.7100296021],"type":"Point"}
}