{
  "type": "Feature",
  "properties": {
    "iso:country":"ES",
    "sg:address":"Avda Nueve De Octubre, 71",
    "sg:city":"Puerto",
    "sg:orig_category":"Empresas De Pintura Y Revestimientos",
    "sg:phone":"+34 962 67 41 15",
    "sg:postcode":"46520",
    "sg:province":"Valencia",
    "wof:name":"Garcia Vivas Vicente",
    "wof:placetype":"venue"
},
  "geometry": {"coordinates":[-0.2292370051,39.6630554199],"type":"Point"}
}