{
  "type": "Feature",
  "properties": {
    "iso:country":"ES",
    "sg:address":"Rond Pilar, 3",
    "sg:city":"Badajoz",
    "sg:orig_category":"Abogados",
    "sg:phone":"+34 924 22 06 22",
    "sg:postcode":"06002",
    "sg:province":"Badajoz",
    "wof:name":"Torres Pereda Jose Javier",
    "wof:placetype":"venue"
},
  "geometry": {"coordinates":[-6.972094059,38.8753013611],"type":"Point"}
}