{
  "type": "Feature",
  "properties": {
    "addr:full":"Avda Martinez Campos, 4 Alcantarilla Murcia 30820",
    "addr:housenumber":"4",
    "addr:postcode":"30820",
    "addr:street":"Avda Martinez Campos",
    "iso:country":"ES",
    "sg:address":"Avda Martinez Campos, 4",
    "sg:city":"Alcantarilla",
    "sg:orig_category":"Cajas De Ahorro",
    "sg:phone":"+34 968 89 22 72",
    "sg:postcode":"30820",
    "sg:province":"Murcia",
    "wof:name":"Caja De Ahorros De Murcia",
    "wof:placetype":"venue"
},
  "geometry": {"coordinates":[-1.2156260014,37.9694633484],"type":"Point"}
}