{
  "type": "Feature",
  "properties": {
    "addr:full":"Disseminat Plana Pont Nou, S/n Manresa Barcelona 08241",
    "addr:housenumber":"s / n",
    "addr:postcode":"08241",
    "iso:country":"ES",
    "sg:address":"Disseminat Plana Pont Nou, S/n",
    "sg:city":"Manresa",
    "sg:orig_category":"Reciclaje Y Tratamiento De Desechos Varios",
    "sg:phone":"+34 938 77 50 20",
    "sg:postcode":"08241",
    "sg:province":"Barcelona",
    "wof:name":"Planta Intercomarcal Del Reciclatge S.a.",
    "wof:placetype":"venue"
},
  "geometry": {"coordinates":[1.829069972,41.7212295532],"type":"Point"}
}