{
  "type": "Feature",
  "properties": {
    "addr:full":"Calle de Gordoniz, 99 Bilbao Vizcaya 48002",
    "addr:housenumber":"99",
    "addr:postcode":"48002",
    "addr:street":"Calle De Gordoniz",
    "iso:country":"ES",
    "sg:address":"Calle de Gordoniz, 99",
    "sg:city":"Bilbao",
    "sg:orig_category":"Reposter\u00cdas",
    "sg:phone":"+34 944 21 18 00",
    "sg:postcode":"48002",
    "sg:province":"Vizcaya",
    "wof:name":"Rubio Cuenca Rosa",
    "wof:placetype":"venue"
},
  "geometry": {"coordinates":[-2.9462339878,43.2519721985],"type":"Point"}
}