{
  "type": "Feature",
  "properties": {
    "addr:full":"Pl. Espanya, 10 Calonge Girona 17251",
    "addr:housenumber":"10",
    "addr:postcode":"17251",
    "addr:street":"Pl. Espanya",
    "iso:country":"ES",
    "sg:address":"Pl. Espanya, 10",
    "sg:city":"Calonge",
    "sg:orig_category":"Molduras, Junquillos, Listones Y Molduras Perforadas",
    "sg:phone":"+34 972 65 16 97",
    "sg:postcode":"17251",
    "sg:province":"Girona",
    "wof:name":"Sociedad Circulo Calongense",
    "wof:placetype":"venue"
},
  "geometry": {"coordinates":[3.07406497,41.861656189],"type":"Point"}
}