{
  "type": "Feature",
  "properties": {
    "iso:country":"ES",
    "sg:address":"Calle de Candilejas, 56",
    "sg:city":"Madrid",
    "sg:orig_category":"Asesor\u00cda Fiscal Y Jur\u00cddica",
    "sg:phone":"+34 915 07 05 90",
    "sg:postcode":"28018",
    "sg:province":"Madrid",
    "wof:name":"Valgeser J.s. S.l.",
    "wof:placetype":"venue"
},
  "geometry": {"coordinates":[-3.6621446609,40.3839912415],"type":"Point"}
}