{
  "type": "Feature",
  "properties": {
    "iso:country":"ES",
    "sg:address":"Calle de Pintor Rufino Martos (del), 3",
    "sg:city":"Jaen",
    "sg:orig_category":"Agencias Y Agentes Comerciales, Representantes",
    "sg:phone":"+34 953 25 04 08",
    "sg:postcode":"23006",
    "sg:province":"Ja\u00e9n",
    "wof:name":"Garcia Garcia Jose Maria",
    "wof:placetype":"venue"
},
  "geometry": {"coordinates":[-3.7931230068,37.7800292969],"type":"Point"}
}