{
  "type": "Feature",
  "properties": {
    "iso:country":"ES",
    "sg:address":"Avda Jose Antonio, 38",
    "sg:city":"Medina Pomar",
    "sg:orig_category":"Perreras, Pensiones Para Perros, Gatos Y Otros Animales",
    "sg:phone":"+34 947 19 17 10",
    "sg:postcode":"09500",
    "sg:province":"Burgos",
    "wof:name":"Asociacion Canina Burgalesa Soriana",
    "wof:placetype":"venue"
},
  "geometry": {"coordinates":[-3.4890911579,42.9284629822],"type":"Point"}
}