{
  "type": "Feature",
  "properties": {
    "addr:full":"Calle de Severo Ochoa, S/n Olivares Sevilla 41804",
    "addr:housenumber":"s",
    "addr:postcode":"41804",
    "addr:street":"Calle De Severo Ochoa;/ N Olivares",
    "iso:country":"ES",
    "sg:address":"Calle de Severo Ochoa, S/n",
    "sg:city":"Olivares",
    "sg:orig_category":"Institutos M\u00c9dicos",
    "sg:phone":"+34 954 11 28 00",
    "sg:postcode":"41804",
    "sg:province":"Sevilla",
    "wof:name":"Servicio Andaluz De Salud",
    "wof:placetype":"venue"
},
  "geometry": {"coordinates":[-6.1601691246,37.4146842957],"type":"Point"}
}