{
  "type": "Feature",
  "properties": {
    "iso:country":"ES",
    "sg:address":"Calle de Juan Castillo Sanchez, 4",
    "sg:city":"Sevilla",
    "sg:orig_category":"Cristaler\u00cdas",
    "sg:phone":"+34 954 64 27 30",
    "sg:postcode":"41006",
    "sg:province":"Sevilla",
    "sg:website":"www.crisarte.es",
    "wof:name":"Crisarte S.l.",
    "wof:placetype":"venue"
},
  "geometry": {"coordinates":[-5.9551339149,37.3692436218],"type":"Point"}
}