{
  "type": "Feature",
  "properties": {
    "addr:full":"Carr Diputacio, 1 Mollerussa Lleida 25230",
    "addr:housenumber":"1",
    "addr:postcode":"25230",
    "addr:street":"Carr Diputacio",
    "iso:country":"ES",
    "sg:address":"Carr Diputacio, 1",
    "sg:city":"Mollerussa",
    "sg:orig_category":"Asilos De Ancianos. Centros Privados",
    "sg:phone":"+34 973 71 14 98",
    "sg:postcode":"25230",
    "sg:province":"Lleida",
    "wof:name":"Torrent Puig Josep",
    "wof:placetype":"venue"
},
  "geometry": {"coordinates":[0.8953850269,41.6325645447],"type":"Point"}
}