{
  "type": "Feature",
  "properties": {
    "iso:country":"ES",
    "sg:address":"Carrer de Bruguera, 96",
    "sg:city":"Calella",
    "sg:orig_category":"Institutos De Belleza",
    "sg:phone":"+34 937 66 15 43",
    "sg:postcode":"08370",
    "sg:province":"Barcelona",
    "wof:name":"Muntet Oliva Rosa Maria",
    "wof:placetype":"venue"
},
  "geometry": {"coordinates":[2.6616868973,41.6151008606],"type":"Point"}
}