{
  "type": "Feature",
  "properties": {
    "addr:full":"Calle de Eras, 18 Salamanca Salamanca 37005",
    "addr:housenumber":"18",
    "addr:postcode":"37005",
    "addr:street":"Calle De Eras",
    "iso:country":"ES",
    "sg:address":"Calle de Eras, 18",
    "sg:city":"Salamanca",
    "sg:orig_category":"M\u00c9dicos: Medicina Interna",
    "sg:phone":"+34 923 24 39 69",
    "sg:postcode":"37005",
    "sg:province":"Salamanca",
    "wof:name":"Sanchez Rodilla Tomas Jesus",
    "wof:placetype":"venue"
},
  "geometry": {"coordinates":[-5.6605739594,40.9699287415],"type":"Point"}
}