{
  "type": "Feature",
  "properties": {
    "addr:full":"Plaz Ribadeo, 8 Madrid Madrid 28029",
    "addr:housenumber":"8",
    "addr:postcode":"madrid;28029",
    "iso:country":"ES",
    "sg:address":"Plaz Ribadeo, 8",
    "sg:city":"Madrid",
    "sg:orig_category":"Servicio De Salud",
    "sg:phone":"+34 917 30 14 80",
    "sg:postcode":"28029",
    "sg:province":"Madrid",
    "wof:name":"Nieto Gonzalez Rafael",
    "wof:placetype":"venue"
},
  "geometry": {"coordinates":[-3.7104849815,40.4772987366],"type":"Point"}
}