{
  "type": "Feature",
  "properties": {
    "addr:full":"Av Gola D'estany, 53 Santa Margarida-salatar Girona 17480",
    "addr:housenumber":"53",
    "addr:postcode":"17480",
    "addr:street":"Av Gola D'Estany",
    "iso:country":"ES",
    "sg:address":"Av Gola D'estany, 53",
    "sg:city":"Santa Margarida-salatar",
    "sg:orig_category":"Inmobiliaria (agencias)",
    "sg:phone":"+34 972 25 68 79",
    "sg:postcode":"17480",
    "sg:province":"Girona",
    "wof:name":"Sacrim S.l.",
    "wof:placetype":"venue"
},
  "geometry": {"coordinates":[3.1536560059,42.2635116577],"type":"Point"}
}