{
  "type": "Feature",
  "properties": {
    "addr:full":"Rua Malecon De Cadarso, S/n Noia La Coru\u00f1a 15200",
    "addr:housenumber":"s / n",
    "addr:postcode":"15200",
    "addr:street":"Rua Malecon De Cadarso;La Corun\u0303A",
    "iso:country":"ES",
    "sg:address":"Rua Malecon De Cadarso, S/n",
    "sg:city":"Noia",
    "sg:orig_category":"Veh\u00cdculos De Ocasi\u00d3n",
    "sg:phone":"+34 981 82 08 08",
    "sg:postcode":"15200",
    "sg:province":"La Coru\u00f1a",
    "sg:website":"www.automovilespatino.com",
    "wof:name":"Pati\u00d1o Ocasion S.l.",
    "wof:placetype":"venue"
},
  "geometry": {"coordinates":[-8.8891181946,42.7813110352],"type":"Point"}
}