{
  "type": "Feature",
  "properties": {
    "addr:full":"Pque San Adrian, 7 Logro\u00f1o La Rioja 26006",
    "addr:housenumber":"7",
    "addr:postcode":"26006",
    "addr:street":"Adrian;Rioja",
    "iso:country":"ES",
    "sg:address":"Pque San Adrian, 7",
    "sg:city":"Logro\u00f1o",
    "sg:orig_category":"Asesor\u00cda Fiscal Y Jur\u00cddica",
    "sg:phone":"+34 941 20 42 38",
    "sg:postcode":"26006",
    "sg:province":"La Rioja",
    "wof:name":"Asesoria De Empresas Pintado & Jimenez S.l.",
    "wof:placetype":"venue"
},
  "geometry": {"coordinates":[-2.3912363052,42.4574165344],"type":"Point"}
}