{
  "type": "Feature",
  "properties": {
    "iso:country":"ES",
    "sg:address":"Calle de Pico Del Aguila (del), 36",
    "sg:city":"Humanes De Madrid",
    "sg:orig_category":"Empresas De Carpinter\u00cda De Madera",
    "sg:phone":"+34 916 04 92 86",
    "sg:postcode":"28970",
    "sg:province":"Madrid",
    "wof:name":"Gordillo Salido Jose Luis",
    "wof:placetype":"venue"
},
  "geometry": {"coordinates":[-3.8127689362,40.2606163025],"type":"Point"}
}