{
  "type": "Feature",
  "properties": {
    "iso:country":"ES",
    "sg:address":"Avgd Ausias March, 44",
    "sg:city":"Alcudia",
    "sg:orig_category":"Institutos De Belleza",
    "sg:phone":"+34 962 99 76 31",
    "sg:postcode":"46250",
    "sg:province":"Valencia",
    "wof:name":"Arnandis Duran Nuria",
    "wof:placetype":"venue"
},
  "geometry": {"coordinates":[-0.5081449151,39.1917762756],"type":"Point"}
}