{
  "type": "Feature",
  "properties": {
    "addr:full":"Calle de Pedro Iii El Grande, 11 Valencia Valencia 46005",
    "addr:housenumber":"11",
    "addr:postcode":"46005",
    "addr:street":"Calle De Pedro Iii El Grande",
    "iso:country":"ES",
    "sg:address":"Calle de Pedro Iii El Grande, 11",
    "sg:city":"Valencia",
    "sg:orig_category":"Centros Empresariales",
    "sg:phone":"+34 963 95 64 69",
    "sg:postcode":"46005",
    "sg:province":"Valencia",
    "wof:name":"Federacion De Sociedades Anonimas Laborales Del Pais Valenciano",
    "wof:placetype":"venue"
},
  "geometry": {"coordinates":[-0.3696439862,39.4624519348],"type":"Point"}
}