{
  "type": "Feature",
  "properties": {
    "addr:full":"Avda Pontevedra (de), Km. 0030,0 Carballi\u00f1o Ourense 32500",
    "addr:postcode":"32500",
    "addr:street":"Avda Pontevedra De Km. 0030,0",
    "iso:country":"ES",
    "sg:address":"Avda Pontevedra (de), Km. 0030,0",
    "sg:city":"Carballi\u00f1o",
    "sg:orig_category":"Hoteles",
    "sg:phone":"+34 988 27 32 26",
    "sg:postcode":"32500",
    "sg:province":"Ourense",
    "wof:name":"Grupo Atlantida S.a.",
    "wof:placetype":"venue"
},
  "geometry": {"coordinates":[-8.0836315155,42.4351921082],"type":"Point"}
}