{
  "type": "Feature",
  "properties": {
    "iso:country":"ES",
    "sg:address":"Calle de Don Ramon De La Cruz, 74",
    "sg:city":"Madrid",
    "sg:orig_category":"Administradores De Bienes Y Delegados De Comunidades De Propietarios",
    "sg:phone":"+34 914 02 10 64",
    "sg:postcode":"28006",
    "sg:province":"Madrid",
    "wof:name":"Inversiones Fincadem Sl",
    "wof:placetype":"venue"
},
  "geometry": {"coordinates":[-3.6748261452,40.4286689758],"type":"Point"}
}