{
  "type": "Feature",
  "properties": {
    "addr:full":"Avda Juan Carlos I, S/n Cristianos Santa Cruz De Tenerife 38650",
    "addr:housenumber":"s / n",
    "addr:postcode":"38650",
    "addr:street":"Avda Juan Carlos I",
    "iso:country":"ES",
    "sg:address":"Avda Juan Carlos I, S/n",
    "sg:city":"Cristianos",
    "sg:orig_category":"Centros De Coordinaci\u00d3n",
    "sg:phone":"+34 922 79 07 12",
    "sg:postcode":"38650",
    "sg:province":"Santa Cruz De Tenerife",
    "wof:name":"Angi  Nicolette",
    "wof:placetype":"venue"
},
  "geometry": {"coordinates":[-16.7124347687,28.0535564423],"type":"Point"}
}