{
  "type": "Feature",
  "properties": {
    "addr:full":"Pase Prado De La Magdalena, 16 Valladolid Valladolid 47005",
    "addr:housenumber":"16",
    "addr:postcode":"47005",
    "addr:street":"Magdalena",
    "iso:country":"ES",
    "sg:address":"Pase Prado De La Magdalena, 16",
    "sg:city":"Valladolid",
    "sg:orig_category":"Electricidad: Instalaciones Industriales",
    "sg:phone":"+34 983 39 99 92",
    "sg:postcode":"47005",
    "sg:province":"Valladolid",
    "wof:name":"Haro Martinez Jose Felix De",
    "wof:placetype":"venue"
},
  "geometry": {"coordinates":[-4.7139577866,41.6556968689],"type":"Point"}
}