{
  "type": "Feature",
  "properties": {
    "addr:full":"Plaz Carlos Pinilla, 4 Muga Sayago Zamora 49212",
    "addr:housenumber":"4",
    "addr:postcode":"49212",
    "addr:street":"Pinilla;Sayago",
    "iso:country":"ES",
    "sg:address":"Plaz Carlos Pinilla, 4",
    "sg:city":"Muga Sayago",
    "sg:orig_category":"Empresas De Desmonte",
    "sg:phone":"+34 980 61 75 62",
    "sg:postcode":"49212",
    "sg:province":"Zamora",
    "wof:name":"Trufero Barrios Jose Miguel",
    "wof:placetype":"venue"
},
  "geometry": {"coordinates":[-6.1981720924,41.3875541687],"type":"Point"}
}