{
  "type": "Feature",
  "properties": {
    "iso:country":"ES",
    "sg:address":"Urb Teuleria, S/n",
    "sg:city":"Polop",
    "sg:orig_category":"Hormig\u00d3n (m\u00c1quinas E Instalaci\u00d3n)",
    "sg:phone":"+34 965 87 05 21",
    "sg:postcode":"03520",
    "sg:province":"Alicante",
    "wof:name":"Holcim Hormigones",
    "wof:placetype":"venue"
},
  "geometry": {"coordinates":[-0.1353240013,38.6092758179],"type":"Point"}
}