{
  "type": "Feature",
  "properties": {
    "addr:full":"Calle de Ancha, 79 Punta Umbria Huelva 21100",
    "addr:housenumber":"79",
    "addr:postcode":"21100",
    "addr:street":"Calle De Ancha",
    "iso:country":"ES",
    "sg:address":"Calle de Ancha, 79",
    "sg:city":"Punta Umbria",
    "sg:orig_category":"Regalos, Souvenires (fabricaci\u00d3n, Al Por Mayor)",
    "sg:phone":"+34 959 31 06 80",
    "sg:postcode":"21100",
    "sg:province":"Huelva",
    "wof:name":"Gonzalez Ferrera Valentina",
    "wof:placetype":"venue"
},
  "geometry": {"coordinates":[-6.9610142708,37.1819076538],"type":"Point"}
}