{
  "type": "Feature",
  "properties": {
    "addr:full":"Calle de Venus, 13 Puebla Montalban Toledo 45516",
    "addr:housenumber":"13",
    "addr:postcode":"45516",
    "addr:street":"Calle De Venus",
    "iso:country":"ES",
    "sg:address":"Calle de Venus, 13",
    "sg:city":"Puebla Montalban",
    "sg:orig_category":"Promotores Constructores",
    "sg:phone":"+34 925 75 12 90",
    "sg:postcode":"45516",
    "sg:province":"Toledo",
    "wof:name":"Construcciones Y Yesos Puebla S.l.",
    "wof:placetype":"venue"
},
  "geometry": {"coordinates":[-4.3537387848,39.8666114807],"type":"Point"}
}