{
  "type": "Feature",
  "properties": {
    "iso:country":"ES",
    "sg:address":"Sa Torre, 49",
    "sg:city":"Montu\u00efri",
    "sg:orig_category":"Charcuter\u00cdas (al Por Mayor)",
    "sg:phone":"+34 971 64 60 70",
    "sg:postcode":"07230",
    "sg:province":"Islas Baleares",
    "sg:website":"www.embotitsmontuiri.com",
    "wof:name":"Embotits Montuiri S.a.",
    "wof:placetype":"venue"
},
  "geometry": {"coordinates":[2.9737401009,39.5984916687],"type":"Point"}
}