{
  "type": "Feature",
  "properties": {
    "iso:country":"ES",
    "sg:address":"Calle de Cardenal Cisneros, 37",
    "sg:city":"Madrid",
    "sg:orig_category":"Agencias Y Asesores De Publicidad",
    "sg:phone":"+34 914 46 21 91",
    "sg:postcode":"28010",
    "sg:province":"Madrid",
    "wof:name":"Duran Lopez Maria Luisa",
    "wof:placetype":"venue"
},
  "geometry": {"coordinates":[-3.7021362782,40.4317092896],"type":"Point"}
}