{
  "type": "Feature",
  "properties": {
    "addr:full":"Calle de Alberto Palacios, 14 Madrid Madrid 28021",
    "addr:housenumber":"14",
    "addr:postcode":"madrid;28021",
    "addr:street":"Calle De Alberto Palacios",
    "iso:country":"ES",
    "sg:address":"Calle de Alberto Palacios, 14",
    "sg:city":"Madrid",
    "sg:orig_category":"Ropa Para Se\u00d1oras Y Caballeros (al Por Menor)",
    "sg:phone":"+34 917 10 02 72",
    "sg:postcode":"28021",
    "sg:province":"Madrid",
    "wof:name":"Rainbow Express S.l.",
    "wof:placetype":"venue"
},
  "geometry": {"coordinates":[-3.7125344276,40.343624115],"type":"Point"}
}