{
  "type": "Feature",
  "properties": {
    "addr:full":"Calle de Choconta, 2 Madrid Madrid 28033",
    "addr:housenumber":"2",
    "addr:postcode":"28033",
    "addr:street":"Calle De Choconta",
    "iso:country":"ES",
    "sg:address":"Calle de Choconta, 2",
    "sg:city":"Madrid",
    "sg:orig_category":"Transportes Por V\u00cdas Navegables",
    "sg:phone":"+34 917 64 61 48",
    "sg:postcode":"28033",
    "sg:province":"Madrid",
    "wof:name":"Transportes Telesforo Gonzalez S.l.",
    "wof:placetype":"venue"
},
  "geometry": {"coordinates":[-3.6321439743,40.470249176],"type":"Point"}
}