{
  "type": "Feature",
  "properties": {
    "addr:full":"Calle de Conde Garay, 17 Salda\u00f1a Palencia 34100",
    "addr:housenumber":"17",
    "addr:postcode":"34100",
    "addr:street":"Calle De Conde Garay",
    "iso:country":"ES",
    "sg:address":"Calle de Conde Garay, 17",
    "sg:city":"Salda\u00f1a",
    "sg:classifiers":[
        {
            "category":"Autos & Motor Vehicles",
            "subcategory":"Automobile Sales",
            "type":"Retail Goods"
        }
    ],
    "sg:phone":"+34 979 89 11 70",
    "sg:postcode":"34100",
    "sg:province":"Palencia",
    "wof:name":"Autoescuela Noelia S.l.",
    "wof:placetype":"venue"
},
  "geometry": {"coordinates":[-4.7366013527,42.5202140808],"type":"Point"}
}