{
  "type": "Feature",
  "properties": {
    "iso:country":"ES",
    "sg:address":"Avda Isabel La Catolica, 9",
    "sg:city":"Albacete",
    "sg:orig_category":"Parafarmacias",
    "sg:phone":"+34 967 21 39 63",
    "sg:postcode":"02005",
    "sg:province":"Albacete",
    "wof:name":"Gonzalez Lopez Raquel",
    "wof:placetype":"venue"
},
  "geometry": {"coordinates":[-1.8588989973,38.9983787537],"type":"Point"}
}