{
  "type": "Feature",
  "properties": {
    "addr:full":"Carrer de Padro, 31 Casc Antic Barcelona 08690",
    "addr:housenumber":"31",
    "addr:postcode":"08690",
    "addr:street":"Carrer De Padro",
    "iso:country":"ES",
    "sg:address":"Carrer de Padro, 31",
    "sg:city":"Casc Antic",
    "sg:orig_category":"Bancos",
    "sg:phone":"+34 936 34 00 55",
    "sg:postcode":"08690",
    "sg:province":"Barcelona",
    "wof:name":"Banc Sabadell S.a.",
    "wof:placetype":"venue"
},
  "geometry": {"coordinates":[2.0219130516,41.3697509766],"type":"Point"}
}