{
  "type": "Feature",
  "properties": {
    "addr:full":"Ubitxa Kalea, 3 Eibar Guip\u00f9zcoa 20600",
    "addr:housenumber":"3",
    "addr:postcode":"20600",
    "addr:street":"Ubitxa Kalea;Guipu\u0300Zcoa",
    "iso:country":"ES",
    "sg:address":"Ubitxa Kalea, 3",
    "sg:city":"Eibar",
    "sg:orig_category":"Masajistas Kinesiterapeutas",
    "sg:phone":"+34 943 82 03 64",
    "sg:postcode":"20600",
    "sg:province":"Guip\u00f9zcoa",
    "wof:name":"Jon Telleria Elgezabal",
    "wof:placetype":"venue"
},
  "geometry": {"coordinates":[-2.4717719555,43.181438446],"type":"Point"}
}