{
  "type": "Feature",
  "properties": {
    "iso:country":"ES",
    "sg:address":"Avda Club Deportivo, 46",
    "sg:city":"Logro\u00f1o",
    "sg:orig_category":"Cl\u00cdnicas Dentales",
    "sg:phone":"+34 941 21 35 98",
    "sg:postcode":"26007",
    "sg:province":"La Rioja",
    "wof:name":"Clinica Dental L & M",
    "wof:placetype":"venue"
},
  "geometry": {"coordinates":[-2.4560830593,42.4573287964],"type":"Point"}
}