{
  "type": "Feature",
  "properties": {
    "addr:full":"Par. Mas Cisa, 15 Sentmenat Barcelona 08181",
    "addr:housenumber":"15",
    "addr:postcode":"08181",
    "iso:country":"ES",
    "sg:address":"Par. Mas Cisa, 15",
    "sg:city":"Sentmenat",
    "sg:orig_category":"M\u00c1rmoles, Granitos Y Piedras Naturales",
    "sg:phone":"+34 937 15 20 20",
    "sg:postcode":"08181",
    "sg:province":"Barcelona",
    "wof:name":"Bullon Gomez Justo",
    "wof:placetype":"venue"
},
  "geometry": {"coordinates":[2.1349349022,41.6101417542],"type":"Point"}
}