{
  "type": "Feature",
  "properties": {
    "iso:country":"ES",
    "sg:address":"Calle de Libra, 4",
    "sg:city":"Madrid",
    "sg:orig_category":"Abogados",
    "sg:phone":"+34 913 07 11 42",
    "sg:postcode":"28023",
    "sg:province":"Madrid",
    "wof:name":"Cobarrubias Maura Juliana",
    "wof:placetype":"venue"
},
  "geometry": {"coordinates":[-3.7755229473,40.4579238892],"type":"Point"}
}