{
  "type": "Feature",
  "properties": {
    "iso:country":"ES",
    "sg:address":"Calle de Cercadillo, 6",
    "sg:city":"Navarredonda",
    "sg:orig_category":"Estudios Y Construcci\u00d3n De Acuarios Y Viveros",
    "sg:phone":"+34 918 99 02 47",
    "sg:postcode":"28210",
    "sg:province":"Madrid",
    "sg:website":"www.biodecora.com",
    "wof:name":"Posidonia S.l.",
    "wof:placetype":"venue"
},
  "geometry": {"coordinates":[-3.7260465622,40.9907798767],"type":"Point"}
}