{
  "type": "Feature",
  "properties": {
    "iso:country":"ES",
    "sg:address":"Calle de Francisco Altimiras, 14",
    "sg:city":"Madrid",
    "sg:orig_category":"Alimentaci\u00d3n Animal (fabricaci\u00d3n, Al Por Mayor)",
    "sg:phone":"+34 917 26 77 44",
    "sg:postcode":"28028",
    "sg:province":"Madrid",
    "sg:website":"www.agrotecnica2000.es",
    "wof:name":"Tecnica Agropecuaria C.d.",
    "wof:placetype":"venue"
},
  "geometry": {"coordinates":[-3.6636650562,40.4344329834],"type":"Point"}
}