{
  "type": "Feature",
  "properties": {
    "iso:country":"ES",
    "sg:address":"Calle de Marroquina, 84",
    "sg:city":"Madrid",
    "sg:orig_category":"Carnicer\u00cdas, Carnicer\u00cdas",
    "sg:phone":"+34 913 28 30 62",
    "sg:postcode":"28030",
    "sg:province":"Madrid",
    "wof:name":"Menendez Lopez Joaquin",
    "wof:placetype":"venue"
},
  "geometry": {"coordinates":[-3.6458339691,40.4099311829],"type":"Point"}
}