{
  "type": "Feature",
  "properties": {
    "addr:full":"Calle de Peligros, 25 Alora M\u00e1laga 29500",
    "addr:housenumber":"25",
    "addr:postcode":"29500",
    "addr:street":"Calle De Peligros;Ma\u0301Laga",
    "iso:country":"ES",
    "sg:address":"Calle de Peligros, 25",
    "sg:city":"Alora",
    "sg:orig_category":"Carnicer\u00cdas, Carnicer\u00cdas",
    "sg:phone":"+34 952 49 76 38",
    "sg:postcode":"29500",
    "sg:province":"M\u00e1laga",
    "wof:name":"Gutierrez Lopez Gloria",
    "wof:placetype":"venue"
},
  "geometry": {"coordinates":[-4.7064151764,36.8250732422],"type":"Point"}
}