{
  "type": "Feature",
  "properties": {
    "addr:full":"Pol Ind De Palmones, 2 Palmones C\u00e1diz 11379",
    "addr:housenumber":"2",
    "addr:postcode":"11379",
    "addr:street":"Ind;Ca\u0301Diz",
    "iso:country":"ES",
    "sg:address":"Pol Ind De Palmones, 2",
    "sg:city":"Palmones",
    "sg:orig_category":"Ropa Para Se\u00d1oras Y Caballeros (al Por Menor)",
    "sg:phone":"+34 956 67 74 32",
    "sg:postcode":"11379",
    "sg:province":"C\u00e1diz",
    "sg:website":"www.adolfo-dominguez.com",
    "wof:name":"Adolfo Dominguez S.a.",
    "wof:placetype":"venue"
},
  "geometry": {"coordinates":[-5.4332337379,36.1807327271],"type":"Point"}
}