{
  "type": "Feature",
  "properties": {
    "iso:country":"ES",
    "sg:address":"Avda Constitucion, 44",
    "sg:city":"Senija",
    "sg:orig_category":"Madera (al Por Menor)",
    "sg:phone":"+34 965 73 24 66",
    "sg:postcode":"03729",
    "sg:province":"Alicante",
    "wof:name":"Lozano Ballesteros Antonio",
    "wof:placetype":"venue"
},
  "geometry": {"coordinates":[0.0399109013,38.727180481],"type":"Point"}
}