{
  "type": "Feature",
  "properties": {
    "addr:full":"Calle de Larramendi Kalea, 20 Tolosa Guip\u00f9zcoa 20400",
    "addr:housenumber":"20",
    "addr:postcode":"20400",
    "addr:street":"Calle De Larramendi Kalea;Guipu\u0300Zcoa",
    "iso:country":"ES",
    "sg:address":"Calle de Larramendi Kalea, 20",
    "sg:city":"Tolosa",
    "sg:classifiers":[
        {
            "category":"Manufacturing",
            "subcategory":"Metals",
            "type":"Manufacturing & Wholesale Goods"
        }
    ],
    "sg:phone":"+34 943 67 40 17",
    "sg:postcode":"20400",
    "sg:province":"Guip\u00f9zcoa",
    "sg:tags":[
        "en",
        "fundiciones"
    ],
    "wof:name":"Fudike S.a.l.",
    "wof:placetype":"venue"
},
  "geometry": {"coordinates":[-2.0714519024,43.1421127319],"type":"Point"}
}