{
  "type": "Feature",
  "properties": {
    "addr:full":"Carr Font (la) (isona), S/n Isona Lleida 25650",
    "addr:housenumber":"s / n",
    "addr:postcode":"25650",
    "addr:street":"Carr Font La Isona",
    "iso:country":"ES",
    "sg:address":"Carr Font (la) (isona), S/n",
    "sg:city":"Isona",
    "sg:orig_category":"Alimentaci\u00d3n General (al Por Mayor)",
    "sg:phone":"+34 973 66 40 07",
    "sg:postcode":"25650",
    "sg:province":"Lleida",
    "wof:name":"Monso Balust Jose Maria",
    "wof:placetype":"venue"
},
  "geometry": {"coordinates":[1.0446749926,42.1168899536],"type":"Point"}
}