{
  "type": "Feature",
  "properties": {
    "addr:full":"Calle de Sierpe, 3 Madrid Madrid 28005",
    "addr:housenumber":"3",
    "addr:postcode":"28005",
    "addr:street":"Calle De Sierpe",
    "iso:country":"ES",
    "sg:address":"Calle de Sierpe, 3",
    "sg:city":"Madrid",
    "sg:orig_category":"Bisuter\u00cda, Joyer\u00cda, Relojer\u00cda (al Por Menor)",
    "sg:phone":"+34 913 64 09 86",
    "sg:postcode":"28005",
    "sg:province":"Madrid",
    "wof:name":"Scasso  Gustavo Diego",
    "wof:placetype":"venue"
},
  "geometry": {"coordinates":[-3.7099170685,40.4099502563],"type":"Point"}
}