{
  "type": "Feature",
  "properties": {
    "addr:full":"Calle de Matiko, 33 Bilbao Vizcaya 48007",
    "addr:housenumber":"33",
    "addr:postcode":"48007",
    "addr:street":"Calle De Matiko",
    "iso:country":"ES",
    "sg:address":"Calle de Matiko, 33",
    "sg:city":"Bilbao",
    "sg:orig_category":"Deportes Y Ocio: Art\u00cdculos Y Ropas (al Por Menor Y Accesorios)",
    "sg:phone":"+34 944 46 60 08",
    "sg:postcode":"48007",
    "sg:province":"Vizcaya",
    "wof:name":"Matiko Kirolak Sl",
    "wof:placetype":"venue"
},
  "geometry": {"coordinates":[-2.9250864983,43.270450592],"type":"Point"}
}