{
  "type": "Feature",
  "properties": {
    "addr:full":"Calle de Torrijos, 15 Madrid Madrid 28029",
    "addr:housenumber":"15",
    "addr:postcode":"madrid;28029",
    "addr:street":"Calle De Torrijos",
    "iso:country":"ES",
    "sg:address":"Calle de Torrijos, 15",
    "sg:city":"Madrid",
    "sg:orig_category":"Postigos, Persianas Y Celos\u00cdas",
    "sg:phone":"+34 915 71 09 89",
    "sg:postcode":"28029",
    "sg:province":"Madrid",
    "wof:name":"Hijos De Benito Palacios S.l",
    "wof:placetype":"venue"
},
  "geometry": {"coordinates":[-3.6951420307,40.4651184082],"type":"Point"}
}