{
  "type": "Feature",
  "properties": {
    "iso:country":"ES",
    "sg:address":"Jesualdo Ferrero, 4",
    "sg:city":"Banyeres Mariola",
    "sg:orig_category":"Agentes, Concesionarios Y Sucursales De Veh\u00cdculos",
    "sg:phone":"+34 965 56 65 93",
    "sg:postcode":"03450",
    "sg:province":"Alicante",
    "wof:name":"Ba\u00f1eres Motor S.l.",
    "wof:placetype":"venue"
},
  "geometry": {"coordinates":[-0.663022995,38.7122077942],"type":"Point"}
}