{
  "type": "Feature",
  "properties": {
    "iso:country":"ES",
    "sg:address":"Calle de Eleuterio Quintanilla, 63",
    "sg:city":"Gijon",
    "sg:orig_category":"Farmacias",
    "sg:phone":"+34 985 38 43 70",
    "sg:postcode":"33208",
    "sg:province":"Asturias",
    "wof:name":"Suarez Junquera Maria Del Carmen",
    "wof:placetype":"venue"
},
  "geometry": {"coordinates":[-5.662938118,43.5306854248],"type":"Point"}
}