{
  "type": "Feature",
  "properties": {
    "iso:country":"ES",
    "sg:address":"Avda Constitucion, 317",
    "sg:city":"Valencia",
    "sg:orig_category":"M\u00c1rmoles, Granitos Y Piedras Naturales",
    "sg:phone":"+34 961 85 88 44",
    "sg:postcode":"46019",
    "sg:province":"Valencia",
    "wof:name":"Gimenez Lluch Vicente",
    "wof:placetype":"venue"
},
  "geometry": {"coordinates":[-0.3686429858,39.5025749207],"type":"Point"}
}