{
  "type": "Feature",
  "properties": {
    "iso:country":"ES",
    "sg:address":"Plaz Santa Barbara, 1",
    "sg:city":"Vitoria-gasteiz",
    "sg:orig_category":"Farmacias",
    "sg:phone":"+34 945 28 23 42",
    "sg:postcode":"01004",
    "sg:province":"\u00c1lava",
    "wof:name":"Farmacia Elicegui C.b",
    "wof:placetype":"venue"
},
  "geometry": {"coordinates":[-2.6663510799,42.8439865112],"type":"Point"}
}