{
  "type": "Feature",
  "properties": {
    "iso:country":"ES",
    "sg:address":"Calle de Urrestarazu Anaiaren, 6",
    "sg:city":"Pasai S. Pedro",
    "sg:orig_category":"Molduras, Junquillos, Listones Y Molduras Perforadas",
    "sg:phone":"+34 943 39 65 75",
    "sg:postcode":"20110",
    "sg:province":"Guip\u00f9zcoa",
    "wof:name":"Call Phone S. L.",
    "wof:placetype":"venue"
},
  "geometry": {"coordinates":[-1.9282419682,43.3245773315],"type":"Point"}
}