{
  "type": "Feature",
  "properties": {
    "addr:full":"Pl. Iglesia, S/n Santuyano De Bimenes Asturias 33527",
    "addr:housenumber":"s / n",
    "addr:postcode":"33527",
    "addr:street":"Pl. Iglesia",
    "iso:country":"ES",
    "sg:address":"Pl. Iglesia, S/n",
    "sg:city":"Santuyano De Bimenes",
    "sg:orig_category":"Empresarios",
    "sg:phone":"+34 985 70 00 88",
    "sg:postcode":"33527",
    "sg:province":"Asturias",
    "wof:name":"Ordo\u00f1ez Arboleya Jesus",
    "wof:placetype":"venue"
},
  "geometry": {"coordinates":[-5.5663490295,43.3295249939],"type":"Point"}
}