{
  "type": "Feature",
  "properties": {
    "iso:country":"ES",
    "sg:address":"La Campana, 33",
    "sg:city":"Ecija",
    "sg:orig_category":"Fabricaci\u00d3n De Muebles",
    "sg:phone":"+34 955 90 34 02",
    "sg:postcode":"41400",
    "sg:province":"Sevilla",
    "wof:name":"Blazquez Perez Miguel Angel",
    "wof:placetype":"venue"
},
  "geometry": {"coordinates":[-5.0792541504,37.5312385559],"type":"Point"}
}