{
  "type": "Feature",
  "properties": {
    "addr:full":"Calle de Baleares, 19 Conil De La Frontera C\u00e1diz 11140",
    "addr:housenumber":"19",
    "addr:postcode":"11140",
    "addr:street":"Calle De Baleares",
    "iso:country":"ES",
    "sg:address":"Calle de Baleares, 19",
    "sg:city":"Conil De La Frontera",
    "sg:orig_category":"T\u00c9cnicos Veterinarios",
    "sg:phone":"+34 956 44 31 96",
    "sg:postcode":"11140",
    "sg:province":"C\u00e1diz",
    "sg:website":"www.vetomo.com",
    "wof:name":"Carlos Romero Mora-figueroa S.l.",
    "wof:placetype":"venue"
},
  "geometry": {"coordinates":[-6.0847921371,36.2803421021],"type":"Point"}
}