{
  "type": "Feature",
  "properties": {
    "iso:country":"ES",
    "sg:address":"Parque Tomas Caballero, 2",
    "sg:city":"Iru\u00f1a",
    "sg:orig_category":"Asistencia Social",
    "sg:phone":"+34 948 15 37 98",
    "sg:postcode":"31005",
    "sg:province":"Navarra",
    "sg:website":"www.amma.es",
    "wof:name":"Amma Gerogestion S.l",
    "wof:placetype":"venue"
},
  "geometry": {"coordinates":[-1.6408561468,42.8069763184],"type":"Point"}
}