{
  "type": "Feature",
  "properties": {
    "addr:full":"C/ Nord, 49 Tarrega Lleida 25300",
    "addr:housenumber":"49",
    "addr:postcode":"25300",
    "addr:street":"C / Nord",
    "iso:country":"ES",
    "sg:address":"C/ Nord, 49",
    "sg:city":"Tarrega",
    "sg:orig_category":"Zapatos (al Por Mayor)",
    "sg:phone":"+34 973 50 04 90",
    "sg:postcode":"25300",
    "sg:province":"Lleida",
    "wof:name":"Badias Morros Jose Maria",
    "wof:placetype":"venue"
},
  "geometry": {"coordinates":[1.1445360184,41.6517333984],"type":"Point"}
}