{
  "type": "Feature",
  "properties": {
    "iso:country":"ES",
    "sg:address":"Calle de Calvo Sotelo, 40",
    "sg:city":"Santa Brigida",
    "sg:orig_category":"Doctores En Medicina",
    "sg:phone":"+34 928 64 83 15",
    "sg:postcode":"35300",
    "sg:province":"Las Palmas",
    "wof:name":"Alonso Bordon Ildefonsa",
    "wof:placetype":"venue"
},
  "geometry": {"coordinates":[-15.4989690781,28.032497406],"type":"Point"}
}