{
  "type": "Feature",
  "properties": {
    "iso:country":"ES",
    "sg:address":"Calle de Barranco, 12",
    "sg:city":"Graus",
    "sg:orig_category":"Inmobiliaria (agencias)",
    "sg:phone":"+34 974 54 04 18",
    "sg:postcode":"22430",
    "sg:province":"Huesca",
    "wof:name":"Fincas Ribagorza S.cv.",
    "wof:placetype":"venue"
},
  "geometry": {"coordinates":[0.3371061087,42.1901664734],"type":"Point"}
}