{
  "type": "Feature",
  "properties": {
    "iso:country":"ES",
    "sg:address":"Carrer de Reverter, 10",
    "sg:city":"Hospitalet Llobregat",
    "sg:orig_category":"Barnizadores",
    "sg:phone":"+34 934 47 01 15",
    "sg:postcode":"08903",
    "sg:province":"Barcelona",
    "wof:name":"Leia S.a.",
    "wof:placetype":"venue"
},
  "geometry": {"coordinates":[2.1225440502,41.3729324341],"type":"Point"}
}