{
  "type": "Feature",
  "properties": {
    "addr:full":"Calle de Artaleku, S/n Irun Guip\u00f9zcoa 20303",
    "addr:housenumber":"s / n",
    "addr:postcode":"20303",
    "addr:street":"Calle De Artaleku;Guipu\u0300Zcoa",
    "iso:country":"ES",
    "sg:address":"Calle de Artaleku, S/n",
    "sg:city":"Irun",
    "sg:orig_category":"Asociaciones Y Clubs Deportivos",
    "sg:phone":"+34 943 62 52 85",
    "sg:postcode":"20303",
    "sg:province":"Guip\u00f9zcoa",
    "wof:name":"Club Deportivo Bidasoa",
    "wof:placetype":"venue"
},
  "geometry": {"coordinates":[-1.7942796946,43.3379745483],"type":"Point"}
}