{
  "type": "Feature",
  "properties": {
    "iso:country":"ES",
    "sg:address":"Avda Ruzafa, 23",
    "sg:city":"Benidorm",
    "sg:orig_category":"Caf\u00c9s, Bares, Cervecer\u00cdas",
    "sg:phone":"+34 965 86 63 53",
    "sg:postcode":"03500",
    "sg:province":"Alicante",
    "wof:name":"Franquicias Tierra Del Cafe, S.l.",
    "wof:placetype":"venue"
},
  "geometry": {"coordinates":[-0.1743289977,38.5408058167],"type":"Point"}
}