{
  "type": "Feature",
  "properties": {
    "iso:country":"ES",
    "sg:address":"Avda El Ferial, 99",
    "sg:city":"Benavente",
    "sg:orig_category":"Supermercados Y Hipermercados",
    "sg:phone":"+34 980 63 30 43",
    "sg:postcode":"49600",
    "sg:province":"Zamora",
    "sg:website":"www.mercadona.es",
    "wof:name":"Mercadona S.a.",
    "wof:placetype":"venue"
},
  "geometry": {"coordinates":[-5.6772432327,41.9970588684],"type":"Point"}
}