{
  "type": "Feature",
  "properties": {
    "addr:full":"Mcdo T. Linea, S/n Sevilla Sevilla 41013",
    "addr:housenumber":"s / n",
    "addr:postcode":"41013",
    "addr:street":"Mcdo T. Linea",
    "iso:country":"ES",
    "sg:address":"Mcdo T. Linea, S/n",
    "sg:city":"Sevilla",
    "sg:orig_category":"Poller\u00cda Y Caza (al Por Menor)",
    "sg:phone":"+34 954 61 76 46",
    "sg:postcode":"41013",
    "sg:province":"Sevilla",
    "wof:name":"Algaba Lerida Maria De Los Angeles",
    "wof:placetype":"venue"
},
  "geometry": {"coordinates":[-5.9753265381,37.3628082275],"type":"Point"}
}