{
  "type": "Feature",
  "properties": {
    "addr:full":"Calle de Mazagon, 14 Huelva Huelva 21007",
    "addr:housenumber":"14",
    "addr:postcode":"21007",
    "addr:street":"Calle De Mazagon",
    "iso:country":"ES",
    "sg:address":"Calle de Mazagon, 14",
    "sg:city":"Huelva",
    "sg:orig_category":"Delegados, Agentes De Tr\u00c1nsito, Auxiliares De Transporte Internacional",
    "sg:phone":"+34 959 27 16 70",
    "sg:postcode":"21007",
    "sg:province":"Huelva",
    "wof:name":"Gonzalez Lopez Manuela",
    "wof:placetype":"venue"
},
  "geometry": {"coordinates":[-6.9339752197,37.2552375793],"type":"Point"}
}