{
  "type": "Feature",
  "properties": {
    "addr:full":"Calle de Andalucia, 258 Palencia Palencia 34004",
    "addr:housenumber":"258",
    "addr:postcode":"34004",
    "addr:street":"Calle De Andalucia",
    "iso:country":"ES",
    "sg:address":"Calle de Andalucia, 258",
    "sg:city":"Palencia",
    "sg:orig_category":"Autob\u00das (explotaci\u00d3n Y Servicios De)",
    "sg:phone":"+34 979 71 03 22",
    "sg:postcode":"34004",
    "sg:province":"Palencia",
    "wof:name":"Jose De Mier Alvarez S.l.",
    "wof:placetype":"venue"
},
  "geometry": {"coordinates":[-4.5117969513,41.9997940063],"type":"Point"}
}