{
  "type": "Feature",
  "properties": {
    "addr:full":"Carrer de Botanica, 73 Hospitalet Llobregat Barcelona 08908",
    "addr:housenumber":"73",
    "addr:postcode":"08908",
    "addr:street":"Carrer De Botanica",
    "iso:country":"ES",
    "sg:address":"Carrer de Botanica, 73",
    "sg:city":"Hospitalet Llobregat",
    "sg:orig_category":"Publicidad (soportes Y Gesti\u00d3n)",
    "sg:phone":"+34 932 63 05 00",
    "sg:postcode":"08908",
    "sg:province":"Barcelona",
    "sg:website":"www.sundisa.es",
    "wof:name":"Sundis S. A.",
    "wof:placetype":"venue"
},
  "geometry": {"coordinates":[2.1282999516,41.3502655029],"type":"Point"}
}