{
  "type": "Feature",
  "properties": {
    "iso:country":"ES",
    "sg:address":"Calle de Nicolas De Las Pe\u00d1as, S/n",
    "sg:city":"Beniel",
    "sg:orig_category":"Reposter\u00cdas",
    "sg:phone":"+34 968 60 12 34",
    "sg:postcode":"30130",
    "sg:province":"Murcia",
    "sg:website":"www.lacolegiala.es",
    "wof:name":"Ba\u00f1os Garre S.l.",
    "wof:placetype":"venue"
},
  "geometry": {"coordinates":[-1.0028990507,38.0466690063],"type":"Point"}
}