{
  "type": "Feature",
  "properties": {
    "addr:full":"Calle de Alvarez Quintero, 19 Sevilla Sevilla 41004",
    "addr:housenumber":"19",
    "addr:postcode":"41004",
    "addr:street":"Calle De Alvarez Quintero",
    "iso:country":"ES",
    "sg:address":"Calle de Alvarez Quintero, 19",
    "sg:city":"Sevilla",
    "sg:orig_category":"Grafistas",
    "sg:phone":"+34 954 21 30 00",
    "sg:postcode":"41004",
    "sg:province":"Sevilla",
    "sg:website":"www.grupoget.com",
    "wof:name":"Tecnomedia Center S.l.",
    "wof:placetype":"venue"
},
  "geometry": {"coordinates":[-5.993200779,37.3889045715],"type":"Point"}
}