{
  "type": "Feature",
  "properties": {
    "addr:full":"Av Catalunya, 25 Sant Joan De Palamos Girona 17230",
    "addr:housenumber":"25",
    "addr:postcode":"17230",
    "addr:street":"Av Catalunya",
    "iso:country":"ES",
    "sg:address":"Av Catalunya, 25",
    "sg:city":"Sant Joan De Palamos",
    "sg:orig_category":"Alquiler De V\u00cddeo",
    "sg:phone":"+34 972 31 88 90",
    "sg:postcode":"17230",
    "sg:province":"Girona",
    "wof:name":"Frigola Vila Lluis",
    "wof:placetype":"venue"
},
  "geometry": {"coordinates":[3.1273210049,41.8513717651],"type":"Point"}
}