{
  "type": "Feature",
  "properties": {
    "addr:full":"Carr Balmes, 39 Badalona Barcelona 08918",
    "addr:housenumber":"39",
    "addr:postcode":"08918",
    "addr:street":"Carr Balmes",
    "iso:country":"ES",
    "sg:address":"Carr Balmes, 39",
    "sg:city":"Badalona",
    "sg:orig_category":"Artes Gr\u00c1ficas, Artes Pl\u00c1sticas (curso)",
    "sg:phone":"+34 933 99 39 40",
    "sg:postcode":"08918",
    "sg:province":"Barcelona",
    "wof:name":"Delfer Arts Grafiques S.l.",
    "wof:placetype":"venue"
},
  "geometry": {"coordinates":[2.2208731174,41.4338226318],"type":"Point"}
}