{
  "type": "Feature",
  "properties": {
    "iso:country":"ES",
    "sg:address":"Ctra Zorrilla, 13",
    "sg:city":"Valencia",
    "sg:classifiers":[
        {
            "category":"Taxi",
            "type":"Transportation"
        }
    ],
    "sg:phone":"+34 963 33 40 35",
    "sg:postcode":"46013",
    "sg:province":"Valencia",
    "wof:name":"Vidal Salcedo Vicente",
    "wof:placetype":"venue"
},
  "geometry": {"coordinates":[-0.3662329912,39.4436607361],"type":"Point"}
}