{
  "type": "Feature",
  "properties": {
    "iso:country":"ES",
    "sg:address":"Carr Escoles, S/n",
    "sg:city":"Estartit",
    "sg:orig_category":"Centros De Educaci\u00d3n Especial",
    "sg:phone":"+34 972 75 19 17",
    "sg:postcode":"17258",
    "sg:province":"Girona",
    "wof:name":"Ajuntament De Torroella De Montgri",
    "wof:placetype":"venue"
},
  "geometry": {"coordinates":[3.1991903782,42.0569839478],"type":"Point"}
}