{
  "type": "Feature",
  "properties": {
    "addr:full":"Calle de Virgen De Las Nieves, 36 Chinchilla Monte-aragon Albacete 02520",
    "addr:housenumber":"36",
    "addr:postcode":"02520",
    "addr:street":"Calle De Virgen De Las Nieves;Monte-Aragon",
    "iso:country":"ES",
    "sg:address":"Calle de Virgen De Las Nieves, 36",
    "sg:city":"Chinchilla Monte-aragon",
    "sg:orig_category":"Peluquer\u00cdas, Peluquer\u00cda Mixta",
    "sg:phone":"+34 967 26 10 10",
    "sg:postcode":"02520",
    "sg:province":"Albacete",
    "wof:name":"Sanchez Del Rey Ascension",
    "wof:placetype":"venue"
},
  "geometry": {"coordinates":[-1.7236679792,38.9190406799],"type":"Point"}
}