{
  "type": "Feature",
  "properties": {
    "iso:country":"ES",
    "sg:address":"Calle de Pasaderas, 40",
    "sg:city":"Cala\u00f1as",
    "sg:orig_category":"Venta, Montaje De Neum\u00c1ticos",
    "sg:phone":"+34 959 56 60 02",
    "sg:postcode":"21300",
    "sg:province":"Huelva",
    "wof:name":"Franroq S.l.",
    "wof:placetype":"venue"
},
  "geometry": {"coordinates":[-6.8764190674,37.6532516479],"type":"Point"}
}