{
  "type": "Feature",
  "properties": {
    "iso:country":"ES",
    "sg:address":"Av Isabel La Catolica, 82",
    "sg:city":"Hospitalet Llobregat",
    "sg:orig_category":"Pod\u00d3logos: Pedicuros",
    "sg:phone":"+34 934 37 50 78",
    "sg:postcode":"08905",
    "sg:province":"Barcelona",
    "wof:name":"Vidal Garmendia Mercedes",
    "wof:placetype":"venue"
},
  "geometry": {"coordinates":[2.1040899754,41.3706283569],"type":"Point"}
}