{
  "type": "Feature",
  "properties": {
    "iso:country":"ES",
    "sg:address":"Calle de Ferrer Del Rio, 21",
    "sg:city":"Madrid",
    "sg:orig_category":"Laboratorios Y Cl\u00cdnicas Veterinarias",
    "sg:phone":"+34 917 26 83 47",
    "sg:postcode":"28028",
    "sg:province":"Madrid",
    "wof:name":"Hernanz Alvarez Francisco",
    "wof:placetype":"venue"
},
  "geometry": {"coordinates":[-3.6714236736,40.4349555969],"type":"Point"}
}