{
  "type": "Feature",
  "properties": {
    "iso:country":"ES",
    "sg:address":"Carr Mossen Jacint Verdaguer, 5",
    "sg:city":"Santa Coloma De Farners",
    "sg:orig_category":"Droguer\u00cdas (al Por Menor)",
    "sg:phone":"+34 972 84 13 57",
    "sg:postcode":"17430",
    "sg:province":"Girona",
    "wof:name":"Drogueria Jacint S.l.",
    "wof:placetype":"venue"
},
  "geometry": {"coordinates":[2.6618490219,41.8629646301],"type":"Point"}
}