{
  "type": "Feature",
  "properties": {
    "iso:country":"ES",
    "sg:address":"Pol Ind El Sorbe, S/n",
    "sg:city":"Humanes",
    "sg:orig_category":"Organizaciones Profesionales",
    "sg:phone":"+34 949 85 12 72",
    "sg:postcode":"19220",
    "sg:province":"Guadalajara",
    "wof:name":"Come Sano Cocinados De La Campi\u00d1a S.l.",
    "wof:placetype":"venue"
},
  "geometry": {"coordinates":[-3.1538040638,40.8272285461],"type":"Point"}
}