{
  "type": "Feature",
  "properties": {
    "iso:country":"ES",
    "sg:address":"Carr Verge Del Remei (de La), 32",
    "sg:city":"Albaida",
    "sg:orig_category":"Ropa Y Accesorios",
    "sg:phone":"+34 962 90 16 69",
    "sg:postcode":"46860",
    "sg:province":"Valencia",
    "wof:name":"Tosmo Jover Maria Del Carmen",
    "wof:placetype":"venue"
},
  "geometry": {"coordinates":[-0.5180540085,38.8377876282],"type":"Point"}
}