{
  "type": "Feature",
  "properties": {
    "iso:country":"ES",
    "sg:address":"Calle de San Miguel, 7",
    "sg:city":"Amorebieta",
    "sg:orig_category":"Alimentaci\u00d3n General (al Por Menor)",
    "sg:phone":"+34 946 73 26 80",
    "sg:postcode":"48340",
    "sg:province":"Vizcaya",
    "wof:name":"Garrote Fernandez Jose Antonio",
    "wof:placetype":"venue"
},
  "geometry": {"coordinates":[-2.7318139076,43.2195091248],"type":"Point"}
}