{
  "type": "Feature",
  "properties": {
    "addr:full":"Calle de San Leopoldo, 19 Madrid Madrid 28029",
    "addr:housenumber":"19",
    "addr:postcode":"madrid;28029",
    "addr:street":"Calle De San Leopoldo",
    "iso:country":"ES",
    "sg:address":"Calle de San Leopoldo, 19",
    "sg:city":"Madrid",
    "sg:orig_category":"Asociaciones Humanitarias, De Cooperaci\u00d3n, De Acci\u00d3n Social",
    "sg:phone":"+34 917 33 30 59",
    "sg:postcode":"28029",
    "sg:province":"Madrid",
    "wof:name":"Asociacion De Mujeres Con Cargas Familiares No Compartidas De Tetuan",
    "wof:placetype":"venue"
},
  "geometry": {"coordinates":[-3.6913731098,40.4696311951],"type":"Point"}
}