{
  "type": "Feature",
  "properties": {
    "iso:country":"ES",
    "sg:address":"Avda Mar (el), 14",
    "sg:city":"Costa Teguise",
    "sg:orig_category":"Caf\u00c9s, Bares, Cervecer\u00cdas",
    "sg:phone":"+34 928 82 71 58",
    "sg:postcode":"35509",
    "sg:province":"Las Palmas",
    "wof:name":"Hertkorn  Alexandra Theresia",
    "wof:placetype":"venue"
},
  "geometry": {"coordinates":[-13.5916891098,28.955160141],"type":"Point"}
}