{
  "type": "Feature",
  "properties": {
    "iso:country":"ES",
    "sg:address":"Calle de Humilladero, 6",
    "sg:city":"Madrid",
    "sg:orig_category":"Molduras, Junquillos, Listones Y Molduras Perforadas",
    "sg:phone":"+34 913 64 11 96",
    "sg:postcode":"28005",
    "sg:province":"Madrid",
    "wof:name":"Mendibil Restauracion S.l.",
    "wof:placetype":"venue"
},
  "geometry": {"coordinates":[-3.7106719017,40.4111213684],"type":"Point"}
}