{
  "type": "Feature",
  "properties": {
    "iso:country":"ES",
    "sg:address":"Calle de Santa Teresa De Jesus, 20",
    "sg:city":"Oviedo",
    "sg:orig_category":"Abogados",
    "sg:phone":"+34 985 25 43 05",
    "sg:postcode":"33005",
    "sg:province":"Asturias",
    "wof:name":"Ardura Gonzalez Ana",
    "wof:placetype":"venue"
},
  "geometry": {"coordinates":[-5.8578057289,43.3592414856],"type":"Point"}
}