{
  "type": "Feature",
  "properties": {
    "iso:country":"ES",
    "sg:address":"Avda Canarias, 119",
    "sg:city":"Vecindario",
    "sg:orig_category":"Art\u00cdculos De Regalo (al Por Menor)",
    "sg:phone":"+34 928 75 90 23",
    "sg:postcode":"35110",
    "sg:province":"Las Palmas",
    "wof:name":"Lantigua Gonzalez Maria Del Carmen",
    "wof:placetype":"venue"
},
  "geometry": {"coordinates":[-15.4408693314,27.8513793945],"type":"Point"}
}