{
  "type": "Feature",
  "properties": {
    "addr:full":"Calle de Rey Baltasar, 11 Cabra C\u00f3rdoba 14940",
    "addr:housenumber":"11",
    "addr:postcode":"14940",
    "addr:street":"Calle De Rey Baltasar;Co\u0301Rdoba",
    "iso:country":"ES",
    "sg:address":"Calle de Rey Baltasar, 11",
    "sg:city":"Cabra",
    "sg:orig_category":"Transportes Por V\u00cdas Navegables",
    "sg:phone":"+34 957 52 03 51",
    "sg:postcode":"14940",
    "sg:province":"C\u00f3rdoba",
    "wof:name":"Gomez Castro Romualdo",
    "wof:placetype":"venue"
},
  "geometry": {"coordinates":[-4.4427027702,37.4782714844],"type":"Point"}
}