{
  "type": "Feature",
  "properties": {
    "iso:country":"ES",
    "sg:address":"Calle de Vista Alegre, 47",
    "sg:city":"Arroyo De La Encomienda",
    "sg:orig_category":"Muebles, Minoristas",
    "sg:phone":"+34 983 40 76 38",
    "sg:postcode":"47195",
    "sg:province":"Valladolid",
    "wof:name":"Fuentes Moyano Oscar De",
    "wof:placetype":"venue"
},
  "geometry": {"coordinates":[-4.7709650993,41.6273460388],"type":"Point"}
}