{
  "type": "Feature",
  "properties": {
    "iso:country":"ES",
    "sg:address":"Carrer de Vint-i-quatre, S/n",
    "sg:city":"Can G\u00fcell",
    "sg:orig_category":"Aguas (distribuci\u00d3n, Servicios)",
    "sg:phone":"+34 936 89 15 90",
    "sg:postcode":"08629",
    "sg:province":"Barcelona",
    "sg:website":"www.aiguesdebarcelona.es",
    "wof:name":"Sociedad General De Aguas S.a.",
    "wof:placetype":"venue"
},
  "geometry": {"coordinates":[1.957398057,41.3547210693],"type":"Point"}
}