{
  "type": "Feature",
  "properties": {
    "addr:full":"Carrer de Pompeu Fabra, 7 Manresa Barcelona 08242",
    "addr:housenumber":"7",
    "addr:postcode":"08242",
    "addr:street":"Carrer De Pompeu Fabra",
    "iso:country":"ES",
    "sg:address":"Carrer de Pompeu Fabra, 7",
    "sg:city":"Manresa",
    "sg:orig_category":"Procuradores",
    "sg:phone":"+34 938 72 13 96",
    "sg:postcode":"08242",
    "sg:province":"Barcelona",
    "wof:name":"Rodriguez Cuadra Lourdes",
    "wof:placetype":"venue"
},
  "geometry": {"coordinates":[1.8221110106,41.7260856628],"type":"Point"}
}