{
  "type": "Feature",
  "properties": {
    "iso:country":"ES",
    "sg:address":"Av. Villava, 10",
    "sg:city":"Iru\u00f1a",
    "sg:orig_category":"Construcciones E Instalaciones Agr\u00cdcolas",
    "sg:phone":"+34 948 14 63 88",
    "sg:postcode":"31015",
    "sg:province":"Navarra",
    "wof:name":"Iruagro S. L.",
    "wof:placetype":"venue"
},
  "geometry": {"coordinates":[-1.6305589676,42.8314208984],"type":"Point"}
}