{
  "type": "Feature",
  "properties": {
    "iso:country":"ES",
    "sg:address":"Calle de Sabinosa, 9",
    "sg:city":"San Isidro",
    "sg:orig_category":"Chapister\u00cda",
    "sg:phone":"+34 922 39 12 07",
    "sg:postcode":"38611",
    "sg:province":"Santa Cruz De Tenerife",
    "wof:name":"Alonso Gonzalez Domingo",
    "wof:placetype":"venue"
},
  "geometry": {"coordinates":[-16.5547008514,28.0722751617],"type":"Point"}
}