{
  "type": "Feature",
  "properties": {
    "iso:country":"ES",
    "sg:address":"Calle de Mendez Nu\u00d1ez, 77",
    "sg:city":"Villacarrillo",
    "sg:orig_category":"Bebidas",
    "sg:phone":"+34 953 44 06 27",
    "sg:postcode":"23300",
    "sg:province":"Ja\u00e9n",
    "wof:name":"Mu\u00f1oz Hicar Vicente",
    "wof:placetype":"venue"
},
  "geometry": {"coordinates":[-3.0840370655,38.1147689819],"type":"Point"}
}