{
  "type": "Feature",
  "properties": {
    "addr:full":"Calle de Comunidad De Madrid (de La), S/n Fuenlabrada Madrid 28944",
    "addr:housenumber":"s",
    "addr:postcode":"28944",
    "addr:street":"Calle De Comunidad;/ N",
    "iso:country":"ES",
    "sg:address":"Calle de Comunidad De Madrid (de La), S/n",
    "sg:city":"Fuenlabrada",
    "sg:orig_category":"Polideportivos",
    "sg:phone":"+34 916 15 42 07",
    "sg:postcode":"28944",
    "sg:province":"Madrid",
    "wof:name":"Patronato Municipal De Deportes De Fuenlabrada",
    "wof:placetype":"venue"
},
  "geometry": {"coordinates":[-3.7977776527,40.2774581909],"type":"Point"}
}