{
  "type": "Feature",
  "properties": {
    "iso:country":"ES",
    "sg:address":"Calle de Calvo Sotelo, 110",
    "sg:city":"Marin",
    "sg:orig_category":"Frutas Y Legumbres Frescas (al Por Mayor)",
    "sg:phone":"+34 986 88 33 02",
    "sg:postcode":"36900",
    "sg:province":"Pontevedra",
    "wof:name":"Frutas Katusa S.l.",
    "wof:placetype":"venue"
},
  "geometry": {"coordinates":[-8.6922874451,42.3951377869],"type":"Point"}
}