{
  "type": "Feature",
  "properties": {
    "addr:full":"Cmno Muchavista, 6 Alacant Alicante 03540",
    "addr:housenumber":"6",
    "addr:postcode":"03540",
    "addr:street":"Cmno Muchavista",
    "iso:country":"ES",
    "sg:address":"Cmno Muchavista, 6",
    "sg:city":"Alacant",
    "sg:orig_category":"Fabricaci\u00d3n De Juegos Y Juguetes",
    "sg:phone":"+34 965 65 04 36",
    "sg:postcode":"03540",
    "sg:province":"Alicante",
    "wof:name":"Riquelme Gonzalez David",
    "wof:placetype":"venue"
},
  "geometry": {"coordinates":[-0.4282369912,38.3684196472],"type":"Point"}
}