{
  "type": "Feature",
  "properties": {
    "iso:country":"ES",
    "sg:address":"Blanca, 6",
    "sg:city":"Murcia",
    "sg:orig_category":"Chapister\u00cda",
    "sg:phone":"+34 968 23 53 63",
    "sg:postcode":"30007",
    "sg:province":"Murcia",
    "wof:name":"Sanchez Cubero Ramon",
    "wof:placetype":"venue"
},
  "geometry": {"coordinates":[-1.1142389774,37.9970092773],"type":"Point"}
}