{
  "type": "Feature",
  "properties": {
    "addr:full":"Laia, S/n Laia Lugo 27205",
    "addr:postcode":"27205",
    "addr:street":"Laia S / N",
    "iso:country":"ES",
    "sg:address":"Laia, S/n",
    "sg:city":"Laia",
    "sg:orig_category":"Producci\u00d3n, Venta De Productos De Agricultura Biol\u00d3gica",
    "sg:phone":"+34 982 18 36 05",
    "sg:postcode":"27205",
    "sg:province":"Lugo",
    "wof:name":"S.a.t. Agro Laia 944 Xuga",
    "wof:placetype":"venue"
},
  "geometry": {"coordinates":[-7.8884081841,42.929271698],"type":"Point"}
}