{
  "type": "Feature",
  "properties": {
    "iso:country":"ES",
    "sg:address":"Calle de Juan Alvargonzalez, 53",
    "sg:city":"Gijon",
    "sg:orig_category":"\u00d3ptica: Instrumentos (fabricaci\u00d3n)",
    "sg:phone":"+34 985 38 80 69",
    "sg:postcode":"33208",
    "sg:province":"Asturias",
    "wof:name":"Toyos Cueli Rafael Enrique",
    "wof:placetype":"venue"
},
  "geometry": {"coordinates":[-5.6666760445,43.5298461914],"type":"Point"}
}