{
  "type": "Feature",
  "properties": {
    "iso:country":"ES",
    "sg:address":"Calle de Angustias, 17",
    "sg:city":"Valladolid",
    "sg:orig_category":"M\u00c9dicos: Pediatr\u00cda. Enfermedades De Los Ni\u00d1os",
    "sg:phone":"+34 983 25 29 07",
    "sg:postcode":"47003",
    "sg:province":"Valladolid",
    "wof:name":"Grajal Rodriguez Manuel",
    "wof:placetype":"venue"
},
  "geometry": {"coordinates":[-4.7241134644,41.6559143066],"type":"Point"}
}