{
  "type": "Feature",
  "properties": {
    "iso:country":"ES",
    "sg:address":"Calle de Calderon De La Barca, 21",
    "sg:city":"Alzira",
    "sg:orig_category":"Confecci\u00d3n De Trajes Para Se\u00d1oras",
    "sg:phone":"+34 962 41 99 58",
    "sg:postcode":"46600",
    "sg:province":"Valencia",
    "wof:name":"Ceramicas Locura S.l.",
    "wof:placetype":"venue"
},
  "geometry": {"coordinates":[-0.4383203089,39.1511001587],"type":"Point"}
}