{
  "type": "Feature",
  "properties": {
    "iso:country":"ES",
    "sg:address":"Calle de Riego, 10",
    "sg:city":"Zamora",
    "sg:orig_category":"Frutas, Legumbres Frescas Y Tempranas (al Por Menor)",
    "sg:phone":"+34 980 53 53 38",
    "sg:postcode":"49004",
    "sg:province":"Zamora",
    "wof:name":"Rio Salagre Maria Lucinda Del",
    "wof:placetype":"venue"
},
  "geometry": {"coordinates":[-5.7458600998,41.5051994324],"type":"Point"}
}