{
  "type": "Feature",
  "properties": {
    "iso:country":"ES",
    "sg:address":"Calle de Marien De Marguan, 4",
    "sg:city":"Zaragoza",
    "sg:orig_category":"Equitaci\u00d3n Y Centros De H\u00cdpica",
    "sg:phone":"+34 976 38 31 70",
    "sg:postcode":"50007",
    "sg:province":"Zaragoza",
    "wof:name":"Melantuche Los Arcos Cristina",
    "wof:placetype":"venue"
},
  "geometry": {"coordinates":[-0.8745340109,41.6245117188],"type":"Point"}
}