{
  "type": "Feature",
  "properties": {
    "addr:full":"Calle de Santander, 31 Valencia Valencia 46017",
    "addr:housenumber":"31",
    "addr:postcode":"46017",
    "addr:street":"Calle De Santander",
    "iso:country":"ES",
    "sg:address":"Calle de Santander, 31",
    "sg:city":"Valencia",
    "sg:orig_category":"Mercer\u00cda, Lencer\u00cda (al Por Menor)",
    "sg:phone":"+34 963 77 17 70",
    "sg:postcode":"46017",
    "sg:province":"Valencia",
    "wof:name":"Ortel Cristobal Bernabe",
    "wof:placetype":"venue"
},
  "geometry": {"coordinates":[-0.3880470097,39.4540328979],"type":"Point"}
}