{
  "type": "Feature",
  "properties": {
    "addr:full":"Avda Infante Don Luis (del), 15 Boadilla Del Monte Madrid 28660",
    "addr:postcode":"28660",
    "addr:street":"Avda Infante Don;Del",
    "iso:country":"ES",
    "sg:address":"Avda Infante Don Luis (del), 15",
    "sg:city":"Boadilla Del Monte",
    "sg:orig_category":"Cl\u00cdnicas Dentales",
    "sg:phone":"+34 916 33 21 90",
    "sg:postcode":"28660",
    "sg:province":"Madrid",
    "wof:name":"Andos Dental S.l.",
    "wof:placetype":"venue"
},
  "geometry": {"coordinates":[-3.8967504501,40.402961731],"type":"Point"}
}