{
  "type": "Feature",
  "properties": {
    "addr:full":"Calle de Joaquin Perez Villanueva, 6 Segovia Segovia 40001",
    "addr:housenumber":"6",
    "addr:postcode":"40001",
    "addr:street":"Calle De Joaquin Perez Villanueva",
    "iso:country":"ES",
    "sg:address":"Calle de Joaquin Perez Villanueva, 6",
    "sg:city":"Segovia",
    "sg:orig_category":"Alquiler De Casas Y Habitaciones Amuebladas",
    "sg:phone":"+34 921 46 32 98",
    "sg:postcode":"40001",
    "sg:province":"Segovia",
    "wof:name":"Consejo Diocesano De Hermandades Del Tra",
    "wof:placetype":"venue"
},
  "geometry": {"coordinates":[-4.118142128,40.9491004944],"type":"Point"}
}