{
  "type": "Feature",
  "properties": {
    "addr:full":"Calle de Antonio Suarez, 27 Valencia Valencia 46021",
    "addr:housenumber":"27",
    "addr:postcode":"46021",
    "addr:street":"Calle De Antonio Suarez",
    "iso:country":"ES",
    "sg:address":"Calle de Antonio Suarez, 27",
    "sg:city":"Valencia",
    "sg:orig_category":"Caf\u00c9s, Bares, Cervecer\u00cdas",
    "sg:phone":"+34 963 61 15 09",
    "sg:postcode":"46021",
    "sg:province":"Valencia",
    "wof:name":"Swing Del Mediterraneo S.l",
    "wof:placetype":"venue"
},
  "geometry": {"coordinates":[-0.3567569852,39.4697799683],"type":"Point"}
}