{
  "type": "Feature",
  "properties": {
    "addr:full":"Avda Pola De Lena, S/n Vega Asturias 33160",
    "addr:housenumber":"s / n",
    "addr:postcode":"33160",
    "addr:street":"Avda Pola De Lena;Asturias",
    "iso:country":"ES",
    "sg:address":"Avda Pola De Lena, S/n",
    "sg:city":"Vega",
    "sg:orig_category":"Talleres: Ropa A Medida",
    "sg:phone":"+34 985 76 60 71",
    "sg:postcode":"33160",
    "sg:province":"Asturias",
    "wof:name":"Suarez Gonzalez German",
    "wof:placetype":"venue"
},
  "geometry": {"coordinates":[-5.8812642097,43.2313308716],"type":"Point"}
}