{
  "type": "Feature",
  "properties": {
    "addr:full":"Calle de Santa Ana, 3 Valverde Camino Huelva 21600",
    "addr:housenumber":"3",
    "addr:postcode":"21600",
    "addr:street":"Calle De Santa Ana;Camino Huelva",
    "iso:country":"ES",
    "sg:address":"Calle de Santa Ana, 3",
    "sg:city":"Valverde Camino",
    "sg:orig_category":"Fabricaci\u00d3n, Venta De Cuadros, Accesorios Para Enmarcar",
    "sg:phone":"+34 959 55 18 26",
    "sg:postcode":"21600",
    "sg:province":"Huelva",
    "wof:name":"Suarez Marquez Antonio",
    "wof:placetype":"venue"
},
  "geometry": {"coordinates":[-6.7522425652,37.5722465515],"type":"Point"}
}