{
  "type": "Feature",
  "properties": {
    "iso:country":"ES",
    "sg:address":"Carrer de L'avio Plus Ultra, 21",
    "sg:city":"Barcelona",
    "sg:orig_category":"Florister\u00cdas",
    "sg:phone":"+34 932 05 76 78",
    "sg:postcode":"08017",
    "sg:province":"Barcelona",
    "wof:name":"Miserachs Vidal Flora",
    "wof:placetype":"venue"
},
  "geometry": {"coordinates":[2.1210715771,41.4009857178],"type":"Point"}
}