{
  "type": "Feature",
  "properties": {
    "addr:full":"Avda Gustavo Adolfo Becquer, 82 Nueva Andalucia M\u00e1laga 29660",
    "addr:housenumber":"82",
    "addr:postcode":"29660",
    "addr:street":"Avda Gustavo Adolfo Becquer;Ma\u0301Laga",
    "iso:country":"ES",
    "sg:address":"Avda Gustavo Adolfo Becquer, 82",
    "sg:city":"Nueva Andalucia",
    "sg:orig_category":"Cerrajer\u00cda, Ferrallista",
    "sg:phone":"+34 952 81 92 78",
    "sg:postcode":"29660",
    "sg:province":"M\u00e1laga",
    "wof:name":"Iglesias Silba Francisco",
    "wof:placetype":"venue"
},
  "geometry": {"coordinates":[-4.9740319252,36.4989013672],"type":"Point"}
}