{
  "type": "Feature",
  "properties": {
    "iso:country":"ES",
    "sg:address":"Ctra Circunvalacion, S/n",
    "sg:city":"Ubeda",
    "sg:orig_category":"Aceites Y Grasas Alimentarias (fabricaci\u00d3n, Al Por Mayor)",
    "sg:phone":"+34 953 75 09 20",
    "sg:postcode":"23400",
    "sg:province":"Ja\u00e9n",
    "wof:name":"Cooperativa Nuestra Se\u00f1ora De Guadalupe",
    "wof:placetype":"venue"
},
  "geometry": {"coordinates":[-3.3697240353,38.0200309753],"type":"Point"}
}