{
  "type": "Feature",
  "properties": {
    "addr:full":"Carrer de Sant Magi, 3 Bellvei Tarragona 43719",
    "addr:housenumber":"3",
    "addr:postcode":"43719",
    "addr:street":"Carrer De Sant Magi",
    "iso:country":"ES",
    "sg:address":"Carrer de Sant Magi, 3",
    "sg:city":"Bellvei",
    "sg:orig_category":"Asociaciones, Organismos Culturales Y Socioeducativos",
    "sg:phone":"+34 977 16 81 97",
    "sg:postcode":"43719",
    "sg:province":"Tarragona",
    "wof:name":"Sociedad Cultural Y Recreativa El Casal",
    "wof:placetype":"venue"
},
  "geometry": {"coordinates":[1.576061964,41.2396087646],"type":"Point"}
}