{
  "type": "Feature",
  "properties": {
    "iso:country":"ES",
    "sg:address":"Carrer de Vidua De Vives, 22",
    "sg:city":"S. Boi Llobregat",
    "sg:orig_category":"Fotograf\u00cda Art\u00cdstica Y Retratos",
    "sg:phone":"+34 936 30 03 62",
    "sg:postcode":"08830",
    "sg:province":"Barcelona",
    "wof:name":"Renau Moratinos Javier",
    "wof:placetype":"venue"
},
  "geometry": {"coordinates":[2.0449779034,41.3480606079],"type":"Point"}
}