{
  "type": "Feature",
  "properties": {
    "addr:full":"Calle de Antonio Povedano, 4 Cabra C\u00f3rdoba 14940",
    "addr:housenumber":"4",
    "addr:postcode":"14940",
    "addr:street":"Calle De Antonio Povedano;Co\u0301Rdoba",
    "iso:country":"ES",
    "sg:address":"Calle de Antonio Povedano, 4",
    "sg:city":"Cabra",
    "sg:orig_category":"Partidos Pol\u00cdticos",
    "sg:phone":"+34 957 52 09 88",
    "sg:postcode":"14940",
    "sg:province":"C\u00f3rdoba",
    "wof:name":"Partido Socialista Obrero Espa\u00f1ol",
    "wof:placetype":"venue"
},
  "geometry": {"coordinates":[-4.4404888153,37.4701576233],"type":"Point"}
}