{
  "type": "Feature",
  "properties": {
    "addr:full":"Calle de Luis Mariano, 14 Irun Guip\u00f9zcoa 20302",
    "addr:housenumber":"14",
    "addr:postcode":"20302",
    "addr:street":"Calle De Luis Mariano;Guipu\u0300Zcoa",
    "iso:country":"ES",
    "sg:address":"Calle de Luis Mariano, 14",
    "sg:city":"Irun",
    "sg:orig_category":"Papeler\u00cdas, Librer\u00cdas",
    "sg:phone":"+34 943 63 14 94",
    "sg:postcode":"20302",
    "sg:province":"Guip\u00f9zcoa",
    "wof:name":"Sanchez Cimorra Jose Antonio",
    "wof:placetype":"venue"
},
  "geometry": {"coordinates":[-1.7927800417,43.3395004272],"type":"Point"}
}