{
  "type": "Feature",
  "properties": {
    "iso:country":"ES",
    "sg:address":"Calle de Francisco Jose Arroyo, 2",
    "sg:city":"Madrid",
    "sg:orig_category":"Agencias Y Asesores De Publicidad",
    "sg:phone":"+34 913 93 02 70",
    "sg:postcode":"28042",
    "sg:province":"Madrid",
    "wof:name":"Publiasesores S.l.",
    "wof:placetype":"venue"
},
  "geometry": {"coordinates":[-3.615596056,40.4526863098],"type":"Point"}
}