{
  "type": "Feature",
  "properties": {
    "addr:full":"Rua Bouci\u00d1a, S/n Bouci\u00d1a Pontevedra 36635",
    "addr:housenumber":"s",
    "addr:postcode":"36635",
    "addr:street":"Rua Boucin\u0303A;/ N",
    "iso:country":"ES",
    "sg:address":"Rua Bouci\u00d1a, S/n",
    "sg:city":"Bouci\u00d1a",
    "sg:orig_category":"Agricultores, Agricultores",
    "sg:phone":"+34 986 71 54 43",
    "sg:postcode":"36635",
    "sg:province":"Pontevedra",
    "wof:name":"Sociedad Agraria De Transformacion",
    "wof:placetype":"venue"
},
  "geometry": {"coordinates":[-8.7641687393,42.3270759583],"type":"Point"}
}