{
  "type": "Feature",
  "properties": {
    "iso:country":"ES",
    "sg:address":"Calle de Toreros, 4",
    "sg:city":"Valladolid",
    "sg:orig_category":"Bisuter\u00cda, Joyer\u00cda, Relojer\u00cda (al Por Menor)",
    "sg:phone":"+34 983 47 98 61",
    "sg:postcode":"47007",
    "sg:province":"Valladolid",
    "wof:name":"Valtierra Prieto Gregorio",
    "wof:placetype":"venue"
},
  "geometry": {"coordinates":[-4.7358088493,41.6401748657],"type":"Point"}
}