{
  "type": "Feature",
  "properties": {
    "iso:country":"ES",
    "sg:address":"Calle de Arapiles, 23",
    "sg:city":"Salamanca",
    "sg:orig_category":"Farmacias",
    "sg:phone":"+34 923 23 24 21",
    "sg:postcode":"37007",
    "sg:province":"Salamanca",
    "wof:name":"Farmacia Bautista Y Perez Teijon",
    "wof:placetype":"venue"
},
  "geometry": {"coordinates":[-5.6725082397,40.970085144],"type":"Point"}
}