{
  "type": "Feature",
  "properties": {
    "addr:full":"Calle de Santa Cruz De Marcenado, 14 Madrid Madrid 28015",
    "addr:housenumber":"14",
    "addr:postcode":"madrid;28015",
    "addr:street":"Calle De Santa Cruz De Marcenado",
    "iso:country":"ES",
    "sg:address":"Calle de Santa Cruz De Marcenado, 14",
    "sg:city":"Madrid",
    "sg:orig_category":"Laboratorios Farmac\u00c9uticos",
    "sg:phone":"+34 914 47 99 61",
    "sg:postcode":"28015",
    "sg:province":"Madrid",
    "sg:website":"www.dentaris-sa.com",
    "wof:name":"Dentaris S.a.",
    "wof:placetype":"venue"
},
  "geometry": {"coordinates":[-3.7085440159,40.428894043],"type":"Point"}
}