{
  "type": "Feature",
  "properties": {
    "iso:country":"ES",
    "sg:address":"Plaz Coca De La Pi\u00d1era, 4",
    "sg:city":"Jaen",
    "sg:orig_category":"Arquitectos",
    "sg:phone":"+34 953 26 01 79",
    "sg:postcode":"23001",
    "sg:province":"Ja\u00e9n",
    "wof:name":"Moreno Ramiro Enrique",
    "wof:placetype":"venue"
},
  "geometry": {"coordinates":[-3.787637949,37.7708625793],"type":"Point"}
}