{
  "type": "Feature",
  "properties": {
    "iso:country":"ES",
    "sg:address":"Calle de Real, 34",
    "sg:city":"Fabero",
    "sg:orig_category":"Agentes Generales De Seguros",
    "sg:phone":"+34 987 55 03 52",
    "sg:postcode":"24420",
    "sg:province":"Le\u00f3n",
    "wof:name":"Lopez Alvarez Alfredo",
    "wof:placetype":"venue"
},
  "geometry": {"coordinates":[-6.627286911,42.7663345337],"type":"Point"}
}