{
  "type": "Feature",
  "properties": {
    "iso:country":"ES",
    "sg:address":"Carr Mallorquines, 29",
    "sg:city":"Urbanitzacio Mallorquines",
    "sg:orig_category":"Forjas Y Altos Hornos",
    "sg:phone":"+34 972 85 31 21",
    "sg:postcode":"17410",
    "sg:province":"Girona",
    "wof:name":"Morell Pons Francisco",
    "wof:placetype":"venue"
},
  "geometry": {"coordinates":[2.745290041,41.8085403442],"type":"Point"}
}