{
  "type": "Feature",
  "properties": {
    "addr:full":"Calle de Galicia, 24 Palmas De Gran Canaria Las Palmas 35006",
    "addr:postcode":"35006",
    "addr:street":"Calle De Galicia 24",
    "iso:country":"ES",
    "sg:address":"Calle de Galicia, 24",
    "sg:city":"Palmas De Gran Canaria",
    "sg:orig_category":"Pescader\u00cdas (al Por Menor)",
    "sg:phone":"+34 928 24 89 75",
    "sg:postcode":"35006",
    "sg:province":"Las Palmas",
    "wof:name":"Pescaderia Hermanos Montesdeoca S.l.",
    "wof:placetype":"venue"
},
  "geometry": {"coordinates":[-15.4329156876,28.132194519],"type":"Point"}
}