{
  "type": "Feature",
  "properties": {
    "iso:country":"ES",
    "sg:address":"Calle de Rio, S/n",
    "sg:city":"Melgosa",
    "sg:orig_category":"Distribuci\u00d3n De Petr\u00d3leo Y Derivados",
    "sg:phone":"+34 969 25 80 56",
    "sg:postcode":"16193",
    "sg:province":"Cuenca",
    "wof:name":"Castilla Energia S.l.",
    "wof:placetype":"venue"
},
  "geometry": {"coordinates":[-2.0219569206,39.951171875],"type":"Point"}
}