{
  "type": "Feature",
  "properties": {
    "iso:country":"ES",
    "sg:address":"Calle de Formentera, 3",
    "sg:city":"Fuengirola",
    "sg:orig_category":"Plomeros",
    "sg:phone":"+34 952 46 64 60",
    "sg:postcode":"29640",
    "sg:province":"M\u00e1laga",
    "wof:name":"Flexagua S.c.",
    "wof:placetype":"venue"
},
  "geometry": {"coordinates":[-4.6295294762,36.5468444824],"type":"Point"}
}