{
  "type": "Feature",
  "properties": {
    "iso:country":"ES",
    "sg:address":"Calle de Doctor Vicente Pallares, 12",
    "sg:city":"Valencia",
    "sg:orig_category":"Molduras, Junquillos, Listones Y Molduras Perforadas",
    "sg:phone":"+34 963 61 72 81",
    "sg:postcode":"46021",
    "sg:province":"Valencia",
    "wof:name":"Ruiz Sanz Teodora",
    "wof:placetype":"venue"
},
  "geometry": {"coordinates":[-0.3524093926,39.4737739563],"type":"Point"}
}