{
  "type": "Feature",
  "properties": {
    "iso:country":"ES",
    "sg:address":"Carrer de Comte D'urgell, 220",
    "sg:city":"Barcelona",
    "sg:orig_category":"Molduras, Junquillos, Listones Y Molduras Perforadas",
    "sg:phone":"+34 934 39 31 79",
    "sg:postcode":"08036",
    "sg:province":"Barcelona",
    "wof:name":"Simoes Estevez Silverio",
    "wof:placetype":"venue"
},
  "geometry": {"coordinates":[2.1495816708,41.3889312744],"type":"Point"}
}