{
  "type": "Feature",
  "properties": {
    "addr:full":"Estd Xunqueira (de), 7 Allariz Ourense 32660",
    "addr:postcode":"32660",
    "iso:country":"ES",
    "sg:address":"Estd Xunqueira (de), 7",
    "sg:city":"Allariz",
    "sg:orig_category":"Internados & Ense\u00d1anza Privada",
    "sg:phone":"+34 988 44 00 28",
    "sg:postcode":"32660",
    "sg:province":"Ourense",
    "wof:name":"Salesianos",
    "wof:placetype":"venue"
},
  "geometry": {"coordinates":[-7.7982821465,42.1902618408],"type":"Point"}
}