{
  "type": "Feature",
  "properties": {
    "iso:country":"ES",
    "sg:address":"Calle de Marmoles, 51",
    "sg:city":"Malaga",
    "sg:orig_category":"Farmacias",
    "sg:phone":"+34 952 30 70 42",
    "sg:postcode":"29007",
    "sg:province":"M\u00e1laga",
    "wof:name":"Ortega Arteaga Antonio",
    "wof:placetype":"venue"
},
  "geometry": {"coordinates":[-4.4315128326,36.7213783264],"type":"Point"}
}