{
  "type": "Feature",
  "properties": {
    "addr:full":"Carrer de Sant Gervasi De Cassoles, 10 Barcelona Barcelona 08022",
    "addr:housenumber":"10",
    "addr:postcode":"08022",
    "addr:street":"Carrer De Sant Gervasi De Cassoles",
    "iso:country":"ES",
    "sg:address":"Carrer de Sant Gervasi De Cassoles, 10",
    "sg:city":"Barcelona",
    "sg:orig_category":"Caf\u00c9s, Bares, Cervecer\u00cdas",
    "sg:phone":"+34 932 53 10 75",
    "sg:postcode":"08022",
    "sg:province":"Barcelona",
    "wof:name":"Galarza Vela Antonio",
    "wof:placetype":"venue"
},
  "geometry": {"coordinates":[2.139523983,41.4043464661],"type":"Point"}
}