{
  "type": "Feature",
  "properties": {
    "addr:full":"Avgd Valencia, 27 Muro Alcoy Alicante 03830",
    "addr:housenumber":"27",
    "addr:postcode":"03830",
    "addr:street":"Valencia",
    "iso:country":"ES",
    "sg:address":"Avgd Valencia, 27",
    "sg:city":"Muro Alcoy",
    "sg:orig_category":"Cajas Para Embalar",
    "sg:phone":"+34 966 54 42 35",
    "sg:postcode":"03830",
    "sg:province":"Alicante",
    "wof:name":"Caja Rural Del Mediterraneo Ruralcaja S Coop De Credito",
    "wof:placetype":"venue"
},
  "geometry": {"coordinates":[-0.4414289892,38.7812538147],"type":"Point"}
}