{
  "type": "Feature",
  "properties": {
    "iso:country":"ES",
    "sg:address":"Carr Aviador Franco, 25",
    "sg:city":"Villarreal",
    "sg:orig_category":"Asociaciones Humanitarias, De Cooperaci\u00d3n, De Acci\u00d3n Social",
    "sg:phone":"+34 964 53 83 75",
    "sg:postcode":"12540",
    "sg:province":"Castell\u00f3n",
    "wof:name":"Reto A La Esperanza Asociacion",
    "wof:placetype":"venue"
},
  "geometry": {"coordinates":[-0.0952939987,39.9453048706],"type":"Point"}
}