{
  "type": "Feature",
  "properties": {
    "addr:full":"Calle de Berastegui, 33 Madrid Madrid 28017",
    "addr:housenumber":"33",
    "addr:postcode":"madrid;28017",
    "addr:street":"Calle De Berastegui",
    "iso:country":"ES",
    "sg:address":"Calle de Berastegui, 33",
    "sg:city":"Madrid",
    "sg:orig_category":"Electricidad, Electr\u00d3nica: Material Y Suministros (al Por Mayor)",
    "sg:phone":"+34 914 07 46 77",
    "sg:postcode":"28017",
    "sg:province":"Madrid",
    "sg:website":"www.malusan.enwanadoo.es",
    "wof:name":"Aparellaje Electrico Industrial S.l.",
    "wof:placetype":"venue"
},
  "geometry": {"coordinates":[-3.6416823864,40.4285736084],"type":"Point"}
}