{
  "type": "Feature",
  "properties": {
    "addr:full":"Psaj Paquitin, 10 Madrid Madrid 28037",
    "addr:housenumber":"10",
    "addr:postcode":"madrid;28037",
    "addr:street":"Paquitin",
    "iso:country":"ES",
    "sg:address":"Psaj Paquitin, 10",
    "sg:city":"Madrid",
    "sg:orig_category":"Fabricaci\u00d3n Y Refinado De Az\u00dacares",
    "sg:phone":"+34 917 54 33 28",
    "sg:postcode":"28037",
    "sg:province":"Madrid",
    "wof:name":"Emproasa",
    "wof:placetype":"venue"
},
  "geometry": {"coordinates":[-3.6251480579,40.4407958984],"type":"Point"}
}