{
  "type": "Feature",
  "properties": {
    "addr:full":"Ctra Tibi, S/n Jijona Alicante 03100",
    "addr:housenumber":"s / n",
    "addr:postcode":"03100",
    "addr:street":"Ctra Tibi",
    "iso:country":"ES",
    "sg:address":"Ctra Tibi, S/n",
    "sg:city":"Jijona",
    "sg:orig_category":"Empresas De Carpinter\u00cda De Madera",
    "sg:phone":"+34 965 61 09 89",
    "sg:postcode":"03100",
    "sg:province":"Alicante",
    "wof:name":"Cremades Colomina Antonio",
    "wof:placetype":"venue"
},
  "geometry": {"coordinates":[-0.5065839887,38.5421600342],"type":"Point"}
}