{
  "type": "Feature",
  "properties": {
    "iso:country":"ES",
    "sg:address":"Calle de Mina, 12",
    "sg:city":"Majadahonda",
    "sg:orig_category":"Florister\u00cdas",
    "sg:phone":"+34 916 34 56 65",
    "sg:postcode":"28220",
    "sg:province":"Madrid",
    "sg:website":"www.laosgarden.com",
    "wof:name":"Laos Garden C.b.",
    "wof:placetype":"venue"
},
  "geometry": {"coordinates":[-3.8751087189,40.4709587097],"type":"Point"}
}