{
  "type": "Feature",
  "properties": {
    "iso:country":"ES",
    "sg:address":"Calle de Torres, 20",
    "sg:city":"Valencia",
    "sg:orig_category":"M\u00c9dicos: Ginecolog\u00cda Y Obstetricia",
    "sg:phone":"+34 963 79 14 40",
    "sg:postcode":"46018",
    "sg:province":"Valencia",
    "wof:name":"Romaguera Torregrosa Rafael",
    "wof:placetype":"venue"
},
  "geometry": {"coordinates":[-0.399082005,39.4728736877],"type":"Point"}
}