{
  "type": "Feature",
  "properties": {
    "addr:full":"Placente, 10 Placente La Coru\u00f1a 15596",
    "addr:housenumber":"10",
    "addr:postcode":"15596",
    "addr:street":"Placente;La Corun\u0303A",
    "iso:country":"ES",
    "sg:address":"Placente, 10",
    "sg:city":"Placente",
    "sg:orig_category":"Carnes De Carnicer\u00cda (al Por Mayor)",
    "sg:phone":"+34 981 36 84 54",
    "sg:postcode":"15596",
    "sg:province":"La Coru\u00f1a",
    "wof:name":"Matadero Industrial Cantalarana S.l.",
    "wof:placetype":"venue"
},
  "geometry": {"coordinates":[-8.117430687,43.5455284119],"type":"Point"}
}