{
  "type": "Feature",
  "properties": {
    "iso:country":"ES",
    "sg:address":"Calle de Gladiolos, 2",
    "sg:city":"Valdelacalzada",
    "sg:orig_category":"Delegados, Agentes De Tr\u00c1nsito, Auxiliares De Transporte Internacional",
    "sg:phone":"+34 924 44 71 84",
    "sg:postcode":"06185",
    "sg:province":"Badajoz",
    "wof:name":"Tena Parra Jose Luis",
    "wof:placetype":"venue"
},
  "geometry": {"coordinates":[-6.6997494698,38.8910751343],"type":"Point"}
}