{
  "type": "Feature",
  "properties": {
    "addr:full":"Carr Duc De Lliria (del), 102 Lliria Valencia 46160",
    "addr:housenumber":"102",
    "addr:postcode":"46160",
    "addr:street":"Carr Duc De Lliria Del",
    "iso:country":"ES",
    "sg:address":"Carr Duc De Lliria (del), 102",
    "sg:city":"Lliria",
    "sg:orig_category":"Farmacias",
    "sg:phone":"+34 962 78 01 62",
    "sg:postcode":"46160",
    "sg:province":"Valencia",
    "wof:name":"Moratal Margarit Francisco Jose",
    "wof:placetype":"venue"
},
  "geometry": {"coordinates":[-0.5996289849,39.629108429],"type":"Point"}
}