{
  "type": "Feature",
  "properties": {
    "addr:full":"Avda Constitucion, 3 San Isidro Nijar Almer\u00eda 04117",
    "addr:housenumber":"3",
    "addr:postcode":"04117",
    "addr:street":"Avda Constitucion",
    "iso:country":"ES",
    "sg:address":"Avda Constitucion, 3",
    "sg:city":"San Isidro Nijar",
    "sg:orig_category":"Inmobiliaria (agencias)",
    "sg:phone":"+34 950 36 62 99",
    "sg:postcode":"04117",
    "sg:province":"Almer\u00eda",
    "wof:name":"Bosch Fontanet Roque",
    "wof:placetype":"venue"
},
  "geometry": {"coordinates":[-2.1763489246,36.9055900574],"type":"Point"}
}