{
  "type": "Feature",
  "properties": {
    "addr:full":"Avda Eusebio Sempere, 5 Alacant Alicante 03003",
    "addr:housenumber":"5",
    "addr:postcode":"03003",
    "addr:street":"Avda Eusebio Sempere",
    "iso:country":"ES",
    "sg:address":"Avda Eusebio Sempere, 5",
    "sg:city":"Alacant",
    "sg:orig_category":"Inmobiliaria (agencias)",
    "sg:phone":"+34 965 13 06 37",
    "sg:postcode":"03003",
    "sg:province":"Alicante",
    "wof:name":"Garfualq S.l.",
    "wof:placetype":"venue"
},
  "geometry": {"coordinates":[-0.4912269115,38.3388595581],"type":"Point"}
}