{
  "type": "Feature",
  "properties": {
    "addr:full":"Paredes, 1 Vilaboa Pontevedra 36141",
    "addr:housenumber":"1",
    "addr:postcode":"36141",
    "addr:street":"Paredes",
    "iso:country":"ES",
    "sg:address":"Paredes, 1",
    "sg:city":"Vilaboa",
    "sg:orig_category":"Discotecas Y Salas De Baile",
    "sg:phone":"+34 986 67 90 22",
    "sg:postcode":"36141",
    "sg:province":"Pontevedra",
    "wof:name":"Pamifran S.l.",
    "wof:placetype":"venue"
},
  "geometry": {"coordinates":[-8.6366939545,42.3592987061],"type":"Point"}
}