{
  "type": "Feature",
  "properties": {
    "iso:country":"ES",
    "sg:address":"Carrer de Santalo, 163",
    "sg:city":"Barcelona",
    "sg:orig_category":"Panader\u00cdas, Panader\u00cdas",
    "sg:phone":"+34 932 01 25 07",
    "sg:postcode":"08021",
    "sg:province":"Barcelona",
    "wof:name":"Dialypa S.l.",
    "wof:placetype":"venue"
},
  "geometry": {"coordinates":[2.1390779018,41.4008598328],"type":"Point"}
}