{
  "type": "Feature",
  "properties": {
    "iso:country":"ES",
    "sg:address":"Calle de General Pardi\u00d1as, 72",
    "sg:city":"Madrid",
    "sg:orig_category":"Arquitectos",
    "sg:phone":"+34 914 02 61 31",
    "sg:postcode":"28006",
    "sg:province":"Madrid",
    "wof:name":"Javier Rueda Y Asociados S.l.",
    "wof:placetype":"venue"
},
  "geometry": {"coordinates":[-3.678154707,40.4307136536],"type":"Point"}
}