{
  "type": "Feature",
  "properties": {
    "addr:full":"Avda Vigo, 162 Ferrol La Coru\u00f1a 15403",
    "addr:housenumber":"162",
    "addr:postcode":"15403",
    "addr:street":"Avda Vigo;La Corun\u0303A",
    "iso:country":"ES",
    "sg:address":"Avda Vigo, 162",
    "sg:city":"Ferrol",
    "sg:orig_category":"Empresas De Carpinter\u00cda Met\u00c1lica",
    "sg:phone":"+34 981 37 20 48",
    "sg:postcode":"15403",
    "sg:province":"La Coru\u00f1a",
    "wof:name":"Cubretend S.l.",
    "wof:placetype":"venue"
},
  "geometry": {"coordinates":[-8.2262935638,43.4850158691],"type":"Point"}
}