{
  "type": "Feature",
  "properties": {
    "iso:country":"ES",
    "sg:address":"Calle de San Vicente, 47",
    "sg:city":"San Vicente De Barakaldo",
    "sg:orig_category":"Complementos De Vestir (al Por Menor)",
    "sg:phone":"+34 944 38 05 41",
    "sg:postcode":"48902",
    "sg:province":"Vizcaya",
    "wof:name":"Lodeiro Rodriguez Aranzazu",
    "wof:placetype":"venue"
},
  "geometry": {"coordinates":[-2.9954819679,43.2956733704],"type":"Point"}
}