{
  "type": "Feature",
  "properties": {
    "iso:country":"ES",
    "sg:address":"C/ Santa Rita, 18",
    "sg:city":"Alcoi",
    "sg:orig_category":"Juegos Y Juguetes (al Por Menor)",
    "sg:phone":"+34 965 54 28 19",
    "sg:postcode":"03801",
    "sg:province":"Alicante",
    "wof:name":"Roma Aura Maria Teresa",
    "wof:placetype":"venue"
},
  "geometry": {"coordinates":[-0.4737809896,38.6968193054],"type":"Point"}
}