{
  "type": "Feature",
  "properties": {
    "addr:full":"Calle de Mayor, S/n Llanes Asturias 33500",
    "addr:housenumber":"s / n",
    "addr:postcode":"33500",
    "addr:street":"Calle De Mayor",
    "iso:country":"ES",
    "sg:address":"Calle de Mayor, S/n",
    "sg:city":"Llanes",
    "sg:orig_category":"Molduras, Junquillos, Listones Y Molduras Perforadas",
    "sg:phone":"+34 985 40 03 43",
    "sg:postcode":"33500",
    "sg:province":"Asturias",
    "wof:name":"Sociedad Regional De Informaticas.a.",
    "wof:placetype":"venue"
},
  "geometry": {"coordinates":[-4.7533707619,43.4208755493],"type":"Point"}
}