{
  "type": "Feature",
  "properties": {
    "iso:country":"ES",
    "sg:address":"Pl. Abastos, 76",
    "sg:city":"Llangreu",
    "sg:orig_category":"Reposter\u00cdas",
    "sg:phone":"+34 985 69 14 94",
    "sg:postcode":"33900",
    "sg:province":"Asturias",
    "wof:name":"Palacios Palacios Maria Isabel",
    "wof:placetype":"venue"
},
  "geometry": {"coordinates":[-5.6692090034,43.2883987427],"type":"Point"}
}