{
  "type": "Feature",
  "properties": {
    "iso:country":"ES",
    "sg:address":"Calle de Monteaveruelo, 52",
    "sg:city":"Sotolargo",
    "sg:orig_category":"Promotores Constructores",
    "sg:phone":"+34 949 33 87 33",
    "sg:postcode":"19176",
    "sg:province":"Guadalajara",
    "wof:name":"Construcciones Florencio Ojeda E Hijos S.l.",
    "wof:placetype":"venue"
},
  "geometry": {"coordinates":[-3.3053190708,40.6373710632],"type":"Point"}
}