{
  "type": "Feature",
  "properties": {
    "addr:full":"Calle de Mu\u00d1oz Torrero, 18 San Vicente Alcantara Badajoz 06500",
    "addr:housenumber":"18",
    "addr:postcode":"06500",
    "addr:street":"Calle De Mun\u0303Oz Torrero",
    "iso:country":"ES",
    "sg:address":"Calle de Mu\u00d1oz Torrero, 18",
    "sg:city":"San Vicente Alcantara",
    "sg:orig_category":"Frutas, Legumbres Frescas Y Tempranas (al Por Menor)",
    "sg:phone":"+34 924 41 08 52",
    "sg:postcode":"06500",
    "sg:province":"Badajoz",
    "wof:name":"Frutas Juaquin Mendoza S.l.",
    "wof:placetype":"venue"
},
  "geometry": {"coordinates":[-7.1407909393,39.3612632751],"type":"Point"}
}