{
  "type": "Feature",
  "properties": {
    "iso:country":"ES",
    "sg:address":"Bo Campo De La Iglesia, 405",
    "sg:city":"Viernoles",
    "sg:orig_category":"Poller\u00cda Y Caza (al Por Menor)",
    "sg:phone":"+34 942 89 20 45",
    "sg:postcode":"39315",
    "sg:province":"Cantabria",
    "wof:name":"Teran Cuevas Maria Jose",
    "wof:placetype":"venue"
},
  "geometry": {"coordinates":[-4.0522389412,43.3210792542],"type":"Point"}
}