{
  "type": "Feature",
  "properties": {
    "addr:full":"Ptda Del Mar, 6 Almassera Valencia 46132",
    "addr:housenumber":"6",
    "addr:postcode":"46132",
    "addr:street":"Ptda Del Mar",
    "iso:country":"ES",
    "sg:address":"Ptda Del Mar, 6",
    "sg:city":"Almassera",
    "sg:orig_category":"Ropa Para Beb\u00c9s Y Ni\u00d1os (confecci\u00d3n, Al Por Mayor)",
    "sg:phone":"+34 961 85 38 92",
    "sg:postcode":"46132",
    "sg:province":"Valencia",
    "wof:name":"Confecciones Paddy S. A.",
    "wof:placetype":"venue"
},
  "geometry": {"coordinates":[-0.3606239855,39.5143966675],"type":"Point"}
}