{
  "type": "Feature",
  "properties": {
    "iso:country":"ES",
    "sg:address":"Pla\u00c7 Esglesia, 10",
    "sg:city":"Estartit",
    "sg:orig_category":"Quincaller\u00cda (al Por Menor)",
    "sg:phone":"+34 972 75 03 51",
    "sg:postcode":"17258",
    "sg:province":"Girona",
    "wof:name":"Ferreteria Batlle S.c.",
    "wof:placetype":"venue"
},
  "geometry": {"coordinates":[3.1995449066,42.053730011],"type":"Point"}
}