{
  "type": "Feature",
  "properties": {
    "addr:full":"Calle de Conde De La Cimera, 2 Madrid Madrid 28040",
    "addr:housenumber":"2",
    "addr:postcode":"28040",
    "addr:street":"Calle De Conde De La Cimera",
    "iso:country":"ES",
    "sg:address":"Calle de Conde De La Cimera, 2",
    "sg:city":"Madrid",
    "sg:orig_category":"M\u00c9dicos: Psiquiatr\u00cda",
    "sg:phone":"+34 915 34 25 84",
    "sg:postcode":"28040",
    "sg:province":"Madrid",
    "wof:name":"Corrons Rodriguez Pedro",
    "wof:placetype":"venue"
},
  "geometry": {"coordinates":[-3.7142269611,40.4467811584],"type":"Point"}
}