{
  "type": "Feature",
  "properties": {
    "addr:full":"Carrer de Parellada (la), 14 Vilafranca Penedes Barcelona 08720",
    "addr:housenumber":"14",
    "addr:postcode":"08720",
    "addr:street":"Carrer De Parellada La;Penedes Barcelona",
    "iso:country":"ES",
    "sg:address":"Carrer de Parellada (la), 14",
    "sg:city":"Vilafranca Penedes",
    "sg:orig_category":"Perfumer\u00cda (al Por Menor)",
    "sg:phone":"+34 938 92 24 03",
    "sg:postcode":"08720",
    "sg:province":"Barcelona",
    "wof:name":"Marti Batlle Concepcio",
    "wof:placetype":"venue"
},
  "geometry": {"coordinates":[1.6990568638,41.3466529846],"type":"Point"}
}