{
  "type": "Feature",
  "properties": {
    "addr:full":"Plaz Cervantes, 9 Paiporta Valencia 46200",
    "addr:housenumber":"9",
    "addr:postcode":"46200",
    "addr:street":"Plaz Cervantes",
    "iso:country":"ES",
    "sg:address":"Plaz Cervantes, 9",
    "sg:city":"Paiporta",
    "sg:orig_category":"Carnicer\u00cdas, Carnicer\u00cdas",
    "sg:phone":"+34 963 97 25 15",
    "sg:postcode":"46200",
    "sg:province":"Valencia",
    "wof:name":"Baselga Villanueva Cristina",
    "wof:placetype":"venue"
},
  "geometry": {"coordinates":[-0.4185520113,39.4278335571],"type":"Point"}
}