{
  "type": "Feature",
  "properties": {
    "iso:country":"ES",
    "sg:address":"Calle de Mira El Sol, 3",
    "sg:city":"Madrid",
    "sg:orig_category":"Instalaci\u00d3n De Aspiraci\u00d3n De Gases Y Humos",
    "sg:phone":"+34 915 28 60 12",
    "sg:postcode":"28005",
    "sg:province":"Madrid",
    "wof:name":"Pemagas S.a.",
    "wof:placetype":"venue"
},
  "geometry": {"coordinates":[-3.704886198,40.4076652527],"type":"Point"}
}