{
  "type": "Feature",
  "properties": {
    "addr:full":"Carr Cristobal Sorni, 44 Burjassot Valencia 46100",
    "addr:housenumber":"44",
    "addr:postcode":"46100",
    "addr:street":"Carr Cristobal Sorni",
    "iso:country":"ES",
    "sg:address":"Carr Cristobal Sorni, 44",
    "sg:city":"Burjassot",
    "sg:classifiers":[
        {
            "category":"Personal",
            "subcategory":"Barber",
            "type":"Services"
        }
    ],
    "sg:phone":"+34 963 63 34 64",
    "sg:postcode":"46100",
    "sg:province":"Valencia",
    "sg:tags":[
        "caballeros",
        "de",
        "peluqueros"
    ],
    "wof:name":"Martinez Ruiz Jose Maria",
    "wof:placetype":"venue"
},
  "geometry": {"coordinates":[-0.4098280072,39.5056686401],"type":"Point"}
}