{
  "type": "Feature",
  "properties": {
    "addr:full":"Avgd Alacant, 6 Lleida Lleida 25001",
    "addr:housenumber":"6",
    "addr:postcode":"25001",
    "addr:street":"Alacant",
    "iso:country":"ES",
    "sg:address":"Avgd Alacant, 6",
    "sg:city":"Lleida",
    "sg:orig_category":"Molduras, Junquillos, Listones Y Molduras Perforadas",
    "sg:phone":"+34 973 20 51 15",
    "sg:postcode":"25001",
    "sg:province":"Lleida",
    "wof:name":"Pulido Rodriguez Antonio",
    "wof:placetype":"venue"
},
  "geometry": {"coordinates":[0.6322460175,41.6122283936],"type":"Point"}
}