{
  "type": "Feature",
  "properties": {
    "addr:full":"Calle de Emilio Thuillier, 76 Malaga M\u00e1laga 29014",
    "addr:housenumber":"76",
    "addr:postcode":"29014",
    "addr:street":"Calle De Emilio Thuillier;Ma\u0301Laga",
    "iso:country":"ES",
    "sg:address":"Calle de Emilio Thuillier, 76",
    "sg:city":"Malaga",
    "sg:orig_category":"Muebles, Minoristas",
    "sg:phone":"+34 952 25 90 16",
    "sg:postcode":"29014",
    "sg:province":"M\u00e1laga",
    "wof:name":"Marin Diaz Miguel Angel",
    "wof:placetype":"venue"
},
  "geometry": {"coordinates":[-4.4215869904,36.7456665039],"type":"Point"}
}