{
  "type": "Feature",
  "properties": {
    "iso:country":"ES",
    "sg:address":"Carrer de Pirineus, 193",
    "sg:city":"Sabadell",
    "sg:orig_category":"Carnicer\u00cdas, Carnicer\u00cdas",
    "sg:phone":"+34 937 17 34 70",
    "sg:postcode":"08208",
    "sg:province":"Barcelona",
    "wof:name":"Alvarez Prieto Angel",
    "wof:placetype":"venue"
},
  "geometry": {"coordinates":[2.1019515991,41.5603981018],"type":"Point"}
}