{
  "type": "Feature",
  "properties": {
    "iso:country":"ES",
    "sg:address":"Tres-los Sauces, S/n",
    "sg:city":"Olimar",
    "sg:orig_category":"Fabricaci\u00d3n De Taburetes, Sillas Y Sillones",
    "sg:phone":"+34 961 80 57 00",
    "sg:postcode":"46370",
    "sg:province":"Valencia",
    "sg:website":"www.andreuworld.com",
    "wof:name":"Andreu World S.a.",
    "wof:placetype":"venue"
},
  "geometry": {"coordinates":[-0.6216540933,39.4688835144],"type":"Point"}
}