{
  "type": "Feature",
  "properties": {
    "iso:country":"ES",
    "sg:address":"Cuesta Blanca, S/n",
    "sg:city":"Constantina",
    "sg:orig_category":"Negocio De Enlosados, Soler\u00cdas",
    "sg:phone":"+34 955 88 10 61",
    "sg:postcode":"41450",
    "sg:province":"Sevilla",
    "wof:name":"Pedro Toman Nieto S.c.",
    "wof:placetype":"venue"
},
  "geometry": {"coordinates":[-5.6196241379,37.8637313843],"type":"Point"}
}