{
  "type": "Feature",
  "properties": {
    "addr:full":"Calle de Batalla De Clavijo, 13 Le\u00f3n Le\u00f3n 24006",
    "addr:housenumber":"13",
    "addr:postcode":"24006",
    "addr:street":"Calle De Batalla De Clavijo;Leo\u0301N",
    "iso:country":"ES",
    "sg:address":"Calle de Batalla De Clavijo, 13",
    "sg:city":"Le\u00f3n",
    "sg:orig_category":"Inform\u00c1tica: Mantenimiento Y Reparaci\u00d3n De Ordenadores",
    "sg:phone":"+34 987 20 33 56",
    "sg:postcode":"24006",
    "sg:province":"Le\u00f3n",
    "wof:name":"Sanchez Ramos Lucio",
    "wof:placetype":"venue"
},
  "geometry": {"coordinates":[-5.5617852211,42.5961303711],"type":"Point"}
}