{
  "type": "Feature",
  "properties": {
    "iso:country":"ES",
    "sg:address":"Calle de Doctor Fleming, 17",
    "sg:city":"Castellon",
    "sg:orig_category":"Carnicer\u00cdas, Carnicer\u00cdas",
    "sg:phone":"+34 964 23 67 18",
    "sg:postcode":"12005",
    "sg:province":"Castell\u00f3n",
    "wof:name":"Roca Beltran Juan Isidro",
    "wof:placetype":"venue"
},
  "geometry": {"coordinates":[-0.033832401,39.9797515869],"type":"Point"}
}