{
  "type": "Feature",
  "properties": {
    "addr:full":"Carr Font (la), 27 Bellpuig Lleida 25250",
    "addr:housenumber":"27",
    "addr:postcode":"25250",
    "addr:street":"Carr Font La",
    "iso:country":"ES",
    "sg:address":"Carr Font (la), 27",
    "sg:city":"Bellpuig",
    "sg:orig_category":"Fabricaci\u00d3n De Harinas, S\u00c9molas, Productos De Elaboraci\u00d3n Del Grano",
    "sg:phone":"+34 973 32 02 86",
    "sg:postcode":"25250",
    "sg:province":"Lleida",
    "wof:name":"La Preferida S. A.",
    "wof:placetype":"venue"
},
  "geometry": {"coordinates":[1.0088200569,41.6270713806],"type":"Point"}
}