{
  "type": "Feature",
  "properties": {
    "iso:country":"ES",
    "sg:address":"Avda Oasis, 154",
    "sg:city":"Ejido",
    "sg:orig_category":"\u00d3ptica: Instrumentos (fabricaci\u00d3n)",
    "sg:phone":"+34 950 48 64 68",
    "sg:postcode":"04700",
    "sg:province":"Almer\u00eda",
    "wof:name":"Medina Estevez Rosa",
    "wof:placetype":"venue"
},
  "geometry": {"coordinates":[-2.8010590076,36.7683181763],"type":"Point"}
}