{
  "type": "Feature",
  "properties": {
    "addr:full":"Carrer de Rosa De Alejandria, 48 Hospitalet Llobregat Barcelona 08906",
    "addr:housenumber":"48",
    "addr:postcode":"08906",
    "addr:street":"Carrer De Rosa De Alejandria",
    "iso:country":"ES",
    "sg:address":"Carrer de Rosa De Alejandria, 48",
    "sg:city":"Hospitalet Llobregat",
    "sg:orig_category":"Bazares, Art\u00cdculos De Limpieza Y De Cocina (al Por Menor)",
    "sg:phone":"+34 934 37 10 61",
    "sg:postcode":"08906",
    "sg:province":"Barcelona",
    "sg:website":"www.bazarelregalo.es",
    "wof:name":"Agrupacion Bazar El Regalo S.a.",
    "wof:placetype":"venue"
},
  "geometry": {"coordinates":[2.1018998623,41.3707618713],"type":"Point"}
}