{
  "type": "Feature",
  "properties": {
    "addr:full":"Calle de Zirilo Arzubiaga, 11 Amorebieta Vizcaya 48340",
    "addr:housenumber":"11",
    "addr:postcode":"48340",
    "addr:street":"Calle De Zirilo Arzubiaga",
    "iso:country":"ES",
    "sg:address":"Calle de Zirilo Arzubiaga, 11",
    "sg:city":"Amorebieta",
    "sg:orig_category":"Transporte En General",
    "sg:phone":"+34 946 73 04 70",
    "sg:postcode":"48340",
    "sg:province":"Vizcaya",
    "wof:name":"Arteche Ere\u00f1o Lucio",
    "wof:placetype":"venue"
},
  "geometry": {"coordinates":[-2.7346496582,43.2199401855],"type":"Point"}
}