{
  "type": "Feature",
  "properties": {
    "iso:country":"ES",
    "sg:address":"Avda Gran Via, 77",
    "sg:city":"Vigo",
    "sg:orig_category":"Guarder\u00cdas",
    "sg:phone":"+34 986 42 38 30",
    "sg:postcode":"36204",
    "sg:province":"Pontevedra",
    "wof:name":"Rapaci\u00f1os Tres S L",
    "wof:placetype":"venue"
},
  "geometry": {"coordinates":[-8.7203235626,42.2273902893],"type":"Point"}
}