{
  "type": "Feature",
  "properties": {
    "addr:full":"Carr Vicente Boix, 10 Xativa Valencia 46800",
    "addr:housenumber":"10",
    "addr:postcode":"46800",
    "addr:street":"Carr Vicente Boix",
    "iso:country":"ES",
    "sg:address":"Carr Vicente Boix, 10",
    "sg:city":"Xativa",
    "sg:orig_category":"Poller\u00cda Y Caza (al Por Menor)",
    "sg:phone":"+34 962 27 00 40",
    "sg:postcode":"46800",
    "sg:province":"Valencia",
    "wof:name":"Mompo Burches Eva",
    "wof:placetype":"venue"
},
  "geometry": {"coordinates":[-0.5247690082,38.9905586243],"type":"Point"}
}