{
  "type": "Feature",
  "properties": {
    "iso:country":"ES",
    "sg:address":"Plaz Mayor, 24",
    "sg:city":"Burgos",
    "sg:orig_category":"Ropa Para Se\u00d1oras (al Por Menor)",
    "sg:phone":"+34 947 20 31 46",
    "sg:postcode":"09003",
    "sg:province":"Burgos",
    "sg:website":"www.benetton.com",
    "wof:name":"Perez Solana Julio",
    "wof:placetype":"venue"
},
  "geometry": {"coordinates":[-3.7009689808,42.3413505554],"type":"Point"}
}