{
  "type": "Feature",
  "properties": {
    "addr:full":"Carrer de Miquel Servet, 40 Manresa Barcelona 08243",
    "addr:housenumber":"40",
    "addr:postcode":"08243",
    "addr:street":"Carrer De Miquel Servet",
    "iso:country":"ES",
    "sg:address":"Carrer de Miquel Servet, 40",
    "sg:city":"Manresa",
    "sg:orig_category":"Muebles",
    "sg:phone":"+34 938 78 48 10",
    "sg:postcode":"08243",
    "sg:province":"Barcelona",
    "sg:website":"www.rafemar.com",
    "wof:name":"Rafemar S. A.",
    "wof:placetype":"venue"
},
  "geometry": {"coordinates":[1.8471440077,41.7107543945],"type":"Point"}
}