{
  "type": "Feature",
  "properties": {
    "addr:full":"Calle de Tantin, 27 Santander Cantabria 39001",
    "addr:housenumber":"27",
    "addr:postcode":"39001",
    "addr:street":"Calle De Tantin",
    "iso:country":"ES",
    "sg:address":"Calle de Tantin, 27",
    "sg:city":"Santander",
    "sg:orig_category":"Obras Y Organismos Sociales",
    "sg:phone":"+34 942 21 19 63",
    "sg:postcode":"39001",
    "sg:province":"Cantabria",
    "wof:name":"Hijas De La Caridad De San Vicente De Paul",
    "wof:placetype":"venue"
},
  "geometry": {"coordinates":[-3.8051381111,43.4644851685],"type":"Point"}
}