{
  "type": "Feature",
  "properties": {
    "addr:full":"Avda Tres De Agosto, 72 Aspe Alicante 03680",
    "addr:housenumber":"72",
    "addr:postcode":"03680",
    "addr:street":"Avda Tres De Agosto",
    "iso:country":"ES",
    "sg:address":"Avda Tres De Agosto, 72",
    "sg:city":"Aspe",
    "sg:orig_category":"Zapater\u00cdas",
    "sg:phone":"+34 965 49 41 38",
    "sg:postcode":"03680",
    "sg:province":"Alicante",
    "wof:name":"Mejias Simon Joaquim",
    "wof:placetype":"venue"
},
  "geometry": {"coordinates":[-0.775323987,38.3406028748],"type":"Point"}
}