{
  "type": "Feature",
  "properties": {
    "iso:country":"ES",
    "sg:address":"Calle de Francisco Oliver, S/n",
    "sg:city":"Mazarron",
    "sg:orig_category":"Venta, Montaje De Neum\u00c1ticos",
    "sg:phone":"+34 968 59 17 05",
    "sg:postcode":"30870",
    "sg:province":"Murcia",
    "wof:name":"Ortiz Mendez Fernando",
    "wof:placetype":"venue"
},
  "geometry": {"coordinates":[-1.3110840321,37.5964508057],"type":"Point"}
}