{
  "type": "Feature",
  "properties": {
    "addr:full":"Calle de Valdes, 9 Alacant Alicante 03001",
    "addr:housenumber":"9",
    "addr:postcode":"03001",
    "addr:street":"Calle De Valdes",
    "iso:country":"ES",
    "sg:address":"Calle de Valdes, 9",
    "sg:city":"Alacant",
    "sg:orig_category":"Restaurantes",
    "sg:phone":"+34 965 20 63 99",
    "sg:postcode":"03001",
    "sg:province":"Alicante",
    "wof:name":"Ramirez Martinez Bartolome",
    "wof:placetype":"venue"
},
  "geometry": {"coordinates":[-0.4859809875,38.3431167603],"type":"Point"}
}