{
  "type": "Feature",
  "properties": {
    "addr:full":"Rbla Carme, 31 Vic Barcelona 08500",
    "addr:housenumber":"31",
    "addr:postcode":"08500",
    "addr:street":"Rbla Carme",
    "iso:country":"ES",
    "sg:address":"Rbla Carme, 31",
    "sg:city":"Vic",
    "sg:orig_category":"Peluqueros: De Se\u00d1oras",
    "sg:phone":"+34 938 86 08 18",
    "sg:postcode":"08500",
    "sg:province":"Barcelona",
    "wof:name":"Bayot Gol Maria Rosa",
    "wof:placetype":"venue"
},
  "geometry": {"coordinates":[2.2548649311,41.9313583374],"type":"Point"}
}