{
  "type": "Feature",
  "properties": {
    "addr:full":"Psaj Jerez, S/n Pizarra M\u00e1laga 29560",
    "addr:housenumber":"s / n",
    "addr:postcode":"29560",
    "iso:country":"ES",
    "sg:address":"Psaj Jerez, S/n",
    "sg:city":"Pizarra",
    "sg:orig_category":"Sociedades, Compa\u00d1\u00cdas Aseguradoras",
    "sg:phone":"+34 952 48 45 45",
    "sg:postcode":"29560",
    "sg:province":"M\u00e1laga",
    "wof:name":"Mapfre Servicios De Informatica",
    "wof:placetype":"venue"
},
  "geometry": {"coordinates":[-4.7082672119,36.7690505981],"type":"Point"}
}