{
  "type": "Feature",
  "properties": {
    "iso:country":"ES",
    "sg:address":"Pol Ind La Pe\u00f1a, 10",
    "sg:city":"Algarrobo",
    "sg:orig_category":"Torrefactado De Caf\u00c9",
    "sg:phone":"+34 952 55 20 43",
    "sg:postcode":"29750",
    "sg:province":"M\u00e1laga",
    "wof:name":"Cafes Santa Gema S.l.",
    "wof:placetype":"venue"
},
  "geometry": {"coordinates":[-4.038918972,36.7717437744],"type":"Point"}
}