{
  "type": "Feature",
  "properties": {
    "iso:country":"ES",
    "sg:address":"Plaz Fueros, 1",
    "sg:city":"S. Adrian",
    "sg:orig_category":"Establecimientos De Cura, Prevenci\u00d3n Y Readaptaci\u00d3n",
    "sg:phone":"+34 948 67 06 94",
    "sg:postcode":"31570",
    "sg:province":"Navarra",
    "wof:name":"El Marinal",
    "wof:placetype":"venue"
},
  "geometry": {"coordinates":[-1.9321240187,42.33335495],"type":"Point"}
}