{
  "type": "Feature",
  "properties": {
    "iso:country":"ES",
    "sg:address":"Rey Alfonso Xiii, 16",
    "sg:city":"Torrejon Rubio",
    "sg:orig_category":"Negocio De Materiales De Construcci\u00d3n",
    "sg:phone":"+34 927 45 50 11",
    "sg:postcode":"10694",
    "sg:province":"C\u00e1ceres",
    "wof:name":"Izquierdo Santiago Damian",
    "wof:placetype":"venue"
},
  "geometry": {"coordinates":[-6.3707604408,39.4761772156],"type":"Point"}
}