{
  "type": "Feature",
  "properties": {
    "addr:full":"Carrer de Setze De Juliol, 29 Poligon Industrial De Son Castello Islas Baleares 07009",
    "addr:housenumber":"29",
    "addr:postcode":"07009",
    "addr:street":"Carrer De Setze De Juliol;Islas",
    "iso:country":"ES",
    "sg:address":"Carrer de Setze De Juliol, 29",
    "sg:city":"Poligon Industrial De Son Castello",
    "sg:orig_category":"Molduras, Junquillos, Listones Y Molduras Perforadas",
    "sg:phone":"+34 971 20 84 06",
    "sg:postcode":"07009",
    "sg:province":"Islas Baleares",
    "wof:name":"Company Martinez Juan Miguel",
    "wof:placetype":"venue"
},
  "geometry": {"coordinates":[2.6776249409,39.6072845459],"type":"Point"}
}