{
  "type": "Feature",
  "properties": {
    "addr:full":"Ctra Leioa-unbe Errepidea Erandio Vizcaya 48950",
    "addr:postcode":"48950",
    "addr:street":"Ctra Leioa-Unbe Errepidea",
    "iso:country":"ES",
    "sg:address":"Ctra Leioa-unbe Errepidea",
    "sg:city":"Erandio",
    "sg:orig_category":"Fotocopias, Reprograf\u00cda",
    "sg:phone":"+34 944 17 01 14",
    "sg:postcode":"48950",
    "sg:province":"Vizcaya",
    "wof:name":"Kopiak S.a.",
    "wof:placetype":"venue"
},
  "geometry": {"coordinates":[-2.944439888,43.3259849548],"type":"Point"}
}