{
  "type": "Feature",
  "properties": {
    "iso:country":"ES",
    "sg:address":"Calle de Fuente Del Rio, 3",
    "sg:city":"Arcos Frontera",
    "sg:orig_category":"Artes Gr\u00c1ficas, Artes Pl\u00c1sticas (curso)",
    "sg:phone":"+34 956 70 34 44",
    "sg:postcode":"11630",
    "sg:province":"C\u00e1diz",
    "wof:name":"Sanchez Jimenez Francisco Javier",
    "wof:placetype":"venue"
},
  "geometry": {"coordinates":[-5.8115739822,36.7515716553],"type":"Point"}
}