{
  "type": "Feature",
  "properties": {
    "iso:country":"ES",
    "sg:address":"Calle de Lopez De Ayala, 31",
    "sg:city":"Montijo",
    "sg:orig_category":"Limpieza Industrial",
    "sg:phone":"+34 924 45 05 93",
    "sg:postcode":"06480",
    "sg:province":"Badajoz",
    "wof:name":"Montes Gragera Maria",
    "wof:placetype":"venue"
},
  "geometry": {"coordinates":[-6.6142787933,38.9098892212],"type":"Point"}
}