{
  "type": "Feature",
  "properties": {
    "addr:full":"Calle de Varela Silvari, 27 Coru\u00d1a La Coru\u00f1a 15001",
    "addr:housenumber":"27",
    "addr:postcode":"15001",
    "addr:street":"Calle De Varela Silvari;La Corun\u0303A",
    "iso:country":"ES",
    "sg:address":"Calle de Varela Silvari, 27",
    "sg:city":"Coru\u00d1a",
    "sg:orig_category":"Tapicer\u00cdas",
    "sg:phone":"+34 981 20 86 53",
    "sg:postcode":"15001",
    "sg:province":"La Coru\u00f1a",
    "wof:name":"Eiroa Parga Gonzalo",
    "wof:placetype":"venue"
},
  "geometry": {"coordinates":[-8.3974599838,43.3725776672],"type":"Point"}
}