{
  "type": "Feature",
  "properties": {
    "iso:country":"ES",
    "sg:address":"Calle de Tomas Edison, 19",
    "sg:city":"Zaragoza",
    "sg:orig_category":"Maquinaria Neum\u00c1tica",
    "sg:phone":"+34 976 47 14 70",
    "sg:postcode":"50014",
    "sg:province":"Zaragoza",
    "sg:website":"www.enar.es",
    "wof:name":"Enarco S. A.",
    "wof:placetype":"venue"
},
  "geometry": {"coordinates":[-0.8656979799,41.6671943665],"type":"Point"}
}