{
  "type": "Feature",
  "properties": {
    "addr:full":"Calle de Islas Cies, 63 Madrid Madrid 28035",
    "addr:housenumber":"63",
    "addr:postcode":"madrid;28035",
    "addr:street":"Calle De Islas Cies",
    "iso:country":"ES",
    "sg:address":"Calle de Islas Cies, 63",
    "sg:city":"Madrid",
    "sg:orig_category":"Cervecer\u00cdas",
    "sg:phone":"+34 917 30 12 13",
    "sg:postcode":"28035",
    "sg:province":"Madrid",
    "wof:name":"De Las Heras Rodriguez Cirilo",
    "wof:placetype":"venue"
},
  "geometry": {"coordinates":[-3.7212510109,40.4794807434],"type":"Point"}
}