{
  "type": "Feature",
  "properties": {
    "addr:full":"Calle de Cuenca, 38 Valencia Valencia 46007",
    "addr:housenumber":"38",
    "addr:postcode":"46007",
    "addr:street":"Calle De Cuenca",
    "iso:country":"ES",
    "sg:address":"Calle de Cuenca, 38",
    "sg:city":"Valencia",
    "sg:orig_category":"Heladeros",
    "sg:phone":"+34 963 85 30 34",
    "sg:postcode":"46007",
    "sg:province":"Valencia",
    "wof:name":"Soriano Garcia Pedro",
    "wof:placetype":"venue"
},
  "geometry": {"coordinates":[-0.385792613,39.4673080444],"type":"Point"}
}