{
  "type": "Feature",
  "properties": {
    "iso:country":"ES",
    "sg:address":"Calle de Regina, 11",
    "sg:city":"Sevilla",
    "sg:orig_category":"Molduras, Junquillos, Listones Y Molduras Perforadas",
    "sg:phone":"+34 954 21 69 90",
    "sg:postcode":"41003",
    "sg:province":"Sevilla",
    "wof:name":"Carpio Rio Manuel Carmelo",
    "wof:placetype":"venue"
},
  "geometry": {"coordinates":[-5.9915819168,37.3950004578],"type":"Point"}
}