{
  "type": "Feature",
  "properties": {
    "iso:country":"ES",
    "sg:address":"Avda Paz (de La), 13",
    "sg:city":"Burgos",
    "sg:orig_category":"Asesor\u00cda Sobre Comunicaci\u00d3n De Empresas",
    "sg:phone":"+34 947 23 08 07",
    "sg:postcode":"09004",
    "sg:province":"Burgos",
    "wof:name":"Rafael Zamora Sl",
    "wof:placetype":"venue"
},
  "geometry": {"coordinates":[-3.6936759949,42.3447647095],"type":"Point"}
}