{
  "type": "Feature",
  "properties": {
    "iso:country":"ES",
    "sg:address":"Rua Cuba, 11",
    "sg:city":"Vigo",
    "sg:orig_category":"Confecci\u00d3n De Trajes Para Se\u00d1oras",
    "sg:phone":"+34 986 41 80 17",
    "sg:postcode":"36204",
    "sg:province":"Pontevedra",
    "wof:name":"Ger Blusas C.b.",
    "wof:placetype":"venue"
},
  "geometry": {"coordinates":[-8.7162942886,42.2328796387],"type":"Point"}
}