{
  "type": "Feature",
  "properties": {
    "addr:full":"Calle de Prim, 26 Daimiel Ciudad Real 13250",
    "addr:housenumber":"26",
    "addr:postcode":"13250",
    "addr:street":"Calle De Prim",
    "iso:country":"ES",
    "sg:address":"Calle de Prim, 26",
    "sg:city":"Daimiel",
    "sg:orig_category":"Organizaciones Internacionales",
    "sg:phone":"+34 926 85 53 98",
    "sg:postcode":"13250",
    "sg:province":"Ciudad Real",
    "wof:name":"Asociacion De Mujeres Y Familias De Ambito Rural",
    "wof:placetype":"venue"
},
  "geometry": {"coordinates":[-3.6102907658,39.0696105957],"type":"Point"}
}