{
  "type": "Feature",
  "properties": {
    "iso:country":"ES",
    "sg:address":"Calle de Primero De Mayo, 62",
    "sg:city":"Pe\u00d1acastillo",
    "sg:orig_category":"Farmacias",
    "sg:phone":"+34 942 32 52 93",
    "sg:postcode":"39011",
    "sg:province":"Cantabria",
    "wof:name":"Sarabia Cervera Jose Ramon",
    "wof:placetype":"venue"
},
  "geometry": {"coordinates":[-3.8739891052,43.4491386414],"type":"Point"}
}