{
  "type": "Feature",
  "properties": {
    "addr:full":"Rambla La Gitana, S/n Aguadulce Almer\u00eda 04720",
    "addr:housenumber":"s / n",
    "addr:postcode":"04720",
    "addr:street":"Gitana;Almeri\u0301A",
    "iso:country":"ES",
    "sg:address":"Rambla La Gitana, S/n",
    "sg:city":"Aguadulce",
    "sg:orig_category":"Teatros Y Salas De Espect\u00c1culos",
    "sg:phone":"+34 950 34 14 06",
    "sg:postcode":"04720",
    "sg:province":"Almer\u00eda",
    "wof:name":"Sintagno S.l.",
    "wof:placetype":"venue"
},
  "geometry": {"coordinates":[-2.5653889179,36.8148078918],"type":"Point"}
}