{
  "type": "Feature",
  "properties": {
    "addr:full":"Ctra. Castro Del Rio, Km. 0001,5 Cabra C\u00f3rdoba 14940",
    "addr:postcode":"14940",
    "addr:street":"Ctra. Castro Del Rio Km. 0001,5",
    "iso:country":"ES",
    "sg:address":"Ctra. Castro Del Rio, Km. 0001,5",
    "sg:city":"Cabra",
    "sg:orig_category":"Empresas De Carpinter\u00cda Met\u00c1lica",
    "sg:phone":"+34 957 52 42 11",
    "sg:postcode":"14940",
    "sg:province":"C\u00f3rdoba",
    "wof:name":"Melametal S.l.",
    "wof:placetype":"venue"
},
  "geometry": {"coordinates":[-4.4467329979,37.4725837708],"type":"Point"}
}