{
  "type": "Feature",
  "properties": {
    "addr:full":"Calle de Donoso Cortes, 25 Caceres C\u00e1ceres 10003",
    "addr:housenumber":"25",
    "addr:postcode":"10003",
    "addr:street":"Calle De Donoso Cortes;Ca\u0301Ceres",
    "iso:country":"ES",
    "sg:address":"Calle de Donoso Cortes, 25",
    "sg:city":"Caceres",
    "sg:orig_category":"Asesor\u00cda Fiscal Y Jur\u00cddica",
    "sg:phone":"+34 927 22 18 86",
    "sg:postcode":"10003",
    "sg:province":"C\u00e1ceres",
    "wof:name":"Dd Economistas Colegiados S.l.",
    "wof:placetype":"venue"
},
  "geometry": {"coordinates":[-6.374671936,39.4730491638],"type":"Point"}
}