{
  "type": "Feature",
  "properties": {
    "addr:full":"Pase Delicias, 71 Madrid Madrid 28045",
    "addr:housenumber":"71",
    "addr:postcode":"madrid;28045",
    "addr:street":"Delicias",
    "iso:country":"ES",
    "sg:address":"Pase Delicias, 71",
    "sg:city":"Madrid",
    "sg:orig_category":"Molduras, Junquillos, Listones Y Molduras Perforadas",
    "sg:phone":"+34 915 27 17 72",
    "sg:postcode":"28045",
    "sg:province":"Madrid",
    "wof:name":"Frejo Garcia Juan Antonio",
    "wof:placetype":"venue"
},
  "geometry": {"coordinates":[-3.6942009926,40.3972816467],"type":"Point"}
}