{
  "type": "Feature",
  "properties": {
    "iso:country":"ES",
    "sg:address":"Calle de Amaya, S/n",
    "sg:city":"Arevalo",
    "sg:orig_category":"Arquitectos",
    "sg:phone":"+34 920 30 12 93",
    "sg:postcode":"05200",
    "sg:province":"\u00c1vila",
    "wof:name":"Mostaza Mu\u00f1oz Mariano",
    "wof:placetype":"venue"
},
  "geometry": {"coordinates":[-4.71296978,41.0518226624],"type":"Point"}
}