{
  "type": "Feature",
  "properties": {
    "iso:country":"ES",
    "sg:address":"Carr Hannover, 11",
    "sg:city":"Mao",
    "sg:orig_category":"Ropa Y Accesorios",
    "sg:phone":"+34 971 36 18 24",
    "sg:postcode":"07703",
    "sg:province":"Islas Baleares",
    "wof:name":"Navarro Gonzalez Domingo",
    "wof:placetype":"venue"
},
  "geometry": {"coordinates":[4.265625,39.8903694153],"type":"Point"}
}