{
  "type": "Feature",
  "properties": {
    "addr:full":"Calle de Francisco Azorin, 10 Yecla Murcia 30510",
    "addr:housenumber":"10",
    "addr:postcode":"30510",
    "addr:street":"Calle De Francisco Azorin",
    "iso:country":"ES",
    "sg:address":"Calle de Francisco Azorin, 10",
    "sg:city":"Yecla",
    "sg:orig_category":"Cer\u00c1micas: Material Y Suministros",
    "sg:phone":"+34 968 75 10 07",
    "sg:postcode":"30510",
    "sg:province":"Murcia",
    "wof:name":"Rodriguez Ramon Angel",
    "wof:placetype":"venue"
},
  "geometry": {"coordinates":[-1.1185569763,38.615486145],"type":"Point"}
}