{
  "type": "Feature",
  "properties": {
    "iso:country":"ES",
    "sg:address":"Calle de Nogal (el), 10",
    "sg:city":"Cordoba",
    "sg:orig_category":"Muebles, Minoristas",
    "sg:phone":"+34 957 27 84 03",
    "sg:postcode":"14006",
    "sg:province":"C\u00f3rdoba",
    "wof:name":"Nuype S.l.",
    "wof:placetype":"venue"
},
  "geometry": {"coordinates":[-4.7836790085,37.8962440491],"type":"Point"}
}