{
  "type": "Feature",
  "properties": {
    "iso:country":"ES",
    "sg:address":"Calle de Dalia (de La), 14",
    "sg:city":"Alcobendas",
    "sg:orig_category":"Asesores De Gesti\u00d3n Del Patrimonio",
    "sg:phone":"+34 916 25 00 08",
    "sg:postcode":"28109",
    "sg:province":"Madrid",
    "wof:name":"Explotaciones Urbanas Enrique Granados S. A.",
    "wof:placetype":"venue"
},
  "geometry": {"coordinates":[-3.645876646,40.5193138123],"type":"Point"}
}