{
  "type": "Feature",
  "properties": {
    "iso:country":"ES",
    "sg:address":"Av Josep Tarradellas, 61",
    "sg:city":"Barcelona",
    "sg:orig_category":"Molduras, Junquillos, Listones Y Molduras Perforadas",
    "sg:phone":"+34 934 10 30 67",
    "sg:postcode":"08029",
    "sg:province":"Barcelona",
    "wof:name":"Vi\u00f1as Herrero Silvia",
    "wof:placetype":"venue"
},
  "geometry": {"coordinates":[2.1424109936,41.3854293823],"type":"Point"}
}