{
  "type": "Feature",
  "properties": {
    "iso:country":"ES",
    "sg:address":"Carrer de Olot, 22",
    "sg:city":"Vic",
    "sg:orig_category":"Construcci\u00d3n Mec\u00c1nica",
    "sg:phone":"+34 938 86 14 21",
    "sg:postcode":"08500",
    "sg:province":"Barcelona",
    "wof:name":"Frestorn Sociedad Cooperativa Catalana Limitada",
    "wof:placetype":"venue"
},
  "geometry": {"coordinates":[2.2577140331,41.9473457336],"type":"Point"}
}