{
  "type": "Feature",
  "properties": {
    "addr:full":"Avda Castelao, 21 Vigo Pontevedra 36209",
    "addr:housenumber":"21",
    "addr:postcode":"36209",
    "addr:street":"Avda Castelao",
    "iso:country":"ES",
    "sg:address":"Avda Castelao, 21",
    "sg:city":"Vigo",
    "sg:orig_category":"Confecci\u00d3n De Trajes Para Se\u00d1oras",
    "sg:phone":"+34 986 20 79 96",
    "sg:postcode":"36209",
    "sg:province":"Pontevedra",
    "wof:name":"Rey Santiago Jose Manuel",
    "wof:placetype":"venue"
},
  "geometry": {"coordinates":[-8.7370710373,42.2195243835],"type":"Point"}
}