{
  "type": "Feature",
  "properties": {
    "addr:full":"Calle de Santa Teresa, 11 Novallas Zaragoza 50510",
    "addr:housenumber":"11",
    "addr:postcode":"50510",
    "addr:street":"Calle De Santa Teresa",
    "iso:country":"ES",
    "sg:address":"Calle de Santa Teresa, 11",
    "sg:city":"Novallas",
    "sg:orig_category":"Doctores En Medicina",
    "sg:phone":"+34 976 19 80 71",
    "sg:postcode":"50510",
    "sg:province":"Zaragoza",
    "wof:name":"Aguado Ullate Crispin",
    "wof:placetype":"venue"
},
  "geometry": {"coordinates":[-1.6957616806,41.9458427429],"type":"Point"}
}