{
  "type": "Feature",
  "properties": {
    "iso:country":"ES",
    "sg:address":"Carrer de Santa Clara, 12",
    "sg:city":"Vilafranca Penedes",
    "sg:orig_category":"Abogados",
    "sg:phone":"+34 938 92 34 35",
    "sg:postcode":"08720",
    "sg:province":"Barcelona",
    "wof:name":"Bufet Prp Advocats Associats",
    "wof:placetype":"venue"
},
  "geometry": {"coordinates":[1.7016459703,41.3464355469],"type":"Point"}
}