{
  "type": "Feature",
  "properties": {
    "addr:full":"Calle de Jose Sanchez Rubio, 5 Torrelodones Madrid 28250",
    "addr:housenumber":"5",
    "addr:postcode":"28250",
    "addr:street":"Calle De Jose Sanchez Rubio",
    "iso:country":"ES",
    "sg:address":"Calle de Jose Sanchez Rubio, 5",
    "sg:city":"Torrelodones",
    "sg:orig_category":"Ense\u00d1anza: Idiomas",
    "sg:phone":"+34 918 59 47 97",
    "sg:postcode":"28250",
    "sg:province":"Madrid",
    "sg:website":"www.alida-lc.com",
    "wof:name":"Alida Language Center S.l.",
    "wof:placetype":"venue"
},
  "geometry": {"coordinates":[-3.9280967712,40.5779418945],"type":"Point"}
}