{
  "type": "Feature",
  "properties": {
    "addr:full":"Calle de Tremedal, 81 Alcala De Xivert Castell\u00f3n 12570",
    "addr:housenumber":"81",
    "addr:postcode":"12570",
    "addr:street":"Calle De Tremedal",
    "iso:country":"ES",
    "sg:address":"Calle de Tremedal, 81",
    "sg:city":"Alcala De Xivert",
    "sg:orig_category":"Carnicer\u00cdas, Carnicer\u00cdas",
    "sg:phone":"+34 964 41 01 48",
    "sg:postcode":"12570",
    "sg:province":"Castell\u00f3n",
    "wof:name":"A\u00f1o Vinuesa Armando",
    "wof:placetype":"venue"
},
  "geometry": {"coordinates":[0.2199818939,40.3037719727],"type":"Point"}
}