{
  "type": "Feature",
  "properties": {
    "iso:country":"ES",
    "sg:address":"Calle de Estacion, 90",
    "sg:city":"Miranda Ebro",
    "sg:orig_category":"Tubos Y Tuber\u00cdas De Goma Y Pl\u00c1stico (fabricaci\u00d3n, Al Por Mayor)",
    "sg:phone":"+34 947 34 70 91",
    "sg:postcode":"09200",
    "sg:province":"Burgos",
    "wof:name":"Alvahidraulica S.l.l.",
    "wof:placetype":"venue"
},
  "geometry": {"coordinates":[-2.9441018105,42.6877479553],"type":"Point"}
}