{
  "type": "Feature",
  "properties": {
    "addr:full":"Carrer de Mas Casanovas, 12 Barcelona Barcelona 08025",
    "addr:housenumber":"12",
    "addr:postcode":"08025",
    "addr:street":"Carrer De Mas Casanovas",
    "iso:country":"ES",
    "sg:address":"Carrer de Mas Casanovas, 12",
    "sg:city":"Barcelona",
    "sg:orig_category":"M\u00c9dicos: Gastroenterolog\u00cda Y Hepatolog\u00cda (aparato Digestivo)",
    "sg:phone":"+34 934 55 67 37",
    "sg:postcode":"08025",
    "sg:province":"Barcelona",
    "wof:name":"Adi Adham Wael",
    "wof:placetype":"venue"
},
  "geometry": {"coordinates":[2.1686513424,41.4115638733],"type":"Point"}
}