{
  "type": "Feature",
  "properties": {
    "iso:country":"ES",
    "sg:address":"Agustin Leitza Kalea, 11",
    "sg:city":"Andoain",
    "sg:classifiers":[
        {
            "category":"Autos & Motor Vehicles",
            "subcategory":"Automobile Sales",
            "type":"Retail Goods"
        }
    ],
    "sg:phone":"+34 943 30 06 04",
    "sg:postcode":"20140",
    "sg:province":"Guip\u00f9zcoa",
    "wof:name":"Martin Bengoechea Tejeria",
    "wof:placetype":"venue"
},
  "geometry": {"coordinates":[-2.0213959217,43.2198066711],"type":"Point"}
}