{
  "type": "Feature",
  "properties": {
    "iso:country":"ES",
    "sg:address":"Plaza De Espa\u00f1a, S/n",
    "sg:city":"Castilleja De Guzman",
    "sg:orig_category":"Administraciones Regionales, Departamentales Y Locales",
    "sg:phone":"+34 955 72 17 30",
    "sg:postcode":"41908",
    "sg:province":"Sevilla",
    "wof:name":"Ayuntamiento De Castilleja De Guzman",
    "wof:placetype":"venue"
},
  "geometry": {"coordinates":[-6.0615444183,37.3803787231],"type":"Point"}
}