{
  "type": "Feature",
  "properties": {
    "iso:country":"ES",
    "sg:address":"Calle de Bureba, 35",
    "sg:city":"Leganes",
    "sg:orig_category":"Zapatos (al Por Menor)",
    "sg:phone":"+34 916 88 16 56",
    "sg:postcode":"28915",
    "sg:province":"Madrid",
    "wof:name":"Sainz Madrigal Cristina",
    "wof:placetype":"venue"
},
  "geometry": {"coordinates":[-3.7502839565,40.3315544128],"type":"Point"}
}