{
  "type": "Feature",
  "properties": {
    "iso:country":"ES",
    "sg:address":"Avda Valencia, 103",
    "sg:city":"Gangosa",
    "sg:orig_category":"Maquinaria Para Industrias Diversas",
    "sg:phone":"+34 950 34 16 53",
    "sg:postcode":"04738",
    "sg:province":"Almer\u00eda",
    "sg:website":"www.mafroda.com",
    "wof:name":"Roda Iberica S.a.",
    "wof:placetype":"venue"
},
  "geometry": {"coordinates":[-2.6150989532,36.8059387207],"type":"Point"}
}