{
  "type": "Feature",
  "properties": {
    "iso:country":"ES",
    "sg:address":"Avda Eduardo Blanco Amor, 61",
    "sg:city":"Pontevedra",
    "sg:orig_category":"Ingeniero",
    "sg:phone":"+34 986 84 40 99",
    "sg:postcode":"36143",
    "sg:province":"Pontevedra",
    "wof:name":"Viveiros Acroa S.l.",
    "wof:placetype":"venue"
},
  "geometry": {"coordinates":[-8.6460371017,42.419708252],"type":"Point"}
}