{
  "type": "Feature",
  "properties": {
    "iso:country":"ES",
    "sg:address":"Avda Reina Sofia, 11",
    "sg:city":"Costa Ballena",
    "sg:orig_category":"Traductores",
    "sg:phone":"+34 956 84 73 09",
    "sg:postcode":"11520",
    "sg:province":"C\u00e1diz",
    "wof:name":"Absolute Translation Comercial Localization S.l.",
    "wof:placetype":"venue"
},
  "geometry": {"coordinates":[-6.407323,36.684402],"type":"Point"}
}