{
  "type": "Feature",
  "properties": {
    "addr:full":"Carr Corts Catalanes, 8 Lleida Lleida 25008",
    "addr:housenumber":"8",
    "addr:postcode":"25008",
    "addr:street":"Carr Corts Catalanes",
    "iso:country":"ES",
    "sg:address":"Carr Corts Catalanes, 8",
    "sg:city":"Lleida",
    "sg:orig_category":"Mec\u00c1nico Del Autom\u00d3vil",
    "sg:phone":"+34 973 24 85 02",
    "sg:postcode":"25008",
    "sg:province":"Lleida",
    "wof:name":"Talleres Tribal C. B",
    "wof:placetype":"venue"
},
  "geometry": {"coordinates":[0.6262230277,41.6244354248],"type":"Point"}
}