{
  "type": "Feature",
  "properties": {
    "iso:country":"ES",
    "sg:address":"Rua Arce, 17",
    "sg:city":"Ferrol",
    "sg:orig_category":"Deportes N\u00c1uticos, Acu\u00c1ticos Y Subacu\u00c1ticos: Art\u00cdculos Y Equipo (al Por Menor)",
    "sg:phone":"+34 981 35 01 78",
    "sg:postcode":"15401",
    "sg:province":"La Coru\u00f1a",
    "wof:name":"Merino Aguilera Maria De La Concepcion",
    "wof:placetype":"venue"
},
  "geometry": {"coordinates":[-8.2381467819,43.481880188],"type":"Point"}
}