{
  "type": "Feature",
  "properties": {
    "addr:full":"Calle de Ramiro I, 3 Piedras Blancas Asturias 33450",
    "addr:housenumber":"3",
    "addr:postcode":"33450",
    "addr:street":"Calle De Ramiro I",
    "iso:country":"ES",
    "sg:address":"Calle de Ramiro I, 3",
    "sg:city":"Piedras Blancas",
    "sg:orig_category":"Ense\u00d1anza: Profesiones Art\u00cdsticas",
    "sg:phone":"+34 985 53 24 48",
    "sg:postcode":"33450",
    "sg:province":"Asturias",
    "wof:name":"Quiros Garcia Sandalio",
    "wof:placetype":"venue"
},
  "geometry": {"coordinates":[-5.9748048782,43.5608024597],"type":"Point"}
}