{
  "type": "Feature",
  "properties": {
    "iso:country":"ES",
    "sg:address":"Calle de Olta, 60",
    "sg:city":"Valencia",
    "sg:orig_category":"Molduras, Junquillos, Listones Y Molduras Perforadas",
    "sg:phone":"+34 963 95 38 98",
    "sg:postcode":"46026",
    "sg:province":"Valencia",
    "wof:name":"Las Chicas De Oro C.b.",
    "wof:placetype":"venue"
},
  "geometry": {"coordinates":[-0.374774009,39.4528121948],"type":"Point"}
}