{
  "type": "Feature",
  "properties": {
    "addr:full":"Calle de Paredes (de), 17 Fuenlabrada Madrid 28946",
    "addr:housenumber":"17",
    "addr:postcode":"28946",
    "addr:street":"Calle De Paredes De",
    "iso:country":"ES",
    "sg:address":"Calle de Paredes (de), 17",
    "sg:city":"Fuenlabrada",
    "sg:orig_category":"Ense\u00d1anza: Profesiones Art\u00cdsticas",
    "sg:phone":"+34 916 90 49 02",
    "sg:postcode":"28946",
    "sg:province":"Madrid",
    "sg:website":"www.maestre.sew.es/",
    "wof:name":"Maestre Bernal Francisco",
    "wof:placetype":"venue"
},
  "geometry": {"coordinates":[-3.7725169659,40.2811927795],"type":"Point"}
}