{
  "type": "Feature",
  "properties": {
    "iso:country":"ES",
    "sg:address":"Avda Medina Del Campo, 17",
    "sg:city":"Valladolid",
    "sg:orig_category":"Farmacias",
    "sg:phone":"+34 983 22 07 99",
    "sg:postcode":"47014",
    "sg:province":"Valladolid",
    "wof:name":"Rua Barrios Maria Del Carmen",
    "wof:placetype":"venue"
},
  "geometry": {"coordinates":[-4.7476792336,41.633441925],"type":"Point"}
}