{
  "type": "Feature",
  "properties": {
    "iso:country":"ES",
    "sg:address":"Calle de Sierra Carbonera, 14",
    "sg:city":"Madrid",
    "sg:orig_category":"Entrega Y Recogida (servicios)",
    "sg:phone":"+34 914 78 41 12",
    "sg:postcode":"28053",
    "sg:province":"Madrid",
    "wof:name":"Campus Difusion C.b.",
    "wof:placetype":"venue"
},
  "geometry": {"coordinates":[-3.663615942,40.3933601379],"type":"Point"}
}