{
  "type": "Feature",
  "properties": {
    "addr:full":"Ctra Malaga (de), 110 Balanegra Almer\u00eda 04713",
    "addr:housenumber":"110",
    "addr:postcode":"04713",
    "addr:street":"Ctra Malaga De;Almeri\u0301A",
    "iso:country":"ES",
    "sg:address":"Ctra Malaga (de), 110",
    "sg:city":"Balanegra",
    "sg:orig_category":"Fabricaci\u00d3n De Distribuidores Autom\u00c1ticos",
    "sg:phone":"+34 950 48 17 04",
    "sg:postcode":"04713",
    "sg:province":"Almer\u00eda",
    "wof:name":"Ecofam Economia Familiar S.l.",
    "wof:placetype":"venue"
},
  "geometry": {"coordinates":[-2.9070239067,36.7499694824],"type":"Point"}
}