{
  "type": "Feature",
  "properties": {
    "addr:full":"Calle de Villaleal, 3 Catedral Murcia 30001",
    "addr:housenumber":"3",
    "addr:postcode":"30001",
    "addr:street":"Calle De Villaleal",
    "iso:country":"ES",
    "sg:address":"Calle de Villaleal, 3",
    "sg:city":"Catedral",
    "sg:orig_category":"Centros Empresariales",
    "sg:phone":"+34 968 35 50 40",
    "sg:postcode":"30001",
    "sg:province":"Murcia",
    "wof:name":"Fomento Empresarial De Murcia S.l.",
    "wof:placetype":"venue"
},
  "geometry": {"coordinates":[-1.1297049522,37.985294342],"type":"Point"}
}