{
  "type": "Feature",
  "properties": {
    "addr:full":"Avda Julio Rodriguez Soto, 20 Carballi\u00f1o Ourense 32500",
    "addr:housenumber":"20",
    "addr:postcode":"32500",
    "addr:street":"Avda Julio;Soto",
    "iso:country":"ES",
    "sg:address":"Avda Julio Rodriguez Soto, 20",
    "sg:city":"Carballi\u00f1o",
    "sg:orig_category":"Molduras, Junquillos, Listones Y Molduras Perforadas",
    "sg:phone":"+34 988 53 05 29",
    "sg:postcode":"32500",
    "sg:province":"Ourense",
    "wof:name":"Hermida Herrera Carla",
    "wof:placetype":"venue"
},
  "geometry": {"coordinates":[-8.0804815292,42.428894043],"type":"Point"}
}