{
  "type": "Feature",
  "properties": {
    "addr:full":"Av Isabel La Catolica, 83 Hospitalet Llobregat Barcelona 08906",
    "addr:housenumber":"83",
    "addr:postcode":"08906",
    "addr:street":"Av Isabel La Catolica",
    "iso:country":"ES",
    "sg:address":"Av Isabel La Catolica, 83",
    "sg:city":"Hospitalet Llobregat",
    "sg:orig_category":"Papel Pintado (al Por Menor)",
    "sg:phone":"+34 934 37 21 20",
    "sg:postcode":"08906",
    "sg:province":"Barcelona",
    "wof:name":"Guerrero Riquelme Eloi",
    "wof:placetype":"venue"
},
  "geometry": {"coordinates":[2.1038899422,41.3709220886],"type":"Point"}
}