{
  "type": "Feature",
  "properties": {
    "addr:full":"Carrer de Holanda, 39 Terrassa Barcelona 08228",
    "addr:housenumber":"39",
    "addr:postcode":"08228",
    "addr:street":"Carrer De Holanda",
    "iso:country":"ES",
    "sg:address":"Carrer de Holanda, 39",
    "sg:city":"Terrassa",
    "sg:orig_category":"Molduras, Junquillos, Listones Y Molduras Perforadas",
    "sg:phone":"+34 937 84 27 21",
    "sg:postcode":"08228",
    "sg:province":"Barcelona",
    "wof:name":"Fernandez Salido Elias",
    "wof:placetype":"venue"
},
  "geometry": {"coordinates":[2.0426280499,41.5330734253],"type":"Point"}
}