{
  "type": "Feature",
  "properties": {
    "addr:full":"Calle de General Ricardos, 127 Madrid Madrid 28019",
    "addr:housenumber":"127",
    "addr:postcode":"28019",
    "addr:street":"Calle De General Ricardos",
    "iso:country":"ES",
    "sg:address":"Calle de General Ricardos, 127",
    "sg:city":"Madrid",
    "sg:orig_category":"Asesor\u00cda Fiscal Y Jur\u00cddica",
    "sg:phone":"+34 914 72 22 74",
    "sg:postcode":"28019",
    "sg:province":"Madrid",
    "wof:name":"Ferleo Consultores S.l.",
    "wof:placetype":"venue"
},
  "geometry": {"coordinates":[-3.7275462151,40.3910903931],"type":"Point"}
}