{
  "type": "Feature",
  "properties": {
    "addr:full":"Trav Dalt, 77 Barcelona Barcelona 08024",
    "addr:housenumber":"77",
    "addr:postcode":"08024",
    "addr:street":"Trav Dalt",
    "iso:country":"ES",
    "sg:address":"Trav Dalt, 77",
    "sg:city":"Barcelona",
    "sg:orig_category":"Molduras, Junquillos, Listones Y Molduras Perforadas",
    "sg:phone":"+34 932 84 32 79",
    "sg:postcode":"08024",
    "sg:province":"Barcelona",
    "wof:name":"Hernandez Gimenez Antonio",
    "wof:placetype":"venue"
},
  "geometry": {"coordinates":[2.1559720039,41.410369873],"type":"Point"}
}