{
  "type": "Feature",
  "properties": {
    "iso:country":"ES",
    "sg:address":"Calle de Gloria, 97",
    "sg:city":"Palmar  O Lugar De Don Juan",
    "sg:orig_category":"Oficinas Y Gesti\u00d3n De Inmuebles",
    "sg:phone":"+34 968 88 01 83",
    "sg:postcode":"30120",
    "sg:province":"Murcia",
    "sg:website":"www.codigozone.com",
    "wof:name":"Codigozone Sc",
    "wof:placetype":"venue"
},
  "geometry": {"coordinates":[-1.1302490234,37.9829597473],"type":"Point"}
}