{
  "type": "Feature",
  "properties": {
    "iso:country":"ES",
    "sg:address":"Calle de Campo De Futbol, 43",
    "sg:city":"Zarza",
    "sg:orig_category":"Electricidad: Instaladores",
    "sg:phone":"+34 924 36 69 77",
    "sg:postcode":"06830",
    "sg:province":"Badajoz",
    "wof:name":"Gil Trinidad Sebastian",
    "wof:placetype":"venue"
},
  "geometry": {"coordinates":[-6.2220611572,38.8161087036],"type":"Point"}
}