{
  "type": "Feature",
  "properties": {
    "addr:full":"Calle de Mayor, 87 Alcorcon Madrid 28922",
    "addr:housenumber":"87",
    "addr:postcode":"28922",
    "addr:street":"Calle De Mayor",
    "iso:country":"ES",
    "sg:address":"Calle de Mayor, 87",
    "sg:city":"Alcorcon",
    "sg:orig_category":"Servicios Gsm",
    "sg:phone":"+34 916 41 26 17",
    "sg:postcode":"28922",
    "sg:province":"Madrid",
    "wof:name":"Comunicaciones Leganes S.l.l.",
    "wof:placetype":"venue"
},
  "geometry": {"coordinates":[-3.8274390697,40.3434715271],"type":"Point"}
}