{
  "type": "Feature",
  "properties": {
    "iso:country":"ES",
    "sg:address":"Calle de Rochapea, S/n",
    "sg:city":"Barasoain",
    "sg:orig_category":"Negocio De Madera",
    "sg:phone":"+34 948 75 20 75",
    "sg:postcode":"31395",
    "sg:province":"Navarra",
    "wof:name":"Matute Iba\u00f1ez Santiago",
    "wof:placetype":"venue"
},
  "geometry": {"coordinates":[-1.6479469538,42.6039619446],"type":"Point"}
}