{
  "type": "Feature",
  "properties": {
    "iso:country":"ES",
    "sg:address":"Calle de Juan Bautista Uriarte, 42",
    "sg:city":"Galdakao",
    "sg:orig_category":"Fotocopias, Reprograf\u00cda",
    "sg:phone":"+34 944 56 71 31",
    "sg:postcode":"48960",
    "sg:province":"Vizcaya",
    "wof:name":"Gonzalez Elorriaga Aitor",
    "wof:placetype":"venue"
},
  "geometry": {"coordinates":[-2.8420319557,43.2304649353],"type":"Point"}
}