{
  "type": "Feature",
  "properties": {
    "addr:full":"Plaz Alamillo, 4 Madrid Madrid 28005",
    "addr:housenumber":"4",
    "addr:postcode":"28005",
    "addr:street":"Plaz Alamillo",
    "iso:country":"ES",
    "sg:address":"Plaz Alamillo, 4",
    "sg:city":"Madrid",
    "sg:orig_category":"Dise\u00d1o Industrial",
    "sg:phone":"+34 913 65 28 10",
    "sg:postcode":"28005",
    "sg:province":"Madrid",
    "wof:name":"Nu\u00f1ez Atienza Fernando",
    "wof:placetype":"venue"
},
  "geometry": {"coordinates":[-3.7122199535,40.4137268066],"type":"Point"}
}