{
  "type": "Feature",
  "properties": {
    "iso:country":"ES",
    "sg:address":"Calle de Hermosilla, 86",
    "sg:city":"Madrid",
    "sg:orig_category":"Ropa De Hogar (al Por Menor)",
    "sg:phone":"+34 914 35 26 01",
    "sg:postcode":"28001",
    "sg:province":"Madrid",
    "wof:name":"Grandes Almacenes S. L.",
    "wof:placetype":"venue"
},
  "geometry": {"coordinates":[-3.6762568951,40.4258117676],"type":"Point"}
}