{
  "type": "Feature",
  "properties": {
    "iso:country":"ES",
    "sg:address":"Carrer de L'hospital, 65",
    "sg:city":"Barcelona",
    "sg:orig_category":"Zapatos (al Por Menor)",
    "sg:phone":"+34 933 01 38 80",
    "sg:postcode":"08001",
    "sg:province":"Barcelona",
    "wof:name":"Nicolau Palou Luis",
    "wof:placetype":"venue"
},
  "geometry": {"coordinates":[2.170668602,41.3805198669],"type":"Point"}
}