{
  "type": "Feature",
  "properties": {
    "addr:full":"Calle de San Jose, 4 Aguas Nuevas Albacete 02049",
    "addr:housenumber":"4",
    "addr:postcode":"02049",
    "addr:street":"Calle De San Jose",
    "iso:country":"ES",
    "sg:address":"Calle de San Jose, 4",
    "sg:city":"Aguas Nuevas",
    "sg:orig_category":"Caf\u00c9s, Bares, Cervecer\u00cdas",
    "sg:phone":"+34 967 27 33 44",
    "sg:postcode":"02049",
    "sg:province":"Albacete",
    "wof:name":"Hermanos Soria De Aguas Nuevas S.l.",
    "wof:placetype":"venue"
},
  "geometry": {"coordinates":[-1.9206520319,38.9230957031],"type":"Point"}
}