{
  "type": "Feature",
  "properties": {
    "iso:country":"ES",
    "sg:address":"Pase China (de La), 1",
    "sg:city":"Almu\u00f1ecar",
    "sg:orig_category":"Supermercados Y Hipermercados",
    "sg:phone":"+34 958 63 57 30",
    "sg:postcode":"18690",
    "sg:province":"Granada",
    "wof:name":"Garcia Peula Enrique",
    "wof:placetype":"venue"
},
  "geometry": {"coordinates":[-3.6938381195,36.7327690125],"type":"Point"}
}