{
  "type": "Feature",
  "properties": {
    "iso:country":"ES",
    "sg:address":"Avda Federico Garcia Lorca, S/n",
    "sg:city":"Nijar",
    "sg:orig_category":"Panader\u00cdas, Panader\u00cdas",
    "sg:phone":"+34 950 36 04 25",
    "sg:postcode":"04100",
    "sg:province":"Almer\u00eda",
    "wof:name":"Lores Sanchez Loli",
    "wof:placetype":"venue"
},
  "geometry": {"coordinates":[-2.2059340477,36.9610366821],"type":"Point"}
}