{
  "type": "Feature",
  "properties": {
    "iso:country":"ES",
    "sg:address":"Calle de Santos Medicos, 19",
    "sg:city":"Montesinos",
    "sg:orig_category":"Empresas De Desmonte",
    "sg:phone":"+34 966 72 12 07",
    "sg:postcode":"03187",
    "sg:province":"Alicante",
    "wof:name":"Sacaterra Excavaciones S.l.",
    "wof:placetype":"venue"
},
  "geometry": {"coordinates":[-0.741846025,38.0268783569],"type":"Point"}
}