{
  "type": "Feature",
  "properties": {
    "addr:full":"Carrer de Comte Borrell, 58 Barcelona Barcelona 08015",
    "addr:housenumber":"58",
    "addr:postcode":"08015",
    "addr:street":"Carrer De Comte Borrell",
    "iso:country":"ES",
    "sg:address":"Carrer de Comte Borrell, 58",
    "sg:city":"Barcelona",
    "sg:orig_category":"Bisuter\u00cda, Joyer\u00cda, Relojer\u00cda (al Por Menor)",
    "sg:phone":"+34 934 23 77 43",
    "sg:postcode":"08015",
    "sg:province":"Barcelona",
    "wof:name":"Tomas Colomer S. A.",
    "wof:placetype":"venue"
},
  "geometry": {"coordinates":[2.1609220505,41.378780365],"type":"Point"}
}