{
  "type": "Feature",
  "properties": {
    "iso:country":"ES",
    "sg:address":"Carr Antoni Saura, 14",
    "sg:city":"Eivissa",
    "sg:orig_category":"Electrodom\u00c9sticos (al Por Menor)",
    "sg:phone":"+34 971 31 04 63",
    "sg:postcode":"07800",
    "sg:province":"Islas Baleares",
    "wof:name":"Talleres Rigo Ibiza C.b.",
    "wof:placetype":"venue"
},
  "geometry": {"coordinates":[1.4230600595,38.9197692871],"type":"Point"}
}