{
  "type": "Feature",
  "properties": {
    "iso:country":"ES",
    "sg:address":"Calle de Arcipreste De Hita, 4",
    "sg:city":"Almansa",
    "sg:orig_category":"Mec\u00c1nico Del Autom\u00d3vil",
    "sg:phone":"+34 967 34 16 19",
    "sg:postcode":"02640",
    "sg:province":"Albacete",
    "wof:name":"Andujar Puche Antonio Jose",
    "wof:placetype":"venue"
},
  "geometry": {"coordinates":[-1.0982384682,38.8726730347],"type":"Point"}
}