{
  "type": "Feature",
  "properties": {
    "iso:country":"ES",
    "sg:address":"Calle de Jeronimo Ibran, 3",
    "sg:city":"Oviedo",
    "sg:orig_category":"Frutas, Legumbres Frescas Y Tempranas (al Por Menor)",
    "sg:phone":"+34 985 29 25 80",
    "sg:postcode":"33001",
    "sg:province":"Asturias",
    "wof:name":"Mendez Garcia Guillermina",
    "wof:placetype":"venue"
},
  "geometry": {"coordinates":[-5.8508791924,43.3677215576],"type":"Point"}
}