{
  "type": "Feature",
  "properties": {
    "addr:full":"Carrer de Torrent De L'olla, 101 Barcelona Barcelona 08012",
    "addr:housenumber":"101",
    "addr:postcode":"08012",
    "addr:street":"Carrer De Torrent De L'Olla",
    "iso:country":"ES",
    "sg:address":"Carrer de Torrent De L'olla, 101",
    "sg:city":"Barcelona",
    "sg:orig_category":"Empresarios",
    "sg:phone":"+34 932 17 83 83",
    "sg:postcode":"08012",
    "sg:province":"Barcelona",
    "wof:name":"J.c.coll S.l.",
    "wof:placetype":"venue"
},
  "geometry": {"coordinates":[2.1571681499,41.4021110535],"type":"Point"}
}