{
  "type": "Feature",
  "properties": {
    "iso:country":"ES",
    "sg:address":"Ctra Vall D'aran, S/n",
    "sg:city":"Almenar",
    "sg:orig_category":"Peluqueros: De Se\u00d1oras",
    "sg:phone":"+34 973 77 04 41",
    "sg:postcode":"25126",
    "sg:province":"Lleida",
    "wof:name":"Cases Larregula Susana",
    "wof:placetype":"venue"
},
  "geometry": {"coordinates":[0.5701000094,41.7965507507],"type":"Point"}
}