{
  "type": "Feature",
  "properties": {
    "addr:full":"Calle de Senador Josep V. Bevia, 6 Alacant Alicante 03014",
    "addr:housenumber":"6",
    "addr:postcode":"03014",
    "addr:street":"Calle De Senador Josep V. Bevia",
    "iso:country":"ES",
    "sg:address":"Calle de Senador Josep V. Bevia, 6",
    "sg:city":"Alacant",
    "sg:orig_category":"Estancos",
    "sg:phone":"+34 965 18 10 32",
    "sg:postcode":"03014",
    "sg:province":"Alicante",
    "wof:name":"Biel Solano Francisca",
    "wof:placetype":"venue"
},
  "geometry": {"coordinates":[-0.4804739952,38.3440856934],"type":"Point"}
}