{
  "type": "Feature",
  "properties": {
    "iso:country":"ES",
    "sg:address":"Calle de Constitucion (la), 84",
    "sg:city":"Pola Gordon",
    "sg:orig_category":"Peluquer\u00cdas, Peluquer\u00cda Mixta",
    "sg:phone":"+34 987 58 81 54",
    "sg:postcode":"24600",
    "sg:province":"Le\u00f3n",
    "wof:name":"Martin Garcia Yolanda",
    "wof:placetype":"venue"
},
  "geometry": {"coordinates":[-5.6709461212,42.8548316956],"type":"Point"}
}