{
  "type": "Feature",
  "properties": {
    "addr:full":"Calle de Puerto, S/n S Jose Almer\u00eda 04118",
    "addr:postcode":"04118",
    "addr:street":"Calle De Puerto S / N S Jose Almeri\u0301A",
    "iso:country":"ES",
    "sg:address":"Calle de Puerto, S/n",
    "sg:city":"S Jose",
    "sg:orig_category":"Asociaciones Y Clubs Deportivos",
    "sg:phone":"+34 950 38 04 62",
    "sg:postcode":"04118",
    "sg:province":"Almer\u00eda",
    "wof:name":"Villegas Carmona Maria Dolores",
    "wof:placetype":"venue"
},
  "geometry": {"coordinates":[-2.1081988811,36.7621688843],"type":"Point"}
}