{
  "type": "Feature",
  "properties": {
    "iso:country":"ES",
    "sg:address":"Calle de Rascon, 10",
    "sg:city":"Huelva",
    "sg:orig_category":"Agricultores, Agricultores",
    "sg:phone":"+34 959 28 43 05",
    "sg:postcode":"21001",
    "sg:province":"Huelva",
    "wof:name":"Maria Luisa S. A.",
    "wof:placetype":"venue"
},
  "geometry": {"coordinates":[-6.9530601501,37.256893158],"type":"Point"}
}