{
  "type": "Feature",
  "properties": {
    "iso:country":"ES",
    "sg:address":"Pla De Lluch, S/n",
    "sg:city":"Masia Pla Lluch",
    "sg:orig_category":"Cerrajer\u00cda, Ferrallista",
    "sg:phone":"+34 964 32 80 00",
    "sg:postcode":"12130",
    "sg:province":"Castell\u00f3n",
    "wof:name":"Gil Navarro Ismael",
    "wof:placetype":"venue"
},
  "geometry": {"coordinates":[-0.1369799972,40.061126709],"type":"Point"}
}