{
  "type": "Feature",
  "properties": {
    "iso:country":"ES",
    "sg:address":"Grup Almenas (las), S/n",
    "sg:city":"Sevilla",
    "sg:orig_category":"Carnicer\u00cdas, Carnicer\u00cdas",
    "sg:phone":"+34 954 94 43 53",
    "sg:postcode":"41008",
    "sg:province":"Sevilla",
    "wof:name":"Ca\u00f1avate Sastre Emilio",
    "wof:placetype":"venue"
},
  "geometry": {"coordinates":[-5.9664239883,37.4154510498],"type":"Point"}
}