{
  "type": "Feature",
  "properties": {
    "iso:country":"ES",
    "sg:address":"Calle de Prim, 11",
    "sg:city":"Madrid",
    "sg:orig_category":"Artes Gr\u00c1ficas, Artes Pl\u00c1sticas (curso)",
    "sg:phone":"+34 915 21 51 18",
    "sg:postcode":"28004",
    "sg:province":"Madrid",
    "wof:name":"Luis Rascon Gomez Y Enrique Diaz Torres S.c.",
    "wof:placetype":"venue"
},
  "geometry": {"coordinates":[-3.6937360764,40.422039032],"type":"Point"}
}