{
  "type": "Feature",
  "properties": {
    "addr:full":"Rua Magdalena, 50 Ferrol A Coru\u00f1a 15402",
    "addr:housenumber":"50",
    "addr:postcode":"15402",
    "addr:street":"Rua Magdalena;A Corun\u0303A",
    "iso:country":"ES",
    "sg:address":"Rua Magdalena, 50",
    "sg:city":"Ferrol",
    "sg:orig_category":"Molduras, Junquillos, Listones Y Molduras Perforadas",
    "sg:phone":"+34 981 35 08 70",
    "sg:postcode":"15402",
    "sg:province":"A Coru\u00f1a",
    "wof:name":"Vazquez Fernandez Benigno",
    "wof:placetype":"venue"
},
  "geometry": {"coordinates":[-8.2306776047,43.4846534729],"type":"Point"}
}