{
  "type": "Feature",
  "properties": {
    "addr:full":"La Lora, 4 Burgos Burgos 09007",
    "addr:housenumber":"4",
    "addr:postcode":"09007",
    "iso:country":"ES",
    "sg:address":"La Lora, 4",
    "sg:city":"Burgos",
    "sg:orig_category":"Ense\u00d1anza, Formaci\u00d3n Profesional: Aprendizaje",
    "sg:phone":"+34 947 48 20 47",
    "sg:postcode":"09007",
    "sg:province":"Burgos",
    "wof:name":"Servicio Territorial De Agricultura-junta De Castila Y Leon",
    "wof:placetype":"venue"
},
  "geometry": {"coordinates":[-3.653331995,42.350894928],"type":"Point"}
}