{
  "type": "Feature",
  "properties": {
    "iso:country":"ES",
    "sg:address":"C/ Estrella, De S', 2",
    "sg:city":"Manacor",
    "sg:orig_category":"Zapatos (al Por Menor)",
    "sg:phone":"+34 971 55 61 09",
    "sg:postcode":"07500",
    "sg:province":"Islas Baleares",
    "wof:name":"Dos Peuets C.b.",
    "wof:placetype":"venue"
},
  "geometry": {"coordinates":[3.2092959881,39.5690345764],"type":"Point"}
}