{
  "type": "Feature",
  "properties": {
    "addr:full":"Calle de Juan Infante, 12 Santillana Cantabria 39330",
    "addr:housenumber":"12",
    "addr:postcode":"39330",
    "addr:street":"Calle De Juan Infante",
    "iso:country":"ES",
    "sg:address":"Calle de Juan Infante, 12",
    "sg:city":"Santillana",
    "sg:orig_category":"Art\u00cdculos De Regalo (al Por Menor)",
    "sg:phone":"+34 942 81 83 93",
    "sg:postcode":"39330",
    "sg:province":"Cantabria",
    "wof:name":"Andres Gutierrez Maria Perfecta",
    "wof:placetype":"venue"
},
  "geometry": {"coordinates":[-4.1086750031,43.3898773193],"type":"Point"}
}