{
  "type": "Feature",
  "properties": {
    "addr:full":"Plaz Dean Mazas, 3 Jaen Ja\u00e9n 23001",
    "addr:housenumber":"3;jae\u0301n",
    "addr:postcode":"23001",
    "addr:street":"Plaz Dean Mazas",
    "iso:country":"ES",
    "sg:address":"Plaz Dean Mazas, 3",
    "sg:city":"Jaen",
    "sg:orig_category":"Doctores En Medicina",
    "sg:phone":"+34 953 19 05 06",
    "sg:postcode":"23001",
    "sg:province":"Ja\u00e9n",
    "wof:name":"Jerez Justicia Diego",
    "wof:placetype":"venue"
},
  "geometry": {"coordinates":[-3.7882089615,37.7670555115],"type":"Point"}
}