{
  "type": "Feature",
  "properties": {
    "iso:country":"ES",
    "sg:address":"Av Magaluf, 8",
    "sg:city":"Magaluf",
    "sg:orig_category":"Perfumer\u00cda (al Por Menor)",
    "sg:phone":"+34 971 13 24 60",
    "sg:postcode":"07181",
    "sg:province":"Islas Baleares",
    "wof:name":"Stefanel Perfumerias S.a.",
    "wof:placetype":"venue"
},
  "geometry": {"coordinates":[2.5328938961,39.5058937073],"type":"Point"}
}