{
  "type": "Feature",
  "properties": {
    "iso:country":"ES",
    "sg:address":"Extremo, 13",
    "sg:city":"Pobra Carami\u00f1al",
    "sg:orig_category":"Electrodom\u00c9sticos (al Por Menor)",
    "sg:phone":"+34 981 83 13 53",
    "sg:postcode":"15940",
    "sg:province":"La Coru\u00f1a",
    "wof:name":"Gomez Trasbach Jose",
    "wof:placetype":"venue"
},
  "geometry": {"coordinates":[-8.9381847382,42.6047096252],"type":"Point"}
}