{
  "type": "Feature",
  "properties": {
    "addr:full":"Calle de Zurbaran, 1 Ubeda Ja\u00e9n 23400",
    "addr:housenumber":"1",
    "addr:postcode":"23400",
    "addr:street":"Calle De Zurbaran;Jae\u0301N",
    "iso:country":"ES",
    "sg:address":"Calle de Zurbaran, 1",
    "sg:city":"Ubeda",
    "sg:orig_category":"Electrodom\u00c9sticos (fabricaci\u00d3n, Al Por Mayor)",
    "sg:phone":"+34 953 75 49 07",
    "sg:postcode":"23400",
    "sg:province":"Ja\u00e9n",
    "wof:name":"Cejudo Azorit Rafael",
    "wof:placetype":"venue"
},
  "geometry": {"coordinates":[-3.3751659393,38.014881134],"type":"Point"}
}