{
  "type": "Feature",
  "properties": {
    "addr:full":"Av Manuel Lopez, 6 Santa Maria D'olo Barcelona 08273",
    "addr:housenumber":"6",
    "addr:postcode":"08273",
    "addr:street":"Av Manuel Lopez",
    "iso:country":"ES",
    "sg:address":"Av Manuel Lopez, 6",
    "sg:city":"Santa Maria D'olo",
    "sg:orig_category":"Albergues",
    "sg:phone":"+34 938 38 50 01",
    "sg:postcode":"08273",
    "sg:province":"Barcelona",
    "wof:name":"Hostal Restaurante Santa Maria S.c.p.",
    "wof:placetype":"venue"
},
  "geometry": {"coordinates":[2.034645319,41.8744888306],"type":"Point"}
}