{
  "type": "Feature",
  "properties": {
    "addr:full":"Calle de Ana De Austria, 34 Madrid Madrid 28050",
    "addr:housenumber":"34",
    "addr:postcode":"madrid;28050",
    "addr:street":"Calle De Ana De Austria",
    "iso:country":"ES",
    "sg:address":"Calle de Ana De Austria, 34",
    "sg:city":"Madrid",
    "sg:orig_category":"Promotores Constructores",
    "sg:phone":"+34 917 67 84 06",
    "sg:postcode":"28050",
    "sg:province":"Madrid",
    "wof:name":"Profpol Construcciones, S.l.",
    "wof:placetype":"venue"
},
  "geometry": {"coordinates":[-3.6551692486,40.4961929321],"type":"Point"}
}