{
  "type": "Feature",
  "properties": {
    "addr:full":"Av Del Comtat De Fabraquer, 140 Sant Joan D'alacant Alicante 03550",
    "addr:housenumber":"140",
    "addr:postcode":"03550",
    "addr:street":"Av Del Comtat",
    "iso:country":"ES",
    "sg:address":"Av Del Comtat De Fabraquer, 140",
    "sg:city":"Sant Joan D'alacant",
    "sg:orig_category":"Importaci\u00d3n",
    "sg:phone":"+34 965 94 21 44",
    "sg:postcode":"03550",
    "sg:province":"Alicante",
    "wof:name":"Roman Belmonte Manuela",
    "wof:placetype":"venue"
},
  "geometry": {"coordinates":[-0.4804700017,38.3440818787],"type":"Point"}
}