{
  "type": "Feature",
  "properties": {
    "addr:full":"Avda Rey Juan Carlos I, 53 Puerto Lumbreras Murcia 30890",
    "addr:housenumber":"53",
    "addr:postcode":"30890",
    "addr:street":"Avda Rey Juan Carlos I",
    "iso:country":"ES",
    "sg:address":"Avda Rey Juan Carlos I, 53",
    "sg:city":"Puerto Lumbreras",
    "sg:orig_category":"Venta, Montaje De Neum\u00c1ticos",
    "sg:phone":"+34 968 40 22 94",
    "sg:postcode":"30890",
    "sg:province":"Murcia",
    "wof:name":"Garcia Mateos Jose",
    "wof:placetype":"venue"
},
  "geometry": {"coordinates":[-1.801954031,37.5689659119],"type":"Point"}
}