{
  "type": "Feature",
  "properties": {
    "addr:full":"Carr Balears, 5 Eivissa Islas Baleares 07800",
    "addr:housenumber":"5",
    "addr:postcode":"07800",
    "addr:street":"Carr Balears",
    "iso:country":"ES",
    "sg:address":"Carr Balears, 5",
    "sg:city":"Eivissa",
    "sg:orig_category":"Ropa Para Ni\u00d1os (al Por Menor)",
    "sg:phone":"+34 971 30 04 74",
    "sg:postcode":"07800",
    "sg:province":"Islas Baleares",
    "wof:name":"Torres Martinez Manuel",
    "wof:placetype":"venue"
},
  "geometry": {"coordinates":[1.4245339632,38.9087409973],"type":"Point"}
}