{
  "type": "Feature",
  "properties": {
    "iso:country":"ES",
    "sg:address":"Avda Torreon Del Alcazar, 5",
    "sg:city":"Ciudad Real",
    "sg:orig_category":"Ingenier\u00cda, Centros De Estudios (diversos)",
    "sg:phone":"+34 926 22 30 56",
    "sg:postcode":"13004",
    "sg:province":"Ciudad Real",
    "wof:name":"Jarava Melgarejo Antonio",
    "wof:placetype":"venue"
},
  "geometry": {"coordinates":[-3.9234740734,38.9844856262],"type":"Point"}
}