{
  "type": "Feature",
  "properties": {
    "addr:full":"Calle de Jorge Juan, 15 Madrid Madrid 28001",
    "addr:housenumber":"15",
    "addr:postcode":"madrid;28001",
    "addr:street":"Calle De Jorge Juan",
    "iso:country":"ES",
    "sg:address":"Calle de Jorge Juan, 15",
    "sg:city":"Madrid",
    "sg:orig_category":"Ropa De Hogar (al Por Menor)",
    "sg:phone":"+34 917 81 34 66",
    "sg:postcode":"28001",
    "sg:province":"Madrid",
    "sg:website":"www.genevievelethu.com",
    "wof:name":"Genevieve Lethu Espa\u00f1a S.l.",
    "wof:placetype":"venue"
},
  "geometry": {"coordinates":[-3.6857590675,40.4239845276],"type":"Point"}
}