{
  "type": "Feature",
  "properties": {
    "addr:full":"Avda Algeciras, 23 Algeciras C\u00e1diz 11206",
    "addr:housenumber":"23;ca\u0301diz",
    "addr:postcode":"11206",
    "addr:street":"Avda Algeciras",
    "iso:country":"ES",
    "sg:address":"Avda Algeciras, 23",
    "sg:city":"Algeciras",
    "sg:orig_category":"Transporte En General",
    "sg:phone":"+34 956 57 39 17",
    "sg:postcode":"11206",
    "sg:province":"C\u00e1diz",
    "wof:name":"Jormas 39 S.l.",
    "wof:placetype":"venue"
},
  "geometry": {"coordinates":[-5.4732589722,36.1143035889],"type":"Point"}
}