{
  "type": "Feature",
  "properties": {
    "addr:full":"Crta Xerta, 11 Jesus Tarragona 43590",
    "addr:housenumber":"11",
    "addr:postcode":"43590",
    "addr:street":"Crta Xerta",
    "iso:country":"ES",
    "sg:address":"Crta Xerta, 11",
    "sg:city":"Jesus",
    "sg:orig_category":"Asesor\u00cda Sobre Comunicaci\u00d3n De Empresas",
    "sg:phone":"+34 977 58 06 68",
    "sg:postcode":"43590",
    "sg:province":"Tarragona",
    "wof:name":"Assesoria Fiscal Dertvsa S.l.",
    "wof:placetype":"venue"
},
  "geometry": {"coordinates":[1.2454571724,41.11901474],"type":"Point"}
}