{
  "type": "Feature",
  "properties": {
    "iso:country":"ES",
    "sg:address":"Carrer de Creteil, 29",
    "sg:city":"Mataro",
    "sg:orig_category":"Asociaciones Y Clubs Deportivos",
    "sg:phone":"+34 937 96 25 56",
    "sg:postcode":"08304",
    "sg:province":"Barcelona",
    "wof:name":"Barrios  Linda Joice",
    "wof:placetype":"venue"
},
  "geometry": {"coordinates":[2.4474439621,41.5537796021],"type":"Point"}
}