{
  "type": "Feature",
  "properties": {
    "addr:full":"Av Francesc Cambo, 12 Barcelona Barcelona 08003",
    "addr:housenumber":"12",
    "addr:postcode":"08003",
    "addr:street":"Av Francesc Cambo",
    "iso:country":"ES",
    "sg:address":"Av Francesc Cambo, 12",
    "sg:city":"Barcelona",
    "sg:orig_category":"Farmacias",
    "sg:phone":"+34 933 19 17 48",
    "sg:postcode":"08003",
    "sg:province":"Barcelona",
    "wof:name":"Carbonell Peris Beatriu",
    "wof:placetype":"venue"
},
  "geometry": {"coordinates":[2.1772119999,41.385799408],"type":"Point"}
}