{
  "type": "Feature",
  "properties": {
    "addr:full":"Calle de Nogales (los), 28 Molar Madrid 28710",
    "addr:housenumber":"28",
    "addr:postcode":"28710",
    "addr:street":"Calle De Nogales Los",
    "iso:country":"ES",
    "sg:address":"Calle de Nogales (los), 28",
    "sg:city":"Molar",
    "sg:orig_category":"Carb\u00d3n, Carb\u00d3n De Madera (al Por Mayor)",
    "sg:phone":"+34 918 43 30 67",
    "sg:postcode":"28710",
    "sg:province":"Madrid",
    "wof:name":"Pascual De Las Eras Carmen",
    "wof:placetype":"venue"
},
  "geometry": {"coordinates":[-3.5906980038,40.7419204712],"type":"Point"}
}