{
  "type": "Feature",
  "properties": {
    "iso:country":"ES",
    "sg:address":"Calle de Cid Campeador, 1",
    "sg:city":"Mostoles",
    "sg:orig_category":"Guarder\u00cdas",
    "sg:phone":"+34 916 14 38 79",
    "sg:postcode":"28935",
    "sg:province":"Madrid",
    "wof:name":"Nueva Bambi S.l.",
    "wof:placetype":"venue"
},
  "geometry": {"coordinates":[-3.8707048893,40.3259162903],"type":"Point"}
}