{
  "type": "Feature",
  "properties": {
    "iso:country":"ES",
    "sg:address":"Carrer de Fruiters, 1",
    "sg:city":"Fruiters",
    "sg:orig_category":"Instalaci\u00d3n De Aspiraci\u00d3n De Gases Y Humos",
    "sg:phone":"+34 937 14 45 55",
    "sg:postcode":"08211",
    "sg:province":"Barcelona",
    "wof:name":"Propano Domestico Industrial R. A. R. S.a.",
    "wof:placetype":"venue"
},
  "geometry": {"coordinates":[2.0857300758,41.6151885986],"type":"Point"}
}