{
  "type": "Feature",
  "properties": {
    "iso:country":"ES",
    "sg:address":"Carrer de Crom, 54",
    "sg:city":"Hospitalet Llobregat",
    "sg:orig_category":"Aparatos De Medida, Control, Regulaci\u00d3n Y Detecci\u00d3n",
    "sg:phone":"+34 932 63 48 11",
    "sg:postcode":"08907",
    "sg:province":"Barcelona",
    "sg:website":"www.midaipressio.com",
    "wof:name":"Mida Pressio S.l.",
    "wof:placetype":"venue"
},
  "geometry": {"coordinates":[2.1018869877,41.3515777588],"type":"Point"}
}