{
  "type": "Feature",
  "properties": {
    "iso:country":"ES",
    "sg:address":"Calle de Profesor Hernandez Pacheco, 6",
    "sg:city":"Caceres",
    "sg:orig_category":"Promotores Constructores",
    "sg:phone":"+34 927 22 14 27",
    "sg:postcode":"10002",
    "sg:province":"C\u00e1ceres",
    "wof:name":"Confebesa S.l",
    "wof:placetype":"venue"
},
  "geometry": {"coordinates":[-6.3717780113,39.4699668884],"type":"Point"}
}