{
  "type": "Feature",
  "properties": {
    "addr:full":"Calle de Cronista Carreres, 11 Valencia Valencia 46003",
    "addr:housenumber":"11",
    "addr:postcode":"46003",
    "addr:street":"Calle De Cronista Carreres",
    "iso:country":"ES",
    "sg:address":"Calle de Cronista Carreres, 11",
    "sg:city":"Valencia",
    "sg:orig_category":"Peluqueros: De Se\u00d1oras",
    "sg:phone":"+34 963 94 07 80",
    "sg:postcode":"46003",
    "sg:province":"Valencia",
    "wof:name":"Olmos Torne Paloma",
    "wof:placetype":"venue"
},
  "geometry": {"coordinates":[-0.3676564991,39.4727478027],"type":"Point"}
}