{
  "type": "Feature",
  "properties": {
    "iso:country":"ES",
    "sg:address":"Calle de Leandro De Saralegui, 7",
    "sg:city":"Valencia",
    "sg:orig_category":"Electrodom\u00c9sticos (al Por Menor)",
    "sg:phone":"+34 963 60 83 65",
    "sg:postcode":"46021",
    "sg:province":"Valencia",
    "wof:name":"Tecnologia Para Cafe Expreso S.l.",
    "wof:placetype":"venue"
},
  "geometry": {"coordinates":[-0.3481118083,39.4751472473],"type":"Point"}
}