{
  "type": "Feature",
  "properties": {
    "iso:country":"ES",
    "sg:address":"Carrer de Salvador Vancell, 26",
    "sg:city":"Suria",
    "sg:orig_category":"Inform\u00c1tica, Ofim\u00c1tica (estudios, Asesor\u00cda, Ingenier\u00cda, Formaci\u00d3n)",
    "sg:phone":"+34 938 68 22 94",
    "sg:postcode":"08260",
    "sg:province":"Barcelona",
    "wof:name":"Grup Julia Martinez S.l.",
    "wof:placetype":"venue"
},
  "geometry": {"coordinates":[1.7507970333,41.8320732117],"type":"Point"}
}