{
  "type": "Feature",
  "properties": {
    "addr:full":"Calle de San Luis Gonzaga, 23 Gines Sevilla 41960",
    "addr:housenumber":"23",
    "addr:postcode":"41960",
    "addr:street":"Calle De San Luis Gonzaga;Sevilla",
    "iso:country":"ES",
    "sg:address":"Calle de San Luis Gonzaga, 23",
    "sg:city":"Gines",
    "sg:orig_category":"Escultores, Estatuarios E Imagineros",
    "sg:phone":"+34 954 71 31 11",
    "sg:postcode":"41960",
    "sg:province":"Sevilla",
    "wof:name":"Alvarez Duarte Luis",
    "wof:placetype":"venue"
},
  "geometry": {"coordinates":[-6.0727958679,37.3821411133],"type":"Point"}
}