{
  "type": "Feature",
  "properties": {
    "addr:full":"Calle de San Torcuato, 4 Guadix Granada 18500",
    "addr:housenumber":"4",
    "addr:postcode":"18500",
    "addr:street":"Calle De San Torcuato",
    "iso:country":"ES",
    "sg:address":"Calle de San Torcuato, 4",
    "sg:city":"Guadix",
    "sg:orig_category":"Inmobiliaria (agencias)",
    "sg:phone":"+34 958 66 00 93",
    "sg:postcode":"18500",
    "sg:province":"Granada",
    "wof:name":"Sierra Ruiz Antonia",
    "wof:placetype":"venue"
},
  "geometry": {"coordinates":[-3.1341640949,37.3011703491],"type":"Point"}
}