{
  "type": "Feature",
  "properties": {
    "addr:full":"Calle de Doctor Marco Merenciano, 25 Valencia Valencia 46025",
    "addr:housenumber":"25",
    "addr:postcode":"46025",
    "addr:street":"Calle De Doctor Marco Merenciano",
    "iso:country":"ES",
    "sg:address":"Calle de Doctor Marco Merenciano, 25",
    "sg:city":"Valencia",
    "sg:orig_category":"Plomeros",
    "sg:phone":"+34 963 47 58 52",
    "sg:postcode":"46025",
    "sg:province":"Valencia",
    "wof:name":"Belenguer Moreno Jose Manuel",
    "wof:placetype":"venue"
},
  "geometry": {"coordinates":[-0.3814870119,39.4914741516],"type":"Point"}
}