{
  "type": "Feature",
  "properties": {
    "addr:full":"Calle de Cruz (la), 5 Navarrete La Rioja 26370",
    "addr:housenumber":"5",
    "addr:postcode":"26370",
    "addr:street":"Calle De Cruz La",
    "iso:country":"ES",
    "sg:address":"Calle de Cruz (la), 5",
    "sg:city":"Navarrete",
    "sg:orig_category":"Promotores Constructores",
    "sg:phone":"+34 941 44 02 77",
    "sg:postcode":"26370",
    "sg:province":"La Rioja",
    "wof:name":"Sierra Saez Lucio",
    "wof:placetype":"venue"
},
  "geometry": {"coordinates":[-2.5590410233,42.4300117493],"type":"Point"}
}