{
  "type": "Feature",
  "properties": {
    "iso:country":"ES",
    "sg:address":"Carrer de Rubio I Ors, 44",
    "sg:city":"Barcelona",
    "sg:orig_category":"Empresarios",
    "sg:phone":"+34 934 36 39 30",
    "sg:postcode":"08041",
    "sg:province":"Barcelona",
    "wof:name":"Valle Vega Joaquin",
    "wof:placetype":"venue"
},
  "geometry": {"coordinates":[2.1774671078,41.420249939],"type":"Point"}
}