{
  "type": "Feature",
  "properties": {
    "iso:country":"ES",
    "sg:address":"Calle de Segovia, S/n",
    "sg:city":"Escarabajosa De Cabezas",
    "sg:orig_category":"Sanatorios M\u00c9dico",
    "sg:phone":"+34 921 56 21 58",
    "sg:postcode":"40291",
    "sg:province":"Segovia",
    "wof:name":"Ayuntamiento De Escarabajosa De Cabezas",
    "wof:placetype":"venue"
},
  "geometry": {"coordinates":[-4.1959781647,41.1034049988],"type":"Point"}
}