{
  "type": "Feature",
  "properties": {
    "addr:full":"Calle de Diego Ponce, 4 Antequera M\u00e1laga 29200",
    "addr:housenumber":"4",
    "addr:postcode":"29200",
    "addr:street":"Calle De Diego Ponce",
    "iso:country":"ES",
    "sg:address":"Calle de Diego Ponce, 4",
    "sg:city":"Antequera",
    "sg:orig_category":"Electrodom\u00c9sticos (al Por Menor)",
    "sg:phone":"+34 952 84 32 25",
    "sg:postcode":"29200",
    "sg:province":"M\u00e1laga",
    "wof:name":"Lopez Torres Antonio",
    "wof:placetype":"venue"
},
  "geometry": {"coordinates":[-4.559525013,37.0192070007],"type":"Point"}
}