{
  "type": "Feature",
  "properties": {
    "iso:country":"ES",
    "sg:address":"Avda Portugal (de), 4",
    "sg:city":"Villodrigo",
    "sg:orig_category":"Panader\u00cdas, Panader\u00cdas",
    "sg:phone":"+34 947 16 60 37",
    "sg:postcode":"34260",
    "sg:province":"Palencia",
    "wof:name":"Panificadora Villodrigo",
    "wof:placetype":"venue"
},
  "geometry": {"coordinates":[-4.1326818466,42.1466064453],"type":"Point"}
}