{
  "type": "Feature",
  "properties": {
    "addr:full":"Calle de Sofocles, 7 Malaga M\u00e1laga 29010",
    "addr:housenumber":"7",
    "addr:postcode":"29010",
    "addr:street":"Calle De Sofocles;Ma\u0301Laga",
    "iso:country":"ES",
    "sg:address":"Calle de Sofocles, 7",
    "sg:city":"Malaga",
    "sg:orig_category":"Droguer\u00cdas (al Por Menor)",
    "sg:phone":"+34 952 39 99 54",
    "sg:postcode":"29010",
    "sg:province":"M\u00e1laga",
    "wof:name":"Hinojosa Pedrosa Francisco",
    "wof:placetype":"venue"
},
  "geometry": {"coordinates":[-4.4819850922,36.7219924927],"type":"Point"}
}