{
  "type": "Feature",
  "properties": {
    "addr:full":"Avda Carolina Coronado, 16 Badajoz Badajoz 06006",
    "addr:housenumber":"16",
    "addr:postcode":"06006",
    "addr:street":"Avda Carolina Coronado",
    "iso:country":"ES",
    "sg:address":"Avda Carolina Coronado, 16",
    "sg:city":"Badajoz",
    "sg:orig_category":"Fotograf\u00cda Art\u00cdstica Y Retratos",
    "sg:phone":"+34 924 27 39 95",
    "sg:postcode":"06006",
    "sg:province":"Badajoz",
    "wof:name":"Miguel Angel Badajoz S.l.",
    "wof:placetype":"venue"
},
  "geometry": {"coordinates":[-6.9825148582,38.8899726868],"type":"Point"}
}