{
  "type": "Feature",
  "properties": {
    "addr:full":"Carrer de Domenech I Montaner, 2 Cornella Llobregat Barcelona 08940",
    "addr:housenumber":"2",
    "addr:postcode":"08940",
    "addr:street":"Carrer De Domenech I Montaner",
    "iso:country":"ES",
    "sg:address":"Carrer de Domenech I Montaner, 2",
    "sg:city":"Cornella Llobregat",
    "sg:orig_category":"Librer\u00cdas",
    "sg:phone":"+34 933 76 44 01",
    "sg:postcode":"08940",
    "sg:province":"Barcelona",
    "wof:name":"Vintro Pons Nuria",
    "wof:placetype":"venue"
},
  "geometry": {"coordinates":[2.0764989853,41.3646507263],"type":"Point"}
}