{
  "type": "Feature",
  "properties": {
    "addr:full":"C/ Comabruna, 21 Tarrega Lleida 25300",
    "addr:housenumber":"21",
    "addr:postcode":"25300",
    "addr:street":"C / Comabruna",
    "iso:country":"ES",
    "sg:address":"C/ Comabruna, 21",
    "sg:city":"Tarrega",
    "sg:orig_category":"Papeler\u00cdas: Art\u00cdculos (al Por Mayor)",
    "sg:phone":"+34 973 50 01 18",
    "sg:postcode":"25300",
    "sg:province":"Lleida",
    "wof:name":"Ofi-escolar Estel S.l.",
    "wof:placetype":"venue"
},
  "geometry": {"coordinates":[1.1422350407,41.6479911804],"type":"Point"}
}