{
  "type": "Feature",
  "properties": {
    "iso:country":"ES",
    "sg:address":"Calle de Guzman El Bueno, 127",
    "sg:city":"Madrid",
    "sg:orig_category":"Caf\u00c9s, Bares, Cervecer\u00cdas",
    "sg:phone":"+34 915 53 90 83",
    "sg:postcode":"28003",
    "sg:province":"Madrid",
    "wof:name":"Picklunch S.a.",
    "wof:placetype":"venue"
},
  "geometry": {"coordinates":[-3.7127659321,40.4423675537],"type":"Point"}
}