{
  "type": "Feature",
  "properties": {
    "iso:country":"ES",
    "sg:address":"Polig. Pocomaco, S/n",
    "sg:city":"A Coru\u00f1a",
    "sg:orig_category":"Librer\u00cdas",
    "sg:phone":"+34 981 29 57 11",
    "sg:postcode":"15190",
    "sg:province":"La Coru\u00f1a",
    "wof:name":"Distribuidora De Las Rias S. A.",
    "wof:placetype":"venue"
},
  "geometry": {"coordinates":[-8.4312744141,43.3228416443],"type":"Point"}
}