{
  "type": "Feature",
  "properties": {
    "iso:country":"ES",
    "sg:address":"Trans Ctra Granada, S/n",
    "sg:city":"Jayena",
    "sg:orig_category":"Frutas Y Legumbres Frescas (al Por Mayor)",
    "sg:phone":"+34 958 36 45 52",
    "sg:postcode":"18127",
    "sg:province":"Granada",
    "wof:name":"Olijayena Sdad.coop.andaluza",
    "wof:placetype":"venue"
},
  "geometry": {"coordinates":[-3.8188650608,36.9488945007],"type":"Point"}
}