{
  "type": "Feature",
  "properties": {
    "iso:country":"ES",
    "sg:address":"Plaz Lugo (de), 9",
    "sg:city":"Viveiro",
    "sg:orig_category":"M\u00c9dicos: Medicina Interna",
    "sg:phone":"+34 982 56 03 89",
    "sg:postcode":"27850",
    "sg:province":"Lugo",
    "wof:name":"Lamas Rocha Ramon",
    "wof:placetype":"venue"
},
  "geometry": {"coordinates":[-7.5959348679,43.6629714966],"type":"Point"}
}