{
  "type": "Feature",
  "properties": {
    "iso:country":"ES",
    "sg:address":"Calle de Yegua, 2",
    "sg:city":"Valdezorras",
    "sg:orig_category":"Promotores Constructores",
    "sg:phone":"+34 954 67 07 87",
    "sg:postcode":"41020",
    "sg:province":"Sevilla",
    "wof:name":"Fernandez Rodriguez Jose Antonio",
    "wof:placetype":"venue"
},
  "geometry": {"coordinates":[-5.9287462234,37.4269828796],"type":"Point"}
}