{
  "type": "Feature",
  "properties": {
    "iso:country":"ES",
    "sg:address":"Calle de Metalurgias (las), 13",
    "sg:city":"Alacant",
    "sg:orig_category":"Comercio De Piezas De Recambio Y De Accesorios De Veh\u00cdculos, Veh\u00cdculos Industriales",
    "sg:phone":"+34 965 28 75 98",
    "sg:postcode":"03008",
    "sg:province":"Alicante",
    "wof:name":"Comercial Fren Aire S.l.",
    "wof:placetype":"venue"
},
  "geometry": {"coordinates":[-0.5156180263,38.3378181458],"type":"Point"}
}