{
  "type": "Feature",
  "properties": {
    "addr:full":"Calle de Manuel Alejandro, 21 Jerez De La Frontera C\u00e1diz 11407",
    "addr:housenumber":"21",
    "addr:postcode":"11407",
    "addr:street":"Calle De Manuel Alejandro",
    "iso:country":"ES",
    "sg:address":"Calle de Manuel Alejandro, 21",
    "sg:city":"Jerez De La Frontera",
    "sg:orig_category":"Mantenimiento Industrial",
    "sg:phone":"+34 956 31 19 13",
    "sg:postcode":"11407",
    "sg:province":"C\u00e1diz",
    "wof:name":"Mantenimientos Industriales Jose A. Lora S.l.",
    "wof:placetype":"venue"
},
  "geometry": {"coordinates":[-6.0982751846,36.7228431702],"type":"Point"}
}