{
  "type": "Feature",
  "properties": {
    "addr:full":"O Igrexario, 103 Hio Pontevedra 36948",
    "addr:housenumber":"103",
    "addr:postcode":"36948",
    "addr:street":"Hio Pontevedra",
    "iso:country":"ES",
    "sg:address":"O Igrexario, 103",
    "sg:city":"Hio",
    "sg:orig_category":"Bazares, Art\u00cdculos De Limpieza Y De Cocina (al Por Menor)",
    "sg:phone":"+34 986 32 94 81",
    "sg:postcode":"36948",
    "sg:province":"Pontevedra",
    "wof:name":"Rial Hermelo Antonio",
    "wof:placetype":"venue"
},
  "geometry": {"coordinates":[-8.6428003311,42.4304618835],"type":"Point"}
}