{
  "type": "Feature",
  "properties": {
    "iso:country":"ES",
    "sg:address":"Calle de Rosa (la), 18",
    "sg:city":"Tauste",
    "sg:orig_category":"Aguas (distribuci\u00d3n, Servicios)",
    "sg:phone":"+34 976 86 97 45",
    "sg:postcode":"50660",
    "sg:province":"Zaragoza",
    "wof:name":"Gestion Y Tecnicas Del Agua S.a.",
    "wof:placetype":"venue"
},
  "geometry": {"coordinates":[-1.2561370134,41.9201087952],"type":"Point"}
}