{
  "type": "Feature",
  "properties": {
    "iso:country":"ES",
    "sg:address":"Rava Jesus, 40",
    "sg:city":"Reus",
    "sg:orig_category":"Farmacias",
    "sg:phone":"+34 977 31 06 57",
    "sg:postcode":"43201",
    "sg:province":"Tarragona",
    "wof:name":"Cavalle Vallverdu Jorge",
    "wof:placetype":"venue"
},
  "geometry": {"coordinates":[1.1078150272,41.15417099],"type":"Point"}
}