{
  "type": "Feature",
  "properties": {
    "addr:full":"Calle de Doctor Gomez Ulla, 53 Salamanca Salamanca 37003",
    "addr:housenumber":"53",
    "addr:postcode":"37003",
    "addr:street":"Calle De Doctor Gomez Ulla",
    "iso:country":"ES",
    "sg:address":"Calle de Doctor Gomez Ulla, 53",
    "sg:city":"Salamanca",
    "sg:orig_category":"Guarder\u00cdas",
    "sg:phone":"+34 923 18 77 30",
    "sg:postcode":"37003",
    "sg:province":"Salamanca",
    "wof:name":"Gonzalez Nuevo Maria Victoria",
    "wof:placetype":"venue"
},
  "geometry": {"coordinates":[-5.651863575,40.9679031372],"type":"Point"}
}