{
  "type": "Feature",
  "properties": {
    "addr:full":"Calle de Efigenia, 23 Madrid Madrid 28032",
    "addr:housenumber":"23",
    "addr:postcode":"madrid;28032",
    "addr:street":"Calle De Efigenia",
    "iso:country":"ES",
    "sg:address":"Calle de Efigenia, 23",
    "sg:city":"Madrid",
    "sg:orig_category":"Quincaller\u00cda (al Por Menor)",
    "sg:phone":"+34 917 76 01 62",
    "sg:postcode":"28032",
    "sg:province":"Madrid",
    "wof:name":"Pedro Pascual Pedro De",
    "wof:placetype":"venue"
},
  "geometry": {"coordinates":[-3.5992040634,40.4040336609],"type":"Point"}
}