{
  "type": "Feature",
  "properties": {
    "addr:full":"Calle de Bulas, 40 Toledo Toledo 45002",
    "addr:housenumber":"40",
    "addr:postcode":"45002",
    "addr:street":"Calle De Bulas",
    "iso:country":"ES",
    "sg:address":"Calle de Bulas, 40",
    "sg:city":"Toledo",
    "sg:orig_category":"Empresas De Vigilancia, Guardia Y Protecci\u00d3n",
    "sg:phone":"+34 925 21 55 89",
    "sg:postcode":"45002",
    "sg:province":"Toledo",
    "wof:name":"Garcia Jimenez Eduardo",
    "wof:placetype":"venue"
},
  "geometry": {"coordinates":[-4.029715538,39.8578910828],"type":"Point"}
}