{
  "type": "Feature",
  "properties": {
    "addr:full":"Calle de Alenza, 1 Madrid Madrid 28003",
    "addr:housenumber":"1",
    "addr:postcode":"28003",
    "addr:street":"Calle De Alenza",
    "iso:country":"ES",
    "sg:address":"Calle de Alenza, 1",
    "sg:city":"Madrid",
    "sg:orig_category":"Asociaciones, Organismos Culturales Y Socioeducativos",
    "sg:phone":"+34 914 41 79 21",
    "sg:postcode":"28003",
    "sg:province":"Madrid",
    "wof:name":"Fundacion Gomez Pardo",
    "wof:placetype":"venue"
},
  "geometry": {"coordinates":[-3.7007236481,40.4425773621],"type":"Point"}
}