{
  "type": "Feature",
  "properties": {
    "iso:country":"ES",
    "sg:address":"C/ Reverend Guillem Coll, 7",
    "sg:city":"Ferreries",
    "sg:orig_category":"Mec\u00c1nico Del Autom\u00d3vil",
    "sg:phone":"+34 971 15 50 20",
    "sg:postcode":"07750",
    "sg:province":"Islas Baleares",
    "wof:name":"Triay Riera Eugenio",
    "wof:placetype":"venue"
},
  "geometry": {"coordinates":[4.0123310089,39.9834480286],"type":"Point"}
}