{
  "type": "Feature",
  "properties": {
    "iso:country":"ES",
    "sg:address":"Calle de San Rafael, 1",
    "sg:city":"Fuengirola",
    "sg:orig_category":"Bisuter\u00cda, Joyer\u00cda, Relojer\u00cda (al Por Menor)",
    "sg:phone":"+34 952 47 10 72",
    "sg:postcode":"29640",
    "sg:province":"M\u00e1laga",
    "wof:name":"Espino Martin Lourdes",
    "wof:placetype":"venue"
},
  "geometry": {"coordinates":[-4.6254911423,36.5377120972],"type":"Point"}
}