{
  "type": "Feature",
  "properties": {
    "iso:country":"ES",
    "sg:address":"Avda Valdelaparra (de), 27",
    "sg:city":"Alcobendas",
    "sg:orig_category":"Centros Empresariales",
    "sg:phone":"+34 916 61 97 89",
    "sg:postcode":"28108",
    "sg:province":"Madrid",
    "wof:name":"Thermo Electron S.a.",
    "wof:placetype":"venue"
},
  "geometry": {"coordinates":[-3.6466300488,40.5387420654],"type":"Point"}
}