{
  "type": "Feature",
  "properties": {
    "iso:country":"ES",
    "sg:address":"Calle de Adelfas, 6",
    "sg:city":"Palma Rio",
    "sg:orig_category":"Supermercados Y Hipermercados",
    "sg:phone":"+34 957 71 00 82",
    "sg:postcode":"14700",
    "sg:province":"C\u00f3rdoba",
    "wof:name":"Consuelo Navarro Garre Y Angeles Garcia Cabrera Cdad.",
    "wof:placetype":"venue"
},
  "geometry": {"coordinates":[-5.2803072929,37.7056617737],"type":"Point"}
}