{
  "type": "Feature",
  "properties": {
    "iso:country":"ES",
    "sg:address":"Carrer de Castellassa, 24",
    "sg:city":"Terrassa",
    "sg:orig_category":"Asociaciones Y Clubs Deportivos",
    "sg:phone":"+34 937 84 18 88",
    "sg:postcode":"08227",
    "sg:province":"Barcelona",
    "wof:name":"Cressi Sub Espa\u00f1a S.a.",
    "wof:placetype":"venue"
},
  "geometry": {"coordinates":[2.0330379009,41.5792922974],"type":"Point"}
}