{
  "type": "Feature",
  "properties": {
    "addr:full":"Av Pais Valenciano, 4 Museros Valencia 46136",
    "addr:housenumber":"4",
    "addr:postcode":"46136",
    "addr:street":"Av Pais Valenciano",
    "iso:country":"ES",
    "sg:address":"Av Pais Valenciano, 4",
    "sg:city":"Museros",
    "sg:orig_category":"Arquitectos",
    "sg:phone":"+34 961 44 06 08",
    "sg:postcode":"46136",
    "sg:province":"Valencia",
    "wof:name":"Campos Fort Jose Maria",
    "wof:placetype":"venue"
},
  "geometry": {"coordinates":[-0.3419679999,39.5628547668],"type":"Point"}
}