{
  "type": "Feature",
  "properties": {
    "addr:full":"Calle de Tajo (del), 17 Mejorada Campo Madrid 28840",
    "addr:housenumber":"17",
    "addr:postcode":"28840",
    "addr:street":"Calle De Tajo Del",
    "iso:country":"ES",
    "sg:address":"Calle de Tajo (del), 17",
    "sg:city":"Mejorada Campo",
    "sg:orig_category":"Rectificaci\u00d3n, Mecanizado, Fresado",
    "sg:phone":"+34 916 68 02 62",
    "sg:postcode":"28840",
    "sg:province":"Madrid",
    "wof:name":"Talleres Rus S.a.",
    "wof:placetype":"venue"
},
  "geometry": {"coordinates":[-3.4860999584,40.3850631714],"type":"Point"}
}