{
  "type": "Feature",
  "properties": {
    "iso:country":"ES",
    "sg:address":"Carrer de Cultura, 39",
    "sg:city":"Santa Coloma De Gramenet",
    "sg:orig_category":"Farmacias",
    "sg:phone":"+34 933 86 23 22",
    "sg:postcode":"08922",
    "sg:province":"Barcelona",
    "wof:name":"Ale Olle Enrique",
    "wof:placetype":"venue"
},
  "geometry": {"coordinates":[2.2082247734,41.4473075867],"type":"Point"}
}