{
  "type": "Feature",
  "properties": {
    "iso:country":"ES",
    "sg:address":"Calle de Isla De La Gomera, 11",
    "sg:city":"Caceres",
    "sg:orig_category":"Enfermeras: Consultas, Atenci\u00d3n A Domicilio",
    "sg:phone":"+34 927 23 05 71",
    "sg:postcode":"10001",
    "sg:province":"C\u00e1ceres",
    "wof:name":"Hernandez Gutierrez Jose Antonio",
    "wof:placetype":"venue"
},
  "geometry": {"coordinates":[-6.3854289055,39.4753875732],"type":"Point"}
}