{
  "type": "Feature",
  "properties": {
    "addr:full":"Pol Ind La Estrella, S/n Coria Rio Sevilla 41100",
    "addr:housenumber":"s",
    "addr:postcode":"41100",
    "addr:street":"/ N",
    "iso:country":"ES",
    "sg:address":"Pol Ind La Estrella, S/n",
    "sg:city":"Coria Rio",
    "sg:orig_category":"Ambulancias",
    "sg:phone":"+34 954 77 55 14",
    "sg:postcode":"41100",
    "sg:province":"Sevilla",
    "wof:name":"Ambulancias Tenorio E Hijos S.l.",
    "wof:placetype":"venue"
},
  "geometry": {"coordinates":[-5.9962949753,37.3826408386],"type":"Point"}
}