{
  "type": "Feature",
  "properties": {
    "iso:country":"ES",
    "sg:address":"Calle de Escalinata, 1",
    "sg:city":"Madrid",
    "sg:orig_category":"Porcelanas, Azulejos (fabricaci\u00d3n, Al Por Mayor)",
    "sg:phone":"+34 915 47 12 47",
    "sg:postcode":"28013",
    "sg:province":"Madrid",
    "wof:name":"Multiplicidad Y Arte En El Regalo S.l.",
    "wof:placetype":"venue"
},
  "geometry": {"coordinates":[-3.70946908,40.4170188904],"type":"Point"}
}