{
  "type": "Feature",
  "properties": {
    "addr:full":"Carrer de Or (de L'), S/n Floresta Tarragona 43006",
    "addr:housenumber":"s / n",
    "addr:postcode":"43006",
    "addr:street":"Carrer De Or De L '",
    "iso:country":"ES",
    "sg:address":"Carrer de Or (de L'), S/n",
    "sg:city":"Floresta",
    "sg:orig_category":"Distribuci\u00d3n De Petr\u00d3leo Y Derivados",
    "sg:phone":"+34 977 55 11 05",
    "sg:postcode":"43006",
    "sg:province":"Tarragona",
    "wof:name":"Agip Espa\u00f1a S.a.",
    "wof:placetype":"venue"
},
  "geometry": {"coordinates":[1.2311987877,41.1406097412],"type":"Point"}
}