{
  "type": "Feature",
  "properties": {
    "addr:full":"Calle de Maria Auxiliadora, 6 Villamartin C\u00e1diz 11650",
    "addr:housenumber":"6",
    "addr:postcode":"11650",
    "addr:street":"Calle De Maria Auxiliadora;Ca\u0301Diz",
    "iso:country":"ES",
    "sg:address":"Calle de Maria Auxiliadora, 6",
    "sg:city":"Villamartin",
    "sg:orig_category":"Muebles, Minoristas",
    "sg:phone":"+34 956 71 52 78",
    "sg:postcode":"11650",
    "sg:province":"C\u00e1diz",
    "wof:name":"Calderon Atienza Juan",
    "wof:placetype":"venue"
},
  "geometry": {"coordinates":[-5.6369972229,36.8578987122],"type":"Point"}
}