{
  "type": "Feature",
  "properties": {
    "iso:country":"ES",
    "sg:address":"Avda Isabel De Moctezuma, 3",
    "sg:city":"Caceres",
    "sg:orig_category":"Estancos",
    "sg:phone":"+34 927 22 42 40",
    "sg:postcode":"10005",
    "sg:province":"C\u00e1ceres",
    "wof:name":"Bernal Garcia Jesus",
    "wof:placetype":"venue"
},
  "geometry": {"coordinates":[-6.3789892197,39.4646110535],"type":"Point"}
}