{
  "type": "Feature",
  "properties": {
    "addr:full":"Carrer de Rasa, 81 Terrassa Barcelona 08221",
    "addr:housenumber":"81",
    "addr:postcode":"08221",
    "addr:street":"Carrer De Rasa",
    "iso:country":"ES",
    "sg:address":"Carrer de Rasa, 81",
    "sg:city":"Terrassa",
    "sg:orig_category":"Inmobiliaria (agencias)",
    "sg:phone":"+34 937 80 67 37",
    "sg:postcode":"08221",
    "sg:province":"Barcelona",
    "wof:name":"Doss Centre D'oficines I Serveis S. L.",
    "wof:placetype":"venue"
},
  "geometry": {"coordinates":[2.0083200932,41.5644111633],"type":"Point"}
}