{
  "type": "Feature",
  "properties": {
    "addr:full":"Plaz Cosmos, 2 Valladolid Valladolid 47009",
    "addr:housenumber":"2",
    "addr:postcode":"47009",
    "iso:country":"ES",
    "sg:address":"Plaz Cosmos, 2",
    "sg:city":"Valladolid",
    "sg:orig_category":"Inform\u00c1tica, Ofim\u00c1tica (estudios, Asesor\u00cda, Ingenier\u00cda, Formaci\u00d3n)",
    "sg:phone":"+34 983 15 54 60",
    "sg:postcode":"47009",
    "sg:province":"Valladolid",
    "wof:name":"Media Networks Castilla 2002, S.l.",
    "wof:placetype":"venue"
},
  "geometry": {"coordinates":[-4.7336750031,41.6636314392],"type":"Point"}
}