{
  "type": "Feature",
  "properties": {
    "addr:full":"Avda Calvario, 4 Rociana Condado Huelva 21720",
    "addr:housenumber":"4",
    "addr:postcode":"21720",
    "addr:street":"Avda Calvario",
    "iso:country":"ES",
    "sg:address":"Avda Calvario, 4",
    "sg:city":"Rociana Condado",
    "sg:orig_category":"Molduras, Junquillos, Listones Y Molduras Perforadas",
    "sg:phone":"+34 959 41 63 30",
    "sg:postcode":"21720",
    "sg:province":"Huelva",
    "wof:name":"Cano Palomo Ceferino",
    "wof:placetype":"venue"
},
  "geometry": {"coordinates":[-6.6019768715,37.3051986694],"type":"Point"}
}