{
  "type": "Feature",
  "properties": {
    "addr:full":"Calle de Alcalde Rafael Diaz, 49 Arucas Las Palmas 35400",
    "addr:housenumber":"49",
    "addr:postcode":"35400",
    "addr:street":"Calle De Alcalde Rafael Diaz",
    "iso:country":"ES",
    "sg:address":"Calle de Alcalde Rafael Diaz, 49",
    "sg:city":"Arucas",
    "sg:orig_category":"Centros Empresariales",
    "sg:phone":"+34 928 62 34 58",
    "sg:postcode":"35400",
    "sg:province":"Las Palmas",
    "wof:name":"Ccorimanya Mamani Balvina",
    "wof:placetype":"venue"
},
  "geometry": {"coordinates":[-15.5259523392,28.1238746643],"type":"Point"}
}