{
  "type": "Feature",
  "properties": {
    "iso:country":"ES",
    "sg:address":"Avda Paz, 168",
    "sg:city":"Yecla",
    "sg:orig_category":"Muebles Y Accesorios Para Cocinas Y Cuartos De Ba\u00d1o (al Por Menor)",
    "sg:phone":"+34 968 75 38 93",
    "sg:postcode":"30510",
    "sg:province":"Murcia",
    "wof:name":"Muebles De Ba\u00f1o Caballito S.l.",
    "wof:placetype":"venue"
},
  "geometry": {"coordinates":[-1.1329590082,38.613571167],"type":"Point"}
}