{
  "type": "Feature",
  "properties": {
    "addr:full":"Calle de Fraguas, 1 Torrejon Ardoz Madrid 28850",
    "addr:housenumber":"1",
    "addr:postcode":"28850",
    "addr:street":"Calle De Fraguas",
    "iso:country":"ES",
    "sg:address":"Calle de Fraguas, 1",
    "sg:city":"Torrejon Ardoz",
    "sg:orig_category":"Organizaciones Internacionales",
    "sg:phone":"+34 916 76 08 60",
    "sg:postcode":"28850",
    "sg:province":"Madrid",
    "wof:name":"Caritas Diocesana De Alcala De Henares",
    "wof:placetype":"venue"
},
  "geometry": {"coordinates":[-3.4802899361,40.4597625732],"type":"Point"}
}