{
  "type": "Feature",
  "properties": {
    "iso:country":"ES",
    "sg:address":"Calle de Cerrillos Redondos, 12",
    "sg:city":"San Rafael",
    "sg:orig_category":"Arquitectos",
    "sg:phone":"+34 921 17 16 87",
    "sg:postcode":"40410",
    "sg:province":"Segovia",
    "wof:name":"Veguillas Diez Jose Manuel",
    "wof:placetype":"venue"
},
  "geometry": {"coordinates":[-4.1829061508,40.7129211426],"type":"Point"}
}