{
  "type": "Feature",
  "properties": {
    "iso:country":"ES",
    "sg:address":"Poli Industrial De Lourdes, S/n",
    "sg:city":"Coin",
    "sg:orig_category":"Panader\u00cdas, Panader\u00cdas",
    "sg:phone":"+34 952 45 29 77",
    "sg:postcode":"29100",
    "sg:province":"M\u00e1laga",
    "wof:name":"Aguepan S.l.",
    "wof:placetype":"venue"
},
  "geometry": {"coordinates":[-4.7484517097,36.6660003662],"type":"Point"}
}