{
  "type": "Feature",
  "properties": {
    "addr:full":"Calle de Marina (la), 26 Santa Cruz De Tenerife Santa Cruz De Tenerife 38001",
    "addr:housenumber":"26",
    "addr:postcode":"38001",
    "addr:street":"Calle De Marina La",
    "iso:country":"ES",
    "sg:address":"Calle de Marina (la), 26",
    "sg:city":"Santa Cruz De Tenerife",
    "sg:orig_category":"Barcos",
    "sg:phone":"+34 922 24 99 63",
    "sg:postcode":"38001",
    "sg:province":"Santa Cruz De Tenerife",
    "wof:name":"Sociedad Estatal De Estiba Y Desestiba Del Puerto De Santa Cruz De Tenerife S.a.",
    "wof:placetype":"venue"
},
  "geometry": {"coordinates":[-16.2474422455,28.4727935791],"type":"Point"}
}