{
  "type": "Feature",
  "properties": {
    "iso:country":"ES",
    "sg:address":"Calle de Iii(romica), 8",
    "sg:city":"Albacete",
    "sg:orig_category":"Montaje, Alquiler De Andamiajes",
    "sg:phone":"+34 967 25 41 80",
    "sg:postcode":"02006",
    "sg:province":"Albacete",
    "wof:name":"Alquiler De Maquinaria Realman S.l.",
    "wof:placetype":"venue"
},
  "geometry": {"coordinates":[-1.9490209818,39.013168335],"type":"Point"}
}