{
  "type": "Feature",
  "properties": {
    "addr:full":"Poli Poligono Industrial Chinales, S/n Cordoba C\u00f3rdoba 14007",
    "addr:housenumber":"s",
    "addr:postcode":"14007",
    "addr:street":"Industrial;/ N;Co\u0301Rdoba",
    "iso:country":"ES",
    "sg:address":"Poli Poligono Industrial Chinales, S/n",
    "sg:city":"Cordoba",
    "sg:orig_category":"Electricidad: Equipos Industriales, Componentes (fabricaci\u00d3n)",
    "sg:phone":"+34 957 40 33 55",
    "sg:postcode":"14007",
    "sg:province":"C\u00f3rdoba",
    "wof:name":"Suministros Electricos Herper S.l.",
    "wof:placetype":"venue"
},
  "geometry": {"coordinates":[-4.7784028053,37.8779411316],"type":"Point"}
}