{
  "type": "Feature",
  "properties": {
    "iso:country":"ES",
    "sg:address":"Avda Gregorio Prieto, 17",
    "sg:city":"Valdepe\u00f1as",
    "sg:orig_category":"Agentes, Concesionarios Y Sucursales De Veh\u00cdculos",
    "sg:phone":"+34 926 32 28 14",
    "sg:postcode":"13300",
    "sg:province":"Ciudad Real",
    "wof:name":"Fuentes Ortega Carlos",
    "wof:placetype":"venue"
},
  "geometry": {"coordinates":[-3.3875789642,38.7660598755],"type":"Point"}
}