{
  "type": "Feature",
  "properties": {
    "addr:full":"Pol Ind Llave Andalucia, S/n Bailen Ja\u00e9n 23710",
    "addr:postcode":"23710",
    "addr:street":"Andalucia S / N;Jae\u0301N",
    "iso:country":"ES",
    "sg:address":"Pol Ind Llave Andalucia, S/n",
    "sg:city":"Bailen",
    "sg:orig_category":"Cer\u00c1mica Art\u00cdstica Y Decorativa",
    "sg:phone":"+34 953 67 39 13",
    "sg:postcode":"23710",
    "sg:province":"Ja\u00e9n",
    "wof:name":"Pastor Garcia Pedro",
    "wof:placetype":"venue"
},
  "geometry": {"coordinates":[-3.7732720375,38.0856132507],"type":"Point"}
}