{
  "type": "Feature",
  "properties": {
    "addr:full":"Pase Castellana, 177 Madrid Madrid 28046",
    "addr:housenumber":"177",
    "addr:postcode":"28046",
    "addr:street":"Castellana",
    "iso:country":"ES",
    "sg:address":"Pase Castellana, 177",
    "sg:city":"Madrid",
    "sg:orig_category":"Psic\u00d3logos",
    "sg:phone":"+34 915 71 57 08",
    "sg:postcode":"28046",
    "sg:province":"Madrid",
    "wof:name":"Fernandez Fernandez Eva Maria",
    "wof:placetype":"venue"
},
  "geometry": {"coordinates":[-3.6902370453,40.4629173279],"type":"Point"}
}