{
  "type": "Feature",
  "properties": {
    "addr:full":"Avda Habana (de La), 11 Ourense Ourense 32003",
    "addr:housenumber":"11",
    "addr:postcode":"32003",
    "addr:street":"Avda Habana De La",
    "iso:country":"ES",
    "sg:address":"Avda Habana (de La), 11",
    "sg:city":"Ourense",
    "sg:orig_category":"Alimentaci\u00d3n General (al Por Menor)",
    "sg:phone":"+34 988 21 02 88",
    "sg:postcode":"32003",
    "sg:province":"Ourense",
    "wof:name":"Murciego Murciego Herminio",
    "wof:placetype":"venue"
},
  "geometry": {"coordinates":[-7.8665571213,42.342956543],"type":"Point"}
}