{
  "type": "Feature",
  "properties": {
    "iso:country":"ES",
    "sg:address":"Carr Onze De Setembre, 19",
    "sg:city":"Cervera",
    "sg:orig_category":"Ebanister\u00cda",
    "sg:phone":"+34 973 53 29 42",
    "sg:postcode":"25200",
    "sg:province":"Lleida",
    "wof:name":"Montero Linares Josep",
    "wof:placetype":"venue"
},
  "geometry": {"coordinates":[1.27303195,41.67552948],"type":"Point"}
}