{
  "type": "Feature",
  "properties": {
    "addr:full":"Av Comunitat Valenciana, 1 Altea Alicante 03590",
    "addr:housenumber":"1",
    "addr:postcode":"03590",
    "addr:street":"Av Comunitat",
    "iso:country":"ES",
    "sg:address":"Av Comunitat Valenciana, 1",
    "sg:city":"Altea",
    "sg:orig_category":"M\u00c9dicos: Estomatolog\u00cda",
    "sg:phone":"+34 965 84 08 54",
    "sg:postcode":"03590",
    "sg:province":"Alicante",
    "wof:name":"Robirosa Pistone Claudia",
    "wof:placetype":"venue"
},
  "geometry": {"coordinates":[-0.0484340005,38.60414505],"type":"Point"}
}