{
  "type": "Feature",
  "properties": {
    "iso:country":"ES",
    "sg:address":"Pol. Ind. S. Joan, 25",
    "sg:city":"Palamos",
    "sg:orig_category":"Fabricaci\u00d3n, Venta, Instalaci\u00d3n De R\u00d3tulos, De R\u00d3tulos Luminosos",
    "sg:phone":"+34 972 60 11 01",
    "sg:postcode":"17230",
    "sg:province":"Girona",
    "wof:name":"Retols Futura S.l.",
    "wof:placetype":"venue"
},
  "geometry": {"coordinates":[3.1294350624,41.85546875],"type":"Point"}
}