{
  "type": "Feature",
  "properties": {
    "addr:full":"Calle de Perez Comend., 17 Malpartida Caceres C\u00e1ceres 10910",
    "addr:housenumber":"17",
    "addr:postcode":"10910",
    "addr:street":"Calle De Perez Comend.;Ca\u0301Ceres",
    "iso:country":"ES",
    "sg:address":"Calle de Perez Comend., 17",
    "sg:city":"Malpartida Caceres",
    "sg:orig_category":"Ense\u00d1anza, Formaci\u00d3n Profesional: Aprendizaje",
    "sg:phone":"+34 927 27 64 62",
    "sg:postcode":"10910",
    "sg:province":"C\u00e1ceres",
    "wof:name":"Mancomunidad De Municipios Tajo-salor",
    "wof:placetype":"venue"
},
  "geometry": {"coordinates":[-6.5076742172,39.4432449341],"type":"Point"}
}