{
  "type": "Feature",
  "properties": {
    "addr:full":"Calle de Molino, 37 Iscar Valladolid 47420",
    "addr:housenumber":"37",
    "addr:postcode":"47420",
    "addr:street":"Calle De Molino",
    "iso:country":"ES",
    "sg:address":"Calle de Molino, 37",
    "sg:city":"Iscar",
    "sg:orig_category":"Ense\u00d1anza: Comercio, Gesti\u00d3n, Inform\u00c1tica",
    "sg:phone":"+34 983 62 02 43",
    "sg:postcode":"47420",
    "sg:province":"Valladolid",
    "wof:name":"Frias Fernandez Angel",
    "wof:placetype":"venue"
},
  "geometry": {"coordinates":[-4.5283689499,41.365688324],"type":"Point"}
}