{
  "type": "Feature",
  "properties": {
    "addr:full":"Calle de Nuestra Se\u00d1ora De Los Angeles, 12 Sangonera La Verde O Ermita Nueva Murcia 30833",
    "addr:housenumber":"12",
    "addr:postcode":"30833",
    "addr:street":"Calle De Nuestra Sen\u0303Ora De Los Angeles",
    "iso:country":"ES",
    "sg:address":"Calle de Nuestra Se\u00d1ora De Los Angeles, 12",
    "sg:city":"Sangonera La Verde O Ermita Nueva",
    "sg:orig_category":"Centros De Educaci\u00d3n Especial",
    "sg:phone":"+34 968 86 85 33",
    "sg:postcode":"30833",
    "sg:province":"Murcia",
    "wof:name":"Colegio Antonio Delgado Dorrego",
    "wof:placetype":"venue"
},
  "geometry": {"coordinates":[-1.2133489847,37.9320373535],"type":"Point"}
}