{
  "type": "Feature",
  "properties": {
    "addr:full":"Calle de Agustin Benito, 1 Matabuena Segovia 40163",
    "addr:housenumber":"1",
    "addr:postcode":"40163",
    "addr:street":"Calle De Agustin Benito",
    "iso:country":"ES",
    "sg:address":"Calle de Agustin Benito, 1",
    "sg:city":"Matabuena",
    "sg:orig_category":"Delegados, Agentes De Tr\u00c1nsito, Auxiliares De Transporte Internacional",
    "sg:phone":"+34 921 50 40 37",
    "sg:postcode":"40163",
    "sg:province":"Segovia",
    "wof:name":"Transportes Marta Y Veronica S.l.",
    "wof:placetype":"venue"
},
  "geometry": {"coordinates":[-3.7550036907,41.0947189331],"type":"Point"}
}