{
  "type": "Feature",
  "properties": {
    "iso:country":"ES",
    "sg:address":"Calle de Prado De Las Banderillas (del), 24",
    "sg:city":"Colmenar Viejo",
    "sg:orig_category":"Centros Empresariales",
    "sg:phone":"+34 918 46 78 87",
    "sg:postcode":"28770",
    "sg:province":"Madrid",
    "wof:name":"Ferreteria Ferayu S.l.",
    "wof:placetype":"venue"
},
  "geometry": {"coordinates":[-3.7664690018,40.6674003601],"type":"Point"}
}