{
  "type": "Feature",
  "properties": {
    "addr:full":"Carr Doctor Sanchis Bergon, 16 Eliana Valencia 46183",
    "addr:housenumber":"16",
    "addr:postcode":"46183",
    "addr:street":"Carr Doctor Sanchis Bergon",
    "iso:country":"ES",
    "sg:address":"Carr Doctor Sanchis Bergon, 16",
    "sg:city":"Eliana",
    "sg:orig_category":"Hoteles",
    "sg:phone":"+34 962 74 28 35",
    "sg:postcode":"46183",
    "sg:province":"Valencia",
    "wof:name":"Hotel Iris S.l.",
    "wof:placetype":"venue"
},
  "geometry": {"coordinates":[-0.5141400099,39.5553588867],"type":"Point"}
}