{
  "type": "Feature",
  "properties": {
    "iso:country":"ES",
    "sg:address":"O Espi\u00f1o, S/n",
    "sg:city":"Filgueira",
    "sg:orig_category":"Negocio De Madera",
    "sg:phone":"+34 986 79 40 94",
    "sg:postcode":"36512",
    "sg:province":"Pontevedra",
    "wof:name":"Blanabel S. L.",
    "wof:placetype":"venue"
},
  "geometry": {"coordinates":[-8.119058609,42.6696968079],"type":"Point"}
}