{
  "type": "Feature",
  "properties": {
    "addr:full":"G.v. Carles Iii, 86 Barcelona Barcelona 08028",
    "addr:housenumber":"86",
    "addr:postcode":"08028",
    "iso:country":"ES",
    "sg:address":"G.v. Carles Iii, 86",
    "sg:city":"Barcelona",
    "sg:orig_category":"Propiedad Industrial: Patentes De Inventos, Marcas, Modelos, Dise\u00d1os",
    "sg:phone":"+34 932 38 74 22",
    "sg:postcode":"08028",
    "sg:province":"Barcelona",
    "sg:website":"www.herreroasociados.es",
    "wof:name":"Herrero Y Asociados S.l.",
    "wof:placetype":"venue"
},
  "geometry": {"coordinates":[2.1687450409,41.3855895996],"type":"Point"}
}