{
  "type": "Feature",
  "properties": {
    "addr:full":"Monasterio Irache, 39 Iru\u00f1a Navarra 31011",
    "addr:housenumber":"39",
    "addr:postcode":"31011",
    "addr:street":"Irache",
    "iso:country":"ES",
    "sg:address":"Monasterio Irache, 39",
    "sg:city":"Iru\u00f1a",
    "sg:classifiers":[
        {
            "category":"Personal",
            "subcategory":"Barber",
            "type":"Services"
        }
    ],
    "sg:phone":"+34 948 17 62 91",
    "sg:postcode":"31011",
    "sg:province":"Navarra",
    "sg:tags":[
        "caballeros",
        "de",
        "peluqueros"
    ],
    "wof:name":"Gil Garcia Juan Carlos",
    "wof:placetype":"venue"
},
  "geometry": {"coordinates":[-1.6616078615,42.8166427612],"type":"Point"}
}