{
  "type": "Feature",
  "properties": {
    "addr:full":"Calle de Farm.agatangelo Soler, S/n Alacant Alicante 03011",
    "addr:postcode":"03011",
    "addr:street":"Calle De Farm.Agatangelo Soler S / N",
    "iso:country":"ES",
    "sg:address":"Calle de Farm.agatangelo Soler, S/n",
    "sg:city":"Alacant",
    "sg:orig_category":"Droguer\u00cdas (al Por Menor)",
    "sg:phone":"+34 965 17 96 31",
    "sg:postcode":"03011",
    "sg:province":"Alicante",
    "wof:name":"Lucas Hernandez Manuel",
    "wof:placetype":"venue"
},
  "geometry": {"coordinates":[-0.4883039892,38.375],"type":"Point"}
}