{
  "type": "Feature",
  "properties": {
    "addr:full":"Calle de Jose Alix Alix (de), 14 San Fernando De Henares Madrid 28830",
    "addr:housenumber":"14",
    "addr:postcode":"28830",
    "addr:street":"Calle De Jose Alix Alix De",
    "iso:country":"ES",
    "sg:address":"Calle de Jose Alix Alix (de), 14",
    "sg:city":"San Fernando De Henares",
    "sg:orig_category":"Asesor\u00cda Fiscal Y Jur\u00cddica",
    "sg:phone":"+34 916 69 60 85",
    "sg:postcode":"28830",
    "sg:province":"Madrid",
    "wof:name":"Gonzalez Parra Ricardo",
    "wof:placetype":"venue"
},
  "geometry": {"coordinates":[-3.5328478813,40.4276733398],"type":"Point"}
}