{
  "type": "Feature",
  "properties": {
    "addr:full":"Avd. Hnos. G. Del Moral, 2 Cabra C\u00f3rdoba 14940",
    "addr:housenumber":"2",
    "addr:postcode":"14940",
    "addr:street":"Hnos. G. Del Moral;Co\u0301Rdoba",
    "iso:country":"ES",
    "sg:address":"Avd. Hnos. G. Del Moral, 2",
    "sg:city":"Cabra",
    "sg:orig_category":"Agencias Y Asesores De Publicidad",
    "sg:phone":"+34 957 52 92 23",
    "sg:postcode":"14940",
    "sg:province":"C\u00f3rdoba",
    "wof:name":"Perez Pacho Sandra",
    "wof:placetype":"venue"
},
  "geometry": {"coordinates":[-4.4467329979,37.4725837708],"type":"Point"}
}