{
  "type": "Feature",
  "properties": {
    "iso:country":"ES",
    "sg:address":"Calle de Beato Tomas De Zumarraga, 5",
    "sg:city":"Vitoria-gasteiz",
    "sg:orig_category":"Centros De Educaci\u00d3n Especial",
    "sg:phone":"+34 945 14 00 66",
    "sg:postcode":"01008",
    "sg:province":"\u00c1lava",
    "wof:name":"Ayuntamiento De Vitoria-gasteiz",
    "wof:placetype":"venue"
},
  "geometry": {"coordinates":[-2.6784029007,42.8495407104],"type":"Point"}
}