{
  "type": "Feature",
  "properties": {
    "iso:country":"ES",
    "sg:address":"Calle de Doctor Villar, 15",
    "sg:city":"Linea De La Concepcion",
    "sg:orig_category":"Bisuter\u00cda, Joyer\u00cda, Relojer\u00cda (al Por Menor)",
    "sg:phone":"+34 956 76 88 06",
    "sg:postcode":"11300",
    "sg:province":"C\u00e1diz",
    "wof:name":"Jesus Franco Casuso Cb",
    "wof:placetype":"venue"
},
  "geometry": {"coordinates":[-5.3504376411,36.1623153687],"type":"Point"}
}