{
  "type": "Feature",
  "properties": {
    "addr:full":"Ptge Sant Cosme I Damia, 2 Vic Barcelona 08500",
    "addr:housenumber":"2",
    "addr:postcode":"08500",
    "addr:street":"Ptge Sant Cosme I Damia",
    "iso:country":"ES",
    "sg:address":"Ptge Sant Cosme I Damia, 2",
    "sg:city":"Vic",
    "sg:orig_category":"Librer\u00cdas",
    "sg:phone":"+34 938 85 11 83",
    "sg:postcode":"08500",
    "sg:province":"Barcelona",
    "wof:name":"Calahorro Escribano Pablo",
    "wof:placetype":"venue"
},
  "geometry": {"coordinates":[2.2542440891,41.9218177795],"type":"Point"}
}