{
  "type": "Feature",
  "properties": {
    "iso:country":"ES",
    "sg:address":"Calle de Bartolome Febles, 21",
    "sg:city":"Tunte",
    "sg:orig_category":"Organizaciones Profesionales",
    "sg:phone":"+34 928 12 70 57",
    "sg:postcode":"35290",
    "sg:province":"Las Palmas",
    "wof:name":"Monzon Gutierrez Juan Carlos",
    "wof:placetype":"venue"
},
  "geometry": {"coordinates":[-15.4300060272,28.1248226166],"type":"Point"}
}