{
  "type": "Feature",
  "properties": {
    "iso:country":"ES",
    "sg:address":"Avda Ejercito, S/n",
    "sg:city":"Guadalajara",
    "sg:orig_category":"Alquiler De Veh\u00cdculos: Turismos Y Utilitarios",
    "sg:phone":"+34 949 21 97 64",
    "sg:postcode":"19004",
    "sg:province":"Guadalajara",
    "wof:name":"Lozano Cuenca Miguel",
    "wof:placetype":"venue"
},
  "geometry": {"coordinates":[-3.1776790619,40.6312866211],"type":"Point"}
}