{
  "type": "Feature",
  "properties": {
    "addr:full":"Calle de Juan Bravo, 21 Segovia Segovia 40001",
    "addr:housenumber":"21",
    "addr:postcode":"40001",
    "addr:street":"Calle De Juan Bravo",
    "iso:country":"ES",
    "sg:address":"Calle de Juan Bravo, 21",
    "sg:city":"Segovia",
    "sg:orig_category":"Peleter\u00cdas",
    "sg:phone":"+34 921 46 26 71",
    "sg:postcode":"40001",
    "sg:province":"Segovia",
    "wof:name":"Calvo Vaca Santiago",
    "wof:placetype":"venue"
},
  "geometry": {"coordinates":[-4.1212468147,40.9482192993],"type":"Point"}
}