{
  "type": "Feature",
  "properties": {
    "addr:full":"Carr Josep Trueta, 3 Blanes Girona 17300",
    "addr:housenumber":"3",
    "addr:postcode":"17300",
    "addr:street":"Carr Josep Trueta",
    "iso:country":"ES",
    "sg:address":"Carr Josep Trueta, 3",
    "sg:city":"Blanes",
    "sg:orig_category":"Pescader\u00cdas (al Por Menor)",
    "sg:phone":"+34 972 33 60 93",
    "sg:postcode":"17300",
    "sg:province":"Girona",
    "wof:name":"Carrasqueor Cambero Dayne",
    "wof:placetype":"venue"
},
  "geometry": {"coordinates":[2.782793045,41.6665992737],"type":"Point"}
}