{
  "type": "Feature",
  "properties": {
    "addr:full":"Cmno Giraba, S/n Fraga Huesca 22520",
    "addr:housenumber":"s",
    "addr:postcode":"22520",
    "addr:street":"Cmno Giraba;/ N Fraga",
    "iso:country":"ES",
    "sg:address":"Cmno Giraba, S/n",
    "sg:city":"Fraga",
    "sg:orig_category":"Mec\u00c1nico Del Autom\u00d3vil",
    "sg:phone":"+34 974 47 21 35",
    "sg:postcode":"22520",
    "sg:province":"Huesca",
    "wof:name":"Europ Auto S. A.",
    "wof:placetype":"venue"
},
  "geometry": {"coordinates":[0.3351979852,41.527797699],"type":"Point"}
}