{
  "type": "Feature",
  "properties": {
    "iso:country":"ES",
    "sg:address":"Calle de Ramon Y Cajal, 5",
    "sg:city":"Ciudad Real",
    "sg:orig_category":"Empleados",
    "sg:phone":"+34 926 25 19 24",
    "sg:postcode":"13001",
    "sg:province":"Ciudad Real",
    "wof:name":"Castellanos Garcia Carmen",
    "wof:placetype":"venue"
},
  "geometry": {"coordinates":[-3.9274749756,38.9839553833],"type":"Point"}
}