{
  "type": "Feature",
  "properties": {
    "iso:country":"ES",
    "sg:address":"Carr Jaume Ii, 20",
    "sg:city":"Bisbal D'emporda",
    "sg:orig_category":"Papeler\u00cdas, Librer\u00cdas",
    "sg:phone":"+34 972 64 35 15",
    "sg:postcode":"17100",
    "sg:province":"Girona",
    "wof:name":"Font Gonzalez Anna",
    "wof:placetype":"venue"
},
  "geometry": {"coordinates":[3.0406308174,41.9640388489],"type":"Point"}
}