{
  "type": "Feature",
  "properties": {
    "addr:full":"Ctra Granada, 336 Jaen Ja\u00e9n 23001",
    "addr:housenumber":"336;jae\u0301n",
    "addr:postcode":"23001",
    "addr:street":"Ctra Granada",
    "iso:country":"ES",
    "sg:address":"Ctra Granada, 336",
    "sg:city":"Jaen",
    "sg:orig_category":"Asesor\u00cda Sobre Comunicaci\u00d3n De Empresas",
    "sg:phone":"+34 953 23 90 18",
    "sg:postcode":"23001",
    "sg:province":"Ja\u00e9n",
    "wof:name":"Proyectos Asesoria Y Servicios S.a.",
    "wof:placetype":"venue"
},
  "geometry": {"coordinates":[-3.7841889858,37.768699646],"type":"Point"}
}