{
  "type": "Feature",
  "properties": {
    "addr:full":"Calle de Alberto Aguilera, 6 Madrid Madrid 28015",
    "addr:housenumber":"6",
    "addr:postcode":"28015",
    "addr:street":"Calle De Alberto Aguilera",
    "iso:country":"ES",
    "sg:address":"Calle de Alberto Aguilera, 6",
    "sg:city":"Madrid",
    "sg:orig_category":"Ense\u00d1anza Variada",
    "sg:phone":"+34 914 45 19 44",
    "sg:postcode":"28015",
    "sg:province":"Madrid",
    "wof:name":"Sapientec Siglo Xxi S.l.",
    "wof:placetype":"venue"
},
  "geometry": {"coordinates":[-3.7067580223,40.4298477173],"type":"Point"}
}