{
  "type": "Feature",
  "properties": {
    "addr:full":"Calle de Progreso, 4 Ayerbe Huesca 22800",
    "addr:housenumber":"4",
    "addr:postcode":"22800",
    "addr:street":"Calle De Progreso",
    "iso:country":"ES",
    "sg:address":"Calle de Progreso, 4",
    "sg:city":"Ayerbe",
    "sg:orig_category":"Centros De Educaci\u00d3n Especial",
    "sg:phone":"+34 974 38 00 28",
    "sg:postcode":"22800",
    "sg:province":"Huesca",
    "wof:name":"Colegio Publico Ramon Y Cajal",
    "wof:placetype":"venue"
},
  "geometry": {"coordinates":[-0.687548995,42.2756767273],"type":"Point"}
}