{
  "type": "Feature",
  "properties": {
    "addr:full":"Calle de Duque De Wellington, 13 Vitoria-gasteiz \u00c1lava 01010",
    "addr:postcode":"01010",
    "addr:street":"Calle De Duque De Wellington 13",
    "iso:country":"ES",
    "sg:address":"Calle de Duque De Wellington, 13",
    "sg:city":"Vitoria-gasteiz",
    "sg:orig_category":"Laboratorios Y Trabajos De Fotograf\u00cda, V\u00cddeo Y Cine",
    "sg:phone":"+34 945 17 62 15",
    "sg:postcode":"01010",
    "sg:province":"\u00c1lava",
    "wof:name":"Foto Enrique Martin Sc",
    "wof:placetype":"venue"
},
  "geometry": {"coordinates":[-2.6915383339,42.8589096069],"type":"Point"}
}