{
  "type": "Feature",
  "properties": {
    "iso:country":"ES",
    "sg:address":"Calle de Miguel Hernandez, 28",
    "sg:city":"Alhama Murcia",
    "sg:orig_category":"Ense\u00d1anza Secundaria: Colegios Y Escuelas Privadas",
    "sg:phone":"+34 968 63 03 44",
    "sg:postcode":"30840",
    "sg:province":"Murcia",
    "wof:name":"Instituto De Educacion Secundaria Miguel Hernandez",
    "wof:placetype":"venue"
},
  "geometry": {"coordinates":[-1.4241490364,37.8507995605],"type":"Point"}
}