{
  "type": "Feature",
  "properties": {
    "addr:full":"Calle de Rio Duero, 8 Alcorcon Madrid 28923",
    "addr:housenumber":"8",
    "addr:postcode":"28923",
    "addr:street":"Calle De Rio Duero",
    "iso:country":"ES",
    "sg:address":"Calle de Rio Duero, 8",
    "sg:city":"Alcorcon",
    "sg:classifiers":[
        {
            "category":"Personal",
            "subcategory":"Barber",
            "type":"Services"
        }
    ],
    "sg:phone":"+34 916 12 77 53",
    "sg:postcode":"28923",
    "sg:province":"Madrid",
    "sg:tags":[
        "caballeros",
        "de",
        "peluqueros"
    ],
    "wof:name":"Ocampos Caballeros Antonio",
    "wof:placetype":"venue"
},
  "geometry": {"coordinates":[-3.8145859241,40.3438606262],"type":"Point"}
}