{
  "type": "Feature",
  "properties": {
    "addr:full":"Calle de Carlos Iv, 6 Madrid Madrid 28037",
    "addr:housenumber":"6",
    "addr:postcode":"28037",
    "addr:street":"Calle De Carlos Iv",
    "iso:country":"ES",
    "sg:address":"Calle de Carlos Iv, 6",
    "sg:city":"Madrid",
    "sg:orig_category":"Alimentaci\u00d3n General (al Por Menor)",
    "sg:phone":"+34 913 04 64 85",
    "sg:postcode":"28037",
    "sg:province":"Madrid",
    "wof:name":"Sanz Abad Fernando",
    "wof:placetype":"venue"
},
  "geometry": {"coordinates":[-3.618103981,40.4349937439],"type":"Point"}
}