{
  "type": "Feature",
  "properties": {
    "addr:full":"Av Francesc Macia, 46 Sabadell Barcelona 08206",
    "addr:housenumber":"46",
    "addr:postcode":"08206",
    "addr:street":"Av Francesc Macia",
    "iso:country":"ES",
    "sg:address":"Av Francesc Macia, 46",
    "sg:city":"Sabadell",
    "sg:orig_category":"Deportes Y Ocio: Art\u00cdculos Y Ropas (al Por Menor Y Accesorios)",
    "sg:phone":"+34 937 23 76 21",
    "sg:postcode":"08206",
    "sg:province":"Barcelona",
    "sg:website":"www.coroneltapiocca.com",
    "wof:name":"Coronel Tapioca S.a.",
    "wof:placetype":"venue"
},
  "geometry": {"coordinates":[2.0982708931,41.5533332825],"type":"Point"}
}