{
  "type": "Feature",
  "properties": {
    "iso:country":"ES",
    "sg:address":"Cami Mig, S/n",
    "sg:city":"Vilassar Dalt",
    "sg:orig_category":"Florister\u00cdas",
    "sg:phone":"+34 937 59 18 41",
    "sg:postcode":"08339",
    "sg:province":"Barcelona",
    "wof:name":"Puchol Sors Josep",
    "wof:placetype":"venue"
},
  "geometry": {"coordinates":[2.3729999065,41.5088233948],"type":"Point"}
}