{
  "type": "Feature",
  "properties": {
    "addr:full":"Avgd Morera, 6 Badalona Barcelona 08915",
    "addr:housenumber":"6",
    "addr:postcode":"08915",
    "addr:street":"Morera",
    "iso:country":"ES",
    "sg:address":"Avgd Morera, 6",
    "sg:city":"Badalona",
    "sg:orig_category":"Cajas De Ahorro",
    "sg:phone":"+34 933 95 01 50",
    "sg:postcode":"08915",
    "sg:province":"Barcelona",
    "wof:name":"Caixa D'estalvis I Pensions De Barcelona",
    "wof:placetype":"venue"
},
  "geometry": {"coordinates":[2.2487080097,41.4602890015],"type":"Point"}
}