{
  "type": "Feature",
  "properties": {
    "addr:full":"Ctra Cordoba-valencia, Km. 0126,0 Tobaruela-la Tortilla Ja\u00e9n 23700",
    "addr:postcode":"23700",
    "addr:street":"Ctra Cordoba-Valencia Km. 0126,0;Jae\u0301N",
    "iso:country":"ES",
    "sg:address":"Ctra Cordoba-valencia, Km. 0126,0",
    "sg:city":"Tobaruela-la Tortilla",
    "sg:orig_category":"Paneles De Madera: Contrachapados, Fibras, Particulados, Estratificados (fabricaci\u00d3n, Venta)",
    "sg:phone":"+34 953 60 70 30",
    "sg:postcode":"23700",
    "sg:province":"Ja\u00e9n",
    "wof:name":"Tableros De Fibras S.a.",
    "wof:placetype":"venue"
},
  "geometry": {"coordinates":[-3.6356039047,38.093914032],"type":"Point"}
}