{
  "type": "Feature",
  "properties": {
    "iso:country":"ES",
    "sg:address":"Carrer de Mestre Vigo I Garreta, 6",
    "sg:city":"Prat Llobregat",
    "sg:orig_category":"Ropa Para Se\u00d1oras Y Caballeros (al Por Menor)",
    "sg:phone":"+34 934 78 65 41",
    "sg:postcode":"08820",
    "sg:province":"Barcelona",
    "wof:name":"Zamora Gallardo Maria Del Carmen",
    "wof:placetype":"venue"
},
  "geometry": {"coordinates":[2.0896866322,41.3229637146],"type":"Point"}
}