{
  "type": "Feature",
  "properties": {
    "addr:full":"Calle de Nutria (de La), 1 Alcobendas Madrid 28109",
    "addr:postcode":"28109",
    "addr:street":"Calle De Nutria De La 1",
    "iso:country":"ES",
    "sg:address":"Calle de Nutria (de La), 1",
    "sg:city":"Alcobendas",
    "sg:orig_category":"Asesor\u00cda Sobre Comunicaci\u00d3n De Empresas",
    "sg:phone":"+34 916 50 26 17",
    "sg:postcode":"28109",
    "sg:province":"Madrid",
    "wof:name":"Persontrade S.l.",
    "wof:placetype":"venue"
},
  "geometry": {"coordinates":[-3.6271030903,40.5264701843],"type":"Point"}
}