{
  "type": "Feature",
  "properties": {
    "iso:country":"ES",
    "sg:address":"Calle de Carpio, 4",
    "sg:city":"Malaga",
    "sg:orig_category":"Puertas Y Portales",
    "sg:phone":"+34 952 33 11 17",
    "sg:postcode":"29002",
    "sg:province":"M\u00e1laga",
    "wof:name":"Villodres Rubio Concepcion",
    "wof:placetype":"venue"
},
  "geometry": {"coordinates":[-4.4385948181,36.7028961182],"type":"Point"}
}