{
  "type": "Feature",
  "properties": {
    "addr:full":"Urdaneta Bidea, 9 Zarautz Guip\u00f9zcoa 20800",
    "addr:housenumber":"9",
    "addr:postcode":"20800",
    "addr:street":"Urdaneta Bidea;Guipu\u0300Zcoa",
    "iso:country":"ES",
    "sg:address":"Urdaneta Bidea, 9",
    "sg:city":"Zarautz",
    "sg:orig_category":"Suministros Y Materiales Industriales",
    "sg:phone":"+34 943 13 20 45",
    "sg:postcode":"20800",
    "sg:province":"Guip\u00f9zcoa",
    "wof:name":"Productos Procesos Y Servicios, S.l.",
    "wof:placetype":"venue"
},
  "geometry": {"coordinates":[-2.1743540764,43.2821350098],"type":"Point"}
}