{
  "type": "Feature",
  "properties": {
    "addr:full":"Trss Creu, 21 Girona Girona 17002",
    "addr:housenumber":"21",
    "addr:postcode":"17002",
    "addr:street":"Creu",
    "iso:country":"ES",
    "sg:address":"Trss Creu, 21",
    "sg:city":"Girona",
    "sg:orig_category":"Materias Pl\u00c1sticas: Productos De Consumo Masivo (fabricaci\u00d3n, Al Por Mayor)",
    "sg:phone":"+34 972 41 23 17",
    "sg:postcode":"17002",
    "sg:province":"Girona",
    "wof:name":"Bdbosses S.l.",
    "wof:placetype":"venue"
},
  "geometry": {"coordinates":[2.8187448978,41.9808616638],"type":"Point"}
}