{
  "type": "Feature",
  "properties": {
    "iso:country":"ES",
    "sg:address":"Calle de Doctor Mara\u00d1on, S/n",
    "sg:city":"Cadiz",
    "sg:orig_category":"Asilos De Ancianos. Centros Privados",
    "sg:phone":"+34 956 22 60 00",
    "sg:postcode":"11002",
    "sg:province":"C\u00e1diz",
    "wof:name":"Diputacion Provincial-residencia De Ancianos Desamparados",
    "wof:placetype":"venue"
},
  "geometry": {"coordinates":[-6.305328846,36.5332450867],"type":"Point"}
}