{
  "type": "Feature",
  "properties": {
    "iso:country":"ES",
    "sg:address":"Carrer de Maladeta, 2",
    "sg:city":"Hospitalet Llobregat",
    "sg:orig_category":"Arreglo, Reparaci\u00d3n, Piezas Sueltas De Televisi\u00d3n, V\u00cddeo, Hi",
    "sg:phone":"+34 934 38 31 76",
    "sg:postcode":"08906",
    "sg:province":"Barcelona",
    "wof:name":"Cortes Pastor Miguel",
    "wof:placetype":"venue"
},
  "geometry": {"coordinates":[2.0989489555,41.3702812195],"type":"Point"}
}