{
  "type": "Feature",
  "properties": {
    "addr:full":"Calle de Estrauntza, 1 Bilbao Vizcaya 48011",
    "addr:housenumber":"1",
    "addr:postcode":"48011",
    "addr:street":"Calle De Estrauntza",
    "iso:country":"ES",
    "sg:address":"Calle de Estrauntza, 1",
    "sg:city":"Bilbao",
    "sg:orig_category":"Caf\u00c9s, Bares, Cervecer\u00cdas",
    "sg:phone":"+34 944 42 54 81",
    "sg:postcode":"48011",
    "sg:province":"Vizcaya",
    "wof:name":"Agorria Ortiz De Zarate Pablo",
    "wof:placetype":"venue"
},
  "geometry": {"coordinates":[-2.9396967888,43.2634658813],"type":"Point"}
}