{
  "type": "Feature",
  "properties": {
    "addr:full":"Calle de Herrero, 10 Castellon Castell\u00f3n 12002",
    "addr:housenumber":"10",
    "addr:postcode":"12002",
    "addr:street":"Calle De Herrero",
    "iso:country":"ES",
    "sg:address":"Calle de Herrero, 10",
    "sg:city":"Castellon",
    "sg:orig_category":"Arquitectos",
    "sg:phone":"+34 964 23 28 16",
    "sg:postcode":"12002",
    "sg:province":"Castell\u00f3n",
    "wof:name":"Monfort Salvador Ramon",
    "wof:placetype":"venue"
},
  "geometry": {"coordinates":[-0.0389279984,39.9825019836],"type":"Point"}
}