{
  "type": "Feature",
  "properties": {
    "iso:country":"ES",
    "sg:address":"Pla\u00c7 Cesar August Torras, 7",
    "sg:city":"Camprodon",
    "sg:orig_category":"Mercer\u00cda, Lencer\u00cda (al Por Menor)",
    "sg:phone":"+34 972 74 07 32",
    "sg:postcode":"17867",
    "sg:province":"Girona",
    "wof:name":"Nogue Salis Maria",
    "wof:placetype":"venue"
},
  "geometry": {"coordinates":[2.3652739525,42.3135986328],"type":"Point"}
}