{
  "type": "Feature",
  "properties": {
    "addr:full":"Calle de Medina Sidonia, 13 Cadiz C\u00e1diz 11012",
    "addr:housenumber":"13",
    "addr:postcode":"11012",
    "addr:street":"Calle De Medina Sidonia",
    "iso:country":"ES",
    "sg:address":"Calle de Medina Sidonia, 13",
    "sg:city":"Cadiz",
    "sg:orig_category":"Electrodom\u00c9sticos (al Por Menor)",
    "sg:phone":"+34 956 26 43 94",
    "sg:postcode":"11012",
    "sg:province":"C\u00e1diz",
    "wof:name":"Pasteleria La Chiclanera S.l.",
    "wof:placetype":"venue"
},
  "geometry": {"coordinates":[-6.2750921249,36.5126953125],"type":"Point"}
}