{
  "type": "Feature",
  "properties": {
    "iso:country":"ES",
    "sg:address":"Avda Cinco Villas, 17",
    "sg:city":"Tauste",
    "sg:orig_category":"Refiner\u00cdas De Petr\u00d3leo",
    "sg:phone":"+34 976 85 60 88",
    "sg:postcode":"50660",
    "sg:province":"Zaragoza",
    "wof:name":"Brus Refrigeration Of Spain Sl",
    "wof:placetype":"venue"
},
  "geometry": {"coordinates":[-1.3244839907,41.9409103394],"type":"Point"}
}