{
  "type": "Feature",
  "properties": {
    "iso:country":"ES",
    "sg:address":"Calle de Albasanz, 76",
    "sg:city":"Madrid",
    "sg:orig_category":"Centros Empresariales",
    "sg:phone":"+34 917 81 83 30",
    "sg:postcode":"28...",
    "sg:province":"Madrid",
    "wof:name":"Calidad Concertada Nuevas Tecnologias S.a.",
    "wof:placetype":"venue"
},
  "geometry": {"coordinates":[-3.6224286556,40.4388198853],"type":"Point"}
}