{
  "type": "Feature",
  "properties": {
    "iso:country":"ES",
    "sg:address":"Calle de Luchana, 27",
    "sg:city":"Madrid",
    "sg:orig_category":"Laboratorios Y Trabajos De Fotograf\u00cda, V\u00cddeo Y Cine",
    "sg:phone":"+34 914 47 05 12",
    "sg:postcode":"28010",
    "sg:province":"Madrid",
    "sg:website":"www.casacarril.com",
    "wof:name":"Casa Carril S. A.",
    "wof:placetype":"venue"
},
  "geometry": {"coordinates":[-3.6989049911,40.4317016602],"type":"Point"}
}