{
  "type": "Feature",
  "properties": {
    "addr:full":"Ugaldeguren I Poligonoa, 4 Ugaldeguren Vizcaya 48170",
    "addr:housenumber":"4",
    "addr:postcode":"48170",
    "addr:street":"I Poligonoa",
    "iso:country":"ES",
    "sg:address":"Ugaldeguren I Poligonoa, 4",
    "sg:city":"Ugaldeguren",
    "sg:orig_category":"Negocio De Materiales De Construcci\u00d3n",
    "sg:phone":"+34 944 54 42 45",
    "sg:postcode":"48170",
    "sg:province":"Vizcaya",
    "wof:name":"Representaciones Jose Garcia S.a.",
    "wof:placetype":"venue"
},
  "geometry": {"coordinates":[-2.8633139133,43.280834198],"type":"Point"}
}