{
  "type": "Feature",
  "properties": {
    "iso:country":"ES",
    "sg:address":"Calle de Mu\u00d1oz Torrero, 13",
    "sg:city":"Badajoz",
    "sg:orig_category":"Abogados",
    "sg:phone":"+34 924 22 16 26",
    "sg:postcode":"06001",
    "sg:province":"Badajoz",
    "wof:name":"Garcia Calderon Luis",
    "wof:placetype":"venue"
},
  "geometry": {"coordinates":[-6.9715270996,38.8785858154],"type":"Point"}
}