{
  "type": "Feature",
  "properties": {
    "iso:country":"ES",
    "sg:address":"Luga Juncalillo, S/n",
    "sg:city":"Juncalillo",
    "sg:orig_category":"Aguas (distribuci\u00d3n, Servicios)",
    "sg:phone":"+34 928 55 51 03",
    "sg:postcode":"35468",
    "sg:province":"Las Palmas",
    "wof:name":"Aguacana S. A.",
    "wof:placetype":"venue"
},
  "geometry": {"coordinates":[-15.6426391602,28.0379047394],"type":"Point"}
}