{
  "type": "Feature",
  "properties": {
    "addr:full":"Calle de Pozuetakogaina Kalea, 6 Irun Guip\u00f9zcoa 20305",
    "addr:housenumber":"6",
    "addr:postcode":"20305",
    "addr:street":"Calle De Pozuetakogaina Kalea;Guipu\u0300Zcoa",
    "iso:country":"ES",
    "sg:address":"Calle de Pozuetakogaina Kalea, 6",
    "sg:city":"Irun",
    "sg:orig_category":"Rectificaci\u00d3n, Mecanizado, Fresado",
    "sg:phone":"+34 943 61 03 54",
    "sg:postcode":"20305",
    "sg:province":"Guip\u00f9zcoa",
    "wof:name":"Landetxe S.a.l.",
    "wof:placetype":"venue"
},
  "geometry": {"coordinates":[-1.7637690306,43.3425445557],"type":"Point"}
}