{
  "type": "Feature",
  "properties": {
    "addr:full":"Calle de Carmen (del), 23 Cartagena Murcia 30201",
    "addr:postcode":"30201",
    "addr:street":"Calle De Carmen Del",
    "iso:country":"ES",
    "sg:address":"Calle de Carmen (del), 23",
    "sg:city":"Cartagena",
    "sg:orig_category":"M\u00c9dicos: Endocrinolog\u00cda Y Metabolismo",
    "sg:phone":"+34 968 50 03 98",
    "sg:postcode":"30201",
    "sg:province":"Murcia",
    "wof:name":"Huertas Sepulcre Julio",
    "wof:placetype":"venue"
},
  "geometry": {"coordinates":[-0.9889224172,37.6037101746],"type":"Point"}
}