{
  "type": "Feature",
  "properties": {
    "iso:country":"ES",
    "sg:address":"Barr Racamonde, S/n",
    "sg:city":"Vilalba",
    "sg:orig_category":"Material Y Herramientas Agr\u00cdcolas",
    "sg:phone":"+34 982 51 00 67",
    "sg:postcode":"27800",
    "sg:province":"Lugo",
    "wof:name":"Talleres Carruxo S. L.",
    "wof:placetype":"venue"
},
  "geometry": {"coordinates":[-7.6823759079,43.3024177551],"type":"Point"}
}