{
  "type": "Feature",
  "properties": {
    "iso:country":"ES",
    "sg:address":"Calle de Mayor Principal, 4",
    "sg:city":"Palencia",
    "sg:orig_category":"Electrodom\u00c9sticos (fabricaci\u00d3n, Al Por Mayor)",
    "sg:phone":"+34 979 74 95 66",
    "sg:postcode":"34001",
    "sg:province":"Palencia",
    "sg:website":"www.redelite.es",
    "wof:name":"Badillo Garcia Raul",
    "wof:placetype":"venue"
},
  "geometry": {"coordinates":[-4.5392618179,42.010433197],"type":"Point"}
}