{
  "type": "Feature",
  "properties": {
    "iso:country":"ES",
    "sg:address":"Carrer de Hospitalet De Llobregat (l'), 11",
    "sg:city":"S. Joan Despi",
    "sg:orig_category":"Fisioterapia",
    "sg:phone":"+34 934 77 03 15",
    "sg:postcode":"08970",
    "sg:province":"Barcelona",
    "wof:name":"Mu\u00f1oz Alcaide Rafael",
    "wof:placetype":"venue"
},
  "geometry": {"coordinates":[2.0744419098,41.3695716858],"type":"Point"}
}