{
  "type": "Feature",
  "properties": {
    "iso:country":"ES",
    "sg:address":"Ctra. Soria Plasencia, S/n",
    "sg:city":"La Colilla",
    "sg:orig_category":"Negocio De Materiales De Construcci\u00d3n",
    "sg:phone":"+34 920 26 97 75",
    "sg:postcode":"05192",
    "sg:province":"\u00c1vila",
    "wof:name":"Berrojalbiz E Hijos S. A.",
    "wof:placetype":"venue"
},
  "geometry": {"coordinates":[-4.7738180161,40.6333389282],"type":"Point"}
}