{
  "type": "Feature",
  "properties": {
    "addr:full":"Carrer de Major, 106 Mora Nova Tarragona 43770",
    "addr:housenumber":"106",
    "addr:postcode":"43770",
    "addr:street":"Carrer De Major",
    "iso:country":"ES",
    "sg:address":"Carrer de Major, 106",
    "sg:city":"Mora Nova",
    "sg:orig_category":"Comercio, Reparaci\u00d3n De Motocicletas, Bicicletas Y Piezas Sueltas",
    "sg:phone":"+34 977 40 06 20",
    "sg:postcode":"43770",
    "sg:province":"Tarragona",
    "wof:name":"Vidiella Mu\u00f1oz Joan Arturo",
    "wof:placetype":"venue"
},
  "geometry": {"coordinates":[0.6513710022,41.1009788513],"type":"Point"}
}