{
  "type": "Feature",
  "properties": {
    "iso:country":"ES",
    "sg:address":"Avda Marques De Rozalejo, S/n",
    "sg:city":"Dolores",
    "sg:orig_category":"Electrodom\u00c9sticos (al Por Menor)",
    "sg:phone":"+34 968 17 33 93",
    "sg:postcode":"30739",
    "sg:province":"Murcia",
    "sg:website":"www.redelite.es",
    "wof:name":"Conesa Aix Cayetano",
    "wof:placetype":"venue"
},
  "geometry": {"coordinates":[-0.8690189719,37.7777137756],"type":"Point"}
}