{
  "type": "Feature",
  "properties": {
    "iso:country":"ES",
    "sg:address":"Rbla Nostra Senyora, 31",
    "sg:city":"Vilafranca Penedes",
    "sg:orig_category":"Molduras, Junquillos, Listones Y Molduras Perforadas",
    "sg:phone":"+34 938 90 28 37",
    "sg:postcode":"08720",
    "sg:province":"Barcelona",
    "wof:name":"Llagostera Montoya Francesc Xavier",
    "wof:placetype":"venue"
},
  "geometry": {"coordinates":[1.7003651857,41.3453521729],"type":"Point"}
}