{
  "type": "Feature",
  "properties": {
    "iso:country":"ES",
    "sg:address":"Calle de Reyes Leoneses, 6",
    "sg:city":"Le\u00f3n",
    "sg:orig_category":"Mec\u00c1nico Del Autom\u00d3vil",
    "sg:phone":"+34 987 22 32 56",
    "sg:postcode":"24008",
    "sg:province":"Le\u00f3n",
    "wof:name":"Difermotor S.l.",
    "wof:placetype":"venue"
},
  "geometry": {"coordinates":[-5.5813570023,42.6048583984],"type":"Point"}
}