{
  "type": "Feature",
  "properties": {
    "iso:country":"ES",
    "sg:address":"Cra. Roses, Km. 0028,7",
    "sg:city":"Figueres",
    "sg:orig_category":"Distribuci\u00d3n De Petr\u00d3leo Y Derivados",
    "sg:phone":"+34 972 50 37 27",
    "sg:postcode":"17600",
    "sg:province":"Girona",
    "wof:name":"Rally Estacion De Servicio S.a.",
    "wof:placetype":"venue"
},
  "geometry": {"coordinates":[2.9581100941,42.2656898499],"type":"Point"}
}