{
  "type": "Feature",
  "properties": {
    "iso:country":"ES",
    "sg:address":"Calle de Blanquerias, 21",
    "sg:city":"Valencia",
    "sg:orig_category":"Escultores, Estatuarios E Imagineros",
    "sg:phone":"+34 963 91 29 29",
    "sg:postcode":"46003",
    "sg:province":"Valencia",
    "wof:name":"Esteve Edo Jose",
    "wof:placetype":"venue"
},
  "geometry": {"coordinates":[-0.3791866899,39.4809646606],"type":"Point"}
}