{
  "type": "Feature",
  "properties": {
    "addr:full":"Calle de Silos, 112 Alcala Guadaira Sevilla 41500",
    "addr:housenumber":"112",
    "addr:postcode":"41500",
    "addr:street":"Calle De Silos",
    "iso:country":"ES",
    "sg:address":"Calle de Silos, 112",
    "sg:city":"Alcala Guadaira",
    "sg:orig_category":"Bazares, Art\u00cdculos De Limpieza Y De Cocina (al Por Menor)",
    "sg:phone":"+34 955 61 04 45",
    "sg:postcode":"41500",
    "sg:province":"Sevilla",
    "wof:name":"Caraballo Virino Marco Antonio",
    "wof:placetype":"venue"
},
  "geometry": {"coordinates":[-5.8458189964,37.3449401855],"type":"Point"}
}