{
  "type": "Feature",
  "properties": {
    "addr:full":"Calle de Chorrito, S/n Alberca Salamanca 37624",
    "addr:housenumber":"s / n",
    "addr:postcode":"37624",
    "addr:street":"Calle De Chorrito",
    "iso:country":"ES",
    "sg:address":"Calle de Chorrito, S/n",
    "sg:city":"Alberca",
    "sg:orig_category":"Charcuter\u00cdas (al Por Mayor)",
    "sg:phone":"+34 923 41 53 20",
    "sg:postcode":"37624",
    "sg:province":"Salamanca",
    "wof:name":"Embutidos Eusebio S.l.",
    "wof:placetype":"venue"
},
  "geometry": {"coordinates":[-6.1113123894,40.488822937],"type":"Point"}
}