{
  "type": "Feature",
  "properties": {
    "iso:country":"ES",
    "sg:address":"Carrer de L'equador, 51",
    "sg:city":"Barcelona",
    "sg:orig_category":"Sonorizaci\u00d3n, Iluminaci\u00d3n Para Cine, Teatro Y Discotecas (al Por Mayor, Al Por Menor)",
    "sg:phone":"+34 933 63 15 15",
    "sg:postcode":"08029",
    "sg:province":"Barcelona",
    "wof:name":"Audiogestion Profesional S.l.",
    "wof:placetype":"venue"
},
  "geometry": {"coordinates":[2.1395022869,41.386428833],"type":"Point"}
}