{
  "type": "Feature",
  "properties": {
    "iso:country":"ES",
    "sg:address":"Calle de Juan Ramon Jimenez, 2",
    "sg:city":"Guadix",
    "sg:orig_category":"Asociaciones Y Clubs Deportivos",
    "sg:phone":"+34 958 66 52 44",
    "sg:postcode":"18500",
    "sg:province":"Granada",
    "wof:name":"Fernandez Ortega Virtudes",
    "wof:placetype":"venue"
},
  "geometry": {"coordinates":[-3.131319046,37.2994804382],"type":"Point"}
}