{
  "type": "Feature",
  "properties": {
    "addr:full":"Avda Aeropuerto (del), 10 Cordoba C\u00f3rdoba 14004",
    "addr:housenumber":"10",
    "addr:postcode":"14004",
    "addr:street":"Avda Aeropuerto Del;Co\u0301Rdoba",
    "iso:country":"ES",
    "sg:address":"Avda Aeropuerto (del), 10",
    "sg:city":"Cordoba",
    "sg:orig_category":"Venta, Colocaci\u00d3n, Reparaci\u00d3n De Parabrisas, Techos Descapotables",
    "sg:phone":"+34 957 41 45 69",
    "sg:postcode":"14004",
    "sg:province":"C\u00f3rdoba",
    "wof:name":"Autocristal Cordoba S.l.",
    "wof:placetype":"venue"
},
  "geometry": {"coordinates":[-4.7981090546,37.8740386963],"type":"Point"}
}