{
  "type": "Feature",
  "properties": {
    "addr:full":"Ctra Alicante-cartagena, Km. 0081,9 Marina Alicante 03194",
    "addr:postcode":"03194",
    "addr:street":"Ctra Alicante-Cartagena Km. 0081,9",
    "iso:country":"ES",
    "sg:address":"Ctra Alicante-cartagena, Km. 0081,9",
    "sg:city":"Marina",
    "sg:orig_category":"Alquiler De Veh\u00cdculos: Turismos Y Utilitarios",
    "sg:phone":"+34 965 41 94 02",
    "sg:postcode":"03194",
    "sg:province":"Alicante",
    "wof:name":"Nederlos  Pieter Adriaan",
    "wof:placetype":"venue"
},
  "geometry": {"coordinates":[-0.4804700017,38.3440818787],"type":"Point"}
}