{
  "type": "Feature",
  "properties": {
    "addr:full":"Calle de Enrique Amat, 23 Montefrio Granada 18270",
    "addr:housenumber":"23",
    "addr:postcode":"18270",
    "addr:street":"Calle De Enrique Amat",
    "iso:country":"ES",
    "sg:address":"Calle de Enrique Amat, 23",
    "sg:city":"Montefrio",
    "sg:orig_category":"Servicio De Salud",
    "sg:phone":"+34 958 31 06 08",
    "sg:postcode":"18270",
    "sg:province":"Granada",
    "wof:name":"Toro Jimenez Rafael",
    "wof:placetype":"venue"
},
  "geometry": {"coordinates":[-4.0085530281,37.3212776184],"type":"Point"}
}