{
  "type": "Feature",
  "properties": {
    "iso:country":"ES",
    "sg:address":"Avda Capuchinos, 6",
    "sg:city":"Castellon",
    "sg:orig_category":"Centros De Coordinaci\u00d3n",
    "sg:phone":"+34 964 72 23 91",
    "sg:postcode":"12004",
    "sg:province":"Castell\u00f3n",
    "wof:name":"Nitrur De Bor S.l.",
    "wof:placetype":"venue"
},
  "geometry": {"coordinates":[-0.0337570012,39.9895210266],"type":"Point"}
}