{
  "type": "Feature",
  "properties": {
    "addr:full":"Calle de Mayor, 129 Tobarra Albacete 02500",
    "addr:housenumber":"129",
    "addr:postcode":"02500",
    "addr:street":"Calle De Mayor",
    "iso:country":"ES",
    "sg:address":"Calle de Mayor, 129",
    "sg:city":"Tobarra",
    "sg:orig_category":"Pescader\u00cdas (al Por Menor)",
    "sg:phone":"+34 967 32 52 36",
    "sg:postcode":"02500",
    "sg:province":"Albacete",
    "wof:name":"Merino Sahori Antonio",
    "wof:placetype":"venue"
},
  "geometry": {"coordinates":[-1.6894140244,38.59167099],"type":"Point"}
}