{
  "type": "Feature",
  "properties": {
    "iso:country":"ES",
    "sg:address":"Avgd De Daniel Gil, 40",
    "sg:city":"Ontinyent",
    "sg:orig_category":"Carnicer\u00cdas, Carnicer\u00cdas",
    "sg:phone":"+34 962 38 33 54",
    "sg:postcode":"46870",
    "sg:province":"Valencia",
    "wof:name":"Donat Garrote S.l.",
    "wof:placetype":"venue"
},
  "geometry": {"coordinates":[-0.6012420058,38.8227462769],"type":"Point"}
}