{
  "type": "Feature",
  "properties": {
    "addr:full":"Calle de Fuente Canonigos, 5 Tudela Navarra 31500",
    "addr:housenumber":"5",
    "addr:postcode":"31500",
    "addr:street":"Calle De Fuente Canonigos",
    "iso:country":"ES",
    "sg:address":"Calle de Fuente Canonigos, 5",
    "sg:city":"Tudela",
    "sg:orig_category":"Arreglo, Reparaci\u00d3n, Piezas Sueltas De Televisi\u00d3n, V\u00cddeo, Hi",
    "sg:phone":"+34 948 82 74 34",
    "sg:postcode":"31500",
    "sg:province":"Navarra",
    "wof:name":"Gonzalez Mayor Raul",
    "wof:placetype":"venue"
},
  "geometry": {"coordinates":[-1.5998063087,42.0565795898],"type":"Point"}
}