{
  "type": "Feature",
  "properties": {
    "iso:country":"ES",
    "sg:address":"Pg Catalunya, 17",
    "sg:city":"Torroella Montgri",
    "sg:orig_category":"Peluquer\u00cdas, Peluquer\u00cda Mixta",
    "sg:phone":"+34 972 75 78 70",
    "sg:postcode":"17257",
    "sg:province":"Girona",
    "wof:name":"Luis Navarro Silvia",
    "wof:placetype":"venue"
},
  "geometry": {"coordinates":[3.1276071072,42.039264679],"type":"Point"}
}