{
  "type": "Feature",
  "properties": {
    "iso:country":"ES",
    "sg:address":"Outeiro, S/n",
    "sg:city":"Calvos",
    "sg:orig_category":"Centros De Educaci\u00d3n Especial",
    "sg:phone":"+34 988 43 40 02",
    "sg:postcode":"32644",
    "sg:province":"Ourense",
    "wof:name":"Colegio Nacional Nuestra Se\u00f1ora Del Carmen",
    "wof:placetype":"venue"
},
  "geometry": {"coordinates":[-7.8409948349,41.9461135864],"type":"Point"}
}