{
  "type": "Feature",
  "properties": {
    "addr:full":"Carr Pirineus, 30 Angles Girona 17160",
    "addr:housenumber":"30",
    "addr:postcode":"17160",
    "addr:street":"Carr Pirineus",
    "iso:country":"ES",
    "sg:address":"Carr Pirineus, 30",
    "sg:city":"Angles",
    "sg:orig_category":"Transporte En General",
    "sg:phone":"+34 972 42 11 22",
    "sg:postcode":"17160",
    "sg:province":"Girona",
    "wof:name":"A.p. Sistemes Electronics S.c.",
    "wof:placetype":"venue"
},
  "geometry": {"coordinates":[2.6365654469,41.9514579773],"type":"Point"}
}