{
  "type": "Feature",
  "properties": {
    "addr:full":"Ctra Coru\u00d1a, 9 San Rafael Segovia 40410",
    "addr:housenumber":"9",
    "addr:postcode":"40410",
    "addr:street":"Ctra Corun\u0303A",
    "iso:country":"ES",
    "sg:address":"Ctra Coru\u00d1a, 9",
    "sg:city":"San Rafael",
    "sg:orig_category":"Producci\u00d3n, Distribuci\u00d3n De Gas Butano Y Propano",
    "sg:phone":"+34 921 17 10 79",
    "sg:postcode":"40410",
    "sg:province":"Segovia",
    "wof:name":"Asistencia Y Distribucion De Gas S.c.s.l.",
    "wof:placetype":"venue"
},
  "geometry": {"coordinates":[-4.1902489662,40.713760376],"type":"Point"}
}