{
  "type": "Feature",
  "properties": {
    "iso:country":"ES",
    "sg:address":"Avda Cid Campeador, 116",
    "sg:city":"Burgos",
    "sg:orig_category":"Caf\u00c9s, Bares, Cervecer\u00cdas",
    "sg:phone":"+34 947 22 65 14",
    "sg:postcode":"09006",
    "sg:province":"Burgos",
    "wof:name":"Torre Pascual Jesus De La",
    "wof:placetype":"venue"
},
  "geometry": {"coordinates":[-3.6917290688,42.3542709351],"type":"Point"}
}