{
  "type": "Feature",
  "properties": {
    "addr:full":"Avda Murcia, 10 Fuente Alamo Murcia 30320",
    "addr:housenumber":"10",
    "addr:postcode":"30320",
    "addr:street":"Avda Murcia",
    "iso:country":"ES",
    "sg:address":"Avda Murcia, 10",
    "sg:city":"Fuente Alamo",
    "sg:orig_category":"Electricidad (montaje, Ensamblaje De Componentes)",
    "sg:phone":"+34 968 59 71 16",
    "sg:postcode":"30320",
    "sg:province":"Murcia",
    "wof:name":"Lopez Martinez Norberto",
    "wof:placetype":"venue"
},
  "geometry": {"coordinates":[-1.0717509985,37.7733230591],"type":"Point"}
}