{
  "type": "Feature",
  "properties": {
    "iso:country":"ES",
    "sg:address":"Carrer de Vilabella (dels), 9",
    "sg:city":"Vic",
    "sg:orig_category":"Alimentaci\u00d3n General (al Por Mayor)",
    "sg:phone":"+34 938 85 46 59",
    "sg:postcode":"08500",
    "sg:province":"Barcelona",
    "wof:name":"Puig Sa\u00f1e Joaquim",
    "wof:placetype":"venue"
},
  "geometry": {"coordinates":[2.2493150234,41.928855896],"type":"Point"}
}