{
  "type": "Feature",
  "properties": {
    "addr:full":"Plaz Del Grano, S/n Benavente Zamora 49600",
    "addr:housenumber":"s / n",
    "addr:postcode":"49600",
    "addr:street":"Plaz Del Grano",
    "iso:country":"ES",
    "sg:address":"Plaz Del Grano, S/n",
    "sg:city":"Benavente",
    "sg:orig_category":"Librer\u00cdas",
    "sg:phone":"+34 980 63 37 39",
    "sg:postcode":"49600",
    "sg:province":"Zamora",
    "wof:name":"Vazquez Martinez Beatriz",
    "wof:placetype":"venue"
},
  "geometry": {"coordinates":[-5.677795887,42.0033531189],"type":"Point"}
}