{
  "type": "Feature",
  "properties": {
    "iso:country":"ES",
    "sg:address":"Avda La Rioja, 25",
    "sg:city":"Haro",
    "sg:orig_category":"Inform\u00c1tica: Material Y Suministros",
    "sg:phone":"+34 941 31 15 15",
    "sg:postcode":"26200",
    "sg:province":"La Rioja",
    "wof:name":"Ricardo Marcos Informatica S.l.",
    "wof:placetype":"venue"
},
  "geometry": {"coordinates":[-2.8514299393,42.5750427246],"type":"Point"}
}