{
  "type": "Feature",
  "properties": {
    "addr:full":"Calle de Maestro Martinez, 14 Ceuti Murcia 30562",
    "addr:housenumber":"14",
    "addr:postcode":"30562",
    "addr:street":"Calle De Maestro Martinez",
    "iso:country":"ES",
    "sg:address":"Calle de Maestro Martinez, 14",
    "sg:city":"Ceuti",
    "sg:orig_category":"Imprenta",
    "sg:phone":"+34 968 69 03 59",
    "sg:postcode":"30562",
    "sg:province":"Murcia",
    "wof:name":"Imprenta Guillen Mira S.l.",
    "wof:placetype":"venue"
},
  "geometry": {"coordinates":[-1.2720509768,38.0783348083],"type":"Point"}
}