{
  "type": "Feature",
  "properties": {
    "addr:full":"Calle de Real, 42 S. Fernando C\u00e1diz 11100",
    "addr:housenumber":"42",
    "addr:postcode":"11100",
    "addr:street":"Calle De Real;S. Fernando Ca\u0301Diz",
    "iso:country":"ES",
    "sg:address":"Calle de Real, 42",
    "sg:city":"S. Fernando",
    "sg:orig_category":"Panader\u00cdas, Panader\u00cdas",
    "sg:phone":"+34 956 89 21 62",
    "sg:postcode":"11100",
    "sg:province":"C\u00e1diz",
    "wof:name":"Urrejola Gutierrez Luciano",
    "wof:placetype":"venue"
},
  "geometry": {"coordinates":[-6.1969490051,36.4652938843],"type":"Point"}
}