{
  "type": "Feature",
  "properties": {
    "addr:full":"Hipodromo Etorbidea-avda Del Hipodromo, 10 Lasarte Guip\u00f9zcoa 20160",
    "addr:housenumber":"10",
    "addr:postcode":"20160",
    "addr:street":"Hipodromo;Guipu\u0300Zcoa",
    "iso:country":"ES",
    "sg:address":"Hipodromo Etorbidea-avda Del Hipodromo, 10",
    "sg:city":"Lasarte",
    "sg:orig_category":"Inform\u00c1tica, Ofim\u00c1tica (estudios, Asesor\u00cda, Ingenier\u00cda, Formaci\u00d3n)",
    "sg:phone":"+34 943 36 08 32",
    "sg:postcode":"20160",
    "sg:province":"Guip\u00f9zcoa",
    "wof:name":"Goitek Informatica Sl",
    "wof:placetype":"venue"
},
  "geometry": {"coordinates":[-2.020414114,43.2698173523],"type":"Point"}
}