{
  "type": "Feature",
  "properties": {
    "addr:full":"Carr Atzeneta Del Maestrat, 3 Atzeneta D'albaida Valencia 46869",
    "addr:housenumber":"3",
    "addr:postcode":"46869",
    "addr:street":"Carr Atzeneta Del Maestrat",
    "iso:country":"ES",
    "sg:address":"Carr Atzeneta Del Maestrat, 3",
    "sg:city":"Atzeneta D'albaida",
    "sg:orig_category":"Explotaci\u00d3n De Canteras",
    "sg:phone":"+34 962 35 70 55",
    "sg:postcode":"46869",
    "sg:province":"Valencia",
    "wof:name":"Aridos Juan Y Francisco Garcia S.l.",
    "wof:placetype":"venue"
},
  "geometry": {"coordinates":[-0.4960668981,38.8366584778],"type":"Point"}
}