{
  "type": "Feature",
  "properties": {
    "iso:country":"ES",
    "sg:address":"Avda Razo, 11",
    "sg:city":"Carballo",
    "sg:orig_category":"Promotores Constructores",
    "sg:phone":"+34 981 75 57 88",
    "sg:postcode":"15100",
    "sg:province":"La Coru\u00f1a",
    "wof:name":"Construcciones Ramon Vazquez Y Reino S.l.",
    "wof:placetype":"venue"
},
  "geometry": {"coordinates":[-8.6918792725,43.2225761414],"type":"Point"}
}