{
  "type": "Feature",
  "properties": {
    "addr:full":"Calle de Aranjuez, 6 Valdemoro Madrid 28340",
    "addr:housenumber":"6",
    "addr:postcode":"28340",
    "addr:street":"Calle De Aranjuez",
    "iso:country":"ES",
    "sg:address":"Calle de Aranjuez, 6",
    "sg:city":"Valdemoro",
    "sg:orig_category":"Delegados, Agentes De Tr\u00c1nsito, Auxiliares De Transporte Internacional",
    "sg:phone":"+34 918 95 13 42",
    "sg:postcode":"28340",
    "sg:province":"Madrid",
    "wof:name":"Marquez Y Rojo S.l.",
    "wof:placetype":"venue"
},
  "geometry": {"coordinates":[-3.6794281006,40.2089996338],"type":"Point"}
}