{
  "type": "Feature",
  "properties": {
    "addr:full":"Pg Vilanova, 7 Sitges Barcelona 08870",
    "addr:housenumber":"7",
    "addr:postcode":"08870",
    "addr:street":"Vilanova",
    "iso:country":"ES",
    "sg:address":"Pg Vilanova, 7",
    "sg:city":"Sitges",
    "sg:orig_category":"Inform\u00c1tica (estudios, Servicios, Asesor\u00cda, Formaci\u00d3n)",
    "sg:phone":"+34 938 94 57 52",
    "sg:postcode":"08870",
    "sg:province":"Barcelona",
    "wof:name":"Mapfre Servicios De Informatica",
    "wof:placetype":"venue"
},
  "geometry": {"coordinates":[1.8066699505,41.2380447388],"type":"Point"}
}