{
  "type": "Feature",
  "properties": {
    "addr:full":"Av Onze De Setembre, 16 Sant Joan De Palamos Girona 17230",
    "addr:housenumber":"16",
    "addr:postcode":"17230",
    "addr:street":"Av Onze De Setembre",
    "iso:country":"ES",
    "sg:address":"Av Onze De Setembre, 16",
    "sg:city":"Sant Joan De Palamos",
    "sg:orig_category":"Agencias De Trabajo Temporal",
    "sg:phone":"+34 972 31 91 31",
    "sg:postcode":"17230",
    "sg:province":"Girona",
    "sg:website":"www.marlex.es",
    "wof:name":"Marlex Gestio Ett S. L.",
    "wof:placetype":"venue"
},
  "geometry": {"coordinates":[3.1294090748,41.8495903015],"type":"Point"}
}