{
  "type": "Feature",
  "properties": {
    "iso:country":"ES",
    "sg:address":"Calle de Apolonio Morales, 31",
    "sg:city":"Madrid",
    "sg:orig_category":"Abogados",
    "sg:phone":"+34 913 45 69 30",
    "sg:postcode":"28036",
    "sg:province":"Madrid",
    "wof:name":"Fontecha Cristobal Luis",
    "wof:placetype":"venue"
},
  "geometry": {"coordinates":[-3.6799879074,40.4638748169],"type":"Point"}
}