{
  "type": "Feature",
  "properties": {
    "addr:full":"Ctra Rellinars, 256 Terrassa Barcelona 08225",
    "addr:housenumber":"256",
    "addr:postcode":"08225",
    "addr:street":"Ctra Rellinars",
    "iso:country":"ES",
    "sg:address":"Ctra Rellinars, 256",
    "sg:city":"Terrassa",
    "sg:orig_category":"Cajas De Ahorro",
    "sg:phone":"+34 937 35 49 22",
    "sg:postcode":"08225",
    "sg:province":"Barcelona",
    "wof:name":"Caixa D'estalvis I Pensions De Barcelona",
    "wof:placetype":"venue"
},
  "geometry": {"coordinates":[2.0056929588,41.5764160156],"type":"Point"}
}