{
  "type": "Feature",
  "properties": {
    "iso:country":"ES",
    "sg:address":"Calle de Tarragona, S/n",
    "sg:city":"Puertollano",
    "sg:orig_category":"Bazares, Art\u00cdculos De Limpieza Y De Cocina (al Por Menor)",
    "sg:phone":"+34 926 42 61 65",
    "sg:postcode":"13500",
    "sg:province":"Ciudad Real",
    "wof:name":"Jugueteria El Poblado S.l.l.",
    "wof:placetype":"venue"
},
  "geometry": {"coordinates":[-4.0949168205,38.6842651367],"type":"Point"}
}