{
  "type": "Feature",
  "properties": {
    "addr:full":"Ctra Torre Pacheco, Km. 0002,0 Los Alcazares Murcia 30710",
    "addr:postcode":"30710",
    "addr:street":"Ctra Torre Pacheco Km. 0002,0 Los Alcazares",
    "iso:country":"ES",
    "sg:address":"Ctra Torre Pacheco, Km. 0002,0",
    "sg:city":"Los Alcazares",
    "sg:orig_category":"Muebles, Minoristas",
    "sg:phone":"+34 968 17 04 99",
    "sg:postcode":"30710",
    "sg:province":"Murcia",
    "sg:website":"www.mueblesjoca.com",
    "wof:name":"Muebles Dune Sl",
    "wof:placetype":"venue"
},
  "geometry": {"coordinates":[-0.8489990234,37.7447319031],"type":"Point"}
}