{
  "type": "Feature",
  "properties": {
    "addr:full":"Calle de Jose Molina, 3 Arrecife Las Palmas 35500",
    "addr:housenumber":"3",
    "addr:postcode":"35500",
    "addr:street":"Calle De Jose Molina",
    "iso:country":"ES",
    "sg:address":"Calle de Jose Molina, 3",
    "sg:city":"Arrecife",
    "sg:orig_category":"Confiter\u00cdas, Chocolater\u00cdas (al Por Menor)",
    "sg:phone":"+34 928 81 76 13",
    "sg:postcode":"35500",
    "sg:province":"Las Palmas",
    "wof:name":"Comercial Zonzomas S.l.",
    "wof:placetype":"venue"
},
  "geometry": {"coordinates":[-13.5491600037,28.958990097],"type":"Point"}
}