{
  "type": "Feature",
  "properties": {
    "iso:country":"ES",
    "sg:address":"Calle de Joaquin Benlloch, 31",
    "sg:city":"Valencia",
    "sg:orig_category":"Ense\u00d1ante, Direcci\u00d3n",
    "sg:phone":"+34 963 34 59 49",
    "sg:postcode":"46006",
    "sg:province":"Valencia",
    "wof:name":"Cabezas Marin Asuncion",
    "wof:placetype":"venue"
},
  "geometry": {"coordinates":[-0.3762440085,39.4534034729],"type":"Point"}
}