{
  "type": "Feature",
  "properties": {
    "addr:full":"Rua Galicia, 37 Lugo Lugo 27002",
    "addr:housenumber":"37",
    "addr:postcode":"27002",
    "addr:street":"Rua Galicia",
    "iso:country":"ES",
    "sg:address":"Rua Galicia, 37",
    "sg:city":"Lugo",
    "sg:orig_category":"Peritos En C\u00c1lculo Inmobiliario, Industrial Y De Fondos De Comercio",
    "sg:phone":"+34 982 25 53 22",
    "sg:postcode":"27002",
    "sg:province":"Lugo",
    "wof:name":"De Prado Soilan Andres Francisco",
    "wof:placetype":"venue"
},
  "geometry": {"coordinates":[-7.5521740913,43.0052528381],"type":"Point"}
}