{
  "type": "Feature",
  "properties": {
    "addr:full":"Calle de Virgen De Legarda, 17 Mendavia Navarra 31587",
    "addr:housenumber":"17",
    "addr:postcode":"31587",
    "addr:street":"Calle De Virgen De Legarda",
    "iso:country":"ES",
    "sg:address":"Calle de Virgen De Legarda, 17",
    "sg:city":"Mendavia",
    "sg:orig_category":"Carnicer\u00cdas, Carnicer\u00cdas",
    "sg:phone":"+34 948 68 53 03",
    "sg:postcode":"31587",
    "sg:province":"Navarra",
    "wof:name":"Ursua Manso Jose Luis",
    "wof:placetype":"venue"
},
  "geometry": {"coordinates":[-2.2021911144,42.4425354004],"type":"Point"}
}