{
  "type": "Feature",
  "properties": {
    "addr:full":"Calle de Fernandez Ladreda, S/n Valladolid Valladolid 47008",
    "addr:housenumber":"/ n",
    "addr:postcode":"47008",
    "addr:street":"Calle De;Ladreda S",
    "iso:country":"ES",
    "sg:address":"Calle de Fernandez Ladreda, S/n",
    "sg:city":"Valladolid",
    "sg:orig_category":"Producci\u00d3n, Comercio De Cereales",
    "sg:phone":"+34 983 22 32 48",
    "sg:postcode":"47008",
    "sg:province":"Valladolid",
    "wof:name":"Mu\u00f1oz Olmos S.a.",
    "wof:placetype":"venue"
},
  "geometry": {"coordinates":[-4.737429142,41.6247673035],"type":"Point"}
}