{
  "type": "Feature",
  "properties": {
    "addr:full":"Av Pla, 126 Javea Alicante 03730",
    "addr:housenumber":"126",
    "addr:postcode":"03730",
    "addr:street":"Av Pla",
    "iso:country":"ES",
    "sg:address":"Av Pla, 126",
    "sg:city":"Javea",
    "sg:orig_category":"Administradores De Bienes Y Delegados De Comunidades De Propietarios",
    "sg:phone":"+34 966 46 30 31",
    "sg:postcode":"03730",
    "sg:province":"Alicante",
    "wof:name":"Gonzalez Boronat Jose",
    "wof:placetype":"venue"
},
  "geometry": {"coordinates":[0.172973007,38.7885856628],"type":"Point"}
}