{
  "type": "Feature",
  "properties": {
    "addr:full":"Calle de Aire, 109 Aguilas Murcia 30880",
    "addr:housenumber":"109",
    "addr:postcode":"30880",
    "addr:street":"Calle De Aire",
    "iso:country":"ES",
    "sg:address":"Calle de Aire, 109",
    "sg:city":"Aguilas",
    "sg:orig_category":"Delegados, Agentes De Tr\u00c1nsito, Auxiliares De Transporte Internacional",
    "sg:phone":"+34 968 41 36 59",
    "sg:postcode":"30880",
    "sg:province":"Murcia",
    "wof:name":"Gomez Garcia Pedro",
    "wof:placetype":"venue"
},
  "geometry": {"coordinates":[-1.5713429451,37.408290863],"type":"Point"}
}