{
  "type": "Feature",
  "properties": {
    "iso:country":"ES",
    "sg:address":"Pase Teruel, 32",
    "sg:city":"Zaragoza",
    "sg:orig_category":"Sociedades, Compa\u00d1\u00cdas Aseguradoras",
    "sg:phone":"+34 976 22 68 57",
    "sg:postcode":"50004",
    "sg:province":"Zaragoza",
    "wof:name":"Multiaragon Servicios S.l.",
    "wof:placetype":"venue"
},
  "geometry": {"coordinates":[-0.8919280171,41.6484298706],"type":"Point"}
}