{
  "type": "Feature",
  "properties": {
    "iso:country":"ES",
    "sg:address":"Calle de Antonio De Cabezon, 75",
    "sg:city":"Madrid",
    "sg:orig_category":"Agencias Y Asesores De Publicidad",
    "sg:phone":"+34 913 58 29 44",
    "sg:postcode":"28034",
    "sg:province":"Madrid",
    "wof:name":"Maderas E.b. S.l.",
    "wof:placetype":"venue"
},
  "geometry": {"coordinates":[-3.6830201149,40.4994735718],"type":"Point"}
}