{
  "type": "Feature",
  "properties": {
    "iso:country":"ES",
    "sg:address":"Avda Reyes Catolicos, 38",
    "sg:city":"Cuenca",
    "sg:orig_category":"Molduras, Junquillos, Listones Y Molduras Perforadas",
    "sg:phone":"+34 969 21 13 94",
    "sg:postcode":"16003",
    "sg:province":"Cuenca",
    "wof:name":"Abril Escalada Pilar",
    "wof:placetype":"venue"
},
  "geometry": {"coordinates":[-2.138671,40.061699],"type":"Point"}
}