{
  "type": "Feature",
  "properties": {
    "iso:country":"ES",
    "sg:address":"Plaz Espa\u00d1a (de), 4",
    "sg:city":"Ateca",
    "sg:orig_category":"Notarios",
    "sg:phone":"+34 976 84 21 60",
    "sg:postcode":"50200",
    "sg:province":"Zaragoza",
    "wof:name":"Esteras Aure Eva Maria",
    "wof:placetype":"venue"
},
  "geometry": {"coordinates":[-1.7889089584,41.3299789429],"type":"Point"}
}