{
  "type": "Feature",
  "properties": {
    "iso:country":"ES",
    "sg:address":"Calle de Laurel, 22",
    "sg:city":"Cheste",
    "sg:orig_category":"Reposter\u00cdas",
    "sg:phone":"+34 962 51 05 28",
    "sg:postcode":"46380",
    "sg:province":"Valencia",
    "wof:name":"Horno El Laurel S.l",
    "wof:placetype":"venue"
},
  "geometry": {"coordinates":[-0.6875540018,39.494682312],"type":"Point"}
}