{
  "type": "Feature",
  "properties": {
    "addr:full":"Carrer de Pere Verges, 1 Barcelona Barcelona 08020",
    "addr:housenumber":"1",
    "addr:postcode":"08020",
    "addr:street":"Carrer De Pere Verges",
    "iso:country":"ES",
    "sg:address":"Carrer de Pere Verges, 1",
    "sg:city":"Barcelona",
    "sg:orig_category":"Planificaci\u00d3n Familiar",
    "sg:phone":"+34 933 05 53 22",
    "sg:postcode":"08020",
    "sg:province":"Barcelona",
    "wof:name":"Associacio De Planificacio Familiar De Catalunya I Balears",
    "wof:placetype":"venue"
},
  "geometry": {"coordinates":[2.2091553211,41.422706604],"type":"Point"}
}