{
  "type": "Feature",
  "properties": {
    "addr:full":"Pase Alberto Casa\u00d1al, 4 Zaragoza Zaragoza 50015",
    "addr:housenumber":"4",
    "addr:postcode":"50015",
    "addr:street":"Casan\u0303Al",
    "iso:country":"ES",
    "sg:address":"Pase Alberto Casa\u00d1al, 4",
    "sg:city":"Zaragoza",
    "sg:orig_category":"Asociaciones Y Clubs Deportivos",
    "sg:phone":"+34 976 51 11 01",
    "sg:postcode":"50015",
    "sg:province":"Zaragoza",
    "sg:website":"www.udbalsaspicarral.com",
    "wof:name":"Union Deportiva Balsas Picarral",
    "wof:placetype":"venue"
},
  "geometry": {"coordinates":[-0.8753560185,41.6725997925],"type":"Point"}
}