{
  "type": "Feature",
  "properties": {
    "iso:country":"ES",
    "sg:address":"Avda Andalucia, 87",
    "sg:city":"Algarrobo-costa",
    "sg:orig_category":"Molduras, Junquillos, Listones Y Molduras Perforadas",
    "sg:phone":"+34 952 55 14 15",
    "sg:postcode":"29750",
    "sg:province":"M\u00e1laga",
    "wof:name":"Montilla Carrera Francisca",
    "wof:placetype":"venue"
},
  "geometry": {"coordinates":[-4.0517511368,36.747051239],"type":"Point"}
}