{
  "type": "Feature",
  "properties": {
    "addr:full":"Carrer de Major, 39 Gorga Alicante 03811",
    "addr:housenumber":"39",
    "addr:postcode":"03811",
    "addr:street":"Carrer De Major",
    "iso:country":"ES",
    "sg:address":"Carrer de Major, 39",
    "sg:city":"Gorga",
    "sg:orig_category":"Poller\u00cda Y Caza (al Por Menor)",
    "sg:phone":"+34 965 51 10 35",
    "sg:postcode":"03811",
    "sg:province":"Alicante",
    "wof:name":"Avicola Genis C.b.",
    "wof:placetype":"venue"
},
  "geometry": {"coordinates":[-0.3564350009,38.7186279297],"type":"Point"}
}