{
  "type": "Feature",
  "properties": {
    "addr:full":"Carrer de Unio, 9 Olesa Montserrat Barcelona 08640",
    "addr:housenumber":"9",
    "addr:postcode":"08640",
    "addr:street":"Carrer De Unio;Barcelona",
    "iso:country":"ES",
    "sg:address":"Carrer de Unio, 9",
    "sg:city":"Olesa Montserrat",
    "sg:orig_category":"Delegados, Agentes De Tr\u00c1nsito, Auxiliares De Transporte Internacional",
    "sg:phone":"+34 937 78 31 10",
    "sg:postcode":"08640",
    "sg:province":"Barcelona",
    "wof:name":"Trans-gomarin S.l.",
    "wof:placetype":"venue"
},
  "geometry": {"coordinates":[1.8990279436,41.5453453064],"type":"Point"}
}