{
  "type": "Feature",
  "properties": {
    "iso:country":"ES",
    "sg:address":"Calle de Jubilados, 34",
    "sg:city":"Massamagrell",
    "sg:orig_category":"Agentes, Concesionarios Y Sucursales De Veh\u00cdculos",
    "sg:phone":"+34 961 44 22 29",
    "sg:postcode":"46130",
    "sg:province":"Valencia",
    "wof:name":"Ferrer Gallego S. L.",
    "wof:placetype":"venue"
},
  "geometry": {"coordinates":[-0.3343470097,39.5732841492],"type":"Point"}
}