{
  "type": "Feature",
  "properties": {
    "iso:country":"ES",
    "sg:address":"Carr Mar, 2",
    "sg:city":"Escala",
    "sg:orig_category":"Frutas, Legumbres Frescas Y Tempranas (al Por Menor)",
    "sg:phone":"+34 972 77 06 01",
    "sg:postcode":"17130",
    "sg:province":"Girona",
    "wof:name":"Alabau Palles Paquita",
    "wof:placetype":"venue"
},
  "geometry": {"coordinates":[3.1367359161,42.123550415],"type":"Point"}
}