{
  "type": "Feature",
  "properties": {
    "addr:full":"Carrer de Lluis Vives, 27 Sabadell Barcelona 08206",
    "addr:housenumber":"27",
    "addr:postcode":"08206",
    "addr:street":"Carrer De Lluis Vives",
    "iso:country":"ES",
    "sg:address":"Carrer de Lluis Vives, 27",
    "sg:city":"Sabadell",
    "sg:orig_category":"Molduras, Junquillos, Listones Y Molduras Perforadas",
    "sg:phone":"+34 937 17 88 52",
    "sg:postcode":"08206",
    "sg:province":"Barcelona",
    "wof:name":"Luna Fuentes Antonio",
    "wof:placetype":"venue"
},
  "geometry": {"coordinates":[2.0921349525,41.5607757568],"type":"Point"}
}