{
  "type": "Feature",
  "properties": {
    "addr:full":"Pase Canilla (la), S/n Portugalete Vizcaya 48920",
    "addr:postcode":"48920",
    "addr:street":"La S / N",
    "iso:country":"ES",
    "sg:address":"Pase Canilla (la), S/n",
    "sg:city":"Portugalete",
    "sg:orig_category":"Asociaciones Y Clubs Deportivos",
    "sg:phone":"+34 944 95 41 71",
    "sg:postcode":"48920",
    "sg:province":"Vizcaya",
    "wof:name":"Club De Remo San Nicolas",
    "wof:placetype":"venue"
},
  "geometry": {"coordinates":[-3.0156140327,43.3197631836],"type":"Point"}
}