{
  "type": "Feature",
  "properties": {
    "addr:full":"Calle de General Gallarza, 25 Calahorra La Rioja 26500",
    "addr:housenumber":"25",
    "addr:postcode":"26500",
    "addr:street":"Calle De General Gallarza",
    "iso:country":"ES",
    "sg:address":"Calle de General Gallarza, 25",
    "sg:city":"Calahorra",
    "sg:orig_category":"Panader\u00cdas, Panader\u00cdas",
    "sg:phone":"+34 941 13 41 02",
    "sg:postcode":"26500",
    "sg:province":"La Rioja",
    "wof:name":"Miranda Mazo Maria Del Carmen",
    "wof:placetype":"venue"
},
  "geometry": {"coordinates":[-1.9665789604,42.3053245544],"type":"Point"}
}