{
  "type": "Feature",
  "properties": {
    "addr:full":"Calle de Fuente Nueva, 6 Navarrete La Rioja 26370",
    "addr:housenumber":"6",
    "addr:postcode":"26370",
    "addr:street":"Calle De Fuente Nueva",
    "iso:country":"ES",
    "sg:address":"Calle de Fuente Nueva, 6",
    "sg:city":"Navarrete",
    "sg:orig_category":"Promotores Constructores",
    "sg:phone":"+34 941 44 07 22",
    "sg:postcode":"26370",
    "sg:province":"La Rioja",
    "wof:name":"Urma Rioja Construcciones S.l.",
    "wof:placetype":"venue"
},
  "geometry": {"coordinates":[-2.5647239685,42.4313964844],"type":"Point"}
}