{
  "type": "Feature",
  "properties": {
    "iso:country":"ES",
    "sg:address":"Calle de Calderon De La Barca, 6",
    "sg:city":"Cuenca",
    "sg:classifiers":[
        {
            "category":"Personal",
            "subcategory":"Barber",
            "type":"Services"
        }
    ],
    "sg:phone":"+34 969 22 40 57",
    "sg:postcode":"16001",
    "sg:province":"Cuenca",
    "sg:tags":[
        "caballeros",
        "de",
        "peluqueros"
    ],
    "wof:name":"Martinez Dominguez Manuel",
    "wof:placetype":"venue"
},
  "geometry": {"coordinates":[-2.1364448071,40.0763244629],"type":"Point"}
}