{
  "type": "Feature",
  "properties": {
    "iso:country":"ES",
    "sg:address":"Praz Estacion (da), S/n",
    "sg:city":"Ourense",
    "sg:orig_category":"Estancos",
    "sg:phone":"+34 988 21 24 36",
    "sg:postcode":"32001",
    "sg:province":"Ourense",
    "wof:name":"Martin Castro Emilia",
    "wof:placetype":"venue"
},
  "geometry": {"coordinates":[-7.8723697662,42.3500747681],"type":"Point"}
}