{
  "type": "Feature",
  "properties": {
    "addr:full":"C/ La Penya, 21 Paterna Valencia 46980",
    "addr:housenumber":"21",
    "addr:postcode":"46980",
    "addr:street":"C / La Penya",
    "iso:country":"ES",
    "sg:address":"C/ La Penya, 21",
    "sg:city":"Paterna",
    "sg:orig_category":"Guarder\u00cdas",
    "sg:phone":"+34 961 38 24 17",
    "sg:postcode":"46980",
    "sg:province":"Valencia",
    "wof:name":"La Gacela S.l.",
    "wof:placetype":"venue"
},
  "geometry": {"coordinates":[-0.4310519993,39.4959487915],"type":"Point"}
}