{
  "type": "Feature",
  "properties": {
    "iso:country":"ES",
    "sg:address":"Calle de Amos Olivares, 39",
    "sg:city":"Pedro Mu\u00e7oz",
    "sg:orig_category":"Bisuter\u00cda, Joyer\u00cda, Relojer\u00cda (al Por Menor)",
    "sg:phone":"+34 926 56 80 41",
    "sg:postcode":"13620",
    "sg:province":"Ciudad Real",
    "wof:name":"Velogar Joyeros S.l.",
    "wof:placetype":"venue"
},
  "geometry": {"coordinates":[-2.9463489056,39.4052200317],"type":"Point"}
}