{
  "type": "Feature",
  "properties": {
    "iso:country":"ES",
    "sg:address":"Rua Quiroga, 1",
    "sg:city":"Lugo",
    "sg:orig_category":"Carnicer\u00cdas, Carnicer\u00cdas",
    "sg:phone":"+34 982 20 35 69",
    "sg:postcode":"27004",
    "sg:province":"Lugo",
    "wof:name":"Pesuma S.coop.galega",
    "wof:placetype":"venue"
},
  "geometry": {"coordinates":[-7.5661020279,43.0131072998],"type":"Point"}
}