{
  "type": "Feature",
  "properties": {
    "addr:full":"Bard Carrascos (los), S/n Carrascos Almer\u00eda 04660",
    "addr:postcode":"04660",
    "addr:street":"Los S / N Carrascos Almeri\u0301A",
    "iso:country":"ES",
    "sg:address":"Bard Carrascos (los), S/n",
    "sg:city":"Carrascos",
    "sg:orig_category":"Hoteles",
    "sg:phone":"+34 950 52 38 70",
    "sg:postcode":"04660",
    "sg:province":"Almer\u00eda",
    "wof:name":"Cortijo Trinidad S.l. Hotel Rural Restaurante",
    "wof:placetype":"venue"
},
  "geometry": {"coordinates":[-2.075040102,37.352481842],"type":"Point"}
}