{
  "type": "Feature",
  "properties": {
    "iso:country":"ES",
    "sg:address":"Av Pirineus, 20",
    "sg:city":"Puigcerda",
    "sg:orig_category":"Agentes, Concesionarios Y Sucursales De Veh\u00cdculos",
    "sg:phone":"+34 972 88 05 72",
    "sg:postcode":"17520",
    "sg:province":"Girona",
    "wof:name":"Bombardo Bertran Ramon",
    "wof:placetype":"venue"
},
  "geometry": {"coordinates":[1.9262160063,42.429309845],"type":"Point"}
}