{
  "type": "Feature",
  "properties": {
    "iso:country":"ES",
    "sg:address":"Calle de Mirabel, 32",
    "sg:city":"Valladolid",
    "sg:orig_category":"Alimentaci\u00d3n General (al Por Menor)",
    "sg:phone":"+34 983 25 27 41",
    "sg:postcode":"47010",
    "sg:province":"Valladolid",
    "wof:name":"Aparicio Guerra Mariano",
    "wof:placetype":"venue"
},
  "geometry": {"coordinates":[-4.7263064384,41.6613540649],"type":"Point"}
}