{
  "type": "Feature",
  "properties": {
    "iso:country":"ES",
    "sg:address":"Tv. Mte Monjardin, 8",
    "sg:city":"Iru\u00f1a",
    "sg:orig_category":"Arquitectos",
    "sg:phone":"+34 948 29 23 08",
    "sg:postcode":"31006",
    "sg:province":"Navarra",
    "wof:name":"Daz Arquitectos",
    "wof:placetype":"venue"
},
  "geometry": {"coordinates":[-1.6323219538,42.8088607788],"type":"Point"}
}