{
  "type": "Feature",
  "properties": {
    "addr:full":"Calle de Aldakonea, 36 Donostia-san Sebastian Guip\u00f9zcoa 20012",
    "addr:housenumber":"36",
    "addr:postcode":"20012",
    "addr:street":"Calle De Aldakonea",
    "iso:country":"ES",
    "sg:address":"Calle de Aldakonea, 36",
    "sg:city":"Donostia-san Sebastian",
    "sg:orig_category":"Asociaciones, Organismos Culturales Y Socioeducativos",
    "sg:phone":"+34 943 32 66 66",
    "sg:postcode":"20012",
    "sg:province":"Guip\u00f9zcoa",
    "sg:website":"nazaret1@sarenet.es",
    "wof:name":"Centro Nazaret",
    "wof:placetype":"venue"
},
  "geometry": {"coordinates":[-1.9698702097,43.3194732666],"type":"Point"}
}