{
  "type": "Feature",
  "properties": {
    "iso:country":"ES",
    "sg:address":"Pol Ind Plazaola Manzana D, 13",
    "sg:city":"Aizoain",
    "sg:orig_category":"Soldadura, Equipo Y Herramental",
    "sg:phone":"+34 948 35 10 30",
    "sg:postcode":"31195",
    "sg:province":"Navarra",
    "wof:name":"Distribuciones Eusebio Y Raul S.l.",
    "wof:placetype":"venue"
},
  "geometry": {"coordinates":[-1.6867979765,42.8470611572],"type":"Point"}
}