{
  "type": "Feature",
  "properties": {
    "addr:full":"Camino Del Pozo, S/n Riba-roja Turia Valencia 46190",
    "addr:housenumber":"s / n",
    "addr:postcode":"46190",
    "addr:street":"Camino Del Pozo",
    "iso:country":"ES",
    "sg:address":"Camino Del Pozo, S/n",
    "sg:city":"Riba-roja Turia",
    "sg:orig_category":"Asesor\u00cda Fiscal Y Jur\u00cddica",
    "sg:phone":"+34 962 77 27 98",
    "sg:postcode":"46190",
    "sg:province":"Valencia",
    "wof:name":"Qualitas Esperience S.l.",
    "wof:placetype":"venue"
},
  "geometry": {"coordinates":[-0.5698940158,39.5458450317],"type":"Point"}
}