{
  "type": "Feature",
  "properties": {
    "addr:full":"Calle de Tomas Echeverria, 7 Malaga M\u00e1laga 29002",
    "addr:postcode":"29002",
    "addr:street":"Calle De Tomas Echeverria 7 Malaga Ma\u0301Laga",
    "iso:country":"ES",
    "sg:address":"Calle de Tomas Echeverria, 7",
    "sg:city":"Malaga",
    "sg:classifiers":[
        {
            "category":"Taxi",
            "type":"Transportation"
        }
    ],
    "sg:phone":"+34 952 35 67 81",
    "sg:postcode":"29002",
    "sg:province":"M\u00e1laga",
    "wof:name":"Garcia Gomez Jose",
    "wof:placetype":"venue"
},
  "geometry": {"coordinates":[-4.4355201721,36.7045860291],"type":"Point"}
}