{
  "type": "Feature",
  "properties": {
    "iso:country":"ES",
    "sg:address":"Carrer de Ramon Estruch, 10",
    "sg:city":"S. Boi Llobregat",
    "sg:orig_category":"Peluqueros: De Se\u00d1oras",
    "sg:phone":"+34 936 52 08 42",
    "sg:postcode":"08830",
    "sg:province":"Barcelona",
    "wof:name":"Moreno Moreno Maria Remedios",
    "wof:placetype":"venue"
},
  "geometry": {"coordinates":[2.0294671059,41.345249176],"type":"Point"}
}