{
  "type": "Feature",
  "properties": {
    "iso:country":"ES",
    "sg:address":"Calle de Corredera De San Marcos, 37",
    "sg:city":"Linares",
    "sg:orig_category":"Cajas Para Embalar",
    "sg:phone":"+34 953 60 29 44",
    "sg:postcode":"23700",
    "sg:province":"Ja\u00e9n",
    "wof:name":"Caja Rural De Jaen",
    "wof:placetype":"venue"
},
  "geometry": {"coordinates":[-3.6333799362,38.0975494385],"type":"Point"}
}