{
  "type": "Feature",
  "properties": {
    "addr:full":"Calle de Tindaya, S/n Gran Tarajal Las Palmas 35620",
    "addr:housenumber":"s / n",
    "addr:postcode":"35620",
    "addr:street":"Calle De Tindaya;Palmas",
    "iso:country":"ES",
    "sg:address":"Calle de Tindaya, S/n",
    "sg:city":"Gran Tarajal",
    "sg:orig_category":"Muebles, Minoristas",
    "sg:phone":"+34 928 16 50 24",
    "sg:postcode":"35620",
    "sg:province":"Las Palmas",
    "wof:name":"Prefabricados Nortysur S.a.",
    "wof:placetype":"venue"
},
  "geometry": {"coordinates":[-14.0195837021,28.2133407593],"type":"Point"}
}