{
  "type": "Feature",
  "properties": {
    "iso:country":"ES",
    "sg:address":"Calle de Castillo De Simancas, 24",
    "sg:city":"Madrid",
    "sg:orig_category":"Carnicer\u00cdas, Carnicer\u00cdas",
    "sg:phone":"+34 913 27 03 28",
    "sg:postcode":"28037",
    "sg:province":"Madrid",
    "wof:name":"Bra\u00f1uelas Guerrero Jaime",
    "wof:placetype":"venue"
},
  "geometry": {"coordinates":[-3.6268334389,40.4296035767],"type":"Point"}
}