{
  "type": "Feature",
  "properties": {
    "addr:full":"Crt. Puebla Bele\u00f1a, S/n Robledillo De Mohernando Guadalajara 19227",
    "addr:housenumber":"/ n",
    "addr:postcode":"19227",
    "addr:street":"Belen\u0303A S",
    "iso:country":"ES",
    "sg:address":"Crt. Puebla Bele\u00f1a, S/n",
    "sg:city":"Robledillo De Mohernando",
    "sg:orig_category":"Aeropuertos Y Servicios Aeroportuarios",
    "sg:phone":"+34 949 82 30 12",
    "sg:postcode":"19227",
    "sg:province":"Guadalajara",
    "wof:name":"Aeropuertos Espa\u00f1oles Y Navegacion Aerea",
    "wof:placetype":"venue"
},
  "geometry": {"coordinates":[-3.2347474098,40.8540000916],"type":"Point"}
}