{
  "type": "Feature",
  "properties": {
    "iso:country":"ES",
    "sg:address":"Calle de Silvano, 77",
    "sg:city":"Madrid",
    "sg:orig_category":"Ropa Para Se\u00d1oras Y Caballeros (al Por Menor)",
    "sg:phone":"+34 913 00 00 77",
    "sg:postcode":"28043",
    "sg:province":"Madrid",
    "sg:website":"www.pullbear.com",
    "wof:name":"Pull & Bear Espa\u00d1a S.a.",
    "wof:placetype":"venue"
},
  "geometry": {"coordinates":[-3.6377539635,40.4627380371],"type":"Point"}
}