{
  "type": "Feature",
  "properties": {
    "addr:full":"Calle de Camino De La Barca, S/n Cordoba C\u00f3rdoba 14010",
    "addr:housenumber":"s / n",
    "addr:postcode":"14010",
    "addr:street":"Calle De Camino De La Barca;Co\u0301Rdoba",
    "iso:country":"ES",
    "sg:address":"Calle de Camino De La Barca, S/n",
    "sg:city":"Cordoba",
    "sg:orig_category":"Promotores Constructores",
    "sg:phone":"+34 957 76 45 09",
    "sg:postcode":"14010",
    "sg:province":"C\u00f3rdoba",
    "wof:name":"Se\u00f1alizaciones Villar S.a.",
    "wof:placetype":"venue"
},
  "geometry": {"coordinates":[-4.7607040405,37.8797035217],"type":"Point"}
}