{
  "type": "Feature",
  "properties": {
    "addr:full":"Pque. Infantas, S/n Granada Granada 18006",
    "addr:housenumber":"s / n",
    "addr:postcode":"18006",
    "iso:country":"ES",
    "sg:address":"Pque. Infantas, S/n",
    "sg:city":"Granada",
    "sg:classifiers":[
        {
            "category":"Autos & Motor Vehicles",
            "subcategory":"Automobile Sales",
            "type":"Retail Goods"
        }
    ],
    "sg:phone":"+34 958 12 90 00",
    "sg:postcode":"18006",
    "sg:province":"Granada",
    "sg:website":"www.50test.com/molina.htm",
    "wof:name":"Autoescuela Jesus Molina S.l.",
    "wof:placetype":"venue"
},
  "geometry": {"coordinates":[-3.6378028393,37.5198402405],"type":"Point"}
}