{
  "type": "Feature",
  "properties": {
    "iso:country":"ES",
    "sg:address":"Calle de Almendro (el), 5",
    "sg:city":"Cordoba",
    "sg:orig_category":"Fabricaci\u00d3n, Importaci\u00d3n De L\u00c1mparas Y Bombillas",
    "sg:phone":"+34 957 27 58 40",
    "sg:postcode":"14006",
    "sg:province":"C\u00f3rdoba",
    "wof:name":"Jimenez Cespedes Antonio",
    "wof:placetype":"venue"
},
  "geometry": {"coordinates":[-4.7833375931,37.8961219788],"type":"Point"}
}