{
  "type": "Feature",
  "properties": {
    "iso:country":"ES",
    "sg:address":"Calle de Puerta De Valencia, 1",
    "sg:city":"Cuenca",
    "sg:orig_category":"Molduras, Junquillos, Listones Y Molduras Perforadas",
    "sg:phone":"+34 969 21 29 28",
    "sg:postcode":"16001",
    "sg:province":"Cuenca",
    "wof:name":"Fernandez Estirado Jose Antonio",
    "wof:placetype":"venue"
},
  "geometry": {"coordinates":[-2.1319189072,40.0739593506],"type":"Point"}
}