{
  "type": "Feature",
  "properties": {
    "addr:full":"Calle de Libertad, 38 Alcazar S. Juan Ciudad Real 13600",
    "addr:housenumber":"38",
    "addr:postcode":"13600",
    "addr:street":"Calle De Libertad;Alcazar S. Juan Ciudad Real",
    "iso:country":"ES",
    "sg:address":"Calle de Libertad, 38",
    "sg:city":"Alcazar S. Juan",
    "sg:orig_category":"Piscinas, Accesorios, Suministros (fabricaci\u00d3n, Al Por Mayor)",
    "sg:phone":"+34 926 54 60 11",
    "sg:postcode":"13600",
    "sg:province":"Ciudad Real",
    "wof:name":"Sanchez-mateos Rubio Eduardo",
    "wof:placetype":"venue"
},
  "geometry": {"coordinates":[-3.2179589272,39.3963317871],"type":"Point"}
}