{
  "type": "Feature",
  "properties": {
    "iso:country":"ES",
    "sg:address":"Calle de Zafra (la), 12",
    "sg:city":"Caudete",
    "sg:orig_category":"Tintes (fabricaci\u00d3n, Al Por Mayor)",
    "sg:phone":"+34 965 82 76 17",
    "sg:postcode":"02660",
    "sg:province":"Albacete",
    "wof:name":"Tintoreria Caudete S.l.",
    "wof:placetype":"venue"
},
  "geometry": {"coordinates":[-0.9862506986,38.7041473389],"type":"Point"}
}