{
  "type": "Feature",
  "properties": {
    "addr:full":"Calle de Murcia, 6 Salamanca Salamanca 37006",
    "addr:housenumber":"6",
    "addr:postcode":"37006",
    "addr:street":"Calle De Murcia",
    "iso:country":"ES",
    "sg:address":"Calle de Murcia, 6",
    "sg:city":"Salamanca",
    "sg:orig_category":"Reparaci\u00d3n Y Restauraci\u00d3n De Objetos Diversos",
    "sg:phone":"+34 923 12 26 55",
    "sg:postcode":"37006",
    "sg:province":"Salamanca",
    "wof:name":"Martin Sanchez Alberto Jose",
    "wof:placetype":"venue"
},
  "geometry": {"coordinates":[-5.6756248474,40.976650238],"type":"Point"}
}