{
  "type": "Feature",
  "properties": {
    "addr:full":"Trva Cascajo Segunda, 49 Fuentespina Burgos 09470",
    "addr:housenumber":"49",
    "addr:postcode":"09470",
    "addr:street":"Trva Cascajo Segunda",
    "iso:country":"ES",
    "sg:address":"Trva Cascajo Segunda, 49",
    "sg:city":"Fuentespina",
    "sg:orig_category":"Empresas De Carpinter\u00cda De Madera",
    "sg:phone":"+34 947 50 61 49",
    "sg:postcode":"09470",
    "sg:province":"Burgos",
    "wof:name":"Martin Moreno Francisco Jesus",
    "wof:placetype":"venue"
},
  "geometry": {"coordinates":[-3.6870539188,41.6330718994],"type":"Point"}
}