{
  "type": "Feature",
  "properties": {
    "iso:country":"ES",
    "sg:address":"Avda Aragon, 7",
    "sg:city":"Alca\u00f1iz",
    "sg:orig_category":"Asesor\u00cda Sobre Comunicaci\u00d3n De Empresas",
    "sg:phone":"+34 978 83 43 52",
    "sg:postcode":"44600",
    "sg:province":"Teruel",
    "wof:name":"Insegestion S.a.",
    "wof:placetype":"venue"
},
  "geometry": {"coordinates":[-0.1295929998,41.0504798889],"type":"Point"}
}