{
  "type": "Feature",
  "properties": {
    "addr:full":"Crta Vinaroz-morella, Km. 0018,9 Traiguera Castell\u00f3n 12330",
    "addr:postcode":"12330",
    "addr:street":"Crta Vinaroz-Morella Km. 0018,9;Castello\u0301N",
    "iso:country":"ES",
    "sg:address":"Crta Vinaroz-morella, Km. 0018,9",
    "sg:city":"Traiguera",
    "sg:orig_category":"Barnizadores",
    "sg:phone":"+34 964 49 52 15",
    "sg:postcode":"12330",
    "sg:province":"Castell\u00f3n",
    "wof:name":"Lacados Gonzalez S.l.",
    "wof:placetype":"venue"
},
  "geometry": {"coordinates":[0.2892799973,40.5237693787],"type":"Point"}
}