{
  "type": "Feature",
  "properties": {
    "iso:country":"ES",
    "sg:address":"Calle de Bethencourt Alfonso, 33",
    "sg:city":"Santa Cruz De Tenerife",
    "sg:orig_category":"Asesor\u00cda Sobre Comunicaci\u00d3n De Empresas",
    "sg:phone":"+34 922 24 56 06",
    "sg:postcode":"38002",
    "sg:province":"Santa Cruz De Tenerife",
    "wof:name":"Medina Fernandez-aceytuno Francisco",
    "wof:placetype":"venue"
},
  "geometry": {"coordinates":[-16.2504882812,28.4675197601],"type":"Point"}
}