{
  "type": "Feature",
  "properties": {
    "addr:full":"Calle de Duque De Wellington, 23 Vitoria-gasteiz \u00c1lava 01010",
    "addr:postcode":"01010",
    "addr:street":"Calle De Duque De Wellington 23",
    "iso:country":"ES",
    "sg:address":"Calle de Duque De Wellington, 23",
    "sg:city":"Vitoria-gasteiz",
    "sg:orig_category":"Librer\u00cdas",
    "sg:phone":"+34 945 17 55 53",
    "sg:postcode":"01010",
    "sg:province":"\u00c1lava",
    "wof:name":"Arana Videa Ana Isabel",
    "wof:placetype":"venue"
},
  "geometry": {"coordinates":[-2.6925075054,42.8602333069],"type":"Point"}
}