{
  "type": "Feature",
  "properties": {
    "addr:full":"Calle de Jorge Juan, 169 Madrid Madrid 28028",
    "addr:housenumber":"169",
    "addr:postcode":"28028",
    "addr:street":"Calle De Jorge Juan",
    "iso:country":"ES",
    "sg:address":"Calle de Jorge Juan, 169",
    "sg:city":"Madrid",
    "sg:orig_category":"Edici\u00d3n De Diarios, Revistas, Boletines",
    "sg:phone":"+34 917 25 94 17",
    "sg:postcode":"28028",
    "sg:province":"Madrid",
    "wof:name":"Vailima Ediciones S.l.",
    "wof:placetype":"venue"
},
  "geometry": {"coordinates":[-3.6640377045,40.4226951599],"type":"Point"}
}