{
  "type": "Feature",
  "properties": {
    "addr:full":"Calle de Amalia Alayon, 3 Cristianos Santa Cruz De Tenerife 38650",
    "addr:housenumber":"3",
    "addr:postcode":"38650",
    "addr:street":"Calle De Amalia Alayon",
    "iso:country":"ES",
    "sg:address":"Calle de Amalia Alayon, 3",
    "sg:city":"Cristianos",
    "sg:orig_category":"Relojer\u00cda (al Por Menor, Reparaci\u00d3n)",
    "sg:phone":"+34 922 79 71 24",
    "sg:postcode":"38650",
    "sg:province":"Santa Cruz De Tenerife",
    "wof:name":"Bustelo Campos Silvia",
    "wof:placetype":"venue"
},
  "geometry": {"coordinates":[-16.7162704468,28.0521907806],"type":"Point"}
}