{
  "type": "Feature",
  "properties": {
    "addr:full":"Rua Central, 3 Monforte De Lemos Lugo 27400",
    "addr:housenumber":"3",
    "addr:postcode":"27400",
    "addr:street":"Rua Central",
    "iso:country":"ES",
    "sg:address":"Rua Central, 3",
    "sg:city":"Monforte De Lemos",
    "sg:orig_category":"Molduras, Junquillos, Listones Y Molduras Perforadas",
    "sg:phone":"+34 982 40 53 72",
    "sg:postcode":"27400",
    "sg:province":"Lugo",
    "wof:name":"Martinez Perez Martin",
    "wof:placetype":"venue"
},
  "geometry": {"coordinates":[-7.5069389343,42.5212554932],"type":"Point"}
}