{
  "type": "Feature",
  "properties": {
    "addr:full":"Calle de Vizcaya, 6 Madrid Madrid 28045",
    "addr:housenumber":"6",
    "addr:postcode":"28045",
    "addr:street":"Calle De Vizcaya",
    "iso:country":"ES",
    "sg:address":"Calle de Vizcaya, 6",
    "sg:city":"Madrid",
    "sg:orig_category":"Agencias De Trabajo Temporal",
    "sg:phone":"+34 915 06 42 80",
    "sg:postcode":"28045",
    "sg:province":"Madrid",
    "wof:name":"Horecca Staffing Services E.t.t. S.a.",
    "wof:placetype":"venue"
},
  "geometry": {"coordinates":[-3.6948490143,40.4046020508],"type":"Point"}
}