{
  "type": "Feature",
  "properties": {
    "iso:country":"ES",
    "sg:address":"Calle de Corredera, 11",
    "sg:city":"San Mateo",
    "sg:orig_category":"Bancos",
    "sg:phone":"+34 968 46 85 00",
    "sg:postcode":"30800",
    "sg:province":"Murcia",
    "wof:name":"Banco Popular Espa\u00f1ol",
    "wof:placetype":"venue"
},
  "geometry": {"coordinates":[-1.6905640364,37.680557251],"type":"Point"}
}