{
  "type": "Feature",
  "properties": {
    "iso:country":"ES",
    "sg:address":"Pque Virgen Del Manzano, 16",
    "sg:city":"Burgos",
    "sg:orig_category":"Delegados, Agentes De Tr\u00c1nsito, Auxiliares De Transporte Internacional",
    "sg:phone":"+34 947 23 59 92",
    "sg:postcode":"09004",
    "sg:province":"Burgos",
    "wof:name":"Garcia Garrido Tomas",
    "wof:placetype":"venue"
},
  "geometry": {"coordinates":[-3.6916100979,42.3455123901],"type":"Point"}
}