{
  "type": "Feature",
  "properties": {
    "iso:country":"ES",
    "sg:address":"Ctra. Nuevalos, Km. 0002,8",
    "sg:city":"Calatayud",
    "sg:orig_category":"Vinos Y Licores (venta Al Por Menor)",
    "sg:phone":"+34 976 88 71 67",
    "sg:postcode":"50300",
    "sg:province":"Zaragoza",
    "wof:name":"Suministros Vinicos S.l.",
    "wof:placetype":"venue"
},
  "geometry": {"coordinates":[-1.6394540071,41.3522415161],"type":"Point"}
}