{
  "type": "Feature",
  "properties": {
    "iso:country":"ES",
    "sg:address":"Calle de Juan Ramon Jimenez (de), 3",
    "sg:city":"Algete",
    "sg:orig_category":"Arreglo, Reparaci\u00d3n, Piezas Sueltas De Televisi\u00d3n, V\u00cddeo, Hi",
    "sg:phone":"+34 916 29 14 78",
    "sg:postcode":"28110",
    "sg:province":"Madrid",
    "wof:name":"Madrid Solis Antonio",
    "wof:placetype":"venue"
},
  "geometry": {"coordinates":[-3.5054180622,40.5977058411],"type":"Point"}
}