{
  "type": "Feature",
  "properties": {
    "iso:country":"ES",
    "sg:address":"Calle de General Espartero, 10",
    "sg:city":"Daimiel",
    "sg:orig_category":"Contenedores (mercanc\u00cdas)",
    "sg:phone":"+34 926 85 25 45",
    "sg:postcode":"13250",
    "sg:province":"Ciudad Real",
    "wof:name":"Sucesores De Vicente Cuesta S. A.",
    "wof:placetype":"venue"
},
  "geometry": {"coordinates":[-3.6129870415,39.0682144165],"type":"Point"}
}