{
  "type": "Feature",
  "properties": {
    "iso:country":"ES",
    "sg:address":"Calle de Clemente M. Pasaron, 21",
    "sg:city":"Ribadeo",
    "sg:orig_category":"Vinos Y Licores (venta Al Por Menor)",
    "sg:phone":"+34 982 12 83 12",
    "sg:postcode":"27700",
    "sg:province":"Lugo",
    "wof:name":"Fernandez Suarez Nicanor",
    "wof:placetype":"venue"
},
  "geometry": {"coordinates":[-7.0401616096,43.5339775085],"type":"Point"}
}