{
  "type": "Feature",
  "properties": {
    "addr:full":"Calle de Malasma\u00d1anas, 7 Alcala Guadaira Sevilla 41500",
    "addr:housenumber":"7",
    "addr:postcode":"41500",
    "addr:street":"Calle De Malasman\u0303Anas",
    "iso:country":"ES",
    "sg:address":"Calle de Malasma\u00d1anas, 7",
    "sg:city":"Alcala Guadaira",
    "sg:orig_category":"Entrega Y Recogida (servicios)",
    "sg:phone":"+34 955 61 36 67",
    "sg:postcode":"41500",
    "sg:province":"Sevilla",
    "sg:website":"www.aceitesbatato.es",
    "wof:name":"Aceites Batato S.l.",
    "wof:placetype":"venue"
},
  "geometry": {"coordinates":[-5.8414163589,37.3425216675],"type":"Point"}
}