{
  "type": "Feature",
  "properties": {
    "addr:full":"Avda Albaida, S/n Beniganim Valencia 46830",
    "addr:housenumber":"s",
    "addr:postcode":"46830",
    "addr:street":"Avda Albaida;/ N",
    "iso:country":"ES",
    "sg:address":"Avda Albaida, S/n",
    "sg:city":"Beniganim",
    "sg:orig_category":"Cooperativas Agr\u00cdcolas",
    "sg:phone":"+34 962 21 52 45",
    "sg:postcode":"46830",
    "sg:province":"Valencia",
    "wof:name":"S.a.t. 45-49 Beata Ines",
    "wof:placetype":"venue"
},
  "geometry": {"coordinates":[-0.4500960112,38.9367523193],"type":"Point"}
}