{
  "type": "Feature",
  "properties": {
    "iso:country":"ES",
    "sg:address":"Trva Convento, 13",
    "sg:city":"Gijon",
    "sg:orig_category":"Procuradores",
    "sg:phone":"+34 985 34 05 34",
    "sg:postcode":"33202",
    "sg:province":"Asturias",
    "wof:name":"Hurtado March Marta",
    "wof:placetype":"venue"
},
  "geometry": {"coordinates":[-5.6594572067,43.5403785706],"type":"Point"}
}