{
  "type": "Feature",
  "properties": {
    "addr:full":"Disseminat, S/n Sta. Eulalia Riuprimer Barcelona 08519",
    "addr:housenumber":"/ n",
    "addr:postcode":"08519",
    "addr:street":"Disseminat S",
    "iso:country":"ES",
    "sg:address":"Disseminat, S/n",
    "sg:city":"Sta. Eulalia Riuprimer",
    "sg:classifiers":[
        {
            "category":"Casinos & Gambling",
            "type":"Entertainment"
        }
    ],
    "sg:phone":"+34 937 43 00 80",
    "sg:postcode":"08519",
    "sg:province":"Barcelona",
    "sg:tags":[
        "locale",
        "de",
        "juego"
    ],
    "wof:name":"Centre D'esplai Ca N'aurell",
    "wof:placetype":"venue"
},
  "geometry": {"coordinates":[2.3260529041,41.9538955688],"type":"Point"}
}