{
  "type": "Feature",
  "properties": {
    "iso:country":"ES",
    "sg:address":"Calle de Mayor, 307",
    "sg:city":"Raal",
    "sg:orig_category":"Electricidad: Instaladores",
    "sg:phone":"+34 968 81 04 40",
    "sg:postcode":"30139",
    "sg:province":"Murcia",
    "wof:name":"Gomez Vivancos Martin",
    "wof:placetype":"venue"
},
  "geometry": {"coordinates":[-1.0297859907,38.0393066406],"type":"Point"}
}