{
  "type": "Feature",
  "properties": {
    "addr:full":"Crrd Capuchinos, 24 Andujar Ja\u00e9n 23740",
    "addr:housenumber":"24",
    "addr:postcode":"23740",
    "iso:country":"ES",
    "sg:address":"Crrd Capuchinos, 24",
    "sg:city":"Andujar",
    "sg:orig_category":"Ropa Para Se\u00d1oras (al Por Menor)",
    "sg:phone":"+34 953 51 17 33",
    "sg:postcode":"23740",
    "sg:province":"Ja\u00e9n",
    "wof:name":"Gomez Verdura Luisa",
    "wof:placetype":"venue"
},
  "geometry": {"coordinates":[-4.0503211021,38.0364952087],"type":"Point"}
}