{
  "type": "Feature",
  "properties": {
    "iso:country":"ES",
    "sg:address":"Calle de Sebastian Herrera, 6",
    "sg:city":"Madrid",
    "sg:orig_category":"Molduras, Junquillos, Listones Y Molduras Perforadas",
    "sg:phone":"+34 914 67 04 43",
    "sg:postcode":"28012",
    "sg:province":"Madrid",
    "wof:name":"El Valle De La Esquina S.l.",
    "wof:placetype":"venue"
},
  "geometry": {"coordinates":[-3.6994678974,40.4037208557],"type":"Point"}
}