{
  "type": "Feature",
  "properties": {
    "iso:country":"ES",
    "sg:address":"Senpere Kalea, 7",
    "sg:city":"Beasain",
    "sg:orig_category":"Empresarios",
    "sg:phone":"+34 943 08 54 84",
    "sg:postcode":"20200",
    "sg:province":"Guip\u00f9zcoa",
    "wof:name":"Ekitel",
    "wof:placetype":"venue"
},
  "geometry": {"coordinates":[-2.1925330162,43.0456504822],"type":"Point"}
}