{
  "type": "Feature",
  "properties": {
    "iso:country":"ES",
    "sg:address":"Rond Alfons X El Savi (d'), S/n",
    "sg:city":"Mataro",
    "sg:orig_category":"Distribuci\u00d3n De Petr\u00d3leo Y Derivados",
    "sg:phone":"+34 937 90 55 24",
    "sg:postcode":"08304",
    "sg:province":"Barcelona",
    "wof:name":"Erg Gestion Iberica S.l.",
    "wof:placetype":"venue"
},
  "geometry": {"coordinates":[2.4469149113,41.5458068848],"type":"Point"}
}