{
  "type": "Feature",
  "properties": {
    "addr:full":"Rua Fernando Perez De Traba, 6 Acea De Ama La Coru\u00f1a 15670",
    "addr:housenumber":"6",
    "addr:postcode":"15670",
    "addr:street":"Rua Fernando Perez De Traba;Corun\u0303A",
    "iso:country":"ES",
    "sg:address":"Rua Fernando Perez De Traba, 6",
    "sg:city":"Acea De Ama",
    "sg:orig_category":"Arquitectos",
    "sg:phone":"+34 981 65 45 04",
    "sg:postcode":"15670",
    "sg:province":"La Coru\u00f1a",
    "wof:name":"A.r.q. Blastojo S.l.",
    "wof:placetype":"venue"
},
  "geometry": {"coordinates":[-8.3703136444,43.3153915405],"type":"Point"}
}