{
  "type": "Feature",
  "properties": {
    "addr:full":"Calle de Vega (la), S/n Utrillas Teruel 44760",
    "addr:postcode":"44760",
    "addr:street":"Calle De Vega La S / N",
    "iso:country":"ES",
    "sg:address":"Calle de Vega (la), S/n",
    "sg:city":"Utrillas",
    "sg:orig_category":"Asociaciones Y Clubs Deportivos",
    "sg:phone":"+34 978 75 77 76",
    "sg:postcode":"44760",
    "sg:province":"Teruel",
    "wof:name":"Club Deportivo Utrillas",
    "wof:placetype":"venue"
},
  "geometry": {"coordinates":[-0.8480380177,40.8117485046],"type":"Point"}
}