{
  "type": "Feature",
  "properties": {
    "addr:full":"Carrer de Rosari (del), 54 Vilassar De Mar Barcelona 08340",
    "addr:postcode":"08340",
    "addr:street":"Carrer De Rosari Del",
    "iso:country":"ES",
    "sg:address":"Carrer de Rosari (del), 54",
    "sg:city":"Vilassar De Mar",
    "sg:orig_category":"Mec\u00c1nico Del Autom\u00d3vil",
    "sg:phone":"+34 937 59 49 62",
    "sg:postcode":"08340",
    "sg:province":"Barcelona",
    "wof:name":"Ardoy Romero Bartolome",
    "wof:placetype":"venue"
},
  "geometry": {"coordinates":[2.3963546753,41.505355835],"type":"Point"}
}