{
  "type": "Feature",
  "properties": {
    "iso:country":"ES",
    "sg:address":"Rua Progreso (do), 69",
    "sg:city":"Ourense",
    "sg:orig_category":"Confecci\u00d3n (fabricaci\u00d3n, Al Por Mayor)",
    "sg:phone":"+34 988 22 71 99",
    "sg:postcode":"32003",
    "sg:province":"Ourense",
    "wof:name":"Fernandez Sousa Julia",
    "wof:placetype":"venue"
},
  "geometry": {"coordinates":[-7.8659520149,42.3376426697],"type":"Point"}
}