{
  "type": "Feature",
  "properties": {
    "iso:country":"ES",
    "sg:address":"Calle de Florencio Celdran, 11",
    "sg:city":"Benijofar",
    "sg:orig_category":"Fabricaci\u00d3n De Su\u00c9ters Y Chalecos De Punto",
    "sg:phone":"+34 966 71 46 29",
    "sg:postcode":"03178",
    "sg:province":"Alicante",
    "wof:name":"Rodriguez Perez Luis",
    "wof:placetype":"venue"
},
  "geometry": {"coordinates":[-0.7388830185,38.0774497986],"type":"Point"}
}