{
  "type": "Feature",
  "properties": {
    "addr:full":"Pase Estacion, 27 Tarancon Cuenca 16400",
    "addr:housenumber":"27",
    "addr:postcode":"16400",
    "addr:street":"Estacion",
    "iso:country":"ES",
    "sg:address":"Pase Estacion, 27",
    "sg:city":"Tarancon",
    "sg:orig_category":"Frutas Y Legumbres Frescas (al Por Mayor)",
    "sg:phone":"+34 969 32 13 27",
    "sg:postcode":"16400",
    "sg:province":"Cuenca",
    "wof:name":"Lopez Cuenca Angel",
    "wof:placetype":"venue"
},
  "geometry": {"coordinates":[-3.0077090263,40.0084877014],"type":"Point"}
}