{
  "type": "Feature",
  "properties": {
    "iso:country":"ES",
    "sg:address":"Carr Espasa, 6",
    "sg:city":"Palamos",
    "sg:orig_category":"Empresarios",
    "sg:phone":"+34 972 31 45 80",
    "sg:postcode":"17230",
    "sg:province":"Girona",
    "wof:name":"Noguer Domenech Joan",
    "wof:placetype":"venue"
},
  "geometry": {"coordinates":[3.1306600571,41.8467254639],"type":"Point"}
}