{
  "type": "Feature",
  "properties": {
    "addr:full":"Carrer de Vicen\u00c7 Bou, 7 Lloret Mar Girona 17310",
    "addr:housenumber":"7",
    "addr:postcode":"17310",
    "addr:street":"Carrer De Vicenc\u0327 Bou",
    "iso:country":"ES",
    "sg:address":"Carrer de Vicen\u00c7 Bou, 7",
    "sg:city":"Lloret Mar",
    "sg:orig_category":"Hoteles",
    "sg:phone":"+34 972 36 50 00",
    "sg:postcode":"17310",
    "sg:province":"Girona",
    "wof:name":"Ab 2006 C.b.",
    "wof:placetype":"venue"
},
  "geometry": {"coordinates":[2.844618,41.70118],"type":"Point"}
}