{
  "type": "Feature",
  "properties": {
    "addr:full":"Rbla Guipuscoa, 33 Barcelona Barcelona 08020",
    "addr:housenumber":"33",
    "addr:postcode":"08020",
    "addr:street":"Rbla Guipuscoa",
    "iso:country":"ES",
    "sg:address":"Rbla Guipuscoa, 33",
    "sg:city":"Barcelona",
    "sg:orig_category":"Molduras, Junquillos, Listones Y Molduras Perforadas",
    "sg:phone":"+34 933 08 36 62",
    "sg:postcode":"08020",
    "sg:province":"Barcelona",
    "wof:name":"Parrado Romero Manuel",
    "wof:placetype":"venue"
},
  "geometry": {"coordinates":[2.1949551105,41.4150695801],"type":"Point"}
}