{
  "type": "Feature",
  "properties": {
    "iso:country":"ES",
    "sg:address":"Avda San Andres, 7",
    "sg:city":"Le\u00f3n",
    "sg:orig_category":"Molduras, Junquillos, Listones Y Molduras Perforadas",
    "sg:phone":"+34 987 22 74 99",
    "sg:postcode":"24009",
    "sg:province":"Le\u00f3n",
    "wof:name":"Fuente Ordas Ignacio Ramon De La",
    "wof:placetype":"venue"
},
  "geometry": {"coordinates":[-5.5894498825,42.6017532349],"type":"Point"}
}