{
  "type": "Feature",
  "properties": {
    "iso:country":"ES",
    "sg:address":"Calle de Ramon Asenjo, 12",
    "sg:city":"Luarca",
    "sg:orig_category":"Perfumer\u00cda (al Por Menor)",
    "sg:phone":"+34 985 64 16 32",
    "sg:postcode":"33700",
    "sg:province":"Asturias",
    "wof:name":"Tiver Perfumerias S.l.",
    "wof:placetype":"venue"
},
  "geometry": {"coordinates":[-6.5347619057,43.542804718],"type":"Point"}
}