{
  "type": "Feature",
  "properties": {
    "addr:full":"Calle de Pintor Espinosa, 17 Cordoba C\u00f3rdoba 14004",
    "addr:housenumber":"17",
    "addr:postcode":"14004",
    "addr:street":"Calle De Pintor Espinosa;Co\u0301Rdoba",
    "iso:country":"ES",
    "sg:address":"Calle de Pintor Espinosa, 17",
    "sg:city":"Cordoba",
    "sg:orig_category":"Cervecer\u00cdas",
    "sg:phone":"+34 957 20 16 87",
    "sg:postcode":"14004",
    "sg:province":"C\u00f3rdoba",
    "wof:name":"Llamas Sanchez Jose Maria",
    "wof:placetype":"venue"
},
  "geometry": {"coordinates":[-4.7929191589,37.8701782227],"type":"Point"}
}