{
  "type": "Feature",
  "properties": {
    "addr:full":"Calle de Paloma, 15 Madrid Madrid 28005",
    "addr:housenumber":"15",
    "addr:postcode":"madrid;28005",
    "addr:street":"Calle De Paloma",
    "iso:country":"ES",
    "sg:address":"Calle de Paloma, 15",
    "sg:city":"Madrid",
    "sg:orig_category":"Garajes De Veh\u00cdculos",
    "sg:phone":"+34 913 64 18 96",
    "sg:postcode":"28005",
    "sg:province":"Madrid",
    "wof:name":"Talleres La Paloma S.l.",
    "wof:placetype":"venue"
},
  "geometry": {"coordinates":[-3.7117986679,40.4085578918],"type":"Point"}
}