{
  "type": "Feature",
  "properties": {
    "iso:country":"ES",
    "sg:address":"Avda Cervantes (de), 122",
    "sg:city":"Guardamar Segura",
    "sg:orig_category":"Inmobiliaria (agencias)",
    "sg:phone":"+34 965 72 94 89",
    "sg:postcode":"03140",
    "sg:province":"Alicante",
    "wof:name":"Gestiones Inmobiliarias Nerta S.l.",
    "wof:placetype":"venue"
},
  "geometry": {"coordinates":[-0.6500070095,38.0838813782],"type":"Point"}
}