{
  "type": "Feature",
  "properties": {
    "addr:full":"Calle de Antonio Machado, 2 Cox Alicante 03350",
    "addr:housenumber":"2",
    "addr:postcode":"03350",
    "addr:street":"Calle De Antonio Machado",
    "iso:country":"ES",
    "sg:address":"Calle de Antonio Machado, 2",
    "sg:city":"Cox",
    "sg:orig_category":"M\u00c9dicos: Estomatolog\u00cda",
    "sg:phone":"+34 965 36 06 62",
    "sg:postcode":"03350",
    "sg:province":"Alicante",
    "wof:name":"Ferrandiz Trigueros Miguel",
    "wof:placetype":"venue"
},
  "geometry": {"coordinates":[-0.8878077865,38.1416397095],"type":"Point"}
}