{
  "type": "Feature",
  "properties": {
    "addr:full":"Calle de Kutxa, 2 Vitoria-gasteiz \u00c1lava 01012",
    "addr:housenumber":"2",
    "addr:postcode":"01012",
    "addr:street":"Calle De Kutxa",
    "iso:country":"ES",
    "sg:address":"Calle de Kutxa, 2",
    "sg:city":"Vitoria-gasteiz",
    "sg:orig_category":"Molduras, Junquillos, Listones Y Molduras Perforadas",
    "sg:phone":"+34 945 14 41 11",
    "sg:postcode":"01012",
    "sg:province":"\u00c1lava",
    "wof:name":"Martinez Diaz Julio",
    "wof:placetype":"venue"
},
  "geometry": {"coordinates":[-2.6754889488,42.8512687683],"type":"Point"}
}