{
  "type": "Feature",
  "properties": {
    "addr:full":"Avda Hispanidade, 75 Vigo Pontevedra 36203",
    "addr:housenumber":"75",
    "addr:postcode":"36203",
    "addr:street":"Avda Hispanidade",
    "iso:country":"ES",
    "sg:address":"Avda Hispanidade, 75",
    "sg:city":"Vigo",
    "sg:orig_category":"Empresas De Limpieza",
    "sg:phone":"+34 986 44 12 07",
    "sg:postcode":"36203",
    "sg:province":"Pontevedra",
    "wof:name":"Clecer S.a.",
    "wof:placetype":"venue"
},
  "geometry": {"coordinates":[-8.7283239365,42.2277145386],"type":"Point"}
}