{
  "type": "Feature",
  "properties": {
    "addr:full":"Avda Gabriel Miro, 4 Calpe Alicante 03710",
    "addr:housenumber":"4",
    "addr:postcode":"03710",
    "addr:street":"Avda Gabriel Miro",
    "iso:country":"ES",
    "sg:address":"Avda Gabriel Miro, 4",
    "sg:city":"Calpe",
    "sg:orig_category":"Comerciantes Al Por Mayor De Vinos, Licores Y Alcoholes",
    "sg:phone":"+34 965 83 00 90",
    "sg:postcode":"03710",
    "sg:province":"Alicante",
    "wof:name":"Avargues Pastor Jacinto",
    "wof:placetype":"venue"
},
  "geometry": {"coordinates":[0.0467029996,38.6438980103],"type":"Point"}
}