{
  "type": "Feature",
  "properties": {
    "iso:country":"ES",
    "sg:address":"Carrer de Girona, 335",
    "sg:city":"Granollers",
    "sg:orig_category":"Carnicer\u00cdas, Carnicer\u00cdas",
    "sg:phone":"+34 938 49 69 60",
    "sg:postcode":"08402",
    "sg:province":"Barcelona",
    "wof:name":"Espinosa Lozano Fernando",
    "wof:placetype":"venue"
},
  "geometry": {"coordinates":[2.2935369015,41.6207389832],"type":"Point"}
}