{
  "type": "Feature",
  "properties": {
    "iso:country":"ES",
    "sg:address":"Carrer de Xercavins, 2",
    "sg:city":"Rubi",
    "sg:orig_category":"Farmacias",
    "sg:phone":"+34 936 99 13 05",
    "sg:postcode":"08191",
    "sg:province":"Barcelona",
    "wof:name":"Parrilla Leal Maria",
    "wof:placetype":"venue"
},
  "geometry": {"coordinates":[2.0300199986,41.4907035828],"type":"Point"}
}