{
  "type": "Feature",
  "properties": {
    "iso:country":"ES",
    "sg:address":"Avda Salinera Espa\u00d1ola, S/n",
    "sg:city":"S. Pedro Pinatar",
    "sg:orig_category":"Sales (al Por Mayor)",
    "sg:phone":"+34 968 18 08 12",
    "sg:postcode":"30740",
    "sg:province":"Murcia",
    "wof:name":"Salinera Espa\u00f1ola S. A.",
    "wof:placetype":"venue"
},
  "geometry": {"coordinates":[-0.7932540178,37.8340911865],"type":"Point"}
}