{
  "type": "Feature",
  "properties": {
    "addr:full":"Linaria, S/n Gordillo Sevilla 41009",
    "addr:housenumber":"s / n",
    "addr:postcode":"41009",
    "addr:street":"Linaria",
    "iso:country":"ES",
    "sg:address":"Linaria, S/n",
    "sg:city":"Gordillo",
    "sg:orig_category":"Mec\u00c1nico Del Autom\u00d3vil",
    "sg:phone":"+34 954 68 61 12",
    "sg:postcode":"41009",
    "sg:province":"Sevilla",
    "wof:name":"Lopez Cristal Jose",
    "wof:placetype":"venue"
},
  "geometry": {"coordinates":[-5.9385099411,37.447429657],"type":"Point"}
}