{
  "type": "Feature",
  "properties": {
    "iso:country":"ES",
    "sg:address":"Barr Plaza (la), S/n",
    "sg:city":"Plaza",
    "sg:orig_category":"Partidos Pol\u00cdticos",
    "sg:phone":"+34 942 70 98 63",
    "sg:postcode":"39592",
    "sg:province":"Cantabria",
    "wof:name":"Partido Socialista Obrero Espa\u00f1ol",
    "wof:placetype":"venue"
},
  "geometry": {"coordinates":[-4.3003191948,43.3168563843],"type":"Point"}
}