{
  "type": "Feature",
  "properties": {
    "addr:full":"Avgd Cami Nou, 76 Benetusser Valencia 46910",
    "addr:housenumber":"76",
    "addr:postcode":"46910",
    "addr:street":"Nou",
    "iso:country":"ES",
    "sg:address":"Avgd Cami Nou, 76",
    "sg:city":"Benetusser",
    "sg:orig_category":"Telas Y Sedas (al Por Menor)",
    "sg:phone":"+34 963 75 77 23",
    "sg:postcode":"46910",
    "sg:province":"Valencia",
    "wof:name":"Mantoan Coccato Armando",
    "wof:placetype":"venue"
},
  "geometry": {"coordinates":[-0.3957450092,39.4231796265],"type":"Point"}
}