{
  "type": "Feature",
  "properties": {
    "iso:country":"ES",
    "sg:address":"Av Balaguer, S/n",
    "sg:city":"Mollerussa",
    "sg:orig_category":"Asociaciones Y Clubs Deportivos",
    "sg:phone":"+34 973 60 27 12",
    "sg:postcode":"25230",
    "sg:province":"Lleida",
    "wof:name":"Club De Tenis Mollerussa",
    "wof:placetype":"venue"
},
  "geometry": {"coordinates":[0.8939399719,41.6323699951],"type":"Point"}
}