{
  "type": "Feature",
  "properties": {
    "iso:country":"ES",
    "sg:address":"Calle de Molino, 2",
    "sg:city":"Sarrion",
    "sg:orig_category":"Iglesia Cat\u00d3lica",
    "sg:phone":"+34 978 78 00 04",
    "sg:postcode":"44460",
    "sg:province":"Teruel",
    "wof:name":"Parroquia San Pedro Y San Pablo",
    "wof:placetype":"venue"
},
  "geometry": {"coordinates":[-0.8139740229,40.1400032043],"type":"Point"}
}