{
  "type": "Feature",
  "properties": {
    "addr:full":"Calle de Pedro De Lobo, 3 Malaga M\u00e1laga 29014",
    "addr:housenumber":"3",
    "addr:postcode":"29014",
    "addr:street":"Calle De Pedro De Lobo;Ma\u0301Laga",
    "iso:country":"ES",
    "sg:address":"Calle de Pedro De Lobo, 3",
    "sg:city":"Malaga",
    "sg:orig_category":"Electricidad: Instaladores",
    "sg:phone":"+34 952 26 00 50",
    "sg:postcode":"29014",
    "sg:province":"M\u00e1laga",
    "wof:name":"Najera Montes Francisco",
    "wof:placetype":"venue"
},
  "geometry": {"coordinates":[-4.4157781601,36.7461433411],"type":"Point"}
}