{
  "type": "Feature",
  "properties": {
    "addr:full":"Calle de Anselmo Fernandez, 12 Requena Valencia 46340",
    "addr:housenumber":"12",
    "addr:postcode":"46340",
    "addr:street":"Calle De Anselmo Fernandez",
    "iso:country":"ES",
    "sg:address":"Calle de Anselmo Fernandez, 12",
    "sg:city":"Requena",
    "sg:orig_category":"Promotores Constructores",
    "sg:phone":"+34 962 30 22 86",
    "sg:postcode":"46340",
    "sg:province":"Valencia",
    "wof:name":"Cooperativa Valenciana De Trabajos Asociados Coreut",
    "wof:placetype":"venue"
},
  "geometry": {"coordinates":[-1.0983252525,39.4867286682],"type":"Point"}
}