{
  "type": "Feature",
  "properties": {
    "iso:country":"ES",
    "sg:address":"Carrer de Benet Morato, S/n",
    "sg:city":"Granollers",
    "sg:orig_category":"Estilistas Y Estudios De Estilo De Corte Y Confecci\u00d3n",
    "sg:phone":"+34 938 70 84 55",
    "sg:postcode":"08402",
    "sg:province":"Barcelona",
    "wof:name":"Canal Gil Jose",
    "wof:placetype":"venue"
},
  "geometry": {"coordinates":[2.289935112,41.6094703674],"type":"Point"}
}