{
  "type": "Feature",
  "properties": {
    "iso:country":"ES",
    "sg:address":"Avgd Blondel, 25",
    "sg:city":"Lleida",
    "sg:orig_category":"Asesor\u00cda Sobre Comunicaci\u00d3n De Empresas",
    "sg:phone":"+34 973 28 38 64",
    "sg:postcode":"25002",
    "sg:province":"Lleida",
    "wof:name":"Instituto De Investigaciones Juridicas S.l.",
    "wof:placetype":"venue"
},
  "geometry": {"coordinates":[0.6228820086,41.6117172241],"type":"Point"}
}