{
  "type": "Feature",
  "properties": {
    "addr:full":"Av Princep D'asturies, 3 Barcelona Barcelona 08012",
    "addr:housenumber":"3",
    "addr:postcode":"08012",
    "addr:street":"Av Princep D'Asturies",
    "iso:country":"ES",
    "sg:address":"Av Princep D'asturies, 3",
    "sg:city":"Barcelona",
    "sg:orig_category":"Inmobiliaria (agencias)",
    "sg:phone":"+34 932 18 18 00",
    "sg:postcode":"08012",
    "sg:province":"Barcelona",
    "wof:name":"Calidis 21 S.l.",
    "wof:placetype":"venue"
},
  "geometry": {"coordinates":[2.1511428356,41.4014472961],"type":"Point"}
}