{
  "type": "Feature",
  "properties": {
    "iso:country":"ES",
    "sg:address":"Calle de Fuente Del Romero, 18",
    "sg:city":"Madrid",
    "sg:orig_category":"Asesor\u00cda Sobre Comunicaci\u00d3n De Empresas",
    "sg:phone":"+34 913 07 86 00",
    "sg:postcode":"28023",
    "sg:province":"Madrid",
    "wof:name":"Finaes S.a.",
    "wof:placetype":"venue"
},
  "geometry": {"coordinates":[-3.7658760548,40.4516792297],"type":"Point"}
}