{
  "type": "Feature",
  "properties": {
    "addr:full":"Carrer de Poima, 9 Poligon Industrial De Can Valero Islas Baleares 07011",
    "addr:housenumber":"9",
    "addr:postcode":"07011",
    "addr:street":"Carrer De Poima;Industrial;Islas",
    "iso:country":"ES",
    "sg:address":"Carrer de Poima, 9",
    "sg:city":"Poligon Industrial De Can Valero",
    "sg:orig_category":"Empresas De Carpinter\u00cda Met\u00c1lica",
    "sg:phone":"+34 971 75 32 93",
    "sg:postcode":"07011",
    "sg:province":"Islas Baleares",
    "wof:name":"Infer S. L.",
    "wof:placetype":"venue"
},
  "geometry": {"coordinates":[2.6205170155,39.5930747986],"type":"Point"}
}