{
  "type": "Feature",
  "properties": {
    "iso:country":"ES",
    "sg:address":"Calle de Meson De Paredes, 56",
    "sg:city":"Madrid",
    "sg:orig_category":"Bisuter\u00cda, Joyer\u00cda, Relojer\u00cda (al Por Menor)",
    "sg:phone":"+34 915 30 79 53",
    "sg:postcode":"28012",
    "sg:province":"Madrid",
    "wof:name":"Pe\u00f1alcarro S.l.",
    "wof:placetype":"venue"
},
  "geometry": {"coordinates":[-3.7038359642,40.4090919495],"type":"Point"}
}