{
  "type": "Feature",
  "properties": {
    "iso:country":"ES",
    "sg:address":"Carrer de Llobateras, 49",
    "sg:city":"Rubi",
    "sg:orig_category":"Agencias De Viajes",
    "sg:phone":"+34 935 88 05 51",
    "sg:postcode":"08191",
    "sg:province":"Barcelona",
    "wof:name":"Xelmon S.l.",
    "wof:placetype":"venue"
},
  "geometry": {"coordinates":[2.0322418213,41.4891281128],"type":"Point"}
}