{
  "type": "Feature",
  "properties": {
    "iso:country":"ES",
    "sg:address":"Avda Madrid De, 51",
    "sg:city":"Fraga",
    "sg:orig_category":"Centros Comerciales Y Grandes Tiendas",
    "sg:phone":"+34 974 45 43 24",
    "sg:postcode":"22520",
    "sg:province":"Huesca",
    "wof:name":"Felipe Esperansi Jorge Juan",
    "wof:placetype":"venue"
},
  "geometry": {"coordinates":[0.3364729881,41.5208396912],"type":"Point"}
}