{
  "type": "Feature",
  "properties": {
    "addr:full":"Calle de Ancha, 21 Santa Cruz C\u00f3rdoba 14820",
    "addr:housenumber":"21",
    "addr:postcode":"14820",
    "addr:street":"Calle De Ancha;Cruz Co\u0301Rdoba",
    "iso:country":"ES",
    "sg:address":"Calle de Ancha, 21",
    "sg:city":"Santa Cruz",
    "sg:orig_category":"Empresarios Y Productoras De Espect\u00c1culos",
    "sg:phone":"+34 957 37 80 14",
    "sg:postcode":"14820",
    "sg:province":"C\u00f3rdoba",
    "wof:name":"Borgas Martinez Francisco Javier",
    "wof:placetype":"venue"
},
  "geometry": {"coordinates":[-4.633699894,37.7337226868],"type":"Point"}
}