{
  "type": "Feature",
  "properties": {
    "addr:full":"Calle de Carretera, 1 Alacon Teruel 44549",
    "addr:housenumber":"1",
    "addr:postcode":"44549",
    "addr:street":"Calle De Carretera",
    "iso:country":"ES",
    "sg:address":"Calle de Carretera, 1",
    "sg:city":"Alacon",
    "sg:orig_category":"T\u00c9cnicos Veterinarios",
    "sg:phone":"+34 978 81 86 66",
    "sg:postcode":"44549",
    "sg:province":"Teruel",
    "wof:name":"Agrupacion Defensa Sanitaria Del Porcino 3",
    "wof:placetype":"venue"
},
  "geometry": {"coordinates":[-0.6980414987,41.0211410522],"type":"Point"}
}