{
  "type": "Feature",
  "properties": {
    "addr:full":"Av Marti Genis I Aguilar, 16 Vic Barcelona 08500",
    "addr:housenumber":"16",
    "addr:postcode":"08500",
    "addr:street":"Av Marti Genis I Aguilar",
    "iso:country":"ES",
    "sg:address":"Av Marti Genis I Aguilar, 16",
    "sg:city":"Vic",
    "sg:orig_category":"Inmobiliaria (agencias)",
    "sg:phone":"+34 938 83 31 93",
    "sg:postcode":"08500",
    "sg:province":"Barcelona",
    "wof:name":"Serrano Gonzalez Manuel",
    "wof:placetype":"venue"
},
  "geometry": {"coordinates":[2.25583601,41.9250488281],"type":"Point"}
}