{
  "type": "Feature",
  "properties": {
    "iso:country":"ES",
    "sg:address":"Avda Nuestra Se\u00d1ora Del Valle, S/n",
    "sg:city":"Ecija",
    "sg:orig_category":"Iglesia Cat\u00d3lica",
    "sg:phone":"+34 954 83 06 13",
    "sg:postcode":"41400",
    "sg:province":"Sevilla",
    "wof:name":"Parroquia Mayor De Santa Cruz",
    "wof:placetype":"venue"
},
  "geometry": {"coordinates":[-5.0820689201,37.5508918762],"type":"Point"}
}