{
  "type": "Feature",
  "properties": {
    "addr:full":"Calle de Conde De Montornes, 26 Valencia Valencia 46003",
    "addr:housenumber":"26",
    "addr:postcode":"46003",
    "addr:street":"Calle De Conde De Montornes",
    "iso:country":"ES",
    "sg:address":"Calle de Conde De Montornes, 26",
    "sg:city":"Valencia",
    "sg:orig_category":"Molduras, Junquillos, Listones Y Molduras Perforadas",
    "sg:phone":"+34 963 51 93 08",
    "sg:postcode":"46003",
    "sg:province":"Valencia",
    "wof:name":"Beltran Ruiz Fernando",
    "wof:placetype":"venue"
},
  "geometry": {"coordinates":[-0.3705019951,39.4738121033],"type":"Point"}
}