{
  "type": "Feature",
  "properties": {
    "iso:country":"ES",
    "sg:address":"Avda Gijon, 99",
    "sg:city":"Valladolid",
    "sg:orig_category":"Piedra Natural",
    "sg:phone":"+34 983 34 18 53",
    "sg:postcode":"47009",
    "sg:province":"Valladolid",
    "sg:website":"www.piedraland.com",
    "wof:name":"Hiperaya S.l.",
    "wof:placetype":"venue"
},
  "geometry": {"coordinates":[-4.7580947876,41.6602554321],"type":"Point"}
}