{
  "type": "Feature",
  "properties": {
    "addr:full":"Calle de Alfareros, 33 Salamanca Salamanca 37006",
    "addr:housenumber":"33",
    "addr:postcode":"37006",
    "addr:street":"Calle De Alfareros",
    "iso:country":"ES",
    "sg:address":"Calle de Alfareros, 33",
    "sg:city":"Salamanca",
    "sg:orig_category":"Seguridad En El Trabajo Y Prevenci\u00d3n De Riesgos Laborales",
    "sg:phone":"+34 923 23 01 70",
    "sg:postcode":"37006",
    "sg:province":"Salamanca",
    "wof:name":"Servicio De Prevencion Integral Leon S.a.",
    "wof:placetype":"venue"
},
  "geometry": {"coordinates":[-5.6735701561,40.9776916504],"type":"Point"}
}