{
  "type": "Feature",
  "properties": {
    "iso:country":"ES",
    "sg:address":"C, 26",
    "sg:city":"Santiago De Compostela",
    "sg:orig_category":"Ropa De Trabajo Y Profesionales (fabricaci\u00d3n, Al Por Mayor)",
    "sg:phone":"+34 981 57 41 72",
    "sg:postcode":"15890",
    "sg:province":"A Coru\u00f1a",
    "wof:name":"Vesla S.l.",
    "wof:placetype":"venue"
},
  "geometry": {"coordinates":[-8.4769210815,42.8835983276],"type":"Point"}
}