{
  "type": "Feature",
  "properties": {
    "addr:full":"Calle de Rio Alberche (del), 32 Humanes De Madrid Madrid 28970",
    "addr:housenumber":"32",
    "addr:postcode":"28970",
    "addr:street":"Calle De Rio Alberche Del",
    "iso:country":"ES",
    "sg:address":"Calle de Rio Alberche (del), 32",
    "sg:city":"Humanes De Madrid",
    "sg:orig_category":"Muebles, Minoristas",
    "sg:phone":"+34 916 90 42 01",
    "sg:postcode":"28970",
    "sg:province":"Madrid",
    "wof:name":"Muebles Azur Confort S.l.",
    "wof:placetype":"venue"
},
  "geometry": {"coordinates":[-3.81189394,40.2646026611],"type":"Point"}
}