{
  "type": "Feature",
  "properties": {
    "iso:country":"ES",
    "sg:address":"Calle de Ibaiondo, 6",
    "sg:city":"Ondarroa",
    "sg:orig_category":"Ense\u00d1anza, Formaci\u00d3n Profesional: Aprendizaje",
    "sg:phone":"+34 946 13 42 62",
    "sg:postcode":"48700",
    "sg:province":"Vizcaya",
    "wof:name":"Instituto Foral De Asistencia Social De Bizkaia",
    "wof:placetype":"venue"
},
  "geometry": {"coordinates":[-2.433907032,43.3196525574],"type":"Point"}
}