{
  "type": "Feature",
  "properties": {
    "iso:country":"ES",
    "sg:address":"Calle de Maria Marin, 29",
    "sg:city":"Albacete",
    "sg:orig_category":"Papeler\u00cdas, Librer\u00cdas",
    "sg:phone":"+34 967 22 92 79",
    "sg:postcode":"02003",
    "sg:province":"Albacete",
    "wof:name":"Soler Soler Modesto",
    "wof:placetype":"venue"
},
  "geometry": {"coordinates":[-1.8618204594,38.9888877869],"type":"Point"}
}